package o;

import android.app.Activity;

public class af
{
  private static int ʽ = 1;
  private static long ˊ = 8097948106342962585L;
  private static int ᐝ = 0;
  private ah ˋ;
  private ai ˎ;
  private String[] ˏ;
  private int ॱ;
  
  public af(String... paramVarArgs)
  {
    try
    {
      this.ˏ = paramVarArgs;
      return;
    }
    catch (Exception paramVarArgs)
    {
      throw paramVarArgs;
    }
  }
  
  private static String ॱ(char[] paramArrayOfChar)
  {
    for (;;)
    {
      try
      {
        j = ʽ;
        j += 15;
        try
        {
          ᐝ = j % 128;
          if (j % 2 == 0) {
            break label95;
          }
        }
        catch (Exception paramArrayOfChar)
        {
          throw paramArrayOfChar;
        }
        label38:
        j = 0;
      }
      catch (Exception paramArrayOfChar)
      {
        throw paramArrayOfChar;
      }
      break label140;
      int k = paramArrayOfChar[0];
      char[] arrayOfChar = new char[paramArrayOfChar.length - 1];
      int i = 1;
      break label155;
      for (;;)
      {
        j = 1;
        switch (j)
        {
        case 0: 
        default: 
          break;
          long l1 = paramArrayOfChar[i] ^ i * k;
          long l2 = ˊ;
          arrayOfChar[(i - 1)] = ((char)(int)(l1 ^ l2));
          i += 1;
          break;
        case 1: 
          label95:
          return new String(arrayOfChar);
          label140:
          if (i < paramArrayOfChar.length) {
            break label38;
          }
        }
      }
      continue;
      label155:
      int j = ᐝ + 107;
      ʽ = j % 128;
      if (j % 2 != 0) {}
    }
  }
  
  /* Error */
  public void ˊ(int paramInt, boolean paramBoolean)
  {
    // Byte code:
    //   0: goto +550 -> 550
    //   3: return
    //   4: aload_0
    //   5: getfield 44	o/af:ˋ	Lo/ah;
    //   8: ifnull +6 -> 14
    //   11: goto +534 -> 545
    //   14: goto +57 -> 71
    //   17: getstatic 20	o/af:ᐝ	I
    //   20: bipush 75
    //   22: iadd
    //   23: istore_3
    //   24: iload_3
    //   25: sipush 128
    //   28: irem
    //   29: putstatic 22	o/af:ʽ	I
    //   32: iload_3
    //   33: iconst_2
    //   34: irem
    //   35: ifne +6 -> 41
    //   38: goto +503 -> 541
    //   41: goto +56 -> 97
    //   44: getstatic 20	o/af:ᐝ	I
    //   47: bipush 79
    //   49: iadd
    //   50: istore_3
    //   51: iload_3
    //   52: sipush 128
    //   55: irem
    //   56: putstatic 22	o/af:ʽ	I
    //   59: iload_3
    //   60: iconst_2
    //   61: irem
    //   62: ifne +6 -> 68
    //   65: goto +488 -> 553
    //   68: goto -64 -> 4
    //   71: iconst_1
    //   72: istore_3
    //   73: iload_3
    //   74: tableswitch	default:+22->96, 0:+-57->17, 1:+470->544
    //   96: return
    //   97: bipush 8
    //   99: newarray char
    //   101: dup
    //   102: iconst_0
    //   103: ldc 45
    //   105: castore
    //   106: dup
    //   107: iconst_1
    //   108: ldc 46
    //   110: castore
    //   111: dup
    //   112: iconst_2
    //   113: ldc 47
    //   115: castore
    //   116: dup
    //   117: iconst_3
    //   118: ldc 48
    //   120: castore
    //   121: dup
    //   122: iconst_4
    //   123: ldc 49
    //   125: castore
    //   126: dup
    //   127: iconst_5
    //   128: ldc 50
    //   130: castore
    //   131: dup
    //   132: bipush 6
    //   134: ldc 51
    //   136: castore
    //   137: dup
    //   138: bipush 7
    //   140: ldc 52
    //   142: castore
    //   143: invokestatic 54	o/af:ॱ	([C)Ljava/lang/String;
    //   146: invokevirtual 58	java/lang/String:intern	()Ljava/lang/String;
    //   149: astore 4
    //   151: bipush 50
    //   153: newarray char
    //   155: dup
    //   156: iconst_0
    //   157: ldc 59
    //   159: castore
    //   160: dup
    //   161: iconst_1
    //   162: ldc 60
    //   164: castore
    //   165: dup
    //   166: iconst_2
    //   167: ldc 61
    //   169: castore
    //   170: dup
    //   171: iconst_3
    //   172: ldc 62
    //   174: castore
    //   175: dup
    //   176: iconst_4
    //   177: ldc 63
    //   179: castore
    //   180: dup
    //   181: iconst_5
    //   182: ldc 64
    //   184: castore
    //   185: dup
    //   186: bipush 6
    //   188: ldc 65
    //   190: castore
    //   191: dup
    //   192: bipush 7
    //   194: ldc 66
    //   196: castore
    //   197: dup
    //   198: bipush 8
    //   200: ldc 67
    //   202: castore
    //   203: dup
    //   204: bipush 9
    //   206: ldc 68
    //   208: castore
    //   209: dup
    //   210: bipush 10
    //   212: ldc 69
    //   214: castore
    //   215: dup
    //   216: bipush 11
    //   218: ldc 70
    //   220: castore
    //   221: dup
    //   222: bipush 12
    //   224: ldc 71
    //   226: castore
    //   227: dup
    //   228: bipush 13
    //   230: ldc 72
    //   232: castore
    //   233: dup
    //   234: bipush 14
    //   236: ldc 73
    //   238: castore
    //   239: dup
    //   240: bipush 15
    //   242: ldc 74
    //   244: castore
    //   245: dup
    //   246: bipush 16
    //   248: ldc 75
    //   250: castore
    //   251: dup
    //   252: bipush 17
    //   254: ldc 76
    //   256: castore
    //   257: dup
    //   258: bipush 18
    //   260: ldc 77
    //   262: castore
    //   263: dup
    //   264: bipush 19
    //   266: ldc 78
    //   268: castore
    //   269: dup
    //   270: bipush 20
    //   272: ldc 79
    //   274: castore
    //   275: dup
    //   276: bipush 21
    //   278: ldc 80
    //   280: castore
    //   281: dup
    //   282: bipush 22
    //   284: ldc 81
    //   286: castore
    //   287: dup
    //   288: bipush 23
    //   290: ldc 82
    //   292: castore
    //   293: dup
    //   294: bipush 24
    //   296: ldc 83
    //   298: castore
    //   299: dup
    //   300: bipush 25
    //   302: ldc 84
    //   304: castore
    //   305: dup
    //   306: bipush 26
    //   308: ldc 85
    //   310: castore
    //   311: dup
    //   312: bipush 27
    //   314: ldc 86
    //   316: castore
    //   317: dup
    //   318: bipush 28
    //   320: ldc 87
    //   322: castore
    //   323: dup
    //   324: bipush 29
    //   326: ldc 88
    //   328: castore
    //   329: dup
    //   330: bipush 30
    //   332: ldc 89
    //   334: castore
    //   335: dup
    //   336: bipush 31
    //   338: ldc 90
    //   340: castore
    //   341: dup
    //   342: bipush 32
    //   344: ldc 91
    //   346: castore
    //   347: dup
    //   348: bipush 33
    //   350: ldc 92
    //   352: castore
    //   353: dup
    //   354: bipush 34
    //   356: ldc 93
    //   358: castore
    //   359: dup
    //   360: bipush 35
    //   362: ldc 94
    //   364: castore
    //   365: dup
    //   366: bipush 36
    //   368: ldc 95
    //   370: castore
    //   371: dup
    //   372: bipush 37
    //   374: ldc 96
    //   376: castore
    //   377: dup
    //   378: bipush 38
    //   380: ldc 97
    //   382: castore
    //   383: dup
    //   384: bipush 39
    //   386: ldc 98
    //   388: castore
    //   389: dup
    //   390: bipush 40
    //   392: ldc 99
    //   394: castore
    //   395: dup
    //   396: bipush 41
    //   398: ldc 100
    //   400: castore
    //   401: dup
    //   402: bipush 42
    //   404: ldc 101
    //   406: castore
    //   407: dup
    //   408: bipush 43
    //   410: ldc 102
    //   412: castore
    //   413: dup
    //   414: bipush 44
    //   416: ldc 103
    //   418: castore
    //   419: dup
    //   420: bipush 45
    //   422: ldc 104
    //   424: castore
    //   425: dup
    //   426: bipush 46
    //   428: ldc 105
    //   430: castore
    //   431: dup
    //   432: bipush 47
    //   434: ldc 106
    //   436: castore
    //   437: dup
    //   438: bipush 48
    //   440: ldc 107
    //   442: castore
    //   443: dup
    //   444: bipush 49
    //   446: ldc 108
    //   448: castore
    //   449: invokestatic 54	o/af:ॱ	([C)Ljava/lang/String;
    //   452: invokevirtual 58	java/lang/String:intern	()Ljava/lang/String;
    //   455: astore 5
    //   457: goto +23 -> 480
    //   460: astore 4
    //   462: aload 4
    //   464: invokevirtual 114	java/lang/Throwable:getCause	()Ljava/lang/Throwable;
    //   467: astore 5
    //   469: aload 5
    //   471: ifnull +6 -> 477
    //   474: aload 5
    //   476: athrow
    //   477: aload 4
    //   479: athrow
    //   480: iconst_4
    //   481: bipush 42
    //   483: ldc 115
    //   485: invokestatic 120	o/O:ˋ	(IIC)Ljava/lang/Object;
    //   488: checkcast 122	java/lang/Class
    //   491: ldc 123
    //   493: iconst_2
    //   494: anewarray 122	java/lang/Class
    //   497: dup
    //   498: iconst_0
    //   499: ldc 38
    //   501: aastore
    //   502: dup
    //   503: iconst_1
    //   504: ldc 38
    //   506: aastore
    //   507: invokevirtual 127	java/lang/Class:getMethod	(Ljava/lang/String;[Ljava/lang/Class;)Ljava/lang/reflect/Method;
    //   510: aconst_null
    //   511: iconst_2
    //   512: anewarray 4	java/lang/Object
    //   515: dup
    //   516: iconst_0
    //   517: aload 4
    //   519: aastore
    //   520: dup
    //   521: iconst_1
    //   522: aload 5
    //   524: aastore
    //   525: invokevirtual 133	java/lang/reflect/Method:invoke	(Ljava/lang/Object;[Ljava/lang/Object;)Ljava/lang/Object;
    //   528: pop
    //   529: aload_0
    //   530: getfield 44	o/af:ˋ	Lo/ah;
    //   533: iload_1
    //   534: iload_2
    //   535: invokevirtual 137	o/ah:ˎ	(IZ)V
    //   538: goto -535 -> 3
    //   541: goto -444 -> 97
    //   544: return
    //   545: iconst_0
    //   546: istore_3
    //   547: goto -474 -> 73
    //   550: goto -506 -> 44
    //   553: goto -549 -> 4
    // Local variable table:
    //   start	length	slot	name	signature
    //   0	556	0	this	af
    //   0	556	1	paramInt	int
    //   0	556	2	paramBoolean	boolean
    //   23	524	3	i	int
    //   149	1	4	str	String
    //   460	58	4	localObject1	Object
    //   455	68	5	localObject2	Object
    // Exception table:
    //   from	to	target	type
    //   480	529	460	finally
  }
  
  /* Error */
  public void ˋ(int paramInt, boolean paramBoolean)
  {
    // Byte code:
    //   0: goto +550 -> 550
    //   3: goto +475 -> 478
    //   6: bipush 54
    //   8: istore_1
    //   9: goto +485 -> 494
    //   12: bipush 14
    //   14: istore_1
    //   15: goto +479 -> 494
    //   18: getstatic 22	o/af:ʽ	I
    //   21: istore_1
    //   22: iload_1
    //   23: bipush 21
    //   25: iadd
    //   26: istore_1
    //   27: iload_1
    //   28: sipush 128
    //   31: irem
    //   32: putstatic 20	o/af:ᐝ	I
    //   35: iload_1
    //   36: iconst_2
    //   37: irem
    //   38: ifeq +6 -> 44
    //   41: goto +516 -> 557
    //   44: goto -41 -> 3
    //   47: bipush 8
    //   49: newarray char
    //   51: dup
    //   52: iconst_0
    //   53: ldc 45
    //   55: castore
    //   56: dup
    //   57: iconst_1
    //   58: ldc 46
    //   60: castore
    //   61: dup
    //   62: iconst_2
    //   63: ldc 47
    //   65: castore
    //   66: dup
    //   67: iconst_3
    //   68: ldc 48
    //   70: castore
    //   71: dup
    //   72: iconst_4
    //   73: ldc 49
    //   75: castore
    //   76: dup
    //   77: iconst_5
    //   78: ldc 50
    //   80: castore
    //   81: dup
    //   82: bipush 6
    //   84: ldc 51
    //   86: castore
    //   87: dup
    //   88: bipush 7
    //   90: ldc 52
    //   92: castore
    //   93: invokestatic 54	o/af:ॱ	([C)Ljava/lang/String;
    //   96: invokevirtual 58	java/lang/String:intern	()Ljava/lang/String;
    //   99: astore 4
    //   101: new 139	java/lang/StringBuilder
    //   104: dup
    //   105: invokespecial 140	java/lang/StringBuilder:<init>	()V
    //   108: bipush 21
    //   110: newarray char
    //   112: dup
    //   113: iconst_0
    //   114: ldc -115
    //   116: castore
    //   117: dup
    //   118: iconst_1
    //   119: ldc -114
    //   121: castore
    //   122: dup
    //   123: iconst_2
    //   124: ldc -113
    //   126: castore
    //   127: dup
    //   128: iconst_3
    //   129: ldc -112
    //   131: castore
    //   132: dup
    //   133: iconst_4
    //   134: ldc -111
    //   136: castore
    //   137: dup
    //   138: iconst_5
    //   139: ldc -110
    //   141: castore
    //   142: dup
    //   143: bipush 6
    //   145: ldc -109
    //   147: castore
    //   148: dup
    //   149: bipush 7
    //   151: ldc -108
    //   153: castore
    //   154: dup
    //   155: bipush 8
    //   157: ldc -107
    //   159: castore
    //   160: dup
    //   161: bipush 9
    //   163: ldc -106
    //   165: castore
    //   166: dup
    //   167: bipush 10
    //   169: ldc -105
    //   171: castore
    //   172: dup
    //   173: bipush 11
    //   175: ldc -104
    //   177: castore
    //   178: dup
    //   179: bipush 12
    //   181: ldc -103
    //   183: castore
    //   184: dup
    //   185: bipush 13
    //   187: ldc -102
    //   189: castore
    //   190: dup
    //   191: bipush 14
    //   193: ldc -101
    //   195: castore
    //   196: dup
    //   197: bipush 15
    //   199: ldc -100
    //   201: castore
    //   202: dup
    //   203: bipush 16
    //   205: ldc -99
    //   207: castore
    //   208: dup
    //   209: bipush 17
    //   211: ldc -98
    //   213: castore
    //   214: dup
    //   215: bipush 18
    //   217: ldc -97
    //   219: castore
    //   220: dup
    //   221: bipush 19
    //   223: ldc -96
    //   225: castore
    //   226: dup
    //   227: bipush 20
    //   229: ldc -95
    //   231: castore
    //   232: invokestatic 54	o/af:ॱ	([C)Ljava/lang/String;
    //   235: invokevirtual 58	java/lang/String:intern	()Ljava/lang/String;
    //   238: invokevirtual 165	java/lang/StringBuilder:append	(Ljava/lang/String;)Ljava/lang/StringBuilder;
    //   241: iload_2
    //   242: invokevirtual 168	java/lang/StringBuilder:append	(Z)Ljava/lang/StringBuilder;
    //   245: bipush 23
    //   247: newarray char
    //   249: dup
    //   250: iconst_0
    //   251: ldc -87
    //   253: castore
    //   254: dup
    //   255: iconst_1
    //   256: ldc -86
    //   258: castore
    //   259: dup
    //   260: iconst_2
    //   261: ldc -85
    //   263: castore
    //   264: dup
    //   265: iconst_3
    //   266: ldc -84
    //   268: castore
    //   269: dup
    //   270: iconst_4
    //   271: ldc -83
    //   273: castore
    //   274: dup
    //   275: iconst_5
    //   276: ldc -82
    //   278: castore
    //   279: dup
    //   280: bipush 6
    //   282: ldc -81
    //   284: castore
    //   285: dup
    //   286: bipush 7
    //   288: ldc -80
    //   290: castore
    //   291: dup
    //   292: bipush 8
    //   294: ldc -79
    //   296: castore
    //   297: dup
    //   298: bipush 9
    //   300: ldc -78
    //   302: castore
    //   303: dup
    //   304: bipush 10
    //   306: ldc -77
    //   308: castore
    //   309: dup
    //   310: bipush 11
    //   312: ldc -76
    //   314: castore
    //   315: dup
    //   316: bipush 12
    //   318: ldc -75
    //   320: castore
    //   321: dup
    //   322: bipush 13
    //   324: ldc -74
    //   326: castore
    //   327: dup
    //   328: bipush 14
    //   330: ldc -73
    //   332: castore
    //   333: dup
    //   334: bipush 15
    //   336: ldc -72
    //   338: castore
    //   339: dup
    //   340: bipush 16
    //   342: ldc -71
    //   344: castore
    //   345: dup
    //   346: bipush 17
    //   348: ldc -70
    //   350: castore
    //   351: dup
    //   352: bipush 18
    //   354: ldc -69
    //   356: castore
    //   357: dup
    //   358: bipush 19
    //   360: ldc -68
    //   362: castore
    //   363: dup
    //   364: bipush 20
    //   366: ldc -67
    //   368: castore
    //   369: dup
    //   370: bipush 21
    //   372: ldc -66
    //   374: castore
    //   375: dup
    //   376: bipush 22
    //   378: ldc -65
    //   380: castore
    //   381: invokestatic 54	o/af:ॱ	([C)Ljava/lang/String;
    //   384: invokevirtual 58	java/lang/String:intern	()Ljava/lang/String;
    //   387: invokevirtual 165	java/lang/StringBuilder:append	(Ljava/lang/String;)Ljava/lang/StringBuilder;
    //   390: iload_1
    //   391: invokevirtual 194	java/lang/StringBuilder:append	(I)Ljava/lang/StringBuilder;
    //   394: invokevirtual 197	java/lang/StringBuilder:toString	()Ljava/lang/String;
    //   397: astore_3
    //   398: goto +20 -> 418
    //   401: astore_3
    //   402: aload_3
    //   403: invokevirtual 114	java/lang/Throwable:getCause	()Ljava/lang/Throwable;
    //   406: astore 4
    //   408: aload 4
    //   410: ifnull +6 -> 416
    //   413: aload 4
    //   415: athrow
    //   416: aload_3
    //   417: athrow
    //   418: iconst_4
    //   419: bipush 42
    //   421: ldc 115
    //   423: invokestatic 120	o/O:ˋ	(IIC)Ljava/lang/Object;
    //   426: checkcast 122	java/lang/Class
    //   429: ldc 123
    //   431: iconst_2
    //   432: anewarray 122	java/lang/Class
    //   435: dup
    //   436: iconst_0
    //   437: ldc 38
    //   439: aastore
    //   440: dup
    //   441: iconst_1
    //   442: ldc 38
    //   444: aastore
    //   445: invokevirtual 127	java/lang/Class:getMethod	(Ljava/lang/String;[Ljava/lang/Class;)Ljava/lang/reflect/Method;
    //   448: aconst_null
    //   449: iconst_2
    //   450: anewarray 4	java/lang/Object
    //   453: dup
    //   454: iconst_0
    //   455: aload 4
    //   457: aastore
    //   458: dup
    //   459: iconst_1
    //   460: aload_3
    //   461: aastore
    //   462: invokevirtual 133	java/lang/reflect/Method:invoke	(Ljava/lang/Object;[Ljava/lang/Object;)Ljava/lang/Object;
    //   465: pop
    //   466: aload_0
    //   467: getfield 44	o/af:ˋ	Lo/ah;
    //   470: iload_1
    //   471: iload_2
    //   472: invokevirtual 199	o/ah:ˋ	(IZ)V
    //   475: goto -457 -> 18
    //   478: goto +45 -> 523
    //   481: aload_0
    //   482: getfield 44	o/af:ˋ	Lo/ah;
    //   485: ifnull +6 -> 491
    //   488: goto -441 -> 47
    //   491: goto -13 -> 478
    //   494: iload_1
    //   495: lookupswitch	default:+25->520, 14:+61->556, 54:+65->560
    //   520: goto +40 -> 560
    //   523: getstatic 22	o/af:ʽ	I
    //   526: bipush 47
    //   528: iadd
    //   529: istore_1
    //   530: iload_1
    //   531: sipush 128
    //   534: irem
    //   535: putstatic 20	o/af:ᐝ	I
    //   538: iload_1
    //   539: iconst_2
    //   540: irem
    //   541: ifeq +6 -> 547
    //   544: goto -538 -> 6
    //   547: goto -535 -> 12
    //   550: goto -69 -> 481
    //   553: astore_3
    //   554: aload_3
    //   555: athrow
    //   556: return
    //   557: goto -554 -> 3
    //   560: new 201	java/lang/NullPointerException
    //   563: dup
    //   564: invokespecial 202	java/lang/NullPointerException:<init>	()V
    //   567: athrow
    // Local variable table:
    //   start	length	slot	name	signature
    //   0	568	0	this	af
    //   0	568	1	paramInt	int
    //   0	568	2	paramBoolean	boolean
    //   397	1	3	str	String
    //   401	60	3	localObject1	Object
    //   553	2	3	localException	Exception
    //   99	357	4	localObject2	Object
    // Exception table:
    //   from	to	target	type
    //   418	466	401	finally
    //   18	22	553	java/lang/Exception
    //   27	35	553	java/lang/Exception
  }
  
  public void ˋ(ah paramAh)
  {
    for (;;)
    {
      int i = 1;
      try
      {
        i = ʽ;
        i += 81;
      }
      catch (Exception paramAh)
      {
        try
        {
          ᐝ = i % 128;
          if (i % 2 == 0)
          {
            continue;
            this.ˋ = paramAh;
            i = 63 / 0;
            return;
          }
          i = 51;
          switch (i)
          {
          }
        }
        catch (Exception paramAh)
        {
          throw paramAh;
        }
        paramAh = paramAh;
        throw paramAh;
      }
    }
    this.ˋ = paramAh;
  }
  
  public boolean ˋ()
  {
    for (;;)
    {
      int i = 1;
      break label133;
      label8:
      break label20;
      break label106;
      label14:
      i = 36;
      try
      {
        label20:
        boolean bool;
        for (;;)
        {
          ai localAi = this.ˎ;
          if (localAi == null)
          {
            break label14;
            bool = false;
            break label167;
          }
          for (;;)
          {
            switch (i)
            {
            }
            i = ʽ + 99;
            ᐝ = i % 128;
            if (i % 2 != 0) {
              break;
            }
            break label159;
            label95:
            bool = true;
            break label167;
            i = 13;
          }
          label106:
          i = ᐝ + 45;
          ʽ = i % 128;
          if (i % 2 == 0) {
            break label8;
          }
        }
        for (;;)
        {
          switch (i)
          {
          case 0: 
          default: 
            label133:
            break label95;
            label159:
            i = 0;
          }
        }
        return bool;
      }
      catch (Exception localException)
      {
        throw localException;
      }
    }
    label167:
    return false;
  }
  
  public ah ˎ()
  {
    break label28;
    int i = 69;
    break label82;
    label9:
    i = 14;
    break label82;
    label15:
    i = null.length;
    ah localAh;
    return localAh;
    for (;;)
    {
      localAh = this.ˋ;
      break label55;
      label28:
      i = ᐝ + 13;
      ʽ = i % 128;
      if (i % 2 != 0)
      {
        continue;
        label55:
        i = ʽ + 59;
        ᐝ = i % 128;
        if (i % 2 != 0) {
          break label9;
        }
        break;
        switch (i)
        {
        case 14: 
        default: 
          label82:
          break label15;
        }
      }
    }
    return localAh;
  }
  
  public void ˎ(Activity paramActivity, int paramInt)
  {
    for (;;)
    {
      try
      {
        label6:
        paramInt = ᐝ;
        paramInt += 113;
        ʽ = paramInt % 128;
        if (paramInt % 2 != 0)
        {
          return;
          for (;;)
          {
            this.ॱ = paramInt;
            ז.ˊ(paramActivity, this.ˏ, paramInt);
            break label6;
            int i = ʽ + 91;
            ᐝ = i % 128;
            if (i % 2 != 0) {
              break;
            }
          }
        }
        return;
      }
      catch (Exception paramActivity)
      {
        throw paramActivity;
      }
    }
  }
  
  public void ˏ(ai paramAi)
  {
    break label91;
    this.ˎ = paramAi;
    return;
    int i;
    for (;;)
    {
      switch (i)
      {
      case 94: 
      default: 
        break label78;
        label39:
        i = 94;
      }
    }
    label78:
    label91:
    for (;;)
    {
      i = ʽ + 81;
      ᐝ = i % 128;
      if (i % 2 == 0) {
        break label39;
      }
      i = 19;
      break;
      this.ˎ = paramAi;
      throw new NullPointerException();
    }
  }
  
  public ai ॱ()
  {
    for (;;)
    {
      int i = 0;
      for (;;)
      {
        return this.ˎ;
        switch (i)
        {
        }
      }
      ai localAi = this.ˎ;
      i = 90 / 0;
      return localAi;
      do
      {
        i = 1;
        break;
        i = ᐝ + 21;
        ʽ = i % 128;
      } while (i % 2 == 0);
    }
  }
  
  /* Error */
  public void ॱ(int paramInt)
  {
    // Byte code:
    //   0: goto +21 -> 21
    //   3: aload_0
    //   4: getfield 44	o/af:ˋ	Lo/ah;
    //   7: astore_3
    //   8: aload_3
    //   9: ifnull +6 -> 15
    //   12: goto +58 -> 70
    //   15: goto +3 -> 18
    //   18: goto +534 -> 552
    //   21: goto +559 -> 580
    //   24: iconst_1
    //   25: istore_2
    //   26: iload_2
    //   27: tableswitch	default:+21->48, 0:+-24->3, 1:+24->51
    //   48: goto -45 -> 3
    //   51: aload_0
    //   52: getfield 44	o/af:ˋ	Lo/ah;
    //   55: astore_3
    //   56: new 201	java/lang/NullPointerException
    //   59: dup
    //   60: invokespecial 202	java/lang/NullPointerException:<init>	()V
    //   63: athrow
    //   64: goto -46 -> 18
    //   67: astore_3
    //   68: aload_3
    //   69: athrow
    //   70: bipush 8
    //   72: newarray char
    //   74: dup
    //   75: iconst_0
    //   76: ldc 45
    //   78: castore
    //   79: dup
    //   80: iconst_1
    //   81: ldc 46
    //   83: castore
    //   84: dup
    //   85: iconst_2
    //   86: ldc 47
    //   88: castore
    //   89: dup
    //   90: iconst_3
    //   91: ldc 48
    //   93: castore
    //   94: dup
    //   95: iconst_4
    //   96: ldc 49
    //   98: castore
    //   99: dup
    //   100: iconst_5
    //   101: ldc 50
    //   103: castore
    //   104: dup
    //   105: bipush 6
    //   107: ldc 51
    //   109: castore
    //   110: dup
    //   111: bipush 7
    //   113: ldc 52
    //   115: castore
    //   116: invokestatic 54	o/af:ॱ	([C)Ljava/lang/String;
    //   119: invokevirtual 58	java/lang/String:intern	()Ljava/lang/String;
    //   122: astore_3
    //   123: new 139	java/lang/StringBuilder
    //   126: dup
    //   127: invokespecial 140	java/lang/StringBuilder:<init>	()V
    //   130: bipush 52
    //   132: newarray char
    //   134: dup
    //   135: iconst_0
    //   136: ldc -37
    //   138: castore
    //   139: dup
    //   140: iconst_1
    //   141: ldc -36
    //   143: castore
    //   144: dup
    //   145: iconst_2
    //   146: ldc -35
    //   148: castore
    //   149: dup
    //   150: iconst_3
    //   151: ldc -34
    //   153: castore
    //   154: dup
    //   155: iconst_4
    //   156: ldc -33
    //   158: castore
    //   159: dup
    //   160: iconst_5
    //   161: ldc -32
    //   163: castore
    //   164: dup
    //   165: bipush 6
    //   167: ldc -31
    //   169: castore
    //   170: dup
    //   171: bipush 7
    //   173: ldc -30
    //   175: castore
    //   176: dup
    //   177: bipush 8
    //   179: ldc -29
    //   181: castore
    //   182: dup
    //   183: bipush 9
    //   185: ldc -28
    //   187: castore
    //   188: dup
    //   189: bipush 10
    //   191: ldc -27
    //   193: castore
    //   194: dup
    //   195: bipush 11
    //   197: ldc -26
    //   199: castore
    //   200: dup
    //   201: bipush 12
    //   203: ldc -25
    //   205: castore
    //   206: dup
    //   207: bipush 13
    //   209: ldc -24
    //   211: castore
    //   212: dup
    //   213: bipush 14
    //   215: ldc -23
    //   217: castore
    //   218: dup
    //   219: bipush 15
    //   221: ldc -22
    //   223: castore
    //   224: dup
    //   225: bipush 16
    //   227: ldc -21
    //   229: castore
    //   230: dup
    //   231: bipush 17
    //   233: ldc -20
    //   235: castore
    //   236: dup
    //   237: bipush 18
    //   239: ldc -19
    //   241: castore
    //   242: dup
    //   243: bipush 19
    //   245: ldc -18
    //   247: castore
    //   248: dup
    //   249: bipush 20
    //   251: ldc -17
    //   253: castore
    //   254: dup
    //   255: bipush 21
    //   257: ldc -16
    //   259: castore
    //   260: dup
    //   261: bipush 22
    //   263: ldc -15
    //   265: castore
    //   266: dup
    //   267: bipush 23
    //   269: ldc -14
    //   271: castore
    //   272: dup
    //   273: bipush 24
    //   275: ldc -13
    //   277: castore
    //   278: dup
    //   279: bipush 25
    //   281: ldc -12
    //   283: castore
    //   284: dup
    //   285: bipush 26
    //   287: ldc -11
    //   289: castore
    //   290: dup
    //   291: bipush 27
    //   293: ldc -10
    //   295: castore
    //   296: dup
    //   297: bipush 28
    //   299: ldc -9
    //   301: castore
    //   302: dup
    //   303: bipush 29
    //   305: ldc -8
    //   307: castore
    //   308: dup
    //   309: bipush 30
    //   311: ldc -7
    //   313: castore
    //   314: dup
    //   315: bipush 31
    //   317: ldc -6
    //   319: castore
    //   320: dup
    //   321: bipush 32
    //   323: ldc -5
    //   325: castore
    //   326: dup
    //   327: bipush 33
    //   329: ldc -4
    //   331: castore
    //   332: dup
    //   333: bipush 34
    //   335: ldc -3
    //   337: castore
    //   338: dup
    //   339: bipush 35
    //   341: ldc -2
    //   343: castore
    //   344: dup
    //   345: bipush 36
    //   347: ldc -1
    //   349: castore
    //   350: dup
    //   351: bipush 37
    //   353: ldc_w 256
    //   356: castore
    //   357: dup
    //   358: bipush 38
    //   360: ldc_w 257
    //   363: castore
    //   364: dup
    //   365: bipush 39
    //   367: ldc_w 258
    //   370: castore
    //   371: dup
    //   372: bipush 40
    //   374: ldc_w 259
    //   377: castore
    //   378: dup
    //   379: bipush 41
    //   381: ldc_w 260
    //   384: castore
    //   385: dup
    //   386: bipush 42
    //   388: ldc_w 261
    //   391: castore
    //   392: dup
    //   393: bipush 43
    //   395: ldc_w 262
    //   398: castore
    //   399: dup
    //   400: bipush 44
    //   402: ldc_w 263
    //   405: castore
    //   406: dup
    //   407: bipush 45
    //   409: ldc_w 264
    //   412: castore
    //   413: dup
    //   414: bipush 46
    //   416: ldc_w 265
    //   419: castore
    //   420: dup
    //   421: bipush 47
    //   423: ldc_w 266
    //   426: castore
    //   427: dup
    //   428: bipush 48
    //   430: ldc_w 267
    //   433: castore
    //   434: dup
    //   435: bipush 49
    //   437: ldc_w 268
    //   440: castore
    //   441: dup
    //   442: bipush 50
    //   444: ldc_w 269
    //   447: castore
    //   448: dup
    //   449: bipush 51
    //   451: ldc_w 270
    //   454: castore
    //   455: invokestatic 54	o/af:ॱ	([C)Ljava/lang/String;
    //   458: invokevirtual 58	java/lang/String:intern	()Ljava/lang/String;
    //   461: invokevirtual 165	java/lang/StringBuilder:append	(Ljava/lang/String;)Ljava/lang/StringBuilder;
    //   464: iload_1
    //   465: invokevirtual 194	java/lang/StringBuilder:append	(I)Ljava/lang/StringBuilder;
    //   468: invokevirtual 197	java/lang/StringBuilder:toString	()Ljava/lang/String;
    //   471: astore 4
    //   473: goto +20 -> 493
    //   476: astore_3
    //   477: aload_3
    //   478: invokevirtual 114	java/lang/Throwable:getCause	()Ljava/lang/Throwable;
    //   481: astore 4
    //   483: aload 4
    //   485: ifnull +6 -> 491
    //   488: aload 4
    //   490: athrow
    //   491: aload_3
    //   492: athrow
    //   493: iconst_4
    //   494: bipush 42
    //   496: ldc 115
    //   498: invokestatic 120	o/O:ˋ	(IIC)Ljava/lang/Object;
    //   501: checkcast 122	java/lang/Class
    //   504: ldc 123
    //   506: iconst_2
    //   507: anewarray 122	java/lang/Class
    //   510: dup
    //   511: iconst_0
    //   512: ldc 38
    //   514: aastore
    //   515: dup
    //   516: iconst_1
    //   517: ldc 38
    //   519: aastore
    //   520: invokevirtual 127	java/lang/Class:getMethod	(Ljava/lang/String;[Ljava/lang/Class;)Ljava/lang/reflect/Method;
    //   523: aconst_null
    //   524: iconst_2
    //   525: anewarray 4	java/lang/Object
    //   528: dup
    //   529: iconst_0
    //   530: aload_3
    //   531: aastore
    //   532: dup
    //   533: iconst_1
    //   534: aload 4
    //   536: aastore
    //   537: invokevirtual 133	java/lang/reflect/Method:invoke	(Ljava/lang/Object;[Ljava/lang/Object;)Ljava/lang/Object;
    //   540: pop
    //   541: aload_0
    //   542: getfield 44	o/af:ˋ	Lo/ah;
    //   545: iload_1
    //   546: invokevirtual 272	o/ah:ˏ	(I)V
    //   549: goto -485 -> 64
    //   552: getstatic 22	o/af:ʽ	I
    //   555: bipush 71
    //   557: iadd
    //   558: istore_1
    //   559: iload_1
    //   560: sipush 128
    //   563: irem
    //   564: putstatic 20	o/af:ᐝ	I
    //   567: iload_1
    //   568: iconst_2
    //   569: irem
    //   570: ifeq +4 -> 574
    //   573: return
    //   574: return
    //   575: iconst_0
    //   576: istore_2
    //   577: goto -551 -> 26
    //   580: getstatic 20	o/af:ᐝ	I
    //   583: bipush 67
    //   585: iadd
    //   586: istore_2
    //   587: iload_2
    //   588: sipush 128
    //   591: irem
    //   592: putstatic 22	o/af:ʽ	I
    //   595: iload_2
    //   596: iconst_2
    //   597: irem
    //   598: ifne +6 -> 604
    //   601: goto -577 -> 24
    //   604: goto -29 -> 575
    // Local variable table:
    //   start	length	slot	name	signature
    //   0	607	0	this	af
    //   0	607	1	paramInt	int
    //   25	573	2	i	int
    //   7	49	3	localAh	ah
    //   67	2	3	localException	Exception
    //   122	1	3	str	String
    //   476	55	3	localObject1	Object
    //   471	64	4	localObject2	Object
    // Exception table:
    //   from	to	target	type
    //   3	8	67	java/lang/Exception
    //   493	541	476	finally
  }
}
