package o;

import android.content.Context;
import android.database.DataSetObserver;
import android.util.AttributeSet;
import android.view.View;

public class aG
  extends ڏ
{
  private static int ʻ = 1;
  private static int ʼ = 0;
  private static long ˋ = -3006676389590857037L;
  private boolean ˊ = true;
  
  public aG(Context paramContext)
  {
    super(paramContext);
  }
  
  public aG(Context paramContext, AttributeSet paramAttributeSet)
  {
    super(paramContext, paramAttributeSet);
  }
  
  /* Error */
  private static String ˋ(char[] paramArrayOfChar)
  {
    // Byte code:
    //   0: goto +44 -> 44
    //   3: bipush 68
    //   5: istore_2
    //   6: goto +117 -> 123
    //   9: aload_0
    //   10: iconst_0
    //   11: caload
    //   12: istore_3
    //   13: aload_0
    //   14: arraylength
    //   15: iconst_1
    //   16: isub
    //   17: newarray char
    //   19: astore 4
    //   21: iconst_1
    //   22: istore_1
    //   23: goto +9 -> 32
    //   26: bipush 28
    //   28: istore_2
    //   29: goto +94 -> 123
    //   32: iload_1
    //   33: aload_0
    //   34: arraylength
    //   35: if_icmpge +6 -> 41
    //   38: goto -12 -> 26
    //   41: goto -38 -> 3
    //   44: goto +111 -> 155
    //   47: goto -38 -> 9
    //   50: goto +6 -> 56
    //   53: astore_0
    //   54: aload_0
    //   55: athrow
    //   56: aload 4
    //   58: iload_1
    //   59: iconst_1
    //   60: isub
    //   61: aload_0
    //   62: iload_1
    //   63: caload
    //   64: iload_1
    //   65: iload_3
    //   66: imul
    //   67: ixor
    //   68: i2l
    //   69: getstatic 23	o/aG:ˋ	J
    //   72: lxor
    //   73: l2i
    //   74: i2c
    //   75: castore
    //   76: iload_1
    //   77: iconst_1
    //   78: iadd
    //   79: istore_1
    //   80: goto -48 -> 32
    //   83: astore_0
    //   84: aload_0
    //   85: athrow
    //   86: getstatic 17	o/aG:ʼ	I
    //   89: bipush 33
    //   91: iadd
    //   92: istore_2
    //   93: iload_2
    //   94: sipush 128
    //   97: irem
    //   98: putstatic 19	o/aG:ʻ	I
    //   101: iload_2
    //   102: iconst_2
    //   103: irem
    //   104: ifne +6 -> 110
    //   107: goto -57 -> 50
    //   110: goto -54 -> 56
    //   113: new 38	java/lang/String
    //   116: dup
    //   117: aload 4
    //   119: invokespecial 41	java/lang/String:<init>	([C)V
    //   122: areturn
    //   123: iload_2
    //   124: lookupswitch	default:+28->152, 28:+-38->86, 68:+-11->113
    //   152: goto -39 -> 113
    //   155: getstatic 19	o/aG:ʻ	I
    //   158: bipush 85
    //   160: iadd
    //   161: istore_1
    //   162: iload_1
    //   163: sipush 128
    //   166: irem
    //   167: putstatic 17	o/aG:ʼ	I
    //   170: iload_1
    //   171: iconst_2
    //   172: irem
    //   173: ifeq +6 -> 179
    //   176: goto -129 -> 47
    //   179: goto -170 -> 9
    // Local variable table:
    //   start	length	slot	name	signature
    //   0	182	0	paramArrayOfChar	char[]
    //   22	151	1	i	int
    //   5	119	2	j	int
    //   12	55	3	k	int
    //   19	99	4	arrayOfChar	char[]
    // Exception table:
    //   from	to	target	type
    //   93	101	53	java/lang/Exception
    //   86	93	83	java/lang/Exception
    //   93	101	83	java/lang/Exception
  }
  
  /* Error */
  public boolean onInterceptTouchEvent(android.view.MotionEvent paramMotionEvent)
  {
    // Byte code:
    //   0: goto +86 -> 86
    //   3: iconst_0
    //   4: istore_2
    //   5: goto +167 -> 172
    //   8: iconst_0
    //   9: ireturn
    //   10: astore_1
    //   11: aload_1
    //   12: athrow
    //   13: iconst_1
    //   14: istore_2
    //   15: goto +157 -> 172
    //   18: bipush 60
    //   20: istore_2
    //   21: goto +87 -> 108
    //   24: iconst_1
    //   25: ireturn
    //   26: aload_0
    //   27: aload_1
    //   28: invokespecial 45	o/ڏ:onInterceptTouchEvent	(Landroid/view/MotionEvent;)Z
    //   31: ifeq +6 -> 37
    //   34: goto +105 -> 139
    //   37: goto +130 -> 167
    //   40: aload_0
    //   41: getfield 30	o/aG:ˊ	Z
    //   44: ifeq +6 -> 50
    //   47: goto -34 -> 13
    //   50: goto -47 -> 3
    //   53: bipush 48
    //   55: istore_2
    //   56: goto +52 -> 108
    //   59: getstatic 17	o/aG:ʼ	I
    //   62: bipush 19
    //   64: iadd
    //   65: istore_2
    //   66: iload_2
    //   67: sipush 128
    //   70: irem
    //   71: putstatic 19	o/aG:ʻ	I
    //   74: iload_2
    //   75: iconst_2
    //   76: irem
    //   77: ifne +6 -> 83
    //   80: goto +9 -> 89
    //   83: goto -57 -> 26
    //   86: goto -46 -> 40
    //   89: aload_0
    //   90: aload_1
    //   91: invokespecial 45	o/ڏ:onInterceptTouchEvent	(Landroid/view/MotionEvent;)Z
    //   94: istore_3
    //   95: aconst_null
    //   96: arraylength
    //   97: istore_2
    //   98: iload_3
    //   99: ifeq +6 -> 105
    //   102: goto -84 -> 18
    //   105: goto -52 -> 53
    //   108: iload_2
    //   109: lookupswitch	default:+27->136, 48:+-101->8, 60:+90->199
    //   136: goto -128 -> 8
    //   139: iconst_1
    //   140: istore_2
    //   141: iload_2
    //   142: tableswitch	default:+22->164, 0:+-134->8, 1:+57->199
    //   164: goto -156 -> 8
    //   167: iconst_0
    //   168: istore_2
    //   169: goto -28 -> 141
    //   172: iload_2
    //   173: tableswitch	default:+23->196, 0:+-165->8, 1:+-114->59
    //   196: goto -137 -> 59
    //   199: goto +6 -> 205
    //   202: astore_1
    //   203: aload_1
    //   204: athrow
    //   205: getstatic 17	o/aG:ʼ	I
    //   208: istore_2
    //   209: iload_2
    //   210: bipush 101
    //   212: iadd
    //   213: istore_2
    //   214: iload_2
    //   215: sipush 128
    //   218: irem
    //   219: putstatic 19	o/aG:ʻ	I
    //   222: iload_2
    //   223: iconst_2
    //   224: irem
    //   225: ifne +5 -> 230
    //   228: iconst_1
    //   229: ireturn
    //   230: goto -206 -> 24
    // Local variable table:
    //   start	length	slot	name	signature
    //   0	233	0	this	aG
    //   0	233	1	paramMotionEvent	android.view.MotionEvent
    //   4	221	2	i	int
    //   94	5	3	bool	boolean
    // Exception table:
    //   from	to	target	type
    //   205	209	10	java/lang/Exception
    //   214	222	202	java/lang/Exception
  }
  
  /* Error */
  public void setAdapter(с paramС)
  {
    // Byte code:
    //   0: goto +331 -> 331
    //   3: iload_2
    //   4: tableswitch	default:+24->28, 0:+257->261, 1:+27->31
    //   28: goto +3 -> 31
    //   31: aload_0
    //   32: aload_1
    //   33: invokespecial 49	o/ڏ:setAdapter	(Lo/с;)V
    //   36: goto +219 -> 255
    //   39: iconst_0
    //   40: istore_2
    //   41: goto -38 -> 3
    //   44: aload_1
    //   45: instanceof 51
    //   48: ifne +6 -> 54
    //   51: goto -12 -> 39
    //   54: goto +245 -> 299
    //   57: astore_1
    //   58: aload_1
    //   59: athrow
    //   60: bipush 28
    //   62: newarray char
    //   64: dup
    //   65: iconst_0
    //   66: ldc 52
    //   68: castore
    //   69: dup
    //   70: iconst_1
    //   71: ldc 53
    //   73: castore
    //   74: dup
    //   75: iconst_2
    //   76: ldc 54
    //   78: castore
    //   79: dup
    //   80: iconst_3
    //   81: ldc 55
    //   83: castore
    //   84: dup
    //   85: iconst_4
    //   86: ldc 56
    //   88: castore
    //   89: dup
    //   90: iconst_5
    //   91: ldc 57
    //   93: castore
    //   94: dup
    //   95: bipush 6
    //   97: ldc 58
    //   99: castore
    //   100: dup
    //   101: bipush 7
    //   103: ldc 59
    //   105: castore
    //   106: dup
    //   107: bipush 8
    //   109: ldc 60
    //   111: castore
    //   112: dup
    //   113: bipush 9
    //   115: ldc 61
    //   117: castore
    //   118: dup
    //   119: bipush 10
    //   121: ldc 62
    //   123: castore
    //   124: dup
    //   125: bipush 11
    //   127: ldc 63
    //   129: castore
    //   130: dup
    //   131: bipush 12
    //   133: ldc 64
    //   135: castore
    //   136: dup
    //   137: bipush 13
    //   139: ldc 65
    //   141: castore
    //   142: dup
    //   143: bipush 14
    //   145: ldc 66
    //   147: castore
    //   148: dup
    //   149: bipush 15
    //   151: ldc 67
    //   153: castore
    //   154: dup
    //   155: bipush 16
    //   157: ldc 68
    //   159: castore
    //   160: dup
    //   161: bipush 17
    //   163: ldc 69
    //   165: castore
    //   166: dup
    //   167: bipush 18
    //   169: ldc 70
    //   171: castore
    //   172: dup
    //   173: bipush 19
    //   175: ldc 71
    //   177: castore
    //   178: dup
    //   179: bipush 20
    //   181: ldc 72
    //   183: castore
    //   184: dup
    //   185: bipush 21
    //   187: ldc 73
    //   189: castore
    //   190: dup
    //   191: bipush 22
    //   193: ldc 74
    //   195: castore
    //   196: dup
    //   197: bipush 23
    //   199: ldc 75
    //   201: castore
    //   202: dup
    //   203: bipush 24
    //   205: ldc 76
    //   207: castore
    //   208: dup
    //   209: bipush 25
    //   211: ldc 77
    //   213: castore
    //   214: dup
    //   215: bipush 26
    //   217: ldc 78
    //   219: castore
    //   220: dup
    //   221: bipush 27
    //   223: ldc 79
    //   225: castore
    //   226: invokestatic 81	o/aG:ˋ	([C)Ljava/lang/String;
    //   229: astore_1
    //   230: new 83	java/lang/IllegalArgumentException
    //   233: dup
    //   234: aload_1
    //   235: invokevirtual 87	java/lang/String:intern	()Ljava/lang/String;
    //   238: invokespecial 90	java/lang/IllegalArgumentException:<init>	(Ljava/lang/String;)V
    //   241: athrow
    //   242: aload_1
    //   243: instanceof 51
    //   246: istore_3
    //   247: new 92	java/lang/NullPointerException
    //   250: dup
    //   251: invokespecial 94	java/lang/NullPointerException:<init>	()V
    //   254: athrow
    //   255: goto +19 -> 274
    //   258: astore_1
    //   259: aload_1
    //   260: athrow
    //   261: aload_1
    //   262: instanceof 96
    //   265: ifeq +6 -> 271
    //   268: goto -237 -> 31
    //   271: goto -211 -> 60
    //   274: getstatic 17	o/aG:ʼ	I
    //   277: istore_2
    //   278: iload_2
    //   279: bipush 123
    //   281: iadd
    //   282: istore_2
    //   283: iload_2
    //   284: sipush 128
    //   287: irem
    //   288: putstatic 19	o/aG:ʻ	I
    //   291: iload_2
    //   292: iconst_2
    //   293: irem
    //   294: ifne +4 -> 298
    //   297: return
    //   298: return
    //   299: iconst_1
    //   300: istore_2
    //   301: goto -298 -> 3
    //   304: getstatic 17	o/aG:ʼ	I
    //   307: bipush 87
    //   309: iadd
    //   310: istore_2
    //   311: iload_2
    //   312: sipush 128
    //   315: irem
    //   316: putstatic 19	o/aG:ʻ	I
    //   319: iload_2
    //   320: iconst_2
    //   321: irem
    //   322: ifne +6 -> 328
    //   325: goto -83 -> 242
    //   328: goto -284 -> 44
    //   331: goto -27 -> 304
    // Local variable table:
    //   start	length	slot	name	signature
    //   0	334	0	this	aG
    //   0	334	1	paramС	с
    //   3	319	2	i	int
    //   246	1	3	bool	boolean
    // Exception table:
    //   from	to	target	type
    //   60	230	57	java/lang/Exception
    //   283	291	57	java/lang/Exception
    //   60	230	258	java/lang/Exception
    //   230	242	258	java/lang/Exception
    //   274	278	258	java/lang/Exception
  }
  
  public void setEmptyView(final View paramView)
  {
    break label98;
    paramView = new DataSetObserver()
    {
      public void onChanged()
      {
        if (aG.this.ˋ().ॱ() == 0)
        {
          paramView.setVisibility(0);
          aG.this.setVisibility(8);
          return;
        }
        paramView.setVisibility(8);
        aG.this.setVisibility(0);
      }
    };
    с localС;
    localС.ˏ(paramView);
    paramView.onChanged();
    label98:
    for (;;)
    {
      try
      {
        localС = ˋ();
        if (localС != null) {
          break;
        }
        continue;
        int i = ʼ + 71;
        ʻ = i % 128;
        if (i % 2 == 0) {
          return;
        }
        return;
        continue;
        i = ʼ + 1;
        ʻ = i % 128;
        if (i % 2 != 0) {}
      }
      catch (Exception paramView)
      {
        throw paramView;
      }
    }
  }
  
  /* Error */
  public void setScrollable(boolean paramBoolean)
  {
    // Byte code:
    //   0: goto +18 -> 18
    //   3: return
    //   4: goto +6 -> 10
    //   7: astore_3
    //   8: aload_3
    //   9: athrow
    //   10: aload_0
    //   11: iload_1
    //   12: putfield 30	o/aG:ˊ	Z
    //   15: goto +33 -> 48
    //   18: getstatic 17	o/aG:ʼ	I
    //   21: bipush 75
    //   23: iadd
    //   24: istore_2
    //   25: iload_2
    //   26: sipush 128
    //   29: irem
    //   30: putstatic 19	o/aG:ʻ	I
    //   33: iload_2
    //   34: iconst_2
    //   35: irem
    //   36: ifne +6 -> 42
    //   39: goto -35 -> 4
    //   42: goto -32 -> 10
    //   45: astore_3
    //   46: aload_3
    //   47: athrow
    //   48: getstatic 17	o/aG:ʼ	I
    //   51: istore_2
    //   52: iload_2
    //   53: bipush 13
    //   55: iadd
    //   56: istore_2
    //   57: iload_2
    //   58: sipush 128
    //   61: irem
    //   62: putstatic 19	o/aG:ʻ	I
    //   65: iload_2
    //   66: iconst_2
    //   67: irem
    //   68: ifne +6 -> 74
    //   71: goto -68 -> 3
    //   74: return
    // Local variable table:
    //   start	length	slot	name	signature
    //   0	75	0	this	aG
    //   0	75	1	paramBoolean	boolean
    //   24	44	2	i	int
    //   7	2	3	localException1	Exception
    //   45	2	3	localException2	Exception
    // Exception table:
    //   from	to	target	type
    //   48	52	7	java/lang/Exception
    //   10	15	45	java/lang/Exception
    //   57	65	45	java/lang/Exception
  }
  
  public View ʼ()
  {
    break label219;
    int i;
    int j;
    switch (i)
    {
    case 21: 
    default: 
      i = j;
      break;
      label37:
      return null;
      for (;;)
      {
        i = 21;
        break;
        label45:
        break label37;
        label48:
        i = ʼ + 9;
        ʻ = i % 128;
        if (i % 2 == 0) {
          break label222;
        }
      }
    }
    for (;;)
    {
      switch (j)
      {
      default: 
        break;
      case 1: 
        label75:
        View localView = getChildAt(i);
        if (((Integer)localView.getTag()).intValue() == ॱ() - 1) {
          break label177;
        }
        break;
      }
      for (;;)
      {
        break label228;
        i = j;
        try
        {
          i = ʻ;
          i += 109;
          try
          {
            ʼ = i % 128;
            if (i % 2 != 0) {
              break label45;
            }
          }
          catch (Exception localException1)
          {
            throw localException1;
          }
          label177:
          i = ʻ + 33;
          ʼ = i % 128;
          if (i % 2 != 0) {
            return localException1;
          }
          return localException1;
        }
        catch (Exception localException2)
        {
          label209:
          throw localException2;
        }
        j = i + 1;
        break label48;
        i = 0;
      }
      for (;;)
      {
        j = 0;
        break label75;
        label219:
        break label209;
        label222:
        i = 7;
        break;
        label228:
        if (i < getChildCount()) {
          break label242;
        }
      }
      label242:
      j = 1;
    }
  }
  
  public boolean ʽ()
  {
    for (;;)
    {
      int i;
      boolean bool;
      switch (i)
      {
      case 0: 
      default: 
        i = null.length;
        return bool;
        i = 0;
        break;
      case 1: 
        try
        {
          for (;;)
          {
            i = ʻ + 117;
            ʼ = i % 128;
            if (i % 2 != 0) {
              break;
            }
            break label102;
            i = ʻ + 31;
            ʼ = i % 128;
            if (i % 2 == 0)
            {
              break label94;
              return bool;
            }
            label94:
            bool = this.ˊ;
          }
          label102:
          i = 1;
        }
        catch (Exception localException)
        {
          throw localException;
        }
      }
    }
  }
  
  /* Error */
  public View ˋॱ()
  {
    // Byte code:
    //   0: goto +192 -> 192
    //   3: iconst_0
    //   4: istore_1
    //   5: goto +219 -> 224
    //   8: astore 4
    //   10: aload 4
    //   12: athrow
    //   13: aconst_null
    //   14: areturn
    //   15: getstatic 19	o/aG:ʻ	I
    //   18: bipush 55
    //   20: iadd
    //   21: istore_2
    //   22: iload_2
    //   23: sipush 128
    //   26: irem
    //   27: putstatic 17	o/aG:ʼ	I
    //   30: iload_2
    //   31: iconst_2
    //   32: irem
    //   33: ifeq +6 -> 39
    //   36: goto +36 -> 72
    //   39: aload_0
    //   40: iload_1
    //   41: invokevirtual 122	o/aG:getChildAt	(I)Landroid/view/View;
    //   44: astore 4
    //   46: aload 4
    //   48: invokevirtual 128	android/view/View:getTag	()Ljava/lang/Object;
    //   51: checkcast 130	java/lang/Integer
    //   54: invokevirtual 134	java/lang/Integer:intValue	()I
    //   57: aload_0
    //   58: invokevirtual 137	o/aG:ॱ	()I
    //   61: iconst_1
    //   62: iadd
    //   63: if_icmpne +6 -> 69
    //   66: goto +121 -> 187
    //   69: goto +74 -> 143
    //   72: aload_0
    //   73: iload_1
    //   74: invokevirtual 122	o/aG:getChildAt	(I)Landroid/view/View;
    //   77: astore 4
    //   79: aload 4
    //   81: invokevirtual 128	android/view/View:getTag	()Ljava/lang/Object;
    //   84: astore 5
    //   86: aload 5
    //   88: checkcast 130	java/lang/Integer
    //   91: astore 5
    //   93: aload 5
    //   95: invokevirtual 134	java/lang/Integer:intValue	()I
    //   98: istore_2
    //   99: aload_0
    //   100: invokevirtual 137	o/aG:ॱ	()I
    //   103: istore_3
    //   104: iload_2
    //   105: iload_3
    //   106: iconst_0
    //   107: ishl
    //   108: if_icmpne +6 -> 114
    //   111: goto +127 -> 238
    //   114: goto +135 -> 249
    //   117: iload_2
    //   118: tableswitch	default:+22->140, 0:+33->151, 1:+30->148
    //   140: goto +11 -> 151
    //   143: iconst_0
    //   144: istore_2
    //   145: goto -28 -> 117
    //   148: aload 4
    //   150: areturn
    //   151: iload_1
    //   152: iconst_1
    //   153: iadd
    //   154: istore_1
    //   155: goto +69 -> 224
    //   158: iload_2
    //   159: lookupswitch	default:+25->184, 18:+-11->148, 48:+-8->151
    //   184: goto -33 -> 151
    //   187: iconst_1
    //   188: istore_2
    //   189: goto -72 -> 117
    //   192: getstatic 17	o/aG:ʼ	I
    //   195: bipush 15
    //   197: iadd
    //   198: istore_1
    //   199: iload_1
    //   200: sipush 128
    //   203: irem
    //   204: putstatic 19	o/aG:ʻ	I
    //   207: iload_1
    //   208: iconst_2
    //   209: irem
    //   210: ifne +6 -> 216
    //   213: goto +31 -> 244
    //   216: goto -213 -> 3
    //   219: astore 4
    //   221: aload 4
    //   223: athrow
    //   224: iload_1
    //   225: aload_0
    //   226: invokevirtual 140	o/aG:getChildCount	()I
    //   229: if_icmpge +6 -> 235
    //   232: goto -217 -> 15
    //   235: goto -222 -> 13
    //   238: bipush 18
    //   240: istore_2
    //   241: goto -83 -> 158
    //   244: iconst_0
    //   245: istore_1
    //   246: goto -22 -> 224
    //   249: bipush 48
    //   251: istore_2
    //   252: goto -94 -> 158
    // Local variable table:
    //   start	length	slot	name	signature
    //   0	255	0	this	aG
    //   4	242	1	i	int
    //   21	231	2	j	int
    //   103	5	3	k	int
    //   8	3	4	localException1	Exception
    //   44	105	4	localView	View
    //   219	3	4	localException2	Exception
    //   84	10	5	localObject	Object
    // Exception table:
    //   from	to	target	type
    //   72	79	8	java/lang/Exception
    //   79	86	8	java/lang/Exception
    //   86	93	8	java/lang/Exception
    //   93	99	8	java/lang/Exception
    //   99	104	8	java/lang/Exception
    //   93	99	219	java/lang/Exception
  }
  
  public View ॱॱ()
  {
    break label37;
    break label40;
    switch (i)
    {
    case 30: 
    default: 
      break;
      return null;
      label37:
      break;
    }
    label40:
    int i = 0;
    int j = ʻ + 69;
    ʼ = j % 128;
    if (j % 2 == 0) {
      break label221;
    }
    label90:
    label133:
    label139:
    label201:
    label221:
    for (;;)
    {
      if (i >= getChildCount()) {
        break label201;
      }
      for (;;)
      {
        i += 1;
        break;
        try
        {
          localView = getChildAt(i);
          localObject = localView.getTag();
          localObject = (Integer)localObject;
        }
        catch (Exception localException1)
        {
          View localView;
          Object localObject;
          int k;
          throw localException1;
        }
        try
        {
          j = ((Integer)localObject).intValue();
          k = ॱ();
          if (j == k) {
            return localView;
          }
        }
        catch (Exception localException2)
        {
          throw localException2;
        }
      }
      i = 44;
      break;
      i = 30;
      break;
      for (;;)
      {
        switch (j)
        {
        }
        break label90;
        i = ʻ + 61;
        ʼ = i % 128;
        if (i % 2 != 0) {
          break label139;
        }
        break label133;
        break;
        j = 1;
        continue;
        j = 0;
      }
    }
  }
}
