package o;

import android.app.Service;
import android.content.BroadcastReceiver;

public class aj
  extends Service
{
  private static int ʻ;
  private static boolean ˊ = true;
  private static char[] ˋ = { 240, 270, 279, 283, 266, 277, 252, 285, 274, 272, 201, 280, 271, 268, 284, 287, 264, 290 };
  private static boolean ˎ;
  private static int ॱ = 169;
  private static int ॱॱ = 0;
  private if ˏ;
  
  static
  {
    ʻ = 1;
    ˎ = true;
  }
  
  public aj() {}
  
  /* Error */
  private static String ॱ(byte[] paramArrayOfByte, int[] paramArrayOfInt, char[] paramArrayOfChar, int paramInt)
  {
    // Byte code:
    //   0: goto +580 -> 580
    //   3: aload_0
    //   4: iload 4
    //   6: aload 9
    //   8: aload_1
    //   9: iload 5
    //   11: iconst_1
    //   12: iadd
    //   13: iload 4
    //   15: idiv
    //   16: iaload
    //   17: iload_3
    //   18: imul
    //   19: caload
    //   20: iload 6
    //   22: idiv
    //   23: i2c
    //   24: castore
    //   25: iload 4
    //   27: bipush 106
    //   29: iadd
    //   30: istore 4
    //   32: goto +156 -> 188
    //   35: iload 5
    //   37: tableswitch	default:+23->60, 0:+534->571, 1:+292->329
    //   60: goto +269 -> 329
    //   63: iload 4
    //   65: iload 7
    //   67: if_icmpge +6 -> 73
    //   70: goto +131 -> 201
    //   73: goto +159 -> 232
    //   76: iload 4
    //   78: lookupswitch	default:+26->104, 83:+398->476, 87:+139->217
    //   104: goto +113 -> 217
    //   107: goto +356 -> 463
    //   110: bipush 83
    //   112: istore 5
    //   114: goto +267 -> 381
    //   117: bipush 87
    //   119: istore 4
    //   121: goto -45 -> 76
    //   124: getstatic 22	o/aj:ॱॱ	I
    //   127: istore 5
    //   129: iload 5
    //   131: bipush 99
    //   133: iadd
    //   134: istore 5
    //   136: iload 5
    //   138: sipush 128
    //   141: irem
    //   142: putstatic 24	o/aj:ʻ	I
    //   145: iload 5
    //   147: iconst_2
    //   148: irem
    //   149: ifne +6 -> 155
    //   152: goto +259 -> 411
    //   155: goto -48 -> 107
    //   158: getstatic 22	o/aj:ॱॱ	I
    //   161: bipush 59
    //   163: iadd
    //   164: istore 7
    //   166: iload 7
    //   168: sipush 128
    //   171: irem
    //   172: putstatic 24	o/aj:ʻ	I
    //   175: iload 7
    //   177: iconst_2
    //   178: irem
    //   179: ifne +6 -> 185
    //   182: goto -179 -> 3
    //   185: goto +306 -> 491
    //   188: iload 4
    //   190: iload 5
    //   192: if_icmpge +6 -> 198
    //   195: goto -37 -> 158
    //   198: goto +174 -> 372
    //   201: iconst_1
    //   202: istore 5
    //   204: goto -169 -> 35
    //   207: bipush 83
    //   209: istore 4
    //   211: goto -135 -> 76
    //   214: goto +308 -> 522
    //   217: aload_1
    //   218: arraylength
    //   219: istore 5
    //   221: iload 5
    //   223: newarray char
    //   225: astore_0
    //   226: iconst_0
    //   227: istore 4
    //   229: goto +131 -> 360
    //   232: iconst_0
    //   233: istore 5
    //   235: goto -200 -> 35
    //   238: getstatic 48	o/aj:ˋ	[C
    //   241: astore 9
    //   243: getstatic 50	o/aj:ॱ	I
    //   246: istore 6
    //   248: getstatic 26	o/aj:ˎ	Z
    //   251: istore 8
    //   253: iload 8
    //   255: ifeq +6 -> 261
    //   258: goto +6 -> 264
    //   261: goto +183 -> 444
    //   264: getstatic 22	o/aj:ॱॱ	I
    //   267: bipush 77
    //   269: iadd
    //   270: istore 4
    //   272: iload 4
    //   274: sipush 128
    //   277: irem
    //   278: putstatic 24	o/aj:ʻ	I
    //   281: iload 4
    //   283: iconst_2
    //   284: irem
    //   285: ifne +6 -> 291
    //   288: goto -74 -> 214
    //   291: goto +231 -> 522
    //   294: astore_0
    //   295: aload_0
    //   296: athrow
    //   297: aload_0
    //   298: iload 4
    //   300: aload 9
    //   302: aload_2
    //   303: iload 7
    //   305: iconst_1
    //   306: iadd
    //   307: iload 4
    //   309: isub
    //   310: caload
    //   311: iload_3
    //   312: isub
    //   313: caload
    //   314: iload 6
    //   316: ishl
    //   317: i2c
    //   318: castore
    //   319: iload 4
    //   321: bipush 62
    //   323: iadd
    //   324: istore 4
    //   326: goto +137 -> 463
    //   329: aload_1
    //   330: iload 4
    //   332: aload 9
    //   334: aload_0
    //   335: iload 7
    //   337: iconst_1
    //   338: isub
    //   339: iload 4
    //   341: isub
    //   342: baload
    //   343: iload_3
    //   344: iadd
    //   345: caload
    //   346: iload 6
    //   348: isub
    //   349: i2c
    //   350: castore
    //   351: iload 4
    //   353: iconst_1
    //   354: iadd
    //   355: istore 4
    //   357: goto -294 -> 63
    //   360: goto -172 -> 188
    //   363: new 59	java/lang/String
    //   366: dup
    //   367: aload_0
    //   368: invokespecial 62	java/lang/String:<init>	([C)V
    //   371: areturn
    //   372: new 59	java/lang/String
    //   375: dup
    //   376: aload_0
    //   377: invokespecial 62	java/lang/String:<init>	([C)V
    //   380: areturn
    //   381: iload 5
    //   383: lookupswitch	default:+25->408, 59:+154->537, 83:+-86->297
    //   408: goto -111 -> 297
    //   411: goto +52 -> 463
    //   414: getstatic 24	o/aj:ʻ	I
    //   417: bipush 119
    //   419: iadd
    //   420: istore 5
    //   422: iload 5
    //   424: sipush 128
    //   427: irem
    //   428: putstatic 22	o/aj:ॱॱ	I
    //   431: iload 5
    //   433: iconst_2
    //   434: irem
    //   435: ifeq +6 -> 441
    //   438: goto -328 -> 110
    //   441: goto +15 -> 456
    //   444: getstatic 28	o/aj:ˊ	Z
    //   447: ifeq +6 -> 453
    //   450: goto -243 -> 207
    //   453: goto -336 -> 117
    //   456: bipush 59
    //   458: istore 5
    //   460: goto -79 -> 381
    //   463: iload 4
    //   465: iload 7
    //   467: if_icmpge +6 -> 473
    //   470: goto -56 -> 414
    //   473: goto -110 -> 363
    //   476: aload_2
    //   477: arraylength
    //   478: istore 7
    //   480: iload 7
    //   482: newarray char
    //   484: astore_0
    //   485: iconst_0
    //   486: istore 4
    //   488: goto -364 -> 124
    //   491: aload_0
    //   492: iload 4
    //   494: aload 9
    //   496: aload_1
    //   497: iload 5
    //   499: iconst_1
    //   500: isub
    //   501: iload 4
    //   503: isub
    //   504: iaload
    //   505: iload_3
    //   506: isub
    //   507: caload
    //   508: iload 6
    //   510: isub
    //   511: i2c
    //   512: castore
    //   513: iload 4
    //   515: iconst_1
    //   516: iadd
    //   517: istore 4
    //   519: goto -331 -> 188
    //   522: aload_0
    //   523: arraylength
    //   524: istore 7
    //   526: iload 7
    //   528: newarray char
    //   530: astore_1
    //   531: iconst_0
    //   532: istore 4
    //   534: goto -471 -> 63
    //   537: aload_0
    //   538: iload 4
    //   540: aload 9
    //   542: aload_2
    //   543: iload 7
    //   545: iconst_1
    //   546: isub
    //   547: iload 4
    //   549: isub
    //   550: caload
    //   551: iload_3
    //   552: isub
    //   553: caload
    //   554: iload 6
    //   556: isub
    //   557: i2c
    //   558: castore
    //   559: iload 4
    //   561: iconst_1
    //   562: iadd
    //   563: istore 4
    //   565: goto -102 -> 463
    //   568: astore_0
    //   569: aload_0
    //   570: athrow
    //   571: new 59	java/lang/String
    //   574: dup
    //   575: aload_1
    //   576: invokespecial 62	java/lang/String:<init>	([C)V
    //   579: areturn
    //   580: goto -342 -> 238
    // Local variable table:
    //   start	length	slot	name	signature
    //   0	583	0	paramArrayOfByte	byte[]
    //   0	583	1	paramArrayOfInt	int[]
    //   0	583	2	paramArrayOfChar	char[]
    //   0	583	3	paramInt	int
    //   4	560	4	i	int
    //   9	492	5	j	int
    //   20	537	6	k	int
    //   65	482	7	m	int
    //   251	3	8	bool	boolean
    //   6	535	9	arrayOfChar	char[]
    // Exception table:
    //   from	to	target	type
    //   124	129	294	java/lang/Exception
    //   243	248	294	java/lang/Exception
    //   136	145	568	java/lang/Exception
    //   238	243	568	java/lang/Exception
    //   248	253	568	java/lang/Exception
  }
  
  /* Error */
  public android.content.res.Resources getResources()
  {
    // Byte code:
    //   0: goto +91 -> 91
    //   3: iload_1
    //   4: lookupswitch	default:+28->32, 42:+90->94, 67:+28->32
    //   32: aload_0
    //   33: invokespecial 66	android/app/Service:getResources	()Landroid/content/res/Resources;
    //   36: astore_2
    //   37: aload_2
    //   38: invokestatic 71	o/oH:ˊ	(Landroid/content/res/Resources;)Landroid/content/res/Resources;
    //   41: astore_2
    //   42: aload_2
    //   43: areturn
    //   44: bipush 67
    //   46: istore_1
    //   47: goto -44 -> 3
    //   50: getstatic 24	o/aj:ʻ	I
    //   53: istore_1
    //   54: iload_1
    //   55: bipush 63
    //   57: iadd
    //   58: istore_1
    //   59: iload_1
    //   60: sipush 128
    //   63: irem
    //   64: putstatic 22	o/aj:ॱॱ	I
    //   67: iload_1
    //   68: iconst_2
    //   69: irem
    //   70: ifeq +6 -> 76
    //   73: goto +9 -> 82
    //   76: goto -32 -> 44
    //   79: astore_2
    //   80: aload_2
    //   81: athrow
    //   82: bipush 42
    //   84: istore_1
    //   85: goto -82 -> 3
    //   88: astore_2
    //   89: aload_2
    //   90: athrow
    //   91: goto -41 -> 50
    //   94: aload_0
    //   95: invokespecial 66	android/app/Service:getResources	()Landroid/content/res/Resources;
    //   98: invokestatic 71	o/oH:ˊ	(Landroid/content/res/Resources;)Landroid/content/res/Resources;
    //   101: pop
    //   102: new 73	java/lang/NullPointerException
    //   105: dup
    //   106: invokespecial 74	java/lang/NullPointerException:<init>	()V
    //   109: athrow
    // Local variable table:
    //   start	length	slot	name	signature
    //   0	110	0	this	aj
    //   3	82	1	i	int
    //   36	7	2	localResources	android.content.res.Resources
    //   79	2	2	localException1	Exception
    //   88	2	2	localException2	Exception
    // Exception table:
    //   from	to	target	type
    //   37	42	79	java/lang/Exception
    //   50	54	88	java/lang/Exception
    //   59	67	88	java/lang/Exception
  }
  
  /* Error */
  public android.os.IBinder onBind(android.content.Intent paramIntent)
  {
    // Byte code:
    //   0: goto +67 -> 67
    //   3: iconst_1
    //   4: istore_2
    //   5: goto +65 -> 70
    //   8: getstatic 24	o/aj:ʻ	I
    //   11: istore_2
    //   12: iload_2
    //   13: bipush 23
    //   15: iadd
    //   16: istore_2
    //   17: iload_2
    //   18: sipush 128
    //   21: irem
    //   22: putstatic 22	o/aj:ॱॱ	I
    //   25: iload_2
    //   26: iconst_2
    //   27: irem
    //   28: ifeq +6 -> 34
    //   31: goto +102 -> 133
    //   34: goto +93 -> 127
    //   37: getstatic 24	o/aj:ʻ	I
    //   40: bipush 123
    //   42: iadd
    //   43: istore_2
    //   44: iload_2
    //   45: sipush 128
    //   48: irem
    //   49: putstatic 22	o/aj:ॱॱ	I
    //   52: iload_2
    //   53: iconst_2
    //   54: irem
    //   55: ifeq +6 -> 61
    //   58: goto +87 -> 145
    //   61: goto -58 -> 3
    //   64: astore_1
    //   65: aload_1
    //   66: athrow
    //   67: goto -59 -> 8
    //   70: iload_2
    //   71: tableswitch	default:+21->92, 0:+87->158, 1:+94->165
    //   92: goto +73 -> 165
    //   95: iload_2
    //   96: lookupswitch	default:+28->124, 12:+43->139, 99:+54->150
    //   124: goto +26 -> 150
    //   127: bipush 12
    //   129: istore_2
    //   130: goto -35 -> 95
    //   133: bipush 99
    //   135: istore_2
    //   136: goto -41 -> 95
    //   139: goto -102 -> 37
    //   142: astore_1
    //   143: aload_1
    //   144: athrow
    //   145: iconst_0
    //   146: istore_2
    //   147: goto -77 -> 70
    //   150: new 73	java/lang/NullPointerException
    //   153: dup
    //   154: invokespecial 74	java/lang/NullPointerException:<init>	()V
    //   157: athrow
    //   158: bipush 86
    //   160: iconst_0
    //   161: idiv
    //   162: istore_2
    //   163: aconst_null
    //   164: areturn
    //   165: aconst_null
    //   166: areturn
    // Local variable table:
    //   start	length	slot	name	signature
    //   0	167	0	this	aj
    //   0	167	1	paramIntent	android.content.Intent
    //   4	159	2	i	int
    // Exception table:
    //   from	to	target	type
    //   8	12	64	java/lang/Exception
    //   17	25	142	java/lang/Exception
  }
  
  public void onCreate()
  {
    super.onCreate();
    this.ˏ = new if();
    int i = ʻ + 105;
    ॱॱ = i % 128;
    if (i % 2 != 0) {}
  }
  
  public void onDestroy()
  {
    break label52;
    return;
    int i;
    for (;;)
    {
      i = 74;
      break;
      i = ॱॱ + 89;
      ʻ = i % 128;
      if (i % 2 == 0) {
        break label121;
      }
    }
    for (;;)
    {
      unregisterReceiver(this.ˏ);
      super.onDestroy();
      break;
      label52:
      do
      {
        break;
        i = 97 / 0;
        return;
        i = ॱॱ + 111;
        ʻ = i % 128;
      } while (i % 2 == 0);
    }
    for (;;)
    {
      switch (i)
      {
      }
      return;
      label121:
      i = 0;
    }
  }
  
  /* Error */
  public int onStartCommand(android.content.Intent paramIntent, int paramInt1, int paramInt2)
  {
    // Byte code:
    //   0: goto +586 -> 586
    //   3: bipush 7
    //   5: newarray byte
    //   7: dup
    //   8: iconst_0
    //   9: ldc 94
    //   11: bastore
    //   12: dup
    //   13: iconst_1
    //   14: ldc 95
    //   16: bastore
    //   17: dup
    //   18: iconst_2
    //   19: ldc 96
    //   21: bastore
    //   22: dup
    //   23: iconst_3
    //   24: ldc 97
    //   26: bastore
    //   27: dup
    //   28: iconst_4
    //   29: ldc 98
    //   31: bastore
    //   32: dup
    //   33: iconst_5
    //   34: ldc 97
    //   36: bastore
    //   37: dup
    //   38: bipush 6
    //   40: ldc 99
    //   42: bastore
    //   43: aconst_null
    //   44: aconst_null
    //   45: bipush 127
    //   47: invokestatic 101	o/aj:ॱ	([B[I[CI)Ljava/lang/String;
    //   50: invokevirtual 105	java/lang/String:intern	()Ljava/lang/String;
    //   53: astore 4
    //   55: bipush 29
    //   57: newarray byte
    //   59: dup
    //   60: iconst_0
    //   61: ldc 97
    //   63: bastore
    //   64: dup
    //   65: iconst_1
    //   66: ldc 106
    //   68: bastore
    //   69: dup
    //   70: iconst_2
    //   71: ldc 107
    //   73: bastore
    //   74: dup
    //   75: iconst_3
    //   76: ldc 108
    //   78: bastore
    //   79: dup
    //   80: iconst_4
    //   81: ldc 96
    //   83: bastore
    //   84: dup
    //   85: iconst_5
    //   86: ldc 97
    //   88: bastore
    //   89: dup
    //   90: bipush 6
    //   92: ldc 109
    //   94: bastore
    //   95: dup
    //   96: bipush 7
    //   98: ldc 110
    //   100: bastore
    //   101: dup
    //   102: bipush 8
    //   104: ldc 98
    //   106: bastore
    //   107: dup
    //   108: bipush 9
    //   110: ldc 111
    //   112: bastore
    //   113: dup
    //   114: bipush 10
    //   116: ldc 107
    //   118: bastore
    //   119: dup
    //   120: bipush 11
    //   122: ldc 112
    //   124: bastore
    //   125: dup
    //   126: bipush 12
    //   128: ldc 95
    //   130: bastore
    //   131: dup
    //   132: bipush 13
    //   134: ldc 106
    //   136: bastore
    //   137: dup
    //   138: bipush 14
    //   140: ldc 107
    //   142: bastore
    //   143: dup
    //   144: bipush 15
    //   146: ldc 113
    //   148: bastore
    //   149: dup
    //   150: bipush 16
    //   152: ldc 107
    //   154: bastore
    //   155: dup
    //   156: bipush 17
    //   158: ldc 112
    //   160: bastore
    //   161: dup
    //   162: bipush 18
    //   164: ldc 111
    //   166: bastore
    //   167: dup
    //   168: bipush 19
    //   170: ldc 98
    //   172: bastore
    //   173: dup
    //   174: bipush 20
    //   176: ldc 110
    //   178: bastore
    //   179: dup
    //   180: bipush 21
    //   182: ldc 114
    //   184: bastore
    //   185: dup
    //   186: bipush 22
    //   188: ldc 98
    //   190: bastore
    //   191: dup
    //   192: bipush 23
    //   194: ldc 107
    //   196: bastore
    //   197: dup
    //   198: bipush 24
    //   200: ldc 112
    //   202: bastore
    //   203: dup
    //   204: bipush 25
    //   206: ldc 96
    //   208: bastore
    //   209: dup
    //   210: bipush 26
    //   212: ldc 95
    //   214: bastore
    //   215: dup
    //   216: bipush 27
    //   218: ldc 112
    //   220: bastore
    //   221: dup
    //   222: bipush 28
    //   224: ldc 115
    //   226: bastore
    //   227: aconst_null
    //   228: aconst_null
    //   229: bipush 127
    //   231: invokestatic 101	o/aj:ॱ	([B[I[CI)Ljava/lang/String;
    //   234: invokevirtual 105	java/lang/String:intern	()Ljava/lang/String;
    //   237: astore 5
    //   239: goto +20 -> 259
    //   242: astore_1
    //   243: aload_1
    //   244: invokevirtual 121	java/lang/Throwable:getCause	()Ljava/lang/Throwable;
    //   247: astore 4
    //   249: aload 4
    //   251: ifnull +6 -> 257
    //   254: aload 4
    //   256: athrow
    //   257: aload_1
    //   258: athrow
    //   259: aload_0
    //   260: invokevirtual 126	android/content/Context:getPackageName	()Ljava/lang/String;
    //   263: invokevirtual 130	java/lang/String:length	()I
    //   266: bipush 7
    //   268: isub
    //   269: aload_0
    //   270: invokevirtual 126	android/content/Context:getPackageName	()Ljava/lang/String;
    //   273: invokevirtual 130	java/lang/String:length	()I
    //   276: bipush 31
    //   278: iadd
    //   279: aload_0
    //   280: invokevirtual 134	android/content/Context:getApplicationInfo	()Landroid/content/pm/ApplicationInfo;
    //   283: getfield 139	android/content/pm/ApplicationInfo:targetSdkVersion	I
    //   286: ldc -116
    //   288: iadd
    //   289: i2c
    //   290: invokestatic 145	o/O:ˋ	(IIC)Ljava/lang/Object;
    //   293: checkcast 147	java/lang/Class
    //   296: ldc -108
    //   298: iconst_2
    //   299: anewarray 147	java/lang/Class
    //   302: dup
    //   303: iconst_0
    //   304: ldc 59
    //   306: aastore
    //   307: dup
    //   308: iconst_1
    //   309: ldc 59
    //   311: aastore
    //   312: invokevirtual 152	java/lang/Class:getMethod	(Ljava/lang/String;[Ljava/lang/Class;)Ljava/lang/reflect/Method;
    //   315: aconst_null
    //   316: iconst_2
    //   317: anewarray 154	java/lang/Object
    //   320: dup
    //   321: iconst_0
    //   322: aload 4
    //   324: aastore
    //   325: dup
    //   326: iconst_1
    //   327: aload 5
    //   329: aastore
    //   330: invokevirtual 160	java/lang/reflect/Method:invoke	(Ljava/lang/Object;[Ljava/lang/Object;)Ljava/lang/Object;
    //   333: pop
    //   334: new 162	android/content/IntentFilter
    //   337: dup
    //   338: invokespecial 163	android/content/IntentFilter:<init>	()V
    //   341: astore 4
    //   343: aload 4
    //   345: bipush 30
    //   347: newarray byte
    //   349: dup
    //   350: iconst_0
    //   351: ldc 96
    //   353: bastore
    //   354: dup
    //   355: iconst_1
    //   356: ldc 97
    //   358: bastore
    //   359: dup
    //   360: iconst_2
    //   361: ldc 108
    //   363: bastore
    //   364: dup
    //   365: iconst_3
    //   366: ldc 107
    //   368: bastore
    //   369: dup
    //   370: iconst_4
    //   371: ldc 97
    //   373: bastore
    //   374: dup
    //   375: iconst_5
    //   376: ldc 106
    //   378: bastore
    //   379: dup
    //   380: bipush 6
    //   382: ldc 97
    //   384: bastore
    //   385: dup
    //   386: bipush 7
    //   388: ldc 96
    //   390: bastore
    //   391: dup
    //   392: bipush 8
    //   394: ldc -92
    //   396: bastore
    //   397: dup
    //   398: bipush 9
    //   400: ldc 97
    //   402: bastore
    //   403: dup
    //   404: bipush 10
    //   406: ldc 106
    //   408: bastore
    //   409: dup
    //   410: bipush 11
    //   412: ldc 107
    //   414: bastore
    //   415: dup
    //   416: bipush 12
    //   418: ldc 108
    //   420: bastore
    //   421: dup
    //   422: bipush 13
    //   424: ldc 96
    //   426: bastore
    //   427: dup
    //   428: bipush 14
    //   430: ldc 97
    //   432: bastore
    //   433: dup
    //   434: bipush 15
    //   436: ldc 109
    //   438: bastore
    //   439: dup
    //   440: bipush 16
    //   442: ldc -92
    //   444: bastore
    //   445: dup
    //   446: bipush 17
    //   448: ldc -91
    //   450: bastore
    //   451: dup
    //   452: bipush 18
    //   454: ldc 113
    //   456: bastore
    //   457: dup
    //   458: bipush 19
    //   460: ldc 107
    //   462: bastore
    //   463: dup
    //   464: bipush 20
    //   466: ldc 112
    //   468: bastore
    //   469: dup
    //   470: bipush 21
    //   472: ldc 111
    //   474: bastore
    //   475: dup
    //   476: bipush 22
    //   478: ldc 98
    //   480: bastore
    //   481: dup
    //   482: bipush 23
    //   484: ldc -92
    //   486: bastore
    //   487: dup
    //   488: bipush 24
    //   490: ldc 98
    //   492: bastore
    //   493: dup
    //   494: bipush 25
    //   496: ldc 111
    //   498: bastore
    //   499: dup
    //   500: bipush 26
    //   502: ldc 107
    //   504: bastore
    //   505: dup
    //   506: bipush 27
    //   508: ldc 112
    //   510: bastore
    //   511: dup
    //   512: bipush 28
    //   514: ldc 106
    //   516: bastore
    //   517: dup
    //   518: bipush 29
    //   520: ldc 95
    //   522: bastore
    //   523: aconst_null
    //   524: aconst_null
    //   525: bipush 127
    //   527: invokestatic 101	o/aj:ॱ	([B[I[CI)Ljava/lang/String;
    //   530: invokevirtual 105	java/lang/String:intern	()Ljava/lang/String;
    //   533: invokevirtual 169	android/content/IntentFilter:addAction	(Ljava/lang/String;)V
    //   536: aload_0
    //   537: aload_0
    //   538: getfield 84	o/aj:ˏ	Lo/aj$if;
    //   541: aload 4
    //   543: invokevirtual 173	o/aj:registerReceiver	(Landroid/content/BroadcastReceiver;Landroid/content/IntentFilter;)Landroid/content/Intent;
    //   546: pop
    //   547: aload_0
    //   548: aload_1
    //   549: iload_2
    //   550: iload_3
    //   551: invokespecial 175	android/app/Service:onStartCommand	(Landroid/content/Intent;II)I
    //   554: istore_2
    //   555: goto +3 -> 558
    //   558: getstatic 24	o/aj:ʻ	I
    //   561: bipush 21
    //   563: iadd
    //   564: istore_3
    //   565: iload_3
    //   566: sipush 128
    //   569: irem
    //   570: putstatic 22	o/aj:ॱॱ	I
    //   573: iload_3
    //   574: iconst_2
    //   575: irem
    //   576: ifeq +5 -> 581
    //   579: iload_2
    //   580: ireturn
    //   581: iload_2
    //   582: ireturn
    //   583: astore_1
    //   584: aload_1
    //   585: athrow
    //   586: goto -583 -> 3
    // Local variable table:
    //   start	length	slot	name	signature
    //   0	589	0	this	aj
    //   0	589	1	paramIntent	android.content.Intent
    //   0	589	2	paramInt1	int
    //   0	589	3	paramInt2	int
    //   53	489	4	localObject	Object
    //   237	91	5	str	String
    // Exception table:
    //   from	to	target	type
    //   259	334	242	finally
    //   558	565	583	java/lang/Exception
    //   565	573	583	java/lang/Exception
  }
  
  public class if
    extends BroadcastReceiver
  {
    private static int ʻ;
    private static short[] ʼ;
    private static int ˊ = -1068977850;
    private static byte[] ˋ;
    private static int ˎ = 1032116156;
    private static int ॱ;
    private static int ᐝ = 0;
    
    static
    {
      ʻ = 1;
      ॱ = 119;
      ˋ = new byte[] { -96, 8, -15, 11, 10, -15, -1, 6, -11, 19, -2, -6, 3, -3, -11, 5, 1, 15, -2, -17, -2, -4, 19, -112, 11, -17, 13, -9, 9, 30, -92, -26, -51, 8, -15, 11, 73, -78, -1, 6, -11, 19, -2, -6, 3, -3, -11, 5, 1, 78, -71, -7, 5, -14, 8, 7, 21, -107, -1, 6, -11, 19, -2, -6, 3, -3, -11, 5, 1 };
    }
    
    public if() {}
    
    /* Error */
    private static String ॱ(short paramShort, int paramInt1, byte paramByte, int paramInt2, int paramInt3)
    {
      // Byte code:
      //   0: goto +232 -> 232
      //   3: getstatic 82	o/aj$if:ʼ	[S
      //   6: getstatic 70	o/aj$if:ˎ	I
      //   9: iload_1
      //   10: iadd
      //   11: saload
      //   12: getstatic 27	o/aj$if:ॱ	I
      //   15: iadd
      //   16: i2s
      //   17: istore 4
      //   19: goto +529 -> 548
      //   22: goto +153 -> 175
      //   25: iload 4
      //   27: istore 7
      //   29: goto +262 -> 291
      //   32: getstatic 23	o/aj$if:ᐝ	I
      //   35: bipush 109
      //   37: iadd
      //   38: istore 4
      //   40: iload 4
      //   42: sipush 128
      //   45: irem
      //   46: putstatic 25	o/aj$if:ʻ	I
      //   49: iload 4
      //   51: iconst_2
      //   52: irem
      //   53: ifne +6 -> 59
      //   56: goto +483 -> 539
      //   59: goto +154 -> 213
      //   62: astore 9
      //   64: aload 9
      //   66: athrow
      //   67: bipush 10
      //   69: istore 4
      //   71: goto +305 -> 376
      //   74: bipush 95
      //   76: istore 6
      //   78: goto +361 -> 439
      //   81: astore 9
      //   83: aload 9
      //   85: athrow
      //   86: getstatic 23	o/aj$if:ᐝ	I
      //   89: bipush 33
      //   91: iadd
      //   92: istore 7
      //   94: iload 7
      //   96: sipush 128
      //   99: irem
      //   100: putstatic 25	o/aj$if:ʻ	I
      //   103: iload 7
      //   105: iconst_2
      //   106: irem
      //   107: ifne +6 -> 113
      //   110: goto +233 -> 343
      //   113: goto -91 -> 22
      //   116: getstatic 25	o/aj$if:ʻ	I
      //   119: bipush 49
      //   121: iadd
      //   122: istore 6
      //   124: iload 6
      //   126: sipush 128
      //   129: irem
      //   130: putstatic 23	o/aj$if:ᐝ	I
      //   133: iload 6
      //   135: iconst_2
      //   136: irem
      //   137: ifeq +6 -> 143
      //   140: goto +200 -> 340
      //   143: goto +271 -> 414
      //   146: iload 4
      //   148: tableswitch	default:+24->172, 0:+487->635, 1:+171->319
      //   172: goto +463 -> 635
      //   175: iload_1
      //   176: iload 4
      //   178: iadd
      //   179: iconst_2
      //   180: isub
      //   181: iload 8
      //   183: iadd
      //   184: iload 6
      //   186: iadd
      //   187: istore_1
      //   188: getstatic 67	o/aj$if:ˊ	I
      //   191: iload_3
      //   192: iadd
      //   193: i2c
      //   194: istore 5
      //   196: aload 9
      //   198: iload 5
      //   200: invokevirtual 88	java/lang/StringBuilder:append	(C)Ljava/lang/StringBuilder;
      //   203: pop
      //   204: iconst_1
      //   205: istore_3
      //   206: iload 5
      //   208: istore 7
      //   210: goto +115 -> 325
      //   213: getstatic 64	o/aj$if:ˋ	[B
      //   216: getstatic 70	o/aj$if:ˎ	I
      //   219: iload_1
      //   220: iadd
      //   221: baload
      //   222: getstatic 27	o/aj$if:ॱ	I
      //   225: iadd
      //   226: i2b
      //   227: istore 4
      //   229: goto -113 -> 116
      //   232: new 84	java/lang/StringBuilder
      //   235: dup
      //   236: invokespecial 89	java/lang/StringBuilder:<init>	()V
      //   239: astore 9
      //   241: getstatic 27	o/aj$if:ॱ	I
      //   244: istore 6
      //   246: iload 6
      //   248: iload 4
      //   250: iadd
      //   251: istore 4
      //   253: iload 4
      //   255: istore 6
      //   257: iload 4
      //   259: iconst_m1
      //   260: if_icmpne +6 -> 266
      //   263: goto +296 -> 559
      //   266: iconst_1
      //   267: istore 4
      //   269: goto -123 -> 146
      //   272: aload 9
      //   274: iload 5
      //   276: invokevirtual 88	java/lang/StringBuilder:append	(C)Ljava/lang/StringBuilder;
      //   279: pop
      //   280: iload_3
      //   281: iconst_1
      //   282: iadd
      //   283: istore_3
      //   284: iload 5
      //   286: istore 7
      //   288: goto +37 -> 325
      //   291: iload 7
      //   293: ifeq +6 -> 299
      //   296: goto +50 -> 346
      //   299: iload 6
      //   301: istore 4
      //   303: goto +245 -> 548
      //   306: iconst_1
      //   307: istore 7
      //   309: goto +422 -> 731
      //   312: bipush 92
      //   314: istore 6
      //   316: goto +123 -> 439
      //   319: iconst_0
      //   320: istore 7
      //   322: goto -31 -> 291
      //   325: iload_3
      //   326: iload 4
      //   328: if_icmpge +6 -> 334
      //   331: goto +363 -> 694
      //   334: aload 9
      //   336: invokevirtual 93	java/lang/StringBuilder:toString	()Ljava/lang/String;
      //   339: areturn
      //   340: goto +74 -> 414
      //   343: goto -168 -> 175
      //   346: getstatic 25	o/aj$if:ʻ	I
      //   349: bipush 47
      //   351: iadd
      //   352: istore 4
      //   354: iload 4
      //   356: sipush 128
      //   359: irem
      //   360: putstatic 23	o/aj$if:ᐝ	I
      //   363: iload 4
      //   365: iconst_2
      //   366: irem
      //   367: ifeq +6 -> 373
      //   370: goto +195 -> 565
      //   373: goto +386 -> 759
      //   376: iload 4
      //   378: lookupswitch	default:+26->404, 10:+221->599, 57:+39->417
      //   404: goto +195 -> 599
      //   407: iload 7
      //   409: istore 6
      //   411: goto -236 -> 175
      //   414: goto +134 -> 548
      //   417: iconst_0
      //   418: istore 4
      //   420: goto +51 -> 471
      //   423: getstatic 70	o/aj$if:ˎ	I
      //   426: istore 8
      //   428: iload 7
      //   430: ifeq +6 -> 436
      //   433: goto +243 -> 676
      //   436: goto +338 -> 774
      //   439: iload 6
      //   441: lookupswitch	default:+27->468, 92:+283->724, 95:+-34->407
      //   468: goto -61 -> 407
      //   471: getstatic 23	o/aj$if:ᐝ	I
      //   474: bipush 33
      //   476: iadd
      //   477: istore 7
      //   479: iload 7
      //   481: sipush 128
      //   484: irem
      //   485: putstatic 25	o/aj$if:ʻ	I
      //   488: iload 7
      //   490: iconst_2
      //   491: irem
      //   492: ifne +6 -> 498
      //   495: goto -189 -> 306
      //   498: goto +44 -> 542
      //   501: bipush 57
      //   503: istore 4
      //   505: goto -129 -> 376
      //   508: getstatic 82	o/aj$if:ʼ	[S
      //   511: astore 10
      //   513: iload_1
      //   514: iconst_1
      //   515: isub
      //   516: istore 6
      //   518: aload 10
      //   520: iload_1
      //   521: saload
      //   522: iload_0
      //   523: iadd
      //   524: i2s
      //   525: iload_2
      //   526: ixor
      //   527: iload 7
      //   529: iadd
      //   530: i2c
      //   531: istore 5
      //   533: iload 6
      //   535: istore_1
      //   536: goto -264 -> 272
      //   539: goto -326 -> 213
      //   542: iconst_0
      //   543: istore 7
      //   545: goto +186 -> 731
      //   548: iload 4
      //   550: ifle +6 -> 556
      //   553: goto -130 -> 423
      //   556: goto -222 -> 334
      //   559: iconst_0
      //   560: istore 4
      //   562: goto -416 -> 146
      //   565: goto +194 -> 759
      //   568: getstatic 64	o/aj$if:ˋ	[B
      //   571: astore 10
      //   573: iload_1
      //   574: iconst_1
      //   575: isub
      //   576: istore 6
      //   578: aload 10
      //   580: iload_1
      //   581: baload
      //   582: iload_0
      //   583: iadd
      //   584: i2b
      //   585: iload_2
      //   586: ixor
      //   587: iload 7
      //   589: iadd
      //   590: i2c
      //   591: istore 5
      //   593: iload 6
      //   595: istore_1
      //   596: goto -324 -> 272
      //   599: iconst_1
      //   600: istore 4
      //   602: goto -131 -> 471
      //   605: getstatic 23	o/aj$if:ᐝ	I
      //   608: bipush 69
      //   610: iadd
      //   611: istore 6
      //   613: iload 6
      //   615: sipush 128
      //   618: irem
      //   619: putstatic 25	o/aj$if:ʻ	I
      //   622: iload 6
      //   624: iconst_2
      //   625: irem
      //   626: ifne +6 -> 632
      //   629: goto -317 -> 312
      //   632: goto -558 -> 74
      //   635: getstatic 25	o/aj$if:ʻ	I
      //   638: istore 4
      //   640: iload 4
      //   642: bipush 121
      //   644: iadd
      //   645: istore 4
      //   647: iload 4
      //   649: sipush 128
      //   652: irem
      //   653: putstatic 23	o/aj$if:ᐝ	I
      //   656: iload 4
      //   658: iconst_2
      //   659: irem
      //   660: ifeq +6 -> 666
      //   663: goto -162 -> 501
      //   666: goto -599 -> 67
      //   669: iload 4
      //   671: istore 7
      //   673: goto -382 -> 291
      //   676: iconst_1
      //   677: istore 6
      //   679: goto -593 -> 86
      //   682: getstatic 64	o/aj$if:ˋ	[B
      //   685: ifnull +6 -> 691
      //   688: goto -120 -> 568
      //   691: goto -183 -> 508
      //   694: getstatic 23	o/aj$if:ᐝ	I
      //   697: bipush 119
      //   699: iadd
      //   700: istore 6
      //   702: iload 6
      //   704: sipush 128
      //   707: irem
      //   708: putstatic 25	o/aj$if:ʻ	I
      //   711: iload 6
      //   713: iconst_2
      //   714: irem
      //   715: ifne +6 -> 721
      //   718: goto +53 -> 771
      //   721: goto -39 -> 682
      //   724: iload 7
      //   726: istore 6
      //   728: goto -553 -> 175
      //   731: iload 7
      //   733: tableswitch	default:+23->756, 0:+-708->25, 1:+-64->669
      //   756: goto -87 -> 669
      //   759: getstatic 64	o/aj$if:ˋ	[B
      //   762: ifnull +6 -> 768
      //   765: goto -733 -> 32
      //   768: goto -765 -> 3
      //   771: goto -89 -> 682
      //   774: iconst_0
      //   775: istore 7
      //   777: goto -172 -> 605
      // Local variable table:
      //   start	length	slot	name	signature
      //   0	780	0	paramShort	short
      //   0	780	1	paramInt1	int
      //   0	780	2	paramByte	byte
      //   0	780	3	paramInt2	int
      //   0	780	4	paramInt3	int
      //   194	398	5	i	int
      //   76	651	6	j	int
      //   27	749	7	k	int
      //   181	246	8	m	int
      //   62	3	9	localException1	Exception
      //   81	116	9	localException2	Exception
      //   239	96	9	localStringBuilder	StringBuilder
      //   511	68	10	localObject	Object
      // Exception table:
      //   from	to	target	type
      //   635	640	62	java/lang/Exception
      //   647	656	62	java/lang/Exception
      //   86	94	81	java/lang/Exception
      //   94	103	81	java/lang/Exception
      //   241	246	81	java/lang/Exception
    }
    
    /* Error */
    public void onReceive(android.content.Context paramContext, android.content.Intent paramIntent)
    {
      // Byte code:
      //   0: goto +591 -> 591
      //   3: iconst_1
      //   4: istore_3
      //   5: goto +80 -> 85
      //   8: getstatic 25	o/aj$if:ʻ	I
      //   11: bipush 115
      //   13: iadd
      //   14: istore_3
      //   15: iload_3
      //   16: sipush 128
      //   19: irem
      //   20: putstatic 23	o/aj$if:ᐝ	I
      //   23: iload_3
      //   24: iconst_2
      //   25: irem
      //   26: ifeq +6 -> 32
      //   29: goto +777 -> 806
      //   32: goto +339 -> 371
      //   35: aload_2
      //   36: aload 7
      //   38: getfield 98	o/ab:ॱ	I
      //   41: aload 8
      //   43: invokevirtual 103	o/ʰ$ˋ:ˏ	()Landroid/app/Notification;
      //   46: invokevirtual 109	android/app/NotificationManager:notify	(ILandroid/app/Notification;)V
      //   49: goto +781 -> 830
      //   52: aload_2
      //   53: invokeinterface 115 1 0
      //   58: astore 9
      //   60: aload 9
      //   62: checkcast 117	o/ac
      //   65: astore 9
      //   67: aload 9
      //   69: invokevirtual 120	o/ac:ˊ	()Lo/ʰ$if;
      //   72: astore 9
      //   74: aload 8
      //   76: aload 9
      //   78: invokevirtual 123	o/ʰ$ˋ:ॱ	(Lo/ʰ$if;)Lo/ʰ$ˋ;
      //   81: pop
      //   82: goto +551 -> 633
      //   85: iload_3
      //   86: tableswitch	default:+22->108, 0:+773->859, 1:+493->579
      //   108: goto +751 -> 859
      //   111: aload_2
      //   112: invokeinterface 127 1 0
      //   117: ifeq +6 -> 123
      //   120: goto +759 -> 879
      //   123: goto +686 -> 809
      //   126: iconst_0
      //   127: istore_3
      //   128: goto +424 -> 552
      //   131: iload_3
      //   132: lookupswitch	default:+28->160, 9:+-80->52, 82:+533->665
      //   160: goto +505 -> 665
      //   163: iconst_0
      //   164: ldc -128
      //   166: iconst_0
      //   167: ldc -127
      //   169: bipush -120
      //   171: invokestatic 131	o/aj$if:ॱ	(SIBII)Ljava/lang/String;
      //   174: invokevirtual 136	java/lang/String:intern	()Ljava/lang/String;
      //   177: astore_2
      //   178: new 84	java/lang/StringBuilder
      //   181: dup
      //   182: invokespecial 89	java/lang/StringBuilder:<init>	()V
      //   185: iconst_0
      //   186: ldc -119
      //   188: iconst_0
      //   189: ldc -118
      //   191: bipush -120
      //   193: invokestatic 131	o/aj$if:ॱ	(SIBII)Ljava/lang/String;
      //   196: invokevirtual 136	java/lang/String:intern	()Ljava/lang/String;
      //   199: invokevirtual 141	java/lang/StringBuilder:append	(Ljava/lang/String;)Ljava/lang/StringBuilder;
      //   202: aload 7
      //   204: invokevirtual 142	o/ab:toString	()Ljava/lang/String;
      //   207: invokevirtual 141	java/lang/StringBuilder:append	(Ljava/lang/String;)Ljava/lang/StringBuilder;
      //   210: invokevirtual 93	java/lang/StringBuilder:toString	()Ljava/lang/String;
      //   213: astore 8
      //   215: goto +17 -> 232
      //   218: astore_2
      //   219: aload_2
      //   220: invokevirtual 148	java/lang/Throwable:getCause	()Ljava/lang/Throwable;
      //   223: astore_1
      //   224: aload_1
      //   225: ifnull +5 -> 230
      //   228: aload_1
      //   229: athrow
      //   230: aload_2
      //   231: athrow
      //   232: iconst_4
      //   233: bipush 42
      //   235: ldc -107
      //   237: invokestatic 154	o/O:ˋ	(IIC)Ljava/lang/Object;
      //   240: checkcast 156	java/lang/Class
      //   243: ldc -99
      //   245: iconst_2
      //   246: anewarray 156	java/lang/Class
      //   249: dup
      //   250: iconst_0
      //   251: ldc -123
      //   253: aastore
      //   254: dup
      //   255: iconst_1
      //   256: ldc -123
      //   258: aastore
      //   259: invokevirtual 161	java/lang/Class:getMethod	(Ljava/lang/String;[Ljava/lang/Class;)Ljava/lang/reflect/Method;
      //   262: aconst_null
      //   263: iconst_2
      //   264: anewarray 163	java/lang/Object
      //   267: dup
      //   268: iconst_0
      //   269: aload_2
      //   270: aastore
      //   271: dup
      //   272: iconst_1
      //   273: aload 8
      //   275: aastore
      //   276: invokevirtual 169	java/lang/reflect/Method:invoke	(Ljava/lang/Object;[Ljava/lang/Object;)Ljava/lang/Object;
      //   279: pop
      //   280: new 100	o/ʰ$ˋ
      //   283: dup
      //   284: aload_1
      //   285: aload 7
      //   287: getfield 173	o/ab:ॱॱ	Ljava/lang/String;
      //   290: invokespecial 176	o/ʰ$ˋ:<init>	(Landroid/content/Context;Ljava/lang/String;)V
      //   293: aload 7
      //   295: getfield 178	o/ab:ˏ	I
      //   298: invokevirtual 181	o/ʰ$ˋ:ˊ	(I)Lo/ʰ$ˋ;
      //   301: aload 7
      //   303: getfield 183	o/ab:ˎ	Ljava/lang/String;
      //   306: invokevirtual 186	o/ʰ$ˋ:ˋ	(Ljava/lang/CharSequence;)Lo/ʰ$ˋ;
      //   309: aload 7
      //   311: getfield 188	o/ab:ˋ	Ljava/lang/String;
      //   314: invokevirtual 190	o/ʰ$ˋ:ॱ	(Ljava/lang/CharSequence;)Lo/ʰ$ˋ;
      //   317: new 192	o/ʰ$If
      //   320: dup
      //   321: invokespecial 193	o/ʰ$If:<init>	()V
      //   324: aload 7
      //   326: getfield 188	o/ab:ˋ	Ljava/lang/String;
      //   329: invokevirtual 196	o/ʰ$If:ˎ	(Ljava/lang/CharSequence;)Lo/ʰ$If;
      //   332: invokevirtual 199	o/ʰ$ˋ:ॱ	(Lo/ʰ$ˊ;)Lo/ʰ$ˋ;
      //   335: aload 7
      //   337: getfield 202	o/ab:ˊ	Landroid/app/PendingIntent;
      //   340: invokevirtual 205	o/ʰ$ˋ:ॱ	(Landroid/app/PendingIntent;)Lo/ʰ$ˋ;
      //   343: iconst_1
      //   344: invokevirtual 208	o/ʰ$ˋ:ॱ	(Z)Lo/ʰ$ˋ;
      //   347: aload 7
      //   349: getfield 211	o/ab:ᐝ	[J
      //   352: invokevirtual 214	o/ʰ$ˋ:ˎ	([J)Lo/ʰ$ˋ;
      //   355: astore 8
      //   357: aload 7
      //   359: getfield 218	o/ab:ʽ	Ljava/util/ArrayList;
      //   362: ifnull +6 -> 368
      //   365: goto +271 -> 636
      //   368: goto +297 -> 665
      //   371: goto +17 -> 388
      //   374: astore_2
      //   375: aload_2
      //   376: invokevirtual 148	java/lang/Throwable:getCause	()Ljava/lang/Throwable;
      //   379: astore_1
      //   380: aload_1
      //   381: ifnull +5 -> 386
      //   384: aload_1
      //   385: athrow
      //   386: aload_2
      //   387: athrow
      //   388: iconst_3
      //   389: iconst_0
      //   390: ldc -37
      //   392: invokestatic 154	o/O:ˋ	(IIC)Ljava/lang/Object;
      //   395: checkcast 156	java/lang/Class
      //   398: ldc -99
      //   400: aconst_null
      //   401: invokevirtual 161	java/lang/Class:getMethod	(Ljava/lang/String;[Ljava/lang/Class;)Ljava/lang/reflect/Method;
      //   404: aconst_null
      //   405: aconst_null
      //   406: invokevirtual 169	java/lang/reflect/Method:invoke	(Ljava/lang/Object;[Ljava/lang/Object;)Ljava/lang/Object;
      //   409: astore_2
      //   410: aload 7
      //   412: getfield 222	o/ab:ʻ	J
      //   415: lstore 4
      //   417: goto +17 -> 434
      //   420: astore_1
      //   421: aload_1
      //   422: invokevirtual 148	java/lang/Throwable:getCause	()Ljava/lang/Throwable;
      //   425: astore_2
      //   426: aload_2
      //   427: ifnull +5 -> 432
      //   430: aload_2
      //   431: athrow
      //   432: aload_1
      //   433: athrow
      //   434: iconst_3
      //   435: iconst_0
      //   436: ldc -37
      //   438: invokestatic 154	o/O:ˋ	(IIC)Ljava/lang/Object;
      //   441: checkcast 156	java/lang/Class
      //   444: ldc -33
      //   446: iconst_1
      //   447: anewarray 156	java/lang/Class
      //   450: dup
      //   451: iconst_0
      //   452: getstatic 229	java/lang/Long:TYPE	Ljava/lang/Class;
      //   455: aastore
      //   456: invokevirtual 161	java/lang/Class:getMethod	(Ljava/lang/String;[Ljava/lang/Class;)Ljava/lang/reflect/Method;
      //   459: aload_2
      //   460: iconst_1
      //   461: anewarray 163	java/lang/Object
      //   464: dup
      //   465: iconst_0
      //   466: lload 4
      //   468: invokestatic 233	java/lang/Long:valueOf	(J)Ljava/lang/Long;
      //   471: aastore
      //   472: invokevirtual 169	java/lang/reflect/Method:invoke	(Ljava/lang/Object;[Ljava/lang/Object;)Ljava/lang/Object;
      //   475: pop
      //   476: goto -313 -> 163
      //   479: iconst_1
      //   480: istore_3
      //   481: goto +350 -> 831
      //   484: iconst_0
      //   485: istore_3
      //   486: goto -401 -> 85
      //   489: aload_2
      //   490: new 235	android/app/NotificationChannel
      //   493: dup
      //   494: aload 7
      //   496: getfield 173	o/ab:ॱॱ	Ljava/lang/String;
      //   499: aload 7
      //   501: getfield 237	o/ab:ʼ	Ljava/lang/String;
      //   504: iconst_3
      //   505: invokespecial 240	android/app/NotificationChannel:<init>	(Ljava/lang/String;Ljava/lang/CharSequence;I)V
      //   508: invokevirtual 244	android/app/NotificationManager:createNotificationChannel	(Landroid/app/NotificationChannel;)V
      //   511: goto +304 -> 815
      //   514: getstatic 23	o/aj$if:ᐝ	I
      //   517: bipush 53
      //   519: iadd
      //   520: istore_3
      //   521: iload_3
      //   522: sipush 128
      //   525: irem
      //   526: putstatic 25	o/aj$if:ʻ	I
      //   529: iload_3
      //   530: iconst_2
      //   531: irem
      //   532: ifne +6 -> 538
      //   535: goto +6 -> 541
      //   538: goto -503 -> 35
      //   541: goto -506 -> 35
      //   544: iconst_0
      //   545: istore_3
      //   546: goto +285 -> 831
      //   549: astore_1
      //   550: aload_1
      //   551: athrow
      //   552: iload_3
      //   553: tableswitch	default:+23->576, 0:+277->830, 1:+-39->514
      //   576: goto -62 -> 514
      //   579: aload 7
      //   581: getfield 218	o/ab:ʽ	Ljava/util/ArrayList;
      //   584: invokevirtual 250	java/util/ArrayList:iterator	()Ljava/util/Iterator;
      //   587: astore_2
      //   588: goto -477 -> 111
      //   591: aload_2
      //   592: iconst_0
      //   593: ldc -5
      //   595: iconst_0
      //   596: ldc -4
      //   598: bipush -120
      //   600: invokestatic 131	o/aj$if:ॱ	(SIBII)Ljava/lang/String;
      //   603: invokevirtual 136	java/lang/String:intern	()Ljava/lang/String;
      //   606: invokevirtual 258	android/content/Intent:getParcelableExtra	(Ljava/lang/String;)Landroid/os/Parcelable;
      //   609: invokestatic 263	o/Aq:ॱ	(Landroid/os/Parcelable;)Ljava/lang/Object;
      //   612: checkcast 97	o/ab
      //   615: astore 7
      //   617: aload 7
      //   619: getfield 222	o/ab:ʻ	J
      //   622: lconst_0
      //   623: lcmp
      //   624: ifle +6 -> 630
      //   627: goto -83 -> 544
      //   630: goto -151 -> 479
      //   633: goto -522 -> 111
      //   636: getstatic 25	o/aj$if:ʻ	I
      //   639: istore_3
      //   640: iload_3
      //   641: bipush 31
      //   643: iadd
      //   644: istore_3
      //   645: iload_3
      //   646: sipush 128
      //   649: irem
      //   650: putstatic 23	o/aj$if:ᐝ	I
      //   653: iload_3
      //   654: iconst_2
      //   655: irem
      //   656: ifeq +6 -> 662
      //   659: goto -175 -> 484
      //   662: goto -659 -> 3
      //   665: aload_1
      //   666: iconst_0
      //   667: ldc_w 264
      //   670: iconst_0
      //   671: ldc_w 265
      //   674: bipush -120
      //   676: invokestatic 131	o/aj$if:ॱ	(SIBII)Ljava/lang/String;
      //   679: invokevirtual 136	java/lang/String:intern	()Ljava/lang/String;
      //   682: invokevirtual 271	android/content/Context:getSystemService	(Ljava/lang/String;)Ljava/lang/Object;
      //   685: checkcast 105	android/app/NotificationManager
      //   688: astore_2
      //   689: goto +17 -> 706
      //   692: astore_1
      //   693: aload_1
      //   694: invokevirtual 148	java/lang/Throwable:getCause	()Ljava/lang/Throwable;
      //   697: astore_2
      //   698: aload_2
      //   699: ifnull +5 -> 704
      //   702: aload_2
      //   703: athrow
      //   704: aload_1
      //   705: athrow
      //   706: iconst_3
      //   707: iconst_0
      //   708: ldc -37
      //   710: invokestatic 154	o/O:ˋ	(IIC)Ljava/lang/Object;
      //   713: checkcast 156	java/lang/Class
      //   716: ldc -99
      //   718: aconst_null
      //   719: invokevirtual 161	java/lang/Class:getMethod	(Ljava/lang/String;[Ljava/lang/Class;)Ljava/lang/reflect/Method;
      //   722: aconst_null
      //   723: aconst_null
      //   724: invokevirtual 169	java/lang/reflect/Method:invoke	(Ljava/lang/Object;[Ljava/lang/Object;)Ljava/lang/Object;
      //   727: astore_1
      //   728: goto +17 -> 745
      //   731: astore_2
      //   732: aload_2
      //   733: invokevirtual 148	java/lang/Throwable:getCause	()Ljava/lang/Throwable;
      //   736: astore_1
      //   737: aload_1
      //   738: ifnull +5 -> 743
      //   741: aload_1
      //   742: athrow
      //   743: aload_2
      //   744: athrow
      //   745: iconst_3
      //   746: iconst_0
      //   747: ldc -37
      //   749: invokestatic 154	o/O:ˋ	(IIC)Ljava/lang/Object;
      //   752: checkcast 156	java/lang/Class
      //   755: ldc_w 272
      //   758: iconst_1
      //   759: anewarray 156	java/lang/Class
      //   762: dup
      //   763: iconst_0
      //   764: getstatic 275	java/lang/Integer:TYPE	Ljava/lang/Class;
      //   767: aastore
      //   768: invokevirtual 161	java/lang/Class:getMethod	(Ljava/lang/String;[Ljava/lang/Class;)Ljava/lang/reflect/Method;
      //   771: aload_1
      //   772: iconst_1
      //   773: anewarray 163	java/lang/Object
      //   776: dup
      //   777: iconst_0
      //   778: bipush 26
      //   780: invokestatic 278	java/lang/Integer:valueOf	(I)Ljava/lang/Integer;
      //   783: aastore
      //   784: invokevirtual 169	java/lang/reflect/Method:invoke	(Ljava/lang/Object;[Ljava/lang/Object;)Ljava/lang/Object;
      //   787: checkcast 280	java/lang/Boolean
      //   790: invokevirtual 283	java/lang/Boolean:booleanValue	()Z
      //   793: istore 6
      //   795: iload 6
      //   797: ifeq +6 -> 803
      //   800: goto -311 -> 489
      //   803: goto +12 -> 815
      //   806: goto -435 -> 371
      //   809: bipush 82
      //   811: istore_3
      //   812: goto -681 -> 131
      //   815: aload_2
      //   816: ifnull +6 -> 822
      //   819: goto +6 -> 825
      //   822: goto -696 -> 126
      //   825: iconst_1
      //   826: istore_3
      //   827: goto -275 -> 552
      //   830: return
      //   831: iload_3
      //   832: tableswitch	default:+24->856, 0:+-824->8, 1:+-669->163
      //   856: goto -848 -> 8
      //   859: aload 7
      //   861: getfield 218	o/ab:ʽ	Ljava/util/ArrayList;
      //   864: invokevirtual 250	java/util/ArrayList:iterator	()Ljava/util/Iterator;
      //   867: astore_1
      //   868: new 285	java/lang/NullPointerException
      //   871: dup
      //   872: invokespecial 286	java/lang/NullPointerException:<init>	()V
      //   875: athrow
      //   876: astore_1
      //   877: aload_1
      //   878: athrow
      //   879: bipush 9
      //   881: istore_3
      //   882: goto -751 -> 131
      // Local variable table:
      //   start	length	slot	name	signature
      //   0	885	0	this	if
      //   0	885	1	paramContext	android.content.Context
      //   0	885	2	paramIntent	android.content.Intent
      //   4	878	3	i	int
      //   415	52	4	l	long
      //   793	3	6	bool	boolean
      //   36	824	7	localAb	ab
      //   41	315	8	localObject1	Object
      //   58	19	9	localObject2	Object
      // Exception table:
      //   from	to	target	type
      //   232	280	218	finally
      //   388	410	374	finally
      //   434	476	420	finally
      //   636	640	549	java/lang/Exception
      //   706	728	692	finally
      //   745	795	731	finally
      //   52	60	876	java/lang/Exception
      //   60	67	876	java/lang/Exception
      //   67	74	876	java/lang/Exception
      //   74	82	876	java/lang/Exception
    }
  }
}
