package o;

import android.content.Context;
import android.support.design.widget.AppBarLayout;
import android.support.design.widget.AppBarLayout.ˊ;
import android.util.AttributeSet;

public final class ar
  extends AppBarLayout
  implements AppBarLayout.ˊ
{
  private static char ʻ = 62358;
  private static int ʼ;
  private static char ˋ = '⁅';
  private static char ˏ = 53124;
  private static char ॱ = '丽';
  private static int ᐝ = 0;
  private int ˊ;
  private ˋ ˎ;
  
  static
  {
    ʼ = 1;
  }
  
  public ar(Context paramContext) {}
  
  public ar(Context paramContext, AttributeSet paramAttributeSet)
  {
    super(paramContext, paramAttributeSet);
  }
  
  private static String ˋ(char[] paramArrayOfChar)
  {
    char[] arrayOfChar1;
    int i;
    char[] arrayOfChar2;
    int j;
    for (;;)
    {
      arrayOfChar1 = new char[paramArrayOfChar.length];
      i = 0;
      arrayOfChar2 = new char[2];
      break;
      j = 0;
      break label123;
    }
    label26:
    break label246;
    paramArrayOfChar = new String(arrayOfChar1, 1, arrayOfChar1[0]);
    label45:
    if (i >= paramArrayOfChar.length)
    {
      break label151;
      j = ʼ + 43;
      ᐝ = j % 128;
      if (j % 2 != 0) {
        break label276;
      }
      break label156;
      i = 79 / 0;
      return paramArrayOfChar;
      return paramArrayOfChar;
      i = ʼ + 117;
      ᐝ = i % 128;
      if (i % 2 == 0)
      {
        i = 74;
        break label215;
        for (;;)
        {
          label123:
          switch (j)
          {
          }
          break;
          label151:
          j = 1;
        }
      }
    }
    label156:
    label215:
    label246:
    label249:
    label276:
    for (;;)
    {
      arrayOfChar2[0] = paramArrayOfChar[i];
      arrayOfChar2[1] = paramArrayOfChar[(i + 1)];
      oP.ˏ(arrayOfChar2, ॱ, ˋ, ˏ, ʻ);
      arrayOfChar1[i] = arrayOfChar2[0];
      arrayOfChar1[(i + 1)] = arrayOfChar2[1];
      i += 2;
      break label249;
      i = 98;
      switch (i)
      {
      }
      return paramArrayOfChar;
      for (;;)
      {
        break label45;
        break;
        j = ᐝ + 13;
        ʼ = j % 128;
        if (j % 2 == 0) {
          break label26;
        }
      }
    }
  }
  
  /* Error */
  public final void setOnScrollStatusChangedListener(ˋ paramˋ)
  {
    // Byte code:
    //   0: goto +230 -> 230
    //   3: iload_2
    //   4: tableswitch	default:+24->28, 0:+30->34, 1:+137->141
    //   28: goto +6 -> 34
    //   31: astore_1
    //   32: aload_1
    //   33: athrow
    //   34: bipush 10
    //   36: newarray char
    //   38: dup
    //   39: iconst_0
    //   40: ldc 59
    //   42: castore
    //   43: dup
    //   44: iconst_1
    //   45: ldc 60
    //   47: castore
    //   48: dup
    //   49: iconst_2
    //   50: ldc 61
    //   52: castore
    //   53: dup
    //   54: iconst_3
    //   55: ldc 62
    //   57: castore
    //   58: dup
    //   59: iconst_4
    //   60: ldc 63
    //   62: castore
    //   63: dup
    //   64: iconst_5
    //   65: ldc 64
    //   67: castore
    //   68: dup
    //   69: bipush 6
    //   71: ldc 65
    //   73: castore
    //   74: dup
    //   75: bipush 7
    //   77: ldc 66
    //   79: castore
    //   80: dup
    //   81: bipush 8
    //   83: ldc 67
    //   85: castore
    //   86: dup
    //   87: bipush 9
    //   89: ldc 68
    //   91: castore
    //   92: invokestatic 70	o/ar:ˋ	([C)Ljava/lang/String;
    //   95: astore_3
    //   96: aload_3
    //   97: invokevirtual 74	java/lang/String:intern	()Ljava/lang/String;
    //   100: astore_3
    //   101: aload_1
    //   102: aload_3
    //   103: invokestatic 79	o/vq:ˎ	(Ljava/lang/Object;Ljava/lang/String;)V
    //   106: aload_0
    //   107: aload_0
    //   108: checkcast 6	android/support/design/widget/AppBarLayout$ˊ
    //   111: invokevirtual 82	o/ar:ˎ	(Landroid/support/design/widget/AppBarLayout$ˊ;)V
    //   114: aload_0
    //   115: aload_1
    //   116: putfield 84	o/ar:ˎ	Lo/ar$ˋ;
    //   119: goto +146 -> 265
    //   122: astore_1
    //   123: aload_1
    //   124: athrow
    //   125: iconst_1
    //   126: istore_2
    //   127: goto -124 -> 3
    //   130: iconst_0
    //   131: istore_2
    //   132: goto -129 -> 3
    //   135: bipush 35
    //   137: istore_2
    //   138: goto +96 -> 234
    //   141: aload_1
    //   142: bipush 10
    //   144: newarray char
    //   146: dup
    //   147: iconst_0
    //   148: ldc 59
    //   150: castore
    //   151: dup
    //   152: iconst_1
    //   153: ldc 60
    //   155: castore
    //   156: dup
    //   157: iconst_2
    //   158: ldc 61
    //   160: castore
    //   161: dup
    //   162: iconst_3
    //   163: ldc 62
    //   165: castore
    //   166: dup
    //   167: iconst_4
    //   168: ldc 63
    //   170: castore
    //   171: dup
    //   172: iconst_5
    //   173: ldc 64
    //   175: castore
    //   176: dup
    //   177: bipush 6
    //   179: ldc 65
    //   181: castore
    //   182: dup
    //   183: bipush 7
    //   185: ldc 66
    //   187: castore
    //   188: dup
    //   189: bipush 8
    //   191: ldc 67
    //   193: castore
    //   194: dup
    //   195: bipush 9
    //   197: ldc 68
    //   199: castore
    //   200: invokestatic 70	o/ar:ˋ	([C)Ljava/lang/String;
    //   203: invokevirtual 74	java/lang/String:intern	()Ljava/lang/String;
    //   206: invokestatic 79	o/vq:ˎ	(Ljava/lang/Object;Ljava/lang/String;)V
    //   209: aload_0
    //   210: aload_0
    //   211: checkcast 6	android/support/design/widget/AppBarLayout$ˊ
    //   214: invokevirtual 82	o/ar:ˎ	(Landroid/support/design/widget/AppBarLayout$ˊ;)V
    //   217: aload_0
    //   218: aload_1
    //   219: putfield 84	o/ar:ˎ	Lo/ar$ˋ;
    //   222: new 86	java/lang/NullPointerException
    //   225: dup
    //   226: invokespecial 88	java/lang/NullPointerException:<init>	()V
    //   229: athrow
    //   230: goto +64 -> 294
    //   233: return
    //   234: iload_2
    //   235: lookupswitch	default:+25->260, 35:+-2->233, 95:+26->261
    //   260: return
    //   261: aconst_null
    //   262: arraylength
    //   263: istore_2
    //   264: return
    //   265: getstatic 23	o/ar:ᐝ	I
    //   268: istore_2
    //   269: iload_2
    //   270: bipush 45
    //   272: iadd
    //   273: istore_2
    //   274: iload_2
    //   275: sipush 128
    //   278: irem
    //   279: putstatic 25	o/ar:ʼ	I
    //   282: iload_2
    //   283: iconst_2
    //   284: irem
    //   285: ifne +6 -> 291
    //   288: goto +33 -> 321
    //   291: goto -156 -> 135
    //   294: getstatic 23	o/ar:ᐝ	I
    //   297: bipush 39
    //   299: iadd
    //   300: istore_2
    //   301: iload_2
    //   302: sipush 128
    //   305: irem
    //   306: putstatic 25	o/ar:ʼ	I
    //   309: iload_2
    //   310: iconst_2
    //   311: irem
    //   312: ifne +6 -> 318
    //   315: goto -190 -> 125
    //   318: goto -188 -> 130
    //   321: bipush 95
    //   323: istore_2
    //   324: goto -90 -> 234
    // Local variable table:
    //   start	length	slot	name	signature
    //   0	327	0	this	ar
    //   0	327	1	paramˋ	ˋ
    //   3	321	2	i	int
    //   95	8	3	str	String
    // Exception table:
    //   from	to	target	type
    //   34	96	31	java/lang/Exception
    //   265	269	31	java/lang/Exception
    //   274	282	31	java/lang/Exception
    //   34	96	122	java/lang/Exception
    //   96	101	122	java/lang/Exception
    //   101	119	122	java/lang/Exception
  }
  
  /* Error */
  public void ˏ(AppBarLayout paramAppBarLayout, int paramInt)
  {
    // Byte code:
    //   0: goto +236 -> 236
    //   3: invokestatic 91	o/vq:ˎ	()V
    //   6: goto +68 -> 74
    //   9: astore_1
    //   10: aload_1
    //   11: athrow
    //   12: getstatic 96	o/H:ॱ	Lo/H;
    //   15: astore_1
    //   16: goto +147 -> 163
    //   19: aload 4
    //   21: aload_1
    //   22: invokeinterface 99 2 0
    //   27: return
    //   28: bipush 71
    //   30: istore_2
    //   31: goto +100 -> 131
    //   34: aconst_null
    //   35: arraylength
    //   36: istore_3
    //   37: aload_1
    //   38: ifnonnull +6 -> 44
    //   41: goto -38 -> 3
    //   44: goto +30 -> 74
    //   47: getstatic 25	o/ar:ʼ	I
    //   50: bipush 23
    //   52: iadd
    //   53: istore_3
    //   54: iload_3
    //   55: sipush 128
    //   58: irem
    //   59: putstatic 23	o/ar:ᐝ	I
    //   62: iload_3
    //   63: iconst_2
    //   64: irem
    //   65: ifeq +6 -> 71
    //   68: goto +379 -> 447
    //   71: goto +319 -> 390
    //   74: aload_1
    //   75: invokevirtual 102	android/support/design/widget/AppBarLayout:ˎ	()I
    //   78: iload_2
    //   79: iconst_m1
    //   80: imul
    //   81: if_icmpne +6 -> 87
    //   84: goto +19 -> 103
    //   87: goto +348 -> 435
    //   90: goto +19 -> 109
    //   93: goto +335 -> 428
    //   96: getstatic 104	o/H:ˎ	Lo/H;
    //   99: astore_1
    //   100: goto +9 -> 109
    //   103: bipush 88
    //   105: istore_3
    //   106: goto +60 -> 166
    //   109: aload_0
    //   110: iload_2
    //   111: putfield 106	o/ar:ˊ	I
    //   114: aload_0
    //   115: getfield 84	o/ar:ˎ	Lo/ar$ˋ;
    //   118: astore 4
    //   120: aload 4
    //   122: ifnonnull +6 -> 128
    //   125: goto -97 -> 28
    //   128: goto +295 -> 423
    //   131: iload_2
    //   132: lookupswitch	default:+28->160, 5:+-113->19, 71:+309->441
    //   160: goto -141 -> 19
    //   163: goto -54 -> 109
    //   166: iload_3
    //   167: lookupswitch	default:+25->192, 40:+213->380, 88:+-71->96
    //   192: goto -96 -> 96
    //   195: iload_2
    //   196: aload_0
    //   197: getfield 106	o/ar:ˊ	I
    //   200: if_icmpge +6 -> 206
    //   203: goto +71 -> 274
    //   206: goto +158 -> 364
    //   209: getstatic 25	o/ar:ʼ	I
    //   212: bipush 85
    //   214: iadd
    //   215: istore_3
    //   216: iload_3
    //   217: sipush 128
    //   220: irem
    //   221: putstatic 23	o/ar:ᐝ	I
    //   224: iload_3
    //   225: iconst_2
    //   226: irem
    //   227: ifeq +6 -> 233
    //   230: goto -137 -> 93
    //   233: goto +195 -> 428
    //   236: goto +71 -> 307
    //   239: iload_3
    //   240: tableswitch	default:+24->264, 0:+-45->195, 1:+-228->12
    //   264: goto -252 -> 12
    //   267: getstatic 108	o/H:ˏ	Lo/H;
    //   270: astore_1
    //   271: goto -162 -> 109
    //   274: getstatic 110	o/H:ˊ	Lo/H;
    //   277: astore_1
    //   278: goto -188 -> 90
    //   281: astore_1
    //   282: aload_1
    //   283: athrow
    //   284: aload_0
    //   285: getfield 84	o/ar:ˎ	Lo/ar$ˋ;
    //   288: astore 4
    //   290: aconst_null
    //   291: arraylength
    //   292: istore_3
    //   293: aload 4
    //   295: ifnull +6 -> 301
    //   298: goto -251 -> 47
    //   301: return
    //   302: iconst_0
    //   303: istore_3
    //   304: goto -65 -> 239
    //   307: getstatic 25	o/ar:ʼ	I
    //   310: bipush 55
    //   312: iadd
    //   313: istore_3
    //   314: iload_3
    //   315: sipush 128
    //   318: irem
    //   319: putstatic 23	o/ar:ᐝ	I
    //   322: iload_3
    //   323: iconst_2
    //   324: irem
    //   325: ifeq +6 -> 331
    //   328: goto -44 -> 284
    //   331: goto +13 -> 344
    //   334: aload_1
    //   335: ifnonnull +6 -> 341
    //   338: goto -335 -> 3
    //   341: goto -267 -> 74
    //   344: aload_0
    //   345: getfield 84	o/ar:ˎ	Lo/ar$ˋ;
    //   348: astore 4
    //   350: aload 4
    //   352: ifnull +6 -> 358
    //   355: goto -308 -> 47
    //   358: return
    //   359: iconst_1
    //   360: istore_3
    //   361: goto -122 -> 239
    //   364: aload_0
    //   365: getfield 106	o/ar:ˊ	I
    //   368: istore_3
    //   369: iload_2
    //   370: iload_3
    //   371: if_icmple +6 -> 377
    //   374: goto -165 -> 209
    //   377: goto -110 -> 267
    //   380: iload_2
    //   381: ifne +6 -> 387
    //   384: goto -25 -> 359
    //   387: goto -85 -> 302
    //   390: bipush 33
    //   392: istore_3
    //   393: iload_3
    //   394: lookupswitch	default:+26->420, 33:+-60->334, 74:+-360->34
    //   420: goto -386 -> 34
    //   423: iconst_5
    //   424: istore_2
    //   425: goto -294 -> 131
    //   428: getstatic 112	o/H:ˋ	Lo/H;
    //   431: astore_1
    //   432: goto -323 -> 109
    //   435: bipush 40
    //   437: istore_3
    //   438: goto -272 -> 166
    //   441: invokestatic 91	o/vq:ˎ	()V
    //   444: goto -425 -> 19
    //   447: bipush 74
    //   449: istore_3
    //   450: goto -57 -> 393
    // Local variable table:
    //   start	length	slot	name	signature
    //   0	453	0	this	ar
    //   0	453	1	paramAppBarLayout	AppBarLayout
    //   0	453	2	paramInt	int
    //   36	414	3	i	int
    //   19	332	4	localˋ	ˋ
    // Exception table:
    //   from	to	target	type
    //   209	216	9	java/lang/Exception
    //   216	224	9	java/lang/Exception
    //   344	350	9	java/lang/Exception
    //   364	369	9	java/lang/Exception
    //   47	62	281	java/lang/Exception
  }
  
  public static abstract interface ˋ
  {
    public abstract void ॱ(H paramH);
  }
}
