package o;

import android.content.Context;
import android.support.design.widget.CoordinatorLayout;
import android.util.AttributeSet;

public final class aw
  extends CoordinatorLayout
{
  private static long ʻ = 4555187125892539130L;
  private static int ʽ = 0;
  private static int ˏॱ = 1;
  private aD ʼ;
  private az ॱॱ;
  private ar ᐝ;
  
  public aw(Context paramContext)
  {
    this(paramContext, null);
  }
  
  public aw(Context paramContext, AttributeSet paramAttributeSet)
  {
    this(paramContext, paramAttributeSet, 0);
  }
  
  public aw(Context paramContext, AttributeSet paramAttributeSet, int paramInt) {}
  
  /* Error */
  private static String ˊ(char[] paramArrayOfChar)
  {
    // Byte code:
    //   0: goto +24 -> 24
    //   3: iconst_4
    //   4: istore_3
    //   5: goto +103 -> 108
    //   8: new 41	java/lang/String
    //   11: dup
    //   12: aload 8
    //   14: invokespecial 44	java/lang/String:<init>	([C)V
    //   17: areturn
    //   18: bipush 28
    //   20: istore_3
    //   21: goto +22 -> 43
    //   24: goto +51 -> 75
    //   27: aload_0
    //   28: astore 9
    //   30: iload_1
    //   31: aload 9
    //   33: arraylength
    //   34: if_icmpge +6 -> 40
    //   37: goto -19 -> 18
    //   40: goto +62 -> 102
    //   43: iload_3
    //   44: lookupswitch	default:+28->72, 28:+168->212, 34:+-36->8
    //   72: goto -64 -> 8
    //   75: getstatic 19	o/aw:ʽ	I
    //   78: bipush 75
    //   80: iadd
    //   81: istore_1
    //   82: iload_1
    //   83: sipush 128
    //   86: irem
    //   87: putstatic 21	o/aw:ˏॱ	I
    //   90: iload_1
    //   91: iconst_2
    //   92: irem
    //   93: ifne +6 -> 99
    //   96: goto +94 -> 190
    //   99: goto +69 -> 168
    //   102: bipush 34
    //   104: istore_3
    //   105: goto -62 -> 43
    //   108: iload_3
    //   109: lookupswitch	default:+27->136, 4:+130->239, 10:+27->136
    //   136: aload 8
    //   138: iload_1
    //   139: iconst_1
    //   140: isub
    //   141: aload 9
    //   143: iload_1
    //   144: caload
    //   145: iload_1
    //   146: iload_2
    //   147: iadd
    //   148: ior
    //   149: i2l
    //   150: getstatic 25	o/aw:ʻ	J
    //   153: lor
    //   154: l2i
    //   155: i2c
    //   156: castore
    //   157: iload_1
    //   158: bipush 11
    //   160: iadd
    //   161: istore_1
    //   162: goto -135 -> 27
    //   165: astore_0
    //   166: aload_0
    //   167: athrow
    //   168: aload_0
    //   169: astore 8
    //   171: aload 8
    //   173: iconst_0
    //   174: caload
    //   175: istore_2
    //   176: aload 8
    //   178: arraylength
    //   179: iconst_1
    //   180: isub
    //   181: newarray char
    //   183: astore 8
    //   185: iconst_1
    //   186: istore_1
    //   187: goto -160 -> 27
    //   190: aload_0
    //   191: astore 8
    //   193: aload 8
    //   195: iconst_1
    //   196: caload
    //   197: istore_2
    //   198: aload 8
    //   200: arraylength
    //   201: iconst_0
    //   202: iushr
    //   203: newarray char
    //   205: astore 8
    //   207: iconst_0
    //   208: istore_1
    //   209: goto -182 -> 27
    //   212: getstatic 19	o/aw:ʽ	I
    //   215: bipush 15
    //   217: iadd
    //   218: istore_3
    //   219: iload_3
    //   220: sipush 128
    //   223: irem
    //   224: putstatic 21	o/aw:ˏॱ	I
    //   227: iload_3
    //   228: iconst_2
    //   229: irem
    //   230: ifne +6 -> 236
    //   233: goto +42 -> 275
    //   236: goto -233 -> 3
    //   239: aload 9
    //   241: iload_1
    //   242: caload
    //   243: iload_1
    //   244: iload_2
    //   245: imul
    //   246: ixor
    //   247: i2l
    //   248: lstore 4
    //   250: getstatic 25	o/aw:ʻ	J
    //   253: lstore 6
    //   255: aload 8
    //   257: iload_1
    //   258: iconst_1
    //   259: isub
    //   260: lload 4
    //   262: lload 6
    //   264: lxor
    //   265: l2i
    //   266: i2c
    //   267: castore
    //   268: iload_1
    //   269: iconst_1
    //   270: iadd
    //   271: istore_1
    //   272: goto -245 -> 27
    //   275: bipush 10
    //   277: istore_3
    //   278: goto -170 -> 108
    // Local variable table:
    //   start	length	slot	name	signature
    //   0	281	0	paramArrayOfChar	char[]
    //   30	242	1	i	int
    //   146	100	2	j	int
    //   4	274	3	k	int
    //   248	13	4	l1	long
    //   253	10	6	l2	long
    //   12	244	8	arrayOfChar1	char[]
    //   28	212	9	arrayOfChar2	char[]
    // Exception table:
    //   from	to	target	type
    //   250	255	165	java/lang/Exception
  }
  
  /* Error */
  private final void ᐝ()
  {
    // Byte code:
    //   0: goto +137 -> 137
    //   3: iconst_1
    //   4: istore_1
    //   5: goto +67 -> 72
    //   8: iload_1
    //   9: lookupswitch	default:+27->36, 0:+185->194, 50:+57->66
    //   36: return
    //   37: getstatic 21	o/aw:ˏॱ	I
    //   40: istore_1
    //   41: iload_1
    //   42: bipush 87
    //   44: iadd
    //   45: istore_1
    //   46: iload_1
    //   47: sipush 128
    //   50: irem
    //   51: putstatic 19	o/aw:ʽ	I
    //   54: iload_1
    //   55: iconst_2
    //   56: irem
    //   57: ifeq +6 -> 63
    //   60: goto +39 -> 99
    //   63: goto +110 -> 173
    //   66: bipush 59
    //   68: iconst_0
    //   69: idiv
    //   70: istore_1
    //   71: return
    //   72: iload_1
    //   73: tableswitch	default:+23->96, 0:+70->143, 1:+32->105
    //   96: goto +47 -> 143
    //   99: bipush 50
    //   101: istore_1
    //   102: goto -94 -> 8
    //   105: goto +35 -> 140
    //   108: astore_2
    //   109: aload_2
    //   110: athrow
    //   111: aload_0
    //   112: aload_0
    //   113: invokevirtual 48	o/aw:getChildCount	()I
    //   116: iconst_1
    //   117: isub
    //   118: invokevirtual 52	o/aw:getChildAt	(I)Landroid/view/View;
    //   121: astore_2
    //   122: aload_0
    //   123: getfield 54	o/aw:ॱॱ	Lo/az;
    //   126: astore_3
    //   127: aload_3
    //   128: ifnull +6 -> 134
    //   131: goto +58 -> 189
    //   134: goto -131 -> 3
    //   137: goto -26 -> 111
    //   140: goto -103 -> 37
    //   143: getstatic 19	o/aw:ʽ	I
    //   146: bipush 51
    //   148: iadd
    //   149: istore_1
    //   150: iload_1
    //   151: sipush 128
    //   154: irem
    //   155: putstatic 21	o/aw:ˏॱ	I
    //   158: iload_1
    //   159: iconst_2
    //   160: irem
    //   161: ifne +6 -> 167
    //   164: goto +6 -> 170
    //   167: goto +14 -> 181
    //   170: goto +11 -> 181
    //   173: iconst_0
    //   174: istore_1
    //   175: goto -167 -> 8
    //   178: astore_2
    //   179: aload_2
    //   180: athrow
    //   181: aload_3
    //   182: aload_2
    //   183: invokevirtual 60	o/az:setMShadowTop	(Landroid/view/View;)V
    //   186: goto -46 -> 140
    //   189: iconst_0
    //   190: istore_1
    //   191: goto -119 -> 72
    //   194: return
    // Local variable table:
    //   start	length	slot	name	signature
    //   0	195	0	this	aw
    //   4	187	1	i	int
    //   108	2	2	localException1	Exception
    //   121	1	2	localView	android.view.View
    //   178	5	2	localException2	Exception
    //   126	56	3	localAz	az
    // Exception table:
    //   from	to	target	type
    //   37	41	108	java/lang/Exception
    //   46	54	108	java/lang/Exception
    //   181	186	178	java/lang/Exception
  }
  
  /* Error */
  protected void onFinishInflate()
  {
    // Byte code:
    //   0: goto +886 -> 886
    //   3: goto +805 -> 808
    //   6: bipush 13
    //   8: newarray char
    //   10: dup
    //   11: iconst_0
    //   12: ldc 62
    //   14: castore
    //   15: dup
    //   16: iconst_1
    //   17: ldc 63
    //   19: castore
    //   20: dup
    //   21: iconst_2
    //   22: ldc 64
    //   24: castore
    //   25: dup
    //   26: iconst_3
    //   27: ldc 65
    //   29: castore
    //   30: dup
    //   31: iconst_4
    //   32: ldc 66
    //   34: castore
    //   35: dup
    //   36: iconst_5
    //   37: ldc 67
    //   39: castore
    //   40: dup
    //   41: bipush 6
    //   43: ldc 68
    //   45: castore
    //   46: dup
    //   47: bipush 7
    //   49: ldc 69
    //   51: castore
    //   52: dup
    //   53: bipush 8
    //   55: ldc 70
    //   57: castore
    //   58: dup
    //   59: bipush 9
    //   61: ldc 71
    //   63: castore
    //   64: dup
    //   65: bipush 10
    //   67: ldc 72
    //   69: castore
    //   70: dup
    //   71: bipush 11
    //   73: ldc 73
    //   75: castore
    //   76: dup
    //   77: bipush 12
    //   79: ldc 74
    //   81: castore
    //   82: invokestatic 76	o/aw:ˊ	([C)Ljava/lang/String;
    //   85: invokevirtual 80	java/lang/String:intern	()Ljava/lang/String;
    //   88: astore 4
    //   90: bipush 88
    //   92: newarray char
    //   94: dup
    //   95: iconst_0
    //   96: ldc 81
    //   98: castore
    //   99: dup
    //   100: iconst_1
    //   101: ldc 82
    //   103: castore
    //   104: dup
    //   105: iconst_2
    //   106: ldc 83
    //   108: castore
    //   109: dup
    //   110: iconst_3
    //   111: ldc 84
    //   113: castore
    //   114: dup
    //   115: iconst_4
    //   116: ldc 85
    //   118: castore
    //   119: dup
    //   120: iconst_5
    //   121: ldc 86
    //   123: castore
    //   124: dup
    //   125: bipush 6
    //   127: ldc 87
    //   129: castore
    //   130: dup
    //   131: bipush 7
    //   133: ldc 88
    //   135: castore
    //   136: dup
    //   137: bipush 8
    //   139: ldc 89
    //   141: castore
    //   142: dup
    //   143: bipush 9
    //   145: ldc 90
    //   147: castore
    //   148: dup
    //   149: bipush 10
    //   151: ldc 91
    //   153: castore
    //   154: dup
    //   155: bipush 11
    //   157: ldc 92
    //   159: castore
    //   160: dup
    //   161: bipush 12
    //   163: ldc 93
    //   165: castore
    //   166: dup
    //   167: bipush 13
    //   169: ldc 94
    //   171: castore
    //   172: dup
    //   173: bipush 14
    //   175: ldc 95
    //   177: castore
    //   178: dup
    //   179: bipush 15
    //   181: ldc 96
    //   183: castore
    //   184: dup
    //   185: bipush 16
    //   187: ldc 97
    //   189: castore
    //   190: dup
    //   191: bipush 17
    //   193: ldc 98
    //   195: castore
    //   196: dup
    //   197: bipush 18
    //   199: ldc 99
    //   201: castore
    //   202: dup
    //   203: bipush 19
    //   205: ldc 100
    //   207: castore
    //   208: dup
    //   209: bipush 20
    //   211: ldc 101
    //   213: castore
    //   214: dup
    //   215: bipush 21
    //   217: ldc 102
    //   219: castore
    //   220: dup
    //   221: bipush 22
    //   223: ldc 103
    //   225: castore
    //   226: dup
    //   227: bipush 23
    //   229: ldc 104
    //   231: castore
    //   232: dup
    //   233: bipush 24
    //   235: ldc 105
    //   237: castore
    //   238: dup
    //   239: bipush 25
    //   241: ldc 106
    //   243: castore
    //   244: dup
    //   245: bipush 26
    //   247: ldc 107
    //   249: castore
    //   250: dup
    //   251: bipush 27
    //   253: ldc 108
    //   255: castore
    //   256: dup
    //   257: bipush 28
    //   259: ldc 109
    //   261: castore
    //   262: dup
    //   263: bipush 29
    //   265: ldc 110
    //   267: castore
    //   268: dup
    //   269: bipush 30
    //   271: ldc 111
    //   273: castore
    //   274: dup
    //   275: bipush 31
    //   277: ldc 112
    //   279: castore
    //   280: dup
    //   281: bipush 32
    //   283: ldc 113
    //   285: castore
    //   286: dup
    //   287: bipush 33
    //   289: ldc 114
    //   291: castore
    //   292: dup
    //   293: bipush 34
    //   295: ldc 115
    //   297: castore
    //   298: dup
    //   299: bipush 35
    //   301: ldc 116
    //   303: castore
    //   304: dup
    //   305: bipush 36
    //   307: ldc 117
    //   309: castore
    //   310: dup
    //   311: bipush 37
    //   313: ldc 118
    //   315: castore
    //   316: dup
    //   317: bipush 38
    //   319: ldc 119
    //   321: castore
    //   322: dup
    //   323: bipush 39
    //   325: ldc 120
    //   327: castore
    //   328: dup
    //   329: bipush 40
    //   331: ldc 121
    //   333: castore
    //   334: dup
    //   335: bipush 41
    //   337: ldc 122
    //   339: castore
    //   340: dup
    //   341: bipush 42
    //   343: ldc 123
    //   345: castore
    //   346: dup
    //   347: bipush 43
    //   349: ldc 124
    //   351: castore
    //   352: dup
    //   353: bipush 44
    //   355: ldc 125
    //   357: castore
    //   358: dup
    //   359: bipush 45
    //   361: ldc 126
    //   363: castore
    //   364: dup
    //   365: bipush 46
    //   367: ldc 127
    //   369: castore
    //   370: dup
    //   371: bipush 47
    //   373: ldc -128
    //   375: castore
    //   376: dup
    //   377: bipush 48
    //   379: ldc -127
    //   381: castore
    //   382: dup
    //   383: bipush 49
    //   385: ldc -126
    //   387: castore
    //   388: dup
    //   389: bipush 50
    //   391: ldc -125
    //   393: castore
    //   394: dup
    //   395: bipush 51
    //   397: ldc -124
    //   399: castore
    //   400: dup
    //   401: bipush 52
    //   403: ldc -123
    //   405: castore
    //   406: dup
    //   407: bipush 53
    //   409: ldc -122
    //   411: castore
    //   412: dup
    //   413: bipush 54
    //   415: ldc -121
    //   417: castore
    //   418: dup
    //   419: bipush 55
    //   421: ldc -120
    //   423: castore
    //   424: dup
    //   425: bipush 56
    //   427: ldc -119
    //   429: castore
    //   430: dup
    //   431: bipush 57
    //   433: ldc -118
    //   435: castore
    //   436: dup
    //   437: bipush 58
    //   439: ldc -117
    //   441: castore
    //   442: dup
    //   443: bipush 59
    //   445: ldc -116
    //   447: castore
    //   448: dup
    //   449: bipush 60
    //   451: ldc -115
    //   453: castore
    //   454: dup
    //   455: bipush 61
    //   457: ldc -114
    //   459: castore
    //   460: dup
    //   461: bipush 62
    //   463: ldc -113
    //   465: castore
    //   466: dup
    //   467: bipush 63
    //   469: ldc -112
    //   471: castore
    //   472: dup
    //   473: bipush 64
    //   475: ldc -111
    //   477: castore
    //   478: dup
    //   479: bipush 65
    //   481: ldc -110
    //   483: castore
    //   484: dup
    //   485: bipush 66
    //   487: ldc -109
    //   489: castore
    //   490: dup
    //   491: bipush 67
    //   493: ldc -108
    //   495: castore
    //   496: dup
    //   497: bipush 68
    //   499: ldc -107
    //   501: castore
    //   502: dup
    //   503: bipush 69
    //   505: ldc -106
    //   507: castore
    //   508: dup
    //   509: bipush 70
    //   511: ldc -105
    //   513: castore
    //   514: dup
    //   515: bipush 71
    //   517: ldc -104
    //   519: castore
    //   520: dup
    //   521: bipush 72
    //   523: ldc -103
    //   525: castore
    //   526: dup
    //   527: bipush 73
    //   529: ldc -102
    //   531: castore
    //   532: dup
    //   533: bipush 74
    //   535: ldc -101
    //   537: castore
    //   538: dup
    //   539: bipush 75
    //   541: ldc -100
    //   543: castore
    //   544: dup
    //   545: bipush 76
    //   547: ldc -99
    //   549: castore
    //   550: dup
    //   551: bipush 77
    //   553: ldc -98
    //   555: castore
    //   556: dup
    //   557: bipush 78
    //   559: ldc -97
    //   561: castore
    //   562: dup
    //   563: bipush 79
    //   565: ldc -96
    //   567: castore
    //   568: dup
    //   569: bipush 80
    //   571: ldc -95
    //   573: castore
    //   574: dup
    //   575: bipush 81
    //   577: ldc -94
    //   579: castore
    //   580: dup
    //   581: bipush 82
    //   583: ldc -93
    //   585: castore
    //   586: dup
    //   587: bipush 83
    //   589: ldc -92
    //   591: castore
    //   592: dup
    //   593: bipush 84
    //   595: ldc -91
    //   597: castore
    //   598: dup
    //   599: bipush 85
    //   601: ldc -90
    //   603: castore
    //   604: dup
    //   605: bipush 86
    //   607: ldc -89
    //   609: castore
    //   610: dup
    //   611: bipush 87
    //   613: ldc -88
    //   615: castore
    //   616: invokestatic 76	o/aw:ˊ	([C)Ljava/lang/String;
    //   619: invokevirtual 80	java/lang/String:intern	()Ljava/lang/String;
    //   622: astore 5
    //   624: goto +23 -> 647
    //   627: astore 4
    //   629: aload 4
    //   631: invokevirtual 174	java/lang/Throwable:getCause	()Ljava/lang/Throwable;
    //   634: astore 5
    //   636: aload 5
    //   638: ifnull +6 -> 644
    //   641: aload 5
    //   643: athrow
    //   644: aload 4
    //   646: athrow
    //   647: iconst_4
    //   648: bipush 42
    //   650: ldc -81
    //   652: invokestatic 181	o/O:ˋ	(IIC)Ljava/lang/Object;
    //   655: checkcast 183	java/lang/Class
    //   658: ldc -71
    //   660: iconst_2
    //   661: anewarray 183	java/lang/Class
    //   664: dup
    //   665: iconst_0
    //   666: ldc 41
    //   668: aastore
    //   669: dup
    //   670: iconst_1
    //   671: ldc 41
    //   673: aastore
    //   674: invokevirtual 189	java/lang/Class:getMethod	(Ljava/lang/String;[Ljava/lang/Class;)Ljava/lang/reflect/Method;
    //   677: aconst_null
    //   678: iconst_2
    //   679: anewarray 191	java/lang/Object
    //   682: dup
    //   683: iconst_0
    //   684: aload 4
    //   686: aastore
    //   687: dup
    //   688: iconst_1
    //   689: aload 5
    //   691: aastore
    //   692: invokevirtual 197	java/lang/reflect/Method:invoke	(Ljava/lang/Object;[Ljava/lang/Object;)Ljava/lang/Object;
    //   695: pop
    //   696: goto +112 -> 808
    //   699: iload_1
    //   700: iload_2
    //   701: if_icmpeq +6 -> 707
    //   704: goto +2023 -> 2727
    //   707: goto +1973 -> 2680
    //   710: aload_0
    //   711: getfield 199	o/aw:ʼ	Lo/aD;
    //   714: astore 4
    //   716: aload 5
    //   718: aload 4
    //   720: invokevirtual 203	o/az:setNestedScroll	(Lo/aD;)V
    //   723: aload_0
    //   724: getfield 54	o/aw:ॱॱ	Lo/az;
    //   727: astore 4
    //   729: aload 4
    //   731: ifnonnull +6 -> 737
    //   734: goto +357 -> 1091
    //   737: goto +72 -> 809
    //   740: iload_3
    //   741: tableswitch	default:+23->764, 0:+87->828, 1:+1993->2734
    //   764: goto +1970 -> 2734
    //   767: bipush 61
    //   769: istore_1
    //   770: goto +1927 -> 2697
    //   773: iconst_1
    //   774: istore_3
    //   775: goto -35 -> 740
    //   778: goto +30 -> 808
    //   781: iconst_0
    //   782: istore_1
    //   783: goto +72 -> 855
    //   786: aload_0
    //   787: invokespecial 205	android/support/design/widget/CoordinatorLayout:onFinishInflate	()V
    //   790: iconst_1
    //   791: istore_1
    //   792: aload_0
    //   793: invokevirtual 48	o/aw:getChildCount	()I
    //   796: istore_2
    //   797: iconst_1
    //   798: iload_2
    //   799: if_icmpgt +6 -> 805
    //   802: goto +1946 -> 2748
    //   805: goto +311 -> 1116
    //   808: return
    //   809: iconst_5
    //   810: istore_1
    //   811: goto +207 -> 1018
    //   814: aload 4
    //   816: instanceof 207
    //   819: ifeq +6 -> 825
    //   822: goto +303 -> 1125
    //   825: goto -126 -> 699
    //   828: getstatic 19	o/aw:ʽ	I
    //   831: bipush 25
    //   833: iadd
    //   834: istore_3
    //   835: iload_3
    //   836: sipush 128
    //   839: irem
    //   840: putstatic 21	o/aw:ˏॱ	I
    //   843: iload_3
    //   844: iconst_2
    //   845: irem
    //   846: ifne +6 -> 852
    //   849: goto +84 -> 933
    //   852: goto +1791 -> 2643
    //   855: iload_1
    //   856: tableswitch	default:+24->880, 0:+144->1000, 1:+196->1052
    //   880: goto +172 -> 1052
    //   883: goto +1687 -> 2570
    //   886: goto +1701 -> 2587
    //   889: aload_0
    //   890: aload 4
    //   892: checkcast 207	o/ar
    //   895: putfield 209	o/aw:ᐝ	Lo/ar;
    //   898: goto -199 -> 699
    //   901: invokestatic 214	o/vq:ˎ	()V
    //   904: goto -194 -> 710
    //   907: astore 4
    //   909: aload 4
    //   911: athrow
    //   912: aload_0
    //   913: iload_1
    //   914: invokevirtual 52	o/aw:getChildAt	(I)Landroid/view/View;
    //   917: astore 4
    //   919: aload 4
    //   921: instanceof 216
    //   924: ifeq +6 -> 930
    //   927: goto +936 -> 1863
    //   930: goto -157 -> 773
    //   933: goto +1710 -> 2643
    //   936: iconst_1
    //   937: istore_1
    //   938: goto -83 -> 855
    //   941: getstatic 19	o/aw:ʽ	I
    //   944: bipush 79
    //   946: iadd
    //   947: istore_1
    //   948: iload_1
    //   949: sipush 128
    //   952: irem
    //   953: putstatic 21	o/aw:ˏॱ	I
    //   956: iload_1
    //   957: iconst_2
    //   958: irem
    //   959: ifne +6 -> 965
    //   962: goto -79 -> 883
    //   965: goto +1605 -> 2570
    //   968: iconst_0
    //   969: istore_1
    //   970: goto +95 -> 1065
    //   973: getstatic 21	o/aw:ˏॱ	I
    //   976: bipush 119
    //   978: iadd
    //   979: istore_1
    //   980: iload_1
    //   981: sipush 128
    //   984: irem
    //   985: putstatic 19	o/aw:ʽ	I
    //   988: iload_1
    //   989: iconst_2
    //   990: irem
    //   991: ifeq +6 -> 997
    //   994: goto +21 -> 1015
    //   997: goto -96 -> 901
    //   1000: invokestatic 214	o/vq:ˎ	()V
    //   1003: goto +49 -> 1052
    //   1006: bipush 49
    //   1008: istore_1
    //   1009: goto +1688 -> 2697
    //   1012: goto -123 -> 889
    //   1015: goto -114 -> 901
    //   1018: iload_1
    //   1019: lookupswitch	default:+25->1044, 5:+1639->2658, 88:+91->1110
    //   1044: goto +1614 -> 2658
    //   1047: iconst_1
    //   1048: istore_1
    //   1049: goto +16 -> 1065
    //   1052: aload 5
    //   1054: aload 4
    //   1056: checkcast 218	o/ar$ˋ
    //   1059: invokevirtual 222	o/ar:setOnScrollStatusChangedListener	(Lo/ar$ˋ;)V
    //   1062: goto -284 -> 778
    //   1065: iload_1
    //   1066: tableswitch	default:+22->1088, 0:+31->1097, 1:+802->1868
    //   1088: goto +9 -> 1097
    //   1091: bipush 88
    //   1093: istore_1
    //   1094: goto -76 -> 1018
    //   1097: aload_0
    //   1098: getfield 54	o/aw:ॱॱ	Lo/az;
    //   1101: ifnonnull +6 -> 1107
    //   1104: goto -337 -> 767
    //   1107: goto -101 -> 1006
    //   1110: invokestatic 214	o/vq:ˎ	()V
    //   1113: goto +9 -> 1122
    //   1116: bipush 78
    //   1118: istore_3
    //   1119: goto +1495 -> 2614
    //   1122: goto +1536 -> 2658
    //   1125: getstatic 19	o/aw:ʽ	I
    //   1128: bipush 61
    //   1130: iadd
    //   1131: istore_3
    //   1132: iload_3
    //   1133: sipush 128
    //   1136: irem
    //   1137: putstatic 21	o/aw:ˏॱ	I
    //   1140: iload_3
    //   1141: iconst_2
    //   1142: irem
    //   1143: ifne +6 -> 1149
    //   1146: goto -134 -> 1012
    //   1149: goto -260 -> 889
    //   1152: bipush 13
    //   1154: newarray char
    //   1156: dup
    //   1157: iconst_0
    //   1158: ldc 62
    //   1160: castore
    //   1161: dup
    //   1162: iconst_1
    //   1163: ldc 63
    //   1165: castore
    //   1166: dup
    //   1167: iconst_2
    //   1168: ldc 64
    //   1170: castore
    //   1171: dup
    //   1172: iconst_3
    //   1173: ldc 65
    //   1175: castore
    //   1176: dup
    //   1177: iconst_4
    //   1178: ldc 66
    //   1180: castore
    //   1181: dup
    //   1182: iconst_5
    //   1183: ldc 67
    //   1185: castore
    //   1186: dup
    //   1187: bipush 6
    //   1189: ldc 68
    //   1191: castore
    //   1192: dup
    //   1193: bipush 7
    //   1195: ldc 69
    //   1197: castore
    //   1198: dup
    //   1199: bipush 8
    //   1201: ldc 70
    //   1203: castore
    //   1204: dup
    //   1205: bipush 9
    //   1207: ldc 71
    //   1209: castore
    //   1210: dup
    //   1211: bipush 10
    //   1213: ldc 72
    //   1215: castore
    //   1216: dup
    //   1217: bipush 11
    //   1219: ldc 73
    //   1221: castore
    //   1222: dup
    //   1223: bipush 12
    //   1225: ldc 74
    //   1227: castore
    //   1228: invokestatic 76	o/aw:ˊ	([C)Ljava/lang/String;
    //   1231: invokevirtual 80	java/lang/String:intern	()Ljava/lang/String;
    //   1234: astore 4
    //   1236: bipush 79
    //   1238: newarray char
    //   1240: dup
    //   1241: iconst_0
    //   1242: ldc -33
    //   1244: castore
    //   1245: dup
    //   1246: iconst_1
    //   1247: ldc -32
    //   1249: castore
    //   1250: dup
    //   1251: iconst_2
    //   1252: ldc -31
    //   1254: castore
    //   1255: dup
    //   1256: iconst_3
    //   1257: ldc -30
    //   1259: castore
    //   1260: dup
    //   1261: iconst_4
    //   1262: ldc -29
    //   1264: castore
    //   1265: dup
    //   1266: iconst_5
    //   1267: ldc -28
    //   1269: castore
    //   1270: dup
    //   1271: bipush 6
    //   1273: ldc -27
    //   1275: castore
    //   1276: dup
    //   1277: bipush 7
    //   1279: ldc -26
    //   1281: castore
    //   1282: dup
    //   1283: bipush 8
    //   1285: ldc -25
    //   1287: castore
    //   1288: dup
    //   1289: bipush 9
    //   1291: ldc -24
    //   1293: castore
    //   1294: dup
    //   1295: bipush 10
    //   1297: ldc -23
    //   1299: castore
    //   1300: dup
    //   1301: bipush 11
    //   1303: ldc -22
    //   1305: castore
    //   1306: dup
    //   1307: bipush 12
    //   1309: ldc -21
    //   1311: castore
    //   1312: dup
    //   1313: bipush 13
    //   1315: ldc -20
    //   1317: castore
    //   1318: dup
    //   1319: bipush 14
    //   1321: ldc -19
    //   1323: castore
    //   1324: dup
    //   1325: bipush 15
    //   1327: ldc -18
    //   1329: castore
    //   1330: dup
    //   1331: bipush 16
    //   1333: ldc -17
    //   1335: castore
    //   1336: dup
    //   1337: bipush 17
    //   1339: ldc -16
    //   1341: castore
    //   1342: dup
    //   1343: bipush 18
    //   1345: ldc -15
    //   1347: castore
    //   1348: dup
    //   1349: bipush 19
    //   1351: ldc -14
    //   1353: castore
    //   1354: dup
    //   1355: bipush 20
    //   1357: ldc -13
    //   1359: castore
    //   1360: dup
    //   1361: bipush 21
    //   1363: ldc -12
    //   1365: castore
    //   1366: dup
    //   1367: bipush 22
    //   1369: ldc -11
    //   1371: castore
    //   1372: dup
    //   1373: bipush 23
    //   1375: ldc -10
    //   1377: castore
    //   1378: dup
    //   1379: bipush 24
    //   1381: ldc -9
    //   1383: castore
    //   1384: dup
    //   1385: bipush 25
    //   1387: ldc -8
    //   1389: castore
    //   1390: dup
    //   1391: bipush 26
    //   1393: ldc -7
    //   1395: castore
    //   1396: dup
    //   1397: bipush 27
    //   1399: ldc -6
    //   1401: castore
    //   1402: dup
    //   1403: bipush 28
    //   1405: ldc -5
    //   1407: castore
    //   1408: dup
    //   1409: bipush 29
    //   1411: ldc -4
    //   1413: castore
    //   1414: dup
    //   1415: bipush 30
    //   1417: ldc -3
    //   1419: castore
    //   1420: dup
    //   1421: bipush 31
    //   1423: ldc -2
    //   1425: castore
    //   1426: dup
    //   1427: bipush 32
    //   1429: ldc -1
    //   1431: castore
    //   1432: dup
    //   1433: bipush 33
    //   1435: ldc_w 256
    //   1438: castore
    //   1439: dup
    //   1440: bipush 34
    //   1442: ldc_w 257
    //   1445: castore
    //   1446: dup
    //   1447: bipush 35
    //   1449: ldc_w 258
    //   1452: castore
    //   1453: dup
    //   1454: bipush 36
    //   1456: ldc_w 259
    //   1459: castore
    //   1460: dup
    //   1461: bipush 37
    //   1463: ldc_w 260
    //   1466: castore
    //   1467: dup
    //   1468: bipush 38
    //   1470: ldc_w 261
    //   1473: castore
    //   1474: dup
    //   1475: bipush 39
    //   1477: ldc_w 262
    //   1480: castore
    //   1481: dup
    //   1482: bipush 40
    //   1484: ldc_w 263
    //   1487: castore
    //   1488: dup
    //   1489: bipush 41
    //   1491: ldc_w 264
    //   1494: castore
    //   1495: dup
    //   1496: bipush 42
    //   1498: ldc_w 265
    //   1501: castore
    //   1502: dup
    //   1503: bipush 43
    //   1505: ldc_w 266
    //   1508: castore
    //   1509: dup
    //   1510: bipush 44
    //   1512: ldc_w 267
    //   1515: castore
    //   1516: dup
    //   1517: bipush 45
    //   1519: ldc_w 268
    //   1522: castore
    //   1523: dup
    //   1524: bipush 46
    //   1526: ldc_w 269
    //   1529: castore
    //   1530: dup
    //   1531: bipush 47
    //   1533: ldc_w 270
    //   1536: castore
    //   1537: dup
    //   1538: bipush 48
    //   1540: ldc_w 271
    //   1543: castore
    //   1544: dup
    //   1545: bipush 49
    //   1547: ldc_w 272
    //   1550: castore
    //   1551: dup
    //   1552: bipush 50
    //   1554: ldc_w 273
    //   1557: castore
    //   1558: dup
    //   1559: bipush 51
    //   1561: ldc_w 274
    //   1564: castore
    //   1565: dup
    //   1566: bipush 52
    //   1568: ldc_w 275
    //   1571: castore
    //   1572: dup
    //   1573: bipush 53
    //   1575: ldc_w 276
    //   1578: castore
    //   1579: dup
    //   1580: bipush 54
    //   1582: ldc_w 277
    //   1585: castore
    //   1586: dup
    //   1587: bipush 55
    //   1589: ldc_w 278
    //   1592: castore
    //   1593: dup
    //   1594: bipush 56
    //   1596: ldc_w 279
    //   1599: castore
    //   1600: dup
    //   1601: bipush 57
    //   1603: ldc_w 280
    //   1606: castore
    //   1607: dup
    //   1608: bipush 58
    //   1610: ldc_w 281
    //   1613: castore
    //   1614: dup
    //   1615: bipush 59
    //   1617: ldc_w 282
    //   1620: castore
    //   1621: dup
    //   1622: bipush 60
    //   1624: ldc_w 283
    //   1627: castore
    //   1628: dup
    //   1629: bipush 61
    //   1631: ldc_w 284
    //   1634: castore
    //   1635: dup
    //   1636: bipush 62
    //   1638: ldc_w 285
    //   1641: castore
    //   1642: dup
    //   1643: bipush 63
    //   1645: ldc_w 286
    //   1648: castore
    //   1649: dup
    //   1650: bipush 64
    //   1652: ldc_w 287
    //   1655: castore
    //   1656: dup
    //   1657: bipush 65
    //   1659: ldc_w 288
    //   1662: castore
    //   1663: dup
    //   1664: bipush 66
    //   1666: ldc_w 289
    //   1669: castore
    //   1670: dup
    //   1671: bipush 67
    //   1673: ldc_w 290
    //   1676: castore
    //   1677: dup
    //   1678: bipush 68
    //   1680: ldc_w 291
    //   1683: castore
    //   1684: dup
    //   1685: bipush 69
    //   1687: ldc_w 292
    //   1690: castore
    //   1691: dup
    //   1692: bipush 70
    //   1694: ldc_w 293
    //   1697: castore
    //   1698: dup
    //   1699: bipush 71
    //   1701: ldc_w 294
    //   1704: castore
    //   1705: dup
    //   1706: bipush 72
    //   1708: ldc_w 295
    //   1711: castore
    //   1712: dup
    //   1713: bipush 73
    //   1715: ldc_w 296
    //   1718: castore
    //   1719: dup
    //   1720: bipush 74
    //   1722: ldc_w 297
    //   1725: castore
    //   1726: dup
    //   1727: bipush 75
    //   1729: ldc_w 298
    //   1732: castore
    //   1733: dup
    //   1734: bipush 76
    //   1736: ldc_w 299
    //   1739: castore
    //   1740: dup
    //   1741: bipush 77
    //   1743: ldc_w 300
    //   1746: castore
    //   1747: dup
    //   1748: bipush 78
    //   1750: ldc_w 301
    //   1753: castore
    //   1754: invokestatic 76	o/aw:ˊ	([C)Ljava/lang/String;
    //   1757: invokevirtual 80	java/lang/String:intern	()Ljava/lang/String;
    //   1760: astore 5
    //   1762: goto +23 -> 1785
    //   1765: astore 4
    //   1767: aload 4
    //   1769: invokevirtual 174	java/lang/Throwable:getCause	()Ljava/lang/Throwable;
    //   1772: astore 5
    //   1774: aload 5
    //   1776: ifnull +6 -> 1782
    //   1779: aload 5
    //   1781: athrow
    //   1782: aload 4
    //   1784: athrow
    //   1785: iconst_4
    //   1786: bipush 42
    //   1788: ldc -81
    //   1790: invokestatic 181	o/O:ˋ	(IIC)Ljava/lang/Object;
    //   1793: checkcast 183	java/lang/Class
    //   1796: ldc -71
    //   1798: iconst_2
    //   1799: anewarray 183	java/lang/Class
    //   1802: dup
    //   1803: iconst_0
    //   1804: ldc 41
    //   1806: aastore
    //   1807: dup
    //   1808: iconst_1
    //   1809: ldc 41
    //   1811: aastore
    //   1812: invokevirtual 189	java/lang/Class:getMethod	(Ljava/lang/String;[Ljava/lang/Class;)Ljava/lang/reflect/Method;
    //   1815: aconst_null
    //   1816: iconst_2
    //   1817: anewarray 191	java/lang/Object
    //   1820: dup
    //   1821: iconst_0
    //   1822: aload 4
    //   1824: aastore
    //   1825: dup
    //   1826: iconst_1
    //   1827: aload 5
    //   1829: aastore
    //   1830: invokevirtual 197	java/lang/reflect/Method:invoke	(Ljava/lang/Object;[Ljava/lang/Object;)Ljava/lang/Object;
    //   1833: pop
    //   1834: aload_0
    //   1835: getfield 54	o/aw:ॱॱ	Lo/az;
    //   1838: astore 5
    //   1840: aload 5
    //   1842: ifnonnull +6 -> 1848
    //   1845: goto -872 -> 973
    //   1848: goto -1138 -> 710
    //   1851: aload_0
    //   1852: aload 4
    //   1854: checkcast 56	o/az
    //   1857: putfield 54	o/aw:ॱॱ	Lo/az;
    //   1860: goto +795 -> 2655
    //   1863: iconst_0
    //   1864: istore_3
    //   1865: goto -1125 -> 740
    //   1868: bipush 13
    //   1870: newarray char
    //   1872: dup
    //   1873: iconst_0
    //   1874: ldc 62
    //   1876: castore
    //   1877: dup
    //   1878: iconst_1
    //   1879: ldc 63
    //   1881: castore
    //   1882: dup
    //   1883: iconst_2
    //   1884: ldc 64
    //   1886: castore
    //   1887: dup
    //   1888: iconst_3
    //   1889: ldc 65
    //   1891: castore
    //   1892: dup
    //   1893: iconst_4
    //   1894: ldc 66
    //   1896: castore
    //   1897: dup
    //   1898: iconst_5
    //   1899: ldc 67
    //   1901: castore
    //   1902: dup
    //   1903: bipush 6
    //   1905: ldc 68
    //   1907: castore
    //   1908: dup
    //   1909: bipush 7
    //   1911: ldc 69
    //   1913: castore
    //   1914: dup
    //   1915: bipush 8
    //   1917: ldc 70
    //   1919: castore
    //   1920: dup
    //   1921: bipush 9
    //   1923: ldc 71
    //   1925: castore
    //   1926: dup
    //   1927: bipush 10
    //   1929: ldc 72
    //   1931: castore
    //   1932: dup
    //   1933: bipush 11
    //   1935: ldc 73
    //   1937: castore
    //   1938: dup
    //   1939: bipush 12
    //   1941: ldc 74
    //   1943: castore
    //   1944: invokestatic 76	o/aw:ˊ	([C)Ljava/lang/String;
    //   1947: invokevirtual 80	java/lang/String:intern	()Ljava/lang/String;
    //   1950: astore 4
    //   1952: bipush 77
    //   1954: newarray char
    //   1956: dup
    //   1957: iconst_0
    //   1958: ldc_w 302
    //   1961: castore
    //   1962: dup
    //   1963: iconst_1
    //   1964: ldc_w 303
    //   1967: castore
    //   1968: dup
    //   1969: iconst_2
    //   1970: ldc_w 304
    //   1973: castore
    //   1974: dup
    //   1975: iconst_3
    //   1976: ldc_w 305
    //   1979: castore
    //   1980: dup
    //   1981: iconst_4
    //   1982: ldc_w 306
    //   1985: castore
    //   1986: dup
    //   1987: iconst_5
    //   1988: ldc_w 307
    //   1991: castore
    //   1992: dup
    //   1993: bipush 6
    //   1995: ldc_w 308
    //   1998: castore
    //   1999: dup
    //   2000: bipush 7
    //   2002: ldc_w 309
    //   2005: castore
    //   2006: dup
    //   2007: bipush 8
    //   2009: ldc_w 310
    //   2012: castore
    //   2013: dup
    //   2014: bipush 9
    //   2016: ldc_w 311
    //   2019: castore
    //   2020: dup
    //   2021: bipush 10
    //   2023: ldc_w 312
    //   2026: castore
    //   2027: dup
    //   2028: bipush 11
    //   2030: ldc_w 313
    //   2033: castore
    //   2034: dup
    //   2035: bipush 12
    //   2037: ldc_w 314
    //   2040: castore
    //   2041: dup
    //   2042: bipush 13
    //   2044: ldc_w 315
    //   2047: castore
    //   2048: dup
    //   2049: bipush 14
    //   2051: ldc_w 316
    //   2054: castore
    //   2055: dup
    //   2056: bipush 15
    //   2058: ldc_w 317
    //   2061: castore
    //   2062: dup
    //   2063: bipush 16
    //   2065: ldc_w 318
    //   2068: castore
    //   2069: dup
    //   2070: bipush 17
    //   2072: ldc_w 319
    //   2075: castore
    //   2076: dup
    //   2077: bipush 18
    //   2079: ldc_w 320
    //   2082: castore
    //   2083: dup
    //   2084: bipush 19
    //   2086: ldc_w 321
    //   2089: castore
    //   2090: dup
    //   2091: bipush 20
    //   2093: ldc_w 322
    //   2096: castore
    //   2097: dup
    //   2098: bipush 21
    //   2100: ldc_w 323
    //   2103: castore
    //   2104: dup
    //   2105: bipush 22
    //   2107: ldc_w 324
    //   2110: castore
    //   2111: dup
    //   2112: bipush 23
    //   2114: ldc_w 325
    //   2117: castore
    //   2118: dup
    //   2119: bipush 24
    //   2121: ldc_w 326
    //   2124: castore
    //   2125: dup
    //   2126: bipush 25
    //   2128: ldc_w 327
    //   2131: castore
    //   2132: dup
    //   2133: bipush 26
    //   2135: ldc_w 328
    //   2138: castore
    //   2139: dup
    //   2140: bipush 27
    //   2142: ldc_w 329
    //   2145: castore
    //   2146: dup
    //   2147: bipush 28
    //   2149: ldc_w 330
    //   2152: castore
    //   2153: dup
    //   2154: bipush 29
    //   2156: ldc_w 331
    //   2159: castore
    //   2160: dup
    //   2161: bipush 30
    //   2163: ldc_w 332
    //   2166: castore
    //   2167: dup
    //   2168: bipush 31
    //   2170: ldc_w 333
    //   2173: castore
    //   2174: dup
    //   2175: bipush 32
    //   2177: ldc_w 334
    //   2180: castore
    //   2181: dup
    //   2182: bipush 33
    //   2184: ldc_w 335
    //   2187: castore
    //   2188: dup
    //   2189: bipush 34
    //   2191: ldc_w 336
    //   2194: castore
    //   2195: dup
    //   2196: bipush 35
    //   2198: ldc_w 337
    //   2201: castore
    //   2202: dup
    //   2203: bipush 36
    //   2205: ldc_w 338
    //   2208: castore
    //   2209: dup
    //   2210: bipush 37
    //   2212: ldc_w 339
    //   2215: castore
    //   2216: dup
    //   2217: bipush 38
    //   2219: ldc_w 340
    //   2222: castore
    //   2223: dup
    //   2224: bipush 39
    //   2226: ldc_w 341
    //   2229: castore
    //   2230: dup
    //   2231: bipush 40
    //   2233: ldc_w 342
    //   2236: castore
    //   2237: dup
    //   2238: bipush 41
    //   2240: ldc_w 343
    //   2243: castore
    //   2244: dup
    //   2245: bipush 42
    //   2247: ldc_w 344
    //   2250: castore
    //   2251: dup
    //   2252: bipush 43
    //   2254: ldc_w 345
    //   2257: castore
    //   2258: dup
    //   2259: bipush 44
    //   2261: ldc_w 346
    //   2264: castore
    //   2265: dup
    //   2266: bipush 45
    //   2268: ldc_w 347
    //   2271: castore
    //   2272: dup
    //   2273: bipush 46
    //   2275: ldc_w 348
    //   2278: castore
    //   2279: dup
    //   2280: bipush 47
    //   2282: ldc_w 349
    //   2285: castore
    //   2286: dup
    //   2287: bipush 48
    //   2289: ldc_w 350
    //   2292: castore
    //   2293: dup
    //   2294: bipush 49
    //   2296: ldc_w 351
    //   2299: castore
    //   2300: dup
    //   2301: bipush 50
    //   2303: ldc_w 352
    //   2306: castore
    //   2307: dup
    //   2308: bipush 51
    //   2310: ldc_w 353
    //   2313: castore
    //   2314: dup
    //   2315: bipush 52
    //   2317: ldc_w 354
    //   2320: castore
    //   2321: dup
    //   2322: bipush 53
    //   2324: ldc_w 355
    //   2327: castore
    //   2328: dup
    //   2329: bipush 54
    //   2331: ldc_w 356
    //   2334: castore
    //   2335: dup
    //   2336: bipush 55
    //   2338: ldc_w 357
    //   2341: castore
    //   2342: dup
    //   2343: bipush 56
    //   2345: ldc_w 358
    //   2348: castore
    //   2349: dup
    //   2350: bipush 57
    //   2352: ldc_w 359
    //   2355: castore
    //   2356: dup
    //   2357: bipush 58
    //   2359: ldc_w 360
    //   2362: castore
    //   2363: dup
    //   2364: bipush 59
    //   2366: ldc_w 361
    //   2369: castore
    //   2370: dup
    //   2371: bipush 60
    //   2373: ldc_w 362
    //   2376: castore
    //   2377: dup
    //   2378: bipush 61
    //   2380: ldc_w 363
    //   2383: castore
    //   2384: dup
    //   2385: bipush 62
    //   2387: ldc_w 364
    //   2390: castore
    //   2391: dup
    //   2392: bipush 63
    //   2394: ldc_w 365
    //   2397: castore
    //   2398: dup
    //   2399: bipush 64
    //   2401: ldc_w 366
    //   2404: castore
    //   2405: dup
    //   2406: bipush 65
    //   2408: ldc_w 367
    //   2411: castore
    //   2412: dup
    //   2413: bipush 66
    //   2415: ldc_w 368
    //   2418: castore
    //   2419: dup
    //   2420: bipush 67
    //   2422: ldc_w 369
    //   2425: castore
    //   2426: dup
    //   2427: bipush 68
    //   2429: ldc_w 370
    //   2432: castore
    //   2433: dup
    //   2434: bipush 69
    //   2436: ldc_w 371
    //   2439: castore
    //   2440: dup
    //   2441: bipush 70
    //   2443: ldc_w 372
    //   2446: castore
    //   2447: dup
    //   2448: bipush 71
    //   2450: ldc_w 373
    //   2453: castore
    //   2454: dup
    //   2455: bipush 72
    //   2457: ldc_w 374
    //   2460: castore
    //   2461: dup
    //   2462: bipush 73
    //   2464: ldc_w 375
    //   2467: castore
    //   2468: dup
    //   2469: bipush 74
    //   2471: ldc_w 376
    //   2474: castore
    //   2475: dup
    //   2476: bipush 75
    //   2478: ldc_w 377
    //   2481: castore
    //   2482: dup
    //   2483: bipush 76
    //   2485: ldc_w 378
    //   2488: castore
    //   2489: invokestatic 76	o/aw:ˊ	([C)Ljava/lang/String;
    //   2492: invokevirtual 80	java/lang/String:intern	()Ljava/lang/String;
    //   2495: astore 5
    //   2497: goto +23 -> 2520
    //   2500: astore 4
    //   2502: aload 4
    //   2504: invokevirtual 174	java/lang/Throwable:getCause	()Ljava/lang/Throwable;
    //   2507: astore 5
    //   2509: aload 5
    //   2511: ifnull +6 -> 2517
    //   2514: aload 5
    //   2516: athrow
    //   2517: aload 4
    //   2519: athrow
    //   2520: iconst_4
    //   2521: bipush 42
    //   2523: ldc -81
    //   2525: invokestatic 181	o/O:ˋ	(IIC)Ljava/lang/Object;
    //   2528: checkcast 183	java/lang/Class
    //   2531: ldc -71
    //   2533: iconst_2
    //   2534: anewarray 183	java/lang/Class
    //   2537: dup
    //   2538: iconst_0
    //   2539: ldc 41
    //   2541: aastore
    //   2542: dup
    //   2543: iconst_1
    //   2544: ldc 41
    //   2546: aastore
    //   2547: invokevirtual 189	java/lang/Class:getMethod	(Ljava/lang/String;[Ljava/lang/Class;)Ljava/lang/reflect/Method;
    //   2550: aconst_null
    //   2551: iconst_2
    //   2552: anewarray 191	java/lang/Object
    //   2555: dup
    //   2556: iconst_0
    //   2557: aload 4
    //   2559: aastore
    //   2560: dup
    //   2561: iconst_1
    //   2562: aload 5
    //   2564: aastore
    //   2565: invokevirtual 197	java/lang/reflect/Method:invoke	(Ljava/lang/Object;[Ljava/lang/Object;)Ljava/lang/Object;
    //   2568: pop
    //   2569: return
    //   2570: aload_0
    //   2571: getfield 54	o/aw:ॱॱ	Lo/az;
    //   2574: astore 4
    //   2576: aload 4
    //   2578: ifnonnull +6 -> 2584
    //   2581: goto -1800 -> 781
    //   2584: goto -1648 -> 936
    //   2587: getstatic 21	o/aw:ˏॱ	I
    //   2590: bipush 83
    //   2592: iadd
    //   2593: istore_1
    //   2594: iload_1
    //   2595: sipush 128
    //   2598: irem
    //   2599: putstatic 19	o/aw:ʽ	I
    //   2602: iload_1
    //   2603: iconst_2
    //   2604: irem
    //   2605: ifeq +6 -> 2611
    //   2608: goto -1822 -> 786
    //   2611: goto +143 -> 2754
    //   2614: iload_3
    //   2615: lookupswitch	default:+25->2640, 70:+-1703->912, 78:+65->2680
    //   2640: goto +40 -> 2680
    //   2643: aload_0
    //   2644: aload 4
    //   2646: checkcast 216	o/aD
    //   2649: putfield 199	o/aw:ʼ	Lo/aD;
    //   2652: goto -1953 -> 699
    //   2655: goto -1956 -> 699
    //   2658: aload 4
    //   2660: invokevirtual 381	o/az:ॱ	()V
    //   2663: aload_0
    //   2664: getfield 209	o/aw:ᐝ	Lo/ar;
    //   2667: astore 5
    //   2669: aload 5
    //   2671: ifnull +6 -> 2677
    //   2674: goto -1733 -> 941
    //   2677: goto -2674 -> 3
    //   2680: aload_0
    //   2681: getfield 199	o/aw:ʼ	Lo/aD;
    //   2684: astore 4
    //   2686: aload 4
    //   2688: ifnonnull +6 -> 2694
    //   2691: goto -1644 -> 1047
    //   2694: goto -1726 -> 968
    //   2697: iload_1
    //   2698: lookupswitch	default:+26->2724, 49:+-1546->1152, 61:+-2692->6
    //   2724: goto -2718 -> 6
    //   2727: iload_1
    //   2728: iconst_1
    //   2729: iadd
    //   2730: istore_1
    //   2731: goto -1819 -> 912
    //   2734: aload 4
    //   2736: instanceof 56
    //   2739: ifeq +6 -> 2745
    //   2742: goto -891 -> 1851
    //   2745: goto -1931 -> 814
    //   2748: bipush 70
    //   2750: istore_3
    //   2751: goto -137 -> 2614
    //   2754: aload_0
    //   2755: invokespecial 205	android/support/design/widget/CoordinatorLayout:onFinishInflate	()V
    //   2758: iconst_0
    //   2759: istore_1
    //   2760: aload_0
    //   2761: invokevirtual 48	o/aw:getChildCount	()I
    //   2764: istore_2
    //   2765: iload_2
    //   2766: ifgt +6 -> 2772
    //   2769: goto -1857 -> 912
    //   2772: goto -92 -> 2680
    // Local variable table:
    //   start	length	slot	name	signature
    //   0	2775	0	this	aw
    //   699	2061	1	i	int
    //   700	2066	2	j	int
    //   740	2011	3	k	int
    //   88	1	4	str1	String
    //   627	58	4	localObject1	Object
    //   714	177	4	localObject2	Object
    //   907	3	4	localException	Exception
    //   917	318	4	localObject3	Object
    //   1765	88	4	localObject4	Object
    //   1950	1	4	str2	String
    //   2500	58	4	localObject5	Object
    //   2574	161	4	localObject6	Object
    //   622	2048	5	localObject7	Object
    // Exception table:
    //   from	to	target	type
    //   647	696	627	finally
    //   710	716	907	java/lang/Exception
    //   716	729	907	java/lang/Exception
    //   1110	1113	907	java/lang/Exception
    //   2680	2686	907	java/lang/Exception
    //   1785	1834	1765	finally
    //   2520	2569	2500	finally
  }
  
  /* Error */
  public final void setShowShadow(boolean paramBoolean)
  {
    // Byte code:
    //   0: goto +96 -> 96
    //   3: bipush 93
    //   5: istore_2
    //   6: goto +148 -> 154
    //   9: iload_2
    //   10: lookupswitch	default:+26->36, 2:+92->102, 23:+143->153
    //   36: goto +66 -> 102
    //   39: getstatic 19	o/aw:ʽ	I
    //   42: bipush 75
    //   44: iadd
    //   45: istore_2
    //   46: iload_2
    //   47: sipush 128
    //   50: irem
    //   51: putstatic 21	o/aw:ˏॱ	I
    //   54: iload_2
    //   55: iconst_2
    //   56: irem
    //   57: ifne +6 -> 63
    //   60: goto +39 -> 99
    //   63: goto +21 -> 84
    //   66: new 385	java/lang/NullPointerException
    //   69: dup
    //   70: invokespecial 387	java/lang/NullPointerException:<init>	()V
    //   73: athrow
    //   74: astore_3
    //   75: aload_3
    //   76: athrow
    //   77: aload_0
    //   78: invokespecial 389	o/aw:ᐝ	()V
    //   81: goto -42 -> 39
    //   84: return
    //   85: iconst_2
    //   86: istore_2
    //   87: goto -78 -> 9
    //   90: astore_3
    //   91: aload_3
    //   92: athrow
    //   93: goto -16 -> 77
    //   96: goto +87 -> 183
    //   99: goto -15 -> 84
    //   102: getstatic 21	o/aw:ˏॱ	I
    //   105: istore_2
    //   106: iload_2
    //   107: bipush 117
    //   109: iadd
    //   110: istore_2
    //   111: iload_2
    //   112: sipush 128
    //   115: irem
    //   116: putstatic 19	o/aw:ʽ	I
    //   119: iload_2
    //   120: iconst_2
    //   121: irem
    //   122: ifeq +6 -> 128
    //   125: goto -32 -> 93
    //   128: goto -51 -> 77
    //   131: bipush 80
    //   133: istore_2
    //   134: goto +20 -> 154
    //   137: bipush 23
    //   139: istore_2
    //   140: goto -131 -> 9
    //   143: iload_1
    //   144: ifeq +6 -> 150
    //   147: goto -62 -> 85
    //   150: goto -13 -> 137
    //   153: return
    //   154: iload_2
    //   155: lookupswitch	default:+25->180, 80:+-89->66, 93:+-12->143
    //   180: goto -37 -> 143
    //   183: getstatic 21	o/aw:ˏॱ	I
    //   186: iconst_1
    //   187: iadd
    //   188: istore_2
    //   189: iload_2
    //   190: sipush 128
    //   193: irem
    //   194: putstatic 19	o/aw:ʽ	I
    //   197: iload_2
    //   198: iconst_2
    //   199: irem
    //   200: ifeq +6 -> 206
    //   203: goto -72 -> 131
    //   206: goto -203 -> 3
    // Local variable table:
    //   start	length	slot	name	signature
    //   0	209	0	this	aw
    //   0	209	1	paramBoolean	boolean
    //   5	195	2	i	int
    //   74	2	3	localException1	Exception
    //   90	2	3	localException2	Exception
    // Exception table:
    //   from	to	target	type
    //   102	106	74	java/lang/Exception
    //   111	119	90	java/lang/Exception
  }
}
