package o;

public final class B
  extends x
{
  private static int ߺ = 184;
  private static char[] ॱˈ;
  private static int ॱˉ = 0;
  private static boolean ॱˌ;
  private static boolean ॱˑ;
  private static int ॱـ = 1;
  
  static
  {
    ॱˌ = true;
    ॱˑ = true;
    ॱˈ = new char[] { 283, 295, 294, 300, 285, 304, 289, 292, 266, 299, 296, 302, 268 };
  }
  
  /* Error */
  public B(android.content.Context paramContext, String paramString1, String paramString2, String paramString3)
  {
    // Byte code:
    //   0: goto +9 -> 9
    //   3: astore_1
    //   4: aload_1
    //   5: athrow
    //   6: astore_1
    //   7: aload_1
    //   8: athrow
    //   9: aconst_null
    //   10: aconst_null
    //   11: bipush 7
    //   13: newarray byte
    //   15: dup
    //   16: iconst_0
    //   17: ldc 46
    //   19: bastore
    //   20: dup
    //   21: iconst_1
    //   22: ldc 47
    //   24: bastore
    //   25: dup
    //   26: iconst_2
    //   27: ldc 48
    //   29: bastore
    //   30: dup
    //   31: iconst_3
    //   32: ldc 46
    //   34: bastore
    //   35: dup
    //   36: iconst_4
    //   37: ldc 49
    //   39: bastore
    //   40: dup
    //   41: iconst_5
    //   42: ldc 50
    //   44: bastore
    //   45: dup
    //   46: bipush 6
    //   48: ldc 51
    //   50: bastore
    //   51: bipush 127
    //   53: invokestatic 55	o/B:ˋ	([C[I[BI)Ljava/lang/String;
    //   56: astore 5
    //   58: aload 5
    //   60: invokevirtual 61	java/lang/String:intern	()Ljava/lang/String;
    //   63: astore 5
    //   65: aload_1
    //   66: aload 5
    //   68: invokestatic 67	o/vq:ˎ	(Ljava/lang/Object;Ljava/lang/String;)V
    //   71: aload_2
    //   72: aconst_null
    //   73: aconst_null
    //   74: bipush 8
    //   76: newarray byte
    //   78: dup
    //   79: iconst_0
    //   80: ldc 68
    //   82: bastore
    //   83: dup
    //   84: iconst_1
    //   85: ldc 48
    //   87: bastore
    //   88: dup
    //   89: iconst_2
    //   90: ldc 69
    //   92: bastore
    //   93: dup
    //   94: iconst_3
    //   95: ldc 48
    //   97: bastore
    //   98: dup
    //   99: iconst_4
    //   100: ldc 70
    //   102: bastore
    //   103: dup
    //   104: iconst_5
    //   105: ldc 46
    //   107: bastore
    //   108: dup
    //   109: bipush 6
    //   111: ldc 71
    //   113: bastore
    //   114: dup
    //   115: bipush 7
    //   117: ldc 46
    //   119: bastore
    //   120: bipush 127
    //   122: invokestatic 55	o/B:ˋ	([C[I[BI)Ljava/lang/String;
    //   125: invokevirtual 61	java/lang/String:intern	()Ljava/lang/String;
    //   128: invokestatic 67	o/vq:ˎ	(Ljava/lang/Object;Ljava/lang/String;)V
    //   131: aload_3
    //   132: aconst_null
    //   133: aconst_null
    //   134: bipush 10
    //   136: newarray byte
    //   138: dup
    //   139: iconst_0
    //   140: ldc 68
    //   142: bastore
    //   143: dup
    //   144: iconst_1
    //   145: ldc 48
    //   147: bastore
    //   148: dup
    //   149: iconst_2
    //   150: ldc 69
    //   152: bastore
    //   153: dup
    //   154: iconst_3
    //   155: ldc 46
    //   157: bastore
    //   158: dup
    //   159: iconst_4
    //   160: ldc 49
    //   162: bastore
    //   163: dup
    //   164: iconst_5
    //   165: ldc 48
    //   167: bastore
    //   168: dup
    //   169: bipush 6
    //   171: ldc 46
    //   173: bastore
    //   174: dup
    //   175: bipush 7
    //   177: ldc 49
    //   179: bastore
    //   180: dup
    //   181: bipush 8
    //   183: ldc 50
    //   185: bastore
    //   186: dup
    //   187: bipush 9
    //   189: ldc 51
    //   191: bastore
    //   192: bipush 127
    //   194: invokestatic 55	o/B:ˋ	([C[I[BI)Ljava/lang/String;
    //   197: invokevirtual 61	java/lang/String:intern	()Ljava/lang/String;
    //   200: invokestatic 67	o/vq:ˎ	(Ljava/lang/Object;Ljava/lang/String;)V
    //   203: aload 4
    //   205: aconst_null
    //   206: aconst_null
    //   207: bipush 12
    //   209: newarray byte
    //   211: dup
    //   212: iconst_0
    //   213: ldc 46
    //   215: bastore
    //   216: dup
    //   217: iconst_1
    //   218: ldc 47
    //   220: bastore
    //   221: dup
    //   222: iconst_2
    //   223: ldc 48
    //   225: bastore
    //   226: dup
    //   227: iconst_3
    //   228: ldc 72
    //   230: bastore
    //   231: dup
    //   232: iconst_4
    //   233: ldc 48
    //   235: bastore
    //   236: dup
    //   237: iconst_5
    //   238: ldc 73
    //   240: bastore
    //   241: dup
    //   242: bipush 6
    //   244: ldc 71
    //   246: bastore
    //   247: dup
    //   248: bipush 7
    //   250: ldc 46
    //   252: bastore
    //   253: dup
    //   254: bipush 8
    //   256: ldc 71
    //   258: bastore
    //   259: dup
    //   260: bipush 9
    //   262: ldc 68
    //   264: bastore
    //   265: dup
    //   266: bipush 10
    //   268: ldc 50
    //   270: bastore
    //   271: dup
    //   272: bipush 11
    //   274: ldc 74
    //   276: bastore
    //   277: bipush 127
    //   279: invokestatic 55	o/B:ˋ	([C[I[BI)Ljava/lang/String;
    //   282: invokevirtual 61	java/lang/String:intern	()Ljava/lang/String;
    //   285: invokestatic 67	o/vq:ˎ	(Ljava/lang/Object;Ljava/lang/String;)V
    //   288: aload_0
    //   289: aload_1
    //   290: invokespecial 77	o/x:<init>	(Landroid/content/Context;)V
    //   293: aload_0
    //   294: aload_2
    //   295: checkcast 79	java/lang/CharSequence
    //   298: invokevirtual 83	o/B:ˊ	(Ljava/lang/CharSequence;)Lo/ᐸ$If;
    //   301: pop
    //   302: aload_0
    //   303: aload_3
    //   304: checkcast 79	java/lang/CharSequence
    //   307: invokevirtual 85	o/B:ˋ	(Ljava/lang/CharSequence;)Lo/ᐸ$If;
    //   310: pop
    //   311: aload_0
    //   312: aload 4
    //   314: checkcast 79	java/lang/CharSequence
    //   317: invokevirtual 87	o/B:ˎ	(Ljava/lang/CharSequence;)Lo/ᐸ$If;
    //   320: pop
    //   321: return
    // Local variable table:
    //   start	length	slot	name	signature
    //   0	322	0	this	B
    //   0	322	1	paramContext	android.content.Context
    //   0	322	2	paramString1	String
    //   0	322	3	paramString2	String
    //   0	322	4	paramString3	String
    //   56	11	5	str	String
    // Exception table:
    //   from	to	target	type
    //   65	71	3	java/lang/Exception
    //   71	321	3	java/lang/Exception
    //   9	58	6	java/lang/Exception
    //   58	65	6	java/lang/Exception
  }
  
  private static String ˋ(char[] paramArrayOfChar, int[] paramArrayOfInt, byte[] paramArrayOfByte, int paramInt)
  {
    break label260;
    paramInt = null.length;
    return paramArrayOfChar;
    for (;;)
    {
      label8:
      label35:
      int i;
      int m;
      switch (j)
      {
      default: 
        break label222;
        if (i < m) {
          break;
        }
        break;
      }
      for (;;)
      {
        i = j;
        break label35;
        label55:
        i = 0;
        break label365;
        label61:
        i = ॱˉ + 67;
        ॱـ = i % 128;
        if (i % 2 != 0)
        {
          break label101;
          i = j;
          break label352;
          label98:
          break label263;
          label101:
          i = 39;
        }
        label123:
        label167:
        char[] arrayOfChar;
        int k;
        for (;;)
        {
          m = paramArrayOfInt.length;
          paramArrayOfChar = new char[m];
          i = 0;
          break label263;
          paramArrayOfChar = new String(paramArrayOfInt);
          switch (i)
          {
          case 88: 
          default: 
            break label493;
            m = paramArrayOfChar.length;
            paramArrayOfInt = new char[m];
            i = 0;
            break label352;
            paramArrayOfChar[i] = ((char)(arrayOfChar[(paramArrayOfByte[(m - 1 - i)] + paramInt)] - k));
            j = i + 1;
            break label407;
            return new String(paramArrayOfChar);
            label222:
            paramArrayOfChar[i] = ((char)(arrayOfChar[(paramArrayOfInt[(m - 1 - i)] - paramInt)] - k));
            i += 1;
            break label98;
            label253:
            i = 52;
            break label506;
            label260:
            break label289;
            label263:
            if (i < m) {
              break label500;
            }
            break label539;
            label289:
            do
            {
              i = 1;
              break label365;
              i = 88;
              break;
              arrayOfChar = ॱˈ;
              k = ߺ;
            } while (ॱˌ);
            break label55;
            try
            {
              boolean bool = ॱˑ;
              if (bool) {
                break label167;
              }
            }
            catch (Exception paramArrayOfChar)
            {
              throw paramArrayOfChar;
            }
          }
        }
        paramInt = ॱˉ + 5;
        ॱـ = paramInt % 128;
        if (paramInt % 2 == 0) {
          break;
        }
        return paramArrayOfChar;
        for (;;)
        {
          label352:
          if (i >= m)
          {
            break label123;
            switch (i)
            {
            case 0: 
            default: 
              break label437;
              return new String(paramArrayOfChar);
              i = j;
              break;
              i = ॱـ + 85;
              ॱˉ = i % 128;
              if (i % 2 != 0) {
                break label253;
              }
              break;
            case 1: 
              label365:
              label407:
              label437:
              m = paramArrayOfByte.length;
              paramArrayOfChar = new char[m];
              i = 0;
              break;
              i = 85;
              break;
            }
          }
          paramArrayOfInt[i] = ((char)(arrayOfChar[(paramArrayOfChar[(m - 1 - i)] - paramInt)] - k));
          j = i + 1;
          break label61;
          label493:
          i = j;
        }
        label500:
        j = 0;
        break label8;
        label506:
        switch (i)
        {
        }
      }
      label539:
      int j = 1;
    }
  }
}
