package o;

import java.io.IOException;
import java.lang.reflect.Array;
import java.util.Iterator;
import java.util.Map;
import java.util.Map.Entry;
import java.util.Set;

abstract class CA<T>
{
  CA() {}
  
  abstract void ˊ(CF paramCF, T paramT);
  
  final CA<Object> ˋ()
  {
    new CA()
    {
      void ˊ(CF paramAnonymousCF, Object paramAnonymousObject)
      {
        if (paramAnonymousObject == null) {
          return;
        }
        int i = 0;
        int j = Array.getLength(paramAnonymousObject);
        while (i < j)
        {
          CA.this.ˊ(paramAnonymousCF, Array.get(paramAnonymousObject, i));
          i += 1;
        }
      }
    };
  }
  
  final CA<Iterable<T>> ˎ()
  {
    new CA()
    {
      void ˎ(CF paramAnonymousCF, Iterable<T> paramAnonymousIterable)
      {
        if (paramAnonymousIterable == null) {
          return;
        }
        paramAnonymousIterable = paramAnonymousIterable.iterator();
        while (paramAnonymousIterable.hasNext())
        {
          Object localObject = paramAnonymousIterable.next();
          CA.this.ˊ(paramAnonymousCF, localObject);
        }
      }
    };
  }
  
  static final class AUx<T>
    extends CA<T>
  {
    private final Cy<T, String> ˊ;
    private final boolean ॱ;
    
    AUx(Cy<T, String> paramCy, boolean paramBoolean)
    {
      this.ˊ = paramCy;
      this.ॱ = paramBoolean;
    }
    
    void ˊ(CF paramCF, T paramT)
    {
      if (paramT == null) {
        return;
      }
      paramCF.ˊ((String)this.ˊ.ˎ(paramT), null, this.ॱ);
    }
  }
  
  static final class IF<T>
    extends CA<T>
  {
    private final boolean ˊ;
    private final String ˎ;
    private final Cy<T, String> ˏ;
    
    IF(String paramString, Cy<T, String> paramCy, boolean paramBoolean)
    {
      this.ˎ = ((String)CM.ˋ(paramString, "name == null"));
      this.ˏ = paramCy;
      this.ˊ = paramBoolean;
    }
    
    void ˊ(CF paramCF, T paramT)
    {
      if (paramT == null) {
        throw new IllegalArgumentException("Path parameter \"" + this.ˎ + "\" value must not be null.");
      }
      paramCF.ˎ(this.ˎ, (String)this.ˏ.ˎ(paramT), this.ˊ);
    }
  }
  
  static final class If<T>
    extends CA<T>
  {
    private final boolean ˋ;
    private final String ˎ;
    private final Cy<T, String> ˏ;
    
    If(String paramString, Cy<T, String> paramCy, boolean paramBoolean)
    {
      this.ˎ = ((String)CM.ˋ(paramString, "name == null"));
      this.ˏ = paramCy;
      this.ˋ = paramBoolean;
    }
    
    void ˊ(CF paramCF, T paramT)
    {
      if (paramT == null) {
        return;
      }
      paramT = (String)this.ˏ.ˎ(paramT);
      if (paramT == null) {
        return;
      }
      paramCF.ˋ(this.ˎ, paramT, this.ˋ);
    }
  }
  
  static final class aux<T>
    extends CA<Map<String, T>>
  {
    private static byte[] ʼ;
    private static int ʽ;
    private static int ˎ;
    private static int ˏ = -1717136575;
    private static int ॱ;
    private static short[] ॱॱ;
    private static int ᐝ = 0;
    private final String ˊ;
    private final Cy<T, xH> ˋ;
    
    static
    {
      ʽ = 1;
      ˎ = 44;
      ʼ = new byte[] { -16, 26, -69, 85, -28, 27, -81, 88, -88, -31, 19, 80, 88, -86, -89, 66, -87, 80, -93, -20, 31, -96, 91, -30, 3, -83, -66, -66, -5, 87, -9, 68, -86, 27, -2, 83, 89, 22, -21, -96, 89, 91, -69, 6, -28, 80, -89, 87, 30, -20, -81, -89, 85, 88, -67, 86, -81, 92, 19, -32, 95, -92, 29, -4, 82, 65, 65 };
      ॱ = 158716751;
    }
    
    aux(Cy<T, xH> paramCy, String paramString) {}
    
    /* Error */
    private static String ˏ(short paramShort, int paramInt1, byte paramByte, int paramInt2, int paramInt3)
    {
      // Byte code:
      //   0: goto +99 -> 99
      //   3: astore 8
      //   5: aload 8
      //   7: athrow
      //   8: iconst_1
      //   9: istore 6
      //   11: goto +50 -> 61
      //   14: iload 4
      //   16: ifle +6 -> 22
      //   19: goto +344 -> 363
      //   22: goto +479 -> 501
      //   25: getstatic 27	o/CA$aux:ʽ	I
      //   28: bipush 57
      //   30: iadd
      //   31: istore 4
      //   33: iload 4
      //   35: sipush 128
      //   38: irem
      //   39: putstatic 25	o/CA$aux:ᐝ	I
      //   42: iload 4
      //   44: iconst_2
      //   45: irem
      //   46: ifeq +6 -> 52
      //   49: goto +175 -> 224
      //   52: goto +257 -> 309
      //   55: aload 8
      //   57: invokevirtual 103	java/lang/StringBuilder:toString	()Ljava/lang/String;
      //   60: areturn
      //   61: iload 6
      //   63: tableswitch	default:+21->84, 0:+-8->55, 1:+416->479
      //   84: goto -29 -> 55
      //   87: iconst_0
      //   88: istore 6
      //   90: goto +418 -> 508
      //   93: iconst_1
      //   94: istore 6
      //   96: goto +412 -> 508
      //   99: goto +271 -> 370
      //   102: iload 6
      //   104: ifeq +6 -> 110
      //   107: goto -82 -> 25
      //   110: goto -96 -> 14
      //   113: getstatic 25	o/CA$aux:ᐝ	I
      //   116: bipush 37
      //   118: iadd
      //   119: istore 4
      //   121: iload 4
      //   123: sipush 128
      //   126: irem
      //   127: putstatic 27	o/CA$aux:ʽ	I
      //   130: iload 4
      //   132: iconst_2
      //   133: irem
      //   134: ifne +6 -> 140
      //   137: goto +278 -> 415
      //   140: goto +51 -> 191
      //   143: iload_1
      //   144: iload 4
      //   146: iadd
      //   147: iconst_2
      //   148: isub
      //   149: iload 7
      //   151: iadd
      //   152: iload 6
      //   154: iadd
      //   155: istore_1
      //   156: getstatic 80	o/CA$aux:ॱ	I
      //   159: istore 6
      //   161: iload 6
      //   163: iload_3
      //   164: iadd
      //   165: i2c
      //   166: istore 5
      //   168: aload 8
      //   170: iload 5
      //   172: invokevirtual 107	java/lang/StringBuilder:append	(C)Ljava/lang/StringBuilder;
      //   175: pop
      //   176: iconst_1
      //   177: istore_3
      //   178: iload 5
      //   180: istore 7
      //   182: goto +90 -> 272
      //   185: iconst_1
      //   186: istore 6
      //   188: goto -86 -> 102
      //   191: getstatic 77	o/CA$aux:ʼ	[B
      //   194: getstatic 83	o/CA$aux:ˏ	I
      //   197: iload_1
      //   198: iadd
      //   199: baload
      //   200: istore 4
      //   202: getstatic 29	o/CA$aux:ˎ	I
      //   205: istore 7
      //   207: iload 4
      //   209: iload 7
      //   211: iadd
      //   212: i2b
      //   213: istore 4
      //   215: goto +383 -> 598
      //   218: iconst_0
      //   219: istore 6
      //   221: goto -119 -> 102
      //   224: goto +85 -> 309
      //   227: iload 6
      //   229: lookupswitch	default:+27->256, 22:+-11->218, 52:+220->449
      //   256: goto -38 -> 218
      //   259: bipush 22
      //   261: istore 6
      //   263: goto -36 -> 227
      //   266: iconst_0
      //   267: istore 6
      //   269: goto -208 -> 61
      //   272: iload_3
      //   273: iload 4
      //   275: if_icmpge +6 -> 281
      //   278: goto -270 -> 8
      //   281: goto -15 -> 266
      //   284: iconst_1
      //   285: istore 6
      //   287: goto -144 -> 143
      //   290: getstatic 109	o/CA$aux:ॱॱ	[S
      //   293: getstatic 83	o/CA$aux:ˏ	I
      //   296: iload_1
      //   297: iadd
      //   298: saload
      //   299: getstatic 29	o/CA$aux:ˎ	I
      //   302: iadd
      //   303: i2s
      //   304: istore 4
      //   306: goto -292 -> 14
      //   309: getstatic 77	o/CA$aux:ʼ	[B
      //   312: astore 9
      //   314: aload 9
      //   316: ifnull +6 -> 322
      //   319: goto -206 -> 113
      //   322: goto -32 -> 290
      //   325: goto -140 -> 185
      //   328: aload 8
      //   330: iload 5
      //   332: invokevirtual 107	java/lang/StringBuilder:append	(C)Ljava/lang/StringBuilder;
      //   335: pop
      //   336: iload_3
      //   337: iconst_1
      //   338: iadd
      //   339: istore_3
      //   340: iload 5
      //   342: istore 7
      //   344: goto -72 -> 272
      //   347: getstatic 83	o/CA$aux:ˏ	I
      //   350: istore 7
      //   352: iload 6
      //   354: ifeq +6 -> 360
      //   357: goto -73 -> 284
      //   360: goto +135 -> 495
      //   363: bipush 21
      //   365: istore 7
      //   367: goto +168 -> 535
      //   370: new 99	java/lang/StringBuilder
      //   373: dup
      //   374: invokespecial 110	java/lang/StringBuilder:<init>	()V
      //   377: astore 8
      //   379: getstatic 29	o/CA$aux:ˎ	I
      //   382: iload 4
      //   384: iadd
      //   385: istore 6
      //   387: iload 6
      //   389: istore 4
      //   391: iload 6
      //   393: iconst_m1
      //   394: if_icmpne +6 -> 400
      //   397: goto +11 -> 408
      //   400: goto -141 -> 259
      //   403: astore 8
      //   405: aload 8
      //   407: athrow
      //   408: bipush 52
      //   410: istore 6
      //   412: goto -185 -> 227
      //   415: goto -224 -> 191
      //   418: getstatic 77	o/CA$aux:ʼ	[B
      //   421: astore 9
      //   423: iload_1
      //   424: iconst_1
      //   425: isub
      //   426: istore 6
      //   428: aload 9
      //   430: iload_1
      //   431: baload
      //   432: iload_0
      //   433: iadd
      //   434: i2b
      //   435: iload_2
      //   436: ixor
      //   437: iload 7
      //   439: iadd
      //   440: i2c
      //   441: istore 5
      //   443: iload 6
      //   445: istore_1
      //   446: goto -118 -> 328
      //   449: getstatic 27	o/CA$aux:ʽ	I
      //   452: bipush 33
      //   454: iadd
      //   455: istore 6
      //   457: iload 6
      //   459: sipush 128
      //   462: irem
      //   463: putstatic 25	o/CA$aux:ᐝ	I
      //   466: iload 6
      //   468: iconst_2
      //   469: irem
      //   470: ifeq +6 -> 476
      //   473: goto -148 -> 325
      //   476: goto -291 -> 185
      //   479: getstatic 77	o/CA$aux:ʼ	[B
      //   482: astore 9
      //   484: aload 9
      //   486: ifnull +6 -> 492
      //   489: goto -402 -> 87
      //   492: goto -399 -> 93
      //   495: iconst_0
      //   496: istore 6
      //   498: goto -355 -> 143
      //   501: bipush 11
      //   503: istore 7
      //   505: goto +30 -> 535
      //   508: iload 6
      //   510: tableswitch	default:+22->532, 0:+-92->418, 1:+57->567
      //   532: goto -114 -> 418
      //   535: iload 7
      //   537: lookupswitch	default:+27->564, 11:+-482->55, 21:+-190->347
      //   564: goto -217 -> 347
      //   567: getstatic 109	o/CA$aux:ॱॱ	[S
      //   570: astore 9
      //   572: iload_1
      //   573: iconst_1
      //   574: isub
      //   575: istore 6
      //   577: aload 9
      //   579: iload_1
      //   580: saload
      //   581: iload_0
      //   582: iadd
      //   583: i2s
      //   584: iload_2
      //   585: ixor
      //   586: iload 7
      //   588: iadd
      //   589: i2c
      //   590: istore 5
      //   592: iload 6
      //   594: istore_1
      //   595: goto -267 -> 328
      //   598: goto -584 -> 14
      // Local variable table:
      //   start	length	slot	name	signature
      //   0	601	0	paramShort	short
      //   0	601	1	paramInt1	int
      //   0	601	2	paramByte	byte
      //   0	601	3	paramInt2	int
      //   0	601	4	paramInt3	int
      //   166	425	5	i	int
      //   9	584	6	j	int
      //   149	440	7	k	int
      //   3	326	8	localException1	Exception
      //   377	1	8	localStringBuilder	StringBuilder
      //   403	3	8	localException2	Exception
      //   312	266	9	localObject	Object
      // Exception table:
      //   from	to	target	type
      //   168	176	3	java/lang/Exception
      //   191	207	3	java/lang/Exception
      //   309	314	3	java/lang/Exception
      //   156	161	403	java/lang/Exception
      //   479	484	403	java/lang/Exception
    }
    
    /* Error */
    void ˊ(CF paramCF, Map<String, T> paramMap)
    {
      // Byte code:
      //   0: goto +325 -> 325
      //   3: aload 4
      //   5: invokeinterface 122 1 0
      //   10: astore 4
      //   12: aload 4
      //   14: ifnonnull +6 -> 20
      //   17: goto +361 -> 378
      //   20: goto +180 -> 200
      //   23: aload_2
      //   24: invokeinterface 126 1 0
      //   29: invokeinterface 132 1 0
      //   34: astore 5
      //   36: goto +6 -> 42
      //   39: astore_1
      //   40: aload_1
      //   41: athrow
      //   42: aload 5
      //   44: invokeinterface 138 1 0
      //   49: ifeq +6 -> 55
      //   52: goto +6 -> 58
      //   55: goto +398 -> 453
      //   58: iconst_1
      //   59: istore_3
      //   60: goto +268 -> 328
      //   63: goto +209 -> 272
      //   66: bipush 72
      //   68: istore_3
      //   69: iload_3
      //   70: lookupswitch	default:+26->96, 56:+97->167, 72:+38->108
      //   96: goto +71 -> 167
      //   99: astore_1
      //   100: aload_1
      //   101: athrow
      //   102: bipush 11
      //   104: iconst_0
      //   105: idiv
      //   106: istore_3
      //   107: return
      //   108: aload 5
      //   110: invokeinterface 141 1 0
      //   115: astore_1
      //   116: aload_1
      //   117: checkcast 118	java/util/Map$Entry
      //   120: astore_1
      //   121: aload_1
      //   122: invokeinterface 144 1 0
      //   127: astore_1
      //   128: aload_1
      //   129: checkcast 146	java/lang/String
      //   132: astore_1
      //   133: new 148	java/lang/NullPointerException
      //   136: dup
      //   137: invokespecial 149	java/lang/NullPointerException:<init>	()V
      //   140: athrow
      //   141: getstatic 27	o/CA$aux:ʽ	I
      //   144: iconst_3
      //   145: iadd
      //   146: istore_3
      //   147: iload_3
      //   148: sipush 128
      //   151: irem
      //   152: putstatic 25	o/CA$aux:ᐝ	I
      //   155: iload_3
      //   156: iconst_2
      //   157: irem
      //   158: ifeq +6 -> 164
      //   161: goto +289 -> 450
      //   164: goto +145 -> 309
      //   167: aload 5
      //   169: invokeinterface 141 1 0
      //   174: checkcast 118	java/util/Map$Entry
      //   177: astore 4
      //   179: aload 4
      //   181: invokeinterface 144 1 0
      //   186: checkcast 146	java/lang/String
      //   189: astore_2
      //   190: aload_2
      //   191: ifnonnull +6 -> 197
      //   194: goto +161 -> 355
      //   197: goto -194 -> 3
      //   200: aload_1
      //   201: iconst_4
      //   202: anewarray 146	java/lang/String
      //   205: dup
      //   206: iconst_0
      //   207: ldc -105
      //   209: aastore
      //   210: dup
      //   211: iconst_1
      //   212: new 99	java/lang/StringBuilder
      //   215: dup
      //   216: invokespecial 110	java/lang/StringBuilder:<init>	()V
      //   219: ldc -103
      //   221: invokevirtual 156	java/lang/StringBuilder:append	(Ljava/lang/String;)Ljava/lang/StringBuilder;
      //   224: aload_2
      //   225: invokevirtual 156	java/lang/StringBuilder:append	(Ljava/lang/String;)Ljava/lang/StringBuilder;
      //   228: ldc -98
      //   230: invokevirtual 156	java/lang/StringBuilder:append	(Ljava/lang/String;)Ljava/lang/StringBuilder;
      //   233: invokevirtual 103	java/lang/StringBuilder:toString	()Ljava/lang/String;
      //   236: aastore
      //   237: dup
      //   238: iconst_2
      //   239: ldc -96
      //   241: aastore
      //   242: dup
      //   243: iconst_3
      //   244: aload_0
      //   245: getfield 92	o/CA$aux:ˊ	Ljava/lang/String;
      //   248: aastore
      //   249: invokestatic 165	o/xz:ˋ	([Ljava/lang/String;)Lo/xz;
      //   252: aload_0
      //   253: getfield 90	o/CA$aux:ˋ	Lo/Cy;
      //   256: aload 4
      //   258: invokeinterface 170 2 0
      //   263: checkcast 172	o/xH
      //   266: invokevirtual 177	o/CF:ˏ	(Lo/xz;Lo/xH;)V
      //   269: goto -227 -> 42
      //   272: getstatic 27	o/CA$aux:ʽ	I
      //   275: istore_3
      //   276: iload_3
      //   277: bipush 57
      //   279: iadd
      //   280: istore_3
      //   281: iload_3
      //   282: sipush 128
      //   285: irem
      //   286: putstatic 25	o/CA$aux:ᐝ	I
      //   289: iload_3
      //   290: iconst_2
      //   291: irem
      //   292: ifeq +6 -> 298
      //   295: goto -193 -> 102
      //   298: return
      //   299: new 179	java/lang/IllegalArgumentException
      //   302: dup
      //   303: ldc -75
      //   305: invokespecial 184	java/lang/IllegalArgumentException:<init>	(Ljava/lang/String;)V
      //   308: athrow
      //   309: aload_2
      //   310: ifnonnull +6 -> 316
      //   313: goto -14 -> 299
      //   316: goto -293 -> 23
      //   319: bipush 56
      //   321: istore_3
      //   322: goto -253 -> 69
      //   325: goto -184 -> 141
      //   328: iload_3
      //   329: tableswitch	default:+23->352, 0:+-266->63, 1:+94->423
      //   352: goto +71 -> 423
      //   355: new 179	java/lang/IllegalArgumentException
      //   358: dup
      //   359: iconst_0
      //   360: ldc -71
      //   362: bipush -81
      //   364: ldc -70
      //   366: bipush -45
      //   368: invokestatic 188	o/CA$aux:ˏ	(SIBII)Ljava/lang/String;
      //   371: invokevirtual 191	java/lang/String:intern	()Ljava/lang/String;
      //   374: invokespecial 184	java/lang/IllegalArgumentException:<init>	(Ljava/lang/String;)V
      //   377: athrow
      //   378: new 179	java/lang/IllegalArgumentException
      //   381: dup
      //   382: new 99	java/lang/StringBuilder
      //   385: dup
      //   386: invokespecial 110	java/lang/StringBuilder:<init>	()V
      //   389: iconst_0
      //   390: ldc -64
      //   392: bipush 80
      //   394: ldc -70
      //   396: bipush -45
      //   398: invokestatic 188	o/CA$aux:ˏ	(SIBII)Ljava/lang/String;
      //   401: invokevirtual 191	java/lang/String:intern	()Ljava/lang/String;
      //   404: invokevirtual 156	java/lang/StringBuilder:append	(Ljava/lang/String;)Ljava/lang/StringBuilder;
      //   407: aload_2
      //   408: invokevirtual 156	java/lang/StringBuilder:append	(Ljava/lang/String;)Ljava/lang/StringBuilder;
      //   411: ldc -62
      //   413: invokevirtual 156	java/lang/StringBuilder:append	(Ljava/lang/String;)Ljava/lang/StringBuilder;
      //   416: invokevirtual 103	java/lang/StringBuilder:toString	()Ljava/lang/String;
      //   419: invokespecial 184	java/lang/IllegalArgumentException:<init>	(Ljava/lang/String;)V
      //   422: athrow
      //   423: getstatic 25	o/CA$aux:ᐝ	I
      //   426: bipush 39
      //   428: iadd
      //   429: istore_3
      //   430: iload_3
      //   431: sipush 128
      //   434: irem
      //   435: putstatic 27	o/CA$aux:ʽ	I
      //   438: iload_3
      //   439: iconst_2
      //   440: irem
      //   441: ifne +6 -> 447
      //   444: goto -378 -> 66
      //   447: goto -128 -> 319
      //   450: goto -141 -> 309
      //   453: iconst_0
      //   454: istore_3
      //   455: goto -127 -> 328
      // Local variable table:
      //   start	length	slot	name	signature
      //   0	458	0	this	aux
      //   0	458	1	paramCF	CF
      //   0	458	2	paramMap	Map<String, T>
      //   59	396	3	i	int
      //   3	254	4	localObject	Object
      //   34	134	5	localIterator	Iterator
      // Exception table:
      //   from	to	target	type
      //   108	116	39	java/lang/Exception
      //   116	121	39	java/lang/Exception
      //   121	128	39	java/lang/Exception
      //   128	133	39	java/lang/Exception
      //   133	141	39	java/lang/Exception
      //   272	276	39	java/lang/Exception
      //   121	128	99	java/lang/Exception
    }
  }
  
  static final class iF<T>
    extends CA<Map<String, T>>
  {
    private static int ʻ;
    private static short[] ʼ;
    private static int ˊ;
    private static int ˋ = 1490181543;
    private static byte[] ˎ;
    private static int ॱ;
    private static int ᐝ = 0;
    private final Cy<T, String> ˏ;
    
    static
    {
      ʻ = 1;
      ˊ = 100;
      ˎ = new byte[] { 2, 99, 81, -64, 3, 119, 68, 116, -67, 11, 76, 68, 114, 127, 90, 117, 76, 123, -72, 7, 124, 67, -70, 29, 122, 118, 120, 75, 106, -83, 77, -100, 10, 121, 86, -79, -73, 110, 73, 0, -73, -71, 25, 94, 60, -80, -3, -83, 118, 68, 5, -3, -85, -72, 19, -82, 5, -76, 113, 64, -75, -4, 115, 86, -77, -81, -79, 4, -93, 0, 0 };
      ॱ = 1665032966;
    }
    
    iF(Cy<T, String> paramCy) {}
    
    /* Error */
    private static String ˊ(short paramShort, int paramInt1, byte paramByte, int paramInt2, int paramInt3)
    {
      // Byte code:
      //   0: goto +168 -> 168
      //   3: astore 8
      //   5: aload 8
      //   7: athrow
      //   8: iconst_1
      //   9: istore 6
      //   11: goto +243 -> 254
      //   14: getstatic 107	o/CA$iF:ʼ	[S
      //   17: astore 9
      //   19: iload_1
      //   20: iconst_1
      //   21: isub
      //   22: istore 6
      //   24: aload 9
      //   26: iload_1
      //   27: saload
      //   28: iload_0
      //   29: iadd
      //   30: i2s
      //   31: iload_2
      //   32: ixor
      //   33: iload 7
      //   35: iadd
      //   36: i2c
      //   37: istore 5
      //   39: iload 6
      //   41: istore_1
      //   42: goto +64 -> 106
      //   45: goto +198 -> 243
      //   48: new 109	java/lang/StringBuilder
      //   51: dup
      //   52: invokespecial 110	java/lang/StringBuilder:<init>	()V
      //   55: astore 8
      //   57: getstatic 27	o/CA$iF:ˊ	I
      //   60: iload 4
      //   62: iadd
      //   63: istore 6
      //   65: iload 6
      //   67: istore 4
      //   69: iload 6
      //   71: iconst_m1
      //   72: if_icmpne +6 -> 78
      //   75: goto +132 -> 207
      //   78: goto +54 -> 132
      //   81: goto +330 -> 411
      //   84: getstatic 87	o/CA$iF:ˎ	[B
      //   87: astore 9
      //   89: aload 9
      //   91: ifnull +6 -> 97
      //   94: goto +232 -> 326
      //   97: goto -83 -> 14
      //   100: iconst_0
      //   101: istore 6
      //   103: goto +208 -> 311
      //   106: aload 8
      //   108: iload 5
      //   110: invokevirtual 114	java/lang/StringBuilder:append	(C)Ljava/lang/StringBuilder;
      //   113: pop
      //   114: iload_3
      //   115: iconst_1
      //   116: iadd
      //   117: istore_3
      //   118: iload 5
      //   120: istore 7
      //   122: goto +34 -> 156
      //   125: bipush 34
      //   127: istore 6
      //   129: goto +48 -> 177
      //   132: iconst_0
      //   133: istore 6
      //   135: goto +10 -> 145
      //   138: bipush 27
      //   140: istore 7
      //   142: goto +239 -> 381
      //   145: iload 6
      //   147: ifeq +6 -> 153
      //   150: goto +164 -> 314
      //   153: goto +90 -> 243
      //   156: iload_3
      //   157: iload 4
      //   159: if_icmpge +6 -> 165
      //   162: goto -78 -> 84
      //   165: goto +191 -> 356
      //   168: goto -120 -> 48
      //   171: iload 6
      //   173: istore_1
      //   174: goto -68 -> 106
      //   177: iload 6
      //   179: lookupswitch	default:+25->204, 34:+-79->100, 91:+-171->8
      //   204: goto -104 -> 100
      //   207: getstatic 23	o/CA$iF:ᐝ	I
      //   210: iconst_1
      //   211: iadd
      //   212: istore 6
      //   214: iload 6
      //   216: sipush 128
      //   219: irem
      //   220: putstatic 25	o/CA$iF:ʻ	I
      //   223: iload 6
      //   225: iconst_2
      //   226: irem
      //   227: ifne +6 -> 233
      //   230: goto -149 -> 81
      //   233: goto +178 -> 411
      //   236: bipush 91
      //   238: istore 6
      //   240: goto -63 -> 177
      //   243: iload 4
      //   245: ifle +6 -> 251
      //   248: goto -110 -> 138
      //   251: goto +217 -> 468
      //   254: iload_1
      //   255: iload 4
      //   257: iadd
      //   258: iconst_2
      //   259: isub
      //   260: iload 7
      //   262: iadd
      //   263: iload 6
      //   265: iadd
      //   266: istore_1
      //   267: getstatic 90	o/CA$iF:ॱ	I
      //   270: iload_3
      //   271: iadd
      //   272: i2c
      //   273: istore 5
      //   275: aload 8
      //   277: iload 5
      //   279: invokevirtual 114	java/lang/StringBuilder:append	(C)Ljava/lang/StringBuilder;
      //   282: pop
      //   283: iconst_1
      //   284: istore_3
      //   285: iload 5
      //   287: istore 7
      //   289: goto -133 -> 156
      //   292: getstatic 107	o/CA$iF:ʼ	[S
      //   295: getstatic 93	o/CA$iF:ˋ	I
      //   298: iload_1
      //   299: iadd
      //   300: saload
      //   301: getstatic 27	o/CA$iF:ˊ	I
      //   304: iadd
      //   305: i2s
      //   306: istore 4
      //   308: goto +130 -> 438
      //   311: goto -57 -> 254
      //   314: getstatic 87	o/CA$iF:ˎ	[B
      //   317: ifnull +6 -> 323
      //   320: goto +42 -> 362
      //   323: goto -31 -> 292
      //   326: getstatic 87	o/CA$iF:ˎ	[B
      //   329: astore 9
      //   331: iload_1
      //   332: iconst_1
      //   333: isub
      //   334: istore 6
      //   336: aload 9
      //   338: iload_1
      //   339: baload
      //   340: istore_1
      //   341: iload_1
      //   342: iload_0
      //   343: iadd
      //   344: i2b
      //   345: iload_2
      //   346: ixor
      //   347: iload 7
      //   349: iadd
      //   350: i2c
      //   351: istore 5
      //   353: goto -182 -> 171
      //   356: aload 8
      //   358: invokevirtual 118	java/lang/StringBuilder:toString	()Ljava/lang/String;
      //   361: areturn
      //   362: getstatic 87	o/CA$iF:ˎ	[B
      //   365: getstatic 93	o/CA$iF:ˋ	I
      //   368: iload_1
      //   369: iadd
      //   370: baload
      //   371: getstatic 27	o/CA$iF:ˊ	I
      //   374: iadd
      //   375: i2b
      //   376: istore 4
      //   378: goto -135 -> 243
      //   381: iload 7
      //   383: lookupswitch	default:+25->408, 27:+39->422, 69:+-27->356
      //   408: goto -52 -> 356
      //   411: iconst_1
      //   412: istore 6
      //   414: goto -269 -> 145
      //   417: astore 8
      //   419: aload 8
      //   421: athrow
      //   422: getstatic 93	o/CA$iF:ˋ	I
      //   425: istore 7
      //   427: iload 6
      //   429: ifeq +6 -> 435
      //   432: goto -196 -> 236
      //   435: goto -310 -> 125
      //   438: getstatic 23	o/CA$iF:ᐝ	I
      //   441: bipush 7
      //   443: iadd
      //   444: istore 7
      //   446: iload 7
      //   448: sipush 128
      //   451: irem
      //   452: putstatic 25	o/CA$iF:ʻ	I
      //   455: iload 7
      //   457: iconst_2
      //   458: irem
      //   459: ifne +6 -> 465
      //   462: goto -417 -> 45
      //   465: goto -420 -> 45
      //   468: bipush 69
      //   470: istore 7
      //   472: goto -91 -> 381
      // Local variable table:
      //   start	length	slot	name	signature
      //   0	475	0	paramShort	short
      //   0	475	1	paramInt1	int
      //   0	475	2	paramByte	byte
      //   0	475	3	paramInt2	int
      //   0	475	4	paramInt3	int
      //   37	315	5	i	int
      //   9	419	6	j	int
      //   33	438	7	k	int
      //   3	3	8	localException1	Exception
      //   55	302	8	localStringBuilder	StringBuilder
      //   417	3	8	localException2	Exception
      //   17	320	9	localObject	Object
      // Exception table:
      //   from	to	target	type
      //   84	89	3	java/lang/Exception
      //   326	331	3	java/lang/Exception
      //   422	427	417	java/lang/Exception
      //   438	446	417	java/lang/Exception
      //   446	455	417	java/lang/Exception
    }
    
    /* Error */
    void ˎ(CF paramCF, Map<String, T> paramMap)
    {
      // Byte code:
      //   0: goto +88 -> 88
      //   3: astore_1
      //   4: aload_1
      //   5: athrow
      //   6: goto +66 -> 72
      //   9: return
      //   10: aload_2
      //   11: ifnonnull +6 -> 17
      //   14: goto +33 -> 47
      //   17: goto +283 -> 300
      //   20: goto +52 -> 72
      //   23: new 126	java/lang/IllegalArgumentException
      //   26: dup
      //   27: bipush -98
      //   29: ldc 127
      //   31: bipush 21
      //   33: ldc -128
      //   35: bipush -70
      //   37: invokestatic 130	o/CA$iF:ˊ	(SIBII)Ljava/lang/String;
      //   40: invokevirtual 135	java/lang/String:intern	()Ljava/lang/String;
      //   43: invokespecial 138	java/lang/IllegalArgumentException:<init>	(Ljava/lang/String;)V
      //   46: athrow
      //   47: new 126	java/lang/IllegalArgumentException
      //   50: dup
      //   51: ldc -116
      //   53: invokespecial 138	java/lang/IllegalArgumentException:<init>	(Ljava/lang/String;)V
      //   56: athrow
      //   57: goto -47 -> 10
      //   60: bipush 14
      //   62: istore_3
      //   63: goto +256 -> 319
      //   66: astore_1
      //   67: aload_1
      //   68: athrow
      //   69: goto +22 -> 91
      //   72: aload 4
      //   74: invokeinterface 146 1 0
      //   79: ifeq +6 -> 85
      //   82: goto -22 -> 60
      //   85: goto +231 -> 316
      //   88: goto +90 -> 178
      //   91: aload 4
      //   93: invokeinterface 150 1 0
      //   98: checkcast 152	java/util/Map$Entry
      //   101: astore 5
      //   103: aload 5
      //   105: invokeinterface 155 1 0
      //   110: checkcast 132	java/lang/String
      //   113: astore_2
      //   114: aload_2
      //   115: ifnonnull +6 -> 121
      //   118: goto -95 -> 23
      //   121: goto +156 -> 277
      //   124: getstatic 25	o/CA$iF:ʻ	I
      //   127: bipush 93
      //   129: iadd
      //   130: istore_3
      //   131: iload_3
      //   132: sipush 128
      //   135: irem
      //   136: putstatic 23	o/CA$iF:ᐝ	I
      //   139: iload_3
      //   140: iconst_2
      //   141: irem
      //   142: ifeq +6 -> 148
      //   145: goto -76 -> 69
      //   148: goto -57 -> 91
      //   151: getstatic 25	o/CA$iF:ʻ	I
      //   154: bipush 105
      //   156: iadd
      //   157: istore_3
      //   158: iload_3
      //   159: sipush 128
      //   162: irem
      //   163: putstatic 23	o/CA$iF:ᐝ	I
      //   166: iload_3
      //   167: iconst_2
      //   168: irem
      //   169: ifeq +6 -> 175
      //   172: goto +125 -> 297
      //   175: goto -169 -> 6
      //   178: getstatic 23	o/CA$iF:ᐝ	I
      //   181: bipush 117
      //   183: iadd
      //   184: istore_3
      //   185: iload_3
      //   186: sipush 128
      //   189: irem
      //   190: putstatic 25	o/CA$iF:ʻ	I
      //   193: iload_3
      //   194: iconst_2
      //   195: irem
      //   196: ifne +6 -> 202
      //   199: goto -142 -> 57
      //   202: goto -192 -> 10
      //   205: aload_0
      //   206: getfield 100	o/CA$iF:ˏ	Lo/Cy;
      //   209: astore 5
      //   211: aload_1
      //   212: aload_2
      //   213: aload 5
      //   215: aload 6
      //   217: invokeinterface 160 2 0
      //   222: checkcast 132	java/lang/String
      //   225: invokevirtual 165	o/CF:ॱ	(Ljava/lang/String;Ljava/lang/String;)V
      //   228: goto -208 -> 20
      //   231: new 126	java/lang/IllegalArgumentException
      //   234: dup
      //   235: new 109	java/lang/StringBuilder
      //   238: dup
      //   239: invokespecial 110	java/lang/StringBuilder:<init>	()V
      //   242: bipush -91
      //   244: ldc -90
      //   246: bipush 85
      //   248: ldc -128
      //   250: bipush -59
      //   252: invokestatic 130	o/CA$iF:ˊ	(SIBII)Ljava/lang/String;
      //   255: invokevirtual 135	java/lang/String:intern	()Ljava/lang/String;
      //   258: invokevirtual 169	java/lang/StringBuilder:append	(Ljava/lang/String;)Ljava/lang/StringBuilder;
      //   261: aload_2
      //   262: invokevirtual 169	java/lang/StringBuilder:append	(Ljava/lang/String;)Ljava/lang/StringBuilder;
      //   265: ldc -85
      //   267: invokevirtual 169	java/lang/StringBuilder:append	(Ljava/lang/String;)Ljava/lang/StringBuilder;
      //   270: invokevirtual 118	java/lang/StringBuilder:toString	()Ljava/lang/String;
      //   273: invokespecial 138	java/lang/IllegalArgumentException:<init>	(Ljava/lang/String;)V
      //   276: athrow
      //   277: aload 5
      //   279: invokeinterface 174 1 0
      //   284: astore 6
      //   286: aload 6
      //   288: ifnonnull +6 -> 294
      //   291: goto -60 -> 231
      //   294: goto -89 -> 205
      //   297: goto -291 -> 6
      //   300: aload_2
      //   301: invokeinterface 178 1 0
      //   306: invokeinterface 184 1 0
      //   311: astore 4
      //   313: goto -162 -> 151
      //   316: bipush 50
      //   318: istore_3
      //   319: iload_3
      //   320: lookupswitch	default:+28->348, 14:+-196->124, 50:+-311->9
      //   348: return
      // Local variable table:
      //   start	length	slot	name	signature
      //   0	349	0	this	iF
      //   0	349	1	paramCF	CF
      //   0	349	2	paramMap	Map<String, T>
      //   62	258	3	i	int
      //   72	240	4	localIterator	Iterator
      //   101	177	5	localObject1	Object
      //   215	72	6	localObject2	Object
      // Exception table:
      //   from	to	target	type
      //   205	211	3	java/lang/Exception
      //   211	228	3	java/lang/Exception
      //   151	158	66	java/lang/Exception
      //   158	166	66	java/lang/Exception
    }
  }
  
  static final class if<T>
    extends CA<Map<String, T>>
  {
    private static byte[] ʻ;
    private static short[] ʼ;
    private static int ʽ = 0;
    private static int ˋ;
    private static int ˎ = 1455180689;
    private static int ॱ;
    private static int ᐝ = 1;
    private final boolean ˊ;
    private final Cy<T, String> ˏ;
    
    static
    {
      ˋ = 110;
      ʻ = new byte[] { -81, -12, 83, 57, -86, -13, 95, 54, 102, -83, -5, 62, 54, 100, 103, 76, 101, 62, 107, -94, -17, 110, 51, -84, -5, 55, 102, 59, -126, -70, -101, 59, -86, -120, -41, 52, -97, -107, -36, 71, -114, -107, -105, 119, -20, 74, -98, -117, -101, -44, 66, -125, -117, -103, -106, 113, -100, -125, -110, -33, 78, -109, -118, -47, 66, -122, -101, -126, -65, -100, 111, 15, 96, 50, -93, 6, 107, 101, -82 };
      ॱ = -1954868657;
    }
    
    if(Cy<T, String> paramCy, boolean paramBoolean)
    {
      this.ˏ = paramCy;
      this.ˊ = paramBoolean;
    }
    
    private static String ˎ(short paramShort, int paramInt1, byte paramByte, int paramInt2, int paramInt3)
    {
      break label239;
      paramInt3 = 14;
      break label614;
      label10:
      paramInt1 = ᐝ + 39;
      ʽ = paramInt1 % 128;
      label37:
      int k;
      label63:
      int j;
      label93:
      Object localObject;
      label109:
      label126:
      int i;
      label142:
      label149:
      label182:
      label193:
      label199:
      label239:
      label242:
      StringBuilder localStringBuilder;
      if (paramInt1 % 2 == 0) {
        switch (k)
        {
        default: 
          break label508;
          j = ᐝ + 47;
          ʽ = j % 128;
          if (j % 2 == 0)
          {
            break label304;
            try
            {
              localObject = ʻ;
              if (localObject != null) {
                break label193;
              }
            }
            catch (Exception localException1)
            {
              throw localException1;
            }
            k = 0;
          }
          else
          {
            j = 1;
            break;
            paramInt1 = j;
            break label310;
            paramInt1 = j;
            k = i;
            break label574;
            paramInt3 = 86;
          }
          break;
        case 0: 
          for (;;)
          {
            if (j == 0) {
              break label411;
            }
            k = 1;
            break;
            k = ˎ;
            if (j != 0) {
              break label555;
            }
            break label652;
            if (paramInt3 > 0) {
              break label109;
            }
            break label608;
            j = 1;
            switch (k)
            {
            case 0: 
            default: 
              break label583;
              j = 0;
              break label242;
              paramInt1 = 85;
              break label335;
              switch (j)
              {
              default: 
                break label417;
                localStringBuilder = new StringBuilder();
                j = ˋ + paramInt3;
                paramInt3 = j;
                if (j == -1) {
                  break label63;
                }
                break label405;
                label304:
                j = 1;
              }
              break;
            }
          }
        }
      }
      label310:
      label335:
      label405:
      label411:
      label417:
      label508:
      label555:
      label574:
      label583:
      label608:
      label614:
      label652:
      label686:
      for (;;)
      {
        try
        {
          localStringBuilder.append(i);
          paramInt2 += 1;
          k = i;
          continue;
          continue;
          break label182;
          switch (paramInt1)
          {
          case 95: 
          default: 
            continue;
            break label149;
            j = paramInt1 + paramInt3 - 2 + k + j;
            i = (char)(ॱ + paramInt2);
            localStringBuilder.append(i);
            paramInt2 = 1;
            break label10;
            j = 0;
            continue;
            k = 0;
            break label37;
            j = ʽ + 17;
            ᐝ = j % 128;
            if (j % 2 == 0) {
              continue;
            }
            continue;
            k = ᐝ + 41;
            ʽ = k % 128;
            if (k % 2 != 0) {
              break label686;
            }
            continue;
            localObject = ʻ;
            j = paramInt1 - 1;
            i = (char)(((byte)(localObject[paramInt1] + paramShort) ^ paramByte) + k);
            paramInt1 = j;
            continue;
            if (ʻ != null) {
              break label142;
            }
            break;
            localObject = ʻ;
            paramInt3 = ˎ;
            paramInt3 = localObject[(paramInt3 + paramInt1)];
            k = ˋ;
            paramInt3 = (byte)(paramInt3 + k);
            break label182;
            j = 1;
            continue;
            paramInt1 = 95;
            break;
          case 85: 
            k = i;
            paramInt1 = j;
          }
          if (paramInt2 < paramInt3) {
            break label93;
          }
          return localStringBuilder.toString();
        }
        catch (Exception localException2)
        {
          throw localException2;
        }
        paramInt3 = (short)(ʼ[(ˎ + paramInt1)] + ˋ);
        continue;
        k = 1;
        break label199;
        switch (paramInt3)
        {
        }
        continue;
        j = 0;
        continue;
        localObject = ʼ;
        j = paramInt1 - 1;
        i = (char)(((short)(localObject[paramInt1] + paramShort) ^ paramByte) + k);
        break label126;
      }
    }
    
    void ˋ(CF paramCF, Map<String, T> paramMap)
    {
      break label267;
      label3:
      int i = 40;
      label6:
      label62:
      Object localObject1;
      String str;
      switch (i)
      {
      default: 
        break label270;
        i = ᐝ + 61;
        ʽ = i % 128;
        if (i % 2 == 0)
        {
          break label161;
          throw new IllegalArgumentException("Field map value '" + localObject1 + "' converted to null by " + this.ˏ.getClass().getName() + ˎ((short)46, -1455180620, (byte)-102, 1954868689, -111).intern() + str + "'.");
          label137:
          throw new IllegalArgumentException(ˎ((short)-79, -1455180689, (byte)16, 1954868727, -111).intern());
          label161:
          if (paramMap != null)
          {
            break;
            label171:
            i = 0;
          }
        }
        break;
      }
      for (;;)
      {
        i = ᐝ + 121;
        ʽ = i % 128;
        if (i % 2 == 0)
        {
          break label171;
          paramMap = paramMap.entrySet().iterator();
          break label438;
          label218:
          break label401;
          label221:
          localObject1 = ((Map.Entry)localObject1).getValue();
          if (localObject1 != null) {
            break label350;
          }
        }
        label267:
        label270:
        label347:
        label350:
        Object localObject2;
        for (;;)
        {
          switch (i)
          {
          default: 
            break label347;
            break;
            i = ʽ + 105;
            ᐝ = i % 128;
            if (i % 2 == 0) {
              break label218;
            }
            break label401;
            throw new IllegalArgumentException(ˎ((short)111, -1455180660, (byte)13, 1954868727, -111).intern() + str + "'.");
          case 1: 
            break;
          case 0: 
            break label438;
            try
            {
              localObject2 = this.ˏ;
              try
              {
                localObject2 = ((Cy)localObject2).ˎ(localObject1);
                localObject2 = (String)localObject2;
                if (localObject2 == null) {
                  break label62;
                }
              }
              catch (Exception paramCF)
              {
                throw paramCF;
              }
              throw new IllegalArgumentException("Field map was null.");
            }
            catch (Exception paramCF)
            {
              throw paramCF;
            }
            break label161;
            label401:
            localObject1 = (Map.Entry)paramMap.next();
            str = (String)((Map.Entry)localObject1).getKey();
            if (str == null) {
              break label137;
            }
            break label221;
            label438:
            boolean bool = paramMap.hasNext();
            if (bool) {
              break label3;
            }
            break label462;
            i = 1;
          }
        }
        label462:
        i = 86;
        break label6;
        paramCF.ˋ(str, (String)localObject2, this.ˊ);
      }
    }
  }
  
  static final class ʻ
    extends CA<Object>
  {
    ʻ() {}
    
    void ˊ(CF paramCF, Object paramObject)
    {
      CM.ˋ(paramObject, "@Url parameter is null.");
      paramCF.ˋ(paramObject);
    }
  }
  
  static final class ʼ
    extends CA<xD.iF>
  {
    static final ʼ ˋ = new ʼ();
    
    private ʼ() {}
    
    void ˋ(CF paramCF, xD.iF paramIF)
    {
      if (paramIF != null) {
        paramCF.ˎ(paramIF);
      }
    }
  }
  
  static final class ˊ<T>
    extends CA<T>
  {
    private final Cy<T, String> ˊ;
    private final String ˎ;
    
    ˊ(String paramString, Cy<T, String> paramCy)
    {
      this.ˎ = ((String)CM.ˋ(paramString, "name == null"));
      this.ˊ = paramCy;
    }
    
    void ˊ(CF paramCF, T paramT)
    {
      if (paramT == null) {
        return;
      }
      paramT = (String)this.ˊ.ˎ(paramT);
      if (paramT == null) {
        return;
      }
      paramCF.ॱ(this.ˎ, paramT);
    }
  }
  
  static final class ˋ<T>
    extends CA<T>
  {
    private final Cy<T, xH> ˏ;
    
    ˋ(Cy<T, xH> paramCy)
    {
      this.ˏ = paramCy;
    }
    
    void ˊ(CF paramCF, T paramT)
    {
      if (paramT == null) {
        throw new IllegalArgumentException("Body parameter value must not be null.");
      }
      xH localXH;
      try
      {
        localXH = (xH)this.ˏ.ˎ(paramT);
      }
      catch (IOException paramCF)
      {
        throw new RuntimeException("Unable to convert " + paramT + " to RequestBody", paramCF);
      }
      paramCF.ˋ(localXH);
    }
  }
  
  static final class ˎ<T>
    extends CA<T>
  {
    private final Cy<T, xH> ˊ;
    private final xz ˋ;
    
    ˎ(xz paramXz, Cy<T, xH> paramCy)
    {
      this.ˋ = paramXz;
      this.ˊ = paramCy;
    }
    
    void ˊ(CF paramCF, T paramT)
    {
      if (paramT == null) {
        return;
      }
      xH localXH;
      try
      {
        localXH = (xH)this.ˊ.ˎ(paramT);
      }
      catch (IOException paramCF)
      {
        throw new RuntimeException("Unable to convert " + paramT + " to RequestBody", paramCF);
      }
      paramCF.ˏ(this.ˋ, localXH);
    }
  }
  
  static final class ˏ<T>
    extends CA<T>
  {
    private final Cy<T, String> ˎ;
    private final boolean ˏ;
    private final String ॱ;
    
    ˏ(String paramString, Cy<T, String> paramCy, boolean paramBoolean)
    {
      this.ॱ = ((String)CM.ˋ(paramString, "name == null"));
      this.ˎ = paramCy;
      this.ˏ = paramBoolean;
    }
    
    void ˊ(CF paramCF, T paramT)
    {
      if (paramT == null) {
        return;
      }
      paramT = (String)this.ˎ.ˎ(paramT);
      if (paramT == null) {
        return;
      }
      paramCF.ˊ(this.ॱ, paramT, this.ˏ);
    }
  }
  
  static final class ᐝ<T>
    extends CA<Map<String, T>>
  {
    private static int ʼ;
    private static int ˊ = 0;
    private static long ˋ;
    private static char ॱ;
    private static int ᐝ = 0;
    private final Cy<T, String> ˎ;
    private final boolean ˏ;
    
    static
    {
      ʼ = 1;
      ॱ = '\000';
      ˋ = -6084150803694945828L;
    }
    
    /* Error */
    ᐝ(Cy<T, String> paramCy, boolean paramBoolean)
    {
      // Byte code:
      //   0: goto +6 -> 6
      //   3: astore_1
      //   4: aload_1
      //   5: athrow
      //   6: aload_0
      //   7: invokespecial 39	o/CA:<init>	()V
      //   10: aload_0
      //   11: aload_1
      //   12: putfield 41	o/CA$ᐝ:ˎ	Lo/Cy;
      //   15: aload_0
      //   16: iload_2
      //   17: putfield 43	o/CA$ᐝ:ˏ	Z
      //   20: return
      //   21: astore_1
      //   22: aload_1
      //   23: athrow
      // Local variable table:
      //   start	length	slot	name	signature
      //   0	24	0	this	ᐝ
      //   0	24	1	paramCy	Cy<T, String>
      //   0	24	2	paramBoolean	boolean
      // Exception table:
      //   from	to	target	type
      //   15	20	3	java/lang/Exception
      //   10	15	21	java/lang/Exception
      //   15	20	21	java/lang/Exception
    }
    
    private static String ˋ(char[] paramArrayOfChar1, char paramChar, char[] paramArrayOfChar2, int paramInt, char[] paramArrayOfChar3)
    {
      for (;;)
      {
        paramChar = 12 / 0;
        return paramArrayOfChar1;
        break label96;
        label13:
        oJ.ˏ(paramArrayOfChar1, paramArrayOfChar3, paramChar);
        char[] arrayOfChar;
        arrayOfChar[paramChar] = ((char)(int)(paramArrayOfChar2[paramChar] ^ paramArrayOfChar1[((paramChar + '\003') % 4)] ^ ˋ ^ ˊ ^ ॱ));
        paramChar += '\001';
        break label215;
        break label150;
        return paramArrayOfChar1;
        for (;;)
        {
          paramInt = 0;
          break label187;
          paramInt = ʼ + 49;
          ᐝ = paramInt % 128;
          if (paramInt % 2 != 0) {
            break label13;
          }
          break label13;
          label96:
          char c;
          for (;;)
          {
            paramArrayOfChar1 = (char[])paramArrayOfChar1.clone();
            paramArrayOfChar3 = (char[])paramArrayOfChar3.clone();
            paramArrayOfChar1[0] = ((char)(paramArrayOfChar1[0] ^ paramChar));
            paramArrayOfChar3[2] = ((char)(paramArrayOfChar3[2] + (char)paramInt));
            c = paramArrayOfChar2.length;
            arrayOfChar = new char[c];
            paramChar = '\000';
            break label215;
            label150:
            c = ᐝ + 105;
            ʼ = c % '';
            if (c % '\002' == 0) {
              break;
            }
          }
          paramChar = '\001';
          label187:
          label215:
          while (paramChar < c)
          {
            paramInt = 1;
            switch (paramInt)
            {
            case 1: 
            default: 
              break label259;
            }
          }
        }
        for (;;)
        {
          paramChar = ᐝ + 51;
          ʼ = paramChar % '';
          if (paramChar % '\002' != 0) {
            break;
          }
          paramChar = '\000';
          break label272;
          label259:
          paramArrayOfChar1 = new String(arrayOfChar);
        }
        label272:
        switch (paramChar)
        {
        }
      }
    }
    
    /* Error */
    void ˏ(CF paramCF, Map<String, T> paramMap)
    {
      // Byte code:
      //   0: goto +243 -> 243
      //   3: goto +907 -> 910
      //   6: new 70	java/lang/IllegalArgumentException
      //   9: dup
      //   10: iconst_4
      //   11: newarray char
      //   13: dup
      //   14: iconst_0
      //   15: ldc 71
      //   17: castore
      //   18: dup
      //   19: iconst_1
      //   20: ldc 72
      //   22: castore
      //   23: dup
      //   24: iconst_2
      //   25: ldc 73
      //   27: castore
      //   28: dup
      //   29: iconst_3
      //   30: ldc 74
      //   32: castore
      //   33: sipush 7800
      //   36: bipush 29
      //   38: newarray char
      //   40: dup
      //   41: iconst_0
      //   42: ldc 75
      //   44: castore
      //   45: dup
      //   46: iconst_1
      //   47: ldc 76
      //   49: castore
      //   50: dup
      //   51: iconst_2
      //   52: ldc 77
      //   54: castore
      //   55: dup
      //   56: iconst_3
      //   57: ldc 78
      //   59: castore
      //   60: dup
      //   61: iconst_4
      //   62: ldc 79
      //   64: castore
      //   65: dup
      //   66: iconst_5
      //   67: ldc 80
      //   69: castore
      //   70: dup
      //   71: bipush 6
      //   73: ldc 81
      //   75: castore
      //   76: dup
      //   77: bipush 7
      //   79: ldc 82
      //   81: castore
      //   82: dup
      //   83: bipush 8
      //   85: ldc 83
      //   87: castore
      //   88: dup
      //   89: bipush 9
      //   91: ldc 84
      //   93: castore
      //   94: dup
      //   95: bipush 10
      //   97: ldc 85
      //   99: castore
      //   100: dup
      //   101: bipush 11
      //   103: ldc 86
      //   105: castore
      //   106: dup
      //   107: bipush 12
      //   109: ldc 87
      //   111: castore
      //   112: dup
      //   113: bipush 13
      //   115: ldc 88
      //   117: castore
      //   118: dup
      //   119: bipush 14
      //   121: ldc 89
      //   123: castore
      //   124: dup
      //   125: bipush 15
      //   127: ldc 90
      //   129: castore
      //   130: dup
      //   131: bipush 16
      //   133: ldc 91
      //   135: castore
      //   136: dup
      //   137: bipush 17
      //   139: ldc 92
      //   141: castore
      //   142: dup
      //   143: bipush 18
      //   145: ldc 93
      //   147: castore
      //   148: dup
      //   149: bipush 19
      //   151: ldc 94
      //   153: castore
      //   154: dup
      //   155: bipush 20
      //   157: ldc 95
      //   159: castore
      //   160: dup
      //   161: bipush 21
      //   163: ldc 96
      //   165: castore
      //   166: dup
      //   167: bipush 22
      //   169: ldc 97
      //   171: castore
      //   172: dup
      //   173: bipush 23
      //   175: ldc 98
      //   177: castore
      //   178: dup
      //   179: bipush 24
      //   181: ldc 99
      //   183: castore
      //   184: dup
      //   185: bipush 25
      //   187: ldc 100
      //   189: castore
      //   190: dup
      //   191: bipush 26
      //   193: ldc 101
      //   195: castore
      //   196: dup
      //   197: bipush 27
      //   199: ldc 102
      //   201: castore
      //   202: dup
      //   203: bipush 28
      //   205: ldc 103
      //   207: castore
      //   208: ldc 104
      //   210: iconst_4
      //   211: newarray char
      //   213: dup
      //   214: iconst_0
      //   215: ldc 105
      //   217: castore
      //   218: dup
      //   219: iconst_1
      //   220: ldc 106
      //   222: castore
      //   223: dup
      //   224: iconst_2
      //   225: ldc 107
      //   227: castore
      //   228: dup
      //   229: iconst_3
      //   230: ldc 108
      //   232: castore
      //   233: invokestatic 110	o/CA$ᐝ:ˋ	([CC[CI[C)Ljava/lang/String;
      //   236: invokevirtual 114	java/lang/String:intern	()Ljava/lang/String;
      //   239: invokespecial 117	java/lang/IllegalArgumentException:<init>	(Ljava/lang/String;)V
      //   242: athrow
      //   243: goto +598 -> 841
      //   246: goto +36 -> 282
      //   249: new 70	java/lang/IllegalArgumentException
      //   252: dup
      //   253: ldc 119
      //   255: invokespecial 117	java/lang/IllegalArgumentException:<init>	(Ljava/lang/String;)V
      //   258: athrow
      //   259: astore_1
      //   260: aload_1
      //   261: athrow
      //   262: aload 5
      //   264: invokeinterface 124 1 0
      //   269: astore 5
      //   271: aload 5
      //   273: ifnonnull +6 -> 279
      //   276: goto +241 -> 517
      //   279: goto +692 -> 971
      //   282: getstatic 22	o/CA$ᐝ:ᐝ	I
      //   285: bipush 81
      //   287: iadd
      //   288: istore_3
      //   289: iload_3
      //   290: sipush 128
      //   293: irem
      //   294: putstatic 24	o/CA$ᐝ:ʼ	I
      //   297: iload_3
      //   298: iconst_2
      //   299: irem
      //   300: ifne +6 -> 306
      //   303: goto +632 -> 935
      //   306: return
      //   307: aload_1
      //   308: aload 4
      //   310: aload 6
      //   312: aload_0
      //   313: getfield 43	o/CA$ᐝ:ˏ	Z
      //   316: invokevirtual 129	o/CF:ˊ	(Ljava/lang/String;Ljava/lang/String;Z)V
      //   319: goto +601 -> 920
      //   322: astore_1
      //   323: aload_1
      //   324: athrow
      //   325: aload_2
      //   326: invokeinterface 133 1 0
      //   331: invokeinterface 139 1 0
      //   336: astore_2
      //   337: goto +583 -> 920
      //   340: new 70	java/lang/IllegalArgumentException
      //   343: dup
      //   344: new 141	java/lang/StringBuilder
      //   347: dup
      //   348: invokespecial 142	java/lang/StringBuilder:<init>	()V
      //   351: ldc -112
      //   353: invokevirtual 148	java/lang/StringBuilder:append	(Ljava/lang/String;)Ljava/lang/StringBuilder;
      //   356: aload 5
      //   358: invokevirtual 151	java/lang/StringBuilder:append	(Ljava/lang/Object;)Ljava/lang/StringBuilder;
      //   361: ldc -103
      //   363: invokevirtual 148	java/lang/StringBuilder:append	(Ljava/lang/String;)Ljava/lang/StringBuilder;
      //   366: aload_0
      //   367: getfield 41	o/CA$ᐝ:ˎ	Lo/Cy;
      //   370: invokevirtual 159	java/lang/Object:getClass	()Ljava/lang/Class;
      //   373: invokevirtual 164	java/lang/Class:getName	()Ljava/lang/String;
      //   376: invokevirtual 148	java/lang/StringBuilder:append	(Ljava/lang/String;)Ljava/lang/StringBuilder;
      //   379: iconst_4
      //   380: newarray char
      //   382: dup
      //   383: iconst_0
      //   384: ldc -91
      //   386: castore
      //   387: dup
      //   388: iconst_1
      //   389: ldc -90
      //   391: castore
      //   392: dup
      //   393: iconst_2
      //   394: ldc -89
      //   396: castore
      //   397: dup
      //   398: iconst_3
      //   399: ldc -88
      //   401: castore
      //   402: iconst_0
      //   403: bipush 10
      //   405: newarray char
      //   407: dup
      //   408: iconst_0
      //   409: ldc -87
      //   411: castore
      //   412: dup
      //   413: iconst_1
      //   414: ldc -86
      //   416: castore
      //   417: dup
      //   418: iconst_2
      //   419: ldc -85
      //   421: castore
      //   422: dup
      //   423: iconst_3
      //   424: ldc -84
      //   426: castore
      //   427: dup
      //   428: iconst_4
      //   429: ldc -83
      //   431: castore
      //   432: dup
      //   433: iconst_5
      //   434: ldc -82
      //   436: castore
      //   437: dup
      //   438: bipush 6
      //   440: ldc -81
      //   442: castore
      //   443: dup
      //   444: bipush 7
      //   446: ldc -80
      //   448: castore
      //   449: dup
      //   450: bipush 8
      //   452: ldc -79
      //   454: castore
      //   455: dup
      //   456: bipush 9
      //   458: ldc -78
      //   460: castore
      //   461: iconst_0
      //   462: iconst_4
      //   463: newarray char
      //   465: dup
      //   466: iconst_0
      //   467: ldc 105
      //   469: castore
      //   470: dup
      //   471: iconst_1
      //   472: ldc 106
      //   474: castore
      //   475: dup
      //   476: iconst_2
      //   477: ldc 107
      //   479: castore
      //   480: dup
      //   481: iconst_3
      //   482: ldc 108
      //   484: castore
      //   485: invokestatic 110	o/CA$ᐝ:ˋ	([CC[CI[C)Ljava/lang/String;
      //   488: invokevirtual 114	java/lang/String:intern	()Ljava/lang/String;
      //   491: invokevirtual 148	java/lang/StringBuilder:append	(Ljava/lang/String;)Ljava/lang/StringBuilder;
      //   494: aload 4
      //   496: invokevirtual 148	java/lang/StringBuilder:append	(Ljava/lang/String;)Ljava/lang/StringBuilder;
      //   499: ldc -76
      //   501: invokevirtual 148	java/lang/StringBuilder:append	(Ljava/lang/String;)Ljava/lang/StringBuilder;
      //   504: invokevirtual 183	java/lang/StringBuilder:toString	()Ljava/lang/String;
      //   507: invokespecial 117	java/lang/IllegalArgumentException:<init>	(Ljava/lang/String;)V
      //   510: athrow
      //   511: bipush 31
      //   513: istore_3
      //   514: goto +425 -> 939
      //   517: new 70	java/lang/IllegalArgumentException
      //   520: dup
      //   521: new 141	java/lang/StringBuilder
      //   524: dup
      //   525: invokespecial 142	java/lang/StringBuilder:<init>	()V
      //   528: iconst_4
      //   529: newarray char
      //   531: dup
      //   532: iconst_0
      //   533: ldc -72
      //   535: castore
      //   536: dup
      //   537: iconst_1
      //   538: ldc -71
      //   540: castore
      //   541: dup
      //   542: iconst_2
      //   543: ldc -70
      //   545: castore
      //   546: dup
      //   547: iconst_3
      //   548: ldc -69
      //   550: castore
      //   551: ldc -68
      //   553: bipush 40
      //   555: newarray char
      //   557: dup
      //   558: iconst_0
      //   559: ldc -67
      //   561: castore
      //   562: dup
      //   563: iconst_1
      //   564: ldc -66
      //   566: castore
      //   567: dup
      //   568: iconst_2
      //   569: ldc -65
      //   571: castore
      //   572: dup
      //   573: iconst_3
      //   574: ldc -64
      //   576: castore
      //   577: dup
      //   578: iconst_4
      //   579: ldc -63
      //   581: castore
      //   582: dup
      //   583: iconst_5
      //   584: ldc -62
      //   586: castore
      //   587: dup
      //   588: bipush 6
      //   590: ldc -61
      //   592: castore
      //   593: dup
      //   594: bipush 7
      //   596: ldc -60
      //   598: castore
      //   599: dup
      //   600: bipush 8
      //   602: ldc -59
      //   604: castore
      //   605: dup
      //   606: bipush 9
      //   608: ldc -58
      //   610: castore
      //   611: dup
      //   612: bipush 10
      //   614: ldc -57
      //   616: castore
      //   617: dup
      //   618: bipush 11
      //   620: ldc -56
      //   622: castore
      //   623: dup
      //   624: bipush 12
      //   626: ldc -55
      //   628: castore
      //   629: dup
      //   630: bipush 13
      //   632: ldc -54
      //   634: castore
      //   635: dup
      //   636: bipush 14
      //   638: ldc -53
      //   640: castore
      //   641: dup
      //   642: bipush 15
      //   644: ldc -52
      //   646: castore
      //   647: dup
      //   648: bipush 16
      //   650: ldc -51
      //   652: castore
      //   653: dup
      //   654: bipush 17
      //   656: ldc -50
      //   658: castore
      //   659: dup
      //   660: bipush 18
      //   662: ldc -49
      //   664: castore
      //   665: dup
      //   666: bipush 19
      //   668: ldc -48
      //   670: castore
      //   671: dup
      //   672: bipush 20
      //   674: ldc -47
      //   676: castore
      //   677: dup
      //   678: bipush 21
      //   680: ldc -46
      //   682: castore
      //   683: dup
      //   684: bipush 22
      //   686: ldc -45
      //   688: castore
      //   689: dup
      //   690: bipush 23
      //   692: ldc -44
      //   694: castore
      //   695: dup
      //   696: bipush 24
      //   698: ldc -43
      //   700: castore
      //   701: dup
      //   702: bipush 25
      //   704: ldc -42
      //   706: castore
      //   707: dup
      //   708: bipush 26
      //   710: ldc -41
      //   712: castore
      //   713: dup
      //   714: bipush 27
      //   716: ldc -40
      //   718: castore
      //   719: dup
      //   720: bipush 28
      //   722: ldc -39
      //   724: castore
      //   725: dup
      //   726: bipush 29
      //   728: ldc -38
      //   730: castore
      //   731: dup
      //   732: bipush 30
      //   734: ldc -37
      //   736: castore
      //   737: dup
      //   738: bipush 31
      //   740: ldc -36
      //   742: castore
      //   743: dup
      //   744: bipush 32
      //   746: ldc -35
      //   748: castore
      //   749: dup
      //   750: bipush 33
      //   752: ldc -34
      //   754: castore
      //   755: dup
      //   756: bipush 34
      //   758: ldc -33
      //   760: castore
      //   761: dup
      //   762: bipush 35
      //   764: ldc -32
      //   766: castore
      //   767: dup
      //   768: bipush 36
      //   770: ldc -31
      //   772: castore
      //   773: dup
      //   774: bipush 37
      //   776: ldc -30
      //   778: castore
      //   779: dup
      //   780: bipush 38
      //   782: ldc -29
      //   784: castore
      //   785: dup
      //   786: bipush 39
      //   788: ldc -28
      //   790: castore
      //   791: iconst_0
      //   792: iconst_4
      //   793: newarray char
      //   795: dup
      //   796: iconst_0
      //   797: ldc 105
      //   799: castore
      //   800: dup
      //   801: iconst_1
      //   802: ldc 106
      //   804: castore
      //   805: dup
      //   806: iconst_2
      //   807: ldc 107
      //   809: castore
      //   810: dup
      //   811: iconst_3
      //   812: ldc 108
      //   814: castore
      //   815: invokestatic 110	o/CA$ᐝ:ˋ	([CC[CI[C)Ljava/lang/String;
      //   818: invokevirtual 114	java/lang/String:intern	()Ljava/lang/String;
      //   821: invokevirtual 148	java/lang/StringBuilder:append	(Ljava/lang/String;)Ljava/lang/StringBuilder;
      //   824: aload 4
      //   826: invokevirtual 148	java/lang/StringBuilder:append	(Ljava/lang/String;)Ljava/lang/StringBuilder;
      //   829: ldc -76
      //   831: invokevirtual 148	java/lang/StringBuilder:append	(Ljava/lang/String;)Ljava/lang/StringBuilder;
      //   834: invokevirtual 183	java/lang/StringBuilder:toString	()Ljava/lang/String;
      //   837: invokespecial 117	java/lang/IllegalArgumentException:<init>	(Ljava/lang/String;)V
      //   840: athrow
      //   841: getstatic 24	o/CA$ᐝ:ʼ	I
      //   844: bipush 81
      //   846: iadd
      //   847: istore_3
      //   848: iload_3
      //   849: sipush 128
      //   852: irem
      //   853: putstatic 22	o/CA$ᐝ:ᐝ	I
      //   856: iload_3
      //   857: iconst_2
      //   858: irem
      //   859: ifeq +6 -> 865
      //   862: goto -859 -> 3
      //   865: goto +45 -> 910
      //   868: aload_2
      //   869: invokeinterface 233 1 0
      //   874: astore 4
      //   876: aload 4
      //   878: checkcast 121	java/util/Map$Entry
      //   881: astore 5
      //   883: aload 5
      //   885: invokeinterface 236 1 0
      //   890: astore 4
      //   892: aload 4
      //   894: checkcast 59	java/lang/String
      //   897: astore 4
      //   899: aload 4
      //   901: ifnonnull +6 -> 907
      //   904: goto -898 -> 6
      //   907: goto -645 -> 262
      //   910: aload_2
      //   911: ifnonnull +6 -> 917
      //   914: goto -665 -> 249
      //   917: goto -592 -> 325
      //   920: aload_2
      //   921: invokeinterface 240 1 0
      //   926: ifeq +6 -> 932
      //   929: goto +7 -> 936
      //   932: goto -421 -> 511
      //   935: return
      //   936: bipush 40
      //   938: istore_3
      //   939: iload_3
      //   940: lookupswitch	default:+28->968, 31:+-694->246, 40:+-72->868
      //   968: goto -100 -> 868
      //   971: aload_0
      //   972: getfield 41	o/CA$ᐝ:ˎ	Lo/Cy;
      //   975: aload 5
      //   977: invokeinterface 245 2 0
      //   982: checkcast 59	java/lang/String
      //   985: astore 6
      //   987: aload 6
      //   989: ifnonnull +6 -> 995
      //   992: goto -652 -> 340
      //   995: goto -688 -> 307
      // Local variable table:
      //   start	length	slot	name	signature
      //   0	998	0	this	ᐝ
      //   0	998	1	paramCF	CF
      //   0	998	2	paramMap	Map<String, T>
      //   288	652	3	i	int
      //   308	592	4	localObject1	Object
      //   262	714	5	localObject2	Object
      //   310	678	6	str	String
      // Exception table:
      //   from	to	target	type
      //   883	892	259	java/lang/Exception
      //   868	876	322	java/lang/Exception
      //   876	883	322	java/lang/Exception
      //   883	892	322	java/lang/Exception
      //   892	899	322	java/lang/Exception
    }
  }
}
