package o;

import java.lang.annotation.Annotation;
import java.lang.reflect.Method;
import java.lang.reflect.Type;
import java.util.LinkedHashSet;
import java.util.Set;
import java.util.regex.Matcher;
import java.util.regex.Pattern;

final class CH<R, T>
{
  static final Pattern ˋ = Pattern.compile("\\{([a-zA-Z][a-zA-Z0-9_-]*)\\}");
  static final Pattern ˏ = Pattern.compile("[a-zA-Z][a-zA-Z0-9_-]*");
  private final String ʻ;
  private final Cy<xF, R> ʼ;
  private final xz ʽ;
  final Cw<R, T> ˊ;
  private final boolean ˊॱ;
  final xj.if ˎ;
  private final boolean ˏॱ;
  private final boolean ͺ;
  private final xy ॱ;
  private final CA<?>[] ॱˊ;
  private final String ॱॱ;
  private final xC ᐝ;
  
  CH(ˊ<R, T> paramˊ)
  {
    this.ˎ = paramˊ.ˊ.ˏ();
    this.ˊ = paramˊ.ʽॱ;
    this.ॱ = paramˊ.ˊ.ॱ();
    this.ʼ = paramˊ.ˈ;
    this.ʻ = paramˊ.ˋॱ;
    this.ॱॱ = paramˊ.ᐝॱ;
    this.ʽ = paramˊ.ॱˋ;
    this.ᐝ = paramˊ.ॱˎ;
    this.ͺ = paramˊ.ͺ;
    this.ˊॱ = paramˊ.ॱˊ;
    this.ˏॱ = paramˊ.ʻॱ;
    this.ॱˊ = paramˊ.ʿ;
  }
  
  static Set<String> ˏ(String paramString)
  {
    paramString = ˋ.matcher(paramString);
    LinkedHashSet localLinkedHashSet = new LinkedHashSet();
    while (paramString.find()) {
      localLinkedHashSet.add(paramString.group(1));
    }
    return localLinkedHashSet;
  }
  
  static Class<?> ॱ(Class<?> paramClass)
  {
    if (Boolean.TYPE == paramClass) {
      return Boolean.class;
    }
    if (Byte.TYPE == paramClass) {
      return Byte.class;
    }
    if (Character.TYPE == paramClass) {
      return Character.class;
    }
    if (Double.TYPE == paramClass) {
      return Double.class;
    }
    if (Float.TYPE == paramClass) {
      return Float.class;
    }
    if (Integer.TYPE == paramClass) {
      return Integer.class;
    }
    if (Long.TYPE == paramClass) {
      return Long.class;
    }
    if (Short.TYPE == paramClass) {
      return Short.class;
    }
    return paramClass;
  }
  
  R ˎ(xF paramXF)
  {
    return this.ʼ.ˎ(paramXF);
  }
  
  xG ॱ(Object... paramVarArgs)
  {
    CF localCF = new CF(this.ʻ, this.ॱ, this.ॱॱ, this.ʽ, this.ᐝ, this.ͺ, this.ˊॱ, this.ˏॱ);
    CA[] arrayOfCA = this.ॱˊ;
    int i;
    if (paramVarArgs != null) {
      i = paramVarArgs.length;
    } else {
      i = 0;
    }
    if (i != arrayOfCA.length) {
      throw new IllegalArgumentException("Argument count (" + i + ") doesn't match expected count (" + arrayOfCA.length + ")");
    }
    int j = 0;
    while (j < i)
    {
      arrayOfCA[j].ˊ(localCF, paramVarArgs[j]);
      j += 1;
    }
    return localCF.ˋ();
  }
  
  static final class ˊ<T, R>
  {
    private static int ʼॱ = 21;
    private static char[] ʾ;
    private static boolean ˉ;
    private static int ˊˊ;
    private static boolean ˊᐝ;
    private static int ˋˊ = 0;
    Type ʻ;
    boolean ʻॱ;
    boolean ʼ;
    boolean ʽ;
    Cw<T, R> ʽॱ;
    CA<?>[] ʿ;
    Cy<xF, T> ˈ;
    final CI ˊ;
    boolean ˊॱ;
    final Method ˋ;
    String ˋॱ;
    final Annotation[] ˎ;
    final Annotation[][] ˏ;
    boolean ˏॱ;
    boolean ͺ;
    final Type[] ॱ;
    boolean ॱˊ;
    xz ॱˋ;
    xC ॱˎ;
    boolean ॱॱ;
    Set<String> ॱᐝ;
    boolean ᐝ;
    String ᐝॱ;
    
    static
    {
      ˊˊ = 1;
      ˊᐝ = true;
      ˉ = true;
      ʾ = new char[] { 85, 102, 138, 122, 135, 142, 98, 118, 133, 53, 128, 136, 130, 137, 119, 132, 123, 104, 126, 131, 124, 79, 93, 121, 91, 129, 101 };
    }
    
    ˊ(CI paramCI, Method paramMethod)
    {
      this.ˊ = paramCI;
      this.ˋ = paramMethod;
      this.ˎ = paramMethod.getAnnotations();
      this.ॱ = paramMethod.getGenericParameterTypes();
      this.ˏ = paramMethod.getParameterAnnotations();
    }
    
    private xz ˊ(String[] paramArrayOfString)
    {
      break label139;
      int i;
      String str = paramArrayOfString[i];
      int j = str.indexOf(':');
      label27:
      label55:
      xz.if localIf;
      Object localObject;
      if (j == -1)
      {
        break label221;
        switch (j)
        {
        default: 
          break;
          localIf.ˎ((String)localObject, str);
          break label342;
          j = ˊˊ + 107;
          ˋˊ = j % 128;
          if (j % 2 != 0) {}
          break;
        }
      }
      for (;;)
      {
        break label366;
        label95:
        localIf = new xz.if();
        int k = paramArrayOfString.length;
        i = 0;
        break label366;
        for (;;)
        {
          switch (j)
          {
          default: 
            label113:
            break label302;
            label139:
            break label95;
            label142:
            j = 0;
          }
        }
        this.ॱˎ = ((xC)localObject);
        break label392;
        try
        {
          label156:
          localObject = str.substring(0, j);
          for (;;)
          {
            try
            {
              str = str.substring(j + 1);
              str = str.trim();
              boolean bool = "Content-Type".equalsIgnoreCase((String)localObject);
              if (!bool)
              {
                break label55;
                label202:
                throw ˋ("Malformed content type: %s", new Object[] { str });
                break;
                label221:
                throw ˋ("@Headers value must be in the form \"Name: Value\". Found: \"%s\"", new Object[] { str });
                j = 1;
                break label27;
                if (j != 0) {
                  break label345;
                }
                continue;
              }
              localObject = xC.ॱ(str);
              if (localObject != null)
              {
                continue;
                i = ˊˊ + 121;
                ˋˊ = i % 128;
                if (i % 2 != 0) {
                  break label389;
                }
                continue;
              }
              j = 0;
            }
            catch (Exception paramArrayOfString)
            {
              label302:
              throw paramArrayOfString;
            }
            j = ˋˊ + 33;
            ˊˊ = j % 128;
            if (j % 2 != 0) {
              continue;
            }
          }
        }
        catch (Exception paramArrayOfString)
        {
          throw paramArrayOfString;
        }
      }
      label342:
      label345:
      label366:
      label389:
      label392:
      for (;;)
      {
        i += 1;
        break;
        continue;
        int m = str.length();
        if (j == m - 1) {
          break label221;
        }
        break label156;
        if (i < k) {
          break label142;
        }
        j = 1;
        break label113;
        return localIf.ˎ();
        break label202;
      }
    }
    
    private RuntimeException ˋ(String paramString, Object... paramVarArgs)
    {
      for (;;)
      {
        paramString = ॱ(null, paramString, paramVarArgs);
        int i = 19 / 0;
        return paramString;
        i = 1;
        break label63;
        return ॱ(null, paramString, paramVarArgs);
        for (;;)
        {
          i = 0;
          break label63;
          i = ˊˊ + 45;
          ˋˊ = i % 128;
          if (i % 2 != 0) {
            break;
          }
        }
        label63:
        switch (i)
        {
        }
      }
    }
    
    /* Error */
    private CA<?> ˋ(int arg1, Type arg2, Annotation[] arg3)
    {
      // Byte code:
      //   0: goto +553 -> 553
      //   3: iconst_1
      //   4: istore 5
      //   6: iload 5
      //   8: tableswitch	default:+24->32, 0:+360->368, 1:+396->404
      //   32: goto +336 -> 368
      //   35: aload 7
      //   37: astore 8
      //   39: goto +258 -> 297
      //   42: getstatic 60	o/CH$ˊ:ˋˊ	I
      //   45: bipush 35
      //   47: iadd
      //   48: istore 5
      //   50: iload 5
      //   52: sipush 128
      //   55: irem
      //   56: putstatic 62	o/CH$ˊ:ˊˊ	I
      //   59: iload 5
      //   61: iconst_2
      //   62: irem
      //   63: ifne +6 -> 69
      //   66: goto +497 -> 563
      //   69: goto -34 -> 35
      //   72: iload 4
      //   74: lookupswitch	default:+26->100, 19:+118->192, 32:+93->167
      //   100: goto +67 -> 167
      //   103: aload_0
      //   104: iload_1
      //   105: aload_2
      //   106: aload_3
      //   107: aload_3
      //   108: iload 4
      //   110: aaload
      //   111: invokespecial 186	o/CH$ˊ:ॱ	(ILjava/lang/reflect/Type;[Ljava/lang/annotation/Annotation;Ljava/lang/annotation/Annotation;)Lo/CA;
      //   114: astore 7
      //   116: aload 7
      //   118: ifnonnull +6 -> 124
      //   121: goto +142 -> 263
      //   124: goto +411 -> 535
      //   127: bipush 33
      //   129: istore 5
      //   131: goto +439 -> 570
      //   134: iload 4
      //   136: lookupswitch	default:+28->164, 14:+202->338, 97:+279->415
      //   164: goto +174 -> 338
      //   167: iload 5
      //   169: istore 4
      //   171: goto +126 -> 297
      //   174: aload_0
      //   175: iload_1
      //   176: ldc -68
      //   178: iconst_0
      //   179: anewarray 5	java/lang/Object
      //   182: invokespecial 191	o/CH$ˊ:ˏ	(ILjava/lang/String;[Ljava/lang/Object;)Ljava/lang/RuntimeException;
      //   185: athrow
      //   186: iconst_0
      //   187: istore 5
      //   189: goto +10 -> 199
      //   192: iload 5
      //   194: istore 4
      //   196: goto +101 -> 297
      //   199: iload 5
      //   201: tableswitch	default:+23->224, 0:+109->310, 1:+-98->103
      //   224: goto +86 -> 310
      //   227: goto +57 -> 284
      //   230: goto +24 -> 254
      //   233: aload_0
      //   234: iload_1
      //   235: ldc -63
      //   237: iconst_1
      //   238: anewarray 5	java/lang/Object
      //   241: invokespecial 191	o/CH$ˊ:ˏ	(ILjava/lang/String;[Ljava/lang/Object;)Ljava/lang/RuntimeException;
      //   244: athrow
      //   245: goto -71 -> 174
      //   248: iconst_0
      //   249: istore 5
      //   251: goto -245 -> 6
      //   254: iload 4
      //   256: iconst_1
      //   257: iadd
      //   258: istore 4
      //   260: goto -218 -> 42
      //   263: goto +262 -> 525
      //   266: aload_0
      //   267: iload_1
      //   268: ldc -63
      //   270: iconst_0
      //   271: anewarray 5	java/lang/Object
      //   274: invokespecial 191	o/CH$ˊ:ˏ	(ILjava/lang/String;[Ljava/lang/Object;)Ljava/lang/RuntimeException;
      //   277: athrow
      //   278: iconst_1
      //   279: istore 5
      //   281: goto -82 -> 199
      //   284: aconst_null
      //   285: astore 8
      //   287: aload_3
      //   288: arraylength
      //   289: istore 6
      //   291: iconst_0
      //   292: istore 5
      //   294: goto +171 -> 465
      //   297: iload 4
      //   299: iload 6
      //   301: if_icmpge +6 -> 307
      //   304: goto -56 -> 248
      //   307: goto -304 -> 3
      //   310: aload_0
      //   311: iload_1
      //   312: aload_2
      //   313: aload_3
      //   314: aload_3
      //   315: iload 4
      //   317: aaload
      //   318: invokespecial 186	o/CH$ˊ:ॱ	(ILjava/lang/reflect/Type;[Ljava/lang/annotation/Annotation;Ljava/lang/annotation/Annotation;)Lo/CA;
      //   321: astore 7
      //   323: aconst_null
      //   324: arraylength
      //   325: istore 5
      //   327: aload 7
      //   329: ifnonnull +6 -> 335
      //   332: goto -69 -> 263
      //   335: goto +200 -> 535
      //   338: getstatic 62	o/CH$ˊ:ˊˊ	I
      //   341: bipush 87
      //   343: iadd
      //   344: istore 4
      //   346: iload 4
      //   348: sipush 128
      //   351: irem
      //   352: putstatic 60	o/CH$ˊ:ˋˊ	I
      //   355: iload 4
      //   357: iconst_2
      //   358: irem
      //   359: ifeq +6 -> 365
      //   362: goto -129 -> 233
      //   365: goto -99 -> 266
      //   368: getstatic 62	o/CH$ˊ:ˊˊ	I
      //   371: iconst_3
      //   372: iadd
      //   373: istore 5
      //   375: iload 5
      //   377: sipush 128
      //   380: irem
      //   381: putstatic 60	o/CH$ˊ:ˋˊ	I
      //   384: iload 5
      //   386: iconst_2
      //   387: irem
      //   388: ifeq +6 -> 394
      //   391: goto -205 -> 186
      //   394: goto -116 -> 278
      //   397: bipush 31
      //   399: istore 5
      //   401: goto +169 -> 570
      //   404: aload 8
      //   406: ifnonnull +6 -> 412
      //   409: goto +137 -> 546
      //   412: goto +144 -> 556
      //   415: aload 8
      //   417: areturn
      //   418: bipush 32
      //   420: istore 4
      //   422: goto -350 -> 72
      //   425: astore_2
      //   426: aload_2
      //   427: athrow
      //   428: getstatic 62	o/CH$ˊ:ˊˊ	I
      //   431: bipush 43
      //   433: iadd
      //   434: istore 4
      //   436: iload 4
      //   438: sipush 128
      //   441: irem
      //   442: putstatic 60	o/CH$ˊ:ˋˊ	I
      //   445: iload 4
      //   447: iconst_2
      //   448: irem
      //   449: ifeq +6 -> 455
      //   452: goto -225 -> 227
      //   455: goto -171 -> 284
      //   458: bipush 19
      //   460: istore 4
      //   462: goto -390 -> 72
      //   465: getstatic 62	o/CH$ˊ:ˊˊ	I
      //   468: bipush 39
      //   470: iadd
      //   471: istore 4
      //   473: iload 4
      //   475: sipush 128
      //   478: irem
      //   479: putstatic 60	o/CH$ˊ:ˋˊ	I
      //   482: iload 4
      //   484: iconst_2
      //   485: irem
      //   486: ifeq +6 -> 492
      //   489: goto -71 -> 418
      //   492: goto -34 -> 458
      //   495: getstatic 62	o/CH$ˊ:ˊˊ	I
      //   498: bipush 93
      //   500: iadd
      //   501: istore 4
      //   503: iload 4
      //   505: sipush 128
      //   508: irem
      //   509: putstatic 60	o/CH$ˊ:ˋˊ	I
      //   512: iload 4
      //   514: iconst_2
      //   515: irem
      //   516: ifeq +6 -> 522
      //   519: goto -274 -> 245
      //   522: goto -348 -> 174
      //   525: aload 8
      //   527: astore 7
      //   529: goto -275 -> 254
      //   532: astore_2
      //   533: aload_2
      //   534: athrow
      //   535: aload 8
      //   537: ifnull +6 -> 543
      //   540: goto -143 -> 397
      //   543: goto -416 -> 127
      //   546: bipush 14
      //   548: istore 4
      //   550: goto -416 -> 134
      //   553: goto -125 -> 428
      //   556: bipush 97
      //   558: istore 4
      //   560: goto -426 -> 134
      //   563: aload 7
      //   565: astore 8
      //   567: goto -270 -> 297
      //   570: iload 5
      //   572: lookupswitch	default:+28->600, 31:+-77->495, 33:+-342->230
      //   600: goto -105 -> 495
      // Exception table:
      //   from	to	target	type
      //   465	473	425	java/lang/Exception
      //   473	482	425	java/lang/Exception
    }
    
    private RuntimeException ˎ(Throwable paramThrowable, int paramInt, String paramString, Object... paramVarArgs)
    {
      for (;;)
      {
        paramInt = ˊˊ + 3;
        ˋˊ = paramInt % 128;
        if (paramInt % 2 == 0)
        {
          break label32;
          break label46;
          label32:
          paramInt = 23;
          break;
          return paramThrowable;
        }
        else
        {
          paramInt = 33;
          break;
        }
        label46:
        paramThrowable = ॱ(paramThrowable, paramString + " (parameter #" + (paramInt + 1) + ")", paramVarArgs);
      }
      switch (paramInt)
      {
      }
      paramInt = 44 / 0;
      return paramThrowable;
    }
    
    /* Error */
    private static String ˎ(byte[] paramArrayOfByte, int[] paramArrayOfInt, char[] paramArrayOfChar, int paramInt)
    {
      // Byte code:
      //   0: goto +451 -> 451
      //   3: iload 5
      //   5: tableswitch	default:+23->28, 0:+232->237, 1:+92->97
      //   28: goto +209 -> 237
      //   31: iload 4
      //   33: iload 7
      //   35: if_icmpge +6 -> 41
      //   38: goto +193 -> 231
      //   41: goto +369 -> 410
      //   44: goto +114 -> 158
      //   47: goto -16 -> 31
      //   50: bipush 60
      //   52: istore 4
      //   54: goto +365 -> 419
      //   57: aload_1
      //   58: iload 4
      //   60: aload 8
      //   62: aload_0
      //   63: iload 5
      //   65: iconst_1
      //   66: isub
      //   67: iload 4
      //   69: isub
      //   70: baload
      //   71: iload_3
      //   72: iadd
      //   73: caload
      //   74: iload 6
      //   76: isub
      //   77: i2c
      //   78: castore
      //   79: iload 4
      //   81: iconst_1
      //   82: iadd
      //   83: istore 4
      //   85: goto +312 -> 397
      //   88: new 131	java/lang/String
      //   91: dup
      //   92: aload_1
      //   93: invokespecial 217	java/lang/String:<init>	([C)V
      //   96: areturn
      //   97: getstatic 62	o/CH$ˊ:ˊˊ	I
      //   100: bipush 89
      //   102: iadd
      //   103: istore 5
      //   105: iload 5
      //   107: sipush 128
      //   110: irem
      //   111: putstatic 60	o/CH$ˊ:ˋˊ	I
      //   114: iload 5
      //   116: iconst_2
      //   117: irem
      //   118: ifeq +6 -> 124
      //   121: goto -77 -> 44
      //   124: goto +34 -> 158
      //   127: aload_0
      //   128: iload 4
      //   130: aload 8
      //   132: aload_1
      //   133: iload 7
      //   135: iconst_1
      //   136: isub
      //   137: iload 4
      //   139: isub
      //   140: iaload
      //   141: iload_3
      //   142: isub
      //   143: caload
      //   144: iload 6
      //   146: isub
      //   147: i2c
      //   148: castore
      //   149: iload 4
      //   151: iconst_1
      //   152: iadd
      //   153: istore 4
      //   155: goto -108 -> 47
      //   158: aload_0
      //   159: iload 4
      //   161: aload 8
      //   163: aload_2
      //   164: iload 7
      //   166: iconst_1
      //   167: isub
      //   168: iload 4
      //   170: isub
      //   171: caload
      //   172: iload_3
      //   173: isub
      //   174: caload
      //   175: iload 6
      //   177: isub
      //   178: i2c
      //   179: castore
      //   180: iload 4
      //   182: iconst_1
      //   183: iadd
      //   184: istore 4
      //   186: goto +169 -> 355
      //   189: iload 4
      //   191: iload 7
      //   193: if_icmpge +6 -> 199
      //   196: goto +147 -> 343
      //   199: goto +150 -> 349
      //   202: iload 5
      //   204: tableswitch	default:+24->228, 0:+-77->127, 1:+75->279
      //   228: goto +51 -> 279
      //   231: iconst_0
      //   232: istore 5
      //   234: goto -32 -> 202
      //   237: new 131	java/lang/String
      //   240: dup
      //   241: aload_0
      //   242: invokespecial 217	java/lang/String:<init>	([C)V
      //   245: areturn
      //   246: getstatic 62	o/CH$ˊ:ˊˊ	I
      //   249: bipush 53
      //   251: iadd
      //   252: istore 7
      //   254: iload 7
      //   256: sipush 128
      //   259: irem
      //   260: putstatic 60	o/CH$ˊ:ˋˊ	I
      //   263: iload 7
      //   265: iconst_2
      //   266: irem
      //   267: ifeq +6 -> 273
      //   270: goto +18 -> 288
      //   273: goto -216 -> 57
      //   276: goto -87 -> 189
      //   279: new 131	java/lang/String
      //   282: dup
      //   283: aload_0
      //   284: invokespecial 217	java/lang/String:<init>	([C)V
      //   287: areturn
      //   288: goto -231 -> 57
      //   291: aload_0
      //   292: arraylength
      //   293: istore 5
      //   295: iload 5
      //   297: newarray char
      //   299: astore_1
      //   300: iconst_0
      //   301: istore 4
      //   303: goto +94 -> 397
      //   306: aload_2
      //   307: arraylength
      //   308: istore 7
      //   310: iload 7
      //   312: newarray char
      //   314: astore_0
      //   315: iconst_0
      //   316: istore 4
      //   318: goto -129 -> 189
      //   321: getstatic 95	o/CH$ˊ:ʾ	[C
      //   324: astore 8
      //   326: getstatic 97	o/CH$ˊ:ʼॱ	I
      //   329: istore 6
      //   331: getstatic 64	o/CH$ˊ:ˊᐝ	Z
      //   334: ifeq +6 -> 340
      //   337: goto +132 -> 469
      //   340: goto -290 -> 50
      //   343: iconst_1
      //   344: istore 5
      //   346: goto -343 -> 3
      //   349: iconst_0
      //   350: istore 5
      //   352: goto -349 -> 3
      //   355: getstatic 60	o/CH$ˊ:ˋˊ	I
      //   358: bipush 45
      //   360: iadd
      //   361: istore 5
      //   363: iload 5
      //   365: sipush 128
      //   368: irem
      //   369: putstatic 62	o/CH$ˊ:ˊˊ	I
      //   372: iload 5
      //   374: iconst_2
      //   375: irem
      //   376: ifne +6 -> 382
      //   379: goto -103 -> 276
      //   382: goto +34 -> 416
      //   385: getstatic 66	o/CH$ˊ:ˉ	Z
      //   388: ifeq +6 -> 394
      //   391: goto -85 -> 306
      //   394: goto +60 -> 454
      //   397: iload 4
      //   399: iload 5
      //   401: if_icmpge +6 -> 407
      //   404: goto -158 -> 246
      //   407: goto -319 -> 88
      //   410: iconst_1
      //   411: istore 5
      //   413: goto -211 -> 202
      //   416: goto -227 -> 189
      //   419: iload 4
      //   421: lookupswitch	default:+27->448, 15:+-130->291, 60:+-36->385
      //   448: goto -157 -> 291
      //   451: goto -130 -> 321
      //   454: aload_1
      //   455: arraylength
      //   456: istore 7
      //   458: iload 7
      //   460: newarray char
      //   462: astore_0
      //   463: iconst_0
      //   464: istore 4
      //   466: goto -435 -> 31
      //   469: bipush 15
      //   471: istore 4
      //   473: goto -54 -> 419
      //   476: astore_0
      //   477: aload_0
      //   478: athrow
      //   479: astore_0
      //   480: aload_0
      //   481: athrow
      // Local variable table:
      //   start	length	slot	name	signature
      //   0	482	0	paramArrayOfByte	byte[]
      //   0	482	1	paramArrayOfInt	int[]
      //   0	482	2	paramArrayOfChar	char[]
      //   0	482	3	paramInt	int
      //   31	441	4	i	int
      //   3	409	5	j	int
      //   74	256	6	k	int
      //   33	426	7	m	int
      //   60	265	8	arrayOfChar	char[]
      // Exception table:
      //   from	to	target	type
      //   105	114	476	java/lang/Exception
      //   97	105	479	java/lang/Exception
      //   105	114	479	java/lang/Exception
    }
    
    /* Error */
    private Cw<T, R> ˎ()
    {
      // Byte code:
      //   0: goto +9 -> 9
      //   3: bipush 9
      //   5: istore_1
      //   6: goto +205 -> 211
      //   9: goto +131 -> 140
      //   12: iconst_0
      //   13: istore_1
      //   14: goto +147 -> 161
      //   17: getstatic 62	o/CH$ˊ:ˊˊ	I
      //   20: bipush 17
      //   22: iadd
      //   23: istore_1
      //   24: iload_1
      //   25: sipush 128
      //   28: irem
      //   29: putstatic 60	o/CH$ˊ:ˋˊ	I
      //   32: iload_1
      //   33: iconst_2
      //   34: irem
      //   35: ifeq +6 -> 41
      //   38: goto +148 -> 186
      //   41: aload_0
      //   42: ldc -34
      //   44: iconst_0
      //   45: anewarray 5	java/lang/Object
      //   48: invokespecial 165	o/CH$ˊ:ˋ	(Ljava/lang/String;[Ljava/lang/Object;)Ljava/lang/RuntimeException;
      //   51: athrow
      //   52: aload_0
      //   53: getfield 106	o/CH$ˊ:ˋ	Ljava/lang/reflect/Method;
      //   56: astore_3
      //   57: aload_3
      //   58: invokevirtual 112	java/lang/reflect/Method:getAnnotations	()[Ljava/lang/annotation/Annotation;
      //   61: astore_3
      //   62: aload_0
      //   63: getfield 104	o/CH$ˊ:ˊ	Lo/CI;
      //   66: aload_2
      //   67: aload_3
      //   68: invokevirtual 227	o/CI:ˎ	(Ljava/lang/reflect/Type;[Ljava/lang/annotation/Annotation;)Lo/Cw;
      //   71: astore_3
      //   72: goto +205 -> 277
      //   75: astore_2
      //   76: aload_2
      //   77: athrow
      //   78: iload_1
      //   79: lookupswitch	default:+25->104, 42:+-27->52, 47:+-62->17
      //   104: goto -52 -> 52
      //   107: aload_0
      //   108: ldc -27
      //   110: iconst_1
      //   111: anewarray 5	java/lang/Object
      //   114: dup
      //   115: iconst_0
      //   116: aload_2
      //   117: aastore
      //   118: invokespecial 165	o/CH$ˊ:ˋ	(Ljava/lang/String;[Ljava/lang/Object;)Ljava/lang/RuntimeException;
      //   121: athrow
      //   122: iconst_1
      //   123: istore_1
      //   124: goto +37 -> 161
      //   127: aload_2
      //   128: getstatic 235	java/lang/Void:TYPE	Ljava/lang/Class;
      //   131: if_acmpne +6 -> 137
      //   134: goto +63 -> 197
      //   137: goto +111 -> 248
      //   140: aload_0
      //   141: getfield 106	o/CH$ˊ:ˋ	Ljava/lang/reflect/Method;
      //   144: invokevirtual 239	java/lang/reflect/Method:getGenericReturnType	()Ljava/lang/reflect/Type;
      //   147: astore_2
      //   148: aload_2
      //   149: invokestatic 244	o/CM:ˋ	(Ljava/lang/reflect/Type;)Z
      //   152: ifeq +6 -> 158
      //   155: goto -152 -> 3
      //   158: goto +96 -> 254
      //   161: iload_1
      //   162: tableswitch	default:+22->184, 0:+41->203, 1:+81->243
      //   184: aload_3
      //   185: areturn
      //   186: aload_0
      //   187: ldc -34
      //   189: iconst_1
      //   190: anewarray 5	java/lang/Object
      //   193: invokespecial 165	o/CH$ˊ:ˋ	(Ljava/lang/String;[Ljava/lang/Object;)Ljava/lang/RuntimeException;
      //   196: athrow
      //   197: bipush 47
      //   199: istore_1
      //   200: goto -122 -> 78
      //   203: new 246	java/lang/NullPointerException
      //   206: dup
      //   207: invokespecial 247	java/lang/NullPointerException:<init>	()V
      //   210: athrow
      //   211: iload_1
      //   212: lookupswitch	default:+28->240, 9:+-105->107, 96:+-85->127
      //   240: goto -113 -> 127
      //   243: aload_3
      //   244: areturn
      //   245: astore_2
      //   246: aload_2
      //   247: athrow
      //   248: bipush 42
      //   250: istore_1
      //   251: goto -173 -> 78
      //   254: bipush 96
      //   256: istore_1
      //   257: goto -46 -> 211
      //   260: astore_3
      //   261: aload_0
      //   262: aload_3
      //   263: ldc -7
      //   265: iconst_1
      //   266: anewarray 5	java/lang/Object
      //   269: dup
      //   270: iconst_0
      //   271: aload_2
      //   272: aastore
      //   273: invokespecial 182	o/CH$ˊ:ॱ	(Ljava/lang/Throwable;Ljava/lang/String;[Ljava/lang/Object;)Ljava/lang/RuntimeException;
      //   276: athrow
      //   277: getstatic 62	o/CH$ˊ:ˊˊ	I
      //   280: bipush 93
      //   282: iadd
      //   283: istore_1
      //   284: iload_1
      //   285: sipush 128
      //   288: irem
      //   289: putstatic 60	o/CH$ˊ:ˋˊ	I
      //   292: iload_1
      //   293: iconst_2
      //   294: irem
      //   295: ifeq +6 -> 301
      //   298: goto -286 -> 12
      //   301: goto -179 -> 122
      // Local variable table:
      //   start	length	slot	name	signature
      //   0	304	0	this	ˊ
      //   5	290	1	i	int
      //   66	1	2	localType1	Type
      //   75	53	2	localException1	Exception
      //   147	2	2	localType2	Type
      //   245	27	2	localException2	Exception
      //   56	188	3	localObject	Object
      //   260	3	3	localRuntimeException	RuntimeException
      // Exception table:
      //   from	to	target	type
      //   277	284	75	java/lang/Exception
      //   284	292	75	java/lang/Exception
      //   52	57	245	java/lang/Exception
      //   57	62	245	java/lang/Exception
      //   62	72	245	java/lang/Exception
      //   62	72	260	java/lang/RuntimeException
    }
    
    private void ˎ(int paramInt, String paramString)
    {
      break label107;
      int i = 80;
      break label77;
      label9:
      i = 30;
      break label77;
      label15:
      break label203;
      Object localObject;
      for (;;)
      {
        throw ˏ(paramInt, "URL \"%s\" does not contain \"{%s}\".", new Object[] { this.ᐝॱ, paramString });
        localObject = new Object[4];
        localObject[0] = this.ᐝॱ;
        localObject[0] = paramString;
        throw ˏ(paramInt, "URL \"%s\" does not contain \"{%s}\".", (Object[])localObject);
        break;
        label73:
        paramInt = null.length;
        return;
        label77:
        switch (i)
        {
        }
      }
      label107:
      break label275;
      label110:
      i = 24;
      for (;;)
      {
        try
        {
          localObject = CH.ˋ;
          localObject = ((Pattern)localObject).pattern();
          throw ˏ(paramInt, "@Path parameter name must match %s. Found: %s", new Object[] { localObject, paramString });
        }
        catch (Exception paramString)
        {
          label203:
          throw paramString;
        }
        switch (i)
        {
        }
        i = ˊˊ + 43;
        ˋˊ = i % 128;
        if (i % 2 != 0) {
          break;
        }
        break label9;
        if (CH.ˏ.matcher(paramString).matches())
        {
          continue;
          paramInt = ˊˊ + 97;
          ˋˊ = paramInt % 128;
          if (paramInt % 2 != 0) {
            break label73;
          }
          return;
          i = 59;
          continue;
          if (!this.ॱᐝ.contains(paramString)) {
            break label110;
          }
          continue;
          label275:
          i = ˊˊ + 93;
          ˋˊ = i % 128;
          if (i % 2 != 0) {
            break label15;
          }
        }
      }
    }
    
    /* Error */
    private RuntimeException ˏ(int paramInt, String paramString, Object... paramVarArgs)
    {
      // Byte code:
      //   0: goto +45 -> 45
      //   3: astore_2
      //   4: aload_2
      //   5: athrow
      //   6: iload_1
      //   7: tableswitch	default:+21->28, 0:+28->35, 1:+30->37
      //   28: aload_2
      //   29: areturn
      //   30: iconst_1
      //   31: istore_1
      //   32: goto -26 -> 6
      //   35: aload_2
      //   36: areturn
      //   37: aconst_null
      //   38: arraylength
      //   39: istore_1
      //   40: aload_2
      //   41: areturn
      //   42: astore_2
      //   43: aload_2
      //   44: athrow
      //   45: new 198	java/lang/StringBuilder
      //   48: dup
      //   49: invokespecial 199	java/lang/StringBuilder:<init>	()V
      //   52: astore 4
      //   54: aload 4
      //   56: aload_2
      //   57: invokevirtual 203	java/lang/StringBuilder:append	(Ljava/lang/String;)Ljava/lang/StringBuilder;
      //   60: astore_2
      //   61: aload_2
      //   62: ldc -51
      //   64: invokevirtual 203	java/lang/StringBuilder:append	(Ljava/lang/String;)Ljava/lang/StringBuilder;
      //   67: astore_2
      //   68: aload_2
      //   69: iload_1
      //   70: iconst_1
      //   71: iadd
      //   72: invokevirtual 208	java/lang/StringBuilder:append	(I)Ljava/lang/StringBuilder;
      //   75: astore_2
      //   76: aload_0
      //   77: aload_2
      //   78: ldc -46
      //   80: invokevirtual 203	java/lang/StringBuilder:append	(Ljava/lang/String;)Ljava/lang/StringBuilder;
      //   83: invokevirtual 213	java/lang/StringBuilder:toString	()Ljava/lang/String;
      //   86: aload_3
      //   87: invokespecial 165	o/CH$ˊ:ˋ	(Ljava/lang/String;[Ljava/lang/Object;)Ljava/lang/RuntimeException;
      //   90: astore_2
      //   91: goto +8 -> 99
      //   94: iconst_0
      //   95: istore_1
      //   96: goto -90 -> 6
      //   99: getstatic 62	o/CH$ˊ:ˊˊ	I
      //   102: bipush 61
      //   104: iadd
      //   105: istore_1
      //   106: iload_1
      //   107: sipush 128
      //   110: irem
      //   111: putstatic 60	o/CH$ˊ:ˋˊ	I
      //   114: iload_1
      //   115: iconst_2
      //   116: irem
      //   117: ifeq +6 -> 123
      //   120: goto -90 -> 30
      //   123: goto -29 -> 94
      // Local variable table:
      //   start	length	slot	name	signature
      //   0	126	0	this	ˊ
      //   0	126	1	paramInt	int
      //   0	126	2	paramString	String
      //   0	126	3	paramVarArgs	Object[]
      //   52	3	4	localStringBuilder	StringBuilder
      // Exception table:
      //   from	to	target	type
      //   68	76	3	java/lang/Exception
      //   54	61	42	java/lang/Exception
      //   61	68	42	java/lang/Exception
      //   68	76	42	java/lang/Exception
      //   76	91	42	java/lang/Exception
    }
    
    /* Error */
    private Cy<xF, T> ˏ()
    {
      // Byte code:
      //   0: goto +154 -> 154
      //   3: getstatic 62	o/CH$ˊ:ˊˊ	I
      //   6: istore_1
      //   7: iload_1
      //   8: bipush 41
      //   10: iadd
      //   11: istore_1
      //   12: iload_1
      //   13: sipush 128
      //   16: irem
      //   17: putstatic 60	o/CH$ˊ:ˋˊ	I
      //   20: iload_1
      //   21: iconst_2
      //   22: irem
      //   23: ifeq +6 -> 29
      //   26: goto +125 -> 151
      //   29: goto +37 -> 66
      //   32: iconst_1
      //   33: istore_1
      //   34: goto +56 -> 90
      //   37: aconst_null
      //   38: arraylength
      //   39: istore_1
      //   40: aload_2
      //   41: areturn
      //   42: astore_2
      //   43: aload_0
      //   44: aload_2
      //   45: ldc_w 288
      //   48: iconst_1
      //   49: anewarray 5	java/lang/Object
      //   52: dup
      //   53: iconst_0
      //   54: aload_0
      //   55: getfield 290	o/CH$ˊ:ʻ	Ljava/lang/reflect/Type;
      //   58: aastore
      //   59: invokespecial 182	o/CH$ˊ:ॱ	(Ljava/lang/Throwable;Ljava/lang/String;[Ljava/lang/Object;)Ljava/lang/RuntimeException;
      //   62: athrow
      //   63: astore_2
      //   64: aload_2
      //   65: athrow
      //   66: aload_0
      //   67: getfield 106	o/CH$ˊ:ˋ	Ljava/lang/reflect/Method;
      //   70: invokevirtual 112	java/lang/reflect/Method:getAnnotations	()[Ljava/lang/annotation/Annotation;
      //   73: astore_2
      //   74: aload_0
      //   75: getfield 104	o/CH$ˊ:ˊ	Lo/CI;
      //   78: aload_0
      //   79: getfield 290	o/CH$ˊ:ʻ	Ljava/lang/reflect/Type;
      //   82: aload_2
      //   83: invokevirtual 293	o/CI:ॱ	(Ljava/lang/reflect/Type;[Ljava/lang/annotation/Annotation;)Lo/Cy;
      //   86: astore_2
      //   87: goto +27 -> 114
      //   90: iload_1
      //   91: tableswitch	default:+21->112, 0:+50->141, 1:+-54->37
      //   112: aload_2
      //   113: areturn
      //   114: getstatic 62	o/CH$ˊ:ˊˊ	I
      //   117: bipush 79
      //   119: iadd
      //   120: istore_1
      //   121: iload_1
      //   122: sipush 128
      //   125: irem
      //   126: putstatic 60	o/CH$ˊ:ˋˊ	I
      //   129: iload_1
      //   130: iconst_2
      //   131: irem
      //   132: ifeq +6 -> 138
      //   135: goto -103 -> 32
      //   138: goto +8 -> 146
      //   141: aload_2
      //   142: areturn
      //   143: astore_2
      //   144: aload_2
      //   145: athrow
      //   146: iconst_0
      //   147: istore_1
      //   148: goto -58 -> 90
      //   151: goto -85 -> 66
      //   154: goto -151 -> 3
      // Local variable table:
      //   start	length	slot	name	signature
      //   0	157	0	this	ˊ
      //   6	142	1	i	int
      //   40	1	2	localCy	Cy<xF, T>
      //   42	3	2	localRuntimeException	RuntimeException
      //   63	2	2	localException1	Exception
      //   73	69	2	localObject	Object
      //   143	2	2	localException2	Exception
      // Exception table:
      //   from	to	target	type
      //   74	87	42	java/lang/RuntimeException
      //   3	7	63	java/lang/Exception
      //   114	121	63	java/lang/Exception
      //   121	129	63	java/lang/Exception
      //   12	20	143	java/lang/Exception
    }
    
    /* Error */
    private void ˏ(String paramString1, String paramString2, boolean paramBoolean)
    {
      // Byte code:
      //   0: goto +436 -> 436
      //   3: iconst_0
      //   4: anewarray 5	java/lang/Object
      //   7: astore_2
      //   8: aload_2
      //   9: iconst_0
      //   10: aload_1
      //   11: aastore
      //   12: aload_0
      //   13: ldc_w 297
      //   16: aload_2
      //   17: invokespecial 165	o/CH$ˊ:ˋ	(Ljava/lang/String;[Ljava/lang/Object;)Ljava/lang/RuntimeException;
      //   20: athrow
      //   21: getstatic 62	o/CH$ˊ:ˊˊ	I
      //   24: bipush 37
      //   26: iadd
      //   27: istore 4
      //   29: iload 4
      //   31: sipush 128
      //   34: irem
      //   35: putstatic 60	o/CH$ˊ:ˋˊ	I
      //   38: iload 4
      //   40: iconst_2
      //   41: irem
      //   42: ifeq +6 -> 48
      //   45: goto +26 -> 71
      //   48: iconst_0
      //   49: istore 4
      //   51: goto +272 -> 323
      //   54: astore_1
      //   55: aload_1
      //   56: athrow
      //   57: bipush 67
      //   59: istore 4
      //   61: goto +232 -> 293
      //   64: bipush 24
      //   66: istore 4
      //   68: goto +46 -> 114
      //   71: iconst_1
      //   72: istore 4
      //   74: goto +249 -> 323
      //   77: aload_2
      //   78: invokevirtual 176	java/lang/String:length	()I
      //   81: istore 4
      //   83: iload 5
      //   85: iload 4
      //   87: iconst_0
      //   88: iushr
      //   89: if_icmpge +6 -> 95
      //   92: goto +347 -> 439
      //   95: goto +398 -> 493
      //   98: aload_0
      //   99: ldc_w 297
      //   102: iconst_1
      //   103: anewarray 5	java/lang/Object
      //   106: dup
      //   107: iconst_0
      //   108: aload_1
      //   109: aastore
      //   110: invokespecial 165	o/CH$ˊ:ˋ	(Ljava/lang/String;[Ljava/lang/Object;)Ljava/lang/RuntimeException;
      //   113: athrow
      //   114: iload 4
      //   116: lookupswitch	default:+28->144, 24:+377->493, 83:+-95->21
      //   144: goto -123 -> 21
      //   147: bipush 39
      //   149: iconst_0
      //   150: idiv
      //   151: istore 4
      //   153: return
      //   154: iload 4
      //   156: lookupswitch	default:+28->184, 57:+198->354, 73:+337->493
      //   184: goto +309 -> 493
      //   187: aload_2
      //   188: bipush 63
      //   190: invokevirtual 135	java/lang/String:indexOf	(I)I
      //   193: istore 5
      //   195: iload 5
      //   197: iconst_m1
      //   198: if_icmpeq +6 -> 204
      //   201: goto +64 -> 265
      //   204: bipush 73
      //   206: istore 4
      //   208: goto -54 -> 154
      //   211: bipush 33
      //   213: istore 4
      //   215: goto +78 -> 293
      //   218: getstatic 62	o/CH$ˊ:ˊˊ	I
      //   221: bipush 31
      //   223: iadd
      //   224: istore 4
      //   226: iload 4
      //   228: sipush 128
      //   231: irem
      //   232: putstatic 60	o/CH$ˊ:ˋˊ	I
      //   235: iload 4
      //   237: iconst_2
      //   238: irem
      //   239: ifeq +6 -> 245
      //   242: goto +109 -> 351
      //   245: goto +222 -> 467
      //   248: iload 5
      //   250: aload_2
      //   251: invokevirtual 176	java/lang/String:length	()I
      //   254: iconst_1
      //   255: isub
      //   256: if_icmpge +6 -> 262
      //   259: goto +180 -> 439
      //   262: goto +231 -> 493
      //   265: bipush 57
      //   267: istore 4
      //   269: goto -115 -> 154
      //   272: aload_0
      //   273: aload_1
      //   274: putfield 299	o/CH$ˊ:ˋॱ	Ljava/lang/String;
      //   277: aload_0
      //   278: iload_3
      //   279: putfield 301	o/CH$ˊ:ͺ	Z
      //   282: aload_2
      //   283: invokevirtual 304	java/lang/String:isEmpty	()Z
      //   286: ifeq +4 -> 290
      //   289: return
      //   290: goto -103 -> 187
      //   293: iload 4
      //   295: lookupswitch	default:+25->320, 33:+-218->77, 67:+-47->248
      //   320: goto -72 -> 248
      //   323: iload 4
      //   325: tableswitch	default:+23->348, 0:+-227->98, 1:+-322->3
      //   348: goto -345 -> 3
      //   351: goto +116 -> 467
      //   354: getstatic 62	o/CH$ˊ:ˊˊ	I
      //   357: bipush 73
      //   359: iadd
      //   360: istore 4
      //   362: iload 4
      //   364: sipush 128
      //   367: irem
      //   368: putstatic 60	o/CH$ˊ:ˋˊ	I
      //   371: iload 4
      //   373: iconst_2
      //   374: irem
      //   375: ifeq +6 -> 381
      //   378: goto -167 -> 211
      //   381: goto -324 -> 57
      //   384: aload_0
      //   385: getfield 299	o/CH$ˊ:ˋॱ	Ljava/lang/String;
      //   388: ifnull +6 -> 394
      //   391: goto -173 -> 218
      //   394: goto -122 -> 272
      //   397: bipush 83
      //   399: istore 4
      //   401: goto -287 -> 114
      //   404: getstatic 62	o/CH$ˊ:ˊˊ	I
      //   407: istore 4
      //   409: iload 4
      //   411: bipush 13
      //   413: iadd
      //   414: istore 4
      //   416: iload 4
      //   418: sipush 128
      //   421: irem
      //   422: putstatic 60	o/CH$ˊ:ˋˊ	I
      //   425: iload 4
      //   427: iconst_2
      //   428: irem
      //   429: ifeq +6 -> 435
      //   432: goto -285 -> 147
      //   435: return
      //   436: goto -52 -> 384
      //   439: aload_2
      //   440: iload 5
      //   442: iconst_1
      //   443: iadd
      //   444: invokevirtual 150	java/lang/String:substring	(I)Ljava/lang/String;
      //   447: astore_1
      //   448: getstatic 258	o/CH:ˋ	Ljava/util/regex/Pattern;
      //   451: aload_1
      //   452: invokevirtual 271	java/util/regex/Pattern:matcher	(Ljava/lang/CharSequence;)Ljava/util/regex/Matcher;
      //   455: invokevirtual 307	java/util/regex/Matcher:find	()Z
      //   458: ifeq +6 -> 464
      //   461: goto -64 -> 397
      //   464: goto -400 -> 64
      //   467: aload_0
      //   468: ldc_w 309
      //   471: iconst_2
      //   472: anewarray 5	java/lang/Object
      //   475: dup
      //   476: iconst_0
      //   477: aload_0
      //   478: getfield 299	o/CH$ˊ:ˋॱ	Ljava/lang/String;
      //   481: aastore
      //   482: dup
      //   483: iconst_1
      //   484: aload_1
      //   485: aastore
      //   486: invokespecial 165	o/CH$ˊ:ˋ	(Ljava/lang/String;[Ljava/lang/Object;)Ljava/lang/RuntimeException;
      //   489: athrow
      //   490: astore_1
      //   491: aload_1
      //   492: athrow
      //   493: aload_0
      //   494: aload_2
      //   495: putfield 255	o/CH$ˊ:ᐝॱ	Ljava/lang/String;
      //   498: aload_0
      //   499: aload_2
      //   500: invokestatic 312	o/CH:ˏ	(Ljava/lang/String;)Ljava/util/Set;
      //   503: putfield 279	o/CH$ˊ:ॱᐝ	Ljava/util/Set;
      //   506: goto -102 -> 404
      // Local variable table:
      //   start	length	slot	name	signature
      //   0	509	0	this	ˊ
      //   0	509	1	paramString1	String
      //   0	509	2	paramString2	String
      //   0	509	3	paramBoolean	boolean
      //   27	402	4	i	int
      //   83	361	5	j	int
      // Exception table:
      //   from	to	target	type
      //   77	83	54	java/lang/Exception
      //   404	409	54	java/lang/Exception
      //   416	425	490	java/lang/Exception
    }
    
    /* Error */
    private RuntimeException ॱ(Throwable paramThrowable, String paramString, Object... paramVarArgs)
    {
      // Byte code:
      //   0: goto +34 -> 34
      //   3: astore_1
      //   4: aload_1
      //   5: athrow
      //   6: getstatic 60	o/CH$ˊ:ˋˊ	I
      //   9: bipush 49
      //   11: iadd
      //   12: istore 4
      //   14: iload 4
      //   16: sipush 128
      //   19: irem
      //   20: putstatic 62	o/CH$ˊ:ˊˊ	I
      //   23: iload 4
      //   25: iconst_2
      //   26: irem
      //   27: ifne +5 -> 32
      //   30: aload_1
      //   31: areturn
      //   32: aload_1
      //   33: areturn
      //   34: aload_2
      //   35: aload_3
      //   36: invokestatic 316	java/lang/String:format	(Ljava/lang/String;[Ljava/lang/Object;)Ljava/lang/String;
      //   39: astore_2
      //   40: new 198	java/lang/StringBuilder
      //   43: dup
      //   44: invokespecial 199	java/lang/StringBuilder:<init>	()V
      //   47: astore_3
      //   48: aload_3
      //   49: aload_2
      //   50: invokevirtual 203	java/lang/StringBuilder:append	(Ljava/lang/String;)Ljava/lang/StringBuilder;
      //   53: astore_2
      //   54: aload_2
      //   55: ldc_w 318
      //   58: invokevirtual 203	java/lang/StringBuilder:append	(Ljava/lang/String;)Ljava/lang/StringBuilder;
      //   61: astore_2
      //   62: aload_0
      //   63: getfield 106	o/CH$ˊ:ˋ	Ljava/lang/reflect/Method;
      //   66: astore_3
      //   67: new 320	java/lang/IllegalArgumentException
      //   70: dup
      //   71: aload_2
      //   72: aload_3
      //   73: invokevirtual 324	java/lang/reflect/Method:getDeclaringClass	()Ljava/lang/Class;
      //   76: invokevirtual 329	java/lang/Class:getSimpleName	()Ljava/lang/String;
      //   79: invokevirtual 203	java/lang/StringBuilder:append	(Ljava/lang/String;)Ljava/lang/StringBuilder;
      //   82: ldc_w 331
      //   85: invokevirtual 203	java/lang/StringBuilder:append	(Ljava/lang/String;)Ljava/lang/StringBuilder;
      //   88: aload_0
      //   89: getfield 106	o/CH$ˊ:ˋ	Ljava/lang/reflect/Method;
      //   92: invokevirtual 334	java/lang/reflect/Method:getName	()Ljava/lang/String;
      //   95: invokevirtual 203	java/lang/StringBuilder:append	(Ljava/lang/String;)Ljava/lang/StringBuilder;
      //   98: invokevirtual 213	java/lang/StringBuilder:toString	()Ljava/lang/String;
      //   101: aload_1
      //   102: invokespecial 337	java/lang/IllegalArgumentException:<init>	(Ljava/lang/String;Ljava/lang/Throwable;)V
      //   105: astore_1
      //   106: goto -100 -> 6
      //   109: astore_1
      //   110: aload_1
      //   111: athrow
      // Local variable table:
      //   start	length	slot	name	signature
      //   0	112	0	this	ˊ
      //   0	112	1	paramThrowable	Throwable
      //   0	112	2	paramString	String
      //   0	112	3	paramVarArgs	Object[]
      //   12	15	4	i	int
      // Exception table:
      //   from	to	target	type
      //   48	54	3	java/lang/Exception
      //   34	48	109	java/lang/Exception
      //   48	54	109	java/lang/Exception
      //   54	62	109	java/lang/Exception
      //   62	67	109	java/lang/Exception
      //   67	106	109	java/lang/Exception
    }
    
    /* Error */
    private CA<?> ॱ(int paramInt, Type paramType, Annotation[] paramArrayOfAnnotation, Annotation paramAnnotation)
    {
      // Byte code:
      //   0: goto +1474 -> 1474
      //   3: ldc_w 339
      //   6: aload 4
      //   8: invokevirtual 343	java/lang/Class:isAssignableFrom	(Ljava/lang/Class;)Z
      //   11: ifeq +6 -> 17
      //   14: goto +1616 -> 1630
      //   17: goto +4406 -> 4423
      //   20: aload 4
      //   22: checkcast 345	o/CV
      //   25: astore 7
      //   27: aload 7
      //   29: invokeinterface 347 1 0
      //   34: astore 4
      //   36: aload 7
      //   38: invokeinterface 349 1 0
      //   43: istore 6
      //   45: aload_0
      //   46: iconst_1
      //   47: putfield 351	o/CH$ˊ:ᐝ	Z
      //   50: aload_2
      //   51: invokestatic 354	o/CM:ˊ	(Ljava/lang/reflect/Type;)Ljava/lang/Class;
      //   54: astore 7
      //   56: ldc_w 356
      //   59: aload 7
      //   61: invokevirtual 343	java/lang/Class:isAssignableFrom	(Ljava/lang/Class;)Z
      //   64: ifeq +6 -> 70
      //   67: goto +796 -> 863
      //   70: goto +3107 -> 3177
      //   73: aload_0
      //   74: getfield 358	o/CH$ˊ:ॱˊ	Z
      //   77: ifne +6 -> 83
      //   80: goto +3640 -> 3720
      //   83: goto -63 -> 20
      //   86: aload 4
      //   88: instanceof 360
      //   91: ifeq +6 -> 97
      //   94: goto +826 -> 920
      //   97: goto +3473 -> 3570
      //   100: getstatic 60	o/CH$ˊ:ˋˊ	I
      //   103: bipush 107
      //   105: iadd
      //   106: istore 5
      //   108: iload 5
      //   110: sipush 128
      //   113: irem
      //   114: putstatic 62	o/CH$ˊ:ˊˊ	I
      //   117: iload 5
      //   119: iconst_2
      //   120: irem
      //   121: ifne +6 -> 127
      //   124: goto +1979 -> 2103
      //   127: goto +3380 -> 3507
      //   130: aload_2
      //   131: ldc_w 362
      //   134: if_acmpeq +6 -> 140
      //   137: goto +2570 -> 2707
      //   140: goto +4051 -> 4191
      //   143: aload_0
      //   144: iload_1
      //   145: ldc_w 364
      //   148: iconst_0
      //   149: anewarray 5	java/lang/Object
      //   152: invokespecial 191	o/CH$ˊ:ˏ	(ILjava/lang/String;[Ljava/lang/Object;)Ljava/lang/RuntimeException;
      //   155: athrow
      //   156: aload_0
      //   157: iload_1
      //   158: new 198	java/lang/StringBuilder
      //   161: dup
      //   162: invokespecial 199	java/lang/StringBuilder:<init>	()V
      //   165: aload 7
      //   167: invokevirtual 329	java/lang/Class:getSimpleName	()Ljava/lang/String;
      //   170: invokevirtual 203	java/lang/StringBuilder:append	(Ljava/lang/String;)Ljava/lang/StringBuilder;
      //   173: ldc_w 366
      //   176: invokevirtual 203	java/lang/StringBuilder:append	(Ljava/lang/String;)Ljava/lang/StringBuilder;
      //   179: aload 7
      //   181: invokevirtual 329	java/lang/Class:getSimpleName	()Ljava/lang/String;
      //   184: invokevirtual 203	java/lang/StringBuilder:append	(Ljava/lang/String;)Ljava/lang/StringBuilder;
      //   187: ldc_w 368
      //   190: invokevirtual 203	java/lang/StringBuilder:append	(Ljava/lang/String;)Ljava/lang/StringBuilder;
      //   193: invokevirtual 213	java/lang/StringBuilder:toString	()Ljava/lang/String;
      //   196: iconst_0
      //   197: anewarray 5	java/lang/Object
      //   200: invokespecial 191	o/CH$ˊ:ˏ	(ILjava/lang/String;[Ljava/lang/Object;)Ljava/lang/RuntimeException;
      //   203: athrow
      //   204: aload_0
      //   205: iload_1
      //   206: ldc_w 370
      //   209: iconst_0
      //   210: anewarray 5	java/lang/Object
      //   213: invokespecial 191	o/CH$ˊ:ˏ	(ILjava/lang/String;[Ljava/lang/Object;)Ljava/lang/RuntimeException;
      //   216: athrow
      //   217: aload 4
      //   219: invokevirtual 373	java/lang/Class:isArray	()Z
      //   222: ifeq +6 -> 228
      //   225: goto +4165 -> 4390
      //   228: goto -225 -> 3
      //   231: aload 4
      //   233: invokevirtual 376	java/lang/Class:getComponentType	()Ljava/lang/Class;
      //   236: invokestatic 379	o/CH:ॱ	(Ljava/lang/Class;)Ljava/lang/Class;
      //   239: astore_2
      //   240: new 381	o/CA$AUx
      //   243: dup
      //   244: aload_0
      //   245: getfield 104	o/CH$ˊ:ˊ	Lo/CI;
      //   248: aload_2
      //   249: aload_3
      //   250: invokevirtual 383	o/CI:ˊ	(Ljava/lang/reflect/Type;[Ljava/lang/annotation/Annotation;)Lo/Cy;
      //   253: iload 6
      //   255: invokespecial 386	o/CA$AUx:<init>	(Lo/Cy;Z)V
      //   258: invokevirtual 389	o/CA$AUx:ˋ	()Lo/CA;
      //   261: areturn
      //   262: aload_0
      //   263: getfield 391	o/CH$ˊ:ʻॱ	Z
      //   266: ifne +6 -> 272
      //   269: goto +3991 -> 4260
      //   272: goto +3500 -> 3772
      //   275: iconst_1
      //   276: istore 5
      //   278: goto +1605 -> 1883
      //   281: aload_0
      //   282: iconst_1
      //   283: putfield 393	o/CH$ˊ:ˊॱ	Z
      //   286: aload_2
      //   287: ldc_w 395
      //   290: if_acmpeq +6 -> 296
      //   293: goto +1780 -> 2073
      //   296: goto +823 -> 1119
      //   299: aload_0
      //   300: iconst_1
      //   301: putfield 397	o/CH$ˊ:ʽ	Z
      //   304: aload_2
      //   305: invokestatic 354	o/CM:ˊ	(Ljava/lang/reflect/Type;)Ljava/lang/Class;
      //   308: astore 7
      //   310: ldc_w 399
      //   313: aload 7
      //   315: invokevirtual 343	java/lang/Class:isAssignableFrom	(Ljava/lang/Class;)Z
      //   318: ifne +6 -> 324
      //   321: goto +654 -> 975
      //   324: goto +2867 -> 3191
      //   327: aload 4
      //   329: checkcast 401	o/Do
      //   332: astore 7
      //   334: aload 7
      //   336: invokeinterface 403 1 0
      //   341: astore 4
      //   343: aload 7
      //   345: invokeinterface 405 1 0
      //   350: istore 6
      //   352: aload_2
      //   353: invokestatic 354	o/CM:ˊ	(Ljava/lang/reflect/Type;)Ljava/lang/Class;
      //   356: astore 7
      //   358: aload_0
      //   359: iconst_1
      //   360: putfield 407	o/CH$ˊ:ˏॱ	Z
      //   363: ldc_w 356
      //   366: aload 7
      //   368: invokevirtual 343	java/lang/Class:isAssignableFrom	(Ljava/lang/Class;)Z
      //   371: ifeq +6 -> 377
      //   374: goto +1537 -> 1911
      //   377: goto +3497 -> 3874
      //   380: aload_2
      //   381: instanceof 326
      //   384: ifeq +6 -> 390
      //   387: goto +3660 -> 4047
      //   390: goto +3851 -> 4241
      //   393: aload_0
      //   394: iload_1
      //   395: new 198	java/lang/StringBuilder
      //   398: dup
      //   399: invokespecial 199	java/lang/StringBuilder:<init>	()V
      //   402: bipush 40
      //   404: newarray byte
      //   406: dup
      //   407: iconst_0
      //   408: ldc_w 408
      //   411: bastore
      //   412: dup
      //   413: iconst_1
      //   414: ldc_w 409
      //   417: bastore
      //   418: dup
      //   419: iconst_2
      //   420: ldc_w 410
      //   423: bastore
      //   424: dup
      //   425: iconst_3
      //   426: ldc_w 411
      //   429: bastore
      //   430: dup
      //   431: iconst_4
      //   432: ldc_w 412
      //   435: bastore
      //   436: dup
      //   437: iconst_5
      //   438: ldc_w 413
      //   441: bastore
      //   442: dup
      //   443: bipush 6
      //   445: ldc_w 414
      //   448: bastore
      //   449: dup
      //   450: bipush 7
      //   452: ldc_w 415
      //   455: bastore
      //   456: dup
      //   457: bipush 8
      //   459: ldc_w 408
      //   462: bastore
      //   463: dup
      //   464: bipush 9
      //   466: ldc_w 416
      //   469: bastore
      //   470: dup
      //   471: bipush 10
      //   473: ldc_w 417
      //   476: bastore
      //   477: dup
      //   478: bipush 11
      //   480: ldc_w 418
      //   483: bastore
      //   484: dup
      //   485: bipush 12
      //   487: ldc_w 414
      //   490: bastore
      //   491: dup
      //   492: bipush 13
      //   494: ldc_w 408
      //   497: bastore
      //   498: dup
      //   499: bipush 14
      //   501: ldc_w 419
      //   504: bastore
      //   505: dup
      //   506: bipush 15
      //   508: ldc_w 420
      //   511: bastore
      //   512: dup
      //   513: bipush 16
      //   515: ldc_w 408
      //   518: bastore
      //   519: dup
      //   520: bipush 17
      //   522: ldc_w 416
      //   525: bastore
      //   526: dup
      //   527: bipush 18
      //   529: ldc_w 421
      //   532: bastore
      //   533: dup
      //   534: bipush 19
      //   536: ldc_w 408
      //   539: bastore
      //   540: dup
      //   541: bipush 20
      //   543: ldc_w 414
      //   546: bastore
      //   547: dup
      //   548: bipush 21
      //   550: ldc_w 422
      //   553: bastore
      //   554: dup
      //   555: bipush 22
      //   557: ldc_w 423
      //   560: bastore
      //   561: dup
      //   562: bipush 23
      //   564: ldc_w 424
      //   567: bastore
      //   568: dup
      //   569: bipush 24
      //   571: ldc_w 408
      //   574: bastore
      //   575: dup
      //   576: bipush 25
      //   578: ldc_w 422
      //   581: bastore
      //   582: dup
      //   583: bipush 26
      //   585: ldc_w 418
      //   588: bastore
      //   589: dup
      //   590: bipush 27
      //   592: ldc_w 416
      //   595: bastore
      //   596: dup
      //   597: bipush 28
      //   599: ldc_w 425
      //   602: bastore
      //   603: dup
      //   604: bipush 29
      //   606: ldc_w 408
      //   609: bastore
      //   610: dup
      //   611: bipush 30
      //   613: ldc_w 417
      //   616: bastore
      //   617: dup
      //   618: bipush 31
      //   620: ldc_w 426
      //   623: bastore
      //   624: dup
      //   625: bipush 32
      //   627: ldc_w 427
      //   630: bastore
      //   631: dup
      //   632: bipush 33
      //   634: ldc_w 413
      //   637: bastore
      //   638: dup
      //   639: bipush 34
      //   641: ldc_w 416
      //   644: bastore
      //   645: dup
      //   646: bipush 35
      //   648: ldc_w 428
      //   651: bastore
      //   652: dup
      //   653: bipush 36
      //   655: ldc_w 426
      //   658: bastore
      //   659: dup
      //   660: bipush 37
      //   662: ldc_w 416
      //   665: bastore
      //   666: dup
      //   667: bipush 38
      //   669: ldc_w 429
      //   672: bastore
      //   673: dup
      //   674: bipush 39
      //   676: ldc_w 430
      //   679: bastore
      //   680: aconst_null
      //   681: aconst_null
      //   682: bipush 127
      //   684: invokestatic 432	o/CH$ˊ:ˎ	([B[I[CI)Ljava/lang/String;
      //   687: invokevirtual 435	java/lang/String:intern	()Ljava/lang/String;
      //   690: invokevirtual 203	java/lang/StringBuilder:append	(Ljava/lang/String;)Ljava/lang/StringBuilder;
      //   693: aload_2
      //   694: invokevirtual 438	java/lang/StringBuilder:append	(Ljava/lang/Object;)Ljava/lang/StringBuilder;
      //   697: invokevirtual 213	java/lang/StringBuilder:toString	()Ljava/lang/String;
      //   700: iconst_0
      //   701: anewarray 5	java/lang/Object
      //   704: invokespecial 191	o/CH$ˊ:ˏ	(ILjava/lang/String;[Ljava/lang/Object;)Ljava/lang/RuntimeException;
      //   707: athrow
      //   708: iconst_1
      //   709: aload_2
      //   710: invokestatic 441	o/CM:ॱ	(ILjava/lang/reflect/ParameterizedType;)Ljava/lang/reflect/Type;
      //   713: astore_2
      //   714: new 443	o/CA$ᐝ
      //   717: dup
      //   718: aload_0
      //   719: getfield 104	o/CH$ˊ:ˊ	Lo/CI;
      //   722: aload_2
      //   723: aload_3
      //   724: invokevirtual 383	o/CI:ˊ	(Ljava/lang/reflect/Type;[Ljava/lang/annotation/Annotation;)Lo/Cy;
      //   727: aload 4
      //   729: checkcast 445	o/Ds
      //   732: invokeinterface 447 1 0
      //   737: invokespecial 448	o/CA$ᐝ:<init>	(Lo/Cy;Z)V
      //   740: areturn
      //   741: goto +2411 -> 3152
      //   744: aload 4
      //   746: invokevirtual 376	java/lang/Class:getComponentType	()Ljava/lang/Class;
      //   749: invokestatic 379	o/CH:ॱ	(Ljava/lang/Class;)Ljava/lang/Class;
      //   752: astore_2
      //   753: ldc_w 339
      //   756: aload_2
      //   757: invokevirtual 343	java/lang/Class:isAssignableFrom	(Ljava/lang/Class;)Z
      //   760: ifeq +6 -> 766
      //   763: goto +1984 -> 2747
      //   766: goto +3151 -> 3917
      //   769: aload 7
      //   771: invokevirtual 376	java/lang/Class:getComponentType	()Ljava/lang/Class;
      //   774: invokestatic 379	o/CH:ॱ	(Ljava/lang/Class;)Ljava/lang/Class;
      //   777: astore_2
      //   778: new 450	o/CA$If
      //   781: dup
      //   782: aload 4
      //   784: aload_0
      //   785: getfield 104	o/CH$ˊ:ˊ	Lo/CI;
      //   788: aload_2
      //   789: aload_3
      //   790: invokevirtual 383	o/CI:ˊ	(Ljava/lang/reflect/Type;[Ljava/lang/annotation/Annotation;)Lo/Cy;
      //   793: iload 6
      //   795: invokespecial 453	o/CA$If:<init>	(Ljava/lang/String;Lo/Cy;Z)V
      //   798: invokevirtual 454	o/CA$If:ˋ	()Lo/CA;
      //   801: areturn
      //   802: aload_0
      //   803: iload_1
      //   804: ldc_w 456
      //   807: iconst_0
      //   808: anewarray 5	java/lang/Object
      //   811: invokespecial 191	o/CH$ˊ:ˏ	(ILjava/lang/String;[Ljava/lang/Object;)Ljava/lang/RuntimeException;
      //   814: athrow
      //   815: new 458	o/CA$ˏ
      //   818: dup
      //   819: aload 4
      //   821: aload_0
      //   822: getfield 104	o/CH$ˊ:ˊ	Lo/CI;
      //   825: aload_2
      //   826: aload_3
      //   827: invokevirtual 383	o/CI:ˊ	(Ljava/lang/reflect/Type;[Ljava/lang/annotation/Annotation;)Lo/Cy;
      //   830: iload 6
      //   832: invokespecial 459	o/CA$ˏ:<init>	(Ljava/lang/String;Lo/Cy;Z)V
      //   835: areturn
      //   836: aload_0
      //   837: iload_1
      //   838: ldc_w 461
      //   841: iconst_0
      //   842: anewarray 5	java/lang/Object
      //   845: invokespecial 191	o/CH$ˊ:ˏ	(ILjava/lang/String;[Ljava/lang/Object;)Ljava/lang/RuntimeException;
      //   848: athrow
      //   849: aload 4
      //   851: instanceof 463
      //   854: ifeq +6 -> 860
      //   857: goto +777 -> 1634
      //   860: goto +1254 -> 2114
      //   863: aload_2
      //   864: instanceof 465
      //   867: ifne +6 -> 873
      //   870: goto +57 -> 927
      //   873: goto +115 -> 988
      //   876: aload_0
      //   877: getfield 255	o/CH$ˊ:ᐝॱ	Ljava/lang/String;
      //   880: ifnull +6 -> 886
      //   883: goto +1373 -> 2256
      //   886: goto -605 -> 281
      //   889: aload 7
      //   891: invokevirtual 376	java/lang/Class:getComponentType	()Ljava/lang/Class;
      //   894: invokestatic 379	o/CH:ॱ	(Ljava/lang/Class;)Ljava/lang/Class;
      //   897: astore_2
      //   898: new 467	o/CA$ˊ
      //   901: dup
      //   902: aload 4
      //   904: aload_0
      //   905: getfield 104	o/CH$ˊ:ˊ	Lo/CI;
      //   908: aload_2
      //   909: aload_3
      //   910: invokevirtual 383	o/CI:ˊ	(Ljava/lang/reflect/Type;[Ljava/lang/annotation/Annotation;)Lo/Cy;
      //   913: invokespecial 470	o/CA$ˊ:<init>	(Ljava/lang/String;Lo/Cy;)V
      //   916: invokevirtual 471	o/CA$ˊ:ˋ	()Lo/CA;
      //   919: areturn
      //   920: bipush 90
      //   922: istore 5
      //   924: goto +1289 -> 2213
      //   927: aload_0
      //   928: iload_1
      //   929: new 198	java/lang/StringBuilder
      //   932: dup
      //   933: invokespecial 199	java/lang/StringBuilder:<init>	()V
      //   936: aload 7
      //   938: invokevirtual 329	java/lang/Class:getSimpleName	()Ljava/lang/String;
      //   941: invokevirtual 203	java/lang/StringBuilder:append	(Ljava/lang/String;)Ljava/lang/StringBuilder;
      //   944: ldc_w 366
      //   947: invokevirtual 203	java/lang/StringBuilder:append	(Ljava/lang/String;)Ljava/lang/StringBuilder;
      //   950: aload 7
      //   952: invokevirtual 329	java/lang/Class:getSimpleName	()Ljava/lang/String;
      //   955: invokevirtual 203	java/lang/StringBuilder:append	(Ljava/lang/String;)Ljava/lang/StringBuilder;
      //   958: ldc_w 368
      //   961: invokevirtual 203	java/lang/StringBuilder:append	(Ljava/lang/String;)Ljava/lang/StringBuilder;
      //   964: invokevirtual 213	java/lang/StringBuilder:toString	()Ljava/lang/String;
      //   967: iconst_0
      //   968: anewarray 5	java/lang/Object
      //   971: invokespecial 191	o/CH$ˊ:ˏ	(ILjava/lang/String;[Ljava/lang/Object;)Ljava/lang/RuntimeException;
      //   974: athrow
      //   975: aload_0
      //   976: iload_1
      //   977: ldc_w 473
      //   980: iconst_0
      //   981: anewarray 5	java/lang/Object
      //   984: invokespecial 191	o/CH$ˊ:ˏ	(ILjava/lang/String;[Ljava/lang/Object;)Ljava/lang/RuntimeException;
      //   987: athrow
      //   988: iconst_0
      //   989: aload_2
      //   990: checkcast 465	java/lang/reflect/ParameterizedType
      //   993: invokestatic 441	o/CM:ॱ	(ILjava/lang/reflect/ParameterizedType;)Ljava/lang/reflect/Type;
      //   996: astore_2
      //   997: new 450	o/CA$If
      //   1000: dup
      //   1001: aload 4
      //   1003: aload_0
      //   1004: getfield 104	o/CH$ˊ:ˊ	Lo/CI;
      //   1007: aload_2
      //   1008: aload_3
      //   1009: invokevirtual 383	o/CI:ˊ	(Ljava/lang/reflect/Type;[Ljava/lang/annotation/Annotation;)Lo/Cy;
      //   1012: iload 6
      //   1014: invokespecial 453	o/CA$If:<init>	(Ljava/lang/String;Lo/Cy;Z)V
      //   1017: invokevirtual 475	o/CA$If:ˎ	()Lo/CA;
      //   1020: areturn
      //   1021: aload_0
      //   1022: iconst_1
      //   1023: putfield 477	o/CH$ˊ:ॱॱ	Z
      //   1026: new 479	o/CA$ˋ
      //   1029: dup
      //   1030: aload_3
      //   1031: invokespecial 482	o/CA$ˋ:<init>	(Lo/Cy;)V
      //   1034: areturn
      //   1035: iconst_1
      //   1036: istore 5
      //   1038: goto +787 -> 1825
      //   1041: aload_2
      //   1042: aload 7
      //   1044: ldc_w 399
      //   1047: invokestatic 485	o/CM:ˎ	(Ljava/lang/reflect/Type;Ljava/lang/Class;Ljava/lang/Class;)Ljava/lang/reflect/Type;
      //   1050: astore_2
      //   1051: aload_2
      //   1052: instanceof 465
      //   1055: ifne +6 -> 1061
      //   1058: goto +3245 -> 4303
      //   1061: goto +932 -> 1993
      //   1064: iconst_0
      //   1065: anewarray 5	java/lang/Object
      //   1068: astore_2
      //   1069: aload_2
      //   1070: iconst_0
      //   1071: aload_0
      //   1072: getfield 299	o/CH$ˊ:ˋॱ	Ljava/lang/String;
      //   1075: aastore
      //   1076: aload_0
      //   1077: iload_1
      //   1078: ldc_w 487
      //   1081: aload_2
      //   1082: invokespecial 191	o/CH$ˊ:ˏ	(ILjava/lang/String;[Ljava/lang/Object;)Ljava/lang/RuntimeException;
      //   1085: athrow
      //   1086: aload_0
      //   1087: getfield 391	o/CH$ˊ:ʻॱ	Z
      //   1090: ifeq +6 -> 1096
      //   1093: goto +1582 -> 2675
      //   1096: goto +2461 -> 3557
      //   1099: aload_0
      //   1100: iload_1
      //   1101: ldc_w 487
      //   1104: iconst_1
      //   1105: anewarray 5	java/lang/Object
      //   1108: dup
      //   1109: iconst_0
      //   1110: aload_0
      //   1111: getfield 299	o/CH$ˊ:ˋॱ	Ljava/lang/String;
      //   1114: aastore
      //   1115: invokespecial 191	o/CH$ˊ:ˏ	(ILjava/lang/String;[Ljava/lang/Object;)Ljava/lang/RuntimeException;
      //   1118: athrow
      //   1119: new 489	o/CA$ʻ
      //   1122: dup
      //   1123: invokespecial 490	o/CA$ʻ:<init>	()V
      //   1126: areturn
      //   1127: aload_0
      //   1128: iload_1
      //   1129: ldc_w 492
      //   1132: iconst_0
      //   1133: anewarray 5	java/lang/Object
      //   1136: invokespecial 191	o/CH$ˊ:ˏ	(ILjava/lang/String;[Ljava/lang/Object;)Ljava/lang/RuntimeException;
      //   1139: athrow
      //   1140: aload 7
      //   1142: invokevirtual 376	java/lang/Class:getComponentType	()Ljava/lang/Class;
      //   1145: invokestatic 379	o/CH:ॱ	(Ljava/lang/Class;)Ljava/lang/Class;
      //   1148: astore_2
      //   1149: new 458	o/CA$ˏ
      //   1152: dup
      //   1153: aload 4
      //   1155: aload_0
      //   1156: getfield 104	o/CH$ˊ:ˊ	Lo/CI;
      //   1159: aload_2
      //   1160: aload_3
      //   1161: invokevirtual 383	o/CI:ˊ	(Ljava/lang/reflect/Type;[Ljava/lang/annotation/Annotation;)Lo/Cy;
      //   1164: iload 6
      //   1166: invokespecial 459	o/CA$ˏ:<init>	(Ljava/lang/String;Lo/Cy;Z)V
      //   1169: invokevirtual 493	o/CA$ˏ:ˋ	()Lo/CA;
      //   1172: areturn
      //   1173: aload_0
      //   1174: iload_1
      //   1175: new 198	java/lang/StringBuilder
      //   1178: dup
      //   1179: invokespecial 199	java/lang/StringBuilder:<init>	()V
      //   1182: bipush 38
      //   1184: newarray byte
      //   1186: dup
      //   1187: iconst_0
      //   1188: ldc_w 408
      //   1191: bastore
      //   1192: dup
      //   1193: iconst_1
      //   1194: ldc_w 409
      //   1197: bastore
      //   1198: dup
      //   1199: iconst_2
      //   1200: ldc_w 410
      //   1203: bastore
      //   1204: dup
      //   1205: iconst_3
      //   1206: ldc_w 411
      //   1209: bastore
      //   1210: dup
      //   1211: iconst_4
      //   1212: ldc_w 412
      //   1215: bastore
      //   1216: dup
      //   1217: iconst_5
      //   1218: ldc_w 413
      //   1221: bastore
      //   1222: dup
      //   1223: bipush 6
      //   1225: ldc_w 414
      //   1228: bastore
      //   1229: dup
      //   1230: bipush 7
      //   1232: ldc_w 415
      //   1235: bastore
      //   1236: dup
      //   1237: bipush 8
      //   1239: ldc_w 408
      //   1242: bastore
      //   1243: dup
      //   1244: bipush 9
      //   1246: ldc_w 416
      //   1249: bastore
      //   1250: dup
      //   1251: bipush 10
      //   1253: ldc_w 417
      //   1256: bastore
      //   1257: dup
      //   1258: bipush 11
      //   1260: ldc_w 418
      //   1263: bastore
      //   1264: dup
      //   1265: bipush 12
      //   1267: ldc_w 414
      //   1270: bastore
      //   1271: dup
      //   1272: bipush 13
      //   1274: ldc_w 408
      //   1277: bastore
      //   1278: dup
      //   1279: bipush 14
      //   1281: ldc_w 419
      //   1284: bastore
      //   1285: dup
      //   1286: bipush 15
      //   1288: ldc_w 420
      //   1291: bastore
      //   1292: dup
      //   1293: bipush 16
      //   1295: ldc_w 408
      //   1298: bastore
      //   1299: dup
      //   1300: bipush 17
      //   1302: ldc_w 416
      //   1305: bastore
      //   1306: dup
      //   1307: bipush 18
      //   1309: ldc_w 421
      //   1312: bastore
      //   1313: dup
      //   1314: bipush 19
      //   1316: ldc_w 408
      //   1319: bastore
      //   1320: dup
      //   1321: bipush 20
      //   1323: ldc_w 414
      //   1326: bastore
      //   1327: dup
      //   1328: bipush 21
      //   1330: ldc_w 422
      //   1333: bastore
      //   1334: dup
      //   1335: bipush 22
      //   1337: ldc_w 423
      //   1340: bastore
      //   1341: dup
      //   1342: bipush 23
      //   1344: ldc_w 424
      //   1347: bastore
      //   1348: dup
      //   1349: bipush 24
      //   1351: ldc_w 408
      //   1354: bastore
      //   1355: dup
      //   1356: bipush 25
      //   1358: ldc_w 422
      //   1361: bastore
      //   1362: dup
      //   1363: bipush 26
      //   1365: ldc_w 418
      //   1368: bastore
      //   1369: dup
      //   1370: bipush 27
      //   1372: ldc_w 416
      //   1375: bastore
      //   1376: dup
      //   1377: bipush 28
      //   1379: ldc_w 425
      //   1382: bastore
      //   1383: dup
      //   1384: bipush 29
      //   1386: ldc_w 408
      //   1389: bastore
      //   1390: dup
      //   1391: bipush 30
      //   1393: ldc_w 417
      //   1396: bastore
      //   1397: dup
      //   1398: bipush 31
      //   1400: ldc_w 426
      //   1403: bastore
      //   1404: dup
      //   1405: bipush 32
      //   1407: ldc_w 427
      //   1410: bastore
      //   1411: dup
      //   1412: bipush 33
      //   1414: ldc_w 414
      //   1417: bastore
      //   1418: dup
      //   1419: bipush 34
      //   1421: ldc_w 413
      //   1424: bastore
      //   1425: dup
      //   1426: bipush 35
      //   1428: ldc_w 426
      //   1431: bastore
      //   1432: dup
      //   1433: bipush 36
      //   1435: ldc_w 494
      //   1438: bastore
      //   1439: dup
      //   1440: bipush 37
      //   1442: ldc_w 430
      //   1445: bastore
      //   1446: aconst_null
      //   1447: aconst_null
      //   1448: bipush 127
      //   1450: invokestatic 432	o/CH$ˊ:ˎ	([B[I[CI)Ljava/lang/String;
      //   1453: invokevirtual 435	java/lang/String:intern	()Ljava/lang/String;
      //   1456: invokevirtual 203	java/lang/StringBuilder:append	(Ljava/lang/String;)Ljava/lang/StringBuilder;
      //   1459: aload_2
      //   1460: invokevirtual 438	java/lang/StringBuilder:append	(Ljava/lang/Object;)Ljava/lang/StringBuilder;
      //   1463: invokevirtual 213	java/lang/StringBuilder:toString	()Ljava/lang/String;
      //   1466: iconst_0
      //   1467: anewarray 5	java/lang/Object
      //   1470: invokespecial 191	o/CH$ˊ:ˏ	(ILjava/lang/String;[Ljava/lang/Object;)Ljava/lang/RuntimeException;
      //   1473: athrow
      //   1474: goto +1597 -> 3071
      //   1477: iconst_4
      //   1478: anewarray 131	java/lang/String
      //   1481: dup
      //   1482: iconst_0
      //   1483: ldc_w 496
      //   1486: aastore
      //   1487: dup
      //   1488: iconst_1
      //   1489: new 198	java/lang/StringBuilder
      //   1492: dup
      //   1493: invokespecial 199	java/lang/StringBuilder:<init>	()V
      //   1496: ldc_w 498
      //   1499: invokevirtual 203	java/lang/StringBuilder:append	(Ljava/lang/String;)Ljava/lang/StringBuilder;
      //   1502: aload 7
      //   1504: invokevirtual 203	java/lang/StringBuilder:append	(Ljava/lang/String;)Ljava/lang/StringBuilder;
      //   1507: ldc_w 500
      //   1510: invokevirtual 203	java/lang/StringBuilder:append	(Ljava/lang/String;)Ljava/lang/StringBuilder;
      //   1513: invokevirtual 213	java/lang/StringBuilder:toString	()Ljava/lang/String;
      //   1516: aastore
      //   1517: dup
      //   1518: iconst_2
      //   1519: ldc_w 502
      //   1522: aastore
      //   1523: dup
      //   1524: iconst_3
      //   1525: aload 8
      //   1527: invokeinterface 505 1 0
      //   1532: aastore
      //   1533: invokestatic 509	o/xz:ˋ	([Ljava/lang/String;)Lo/xz;
      //   1536: astore 7
      //   1538: ldc_w 356
      //   1541: aload 4
      //   1543: invokevirtual 343	java/lang/Class:isAssignableFrom	(Ljava/lang/Class;)Z
      //   1546: ifeq +6 -> 1552
      //   1549: goto +1536 -> 3085
      //   1552: goto +507 -> 2059
      //   1555: aload_2
      //   1556: aload 4
      //   1558: ldc_w 399
      //   1561: invokestatic 485	o/CM:ˎ	(Ljava/lang/reflect/Type;Ljava/lang/Class;Ljava/lang/Class;)Ljava/lang/reflect/Type;
      //   1564: astore_2
      //   1565: aload_2
      //   1566: instanceof 465
      //   1569: ifne +6 -> 1575
      //   1572: goto +2066 -> 3638
      //   1575: goto +2441 -> 4016
      //   1578: aload 4
      //   1580: instanceof 445
      //   1583: ifeq +6 -> 1589
      //   1586: goto +1934 -> 3520
      //   1589: goto +1557 -> 3146
      //   1592: aload_0
      //   1593: iload_1
      //   1594: ldc_w 511
      //   1597: iconst_0
      //   1598: anewarray 5	java/lang/Object
      //   1601: invokespecial 191	o/CH$ˊ:ˏ	(ILjava/lang/String;[Ljava/lang/Object;)Ljava/lang/RuntimeException;
      //   1604: athrow
      //   1605: aload_2
      //   1606: checkcast 465	java/lang/reflect/ParameterizedType
      //   1609: astore 7
      //   1611: iconst_0
      //   1612: aload 7
      //   1614: invokestatic 441	o/CM:ॱ	(ILjava/lang/reflect/ParameterizedType;)Ljava/lang/reflect/Type;
      //   1617: astore_2
      //   1618: ldc -125
      //   1620: aload_2
      //   1621: if_acmpeq +6 -> 1627
      //   1624: goto -451 -> 1173
      //   1627: goto +688 -> 2315
      //   1630: getstatic 516	o/CA$ʼ:ˋ	Lo/CA$ʼ;
      //   1633: areturn
      //   1634: aload 4
      //   1636: checkcast 463	o/Dg
      //   1639: invokeinterface 517 1 0
      //   1644: astore 4
      //   1646: aload_2
      //   1647: invokestatic 354	o/CM:ˊ	(Ljava/lang/reflect/Type;)Ljava/lang/Class;
      //   1650: astore 7
      //   1652: ldc_w 356
      //   1655: aload 7
      //   1657: invokevirtual 343	java/lang/Class:isAssignableFrom	(Ljava/lang/Class;)Z
      //   1660: ifeq +6 -> 1666
      //   1663: goto +1624 -> 3287
      //   1666: goto +1094 -> 2760
      //   1669: getstatic 60	o/CH$ˊ:ˋˊ	I
      //   1672: bipush 103
      //   1674: iadd
      //   1675: istore 5
      //   1677: iload 5
      //   1679: sipush 128
      //   1682: irem
      //   1683: putstatic 62	o/CH$ˊ:ˊˊ	I
      //   1686: iload 5
      //   1688: iconst_2
      //   1689: irem
      //   1690: ifne +6 -> 1696
      //   1693: goto +472 -> 2165
      //   1696: goto +2620 -> 4316
      //   1699: aload_2
      //   1700: invokestatic 354	o/CM:ˊ	(Ljava/lang/reflect/Type;)Ljava/lang/Class;
      //   1703: astore 7
      //   1705: ldc_w 399
      //   1708: aload 7
      //   1710: invokevirtual 343	java/lang/Class:isAssignableFrom	(Ljava/lang/Class;)Z
      //   1713: ifne +6 -> 1719
      //   1716: goto -124 -> 1592
      //   1719: goto -678 -> 1041
      //   1722: ldc_w 339
      //   1725: iconst_0
      //   1726: aload_2
      //   1727: checkcast 465	java/lang/reflect/ParameterizedType
      //   1730: invokestatic 441	o/CM:ॱ	(ILjava/lang/reflect/ParameterizedType;)Ljava/lang/reflect/Type;
      //   1733: invokestatic 354	o/CM:ˊ	(Ljava/lang/reflect/Type;)Ljava/lang/Class;
      //   1736: invokevirtual 343	java/lang/Class:isAssignableFrom	(Ljava/lang/Class;)Z
      //   1739: ifne +6 -> 1745
      //   1742: goto +1835 -> 3577
      //   1745: goto +1062 -> 2807
      //   1748: iconst_1
      //   1749: aload_2
      //   1750: invokestatic 441	o/CM:ॱ	(ILjava/lang/reflect/ParameterizedType;)Ljava/lang/reflect/Type;
      //   1753: astore_2
      //   1754: aload_0
      //   1755: getfield 104	o/CH$ˊ:ˊ	Lo/CI;
      //   1758: aload_2
      //   1759: aload_3
      //   1760: invokevirtual 383	o/CI:ˊ	(Ljava/lang/reflect/Type;[Ljava/lang/annotation/Annotation;)Lo/Cy;
      //   1763: astore_2
      //   1764: aload_0
      //   1765: iconst_1
      //   1766: putfield 351	o/CH$ˊ:ᐝ	Z
      //   1769: new 519	o/CA$if
      //   1772: dup
      //   1773: aload_2
      //   1774: aload 4
      //   1776: checkcast 521	o/Da
      //   1779: invokeinterface 523 1 0
      //   1784: invokespecial 524	o/CA$if:<init>	(Lo/Cy;Z)V
      //   1787: areturn
      //   1788: getstatic 516	o/CA$ʼ:ˋ	Lo/CA$ʼ;
      //   1791: invokevirtual 525	o/CA$ʼ:ˋ	()Lo/CA;
      //   1794: areturn
      //   1795: new 527	o/CA$ˎ
      //   1798: dup
      //   1799: aload 7
      //   1801: aload_0
      //   1802: getfield 104	o/CH$ˊ:ˊ	Lo/CI;
      //   1805: aload_2
      //   1806: aload_3
      //   1807: aload_0
      //   1808: getfield 114	o/CH$ˊ:ˎ	[Ljava/lang/annotation/Annotation;
      //   1811: invokevirtual 530	o/CI:ˋ	(Ljava/lang/reflect/Type;[Ljava/lang/annotation/Annotation;[Ljava/lang/annotation/Annotation;)Lo/Cy;
      //   1814: invokespecial 533	o/CA$ˎ:<init>	(Lo/xz;Lo/Cy;)V
      //   1817: areturn
      //   1818: bipush 34
      //   1820: istore 5
      //   1822: goto +1653 -> 3475
      //   1825: iload 5
      //   1827: tableswitch	default:+21->1848, 0:+-1500->327, 1:+324->2151
      //   1848: goto -1521 -> 327
      //   1851: iconst_1
      //   1852: istore 5
      //   1854: goto +2089 -> 3943
      //   1857: aload_0
      //   1858: getfield 255	o/CH$ˊ:ᐝॱ	Ljava/lang/String;
      //   1861: ifnonnull +6 -> 1867
      //   1864: goto +923 -> 2787
      //   1867: goto +990 -> 2857
      //   1870: aload_0
      //   1871: getfield 391	o/CH$ˊ:ʻॱ	Z
      //   1874: ifne +6 -> 1880
      //   1877: goto +1856 -> 3733
      //   1880: goto -1581 -> 299
      //   1883: iload 5
      //   1885: tableswitch	default:+23->1908, 0:+-408->1477, 1:+1046->2931
      //   1908: goto -431 -> 1477
      //   1911: getstatic 62	o/CH$ˊ:ˊˊ	I
      //   1914: bipush 73
      //   1916: iadd
      //   1917: istore 5
      //   1919: iload 5
      //   1921: sipush 128
      //   1924: irem
      //   1925: putstatic 60	o/CH$ˊ:ˋˊ	I
      //   1928: iload 5
      //   1930: iconst_2
      //   1931: irem
      //   1932: ifeq +6 -> 1938
      //   1935: goto +243 -> 2178
      //   1938: goto +2309 -> 4247
      //   1941: aload_2
      //   1942: instanceof 465
      //   1945: ifne +6 -> 1951
      //   1948: goto +2125 -> 4073
      //   1951: goto +1380 -> 3331
      //   1954: bipush 75
      //   1956: istore 5
      //   1958: goto +1517 -> 3475
      //   1961: aload_0
      //   1962: iload_1
      //   1963: ldc_w 535
      //   1966: iconst_0
      //   1967: anewarray 5	java/lang/Object
      //   1970: invokespecial 191	o/CH$ˊ:ˏ	(ILjava/lang/String;[Ljava/lang/Object;)Ljava/lang/RuntimeException;
      //   1973: athrow
      //   1974: new 467	o/CA$ˊ
      //   1977: dup
      //   1978: aload 4
      //   1980: aload_0
      //   1981: getfield 104	o/CH$ˊ:ˊ	Lo/CI;
      //   1984: aload_2
      //   1985: aload_3
      //   1986: invokevirtual 383	o/CI:ˊ	(Ljava/lang/reflect/Type;[Ljava/lang/annotation/Annotation;)Lo/Cy;
      //   1989: invokespecial 470	o/CA$ˊ:<init>	(Ljava/lang/String;Lo/Cy;)V
      //   1992: areturn
      //   1993: aload_2
      //   1994: checkcast 465	java/lang/reflect/ParameterizedType
      //   1997: astore_2
      //   1998: iconst_0
      //   1999: aload_2
      //   2000: invokestatic 441	o/CM:ॱ	(ILjava/lang/reflect/ParameterizedType;)Ljava/lang/reflect/Type;
      //   2003: astore 7
      //   2005: ldc -125
      //   2007: aload 7
      //   2009: if_acmpeq +6 -> 2015
      //   2012: goto +354 -> 2366
      //   2015: goto -267 -> 1748
      //   2018: aload_0
      //   2019: iload_1
      //   2020: ldc_w 537
      //   2023: iconst_0
      //   2024: anewarray 5	java/lang/Object
      //   2027: invokespecial 191	o/CH$ˊ:ˏ	(ILjava/lang/String;[Ljava/lang/Object;)Ljava/lang/RuntimeException;
      //   2030: athrow
      //   2031: iconst_0
      //   2032: aload_2
      //   2033: checkcast 465	java/lang/reflect/ParameterizedType
      //   2036: invokestatic 441	o/CM:ॱ	(ILjava/lang/reflect/ParameterizedType;)Ljava/lang/reflect/Type;
      //   2039: astore_2
      //   2040: ldc_w 339
      //   2043: aload_2
      //   2044: invokestatic 354	o/CM:ˊ	(Ljava/lang/reflect/Type;)Ljava/lang/Class;
      //   2047: invokevirtual 343	java/lang/Class:isAssignableFrom	(Ljava/lang/Class;)Z
      //   2050: ifeq +6 -> 2056
      //   2053: goto +2276 -> 4329
      //   2056: goto +2702 -> 4758
      //   2059: aload 4
      //   2061: invokevirtual 373	java/lang/Class:isArray	()Z
      //   2064: ifeq +6 -> 2070
      //   2067: goto -1323 -> 744
      //   2070: goto +1313 -> 3383
      //   2073: getstatic 62	o/CH$ˊ:ˊˊ	I
      //   2076: bipush 109
      //   2078: iadd
      //   2079: istore 5
      //   2081: iload 5
      //   2083: sipush 128
      //   2086: irem
      //   2087: putstatic 60	o/CH$ˊ:ˋˊ	I
      //   2090: iload 5
      //   2092: iconst_2
      //   2093: irem
      //   2094: ifeq +6 -> 2100
      //   2097: goto -1356 -> 741
      //   2100: goto +1052 -> 3152
      //   2103: goto +1404 -> 3507
      //   2106: aconst_null
      //   2107: areturn
      //   2108: iconst_0
      //   2109: istore 5
      //   2111: goto +1292 -> 3403
      //   2114: aload 4
      //   2116: instanceof 539
      //   2119: ifeq +6 -> 2125
      //   2122: goto +6 -> 2128
      //   2125: goto +1089 -> 3214
      //   2128: aload_2
      //   2129: invokestatic 354	o/CM:ˊ	(Ljava/lang/reflect/Type;)Ljava/lang/Class;
      //   2132: astore 4
      //   2134: ldc_w 399
      //   2137: aload 4
      //   2139: invokevirtual 343	java/lang/Class:isAssignableFrom	(Ljava/lang/Class;)Z
      //   2142: ifne +6 -> 2148
      //   2145: goto -127 -> 2018
      //   2148: goto -593 -> 1555
      //   2151: aload 4
      //   2153: instanceof 541
      //   2156: ifeq +6 -> 2162
      //   2159: goto +1069 -> 3228
      //   2162: goto -584 -> 1578
      //   2165: aload_0
      //   2166: iload_1
      //   2167: ldc_w 543
      //   2170: iconst_0
      //   2171: anewarray 5	java/lang/Object
      //   2174: invokespecial 191	o/CH$ˊ:ˏ	(ILjava/lang/String;[Ljava/lang/Object;)Ljava/lang/RuntimeException;
      //   2177: athrow
      //   2178: goto +2069 -> 4247
      //   2181: aload_0
      //   2182: iload_1
      //   2183: ldc_w 545
      //   2186: iconst_0
      //   2187: anewarray 5	java/lang/Object
      //   2190: invokespecial 191	o/CH$ˊ:ˏ	(ILjava/lang/String;[Ljava/lang/Object;)Ljava/lang/RuntimeException;
      //   2193: athrow
      //   2194: aload_0
      //   2195: iload_1
      //   2196: ldc_w 535
      //   2199: iconst_1
      //   2200: anewarray 5	java/lang/Object
      //   2203: invokespecial 191	o/CH$ˊ:ˏ	(ILjava/lang/String;[Ljava/lang/Object;)Ljava/lang/RuntimeException;
      //   2206: athrow
      //   2207: iconst_0
      //   2208: istore 5
      //   2210: goto -327 -> 1883
      //   2213: iload 5
      //   2215: lookupswitch	default:+25->2240, 17:+1436->3651, 90:+-345->1870
      //   2240: goto -370 -> 1870
      //   2243: aload_0
      //   2244: iload_1
      //   2245: ldc_w 456
      //   2248: iconst_0
      //   2249: anewarray 5	java/lang/Object
      //   2252: invokespecial 191	o/CH$ˊ:ˏ	(ILjava/lang/String;[Ljava/lang/Object;)Ljava/lang/RuntimeException;
      //   2255: athrow
      //   2256: getstatic 60	o/CH$ˊ:ˋˊ	I
      //   2259: bipush 67
      //   2261: iadd
      //   2262: istore 5
      //   2264: iload 5
      //   2266: sipush 128
      //   2269: irem
      //   2270: putstatic 62	o/CH$ˊ:ˊˊ	I
      //   2273: iload 5
      //   2275: iconst_2
      //   2276: irem
      //   2277: ifne +6 -> 2283
      //   2280: goto +631 -> 2911
      //   2283: goto +1688 -> 3971
      //   2286: iload 5
      //   2288: tableswitch	default:+24->2312, 0:+-1224->1064, 1:+-1189->1099
      //   2312: goto -1213 -> 1099
      //   2315: iconst_1
      //   2316: aload 7
      //   2318: invokestatic 441	o/CM:ॱ	(ILjava/lang/reflect/ParameterizedType;)Ljava/lang/reflect/Type;
      //   2321: astore_2
      //   2322: ldc_w 339
      //   2325: aload_2
      //   2326: invokestatic 354	o/CM:ˊ	(Ljava/lang/reflect/Type;)Ljava/lang/Class;
      //   2329: invokevirtual 343	java/lang/Class:isAssignableFrom	(Ljava/lang/Class;)Z
      //   2332: ifeq +6 -> 2338
      //   2335: goto +1330 -> 3665
      //   2338: goto +1188 -> 3526
      //   2341: aload_2
      //   2342: checkcast 465	java/lang/reflect/ParameterizedType
      //   2345: astore_2
      //   2346: iconst_0
      //   2347: aload_2
      //   2348: invokestatic 441	o/CM:ॱ	(ILjava/lang/reflect/ParameterizedType;)Ljava/lang/reflect/Type;
      //   2351: astore 7
      //   2353: ldc -125
      //   2355: aload 7
      //   2357: if_acmpeq +6 -> 2363
      //   2360: goto +2089 -> 4449
      //   2363: goto -1655 -> 708
      //   2366: aload_0
      //   2367: iload_1
      //   2368: new 198	java/lang/StringBuilder
      //   2371: dup
      //   2372: invokespecial 199	java/lang/StringBuilder:<init>	()V
      //   2375: bipush 39
      //   2377: newarray byte
      //   2379: dup
      //   2380: iconst_0
      //   2381: ldc_w 408
      //   2384: bastore
      //   2385: dup
      //   2386: iconst_1
      //   2387: ldc_w 409
      //   2390: bastore
      //   2391: dup
      //   2392: iconst_2
      //   2393: ldc_w 410
      //   2396: bastore
      //   2397: dup
      //   2398: iconst_3
      //   2399: ldc_w 411
      //   2402: bastore
      //   2403: dup
      //   2404: iconst_4
      //   2405: ldc_w 412
      //   2408: bastore
      //   2409: dup
      //   2410: iconst_5
      //   2411: ldc_w 413
      //   2414: bastore
      //   2415: dup
      //   2416: bipush 6
      //   2418: ldc_w 414
      //   2421: bastore
      //   2422: dup
      //   2423: bipush 7
      //   2425: ldc_w 415
      //   2428: bastore
      //   2429: dup
      //   2430: bipush 8
      //   2432: ldc_w 408
      //   2435: bastore
      //   2436: dup
      //   2437: bipush 9
      //   2439: ldc_w 416
      //   2442: bastore
      //   2443: dup
      //   2444: bipush 10
      //   2446: ldc_w 417
      //   2449: bastore
      //   2450: dup
      //   2451: bipush 11
      //   2453: ldc_w 418
      //   2456: bastore
      //   2457: dup
      //   2458: bipush 12
      //   2460: ldc_w 414
      //   2463: bastore
      //   2464: dup
      //   2465: bipush 13
      //   2467: ldc_w 408
      //   2470: bastore
      //   2471: dup
      //   2472: bipush 14
      //   2474: ldc_w 419
      //   2477: bastore
      //   2478: dup
      //   2479: bipush 15
      //   2481: ldc_w 420
      //   2484: bastore
      //   2485: dup
      //   2486: bipush 16
      //   2488: ldc_w 408
      //   2491: bastore
      //   2492: dup
      //   2493: bipush 17
      //   2495: ldc_w 416
      //   2498: bastore
      //   2499: dup
      //   2500: bipush 18
      //   2502: ldc_w 421
      //   2505: bastore
      //   2506: dup
      //   2507: bipush 19
      //   2509: ldc_w 408
      //   2512: bastore
      //   2513: dup
      //   2514: bipush 20
      //   2516: ldc_w 414
      //   2519: bastore
      //   2520: dup
      //   2521: bipush 21
      //   2523: ldc_w 422
      //   2526: bastore
      //   2527: dup
      //   2528: bipush 22
      //   2530: ldc_w 423
      //   2533: bastore
      //   2534: dup
      //   2535: bipush 23
      //   2537: ldc_w 424
      //   2540: bastore
      //   2541: dup
      //   2542: bipush 24
      //   2544: ldc_w 408
      //   2547: bastore
      //   2548: dup
      //   2549: bipush 25
      //   2551: ldc_w 422
      //   2554: bastore
      //   2555: dup
      //   2556: bipush 26
      //   2558: ldc_w 418
      //   2561: bastore
      //   2562: dup
      //   2563: bipush 27
      //   2565: ldc_w 416
      //   2568: bastore
      //   2569: dup
      //   2570: bipush 28
      //   2572: ldc_w 425
      //   2575: bastore
      //   2576: dup
      //   2577: bipush 29
      //   2579: ldc_w 408
      //   2582: bastore
      //   2583: dup
      //   2584: bipush 30
      //   2586: ldc_w 417
      //   2589: bastore
      //   2590: dup
      //   2591: bipush 31
      //   2593: ldc_w 426
      //   2596: bastore
      //   2597: dup
      //   2598: bipush 32
      //   2600: ldc_w 427
      //   2603: bastore
      //   2604: dup
      //   2605: bipush 33
      //   2607: ldc_w 428
      //   2610: bastore
      //   2611: dup
      //   2612: bipush 34
      //   2614: ldc_w 546
      //   2617: bastore
      //   2618: dup
      //   2619: bipush 35
      //   2621: ldc_w 416
      //   2624: bastore
      //   2625: dup
      //   2626: bipush 36
      //   2628: ldc_w 412
      //   2631: bastore
      //   2632: dup
      //   2633: bipush 37
      //   2635: ldc_w 547
      //   2638: bastore
      //   2639: dup
      //   2640: bipush 38
      //   2642: ldc_w 430
      //   2645: bastore
      //   2646: aconst_null
      //   2647: aconst_null
      //   2648: bipush 127
      //   2650: invokestatic 432	o/CH$ˊ:ˎ	([B[I[CI)Ljava/lang/String;
      //   2653: invokevirtual 435	java/lang/String:intern	()Ljava/lang/String;
      //   2656: invokevirtual 203	java/lang/StringBuilder:append	(Ljava/lang/String;)Ljava/lang/StringBuilder;
      //   2659: aload 7
      //   2661: invokevirtual 438	java/lang/StringBuilder:append	(Ljava/lang/Object;)Ljava/lang/StringBuilder;
      //   2664: invokevirtual 213	java/lang/StringBuilder:toString	()Ljava/lang/String;
      //   2667: iconst_0
      //   2668: anewarray 5	java/lang/Object
      //   2671: invokespecial 191	o/CH$ˊ:ˏ	(ILjava/lang/String;[Ljava/lang/Object;)Ljava/lang/RuntimeException;
      //   2674: athrow
      //   2675: aload_0
      //   2676: iload_1
      //   2677: ldc_w 549
      //   2680: iconst_0
      //   2681: anewarray 5	java/lang/Object
      //   2684: invokespecial 191	o/CH$ˊ:ˏ	(ILjava/lang/String;[Ljava/lang/Object;)Ljava/lang/RuntimeException;
      //   2687: athrow
      //   2688: astore_3
      //   2689: aload_0
      //   2690: aload_3
      //   2691: iload_1
      //   2692: ldc_w 551
      //   2695: iconst_1
      //   2696: anewarray 5	java/lang/Object
      //   2699: dup
      //   2700: iconst_0
      //   2701: aload_2
      //   2702: aastore
      //   2703: invokespecial 553	o/CH$ˊ:ˎ	(Ljava/lang/Throwable;ILjava/lang/String;[Ljava/lang/Object;)Ljava/lang/RuntimeException;
      //   2706: athrow
      //   2707: bipush 24
      //   2709: istore 5
      //   2711: goto +264 -> 2975
      //   2714: iconst_0
      //   2715: aload_2
      //   2716: checkcast 465	java/lang/reflect/ParameterizedType
      //   2719: invokestatic 441	o/CM:ॱ	(ILjava/lang/reflect/ParameterizedType;)Ljava/lang/reflect/Type;
      //   2722: astore_2
      //   2723: new 458	o/CA$ˏ
      //   2726: dup
      //   2727: aload 4
      //   2729: aload_0
      //   2730: getfield 104	o/CH$ˊ:ˊ	Lo/CI;
      //   2733: aload_2
      //   2734: aload_3
      //   2735: invokevirtual 383	o/CI:ˊ	(Ljava/lang/reflect/Type;[Ljava/lang/annotation/Annotation;)Lo/Cy;
      //   2738: iload 6
      //   2740: invokespecial 459	o/CA$ˏ:<init>	(Ljava/lang/String;Lo/Cy;Z)V
      //   2743: invokevirtual 554	o/CA$ˏ:ˎ	()Lo/CA;
      //   2746: areturn
      //   2747: aload_0
      //   2748: iload_1
      //   2749: ldc_w 492
      //   2752: iconst_0
      //   2753: anewarray 5	java/lang/Object
      //   2756: invokespecial 191	o/CH$ˊ:ˏ	(ILjava/lang/String;[Ljava/lang/Object;)Ljava/lang/RuntimeException;
      //   2759: athrow
      //   2760: aload 7
      //   2762: invokevirtual 373	java/lang/Class:isArray	()Z
      //   2765: ifeq +6 -> 2771
      //   2768: goto -1879 -> 889
      //   2771: goto -797 -> 1974
      //   2774: aload_2
      //   2775: instanceof 465
      //   2778: ifne +6 -> 2784
      //   2781: goto +1032 -> 3813
      //   2784: goto -1062 -> 1722
      //   2787: aload_0
      //   2788: iload_1
      //   2789: ldc_w 556
      //   2792: iconst_1
      //   2793: anewarray 5	java/lang/Object
      //   2796: dup
      //   2797: iconst_0
      //   2798: aload_0
      //   2799: getfield 299	o/CH$ˊ:ˋॱ	Ljava/lang/String;
      //   2802: aastore
      //   2803: invokespecial 191	o/CH$ˊ:ˏ	(ILjava/lang/String;[Ljava/lang/Object;)Ljava/lang/RuntimeException;
      //   2806: athrow
      //   2807: getstatic 516	o/CA$ʼ:ˋ	Lo/CA$ʼ;
      //   2810: invokevirtual 557	o/CA$ʼ:ˎ	()Lo/CA;
      //   2813: areturn
      //   2814: aload_2
      //   2815: checkcast 465	java/lang/reflect/ParameterizedType
      //   2818: astore_2
      //   2819: iconst_0
      //   2820: aload_2
      //   2821: invokestatic 441	o/CM:ॱ	(ILjava/lang/reflect/ParameterizedType;)Ljava/lang/reflect/Type;
      //   2824: astore_2
      //   2825: aload_0
      //   2826: getfield 104	o/CH$ˊ:ˊ	Lo/CI;
      //   2829: astore 7
      //   2831: aload 7
      //   2833: aload_2
      //   2834: aload_3
      //   2835: invokevirtual 383	o/CI:ˊ	(Ljava/lang/reflect/Type;[Ljava/lang/annotation/Annotation;)Lo/Cy;
      //   2838: astore_2
      //   2839: new 467	o/CA$ˊ
      //   2842: dup
      //   2843: aload 4
      //   2845: aload_2
      //   2846: invokespecial 470	o/CA$ˊ:<init>	(Ljava/lang/String;Lo/Cy;)V
      //   2849: astore_2
      //   2850: aload_2
      //   2851: invokevirtual 558	o/CA$ˊ:ˎ	()Lo/CA;
      //   2854: astore_2
      //   2855: aload_2
      //   2856: areturn
      //   2857: aload_0
      //   2858: iconst_1
      //   2859: putfield 560	o/CH$ˊ:ʼ	Z
      //   2862: aload 4
      //   2864: checkcast 562	o/Dp
      //   2867: astore 7
      //   2869: aload 7
      //   2871: invokeinterface 564 1 0
      //   2876: astore 4
      //   2878: aload_0
      //   2879: iload_1
      //   2880: aload 4
      //   2882: invokespecial 566	o/CH$ˊ:ˎ	(ILjava/lang/String;)V
      //   2885: new 568	o/CA$IF
      //   2888: dup
      //   2889: aload 4
      //   2891: aload_0
      //   2892: getfield 104	o/CH$ˊ:ˊ	Lo/CI;
      //   2895: aload_2
      //   2896: aload_3
      //   2897: invokevirtual 383	o/CI:ˊ	(Ljava/lang/reflect/Type;[Ljava/lang/annotation/Annotation;)Lo/Cy;
      //   2900: aload 7
      //   2902: invokeinterface 569 1 0
      //   2907: invokespecial 570	o/CA$IF:<init>	(Ljava/lang/String;Lo/Cy;Z)V
      //   2910: areturn
      //   2911: iconst_0
      //   2912: istore 5
      //   2914: goto -628 -> 2286
      //   2917: aload 4
      //   2919: invokevirtual 373	java/lang/Class:isArray	()Z
      //   2922: ifeq +6 -> 2928
      //   2925: goto -2694 -> 231
      //   2928: goto +340 -> 3268
      //   2931: ldc_w 356
      //   2934: aload 4
      //   2936: invokevirtual 343	java/lang/Class:isAssignableFrom	(Ljava/lang/Class;)Z
      //   2939: ifeq +6 -> 2945
      //   2942: goto -168 -> 2774
      //   2945: goto -2728 -> 217
      //   2948: iload 5
      //   2950: tableswitch	default:+22->2972, 0:+-2101->849, 1:+1218->4168
      //   2972: goto -2123 -> 849
      //   2975: iload 5
      //   2977: lookupswitch	default:+27->3004, 24:+-2597->380, 41:+-1858->1119
      //   3004: goto -1885 -> 1119
      //   3007: iconst_0
      //   3008: istore 5
      //   3010: goto -1185 -> 1825
      //   3013: aload 4
      //   3015: instanceof 521
      //   3018: ifeq +6 -> 3024
      //   3021: goto +1389 -> 4410
      //   3024: goto +293 -> 3317
      //   3027: aload 4
      //   3029: instanceof 562
      //   3032: ifeq +6 -> 3038
      //   3035: goto -2935 -> 100
      //   3038: goto +393 -> 3431
      //   3041: aload_0
      //   3042: iload_1
      //   3043: ldc_w 572
      //   3046: iconst_1
      //   3047: anewarray 5	java/lang/Object
      //   3050: invokespecial 191	o/CH$ˊ:ˏ	(ILjava/lang/String;[Ljava/lang/Object;)Ljava/lang/RuntimeException;
      //   3053: athrow
      //   3054: aload_0
      //   3055: getfield 104	o/CH$ˊ:ˊ	Lo/CI;
      //   3058: aload_2
      //   3059: aload_3
      //   3060: aload_0
      //   3061: getfield 114	o/CH$ˊ:ˎ	[Ljava/lang/annotation/Annotation;
      //   3064: invokevirtual 530	o/CI:ˋ	(Ljava/lang/reflect/Type;[Ljava/lang/annotation/Annotation;[Ljava/lang/annotation/Annotation;)Lo/Cy;
      //   3067: astore_3
      //   3068: goto -2047 -> 1021
      //   3071: aload 4
      //   3073: instanceof 574
      //   3076: ifeq +6 -> 3082
      //   3079: goto +898 -> 3977
      //   3082: goto -55 -> 3027
      //   3085: aload_2
      //   3086: instanceof 465
      //   3089: ifne +6 -> 3095
      //   3092: goto +1250 -> 4342
      //   3095: goto -1064 -> 2031
      //   3098: aload_0
      //   3099: iload_1
      //   3100: new 198	java/lang/StringBuilder
      //   3103: dup
      //   3104: invokespecial 199	java/lang/StringBuilder:<init>	()V
      //   3107: aload 7
      //   3109: invokevirtual 329	java/lang/Class:getSimpleName	()Ljava/lang/String;
      //   3112: invokevirtual 203	java/lang/StringBuilder:append	(Ljava/lang/String;)Ljava/lang/StringBuilder;
      //   3115: ldc_w 366
      //   3118: invokevirtual 203	java/lang/StringBuilder:append	(Ljava/lang/String;)Ljava/lang/StringBuilder;
      //   3121: aload 7
      //   3123: invokevirtual 329	java/lang/Class:getSimpleName	()Ljava/lang/String;
      //   3126: invokevirtual 203	java/lang/StringBuilder:append	(Ljava/lang/String;)Ljava/lang/StringBuilder;
      //   3129: ldc_w 368
      //   3132: invokevirtual 203	java/lang/StringBuilder:append	(Ljava/lang/String;)Ljava/lang/StringBuilder;
      //   3135: invokevirtual 213	java/lang/StringBuilder:toString	()Ljava/lang/String;
      //   3138: iconst_0
      //   3139: anewarray 5	java/lang/Object
      //   3142: invokespecial 191	o/CH$ˊ:ˏ	(ILjava/lang/String;[Ljava/lang/Object;)Ljava/lang/RuntimeException;
      //   3145: athrow
      //   3146: iconst_0
      //   3147: istore 5
      //   3149: goto -201 -> 2948
      //   3152: aload_2
      //   3153: ldc -125
      //   3155: if_acmpeq +6 -> 3161
      //   3158: goto -3028 -> 130
      //   3161: goto -2042 -> 1119
      //   3164: aload_0
      //   3165: getfield 393	o/CH$ˊ:ˊॱ	Z
      //   3168: ifeq +6 -> 3174
      //   3171: goto +717 -> 3888
      //   3174: goto -1317 -> 1857
      //   3177: aload 7
      //   3179: invokevirtual 373	java/lang/Class:isArray	()Z
      //   3182: ifeq +6 -> 3188
      //   3185: goto -2416 -> 769
      //   3188: goto +174 -> 3362
      //   3191: aload_2
      //   3192: aload 7
      //   3194: ldc_w 399
      //   3197: invokestatic 485	o/CM:ˎ	(Ljava/lang/reflect/Type;Ljava/lang/Class;Ljava/lang/Class;)Ljava/lang/reflect/Type;
      //   3200: astore_2
      //   3201: aload_2
      //   3202: instanceof 465
      //   3205: ifne +6 -> 3211
      //   3208: goto -1100 -> 2108
      //   3211: goto +830 -> 4041
      //   3214: aload 4
      //   3216: instanceof 345
      //   3219: ifeq +6 -> 3225
      //   3222: goto -3149 -> 73
      //   3225: goto -212 -> 3013
      //   3228: aload 4
      //   3230: checkcast 541	o/Dq
      //   3233: invokeinterface 575 1 0
      //   3238: istore 6
      //   3240: aload_2
      //   3241: invokestatic 354	o/CM:ˊ	(Ljava/lang/reflect/Type;)Ljava/lang/Class;
      //   3244: astore 4
      //   3246: aload_0
      //   3247: iconst_1
      //   3248: putfield 407	o/CH$ˊ:ˏॱ	Z
      //   3251: ldc_w 356
      //   3254: aload 4
      //   3256: invokevirtual 343	java/lang/Class:isAssignableFrom	(Ljava/lang/Class;)Z
      //   3259: ifeq +6 -> 3265
      //   3262: goto +791 -> 4053
      //   3265: goto -1414 -> 1851
      //   3268: new 381	o/CA$AUx
      //   3271: dup
      //   3272: aload_0
      //   3273: getfield 104	o/CH$ˊ:ˊ	Lo/CI;
      //   3276: aload_2
      //   3277: aload_3
      //   3278: invokevirtual 383	o/CI:ˊ	(Ljava/lang/reflect/Type;[Ljava/lang/annotation/Annotation;)Lo/Cy;
      //   3281: iload 6
      //   3283: invokespecial 386	o/CA$AUx:<init>	(Lo/Cy;Z)V
      //   3286: areturn
      //   3287: getstatic 62	o/CH$ˊ:ˊˊ	I
      //   3290: bipush 31
      //   3292: iadd
      //   3293: istore 5
      //   3295: iload 5
      //   3297: sipush 128
      //   3300: irem
      //   3301: putstatic 60	o/CH$ˊ:ˋˊ	I
      //   3304: iload 5
      //   3306: iconst_2
      //   3307: irem
      //   3308: ifeq +6 -> 3314
      //   3311: goto +748 -> 4059
      //   3314: goto +393 -> 3707
      //   3317: aload 4
      //   3319: instanceof 504
      //   3322: ifeq +6 -> 3328
      //   3325: goto -3063 -> 262
      //   3328: goto -3242 -> 86
      //   3331: iconst_0
      //   3332: aload_2
      //   3333: checkcast 465	java/lang/reflect/ParameterizedType
      //   3336: invokestatic 441	o/CM:ॱ	(ILjava/lang/reflect/ParameterizedType;)Ljava/lang/reflect/Type;
      //   3339: astore_2
      //   3340: new 381	o/CA$AUx
      //   3343: dup
      //   3344: aload_0
      //   3345: getfield 104	o/CH$ˊ:ˊ	Lo/CI;
      //   3348: aload_2
      //   3349: aload_3
      //   3350: invokevirtual 383	o/CI:ˊ	(Ljava/lang/reflect/Type;[Ljava/lang/annotation/Annotation;)Lo/Cy;
      //   3353: iload 6
      //   3355: invokespecial 386	o/CA$AUx:<init>	(Lo/Cy;Z)V
      //   3358: invokevirtual 576	o/CA$AUx:ˎ	()Lo/CA;
      //   3361: areturn
      //   3362: new 450	o/CA$If
      //   3365: dup
      //   3366: aload 4
      //   3368: aload_0
      //   3369: getfield 104	o/CH$ˊ:ˊ	Lo/CI;
      //   3372: aload_2
      //   3373: aload_3
      //   3374: invokevirtual 383	o/CI:ˊ	(Ljava/lang/reflect/Type;[Ljava/lang/annotation/Annotation;)Lo/Cy;
      //   3377: iload 6
      //   3379: invokespecial 453	o/CA$If:<init>	(Ljava/lang/String;Lo/Cy;Z)V
      //   3382: areturn
      //   3383: ldc_w 339
      //   3386: aload 4
      //   3388: invokevirtual 343	java/lang/Class:isAssignableFrom	(Ljava/lang/Class;)Z
      //   3391: ifeq +6 -> 3397
      //   3394: goto -2267 -> 1127
      //   3397: goto -1602 -> 1795
      //   3400: astore_2
      //   3401: aload_2
      //   3402: athrow
      //   3403: iload 5
      //   3405: tableswitch	default:+23->3428, 0:+185->3590, 1:+-1800->1605
      //   3428: goto +162 -> 3590
      //   3431: aload 4
      //   3433: instanceof 401
      //   3436: ifeq +6 -> 3442
      //   3439: goto -432 -> 3007
      //   3442: goto -2407 -> 1035
      //   3445: getstatic 60	o/CH$ˊ:ˋˊ	I
      //   3448: bipush 65
      //   3450: iadd
      //   3451: istore 5
      //   3453: iload 5
      //   3455: sipush 128
      //   3458: irem
      //   3459: putstatic 62	o/CH$ˊ:ˊˊ	I
      //   3462: iload 5
      //   3464: iconst_2
      //   3465: irem
      //   3466: ifne +6 -> 3472
      //   3469: goto -1275 -> 2194
      //   3472: goto -1511 -> 1961
      //   3475: iload 5
      //   3477: lookupswitch	default:+27->3504, 34:+668->4145, 75:+-1808->1669
      //   3504: goto -1835 -> 1669
      //   3507: aload_0
      //   3508: getfield 407	o/CH$ˊ:ˏॱ	Z
      //   3511: ifeq +6 -> 3517
      //   3514: goto +714 -> 4228
      //   3517: goto -353 -> 3164
      //   3520: iconst_1
      //   3521: istore 5
      //   3523: goto -575 -> 2948
      //   3526: new 578	o/CA$aux
      //   3529: dup
      //   3530: aload_0
      //   3531: getfield 104	o/CH$ˊ:ˊ	Lo/CI;
      //   3534: aload_2
      //   3535: aload_3
      //   3536: aload_0
      //   3537: getfield 114	o/CH$ˊ:ˎ	[Ljava/lang/annotation/Annotation;
      //   3540: invokevirtual 530	o/CI:ˋ	(Ljava/lang/reflect/Type;[Ljava/lang/annotation/Annotation;[Ljava/lang/annotation/Annotation;)Lo/Cy;
      //   3543: aload 4
      //   3545: checkcast 360	o/Dj
      //   3548: invokeinterface 579 1 0
      //   3553: invokespecial 582	o/CA$aux:<init>	(Lo/Cy;Ljava/lang/String;)V
      //   3556: areturn
      //   3557: aload_0
      //   3558: getfield 477	o/CH$ˊ:ॱॱ	Z
      //   3561: ifeq +6 -> 3567
      //   3564: goto -2728 -> 836
      //   3567: goto -513 -> 3054
      //   3570: bipush 17
      //   3572: istore 5
      //   3574: goto -1361 -> 2213
      //   3577: aload_0
      //   3578: iload_1
      //   3579: ldc_w 364
      //   3582: iconst_0
      //   3583: anewarray 5	java/lang/Object
      //   3586: invokespecial 191	o/CH$ˊ:ˏ	(ILjava/lang/String;[Ljava/lang/Object;)Ljava/lang/RuntimeException;
      //   3589: athrow
      //   3590: aload_0
      //   3591: iload_1
      //   3592: ldc_w 584
      //   3595: iconst_0
      //   3596: anewarray 5	java/lang/Object
      //   3599: invokespecial 191	o/CH$ˊ:ˏ	(ILjava/lang/String;[Ljava/lang/Object;)Ljava/lang/RuntimeException;
      //   3602: athrow
      //   3603: aload_0
      //   3604: iload_1
      //   3605: ldc_w 586
      //   3608: iconst_0
      //   3609: anewarray 5	java/lang/Object
      //   3612: invokespecial 191	o/CH$ˊ:ˏ	(ILjava/lang/String;[Ljava/lang/Object;)Ljava/lang/RuntimeException;
      //   3615: athrow
      //   3616: ldc_w 588
      //   3619: aload_2
      //   3620: checkcast 326	java/lang/Class
      //   3623: invokevirtual 589	java/lang/Class:getName	()Ljava/lang/String;
      //   3626: invokevirtual 592	java/lang/String:equals	(Ljava/lang/Object;)Z
      //   3629: ifeq +6 -> 3635
      //   3632: goto -2513 -> 1119
      //   3635: goto -1454 -> 2181
      //   3638: aload_0
      //   3639: iload_1
      //   3640: ldc_w 584
      //   3643: iconst_0
      //   3644: anewarray 5	java/lang/Object
      //   3647: invokespecial 191	o/CH$ˊ:ˏ	(ILjava/lang/String;[Ljava/lang/Object;)Ljava/lang/RuntimeException;
      //   3650: athrow
      //   3651: aload 4
      //   3653: instanceof 594
      //   3656: ifeq +6 -> 3662
      //   3659: goto +87 -> 3746
      //   3662: goto -1556 -> 2106
      //   3665: aload_0
      //   3666: iload_1
      //   3667: ldc_w 596
      //   3670: iconst_0
      //   3671: anewarray 5	java/lang/Object
      //   3674: invokespecial 191	o/CH$ˊ:ˏ	(ILjava/lang/String;[Ljava/lang/Object;)Ljava/lang/RuntimeException;
      //   3677: athrow
      //   3678: iload 5
      //   3680: tableswitch	default:+24->3704, 0:+-1499->2181, 1:+-64->3616
      //   3704: goto -1523 -> 2181
      //   3707: aload_2
      //   3708: instanceof 465
      //   3711: ifne +6 -> 3717
      //   3714: goto -3558 -> 156
      //   3717: goto -903 -> 2814
      //   3720: aload_0
      //   3721: iload_1
      //   3722: ldc_w 598
      //   3725: iconst_0
      //   3726: anewarray 5	java/lang/Object
      //   3729: invokespecial 191	o/CH$ˊ:ˏ	(ILjava/lang/String;[Ljava/lang/Object;)Ljava/lang/RuntimeException;
      //   3732: athrow
      //   3733: aload_0
      //   3734: iload_1
      //   3735: ldc_w 600
      //   3738: iconst_0
      //   3739: anewarray 5	java/lang/Object
      //   3742: invokespecial 191	o/CH$ˊ:ˏ	(ILjava/lang/String;[Ljava/lang/Object;)Ljava/lang/RuntimeException;
      //   3745: athrow
      //   3746: aload_0
      //   3747: getfield 358	o/CH$ˊ:ॱˊ	Z
      //   3750: ifne +6 -> 3756
      //   3753: goto -2667 -> 1086
      //   3756: goto -1081 -> 2675
      //   3759: aload_0
      //   3760: iload_1
      //   3761: ldc_w 586
      //   3764: iconst_1
      //   3765: anewarray 5	java/lang/Object
      //   3768: invokespecial 191	o/CH$ˊ:ˏ	(ILjava/lang/String;[Ljava/lang/Object;)Ljava/lang/RuntimeException;
      //   3771: athrow
      //   3772: aload 4
      //   3774: checkcast 504	o/Dn
      //   3777: astore 8
      //   3779: aload_0
      //   3780: iconst_1
      //   3781: putfield 397	o/CH$ˊ:ʽ	Z
      //   3784: aload 8
      //   3786: invokeinterface 602 1 0
      //   3791: astore 7
      //   3793: aload_2
      //   3794: invokestatic 354	o/CM:ˊ	(Ljava/lang/reflect/Type;)Ljava/lang/Class;
      //   3797: astore 4
      //   3799: aload 7
      //   3801: invokevirtual 304	java/lang/String:isEmpty	()Z
      //   3804: ifeq +6 -> 3810
      //   3807: goto -3532 -> 275
      //   3810: goto -1603 -> 2207
      //   3813: aload_0
      //   3814: iload_1
      //   3815: new 198	java/lang/StringBuilder
      //   3818: dup
      //   3819: invokespecial 199	java/lang/StringBuilder:<init>	()V
      //   3822: aload 4
      //   3824: invokevirtual 329	java/lang/Class:getSimpleName	()Ljava/lang/String;
      //   3827: invokevirtual 203	java/lang/StringBuilder:append	(Ljava/lang/String;)Ljava/lang/StringBuilder;
      //   3830: ldc_w 366
      //   3833: invokevirtual 203	java/lang/StringBuilder:append	(Ljava/lang/String;)Ljava/lang/StringBuilder;
      //   3836: aload 4
      //   3838: invokevirtual 329	java/lang/Class:getSimpleName	()Ljava/lang/String;
      //   3841: invokevirtual 203	java/lang/StringBuilder:append	(Ljava/lang/String;)Ljava/lang/StringBuilder;
      //   3844: ldc_w 368
      //   3847: invokevirtual 203	java/lang/StringBuilder:append	(Ljava/lang/String;)Ljava/lang/StringBuilder;
      //   3850: invokevirtual 213	java/lang/StringBuilder:toString	()Ljava/lang/String;
      //   3853: iconst_0
      //   3854: anewarray 5	java/lang/Object
      //   3857: invokespecial 191	o/CH$ˊ:ˏ	(ILjava/lang/String;[Ljava/lang/Object;)Ljava/lang/RuntimeException;
      //   3860: athrow
      //   3861: aload_0
      //   3862: iload_1
      //   3863: ldc_w 572
      //   3866: iconst_0
      //   3867: anewarray 5	java/lang/Object
      //   3870: invokespecial 191	o/CH$ˊ:ˏ	(ILjava/lang/String;[Ljava/lang/Object;)Ljava/lang/RuntimeException;
      //   3873: athrow
      //   3874: aload 7
      //   3876: invokevirtual 373	java/lang/Class:isArray	()Z
      //   3879: ifeq +6 -> 3885
      //   3882: goto -2742 -> 1140
      //   3885: goto -3070 -> 815
      //   3888: getstatic 62	o/CH$ˊ:ˊˊ	I
      //   3891: iconst_3
      //   3892: iadd
      //   3893: istore 5
      //   3895: iload 5
      //   3897: sipush 128
      //   3900: irem
      //   3901: putstatic 60	o/CH$ˊ:ˋˊ	I
      //   3904: iload 5
      //   3906: iconst_2
      //   3907: irem
      //   3908: ifeq +6 -> 3914
      //   3911: goto +92 -> 4003
      //   3914: goto -1671 -> 2243
      //   3917: new 527	o/CA$ˎ
      //   3920: dup
      //   3921: aload 7
      //   3923: aload_0
      //   3924: getfield 104	o/CH$ˊ:ˊ	Lo/CI;
      //   3927: aload_2
      //   3928: aload_3
      //   3929: aload_0
      //   3930: getfield 114	o/CH$ˊ:ˎ	[Ljava/lang/annotation/Annotation;
      //   3933: invokevirtual 530	o/CI:ˋ	(Ljava/lang/reflect/Type;[Ljava/lang/annotation/Annotation;[Ljava/lang/annotation/Annotation;)Lo/Cy;
      //   3936: invokespecial 533	o/CA$ˎ:<init>	(Lo/xz;Lo/Cy;)V
      //   3939: invokevirtual 603	o/CA$ˎ:ˋ	()Lo/CA;
      //   3942: areturn
      //   3943: iload 5
      //   3945: tableswitch	default:+23->3968, 0:+-2004->1941, 1:+-1028->2917
      //   3968: goto -2027 -> 1941
      //   3971: iconst_1
      //   3972: istore 5
      //   3974: goto -1688 -> 2286
      //   3977: aload_0
      //   3978: getfield 393	o/CH$ˊ:ˊॱ	Z
      //   3981: ifeq +6 -> 3987
      //   3984: goto -539 -> 3445
      //   3987: goto +303 -> 4290
      //   3990: aload_0
      //   3991: iload_1
      //   3992: ldc_w 584
      //   3995: iconst_0
      //   3996: anewarray 5	java/lang/Object
      //   3999: invokespecial 191	o/CH$ˊ:ˏ	(ILjava/lang/String;[Ljava/lang/Object;)Ljava/lang/RuntimeException;
      //   4002: athrow
      //   4003: aload_0
      //   4004: iload_1
      //   4005: ldc_w 456
      //   4008: iconst_1
      //   4009: anewarray 5	java/lang/Object
      //   4012: invokespecial 191	o/CH$ˊ:ˏ	(ILjava/lang/String;[Ljava/lang/Object;)Ljava/lang/RuntimeException;
      //   4015: athrow
      //   4016: aload_2
      //   4017: checkcast 465	java/lang/reflect/ParameterizedType
      //   4020: astore 4
      //   4022: iconst_0
      //   4023: aload 4
      //   4025: invokestatic 441	o/CM:ॱ	(ILjava/lang/reflect/ParameterizedType;)Ljava/lang/reflect/Type;
      //   4028: astore_2
      //   4029: ldc -125
      //   4031: aload_2
      //   4032: if_acmpeq +6 -> 4038
      //   4035: goto -3642 -> 393
      //   4038: goto +83 -> 4121
      //   4041: iconst_1
      //   4042: istore 5
      //   4044: goto -641 -> 3403
      //   4047: iconst_1
      //   4048: istore 5
      //   4050: goto -372 -> 3678
      //   4053: iconst_0
      //   4054: istore 5
      //   4056: goto -113 -> 3943
      //   4059: aload_2
      //   4060: instanceof 465
      //   4063: istore 6
      //   4065: new 246	java/lang/NullPointerException
      //   4068: dup
      //   4069: invokespecial 247	java/lang/NullPointerException:<init>	()V
      //   4072: athrow
      //   4073: aload_0
      //   4074: iload_1
      //   4075: new 198	java/lang/StringBuilder
      //   4078: dup
      //   4079: invokespecial 199	java/lang/StringBuilder:<init>	()V
      //   4082: aload 4
      //   4084: invokevirtual 329	java/lang/Class:getSimpleName	()Ljava/lang/String;
      //   4087: invokevirtual 203	java/lang/StringBuilder:append	(Ljava/lang/String;)Ljava/lang/StringBuilder;
      //   4090: ldc_w 366
      //   4093: invokevirtual 203	java/lang/StringBuilder:append	(Ljava/lang/String;)Ljava/lang/StringBuilder;
      //   4096: aload 4
      //   4098: invokevirtual 329	java/lang/Class:getSimpleName	()Ljava/lang/String;
      //   4101: invokevirtual 203	java/lang/StringBuilder:append	(Ljava/lang/String;)Ljava/lang/StringBuilder;
      //   4104: ldc_w 368
      //   4107: invokevirtual 203	java/lang/StringBuilder:append	(Ljava/lang/String;)Ljava/lang/StringBuilder;
      //   4110: invokevirtual 213	java/lang/StringBuilder:toString	()Ljava/lang/String;
      //   4113: iconst_0
      //   4114: anewarray 5	java/lang/Object
      //   4117: invokespecial 191	o/CH$ˊ:ˏ	(ILjava/lang/String;[Ljava/lang/Object;)Ljava/lang/RuntimeException;
      //   4120: athrow
      //   4121: iconst_1
      //   4122: aload 4
      //   4124: invokestatic 441	o/CM:ॱ	(ILjava/lang/reflect/ParameterizedType;)Ljava/lang/reflect/Type;
      //   4127: astore_2
      //   4128: new 605	o/CA$iF
      //   4131: dup
      //   4132: aload_0
      //   4133: getfield 104	o/CH$ˊ:ˊ	Lo/CI;
      //   4136: aload_2
      //   4137: aload_3
      //   4138: invokevirtual 383	o/CI:ˊ	(Ljava/lang/reflect/Type;[Ljava/lang/annotation/Annotation;)Lo/Cy;
      //   4141: invokespecial 606	o/CA$iF:<init>	(Lo/Cy;)V
      //   4144: areturn
      //   4145: aload_2
      //   4146: aload 7
      //   4148: ldc_w 399
      //   4151: invokestatic 485	o/CM:ˎ	(Ljava/lang/reflect/Type;Ljava/lang/Class;Ljava/lang/Class;)Ljava/lang/reflect/Type;
      //   4154: astore_2
      //   4155: aload_2
      //   4156: instanceof 465
      //   4159: ifne +6 -> 4165
      //   4162: goto -172 -> 3990
      //   4165: goto -1824 -> 2341
      //   4168: aload_2
      //   4169: invokestatic 354	o/CM:ˊ	(Ljava/lang/reflect/Type;)Ljava/lang/Class;
      //   4172: astore 7
      //   4174: ldc_w 399
      //   4177: aload 7
      //   4179: invokevirtual 343	java/lang/Class:isAssignableFrom	(Ljava/lang/Class;)Z
      //   4182: ifne +6 -> 4188
      //   4185: goto -2231 -> 1954
      //   4188: goto -2370 -> 1818
      //   4191: bipush 41
      //   4193: istore 5
      //   4195: goto -1220 -> 2975
      //   4198: getstatic 60	o/CH$ˊ:ˋˊ	I
      //   4201: bipush 35
      //   4203: iadd
      //   4204: istore 5
      //   4206: iload 5
      //   4208: sipush 128
      //   4211: irem
      //   4212: putstatic 62	o/CH$ˊ:ˊˊ	I
      //   4215: iload 5
      //   4217: iconst_2
      //   4218: irem
      //   4219: ifne +6 -> 4225
      //   4222: goto -1181 -> 3041
      //   4225: goto -364 -> 3861
      //   4228: aload_0
      //   4229: iload_1
      //   4230: ldc_w 608
      //   4233: iconst_0
      //   4234: anewarray 5	java/lang/Object
      //   4237: invokespecial 191	o/CH$ˊ:ˏ	(ILjava/lang/String;[Ljava/lang/Object;)Ljava/lang/RuntimeException;
      //   4240: athrow
      //   4241: iconst_0
      //   4242: istore 5
      //   4244: goto -566 -> 3678
      //   4247: aload_2
      //   4248: instanceof 465
      //   4251: ifne +6 -> 4257
      //   4254: goto -1156 -> 3098
      //   4257: goto -1543 -> 2714
      //   4260: getstatic 60	o/CH$ˊ:ˋˊ	I
      //   4263: bipush 87
      //   4265: iadd
      //   4266: istore 5
      //   4268: iload 5
      //   4270: sipush 128
      //   4273: irem
      //   4274: putstatic 62	o/CH$ˊ:ˊˊ	I
      //   4277: iload 5
      //   4279: iconst_2
      //   4280: irem
      //   4281: ifne +6 -> 4287
      //   4284: goto -525 -> 3759
      //   4287: goto -684 -> 3603
      //   4290: aload_0
      //   4291: getfield 560	o/CH$ˊ:ʼ	Z
      //   4294: ifeq +6 -> 4300
      //   4297: goto -3495 -> 802
      //   4300: goto +136 -> 4436
      //   4303: aload_0
      //   4304: iload_1
      //   4305: ldc_w 584
      //   4308: iconst_0
      //   4309: anewarray 5	java/lang/Object
      //   4312: invokespecial 191	o/CH$ˊ:ˏ	(ILjava/lang/String;[Ljava/lang/Object;)Ljava/lang/RuntimeException;
      //   4315: athrow
      //   4316: aload_0
      //   4317: iload_1
      //   4318: ldc_w 543
      //   4321: iconst_0
      //   4322: anewarray 5	java/lang/Object
      //   4325: invokespecial 191	o/CH$ˊ:ˏ	(ILjava/lang/String;[Ljava/lang/Object;)Ljava/lang/RuntimeException;
      //   4328: athrow
      //   4329: aload_0
      //   4330: iload_1
      //   4331: ldc_w 492
      //   4334: iconst_0
      //   4335: anewarray 5	java/lang/Object
      //   4338: invokespecial 191	o/CH$ˊ:ˏ	(ILjava/lang/String;[Ljava/lang/Object;)Ljava/lang/RuntimeException;
      //   4341: athrow
      //   4342: aload_0
      //   4343: iload_1
      //   4344: new 198	java/lang/StringBuilder
      //   4347: dup
      //   4348: invokespecial 199	java/lang/StringBuilder:<init>	()V
      //   4351: aload 4
      //   4353: invokevirtual 329	java/lang/Class:getSimpleName	()Ljava/lang/String;
      //   4356: invokevirtual 203	java/lang/StringBuilder:append	(Ljava/lang/String;)Ljava/lang/StringBuilder;
      //   4359: ldc_w 366
      //   4362: invokevirtual 203	java/lang/StringBuilder:append	(Ljava/lang/String;)Ljava/lang/StringBuilder;
      //   4365: aload 4
      //   4367: invokevirtual 329	java/lang/Class:getSimpleName	()Ljava/lang/String;
      //   4370: invokevirtual 203	java/lang/StringBuilder:append	(Ljava/lang/String;)Ljava/lang/StringBuilder;
      //   4373: ldc_w 368
      //   4376: invokevirtual 203	java/lang/StringBuilder:append	(Ljava/lang/String;)Ljava/lang/StringBuilder;
      //   4379: invokevirtual 213	java/lang/StringBuilder:toString	()Ljava/lang/String;
      //   4382: iconst_0
      //   4383: anewarray 5	java/lang/Object
      //   4386: invokespecial 191	o/CH$ˊ:ˏ	(ILjava/lang/String;[Ljava/lang/Object;)Ljava/lang/RuntimeException;
      //   4389: athrow
      //   4390: ldc_w 339
      //   4393: aload 4
      //   4395: invokevirtual 376	java/lang/Class:getComponentType	()Ljava/lang/Class;
      //   4398: invokevirtual 343	java/lang/Class:isAssignableFrom	(Ljava/lang/Class;)Z
      //   4401: ifne +6 -> 4407
      //   4404: goto -4261 -> 143
      //   4407: goto -2619 -> 1788
      //   4410: aload_0
      //   4411: getfield 358	o/CH$ˊ:ॱˊ	Z
      //   4414: ifne +6 -> 4420
      //   4417: goto -4213 -> 204
      //   4420: goto -2721 -> 1699
      //   4423: aload_0
      //   4424: iload_1
      //   4425: ldc_w 364
      //   4428: iconst_0
      //   4429: anewarray 5	java/lang/Object
      //   4432: invokespecial 191	o/CH$ˊ:ˏ	(ILjava/lang/String;[Ljava/lang/Object;)Ljava/lang/RuntimeException;
      //   4435: athrow
      //   4436: aload_0
      //   4437: getfield 407	o/CH$ˊ:ˏॱ	Z
      //   4440: ifeq +6 -> 4446
      //   4443: goto -245 -> 4198
      //   4446: goto -3570 -> 876
      //   4449: aload_0
      //   4450: iload_1
      //   4451: new 198	java/lang/StringBuilder
      //   4454: dup
      //   4455: invokespecial 199	java/lang/StringBuilder:<init>	()V
      //   4458: bipush 39
      //   4460: newarray byte
      //   4462: dup
      //   4463: iconst_0
      //   4464: ldc_w 408
      //   4467: bastore
      //   4468: dup
      //   4469: iconst_1
      //   4470: ldc_w 409
      //   4473: bastore
      //   4474: dup
      //   4475: iconst_2
      //   4476: ldc_w 410
      //   4479: bastore
      //   4480: dup
      //   4481: iconst_3
      //   4482: ldc_w 411
      //   4485: bastore
      //   4486: dup
      //   4487: iconst_4
      //   4488: ldc_w 412
      //   4491: bastore
      //   4492: dup
      //   4493: iconst_5
      //   4494: ldc_w 413
      //   4497: bastore
      //   4498: dup
      //   4499: bipush 6
      //   4501: ldc_w 414
      //   4504: bastore
      //   4505: dup
      //   4506: bipush 7
      //   4508: ldc_w 415
      //   4511: bastore
      //   4512: dup
      //   4513: bipush 8
      //   4515: ldc_w 408
      //   4518: bastore
      //   4519: dup
      //   4520: bipush 9
      //   4522: ldc_w 416
      //   4525: bastore
      //   4526: dup
      //   4527: bipush 10
      //   4529: ldc_w 417
      //   4532: bastore
      //   4533: dup
      //   4534: bipush 11
      //   4536: ldc_w 418
      //   4539: bastore
      //   4540: dup
      //   4541: bipush 12
      //   4543: ldc_w 414
      //   4546: bastore
      //   4547: dup
      //   4548: bipush 13
      //   4550: ldc_w 408
      //   4553: bastore
      //   4554: dup
      //   4555: bipush 14
      //   4557: ldc_w 419
      //   4560: bastore
      //   4561: dup
      //   4562: bipush 15
      //   4564: ldc_w 420
      //   4567: bastore
      //   4568: dup
      //   4569: bipush 16
      //   4571: ldc_w 408
      //   4574: bastore
      //   4575: dup
      //   4576: bipush 17
      //   4578: ldc_w 416
      //   4581: bastore
      //   4582: dup
      //   4583: bipush 18
      //   4585: ldc_w 421
      //   4588: bastore
      //   4589: dup
      //   4590: bipush 19
      //   4592: ldc_w 408
      //   4595: bastore
      //   4596: dup
      //   4597: bipush 20
      //   4599: ldc_w 414
      //   4602: bastore
      //   4603: dup
      //   4604: bipush 21
      //   4606: ldc_w 422
      //   4609: bastore
      //   4610: dup
      //   4611: bipush 22
      //   4613: ldc_w 423
      //   4616: bastore
      //   4617: dup
      //   4618: bipush 23
      //   4620: ldc_w 424
      //   4623: bastore
      //   4624: dup
      //   4625: bipush 24
      //   4627: ldc_w 408
      //   4630: bastore
      //   4631: dup
      //   4632: bipush 25
      //   4634: ldc_w 422
      //   4637: bastore
      //   4638: dup
      //   4639: bipush 26
      //   4641: ldc_w 418
      //   4644: bastore
      //   4645: dup
      //   4646: bipush 27
      //   4648: ldc_w 416
      //   4651: bastore
      //   4652: dup
      //   4653: bipush 28
      //   4655: ldc_w 425
      //   4658: bastore
      //   4659: dup
      //   4660: bipush 29
      //   4662: ldc_w 408
      //   4665: bastore
      //   4666: dup
      //   4667: bipush 30
      //   4669: ldc_w 417
      //   4672: bastore
      //   4673: dup
      //   4674: bipush 31
      //   4676: ldc_w 426
      //   4679: bastore
      //   4680: dup
      //   4681: bipush 32
      //   4683: ldc_w 427
      //   4686: bastore
      //   4687: dup
      //   4688: bipush 33
      //   4690: ldc_w 418
      //   4693: bastore
      //   4694: dup
      //   4695: bipush 34
      //   4697: ldc_w 413
      //   4700: bastore
      //   4701: dup
      //   4702: bipush 35
      //   4704: ldc_w 416
      //   4707: bastore
      //   4708: dup
      //   4709: bipush 36
      //   4711: ldc_w 423
      //   4714: bastore
      //   4715: dup
      //   4716: bipush 37
      //   4718: ldc_w 609
      //   4721: bastore
      //   4722: dup
      //   4723: bipush 38
      //   4725: ldc_w 430
      //   4728: bastore
      //   4729: aconst_null
      //   4730: aconst_null
      //   4731: bipush 127
      //   4733: invokestatic 432	o/CH$ˊ:ˎ	([B[I[CI)Ljava/lang/String;
      //   4736: invokevirtual 435	java/lang/String:intern	()Ljava/lang/String;
      //   4739: invokevirtual 203	java/lang/StringBuilder:append	(Ljava/lang/String;)Ljava/lang/StringBuilder;
      //   4742: aload 7
      //   4744: invokevirtual 438	java/lang/StringBuilder:append	(Ljava/lang/Object;)Ljava/lang/StringBuilder;
      //   4747: invokevirtual 213	java/lang/StringBuilder:toString	()Ljava/lang/String;
      //   4750: iconst_0
      //   4751: anewarray 5	java/lang/Object
      //   4754: invokespecial 191	o/CH$ˊ:ˏ	(ILjava/lang/String;[Ljava/lang/Object;)Ljava/lang/RuntimeException;
      //   4757: athrow
      //   4758: new 527	o/CA$ˎ
      //   4761: dup
      //   4762: aload 7
      //   4764: aload_0
      //   4765: getfield 104	o/CH$ˊ:ˊ	Lo/CI;
      //   4768: aload_2
      //   4769: aload_3
      //   4770: aload_0
      //   4771: getfield 114	o/CH$ˊ:ˎ	[Ljava/lang/annotation/Annotation;
      //   4774: invokevirtual 530	o/CI:ˋ	(Ljava/lang/reflect/Type;[Ljava/lang/annotation/Annotation;[Ljava/lang/annotation/Annotation;)Lo/Cy;
      //   4777: invokespecial 533	o/CA$ˎ:<init>	(Lo/xz;Lo/Cy;)V
      //   4780: invokevirtual 610	o/CA$ˎ:ˎ	()Lo/CA;
      //   4783: areturn
      // Local variable table:
      //   start	length	slot	name	signature
      //   0	4784	0	this	ˊ
      //   0	4784	1	paramInt	int
      //   0	4784	2	paramType	Type
      //   0	4784	3	paramArrayOfAnnotation	Annotation[]
      //   0	4784	4	paramAnnotation	Annotation
      //   106	4175	5	i	int
      //   43	4021	6	bool	boolean
      //   25	4738	7	localObject	Object
      //   1525	2260	8	localDn	Dn
      // Exception table:
      //   from	to	target	type
      //   3054	3068	2688	java/lang/RuntimeException
      //   2814	2819	3400	java/lang/Exception
      //   2819	2825	3400	java/lang/Exception
      //   2825	2831	3400	java/lang/Exception
      //   2831	2839	3400	java/lang/Exception
      //   2839	2850	3400	java/lang/Exception
      //   2850	2855	3400	java/lang/Exception
    }
    
    /* Error */
    private void ॱ(Annotation paramAnnotation)
    {
      // Byte code:
      //   0: goto +571 -> 571
      //   3: getstatic 60	o/CH$ˊ:ˋˊ	I
      //   6: bipush 49
      //   8: iadd
      //   9: istore_2
      //   10: iload_2
      //   11: sipush 128
      //   14: irem
      //   15: putstatic 62	o/CH$ˊ:ˊˊ	I
      //   18: iload_2
      //   19: iconst_2
      //   20: irem
      //   21: ifne +6 -> 27
      //   24: goto +44 -> 68
      //   27: aload_0
      //   28: ldc_w 614
      //   31: aload_1
      //   32: checkcast 616	o/Dl
      //   35: invokeinterface 617 1 0
      //   40: iconst_1
      //   41: invokespecial 619	o/CH$ˊ:ˏ	(Ljava/lang/String;Ljava/lang/String;Z)V
      //   44: goto +756 -> 800
      //   47: aload_1
      //   48: checkcast 621	o/Di
      //   51: invokeinterface 624 1 0
      //   56: astore_1
      //   57: aload_1
      //   58: arraylength
      //   59: ifne +6 -> 65
      //   62: goto +193 -> 255
      //   65: goto +145 -> 210
      //   68: goto -41 -> 27
      //   71: getstatic 60	o/CH$ˊ:ˋˊ	I
      //   74: bipush 65
      //   76: iadd
      //   77: istore_2
      //   78: iload_2
      //   79: sipush 128
      //   82: irem
      //   83: putstatic 62	o/CH$ˊ:ˊˊ	I
      //   86: iload_2
      //   87: iconst_2
      //   88: irem
      //   89: ifne +6 -> 95
      //   92: goto +11 -> 103
      //   95: goto +629 -> 724
      //   98: iconst_0
      //   99: istore_2
      //   100: goto +390 -> 490
      //   103: aload_0
      //   104: getfield 358	o/CH$ˊ:ॱˊ	Z
      //   107: istore_3
      //   108: bipush 44
      //   110: iconst_0
      //   111: idiv
      //   112: istore_2
      //   113: iload_3
      //   114: ifeq +6 -> 120
      //   117: goto +499 -> 616
      //   120: goto +58 -> 178
      //   123: iload_2
      //   124: tableswitch	default:+24->148, 0:+54->178, 1:+492->616
      //   148: goto +468 -> 616
      //   151: getstatic 62	o/CH$ˊ:ˊˊ	I
      //   154: bipush 81
      //   156: iadd
      //   157: istore_2
      //   158: iload_2
      //   159: sipush 128
      //   162: irem
      //   163: putstatic 60	o/CH$ˊ:ˋˊ	I
      //   166: iload_2
      //   167: iconst_2
      //   168: irem
      //   169: ifeq +6 -> 175
      //   172: goto +469 -> 641
      //   175: goto +529 -> 704
      //   178: aload_0
      //   179: iconst_1
      //   180: putfield 391	o/CH$ˊ:ʻॱ	Z
      //   183: goto +617 -> 800
      //   186: astore_1
      //   187: aload_1
      //   188: athrow
      //   189: aload_0
      //   190: iconst_1
      //   191: putfield 358	o/CH$ˊ:ॱˊ	Z
      //   194: goto +606 -> 800
      //   197: aload_1
      //   198: instanceof 616
      //   201: ifeq +6 -> 207
      //   204: goto -201 -> 3
      //   207: goto +203 -> 410
      //   210: aload_0
      //   211: aload_0
      //   212: aload_1
      //   213: invokespecial 626	o/CH$ˊ:ˊ	([Ljava/lang/String;)Lo/xz;
      //   216: putfield 628	o/CH$ˊ:ॱˋ	Lo/xz;
      //   219: goto +361 -> 580
      //   222: aload_0
      //   223: ldc_w 630
      //   226: aload_1
      //   227: checkcast 632	o/Dk
      //   230: invokeinterface 633 1 0
      //   235: iconst_1
      //   236: invokespecial 619	o/CH$ˊ:ˏ	(Ljava/lang/String;Ljava/lang/String;Z)V
      //   239: goto +561 -> 800
      //   242: aload_1
      //   243: instanceof 621
      //   246: ifeq +6 -> 252
      //   249: goto -202 -> 47
      //   252: goto +212 -> 464
      //   255: aload_0
      //   256: ldc_w 635
      //   259: iconst_0
      //   260: anewarray 5	java/lang/Object
      //   263: invokespecial 165	o/CH$ˊ:ˋ	(Ljava/lang/String;[Ljava/lang/Object;)Ljava/lang/RuntimeException;
      //   266: athrow
      //   267: aload_0
      //   268: ldc_w 637
      //   271: aload_1
      //   272: checkcast 639	o/CY
      //   275: invokeinterface 640 1 0
      //   280: iconst_0
      //   281: invokespecial 619	o/CH$ˊ:ˏ	(Ljava/lang/String;Ljava/lang/String;Z)V
      //   284: goto +516 -> 800
      //   287: aload_1
      //   288: instanceof 642
      //   291: ifeq +6 -> 297
      //   294: goto +260 -> 554
      //   297: goto -199 -> 98
      //   300: goto +500 -> 800
      //   303: getstatic 60	o/CH$ˊ:ˋˊ	I
      //   306: bipush 19
      //   308: iadd
      //   309: istore_2
      //   310: iload_2
      //   311: sipush 128
      //   314: irem
      //   315: putstatic 62	o/CH$ˊ:ˊˊ	I
      //   318: iload_2
      //   319: iconst_2
      //   320: irem
      //   321: ifne +6 -> 327
      //   324: goto +99 -> 423
      //   327: goto -60 -> 267
      //   330: iconst_1
      //   331: istore_2
      //   332: goto -209 -> 123
      //   335: iconst_1
      //   336: istore_2
      //   337: goto +89 -> 426
      //   340: iconst_0
      //   341: istore_2
      //   342: goto -219 -> 123
      //   345: goto +456 -> 801
      //   348: iconst_0
      //   349: istore_2
      //   350: goto +76 -> 426
      //   353: aload_1
      //   354: checkcast 644	o/Dd
      //   357: astore_1
      //   358: aload_0
      //   359: aload_1
      //   360: invokeinterface 646 1 0
      //   365: aload_1
      //   366: invokeinterface 647 1 0
      //   371: aload_1
      //   372: invokeinterface 648 1 0
      //   377: invokespecial 619	o/CH$ˊ:ˏ	(Ljava/lang/String;Ljava/lang/String;Z)V
      //   380: goto +420 -> 800
      //   383: getstatic 60	o/CH$ˊ:ˋˊ	I
      //   386: bipush 19
      //   388: iadd
      //   389: istore_2
      //   390: iload_2
      //   391: sipush 128
      //   394: irem
      //   395: putstatic 62	o/CH$ˊ:ˊˊ	I
      //   398: iload_2
      //   399: iconst_2
      //   400: irem
      //   401: ifne +6 -> 407
      //   404: goto -59 -> 345
      //   407: goto +394 -> 801
      //   410: aload_1
      //   411: instanceof 650
      //   414: ifeq +6 -> 420
      //   417: goto +350 -> 767
      //   420: goto +208 -> 628
      //   423: goto -156 -> 267
      //   426: iload_2
      //   427: tableswitch	default:+21->448, 0:+-230->197, 1:+-205->222
      //   448: goto -226 -> 222
      //   451: aload_1
      //   452: instanceof 652
      //   455: ifeq +6 -> 461
      //   458: goto +57 -> 515
      //   461: goto +142 -> 603
      //   464: aload_1
      //   465: instanceof 654
      //   468: ifeq +6 -> 474
      //   471: goto +103 -> 574
      //   474: goto +200 -> 674
      //   477: aload_1
      //   478: instanceof 639
      //   481: ifeq +6 -> 487
      //   484: goto -181 -> 303
      //   487: goto -200 -> 287
      //   490: iload_2
      //   491: tableswitch	default:+21->512, 0:+-40->451, 1:+92->583
      //   512: goto +71 -> 583
      //   515: aload_1
      //   516: checkcast 652	o/CZ
      //   519: astore_1
      //   520: aload_0
      //   521: ldc_w 656
      //   524: aload_1
      //   525: invokeinterface 657 1 0
      //   530: iconst_0
      //   531: invokespecial 619	o/CH$ˊ:ˏ	(Ljava/lang/String;Ljava/lang/String;Z)V
      //   534: ldc -25
      //   536: aload_0
      //   537: getfield 290	o/CH$ˊ:ʻ	Ljava/lang/reflect/Type;
      //   540: invokevirtual 658	java/lang/Object:equals	(Ljava/lang/Object;)Z
      //   543: istore_3
      //   544: iload_3
      //   545: ifne +6 -> 551
      //   548: goto +132 -> 680
      //   551: goto +249 -> 800
      //   554: iconst_1
      //   555: istore_2
      //   556: goto -66 -> 490
      //   559: aload_0
      //   560: ldc_w 660
      //   563: iconst_0
      //   564: anewarray 5	java/lang/Object
      //   567: invokespecial 165	o/CH$ˊ:ˋ	(Ljava/lang/String;[Ljava/lang/Object;)Ljava/lang/RuntimeException;
      //   570: athrow
      //   571: goto -94 -> 477
      //   574: bipush 22
      //   576: istore_2
      //   577: goto +160 -> 737
      //   580: goto +220 -> 800
      //   583: aload_0
      //   584: ldc_w 662
      //   587: aload_1
      //   588: checkcast 642	o/Dc
      //   591: invokeinterface 663 1 0
      //   596: iconst_0
      //   597: invokespecial 619	o/CH$ˊ:ˏ	(Ljava/lang/String;Ljava/lang/String;Z)V
      //   600: goto +200 -> 800
      //   603: aload_1
      //   604: instanceof 665
      //   607: ifeq +6 -> 613
      //   610: goto -459 -> 151
      //   613: goto +174 -> 787
      //   616: aload_0
      //   617: ldc_w 660
      //   620: iconst_0
      //   621: anewarray 5	java/lang/Object
      //   624: invokespecial 165	o/CH$ˊ:ˋ	(Ljava/lang/String;[Ljava/lang/Object;)Ljava/lang/RuntimeException;
      //   627: athrow
      //   628: aload_1
      //   629: instanceof 644
      //   632: ifeq +6 -> 638
      //   635: goto -282 -> 353
      //   638: goto -396 -> 242
      //   641: aload_0
      //   642: ldc_w 667
      //   645: aload_1
      //   646: checkcast 665	o/Dm
      //   649: invokeinterface 668 1 0
      //   654: iconst_0
      //   655: invokespecial 619	o/CH$ˊ:ˏ	(Ljava/lang/String;Ljava/lang/String;Z)V
      //   658: goto +142 -> 800
      //   661: aload_1
      //   662: instanceof 670
      //   665: ifeq +6 -> 671
      //   668: goto -285 -> 383
      //   671: goto +129 -> 800
      //   674: bipush 87
      //   676: istore_2
      //   677: goto +60 -> 737
      //   680: aload_0
      //   681: ldc_w 672
      //   684: iconst_0
      //   685: anewarray 5	java/lang/Object
      //   688: invokespecial 165	o/CH$ˊ:ˋ	(Ljava/lang/String;[Ljava/lang/Object;)Ljava/lang/RuntimeException;
      //   691: athrow
      //   692: aload_0
      //   693: ldc_w 660
      //   696: iconst_0
      //   697: anewarray 5	java/lang/Object
      //   700: invokespecial 165	o/CH$ˊ:ˋ	(Ljava/lang/String;[Ljava/lang/Object;)Ljava/lang/RuntimeException;
      //   703: athrow
      //   704: aload_0
      //   705: ldc_w 667
      //   708: aload_1
      //   709: checkcast 665	o/Dm
      //   712: invokeinterface 668 1 0
      //   717: iconst_1
      //   718: invokespecial 619	o/CH$ˊ:ˏ	(Ljava/lang/String;Ljava/lang/String;Z)V
      //   721: goto +79 -> 800
      //   724: aload_0
      //   725: getfield 358	o/CH$ˊ:ॱˊ	Z
      //   728: ifeq +6 -> 734
      //   731: goto -401 -> 330
      //   734: goto -394 -> 340
      //   737: iload_2
      //   738: lookupswitch	default:+26->764, 22:+-667->71, 87:+-77->661
      //   764: goto -103 -> 661
      //   767: aload_0
      //   768: ldc_w 674
      //   771: aload_1
      //   772: checkcast 650	o/Dh
      //   775: invokeinterface 675 1 0
      //   780: iconst_0
      //   781: invokespecial 619	o/CH$ˊ:ˏ	(Ljava/lang/String;Ljava/lang/String;Z)V
      //   784: goto -484 -> 300
      //   787: aload_1
      //   788: instanceof 632
      //   791: ifeq +6 -> 797
      //   794: goto -459 -> 335
      //   797: goto -449 -> 348
      //   800: return
      //   801: aload_0
      //   802: getfield 391	o/CH$ˊ:ʻॱ	Z
      //   805: ifeq +6 -> 811
      //   808: goto +6 -> 814
      //   811: goto -622 -> 189
      //   814: getstatic 62	o/CH$ˊ:ˊˊ	I
      //   817: bipush 97
      //   819: iadd
      //   820: istore_2
      //   821: iload_2
      //   822: sipush 128
      //   825: irem
      //   826: putstatic 60	o/CH$ˊ:ˋˊ	I
      //   829: iload_2
      //   830: iconst_2
      //   831: irem
      //   832: ifeq +6 -> 838
      //   835: goto -276 -> 559
      //   838: goto -146 -> 692
      // Local variable table:
      //   start	length	slot	name	signature
      //   0	841	0	this	ˊ
      //   0	841	1	paramAnnotation	Annotation
      //   9	823	2	i	int
      //   107	438	3	bool	boolean
      // Exception table:
      //   from	to	target	type
      //   515	520	186	java/lang/Exception
      //   520	534	186	java/lang/Exception
      //   534	544	186	java/lang/Exception
    }
    
    /* Error */
    public CH ˊ()
    {
      // Byte code:
      //   0: goto +131 -> 131
      //   3: aload_0
      //   4: getfield 358	o/CH$ˊ:ॱˊ	Z
      //   7: ifne +6 -> 13
      //   10: goto +791 -> 801
      //   13: goto +226 -> 239
      //   16: aload_0
      //   17: getfield 391	o/CH$ˊ:ʻॱ	Z
      //   20: ifeq +6 -> 26
      //   23: goto +265 -> 288
      //   26: goto +92 -> 118
      //   29: aload_0
      //   30: aload 5
      //   32: iload_1
      //   33: aaload
      //   34: invokespecial 678	o/CH$ˊ:ॱ	(Ljava/lang/annotation/Annotation;)V
      //   37: iload_1
      //   38: iconst_1
      //   39: iadd
      //   40: istore_1
      //   41: goto +888 -> 929
      //   44: iconst_1
      //   45: istore_1
      //   46: goto +812 -> 858
      //   49: iconst_1
      //   50: istore_1
      //   51: goto +422 -> 473
      //   54: bipush 60
      //   56: istore_1
      //   57: goto +106 -> 163
      //   60: bipush 52
      //   62: istore_1
      //   63: goto +71 -> 134
      //   66: aload_0
      //   67: ldc_w 680
      //   70: iconst_1
      //   71: anewarray 5	java/lang/Object
      //   74: invokespecial 165	o/CH$ˊ:ˋ	(Ljava/lang/String;[Ljava/lang/Object;)Ljava/lang/RuntimeException;
      //   77: athrow
      //   78: iload_1
      //   79: tableswitch	default:+21->100, 0:+735->814, 1:+272->351
      //   100: goto +251 -> 351
      //   103: bipush 16
      //   105: istore_1
      //   106: goto +28 -> 134
      //   109: goto +935 -> 1044
      //   112: bipush 95
      //   114: istore_2
      //   115: goto +185 -> 300
      //   118: aload_0
      //   119: getfield 358	o/CH$ˊ:ॱˊ	Z
      //   122: ifeq +6 -> 128
      //   125: goto +253 -> 378
      //   128: goto +129 -> 257
      //   131: goto +873 -> 1004
      //   134: iload_1
      //   135: lookupswitch	default:+25->160, 16:+547->682, 52:+104->239
      //   160: goto +79 -> 239
      //   163: iload_1
      //   164: lookupswitch	default:+28->192, 37:+-98->66, 60:+430->594
      //   192: goto -126 -> 66
      //   195: aload_0
      //   196: getfield 290	o/CH$ˊ:ʻ	Ljava/lang/reflect/Type;
      //   199: ldc_w 682
      //   202: if_acmpne +6 -> 208
      //   205: goto +609 -> 814
      //   208: goto +451 -> 659
      //   211: aload_0
      //   212: getfield 126	o/CH$ˊ:ˏ	[[Ljava/lang/annotation/Annotation;
      //   215: iload_1
      //   216: aaload
      //   217: astore 5
      //   219: aload 5
      //   221: ifnonnull +6 -> 227
      //   224: goto -112 -> 112
      //   227: goto +550 -> 777
      //   230: new 7	o/CH
      //   233: dup
      //   234: aload_0
      //   235: invokespecial 685	o/CH:<init>	(Lo/CH$ˊ;)V
      //   238: areturn
      //   239: aload_0
      //   240: getfield 358	o/CH$ˊ:ॱˊ	Z
      //   243: ifeq +6 -> 249
      //   246: goto +292 -> 538
      //   249: goto +485 -> 734
      //   252: iconst_0
      //   253: istore_1
      //   254: goto +604 -> 858
      //   257: aload_0
      //   258: getfield 126	o/CH$ˊ:ˏ	[[Ljava/lang/annotation/Annotation;
      //   261: arraylength
      //   262: istore_3
      //   263: aload_0
      //   264: iload_3
      //   265: anewarray 687	o/CA
      //   268: putfield 689	o/CH$ˊ:ʿ	[Lo/CA;
      //   271: iconst_0
      //   272: istore_1
      //   273: goto +297 -> 570
      //   276: aload_0
      //   277: ldc_w 691
      //   280: iconst_1
      //   281: anewarray 5	java/lang/Object
      //   284: invokespecial 165	o/CH$ˊ:ˋ	(Ljava/lang/String;[Ljava/lang/Object;)Ljava/lang/RuntimeException;
      //   287: athrow
      //   288: aload_0
      //   289: ldc_w 693
      //   292: iconst_0
      //   293: anewarray 5	java/lang/Object
      //   296: invokespecial 165	o/CH$ˊ:ˋ	(Ljava/lang/String;[Ljava/lang/Object;)Ljava/lang/RuntimeException;
      //   299: athrow
      //   300: iload_2
      //   301: lookupswitch	default:+27->328, 88:+250->551, 95:+225->526
      //   328: goto +223 -> 551
      //   331: aload_0
      //   332: ldc_w 695
      //   335: iconst_0
      //   336: anewarray 5	java/lang/Object
      //   339: invokespecial 165	o/CH$ˊ:ˋ	(Ljava/lang/String;[Ljava/lang/Object;)Ljava/lang/RuntimeException;
      //   342: athrow
      //   343: goto +404 -> 747
      //   346: astore 5
      //   348: aload 5
      //   350: athrow
      //   351: getstatic 62	o/CH$ˊ:ˊˊ	I
      //   354: bipush 65
      //   356: iadd
      //   357: istore_1
      //   358: iload_1
      //   359: sipush 128
      //   362: irem
      //   363: putstatic 60	o/CH$ˊ:ˋˊ	I
      //   366: iload_1
      //   367: iconst_2
      //   368: irem
      //   369: ifeq +6 -> 375
      //   372: goto +597 -> 969
      //   375: goto -180 -> 195
      //   378: aload_0
      //   379: ldc_w 697
      //   382: iconst_0
      //   383: anewarray 5	java/lang/Object
      //   386: invokespecial 165	o/CH$ˊ:ˋ	(Ljava/lang/String;[Ljava/lang/Object;)Ljava/lang/RuntimeException;
      //   389: athrow
      //   390: aload_0
      //   391: getfield 255	o/CH$ˊ:ᐝॱ	Ljava/lang/String;
      //   394: astore 5
      //   396: aload 5
      //   398: ifnonnull +6 -> 404
      //   401: goto +226 -> 627
      //   404: goto -401 -> 3
      //   407: aload_0
      //   408: getfield 397	o/CH$ˊ:ʽ	Z
      //   411: ifne +6 -> 417
      //   414: goto -83 -> 331
      //   417: goto -187 -> 230
      //   420: getstatic 60	o/CH$ˊ:ˋˊ	I
      //   423: bipush 121
      //   425: iadd
      //   426: istore_1
      //   427: iload_1
      //   428: sipush 128
      //   431: irem
      //   432: putstatic 62	o/CH$ˊ:ˊˊ	I
      //   435: iload_1
      //   436: iconst_2
      //   437: irem
      //   438: ifne +6 -> 444
      //   441: goto +499 -> 940
      //   444: goto -395 -> 49
      //   447: aload_0
      //   448: getfield 120	o/CH$ˊ:ॱ	[Ljava/lang/reflect/Type;
      //   451: iload_1
      //   452: aaload
      //   453: astore 6
      //   455: aload 6
      //   457: invokestatic 244	o/CM:ˋ	(Ljava/lang/reflect/Type;)Z
      //   460: istore 4
      //   462: iload 4
      //   464: ifeq +6 -> 470
      //   467: goto +316 -> 783
      //   470: goto -259 -> 211
      //   473: iload_1
      //   474: tableswitch	default:+22->496, 0:+-198->276, 1:+518->992
      //   496: goto +496 -> 992
      //   499: getstatic 60	o/CH$ˊ:ˋˊ	I
      //   502: bipush 55
      //   504: iadd
      //   505: istore_1
      //   506: iload_1
      //   507: sipush 128
      //   510: irem
      //   511: putstatic 62	o/CH$ˊ:ˊˊ	I
      //   514: iload_1
      //   515: iconst_2
      //   516: irem
      //   517: ifne +6 -> 523
      //   520: goto +91 -> 611
      //   523: goto +433 -> 956
      //   526: aload_0
      //   527: iload_1
      //   528: ldc -63
      //   530: iconst_0
      //   531: anewarray 5	java/lang/Object
      //   534: invokespecial 191	o/CH$ˊ:ˏ	(ILjava/lang/String;[Ljava/lang/Object;)Ljava/lang/RuntimeException;
      //   537: athrow
      //   538: aload_0
      //   539: getfield 351	o/CH$ˊ:ᐝ	Z
      //   542: ifne +6 -> 548
      //   545: goto -125 -> 420
      //   548: goto +186 -> 734
      //   551: aload_0
      //   552: getfield 689	o/CH$ˊ:ʿ	[Lo/CA;
      //   555: iload_1
      //   556: aload_0
      //   557: iload_1
      //   558: aload 6
      //   560: aload 5
      //   562: invokespecial 699	o/CH$ˊ:ˋ	(ILjava/lang/reflect/Type;[Ljava/lang/annotation/Annotation;)Lo/CA;
      //   565: aastore
      //   566: iload_1
      //   567: iconst_1
      //   568: iadd
      //   569: istore_1
      //   570: iload_1
      //   571: iload_3
      //   572: if_icmpge +6 -> 578
      //   575: goto -128 -> 447
      //   578: goto -188 -> 390
      //   581: aload_0
      //   582: getfield 301	o/CH$ˊ:ͺ	Z
      //   585: ifne +6 -> 591
      //   588: goto -572 -> 16
      //   591: goto -334 -> 257
      //   594: aload_0
      //   595: ldc_w 680
      //   598: iconst_0
      //   599: anewarray 5	java/lang/Object
      //   602: invokespecial 165	o/CH$ˊ:ˋ	(Ljava/lang/String;[Ljava/lang/Object;)Ljava/lang/RuntimeException;
      //   605: athrow
      //   606: astore 5
      //   608: aload 5
      //   610: athrow
      //   611: goto +345 -> 956
      //   614: aload_0
      //   615: getfield 393	o/CH$ˊ:ˊॱ	Z
      //   618: ifne +6 -> 624
      //   621: goto +289 -> 910
      //   624: goto -621 -> 3
      //   627: getstatic 62	o/CH$ˊ:ˊˊ	I
      //   630: bipush 111
      //   632: iadd
      //   633: istore_1
      //   634: iload_1
      //   635: sipush 128
      //   638: irem
      //   639: putstatic 60	o/CH$ˊ:ˋˊ	I
      //   642: iload_1
      //   643: iconst_2
      //   644: irem
      //   645: ifeq +6 -> 651
      //   648: goto +393 -> 1041
      //   651: goto -37 -> 614
      //   654: iconst_1
      //   655: istore_1
      //   656: goto -578 -> 78
      //   659: aload_0
      //   660: aload_0
      //   661: invokespecial 701	o/CH$ˊ:ˏ	()Lo/Cy;
      //   664: putfield 703	o/CH$ˊ:ˈ	Lo/Cy;
      //   667: aload_0
      //   668: getfield 114	o/CH$ˊ:ˎ	[Ljava/lang/annotation/Annotation;
      //   671: astore 5
      //   673: aload 5
      //   675: arraylength
      //   676: istore_2
      //   677: iconst_0
      //   678: istore_1
      //   679: goto +71 -> 750
      //   682: aload_0
      //   683: ldc_w 705
      //   686: iconst_0
      //   687: anewarray 5	java/lang/Object
      //   690: invokespecial 165	o/CH$ˊ:ˋ	(Ljava/lang/String;[Ljava/lang/Object;)Ljava/lang/RuntimeException;
      //   693: athrow
      //   694: getstatic 62	o/CH$ˊ:ˊˊ	I
      //   697: bipush 59
      //   699: iadd
      //   700: istore_1
      //   701: iload_1
      //   702: sipush 128
      //   705: irem
      //   706: putstatic 60	o/CH$ˊ:ˋˊ	I
      //   709: iload_1
      //   710: iconst_2
      //   711: irem
      //   712: ifeq +6 -> 718
      //   715: goto +235 -> 950
      //   718: goto -664 -> 54
      //   721: aload_0
      //   722: getfield 299	o/CH$ˊ:ˋॱ	Ljava/lang/String;
      //   725: ifnonnull +6 -> 731
      //   728: goto -34 -> 694
      //   731: goto -150 -> 581
      //   734: aload_0
      //   735: getfield 391	o/CH$ˊ:ʻॱ	Z
      //   738: ifeq +6 -> 744
      //   741: goto -334 -> 407
      //   744: goto -514 -> 230
      //   747: goto +182 -> 929
      //   750: getstatic 60	o/CH$ˊ:ˋˊ	I
      //   753: bipush 71
      //   755: iadd
      //   756: istore_3
      //   757: iload_3
      //   758: sipush 128
      //   761: irem
      //   762: putstatic 62	o/CH$ˊ:ˊˊ	I
      //   765: iload_3
      //   766: iconst_2
      //   767: irem
      //   768: ifne +6 -> 774
      //   771: goto -428 -> 343
      //   774: goto -27 -> 747
      //   777: bipush 88
      //   779: istore_2
      //   780: goto -480 -> 300
      //   783: aload_0
      //   784: iload_1
      //   785: ldc_w 707
      //   788: iconst_1
      //   789: anewarray 5	java/lang/Object
      //   792: dup
      //   793: iconst_0
      //   794: aload 6
      //   796: aastore
      //   797: invokespecial 191	o/CH$ˊ:ˏ	(ILjava/lang/String;[Ljava/lang/Object;)Ljava/lang/RuntimeException;
      //   800: athrow
      //   801: aload_0
      //   802: getfield 391	o/CH$ˊ:ʻॱ	Z
      //   805: ifne +6 -> 811
      //   808: goto -764 -> 44
      //   811: goto -559 -> 252
      //   814: aload_0
      //   815: new 198	java/lang/StringBuilder
      //   818: dup
      //   819: invokespecial 199	java/lang/StringBuilder:<init>	()V
      //   822: ldc_w 709
      //   825: invokevirtual 203	java/lang/StringBuilder:append	(Ljava/lang/String;)Ljava/lang/StringBuilder;
      //   828: aload_0
      //   829: getfield 290	o/CH$ˊ:ʻ	Ljava/lang/reflect/Type;
      //   832: invokestatic 354	o/CM:ˊ	(Ljava/lang/reflect/Type;)Ljava/lang/Class;
      //   835: invokevirtual 589	java/lang/Class:getName	()Ljava/lang/String;
      //   838: invokevirtual 203	java/lang/StringBuilder:append	(Ljava/lang/String;)Ljava/lang/StringBuilder;
      //   841: ldc_w 711
      //   844: invokevirtual 203	java/lang/StringBuilder:append	(Ljava/lang/String;)Ljava/lang/StringBuilder;
      //   847: invokevirtual 213	java/lang/StringBuilder:toString	()Ljava/lang/String;
      //   850: iconst_0
      //   851: anewarray 5	java/lang/Object
      //   854: invokespecial 165	o/CH$ˊ:ˋ	(Ljava/lang/String;[Ljava/lang/Object;)Ljava/lang/RuntimeException;
      //   857: athrow
      //   858: iload_1
      //   859: tableswitch	default:+21->880, 0:+-620->239, 1:+-360->499
      //   880: goto -381 -> 499
      //   883: getstatic 62	o/CH$ˊ:ˊˊ	I
      //   886: bipush 87
      //   888: iadd
      //   889: istore_1
      //   890: iload_1
      //   891: sipush 128
      //   894: irem
      //   895: putstatic 60	o/CH$ˊ:ˋˊ	I
      //   898: iload_1
      //   899: iconst_2
      //   900: irem
      //   901: ifeq +6 -> 907
      //   904: goto -795 -> 109
      //   907: goto +137 -> 1044
      //   910: aload_0
      //   911: ldc_w 713
      //   914: iconst_1
      //   915: anewarray 5	java/lang/Object
      //   918: dup
      //   919: iconst_0
      //   920: aload_0
      //   921: getfield 299	o/CH$ˊ:ˋॱ	Ljava/lang/String;
      //   924: aastore
      //   925: invokespecial 165	o/CH$ˊ:ˋ	(Ljava/lang/String;[Ljava/lang/Object;)Ljava/lang/RuntimeException;
      //   928: athrow
      //   929: iload_1
      //   930: iload_2
      //   931: if_icmpge +6 -> 937
      //   934: goto -905 -> 29
      //   937: goto -216 -> 721
      //   940: iconst_0
      //   941: istore_1
      //   942: goto -469 -> 473
      //   945: iconst_0
      //   946: istore_1
      //   947: goto -869 -> 78
      //   950: bipush 37
      //   952: istore_1
      //   953: goto -790 -> 163
      //   956: aload_0
      //   957: getfield 301	o/CH$ˊ:ͺ	Z
      //   960: ifne +6 -> 966
      //   963: goto -80 -> 883
      //   966: goto -727 -> 239
      //   969: aload_0
      //   970: getfield 290	o/CH$ˊ:ʻ	Ljava/lang/reflect/Type;
      //   973: astore 5
      //   975: aconst_null
      //   976: arraylength
      //   977: istore_1
      //   978: aload 5
      //   980: ldc_w 682
      //   983: if_acmpne +6 -> 989
      //   986: goto -172 -> 814
      //   989: goto -330 -> 659
      //   992: aload_0
      //   993: ldc_w 691
      //   996: iconst_0
      //   997: anewarray 5	java/lang/Object
      //   1000: invokespecial 165	o/CH$ˊ:ˋ	(Ljava/lang/String;[Ljava/lang/Object;)Ljava/lang/RuntimeException;
      //   1003: athrow
      //   1004: aload_0
      //   1005: aload_0
      //   1006: invokespecial 715	o/CH$ˊ:ˎ	()Lo/Cw;
      //   1009: putfield 717	o/CH$ˊ:ʽॱ	Lo/Cw;
      //   1012: aload_0
      //   1013: aload_0
      //   1014: getfield 717	o/CH$ˊ:ʽॱ	Lo/Cw;
      //   1017: invokeinterface 721 1 0
      //   1022: putfield 290	o/CH$ˊ:ʻ	Ljava/lang/reflect/Type;
      //   1025: aload_0
      //   1026: getfield 290	o/CH$ˊ:ʻ	Ljava/lang/reflect/Type;
      //   1029: ldc_w 723
      //   1032: if_acmpeq +6 -> 1038
      //   1035: goto -381 -> 654
      //   1038: goto -93 -> 945
      //   1041: goto -427 -> 614
      //   1044: aload_0
      //   1045: getfield 477	o/CH$ˊ:ॱॱ	Z
      //   1048: ifeq +6 -> 1054
      //   1051: goto -948 -> 103
      //   1054: goto -994 -> 60
      // Local variable table:
      //   start	length	slot	name	signature
      //   0	1057	0	this	ˊ
      //   32	946	1	i	int
      //   114	818	2	j	int
      //   262	506	3	k	int
      //   460	3	4	bool	boolean
      //   30	190	5	arrayOfAnnotation	Annotation[]
      //   346	3	5	localException1	Exception
      //   394	167	5	str	String
      //   606	3	5	localException2	Exception
      //   671	308	5	localObject	Object
      //   453	342	6	localType	Type
      // Exception table:
      //   from	to	target	type
      //   390	396	346	java/lang/Exception
      //   526	538	346	java/lang/Exception
      //   447	455	606	java/lang/Exception
      //   455	462	606	java/lang/Exception
    }
  }
}
