package o;

class cOn
  extends ˈ
{
  private static char[] ˊ = { -4293, -18183, 16560, -6059, -20450, 22568, -7774, -30328, 20806, -1675, -32458, 10989, -3443, -25951, 8808, -13805, -27691, 15233, -15430, 27477, 13072, -9015, 25828, 3244, -11184, 31745, 1059, -21018, 30124, 7444, 84, 22439, -20485, 1869, 24392, -18582, 3773, 26249, -16866, 5672, 28260, -14907, 7618, 30186, -13001, 9558, 31919, -11055, 11515, -31696, -9143, 13193, -29789, -7174, 15159, -27812, -5277, 17068, -25914, -3556, 18979, -23965, -1660, 20879, -22249, 318, 22844, -20350, 2260, 24831, -18375, 4171, 26527, -16479, 6074, 28483, -14496, 8036, 30387, -12550, 9735, 32331, -10647, 11711, -31344, -8871 };
  private static int ˋ;
  private static long ˎ;
  private static int ˏ = 0;
  
  static
  {
    ˋ = 1;
    ˎ = -7984775584119236657L;
  }
  
  public cOn() {}
  
  private static String ˋ(int paramInt1, int paramInt2, char paramChar)
  {
    break label182;
    int j;
    switch (j)
    {
    default: 
      break;
    }
    int i;
    Object localObject;
    for (;;)
    {
      if (i < paramInt1) {
        break label157;
      }
      break label176;
      j = ˏ + 57;
      ˋ = j % 128;
      if (j % 2 != 0) {
        break label89;
      }
      break label89;
      localObject = new String((char[])localObject);
      break;
      label89:
      localObject[i] = ((char)(int)(ˊ[(paramInt2 + i)] ^ i * ˎ ^ paramChar));
      i += 1;
    }
    label157:
    label176:
    label182:
    for (;;)
    {
      try
      {
        paramInt1 = ˏ + 53;
        try
        {
          ˋ = paramInt1 % 128;
          if (paramInt1 % 2 == 0) {
            continue;
          }
          return localObject;
        }
        catch (Exception localException1)
        {
          throw localException1;
        }
        localObject = new char[paramInt1];
        i = 0;
      }
      catch (Exception localException2)
      {
        throw localException2;
      }
      j = 0;
      break;
      return localException1;
      j = 1;
      break;
    }
  }
  
  /* Error */
  public android.databinding.ViewDataBinding ˊ(ˉ paramˉ, android.view.View[] paramArrayOfView, int paramInt)
  {
    // Byte code:
    //   0: goto +119 -> 119
    //   3: getstatic 15	o/cOn:ˏ	I
    //   6: istore_3
    //   7: iload_3
    //   8: bipush 69
    //   10: iadd
    //   11: istore_3
    //   12: iload_3
    //   13: sipush 128
    //   16: irem
    //   17: putstatic 17	o/cOn:ˋ	I
    //   20: iload_3
    //   21: iconst_2
    //   22: irem
    //   23: ifne +6 -> 29
    //   26: goto +73 -> 99
    //   29: iconst_0
    //   30: istore_3
    //   31: goto +91 -> 122
    //   34: bipush 30
    //   36: iconst_0
    //   37: idiv
    //   38: istore_3
    //   39: getstatic 15	o/cOn:ˏ	I
    //   42: bipush 49
    //   44: iadd
    //   45: istore_3
    //   46: iload_3
    //   47: sipush 128
    //   50: irem
    //   51: putstatic 17	o/cOn:ˋ	I
    //   54: iload_3
    //   55: iconst_2
    //   56: irem
    //   57: ifne +6 -> 63
    //   60: goto +44 -> 104
    //   63: goto +28 -> 91
    //   66: iload_3
    //   67: tableswitch	default:+21->88, 0:+42->109, 1:+50->117
    //   88: goto +21 -> 109
    //   91: iconst_1
    //   92: istore_3
    //   93: goto -27 -> 66
    //   96: goto -57 -> 39
    //   99: iconst_1
    //   100: istore_3
    //   101: goto +21 -> 122
    //   104: iconst_0
    //   105: istore_3
    //   106: goto -40 -> 66
    //   109: new 124	java/lang/NullPointerException
    //   112: dup
    //   113: invokespecial 125	java/lang/NullPointerException:<init>	()V
    //   116: athrow
    //   117: aconst_null
    //   118: areturn
    //   119: goto -116 -> 3
    //   122: iload_3
    //   123: tableswitch	default:+21->144, 0:+-27->96, 1:+-89->34
    //   144: goto -110 -> 34
    //   147: astore_1
    //   148: aload_1
    //   149: athrow
    // Local variable table:
    //   start	length	slot	name	signature
    //   0	150	0	this	cOn
    //   0	150	1	paramˉ	ˉ
    //   0	150	2	paramArrayOfView	android.view.View[]
    //   0	150	3	paramInt	int
    // Exception table:
    //   from	to	target	type
    //   3	7	147	java/lang/Exception
    //   12	20	147	java/lang/Exception
  }
  
  /* Error */
  public int ˋ(String paramString)
  {
    // Byte code:
    //   0: goto +558 -> 558
    //   3: iload_2
    //   4: tableswitch	default:+24->28, 0:+634->638, 1:+421->425
    //   28: goto +397 -> 425
    //   31: ldc 127
    //   33: ireturn
    //   34: aload_1
    //   35: ldc -127
    //   37: invokevirtual 133	java/lang/String:equals	(Ljava/lang/Object;)Z
    //   40: ifeq +6 -> 46
    //   43: goto +172 -> 215
    //   46: goto +592 -> 638
    //   49: aload_1
    //   50: ldc -121
    //   52: invokevirtual 133	java/lang/String:equals	(Ljava/lang/Object;)Z
    //   55: ifeq +6 -> 61
    //   58: goto +2402 -> 2460
    //   61: goto +577 -> 638
    //   64: ldc -120
    //   66: ireturn
    //   67: getstatic 17	o/cOn:ˋ	I
    //   70: bipush 37
    //   72: iadd
    //   73: istore_2
    //   74: iload_2
    //   75: sipush 128
    //   78: irem
    //   79: putstatic 15	o/cOn:ˏ	I
    //   82: iload_2
    //   83: iconst_2
    //   84: irem
    //   85: ifeq +6 -> 91
    //   88: goto +741 -> 829
    //   91: goto +2664 -> 2755
    //   94: aload_1
    //   95: ldc -118
    //   97: invokevirtual 133	java/lang/String:equals	(Ljava/lang/Object;)Z
    //   100: ifeq +6 -> 106
    //   103: goto +2302 -> 2405
    //   106: goto +532 -> 638
    //   109: ldc -117
    //   111: ireturn
    //   112: ldc -116
    //   114: ireturn
    //   115: aload_1
    //   116: ldc -114
    //   118: invokevirtual 133	java/lang/String:equals	(Ljava/lang/Object;)Z
    //   121: ifeq +6 -> 127
    //   124: goto +2984 -> 3108
    //   127: goto +511 -> 638
    //   130: iconst_0
    //   131: istore_2
    //   132: goto +530 -> 662
    //   135: ldc -113
    //   137: ireturn
    //   138: bipush 82
    //   140: istore_2
    //   141: goto +213 -> 354
    //   144: aload_1
    //   145: ldc -111
    //   147: invokevirtual 133	java/lang/String:equals	(Ljava/lang/Object;)Z
    //   150: ifeq +6 -> 156
    //   153: goto +1829 -> 1982
    //   156: goto +482 -> 638
    //   159: aload_1
    //   160: ldc -109
    //   162: invokevirtual 133	java/lang/String:equals	(Ljava/lang/Object;)Z
    //   165: ifeq +6 -> 171
    //   168: goto -101 -> 67
    //   171: goto +467 -> 638
    //   174: bipush 43
    //   176: istore_2
    //   177: goto +1746 -> 1923
    //   180: iconst_0
    //   181: ireturn
    //   182: ldc -108
    //   184: ireturn
    //   185: aload_1
    //   186: ldc -106
    //   188: invokevirtual 133	java/lang/String:equals	(Ljava/lang/Object;)Z
    //   191: ifeq +6 -> 197
    //   194: goto +125 -> 319
    //   197: goto +597 -> 794
    //   200: aload_1
    //   201: ldc -104
    //   203: invokevirtual 133	java/lang/String:equals	(Ljava/lang/Object;)Z
    //   206: ifeq +6 -> 212
    //   209: goto +582 -> 791
    //   212: goto +426 -> 638
    //   215: ldc -103
    //   217: ireturn
    //   218: aload_1
    //   219: ldc -101
    //   221: invokevirtual 133	java/lang/String:equals	(Ljava/lang/Object;)Z
    //   224: ifeq +6 -> 230
    //   227: goto +915 -> 1142
    //   230: goto +408 -> 638
    //   233: ldc -100
    //   235: ireturn
    //   236: iconst_1
    //   237: istore_2
    //   238: goto +1764 -> 2002
    //   241: aload_1
    //   242: ldc -98
    //   244: invokevirtual 133	java/lang/String:equals	(Ljava/lang/Object;)Z
    //   247: ifeq +6 -> 253
    //   250: goto +2159 -> 2409
    //   253: goto +385 -> 638
    //   256: aload_1
    //   257: ldc -96
    //   259: invokevirtual 133	java/lang/String:equals	(Ljava/lang/Object;)Z
    //   262: ifeq +6 -> 268
    //   265: goto +540 -> 805
    //   268: goto +370 -> 638
    //   271: aload_1
    //   272: ldc -94
    //   274: invokevirtual 133	java/lang/String:equals	(Ljava/lang/Object;)Z
    //   277: ifeq +6 -> 283
    //   280: goto +2361 -> 2641
    //   283: goto +355 -> 638
    //   286: aload_1
    //   287: ldc -92
    //   289: invokevirtual 133	java/lang/String:equals	(Ljava/lang/Object;)Z
    //   292: ifeq +6 -> 298
    //   295: goto +2647 -> 2942
    //   298: goto +340 -> 638
    //   301: ldc -91
    //   303: ireturn
    //   304: aload_1
    //   305: ldc -89
    //   307: invokevirtual 133	java/lang/String:equals	(Ljava/lang/Object;)Z
    //   310: ifeq +6 -> 316
    //   313: goto +1790 -> 2103
    //   316: goto +322 -> 638
    //   319: iconst_1
    //   320: istore_2
    //   321: goto +2518 -> 2839
    //   324: aload_1
    //   325: ldc -87
    //   327: invokevirtual 133	java/lang/String:equals	(Ljava/lang/Object;)Z
    //   330: ifeq +6 -> 336
    //   333: goto +2569 -> 2902
    //   336: goto +302 -> 638
    //   339: aload_1
    //   340: ldc -85
    //   342: invokevirtual 133	java/lang/String:equals	(Ljava/lang/Object;)Z
    //   345: ifeq +6 -> 351
    //   348: goto +582 -> 930
    //   351: goto +287 -> 638
    //   354: iload_2
    //   355: lookupswitch	default:+25->380, 70:+283->638, 82:+400->755
    //   380: goto +375 -> 755
    //   383: ldc -84
    //   385: ireturn
    //   386: aload_1
    //   387: ldc -82
    //   389: invokevirtual 133	java/lang/String:equals	(Ljava/lang/Object;)Z
    //   392: ifeq +6 -> 398
    //   395: goto +2678 -> 3073
    //   398: goto +240 -> 638
    //   401: goto +499 -> 900
    //   404: aload_1
    //   405: ldc -80
    //   407: invokevirtual 133	java/lang/String:equals	(Ljava/lang/Object;)Z
    //   410: ifeq +6 -> 416
    //   413: goto +1920 -> 2333
    //   416: goto +222 -> 638
    //   419: ldc -79
    //   421: ireturn
    //   422: ldc -78
    //   424: ireturn
    //   425: getstatic 17	o/cOn:ˋ	I
    //   428: bipush 33
    //   430: iadd
    //   431: istore_2
    //   432: iload_2
    //   433: sipush 128
    //   436: irem
    //   437: putstatic 15	o/cOn:ˏ	I
    //   440: iload_2
    //   441: iconst_2
    //   442: irem
    //   443: ifeq +6 -> 449
    //   446: goto +2437 -> 2883
    //   449: goto +174 -> 623
    //   452: ldc -77
    //   454: ireturn
    //   455: iload_2
    //   456: tableswitch	default:+24->480, 0:+182->638, 1:+105->561
    //   480: goto +158 -> 638
    //   483: aload_1
    //   484: ldc -75
    //   486: invokevirtual 133	java/lang/String:equals	(Ljava/lang/Object;)Z
    //   489: ifeq +6 -> 495
    //   492: goto +557 -> 1049
    //   495: goto +143 -> 638
    //   498: aload_1
    //   499: ldc -73
    //   501: invokevirtual 133	java/lang/String:equals	(Ljava/lang/Object;)Z
    //   504: ifeq +6 -> 510
    //   507: goto +2021 -> 2528
    //   510: goto +128 -> 638
    //   513: ldc -72
    //   515: ireturn
    //   516: getstatic 17	o/cOn:ˋ	I
    //   519: bipush 81
    //   521: iadd
    //   522: istore_2
    //   523: iload_2
    //   524: sipush 128
    //   527: irem
    //   528: putstatic 15	o/cOn:ˏ	I
    //   531: iload_2
    //   532: iconst_2
    //   533: irem
    //   534: ifeq +6 -> 540
    //   537: goto +498 -> 1035
    //   540: goto -121 -> 419
    //   543: aload_1
    //   544: ldc -70
    //   546: invokevirtual 133	java/lang/String:equals	(Ljava/lang/Object;)Z
    //   549: ifeq +6 -> 555
    //   552: goto +538 -> 1090
    //   555: goto +83 -> 638
    //   558: goto +1803 -> 2361
    //   561: ldc -69
    //   563: ireturn
    //   564: iconst_1
    //   565: istore_2
    //   566: goto -111 -> 455
    //   569: aload_1
    //   570: ldc -67
    //   572: invokevirtual 133	java/lang/String:equals	(Ljava/lang/Object;)Z
    //   575: ifeq +6 -> 581
    //   578: goto +1321 -> 1899
    //   581: goto +57 -> 638
    //   584: aload_1
    //   585: bipush 30
    //   587: iconst_0
    //   588: ldc -66
    //   590: invokestatic 192	o/cOn:ˋ	(IIC)Ljava/lang/String;
    //   593: invokevirtual 196	java/lang/String:intern	()Ljava/lang/String;
    //   596: invokevirtual 133	java/lang/String:equals	(Ljava/lang/Object;)Z
    //   599: ifeq +6 -> 605
    //   602: goto -369 -> 233
    //   605: goto +33 -> 638
    //   608: aload_1
    //   609: ldc -58
    //   611: invokevirtual 133	java/lang/String:equals	(Ljava/lang/Object;)Z
    //   614: ifeq +6 -> 620
    //   617: goto +1708 -> 2325
    //   620: goto +18 -> 638
    //   623: goto +1881 -> 2504
    //   626: aload_1
    //   627: ldc -56
    //   629: invokevirtual 133	java/lang/String:equals	(Ljava/lang/Object;)Z
    //   632: ifeq +6 -> 638
    //   635: goto +2493 -> 3128
    //   638: goto +2088 -> 2726
    //   641: ldc -55
    //   643: ireturn
    //   644: ldc -54
    //   646: ireturn
    //   647: aload_1
    //   648: ldc -52
    //   650: invokevirtual 133	java/lang/String:equals	(Ljava/lang/Object;)Z
    //   653: ifeq +6 -> 659
    //   656: goto -143 -> 513
    //   659: goto -21 -> 638
    //   662: iload_2
    //   663: tableswitch	default:+21->684, 0:+-481->182, 1:+-25->638
    //   684: goto -502 -> 182
    //   687: aload_1
    //   688: ldc -50
    //   690: invokevirtual 133	java/lang/String:equals	(Ljava/lang/Object;)Z
    //   693: ifeq +6 -> 699
    //   696: goto +1973 -> 2669
    //   699: goto -61 -> 638
    //   702: bipush 72
    //   704: iconst_0
    //   705: idiv
    //   706: istore_2
    //   707: ldc -49
    //   709: ireturn
    //   710: aload_1
    //   711: ldc -47
    //   713: invokevirtual 133	java/lang/String:equals	(Ljava/lang/Object;)Z
    //   716: ifeq +6 -> 722
    //   719: goto +1990 -> 2709
    //   722: goto -84 -> 638
    //   725: ldc -46
    //   727: ireturn
    //   728: aload_1
    //   729: ldc -44
    //   731: invokevirtual 133	java/lang/String:equals	(Ljava/lang/Object;)Z
    //   734: ifeq +6 -> 740
    //   737: goto +136 -> 873
    //   740: goto -102 -> 638
    //   743: astore_1
    //   744: aload_1
    //   745: athrow
    //   746: bipush 57
    //   748: istore_2
    //   749: goto +345 -> 1094
    //   752: ldc -43
    //   754: ireturn
    //   755: ldc -42
    //   757: ireturn
    //   758: aload_1
    //   759: ldc -40
    //   761: invokevirtual 133	java/lang/String:equals	(Ljava/lang/Object;)Z
    //   764: ifeq +6 -> 770
    //   767: goto -632 -> 135
    //   770: goto -132 -> 638
    //   773: ldc -39
    //   775: ireturn
    //   776: aload_1
    //   777: ldc -37
    //   779: invokevirtual 133	java/lang/String:equals	(Ljava/lang/Object;)Z
    //   782: ifeq +6 -> 788
    //   785: goto -363 -> 422
    //   788: goto -150 -> 638
    //   791: ldc -36
    //   793: ireturn
    //   794: iconst_0
    //   795: istore_2
    //   796: goto +2043 -> 2839
    //   799: bipush 75
    //   801: istore_2
    //   802: goto +1121 -> 1923
    //   805: ldc -35
    //   807: ireturn
    //   808: ldc -34
    //   810: ireturn
    //   811: aload_1
    //   812: ldc -32
    //   814: invokevirtual 133	java/lang/String:equals	(Ljava/lang/Object;)Z
    //   817: ifeq +6 -> 823
    //   820: goto +2257 -> 3077
    //   823: goto -185 -> 638
    //   826: ldc -31
    //   828: ireturn
    //   829: new 124	java/lang/NullPointerException
    //   832: dup
    //   833: invokespecial 125	java/lang/NullPointerException:<init>	()V
    //   836: athrow
    //   837: aload_1
    //   838: ldc -29
    //   840: invokevirtual 133	java/lang/String:equals	(Ljava/lang/Object;)Z
    //   843: ifeq +6 -> 849
    //   846: goto +2092 -> 2938
    //   849: goto -211 -> 638
    //   852: ldc -28
    //   854: ireturn
    //   855: aload_1
    //   856: ldc -26
    //   858: invokevirtual 133	java/lang/String:equals	(Ljava/lang/Object;)Z
    //   861: ifeq +6 -> 867
    //   864: goto +174 -> 1038
    //   867: goto -229 -> 638
    //   870: ldc -25
    //   872: ireturn
    //   873: getstatic 15	o/cOn:ˏ	I
    //   876: bipush 71
    //   878: iadd
    //   879: istore_2
    //   880: iload_2
    //   881: sipush 128
    //   884: irem
    //   885: putstatic 17	o/cOn:ˋ	I
    //   888: iload_2
    //   889: iconst_2
    //   890: irem
    //   891: ifne +6 -> 897
    //   894: goto +147 -> 1041
    //   897: goto +226 -> 1123
    //   900: ldc -24
    //   902: ireturn
    //   903: ldc -23
    //   905: ireturn
    //   906: aload_1
    //   907: ldc -21
    //   909: invokevirtual 133	java/lang/String:equals	(Ljava/lang/Object;)Z
    //   912: ifeq +6 -> 918
    //   915: goto +1806 -> 2721
    //   918: goto +167 -> 1085
    //   921: ldc -20
    //   923: ireturn
    //   924: ldc -19
    //   926: ireturn
    //   927: ldc -18
    //   929: ireturn
    //   930: ldc -17
    //   932: ireturn
    //   933: aload_1
    //   934: ldc -15
    //   936: invokevirtual 133	java/lang/String:equals	(Ljava/lang/Object;)Z
    //   939: ifeq +6 -> 945
    //   942: goto +1498 -> 2440
    //   945: goto -307 -> 638
    //   948: bipush 17
    //   950: istore_2
    //   951: goto +143 -> 1094
    //   954: aload_1
    //   955: ldc -13
    //   957: invokevirtual 133	java/lang/String:equals	(Ljava/lang/Object;)Z
    //   960: ifeq +6 -> 966
    //   963: goto +1754 -> 2717
    //   966: goto -328 -> 638
    //   969: ldc -12
    //   971: ireturn
    //   972: aload_1
    //   973: ldc -10
    //   975: invokevirtual 133	java/lang/String:equals	(Ljava/lang/Object;)Z
    //   978: ifeq +6 -> 984
    //   981: goto +974 -> 1955
    //   984: goto -346 -> 638
    //   987: ldc -9
    //   989: ireturn
    //   990: ldc -8
    //   992: ireturn
    //   993: getstatic 17	o/cOn:ˋ	I
    //   996: bipush 91
    //   998: iadd
    //   999: istore_2
    //   1000: iload_2
    //   1001: sipush 128
    //   1004: irem
    //   1005: putstatic 15	o/cOn:ˏ	I
    //   1008: iload_2
    //   1009: iconst_2
    //   1010: irem
    //   1011: ifeq +6 -> 1017
    //   1014: goto +1339 -> 2353
    //   1017: goto -634 -> 383
    //   1020: aload_1
    //   1021: ldc -6
    //   1023: invokevirtual 133	java/lang/String:equals	(Ljava/lang/Object;)Z
    //   1026: ifeq +6 -> 1032
    //   1029: goto -304 -> 725
    //   1032: goto -394 -> 638
    //   1035: goto -616 -> 419
    //   1038: ldc -5
    //   1040: ireturn
    //   1041: new 124	java/lang/NullPointerException
    //   1044: dup
    //   1045: invokespecial 125	java/lang/NullPointerException:<init>	()V
    //   1048: athrow
    //   1049: ldc -4
    //   1051: ireturn
    //   1052: aload_1
    //   1053: ldc -2
    //   1055: invokevirtual 133	java/lang/String:equals	(Ljava/lang/Object;)Z
    //   1058: ifeq +6 -> 1064
    //   1061: goto +1340 -> 2401
    //   1064: goto -426 -> 638
    //   1067: aload_1
    //   1068: ldc_w 256
    //   1071: invokevirtual 133	java/lang/String:equals	(Ljava/lang/Object;)Z
    //   1074: istore_3
    //   1075: iload_3
    //   1076: ifeq +6 -> 1082
    //   1079: goto +1586 -> 2665
    //   1082: goto -444 -> 638
    //   1085: iconst_0
    //   1086: istore_2
    //   1087: goto -1084 -> 3
    //   1090: ldc_w 257
    //   1093: ireturn
    //   1094: iload_2
    //   1095: lookupswitch	default:+25->1120, 17:+-457->638, 57:+1389->2484
    //   1120: goto +1364 -> 2484
    //   1123: goto -253 -> 870
    //   1126: aload_1
    //   1127: ldc_w 259
    //   1130: invokevirtual 133	java/lang/String:equals	(Ljava/lang/Object;)Z
    //   1133: ifeq +6 -> 1139
    //   1136: goto +2132 -> 3268
    //   1139: goto -501 -> 638
    //   1142: ldc_w 260
    //   1145: ireturn
    //   1146: aload_1
    //   1147: invokevirtual 264	java/lang/String:hashCode	()I
    //   1150: lookupswitch	default:+746->1896, -2057260279:+1262->2412, -1999665289:+1294->2444, -1989322699:+898->2048, -1978395800:+-542->608, -1934629801:+-607->543, -1913096341:+-826->324, -1774265581:+1982->3132, -1767251660:+1338->2488, -1742165942:+1159->2309, -1657496151:+1018->2168, -1644618493:+1107->2257, -1642052881:+-746->404, -1588481409:+1756->2906, -1524299307:+914->2064, -1488568577:+-83->1067, -1402474458:+1851->3001, -1374874056:+-244->906, -1156164891:+1539->2689, -1087385267:+-879->271, -1060470695:+1087->2237, -1043806555:+1221->2371, -1025820087:+1139->2289, -1022551640:+1398->2548, -980020387:+-98->1052, -959818756:+1414->2564, -945485594:+-196->954, -913061265:+1055->2205, -891362246:+-965->185, -849728457:+-503->647, -793060063:+1439->2589, -772355337:+-339->811, -724945712:+1471->2621, -714790332:+1523->2673, -573935549:+-440->710, -519601685:+997->2147, -481288134:+1123->2273, -463500017:+933->2083, -447650835:+1962->3112, -423086544:+-1116->34, -415786017:+1867->3017, -386250161:+981->2131, -381073663:+-811->339, -305732682:+1907->3057, -200389075:+-652->498, -163505992:+957->2107, -129333368:+1187->2337, -105522225:+-909->241, -69632055:+-422->728, -19359352:+1499->2649, -14952282:+1318->2468, 22457743:+-950->200, 42502202:+-846->304, 118507156:+-24->1126, 177868101:+-217->933, 232518378:+-1056->94, 257327738:+1071->2221, 355876960:+-894->256, 370684137:+757->1907, 405033457:+-1035->115, 460637623:+-991->159, 466859661:+2041->3191, 512642186:+-374->776, 521380460:+-463->687, 576565823:+-566->584, 589016449:+882->2032, 688348481:+1717->2867, 718516622:+-932->218, 727926501:+-178->972, 735100261:+1826->2976, 922427830:+1736->2886, 932361555:+-130->1020, 999069516:+-764->386, 1065045877:+1645->2795, 1183570349:+-1006->144, 1211632107:+1998->3148, 1285668364:+-864->286, 1483245418:+-524->626, 1614150908:+-313->837, 1685137356:+2057->3207, 1736094136:+1891->3041, 1757167196:+1772->2922, 1807358232:+-581->569, 1814340106:+1801->2951, 1856311604:+836->1986, 1896496964:+1382->2532, 1924201191:+1455->2605, 1996898690:+-392->758, 2001858965:+-1101->49, 2045048036:+-295->855, 2064288936:+1358->2508, 2076527228:+1037->2187, 2130188369:+-667->483
    //   1896: goto -1258 -> 638
    //   1899: ldc_w 265
    //   1902: ireturn
    //   1903: ldc_w 266
    //   1906: ireturn
    //   1907: aload_1
    //   1908: ldc_w 268
    //   1911: invokevirtual 133	java/lang/String:equals	(Ljava/lang/Object;)Z
    //   1914: ifeq +6 -> 1920
    //   1917: goto +470 -> 2387
    //   1920: goto -1282 -> 638
    //   1923: iload_2
    //   1924: lookupswitch	default:+28->1952, 43:+-1072->852, 75:+-1286->638
    //   1952: goto -1100 -> 852
    //   1955: getstatic 15	o/cOn:ˏ	I
    //   1958: bipush 23
    //   1960: iadd
    //   1961: istore_2
    //   1962: iload_2
    //   1963: sipush 128
    //   1966: irem
    //   1967: putstatic 17	o/cOn:ˋ	I
    //   1970: iload_2
    //   1971: iconst_2
    //   1972: irem
    //   1973: ifne +6 -> 1979
    //   1976: goto -1274 -> 702
    //   1979: goto +205 -> 2184
    //   1982: ldc_w 269
    //   1985: ireturn
    //   1986: aload_1
    //   1987: ldc_w 271
    //   1990: invokevirtual 133	java/lang/String:equals	(Ljava/lang/Object;)Z
    //   1993: ifeq +6 -> 1999
    //   1996: goto +1085 -> 3081
    //   1999: goto -1361 -> 638
    //   2002: iload_2
    //   2003: tableswitch	default:+21->2024, 0:+21->2024, 1:+-1365->638
    //   2024: ldc_w 272
    //   2027: ireturn
    //   2028: ldc_w 273
    //   2031: ireturn
    //   2032: aload_1
    //   2033: ldc_w 275
    //   2036: invokevirtual 133	java/lang/String:equals	(Ljava/lang/Object;)Z
    //   2039: ifeq +6 -> 2045
    //   2042: goto +422 -> 2464
    //   2045: goto -1407 -> 638
    //   2048: aload_1
    //   2049: ldc_w 277
    //   2052: invokevirtual 133	java/lang/String:equals	(Ljava/lang/Object;)Z
    //   2055: ifeq +6 -> 2061
    //   2058: goto -2027 -> 31
    //   2061: goto -1423 -> 638
    //   2064: aload_1
    //   2065: ldc_w 279
    //   2068: invokevirtual 133	java/lang/String:equals	(Ljava/lang/Object;)Z
    //   2071: ifeq +6 -> 2077
    //   2074: goto -1433 -> 641
    //   2077: goto -1439 -> 638
    //   2080: goto -1177 -> 903
    //   2083: aload_1
    //   2084: ldc_w 281
    //   2087: invokevirtual 133	java/lang/String:equals	(Ljava/lang/Object;)Z
    //   2090: ifeq +6 -> 2096
    //   2093: goto +487 -> 2580
    //   2096: goto -1860 -> 236
    //   2099: ldc_w 282
    //   2102: ireturn
    //   2103: ldc_w 283
    //   2106: ireturn
    //   2107: aload_1
    //   2108: ldc_w 285
    //   2111: invokevirtual 133	java/lang/String:equals	(Ljava/lang/Object;)Z
    //   2114: ifeq +6 -> 2120
    //   2117: goto -2008 -> 109
    //   2120: goto -1482 -> 638
    //   2123: ldc_w 286
    //   2126: ireturn
    //   2127: ldc_w 287
    //   2130: ireturn
    //   2131: aload_1
    //   2132: ldc_w 289
    //   2135: invokevirtual 133	java/lang/String:equals	(Ljava/lang/Object;)Z
    //   2138: ifeq +6 -> 2144
    //   2141: goto -1967 -> 174
    //   2144: goto -1345 -> 799
    //   2147: aload_1
    //   2148: ldc_w 291
    //   2151: invokevirtual 133	java/lang/String:equals	(Ljava/lang/Object;)Z
    //   2154: ifeq +6 -> 2160
    //   2157: goto +815 -> 2972
    //   2160: goto -1522 -> 638
    //   2163: iconst_1
    //   2164: istore_2
    //   2165: goto -1503 -> 662
    //   2168: aload_1
    //   2169: ldc_w 293
    //   2172: invokevirtual 133	java/lang/String:equals	(Ljava/lang/Object;)Z
    //   2175: ifeq +6 -> 2181
    //   2178: goto -1614 -> 564
    //   2181: goto +578 -> 2759
    //   2184: ldc -49
    //   2186: ireturn
    //   2187: aload_1
    //   2188: ldc_w 295
    //   2191: invokevirtual 133	java/lang/String:equals	(Ljava/lang/Object;)Z
    //   2194: istore_3
    //   2195: iload_3
    //   2196: ifeq +6 -> 2202
    //   2199: goto +1038 -> 3237
    //   2202: goto -1564 -> 638
    //   2205: aload_1
    //   2206: ldc_w 297
    //   2209: invokevirtual 133	java/lang/String:equals	(Ljava/lang/Object;)Z
    //   2212: ifeq +6 -> 2218
    //   2215: goto -2151 -> 64
    //   2218: goto -1580 -> 638
    //   2221: aload_1
    //   2222: ldc_w 299
    //   2225: invokevirtual 133	java/lang/String:equals	(Ljava/lang/Object;)Z
    //   2228: ifeq +6 -> 2234
    //   2231: goto -1244 -> 987
    //   2234: goto -1596 -> 638
    //   2237: aload_1
    //   2238: ldc_w 301
    //   2241: invokevirtual 133	java/lang/String:equals	(Ljava/lang/Object;)Z
    //   2244: ifeq +6 -> 2250
    //   2247: goto +976 -> 3223
    //   2250: goto +717 -> 2967
    //   2253: ldc_w 302
    //   2256: ireturn
    //   2257: aload_1
    //   2258: ldc_w 304
    //   2261: invokevirtual 133	java/lang/String:equals	(Ljava/lang/Object;)Z
    //   2264: ifeq +6 -> 2270
    //   2267: goto -1343 -> 924
    //   2270: goto -1632 -> 638
    //   2273: aload_1
    //   2274: ldc_w 306
    //   2277: invokevirtual 133	java/lang/String:equals	(Ljava/lang/Object;)Z
    //   2280: ifeq +6 -> 2286
    //   2283: goto -1982 -> 301
    //   2286: goto -1648 -> 638
    //   2289: aload_1
    //   2290: ldc_w 308
    //   2293: invokevirtual 133	java/lang/String:equals	(Ljava/lang/Object;)Z
    //   2296: ifeq +6 -> 2302
    //   2299: goto -1547 -> 752
    //   2302: goto -1664 -> 638
    //   2305: ldc_w 309
    //   2308: ireturn
    //   2309: aload_1
    //   2310: ldc_w 311
    //   2313: invokevirtual 133	java/lang/String:equals	(Ljava/lang/Object;)Z
    //   2316: ifeq +6 -> 2322
    //   2319: goto -1675 -> 644
    //   2322: goto -1684 -> 638
    //   2325: ldc_w 312
    //   2328: ireturn
    //   2329: ldc_w 313
    //   2332: ireturn
    //   2333: ldc_w 314
    //   2336: ireturn
    //   2337: aload_1
    //   2338: ldc_w 316
    //   2341: invokevirtual 133	java/lang/String:equals	(Ljava/lang/Object;)Z
    //   2344: ifeq +6 -> 2350
    //   2347: goto -1574 -> 773
    //   2350: goto -1712 -> 638
    //   2353: bipush 24
    //   2355: iconst_0
    //   2356: idiv
    //   2357: istore_2
    //   2358: ldc -84
    //   2360: ireturn
    //   2361: aload_1
    //   2362: ifnonnull +6 -> 2368
    //   2365: goto -2185 -> 180
    //   2368: goto -1222 -> 1146
    //   2371: aload_1
    //   2372: ldc_w 318
    //   2375: invokevirtual 133	java/lang/String:equals	(Ljava/lang/Object;)Z
    //   2378: ifeq +6 -> 2384
    //   2381: goto +143 -> 2524
    //   2384: goto -1746 -> 638
    //   2387: ldc_w 319
    //   2390: ireturn
    //   2391: bipush 70
    //   2393: istore_2
    //   2394: goto -2040 -> 354
    //   2397: ldc_w 320
    //   2400: ireturn
    //   2401: ldc_w 321
    //   2404: ireturn
    //   2405: ldc_w 322
    //   2408: ireturn
    //   2409: goto +824 -> 3233
    //   2412: aload_1
    //   2413: ldc_w 324
    //   2416: invokevirtual 133	java/lang/String:equals	(Ljava/lang/Object;)Z
    //   2419: ifeq +6 -> 2425
    //   2422: goto +10 -> 2432
    //   2425: goto -1787 -> 638
    //   2428: ldc_w 325
    //   2431: ireturn
    //   2432: ldc_w 326
    //   2435: ireturn
    //   2436: ldc_w 327
    //   2439: ireturn
    //   2440: ldc_w 328
    //   2443: ireturn
    //   2444: aload_1
    //   2445: ldc_w 330
    //   2448: invokevirtual 133	java/lang/String:equals	(Ljava/lang/Object;)Z
    //   2451: ifeq +6 -> 2457
    //   2454: goto +259 -> 2713
    //   2457: goto -1819 -> 638
    //   2460: ldc_w 331
    //   2463: ireturn
    //   2464: ldc_w 332
    //   2467: ireturn
    //   2468: aload_1
    //   2469: ldc_w 334
    //   2472: invokevirtual 133	java/lang/String:equals	(Ljava/lang/Object;)Z
    //   2475: ifeq +6 -> 2481
    //   2478: goto -1962 -> 516
    //   2481: goto -1843 -> 638
    //   2484: ldc_w 335
    //   2487: ireturn
    //   2488: aload_1
    //   2489: ldc_w 337
    //   2492: invokevirtual 133	java/lang/String:equals	(Ljava/lang/Object;)Z
    //   2495: ifeq +6 -> 2501
    //   2498: goto -1505 -> 993
    //   2501: goto -1863 -> 638
    //   2504: ldc_w 338
    //   2507: ireturn
    //   2508: aload_1
    //   2509: ldc_w 340
    //   2512: invokevirtual 133	java/lang/String:equals	(Ljava/lang/Object;)Z
    //   2515: ifeq +6 -> 2521
    //   2518: goto +273 -> 2791
    //   2521: goto -1883 -> 638
    //   2524: ldc_w 341
    //   2527: ireturn
    //   2528: ldc_w 342
    //   2531: ireturn
    //   2532: aload_1
    //   2533: ldc_w 344
    //   2536: invokevirtual 133	java/lang/String:equals	(Ljava/lang/Object;)Z
    //   2539: ifeq +6 -> 2545
    //   2542: goto -415 -> 2127
    //   2545: goto -1907 -> 638
    //   2548: aload_1
    //   2549: ldc_w 346
    //   2552: invokevirtual 133	java/lang/String:equals	(Ljava/lang/Object;)Z
    //   2555: ifeq +6 -> 2561
    //   2558: goto -2446 -> 112
    //   2561: goto -1923 -> 638
    //   2564: aload_1
    //   2565: ldc_w 348
    //   2568: invokevirtual 133	java/lang/String:equals	(Ljava/lang/Object;)Z
    //   2571: ifeq +6 -> 2577
    //   2574: goto +590 -> 3164
    //   2577: goto -1939 -> 638
    //   2580: iconst_0
    //   2581: istore_2
    //   2582: goto -580 -> 2002
    //   2585: ldc_w 349
    //   2588: ireturn
    //   2589: aload_1
    //   2590: ldc_w 351
    //   2593: invokevirtual 133	java/lang/String:equals	(Ljava/lang/Object;)Z
    //   2596: ifeq +6 -> 2602
    //   2599: goto -2461 -> 138
    //   2602: goto -211 -> 2391
    //   2605: aload_1
    //   2606: ldc_w 353
    //   2609: invokevirtual 133	java/lang/String:equals	(Ljava/lang/Object;)Z
    //   2612: ifeq +6 -> 2618
    //   2615: goto -492 -> 2123
    //   2618: goto -1980 -> 638
    //   2621: aload_1
    //   2622: ldc_w 355
    //   2625: invokevirtual 133	java/lang/String:equals	(Ljava/lang/Object;)Z
    //   2628: ifeq +6 -> 2634
    //   2631: goto +97 -> 2728
    //   2634: goto -1996 -> 638
    //   2637: ldc_w 356
    //   2640: ireturn
    //   2641: ldc_w 357
    //   2644: ireturn
    //   2645: ldc_w 358
    //   2648: ireturn
    //   2649: aload_1
    //   2650: ldc_w 360
    //   2653: invokevirtual 133	java/lang/String:equals	(Ljava/lang/Object;)Z
    //   2656: ifeq +6 -> 2662
    //   2659: goto -2207 -> 452
    //   2662: goto -2024 -> 638
    //   2665: ldc_w 361
    //   2668: ireturn
    //   2669: ldc_w 362
    //   2672: ireturn
    //   2673: aload_1
    //   2674: ldc_w 364
    //   2677: invokevirtual 133	java/lang/String:equals	(Ljava/lang/Object;)Z
    //   2680: ifeq +6 -> 2686
    //   2683: goto -1937 -> 746
    //   2686: goto -1738 -> 948
    //   2689: aload_1
    //   2690: ldc_w 366
    //   2693: invokevirtual 133	java/lang/String:equals	(Ljava/lang/Object;)Z
    //   2696: ifeq +6 -> 2702
    //   2699: goto -2569 -> 130
    //   2702: goto -539 -> 2163
    //   2705: ldc_w 367
    //   2708: ireturn
    //   2709: ldc_w 368
    //   2712: ireturn
    //   2713: ldc_w 369
    //   2716: ireturn
    //   2717: ldc_w 370
    //   2720: ireturn
    //   2721: iconst_1
    //   2722: istore_2
    //   2723: goto -2720 -> 3
    //   2726: iconst_0
    //   2727: ireturn
    //   2728: getstatic 17	o/cOn:ˋ	I
    //   2731: bipush 109
    //   2733: iadd
    //   2734: istore_2
    //   2735: iload_2
    //   2736: sipush 128
    //   2739: irem
    //   2740: putstatic 15	o/cOn:ˏ	I
    //   2743: iload_2
    //   2744: iconst_2
    //   2745: irem
    //   2746: ifeq +6 -> 2752
    //   2749: goto +243 -> 2992
    //   2752: goto -724 -> 2028
    //   2755: ldc_w 371
    //   2758: ireturn
    //   2759: iconst_0
    //   2760: istore_2
    //   2761: goto -2306 -> 455
    //   2764: iload_2
    //   2765: tableswitch	default:+23->2788, 0:+-2127->638, 1:+-60->2705
    //   2788: goto -2150 -> 638
    //   2791: ldc_w 372
    //   2794: ireturn
    //   2795: aload_1
    //   2796: ldc_w 374
    //   2799: invokevirtual 133	java/lang/String:equals	(Ljava/lang/Object;)Z
    //   2802: ifeq +6 -> 2808
    //   2805: goto +141 -> 2946
    //   2808: goto +420 -> 3228
    //   2811: iload_2
    //   2812: tableswitch	default:+24->2836, 0:+-2174->638, 1:+-415->2397
    //   2836: goto -439 -> 2397
    //   2839: iload_2
    //   2840: tableswitch	default:+24->2864, 0:+-2202->638, 1:+-1913->927
    //   2864: goto -1937 -> 927
    //   2867: aload_1
    //   2868: ldc_w 376
    //   2871: invokevirtual 133	java/lang/String:equals	(Ljava/lang/Object;)Z
    //   2874: ifeq +6 -> 2880
    //   2877: goto -548 -> 2329
    //   2880: goto -2242 -> 638
    //   2883: goto -2260 -> 623
    //   2886: aload_1
    //   2887: ldc_w 378
    //   2890: invokevirtual 133	java/lang/String:equals	(Ljava/lang/Object;)Z
    //   2893: ifeq +6 -> 2899
    //   2896: goto -591 -> 2305
    //   2899: goto -2261 -> 638
    //   2902: ldc_w 379
    //   2905: ireturn
    //   2906: aload_1
    //   2907: ldc_w 381
    //   2910: invokevirtual 133	java/lang/String:equals	(Ljava/lang/Object;)Z
    //   2913: ifeq +6 -> 2919
    //   2916: goto -1926 -> 990
    //   2919: goto -2281 -> 638
    //   2922: aload_1
    //   2923: ldc_w 383
    //   2926: invokevirtual 133	java/lang/String:equals	(Ljava/lang/Object;)Z
    //   2929: ifeq +6 -> 2935
    //   2932: goto -287 -> 2645
    //   2935: goto -2297 -> 638
    //   2938: ldc_w 384
    //   2941: ireturn
    //   2942: ldc_w 385
    //   2945: ireturn
    //   2946: iconst_1
    //   2947: istore_2
    //   2948: goto -184 -> 2764
    //   2951: aload_1
    //   2952: ldc_w 387
    //   2955: invokevirtual 133	java/lang/String:equals	(Ljava/lang/Object;)Z
    //   2958: ifeq +6 -> 2964
    //   2961: goto -324 -> 2637
    //   2964: goto -2326 -> 638
    //   2967: iconst_0
    //   2968: istore_2
    //   2969: goto -158 -> 2811
    //   2972: ldc_w 388
    //   2975: ireturn
    //   2976: aload_1
    //   2977: ldc_w 390
    //   2980: invokevirtual 133	java/lang/String:equals	(Ljava/lang/Object;)Z
    //   2983: ifeq +6 -> 2989
    //   2986: goto -2065 -> 921
    //   2989: goto -2351 -> 638
    //   2992: bipush 72
    //   2994: iconst_0
    //   2995: idiv
    //   2996: istore_2
    //   2997: ldc_w 273
    //   3000: ireturn
    //   3001: aload_1
    //   3002: ldc_w 392
    //   3005: invokevirtual 133	java/lang/String:equals	(Ljava/lang/Object;)Z
    //   3008: ifeq +6 -> 3014
    //   3011: goto -758 -> 2253
    //   3014: goto -2376 -> 638
    //   3017: aload_1
    //   3018: ldc_w 394
    //   3021: invokevirtual 133	java/lang/String:equals	(Ljava/lang/Object;)Z
    //   3024: ifeq +6 -> 3030
    //   3027: goto -1124 -> 1903
    //   3030: goto -2392 -> 638
    //   3033: new 124	java/lang/NullPointerException
    //   3036: dup
    //   3037: invokespecial 125	java/lang/NullPointerException:<init>	()V
    //   3040: athrow
    //   3041: aload_1
    //   3042: ldc_w 396
    //   3045: invokevirtual 133	java/lang/String:equals	(Ljava/lang/Object;)Z
    //   3048: ifeq +6 -> 3054
    //   3051: goto -466 -> 2585
    //   3054: goto -2416 -> 638
    //   3057: aload_1
    //   3058: ldc_w 398
    //   3061: invokevirtual 133	java/lang/String:equals	(Ljava/lang/Object;)Z
    //   3064: ifeq +6 -> 3070
    //   3067: goto -2241 -> 826
    //   3070: goto -2432 -> 638
    //   3073: ldc_w 399
    //   3076: ireturn
    //   3077: ldc_w 400
    //   3080: ireturn
    //   3081: getstatic 15	o/cOn:ˏ	I
    //   3084: bipush 71
    //   3086: iadd
    //   3087: istore_2
    //   3088: iload_2
    //   3089: sipush 128
    //   3092: irem
    //   3093: putstatic 17	o/cOn:ˋ	I
    //   3096: iload_2
    //   3097: iconst_2
    //   3098: irem
    //   3099: ifne +6 -> 3105
    //   3102: goto -1022 -> 2080
    //   3105: goto -2202 -> 903
    //   3108: ldc_w 401
    //   3111: ireturn
    //   3112: aload_1
    //   3113: ldc_w 403
    //   3116: invokevirtual 133	java/lang/String:equals	(Ljava/lang/Object;)Z
    //   3119: ifeq +6 -> 3125
    //   3122: goto -1023 -> 2099
    //   3125: goto -2487 -> 638
    //   3128: ldc_w 404
    //   3131: ireturn
    //   3132: aload_1
    //   3133: ldc_w 406
    //   3136: invokevirtual 133	java/lang/String:equals	(Ljava/lang/Object;)Z
    //   3139: ifeq +6 -> 3145
    //   3142: goto -2334 -> 808
    //   3145: goto -2507 -> 638
    //   3148: aload_1
    //   3149: ldc_w 408
    //   3152: invokevirtual 133	java/lang/String:equals	(Ljava/lang/Object;)Z
    //   3155: ifeq +6 -> 3161
    //   3158: goto +106 -> 3264
    //   3161: goto -2523 -> 638
    //   3164: getstatic 15	o/cOn:ˏ	I
    //   3167: bipush 61
    //   3169: iadd
    //   3170: istore_2
    //   3171: iload_2
    //   3172: sipush 128
    //   3175: irem
    //   3176: putstatic 17	o/cOn:ˋ	I
    //   3179: iload_2
    //   3180: iconst_2
    //   3181: irem
    //   3182: ifne +6 -> 3188
    //   3185: goto -2784 -> 401
    //   3188: goto -2288 -> 900
    //   3191: aload_1
    //   3192: ldc_w 410
    //   3195: invokevirtual 133	java/lang/String:equals	(Ljava/lang/Object;)Z
    //   3198: ifeq +6 -> 3204
    //   3201: goto -773 -> 2428
    //   3204: goto -2566 -> 638
    //   3207: aload_1
    //   3208: ldc_w 412
    //   3211: invokevirtual 133	java/lang/String:equals	(Ljava/lang/Object;)Z
    //   3214: ifeq +6 -> 3220
    //   3217: goto -781 -> 2436
    //   3220: goto -2582 -> 638
    //   3223: iconst_1
    //   3224: istore_2
    //   3225: goto -414 -> 2811
    //   3228: iconst_0
    //   3229: istore_2
    //   3230: goto -466 -> 2764
    //   3233: ldc_w 413
    //   3236: ireturn
    //   3237: getstatic 15	o/cOn:ˏ	I
    //   3240: bipush 21
    //   3242: iadd
    //   3243: istore_2
    //   3244: iload_2
    //   3245: sipush 128
    //   3248: irem
    //   3249: putstatic 17	o/cOn:ˋ	I
    //   3252: iload_2
    //   3253: iconst_2
    //   3254: irem
    //   3255: ifne +6 -> 3261
    //   3258: goto -225 -> 3033
    //   3261: goto -2292 -> 969
    //   3264: ldc_w 414
    //   3267: ireturn
    //   3268: ldc_w 415
    //   3271: ireturn
    // Local variable table:
    //   start	length	slot	name	signature
    //   0	3272	0	this	cOn
    //   0	3272	1	paramString	String
    //   3	3252	2	i	int
    //   1074	1122	3	bool	boolean
    // Exception table:
    //   from	to	target	type
    //   1067	1075	743	java/lang/Exception
    //   2187	2195	743	java/lang/Exception
  }
  
  /* Error */
  public android.databinding.ViewDataBinding ˏ(ˉ paramˉ, android.view.View paramView, int paramInt)
  {
    // Byte code:
    //   0: goto +5418 -> 5418
    //   3: new 418	java/lang/IllegalArgumentException
    //   6: dup
    //   7: new 420	java/lang/StringBuilder
    //   10: dup
    //   11: invokespecial 421	java/lang/StringBuilder:<init>	()V
    //   14: ldc_w 423
    //   17: invokevirtual 427	java/lang/StringBuilder:append	(Ljava/lang/String;)Ljava/lang/StringBuilder;
    //   20: aload 6
    //   22: invokevirtual 430	java/lang/StringBuilder:append	(Ljava/lang/Object;)Ljava/lang/StringBuilder;
    //   25: invokevirtual 433	java/lang/StringBuilder:toString	()Ljava/lang/String;
    //   28: invokespecial 436	java/lang/IllegalArgumentException:<init>	(Ljava/lang/String;)V
    //   31: athrow
    //   32: new 418	java/lang/IllegalArgumentException
    //   35: dup
    //   36: new 420	java/lang/StringBuilder
    //   39: dup
    //   40: invokespecial 421	java/lang/StringBuilder:<init>	()V
    //   43: ldc_w 438
    //   46: invokevirtual 427	java/lang/StringBuilder:append	(Ljava/lang/String;)Ljava/lang/StringBuilder;
    //   49: aload 6
    //   51: invokevirtual 430	java/lang/StringBuilder:append	(Ljava/lang/Object;)Ljava/lang/StringBuilder;
    //   54: invokevirtual 433	java/lang/StringBuilder:toString	()Ljava/lang/String;
    //   57: invokespecial 436	java/lang/IllegalArgumentException:<init>	(Ljava/lang/String;)V
    //   60: athrow
    //   61: aload_2
    //   62: invokevirtual 444	android/view/View:getTag	()Ljava/lang/Object;
    //   65: astore 6
    //   67: aload 6
    //   69: ifnonnull +6 -> 75
    //   72: goto +1550 -> 1622
    //   75: goto +6748 -> 6823
    //   78: new 446	java/lang/RuntimeException
    //   81: dup
    //   82: ldc_w 448
    //   85: invokespecial 449	java/lang/RuntimeException:<init>	(Ljava/lang/String;)V
    //   88: athrow
    //   89: new 451	o/DA
    //   92: dup
    //   93: aload_1
    //   94: aload_2
    //   95: invokespecial 454	o/DA:<init>	(Lo/ˉ;Landroid/view/View;)V
    //   98: areturn
    //   99: new 446	java/lang/RuntimeException
    //   102: dup
    //   103: ldc_w 448
    //   106: invokespecial 449	java/lang/RuntimeException:<init>	(Ljava/lang/String;)V
    //   109: athrow
    //   110: aload_2
    //   111: invokevirtual 444	android/view/View:getTag	()Ljava/lang/Object;
    //   114: astore 6
    //   116: aload 6
    //   118: ifnonnull +6 -> 124
    //   121: goto +7745 -> 7866
    //   124: goto +5297 -> 5421
    //   127: new 446	java/lang/RuntimeException
    //   130: dup
    //   131: ldc_w 448
    //   134: invokespecial 449	java/lang/RuntimeException:<init>	(Ljava/lang/String;)V
    //   137: athrow
    //   138: new 446	java/lang/RuntimeException
    //   141: dup
    //   142: ldc_w 448
    //   145: invokespecial 449	java/lang/RuntimeException:<init>	(Ljava/lang/String;)V
    //   148: athrow
    //   149: new 446	java/lang/RuntimeException
    //   152: dup
    //   153: ldc_w 448
    //   156: invokespecial 449	java/lang/RuntimeException:<init>	(Ljava/lang/String;)V
    //   159: athrow
    //   160: new 418	java/lang/IllegalArgumentException
    //   163: dup
    //   164: new 420	java/lang/StringBuilder
    //   167: dup
    //   168: invokespecial 421	java/lang/StringBuilder:<init>	()V
    //   171: ldc_w 456
    //   174: invokevirtual 427	java/lang/StringBuilder:append	(Ljava/lang/String;)Ljava/lang/StringBuilder;
    //   177: aload 6
    //   179: invokevirtual 430	java/lang/StringBuilder:append	(Ljava/lang/Object;)Ljava/lang/StringBuilder;
    //   182: invokevirtual 433	java/lang/StringBuilder:toString	()Ljava/lang/String;
    //   185: invokespecial 436	java/lang/IllegalArgumentException:<init>	(Ljava/lang/String;)V
    //   188: athrow
    //   189: ldc_w 387
    //   192: aload 6
    //   194: invokevirtual 133	java/lang/String:equals	(Ljava/lang/Object;)Z
    //   197: ifeq +6 -> 203
    //   200: goto +5483 -> 5683
    //   203: goto +6823 -> 7026
    //   206: new 458	o/Lr
    //   209: dup
    //   210: aload_1
    //   211: aload_2
    //   212: invokespecial 459	o/Lr:<init>	(Lo/ˉ;Landroid/view/View;)V
    //   215: areturn
    //   216: aload_2
    //   217: invokevirtual 444	android/view/View:getTag	()Ljava/lang/Object;
    //   220: astore 6
    //   222: aload 6
    //   224: ifnonnull +6 -> 230
    //   227: goto +8315 -> 8542
    //   230: goto +1082 -> 1312
    //   233: new 446	java/lang/RuntimeException
    //   236: dup
    //   237: ldc_w 448
    //   240: invokespecial 449	java/lang/RuntimeException:<init>	(Ljava/lang/String;)V
    //   243: athrow
    //   244: aload_2
    //   245: invokevirtual 444	android/view/View:getTag	()Ljava/lang/Object;
    //   248: astore 6
    //   250: aload 6
    //   252: ifnonnull +6 -> 258
    //   255: goto +4083 -> 4338
    //   258: goto +2327 -> 2585
    //   261: ldc_w 275
    //   264: aload 6
    //   266: invokevirtual 133	java/lang/String:equals	(Ljava/lang/Object;)Z
    //   269: ifeq +6 -> 275
    //   272: goto +1769 -> 2041
    //   275: goto +5428 -> 5703
    //   278: ldc -85
    //   280: aload 6
    //   282: invokevirtual 133	java/lang/String:equals	(Ljava/lang/Object;)Z
    //   285: ifeq +6 -> 291
    //   288: goto +5291 -> 5579
    //   291: goto +8113 -> 8404
    //   294: aload_2
    //   295: invokevirtual 444	android/view/View:getTag	()Ljava/lang/Object;
    //   298: astore 6
    //   300: aload 6
    //   302: ifnonnull +6 -> 308
    //   305: goto +2070 -> 2375
    //   308: goto +7918 -> 8226
    //   311: new 461	o/MA
    //   314: dup
    //   315: aload_1
    //   316: aload_2
    //   317: invokespecial 462	o/MA:<init>	(Lo/ˉ;Landroid/view/View;)V
    //   320: areturn
    //   321: new 464	o/JV
    //   324: dup
    //   325: aload_1
    //   326: aload_2
    //   327: invokespecial 465	o/JV:<init>	(Lo/ˉ;Landroid/view/View;)V
    //   330: areturn
    //   331: ldc_w 412
    //   334: aload 6
    //   336: invokevirtual 133	java/lang/String:equals	(Ljava/lang/Object;)Z
    //   339: ifeq +6 -> 345
    //   342: goto +1758 -> 2100
    //   345: goto +7946 -> 8291
    //   348: bipush 14
    //   350: istore_3
    //   351: goto +1415 -> 1766
    //   354: new 418	java/lang/IllegalArgumentException
    //   357: dup
    //   358: new 420	java/lang/StringBuilder
    //   361: dup
    //   362: invokespecial 421	java/lang/StringBuilder:<init>	()V
    //   365: ldc_w 467
    //   368: invokevirtual 427	java/lang/StringBuilder:append	(Ljava/lang/String;)Ljava/lang/StringBuilder;
    //   371: aload 6
    //   373: invokevirtual 430	java/lang/StringBuilder:append	(Ljava/lang/Object;)Ljava/lang/StringBuilder;
    //   376: invokevirtual 433	java/lang/StringBuilder:toString	()Ljava/lang/String;
    //   379: invokespecial 436	java/lang/IllegalArgumentException:<init>	(Ljava/lang/String;)V
    //   382: athrow
    //   383: new 446	java/lang/RuntimeException
    //   386: dup
    //   387: ldc_w 448
    //   390: invokespecial 449	java/lang/RuntimeException:<init>	(Ljava/lang/String;)V
    //   393: athrow
    //   394: new 418	java/lang/IllegalArgumentException
    //   397: dup
    //   398: new 420	java/lang/StringBuilder
    //   401: dup
    //   402: invokespecial 421	java/lang/StringBuilder:<init>	()V
    //   405: ldc_w 469
    //   408: invokevirtual 427	java/lang/StringBuilder:append	(Ljava/lang/String;)Ljava/lang/StringBuilder;
    //   411: aload 6
    //   413: invokevirtual 430	java/lang/StringBuilder:append	(Ljava/lang/Object;)Ljava/lang/StringBuilder;
    //   416: invokevirtual 433	java/lang/StringBuilder:toString	()Ljava/lang/String;
    //   419: invokespecial 436	java/lang/IllegalArgumentException:<init>	(Ljava/lang/String;)V
    //   422: athrow
    //   423: aload_2
    //   424: invokevirtual 444	android/view/View:getTag	()Ljava/lang/Object;
    //   427: astore 6
    //   429: aload 6
    //   431: ifnonnull +6 -> 437
    //   434: goto +477 -> 911
    //   437: goto +5968 -> 6405
    //   440: new 446	java/lang/RuntimeException
    //   443: dup
    //   444: ldc_w 448
    //   447: invokespecial 449	java/lang/RuntimeException:<init>	(Ljava/lang/String;)V
    //   450: athrow
    //   451: new 471	o/JL
    //   454: dup
    //   455: aload_1
    //   456: aload_2
    //   457: invokespecial 472	o/JL:<init>	(Lo/ˉ;Landroid/view/View;)V
    //   460: areturn
    //   461: aload_2
    //   462: invokevirtual 444	android/view/View:getTag	()Ljava/lang/Object;
    //   465: astore 6
    //   467: aload 6
    //   469: ifnonnull +6 -> 475
    //   472: goto +7522 -> 7994
    //   475: goto +5701 -> 6176
    //   478: new 446	java/lang/RuntimeException
    //   481: dup
    //   482: ldc_w 448
    //   485: invokespecial 449	java/lang/RuntimeException:<init>	(Ljava/lang/String;)V
    //   488: athrow
    //   489: ldc -98
    //   491: aload 6
    //   493: invokevirtual 133	java/lang/String:equals	(Ljava/lang/Object;)Z
    //   496: ifeq +6 -> 502
    //   499: goto +2489 -> 2988
    //   502: goto +1887 -> 2389
    //   505: new 474	o/LG
    //   508: dup
    //   509: aload_1
    //   510: aload_2
    //   511: invokespecial 475	o/LG:<init>	(Lo/ˉ;Landroid/view/View;)V
    //   514: areturn
    //   515: aload_2
    //   516: invokevirtual 444	android/view/View:getTag	()Ljava/lang/Object;
    //   519: astore 6
    //   521: aload 6
    //   523: ifnonnull +6 -> 529
    //   526: goto +7191 -> 7717
    //   529: goto +7802 -> 8331
    //   532: new 477	o/MT
    //   535: dup
    //   536: aload_1
    //   537: aload_2
    //   538: invokespecial 478	o/MT:<init>	(Lo/ˉ;Landroid/view/View;)V
    //   541: areturn
    //   542: new 480	o/Mt
    //   545: dup
    //   546: aload_1
    //   547: aload_2
    //   548: invokespecial 481	o/Mt:<init>	(Lo/ˉ;Landroid/view/View;)V
    //   551: areturn
    //   552: aload_2
    //   553: invokevirtual 444	android/view/View:getTag	()Ljava/lang/Object;
    //   556: astore 6
    //   558: aload 6
    //   560: ifnonnull +6 -> 566
    //   563: goto +7920 -> 8483
    //   566: goto +5476 -> 6042
    //   569: aload_2
    //   570: invokevirtual 444	android/view/View:getTag	()Ljava/lang/Object;
    //   573: astore 6
    //   575: aload 6
    //   577: ifnonnull +6 -> 583
    //   580: goto +4028 -> 4608
    //   583: goto +641 -> 1224
    //   586: ldc_w 364
    //   589: aload 6
    //   591: invokevirtual 133	java/lang/String:equals	(Ljava/lang/Object;)Z
    //   594: ifeq +6 -> 600
    //   597: goto -55 -> 542
    //   600: goto +1451 -> 2051
    //   603: new 418	java/lang/IllegalArgumentException
    //   606: dup
    //   607: new 420	java/lang/StringBuilder
    //   610: dup
    //   611: invokespecial 421	java/lang/StringBuilder:<init>	()V
    //   614: ldc_w 483
    //   617: invokevirtual 427	java/lang/StringBuilder:append	(Ljava/lang/String;)Ljava/lang/StringBuilder;
    //   620: aload 6
    //   622: invokevirtual 430	java/lang/StringBuilder:append	(Ljava/lang/Object;)Ljava/lang/StringBuilder;
    //   625: invokevirtual 433	java/lang/StringBuilder:toString	()Ljava/lang/String;
    //   628: invokespecial 436	java/lang/IllegalArgumentException:<init>	(Ljava/lang/String;)V
    //   631: athrow
    //   632: aload_2
    //   633: invokevirtual 444	android/view/View:getTag	()Ljava/lang/Object;
    //   636: astore 6
    //   638: aload 6
    //   640: ifnonnull +6 -> 646
    //   643: goto +421 -> 1064
    //   646: goto +1280 -> 1926
    //   649: new 418	java/lang/IllegalArgumentException
    //   652: dup
    //   653: new 420	java/lang/StringBuilder
    //   656: dup
    //   657: invokespecial 421	java/lang/StringBuilder:<init>	()V
    //   660: ldc_w 485
    //   663: invokevirtual 427	java/lang/StringBuilder:append	(Ljava/lang/String;)Ljava/lang/StringBuilder;
    //   666: aload 6
    //   668: invokevirtual 430	java/lang/StringBuilder:append	(Ljava/lang/Object;)Ljava/lang/StringBuilder;
    //   671: invokevirtual 433	java/lang/StringBuilder:toString	()Ljava/lang/String;
    //   674: invokespecial 436	java/lang/IllegalArgumentException:<init>	(Ljava/lang/String;)V
    //   677: athrow
    //   678: aload_2
    //   679: invokevirtual 444	android/view/View:getTag	()Ljava/lang/Object;
    //   682: astore 6
    //   684: aload 6
    //   686: ifnonnull +6 -> 692
    //   689: goto +107 -> 796
    //   692: goto +4763 -> 5455
    //   695: aload_2
    //   696: invokevirtual 444	android/view/View:getTag	()Ljava/lang/Object;
    //   699: astore 6
    //   701: aload 6
    //   703: ifnonnull +6 -> 709
    //   706: goto +5888 -> 6594
    //   709: goto +3954 -> 4663
    //   712: new 418	java/lang/IllegalArgumentException
    //   715: dup
    //   716: new 420	java/lang/StringBuilder
    //   719: dup
    //   720: invokespecial 421	java/lang/StringBuilder:<init>	()V
    //   723: ldc_w 487
    //   726: invokevirtual 427	java/lang/StringBuilder:append	(Ljava/lang/String;)Ljava/lang/StringBuilder;
    //   729: aload 6
    //   731: invokevirtual 430	java/lang/StringBuilder:append	(Ljava/lang/Object;)Ljava/lang/StringBuilder;
    //   734: invokevirtual 433	java/lang/StringBuilder:toString	()Ljava/lang/String;
    //   737: invokespecial 436	java/lang/IllegalArgumentException:<init>	(Ljava/lang/String;)V
    //   740: athrow
    //   741: aload_2
    //   742: invokevirtual 444	android/view/View:getTag	()Ljava/lang/Object;
    //   745: astore 6
    //   747: aload 6
    //   749: ifnonnull +6 -> 755
    //   752: goto +2256 -> 3008
    //   755: goto +917 -> 1672
    //   758: new 489	o/Ka
    //   761: dup
    //   762: aload_1
    //   763: aload_2
    //   764: invokespecial 490	o/Ka:<init>	(Lo/ˉ;Landroid/view/View;)V
    //   767: areturn
    //   768: aload_2
    //   769: invokevirtual 444	android/view/View:getTag	()Ljava/lang/Object;
    //   772: astore 6
    //   774: aload 6
    //   776: ifnonnull +6 -> 782
    //   779: goto +6711 -> 7490
    //   782: goto +940 -> 1722
    //   785: new 446	java/lang/RuntimeException
    //   788: dup
    //   789: ldc_w 448
    //   792: invokespecial 449	java/lang/RuntimeException:<init>	(Ljava/lang/String;)V
    //   795: athrow
    //   796: new 446	java/lang/RuntimeException
    //   799: dup
    //   800: ldc_w 448
    //   803: invokespecial 449	java/lang/RuntimeException:<init>	(Ljava/lang/String;)V
    //   806: athrow
    //   807: aload_2
    //   808: invokevirtual 444	android/view/View:getTag	()Ljava/lang/Object;
    //   811: astore 6
    //   813: aload 6
    //   815: ifnonnull +6 -> 821
    //   818: goto +3599 -> 4417
    //   821: goto +6109 -> 6930
    //   824: ldc -67
    //   826: aload 6
    //   828: invokevirtual 133	java/lang/String:equals	(Ljava/lang/Object;)Z
    //   831: ifeq +6 -> 837
    //   834: goto +635 -> 1469
    //   837: goto +1143 -> 1980
    //   840: new 446	java/lang/RuntimeException
    //   843: dup
    //   844: ldc_w 448
    //   847: invokespecial 449	java/lang/RuntimeException:<init>	(Ljava/lang/String;)V
    //   850: athrow
    //   851: new 418	java/lang/IllegalArgumentException
    //   854: dup
    //   855: new 420	java/lang/StringBuilder
    //   858: dup
    //   859: invokespecial 421	java/lang/StringBuilder:<init>	()V
    //   862: ldc_w 492
    //   865: invokevirtual 427	java/lang/StringBuilder:append	(Ljava/lang/String;)Ljava/lang/StringBuilder;
    //   868: aload 6
    //   870: invokevirtual 430	java/lang/StringBuilder:append	(Ljava/lang/Object;)Ljava/lang/StringBuilder;
    //   873: invokevirtual 433	java/lang/StringBuilder:toString	()Ljava/lang/String;
    //   876: invokespecial 436	java/lang/IllegalArgumentException:<init>	(Ljava/lang/String;)V
    //   879: athrow
    //   880: new 446	java/lang/RuntimeException
    //   883: dup
    //   884: ldc_w 448
    //   887: invokespecial 449	java/lang/RuntimeException:<init>	(Ljava/lang/String;)V
    //   890: athrow
    //   891: new 494	o/GR
    //   894: dup
    //   895: aload_1
    //   896: aload_2
    //   897: invokespecial 495	o/GR:<init>	(Lo/ˉ;Landroid/view/View;)V
    //   900: areturn
    //   901: new 497	o/MM
    //   904: dup
    //   905: aload_1
    //   906: aload_2
    //   907: invokespecial 498	o/MM:<init>	(Lo/ˉ;Landroid/view/View;)V
    //   910: areturn
    //   911: new 446	java/lang/RuntimeException
    //   914: dup
    //   915: ldc_w 448
    //   918: invokespecial 449	java/lang/RuntimeException:<init>	(Ljava/lang/String;)V
    //   921: athrow
    //   922: new 418	java/lang/IllegalArgumentException
    //   925: dup
    //   926: new 420	java/lang/StringBuilder
    //   929: dup
    //   930: invokespecial 421	java/lang/StringBuilder:<init>	()V
    //   933: ldc_w 500
    //   936: invokevirtual 427	java/lang/StringBuilder:append	(Ljava/lang/String;)Ljava/lang/StringBuilder;
    //   939: aload 6
    //   941: invokevirtual 430	java/lang/StringBuilder:append	(Ljava/lang/Object;)Ljava/lang/StringBuilder;
    //   944: invokevirtual 433	java/lang/StringBuilder:toString	()Ljava/lang/String;
    //   947: invokespecial 436	java/lang/IllegalArgumentException:<init>	(Ljava/lang/String;)V
    //   950: athrow
    //   951: new 446	java/lang/RuntimeException
    //   954: dup
    //   955: ldc_w 448
    //   958: invokespecial 449	java/lang/RuntimeException:<init>	(Ljava/lang/String;)V
    //   961: athrow
    //   962: new 502	o/JP
    //   965: dup
    //   966: aload_1
    //   967: aload_2
    //   968: invokespecial 503	o/JP:<init>	(Lo/ˉ;Landroid/view/View;)V
    //   971: areturn
    //   972: ldc -13
    //   974: aload 6
    //   976: invokevirtual 133	java/lang/String:equals	(Ljava/lang/Object;)Z
    //   979: ifeq +6 -> 985
    //   982: goto +6134 -> 7116
    //   985: goto +912 -> 1897
    //   988: iconst_1
    //   989: istore_3
    //   990: goto +776 -> 1766
    //   993: new 446	java/lang/RuntimeException
    //   996: dup
    //   997: ldc_w 448
    //   1000: invokespecial 449	java/lang/RuntimeException:<init>	(Ljava/lang/String;)V
    //   1003: athrow
    //   1004: ldc -82
    //   1006: aload 6
    //   1008: invokevirtual 133	java/lang/String:equals	(Ljava/lang/Object;)Z
    //   1011: ifeq +6 -> 1017
    //   1014: goto +4648 -> 5662
    //   1017: goto +2806 -> 3823
    //   1020: ldc -92
    //   1022: aload 6
    //   1024: invokevirtual 133	java/lang/String:equals	(Ljava/lang/Object;)Z
    //   1027: ifeq +6 -> 1033
    //   1030: goto +3298 -> 4328
    //   1033: goto +6293 -> 7326
    //   1036: new 446	java/lang/RuntimeException
    //   1039: dup
    //   1040: ldc_w 448
    //   1043: invokespecial 449	java/lang/RuntimeException:<init>	(Ljava/lang/String;)V
    //   1046: athrow
    //   1047: aload_2
    //   1048: invokevirtual 444	android/view/View:getTag	()Ljava/lang/Object;
    //   1051: astore 6
    //   1053: aload 6
    //   1055: ifnonnull +6 -> 1061
    //   1058: goto +4919 -> 5977
    //   1061: goto +5431 -> 6492
    //   1064: new 446	java/lang/RuntimeException
    //   1067: dup
    //   1068: ldc_w 448
    //   1071: invokespecial 449	java/lang/RuntimeException:<init>	(Ljava/lang/String;)V
    //   1074: athrow
    //   1075: aload_2
    //   1076: invokevirtual 444	android/view/View:getTag	()Ljava/lang/Object;
    //   1079: astore 6
    //   1081: aload 6
    //   1083: ifnonnull +6 -> 1089
    //   1086: goto +2783 -> 3869
    //   1089: goto -503 -> 586
    //   1092: new 418	java/lang/IllegalArgumentException
    //   1095: dup
    //   1096: new 420	java/lang/StringBuilder
    //   1099: dup
    //   1100: invokespecial 421	java/lang/StringBuilder:<init>	()V
    //   1103: ldc_w 505
    //   1106: invokevirtual 427	java/lang/StringBuilder:append	(Ljava/lang/String;)Ljava/lang/StringBuilder;
    //   1109: aload 6
    //   1111: invokevirtual 430	java/lang/StringBuilder:append	(Ljava/lang/Object;)Ljava/lang/StringBuilder;
    //   1114: invokevirtual 433	java/lang/StringBuilder:toString	()Ljava/lang/String;
    //   1117: invokespecial 436	java/lang/IllegalArgumentException:<init>	(Ljava/lang/String;)V
    //   1120: athrow
    //   1121: new 507	o/GM
    //   1124: dup
    //   1125: aload_1
    //   1126: aload_2
    //   1127: invokespecial 508	o/GM:<init>	(Lo/ˉ;Landroid/view/View;)V
    //   1130: areturn
    //   1131: new 446	java/lang/RuntimeException
    //   1134: dup
    //   1135: ldc_w 448
    //   1138: invokespecial 449	java/lang/RuntimeException:<init>	(Ljava/lang/String;)V
    //   1141: athrow
    //   1142: new 418	java/lang/IllegalArgumentException
    //   1145: dup
    //   1146: new 420	java/lang/StringBuilder
    //   1149: dup
    //   1150: invokespecial 421	java/lang/StringBuilder:<init>	()V
    //   1153: ldc_w 510
    //   1156: invokevirtual 427	java/lang/StringBuilder:append	(Ljava/lang/String;)Ljava/lang/StringBuilder;
    //   1159: aload 6
    //   1161: invokevirtual 430	java/lang/StringBuilder:append	(Ljava/lang/Object;)Ljava/lang/StringBuilder;
    //   1164: invokevirtual 433	java/lang/StringBuilder:toString	()Ljava/lang/String;
    //   1167: invokespecial 436	java/lang/IllegalArgumentException:<init>	(Ljava/lang/String;)V
    //   1170: athrow
    //   1171: new 512	o/GW
    //   1174: dup
    //   1175: aload_1
    //   1176: aload_2
    //   1177: invokespecial 513	o/GW:<init>	(Lo/ˉ;Landroid/view/View;)V
    //   1180: areturn
    //   1181: ldc -56
    //   1183: aload 6
    //   1185: invokevirtual 133	java/lang/String:equals	(Ljava/lang/Object;)Z
    //   1188: ifeq +6 -> 1194
    //   1191: goto +1088 -> 2279
    //   1194: goto +5097 -> 6291
    //   1197: ldc_w 295
    //   1200: aload 6
    //   1202: invokevirtual 133	java/lang/String:equals	(Ljava/lang/Object;)Z
    //   1205: ifeq +6 -> 1211
    //   1208: goto +4575 -> 5783
    //   1211: goto +1910 -> 3121
    //   1214: new 515	o/JR
    //   1217: dup
    //   1218: aload_1
    //   1219: aload_2
    //   1220: invokespecial 516	o/JR:<init>	(Lo/ˉ;Landroid/view/View;)V
    //   1223: areturn
    //   1224: ldc_w 355
    //   1227: aload 6
    //   1229: invokevirtual 133	java/lang/String:equals	(Ljava/lang/Object;)Z
    //   1232: ifeq +6 -> 1238
    //   1235: goto -344 -> 891
    //   1238: goto +13 -> 1251
    //   1241: new 518	o/LE
    //   1244: dup
    //   1245: aload_1
    //   1246: aload_2
    //   1247: invokespecial 519	o/LE:<init>	(Lo/ˉ;Landroid/view/View;)V
    //   1250: areturn
    //   1251: new 418	java/lang/IllegalArgumentException
    //   1254: dup
    //   1255: new 420	java/lang/StringBuilder
    //   1258: dup
    //   1259: invokespecial 421	java/lang/StringBuilder:<init>	()V
    //   1262: ldc_w 521
    //   1265: invokevirtual 427	java/lang/StringBuilder:append	(Ljava/lang/String;)Ljava/lang/StringBuilder;
    //   1268: aload 6
    //   1270: invokevirtual 430	java/lang/StringBuilder:append	(Ljava/lang/Object;)Ljava/lang/StringBuilder;
    //   1273: invokevirtual 433	java/lang/StringBuilder:toString	()Ljava/lang/String;
    //   1276: invokespecial 436	java/lang/IllegalArgumentException:<init>	(Ljava/lang/String;)V
    //   1279: athrow
    //   1280: new 446	java/lang/RuntimeException
    //   1283: dup
    //   1284: ldc_w 448
    //   1287: invokespecial 449	java/lang/RuntimeException:<init>	(Ljava/lang/String;)V
    //   1290: athrow
    //   1291: new 523	o/Kc
    //   1294: dup
    //   1295: aload_1
    //   1296: aload_2
    //   1297: invokespecial 524	o/Kc:<init>	(Lo/ˉ;Landroid/view/View;)V
    //   1300: areturn
    //   1301: new 446	java/lang/RuntimeException
    //   1304: dup
    //   1305: ldc_w 448
    //   1308: invokespecial 449	java/lang/RuntimeException:<init>	(Ljava/lang/String;)V
    //   1311: athrow
    //   1312: ldc_w 353
    //   1315: aload 6
    //   1317: invokevirtual 133	java/lang/String:equals	(Ljava/lang/Object;)Z
    //   1320: ifeq +6 -> 1326
    //   1323: goto -361 -> 962
    //   1326: goto -475 -> 851
    //   1329: new 418	java/lang/IllegalArgumentException
    //   1332: dup
    //   1333: new 420	java/lang/StringBuilder
    //   1336: dup
    //   1337: invokespecial 421	java/lang/StringBuilder:<init>	()V
    //   1340: ldc_w 526
    //   1343: invokevirtual 427	java/lang/StringBuilder:append	(Ljava/lang/String;)Ljava/lang/StringBuilder;
    //   1346: aload 6
    //   1348: invokevirtual 430	java/lang/StringBuilder:append	(Ljava/lang/Object;)Ljava/lang/StringBuilder;
    //   1351: invokevirtual 433	java/lang/StringBuilder:toString	()Ljava/lang/String;
    //   1354: invokespecial 436	java/lang/IllegalArgumentException:<init>	(Ljava/lang/String;)V
    //   1357: athrow
    //   1358: new 528	o/Mo
    //   1361: dup
    //   1362: aload_1
    //   1363: aload_2
    //   1364: invokespecial 529	o/Mo:<init>	(Lo/ˉ;Landroid/view/View;)V
    //   1367: areturn
    //   1368: new 418	java/lang/IllegalArgumentException
    //   1371: dup
    //   1372: new 420	java/lang/StringBuilder
    //   1375: dup
    //   1376: invokespecial 421	java/lang/StringBuilder:<init>	()V
    //   1379: ldc_w 531
    //   1382: invokevirtual 427	java/lang/StringBuilder:append	(Ljava/lang/String;)Ljava/lang/StringBuilder;
    //   1385: aload 6
    //   1387: invokevirtual 430	java/lang/StringBuilder:append	(Ljava/lang/Object;)Ljava/lang/StringBuilder;
    //   1390: invokevirtual 433	java/lang/StringBuilder:toString	()Ljava/lang/String;
    //   1393: invokespecial 436	java/lang/IllegalArgumentException:<init>	(Ljava/lang/String;)V
    //   1396: athrow
    //   1397: new 418	java/lang/IllegalArgumentException
    //   1400: dup
    //   1401: new 420	java/lang/StringBuilder
    //   1404: dup
    //   1405: invokespecial 421	java/lang/StringBuilder:<init>	()V
    //   1408: ldc_w 533
    //   1411: invokevirtual 427	java/lang/StringBuilder:append	(Ljava/lang/String;)Ljava/lang/StringBuilder;
    //   1414: aload 6
    //   1416: invokevirtual 430	java/lang/StringBuilder:append	(Ljava/lang/Object;)Ljava/lang/StringBuilder;
    //   1419: invokevirtual 433	java/lang/StringBuilder:toString	()Ljava/lang/String;
    //   1422: invokespecial 436	java/lang/IllegalArgumentException:<init>	(Ljava/lang/String;)V
    //   1425: athrow
    //   1426: ldc -2
    //   1428: aload 6
    //   1430: invokevirtual 133	java/lang/String:equals	(Ljava/lang/Object;)Z
    //   1433: ifeq +6 -> 1439
    //   1436: goto +644 -> 2080
    //   1439: goto +2345 -> 3784
    //   1442: aload_2
    //   1443: invokevirtual 444	android/view/View:getTag	()Ljava/lang/Object;
    //   1446: astore 6
    //   1448: aload 6
    //   1450: ifnonnull +6 -> 1456
    //   1453: goto -1354 -> 99
    //   1456: goto +5926 -> 7382
    //   1459: new 535	o/GY
    //   1462: dup
    //   1463: aload_1
    //   1464: aload_2
    //   1465: invokespecial 536	o/GY:<init>	(Lo/ˉ;Landroid/view/View;)V
    //   1468: areturn
    //   1469: new 538	o/LJ
    //   1472: dup
    //   1473: aload_1
    //   1474: aload_2
    //   1475: invokespecial 539	o/LJ:<init>	(Lo/ˉ;Landroid/view/View;)V
    //   1478: areturn
    //   1479: new 418	java/lang/IllegalArgumentException
    //   1482: dup
    //   1483: new 420	java/lang/StringBuilder
    //   1486: dup
    //   1487: invokespecial 421	java/lang/StringBuilder:<init>	()V
    //   1490: bipush 56
    //   1492: bipush 30
    //   1494: iconst_0
    //   1495: invokestatic 192	o/cOn:ˋ	(IIC)Ljava/lang/String;
    //   1498: invokevirtual 196	java/lang/String:intern	()Ljava/lang/String;
    //   1501: invokevirtual 427	java/lang/StringBuilder:append	(Ljava/lang/String;)Ljava/lang/StringBuilder;
    //   1504: aload 6
    //   1506: invokevirtual 430	java/lang/StringBuilder:append	(Ljava/lang/Object;)Ljava/lang/StringBuilder;
    //   1509: invokevirtual 433	java/lang/StringBuilder:toString	()Ljava/lang/String;
    //   1512: invokespecial 436	java/lang/IllegalArgumentException:<init>	(Ljava/lang/String;)V
    //   1515: athrow
    //   1516: new 418	java/lang/IllegalArgumentException
    //   1519: dup
    //   1520: new 420	java/lang/StringBuilder
    //   1523: dup
    //   1524: invokespecial 421	java/lang/StringBuilder:<init>	()V
    //   1527: ldc_w 541
    //   1530: invokevirtual 427	java/lang/StringBuilder:append	(Ljava/lang/String;)Ljava/lang/StringBuilder;
    //   1533: aload 6
    //   1535: invokevirtual 430	java/lang/StringBuilder:append	(Ljava/lang/Object;)Ljava/lang/StringBuilder;
    //   1538: invokevirtual 433	java/lang/StringBuilder:toString	()Ljava/lang/String;
    //   1541: invokespecial 436	java/lang/IllegalArgumentException:<init>	(Ljava/lang/String;)V
    //   1544: athrow
    //   1545: ldc_w 337
    //   1548: aload 6
    //   1550: invokevirtual 133	java/lang/String:equals	(Ljava/lang/Object;)Z
    //   1553: ifeq +6 -> 1559
    //   1556: goto +6095 -> 7651
    //   1559: goto -1165 -> 394
    //   1562: new 446	java/lang/RuntimeException
    //   1565: dup
    //   1566: ldc_w 448
    //   1569: invokespecial 449	java/lang/RuntimeException:<init>	(Ljava/lang/String;)V
    //   1572: athrow
    //   1573: new 446	java/lang/RuntimeException
    //   1576: dup
    //   1577: ldc_w 448
    //   1580: invokespecial 449	java/lang/RuntimeException:<init>	(Ljava/lang/String;)V
    //   1583: athrow
    //   1584: aload_2
    //   1585: invokevirtual 444	android/view/View:getTag	()Ljava/lang/Object;
    //   1588: astore 6
    //   1590: aload 6
    //   1592: ifnonnull +6 -> 1598
    //   1595: goto +5161 -> 6756
    //   1598: goto +1421 -> 3019
    //   1601: new 543	o/JE
    //   1604: dup
    //   1605: aload_1
    //   1606: aload_2
    //   1607: invokespecial 544	o/JE:<init>	(Lo/ˉ;Landroid/view/View;)V
    //   1610: areturn
    //   1611: new 446	java/lang/RuntimeException
    //   1614: dup
    //   1615: ldc_w 448
    //   1618: invokespecial 449	java/lang/RuntimeException:<init>	(Ljava/lang/String;)V
    //   1621: athrow
    //   1622: new 446	java/lang/RuntimeException
    //   1625: dup
    //   1626: ldc_w 448
    //   1629: invokespecial 449	java/lang/RuntimeException:<init>	(Ljava/lang/String;)V
    //   1632: athrow
    //   1633: new 546	o/My
    //   1636: dup
    //   1637: aload_1
    //   1638: aload_2
    //   1639: invokespecial 547	o/My:<init>	(Lo/ˉ;Landroid/view/View;)V
    //   1642: areturn
    //   1643: new 418	java/lang/IllegalArgumentException
    //   1646: dup
    //   1647: new 420	java/lang/StringBuilder
    //   1650: dup
    //   1651: invokespecial 421	java/lang/StringBuilder:<init>	()V
    //   1654: ldc_w 549
    //   1657: invokevirtual 427	java/lang/StringBuilder:append	(Ljava/lang/String;)Ljava/lang/StringBuilder;
    //   1660: aload 6
    //   1662: invokevirtual 430	java/lang/StringBuilder:append	(Ljava/lang/Object;)Ljava/lang/StringBuilder;
    //   1665: invokevirtual 433	java/lang/StringBuilder:toString	()Ljava/lang/String;
    //   1668: invokespecial 436	java/lang/IllegalArgumentException:<init>	(Ljava/lang/String;)V
    //   1671: athrow
    //   1672: ldc_w 346
    //   1675: aload 6
    //   1677: invokevirtual 133	java/lang/String:equals	(Ljava/lang/Object;)Z
    //   1680: ifeq +6 -> 1686
    //   1683: goto +5746 -> 7429
    //   1686: goto -1683 -> 3
    //   1689: ldc -50
    //   1691: aload 6
    //   1693: invokevirtual 133	java/lang/String:equals	(Ljava/lang/Object;)Z
    //   1696: ifeq +6 -> 1702
    //   1699: goto -1493 -> 206
    //   1702: goto +2455 -> 4157
    //   1705: aload_2
    //   1706: invokevirtual 444	android/view/View:getTag	()Ljava/lang/Object;
    //   1709: astore 6
    //   1711: aload 6
    //   1713: ifnonnull +6 -> 1719
    //   1716: goto -585 -> 1131
    //   1719: goto +1956 -> 3675
    //   1722: ldc -47
    //   1724: aload 6
    //   1726: invokevirtual 133	java/lang/String:equals	(Ljava/lang/Object;)Z
    //   1729: ifeq +6 -> 1735
    //   1732: goto +4225 -> 5957
    //   1735: goto +116 -> 1851
    //   1738: ldc_w 268
    //   1741: aload 6
    //   1743: invokevirtual 133	java/lang/String:equals	(Ljava/lang/Object;)Z
    //   1746: ifeq +6 -> 1752
    //   1749: goto +3944 -> 5693
    //   1752: goto +666 -> 2418
    //   1755: new 446	java/lang/RuntimeException
    //   1758: dup
    //   1759: ldc_w 448
    //   1762: invokespecial 449	java/lang/RuntimeException:<init>	(Ljava/lang/String;)V
    //   1765: athrow
    //   1766: iload_3
    //   1767: lookupswitch	default:+25->1792, 1:+1208->2975, 14:+252->2019
    //   1792: goto +227 -> 2019
    //   1795: new 418	java/lang/IllegalArgumentException
    //   1798: dup
    //   1799: new 420	java/lang/StringBuilder
    //   1802: dup
    //   1803: invokespecial 421	java/lang/StringBuilder:<init>	()V
    //   1806: ldc_w 551
    //   1809: invokevirtual 427	java/lang/StringBuilder:append	(Ljava/lang/String;)Ljava/lang/StringBuilder;
    //   1812: aload 6
    //   1814: invokevirtual 430	java/lang/StringBuilder:append	(Ljava/lang/Object;)Ljava/lang/StringBuilder;
    //   1817: invokevirtual 433	java/lang/StringBuilder:toString	()Ljava/lang/String;
    //   1820: invokespecial 436	java/lang/IllegalArgumentException:<init>	(Ljava/lang/String;)V
    //   1823: athrow
    //   1824: new 446	java/lang/RuntimeException
    //   1827: dup
    //   1828: ldc_w 448
    //   1831: invokespecial 449	java/lang/RuntimeException:<init>	(Ljava/lang/String;)V
    //   1834: athrow
    //   1835: ldc -6
    //   1837: aload 6
    //   1839: invokevirtual 133	java/lang/String:equals	(Ljava/lang/Object;)Z
    //   1842: ifeq +6 -> 1848
    //   1845: goto +4243 -> 6088
    //   1848: goto +5840 -> 7688
    //   1851: new 418	java/lang/IllegalArgumentException
    //   1854: dup
    //   1855: new 420	java/lang/StringBuilder
    //   1858: dup
    //   1859: invokespecial 421	java/lang/StringBuilder:<init>	()V
    //   1862: ldc_w 553
    //   1865: invokevirtual 427	java/lang/StringBuilder:append	(Ljava/lang/String;)Ljava/lang/StringBuilder;
    //   1868: aload 6
    //   1870: invokevirtual 430	java/lang/StringBuilder:append	(Ljava/lang/Object;)Ljava/lang/StringBuilder;
    //   1873: invokevirtual 433	java/lang/StringBuilder:toString	()Ljava/lang/String;
    //   1876: invokespecial 436	java/lang/IllegalArgumentException:<init>	(Ljava/lang/String;)V
    //   1879: athrow
    //   1880: aload_2
    //   1881: invokevirtual 444	android/view/View:getTag	()Ljava/lang/Object;
    //   1884: astore 6
    //   1886: aload 6
    //   1888: ifnonnull +6 -> 1894
    //   1891: goto +2115 -> 4006
    //   1894: goto +2326 -> 4220
    //   1897: new 418	java/lang/IllegalArgumentException
    //   1900: dup
    //   1901: new 420	java/lang/StringBuilder
    //   1904: dup
    //   1905: invokespecial 421	java/lang/StringBuilder:<init>	()V
    //   1908: ldc_w 555
    //   1911: invokevirtual 427	java/lang/StringBuilder:append	(Ljava/lang/String;)Ljava/lang/StringBuilder;
    //   1914: aload 6
    //   1916: invokevirtual 430	java/lang/StringBuilder:append	(Ljava/lang/Object;)Ljava/lang/StringBuilder;
    //   1919: invokevirtual 433	java/lang/StringBuilder:toString	()Ljava/lang/String;
    //   1922: invokespecial 436	java/lang/IllegalArgumentException:<init>	(Ljava/lang/String;)V
    //   1925: athrow
    //   1926: ldc -75
    //   1928: aload 6
    //   1930: invokevirtual 133	java/lang/String:equals	(Ljava/lang/Object;)Z
    //   1933: ifeq +6 -> 1939
    //   1936: goto +4573 -> 6509
    //   1939: goto +5348 -> 7287
    //   1942: new 557	o/JU
    //   1945: dup
    //   1946: aload_1
    //   1947: aload_2
    //   1948: invokespecial 558	o/JU:<init>	(Lo/ˉ;Landroid/view/View;)V
    //   1951: areturn
    //   1952: aload_2
    //   1953: invokevirtual 444	android/view/View:getTag	()Ljava/lang/Object;
    //   1956: astore 6
    //   1958: aload 6
    //   1960: ifnonnull +6 -> 1966
    //   1963: goto -1825 -> 138
    //   1966: goto +1742 -> 3708
    //   1969: new 446	java/lang/RuntimeException
    //   1972: dup
    //   1973: ldc_w 448
    //   1976: invokespecial 449	java/lang/RuntimeException:<init>	(Ljava/lang/String;)V
    //   1979: athrow
    //   1980: new 418	java/lang/IllegalArgumentException
    //   1983: dup
    //   1984: new 420	java/lang/StringBuilder
    //   1987: dup
    //   1988: invokespecial 421	java/lang/StringBuilder:<init>	()V
    //   1991: ldc_w 560
    //   1994: invokevirtual 427	java/lang/StringBuilder:append	(Ljava/lang/String;)Ljava/lang/StringBuilder;
    //   1997: aload 6
    //   1999: invokevirtual 430	java/lang/StringBuilder:append	(Ljava/lang/Object;)Ljava/lang/StringBuilder;
    //   2002: invokevirtual 433	java/lang/StringBuilder:toString	()Ljava/lang/String;
    //   2005: invokespecial 436	java/lang/IllegalArgumentException:<init>	(Ljava/lang/String;)V
    //   2008: athrow
    //   2009: new 562	o/GL
    //   2012: dup
    //   2013: aload_1
    //   2014: aload_2
    //   2015: invokespecial 563	o/GL:<init>	(Lo/ˉ;Landroid/view/View;)V
    //   2018: areturn
    //   2019: aconst_null
    //   2020: arraylength
    //   2021: istore_3
    //   2022: aload_1
    //   2023: areturn
    //   2024: aload_2
    //   2025: invokevirtual 444	android/view/View:getTag	()Ljava/lang/Object;
    //   2028: astore 6
    //   2030: aload 6
    //   2032: ifnonnull +6 -> 2038
    //   2035: goto +1424 -> 3459
    //   2038: goto +1330 -> 3368
    //   2041: new 565	o/JT
    //   2044: dup
    //   2045: aload_1
    //   2046: aload_2
    //   2047: invokespecial 566	o/JT:<init>	(Lo/ˉ;Landroid/view/View;)V
    //   2050: areturn
    //   2051: new 418	java/lang/IllegalArgumentException
    //   2054: dup
    //   2055: new 420	java/lang/StringBuilder
    //   2058: dup
    //   2059: invokespecial 421	java/lang/StringBuilder:<init>	()V
    //   2062: ldc_w 568
    //   2065: invokevirtual 427	java/lang/StringBuilder:append	(Ljava/lang/String;)Ljava/lang/StringBuilder;
    //   2068: aload 6
    //   2070: invokevirtual 430	java/lang/StringBuilder:append	(Ljava/lang/Object;)Ljava/lang/StringBuilder;
    //   2073: invokevirtual 433	java/lang/StringBuilder:toString	()Ljava/lang/String;
    //   2076: invokespecial 436	java/lang/IllegalArgumentException:<init>	(Ljava/lang/String;)V
    //   2079: athrow
    //   2080: new 570	o/MV
    //   2083: dup
    //   2084: aload_1
    //   2085: aload_2
    //   2086: invokespecial 571	o/MV:<init>	(Lo/ˉ;Landroid/view/View;)V
    //   2089: areturn
    //   2090: new 573	o/JN
    //   2093: dup
    //   2094: aload_1
    //   2095: aload_2
    //   2096: invokespecial 574	o/JN:<init>	(Lo/ˉ;Landroid/view/View;)V
    //   2099: areturn
    //   2100: new 576	o/LI
    //   2103: dup
    //   2104: aload_1
    //   2105: aload_2
    //   2106: invokespecial 577	o/LI:<init>	(Lo/ˉ;Landroid/view/View;)V
    //   2109: areturn
    //   2110: new 418	java/lang/IllegalArgumentException
    //   2113: dup
    //   2114: new 420	java/lang/StringBuilder
    //   2117: dup
    //   2118: invokespecial 421	java/lang/StringBuilder:<init>	()V
    //   2121: ldc_w 579
    //   2124: invokevirtual 427	java/lang/StringBuilder:append	(Ljava/lang/String;)Ljava/lang/StringBuilder;
    //   2127: aload 6
    //   2129: invokevirtual 430	java/lang/StringBuilder:append	(Ljava/lang/Object;)Ljava/lang/StringBuilder;
    //   2132: invokevirtual 433	java/lang/StringBuilder:toString	()Ljava/lang/String;
    //   2135: invokespecial 436	java/lang/IllegalArgumentException:<init>	(Ljava/lang/String;)V
    //   2138: athrow
    //   2139: new 418	java/lang/IllegalArgumentException
    //   2142: dup
    //   2143: new 420	java/lang/StringBuilder
    //   2146: dup
    //   2147: invokespecial 421	java/lang/StringBuilder:<init>	()V
    //   2150: ldc_w 581
    //   2153: invokevirtual 427	java/lang/StringBuilder:append	(Ljava/lang/String;)Ljava/lang/StringBuilder;
    //   2156: aload 6
    //   2158: invokevirtual 430	java/lang/StringBuilder:append	(Ljava/lang/Object;)Ljava/lang/StringBuilder;
    //   2161: invokevirtual 433	java/lang/StringBuilder:toString	()Ljava/lang/String;
    //   2164: invokespecial 436	java/lang/IllegalArgumentException:<init>	(Ljava/lang/String;)V
    //   2167: athrow
    //   2168: ldc -15
    //   2170: aload 6
    //   2172: invokevirtual 133	java/lang/String:equals	(Ljava/lang/Object;)Z
    //   2175: ifeq +6 -> 2181
    //   2178: goto +4589 -> 6767
    //   2181: goto +5712 -> 7893
    //   2184: new 446	java/lang/RuntimeException
    //   2187: dup
    //   2188: ldc_w 448
    //   2191: invokespecial 449	java/lang/RuntimeException:<init>	(Ljava/lang/String;)V
    //   2194: athrow
    //   2195: new 446	java/lang/RuntimeException
    //   2198: dup
    //   2199: ldc_w 448
    //   2202: invokespecial 449	java/lang/RuntimeException:<init>	(Ljava/lang/String;)V
    //   2205: athrow
    //   2206: aload_2
    //   2207: invokevirtual 444	android/view/View:getTag	()Ljava/lang/Object;
    //   2210: astore 6
    //   2212: aload 6
    //   2214: ifnonnull +6 -> 2220
    //   2217: goto +760 -> 2977
    //   2220: goto +1086 -> 3306
    //   2223: aload_2
    //   2224: invokevirtual 444	android/view/View:getTag	()Ljava/lang/Object;
    //   2227: astore 6
    //   2229: aload 6
    //   2231: ifnonnull +6 -> 2237
    //   2234: goto -265 -> 1969
    //   2237: goto -1233 -> 1004
    //   2240: new 446	java/lang/RuntimeException
    //   2243: dup
    //   2244: ldc_w 448
    //   2247: invokespecial 449	java/lang/RuntimeException:<init>	(Ljava/lang/String;)V
    //   2250: athrow
    //   2251: new 446	java/lang/RuntimeException
    //   2254: dup
    //   2255: ldc_w 448
    //   2258: invokespecial 449	java/lang/RuntimeException:<init>	(Ljava/lang/String;)V
    //   2261: athrow
    //   2262: aload_2
    //   2263: invokevirtual 444	android/view/View:getTag	()Ljava/lang/Object;
    //   2266: astore 6
    //   2268: aload 6
    //   2270: ifnonnull +6 -> 2276
    //   2273: goto +4703 -> 6976
    //   2276: goto +3327 -> 5603
    //   2279: new 583	o/Ln
    //   2282: dup
    //   2283: aload_1
    //   2284: aload_2
    //   2285: invokespecial 584	o/Ln:<init>	(Lo/ˉ;Landroid/view/View;)V
    //   2288: areturn
    //   2289: new 418	java/lang/IllegalArgumentException
    //   2292: dup
    //   2293: new 420	java/lang/StringBuilder
    //   2296: dup
    //   2297: invokespecial 421	java/lang/StringBuilder:<init>	()V
    //   2300: ldc_w 586
    //   2303: invokevirtual 427	java/lang/StringBuilder:append	(Ljava/lang/String;)Ljava/lang/StringBuilder;
    //   2306: aload 6
    //   2308: invokevirtual 430	java/lang/StringBuilder:append	(Ljava/lang/Object;)Ljava/lang/StringBuilder;
    //   2311: invokevirtual 433	java/lang/StringBuilder:toString	()Ljava/lang/String;
    //   2314: invokespecial 436	java/lang/IllegalArgumentException:<init>	(Ljava/lang/String;)V
    //   2317: athrow
    //   2318: ldc_w 394
    //   2321: aload 6
    //   2323: invokevirtual 133	java/lang/String:equals	(Ljava/lang/Object;)Z
    //   2326: ifeq +6 -> 2332
    //   2329: goto +3229 -> 5558
    //   2332: goto +1616 -> 3948
    //   2335: new 418	java/lang/IllegalArgumentException
    //   2338: dup
    //   2339: new 420	java/lang/StringBuilder
    //   2342: dup
    //   2343: invokespecial 421	java/lang/StringBuilder:<init>	()V
    //   2346: ldc_w 588
    //   2349: invokevirtual 427	java/lang/StringBuilder:append	(Ljava/lang/String;)Ljava/lang/StringBuilder;
    //   2352: aload 6
    //   2354: invokevirtual 430	java/lang/StringBuilder:append	(Ljava/lang/Object;)Ljava/lang/StringBuilder;
    //   2357: invokevirtual 433	java/lang/StringBuilder:toString	()Ljava/lang/String;
    //   2360: invokespecial 436	java/lang/IllegalArgumentException:<init>	(Ljava/lang/String;)V
    //   2363: athrow
    //   2364: new 446	java/lang/RuntimeException
    //   2367: dup
    //   2368: ldc_w 448
    //   2371: invokespecial 449	java/lang/RuntimeException:<init>	(Ljava/lang/String;)V
    //   2374: athrow
    //   2375: new 446	java/lang/RuntimeException
    //   2378: dup
    //   2379: ldc_w 448
    //   2382: invokespecial 449	java/lang/RuntimeException:<init>	(Ljava/lang/String;)V
    //   2385: athrow
    //   2386: astore_1
    //   2387: aload_1
    //   2388: athrow
    //   2389: new 418	java/lang/IllegalArgumentException
    //   2392: dup
    //   2393: new 420	java/lang/StringBuilder
    //   2396: dup
    //   2397: invokespecial 421	java/lang/StringBuilder:<init>	()V
    //   2400: ldc_w 590
    //   2403: invokevirtual 427	java/lang/StringBuilder:append	(Ljava/lang/String;)Ljava/lang/StringBuilder;
    //   2406: aload 6
    //   2408: invokevirtual 430	java/lang/StringBuilder:append	(Ljava/lang/Object;)Ljava/lang/StringBuilder;
    //   2411: invokevirtual 433	java/lang/StringBuilder:toString	()Ljava/lang/String;
    //   2414: invokespecial 436	java/lang/IllegalArgumentException:<init>	(Ljava/lang/String;)V
    //   2417: athrow
    //   2418: new 418	java/lang/IllegalArgumentException
    //   2421: dup
    //   2422: new 420	java/lang/StringBuilder
    //   2425: dup
    //   2426: invokespecial 421	java/lang/StringBuilder:<init>	()V
    //   2429: ldc_w 592
    //   2432: invokevirtual 427	java/lang/StringBuilder:append	(Ljava/lang/String;)Ljava/lang/StringBuilder;
    //   2435: aload 6
    //   2437: invokevirtual 430	java/lang/StringBuilder:append	(Ljava/lang/Object;)Ljava/lang/StringBuilder;
    //   2440: invokevirtual 433	java/lang/StringBuilder:toString	()Ljava/lang/String;
    //   2443: invokespecial 436	java/lang/IllegalArgumentException:<init>	(Ljava/lang/String;)V
    //   2446: athrow
    //   2447: aload_2
    //   2448: invokevirtual 444	android/view/View:getTag	()Ljava/lang/Object;
    //   2451: astore 6
    //   2453: aload 6
    //   2455: ifnonnull +6 -> 2461
    //   2458: goto -2309 -> 149
    //   2461: goto -723 -> 1738
    //   2464: aload_2
    //   2465: invokevirtual 444	android/view/View:getTag	()Ljava/lang/Object;
    //   2468: astore 6
    //   2470: aload 6
    //   2472: ifnonnull +6 -> 2478
    //   2475: goto -2242 -> 233
    //   2478: goto -1458 -> 1020
    //   2481: ldc_w 348
    //   2484: aload 6
    //   2486: invokevirtual 133	java/lang/String:equals	(Ljava/lang/Object;)Z
    //   2489: ifeq +6 -> 2495
    //   2492: goto -2181 -> 311
    //   2495: goto +34 -> 2529
    //   2498: new 446	java/lang/RuntimeException
    //   2501: dup
    //   2502: ldc_w 448
    //   2505: invokespecial 449	java/lang/RuntimeException:<init>	(Ljava/lang/String;)V
    //   2508: athrow
    //   2509: new 594	o/Jo
    //   2512: dup
    //   2513: aload_1
    //   2514: aload_2
    //   2515: invokespecial 595	o/Jo:<init>	(Lo/ˉ;Landroid/view/View;)V
    //   2518: areturn
    //   2519: new 597	o/Dy
    //   2522: dup
    //   2523: aload_1
    //   2524: aload_2
    //   2525: invokespecial 598	o/Dy:<init>	(Lo/ˉ;Landroid/view/View;)V
    //   2528: areturn
    //   2529: new 418	java/lang/IllegalArgumentException
    //   2532: dup
    //   2533: new 420	java/lang/StringBuilder
    //   2536: dup
    //   2537: invokespecial 421	java/lang/StringBuilder:<init>	()V
    //   2540: ldc_w 600
    //   2543: invokevirtual 427	java/lang/StringBuilder:append	(Ljava/lang/String;)Ljava/lang/StringBuilder;
    //   2546: aload 6
    //   2548: invokevirtual 430	java/lang/StringBuilder:append	(Ljava/lang/Object;)Ljava/lang/StringBuilder;
    //   2551: invokevirtual 433	java/lang/StringBuilder:toString	()Ljava/lang/String;
    //   2554: invokespecial 436	java/lang/IllegalArgumentException:<init>	(Ljava/lang/String;)V
    //   2557: athrow
    //   2558: new 602	o/GZ
    //   2561: dup
    //   2562: aload_1
    //   2563: aload_2
    //   2564: invokespecial 603	o/GZ:<init>	(Lo/ˉ;Landroid/view/View;)V
    //   2567: areturn
    //   2568: aload_2
    //   2569: invokevirtual 444	android/view/View:getTag	()Ljava/lang/Object;
    //   2572: astore 6
    //   2574: aload 6
    //   2576: ifnonnull +6 -> 2582
    //   2579: goto +3902 -> 6481
    //   2582: goto +860 -> 3442
    //   2585: ldc -10
    //   2587: aload 6
    //   2589: invokevirtual 133	java/lang/String:equals	(Ljava/lang/Object;)Z
    //   2592: ifeq +6 -> 2598
    //   2595: goto +1502 -> 4097
    //   2598: goto -459 -> 2139
    //   2601: new 418	java/lang/IllegalArgumentException
    //   2604: dup
    //   2605: new 420	java/lang/StringBuilder
    //   2608: dup
    //   2609: invokespecial 421	java/lang/StringBuilder:<init>	()V
    //   2612: ldc_w 605
    //   2615: invokevirtual 427	java/lang/StringBuilder:append	(Ljava/lang/String;)Ljava/lang/StringBuilder;
    //   2618: aload 6
    //   2620: invokevirtual 430	java/lang/StringBuilder:append	(Ljava/lang/Object;)Ljava/lang/StringBuilder;
    //   2623: invokevirtual 433	java/lang/StringBuilder:toString	()Ljava/lang/String;
    //   2626: invokespecial 436	java/lang/IllegalArgumentException:<init>	(Ljava/lang/String;)V
    //   2629: athrow
    //   2630: new 418	java/lang/IllegalArgumentException
    //   2633: dup
    //   2634: new 420	java/lang/StringBuilder
    //   2637: dup
    //   2638: invokespecial 421	java/lang/StringBuilder:<init>	()V
    //   2641: ldc_w 607
    //   2644: invokevirtual 427	java/lang/StringBuilder:append	(Ljava/lang/String;)Ljava/lang/StringBuilder;
    //   2647: aload 6
    //   2649: invokevirtual 430	java/lang/StringBuilder:append	(Ljava/lang/Object;)Ljava/lang/StringBuilder;
    //   2652: invokevirtual 433	java/lang/StringBuilder:toString	()Ljava/lang/String;
    //   2655: invokespecial 436	java/lang/IllegalArgumentException:<init>	(Ljava/lang/String;)V
    //   2658: athrow
    //   2659: aload_2
    //   2660: invokevirtual 444	android/view/View:getTag	()Ljava/lang/Object;
    //   2663: astore 6
    //   2665: aload 6
    //   2667: ifnonnull +6 -> 2673
    //   2670: goto -1885 -> 785
    //   2673: goto +4945 -> 7618
    //   2676: new 446	java/lang/RuntimeException
    //   2679: dup
    //   2680: ldc_w 448
    //   2683: invokespecial 449	java/lang/RuntimeException:<init>	(Ljava/lang/String;)V
    //   2686: athrow
    //   2687: new 418	java/lang/IllegalArgumentException
    //   2690: dup
    //   2691: new 420	java/lang/StringBuilder
    //   2694: dup
    //   2695: invokespecial 421	java/lang/StringBuilder:<init>	()V
    //   2698: ldc_w 609
    //   2701: invokevirtual 427	java/lang/StringBuilder:append	(Ljava/lang/String;)Ljava/lang/StringBuilder;
    //   2704: aload 6
    //   2706: invokevirtual 430	java/lang/StringBuilder:append	(Ljava/lang/Object;)Ljava/lang/StringBuilder;
    //   2709: invokevirtual 433	java/lang/StringBuilder:toString	()Ljava/lang/String;
    //   2712: invokespecial 436	java/lang/IllegalArgumentException:<init>	(Ljava/lang/String;)V
    //   2715: athrow
    //   2716: aload_2
    //   2717: invokevirtual 444	android/view/View:getTag	()Ljava/lang/Object;
    //   2720: astore 6
    //   2722: aload 6
    //   2724: ifnonnull +6 -> 2730
    //   2727: goto -363 -> 2364
    //   2730: goto +3507 -> 6237
    //   2733: aload_2
    //   2734: invokevirtual 444	android/view/View:getTag	()Ljava/lang/Object;
    //   2737: astore 6
    //   2739: aload 6
    //   2741: ifnonnull +6 -> 2747
    //   2744: goto -920 -> 1824
    //   2747: goto +1439 -> 4186
    //   2750: new 611	o/LB
    //   2753: dup
    //   2754: aload_1
    //   2755: aload_2
    //   2756: invokespecial 612	o/LB:<init>	(Lo/ˉ;Landroid/view/View;)V
    //   2759: areturn
    //   2760: new 614	o/Mv
    //   2763: dup
    //   2764: aload_1
    //   2765: aload_2
    //   2766: invokespecial 615	o/Mv:<init>	(Lo/ˉ;Landroid/view/View;)V
    //   2769: areturn
    //   2770: new 418	java/lang/IllegalArgumentException
    //   2773: dup
    //   2774: new 420	java/lang/StringBuilder
    //   2777: dup
    //   2778: invokespecial 421	java/lang/StringBuilder:<init>	()V
    //   2781: ldc_w 617
    //   2784: invokevirtual 427	java/lang/StringBuilder:append	(Ljava/lang/String;)Ljava/lang/StringBuilder;
    //   2787: aload 6
    //   2789: invokevirtual 430	java/lang/StringBuilder:append	(Ljava/lang/Object;)Ljava/lang/StringBuilder;
    //   2792: invokevirtual 433	java/lang/StringBuilder:toString	()Ljava/lang/String;
    //   2795: invokespecial 436	java/lang/IllegalArgumentException:<init>	(Ljava/lang/String;)V
    //   2798: athrow
    //   2799: ldc_w 378
    //   2802: aload 6
    //   2804: invokevirtual 133	java/lang/String:equals	(Ljava/lang/Object;)Z
    //   2807: ifeq +6 -> 2813
    //   2810: goto -801 -> 2009
    //   2813: goto +70 -> 2883
    //   2816: ldc_w 285
    //   2819: aload 6
    //   2821: invokevirtual 133	java/lang/String:equals	(Ljava/lang/Object;)Z
    //   2824: ifeq +6 -> 2830
    //   2827: goto -737 -> 2090
    //   2830: goto +4990 -> 7820
    //   2833: ldc -114
    //   2835: aload 6
    //   2837: invokevirtual 133	java/lang/String:equals	(Ljava/lang/Object;)Z
    //   2840: ifeq +6 -> 2846
    //   2843: goto +4173 -> 7016
    //   2846: goto -2492 -> 354
    //   2849: aload_2
    //   2850: invokevirtual 444	android/view/View:getTag	()Ljava/lang/Object;
    //   2853: astore 6
    //   2855: aload 6
    //   2857: ifnonnull +6 -> 2863
    //   2860: goto -1580 -> 1280
    //   2863: goto -1028 -> 1835
    //   2866: ldc_w 311
    //   2869: aload 6
    //   2871: invokevirtual 133	java/lang/String:equals	(Ljava/lang/Object;)Z
    //   2874: ifeq +6 -> 2880
    //   2877: goto +3518 -> 6395
    //   2880: goto +3048 -> 5928
    //   2883: new 418	java/lang/IllegalArgumentException
    //   2886: dup
    //   2887: new 420	java/lang/StringBuilder
    //   2890: dup
    //   2891: invokespecial 421	java/lang/StringBuilder:<init>	()V
    //   2894: ldc_w 619
    //   2897: invokevirtual 427	java/lang/StringBuilder:append	(Ljava/lang/String;)Ljava/lang/StringBuilder;
    //   2900: aload 6
    //   2902: invokevirtual 430	java/lang/StringBuilder:append	(Ljava/lang/Object;)Ljava/lang/StringBuilder;
    //   2905: invokevirtual 433	java/lang/StringBuilder:toString	()Ljava/lang/String;
    //   2908: invokespecial 436	java/lang/IllegalArgumentException:<init>	(Ljava/lang/String;)V
    //   2911: athrow
    //   2912: new 418	java/lang/IllegalArgumentException
    //   2915: dup
    //   2916: new 420	java/lang/StringBuilder
    //   2919: dup
    //   2920: invokespecial 421	java/lang/StringBuilder:<init>	()V
    //   2923: ldc_w 621
    //   2926: invokevirtual 427	java/lang/StringBuilder:append	(Ljava/lang/String;)Ljava/lang/StringBuilder;
    //   2929: aload 6
    //   2931: invokevirtual 430	java/lang/StringBuilder:append	(Ljava/lang/Object;)Ljava/lang/StringBuilder;
    //   2934: invokevirtual 433	java/lang/StringBuilder:toString	()Ljava/lang/String;
    //   2937: invokespecial 436	java/lang/IllegalArgumentException:<init>	(Ljava/lang/String;)V
    //   2940: athrow
    //   2941: ldc_w 396
    //   2944: aload 6
    //   2946: invokevirtual 133	java/lang/String:equals	(Ljava/lang/Object;)Z
    //   2949: ifeq +6 -> 2955
    //   2952: goto +269 -> 3221
    //   2955: goto -620 -> 2335
    //   2958: aload_2
    //   2959: invokevirtual 444	android/view/View:getTag	()Ljava/lang/Object;
    //   2962: astore 6
    //   2964: aload 6
    //   2966: ifnonnull +6 -> 2972
    //   2969: goto -774 -> 2195
    //   2972: goto -1546 -> 1426
    //   2975: aload_1
    //   2976: areturn
    //   2977: new 446	java/lang/RuntimeException
    //   2980: dup
    //   2981: ldc_w 448
    //   2984: invokespecial 449	java/lang/RuntimeException:<init>	(Ljava/lang/String;)V
    //   2987: athrow
    //   2988: new 623	o/GH
    //   2991: dup
    //   2992: aload_1
    //   2993: aload_2
    //   2994: invokespecial 624	o/GH:<init>	(Lo/ˉ;Landroid/view/View;)V
    //   2997: areturn
    //   2998: new 626	o/GV
    //   3001: dup
    //   3002: aload_1
    //   3003: aload_2
    //   3004: invokespecial 627	o/GV:<init>	(Lo/ˉ;Landroid/view/View;)V
    //   3007: areturn
    //   3008: new 446	java/lang/RuntimeException
    //   3011: dup
    //   3012: ldc_w 448
    //   3015: invokespecial 449	java/lang/RuntimeException:<init>	(Ljava/lang/String;)V
    //   3018: athrow
    //   3019: ldc_w 279
    //   3022: aload 6
    //   3024: invokevirtual 133	java/lang/String:equals	(Ljava/lang/Object;)Z
    //   3027: ifeq +6 -> 3033
    //   3030: goto -1672 -> 1358
    //   3033: goto -1665 -> 1368
    //   3036: new 446	java/lang/RuntimeException
    //   3039: dup
    //   3040: ldc_w 448
    //   3043: invokespecial 449	java/lang/RuntimeException:<init>	(Ljava/lang/String;)V
    //   3046: athrow
    //   3047: ldc_w 344
    //   3050: aload 6
    //   3052: invokevirtual 133	java/lang/String:equals	(Ljava/lang/Object;)Z
    //   3055: ifeq +6 -> 3061
    //   3058: goto +3223 -> 6281
    //   3061: goto +4124 -> 7185
    //   3064: new 418	java/lang/IllegalArgumentException
    //   3067: dup
    //   3068: new 420	java/lang/StringBuilder
    //   3071: dup
    //   3072: invokespecial 421	java/lang/StringBuilder:<init>	()V
    //   3075: ldc_w 629
    //   3078: invokevirtual 427	java/lang/StringBuilder:append	(Ljava/lang/String;)Ljava/lang/StringBuilder;
    //   3081: aload 6
    //   3083: invokevirtual 430	java/lang/StringBuilder:append	(Ljava/lang/Object;)Ljava/lang/StringBuilder;
    //   3086: invokevirtual 433	java/lang/StringBuilder:toString	()Ljava/lang/String;
    //   3089: invokespecial 436	java/lang/IllegalArgumentException:<init>	(Ljava/lang/String;)V
    //   3092: athrow
    //   3093: new 446	java/lang/RuntimeException
    //   3096: dup
    //   3097: ldc_w 448
    //   3100: invokespecial 449	java/lang/RuntimeException:<init>	(Ljava/lang/String;)V
    //   3103: athrow
    //   3104: aload_2
    //   3105: invokevirtual 444	android/view/View:getTag	()Ljava/lang/Object;
    //   3108: astore 6
    //   3110: aload 6
    //   3112: ifnonnull +6 -> 3118
    //   3115: goto +449 -> 3564
    //   3118: goto +633 -> 3751
    //   3121: new 418	java/lang/IllegalArgumentException
    //   3124: dup
    //   3125: new 420	java/lang/StringBuilder
    //   3128: dup
    //   3129: invokespecial 421	java/lang/StringBuilder:<init>	()V
    //   3132: ldc_w 631
    //   3135: invokevirtual 427	java/lang/StringBuilder:append	(Ljava/lang/String;)Ljava/lang/StringBuilder;
    //   3138: aload 6
    //   3140: invokevirtual 430	java/lang/StringBuilder:append	(Ljava/lang/Object;)Ljava/lang/StringBuilder;
    //   3143: invokevirtual 433	java/lang/StringBuilder:toString	()Ljava/lang/String;
    //   3146: invokespecial 436	java/lang/IllegalArgumentException:<init>	(Ljava/lang/String;)V
    //   3149: athrow
    //   3150: new 446	java/lang/RuntimeException
    //   3153: dup
    //   3154: ldc_w 448
    //   3157: invokespecial 449	java/lang/RuntimeException:<init>	(Ljava/lang/String;)V
    //   3160: athrow
    //   3161: ldc -21
    //   3163: aload 6
    //   3165: invokevirtual 133	java/lang/String:equals	(Ljava/lang/Object;)Z
    //   3168: ifeq +6 -> 3174
    //   3171: goto +4950 -> 8121
    //   3174: goto -1531 -> 1643
    //   3177: aload_2
    //   3178: invokevirtual 444	android/view/View:getTag	()Ljava/lang/Object;
    //   3181: astore 6
    //   3183: aload 6
    //   3185: ifnonnull +6 -> 3191
    //   3188: goto -1626 -> 1562
    //   3191: goto -873 -> 2318
    //   3194: ldc -44
    //   3196: aload 6
    //   3198: invokevirtual 133	java/lang/String:equals	(Ljava/lang/Object;)Z
    //   3201: ifeq +6 -> 3207
    //   3204: goto +3363 -> 6567
    //   3207: goto -1412 -> 1795
    //   3210: new 446	java/lang/RuntimeException
    //   3213: dup
    //   3214: ldc_w 448
    //   3217: invokespecial 449	java/lang/RuntimeException:<init>	(Ljava/lang/String;)V
    //   3220: athrow
    //   3221: new 633	o/Ms
    //   3224: dup
    //   3225: aload_1
    //   3226: aload_2
    //   3227: invokespecial 634	o/Ms:<init>	(Lo/ˉ;Landroid/view/View;)V
    //   3230: areturn
    //   3231: aload_2
    //   3232: invokevirtual 444	android/view/View:getTag	()Ljava/lang/Object;
    //   3235: astore 6
    //   3237: aload 6
    //   3239: ifnonnull +6 -> 3245
    //   3242: goto +695 -> 3937
    //   3245: goto +4732 -> 7977
    //   3248: new 418	java/lang/IllegalArgumentException
    //   3251: dup
    //   3252: new 420	java/lang/StringBuilder
    //   3255: dup
    //   3256: invokespecial 421	java/lang/StringBuilder:<init>	()V
    //   3259: ldc_w 636
    //   3262: invokevirtual 427	java/lang/StringBuilder:append	(Ljava/lang/String;)Ljava/lang/StringBuilder;
    //   3265: aload 6
    //   3267: invokevirtual 430	java/lang/StringBuilder:append	(Ljava/lang/Object;)Ljava/lang/StringBuilder;
    //   3270: invokevirtual 433	java/lang/StringBuilder:toString	()Ljava/lang/String;
    //   3273: invokespecial 436	java/lang/IllegalArgumentException:<init>	(Ljava/lang/String;)V
    //   3276: athrow
    //   3277: new 418	java/lang/IllegalArgumentException
    //   3280: dup
    //   3281: new 420	java/lang/StringBuilder
    //   3284: dup
    //   3285: invokespecial 421	java/lang/StringBuilder:<init>	()V
    //   3288: ldc_w 638
    //   3291: invokevirtual 427	java/lang/StringBuilder:append	(Ljava/lang/String;)Ljava/lang/StringBuilder;
    //   3294: aload 6
    //   3296: invokevirtual 430	java/lang/StringBuilder:append	(Ljava/lang/Object;)Ljava/lang/StringBuilder;
    //   3299: invokevirtual 433	java/lang/StringBuilder:toString	()Ljava/lang/String;
    //   3302: invokespecial 436	java/lang/IllegalArgumentException:<init>	(Ljava/lang/String;)V
    //   3305: athrow
    //   3306: ldc -37
    //   3308: aload 6
    //   3310: invokevirtual 133	java/lang/String:equals	(Ljava/lang/Object;)Z
    //   3313: ifeq +6 -> 3319
    //   3316: goto +4345 -> 7661
    //   3319: goto -407 -> 2912
    //   3322: ldc_w 281
    //   3325: aload 6
    //   3327: invokevirtual 133	java/lang/String:equals	(Ljava/lang/Object;)Z
    //   3330: ifeq +6 -> 3336
    //   3333: goto +3983 -> 7316
    //   3336: goto +681 -> 4017
    //   3339: new 418	java/lang/IllegalArgumentException
    //   3342: dup
    //   3343: new 420	java/lang/StringBuilder
    //   3346: dup
    //   3347: invokespecial 421	java/lang/StringBuilder:<init>	()V
    //   3350: ldc_w 640
    //   3353: invokevirtual 427	java/lang/StringBuilder:append	(Ljava/lang/String;)Ljava/lang/StringBuilder;
    //   3356: aload 6
    //   3358: invokevirtual 430	java/lang/StringBuilder:append	(Ljava/lang/Object;)Ljava/lang/StringBuilder;
    //   3361: invokevirtual 433	java/lang/StringBuilder:toString	()Ljava/lang/String;
    //   3364: invokespecial 436	java/lang/IllegalArgumentException:<init>	(Ljava/lang/String;)V
    //   3367: athrow
    //   3368: ldc_w 392
    //   3371: aload 6
    //   3373: invokevirtual 133	java/lang/String:equals	(Ljava/lang/Object;)Z
    //   3376: ifeq +6 -> 3382
    //   3379: goto +4969 -> 8348
    //   3382: goto +3395 -> 6777
    //   3385: new 418	java/lang/IllegalArgumentException
    //   3388: dup
    //   3389: new 420	java/lang/StringBuilder
    //   3392: dup
    //   3393: invokespecial 421	java/lang/StringBuilder:<init>	()V
    //   3396: ldc_w 642
    //   3399: invokevirtual 427	java/lang/StringBuilder:append	(Ljava/lang/String;)Ljava/lang/StringBuilder;
    //   3402: aload 6
    //   3404: invokevirtual 430	java/lang/StringBuilder:append	(Ljava/lang/Object;)Ljava/lang/StringBuilder;
    //   3407: invokevirtual 433	java/lang/StringBuilder:toString	()Ljava/lang/String;
    //   3410: invokespecial 436	java/lang/IllegalArgumentException:<init>	(Ljava/lang/String;)V
    //   3413: athrow
    //   3414: ldc_w 297
    //   3417: aload 6
    //   3419: invokevirtual 133	java/lang/String:equals	(Ljava/lang/Object;)Z
    //   3422: ifeq +6 -> 3428
    //   3425: goto -2254 -> 1171
    //   3428: goto +3204 -> 6632
    //   3431: new 446	java/lang/RuntimeException
    //   3434: dup
    //   3435: ldc_w 448
    //   3438: invokespecial 449	java/lang/RuntimeException:<init>	(Ljava/lang/String;)V
    //   3441: athrow
    //   3442: ldc_w 398
    //   3445: aload 6
    //   3447: invokevirtual 133	java/lang/String:equals	(Ljava/lang/Object;)Z
    //   3450: ifeq +6 -> 3456
    //   3453: goto -895 -> 2558
    //   3456: goto -2314 -> 1142
    //   3459: new 446	java/lang/RuntimeException
    //   3462: dup
    //   3463: ldc_w 448
    //   3466: invokespecial 449	java/lang/RuntimeException:<init>	(Ljava/lang/String;)V
    //   3469: athrow
    //   3470: new 644	o/DB
    //   3473: dup
    //   3474: aload_1
    //   3475: aload_2
    //   3476: invokespecial 645	o/DB:<init>	(Lo/ˉ;Landroid/view/View;)V
    //   3479: areturn
    //   3480: new 446	java/lang/RuntimeException
    //   3483: dup
    //   3484: ldc_w 448
    //   3487: invokespecial 449	java/lang/RuntimeException:<init>	(Ljava/lang/String;)V
    //   3490: athrow
    //   3491: aload_2
    //   3492: invokevirtual 444	android/view/View:getTag	()Ljava/lang/Object;
    //   3495: astore 6
    //   3497: aload 6
    //   3499: ifnonnull +6 -> 3505
    //   3502: goto +4629 -> 8131
    //   3505: goto -3227 -> 278
    //   3508: new 418	java/lang/IllegalArgumentException
    //   3511: dup
    //   3512: new 420	java/lang/StringBuilder
    //   3515: dup
    //   3516: invokespecial 421	java/lang/StringBuilder:<init>	()V
    //   3519: ldc_w 647
    //   3522: invokevirtual 427	java/lang/StringBuilder:append	(Ljava/lang/String;)Ljava/lang/StringBuilder;
    //   3525: aload 6
    //   3527: invokevirtual 430	java/lang/StringBuilder:append	(Ljava/lang/Object;)Ljava/lang/StringBuilder;
    //   3530: invokevirtual 433	java/lang/StringBuilder:toString	()Ljava/lang/String;
    //   3533: invokespecial 436	java/lang/IllegalArgumentException:<init>	(Ljava/lang/String;)V
    //   3536: athrow
    //   3537: ldc -80
    //   3539: aload 6
    //   3541: invokevirtual 133	java/lang/String:equals	(Ljava/lang/Object;)Z
    //   3544: ifeq +6 -> 3550
    //   3547: goto +3579 -> 7126
    //   3550: goto +496 -> 4046
    //   3553: new 446	java/lang/RuntimeException
    //   3556: dup
    //   3557: ldc_w 448
    //   3560: invokespecial 449	java/lang/RuntimeException:<init>	(Ljava/lang/String;)V
    //   3563: athrow
    //   3564: new 446	java/lang/RuntimeException
    //   3567: dup
    //   3568: ldc_w 448
    //   3571: invokespecial 449	java/lang/RuntimeException:<init>	(Ljava/lang/String;)V
    //   3574: athrow
    //   3575: ldc_w 316
    //   3578: aload 6
    //   3580: invokevirtual 133	java/lang/String:equals	(Ljava/lang/Object;)Z
    //   3583: ifeq +6 -> 3589
    //   3586: goto +4695 -> 8281
    //   3589: goto -2940 -> 649
    //   3592: new 418	java/lang/IllegalArgumentException
    //   3595: dup
    //   3596: new 420	java/lang/StringBuilder
    //   3599: dup
    //   3600: invokespecial 421	java/lang/StringBuilder:<init>	()V
    //   3603: ldc_w 649
    //   3606: invokevirtual 427	java/lang/StringBuilder:append	(Ljava/lang/String;)Ljava/lang/StringBuilder;
    //   3609: aload 6
    //   3611: invokevirtual 430	java/lang/StringBuilder:append	(Ljava/lang/Object;)Ljava/lang/StringBuilder;
    //   3614: invokevirtual 433	java/lang/StringBuilder:toString	()Ljava/lang/String;
    //   3617: invokespecial 436	java/lang/IllegalArgumentException:<init>	(Ljava/lang/String;)V
    //   3620: athrow
    //   3621: new 651	o/Kg
    //   3624: dup
    //   3625: aload_1
    //   3626: aload_2
    //   3627: invokespecial 652	o/Kg:<init>	(Lo/ˉ;Landroid/view/View;)V
    //   3630: areturn
    //   3631: ldc -73
    //   3633: aload 6
    //   3635: invokevirtual 133	java/lang/String:equals	(Ljava/lang/Object;)Z
    //   3638: ifeq +6 -> 3644
    //   3641: goto -2008 -> 1633
    //   3644: goto -1355 -> 2289
    //   3647: ldc_w 259
    //   3650: aload 6
    //   3652: invokevirtual 133	java/lang/String:equals	(Ljava/lang/Object;)Z
    //   3655: ifeq +6 -> 3661
    //   3658: goto +1021 -> 4679
    //   3661: goto +4520 -> 8181
    //   3664: new 446	java/lang/RuntimeException
    //   3667: dup
    //   3668: ldc_w 448
    //   3671: invokespecial 449	java/lang/RuntimeException:<init>	(Ljava/lang/String;)V
    //   3674: athrow
    //   3675: ldc -121
    //   3677: aload 6
    //   3679: invokevirtual 133	java/lang/String:equals	(Ljava/lang/Object;)Z
    //   3682: ifeq +6 -> 3688
    //   3685: goto -3364 -> 321
    //   3688: goto +3259 -> 6947
    //   3691: aload_2
    //   3692: invokevirtual 444	android/view/View:getTag	()Ljava/lang/Object;
    //   3695: astore 6
    //   3697: aload 6
    //   3699: ifnonnull +6 -> 3705
    //   3702: goto +4618 -> 8320
    //   3705: goto -3444 -> 261
    //   3708: ldc_w 299
    //   3711: aload 6
    //   3713: invokevirtual 133	java/lang/String:equals	(Ljava/lang/Object;)Z
    //   3716: ifeq +6 -> 3722
    //   3719: goto -1210 -> 2509
    //   3722: goto -1121 -> 2601
    //   3725: new 654	o/JG
    //   3728: dup
    //   3729: aload_1
    //   3730: aload_2
    //   3731: invokespecial 655	o/JG:<init>	(Lo/ˉ;Landroid/view/View;)V
    //   3734: areturn
    //   3735: ldc -58
    //   3737: aload 6
    //   3739: invokevirtual 133	java/lang/String:equals	(Ljava/lang/Object;)Z
    //   3742: ifeq +6 -> 3748
    //   3745: goto -747 -> 2998
    //   3748: goto +2913 -> 6661
    //   3751: ldc_w 291
    //   3754: aload 6
    //   3756: invokevirtual 133	java/lang/String:equals	(Ljava/lang/Object;)Z
    //   3759: ifeq +6 -> 3765
    //   3762: goto -3004 -> 758
    //   3765: goto -488 -> 3277
    //   3768: ldc -104
    //   3770: aload 6
    //   3772: invokevirtual 133	java/lang/String:equals	(Ljava/lang/Object;)Z
    //   3775: ifeq +6 -> 3781
    //   3778: goto -157 -> 3621
    //   3781: goto -1011 -> 2770
    //   3784: new 418	java/lang/IllegalArgumentException
    //   3787: dup
    //   3788: new 420	java/lang/StringBuilder
    //   3791: dup
    //   3792: invokespecial 421	java/lang/StringBuilder:<init>	()V
    //   3795: ldc_w 657
    //   3798: invokevirtual 427	java/lang/StringBuilder:append	(Ljava/lang/String;)Ljava/lang/StringBuilder;
    //   3801: aload 6
    //   3803: invokevirtual 430	java/lang/StringBuilder:append	(Ljava/lang/Object;)Ljava/lang/StringBuilder;
    //   3806: invokevirtual 433	java/lang/StringBuilder:toString	()Ljava/lang/String;
    //   3809: invokespecial 436	java/lang/IllegalArgumentException:<init>	(Ljava/lang/String;)V
    //   3812: athrow
    //   3813: new 659	o/MB
    //   3816: dup
    //   3817: aload_1
    //   3818: aload_2
    //   3819: invokespecial 660	o/MB:<init>	(Lo/ˉ;Landroid/view/View;)V
    //   3822: areturn
    //   3823: new 418	java/lang/IllegalArgumentException
    //   3826: dup
    //   3827: new 420	java/lang/StringBuilder
    //   3830: dup
    //   3831: invokespecial 421	java/lang/StringBuilder:<init>	()V
    //   3834: ldc_w 662
    //   3837: invokevirtual 427	java/lang/StringBuilder:append	(Ljava/lang/String;)Ljava/lang/StringBuilder;
    //   3840: aload 6
    //   3842: invokevirtual 430	java/lang/StringBuilder:append	(Ljava/lang/Object;)Ljava/lang/StringBuilder;
    //   3845: invokevirtual 433	java/lang/StringBuilder:toString	()Ljava/lang/String;
    //   3848: invokespecial 436	java/lang/IllegalArgumentException:<init>	(Ljava/lang/String;)V
    //   3851: athrow
    //   3852: aload_2
    //   3853: invokevirtual 444	android/view/View:getTag	()Ljava/lang/Object;
    //   3856: astore 6
    //   3858: aload 6
    //   3860: ifnonnull +6 -> 3866
    //   3863: goto -1623 -> 2240
    //   3866: goto -1033 -> 2833
    //   3869: new 446	java/lang/RuntimeException
    //   3872: dup
    //   3873: ldc_w 448
    //   3876: invokespecial 449	java/lang/RuntimeException:<init>	(Ljava/lang/String;)V
    //   3879: athrow
    //   3880: ldc_w 256
    //   3883: aload 6
    //   3885: invokevirtual 133	java/lang/String:equals	(Ljava/lang/Object;)Z
    //   3888: ifeq +6 -> 3894
    //   3891: goto -3440 -> 451
    //   3894: goto +484 -> 4378
    //   3897: new 418	java/lang/IllegalArgumentException
    //   3900: dup
    //   3901: new 420	java/lang/StringBuilder
    //   3904: dup
    //   3905: invokespecial 421	java/lang/StringBuilder:<init>	()V
    //   3908: ldc_w 664
    //   3911: invokevirtual 427	java/lang/StringBuilder:append	(Ljava/lang/String;)Ljava/lang/StringBuilder;
    //   3914: aload 6
    //   3916: invokevirtual 430	java/lang/StringBuilder:append	(Ljava/lang/Object;)Ljava/lang/StringBuilder;
    //   3919: invokevirtual 433	java/lang/StringBuilder:toString	()Ljava/lang/String;
    //   3922: invokespecial 436	java/lang/IllegalArgumentException:<init>	(Ljava/lang/String;)V
    //   3925: athrow
    //   3926: new 446	java/lang/RuntimeException
    //   3929: dup
    //   3930: ldc_w 448
    //   3933: invokespecial 449	java/lang/RuntimeException:<init>	(Ljava/lang/String;)V
    //   3936: athrow
    //   3937: new 446	java/lang/RuntimeException
    //   3940: dup
    //   3941: ldc_w 448
    //   3944: invokespecial 449	java/lang/RuntimeException:<init>	(Ljava/lang/String;)V
    //   3947: athrow
    //   3948: new 418	java/lang/IllegalArgumentException
    //   3951: dup
    //   3952: new 420	java/lang/StringBuilder
    //   3955: dup
    //   3956: invokespecial 421	java/lang/StringBuilder:<init>	()V
    //   3959: ldc_w 666
    //   3962: invokevirtual 427	java/lang/StringBuilder:append	(Ljava/lang/String;)Ljava/lang/StringBuilder;
    //   3965: aload 6
    //   3967: invokevirtual 430	java/lang/StringBuilder:append	(Ljava/lang/Object;)Ljava/lang/StringBuilder;
    //   3970: invokevirtual 433	java/lang/StringBuilder:toString	()Ljava/lang/String;
    //   3973: invokespecial 436	java/lang/IllegalArgumentException:<init>	(Ljava/lang/String;)V
    //   3976: athrow
    //   3977: new 418	java/lang/IllegalArgumentException
    //   3980: dup
    //   3981: new 420	java/lang/StringBuilder
    //   3984: dup
    //   3985: invokespecial 421	java/lang/StringBuilder:<init>	()V
    //   3988: ldc_w 668
    //   3991: invokevirtual 427	java/lang/StringBuilder:append	(Ljava/lang/String;)Ljava/lang/StringBuilder;
    //   3994: aload 6
    //   3996: invokevirtual 430	java/lang/StringBuilder:append	(Ljava/lang/Object;)Ljava/lang/StringBuilder;
    //   3999: invokevirtual 433	java/lang/StringBuilder:toString	()Ljava/lang/String;
    //   4002: invokespecial 436	java/lang/IllegalArgumentException:<init>	(Ljava/lang/String;)V
    //   4005: athrow
    //   4006: new 446	java/lang/RuntimeException
    //   4009: dup
    //   4010: ldc_w 448
    //   4013: invokespecial 449	java/lang/RuntimeException:<init>	(Ljava/lang/String;)V
    //   4016: athrow
    //   4017: new 418	java/lang/IllegalArgumentException
    //   4020: dup
    //   4021: new 420	java/lang/StringBuilder
    //   4024: dup
    //   4025: invokespecial 421	java/lang/StringBuilder:<init>	()V
    //   4028: ldc_w 670
    //   4031: invokevirtual 427	java/lang/StringBuilder:append	(Ljava/lang/String;)Ljava/lang/StringBuilder;
    //   4034: aload 6
    //   4036: invokevirtual 430	java/lang/StringBuilder:append	(Ljava/lang/Object;)Ljava/lang/StringBuilder;
    //   4039: invokevirtual 433	java/lang/StringBuilder:toString	()Ljava/lang/String;
    //   4042: invokespecial 436	java/lang/IllegalArgumentException:<init>	(Ljava/lang/String;)V
    //   4045: athrow
    //   4046: new 418	java/lang/IllegalArgumentException
    //   4049: dup
    //   4050: new 420	java/lang/StringBuilder
    //   4053: dup
    //   4054: invokespecial 421	java/lang/StringBuilder:<init>	()V
    //   4057: ldc_w 672
    //   4060: invokevirtual 427	java/lang/StringBuilder:append	(Ljava/lang/String;)Ljava/lang/StringBuilder;
    //   4063: aload 6
    //   4065: invokevirtual 430	java/lang/StringBuilder:append	(Ljava/lang/Object;)Ljava/lang/StringBuilder;
    //   4068: invokevirtual 433	java/lang/StringBuilder:toString	()Ljava/lang/String;
    //   4071: invokespecial 436	java/lang/IllegalArgumentException:<init>	(Ljava/lang/String;)V
    //   4074: athrow
    //   4075: new 446	java/lang/RuntimeException
    //   4078: dup
    //   4079: ldc_w 448
    //   4082: invokespecial 449	java/lang/RuntimeException:<init>	(Ljava/lang/String;)V
    //   4085: athrow
    //   4086: new 446	java/lang/RuntimeException
    //   4089: dup
    //   4090: ldc_w 448
    //   4093: invokespecial 449	java/lang/RuntimeException:<init>	(Ljava/lang/String;)V
    //   4096: athrow
    //   4097: new 674	o/GQ
    //   4100: dup
    //   4101: aload_1
    //   4102: aload_2
    //   4103: invokespecial 675	o/GQ:<init>	(Lo/ˉ;Landroid/view/View;)V
    //   4106: areturn
    //   4107: aload_2
    //   4108: invokevirtual 444	android/view/View:getTag	()Ljava/lang/Object;
    //   4111: astore 6
    //   4113: aload 6
    //   4115: ifnonnull +6 -> 4121
    //   4118: goto +3124 -> 7242
    //   4121: goto +19 -> 4140
    //   4124: ldc -89
    //   4126: aload 6
    //   4128: invokevirtual 133	java/lang/String:equals	(Ljava/lang/Object;)Z
    //   4131: ifeq +6 -> 4137
    //   4134: goto -2893 -> 1241
    //   4137: goto +3591 -> 7728
    //   4140: ldc_w 374
    //   4143: aload 6
    //   4145: invokevirtual 133	java/lang/String:equals	(Ljava/lang/Object;)Z
    //   4148: ifeq +6 -> 4154
    //   4151: goto +3024 -> 7175
    //   4154: goto +1745 -> 5899
    //   4157: new 418	java/lang/IllegalArgumentException
    //   4160: dup
    //   4161: new 420	java/lang/StringBuilder
    //   4164: dup
    //   4165: invokespecial 421	java/lang/StringBuilder:<init>	()V
    //   4168: ldc_w 677
    //   4171: invokevirtual 427	java/lang/StringBuilder:append	(Ljava/lang/String;)Ljava/lang/StringBuilder;
    //   4174: aload 6
    //   4176: invokevirtual 430	java/lang/StringBuilder:append	(Ljava/lang/Object;)Ljava/lang/StringBuilder;
    //   4179: invokevirtual 433	java/lang/StringBuilder:toString	()Ljava/lang/String;
    //   4182: invokespecial 436	java/lang/IllegalArgumentException:<init>	(Ljava/lang/String;)V
    //   4185: athrow
    //   4186: ldc_w 318
    //   4189: aload 6
    //   4191: invokevirtual 133	java/lang/String:equals	(Ljava/lang/Object;)Z
    //   4194: ifeq +6 -> 4200
    //   4197: goto -727 -> 3470
    //   4200: goto -3597 -> 603
    //   4203: aload_2
    //   4204: invokevirtual 444	android/view/View:getTag	()Ljava/lang/Object;
    //   4207: astore 6
    //   4209: aload 6
    //   4211: ifnonnull +6 -> 4217
    //   4214: goto +1193 -> 5407
    //   4217: goto +429 -> 4646
    //   4220: ldc_w 410
    //   4223: aload 6
    //   4225: invokevirtual 133	java/lang/String:equals	(Ljava/lang/Object;)Z
    //   4228: ifeq +6 -> 4234
    //   4231: goto +2636 -> 6867
    //   4234: goto +4008 -> 8242
    //   4237: aload_2
    //   4238: invokevirtual 444	android/view/View:getTag	()Ljava/lang/Object;
    //   4241: astore 6
    //   4243: aload 6
    //   4245: ifnonnull +6 -> 4251
    //   4248: goto -4170 -> 78
    //   4251: goto +3681 -> 7932
    //   4254: aload_2
    //   4255: invokevirtual 444	android/view/View:getTag	()Ljava/lang/Object;
    //   4258: astore 6
    //   4260: aload 6
    //   4262: ifnonnull +6 -> 4268
    //   4265: goto +3331 -> 7596
    //   4268: goto -4079 -> 189
    //   4271: new 418	java/lang/IllegalArgumentException
    //   4274: dup
    //   4275: new 420	java/lang/StringBuilder
    //   4278: dup
    //   4279: invokespecial 421	java/lang/StringBuilder:<init>	()V
    //   4282: ldc_w 679
    //   4285: invokevirtual 427	java/lang/StringBuilder:append	(Ljava/lang/String;)Ljava/lang/StringBuilder;
    //   4288: aload 6
    //   4290: invokevirtual 430	java/lang/StringBuilder:append	(Ljava/lang/Object;)Ljava/lang/StringBuilder;
    //   4293: invokevirtual 433	java/lang/StringBuilder:toString	()Ljava/lang/String;
    //   4296: invokespecial 436	java/lang/IllegalArgumentException:<init>	(Ljava/lang/String;)V
    //   4299: athrow
    //   4300: aload_2
    //   4301: invokevirtual 444	android/view/View:getTag	()Ljava/lang/Object;
    //   4304: astore 6
    //   4306: aload 6
    //   4308: ifnonnull +6 -> 4314
    //   4311: goto -1275 -> 3036
    //   4314: goto -3983 -> 331
    //   4317: new 446	java/lang/RuntimeException
    //   4320: dup
    //   4321: ldc_w 448
    //   4324: invokespecial 449	java/lang/RuntimeException:<init>	(Ljava/lang/String;)V
    //   4327: athrow
    //   4328: new 681	o/JM
    //   4331: dup
    //   4332: aload_1
    //   4333: aload_2
    //   4334: invokespecial 682	o/JM:<init>	(Lo/ˉ;Landroid/view/View;)V
    //   4337: areturn
    //   4338: new 446	java/lang/RuntimeException
    //   4341: dup
    //   4342: ldc_w 448
    //   4345: invokespecial 449	java/lang/RuntimeException:<init>	(Ljava/lang/String;)V
    //   4348: athrow
    //   4349: new 418	java/lang/IllegalArgumentException
    //   4352: dup
    //   4353: new 420	java/lang/StringBuilder
    //   4356: dup
    //   4357: invokespecial 421	java/lang/StringBuilder:<init>	()V
    //   4360: ldc_w 684
    //   4363: invokevirtual 427	java/lang/StringBuilder:append	(Ljava/lang/String;)Ljava/lang/StringBuilder;
    //   4366: aload 6
    //   4368: invokevirtual 430	java/lang/StringBuilder:append	(Ljava/lang/Object;)Ljava/lang/StringBuilder;
    //   4371: invokevirtual 433	java/lang/StringBuilder:toString	()Ljava/lang/String;
    //   4374: invokespecial 436	java/lang/IllegalArgumentException:<init>	(Ljava/lang/String;)V
    //   4377: athrow
    //   4378: new 418	java/lang/IllegalArgumentException
    //   4381: dup
    //   4382: new 420	java/lang/StringBuilder
    //   4385: dup
    //   4386: invokespecial 421	java/lang/StringBuilder:<init>	()V
    //   4389: ldc_w 686
    //   4392: invokevirtual 427	java/lang/StringBuilder:append	(Ljava/lang/String;)Ljava/lang/StringBuilder;
    //   4395: aload 6
    //   4397: invokevirtual 430	java/lang/StringBuilder:append	(Ljava/lang/Object;)Ljava/lang/StringBuilder;
    //   4400: invokevirtual 433	java/lang/StringBuilder:toString	()Ljava/lang/String;
    //   4403: invokespecial 436	java/lang/IllegalArgumentException:<init>	(Ljava/lang/String;)V
    //   4406: athrow
    //   4407: new 688	o/Mn
    //   4410: dup
    //   4411: aload_1
    //   4412: aload_2
    //   4413: invokespecial 689	o/Mn:<init>	(Lo/ˉ;Landroid/view/View;)V
    //   4416: areturn
    //   4417: new 446	java/lang/RuntimeException
    //   4420: dup
    //   4421: ldc_w 448
    //   4424: invokespecial 449	java/lang/RuntimeException:<init>	(Ljava/lang/String;)V
    //   4427: athrow
    //   4428: aload_2
    //   4429: invokevirtual 444	android/view/View:getTag	()Ljava/lang/Object;
    //   4432: astore 6
    //   4434: aload 6
    //   4436: ifnonnull +6 -> 4442
    //   4439: goto +3090 -> 7529
    //   4442: goto +1413 -> 5855
    //   4445: aload_2
    //   4446: invokevirtual 444	android/view/View:getTag	()Ljava/lang/Object;
    //   4449: astore 6
    //   4451: aload 6
    //   4453: ifnonnull +6 -> 4459
    //   4456: goto -3505 -> 951
    //   4459: goto -1137 -> 3322
    //   4462: new 446	java/lang/RuntimeException
    //   4465: dup
    //   4466: ldc_w 448
    //   4469: invokespecial 449	java/lang/RuntimeException:<init>	(Ljava/lang/String;)V
    //   4472: athrow
    //   4473: ldc_w 330
    //   4476: aload 6
    //   4478: invokevirtual 133	java/lang/String:equals	(Ljava/lang/Object;)Z
    //   4481: ifeq +6 -> 4487
    //   4484: goto +57 -> 4541
    //   4487: goto -1423 -> 3064
    //   4490: aload_2
    //   4491: invokevirtual 444	android/view/View:getTag	()Ljava/lang/Object;
    //   4494: astore 6
    //   4496: aload 6
    //   4498: ifnonnull +6 -> 4504
    //   4501: goto +1769 -> 6270
    //   4504: goto -1457 -> 3047
    //   4507: aload_2
    //   4508: invokevirtual 444	android/view/View:getTag	()Ljava/lang/Object;
    //   4511: astore 6
    //   4513: aload 6
    //   4515: ifnonnull +6 -> 4521
    //   4518: goto -3525 -> 993
    //   4521: goto +4004 -> 8525
    //   4524: aload_2
    //   4525: invokevirtual 444	android/view/View:getTag	()Ljava/lang/Object;
    //   4528: astore 6
    //   4530: aload 6
    //   4532: ifnonnull +6 -> 4538
    //   4535: goto +3072 -> 7607
    //   4538: goto -891 -> 3647
    //   4541: new 691	o/Kd
    //   4544: dup
    //   4545: aload_1
    //   4546: aload_2
    //   4547: invokespecial 692	o/Kd:<init>	(Lo/ˉ;Landroid/view/View;)V
    //   4550: areturn
    //   4551: new 446	java/lang/RuntimeException
    //   4554: dup
    //   4555: ldc_w 448
    //   4558: invokespecial 449	java/lang/RuntimeException:<init>	(Ljava/lang/String;)V
    //   4561: athrow
    //   4562: new 418	java/lang/IllegalArgumentException
    //   4565: dup
    //   4566: new 420	java/lang/StringBuilder
    //   4569: dup
    //   4570: invokespecial 421	java/lang/StringBuilder:<init>	()V
    //   4573: ldc_w 694
    //   4576: invokevirtual 427	java/lang/StringBuilder:append	(Ljava/lang/String;)Ljava/lang/StringBuilder;
    //   4579: aload 6
    //   4581: invokevirtual 430	java/lang/StringBuilder:append	(Ljava/lang/Object;)Ljava/lang/StringBuilder;
    //   4584: invokevirtual 433	java/lang/StringBuilder:toString	()Ljava/lang/String;
    //   4587: invokespecial 436	java/lang/IllegalArgumentException:<init>	(Ljava/lang/String;)V
    //   4590: athrow
    //   4591: aload_2
    //   4592: invokevirtual 444	android/view/View:getTag	()Ljava/lang/Object;
    //   4595: astore 6
    //   4597: aload 6
    //   4599: ifnonnull +6 -> 4605
    //   4602: goto +2254 -> 6856
    //   4605: goto +3029 -> 7634
    //   4608: new 446	java/lang/RuntimeException
    //   4611: dup
    //   4612: ldc_w 448
    //   4615: invokespecial 449	java/lang/RuntimeException:<init>	(Ljava/lang/String;)V
    //   4618: athrow
    //   4619: getstatic 17	o/cOn:ˋ	I
    //   4622: bipush 23
    //   4624: iadd
    //   4625: istore_3
    //   4626: iload_3
    //   4627: sipush 128
    //   4630: irem
    //   4631: putstatic 15	o/cOn:ˏ	I
    //   4634: iload_3
    //   4635: iconst_2
    //   4636: irem
    //   4637: ifeq +6 -> 4643
    //   4640: goto -4292 -> 348
    //   4643: goto -3655 -> 988
    //   4646: ldc_w 390
    //   4649: aload 6
    //   4651: invokevirtual 133	java/lang/String:equals	(Ljava/lang/Object;)Z
    //   4654: ifeq +6 -> 4660
    //   4657: goto +1358 -> 6015
    //   4660: goto -3331 -> 1329
    //   4663: ldc -118
    //   4665: aload 6
    //   4667: invokevirtual 133	java/lang/String:equals	(Ljava/lang/Object;)Z
    //   4670: ifeq +6 -> 4676
    //   4673: goto +1657 -> 6330
    //   4676: goto +824 -> 5500
    //   4679: new 696	o/LF
    //   4682: dup
    //   4683: aload_1
    //   4684: aload_2
    //   4685: invokespecial 697	o/LF:<init>	(Lo/ˉ;Landroid/view/View;)V
    //   4688: areturn
    //   4689: iload_3
    //   4690: tableswitch	default:+714->5404, 2131427355:+-183->4507, 2131427356:+-3106->1584, 2131427357:+-2666->2024, 2131427358:+-3922->768, 2131427359:+2149->6839, 2131427360:+-2428->2262, 2131427361:+2206->6896, 2131427362:+-3949->741, 2131427363:+2535->7225, 2131427364:+-4396->294, 2131427365:+-838->3852, 2131427366:+-2243->2447, 2131427367:+3113->7803, 2131427368:+-2738->1952, 2131427369:+-2467->2223, 2131427370:+-2484->2206, 2131427371:+3096->7786, 2131427372:+-3615->1075, 2131427373:+1530->6220, 2131427374:+1148->5838, 2131427375:+-487->4203, 2131427376:+1503->6193, 2131427377:+1192->5882, 2131427378:+-390->4300, 2131427379:+-2226->2464, 2131427380:+2981->7671, 2131427381:+1408->6098, 2131427382:+1076->5766, 2131427383:+-4012->678, 2131427384:+-1513->3177, 2131427385:+-4138->552, 2131427386:+-436->4254, 2131427387:+2116->6806, 2131427388:+1335->6025, 2131427389:+-4267->423, 2131427390:+1425->6115, 2131427391:+2458->7148, 2131427392:+2456->7146, 2131427393:+1131->5821, 2131427394:+2456->7146, 2131427395:+2456->7146, 2131427396:+2456->7146, 2131427397:+2456->7146, 2131427398:+2456->7146, 2131427399:+2456->7146, 2131427400:+2456->7146, 2131427401:+2456->7146, 2131427402:+2456->7146, 2131427403:+2456->7146, 2131427404:+2456->7146, 2131427405:+2456->7146, 2131427406:+2456->7146, 2131427407:+2456->7146, 2131427408:+2456->7146, 2131427409:+2456->7146, 2131427410:+2456->7146, 2131427411:+2456->7146, 2131427412:+1469->6159, 2131427413:+2580->7270, 2131427414:+-4446->244, 2131427415:+3398->8088, 2131427416:+-4474->216, 2131427417:+-1459->3231, 2131427418:+-2031->2659, 2131427419:+3159->7849, 2131427420:+2456->7146, 2131427421:+2749->7439, 2131427422:+-3248->1442, 2131427423:+-3995->695, 2131427424:+1887->6577, 2131427425:+-1957->2733, 2131427426:+930->5620, 2131427427:+-2985->1705, 2131427428:+1915->6605, 2131427429:+-166->4524, 2131427430:+-4175->515, 2131427431:+-1974->2716, 2131427432:+2822->7512, 2131427433:+2889->7579, 2131427434:+2456->7146, 2131427435:+2456->7146, 2131427436:+2456->7146, 2131427437:+2456->7146, 2131427438:+2456->7146, 2131427439:+2456->7146, 2131427440:+2456->7146, 2131427441:+2456->7146, 2131427442:+2456->7146, 2131427443:+2456->7146, 2131427444:+2456->7146, 2131427445:+2456->7146, 2131427446:+2456->7146, 2131427447:+2456->7146, 2131427448:+2456->7146, 2131427449:+2456->7146, 2131427450:+2456->7146, 2131427451:+2456->7146, 2131427452:+2456->7146, 2131427453:+2456->7146, 2131427454:+2456->7146, 2131427455:+2456->7146, 2131427456:+2456->7146, 2131427457:+2456->7146, 2131427458:+2456->7146, 2131427459:+2456->7146, 2131427460:+2456->7146, 2131427461:+2456->7146, 2131427462:+2456->7146, 2131427463:+2456->7146, 2131427464:+2456->7146, 2131427465:+2456->7146, 2131427466:+2456->7146, 2131427467:+2456->7146, 2131427468:+2456->7146, 2131427469:+2456->7146, 2131427470:+2456->7146, 2131427471:+2456->7146, 2131427472:+2456->7146, 2131427473:+2456->7146, 2131427474:+2456->7146, 2131427475:+2456->7146, 2131427476:+2456->7146, 2131427477:+2456->7146, 2131427478:+2456->7146, 2131427479:+2456->7146, 2131427480:+2456->7146, 2131427481:+2456->7146, 2131427482:+2456->7146, 2131427483:+2456->7146, 2131427484:+2456->7146, 2131427485:+2456->7146, 2131427486:+2456->7146, 2131427487:+2456->7146, 2131427488:+2456->7146, 2131427489:+2456->7146, 2131427490:+2456->7146, 2131427491:+2456->7146, 2131427492:+2456->7146, 2131427493:+2456->7146, 2131427494:+2456->7146, 2131427495:+2456->7146, 2131427496:+-1732->2958, 2131427497:+2456->7146, 2131427498:+1563->6253, 2131427499:+3371->8061, 2131427500:+-4229->461, 2131427501:+3354->8044, 2131427502:+-999->3691, 2131427503:+-1199->3491, 2131427504:+-4580->110, 2131427505:+-245->4445, 2131427506:+-200->4490, 2131427507:+-1586->3104, 2131427508:+-1841->2849, 2131427509:+-453->4237, 2131427510:+3668->8358, 2131427511:+-3643->1047, 2131427512:+-4121->569, 2131427513:+1059->5749, 2131427514:+-99->4591, 2131427515:+1829->6519, 2131427516:+-4058->632, 2131427517:+1774->6464, 2131427518:+1442->6132, 2131427519:+2223->6913, 2131427520:+-262->4428, 2131427521:+-4629->61, 2131427522:+2017->6707, 2131427523:+-583->4107, 2131427524:+-2810->1880, 2131427525:+-2122->2568, 2131427526:+-3883->807, 2131427527:+1042->5732, 2131427528:+748->5438, 2131427529:+2766->7456
    //   5404: goto +1742 -> 7146
    //   5407: new 446	java/lang/RuntimeException
    //   5410: dup
    //   5411: ldc_w 448
    //   5414: invokespecial 449	java/lang/RuntimeException:<init>	(Ljava/lang/String;)V
    //   5417: athrow
    //   5418: goto +1981 -> 7399
    //   5421: ldc_w 334
    //   5424: aload 6
    //   5426: invokevirtual 133	java/lang/String:equals	(Ljava/lang/Object;)Z
    //   5429: ifeq +6 -> 5435
    //   5432: goto +3062 -> 8494
    //   5435: goto -4038 -> 1397
    //   5438: aload_2
    //   5439: invokevirtual 444	android/view/View:getTag	()Ljava/lang/Object;
    //   5442: astore 6
    //   5444: aload 6
    //   5446: ifnonnull +6 -> 5452
    //   5449: goto -2356 -> 3093
    //   5452: goto -979 -> 4473
    //   5455: ldc -111
    //   5457: aload 6
    //   5459: invokevirtual 133	java/lang/String:equals	(Ljava/lang/Object;)Z
    //   5462: ifeq +6 -> 5468
    //   5465: goto +1700 -> 7165
    //   5468: goto -2083 -> 3385
    //   5471: new 418	java/lang/IllegalArgumentException
    //   5474: dup
    //   5475: new 420	java/lang/StringBuilder
    //   5478: dup
    //   5479: invokespecial 421	java/lang/StringBuilder:<init>	()V
    //   5482: ldc_w 699
    //   5485: invokevirtual 427	java/lang/StringBuilder:append	(Ljava/lang/String;)Ljava/lang/StringBuilder;
    //   5488: aload 6
    //   5490: invokevirtual 430	java/lang/StringBuilder:append	(Ljava/lang/Object;)Ljava/lang/StringBuilder;
    //   5493: invokevirtual 433	java/lang/StringBuilder:toString	()Ljava/lang/String;
    //   5496: invokespecial 436	java/lang/IllegalArgumentException:<init>	(Ljava/lang/String;)V
    //   5499: athrow
    //   5500: new 418	java/lang/IllegalArgumentException
    //   5503: dup
    //   5504: new 420	java/lang/StringBuilder
    //   5507: dup
    //   5508: invokespecial 421	java/lang/StringBuilder:<init>	()V
    //   5511: ldc_w 701
    //   5514: invokevirtual 427	java/lang/StringBuilder:append	(Ljava/lang/String;)Ljava/lang/StringBuilder;
    //   5517: aload 6
    //   5519: invokevirtual 430	java/lang/StringBuilder:append	(Ljava/lang/Object;)Ljava/lang/StringBuilder;
    //   5522: invokevirtual 433	java/lang/StringBuilder:toString	()Ljava/lang/String;
    //   5525: invokespecial 436	java/lang/IllegalArgumentException:<init>	(Ljava/lang/String;)V
    //   5528: athrow
    //   5529: new 418	java/lang/IllegalArgumentException
    //   5532: dup
    //   5533: new 420	java/lang/StringBuilder
    //   5536: dup
    //   5537: invokespecial 421	java/lang/StringBuilder:<init>	()V
    //   5540: ldc_w 703
    //   5543: invokevirtual 427	java/lang/StringBuilder:append	(Ljava/lang/String;)Ljava/lang/StringBuilder;
    //   5546: aload 6
    //   5548: invokevirtual 430	java/lang/StringBuilder:append	(Ljava/lang/Object;)Ljava/lang/StringBuilder;
    //   5551: invokevirtual 433	java/lang/StringBuilder:toString	()Ljava/lang/String;
    //   5554: invokespecial 436	java/lang/IllegalArgumentException:<init>	(Ljava/lang/String;)V
    //   5557: athrow
    //   5558: new 705	o/MU
    //   5561: dup
    //   5562: aload_1
    //   5563: aload_2
    //   5564: invokespecial 706	o/MU:<init>	(Lo/ˉ;Landroid/view/View;)V
    //   5567: areturn
    //   5568: new 446	java/lang/RuntimeException
    //   5571: dup
    //   5572: ldc_w 448
    //   5575: invokespecial 449	java/lang/RuntimeException:<init>	(Ljava/lang/String;)V
    //   5578: athrow
    //   5579: new 708	o/GO
    //   5582: dup
    //   5583: aload_1
    //   5584: aload_2
    //   5585: invokespecial 709	o/GO:<init>	(Lo/ˉ;Landroid/view/View;)V
    //   5588: astore_1
    //   5589: goto -970 -> 4619
    //   5592: new 446	java/lang/RuntimeException
    //   5595: dup
    //   5596: ldc_w 448
    //   5599: invokespecial 449	java/lang/RuntimeException:<init>	(Ljava/lang/String;)V
    //   5602: athrow
    //   5603: ldc_w 366
    //   5606: aload 6
    //   5608: invokevirtual 133	java/lang/String:equals	(Ljava/lang/Object;)Z
    //   5611: ifeq +6 -> 5617
    //   5614: goto -4713 -> 901
    //   5617: goto +1370 -> 6987
    //   5620: aload_2
    //   5621: invokevirtual 444	android/view/View:getTag	()Ljava/lang/Object;
    //   5624: astore 6
    //   5626: aload 6
    //   5628: ifnonnull +6 -> 5634
    //   5631: goto +1870 -> 7501
    //   5634: goto -4437 -> 1197
    //   5637: bipush 30
    //   5639: iconst_0
    //   5640: ldc -66
    //   5642: invokestatic 192	o/cOn:ˋ	(IIC)Ljava/lang/String;
    //   5645: invokevirtual 196	java/lang/String:intern	()Ljava/lang/String;
    //   5648: aload 6
    //   5650: invokevirtual 133	java/lang/String:equals	(Ljava/lang/Object;)Z
    //   5653: ifeq +6 -> 5659
    //   5656: goto +1913 -> 7569
    //   5659: goto -4180 -> 1479
    //   5662: new 711	o/JJ
    //   5665: dup
    //   5666: aload_1
    //   5667: aload_2
    //   5668: invokespecial 712	o/JJ:<init>	(Lo/ˉ;Landroid/view/View;)V
    //   5671: areturn
    //   5672: new 446	java/lang/RuntimeException
    //   5675: dup
    //   5676: ldc_w 448
    //   5679: invokespecial 449	java/lang/RuntimeException:<init>	(Ljava/lang/String;)V
    //   5682: athrow
    //   5683: new 714	o/Dw
    //   5686: dup
    //   5687: aload_1
    //   5688: aload_2
    //   5689: invokespecial 715	o/Dw:<init>	(Lo/ˉ;Landroid/view/View;)V
    //   5692: areturn
    //   5693: new 717	o/MS
    //   5696: dup
    //   5697: aload_1
    //   5698: aload_2
    //   5699: invokespecial 718	o/MS:<init>	(Lo/ˉ;Landroid/view/View;)V
    //   5702: areturn
    //   5703: new 418	java/lang/IllegalArgumentException
    //   5706: dup
    //   5707: new 420	java/lang/StringBuilder
    //   5710: dup
    //   5711: invokespecial 421	java/lang/StringBuilder:<init>	()V
    //   5714: ldc_w 720
    //   5717: invokevirtual 427	java/lang/StringBuilder:append	(Ljava/lang/String;)Ljava/lang/StringBuilder;
    //   5720: aload 6
    //   5722: invokevirtual 430	java/lang/StringBuilder:append	(Ljava/lang/Object;)Ljava/lang/StringBuilder;
    //   5725: invokevirtual 433	java/lang/StringBuilder:toString	()Ljava/lang/String;
    //   5728: invokespecial 436	java/lang/IllegalArgumentException:<init>	(Ljava/lang/String;)V
    //   5731: athrow
    //   5732: aload_2
    //   5733: invokevirtual 444	android/view/View:getTag	()Ljava/lang/Object;
    //   5736: astore 6
    //   5738: aload 6
    //   5740: ifnonnull +6 -> 5746
    //   5743: goto -5265 -> 478
    //   5746: goto -4201 -> 1545
    //   5749: aload_2
    //   5750: invokevirtual 444	android/view/View:getTag	()Ljava/lang/Object;
    //   5753: astore 6
    //   5755: aload 6
    //   5757: ifnonnull +6 -> 5763
    //   5760: goto -1834 -> 3926
    //   5763: goto +2114 -> 7877
    //   5766: aload_2
    //   5767: invokevirtual 444	android/view/View:getTag	()Ljava/lang/Object;
    //   5770: astore 6
    //   5772: aload 6
    //   5774: ifnonnull +6 -> 5780
    //   5777: goto -5337 -> 440
    //   5780: goto -1900 -> 3880
    //   5783: new 722	o/Mx
    //   5786: dup
    //   5787: aload_1
    //   5788: aload_2
    //   5789: invokespecial 723	o/Mx:<init>	(Lo/ˉ;Landroid/view/View;)V
    //   5792: areturn
    //   5793: new 446	java/lang/RuntimeException
    //   5796: dup
    //   5797: ldc_w 448
    //   5800: invokespecial 449	java/lang/RuntimeException:<init>	(Ljava/lang/String;)V
    //   5803: athrow
    //   5804: ldc_w 293
    //   5807: aload 6
    //   5809: invokevirtual 133	java/lang/String:equals	(Ljava/lang/Object;)Z
    //   5812: ifeq +6 -> 5818
    //   5815: goto -4214 -> 1601
    //   5818: goto +906 -> 6724
    //   5821: aload_2
    //   5822: invokevirtual 444	android/view/View:getTag	()Ljava/lang/Object;
    //   5825: astore 6
    //   5827: aload 6
    //   5829: ifnonnull +6 -> 5835
    //   5832: goto -2279 -> 3553
    //   5835: goto -3036 -> 2799
    //   5838: aload_2
    //   5839: invokevirtual 444	android/view/View:getTag	()Ljava/lang/Object;
    //   5842: astore 6
    //   5844: aload 6
    //   5846: ifnonnull +6 -> 5852
    //   5849: goto -2185 -> 3664
    //   5852: goto -2691 -> 3161
    //   5855: ldc_w 403
    //   5858: aload 6
    //   5860: invokevirtual 133	java/lang/String:equals	(Ljava/lang/Object;)Z
    //   5863: ifeq +6 -> 5869
    //   5866: goto +691 -> 6557
    //   5869: goto -2277 -> 3592
    //   5872: new 725	o/LK
    //   5875: dup
    //   5876: aload_1
    //   5877: aload_2
    //   5878: invokespecial 726	o/LK:<init>	(Lo/ˉ;Landroid/view/View;)V
    //   5881: areturn
    //   5882: aload_2
    //   5883: invokevirtual 444	android/view/View:getTag	()Ljava/lang/Object;
    //   5886: astore 6
    //   5888: aload 6
    //   5890: ifnonnull +6 -> 5896
    //   5893: goto +2579 -> 8472
    //   5896: goto +92 -> 5988
    //   5899: new 418	java/lang/IllegalArgumentException
    //   5902: dup
    //   5903: new 420	java/lang/StringBuilder
    //   5906: dup
    //   5907: invokespecial 421	java/lang/StringBuilder:<init>	()V
    //   5910: ldc_w 728
    //   5913: invokevirtual 427	java/lang/StringBuilder:append	(Ljava/lang/String;)Ljava/lang/StringBuilder;
    //   5916: aload 6
    //   5918: invokevirtual 430	java/lang/StringBuilder:append	(Ljava/lang/Object;)Ljava/lang/StringBuilder;
    //   5921: invokevirtual 433	java/lang/StringBuilder:toString	()Ljava/lang/String;
    //   5924: invokespecial 436	java/lang/IllegalArgumentException:<init>	(Ljava/lang/String;)V
    //   5927: athrow
    //   5928: new 418	java/lang/IllegalArgumentException
    //   5931: dup
    //   5932: new 420	java/lang/StringBuilder
    //   5935: dup
    //   5936: invokespecial 421	java/lang/StringBuilder:<init>	()V
    //   5939: ldc_w 730
    //   5942: invokevirtual 427	java/lang/StringBuilder:append	(Ljava/lang/String;)Ljava/lang/StringBuilder;
    //   5945: aload 6
    //   5947: invokevirtual 430	java/lang/StringBuilder:append	(Ljava/lang/Object;)Ljava/lang/StringBuilder;
    //   5950: invokevirtual 433	java/lang/StringBuilder:toString	()Ljava/lang/String;
    //   5953: invokespecial 436	java/lang/IllegalArgumentException:<init>	(Ljava/lang/String;)V
    //   5956: athrow
    //   5957: new 732	o/JH
    //   5960: dup
    //   5961: aload_1
    //   5962: aload_2
    //   5963: invokespecial 733	o/JH:<init>	(Lo/ˉ;Landroid/view/View;)V
    //   5966: areturn
    //   5967: new 735	o/MQ
    //   5970: dup
    //   5971: aload_1
    //   5972: aload_2
    //   5973: invokespecial 736	o/MQ:<init>	(Lo/ˉ;Landroid/view/View;)V
    //   5976: areturn
    //   5977: new 446	java/lang/RuntimeException
    //   5980: dup
    //   5981: ldc_w 448
    //   5984: invokespecial 449	java/lang/RuntimeException:<init>	(Ljava/lang/String;)V
    //   5987: athrow
    //   5988: ldc -87
    //   5990: aload 6
    //   5992: invokevirtual 133	java/lang/String:equals	(Ljava/lang/Object;)Z
    //   5995: ifeq +6 -> 6001
    //   5998: goto -3248 -> 2750
    //   6001: goto +349 -> 6350
    //   6004: new 446	java/lang/RuntimeException
    //   6007: dup
    //   6008: ldc_w 448
    //   6011: invokespecial 449	java/lang/RuntimeException:<init>	(Ljava/lang/String;)V
    //   6014: athrow
    //   6015: new 738	o/LD
    //   6018: dup
    //   6019: aload_1
    //   6020: aload_2
    //   6021: invokespecial 739	o/LD:<init>	(Lo/ˉ;Landroid/view/View;)V
    //   6024: areturn
    //   6025: aload_2
    //   6026: invokevirtual 444	android/view/View:getTag	()Ljava/lang/Object;
    //   6029: astore 6
    //   6031: aload 6
    //   6033: ifnonnull +6 -> 6039
    //   6036: goto -4735 -> 1301
    //   6039: goto +2171 -> 8210
    //   6042: ldc_w 301
    //   6045: aload 6
    //   6047: invokevirtual 133	java/lang/String:equals	(Ljava/lang/Object;)Z
    //   6050: ifeq +6 -> 6056
    //   6053: goto -4839 -> 1214
    //   6056: goto -2717 -> 3339
    //   6059: new 418	java/lang/IllegalArgumentException
    //   6062: dup
    //   6063: new 420	java/lang/StringBuilder
    //   6066: dup
    //   6067: invokespecial 421	java/lang/StringBuilder:<init>	()V
    //   6070: ldc_w 741
    //   6073: invokevirtual 427	java/lang/StringBuilder:append	(Ljava/lang/String;)Ljava/lang/StringBuilder;
    //   6076: aload 6
    //   6078: invokevirtual 430	java/lang/StringBuilder:append	(Ljava/lang/Object;)Ljava/lang/StringBuilder;
    //   6081: invokevirtual 433	java/lang/StringBuilder:toString	()Ljava/lang/String;
    //   6084: invokespecial 436	java/lang/IllegalArgumentException:<init>	(Ljava/lang/String;)V
    //   6087: athrow
    //   6088: new 743	o/GS
    //   6091: dup
    //   6092: aload_1
    //   6093: aload_2
    //   6094: invokespecial 744	o/GS:<init>	(Lo/ˉ;Landroid/view/View;)V
    //   6097: areturn
    //   6098: aload_2
    //   6099: invokevirtual 444	android/view/View:getTag	()Ljava/lang/Object;
    //   6102: astore 6
    //   6104: aload 6
    //   6106: ifnonnull +6 -> 6112
    //   6109: goto -1558 -> 4551
    //   6112: goto -3171 -> 2941
    //   6115: aload_2
    //   6116: invokevirtual 444	android/view/View:getTag	()Ljava/lang/Object;
    //   6119: astore 6
    //   6121: aload 6
    //   6123: ifnonnull +6 -> 6129
    //   6126: goto -2040 -> 4086
    //   6129: goto +407 -> 6536
    //   6132: aload_2
    //   6133: invokevirtual 444	android/view/View:getTag	()Ljava/lang/Object;
    //   6136: astore 6
    //   6138: aload 6
    //   6140: ifnonnull +6 -> 6146
    //   6143: goto -3467 -> 2676
    //   6146: goto +909 -> 7055
    //   6149: new 746	o/LA
    //   6152: dup
    //   6153: aload_1
    //   6154: aload_2
    //   6155: invokespecial 747	o/LA:<init>	(Lo/ˉ;Landroid/view/View;)V
    //   6158: areturn
    //   6159: aload_2
    //   6160: invokevirtual 444	android/view/View:getTag	()Ljava/lang/Object;
    //   6163: astore 6
    //   6165: aload 6
    //   6167: ifnonnull +6 -> 6173
    //   6170: goto -602 -> 5568
    //   6173: goto -5684 -> 489
    //   6176: ldc_w 306
    //   6179: aload 6
    //   6181: invokevirtual 133	java/lang/String:equals	(Ljava/lang/Object;)Z
    //   6184: ifeq +6 -> 6190
    //   6187: goto -4245 -> 1942
    //   6190: goto +1567 -> 7757
    //   6193: aload_2
    //   6194: invokevirtual 444	android/view/View:getTag	()Ljava/lang/Object;
    //   6197: astore 6
    //   6199: aload 6
    //   6201: ifnonnull +6 -> 6207
    //   6204: goto -3706 -> 2498
    //   6207: goto +172 -> 6379
    //   6210: new 749	o/GU
    //   6213: dup
    //   6214: aload_1
    //   6215: aload_2
    //   6216: invokespecial 750	o/GU:<init>	(Lo/ˉ;Landroid/view/View;)V
    //   6219: areturn
    //   6220: aload_2
    //   6221: invokevirtual 444	android/view/View:getTag	()Ljava/lang/Object;
    //   6224: astore 6
    //   6226: aload 6
    //   6228: ifnonnull +6 -> 6234
    //   6231: goto -3021 -> 3210
    //   6234: goto -5053 -> 1181
    //   6237: ldc -52
    //   6239: aload 6
    //   6241: invokevirtual 133	java/lang/String:equals	(Ljava/lang/Object;)Z
    //   6244: ifeq +6 -> 6250
    //   6247: goto +1831 -> 8078
    //   6250: goto -1979 -> 4271
    //   6253: aload_2
    //   6254: invokevirtual 444	android/view/View:getTag	()Ljava/lang/Object;
    //   6257: astore 6
    //   6259: aload 6
    //   6261: ifnonnull +6 -> 6267
    //   6264: goto -471 -> 5793
    //   6267: goto +1838 -> 8105
    //   6270: new 446	java/lang/RuntimeException
    //   6273: dup
    //   6274: ldc_w 448
    //   6277: invokespecial 449	java/lang/RuntimeException:<init>	(Ljava/lang/String;)V
    //   6280: athrow
    //   6281: new 752	o/JX
    //   6284: dup
    //   6285: aload_1
    //   6286: aload_2
    //   6287: invokespecial 753	o/JX:<init>	(Lo/ˉ;Landroid/view/View;)V
    //   6290: areturn
    //   6291: new 418	java/lang/IllegalArgumentException
    //   6294: dup
    //   6295: new 420	java/lang/StringBuilder
    //   6298: dup
    //   6299: invokespecial 421	java/lang/StringBuilder:<init>	()V
    //   6302: ldc_w 755
    //   6305: invokevirtual 427	java/lang/StringBuilder:append	(Ljava/lang/String;)Ljava/lang/StringBuilder;
    //   6308: aload 6
    //   6310: invokevirtual 430	java/lang/StringBuilder:append	(Ljava/lang/Object;)Ljava/lang/StringBuilder;
    //   6313: invokevirtual 433	java/lang/StringBuilder:toString	()Ljava/lang/String;
    //   6316: invokespecial 436	java/lang/IllegalArgumentException:<init>	(Ljava/lang/String;)V
    //   6319: athrow
    //   6320: new 757	o/JQ
    //   6323: dup
    //   6324: aload_1
    //   6325: aload_2
    //   6326: invokespecial 758	o/JQ:<init>	(Lo/ˉ;Landroid/view/View;)V
    //   6329: areturn
    //   6330: new 760	o/JO
    //   6333: dup
    //   6334: aload_1
    //   6335: aload_2
    //   6336: invokespecial 761	o/JO:<init>	(Lo/ˉ;Landroid/view/View;)V
    //   6339: areturn
    //   6340: new 763	o/LM
    //   6343: dup
    //   6344: aload_1
    //   6345: aload_2
    //   6346: invokespecial 764	o/LM:<init>	(Lo/ˉ;Landroid/view/View;)V
    //   6349: areturn
    //   6350: new 418	java/lang/IllegalArgumentException
    //   6353: dup
    //   6354: new 420	java/lang/StringBuilder
    //   6357: dup
    //   6358: invokespecial 421	java/lang/StringBuilder:<init>	()V
    //   6361: ldc_w 766
    //   6364: invokevirtual 427	java/lang/StringBuilder:append	(Ljava/lang/String;)Ljava/lang/StringBuilder;
    //   6367: aload 6
    //   6369: invokevirtual 430	java/lang/StringBuilder:append	(Ljava/lang/Object;)Ljava/lang/StringBuilder;
    //   6372: invokevirtual 433	java/lang/StringBuilder:toString	()Ljava/lang/String;
    //   6375: invokespecial 436	java/lang/IllegalArgumentException:<init>	(Ljava/lang/String;)V
    //   6378: athrow
    //   6379: ldc -32
    //   6381: aload 6
    //   6383: invokevirtual 133	java/lang/String:equals	(Ljava/lang/Object;)Z
    //   6386: ifeq +6 -> 6392
    //   6389: goto -240 -> 6149
    //   6392: goto -3705 -> 2687
    //   6395: new 768	o/GP
    //   6398: dup
    //   6399: aload_1
    //   6400: aload_2
    //   6401: invokespecial 769	o/GP:<init>	(Lo/ˉ;Landroid/view/View;)V
    //   6404: areturn
    //   6405: ldc_w 340
    //   6408: aload 6
    //   6410: invokevirtual 133	java/lang/String:equals	(Ljava/lang/Object;)Z
    //   6413: ifeq +6 -> 6419
    //   6416: goto -3656 -> 2760
    //   6419: goto +1121 -> 7540
    //   6422: new 446	java/lang/RuntimeException
    //   6425: dup
    //   6426: ldc_w 448
    //   6429: invokespecial 449	java/lang/RuntimeException:<init>	(Ljava/lang/String;)V
    //   6432: athrow
    //   6433: new 420	java/lang/StringBuilder
    //   6436: dup
    //   6437: invokespecial 421	java/lang/StringBuilder:<init>	()V
    //   6440: astore_1
    //   6441: new 418	java/lang/IllegalArgumentException
    //   6444: dup
    //   6445: aload_1
    //   6446: ldc_w 771
    //   6449: invokevirtual 427	java/lang/StringBuilder:append	(Ljava/lang/String;)Ljava/lang/StringBuilder;
    //   6452: aload 6
    //   6454: invokevirtual 430	java/lang/StringBuilder:append	(Ljava/lang/Object;)Ljava/lang/StringBuilder;
    //   6457: invokevirtual 433	java/lang/StringBuilder:toString	()Ljava/lang/String;
    //   6460: invokespecial 436	java/lang/IllegalArgumentException:<init>	(Ljava/lang/String;)V
    //   6463: athrow
    //   6464: aload_2
    //   6465: invokevirtual 444	android/view/View:getTag	()Ljava/lang/Object;
    //   6468: astore 6
    //   6470: aload 6
    //   6472: ifnonnull +6 -> 6478
    //   6475: goto -471 -> 6004
    //   6478: goto -841 -> 5637
    //   6481: new 446	java/lang/RuntimeException
    //   6484: dup
    //   6485: ldc_w 448
    //   6488: invokespecial 449	java/lang/RuntimeException:<init>	(Ljava/lang/String;)V
    //   6491: athrow
    //   6492: ldc_w 376
    //   6495: aload 6
    //   6497: invokevirtual 133	java/lang/String:equals	(Ljava/lang/Object;)Z
    //   6500: ifeq +6 -> 6506
    //   6503: goto -2690 -> 3813
    //   6506: goto -2609 -> 3897
    //   6509: new 773	o/Ls
    //   6512: dup
    //   6513: aload_1
    //   6514: aload_2
    //   6515: invokespecial 774	o/Ls:<init>	(Lo/ˉ;Landroid/view/View;)V
    //   6518: areturn
    //   6519: aload_2
    //   6520: invokevirtual 444	android/view/View:getTag	()Ljava/lang/Object;
    //   6523: astore 6
    //   6525: aload 6
    //   6527: ifnonnull +6 -> 6533
    //   6530: goto -6147 -> 383
    //   6533: goto -3119 -> 3414
    //   6536: ldc_w 408
    //   6539: aload 6
    //   6541: invokevirtual 133	java/lang/String:equals	(Ljava/lang/Object;)Z
    //   6544: istore 5
    //   6546: iload 5
    //   6548: ifeq +6 -> 6554
    //   6551: goto +1964 -> 8515
    //   6554: goto +1879 -> 8433
    //   6557: new 776	o/Ke
    //   6560: dup
    //   6561: aload_1
    //   6562: aload_2
    //   6563: invokespecial 777	o/Ke:<init>	(Lo/ˉ;Landroid/view/View;)V
    //   6566: areturn
    //   6567: new 779	o/Mu
    //   6570: dup
    //   6571: aload_1
    //   6572: aload_2
    //   6573: invokespecial 780	o/Mu:<init>	(Lo/ˉ;Landroid/view/View;)V
    //   6576: areturn
    //   6577: aload_2
    //   6578: invokevirtual 444	android/view/View:getTag	()Ljava/lang/Object;
    //   6581: astore 6
    //   6583: aload 6
    //   6585: ifnonnull +6 -> 6591
    //   6588: goto +626 -> 7214
    //   6591: goto +1369 -> 7960
    //   6594: new 446	java/lang/RuntimeException
    //   6597: dup
    //   6598: ldc_w 448
    //   6601: invokespecial 449	java/lang/RuntimeException:<init>	(Ljava/lang/String;)V
    //   6604: athrow
    //   6605: aload_2
    //   6606: invokevirtual 444	android/view/View:getTag	()Ljava/lang/Object;
    //   6609: astore 6
    //   6611: aload 6
    //   6613: ifnonnull +6 -> 6619
    //   6616: goto -194 -> 6422
    //   6619: goto -4930 -> 1689
    //   6622: new 782	o/LH
    //   6625: dup
    //   6626: aload_1
    //   6627: aload_2
    //   6628: invokespecial 783	o/LH:<init>	(Lo/ˉ;Landroid/view/View;)V
    //   6631: areturn
    //   6632: new 418	java/lang/IllegalArgumentException
    //   6635: dup
    //   6636: new 420	java/lang/StringBuilder
    //   6639: dup
    //   6640: invokespecial 421	java/lang/StringBuilder:<init>	()V
    //   6643: ldc_w 785
    //   6646: invokevirtual 427	java/lang/StringBuilder:append	(Ljava/lang/String;)Ljava/lang/StringBuilder;
    //   6649: aload 6
    //   6651: invokevirtual 430	java/lang/StringBuilder:append	(Ljava/lang/Object;)Ljava/lang/StringBuilder;
    //   6654: invokevirtual 433	java/lang/StringBuilder:toString	()Ljava/lang/String;
    //   6657: invokespecial 436	java/lang/IllegalArgumentException:<init>	(Ljava/lang/String;)V
    //   6660: athrow
    //   6661: new 418	java/lang/IllegalArgumentException
    //   6664: dup
    //   6665: new 420	java/lang/StringBuilder
    //   6668: dup
    //   6669: invokespecial 421	java/lang/StringBuilder:<init>	()V
    //   6672: ldc_w 787
    //   6675: invokevirtual 427	java/lang/StringBuilder:append	(Ljava/lang/String;)Ljava/lang/StringBuilder;
    //   6678: aload 6
    //   6680: invokevirtual 430	java/lang/StringBuilder:append	(Ljava/lang/Object;)Ljava/lang/StringBuilder;
    //   6683: invokevirtual 433	java/lang/StringBuilder:toString	()Ljava/lang/String;
    //   6686: invokespecial 436	java/lang/IllegalArgumentException:<init>	(Ljava/lang/String;)V
    //   6689: athrow
    //   6690: ldc_w 271
    //   6693: aload 6
    //   6695: invokevirtual 133	java/lang/String:equals	(Ljava/lang/Object;)Z
    //   6698: ifeq +6 -> 6704
    //   6701: goto +435 -> 7136
    //   6704: goto -1233 -> 5471
    //   6707: aload_2
    //   6708: invokevirtual 444	android/view/View:getTag	()Ljava/lang/Object;
    //   6711: astore 6
    //   6713: aload 6
    //   6715: ifnonnull +6 -> 6721
    //   6718: goto -2401 -> 4317
    //   6721: goto -5897 -> 824
    //   6724: new 418	java/lang/IllegalArgumentException
    //   6727: dup
    //   6728: new 420	java/lang/StringBuilder
    //   6731: dup
    //   6732: invokespecial 421	java/lang/StringBuilder:<init>	()V
    //   6735: ldc_w 789
    //   6738: invokevirtual 427	java/lang/StringBuilder:append	(Ljava/lang/String;)Ljava/lang/StringBuilder;
    //   6741: aload 6
    //   6743: invokevirtual 430	java/lang/StringBuilder:append	(Ljava/lang/Object;)Ljava/lang/StringBuilder;
    //   6746: invokevirtual 433	java/lang/StringBuilder:toString	()Ljava/lang/String;
    //   6749: invokespecial 436	java/lang/IllegalArgumentException:<init>	(Ljava/lang/String;)V
    //   6752: athrow
    //   6753: goto -2064 -> 4689
    //   6756: new 446	java/lang/RuntimeException
    //   6759: dup
    //   6760: ldc_w 448
    //   6763: invokespecial 449	java/lang/RuntimeException:<init>	(Ljava/lang/String;)V
    //   6766: athrow
    //   6767: new 791	o/JW
    //   6770: dup
    //   6771: aload_1
    //   6772: aload_2
    //   6773: invokespecial 792	o/JW:<init>	(Lo/ˉ;Landroid/view/View;)V
    //   6776: areturn
    //   6777: new 418	java/lang/IllegalArgumentException
    //   6780: dup
    //   6781: new 420	java/lang/StringBuilder
    //   6784: dup
    //   6785: invokespecial 421	java/lang/StringBuilder:<init>	()V
    //   6788: ldc_w 794
    //   6791: invokevirtual 427	java/lang/StringBuilder:append	(Ljava/lang/String;)Ljava/lang/StringBuilder;
    //   6794: aload 6
    //   6796: invokevirtual 430	java/lang/StringBuilder:append	(Ljava/lang/Object;)Ljava/lang/StringBuilder;
    //   6799: invokevirtual 433	java/lang/StringBuilder:toString	()Ljava/lang/String;
    //   6802: invokespecial 436	java/lang/IllegalArgumentException:<init>	(Ljava/lang/String;)V
    //   6805: athrow
    //   6806: aload_2
    //   6807: invokevirtual 444	android/view/View:getTag	()Ljava/lang/Object;
    //   6810: astore 6
    //   6812: aload 6
    //   6814: ifnonnull +6 -> 6820
    //   6817: goto -6690 -> 127
    //   6820: goto -3283 -> 3537
    //   6823: ldc -101
    //   6825: aload 6
    //   6827: invokevirtual 133	java/lang/String:equals	(Ljava/lang/Object;)Z
    //   6830: ifeq +6 -> 6836
    //   6833: goto -5374 -> 1459
    //   6836: goto +1169 -> 8005
    //   6839: aload_2
    //   6840: invokevirtual 444	android/view/View:getTag	()Ljava/lang/Object;
    //   6843: astore 6
    //   6845: aload 6
    //   6847: ifnonnull +6 -> 6853
    //   6850: goto +521 -> 7371
    //   6853: goto +400 -> 7253
    //   6856: new 446	java/lang/RuntimeException
    //   6859: dup
    //   6860: ldc_w 448
    //   6863: invokespecial 449	java/lang/RuntimeException:<init>	(Ljava/lang/String;)V
    //   6866: athrow
    //   6867: new 796	o/Ha
    //   6870: dup
    //   6871: aload_1
    //   6872: aload_2
    //   6873: invokespecial 797	o/Ha:<init>	(Lo/ˉ;Landroid/view/View;)V
    //   6876: areturn
    //   6877: ldc -70
    //   6879: aload 6
    //   6881: invokevirtual 133	java/lang/String:equals	(Ljava/lang/Object;)Z
    //   6884: ifeq +6 -> 6890
    //   6887: goto -2480 -> 4407
    //   6890: goto -6178 -> 712
    //   6893: astore_1
    //   6894: aload_1
    //   6895: athrow
    //   6896: aload_2
    //   6897: invokevirtual 444	android/view/View:getTag	()Ljava/lang/Object;
    //   6900: astore 6
    //   6902: aload 6
    //   6904: ifnonnull +6 -> 6910
    //   6907: goto -3427 -> 3480
    //   6910: goto -5938 -> 972
    //   6913: aload_2
    //   6914: invokevirtual 444	android/view/View:getTag	()Ljava/lang/Object;
    //   6917: astore 6
    //   6919: aload 6
    //   6921: ifnonnull +6 -> 6927
    //   6924: goto -5169 -> 1755
    //   6927: goto -3159 -> 3768
    //   6930: ldc_w 381
    //   6933: aload 6
    //   6935: invokevirtual 133	java/lang/String:equals	(Ljava/lang/Object;)Z
    //   6938: ifeq +6 -> 6944
    //   6941: goto -5650 -> 1291
    //   6944: goto -4314 -> 2630
    //   6947: new 418	java/lang/IllegalArgumentException
    //   6950: dup
    //   6951: new 420	java/lang/StringBuilder
    //   6954: dup
    //   6955: invokespecial 421	java/lang/StringBuilder:<init>	()V
    //   6958: ldc_w 799
    //   6961: invokevirtual 427	java/lang/StringBuilder:append	(Ljava/lang/String;)Ljava/lang/StringBuilder;
    //   6964: aload 6
    //   6966: invokevirtual 430	java/lang/StringBuilder:append	(Ljava/lang/Object;)Ljava/lang/StringBuilder;
    //   6969: invokevirtual 433	java/lang/StringBuilder:toString	()Ljava/lang/String;
    //   6972: invokespecial 436	java/lang/IllegalArgumentException:<init>	(Ljava/lang/String;)V
    //   6975: athrow
    //   6976: new 446	java/lang/RuntimeException
    //   6979: dup
    //   6980: ldc_w 448
    //   6983: invokespecial 449	java/lang/RuntimeException:<init>	(Ljava/lang/String;)V
    //   6986: athrow
    //   6987: new 418	java/lang/IllegalArgumentException
    //   6990: dup
    //   6991: new 420	java/lang/StringBuilder
    //   6994: dup
    //   6995: invokespecial 421	java/lang/StringBuilder:<init>	()V
    //   6998: ldc_w 801
    //   7001: invokevirtual 427	java/lang/StringBuilder:append	(Ljava/lang/String;)Ljava/lang/StringBuilder;
    //   7004: aload 6
    //   7006: invokevirtual 430	java/lang/StringBuilder:append	(Ljava/lang/Object;)Ljava/lang/StringBuilder;
    //   7009: invokevirtual 433	java/lang/StringBuilder:toString	()Ljava/lang/String;
    //   7012: invokespecial 436	java/lang/IllegalArgumentException:<init>	(Ljava/lang/String;)V
    //   7015: athrow
    //   7016: new 803	o/GJ
    //   7019: dup
    //   7020: aload_1
    //   7021: aload_2
    //   7022: invokespecial 804	o/GJ:<init>	(Lo/ˉ;Landroid/view/View;)V
    //   7025: areturn
    //   7026: new 418	java/lang/IllegalArgumentException
    //   7029: dup
    //   7030: new 420	java/lang/StringBuilder
    //   7033: dup
    //   7034: invokespecial 421	java/lang/StringBuilder:<init>	()V
    //   7037: ldc_w 806
    //   7040: invokevirtual 427	java/lang/StringBuilder:append	(Ljava/lang/String;)Ljava/lang/StringBuilder;
    //   7043: aload 6
    //   7045: invokevirtual 430	java/lang/StringBuilder:append	(Ljava/lang/Object;)Ljava/lang/StringBuilder;
    //   7048: invokevirtual 433	java/lang/StringBuilder:toString	()Ljava/lang/String;
    //   7051: invokespecial 436	java/lang/IllegalArgumentException:<init>	(Ljava/lang/String;)V
    //   7054: athrow
    //   7055: ldc -29
    //   7057: aload 6
    //   7059: invokevirtual 133	java/lang/String:equals	(Ljava/lang/Object;)Z
    //   7062: ifeq +6 -> 7068
    //   7065: goto -1193 -> 5872
    //   7068: goto -2506 -> 4562
    //   7071: ldc -94
    //   7073: aload 6
    //   7075: invokevirtual 133	java/lang/String:equals	(Ljava/lang/Object;)Z
    //   7078: ifeq +6 -> 7084
    //   7081: goto -6576 -> 505
    //   7084: goto -6924 -> 160
    //   7087: new 418	java/lang/IllegalArgumentException
    //   7090: dup
    //   7091: new 420	java/lang/StringBuilder
    //   7094: dup
    //   7095: invokespecial 421	java/lang/StringBuilder:<init>	()V
    //   7098: ldc_w 808
    //   7101: invokevirtual 427	java/lang/StringBuilder:append	(Ljava/lang/String;)Ljava/lang/StringBuilder;
    //   7104: aload 6
    //   7106: invokevirtual 430	java/lang/StringBuilder:append	(Ljava/lang/Object;)Ljava/lang/StringBuilder;
    //   7109: invokevirtual 433	java/lang/StringBuilder:toString	()Ljava/lang/String;
    //   7112: invokespecial 436	java/lang/IllegalArgumentException:<init>	(Ljava/lang/String;)V
    //   7115: athrow
    //   7116: new 810	o/JF
    //   7119: dup
    //   7120: aload_1
    //   7121: aload_2
    //   7122: invokespecial 811	o/JF:<init>	(Lo/ˉ;Landroid/view/View;)V
    //   7125: areturn
    //   7126: new 813	o/Dx
    //   7129: dup
    //   7130: aload_1
    //   7131: aload_2
    //   7132: invokespecial 814	o/Dx:<init>	(Lo/ˉ;Landroid/view/View;)V
    //   7135: areturn
    //   7136: new 816	o/Mw
    //   7139: dup
    //   7140: aload_1
    //   7141: aload_2
    //   7142: invokespecial 817	o/Mw:<init>	(Lo/ˉ;Landroid/view/View;)V
    //   7145: areturn
    //   7146: aconst_null
    //   7147: areturn
    //   7148: aload_2
    //   7149: invokevirtual 444	android/view/View:getTag	()Ljava/lang/Object;
    //   7152: astore 6
    //   7154: aload 6
    //   7156: ifnonnull +6 -> 7162
    //   7159: goto -6123 -> 1036
    //   7162: goto -3587 -> 3575
    //   7165: new 819	o/JK
    //   7168: dup
    //   7169: aload_1
    //   7170: aload_2
    //   7171: invokespecial 820	o/JK:<init>	(Lo/ˉ;Landroid/view/View;)V
    //   7174: areturn
    //   7175: new 822	o/LL
    //   7178: dup
    //   7179: aload_1
    //   7180: aload_2
    //   7181: invokespecial 823	o/LL:<init>	(Lo/ˉ;Landroid/view/View;)V
    //   7184: areturn
    //   7185: new 418	java/lang/IllegalArgumentException
    //   7188: dup
    //   7189: new 420	java/lang/StringBuilder
    //   7192: dup
    //   7193: invokespecial 421	java/lang/StringBuilder:<init>	()V
    //   7196: ldc_w 825
    //   7199: invokevirtual 427	java/lang/StringBuilder:append	(Ljava/lang/String;)Ljava/lang/StringBuilder;
    //   7202: aload 6
    //   7204: invokevirtual 430	java/lang/StringBuilder:append	(Ljava/lang/Object;)Ljava/lang/StringBuilder;
    //   7207: invokevirtual 433	java/lang/StringBuilder:toString	()Ljava/lang/String;
    //   7210: invokespecial 436	java/lang/IllegalArgumentException:<init>	(Ljava/lang/String;)V
    //   7213: athrow
    //   7214: new 446	java/lang/RuntimeException
    //   7217: dup
    //   7218: ldc_w 448
    //   7221: invokespecial 449	java/lang/RuntimeException:<init>	(Ljava/lang/String;)V
    //   7224: athrow
    //   7225: aload_2
    //   7226: invokevirtual 444	android/view/View:getTag	()Ljava/lang/Object;
    //   7229: astore 6
    //   7231: aload 6
    //   7233: ifnonnull +6 -> 7239
    //   7236: goto -4985 -> 2251
    //   7239: goto -362 -> 6877
    //   7242: new 446	java/lang/RuntimeException
    //   7245: dup
    //   7246: ldc_w 448
    //   7249: invokespecial 449	java/lang/RuntimeException:<init>	(Ljava/lang/String;)V
    //   7252: athrow
    //   7253: ldc_w 289
    //   7256: aload 6
    //   7258: invokevirtual 133	java/lang/String:equals	(Ljava/lang/Object;)Z
    //   7261: ifeq +6 -> 7267
    //   7264: goto -3539 -> 3725
    //   7267: goto -3759 -> 3508
    //   7270: aload_2
    //   7271: invokevirtual 444	android/view/View:getTag	()Ljava/lang/Object;
    //   7274: astore 6
    //   7276: aload 6
    //   7278: ifnonnull +6 -> 7284
    //   7281: goto -6401 -> 880
    //   7284: goto -4468 -> 2816
    //   7287: new 418	java/lang/IllegalArgumentException
    //   7290: dup
    //   7291: new 420	java/lang/StringBuilder
    //   7294: dup
    //   7295: invokespecial 421	java/lang/StringBuilder:<init>	()V
    //   7298: ldc_w 827
    //   7301: invokevirtual 427	java/lang/StringBuilder:append	(Ljava/lang/String;)Ljava/lang/StringBuilder;
    //   7304: aload 6
    //   7306: invokevirtual 430	java/lang/StringBuilder:append	(Ljava/lang/Object;)Ljava/lang/StringBuilder;
    //   7309: invokevirtual 433	java/lang/StringBuilder:toString	()Ljava/lang/String;
    //   7312: invokespecial 436	java/lang/IllegalArgumentException:<init>	(Ljava/lang/String;)V
    //   7315: athrow
    //   7316: new 829	o/JZ
    //   7319: dup
    //   7320: aload_1
    //   7321: aload_2
    //   7322: invokespecial 830	o/JZ:<init>	(Lo/ˉ;Landroid/view/View;)V
    //   7325: areturn
    //   7326: new 418	java/lang/IllegalArgumentException
    //   7329: dup
    //   7330: new 420	java/lang/StringBuilder
    //   7333: dup
    //   7334: invokespecial 421	java/lang/StringBuilder:<init>	()V
    //   7337: ldc_w 832
    //   7340: invokevirtual 427	java/lang/StringBuilder:append	(Ljava/lang/String;)Ljava/lang/StringBuilder;
    //   7343: aload 6
    //   7345: invokevirtual 430	java/lang/StringBuilder:append	(Ljava/lang/Object;)Ljava/lang/StringBuilder;
    //   7348: invokevirtual 433	java/lang/StringBuilder:toString	()Ljava/lang/String;
    //   7351: invokespecial 436	java/lang/IllegalArgumentException:<init>	(Ljava/lang/String;)V
    //   7354: athrow
    //   7355: ldc -127
    //   7357: aload 6
    //   7359: invokevirtual 133	java/lang/String:equals	(Ljava/lang/Object;)Z
    //   7362: ifeq +6 -> 7368
    //   7365: goto +906 -> 8271
    //   7368: goto -1839 -> 5529
    //   7371: new 446	java/lang/RuntimeException
    //   7374: dup
    //   7375: ldc_w 448
    //   7378: invokespecial 449	java/lang/RuntimeException:<init>	(Ljava/lang/String;)V
    //   7381: athrow
    //   7382: ldc_w 324
    //   7385: aload 6
    //   7387: invokevirtual 133	java/lang/String:equals	(Ljava/lang/Object;)Z
    //   7390: ifeq +6 -> 7396
    //   7393: goto -1073 -> 6320
    //   7396: goto -5880 -> 1516
    //   7399: getstatic 17	o/cOn:ˋ	I
    //   7402: bipush 87
    //   7404: iadd
    //   7405: istore 4
    //   7407: iload 4
    //   7409: sipush 128
    //   7412: irem
    //   7413: putstatic 15	o/cOn:ˏ	I
    //   7416: iload 4
    //   7418: iconst_2
    //   7419: irem
    //   7420: ifeq +6 -> 7426
    //   7423: goto -670 -> 6753
    //   7426: goto -2737 -> 4689
    //   7429: new 834	o/JD
    //   7432: dup
    //   7433: aload_1
    //   7434: aload_2
    //   7435: invokespecial 835	o/JD:<init>	(Lo/ˉ;Landroid/view/View;)V
    //   7438: areturn
    //   7439: aload_2
    //   7440: invokevirtual 444	android/view/View:getTag	()Ljava/lang/Object;
    //   7443: astore 6
    //   7445: aload 6
    //   7447: ifnonnull +6 -> 7453
    //   7450: goto -5877 -> 1573
    //   7453: goto -382 -> 7071
    //   7456: aload_2
    //   7457: invokevirtual 444	android/view/View:getTag	()Ljava/lang/Object;
    //   7460: astore 6
    //   7462: aload 6
    //   7464: ifnonnull +6 -> 7470
    //   7467: goto -1875 -> 5592
    //   7470: goto -115 -> 7355
    //   7473: ldc_w 304
    //   7476: aload 6
    //   7478: invokevirtual 133	java/lang/String:equals	(Ljava/lang/Object;)Z
    //   7481: ifeq +6 -> 7487
    //   7484: goto -1144 -> 6340
    //   7487: goto -3510 -> 3977
    //   7490: new 446	java/lang/RuntimeException
    //   7493: dup
    //   7494: ldc_w 448
    //   7497: invokespecial 449	java/lang/RuntimeException:<init>	(Ljava/lang/String;)V
    //   7500: athrow
    //   7501: new 446	java/lang/RuntimeException
    //   7504: dup
    //   7505: ldc_w 448
    //   7508: invokespecial 449	java/lang/RuntimeException:<init>	(Ljava/lang/String;)V
    //   7511: athrow
    //   7512: aload_2
    //   7513: invokevirtual 444	android/view/View:getTag	()Ljava/lang/Object;
    //   7516: astore 6
    //   7518: aload 6
    //   7520: ifnonnull +6 -> 7526
    //   7523: goto -3448 -> 4075
    //   7526: goto -5358 -> 2168
    //   7529: new 446	java/lang/RuntimeException
    //   7532: dup
    //   7533: ldc_w 448
    //   7536: invokespecial 449	java/lang/RuntimeException:<init>	(Ljava/lang/String;)V
    //   7539: athrow
    //   7540: new 418	java/lang/IllegalArgumentException
    //   7543: dup
    //   7544: new 420	java/lang/StringBuilder
    //   7547: dup
    //   7548: invokespecial 421	java/lang/StringBuilder:<init>	()V
    //   7551: ldc_w 837
    //   7554: invokevirtual 427	java/lang/StringBuilder:append	(Ljava/lang/String;)Ljava/lang/StringBuilder;
    //   7557: aload 6
    //   7559: invokevirtual 430	java/lang/StringBuilder:append	(Ljava/lang/Object;)Ljava/lang/StringBuilder;
    //   7562: invokevirtual 433	java/lang/StringBuilder:toString	()Ljava/lang/String;
    //   7565: invokespecial 436	java/lang/IllegalArgumentException:<init>	(Ljava/lang/String;)V
    //   7568: athrow
    //   7569: new 839	o/Kb
    //   7572: dup
    //   7573: aload_1
    //   7574: aload_2
    //   7575: invokespecial 840	o/Kb:<init>	(Lo/ˉ;Landroid/view/View;)V
    //   7578: areturn
    //   7579: aload_2
    //   7580: invokevirtual 444	android/view/View:getTag	()Ljava/lang/Object;
    //   7583: astore 6
    //   7585: aload 6
    //   7587: ifnonnull +6 -> 7593
    //   7590: goto -1918 -> 5672
    //   7593: goto -3962 -> 3631
    //   7596: new 446	java/lang/RuntimeException
    //   7599: dup
    //   7600: ldc_w 448
    //   7603: invokespecial 449	java/lang/RuntimeException:<init>	(Ljava/lang/String;)V
    //   7606: athrow
    //   7607: new 446	java/lang/RuntimeException
    //   7610: dup
    //   7611: ldc_w 448
    //   7614: invokespecial 449	java/lang/RuntimeException:<init>	(Ljava/lang/String;)V
    //   7617: athrow
    //   7618: ldc -106
    //   7620: aload 6
    //   7622: invokevirtual 133	java/lang/String:equals	(Ljava/lang/Object;)Z
    //   7625: ifeq +6 -> 7631
    //   7628: goto -7096 -> 532
    //   7631: goto -544 -> 7087
    //   7634: ldc_w 383
    //   7637: aload 6
    //   7639: invokevirtual 133	java/lang/String:equals	(Ljava/lang/Object;)Z
    //   7642: ifeq +6 -> 7648
    //   7645: goto +277 -> 7922
    //   7648: goto -6556 -> 1092
    //   7651: new 842	o/GX
    //   7654: dup
    //   7655: aload_1
    //   7656: aload_2
    //   7657: invokespecial 843	o/GX:<init>	(Lo/ˉ;Landroid/view/View;)V
    //   7660: areturn
    //   7661: new 845	o/JI
    //   7664: dup
    //   7665: aload_1
    //   7666: aload_2
    //   7667: invokespecial 846	o/JI:<init>	(Lo/ˉ;Landroid/view/View;)V
    //   7670: areturn
    //   7671: aload_2
    //   7672: invokevirtual 444	android/view/View:getTag	()Ljava/lang/Object;
    //   7675: astore 6
    //   7677: aload 6
    //   7679: ifnonnull +6 -> 7685
    //   7682: goto -4532 -> 3150
    //   7685: goto -995 -> 6690
    //   7688: new 418	java/lang/IllegalArgumentException
    //   7691: dup
    //   7692: new 420	java/lang/StringBuilder
    //   7695: dup
    //   7696: invokespecial 421	java/lang/StringBuilder:<init>	()V
    //   7699: ldc_w 848
    //   7702: invokevirtual 427	java/lang/StringBuilder:append	(Ljava/lang/String;)Ljava/lang/StringBuilder;
    //   7705: aload 6
    //   7707: invokevirtual 430	java/lang/StringBuilder:append	(Ljava/lang/Object;)Ljava/lang/StringBuilder;
    //   7710: invokevirtual 433	java/lang/StringBuilder:toString	()Ljava/lang/String;
    //   7713: invokespecial 436	java/lang/IllegalArgumentException:<init>	(Ljava/lang/String;)V
    //   7716: athrow
    //   7717: new 446	java/lang/RuntimeException
    //   7720: dup
    //   7721: ldc_w 448
    //   7724: invokespecial 449	java/lang/RuntimeException:<init>	(Ljava/lang/String;)V
    //   7727: athrow
    //   7728: new 418	java/lang/IllegalArgumentException
    //   7731: dup
    //   7732: new 420	java/lang/StringBuilder
    //   7735: dup
    //   7736: invokespecial 421	java/lang/StringBuilder:<init>	()V
    //   7739: ldc_w 850
    //   7742: invokevirtual 427	java/lang/StringBuilder:append	(Ljava/lang/String;)Ljava/lang/StringBuilder;
    //   7745: aload 6
    //   7747: invokevirtual 430	java/lang/StringBuilder:append	(Ljava/lang/Object;)Ljava/lang/StringBuilder;
    //   7750: invokevirtual 433	java/lang/StringBuilder:toString	()Ljava/lang/String;
    //   7753: invokespecial 436	java/lang/IllegalArgumentException:<init>	(Ljava/lang/String;)V
    //   7756: athrow
    //   7757: new 418	java/lang/IllegalArgumentException
    //   7760: dup
    //   7761: new 420	java/lang/StringBuilder
    //   7764: dup
    //   7765: invokespecial 421	java/lang/StringBuilder:<init>	()V
    //   7768: ldc_w 852
    //   7771: invokevirtual 427	java/lang/StringBuilder:append	(Ljava/lang/String;)Ljava/lang/StringBuilder;
    //   7774: aload 6
    //   7776: invokevirtual 430	java/lang/StringBuilder:append	(Ljava/lang/Object;)Ljava/lang/StringBuilder;
    //   7779: invokevirtual 433	java/lang/StringBuilder:toString	()Ljava/lang/String;
    //   7782: invokespecial 436	java/lang/IllegalArgumentException:<init>	(Ljava/lang/String;)V
    //   7785: athrow
    //   7786: aload_2
    //   7787: invokevirtual 444	android/view/View:getTag	()Ljava/lang/Object;
    //   7790: astore 6
    //   7792: aload 6
    //   7794: ifnonnull +6 -> 7800
    //   7797: goto -6186 -> 1611
    //   7800: goto -4606 -> 3194
    //   7803: aload_2
    //   7804: invokevirtual 444	android/view/View:getTag	()Ljava/lang/Object;
    //   7807: astore 6
    //   7809: aload 6
    //   7811: ifnonnull +6 -> 7817
    //   7814: goto +135 -> 7949
    //   7817: goto -2013 -> 5804
    //   7820: new 418	java/lang/IllegalArgumentException
    //   7823: dup
    //   7824: new 420	java/lang/StringBuilder
    //   7827: dup
    //   7828: invokespecial 421	java/lang/StringBuilder:<init>	()V
    //   7831: ldc_w 854
    //   7834: invokevirtual 427	java/lang/StringBuilder:append	(Ljava/lang/String;)Ljava/lang/StringBuilder;
    //   7837: aload 6
    //   7839: invokevirtual 430	java/lang/StringBuilder:append	(Ljava/lang/Object;)Ljava/lang/StringBuilder;
    //   7842: invokevirtual 433	java/lang/StringBuilder:toString	()Ljava/lang/String;
    //   7845: invokespecial 436	java/lang/IllegalArgumentException:<init>	(Ljava/lang/String;)V
    //   7848: athrow
    //   7849: aload_2
    //   7850: invokevirtual 444	android/view/View:getTag	()Ljava/lang/Object;
    //   7853: astore 6
    //   7855: aload 6
    //   7857: ifnonnull +6 -> 7863
    //   7860: goto -3398 -> 4462
    //   7863: goto -4997 -> 2866
    //   7866: new 446	java/lang/RuntimeException
    //   7869: dup
    //   7870: ldc_w 448
    //   7873: invokespecial 449	java/lang/RuntimeException:<init>	(Ljava/lang/String;)V
    //   7876: athrow
    //   7877: ldc -40
    //   7879: aload 6
    //   7881: invokevirtual 133	java/lang/String:equals	(Ljava/lang/Object;)Z
    //   7884: ifeq +6 -> 7890
    //   7887: goto -1677 -> 6210
    //   7890: goto +485 -> 8375
    //   7893: new 418	java/lang/IllegalArgumentException
    //   7896: dup
    //   7897: new 420	java/lang/StringBuilder
    //   7900: dup
    //   7901: invokespecial 421	java/lang/StringBuilder:<init>	()V
    //   7904: ldc_w 856
    //   7907: invokevirtual 427	java/lang/StringBuilder:append	(Ljava/lang/String;)Ljava/lang/StringBuilder;
    //   7910: aload 6
    //   7912: invokevirtual 430	java/lang/StringBuilder:append	(Ljava/lang/Object;)Ljava/lang/StringBuilder;
    //   7915: invokevirtual 433	java/lang/StringBuilder:toString	()Ljava/lang/String;
    //   7918: invokespecial 436	java/lang/IllegalArgumentException:<init>	(Ljava/lang/String;)V
    //   7921: athrow
    //   7922: new 858	o/GT
    //   7925: dup
    //   7926: aload_1
    //   7927: aload_2
    //   7928: invokespecial 859	o/GT:<init>	(Lo/ˉ;Landroid/view/View;)V
    //   7931: areturn
    //   7932: ldc_w 277
    //   7935: aload 6
    //   7937: invokevirtual 133	java/lang/String:equals	(Ljava/lang/Object;)Z
    //   7940: ifeq +6 -> 7946
    //   7943: goto +91 -> 8034
    //   7946: goto -5836 -> 2110
    //   7949: new 446	java/lang/RuntimeException
    //   7952: dup
    //   7953: ldc_w 448
    //   7956: invokespecial 449	java/lang/RuntimeException:<init>	(Ljava/lang/String;)V
    //   7959: athrow
    //   7960: ldc_w 360
    //   7963: aload 6
    //   7965: invokevirtual 133	java/lang/String:equals	(Ljava/lang/Object;)Z
    //   7968: ifeq +6 -> 7974
    //   7971: goto -7882 -> 89
    //   7974: goto -7052 -> 922
    //   7977: ldc_w 308
    //   7980: aload 6
    //   7982: invokevirtual 133	java/lang/String:equals	(Ljava/lang/Object;)Z
    //   7985: ifeq +6 -> 7991
    //   7988: goto +474 -> 8462
    //   7991: goto -7959 -> 32
    //   7994: new 446	java/lang/RuntimeException
    //   7997: dup
    //   7998: ldc_w 448
    //   8001: invokespecial 449	java/lang/RuntimeException:<init>	(Ljava/lang/String;)V
    //   8004: athrow
    //   8005: new 418	java/lang/IllegalArgumentException
    //   8008: dup
    //   8009: new 420	java/lang/StringBuilder
    //   8012: dup
    //   8013: invokespecial 421	java/lang/StringBuilder:<init>	()V
    //   8016: ldc_w 861
    //   8019: invokevirtual 427	java/lang/StringBuilder:append	(Ljava/lang/String;)Ljava/lang/StringBuilder;
    //   8022: aload 6
    //   8024: invokevirtual 430	java/lang/StringBuilder:append	(Ljava/lang/Object;)Ljava/lang/StringBuilder;
    //   8027: invokevirtual 433	java/lang/StringBuilder:toString	()Ljava/lang/String;
    //   8030: invokespecial 436	java/lang/IllegalArgumentException:<init>	(Ljava/lang/String;)V
    //   8033: athrow
    //   8034: new 863	o/JY
    //   8037: dup
    //   8038: aload_1
    //   8039: aload_2
    //   8040: invokespecial 864	o/JY:<init>	(Lo/ˉ;Landroid/view/View;)V
    //   8043: areturn
    //   8044: aload_2
    //   8045: invokevirtual 444	android/view/View:getTag	()Ljava/lang/Object;
    //   8048: astore 6
    //   8050: aload 6
    //   8052: ifnonnull +6 -> 8058
    //   8055: goto +449 -> 8504
    //   8058: goto -5577 -> 2481
    //   8061: aload_2
    //   8062: invokevirtual 444	android/view/View:getTag	()Ljava/lang/Object;
    //   8065: astore 6
    //   8067: aload 6
    //   8069: ifnonnull +6 -> 8075
    //   8072: goto -7232 -> 840
    //   8075: goto -602 -> 7473
    //   8078: new 866	o/LN
    //   8081: dup
    //   8082: aload_1
    //   8083: aload_2
    //   8084: invokespecial 867	o/LN:<init>	(Lo/ˉ;Landroid/view/View;)V
    //   8087: areturn
    //   8088: aload_2
    //   8089: invokevirtual 444	android/view/View:getTag	()Ljava/lang/Object;
    //   8092: astore 6
    //   8094: aload 6
    //   8096: ifnonnull +6 -> 8102
    //   8099: goto -5915 -> 2184
    //   8102: goto -3978 -> 4124
    //   8105: ldc -96
    //   8107: aload 6
    //   8109: invokevirtual 133	java/lang/String:equals	(Ljava/lang/Object;)Z
    //   8112: ifeq +6 -> 8118
    //   8115: goto -6994 -> 1121
    //   8118: goto -4870 -> 3248
    //   8121: new 869	o/Lo
    //   8124: dup
    //   8125: aload_1
    //   8126: aload_2
    //   8127: invokespecial 870	o/Lo:<init>	(Lo/ˉ;Landroid/view/View;)V
    //   8130: areturn
    //   8131: new 446	java/lang/RuntimeException
    //   8134: dup
    //   8135: ldc_w 448
    //   8138: invokespecial 449	java/lang/RuntimeException:<init>	(Ljava/lang/String;)V
    //   8141: athrow
    //   8142: new 418	java/lang/IllegalArgumentException
    //   8145: dup
    //   8146: new 420	java/lang/StringBuilder
    //   8149: dup
    //   8150: invokespecial 421	java/lang/StringBuilder:<init>	()V
    //   8153: ldc_w 872
    //   8156: invokevirtual 427	java/lang/StringBuilder:append	(Ljava/lang/String;)Ljava/lang/StringBuilder;
    //   8159: aload 6
    //   8161: invokevirtual 430	java/lang/StringBuilder:append	(Ljava/lang/Object;)Ljava/lang/StringBuilder;
    //   8164: invokevirtual 433	java/lang/StringBuilder:toString	()Ljava/lang/String;
    //   8167: invokespecial 436	java/lang/IllegalArgumentException:<init>	(Ljava/lang/String;)V
    //   8170: athrow
    //   8171: new 874	o/Mr
    //   8174: dup
    //   8175: aload_1
    //   8176: aload_2
    //   8177: invokespecial 875	o/Mr:<init>	(Lo/ˉ;Landroid/view/View;)V
    //   8180: areturn
    //   8181: new 418	java/lang/IllegalArgumentException
    //   8184: dup
    //   8185: new 420	java/lang/StringBuilder
    //   8188: dup
    //   8189: invokespecial 421	java/lang/StringBuilder:<init>	()V
    //   8192: ldc_w 877
    //   8195: invokevirtual 427	java/lang/StringBuilder:append	(Ljava/lang/String;)Ljava/lang/StringBuilder;
    //   8198: aload 6
    //   8200: invokevirtual 430	java/lang/StringBuilder:append	(Ljava/lang/Object;)Ljava/lang/StringBuilder;
    //   8203: invokevirtual 433	java/lang/StringBuilder:toString	()Ljava/lang/String;
    //   8206: invokespecial 436	java/lang/IllegalArgumentException:<init>	(Ljava/lang/String;)V
    //   8209: athrow
    //   8210: ldc -109
    //   8212: aload 6
    //   8214: invokevirtual 133	java/lang/String:equals	(Ljava/lang/Object;)Z
    //   8217: ifeq +6 -> 8223
    //   8220: goto -5701 -> 2519
    //   8223: goto -3874 -> 4349
    //   8226: ldc -26
    //   8228: aload 6
    //   8230: invokevirtual 133	java/lang/String:equals	(Ljava/lang/Object;)Z
    //   8233: ifeq +6 -> 8239
    //   8236: goto -65 -> 8171
    //   8239: goto -1806 -> 6433
    //   8242: new 418	java/lang/IllegalArgumentException
    //   8245: dup
    //   8246: new 420	java/lang/StringBuilder
    //   8249: dup
    //   8250: invokespecial 421	java/lang/StringBuilder:<init>	()V
    //   8253: ldc_w 879
    //   8256: invokevirtual 427	java/lang/StringBuilder:append	(Ljava/lang/String;)Ljava/lang/StringBuilder;
    //   8259: aload 6
    //   8261: invokevirtual 430	java/lang/StringBuilder:append	(Ljava/lang/Object;)Ljava/lang/StringBuilder;
    //   8264: invokevirtual 433	java/lang/StringBuilder:toString	()Ljava/lang/String;
    //   8267: invokespecial 436	java/lang/IllegalArgumentException:<init>	(Ljava/lang/String;)V
    //   8270: athrow
    //   8271: new 881	o/Kf
    //   8274: dup
    //   8275: aload_1
    //   8276: aload_2
    //   8277: invokespecial 882	o/Kf:<init>	(Lo/ˉ;Landroid/view/View;)V
    //   8280: areturn
    //   8281: new 884	o/MR
    //   8284: dup
    //   8285: aload_1
    //   8286: aload_2
    //   8287: invokespecial 885	o/MR:<init>	(Lo/ˉ;Landroid/view/View;)V
    //   8290: areturn
    //   8291: new 418	java/lang/IllegalArgumentException
    //   8294: dup
    //   8295: new 420	java/lang/StringBuilder
    //   8298: dup
    //   8299: invokespecial 421	java/lang/StringBuilder:<init>	()V
    //   8302: ldc_w 887
    //   8305: invokevirtual 427	java/lang/StringBuilder:append	(Ljava/lang/String;)Ljava/lang/StringBuilder;
    //   8308: aload 6
    //   8310: invokevirtual 430	java/lang/StringBuilder:append	(Ljava/lang/Object;)Ljava/lang/StringBuilder;
    //   8313: invokevirtual 433	java/lang/StringBuilder:toString	()Ljava/lang/String;
    //   8316: invokespecial 436	java/lang/IllegalArgumentException:<init>	(Ljava/lang/String;)V
    //   8319: athrow
    //   8320: new 446	java/lang/RuntimeException
    //   8323: dup
    //   8324: ldc_w 448
    //   8327: invokespecial 449	java/lang/RuntimeException:<init>	(Ljava/lang/String;)V
    //   8330: athrow
    //   8331: ldc_w 351
    //   8334: aload 6
    //   8336: invokevirtual 133	java/lang/String:equals	(Ljava/lang/Object;)Z
    //   8339: ifeq +6 -> 8345
    //   8342: goto -1720 -> 6622
    //   8345: goto -2286 -> 6059
    //   8348: new 889	o/Mq
    //   8351: dup
    //   8352: aload_1
    //   8353: aload_2
    //   8354: invokespecial 890	o/Mq:<init>	(Lo/ˉ;Landroid/view/View;)V
    //   8357: areturn
    //   8358: aload_2
    //   8359: invokevirtual 444	android/view/View:getTag	()Ljava/lang/Object;
    //   8362: astore 6
    //   8364: aload 6
    //   8366: ifnonnull +6 -> 8372
    //   8369: goto -4938 -> 3431
    //   8372: goto -4637 -> 3735
    //   8375: new 418	java/lang/IllegalArgumentException
    //   8378: dup
    //   8379: new 420	java/lang/StringBuilder
    //   8382: dup
    //   8383: invokespecial 421	java/lang/StringBuilder:<init>	()V
    //   8386: ldc_w 892
    //   8389: invokevirtual 427	java/lang/StringBuilder:append	(Ljava/lang/String;)Ljava/lang/StringBuilder;
    //   8392: aload 6
    //   8394: invokevirtual 430	java/lang/StringBuilder:append	(Ljava/lang/Object;)Ljava/lang/StringBuilder;
    //   8397: invokevirtual 433	java/lang/StringBuilder:toString	()Ljava/lang/String;
    //   8400: invokespecial 436	java/lang/IllegalArgumentException:<init>	(Ljava/lang/String;)V
    //   8403: athrow
    //   8404: new 418	java/lang/IllegalArgumentException
    //   8407: dup
    //   8408: new 420	java/lang/StringBuilder
    //   8411: dup
    //   8412: invokespecial 421	java/lang/StringBuilder:<init>	()V
    //   8415: ldc_w 894
    //   8418: invokevirtual 427	java/lang/StringBuilder:append	(Ljava/lang/String;)Ljava/lang/StringBuilder;
    //   8421: aload 6
    //   8423: invokevirtual 430	java/lang/StringBuilder:append	(Ljava/lang/Object;)Ljava/lang/StringBuilder;
    //   8426: invokevirtual 433	java/lang/StringBuilder:toString	()Ljava/lang/String;
    //   8429: invokespecial 436	java/lang/IllegalArgumentException:<init>	(Ljava/lang/String;)V
    //   8432: athrow
    //   8433: new 418	java/lang/IllegalArgumentException
    //   8436: dup
    //   8437: new 420	java/lang/StringBuilder
    //   8440: dup
    //   8441: invokespecial 421	java/lang/StringBuilder:<init>	()V
    //   8444: ldc_w 896
    //   8447: invokevirtual 427	java/lang/StringBuilder:append	(Ljava/lang/String;)Ljava/lang/StringBuilder;
    //   8450: aload 6
    //   8452: invokevirtual 430	java/lang/StringBuilder:append	(Ljava/lang/Object;)Ljava/lang/StringBuilder;
    //   8455: invokevirtual 433	java/lang/StringBuilder:toString	()Ljava/lang/String;
    //   8458: invokespecial 436	java/lang/IllegalArgumentException:<init>	(Ljava/lang/String;)V
    //   8461: athrow
    //   8462: new 898	o/GN
    //   8465: dup
    //   8466: aload_1
    //   8467: aload_2
    //   8468: invokespecial 899	o/GN:<init>	(Lo/ˉ;Landroid/view/View;)V
    //   8471: areturn
    //   8472: new 446	java/lang/RuntimeException
    //   8475: dup
    //   8476: ldc_w 448
    //   8479: invokespecial 449	java/lang/RuntimeException:<init>	(Ljava/lang/String;)V
    //   8482: athrow
    //   8483: new 446	java/lang/RuntimeException
    //   8486: dup
    //   8487: ldc_w 448
    //   8490: invokespecial 449	java/lang/RuntimeException:<init>	(Ljava/lang/String;)V
    //   8493: athrow
    //   8494: new 901	o/JS
    //   8497: dup
    //   8498: aload_1
    //   8499: aload_2
    //   8500: invokespecial 902	o/JS:<init>	(Lo/ˉ;Landroid/view/View;)V
    //   8503: areturn
    //   8504: new 446	java/lang/RuntimeException
    //   8507: dup
    //   8508: ldc_w 448
    //   8511: invokespecial 449	java/lang/RuntimeException:<init>	(Ljava/lang/String;)V
    //   8514: athrow
    //   8515: new 904	o/Mz
    //   8518: dup
    //   8519: aload_1
    //   8520: aload_2
    //   8521: invokespecial 905	o/Mz:<init>	(Lo/ˉ;Landroid/view/View;)V
    //   8524: areturn
    //   8525: ldc_w 406
    //   8528: aload 6
    //   8530: invokevirtual 133	java/lang/String:equals	(Ljava/lang/Object;)Z
    //   8533: ifeq +6 -> 8539
    //   8536: goto -2569 -> 5967
    //   8539: goto -397 -> 8142
    //   8542: new 446	java/lang/RuntimeException
    //   8545: dup
    //   8546: ldc_w 448
    //   8549: invokespecial 449	java/lang/RuntimeException:<init>	(Ljava/lang/String;)V
    //   8552: athrow
    // Local variable table:
    //   start	length	slot	name	signature
    //   0	8553	0	this	cOn
    //   0	8553	1	paramˉ	ˉ
    //   0	8553	2	paramView	android.view.View
    //   0	8553	3	paramInt	int
    //   7405	15	4	i	int
    //   6544	3	5	bool	boolean
    //   20	8509	6	localObject	Object
    // Exception table:
    //   from	to	target	type
    //   6441	6464	2386	java/lang/Exception
    //   2364	2375	6893	java/lang/Exception
    //   2977	2988	6893	java/lang/Exception
    //   6536	6546	6893	java/lang/Exception
  }
}
