package o;

public final class D
  extends x
  implements ᐸ.ˏ
{
  private static byte ॱˈ;
  private static int ॱˉ;
  private static int ॱˌ;
  private static int ॱˑ;
  private boolean ߺ;
  
  static
  {
    try
    {
      for (;;)
      {
        for (i = ॱˑ + 91;; i = 61) {
          try
          {
            ॱˉ = i % 128;
            if (i % 2 != 0)
            {
              i = 39;
              switch (i)
              {
              default: 
                return;
              }
            }
          }
          catch (Exception localException1)
          {
            throw localException1;
          }
        }
        ॱˑ = 0;
        ॱˉ = 1;
        ˎ();
        ॱˈ = -102;
      }
      int i = 17 / 0;
      return;
    }
    catch (Exception localException2)
    {
      throw localException2;
    }
  }
  
  /* Error */
  public D(android.content.Context paramContext, boolean paramBoolean)
  {
    // Byte code:
    //   0: goto +9 -> 9
    //   3: bipush 96
    //   5: istore_3
    //   6: goto +129 -> 135
    //   9: aload_1
    //   10: bipush 7
    //   12: iconst_1
    //   13: sipush 228
    //   16: bipush 7
    //   18: bipush 7
    //   20: newarray char
    //   22: dup
    //   23: iconst_0
    //   24: ldc 31
    //   26: castore
    //   27: dup
    //   28: iconst_1
    //   29: ldc 32
    //   31: castore
    //   32: dup
    //   33: iconst_2
    //   34: ldc 33
    //   36: castore
    //   37: dup
    //   38: iconst_3
    //   39: ldc 31
    //   41: castore
    //   42: dup
    //   43: iconst_4
    //   44: ldc 34
    //   46: castore
    //   47: dup
    //   48: iconst_5
    //   49: ldc 35
    //   51: castore
    //   52: dup
    //   53: bipush 6
    //   55: ldc 36
    //   57: castore
    //   58: invokestatic 40	o/D:ˊ	(IZII[C)Ljava/lang/String;
    //   61: invokevirtual 46	java/lang/String:intern	()Ljava/lang/String;
    //   64: invokestatic 51	o/vq:ˎ	(Ljava/lang/Object;Ljava/lang/String;)V
    //   67: aload_0
    //   68: aload_1
    //   69: invokespecial 54	o/x:<init>	(Landroid/content/Context;)V
    //   72: aload_0
    //   73: iload_2
    //   74: putfield 56	o/D:ߺ	Z
    //   77: aload_1
    //   78: getstatic 61	o/h$if:missing_data_connection	I
    //   81: invokevirtual 67	android/content/Context:getString	(I)Ljava/lang/String;
    //   84: astore 4
    //   86: aload 4
    //   88: iconst_3
    //   89: iconst_1
    //   90: sipush 131
    //   93: iconst_4
    //   94: iconst_4
    //   95: newarray char
    //   97: dup
    //   98: iconst_0
    //   99: ldc 68
    //   101: castore
    //   102: dup
    //   103: iconst_1
    //   104: ldc 69
    //   106: castore
    //   107: dup
    //   108: iconst_2
    //   109: ldc 70
    //   111: castore
    //   112: dup
    //   113: iconst_3
    //   114: ldc 71
    //   116: castore
    //   117: invokestatic 40	o/D:ˊ	(IZII[C)Ljava/lang/String;
    //   120: invokevirtual 46	java/lang/String:intern	()Ljava/lang/String;
    //   123: invokevirtual 75	java/lang/String:startsWith	(Ljava/lang/String;)Z
    //   126: ifeq +6 -> 132
    //   129: goto +105 -> 234
    //   132: goto +126 -> 258
    //   135: iload_3
    //   136: lookupswitch	default:+28->164, 63:+197->333, 96:+28->164
    //   164: aload_0
    //   165: aload 4
    //   167: iconst_4
    //   168: invokevirtual 78	java/lang/String:substring	(I)Ljava/lang/String;
    //   171: invokespecial 82	o/D:ॱ	(Ljava/lang/String;)Ljava/lang/String;
    //   174: invokevirtual 46	java/lang/String:intern	()Ljava/lang/String;
    //   177: astore 4
    //   179: goto +356 -> 535
    //   182: astore_1
    //   183: aload_1
    //   184: athrow
    //   185: bipush 18
    //   187: istore_3
    //   188: goto +168 -> 356
    //   191: bipush 57
    //   193: istore_3
    //   194: goto +162 -> 356
    //   197: aload 4
    //   199: astore_1
    //   200: iload_3
    //   201: lookupswitch	default:+27->228, 46:+280->481, 92:+253->454
    //   228: aload 4
    //   230: astore_1
    //   231: goto +250 -> 481
    //   234: aload_0
    //   235: aload 4
    //   237: iconst_4
    //   238: invokevirtual 78	java/lang/String:substring	(I)Ljava/lang/String;
    //   241: invokespecial 82	o/D:ॱ	(Ljava/lang/String;)Ljava/lang/String;
    //   244: invokevirtual 46	java/lang/String:intern	()Ljava/lang/String;
    //   247: astore 4
    //   249: goto +9 -> 258
    //   252: bipush 46
    //   254: istore_3
    //   255: goto -58 -> 197
    //   258: aload 4
    //   260: checkcast 84	java/lang/CharSequence
    //   263: astore 4
    //   265: aload_0
    //   266: aload 4
    //   268: putfield 87	o/D:ˎ	Ljava/lang/CharSequence;
    //   271: getstatic 90	o/h$if:no_internet_connection	I
    //   274: istore_3
    //   275: aload_1
    //   276: iload_3
    //   277: invokevirtual 67	android/content/Context:getString	(I)Ljava/lang/String;
    //   280: astore 4
    //   282: aload 4
    //   284: iconst_3
    //   285: iconst_1
    //   286: sipush 131
    //   289: iconst_4
    //   290: iconst_4
    //   291: newarray char
    //   293: dup
    //   294: iconst_0
    //   295: ldc 68
    //   297: castore
    //   298: dup
    //   299: iconst_1
    //   300: ldc 69
    //   302: castore
    //   303: dup
    //   304: iconst_2
    //   305: ldc 70
    //   307: castore
    //   308: dup
    //   309: iconst_3
    //   310: ldc 71
    //   312: castore
    //   313: invokestatic 40	o/D:ˊ	(IZII[C)Ljava/lang/String;
    //   316: invokevirtual 46	java/lang/String:intern	()Ljava/lang/String;
    //   319: invokevirtual 75	java/lang/String:startsWith	(Ljava/lang/String;)Z
    //   322: istore_2
    //   323: iload_2
    //   324: ifeq +6 -> 330
    //   327: goto +292 -> 619
    //   330: goto +205 -> 535
    //   333: aload_0
    //   334: aload 4
    //   336: iconst_4
    //   337: invokevirtual 78	java/lang/String:substring	(I)Ljava/lang/String;
    //   340: invokespecial 82	o/D:ॱ	(Ljava/lang/String;)Ljava/lang/String;
    //   343: invokevirtual 46	java/lang/String:intern	()Ljava/lang/String;
    //   346: astore 4
    //   348: bipush 54
    //   350: iconst_0
    //   351: idiv
    //   352: istore_3
    //   353: goto +182 -> 535
    //   356: iload_3
    //   357: lookupswitch	default:+27->384, 18:+40->397, 57:+245->602
    //   384: goto +218 -> 602
    //   387: bipush 92
    //   389: istore_3
    //   390: goto -193 -> 197
    //   393: aconst_null
    //   394: arraylength
    //   395: istore_3
    //   396: return
    //   397: aload_0
    //   398: aload 4
    //   400: iconst_4
    //   401: invokevirtual 78	java/lang/String:substring	(I)Ljava/lang/String;
    //   404: invokespecial 82	o/D:ॱ	(Ljava/lang/String;)Ljava/lang/String;
    //   407: invokevirtual 46	java/lang/String:intern	()Ljava/lang/String;
    //   410: astore_1
    //   411: aconst_null
    //   412: arraylength
    //   413: istore_3
    //   414: goto +9 -> 423
    //   417: bipush 63
    //   419: istore_3
    //   420: goto -285 -> 135
    //   423: goto +58 -> 481
    //   426: astore_1
    //   427: aload_1
    //   428: athrow
    //   429: getstatic 20	o/D:ॱˑ	I
    //   432: bipush 51
    //   434: iadd
    //   435: istore_3
    //   436: iload_3
    //   437: sipush 128
    //   440: irem
    //   441: putstatic 22	o/D:ॱˉ	I
    //   444: iload_3
    //   445: iconst_2
    //   446: irem
    //   447: ifne +6 -> 453
    //   450: goto -57 -> 393
    //   453: return
    //   454: getstatic 20	o/D:ॱˑ	I
    //   457: bipush 77
    //   459: iadd
    //   460: istore_3
    //   461: iload_3
    //   462: sipush 128
    //   465: irem
    //   466: putstatic 22	o/D:ॱˉ	I
    //   469: iload_3
    //   470: iconst_2
    //   471: irem
    //   472: ifne +6 -> 478
    //   475: goto -290 -> 185
    //   478: goto -287 -> 191
    //   481: aload_0
    //   482: aload_1
    //   483: checkcast 84	java/lang/CharSequence
    //   486: invokevirtual 93	o/D:ॱ	(Ljava/lang/CharSequence;)Lo/ᐸ$If;
    //   489: pop
    //   490: aload_0
    //   491: aload_0
    //   492: checkcast 6	o/ᐸ$ˏ
    //   495: invokevirtual 96	o/D:ॱ	(Lo/ᐸ$ˏ;)Lo/ᐸ$If;
    //   498: pop
    //   499: aload_0
    //   500: aload_0
    //   501: checkcast 6	o/ᐸ$ˏ
    //   504: invokevirtual 98	o/D:ˊ	(Lo/ᐸ$ˏ;)Lo/ᐸ$If;
    //   507: pop
    //   508: aload_0
    //   509: iconst_1
    //   510: invokevirtual 102	o/D:ˋ	(Z)Lo/ᐸ$If;
    //   513: pop
    //   514: goto -85 -> 429
    //   517: aload_0
    //   518: aload 4
    //   520: iconst_4
    //   521: invokevirtual 78	java/lang/String:substring	(I)Ljava/lang/String;
    //   524: invokespecial 82	o/D:ॱ	(Ljava/lang/String;)Ljava/lang/String;
    //   527: invokevirtual 46	java/lang/String:intern	()Ljava/lang/String;
    //   530: astore 4
    //   532: goto +114 -> 646
    //   535: aload_0
    //   536: aload 4
    //   538: checkcast 84	java/lang/CharSequence
    //   541: putfield 105	o/D:ˊॱ	Ljava/lang/CharSequence;
    //   544: aload_1
    //   545: getstatic 108	o/h$if:device_settings	I
    //   548: invokevirtual 67	android/content/Context:getString	(I)Ljava/lang/String;
    //   551: astore 4
    //   553: aload 4
    //   555: iconst_3
    //   556: iconst_1
    //   557: sipush 131
    //   560: iconst_4
    //   561: iconst_4
    //   562: newarray char
    //   564: dup
    //   565: iconst_0
    //   566: ldc 68
    //   568: castore
    //   569: dup
    //   570: iconst_1
    //   571: ldc 69
    //   573: castore
    //   574: dup
    //   575: iconst_2
    //   576: ldc 70
    //   578: castore
    //   579: dup
    //   580: iconst_3
    //   581: ldc 71
    //   583: castore
    //   584: invokestatic 40	o/D:ˊ	(IZII[C)Ljava/lang/String;
    //   587: invokevirtual 46	java/lang/String:intern	()Ljava/lang/String;
    //   590: invokevirtual 75	java/lang/String:startsWith	(Ljava/lang/String;)Z
    //   593: ifeq +6 -> 599
    //   596: goto -79 -> 517
    //   599: goto +47 -> 646
    //   602: aload_0
    //   603: aload 4
    //   605: iconst_4
    //   606: invokevirtual 78	java/lang/String:substring	(I)Ljava/lang/String;
    //   609: invokespecial 82	o/D:ॱ	(Ljava/lang/String;)Ljava/lang/String;
    //   612: invokevirtual 46	java/lang/String:intern	()Ljava/lang/String;
    //   615: astore_1
    //   616: goto -193 -> 423
    //   619: getstatic 20	o/D:ॱˑ	I
    //   622: bipush 45
    //   624: iadd
    //   625: istore_3
    //   626: iload_3
    //   627: sipush 128
    //   630: irem
    //   631: putstatic 22	o/D:ॱˉ	I
    //   634: iload_3
    //   635: iconst_2
    //   636: irem
    //   637: ifne +6 -> 643
    //   640: goto -223 -> 417
    //   643: goto -640 -> 3
    //   646: aload_0
    //   647: aload 4
    //   649: checkcast 84	java/lang/CharSequence
    //   652: invokevirtual 110	o/D:ˎ	(Ljava/lang/CharSequence;)Lo/ᐸ$If;
    //   655: pop
    //   656: aload_1
    //   657: getstatic 113	o/h$if:close	I
    //   660: invokevirtual 67	android/content/Context:getString	(I)Ljava/lang/String;
    //   663: astore 4
    //   665: aload 4
    //   667: iconst_3
    //   668: iconst_1
    //   669: sipush 131
    //   672: iconst_4
    //   673: iconst_4
    //   674: newarray char
    //   676: dup
    //   677: iconst_0
    //   678: ldc 68
    //   680: castore
    //   681: dup
    //   682: iconst_1
    //   683: ldc 69
    //   685: castore
    //   686: dup
    //   687: iconst_2
    //   688: ldc 70
    //   690: castore
    //   691: dup
    //   692: iconst_3
    //   693: ldc 71
    //   695: castore
    //   696: invokestatic 40	o/D:ˊ	(IZII[C)Ljava/lang/String;
    //   699: invokevirtual 46	java/lang/String:intern	()Ljava/lang/String;
    //   702: invokevirtual 75	java/lang/String:startsWith	(Ljava/lang/String;)Z
    //   705: ifeq +6 -> 711
    //   708: goto -321 -> 387
    //   711: goto -459 -> 252
    // Local variable table:
    //   start	length	slot	name	signature
    //   0	714	0	this	D
    //   0	714	1	paramContext	android.content.Context
    //   0	714	2	paramBoolean	boolean
    //   5	632	3	i	int
    //   84	582	4	localObject	Object
    // Exception table:
    //   from	to	target	type
    //   258	265	182	java/lang/Exception
    //   265	271	182	java/lang/Exception
    //   271	275	182	java/lang/Exception
    //   275	282	182	java/lang/Exception
    //   282	323	182	java/lang/Exception
    //   275	282	426	java/lang/Exception
  }
  
  private static String ˊ(int paramInt1, boolean paramBoolean, int paramInt2, int paramInt3, char[] paramArrayOfChar)
  {
    break label296;
    while (paramInt1 >= paramInt3) {
      break label153;
    }
    label17:
    label23:
    Object localObject;
    int j;
    label84:
    label111:
    int i;
    label126:
    label153:
    label156:
    label166:
    for (;;)
    {
      break;
      for (;;)
      {
        paramInt1 = 87;
        paramArrayOfChar = (char[])localObject;
        switch (paramInt1)
        {
        default: 
          break label286;
          paramArrayOfChar[paramInt1] = localObject[(paramInt3 - paramInt1 - 1)];
          paramInt1 += 1;
          break label126;
          for (;;)
          {
            j = 2;
            break label305;
            paramInt2 = ॱˉ + 111;
            ॱˑ = paramInt2 % 128;
            if (paramInt2 % 2 != 0) {
              break;
            }
            break;
            if (i < paramInt3) {
              break label258;
            }
          }
          break label206;
          paramInt2 = ॱˉ + 27;
          ॱˑ = paramInt2 % 128;
          if (paramInt2 % 2 != 0) {
            break label166;
          }
          break label17;
          break label248;
          if (paramBoolean) {
            break label299;
          }
        }
      }
    }
    for (;;)
    {
      localObject[i] = ((char)(paramInt2 + paramArrayOfChar[i]));
      localObject[i] = ((char)(localObject[i] - ॱˌ));
      i += 1;
      break label111;
      label206:
      paramArrayOfChar = new char[paramInt3];
      System.arraycopy(localObject, 0, paramArrayOfChar, 0, paramInt3);
      System.arraycopy(paramArrayOfChar, 0, localObject, paramInt3 - paramInt1, paramInt1);
      System.arraycopy(paramArrayOfChar, paramInt1, localObject, 0, paramInt3 - paramInt1);
      break label156;
      label248:
      return new String(paramArrayOfChar);
      label258:
      j = 25;
      break label305;
      if (paramInt1 > 0) {
        break label84;
      }
      break label156;
      label286:
      label296:
      for (;;)
      {
        localObject = new char[paramInt3];
        i = 0;
        break label111;
        paramArrayOfChar = new char[paramInt3];
        paramInt1 = 0;
        break;
      }
      label299:
      paramInt1 = 36;
      break label23;
      label305:
      switch (j)
      {
      }
    }
  }
  
  static void ˎ()
  {
    ॱˌ = 118;
  }
  
  /* Error */
  private String ॱ(String paramString)
  {
    // Byte code:
    //   0: goto +36 -> 36
    //   3: iconst_0
    //   4: istore_2
    //   5: goto +132 -> 137
    //   8: aload_1
    //   9: iload_2
    //   10: aload 4
    //   12: aload 4
    //   14: arraylength
    //   15: iload_2
    //   16: isub
    //   17: iconst_1
    //   18: isub
    //   19: baload
    //   20: getstatic 27	o/D:ॱˈ	B
    //   23: ixor
    //   24: i2b
    //   25: bastore
    //   26: iload_2
    //   27: iconst_1
    //   28: iadd
    //   29: istore_2
    //   30: goto +167 -> 197
    //   33: astore_1
    //   34: aload_1
    //   35: athrow
    //   36: goto +8 -> 44
    //   39: iconst_0
    //   40: istore_3
    //   41: goto +348 -> 389
    //   44: getstatic 20	o/D:ॱˑ	I
    //   47: bipush 91
    //   49: iadd
    //   50: istore_2
    //   51: iload_2
    //   52: sipush 128
    //   55: irem
    //   56: putstatic 22	o/D:ॱˉ	I
    //   59: iload_2
    //   60: iconst_2
    //   61: irem
    //   62: ifne +6 -> 68
    //   65: goto -62 -> 3
    //   68: goto +67 -> 135
    //   71: astore_1
    //   72: new 128	java/lang/RuntimeException
    //   75: dup
    //   76: aload_1
    //   77: invokespecial 131	java/lang/RuntimeException:<init>	(Ljava/lang/Throwable;)V
    //   80: athrow
    //   81: new 42	java/lang/String
    //   84: dup
    //   85: aload_1
    //   86: iconst_1
    //   87: iconst_0
    //   88: sipush 186
    //   91: iconst_5
    //   92: iconst_5
    //   93: newarray char
    //   95: dup
    //   96: iconst_0
    //   97: ldc -124
    //   99: castore
    //   100: dup
    //   101: iconst_1
    //   102: ldc -123
    //   104: castore
    //   105: dup
    //   106: iconst_2
    //   107: ldc -122
    //   109: castore
    //   110: dup
    //   111: iconst_3
    //   112: ldc -121
    //   114: castore
    //   115: dup
    //   116: iconst_4
    //   117: ldc -120
    //   119: castore
    //   120: invokestatic 40	o/D:ˊ	(IZII[C)Ljava/lang/String;
    //   123: invokevirtual 46	java/lang/String:intern	()Ljava/lang/String;
    //   126: invokespecial 139	java/lang/String:<init>	([BLjava/lang/String;)V
    //   129: astore_1
    //   130: aload_1
    //   131: areturn
    //   132: astore_1
    //   133: aload_1
    //   134: athrow
    //   135: iconst_1
    //   136: istore_2
    //   137: iload_2
    //   138: tableswitch	default:+22->160, 0:+77->215, 1:+165->303
    //   160: goto +143 -> 303
    //   163: iconst_1
    //   164: istore_3
    //   165: goto +224 -> 389
    //   168: getstatic 20	o/D:ॱˑ	I
    //   171: istore_3
    //   172: iload_3
    //   173: bipush 13
    //   175: iadd
    //   176: istore_3
    //   177: iload_3
    //   178: sipush 128
    //   181: irem
    //   182: putstatic 22	o/D:ॱˉ	I
    //   185: iload_3
    //   186: iconst_2
    //   187: irem
    //   188: ifne +6 -> 194
    //   191: goto +21 -> 212
    //   194: goto -186 -> 8
    //   197: aload 4
    //   199: arraylength
    //   200: istore_3
    //   201: iload_2
    //   202: iload_3
    //   203: if_icmpge +6 -> 209
    //   206: goto -167 -> 39
    //   209: goto -46 -> 163
    //   212: goto -204 -> 8
    //   215: aload_1
    //   216: iconst_3
    //   217: iconst_0
    //   218: sipush 9824
    //   221: bipush 52
    //   223: bipush 10
    //   225: newarray char
    //   227: dup
    //   228: iconst_0
    //   229: ldc -116
    //   231: castore
    //   232: dup
    //   233: iconst_1
    //   234: ldc -115
    //   236: castore
    //   237: dup
    //   238: iconst_2
    //   239: ldc -114
    //   241: castore
    //   242: dup
    //   243: iconst_3
    //   244: ldc -113
    //   246: castore
    //   247: dup
    //   248: iconst_4
    //   249: ldc -112
    //   251: castore
    //   252: dup
    //   253: iconst_5
    //   254: ldc -116
    //   256: castore
    //   257: dup
    //   258: bipush 6
    //   260: ldc 68
    //   262: castore
    //   263: dup
    //   264: bipush 7
    //   266: ldc -111
    //   268: castore
    //   269: dup
    //   270: bipush 8
    //   272: ldc -110
    //   274: castore
    //   275: dup
    //   276: bipush 9
    //   278: ldc -110
    //   280: castore
    //   281: invokestatic 40	o/D:ˊ	(IZII[C)Ljava/lang/String;
    //   284: invokevirtual 46	java/lang/String:intern	()Ljava/lang/String;
    //   287: invokevirtual 150	java/lang/String:getBytes	(Ljava/lang/String;)[B
    //   290: astore 4
    //   292: aload 4
    //   294: arraylength
    //   295: newarray byte
    //   297: astore_1
    //   298: iconst_0
    //   299: istore_2
    //   300: goto -103 -> 197
    //   303: aload_1
    //   304: iconst_4
    //   305: iconst_1
    //   306: sipush 177
    //   309: bipush 10
    //   311: bipush 10
    //   313: newarray char
    //   315: dup
    //   316: iconst_0
    //   317: ldc -116
    //   319: castore
    //   320: dup
    //   321: iconst_1
    //   322: ldc -115
    //   324: castore
    //   325: dup
    //   326: iconst_2
    //   327: ldc -114
    //   329: castore
    //   330: dup
    //   331: iconst_3
    //   332: ldc -113
    //   334: castore
    //   335: dup
    //   336: iconst_4
    //   337: ldc -112
    //   339: castore
    //   340: dup
    //   341: iconst_5
    //   342: ldc -116
    //   344: castore
    //   345: dup
    //   346: bipush 6
    //   348: ldc 68
    //   350: castore
    //   351: dup
    //   352: bipush 7
    //   354: ldc -111
    //   356: castore
    //   357: dup
    //   358: bipush 8
    //   360: ldc -110
    //   362: castore
    //   363: dup
    //   364: bipush 9
    //   366: ldc -110
    //   368: castore
    //   369: invokestatic 40	o/D:ˊ	(IZII[C)Ljava/lang/String;
    //   372: invokevirtual 46	java/lang/String:intern	()Ljava/lang/String;
    //   375: invokevirtual 150	java/lang/String:getBytes	(Ljava/lang/String;)[B
    //   378: astore 4
    //   380: aload 4
    //   382: arraylength
    //   383: newarray byte
    //   385: astore_1
    //   386: goto -88 -> 298
    //   389: iload_3
    //   390: tableswitch	default:+22->412, 0:+-222->168, 1:+-309->81
    //   412: goto -244 -> 168
    // Local variable table:
    //   start	length	slot	name	signature
    //   0	415	0	this	D
    //   0	415	1	paramString	String
    //   4	296	2	i	int
    //   40	350	3	j	int
    //   10	371	4	arrayOfByte	byte[]
    // Exception table:
    //   from	to	target	type
    //   51	59	33	java/lang/Exception
    //   168	172	33	java/lang/Exception
    //   8	26	71	java/io/UnsupportedEncodingException
    //   81	130	71	java/io/UnsupportedEncodingException
    //   197	201	71	java/io/UnsupportedEncodingException
    //   215	298	71	java/io/UnsupportedEncodingException
    //   303	386	71	java/io/UnsupportedEncodingException
    //   44	51	132	java/lang/Exception
    //   51	59	132	java/lang/Exception
    //   177	185	132	java/lang/Exception
  }
  
  /* Error */
  public void ˋ(ᐸ paramᐸ, ะ paramะ)
  {
    // Byte code:
    //   0: goto +70 -> 70
    //   3: aload_0
    //   4: getfield 56	o/D:ߺ	Z
    //   7: ifeq +6 -> 13
    //   10: goto +966 -> 976
    //   13: goto +428 -> 441
    //   16: iload_3
    //   17: lookupswitch	default:+27->44, 41:+80->97, 67:+958->975
    //   44: return
    //   45: bipush 69
    //   47: istore_3
    //   48: goto +897 -> 945
    //   51: astore_1
    //   52: aload_1
    //   53: athrow
    //   54: goto +67 -> 121
    //   57: aload_1
    //   58: checkcast 153	android/app/Activity
    //   61: invokevirtual 156	android/app/Activity:finish	()V
    //   64: return
    //   65: iconst_1
    //   66: istore_3
    //   67: goto +878 -> 945
    //   70: getstatic 22	o/D:ॱˉ	I
    //   73: bipush 23
    //   75: iadd
    //   76: istore_3
    //   77: iload_3
    //   78: sipush 128
    //   81: irem
    //   82: putstatic 20	o/D:ॱˑ	I
    //   85: iload_3
    //   86: iconst_2
    //   87: irem
    //   88: ifeq +6 -> 94
    //   91: goto -46 -> 45
    //   94: goto -29 -> 65
    //   97: getstatic 20	o/D:ॱˑ	I
    //   100: bipush 65
    //   102: iadd
    //   103: istore_3
    //   104: iload_3
    //   105: sipush 128
    //   108: irem
    //   109: putstatic 22	o/D:ॱˉ	I
    //   112: iload_3
    //   113: iconst_2
    //   114: irem
    //   115: ifne +6 -> 121
    //   118: goto -64 -> 54
    //   121: aload_0
    //   122: getfield 160	o/D:ˏ	Landroid/content/Context;
    //   125: astore_1
    //   126: aload_1
    //   127: ifnonnull +6 -> 133
    //   130: goto +317 -> 447
    //   133: goto -76 -> 57
    //   136: aload_1
    //   137: iconst_1
    //   138: iconst_1
    //   139: sipush 222
    //   142: bipush 6
    //   144: bipush 6
    //   146: newarray char
    //   148: dup
    //   149: iconst_0
    //   150: ldc -95
    //   152: castore
    //   153: dup
    //   154: iconst_1
    //   155: ldc 71
    //   157: castore
    //   158: dup
    //   159: iconst_2
    //   160: ldc -94
    //   162: castore
    //   163: dup
    //   164: iconst_3
    //   165: ldc -93
    //   167: castore
    //   168: dup
    //   169: iconst_4
    //   170: ldc -92
    //   172: castore
    //   173: dup
    //   174: iconst_5
    //   175: ldc 35
    //   177: castore
    //   178: invokestatic 40	o/D:ˊ	(IZII[C)Ljava/lang/String;
    //   181: invokevirtual 46	java/lang/String:intern	()Ljava/lang/String;
    //   184: invokestatic 51	o/vq:ˎ	(Ljava/lang/Object;Ljava/lang/String;)V
    //   187: aload_2
    //   188: iconst_3
    //   189: iconst_1
    //   190: sipush 224
    //   193: iconst_5
    //   194: iconst_5
    //   195: newarray char
    //   197: dup
    //   198: iconst_0
    //   199: ldc 71
    //   201: castore
    //   202: dup
    //   203: iconst_1
    //   204: ldc 68
    //   206: castore
    //   207: dup
    //   208: iconst_2
    //   209: ldc 69
    //   211: castore
    //   212: dup
    //   213: iconst_3
    //   214: ldc 68
    //   216: castore
    //   217: dup
    //   218: iconst_4
    //   219: ldc -92
    //   221: castore
    //   222: invokestatic 40	o/D:ˊ	(IZII[C)Ljava/lang/String;
    //   225: invokevirtual 46	java/lang/String:intern	()Ljava/lang/String;
    //   228: invokestatic 51	o/vq:ˎ	(Ljava/lang/Object;Ljava/lang/String;)V
    //   231: getstatic 169	o/C:ˊ	[I
    //   234: aload_2
    //   235: invokevirtual 175	o/ะ:ordinal	()I
    //   238: iaload
    //   239: tableswitch	default:+21->260, 1:+25->264, 2:+-236->3
    //   260: return
    //   261: astore_1
    //   262: aload_1
    //   263: athrow
    //   264: aload_0
    //   265: getfield 160	o/D:ˏ	Landroid/content/Context;
    //   268: new 177	android/content/Intent
    //   271: dup
    //   272: bipush 22
    //   274: iconst_0
    //   275: sipush 211
    //   278: bipush 25
    //   280: bipush 25
    //   282: newarray char
    //   284: dup
    //   285: iconst_0
    //   286: ldc -78
    //   288: castore
    //   289: dup
    //   290: iconst_1
    //   291: ldc -77
    //   293: castore
    //   294: dup
    //   295: iconst_2
    //   296: ldc -76
    //   298: castore
    //   299: dup
    //   300: iconst_3
    //   301: ldc -94
    //   303: castore
    //   304: dup
    //   305: iconst_4
    //   306: ldc -75
    //   308: castore
    //   309: dup
    //   310: iconst_5
    //   311: ldc -74
    //   313: castore
    //   314: dup
    //   315: bipush 6
    //   317: ldc -73
    //   319: castore
    //   320: dup
    //   321: bipush 7
    //   323: ldc -72
    //   325: castore
    //   326: dup
    //   327: bipush 8
    //   329: ldc -72
    //   331: castore
    //   332: dup
    //   333: bipush 9
    //   335: ldc -76
    //   337: castore
    //   338: dup
    //   339: bipush 10
    //   341: ldc -123
    //   343: castore
    //   344: dup
    //   345: bipush 11
    //   347: ldc 32
    //   349: castore
    //   350: dup
    //   351: bipush 12
    //   353: ldc -74
    //   355: castore
    //   356: dup
    //   357: bipush 13
    //   359: ldc -75
    //   361: castore
    //   362: dup
    //   363: bipush 14
    //   365: ldc -112
    //   367: castore
    //   368: dup
    //   369: bipush 15
    //   371: ldc -71
    //   373: castore
    //   374: dup
    //   375: bipush 16
    //   377: ldc 33
    //   379: castore
    //   380: dup
    //   381: bipush 17
    //   383: ldc 33
    //   385: castore
    //   386: dup
    //   387: bipush 18
    //   389: ldc -70
    //   391: castore
    //   392: dup
    //   393: bipush 19
    //   395: ldc -69
    //   397: castore
    //   398: dup
    //   399: bipush 20
    //   401: ldc -68
    //   403: castore
    //   404: dup
    //   405: bipush 21
    //   407: ldc -112
    //   409: castore
    //   410: dup
    //   411: bipush 22
    //   413: ldc -93
    //   415: castore
    //   416: dup
    //   417: bipush 23
    //   419: ldc -123
    //   421: castore
    //   422: dup
    //   423: bipush 24
    //   425: ldc -94
    //   427: castore
    //   428: invokestatic 40	o/D:ˊ	(IZII[C)Ljava/lang/String;
    //   431: invokevirtual 46	java/lang/String:intern	()Ljava/lang/String;
    //   434: invokespecial 191	android/content/Intent:<init>	(Ljava/lang/String;)V
    //   437: invokevirtual 195	android/content/Context:startActivity	(Landroid/content/Intent;)V
    //   440: return
    //   441: bipush 67
    //   443: istore_3
    //   444: goto -428 -> 16
    //   447: new 197	o/uH
    //   450: dup
    //   451: bipush 37
    //   453: iconst_1
    //   454: sipush 213
    //   457: bipush 57
    //   459: bipush 57
    //   461: newarray char
    //   463: dup
    //   464: iconst_0
    //   465: ldc -58
    //   467: castore
    //   468: dup
    //   469: iconst_1
    //   470: ldc 31
    //   472: castore
    //   473: dup
    //   474: iconst_2
    //   475: ldc -123
    //   477: castore
    //   478: dup
    //   479: iconst_3
    //   480: ldc -57
    //   482: castore
    //   483: dup
    //   484: iconst_4
    //   485: ldc -78
    //   487: castore
    //   488: dup
    //   489: iconst_5
    //   490: ldc -58
    //   492: castore
    //   493: dup
    //   494: bipush 6
    //   496: ldc 69
    //   498: castore
    //   499: dup
    //   500: bipush 7
    //   502: ldc 69
    //   504: castore
    //   505: dup
    //   506: bipush 8
    //   508: ldc -74
    //   510: castore
    //   511: dup
    //   512: bipush 9
    //   514: ldc -56
    //   516: castore
    //   517: dup
    //   518: bipush 10
    //   520: ldc -55
    //   522: castore
    //   523: dup
    //   524: bipush 11
    //   526: ldc -56
    //   528: castore
    //   529: dup
    //   530: bipush 12
    //   532: ldc -122
    //   534: castore
    //   535: dup
    //   536: bipush 13
    //   538: ldc -56
    //   540: castore
    //   541: dup
    //   542: bipush 14
    //   544: ldc -58
    //   546: castore
    //   547: dup
    //   548: bipush 15
    //   550: ldc -122
    //   552: castore
    //   553: dup
    //   554: bipush 16
    //   556: ldc -78
    //   558: castore
    //   559: dup
    //   560: bipush 17
    //   562: ldc -58
    //   564: castore
    //   565: dup
    //   566: bipush 18
    //   568: ldc -78
    //   570: castore
    //   571: dup
    //   572: bipush 19
    //   574: ldc -115
    //   576: castore
    //   577: dup
    //   578: bipush 20
    //   580: ldc -121
    //   582: castore
    //   583: dup
    //   584: bipush 21
    //   586: ldc -93
    //   588: castore
    //   589: dup
    //   590: bipush 22
    //   592: ldc -58
    //   594: castore
    //   595: dup
    //   596: bipush 23
    //   598: ldc 31
    //   600: castore
    //   601: dup
    //   602: bipush 24
    //   604: ldc -54
    //   606: castore
    //   607: dup
    //   608: bipush 25
    //   610: ldc -58
    //   612: castore
    //   613: dup
    //   614: bipush 26
    //   616: ldc -78
    //   618: castore
    //   619: dup
    //   620: bipush 27
    //   622: ldc -122
    //   624: castore
    //   625: dup
    //   626: bipush 28
    //   628: ldc -56
    //   630: castore
    //   631: dup
    //   632: bipush 29
    //   634: ldc -56
    //   636: castore
    //   637: dup
    //   638: bipush 30
    //   640: ldc -121
    //   642: castore
    //   643: dup
    //   644: bipush 31
    //   646: ldc -93
    //   648: castore
    //   649: dup
    //   650: bipush 32
    //   652: ldc -58
    //   654: castore
    //   655: dup
    //   656: bipush 33
    //   658: ldc 69
    //   660: castore
    //   661: dup
    //   662: bipush 34
    //   664: ldc 69
    //   666: castore
    //   667: dup
    //   668: bipush 35
    //   670: ldc -74
    //   672: castore
    //   673: dup
    //   674: bipush 36
    //   676: ldc -56
    //   678: castore
    //   679: dup
    //   680: bipush 37
    //   682: ldc -57
    //   684: castore
    //   685: dup
    //   686: bipush 38
    //   688: ldc -78
    //   690: castore
    //   691: dup
    //   692: bipush 39
    //   694: ldc 32
    //   696: castore
    //   697: dup
    //   698: bipush 40
    //   700: ldc -72
    //   702: castore
    //   703: dup
    //   704: bipush 41
    //   706: ldc 32
    //   708: castore
    //   709: dup
    //   710: bipush 42
    //   712: ldc -78
    //   714: castore
    //   715: dup
    //   716: bipush 43
    //   718: ldc -93
    //   720: castore
    //   721: dup
    //   722: bipush 44
    //   724: ldc -53
    //   726: castore
    //   727: dup
    //   728: bipush 45
    //   730: ldc -52
    //   732: castore
    //   733: dup
    //   734: bipush 46
    //   736: ldc -123
    //   738: castore
    //   739: dup
    //   740: bipush 47
    //   742: ldc -123
    //   744: castore
    //   745: dup
    //   746: bipush 48
    //   748: ldc -121
    //   750: castore
    //   751: dup
    //   752: bipush 49
    //   754: ldc -52
    //   756: castore
    //   757: dup
    //   758: bipush 50
    //   760: ldc -51
    //   762: castore
    //   763: dup
    //   764: bipush 51
    //   766: ldc 32
    //   768: castore
    //   769: dup
    //   770: bipush 52
    //   772: ldc -122
    //   774: castore
    //   775: dup
    //   776: bipush 53
    //   778: ldc -50
    //   780: castore
    //   781: dup
    //   782: bipush 54
    //   784: ldc -51
    //   786: castore
    //   787: dup
    //   788: bipush 55
    //   790: ldc -56
    //   792: castore
    //   793: dup
    //   794: bipush 56
    //   796: ldc -121
    //   798: castore
    //   799: invokestatic 40	o/D:ˊ	(IZII[C)Ljava/lang/String;
    //   802: invokevirtual 46	java/lang/String:intern	()Ljava/lang/String;
    //   805: invokespecial 207	o/uH:<init>	(Ljava/lang/String;)V
    //   808: athrow
    //   809: iconst_1
    //   810: iconst_0
    //   811: sipush 14237
    //   814: bipush 68
    //   816: bipush 6
    //   818: newarray char
    //   820: dup
    //   821: iconst_0
    //   822: ldc -95
    //   824: castore
    //   825: dup
    //   826: iconst_1
    //   827: ldc 71
    //   829: castore
    //   830: dup
    //   831: iconst_2
    //   832: ldc -94
    //   834: castore
    //   835: dup
    //   836: iconst_3
    //   837: ldc -93
    //   839: castore
    //   840: dup
    //   841: iconst_4
    //   842: ldc -92
    //   844: castore
    //   845: dup
    //   846: iconst_5
    //   847: ldc 35
    //   849: castore
    //   850: invokestatic 40	o/D:ˊ	(IZII[C)Ljava/lang/String;
    //   853: astore 4
    //   855: aload 4
    //   857: invokevirtual 46	java/lang/String:intern	()Ljava/lang/String;
    //   860: astore 4
    //   862: aload_1
    //   863: aload 4
    //   865: invokestatic 51	o/vq:ˎ	(Ljava/lang/Object;Ljava/lang/String;)V
    //   868: aload_2
    //   869: iconst_2
    //   870: iconst_1
    //   871: sipush 25268
    //   874: iconst_2
    //   875: iconst_5
    //   876: newarray char
    //   878: dup
    //   879: iconst_0
    //   880: ldc 71
    //   882: castore
    //   883: dup
    //   884: iconst_1
    //   885: ldc 68
    //   887: castore
    //   888: dup
    //   889: iconst_2
    //   890: ldc 69
    //   892: castore
    //   893: dup
    //   894: iconst_3
    //   895: ldc 68
    //   897: castore
    //   898: dup
    //   899: iconst_4
    //   900: ldc -92
    //   902: castore
    //   903: invokestatic 40	o/D:ˊ	(IZII[C)Ljava/lang/String;
    //   906: invokevirtual 46	java/lang/String:intern	()Ljava/lang/String;
    //   909: invokestatic 51	o/vq:ˎ	(Ljava/lang/Object;Ljava/lang/String;)V
    //   912: getstatic 169	o/C:ˊ	[I
    //   915: aload_2
    //   916: invokevirtual 175	o/ะ:ordinal	()I
    //   919: iaload
    //   920: istore_3
    //   921: iload_3
    //   922: tableswitch	default:+22->944, 1:+-658->264, 2:+-919->3
    //   944: return
    //   945: iload_3
    //   946: lookupswitch	default:+26->972, 1:+-810->136, 69:+-137->809
    //   972: goto -163 -> 809
    //   975: return
    //   976: bipush 41
    //   978: istore_3
    //   979: goto -963 -> 16
    // Local variable table:
    //   start	length	slot	name	signature
    //   0	982	0	this	D
    //   0	982	1	paramᐸ	ᐸ
    //   0	982	2	paramะ	ะ
    //   16	963	3	i	int
    //   853	11	4	str	String
    // Exception table:
    //   from	to	target	type
    //   809	855	51	java/lang/Exception
    //   862	868	51	java/lang/Exception
    //   868	921	51	java/lang/Exception
    //   855	862	261	java/lang/Exception
  }
}
