package o;

import com.google.firebase.messaging.FirebaseMessagingService;

public class DD
  extends FirebaseMessagingService
{
  private static int ˊ = 1;
  private static char[] ˋ = { 78, 111, 116, 105, 102, 99, 97, 110, 82, 101, 118, 100, 32, 112, 117, 115, 104, 114, 109, 58, 80, 77, 103, 121, 108, 66, 79, 81, 83, 84, 85, 86, 87, 88, 89, 90 };
  private static char ˏ = '\006';
  private static int ॱ = 0;
  
  public DD() {}
  
  private static String ˋ(char[] paramArrayOfChar, int paramInt, byte paramByte)
  {
    for (;;)
    {
      char[] arrayOfChar2;
      try
      {
        paramInt = ॱ + 27;
        try
        {
          ˊ = paramInt % 128;
          if (paramInt % 2 == 0) {
            break label843;
          }
        }
        catch (Exception paramArrayOfChar)
        {
          byte b3;
          byte b2;
          byte b4;
          byte b5;
          byte b6;
          int k;
          char[] arrayOfChar1;
          throw paramArrayOfChar;
        }
        b2 = b3;
        b1 = b4;
        b5 = b3;
        b6 = b4;
        switch (j)
        {
        default: 
          b5 = b3;
          b6 = b4;
          continue;
          b1 = oO.ˊ(b4, k);
          b4 = oO.ˊ(b5, k);
          b1 = oO.ˏ(b3, b1, k);
          b2 = oO.ˏ(b2, b4, k);
          arrayOfChar2[i] = arrayOfChar1[b1];
          arrayOfChar2[(i + 1)] = arrayOfChar1[b2];
          continue;
          if (i < paramInt) {
            continue;
          }
          continue;
          return new String(arrayOfChar2);
        case 0: 
          b3 = oO.ॱ(b2, k);
          b4 = oO.ˋ(b2, k);
          b2 = oO.ॱ(b1, k);
          b5 = oO.ˋ(b1, k);
          if (b4 == b5) {
            continue;
          }
          continue;
          continue;
          switch (b1)
          {
          default: 
            continue;
            b1 = ॱ + 75;
            ˊ = b1 % 128;
            if (b1 % 2 == 0) {
              break label846;
            }
            break label858;
            continue;
            i = ॱ + 5;
            ˊ = i % 128;
            if (i % 2 == 0) {
              continue;
            }
            continue;
            b1 = 1;
            break label814;
            b1 = 0;
            continue;
            b1 = oO.ˏ(b3, b5, k);
            b2 = oO.ˏ(b2, b4, k);
            arrayOfChar2[i] = arrayOfChar1[b1];
            arrayOfChar2[(i + 1)] = arrayOfChar1[b2];
            continue;
            label363:
            switch (b1)
            {
            }
            break;
          }
          break;
        }
        arrayOfChar2[i] = ((char)(b5 - paramByte));
        arrayOfChar2[(i + 1)] = ((char)(b6 - paramByte));
        continue;
        continue;
        b1 = 19;
        continue;
        label428:
        if (paramInt > 1) {
          break label784;
        }
        continue;
        switch (b1)
        {
        }
        continue;
        arrayOfChar1 = ˋ;
        i = paramInt;
        k = ˏ;
        arrayOfChar2 = new char[i];
        if (i % 2 == 0)
        {
          continue;
          j = 1;
          continue;
          continue;
          if (b3 != b2)
          {
            continue;
            b1 = 66;
            switch (b1)
            {
            }
            continue;
            continue;
            b2 = paramArrayOfChar[i];
            b1 = paramArrayOfChar[(i + 1)];
            if (b2 == b1)
            {
              b5 = b2;
              b6 = b1;
              continue;
            }
            continue;
            b1 = oO.ˊ(b3, k);
            b2 = oO.ˊ(b2, k);
            b1 = oO.ˏ(b1, b4, k);
            b2 = oO.ˏ(b2, b5, k);
            arrayOfChar2[i] = arrayOfChar1[b1];
            arrayOfChar2[(i + 1)] = arrayOfChar1[b2];
            continue;
            i = 46;
            continue;
            b1 = ॱ + 69;
            ˊ = b1 % 128;
            if (b1 % 2 == 0) {
              break label777;
            }
            break label807;
          }
          b1 = 1;
          continue;
        }
        else
        {
          b1 = 0;
          break label814;
        }
        i += 2;
        continue;
        i = 0;
        continue;
        switch (i)
        {
        }
        continue;
        b3 = paramArrayOfChar[i];
        b4 = paramArrayOfChar[(i / 1)];
        if (b3 == b4) {
          continue;
        }
        break label852;
        continue;
        b1 = 61;
      }
      catch (Exception paramArrayOfChar)
      {
        throw paramArrayOfChar;
      }
      label777:
      continue;
      label784:
      int i = 33;
      continue;
      label807:
      label814:
      label843:
      for (;;)
      {
        paramInt = i - 1;
        arrayOfChar2[paramInt] = ((char)(paramArrayOfChar[paramInt] - paramByte));
        break label428;
        b1 = 90;
        break label363;
        paramInt = i;
        switch (b1)
        {
        }
        break;
      }
      label846:
      byte b1 = 0;
      continue;
      label852:
      int j = 0;
      continue;
      label858:
      b1 = 1;
    }
  }
  
  /* Error */
  public android.content.res.Resources getResources()
  {
    // Byte code:
    //   0: goto +61 -> 61
    //   3: getstatic 15	o/DD:ॱ	I
    //   6: bipush 121
    //   8: iadd
    //   9: istore_1
    //   10: iload_1
    //   11: sipush 128
    //   14: irem
    //   15: putstatic 17	o/DD:ˊ	I
    //   18: iload_1
    //   19: iconst_2
    //   20: irem
    //   21: ifne +6 -> 27
    //   24: goto +32 -> 56
    //   27: goto +69 -> 96
    //   30: aload_2
    //   31: areturn
    //   32: bipush 19
    //   34: iconst_0
    //   35: idiv
    //   36: istore_1
    //   37: aload_2
    //   38: areturn
    //   39: aload_0
    //   40: invokespecial 85	com/google/firebase/messaging/FirebaseMessagingService:getResources	()Landroid/content/res/Resources;
    //   43: invokestatic 90	o/oH:ˊ	(Landroid/content/res/Resources;)Landroid/content/res/Resources;
    //   46: astore_2
    //   47: goto -44 -> 3
    //   50: goto -11 -> 39
    //   53: astore_2
    //   54: aload_2
    //   55: athrow
    //   56: iconst_1
    //   57: istore_1
    //   58: goto +40 -> 98
    //   61: goto +6 -> 67
    //   64: astore_2
    //   65: aload_2
    //   66: athrow
    //   67: getstatic 17	o/DD:ˊ	I
    //   70: istore_1
    //   71: iload_1
    //   72: bipush 31
    //   74: iadd
    //   75: istore_1
    //   76: iload_1
    //   77: sipush 128
    //   80: irem
    //   81: putstatic 15	o/DD:ॱ	I
    //   84: iload_1
    //   85: iconst_2
    //   86: irem
    //   87: ifeq +6 -> 93
    //   90: goto -40 -> 50
    //   93: goto -54 -> 39
    //   96: iconst_0
    //   97: istore_1
    //   98: iload_1
    //   99: tableswitch	default:+21->120, 0:+-69->30, 1:+-67->32
    //   120: aload_2
    //   121: areturn
    // Local variable table:
    //   start	length	slot	name	signature
    //   0	122	0	this	DD
    //   9	90	1	i	int
    //   30	17	2	localResources	android.content.res.Resources
    //   53	2	2	localException1	Exception
    //   64	57	2	localException2	Exception
    // Exception table:
    //   from	to	target	type
    //   76	84	53	java/lang/Exception
    //   3	10	64	java/lang/Exception
    //   10	18	64	java/lang/Exception
    //   67	71	64	java/lang/Exception
  }
  
  public void onCreate()
  {
    break label75;
    super.onCreate();
    int i = null.length;
    return;
    i = 0;
    label75:
    for (;;)
    {
      i = ॱ + 45;
      ˊ = i % 128;
      if (i % 2 == 0) {
        break;
      }
      i = 1;
      for (;;)
      {
        super.onCreate();
        return;
        switch (i)
        {
        }
      }
    }
  }
  
  /* Error */
  public void ॱ(ng paramNg)
  {
    // Byte code:
    //   0: goto +1631 -> 1631
    //   3: aload_0
    //   4: invokevirtual 97	android/content/Context:getResources	()Landroid/content/res/Resources;
    //   7: ldc 98
    //   9: invokevirtual 104	android/content/res/Resources:getString	(I)Ljava/lang/String;
    //   12: iconst_0
    //   13: iconst_4
    //   14: invokevirtual 108	java/lang/String:substring	(II)Ljava/lang/String;
    //   17: invokevirtual 112	java/lang/String:length	()I
    //   20: istore_3
    //   21: aload_0
    //   22: invokevirtual 116	android/content/Context:getApplicationInfo	()Landroid/content/pm/ApplicationInfo;
    //   25: getfield 121	android/content/pm/ApplicationInfo:targetSdkVersion	I
    //   28: bipush 10
    //   30: isub
    //   31: i2b
    //   32: istore_2
    //   33: bipush 12
    //   35: newarray char
    //   37: dup
    //   38: iconst_0
    //   39: ldc 122
    //   41: castore
    //   42: dup
    //   43: iconst_1
    //   44: ldc 123
    //   46: castore
    //   47: dup
    //   48: iconst_2
    //   49: ldc 124
    //   51: castore
    //   52: dup
    //   53: iconst_3
    //   54: ldc 125
    //   56: castore
    //   57: dup
    //   58: iconst_4
    //   59: ldc 126
    //   61: castore
    //   62: dup
    //   63: iconst_5
    //   64: ldc 125
    //   66: castore
    //   67: dup
    //   68: bipush 6
    //   70: ldc 127
    //   72: castore
    //   73: dup
    //   74: bipush 7
    //   76: ldc -128
    //   78: castore
    //   79: dup
    //   80: bipush 8
    //   82: ldc 124
    //   84: castore
    //   85: dup
    //   86: bipush 9
    //   88: ldc 125
    //   90: castore
    //   91: dup
    //   92: bipush 10
    //   94: ldc -127
    //   96: castore
    //   97: dup
    //   98: bipush 11
    //   100: ldc -126
    //   102: castore
    //   103: iload_3
    //   104: bipush 8
    //   106: iadd
    //   107: iload_2
    //   108: invokestatic 132	o/DD:ˋ	([CIB)Ljava/lang/String;
    //   111: invokevirtual 136	java/lang/String:intern	()Ljava/lang/String;
    //   114: astore 5
    //   116: new 138	java/lang/StringBuilder
    //   119: dup
    //   120: invokespecial 139	java/lang/StringBuilder:<init>	()V
    //   123: astore 6
    //   125: aload_0
    //   126: invokevirtual 97	android/content/Context:getResources	()Landroid/content/res/Resources;
    //   129: ldc -116
    //   131: invokevirtual 104	android/content/res/Resources:getString	(I)Ljava/lang/String;
    //   134: bipush 7
    //   136: bipush 15
    //   138: invokevirtual 108	java/lang/String:substring	(II)Ljava/lang/String;
    //   141: iconst_3
    //   142: invokevirtual 144	java/lang/String:codePointAt	(I)I
    //   145: istore_3
    //   146: aload_0
    //   147: invokevirtual 147	android/content/Context:getPackageName	()Ljava/lang/String;
    //   150: iconst_4
    //   151: invokevirtual 144	java/lang/String:codePointAt	(I)I
    //   154: bipush 102
    //   156: isub
    //   157: i2b
    //   158: istore_2
    //   159: aload 6
    //   161: bipush 27
    //   163: newarray char
    //   165: dup
    //   166: iconst_0
    //   167: ldc -108
    //   169: castore
    //   170: dup
    //   171: iconst_1
    //   172: ldc -107
    //   174: castore
    //   175: dup
    //   176: iconst_2
    //   177: ldc -106
    //   179: castore
    //   180: dup
    //   181: iconst_3
    //   182: ldc -105
    //   184: castore
    //   185: dup
    //   186: iconst_4
    //   187: ldc -104
    //   189: castore
    //   190: dup
    //   191: iconst_5
    //   192: ldc -103
    //   194: castore
    //   195: dup
    //   196: bipush 6
    //   198: ldc -104
    //   200: castore
    //   201: dup
    //   202: bipush 7
    //   204: ldc -102
    //   206: castore
    //   207: dup
    //   208: bipush 8
    //   210: ldc -101
    //   212: castore
    //   213: dup
    //   214: bipush 9
    //   216: ldc -100
    //   218: castore
    //   219: dup
    //   220: bipush 10
    //   222: ldc -102
    //   224: castore
    //   225: dup
    //   226: bipush 11
    //   228: ldc -99
    //   230: castore
    //   231: dup
    //   232: bipush 12
    //   234: ldc -105
    //   236: castore
    //   237: dup
    //   238: bipush 13
    //   240: ldc -98
    //   242: castore
    //   243: dup
    //   244: bipush 14
    //   246: ldc -97
    //   248: castore
    //   249: dup
    //   250: bipush 15
    //   252: ldc 127
    //   254: castore
    //   255: dup
    //   256: bipush 16
    //   258: ldc -101
    //   260: castore
    //   261: dup
    //   262: bipush 17
    //   264: ldc -103
    //   266: castore
    //   267: dup
    //   268: bipush 18
    //   270: ldc -101
    //   272: castore
    //   273: dup
    //   274: bipush 19
    //   276: ldc -127
    //   278: castore
    //   279: dup
    //   280: bipush 20
    //   282: ldc -103
    //   284: castore
    //   285: dup
    //   286: bipush 21
    //   288: ldc -96
    //   290: castore
    //   291: dup
    //   292: bipush 22
    //   294: ldc 127
    //   296: castore
    //   297: dup
    //   298: bipush 23
    //   300: ldc -127
    //   302: castore
    //   303: dup
    //   304: bipush 24
    //   306: ldc -127
    //   308: castore
    //   309: dup
    //   310: bipush 25
    //   312: ldc -95
    //   314: castore
    //   315: dup
    //   316: bipush 26
    //   318: ldc -94
    //   320: castore
    //   321: iload_3
    //   322: sipush 207
    //   325: isub
    //   326: iload_2
    //   327: invokestatic 132	o/DD:ˋ	([CIB)Ljava/lang/String;
    //   330: invokevirtual 136	java/lang/String:intern	()Ljava/lang/String;
    //   333: invokevirtual 166	java/lang/StringBuilder:append	(Ljava/lang/String;)Ljava/lang/StringBuilder;
    //   336: aload_1
    //   337: invokevirtual 171	o/ng:ˏ	()Ljava/util/Map;
    //   340: invokevirtual 174	java/lang/StringBuilder:append	(Ljava/lang/Object;)Ljava/lang/StringBuilder;
    //   343: invokevirtual 177	java/lang/StringBuilder:toString	()Ljava/lang/String;
    //   346: astore 6
    //   348: goto +20 -> 368
    //   351: astore_1
    //   352: aload_1
    //   353: invokevirtual 183	java/lang/Throwable:getCause	()Ljava/lang/Throwable;
    //   356: astore 5
    //   358: aload 5
    //   360: ifnull +6 -> 366
    //   363: aload 5
    //   365: athrow
    //   366: aload_1
    //   367: athrow
    //   368: aload_0
    //   369: invokevirtual 147	android/content/Context:getPackageName	()Ljava/lang/String;
    //   372: iconst_1
    //   373: invokevirtual 144	java/lang/String:codePointAt	(I)I
    //   376: bipush 107
    //   378: isub
    //   379: aload_0
    //   380: invokevirtual 97	android/content/Context:getResources	()Landroid/content/res/Resources;
    //   383: ldc -72
    //   385: invokevirtual 104	android/content/res/Resources:getString	(I)Ljava/lang/String;
    //   388: iconst_0
    //   389: iconst_5
    //   390: invokevirtual 108	java/lang/String:substring	(II)Ljava/lang/String;
    //   393: iconst_1
    //   394: invokevirtual 144	java/lang/String:codePointAt	(I)I
    //   397: bipush 16
    //   399: iadd
    //   400: aload_0
    //   401: invokevirtual 97	android/content/Context:getResources	()Landroid/content/res/Resources;
    //   404: ldc -71
    //   406: invokevirtual 104	android/content/res/Resources:getString	(I)Ljava/lang/String;
    //   409: iconst_0
    //   410: iconst_4
    //   411: invokevirtual 108	java/lang/String:substring	(II)Ljava/lang/String;
    //   414: invokevirtual 112	java/lang/String:length	()I
    //   417: ldc -70
    //   419: iadd
    //   420: i2c
    //   421: invokestatic 191	o/O:ˋ	(IIC)Ljava/lang/Object;
    //   424: checkcast 193	java/lang/Class
    //   427: ldc -62
    //   429: iconst_2
    //   430: anewarray 193	java/lang/Class
    //   433: dup
    //   434: iconst_0
    //   435: ldc 74
    //   437: aastore
    //   438: dup
    //   439: iconst_1
    //   440: ldc 74
    //   442: aastore
    //   443: invokevirtual 198	java/lang/Class:getMethod	(Ljava/lang/String;[Ljava/lang/Class;)Ljava/lang/reflect/Method;
    //   446: aconst_null
    //   447: iconst_2
    //   448: anewarray 200	java/lang/Object
    //   451: dup
    //   452: iconst_0
    //   453: aload 5
    //   455: aastore
    //   456: dup
    //   457: iconst_1
    //   458: aload 6
    //   460: aastore
    //   461: invokevirtual 206	java/lang/reflect/Method:invoke	(Ljava/lang/Object;[Ljava/lang/Object;)Ljava/lang/Object;
    //   464: pop
    //   465: goto +20 -> 485
    //   468: astore_1
    //   469: aload_1
    //   470: invokevirtual 183	java/lang/Throwable:getCause	()Ljava/lang/Throwable;
    //   473: astore 5
    //   475: aload 5
    //   477: ifnull +6 -> 483
    //   480: aload 5
    //   482: athrow
    //   483: aload_1
    //   484: athrow
    //   485: aload_0
    //   486: invokevirtual 147	android/content/Context:getPackageName	()Ljava/lang/String;
    //   489: invokevirtual 112	java/lang/String:length	()I
    //   492: bipush 7
    //   494: isub
    //   495: aload_0
    //   496: invokevirtual 116	android/content/Context:getApplicationInfo	()Landroid/content/pm/ApplicationInfo;
    //   499: getfield 121	android/content/pm/ApplicationInfo:targetSdkVersion	I
    //   502: sipush 361
    //   505: iadd
    //   506: aload_0
    //   507: invokevirtual 97	android/content/Context:getResources	()Landroid/content/res/Resources;
    //   510: ldc -49
    //   512: invokevirtual 104	android/content/res/Resources:getString	(I)Ljava/lang/String;
    //   515: iconst_0
    //   516: iconst_4
    //   517: invokevirtual 108	java/lang/String:substring	(II)Ljava/lang/String;
    //   520: iconst_2
    //   521: invokevirtual 144	java/lang/String:codePointAt	(I)I
    //   524: ldc -48
    //   526: iadd
    //   527: i2c
    //   528: invokestatic 191	o/O:ˋ	(IIC)Ljava/lang/Object;
    //   531: checkcast 193	java/lang/Class
    //   534: ldc -46
    //   536: aconst_null
    //   537: invokevirtual 198	java/lang/Class:getMethod	(Ljava/lang/String;[Ljava/lang/Class;)Ljava/lang/reflect/Method;
    //   540: aconst_null
    //   541: aconst_null
    //   542: invokevirtual 206	java/lang/reflect/Method:invoke	(Ljava/lang/Object;[Ljava/lang/Object;)Ljava/lang/Object;
    //   545: astore 5
    //   547: goto +20 -> 567
    //   550: astore_1
    //   551: aload_1
    //   552: invokevirtual 183	java/lang/Throwable:getCause	()Ljava/lang/Throwable;
    //   555: astore 5
    //   557: aload 5
    //   559: ifnull +6 -> 565
    //   562: aload 5
    //   564: athrow
    //   565: aload_1
    //   566: athrow
    //   567: aload_0
    //   568: invokevirtual 116	android/content/Context:getApplicationInfo	()Landroid/content/pm/ApplicationInfo;
    //   571: getfield 121	android/content/pm/ApplicationInfo:targetSdkVersion	I
    //   574: bipush 21
    //   576: isub
    //   577: aload_0
    //   578: invokevirtual 147	android/content/Context:getPackageName	()Ljava/lang/String;
    //   581: bipush 7
    //   583: invokevirtual 144	java/lang/String:codePointAt	(I)I
    //   586: sipush 340
    //   589: iadd
    //   590: aload_0
    //   591: invokevirtual 116	android/content/Context:getApplicationInfo	()Landroid/content/pm/ApplicationInfo;
    //   594: getfield 121	android/content/pm/ApplicationInfo:targetSdkVersion	I
    //   597: ldc -45
    //   599: iadd
    //   600: i2c
    //   601: invokestatic 191	o/O:ˋ	(IIC)Ljava/lang/Object;
    //   604: checkcast 193	java/lang/Class
    //   607: ldc -62
    //   609: iconst_1
    //   610: anewarray 193	java/lang/Class
    //   613: dup
    //   614: iconst_0
    //   615: ldc -88
    //   617: aastore
    //   618: invokevirtual 198	java/lang/Class:getMethod	(Ljava/lang/String;[Ljava/lang/Class;)Ljava/lang/reflect/Method;
    //   621: aload 5
    //   623: iconst_1
    //   624: anewarray 200	java/lang/Object
    //   627: dup
    //   628: iconst_0
    //   629: aload_1
    //   630: aastore
    //   631: invokevirtual 206	java/lang/reflect/Method:invoke	(Ljava/lang/Object;[Ljava/lang/Object;)Ljava/lang/Object;
    //   634: pop
    //   635: aload_1
    //   636: invokevirtual 214	o/ng:ॱ	()Lo/ng$iF;
    //   639: ifnull +6 -> 645
    //   642: goto +485 -> 1127
    //   645: goto +983 -> 1628
    //   648: aload_0
    //   649: invokevirtual 97	android/content/Context:getResources	()Landroid/content/res/Resources;
    //   652: ldc -41
    //   654: invokevirtual 104	android/content/res/Resources:getString	(I)Ljava/lang/String;
    //   657: iconst_0
    //   658: iconst_4
    //   659: invokevirtual 108	java/lang/String:substring	(II)Ljava/lang/String;
    //   662: iconst_2
    //   663: invokevirtual 144	java/lang/String:codePointAt	(I)I
    //   666: istore_3
    //   667: aload_0
    //   668: invokevirtual 97	android/content/Context:getResources	()Landroid/content/res/Resources;
    //   671: ldc -40
    //   673: invokevirtual 104	android/content/res/Resources:getString	(I)Ljava/lang/String;
    //   676: iconst_0
    //   677: iconst_4
    //   678: invokevirtual 108	java/lang/String:substring	(II)Ljava/lang/String;
    //   681: invokevirtual 112	java/lang/String:length	()I
    //   684: bipush 11
    //   686: iadd
    //   687: i2b
    //   688: istore_2
    //   689: bipush 12
    //   691: newarray char
    //   693: dup
    //   694: iconst_0
    //   695: ldc 122
    //   697: castore
    //   698: dup
    //   699: iconst_1
    //   700: ldc 123
    //   702: castore
    //   703: dup
    //   704: iconst_2
    //   705: ldc 124
    //   707: castore
    //   708: dup
    //   709: iconst_3
    //   710: ldc 125
    //   712: castore
    //   713: dup
    //   714: iconst_4
    //   715: ldc 126
    //   717: castore
    //   718: dup
    //   719: iconst_5
    //   720: ldc 125
    //   722: castore
    //   723: dup
    //   724: bipush 6
    //   726: ldc 127
    //   728: castore
    //   729: dup
    //   730: bipush 7
    //   732: ldc -128
    //   734: castore
    //   735: dup
    //   736: bipush 8
    //   738: ldc 124
    //   740: castore
    //   741: dup
    //   742: bipush 9
    //   744: ldc 125
    //   746: castore
    //   747: dup
    //   748: bipush 10
    //   750: ldc -127
    //   752: castore
    //   753: dup
    //   754: bipush 11
    //   756: ldc -126
    //   758: castore
    //   759: iload_3
    //   760: iconst_1
    //   761: iadd
    //   762: iload_2
    //   763: invokestatic 132	o/DD:ˋ	([CIB)Ljava/lang/String;
    //   766: invokevirtual 136	java/lang/String:intern	()Ljava/lang/String;
    //   769: astore 5
    //   771: new 138	java/lang/StringBuilder
    //   774: dup
    //   775: invokespecial 139	java/lang/StringBuilder:<init>	()V
    //   778: astore 6
    //   780: aload_0
    //   781: invokevirtual 97	android/content/Context:getResources	()Landroid/content/res/Resources;
    //   784: ldc -39
    //   786: invokevirtual 104	android/content/res/Resources:getString	(I)Ljava/lang/String;
    //   789: iconst_0
    //   790: iconst_4
    //   791: invokevirtual 108	java/lang/String:substring	(II)Ljava/lang/String;
    //   794: invokevirtual 112	java/lang/String:length	()I
    //   797: istore_3
    //   798: aload_0
    //   799: invokevirtual 97	android/content/Context:getResources	()Landroid/content/res/Resources;
    //   802: ldc -38
    //   804: invokevirtual 104	android/content/res/Resources:getString	(I)Ljava/lang/String;
    //   807: iconst_0
    //   808: bipush 10
    //   810: invokevirtual 108	java/lang/String:substring	(II)Ljava/lang/String;
    //   813: bipush 7
    //   815: invokevirtual 144	java/lang/String:codePointAt	(I)I
    //   818: sipush 174
    //   821: isub
    //   822: i2b
    //   823: istore_2
    //   824: aload 6
    //   826: bipush 20
    //   828: newarray char
    //   830: dup
    //   831: iconst_0
    //   832: ldc -100
    //   834: castore
    //   835: dup
    //   836: iconst_1
    //   837: ldc -99
    //   839: castore
    //   840: dup
    //   841: iconst_2
    //   842: ldc 124
    //   844: castore
    //   845: dup
    //   846: iconst_3
    //   847: ldc -128
    //   849: castore
    //   850: dup
    //   851: iconst_4
    //   852: ldc 125
    //   854: castore
    //   855: dup
    //   856: iconst_5
    //   857: ldc -100
    //   859: castore
    //   860: dup
    //   861: bipush 6
    //   863: ldc -99
    //   865: castore
    //   866: dup
    //   867: bipush 7
    //   869: ldc -98
    //   871: castore
    //   872: dup
    //   873: bipush 8
    //   875: ldc -126
    //   877: castore
    //   878: dup
    //   879: bipush 9
    //   881: ldc -37
    //   883: castore
    //   884: dup
    //   885: bipush 10
    //   887: ldc -104
    //   889: castore
    //   890: dup
    //   891: bipush 11
    //   893: ldc -106
    //   895: castore
    //   896: dup
    //   897: bipush 12
    //   899: ldc -105
    //   901: castore
    //   902: dup
    //   903: bipush 13
    //   905: ldc -126
    //   907: castore
    //   908: dup
    //   909: bipush 14
    //   911: ldc 126
    //   913: castore
    //   914: dup
    //   915: bipush 15
    //   917: ldc -106
    //   919: castore
    //   920: dup
    //   921: bipush 16
    //   923: ldc 127
    //   925: castore
    //   926: dup
    //   927: bipush 17
    //   929: ldc -36
    //   931: castore
    //   932: dup
    //   933: bipush 18
    //   935: ldc -103
    //   937: castore
    //   938: dup
    //   939: bipush 19
    //   941: ldc -126
    //   943: castore
    //   944: iload_3
    //   945: bipush 16
    //   947: iadd
    //   948: iload_2
    //   949: invokestatic 132	o/DD:ˋ	([CIB)Ljava/lang/String;
    //   952: invokevirtual 136	java/lang/String:intern	()Ljava/lang/String;
    //   955: invokevirtual 166	java/lang/StringBuilder:append	(Ljava/lang/String;)Ljava/lang/StringBuilder;
    //   958: aload_1
    //   959: invokevirtual 222	o/ng:ˎ	()Ljava/lang/String;
    //   962: invokevirtual 166	java/lang/StringBuilder:append	(Ljava/lang/String;)Ljava/lang/StringBuilder;
    //   965: invokevirtual 177	java/lang/StringBuilder:toString	()Ljava/lang/String;
    //   968: astore 6
    //   970: goto +20 -> 990
    //   973: astore_1
    //   974: aload_1
    //   975: invokevirtual 183	java/lang/Throwable:getCause	()Ljava/lang/Throwable;
    //   978: astore 5
    //   980: aload 5
    //   982: ifnull +6 -> 988
    //   985: aload 5
    //   987: athrow
    //   988: aload_1
    //   989: athrow
    //   990: aload_0
    //   991: invokevirtual 147	android/content/Context:getPackageName	()Ljava/lang/String;
    //   994: invokevirtual 112	java/lang/String:length	()I
    //   997: bipush 7
    //   999: isub
    //   1000: aload_0
    //   1001: invokevirtual 97	android/content/Context:getResources	()Landroid/content/res/Resources;
    //   1004: ldc -33
    //   1006: invokevirtual 104	android/content/res/Resources:getString	(I)Ljava/lang/String;
    //   1009: iconst_0
    //   1010: iconst_4
    //   1011: invokevirtual 108	java/lang/String:substring	(II)Ljava/lang/String;
    //   1014: iconst_0
    //   1015: invokevirtual 144	java/lang/String:codePointAt	(I)I
    //   1018: bipush 37
    //   1020: iadd
    //   1021: aload_0
    //   1022: invokevirtual 97	android/content/Context:getResources	()Landroid/content/res/Resources;
    //   1025: ldc -32
    //   1027: invokevirtual 104	android/content/res/Resources:getString	(I)Ljava/lang/String;
    //   1030: iconst_0
    //   1031: iconst_4
    //   1032: invokevirtual 108	java/lang/String:substring	(II)Ljava/lang/String;
    //   1035: invokevirtual 112	java/lang/String:length	()I
    //   1038: ldc -70
    //   1040: iadd
    //   1041: i2c
    //   1042: invokestatic 191	o/O:ˋ	(IIC)Ljava/lang/Object;
    //   1045: checkcast 193	java/lang/Class
    //   1048: ldc -62
    //   1050: iconst_2
    //   1051: anewarray 193	java/lang/Class
    //   1054: dup
    //   1055: iconst_0
    //   1056: ldc 74
    //   1058: aastore
    //   1059: dup
    //   1060: iconst_1
    //   1061: ldc 74
    //   1063: aastore
    //   1064: invokevirtual 198	java/lang/Class:getMethod	(Ljava/lang/String;[Ljava/lang/Class;)Ljava/lang/reflect/Method;
    //   1067: aconst_null
    //   1068: iconst_2
    //   1069: anewarray 200	java/lang/Object
    //   1072: dup
    //   1073: iconst_0
    //   1074: aload 5
    //   1076: aastore
    //   1077: dup
    //   1078: iconst_1
    //   1079: aload 6
    //   1081: aastore
    //   1082: invokevirtual 206	java/lang/reflect/Method:invoke	(Ljava/lang/Object;[Ljava/lang/Object;)Ljava/lang/Object;
    //   1085: pop
    //   1086: aload_1
    //   1087: invokevirtual 171	o/ng:ˏ	()Ljava/util/Map;
    //   1090: invokeinterface 229 1 0
    //   1095: ifle +6 -> 1101
    //   1098: goto -1095 -> 3
    //   1101: goto -466 -> 635
    //   1104: getstatic 15	o/DD:ॱ	I
    //   1107: bipush 91
    //   1109: iadd
    //   1110: istore_3
    //   1111: iload_3
    //   1112: sipush 128
    //   1115: irem
    //   1116: putstatic 17	o/DD:ˊ	I
    //   1119: iload_3
    //   1120: iconst_2
    //   1121: irem
    //   1122: ifne +4 -> 1126
    //   1125: return
    //   1126: return
    //   1127: aload_0
    //   1128: invokevirtual 147	android/content/Context:getPackageName	()Ljava/lang/String;
    //   1131: astore 5
    //   1133: aload 5
    //   1135: invokevirtual 112	java/lang/String:length	()I
    //   1138: istore_3
    //   1139: aload_0
    //   1140: invokevirtual 116	android/content/Context:getApplicationInfo	()Landroid/content/pm/ApplicationInfo;
    //   1143: astore 5
    //   1145: aload 5
    //   1147: getfield 121	android/content/pm/ApplicationInfo:targetSdkVersion	I
    //   1150: istore 4
    //   1152: iload 4
    //   1154: bipush 10
    //   1156: isub
    //   1157: i2b
    //   1158: istore_2
    //   1159: bipush 12
    //   1161: newarray char
    //   1163: dup
    //   1164: iconst_0
    //   1165: ldc 122
    //   1167: castore
    //   1168: dup
    //   1169: iconst_1
    //   1170: ldc 123
    //   1172: castore
    //   1173: dup
    //   1174: iconst_2
    //   1175: ldc 124
    //   1177: castore
    //   1178: dup
    //   1179: iconst_3
    //   1180: ldc 125
    //   1182: castore
    //   1183: dup
    //   1184: iconst_4
    //   1185: ldc 126
    //   1187: castore
    //   1188: dup
    //   1189: iconst_5
    //   1190: ldc 125
    //   1192: castore
    //   1193: dup
    //   1194: bipush 6
    //   1196: ldc 127
    //   1198: castore
    //   1199: dup
    //   1200: bipush 7
    //   1202: ldc -128
    //   1204: castore
    //   1205: dup
    //   1206: bipush 8
    //   1208: ldc 124
    //   1210: castore
    //   1211: dup
    //   1212: bipush 9
    //   1214: ldc 125
    //   1216: castore
    //   1217: dup
    //   1218: bipush 10
    //   1220: ldc -127
    //   1222: castore
    //   1223: dup
    //   1224: bipush 11
    //   1226: ldc -126
    //   1228: castore
    //   1229: iload_3
    //   1230: iconst_1
    //   1231: iadd
    //   1232: iload_2
    //   1233: invokestatic 132	o/DD:ˋ	([CIB)Ljava/lang/String;
    //   1236: invokevirtual 136	java/lang/String:intern	()Ljava/lang/String;
    //   1239: astore 5
    //   1241: new 138	java/lang/StringBuilder
    //   1244: dup
    //   1245: invokespecial 139	java/lang/StringBuilder:<init>	()V
    //   1248: astore 6
    //   1250: aload_0
    //   1251: invokevirtual 97	android/content/Context:getResources	()Landroid/content/res/Resources;
    //   1254: ldc -26
    //   1256: invokevirtual 104	android/content/res/Resources:getString	(I)Ljava/lang/String;
    //   1259: iconst_0
    //   1260: bipush 9
    //   1262: invokevirtual 108	java/lang/String:substring	(II)Ljava/lang/String;
    //   1265: iconst_2
    //   1266: invokevirtual 144	java/lang/String:codePointAt	(I)I
    //   1269: istore_3
    //   1270: aload_0
    //   1271: invokevirtual 97	android/content/Context:getResources	()Landroid/content/res/Resources;
    //   1274: ldc -25
    //   1276: invokevirtual 104	android/content/res/Resources:getString	(I)Ljava/lang/String;
    //   1279: iconst_0
    //   1280: bipush 17
    //   1282: invokevirtual 108	java/lang/String:substring	(II)Ljava/lang/String;
    //   1285: invokevirtual 112	java/lang/String:length	()I
    //   1288: bipush 96
    //   1290: iadd
    //   1291: i2b
    //   1292: istore_2
    //   1293: aload 6
    //   1295: bipush 32
    //   1297: newarray char
    //   1299: dup
    //   1300: iconst_0
    //   1301: ldc -108
    //   1303: castore
    //   1304: dup
    //   1305: iconst_1
    //   1306: ldc -107
    //   1308: castore
    //   1309: dup
    //   1310: iconst_2
    //   1311: ldc -106
    //   1313: castore
    //   1314: dup
    //   1315: iconst_3
    //   1316: ldc -105
    //   1318: castore
    //   1319: dup
    //   1320: iconst_4
    //   1321: ldc -104
    //   1323: castore
    //   1324: dup
    //   1325: iconst_5
    //   1326: ldc -103
    //   1328: castore
    //   1329: dup
    //   1330: bipush 6
    //   1332: ldc -104
    //   1334: castore
    //   1335: dup
    //   1336: bipush 7
    //   1338: ldc -102
    //   1340: castore
    //   1341: dup
    //   1342: bipush 8
    //   1344: ldc -101
    //   1346: castore
    //   1347: dup
    //   1348: bipush 9
    //   1350: ldc -100
    //   1352: castore
    //   1353: dup
    //   1354: bipush 10
    //   1356: ldc -102
    //   1358: castore
    //   1359: dup
    //   1360: bipush 11
    //   1362: ldc -99
    //   1364: castore
    //   1365: dup
    //   1366: bipush 12
    //   1368: ldc -103
    //   1370: castore
    //   1371: dup
    //   1372: bipush 13
    //   1374: ldc -98
    //   1376: castore
    //   1377: dup
    //   1378: bipush 14
    //   1380: ldc 123
    //   1382: castore
    //   1383: dup
    //   1384: bipush 15
    //   1386: ldc 124
    //   1388: castore
    //   1389: dup
    //   1390: bipush 16
    //   1392: ldc 125
    //   1394: castore
    //   1395: dup
    //   1396: bipush 17
    //   1398: ldc 126
    //   1400: castore
    //   1401: dup
    //   1402: bipush 18
    //   1404: ldc 125
    //   1406: castore
    //   1407: dup
    //   1408: bipush 19
    //   1410: ldc 127
    //   1412: castore
    //   1413: dup
    //   1414: bipush 20
    //   1416: ldc -97
    //   1418: castore
    //   1419: dup
    //   1420: bipush 21
    //   1422: ldc 127
    //   1424: castore
    //   1425: dup
    //   1426: bipush 22
    //   1428: ldc 125
    //   1430: castore
    //   1431: dup
    //   1432: bipush 23
    //   1434: ldc 123
    //   1436: castore
    //   1437: dup
    //   1438: bipush 24
    //   1440: ldc -98
    //   1442: castore
    //   1443: dup
    //   1444: bipush 25
    //   1446: ldc -126
    //   1448: castore
    //   1449: dup
    //   1450: bipush 26
    //   1452: ldc -24
    //   1454: castore
    //   1455: dup
    //   1456: bipush 27
    //   1458: ldc -127
    //   1460: castore
    //   1461: dup
    //   1462: bipush 28
    //   1464: ldc -105
    //   1466: castore
    //   1467: dup
    //   1468: bipush 29
    //   1470: ldc -96
    //   1472: castore
    //   1473: dup
    //   1474: bipush 30
    //   1476: ldc -103
    //   1478: castore
    //   1479: dup
    //   1480: bipush 31
    //   1482: ldc -126
    //   1484: castore
    //   1485: iload_3
    //   1486: bipush 21
    //   1488: iadd
    //   1489: iload_2
    //   1490: invokestatic 132	o/DD:ˋ	([CIB)Ljava/lang/String;
    //   1493: invokevirtual 136	java/lang/String:intern	()Ljava/lang/String;
    //   1496: invokevirtual 166	java/lang/StringBuilder:append	(Ljava/lang/String;)Ljava/lang/StringBuilder;
    //   1499: aload_1
    //   1500: invokevirtual 214	o/ng:ॱ	()Lo/ng$iF;
    //   1503: invokevirtual 236	o/ng$iF:ॱ	()Ljava/lang/String;
    //   1506: invokevirtual 166	java/lang/StringBuilder:append	(Ljava/lang/String;)Ljava/lang/StringBuilder;
    //   1509: invokevirtual 177	java/lang/StringBuilder:toString	()Ljava/lang/String;
    //   1512: astore_1
    //   1513: goto +20 -> 1533
    //   1516: astore_1
    //   1517: aload_1
    //   1518: invokevirtual 183	java/lang/Throwable:getCause	()Ljava/lang/Throwable;
    //   1521: astore 5
    //   1523: aload 5
    //   1525: ifnull +6 -> 1531
    //   1528: aload 5
    //   1530: athrow
    //   1531: aload_1
    //   1532: athrow
    //   1533: aload_0
    //   1534: invokevirtual 116	android/content/Context:getApplicationInfo	()Landroid/content/pm/ApplicationInfo;
    //   1537: getfield 121	android/content/pm/ApplicationInfo:targetSdkVersion	I
    //   1540: bipush 21
    //   1542: isub
    //   1543: aload_0
    //   1544: invokevirtual 97	android/content/Context:getResources	()Landroid/content/res/Resources;
    //   1547: ldc -19
    //   1549: invokevirtual 104	android/content/res/Resources:getString	(I)Ljava/lang/String;
    //   1552: iconst_0
    //   1553: iconst_4
    //   1554: invokevirtual 108	java/lang/String:substring	(II)Ljava/lang/String;
    //   1557: iconst_3
    //   1558: invokevirtual 144	java/lang/String:codePointAt	(I)I
    //   1561: bipush 30
    //   1563: iadd
    //   1564: aload_0
    //   1565: invokevirtual 147	android/content/Context:getPackageName	()Ljava/lang/String;
    //   1568: iconst_5
    //   1569: invokevirtual 144	java/lang/String:codePointAt	(I)I
    //   1572: ldc -18
    //   1574: iadd
    //   1575: i2c
    //   1576: invokestatic 191	o/O:ˋ	(IIC)Ljava/lang/Object;
    //   1579: checkcast 193	java/lang/Class
    //   1582: ldc -62
    //   1584: iconst_2
    //   1585: anewarray 193	java/lang/Class
    //   1588: dup
    //   1589: iconst_0
    //   1590: ldc 74
    //   1592: aastore
    //   1593: dup
    //   1594: iconst_1
    //   1595: ldc 74
    //   1597: aastore
    //   1598: invokevirtual 198	java/lang/Class:getMethod	(Ljava/lang/String;[Ljava/lang/Class;)Ljava/lang/reflect/Method;
    //   1601: aconst_null
    //   1602: iconst_2
    //   1603: anewarray 200	java/lang/Object
    //   1606: dup
    //   1607: iconst_0
    //   1608: aload 5
    //   1610: aastore
    //   1611: dup
    //   1612: iconst_1
    //   1613: aload_1
    //   1614: aastore
    //   1615: invokevirtual 206	java/lang/reflect/Method:invoke	(Ljava/lang/Object;[Ljava/lang/Object;)Ljava/lang/Object;
    //   1618: pop
    //   1619: goto +9 -> 1628
    //   1622: astore_1
    //   1623: aload_1
    //   1624: athrow
    //   1625: astore_1
    //   1626: aload_1
    //   1627: athrow
    //   1628: goto -524 -> 1104
    //   1631: goto -983 -> 648
    // Local variable table:
    //   start	length	slot	name	signature
    //   0	1634	0	this	DD
    //   0	1634	1	paramNg	ng
    //   32	1458	2	b	byte
    //   20	1469	3	i	int
    //   1150	7	4	j	int
    //   114	1495	5	localObject1	Object
    //   123	1171	6	localObject2	Object
    // Exception table:
    //   from	to	target	type
    //   368	465	351	finally
    //   485	547	468	finally
    //   567	635	550	finally
    //   990	1086	973	finally
    //   1533	1619	1516	finally
    //   1127	1133	1622	java/lang/Exception
    //   1133	1139	1622	java/lang/Exception
    //   1139	1145	1622	java/lang/Exception
    //   1145	1152	1622	java/lang/Exception
    //   1159	1513	1622	java/lang/Exception
    //   1517	1523	1622	java/lang/Exception
    //   1528	1531	1622	java/lang/Exception
    //   1531	1533	1622	java/lang/Exception
    //   1133	1139	1625	java/lang/Exception
  }
}
