package o;

import android.content.Context;
import android.content.res.Resources;
import android.text.TextUtils;
import com.google.firebase.iid.FirebaseInstanceIdService;

public final class DG
  extends FirebaseInstanceIdService
{
  private static int ʼ = 1;
  private static int ˊ = 0;
  private static long ˋ = -7644939847631573324L;
  private static char[] ˏ = { -28217, 32610, 19646, 24022, 11039, 14401, 2559, 5950, -7057, -2659, -15680, -12199, -24135, -28948, -25590, 27983, 31390, 18470, 70, -4387, -8934, -13191, -17742, -22043, -26549, -31095, 30185, 25658, 21371, 16840, 12305, 8010, 3515, -791, -5367, -9840, -14202, -18629, -22923, -27472, -31951, 29250, 24723, 20448, 15913, 11410, 7123, 2561, -1744, -6171, -30711, 26271, 21832, 17463, 13036, 8619, 4122, -29908, 26039, 22128, 18195, 12760, 8847, 4897, 3555, -278, -4233, -10202, -13588, -17606, 70, -4387, -8934, -13191, -17742, -22043, -26549, -31095, 30080, 25600, 21351, 16855, 12309, 8010, 3554, -852, 65, -4412, -8936, -13200, -17735, -22041, -26535, -31080, 30153, 25659, 21350, 16885, 12308, 65, -4412, -8959, -13231, -17743, -22038, -26535, -31093, 30149, 25638, 21286, 16861, 12288, 8013, 3568, -859 };
  private final Id ॱ;
  
  /* Error */
  public DG()
  {
    // Byte code:
    //   0: aload_0
    //   1: invokespecial 144	com/google/firebase/iid/FirebaseInstanceIdService:<init>	()V
    //   4: goto +17 -> 21
    //   7: astore_1
    //   8: aload_1
    //   9: invokevirtual 150	java/lang/Throwable:getCause	()Ljava/lang/Throwable;
    //   12: astore_2
    //   13: aload_2
    //   14: ifnull +5 -> 19
    //   17: aload_2
    //   18: athrow
    //   19: aload_1
    //   20: athrow
    //   21: iconst_4
    //   22: sipush 135
    //   25: ldc -105
    //   27: invokestatic 156	o/O:ˋ	(IIC)Ljava/lang/Object;
    //   30: checkcast 158	java/lang/Class
    //   33: ldc -96
    //   35: aconst_null
    //   36: invokevirtual 164	java/lang/Class:getMethod	(Ljava/lang/String;[Ljava/lang/Class;)Ljava/lang/reflect/Method;
    //   39: aconst_null
    //   40: aconst_null
    //   41: invokevirtual 170	java/lang/reflect/Method:invoke	(Ljava/lang/Object;[Ljava/lang/Object;)Ljava/lang/Object;
    //   44: checkcast 172	o/Id
    //   47: astore_1
    //   48: bipush 99
    //   50: iconst_0
    //   51: bipush 16
    //   53: invokestatic 175	o/DG:ˏ	(ICI)Ljava/lang/String;
    //   56: astore_2
    //   57: aload_2
    //   58: invokevirtual 181	java/lang/String:intern	()Ljava/lang/String;
    //   61: astore_2
    //   62: aload_1
    //   63: aload_2
    //   64: invokestatic 186	o/vq:ˋ	(Ljava/lang/Object;Ljava/lang/String;)V
    //   67: aload_0
    //   68: aload_1
    //   69: putfield 188	o/DG:ॱ	Lo/Id;
    //   72: return
    //   73: astore_1
    //   74: aload_1
    //   75: athrow
    // Local variable table:
    //   start	length	slot	name	signature
    //   0	76	0	this	DG
    //   7	13	1	localObject1	Object
    //   47	22	1	localId	Id
    //   73	2	1	localException	Exception
    //   12	52	2	localObject2	Object
    // Exception table:
    //   from	to	target	type
    //   21	48	7	finally
    //   8	13	73	java/lang/Exception
    //   17	19	73	java/lang/Exception
    //   19	21	73	java/lang/Exception
    //   48	57	73	java/lang/Exception
    //   57	62	73	java/lang/Exception
    //   62	72	73	java/lang/Exception
  }
  
  private static String ˏ(int paramInt1, char paramChar, int paramInt2)
  {
    break label351;
    char[] arrayOfChar1 = new char[paramInt2];
    int i = 1;
    break label232;
    int k;
    int j;
    for (;;)
    {
      try
      {
        char[] arrayOfChar3 = ˏ;
        long l1 = arrayOfChar3[(k + paramInt1)];
        long l2 = paramInt1;
        try
        {
          arrayOfChar1[paramInt1] = ((char)(int)(l1 ^ l2 * ˋ ^ j));
          paramInt1 += 1;
        }
        catch (Exception localException1)
        {
          throw localException1;
        }
        switch (paramChar)
        {
        default: 
          continue;
          i = 1;
          switch (i)
          {
          }
          break;
        case '\000': 
          break;
          label126:
          paramChar = '\000';
          continue;
          arrayOfChar2 = new char[paramInt2];
          i = 0;
        }
      }
      catch (Exception localException2)
      {
        char[] arrayOfChar2;
        throw localException2;
      }
      arrayOfChar2[paramInt1] = ((char)(int)(ˏ[(k - paramInt1)] % (paramInt1 & ˋ) ^ j));
      paramInt1 += 75;
      break label308;
      break;
      label183:
      i = 53;
      continue;
      label189:
      paramChar = '\001';
    }
    for (;;)
    {
      if (paramInt1 >= paramInt2) {
        break label341;
      }
      paramChar = ˊ + 61;
      ʼ = paramChar % '';
      if (paramChar % '\002' == 0) {
        break;
      }
      break label335;
      label232:
      j = paramChar;
      k = paramInt1;
      paramInt1 = i;
    }
    for (;;)
    {
      label243:
      switch (paramChar)
      {
      }
      break;
      paramChar = 'Z';
    }
    label308:
    label335:
    label341:
    label351:
    for (;;)
    {
      i = ʼ + 17;
      ˊ = i % 128;
      if (i % 2 != 0) {
        break label183;
      }
      break;
      paramChar = ʼ + 39;
      ˊ = paramChar % '';
      if (paramChar % '\002' != 0) {
        break label189;
      }
      break label126;
      paramChar = '#';
      break label243;
      return new String(localException2);
    }
  }
  
  /* Error */
  private final void ॱ(String paramString)
  {
    // Byte code:
    //   0: goto +1045 -> 1045
    //   3: iload_2
    //   4: tableswitch	default:+24->28, 0:+1044->1048, 1:+1102->1106
    //   28: return
    //   29: getstatic 204	o/Gw:UNKNOWN	Lo/Gw;
    //   32: iconst_1
    //   33: anewarray 200	o/Gw
    //   36: dup
    //   37: iconst_0
    //   38: aload 4
    //   40: aastore
    //   41: invokevirtual 207	o/Gw:ˎ	([Lo/Gw;)Z
    //   44: ifeq +6 -> 50
    //   47: goto +1003 -> 1050
    //   50: return
    //   51: getstatic 27	o/DG:ˊ	I
    //   54: bipush 87
    //   56: iadd
    //   57: istore_2
    //   58: iload_2
    //   59: sipush 128
    //   62: irem
    //   63: putstatic 29	o/DG:ʼ	I
    //   66: iload_2
    //   67: iconst_2
    //   68: irem
    //   69: ifne +6 -> 75
    //   72: goto +41 -> 113
    //   75: goto +974 -> 1049
    //   78: iconst_0
    //   79: istore_2
    //   80: goto +1053 -> 1133
    //   83: getstatic 210	o/Gw:NOT_REGISTERED	Lo/Gw;
    //   86: astore 5
    //   88: aload 5
    //   90: iconst_1
    //   91: anewarray 200	o/Gw
    //   94: dup
    //   95: iconst_0
    //   96: aload 4
    //   98: aastore
    //   99: invokevirtual 207	o/Gw:ˎ	([Lo/Gw;)Z
    //   102: istore_3
    //   103: iload_3
    //   104: ifeq +6 -> 110
    //   107: goto -29 -> 78
    //   110: goto +1054 -> 1164
    //   113: goto +936 -> 1049
    //   116: invokestatic 215	com/google/firebase/iid/FirebaseInstanceId:ˊ	()Lcom/google/firebase/iid/FirebaseInstanceId;
    //   119: astore 4
    //   121: aload 4
    //   123: aload_0
    //   124: invokevirtual 221	android/content/Context:getResources	()Landroid/content/res/Resources;
    //   127: ldc -34
    //   129: invokevirtual 228	android/content/res/Resources:getString	(I)Ljava/lang/String;
    //   132: iconst_0
    //   133: iconst_5
    //   134: invokevirtual 232	java/lang/String:substring	(II)Ljava/lang/String;
    //   137: invokevirtual 236	java/lang/String:length	()I
    //   140: bipush 13
    //   142: iadd
    //   143: aload_0
    //   144: invokevirtual 221	android/content/Context:getResources	()Landroid/content/res/Resources;
    //   147: ldc -19
    //   149: invokevirtual 228	android/content/res/Resources:getString	(I)Ljava/lang/String;
    //   152: iconst_0
    //   153: bipush 9
    //   155: invokevirtual 232	java/lang/String:substring	(II)Ljava/lang/String;
    //   158: bipush 6
    //   160: invokevirtual 241	java/lang/String:codePointAt	(I)I
    //   163: sipush 251
    //   166: isub
    //   167: i2c
    //   168: aload_0
    //   169: invokevirtual 221	android/content/Context:getResources	()Landroid/content/res/Resources;
    //   172: ldc -14
    //   174: invokevirtual 228	android/content/res/Resources:getString	(I)Ljava/lang/String;
    //   177: bipush 9
    //   179: bipush 18
    //   181: invokevirtual 232	java/lang/String:substring	(II)Ljava/lang/String;
    //   184: invokevirtual 236	java/lang/String:length	()I
    //   187: bipush 23
    //   189: iadd
    //   190: invokestatic 175	o/DG:ˏ	(ICI)Ljava/lang/String;
    //   193: invokevirtual 181	java/lang/String:intern	()Ljava/lang/String;
    //   196: invokestatic 186	o/vq:ˋ	(Ljava/lang/Object;Ljava/lang/String;)V
    //   199: aload 4
    //   201: invokevirtual 244	com/google/firebase/iid/FirebaseInstanceId:ˏ	()Ljava/lang/String;
    //   204: astore 4
    //   206: aload_0
    //   207: invokevirtual 247	android/content/Context:getPackageName	()Ljava/lang/String;
    //   210: iconst_4
    //   211: invokevirtual 241	java/lang/String:codePointAt	(I)I
    //   214: bipush 66
    //   216: isub
    //   217: aload_0
    //   218: invokevirtual 221	android/content/Context:getResources	()Landroid/content/res/Resources;
    //   221: ldc -8
    //   223: invokevirtual 228	android/content/res/Resources:getString	(I)Ljava/lang/String;
    //   226: iconst_0
    //   227: iconst_4
    //   228: invokevirtual 232	java/lang/String:substring	(II)Ljava/lang/String;
    //   231: invokevirtual 236	java/lang/String:length	()I
    //   234: ldc -7
    //   236: iadd
    //   237: i2c
    //   238: aload_0
    //   239: invokevirtual 221	android/content/Context:getResources	()Landroid/content/res/Resources;
    //   242: ldc -6
    //   244: invokevirtual 228	android/content/res/Resources:getString	(I)Ljava/lang/String;
    //   247: iconst_0
    //   248: iconst_5
    //   249: invokevirtual 232	java/lang/String:substring	(II)Ljava/lang/String;
    //   252: iconst_1
    //   253: invokevirtual 241	java/lang/String:codePointAt	(I)I
    //   256: bipush 19
    //   258: isub
    //   259: invokestatic 175	o/DG:ˏ	(ICI)Ljava/lang/String;
    //   262: invokevirtual 181	java/lang/String:intern	()Ljava/lang/String;
    //   265: astore 5
    //   267: new 252	java/lang/StringBuilder
    //   270: dup
    //   271: invokespecial 253	java/lang/StringBuilder:<init>	()V
    //   274: aload_0
    //   275: invokevirtual 221	android/content/Context:getResources	()Landroid/content/res/Resources;
    //   278: ldc -2
    //   280: invokevirtual 228	android/content/res/Resources:getString	(I)Ljava/lang/String;
    //   283: iconst_0
    //   284: bipush 8
    //   286: invokevirtual 232	java/lang/String:substring	(II)Ljava/lang/String;
    //   289: iconst_4
    //   290: invokevirtual 241	java/lang/String:codePointAt	(I)I
    //   293: sipush 176
    //   296: isub
    //   297: aload_0
    //   298: invokevirtual 247	android/content/Context:getPackageName	()Ljava/lang/String;
    //   301: iconst_4
    //   302: invokevirtual 241	java/lang/String:codePointAt	(I)I
    //   305: ldc -1
    //   307: iadd
    //   308: i2c
    //   309: aload_0
    //   310: invokevirtual 221	android/content/Context:getResources	()Landroid/content/res/Resources;
    //   313: ldc_w 256
    //   316: invokevirtual 228	android/content/res/Resources:getString	(I)Ljava/lang/String;
    //   319: iconst_0
    //   320: iconst_4
    //   321: invokevirtual 232	java/lang/String:substring	(II)Ljava/lang/String;
    //   324: iconst_1
    //   325: invokevirtual 241	java/lang/String:codePointAt	(I)I
    //   328: bipush 13
    //   330: isub
    //   331: invokestatic 175	o/DG:ˏ	(ICI)Ljava/lang/String;
    //   334: invokevirtual 181	java/lang/String:intern	()Ljava/lang/String;
    //   337: invokevirtual 260	java/lang/StringBuilder:append	(Ljava/lang/String;)Ljava/lang/StringBuilder;
    //   340: aload 4
    //   342: invokevirtual 260	java/lang/StringBuilder:append	(Ljava/lang/String;)Ljava/lang/StringBuilder;
    //   345: invokevirtual 263	java/lang/StringBuilder:toString	()Ljava/lang/String;
    //   348: astore 6
    //   350: goto +20 -> 370
    //   353: astore_1
    //   354: aload_1
    //   355: invokevirtual 150	java/lang/Throwable:getCause	()Ljava/lang/Throwable;
    //   358: astore 4
    //   360: aload 4
    //   362: ifnull +6 -> 368
    //   365: aload 4
    //   367: athrow
    //   368: aload_1
    //   369: athrow
    //   370: aload_0
    //   371: invokevirtual 247	android/content/Context:getPackageName	()Ljava/lang/String;
    //   374: invokevirtual 236	java/lang/String:length	()I
    //   377: bipush 7
    //   379: isub
    //   380: aload_0
    //   381: invokevirtual 247	android/content/Context:getPackageName	()Ljava/lang/String;
    //   384: invokevirtual 236	java/lang/String:length	()I
    //   387: bipush 31
    //   389: iadd
    //   390: aload_0
    //   391: invokevirtual 267	android/content/Context:getApplicationInfo	()Landroid/content/pm/ApplicationInfo;
    //   394: getfield 272	android/content/pm/ApplicationInfo:targetSdkVersion	I
    //   397: ldc_w 273
    //   400: iadd
    //   401: i2c
    //   402: invokestatic 156	o/O:ˋ	(IIC)Ljava/lang/Object;
    //   405: checkcast 158	java/lang/Class
    //   408: ldc_w 274
    //   411: iconst_2
    //   412: anewarray 158	java/lang/Class
    //   415: dup
    //   416: iconst_0
    //   417: ldc -79
    //   419: aastore
    //   420: dup
    //   421: iconst_1
    //   422: ldc -79
    //   424: aastore
    //   425: invokevirtual 164	java/lang/Class:getMethod	(Ljava/lang/String;[Ljava/lang/Class;)Ljava/lang/reflect/Method;
    //   428: aconst_null
    //   429: iconst_2
    //   430: anewarray 276	java/lang/Object
    //   433: dup
    //   434: iconst_0
    //   435: aload 5
    //   437: aastore
    //   438: dup
    //   439: iconst_1
    //   440: aload 6
    //   442: aastore
    //   443: invokevirtual 170	java/lang/reflect/Method:invoke	(Ljava/lang/Object;[Ljava/lang/Object;)Ljava/lang/Object;
    //   446: pop
    //   447: aload_0
    //   448: invokevirtual 221	android/content/Context:getResources	()Landroid/content/res/Resources;
    //   451: ldc_w 277
    //   454: invokevirtual 228	android/content/res/Resources:getString	(I)Ljava/lang/String;
    //   457: iconst_0
    //   458: iconst_4
    //   459: invokevirtual 232	java/lang/String:substring	(II)Ljava/lang/String;
    //   462: invokevirtual 236	java/lang/String:length	()I
    //   465: bipush 46
    //   467: iadd
    //   468: aload_0
    //   469: invokevirtual 247	android/content/Context:getPackageName	()Ljava/lang/String;
    //   472: invokevirtual 236	java/lang/String:length	()I
    //   475: ldc_w 278
    //   478: iadd
    //   479: i2c
    //   480: aload_0
    //   481: invokevirtual 247	android/content/Context:getPackageName	()Ljava/lang/String;
    //   484: invokevirtual 236	java/lang/String:length	()I
    //   487: iconst_4
    //   488: isub
    //   489: invokestatic 175	o/DG:ˏ	(ICI)Ljava/lang/String;
    //   492: invokevirtual 181	java/lang/String:intern	()Ljava/lang/String;
    //   495: astore 5
    //   497: new 252	java/lang/StringBuilder
    //   500: dup
    //   501: invokespecial 253	java/lang/StringBuilder:<init>	()V
    //   504: aload_0
    //   505: invokevirtual 267	android/content/Context:getApplicationInfo	()Landroid/content/pm/ApplicationInfo;
    //   508: getfield 272	android/content/pm/ApplicationInfo:targetSdkVersion	I
    //   511: bipush 45
    //   513: iadd
    //   514: aload_0
    //   515: invokevirtual 267	android/content/Context:getApplicationInfo	()Landroid/content/pm/ApplicationInfo;
    //   518: getfield 272	android/content/pm/ApplicationInfo:targetSdkVersion	I
    //   521: bipush 25
    //   523: isub
    //   524: i2c
    //   525: aload_0
    //   526: invokevirtual 221	android/content/Context:getResources	()Landroid/content/res/Resources;
    //   529: ldc_w 279
    //   532: invokevirtual 228	android/content/res/Resources:getString	(I)Ljava/lang/String;
    //   535: iconst_0
    //   536: iconst_4
    //   537: invokevirtual 232	java/lang/String:substring	(II)Ljava/lang/String;
    //   540: iconst_3
    //   541: invokevirtual 241	java/lang/String:codePointAt	(I)I
    //   544: iconst_4
    //   545: iadd
    //   546: invokestatic 175	o/DG:ˏ	(ICI)Ljava/lang/String;
    //   549: invokevirtual 181	java/lang/String:intern	()Ljava/lang/String;
    //   552: invokevirtual 260	java/lang/StringBuilder:append	(Ljava/lang/String;)Ljava/lang/StringBuilder;
    //   555: aload_1
    //   556: invokevirtual 260	java/lang/StringBuilder:append	(Ljava/lang/String;)Ljava/lang/StringBuilder;
    //   559: invokevirtual 263	java/lang/StringBuilder:toString	()Ljava/lang/String;
    //   562: astore 6
    //   564: goto +20 -> 584
    //   567: astore_1
    //   568: aload_1
    //   569: invokevirtual 150	java/lang/Throwable:getCause	()Ljava/lang/Throwable;
    //   572: astore 4
    //   574: aload 4
    //   576: ifnull +6 -> 582
    //   579: aload 4
    //   581: athrow
    //   582: aload_1
    //   583: athrow
    //   584: aload_0
    //   585: invokevirtual 221	android/content/Context:getResources	()Landroid/content/res/Resources;
    //   588: ldc_w 280
    //   591: invokevirtual 228	android/content/res/Resources:getString	(I)Ljava/lang/String;
    //   594: iconst_0
    //   595: iconst_5
    //   596: invokevirtual 232	java/lang/String:substring	(II)Ljava/lang/String;
    //   599: iconst_1
    //   600: invokevirtual 241	java/lang/String:codePointAt	(I)I
    //   603: bipush 22
    //   605: isub
    //   606: aload_0
    //   607: invokevirtual 247	android/content/Context:getPackageName	()Ljava/lang/String;
    //   610: invokevirtual 236	java/lang/String:length	()I
    //   613: bipush 31
    //   615: iadd
    //   616: aload_0
    //   617: invokevirtual 221	android/content/Context:getResources	()Landroid/content/res/Resources;
    //   620: ldc_w 281
    //   623: invokevirtual 228	android/content/res/Resources:getString	(I)Ljava/lang/String;
    //   626: iconst_0
    //   627: iconst_4
    //   628: invokevirtual 232	java/lang/String:substring	(II)Ljava/lang/String;
    //   631: invokevirtual 236	java/lang/String:length	()I
    //   634: ldc_w 282
    //   637: iadd
    //   638: i2c
    //   639: invokestatic 156	o/O:ˋ	(IIC)Ljava/lang/Object;
    //   642: checkcast 158	java/lang/Class
    //   645: ldc_w 274
    //   648: iconst_2
    //   649: anewarray 158	java/lang/Class
    //   652: dup
    //   653: iconst_0
    //   654: ldc -79
    //   656: aastore
    //   657: dup
    //   658: iconst_1
    //   659: ldc -79
    //   661: aastore
    //   662: invokevirtual 164	java/lang/Class:getMethod	(Ljava/lang/String;[Ljava/lang/Class;)Ljava/lang/reflect/Method;
    //   665: aconst_null
    //   666: iconst_2
    //   667: anewarray 276	java/lang/Object
    //   670: dup
    //   671: iconst_0
    //   672: aload 5
    //   674: aastore
    //   675: dup
    //   676: iconst_1
    //   677: aload 6
    //   679: aastore
    //   680: invokevirtual 170	java/lang/reflect/Method:invoke	(Ljava/lang/Object;[Ljava/lang/Object;)Ljava/lang/Object;
    //   683: pop
    //   684: aload_0
    //   685: invokevirtual 267	android/content/Context:getApplicationInfo	()Landroid/content/pm/ApplicationInfo;
    //   688: getfield 272	android/content/pm/ApplicationInfo:targetSdkVersion	I
    //   691: bipush 61
    //   693: iadd
    //   694: aload_0
    //   695: invokevirtual 247	android/content/Context:getPackageName	()Ljava/lang/String;
    //   698: iconst_0
    //   699: invokevirtual 241	java/lang/String:codePointAt	(I)I
    //   702: bipush 114
    //   704: isub
    //   705: i2c
    //   706: aload_0
    //   707: invokevirtual 221	android/content/Context:getResources	()Landroid/content/res/Resources;
    //   710: ldc_w 283
    //   713: invokevirtual 228	android/content/res/Resources:getString	(I)Ljava/lang/String;
    //   716: iconst_0
    //   717: iconst_1
    //   718: invokevirtual 232	java/lang/String:substring	(II)Ljava/lang/String;
    //   721: iconst_0
    //   722: invokevirtual 241	java/lang/String:codePointAt	(I)I
    //   725: bipush 36
    //   727: isub
    //   728: invokestatic 175	o/DG:ˏ	(ICI)Ljava/lang/String;
    //   731: invokevirtual 181	java/lang/String:intern	()Ljava/lang/String;
    //   734: aload 4
    //   736: invokestatic 288	com/crashlytics/android/Crashlytics:ॱ	(Ljava/lang/String;Ljava/lang/String;)V
    //   739: aload_0
    //   740: invokevirtual 221	android/content/Context:getResources	()Landroid/content/res/Resources;
    //   743: ldc_w 289
    //   746: invokevirtual 228	android/content/res/Resources:getString	(I)Ljava/lang/String;
    //   749: iconst_0
    //   750: iconst_4
    //   751: invokevirtual 232	java/lang/String:substring	(II)Ljava/lang/String;
    //   754: iconst_1
    //   755: invokevirtual 241	java/lang/String:codePointAt	(I)I
    //   758: bipush 22
    //   760: isub
    //   761: aload_0
    //   762: invokevirtual 247	android/content/Context:getPackageName	()Ljava/lang/String;
    //   765: invokevirtual 236	java/lang/String:length	()I
    //   768: sipush 402
    //   771: iadd
    //   772: aload_0
    //   773: invokevirtual 221	android/content/Context:getResources	()Landroid/content/res/Resources;
    //   776: ldc_w 290
    //   779: invokevirtual 228	android/content/res/Resources:getString	(I)Ljava/lang/String;
    //   782: iconst_0
    //   783: bipush 10
    //   785: invokevirtual 232	java/lang/String:substring	(II)Ljava/lang/String;
    //   788: bipush 8
    //   790: invokevirtual 241	java/lang/String:codePointAt	(I)I
    //   793: sipush 30020
    //   796: iadd
    //   797: i2c
    //   798: invokestatic 156	o/O:ˋ	(IIC)Ljava/lang/Object;
    //   801: checkcast 158	java/lang/Class
    //   804: ldc_w 291
    //   807: invokevirtual 295	java/lang/Class:getField	(Ljava/lang/String;)Ljava/lang/reflect/Field;
    //   810: aconst_null
    //   811: invokevirtual 301	java/lang/reflect/Field:get	(Ljava/lang/Object;)Ljava/lang/Object;
    //   814: astore 4
    //   816: goto +20 -> 836
    //   819: astore_1
    //   820: aload_1
    //   821: invokevirtual 150	java/lang/Throwable:getCause	()Ljava/lang/Throwable;
    //   824: astore 4
    //   826: aload 4
    //   828: ifnull +6 -> 834
    //   831: aload 4
    //   833: athrow
    //   834: aload_1
    //   835: athrow
    //   836: aload_0
    //   837: invokevirtual 221	android/content/Context:getResources	()Landroid/content/res/Resources;
    //   840: ldc_w 302
    //   843: invokevirtual 228	android/content/res/Resources:getString	(I)Ljava/lang/String;
    //   846: iconst_0
    //   847: iconst_4
    //   848: invokevirtual 232	java/lang/String:substring	(II)Ljava/lang/String;
    //   851: invokevirtual 236	java/lang/String:length	()I
    //   854: iconst_2
    //   855: iadd
    //   856: aload_0
    //   857: invokevirtual 247	android/content/Context:getPackageName	()Ljava/lang/String;
    //   860: bipush 8
    //   862: invokevirtual 241	java/lang/String:codePointAt	(I)I
    //   865: sipush 305
    //   868: iadd
    //   869: aload_0
    //   870: invokevirtual 267	android/content/Context:getApplicationInfo	()Landroid/content/pm/ApplicationInfo;
    //   873: getfield 272	android/content/pm/ApplicationInfo:targetSdkVersion	I
    //   876: bipush 25
    //   878: isub
    //   879: i2c
    //   880: invokestatic 156	o/O:ˋ	(IIC)Ljava/lang/Object;
    //   883: checkcast 158	java/lang/Class
    //   886: ldc_w 303
    //   889: aconst_null
    //   890: invokevirtual 164	java/lang/Class:getMethod	(Ljava/lang/String;[Ljava/lang/Class;)Ljava/lang/reflect/Method;
    //   893: aload 4
    //   895: aconst_null
    //   896: invokevirtual 170	java/lang/reflect/Method:invoke	(Ljava/lang/Object;[Ljava/lang/Object;)Ljava/lang/Object;
    //   899: astore 4
    //   901: goto +20 -> 921
    //   904: astore_1
    //   905: aload_1
    //   906: invokevirtual 150	java/lang/Throwable:getCause	()Ljava/lang/Throwable;
    //   909: astore 4
    //   911: aload 4
    //   913: ifnull +6 -> 919
    //   916: aload 4
    //   918: athrow
    //   919: aload_1
    //   920: athrow
    //   921: aload_0
    //   922: invokevirtual 221	android/content/Context:getResources	()Landroid/content/res/Resources;
    //   925: ldc_w 304
    //   928: invokevirtual 228	android/content/res/Resources:getString	(I)Ljava/lang/String;
    //   931: iconst_0
    //   932: iconst_4
    //   933: invokevirtual 232	java/lang/String:substring	(II)Ljava/lang/String;
    //   936: invokevirtual 236	java/lang/String:length	()I
    //   939: iconst_0
    //   940: iadd
    //   941: aload_0
    //   942: invokevirtual 267	android/content/Context:getApplicationInfo	()Landroid/content/pm/ApplicationInfo;
    //   945: getfield 272	android/content/pm/ApplicationInfo:targetSdkVersion	I
    //   948: sipush 388
    //   951: iadd
    //   952: aload_0
    //   953: invokevirtual 221	android/content/Context:getResources	()Landroid/content/res/Resources;
    //   956: ldc_w 305
    //   959: invokevirtual 228	android/content/res/Resources:getString	(I)Ljava/lang/String;
    //   962: iconst_0
    //   963: iconst_4
    //   964: invokevirtual 232	java/lang/String:substring	(II)Ljava/lang/String;
    //   967: iconst_1
    //   968: invokevirtual 241	java/lang/String:codePointAt	(I)I
    //   971: sipush 30227
    //   974: iadd
    //   975: i2c
    //   976: invokestatic 156	o/O:ˋ	(IIC)Ljava/lang/Object;
    //   979: checkcast 158	java/lang/Class
    //   982: ldc_w 307
    //   985: aconst_null
    //   986: invokevirtual 164	java/lang/Class:getMethod	(Ljava/lang/String;[Ljava/lang/Class;)Ljava/lang/reflect/Method;
    //   989: aload 4
    //   991: aconst_null
    //   992: invokevirtual 170	java/lang/reflect/Method:invoke	(Ljava/lang/Object;[Ljava/lang/Object;)Ljava/lang/Object;
    //   995: astore 4
    //   997: invokestatic 313	o/Dt:ॱॱ	()Lo/Dt;
    //   1000: invokevirtual 317	o/Dt:ͺ	()Z
    //   1003: ifeq +6 -> 1009
    //   1006: goto +153 -> 1159
    //   1009: goto +160 -> 1169
    //   1012: getstatic 210	o/Gw:NOT_REGISTERED	Lo/Gw;
    //   1015: astore 5
    //   1017: iconst_1
    //   1018: anewarray 200	o/Gw
    //   1021: astore 6
    //   1023: aload 6
    //   1025: iconst_1
    //   1026: aload 4
    //   1028: aastore
    //   1029: aload 5
    //   1031: aload 6
    //   1033: invokevirtual 207	o/Gw:ˎ	([Lo/Gw;)Z
    //   1036: ifeq +6 -> 1042
    //   1039: goto -1010 -> 29
    //   1042: goto +8 -> 1050
    //   1045: goto -929 -> 116
    //   1048: return
    //   1049: return
    //   1050: aload_0
    //   1051: getfield 188	o/DG:ॱ	Lo/Id;
    //   1054: new 319	o/EI
    //   1057: dup
    //   1058: aload_1
    //   1059: invokespecial 321	o/EI:<init>	(Ljava/lang/String;)V
    //   1062: invokeinterface 324 2 0
    //   1067: invokestatic 329	o/ur:ॱ	()Lo/sy;
    //   1070: invokevirtual 334	o/sp:ˋ	(Lo/sy;)Lo/sp;
    //   1073: invokestatic 338	o/sB:ˋ	()Lo/sy;
    //   1076: invokevirtual 340	o/sp:ॱ	(Lo/sy;)Lo/sp;
    //   1079: new 12	o/DG$ˊ
    //   1082: dup
    //   1083: aload_1
    //   1084: invokespecial 341	o/DG$ˊ:<init>	(Ljava/lang/String;)V
    //   1087: checkcast 343	o/sR
    //   1090: getstatic 346	o/DG$iF:ˋ	Lo/DG$iF;
    //   1093: checkcast 348	o/sW
    //   1096: invokevirtual 351	o/sp:ˋ	(Lo/sR;Lo/sW;)Lo/sH;
    //   1099: pop
    //   1100: goto -1049 -> 51
    //   1103: astore_1
    //   1104: aload_1
    //   1105: athrow
    //   1106: getstatic 27	o/DG:ˊ	I
    //   1109: bipush 57
    //   1111: iadd
    //   1112: istore_2
    //   1113: iload_2
    //   1114: sipush 128
    //   1117: irem
    //   1118: putstatic 29	o/DG:ʼ	I
    //   1121: iload_2
    //   1122: iconst_2
    //   1123: irem
    //   1124: ifne +6 -> 1130
    //   1127: goto -115 -> 1012
    //   1130: goto -1047 -> 83
    //   1133: iload_2
    //   1134: tableswitch	default:+22->1156, 0:+-1105->29, 1:+-84->1050
    //   1156: goto -106 -> 1050
    //   1159: iconst_1
    //   1160: istore_2
    //   1161: goto -1158 -> 3
    //   1164: iconst_1
    //   1165: istore_2
    //   1166: goto -33 -> 1133
    //   1169: iconst_0
    //   1170: istore_2
    //   1171: goto -1168 -> 3
    // Local variable table:
    //   start	length	slot	name	signature
    //   0	1174	0	this	DG
    //   0	1174	1	paramString	String
    //   3	1168	2	i	int
    //   102	2	3	bool	boolean
    //   38	989	4	localObject1	Object
    //   86	944	5	localObject2	Object
    //   348	684	6	localObject3	Object
    // Exception table:
    //   from	to	target	type
    //   370	447	353	finally
    //   584	684	567	finally
    //   836	901	819	finally
    //   921	997	904	finally
    //   83	88	1103	java/lang/Exception
    //   88	103	1103	java/lang/Exception
    //   1106	1113	1103	java/lang/Exception
    //   1113	1121	1103	java/lang/Exception
  }
  
  public Resources getResources()
  {
    break label13;
    int i = 1;
    break label64;
    label8:
    i = 0;
    break label64;
    label13:
    break label37;
    return oH.ˊ(super.getResources());
    for (;;)
    {
      Resources localResources = oH.ˊ(super.getResources());
      i = null.length;
      return localResources;
      label37:
      i = ˊ + 25;
      ʼ = i % 128;
      if (i % 2 == 0) {
        break;
      }
      break label8;
      label64:
      switch (i)
      {
      }
    }
  }
  
  public void ˏ()
  {
    for (;;)
    {
      super.ˏ();
      Ea.ˋ localˋ = Ea.ˋ;
      Context localContext = getApplicationContext();
      vq.ˋ(localContext, ˏ(getPackageName().length() - 11, (char)(getPackageName().length() + 37275), getResources().getString(2131755105).substring(0, 5).codePointAt(1) - 8).intern());
      localˋ.ˋ(localContext).ˎ(ur.ˊ()).ˋ(sB.ˋ()).ˏ((sX)ˋ.ˋ).ˏ((sW)new If(this), (sW)if.ˊ);
      break;
    }
    do
    {
      i = 4;
      break;
      i = ˊ + 59;
      ʼ = i % 128;
    } while (i % 2 == 0);
    int i = 90;
    switch (i)
    {
    default: 
      break;
    case 90: 
      return;
    }
    i = 24 / 0;
  }
  
  static final class If<T>
    implements sW<String>
  {
    private static int[] ˋ = { 1347596190, 1847372700, -917387962, 1700603050, 1571866471, 275268801, 1667646252, -1694436537, 1097917167, -1980465183, 2078594334, 879182262, 751387480, -1670271887, -469449619, 1061129511, -1872925327, 461859463 };
    private static int ˎ = 0;
    private static int ˏ = 1;
    
    If(DG paramDG) {}
    
    private static String ˏ(int[] paramArrayOfInt, int paramInt)
    {
      break label241;
      int i;
      for (;;)
      {
        switch (i)
        {
        default: 
          break label297;
          i = 85;
        }
      }
      char[] arrayOfChar1;
      char[] arrayOfChar2;
      int[] arrayOfInt1;
      label128:
      int[] arrayOfInt2;
      for (;;)
      {
        try
        {
          j = ˏ;
          j += 27;
          ˎ = j % 128;
          if (j % 2 != 0) {
            break label326;
          }
          continue;
          arrayOfChar1 = new char[4];
          arrayOfChar2 = new char[paramArrayOfInt.length << 1];
          arrayOfInt1 = (int[])ˋ.clone();
          i = 0;
          break label329;
          i = ˏ;
          i += 93;
          ˎ = i % 128;
          if (i % 2 != 0) {
            break label345;
          }
          break;
          arrayOfChar1[0] = ((char)(arrayOfInt2[i] >> 16));
          arrayOfChar1[1] = ((char)arrayOfInt2[i]);
          arrayOfChar1[2] = ((char)(arrayOfInt2[(i + 1)] >> 16));
          arrayOfChar1[3] = ((char)arrayOfInt2[(i + 1)]);
          oN.ˏ(arrayOfChar1, arrayOfInt1, false);
          arrayOfChar2[(i << 1)] = arrayOfChar1[0];
          arrayOfChar2[((i << 1) + 1)] = arrayOfChar1[1];
          arrayOfChar2[((i << 1) + 2)] = arrayOfChar1[2];
          arrayOfChar2[((i << 1) + 3)] = arrayOfChar1[3];
          i += 2;
        }
        catch (Exception paramArrayOfInt)
        {
          label236:
          label241:
          throw paramArrayOfInt;
        }
        j = 0;
        break label351;
      }
      label244:
      int j = 1;
      for (;;)
      {
        try
        {
          paramInt = ˎ;
          paramInt += 69;
          ˏ = paramInt % 128;
          if (paramInt % 2 == 0) {
            return paramArrayOfInt;
          }
          return paramArrayOfInt;
        }
        catch (Exception paramArrayOfInt)
        {
          throw paramArrayOfInt;
        }
        paramArrayOfInt = new String(arrayOfChar2, 0, paramInt);
        continue;
        label297:
        arrayOfChar1 = new char[5];
        arrayOfChar2 = new char[paramArrayOfInt.length << 0];
        arrayOfInt1 = (int[])ˋ.clone();
        i = 1;
        break label329;
        label326:
        break label128;
        label329:
        arrayOfInt2 = paramArrayOfInt;
        if (i < arrayOfInt2.length) {
          break label236;
        }
        break label244;
        label345:
        i = 77;
        break;
        label351:
        switch (j)
        {
        }
      }
    }
    
    public final void ˏ(String paramString)
    {
      break label155;
      DG localDG = this.ˊ;
      vq.ˋ(paramString, ˏ(new int[] { 1138313837, 1893083183, 556478627, 1715934072 }, 3).intern());
      DG.ˊ(localDG, paramString);
      return;
      label155:
      label158:
      for (int i = 65;; i = 98) {
        switch (i)
        {
        case 65: 
        default: 
          break;
        case 98: 
          for (;;)
          {
            i = ˏ + 35;
            ˎ = i % 128;
            if (i % 2 != 0) {
              break;
            }
            break label158;
            localDG = this.ˊ;
            vq.ˋ(paramString, ˏ(new int[] { 1138313837, 1893083183, 556478627, 1715934072 }, 5).intern());
            DG.ˊ(localDG, paramString);
            return;
          }
        }
      }
    }
  }
  
  static final class iF<T>
    implements sW<Throwable>
  {
    private static char[] ˊ;
    public static final iF ˋ;
    private static boolean ˎ;
    private static int ˏ;
    private static boolean ॱ;
    private static int ॱॱ;
    private static int ᐝ;
    
    /* Error */
    static
    {
      // Byte code:
      //   0: goto +9 -> 9
      //   3: astore_1
      //   4: aload_1
      //   5: athrow
      //   6: astore_1
      //   7: aload_1
      //   8: athrow
      //   9: iconst_0
      //   10: putstatic 28	o/DG$iF:ॱॱ	I
      //   13: iconst_1
      //   14: putstatic 30	o/DG$iF:ᐝ	I
      //   17: invokestatic 32	o/DG$iF:ˊ	()V
      //   20: new 2	o/DG$iF
      //   23: dup
      //   24: invokespecial 35	o/DG$iF:<init>	()V
      //   27: astore_1
      //   28: aload_1
      //   29: putstatic 37	o/DG$iF:ˋ	Lo/DG$iF;
      //   32: getstatic 28	o/DG$iF:ॱॱ	I
      //   35: bipush 21
      //   37: iadd
      //   38: istore_0
      //   39: iload_0
      //   40: sipush 128
      //   43: irem
      //   44: putstatic 30	o/DG$iF:ᐝ	I
      //   47: iload_0
      //   48: iconst_2
      //   49: irem
      //   50: ifne +4 -> 54
      //   53: return
      //   54: return
      // Local variable table:
      //   start	length	slot	name	signature
      //   38	12	0	i	int
      //   3	2	1	localException1	Exception
      //   6	2	1	localException2	Exception
      //   27	2	1	localIF	iF
      // Exception table:
      //   from	to	target	type
      //   17	20	3	java/lang/Exception
      //   9	13	6	java/lang/Exception
      //   13	17	6	java/lang/Exception
      //   17	20	6	java/lang/Exception
      //   20	28	6	java/lang/Exception
      //   28	32	6	java/lang/Exception
    }
    
    iF() {}
    
    static void ˊ()
    {
      ॱ = true;
      ˎ = true;
      ˊ = new char[] { 207, 230, 245, 248, 240, 243, 236 };
      ˏ = 129;
    }
    
    /* Error */
    private static String ˎ(byte[] paramArrayOfByte, int[] paramArrayOfInt, char[] paramArrayOfChar, int paramInt)
    {
      // Byte code:
      //   0: goto +16 -> 16
      //   3: iload 4
      //   5: iload 7
      //   7: if_icmpge +6 -> 13
      //   10: goto +115 -> 125
      //   13: goto +106 -> 119
      //   16: getstatic 30	o/DG$iF:ᐝ	I
      //   19: bipush 31
      //   21: iadd
      //   22: istore 4
      //   24: iload 4
      //   26: sipush 128
      //   29: irem
      //   30: putstatic 28	o/DG$iF:ॱॱ	I
      //   33: iload 4
      //   35: iconst_2
      //   36: irem
      //   37: ifeq +6 -> 43
      //   40: goto +109 -> 149
      //   43: goto +197 -> 240
      //   46: aload_1
      //   47: iload 4
      //   49: aload_0
      //   50: aload_2
      //   51: iload 6
      //   53: iconst_1
      //   54: isub
      //   55: iload 4
      //   57: isub
      //   58: caload
      //   59: iload_3
      //   60: isub
      //   61: caload
      //   62: iload 5
      //   64: isub
      //   65: i2c
      //   66: castore
      //   67: iload 4
      //   69: iconst_1
      //   70: iadd
      //   71: istore 4
      //   73: goto +460 -> 533
      //   76: astore_0
      //   77: aload_0
      //   78: athrow
      //   79: aload_1
      //   80: arraylength
      //   81: istore 7
      //   83: iload 7
      //   85: newarray char
      //   87: astore_2
      //   88: iconst_0
      //   89: istore 4
      //   91: goto -88 -> 3
      //   94: iload 5
      //   96: iload 7
      //   98: if_icmpge +6 -> 104
      //   101: goto +425 -> 526
      //   104: goto +251 -> 355
      //   107: new 57	java/lang/String
      //   110: dup
      //   111: aload_1
      //   112: invokespecial 60	java/lang/String:<init>	([C)V
      //   115: astore_0
      //   116: goto +160 -> 276
      //   119: iconst_0
      //   120: istore 6
      //   122: goto +80 -> 202
      //   125: iconst_1
      //   126: istore 6
      //   128: goto +74 -> 202
      //   131: aload_0
      //   132: arraylength
      //   133: istore 7
      //   135: iload 7
      //   137: newarray char
      //   139: astore_1
      //   140: iconst_0
      //   141: istore 5
      //   143: goto +283 -> 426
      //   146: goto -52 -> 94
      //   149: iconst_0
      //   150: istore 4
      //   152: goto +394 -> 546
      //   155: aload_1
      //   156: iload 5
      //   158: aload 9
      //   160: aload_0
      //   161: iload 7
      //   163: iconst_1
      //   164: isub
      //   165: iload 5
      //   167: isub
      //   168: baload
      //   169: iload_3
      //   170: iadd
      //   171: caload
      //   172: iload 4
      //   174: isub
      //   175: i2c
      //   176: castore
      //   177: iload 5
      //   179: iconst_1
      //   180: iadd
      //   181: istore 5
      //   183: goto -89 -> 94
      //   186: getstatic 43	o/DG$iF:ˎ	Z
      //   189: istore 8
      //   191: iload 8
      //   193: ifeq +6 -> 199
      //   196: goto +144 -> 340
      //   199: goto -120 -> 79
      //   202: iload 6
      //   204: tableswitch	default:+24->228, 0:+127->331, 1:+42->246
      //   228: goto +103 -> 331
      //   231: new 57	java/lang/String
      //   234: dup
      //   235: aload_1
      //   236: invokespecial 60	java/lang/String:<init>	([C)V
      //   239: areturn
      //   240: iconst_1
      //   241: istore 4
      //   243: goto +303 -> 546
      //   246: getstatic 28	o/DG$iF:ॱॱ	I
      //   249: bipush 43
      //   251: iadd
      //   252: istore 6
      //   254: iload 6
      //   256: sipush 128
      //   259: irem
      //   260: putstatic 30	o/DG$iF:ᐝ	I
      //   263: iload 6
      //   265: iconst_2
      //   266: irem
      //   267: ifne +6 -> 273
      //   270: goto +92 -> 362
      //   273: goto +183 -> 456
      //   276: getstatic 30	o/DG$iF:ᐝ	I
      //   279: bipush 105
      //   281: iadd
      //   282: istore_3
      //   283: iload_3
      //   284: sipush 128
      //   287: irem
      //   288: putstatic 28	o/DG$iF:ॱॱ	I
      //   291: iload_3
      //   292: iconst_2
      //   293: irem
      //   294: ifeq +6 -> 300
      //   297: goto +278 -> 575
      //   300: aload_0
      //   301: areturn
      //   302: getstatic 52	o/DG$iF:ˊ	[C
      //   305: astore 9
      //   307: getstatic 54	o/DG$iF:ˏ	I
      //   310: istore 4
      //   312: getstatic 41	o/DG$iF:ॱ	Z
      //   315: ifeq +6 -> 321
      //   318: goto -187 -> 131
      //   321: aload 9
      //   323: astore_0
      //   324: iload 4
      //   326: istore 5
      //   328: goto -142 -> 186
      //   331: new 57	java/lang/String
      //   334: dup
      //   335: aload_2
      //   336: invokespecial 60	java/lang/String:<init>	([C)V
      //   339: areturn
      //   340: aload_2
      //   341: arraylength
      //   342: istore 6
      //   344: iload 6
      //   346: newarray char
      //   348: astore_1
      //   349: iconst_0
      //   350: istore 4
      //   352: goto +181 -> 533
      //   355: bipush 66
      //   357: istore 6
      //   359: goto +34 -> 393
      //   362: aload_2
      //   363: iload 4
      //   365: aload_0
      //   366: aload_1
      //   367: iload 7
      //   369: iconst_0
      //   370: iadd
      //   371: iload 4
      //   373: idiv
      //   374: iaload
      //   375: iload_3
      //   376: imul
      //   377: caload
      //   378: iload 5
      //   380: imul
      //   381: i2c
      //   382: castore
      //   383: iload 4
      //   385: bipush 82
      //   387: iadd
      //   388: istore 4
      //   390: goto -387 -> 3
      //   393: iload 6
      //   395: lookupswitch	default:+25->420, 31:+-240->155, 66:+-288->107
      //   420: goto -265 -> 155
      //   423: astore_0
      //   424: aload_0
      //   425: athrow
      //   426: getstatic 30	o/DG$iF:ᐝ	I
      //   429: bipush 27
      //   431: iadd
      //   432: istore 6
      //   434: iload 6
      //   436: sipush 128
      //   439: irem
      //   440: putstatic 28	o/DG$iF:ॱॱ	I
      //   443: iload 6
      //   445: iconst_2
      //   446: irem
      //   447: ifeq +6 -> 453
      //   450: goto -304 -> 146
      //   453: goto +70 -> 523
      //   456: aload_2
      //   457: iload 4
      //   459: aload_0
      //   460: aload_1
      //   461: iload 7
      //   463: iconst_1
      //   464: isub
      //   465: iload 4
      //   467: isub
      //   468: iaload
      //   469: iload_3
      //   470: isub
      //   471: caload
      //   472: iload 5
      //   474: isub
      //   475: i2c
      //   476: castore
      //   477: iload 4
      //   479: iconst_1
      //   480: iadd
      //   481: istore 4
      //   483: goto -480 -> 3
      //   486: getstatic 52	o/DG$iF:ˊ	[C
      //   489: astore 9
      //   491: getstatic 54	o/DG$iF:ˏ	I
      //   494: istore 4
      //   496: getstatic 41	o/DG$iF:ॱ	Z
      //   499: istore 8
      //   501: aconst_null
      //   502: arraylength
      //   503: istore 5
      //   505: iload 8
      //   507: ifeq +6 -> 513
      //   510: goto -379 -> 131
      //   513: aload 9
      //   515: astore_0
      //   516: iload 4
      //   518: istore 5
      //   520: goto -334 -> 186
      //   523: goto -429 -> 94
      //   526: bipush 31
      //   528: istore 6
      //   530: goto -137 -> 393
      //   533: iload 4
      //   535: iload 6
      //   537: if_icmpge +6 -> 543
      //   540: goto -494 -> 46
      //   543: goto -312 -> 231
      //   546: iload 4
      //   548: tableswitch	default:+24->572, 0:+-62->486, 1:+-246->302
      //   572: goto -86 -> 486
      //   575: new 62	java/lang/NullPointerException
      //   578: dup
      //   579: invokespecial 63	java/lang/NullPointerException:<init>	()V
      //   582: athrow
      // Local variable table:
      //   start	length	slot	name	signature
      //   0	583	0	paramArrayOfByte	byte[]
      //   0	583	1	paramArrayOfInt	int[]
      //   0	583	2	paramArrayOfChar	char[]
      //   0	583	3	paramInt	int
      //   3	544	4	i	int
      //   62	457	5	j	int
      //   51	487	6	k	int
      //   5	460	7	m	int
      //   189	317	8	bool	boolean
      //   158	356	9	arrayOfChar	char[]
      // Exception table:
      //   from	to	target	type
      //   186	191	76	java/lang/Exception
      //   276	283	76	java/lang/Exception
      //   283	291	76	java/lang/Exception
      //   16	24	423	java/lang/Exception
      //   24	33	423	java/lang/Exception
    }
    
    /* Error */
    public final void ॱ(Throwable paramThrowable)
    {
      // Byte code:
      //   0: goto +265 -> 265
      //   3: bipush 68
      //   5: istore_2
      //   6: goto +288 -> 294
      //   9: astore_1
      //   10: aload_1
      //   11: athrow
      //   12: bipush 7
      //   14: newarray byte
      //   16: dup
      //   17: iconst_0
      //   18: ldc 70
      //   20: bastore
      //   21: dup
      //   22: iconst_1
      //   23: ldc 71
      //   25: bastore
      //   26: dup
      //   27: iconst_2
      //   28: ldc 72
      //   30: bastore
      //   31: dup
      //   32: iconst_3
      //   33: ldc 73
      //   35: bastore
      //   36: dup
      //   37: iconst_4
      //   38: ldc 74
      //   40: bastore
      //   41: dup
      //   42: iconst_5
      //   43: ldc 75
      //   45: bastore
      //   46: dup
      //   47: bipush 6
      //   49: ldc 76
      //   51: bastore
      //   52: aconst_null
      //   53: aconst_null
      //   54: bipush 25
      //   56: invokestatic 78	o/DG$iF:ˎ	([B[I[CI)Ljava/lang/String;
      //   59: invokevirtual 82	java/lang/String:intern	()Ljava/lang/String;
      //   62: astore_3
      //   63: aload_1
      //   64: invokevirtual 85	java/lang/Throwable:getMessage	()Ljava/lang/String;
      //   67: astore_1
      //   68: goto +17 -> 85
      //   71: astore_1
      //   72: aload_1
      //   73: invokevirtual 89	java/lang/Throwable:getCause	()Ljava/lang/Throwable;
      //   76: astore_3
      //   77: aload_3
      //   78: ifnull +5 -> 83
      //   81: aload_3
      //   82: athrow
      //   83: aload_1
      //   84: athrow
      //   85: iconst_4
      //   86: bipush 42
      //   88: ldc 90
      //   90: invokestatic 95	o/O:ˋ	(IIC)Ljava/lang/Object;
      //   93: checkcast 97	java/lang/Class
      //   96: ldc 98
      //   98: iconst_2
      //   99: anewarray 97	java/lang/Class
      //   102: dup
      //   103: iconst_0
      //   104: ldc 57
      //   106: aastore
      //   107: dup
      //   108: iconst_1
      //   109: ldc 57
      //   111: aastore
      //   112: invokevirtual 102	java/lang/Class:getMethod	(Ljava/lang/String;[Ljava/lang/Class;)Ljava/lang/reflect/Method;
      //   115: aconst_null
      //   116: iconst_2
      //   117: anewarray 5	java/lang/Object
      //   120: dup
      //   121: iconst_0
      //   122: aload_3
      //   123: aastore
      //   124: dup
      //   125: iconst_1
      //   126: aload_1
      //   127: aastore
      //   128: invokevirtual 108	java/lang/reflect/Method:invoke	(Ljava/lang/Object;[Ljava/lang/Object;)Ljava/lang/Object;
      //   131: pop
      //   132: return
      //   133: bipush 33
      //   135: istore_2
      //   136: goto +158 -> 294
      //   139: astore_1
      //   140: aload_1
      //   141: athrow
      //   142: bipush 7
      //   144: newarray byte
      //   146: dup
      //   147: iconst_0
      //   148: ldc 70
      //   150: bastore
      //   151: dup
      //   152: iconst_1
      //   153: ldc 71
      //   155: bastore
      //   156: dup
      //   157: iconst_2
      //   158: ldc 72
      //   160: bastore
      //   161: dup
      //   162: iconst_3
      //   163: ldc 73
      //   165: bastore
      //   166: dup
      //   167: iconst_4
      //   168: ldc 74
      //   170: bastore
      //   171: dup
      //   172: iconst_5
      //   173: ldc 75
      //   175: bastore
      //   176: dup
      //   177: bipush 6
      //   179: ldc 76
      //   181: bastore
      //   182: aconst_null
      //   183: aconst_null
      //   184: bipush 127
      //   186: invokestatic 78	o/DG$iF:ˎ	([B[I[CI)Ljava/lang/String;
      //   189: astore_3
      //   190: aload_3
      //   191: invokevirtual 82	java/lang/String:intern	()Ljava/lang/String;
      //   194: astore_3
      //   195: aload_1
      //   196: invokevirtual 85	java/lang/Throwable:getMessage	()Ljava/lang/String;
      //   199: astore_1
      //   200: goto +17 -> 217
      //   203: astore_1
      //   204: aload_1
      //   205: invokevirtual 89	java/lang/Throwable:getCause	()Ljava/lang/Throwable;
      //   208: astore_3
      //   209: aload_3
      //   210: ifnull +5 -> 215
      //   213: aload_3
      //   214: athrow
      //   215: aload_1
      //   216: athrow
      //   217: iconst_4
      //   218: bipush 42
      //   220: ldc 90
      //   222: invokestatic 95	o/O:ˋ	(IIC)Ljava/lang/Object;
      //   225: checkcast 97	java/lang/Class
      //   228: ldc 98
      //   230: iconst_2
      //   231: anewarray 97	java/lang/Class
      //   234: dup
      //   235: iconst_0
      //   236: ldc 57
      //   238: aastore
      //   239: dup
      //   240: iconst_1
      //   241: ldc 57
      //   243: aastore
      //   244: invokevirtual 102	java/lang/Class:getMethod	(Ljava/lang/String;[Ljava/lang/Class;)Ljava/lang/reflect/Method;
      //   247: aconst_null
      //   248: iconst_2
      //   249: anewarray 5	java/lang/Object
      //   252: dup
      //   253: iconst_0
      //   254: aload_3
      //   255: aastore
      //   256: dup
      //   257: iconst_1
      //   258: aload_1
      //   259: aastore
      //   260: invokevirtual 108	java/lang/reflect/Method:invoke	(Ljava/lang/Object;[Ljava/lang/Object;)Ljava/lang/Object;
      //   263: pop
      //   264: return
      //   265: getstatic 30	o/DG$iF:ᐝ	I
      //   268: istore_2
      //   269: iload_2
      //   270: bipush 61
      //   272: iadd
      //   273: istore_2
      //   274: iload_2
      //   275: sipush 128
      //   278: irem
      //   279: putstatic 28	o/DG$iF:ॱॱ	I
      //   282: iload_2
      //   283: iconst_2
      //   284: irem
      //   285: ifeq +6 -> 291
      //   288: goto -155 -> 133
      //   291: goto -288 -> 3
      //   294: iload_2
      //   295: lookupswitch	default:+25->320, 33:+-283->12, 68:+-153->142
      //   320: goto -178 -> 142
      // Local variable table:
      //   start	length	slot	name	signature
      //   0	323	0	this	iF
      //   0	323	1	paramThrowable	Throwable
      //   5	290	2	i	int
      //   62	193	3	localObject	Object
      // Exception table:
      //   from	to	target	type
      //   142	190	9	java/lang/Exception
      //   274	282	9	java/lang/Exception
      //   85	132	71	finally
      //   190	200	139	java/lang/Exception
      //   204	209	139	java/lang/Exception
      //   213	215	139	java/lang/Exception
      //   215	217	139	java/lang/Exception
      //   265	269	139	java/lang/Exception
      //   217	264	203	finally
    }
  }
  
  static final class if<T>
    implements sW<Throwable>
  {
    public static final if ˊ;
    private static int ˋ;
    private static long ˎ;
    private static int ॱ;
    
    static
    {
      for (;;)
      {
        int i = 1;
        break label43;
        throw new NullPointerException();
        return;
        ॱ = 0;
        ˋ = 1;
        ॱ();
        ˊ = new if();
        label43:
        do
        {
          i = 0;
          switch (i)
          {
          }
          return;
          i = ॱ + 83;
          ˋ = i % 128;
        } while (i % 2 == 0);
      }
    }
    
    if() {}
    
    /* Error */
    private static String ˎ(char[] paramArrayOfChar)
    {
      // Byte code:
      //   0: goto +193 -> 193
      //   3: astore_0
      //   4: aload_0
      //   5: athrow
      //   6: iconst_5
      //   7: iconst_4
      //   8: idiv
      //   9: istore_3
      //   10: goto +138 -> 148
      //   13: bipush 27
      //   15: istore_1
      //   16: goto +38 -> 54
      //   19: aload_0
      //   20: iload_2
      //   21: caload
      //   22: iload_2
      //   23: iload_1
      //   24: imul
      //   25: ixor
      //   26: i2l
      //   27: lstore 4
      //   29: getstatic 41	o/DG$if:ˎ	J
      //   32: lstore 6
      //   34: aload 8
      //   36: iload_2
      //   37: iconst_1
      //   38: isub
      //   39: lload 4
      //   41: lload 6
      //   43: lxor
      //   44: l2i
      //   45: i2c
      //   46: castore
      //   47: iload_2
      //   48: iconst_1
      //   49: iadd
      //   50: istore_2
      //   51: goto +97 -> 148
      //   54: iload_1
      //   55: lookupswitch	default:+25->80, 27:+180->235, 98:+28->83
      //   80: goto +155 -> 235
      //   83: aload_0
      //   84: astore 8
      //   86: aload 8
      //   88: iconst_0
      //   89: caload
      //   90: istore_1
      //   91: aload 8
      //   93: arraylength
      //   94: iconst_1
      //   95: isub
      //   96: newarray char
      //   98: astore 8
      //   100: goto +104 -> 204
      //   103: getstatic 29	o/DG$if:ˋ	I
      //   106: bipush 29
      //   108: iadd
      //   109: istore_1
      //   110: iload_1
      //   111: sipush 128
      //   114: irem
      //   115: putstatic 27	o/DG$if:ॱ	I
      //   118: iload_1
      //   119: iconst_2
      //   120: irem
      //   121: ifeq +6 -> 127
      //   124: goto -111 -> 13
      //   127: goto +60 -> 187
      //   130: astore_0
      //   131: aload_0
      //   132: athrow
      //   133: iconst_1
      //   134: istore_3
      //   135: goto +25 -> 160
      //   138: new 43	java/lang/String
      //   141: dup
      //   142: aload 8
      //   144: invokespecial 46	java/lang/String:<init>	([C)V
      //   147: areturn
      //   148: iload_2
      //   149: aload_0
      //   150: arraylength
      //   151: if_icmpge +6 -> 157
      //   154: goto -21 -> 133
      //   157: goto +42 -> 199
      //   160: iload_3
      //   161: tableswitch	default:+23->184, 0:+-23->138, 1:+-142->19
      //   184: goto -46 -> 138
      //   187: bipush 98
      //   189: istore_1
      //   190: goto -136 -> 54
      //   193: goto -90 -> 103
      //   196: goto -48 -> 148
      //   199: iconst_0
      //   200: istore_3
      //   201: goto -41 -> 160
      //   204: iconst_1
      //   205: istore_2
      //   206: getstatic 29	o/DG$if:ˋ	I
      //   209: istore_3
      //   210: iload_3
      //   211: bipush 91
      //   213: iadd
      //   214: istore_3
      //   215: iload_3
      //   216: sipush 128
      //   219: irem
      //   220: putstatic 27	o/DG$if:ॱ	I
      //   223: iload_3
      //   224: iconst_2
      //   225: irem
      //   226: ifeq +6 -> 232
      //   229: goto -223 -> 6
      //   232: goto -36 -> 196
      //   235: aload_0
      //   236: astore 8
      //   238: aload 8
      //   240: iconst_0
      //   241: caload
      //   242: istore_1
      //   243: aload 8
      //   245: arraylength
      //   246: iconst_1
      //   247: ishl
      //   248: newarray char
      //   250: astore 8
      //   252: goto -48 -> 204
      // Local variable table:
      //   start	length	slot	name	signature
      //   0	255	0	paramArrayOfChar	char[]
      //   15	228	1	i	int
      //   20	186	2	j	int
      //   9	217	3	k	int
      //   27	13	4	l1	long
      //   32	10	6	l2	long
      //   34	217	8	arrayOfChar	char[]
      // Exception table:
      //   from	to	target	type
      //   206	210	3	java/lang/Exception
      //   29	34	130	java/lang/Exception
      //   103	110	130	java/lang/Exception
      //   110	118	130	java/lang/Exception
      //   215	223	130	java/lang/Exception
    }
    
    static void ॱ()
    {
      ˎ = -9190841672516822286L;
    }
    
    /* Error */
    public final void ॱ(Throwable paramThrowable)
    {
      // Byte code:
      //   0: goto +171 -> 171
      //   3: astore_1
      //   4: aload_1
      //   5: athrow
      //   6: bipush 8
      //   8: newarray char
      //   10: dup
      //   11: iconst_0
      //   12: ldc 55
      //   14: castore
      //   15: dup
      //   16: iconst_1
      //   17: ldc 56
      //   19: castore
      //   20: dup
      //   21: iconst_2
      //   22: ldc 57
      //   24: castore
      //   25: dup
      //   26: iconst_3
      //   27: ldc 58
      //   29: castore
      //   30: dup
      //   31: iconst_4
      //   32: ldc 59
      //   34: castore
      //   35: dup
      //   36: iconst_5
      //   37: ldc 60
      //   39: castore
      //   40: dup
      //   41: bipush 6
      //   43: ldc 61
      //   45: castore
      //   46: dup
      //   47: bipush 7
      //   49: ldc 62
      //   51: castore
      //   52: invokestatic 64	o/DG$if:ˎ	([C)Ljava/lang/String;
      //   55: invokevirtual 68	java/lang/String:intern	()Ljava/lang/String;
      //   58: astore_3
      //   59: aload_1
      //   60: invokevirtual 71	java/lang/Throwable:getMessage	()Ljava/lang/String;
      //   63: astore_1
      //   64: goto +17 -> 81
      //   67: astore_3
      //   68: aload_3
      //   69: invokevirtual 75	java/lang/Throwable:getCause	()Ljava/lang/Throwable;
      //   72: astore_1
      //   73: aload_1
      //   74: ifnull +5 -> 79
      //   77: aload_1
      //   78: athrow
      //   79: aload_3
      //   80: athrow
      //   81: iconst_4
      //   82: bipush 42
      //   84: ldc 76
      //   86: invokestatic 81	o/O:ˋ	(IIC)Ljava/lang/Object;
      //   89: checkcast 83	java/lang/Class
      //   92: ldc 84
      //   94: iconst_2
      //   95: anewarray 83	java/lang/Class
      //   98: dup
      //   99: iconst_0
      //   100: ldc 43
      //   102: aastore
      //   103: dup
      //   104: iconst_1
      //   105: ldc 43
      //   107: aastore
      //   108: invokevirtual 88	java/lang/Class:getMethod	(Ljava/lang/String;[Ljava/lang/Class;)Ljava/lang/reflect/Method;
      //   111: aconst_null
      //   112: iconst_2
      //   113: anewarray 5	java/lang/Object
      //   116: dup
      //   117: iconst_0
      //   118: aload_3
      //   119: aastore
      //   120: dup
      //   121: iconst_1
      //   122: aload_1
      //   123: aastore
      //   124: invokevirtual 94	java/lang/reflect/Method:invoke	(Ljava/lang/Object;[Ljava/lang/Object;)Ljava/lang/Object;
      //   127: pop
      //   128: new 22	java/lang/NullPointerException
      //   131: dup
      //   132: invokespecial 25	java/lang/NullPointerException:<init>	()V
      //   135: athrow
      //   136: iconst_0
      //   137: istore_2
      //   138: iload_2
      //   139: tableswitch	default:+21->160, 0:+-133->6, 1:+35->174
      //   160: goto +14 -> 174
      //   163: iconst_1
      //   164: istore_2
      //   165: goto -27 -> 138
      //   168: astore_1
      //   169: aload_1
      //   170: athrow
      //   171: goto +126 -> 297
      //   174: bipush 8
      //   176: newarray char
      //   178: dup
      //   179: iconst_0
      //   180: ldc 55
      //   182: castore
      //   183: dup
      //   184: iconst_1
      //   185: ldc 56
      //   187: castore
      //   188: dup
      //   189: iconst_2
      //   190: ldc 57
      //   192: castore
      //   193: dup
      //   194: iconst_3
      //   195: ldc 58
      //   197: castore
      //   198: dup
      //   199: iconst_4
      //   200: ldc 59
      //   202: castore
      //   203: dup
      //   204: iconst_5
      //   205: ldc 60
      //   207: castore
      //   208: dup
      //   209: bipush 6
      //   211: ldc 61
      //   213: castore
      //   214: dup
      //   215: bipush 7
      //   217: ldc 62
      //   219: castore
      //   220: invokestatic 64	o/DG$if:ˎ	([C)Ljava/lang/String;
      //   223: invokevirtual 68	java/lang/String:intern	()Ljava/lang/String;
      //   226: astore_3
      //   227: aload_1
      //   228: invokevirtual 71	java/lang/Throwable:getMessage	()Ljava/lang/String;
      //   231: astore_1
      //   232: goto +17 -> 249
      //   235: astore_1
      //   236: aload_1
      //   237: invokevirtual 75	java/lang/Throwable:getCause	()Ljava/lang/Throwable;
      //   240: astore_3
      //   241: aload_3
      //   242: ifnull +5 -> 247
      //   245: aload_3
      //   246: athrow
      //   247: aload_1
      //   248: athrow
      //   249: iconst_4
      //   250: bipush 42
      //   252: ldc 76
      //   254: invokestatic 81	o/O:ˋ	(IIC)Ljava/lang/Object;
      //   257: checkcast 83	java/lang/Class
      //   260: ldc 84
      //   262: iconst_2
      //   263: anewarray 83	java/lang/Class
      //   266: dup
      //   267: iconst_0
      //   268: ldc 43
      //   270: aastore
      //   271: dup
      //   272: iconst_1
      //   273: ldc 43
      //   275: aastore
      //   276: invokevirtual 88	java/lang/Class:getMethod	(Ljava/lang/String;[Ljava/lang/Class;)Ljava/lang/reflect/Method;
      //   279: aconst_null
      //   280: iconst_2
      //   281: anewarray 5	java/lang/Object
      //   284: dup
      //   285: iconst_0
      //   286: aload_3
      //   287: aastore
      //   288: dup
      //   289: iconst_1
      //   290: aload_1
      //   291: aastore
      //   292: invokevirtual 94	java/lang/reflect/Method:invoke	(Ljava/lang/Object;[Ljava/lang/Object;)Ljava/lang/Object;
      //   295: pop
      //   296: return
      //   297: getstatic 27	o/DG$if:ॱ	I
      //   300: bipush 89
      //   302: iadd
      //   303: istore_2
      //   304: iload_2
      //   305: sipush 128
      //   308: irem
      //   309: putstatic 29	o/DG$if:ˋ	I
      //   312: iload_2
      //   313: iconst_2
      //   314: irem
      //   315: ifne +6 -> 321
      //   318: goto -182 -> 136
      //   321: goto -158 -> 163
      // Local variable table:
      //   start	length	slot	name	signature
      //   0	324	0	this	if
      //   0	324	1	paramThrowable	Throwable
      //   137	178	2	i	int
      //   58	1	3	str	String
      //   67	52	3	localObject1	Object
      //   226	61	3	localObject2	Object
      // Exception table:
      //   from	to	target	type
      //   304	312	3	java/lang/Exception
      //   81	128	67	finally
      //   297	304	168	java/lang/Exception
      //   304	312	168	java/lang/Exception
      //   249	296	235	finally
    }
  }
  
  static final class ˊ
    implements sR
  {
    private static int ʽ = 0;
    private static boolean ˊ;
    private static char[] ˋ = { 335, 358, 373, 376, 368, 371, 364, 341, 361, 289, 369, 374, 372, 367, 354, 357, 315 };
    private static int ˏ = 257;
    private static boolean ॱ;
    private static int ॱॱ = 1;
    
    static
    {
      ˊ = true;
      ॱ = true;
    }
    
    /* Error */
    ˊ(String paramString)
    {
      // Byte code:
      //   0: goto +6 -> 6
      //   3: astore_1
      //   4: aload_1
      //   5: athrow
      //   6: aload_0
      //   7: aload_1
      //   8: putfield 58	o/DG$ˊ:ˎ	Ljava/lang/String;
      //   11: aload_0
      //   12: invokespecial 60	java/lang/Object:<init>	()V
      //   15: return
      // Local variable table:
      //   start	length	slot	name	signature
      //   0	16	0	this	ˊ
      //   0	16	1	paramString	String
      // Exception table:
      //   from	to	target	type
      //   6	11	3	java/lang/Exception
    }
    
    /* Error */
    private static String ˎ(byte[] paramArrayOfByte, int[] paramArrayOfInt, char[] paramArrayOfChar, int paramInt)
    {
      // Byte code:
      //   0: goto +188 -> 188
      //   3: aload_2
      //   4: arraylength
      //   5: istore 7
      //   7: iload 7
      //   9: newarray char
      //   11: astore_0
      //   12: iconst_0
      //   13: istore 4
      //   15: goto +396 -> 411
      //   18: new 63	java/lang/String
      //   21: dup
      //   22: aload_0
      //   23: invokespecial 66	java/lang/String:<init>	([C)V
      //   26: areturn
      //   27: iload 4
      //   29: iload 5
      //   31: if_icmpge +6 -> 37
      //   34: goto +347 -> 381
      //   37: goto +142 -> 179
      //   40: getstatic 27	o/DG$ˊ:ॱॱ	I
      //   43: istore 5
      //   45: iload 5
      //   47: bipush 57
      //   49: iadd
      //   50: istore 5
      //   52: iload 5
      //   54: sipush 128
      //   57: irem
      //   58: putstatic 25	o/DG$ˊ:ʽ	I
      //   61: iload 5
      //   63: iconst_2
      //   64: irem
      //   65: ifeq +6 -> 71
      //   68: goto +400 -> 468
      //   71: goto +212 -> 283
      //   74: goto -47 -> 27
      //   77: aload_0
      //   78: arraylength
      //   79: istore 7
      //   81: iload 7
      //   83: newarray char
      //   85: astore_1
      //   86: iconst_0
      //   87: istore 4
      //   89: goto +111 -> 200
      //   92: aload_0
      //   93: iload 4
      //   95: aload 8
      //   97: aload_1
      //   98: iload 5
      //   100: iconst_1
      //   101: isub
      //   102: iload 4
      //   104: isub
      //   105: iaload
      //   106: iload_3
      //   107: isub
      //   108: caload
      //   109: iload 6
      //   111: isub
      //   112: i2c
      //   113: castore
      //   114: iload 4
      //   116: iconst_1
      //   117: iadd
      //   118: istore 4
      //   120: goto -93 -> 27
      //   123: iconst_0
      //   124: istore 5
      //   126: goto +130 -> 256
      //   129: aload_1
      //   130: arraylength
      //   131: istore 5
      //   133: iload 5
      //   135: newarray char
      //   137: astore_0
      //   138: iconst_0
      //   139: istore 4
      //   141: goto -67 -> 74
      //   144: goto -141 -> 3
      //   147: iload 5
      //   149: lookupswitch	default:+27->176, 8:+-131->18, 61:+76->225
      //   176: goto -158 -> 18
      //   179: new 63	java/lang/String
      //   182: dup
      //   183: aload_0
      //   184: invokespecial 66	java/lang/String:<init>	([C)V
      //   187: areturn
      //   188: goto +132 -> 320
      //   191: new 63	java/lang/String
      //   194: dup
      //   195: aload_1
      //   196: invokespecial 66	java/lang/String:<init>	([C)V
      //   199: areturn
      //   200: iload 4
      //   202: iload 7
      //   204: if_icmpge +6 -> 210
      //   207: goto +143 -> 350
      //   210: goto -87 -> 123
      //   213: getstatic 31	o/DG$ˊ:ॱ	Z
      //   216: ifeq +6 -> 222
      //   219: goto +205 -> 424
      //   222: goto -93 -> 129
      //   225: aload_0
      //   226: iload 4
      //   228: aload 8
      //   230: aload_2
      //   231: iload 7
      //   233: iconst_1
      //   234: isub
      //   235: iload 4
      //   237: isub
      //   238: caload
      //   239: iload_3
      //   240: isub
      //   241: caload
      //   242: iload 6
      //   244: isub
      //   245: i2c
      //   246: castore
      //   247: iload 4
      //   249: iconst_1
      //   250: iadd
      //   251: istore 4
      //   253: goto +158 -> 411
      //   256: iload 5
      //   258: tableswitch	default:+22->280, 0:+-67->191, 1:+-218->40
      //   280: goto -89 -> 191
      //   283: aload_1
      //   284: iload 4
      //   286: aload 8
      //   288: aload_0
      //   289: iload 7
      //   291: iconst_1
      //   292: isub
      //   293: iload 4
      //   295: isub
      //   296: baload
      //   297: iload_3
      //   298: iadd
      //   299: caload
      //   300: iload 6
      //   302: isub
      //   303: i2c
      //   304: castore
      //   305: iload 4
      //   307: iconst_1
      //   308: iadd
      //   309: istore 4
      //   311: goto +6 -> 317
      //   314: goto -222 -> 92
      //   317: goto -117 -> 200
      //   320: getstatic 25	o/DG$ˊ:ʽ	I
      //   323: bipush 55
      //   325: iadd
      //   326: istore 4
      //   328: iload 4
      //   330: sipush 128
      //   333: irem
      //   334: putstatic 27	o/DG$ˊ:ॱॱ	I
      //   337: iload 4
      //   339: iconst_2
      //   340: irem
      //   341: ifne +6 -> 347
      //   344: goto +34 -> 378
      //   347: goto +9 -> 356
      //   350: iconst_1
      //   351: istore 5
      //   353: goto -97 -> 256
      //   356: getstatic 50	o/DG$ˊ:ˋ	[C
      //   359: astore 8
      //   361: getstatic 52	o/DG$ˊ:ˏ	I
      //   364: istore 6
      //   366: getstatic 29	o/DG$ˊ:ˊ	Z
      //   369: ifeq +6 -> 375
      //   372: goto -295 -> 77
      //   375: goto -162 -> 213
      //   378: goto -22 -> 356
      //   381: getstatic 25	o/DG$ˊ:ʽ	I
      //   384: bipush 85
      //   386: iadd
      //   387: istore 7
      //   389: iload 7
      //   391: sipush 128
      //   394: irem
      //   395: putstatic 27	o/DG$ˊ:ॱॱ	I
      //   398: iload 7
      //   400: iconst_2
      //   401: irem
      //   402: ifne +6 -> 408
      //   405: goto -91 -> 314
      //   408: goto -316 -> 92
      //   411: iload 4
      //   413: iload 7
      //   415: if_icmpge +6 -> 421
      //   418: goto +36 -> 454
      //   421: goto +40 -> 461
      //   424: getstatic 27	o/DG$ˊ:ॱॱ	I
      //   427: bipush 83
      //   429: iadd
      //   430: istore 4
      //   432: iload 4
      //   434: sipush 128
      //   437: irem
      //   438: putstatic 25	o/DG$ˊ:ʽ	I
      //   441: iload 4
      //   443: iconst_2
      //   444: irem
      //   445: ifeq +6 -> 451
      //   448: goto -304 -> 144
      //   451: goto -448 -> 3
      //   454: bipush 61
      //   456: istore 5
      //   458: goto -311 -> 147
      //   461: bipush 8
      //   463: istore 5
      //   465: goto -318 -> 147
      //   468: goto -185 -> 283
      //   471: astore_0
      //   472: aload_0
      //   473: athrow
      //   474: astore_0
      //   475: aload_0
      //   476: athrow
      // Local variable table:
      //   start	length	slot	name	signature
      //   0	477	0	paramArrayOfByte	byte[]
      //   0	477	1	paramArrayOfInt	int[]
      //   0	477	2	paramArrayOfChar	char[]
      //   0	477	3	paramInt	int
      //   13	432	4	i	int
      //   29	435	5	j	int
      //   109	256	6	k	int
      //   5	411	7	m	int
      //   95	265	8	arrayOfChar	char[]
      // Exception table:
      //   from	to	target	type
      //   40	45	471	java/lang/Exception
      //   52	61	474	java/lang/Exception
      //   424	432	474	java/lang/Exception
      //   432	441	474	java/lang/Exception
    }
    
    /* Error */
    public final void ॱ()
    {
      // Byte code:
      //   0: goto +33 -> 33
      //   3: iload_1
      //   4: lookupswitch	default:+28->32, 72:+407->411, 81:+65->69
      //   32: return
      //   33: goto +37 -> 70
      //   36: getstatic 25	o/DG$ˊ:ʽ	I
      //   39: bipush 41
      //   41: iadd
      //   42: istore_1
      //   43: iload_1
      //   44: sipush 128
      //   47: irem
      //   48: putstatic 27	o/DG$ˊ:ॱॱ	I
      //   51: iload_1
      //   52: iconst_2
      //   53: irem
      //   54: ifne +6 -> 60
      //   57: goto +365 -> 422
      //   60: bipush 81
      //   62: istore_1
      //   63: goto -60 -> 3
      //   66: astore_2
      //   67: aload_2
      //   68: athrow
      //   69: return
      //   70: bipush 7
      //   72: newarray byte
      //   74: dup
      //   75: iconst_0
      //   76: ldc 67
      //   78: bastore
      //   79: dup
      //   80: iconst_1
      //   81: ldc 68
      //   83: bastore
      //   84: dup
      //   85: iconst_2
      //   86: ldc 69
      //   88: bastore
      //   89: dup
      //   90: iconst_3
      //   91: ldc 70
      //   93: bastore
      //   94: dup
      //   95: iconst_4
      //   96: ldc 71
      //   98: bastore
      //   99: dup
      //   100: iconst_5
      //   101: ldc 72
      //   103: bastore
      //   104: dup
      //   105: bipush 6
      //   107: ldc 73
      //   109: bastore
      //   110: aconst_null
      //   111: aconst_null
      //   112: bipush 127
      //   114: invokestatic 75	o/DG$ˊ:ˎ	([B[I[CI)Ljava/lang/String;
      //   117: astore_2
      //   118: aload_2
      //   119: invokevirtual 79	java/lang/String:intern	()Ljava/lang/String;
      //   122: astore_2
      //   123: new 81	java/lang/StringBuilder
      //   126: dup
      //   127: invokespecial 82	java/lang/StringBuilder:<init>	()V
      //   130: astore_3
      //   131: bipush 31
      //   133: newarray byte
      //   135: dup
      //   136: iconst_0
      //   137: ldc 83
      //   139: bastore
      //   140: dup
      //   141: iconst_1
      //   142: ldc 84
      //   144: bastore
      //   145: dup
      //   146: iconst_2
      //   147: ldc 69
      //   149: bastore
      //   150: dup
      //   151: iconst_3
      //   152: ldc 71
      //   154: bastore
      //   155: dup
      //   156: iconst_4
      //   157: ldc 83
      //   159: bastore
      //   160: dup
      //   161: iconst_5
      //   162: ldc 85
      //   164: bastore
      //   165: dup
      //   166: bipush 6
      //   168: ldc 72
      //   170: bastore
      //   171: dup
      //   172: bipush 7
      //   174: ldc 71
      //   176: bastore
      //   177: dup
      //   178: bipush 8
      //   180: ldc 86
      //   182: bastore
      //   183: dup
      //   184: bipush 9
      //   186: ldc 85
      //   188: bastore
      //   189: dup
      //   190: bipush 10
      //   192: ldc 87
      //   194: bastore
      //   195: dup
      //   196: bipush 11
      //   198: ldc 88
      //   200: bastore
      //   201: dup
      //   202: bipush 12
      //   204: ldc 83
      //   206: bastore
      //   207: dup
      //   208: bipush 13
      //   210: ldc 89
      //   212: bastore
      //   213: dup
      //   214: bipush 14
      //   216: ldc 86
      //   218: bastore
      //   219: dup
      //   220: bipush 15
      //   222: ldc 70
      //   224: bastore
      //   225: dup
      //   226: bipush 16
      //   228: ldc 83
      //   230: bastore
      //   231: dup
      //   232: bipush 17
      //   234: ldc 90
      //   236: bastore
      //   237: dup
      //   238: bipush 18
      //   240: ldc 72
      //   242: bastore
      //   243: dup
      //   244: bipush 19
      //   246: ldc 67
      //   248: bastore
      //   249: dup
      //   250: bipush 20
      //   252: ldc 69
      //   254: bastore
      //   255: dup
      //   256: bipush 21
      //   258: ldc 71
      //   260: bastore
      //   261: dup
      //   262: bipush 22
      //   264: ldc 83
      //   266: bastore
      //   267: dup
      //   268: bipush 23
      //   270: ldc 91
      //   272: bastore
      //   273: dup
      //   274: bipush 24
      //   276: ldc 89
      //   278: bastore
      //   279: dup
      //   280: bipush 25
      //   282: ldc 88
      //   284: bastore
      //   285: dup
      //   286: bipush 26
      //   288: ldc 87
      //   290: bastore
      //   291: dup
      //   292: bipush 27
      //   294: ldc 83
      //   296: bastore
      //   297: dup
      //   298: bipush 28
      //   300: ldc 72
      //   302: bastore
      //   303: dup
      //   304: bipush 29
      //   306: ldc 91
      //   308: bastore
      //   309: dup
      //   310: bipush 30
      //   312: ldc 92
      //   314: bastore
      //   315: aconst_null
      //   316: aconst_null
      //   317: bipush 127
      //   319: invokestatic 75	o/DG$ˊ:ˎ	([B[I[CI)Ljava/lang/String;
      //   322: astore 4
      //   324: aload_3
      //   325: aload 4
      //   327: invokevirtual 79	java/lang/String:intern	()Ljava/lang/String;
      //   330: invokevirtual 96	java/lang/StringBuilder:append	(Ljava/lang/String;)Ljava/lang/StringBuilder;
      //   333: aload_0
      //   334: getfield 58	o/DG$ˊ:ˎ	Ljava/lang/String;
      //   337: invokevirtual 96	java/lang/StringBuilder:append	(Ljava/lang/String;)Ljava/lang/StringBuilder;
      //   340: invokevirtual 99	java/lang/StringBuilder:toString	()Ljava/lang/String;
      //   343: astore_3
      //   344: goto +17 -> 361
      //   347: astore_2
      //   348: aload_2
      //   349: invokevirtual 105	java/lang/Throwable:getCause	()Ljava/lang/Throwable;
      //   352: astore_3
      //   353: aload_3
      //   354: ifnull +5 -> 359
      //   357: aload_3
      //   358: athrow
      //   359: aload_2
      //   360: athrow
      //   361: iconst_4
      //   362: bipush 42
      //   364: ldc 106
      //   366: invokestatic 111	o/O:ˋ	(IIC)Ljava/lang/Object;
      //   369: checkcast 113	java/lang/Class
      //   372: ldc 114
      //   374: iconst_2
      //   375: anewarray 113	java/lang/Class
      //   378: dup
      //   379: iconst_0
      //   380: ldc 63
      //   382: aastore
      //   383: dup
      //   384: iconst_1
      //   385: ldc 63
      //   387: aastore
      //   388: invokevirtual 118	java/lang/Class:getMethod	(Ljava/lang/String;[Ljava/lang/Class;)Ljava/lang/reflect/Method;
      //   391: aconst_null
      //   392: iconst_2
      //   393: anewarray 4	java/lang/Object
      //   396: dup
      //   397: iconst_0
      //   398: aload_2
      //   399: aastore
      //   400: dup
      //   401: iconst_1
      //   402: aload_3
      //   403: aastore
      //   404: invokevirtual 124	java/lang/reflect/Method:invoke	(Ljava/lang/Object;[Ljava/lang/Object;)Ljava/lang/Object;
      //   407: pop
      //   408: goto -372 -> 36
      //   411: new 126	java/lang/NullPointerException
      //   414: dup
      //   415: invokespecial 127	java/lang/NullPointerException:<init>	()V
      //   418: athrow
      //   419: astore_2
      //   420: aload_2
      //   421: athrow
      //   422: bipush 72
      //   424: istore_1
      //   425: goto -422 -> 3
      // Local variable table:
      //   start	length	slot	name	signature
      //   0	428	0	this	ˊ
      //   3	422	1	i	int
      //   66	2	2	localException1	Exception
      //   117	6	2	str1	String
      //   347	52	2	localObject1	Object
      //   419	2	2	localException2	Exception
      //   130	273	3	localObject2	Object
      //   322	4	4	str2	String
      // Exception table:
      //   from	to	target	type
      //   70	118	66	java/lang/Exception
      //   118	131	66	java/lang/Exception
      //   131	324	66	java/lang/Exception
      //   324	344	66	java/lang/Exception
      //   348	353	66	java/lang/Exception
      //   357	359	66	java/lang/Exception
      //   359	361	66	java/lang/Exception
      //   361	408	347	finally
      //   131	324	419	java/lang/Exception
    }
  }
  
  static final class ˋ<T>
    implements sX<String>
  {
    public static final ˋ ˋ;
    private static int ˎ;
    private static long ˏ;
    private static int ॱ;
    
    static
    {
      break label74;
      return;
      int i;
      for (;;)
      {
        switch (i)
        {
        case 0: 
        default: 
          break label63;
          label31:
          i = 1;
        }
      }
      for (;;)
      {
        i = ˎ + 45;
        ॱ = i % 128;
        if (i % 2 == 0) {
          break label31;
        }
        break label69;
        label63:
        i = 61 / 0;
        return;
        label69:
        i = 0;
        break;
        label74:
        ˎ = 0;
        ॱ = 1;
        ˋ();
        ˋ = new ˋ();
      }
    }
    
    ˋ() {}
    
    /* Error */
    private static String ˋ(char[] paramArrayOfChar)
    {
      // Byte code:
      //   0: goto +208 -> 208
      //   3: aload_0
      //   4: iload_1
      //   5: aload_0
      //   6: iload_1
      //   7: caload
      //   8: aload_0
      //   9: iload_1
      //   10: iconst_5
      //   11: idiv
      //   12: caload
      //   13: ior
      //   14: i2l
      //   15: iload_1
      //   16: iconst_3
      //   17: iadd
      //   18: i2l
      //   19: getstatic 37	o/DG$ˋ:ˏ	J
      //   22: land
      //   23: lor
      //   24: l2i
      //   25: i2c
      //   26: castore
      //   27: iload_1
      //   28: bipush 50
      //   30: iadd
      //   31: istore_1
      //   32: goto +185 -> 217
      //   35: iload_2
      //   36: lookupswitch	default:+28->64, 55:+78->114, 59:+-33->3
      //   64: goto -61 -> 3
      //   67: getstatic 21	o/DG$ˋ:ˎ	I
      //   70: bipush 69
      //   72: iadd
      //   73: istore_2
      //   74: iload_2
      //   75: sipush 128
      //   78: irem
      //   79: putstatic 23	o/DG$ˋ:ॱ	I
      //   82: iload_2
      //   83: iconst_2
      //   84: irem
      //   85: ifne +6 -> 91
      //   88: goto +156 -> 244
      //   91: goto +17 -> 108
      //   94: new 39	java/lang/String
      //   97: dup
      //   98: aload_0
      //   99: iconst_4
      //   100: aload_0
      //   101: arraylength
      //   102: iconst_4
      //   103: isub
      //   104: invokespecial 42	java/lang/String:<init>	([CII)V
      //   107: areturn
      //   108: bipush 55
      //   110: istore_2
      //   111: goto -76 -> 35
      //   114: aload_0
      //   115: iload_1
      //   116: aload_0
      //   117: iload_1
      //   118: caload
      //   119: aload_0
      //   120: iload_1
      //   121: iconst_4
      //   122: irem
      //   123: caload
      //   124: ixor
      //   125: i2l
      //   126: iload_1
      //   127: iconst_4
      //   128: isub
      //   129: i2l
      //   130: getstatic 37	o/DG$ˋ:ˏ	J
      //   133: lmul
      //   134: lxor
      //   135: l2i
      //   136: i2c
      //   137: castore
      //   138: iload_1
      //   139: iconst_1
      //   140: iadd
      //   141: istore_1
      //   142: goto +75 -> 217
      //   145: iload_1
      //   146: lookupswitch	default:+26->172, 14:+104->250, 51:+83->229
      //   172: goto +78 -> 250
      //   175: astore_0
      //   176: aload_0
      //   177: athrow
      //   178: goto +39 -> 217
      //   181: getstatic 21	o/DG$ˋ:ˎ	I
      //   184: bipush 123
      //   186: iadd
      //   187: istore_1
      //   188: iload_1
      //   189: sipush 128
      //   192: irem
      //   193: putstatic 23	o/DG$ˋ:ॱ	I
      //   196: iload_1
      //   197: iconst_2
      //   198: irem
      //   199: ifne +6 -> 205
      //   202: goto +61 -> 263
      //   205: goto +6 -> 211
      //   208: goto -27 -> 181
      //   211: bipush 14
      //   213: istore_1
      //   214: goto -69 -> 145
      //   217: iload_1
      //   218: aload_0
      //   219: arraylength
      //   220: if_icmpge +6 -> 226
      //   223: goto -156 -> 67
      //   226: goto -132 -> 94
      //   229: getstatic 37	o/DG$ˋ:ˏ	J
      //   232: lstore_3
      //   233: lload_3
      //   234: aload_0
      //   235: invokestatic 47	o/oL:ˋ	(J[C)[C
      //   238: astore_0
      //   239: iconst_2
      //   240: istore_1
      //   241: goto -63 -> 178
      //   244: bipush 59
      //   246: istore_2
      //   247: goto -212 -> 35
      //   250: getstatic 37	o/DG$ˋ:ˏ	J
      //   253: aload_0
      //   254: invokestatic 47	o/oL:ˋ	(J[C)[C
      //   257: astore_0
      //   258: iconst_4
      //   259: istore_1
      //   260: goto -82 -> 178
      //   263: bipush 51
      //   265: istore_1
      //   266: goto -121 -> 145
      // Local variable table:
      //   start	length	slot	name	signature
      //   0	269	0	paramArrayOfChar	char[]
      //   4	262	1	i	int
      //   35	212	2	j	int
      //   232	2	3	l	long
      // Exception table:
      //   from	to	target	type
      //   181	188	175	java/lang/Exception
      //   188	196	175	java/lang/Exception
      //   229	233	175	java/lang/Exception
      //   233	239	175	java/lang/Exception
    }
    
    static void ˋ()
    {
      ˏ = -6266442677842411847L;
    }
    
    public final boolean ˏ(String paramString)
    {
      break label27;
      return false;
      int i;
      boolean bool;
      for (;;)
      {
        i = 0;
        break;
        bool = false;
        break label135;
        i = 47;
        break label162;
        label21:
        i = 29;
        break label162;
        label27:
        vq.ˎ(paramString, ˋ(new char[] { -17156, -17272, -13156, 12874, -1007, 2876, 264, -2190, 18038 }).intern());
        if (!TextUtils.isEmpty((CharSequence)paramString)) {
          break label191;
        }
      }
      label105:
      label107:
      for (;;)
      {
        return bool;
      }
      switch (i)
      {
      case 0: 
      default: 
        label110:
        break;
      }
      for (;;)
      {
        label135:
        i = ॱ + 43;
        ˎ = i % 128;
        if (i % 2 != 0) {
          break label107;
        }
        break label105;
        switch (i)
        {
        case 29: 
        default: 
          break label223;
          i = 1;
          break label110;
          i = ˎ + 61;
          ॱ = i % 128;
          if (i % 2 == 0) {
            break label21;
          }
          break;
        case 47: 
          label162:
          label191:
          label223:
          bool = true;
        }
      }
    }
  }
}
