package o;

import ro.btrl.commons.repository.AppRepository;

@uw
public final class DH
  extends AppRepository
  implements DF
{
  private static int ˎ = 0;
  private static int ˏ = 1;
  private static long ॱ = 1313186014800126045L;
  
  @uv
  public DH() {}
  
  private static String ॱ(char[] paramArrayOfChar)
  {
    break label37;
    break label152;
    label6:
    int i;
    paramArrayOfChar[i] = ((char)(int)(paramArrayOfChar[i] ^ paramArrayOfChar[(i % 4)] ^ (i - 4) * ॱ));
    i += 1;
    for (;;)
    {
      label37:
      int j;
      try
      {
        i = ˎ;
        i += 5;
        try
        {
          ˏ = i % 128;
          if (i % 2 == 0) {
            break label183;
          }
          return paramArrayOfChar;
        }
        catch (Exception paramArrayOfChar)
        {
          throw paramArrayOfChar;
        }
        paramArrayOfChar = new String(paramArrayOfChar, 4, paramArrayOfChar.length - 4);
        continue;
        j = ˏ + 9;
        ˎ = j % 128;
        if (j % 2 == 0)
        {
          break;
          switch (j)
          {
          }
          break label6;
          j = 85;
          continue;
        }
      }
      catch (Exception paramArrayOfChar)
      {
        label152:
        throw paramArrayOfChar;
      }
      if (i >= paramArrayOfChar.length)
      {
        continue;
        paramArrayOfChar = oL.ˋ(ॱ, paramArrayOfChar);
        i = 4;
        continue;
        label183:
        return paramArrayOfChar;
      }
      else
      {
        j = 41;
      }
    }
  }
  
  public sp ˎ(final Gr paramGr)
  {
    for (;;)
    {
      vq.ˎ(paramGr, ॱ(new char[] { -24130, -24101, 6760, -12963, 1494, 14936, -29306, 25768, 8358, -17416, 3863, -6343, -23772, 14664, -29044, 26202 }).intern());
      paramGr = ॱॱ().ॱ().ˋ((sV)iF.ˏ).ˎ((sV)new ˋ(this, paramGr)).ˋ(ur.ॱ());
      vq.ˋ(paramGr, ॱ(new char[] { 11718, 11682, -8059, -6111, -32388, -16198, -22347, -8180, -21289, 16672, 10843, 25490, 12124, -15443, -21520, -7486, -22028, 17496, 11636, 25696, 10360, -14644, -20798, -6161, -21781, 18251, 12209, 26964, 1368, -13853, -24272, -5951, -22653, 19054, 8866, 27248, 9736, -13488, -23512, -4696, -24390, 19857, 9611, 28450, 8994, -12795, -22767, -4464, -24044, 20661, 14584, 28743, 15519, -11935 }).intern());
      int i = ˏ + 87;
      ˎ = i % 128;
      if (i % 2 == 0) {
        return paramGr;
      }
      return paramGr;
    }
  }
  
  public sz<Gn> ˎ()
  {
    break label21;
    sz localSz = ॱॱ().ॱ();
    throw new NullPointerException();
    label21:
    break label106;
    label24:
    int i = ˎ + 13;
    ˏ = i % 128;
    if (i % 2 != 0) {
      return localSz;
    }
    for (;;)
    {
      switch (i)
      {
      case 80: 
      default: 
        break;
      case 62: 
        localSz = ॱॱ().ॱ();
        break label24;
        return localSz;
        label94:
        i = 80;
      }
    }
    for (;;)
    {
      i = 62;
      break;
      label106:
      i = ˎ + 21;
      ˏ = i % 128;
      if (i % 2 == 0) {
        break label94;
      }
    }
  }
  
  public sp ˏ()
  {
    sp localSp;
    for (;;)
    {
      int i = 0;
      switch (i)
      {
      default: 
        break;
      case 1: 
        do
        {
          i = 1;
          break;
          for (;;)
          {
            localSp = ॱॱ().ॱ().ˋ((sV)If.ˏ).ˎ((sV)new ˊ(this)).ˋ(ur.ॱ());
            vq.ˋ(localSp, ॱ(new char[] { 11718, 11682, -8059, -6111, -32388, -16198, -22347, -8180, -21289, 16672, 10843, 25490, 12124, -15443, -21520, -7486, -22028, 17496, 11636, 25696, 10360, -14644, -20798, -6161, -21781, 18251, 12209, 26964, 1368, -13853, -24272, -5951, -22653, 19054, 8866, 27248, 9736, -13488, -23512, -4696, -24390, 19857, 9611, 28450, 8994, -12795, -22767, -4464, -24044, 20661, 14584, 28743, 15519, -11935 }).intern());
            break;
            i = null.length;
            return localSp;
          }
          i = ˏ + 47;
          ˎ = i % 128;
        } while (i % 2 != 0);
      }
    }
    return localSp;
  }
  
  static final class If<T, R>
    implements sV<T, R>
  {
    private static int ˊ;
    private static char[] ˋ;
    private static long ˎ;
    public static final If ˏ;
    private static int ॱ;
    
    static
    {
      for (;;)
      {
        int i = ˊ + 1;
        ॱ = i % 128;
        if (i % 2 == 0) {
          return;
        }
        return;
        ˊ = 0;
        ॱ = 1;
        ॱ();
        ˏ = new If();
      }
    }
    
    If() {}
    
    /* Error */
    private static String ॱ(int paramInt1, char paramChar, int paramInt2)
    {
      // Byte code:
      //   0: goto +73 -> 73
      //   3: iload 4
      //   5: tableswitch	default:+23->28, 0:+71->76, 1:+91->96
      //   28: goto +48 -> 76
      //   31: iconst_1
      //   32: istore 4
      //   34: goto -31 -> 3
      //   37: iconst_0
      //   38: istore 4
      //   40: goto -37 -> 3
      //   43: getstatic 26	o/DH$If:ॱ	I
      //   46: bipush 85
      //   48: iadd
      //   49: istore_3
      //   50: iload_3
      //   51: sipush 128
      //   54: irem
      //   55: putstatic 24	o/DH$If:ˊ	I
      //   58: iload_3
      //   59: iconst_2
      //   60: irem
      //   61: ifeq +6 -> 67
      //   64: goto +63 -> 127
      //   67: goto +74 -> 141
      //   70: goto +60 -> 130
      //   73: goto -30 -> 43
      //   76: new 40	java/lang/String
      //   79: dup
      //   80: aload 5
      //   82: invokespecial 43	java/lang/String:<init>	([C)V
      //   85: areturn
      //   86: astore 5
      //   88: aload 5
      //   90: athrow
      //   91: astore 5
      //   93: aload 5
      //   95: athrow
      //   96: aload 5
      //   98: iload_3
      //   99: getstatic 45	o/DH$If:ˋ	[C
      //   102: iload_0
      //   103: iload_3
      //   104: iadd
      //   105: caload
      //   106: i2l
      //   107: iload_3
      //   108: i2l
      //   109: getstatic 47	o/DH$If:ˎ	J
      //   112: lmul
      //   113: lxor
      //   114: iload_1
      //   115: i2l
      //   116: lxor
      //   117: l2i
      //   118: i2c
      //   119: castore
      //   120: iload_3
      //   121: iconst_1
      //   122: iadd
      //   123: istore_3
      //   124: goto +6 -> 130
      //   127: goto +14 -> 141
      //   130: iload_3
      //   131: iload_2
      //   132: if_icmpge +6 -> 138
      //   135: goto -104 -> 31
      //   138: goto -101 -> 37
      //   141: iload_2
      //   142: newarray char
      //   144: astore 5
      //   146: iconst_0
      //   147: istore_3
      //   148: getstatic 26	o/DH$If:ॱ	I
      //   151: bipush 41
      //   153: iadd
      //   154: istore 4
      //   156: iload 4
      //   158: sipush 128
      //   161: irem
      //   162: putstatic 24	o/DH$If:ˊ	I
      //   165: iload 4
      //   167: iconst_2
      //   168: irem
      //   169: ifeq +6 -> 175
      //   172: goto +6 -> 178
      //   175: goto -105 -> 70
      //   178: goto -108 -> 70
      // Local variable table:
      //   start	length	slot	name	signature
      //   0	181	0	paramInt1	int
      //   0	181	1	paramChar	char
      //   0	181	2	paramInt2	int
      //   49	99	3	i	int
      //   3	166	4	j	int
      //   80	1	5	arrayOfChar1	char[]
      //   86	3	5	localException1	Exception
      //   91	6	5	localException2	Exception
      //   144	1	5	arrayOfChar2	char[]
      // Exception table:
      //   from	to	target	type
      //   156	165	86	java/lang/Exception
      //   148	156	91	java/lang/Exception
      //   156	165	91	java/lang/Exception
    }
    
    static void ॱ()
    {
      ˎ = -6467178840070399840L;
      ˋ = new char[] { -4202, -18653, 24257, -6569, -29417, 21675, -954 };
    }
    
    public final String ˊ(Gn paramGn)
    {
      break label51;
      vq.ˎ(paramGn, ॱ(0, 61410, 7).intern());
      return paramGn.ˏ();
      for (;;)
      {
        int i;
        switch (i)
        {
        case 1: 
        default: 
          break label88;
          label51:
          do
          {
            i = 0;
            break;
            i = ˊ + 19;
            ॱ = i % 128;
          } while (i % 2 == 0);
          i = 1;
        }
      }
      label88:
      vq.ˎ(paramGn, ॱ(0, 61410, 45).intern());
      return paramGn.ˏ();
    }
  }
  
  static final class iF<T, R>
    implements sV<T, R>
  {
    private static int ʻ;
    private static int ʽ;
    private static boolean ˊ;
    private static boolean ˋ;
    private static int ˎ;
    public static final iF ˏ;
    private static char[] ॱ;
    
    static
    {
      for (;;)
      {
        int i = ʻ + 9;
        ʽ = i % 128;
        if (i % 2 != 0) {
          break;
        }
        return;
        ʽ = 0;
        ʻ = 1;
        ॱ();
        ˏ = new iF();
      }
    }
    
    iF() {}
    
    /* Error */
    private static String ˎ(byte[] paramArrayOfByte, int[] paramArrayOfInt, char[] paramArrayOfChar, int paramInt)
    {
      // Byte code:
      //   0: goto +259 -> 259
      //   3: goto +184 -> 187
      //   6: getstatic 42	o/DH$iF:ॱ	[C
      //   9: astore 9
      //   11: getstatic 44	o/DH$iF:ˎ	I
      //   14: istore 6
      //   16: getstatic 46	o/DH$iF:ˋ	Z
      //   19: istore 8
      //   21: iload 8
      //   23: ifeq +6 -> 29
      //   26: goto +271 -> 297
      //   29: goto +218 -> 247
      //   32: getstatic 26	o/DH$iF:ʻ	I
      //   35: istore 4
      //   37: iload 4
      //   39: bipush 17
      //   41: iadd
      //   42: istore 4
      //   44: iload 4
      //   46: sipush 128
      //   49: irem
      //   50: putstatic 28	o/DH$iF:ʽ	I
      //   53: iload 4
      //   55: iconst_2
      //   56: irem
      //   57: ifeq +6 -> 63
      //   60: goto +121 -> 181
      //   63: goto +219 -> 282
      //   66: astore_0
      //   67: aload_0
      //   68: athrow
      //   69: getstatic 26	o/DH$iF:ʻ	I
      //   72: bipush 13
      //   74: iadd
      //   75: istore 5
      //   77: iload 5
      //   79: sipush 128
      //   82: irem
      //   83: putstatic 28	o/DH$iF:ʽ	I
      //   86: iload 5
      //   88: iconst_2
      //   89: irem
      //   90: ifeq +6 -> 96
      //   93: goto -90 -> 3
      //   96: goto +91 -> 187
      //   99: iconst_1
      //   100: istore 5
      //   102: iload 5
      //   104: tableswitch	default:+24->128, 0:+255->359, 1:+353->457
      //   128: goto +329 -> 457
      //   131: aload_0
      //   132: arraylength
      //   133: istore 7
      //   135: iload 7
      //   137: newarray char
      //   139: astore_1
      //   140: iconst_0
      //   141: istore 4
      //   143: goto +12 -> 155
      //   146: new 48	java/lang/String
      //   149: dup
      //   150: aload_0
      //   151: invokespecial 51	java/lang/String:<init>	([C)V
      //   154: areturn
      //   155: iload 4
      //   157: iload 7
      //   159: if_icmpge +6 -> 165
      //   162: goto +107 -> 269
      //   165: goto -66 -> 99
      //   168: iload 4
      //   170: iload 5
      //   172: if_icmpge +6 -> 178
      //   175: goto +248 -> 423
      //   178: goto -32 -> 146
      //   181: goto +101 -> 282
      //   184: goto -29 -> 155
      //   187: aload_0
      //   188: iload 4
      //   190: aload 9
      //   192: aload_2
      //   193: iload 7
      //   195: iconst_1
      //   196: isub
      //   197: iload 4
      //   199: isub
      //   200: caload
      //   201: iload_3
      //   202: isub
      //   203: caload
      //   204: iload 6
      //   206: isub
      //   207: i2c
      //   208: castore
      //   209: iload 4
      //   211: iconst_1
      //   212: iadd
      //   213: istore 4
      //   215: iload 4
      //   217: iload 7
      //   219: if_icmpge +6 -> 225
      //   222: goto +40 -> 262
      //   225: goto +50 -> 275
      //   228: bipush 35
      //   230: istore 4
      //   232: goto +158 -> 390
      //   235: goto -80 -> 155
      //   238: new 48	java/lang/String
      //   241: dup
      //   242: aload_0
      //   243: invokespecial 51	java/lang/String:<init>	([C)V
      //   246: areturn
      //   247: getstatic 53	o/DH$iF:ˊ	Z
      //   250: ifeq +6 -> 256
      //   253: goto -25 -> 228
      //   256: goto +210 -> 466
      //   259: goto -253 -> 6
      //   262: bipush 86
      //   264: istore 5
      //   266: goto +61 -> 327
      //   269: iconst_0
      //   270: istore 5
      //   272: goto -170 -> 102
      //   275: bipush 24
      //   277: istore 5
      //   279: goto +48 -> 327
      //   282: aload_2
      //   283: arraylength
      //   284: istore 7
      //   286: iload 7
      //   288: newarray char
      //   290: astore_0
      //   291: iconst_0
      //   292: istore 4
      //   294: goto +194 -> 488
      //   297: getstatic 26	o/DH$iF:ʻ	I
      //   300: bipush 89
      //   302: iadd
      //   303: istore 4
      //   305: iload 4
      //   307: sipush 128
      //   310: irem
      //   311: putstatic 28	o/DH$iF:ʽ	I
      //   314: iload 4
      //   316: iconst_2
      //   317: irem
      //   318: ifeq +6 -> 324
      //   321: goto +170 -> 491
      //   324: goto -193 -> 131
      //   327: iload 5
      //   329: lookupswitch	default:+27->356, 24:+-91->238, 86:+-260->69
      //   356: goto -118 -> 238
      //   359: aload_1
      //   360: iload 4
      //   362: aload 9
      //   364: aload_0
      //   365: iload 7
      //   367: iconst_1
      //   368: isub
      //   369: iload 4
      //   371: isub
      //   372: baload
      //   373: iload_3
      //   374: iadd
      //   375: caload
      //   376: iload 6
      //   378: isub
      //   379: i2c
      //   380: castore
      //   381: iload 4
      //   383: iconst_1
      //   384: iadd
      //   385: istore 4
      //   387: goto +107 -> 494
      //   390: iload 4
      //   392: lookupswitch	default:+28->420, 35:+-360->32, 78:+81->473
      //   420: goto +53 -> 473
      //   423: aload_0
      //   424: iload 4
      //   426: aload 9
      //   428: aload_1
      //   429: iload 5
      //   431: iconst_1
      //   432: isub
      //   433: iload 4
      //   435: isub
      //   436: iaload
      //   437: iload_3
      //   438: isub
      //   439: caload
      //   440: iload 6
      //   442: isub
      //   443: i2c
      //   444: castore
      //   445: iload 4
      //   447: iconst_1
      //   448: iadd
      //   449: istore 4
      //   451: goto -283 -> 168
      //   454: astore_0
      //   455: aload_0
      //   456: athrow
      //   457: new 48	java/lang/String
      //   460: dup
      //   461: aload_1
      //   462: invokespecial 51	java/lang/String:<init>	([C)V
      //   465: areturn
      //   466: bipush 78
      //   468: istore 4
      //   470: goto -80 -> 390
      //   473: aload_1
      //   474: arraylength
      //   475: istore 5
      //   477: iload 5
      //   479: newarray char
      //   481: astore_0
      //   482: iconst_0
      //   483: istore 4
      //   485: goto -317 -> 168
      //   488: goto -273 -> 215
      //   491: goto -360 -> 131
      //   494: getstatic 28	o/DH$iF:ʽ	I
      //   497: bipush 99
      //   499: iadd
      //   500: istore 5
      //   502: iload 5
      //   504: sipush 128
      //   507: irem
      //   508: putstatic 26	o/DH$iF:ʻ	I
      //   511: iload 5
      //   513: iconst_2
      //   514: irem
      //   515: ifne +6 -> 521
      //   518: goto -283 -> 235
      //   521: goto -337 -> 184
      // Local variable table:
      //   start	length	slot	name	signature
      //   0	524	0	paramArrayOfByte	byte[]
      //   0	524	1	paramArrayOfInt	int[]
      //   0	524	2	paramArrayOfChar	char[]
      //   0	524	3	paramInt	int
      //   35	449	4	i	int
      //   75	440	5	j	int
      //   14	429	6	k	int
      //   133	236	7	m	int
      //   19	3	8	bool	boolean
      //   9	418	9	arrayOfChar	char[]
      // Exception table:
      //   from	to	target	type
      //   6	11	66	java/lang/Exception
      //   11	16	66	java/lang/Exception
      //   16	21	66	java/lang/Exception
      //   11	16	454	java/lang/Exception
      //   32	37	454	java/lang/Exception
      //   44	53	454	java/lang/Exception
    }
    
    static void ॱ()
    {
      ˋ = true;
      ˊ = true;
      ॱ = new char[] { 150, 131, 133, 119, 151, 139, 134 };
      ˎ = 34;
    }
    
    public final String ˊ(Gn paramGn)
    {
      for (;;)
      {
        int i = ʽ + 95;
        ʻ = i % 128;
        if (i % 2 != 0) {
          return paramGn;
        } else {
          return paramGn;
        }
        try
        {
          i = ʽ + 41;
          ʻ = i % 128;
          if (i % 2 == 0) {
            break label64;
          }
        }
        catch (Exception paramGn)
        {
          throw paramGn;
        }
        label64:
        vq.ˎ(paramGn, ˎ(new byte[] { -121, -122, -123, -124, -125, -126, -127 }, null, null, 127).intern());
        paramGn = paramGn.ˏ();
      }
    }
  }
  
  static final class ˊ<T, R>
    implements sV<String, sq>
  {
    private static int ˋ;
    private static char ˎ = '\003';
    private static char[] ˏ;
    private static int ॱ = 0;
    
    static
    {
      ˋ = 1;
      ˏ = new char[] { 116, 97, 99, 85, 117, 105, 100, 118, 119 };
    }
    
    ˊ(DH paramDH) {}
    
    private static String ˎ(char[] paramArrayOfChar, int paramInt, byte paramByte)
    {
      break label140;
      int i = 1;
      break label27;
      int j = 1;
      break label559;
      label14:
      j = 1;
      break label225;
      label20:
      i += 2;
      label27:
      label115:
      char[] arrayOfChar2;
      for (;;)
      {
        switch (i)
        {
        default: 
          break label397;
          j = ॱ + 23;
          ˋ = j % 128;
          if (j % 2 == 0) {
            break label703;
          }
          break label137;
          j = ˋ + 115;
          ॱ = j % 128;
          if (j % 2 != 0) {
            break label284;
          }
          break label587;
          paramInt -= 1;
          arrayOfChar2[paramInt] = ((char)(paramArrayOfChar[paramInt] - paramByte));
          break label657;
          label132:
          i = 0;
        }
      }
      label137:
      label140:
      label143:
      label212:
      label225:
      label278:
      label284:
      label287:
      label318:
      label397:
      label412:
      label422:
      label449:
      label460:
      label529:
      label559:
      label587:
      label657:
      label668:
      label674:
      label697:
      label703:
      for (;;)
      {
        break label449;
        break label422;
        int m;
        int k;
        j = oO.ˊ(m, k);
        byte b1 = oO.ˊ(b1, k);
        int n;
        j = oO.ˏ(j, n, k);
        byte b2;
        b1 = oO.ˏ(b1, b2, k);
        char[] arrayOfChar1;
        arrayOfChar2[i] = arrayOfChar1[j];
        arrayOfChar2[(i + 1)] = arrayOfChar1[b1];
        break label20;
        j = 1;
        break label287;
        if (m == b1) {
          break label14;
        }
        break label460;
        switch (j)
        {
        case 1: 
        default: 
          j = ॱ + 71;
          ˋ = j % 128;
          if (j % 2 != 0)
          {
            break;
            j = 0;
          }
          break;
        }
        for (;;)
        {
          switch (j)
          {
          default: 
            break label674;
            break;
          case 0: 
            m = oO.ॱ(b1, k);
            n = oO.ˋ(b1, k);
            b1 = oO.ॱ(b2, k);
            b2 = oO.ˋ(b2, k);
            if (n == b2) {
              break label143;
            }
            break label212;
            i = ˋ + 57;
            ॱ = i % 128;
            if (i % 2 != 0) {
              break label132;
            }
            break;
            i = j;
            break label449;
            i = j;
            for (;;)
            {
              break label20;
              return new String(arrayOfChar2);
              arrayOfChar1 = ˏ;
              k = ˎ;
              arrayOfChar2 = new char[paramInt];
              if (paramInt % 2 != 0) {
                break label115;
              }
              break label657;
              if (i < paramInt) {
                break label668;
              }
              break;
              j = 0;
              break label225;
              j = oO.ˊ(n, k);
              n = oO.ˊ(b2, k);
              j = oO.ˏ(m, j, k);
              b1 = oO.ˏ(b1, n, k);
              arrayOfChar2[i] = arrayOfChar1[j];
              arrayOfChar2[(i + 1)] = arrayOfChar1[b1];
              break label20;
              j = ॱ + 95;
              ˋ = j % 128;
              if (j % 2 == 0) {
                break label318;
              }
            }
            for (;;)
            {
              switch (j)
              {
              }
              break label412;
              b1 = paramArrayOfChar[i];
              b2 = paramArrayOfChar[(i + 1)];
              if (b1 == b2) {
                break;
              }
              break label697;
              j = oO.ˏ(m, b2, k);
              b1 = oO.ˏ(b1, n, k);
              arrayOfChar2[i] = arrayOfChar1[j];
              arrayOfChar2[(i + 1)] = arrayOfChar1[b1];
              break label529;
              if (paramInt > 1) {
                break label278;
              }
              break label412;
              j = 0;
            }
          case 1: 
            arrayOfChar2[i] = ((char)(b1 - paramByte));
            arrayOfChar2[(i + 1)] = ((char)(b2 - paramByte));
            break label20;
            j = 0;
          }
        }
      }
    }
    
    public final sp ˋ(String paramString)
    {
      for (;;)
      {
        vq.ˎ(paramString, ˎ(new char[] { 1, 2, 0, 5, 5, 3, 160 }, 7, (byte)60).intern());
        paramString = this.ˊ.ʻ().ˊ(paramString);
        int i = ॱ + 83;
        ˋ = i % 128;
        if (i % 2 == 0) {
          return paramString;
        }
        return paramString;
        i = ˋ + 119;
        ॱ = i % 128;
        if (i % 2 == 0) {}
      }
    }
  }
  
  static final class ˋ<T, R>
    implements sV<String, sq>
  {
    private static int ʽ = 1;
    private static int ˊ = 0;
    private static char[] ˋ = { 116, 97, 99, 85, 117, 105, 100, 118, 119 };
    private static char ॱ = '\003';
    
    ˋ(DH paramDH, Gr paramGr) {}
    
    /* Error */
    private static String ˏ(char[] paramArrayOfChar, int paramInt, byte paramByte)
    {
      // Byte code:
      //   0: goto +116 -> 116
      //   3: iconst_1
      //   4: istore_1
      //   5: goto +114 -> 119
      //   8: iload 6
      //   10: iload 8
      //   12: iload 5
      //   14: invokestatic 58	o/oO:ˏ	(III)I
      //   17: istore 6
      //   19: iload 4
      //   21: iload 7
      //   23: iload 5
      //   25: invokestatic 58	o/oO:ˏ	(III)I
      //   28: istore 4
      //   30: aload 11
      //   32: iload_1
      //   33: aload 10
      //   35: iload 6
      //   37: caload
      //   38: castore
      //   39: aload 11
      //   41: iload_1
      //   42: iconst_1
      //   43: iadd
      //   44: aload 10
      //   46: iload 4
      //   48: caload
      //   49: castore
      //   50: goto +523 -> 573
      //   53: iload 6
      //   55: iload 5
      //   57: invokestatic 61	o/oO:ˊ	(II)I
      //   60: istore 6
      //   62: iload 4
      //   64: iload 5
      //   66: invokestatic 61	o/oO:ˊ	(II)I
      //   69: istore 4
      //   71: iload 6
      //   73: iload 7
      //   75: iload 5
      //   77: invokestatic 58	o/oO:ˏ	(III)I
      //   80: istore 6
      //   82: iload 4
      //   84: iload 8
      //   86: iload 5
      //   88: invokestatic 58	o/oO:ˏ	(III)I
      //   91: istore 4
      //   93: aload 11
      //   95: iload_1
      //   96: aload 10
      //   98: iload 6
      //   100: caload
      //   101: castore
      //   102: aload 11
      //   104: iload_1
      //   105: iconst_1
      //   106: iadd
      //   107: aload 10
      //   109: iload 4
      //   111: caload
      //   112: castore
      //   113: goto +460 -> 573
      //   116: goto +464 -> 580
      //   119: iload_1
      //   120: iload_3
      //   121: if_icmpge +6 -> 127
      //   124: goto +36 -> 160
      //   127: goto +140 -> 267
      //   130: astore_0
      //   131: aload_0
      //   132: athrow
      //   133: getstatic 28	o/DH$ˋ:ʽ	I
      //   136: bipush 117
      //   138: iadd
      //   139: istore_1
      //   140: iload_1
      //   141: sipush 128
      //   144: irem
      //   145: putstatic 26	o/DH$ˋ:ˊ	I
      //   148: iload_1
      //   149: iconst_2
      //   150: irem
      //   151: ifeq +6 -> 157
      //   154: goto +453 -> 607
      //   157: goto +92 -> 249
      //   160: getstatic 26	o/DH$ˋ:ˊ	I
      //   163: bipush 9
      //   165: iadd
      //   166: istore 4
      //   168: iload 4
      //   170: sipush 128
      //   173: irem
      //   174: putstatic 28	o/DH$ˋ:ʽ	I
      //   177: iload 4
      //   179: iconst_2
      //   180: irem
      //   181: ifne +6 -> 187
      //   184: goto +73 -> 257
      //   187: goto +97 -> 284
      //   190: iload 7
      //   192: iload 5
      //   194: invokestatic 63	o/oO:ॱ	(II)I
      //   197: istore 6
      //   199: iload 7
      //   201: iload 5
      //   203: invokestatic 65	o/oO:ˋ	(II)I
      //   206: istore 7
      //   208: iload 8
      //   210: iload 5
      //   212: invokestatic 63	o/oO:ॱ	(II)I
      //   215: istore 4
      //   217: iload 8
      //   219: iload 5
      //   221: invokestatic 65	o/oO:ˋ	(II)I
      //   224: istore 8
      //   226: iload 7
      //   228: iload 8
      //   230: if_icmpne +6 -> 236
      //   233: goto +209 -> 442
      //   236: goto +96 -> 332
      //   239: goto -186 -> 53
      //   242: bipush 37
      //   244: istore 4
      //   246: goto +162 -> 408
      //   249: iconst_1
      //   250: istore_1
      //   251: goto +261 -> 512
      //   254: goto +319 -> 573
      //   257: goto +27 -> 284
      //   260: bipush 79
      //   262: istore 4
      //   264: goto +275 -> 539
      //   267: new 67	java/lang/String
      //   270: dup
      //   271: aload 11
      //   273: invokespecial 70	java/lang/String:<init>	([C)V
      //   276: areturn
      //   277: bipush 57
      //   279: istore 4
      //   281: goto +258 -> 539
      //   284: aload_0
      //   285: iload_1
      //   286: caload
      //   287: istore 7
      //   289: aload_0
      //   290: iload_1
      //   291: iconst_1
      //   292: iadd
      //   293: caload
      //   294: istore 8
      //   296: iload 7
      //   298: iload 8
      //   300: if_icmpne +6 -> 306
      //   303: goto -61 -> 242
      //   306: goto +166 -> 472
      //   309: aload 11
      //   311: iload_1
      //   312: iload 7
      //   314: iload_2
      //   315: isub
      //   316: i2c
      //   317: castore
      //   318: aload 11
      //   320: iload_1
      //   321: iconst_1
      //   322: iadd
      //   323: iload 8
      //   325: iload_2
      //   326: isub
      //   327: i2c
      //   328: castore
      //   329: goto +244 -> 573
      //   332: iload 6
      //   334: iload 4
      //   336: if_icmpne +6 -> 342
      //   339: goto +273 -> 612
      //   342: goto -334 -> 8
      //   345: iload 7
      //   347: iload 5
      //   349: invokestatic 61	o/oO:ˊ	(II)I
      //   352: istore 7
      //   354: iload 8
      //   356: iload 5
      //   358: invokestatic 61	o/oO:ˊ	(II)I
      //   361: istore 8
      //   363: iload 6
      //   365: iload 7
      //   367: iload 5
      //   369: invokestatic 58	o/oO:ˏ	(III)I
      //   372: istore 6
      //   374: iload 4
      //   376: iload 8
      //   378: iload 5
      //   380: invokestatic 58	o/oO:ˏ	(III)I
      //   383: istore 4
      //   385: aload 11
      //   387: iload_1
      //   388: aload 10
      //   390: iload 6
      //   392: caload
      //   393: castore
      //   394: aload 11
      //   396: iload_1
      //   397: iconst_1
      //   398: iadd
      //   399: aload 10
      //   401: iload 4
      //   403: caload
      //   404: castore
      //   405: goto -151 -> 254
      //   408: iload 4
      //   410: lookupswitch	default:+26->436, 37:+-101->309, 68:+-220->190
      //   436: goto -246 -> 190
      //   439: astore_0
      //   440: aload_0
      //   441: athrow
      //   442: getstatic 26	o/DH$ˋ:ˊ	I
      //   445: bipush 99
      //   447: iadd
      //   448: istore 9
      //   450: iload 9
      //   452: sipush 128
      //   455: irem
      //   456: putstatic 28	o/DH$ˋ:ʽ	I
      //   459: iload 9
      //   461: iconst_2
      //   462: irem
      //   463: ifne +6 -> 469
      //   466: goto -227 -> 239
      //   469: goto -416 -> 53
      //   472: bipush 68
      //   474: istore 4
      //   476: goto -68 -> 408
      //   479: iload_1
      //   480: iconst_1
      //   481: isub
      //   482: istore_3
      //   483: aload 11
      //   485: iload_3
      //   486: aload_0
      //   487: iload_3
      //   488: caload
      //   489: iload_2
      //   490: isub
      //   491: i2c
      //   492: castore
      //   493: goto +8 -> 501
      //   496: iconst_0
      //   497: istore_1
      //   498: goto -379 -> 119
      //   501: iload_3
      //   502: iconst_1
      //   503: if_icmple +6 -> 509
      //   506: goto -373 -> 133
      //   509: goto -242 -> 267
      //   512: iload_1
      //   513: tableswitch	default:+23->536, 0:+-510->3, 1:+-17->496
      //   536: goto -533 -> 3
      //   539: iload_1
      //   540: istore_3
      //   541: iload 4
      //   543: lookupswitch	default:+25->568, 57:+-42->501, 79:+-64->479
      //   568: iload_1
      //   569: istore_3
      //   570: goto -69 -> 501
      //   573: iload_1
      //   574: iconst_2
      //   575: iadd
      //   576: istore_1
      //   577: goto -458 -> 119
      //   580: getstatic 39	o/DH$ˋ:ˋ	[C
      //   583: astore 10
      //   585: getstatic 41	o/DH$ˋ:ॱ	C
      //   588: istore 5
      //   590: iload_1
      //   591: newarray char
      //   593: astore 11
      //   595: iload_1
      //   596: iconst_2
      //   597: irem
      //   598: ifeq +6 -> 604
      //   601: goto -341 -> 260
      //   604: goto -327 -> 277
      //   607: iconst_0
      //   608: istore_1
      //   609: goto -97 -> 512
      //   612: getstatic 28	o/DH$ˋ:ʽ	I
      //   615: bipush 59
      //   617: iadd
      //   618: istore 9
      //   620: iload 9
      //   622: sipush 128
      //   625: irem
      //   626: putstatic 26	o/DH$ˋ:ˊ	I
      //   629: iload 9
      //   631: iconst_2
      //   632: irem
      //   633: ifeq +6 -> 639
      //   636: goto -291 -> 345
      //   639: goto -294 -> 345
      // Local variable table:
      //   start	length	slot	name	signature
      //   0	642	0	paramArrayOfChar	char[]
      //   0	642	1	paramInt	int
      //   0	642	2	paramByte	byte
      //   120	450	3	i	int
      //   19	523	4	j	int
      //   12	577	5	k	int
      //   8	383	6	m	int
      //   21	345	7	b1	byte
      //   10	367	8	b2	byte
      //   448	185	9	n	int
      //   33	551	10	arrayOfChar1	char[]
      //   30	564	11	arrayOfChar2	char[]
      // Exception table:
      //   from	to	target	type
      //   199	208	130	java/lang/Exception
      //   190	199	439	java/lang/Exception
      //   199	208	439	java/lang/Exception
      //   208	217	439	java/lang/Exception
      //   217	226	439	java/lang/Exception
    }
    
    public final sp ˎ(String paramString)
    {
      for (;;)
      {
        try
        {
          int i = ˊ;
          i += 85;
          ʽ = i % 128;
          if (i % 2 == 0) {
            break;
          }
          continue;
          i = ˊ + 49;
          ʽ = i % 128;
          if (i % 2 != 0)
          {
            return paramString;
            vq.ˎ(paramString, ˏ(new char[] { 1, 2, 0, 5, 5, 3, 183 }, 7, (byte)83).intern());
            paramString = this.ˏ.ʻ().ˊ(paramString, paramGr);
          }
          else
          {
            return paramString;
          }
        }
        catch (Exception paramString)
        {
          throw paramString;
        }
      }
    }
  }
}
