package o;

public final class DL
  extends Iy<DK.ˋ, DF>
  implements DK.iF
{
  private static int ˋ = 0;
  private static int ˎ = 151;
  private static int ॱ = 1;
  
  @uv
  public DL(DK.ˋ paramˋ, DF paramDF)
  {
    super((Iu.if)paramˋ, (Ib)paramDF);
  }
  
  /* Error */
  private static String ˋ(int paramInt1, int paramInt2, char[] paramArrayOfChar, int paramInt3, boolean paramBoolean)
  {
    // Byte code:
    //   0: goto +159 -> 159
    //   3: aload_2
    //   4: iload_0
    //   5: aload 7
    //   7: iload_1
    //   8: iload_0
    //   9: isub
    //   10: iconst_1
    //   11: isub
    //   12: caload
    //   13: castore
    //   14: iload_0
    //   15: iconst_1
    //   16: iadd
    //   17: istore_0
    //   18: goto +376 -> 394
    //   21: goto +88 -> 109
    //   24: bipush 79
    //   26: istore_3
    //   27: goto +288 -> 315
    //   30: goto +79 -> 109
    //   33: iconst_0
    //   34: istore_0
    //   35: goto +127 -> 162
    //   38: goto +31 -> 69
    //   41: bipush 37
    //   43: istore_0
    //   44: goto +86 -> 130
    //   47: aload_2
    //   48: iload_0
    //   49: aload 7
    //   51: iload_1
    //   52: iload_0
    //   53: ishr
    //   54: iconst_1
    //   55: irem
    //   56: caload
    //   57: castore
    //   58: iload_0
    //   59: bipush 25
    //   61: iadd
    //   62: istore_0
    //   63: goto +331 -> 394
    //   66: astore_2
    //   67: aload_2
    //   68: athrow
    //   69: aload 7
    //   71: iload 5
    //   73: iload_0
    //   74: aload_2
    //   75: iload 5
    //   77: caload
    //   78: iadd
    //   79: i2c
    //   80: castore
    //   81: aload 7
    //   83: iload 5
    //   85: caload
    //   86: istore 6
    //   88: aload 7
    //   90: iload 5
    //   92: iload 6
    //   94: getstatic 33	o/DL:ˎ	I
    //   97: isub
    //   98: i2c
    //   99: castore
    //   100: iload 5
    //   102: iconst_1
    //   103: iadd
    //   104: istore 5
    //   106: goto +179 -> 285
    //   109: iload 5
    //   111: iload_1
    //   112: if_icmpge +6 -> 118
    //   115: goto +120 -> 235
    //   118: goto +298 -> 416
    //   121: new 46	java/lang/String
    //   124: dup
    //   125: aload_2
    //   126: invokespecial 75	java/lang/String:<init>	([C)V
    //   129: areturn
    //   130: iload_0
    //   131: lookupswitch	default:+25->156, 37:+66->197, 75:+77->208
    //   156: goto +52 -> 208
    //   159: goto +246 -> 405
    //   162: aload 7
    //   164: astore_2
    //   165: iload_0
    //   166: tableswitch	default:+22->188, 0:+222->388, 1:+-45->121
    //   188: aload 7
    //   190: astore_2
    //   191: goto -70 -> 121
    //   194: goto +153 -> 347
    //   197: iload 4
    //   199: ifeq +6 -> 205
    //   202: goto -169 -> 33
    //   205: goto +75 -> 280
    //   208: getstatic 29	o/DL:ˋ	I
    //   211: bipush 107
    //   213: iadd
    //   214: istore_0
    //   215: iload_0
    //   216: sipush 128
    //   219: irem
    //   220: putstatic 31	o/DL:ॱ	I
    //   223: iload_0
    //   224: iconst_2
    //   225: irem
    //   226: ifne +6 -> 232
    //   229: goto -35 -> 194
    //   232: goto +115 -> 347
    //   235: getstatic 29	o/DL:ˋ	I
    //   238: bipush 21
    //   240: iadd
    //   241: istore 6
    //   243: iload 6
    //   245: sipush 128
    //   248: irem
    //   249: putstatic 31	o/DL:ॱ	I
    //   252: iload 6
    //   254: iconst_2
    //   255: irem
    //   256: ifne +6 -> 262
    //   259: goto -221 -> 38
    //   262: goto -193 -> 69
    //   265: bipush 50
    //   267: istore_3
    //   268: goto +47 -> 315
    //   271: goto -250 -> 21
    //   274: bipush 75
    //   276: istore_0
    //   277: goto -147 -> 130
    //   280: iconst_1
    //   281: istore_0
    //   282: goto -120 -> 162
    //   285: getstatic 31	o/DL:ॱ	I
    //   288: bipush 77
    //   290: iadd
    //   291: istore 6
    //   293: iload 6
    //   295: sipush 128
    //   298: irem
    //   299: putstatic 29	o/DL:ˋ	I
    //   302: iload 6
    //   304: iconst_2
    //   305: irem
    //   306: ifeq +6 -> 312
    //   309: goto -38 -> 271
    //   312: goto -291 -> 21
    //   315: iload_3
    //   316: lookupswitch	default:+28->344, 50:+110->426, 79:+69->385
    //   344: goto +41 -> 385
    //   347: iload_1
    //   348: newarray char
    //   350: astore_2
    //   351: aload 7
    //   353: iconst_0
    //   354: aload_2
    //   355: iconst_0
    //   356: iload_1
    //   357: invokestatic 81	java/lang/System:arraycopy	(Ljava/lang/Object;ILjava/lang/Object;II)V
    //   360: aload_2
    //   361: iconst_0
    //   362: aload 7
    //   364: iload_1
    //   365: iload_3
    //   366: isub
    //   367: iload_3
    //   368: invokestatic 81	java/lang/System:arraycopy	(Ljava/lang/Object;ILjava/lang/Object;II)V
    //   371: aload_2
    //   372: iload_3
    //   373: aload 7
    //   375: iconst_0
    //   376: iload_1
    //   377: iload_3
    //   378: isub
    //   379: invokestatic 81	java/lang/System:arraycopy	(Ljava/lang/Object;ILjava/lang/Object;II)V
    //   382: goto -185 -> 197
    //   385: goto -264 -> 121
    //   388: iload_1
    //   389: newarray char
    //   391: astore_2
    //   392: iconst_0
    //   393: istore_0
    //   394: iload_0
    //   395: iload_1
    //   396: if_icmpge +6 -> 402
    //   399: goto -134 -> 265
    //   402: goto -378 -> 24
    //   405: iload_1
    //   406: newarray char
    //   408: astore 7
    //   410: iconst_0
    //   411: istore 5
    //   413: goto -383 -> 30
    //   416: iload_3
    //   417: ifle +6 -> 423
    //   420: goto -146 -> 274
    //   423: goto -382 -> 41
    //   426: getstatic 29	o/DL:ˋ	I
    //   429: bipush 101
    //   431: iadd
    //   432: istore_3
    //   433: iload_3
    //   434: sipush 128
    //   437: irem
    //   438: putstatic 31	o/DL:ॱ	I
    //   441: iload_3
    //   442: iconst_2
    //   443: irem
    //   444: ifne +6 -> 450
    //   447: goto -400 -> 47
    //   450: goto -447 -> 3
    // Local variable table:
    //   start	length	slot	name	signature
    //   0	453	0	paramInt1	int
    //   0	453	1	paramInt2	int
    //   0	453	2	paramArrayOfChar	char[]
    //   0	453	3	paramInt3	int
    //   0	453	4	paramBoolean	boolean
    //   71	341	5	i	int
    //   86	220	6	j	int
    //   5	404	7	localObject	Object
    // Exception table:
    //   from	to	target	type
    //   88	100	66	java/lang/Exception
    //   208	215	66	java/lang/Exception
    //   215	223	66	java/lang/Exception
  }
  
  public void ˊ()
  {
    for (;;)
    {
      int i = ॱ + 123;
      ˋ = i % 128;
      if (i % 2 == 0) {
        return;
      }
      return;
      ((DF)ʼ()).ˏ().ॱ(sB.ˋ()).ॱ((sW)new if(this)).ˋ((sR)new iF(this), (sW)new ˋ(this));
    }
  }
  
  public void ˋ(final String paramString)
  {
    break label8;
    int i = 0;
    break label264;
    label8:
    break label55;
    if (Gv.ˊ.ˎ().ˏॱ() == null)
    {
      return;
      label27:
      return;
    }
    for (;;)
    {
      i = ˋ + 89;
      ॱ = i % 128;
      if (i % 2 != 0)
      {
        break label190;
        label55:
        vq.ˎ(paramString, ˋ(253, 12, new char[] { -2, -2, -37, 6, 3, -5, 7, -1, 13, 13, -1, 12 }, 8, true).intern());
        if (aq.ˏ((CharSequence)paramString)) {
          break;
        }
        i = 1;
        break label264;
      }
      for (;;)
      {
        i = ˋ + 47;
        ॱ = i % 128;
        if (i % 2 == 0) {
          return;
        }
        return;
        label190:
        ((DK.ˋ)ʽ()).ʾ();
      }
      ((DF)ʼ()).ˎ(new Gr(paramString)).ॱ(sB.ˋ()).ॱ((sW)new aux(this)).ॱ((sR)new ᐝ(this, paramString));
      break label27;
      label264:
      switch (i)
      {
      }
    }
  }
  
  public void ˏ()
  {
    for (int i = 72;; i = 36) {
      switch (i)
      {
      default: 
        break label145;
        try
        {
          for (;;)
          {
            i = ˋ + 75;
            try
            {
              ॱ = i % 128;
              if (i % 2 == 0) {
                break;
              }
            }
            catch (Exception localException1)
            {
              throw localException1;
            }
            ((DK.ˋ)ʽ()).ॱˎ();
          }
          i = ॱ + 5;
          ˋ = i % 128;
          if (i % 2 != 0) {
            break label151;
          }
        }
        catch (Exception localException2)
        {
          throw localException2;
        }
      }
    }
    for (;;)
    {
      Object localObject = ʽ();
      localObject = (DK.ˋ)localObject;
      ((DK.ˋ)localObject).ॱˎ();
      i = null.length;
      break;
      i = 0;
      break label153;
      label145:
      i = 50 / 0;
      return;
      label151:
      i = 1;
      label153:
      switch (i)
      {
      }
    }
  }
  
  public void ॱ()
  {
    break label59;
    int i = ˋ + 77;
    ॱ = i % 128;
    if (i % 2 != 0) {
      break label108;
    }
    for (;;)
    {
      switch (i)
      {
      default: 
        break;
      case 48: 
        return;
        ((DF)ʼ()).ˎ().ˋ((sV)If.ˏ).ˋ(sB.ˋ()).ॱ((sW)new ˊ(this));
        break;
        i = 48;
        break;
      case 55: 
        label59:
        label108:
        i = null.length;
        return;
        i = 55;
      }
    }
  }
  
  static final class If<T, R>
    implements sV<T, R>
  {
    private static int ˋ;
    private static int ˎ;
    public static final If ˏ;
    private static int ॱ;
    
    /* Error */
    static
    {
      // Byte code:
      //   0: goto +7 -> 7
      //   3: astore_1
      //   4: aload_1
      //   5: athrow
      //   6: return
      //   7: iconst_0
      //   8: putstatic 22	o/DL$If:ॱ	I
      //   11: iconst_1
      //   12: putstatic 24	o/DL$If:ˎ	I
      //   15: invokestatic 26	o/DL$If:ˋ	()V
      //   18: new 2	o/DL$If
      //   21: dup
      //   22: invokespecial 29	o/DL$If:<init>	()V
      //   25: putstatic 31	o/DL$If:ˏ	Lo/DL$If;
      //   28: goto +11 -> 39
      //   31: astore_1
      //   32: aload_1
      //   33: athrow
      //   34: iconst_0
      //   35: istore_0
      //   36: goto +31 -> 67
      //   39: getstatic 24	o/DL$If:ˎ	I
      //   42: istore_0
      //   43: iload_0
      //   44: bipush 93
      //   46: iadd
      //   47: istore_0
      //   48: iload_0
      //   49: sipush 128
      //   52: irem
      //   53: putstatic 22	o/DL$If:ॱ	I
      //   56: iload_0
      //   57: iconst_2
      //   58: irem
      //   59: ifeq +6 -> 65
      //   62: goto -28 -> 34
      //   65: iconst_1
      //   66: istore_0
      //   67: iload_0
      //   68: tableswitch	default:+24->92, 0:+24->92, 1:+-62->6
      //   92: bipush 58
      //   94: iconst_0
      //   95: idiv
      //   96: istore_0
      //   97: return
      // Local variable table:
      //   start	length	slot	name	signature
      //   35	62	0	i	int
      //   3	2	1	localException1	Exception
      //   31	2	1	localException2	Exception
      // Exception table:
      //   from	to	target	type
      //   39	43	3	java/lang/Exception
      //   48	56	31	java/lang/Exception
    }
    
    If() {}
    
    private static String ˋ(int paramInt1, int paramInt2, char[] paramArrayOfChar, int paramInt3, boolean paramBoolean)
    {
      break label249;
      label31:
      char[] arrayOfChar;
      int i;
      switch (paramInt1)
      {
      default: 
        break label328;
        arrayOfChar[i] = ((char)(paramInt1 + paramArrayOfChar[i]));
        arrayOfChar[i] = ((char)(arrayOfChar[i] - ˋ));
        i += 1;
        break label266;
        for (;;)
        {
          label67:
          paramArrayOfChar = new char[paramInt2];
          paramInt1 = 0;
          break label366;
          paramInt1 = ˎ + 17;
          ॱ = paramInt1 % 128;
          if (paramInt1 % 2 != 0) {
            break;
          }
        }
        paramInt1 = ॱ + 111;
        ˎ = paramInt1 % 128;
        if (paramInt1 % 2 != 0)
        {
          break label278;
          paramInt1 = 3 / 2;
        }
        break;
      }
      for (;;)
      {
        label137:
        paramArrayOfChar = arrayOfChar;
        switch (paramInt1)
        {
        case 75: 
        default: 
          paramArrayOfChar = arrayOfChar;
          break label382;
          label174:
          paramArrayOfChar[paramInt1] = arrayOfChar[(paramInt2 % paramInt1 * 1)];
          paramInt1 += 6;
          break;
          label193:
          if (paramInt3 <= 0)
          {
            break label241;
            label203:
            switch (paramInt1)
            {
            }
          }
          break;
        }
        for (;;)
        {
          break label366;
          break label284;
          label241:
          paramInt1 = 0;
          break;
          break label67;
          label249:
          arrayOfChar = new char[paramInt2];
          i = 0;
          break label266;
          paramInt1 = 30;
          break label203;
          label266:
          if (i < paramInt2) {
            break label31;
          }
          break label193;
          label278:
          paramInt1 = 62;
          break label203;
          label284:
          if (paramBoolean) {
            break label409;
          }
          label328:
          label366:
          while (paramInt1 < paramInt2)
          {
            paramInt3 = ˎ + 107;
            ॱ = paramInt3 % 128;
            if (paramInt3 % 2 != 0) {
              break label174;
            }
            break label391;
            paramInt1 = 53;
            break label137;
            paramArrayOfChar = new char[paramInt2];
            System.arraycopy(arrayOfChar, 0, paramArrayOfChar, 0, paramInt2);
            System.arraycopy(paramArrayOfChar, 0, arrayOfChar, paramInt2 - paramInt3, paramInt3);
            System.arraycopy(paramArrayOfChar, paramInt3, arrayOfChar, 0, paramInt2 - paramInt3);
            break;
          }
          break label382;
          paramInt1 = 1;
          break;
          label382:
          return new String(paramArrayOfChar);
          label391:
          paramArrayOfChar[paramInt1] = arrayOfChar[(paramInt2 - paramInt1 - 1)];
          paramInt1 += 1;
        }
        label409:
        paramInt1 = 75;
      }
    }
    
    static void ˋ()
    {
      ˋ = 18;
    }
    
    public final DE ˎ(Gn paramGn)
    {
      for (;;)
      {
        vq.ˎ(paramGn, ˋ(122, 3, new char[] { -5, 12, -7 }, 1, false).intern());
        paramGn = paramGn.terms;
        vq.ˋ(paramGn, ˋ(119, 9, new char[] { 13, 0, 15, -55, -2, -4, 15, 14, 8 }, 7, true).intern());
        paramGn = new DE(paramGn);
        break;
      }
      int i = ˎ + 17;
      ॱ = i % 128;
      if (i % 2 != 0) {
        return paramGn;
      }
      return paramGn;
    }
  }
  
  static final class aux<T>
    implements sW<sH>
  {
    aux(DL paramDL) {}
    
    public final void ˊ(sH paramSH)
    {
      DL.ˏ(this.ˋ).ʼॱ();
    }
  }
  
  static final class iF
    implements sR
  {
    iF(DL paramDL) {}
    
    public final void ॱ()
    {
      DL.ॱ(this.ˏ).ॱ().ˊ(true);
      DL.ˏ(this.ˏ).ʽॱ();
    }
  }
  
  static final class if<T>
    implements sW<sH>
  {
    if(DL paramDL) {}
    
    public final void ˋ(sH paramSH)
    {
      DL.ˏ(this.ˎ).ˈ();
    }
  }
  
  static final class ˊ<T>
    implements sW<DE>
  {
    private static char ˊ = '\003';
    private static int ˋ = 0;
    private static char[] ˎ;
    private static int ˏ = 1;
    
    static
    {
      ˎ = new char[] { 116, 97, 99, 77, 111, 100, 101, 108, 117 };
    }
    
    ˊ(DL paramDL) {}
    
    /* Error */
    private static String ˊ(char[] paramArrayOfChar, int paramInt, byte paramByte)
    {
      // Byte code:
      //   0: goto +403 -> 403
      //   3: getstatic 23	o/DL$ˊ:ˋ	I
      //   6: bipush 109
      //   8: iadd
      //   9: istore_3
      //   10: iload_3
      //   11: sipush 128
      //   14: irem
      //   15: putstatic 25	o/DL$ˊ:ˏ	I
      //   18: iload_3
      //   19: iconst_2
      //   20: irem
      //   21: ifne +6 -> 27
      //   24: goto +237 -> 261
      //   27: goto +81 -> 108
      //   30: new 50	java/lang/String
      //   33: dup
      //   34: aload 13
      //   36: invokespecial 53	java/lang/String:<init>	([C)V
      //   39: areturn
      //   40: iload 7
      //   42: iload_1
      //   43: invokestatic 58	o/oO:ˊ	(II)I
      //   46: istore 4
      //   48: iload 8
      //   50: iload_1
      //   51: invokestatic 58	o/oO:ˊ	(II)I
      //   54: istore 7
      //   56: iload 6
      //   58: iload 4
      //   60: iload_1
      //   61: invokestatic 61	o/oO:ˏ	(III)I
      //   64: istore 4
      //   66: iload 5
      //   68: iload 7
      //   70: iload_1
      //   71: invokestatic 61	o/oO:ˏ	(III)I
      //   74: istore 5
      //   76: aload 13
      //   78: iload_2
      //   79: aload 12
      //   81: iload 4
      //   83: caload
      //   84: castore
      //   85: aload 13
      //   87: iload_2
      //   88: iconst_1
      //   89: iadd
      //   90: aload 12
      //   92: iload 5
      //   94: caload
      //   95: castore
      //   96: goto +349 -> 445
      //   99: goto +76 -> 175
      //   102: iconst_2
      //   103: istore 4
      //   105: goto +38 -> 143
      //   108: getstatic 36	o/DL$ˊ:ˎ	[C
      //   111: astore 12
      //   113: iload_1
      //   114: istore_3
      //   115: getstatic 38	o/DL$ˊ:ˊ	C
      //   118: istore 4
      //   120: iload_3
      //   121: newarray char
      //   123: astore 13
      //   125: iload_3
      //   126: iconst_2
      //   127: irem
      //   128: ifeq +9 -> 137
      //   131: iload 4
      //   133: istore_3
      //   134: goto +52 -> 186
      //   137: iload 4
      //   139: istore_1
      //   140: goto +291 -> 431
      //   143: iload 4
      //   145: lookupswitch	default:+27->172, 2:+151->296, 58:+514->659
      //   172: goto +124 -> 296
      //   175: iload_2
      //   176: iload_3
      //   177: if_icmpge +6 -> 183
      //   180: goto +51 -> 231
      //   183: goto -153 -> 30
      //   186: iload_1
      //   187: iconst_1
      //   188: isub
      //   189: istore 4
      //   191: aload 13
      //   193: iload 4
      //   195: aload_0
      //   196: iload 4
      //   198: caload
      //   199: iload_2
      //   200: isub
      //   201: i2c
      //   202: castore
      //   203: iload_3
      //   204: istore_1
      //   205: iload 4
      //   207: istore_3
      //   208: goto +223 -> 431
      //   211: astore_0
      //   212: aload_0
      //   213: athrow
      //   214: goto -39 -> 175
      //   217: bipush 51
      //   219: istore 10
      //   221: goto +382 -> 603
      //   224: bipush 39
      //   226: istore 10
      //   228: goto +375 -> 603
      //   231: getstatic 25	o/DL$ˊ:ˏ	I
      //   234: bipush 39
      //   236: iadd
      //   237: istore 4
      //   239: iload 4
      //   241: sipush 128
      //   244: irem
      //   245: putstatic 23	o/DL$ˊ:ˋ	I
      //   248: iload 4
      //   250: iconst_2
      //   251: irem
      //   252: ifeq +6 -> 258
      //   255: goto +290 -> 545
      //   258: goto +254 -> 512
      //   261: getstatic 36	o/DL$ˊ:ˎ	[C
      //   264: astore 12
      //   266: iload_1
      //   267: istore_3
      //   268: getstatic 38	o/DL$ˊ:ˊ	C
      //   271: istore 4
      //   273: iload_3
      //   274: newarray char
      //   276: astore 13
      //   278: iload_3
      //   279: iconst_2
      //   280: irem
      //   281: ifeq +9 -> 290
      //   284: iload 4
      //   286: istore_3
      //   287: goto -101 -> 186
      //   290: iload 4
      //   292: istore_1
      //   293: goto +138 -> 431
      //   296: iload 6
      //   298: iload 8
      //   300: iload_1
      //   301: invokestatic 61	o/oO:ˏ	(III)I
      //   304: istore 4
      //   306: iload 5
      //   308: iload 7
      //   310: iload_1
      //   311: invokestatic 61	o/oO:ˏ	(III)I
      //   314: istore 5
      //   316: aload 13
      //   318: iload_2
      //   319: aload 12
      //   321: iload 4
      //   323: caload
      //   324: castore
      //   325: aload 13
      //   327: iload_2
      //   328: iconst_1
      //   329: iadd
      //   330: aload 12
      //   332: iload 5
      //   334: caload
      //   335: castore
      //   336: goto +109 -> 445
      //   339: iconst_0
      //   340: istore_2
      //   341: goto +229 -> 570
      //   344: iload 6
      //   346: iload_1
      //   347: invokestatic 58	o/oO:ˊ	(II)I
      //   350: istore 4
      //   352: iload 5
      //   354: iload_1
      //   355: invokestatic 58	o/oO:ˊ	(II)I
      //   358: istore 5
      //   360: iload 4
      //   362: iload 7
      //   364: iload_1
      //   365: invokestatic 61	o/oO:ˏ	(III)I
      //   368: istore 4
      //   370: iload 5
      //   372: iload 8
      //   374: iload_1
      //   375: invokestatic 61	o/oO:ˏ	(III)I
      //   378: istore 5
      //   380: aload 13
      //   382: iload_2
      //   383: aload 12
      //   385: iload 4
      //   387: caload
      //   388: castore
      //   389: aload 13
      //   391: iload_2
      //   392: iconst_1
      //   393: iadd
      //   394: aload 12
      //   396: iload 5
      //   398: caload
      //   399: castore
      //   400: goto +45 -> 445
      //   403: goto -400 -> 3
      //   406: aload 13
      //   408: iload_2
      //   409: iload 8
      //   411: iload 11
      //   413: isub
      //   414: i2c
      //   415: castore
      //   416: aload 13
      //   418: iload_2
      //   419: iconst_1
      //   420: iadd
      //   421: iload 9
      //   423: iload 11
      //   425: isub
      //   426: i2c
      //   427: castore
      //   428: goto +17 -> 445
      //   431: iload_2
      //   432: istore 11
      //   434: iload_3
      //   435: iconst_1
      //   436: if_icmple +6 -> 442
      //   439: goto -100 -> 339
      //   442: goto +156 -> 598
      //   445: iload_2
      //   446: iconst_2
      //   447: iadd
      //   448: istore_2
      //   449: goto -235 -> 214
      //   452: getstatic 23	o/DL$ˊ:ˋ	I
      //   455: bipush 109
      //   457: iadd
      //   458: istore 4
      //   460: iload 4
      //   462: sipush 128
      //   465: irem
      //   466: putstatic 25	o/DL$ˊ:ˏ	I
      //   469: iload 4
      //   471: iconst_2
      //   472: irem
      //   473: ifne +6 -> 479
      //   476: goto +286 -> 762
      //   479: goto -380 -> 99
      //   482: goto +207 -> 689
      //   485: getstatic 25	o/DL$ˊ:ˏ	I
      //   488: bipush 93
      //   490: iadd
      //   491: istore_2
      //   492: iload_2
      //   493: sipush 128
      //   496: irem
      //   497: putstatic 23	o/DL$ˊ:ˋ	I
      //   500: iload_2
      //   501: iconst_2
      //   502: irem
      //   503: ifeq +6 -> 509
      //   506: goto -24 -> 482
      //   509: goto +180 -> 689
      //   512: aload_0
      //   513: iload_2
      //   514: caload
      //   515: istore 7
      //   517: aload_0
      //   518: iload_2
      //   519: iconst_1
      //   520: iadd
      //   521: caload
      //   522: istore 4
      //   524: iload 7
      //   526: iload 4
      //   528: if_icmpne +14 -> 542
      //   531: iload 7
      //   533: istore 8
      //   535: iload 4
      //   537: istore 9
      //   539: goto -133 -> 406
      //   542: goto +168 -> 710
      //   545: aload_0
      //   546: iload_2
      //   547: caload
      //   548: istore 5
      //   550: aload_0
      //   551: iload_2
      //   552: iconst_0
      //   553: ishl
      //   554: caload
      //   555: istore 6
      //   557: iload 5
      //   559: iload 6
      //   561: if_icmpne +6 -> 567
      //   564: goto -347 -> 217
      //   567: goto -343 -> 224
      //   570: iload_2
      //   571: tableswitch	default:+21->592, 0:+-86->485, 1:+-541->30
      //   592: goto -562 -> 30
      //   595: astore_0
      //   596: aload_0
      //   597: athrow
      //   598: iconst_1
      //   599: istore_2
      //   600: goto -30 -> 570
      //   603: iload 5
      //   605: istore 8
      //   607: iload 6
      //   609: istore 9
      //   611: iload 5
      //   613: istore 7
      //   615: iload 6
      //   617: istore 4
      //   619: iload 10
      //   621: lookupswitch	default:+27->648, 39:+89->710, 51:+-215->406
      //   648: iload 5
      //   650: istore 8
      //   652: iload 6
      //   654: istore 9
      //   656: goto -250 -> 406
      //   659: getstatic 25	o/DL$ˊ:ˏ	I
      //   662: bipush 43
      //   664: iadd
      //   665: istore 4
      //   667: iload 4
      //   669: sipush 128
      //   672: irem
      //   673: putstatic 23	o/DL$ˊ:ˋ	I
      //   676: iload 4
      //   678: iconst_2
      //   679: irem
      //   680: ifeq +6 -> 686
      //   683: goto +11 -> 694
      //   686: goto -646 -> 40
      //   689: iconst_0
      //   690: istore_2
      //   691: goto -239 -> 452
      //   694: goto -654 -> 40
      //   697: iload 6
      //   699: iload 5
      //   701: if_icmpne +6 -> 707
      //   704: goto +51 -> 755
      //   707: goto -605 -> 102
      //   710: iload 7
      //   712: iload_1
      //   713: invokestatic 63	o/oO:ॱ	(II)I
      //   716: istore 6
      //   718: iload 7
      //   720: iload_1
      //   721: invokestatic 65	o/oO:ˋ	(II)I
      //   724: istore 7
      //   726: iload 4
      //   728: iload_1
      //   729: invokestatic 63	o/oO:ॱ	(II)I
      //   732: istore 5
      //   734: iload 4
      //   736: iload_1
      //   737: invokestatic 65	o/oO:ˋ	(II)I
      //   740: istore 8
      //   742: iload 7
      //   744: iload 8
      //   746: if_icmpne +6 -> 752
      //   749: goto -405 -> 344
      //   752: goto -55 -> 697
      //   755: bipush 58
      //   757: istore 4
      //   759: goto -616 -> 143
      //   762: goto -663 -> 99
      // Local variable table:
      //   start	length	slot	name	signature
      //   0	765	0	paramArrayOfChar	char[]
      //   0	765	1	paramInt	int
      //   0	765	2	paramByte	byte
      //   9	428	3	b1	byte
      //   46	712	4	b2	byte
      //   66	667	5	i	int
      //   56	661	6	b3	byte
      //   40	707	7	j	int
      //   48	699	8	k	int
      //   421	234	9	m	int
      //   219	401	10	n	int
      //   411	22	11	i1	int
      //   79	316	12	arrayOfChar1	char[]
      //   34	383	13	arrayOfChar2	char[]
      // Exception table:
      //   from	to	target	type
      //   306	316	211	java/lang/Exception
      //   296	306	595	java/lang/Exception
      //   306	316	595	java/lang/Exception
    }
    
    public final void ˋ(DE paramDE)
    {
      for (;;)
      {
        int i = ˋ + 39;
        ˏ = i % 128;
        if (i % 2 != 0) {
          break label65;
        }
        for (;;)
        {
          switch (i)
          {
          default: 
            break label150;
            i = 22;
            continue;
            label65:
            i = 83;
          }
        }
        localˋ = DL.ˏ(this.ॱ);
        vq.ˋ(paramDE, ˊ(new char[] { 1, 2, 0, 5, 5, 3, 7, 8 }, 8, (byte)73).intern());
        localˋ.ॱ(paramDE);
        return;
      }
      label150:
      DK.ˋ localˋ = DL.ˏ(this.ॱ);
      vq.ˋ(paramDE, ˊ(new char[] { 1, 2, 0, 5, 5, 3, 7, 8 }, 126, (byte)1).intern());
      localˋ.ॱ(paramDE);
    }
  }
  
  static final class ˋ<T>
    implements sW<Throwable>
  {
    ˋ(DL paramDL) {}
    
    public final void ˋ(Throwable paramThrowable)
    {
      DL.ˏ(this.ˊ).ʿ();
    }
  }
  
  static final class ᐝ
    implements sR
  {
    ᐝ(DL paramDL, String paramString) {}
    
    public final void ॱ()
    {
      DL.ˏ(this.ॱ).ˋ(paramString);
    }
  }
}
