package o;

public class DN
  extends K<DB>
{
  private static int ʻ;
  private static int ˊ = 0;
  private static char ˋ;
  private static int ˎ = 0;
  private static long ॱ;
  
  static
  {
    ʻ = 1;
    ˋ = '\000';
    ॱ = -3768630245144571507L;
  }
  
  public DN() {}
  
  private static String ˊ(char[] paramArrayOfChar1, char paramChar, char[] paramArrayOfChar2, int paramInt, char[] paramArrayOfChar3)
  {
    break label196;
    label6:
    char c;
    for (;;)
    {
      break;
      c = ʻ + 49;
      ˊ = c % '';
      if (c % '\002' == 0)
      {
        break;
        break label238;
      }
    }
    label196:
    label238:
    label247:
    for (;;)
    {
      try
      {
        paramArrayOfChar1 = paramArrayOfChar1.clone();
        try
        {
          paramArrayOfChar1 = (char[])paramArrayOfChar1;
          paramArrayOfChar3 = paramArrayOfChar3.clone();
          paramArrayOfChar3 = (char[])paramArrayOfChar3;
          paramArrayOfChar1[0] = ((char)(paramArrayOfChar1[0] ^ paramChar));
          paramArrayOfChar3[2] = ((char)(paramArrayOfChar3[2] + (char)paramInt));
          c = paramArrayOfChar2.length;
          char[] arrayOfChar = new char[c];
          paramChar = '\000';
          continue;
          paramInt = 8;
          continue;
          return new String(arrayOfChar);
          switch (paramInt)
          {
          case 44: 
          default: 
            continue;
            break;
          case 8: 
            oJ.ˏ(paramArrayOfChar1, paramArrayOfChar3, paramChar);
            arrayOfChar[paramChar] = ((char)(int)(paramArrayOfChar2[paramChar] ^ paramArrayOfChar1[((paramChar + '\003') % 4)] ^ ॱ ^ ˎ ^ ˋ));
            paramChar += '\001';
            break;
            break label6;
            paramInt = 44;
            break;
          }
          paramInt = ʻ + 63;
          ˊ = paramInt % 128;
          if (paramInt % 2 != 0) {
            continue;
          }
        }
        catch (Exception paramArrayOfChar1)
        {
          throw paramArrayOfChar1;
        }
        if (paramChar >= c) {
          break label247;
        }
      }
      catch (Exception paramArrayOfChar1)
      {
        throw paramArrayOfChar1;
      }
    }
  }
  
  /* Error */
  private void ˋ()
  {
    // Byte code:
    //   0: goto +32 -> 32
    //   3: getstatic 19	o/DN:ʻ	I
    //   6: bipush 89
    //   8: iadd
    //   9: istore_1
    //   10: iload_1
    //   11: sipush 128
    //   14: irem
    //   15: putstatic 17	o/DN:ˊ	I
    //   18: iload_1
    //   19: iconst_2
    //   20: irem
    //   21: ifeq +6 -> 27
    //   24: goto +7 -> 31
    //   27: return
    //   28: astore_2
    //   29: aload_2
    //   30: athrow
    //   31: return
    //   32: aload_0
    //   33: getfield 54	o/DN:ˏ	Landroid/databinding/ViewDataBinding;
    //   36: astore_2
    //   37: aload_2
    //   38: checkcast 56	o/DB
    //   41: astore_2
    //   42: aload_2
    //   43: getfield 59	o/DB:ॱ	Landroid/widget/ImageView;
    //   46: astore_2
    //   47: aload_2
    //   48: iconst_4
    //   49: newarray char
    //   51: dup
    //   52: iconst_0
    //   53: ldc 60
    //   55: castore
    //   56: dup
    //   57: iconst_1
    //   58: ldc 61
    //   60: castore
    //   61: dup
    //   62: iconst_2
    //   63: ldc 62
    //   65: castore
    //   66: dup
    //   67: iconst_3
    //   68: ldc 63
    //   70: castore
    //   71: iconst_0
    //   72: bipush 12
    //   74: newarray char
    //   76: dup
    //   77: iconst_0
    //   78: ldc 64
    //   80: castore
    //   81: dup
    //   82: iconst_1
    //   83: ldc 65
    //   85: castore
    //   86: dup
    //   87: iconst_2
    //   88: ldc 66
    //   90: castore
    //   91: dup
    //   92: iconst_3
    //   93: ldc 67
    //   95: castore
    //   96: dup
    //   97: iconst_4
    //   98: ldc 68
    //   100: castore
    //   101: dup
    //   102: iconst_5
    //   103: ldc 69
    //   105: castore
    //   106: dup
    //   107: bipush 6
    //   109: ldc 70
    //   111: castore
    //   112: dup
    //   113: bipush 7
    //   115: ldc 71
    //   117: castore
    //   118: dup
    //   119: bipush 8
    //   121: ldc 72
    //   123: castore
    //   124: dup
    //   125: bipush 9
    //   127: ldc 73
    //   129: castore
    //   130: dup
    //   131: bipush 10
    //   133: ldc 74
    //   135: castore
    //   136: dup
    //   137: bipush 11
    //   139: ldc 75
    //   141: castore
    //   142: iconst_0
    //   143: iconst_4
    //   144: newarray char
    //   146: dup
    //   147: iconst_0
    //   148: ldc 76
    //   150: castore
    //   151: dup
    //   152: iconst_1
    //   153: ldc 77
    //   155: castore
    //   156: dup
    //   157: iconst_2
    //   158: ldc 78
    //   160: castore
    //   161: dup
    //   162: iconst_3
    //   163: ldc 79
    //   165: castore
    //   166: invokestatic 81	o/DN:ˊ	([CC[CI[C)Ljava/lang/String;
    //   169: invokevirtual 85	java/lang/String:intern	()Ljava/lang/String;
    //   172: iconst_2
    //   173: newarray float
    //   175: dup
    //   176: iconst_0
    //   177: fconst_0
    //   178: fastore
    //   179: dup
    //   180: iconst_1
    //   181: ldc 86
    //   183: fastore
    //   184: invokestatic 92	android/animation/ObjectAnimator:ofFloat	(Ljava/lang/Object;Ljava/lang/String;[F)Landroid/animation/ObjectAnimator;
    //   187: astore_2
    //   188: aload_2
    //   189: ldc2_w 93
    //   192: invokevirtual 98	android/animation/ObjectAnimator:setDuration	(J)Landroid/animation/ObjectAnimator;
    //   195: pop
    //   196: aload_2
    //   197: new 100	android/view/animation/LinearInterpolator
    //   200: dup
    //   201: invokespecial 101	android/view/animation/LinearInterpolator:<init>	()V
    //   204: invokevirtual 105	android/animation/ObjectAnimator:setInterpolator	(Landroid/animation/TimeInterpolator;)V
    //   207: aload_2
    //   208: invokevirtual 108	android/animation/ObjectAnimator:start	()V
    //   211: goto -208 -> 3
    //   214: astore_2
    //   215: aload_2
    //   216: athrow
    // Local variable table:
    //   start	length	slot	name	signature
    //   0	217	0	this	DN
    //   9	12	1	i	int
    //   28	2	2	localException1	Exception
    //   36	172	2	localObject	Object
    //   214	2	2	localException2	Exception
    // Exception table:
    //   from	to	target	type
    //   32	37	28	java/lang/Exception
    //   37	42	28	java/lang/Exception
    //   42	47	28	java/lang/Exception
    //   47	211	28	java/lang/Exception
    //   42	47	214	java/lang/Exception
  }
  
  /* Error */
  public static DN ॱ(int paramInt)
  {
    // Byte code:
    //   0: goto +74 -> 74
    //   3: astore_1
    //   4: aload_1
    //   5: athrow
    //   6: aload_1
    //   7: areturn
    //   8: getstatic 19	o/DN:ʻ	I
    //   11: istore_0
    //   12: iload_0
    //   13: bipush 51
    //   15: iadd
    //   16: istore_0
    //   17: iload_0
    //   18: sipush 128
    //   21: irem
    //   22: putstatic 17	o/DN:ˊ	I
    //   25: iload_0
    //   26: iconst_2
    //   27: irem
    //   28: ifeq +6 -> 34
    //   31: goto +209 -> 240
    //   34: iconst_1
    //   35: istore_0
    //   36: goto +11 -> 47
    //   39: aconst_null
    //   40: arraylength
    //   41: istore_0
    //   42: aload_1
    //   43: areturn
    //   44: astore_1
    //   45: aload_1
    //   46: athrow
    //   47: iload_0
    //   48: tableswitch	default:+24->72, 0:+-9->39, 1:+-42->6
    //   72: aload_1
    //   73: areturn
    //   74: new 2	o/DN
    //   77: dup
    //   78: invokespecial 110	o/DN:<init>	()V
    //   81: astore_1
    //   82: new 112	android/os/Bundle
    //   85: dup
    //   86: invokespecial 113	android/os/Bundle:<init>	()V
    //   89: astore_2
    //   90: aload_2
    //   91: iconst_4
    //   92: newarray char
    //   94: dup
    //   95: iconst_0
    //   96: ldc 114
    //   98: castore
    //   99: dup
    //   100: iconst_1
    //   101: ldc 115
    //   103: castore
    //   104: dup
    //   105: iconst_2
    //   106: ldc 116
    //   108: castore
    //   109: dup
    //   110: iconst_3
    //   111: ldc 117
    //   113: castore
    //   114: ldc 118
    //   116: bipush 14
    //   118: newarray char
    //   120: dup
    //   121: iconst_0
    //   122: ldc 119
    //   124: castore
    //   125: dup
    //   126: iconst_1
    //   127: ldc 120
    //   129: castore
    //   130: dup
    //   131: iconst_2
    //   132: ldc 121
    //   134: castore
    //   135: dup
    //   136: iconst_3
    //   137: ldc 122
    //   139: castore
    //   140: dup
    //   141: iconst_4
    //   142: ldc 123
    //   144: castore
    //   145: dup
    //   146: iconst_5
    //   147: ldc 124
    //   149: castore
    //   150: dup
    //   151: bipush 6
    //   153: ldc 125
    //   155: castore
    //   156: dup
    //   157: bipush 7
    //   159: ldc 126
    //   161: castore
    //   162: dup
    //   163: bipush 8
    //   165: ldc 127
    //   167: castore
    //   168: dup
    //   169: bipush 9
    //   171: ldc -128
    //   173: castore
    //   174: dup
    //   175: bipush 10
    //   177: ldc -127
    //   179: castore
    //   180: dup
    //   181: bipush 11
    //   183: ldc -126
    //   185: castore
    //   186: dup
    //   187: bipush 12
    //   189: ldc -125
    //   191: castore
    //   192: dup
    //   193: bipush 13
    //   195: ldc -124
    //   197: castore
    //   198: iconst_0
    //   199: iconst_4
    //   200: newarray char
    //   202: dup
    //   203: iconst_0
    //   204: ldc 76
    //   206: castore
    //   207: dup
    //   208: iconst_1
    //   209: ldc 77
    //   211: castore
    //   212: dup
    //   213: iconst_2
    //   214: ldc 78
    //   216: castore
    //   217: dup
    //   218: iconst_3
    //   219: ldc 79
    //   221: castore
    //   222: invokestatic 81	o/DN:ˊ	([CC[CI[C)Ljava/lang/String;
    //   225: invokevirtual 85	java/lang/String:intern	()Ljava/lang/String;
    //   228: iload_0
    //   229: invokevirtual 136	android/os/Bundle:putInt	(Ljava/lang/String;I)V
    //   232: aload_1
    //   233: aload_2
    //   234: invokevirtual 140	o/DN:ʽ	(Landroid/os/Bundle;)V
    //   237: goto -229 -> 8
    //   240: iconst_0
    //   241: istore_0
    //   242: goto -195 -> 47
    // Local variable table:
    //   start	length	slot	name	signature
    //   0	245	0	paramInt	int
    //   3	40	1	localException1	Exception
    //   44	29	1	localException2	Exception
    //   81	152	1	localDN	DN
    //   89	145	2	localBundle	android.os.Bundle
    // Exception table:
    //   from	to	target	type
    //   17	25	3	java/lang/Exception
    //   8	12	44	java/lang/Exception
  }
  
  public int ˎ()
  {
    for (;;)
    {
      try
      {
        i = Dv.ˋ.fragment_tour_slide;
        continue;
        i = Dv.ˋ.fragment_tour_slide;
        int j = null.length;
        continue;
        switch (i)
        {
        }
        continue;
        break label93;
        i = 97;
        continue;
        j = ˊ + 5;
        ʻ = j % 128;
        if (j % 2 == 0) {
          return i;
        }
        return i;
      }
      catch (Exception localException)
      {
        throw localException;
      }
      int i = 76;
      continue;
      label93:
      i = ˊ + 91;
      ʻ = i % 128;
      if (i % 2 == 0) {}
    }
  }
  
  /* Error */
  public void ˎ(android.os.Bundle paramBundle)
  {
    // Byte code:
    //   0: goto +228 -> 228
    //   3: return
    //   4: aload_0
    //   5: aload_1
    //   6: invokespecial 148	o/K:ˎ	(Landroid/os/Bundle;)V
    //   9: aload_0
    //   10: invokevirtual 151	o/DN:ʽ	()Landroid/os/Bundle;
    //   13: astore_1
    //   14: aload_1
    //   15: ifnull +6 -> 21
    //   18: goto +213 -> 231
    //   21: goto +245 -> 266
    //   24: getstatic 19	o/DN:ʻ	I
    //   27: bipush 55
    //   29: iadd
    //   30: istore_2
    //   31: iload_2
    //   32: sipush 128
    //   35: irem
    //   36: putstatic 17	o/DN:ˊ	I
    //   39: iload_2
    //   40: iconst_2
    //   41: irem
    //   42: ifeq +6 -> 48
    //   45: goto +218 -> 263
    //   48: goto -45 -> 3
    //   51: astore_1
    //   52: aload_1
    //   53: athrow
    //   54: goto -50 -> 4
    //   57: return
    //   58: aload_0
    //   59: getfield 54	o/DN:ˏ	Landroid/databinding/ViewDataBinding;
    //   62: astore_3
    //   63: aload_3
    //   64: checkcast 56	o/DB
    //   67: astore_3
    //   68: aload_3
    //   69: getfield 59	o/DB:ॱ	Landroid/widget/ImageView;
    //   72: astore_3
    //   73: aload_3
    //   74: aload_1
    //   75: iconst_4
    //   76: newarray char
    //   78: dup
    //   79: iconst_0
    //   80: ldc 114
    //   82: castore
    //   83: dup
    //   84: iconst_1
    //   85: ldc 115
    //   87: castore
    //   88: dup
    //   89: iconst_2
    //   90: ldc 116
    //   92: castore
    //   93: dup
    //   94: iconst_3
    //   95: ldc 117
    //   97: castore
    //   98: ldc 118
    //   100: bipush 14
    //   102: newarray char
    //   104: dup
    //   105: iconst_0
    //   106: ldc 119
    //   108: castore
    //   109: dup
    //   110: iconst_1
    //   111: ldc 120
    //   113: castore
    //   114: dup
    //   115: iconst_2
    //   116: ldc 121
    //   118: castore
    //   119: dup
    //   120: iconst_3
    //   121: ldc 122
    //   123: castore
    //   124: dup
    //   125: iconst_4
    //   126: ldc 123
    //   128: castore
    //   129: dup
    //   130: iconst_5
    //   131: ldc 124
    //   133: castore
    //   134: dup
    //   135: bipush 6
    //   137: ldc 125
    //   139: castore
    //   140: dup
    //   141: bipush 7
    //   143: ldc 126
    //   145: castore
    //   146: dup
    //   147: bipush 8
    //   149: ldc 127
    //   151: castore
    //   152: dup
    //   153: bipush 9
    //   155: ldc -128
    //   157: castore
    //   158: dup
    //   159: bipush 10
    //   161: ldc -127
    //   163: castore
    //   164: dup
    //   165: bipush 11
    //   167: ldc -126
    //   169: castore
    //   170: dup
    //   171: bipush 12
    //   173: ldc -125
    //   175: castore
    //   176: dup
    //   177: bipush 13
    //   179: ldc -124
    //   181: castore
    //   182: iconst_0
    //   183: iconst_4
    //   184: newarray char
    //   186: dup
    //   187: iconst_0
    //   188: ldc 76
    //   190: castore
    //   191: dup
    //   192: iconst_1
    //   193: ldc 77
    //   195: castore
    //   196: dup
    //   197: iconst_2
    //   198: ldc 78
    //   200: castore
    //   201: dup
    //   202: iconst_3
    //   203: ldc 79
    //   205: castore
    //   206: invokestatic 81	o/DN:ˊ	([CC[CI[C)Ljava/lang/String;
    //   209: invokevirtual 85	java/lang/String:intern	()Ljava/lang/String;
    //   212: invokevirtual 155	android/os/Bundle:getInt	(Ljava/lang/String;)I
    //   215: invokevirtual 161	android/widget/ImageView:setImageResource	(I)V
    //   218: aload_0
    //   219: invokespecial 163	o/DN:ˋ	()V
    //   222: goto -198 -> 24
    //   225: astore_1
    //   226: aload_1
    //   227: athrow
    //   228: goto +8 -> 236
    //   231: iconst_3
    //   232: istore_2
    //   233: goto +36 -> 269
    //   236: getstatic 17	o/DN:ˊ	I
    //   239: bipush 65
    //   241: iadd
    //   242: istore_2
    //   243: iload_2
    //   244: sipush 128
    //   247: irem
    //   248: putstatic 19	o/DN:ʻ	I
    //   251: iload_2
    //   252: iconst_2
    //   253: irem
    //   254: ifne +6 -> 260
    //   257: goto -203 -> 54
    //   260: goto -256 -> 4
    //   263: goto -260 -> 3
    //   266: bipush 79
    //   268: istore_2
    //   269: iload_2
    //   270: lookupswitch	default:+26->296, 3:+-212->58, 79:+-213->57
    //   296: goto -238 -> 58
    // Local variable table:
    //   start	length	slot	name	signature
    //   0	299	0	this	DN
    //   0	299	1	paramBundle	android.os.Bundle
    //   30	240	2	i	int
    //   62	12	3	localObject	Object
    // Exception table:
    //   from	to	target	type
    //   63	68	51	java/lang/Exception
    //   58	63	225	java/lang/Exception
    //   63	68	225	java/lang/Exception
    //   68	73	225	java/lang/Exception
    //   73	222	225	java/lang/Exception
  }
}
