package o;

public final class DR
  extends Iy<DO.if, DF>
  implements DO.iF
{
  private static char ˊ = 55225;
  private static char ˋ;
  private static char ˎ;
  private static int ˏ = 0;
  private static char ॱ = 'ℽ';
  private static int ॱॱ = 1;
  
  static
  {
    ˋ = 43812;
    ˎ = '䂭';
  }
  
  /* Error */
  @uv
  public DR(DO.if paramIf, DF paramDF)
  {
    // Byte code:
    //   0: bipush 6
    //   2: newarray char
    //   4: dup
    //   5: iconst_0
    //   6: ldc 38
    //   8: castore
    //   9: dup
    //   10: iconst_1
    //   11: ldc 39
    //   13: castore
    //   14: dup
    //   15: iconst_2
    //   16: ldc 40
    //   18: castore
    //   19: dup
    //   20: iconst_3
    //   21: ldc 41
    //   23: castore
    //   24: dup
    //   25: iconst_4
    //   26: ldc 42
    //   28: castore
    //   29: dup
    //   30: iconst_5
    //   31: ldc 43
    //   33: castore
    //   34: invokestatic 46	o/DR:ˏ	([C)Ljava/lang/String;
    //   37: astore_3
    //   38: aload_3
    //   39: invokevirtual 52	java/lang/String:intern	()Ljava/lang/String;
    //   42: astore_3
    //   43: aload_1
    //   44: aload_3
    //   45: invokestatic 57	o/vq:ˎ	(Ljava/lang/Object;Ljava/lang/String;)V
    //   48: aload_2
    //   49: bipush 12
    //   51: newarray char
    //   53: dup
    //   54: iconst_0
    //   55: ldc 58
    //   57: castore
    //   58: dup
    //   59: iconst_1
    //   60: ldc 59
    //   62: castore
    //   63: dup
    //   64: iconst_2
    //   65: ldc 60
    //   67: castore
    //   68: dup
    //   69: iconst_3
    //   70: ldc 61
    //   72: castore
    //   73: dup
    //   74: iconst_4
    //   75: ldc 62
    //   77: castore
    //   78: dup
    //   79: iconst_5
    //   80: ldc 63
    //   82: castore
    //   83: dup
    //   84: bipush 6
    //   86: ldc 64
    //   88: castore
    //   89: dup
    //   90: bipush 7
    //   92: ldc 65
    //   94: castore
    //   95: dup
    //   96: bipush 8
    //   98: ldc 66
    //   100: castore
    //   101: dup
    //   102: bipush 9
    //   104: ldc 67
    //   106: castore
    //   107: dup
    //   108: bipush 10
    //   110: ldc 68
    //   112: castore
    //   113: dup
    //   114: bipush 11
    //   116: ldc 69
    //   118: castore
    //   119: invokestatic 46	o/DR:ˏ	([C)Ljava/lang/String;
    //   122: invokevirtual 52	java/lang/String:intern	()Ljava/lang/String;
    //   125: invokestatic 57	o/vq:ˎ	(Ljava/lang/Object;Ljava/lang/String;)V
    //   128: aload_0
    //   129: aload_1
    //   130: checkcast 71	o/Iu$if
    //   133: aload_2
    //   134: checkcast 73	o/Ib
    //   137: invokespecial 76	o/Iy:<init>	(Lo/Iu$if;Lo/Ib;)V
    //   140: return
    //   141: astore_1
    //   142: aload_1
    //   143: athrow
    //   144: astore_1
    //   145: aload_1
    //   146: athrow
    // Local variable table:
    //   start	length	slot	name	signature
    //   0	147	0	this	DR
    //   0	147	1	paramIf	DO.if
    //   0	147	2	paramDF	DF
    //   37	8	3	str	String
    // Exception table:
    //   from	to	target	type
    //   0	38	141	java/lang/Exception
    //   43	48	141	java/lang/Exception
    //   48	140	141	java/lang/Exception
    //   38	43	144	java/lang/Exception
  }
  
  /* Error */
  private static String ˏ(char[] paramArrayOfChar)
  {
    // Byte code:
    //   0: goto +121 -> 121
    //   3: new 79	java/lang/NullPointerException
    //   6: dup
    //   7: invokespecial 81	java/lang/NullPointerException:<init>	()V
    //   10: athrow
    //   11: astore_0
    //   12: aload_0
    //   13: athrow
    //   14: aload 4
    //   16: iconst_0
    //   17: aload_0
    //   18: iload_1
    //   19: caload
    //   20: castore
    //   21: aload 4
    //   23: iconst_1
    //   24: aload_0
    //   25: iload_1
    //   26: iconst_1
    //   27: iadd
    //   28: caload
    //   29: castore
    //   30: aload 4
    //   32: getstatic 31	o/DR:ॱ	C
    //   35: getstatic 26	o/DR:ˎ	C
    //   38: getstatic 29	o/DR:ˊ	C
    //   41: getstatic 24	o/DR:ˋ	C
    //   44: invokestatic 86	o/oP:ˏ	([CCCCC)V
    //   47: aload_3
    //   48: iload_1
    //   49: aload 4
    //   51: iconst_0
    //   52: caload
    //   53: castore
    //   54: aload_3
    //   55: iload_1
    //   56: iconst_1
    //   57: iadd
    //   58: aload 4
    //   60: iconst_1
    //   61: caload
    //   62: castore
    //   63: iload_1
    //   64: iconst_2
    //   65: iadd
    //   66: istore_1
    //   67: goto +5 -> 72
    //   70: aload_0
    //   71: areturn
    //   72: iload_1
    //   73: aload_0
    //   74: arraylength
    //   75: if_icmpge +6 -> 81
    //   78: goto +46 -> 124
    //   81: goto +30 -> 111
    //   84: iload_2
    //   85: tableswitch	default:+23->108, 0:+72->157, 1:+-71->14
    //   108: goto -94 -> 14
    //   111: iconst_0
    //   112: istore_2
    //   113: goto -29 -> 84
    //   116: iconst_1
    //   117: istore_1
    //   118: goto +11 -> 129
    //   121: goto +52 -> 173
    //   124: iconst_1
    //   125: istore_2
    //   126: goto -42 -> 84
    //   129: iload_1
    //   130: tableswitch	default:+22->152, 0:+-60->70, 1:+-127->3
    //   152: aload_0
    //   153: areturn
    //   154: goto +45 -> 199
    //   157: new 48	java/lang/String
    //   160: dup
    //   161: aload_3
    //   162: iconst_1
    //   163: aload_3
    //   164: iconst_0
    //   165: caload
    //   166: invokespecial 89	java/lang/String:<init>	([CII)V
    //   169: astore_0
    //   170: goto +49 -> 219
    //   173: getstatic 21	o/DR:ॱॱ	I
    //   176: istore_1
    //   177: iload_1
    //   178: bipush 37
    //   180: iadd
    //   181: istore_1
    //   182: iload_1
    //   183: sipush 128
    //   186: irem
    //   187: putstatic 19	o/DR:ˏ	I
    //   190: iload_1
    //   191: iconst_2
    //   192: irem
    //   193: ifeq +6 -> 199
    //   196: goto -42 -> 154
    //   199: aload_0
    //   200: arraylength
    //   201: newarray char
    //   203: astore_3
    //   204: iconst_0
    //   205: istore_1
    //   206: iconst_2
    //   207: newarray char
    //   209: astore 4
    //   211: goto -139 -> 72
    //   214: iconst_0
    //   215: istore_1
    //   216: goto -87 -> 129
    //   219: getstatic 19	o/DR:ˏ	I
    //   222: bipush 15
    //   224: iadd
    //   225: istore_1
    //   226: iload_1
    //   227: sipush 128
    //   230: irem
    //   231: putstatic 21	o/DR:ॱॱ	I
    //   234: iload_1
    //   235: iconst_2
    //   236: irem
    //   237: ifne +6 -> 243
    //   240: goto -124 -> 116
    //   243: goto -29 -> 214
    // Local variable table:
    //   start	length	slot	name	signature
    //   0	246	0	paramArrayOfChar	char[]
    //   18	219	1	i	int
    //   84	42	2	j	int
    //   47	157	3	arrayOfChar1	char[]
    //   14	196	4	arrayOfChar2	char[]
    // Exception table:
    //   from	to	target	type
    //   173	177	11	java/lang/Exception
    //   182	190	11	java/lang/Exception
  }
  
  public void ˏ()
  {
    break label91;
    int i = 1;
    label91:
    label118:
    label122:
    label127:
    for (;;)
    {
      try
      {
        i = ॱॱ;
        i += 89;
        ˏ = i % 128;
        if (i % 2 != 0) {
          break label127;
        }
        continue;
        return;
        i = ॱॱ + 121;
        ˏ = i % 128;
        if (i % 2 != 0) {
          break label122;
        }
        break;
        switch (i)
        {
        case 1: 
        default: 
          break label118;
          continue;
          ((DF)ʼ()).ˋ().ˋ(true);
          break;
        case 0: 
          i = null.length;
        }
      }
      catch (Exception localException)
      {
        throw localException;
      }
      return;
      i = 0;
    }
  }
}
