package o;

public final class DS
  implements X
{
  public DS() {}
  
  /* Error */
  public boolean ॱ(int paramInt1, int paramInt2)
  {
    // Byte code:
    //   0: getstatic 19	o/Gv:ˊ	Lo/Gv$If;
    //   3: invokevirtual 25	o/Gv$If:ˎ	()Lo/Gv;
    //   6: invokevirtual 29	o/Gv:ˏॱ	()Ljava/lang/String;
    //   9: astore 4
    //   11: iconst_4
    //   12: sipush 362
    //   15: ldc 30
    //   17: invokestatic 36	o/O:ˋ	(IIC)Ljava/lang/Object;
    //   20: checkcast 38	java/lang/Class
    //   23: ldc 39
    //   25: invokevirtual 43	java/lang/Class:getField	(Ljava/lang/String;)Ljava/lang/reflect/Field;
    //   28: aconst_null
    //   29: invokevirtual 49	java/lang/reflect/Field:get	(Ljava/lang/Object;)Ljava/lang/Object;
    //   32: astore 5
    //   34: goto +23 -> 57
    //   37: astore 4
    //   39: aload 4
    //   41: invokevirtual 55	java/lang/Throwable:getCause	()Ljava/lang/Throwable;
    //   44: astore 5
    //   46: aload 5
    //   48: ifnull +6 -> 54
    //   51: aload 5
    //   53: athrow
    //   54: aload 4
    //   56: athrow
    //   57: bipush 7
    //   59: sipush 366
    //   62: iconst_0
    //   63: invokestatic 36	o/O:ˋ	(IIC)Ljava/lang/Object;
    //   66: checkcast 38	java/lang/Class
    //   69: ldc 56
    //   71: aconst_null
    //   72: invokevirtual 60	java/lang/Class:getMethod	(Ljava/lang/String;[Ljava/lang/Class;)Ljava/lang/reflect/Method;
    //   75: aload 5
    //   77: aconst_null
    //   78: invokevirtual 66	java/lang/reflect/Method:invoke	(Ljava/lang/Object;[Ljava/lang/Object;)Ljava/lang/Object;
    //   81: astore 5
    //   83: goto +23 -> 106
    //   86: astore 4
    //   88: aload 4
    //   90: invokevirtual 55	java/lang/Throwable:getCause	()Ljava/lang/Throwable;
    //   93: astore 5
    //   95: aload 5
    //   97: ifnull +6 -> 103
    //   100: aload 5
    //   102: athrow
    //   103: aload 4
    //   105: athrow
    //   106: iconst_4
    //   107: sipush 362
    //   110: ldc 30
    //   112: invokestatic 36	o/O:ˋ	(IIC)Ljava/lang/Object;
    //   115: checkcast 38	java/lang/Class
    //   118: ldc 68
    //   120: aconst_null
    //   121: invokevirtual 60	java/lang/Class:getMethod	(Ljava/lang/String;[Ljava/lang/Class;)Ljava/lang/reflect/Method;
    //   124: aload 5
    //   126: aconst_null
    //   127: invokevirtual 66	java/lang/reflect/Method:invoke	(Ljava/lang/Object;[Ljava/lang/Object;)Ljava/lang/Object;
    //   130: astore 5
    //   132: goto +23 -> 155
    //   135: astore 4
    //   137: aload 4
    //   139: invokevirtual 55	java/lang/Throwable:getCause	()Ljava/lang/Throwable;
    //   142: astore 5
    //   144: aload 5
    //   146: ifnull +6 -> 152
    //   149: aload 5
    //   151: athrow
    //   152: aload 4
    //   154: athrow
    //   155: iconst_4
    //   156: sipush 160
    //   159: iconst_0
    //   160: invokestatic 36	o/O:ˋ	(IIC)Ljava/lang/Object;
    //   163: checkcast 38	java/lang/Class
    //   166: ldc 39
    //   168: iconst_2
    //   169: anewarray 38	java/lang/Class
    //   172: dup
    //   173: iconst_0
    //   174: ldc 70
    //   176: aastore
    //   177: dup
    //   178: iconst_1
    //   179: ldc 70
    //   181: aastore
    //   182: invokevirtual 60	java/lang/Class:getMethod	(Ljava/lang/String;[Ljava/lang/Class;)Ljava/lang/reflect/Method;
    //   185: aconst_null
    //   186: iconst_2
    //   187: anewarray 4	java/lang/Object
    //   190: dup
    //   191: iconst_0
    //   192: aload 4
    //   194: aastore
    //   195: dup
    //   196: iconst_1
    //   197: aload 5
    //   199: aastore
    //   200: invokevirtual 66	java/lang/reflect/Method:invoke	(Ljava/lang/Object;[Ljava/lang/Object;)Ljava/lang/Object;
    //   203: checkcast 72	java/lang/Boolean
    //   206: invokevirtual 76	java/lang/Boolean:booleanValue	()Z
    //   209: istore_3
    //   210: iload_3
    //   211: ireturn
    // Local variable table:
    //   start	length	slot	name	signature
    //   0	212	0	this	DS
    //   0	212	1	paramInt1	int
    //   0	212	2	paramInt2	int
    //   209	2	3	bool	boolean
    //   9	1	4	str	String
    //   37	18	4	localObject1	Object
    //   86	18	4	localObject2	Object
    //   135	58	4	localObject3	Object
    //   32	166	5	localObject4	Object
    // Exception table:
    //   from	to	target	type
    //   57	83	37	finally
    //   106	132	86	finally
    //   155	210	135	finally
  }
}
