package o;

import android.app.Activity;
import android.content.res.Resources;
import com.crashlytics.android.Crashlytics;

public abstract class Dt
  extends Gv
  implements Thread.UncaughtExceptionHandler
{
  private static long ʻ = 5792928513683965357L;
  private static int ʼ;
  private static Dt ˏ;
  private static int ॱॱ = 0;
  private static char[] ᐝ = { -7619, -22639, 26996, 71, 17864, -29900, -11934, 5830, 23552, -23966, -28973, -13486, 1471, 24571, -26560, -11567, 11504, 26948, -23668, -603, 13877, 28826, -13598, 1852, 16788, -25646, -11212, 11912, 26778, -23245, -132, 14788, 29294, -13192, 1735, 17176, -25233, -10278, 4114, 27232, -23371, -7934, 15172, 30132, -12795, 2137, 17124, -25350, -9893, 5042, 28139, -11772, -26747, 22888, 812, -15209, -29178, 28711, 13715, -165, -24206, 27362, 11341, -27083, 23531, 7491, -14587, -30493, 29279, 13389, -1564, -23637, 25875, 11961, -28481, 23063, 8131, -15961, -29923, 19663, 14078, -1935, -16954, 26498, 10604, -27944, 21650, 7798, -16344, -31350, 20345, 12604, -1326, -17330, 26157, 11138, -4771, -31647, -15928, 3881, -4137, -21930, 25787, 16127, -1724, -19499, 19956, 2112, -15736, -25439, 22321, 4510, -21530, 26168, 8336, -1322, -19152, 20364, 2462, -15305, -24968, 22720, 4970, -21125, 26574, 8785, -915, -18738, 28929, 65, 17885, -29910, -11925, 5853, 23554, -23953, -6193, 11521, 29562, -18260, -474, 17528, -12003, -27468, 23107, 18, -14446, -29370, 29463, 13993, -903, -24063, 27091, 12145, -27378, 22782, 7757, -15358, -29720, 28998, 14099, -1344, -24339, 26134, 11710, -27751, 22825, 7396, -15737, -30679, 20477, 13704, -1211, -16672, 25778, 10838, -28223, 22400, 7523, -15562, -31059, 19559, 12825, -1662, -16521, 25886, 10413, -4522, 21519, 7121, -16031, -30948, 19166, 12395, -2516, -16946, 25371, 10558, -4921, 21139, 6190, -8244, -31347, 19288, 3828, -2902, -17851, 25042, 10159, -4804, 20725, 5818, -9092, -31746, 18869, 3889, -2811, -18279, 32312, 9230, -5241, 20806, 5946, -9579, -32701, 17938, 3541, -3245, -18057, 31991, 8810, -6050, -20509, 5448, -9459, -24834, 17573, 2580, -3704, -18511, 32069, 8417, -6491, -21378, 5082, -9731, -24800, 17122, 2241, -12694, -18973, 31637, 8499, -6300, -21804, 4184, -10692, -25172, 17156, 2353, -13149, -19889, 30843, 16293, -6795, -21633, 28356, -11196, -26108, 16853, 1924, -13046, -20262, 30399, 15420, -7197, -22085, 28431, -11526, -26468, 24155, 1509, -13383, -20148, 29892, 14985, -8110, -22571, 28066, -11458, -26351, 23731, 614, -14314, -28772, 30046, 15151, -370, -23539, 27141, -11802, -26801, 23833, 204, -14783, -29671, 29681, 14726, -180, -23827, 26803, 11836, -27157, 23429, 314, -15118, -30029, 28739, 14314, -640, -23688, 26259, 11460, -28073, 22913, 8109, -14979, -29937, 20101, 13376, -1478, -24145, 26382, 11535, -28427, 22087, 7199, -15368, -30345, 20245, 13012, -2022, -16869, 26068, 11139, -28345, 21704, 6828, -16363, -30780, 19856, 13091, -2343, -17267, 25197, 10697, -4169, 21800, 6365, -8542, -31694, 19447, 12708, -2224, -17100, 24705, 9826, -5106, 21385, 6464, -8413, -32090, 18504, 3609, -2565, -17642, 24858, 9384, -5544, 20480, 6127, -8826, -31967, 18120, 3219, -3582, -17952, 32681, 9534, -5926, -20829, 5233, -9328, -32259, 18256, 2815, -3929, -18847, 31748, 9163, -5806, -20625, 4777, -10126, -24981, 17809, 2902, -3839, -19260, 31304, 8316, -6149, -21226, 4920, -10524, -25525, 16959, 2496, -12353, -19122, 30938, 16106, -7127, -21565, 4494, -10494, -25909, 16624, 1661, -12845, -19564, 31071, 15609, -7481, -22443, 28222, -10859, -25789, 16692, 1171, -13724, -20375, 30617, 15738, -7411, -22789, 27751, -11748, -26176, 24342, 1287, -14112, -29079, 29752, 15354, -7782, -22780, 27372, -12124, -27048, 24034, 928, -13990, -29453, 29313, 14454, -113, -23118, 27519, 12009, -27469, 23158, 34, -14436, -29361, 29548, 13957, -921, -23952, 27048, 12116, -27376, 22688, 7784, -15334, -29738, 29001, 14107, -1325, -24468, 26133, 11774, -27718, 22823, 7365, -15701, -30659, 20445, 13735, -1176, -16654, 25732, 10848, -28184, 22456, 7517, -16154, -31069, 19523, 12856, -1613, -16513, 25870, 10412, -4489, 21538, 7074, -16115, -30930, 19136, 12315, -2533, -16904, 25457, 10513, -4884, 21182, 6203, -8241, -31313, 19246, 3783, -2834, -17907, 25081, 10146, -4769, 20733, 5773, -9128, -31773, 18864, 3943, -3382, -18241, 32326, 9240, -5204, 20837, 5994, -9599, -32742, 18036, 3465, -3233, -18125, 31972, 8779, -6077, -20513, 5500, -9458, -24912, 17547, 2574, -3631, -18559, 32085, 8410, -6507, -21495, 5119, -9856, -24734, 17098, 2177, -12696, -19042, 31707, 8571, -6961, -21875, 4219, -10704, -25125, 17246, 2363, -13181, -19888, 30729, 16339, -6828, -21721, 28368, -11189, -26046, 16887, 1891, -13040, -20302, 30361, 15379, -7185, -22111, 28496, -11547, -26447, 24065, 1529, -13431, -20125, 29920, 15007, -8085, -22639, 28099, -11444, -26899, 23730, 595, -14292, -28759, 30041, 15131, -357, -23453, 27174, -11797, -26760, 23832, 200, -14765, -29666, 29615, 14663, -233, -23837, 26851, 11825, -27174, 23436, 338, -15133, -30059, 28682, 14323, -605, -23774, 26356, 11435, -28040, 22980, 8101, -15045, -29825, 20159, 13414, -1435, -24108, 26374, 11542, -28511, 22097, 7283, -15369, -30448, 20348, 12995, -1962, -16835, 26049, 11082, -28376, 21696, 6839, -16328, -30725, 19890, 13087, -2318, -17167, 25146, 10742, -4122, 21829, 6377, -8503, -31621, 19410, 12719, -2223, -17052, 24782, 9820, -5118, 21427, 6488, -8437, -32074, 18508, 3639, -2570, -17556, 24890, 9442, -5559, 20535, 6139, -8888, -31972, 18168, 3201, -3547, -17977, 32747, 9484, -5928, -20742, 5190, -9226, -32270, 18303, 2706, -3964, -18833, 32243, 9129, -5807, -20700, 4781, -10113, -25047, 17802, 2897, -3795, -19301, 31243, 8309, -6235, -21148, 4893, -10589, -25531, 16915, 2555, -12442, -19178, 30942, 16063, -7117, -21546, 4507, -10448, -25980, 16552, 1573, -12918, -19550, 31071, 15587, -7529, -22410, 28565, -10802, -25783, 16661, 1163, -13720, -20471, 30629, 15712, -7370, -22821, 27773, -11652, -26164, 24337, 1323, -14167, -29090, 29720, 15347, -7755, -22724, 27365, -12124, -27120, 23944, 956, -14079, -29502, 29351, 14454, -108, -23168, 27472, 11917, -27465, 23127, 489, -14398, -29378, 29537, 14037, -905, -24036, 27047, 12062, -27371, 22658, 7782, -15233, -29714, 29043, 14115, -1361, -24477, 26146, 11718, -27772, 22862, 7332, -15703, -30671, 20471, 13701, -1252, -16703, 25840, 10843, -28263, 22405, 7473, -16144, -31074, 19573, 13214, -1620, -16541, 25965, 10379, -4512, 21552, 7067, -16008, -30918, 19161, 12414, -2541, -16906, 25445, 10562, -4872, 21118, 6223, -8216, -31354, 19259, 3806, -2833, -17871, 25047, 10160, -4850, 20620, 5776, -9157, -31796, 18847, 3934, -3439, -18233, 32370, 9686, -5235, 20805, 5908, -9575, -32698, 17966, 3494, -3202, -18131, 31957, 8821, -6102, -20525, 5492, -9415, -24867, 17483, 2600, -3646, -18518, 32025, 8392, -6500, -21503, 5061, -9814, -24809, 17114, 2215, -12734, -19051, 31617, 8539, -6964, -21856, 4178, -10691, -25173, 17216, 2330, -13139, -19847, 30739, 16281, -6828, -21716, 28331, -11257, -26091, 16842, 1812, -13008, -20262, 30297, 15378, -7246, -22119, 28426, -11523, -26456, 24159, 1474, -13384, -20215, 29833, 15033, -8096, -22585, 28104, -11417, -26980, 23759, 616, -14329, -28781, 30019, 15153, -375, -23429, 27245, -11845, -26816, 23838, 224, -14749, -29570, 29609, 14686, -251, -23845, 26629, 11807, -27225, 23533, 301, -15156, -30033, 28742, 14212, -598, -23702, 26317, 11423, -28125, 22940, 8120, -14979, -30588, 20104, 13431, -1506, -24114, 26427, 11541, -28489, 22080, 7202, -15442, -30449, 20247, 13005, -1933, -16888, 26109, 11104, -28372, 21703, 6750, -16307, -30726, 19863, 13078, -2364, -17173, 25114, 10750, -4217, 21853, 6279, -8456, -31697, 19400, 12706, -2227, -17665, 24781, 9822, -5113, 21422, 6491, -8350, -32044, 18542, 3605, -2646, -17662, 24850, 9453, -5523, 20534, 6090, -8861, -31968, 18100, 3304, -3510, -17938, 32743, 9533, -5895, -20848, 5178, -9237, -32369, 18272, 2800, -3907, -18850, 32224, 9141, -5771, -21259, 4744, -10188, -25082, 17813, 2891, -3787, -19266, 31332, 8201, -6227, -21157, 4888, -10542, -25484, 16914, 2477, -12432, -19196, 30963, 16043, -7124, -21564, 4539, -10458, -25897, 16536, 1568, -12834, -19479, 31042, 15602, -7520, -22483, 28552, -10848, -25737, 24300, 1155, -13734, -20430, 30619, 15702, -7393, -22876, 27726, -11723, -26137, 24388, 1321, -14129, -29164, 29696, 15277, -7867, -22735, 27369, -12054, -27058, 24001, 943, -14066, -29566, 29432, 14380, -46, -23106, 27483, 11983, -27419, 23082, 475, -14463, -29330, 28827, 13977, -953, -24047, 27014, 12041, -27292, 22719, 7695, -15347, -29705, 29043, 14141, -1330, -24548, 26183, 11728, -27808, 22798, 7373, -15643, -30687, 20447, 13806, -1276, -16755, 25834, 10839, -28180, 22521, 7550, -16184, -31071, 19557, 13311, -1605, -16569, 25880, 10442, -4501, 21541, 7102, -16001, -30859, 19101, 12394, -2511, -16907, 25455, 10549, -4881, 21116, 6209, -8212, -31412, 19217, 3786, -2938, -17833, 25028, 10211, -4769, 20678, 5803, -9178, -31747, 18943, 3924, -3392, -18262, 32342, 9668, -5186, 20841, 6014, -9592, -32643, 17981, 3472, -3253, -18165, 31881, 8811, -6026, -20495, 5473, -9460, -24867, 17427, 2629, -3640, -18572, 32053, 8394, -6406, -21424, 5028, -9746, -24832, 17090, 2183, -12762, -19059, 31666, 8547, -7011, -21850, 4205, -10278, -25193, 17266, 2329, -13123, -19861, 30728, 16293, -6815, -21755, 28340, -11169, -26004, 16889, 1862, -13000, -20231, 30211, 15382, -7187, -22187, 28457, -11600, -26395, 24082, 1529, -13401, -20188, 29941, 15025, -8078, -22537, 28051, -11413, -26896, 23745, 564, -13882, -28739, 30029, 15159, -331, -23488, 27192, -11842, -26879, 23814, 150, -14840, -29682, 29636, 14691, -220, -23811, 26696, 11869, -27191, 23446, 342, -15124, -30054, 28757, 14212, -614, -23740, 26312, 11394, -28118, 22989, 8105, -15060, -30510, 20133, 13395, -1042, -24173, 26479, 11619, -28520, 22117, 7211, -15430, -30451, 20233, 12987, -1940, -16836, 26107, 11024, -28396, 21740, 6726, -16333, -30736, 19869, 13097, -2328, -17249, 25106, 10711, -4172, 21819, 6336, -8554, -31641, 19416, 12796, -2181, -17694, 24709, 9792, -4639, 21379, 6491, -8397, -32124, 18487, 3633, -2632, -17567, 24846, 9381, -5520, 20483, 6142, -8945, -31937, 18173, 3165, -3510, -17942, 32674, 9502, -5906, -20851, 5202, -9269, -32326, 18181, 2762, -3919, -18858, 32144, 9103, -5812, -21307, 4741, -10136, -24618, 17828, 2926, -3778, -19274, 31337, 8213, -6215, -21158, 4892, -10553, -25525, 16896, 2522, -12429, -19179, 30888, 15993, -7082, -21567, 4511, -10477, -25906, 16543, 1573, -12924, -19573, 30988, 15502, -7535, -22460, 28649, -10867, -25733, 24312, 1205, -13750, -20443, 30623, 15728, -7404, -22894, 27713, -11721, -26202, 24418, 1331, -14127, -29092, 29729, 15336, -7817, -22746, 27374, -12210, -27096, 24012, 908, -13991, -29535, 29355, 14365, -42, -23114, 27417, 11914, -27491, 23108, 489, -14411, -29329, 28888, 14011, -921, -24027, 27036, 12125, -27335, 22691, 7803, -15306, -29814, 29001, 14100, -1303, -24488, 26146, 11701, -27820, 22844, 7392, -15793, -30706, 20461, 13703, -1237, -16707, 25771, 10801, -28217, 22419, 7508, -16142, -31090, 19520, 13262, -1648, -16557, 25288, 10386, -4505, 21610, 7124, -16034, -30955, 19120, 12413, -2537, -17018, 25433, 10514, -4909, 21010, 6164, -8216, -31481, 19236, 3808, -2947, -17877, 25009, 10168, -4849, 20710, 5772, -9160, -31747, 18826, 3967, -3336, -18182, 32364, 9666, -5247, 20841, 5334, -9592, -32719, 17983, 3470, -3270, -18121, 31909, 8816, -6108, -20543, 5450, -9460, -24864, 17491, 2593, -3671, -18594, 32055, 8393, -6487, -21461, 5095, -9838, -24829, 17094, 2228, -12751, -18977, 31669, 8554, -6971, -21834, 4143, -10297, -25190, 17232, 1688, -13156, -19875, 30770, 16307, -6837, -21734, 28383, -11199, -26088, 16858, 1911, -13026, -20241, 30290, 15369, -7186, -22242, 28461, -11596, -26434, 24122, 1470, -13426, -20206, 29945, 15005, -8181, -22552, 28034, -11419, -26898, 23743, 632, -13853, -28766, 30059, 14543, -360, -23457, 27137, -11889, -26785, 23863, 143, -14734, -29694, 29682, 14700, -226, -23897, 26750, 11830, -27185, 23314, 269, -15156, -30047, 28716, 14297, -623, -23804, 26328, 11444, -28156, 23016, 8072, -14979, -30496, 20132, 13439, -1123, -24177, 26433, 10999, -28504, 22114, 7231, -15468, -30392, 20237, 12953, -1984, -16875, 26064, 11127, -28374, 21683, 6685, -16360, -30723, 19822, 13076, -2380, -17245, 25169, 10686, -4113, 21792, 6303, -8570, -31717, 19445, 12784, -2210, -17670, 24710, 9851, -4708, 21414, 6474, -8440, -32101, 18499, 3613, -2681, -17552, 24856, 9351, -5617, 20512, 6100, -8883, -31876, 18120, 3169, -3525, -17935, 32542, 9538, -5949, -20842, 5164, -9268, -32272, 18222, 2796, -3915, -18891, 32239, 9130, -5763, -21280, 4797, -10145, -24581, 17884, 2933, -3834, -19247, 31340, 8203, -6190, -21183, 4878, -10590, -25493, 16947, 2557, -12439, -19158, 30935, 15974, -7156, -21534, 4478, -10434, -25881, 16517, 1580, -12842, -19477, 31056, 15612, -7525, -22443, 28552, -10829, -25742, 24212, 1163, -13733, -19982, 30645, 15735, -7399, -22856, 27773, -11756, -26230, 24423, 1330, -14117, -29182, 29733, 15320, -7855, -22772, 27385, -12193, -27118, 23999, 786, 77, 17892, -29933, -11963, 5885, 23563, -23985, -6155, 11562, 29554, -18263, -482, 17524, -30302, -12513, 5476, 23273, -24566, -6630, 11157, 29125, -18592, -869, 17101, -30599, -12892, 5085, 22908, -24915, -6968, 10878, 28594, -18963, -1276, 16563, -31003, -13289, 4710, 22501, -25320, -7351, 10468, 28199, -19378, -1584, 16170, -31417, -13643, 4114, 22103, -25671, -7879, 10081, 27834, -19907, -1971, 15786, -31798, -14011, 3719, 21698, -25996, -8317, 9713, 27410, -20344, -2317, 15381, -32355, -14443, 3351, 21133, -26421, -8704, 9329, 27073, -20718, -2782, 15043, -32745, -14746, 3039, 20763, -26759, -9034, 8735, 26735, -21071, -3317, 14677, 32385, -15340, 2687, 20370, -27170, -9466, 8404, 26305, -21495, -3665, 14320, 32057, -15683, 2255, 20093, -27737, -9791, 7964, 25747, -21777, -4060, 13906, 31739, -16119, 1907, 19586, -28085, -10165, 7639, 25373, -22227, -4465, 13331, 31325, -16460, 1312, 19310, -28503, -10539, 7257, 25006, -22607, -4756, 12940, 30915, -16821, 991, 18896, -28920, -11136, 6886, 24638, -23167, -5141, 12548, 30372, -17185, 575, 18546, -29247, -11495, 6463, 24313, -23466, -5515, 12280, 29956, -17574, 190, 17980, -29593, -11877, 5939, 23893, -23877, -5974, 11892, 29615, -17988, -145, 17627, -29984, -12206, 5528, 23461, -24293, -6488, 11470, 29190, -18534, -619, 17204, -30533, -12568, 5172, 23132, -24591, -6855, 11114, 28905, -18901, -955, 16803, -30923, -12930, 4771, 22531, -24984, -7174, 10554, 28540, -19297, -1343, 16505, -31338, -13366, 4474, 22188, -25358, -7602, 10153, 28096, -19702, -1868, 16070, -31619, -13901, 4052, 21856, -25966, -7997, 9742, 27689, -20001, -2262, 15721, -32107, -14241, 3673, 21384, -26312, -8362, 9404, 27201, -20411, -2684, 15146, -32436, -14623, 3296, 21087, -26634, -8743, 9051, 26774, -20797, -2957, 14726, 32729, -15092, 2777, 20688, -27112, -9292, 8598, 26402, -21130, -3378, 14446, 32335, -15461, 2350, 20350, -27504, -9679, 8284, 26096, -21756, -3795, 14075, 31806, -15776, 1951, 19740, -27796, -10091, 7868, 25687, -22131, -4158, 13691, 31369, -16171, 1542, 19389, -28256, -10433, 7366, 25331, -22521, -4674, 13282, 30998, -16522, 1273, 18970, -28593, -10783, 6948, 24902, -22829, -5101, 12835, 30609, -17117, 804, 18686, -29182, -11150, 6563, 24401, -23172, -5449, 12512, 30211, -17489, 455, 18198, -29529, -11610, 6160, 23937, -23556, -5888, 11952, 29848, -17793, -77, 17882, -29890, -11914, 5850, 23575, -23976, -6150, 11554, 29546, -18186, -509, 17486, -30285, -12541, 5497, 23200, -24514, -6556, 11184, 28967, -18657, -847, 17151, -30638, -12879, 5095, 22895, -24918, -6949, 10868, 28607, -18994, -1249, 16561, -31083, -13290, 4548, 22431, -25343, -7313, 10462, 28213, -19366, -1596, 16203, -31395, -13589, 4102, 22099, -25675, -7915, 10056, 27830, -19960, -1981, 15843, -31765, -13990, 3731, 21699, -25995, -8272, 9679, 27513, 98, 17881, -29907, -11930, 5848, 23565, -23957, -6193, 11590, 29509, -18301, -458, 17489, -30324, -12488, 5495, 23183, -24516, -6551, 11139, 29133, -18585, -873, 17119, -30623, 65, 17885, -29910, -11925, 5853, 23554, -23953, -6193, 11521, 29562, -18260, -433, 17524, -30296, -12539, 5379, 23187, -24529, -6549, 11140, 29132, -18572, -870, 17073, -30696, 20562, 5618, -9464, -32442, 18154 };
  private Thread.UncaughtExceptionHandler ˋ;
  
  static
  {
    ʼ = 1;
  }
  
  public Dt() {}
  
  /* Error */
  private void ʻॱ()
  {
    // Byte code:
    //   0: goto +119 -> 119
    //   3: iload_1
    //   4: tableswitch	default:+24->28, 0:+254->258, 1:+151->155
    //   28: return
    //   29: getstatic 23	o/Dt:ʼ	I
    //   32: istore_1
    //   33: iload_1
    //   34: bipush 29
    //   36: iadd
    //   37: istore_1
    //   38: iload_1
    //   39: sipush 128
    //   42: irem
    //   43: putstatic 21	o/Dt:ॱॱ	I
    //   46: iload_1
    //   47: iconst_2
    //   48: irem
    //   49: ifeq +6 -> 55
    //   52: goto +159 -> 211
    //   55: goto +146 -> 201
    //   58: iconst_0
    //   59: istore_1
    //   60: goto +62 -> 122
    //   63: iconst_1
    //   64: istore_1
    //   65: goto -62 -> 3
    //   68: iconst_1
    //   69: istore_1
    //   70: goto +52 -> 122
    //   73: aload_0
    //   74: invokevirtual 2200	android/content/Context:getApplicationInfo	()Landroid/content/pm/ApplicationInfo;
    //   77: astore_2
    //   78: aload_2
    //   79: getfield 2205	android/content/pm/ApplicationInfo:targetSdkVersion	I
    //   82: bipush 104
    //   84: iadd
    //   85: aload_0
    //   86: invokevirtual 2200	android/content/Context:getApplicationInfo	()Landroid/content/pm/ApplicationInfo;
    //   89: getfield 2205	android/content/pm/ApplicationInfo:targetSdkVersion	I
    //   92: bipush 25
    //   94: isub
    //   95: i2c
    //   96: aload_0
    //   97: invokevirtual 2200	android/content/Context:getApplicationInfo	()Landroid/content/pm/ApplicationInfo;
    //   100: getfield 2205	android/content/pm/ApplicationInfo:targetSdkVersion	I
    //   103: bipush 12
    //   105: isub
    //   106: invokestatic 2208	o/Dt:ˏ	(ICI)Ljava/lang/String;
    //   109: invokevirtual 2214	java/lang/String:intern	()Ljava/lang/String;
    //   112: aload_3
    //   113: invokestatic 2220	com/crashlytics/android/Crashlytics:ॱ	(Ljava/lang/String;Ljava/lang/String;)V
    //   116: goto +405 -> 521
    //   119: goto +37 -> 156
    //   122: iload_1
    //   123: tableswitch	default:+21->144, 0:+51->174, 1:+398->521
    //   144: goto +377 -> 521
    //   147: astore_2
    //   148: aload_2
    //   149: athrow
    //   150: iconst_0
    //   151: istore_1
    //   152: goto -149 -> 3
    //   155: return
    //   156: aload_0
    //   157: invokevirtual 2223	o/Dt:ˏॱ	()Ljava/lang/String;
    //   160: astore_3
    //   161: aload_3
    //   162: invokestatic 2229	android/text/TextUtils:isEmpty	(Ljava/lang/CharSequence;)Z
    //   165: ifne +6 -> 171
    //   168: goto -110 -> 58
    //   171: goto -103 -> 68
    //   174: getstatic 21	o/Dt:ॱॱ	I
    //   177: bipush 17
    //   179: iadd
    //   180: istore_1
    //   181: iload_1
    //   182: sipush 128
    //   185: irem
    //   186: putstatic 23	o/Dt:ʼ	I
    //   189: iload_1
    //   190: iconst_2
    //   191: irem
    //   192: ifne +6 -> 198
    //   195: goto +19 -> 214
    //   198: goto -125 -> 73
    //   201: aload_2
    //   202: invokestatic 2232	com/crashlytics/android/Crashlytics:ॱ	(Ljava/lang/String;)V
    //   205: goto +58 -> 263
    //   208: astore_2
    //   209: aload_2
    //   210: athrow
    //   211: goto -10 -> 201
    //   214: bipush 30
    //   216: aload_0
    //   217: invokevirtual 2200	android/content/Context:getApplicationInfo	()Landroid/content/pm/ApplicationInfo;
    //   220: getfield 2205	android/content/pm/ApplicationInfo:targetSdkVersion	I
    //   223: idiv
    //   224: aload_0
    //   225: invokevirtual 2200	android/content/Context:getApplicationInfo	()Landroid/content/pm/ApplicationInfo;
    //   228: getfield 2205	android/content/pm/ApplicationInfo:targetSdkVersion	I
    //   231: bipush 124
    //   233: iadd
    //   234: i2c
    //   235: aload_0
    //   236: invokevirtual 2200	android/content/Context:getApplicationInfo	()Landroid/content/pm/ApplicationInfo;
    //   239: getfield 2205	android/content/pm/ApplicationInfo:targetSdkVersion	I
    //   242: bipush 41
    //   244: isub
    //   245: invokestatic 2208	o/Dt:ˏ	(ICI)Ljava/lang/String;
    //   248: invokevirtual 2214	java/lang/String:intern	()Ljava/lang/String;
    //   251: aload_3
    //   252: invokestatic 2220	com/crashlytics/android/Crashlytics:ॱ	(Ljava/lang/String;Ljava/lang/String;)V
    //   255: goto +266 -> 521
    //   258: aload_2
    //   259: invokestatic 2234	com/crashlytics/android/Crashlytics:ˏ	(Ljava/lang/String;)V
    //   262: return
    //   263: aload_0
    //   264: invokevirtual 2238	android/content/Context:getResources	()Landroid/content/res/Resources;
    //   267: ldc_w 2239
    //   270: invokevirtual 2245	android/content/res/Resources:getString	(I)Ljava/lang/String;
    //   273: iconst_0
    //   274: iconst_4
    //   275: invokevirtual 2249	java/lang/String:substring	(II)Ljava/lang/String;
    //   278: invokevirtual 2253	java/lang/String:length	()I
    //   281: iconst_0
    //   282: iadd
    //   283: aload_0
    //   284: invokevirtual 2200	android/content/Context:getApplicationInfo	()Landroid/content/pm/ApplicationInfo;
    //   287: getfield 2205	android/content/pm/ApplicationInfo:targetSdkVersion	I
    //   290: sipush 337
    //   293: iadd
    //   294: aload_0
    //   295: invokevirtual 2238	android/content/Context:getResources	()Landroid/content/res/Resources;
    //   298: ldc_w 2254
    //   301: invokevirtual 2245	android/content/res/Resources:getString	(I)Ljava/lang/String;
    //   304: iconst_0
    //   305: iconst_5
    //   306: invokevirtual 2249	java/lang/String:substring	(II)Ljava/lang/String;
    //   309: iconst_3
    //   310: invokevirtual 2258	java/lang/String:codePointAt	(I)I
    //   313: ldc_w 2259
    //   316: iadd
    //   317: i2c
    //   318: invokestatic 2264	o/O:ˋ	(IIC)Ljava/lang/Object;
    //   321: checkcast 2266	java/lang/Class
    //   324: ldc_w 2268
    //   327: invokevirtual 2272	java/lang/Class:getField	(Ljava/lang/String;)Ljava/lang/reflect/Field;
    //   330: aconst_null
    //   331: invokevirtual 2278	java/lang/reflect/Field:get	(Ljava/lang/Object;)Ljava/lang/Object;
    //   334: astore_2
    //   335: goto +17 -> 352
    //   338: astore_2
    //   339: aload_2
    //   340: invokevirtual 2284	java/lang/Throwable:getCause	()Ljava/lang/Throwable;
    //   343: astore_3
    //   344: aload_3
    //   345: ifnull +5 -> 350
    //   348: aload_3
    //   349: athrow
    //   350: aload_2
    //   351: athrow
    //   352: aload_0
    //   353: invokevirtual 2287	android/content/Context:getPackageName	()Ljava/lang/String;
    //   356: invokevirtual 2253	java/lang/String:length	()I
    //   359: iconst_4
    //   360: isub
    //   361: aload_0
    //   362: invokevirtual 2287	android/content/Context:getPackageName	()Ljava/lang/String;
    //   365: iconst_1
    //   366: invokevirtual 2258	java/lang/String:codePointAt	(I)I
    //   369: sipush 255
    //   372: iadd
    //   373: aload_0
    //   374: invokevirtual 2238	android/content/Context:getResources	()Landroid/content/res/Resources;
    //   377: ldc_w 2288
    //   380: invokevirtual 2245	android/content/res/Resources:getString	(I)Ljava/lang/String;
    //   383: iconst_0
    //   384: iconst_5
    //   385: invokevirtual 2249	java/lang/String:substring	(II)Ljava/lang/String;
    //   388: iconst_0
    //   389: invokevirtual 2258	java/lang/String:codePointAt	(I)I
    //   392: iconst_5
    //   393: isub
    //   394: i2c
    //   395: invokestatic 2264	o/O:ˋ	(IIC)Ljava/lang/Object;
    //   398: checkcast 2266	java/lang/Class
    //   401: ldc_w 2289
    //   404: aconst_null
    //   405: invokevirtual 2293	java/lang/Class:getMethod	(Ljava/lang/String;[Ljava/lang/Class;)Ljava/lang/reflect/Method;
    //   408: aload_2
    //   409: aconst_null
    //   410: invokevirtual 2299	java/lang/reflect/Method:invoke	(Ljava/lang/Object;[Ljava/lang/Object;)Ljava/lang/Object;
    //   413: astore_2
    //   414: goto +17 -> 431
    //   417: astore_2
    //   418: aload_2
    //   419: invokevirtual 2284	java/lang/Throwable:getCause	()Ljava/lang/Throwable;
    //   422: astore_3
    //   423: aload_3
    //   424: ifnull +5 -> 429
    //   427: aload_3
    //   428: athrow
    //   429: aload_2
    //   430: athrow
    //   431: aload_0
    //   432: invokevirtual 2238	android/content/Context:getResources	()Landroid/content/res/Resources;
    //   435: ldc_w 2300
    //   438: invokevirtual 2245	android/content/res/Resources:getString	(I)Ljava/lang/String;
    //   441: iconst_0
    //   442: iconst_4
    //   443: invokevirtual 2249	java/lang/String:substring	(II)Ljava/lang/String;
    //   446: invokevirtual 2253	java/lang/String:length	()I
    //   449: iconst_0
    //   450: iadd
    //   451: aload_0
    //   452: invokevirtual 2238	android/content/Context:getResources	()Landroid/content/res/Resources;
    //   455: ldc_w 2301
    //   458: invokevirtual 2245	android/content/res/Resources:getString	(I)Ljava/lang/String;
    //   461: iconst_0
    //   462: iconst_4
    //   463: invokevirtual 2249	java/lang/String:substring	(II)Ljava/lang/String;
    //   466: iconst_2
    //   467: invokevirtual 2258	java/lang/String:codePointAt	(I)I
    //   470: sipush 351
    //   473: iadd
    //   474: aload_0
    //   475: invokevirtual 2200	android/content/Context:getApplicationInfo	()Landroid/content/pm/ApplicationInfo;
    //   478: getfield 2205	android/content/pm/ApplicationInfo:targetSdkVersion	I
    //   481: ldc_w 2302
    //   484: iadd
    //   485: i2c
    //   486: invokestatic 2264	o/O:ˋ	(IIC)Ljava/lang/Object;
    //   489: checkcast 2266	java/lang/Class
    //   492: ldc_w 2268
    //   495: aconst_null
    //   496: invokevirtual 2293	java/lang/Class:getMethod	(Ljava/lang/String;[Ljava/lang/Class;)Ljava/lang/reflect/Method;
    //   499: aload_2
    //   500: aconst_null
    //   501: invokevirtual 2299	java/lang/reflect/Method:invoke	(Ljava/lang/Object;[Ljava/lang/Object;)Ljava/lang/Object;
    //   504: checkcast 2210	java/lang/String
    //   507: astore_2
    //   508: aload_2
    //   509: invokestatic 2229	android/text/TextUtils:isEmpty	(Ljava/lang/CharSequence;)Z
    //   512: ifne +6 -> 518
    //   515: goto -365 -> 150
    //   518: goto -455 -> 63
    //   521: aload_0
    //   522: invokevirtual 2287	android/content/Context:getPackageName	()Ljava/lang/String;
    //   525: bipush 8
    //   527: invokevirtual 2258	java/lang/String:codePointAt	(I)I
    //   530: bipush 108
    //   532: isub
    //   533: aload_0
    //   534: invokevirtual 2287	android/content/Context:getPackageName	()Ljava/lang/String;
    //   537: iconst_2
    //   538: invokevirtual 2258	java/lang/String:codePointAt	(I)I
    //   541: sipush 316
    //   544: iadd
    //   545: aload_0
    //   546: invokevirtual 2287	android/content/Context:getPackageName	()Ljava/lang/String;
    //   549: invokevirtual 2253	java/lang/String:length	()I
    //   552: ldc_w 2303
    //   555: iadd
    //   556: i2c
    //   557: invokestatic 2264	o/O:ˋ	(IIC)Ljava/lang/Object;
    //   560: checkcast 2266	java/lang/Class
    //   563: ldc_w 2268
    //   566: invokevirtual 2272	java/lang/Class:getField	(Ljava/lang/String;)Ljava/lang/reflect/Field;
    //   569: aconst_null
    //   570: invokevirtual 2278	java/lang/reflect/Field:get	(Ljava/lang/Object;)Ljava/lang/Object;
    //   573: astore_2
    //   574: goto +17 -> 591
    //   577: astore_2
    //   578: aload_2
    //   579: invokevirtual 2284	java/lang/Throwable:getCause	()Ljava/lang/Throwable;
    //   582: astore_3
    //   583: aload_3
    //   584: ifnull +5 -> 589
    //   587: aload_3
    //   588: athrow
    //   589: aload_2
    //   590: athrow
    //   591: aload_0
    //   592: invokevirtual 2238	android/content/Context:getResources	()Landroid/content/res/Resources;
    //   595: ldc_w 2304
    //   598: invokevirtual 2245	android/content/res/Resources:getString	(I)Ljava/lang/String;
    //   601: iconst_0
    //   602: iconst_4
    //   603: invokevirtual 2249	java/lang/String:substring	(II)Ljava/lang/String;
    //   606: invokevirtual 2253	java/lang/String:length	()I
    //   609: iconst_3
    //   610: iadd
    //   611: aload_0
    //   612: invokevirtual 2238	android/content/Context:getResources	()Landroid/content/res/Resources;
    //   615: ldc_w 2305
    //   618: invokevirtual 2245	android/content/res/Resources:getString	(I)Ljava/lang/String;
    //   621: iconst_0
    //   622: iconst_4
    //   623: invokevirtual 2249	java/lang/String:substring	(II)Ljava/lang/String;
    //   626: iconst_0
    //   627: invokevirtual 2258	java/lang/String:codePointAt	(I)I
    //   630: sipush 361
    //   633: iadd
    //   634: aload_0
    //   635: invokevirtual 2287	android/content/Context:getPackageName	()Ljava/lang/String;
    //   638: invokevirtual 2253	java/lang/String:length	()I
    //   641: bipush 11
    //   643: isub
    //   644: i2c
    //   645: invokestatic 2264	o/O:ˋ	(IIC)Ljava/lang/Object;
    //   648: checkcast 2266	java/lang/Class
    //   651: ldc_w 2289
    //   654: aconst_null
    //   655: invokevirtual 2293	java/lang/Class:getMethod	(Ljava/lang/String;[Ljava/lang/Class;)Ljava/lang/reflect/Method;
    //   658: aload_2
    //   659: aconst_null
    //   660: invokevirtual 2299	java/lang/reflect/Method:invoke	(Ljava/lang/Object;[Ljava/lang/Object;)Ljava/lang/Object;
    //   663: astore_2
    //   664: goto +17 -> 681
    //   667: astore_2
    //   668: aload_2
    //   669: invokevirtual 2284	java/lang/Throwable:getCause	()Ljava/lang/Throwable;
    //   672: astore_3
    //   673: aload_3
    //   674: ifnull +5 -> 679
    //   677: aload_3
    //   678: athrow
    //   679: aload_2
    //   680: athrow
    //   681: aload_0
    //   682: invokevirtual 2200	android/content/Context:getApplicationInfo	()Landroid/content/pm/ApplicationInfo;
    //   685: getfield 2205	android/content/pm/ApplicationInfo:targetSdkVersion	I
    //   688: bipush 21
    //   690: isub
    //   691: aload_0
    //   692: invokevirtual 2200	android/content/Context:getApplicationInfo	()Landroid/content/pm/ApplicationInfo;
    //   695: getfield 2205	android/content/pm/ApplicationInfo:targetSdkVersion	I
    //   698: sipush 337
    //   701: iadd
    //   702: aload_0
    //   703: invokevirtual 2238	android/content/Context:getResources	()Landroid/content/res/Resources;
    //   706: ldc_w 2306
    //   709: invokevirtual 2245	android/content/res/Resources:getString	(I)Ljava/lang/String;
    //   712: iconst_0
    //   713: iconst_4
    //   714: invokevirtual 2249	java/lang/String:substring	(II)Ljava/lang/String;
    //   717: iconst_1
    //   718: invokevirtual 2258	java/lang/String:codePointAt	(I)I
    //   721: ldc_w 2307
    //   724: iadd
    //   725: i2c
    //   726: invokestatic 2264	o/O:ˋ	(IIC)Ljava/lang/Object;
    //   729: checkcast 2266	java/lang/Class
    //   732: ldc_w 2308
    //   735: aconst_null
    //   736: invokevirtual 2293	java/lang/Class:getMethod	(Ljava/lang/String;[Ljava/lang/Class;)Ljava/lang/reflect/Method;
    //   739: aload_2
    //   740: aconst_null
    //   741: invokevirtual 2299	java/lang/reflect/Method:invoke	(Ljava/lang/Object;[Ljava/lang/Object;)Ljava/lang/Object;
    //   744: checkcast 2210	java/lang/String
    //   747: astore_2
    //   748: aload_2
    //   749: invokestatic 2229	android/text/TextUtils:isEmpty	(Ljava/lang/CharSequence;)Z
    //   752: ifne +6 -> 758
    //   755: goto -726 -> 29
    //   758: goto -495 -> 263
    // Local variable table:
    //   start	length	slot	name	signature
    //   0	761	0	this	Dt
    //   3	189	1	i	int
    //   77	2	2	localApplicationInfo	android.content.pm.ApplicationInfo
    //   147	55	2	localException1	Exception
    //   208	51	2	localException2	Exception
    //   334	1	2	localObject1	Object
    //   338	71	2	localObject2	Object
    //   413	1	2	localObject3	Object
    //   417	83	2	localObject4	Object
    //   507	67	2	localObject5	Object
    //   577	82	2	localObject6	Object
    //   663	1	2	localObject7	Object
    //   667	73	2	localObject8	Object
    //   747	2	2	str	String
    //   112	566	3	localObject9	Object
    // Exception table:
    //   from	to	target	type
    //   29	33	147	java/lang/Exception
    //   201	205	147	java/lang/Exception
    //   38	46	208	java/lang/Exception
    //   73	78	208	java/lang/Exception
    //   258	262	208	java/lang/Exception
    //   352	414	338	finally
    //   431	508	417	finally
    //   591	664	577	finally
    //   681	748	667	finally
  }
  
  private static String ˏ(int paramInt1, char paramChar, int paramInt2)
  {
    break label112;
    int i = 10;
    break label27;
    label9:
    i = paramChar;
    int j = paramInt1;
    paramInt1 = 0;
    label16:
    if (paramInt1 >= paramInt2)
    {
      break label142;
      switch (i)
      {
      default: 
        label27:
        break;
      }
    }
    for (;;)
    {
      i = 61;
      break label27;
      char[] arrayOfChar = new char[paramInt2];
      break label9;
      arrayOfChar[paramInt1] = ((char)(int)(ᐝ[(j >> paramInt1)] * (paramInt1 ^ ʻ) % i));
      paramInt1 += 127;
      break label16;
      label112:
      do
      {
        paramChar = 'J';
        break label218;
        break;
        paramChar = ʼ + 75;
        ॱॱ = paramChar % '';
      } while (paramChar % '\002' != 0);
      break label247;
      label142:
      return new String(arrayOfChar);
      arrayOfChar = new char[paramInt2];
      break label9;
      arrayOfChar[paramInt1] = ((char)(int)(ᐝ[(j + paramInt1)] ^ paramInt1 * ʻ ^ i));
      paramInt1 += 1;
      break label16;
      i = ʼ + 5;
      ॱॱ = i % 128;
      if (i % 2 != 0) {
        break;
      }
    }
    for (;;)
    {
      label218:
      switch (paramChar)
      {
      }
      break;
      label247:
      paramChar = 'G';
    }
  }
  
  /* Error */
  private void ॱˋ()
  {
    // Byte code:
    //   0: goto +16 -> 16
    //   3: bipush 45
    //   5: istore_1
    //   6: goto +645 -> 651
    //   9: return
    //   10: bipush 84
    //   12: istore_1
    //   13: goto +638 -> 651
    //   16: goto +672 -> 688
    //   19: goto +30 -> 49
    //   22: getstatic 21	o/Dt:ॱॱ	I
    //   25: bipush 25
    //   27: iadd
    //   28: istore_1
    //   29: iload_1
    //   30: sipush 128
    //   33: irem
    //   34: putstatic 23	o/Dt:ʼ	I
    //   37: iload_1
    //   38: iconst_2
    //   39: irem
    //   40: ifne +6 -> 46
    //   43: goto -40 -> 3
    //   46: goto -36 -> 10
    //   49: aload_0
    //   50: invokevirtual 2238	android/content/Context:getResources	()Landroid/content/res/Resources;
    //   53: ldc_w 2313
    //   56: invokevirtual 2245	android/content/res/Resources:getString	(I)Ljava/lang/String;
    //   59: iconst_0
    //   60: iconst_1
    //   61: invokevirtual 2249	java/lang/String:substring	(II)Ljava/lang/String;
    //   64: invokevirtual 2253	java/lang/String:length	()I
    //   67: iconst_3
    //   68: iadd
    //   69: aload_0
    //   70: invokevirtual 2200	android/content/Context:getApplicationInfo	()Landroid/content/pm/ApplicationInfo;
    //   73: getfield 2205	android/content/pm/ApplicationInfo:targetSdkVersion	I
    //   76: sipush 337
    //   79: iadd
    //   80: aload_0
    //   81: invokevirtual 2287	android/content/Context:getPackageName	()Ljava/lang/String;
    //   84: invokevirtual 2253	java/lang/String:length	()I
    //   87: ldc_w 2303
    //   90: iadd
    //   91: i2c
    //   92: invokestatic 2264	o/O:ˋ	(IIC)Ljava/lang/Object;
    //   95: checkcast 2266	java/lang/Class
    //   98: ldc_w 2268
    //   101: invokevirtual 2272	java/lang/Class:getField	(Ljava/lang/String;)Ljava/lang/reflect/Field;
    //   104: aconst_null
    //   105: invokevirtual 2278	java/lang/reflect/Field:get	(Ljava/lang/Object;)Ljava/lang/Object;
    //   108: astore_2
    //   109: goto +17 -> 126
    //   112: astore_2
    //   113: aload_2
    //   114: invokevirtual 2284	java/lang/Throwable:getCause	()Ljava/lang/Throwable;
    //   117: astore_3
    //   118: aload_3
    //   119: ifnull +5 -> 124
    //   122: aload_3
    //   123: athrow
    //   124: aload_2
    //   125: athrow
    //   126: aload_0
    //   127: invokevirtual 2200	android/content/Context:getApplicationInfo	()Landroid/content/pm/ApplicationInfo;
    //   130: getfield 2205	android/content/pm/ApplicationInfo:targetSdkVersion	I
    //   133: bipush 18
    //   135: isub
    //   136: aload_0
    //   137: invokevirtual 2200	android/content/Context:getApplicationInfo	()Landroid/content/pm/ApplicationInfo;
    //   140: getfield 2205	android/content/pm/ApplicationInfo:targetSdkVersion	I
    //   143: sipush 341
    //   146: iadd
    //   147: aload_0
    //   148: invokevirtual 2238	android/content/Context:getResources	()Landroid/content/res/Resources;
    //   151: ldc_w 2314
    //   154: invokevirtual 2245	android/content/res/Resources:getString	(I)Ljava/lang/String;
    //   157: iconst_0
    //   158: iconst_5
    //   159: invokevirtual 2249	java/lang/String:substring	(II)Ljava/lang/String;
    //   162: iconst_1
    //   163: invokevirtual 2258	java/lang/String:codePointAt	(I)I
    //   166: bipush 26
    //   168: isub
    //   169: i2c
    //   170: invokestatic 2264	o/O:ˋ	(IIC)Ljava/lang/Object;
    //   173: checkcast 2266	java/lang/Class
    //   176: ldc_w 2289
    //   179: aconst_null
    //   180: invokevirtual 2293	java/lang/Class:getMethod	(Ljava/lang/String;[Ljava/lang/Class;)Ljava/lang/reflect/Method;
    //   183: aload_2
    //   184: aconst_null
    //   185: invokevirtual 2299	java/lang/reflect/Method:invoke	(Ljava/lang/Object;[Ljava/lang/Object;)Ljava/lang/Object;
    //   188: astore_2
    //   189: aload_0
    //   190: invokevirtual 2200	android/content/Context:getApplicationInfo	()Landroid/content/pm/ApplicationInfo;
    //   193: getfield 2205	android/content/pm/ApplicationInfo:targetSdkVersion	I
    //   196: bipush 117
    //   198: iadd
    //   199: aload_0
    //   200: invokevirtual 2238	android/content/Context:getResources	()Landroid/content/res/Resources;
    //   203: ldc_w 2315
    //   206: invokevirtual 2245	android/content/res/Resources:getString	(I)Ljava/lang/String;
    //   209: iconst_0
    //   210: iconst_5
    //   211: invokevirtual 2249	java/lang/String:substring	(II)Ljava/lang/String;
    //   214: iconst_1
    //   215: invokevirtual 2258	java/lang/String:codePointAt	(I)I
    //   218: ldc_w 2316
    //   221: iadd
    //   222: i2c
    //   223: aload_0
    //   224: invokevirtual 2238	android/content/Context:getResources	()Landroid/content/res/Resources;
    //   227: ldc_w 2317
    //   230: invokevirtual 2245	android/content/res/Resources:getString	(I)Ljava/lang/String;
    //   233: iconst_0
    //   234: bipush 9
    //   236: invokevirtual 2249	java/lang/String:substring	(II)Ljava/lang/String;
    //   239: invokevirtual 2253	java/lang/String:length	()I
    //   242: sipush 1619
    //   245: iadd
    //   246: invokestatic 2208	o/Dt:ˏ	(ICI)Ljava/lang/String;
    //   249: invokevirtual 2214	java/lang/String:intern	()Ljava/lang/String;
    //   252: astore_3
    //   253: goto +17 -> 270
    //   256: astore_2
    //   257: aload_2
    //   258: invokevirtual 2284	java/lang/Throwable:getCause	()Ljava/lang/Throwable;
    //   261: astore_3
    //   262: aload_3
    //   263: ifnull +5 -> 268
    //   266: aload_3
    //   267: athrow
    //   268: aload_2
    //   269: athrow
    //   270: aload_0
    //   271: invokevirtual 2238	android/content/Context:getResources	()Landroid/content/res/Resources;
    //   274: ldc_w 2318
    //   277: invokevirtual 2245	android/content/res/Resources:getString	(I)Ljava/lang/String;
    //   280: iconst_0
    //   281: iconst_4
    //   282: invokevirtual 2249	java/lang/String:substring	(II)Ljava/lang/String;
    //   285: invokevirtual 2253	java/lang/String:length	()I
    //   288: iconst_0
    //   289: iadd
    //   290: aload_0
    //   291: invokevirtual 2200	android/content/Context:getApplicationInfo	()Landroid/content/pm/ApplicationInfo;
    //   294: getfield 2205	android/content/pm/ApplicationInfo:targetSdkVersion	I
    //   297: sipush 337
    //   300: iadd
    //   301: aload_0
    //   302: invokevirtual 2238	android/content/Context:getResources	()Landroid/content/res/Resources;
    //   305: ldc_w 2319
    //   308: invokevirtual 2245	android/content/res/Resources:getString	(I)Ljava/lang/String;
    //   311: iconst_0
    //   312: iconst_4
    //   313: invokevirtual 2249	java/lang/String:substring	(II)Ljava/lang/String;
    //   316: invokevirtual 2253	java/lang/String:length	()I
    //   319: ldc_w 2320
    //   322: iadd
    //   323: i2c
    //   324: invokestatic 2264	o/O:ˋ	(IIC)Ljava/lang/Object;
    //   327: checkcast 2266	java/lang/Class
    //   330: ldc_w 2289
    //   333: iconst_1
    //   334: anewarray 2266	java/lang/Class
    //   337: dup
    //   338: iconst_0
    //   339: ldc_w 2210
    //   342: aastore
    //   343: invokevirtual 2293	java/lang/Class:getMethod	(Ljava/lang/String;[Ljava/lang/Class;)Ljava/lang/reflect/Method;
    //   346: aload_2
    //   347: iconst_1
    //   348: anewarray 2322	java/lang/Object
    //   351: dup
    //   352: iconst_0
    //   353: aload_3
    //   354: aastore
    //   355: invokevirtual 2299	java/lang/reflect/Method:invoke	(Ljava/lang/Object;[Ljava/lang/Object;)Ljava/lang/Object;
    //   358: pop
    //   359: aload_0
    //   360: invokevirtual 2200	android/content/Context:getApplicationInfo	()Landroid/content/pm/ApplicationInfo;
    //   363: getfield 2205	android/content/pm/ApplicationInfo:targetSdkVersion	I
    //   366: bipush 21
    //   368: isub
    //   369: aload_0
    //   370: invokevirtual 2200	android/content/Context:getApplicationInfo	()Landroid/content/pm/ApplicationInfo;
    //   373: getfield 2205	android/content/pm/ApplicationInfo:targetSdkVersion	I
    //   376: sipush 337
    //   379: iadd
    //   380: aload_0
    //   381: invokevirtual 2287	android/content/Context:getPackageName	()Ljava/lang/String;
    //   384: invokevirtual 2253	java/lang/String:length	()I
    //   387: ldc_w 2303
    //   390: iadd
    //   391: i2c
    //   392: invokestatic 2264	o/O:ˋ	(IIC)Ljava/lang/Object;
    //   395: checkcast 2266	java/lang/Class
    //   398: ldc_w 2268
    //   401: invokevirtual 2272	java/lang/Class:getField	(Ljava/lang/String;)Ljava/lang/reflect/Field;
    //   404: aconst_null
    //   405: invokevirtual 2278	java/lang/reflect/Field:get	(Ljava/lang/Object;)Ljava/lang/Object;
    //   408: astore_2
    //   409: goto +17 -> 426
    //   412: astore_2
    //   413: aload_2
    //   414: invokevirtual 2284	java/lang/Throwable:getCause	()Ljava/lang/Throwable;
    //   417: astore_3
    //   418: aload_3
    //   419: ifnull +5 -> 424
    //   422: aload_3
    //   423: athrow
    //   424: aload_2
    //   425: athrow
    //   426: aload_0
    //   427: invokevirtual 2238	android/content/Context:getResources	()Landroid/content/res/Resources;
    //   430: ldc_w 2254
    //   433: invokevirtual 2245	android/content/res/Resources:getString	(I)Ljava/lang/String;
    //   436: iconst_0
    //   437: iconst_5
    //   438: invokevirtual 2249	java/lang/String:substring	(II)Ljava/lang/String;
    //   441: iconst_2
    //   442: invokevirtual 2258	java/lang/String:codePointAt	(I)I
    //   445: iconst_4
    //   446: isub
    //   447: aload_0
    //   448: invokevirtual 2200	android/content/Context:getApplicationInfo	()Landroid/content/pm/ApplicationInfo;
    //   451: getfield 2205	android/content/pm/ApplicationInfo:targetSdkVersion	I
    //   454: sipush 341
    //   457: iadd
    //   458: aload_0
    //   459: invokevirtual 2238	android/content/Context:getResources	()Landroid/content/res/Resources;
    //   462: ldc_w 2323
    //   465: invokevirtual 2245	android/content/res/Resources:getString	(I)Ljava/lang/String;
    //   468: iconst_0
    //   469: iconst_4
    //   470: invokevirtual 2249	java/lang/String:substring	(II)Ljava/lang/String;
    //   473: invokevirtual 2253	java/lang/String:length	()I
    //   476: iconst_4
    //   477: isub
    //   478: i2c
    //   479: invokestatic 2264	o/O:ˋ	(IIC)Ljava/lang/Object;
    //   482: checkcast 2266	java/lang/Class
    //   485: ldc_w 2289
    //   488: aconst_null
    //   489: invokevirtual 2293	java/lang/Class:getMethod	(Ljava/lang/String;[Ljava/lang/Class;)Ljava/lang/reflect/Method;
    //   492: aload_2
    //   493: aconst_null
    //   494: invokevirtual 2299	java/lang/reflect/Method:invoke	(Ljava/lang/Object;[Ljava/lang/Object;)Ljava/lang/Object;
    //   497: astore_2
    //   498: aload_0
    //   499: invokevirtual 2287	android/content/Context:getPackageName	()Ljava/lang/String;
    //   502: invokevirtual 2253	java/lang/String:length	()I
    //   505: sipush 1759
    //   508: iadd
    //   509: aload_0
    //   510: invokevirtual 2200	android/content/Context:getApplicationInfo	()Landroid/content/pm/ApplicationInfo;
    //   513: getfield 2205	android/content/pm/ApplicationInfo:targetSdkVersion	I
    //   516: bipush 25
    //   518: isub
    //   519: i2c
    //   520: aload_0
    //   521: invokevirtual 2287	android/content/Context:getPackageName	()Ljava/lang/String;
    //   524: invokevirtual 2253	java/lang/String:length	()I
    //   527: sipush 381
    //   530: iadd
    //   531: invokestatic 2208	o/Dt:ˏ	(ICI)Ljava/lang/String;
    //   534: invokevirtual 2214	java/lang/String:intern	()Ljava/lang/String;
    //   537: astore_3
    //   538: goto +17 -> 555
    //   541: astore_2
    //   542: aload_2
    //   543: invokevirtual 2284	java/lang/Throwable:getCause	()Ljava/lang/Throwable;
    //   546: astore_3
    //   547: aload_3
    //   548: ifnull +5 -> 553
    //   551: aload_3
    //   552: athrow
    //   553: aload_2
    //   554: athrow
    //   555: aload_0
    //   556: invokevirtual 2238	android/content/Context:getResources	()Landroid/content/res/Resources;
    //   559: ldc_w 2324
    //   562: invokevirtual 2245	android/content/res/Resources:getString	(I)Ljava/lang/String;
    //   565: iconst_0
    //   566: iconst_4
    //   567: invokevirtual 2249	java/lang/String:substring	(II)Ljava/lang/String;
    //   570: iconst_1
    //   571: invokevirtual 2258	java/lang/String:codePointAt	(I)I
    //   574: bipush 22
    //   576: isub
    //   577: aload_0
    //   578: invokevirtual 2238	android/content/Context:getResources	()Landroid/content/res/Resources;
    //   581: ldc_w 2325
    //   584: invokevirtual 2245	android/content/res/Resources:getString	(I)Ljava/lang/String;
    //   587: iconst_0
    //   588: bipush 6
    //   590: invokevirtual 2249	java/lang/String:substring	(II)Ljava/lang/String;
    //   593: invokevirtual 2253	java/lang/String:length	()I
    //   596: sipush 356
    //   599: iadd
    //   600: aload_0
    //   601: invokevirtual 2287	android/content/Context:getPackageName	()Ljava/lang/String;
    //   604: iconst_2
    //   605: invokevirtual 2258	java/lang/String:codePointAt	(I)I
    //   608: ldc_w 2326
    //   611: iadd
    //   612: i2c
    //   613: invokestatic 2264	o/O:ˋ	(IIC)Ljava/lang/Object;
    //   616: checkcast 2266	java/lang/Class
    //   619: ldc_w 2268
    //   622: iconst_1
    //   623: anewarray 2266	java/lang/Class
    //   626: dup
    //   627: iconst_0
    //   628: ldc_w 2210
    //   631: aastore
    //   632: invokevirtual 2293	java/lang/Class:getMethod	(Ljava/lang/String;[Ljava/lang/Class;)Ljava/lang/reflect/Method;
    //   635: aload_2
    //   636: iconst_1
    //   637: anewarray 2322	java/lang/Object
    //   640: dup
    //   641: iconst_0
    //   642: aload_3
    //   643: aastore
    //   644: invokevirtual 2299	java/lang/reflect/Method:invoke	(Ljava/lang/Object;[Ljava/lang/Object;)Ljava/lang/Object;
    //   647: pop
    //   648: goto -626 -> 22
    //   651: iload_1
    //   652: lookupswitch	default:+28->680, 45:+29->681, 84:+-643->9
    //   680: return
    //   681: aconst_null
    //   682: arraylength
    //   683: istore_1
    //   684: return
    //   685: astore_2
    //   686: aload_2
    //   687: athrow
    //   688: getstatic 23	o/Dt:ʼ	I
    //   691: bipush 85
    //   693: iadd
    //   694: istore_1
    //   695: iload_1
    //   696: sipush 128
    //   699: irem
    //   700: putstatic 21	o/Dt:ॱॱ	I
    //   703: iload_1
    //   704: iconst_2
    //   705: irem
    //   706: ifeq +6 -> 712
    //   709: goto -690 -> 19
    //   712: goto -663 -> 49
    // Local variable table:
    //   start	length	slot	name	signature
    //   0	715	0	this	Dt
    //   5	701	1	i	int
    //   108	1	2	localObject1	Object
    //   112	72	2	localObject2	Object
    //   188	1	2	localObject3	Object
    //   256	91	2	localObject4	Object
    //   408	1	2	localObject5	Object
    //   412	81	2	localObject6	Object
    //   497	1	2	localObject7	Object
    //   541	95	2	localObject8	Object
    //   685	2	2	localException	Exception
    //   117	526	3	localObject9	Object
    // Exception table:
    //   from	to	target	type
    //   126	189	112	finally
    //   270	359	256	finally
    //   426	498	412	finally
    //   555	648	541	finally
    //   22	29	685	java/lang/Exception
    //   29	37	685	java/lang/Exception
  }
  
  /* Error */
  private boolean ॱˎ()
  {
    // Byte code:
    //   0: goto +757 -> 757
    //   3: bipush 52
    //   5: istore_1
    //   6: goto +671 -> 677
    //   9: getstatic 21	o/Dt:ॱॱ	I
    //   12: bipush 85
    //   14: iadd
    //   15: istore_1
    //   16: iload_1
    //   17: sipush 128
    //   20: irem
    //   21: putstatic 23	o/Dt:ʼ	I
    //   24: iload_1
    //   25: iconst_2
    //   26: irem
    //   27: ifne +6 -> 33
    //   30: goto +713 -> 743
    //   33: goto +244 -> 277
    //   36: getstatic 23	o/Dt:ʼ	I
    //   39: bipush 73
    //   41: iadd
    //   42: istore_1
    //   43: iload_1
    //   44: sipush 128
    //   47: irem
    //   48: putstatic 21	o/Dt:ॱॱ	I
    //   51: iload_1
    //   52: iconst_2
    //   53: irem
    //   54: ifeq +6 -> 60
    //   57: goto +217 -> 274
    //   60: goto +735 -> 795
    //   63: goto +20 -> 83
    //   66: astore_3
    //   67: aload_3
    //   68: invokevirtual 2284	java/lang/Throwable:getCause	()Ljava/lang/Throwable;
    //   71: astore 4
    //   73: aload 4
    //   75: ifnull +6 -> 81
    //   78: aload 4
    //   80: athrow
    //   81: aload_3
    //   82: athrow
    //   83: aload_0
    //   84: invokevirtual 2287	android/content/Context:getPackageName	()Ljava/lang/String;
    //   87: iconst_1
    //   88: invokevirtual 2258	java/lang/String:codePointAt	(I)I
    //   91: bipush 107
    //   93: isub
    //   94: aload_0
    //   95: invokevirtual 2287	android/content/Context:getPackageName	()Ljava/lang/String;
    //   98: bipush 8
    //   100: invokevirtual 2258	java/lang/String:codePointAt	(I)I
    //   103: sipush 155
    //   106: iadd
    //   107: aload_0
    //   108: invokevirtual 2238	android/content/Context:getResources	()Landroid/content/res/Resources;
    //   111: ldc_w 2329
    //   114: invokevirtual 2245	android/content/res/Resources:getString	(I)Ljava/lang/String;
    //   117: bipush 7
    //   119: bipush 13
    //   121: invokevirtual 2249	java/lang/String:substring	(II)Ljava/lang/String;
    //   124: iconst_2
    //   125: invokevirtual 2258	java/lang/String:codePointAt	(I)I
    //   128: sipush 14554
    //   131: iadd
    //   132: i2c
    //   133: invokestatic 2264	o/O:ˋ	(IIC)Ljava/lang/Object;
    //   136: checkcast 2266	java/lang/Class
    //   139: ldc_w 2289
    //   142: aconst_null
    //   143: invokevirtual 2293	java/lang/Class:getMethod	(Ljava/lang/String;[Ljava/lang/Class;)Ljava/lang/reflect/Method;
    //   146: aconst_null
    //   147: aconst_null
    //   148: invokevirtual 2299	java/lang/reflect/Method:invoke	(Ljava/lang/Object;[Ljava/lang/Object;)Ljava/lang/Object;
    //   151: astore_3
    //   152: goto +20 -> 172
    //   155: astore_3
    //   156: aload_3
    //   157: invokevirtual 2284	java/lang/Throwable:getCause	()Ljava/lang/Throwable;
    //   160: astore 4
    //   162: aload 4
    //   164: ifnull +6 -> 170
    //   167: aload 4
    //   169: athrow
    //   170: aload_3
    //   171: athrow
    //   172: aload_0
    //   173: invokevirtual 2238	android/content/Context:getResources	()Landroid/content/res/Resources;
    //   176: ldc_w 2330
    //   179: invokevirtual 2245	android/content/res/Resources:getString	(I)Ljava/lang/String;
    //   182: bipush 33
    //   184: bipush 34
    //   186: invokevirtual 2249	java/lang/String:substring	(II)Ljava/lang/String;
    //   189: invokevirtual 2253	java/lang/String:length	()I
    //   192: iconst_3
    //   193: iadd
    //   194: aload_0
    //   195: invokevirtual 2238	android/content/Context:getResources	()Landroid/content/res/Resources;
    //   198: ldc_w 2331
    //   201: invokevirtual 2245	android/content/res/Resources:getString	(I)Ljava/lang/String;
    //   204: iconst_0
    //   205: iconst_4
    //   206: invokevirtual 2249	java/lang/String:substring	(II)Ljava/lang/String;
    //   209: invokevirtual 2253	java/lang/String:length	()I
    //   212: sipush 263
    //   215: iadd
    //   216: aload_0
    //   217: invokevirtual 2238	android/content/Context:getResources	()Landroid/content/res/Resources;
    //   220: ldc_w 2313
    //   223: invokevirtual 2245	android/content/res/Resources:getString	(I)Ljava/lang/String;
    //   226: iconst_0
    //   227: iconst_1
    //   228: invokevirtual 2249	java/lang/String:substring	(II)Ljava/lang/String;
    //   231: invokevirtual 2253	java/lang/String:length	()I
    //   234: sipush 14787
    //   237: iadd
    //   238: i2c
    //   239: invokestatic 2264	o/O:ˋ	(IIC)Ljava/lang/Object;
    //   242: checkcast 2266	java/lang/Class
    //   245: ldc_w 2332
    //   248: aconst_null
    //   249: invokevirtual 2293	java/lang/Class:getMethod	(Ljava/lang/String;[Ljava/lang/Class;)Ljava/lang/reflect/Method;
    //   252: aload_3
    //   253: aconst_null
    //   254: invokevirtual 2299	java/lang/reflect/Method:invoke	(Ljava/lang/Object;[Ljava/lang/Object;)Ljava/lang/Object;
    //   257: checkcast 2334	java/lang/Boolean
    //   260: invokevirtual 2337	java/lang/Boolean:booleanValue	()Z
    //   263: pop
    //   264: aload_0
    //   265: invokespecial 2339	o/Dt:ॱˋ	()V
    //   268: goto -259 -> 9
    //   271: goto -235 -> 36
    //   274: goto +521 -> 795
    //   277: iconst_1
    //   278: ireturn
    //   279: goto +20 -> 299
    //   282: astore_3
    //   283: aload_3
    //   284: invokevirtual 2284	java/lang/Throwable:getCause	()Ljava/lang/Throwable;
    //   287: astore 4
    //   289: aload 4
    //   291: ifnull +6 -> 297
    //   294: aload 4
    //   296: athrow
    //   297: aload_3
    //   298: athrow
    //   299: aload_0
    //   300: invokevirtual 2238	android/content/Context:getResources	()Landroid/content/res/Resources;
    //   303: ldc_w 2340
    //   306: invokevirtual 2245	android/content/res/Resources:getString	(I)Ljava/lang/String;
    //   309: iconst_0
    //   310: iconst_4
    //   311: invokevirtual 2249	java/lang/String:substring	(II)Ljava/lang/String;
    //   314: invokevirtual 2253	java/lang/String:length	()I
    //   317: iconst_0
    //   318: iadd
    //   319: aload_0
    //   320: invokevirtual 2200	android/content/Context:getApplicationInfo	()Landroid/content/pm/ApplicationInfo;
    //   323: getfield 2205	android/content/pm/ApplicationInfo:targetSdkVersion	I
    //   326: sipush 242
    //   329: iadd
    //   330: aload_0
    //   331: invokevirtual 2200	android/content/Context:getApplicationInfo	()Landroid/content/pm/ApplicationInfo;
    //   334: getfield 2205	android/content/pm/ApplicationInfo:targetSdkVersion	I
    //   337: sipush 14763
    //   340: iadd
    //   341: i2c
    //   342: invokestatic 2264	o/O:ˋ	(IIC)Ljava/lang/Object;
    //   345: checkcast 2266	java/lang/Class
    //   348: ldc_w 2289
    //   351: aconst_null
    //   352: invokevirtual 2293	java/lang/Class:getMethod	(Ljava/lang/String;[Ljava/lang/Class;)Ljava/lang/reflect/Method;
    //   355: aconst_null
    //   356: aconst_null
    //   357: invokevirtual 2299	java/lang/reflect/Method:invoke	(Ljava/lang/Object;[Ljava/lang/Object;)Ljava/lang/Object;
    //   360: astore_3
    //   361: goto +20 -> 381
    //   364: astore_3
    //   365: aload_3
    //   366: invokevirtual 2284	java/lang/Throwable:getCause	()Ljava/lang/Throwable;
    //   369: astore 4
    //   371: aload 4
    //   373: ifnull +6 -> 379
    //   376: aload 4
    //   378: athrow
    //   379: aload_3
    //   380: athrow
    //   381: aload_0
    //   382: invokevirtual 2238	android/content/Context:getResources	()Landroid/content/res/Resources;
    //   385: ldc_w 2341
    //   388: invokevirtual 2245	android/content/res/Resources:getString	(I)Ljava/lang/String;
    //   391: bipush 11
    //   393: bipush 13
    //   395: invokevirtual 2249	java/lang/String:substring	(II)Ljava/lang/String;
    //   398: iconst_0
    //   399: invokevirtual 2258	java/lang/String:codePointAt	(I)I
    //   402: bipush 104
    //   404: isub
    //   405: aload_0
    //   406: invokevirtual 2200	android/content/Context:getApplicationInfo	()Landroid/content/pm/ApplicationInfo;
    //   409: getfield 2205	android/content/pm/ApplicationInfo:targetSdkVersion	I
    //   412: sipush 242
    //   415: iadd
    //   416: aload_0
    //   417: invokevirtual 2200	android/content/Context:getApplicationInfo	()Landroid/content/pm/ApplicationInfo;
    //   420: getfield 2205	android/content/pm/ApplicationInfo:targetSdkVersion	I
    //   423: sipush 14763
    //   426: iadd
    //   427: i2c
    //   428: invokestatic 2264	o/O:ˋ	(IIC)Ljava/lang/Object;
    //   431: checkcast 2266	java/lang/Class
    //   434: ldc_w 2342
    //   437: aconst_null
    //   438: invokevirtual 2293	java/lang/Class:getMethod	(Ljava/lang/String;[Ljava/lang/Class;)Ljava/lang/reflect/Method;
    //   441: aload_3
    //   442: aconst_null
    //   443: invokevirtual 2299	java/lang/reflect/Method:invoke	(Ljava/lang/Object;[Ljava/lang/Object;)Ljava/lang/Object;
    //   446: checkcast 2334	java/lang/Boolean
    //   449: invokevirtual 2337	java/lang/Boolean:booleanValue	()Z
    //   452: istore_2
    //   453: iload_2
    //   454: ifeq +6 -> 460
    //   457: goto -394 -> 63
    //   460: goto -189 -> 271
    //   463: goto +20 -> 483
    //   466: astore_3
    //   467: aload_3
    //   468: invokevirtual 2284	java/lang/Throwable:getCause	()Ljava/lang/Throwable;
    //   471: astore 4
    //   473: aload 4
    //   475: ifnull +6 -> 481
    //   478: aload 4
    //   480: athrow
    //   481: aload_3
    //   482: athrow
    //   483: aload_0
    //   484: invokevirtual 2238	android/content/Context:getResources	()Landroid/content/res/Resources;
    //   487: ldc_w 2341
    //   490: invokevirtual 2245	android/content/res/Resources:getString	(I)Ljava/lang/String;
    //   493: bipush 11
    //   495: bipush 13
    //   497: invokevirtual 2249	java/lang/String:substring	(II)Ljava/lang/String;
    //   500: iconst_1
    //   501: invokevirtual 2258	java/lang/String:codePointAt	(I)I
    //   504: bipush 28
    //   506: isub
    //   507: aload_0
    //   508: invokevirtual 2200	android/content/Context:getApplicationInfo	()Landroid/content/pm/ApplicationInfo;
    //   511: getfield 2205	android/content/pm/ApplicationInfo:targetSdkVersion	I
    //   514: sipush 242
    //   517: iadd
    //   518: aload_0
    //   519: invokevirtual 2238	android/content/Context:getResources	()Landroid/content/res/Resources;
    //   522: ldc_w 2343
    //   525: invokevirtual 2245	android/content/res/Resources:getString	(I)Ljava/lang/String;
    //   528: iconst_0
    //   529: iconst_4
    //   530: invokevirtual 2249	java/lang/String:substring	(II)Ljava/lang/String;
    //   533: iconst_0
    //   534: invokevirtual 2258	java/lang/String:codePointAt	(I)I
    //   537: sipush 14783
    //   540: iadd
    //   541: i2c
    //   542: invokestatic 2264	o/O:ˋ	(IIC)Ljava/lang/Object;
    //   545: checkcast 2266	java/lang/Class
    //   548: ldc_w 2289
    //   551: aconst_null
    //   552: invokevirtual 2293	java/lang/Class:getMethod	(Ljava/lang/String;[Ljava/lang/Class;)Ljava/lang/reflect/Method;
    //   555: aconst_null
    //   556: aconst_null
    //   557: invokevirtual 2299	java/lang/reflect/Method:invoke	(Ljava/lang/Object;[Ljava/lang/Object;)Ljava/lang/Object;
    //   560: astore_3
    //   561: goto +20 -> 581
    //   564: astore_3
    //   565: aload_3
    //   566: invokevirtual 2284	java/lang/Throwable:getCause	()Ljava/lang/Throwable;
    //   569: astore 4
    //   571: aload 4
    //   573: ifnull +6 -> 579
    //   576: aload 4
    //   578: athrow
    //   579: aload_3
    //   580: athrow
    //   581: aload_0
    //   582: invokevirtual 2238	android/content/Context:getResources	()Landroid/content/res/Resources;
    //   585: ldc_w 2314
    //   588: invokevirtual 2245	android/content/res/Resources:getString	(I)Ljava/lang/String;
    //   591: iconst_0
    //   592: iconst_5
    //   593: invokevirtual 2249	java/lang/String:substring	(II)Ljava/lang/String;
    //   596: iconst_3
    //   597: invokevirtual 2258	java/lang/String:codePointAt	(I)I
    //   600: bipush 8
    //   602: isub
    //   603: aload_0
    //   604: invokevirtual 2287	android/content/Context:getPackageName	()Ljava/lang/String;
    //   607: iconst_4
    //   608: invokevirtual 2258	java/lang/String:codePointAt	(I)I
    //   611: sipush 151
    //   614: iadd
    //   615: aload_0
    //   616: invokevirtual 2238	android/content/Context:getResources	()Landroid/content/res/Resources;
    //   619: ldc_w 2344
    //   622: invokevirtual 2245	android/content/res/Resources:getString	(I)Ljava/lang/String;
    //   625: iconst_0
    //   626: iconst_5
    //   627: invokevirtual 2249	java/lang/String:substring	(II)Ljava/lang/String;
    //   630: iconst_2
    //   631: invokevirtual 2258	java/lang/String:codePointAt	(I)I
    //   634: sipush 14777
    //   637: iadd
    //   638: i2c
    //   639: invokestatic 2264	o/O:ˋ	(IIC)Ljava/lang/Object;
    //   642: checkcast 2266	java/lang/Class
    //   645: ldc_w 2342
    //   648: aconst_null
    //   649: invokevirtual 2293	java/lang/Class:getMethod	(Ljava/lang/String;[Ljava/lang/Class;)Ljava/lang/reflect/Method;
    //   652: aload_3
    //   653: aconst_null
    //   654: invokevirtual 2299	java/lang/reflect/Method:invoke	(Ljava/lang/Object;[Ljava/lang/Object;)Ljava/lang/Object;
    //   657: checkcast 2334	java/lang/Boolean
    //   660: invokevirtual 2337	java/lang/Boolean:booleanValue	()Z
    //   663: istore_2
    //   664: aconst_null
    //   665: arraylength
    //   666: istore_1
    //   667: iload_2
    //   668: ifeq +6 -> 674
    //   671: goto -668 -> 3
    //   674: goto +60 -> 734
    //   677: iload_1
    //   678: lookupswitch	default:+26->704, 20:+-407->271, 52:+-615->63
    //   704: goto -641 -> 63
    //   707: getstatic 21	o/Dt:ॱॱ	I
    //   710: bipush 123
    //   712: iadd
    //   713: istore_1
    //   714: iload_1
    //   715: sipush 128
    //   718: irem
    //   719: putstatic 23	o/Dt:ʼ	I
    //   722: iload_1
    //   723: iconst_2
    //   724: irem
    //   725: ifne +6 -> 731
    //   728: goto +32 -> 760
    //   731: goto +17 -> 748
    //   734: bipush 20
    //   736: istore_1
    //   737: goto -60 -> 677
    //   740: astore_3
    //   741: aload_3
    //   742: athrow
    //   743: aconst_null
    //   744: arraylength
    //   745: istore_1
    //   746: iconst_1
    //   747: ireturn
    //   748: bipush 66
    //   750: istore_1
    //   751: goto +12 -> 763
    //   754: astore_3
    //   755: aload_3
    //   756: athrow
    //   757: goto -50 -> 707
    //   760: bipush 23
    //   762: istore_1
    //   763: iload_1
    //   764: lookupswitch	default:+28->792, 23:+-301->463, 66:+-485->279
    //   792: goto -513 -> 279
    //   795: iconst_0
    //   796: ireturn
    // Local variable table:
    //   start	length	slot	name	signature
    //   0	797	0	this	Dt
    //   5	759	1	i	int
    //   452	216	2	bool	boolean
    //   66	16	3	localObject1	Object
    //   151	1	3	localObject2	Object
    //   155	98	3	localObject3	Object
    //   282	16	3	localObject4	Object
    //   360	1	3	localObject5	Object
    //   364	78	3	localObject6	Object
    //   466	16	3	localObject7	Object
    //   560	1	3	localObject8	Object
    //   564	89	3	localObject9	Object
    //   740	2	3	localException1	Exception
    //   754	2	3	localException2	Exception
    //   71	506	4	localThrowable	Throwable
    // Exception table:
    //   from	to	target	type
    //   83	152	66	finally
    //   172	264	155	finally
    //   299	361	282	finally
    //   381	453	364	finally
    //   483	561	466	finally
    //   581	664	564	finally
    //   365	371	740	java/lang/Exception
    //   376	379	740	java/lang/Exception
    //   379	381	740	java/lang/Exception
    //   67	73	754	java/lang/Exception
    //   78	81	754	java/lang/Exception
    //   81	83	754	java/lang/Exception
    //   156	162	754	java/lang/Exception
    //   167	170	754	java/lang/Exception
    //   170	172	754	java/lang/Exception
    //   264	268	754	java/lang/Exception
    //   283	289	754	java/lang/Exception
    //   294	297	754	java/lang/Exception
    //   297	299	754	java/lang/Exception
    //   365	371	754	java/lang/Exception
    //   376	379	754	java/lang/Exception
    //   379	381	754	java/lang/Exception
  }
  
  /* Error */
  public static Dt ॱॱ()
  {
    // Byte code:
    //   0: goto +87 -> 87
    //   3: astore_1
    //   4: aload_1
    //   5: athrow
    //   6: getstatic 23	o/Dt:ʼ	I
    //   9: bipush 91
    //   11: iadd
    //   12: istore_0
    //   13: iload_0
    //   14: sipush 128
    //   17: irem
    //   18: putstatic 21	o/Dt:ॱॱ	I
    //   21: iload_0
    //   22: iconst_2
    //   23: irem
    //   24: ifeq +6 -> 30
    //   27: goto +75 -> 102
    //   30: goto +60 -> 90
    //   33: getstatic 21	o/Dt:ॱॱ	I
    //   36: bipush 61
    //   38: iadd
    //   39: istore_0
    //   40: iload_0
    //   41: sipush 128
    //   44: irem
    //   45: putstatic 23	o/Dt:ʼ	I
    //   48: iload_0
    //   49: iconst_2
    //   50: irem
    //   51: ifne +6 -> 57
    //   54: goto +5 -> 59
    //   57: aload_1
    //   58: areturn
    //   59: aload_1
    //   60: areturn
    //   61: iload_0
    //   62: tableswitch	default:+22->84, 0:+45->107, 1:+33->95
    //   84: goto +23 -> 107
    //   87: goto -81 -> 6
    //   90: iconst_1
    //   91: istore_0
    //   92: goto -31 -> 61
    //   95: getstatic 2347	o/Dt:ˏ	Lo/Dt;
    //   98: astore_1
    //   99: goto -66 -> 33
    //   102: iconst_0
    //   103: istore_0
    //   104: goto -43 -> 61
    //   107: getstatic 2347	o/Dt:ˏ	Lo/Dt;
    //   110: astore_1
    //   111: aconst_null
    //   112: arraylength
    //   113: istore_0
    //   114: goto -81 -> 33
    // Local variable table:
    //   start	length	slot	name	signature
    //   12	102	0	i	int
    //   3	57	1	localException	Exception
    //   98	13	1	localDt	Dt
    // Exception table:
    //   from	to	target	type
    //   33	40	3	java/lang/Exception
    //   40	48	3	java/lang/Exception
  }
  
  /* Error */
  private void ॱᐝ()
  {
    // Byte code:
    //   0: goto +866 -> 866
    //   3: iconst_0
    //   4: istore_1
    //   5: goto +1532 -> 1537
    //   8: getstatic 23	o/Dt:ʼ	I
    //   11: bipush 119
    //   13: iadd
    //   14: istore_1
    //   15: iload_1
    //   16: sipush 128
    //   19: irem
    //   20: putstatic 21	o/Dt:ॱॱ	I
    //   23: iload_1
    //   24: iconst_2
    //   25: irem
    //   26: ifeq +6 -> 32
    //   29: goto +2073 -> 2102
    //   32: goto +1057 -> 1089
    //   35: goto +1543 -> 1578
    //   38: aload_0
    //   39: invokevirtual 2238	android/content/Context:getResources	()Landroid/content/res/Resources;
    //   42: ldc_w 2351
    //   45: invokevirtual 2245	android/content/res/Resources:getString	(I)Ljava/lang/String;
    //   48: bipush 7
    //   50: bipush 17
    //   52: invokevirtual 2249	java/lang/String:substring	(II)Ljava/lang/String;
    //   55: bipush 6
    //   57: invokevirtual 2258	java/lang/String:codePointAt	(I)I
    //   60: sipush 244
    //   63: isub
    //   64: aload_0
    //   65: invokevirtual 2238	android/content/Context:getResources	()Landroid/content/res/Resources;
    //   68: ldc_w 2352
    //   71: invokevirtual 2245	android/content/res/Resources:getString	(I)Ljava/lang/String;
    //   74: iconst_0
    //   75: iconst_4
    //   76: invokevirtual 2249	java/lang/String:substring	(II)Ljava/lang/String;
    //   79: invokevirtual 2253	java/lang/String:length	()I
    //   82: iconst_1
    //   83: isub
    //   84: aload_0
    //   85: invokevirtual 2200	android/content/Context:getApplicationInfo	()Landroid/content/pm/ApplicationInfo;
    //   88: getfield 2205	android/content/pm/ApplicationInfo:targetSdkVersion	I
    //   91: bipush 25
    //   93: isub
    //   94: i2c
    //   95: invokestatic 2264	o/O:ˋ	(IIC)Ljava/lang/Object;
    //   98: checkcast 2266	java/lang/Class
    //   101: ldc_w 2268
    //   104: invokevirtual 2272	java/lang/Class:getField	(Ljava/lang/String;)Ljava/lang/reflect/Field;
    //   107: aconst_null
    //   108: invokevirtual 2278	java/lang/reflect/Field:get	(Ljava/lang/Object;)Ljava/lang/Object;
    //   111: astore_3
    //   112: goto +20 -> 132
    //   115: astore_3
    //   116: aload_3
    //   117: invokevirtual 2284	java/lang/Throwable:getCause	()Ljava/lang/Throwable;
    //   120: astore 4
    //   122: aload 4
    //   124: ifnull +6 -> 130
    //   127: aload 4
    //   129: athrow
    //   130: aload_3
    //   131: athrow
    //   132: aload_0
    //   133: invokevirtual 2200	android/content/Context:getApplicationInfo	()Landroid/content/pm/ApplicationInfo;
    //   136: getfield 2205	android/content/pm/ApplicationInfo:targetSdkVersion	I
    //   139: bipush 19
    //   141: isub
    //   142: aload_0
    //   143: invokevirtual 2200	android/content/Context:getApplicationInfo	()Landroid/content/pm/ApplicationInfo;
    //   146: getfield 2205	android/content/pm/ApplicationInfo:targetSdkVersion	I
    //   149: bipush 19
    //   151: isub
    //   152: aload_0
    //   153: invokevirtual 2287	android/content/Context:getPackageName	()Ljava/lang/String;
    //   156: iconst_5
    //   157: invokevirtual 2258	java/lang/String:codePointAt	(I)I
    //   160: sipush 10426
    //   163: iadd
    //   164: i2c
    //   165: invokestatic 2264	o/O:ˋ	(IIC)Ljava/lang/Object;
    //   168: checkcast 2266	java/lang/Class
    //   171: ldc_w 2353
    //   174: aconst_null
    //   175: invokevirtual 2293	java/lang/Class:getMethod	(Ljava/lang/String;[Ljava/lang/Class;)Ljava/lang/reflect/Method;
    //   178: aload_3
    //   179: aconst_null
    //   180: invokevirtual 2299	java/lang/reflect/Method:invoke	(Ljava/lang/Object;[Ljava/lang/Object;)Ljava/lang/Object;
    //   183: astore_3
    //   184: goto +20 -> 204
    //   187: astore 4
    //   189: aload 4
    //   191: invokevirtual 2284	java/lang/Throwable:getCause	()Ljava/lang/Throwable;
    //   194: astore_3
    //   195: aload_3
    //   196: ifnull +5 -> 201
    //   199: aload_3
    //   200: athrow
    //   201: aload 4
    //   203: athrow
    //   204: aload_0
    //   205: invokevirtual 2200	android/content/Context:getApplicationInfo	()Landroid/content/pm/ApplicationInfo;
    //   208: getfield 2205	android/content/pm/ApplicationInfo:targetSdkVersion	I
    //   211: bipush 22
    //   213: isub
    //   214: aload_0
    //   215: invokevirtual 2238	android/content/Context:getResources	()Landroid/content/res/Resources;
    //   218: ldc_w 2354
    //   221: invokevirtual 2245	android/content/res/Resources:getString	(I)Ljava/lang/String;
    //   224: iconst_0
    //   225: iconst_5
    //   226: invokevirtual 2249	java/lang/String:substring	(II)Ljava/lang/String;
    //   229: invokevirtual 2253	java/lang/String:length	()I
    //   232: iconst_2
    //   233: isub
    //   234: aload_0
    //   235: invokevirtual 2238	android/content/Context:getResources	()Landroid/content/res/Resources;
    //   238: ldc_w 2355
    //   241: invokevirtual 2245	android/content/res/Resources:getString	(I)Ljava/lang/String;
    //   244: iconst_0
    //   245: iconst_4
    //   246: invokevirtual 2249	java/lang/String:substring	(II)Ljava/lang/String;
    //   249: invokevirtual 2253	java/lang/String:length	()I
    //   252: iconst_4
    //   253: isub
    //   254: i2c
    //   255: invokestatic 2264	o/O:ˋ	(IIC)Ljava/lang/Object;
    //   258: checkcast 2266	java/lang/Class
    //   261: ldc_w 2289
    //   264: aconst_null
    //   265: invokevirtual 2293	java/lang/Class:getMethod	(Ljava/lang/String;[Ljava/lang/Class;)Ljava/lang/reflect/Method;
    //   268: aload_3
    //   269: aconst_null
    //   270: invokevirtual 2299	java/lang/reflect/Method:invoke	(Ljava/lang/Object;[Ljava/lang/Object;)Ljava/lang/Object;
    //   273: checkcast 2357	o/uB
    //   276: astore 4
    //   278: aload 4
    //   280: invokevirtual 2360	o/uB:ˋ	()Ljava/lang/Object;
    //   283: checkcast 2362	javax/crypto/SecretKey
    //   286: invokeinterface 2366 1 0
    //   291: iconst_2
    //   292: invokestatic 2372	android/util/Base64:encodeToString	([BI)Ljava/lang/String;
    //   295: astore_3
    //   296: aload 4
    //   298: invokevirtual 2374	o/uB:ˎ	()Ljava/lang/Object;
    //   301: checkcast 2362	javax/crypto/SecretKey
    //   304: invokeinterface 2366 1 0
    //   309: iconst_2
    //   310: invokestatic 2372	android/util/Base64:encodeToString	([BI)Ljava/lang/String;
    //   313: astore 4
    //   315: aload_0
    //   316: invokevirtual 2200	android/content/Context:getApplicationInfo	()Landroid/content/pm/ApplicationInfo;
    //   319: getfield 2205	android/content/pm/ApplicationInfo:targetSdkVersion	I
    //   322: bipush 21
    //   324: isub
    //   325: aload_0
    //   326: invokevirtual 2238	android/content/Context:getResources	()Landroid/content/res/Resources;
    //   329: ldc_w 2375
    //   332: invokevirtual 2245	android/content/res/Resources:getString	(I)Ljava/lang/String;
    //   335: iconst_0
    //   336: iconst_4
    //   337: invokevirtual 2249	java/lang/String:substring	(II)Ljava/lang/String;
    //   340: invokevirtual 2253	java/lang/String:length	()I
    //   343: sipush 358
    //   346: iadd
    //   347: aload_0
    //   348: invokevirtual 2238	android/content/Context:getResources	()Landroid/content/res/Resources;
    //   351: ldc_w 2376
    //   354: invokevirtual 2245	android/content/res/Resources:getString	(I)Ljava/lang/String;
    //   357: iconst_0
    //   358: bipush 6
    //   360: invokevirtual 2249	java/lang/String:substring	(II)Ljava/lang/String;
    //   363: iconst_4
    //   364: invokevirtual 2258	java/lang/String:codePointAt	(I)I
    //   367: ldc_w 2377
    //   370: iadd
    //   371: i2c
    //   372: invokestatic 2264	o/O:ˋ	(IIC)Ljava/lang/Object;
    //   375: checkcast 2266	java/lang/Class
    //   378: ldc_w 2268
    //   381: invokevirtual 2272	java/lang/Class:getField	(Ljava/lang/String;)Ljava/lang/reflect/Field;
    //   384: aconst_null
    //   385: invokevirtual 2278	java/lang/reflect/Field:get	(Ljava/lang/Object;)Ljava/lang/Object;
    //   388: astore 5
    //   390: goto +20 -> 410
    //   393: astore_3
    //   394: aload_3
    //   395: invokevirtual 2284	java/lang/Throwable:getCause	()Ljava/lang/Throwable;
    //   398: astore 4
    //   400: aload 4
    //   402: ifnull +6 -> 408
    //   405: aload 4
    //   407: athrow
    //   408: aload_3
    //   409: athrow
    //   410: aload_0
    //   411: invokevirtual 2200	android/content/Context:getApplicationInfo	()Landroid/content/pm/ApplicationInfo;
    //   414: getfield 2205	android/content/pm/ApplicationInfo:targetSdkVersion	I
    //   417: bipush 18
    //   419: isub
    //   420: aload_0
    //   421: invokevirtual 2200	android/content/Context:getApplicationInfo	()Landroid/content/pm/ApplicationInfo;
    //   424: getfield 2205	android/content/pm/ApplicationInfo:targetSdkVersion	I
    //   427: sipush 341
    //   430: iadd
    //   431: aload_0
    //   432: invokevirtual 2287	android/content/Context:getPackageName	()Ljava/lang/String;
    //   435: invokevirtual 2253	java/lang/String:length	()I
    //   438: bipush 11
    //   440: isub
    //   441: i2c
    //   442: invokestatic 2264	o/O:ˋ	(IIC)Ljava/lang/Object;
    //   445: checkcast 2266	java/lang/Class
    //   448: ldc_w 2289
    //   451: aconst_null
    //   452: invokevirtual 2293	java/lang/Class:getMethod	(Ljava/lang/String;[Ljava/lang/Class;)Ljava/lang/reflect/Method;
    //   455: aload 5
    //   457: aconst_null
    //   458: invokevirtual 2299	java/lang/reflect/Method:invoke	(Ljava/lang/Object;[Ljava/lang/Object;)Ljava/lang/Object;
    //   461: astore 5
    //   463: goto +20 -> 483
    //   466: astore 4
    //   468: aload 4
    //   470: invokevirtual 2284	java/lang/Throwable:getCause	()Ljava/lang/Throwable;
    //   473: astore_3
    //   474: aload_3
    //   475: ifnull +5 -> 480
    //   478: aload_3
    //   479: athrow
    //   480: aload 4
    //   482: athrow
    //   483: aload_0
    //   484: invokevirtual 2287	android/content/Context:getPackageName	()Ljava/lang/String;
    //   487: iconst_5
    //   488: invokevirtual 2258	java/lang/String:codePointAt	(I)I
    //   491: bipush 110
    //   493: isub
    //   494: aload_0
    //   495: invokevirtual 2287	android/content/Context:getPackageName	()Ljava/lang/String;
    //   498: iconst_3
    //   499: invokevirtual 2258	java/lang/String:codePointAt	(I)I
    //   502: sipush 264
    //   505: iadd
    //   506: aload_0
    //   507: invokevirtual 2238	android/content/Context:getResources	()Landroid/content/res/Resources;
    //   510: ldc_w 2378
    //   513: invokevirtual 2245	android/content/res/Resources:getString	(I)Ljava/lang/String;
    //   516: iconst_0
    //   517: bipush 10
    //   519: invokevirtual 2249	java/lang/String:substring	(II)Ljava/lang/String;
    //   522: iconst_4
    //   523: invokevirtual 2258	java/lang/String:codePointAt	(I)I
    //   526: ldc_w 2379
    //   529: iadd
    //   530: i2c
    //   531: invokestatic 2264	o/O:ˋ	(IIC)Ljava/lang/Object;
    //   534: checkcast 2266	java/lang/Class
    //   537: ldc_w 2381
    //   540: iconst_1
    //   541: anewarray 2266	java/lang/Class
    //   544: dup
    //   545: iconst_0
    //   546: ldc_w 2210
    //   549: aastore
    //   550: invokevirtual 2293	java/lang/Class:getMethod	(Ljava/lang/String;[Ljava/lang/Class;)Ljava/lang/reflect/Method;
    //   553: aload 5
    //   555: iconst_1
    //   556: anewarray 2322	java/lang/Object
    //   559: dup
    //   560: iconst_0
    //   561: aload_3
    //   562: aastore
    //   563: invokevirtual 2299	java/lang/reflect/Method:invoke	(Ljava/lang/Object;[Ljava/lang/Object;)Ljava/lang/Object;
    //   566: pop
    //   567: aload_0
    //   568: invokevirtual 2200	android/content/Context:getApplicationInfo	()Landroid/content/pm/ApplicationInfo;
    //   571: getfield 2205	android/content/pm/ApplicationInfo:targetSdkVersion	I
    //   574: bipush 21
    //   576: isub
    //   577: aload_0
    //   578: invokevirtual 2200	android/content/Context:getApplicationInfo	()Landroid/content/pm/ApplicationInfo;
    //   581: getfield 2205	android/content/pm/ApplicationInfo:targetSdkVersion	I
    //   584: sipush 337
    //   587: iadd
    //   588: aload_0
    //   589: invokevirtual 2200	android/content/Context:getApplicationInfo	()Landroid/content/pm/ApplicationInfo;
    //   592: getfield 2205	android/content/pm/ApplicationInfo:targetSdkVersion	I
    //   595: ldc_w 2302
    //   598: iadd
    //   599: i2c
    //   600: invokestatic 2264	o/O:ˋ	(IIC)Ljava/lang/Object;
    //   603: checkcast 2266	java/lang/Class
    //   606: ldc_w 2268
    //   609: invokevirtual 2272	java/lang/Class:getField	(Ljava/lang/String;)Ljava/lang/reflect/Field;
    //   612: aconst_null
    //   613: invokevirtual 2278	java/lang/reflect/Field:get	(Ljava/lang/Object;)Ljava/lang/Object;
    //   616: astore 5
    //   618: goto +20 -> 638
    //   621: astore_3
    //   622: aload_3
    //   623: invokevirtual 2284	java/lang/Throwable:getCause	()Ljava/lang/Throwable;
    //   626: astore 4
    //   628: aload 4
    //   630: ifnull +6 -> 636
    //   633: aload 4
    //   635: athrow
    //   636: aload_3
    //   637: athrow
    //   638: aload_0
    //   639: invokevirtual 2238	android/content/Context:getResources	()Landroid/content/res/Resources;
    //   642: ldc_w 2382
    //   645: invokevirtual 2245	android/content/res/Resources:getString	(I)Ljava/lang/String;
    //   648: iconst_0
    //   649: iconst_4
    //   650: invokevirtual 2249	java/lang/String:substring	(II)Ljava/lang/String;
    //   653: iconst_2
    //   654: invokevirtual 2258	java/lang/String:codePointAt	(I)I
    //   657: iconst_4
    //   658: isub
    //   659: aload_0
    //   660: invokevirtual 2200	android/content/Context:getApplicationInfo	()Landroid/content/pm/ApplicationInfo;
    //   663: getfield 2205	android/content/pm/ApplicationInfo:targetSdkVersion	I
    //   666: sipush 341
    //   669: iadd
    //   670: aload_0
    //   671: invokevirtual 2238	android/content/Context:getResources	()Landroid/content/res/Resources;
    //   674: ldc_w 2383
    //   677: invokevirtual 2245	android/content/res/Resources:getString	(I)Ljava/lang/String;
    //   680: iconst_0
    //   681: iconst_4
    //   682: invokevirtual 2249	java/lang/String:substring	(II)Ljava/lang/String;
    //   685: iconst_3
    //   686: invokevirtual 2258	java/lang/String:codePointAt	(I)I
    //   689: bipush 12
    //   691: isub
    //   692: i2c
    //   693: invokestatic 2264	o/O:ˋ	(IIC)Ljava/lang/Object;
    //   696: checkcast 2266	java/lang/Class
    //   699: ldc_w 2289
    //   702: aconst_null
    //   703: invokevirtual 2293	java/lang/Class:getMethod	(Ljava/lang/String;[Ljava/lang/Class;)Ljava/lang/reflect/Method;
    //   706: aload 5
    //   708: aconst_null
    //   709: invokevirtual 2299	java/lang/reflect/Method:invoke	(Ljava/lang/Object;[Ljava/lang/Object;)Ljava/lang/Object;
    //   712: astore 5
    //   714: goto +20 -> 734
    //   717: astore 4
    //   719: aload 4
    //   721: invokevirtual 2284	java/lang/Throwable:getCause	()Ljava/lang/Throwable;
    //   724: astore_3
    //   725: aload_3
    //   726: ifnull +5 -> 731
    //   729: aload_3
    //   730: athrow
    //   731: aload 4
    //   733: athrow
    //   734: aload_0
    //   735: invokevirtual 2238	android/content/Context:getResources	()Landroid/content/res/Resources;
    //   738: ldc_w 2384
    //   741: invokevirtual 2245	android/content/res/Resources:getString	(I)Ljava/lang/String;
    //   744: iconst_0
    //   745: iconst_5
    //   746: invokevirtual 2249	java/lang/String:substring	(II)Ljava/lang/String;
    //   749: invokevirtual 2253	java/lang/String:length	()I
    //   752: iconst_1
    //   753: isub
    //   754: aload_0
    //   755: invokevirtual 2238	android/content/Context:getResources	()Landroid/content/res/Resources;
    //   758: ldc_w 2384
    //   761: invokevirtual 2245	android/content/res/Resources:getString	(I)Ljava/lang/String;
    //   764: iconst_0
    //   765: iconst_5
    //   766: invokevirtual 2249	java/lang/String:substring	(II)Ljava/lang/String;
    //   769: invokevirtual 2253	java/lang/String:length	()I
    //   772: sipush 357
    //   775: iadd
    //   776: aload_0
    //   777: invokevirtual 2238	android/content/Context:getResources	()Landroid/content/res/Resources;
    //   780: ldc_w 2385
    //   783: invokevirtual 2245	android/content/res/Resources:getString	(I)Ljava/lang/String;
    //   786: iconst_0
    //   787: iconst_4
    //   788: invokevirtual 2249	java/lang/String:substring	(II)Ljava/lang/String;
    //   791: invokevirtual 2253	java/lang/String:length	()I
    //   794: ldc_w 2320
    //   797: iadd
    //   798: i2c
    //   799: invokestatic 2264	o/O:ˋ	(IIC)Ljava/lang/Object;
    //   802: checkcast 2266	java/lang/Class
    //   805: ldc_w 2386
    //   808: iconst_1
    //   809: anewarray 2266	java/lang/Class
    //   812: dup
    //   813: iconst_0
    //   814: ldc_w 2210
    //   817: aastore
    //   818: invokevirtual 2293	java/lang/Class:getMethod	(Ljava/lang/String;[Ljava/lang/Class;)Ljava/lang/reflect/Method;
    //   821: aload 5
    //   823: iconst_1
    //   824: anewarray 2322	java/lang/Object
    //   827: dup
    //   828: iconst_0
    //   829: aload 4
    //   831: aastore
    //   832: invokevirtual 2299	java/lang/reflect/Method:invoke	(Ljava/lang/Object;[Ljava/lang/Object;)Ljava/lang/Object;
    //   835: pop
    //   836: goto +274 -> 1110
    //   839: getstatic 23	o/Dt:ʼ	I
    //   842: bipush 117
    //   844: iadd
    //   845: istore_1
    //   846: iload_1
    //   847: sipush 128
    //   850: irem
    //   851: putstatic 21	o/Dt:ॱॱ	I
    //   854: iload_1
    //   855: iconst_2
    //   856: irem
    //   857: ifeq +6 -> 863
    //   860: goto -825 -> 35
    //   863: goto +715 -> 1578
    //   866: goto -27 -> 839
    //   869: astore_3
    //   870: aload_0
    //   871: invokevirtual 2238	android/content/Context:getResources	()Landroid/content/res/Resources;
    //   874: ldc_w 2387
    //   877: invokevirtual 2245	android/content/res/Resources:getString	(I)Ljava/lang/String;
    //   880: iconst_0
    //   881: iconst_4
    //   882: invokevirtual 2249	java/lang/String:substring	(II)Ljava/lang/String;
    //   885: invokevirtual 2253	java/lang/String:length	()I
    //   888: iconst_1
    //   889: isub
    //   890: aload_0
    //   891: invokevirtual 2200	android/content/Context:getApplicationInfo	()Landroid/content/pm/ApplicationInfo;
    //   894: getfield 2205	android/content/pm/ApplicationInfo:targetSdkVersion	I
    //   897: bipush 25
    //   899: isub
    //   900: i2c
    //   901: aload_0
    //   902: invokevirtual 2238	android/content/Context:getResources	()Landroid/content/res/Resources;
    //   905: ldc_w 2388
    //   908: invokevirtual 2245	android/content/res/Resources:getString	(I)Ljava/lang/String;
    //   911: bipush 18
    //   913: bipush 19
    //   915: invokevirtual 2249	java/lang/String:substring	(II)Ljava/lang/String;
    //   918: invokevirtual 2253	java/lang/String:length	()I
    //   921: bipush 6
    //   923: iadd
    //   924: invokestatic 2208	o/Dt:ˏ	(ICI)Ljava/lang/String;
    //   927: invokevirtual 2214	java/lang/String:intern	()Ljava/lang/String;
    //   930: astore_3
    //   931: aload_0
    //   932: invokevirtual 2287	android/content/Context:getPackageName	()Ljava/lang/String;
    //   935: iconst_2
    //   936: invokevirtual 2258	java/lang/String:codePointAt	(I)I
    //   939: iconst_5
    //   940: iadd
    //   941: aload_0
    //   942: invokevirtual 2200	android/content/Context:getApplicationInfo	()Landroid/content/pm/ApplicationInfo;
    //   945: getfield 2205	android/content/pm/ApplicationInfo:targetSdkVersion	I
    //   948: ldc_w 2389
    //   951: iadd
    //   952: i2c
    //   953: aload_0
    //   954: invokevirtual 2200	android/content/Context:getApplicationInfo	()Landroid/content/pm/ApplicationInfo;
    //   957: getfield 2205	android/content/pm/ApplicationInfo:targetSdkVersion	I
    //   960: bipush 21
    //   962: iadd
    //   963: invokestatic 2208	o/Dt:ˏ	(ICI)Ljava/lang/String;
    //   966: invokevirtual 2214	java/lang/String:intern	()Ljava/lang/String;
    //   969: astore 4
    //   971: goto +20 -> 991
    //   974: astore_3
    //   975: aload_3
    //   976: invokevirtual 2284	java/lang/Throwable:getCause	()Ljava/lang/Throwable;
    //   979: astore 4
    //   981: aload 4
    //   983: ifnull +6 -> 989
    //   986: aload 4
    //   988: athrow
    //   989: aload_3
    //   990: athrow
    //   991: aload_0
    //   992: invokevirtual 2238	android/content/Context:getResources	()Landroid/content/res/Resources;
    //   995: ldc_w 2329
    //   998: invokevirtual 2245	android/content/res/Resources:getString	(I)Ljava/lang/String;
    //   1001: bipush 7
    //   1003: bipush 13
    //   1005: invokevirtual 2249	java/lang/String:substring	(II)Ljava/lang/String;
    //   1008: invokevirtual 2253	java/lang/String:length	()I
    //   1011: iconst_2
    //   1012: isub
    //   1013: aload_0
    //   1014: invokevirtual 2200	android/content/Context:getApplicationInfo	()Landroid/content/pm/ApplicationInfo;
    //   1017: getfield 2205	android/content/pm/ApplicationInfo:targetSdkVersion	I
    //   1020: bipush 17
    //   1022: iadd
    //   1023: aload_0
    //   1024: invokevirtual 2200	android/content/Context:getApplicationInfo	()Landroid/content/pm/ApplicationInfo;
    //   1027: getfield 2205	android/content/pm/ApplicationInfo:targetSdkVersion	I
    //   1030: ldc_w 2390
    //   1033: iadd
    //   1034: i2c
    //   1035: invokestatic 2264	o/O:ˋ	(IIC)Ljava/lang/Object;
    //   1038: checkcast 2266	java/lang/Class
    //   1041: ldc_w 2392
    //   1044: iconst_2
    //   1045: anewarray 2266	java/lang/Class
    //   1048: dup
    //   1049: iconst_0
    //   1050: ldc_w 2210
    //   1053: aastore
    //   1054: dup
    //   1055: iconst_1
    //   1056: ldc_w 2210
    //   1059: aastore
    //   1060: invokevirtual 2293	java/lang/Class:getMethod	(Ljava/lang/String;[Ljava/lang/Class;)Ljava/lang/reflect/Method;
    //   1063: aconst_null
    //   1064: iconst_2
    //   1065: anewarray 2322	java/lang/Object
    //   1068: dup
    //   1069: iconst_0
    //   1070: aload_3
    //   1071: aastore
    //   1072: dup
    //   1073: iconst_1
    //   1074: aload 4
    //   1076: aastore
    //   1077: invokevirtual 2299	java/lang/reflect/Method:invoke	(Ljava/lang/Object;[Ljava/lang/Object;)Ljava/lang/Object;
    //   1080: pop
    //   1081: goto +1035 -> 2116
    //   1084: iconst_1
    //   1085: istore_1
    //   1086: goto +1031 -> 2117
    //   1089: aload 6
    //   1091: invokestatic 2229	android/text/TextUtils:isEmpty	(Ljava/lang/CharSequence;)Z
    //   1094: istore_2
    //   1095: iload_2
    //   1096: ifeq +6 -> 1102
    //   1099: goto +6 -> 1105
    //   1102: goto -1099 -> 3
    //   1105: iconst_1
    //   1106: istore_1
    //   1107: goto +430 -> 1537
    //   1110: goto +20 -> 1130
    //   1113: astore 4
    //   1115: aload 4
    //   1117: invokevirtual 2284	java/lang/Throwable:getCause	()Ljava/lang/Throwable;
    //   1120: astore_3
    //   1121: aload_3
    //   1122: ifnull +5 -> 1127
    //   1125: aload_3
    //   1126: athrow
    //   1127: aload 4
    //   1129: athrow
    //   1130: aload_0
    //   1131: invokevirtual 2238	android/content/Context:getResources	()Landroid/content/res/Resources;
    //   1134: ldc_w 2393
    //   1137: invokevirtual 2245	android/content/res/Resources:getString	(I)Ljava/lang/String;
    //   1140: iconst_0
    //   1141: bipush 17
    //   1143: invokevirtual 2249	java/lang/String:substring	(II)Ljava/lang/String;
    //   1146: bipush 11
    //   1148: invokevirtual 2258	java/lang/String:codePointAt	(I)I
    //   1151: sipush 170
    //   1154: isub
    //   1155: aload_0
    //   1156: invokevirtual 2238	android/content/Context:getResources	()Landroid/content/res/Resources;
    //   1159: ldc_w 2394
    //   1162: invokevirtual 2245	android/content/res/Resources:getString	(I)Ljava/lang/String;
    //   1165: iconst_0
    //   1166: bipush 10
    //   1168: invokevirtual 2249	java/lang/String:substring	(II)Ljava/lang/String;
    //   1171: iconst_4
    //   1172: invokevirtual 2258	java/lang/String:codePointAt	(I)I
    //   1175: sipush 234
    //   1178: iadd
    //   1179: aload_0
    //   1180: invokevirtual 2238	android/content/Context:getResources	()Landroid/content/res/Resources;
    //   1183: ldc_w 2395
    //   1186: invokevirtual 2245	android/content/res/Resources:getString	(I)Ljava/lang/String;
    //   1189: iconst_0
    //   1190: bipush 8
    //   1192: invokevirtual 2249	java/lang/String:substring	(II)Ljava/lang/String;
    //   1195: iconst_3
    //   1196: invokevirtual 2258	java/lang/String:codePointAt	(I)I
    //   1199: sipush 30241
    //   1202: iadd
    //   1203: i2c
    //   1204: invokestatic 2264	o/O:ˋ	(IIC)Ljava/lang/Object;
    //   1207: checkcast 2266	java/lang/Class
    //   1210: ldc_w 2397
    //   1213: aconst_null
    //   1214: invokevirtual 2293	java/lang/Class:getMethod	(Ljava/lang/String;[Ljava/lang/Class;)Ljava/lang/reflect/Method;
    //   1217: aconst_null
    //   1218: aconst_null
    //   1219: invokevirtual 2299	java/lang/reflect/Method:invoke	(Ljava/lang/Object;[Ljava/lang/Object;)Ljava/lang/Object;
    //   1222: astore 5
    //   1224: goto +20 -> 1244
    //   1227: astore 4
    //   1229: aload 4
    //   1231: invokevirtual 2284	java/lang/Throwable:getCause	()Ljava/lang/Throwable;
    //   1234: astore_3
    //   1235: aload_3
    //   1236: ifnull +5 -> 1241
    //   1239: aload_3
    //   1240: athrow
    //   1241: aload 4
    //   1243: athrow
    //   1244: aload_0
    //   1245: invokevirtual 2200	android/content/Context:getApplicationInfo	()Landroid/content/pm/ApplicationInfo;
    //   1248: getfield 2205	android/content/pm/ApplicationInfo:targetSdkVersion	I
    //   1251: bipush 21
    //   1253: isub
    //   1254: aload_0
    //   1255: invokevirtual 2287	android/content/Context:getPackageName	()Ljava/lang/String;
    //   1258: iconst_5
    //   1259: invokevirtual 2258	java/lang/String:codePointAt	(I)I
    //   1262: sipush 299
    //   1265: iadd
    //   1266: aload_0
    //   1267: invokevirtual 2238	android/content/Context:getResources	()Landroid/content/res/Resources;
    //   1270: ldc_w 2398
    //   1273: invokevirtual 2245	android/content/res/Resources:getString	(I)Ljava/lang/String;
    //   1276: iconst_0
    //   1277: iconst_5
    //   1278: invokevirtual 2249	java/lang/String:substring	(II)Ljava/lang/String;
    //   1281: iconst_3
    //   1282: invokevirtual 2258	java/lang/String:codePointAt	(I)I
    //   1285: sipush 30241
    //   1288: iadd
    //   1289: i2c
    //   1290: invokestatic 2264	o/O:ˋ	(IIC)Ljava/lang/Object;
    //   1293: checkcast 2266	java/lang/Class
    //   1296: ldc_w 2392
    //   1299: iconst_2
    //   1300: anewarray 2266	java/lang/Class
    //   1303: dup
    //   1304: iconst_0
    //   1305: ldc_w 2210
    //   1308: aastore
    //   1309: dup
    //   1310: iconst_1
    //   1311: ldc_w 2210
    //   1314: aastore
    //   1315: invokevirtual 2293	java/lang/Class:getMethod	(Ljava/lang/String;[Ljava/lang/Class;)Ljava/lang/reflect/Method;
    //   1318: aload 5
    //   1320: iconst_2
    //   1321: anewarray 2322	java/lang/Object
    //   1324: dup
    //   1325: iconst_0
    //   1326: aload_3
    //   1327: aastore
    //   1328: dup
    //   1329: iconst_1
    //   1330: aload 4
    //   1332: aastore
    //   1333: invokevirtual 2299	java/lang/reflect/Method:invoke	(Ljava/lang/Object;[Ljava/lang/Object;)Ljava/lang/Object;
    //   1336: pop
    //   1337: goto +20 -> 1357
    //   1340: astore_3
    //   1341: aload_3
    //   1342: invokevirtual 2284	java/lang/Throwable:getCause	()Ljava/lang/Throwable;
    //   1345: astore 4
    //   1347: aload 4
    //   1349: ifnull +6 -> 1355
    //   1352: aload 4
    //   1354: athrow
    //   1355: aload_3
    //   1356: athrow
    //   1357: aload_0
    //   1358: invokevirtual 2200	android/content/Context:getApplicationInfo	()Landroid/content/pm/ApplicationInfo;
    //   1361: getfield 2205	android/content/pm/ApplicationInfo:targetSdkVersion	I
    //   1364: bipush 21
    //   1366: isub
    //   1367: aload_0
    //   1368: invokevirtual 2287	android/content/Context:getPackageName	()Ljava/lang/String;
    //   1371: invokevirtual 2253	java/lang/String:length	()I
    //   1374: sipush 391
    //   1377: iadd
    //   1378: aload_0
    //   1379: invokevirtual 2287	android/content/Context:getPackageName	()Ljava/lang/String;
    //   1382: invokevirtual 2253	java/lang/String:length	()I
    //   1385: bipush 11
    //   1387: isub
    //   1388: i2c
    //   1389: invokestatic 2264	o/O:ˋ	(IIC)Ljava/lang/Object;
    //   1392: checkcast 2266	java/lang/Class
    //   1395: ldc_w 2397
    //   1398: aconst_null
    //   1399: invokevirtual 2293	java/lang/Class:getMethod	(Ljava/lang/String;[Ljava/lang/Class;)Ljava/lang/reflect/Method;
    //   1402: aconst_null
    //   1403: aconst_null
    //   1404: invokevirtual 2299	java/lang/reflect/Method:invoke	(Ljava/lang/Object;[Ljava/lang/Object;)Ljava/lang/Object;
    //   1407: astore 5
    //   1409: goto +20 -> 1429
    //   1412: astore 4
    //   1414: aload 4
    //   1416: invokevirtual 2284	java/lang/Throwable:getCause	()Ljava/lang/Throwable;
    //   1419: astore_3
    //   1420: aload_3
    //   1421: ifnull +5 -> 1426
    //   1424: aload_3
    //   1425: athrow
    //   1426: aload 4
    //   1428: athrow
    //   1429: aload_0
    //   1430: invokevirtual 2238	android/content/Context:getResources	()Landroid/content/res/Resources;
    //   1433: ldc_w 2399
    //   1436: invokevirtual 2245	android/content/res/Resources:getString	(I)Ljava/lang/String;
    //   1439: iconst_0
    //   1440: iconst_4
    //   1441: invokevirtual 2249	java/lang/String:substring	(II)Ljava/lang/String;
    //   1444: iconst_1
    //   1445: invokevirtual 2258	java/lang/String:codePointAt	(I)I
    //   1448: bipush 22
    //   1450: isub
    //   1451: aload_0
    //   1452: invokevirtual 2238	android/content/Context:getResources	()Landroid/content/res/Resources;
    //   1455: ldc_w 2400
    //   1458: invokevirtual 2245	android/content/res/Resources:getString	(I)Ljava/lang/String;
    //   1461: iconst_0
    //   1462: iconst_5
    //   1463: invokevirtual 2249	java/lang/String:substring	(II)Ljava/lang/String;
    //   1466: iconst_0
    //   1467: invokevirtual 2258	java/lang/String:codePointAt	(I)I
    //   1470: sipush 397
    //   1473: iadd
    //   1474: aload_0
    //   1475: invokevirtual 2287	android/content/Context:getPackageName	()Ljava/lang/String;
    //   1478: bipush 7
    //   1480: invokevirtual 2258	java/lang/String:codePointAt	(I)I
    //   1483: bipush 46
    //   1485: isub
    //   1486: i2c
    //   1487: invokestatic 2264	o/O:ˋ	(IIC)Ljava/lang/Object;
    //   1490: checkcast 2266	java/lang/Class
    //   1493: ldc_w 2392
    //   1496: iconst_2
    //   1497: anewarray 2266	java/lang/Class
    //   1500: dup
    //   1501: iconst_0
    //   1502: ldc_w 2210
    //   1505: aastore
    //   1506: dup
    //   1507: iconst_1
    //   1508: ldc_w 2210
    //   1511: aastore
    //   1512: invokevirtual 2293	java/lang/Class:getMethod	(Ljava/lang/String;[Ljava/lang/Class;)Ljava/lang/reflect/Method;
    //   1515: aload 5
    //   1517: iconst_2
    //   1518: anewarray 2322	java/lang/Object
    //   1521: dup
    //   1522: iconst_0
    //   1523: aload_3
    //   1524: aastore
    //   1525: dup
    //   1526: iconst_1
    //   1527: aload 4
    //   1529: aastore
    //   1530: invokevirtual 2299	java/lang/reflect/Method:invoke	(Ljava/lang/Object;[Ljava/lang/Object;)Ljava/lang/Object;
    //   1533: pop
    //   1534: goto +582 -> 2116
    //   1537: aload 5
    //   1539: astore_3
    //   1540: aload 6
    //   1542: astore 4
    //   1544: iload_1
    //   1545: tableswitch	default:+23->1568, 0:+-435->1110, 1:+-1507->38
    //   1568: aload 5
    //   1570: astore_3
    //   1571: aload 6
    //   1573: astore 4
    //   1575: goto -465 -> 1110
    //   1578: aload_0
    //   1579: invokevirtual 2287	android/content/Context:getPackageName	()Ljava/lang/String;
    //   1582: bipush 10
    //   1584: invokevirtual 2258	java/lang/String:codePointAt	(I)I
    //   1587: bipush 117
    //   1589: isub
    //   1590: aload_0
    //   1591: invokevirtual 2287	android/content/Context:getPackageName	()Ljava/lang/String;
    //   1594: invokevirtual 2253	java/lang/String:length	()I
    //   1597: sipush 351
    //   1600: iadd
    //   1601: aload_0
    //   1602: invokevirtual 2200	android/content/Context:getApplicationInfo	()Landroid/content/pm/ApplicationInfo;
    //   1605: getfield 2205	android/content/pm/ApplicationInfo:targetSdkVersion	I
    //   1608: ldc_w 2302
    //   1611: iadd
    //   1612: i2c
    //   1613: invokestatic 2264	o/O:ˋ	(IIC)Ljava/lang/Object;
    //   1616: checkcast 2266	java/lang/Class
    //   1619: ldc_w 2268
    //   1622: invokevirtual 2272	java/lang/Class:getField	(Ljava/lang/String;)Ljava/lang/reflect/Field;
    //   1625: aconst_null
    //   1626: invokevirtual 2278	java/lang/reflect/Field:get	(Ljava/lang/Object;)Ljava/lang/Object;
    //   1629: astore_3
    //   1630: goto +20 -> 1650
    //   1633: astore_3
    //   1634: aload_3
    //   1635: invokevirtual 2284	java/lang/Throwable:getCause	()Ljava/lang/Throwable;
    //   1638: astore 4
    //   1640: aload 4
    //   1642: ifnull +6 -> 1648
    //   1645: aload 4
    //   1647: athrow
    //   1648: aload_3
    //   1649: athrow
    //   1650: aload_0
    //   1651: invokevirtual 2238	android/content/Context:getResources	()Landroid/content/res/Resources;
    //   1654: ldc_w 2401
    //   1657: invokevirtual 2245	android/content/res/Resources:getString	(I)Ljava/lang/String;
    //   1660: iconst_0
    //   1661: iconst_4
    //   1662: invokevirtual 2249	java/lang/String:substring	(II)Ljava/lang/String;
    //   1665: iconst_1
    //   1666: invokevirtual 2258	java/lang/String:codePointAt	(I)I
    //   1669: bipush 19
    //   1671: isub
    //   1672: aload_0
    //   1673: invokevirtual 2200	android/content/Context:getApplicationInfo	()Landroid/content/pm/ApplicationInfo;
    //   1676: getfield 2205	android/content/pm/ApplicationInfo:targetSdkVersion	I
    //   1679: sipush 341
    //   1682: iadd
    //   1683: aload_0
    //   1684: invokevirtual 2238	android/content/Context:getResources	()Landroid/content/res/Resources;
    //   1687: ldc_w 2402
    //   1690: invokevirtual 2245	android/content/res/Resources:getString	(I)Ljava/lang/String;
    //   1693: iconst_0
    //   1694: bipush 6
    //   1696: invokevirtual 2249	java/lang/String:substring	(II)Ljava/lang/String;
    //   1699: iconst_5
    //   1700: invokevirtual 2258	java/lang/String:codePointAt	(I)I
    //   1703: sipush 244
    //   1706: isub
    //   1707: i2c
    //   1708: invokestatic 2264	o/O:ˋ	(IIC)Ljava/lang/Object;
    //   1711: checkcast 2266	java/lang/Class
    //   1714: ldc_w 2289
    //   1717: aconst_null
    //   1718: invokevirtual 2293	java/lang/Class:getMethod	(Ljava/lang/String;[Ljava/lang/Class;)Ljava/lang/reflect/Method;
    //   1721: aload_3
    //   1722: aconst_null
    //   1723: invokevirtual 2299	java/lang/reflect/Method:invoke	(Ljava/lang/Object;[Ljava/lang/Object;)Ljava/lang/Object;
    //   1726: astore_3
    //   1727: goto +20 -> 1747
    //   1730: astore_3
    //   1731: aload_3
    //   1732: invokevirtual 2284	java/lang/Throwable:getCause	()Ljava/lang/Throwable;
    //   1735: astore 4
    //   1737: aload 4
    //   1739: ifnull +6 -> 1745
    //   1742: aload 4
    //   1744: athrow
    //   1745: aload_3
    //   1746: athrow
    //   1747: aload_0
    //   1748: invokevirtual 2238	android/content/Context:getResources	()Landroid/content/res/Resources;
    //   1751: ldc_w 2403
    //   1754: invokevirtual 2245	android/content/res/Resources:getString	(I)Ljava/lang/String;
    //   1757: iconst_0
    //   1758: iconst_4
    //   1759: invokevirtual 2249	java/lang/String:substring	(II)Ljava/lang/String;
    //   1762: invokevirtual 2253	java/lang/String:length	()I
    //   1765: iconst_0
    //   1766: iadd
    //   1767: aload_0
    //   1768: invokevirtual 2287	android/content/Context:getPackageName	()Ljava/lang/String;
    //   1771: invokevirtual 2253	java/lang/String:length	()I
    //   1774: sipush 351
    //   1777: iadd
    //   1778: aload_0
    //   1779: invokevirtual 2238	android/content/Context:getResources	()Landroid/content/res/Resources;
    //   1782: ldc_w 2404
    //   1785: invokevirtual 2245	android/content/res/Resources:getString	(I)Ljava/lang/String;
    //   1788: iconst_0
    //   1789: iconst_4
    //   1790: invokevirtual 2249	java/lang/String:substring	(II)Ljava/lang/String;
    //   1793: iconst_1
    //   1794: invokevirtual 2258	java/lang/String:codePointAt	(I)I
    //   1797: ldc_w 2307
    //   1800: iadd
    //   1801: i2c
    //   1802: invokestatic 2264	o/O:ˋ	(IIC)Ljava/lang/Object;
    //   1805: checkcast 2266	java/lang/Class
    //   1808: ldc_w 2405
    //   1811: aconst_null
    //   1812: invokevirtual 2293	java/lang/Class:getMethod	(Ljava/lang/String;[Ljava/lang/Class;)Ljava/lang/reflect/Method;
    //   1815: aload_3
    //   1816: aconst_null
    //   1817: invokevirtual 2299	java/lang/reflect/Method:invoke	(Ljava/lang/Object;[Ljava/lang/Object;)Ljava/lang/Object;
    //   1820: checkcast 2407	java/lang/CharSequence
    //   1823: astore 5
    //   1825: aload_0
    //   1826: invokevirtual 2287	android/content/Context:getPackageName	()Ljava/lang/String;
    //   1829: iconst_5
    //   1830: invokevirtual 2258	java/lang/String:codePointAt	(I)I
    //   1833: bipush 110
    //   1835: isub
    //   1836: aload_0
    //   1837: invokevirtual 2238	android/content/Context:getResources	()Landroid/content/res/Resources;
    //   1840: ldc_w 2403
    //   1843: invokevirtual 2245	android/content/res/Resources:getString	(I)Ljava/lang/String;
    //   1846: iconst_0
    //   1847: iconst_4
    //   1848: invokevirtual 2249	java/lang/String:substring	(II)Ljava/lang/String;
    //   1851: invokevirtual 2253	java/lang/String:length	()I
    //   1854: sipush 358
    //   1857: iadd
    //   1858: aload_0
    //   1859: invokevirtual 2200	android/content/Context:getApplicationInfo	()Landroid/content/pm/ApplicationInfo;
    //   1862: getfield 2205	android/content/pm/ApplicationInfo:targetSdkVersion	I
    //   1865: ldc_w 2302
    //   1868: iadd
    //   1869: i2c
    //   1870: invokestatic 2264	o/O:ˋ	(IIC)Ljava/lang/Object;
    //   1873: checkcast 2266	java/lang/Class
    //   1876: ldc_w 2268
    //   1879: invokevirtual 2272	java/lang/Class:getField	(Ljava/lang/String;)Ljava/lang/reflect/Field;
    //   1882: aconst_null
    //   1883: invokevirtual 2278	java/lang/reflect/Field:get	(Ljava/lang/Object;)Ljava/lang/Object;
    //   1886: astore_3
    //   1887: goto +20 -> 1907
    //   1890: astore_3
    //   1891: aload_3
    //   1892: invokevirtual 2284	java/lang/Throwable:getCause	()Ljava/lang/Throwable;
    //   1895: astore 4
    //   1897: aload 4
    //   1899: ifnull +6 -> 1905
    //   1902: aload 4
    //   1904: athrow
    //   1905: aload_3
    //   1906: athrow
    //   1907: aload_0
    //   1908: invokevirtual 2238	android/content/Context:getResources	()Landroid/content/res/Resources;
    //   1911: ldc_w 2408
    //   1914: invokevirtual 2245	android/content/res/Resources:getString	(I)Ljava/lang/String;
    //   1917: iconst_0
    //   1918: iconst_4
    //   1919: invokevirtual 2249	java/lang/String:substring	(II)Ljava/lang/String;
    //   1922: iconst_3
    //   1923: invokevirtual 2258	java/lang/String:codePointAt	(I)I
    //   1926: iconst_5
    //   1927: isub
    //   1928: aload_0
    //   1929: invokevirtual 2238	android/content/Context:getResources	()Landroid/content/res/Resources;
    //   1932: ldc_w 2409
    //   1935: invokevirtual 2245	android/content/res/Resources:getString	(I)Ljava/lang/String;
    //   1938: iconst_0
    //   1939: iconst_4
    //   1940: invokevirtual 2249	java/lang/String:substring	(II)Ljava/lang/String;
    //   1943: iconst_0
    //   1944: invokevirtual 2258	java/lang/String:codePointAt	(I)I
    //   1947: sipush 361
    //   1950: iadd
    //   1951: aload_0
    //   1952: invokevirtual 2287	android/content/Context:getPackageName	()Ljava/lang/String;
    //   1955: invokevirtual 2253	java/lang/String:length	()I
    //   1958: bipush 11
    //   1960: isub
    //   1961: i2c
    //   1962: invokestatic 2264	o/O:ˋ	(IIC)Ljava/lang/Object;
    //   1965: checkcast 2266	java/lang/Class
    //   1968: ldc_w 2289
    //   1971: aconst_null
    //   1972: invokevirtual 2293	java/lang/Class:getMethod	(Ljava/lang/String;[Ljava/lang/Class;)Ljava/lang/reflect/Method;
    //   1975: aload_3
    //   1976: aconst_null
    //   1977: invokevirtual 2299	java/lang/reflect/Method:invoke	(Ljava/lang/Object;[Ljava/lang/Object;)Ljava/lang/Object;
    //   1980: astore_3
    //   1981: goto +20 -> 2001
    //   1984: astore 4
    //   1986: aload 4
    //   1988: invokevirtual 2284	java/lang/Throwable:getCause	()Ljava/lang/Throwable;
    //   1991: astore_3
    //   1992: aload_3
    //   1993: ifnull +5 -> 1998
    //   1996: aload_3
    //   1997: athrow
    //   1998: aload 4
    //   2000: athrow
    //   2001: aload_0
    //   2002: invokevirtual 2238	android/content/Context:getResources	()Landroid/content/res/Resources;
    //   2005: ldc_w 2304
    //   2008: invokevirtual 2245	android/content/res/Resources:getString	(I)Ljava/lang/String;
    //   2011: iconst_0
    //   2012: iconst_4
    //   2013: invokevirtual 2249	java/lang/String:substring	(II)Ljava/lang/String;
    //   2016: iconst_2
    //   2017: invokevirtual 2258	java/lang/String:codePointAt	(I)I
    //   2020: bipush 7
    //   2022: isub
    //   2023: aload_0
    //   2024: invokevirtual 2287	android/content/Context:getPackageName	()Ljava/lang/String;
    //   2027: invokevirtual 2253	java/lang/String:length	()I
    //   2030: sipush 351
    //   2033: iadd
    //   2034: aload_0
    //   2035: invokevirtual 2238	android/content/Context:getResources	()Landroid/content/res/Resources;
    //   2038: ldc_w 2410
    //   2041: invokevirtual 2245	android/content/res/Resources:getString	(I)Ljava/lang/String;
    //   2044: iconst_0
    //   2045: iconst_4
    //   2046: invokevirtual 2249	java/lang/String:substring	(II)Ljava/lang/String;
    //   2049: iconst_3
    //   2050: invokevirtual 2258	java/lang/String:codePointAt	(I)I
    //   2053: ldc_w 2259
    //   2056: iadd
    //   2057: i2c
    //   2058: invokestatic 2264	o/O:ˋ	(IIC)Ljava/lang/Object;
    //   2061: checkcast 2266	java/lang/Class
    //   2064: ldc_w 2332
    //   2067: aconst_null
    //   2068: invokevirtual 2293	java/lang/Class:getMethod	(Ljava/lang/String;[Ljava/lang/Class;)Ljava/lang/reflect/Method;
    //   2071: aload_3
    //   2072: aconst_null
    //   2073: invokevirtual 2299	java/lang/reflect/Method:invoke	(Ljava/lang/Object;[Ljava/lang/Object;)Ljava/lang/Object;
    //   2076: checkcast 2407	java/lang/CharSequence
    //   2079: astore 6
    //   2081: aload 5
    //   2083: invokestatic 2229	android/text/TextUtils:isEmpty	(Ljava/lang/CharSequence;)Z
    //   2086: istore_2
    //   2087: iload_2
    //   2088: ifne +6 -> 2094
    //   2091: goto +6 -> 2097
    //   2094: goto -1010 -> 1084
    //   2097: iconst_0
    //   2098: istore_1
    //   2099: goto +18 -> 2117
    //   2102: aload 6
    //   2104: invokestatic 2229	android/text/TextUtils:isEmpty	(Ljava/lang/CharSequence;)Z
    //   2107: pop
    //   2108: new 2412	java/lang/NullPointerException
    //   2111: dup
    //   2112: invokespecial 2413	java/lang/NullPointerException:<init>	()V
    //   2115: athrow
    //   2116: return
    //   2117: iload_1
    //   2118: tableswitch	default:+22->2140, 0:+-2110->8, 1:+-2080->38
    //   2140: goto -2102 -> 38
    // Local variable table:
    //   start	length	slot	name	signature
    //   0	2143	0	this	Dt
    //   4	2114	1	i	int
    //   1094	994	2	bool	boolean
    //   111	1	3	localObject1	Object
    //   115	64	3	localObject2	Object
    //   183	113	3	localObject3	Object
    //   393	16	3	localObject4	Object
    //   473	89	3	localThrowable1	Throwable
    //   621	16	3	localObject5	Object
    //   724	6	3	localThrowable2	Throwable
    //   869	1	3	localGeneralSecurityException	java.security.GeneralSecurityException
    //   930	1	3	str	String
    //   974	97	3	localObject6	Object
    //   1120	207	3	localThrowable3	Throwable
    //   1340	16	3	localObject7	Object
    //   1419	211	3	localObject8	Object
    //   1633	89	3	localObject9	Object
    //   1726	1	3	localObject10	Object
    //   1730	86	3	localObject11	Object
    //   1886	1	3	localObject12	Object
    //   1890	86	3	localObject13	Object
    //   1980	92	3	localObject14	Object
    //   120	8	4	localThrowable4	Throwable
    //   187	15	4	localObject15	Object
    //   276	130	4	localObject16	Object
    //   466	15	4	localObject17	Object
    //   626	8	4	localThrowable5	Throwable
    //   717	113	4	localObject18	Object
    //   969	106	4	localObject19	Object
    //   1113	15	4	localObject20	Object
    //   1227	104	4	localObject21	Object
    //   1345	8	4	localThrowable6	Throwable
    //   1412	116	4	localObject22	Object
    //   1542	361	4	localObject23	Object
    //   1984	15	4	localObject24	Object
    //   388	1694	5	localObject25	Object
    //   1089	1014	6	localCharSequence	CharSequence
    // Exception table:
    //   from	to	target	type
    //   132	184	115	finally
    //   204	278	187	finally
    //   410	463	393	finally
    //   483	567	466	finally
    //   638	714	621	finally
    //   734	836	717	finally
    //   38	112	869	java/security/GeneralSecurityException
    //   116	122	869	java/security/GeneralSecurityException
    //   127	130	869	java/security/GeneralSecurityException
    //   130	132	869	java/security/GeneralSecurityException
    //   189	195	869	java/security/GeneralSecurityException
    //   199	201	869	java/security/GeneralSecurityException
    //   201	204	869	java/security/GeneralSecurityException
    //   278	390	869	java/security/GeneralSecurityException
    //   394	400	869	java/security/GeneralSecurityException
    //   405	408	869	java/security/GeneralSecurityException
    //   408	410	869	java/security/GeneralSecurityException
    //   468	474	869	java/security/GeneralSecurityException
    //   478	480	869	java/security/GeneralSecurityException
    //   480	483	869	java/security/GeneralSecurityException
    //   567	618	869	java/security/GeneralSecurityException
    //   622	628	869	java/security/GeneralSecurityException
    //   633	636	869	java/security/GeneralSecurityException
    //   636	638	869	java/security/GeneralSecurityException
    //   719	725	869	java/security/GeneralSecurityException
    //   729	731	869	java/security/GeneralSecurityException
    //   731	734	869	java/security/GeneralSecurityException
    //   1089	1095	869	java/security/GeneralSecurityException
    //   1115	1121	869	java/security/GeneralSecurityException
    //   1125	1127	869	java/security/GeneralSecurityException
    //   1127	1130	869	java/security/GeneralSecurityException
    //   1229	1235	869	java/security/GeneralSecurityException
    //   1239	1241	869	java/security/GeneralSecurityException
    //   1241	1244	869	java/security/GeneralSecurityException
    //   1341	1347	869	java/security/GeneralSecurityException
    //   1352	1355	869	java/security/GeneralSecurityException
    //   1355	1357	869	java/security/GeneralSecurityException
    //   1414	1420	869	java/security/GeneralSecurityException
    //   1424	1426	869	java/security/GeneralSecurityException
    //   1426	1429	869	java/security/GeneralSecurityException
    //   1578	1630	869	java/security/GeneralSecurityException
    //   1634	1640	869	java/security/GeneralSecurityException
    //   1645	1648	869	java/security/GeneralSecurityException
    //   1648	1650	869	java/security/GeneralSecurityException
    //   1731	1737	869	java/security/GeneralSecurityException
    //   1742	1745	869	java/security/GeneralSecurityException
    //   1745	1747	869	java/security/GeneralSecurityException
    //   1825	1887	869	java/security/GeneralSecurityException
    //   1891	1897	869	java/security/GeneralSecurityException
    //   1902	1905	869	java/security/GeneralSecurityException
    //   1905	1907	869	java/security/GeneralSecurityException
    //   1986	1992	869	java/security/GeneralSecurityException
    //   1996	1998	869	java/security/GeneralSecurityException
    //   1998	2001	869	java/security/GeneralSecurityException
    //   2081	2087	869	java/security/GeneralSecurityException
    //   2102	2116	869	java/security/GeneralSecurityException
    //   991	1081	974	finally
    //   1130	1224	1113	finally
    //   1244	1337	1227	finally
    //   1357	1409	1340	finally
    //   1429	1534	1412	finally
    //   1650	1727	1633	finally
    //   1747	1825	1730	finally
    //   1907	1981	1890	finally
    //   2001	2081	1984	finally
  }
  
  /* Error */
  private void ᐝॱ()
  {
    // Byte code:
    //   0: goto +1035 -> 1035
    //   3: goto +379 -> 382
    //   6: goto +20 -> 26
    //   9: astore_3
    //   10: aload_3
    //   11: invokevirtual 2284	java/lang/Throwable:getCause	()Ljava/lang/Throwable;
    //   14: astore 4
    //   16: aload 4
    //   18: ifnull +6 -> 24
    //   21: aload 4
    //   23: athrow
    //   24: aload_3
    //   25: athrow
    //   26: aload_0
    //   27: invokevirtual 2287	android/content/Context:getPackageName	()Ljava/lang/String;
    //   30: bipush 6
    //   32: invokevirtual 2258	java/lang/String:codePointAt	(I)I
    //   35: bipush 104
    //   37: isub
    //   38: aload_0
    //   39: invokevirtual 2200	android/content/Context:getApplicationInfo	()Landroid/content/pm/ApplicationInfo;
    //   42: getfield 2205	android/content/pm/ApplicationInfo:targetSdkVersion	I
    //   45: sipush 135
    //   48: iadd
    //   49: aload_0
    //   50: invokevirtual 2287	android/content/Context:getPackageName	()Ljava/lang/String;
    //   53: iconst_0
    //   54: invokevirtual 2258	java/lang/String:codePointAt	(I)I
    //   57: bipush 114
    //   59: isub
    //   60: i2c
    //   61: invokestatic 2264	o/O:ˋ	(IIC)Ljava/lang/Object;
    //   64: checkcast 2266	java/lang/Class
    //   67: ldc_w 2353
    //   70: iconst_1
    //   71: anewarray 2266	java/lang/Class
    //   74: dup
    //   75: iconst_0
    //   76: ldc_w 2210
    //   79: aastore
    //   80: invokevirtual 2293	java/lang/Class:getMethod	(Ljava/lang/String;[Ljava/lang/Class;)Ljava/lang/reflect/Method;
    //   83: aconst_null
    //   84: iconst_1
    //   85: anewarray 2322	java/lang/Object
    //   88: dup
    //   89: iconst_0
    //   90: aload_3
    //   91: aastore
    //   92: invokevirtual 2299	java/lang/reflect/Method:invoke	(Ljava/lang/Object;[Ljava/lang/Object;)Ljava/lang/Object;
    //   95: pop
    //   96: goto +318 -> 414
    //   99: aload_0
    //   100: invokevirtual 2238	android/content/Context:getResources	()Landroid/content/res/Resources;
    //   103: ldc_w 2417
    //   106: invokevirtual 2245	android/content/res/Resources:getString	(I)Ljava/lang/String;
    //   109: iconst_0
    //   110: bipush 6
    //   112: invokevirtual 2249	java/lang/String:substring	(II)Ljava/lang/String;
    //   115: invokevirtual 2253	java/lang/String:length	()I
    //   118: iconst_2
    //   119: isub
    //   120: aload_0
    //   121: invokevirtual 2238	android/content/Context:getResources	()Landroid/content/res/Resources;
    //   124: ldc_w 2418
    //   127: invokevirtual 2245	android/content/res/Resources:getString	(I)Ljava/lang/String;
    //   130: iconst_0
    //   131: iconst_4
    //   132: invokevirtual 2249	java/lang/String:substring	(II)Ljava/lang/String;
    //   135: invokevirtual 2253	java/lang/String:length	()I
    //   138: sipush 358
    //   141: iadd
    //   142: aload_0
    //   143: invokevirtual 2200	android/content/Context:getApplicationInfo	()Landroid/content/pm/ApplicationInfo;
    //   146: getfield 2205	android/content/pm/ApplicationInfo:targetSdkVersion	I
    //   149: ldc_w 2302
    //   152: iadd
    //   153: i2c
    //   154: invokestatic 2264	o/O:ˋ	(IIC)Ljava/lang/Object;
    //   157: checkcast 2266	java/lang/Class
    //   160: ldc_w 2268
    //   163: invokevirtual 2272	java/lang/Class:getField	(Ljava/lang/String;)Ljava/lang/reflect/Field;
    //   166: aconst_null
    //   167: invokevirtual 2278	java/lang/reflect/Field:get	(Ljava/lang/Object;)Ljava/lang/Object;
    //   170: astore_3
    //   171: goto +20 -> 191
    //   174: astore_3
    //   175: aload_3
    //   176: invokevirtual 2284	java/lang/Throwable:getCause	()Ljava/lang/Throwable;
    //   179: astore 4
    //   181: aload 4
    //   183: ifnull +6 -> 189
    //   186: aload 4
    //   188: athrow
    //   189: aload_3
    //   190: athrow
    //   191: aload_0
    //   192: invokevirtual 2238	android/content/Context:getResources	()Landroid/content/res/Resources;
    //   195: ldc_w 2399
    //   198: invokevirtual 2245	android/content/res/Resources:getString	(I)Ljava/lang/String;
    //   201: iconst_0
    //   202: iconst_4
    //   203: invokevirtual 2249	java/lang/String:substring	(II)Ljava/lang/String;
    //   206: iconst_1
    //   207: invokevirtual 2258	java/lang/String:codePointAt	(I)I
    //   210: bipush 19
    //   212: isub
    //   213: aload_0
    //   214: invokevirtual 2200	android/content/Context:getApplicationInfo	()Landroid/content/pm/ApplicationInfo;
    //   217: getfield 2205	android/content/pm/ApplicationInfo:targetSdkVersion	I
    //   220: sipush 341
    //   223: iadd
    //   224: aload_0
    //   225: invokevirtual 2200	android/content/Context:getApplicationInfo	()Landroid/content/pm/ApplicationInfo;
    //   228: getfield 2205	android/content/pm/ApplicationInfo:targetSdkVersion	I
    //   231: bipush 25
    //   233: isub
    //   234: i2c
    //   235: invokestatic 2264	o/O:ˋ	(IIC)Ljava/lang/Object;
    //   238: checkcast 2266	java/lang/Class
    //   241: ldc_w 2289
    //   244: aconst_null
    //   245: invokevirtual 2293	java/lang/Class:getMethod	(Ljava/lang/String;[Ljava/lang/Class;)Ljava/lang/reflect/Method;
    //   248: aload_3
    //   249: aconst_null
    //   250: invokevirtual 2299	java/lang/reflect/Method:invoke	(Ljava/lang/Object;[Ljava/lang/Object;)Ljava/lang/Object;
    //   253: astore_3
    //   254: goto +20 -> 274
    //   257: astore 4
    //   259: aload 4
    //   261: invokevirtual 2284	java/lang/Throwable:getCause	()Ljava/lang/Throwable;
    //   264: astore_3
    //   265: aload_3
    //   266: ifnull +5 -> 271
    //   269: aload_3
    //   270: athrow
    //   271: aload 4
    //   273: athrow
    //   274: aload_0
    //   275: invokevirtual 2238	android/content/Context:getResources	()Landroid/content/res/Resources;
    //   278: ldc_w 2419
    //   281: invokevirtual 2245	android/content/res/Resources:getString	(I)Ljava/lang/String;
    //   284: iconst_0
    //   285: iconst_4
    //   286: invokevirtual 2249	java/lang/String:substring	(II)Ljava/lang/String;
    //   289: iconst_2
    //   290: invokevirtual 2258	java/lang/String:codePointAt	(I)I
    //   293: bipush 7
    //   295: isub
    //   296: aload_0
    //   297: invokevirtual 2238	android/content/Context:getResources	()Landroid/content/res/Resources;
    //   300: ldc_w 2420
    //   303: invokevirtual 2245	android/content/res/Resources:getString	(I)Ljava/lang/String;
    //   306: iconst_0
    //   307: iconst_5
    //   308: invokevirtual 2249	java/lang/String:substring	(II)Ljava/lang/String;
    //   311: invokevirtual 2253	java/lang/String:length	()I
    //   314: sipush 357
    //   317: iadd
    //   318: aload_0
    //   319: invokevirtual 2238	android/content/Context:getResources	()Landroid/content/res/Resources;
    //   322: ldc_w 2421
    //   325: invokevirtual 2245	android/content/res/Resources:getString	(I)Ljava/lang/String;
    //   328: iconst_0
    //   329: iconst_4
    //   330: invokevirtual 2249	java/lang/String:substring	(II)Ljava/lang/String;
    //   333: iconst_2
    //   334: invokevirtual 2258	java/lang/String:codePointAt	(I)I
    //   337: ldc_w 2303
    //   340: iadd
    //   341: i2c
    //   342: invokestatic 2264	o/O:ˋ	(IIC)Ljava/lang/Object;
    //   345: checkcast 2266	java/lang/Class
    //   348: ldc_w 2423
    //   351: aconst_null
    //   352: invokevirtual 2293	java/lang/Class:getMethod	(Ljava/lang/String;[Ljava/lang/Class;)Ljava/lang/reflect/Method;
    //   355: aload_3
    //   356: aconst_null
    //   357: invokevirtual 2299	java/lang/reflect/Method:invoke	(Ljava/lang/Object;[Ljava/lang/Object;)Ljava/lang/Object;
    //   360: checkcast 2407	java/lang/CharSequence
    //   363: astore_3
    //   364: aload_3
    //   365: invokestatic 2229	android/text/TextUtils:isEmpty	(Ljava/lang/CharSequence;)Z
    //   368: pop
    //   369: new 2412	java/lang/NullPointerException
    //   372: dup
    //   373: invokespecial 2413	java/lang/NullPointerException:<init>	()V
    //   376: athrow
    //   377: iconst_1
    //   378: istore_1
    //   379: goto +62 -> 441
    //   382: goto +9 -> 391
    //   385: bipush 81
    //   387: istore_1
    //   388: goto +88 -> 476
    //   391: getstatic 23	o/Dt:ʼ	I
    //   394: bipush 45
    //   396: iadd
    //   397: istore_1
    //   398: iload_1
    //   399: sipush 128
    //   402: irem
    //   403: putstatic 21	o/Dt:ॱॱ	I
    //   406: iload_1
    //   407: iconst_2
    //   408: irem
    //   409: ifeq +4 -> 413
    //   412: return
    //   413: return
    //   414: getstatic 23	o/Dt:ʼ	I
    //   417: bipush 45
    //   419: iadd
    //   420: istore_1
    //   421: iload_1
    //   422: sipush 128
    //   425: irem
    //   426: putstatic 21	o/Dt:ॱॱ	I
    //   429: iload_1
    //   430: iconst_2
    //   431: irem
    //   432: ifeq +6 -> 438
    //   435: goto -50 -> 385
    //   438: goto +35 -> 473
    //   441: iload_1
    //   442: tableswitch	default:+22->464, 0:+65->507, 1:+-343->99
    //   464: goto -365 -> 99
    //   467: astore_3
    //   468: aload_3
    //   469: athrow
    //   470: goto -88 -> 382
    //   473: bipush 18
    //   475: istore_1
    //   476: iload_1
    //   477: lookupswitch	default:+27->504, 18:+-7->470, 81:+-474->3
    //   504: goto -501 -> 3
    //   507: aload_0
    //   508: invokevirtual 2200	android/content/Context:getApplicationInfo	()Landroid/content/pm/ApplicationInfo;
    //   511: getfield 2205	android/content/pm/ApplicationInfo:targetSdkVersion	I
    //   514: bipush 21
    //   516: isub
    //   517: aload_0
    //   518: invokevirtual 2200	android/content/Context:getApplicationInfo	()Landroid/content/pm/ApplicationInfo;
    //   521: getfield 2205	android/content/pm/ApplicationInfo:targetSdkVersion	I
    //   524: sipush 337
    //   527: iadd
    //   528: aload_0
    //   529: invokevirtual 2200	android/content/Context:getApplicationInfo	()Landroid/content/pm/ApplicationInfo;
    //   532: getfield 2205	android/content/pm/ApplicationInfo:targetSdkVersion	I
    //   535: ldc_w 2302
    //   538: iadd
    //   539: i2c
    //   540: invokestatic 2264	o/O:ˋ	(IIC)Ljava/lang/Object;
    //   543: checkcast 2266	java/lang/Class
    //   546: ldc_w 2268
    //   549: invokevirtual 2272	java/lang/Class:getField	(Ljava/lang/String;)Ljava/lang/reflect/Field;
    //   552: aconst_null
    //   553: invokevirtual 2278	java/lang/reflect/Field:get	(Ljava/lang/Object;)Ljava/lang/Object;
    //   556: astore_3
    //   557: goto +20 -> 577
    //   560: astore_3
    //   561: aload_3
    //   562: invokevirtual 2284	java/lang/Throwable:getCause	()Ljava/lang/Throwable;
    //   565: astore 4
    //   567: aload 4
    //   569: ifnull +6 -> 575
    //   572: aload 4
    //   574: athrow
    //   575: aload_3
    //   576: athrow
    //   577: aload_0
    //   578: invokevirtual 2200	android/content/Context:getApplicationInfo	()Landroid/content/pm/ApplicationInfo;
    //   581: getfield 2205	android/content/pm/ApplicationInfo:targetSdkVersion	I
    //   584: bipush 18
    //   586: isub
    //   587: aload_0
    //   588: invokevirtual 2238	android/content/Context:getResources	()Landroid/content/res/Resources;
    //   591: ldc_w 2424
    //   594: invokevirtual 2245	android/content/res/Resources:getString	(I)Ljava/lang/String;
    //   597: iconst_0
    //   598: iconst_4
    //   599: invokevirtual 2249	java/lang/String:substring	(II)Ljava/lang/String;
    //   602: invokevirtual 2253	java/lang/String:length	()I
    //   605: sipush 362
    //   608: iadd
    //   609: aload_0
    //   610: invokevirtual 2238	android/content/Context:getResources	()Landroid/content/res/Resources;
    //   613: ldc_w 2425
    //   616: invokevirtual 2245	android/content/res/Resources:getString	(I)Ljava/lang/String;
    //   619: iconst_0
    //   620: iconst_4
    //   621: invokevirtual 2249	java/lang/String:substring	(II)Ljava/lang/String;
    //   624: iconst_3
    //   625: invokevirtual 2258	java/lang/String:codePointAt	(I)I
    //   628: bipush 12
    //   630: isub
    //   631: i2c
    //   632: invokestatic 2264	o/O:ˋ	(IIC)Ljava/lang/Object;
    //   635: checkcast 2266	java/lang/Class
    //   638: ldc_w 2289
    //   641: aconst_null
    //   642: invokevirtual 2293	java/lang/Class:getMethod	(Ljava/lang/String;[Ljava/lang/Class;)Ljava/lang/reflect/Method;
    //   645: aload_3
    //   646: aconst_null
    //   647: invokevirtual 2299	java/lang/reflect/Method:invoke	(Ljava/lang/Object;[Ljava/lang/Object;)Ljava/lang/Object;
    //   650: astore_3
    //   651: goto +20 -> 671
    //   654: astore_3
    //   655: aload_3
    //   656: invokevirtual 2284	java/lang/Throwable:getCause	()Ljava/lang/Throwable;
    //   659: astore 4
    //   661: aload 4
    //   663: ifnull +6 -> 669
    //   666: aload 4
    //   668: athrow
    //   669: aload_3
    //   670: athrow
    //   671: aload_0
    //   672: invokevirtual 2287	android/content/Context:getPackageName	()Ljava/lang/String;
    //   675: invokevirtual 2253	java/lang/String:length	()I
    //   678: bipush 7
    //   680: isub
    //   681: aload_0
    //   682: invokevirtual 2238	android/content/Context:getResources	()Landroid/content/res/Resources;
    //   685: ldc_w 2426
    //   688: invokevirtual 2245	android/content/res/Resources:getString	(I)Ljava/lang/String;
    //   691: iconst_0
    //   692: iconst_4
    //   693: invokevirtual 2249	java/lang/String:substring	(II)Ljava/lang/String;
    //   696: invokevirtual 2253	java/lang/String:length	()I
    //   699: sipush 358
    //   702: iadd
    //   703: aload_0
    //   704: invokevirtual 2238	android/content/Context:getResources	()Landroid/content/res/Resources;
    //   707: ldc_w 2427
    //   710: invokevirtual 2245	android/content/res/Resources:getString	(I)Ljava/lang/String;
    //   713: iconst_0
    //   714: iconst_5
    //   715: invokevirtual 2249	java/lang/String:substring	(II)Ljava/lang/String;
    //   718: iconst_4
    //   719: invokevirtual 2258	java/lang/String:codePointAt	(I)I
    //   722: ldc_w 2428
    //   725: iadd
    //   726: i2c
    //   727: invokestatic 2264	o/O:ˋ	(IIC)Ljava/lang/Object;
    //   730: checkcast 2266	java/lang/Class
    //   733: ldc_w 2423
    //   736: aconst_null
    //   737: invokevirtual 2293	java/lang/Class:getMethod	(Ljava/lang/String;[Ljava/lang/Class;)Ljava/lang/reflect/Method;
    //   740: aload_3
    //   741: aconst_null
    //   742: invokevirtual 2299	java/lang/reflect/Method:invoke	(Ljava/lang/Object;[Ljava/lang/Object;)Ljava/lang/Object;
    //   745: checkcast 2407	java/lang/CharSequence
    //   748: astore_3
    //   749: aload_3
    //   750: invokestatic 2229	android/text/TextUtils:isEmpty	(Ljava/lang/CharSequence;)Z
    //   753: istore_2
    //   754: iload_2
    //   755: ifeq +6 -> 761
    //   758: goto +280 -> 1038
    //   761: goto -755 -> 6
    //   764: getstatic 23	o/Dt:ʼ	I
    //   767: istore_1
    //   768: iload_1
    //   769: bipush 75
    //   771: iadd
    //   772: istore_1
    //   773: iload_1
    //   774: sipush 128
    //   777: irem
    //   778: putstatic 21	o/Dt:ॱॱ	I
    //   781: iload_1
    //   782: iconst_2
    //   783: irem
    //   784: ifeq +6 -> 790
    //   787: goto -410 -> 377
    //   790: goto +633 -> 1423
    //   793: astore_3
    //   794: aload_0
    //   795: invokevirtual 2287	android/content/Context:getPackageName	()Ljava/lang/String;
    //   798: bipush 9
    //   800: invokevirtual 2258	java/lang/String:codePointAt	(I)I
    //   803: bipush 94
    //   805: isub
    //   806: aload_0
    //   807: invokevirtual 2200	android/content/Context:getApplicationInfo	()Landroid/content/pm/ApplicationInfo;
    //   810: getfield 2205	android/content/pm/ApplicationInfo:targetSdkVersion	I
    //   813: bipush 25
    //   815: isub
    //   816: i2c
    //   817: aload_0
    //   818: invokevirtual 2238	android/content/Context:getResources	()Landroid/content/res/Resources;
    //   821: ldc_w 2429
    //   824: invokevirtual 2245	android/content/res/Resources:getString	(I)Ljava/lang/String;
    //   827: iconst_0
    //   828: iconst_5
    //   829: invokevirtual 2249	java/lang/String:substring	(II)Ljava/lang/String;
    //   832: iconst_2
    //   833: invokevirtual 2258	java/lang/String:codePointAt	(I)I
    //   836: iconst_4
    //   837: isub
    //   838: invokestatic 2208	o/Dt:ˏ	(ICI)Ljava/lang/String;
    //   841: invokevirtual 2214	java/lang/String:intern	()Ljava/lang/String;
    //   844: astore 4
    //   846: aload_0
    //   847: invokevirtual 2238	android/content/Context:getResources	()Landroid/content/res/Resources;
    //   850: ldc_w 2430
    //   853: invokevirtual 2245	android/content/res/Resources:getString	(I)Ljava/lang/String;
    //   856: iconst_0
    //   857: iconst_4
    //   858: invokevirtual 2249	java/lang/String:substring	(II)Ljava/lang/String;
    //   861: iconst_0
    //   862: invokevirtual 2258	java/lang/String:codePointAt	(I)I
    //   865: bipush 95
    //   867: iadd
    //   868: aload_0
    //   869: invokevirtual 2238	android/content/Context:getResources	()Landroid/content/res/Resources;
    //   872: ldc_w 2431
    //   875: invokevirtual 2245	android/content/res/Resources:getString	(I)Ljava/lang/String;
    //   878: iconst_0
    //   879: iconst_4
    //   880: invokevirtual 2249	java/lang/String:substring	(II)Ljava/lang/String;
    //   883: invokevirtual 2253	java/lang/String:length	()I
    //   886: ldc_w 2432
    //   889: iadd
    //   890: i2c
    //   891: aload_0
    //   892: invokevirtual 2287	android/content/Context:getPackageName	()Ljava/lang/String;
    //   895: bipush 9
    //   897: invokevirtual 2258	java/lang/String:codePointAt	(I)I
    //   900: bipush 68
    //   902: isub
    //   903: invokestatic 2208	o/Dt:ˏ	(ICI)Ljava/lang/String;
    //   906: invokevirtual 2214	java/lang/String:intern	()Ljava/lang/String;
    //   909: astore_3
    //   910: goto +20 -> 930
    //   913: astore 4
    //   915: aload 4
    //   917: invokevirtual 2284	java/lang/Throwable:getCause	()Ljava/lang/Throwable;
    //   920: astore_3
    //   921: aload_3
    //   922: ifnull +5 -> 927
    //   925: aload_3
    //   926: athrow
    //   927: aload 4
    //   929: athrow
    //   930: aload_0
    //   931: invokevirtual 2200	android/content/Context:getApplicationInfo	()Landroid/content/pm/ApplicationInfo;
    //   934: getfield 2205	android/content/pm/ApplicationInfo:targetSdkVersion	I
    //   937: bipush 21
    //   939: isub
    //   940: aload_0
    //   941: invokevirtual 2238	android/content/Context:getResources	()Landroid/content/res/Resources;
    //   944: ldc_w 2433
    //   947: invokevirtual 2245	android/content/res/Resources:getString	(I)Ljava/lang/String;
    //   950: iconst_0
    //   951: bipush 10
    //   953: invokevirtual 2249	java/lang/String:substring	(II)Ljava/lang/String;
    //   956: invokevirtual 2253	java/lang/String:length	()I
    //   959: bipush 32
    //   961: iadd
    //   962: aload_0
    //   963: invokevirtual 2238	android/content/Context:getResources	()Landroid/content/res/Resources;
    //   966: ldc_w 2434
    //   969: invokevirtual 2245	android/content/res/Resources:getString	(I)Ljava/lang/String;
    //   972: iconst_0
    //   973: bipush 8
    //   975: invokevirtual 2249	java/lang/String:substring	(II)Ljava/lang/String;
    //   978: invokevirtual 2253	java/lang/String:length	()I
    //   981: ldc_w 2435
    //   984: iadd
    //   985: i2c
    //   986: invokestatic 2264	o/O:ˋ	(IIC)Ljava/lang/Object;
    //   989: checkcast 2266	java/lang/Class
    //   992: ldc_w 2392
    //   995: iconst_2
    //   996: anewarray 2266	java/lang/Class
    //   999: dup
    //   1000: iconst_0
    //   1001: ldc_w 2210
    //   1004: aastore
    //   1005: dup
    //   1006: iconst_1
    //   1007: ldc_w 2210
    //   1010: aastore
    //   1011: invokevirtual 2293	java/lang/Class:getMethod	(Ljava/lang/String;[Ljava/lang/Class;)Ljava/lang/reflect/Method;
    //   1014: aconst_null
    //   1015: iconst_2
    //   1016: anewarray 2322	java/lang/Object
    //   1019: dup
    //   1020: iconst_0
    //   1021: aload 4
    //   1023: aastore
    //   1024: dup
    //   1025: iconst_1
    //   1026: aload_3
    //   1027: aastore
    //   1028: invokevirtual 2299	java/lang/reflect/Method:invoke	(Ljava/lang/Object;[Ljava/lang/Object;)Ljava/lang/Object;
    //   1031: pop
    //   1032: goto -650 -> 382
    //   1035: goto -271 -> 764
    //   1038: aload_0
    //   1039: invokevirtual 2238	android/content/Context:getResources	()Landroid/content/res/Resources;
    //   1042: ldc_w 2436
    //   1045: invokevirtual 2245	android/content/res/Resources:getString	(I)Ljava/lang/String;
    //   1048: iconst_0
    //   1049: iconst_4
    //   1050: invokevirtual 2249	java/lang/String:substring	(II)Ljava/lang/String;
    //   1053: iconst_3
    //   1054: invokevirtual 2258	java/lang/String:codePointAt	(I)I
    //   1057: bipush 85
    //   1059: iadd
    //   1060: aload_0
    //   1061: invokevirtual 2238	android/content/Context:getResources	()Landroid/content/res/Resources;
    //   1064: ldc_w 2437
    //   1067: invokevirtual 2245	android/content/res/Resources:getString	(I)Ljava/lang/String;
    //   1070: bipush 7
    //   1072: bipush 15
    //   1074: invokevirtual 2249	java/lang/String:substring	(II)Ljava/lang/String;
    //   1077: invokevirtual 2253	java/lang/String:length	()I
    //   1080: ldc_w 2438
    //   1083: iadd
    //   1084: i2c
    //   1085: aload_0
    //   1086: invokevirtual 2238	android/content/Context:getResources	()Landroid/content/res/Resources;
    //   1089: ldc_w 2317
    //   1092: invokevirtual 2245	android/content/res/Resources:getString	(I)Ljava/lang/String;
    //   1095: iconst_0
    //   1096: bipush 9
    //   1098: invokevirtual 2249	java/lang/String:substring	(II)Ljava/lang/String;
    //   1101: invokevirtual 2253	java/lang/String:length	()I
    //   1104: bipush 6
    //   1106: isub
    //   1107: invokestatic 2208	o/Dt:ˏ	(ICI)Ljava/lang/String;
    //   1110: invokevirtual 2214	java/lang/String:intern	()Ljava/lang/String;
    //   1113: invokestatic 2444	javax/crypto/KeyGenerator:getInstance	(Ljava/lang/String;)Ljavax/crypto/KeyGenerator;
    //   1116: astore_3
    //   1117: aload_3
    //   1118: sipush 256
    //   1121: invokevirtual 2448	javax/crypto/KeyGenerator:init	(I)V
    //   1124: aload_3
    //   1125: invokevirtual 2452	javax/crypto/KeyGenerator:generateKey	()Ljavax/crypto/SecretKey;
    //   1128: invokeinterface 2366 1 0
    //   1133: iconst_2
    //   1134: invokestatic 2372	android/util/Base64:encodeToString	([BI)Ljava/lang/String;
    //   1137: astore_3
    //   1138: aload_0
    //   1139: invokevirtual 2238	android/content/Context:getResources	()Landroid/content/res/Resources;
    //   1142: ldc_w 2453
    //   1145: invokevirtual 2245	android/content/res/Resources:getString	(I)Ljava/lang/String;
    //   1148: iconst_0
    //   1149: iconst_4
    //   1150: invokevirtual 2249	java/lang/String:substring	(II)Ljava/lang/String;
    //   1153: iconst_3
    //   1154: invokevirtual 2258	java/lang/String:codePointAt	(I)I
    //   1157: bipush 8
    //   1159: isub
    //   1160: aload_0
    //   1161: invokevirtual 2238	android/content/Context:getResources	()Landroid/content/res/Resources;
    //   1164: ldc_w 2375
    //   1167: invokevirtual 2245	android/content/res/Resources:getString	(I)Ljava/lang/String;
    //   1170: iconst_0
    //   1171: iconst_4
    //   1172: invokevirtual 2249	java/lang/String:substring	(II)Ljava/lang/String;
    //   1175: invokevirtual 2253	java/lang/String:length	()I
    //   1178: sipush 358
    //   1181: iadd
    //   1182: aload_0
    //   1183: invokevirtual 2287	android/content/Context:getPackageName	()Ljava/lang/String;
    //   1186: iconst_0
    //   1187: invokevirtual 2258	java/lang/String:codePointAt	(I)I
    //   1190: ldc_w 2454
    //   1193: iadd
    //   1194: i2c
    //   1195: invokestatic 2264	o/O:ˋ	(IIC)Ljava/lang/Object;
    //   1198: checkcast 2266	java/lang/Class
    //   1201: ldc_w 2268
    //   1204: invokevirtual 2272	java/lang/Class:getField	(Ljava/lang/String;)Ljava/lang/reflect/Field;
    //   1207: aconst_null
    //   1208: invokevirtual 2278	java/lang/reflect/Field:get	(Ljava/lang/Object;)Ljava/lang/Object;
    //   1211: astore 4
    //   1213: goto +20 -> 1233
    //   1216: astore 4
    //   1218: aload 4
    //   1220: invokevirtual 2284	java/lang/Throwable:getCause	()Ljava/lang/Throwable;
    //   1223: astore_3
    //   1224: aload_3
    //   1225: ifnull +5 -> 1230
    //   1228: aload_3
    //   1229: athrow
    //   1230: aload 4
    //   1232: athrow
    //   1233: aload_0
    //   1234: invokevirtual 2287	android/content/Context:getPackageName	()Ljava/lang/String;
    //   1237: invokevirtual 2253	java/lang/String:length	()I
    //   1240: iconst_4
    //   1241: isub
    //   1242: aload_0
    //   1243: invokevirtual 2238	android/content/Context:getResources	()Landroid/content/res/Resources;
    //   1246: ldc_w 2455
    //   1249: invokevirtual 2245	android/content/res/Resources:getString	(I)Ljava/lang/String;
    //   1252: iconst_0
    //   1253: iconst_5
    //   1254: invokevirtual 2249	java/lang/String:substring	(II)Ljava/lang/String;
    //   1257: invokevirtual 2253	java/lang/String:length	()I
    //   1260: sipush 361
    //   1263: iadd
    //   1264: aload_0
    //   1265: invokevirtual 2238	android/content/Context:getResources	()Landroid/content/res/Resources;
    //   1268: ldc_w 2456
    //   1271: invokevirtual 2245	android/content/res/Resources:getString	(I)Ljava/lang/String;
    //   1274: iconst_0
    //   1275: iconst_4
    //   1276: invokevirtual 2249	java/lang/String:substring	(II)Ljava/lang/String;
    //   1279: invokevirtual 2253	java/lang/String:length	()I
    //   1282: iconst_4
    //   1283: isub
    //   1284: i2c
    //   1285: invokestatic 2264	o/O:ˋ	(IIC)Ljava/lang/Object;
    //   1288: checkcast 2266	java/lang/Class
    //   1291: ldc_w 2289
    //   1294: aconst_null
    //   1295: invokevirtual 2293	java/lang/Class:getMethod	(Ljava/lang/String;[Ljava/lang/Class;)Ljava/lang/reflect/Method;
    //   1298: aload 4
    //   1300: aconst_null
    //   1301: invokevirtual 2299	java/lang/reflect/Method:invoke	(Ljava/lang/Object;[Ljava/lang/Object;)Ljava/lang/Object;
    //   1304: astore 4
    //   1306: goto +20 -> 1326
    //   1309: astore_3
    //   1310: aload_3
    //   1311: invokevirtual 2284	java/lang/Throwable:getCause	()Ljava/lang/Throwable;
    //   1314: astore 4
    //   1316: aload 4
    //   1318: ifnull +6 -> 1324
    //   1321: aload 4
    //   1323: athrow
    //   1324: aload_3
    //   1325: athrow
    //   1326: aload_0
    //   1327: invokevirtual 2238	android/content/Context:getResources	()Landroid/content/res/Resources;
    //   1330: ldc_w 2457
    //   1333: invokevirtual 2245	android/content/res/Resources:getString	(I)Ljava/lang/String;
    //   1336: iconst_5
    //   1337: bipush 6
    //   1339: invokevirtual 2249	java/lang/String:substring	(II)Ljava/lang/String;
    //   1342: iconst_0
    //   1343: invokevirtual 2258	java/lang/String:codePointAt	(I)I
    //   1346: bipush 101
    //   1348: isub
    //   1349: aload_0
    //   1350: invokevirtual 2287	android/content/Context:getPackageName	()Ljava/lang/String;
    //   1353: invokevirtual 2253	java/lang/String:length	()I
    //   1356: sipush 351
    //   1359: iadd
    //   1360: aload_0
    //   1361: invokevirtual 2238	android/content/Context:getResources	()Landroid/content/res/Resources;
    //   1364: ldc_w 2458
    //   1367: invokevirtual 2245	android/content/res/Resources:getString	(I)Ljava/lang/String;
    //   1370: iconst_0
    //   1371: iconst_5
    //   1372: invokevirtual 2249	java/lang/String:substring	(II)Ljava/lang/String;
    //   1375: iconst_1
    //   1376: invokevirtual 2258	java/lang/String:codePointAt	(I)I
    //   1379: ldc_w 2307
    //   1382: iadd
    //   1383: i2c
    //   1384: invokestatic 2264	o/O:ˋ	(IIC)Ljava/lang/Object;
    //   1387: checkcast 2266	java/lang/Class
    //   1390: ldc_w 2460
    //   1393: iconst_1
    //   1394: anewarray 2266	java/lang/Class
    //   1397: dup
    //   1398: iconst_0
    //   1399: ldc_w 2210
    //   1402: aastore
    //   1403: invokevirtual 2293	java/lang/Class:getMethod	(Ljava/lang/String;[Ljava/lang/Class;)Ljava/lang/reflect/Method;
    //   1406: aload 4
    //   1408: iconst_1
    //   1409: anewarray 2322	java/lang/Object
    //   1412: dup
    //   1413: iconst_0
    //   1414: aload_3
    //   1415: aastore
    //   1416: invokevirtual 2299	java/lang/reflect/Method:invoke	(Ljava/lang/Object;[Ljava/lang/Object;)Ljava/lang/Object;
    //   1419: pop
    //   1420: goto -1414 -> 6
    //   1423: iconst_0
    //   1424: istore_1
    //   1425: goto -984 -> 441
    // Local variable table:
    //   start	length	slot	name	signature
    //   0	1428	0	this	Dt
    //   378	1047	1	i	int
    //   753	2	2	bool	boolean
    //   9	82	3	localObject1	Object
    //   170	1	3	localObject2	Object
    //   174	75	3	localObject3	Object
    //   253	112	3	localObject4	Object
    //   467	2	3	localException	Exception
    //   556	1	3	localObject5	Object
    //   560	86	3	localObject6	Object
    //   650	1	3	localObject7	Object
    //   654	87	3	localObject8	Object
    //   748	2	3	localCharSequence	CharSequence
    //   793	1	3	localNoSuchAlgorithmException	java.security.NoSuchAlgorithmException
    //   909	320	3	localObject9	Object
    //   1309	106	3	localObject10	Object
    //   14	173	4	localThrowable	Throwable
    //   257	15	4	localObject11	Object
    //   565	280	4	localObject12	Object
    //   913	109	4	localObject13	Object
    //   1211	1	4	localObject14	Object
    //   1216	83	4	localObject15	Object
    //   1304	103	4	localObject16	Object
    // Exception table:
    //   from	to	target	type
    //   26	96	9	finally
    //   191	254	174	finally
    //   274	364	257	finally
    //   764	768	467	java/lang/Exception
    //   773	781	467	java/lang/Exception
    //   577	651	560	finally
    //   671	749	654	finally
    //   10	16	793	java/security/NoSuchAlgorithmException
    //   21	24	793	java/security/NoSuchAlgorithmException
    //   24	26	793	java/security/NoSuchAlgorithmException
    //   99	171	793	java/security/NoSuchAlgorithmException
    //   175	181	793	java/security/NoSuchAlgorithmException
    //   186	189	793	java/security/NoSuchAlgorithmException
    //   189	191	793	java/security/NoSuchAlgorithmException
    //   259	265	793	java/security/NoSuchAlgorithmException
    //   269	271	793	java/security/NoSuchAlgorithmException
    //   271	274	793	java/security/NoSuchAlgorithmException
    //   364	377	793	java/security/NoSuchAlgorithmException
    //   507	557	793	java/security/NoSuchAlgorithmException
    //   561	567	793	java/security/NoSuchAlgorithmException
    //   572	575	793	java/security/NoSuchAlgorithmException
    //   575	577	793	java/security/NoSuchAlgorithmException
    //   655	661	793	java/security/NoSuchAlgorithmException
    //   666	669	793	java/security/NoSuchAlgorithmException
    //   669	671	793	java/security/NoSuchAlgorithmException
    //   749	754	793	java/security/NoSuchAlgorithmException
    //   1038	1213	793	java/security/NoSuchAlgorithmException
    //   1218	1224	793	java/security/NoSuchAlgorithmException
    //   1228	1230	793	java/security/NoSuchAlgorithmException
    //   1230	1233	793	java/security/NoSuchAlgorithmException
    //   1310	1316	793	java/security/NoSuchAlgorithmException
    //   1321	1324	793	java/security/NoSuchAlgorithmException
    //   1324	1326	793	java/security/NoSuchAlgorithmException
    //   930	1032	913	finally
    //   1233	1306	1216	finally
    //   1326	1420	1309	finally
  }
  
  public Resources getResources()
  {
    break label69;
    int i = ʼ + 93;
    ॱॱ = i % 128;
    label30:
    Resources localResources;
    if (i % 2 == 0)
    {
      break label58;
      i = ʼ + 121;
      ॱॱ = i % 128;
      if (i % 2 == 0) {
        return localResources;
      }
      return localResources;
    }
    for (;;)
    {
      label58:
      localResources = oH.ˊ(super.getResources());
      break label30;
      label69:
      break;
    }
  }
  
  public void onActivityResumed(Activity paramActivity)
  {
    for (;;)
    {
      int i = ʼ + 101;
      ॱॱ = i % 128;
      if (i % 2 == 0) {
        return;
      }
      switch (i)
      {
      default: 
        break;
      case 1: 
        for (;;)
        {
          label28:
          i = ॱॱ + 17;
          ʼ = i % 128;
          if (i % 2 != 0)
          {
            i = 0;
            break label28;
            super.onActivityResumed(paramActivity);
            GA.ॱ.ˏ().ˊ(paramActivity);
            i = 35 / 0;
            break;
            return;
          }
          i = 1;
          break label28;
        }
      }
      super.onActivityResumed(paramActivity);
      GA.ॱ.ˏ().ˊ(paramActivity);
    }
  }
  
  public void onCreate()
  {
    break label77;
    for (;;)
    {
      int i = ॱॱ + 1;
      ʼ = i % 128;
      if (i % 2 == 0) {
        break;
      }
      return;
    }
    return;
    for (;;)
    {
      Gz.ˏ(this).ˋ();
      this.ˋ = Thread.getDefaultUncaughtExceptionHandler();
      Thread.setDefaultUncaughtExceptionHandler(ॱॱ());
      ॱᐝ();
      ᐝॱ();
      DT.ˎ.ˎ().ˋ();
      ˏ();
      ʻ();
      return;
      label77:
      super.onCreate();
      ˏ = this;
      qr.ॱ(this, new qw[] { new Crashlytics() });
      if (!Gz.ˏ(this).ˎ()) {
        break;
      }
    }
  }
  
  /* Error */
  public void uncaughtException(Thread paramThread, Throwable paramThrowable)
  {
    // Byte code:
    //   0: goto +41 -> 41
    //   3: iload_3
    //   4: lookupswitch	default:+28->32, 30:+541->545, 64:+73->77
    //   32: goto +45 -> 77
    //   35: bipush 30
    //   37: istore_3
    //   38: goto -35 -> 3
    //   41: goto +146 -> 187
    //   44: bipush 7
    //   46: istore_3
    //   47: goto +109 -> 156
    //   50: astore_1
    //   51: aload_1
    //   52: athrow
    //   53: bipush 70
    //   55: istore_3
    //   56: goto +100 -> 156
    //   59: aload_0
    //   60: getfield 2499	o/Dt:ˋ	Ljava/lang/Thread$UncaughtExceptionHandler;
    //   63: aload_1
    //   64: aload_2
    //   65: invokeinterface 2540 3 0
    //   70: iconst_0
    //   71: invokestatic 2545	java/lang/System:exit	(I)V
    //   74: goto +55 -> 129
    //   77: invokestatic 2549	java/lang/System:currentTimeMillis	()J
    //   80: lstore 4
    //   82: aload 7
    //   84: iconst_1
    //   85: lload 4
    //   87: ldc2_w 2550
    //   90: ladd
    //   91: aload 6
    //   93: invokevirtual 2557	android/app/AlarmManager:set	(IJLandroid/app/PendingIntent;)V
    //   96: goto -37 -> 59
    //   99: astore_1
    //   100: aload_1
    //   101: athrow
    //   102: getstatic 23	o/Dt:ʼ	I
    //   105: bipush 63
    //   107: iadd
    //   108: istore_3
    //   109: iload_3
    //   110: sipush 128
    //   113: irem
    //   114: putstatic 21	o/Dt:ॱॱ	I
    //   117: iload_3
    //   118: iconst_2
    //   119: irem
    //   120: ifeq +6 -> 126
    //   123: goto -88 -> 35
    //   126: goto +438 -> 564
    //   129: getstatic 21	o/Dt:ॱॱ	I
    //   132: istore_3
    //   133: iload_3
    //   134: bipush 57
    //   136: iadd
    //   137: istore_3
    //   138: iload_3
    //   139: sipush 128
    //   142: irem
    //   143: putstatic 23	o/Dt:ʼ	I
    //   146: iload_3
    //   147: iconst_2
    //   148: irem
    //   149: ifne +6 -> 155
    //   152: goto +411 -> 563
    //   155: return
    //   156: iload_3
    //   157: lookupswitch	default:+27->184, 7:+-98->59, 70:+-55->102
    //   184: goto -125 -> 59
    //   187: aload_0
    //   188: invokevirtual 2200	android/content/Context:getApplicationInfo	()Landroid/content/pm/ApplicationInfo;
    //   191: getfield 2205	android/content/pm/ApplicationInfo:targetSdkVersion	I
    //   194: bipush 22
    //   196: isub
    //   197: aload_0
    //   198: invokevirtual 2287	android/content/Context:getPackageName	()Ljava/lang/String;
    //   201: invokevirtual 2253	java/lang/String:length	()I
    //   204: bipush 11
    //   206: isub
    //   207: i2c
    //   208: aload_0
    //   209: invokevirtual 2238	android/content/Context:getResources	()Landroid/content/res/Resources;
    //   212: ldc_w 2558
    //   215: invokevirtual 2245	android/content/res/Resources:getString	(I)Ljava/lang/String;
    //   218: iconst_0
    //   219: iconst_5
    //   220: invokevirtual 2249	java/lang/String:substring	(II)Ljava/lang/String;
    //   223: invokevirtual 2253	java/lang/String:length	()I
    //   226: iconst_2
    //   227: iadd
    //   228: invokestatic 2208	o/Dt:ˏ	(ICI)Ljava/lang/String;
    //   231: invokevirtual 2214	java/lang/String:intern	()Ljava/lang/String;
    //   234: astore 6
    //   236: new 2560	java/lang/StringBuilder
    //   239: dup
    //   240: invokespecial 2561	java/lang/StringBuilder:<init>	()V
    //   243: aload_0
    //   244: invokevirtual 2200	android/content/Context:getApplicationInfo	()Landroid/content/pm/ApplicationInfo;
    //   247: getfield 2205	android/content/pm/ApplicationInfo:targetSdkVersion	I
    //   250: sipush 2162
    //   253: iadd
    //   254: aload_0
    //   255: invokevirtual 2200	android/content/Context:getApplicationInfo	()Landroid/content/pm/ApplicationInfo;
    //   258: getfield 2205	android/content/pm/ApplicationInfo:targetSdkVersion	I
    //   261: bipush 25
    //   263: isub
    //   264: i2c
    //   265: aload_0
    //   266: invokevirtual 2238	android/content/Context:getResources	()Landroid/content/res/Resources;
    //   269: ldc_w 2562
    //   272: invokevirtual 2245	android/content/res/Resources:getString	(I)Ljava/lang/String;
    //   275: iconst_0
    //   276: iconst_5
    //   277: invokevirtual 2249	java/lang/String:substring	(II)Ljava/lang/String;
    //   280: iconst_3
    //   281: invokevirtual 2258	java/lang/String:codePointAt	(I)I
    //   284: bipush 13
    //   286: iadd
    //   287: invokestatic 2208	o/Dt:ˏ	(ICI)Ljava/lang/String;
    //   290: invokevirtual 2214	java/lang/String:intern	()Ljava/lang/String;
    //   293: invokevirtual 2566	java/lang/StringBuilder:append	(Ljava/lang/String;)Ljava/lang/StringBuilder;
    //   296: aload_2
    //   297: invokevirtual 2569	java/lang/Throwable:getMessage	()Ljava/lang/String;
    //   300: invokevirtual 2566	java/lang/StringBuilder:append	(Ljava/lang/String;)Ljava/lang/StringBuilder;
    //   303: invokevirtual 2572	java/lang/StringBuilder:toString	()Ljava/lang/String;
    //   306: astore 7
    //   308: goto +17 -> 325
    //   311: astore_1
    //   312: aload_1
    //   313: invokevirtual 2284	java/lang/Throwable:getCause	()Ljava/lang/Throwable;
    //   316: astore_2
    //   317: aload_2
    //   318: ifnull +5 -> 323
    //   321: aload_2
    //   322: athrow
    //   323: aload_1
    //   324: athrow
    //   325: aload_0
    //   326: invokevirtual 2238	android/content/Context:getResources	()Landroid/content/res/Resources;
    //   329: ldc_w 2573
    //   332: invokevirtual 2245	android/content/res/Resources:getString	(I)Ljava/lang/String;
    //   335: iconst_0
    //   336: iconst_4
    //   337: invokevirtual 2249	java/lang/String:substring	(II)Ljava/lang/String;
    //   340: iconst_1
    //   341: invokevirtual 2258	java/lang/String:codePointAt	(I)I
    //   344: bipush 22
    //   346: isub
    //   347: aload_0
    //   348: invokevirtual 2238	android/content/Context:getResources	()Landroid/content/res/Resources;
    //   351: ldc_w 2574
    //   354: invokevirtual 2245	android/content/res/Resources:getString	(I)Ljava/lang/String;
    //   357: iconst_0
    //   358: iconst_4
    //   359: invokevirtual 2249	java/lang/String:substring	(II)Ljava/lang/String;
    //   362: iconst_2
    //   363: invokevirtual 2258	java/lang/String:codePointAt	(I)I
    //   366: bipush 31
    //   368: iadd
    //   369: aload_0
    //   370: invokevirtual 2200	android/content/Context:getApplicationInfo	()Landroid/content/pm/ApplicationInfo;
    //   373: getfield 2205	android/content/pm/ApplicationInfo:targetSdkVersion	I
    //   376: ldc_w 2390
    //   379: iadd
    //   380: i2c
    //   381: invokestatic 2264	o/O:ˋ	(IIC)Ljava/lang/Object;
    //   384: checkcast 2266	java/lang/Class
    //   387: ldc_w 2392
    //   390: iconst_2
    //   391: anewarray 2266	java/lang/Class
    //   394: dup
    //   395: iconst_0
    //   396: ldc_w 2210
    //   399: aastore
    //   400: dup
    //   401: iconst_1
    //   402: ldc_w 2210
    //   405: aastore
    //   406: invokevirtual 2293	java/lang/Class:getMethod	(Ljava/lang/String;[Ljava/lang/Class;)Ljava/lang/reflect/Method;
    //   409: aconst_null
    //   410: iconst_2
    //   411: anewarray 2322	java/lang/Object
    //   414: dup
    //   415: iconst_0
    //   416: aload 6
    //   418: aastore
    //   419: dup
    //   420: iconst_1
    //   421: aload 7
    //   423: aastore
    //   424: invokevirtual 2299	java/lang/reflect/Method:invoke	(Ljava/lang/Object;[Ljava/lang/Object;)Ljava/lang/Object;
    //   427: pop
    //   428: aload_0
    //   429: invokestatic 2579	o/Ic:ˏ	(Landroid/content/Context;)Lo/Ic;
    //   432: invokevirtual 2582	o/Ic:ॱॱ	()Lo/j;
    //   435: invokevirtual 2587	o/j:ˋ	()Landroid/content/Intent;
    //   438: astore 6
    //   440: aload 6
    //   442: ldc_w 2588
    //   445: invokevirtual 2594	android/content/Intent:addFlags	(I)Landroid/content/Intent;
    //   448: pop
    //   449: aload_0
    //   450: iconst_0
    //   451: aload 6
    //   453: ldc_w 2595
    //   456: invokestatic 2601	android/app/PendingIntent:getActivity	(Landroid/content/Context;ILandroid/content/Intent;I)Landroid/app/PendingIntent;
    //   459: astore 6
    //   461: aload_0
    //   462: aload_0
    //   463: invokevirtual 2238	android/content/Context:getResources	()Landroid/content/res/Resources;
    //   466: ldc_w 2602
    //   469: invokevirtual 2245	android/content/res/Resources:getString	(I)Ljava/lang/String;
    //   472: iconst_0
    //   473: iconst_4
    //   474: invokevirtual 2249	java/lang/String:substring	(II)Ljava/lang/String;
    //   477: iconst_2
    //   478: invokevirtual 2258	java/lang/String:codePointAt	(I)I
    //   481: sipush 2201
    //   484: iadd
    //   485: aload_0
    //   486: invokevirtual 2200	android/content/Context:getApplicationInfo	()Landroid/content/pm/ApplicationInfo;
    //   489: getfield 2205	android/content/pm/ApplicationInfo:targetSdkVersion	I
    //   492: sipush 20506
    //   495: iadd
    //   496: i2c
    //   497: aload_0
    //   498: invokevirtual 2238	android/content/Context:getResources	()Landroid/content/res/Resources;
    //   501: ldc_w 2603
    //   504: invokevirtual 2245	android/content/res/Resources:getString	(I)Ljava/lang/String;
    //   507: iconst_0
    //   508: bipush 9
    //   510: invokevirtual 2249	java/lang/String:substring	(II)Ljava/lang/String;
    //   513: iconst_1
    //   514: invokevirtual 2258	java/lang/String:codePointAt	(I)I
    //   517: bipush 21
    //   519: isub
    //   520: invokestatic 2208	o/Dt:ˏ	(ICI)Ljava/lang/String;
    //   523: invokevirtual 2214	java/lang/String:intern	()Ljava/lang/String;
    //   526: invokevirtual 2607	o/Dt:getSystemService	(Ljava/lang/String;)Ljava/lang/Object;
    //   529: checkcast 2553	android/app/AlarmManager
    //   532: astore 7
    //   534: aload 7
    //   536: ifnull +6 -> 542
    //   539: goto -486 -> 53
    //   542: goto -498 -> 44
    //   545: aload 7
    //   547: iconst_1
    //   548: invokestatic 2549	java/lang/System:currentTimeMillis	()J
    //   551: ldc2_w 2550
    //   554: lmul
    //   555: aload 6
    //   557: invokevirtual 2557	android/app/AlarmManager:set	(IJLandroid/app/PendingIntent;)V
    //   560: goto -501 -> 59
    //   563: return
    //   564: bipush 64
    //   566: istore_3
    //   567: goto -564 -> 3
    // Local variable table:
    //   start	length	slot	name	signature
    //   0	570	0	this	Dt
    //   0	570	1	paramThread	Thread
    //   0	570	2	paramThrowable	Throwable
    //   3	564	3	i	int
    //   80	6	4	l	long
    //   91	465	6	localObject1	Object
    //   82	464	7	localObject2	Object
    // Exception table:
    //   from	to	target	type
    //   77	82	50	java/lang/Exception
    //   82	96	50	java/lang/Exception
    //   129	133	99	java/lang/Exception
    //   138	146	99	java/lang/Exception
    //   325	428	311	finally
  }
  
  /* Error */
  public void ʻ()
  {
    // Byte code:
    //   0: goto +6 -> 6
    //   3: astore_3
    //   4: aload_3
    //   5: athrow
    //   6: getstatic 21	o/Dt:ॱॱ	I
    //   9: bipush 87
    //   11: iadd
    //   12: istore_1
    //   13: iload_1
    //   14: sipush 128
    //   17: irem
    //   18: putstatic 23	o/Dt:ʼ	I
    //   21: iload_1
    //   22: iconst_2
    //   23: irem
    //   24: ifne +6 -> 30
    //   27: goto +391 -> 418
    //   30: goto +482 -> 512
    //   33: return
    //   34: iload_1
    //   35: tableswitch	default:+21->56, 0:+423->458, 1:+28->63
    //   56: goto +402 -> 458
    //   59: iconst_3
    //   60: iconst_2
    //   61: idiv
    //   62: istore_1
    //   63: return
    //   64: aload_0
    //   65: invokevirtual 2238	android/content/Context:getResources	()Landroid/content/res/Resources;
    //   68: ldc_w 2608
    //   71: invokevirtual 2245	android/content/res/Resources:getString	(I)Ljava/lang/String;
    //   74: iconst_0
    //   75: iconst_4
    //   76: invokevirtual 2249	java/lang/String:substring	(II)Ljava/lang/String;
    //   79: invokevirtual 2253	java/lang/String:length	()I
    //   82: iconst_0
    //   83: iadd
    //   84: aload_0
    //   85: invokevirtual 2238	android/content/Context:getResources	()Landroid/content/res/Resources;
    //   88: ldc_w 2609
    //   91: invokevirtual 2245	android/content/res/Resources:getString	(I)Ljava/lang/String;
    //   94: iconst_0
    //   95: iconst_4
    //   96: invokevirtual 2249	java/lang/String:substring	(II)Ljava/lang/String;
    //   99: invokevirtual 2253	java/lang/String:length	()I
    //   102: sipush 160
    //   105: iadd
    //   106: aload_0
    //   107: invokevirtual 2238	android/content/Context:getResources	()Landroid/content/res/Resources;
    //   110: ldc_w 2610
    //   113: invokevirtual 2245	android/content/res/Resources:getString	(I)Ljava/lang/String;
    //   116: iconst_0
    //   117: iconst_4
    //   118: invokevirtual 2249	java/lang/String:substring	(II)Ljava/lang/String;
    //   121: iconst_1
    //   122: invokevirtual 2258	java/lang/String:codePointAt	(I)I
    //   125: bipush 26
    //   127: isub
    //   128: i2c
    //   129: invokestatic 2264	o/O:ˋ	(IIC)Ljava/lang/Object;
    //   132: checkcast 2266	java/lang/Class
    //   135: ldc_w 2353
    //   138: invokevirtual 2272	java/lang/Class:getField	(Ljava/lang/String;)Ljava/lang/reflect/Field;
    //   141: aconst_null
    //   142: invokevirtual 2278	java/lang/reflect/Field:get	(Ljava/lang/Object;)Ljava/lang/Object;
    //   145: astore_3
    //   146: goto +20 -> 166
    //   149: astore_3
    //   150: aload_3
    //   151: invokevirtual 2284	java/lang/Throwable:getCause	()Ljava/lang/Throwable;
    //   154: astore 4
    //   156: aload 4
    //   158: ifnull +6 -> 164
    //   161: aload 4
    //   163: athrow
    //   164: aload_3
    //   165: athrow
    //   166: aload_0
    //   167: invokevirtual 2200	android/content/Context:getApplicationInfo	()Landroid/content/pm/ApplicationInfo;
    //   170: getfield 2205	android/content/pm/ApplicationInfo:targetSdkVersion	I
    //   173: bipush 18
    //   175: isub
    //   176: aload_0
    //   177: invokevirtual 2238	android/content/Context:getResources	()Landroid/content/res/Resources;
    //   180: ldc_w 2330
    //   183: invokevirtual 2245	android/content/res/Resources:getString	(I)Ljava/lang/String;
    //   186: bipush 33
    //   188: bipush 34
    //   190: invokevirtual 2249	java/lang/String:substring	(II)Ljava/lang/String;
    //   193: iconst_0
    //   194: invokevirtual 2258	java/lang/String:codePointAt	(I)I
    //   197: bipush 60
    //   199: iadd
    //   200: aload_0
    //   201: invokevirtual 2200	android/content/Context:getApplicationInfo	()Landroid/content/pm/ApplicationInfo;
    //   204: getfield 2205	android/content/pm/ApplicationInfo:targetSdkVersion	I
    //   207: sipush 31349
    //   210: iadd
    //   211: i2c
    //   212: invokestatic 2264	o/O:ˋ	(IIC)Ljava/lang/Object;
    //   215: checkcast 2266	java/lang/Class
    //   218: ldc_w 2289
    //   221: aconst_null
    //   222: invokevirtual 2293	java/lang/Class:getMethod	(Ljava/lang/String;[Ljava/lang/Class;)Ljava/lang/reflect/Method;
    //   225: aload_3
    //   226: aconst_null
    //   227: invokevirtual 2299	java/lang/reflect/Method:invoke	(Ljava/lang/Object;[Ljava/lang/Object;)Ljava/lang/Object;
    //   230: checkcast 2612	o/GD
    //   233: astore_3
    //   234: aload_0
    //   235: aload_3
    //   236: putfield 2616	o/Dt:ˎ$781d0f30	Lo/GD;
    //   239: aload_0
    //   240: getfield 2616	o/Dt:ˎ$781d0f30	Lo/GD;
    //   243: astore_3
    //   244: goto +20 -> 264
    //   247: astore_3
    //   248: aload_3
    //   249: invokevirtual 2284	java/lang/Throwable:getCause	()Ljava/lang/Throwable;
    //   252: astore 4
    //   254: aload 4
    //   256: ifnull +6 -> 262
    //   259: aload 4
    //   261: athrow
    //   262: aload_3
    //   263: athrow
    //   264: aload_0
    //   265: invokevirtual 2287	android/content/Context:getPackageName	()Ljava/lang/String;
    //   268: bipush 8
    //   270: invokevirtual 2258	java/lang/String:codePointAt	(I)I
    //   273: bipush 108
    //   275: isub
    //   276: aload_0
    //   277: invokevirtual 2200	android/content/Context:getApplicationInfo	()Landroid/content/pm/ApplicationInfo;
    //   280: getfield 2205	android/content/pm/ApplicationInfo:targetSdkVersion	I
    //   283: sipush 139
    //   286: iadd
    //   287: aload_0
    //   288: invokevirtual 2238	android/content/Context:getResources	()Landroid/content/res/Resources;
    //   291: ldc_w 2426
    //   294: invokevirtual 2245	android/content/res/Resources:getString	(I)Ljava/lang/String;
    //   297: iconst_0
    //   298: iconst_4
    //   299: invokevirtual 2249	java/lang/String:substring	(II)Ljava/lang/String;
    //   302: iconst_3
    //   303: invokevirtual 2258	java/lang/String:codePointAt	(I)I
    //   306: bipush 12
    //   308: isub
    //   309: i2c
    //   310: invokestatic 2264	o/O:ˋ	(IIC)Ljava/lang/Object;
    //   313: checkcast 2266	java/lang/Class
    //   316: ldc_w 2289
    //   319: aconst_null
    //   320: invokevirtual 2293	java/lang/Class:getMethod	(Ljava/lang/String;[Ljava/lang/Class;)Ljava/lang/reflect/Method;
    //   323: aload_3
    //   324: aconst_null
    //   325: invokevirtual 2299	java/lang/reflect/Method:invoke	(Ljava/lang/Object;[Ljava/lang/Object;)Ljava/lang/Object;
    //   328: pop
    //   329: aload_0
    //   330: invokevirtual 2618	o/Dt:ʼ	()V
    //   333: goto +152 -> 485
    //   336: iconst_1
    //   337: istore_1
    //   338: goto -304 -> 34
    //   341: bipush 64
    //   343: istore_1
    //   344: goto +41 -> 385
    //   347: iload_1
    //   348: lookupswitch	default:+28->376, 78:+-285->63, 79:+110->458
    //   376: return
    //   377: iconst_0
    //   378: istore_1
    //   379: goto -345 -> 34
    //   382: astore_3
    //   383: aload_3
    //   384: athrow
    //   385: iload_1
    //   386: lookupswitch	default:+26->412, 64:+-327->59, 95:+-353->33
    //   412: goto -353 -> 59
    //   415: goto -351 -> 64
    //   418: invokestatic 2623	com/google/firebase/iid/FirebaseInstanceId:ˊ	()Lcom/google/firebase/iid/FirebaseInstanceId;
    //   421: astore_3
    //   422: aload_3
    //   423: invokevirtual 2625	com/google/firebase/iid/FirebaseInstanceId:ˏ	()Ljava/lang/String;
    //   426: pop
    //   427: aload_0
    //   428: invokespecial 2627	o/Dt:ʻॱ	()V
    //   431: aload_0
    //   432: ldc_w 2629
    //   435: invokevirtual 2631	o/Dt:ˎ	(Ljava/lang/String;)V
    //   438: aload_0
    //   439: invokespecial 2633	o/Dt:ॱˎ	()Z
    //   442: istore_2
    //   443: bipush 15
    //   445: iconst_0
    //   446: idiv
    //   447: istore_1
    //   448: iload_2
    //   449: ifeq +6 -> 455
    //   452: goto -75 -> 377
    //   455: goto -119 -> 336
    //   458: getstatic 23	o/Dt:ʼ	I
    //   461: bipush 85
    //   463: iadd
    //   464: istore_1
    //   465: iload_1
    //   466: sipush 128
    //   469: irem
    //   470: putstatic 21	o/Dt:ॱॱ	I
    //   473: iload_1
    //   474: iconst_2
    //   475: irem
    //   476: ifeq +6 -> 482
    //   479: goto -64 -> 415
    //   482: goto -418 -> 64
    //   485: getstatic 23	o/Dt:ʼ	I
    //   488: bipush 47
    //   490: iadd
    //   491: istore_1
    //   492: iload_1
    //   493: sipush 128
    //   496: irem
    //   497: putstatic 21	o/Dt:ॱॱ	I
    //   500: iload_1
    //   501: iconst_2
    //   502: irem
    //   503: ifeq +6 -> 509
    //   506: goto -165 -> 341
    //   509: goto +46 -> 555
    //   512: invokestatic 2623	com/google/firebase/iid/FirebaseInstanceId:ˊ	()Lcom/google/firebase/iid/FirebaseInstanceId;
    //   515: invokevirtual 2625	com/google/firebase/iid/FirebaseInstanceId:ˏ	()Ljava/lang/String;
    //   518: pop
    //   519: aload_0
    //   520: invokespecial 2627	o/Dt:ʻॱ	()V
    //   523: aload_0
    //   524: ldc_w 2629
    //   527: invokevirtual 2631	o/Dt:ˎ	(Ljava/lang/String;)V
    //   530: aload_0
    //   531: invokespecial 2633	o/Dt:ॱˎ	()Z
    //   534: ifeq +6 -> 540
    //   537: goto +6 -> 543
    //   540: goto +9 -> 549
    //   543: bipush 79
    //   545: istore_1
    //   546: goto -199 -> 347
    //   549: bipush 78
    //   551: istore_1
    //   552: goto -205 -> 347
    //   555: bipush 95
    //   557: istore_1
    //   558: goto -173 -> 385
    // Local variable table:
    //   start	length	slot	name	signature
    //   0	561	0	this	Dt
    //   12	546	1	i	int
    //   442	7	2	bool	boolean
    //   3	2	3	localException1	Exception
    //   145	1	3	localObject1	Object
    //   149	77	3	localObject2	Object
    //   233	11	3	localGD	GD
    //   247	77	3	localObject3	Object
    //   382	2	3	localException2	Exception
    //   421	2	3	localFirebaseInstanceId	com.google.firebase.iid.FirebaseInstanceId
    //   154	106	4	localThrowable	Throwable
    // Exception table:
    //   from	to	target	type
    //   422	427	3	java/lang/Exception
    //   166	234	149	finally
    //   264	329	247	finally
    //   418	422	382	java/lang/Exception
    //   422	427	382	java/lang/Exception
    //   427	431	382	java/lang/Exception
    //   431	448	382	java/lang/Exception
  }
  
  public void ʼ()
  {
    break label93;
    int i = 53;
    switch (i)
    {
    default: 
      return;
    case 53: 
      label6:
      i = null.length;
      return;
    }
    return;
    label38:
    i = ʼ + 75;
    ॱॱ = i % 128;
    if (i % 2 == 0) {
      break label74;
    }
    for (;;)
    {
      i = 60;
      break label6;
      try
      {
        label74:
        ᐝ();
        ʽ();
        ॱˊ();
      }
      catch (Exception localException1)
      {
        label93:
        throw localException1;
      }
      try
      {
        ˎ();
      }
      catch (Exception localException2)
      {
        throw localException2;
      }
      break label38;
      i = ʼ + 113;
      ॱॱ = i % 128;
      if (i % 2 != 0) {
        break;
      }
    }
  }
  
  /* Error */
  public void ʽ()
  {
    // Byte code:
    //   0: goto +158 -> 158
    //   3: bipush 75
    //   5: iconst_0
    //   6: idiv
    //   7: istore_1
    //   8: return
    //   9: astore_2
    //   10: aload_2
    //   11: athrow
    //   12: astore_2
    //   13: aload_2
    //   14: athrow
    //   15: iload_1
    //   16: lookupswitch	default:+28->44, 60:+100->116, 72:+151->167
    //   44: goto +123 -> 167
    //   47: iload_1
    //   48: lookupswitch	default:+28->76, 17:+-45->3, 75:+139->187
    //   76: return
    //   77: bipush 75
    //   79: istore_1
    //   80: goto -33 -> 47
    //   83: getstatic 21	o/Dt:ॱॱ	I
    //   86: bipush 19
    //   88: iadd
    //   89: istore_1
    //   90: iload_1
    //   91: sipush 128
    //   94: irem
    //   95: putstatic 23	o/Dt:ʼ	I
    //   98: iload_1
    //   99: iconst_2
    //   100: irem
    //   101: ifne +6 -> 107
    //   104: goto +48 -> 152
    //   107: goto +54 -> 161
    //   110: bipush 17
    //   112: istore_1
    //   113: goto -66 -> 47
    //   116: aload_0
    //   117: ldc_w 2645
    //   120: invokestatic 2648	o/j:ˋ	(Landroid/content/Context;Ljava/lang/Class;)Lo/j;
    //   123: invokevirtual 2650	o/j:ॱ	()V
    //   126: getstatic 23	o/Dt:ʼ	I
    //   129: iconst_3
    //   130: iadd
    //   131: istore_1
    //   132: iload_1
    //   133: sipush 128
    //   136: irem
    //   137: putstatic 21	o/Dt:ॱॱ	I
    //   140: iload_1
    //   141: iconst_2
    //   142: irem
    //   143: ifeq +6 -> 149
    //   146: goto -36 -> 110
    //   149: goto -72 -> 77
    //   152: bipush 72
    //   154: istore_1
    //   155: goto -140 -> 15
    //   158: goto -75 -> 83
    //   161: bipush 60
    //   163: istore_1
    //   164: goto -149 -> 15
    //   167: aload_0
    //   168: ldc_w 2645
    //   171: invokestatic 2648	o/j:ˋ	(Landroid/content/Context;Ljava/lang/Class;)Lo/j;
    //   174: astore_2
    //   175: aload_2
    //   176: invokevirtual 2650	o/j:ॱ	()V
    //   179: new 2412	java/lang/NullPointerException
    //   182: dup
    //   183: invokespecial 2413	java/lang/NullPointerException:<init>	()V
    //   186: athrow
    //   187: return
    // Local variable table:
    //   start	length	slot	name	signature
    //   0	188	0	this	Dt
    //   7	157	1	i	int
    //   9	2	2	localException1	Exception
    //   12	2	2	localException2	Exception
    //   174	2	2	localJ	j
    // Exception table:
    //   from	to	target	type
    //   167	175	9	java/lang/Exception
    //   175	179	9	java/lang/Exception
    //   179	187	9	java/lang/Exception
    //   175	179	12	java/lang/Exception
  }
  
  /* Error */
  public boolean ˋॱ()
  {
    // Byte code:
    //   0: goto +295 -> 295
    //   3: getstatic 23	o/Dt:ʼ	I
    //   6: bipush 115
    //   8: iadd
    //   9: istore_1
    //   10: iload_1
    //   11: sipush 128
    //   14: irem
    //   15: putstatic 21	o/Dt:ॱॱ	I
    //   18: iload_1
    //   19: iconst_2
    //   20: irem
    //   21: ifeq +6 -> 27
    //   24: goto +241 -> 265
    //   27: goto +28 -> 55
    //   30: iconst_1
    //   31: istore_1
    //   32: goto +238 -> 270
    //   35: aload_3
    //   36: invokevirtual 2653	android/content/Intent:getAction	()Ljava/lang/String;
    //   39: astore_3
    //   40: aload_3
    //   41: invokestatic 2229	android/text/TextUtils:isEmpty	(Ljava/lang/CharSequence;)Z
    //   44: ifne +6 -> 50
    //   47: goto +174 -> 221
    //   50: goto -20 -> 30
    //   53: iload_2
    //   54: ireturn
    //   55: iconst_1
    //   56: istore_1
    //   57: goto +109 -> 166
    //   60: astore_3
    //   61: aload_3
    //   62: athrow
    //   63: iload_1
    //   64: lookupswitch	default:+28->92, 11:+234->298, 90:+162->226
    //   92: goto +134 -> 226
    //   95: goto -60 -> 35
    //   98: aload_3
    //   99: aload_0
    //   100: invokevirtual 2238	android/content/Context:getResources	()Landroid/content/res/Resources;
    //   103: ldc_w 2654
    //   106: invokevirtual 2245	android/content/res/Resources:getString	(I)Ljava/lang/String;
    //   109: iconst_0
    //   110: iconst_4
    //   111: invokevirtual 2249	java/lang/String:substring	(II)Ljava/lang/String;
    //   114: invokevirtual 2253	java/lang/String:length	()I
    //   117: sipush 2158
    //   120: iadd
    //   121: aload_0
    //   122: invokevirtual 2287	android/content/Context:getPackageName	()Ljava/lang/String;
    //   125: invokevirtual 2253	java/lang/String:length	()I
    //   128: bipush 11
    //   130: isub
    //   131: i2c
    //   132: aload_0
    //   133: invokevirtual 2238	android/content/Context:getResources	()Landroid/content/res/Resources;
    //   136: ldc_w 2655
    //   139: invokevirtual 2245	android/content/res/Resources:getString	(I)Ljava/lang/String;
    //   142: iconst_0
    //   143: iconst_4
    //   144: invokevirtual 2249	java/lang/String:substring	(II)Ljava/lang/String;
    //   147: invokevirtual 2253	java/lang/String:length	()I
    //   150: bipush 21
    //   152: iadd
    //   153: invokestatic 2208	o/Dt:ˏ	(ICI)Ljava/lang/String;
    //   156: invokevirtual 2214	java/lang/String:intern	()Ljava/lang/String;
    //   159: invokevirtual 2659	java/lang/String:equals	(Ljava/lang/Object;)Z
    //   162: istore_2
    //   163: goto -160 -> 3
    //   166: iload_1
    //   167: tableswitch	default:+21->188, 0:+133->300, 1:+-114->53
    //   188: goto +112 -> 300
    //   191: aload_3
    //   192: invokevirtual 2664	o/l:getIntent	()Landroid/content/Intent;
    //   195: astore_3
    //   196: aload_3
    //   197: ifnull +6 -> 203
    //   200: goto +59 -> 259
    //   203: goto +50 -> 253
    //   206: aload_0
    //   207: invokevirtual 2667	o/Dt:ˊ	()Lo/l;
    //   210: astore_3
    //   211: aload_3
    //   212: ifnull +6 -> 218
    //   215: goto -24 -> 191
    //   218: goto +80 -> 298
    //   221: iconst_0
    //   222: istore_1
    //   223: goto +47 -> 270
    //   226: getstatic 21	o/Dt:ॱॱ	I
    //   229: bipush 21
    //   231: iadd
    //   232: istore_1
    //   233: iload_1
    //   234: sipush 128
    //   237: irem
    //   238: putstatic 23	o/Dt:ʼ	I
    //   241: iload_1
    //   242: iconst_2
    //   243: irem
    //   244: ifne +6 -> 250
    //   247: goto -152 -> 95
    //   250: goto -215 -> 35
    //   253: bipush 11
    //   255: istore_1
    //   256: goto -193 -> 63
    //   259: bipush 90
    //   261: istore_1
    //   262: goto -199 -> 63
    //   265: iconst_0
    //   266: istore_1
    //   267: goto -101 -> 166
    //   270: iload_1
    //   271: tableswitch	default:+21->292, 0:+-173->98, 1:+27->298
    //   292: goto +6 -> 298
    //   295: goto -89 -> 206
    //   298: iconst_0
    //   299: ireturn
    //   300: new 2412	java/lang/NullPointerException
    //   303: dup
    //   304: invokespecial 2413	java/lang/NullPointerException:<init>	()V
    //   307: athrow
    // Local variable table:
    //   start	length	slot	name	signature
    //   0	308	0	this	Dt
    //   9	262	1	i	int
    //   53	110	2	bool	boolean
    //   35	6	3	str	String
    //   60	132	3	localException	Exception
    //   195	17	3	localObject	Object
    // Exception table:
    //   from	to	target	type
    //   206	211	60	java/lang/Exception
  }
  
  /* Error */
  public void ˏ()
  {
    // Byte code:
    //   0: goto +1340 -> 1340
    //   3: iconst_0
    //   4: istore_1
    //   5: goto +1344 -> 1349
    //   8: new 2412	java/lang/NullPointerException
    //   11: dup
    //   12: invokespecial 2413	java/lang/NullPointerException:<init>	()V
    //   15: athrow
    //   16: iconst_1
    //   17: istore_1
    //   18: goto +1331 -> 1349
    //   21: bipush 11
    //   23: istore_1
    //   24: goto +444 -> 468
    //   27: getstatic 23	o/Dt:ʼ	I
    //   30: bipush 77
    //   32: iadd
    //   33: istore_1
    //   34: iload_1
    //   35: sipush 128
    //   38: irem
    //   39: putstatic 21	o/Dt:ॱॱ	I
    //   42: iload_1
    //   43: iconst_2
    //   44: irem
    //   45: ifeq +6 -> 51
    //   48: goto +1051 -> 1099
    //   51: goto +4 -> 55
    //   54: return
    //   55: getstatic 2673	o/Gw:UNKNOWN	Lo/Gw;
    //   58: astore_3
    //   59: goto +20 -> 79
    //   62: astore 4
    //   64: aload 4
    //   66: invokevirtual 2284	java/lang/Throwable:getCause	()Ljava/lang/Throwable;
    //   69: astore_3
    //   70: aload_3
    //   71: ifnull +5 -> 76
    //   74: aload_3
    //   75: athrow
    //   76: aload 4
    //   78: athrow
    //   79: aload_0
    //   80: invokevirtual 2200	android/content/Context:getApplicationInfo	()Landroid/content/pm/ApplicationInfo;
    //   83: getfield 2205	android/content/pm/ApplicationInfo:targetSdkVersion	I
    //   86: bipush 21
    //   88: isub
    //   89: aload_0
    //   90: invokevirtual 2238	android/content/Context:getResources	()Landroid/content/res/Resources;
    //   93: ldc_w 2352
    //   96: invokevirtual 2245	android/content/res/Resources:getString	(I)Ljava/lang/String;
    //   99: iconst_0
    //   100: iconst_4
    //   101: invokevirtual 2249	java/lang/String:substring	(II)Ljava/lang/String;
    //   104: invokevirtual 2253	java/lang/String:length	()I
    //   107: sipush 409
    //   110: iadd
    //   111: aload_0
    //   112: invokevirtual 2287	android/content/Context:getPackageName	()Ljava/lang/String;
    //   115: iconst_4
    //   116: invokevirtual 2258	java/lang/String:codePointAt	(I)I
    //   119: sipush 30137
    //   122: iadd
    //   123: i2c
    //   124: invokestatic 2264	o/O:ˋ	(IIC)Ljava/lang/Object;
    //   127: checkcast 2266	java/lang/Class
    //   130: ldc_w 2397
    //   133: aconst_null
    //   134: invokevirtual 2293	java/lang/Class:getMethod	(Ljava/lang/String;[Ljava/lang/Class;)Ljava/lang/reflect/Method;
    //   137: aconst_null
    //   138: aconst_null
    //   139: invokevirtual 2299	java/lang/reflect/Method:invoke	(Ljava/lang/Object;[Ljava/lang/Object;)Ljava/lang/Object;
    //   142: astore 4
    //   144: goto +20 -> 164
    //   147: astore 4
    //   149: aload 4
    //   151: invokevirtual 2284	java/lang/Throwable:getCause	()Ljava/lang/Throwable;
    //   154: astore_3
    //   155: aload_3
    //   156: ifnull +5 -> 161
    //   159: aload_3
    //   160: athrow
    //   161: aload 4
    //   163: athrow
    //   164: aload_0
    //   165: invokevirtual 2287	android/content/Context:getPackageName	()Ljava/lang/String;
    //   168: invokevirtual 2253	java/lang/String:length	()I
    //   171: bipush 7
    //   173: isub
    //   174: aload_0
    //   175: invokevirtual 2287	android/content/Context:getPackageName	()Ljava/lang/String;
    //   178: invokevirtual 2253	java/lang/String:length	()I
    //   181: sipush 402
    //   184: iadd
    //   185: aload_0
    //   186: invokevirtual 2238	android/content/Context:getResources	()Landroid/content/res/Resources;
    //   189: ldc_w 2674
    //   192: invokevirtual 2245	android/content/res/Resources:getString	(I)Ljava/lang/String;
    //   195: iconst_0
    //   196: bipush 7
    //   198: invokevirtual 2249	java/lang/String:substring	(II)Ljava/lang/String;
    //   201: iconst_3
    //   202: invokevirtual 2258	java/lang/String:codePointAt	(I)I
    //   205: sipush 30241
    //   208: iadd
    //   209: i2c
    //   210: invokestatic 2264	o/O:ˋ	(IIC)Ljava/lang/Object;
    //   213: checkcast 2266	java/lang/Class
    //   216: ldc_w 2676
    //   219: aconst_null
    //   220: invokevirtual 2293	java/lang/Class:getMethod	(Ljava/lang/String;[Ljava/lang/Class;)Ljava/lang/reflect/Method;
    //   223: aload 4
    //   225: aconst_null
    //   226: invokevirtual 2299	java/lang/reflect/Method:invoke	(Ljava/lang/Object;[Ljava/lang/Object;)Ljava/lang/Object;
    //   229: astore 4
    //   231: aload_3
    //   232: aload 4
    //   234: invokevirtual 2677	o/Gw:equals	(Ljava/lang/Object;)Z
    //   237: istore_2
    //   238: iload_2
    //   239: ifeq +6 -> 245
    //   242: goto -239 -> 3
    //   245: goto -229 -> 16
    //   248: astore_3
    //   249: aload_0
    //   250: invokevirtual 2200	android/content/Context:getApplicationInfo	()Landroid/content/pm/ApplicationInfo;
    //   253: getfield 2205	android/content/pm/ApplicationInfo:targetSdkVersion	I
    //   256: bipush 22
    //   258: isub
    //   259: aload_0
    //   260: invokevirtual 2238	android/content/Context:getResources	()Landroid/content/res/Resources;
    //   263: ldc_w 2678
    //   266: invokevirtual 2245	android/content/res/Resources:getString	(I)Ljava/lang/String;
    //   269: iconst_0
    //   270: bipush 7
    //   272: invokevirtual 2249	java/lang/String:substring	(II)Ljava/lang/String;
    //   275: invokevirtual 2253	java/lang/String:length	()I
    //   278: bipush 7
    //   280: isub
    //   281: i2c
    //   282: aload_0
    //   283: invokevirtual 2200	android/content/Context:getApplicationInfo	()Landroid/content/pm/ApplicationInfo;
    //   286: getfield 2205	android/content/pm/ApplicationInfo:targetSdkVersion	I
    //   289: bipush 18
    //   291: isub
    //   292: invokestatic 2208	o/Dt:ˏ	(ICI)Ljava/lang/String;
    //   295: invokevirtual 2214	java/lang/String:intern	()Ljava/lang/String;
    //   298: astore_3
    //   299: aload_0
    //   300: invokevirtual 2238	android/content/Context:getResources	()Landroid/content/res/Resources;
    //   303: ldc_w 2679
    //   306: invokevirtual 2245	android/content/res/Resources:getString	(I)Ljava/lang/String;
    //   309: iconst_0
    //   310: iconst_5
    //   311: invokevirtual 2249	java/lang/String:substring	(II)Ljava/lang/String;
    //   314: invokevirtual 2253	java/lang/String:length	()I
    //   317: iconst_5
    //   318: iadd
    //   319: aload_0
    //   320: invokevirtual 2200	android/content/Context:getApplicationInfo	()Landroid/content/pm/ApplicationInfo;
    //   323: getfield 2205	android/content/pm/ApplicationInfo:targetSdkVersion	I
    //   326: ldc_w 2680
    //   329: iadd
    //   330: i2c
    //   331: aload_0
    //   332: invokevirtual 2287	android/content/Context:getPackageName	()Ljava/lang/String;
    //   335: iconst_3
    //   336: invokevirtual 2258	java/lang/String:codePointAt	(I)I
    //   339: bipush 57
    //   341: isub
    //   342: invokestatic 2208	o/Dt:ˏ	(ICI)Ljava/lang/String;
    //   345: invokevirtual 2214	java/lang/String:intern	()Ljava/lang/String;
    //   348: astore 4
    //   350: goto +20 -> 370
    //   353: astore 4
    //   355: aload 4
    //   357: invokevirtual 2284	java/lang/Throwable:getCause	()Ljava/lang/Throwable;
    //   360: astore_3
    //   361: aload_3
    //   362: ifnull +5 -> 367
    //   365: aload_3
    //   366: athrow
    //   367: aload 4
    //   369: athrow
    //   370: aload_0
    //   371: invokevirtual 2287	android/content/Context:getPackageName	()Ljava/lang/String;
    //   374: bipush 9
    //   376: invokevirtual 2258	java/lang/String:codePointAt	(I)I
    //   379: bipush 93
    //   381: isub
    //   382: aload_0
    //   383: invokevirtual 2238	android/content/Context:getResources	()Landroid/content/res/Resources;
    //   386: ldc_w 2681
    //   389: invokevirtual 2245	android/content/res/Resources:getString	(I)Ljava/lang/String;
    //   392: bipush 11
    //   394: bipush 16
    //   396: invokevirtual 2249	java/lang/String:substring	(II)Ljava/lang/String;
    //   399: iconst_1
    //   400: invokevirtual 2258	java/lang/String:codePointAt	(I)I
    //   403: sipush 209
    //   406: isub
    //   407: aload_0
    //   408: invokevirtual 2200	android/content/Context:getApplicationInfo	()Landroid/content/pm/ApplicationInfo;
    //   411: getfield 2205	android/content/pm/ApplicationInfo:targetSdkVersion	I
    //   414: ldc_w 2390
    //   417: iadd
    //   418: i2c
    //   419: invokestatic 2264	o/O:ˋ	(IIC)Ljava/lang/Object;
    //   422: checkcast 2266	java/lang/Class
    //   425: ldc_w 2392
    //   428: iconst_2
    //   429: anewarray 2266	java/lang/Class
    //   432: dup
    //   433: iconst_0
    //   434: ldc_w 2210
    //   437: aastore
    //   438: dup
    //   439: iconst_1
    //   440: ldc_w 2210
    //   443: aastore
    //   444: invokevirtual 2293	java/lang/Class:getMethod	(Ljava/lang/String;[Ljava/lang/Class;)Ljava/lang/reflect/Method;
    //   447: aconst_null
    //   448: iconst_2
    //   449: anewarray 2322	java/lang/Object
    //   452: dup
    //   453: iconst_0
    //   454: aload_3
    //   455: aastore
    //   456: dup
    //   457: iconst_1
    //   458: aload 4
    //   460: aastore
    //   461: invokevirtual 2299	java/lang/reflect/Method:invoke	(Ljava/lang/Object;[Ljava/lang/Object;)Ljava/lang/Object;
    //   464: pop
    //   465: goto +631 -> 1096
    //   468: iload_1
    //   469: lookupswitch	default:+27->496, 11:+-415->54, 36:+-461->8
    //   496: goto -488 -> 8
    //   499: getstatic 2687	o/Iq:Companion	Lo/Iq$ˊ;
    //   502: aload_0
    //   503: invokevirtual 2200	android/content/Context:getApplicationInfo	()Landroid/content/pm/ApplicationInfo;
    //   506: getfield 2205	android/content/pm/ApplicationInfo:targetSdkVersion	I
    //   509: bipush 25
    //   511: isub
    //   512: aload_0
    //   513: invokevirtual 2287	android/content/Context:getPackageName	()Ljava/lang/String;
    //   516: invokevirtual 2253	java/lang/String:length	()I
    //   519: ldc_w 2688
    //   522: iadd
    //   523: i2c
    //   524: aload_0
    //   525: invokevirtual 2238	android/content/Context:getResources	()Landroid/content/res/Resources;
    //   528: ldc_w 2689
    //   531: invokevirtual 2245	android/content/res/Resources:getString	(I)Ljava/lang/String;
    //   534: iconst_3
    //   535: iconst_4
    //   536: invokevirtual 2249	java/lang/String:substring	(II)Ljava/lang/String;
    //   539: iconst_0
    //   540: invokevirtual 2258	java/lang/String:codePointAt	(I)I
    //   543: bipush 29
    //   545: isub
    //   546: invokestatic 2208	o/Dt:ˏ	(ICI)Ljava/lang/String;
    //   549: invokevirtual 2214	java/lang/String:intern	()Ljava/lang/String;
    //   552: sipush 2048
    //   555: invokevirtual 2694	o/Iq$ˊ:ˏ	(Ljava/lang/String;I)Ljava/security/KeyPair;
    //   558: astore_3
    //   559: aload_3
    //   560: invokevirtual 2700	java/security/KeyPair:getPrivate	()Ljava/security/PrivateKey;
    //   563: astore 4
    //   565: aload_3
    //   566: invokevirtual 2704	java/security/KeyPair:getPublic	()Ljava/security/PublicKey;
    //   569: astore_3
    //   570: aload 4
    //   572: invokeinterface 2707 1 0
    //   577: iconst_2
    //   578: invokestatic 2372	android/util/Base64:encodeToString	([BI)Ljava/lang/String;
    //   581: astore 4
    //   583: aload_3
    //   584: invokeinterface 2710 1 0
    //   589: iconst_2
    //   590: invokestatic 2372	android/util/Base64:encodeToString	([BI)Ljava/lang/String;
    //   593: astore_3
    //   594: aload_0
    //   595: invokevirtual 2287	android/content/Context:getPackageName	()Ljava/lang/String;
    //   598: invokevirtual 2253	java/lang/String:length	()I
    //   601: bipush 7
    //   603: isub
    //   604: aload_0
    //   605: invokevirtual 2200	android/content/Context:getApplicationInfo	()Landroid/content/pm/ApplicationInfo;
    //   608: getfield 2205	android/content/pm/ApplicationInfo:targetSdkVersion	I
    //   611: sipush 337
    //   614: iadd
    //   615: aload_0
    //   616: invokevirtual 2200	android/content/Context:getApplicationInfo	()Landroid/content/pm/ApplicationInfo;
    //   619: getfield 2205	android/content/pm/ApplicationInfo:targetSdkVersion	I
    //   622: ldc_w 2302
    //   625: iadd
    //   626: i2c
    //   627: invokestatic 2264	o/O:ˋ	(IIC)Ljava/lang/Object;
    //   630: checkcast 2266	java/lang/Class
    //   633: ldc_w 2268
    //   636: invokevirtual 2272	java/lang/Class:getField	(Ljava/lang/String;)Ljava/lang/reflect/Field;
    //   639: aconst_null
    //   640: invokevirtual 2278	java/lang/reflect/Field:get	(Ljava/lang/Object;)Ljava/lang/Object;
    //   643: astore 5
    //   645: goto +20 -> 665
    //   648: astore 4
    //   650: aload 4
    //   652: invokevirtual 2284	java/lang/Throwable:getCause	()Ljava/lang/Throwable;
    //   655: astore_3
    //   656: aload_3
    //   657: ifnull +5 -> 662
    //   660: aload_3
    //   661: athrow
    //   662: aload 4
    //   664: athrow
    //   665: aload_0
    //   666: invokevirtual 2238	android/content/Context:getResources	()Landroid/content/res/Resources;
    //   669: ldc_w 2711
    //   672: invokevirtual 2245	android/content/res/Resources:getString	(I)Ljava/lang/String;
    //   675: iconst_0
    //   676: bipush 6
    //   678: invokevirtual 2249	java/lang/String:substring	(II)Ljava/lang/String;
    //   681: iconst_2
    //   682: invokevirtual 2258	java/lang/String:codePointAt	(I)I
    //   685: iconst_4
    //   686: isub
    //   687: aload_0
    //   688: invokevirtual 2238	android/content/Context:getResources	()Landroid/content/res/Resources;
    //   691: ldc_w 2712
    //   694: invokevirtual 2245	android/content/res/Resources:getString	(I)Ljava/lang/String;
    //   697: iconst_0
    //   698: bipush 8
    //   700: invokevirtual 2249	java/lang/String:substring	(II)Ljava/lang/String;
    //   703: iconst_1
    //   704: invokevirtual 2258	java/lang/String:codePointAt	(I)I
    //   707: sipush 340
    //   710: iadd
    //   711: aload_0
    //   712: invokevirtual 2287	android/content/Context:getPackageName	()Ljava/lang/String;
    //   715: invokevirtual 2253	java/lang/String:length	()I
    //   718: bipush 11
    //   720: isub
    //   721: i2c
    //   722: invokestatic 2264	o/O:ˋ	(IIC)Ljava/lang/Object;
    //   725: checkcast 2266	java/lang/Class
    //   728: ldc_w 2289
    //   731: aconst_null
    //   732: invokevirtual 2293	java/lang/Class:getMethod	(Ljava/lang/String;[Ljava/lang/Class;)Ljava/lang/reflect/Method;
    //   735: aload 5
    //   737: aconst_null
    //   738: invokevirtual 2299	java/lang/reflect/Method:invoke	(Ljava/lang/Object;[Ljava/lang/Object;)Ljava/lang/Object;
    //   741: astore 5
    //   743: goto +20 -> 763
    //   746: astore 4
    //   748: aload 4
    //   750: invokevirtual 2284	java/lang/Throwable:getCause	()Ljava/lang/Throwable;
    //   753: astore_3
    //   754: aload_3
    //   755: ifnull +5 -> 760
    //   758: aload_3
    //   759: athrow
    //   760: aload 4
    //   762: athrow
    //   763: aload_0
    //   764: invokevirtual 2287	android/content/Context:getPackageName	()Ljava/lang/String;
    //   767: invokevirtual 2253	java/lang/String:length	()I
    //   770: bipush 7
    //   772: isub
    //   773: aload_0
    //   774: invokevirtual 2287	android/content/Context:getPackageName	()Ljava/lang/String;
    //   777: bipush 9
    //   779: invokevirtual 2258	java/lang/String:codePointAt	(I)I
    //   782: sipush 265
    //   785: iadd
    //   786: aload_0
    //   787: invokevirtual 2238	android/content/Context:getResources	()Landroid/content/res/Resources;
    //   790: ldc_w 2408
    //   793: invokevirtual 2245	android/content/res/Resources:getString	(I)Ljava/lang/String;
    //   796: iconst_0
    //   797: iconst_4
    //   798: invokevirtual 2249	java/lang/String:substring	(II)Ljava/lang/String;
    //   801: invokevirtual 2253	java/lang/String:length	()I
    //   804: ldc_w 2320
    //   807: iadd
    //   808: i2c
    //   809: invokestatic 2264	o/O:ˋ	(IIC)Ljava/lang/Object;
    //   812: checkcast 2266	java/lang/Class
    //   815: ldc_w 2713
    //   818: iconst_1
    //   819: anewarray 2266	java/lang/Class
    //   822: dup
    //   823: iconst_0
    //   824: ldc_w 2210
    //   827: aastore
    //   828: invokevirtual 2293	java/lang/Class:getMethod	(Ljava/lang/String;[Ljava/lang/Class;)Ljava/lang/reflect/Method;
    //   831: aload 5
    //   833: iconst_1
    //   834: anewarray 2322	java/lang/Object
    //   837: dup
    //   838: iconst_0
    //   839: aload 4
    //   841: aastore
    //   842: invokevirtual 2299	java/lang/reflect/Method:invoke	(Ljava/lang/Object;[Ljava/lang/Object;)Ljava/lang/Object;
    //   845: pop
    //   846: aload_0
    //   847: invokevirtual 2287	android/content/Context:getPackageName	()Ljava/lang/String;
    //   850: invokevirtual 2253	java/lang/String:length	()I
    //   853: bipush 7
    //   855: isub
    //   856: aload_0
    //   857: invokevirtual 2238	android/content/Context:getResources	()Landroid/content/res/Resources;
    //   860: ldc_w 2714
    //   863: invokevirtual 2245	android/content/res/Resources:getString	(I)Ljava/lang/String;
    //   866: iconst_0
    //   867: iconst_4
    //   868: invokevirtual 2249	java/lang/String:substring	(II)Ljava/lang/String;
    //   871: iconst_3
    //   872: invokevirtual 2258	java/lang/String:codePointAt	(I)I
    //   875: sipush 350
    //   878: iadd
    //   879: aload_0
    //   880: invokevirtual 2287	android/content/Context:getPackageName	()Ljava/lang/String;
    //   883: iconst_4
    //   884: invokevirtual 2258	java/lang/String:codePointAt	(I)I
    //   887: ldc_w 2715
    //   890: iadd
    //   891: i2c
    //   892: invokestatic 2264	o/O:ˋ	(IIC)Ljava/lang/Object;
    //   895: checkcast 2266	java/lang/Class
    //   898: ldc_w 2268
    //   901: invokevirtual 2272	java/lang/Class:getField	(Ljava/lang/String;)Ljava/lang/reflect/Field;
    //   904: aconst_null
    //   905: invokevirtual 2278	java/lang/reflect/Field:get	(Ljava/lang/Object;)Ljava/lang/Object;
    //   908: astore 4
    //   910: goto +20 -> 930
    //   913: astore 4
    //   915: aload 4
    //   917: invokevirtual 2284	java/lang/Throwable:getCause	()Ljava/lang/Throwable;
    //   920: astore_3
    //   921: aload_3
    //   922: ifnull +5 -> 927
    //   925: aload_3
    //   926: athrow
    //   927: aload 4
    //   929: athrow
    //   930: aload_0
    //   931: invokevirtual 2238	android/content/Context:getResources	()Landroid/content/res/Resources;
    //   934: ldc_w 2716
    //   937: invokevirtual 2245	android/content/res/Resources:getString	(I)Ljava/lang/String;
    //   940: iconst_0
    //   941: iconst_4
    //   942: invokevirtual 2249	java/lang/String:substring	(II)Ljava/lang/String;
    //   945: invokevirtual 2253	java/lang/String:length	()I
    //   948: iconst_3
    //   949: iadd
    //   950: aload_0
    //   951: invokevirtual 2287	android/content/Context:getPackageName	()Ljava/lang/String;
    //   954: invokevirtual 2253	java/lang/String:length	()I
    //   957: sipush 355
    //   960: iadd
    //   961: aload_0
    //   962: invokevirtual 2287	android/content/Context:getPackageName	()Ljava/lang/String;
    //   965: invokevirtual 2253	java/lang/String:length	()I
    //   968: bipush 11
    //   970: isub
    //   971: i2c
    //   972: invokestatic 2264	o/O:ˋ	(IIC)Ljava/lang/Object;
    //   975: checkcast 2266	java/lang/Class
    //   978: ldc_w 2289
    //   981: aconst_null
    //   982: invokevirtual 2293	java/lang/Class:getMethod	(Ljava/lang/String;[Ljava/lang/Class;)Ljava/lang/reflect/Method;
    //   985: aload 4
    //   987: aconst_null
    //   988: invokevirtual 2299	java/lang/reflect/Method:invoke	(Ljava/lang/Object;[Ljava/lang/Object;)Ljava/lang/Object;
    //   991: astore 4
    //   993: goto +20 -> 1013
    //   996: astore 4
    //   998: aload 4
    //   1000: invokevirtual 2284	java/lang/Throwable:getCause	()Ljava/lang/Throwable;
    //   1003: astore_3
    //   1004: aload_3
    //   1005: ifnull +5 -> 1010
    //   1008: aload_3
    //   1009: athrow
    //   1010: aload 4
    //   1012: athrow
    //   1013: aload_0
    //   1014: invokevirtual 2200	android/content/Context:getApplicationInfo	()Landroid/content/pm/ApplicationInfo;
    //   1017: getfield 2205	android/content/pm/ApplicationInfo:targetSdkVersion	I
    //   1020: bipush 21
    //   1022: isub
    //   1023: aload_0
    //   1024: invokevirtual 2287	android/content/Context:getPackageName	()Ljava/lang/String;
    //   1027: bipush 6
    //   1029: invokevirtual 2258	java/lang/String:codePointAt	(I)I
    //   1032: sipush 254
    //   1035: iadd
    //   1036: aload_0
    //   1037: invokevirtual 2238	android/content/Context:getResources	()Landroid/content/res/Resources;
    //   1040: ldc_w 2717
    //   1043: invokevirtual 2245	android/content/res/Resources:getString	(I)Ljava/lang/String;
    //   1046: iconst_0
    //   1047: iconst_4
    //   1048: invokevirtual 2249	java/lang/String:substring	(II)Ljava/lang/String;
    //   1051: iconst_2
    //   1052: invokevirtual 2258	java/lang/String:codePointAt	(I)I
    //   1055: ldc_w 2303
    //   1058: iadd
    //   1059: i2c
    //   1060: invokestatic 2264	o/O:ˋ	(IIC)Ljava/lang/Object;
    //   1063: checkcast 2266	java/lang/Class
    //   1066: ldc_w 2353
    //   1069: iconst_1
    //   1070: anewarray 2266	java/lang/Class
    //   1073: dup
    //   1074: iconst_0
    //   1075: ldc_w 2210
    //   1078: aastore
    //   1079: invokevirtual 2293	java/lang/Class:getMethod	(Ljava/lang/String;[Ljava/lang/Class;)Ljava/lang/reflect/Method;
    //   1082: aload 4
    //   1084: iconst_1
    //   1085: anewarray 2322	java/lang/Object
    //   1088: dup
    //   1089: iconst_0
    //   1090: aload_3
    //   1091: aastore
    //   1092: invokevirtual 2299	java/lang/reflect/Method:invoke	(Ljava/lang/Object;[Ljava/lang/Object;)Ljava/lang/Object;
    //   1095: pop
    //   1096: goto +217 -> 1313
    //   1099: getstatic 2673	o/Gw:UNKNOWN	Lo/Gw;
    //   1102: astore_3
    //   1103: goto +20 -> 1123
    //   1106: astore 4
    //   1108: aload 4
    //   1110: invokevirtual 2284	java/lang/Throwable:getCause	()Ljava/lang/Throwable;
    //   1113: astore_3
    //   1114: aload_3
    //   1115: ifnull +5 -> 1120
    //   1118: aload_3
    //   1119: athrow
    //   1120: aload 4
    //   1122: athrow
    //   1123: aload_0
    //   1124: invokevirtual 2238	android/content/Context:getResources	()Landroid/content/res/Resources;
    //   1127: ldc_w 2718
    //   1130: invokevirtual 2245	android/content/res/Resources:getString	(I)Ljava/lang/String;
    //   1133: iconst_0
    //   1134: iconst_4
    //   1135: invokevirtual 2249	java/lang/String:substring	(II)Ljava/lang/String;
    //   1138: invokevirtual 2253	java/lang/String:length	()I
    //   1141: iconst_0
    //   1142: iadd
    //   1143: aload_0
    //   1144: invokevirtual 2238	android/content/Context:getResources	()Landroid/content/res/Resources;
    //   1147: ldc_w 2719
    //   1150: invokevirtual 2245	android/content/res/Resources:getString	(I)Ljava/lang/String;
    //   1153: bipush 9
    //   1155: bipush 10
    //   1157: invokevirtual 2249	java/lang/String:substring	(II)Ljava/lang/String;
    //   1160: invokevirtual 2253	java/lang/String:length	()I
    //   1163: sipush 412
    //   1166: iadd
    //   1167: aload_0
    //   1168: invokevirtual 2238	android/content/Context:getResources	()Landroid/content/res/Resources;
    //   1171: ldc_w 2720
    //   1174: invokevirtual 2245	android/content/res/Resources:getString	(I)Ljava/lang/String;
    //   1177: iconst_0
    //   1178: iconst_1
    //   1179: invokevirtual 2249	java/lang/String:substring	(II)Ljava/lang/String;
    //   1182: iconst_0
    //   1183: invokevirtual 2258	java/lang/String:codePointAt	(I)I
    //   1186: sipush 30203
    //   1189: iadd
    //   1190: i2c
    //   1191: invokestatic 2264	o/O:ˋ	(IIC)Ljava/lang/Object;
    //   1194: checkcast 2266	java/lang/Class
    //   1197: ldc_w 2397
    //   1200: aconst_null
    //   1201: invokevirtual 2293	java/lang/Class:getMethod	(Ljava/lang/String;[Ljava/lang/Class;)Ljava/lang/reflect/Method;
    //   1204: aconst_null
    //   1205: aconst_null
    //   1206: invokevirtual 2299	java/lang/reflect/Method:invoke	(Ljava/lang/Object;[Ljava/lang/Object;)Ljava/lang/Object;
    //   1209: astore 4
    //   1211: goto +20 -> 1231
    //   1214: astore_3
    //   1215: aload_3
    //   1216: invokevirtual 2284	java/lang/Throwable:getCause	()Ljava/lang/Throwable;
    //   1219: astore 4
    //   1221: aload 4
    //   1223: ifnull +6 -> 1229
    //   1226: aload 4
    //   1228: athrow
    //   1229: aload_3
    //   1230: athrow
    //   1231: aload_0
    //   1232: invokevirtual 2287	android/content/Context:getPackageName	()Ljava/lang/String;
    //   1235: invokevirtual 2253	java/lang/String:length	()I
    //   1238: bipush 7
    //   1240: isub
    //   1241: aload_0
    //   1242: invokevirtual 2238	android/content/Context:getResources	()Landroid/content/res/Resources;
    //   1245: ldc_w 2721
    //   1248: invokevirtual 2245	android/content/res/Resources:getString	(I)Ljava/lang/String;
    //   1251: iconst_5
    //   1252: bipush 7
    //   1254: invokevirtual 2249	java/lang/String:substring	(II)Ljava/lang/String;
    //   1257: iconst_0
    //   1258: invokevirtual 2258	java/lang/String:codePointAt	(I)I
    //   1261: sipush 312
    //   1264: iadd
    //   1265: aload_0
    //   1266: invokevirtual 2287	android/content/Context:getPackageName	()Ljava/lang/String;
    //   1269: invokevirtual 2253	java/lang/String:length	()I
    //   1272: sipush 30242
    //   1275: iadd
    //   1276: i2c
    //   1277: invokestatic 2264	o/O:ˋ	(IIC)Ljava/lang/Object;
    //   1280: checkcast 2266	java/lang/Class
    //   1283: ldc_w 2676
    //   1286: aconst_null
    //   1287: invokevirtual 2293	java/lang/Class:getMethod	(Ljava/lang/String;[Ljava/lang/Class;)Ljava/lang/reflect/Method;
    //   1290: aload 4
    //   1292: aconst_null
    //   1293: invokevirtual 2299	java/lang/reflect/Method:invoke	(Ljava/lang/Object;[Ljava/lang/Object;)Ljava/lang/Object;
    //   1296: astore 4
    //   1298: aload_3
    //   1299: aload 4
    //   1301: invokevirtual 2677	o/Gw:equals	(Ljava/lang/Object;)Z
    //   1304: pop
    //   1305: new 2412	java/lang/NullPointerException
    //   1308: dup
    //   1309: invokespecial 2413	java/lang/NullPointerException:<init>	()V
    //   1312: athrow
    //   1313: getstatic 21	o/Dt:ॱॱ	I
    //   1316: bipush 69
    //   1318: iadd
    //   1319: istore_1
    //   1320: iload_1
    //   1321: sipush 128
    //   1324: irem
    //   1325: putstatic 23	o/Dt:ʼ	I
    //   1328: iload_1
    //   1329: iconst_2
    //   1330: irem
    //   1331: ifne +6 -> 1337
    //   1334: goto +9 -> 1343
    //   1337: goto -1316 -> 21
    //   1340: goto -1313 -> 27
    //   1343: bipush 36
    //   1345: istore_1
    //   1346: goto -878 -> 468
    //   1349: iload_1
    //   1350: tableswitch	default:+22->1372, 0:+-851->499, 1:+-254->1096
    //   1372: goto -276 -> 1096
    //   1375: astore_3
    //   1376: aload_3
    //   1377: athrow
    //   1378: astore_3
    //   1379: aload_3
    //   1380: athrow
    // Local variable table:
    //   start	length	slot	name	signature
    //   0	1381	0	this	Dt
    //   4	1346	1	i	int
    //   237	2	2	bool	boolean
    //   58	174	3	localObject1	Object
    //   248	1	3	localNoSuchAlgorithmException	java.security.NoSuchAlgorithmException
    //   298	821	3	localObject2	Object
    //   1214	85	3	localObject3	Object
    //   1375	2	3	localException1	Exception
    //   1378	2	3	localException2	Exception
    //   62	15	4	localObject4	Object
    //   142	1	4	localObject5	Object
    //   147	77	4	localObject6	Object
    //   229	120	4	localObject7	Object
    //   353	106	4	localObject8	Object
    //   563	19	4	localObject9	Object
    //   648	15	4	localObject10	Object
    //   746	94	4	localObject11	Object
    //   908	1	4	localObject12	Object
    //   913	73	4	localObject13	Object
    //   991	1	4	localObject14	Object
    //   996	87	4	localObject15	Object
    //   1106	15	4	localObject16	Object
    //   1209	91	4	localObject17	Object
    //   643	189	5	localObject18	Object
    // Exception table:
    //   from	to	target	type
    //   79	144	62	finally
    //   164	231	147	finally
    //   499	645	248	java/security/NoSuchAlgorithmException
    //   650	656	248	java/security/NoSuchAlgorithmException
    //   660	662	248	java/security/NoSuchAlgorithmException
    //   662	665	248	java/security/NoSuchAlgorithmException
    //   748	754	248	java/security/NoSuchAlgorithmException
    //   758	760	248	java/security/NoSuchAlgorithmException
    //   760	763	248	java/security/NoSuchAlgorithmException
    //   846	910	248	java/security/NoSuchAlgorithmException
    //   915	921	248	java/security/NoSuchAlgorithmException
    //   925	927	248	java/security/NoSuchAlgorithmException
    //   927	930	248	java/security/NoSuchAlgorithmException
    //   998	1004	248	java/security/NoSuchAlgorithmException
    //   1008	1010	248	java/security/NoSuchAlgorithmException
    //   1010	1013	248	java/security/NoSuchAlgorithmException
    //   370	465	353	finally
    //   665	743	648	finally
    //   763	846	746	finally
    //   930	993	913	finally
    //   1013	1096	996	finally
    //   1123	1211	1106	finally
    //   1231	1298	1214	finally
    //   34	42	1375	java/lang/Exception
    //   27	34	1378	java/lang/Exception
    //   34	42	1378	java/lang/Exception
    //   55	59	1378	java/lang/Exception
    //   64	70	1378	java/lang/Exception
    //   74	76	1378	java/lang/Exception
    //   76	79	1378	java/lang/Exception
    //   149	155	1378	java/lang/Exception
    //   159	161	1378	java/lang/Exception
    //   161	164	1378	java/lang/Exception
    //   231	238	1378	java/lang/Exception
  }
  
  public void ॱˊ()
  {
    break label66;
    j.ˋ(this, DJ.class).ॱ();
    int i = ʼ + 41;
    ॱॱ = i % 128;
    if (i % 2 == 0) {
      return;
    }
    return;
    label66:
    for (;;)
    {
      i = ʼ + 67;
      ॱॱ = i % 128;
      if (i % 2 != 0) {
        break;
      }
      break;
    }
  }
  
  public void ᐝ()
  {
    break label117;
    label3:
    int i = ʼ + 57;
    ॱॱ = i % 128;
    if (i % 2 == 0) {
      break label120;
    }
    for (;;)
    {
      switch (i)
      {
      default: 
        break;
      case 1: 
        j.ˋ(this, DG.class).ॱ();
        do
        {
          return;
          i = ʼ + 51;
          ॱॱ = i % 128;
        } while (i % 2 != 0);
        return;
        i = 0;
        break;
      case 0: 
        j.ˋ(this, DG.class).ॱ();
        throw new NullPointerException();
        label117:
        break label3;
        label120:
        i = 1;
      }
    }
  }
}
