package o;

import java.util.ArrayList;

public final class DT
  extends GD
{
  private static char[] ˊ;
  public static final if ˎ;
  private static final uA ॱ;
  private static int ॱॱ;
  private static int ᐝ;
  private ArrayList<X> ˋ;
  private int ˏ;
  
  static
  {
    for (;;)
    {
      int i = ॱॱ + 17;
      ᐝ = i % 128;
      if (i % 2 == 0) {
        break;
      }
      return;
      ॱॱ = 0;
      ᐝ = 1;
      ॱॱ();
      ˎ = new if(null);
      ॱ = uC.ˋ((vh)If.ˎ);
    }
  }
  
  /* Error */
  public DT()
  {
    // Byte code:
    //   0: goto +3 -> 3
    //   3: aload_0
    //   4: invokespecial 53	o/GD:<init>	()V
    //   7: iconst_4
    //   8: sipush 413
    //   11: sipush 30253
    //   14: invokestatic 58	o/O:ˋ	(IIC)Ljava/lang/Object;
    //   17: checkcast 60	java/lang/Class
    //   20: ldc 61
    //   22: invokevirtual 65	java/lang/Class:getField	(Ljava/lang/String;)Ljava/lang/reflect/Field;
    //   25: aconst_null
    //   26: invokevirtual 71	java/lang/reflect/Field:get	(Ljava/lang/Object;)Ljava/lang/Object;
    //   29: astore_2
    //   30: goto +17 -> 47
    //   33: astore_2
    //   34: aload_2
    //   35: invokevirtual 77	java/lang/Throwable:getCause	()Ljava/lang/Throwable;
    //   38: astore_3
    //   39: aload_3
    //   40: ifnull +5 -> 45
    //   43: aload_3
    //   44: athrow
    //   45: aload_2
    //   46: athrow
    //   47: bipush 6
    //   49: sipush 417
    //   52: iconst_0
    //   53: invokestatic 58	o/O:ˋ	(IIC)Ljava/lang/Object;
    //   56: checkcast 60	java/lang/Class
    //   59: ldc 78
    //   61: aconst_null
    //   62: invokevirtual 82	java/lang/Class:getMethod	(Ljava/lang/String;[Ljava/lang/Class;)Ljava/lang/reflect/Method;
    //   65: aload_2
    //   66: aconst_null
    //   67: invokevirtual 88	java/lang/reflect/Method:invoke	(Ljava/lang/Object;[Ljava/lang/Object;)Ljava/lang/Object;
    //   70: astore_2
    //   71: goto +17 -> 88
    //   74: astore_2
    //   75: aload_2
    //   76: invokevirtual 77	java/lang/Throwable:getCause	()Ljava/lang/Throwable;
    //   79: astore_3
    //   80: aload_3
    //   81: ifnull +5 -> 86
    //   84: aload_3
    //   85: athrow
    //   86: aload_2
    //   87: athrow
    //   88: iconst_4
    //   89: sipush 413
    //   92: sipush 30253
    //   95: invokestatic 58	o/O:ˋ	(IIC)Ljava/lang/Object;
    //   98: checkcast 60	java/lang/Class
    //   101: ldc 90
    //   103: aconst_null
    //   104: invokevirtual 82	java/lang/Class:getMethod	(Ljava/lang/String;[Ljava/lang/Class;)Ljava/lang/reflect/Method;
    //   107: aload_2
    //   108: aconst_null
    //   109: invokevirtual 88	java/lang/reflect/Method:invoke	(Ljava/lang/Object;[Ljava/lang/Object;)Ljava/lang/Object;
    //   112: checkcast 92	java/lang/Integer
    //   115: invokevirtual 96	java/lang/Integer:intValue	()I
    //   118: istore_1
    //   119: aload_0
    //   120: iload_1
    //   121: putfield 98	o/DT:ˏ	I
    //   124: aload_0
    //   125: new 100	java/util/ArrayList
    //   128: dup
    //   129: invokespecial 101	java/util/ArrayList:<init>	()V
    //   132: putfield 103	o/DT:ˋ	Ljava/util/ArrayList;
    //   135: return
    // Local variable table:
    //   start	length	slot	name	signature
    //   0	136	0	this	DT
    //   118	3	1	i	int
    //   29	1	2	localObject1	Object
    //   33	33	2	localObject2	Object
    //   70	1	2	localObject3	Object
    //   74	34	2	localObject4	Object
    //   38	47	3	localThrowable	Throwable
    // Exception table:
    //   from	to	target	type
    //   47	71	33	finally
    //   88	119	74	finally
  }
  
  /* Error */
  private static String ˏ(int[] paramArrayOfInt, byte[] paramArrayOfByte, boolean paramBoolean)
  {
    // Byte code:
    //   0: goto +547 -> 547
    //   3: aload 9
    //   5: iload 4
    //   7: caload
    //   8: istore_3
    //   9: iload 4
    //   11: iconst_1
    //   12: iadd
    //   13: istore 4
    //   15: goto +254 -> 269
    //   18: aload 9
    //   20: iload 4
    //   22: aload 10
    //   24: iload 4
    //   26: caload
    //   27: iconst_1
    //   28: ishl
    //   29: iconst_1
    //   30: iadd
    //   31: iload_3
    //   32: isub
    //   33: i2c
    //   34: castore
    //   35: goto -32 -> 3
    //   38: aload_1
    //   39: iload 4
    //   41: baload
    //   42: ifne +6 -> 48
    //   45: goto +436 -> 481
    //   48: goto +127 -> 175
    //   51: bipush 89
    //   53: istore_3
    //   54: goto +674 -> 728
    //   57: iload 7
    //   59: ifle +6 -> 65
    //   62: goto +345 -> 407
    //   65: goto +542 -> 607
    //   68: aload_0
    //   69: iconst_0
    //   70: iaload
    //   71: istore_3
    //   72: aload_0
    //   73: iconst_1
    //   74: iaload
    //   75: istore 6
    //   77: aload_0
    //   78: iconst_2
    //   79: iaload
    //   80: istore 7
    //   82: aload_0
    //   83: iconst_3
    //   84: iaload
    //   85: istore 8
    //   87: getstatic 109	o/DT:ˊ	[C
    //   90: astore 9
    //   92: iload 6
    //   94: newarray char
    //   96: astore 10
    //   98: aload 9
    //   100: iload_3
    //   101: aload 10
    //   103: iconst_0
    //   104: iload 6
    //   106: invokestatic 115	java/lang/System:arraycopy	(Ljava/lang/Object;ILjava/lang/Object;II)V
    //   109: aload_1
    //   110: ifnull +6 -> 116
    //   113: goto +205 -> 318
    //   116: aload 10
    //   118: astore_1
    //   119: goto +521 -> 640
    //   122: iload 5
    //   124: lookupswitch	default:+28->152, 60:+-106->18, 93:+332->456
    //   152: goto -134 -> 18
    //   155: goto +485 -> 640
    //   158: iload 6
    //   160: newarray char
    //   162: astore 9
    //   164: iconst_0
    //   165: istore_3
    //   166: goto +229 -> 395
    //   169: bipush 71
    //   171: istore_3
    //   172: goto +556 -> 728
    //   175: aload 9
    //   177: iload 4
    //   179: aload 10
    //   181: iload 4
    //   183: caload
    //   184: iconst_1
    //   185: ishl
    //   186: iload_3
    //   187: isub
    //   188: i2c
    //   189: castore
    //   190: goto -187 -> 3
    //   193: aload 9
    //   195: astore_1
    //   196: goto -41 -> 155
    //   199: bipush 60
    //   201: istore 5
    //   203: goto -81 -> 122
    //   206: iload 4
    //   208: lookupswitch	default:+28->236, 0:+456->664, 33:+229->437
    //   236: goto +428 -> 664
    //   239: goto -182 -> 57
    //   242: getstatic 28	o/DT:ॱॱ	I
    //   245: bipush 81
    //   247: iadd
    //   248: istore_3
    //   249: iload_3
    //   250: sipush 128
    //   253: irem
    //   254: putstatic 30	o/DT:ᐝ	I
    //   257: iload_3
    //   258: iconst_2
    //   259: irem
    //   260: ifne +6 -> 266
    //   263: goto +49 -> 312
    //   266: goto -198 -> 68
    //   269: iload 4
    //   271: iload 6
    //   273: if_icmpge +6 -> 279
    //   276: goto +6 -> 282
    //   279: goto -86 -> 193
    //   282: getstatic 28	o/DT:ॱॱ	I
    //   285: bipush 35
    //   287: iadd
    //   288: istore 5
    //   290: iload 5
    //   292: sipush 128
    //   295: irem
    //   296: putstatic 30	o/DT:ᐝ	I
    //   299: iload 5
    //   301: iconst_2
    //   302: irem
    //   303: ifne +6 -> 309
    //   306: goto -268 -> 38
    //   309: goto +45 -> 354
    //   312: goto -244 -> 68
    //   315: astore_0
    //   316: aload_0
    //   317: athrow
    //   318: getstatic 28	o/DT:ॱॱ	I
    //   321: bipush 13
    //   323: iadd
    //   324: istore_3
    //   325: iload_3
    //   326: sipush 128
    //   329: irem
    //   330: putstatic 30	o/DT:ᐝ	I
    //   333: iload_3
    //   334: iconst_2
    //   335: irem
    //   336: ifne +6 -> 342
    //   339: goto +251 -> 590
    //   342: goto +372 -> 714
    //   345: iconst_0
    //   346: istore 4
    //   348: goto -142 -> 206
    //   351: goto +253 -> 604
    //   354: aload_1
    //   355: iload 4
    //   357: baload
    //   358: iconst_1
    //   359: if_icmpne +6 -> 365
    //   362: goto +119 -> 481
    //   365: goto -190 -> 175
    //   368: getstatic 28	o/DT:ॱॱ	I
    //   371: bipush 111
    //   373: iadd
    //   374: istore_3
    //   375: iload_3
    //   376: sipush 128
    //   379: irem
    //   380: putstatic 30	o/DT:ᐝ	I
    //   383: iload_3
    //   384: iconst_2
    //   385: irem
    //   386: ifne +6 -> 392
    //   389: goto +269 -> 658
    //   392: goto +383 -> 775
    //   395: iload_3
    //   396: iload 6
    //   398: if_icmpge +6 -> 404
    //   401: goto +110 -> 511
    //   404: goto -59 -> 345
    //   407: getstatic 30	o/DT:ᐝ	I
    //   410: bipush 69
    //   412: iadd
    //   413: istore_3
    //   414: iload_3
    //   415: sipush 128
    //   418: irem
    //   419: putstatic 28	o/DT:ॱॱ	I
    //   422: iload_3
    //   423: iconst_2
    //   424: irem
    //   425: ifeq +6 -> 431
    //   428: goto +353 -> 781
    //   431: goto +45 -> 476
    //   434: goto -377 -> 57
    //   437: aload 9
    //   439: iload_3
    //   440: aload_1
    //   441: iload 6
    //   443: iload_3
    //   444: isub
    //   445: iconst_1
    //   446: isub
    //   447: caload
    //   448: castore
    //   449: iload_3
    //   450: iconst_1
    //   451: iadd
    //   452: istore_3
    //   453: goto +107 -> 560
    //   456: aload 9
    //   458: iload 4
    //   460: aload 10
    //   462: iload 4
    //   464: caload
    //   465: iconst_0
    //   466: irem
    //   467: iconst_1
    //   468: ishl
    //   469: iload_3
    //   470: idiv
    //   471: i2c
    //   472: castore
    //   473: goto -470 -> 3
    //   476: iconst_0
    //   477: istore_3
    //   478: goto +285 -> 763
    //   481: getstatic 28	o/DT:ॱॱ	I
    //   484: bipush 25
    //   486: iadd
    //   487: istore 5
    //   489: iload 5
    //   491: sipush 128
    //   494: irem
    //   495: putstatic 30	o/DT:ᐝ	I
    //   498: iload 5
    //   500: iconst_2
    //   501: irem
    //   502: ifne +6 -> 508
    //   505: goto +146 -> 651
    //   508: goto -309 -> 199
    //   511: bipush 33
    //   513: istore 4
    //   515: goto -309 -> 206
    //   518: iload_3
    //   519: lookupswitch	default:+25->544, 28:+-85->434, 35:+-280->239
    //   544: goto -305 -> 239
    //   547: goto -305 -> 242
    //   550: iload_2
    //   551: ifeq +6 -> 557
    //   554: goto -503 -> 51
    //   557: goto -388 -> 169
    //   560: getstatic 28	o/DT:ॱॱ	I
    //   563: bipush 61
    //   565: iadd
    //   566: istore 4
    //   568: iload 4
    //   570: sipush 128
    //   573: irem
    //   574: putstatic 30	o/DT:ᐝ	I
    //   577: iload 4
    //   579: iconst_2
    //   580: irem
    //   581: ifne +6 -> 587
    //   584: goto -233 -> 351
    //   587: goto +17 -> 604
    //   590: iload 6
    //   592: newarray char
    //   594: astore 9
    //   596: iconst_0
    //   597: istore_3
    //   598: iconst_1
    //   599: istore 4
    //   601: goto -332 -> 269
    //   604: goto -209 -> 395
    //   607: new 117	java/lang/String
    //   610: dup
    //   611: aload 9
    //   613: invokespecial 120	java/lang/String:<init>	([C)V
    //   616: areturn
    //   617: aload 9
    //   619: iload_3
    //   620: aload 9
    //   622: iload_3
    //   623: caload
    //   624: aload_0
    //   625: iconst_2
    //   626: iaload
    //   627: isub
    //   628: i2c
    //   629: castore
    //   630: iload_3
    //   631: iconst_1
    //   632: iadd
    //   633: istore_3
    //   634: goto +129 -> 763
    //   637: astore_0
    //   638: aload_0
    //   639: athrow
    //   640: iload 8
    //   642: ifle +6 -> 648
    //   645: goto +22 -> 667
    //   648: goto -98 -> 550
    //   651: bipush 93
    //   653: istore 5
    //   655: goto -533 -> 122
    //   658: bipush 28
    //   660: istore_3
    //   661: goto -143 -> 518
    //   664: goto -296 -> 368
    //   667: iload 6
    //   669: newarray char
    //   671: astore 9
    //   673: aload_1
    //   674: iconst_0
    //   675: aload 9
    //   677: iconst_0
    //   678: iload 6
    //   680: invokestatic 115	java/lang/System:arraycopy	(Ljava/lang/Object;ILjava/lang/Object;II)V
    //   683: aload 9
    //   685: iconst_0
    //   686: aload_1
    //   687: iload 6
    //   689: iload 8
    //   691: isub
    //   692: iload 8
    //   694: invokestatic 115	java/lang/System:arraycopy	(Ljava/lang/Object;ILjava/lang/Object;II)V
    //   697: aload 9
    //   699: iload 8
    //   701: aload_1
    //   702: iconst_0
    //   703: iload 6
    //   705: iload 8
    //   707: isub
    //   708: invokestatic 115	java/lang/System:arraycopy	(Ljava/lang/Object;ILjava/lang/Object;II)V
    //   711: goto -161 -> 550
    //   714: iload 6
    //   716: newarray char
    //   718: astore 9
    //   720: iconst_0
    //   721: istore_3
    //   722: iconst_0
    //   723: istore 4
    //   725: goto -456 -> 269
    //   728: aload_1
    //   729: astore 9
    //   731: iload_3
    //   732: lookupswitch	default:+28->760, 71:+-675->57, 89:+-574->158
    //   760: goto -602 -> 158
    //   763: iload_3
    //   764: iload 6
    //   766: if_icmpge +6 -> 772
    //   769: goto -152 -> 617
    //   772: goto -165 -> 607
    //   775: bipush 35
    //   777: istore_3
    //   778: goto -260 -> 518
    //   781: goto -305 -> 476
    // Local variable table:
    //   start	length	slot	name	signature
    //   0	784	0	paramArrayOfInt	int[]
    //   0	784	1	paramArrayOfByte	byte[]
    //   0	784	2	paramBoolean	boolean
    //   8	770	3	i	int
    //   5	719	4	j	int
    //   122	532	5	k	int
    //   75	692	6	m	int
    //   57	24	7	n	int
    //   85	623	8	i1	int
    //   3	727	9	localObject	Object
    //   22	439	10	arrayOfChar	char[]
    // Exception table:
    //   from	to	target	type
    //   568	577	315	java/lang/Exception
    //   560	568	637	java/lang/Exception
    //   568	577	637	java/lang/Exception
  }
  
  static void ॱॱ()
  {
    ˊ = new char[] { 73, 153, 151, 151, 160, 150, 150, 153, 149, 153, 147, 153 };
  }
  
  /* Error */
  private final void ᐝ()
  {
    // Byte code:
    //   0: goto +235 -> 235
    //   3: getstatic 28	o/DT:ॱॱ	I
    //   6: bipush 75
    //   8: iadd
    //   9: istore_1
    //   10: iload_1
    //   11: sipush 128
    //   14: irem
    //   15: putstatic 30	o/DT:ᐝ	I
    //   18: iload_1
    //   19: iconst_2
    //   20: irem
    //   21: ifne +6 -> 27
    //   24: goto +333 -> 357
    //   27: goto +21 -> 48
    //   30: iconst_1
    //   31: istore_1
    //   32: aload_0
    //   33: getfield 103	o/DT:ˋ	Ljava/util/ArrayList;
    //   36: astore_3
    //   37: aload_3
    //   38: invokevirtual 131	java/util/ArrayList:iterator	()Ljava/util/Iterator;
    //   41: astore_3
    //   42: goto +209 -> 251
    //   45: astore_3
    //   46: aload_3
    //   47: athrow
    //   48: iconst_4
    //   49: sipush 413
    //   52: sipush 30253
    //   55: invokestatic 58	o/O:ˋ	(IIC)Ljava/lang/Object;
    //   58: checkcast 60	java/lang/Class
    //   61: ldc 61
    //   63: invokevirtual 65	java/lang/Class:getField	(Ljava/lang/String;)Ljava/lang/reflect/Field;
    //   66: aconst_null
    //   67: invokevirtual 71	java/lang/reflect/Field:get	(Ljava/lang/Object;)Ljava/lang/Object;
    //   70: astore_3
    //   71: goto +20 -> 91
    //   74: astore_3
    //   75: aload_3
    //   76: invokevirtual 77	java/lang/Throwable:getCause	()Ljava/lang/Throwable;
    //   79: astore 4
    //   81: aload 4
    //   83: ifnull +6 -> 89
    //   86: aload 4
    //   88: athrow
    //   89: aload_3
    //   90: athrow
    //   91: bipush 6
    //   93: sipush 417
    //   96: iconst_0
    //   97: invokestatic 58	o/O:ˋ	(IIC)Ljava/lang/Object;
    //   100: checkcast 60	java/lang/Class
    //   103: ldc 78
    //   105: aconst_null
    //   106: invokevirtual 82	java/lang/Class:getMethod	(Ljava/lang/String;[Ljava/lang/Class;)Ljava/lang/reflect/Method;
    //   109: aload_3
    //   110: aconst_null
    //   111: invokevirtual 88	java/lang/reflect/Method:invoke	(Ljava/lang/Object;[Ljava/lang/Object;)Ljava/lang/Object;
    //   114: astore_3
    //   115: goto +20 -> 135
    //   118: astore_3
    //   119: aload_3
    //   120: invokevirtual 77	java/lang/Throwable:getCause	()Ljava/lang/Throwable;
    //   123: astore 4
    //   125: aload 4
    //   127: ifnull +6 -> 133
    //   130: aload 4
    //   132: athrow
    //   133: aload_3
    //   134: athrow
    //   135: iconst_4
    //   136: sipush 413
    //   139: sipush 30253
    //   142: invokestatic 58	o/O:ˋ	(IIC)Ljava/lang/Object;
    //   145: checkcast 60	java/lang/Class
    //   148: ldc 61
    //   150: iconst_1
    //   151: anewarray 60	java/lang/Class
    //   154: dup
    //   155: iconst_0
    //   156: getstatic 135	java/lang/Integer:TYPE	Ljava/lang/Class;
    //   159: aastore
    //   160: invokevirtual 82	java/lang/Class:getMethod	(Ljava/lang/String;[Ljava/lang/Class;)Ljava/lang/reflect/Method;
    //   163: aload_3
    //   164: iconst_1
    //   165: anewarray 137	java/lang/Object
    //   168: dup
    //   169: iconst_0
    //   170: iconst_5
    //   171: invokestatic 141	java/lang/Integer:valueOf	(I)Ljava/lang/Integer;
    //   174: aastore
    //   175: invokevirtual 88	java/lang/reflect/Method:invoke	(Ljava/lang/Object;[Ljava/lang/Object;)Ljava/lang/Object;
    //   178: pop
    //   179: return
    //   180: getstatic 28	o/DT:ॱॱ	I
    //   183: iconst_3
    //   184: iadd
    //   185: istore_1
    //   186: iload_1
    //   187: sipush 128
    //   190: irem
    //   191: putstatic 30	o/DT:ᐝ	I
    //   194: iload_1
    //   195: iconst_2
    //   196: irem
    //   197: ifne +6 -> 203
    //   200: goto +12 -> 212
    //   203: goto -173 -> 30
    //   206: bipush 71
    //   208: istore_2
    //   209: goto +93 -> 302
    //   212: iconst_0
    //   213: istore_1
    //   214: aload_0
    //   215: getfield 103	o/DT:ˋ	Ljava/util/ArrayList;
    //   218: astore_3
    //   219: aload_3
    //   220: invokevirtual 131	java/util/ArrayList:iterator	()Ljava/util/Iterator;
    //   223: astore_3
    //   224: goto +27 -> 251
    //   227: astore_3
    //   228: aload_3
    //   229: athrow
    //   230: iconst_1
    //   231: istore_1
    //   232: goto +99 -> 331
    //   235: goto -55 -> 180
    //   238: goto +13 -> 251
    //   241: iload_1
    //   242: ifeq +6 -> 248
    //   245: goto +27 -> 272
    //   248: goto -18 -> 230
    //   251: aload_3
    //   252: invokeinterface 147 1 0
    //   257: ifeq +6 -> 263
    //   260: goto +6 -> 266
    //   263: goto -57 -> 206
    //   266: bipush 44
    //   268: istore_2
    //   269: goto +33 -> 302
    //   272: iconst_0
    //   273: istore_1
    //   274: goto +57 -> 331
    //   277: iload_1
    //   278: aload_3
    //   279: invokeinterface 151 1 0
    //   284: checkcast 153	o/X
    //   287: aload_0
    //   288: getfield 98	o/DT:ˏ	I
    //   291: iconst_5
    //   292: invokeinterface 156 3 0
    //   297: iand
    //   298: istore_1
    //   299: goto -61 -> 238
    //   302: iload_2
    //   303: lookupswitch	default:+25->328, 44:+-26->277, 71:+-62->241
    //   328: goto -87 -> 241
    //   331: iload_1
    //   332: tableswitch	default:+24->356, 0:+-329->3, 1:+156->488
    //   356: return
    //   357: iconst_4
    //   358: sipush 413
    //   361: sipush 30253
    //   364: invokestatic 58	o/O:ˋ	(IIC)Ljava/lang/Object;
    //   367: checkcast 60	java/lang/Class
    //   370: ldc 61
    //   372: invokevirtual 65	java/lang/Class:getField	(Ljava/lang/String;)Ljava/lang/reflect/Field;
    //   375: aconst_null
    //   376: invokevirtual 71	java/lang/reflect/Field:get	(Ljava/lang/Object;)Ljava/lang/Object;
    //   379: astore_3
    //   380: goto +20 -> 400
    //   383: astore_3
    //   384: aload_3
    //   385: invokevirtual 77	java/lang/Throwable:getCause	()Ljava/lang/Throwable;
    //   388: astore 4
    //   390: aload 4
    //   392: ifnull +6 -> 398
    //   395: aload 4
    //   397: athrow
    //   398: aload_3
    //   399: athrow
    //   400: bipush 6
    //   402: sipush 417
    //   405: iconst_0
    //   406: invokestatic 58	o/O:ˋ	(IIC)Ljava/lang/Object;
    //   409: checkcast 60	java/lang/Class
    //   412: ldc 78
    //   414: aconst_null
    //   415: invokevirtual 82	java/lang/Class:getMethod	(Ljava/lang/String;[Ljava/lang/Class;)Ljava/lang/reflect/Method;
    //   418: aload_3
    //   419: aconst_null
    //   420: invokevirtual 88	java/lang/reflect/Method:invoke	(Ljava/lang/Object;[Ljava/lang/Object;)Ljava/lang/Object;
    //   423: astore_3
    //   424: goto +20 -> 444
    //   427: astore_3
    //   428: aload_3
    //   429: invokevirtual 77	java/lang/Throwable:getCause	()Ljava/lang/Throwable;
    //   432: astore 4
    //   434: aload 4
    //   436: ifnull +6 -> 442
    //   439: aload 4
    //   441: athrow
    //   442: aload_3
    //   443: athrow
    //   444: iconst_4
    //   445: sipush 413
    //   448: sipush 30253
    //   451: invokestatic 58	o/O:ˋ	(IIC)Ljava/lang/Object;
    //   454: checkcast 60	java/lang/Class
    //   457: ldc 61
    //   459: iconst_1
    //   460: anewarray 60	java/lang/Class
    //   463: dup
    //   464: iconst_0
    //   465: getstatic 135	java/lang/Integer:TYPE	Ljava/lang/Class;
    //   468: aastore
    //   469: invokevirtual 82	java/lang/Class:getMethod	(Ljava/lang/String;[Ljava/lang/Class;)Ljava/lang/reflect/Method;
    //   472: aload_3
    //   473: iconst_1
    //   474: anewarray 137	java/lang/Object
    //   477: dup
    //   478: iconst_0
    //   479: iconst_2
    //   480: invokestatic 141	java/lang/Integer:valueOf	(I)Ljava/lang/Integer;
    //   483: aastore
    //   484: invokevirtual 88	java/lang/reflect/Method:invoke	(Ljava/lang/Object;[Ljava/lang/Object;)Ljava/lang/Object;
    //   487: pop
    //   488: return
    // Local variable table:
    //   start	length	slot	name	signature
    //   0	489	0	this	DT
    //   9	289	1	i	int
    //   298	34	1	bool	boolean
    //   208	95	2	j	int
    //   36	6	3	localObject1	Object
    //   45	2	3	localException1	Exception
    //   70	1	3	localObject2	Object
    //   74	36	3	localObject3	Object
    //   114	1	3	localObject4	Object
    //   118	46	3	localObject5	Object
    //   218	6	3	localObject6	Object
    //   227	52	3	localException2	Exception
    //   379	1	3	localObject7	Object
    //   383	36	3	localObject8	Object
    //   423	1	3	localObject9	Object
    //   427	46	3	localObject10	Object
    //   79	361	4	localThrowable	Throwable
    // Exception table:
    //   from	to	target	type
    //   214	219	45	java/lang/Exception
    //   219	224	45	java/lang/Exception
    //   91	115	74	finally
    //   135	179	118	finally
    //   32	37	227	java/lang/Exception
    //   37	42	227	java/lang/Exception
    //   180	194	227	java/lang/Exception
    //   400	424	383	finally
    //   444	488	427	finally
  }
  
  /* Error */
  public final void ˋ()
  {
    // Byte code:
    //   0: goto +30 -> 30
    //   3: getstatic 30	o/DT:ᐝ	I
    //   6: bipush 107
    //   8: iadd
    //   9: istore_1
    //   10: iload_1
    //   11: sipush 128
    //   14: irem
    //   15: putstatic 28	o/DT:ॱॱ	I
    //   18: iload_1
    //   19: iconst_2
    //   20: irem
    //   21: ifeq +6 -> 27
    //   24: goto +57 -> 81
    //   27: goto +169 -> 196
    //   30: goto +474 -> 504
    //   33: aload_0
    //   34: getfield 103	o/DT:ˋ	Ljava/util/ArrayList;
    //   37: new 158	o/DX
    //   40: dup
    //   41: invokespecial 159	o/DX:<init>	()V
    //   44: invokevirtual 163	java/util/ArrayList:add	(Ljava/lang/Object;)Z
    //   47: pop
    //   48: aload_0
    //   49: getfield 103	o/DT:ˋ	Ljava/util/ArrayList;
    //   52: new 165	o/DS
    //   55: dup
    //   56: invokespecial 166	o/DS:<init>	()V
    //   59: invokevirtual 163	java/util/ArrayList:add	(Ljava/lang/Object;)Z
    //   62: pop
    //   63: aload_0
    //   64: getfield 103	o/DT:ˋ	Ljava/util/ArrayList;
    //   67: new 168	o/DW
    //   70: dup
    //   71: invokespecial 169	o/DW:<init>	()V
    //   74: invokevirtual 163	java/util/ArrayList:add	(Ljava/lang/Object;)Z
    //   77: pop
    //   78: goto +360 -> 438
    //   81: goto +115 -> 196
    //   84: iconst_4
    //   85: sipush 413
    //   88: sipush 30253
    //   91: invokestatic 58	o/O:ˋ	(IIC)Ljava/lang/Object;
    //   94: checkcast 60	java/lang/Class
    //   97: ldc 61
    //   99: invokevirtual 65	java/lang/Class:getField	(Ljava/lang/String;)Ljava/lang/reflect/Field;
    //   102: aconst_null
    //   103: invokevirtual 71	java/lang/reflect/Field:get	(Ljava/lang/Object;)Ljava/lang/Object;
    //   106: astore_2
    //   107: goto +17 -> 124
    //   110: astore_2
    //   111: aload_2
    //   112: invokevirtual 77	java/lang/Throwable:getCause	()Ljava/lang/Throwable;
    //   115: astore_3
    //   116: aload_3
    //   117: ifnull +5 -> 122
    //   120: aload_3
    //   121: athrow
    //   122: aload_2
    //   123: athrow
    //   124: bipush 6
    //   126: sipush 417
    //   129: iconst_0
    //   130: invokestatic 58	o/O:ˋ	(IIC)Ljava/lang/Object;
    //   133: checkcast 60	java/lang/Class
    //   136: ldc 78
    //   138: aconst_null
    //   139: invokevirtual 82	java/lang/Class:getMethod	(Ljava/lang/String;[Ljava/lang/Class;)Ljava/lang/reflect/Method;
    //   142: aload_2
    //   143: aconst_null
    //   144: invokevirtual 88	java/lang/reflect/Method:invoke	(Ljava/lang/Object;[Ljava/lang/Object;)Ljava/lang/Object;
    //   147: astore_2
    //   148: goto +17 -> 165
    //   151: astore_2
    //   152: aload_2
    //   153: invokevirtual 77	java/lang/Throwable:getCause	()Ljava/lang/Throwable;
    //   156: astore_3
    //   157: aload_3
    //   158: ifnull +5 -> 163
    //   161: aload_3
    //   162: athrow
    //   163: aload_2
    //   164: athrow
    //   165: iconst_4
    //   166: sipush 413
    //   169: sipush 30253
    //   172: invokestatic 58	o/O:ˋ	(IIC)Ljava/lang/Object;
    //   175: checkcast 60	java/lang/Class
    //   178: ldc -85
    //   180: aconst_null
    //   181: invokevirtual 82	java/lang/Class:getMethod	(Ljava/lang/String;[Ljava/lang/Class;)Ljava/lang/reflect/Method;
    //   184: aload_2
    //   185: aconst_null
    //   186: invokevirtual 88	java/lang/reflect/Method:invoke	(Ljava/lang/Object;[Ljava/lang/Object;)Ljava/lang/Object;
    //   189: pop
    //   190: goto +253 -> 443
    //   193: goto +245 -> 438
    //   196: iconst_4
    //   197: sipush 413
    //   200: sipush 30253
    //   203: invokestatic 58	o/O:ˋ	(IIC)Ljava/lang/Object;
    //   206: checkcast 60	java/lang/Class
    //   209: ldc 61
    //   211: invokevirtual 65	java/lang/Class:getField	(Ljava/lang/String;)Ljava/lang/reflect/Field;
    //   214: aconst_null
    //   215: invokevirtual 71	java/lang/reflect/Field:get	(Ljava/lang/Object;)Ljava/lang/Object;
    //   218: astore_2
    //   219: goto +17 -> 236
    //   222: astore_2
    //   223: aload_2
    //   224: invokevirtual 77	java/lang/Throwable:getCause	()Ljava/lang/Throwable;
    //   227: astore_3
    //   228: aload_3
    //   229: ifnull +5 -> 234
    //   232: aload_3
    //   233: athrow
    //   234: aload_2
    //   235: athrow
    //   236: bipush 6
    //   238: sipush 417
    //   241: iconst_0
    //   242: invokestatic 58	o/O:ˋ	(IIC)Ljava/lang/Object;
    //   245: checkcast 60	java/lang/Class
    //   248: ldc 78
    //   250: aconst_null
    //   251: invokevirtual 82	java/lang/Class:getMethod	(Ljava/lang/String;[Ljava/lang/Class;)Ljava/lang/reflect/Method;
    //   254: aload_2
    //   255: aconst_null
    //   256: invokevirtual 88	java/lang/reflect/Method:invoke	(Ljava/lang/Object;[Ljava/lang/Object;)Ljava/lang/Object;
    //   259: astore_2
    //   260: goto +17 -> 277
    //   263: astore_2
    //   264: aload_2
    //   265: invokevirtual 77	java/lang/Throwable:getCause	()Ljava/lang/Throwable;
    //   268: astore_3
    //   269: aload_3
    //   270: ifnull +5 -> 275
    //   273: aload_3
    //   274: athrow
    //   275: aload_2
    //   276: athrow
    //   277: iconst_4
    //   278: sipush 413
    //   281: sipush 30253
    //   284: invokestatic 58	o/O:ˋ	(IIC)Ljava/lang/Object;
    //   287: checkcast 60	java/lang/Class
    //   290: ldc 78
    //   292: aconst_null
    //   293: invokevirtual 82	java/lang/Class:getMethod	(Ljava/lang/String;[Ljava/lang/Class;)Ljava/lang/reflect/Method;
    //   296: aload_2
    //   297: aconst_null
    //   298: invokevirtual 88	java/lang/reflect/Method:invoke	(Ljava/lang/Object;[Ljava/lang/Object;)Ljava/lang/Object;
    //   301: checkcast 173	android/content/SharedPreferences
    //   304: astore_2
    //   305: aload_2
    //   306: iconst_4
    //   307: newarray int
    //   309: dup
    //   310: iconst_0
    //   311: iconst_0
    //   312: iastore
    //   313: dup
    //   314: iconst_1
    //   315: bipush 12
    //   317: iastore
    //   318: dup
    //   319: iconst_2
    //   320: bipush 45
    //   322: iastore
    //   323: dup
    //   324: iconst_3
    //   325: iconst_0
    //   326: iastore
    //   327: bipush 12
    //   329: newarray byte
    //   331: dup
    //   332: iconst_0
    //   333: ldc -82
    //   335: bastore
    //   336: dup
    //   337: iconst_1
    //   338: ldc -81
    //   340: bastore
    //   341: dup
    //   342: iconst_2
    //   343: ldc -81
    //   345: bastore
    //   346: dup
    //   347: iconst_3
    //   348: ldc -81
    //   350: bastore
    //   351: dup
    //   352: iconst_4
    //   353: ldc -81
    //   355: bastore
    //   356: dup
    //   357: iconst_5
    //   358: ldc -82
    //   360: bastore
    //   361: dup
    //   362: bipush 6
    //   364: ldc -81
    //   366: bastore
    //   367: dup
    //   368: bipush 7
    //   370: ldc -81
    //   372: bastore
    //   373: dup
    //   374: bipush 8
    //   376: ldc -81
    //   378: bastore
    //   379: dup
    //   380: bipush 9
    //   382: ldc -82
    //   384: bastore
    //   385: dup
    //   386: bipush 10
    //   388: ldc -81
    //   390: bastore
    //   391: dup
    //   392: bipush 11
    //   394: ldc -82
    //   396: bastore
    //   397: iconst_1
    //   398: invokestatic 177	o/DT:ˏ	([I[BZ)Ljava/lang/String;
    //   401: invokevirtual 181	java/lang/String:intern	()Ljava/lang/String;
    //   404: getstatic 187	o/Gw:UNKNOWN	Lo/Gw;
    //   407: invokevirtual 190	o/Gw:toString	()Ljava/lang/String;
    //   410: invokeinterface 194 3 0
    //   415: getstatic 187	o/Gw:UNKNOWN	Lo/Gw;
    //   418: invokevirtual 190	o/Gw:toString	()Ljava/lang/String;
    //   421: invokestatic 199	o/vq:ˊ	(Ljava/lang/Object;Ljava/lang/Object;)Z
    //   424: iconst_1
    //   425: ixor
    //   426: ifeq +6 -> 432
    //   429: goto -396 -> 33
    //   432: goto -348 -> 84
    //   435: goto -242 -> 193
    //   438: aload_0
    //   439: invokespecial 201	o/DT:ᐝ	()V
    //   442: return
    //   443: getstatic 30	o/DT:ᐝ	I
    //   446: bipush 103
    //   448: iadd
    //   449: istore_1
    //   450: iload_1
    //   451: sipush 128
    //   454: irem
    //   455: putstatic 28	o/DT:ॱॱ	I
    //   458: iload_1
    //   459: iconst_2
    //   460: irem
    //   461: ifeq +6 -> 467
    //   464: goto -29 -> 435
    //   467: goto -274 -> 193
    //   470: iconst_1
    //   471: istore_1
    //   472: iload_1
    //   473: tableswitch	default:+23->496, 0:+-35->438, 1:+-470->3
    //   496: goto -58 -> 438
    //   499: iconst_0
    //   500: istore_1
    //   501: goto -29 -> 472
    //   504: iconst_4
    //   505: sipush 413
    //   508: sipush 30253
    //   511: invokestatic 58	o/O:ˋ	(IIC)Ljava/lang/Object;
    //   514: checkcast 60	java/lang/Class
    //   517: ldc 61
    //   519: invokevirtual 65	java/lang/Class:getField	(Ljava/lang/String;)Ljava/lang/reflect/Field;
    //   522: aconst_null
    //   523: invokevirtual 71	java/lang/reflect/Field:get	(Ljava/lang/Object;)Ljava/lang/Object;
    //   526: astore_2
    //   527: goto +17 -> 544
    //   530: astore_2
    //   531: aload_2
    //   532: invokevirtual 77	java/lang/Throwable:getCause	()Ljava/lang/Throwable;
    //   535: astore_3
    //   536: aload_3
    //   537: ifnull +5 -> 542
    //   540: aload_3
    //   541: athrow
    //   542: aload_2
    //   543: athrow
    //   544: bipush 6
    //   546: sipush 417
    //   549: iconst_0
    //   550: invokestatic 58	o/O:ˋ	(IIC)Ljava/lang/Object;
    //   553: checkcast 60	java/lang/Class
    //   556: ldc 78
    //   558: aconst_null
    //   559: invokevirtual 82	java/lang/Class:getMethod	(Ljava/lang/String;[Ljava/lang/Class;)Ljava/lang/reflect/Method;
    //   562: aload_2
    //   563: aconst_null
    //   564: invokevirtual 88	java/lang/reflect/Method:invoke	(Ljava/lang/Object;[Ljava/lang/Object;)Ljava/lang/Object;
    //   567: astore_2
    //   568: goto +17 -> 585
    //   571: astore_2
    //   572: aload_2
    //   573: invokevirtual 77	java/lang/Throwable:getCause	()Ljava/lang/Throwable;
    //   576: astore_3
    //   577: aload_3
    //   578: ifnull +5 -> 583
    //   581: aload_3
    //   582: athrow
    //   583: aload_2
    //   584: athrow
    //   585: iconst_4
    //   586: sipush 413
    //   589: sipush 30253
    //   592: invokestatic 58	o/O:ˋ	(IIC)Ljava/lang/Object;
    //   595: checkcast 60	java/lang/Class
    //   598: ldc 90
    //   600: aconst_null
    //   601: invokevirtual 82	java/lang/Class:getMethod	(Ljava/lang/String;[Ljava/lang/Class;)Ljava/lang/reflect/Method;
    //   604: aload_2
    //   605: aconst_null
    //   606: invokevirtual 88	java/lang/reflect/Method:invoke	(Ljava/lang/Object;[Ljava/lang/Object;)Ljava/lang/Object;
    //   609: checkcast 92	java/lang/Integer
    //   612: invokevirtual 96	java/lang/Integer:intValue	()I
    //   615: istore_1
    //   616: aload_0
    //   617: iload_1
    //   618: putfield 98	o/DT:ˏ	I
    //   621: aload_0
    //   622: getfield 98	o/DT:ˏ	I
    //   625: getstatic 207	o/Gq:VERSION_0	Lo/Gq;
    //   628: invokevirtual 209	o/Gq:ॱ	()I
    //   631: if_icmpne +6 -> 637
    //   634: goto -164 -> 470
    //   637: goto -138 -> 499
    // Local variable table:
    //   start	length	slot	name	signature
    //   0	640	0	this	DT
    //   9	609	1	i	int
    //   106	1	2	localObject1	Object
    //   110	33	2	localObject2	Object
    //   147	1	2	localObject3	Object
    //   151	34	2	localObject4	Object
    //   218	1	2	localObject5	Object
    //   222	33	2	localObject6	Object
    //   259	1	2	localObject7	Object
    //   263	34	2	localObject8	Object
    //   304	223	2	localObject9	Object
    //   530	33	2	localObject10	Object
    //   567	1	2	localObject11	Object
    //   571	34	2	localObject12	Object
    //   115	467	3	localThrowable	Throwable
    // Exception table:
    //   from	to	target	type
    //   124	148	110	finally
    //   165	190	151	finally
    //   236	260	222	finally
    //   277	305	263	finally
    //   544	568	530	finally
    //   585	616	571	finally
  }
  
  static final class If
    extends vs
    implements vh<DT>
  {
    public static final If ˎ = new If();
    
    If()
    {
      super();
    }
    
    public final DT ॱ()
    {
      return DT.ˊ.ॱ.ˏ();
    }
  }
  
  public static final class if
  {
    private static int ˊ = 0;
    private static char[] ˏ;
    private static int ॱ = 1;
    
    static
    {
      break label40;
      int i = ॱ + 69;
      ˊ = i % 128;
      if (i % 2 == 0) {
        i = 0;
      }
      for (;;)
      {
        try
        {
          label40:
          ॱ();
          localVG = vu.ˋ(if.class);
        }
        catch (Exception localException1)
        {
          vG localVG;
          throw localException1;
        }
        try
        {
          ˋ = new vF[] { (vF)vu.ˋ(new vr(localVG, ॱ(new int[] { 0, 8, 0, 0 }, new byte[] { 1, 1, 1, 1, 1, 1, 1, 0 }, false).intern(), ॱ(new int[] { 8, 58, 0, 42 }, new byte[] { 1, 1, 0, 0, 0, 1, 1, 1, 0, 1, 1, 0, 1, 1, 1, 1, 1, 1, 0, 0, 0, 1, 1, 0, 0, 1, 1, 0, 1, 1, 1, 1, 1, 1, 0, 0, 1, 1, 0, 0, 1, 1, 0, 0, 1, 1, 1, 1, 1, 1, 1, 1, 0, 1, 1, 1, 0, 1 }, false).intern())) };
        }
        catch (Exception localException2)
        {
          throw localException2;
        }
        switch (i)
        {
        default: 
          return;
        case 0: 
          return;
        }
        i = null.length;
        return;
        i = 1;
      }
    }
    
    private if() {}
    
    /* Error */
    private static String ॱ(int[] paramArrayOfInt, byte[] paramArrayOfByte, boolean paramBoolean)
    {
      // Byte code:
      //   0: goto +188 -> 188
      //   3: iload_3
      //   4: iload 6
      //   6: if_icmpge +6 -> 12
      //   9: goto +665 -> 674
      //   12: goto +668 -> 680
      //   15: iconst_0
      //   16: istore_3
      //   17: goto -14 -> 3
      //   20: astore_0
      //   21: aload_0
      //   22: athrow
      //   23: aload 10
      //   25: astore 9
      //   27: iload_3
      //   28: lookupswitch	default:+28->56, 24:+430->458, 68:+661->689
      //   56: goto +402 -> 458
      //   59: bipush 61
      //   61: istore_3
      //   62: goto +313 -> 375
      //   65: goto +434 -> 499
      //   68: getstatic 22	o/DT$if:ॱ	I
      //   71: istore 4
      //   73: iload 4
      //   75: bipush 123
      //   77: iadd
      //   78: istore 4
      //   80: iload 4
      //   82: sipush 128
      //   85: irem
      //   86: putstatic 20	o/DT$if:ˊ	I
      //   89: iload 4
      //   91: iconst_2
      //   92: irem
      //   93: ifeq +6 -> 99
      //   96: goto -31 -> 65
      //   99: goto +400 -> 499
      //   102: iload_2
      //   103: ifeq +6 -> 109
      //   106: goto +131 -> 237
      //   109: goto +466 -> 575
      //   112: bipush 24
      //   114: istore_3
      //   115: goto -92 -> 23
      //   118: bipush 85
      //   120: istore_3
      //   121: goto +579 -> 700
      //   124: iload 5
      //   126: istore_3
      //   127: goto +97 -> 224
      //   130: iload 6
      //   132: newarray char
      //   134: astore_1
      //   135: aload 9
      //   137: iconst_0
      //   138: aload_1
      //   139: iconst_0
      //   140: iload 6
      //   142: invokestatic 64	java/lang/System:arraycopy	(Ljava/lang/Object;ILjava/lang/Object;II)V
      //   145: aload_1
      //   146: iconst_0
      //   147: aload 9
      //   149: iload 6
      //   151: iload 8
      //   153: isub
      //   154: iload 8
      //   156: invokestatic 64	java/lang/System:arraycopy	(Ljava/lang/Object;ILjava/lang/Object;II)V
      //   159: aload_1
      //   160: iload 8
      //   162: aload 9
      //   164: iconst_0
      //   165: iload 6
      //   167: iload 8
      //   169: isub
      //   170: invokestatic 64	java/lang/System:arraycopy	(Ljava/lang/Object;ILjava/lang/Object;II)V
      //   173: goto -71 -> 102
      //   176: iload_3
      //   177: iload 6
      //   179: if_icmpge +6 -> 185
      //   182: goto -114 -> 68
      //   185: goto +486 -> 671
      //   188: goto +219 -> 407
      //   191: getstatic 20	o/DT$if:ˊ	I
      //   194: bipush 71
      //   196: iadd
      //   197: istore_3
      //   198: iload_3
      //   199: sipush 128
      //   202: irem
      //   203: putstatic 22	o/DT$if:ॱ	I
      //   206: iload_3
      //   207: iconst_2
      //   208: irem
      //   209: ifne +6 -> 215
      //   212: goto +447 -> 659
      //   215: goto -97 -> 118
      //   218: bipush 96
      //   220: istore_3
      //   221: goto +154 -> 375
      //   224: iload 4
      //   226: iload 6
      //   228: if_icmpge +6 -> 234
      //   231: goto +330 -> 561
      //   234: goto +324 -> 558
      //   237: bipush 43
      //   239: istore_3
      //   240: goto +385 -> 625
      //   243: getstatic 22	o/DT$if:ॱ	I
      //   246: bipush 41
      //   248: iadd
      //   249: istore_3
      //   250: iload_3
      //   251: sipush 128
      //   254: irem
      //   255: putstatic 20	o/DT$if:ˊ	I
      //   258: iload_3
      //   259: iconst_2
      //   260: irem
      //   261: ifeq +6 -> 267
      //   264: goto +108 -> 372
      //   267: goto +398 -> 665
      //   270: new 40	java/lang/String
      //   273: dup
      //   274: aload_1
      //   275: invokespecial 67	java/lang/String:<init>	([C)V
      //   278: areturn
      //   279: goto -103 -> 176
      //   282: getstatic 20	o/DT$if:ˊ	I
      //   285: bipush 9
      //   287: iadd
      //   288: istore_3
      //   289: iload_3
      //   290: sipush 128
      //   293: irem
      //   294: putstatic 22	o/DT$if:ॱ	I
      //   297: iload_3
      //   298: iconst_2
      //   299: irem
      //   300: ifne +6 -> 306
      //   303: goto +24 -> 327
      //   306: goto -176 -> 130
      //   309: aload_1
      //   310: iload_3
      //   311: aload_1
      //   312: iload_3
      //   313: caload
      //   314: aload_0
      //   315: iconst_2
      //   316: iaload
      //   317: isub
      //   318: i2c
      //   319: castore
      //   320: iload_3
      //   321: iconst_1
      //   322: iadd
      //   323: istore_3
      //   324: goto -321 -> 3
      //   327: goto -197 -> 130
      //   330: iload 7
      //   332: ifle +6 -> 338
      //   335: goto -320 -> 15
      //   338: goto -68 -> 270
      //   341: aload 9
      //   343: iload 4
      //   345: aload 10
      //   347: iload 4
      //   349: caload
      //   350: iconst_1
      //   351: ishl
      //   352: iload_3
      //   353: isub
      //   354: i2c
      //   355: castore
      //   356: aload 9
      //   358: iload 4
      //   360: caload
      //   361: istore 5
      //   363: iload 4
      //   365: iconst_1
      //   366: iadd
      //   367: istore 4
      //   369: goto -178 -> 191
      //   372: goto +317 -> 689
      //   375: iload_3
      //   376: lookupswitch	default:+28->404, 61:+152->528, 96:+142->518
      //   404: goto +114 -> 518
      //   407: aload_0
      //   408: iconst_0
      //   409: iaload
      //   410: istore_3
      //   411: aload_0
      //   412: iconst_1
      //   413: iaload
      //   414: istore 6
      //   416: aload_0
      //   417: iconst_2
      //   418: iaload
      //   419: istore 7
      //   421: aload_0
      //   422: iconst_3
      //   423: iaload
      //   424: istore 8
      //   426: getstatic 69	o/DT$if:ˏ	[C
      //   429: astore 9
      //   431: iload 6
      //   433: newarray char
      //   435: astore 10
      //   437: aload 9
      //   439: iload_3
      //   440: aload 10
      //   442: iconst_0
      //   443: iload 6
      //   445: invokestatic 64	java/lang/System:arraycopy	(Ljava/lang/Object;ILjava/lang/Object;II)V
      //   448: aload_1
      //   449: ifnull +6 -> 455
      //   452: goto -340 -> 112
      //   455: goto +126 -> 581
      //   458: iload 6
      //   460: newarray char
      //   462: astore 9
      //   464: iconst_0
      //   465: istore_3
      //   466: iconst_0
      //   467: istore 4
      //   469: goto +199 -> 668
      //   472: getstatic 22	o/DT$if:ॱ	I
      //   475: bipush 123
      //   477: iadd
      //   478: istore_3
      //   479: iload_3
      //   480: sipush 128
      //   483: irem
      //   484: putstatic 20	o/DT$if:ˊ	I
      //   487: iload_3
      //   488: iconst_2
      //   489: irem
      //   490: ifeq +6 -> 496
      //   493: goto -434 -> 59
      //   496: goto -278 -> 218
      //   499: aload_1
      //   500: iload_3
      //   501: aload 9
      //   503: iload 6
      //   505: iload_3
      //   506: isub
      //   507: iconst_1
      //   508: isub
      //   509: caload
      //   510: castore
      //   511: iload_3
      //   512: iconst_1
      //   513: iadd
      //   514: istore_3
      //   515: goto -236 -> 279
      //   518: iload 6
      //   520: newarray char
      //   522: astore_1
      //   523: iconst_0
      //   524: istore_3
      //   525: goto -349 -> 176
      //   528: iload 6
      //   530: newarray char
      //   532: astore_1
      //   533: iconst_1
      //   534: istore_3
      //   535: goto -359 -> 176
      //   538: aload 9
      //   540: iload 4
      //   542: aload 10
      //   544: iload 4
      //   546: caload
      //   547: iconst_1
      //   548: ishl
      //   549: iconst_1
      //   550: iadd
      //   551: iload_3
      //   552: isub
      //   553: i2c
      //   554: castore
      //   555: goto -199 -> 356
      //   558: goto -315 -> 243
      //   561: aload_1
      //   562: iload 4
      //   564: baload
      //   565: iconst_1
      //   566: if_icmpne +6 -> 572
      //   569: goto -31 -> 538
      //   572: goto -231 -> 341
      //   575: bipush 48
      //   577: istore_3
      //   578: goto +47 -> 625
      //   581: bipush 68
      //   583: istore_3
      //   584: goto -561 -> 23
      //   587: iload 4
      //   589: tableswitch	default:+23->612, 0:+-280->309, 1:+-319->270
      //   612: goto -342 -> 270
      //   615: iconst_4
      //   616: iconst_4
      //   617: idiv
      //   618: istore_3
      //   619: iload 5
      //   621: istore_3
      //   622: goto -398 -> 224
      //   625: aload 9
      //   627: astore_1
      //   628: iload_3
      //   629: lookupswitch	default:+27->656, 43:+-157->472, 48:+-299->330
      //   656: goto -184 -> 472
      //   659: bipush 19
      //   661: istore_3
      //   662: goto +38 -> 700
      //   665: goto +24 -> 689
      //   668: goto -444 -> 224
      //   671: goto -341 -> 330
      //   674: iconst_0
      //   675: istore 4
      //   677: goto -90 -> 587
      //   680: iconst_1
      //   681: istore 4
      //   683: goto -96 -> 587
      //   686: astore_0
      //   687: aload_0
      //   688: athrow
      //   689: iload 8
      //   691: ifle +6 -> 697
      //   694: goto -412 -> 282
      //   697: goto -595 -> 102
      //   700: iload_3
      //   701: lookupswitch	default:+27->728, 19:+-86->615, 85:+-577->124
      //   728: goto -604 -> 124
      // Local variable table:
      //   start	length	slot	name	signature
      //   0	731	0	paramArrayOfInt	int[]
      //   0	731	1	paramArrayOfByte	byte[]
      //   0	731	2	paramBoolean	boolean
      //   3	698	3	i	int
      //   71	611	4	j	int
      //   124	496	5	k	int
      //   4	525	6	m	int
      //   330	90	7	n	int
      //   151	539	8	i1	int
      //   25	601	9	arrayOfChar1	char[]
      //   23	520	10	arrayOfChar2	char[]
      // Exception table:
      //   from	to	target	type
      //   135	145	20	java/lang/Exception
      //   68	73	686	java/lang/Exception
      //   80	89	686	java/lang/Exception
      //   282	289	686	java/lang/Exception
      //   289	297	686	java/lang/Exception
    }
    
    static void ॱ()
    {
      ˏ = new char[] { 52, 107, 112, 115, 106, 103, 104, 100, 23, 72, 107, 115, 111, 77, 72, 104, 111, 113, 81, 82, 114, 107, 108, 105, 98, 100, 74, 78, 103, 103, 103, 100, 102, 107, 80, 66, 98, 107, 108, 105, 98, 100, 89, 87, 103, 103, 100, 102, 107, 86, 81, 102, 108, 94, 91, 112, 115, 106, 103, 104, 100, 70, 40, 58, 95, 112 };
    }
    
    public final DT ˎ()
    {
      int i;
      for (;;)
      {
        switch (i)
        {
        default: 
          break;
        case 0: 
          localObject = DT.ˎ();
          localVF = ˋ[0];
          localObject = (DT)((uA)localObject).ˋ();
          break label92;
          label57:
          i = 1;
        }
      }
      label62:
      return localObject;
      Object localObject = DT.ˎ();
      vF localVF = ˋ[0];
      localObject = (DT)((uA)localObject).ˋ();
      for (;;)
      {
        i = 0;
        break;
        label92:
        i = ॱ + 77;
        ˊ = i % 128;
        if (i % 2 != 0) {
          break label62;
        }
        return localObject;
        i = ॱ + 103;
        ˊ = i % 128;
        if (i % 2 != 0) {
          break label57;
        }
      }
    }
  }
  
  static final class ˊ
  {
    private static final DT ˏ = new DT();
    public static final ˊ ॱ = new ˊ();
    
    private ˊ() {}
    
    public final DT ˏ()
    {
      return ˏ;
    }
  }
}
