package o;

public final class DX
  implements X
{
  private static int ʻ;
  private static char[] ˊ = { 196, 230, 217, 218, 226, 215, 231, 183, 220, 213, 219, 221, 148, 232, 227, 237, 228, 216, 149 };
  private static int ˋ = 0;
  private static int ˎ = 116;
  private static boolean ˏ;
  private static boolean ॱ;
  
  static
  {
    ʻ = 1;
    ॱ = true;
    ˏ = true;
  }
  
  public DX() {}
  
  private static String ˎ(byte[] paramArrayOfByte, int[] paramArrayOfInt, char[] paramArrayOfChar, int paramInt)
  {
    break label347;
    paramInt = 1;
    break label251;
    int i;
    int k;
    label48:
    char[] arrayOfChar;
    int j;
    label79:
    label152:
    int m;
    switch (i)
    {
    default: 
      break;
      for (;;)
      {
        if (i >= k)
        {
          break label326;
          paramArrayOfInt[i] = ((char)(arrayOfChar[(paramArrayOfByte[(k - 1 - i)] + paramInt)] - j));
          i += 1;
          break label219;
          paramInt = ʻ + 17;
          ˋ = paramInt % 128;
          if (paramInt % 2 != 0) {
            break;
          }
          break label241;
        }
        paramArrayOfByte[i] = ((char)(arrayOfChar[(paramArrayOfInt[(k - 1 - i)] - paramInt)] - j));
        i += 1;
      }
    case 1: 
      k = paramArrayOfChar.length;
      paramArrayOfByte = new char[k];
      i = 0;
      break label362;
      m = ʻ + 47;
      ˋ = m % 128;
      if (m % 2 != 0) {}
      break;
    }
    for (;;)
    {
      if (!ˏ)
      {
        break label201;
        paramInt = 85 / 0;
        return paramArrayOfByte;
        label201:
        i = 0;
        break;
      }
      label219:
      label241:
      label251:
      label326:
      label347:
      label350:
      label359:
      label362:
      label375:
      label406:
      do
      {
        k = paramArrayOfByte.length;
        paramArrayOfInt = new char[k];
        i = 0;
        if (i >= k)
        {
          break label350;
          i = 1;
          break;
        }
        for (;;)
        {
          break label362;
          paramInt = 0;
          break label251;
          return paramArrayOfByte;
          break label375;
          switch (paramInt)
          {
          }
          return paramArrayOfByte;
          m = ʻ + 51;
          ˋ = m % 128;
          if (m % 2 == 0)
          {
            break label48;
            k = paramArrayOfInt.length;
            paramArrayOfByte = new char[k];
            i = 0;
            break label359;
          }
          break label48;
          return new String(paramArrayOfByte);
          for (;;)
          {
            paramArrayOfByte = new String(paramArrayOfByte);
            break label79;
            break label406;
            return new String(paramArrayOfInt);
            break;
            if (i < k) {
              break label152;
            }
          }
          paramArrayOfByte[i] = ((char)(arrayOfChar[(paramArrayOfChar[(k - 1 - i)] - paramInt)] - j));
          i += 1;
        }
        arrayOfChar = ˊ;
        j = ˎ;
      } while (ॱ);
    }
  }
  
  /* Error */
  public boolean ॱ(int arg1, int arg2)
  {
    // Byte code:
    //   0: goto +1641 -> 1641
    //   3: bipush 11
    //   5: newarray byte
    //   7: dup
    //   8: iconst_0
    //   9: ldc 62
    //   11: bastore
    //   12: dup
    //   13: iconst_1
    //   14: ldc 63
    //   16: bastore
    //   17: dup
    //   18: iconst_2
    //   19: ldc 64
    //   21: bastore
    //   22: dup
    //   23: iconst_3
    //   24: ldc 65
    //   26: bastore
    //   27: dup
    //   28: iconst_4
    //   29: ldc 63
    //   31: bastore
    //   32: dup
    //   33: iconst_5
    //   34: ldc 66
    //   36: bastore
    //   37: dup
    //   38: bipush 6
    //   40: ldc 63
    //   42: bastore
    //   43: dup
    //   44: bipush 7
    //   46: ldc 67
    //   48: bastore
    //   49: dup
    //   50: bipush 8
    //   52: ldc 63
    //   54: bastore
    //   55: dup
    //   56: bipush 9
    //   58: ldc 66
    //   60: bastore
    //   61: dup
    //   62: bipush 10
    //   64: ldc 68
    //   66: bastore
    //   67: aconst_null
    //   68: aconst_null
    //   69: bipush 38
    //   71: invokestatic 70	o/DX:ˎ	([B[I[CI)Ljava/lang/String;
    //   74: invokevirtual 74	java/lang/String:intern	()Ljava/lang/String;
    //   77: astore 4
    //   79: bipush 43
    //   81: newarray byte
    //   83: dup
    //   84: iconst_0
    //   85: ldc 75
    //   87: bastore
    //   88: dup
    //   89: iconst_1
    //   90: ldc 63
    //   92: bastore
    //   93: dup
    //   94: iconst_2
    //   95: ldc 64
    //   97: bastore
    //   98: dup
    //   99: iconst_3
    //   100: ldc 65
    //   102: bastore
    //   103: dup
    //   104: iconst_4
    //   105: ldc 63
    //   107: bastore
    //   108: dup
    //   109: iconst_5
    //   110: ldc 66
    //   112: bastore
    //   113: dup
    //   114: bipush 6
    //   116: ldc 63
    //   118: bastore
    //   119: dup
    //   120: bipush 7
    //   122: ldc 67
    //   124: bastore
    //   125: dup
    //   126: bipush 8
    //   128: ldc 63
    //   130: bastore
    //   131: dup
    //   132: bipush 9
    //   134: ldc 66
    //   136: bastore
    //   137: dup
    //   138: bipush 10
    //   140: ldc 76
    //   142: bastore
    //   143: dup
    //   144: bipush 11
    //   146: ldc 77
    //   148: bastore
    //   149: dup
    //   150: bipush 12
    //   152: ldc 78
    //   154: bastore
    //   155: dup
    //   156: bipush 13
    //   158: ldc 63
    //   160: bastore
    //   161: dup
    //   162: bipush 14
    //   164: ldc 66
    //   166: bastore
    //   167: dup
    //   168: bipush 15
    //   170: ldc 79
    //   172: bastore
    //   173: dup
    //   174: bipush 16
    //   176: ldc 80
    //   178: bastore
    //   179: dup
    //   180: bipush 17
    //   182: ldc 62
    //   184: bastore
    //   185: dup
    //   186: bipush 18
    //   188: ldc 77
    //   190: bastore
    //   191: dup
    //   192: bipush 19
    //   194: ldc 78
    //   196: bastore
    //   197: dup
    //   198: bipush 20
    //   200: ldc 63
    //   202: bastore
    //   203: dup
    //   204: bipush 21
    //   206: ldc 81
    //   208: bastore
    //   209: dup
    //   210: bipush 22
    //   212: ldc 76
    //   214: bastore
    //   215: dup
    //   216: bipush 23
    //   218: ldc 82
    //   220: bastore
    //   221: dup
    //   222: bipush 24
    //   224: ldc 66
    //   226: bastore
    //   227: dup
    //   228: bipush 25
    //   230: ldc 64
    //   232: bastore
    //   233: dup
    //   234: bipush 26
    //   236: ldc 65
    //   238: bastore
    //   239: dup
    //   240: bipush 27
    //   242: ldc 63
    //   244: bastore
    //   245: dup
    //   246: bipush 28
    //   248: ldc 77
    //   250: bastore
    //   251: dup
    //   252: bipush 29
    //   254: ldc 65
    //   256: bastore
    //   257: dup
    //   258: bipush 30
    //   260: ldc 79
    //   262: bastore
    //   263: dup
    //   264: bipush 31
    //   266: ldc 77
    //   268: bastore
    //   269: dup
    //   270: bipush 32
    //   272: ldc 83
    //   274: bastore
    //   275: dup
    //   276: bipush 33
    //   278: ldc 81
    //   280: bastore
    //   281: dup
    //   282: bipush 34
    //   284: ldc 77
    //   286: bastore
    //   287: dup
    //   288: bipush 35
    //   290: ldc 84
    //   292: bastore
    //   293: dup
    //   294: bipush 36
    //   296: ldc 65
    //   298: bastore
    //   299: dup
    //   300: bipush 37
    //   302: ldc 85
    //   304: bastore
    //   305: dup
    //   306: bipush 38
    //   308: ldc 84
    //   310: bastore
    //   311: dup
    //   312: bipush 39
    //   314: ldc 65
    //   316: bastore
    //   317: dup
    //   318: bipush 40
    //   320: ldc 79
    //   322: bastore
    //   323: dup
    //   324: bipush 41
    //   326: ldc 80
    //   328: bastore
    //   329: dup
    //   330: bipush 42
    //   332: ldc 86
    //   334: bastore
    //   335: aconst_null
    //   336: aconst_null
    //   337: bipush 48
    //   339: invokestatic 70	o/DX:ˎ	([B[I[CI)Ljava/lang/String;
    //   342: invokevirtual 74	java/lang/String:intern	()Ljava/lang/String;
    //   345: astore 5
    //   347: goto +23 -> 370
    //   350: astore 4
    //   352: aload 4
    //   354: invokevirtual 92	java/lang/Throwable:getCause	()Ljava/lang/Throwable;
    //   357: astore 5
    //   359: aload 5
    //   361: ifnull +6 -> 367
    //   364: aload 5
    //   366: athrow
    //   367: aload 4
    //   369: athrow
    //   370: iconst_4
    //   371: bipush 42
    //   373: ldc 93
    //   375: invokestatic 98	o/O:ˋ	(IIC)Ljava/lang/Object;
    //   378: checkcast 100	java/lang/Class
    //   381: ldc 101
    //   383: iconst_2
    //   384: anewarray 100	java/lang/Class
    //   387: dup
    //   388: iconst_0
    //   389: ldc 55
    //   391: aastore
    //   392: dup
    //   393: iconst_1
    //   394: ldc 55
    //   396: aastore
    //   397: invokevirtual 105	java/lang/Class:getMethod	(Ljava/lang/String;[Ljava/lang/Class;)Ljava/lang/reflect/Method;
    //   400: aconst_null
    //   401: iconst_2
    //   402: anewarray 4	java/lang/Object
    //   405: dup
    //   406: iconst_0
    //   407: aload 4
    //   409: aastore
    //   410: dup
    //   411: iconst_1
    //   412: aload 5
    //   414: aastore
    //   415: invokevirtual 111	java/lang/reflect/Method:invoke	(Ljava/lang/Object;[Ljava/lang/Object;)Ljava/lang/Object;
    //   418: pop
    //   419: iconst_4
    //   420: sipush 413
    //   423: sipush 30253
    //   426: invokestatic 98	o/O:ˋ	(IIC)Ljava/lang/Object;
    //   429: checkcast 100	java/lang/Class
    //   432: ldc 112
    //   434: invokevirtual 116	java/lang/Class:getField	(Ljava/lang/String;)Ljava/lang/reflect/Field;
    //   437: aconst_null
    //   438: invokevirtual 122	java/lang/reflect/Field:get	(Ljava/lang/Object;)Ljava/lang/Object;
    //   441: astore 4
    //   443: goto +23 -> 466
    //   446: astore 4
    //   448: aload 4
    //   450: invokevirtual 92	java/lang/Throwable:getCause	()Ljava/lang/Throwable;
    //   453: astore 5
    //   455: aload 5
    //   457: ifnull +6 -> 463
    //   460: aload 5
    //   462: athrow
    //   463: aload 4
    //   465: athrow
    //   466: bipush 6
    //   468: sipush 417
    //   471: iconst_0
    //   472: invokestatic 98	o/O:ˋ	(IIC)Ljava/lang/Object;
    //   475: checkcast 100	java/lang/Class
    //   478: ldc 123
    //   480: aconst_null
    //   481: invokevirtual 105	java/lang/Class:getMethod	(Ljava/lang/String;[Ljava/lang/Class;)Ljava/lang/reflect/Method;
    //   484: aload 4
    //   486: aconst_null
    //   487: invokevirtual 111	java/lang/reflect/Method:invoke	(Ljava/lang/Object;[Ljava/lang/Object;)Ljava/lang/Object;
    //   490: astore 4
    //   492: goto +23 -> 515
    //   495: astore 4
    //   497: aload 4
    //   499: invokevirtual 92	java/lang/Throwable:getCause	()Ljava/lang/Throwable;
    //   502: astore 5
    //   504: aload 5
    //   506: ifnull +6 -> 512
    //   509: aload 5
    //   511: athrow
    //   512: aload 4
    //   514: athrow
    //   515: iconst_4
    //   516: sipush 413
    //   519: sipush 30253
    //   522: invokestatic 98	o/O:ˋ	(IIC)Ljava/lang/Object;
    //   525: checkcast 100	java/lang/Class
    //   528: ldc 125
    //   530: aconst_null
    //   531: invokevirtual 105	java/lang/Class:getMethod	(Ljava/lang/String;[Ljava/lang/Class;)Ljava/lang/reflect/Method;
    //   534: aload 4
    //   536: aconst_null
    //   537: invokevirtual 111	java/lang/reflect/Method:invoke	(Ljava/lang/Object;[Ljava/lang/Object;)Ljava/lang/Object;
    //   540: checkcast 127	java/lang/Boolean
    //   543: invokevirtual 131	java/lang/Boolean:booleanValue	()Z
    //   546: istore_3
    //   547: iload_3
    //   548: ifne +6 -> 554
    //   551: goto +1084 -> 1635
    //   554: goto +429 -> 983
    //   557: iload_1
    //   558: lookupswitch	default:+26->584, 49:+503->1061, 61:+436->994
    //   584: goto +477 -> 1061
    //   587: iconst_4
    //   588: sipush 413
    //   591: sipush 30253
    //   594: invokestatic 98	o/O:ˋ	(IIC)Ljava/lang/Object;
    //   597: checkcast 100	java/lang/Class
    //   600: ldc 112
    //   602: invokevirtual 116	java/lang/Class:getField	(Ljava/lang/String;)Ljava/lang/reflect/Field;
    //   605: aconst_null
    //   606: invokevirtual 122	java/lang/reflect/Field:get	(Ljava/lang/Object;)Ljava/lang/Object;
    //   609: astore 4
    //   611: goto +23 -> 634
    //   614: astore 4
    //   616: aload 4
    //   618: invokevirtual 92	java/lang/Throwable:getCause	()Ljava/lang/Throwable;
    //   621: astore 5
    //   623: aload 5
    //   625: ifnull +6 -> 631
    //   628: aload 5
    //   630: athrow
    //   631: aload 4
    //   633: athrow
    //   634: bipush 6
    //   636: sipush 417
    //   639: iconst_0
    //   640: invokestatic 98	o/O:ˋ	(IIC)Ljava/lang/Object;
    //   643: checkcast 100	java/lang/Class
    //   646: ldc 123
    //   648: aconst_null
    //   649: invokevirtual 105	java/lang/Class:getMethod	(Ljava/lang/String;[Ljava/lang/Class;)Ljava/lang/reflect/Method;
    //   652: aload 4
    //   654: aconst_null
    //   655: invokevirtual 111	java/lang/reflect/Method:invoke	(Ljava/lang/Object;[Ljava/lang/Object;)Ljava/lang/Object;
    //   658: astore 4
    //   660: goto +23 -> 683
    //   663: astore 4
    //   665: aload 4
    //   667: invokevirtual 92	java/lang/Throwable:getCause	()Ljava/lang/Throwable;
    //   670: astore 5
    //   672: aload 5
    //   674: ifnull +6 -> 680
    //   677: aload 5
    //   679: athrow
    //   680: aload 4
    //   682: athrow
    //   683: iconst_4
    //   684: sipush 413
    //   687: sipush 30253
    //   690: invokestatic 98	o/O:ˋ	(IIC)Ljava/lang/Object;
    //   693: checkcast 100	java/lang/Class
    //   696: ldc -123
    //   698: aconst_null
    //   699: invokevirtual 105	java/lang/Class:getMethod	(Ljava/lang/String;[Ljava/lang/Class;)Ljava/lang/reflect/Method;
    //   702: aload 4
    //   704: aconst_null
    //   705: invokevirtual 111	java/lang/reflect/Method:invoke	(Ljava/lang/Object;[Ljava/lang/Object;)Ljava/lang/Object;
    //   708: pop
    //   709: iconst_4
    //   710: sipush 402
    //   713: iconst_0
    //   714: invokestatic 98	o/O:ˋ	(IIC)Ljava/lang/Object;
    //   717: checkcast 100	java/lang/Class
    //   720: ldc -122
    //   722: invokevirtual 116	java/lang/Class:getField	(Ljava/lang/String;)Ljava/lang/reflect/Field;
    //   725: aconst_null
    //   726: invokevirtual 122	java/lang/reflect/Field:get	(Ljava/lang/Object;)Ljava/lang/Object;
    //   729: astore 4
    //   731: goto +23 -> 754
    //   734: astore 4
    //   736: aload 4
    //   738: invokevirtual 92	java/lang/Throwable:getCause	()Ljava/lang/Throwable;
    //   741: astore 5
    //   743: aload 5
    //   745: ifnull +6 -> 751
    //   748: aload 5
    //   750: athrow
    //   751: aload 4
    //   753: athrow
    //   754: bipush 7
    //   756: sipush 406
    //   759: ldc -121
    //   761: invokestatic 98	o/O:ˋ	(IIC)Ljava/lang/Object;
    //   764: checkcast 100	java/lang/Class
    //   767: ldc 123
    //   769: aconst_null
    //   770: invokevirtual 105	java/lang/Class:getMethod	(Ljava/lang/String;[Ljava/lang/Class;)Ljava/lang/reflect/Method;
    //   773: aload 4
    //   775: aconst_null
    //   776: invokevirtual 111	java/lang/reflect/Method:invoke	(Ljava/lang/Object;[Ljava/lang/Object;)Ljava/lang/Object;
    //   779: astore 4
    //   781: goto +23 -> 804
    //   784: astore 4
    //   786: aload 4
    //   788: invokevirtual 92	java/lang/Throwable:getCause	()Ljava/lang/Throwable;
    //   791: astore 5
    //   793: aload 5
    //   795: ifnull +6 -> 801
    //   798: aload 5
    //   800: athrow
    //   801: aload 4
    //   803: athrow
    //   804: iconst_4
    //   805: sipush 402
    //   808: iconst_0
    //   809: invokestatic 98	o/O:ˋ	(IIC)Ljava/lang/Object;
    //   812: checkcast 100	java/lang/Class
    //   815: ldc -123
    //   817: aconst_null
    //   818: invokevirtual 105	java/lang/Class:getMethod	(Ljava/lang/String;[Ljava/lang/Class;)Ljava/lang/reflect/Method;
    //   821: aload 4
    //   823: aconst_null
    //   824: invokevirtual 111	java/lang/reflect/Method:invoke	(Ljava/lang/Object;[Ljava/lang/Object;)Ljava/lang/Object;
    //   827: pop
    //   828: iconst_4
    //   829: sipush 413
    //   832: sipush 30253
    //   835: invokestatic 98	o/O:ˋ	(IIC)Ljava/lang/Object;
    //   838: checkcast 100	java/lang/Class
    //   841: ldc 112
    //   843: invokevirtual 116	java/lang/Class:getField	(Ljava/lang/String;)Ljava/lang/reflect/Field;
    //   846: aconst_null
    //   847: invokevirtual 122	java/lang/reflect/Field:get	(Ljava/lang/Object;)Ljava/lang/Object;
    //   850: astore 4
    //   852: goto +23 -> 875
    //   855: astore 4
    //   857: aload 4
    //   859: invokevirtual 92	java/lang/Throwable:getCause	()Ljava/lang/Throwable;
    //   862: astore 5
    //   864: aload 5
    //   866: ifnull +6 -> 872
    //   869: aload 5
    //   871: athrow
    //   872: aload 4
    //   874: athrow
    //   875: bipush 6
    //   877: sipush 417
    //   880: iconst_0
    //   881: invokestatic 98	o/O:ˋ	(IIC)Ljava/lang/Object;
    //   884: checkcast 100	java/lang/Class
    //   887: ldc 123
    //   889: aconst_null
    //   890: invokevirtual 105	java/lang/Class:getMethod	(Ljava/lang/String;[Ljava/lang/Class;)Ljava/lang/reflect/Method;
    //   893: aload 4
    //   895: aconst_null
    //   896: invokevirtual 111	java/lang/reflect/Method:invoke	(Ljava/lang/Object;[Ljava/lang/Object;)Ljava/lang/Object;
    //   899: astore 4
    //   901: goto +23 -> 924
    //   904: astore 4
    //   906: aload 4
    //   908: invokevirtual 92	java/lang/Throwable:getCause	()Ljava/lang/Throwable;
    //   911: astore 5
    //   913: aload 5
    //   915: ifnull +6 -> 921
    //   918: aload 5
    //   920: athrow
    //   921: aload 4
    //   923: athrow
    //   924: iconst_4
    //   925: sipush 413
    //   928: sipush 30253
    //   931: invokestatic 98	o/O:ˋ	(IIC)Ljava/lang/Object;
    //   934: checkcast 100	java/lang/Class
    //   937: ldc -119
    //   939: aconst_null
    //   940: invokevirtual 105	java/lang/Class:getMethod	(Ljava/lang/String;[Ljava/lang/Class;)Ljava/lang/reflect/Method;
    //   943: aload 4
    //   945: aconst_null
    //   946: invokevirtual 111	java/lang/reflect/Method:invoke	(Ljava/lang/Object;[Ljava/lang/Object;)Ljava/lang/Object;
    //   949: pop
    //   950: goto +111 -> 1061
    //   953: iload_1
    //   954: lookupswitch	default:+26->980, 11:+107->1061, 58:+40->994
    //   980: goto +81 -> 1061
    //   983: bipush 49
    //   985: istore_1
    //   986: goto -429 -> 557
    //   989: astore 4
    //   991: aload 4
    //   993: athrow
    //   994: getstatic 21	o/DX:ʻ	I
    //   997: bipush 69
    //   999: iadd
    //   1000: istore_1
    //   1001: iload_1
    //   1002: sipush 128
    //   1005: irem
    //   1006: putstatic 19	o/DX:ˋ	I
    //   1009: iload_1
    //   1010: iconst_2
    //   1011: irem
    //   1012: ifeq +6 -> 1018
    //   1015: goto +617 -> 1632
    //   1018: goto -431 -> 587
    //   1021: astore 4
    //   1023: aload 4
    //   1025: athrow
    //   1026: iconst_1
    //   1027: ireturn
    //   1028: bipush 11
    //   1030: istore_1
    //   1031: goto -78 -> 953
    //   1034: getstatic 21	o/DX:ʻ	I
    //   1037: bipush 73
    //   1039: iadd
    //   1040: istore_1
    //   1041: iload_1
    //   1042: sipush 128
    //   1045: irem
    //   1046: putstatic 19	o/DX:ˋ	I
    //   1049: iload_1
    //   1050: iconst_2
    //   1051: irem
    //   1052: ifeq +6 -> 1058
    //   1055: goto -1052 -> 3
    //   1058: goto +6 -> 1064
    //   1061: goto -35 -> 1026
    //   1064: bipush 11
    //   1066: newarray byte
    //   1068: dup
    //   1069: iconst_0
    //   1070: ldc 62
    //   1072: bastore
    //   1073: dup
    //   1074: iconst_1
    //   1075: ldc 63
    //   1077: bastore
    //   1078: dup
    //   1079: iconst_2
    //   1080: ldc 64
    //   1082: bastore
    //   1083: dup
    //   1084: iconst_3
    //   1085: ldc 65
    //   1087: bastore
    //   1088: dup
    //   1089: iconst_4
    //   1090: ldc 63
    //   1092: bastore
    //   1093: dup
    //   1094: iconst_5
    //   1095: ldc 66
    //   1097: bastore
    //   1098: dup
    //   1099: bipush 6
    //   1101: ldc 63
    //   1103: bastore
    //   1104: dup
    //   1105: bipush 7
    //   1107: ldc 67
    //   1109: bastore
    //   1110: dup
    //   1111: bipush 8
    //   1113: ldc 63
    //   1115: bastore
    //   1116: dup
    //   1117: bipush 9
    //   1119: ldc 66
    //   1121: bastore
    //   1122: dup
    //   1123: bipush 10
    //   1125: ldc 68
    //   1127: bastore
    //   1128: aconst_null
    //   1129: aconst_null
    //   1130: bipush 127
    //   1132: invokestatic 70	o/DX:ˎ	([B[I[CI)Ljava/lang/String;
    //   1135: astore 4
    //   1137: aload 4
    //   1139: invokevirtual 74	java/lang/String:intern	()Ljava/lang/String;
    //   1142: astore 4
    //   1144: bipush 43
    //   1146: newarray byte
    //   1148: dup
    //   1149: iconst_0
    //   1150: ldc 75
    //   1152: bastore
    //   1153: dup
    //   1154: iconst_1
    //   1155: ldc 63
    //   1157: bastore
    //   1158: dup
    //   1159: iconst_2
    //   1160: ldc 64
    //   1162: bastore
    //   1163: dup
    //   1164: iconst_3
    //   1165: ldc 65
    //   1167: bastore
    //   1168: dup
    //   1169: iconst_4
    //   1170: ldc 63
    //   1172: bastore
    //   1173: dup
    //   1174: iconst_5
    //   1175: ldc 66
    //   1177: bastore
    //   1178: dup
    //   1179: bipush 6
    //   1181: ldc 63
    //   1183: bastore
    //   1184: dup
    //   1185: bipush 7
    //   1187: ldc 67
    //   1189: bastore
    //   1190: dup
    //   1191: bipush 8
    //   1193: ldc 63
    //   1195: bastore
    //   1196: dup
    //   1197: bipush 9
    //   1199: ldc 66
    //   1201: bastore
    //   1202: dup
    //   1203: bipush 10
    //   1205: ldc 76
    //   1207: bastore
    //   1208: dup
    //   1209: bipush 11
    //   1211: ldc 77
    //   1213: bastore
    //   1214: dup
    //   1215: bipush 12
    //   1217: ldc 78
    //   1219: bastore
    //   1220: dup
    //   1221: bipush 13
    //   1223: ldc 63
    //   1225: bastore
    //   1226: dup
    //   1227: bipush 14
    //   1229: ldc 66
    //   1231: bastore
    //   1232: dup
    //   1233: bipush 15
    //   1235: ldc 79
    //   1237: bastore
    //   1238: dup
    //   1239: bipush 16
    //   1241: ldc 80
    //   1243: bastore
    //   1244: dup
    //   1245: bipush 17
    //   1247: ldc 62
    //   1249: bastore
    //   1250: dup
    //   1251: bipush 18
    //   1253: ldc 77
    //   1255: bastore
    //   1256: dup
    //   1257: bipush 19
    //   1259: ldc 78
    //   1261: bastore
    //   1262: dup
    //   1263: bipush 20
    //   1265: ldc 63
    //   1267: bastore
    //   1268: dup
    //   1269: bipush 21
    //   1271: ldc 81
    //   1273: bastore
    //   1274: dup
    //   1275: bipush 22
    //   1277: ldc 76
    //   1279: bastore
    //   1280: dup
    //   1281: bipush 23
    //   1283: ldc 82
    //   1285: bastore
    //   1286: dup
    //   1287: bipush 24
    //   1289: ldc 66
    //   1291: bastore
    //   1292: dup
    //   1293: bipush 25
    //   1295: ldc 64
    //   1297: bastore
    //   1298: dup
    //   1299: bipush 26
    //   1301: ldc 65
    //   1303: bastore
    //   1304: dup
    //   1305: bipush 27
    //   1307: ldc 63
    //   1309: bastore
    //   1310: dup
    //   1311: bipush 28
    //   1313: ldc 77
    //   1315: bastore
    //   1316: dup
    //   1317: bipush 29
    //   1319: ldc 65
    //   1321: bastore
    //   1322: dup
    //   1323: bipush 30
    //   1325: ldc 79
    //   1327: bastore
    //   1328: dup
    //   1329: bipush 31
    //   1331: ldc 77
    //   1333: bastore
    //   1334: dup
    //   1335: bipush 32
    //   1337: ldc 83
    //   1339: bastore
    //   1340: dup
    //   1341: bipush 33
    //   1343: ldc 81
    //   1345: bastore
    //   1346: dup
    //   1347: bipush 34
    //   1349: ldc 77
    //   1351: bastore
    //   1352: dup
    //   1353: bipush 35
    //   1355: ldc 84
    //   1357: bastore
    //   1358: dup
    //   1359: bipush 36
    //   1361: ldc 65
    //   1363: bastore
    //   1364: dup
    //   1365: bipush 37
    //   1367: ldc 85
    //   1369: bastore
    //   1370: dup
    //   1371: bipush 38
    //   1373: ldc 84
    //   1375: bastore
    //   1376: dup
    //   1377: bipush 39
    //   1379: ldc 65
    //   1381: bastore
    //   1382: dup
    //   1383: bipush 40
    //   1385: ldc 79
    //   1387: bastore
    //   1388: dup
    //   1389: bipush 41
    //   1391: ldc 80
    //   1393: bastore
    //   1394: dup
    //   1395: bipush 42
    //   1397: ldc 86
    //   1399: bastore
    //   1400: aconst_null
    //   1401: aconst_null
    //   1402: bipush 127
    //   1404: invokestatic 70	o/DX:ˎ	([B[I[CI)Ljava/lang/String;
    //   1407: astore 5
    //   1409: aload 5
    //   1411: invokevirtual 74	java/lang/String:intern	()Ljava/lang/String;
    //   1414: astore 5
    //   1416: goto +23 -> 1439
    //   1419: astore 4
    //   1421: aload 4
    //   1423: invokevirtual 92	java/lang/Throwable:getCause	()Ljava/lang/Throwable;
    //   1426: astore 5
    //   1428: aload 5
    //   1430: ifnull +6 -> 1436
    //   1433: aload 5
    //   1435: athrow
    //   1436: aload 4
    //   1438: athrow
    //   1439: iconst_4
    //   1440: bipush 42
    //   1442: ldc 93
    //   1444: invokestatic 98	o/O:ˋ	(IIC)Ljava/lang/Object;
    //   1447: checkcast 100	java/lang/Class
    //   1450: ldc 101
    //   1452: iconst_2
    //   1453: anewarray 100	java/lang/Class
    //   1456: dup
    //   1457: iconst_0
    //   1458: ldc 55
    //   1460: aastore
    //   1461: dup
    //   1462: iconst_1
    //   1463: ldc 55
    //   1465: aastore
    //   1466: invokevirtual 105	java/lang/Class:getMethod	(Ljava/lang/String;[Ljava/lang/Class;)Ljava/lang/reflect/Method;
    //   1469: aconst_null
    //   1470: iconst_2
    //   1471: anewarray 4	java/lang/Object
    //   1474: dup
    //   1475: iconst_0
    //   1476: aload 4
    //   1478: aastore
    //   1479: dup
    //   1480: iconst_1
    //   1481: aload 5
    //   1483: aastore
    //   1484: invokevirtual 111	java/lang/reflect/Method:invoke	(Ljava/lang/Object;[Ljava/lang/Object;)Ljava/lang/Object;
    //   1487: pop
    //   1488: iconst_4
    //   1489: sipush 413
    //   1492: sipush 30253
    //   1495: invokestatic 98	o/O:ˋ	(IIC)Ljava/lang/Object;
    //   1498: checkcast 100	java/lang/Class
    //   1501: ldc 112
    //   1503: invokevirtual 116	java/lang/Class:getField	(Ljava/lang/String;)Ljava/lang/reflect/Field;
    //   1506: aconst_null
    //   1507: invokevirtual 122	java/lang/reflect/Field:get	(Ljava/lang/Object;)Ljava/lang/Object;
    //   1510: astore 4
    //   1512: goto +23 -> 1535
    //   1515: astore 4
    //   1517: aload 4
    //   1519: invokevirtual 92	java/lang/Throwable:getCause	()Ljava/lang/Throwable;
    //   1522: astore 5
    //   1524: aload 5
    //   1526: ifnull +6 -> 1532
    //   1529: aload 5
    //   1531: athrow
    //   1532: aload 4
    //   1534: athrow
    //   1535: bipush 6
    //   1537: sipush 417
    //   1540: iconst_0
    //   1541: invokestatic 98	o/O:ˋ	(IIC)Ljava/lang/Object;
    //   1544: checkcast 100	java/lang/Class
    //   1547: ldc 123
    //   1549: aconst_null
    //   1550: invokevirtual 105	java/lang/Class:getMethod	(Ljava/lang/String;[Ljava/lang/Class;)Ljava/lang/reflect/Method;
    //   1553: aload 4
    //   1555: aconst_null
    //   1556: invokevirtual 111	java/lang/reflect/Method:invoke	(Ljava/lang/Object;[Ljava/lang/Object;)Ljava/lang/Object;
    //   1559: astore 4
    //   1561: goto +23 -> 1584
    //   1564: astore 4
    //   1566: aload 4
    //   1568: invokevirtual 92	java/lang/Throwable:getCause	()Ljava/lang/Throwable;
    //   1571: astore 5
    //   1573: aload 5
    //   1575: ifnull +6 -> 1581
    //   1578: aload 5
    //   1580: athrow
    //   1581: aload 4
    //   1583: athrow
    //   1584: iconst_4
    //   1585: sipush 413
    //   1588: sipush 30253
    //   1591: invokestatic 98	o/O:ˋ	(IIC)Ljava/lang/Object;
    //   1594: checkcast 100	java/lang/Class
    //   1597: ldc 125
    //   1599: aconst_null
    //   1600: invokevirtual 105	java/lang/Class:getMethod	(Ljava/lang/String;[Ljava/lang/Class;)Ljava/lang/reflect/Method;
    //   1603: aload 4
    //   1605: aconst_null
    //   1606: invokevirtual 111	java/lang/reflect/Method:invoke	(Ljava/lang/Object;[Ljava/lang/Object;)Ljava/lang/Object;
    //   1609: checkcast 127	java/lang/Boolean
    //   1612: invokevirtual 131	java/lang/Boolean:booleanValue	()Z
    //   1615: istore_3
    //   1616: iload_3
    //   1617: ifne +6 -> 1623
    //   1620: goto +6 -> 1626
    //   1623: goto -595 -> 1028
    //   1626: bipush 58
    //   1628: istore_1
    //   1629: goto -676 -> 953
    //   1632: goto -1045 -> 587
    //   1635: bipush 61
    //   1637: istore_1
    //   1638: goto -1081 -> 557
    //   1641: goto -607 -> 1034
    // Exception table:
    //   from	to	target	type
    //   370	419	350	finally
    //   466	492	446	finally
    //   515	547	495	finally
    //   634	660	614	finally
    //   683	709	663	finally
    //   754	781	734	finally
    //   804	828	784	finally
    //   875	901	855	finally
    //   924	950	904	finally
    //   1064	1137	989	java/lang/Exception
    //   1137	1144	989	java/lang/Exception
    //   1144	1409	989	java/lang/Exception
    //   1409	1416	989	java/lang/Exception
    //   1421	1428	989	java/lang/Exception
    //   1433	1436	989	java/lang/Exception
    //   1436	1439	989	java/lang/Exception
    //   1488	1512	989	java/lang/Exception
    //   1517	1524	989	java/lang/Exception
    //   1529	1532	989	java/lang/Exception
    //   1532	1535	989	java/lang/Exception
    //   1566	1573	989	java/lang/Exception
    //   1578	1581	989	java/lang/Exception
    //   1581	1584	989	java/lang/Exception
    //   1439	1488	1419	finally
    //   1535	1561	1515	finally
    //   1584	1616	1564	finally
  }
}
