package o;

import android.databinding.ViewDataBinding;
import android.databinding.ViewDataBinding.If;
import android.util.SparseIntArray;
import android.view.View;
import android.view.View.OnClickListener;
import android.webkit.WebView;
import android.widget.Button;
import android.widget.EditText;
import android.widget.FrameLayout;
import android.widget.LinearLayout;
import android.widget.ProgressBar;
import android.widget.RelativeLayout;
import android.widget.TextView;
import java.io.UnsupportedEncodingException;

public class Dx
  extends ViewDataBinding
  implements ᴵ.If
{
  private static byte ˊˊ;
  private static long ˋˊ;
  private static final ViewDataBinding.If ˋॱ;
  private static int ˌ;
  private static int ˍ;
  private static final SparseIntArray ͺ;
  public final ProgressBar ʻ;
  private final LinearLayout ʻॱ;
  public final ap ʼ;
  private DE ʼॱ;
  public final aA ʽ;
  private boolean ʽॱ;
  private boolean ʾ;
  private String ʿ;
  private boolean ˈ;
  private final View.OnClickListener ˉ;
  public final FrameLayout ˊ;
  private final View.OnClickListener ˊˋ;
  public final WebView ˊॱ;
  private long ˊᐝ = -1L;
  public final Button ˎ;
  private final RelativeLayout ˏॱ;
  public final EditText ॱ;
  public final TextView ॱˊ;
  private final TextView ॱˋ;
  private final TextView ॱˎ;
  public final LinearLayout ॱॱ;
  private final TextView ॱᐝ;
  public final aD ᐝ;
  private DK.iF ᐝॱ;
  
  static
  {
    for (;;)
    {
      int i = ˍ + 27;
      ˌ = i % 128;
      if (i % 2 != 0) {
        break;
      }
      return;
      ˌ = 0;
      ˍ = 1;
      ॱˊ();
      ˏॱ();
      ˋॱ = null;
      ͺ = new SparseIntArray();
      ͺ.put(2131296628, 12);
      ͺ.put(2131296654, 13);
      ͺ.put(2131296273, 14);
    }
  }
  
  public Dx(ˉ paramˉ, View paramView)
  {
    super(paramˉ, paramView, 0);
    paramˉ = ॱ(paramˉ, paramView, 15, ˋॱ, ͺ);
    this.ˎ = ((Button)paramˉ[11]);
    this.ˎ.setTag(null);
    this.ˊ = ((FrameLayout)paramˉ[14]);
    this.ॱ = ((EditText)paramˉ[6]);
    this.ॱ.setTag(null);
    this.ˏॱ = ((RelativeLayout)paramˉ[0]);
    this.ˏॱ.setTag(null);
    this.ॱˋ = ((TextView)paramˉ[2]);
    this.ॱˋ.setTag(null);
    this.ॱˎ = ((TextView)paramˉ[3]);
    this.ॱˎ.setTag(null);
    this.ʻॱ = ((LinearLayout)paramˉ[5]);
    this.ʻॱ.setTag(null);
    this.ॱᐝ = ((TextView)paramˉ[9]);
    this.ॱᐝ.setTag(null);
    this.ॱॱ = ((LinearLayout)paramˉ[8]);
    this.ॱॱ.setTag(null);
    this.ᐝ = ((aD)paramˉ[12]);
    this.ʽ = ((aA)paramˉ[1]);
    this.ʽ.setTag(null);
    this.ʼ = ((ap)paramˉ[7]);
    this.ʼ.setTag(null);
    this.ʻ = ((ProgressBar)paramˉ[13]);
    this.ॱˊ = ((TextView)paramˉ[4]);
    this.ॱˊ.setTag(null);
    this.ˊॱ = ((WebView)paramˉ[10]);
    this.ˊॱ.setTag(null);
    ˋ(paramView);
    this.ˉ = new ᴵ(this, 2);
    this.ˊˋ = new ᴵ(this, 1);
    ͺ();
  }
  
  private static String ˋ(char[] paramArrayOfChar)
  {
    break label237;
    break label224;
    return new String(paramArrayOfChar, 4, paramArrayOfChar.length - 4);
    label25:
    int i;
    for (;;)
    {
      j = 1;
      break label100;
      paramArrayOfChar[i] = ((char)(int)(paramArrayOfChar[i] ^ paramArrayOfChar[(i % 4)] ^ (i - 4) * ˋˊ));
      i += 1;
      break label221;
      if (i < paramArrayOfChar.length) {
        break;
      }
    }
    int j = 0;
    for (;;)
    {
      j = ˌ + 41;
      ˍ = j % 128;
      if (j % 2 == 0) {
        break;
      }
      break label184;
      label100:
      switch (j)
      {
      }
    }
    label184:
    label221:
    label224:
    label237:
    for (;;)
    {
      i = ˌ + 113;
      ˍ = i % 128;
      if (i % 2 == 0) {
        break;
      }
      break;
      for (;;)
      {
        switch (j)
        {
        case 1: 
        default: 
          break label25;
          j = 0;
          continue;
          j = 1;
        }
      }
      for (;;)
      {
        break;
        paramArrayOfChar[i] = ((char)(int)(paramArrayOfChar[i] | paramArrayOfChar[(i >>> 3)] | i << 2 ^ ˋˊ));
        i += 15;
        break;
        paramArrayOfChar = oL.ˋ(ˋˊ, paramArrayOfChar);
        i = 4;
      }
    }
  }
  
  /* Error */
  static void ˏॱ()
  {
    // Byte code:
    //   0: goto +48 -> 48
    //   3: return
    //   4: goto +104 -> 108
    //   7: aconst_null
    //   8: arraylength
    //   9: istore_0
    //   10: return
    //   11: iconst_1
    //   12: istore_0
    //   13: goto +38 -> 51
    //   16: astore_1
    //   17: aload_1
    //   18: athrow
    //   19: getstatic 61	o/Dx:ˍ	I
    //   22: istore_0
    //   23: iload_0
    //   24: bipush 91
    //   26: iadd
    //   27: istore_0
    //   28: iload_0
    //   29: sipush 128
    //   32: irem
    //   33: putstatic 63	o/Dx:ˌ	I
    //   36: iload_0
    //   37: iconst_2
    //   38: irem
    //   39: ifeq +6 -> 45
    //   42: goto -38 -> 4
    //   45: goto +63 -> 108
    //   48: goto -29 -> 19
    //   51: iload_0
    //   52: tableswitch	default:+24->76, 0:+-45->7, 1:+-49->3
    //   76: return
    //   77: getstatic 61	o/Dx:ˍ	I
    //   80: iconst_3
    //   81: iadd
    //   82: istore_0
    //   83: iload_0
    //   84: sipush 128
    //   87: irem
    //   88: putstatic 63	o/Dx:ˌ	I
    //   91: iload_0
    //   92: iconst_2
    //   93: irem
    //   94: ifeq +6 -> 100
    //   97: goto +6 -> 103
    //   100: goto -89 -> 11
    //   103: iconst_0
    //   104: istore_0
    //   105: goto -54 -> 51
    //   108: bipush -102
    //   110: putstatic 190	o/Dx:ˊˊ	B
    //   113: goto -36 -> 77
    //   116: astore_1
    //   117: aload_1
    //   118: athrow
    // Local variable table:
    //   start	length	slot	name	signature
    //   9	96	0	i	int
    //   16	2	1	localException1	Exception
    //   116	2	1	localException2	Exception
    // Exception table:
    //   from	to	target	type
    //   28	36	16	java/lang/Exception
    //   108	113	16	java/lang/Exception
    //   19	23	116	java/lang/Exception
  }
  
  private String ॱ(String paramString)
  {
    for (;;)
    {
      break label14;
      break label95;
      int j = 0;
      break label67;
      label14:
      int i;
      for (;;)
      {
        try
        {
          j = paramString.length;
          if (i < j) {
            break;
          }
        }
        catch (UnsupportedEncodingException paramString)
        {
          throw new RuntimeException(paramString);
        }
        switch (i)
        {
        case 0: 
        default: 
          label38:
          i = j;
        }
      }
      j = 1;
      label67:
      label95:
      byte[] arrayOfByte;
      switch (j)
      {
      default: 
        break;
        paramString = paramString.getBytes(ˋ(new char[] { 18628, 18573, 6702, -19272, -29767, -25426, -10628, -28468, -3096, 29647, -12585, 22422, 16065, 16114 }).intern());
        arrayOfByte = new byte[paramString.length];
        i = 0;
        break;
      }
      label330:
      do
      {
        break;
        do
        {
          i = 0;
          break label38;
          i = j;
          break;
          arrayOfByte[i] = ((byte)(paramString[(paramString.length - i - 1)] ^ ˊˊ));
          j = i + 1;
          i = ˌ + 81;
          ˍ = i % 128;
        } while (i % 2 == 0);
        break label330;
        paramString = new String(arrayOfByte, ˋ(new char[] { 15531, 15614, -11482, 32183, -21507, -30585, -2511, -31515, -30841 }).intern());
        return paramString;
        i = 1;
        break label38;
        j = ˍ + 63;
        ˌ = j % 128;
      } while (j % 2 != 0);
    }
  }
  
  static void ॱˊ()
  {
    ˋˊ = 2180287860487859909L;
  }
  
  public void ˊ(String paramString)
  {
    this.ʿ = paramString;
    try
    {
      this.ˊᐝ |= 0x10;
    }
    finally
    {
      paramString = finally;
      throw paramString;
    }
    ˊ(32);
    super.ʽ();
  }
  
  public void ˋ(boolean paramBoolean)
  {
    this.ˈ = paramBoolean;
    try
    {
      this.ˊᐝ |= 0x2;
    }
    finally
    {
      localObject = finally;
      throw localObject;
    }
    ˊ(70);
    super.ʽ();
  }
  
  public void ˎ(DE paramDE)
  {
    this.ʼॱ = paramDE;
    try
    {
      this.ˊᐝ |= 0x40;
    }
    finally
    {
      paramDE = finally;
      throw paramDE;
    }
    ˊ(124);
    super.ʽ();
  }
  
  public void ˎ(DK.iF paramIF)
  {
    this.ᐝॱ = paramIF;
    try
    {
      this.ˊᐝ |= 1L;
    }
    finally
    {
      paramIF = finally;
      throw paramIF;
    }
    ˊ(110);
    super.ʽ();
  }
  
  /* Error */
  public void ˏ()
  {
    // Byte code:
    //   0: bipush 8
    //   2: newarray char
    //   4: dup
    //   5: iconst_0
    //   6: ldc_w 261
    //   9: castore
    //   10: dup
    //   11: iconst_1
    //   12: ldc_w 262
    //   15: castore
    //   16: dup
    //   17: iconst_2
    //   18: ldc_w 263
    //   21: castore
    //   22: dup
    //   23: iconst_3
    //   24: ldc_w 264
    //   27: castore
    //   28: dup
    //   29: iconst_4
    //   30: ldc_w 265
    //   33: castore
    //   34: dup
    //   35: iconst_5
    //   36: ldc_w 266
    //   39: castore
    //   40: dup
    //   41: bipush 6
    //   43: ldc_w 267
    //   46: castore
    //   47: dup
    //   48: bipush 7
    //   50: ldc_w 268
    //   53: castore
    //   54: invokestatic 214	o/Dx:ˋ	([C)Ljava/lang/String;
    //   57: invokevirtual 218	java/lang/String:intern	()Ljava/lang/String;
    //   60: astore 15
    //   62: aload_0
    //   63: monitorenter
    //   64: aload_0
    //   65: getfield 92	o/Dx:ˊᐝ	J
    //   68: lstore 6
    //   70: aload_0
    //   71: lconst_0
    //   72: putfield 92	o/Dx:ˊᐝ	J
    //   75: aload_0
    //   76: monitorexit
    //   77: goto +10 -> 87
    //   80: astore 12
    //   82: aload_0
    //   83: monitorexit
    //   84: aload 12
    //   86: athrow
    //   87: iconst_0
    //   88: istore 8
    //   90: aload_0
    //   91: getfield 259	o/Dx:ᐝॱ	Lo/DK$iF;
    //   94: astore 12
    //   96: aload_0
    //   97: getfield 249	o/Dx:ˈ	Z
    //   100: istore 11
    //   102: aload_0
    //   103: getfield 270	o/Dx:ʽॱ	Z
    //   106: istore 10
    //   108: aload_0
    //   109: getfield 239	o/Dx:ʿ	Ljava/lang/String;
    //   112: astore 16
    //   114: aload_0
    //   115: getfield 272	o/Dx:ʾ	Z
    //   118: istore 9
    //   120: iconst_0
    //   121: istore_2
    //   122: iconst_0
    //   123: istore_1
    //   124: iconst_0
    //   125: istore_3
    //   126: aload_0
    //   127: getfield 254	o/Dx:ʼॱ	Lo/DE;
    //   130: astore 14
    //   132: aconst_null
    //   133: astore 13
    //   135: lload 6
    //   137: lstore 4
    //   139: ldc2_w 273
    //   142: lload 6
    //   144: land
    //   145: lconst_0
    //   146: lcmp
    //   147: ifeq +55 -> 202
    //   150: lload 6
    //   152: lstore 4
    //   154: ldc2_w 273
    //   157: lload 6
    //   159: land
    //   160: lconst_0
    //   161: lcmp
    //   162: ifeq +27 -> 189
    //   165: iload 11
    //   167: ifeq +14 -> 181
    //   170: lload 6
    //   172: ldc2_w 275
    //   175: lor
    //   176: lstore 4
    //   178: goto +11 -> 189
    //   181: lload 6
    //   183: ldc2_w 277
    //   186: lor
    //   187: lstore 4
    //   189: iload 11
    //   191: ifeq +8 -> 199
    //   194: iconst_0
    //   195: istore_1
    //   196: goto +6 -> 202
    //   199: bipush 8
    //   201: istore_1
    //   202: lload 4
    //   204: lstore 6
    //   206: ldc2_w 279
    //   209: lload 4
    //   211: land
    //   212: lconst_0
    //   213: lcmp
    //   214: ifeq +56 -> 270
    //   217: lload 4
    //   219: lstore 6
    //   221: ldc2_w 279
    //   224: lload 4
    //   226: land
    //   227: lconst_0
    //   228: lcmp
    //   229: ifeq +27 -> 256
    //   232: iload 10
    //   234: ifeq +14 -> 248
    //   237: lload 4
    //   239: ldc2_w 281
    //   242: lor
    //   243: lstore 6
    //   245: goto +11 -> 256
    //   248: lload 4
    //   250: ldc2_w 283
    //   253: lor
    //   254: lstore 6
    //   256: iload 10
    //   258: ifeq +9 -> 267
    //   261: iconst_1
    //   262: istore 8
    //   264: goto +6 -> 270
    //   267: iconst_0
    //   268: istore 8
    //   270: lload 6
    //   272: lstore 4
    //   274: ldc2_w 285
    //   277: lload 6
    //   279: land
    //   280: lconst_0
    //   281: lcmp
    //   282: ifeq +76 -> 358
    //   285: lload 6
    //   287: lstore 4
    //   289: ldc2_w 285
    //   292: lload 6
    //   294: land
    //   295: lconst_0
    //   296: lcmp
    //   297: ifeq +35 -> 332
    //   300: iload 9
    //   302: ifeq +18 -> 320
    //   305: lload 6
    //   307: ldc2_w 287
    //   310: lor
    //   311: ldc2_w 289
    //   314: lor
    //   315: lstore 4
    //   317: goto +15 -> 332
    //   320: lload 6
    //   322: ldc2_w 291
    //   325: lor
    //   326: ldc2_w 293
    //   329: lor
    //   330: lstore 4
    //   332: iload 9
    //   334: ifeq +8 -> 342
    //   337: iconst_0
    //   338: istore_2
    //   339: goto +6 -> 345
    //   342: bipush 8
    //   344: istore_2
    //   345: iload 9
    //   347: ifeq +9 -> 356
    //   350: bipush 8
    //   352: istore_3
    //   353: goto +5 -> 358
    //   356: iconst_0
    //   357: istore_3
    //   358: lload 4
    //   360: lstore 6
    //   362: ldc2_w 295
    //   365: lload 4
    //   367: land
    //   368: lconst_0
    //   369: lcmp
    //   370: ifeq +173 -> 543
    //   373: lload 4
    //   375: lstore 6
    //   377: ldc2_w 295
    //   380: lload 4
    //   382: land
    //   383: lconst_0
    //   384: lcmp
    //   385: ifeq +158 -> 543
    //   388: goto +23 -> 411
    //   391: astore 12
    //   393: aload 12
    //   395: invokevirtual 302	java/lang/Throwable:getCause	()Ljava/lang/Throwable;
    //   398: astore 13
    //   400: aload 13
    //   402: ifnull +6 -> 408
    //   405: aload 13
    //   407: athrow
    //   408: aload 12
    //   410: athrow
    //   411: iconst_3
    //   412: iconst_0
    //   413: ldc_w 303
    //   416: invokestatic 308	o/O:ˋ	(IIC)Ljava/lang/Object;
    //   419: checkcast 310	java/lang/Class
    //   422: ldc_w 311
    //   425: aconst_null
    //   426: invokevirtual 315	java/lang/Class:getMethod	(Ljava/lang/String;[Ljava/lang/Class;)Ljava/lang/reflect/Method;
    //   429: aconst_null
    //   430: aconst_null
    //   431: invokevirtual 321	java/lang/reflect/Method:invoke	(Ljava/lang/Object;[Ljava/lang/Object;)Ljava/lang/Object;
    //   434: astore 12
    //   436: goto +23 -> 459
    //   439: astore 12
    //   441: aload 12
    //   443: invokevirtual 302	java/lang/Throwable:getCause	()Ljava/lang/Throwable;
    //   446: astore 13
    //   448: aload 13
    //   450: ifnull +6 -> 456
    //   453: aload 13
    //   455: athrow
    //   456: aload 12
    //   458: athrow
    //   459: iconst_3
    //   460: iconst_0
    //   461: ldc_w 303
    //   464: invokestatic 308	o/O:ˋ	(IIC)Ljava/lang/Object;
    //   467: checkcast 310	java/lang/Class
    //   470: ldc_w 322
    //   473: iconst_1
    //   474: anewarray 310	java/lang/Class
    //   477: dup
    //   478: iconst_0
    //   479: getstatic 328	java/lang/Integer:TYPE	Ljava/lang/Class;
    //   482: aastore
    //   483: invokevirtual 315	java/lang/Class:getMethod	(Ljava/lang/String;[Ljava/lang/Class;)Ljava/lang/reflect/Method;
    //   486: aload 12
    //   488: iconst_1
    //   489: anewarray 330	java/lang/Object
    //   492: dup
    //   493: iconst_0
    //   494: bipush 21
    //   496: invokestatic 334	java/lang/Integer:valueOf	(I)Ljava/lang/Integer;
    //   499: aastore
    //   500: invokevirtual 321	java/lang/reflect/Method:invoke	(Ljava/lang/Object;[Ljava/lang/Object;)Ljava/lang/Object;
    //   503: checkcast 336	java/lang/Boolean
    //   506: invokevirtual 340	java/lang/Boolean:booleanValue	()Z
    //   509: istore 9
    //   511: iload 9
    //   513: ifeq +18 -> 531
    //   516: lload 4
    //   518: ldc2_w 341
    //   521: lor
    //   522: ldc2_w 343
    //   525: lor
    //   526: lstore 6
    //   528: goto +15 -> 543
    //   531: lload 4
    //   533: ldc2_w 345
    //   536: lor
    //   537: ldc2_w 347
    //   540: lor
    //   541: lstore 6
    //   543: aload 13
    //   545: astore 12
    //   547: ldc2_w 349
    //   550: lload 6
    //   552: land
    //   553: lconst_0
    //   554: lcmp
    //   555: ifeq +19 -> 574
    //   558: aload 13
    //   560: astore 12
    //   562: aload 14
    //   564: ifnull +10 -> 574
    //   567: aload 14
    //   569: invokevirtual 354	o/DE:ˊ	()Ljava/lang/String;
    //   572: astore 12
    //   574: ldc2_w 279
    //   577: lload 6
    //   579: land
    //   580: lconst_0
    //   581: lcmp
    //   582: ifeq +12 -> 594
    //   585: aload_0
    //   586: getfield 99	o/Dx:ˎ	Landroid/widget/Button;
    //   589: iload 8
    //   591: invokevirtual 357	android/widget/Button:setEnabled	(Z)V
    //   594: ldc2_w 295
    //   597: lload 6
    //   599: land
    //   600: lconst_0
    //   601: lcmp
    //   602: ifeq +737 -> 1339
    //   605: aload_0
    //   606: getfield 99	o/Dx:ˎ	Landroid/widget/Button;
    //   609: aload_0
    //   610: getfield 169	o/Dx:ˉ	Landroid/view/View$OnClickListener;
    //   613: invokevirtual 361	android/widget/Button:setOnClickListener	(Landroid/view/View$OnClickListener;)V
    //   616: aload_0
    //   617: getfield 99	o/Dx:ˎ	Landroid/widget/Button;
    //   620: astore 17
    //   622: aload_0
    //   623: getfield 99	o/Dx:ˎ	Landroid/widget/Button;
    //   626: invokevirtual 365	android/widget/Button:getResources	()Landroid/content/res/Resources;
    //   629: ldc_w 366
    //   632: invokevirtual 372	android/content/res/Resources:getString	(I)Ljava/lang/String;
    //   635: astore 14
    //   637: aload 14
    //   639: astore 13
    //   641: aload 14
    //   643: aload 15
    //   645: invokevirtual 376	java/lang/String:startsWith	(Ljava/lang/String;)Z
    //   648: ifeq +18 -> 666
    //   651: aload_0
    //   652: aload 14
    //   654: iconst_4
    //   655: invokevirtual 379	java/lang/String:substring	(I)Ljava/lang/String;
    //   658: invokespecial 381	o/Dx:ॱ	(Ljava/lang/String;)Ljava/lang/String;
    //   661: invokevirtual 218	java/lang/String:intern	()Ljava/lang/String;
    //   664: astore 13
    //   666: aload 17
    //   668: aload 13
    //   670: invokestatic 386	o/ʹ:ˊ	(Landroid/widget/TextView;Ljava/lang/CharSequence;)V
    //   673: aload_0
    //   674: getfield 111	o/Dx:ॱ	Landroid/widget/EditText;
    //   677: astore 17
    //   679: aload_0
    //   680: getfield 111	o/Dx:ॱ	Landroid/widget/EditText;
    //   683: invokevirtual 387	android/widget/EditText:getResources	()Landroid/content/res/Resources;
    //   686: ldc_w 388
    //   689: invokevirtual 372	android/content/res/Resources:getString	(I)Ljava/lang/String;
    //   692: astore 14
    //   694: aload 14
    //   696: astore 13
    //   698: aload 14
    //   700: aload 15
    //   702: invokevirtual 376	java/lang/String:startsWith	(Ljava/lang/String;)Z
    //   705: ifeq +18 -> 723
    //   708: aload_0
    //   709: aload 14
    //   711: iconst_4
    //   712: invokevirtual 379	java/lang/String:substring	(I)Ljava/lang/String;
    //   715: invokespecial 381	o/Dx:ॱ	(Ljava/lang/String;)Ljava/lang/String;
    //   718: invokevirtual 218	java/lang/String:intern	()Ljava/lang/String;
    //   721: astore 13
    //   723: aload 17
    //   725: aload 13
    //   727: invokevirtual 392	android/widget/EditText:setHint	(Ljava/lang/CharSequence;)V
    //   730: aload_0
    //   731: getfield 121	o/Dx:ॱˋ	Landroid/widget/TextView;
    //   734: astore 17
    //   736: aload_0
    //   737: getfield 121	o/Dx:ॱˋ	Landroid/widget/TextView;
    //   740: invokevirtual 393	android/widget/TextView:getResources	()Landroid/content/res/Resources;
    //   743: ldc_w 394
    //   746: invokevirtual 372	android/content/res/Resources:getString	(I)Ljava/lang/String;
    //   749: astore 14
    //   751: aload 14
    //   753: astore 13
    //   755: aload 14
    //   757: aload 15
    //   759: invokevirtual 376	java/lang/String:startsWith	(Ljava/lang/String;)Z
    //   762: ifeq +18 -> 780
    //   765: aload_0
    //   766: aload 14
    //   768: iconst_4
    //   769: invokevirtual 379	java/lang/String:substring	(I)Ljava/lang/String;
    //   772: invokespecial 381	o/Dx:ॱ	(Ljava/lang/String;)Ljava/lang/String;
    //   775: invokevirtual 218	java/lang/String:intern	()Ljava/lang/String;
    //   778: astore 13
    //   780: aload 17
    //   782: aload 13
    //   784: invokestatic 386	o/ʹ:ˊ	(Landroid/widget/TextView;Ljava/lang/CharSequence;)V
    //   787: aload_0
    //   788: getfield 124	o/Dx:ॱˎ	Landroid/widget/TextView;
    //   791: astore 17
    //   793: aload_0
    //   794: getfield 124	o/Dx:ॱˎ	Landroid/widget/TextView;
    //   797: invokevirtual 393	android/widget/TextView:getResources	()Landroid/content/res/Resources;
    //   800: ldc_w 395
    //   803: invokevirtual 372	android/content/res/Resources:getString	(I)Ljava/lang/String;
    //   806: astore 14
    //   808: aload 14
    //   810: astore 13
    //   812: aload 14
    //   814: aload 15
    //   816: invokevirtual 376	java/lang/String:startsWith	(Ljava/lang/String;)Z
    //   819: ifeq +18 -> 837
    //   822: aload_0
    //   823: aload 14
    //   825: iconst_4
    //   826: invokevirtual 379	java/lang/String:substring	(I)Ljava/lang/String;
    //   829: invokespecial 381	o/Dx:ॱ	(Ljava/lang/String;)Ljava/lang/String;
    //   832: invokevirtual 218	java/lang/String:intern	()Ljava/lang/String;
    //   835: astore 13
    //   837: aload 17
    //   839: aload 13
    //   841: invokestatic 386	o/ʹ:ˊ	(Landroid/widget/TextView;Ljava/lang/CharSequence;)V
    //   844: aload_0
    //   845: getfield 131	o/Dx:ॱᐝ	Landroid/widget/TextView;
    //   848: astore 17
    //   850: aload_0
    //   851: getfield 131	o/Dx:ॱᐝ	Landroid/widget/TextView;
    //   854: invokevirtual 393	android/widget/TextView:getResources	()Landroid/content/res/Resources;
    //   857: ldc_w 396
    //   860: invokevirtual 372	android/content/res/Resources:getString	(I)Ljava/lang/String;
    //   863: astore 14
    //   865: aload 14
    //   867: astore 13
    //   869: aload 14
    //   871: aload 15
    //   873: invokevirtual 376	java/lang/String:startsWith	(Ljava/lang/String;)Z
    //   876: ifeq +18 -> 894
    //   879: aload_0
    //   880: aload 14
    //   882: iconst_4
    //   883: invokevirtual 379	java/lang/String:substring	(I)Ljava/lang/String;
    //   886: invokespecial 381	o/Dx:ॱ	(Ljava/lang/String;)Ljava/lang/String;
    //   889: invokevirtual 218	java/lang/String:intern	()Ljava/lang/String;
    //   892: astore 13
    //   894: aload 17
    //   896: aload 13
    //   898: invokestatic 386	o/ʹ:ˊ	(Landroid/widget/TextView;Ljava/lang/CharSequence;)V
    //   901: aload_0
    //   902: getfield 141	o/Dx:ʽ	Lo/aA;
    //   905: aload_0
    //   906: getfield 141	o/Dx:ʽ	Lo/aA;
    //   909: ldc_w 397
    //   912: invokestatic 400	o/Dx:ॱ	(Landroid/view/View;I)Landroid/graphics/drawable/Drawable;
    //   915: invokevirtual 404	o/aA:setShadowBottom	(Landroid/graphics/drawable/Drawable;)V
    //   918: aload_0
    //   919: getfield 141	o/Dx:ʽ	Lo/aA;
    //   922: aload_0
    //   923: getfield 141	o/Dx:ʽ	Lo/aA;
    //   926: ldc_w 405
    //   929: invokestatic 400	o/Dx:ॱ	(Landroid/view/View;I)Landroid/graphics/drawable/Drawable;
    //   932: invokevirtual 408	o/aA:setShadowTop	(Landroid/graphics/drawable/Drawable;)V
    //   935: aload_0
    //   936: getfield 146	o/Dx:ʼ	Lo/ap;
    //   939: astore 14
    //   941: goto +23 -> 964
    //   944: astore 12
    //   946: aload 12
    //   948: invokevirtual 302	java/lang/Throwable:getCause	()Ljava/lang/Throwable;
    //   951: astore 13
    //   953: aload 13
    //   955: ifnull +6 -> 961
    //   958: aload 13
    //   960: athrow
    //   961: aload 12
    //   963: athrow
    //   964: iconst_3
    //   965: iconst_0
    //   966: ldc_w 303
    //   969: invokestatic 308	o/O:ˋ	(IIC)Ljava/lang/Object;
    //   972: checkcast 310	java/lang/Class
    //   975: ldc_w 311
    //   978: aconst_null
    //   979: invokevirtual 315	java/lang/Class:getMethod	(Ljava/lang/String;[Ljava/lang/Class;)Ljava/lang/reflect/Method;
    //   982: aconst_null
    //   983: aconst_null
    //   984: invokevirtual 321	java/lang/reflect/Method:invoke	(Ljava/lang/Object;[Ljava/lang/Object;)Ljava/lang/Object;
    //   987: astore 13
    //   989: goto +23 -> 1012
    //   992: astore 12
    //   994: aload 12
    //   996: invokevirtual 302	java/lang/Throwable:getCause	()Ljava/lang/Throwable;
    //   999: astore 13
    //   1001: aload 13
    //   1003: ifnull +6 -> 1009
    //   1006: aload 13
    //   1008: athrow
    //   1009: aload 12
    //   1011: athrow
    //   1012: iconst_3
    //   1013: iconst_0
    //   1014: ldc_w 303
    //   1017: invokestatic 308	o/O:ˋ	(IIC)Ljava/lang/Object;
    //   1020: checkcast 310	java/lang/Class
    //   1023: ldc_w 322
    //   1026: iconst_1
    //   1027: anewarray 310	java/lang/Class
    //   1030: dup
    //   1031: iconst_0
    //   1032: getstatic 328	java/lang/Integer:TYPE	Ljava/lang/Class;
    //   1035: aastore
    //   1036: invokevirtual 315	java/lang/Class:getMethod	(Ljava/lang/String;[Ljava/lang/Class;)Ljava/lang/reflect/Method;
    //   1039: aload 13
    //   1041: iconst_1
    //   1042: anewarray 330	java/lang/Object
    //   1045: dup
    //   1046: iconst_0
    //   1047: bipush 21
    //   1049: invokestatic 334	java/lang/Integer:valueOf	(I)Ljava/lang/Integer;
    //   1052: aastore
    //   1053: invokevirtual 321	java/lang/reflect/Method:invoke	(Ljava/lang/Object;[Ljava/lang/Object;)Ljava/lang/Object;
    //   1056: checkcast 336	java/lang/Boolean
    //   1059: invokevirtual 340	java/lang/Boolean:booleanValue	()Z
    //   1062: istore 8
    //   1064: iload 8
    //   1066: ifeq +18 -> 1084
    //   1069: aload_0
    //   1070: getfield 146	o/Dx:ʼ	Lo/ap;
    //   1073: ldc_w 409
    //   1076: invokestatic 400	o/Dx:ॱ	(Landroid/view/View;I)Landroid/graphics/drawable/Drawable;
    //   1079: astore 13
    //   1081: goto +15 -> 1096
    //   1084: aload_0
    //   1085: getfield 146	o/Dx:ʼ	Lo/ap;
    //   1088: ldc_w 410
    //   1091: invokestatic 400	o/Dx:ॱ	(Landroid/view/View;I)Landroid/graphics/drawable/Drawable;
    //   1094: astore 13
    //   1096: aload 14
    //   1098: aload 13
    //   1100: invokevirtual 413	o/ap:setSrcEnd	(Landroid/graphics/drawable/Drawable;)V
    //   1103: aload_0
    //   1104: getfield 146	o/Dx:ʼ	Lo/ap;
    //   1107: astore 14
    //   1109: goto +23 -> 1132
    //   1112: astore 12
    //   1114: aload 12
    //   1116: invokevirtual 302	java/lang/Throwable:getCause	()Ljava/lang/Throwable;
    //   1119: astore 13
    //   1121: aload 13
    //   1123: ifnull +6 -> 1129
    //   1126: aload 13
    //   1128: athrow
    //   1129: aload 12
    //   1131: athrow
    //   1132: iconst_3
    //   1133: iconst_0
    //   1134: ldc_w 303
    //   1137: invokestatic 308	o/O:ˋ	(IIC)Ljava/lang/Object;
    //   1140: checkcast 310	java/lang/Class
    //   1143: ldc_w 311
    //   1146: aconst_null
    //   1147: invokevirtual 315	java/lang/Class:getMethod	(Ljava/lang/String;[Ljava/lang/Class;)Ljava/lang/reflect/Method;
    //   1150: aconst_null
    //   1151: aconst_null
    //   1152: invokevirtual 321	java/lang/reflect/Method:invoke	(Ljava/lang/Object;[Ljava/lang/Object;)Ljava/lang/Object;
    //   1155: astore 13
    //   1157: goto +23 -> 1180
    //   1160: astore 12
    //   1162: aload 12
    //   1164: invokevirtual 302	java/lang/Throwable:getCause	()Ljava/lang/Throwable;
    //   1167: astore 13
    //   1169: aload 13
    //   1171: ifnull +6 -> 1177
    //   1174: aload 13
    //   1176: athrow
    //   1177: aload 12
    //   1179: athrow
    //   1180: iconst_3
    //   1181: iconst_0
    //   1182: ldc_w 303
    //   1185: invokestatic 308	o/O:ˋ	(IIC)Ljava/lang/Object;
    //   1188: checkcast 310	java/lang/Class
    //   1191: ldc_w 322
    //   1194: iconst_1
    //   1195: anewarray 310	java/lang/Class
    //   1198: dup
    //   1199: iconst_0
    //   1200: getstatic 328	java/lang/Integer:TYPE	Ljava/lang/Class;
    //   1203: aastore
    //   1204: invokevirtual 315	java/lang/Class:getMethod	(Ljava/lang/String;[Ljava/lang/Class;)Ljava/lang/reflect/Method;
    //   1207: aload 13
    //   1209: iconst_1
    //   1210: anewarray 330	java/lang/Object
    //   1213: dup
    //   1214: iconst_0
    //   1215: bipush 21
    //   1217: invokestatic 334	java/lang/Integer:valueOf	(I)Ljava/lang/Integer;
    //   1220: aastore
    //   1221: invokevirtual 321	java/lang/reflect/Method:invoke	(Ljava/lang/Object;[Ljava/lang/Object;)Ljava/lang/Object;
    //   1224: checkcast 336	java/lang/Boolean
    //   1227: invokevirtual 340	java/lang/Boolean:booleanValue	()Z
    //   1230: istore 8
    //   1232: iload 8
    //   1234: ifeq +18 -> 1252
    //   1237: aload_0
    //   1238: getfield 146	o/Dx:ʼ	Lo/ap;
    //   1241: ldc_w 414
    //   1244: invokestatic 400	o/Dx:ॱ	(Landroid/view/View;I)Landroid/graphics/drawable/Drawable;
    //   1247: astore 13
    //   1249: goto +15 -> 1264
    //   1252: aload_0
    //   1253: getfield 146	o/Dx:ʼ	Lo/ap;
    //   1256: ldc_w 415
    //   1259: invokestatic 400	o/Dx:ॱ	(Landroid/view/View;I)Landroid/graphics/drawable/Drawable;
    //   1262: astore 13
    //   1264: aload 14
    //   1266: aload 13
    //   1268: invokevirtual 418	o/ap:setSrcStart	(Landroid/graphics/drawable/Drawable;)V
    //   1271: aload_0
    //   1272: getfield 153	o/Dx:ॱˊ	Landroid/widget/TextView;
    //   1275: aload_0
    //   1276: getfield 171	o/Dx:ˊˋ	Landroid/view/View$OnClickListener;
    //   1279: invokevirtual 419	android/widget/TextView:setOnClickListener	(Landroid/view/View$OnClickListener;)V
    //   1282: aload_0
    //   1283: getfield 153	o/Dx:ॱˊ	Landroid/widget/TextView;
    //   1286: astore 17
    //   1288: aload_0
    //   1289: getfield 153	o/Dx:ॱˊ	Landroid/widget/TextView;
    //   1292: invokevirtual 393	android/widget/TextView:getResources	()Landroid/content/res/Resources;
    //   1295: ldc_w 420
    //   1298: invokevirtual 372	android/content/res/Resources:getString	(I)Ljava/lang/String;
    //   1301: astore 14
    //   1303: aload 14
    //   1305: astore 13
    //   1307: aload 14
    //   1309: aload 15
    //   1311: invokevirtual 376	java/lang/String:startsWith	(Ljava/lang/String;)Z
    //   1314: ifeq +18 -> 1332
    //   1317: aload_0
    //   1318: aload 14
    //   1320: iconst_4
    //   1321: invokevirtual 379	java/lang/String:substring	(I)Ljava/lang/String;
    //   1324: invokespecial 381	o/Dx:ॱ	(Ljava/lang/String;)Ljava/lang/String;
    //   1327: invokevirtual 218	java/lang/String:intern	()Ljava/lang/String;
    //   1330: astore 13
    //   1332: aload 17
    //   1334: aload 13
    //   1336: invokestatic 386	o/ʹ:ˊ	(Landroid/widget/TextView;Ljava/lang/CharSequence;)V
    //   1339: ldc2_w 421
    //   1342: lload 6
    //   1344: land
    //   1345: lconst_0
    //   1346: lcmp
    //   1347: ifeq +12 -> 1359
    //   1350: aload_0
    //   1351: getfield 111	o/Dx:ॱ	Landroid/widget/EditText;
    //   1354: aload 16
    //   1356: invokestatic 386	o/ʹ:ˊ	(Landroid/widget/TextView;Ljava/lang/CharSequence;)V
    //   1359: ldc2_w 285
    //   1362: lload 6
    //   1364: land
    //   1365: lconst_0
    //   1366: lcmp
    //   1367: ifeq +19 -> 1386
    //   1370: aload_0
    //   1371: getfield 128	o/Dx:ʻॱ	Landroid/widget/LinearLayout;
    //   1374: iload_2
    //   1375: invokevirtual 425	android/widget/LinearLayout:setVisibility	(I)V
    //   1378: aload_0
    //   1379: getfield 153	o/Dx:ॱˊ	Landroid/widget/TextView;
    //   1382: iload_3
    //   1383: invokevirtual 426	android/widget/TextView:setVisibility	(I)V
    //   1386: ldc2_w 273
    //   1389: lload 6
    //   1391: land
    //   1392: lconst_0
    //   1393: lcmp
    //   1394: ifeq +11 -> 1405
    //   1397: aload_0
    //   1398: getfield 133	o/Dx:ॱॱ	Landroid/widget/LinearLayout;
    //   1401: iload_1
    //   1402: invokevirtual 425	android/widget/LinearLayout:setVisibility	(I)V
    //   1405: ldc2_w 349
    //   1408: lload 6
    //   1410: land
    //   1411: lconst_0
    //   1412: lcmp
    //   1413: ifeq +12 -> 1425
    //   1416: aload_0
    //   1417: getfield 157	o/Dx:ˊॱ	Landroid/webkit/WebView;
    //   1420: aload 12
    //   1422: invokestatic 431	o/y:ˋ	(Landroid/webkit/WebView;Ljava/lang/String;)V
    //   1425: return
    // Local variable table:
    //   start	length	slot	name	signature
    //   0	1426	0	this	Dx
    //   123	1279	1	i	int
    //   121	1254	2	j	int
    //   125	1258	3	k	int
    //   137	395	4	l1	long
    //   68	1341	6	l2	long
    //   88	1145	8	bool1	boolean
    //   118	394	9	bool2	boolean
    //   106	151	10	bool3	boolean
    //   100	90	11	bool4	boolean
    //   80	5	12	localObject1	Object
    //   94	1	12	localIF	DK.iF
    //   391	18	12	localObject2	Object
    //   434	1	12	localObject3	Object
    //   439	48	12	localObject4	Object
    //   545	28	12	localObject5	Object
    //   944	18	12	localObject6	Object
    //   992	18	12	localObject7	Object
    //   1112	18	12	localObject8	Object
    //   1160	261	12	str1	String
    //   133	1202	13	localObject9	Object
    //   130	1189	14	localObject10	Object
    //   60	1250	15	str2	String
    //   112	1243	16	str3	String
    //   620	713	17	localObject11	Object
    // Exception table:
    //   from	to	target	type
    //   64	75	80	finally
    //   411	436	391	finally
    //   459	511	439	finally
    //   964	989	944	finally
    //   1012	1064	992	finally
    //   1132	1157	1112	finally
    //   1180	1232	1160	finally
  }
  
  public final void ˏ(int paramInt, View paramView)
  {
    break label191;
    label56:
    label92:
    label119:
    int i;
    for (;;)
    {
      try
      {
        paramView = this.ᐝॱ;
        if (paramView != null) {
          break label92;
        }
        continue;
        paramInt = ˌ + 61;
        ˍ = paramInt % 128;
        if (paramInt % 2 == 0) {
          break label153;
        }
        break label300;
        paramInt = 0;
      }
      catch (Exception paramView)
      {
        throw paramView;
      }
      break label283;
      break;
      paramInt = 42;
      switch (paramInt)
      {
      default: 
        break;
      case 42: 
        return;
        paramInt = ˌ + 111;
        ˍ = paramInt % 128;
        if (paramInt % 2 == 0) {
          break label181;
        }
        break label215;
        i = 0;
      }
    }
    for (;;)
    {
      switch (paramInt)
      {
      case 1: 
      default: 
        return;
        paramInt = 28;
        break label252;
        paramInt = 1;
        break;
      case 2: 
        for (;;)
        {
          label153:
          label159:
          if (paramInt == 0)
          {
            return;
            paramInt = 2 / 4;
            paramInt = i;
            break label283;
          }
          else
          {
            label181:
            paramView.ˏ();
            return;
            label191:
            break label225;
            label194:
            paramInt = 60;
            break;
            paramView = this.ᐝॱ;
            if (paramView != null) {
              break label159;
            }
            break label119;
          }
          label215:
          paramInt = 1;
        }
        label220:
        paramInt = i;
        break;
        label225:
        i = ˍ + 53;
        ˌ = i % 128;
        if (i % 2 != 0) {
          break label56;
        }
      }
    }
    for (;;)
    {
      label252:
      switch (paramInt)
      {
      }
      break label220;
      label283:
      if (paramInt != 0) {
        break label194;
      }
      break;
      paramView.ˊ();
      return;
      label300:
      paramInt = 84;
    }
  }
  
  public void ˏ(boolean paramBoolean)
  {
    this.ʽॱ = paramBoolean;
    try
    {
      this.ˊᐝ |= 0x4;
    }
    finally
    {
      localObject = finally;
      throw localObject;
    }
    ˊ(75);
    super.ʽ();
  }
  
  /* Error */
  public boolean ˏ(int paramInt1, Object paramObject, int paramInt2)
  {
    // Byte code:
    //   0: goto +143 -> 143
    //   3: bipush 44
    //   5: istore_1
    //   6: goto +33 -> 39
    //   9: goto +79 -> 88
    //   12: getstatic 63	o/Dx:ˌ	I
    //   15: bipush 119
    //   17: iadd
    //   18: istore_1
    //   19: iload_1
    //   20: sipush 128
    //   23: irem
    //   24: putstatic 61	o/Dx:ˍ	I
    //   27: iload_1
    //   28: iconst_2
    //   29: irem
    //   30: ifne +6 -> 36
    //   33: goto +45 -> 78
    //   36: goto +47 -> 83
    //   39: iload_1
    //   40: lookupswitch	default:+28->68, 1:+114->154, 44:+28->68
    //   68: bipush 6
    //   70: iconst_0
    //   71: idiv
    //   72: istore_1
    //   73: iconst_0
    //   74: ireturn
    //   75: astore_2
    //   76: aload_2
    //   77: athrow
    //   78: iconst_1
    //   79: istore_1
    //   80: goto +35 -> 115
    //   83: iconst_0
    //   84: istore_1
    //   85: goto +30 -> 115
    //   88: getstatic 63	o/Dx:ˌ	I
    //   91: bipush 123
    //   93: iadd
    //   94: istore_1
    //   95: iload_1
    //   96: sipush 128
    //   99: irem
    //   100: putstatic 61	o/Dx:ˍ	I
    //   103: iload_1
    //   104: iconst_2
    //   105: irem
    //   106: ifne +6 -> 112
    //   109: goto -106 -> 3
    //   112: goto +37 -> 149
    //   115: iload_1
    //   116: tableswitch	default:+24->140, 0:+-107->9, 1:+-28->88
    //   140: goto -131 -> 9
    //   143: goto -131 -> 12
    //   146: astore_2
    //   147: aload_2
    //   148: athrow
    //   149: iconst_1
    //   150: istore_1
    //   151: goto -112 -> 39
    //   154: iconst_0
    //   155: ireturn
    // Local variable table:
    //   start	length	slot	name	signature
    //   0	156	0	this	Dx
    //   0	156	1	paramInt1	int
    //   0	156	2	paramObject	Object
    //   0	156	3	paramInt2	int
    // Exception table:
    //   from	to	target	type
    //   95	103	75	java/lang/Exception
    //   88	95	146	java/lang/Exception
    //   95	103	146	java/lang/Exception
  }
  
  public void ͺ()
  {
    try
    {
      this.ˊᐝ = 128L;
    }
    finally
    {
      localObject = finally;
      throw localObject;
    }
    ʽ();
  }
  
  public void ॱ(boolean paramBoolean)
  {
    this.ʾ = paramBoolean;
    try
    {
      this.ˊᐝ |= 0x20;
    }
    finally
    {
      localObject = finally;
      throw localObject;
    }
    ˊ(81);
    super.ʽ();
  }
  
  public boolean ॱ()
  {
    try
    {
      long l = this.ˊᐝ;
      if (l != 0L) {
        return true;
      }
    }
    finally
    {
      localObject = finally;
      throw localObject;
    }
    return false;
  }
}
