package o;

import android.content.res.Resources;
import android.databinding.ViewDataBinding;
import android.databinding.ViewDataBinding.If;
import android.util.SparseIntArray;
import android.widget.Button;
import android.widget.FrameLayout;
import android.widget.RelativeLayout;
import android.widget.TextView;

public class Dy
  extends ViewDataBinding
{
  private static final SparseIntArray ʻ;
  private static char ˋॱ;
  private static int ˏॱ;
  private static byte ͺ;
  private static long ॱˊ;
  private static int ॱˋ;
  private static final ViewDataBinding.If ॱॱ;
  private static int ॱᐝ;
  private final TextView ʼ;
  public final aG ʽ;
  public final Button ˊ;
  private long ˊॱ;
  public final FrameLayout ˎ;
  public final IX ॱ;
  private final RelativeLayout ᐝ;
  
  static
  {
    for (;;)
    {
      int i = ॱᐝ + 105;
      ॱˋ = i % 128;
      if (i % 2 == 0) {
        break;
      }
      return;
      ॱᐝ = 0;
      ॱˋ = 1;
      ˋॱ();
      ˊॱ();
      ॱॱ = null;
      ʻ = new SparseIntArray();
      ʻ.put(2131296448, 3);
      ʻ.put(2131296765, 4);
      ʻ.put(2131296405, 5);
    }
  }
  
  /* Error */
  public Dy(ˉ paramˉ, android.view.View paramView)
  {
    // Byte code:
    //   0: goto +9 -> 9
    //   3: astore_1
    //   4: aload_1
    //   5: athrow
    //   6: astore_1
    //   7: aload_1
    //   8: athrow
    //   9: aload_0
    //   10: aload_1
    //   11: aload_2
    //   12: iconst_0
    //   13: invokespecial 64	android/databinding/ViewDataBinding:<init>	(Lo/ˉ;Landroid/view/View;I)V
    //   16: aload_0
    //   17: ldc2_w 65
    //   20: putfield 68	o/Dy:ˊॱ	J
    //   23: getstatic 43	o/Dy:ॱॱ	Landroid/databinding/ViewDataBinding$If;
    //   26: astore_3
    //   27: getstatic 50	o/Dy:ʻ	Landroid/util/SparseIntArray;
    //   30: astore 4
    //   32: aload_1
    //   33: aload_2
    //   34: bipush 6
    //   36: aload_3
    //   37: aload 4
    //   39: invokestatic 71	o/Dy:ॱ	(Lo/ˉ;Landroid/view/View;ILandroid/databinding/ViewDataBinding$If;Landroid/util/SparseIntArray;)[Ljava/lang/Object;
    //   42: astore_1
    //   43: aload_0
    //   44: aload_1
    //   45: iconst_1
    //   46: aaload
    //   47: checkcast 73	android/widget/Button
    //   50: putfield 75	o/Dy:ˊ	Landroid/widget/Button;
    //   53: aload_0
    //   54: getfield 75	o/Dy:ˊ	Landroid/widget/Button;
    //   57: aconst_null
    //   58: invokevirtual 79	android/widget/Button:setTag	(Ljava/lang/Object;)V
    //   61: aload_0
    //   62: aload_1
    //   63: iconst_5
    //   64: aaload
    //   65: checkcast 81	o/IX
    //   68: putfield 83	o/Dy:ॱ	Lo/IX;
    //   71: aload_0
    //   72: aload_1
    //   73: iconst_3
    //   74: aaload
    //   75: checkcast 85	android/widget/FrameLayout
    //   78: putfield 87	o/Dy:ˎ	Landroid/widget/FrameLayout;
    //   81: aload_0
    //   82: aload_1
    //   83: iconst_0
    //   84: aaload
    //   85: checkcast 89	android/widget/RelativeLayout
    //   88: putfield 91	o/Dy:ᐝ	Landroid/widget/RelativeLayout;
    //   91: aload_0
    //   92: getfield 91	o/Dy:ᐝ	Landroid/widget/RelativeLayout;
    //   95: aconst_null
    //   96: invokevirtual 92	android/widget/RelativeLayout:setTag	(Ljava/lang/Object;)V
    //   99: aload_0
    //   100: aload_1
    //   101: iconst_2
    //   102: aaload
    //   103: checkcast 94	android/widget/TextView
    //   106: putfield 96	o/Dy:ʼ	Landroid/widget/TextView;
    //   109: aload_0
    //   110: getfield 96	o/Dy:ʼ	Landroid/widget/TextView;
    //   113: aconst_null
    //   114: invokevirtual 97	android/widget/TextView:setTag	(Ljava/lang/Object;)V
    //   117: aload_0
    //   118: aload_1
    //   119: iconst_4
    //   120: aaload
    //   121: checkcast 99	o/aG
    //   124: putfield 101	o/Dy:ʽ	Lo/aG;
    //   127: aload_0
    //   128: aload_2
    //   129: invokevirtual 105	o/Dy:ˋ	(Landroid/view/View;)V
    //   132: aload_0
    //   133: invokevirtual 107	o/Dy:ͺ	()V
    //   136: return
    // Local variable table:
    //   start	length	slot	name	signature
    //   0	137	0	this	Dy
    //   0	137	1	paramˉ	ˉ
    //   0	137	2	paramView	android.view.View
    //   26	11	3	localIf	ViewDataBinding.If
    //   30	8	4	localSparseIntArray	SparseIntArray
    // Exception table:
    //   from	to	target	type
    //   23	27	3	java/lang/Exception
    //   27	32	3	java/lang/Exception
    //   32	136	3	java/lang/Exception
    //   16	23	6	java/lang/Exception
  }
  
  static void ˊॱ()
  {
    break label119;
    ͺ = 7;
    break label25;
    ͺ = -102;
    break label25;
    label19:
    int i = 67;
    label25:
    label119:
    for (;;)
    {
      try
      {
        i = ॱᐝ;
        i += 75;
        ॱˋ = i % 128;
        if (i % 2 == 0) {
          return;
        }
        return;
      }
      catch (Exception localException)
      {
        throw localException;
      }
      i = ॱˋ;
      i += 7;
      ॱᐝ = i % 128;
      if (i % 2 != 0) {
        break label19;
      }
      i = 34;
      switch (i)
      {
      }
      break;
    }
  }
  
  static void ˋॱ()
  {
    ˋॱ = 49087;
    ॱˊ = 0L;
    ˏॱ = 0;
  }
  
  /* Error */
  private String ˎ(String paramString)
  {
    // Byte code:
    //   0: goto +41 -> 41
    //   3: getstatic 37	o/Dy:ॱˋ	I
    //   6: bipush 25
    //   8: iadd
    //   9: istore_2
    //   10: iload_2
    //   11: sipush 128
    //   14: irem
    //   15: putstatic 35	o/Dy:ॱᐝ	I
    //   18: iload_2
    //   19: iconst_2
    //   20: irem
    //   21: ifeq +6 -> 27
    //   24: goto +428 -> 452
    //   27: goto +64 -> 91
    //   30: iconst_0
    //   31: istore_3
    //   32: goto +378 -> 410
    //   35: astore_1
    //   36: aload_1
    //   37: athrow
    //   38: goto +272 -> 310
    //   41: goto +86 -> 127
    //   44: bipush 65
    //   46: iconst_0
    //   47: idiv
    //   48: istore_2
    //   49: aload_1
    //   50: areturn
    //   51: aload_1
    //   52: arraylength
    //   53: istore_3
    //   54: iload_2
    //   55: iload_3
    //   56: if_icmpge +6 -> 62
    //   59: goto -29 -> 30
    //   62: goto +373 -> 435
    //   65: getstatic 35	o/Dy:ॱᐝ	I
    //   68: iconst_5
    //   69: iadd
    //   70: istore_3
    //   71: iload_3
    //   72: sipush 128
    //   75: irem
    //   76: putstatic 37	o/Dy:ॱˋ	I
    //   79: iload_3
    //   80: iconst_2
    //   81: irem
    //   82: ifne +6 -> 88
    //   85: goto +12 -> 97
    //   88: goto +167 -> 255
    //   91: bipush 92
    //   93: istore_2
    //   94: goto +185 -> 279
    //   97: goto +158 -> 255
    //   100: getstatic 37	o/Dy:ॱˋ	I
    //   103: bipush 113
    //   105: iadd
    //   106: istore_3
    //   107: iload_3
    //   108: sipush 128
    //   111: irem
    //   112: putstatic 35	o/Dy:ॱᐝ	I
    //   115: iload_3
    //   116: iconst_2
    //   117: irem
    //   118: ifeq +6 -> 124
    //   121: goto -83 -> 38
    //   124: goto +186 -> 310
    //   127: aload_1
    //   128: iconst_4
    //   129: newarray char
    //   131: dup
    //   132: iconst_0
    //   133: ldc 120
    //   135: castore
    //   136: dup
    //   137: iconst_1
    //   138: ldc 121
    //   140: castore
    //   141: dup
    //   142: iconst_2
    //   143: ldc 122
    //   145: castore
    //   146: dup
    //   147: iconst_3
    //   148: ldc 123
    //   150: castore
    //   151: iconst_0
    //   152: bipush 10
    //   154: newarray char
    //   156: dup
    //   157: iconst_0
    //   158: ldc 124
    //   160: castore
    //   161: dup
    //   162: iconst_1
    //   163: ldc 125
    //   165: castore
    //   166: dup
    //   167: iconst_2
    //   168: ldc 126
    //   170: castore
    //   171: dup
    //   172: iconst_3
    //   173: ldc 127
    //   175: castore
    //   176: dup
    //   177: iconst_4
    //   178: ldc -128
    //   180: castore
    //   181: dup
    //   182: iconst_5
    //   183: ldc -127
    //   185: castore
    //   186: dup
    //   187: bipush 6
    //   189: ldc -126
    //   191: castore
    //   192: dup
    //   193: bipush 7
    //   195: ldc -125
    //   197: castore
    //   198: dup
    //   199: bipush 8
    //   201: ldc -124
    //   203: castore
    //   204: dup
    //   205: bipush 9
    //   207: ldc -123
    //   209: castore
    //   210: iconst_0
    //   211: iconst_4
    //   212: newarray char
    //   214: dup
    //   215: iconst_0
    //   216: ldc -122
    //   218: castore
    //   219: dup
    //   220: iconst_1
    //   221: ldc -122
    //   223: castore
    //   224: dup
    //   225: iconst_2
    //   226: ldc -122
    //   228: castore
    //   229: dup
    //   230: iconst_3
    //   231: ldc -122
    //   233: castore
    //   234: invokestatic 138	o/Dy:ˏ	([CC[CI[C)Ljava/lang/String;
    //   237: invokevirtual 144	java/lang/String:intern	()Ljava/lang/String;
    //   240: invokevirtual 148	java/lang/String:getBytes	(Ljava/lang/String;)[B
    //   243: astore_1
    //   244: aload_1
    //   245: arraylength
    //   246: newarray byte
    //   248: astore 4
    //   250: iconst_0
    //   251: istore_2
    //   252: goto -201 -> 51
    //   255: aload 4
    //   257: iload_2
    //   258: aload_1
    //   259: aload_1
    //   260: arraylength
    //   261: iload_2
    //   262: isub
    //   263: iconst_1
    //   264: isub
    //   265: baload
    //   266: getstatic 109	o/Dy:ͺ	B
    //   269: ixor
    //   270: i2b
    //   271: bastore
    //   272: iload_2
    //   273: iconst_1
    //   274: iadd
    //   275: istore_2
    //   276: goto -176 -> 100
    //   279: iload_2
    //   280: lookupswitch	default:+28->308, 19:+-236->44, 92:+160->440
    //   308: aload_1
    //   309: areturn
    //   310: goto -259 -> 51
    //   313: new 140	java/lang/String
    //   316: dup
    //   317: aload 4
    //   319: iconst_4
    //   320: newarray char
    //   322: dup
    //   323: iconst_0
    //   324: ldc -107
    //   326: castore
    //   327: dup
    //   328: iconst_1
    //   329: ldc -106
    //   331: castore
    //   332: dup
    //   333: iconst_2
    //   334: ldc -105
    //   336: castore
    //   337: dup
    //   338: iconst_3
    //   339: ldc -104
    //   341: castore
    //   342: ldc -103
    //   344: iconst_5
    //   345: newarray char
    //   347: dup
    //   348: iconst_0
    //   349: ldc -102
    //   351: castore
    //   352: dup
    //   353: iconst_1
    //   354: ldc -101
    //   356: castore
    //   357: dup
    //   358: iconst_2
    //   359: ldc -100
    //   361: castore
    //   362: dup
    //   363: iconst_3
    //   364: ldc -99
    //   366: castore
    //   367: dup
    //   368: iconst_4
    //   369: ldc -98
    //   371: castore
    //   372: ldc -97
    //   374: iconst_4
    //   375: newarray char
    //   377: dup
    //   378: iconst_0
    //   379: ldc -122
    //   381: castore
    //   382: dup
    //   383: iconst_1
    //   384: ldc -122
    //   386: castore
    //   387: dup
    //   388: iconst_2
    //   389: ldc -122
    //   391: castore
    //   392: dup
    //   393: iconst_3
    //   394: ldc -122
    //   396: castore
    //   397: invokestatic 138	o/Dy:ˏ	([CC[CI[C)Ljava/lang/String;
    //   400: invokevirtual 144	java/lang/String:intern	()Ljava/lang/String;
    //   403: invokespecial 162	java/lang/String:<init>	([BLjava/lang/String;)V
    //   406: astore_1
    //   407: goto -404 -> 3
    //   410: iload_3
    //   411: tableswitch	default:+21->432, 0:+-346->65, 1:+-98->313
    //   432: goto -119 -> 313
    //   435: iconst_1
    //   436: istore_3
    //   437: goto -27 -> 410
    //   440: aload_1
    //   441: areturn
    //   442: astore_1
    //   443: new 164	java/lang/RuntimeException
    //   446: dup
    //   447: aload_1
    //   448: invokespecial 167	java/lang/RuntimeException:<init>	(Ljava/lang/Throwable;)V
    //   451: athrow
    //   452: bipush 19
    //   454: istore_2
    //   455: goto -176 -> 279
    // Local variable table:
    //   start	length	slot	name	signature
    //   0	458	0	this	Dy
    //   0	458	1	paramString	String
    //   9	446	2	i	int
    //   31	406	3	j	int
    //   248	70	4	arrayOfByte	byte[]
    // Exception table:
    //   from	to	target	type
    //   100	107	35	java/lang/Exception
    //   107	115	35	java/lang/Exception
    //   51	54	442	java/io/UnsupportedEncodingException
    //   127	250	442	java/io/UnsupportedEncodingException
    //   255	272	442	java/io/UnsupportedEncodingException
    //   313	407	442	java/io/UnsupportedEncodingException
  }
  
  /* Error */
  private static String ˏ(char[] paramArrayOfChar1, char paramChar, char[] paramArrayOfChar2, int paramInt, char[] paramArrayOfChar3)
  {
    // Byte code:
    //   0: goto +53 -> 53
    //   3: iload_3
    //   4: tableswitch	default:+24->28, 0:+178->182, 1:+24->28
    //   28: new 140	java/lang/String
    //   31: dup
    //   32: aload 6
    //   34: invokespecial 170	java/lang/String:<init>	([C)V
    //   37: astore_0
    //   38: goto +80 -> 118
    //   41: iload_1
    //   42: iload 5
    //   44: if_icmpge +6 -> 50
    //   47: goto +181 -> 228
    //   50: goto +6 -> 56
    //   53: goto +97 -> 150
    //   56: iconst_1
    //   57: istore_3
    //   58: goto -55 -> 3
    //   61: aload_0
    //   62: invokevirtual 176	[C:clone	()Ljava/lang/Object;
    //   65: checkcast 172	[C
    //   68: astore_0
    //   69: aload 4
    //   71: invokevirtual 176	[C:clone	()Ljava/lang/Object;
    //   74: checkcast 172	[C
    //   77: astore 4
    //   79: aload_0
    //   80: iconst_0
    //   81: aload_0
    //   82: iconst_0
    //   83: caload
    //   84: iload_1
    //   85: ixor
    //   86: i2c
    //   87: castore
    //   88: aload 4
    //   90: iconst_2
    //   91: aload 4
    //   93: iconst_2
    //   94: caload
    //   95: iload_3
    //   96: i2c
    //   97: iadd
    //   98: i2c
    //   99: castore
    //   100: aload_2
    //   101: arraylength
    //   102: istore 5
    //   104: iload 5
    //   106: newarray char
    //   108: astore 6
    //   110: iconst_0
    //   111: istore_1
    //   112: goto -71 -> 41
    //   115: goto -54 -> 61
    //   118: getstatic 37	o/Dy:ॱˋ	I
    //   121: bipush 79
    //   123: iadd
    //   124: istore_1
    //   125: iload_1
    //   126: sipush 128
    //   129: irem
    //   130: putstatic 35	o/Dy:ॱᐝ	I
    //   133: iload_1
    //   134: iconst_2
    //   135: irem
    //   136: ifeq +6 -> 142
    //   139: goto +41 -> 180
    //   142: aload_0
    //   143: areturn
    //   144: astore_0
    //   145: aload_0
    //   146: athrow
    //   147: astore_0
    //   148: aload_0
    //   149: athrow
    //   150: getstatic 35	o/Dy:ॱᐝ	I
    //   153: bipush 21
    //   155: iadd
    //   156: istore 5
    //   158: iload 5
    //   160: sipush 128
    //   163: irem
    //   164: putstatic 37	o/Dy:ॱˋ	I
    //   167: iload 5
    //   169: iconst_2
    //   170: irem
    //   171: ifne +6 -> 177
    //   174: goto -59 -> 115
    //   177: goto -116 -> 61
    //   180: aload_0
    //   181: areturn
    //   182: aload_0
    //   183: aload 4
    //   185: iload_1
    //   186: invokestatic 181	o/oJ:ˏ	([C[CI)V
    //   189: aload 6
    //   191: iload_1
    //   192: aload_2
    //   193: iload_1
    //   194: caload
    //   195: aload_0
    //   196: iload_1
    //   197: iconst_3
    //   198: iadd
    //   199: iconst_4
    //   200: irem
    //   201: caload
    //   202: ixor
    //   203: i2l
    //   204: getstatic 114	o/Dy:ॱˊ	J
    //   207: lxor
    //   208: getstatic 116	o/Dy:ˏॱ	I
    //   211: i2l
    //   212: lxor
    //   213: getstatic 112	o/Dy:ˋॱ	C
    //   216: i2l
    //   217: lxor
    //   218: l2i
    //   219: i2c
    //   220: castore
    //   221: iload_1
    //   222: iconst_1
    //   223: iadd
    //   224: istore_1
    //   225: goto -184 -> 41
    //   228: iconst_0
    //   229: istore_3
    //   230: goto -227 -> 3
    // Local variable table:
    //   start	length	slot	name	signature
    //   0	233	0	paramArrayOfChar1	char[]
    //   0	233	1	paramChar	char
    //   0	233	2	paramArrayOfChar2	char[]
    //   0	233	3	paramInt	int
    //   0	233	4	paramArrayOfChar3	char[]
    //   42	129	5	c	char
    //   32	158	6	arrayOfChar	char[]
    // Exception table:
    //   from	to	target	type
    //   150	158	144	java/lang/Exception
    //   158	167	144	java/lang/Exception
    //   158	167	147	java/lang/Exception
  }
  
  public void ˏ()
  {
    long l;
    try
    {
      l = this.ˊॱ;
      this.ˊॱ = 0L;
    }
    finally
    {
      localObject1 = finally;
      throw localObject1;
    }
    if ((1L & l) != 0L)
    {
      Object localObject3 = this.ˊ;
      String str = this.ˊ.getResources().getString(2131755147);
      Object localObject2 = str;
      if (str.startsWith(ˏ(new char[] { -12431, 30206, -28902, -28140 }, 'ᒏ', new char[] { -13950, -14436, 32133, -7858 }, 0, new char[] { 0, 0, 0, 0 }).intern())) {
        localObject2 = ˎ(str.substring(4)).intern();
      }
      ʹ.ˊ((TextView)localObject3, (CharSequence)localObject2);
      localObject3 = this.ʼ;
      str = this.ʼ.getResources().getString(2131755553);
      localObject2 = str;
      if (str.startsWith(ˏ(new char[] { -12431, 30206, -28902, -28140 }, 'ᒏ', new char[] { -13950, -14436, 32133, -7858 }, 0, new char[] { 0, 0, 0, 0 }).intern())) {
        localObject2 = ˎ(str.substring(4)).intern();
      }
      ʹ.ˊ((TextView)localObject3, (CharSequence)localObject2);
    }
  }
  
  public boolean ˏ(int paramInt1, Object paramObject, int paramInt2)
  {
    for (;;)
    {
      paramInt1 = ॱᐝ + 37;
      ॱˋ = paramInt1 % 128;
      if (paramInt1 % 2 != 0) {
        break label35;
      }
      for (;;)
      {
        paramInt1 = 1;
        break label75;
        label35:
        paramInt1 = 41;
        break label43;
        return false;
        switch (paramInt1)
        {
        default: 
          break;
          switch (paramInt1)
          {
          }
          break;
        case 41: 
          label43:
          label75:
          break;
        }
        do
        {
          paramInt1 = 0;
          break label75;
          paramInt1 = 18;
          break;
          paramInt1 = null.length;
          return false;
          paramInt1 = ॱᐝ + 15;
          ॱˋ = paramInt1 % 128;
        } while (paramInt1 % 2 == 0);
      }
    }
  }
  
  public void ͺ()
  {
    try
    {
      this.ˊॱ = 1L;
    }
    finally
    {
      localObject = finally;
      throw localObject;
    }
    ʽ();
  }
  
  public boolean ॱ()
  {
    try
    {
      long l = this.ˊॱ;
      if (l != 0L) {
        return true;
      }
    }
    finally
    {
      localObject = finally;
      throw localObject;
    }
    return false;
  }
}
