package o;

import ro.btrl.boot.di.module.BootModule;

public final class Dz
  implements qo<DO.iF>
{
  private static int ʻ = -986856076;
  private static short[] ʼ;
  private static byte[] ʽ;
  private static int ˎ;
  private static int ˏ = 1177152428;
  private static int ॱॱ = 0;
  private static int ᐝ = 1;
  private final BootModule ˊ;
  private final uu<DF> ˋ;
  private final uu<DO.if> ॱ;
  
  static
  {
    ˎ = 68;
    ʽ = new byte[] { 22, -28, 23, -20, 27, -82, 78, -19, -30, 24, 16, -28, 30, -63, -13, -61, 88, 26, -23, -30, 22, -29, 20, -60, -19, -16, 92, 28, -30, -83, 92, -94, 80, 29, 30, -17, -91, 87, -29, 20, -28, -83, 81, 31, 30, -30, -20, 16, -79, 79, -26, -30, -29, -18, -3, 0 };
  }
  
  /* Error */
  private static String ˎ(short paramShort, int paramInt1, byte paramByte, int paramInt2, int paramInt3)
  {
    // Byte code:
    //   0: goto +119 -> 119
    //   3: astore 8
    //   5: aload 8
    //   7: athrow
    //   8: goto +39 -> 47
    //   11: iconst_1
    //   12: istore 6
    //   14: goto +234 -> 248
    //   17: iload 4
    //   19: lookupswitch	default:+25->44, 0:+437->456, 26:+145->164
    //   44: goto +412 -> 456
    //   47: getstatic 73	o/Dz:ʽ	[B
    //   50: astore 9
    //   52: iload_1
    //   53: iconst_1
    //   54: isub
    //   55: istore 6
    //   57: aload 9
    //   59: iload_1
    //   60: baload
    //   61: iload_0
    //   62: iadd
    //   63: i2b
    //   64: iload_2
    //   65: ixor
    //   66: iload 7
    //   68: iadd
    //   69: i2c
    //   70: istore 5
    //   72: goto +50 -> 122
    //   75: iconst_1
    //   76: istore 6
    //   78: goto +271 -> 349
    //   81: iconst_0
    //   82: istore 4
    //   84: goto +322 -> 406
    //   87: goto +246 -> 333
    //   90: iload 6
    //   92: tableswitch	default:+24->116, 0:+206->298, 1:+96->188
    //   116: goto +182 -> 298
    //   119: goto +422 -> 541
    //   122: iload 6
    //   124: istore_1
    //   125: goto +189 -> 314
    //   128: getstatic 28	o/Dz:ॱॱ	I
    //   131: bipush 81
    //   133: iadd
    //   134: istore 4
    //   136: iload 4
    //   138: sipush 128
    //   141: irem
    //   142: putstatic 30	o/Dz:ᐝ	I
    //   145: iload 4
    //   147: iconst_2
    //   148: irem
    //   149: ifne +6 -> 155
    //   152: goto +455 -> 607
    //   155: goto +321 -> 476
    //   158: iconst_0
    //   159: istore 6
    //   161: goto -71 -> 90
    //   164: getstatic 73	o/Dz:ʽ	[B
    //   167: ifnull +6 -> 173
    //   170: goto +6 -> 176
    //   173: goto +246 -> 419
    //   176: bipush 14
    //   178: istore 4
    //   180: goto +480 -> 660
    //   183: astore 8
    //   185: aload 8
    //   187: athrow
    //   188: getstatic 28	o/Dz:ॱॱ	I
    //   191: bipush 11
    //   193: iadd
    //   194: istore 6
    //   196: iload 6
    //   198: sipush 128
    //   201: irem
    //   202: putstatic 30	o/Dz:ᐝ	I
    //   205: iload 6
    //   207: iconst_2
    //   208: irem
    //   209: ifne +6 -> 215
    //   212: goto +445 -> 657
    //   215: goto +71 -> 286
    //   218: getstatic 28	o/Dz:ॱॱ	I
    //   221: bipush 65
    //   223: iadd
    //   224: istore 7
    //   226: iload 7
    //   228: sipush 128
    //   231: irem
    //   232: putstatic 30	o/Dz:ᐝ	I
    //   235: iload 7
    //   237: iconst_2
    //   238: irem
    //   239: ifne +6 -> 245
    //   242: goto -155 -> 87
    //   245: goto +88 -> 333
    //   248: iload 6
    //   250: tableswitch	default:+22->272, 0:+327->577, 1:+363->613
    //   272: goto +305 -> 577
    //   275: iload 4
    //   277: ifle +6 -> 283
    //   280: goto -62 -> 218
    //   283: goto +15 -> 298
    //   286: getstatic 73	o/Dz:ʽ	[B
    //   289: ifnull +6 -> 295
    //   292: goto +121 -> 413
    //   295: goto -284 -> 11
    //   298: aload 8
    //   300: invokevirtual 89	java/lang/StringBuilder:toString	()Ljava/lang/String;
    //   303: astore 8
    //   305: aload 8
    //   307: areturn
    //   308: iconst_0
    //   309: istore 6
    //   311: goto +38 -> 349
    //   314: aload 8
    //   316: iload 5
    //   318: invokevirtual 93	java/lang/StringBuilder:append	(C)Ljava/lang/StringBuilder;
    //   321: pop
    //   322: iload_3
    //   323: iconst_1
    //   324: iadd
    //   325: istore_3
    //   326: iload 5
    //   328: istore 7
    //   330: goto +193 -> 523
    //   333: getstatic 79	o/Dz:ˏ	I
    //   336: istore 7
    //   338: iload 6
    //   340: ifeq +6 -> 346
    //   343: goto -268 -> 75
    //   346: goto -38 -> 308
    //   349: iload_1
    //   350: iload 4
    //   352: iadd
    //   353: iconst_2
    //   354: isub
    //   355: iload 7
    //   357: iadd
    //   358: iload 6
    //   360: iadd
    //   361: istore_1
    //   362: getstatic 76	o/Dz:ʻ	I
    //   365: istore 6
    //   367: iload 6
    //   369: iload_3
    //   370: iadd
    //   371: i2c
    //   372: istore 5
    //   374: aload 8
    //   376: iload 5
    //   378: invokevirtual 93	java/lang/StringBuilder:append	(C)Ljava/lang/StringBuilder;
    //   381: pop
    //   382: iconst_1
    //   383: istore_3
    //   384: goto +266 -> 650
    //   387: getstatic 95	o/Dz:ʼ	[S
    //   390: getstatic 79	o/Dz:ˏ	I
    //   393: iload_1
    //   394: iadd
    //   395: saload
    //   396: getstatic 32	o/Dz:ˎ	I
    //   399: iadd
    //   400: i2s
    //   401: istore 4
    //   403: goto -128 -> 275
    //   406: iload 4
    //   408: istore 6
    //   410: goto +73 -> 483
    //   413: iconst_0
    //   414: istore 6
    //   416: goto -168 -> 248
    //   419: bipush 31
    //   421: istore 4
    //   423: goto +237 -> 660
    //   426: getstatic 30	o/Dz:ᐝ	I
    //   429: bipush 33
    //   431: iadd
    //   432: istore 4
    //   434: iload 4
    //   436: sipush 128
    //   439: irem
    //   440: putstatic 28	o/Dz:ॱॱ	I
    //   443: iload 4
    //   445: iconst_2
    //   446: irem
    //   447: ifeq +6 -> 453
    //   450: goto -369 -> 81
    //   453: goto +82 -> 535
    //   456: getstatic 73	o/Dz:ʽ	[B
    //   459: astore 9
    //   461: aconst_null
    //   462: arraylength
    //   463: istore 4
    //   465: aload 9
    //   467: ifnull +6 -> 473
    //   470: goto +28 -> 498
    //   473: goto -86 -> 387
    //   476: bipush 26
    //   478: istore 4
    //   480: goto -463 -> 17
    //   483: iload 6
    //   485: ifeq +6 -> 491
    //   488: goto -360 -> 128
    //   491: iload 7
    //   493: istore 4
    //   495: goto -220 -> 275
    //   498: getstatic 73	o/Dz:ʽ	[B
    //   501: getstatic 79	o/Dz:ˏ	I
    //   504: iload_1
    //   505: iadd
    //   506: baload
    //   507: getstatic 32	o/Dz:ˎ	I
    //   510: iadd
    //   511: i2b
    //   512: istore 4
    //   514: goto +60 -> 574
    //   517: iconst_1
    //   518: istore 6
    //   520: goto -430 -> 90
    //   523: iload_3
    //   524: iload 4
    //   526: if_icmpge +6 -> 532
    //   529: goto -12 -> 517
    //   532: goto -374 -> 158
    //   535: iconst_1
    //   536: istore 4
    //   538: goto -132 -> 406
    //   541: new 85	java/lang/StringBuilder
    //   544: dup
    //   545: invokespecial 98	java/lang/StringBuilder:<init>	()V
    //   548: astore 8
    //   550: getstatic 32	o/Dz:ˎ	I
    //   553: iload 4
    //   555: iadd
    //   556: istore 4
    //   558: iload 4
    //   560: istore 7
    //   562: iload 4
    //   564: iconst_m1
    //   565: if_icmpne +6 -> 571
    //   568: goto -142 -> 426
    //   571: goto +73 -> 644
    //   574: goto -299 -> 275
    //   577: getstatic 30	o/Dz:ᐝ	I
    //   580: bipush 83
    //   582: iadd
    //   583: istore 6
    //   585: iload 6
    //   587: sipush 128
    //   590: irem
    //   591: putstatic 28	o/Dz:ॱॱ	I
    //   594: iload 6
    //   596: iconst_2
    //   597: irem
    //   598: ifeq +6 -> 604
    //   601: goto -593 -> 8
    //   604: goto -557 -> 47
    //   607: iconst_0
    //   608: istore 4
    //   610: goto -593 -> 17
    //   613: getstatic 95	o/Dz:ʼ	[S
    //   616: astore 9
    //   618: iload_1
    //   619: iconst_1
    //   620: isub
    //   621: istore 6
    //   623: aload 9
    //   625: iload_1
    //   626: saload
    //   627: iload_0
    //   628: iadd
    //   629: i2s
    //   630: iload_2
    //   631: ixor
    //   632: iload 7
    //   634: iadd
    //   635: i2c
    //   636: istore 5
    //   638: iload 6
    //   640: istore_1
    //   641: goto -327 -> 314
    //   644: iconst_0
    //   645: istore 6
    //   647: goto -164 -> 483
    //   650: iload 5
    //   652: istore 7
    //   654: goto -131 -> 523
    //   657: goto -371 -> 286
    //   660: iload 4
    //   662: lookupswitch	default:+26->688, 14:+-164->498, 31:+-275->387
    //   688: goto -301 -> 387
    // Local variable table:
    //   start	length	slot	name	signature
    //   0	691	0	paramShort	short
    //   0	691	1	paramInt1	int
    //   0	691	2	paramByte	byte
    //   0	691	3	paramInt2	int
    //   0	691	4	paramInt3	int
    //   70	581	5	i	int
    //   12	634	6	j	int
    //   66	587	7	k	int
    //   3	3	8	localException1	Exception
    //   183	116	8	localException2	Exception
    //   303	246	8	localObject1	Object
    //   50	574	9	localObject2	Object
    // Exception table:
    //   from	to	target	type
    //   196	205	3	java/lang/Exception
    //   374	382	3	java/lang/Exception
    //   188	196	183	java/lang/Exception
    //   196	205	183	java/lang/Exception
    //   298	305	183	java/lang/Exception
    //   362	367	183	java/lang/Exception
  }
  
  /* Error */
  public static DO.iF ॱ(BootModule paramBootModule, DO.if paramIf, DF paramDF)
  {
    // Byte code:
    //   0: goto +36 -> 36
    //   3: getstatic 30	o/Dz:ᐝ	I
    //   6: bipush 87
    //   8: iadd
    //   9: istore_3
    //   10: iload_3
    //   11: sipush 128
    //   14: irem
    //   15: putstatic 28	o/Dz:ॱॱ	I
    //   18: iload_3
    //   19: iconst_2
    //   20: irem
    //   21: ifeq +6 -> 27
    //   24: goto +170 -> 194
    //   27: goto +160 -> 187
    //   30: bipush 50
    //   32: istore_3
    //   33: goto +95 -> 128
    //   36: goto +65 -> 101
    //   39: iload_3
    //   40: tableswitch	default:+24->64, 0:+152->192, 1:+159->199
    //   64: goto +135 -> 199
    //   67: astore_0
    //   68: aload_0
    //   69: athrow
    //   70: aload_0
    //   71: aload_1
    //   72: aload_2
    //   73: invokevirtual 104	ro/btrl/boot/di/module/BootModule:ॱ	(Lo/DO$if;Lo/DF;)Lo/DO$iF;
    //   76: iconst_1
    //   77: ldc 105
    //   79: bipush 96
    //   81: ldc 106
    //   83: bipush 123
    //   85: invokestatic 108	o/Dz:ˎ	(SIBII)Ljava/lang/String;
    //   88: invokevirtual 113	java/lang/String:intern	()Ljava/lang/String;
    //   91: invokestatic 118	o/qn:ॱ	(Ljava/lang/Object;Ljava/lang/String;)Ljava/lang/Object;
    //   94: checkcast 120	o/DO$iF
    //   97: astore_0
    //   98: goto -95 -> 3
    //   101: getstatic 30	o/Dz:ᐝ	I
    //   104: bipush 59
    //   106: iadd
    //   107: istore_3
    //   108: iload_3
    //   109: sipush 128
    //   112: irem
    //   113: putstatic 28	o/Dz:ॱॱ	I
    //   116: iload_3
    //   117: iconst_2
    //   118: irem
    //   119: ifeq +6 -> 125
    //   122: goto +82 -> 204
    //   125: goto -95 -> 30
    //   128: iload_3
    //   129: lookupswitch	default:+27->156, 25:+-59->70, 50:+27->156
    //   156: aload_0
    //   157: aload_1
    //   158: aload_2
    //   159: invokevirtual 104	ro/btrl/boot/di/module/BootModule:ॱ	(Lo/DO$if;Lo/DF;)Lo/DO$iF;
    //   162: iconst_0
    //   163: ldc 105
    //   165: bipush -29
    //   167: ldc 106
    //   169: bipush -12
    //   171: invokestatic 108	o/Dz:ˎ	(SIBII)Ljava/lang/String;
    //   174: invokevirtual 113	java/lang/String:intern	()Ljava/lang/String;
    //   177: invokestatic 118	o/qn:ॱ	(Ljava/lang/Object;Ljava/lang/String;)Ljava/lang/Object;
    //   180: checkcast 120	o/DO$iF
    //   183: astore_0
    //   184: goto -181 -> 3
    //   187: iconst_0
    //   188: istore_3
    //   189: goto -150 -> 39
    //   192: aload_0
    //   193: areturn
    //   194: iconst_1
    //   195: istore_3
    //   196: goto -157 -> 39
    //   199: aconst_null
    //   200: arraylength
    //   201: istore_3
    //   202: aload_0
    //   203: areturn
    //   204: bipush 25
    //   206: istore_3
    //   207: goto -79 -> 128
    //   210: astore_0
    //   211: aload_0
    //   212: athrow
    // Local variable table:
    //   start	length	slot	name	signature
    //   0	213	0	paramBootModule	BootModule
    //   0	213	1	paramIf	DO.if
    //   0	213	2	paramDF	DF
    //   9	198	3	i	int
    // Exception table:
    //   from	to	target	type
    //   3	10	67	java/lang/Exception
    //   10	18	67	java/lang/Exception
    //   156	184	67	java/lang/Exception
    //   10	18	210	java/lang/Exception
  }
  
  public DO.iF ˊ()
  {
    break label97;
    int i = ᐝ + 101;
    ॱॱ = i % 128;
    if (i % 2 == 0) {
      break label124;
    }
    for (;;)
    {
      try
      {
        Object localObject1 = this.ˊ;
        try
        {
          Object localObject2 = this.ॱ;
          localObject2 = ((uu)localObject2).ˋ();
          localObject2 = (DO.if)localObject2;
          localObject1 = (DO.iF)qn.ॱ(((BootModule)localObject1).ॱ((DO.if)localObject2, (DF)this.ˋ.ˋ()), ˎ((short)0, -1177152428, (byte)-29, 986856143, -12).intern());
        }
        catch (Exception localException1)
        {
          throw localException1;
        }
        continue;
        label97:
        i = ॱॱ + 29;
        ᐝ = i % 128;
        if (i % 2 == 0) {
          continue;
        }
        continue;
        label124:
        i = 31;
        continue;
        i = 71 / 0;
        return localObject1;
        switch (i)
        {
        case 62: 
        default: 
          return localObject1;
        }
      }
      catch (Exception localException2)
      {
        throw localException2;
      }
      return localException2;
      i = 62;
    }
  }
}
