package o;

public enum ED
{
  private static int ʼ;
  private static int ʽ;
  private static short[] ˊ;
  private static byte[] ˋ;
  private static int ˎ;
  private static int ˏ;
  private static int ॱ;
  
  /* Error */
  static
  {
    // Byte code:
    //   0: goto +35 -> 35
    //   3: getstatic 27	o/ED:ʼ	I
    //   6: bipush 85
    //   8: iadd
    //   9: istore_0
    //   10: iload_0
    //   11: sipush 128
    //   14: irem
    //   15: putstatic 29	o/ED:ʽ	I
    //   18: iload_0
    //   19: iconst_2
    //   20: irem
    //   21: ifne +6 -> 27
    //   24: goto +7 -> 31
    //   27: return
    //   28: astore_1
    //   29: aload_1
    //   30: athrow
    //   31: return
    //   32: astore_1
    //   33: aload_1
    //   34: athrow
    //   35: iconst_0
    //   36: putstatic 27	o/ED:ʼ	I
    //   39: iconst_1
    //   40: putstatic 29	o/ED:ʽ	I
    //   43: invokestatic 31	o/ED:ˊ	()V
    //   46: new 2	o/ED
    //   49: dup
    //   50: iconst_0
    //   51: ldc 32
    //   53: iconst_0
    //   54: ldc 33
    //   56: bipush -32
    //   58: invokestatic 36	o/ED:ˏ	(SIBII)Ljava/lang/String;
    //   61: invokevirtual 42	java/lang/String:intern	()Ljava/lang/String;
    //   64: iconst_0
    //   65: invokespecial 46	o/ED:<init>	(Ljava/lang/String;I)V
    //   68: putstatic 48	o/ED:DISPLAY_ENTER_BIRTH_DATE_SCREEN	Lo/ED;
    //   71: new 2	o/ED
    //   74: dup
    //   75: iconst_0
    //   76: ldc 49
    //   78: iconst_0
    //   79: ldc 50
    //   81: bipush -32
    //   83: invokestatic 36	o/ED:ˏ	(SIBII)Ljava/lang/String;
    //   86: invokevirtual 42	java/lang/String:intern	()Ljava/lang/String;
    //   89: iconst_1
    //   90: invokespecial 46	o/ED:<init>	(Ljava/lang/String;I)V
    //   93: putstatic 52	o/ED:USER_IDENTIFIED	Lo/ED;
    //   96: new 2	o/ED
    //   99: dup
    //   100: iconst_0
    //   101: ldc 53
    //   103: iconst_0
    //   104: ldc 50
    //   106: bipush -32
    //   108: invokestatic 36	o/ED:ˏ	(SIBII)Ljava/lang/String;
    //   111: invokevirtual 42	java/lang/String:intern	()Ljava/lang/String;
    //   114: iconst_2
    //   115: invokespecial 46	o/ED:<init>	(Ljava/lang/String;I)V
    //   118: putstatic 55	o/ED:USER_NOT_IDENTIFIED	Lo/ED;
    //   121: iconst_3
    //   122: anewarray 2	o/ED
    //   125: dup
    //   126: iconst_0
    //   127: getstatic 48	o/ED:DISPLAY_ENTER_BIRTH_DATE_SCREEN	Lo/ED;
    //   130: aastore
    //   131: dup
    //   132: iconst_1
    //   133: getstatic 52	o/ED:USER_IDENTIFIED	Lo/ED;
    //   136: aastore
    //   137: dup
    //   138: iconst_2
    //   139: getstatic 55	o/ED:USER_NOT_IDENTIFIED	Lo/ED;
    //   142: aastore
    //   143: putstatic 57	o/ED:$VALUES	[Lo/ED;
    //   146: goto -143 -> 3
    // Local variable table:
    //   start	length	slot	name	signature
    //   9	12	0	i	int
    //   28	2	1	localException1	Exception
    //   32	2	1	localException2	Exception
    // Exception table:
    //   from	to	target	type
    //   39	43	28	java/lang/Exception
    //   35	39	32	java/lang/Exception
    //   39	43	32	java/lang/Exception
    //   43	46	32	java/lang/Exception
    //   46	146	32	java/lang/Exception
  }
  
  private ED() {}
  
  static void ˊ()
  {
    ˏ = 31;
    ˋ = new byte[] { 0, 9, 0, -13, 15, -16, -12, 26, -15, 19, -3, -27, 23, -12, 2, 9, 7, -29, 13, 13, -15, 6, 9, -26, 6, 24, -11, -4, -3, 10, 5, -16, -1, -4, 3, -3, -11, 6, 9, 1, -5, -22, 13, 13, -14, -2, -12, -1, -4, 3, -3, -11, 6, 9, 1, -5, -22, 11, 5, 1, -17, 13, 13, -14, -2 };
    ॱ = 869558787;
    ˎ = -593711698;
  }
  
  private static String ˏ(short paramShort, int paramInt1, byte paramByte, int paramInt2, int paramInt3)
  {
    break label336;
    break label133;
    label6:
    paramInt3 = ʽ + 29;
    ʼ = paramInt3 % 128;
    if (paramInt3 % 2 == 0)
    {
      break label106;
      label36:
      if (paramInt2 < paramInt3) {
        break label547;
      }
    }
    int j;
    label54:
    label87:
    label106:
    int k;
    for (;;)
    {
      paramInt1 = j;
      StringBuilder localStringBuilder;
      switch (j)
      {
      default: 
        break label488;
        localStringBuilder.append(i);
        paramInt2 += 1;
        char c = i;
        break;
      case 34: 
        for (;;)
        {
          try
          {
            paramInt3 = ˋ[(ˎ + paramInt1)];
            k = ˏ;
            paramInt3 = (byte)(paramInt3 + k);
            continue;
            label133:
            paramInt1 = paramInt1 + paramInt3 - 2 + k + j;
            i = (char)(ॱ + paramInt2);
            localStringBuilder.append(i);
            paramInt2 = 1;
            k = i;
            break label36;
            j = 1;
            break label554;
            switch (j)
            {
            default: 
              label177:
              break label524;
              localStringBuilder = new StringBuilder();
              j = ˏ + paramInt3;
              paramInt3 = j;
              if (j == -1) {
                continue;
              }
              break label358;
              label240:
              if (ˋ != null) {
                break label6;
              }
              break label339;
              j = 59;
              continue;
              switch (j)
              {
              default: 
                label259:
                break label375;
                localObject = ˋ;
                j = paramInt1 - 1;
                i = (char)(((byte)(localObject[paramInt1] + paramShort) ^ paramByte) + k);
                paramInt1 = j;
                break label87;
              }
              break;
            }
          }
          catch (Exception localException1)
          {
            throw localException1;
          }
          k = 52;
          break label416;
          continue;
          label336:
          continue;
          label339:
          paramInt3 = (short)(ˊ[(ˎ + paramInt1)] + ˏ);
          break label364;
          label358:
          j = 0;
          break label581;
          label364:
          if (paramInt3 > 0) {
            break label565;
          }
          break label524;
          label375:
          j = 0;
          break;
          label381:
          j = 89;
          break label54;
          label388:
          j = 1;
        }
      }
      for (;;)
      {
        j = 0;
        break label133;
        localObject = ˋ;
        if (localObject == null)
        {
          break label381;
          label416:
          switch (k)
          {
          }
          break label240;
        }
        j = 34;
        break;
        j = ʼ;
        j += 113;
        try
        {
          ʽ = j % 128;
          if (j % 2 == 0) {}
        }
        catch (Exception localException2)
        {
          label488:
          throw localException2;
        }
      }
      Object localObject = ˊ;
      j = paramInt1 - 1;
      paramInt1 = localObject[paramInt1];
      int i = (char)(((short)(paramInt1 + paramShort) ^ paramByte) + k);
    }
    label524:
    label541:
    label547:
    label554:
    label565:
    label581:
    label582:
    for (;;)
    {
      k = 5;
      break label416;
      return localException1.toString();
      j = 1;
      break;
      j = 0;
      break label259;
      j = 76;
      break label177;
      for (;;)
      {
        if (j != 0) {
          break label582;
        }
        break;
        k = ˎ;
        if (j != 0) {
          break label541;
        }
        break label388;
      }
    }
  }
}
