package o;

public enum EF
{
  private static int ˊ;
  private static int ˋ;
  private static long ˏ;
  private static char[] ॱ;
  private String mCode;
  private String mMessage;
  
  static
  {
    break label51;
    return;
    throw new NullPointerException();
    int i = 58;
    label15:
    switch (i)
    {
    }
    return;
    for (;;)
    {
      i = 6;
      break label15;
      label51:
      ˊ = 0;
      ˋ = 1;
      ˋ();
      String str1 = ॱ(23, 'ぃ', 6).intern();
      String str3 = ॱ(861, '\000', 6).intern();
      String str2 = ॱ(2760, '\000', 6).intern();
      BTW_TNC_OS_DOESNT_MATCH = new EF(ॱ(0, '\000', 23).intern(), 0, str1, ॱ(29, 'ኍ', 80).intern());
      BTW_SRY_UNKNOWN_SERVER_NONCE = new EF(ॱ(109, '\000', 28).intern(), 1, str1, ॱ(137, '\000', 41).intern());
      BTW_SRY_UNKNOWN_CLIENT_NONCE = new EF(ॱ(178, '\000', 28).intern(), 2, str1, ॱ(206, '\000', 41).intern());
      BTW_TNC_UNKNOWN_TNC = new EF(ॱ(247, '\000', 19).intern(), 3, str1, ॱ(266, 33445, 58).intern());
      BTW_TNC_UNKNOWN_EMAIL = new EF(ॱ(324, '乧', 21).intern(), 4, str1, ॱ(345, '\000', 34).intern());
      BTW_CRD_UNKNOWN_WALLET = new EF(ॱ(379, '\000', 22).intern(), 5, str1, ॱ(401, '\000', 35).intern());
      BTW_CRD_ALREADY_REGISTERED = new EF(ॱ(436, 45539, 26).intern(), 6, str1, ॱ(462, '\000', 38).intern());
      BTW_CRD_CHANNEL_OR_DESTINATION_DONT_MATCH = new EF(ॱ(500, '\000', 41).intern(), 7, str1, ॱ(541, '\000', 82).intern());
      BTW_GENERIC_RUNTIME_EXCEPTION = new EF(ॱ(623, '\000', 29).intern(), 8, ॱ(652, '㕹', 6).intern(), ॱ(658, '\000', 46).intern());
      BTW_CRD_CANNOT_MAKE_CARD_PRESENTMENT_FOR_UNREGISTERED_WALLET = new EF(ॱ(704, 44125, 60).intern(), 9, str1, ॱ(764, 34647, 64).intern());
      BTW_P2P_CANNOT_FIND_CARD_INSTANCE = new EF(ॱ(828, 62350, 33).intern(), 10, str3, ॱ(867, '\000', 45).intern());
      BTW_P2P_CANNOT_FIND_WALLET = new EF(ॱ(912, '\000', 26).intern(), 11, str3, ॱ(938, '\000', 57).intern());
      BTW_CRD_UNKNOWN_CARD_INSTANCE = new EF(ॱ(995, '寉', 29).intern(), 12, str1, ॱ(1024, '\000', 106).intern());
      BTW_CRD_UNKNOWN_CARD_TOKEN = new EF(ॱ(1130, 53755, 26).intern(), 13, str1, ॱ(1156, '\000', 19).intern());
      BTW_CRD_UNKNOWN_FROM_DATE = new EF(ॱ(1175, '\000', 25).intern(), 14, str1, ॱ(1200, '\000', 53).intern());
      BTW_CRD_UNKNOWN_TO_DATE = new EF(ॱ(1253, '䄺', 23).intern(), 15, str1, ॱ(1276, '\000', 51).intern());
      BTW_CRD_FROM_DATE_IN_THE_FUTURE = new EF(ॱ(1327, 'ຝ', 31).intern(), 16, str1, ॱ(1358, '\000', 69).intern());
      BTW_CRD_TO_DATE_IN_THE_FUTURE = new EF(ॱ(1427, '\000', 29).intern(), 17, str1, ॱ(1456, '⼸', 67).intern());
      BTW_CRD_FROM_DATE_CANNOT_BE_AFTER_TO_DATE = new EF(ॱ(1523, '\000', 41).intern(), 18, str1, ॱ(1564, '\000', 68).intern());
      BTW_CRD_UNKNOWN_IMAGE_LOCATION = new EF(ॱ(1632, '\000', 30).intern(), 19, str1, ॱ(1662, '瀅', 28).intern());
      BTW_CRD_UNKNOWN_CARD = new EF(ॱ(1690, '\000', 20).intern(), 20, str1, ॱ(1710, '\000', 42).intern());
      BTW_NO_UNIQUE_IDENTIFIER_FOUND = new EF(ॱ(1752, '\000', 30).intern(), 21, ॱ(1782, '\000', 7).intern(), ॱ(1789, '\000', 39).intern());
      BTW_WLT_APP_INSTANCE_ID_ALREADY_REGISTERED = new EF(ॱ(1828, '⼂', 42).intern(), 22, ॱ(1870, '㊯', 6).intern(), ॱ(1876, '䆶', 103).intern());
      BTW_WLT_NOT_FOUND = new EF(ॱ(1979, 33462, 17).intern(), 23, ॱ(1870, '㊯', 6).intern(), ॱ(1996, 50677, 48).intern());
      BTW_WLT_CANNOT_UPDATE_REGISTERED_WALLET = new EF(ॱ(2044, '\000', 39).intern(), 24, ॱ(1870, '㊯', 6).intern(), ॱ(2083, '\000', 43).intern());
      BTW_TNC_FAILED_TO_SEND_EMAIL = new EF(ॱ(2126, 47448, 28).intern(), 25, ॱ(2154, 'ᑂ', 6).intern(), ॱ(2160, '\000', 46).intern());
      BTW_TNC_UNKNOWN_WALLET = new EF(ॱ(2206, '\000', 22).intern(), 26, ॱ(2154, 'ᑂ', 6).intern(), ॱ(401, '\000', 35).intern());
      BTW_TNC_NOT_FOUND = new EF(ॱ(2228, '\000', 17).intern(), 27, ॱ(2154, 'ᑂ', 6).intern(), ॱ(2245, '\000', 31).intern());
      BTW_WLT_UNKNOWN_WALLET = new EF(ॱ(2276, '\000', 22).intern(), 28, ॱ(2298, '\000', 6).intern(), ॱ(401, '\000', 35).intern());
      BTW_P2P_UNKNOWN_P2P_CARD_INSTANCE_FROM_WRONG_WALLET = new EF(ॱ(2304, '\000', 51).intern(), 29, str3, ॱ(2355, '\000', 48).intern());
      BTW_P2P_UNKNOWN_P2P_CARD_INSTANCE = new EF(ॱ(2403, '\000', 33).intern(), 30, str3, ॱ(2436, '\000', 42).intern());
      BTW_P2P_UNKNOWN_P2P_TRANSACTION = new EF(ॱ(2478, '\000', 31).intern(), 31, str3, ॱ(2509, '\000', 44).intern());
      BTW_P2P_UNKNOWN_P2P_ACCEPTER_WALLET = new EF(ॱ(2553, '䆓', 35).intern(), 32, str3, ॱ(2588, '\000', 51).intern());
      BTW_P2P_UNKNOWN_P2P_ACCEPTER = new EF(ॱ(2639, 41056, 28).intern(), 33, str3, ॱ(2667, 41128, 72).intern());
      BTW_P2P_CANNOT_CANCEL = new EF(ॱ(2739, '\000', 21).intern(), 34, str2, ॱ(2766, '\000', 107).intern());
      BTW_P2P_CANNOT_DECLINE = new EF(ॱ(2873, '\000', 22).intern(), 35, str2, ॱ(2895, '歞', 95).intern());
      BTW_P2P_CANNOT_DECLINE_WITHOUT_REASON = new EF(ॱ(2990, 33296, 37).intern(), 36, str2, ॱ(3027, 53125, 64).intern());
      BTW_P2P_CANNOT_ACKNOWLEDGE = new EF(ॱ(3091, '笰', 26).intern(), 37, str2, ॱ(3117, 41012, 96).intern());
      BTW_P2P_CANNOT_ACCEPT = new EF(ॱ(3213, '\000', 21).intern(), 38, str2, ॱ(3234, '\000', 94).intern());
      BTW_P2P_CANCELER_NOT_INITIATOR = new EF(ॱ(3328, '\000', 30).intern(), 39, str2, ॱ(3358, 39858, 102).intern());
      FEATURE_NOT_IMPLEMENTED = new EF(ॱ(3460, '列', 23).intern(), 40, ॱ(1782, '\000', 7).intern(), ॱ(3483, 47304, 30).intern());
      FEATURE_NOT_ALLOWED = new EF(ॱ(3513, 52998, 19).intern(), 41, ॱ(1782, '\000', 7).intern(), ॱ(3532, 35519, 33).intern());
      INVALID_USER_CREDENTIALS = new EF(ॱ(3565, '䈈', 24).intern(), 42, ॱ(3589, '\000', 4).intern(), ॱ(3593, 52864, 21).intern());
      USER_REQUEST_FAILED = new EF(ॱ(3614, '\000', 19).intern(), 43, ॱ(3633, '\000', 4).intern(), ॱ(3637, '匿', 19).intern());
      BTW_COMMUNICATION_UNKNOWN_CHANNEL = new EF(ॱ(3656, '\000', 33).intern(), 44, ॱ(3689, '沰', 6).intern(), ॱ(3695, '㘼', 30).intern());
      BTW_CARD_NOT_FOUND_BY_UUID = new EF(ॱ(3725, '䁊', 26).intern(), 45, str1, ॱ(3751, 39625, 47).intern());
      BTW_WALLET_NOT_FOUND_BY_AID = new EF(ॱ(3798, 55510, 27).intern(), 46, ॱ(2298, '\000', 6).intern(), ॱ(3825, '\000', 68).intern());
      BTW_COMMUNICATION_INVALID_PHONE_NUMBER = new EF(ॱ(3893, '⮀', 38).intern(), 47, ॱ(3931, 'ណ', 6).intern(), ॱ(3937, '\000', 105).intern());
      BTW_COMMUNICATION_INVALID_EMAIL = new EF(ॱ(4042, '梣', 31).intern(), 48, ॱ(4073, '\000', 6).intern(), ॱ(4079, '⹊', 99).intern());
      BTW_COMMUNICATION_FAILED_TO_SEND_EMAIL = new EF(ॱ(4178, '\000', 38).intern(), 49, ॱ(4073, '\000', 6).intern(), ॱ(4216, '㉗', 21).intern());
      BTW_COMMUNICATION_FAILED_TO_SEND_SMS = new EF(ॱ(4237, '⾖', 36).intern(), 50, ॱ(4073, '\000', 6).intern(), ॱ(4273, '\000', 19).intern());
      BTW_OTP_UNKNOWN_OTP_TRANSACTION = new EF(ॱ(4292, '\000', 31).intern(), 51, ॱ(4323, '\000', 6).intern(), ॱ(4329, '\000', 44).intern());
      BTW_OTP_UNEXPECTED_NULL_SCOPE = new EF(ॱ(4373, '䉼', 29).intern(), 52, ॱ(4323, '\000', 6).intern(), ॱ(4402, 55104, 38).intern());
      BTW_OTP_UNEXPECTED_NULL_CHANNEL = new EF(ॱ(4440, '⩴', 31).intern(), 53, ॱ(4323, '\000', 6).intern(), ॱ(4471, 38958, 54).intern());
      BTW_OTP_UNEXPECTED_NULL_DESTINATION = new EF(ॱ(4525, 58984, 35).intern(), 54, ॱ(4323, '\000', 6).intern(), ॱ(4560, 52678, 58).intern());
      BTW_OTP_UNKNOWN_OTP_SCOPED_COUNTER = new EF(ॱ(4618, 39946, 34).intern(), 55, ॱ(4652, '珆', 6).intern(), ॱ(4658, '氕', 47).intern());
      BTW_OTP_NULL_OTP_COUNTER = new EF(ॱ(4705, '\000', 24).intern(), 56, ॱ(4652, '珆', 6).intern(), ॱ(4658, '氕', 47).intern());
      BTW_P2P_AMBIGUOUS_TRANSACTION_STATUS = new EF(ॱ(4729, '\000', 36).intern(), 57, str3, ॱ(4765, 54144, 98).intern());
      BTW_OTP_INCORRECT_ENTERED_OTP = new EF(ॱ(4863, '\000', 29).intern(), 58, ॱ(4892, '\000', 9).intern(), ॱ(4901, '毰', 23).intern());
      BTW_OTP_ENTER_EXPIRED_OTP = new EF(ॱ(4924, '緢', 25).intern(), 59, ॱ(4949, 49005, 11).intern(), ॱ(4329, '\000', 44).intern());
      BTW_OTP_ENTER_EXCEEDED_THRESHOLD = new EF(ॱ(4960, '\000', 32).intern(), 60, ॱ(4992, 38096, 11).intern(), ॱ(5003, '\000', 74).intern());
      BTW_PERSISTENCE_NULL_ENTITY = new EF(ॱ(5077, 60712, 27).intern(), 61, ॱ(5104, 52892, 5).intern(), ॱ(5109, '\000', 29).intern());
      BTW_PERSISTENCE_NULL_UUID = new EF(ॱ(5138, '攨', 25).intern(), 62, ॱ(5104, 52892, 5).intern(), ॱ(5109, '\000', 29).intern());
      BTW_SECURITY_NO_SUCH_ALGORITHM = new EF(ॱ(5163, 50588, 30).intern(), 63, ॱ(5104, 52892, 5).intern(), ॱ(5193, '\000', 82).intern());
      BTW_SECURITY_INVALID_KEY = new EF(ॱ(5275, '䊌', 24).intern(), 64, ॱ(5104, 52892, 5).intern(), ॱ(5299, '\000', 140).intern());
      BTW_NULL_PRODUCT_CODE = new EF(ॱ(5439, '\000', 21).intern(), 65, ॱ(5460, 46618, 5).intern(), ॱ(5465, 36845, 34).intern());
      BTW_NULL_P2P_TRANSACTION_TYPE = new EF(ॱ(5499, '\000', 29).intern(), 66, ॱ(5528, '\000', 6).intern(), ॱ(5534, '䨥', 42).intern());
      BTW_NULL_AMOUNT = new EF(ॱ(5576, 54137, 15).intern(), 67, ॱ(5591, 'ఔ', 6).intern(), ॱ(5597, 'ᬫ', 28).intern());
      BTW_CRD_NULL_ENTITY = new EF(ॱ(5625, '\000', 19).intern(), 68, ॱ(5644, '\000', 6).intern(), ॱ(5650, 37232, 33).intern());
      BTW_SECURITY_NULL_SECURITY_CONTEXT = new EF(ॱ(5683, '\000', 34).intern(), 69, ॱ(5717, '\000', 6).intern(), ॱ(5723, '\000', 98).intern());
      BTW_PERSISTENCE_NULL_PARENT = new EF(ॱ(5821, 49249, 27).intern(), 70, ॱ(5848, 'ᑇ', 5).intern(), ॱ(5853, 63331, 56).intern());
      BTW_NULL_CURRENCY = new EF(ॱ(5909, '\000', 17).intern(), 71, ॱ(5926, '\000', 6).intern(), ॱ(5932, 63484, 30).intern());
      BTW_FORM_INVALID_CODE = new EF(ॱ(5962, '\000', 21).intern(), 72, ॱ(5983, 37294, 4).intern(), ॱ(5987, '\000', 12).intern());
      BTW_FORM_INVALID_TYPE = new EF(ॱ(5999, 37940, 21).intern(), 73, ॱ(6020, '\000', 5).intern(), ॱ(6025, '\000', 12).intern());
      BTW_FORM_INVALID_RENDER_TYPE = new EF(ॱ(6037, '\000', 28).intern(), 74, ॱ(6065, '\000', 4).intern(), ॱ(6069, '\000', 19).intern());
      BTW_INACTIVE_WALLET = new EF(ॱ(6088, 50962, 19).intern(), 75, ॱ(6107, '\000', 11).intern(), ॱ(6118, 45639, 31).intern());
      BTW_COMMUNICATION_CHANNELS_EXPIRED = new EF(ॱ(6149, 'ヱ', 34).intern(), 76, ॱ(6183, 61642, 11).intern(), ॱ(6194, '㊣', 48).intern());
      DF_PUBLISHING_NULL_TBP_UUID = new EF(ॱ(6242, '\000', 27).intern(), 77, ॱ(6269, '\000', 4).intern(), ॱ(6273, '\000', 66).intern());
      DF_PUBLISHING_INVALID_TBP_UUID = new EF(ॱ(6339, '䚑', 30).intern(), 78, ॱ(6369, '\000', 4).intern(), ॱ(6373, 'ඊ', 81).intern());
      DF_PUBLISHING_INVALID_TBP_FORM_UUID = new EF(ॱ(6454, '\000', 35).intern(), 79, ॱ(6489, '㢾', 4).intern(), ॱ(6493, '繹', 82).intern());
      DF_PUBLISHING_CORRUPTED_TBP_UUID = new EF(ॱ(6575, 59907, 32).intern(), 80, ॱ(6369, '\000', 4).intern(), ॱ(6607, '巸', 160).intern());
      DF_FETCH_FROM_VP_FAILED = new EF(ॱ(6767, 35936, 23).intern(), 81, ॱ(6790, '˽', 4).intern(), ॱ(6794, '\000', 42).intern());
      CARD_ALREADY_REGISTERED = new EF(ॱ(6836, '\000', 23).intern(), 82, ॱ(6859, '\000', 11).intern(), ॱ(6870, '\000', 33).intern());
      BLACKLISTED_DEVICE = new EF(ॱ(6903, '\000', 18).intern(), 83, ॱ(6921, '殫', 11).intern(), ॱ(6932, 64534, 22).intern());
      BLACKLISTED_MOBILE_APP_VERSION = new EF(ॱ(6954, '嘶', 30).intern(), 84, ॱ(6984, 56053, 11).intern(), ॱ(6995, '埦', 34).intern());
      MULTIPLE_WALLETS = new EF(ॱ(7029, '\000', 16).intern(), 85, ॱ(5644, '\000', 6).intern(), ॱ(7045, '\000', 35).intern());
      $VALUES = new EF[] { BTW_TNC_OS_DOESNT_MATCH, BTW_SRY_UNKNOWN_SERVER_NONCE, BTW_SRY_UNKNOWN_CLIENT_NONCE, BTW_TNC_UNKNOWN_TNC, BTW_TNC_UNKNOWN_EMAIL, BTW_CRD_UNKNOWN_WALLET, BTW_CRD_ALREADY_REGISTERED, BTW_CRD_CHANNEL_OR_DESTINATION_DONT_MATCH, BTW_GENERIC_RUNTIME_EXCEPTION, BTW_CRD_CANNOT_MAKE_CARD_PRESENTMENT_FOR_UNREGISTERED_WALLET, BTW_P2P_CANNOT_FIND_CARD_INSTANCE, BTW_P2P_CANNOT_FIND_WALLET, BTW_CRD_UNKNOWN_CARD_INSTANCE, BTW_CRD_UNKNOWN_CARD_TOKEN, BTW_CRD_UNKNOWN_FROM_DATE, BTW_CRD_UNKNOWN_TO_DATE, BTW_CRD_FROM_DATE_IN_THE_FUTURE, BTW_CRD_TO_DATE_IN_THE_FUTURE, BTW_CRD_FROM_DATE_CANNOT_BE_AFTER_TO_DATE, BTW_CRD_UNKNOWN_IMAGE_LOCATION, BTW_CRD_UNKNOWN_CARD, BTW_NO_UNIQUE_IDENTIFIER_FOUND, BTW_WLT_APP_INSTANCE_ID_ALREADY_REGISTERED, BTW_WLT_NOT_FOUND, BTW_WLT_CANNOT_UPDATE_REGISTERED_WALLET, BTW_TNC_FAILED_TO_SEND_EMAIL, BTW_TNC_UNKNOWN_WALLET, BTW_TNC_NOT_FOUND, BTW_WLT_UNKNOWN_WALLET, BTW_P2P_UNKNOWN_P2P_CARD_INSTANCE_FROM_WRONG_WALLET, BTW_P2P_UNKNOWN_P2P_CARD_INSTANCE, BTW_P2P_UNKNOWN_P2P_TRANSACTION, BTW_P2P_UNKNOWN_P2P_ACCEPTER_WALLET, BTW_P2P_UNKNOWN_P2P_ACCEPTER, BTW_P2P_CANNOT_CANCEL, BTW_P2P_CANNOT_DECLINE, BTW_P2P_CANNOT_DECLINE_WITHOUT_REASON, BTW_P2P_CANNOT_ACKNOWLEDGE, BTW_P2P_CANNOT_ACCEPT, BTW_P2P_CANCELER_NOT_INITIATOR, FEATURE_NOT_IMPLEMENTED, FEATURE_NOT_ALLOWED, INVALID_USER_CREDENTIALS, USER_REQUEST_FAILED, BTW_COMMUNICATION_UNKNOWN_CHANNEL, BTW_CARD_NOT_FOUND_BY_UUID, BTW_WALLET_NOT_FOUND_BY_AID, BTW_COMMUNICATION_INVALID_PHONE_NUMBER, BTW_COMMUNICATION_INVALID_EMAIL, BTW_COMMUNICATION_FAILED_TO_SEND_EMAIL, BTW_COMMUNICATION_FAILED_TO_SEND_SMS, BTW_OTP_UNKNOWN_OTP_TRANSACTION, BTW_OTP_UNEXPECTED_NULL_SCOPE, BTW_OTP_UNEXPECTED_NULL_CHANNEL, BTW_OTP_UNEXPECTED_NULL_DESTINATION, BTW_OTP_UNKNOWN_OTP_SCOPED_COUNTER, BTW_OTP_NULL_OTP_COUNTER, BTW_P2P_AMBIGUOUS_TRANSACTION_STATUS, BTW_OTP_INCORRECT_ENTERED_OTP, BTW_OTP_ENTER_EXPIRED_OTP, BTW_OTP_ENTER_EXCEEDED_THRESHOLD, BTW_PERSISTENCE_NULL_ENTITY, BTW_PERSISTENCE_NULL_UUID, BTW_SECURITY_NO_SUCH_ALGORITHM, BTW_SECURITY_INVALID_KEY, BTW_NULL_PRODUCT_CODE, BTW_NULL_P2P_TRANSACTION_TYPE, BTW_NULL_AMOUNT, BTW_CRD_NULL_ENTITY, BTW_SECURITY_NULL_SECURITY_CONTEXT, BTW_PERSISTENCE_NULL_PARENT, BTW_NULL_CURRENCY, BTW_FORM_INVALID_CODE, BTW_FORM_INVALID_TYPE, BTW_FORM_INVALID_RENDER_TYPE, BTW_INACTIVE_WALLET, BTW_COMMUNICATION_CHANNELS_EXPIRED, DF_PUBLISHING_NULL_TBP_UUID, DF_PUBLISHING_INVALID_TBP_UUID, DF_PUBLISHING_INVALID_TBP_FORM_UUID, DF_PUBLISHING_CORRUPTED_TBP_UUID, DF_FETCH_FROM_VP_FAILED, CARD_ALREADY_REGISTERED, BLACKLISTED_DEVICE, BLACKLISTED_MOBILE_APP_VERSION, MULTIPLE_WALLETS };
      i = ˋ + 109;
      ˊ = i % 128;
      if (i % 2 != 0) {
        break;
      }
    }
  }
  
  static void ˋ()
  {
    ˏ = 9169334431207799431L;
    ॱ = new char[] { 66, 15059, 30041, -20534, -5560, 9453, 24425, -26130, -11145, 3820, 18713, -31863, -16869, -1890, 13105, 28071, -22492, -7512, 7475, 22596, -27944, -12976, 2002, 12288, 2710, 17673, -24602, -9617, 5329, 4802, 10329, 26531, -17026, -1821, 13889, 19914, -29924, -14623, 7255, 23481, -28371, -21334, -5514, 8590, 32522, -17767, -4006, 4016, 19175, -32657, -8198, 5502, 20696, 28236, -23091, -7339, 16067, 29801, -19550, -14032, 1201, 16926, -26236, -10428, 4748, 10321, 26467, -23834, -1944, 14326, 19834, -30581, -14764, 7633, 23379, -26897, -21493, -5234, 8570, 31925, -17894, -3698, 3859, 19159, -32264, -8339, 6887, 20539, 28615, -23224, -7990, 15955, 30161, -19655, -12563, 1072, 17400, -26347, -11125, 4625, 10645, 26390, -23913, -1621, 14153, 29431, -30608, -14400, 7434, 66, 15059, 30041, -20534, -5553, 9457, 24435, -26130, -11155, 3825, 18701, -31869, -16869, -1908, 13100, 28086, -22493, -7502, 7468, 22611, -27959, -12991, 1989, 17007, 31975, -18591, -3595, 11384, 69, 15081, 30061, -20486, -5527, 9421, 24414, -26156, -11190, 3802, 18722, -31763, -16863, -1867, 13063, 28049, -22528, -7534, 7453, 22641, -27927, -12937, 1978, 17007, 31997, -18589, -3590, 11293, 26263, -24274, -9312, 5679, 20613, -29931, -14898, 59, 14995, 30189, -20375, -5388, 9526, 66, 15059, 30041, -20534, -5553, 9457, 24435, -26130, -11155, 3825, 18701, -31869, -16869, -1908, 13100, 28086, -22477, -7493, 7479, 22592, -27966, -12985, 1989, 17007, 31975, -18591, -3595, 11384, 69, 15081, 30061, -20486, -5527, 9421, 24414, -26156, -11190, 3802, 18722, -31763, -16863, -1867, 13063, 28049, -22528, -7534, 7453, 22641, -27927, -12937, 1978, 17007, 31997, -18589, -3590, 11293, 26247, -24281, -9285, 5692, 20622, -29933, -14898, 59, 14995, 30189, -20375, -5388, 9526, 66, 15059, 30041, -20534, -5560, 9453, 24425, -26130, -11155, 3825, 18701, -31869, -16869, -1908, 13100, 28086, -22492, -7495, 7485, -32032, -18356, -2104, 11615, 26828, -22936, -8709, 7025, 22255, -29569, -13433, 328, 15492, 31248, -20062, -4300, 10917, 24631, -24648, -9516, 4172, 20434, -31457, -16182, -424, 13766, 29535, -20808, -7116, 9147, 22846, -27464, -11675, 2468, 18212, -32094, -18311, -2190, 13002, 26694, -22576, -8887, 6307, 22121, -29185, -13446, 1735, 15407, 31642, -20196, -4961, 10793, 25021, -24769, -9552, 4554, 20318, -30076, 20005, 29876, 15166, -7763, -23505, 27274, 4366, -10359, -26102, 16534, 1898, -12828, -3972, -18709, 32075, 9169, -6574, -21283, 21336, 5675, -9049, 69, 15081, 30061, -20486, -5527, 9421, 24414, -26156, -11190, 3802, 18722, -31763, -16863, -1867, 13063, 28049, -22528, -7534, 7453, 22641, -27927, -12937, 1978, 17007, 31997, -18589, -3590, 11293, 26241, -24314, -9293, 5680, 20620, -29879, 66, 15059, 30041, -20534, -5537, 9457, 24430, -26130, -11155, 3825, 18701, -31869, -16869, -1908, 13100, 28086, -22489, -7498, 7474, 22601, -27959, -12985, 69, 15081, 30061, -20486, -5527, 9421, 24414, -26156, -11190, 3802, 18722, -31763, -16863, -1867, 13063, 28049, -22528, -7534, 7453, 22641, -27927, -12937, 1978, 17007, 31997, -18589, -3590, 11293, 26259, -24278, -9282, 5685, 20613, -29933, -14912, -20063, -29904, -15174, 7721, 23484, -27374, -4467, 10253, 26010, -16624, -1801, 12907, 4086, 18812, -32040, -9131, 6593, 21329, -21286, -5713, 9020, 31908, -18884, -3184, -13042, 1672, 67, 15078, 30076, -20495, -5572, 9410, 24390, -26173, -11171, 3806, 18722, -31820, -16780, -1879, 13063, 28046, -22503, -7548, 7434, 22624, -27906, -12938, 2046, 16897, 31964, -18624, -3690, 11337, 26284, -24274, -9230, 5646, 20609, -29941, -14974, 16, 14984, 30125, 66, 15059, 30041, -20534, -5537, 9457, 24430, -26130, -11141, 3831, 18695, -31869, -16870, -1890, 13102, 28086, -22465, -7515, 7457, 22593, -27959, -12992, 1998, 17000, 31974, -18578, -3614, 11380, 26251, -24315, -9331, 5661, 20655, -29911, -14918, 42, 15025, 30146, -20386, -5422, 9552, 67, 15080, 30051, -20488, -5527, 9421, 24387, -26158, -11175, 3787, 18735, -31838, -16838, -1797, 13089, 28033, -22511, -7527, 7440, 22624, -27936, -13005, 2043, 16975, 31948, -18688, -3623, 11343, 26340, -24305, -9289, 5674, 20628, -29938, -14976, 20, 14984, 30186, -20379, -5377, 9528, 24571, -26039, -11064, 3911, 18901, -31643, -16707, -1680, 13242, 28223, -22383, -7409, 7579, 22618, -27786, -12831, 2171, 17150, 32061, -18480, -3517, 11479, 26393, -24142, -9182, 5801, 20796, -29777, -14825, 143, 15107, 30109, -20453, -5338, 9690, 24693, -25865, -10930, 4044, 19012, -31591, 66, 15059, 30041, -20534, -5541, 9446, 24420, -26124, -11158, 3830, 18693, -31854, -16890, -1906, 13100, 28093, -22471, -7494, 7483, 22618, -27959, -12981, 2009, 16996, 31992, -18565, -3585, 11378, 26250, 13611, 4016, 16419, -25892, -8363, 4587, 82, 15090, 30048, -20511, -5515, 9422, 24399, -26223, -11139, 3783, 18725, -31832, -16860, -1873, 13067, 28038, -22498, -7465, 7441, 22630, -27921, -12954, 2024, 16979, 31949, -18613, -3690, 11353, 26289, -24263, -9285, 5687, 20615, -29881, -14950, 29, 15001, 30115, -20358, -5405, 9591, 24572, -26045, -11042, 3911, 18837, -21473, -26994, -9980, 919, 17922, -30548, -3277, 13747, 30758, -23901, -6827, 12254, 4678, 21714, -24736, -15879, 1132, 20193, -20122, -3065, 16018, 24847, -21611, -4552, -12118, 6946, 23993, -32731, -13622, 3411, 30657, -17840, -784, 10111, 27133, -21380, -26882, -9832, 7192, 18078, -30438, -3177, 13877, 30882, -23764, -6751, 10326, 4807, 21849, -24625, -15791, 1277, 20341, -19983, -2960, 16157, 24985, -23522, -4466, -12012, -30956, -16975, -3529, 10412, 27940, -23680, -10147, 7819, 21262, -30333, -12684, 1210, 14656, 32749, -19385, -5414, 12039, 26096, -26021, -8393, 5544, 18977, -32605, -15102, -1134, 12317, 30351, -21730, -7757, 9850, 23786, -28292, -10345, 3175, 17112, -30898, -16953, -3407, 14121, 28134, -24008, -10080, 7448, 21401, -30709, -12596, 892, 14829, 32295, -19218, -5786, 12230, 25627, -25898, -8376, 5169, 19126, -28885, -14923, -1489, 12417, 29977, -21631, -8128, -3124, -13987, -31017, 23620, 6594, -10465, -21260, 27232, 10229, -656, -17786, 28685, 19861, 2817, -16205, -25055, 23479, 4407, -4428, -21548, 24897, 16092, -3002, -19989, -28807, 17640, 630, -8224, -27362, 21124, 10258, -6764, -23765, 80, 15029, 30046, -20571, -5588, 9362, 67, 15078, 30048, -20485, -5517, 9431, 24330, -26153, -11183, 3793, 18722, -31763, -16873, -1862, 13072, 28045, -22448, -7490, 7440, 22646, -27912, -12942, 2036, 16962, 31949, -18673, -3632, 11346, 26294, -24213, -9306, 5681, 20613, -29881, -14967, 28, 14986, 30182, -20380, -5455, 9549, 24522, -26001, -11031, 3866, 66, 15059, 30041, -20534, -5556, 9361, 24442, -26130, -11141, 3838, 18696, -31869, -16869, -1905, 13117, 28079, -22471, -7495, 7482, 22618, -27941, -12974, 2006, 17005, 31981, -18565, 67, 15078, 30048, -20485, -5517, 9431, 24330, -26153, -11183, 3793, 18722, -31763, -16893, -1862, 13070, 28037, -22507, -7549, 7518, 22627, -27933, -12959, 1978, 16981, 31936, -18614, -3690, 11354, 26285, -24259, -9289, 5687, 20672, -29914, -14946, 5, 14992, 30186, -20375, -5392, 9580, 24566, -26039, -11069, 3860, 18930, -31700, -16710, -1756, 13238, 28208, -22394, -7415, 7635, 22579, -27835, -12890, 23435, 24858, 11920, -3069, -20074, 32568, 1191, -15833, -28764, 21816, 4804, -10166, -6702, -23739, 26853, 13951, -3078, -18049, 18149, 904, -14054, -26989, 23581, 6587, 10037, -4953, -21967, 30647, 15688, 85, 15081, 30053, -20485, -5517, 9428, 24388, -26223, -11141, 3806, 18740, -31831, -16780, -1902, 13068, 28058, -22524, -7530, 7440, 22630, -27927, -13005, 2044, 16974, 31962, -18673, -3642, 11343, 26283, -24259, -9285, 5693, 20613, -29949, -14898, 34, 15005, 30191, -20378, -5388, 9580, 24497, -26106, -11011, 3928, 18910, -31709, -16710, -1739, 13303, 28206, -22377, -7421, 7557, 22547, -27803, -12819, 2095, 17143, 32061, -18489, -3510, 11456, 26461, -24096, -9165, 5798, 20788, -29784, -14781, 131, 15106, 30168, -20450, -5270, 9727, 24689, -25862, -10938, 4048, 18960, -31547, -16549, -1630, 13349, 28320, -22226, -7292, 7706, 22666, -27886, -12835, 2288, 17252, 32178, -18323, -3384, 11586, 26510, -23966, -8995, 5935, 20902, -29644, -14676, 369, -11847, -5336, -23390, 32305, 15268, -2806, -29035, 18453, 1430, -8438, -26378, 21112, 28640, 10615, -7465, -17331, 31176, 13133, -13097, -30278, 17192, 7356, -10706, -27759, -21226, 26266, 85, 15081, 30053, -20485, -5517, 9428, 24388, -26223, -11141, 3806, 18740, -31831, -16780, -1905, 13069, 28034, -22507, -7527, 7504, 66, 15059, 30041, -20534, -5537, 9457, 24430, -26130, -11155, 3825, 18701, -31869, -16869, -1908, 13100, 28086, -22474, -7515, 7473, 22600, -27949, -12969, 2011, 17013, 31981, 85, 15081, 30053, -20485, -5517, 9428, 24388, -26223, -11138, 3789, 18729, -31840, -16780, -1889, 13059, 28061, -22507, -7465, 7433, 22637, -27931, -12929, 2047, 16897, 31950, -18614, -3646, 11358, 26284, -24286, -9284, 5694, 20672, -29873, -14931, 20, 14990, 30183, -20445, -5455, 9548, 24557, -26041, -11069, 3911, 18906, -31711, -16707, -1735, 13240, 28208, -22378, -7358, 16760, 31721, 13411, -4368, -21659, 26059, 7764, -10028, -27305, 20427, 2103, -15687, -223, -17994, 29206, 11404, -5858, -23678, 23579, 6523, -11273, -29571, 18149, 85, 15081, 30053, -20485, -5517, 9428, 24388, -26223, -11156, 3792, 18790, -31863, -16843, -1873, 13063, 28105, -22521, -7521, 7447, 22633, -27927, -13005, 2044, 16964, 31964, -18612, -3618, 11348, 26282, -24276, -9230, 5745, 20643, -29946, -14948, 17, 15061, 30115, -20386, -5405, 9593, 24561, -26027, -11060, 3927, 18895, -31701, -16730, -1730, 13220, 28272, 3807, 13390, 31684, -24233, -6974, 10860, 20979, -26765, -9501, 112, 18324, -29411, -20330, -2558, 15806, 25376, -22872, -5067, 5034, 22230, -25522, -15398, 2383, 19705, 29290, -17932, -130, 8948, 26636, -20604, -10998, 70, 15093, 30049, -20488, -5572, 9447, 24395, -26171, -11171, 3743, 18725, -31828, -16838, -1867, 13069, 28061, -22448, -7531, 7451, 22565, -27931, -12931, 1978, 16981, 31936, -18614, -3690, 11355, 26289, -24257, -9305, 5675, 20613, -29881, -14951, 29, 14997, 30191, -20369, -5455, 9598, 24570, -26030, -11058, 3932, 18898, -31700, -16722, -1680, 13311, 28189, -22396, -7394, 7575, 22611, -27871, -12836, 2173, 17143, 32115, -18473, -3510, 11473, 26445, -24151, -9176, 5792, 20774, -29710, 66, 15059, 30041, -20534, -5537, 9457, 24430, -26130, -11156, 3824, 18713, -31863, -16875, -1905, 13095, 28086, -22471, -7495, 7457, 22609, -27964, -12970, 1989, 16999, 31997, -18565, -3613, 11375, 26241, 12140, 5584, 23062, -32535, -15035, 3055, 28791, -18775, -1181, 8678, 26128, -21349, -28413, -10345, 7290, 17075, -30931, -12817, 12847, 30547, -17004, -7585, 10442, 28028, 21424, -26511, -8453, 881, 18825, -29183, -2929, 14657, 32687, -23497, -5441, 12065, 5537, 23195, -24748, -14900, 2644, 28868, -19082, -1028, 8290, 26340, -21670, -28199, -10709, 7310, 16660, -30791, -13187, 13035, 30486, -17333, -7471, 10073, 28125, 21060, -26369, -8857, 995, 18542, -29034, -3316, 14808, 66, 15059, 30041, -20534, -5537, 9457, 24430, -26130, -11138, 3821, 18697, -31872, -16885, -1889, 13091, 28093, -22475, -7512, 7485, 22596, -27966, -12963, 2005, 17013, 31991, -18579, -3597, 11362, 26245, -24307, -9338, 5660, 20658, -29896, -14918, 58, 15011, 30151, -20405, -5435, 9565, 84, 15080, 29998, -20527, -5507, 9431, 24399, -26223, -11173, 3806, 18728, -31837, -16837, -1873, 13122, 28057, -22526, -7534, 7453, 22624, -27928, -12938, 1978, 16999, 31962, -18624, -3621, 11293, 26240, -24278, -9306, 5692, 20672, -29936, -14970, 28, 14992, 30182, -20438, -5385, 9597, 24555, -26043, -11067, 3933, 18901, -31707, -16663, -1672, 13204, 28223, -22377, -7416, 7642, 22618, -27819, -12806, 2158, 17144, 32110, -18491, -3512, 11462, 26448, -24145, -9175, 5821, 20859, 66, 15059, 30041, -20534, -5537, 9457, 24430, -26130, -11155, 3825, 18701, -31869, -16869, -1908, 13100, 28086, -22471, -7494, 7487, 22594, -27959, -12980, 2006, 17006, 31979, -18578, -3614, 11380, 26251, -24315, 28752, 19180, 1376, -8194, -25994, 21713, 12097, -5740, -23426, 32475, 14641, -3156, -12687, -30569, 17162, 7565, -10222, -28009, 27995, 10316, -7450, -17035, 30718, 12880, 3268, -14523, -32291, 23574, 66, 15059, 30041, -20534, -5537, 9457, 24430, -26130, -11155, 3825, 18701, -31869, -16869, -1908, 13100, 28086, -22477, -7498, 7468, 22593, 85, 15081, 30053, -20485, -5517, 9428, 24388, -26223, -11141, 3806, 18740, -31831, -16774, -1797, 13106, 28037, -22507, -7530, 7437, 22624, -27988, -12957, 2024, 16974, 31966, -18618, -3630, 11352, 26340, -24278, -9230, 5679, 20609, -29941, -14969, 17, 15068, 30144, -20373, -5405, 9596, 24497, 66, 15059, 30041, -20534, -5550, 9452, 24437, -26140, -11146, 3830, 18711, -31848, -16879, -1916, 13099, 28077, -22475, -7495, 7466, 22604, -27958, -12966, 2015, 17011, 31991, -18583, -3591, 11368, 26250, -24305, 87, 15051, 30042, -20571, -5588, 9363, 24346, 78, 15080, 29998, -20512, -5518, 9418, 24411, -26172, -11171, 3743, 18735, -31831, -16847, -1867, 13078, 28032, -22506, -7522, 7451, 22647, -27988, -12939, 2037, 16980, 31942, -18613, -3690, 11285, 26273, -24219, -9291, 5751, 20672, -29902, -14917, 60, 15032, 30122, -20444, 12096, 5585, 23131, -32568, -15031, 3053, 28796, -18708, -1157, 8685, 26132, -21360, -28385, -10345, 7219, 17087, -30925, -12869, 12863, 30530, -16943, -7592, 10460, 28028, 21483, -26527, -8474, 890, 18823, -29171, -2935, 14596, 32688, -23520, -5461, 12094, 5549, 23253, -24755, -14911, 2655, 28889, 13053, 2157, 18406, -25334, -10109, 5693, 16885, 31568, 13526, -4531, -21563, 25953, 7868, -10121, -27140, 20332, 2178, -15842, -123, -18172, 29351, 11307, -5725, -23757, 23784, 6610, -11494, -29454, 17997, 1019, 15730, -2308, -20364, 28075, 10004, -8046, -26090, 22479, 4386, -13639, -31683, 16867, 31533, 13404, -3638, -21694, 25792, 7689, -9263, -27285, 20210, 2145, -14947, -228, -18297, 29205, 12161, -5828, -23884, 23653, 6533, -11559, -29619, 18893, 833, 15557, -2447, -19464, 27940, 9926, -8142, -25123, 22360, 4226, -13799, -30731, 16680, 31407, 13355, -3653, -21803, 25627, 8651, -9378, -27468, 20094, 3050, -14989, -275, -18414, 30110, 12060, -5940, -24010, 24574, 6414, -11615, -29657, 18782, 728, 15440, -1649, -19600, 27902, 9834, -7261, -25245, 22145, 4178, -32012, -18331, -2065, 11644, 26877, -22951, -8760, 7000, 22208, -29626, -13404, 292, 15524, 31266, -20095, -4335, 10882, -14922, -237, -20331, 27150, 12166, -7902, -25857, 23586, 4516, -13532, -29481, 17944, 31680, 15680, -2322, -22468, 28114, 10083, -10009, -25188, 22300, 2194, -15793, -30798, -18126, 29352, 13411, -5700, -23719, 25819, 7687, -11317, -27268, 20196, 126, -14866, -215, -20417, 30107, 12033, -8061, -26082, 24506, 4414, -13656, -29653, 16837, 31506, 66, 15059, 30041, -20534, -5557, 9455, 24446, -26130, -11141, 3838, 18696, -31869, -16869, -1905, 13117, 28092, -22496, -7501, 7487, 22609, -27959, -12980, 1992, 16996, 31983, -18586, -3611, 11369, 26241, -24295, -9321, 5661, 20671, -29904, -14929, 57, 15024, 30150, -20386, 67, 15078, 30048, -20485, -5517, 9431, 24330, -26172, -11192, 3803, 18727, -31815, -16847, -1797, 13059, 28039, -22448, -7530, 7442, 22647, -27927, -12942, 2046, 16984, 31880, -18595, -3629, 11354, 26285, -24264, -9306, 5692, 20626, -29950, -14966, 85, 15019, 30178, -20378, -5379, 9597, 24555, -26104, -18150, -31861, -13311, 5778, 21264, -25163, -6607, 8374, 27942, -18522, -4009, 15065, 1865, 16839, -30107, -11035, 4455, 23536, -23435, -7912, 11162, 29711, -16739, -1220, -14915, 3638, 18599, -27351, 5142, 11915, 24847, -17433, -402, 12496, 70, 15078, 30055, -20487, -5511, 9415, 24330, -26171, -11177, 3743, 18741, -31832, -16838, -1857, 13122, 28093, -22507, -7547, 7443, 22646, -27988, -12942, 2036, 16965, 31880, -18580, -3623, 11347, 26272, -24286, -9306, 5680, 20623, -29943, -14947, 85, 14986, 30186, -20373, -5455, 9565, 24530, -26041, -11068, 3928, 18837, 66, 15059, 30041, -20534, -5560, 9453, 24425, -26130, -11155, 3825, 18701, -31869, -16869, -1908, 13100, 28086, -22489, -7498, 7474, 22601, -27959, -12985, 66, 15059, 30041, -20534, -5560, 9453, 24425, -26130, -11146, 3824, 18706, -31854, -16878, -1900, 13111, 28071, -22476, 84, 15074, 30076, -20488, -5521, 9347, 24395, -26145, -11172, 3743, 18693, -31838, -16838, -1857, 13067, 28061, -22503, -7528, 7440, 22646, -27988, -12931, 2037, 16981, 31880, -18615, -3623, 11336, 26282, -24273, -9220, 66, 15059, 30041, -20534, -5557, 9455, 24446, -26130, -11155, 3825, 18701, -31869, -16869, -1908, 13100, 28086, -22489, -7498, 7474, 22601, -27959, -12985, 87, 15051, 30042, -20571, -5588, 9362, 66, 15059, 30041, -20534, -5556, 9361, 24442, -26130, -11155, 3825, 18701, -31869, -16869, -1908, 13100, 28086, -22496, -7483, 7470, 22618, -27953, -12974, 1992, 16997, 31991, -18586, -3592, 11374, 26256, -24310, -9316, 5658, 20645, -29896, -14936, 39, 15027, 30158, -20395, -5434, 9546, 24528, -26008, -11030, 3947, 18924, -31741, -16763, -1764, 13202, 28170, 69, 15081, 30061, -20486, -5527, 9421, 24414, -26156, -11190, 3802, 18722, -31763, -16843, -1797, 13089, 28040, -22526, -7533, 7518, 22604, -27934, -12960, 2030, 16960, 31942, -18612, -3629, 11293, 26274, -24263, -9283, 5684, 20672, -29946, -14898, 2, 14990, 30188, -20380, -5386, 9528, 24520, -26041, -11071, 3928, 18910, -31690, -16665, 66, 15059, 30041, -20534, -5556, 9361, 24442, -26130, -11155, 3825, 18701, -31869, -16869, -1908, 13100, 28086, -22496, -7483, 7470, 22618, -27953, -12974, 1992, 16997, 31991, -18586, -3592, 11374, 26256, -24310, -9316, 5658, 20645, 69, 15081, 30061, -20486, -5527, 9421, 24414, -26156, -11190, 3802, 18722, -31763, -16863, -1867, 13063, 28049, -22528, -7534, 7453, 22641, -27927, -12937, 1978, 17007, 31997, -18589, -3590, 11293, 26247, -24278, -9312, 5693, 20672, -29906, -14976, 6, 14984, 30178, -20380, -5390, 9597, 24497, 66, 15059, 30041, -20534, -5556, 9361, 24442, -26130, -11155, 3825, 18701, -31869, -16869, -1908, 13100, 28086, -22496, -7483, 7470, 22618, -27944, -12991, 2011, 17007, 31995, -18578, -3595, 11369, 26253, -24316, -9316, 69, 15081, 30061, -20486, -5527, 9421, 24414, -26156, -11190, 3802, 18722, -31763, -16863, -1867, 13063, 28049, -22528, -7534, 7453, 22641, -27927, -12937, 1978, 17007, 31997, -18589, -3590, 11293, 26260, -24199, -9342, 5753, 20660, -29931, -14961, 27, 14991, 30178, -20375, -5403, 9585, 24560, -26040, -11133, 16849, 31552, 13514, -4519, -21537, 25858, 7913, -10115, -27138, 20322, 2206, -15856, -120, -18145, 29375, 11301, -5709, -23722, 23741, 6601, -11426, -29501, 17994, 1015, 15723, -2328, -20384, 28156, 9992, -8049, -26112, 22406, 4415, -13647, -31703, 69, 15081, 30061, -20486, -5527, 9421, 24414, -26156, -11190, 3802, 18722, -31763, -16863, -1867, 13063, 28049, -22528, -7534, 7453, 22641, -27927, -12937, 1978, 17007, 31997, -18589, -3590, 11293, 26259, -24278, -9282, 5685, 20613, -29933, -14898, 20, 14991, 30115, -20354, -5383, 9597, 24511, -26009, -11058, 3927, 18910, -31694, -16707, -1739, 13221, 28272, -24542, -25933, -10951, 4010, 18988, -31503, -230, 14734, 29709, -20847, -5779, 9187, 7803, 22764, -27828, -12842, 2112, 17061, -17074, -1990, 12973, 27952, -22599, -7676, -9064, 5915, 20883, -29681, -24339, -26047, -10811, 3922, 19137, -31643, -10, 14716, 29922, -20878, -5750, 9029, 7817, 22557, -27729, -12999, 2216, 16954, -16971, -1831, 12865, 28127, -22766, -7481, -9131, 6091, 20818, -29515, -14789, 386, 31510, -18787, -4051, 11195, 25958, -24388, -26054, -10929, 4237, 19030, -31294, -233, 15053, 29796, -20498, -5769, 9418, 7720, 22934, -27892, -12670, 2092, 17322, -17096, -1865, 13193, 27969, -22316, -7650, -8767, 5988, 21222, -29638, -14384, 267, 31884, -18941, -3699, 11008, 26286, -24528, -25609, 66, 15059, 30041, -20534, -5556, 9361, 24442, -26130, -11141, 3838, 18696, -31869, -16869, -1905, 13117, 28074, -22479, -7495, 7485, 22592, -27968, 80, 15029, 30046, -20571, -5588, 9363, 65, 15091, 30074, -20496, -5519, 9427, 24414, -26223, -11188, 3792, 18790, -31858, -16843, -1867, 13057, 28044, -22500, -7465, 7455, 22565, -27940, -13023, 1994, 16897, 31996, -18595, -3625, 11347, 26295, -24278, -9295, 5677, 20617, -29944, -14976, 85, 14987, 30187, -20381, -5390, 9584, 24511, -26033, -11042, 3860, 18901, -31699, -16707, -1680, 13246, 28208, -22331, -7411, 7568, 22553, -27804, -12808, 2171, 17143, 32127, -18488, -3506, 11410, 26474, -24140, -9178, 5818, 20768, -29777, -14771, 202, 15156, 30080, -20465, -5277, 9710, 24672, -25858, -10938, 3987, 18960, -31490, -16560, -1620, 13368, 28346, -22213, -7275, 7693, 22667, -27818, -12910, 2294, 17195, 32211, -18310, -3381, 11593, 26561, -23998, -9008, 5926, 20910, -29642, -14659, 315, 15304, 66, 15059, 30041, -20534, -5556, 9361, 24442, -26130, -11141, 3838, 18696, -31869, -16869, -1905, 13117, 28077, -22475, -7500, 7474, 22604, -27966, -12970, 27423, 20909, 7716, -15186, -32465, 20365, 13312, -3377, -16622, 25998, 8760, -5929, -10897, -27674, 22608, 1758, -15552, -30260, 30208, 13114, -1550, -23011, 27894, 10543, 6102, -9179, -25958, 18178, 3572, -13722, -20243, 32100, 15306, -8112, -20769, 27461, 20866, 7850, -9412, -32346, 20005, 13481, -3752, -16486, 25625, 8901, -4238, -10760, -28038, 22697, 1385, -15403, -30702, 30412, 13127, -1988, -22861, 25377, 10684, 5666, -9064, -26343, 18313, 3143, -13619, -18579, 32241, 14975, -7945, -21170, 27546, 20495, 7907, -9383, -32728, 20150, 2857, -3663, -16871, 25747, 8532, -4151, -11231, -27912, 24441, 1507, -15765, -30520, 30042, 13268, -1972, -22844, 25535, 10289, 5858, -32174, -18237, -2231, 11738, 26716, -22911, -8854, 7166, 22123, -29458, -13544, 403, 15371, 31391, -20179, -4163, 10789, 24740, -24798, -9636, 4306, 20294, -31275, -16282, -271, 13675, 29678, -20894, -7039, 8975, 22941, -27621, -11595, 2358, 18349, -32214, -18270, -12348, -2698, -17665, 24693, 9716, -5290, -28453, 22036, 7113, -16043, -31005, 19468, 29108, 14141, -885, -24059, 26523, 11543, -11557, -26655, 23849, 710, -14291, -29196, -19699, 30974, 15937, -7207, -22225, 28349, 5174, -9793, -24815, 17547, 2564, -12386, -2727, -17807, 32742, 9568, -5387, -28555, 21974, 7004, -16239, -31149, 19362, 28962, 13985, -965, -24140, 26382, 11392, -11752, -26728, 23716, 620, -14422, -29375, -19715, 30784, 15837, -7336, -22318, 31602, 16867, 3689, -11014, -28292, 24481, 9290, -7458, -20661, 30158, 12856, -1869, -15061, -31809, 18445, 5784, -11517, -26228, 26112, 9082, -5653, -18833, 31983, 14677, 2015, -13222, -24459, -25913, -10930, 4036, 19013, -31513, -150, 14757, 29816, -20764, -5806, 9144, 7683, 22660, -27848, -12878, 2099, 17071, -17105, -1963, 13023, 27970, -22642, -7564, -9028, 5963, 20912, -29607, -14640, 299, 31636, -18932, -3910, 11040, 26043, -24542, -25924, -10786, 4177, 19147, -31476, -36, 14970, 29936, -20637, -5657, 9302, 7828, 22807, -27709, -12796, 2238, 17196, -16921, -2009, 13147, 28060, -22438, -7487, -8886, 6133, 21103, -29454, -14484, 406, 31775, -18785, -3775, 11195, 26147, -24385, -25807, -10823, 4152, 19228, -31335, -16283, 15063, 30054, -20488, -5529, 9463, 8047, 22933, -27582, -12601, 2343, 17307, -16875, -1905, 13067, 28040, -22300, -7302, -8734, 6147, 66, 15059, 30041, -20534, -5556, 9361, 24442, -26130, -11141, 3838, 18696, -31869, -16869, -1905, 13117, 28072, -22477, -7500, 7483, 22613, -27944, 65, 15091, 30074, -20496, -5519, 9427, 24414, -26223, -11188, 3792, 18790, -31860, -16841, -1864, 13063, 28057, -22524, -7465, 7455, 22565, -27940, -13023, 1994, 16897, 31996, -18595, -3625, 11347, 26295, -24278, -9295, 5677, 20617, -29944, -14976, 85, 14987, 30187, -20381, -5390, 9584, 24511, -26033, -11042, 3860, 18901, -31699, -16707, -1680, 13246, 28208, -22331, -7411, 7568, 22553, -27804, -12808, 2171, 17143, 32127, -18488, -3506, 11410, 26474, -24140, -9178, 5818, 20768, -29777, -14771, 202, 15156, 30080, -20465, -5277, 9710, 24672, -25858, -10938, 3987, 18960, -31498, -16515, -1650, 13314, 28316, -22259, -7251, 7725, 22699, -27855, -12872, 2240, 17189, 66, 15059, 30041, -20534, -5556, 9361, 24442, -26130, -11141, 3838, 18696, -31858, -16879, -1897, 13095, 28091, -22481, -7495, 7473, 22609, -27949, -12966, 2004, 17000, 31996, -18586, -3593, 11369, 26251, -24295, -25613, -24255, -4408, 13378, 29123, -16543, -15124, 547, 20478, -27294, -11564, 6204, 9607, 25351, -22349, -2498, 13230, 31077, -31059, -15465, 2414, 22163, -25480, -9805, -6322, 11503, 27237, -18463, -763, 15000, 16387, -29281, -13509, 4282, 24114, -25625, -24276, -4536, 11160, 28994, -16758, -15287, 509, 20345, -27424, -11668, 8066, 9502, 25228, -22511, -2612, 13056, 30911, -31187, -15452, 2262, 22094, -27747, -9904, -6457, 11383, 27127, -18656, -769, 14874, 18320, -29348, -13688, 4096, 23988, -25736, -24393, -4574, 11180, 28864, -16865, -1041, 327, 20217, -27537, -11797, 8036, 9464, 25106, -20582, -2751, 12956, 30779, -31297, -15491, 2224, 22077, -27817, -10025, -6573, 9162, 26993, -18719, -907, 14824, 18272, -29473, 21073, 26837, 10072, -554, -18338, 30438, 3448, -13319, -31135, 23783, 6917, -11899, -5110, -21887, 24869, 16306, -1502, -20307, 20268, 2652, -16177, -24767, 21961, -18290, -32214, -12889, 5929, 21153, -25575, -6265, 8537, 27806, -18920, -3590, 15141, 1716, 16490, -29745, -10923, 4241, 23071, -23073, -8032, 10804, 30135, -16585, -1404, -15355, 3977, 18698, -27504, -8600, 6573, -12480, -2620, -17847, 24775, 9551, -5129, -28567, 22248, 7024, -15882, -31212, 19604, 28947, 14225, -984, -23904, 26401, 11700, -11716, -29974, -20408, -43, 9547, 24791, -20871, -10827, 4967, 24308, -31712, -15465, 2333, 13471, 29252, -17988, -6342, 8867, 26663, -26698, -11553, 6231, 18316, -29373, -14095, -2459, 15792, 31582, -22813, -5097, 11160, 20744, -25454, -9615, 16961, 30913, 14160, -4644, -22440, 26338, 7526, -9242, -27035, 19684, 2827, -15977, -1021, -17776, 28984, 12196, -5572, -24390, 24376, 6745, -12083, -28838, 17886, 122, 85, 15061, 30014, -20571, -12607, -2958, -17414, 24957, 9459, -5551, -28221, 22347, 6873, -16309, -30801, 19746, 28858, 13947, -636, -23800, 26265, 11291, -11365, -26911, 23586, 85, 15060, 30027, -20537, -5565, 9457, 24431, -26144, -11155, 3834, 18709, -31847, -16885, -1891, 13091, 28064, -22468, -7502, 7482, 85, 15061, 30014, -20572, 21354, 27083, 9812, -808, -18173, 30670, 3184, -13569, -30862, 24037, 6666, -12154, -4789, -21598, 24636, 16063, -1245, -20051, 20005, 66, 15059, 30041, -20534, -5537, 9452, 24423, -26116, -11155, 3825, 18703, -31858, -16875, -1905, 13099, 28070, -22466, -7512, 7467, 22603, -27961, -12963, 2005, 17014, 31974, -18576, -3595, 11381, 26245, -24315, -9316, 5660, 20652, 27891, 22136, 6643, -15595, -31076, 18467, 13929, 3285, 17241, -26169, -9137, 4840, 27000, -20563, -7577, 14572, 32535, -19044, -30691, -12663, 1335, 23478, -25043, -11073, 11051, 28246, -23330, -1265, 12741, 29813, 19189, -32387, -14364, 6756, 20628, -26791, 16392, 31385, 13587, -4224, -21995, 25768, 7986, -9793, -27603, 20155, 2371, -15405, -447, -18217, 29543, 11766, -6028, -23815, 23915, 6157, -11617, -29434, 18309, 574, 15531, -2271, -25974, -24529, -4183, 13618, 28858, -16866, -14909, 798, 20120, -27624, -11285, 6436, 9468, 25138, -22074, -2239, 13005, 30813, -30753, -15707, 2091, 22461, -25229, -10069, -6656, 11668, 27419, -18732, -917, 15341, 16745, -29520, -13731, 4550, 24386, -25956, -24494, -4317, 10933, 28733, -16449, -14986, 186, 20017, -27212, -11466, 7845, -10092, -7675, -21105, 30492, 12957, -972, -30800, 16683, 3243, -10691, -28209, 23381, 26317, 8281, -5141, -19079, 28905, 14964, -14874, -32617, 18949, 5511, -8427, -25944, -23489, 28592, 10532, 67, 15078, 30048, -20485, -5517, 9431, 24330, -26153, -11183, 3793, 18722, -31763, -16843, -1797, 13071, 28040, -22524, -7532, 7446, 22636, -27934, -12940, 1978, 17014, 31945, -18621, -3622, 11352, 26288, -24213, -9292, 5686, 20626, -29881, -14950, 29, 15001, 30115, -20371, -5384, 9582, 24570, -26040, -11123, 3957, 18891, -31694, -16731, -1735, 13236, 28223, -22383, -7419, 7580, 22548, -27871, -12863, 2145, 17125, 32105, -18491, -3515, 11473, 26460, -24096, -9202, 5770, 20859, 11202, 4435, 24281, -31670, -15905, 3948, 29927, -19844, -19, 9585, 25231, -22514, -27243, -11505, 6315, 17958, -31810, -14040, 14007, 29643, -18086, -6446, 11350, 27112, 22380, -25360, -9626, 2037, 19723, -30075, -4073, 15750, 31534, -24398, -4573, 11191, 4409, 24145, 6093, 11590, 25293, -18389, -606, 13084, 80, 15087, 30049, -20485, -5511, 9347, 24388, -26172, -11179, 3805, 18723, -31809, -16780, -1870, 13073, 28105, -22503, -7527, 7432, 22628, -27936, -12934, 2046, 16911, 31880, -18580, -3625, 11347, 26282, -24284, -9306, 5753, 20630, -29946, -14974, 28, 15000, 30178, -20354, -5388, 9528, 24555, -26034, -11064, 3860, 18908, -31701, -16705, -1739, 13241, 28286, -22379, -7420, 7580, 22548, -27804, -12888, 2145, 17123, 32112, -18490, -3506, 11456, 26393, -24159, -9184, 5807, 20796, -29774, -14832, 158, 15185, 30092, -20457, -5277, 9645, 24701, -25867, -10922, 4044, 19010, -31527, -16545, -1615, 13349, 28348, -22220, -7296, 7684, 22735, -27899, -12919, 2277, 17253, 32246, -18312, -3374, 11587, 26510, -23993, -8999, 5924, 20911, -29655, -14602, 26849, 21104, 7674, -14487, -32004, 19535, 14276, -3745, -17202, 26194, 8620, -5331, -10570, -28628, 23432, 1285, -16227, -30197, 30100, 12520, -1415, -23055, 28533, 10955, 5199, -8237, -26288, 17619, 3622, -13919, -19651, 67, 15048, 30019, -20571, -5588, 9361, 11791, 5248, 23333, -32330, -15302, 2761, 28937, -18552, -1454, 8348, 26466, -21007, -28545, -10499, 7489, 17351, -31212, -13155, 13175, 30254, -17240, -7369, 10687, 27679, 21186, -26349, -8291, 539, 18663, -28827, -2567, 14439, 32463, -23283, -5168, 11863, 5331, 23529, -25049, -15182, 2852, 29104, -19454, -1337, 8475, 26524, -21911, -28438, -10378, 7613, 16501, -31029, -12990, 13259, 30293, -17096, -7247, 9829, 27837, 21296, -26225, -9208, 662, 18688, -28674, -3539, 14576, 32631, -23053, -6135, 11977, 5461, 23494, -25008, -15042, 2985, 20031, -19291, -1279, 8588, 25620, -21860, -28392, -10321, 6773, 16621, -30863, -12859, 12358, 30404, -17074, -7213, 9966, 27955, 21437, -27084, -9073, 789, 18890, 66, 15059, 30041, -20534, -5537, 9452, 24423, -26116, -11155, 3825, 18703, -31858, -16875, -1905, 13099, 28070, -22466, -7512, 7480, 22596, -27963, -12961, 2015, 16997, 31991, -18565, -3591, 11362, 26263, -24306, -9316, 5661, 20671, -29918, -14941, 52, 15029, 30159, 12817, 2225, 18224, -25170, -10194, 5776, 27997, -21614, -6656, 15560, 31586, -19969, -29587, -13592, 277, 24571, -26006, -12095, 12096, 27198, -24331, 12244, 5445, 23247, -32676, -14903, 2938, 28913, -18838, -1029, 8551, 26265, -21480, -28285, -10471, 7357, 16944, -30808, -12994, 12974, 30674, -17069, -7479, 10313, 28147, 21345, -26387, -8593, 1012, 18689, -29032, -3062, 14731, 32553, -23390, -5579, 12208, 70, 15078, 30055, -20487, -5511, 9415, 24330, -26171, -11177, 3743, 18741, -31832, -16838, -1857, 13122, 28090, -22467, -7516, 7504, 66, 15059, 30041, -20534, -5549, 9463, 24442, -26130, -11155, 3825, 18701, -31869, -16869, -1908, 13100, 28086, -22465, -7517, 7470, 22618, -27944, -12991, 2011, 17007, 31995, -18578, -3595, 11369, 26253, -24316, -9316, 79, 15059, 30046, -20571, -5588, 9362, 69, 15081, 30061, -20486, -5527, 9421, 24414, -26156, -11190, 3802, 18722, -31763, -16863, -1867, 13063, 28049, -22528, -7534, 7453, 22641, -27927, -12937, 1978, 17007, 31997, -18589, -3590, 11293, 26251, -24289, -9342, 5753, 20660, -29931, -14961, 27, 14991, 30178, -20375, -5403, 9585, 24560, -26040, -11133, 16958, 30895, 14117, -4682, -22481, 26251, 7430, -9326, -27119, 19597, 2943, -15895, -904, -17694, 29021, 12225, -5559, -24369, 24413, 6711, -12123, -28893, 17834, 2, 16007, -2800, -19579, 28177, 9469, -10491, -4695, -24019, 30906, 15657, -3187, -30690, 20116, 778, -9830, -24990, 21677, 26977, 12277, -7097, -17711, 32576, 13778, -13731, -28879, 17833, 6711, -12038, -27345, -21571, 24611, 9914, -1187, -20021, 30303, 3266, -16071, -30733, 23620, 4801, -10427, -4647, -23827, 10806, 4263, 24365, -31298, -16345, 3715, 29966, -19558, -487, 9349, 25463, -22047, -27536, -11542, 6485, 18377, -32191, -14137, 14165, 29247, -18259, -6357, 11682, 26634, 22175, -25325, -9341, 1543, 19710, -29830, -3606, -26517, -23865, -4797, 14292, 29255, -17181, -14480, 506, 19556, -26892, -12020, 7107, 9743, 24731, -21719, -2625, 12334, 31420, -31437, -16289, 2759, 21849, -24684, -9663, -6957, 12109, 27092, -19405, -347, 14641, 17324, -29097, -14195, 4902, 23981, -26570, -23897, -4669, 10317, 29404, -17065, -14395, 609, 19692, -26764, -11851, 7215, 9871, 24863, -21609, -2530, 12462, 31534, -31245, -6614, -9029, -27855, 18850, 3131, -15713, -18158, 32646, 12805, -5991, -20629, 26109, 22636, 7926, -10935, -29739, 20061, 1243, -1207, -16861, 29873, 11063, -7746, -23530, -25980, 20738, 6029, -13823, -32539, 18285, 15867, -3995, -18751, 27968, 9160, -12925, -2257, -18261, 25148, 10159, -5877, -28008, 21522, 6540, -15588, -31516, 20011, 29671, 13683, -319, -24489, 26054, 12116, -12069, -27209, 24367, 177, -13700, -28759, -20165, 31397, 15420, -7717, -21683, 27865, 5700, -9281, -25243, 18126, 2117, -12834, -2225, -18389, 32165, 10036, -5953, -28115, 22409, 6404, -15716, -31651, 18880, 29546, 13541, -411, -23567, 25933, 11979, -12223, -27179, 24232, 32, -14873, -25528, -22823, -5805, 13248, 30297, -18179, -15504, 1508, 18535, -27909, -11001, 8073, 8721, 25734, -20698, -3652, 13365, 32425, -32476, -15280, 3797, 20826, -25633, -8581, -7961, 11105, 28131, -20364, -1407, 15636, 18326, -30201, -13137, 5951, 29577, 18709, 1688, -9117, -26134, 22359, 27728, 22268, 6520, -15377, -31108, 18648, 13131, -2623, -18337, 25295, 9527, -4104, -11724, -27488, 24338, 388, -15339, -29049, 28936, 13412, -260, -24222, 27567, 11898, 4328, -9354, -25105, 16392, 2718, -13046, -18537, 31340, 15526, -6383, -22124, 27664, 22156, 6642, -9153, -31033, 18786, 13311, -2467, -18228, 25412, 9692, -6023, 66, 15059, 30041, -20534, -5549, 9463, 24442, -26130, -11146, 3818, 18698, -31871, -16885, -1900, 13110, 28089, -22481, -7500, 7473, 22608, -27966, -12985, 2015, 17011, 66, 15059, 30041, -20534, -5556, 9361, 24442, -26130, -11143, 3826, 18692, -31868, -16877, -1906, 13101, 28092, -22493, -7512, 7466, 22615, -27955, -12963, 1993, 16992, 31979, -18565, -3585, 11378, 26250, -24300, -9343, 5645, 20641, -29901, -14917, 38, -11325, -5786, -22816, 31867, 14835, -2217, -29558, 19026, 1994, -8870, -25945, 20537, 28081, 11131, -8061, -16823, 31648, 12613, -12626, -29787, 16728, 7905, -11141, -28209, -20645, 25806, 8789, -55, -19155, 29348, 2108, -14855, -31985, 22657, 5710, -11359, -5883, -22925, 25583, 14641, -2351, -29615, 18916, 1890, -8991, -25995, 22406, 28009, 10919, -8130, -16982, 31501, 12492, -12782, -29734, 16626, 7804, -9234, -28318, -20760, 25687, 8587, -170, -19248, 29222, 4001, -15061, -32089, 22585, 5517, -11490, -5935, -23010, 25485, 14569, -2464, -19532, 18778, 1761, -9110, -26123, 22375, 27882, 10752, -6264, -17037, 31413, 12307, -12856, -29908, 16567, 7731, -9401, -28466, -20898, 27612, 8548, -375, 66, 15059, 30041, -20534, -5549, 9463, 24442, -26130, -11151, 3825, 18693, -31870, -16890, -1911, 13095, 28074, -22492, -7512, 7483, 22603, -27944, -12970, 1992, 16996, 31980, -18576, -3591, 11369, 26260, 65, 15063, 30023, -20534, -5549, 9463, 24442, -26130, -11253, 27574, 20758, 7831, -15351, -32375, 20279, 13562, -3531, -16473, 25967, 8896, -6052, -10808, -27838, 22774, 1656, -15372, -30366, 30382, 13242, -1752, -22861, 27716, 32160, 18225, 2235, -11736, -26703, 22805, 8856, -7156, -22113, 29459, 13552, -406, -15388, -31386, 20165, 4179, -10814, -24740, 24782, 9634, -4310, -20306, 31287, 16279, 282, -16578, -31323, -13773, 4263, 21797, -25700, -8183, 9859, 27493, -19998, -2534, 66, 15059, 30041, -20534, -5549, 9463, 24442, -26130, -11139, 3825, 18706, -31864, -16890, -1916, 13095, 28081, -22477, -7502, 7483, 22593, -27959, -12969, 1989, 17013, 31968, -18563, -3597, 11374, 26252, -24316, -9314, 5661, -27517, -20968, -7794, 15130, 32408, -20447, -13388, 3390, 16601, -26017, -8794, 79, 15059, 30046, -20555, -5553, 9408, 24389, -26175, -11171, 3803, 18790, -31858, -16837, -1874, 13068, 28061, -22507, -7547, 7518, 22636, -27905, -13005, 2037, 16975, 31880, -18612, -3623, 11346, 26280, -24273, -9283, 5678, 20622, -29881, -14947, 28, 14994, 30176, -20369, -5455, 9585, 24555, -26106, -11064, 3916, 18904, -31705, -16724, -1740, 13234, 28218, -22331, -7400, 7579, 22559, -27871, -12821, 2144, 17123, 32115, -18480, -3506, 11456, 26393, -24140, -9169, 5820, 20784, -29777, -14837, 133, 15133, 30108, -20399, -4758, -10245, -26511, 17122, 1892, -13874, -19888, 29898, 14681, -7228, -23494, 28320, 21298, 5552, -8689, -32610, 17686, 3978, -4070, -19103, 32763, 8318, -5380, -20643, -28215, 23123, 7367, -12584, -2979, -17502, 24889, 9393, 67, 15078, 30048, -20485, -5517, 9431, 24330, -26175, -11171, 3789, 18741, -31836, -16857, -1873, 13122, 28040, -22448, -7495, 7467, 22601, -27968, -13005, 2015, 16975, 31964, -18618, -3646, 11332, 26346, 25962, 24571, 4209, -13598, -28828, 16846, 14928, -822, -20135, 27588, 11322, -6496, -9422, -25168, 22031, 2206, -13034, -30838, 30746, 15713, -2053, -22418, 25319, 10048, 6596, -14882, -177, -20283, 27222, 12243, -7814, -25867, 23672, 4598, -13462, -29554, 17928, 31639, 15625, -2383, -22486, 28095, 10046, -10079, -25135, 22351, 2254, -15798, -30726, -18053, 29409, 13411, -5643, -23792, 25754, 84, 15087, 30059, -20505, -5511, 9347, 24413, -26160, -11189, 3743, 18727, -31837, -16780, -1858, 13072, 28059, -22497, -7547, 7518, 22642, -27932, -12934, 2038, 16964, 31880, -18597, -3644, 11332, 26285, -24283, -9291, 5753, 20628, -29944, -14898, 26, 15006, 30199, -20373, -5384, 9590, 24511, -26041, -11069, 3860, 18898, -31700, -16710, -1756, 13238, 28208, -22394, -7415, 7635, 22549, -27801, -12888, 2171, 17150, 32120, -18556, -3506, 11484, 26458, -24142, -9154, 5822, 20769, -29771, -14836, 132, 15185, 30105, -20461, -5279, 9698, 24678, -25870, -10922, 4033, 19037, -31591, 17102, 30815, 14293, -4794, -22333, 26218, 7653, -9368, -26906, 19578, 2974, -16104, -889, -17890, 29088, 12083, -5443, -24521, 24507, 6861, -12193, -28716, 17747, 244, 84, 15087, 30059, -20505, -5511, 9347, 24413, -26160, -11189, 3743, 18727, -31837, -16780, -1858, 13072, 28059, -22497, -7547, 7518, 22642, -27932, -12934, 2038, 16964, 31880, -18597, -3644, 11332, 26285, -24283, -9291, 5753, 20628, -29944, -14898, 16, 14980, 30182, -20375, -5404, 9580, 24570, -26106, -11047, 3932, 18910, -31646, -16707, -1736, 13234, 28286, -22400, -7422, 7568, 22536, -27784, -12808, 2171, 17151, 32114, -18486, -3573, 11475, 26453, -24153, -9176, 5820, 20796, -29784, -14837, 135, 15199, 30168, -20426, -5272, 9723, 24693, -25865, -10933, 4045, 18960, -31492, -16549, -1604, 13375, 28403, -22158, -7288, 7686, 22681, -27881, -12911, 2285, 17263, 32178, -18308, -3378, 11588, 26561, -23983, -9003, 5933, 20909, -29571, -14600, 296, 15252, 30210, -20326, -5348, 9762, 24805, -25739, -10759, 4217, 19153, -31420, -16481, -1510, 13492, 28454, -22106, -7112, 7860, 22800, -27774, -12781, 2197, 17385, 32381, -18197, -3215, 11696, 26627, -23857, -8891, 6107, 21014, -29464, -14493, 66, 15059, 30041, -20534, -5550, 9462, 24422, -26115, -11161, 3823, 18708, -31870, -16880, -1906, 13089, 28093, -22481, -7500, 7473, 22593, -27959, -18870, -29474, -15580, 6591, 23607, -28743, -19198, -1402, 8280, 25985, -21700, -12120, 5688, 23456, -32463, -14625, 3072, 12762, 30553, -17173, -7583, 10173, 28019, -27936, -10296, 7439, 17035, -30693, -12896, -3227, 14509, 32297, -23568, -5812, 11979, 21583, -26176, -8332, 1188, 66, 15059, 30041, -20534, -5550, 9462, 24422, -26115, -11161, 3823, 18804, -31843, -16885, -1905, 13104, 28072, -22466, -7516, 7487, 22598, -27944, -12966, 2005, 17007, 31991, -18565, -3601, 11373, 26241, 80, 15029, 30046, -20571, -5588, 9361, 19057, 28874, 16206, -6768, -24471, 28340, 5471, -11340, -24983, 17640, 770, -13946, -3070, -19809, 31012, 10168, -7620, -22339, 22325, 4608, -10019, -30897, 19919, 2145, 13997, -669, -17440, 26168, 11407, -5349, -28261, 23568, 6885, -16083, -28743, 19056, 28860, 16331, -1441, -24384, 28484, 5524, -11461, -5718, -23008, 31923, 14635, -2161, -29665, 19076, 1822, -8825, -25998, 20731, 28024, 11244, -8113, 3158, 14023, 31053, -23631, -6600, 10373, 7039, 8644, 28224, -19298, -3754, 16357, 17518, -32017, -12419, 5600, 21069, -26481, -23284, -7216, 10279, 30391, -19657, -1616, 1653, 17217, -30251, -10728, 7380, 22887, 26611, -21392, -5404, 14136, 66, 15059, 30041, -20534, -5537, 9457, 24430, -26130, -11146, 3818, 18698, -31871, -16885, -1890, 13100, 28093, -22471, -7517, 7463, 66, 15059, 30041, -20571, -5588, 9367, -28380, -21601, -7141, 16069, 31503, -19022, -12760, 2213, 17768, -24662, -10152, 4809, 12109, 27103, -23957, -839, 14697, 29684, -29650, -14053, 905, 23567, -27002, -11407, -4681, 9773, 24806, -17112, -2087, 12363, 19158, -30896, -15938, 66, 15059, 30041, -20534, -5553, 9446, 24425, -26140, -11158, 3830, 18706, -31852, -16885, -1899, 13111, 28069, -22468, -7512, 7469, 22592, -27953, -12986, 1992, 17000, 31996, -18570, -3607, 11390, 26251, -24315, -9338, 5660, 20664, -29901, 83, 15061, 30039, -20571, -5588, 9363, 85, 15081, 30063, -20489, -5520, 9414, 24330, -26171, -11177, 3743, 18727, -31826, -16841, -1858, 13073, 28058, -22448, -7549, 7446, 22624, -27988, -12992, 2047, 16962, 31965, -18595, -3617, 11337, 26301, -24213, -9327, 5686, 20622, -29933, -14965, 13, 14984, 30115, -20379, -5405, 9528, 24566, -26030, -11042, 3860, 18904, -31699, -16729, -1756, 13234, 28208, -22383, -7393, 7645, 22618, -27832, -12804, 2095, 17125, 32120, -18495, -3514, 11457, 26393, -24155, -9170, 5818, 20797, -29767, -14831, 202, 15128, 30092, -20385, -5271, 9727, 24628, -25870, -10922, 4058, 18960, -31532, -16559, -1621, 13368, 28342, -22220, -7275, 7752, 22670, -27900, -12904, 2212, 17221, 32199, -18347, -3348, 11529, -16349, -1358, -19144, 28587, 10797, -7033, -24807, 22915, 5136, -12659, -30349, 17385, 32379, 14585, -3258, -21033, 26719, 8899, -8877, -26584, 21170, 3362, -14406, -32238, -17268, 30464, 12675, 5123, 11910, 24953, -17438, -407, -2272, -12923, -32253, 22680, 7440, -11340, -22423, 28322, 9022, -1618, -16810, 29895, 18756, 4044, -15327, -25877, 24445, 5556, -5512, -20728, 26011, 14873, -3955, -19141, -29717, 16416, 1724, -9424, -28212, 22093, 11477, -7910, -22537, 31851, 12973, -2185, -12865, -32082, 18236, 7614, -11721, -22308, 27925, 9135, -2011, -16707, 29519, 18910, 3603, -15119, -26285, 24562, 5222, -5404, -20640, 25676, 66, 15059, 30041, -20534, -5550, 9462, 24422, -26115, -11161, 3836, 18707, -31841, -16890, -1890, 13100, 28074, -22487, 66, 15059, 30041, -20571, -5588, 9360, -2136, -13037, -32105, 22601, 7555, -11478, -22364, 28223, 9121, -1747, -16679, 29768, 18824, 3918, -15123, -26059, 24546, 5502, -5394, -20587, 25936, 14976, -4076, -18947, -29903, 16574, 1594, -9291, -28351, 22169, 66, 15059, 30041, -20534, -5542, 9452, 24440, -26116, -11161, 3830, 18696, -31845, -16875, -1897, 13099, 28077, -22481, -7500, 7473, 22593, -27959, -28182, -21649, -7024, 15882, 73, 15081, 30072, -20492, -5520, 9418, 24398, -26223, -11141, 3792, 18722, -31832, -27530, -20761, -7827, 15358, 32366, -20264, -13492, 3528, 16467, -25918, -8900, 6063, 10785, 27811, -22753, -1639, 15387, 30359, -30445, -13215, 1789, 82, 15042, 30024, -20571, -5587, 73, 15081, 30072, -20492, -5520, 9418, 24398, -26223, -11156, 3782, 18742, -31832, 66, 15059, 30041, -20534, -5542, 9452, 24440, -26116, -11161, 3830, 18696, -31845, -16875, -1897, 13099, 28077, -22481, -7515, 7483, 22603, -27960, -12970, 1992, 17022, 31996, -18570, -3610, 11384, 68, 15041, 30014, -20569, 73, 15081, 30072, -20492, -5520, 9418, 24398, -26223, -11158, 3802, 18728, -31831, -16847, -1879, 13122, 28093, -22519, -7545, 7451, -14512, -575, -19893, 26840, 11591, -7169, -26503, 24288, 4990, -13852, -29182, 17562, 31001, 16286, -3023, -21833, 28462, 9632, -9672, 83, 15061, 30039, -20534, -5557, 9447, 24419, -26130, -11255, 3727, 18806, -19949, -30552, -14548, 7666, 22584, -26991, -4833, 11140, 26138, -17258, -1163, 12714, 3172, 19197, -32439, -8254, 6738, 20676, -20711, -5589, 8376, 32628, -19020, -4088, -12658, 1291, 17285, -25069, -11019, 4969, 27060, 12467, 2594, 17832, -24773, -9554, 5149, 28566, -22259, -7012, 15872, 31230, -19585, -28956, -14210, 986, 23895, -26417, -11687, 11724, 26812, -24004, -596, 14117, 29333, 19477, -30835, -16104, 7305, 22125, -28182, -5270, 9978, 24660, -17454, -3943, -13822, -31340, 24320, 6805, -11225, -20556, 26916, 9410, -443, -17987, 13024, 2117, 18371, -25256, -10032, 5748, 28073, -21642, -6402, 15464, 31616, -20211, -29565, -13736, 418, 24357, -25922, -12231, 12200, 27336, -24506, -45, 13656, 28918, 20066, -31261, -15493, 7870, 21508, -27776, -5872, 9364, 25133, -18015, -2271, 13046, 2107, 18245, -32038, -10170, 6098, 27986, -22300, -6534, 15870, 31607, -18801, -29628, 68, 15041, 30033, -20539, -5559, 9441, 24422, -26120, -11157, 3831, 18703, -31869, -16877, -1916, 13100, 28092, -22468, -7493, 7457, 22609, -27954, -12989, 1989, 17012, 31997, -18586, -3598, 68, 15041, 30015, -20571, 73, 15081, 30072, -20492, -5520, 9418, 24398, -26223, -11155, 3818, 18703, -31863, -16780, -1859, 13069, 28059, -22448, -7549, 7446, 22624, -27988, -12985, 2037, 16897, 31978, -18614, -3690, 11373, 26289, -24279, -9282, 5680, 20627, -29937, -14965, 17, 15068, 30165, -20369, -5405, 9579, 24566, -26039, -11069, 3866, 18843, -31732, -16740, -1764, 13211, 28286, -22388, -7393, 7635, 22548, -27794, -12804, 2095, 17143, 32113, -18488, -3516, 11461, 26460, -24156, -9114, 18133, 31824, 13248, -5804, -21288, 25200, 6647, -8343, -27910, 18534, 3998, -15086, -1918, -16875, 30138, 11062, -4425, -23513, 23459, 7901, -11175, -29731, 16735, 1266, 14953, -3615, -18574, 27385, 8220, -6242, 68, 15041, 30015, -20572, 3523, 14179, 30962, -23938, -6150, 10560, 21188, -27621, -9753, 864, 17541, -29181, -19458, -2761, 16007, 24593, -23078, -4343, 4252, 21994, -24794, -16179, 2687, 20363, 29024, -17728, -996, 8679, 27451, -21341, -10700, 7098, 23833, -31099, -14335, 3483, 14166, 30815, -16923, -6295, 10465, 21116, -26685, -9911, 656, 17425, -30330, -19668, -2822, 15883, 25521, -23267, -4459, 4112, 21919, -24859, -16350, 1507, 20339, 28898, -17856, -59, 8472, 27349, -21467, -11841, 7012, 23723, -31170, -13428, 3392, 13980, 30747, -17021, -6423, 10345, 28094, -26812, -9987, 618, 18430, 68, 15041, 30033, -20539, -5559, 9441, 24422, -26120, -11157, 3831, 18703, -31869, -16877, -1916, 13099, 28071, -22490, -7498, 7474, 22604, -27960, -12980, 1998, 16995, 31992, -18576, -3600, 11378, 26262, -24314, -9331, 5644, 20661, -29906, -14934, 14586, 639, 19841, -26855, 32304, 17552, 2817, -11891, -27639, 23219, 8503, -6168, -21996, 28819, 14198, -528, -16371, -31036, 19828, 5090, -10711, -25350, 25455, 9753, -4907, -19666, 31130, 15414, 688, -14021, -28762, 21031, 6301, -8332, -23100, 26706, 12020, -2754, -17437, 32355, 17573, 2957, -12773, -27519, 23298, 8590, -7041, -21856, 28965, 14247, -1509, -16156, -30906, 19843, 4197, -10503, -25288, 25562, 9846, -4838, -19555, 30239, 15516, 780, -13896, -29642, 21227, 6422, -8228, -23988, 26820, 12101, -2614, -18316, 32435, 17770, 3044, -12694, -27376, 23450, 7690, -7023, -21637, 29092, 13350, -1312, -5561, -12094, -24750, 17862, 74, -12574, -19099, 29691, 15976, -6924, -23796, 27008, 21520, 4743, -9950, -30811, 16929, 2214, -2264, -19882, 30939, 10069, -4643, -22403, -26881, 23918, 7141, -14751, -29550, 19229, 12696, -994, 23985, 26385, 10368, -3572, -18552, 31026, 694, -15255, -30315, 21266, 5367, -8591, -7284, -23227, 28405, 12387, -2648, -16517, 16622, 1432, -12460, -28481, 23053, 8185, 8466, -5454, -21394, 29077, 15177, -815, -31162, 19400, 3435, -10505, -26509, 24041, 26404, 10285, -4713, -18661, 30867, 526, -14415, -30405, 21218, 5219, -9746, -7335, -23347, 28175, 13296, -2696, -16666, 16504, 1515, -12650, -28642, 21975, 7944, 8330, -5591, -20547, 28974, 15073, -930, -32304, 19268, 3213, -10672, -25613, 23927, 26281, 10343, -4626, -18808, 30736, 15746, -14525, -30577, 20996, 6017, -9973, -7450, -23463, 27099, 13134, -2863, -16777, 17335, 1379, -12626, -28569, 21785, 7839, 8197, -6769, -20673, 28927, 14882, -94, -32412, 19162, 3164, -11824, -25856, 23779, 26215, 11259, -4755, -18706, 31635, 15634, -14648, -30679, 19849, 5935, -10055, -7577, -22558, 26960, 13022, -2989, -17977, 17222, 1277, -12697, -27677, 21871, 7711, 9183, -6910, -20859, 28677, 13743, -142, -32579, 18984, 4002, -12002, -25871, 23662, 24963, 11134, -4880, -18820, 31726, 15654, -14828, -29817, 19787, 5761, -10186, -25182, -22747, 26811, 12853, -2104, -18090, 17102, 1024, -29660, -18783, -1743, 9139, 26169, -22377, -11511, 5529, 22535, -32103, -14988, 4066, 12921, 29924, -16556, -7719, 9295, 28369, -28321, -11220, 7840, 16694, -29762, 697, 14396, 30657, -21160, 70, 15086, 30050, -20496, -5512, 9347, 24414, -26146, -11240, 3801, 18723, -31815, -16841, -1869, 13122, 28045, -22511, -7549, 7455, 22565, -27926, -12959, 2037, 16972, 31880, -18567, -3610, 11293, 26348, -24292, -9289, 5691, 20681, -29881, -14915, 16, 14990, 30197, -20381, -5390, 9597, 24497, 67, 15046, 30044, -20527, -5565, 9442, 24422, -26141, -11139, 3838, 18690, -31852, -16885, -1911, 13095, 28078, -22471, -7516, 7466, 22592, -27938, -12970, 2014, 67, 15061, 30026, -20534, -5544, 9463, 24427, -26130, -11255, 3726, 18801, 67, 15078, 30076, -20495, -5572, 9410, 24390, -26173, -11171, 3806, 18722, -31820, -16780, -1862, 13062, 28045, -22507, -7533, 7518, 22641, -27933, -13005, 2030, 16969, 31949, -18673, -3615, 11356, 26280, -24281, -9289, 5677, 20686, 66, 15051, 30031, -20522, -5545, 9455, 24419, -26142, -11156, 3834, 18690, -31854, -16880, -1890, 13108, 28064, -22477, -7502, 27640, 20862, 7932, -15263, -32267, 20300, 13512, -3515, -16478, 25892, 8925, -942, -14604, -30354, 21482, 5737, -10032, -23780, 26064, 10319, -3366, -19088, 32697, 16942, 1196, -12521, -28268, 21514, 7816, -7909, -23449, 28415, 12641, 22132, 27901, 9081, -1568, -17311, 29401, 2389, -12332, -32166, 22732, 7988, -10844, -6097, -20830, 25878, 15254, -502, -19324, 19223, 3698, -15126, -25739, 20979, 5185, 10971, -7861, -22573, 31298, 12477, -2253, -9562, -8160, -20574, 30015, 12459, -485, -31351, 17179, 3836, -11142, -27773, 22443, 27918, 8842, -2022, -17002, 29472, 2284, -12746, -31826, 22825, 7808, -11171, -5673, -20657, 25847, 14950, -7, -19073, 19128, 3988, -15093, -25978, 20572, 5541, 11042, -8024, -22989, 31664, 12622, -2364, -29625, 16843, 1891, -8987, 77, 15058, 30018, -20543, -5547, 9459, 24422, -26124, -11161, 3816, 18695, -31871, -16872, -1890, 13110, 28090, 77, 15090, 30050, -20511, -5515, 9427, 24390, -26156, -11240, 3784, 18727, -31839, -16840, -1858, 13078, 28058, -22448, -7528, 7440, 22565, -27912, -12933, 2047, 16897, 31963, -18610, -3621, 11352, 26340, -24283, -9305, 5684, 20610, -29950, -14948 };
  }
  
  /* Error */
  private static String ॱ(int paramInt1, char paramChar, int paramInt2)
  {
    // Byte code:
    //   0: goto +111 -> 111
    //   3: astore 5
    //   5: aload 5
    //   7: athrow
    //   8: new 122	java/lang/String
    //   11: dup
    //   12: aload 5
    //   14: invokespecial 5212	java/lang/String:<init>	([C)V
    //   17: areturn
    //   18: iload_3
    //   19: iload_2
    //   20: if_icmpge +6 -> 26
    //   23: goto +16 -> 39
    //   26: goto +19 -> 45
    //   29: iload_2
    //   30: newarray char
    //   32: astore 5
    //   34: iconst_0
    //   35: istore_3
    //   36: goto +81 -> 117
    //   39: iconst_0
    //   40: istore 4
    //   42: goto +43 -> 85
    //   45: iconst_1
    //   46: istore 4
    //   48: goto +37 -> 85
    //   51: aload 5
    //   53: iload_3
    //   54: getstatic 5209	o/EF:ॱ	[C
    //   57: iload_0
    //   58: iload_3
    //   59: iadd
    //   60: caload
    //   61: i2l
    //   62: iload_3
    //   63: i2l
    //   64: getstatic 379	o/EF:ˏ	J
    //   67: lmul
    //   68: lxor
    //   69: iload_1
    //   70: i2l
    //   71: lxor
    //   72: l2i
    //   73: i2c
    //   74: castore
    //   75: iload_3
    //   76: iconst_1
    //   77: iadd
    //   78: istore_3
    //   79: goto -61 -> 18
    //   82: goto -53 -> 29
    //   85: iload 4
    //   87: tableswitch	default:+21->108, 0:+60->147, 1:+-79->8
    //   108: goto +39 -> 147
    //   111: goto +9 -> 120
    //   114: goto -63 -> 51
    //   117: goto -99 -> 18
    //   120: getstatic 115	o/EF:ˋ	I
    //   123: bipush 9
    //   125: iadd
    //   126: istore_3
    //   127: iload_3
    //   128: sipush 128
    //   131: irem
    //   132: putstatic 113	o/EF:ˊ	I
    //   135: iload_3
    //   136: iconst_2
    //   137: irem
    //   138: ifeq +6 -> 144
    //   141: goto -59 -> 82
    //   144: goto -115 -> 29
    //   147: getstatic 113	o/EF:ˊ	I
    //   150: istore 4
    //   152: iload 4
    //   154: bipush 43
    //   156: iadd
    //   157: istore 4
    //   159: iload 4
    //   161: sipush 128
    //   164: irem
    //   165: putstatic 115	o/EF:ˋ	I
    //   168: iload 4
    //   170: iconst_2
    //   171: irem
    //   172: ifne +6 -> 178
    //   175: goto -61 -> 114
    //   178: goto -127 -> 51
    // Local variable table:
    //   start	length	slot	name	signature
    //   0	181	0	paramInt1	int
    //   0	181	1	paramChar	char
    //   0	181	2	paramInt2	int
    //   18	120	3	i	int
    //   40	132	4	j	int
    //   3	10	5	localException	Exception
    //   32	20	5	arrayOfChar	char[]
    // Exception table:
    //   from	to	target	type
    //   147	152	3	java/lang/Exception
    //   159	168	3	java/lang/Exception
  }
  
  /* Error */
  public String ˏ()
  {
    // Byte code:
    //   0: goto +72 -> 72
    //   3: aload_2
    //   4: areturn
    //   5: getstatic 115	o/EF:ˋ	I
    //   8: bipush 97
    //   10: iadd
    //   11: istore_1
    //   12: iload_1
    //   13: sipush 128
    //   16: irem
    //   17: putstatic 113	o/EF:ˊ	I
    //   20: iload_1
    //   21: iconst_2
    //   22: irem
    //   23: ifeq +6 -> 29
    //   26: goto +6 -> 32
    //   29: goto +35 -> 64
    //   32: goto +32 -> 64
    //   35: astore_2
    //   36: aload_2
    //   37: athrow
    //   38: getstatic 113	o/EF:ˊ	I
    //   41: bipush 73
    //   43: iadd
    //   44: istore_1
    //   45: iload_1
    //   46: sipush 128
    //   49: irem
    //   50: putstatic 115	o/EF:ˋ	I
    //   53: iload_1
    //   54: iconst_2
    //   55: irem
    //   56: ifne +6 -> 62
    //   59: goto -56 -> 3
    //   62: aload_2
    //   63: areturn
    //   64: aload_0
    //   65: getfield 357	o/EF:mCode	Ljava/lang/String;
    //   68: astore_2
    //   69: goto -31 -> 38
    //   72: goto -67 -> 5
    // Local variable table:
    //   start	length	slot	name	signature
    //   0	75	0	this	EF
    //   11	45	1	i	int
    //   3	1	2	str1	String
    //   35	28	2	localException	Exception
    //   68	1	2	str2	String
    // Exception table:
    //   from	to	target	type
    //   64	69	35	java/lang/Exception
  }
}
