package o;

public final class EH
{
  private static char[] ˋ = { -27392, -8033, 32277, -2633, 17197, -8488, 21584, -23597, 14704, -19202, 693, -26620, 6059, 27954, -1835, 30284, -12813, 23419, -10555, 11422, -10485, -23916, 15366, -18516, 315, -25393, 5727, -7684, 31603, -2309, 16520, -9690, 21927, 12078, -17699, 13393, -28699, 6506, 97, 30206, -5268, 24774, -10671, 19365, -16075, 13974, -21479, 8593, -26654, 3411, -32020, 1824, 29368, -5076, 26525, -12012, 19688, -14765, 12736, -21689, 9948, -15625, -18568, 10745, -23984, 5320, -30416, 910, -3041, 28293, -7422, -31630, -3627, 28486, -6938, 21059, -12400, 17676, -19788, 10299, -23128, 5065, -30400, 1745, 31846, -5751, 26368, -8969, 18977, -14430, 15820, -21686, 8444, -24987, 2953, -32466, -367, 29731, -7796, 24537, -10918, 17135, -18324, 13713, -23790, 6278, -27108, 931, 31108, -27737, -6619, 30966, -3247, 17859, -10207, 21174, -23286, 16282, -19967, 1134, -24834, 4429, 27627, -470, 28843, -13544, 23948, -12264, 10863, -17234, -19709, -14719, 22610, -11275, 25959, -1915, 29202, -31314, 7998, -27995, 9418, -16806, 12777, 19280, -8529, 20544, 44, 30126, -5249, 24799, -10677, 19378, -16069, 13967, -21452, 8607, -26632, 3451, -32107, 44, 30126, -5256, 24783, -10674, 19375, -16073, 13959, -21447, 8592, -26646, 3445, -32107, 41 };
  private static long ˎ;
  private static int ˏ = 0;
  private static int ॱ = 1;
  private final String applicationID;
  private final String applicationVersion;
  private final If customData;
  private final ˊ deviceInfo;
  private final String paymentAppInstanceId;
  
  static
  {
    ˎ = -6964030289829202546L;
  }
  
  public EH(String paramString1, String paramString2, String paramString3, If paramIf, ˊ paramˊ)
  {
    this.paymentAppInstanceId = paramString1;
    this.applicationVersion = paramString2;
    this.applicationID = paramString3;
    this.customData = paramIf;
    this.deviceInfo = paramˊ;
  }
  
  /* Error */
  private static String ˊ(int paramInt1, char paramChar, int paramInt2)
  {
    // Byte code:
    //   0: goto +107 -> 107
    //   3: goto +163 -> 166
    //   6: getstatic 29	o/EH:ˏ	I
    //   9: bipush 29
    //   11: iadd
    //   12: istore_3
    //   13: iload_3
    //   14: sipush 128
    //   17: irem
    //   18: putstatic 31	o/EH:ॱ	I
    //   21: iload_3
    //   22: iconst_2
    //   23: irem
    //   24: ifne +6 -> 30
    //   27: goto -24 -> 3
    //   30: goto +136 -> 166
    //   33: astore 5
    //   35: aload 5
    //   37: athrow
    //   38: iload 4
    //   40: tableswitch	default:+24->64, 0:+24->64, 1:+54->94
    //   64: getstatic 31	o/EH:ॱ	I
    //   67: bipush 49
    //   69: iadd
    //   70: istore 4
    //   72: iload 4
    //   74: sipush 128
    //   77: irem
    //   78: putstatic 29	o/EH:ˏ	I
    //   81: iload 4
    //   83: iconst_2
    //   84: irem
    //   85: ifeq +6 -> 91
    //   88: goto +124 -> 212
    //   91: goto +27 -> 118
    //   94: new 216	java/lang/String
    //   97: dup
    //   98: aload 5
    //   100: invokespecial 244	java/lang/String:<init>	([C)V
    //   103: areturn
    //   104: goto +6 -> 110
    //   107: goto -101 -> 6
    //   110: goto +39 -> 149
    //   113: astore 5
    //   115: aload 5
    //   117: athrow
    //   118: aload 5
    //   120: iload_3
    //   121: getstatic 207	o/EH:ˋ	[C
    //   124: iload_0
    //   125: iload_3
    //   126: iadd
    //   127: caload
    //   128: i2l
    //   129: iload_3
    //   130: i2l
    //   131: getstatic 35	o/EH:ˎ	J
    //   134: lmul
    //   135: lxor
    //   136: iload_1
    //   137: i2l
    //   138: lxor
    //   139: l2i
    //   140: i2c
    //   141: castore
    //   142: iload_3
    //   143: iconst_1
    //   144: iadd
    //   145: istore_3
    //   146: goto +30 -> 176
    //   149: iload_3
    //   150: iload_2
    //   151: if_icmpge +6 -> 157
    //   154: goto +6 -> 160
    //   157: goto +49 -> 206
    //   160: iconst_0
    //   161: istore 4
    //   163: goto -125 -> 38
    //   166: iload_2
    //   167: newarray char
    //   169: astore 5
    //   171: iconst_0
    //   172: istore_3
    //   173: goto -24 -> 149
    //   176: getstatic 31	o/EH:ॱ	I
    //   179: bipush 17
    //   181: iadd
    //   182: istore 4
    //   184: iload 4
    //   186: sipush 128
    //   189: irem
    //   190: putstatic 29	o/EH:ˏ	I
    //   193: iload 4
    //   195: iconst_2
    //   196: irem
    //   197: ifeq +6 -> 203
    //   200: goto -96 -> 104
    //   203: goto -93 -> 110
    //   206: iconst_1
    //   207: istore 4
    //   209: goto -171 -> 38
    //   212: goto -94 -> 118
    // Local variable table:
    //   start	length	slot	name	signature
    //   0	215	0	paramInt1	int
    //   0	215	1	paramChar	char
    //   0	215	2	paramInt2	int
    //   12	161	3	i	int
    //   38	170	4	j	int
    //   33	66	5	localException1	Exception
    //   113	6	5	localException2	Exception
    //   169	1	5	arrayOfChar	char[]
    // Exception table:
    //   from	to	target	type
    //   6	13	33	java/lang/Exception
    //   13	21	33	java/lang/Exception
    //   64	72	33	java/lang/Exception
    //   72	81	33	java/lang/Exception
    //   176	193	113	java/lang/Exception
  }
  
  /* Error */
  public boolean equals(Object paramObject)
  {
    // Byte code:
    //   0: goto +301 -> 301
    //   3: iconst_0
    //   4: istore_2
    //   5: goto +223 -> 228
    //   8: aload_0
    //   9: getfield 235	o/EH:applicationID	Ljava/lang/String;
    //   12: aload_1
    //   13: getfield 235	o/EH:applicationID	Ljava/lang/String;
    //   16: invokestatic 249	o/vq:ˊ	(Ljava/lang/Object;Ljava/lang/Object;)Z
    //   19: ifeq +6 -> 25
    //   22: goto +157 -> 179
    //   25: goto +42 -> 67
    //   28: bipush 74
    //   30: istore_2
    //   31: goto +116 -> 147
    //   34: getstatic 29	o/EH:ˏ	I
    //   37: bipush 65
    //   39: iadd
    //   40: istore_2
    //   41: iload_2
    //   42: sipush 128
    //   45: irem
    //   46: putstatic 31	o/EH:ॱ	I
    //   49: iload_2
    //   50: iconst_2
    //   51: irem
    //   52: ifne +6 -> 58
    //   55: goto +324 -> 379
    //   58: goto +12 -> 70
    //   61: bipush 80
    //   63: istore_2
    //   64: goto +243 -> 307
    //   67: goto +318 -> 385
    //   70: aload_0
    //   71: getfield 239	o/EH:deviceInfo	Lo/EH$ˊ;
    //   74: aload_1
    //   75: getfield 239	o/EH:deviceInfo	Lo/EH$ˊ;
    //   78: invokestatic 249	o/vq:ˊ	(Ljava/lang/Object;Ljava/lang/Object;)Z
    //   81: ifeq +6 -> 87
    //   84: goto +6 -> 90
    //   87: goto -20 -> 67
    //   90: goto +249 -> 339
    //   93: aload_0
    //   94: getfield 233	o/EH:applicationVersion	Ljava/lang/String;
    //   97: aload_1
    //   98: getfield 233	o/EH:applicationVersion	Ljava/lang/String;
    //   101: invokestatic 249	o/vq:ˊ	(Ljava/lang/Object;Ljava/lang/Object;)Z
    //   104: istore_3
    //   105: bipush 6
    //   107: iconst_0
    //   108: idiv
    //   109: istore_2
    //   110: iload_3
    //   111: ifeq +6 -> 117
    //   114: goto +238 -> 352
    //   117: goto -50 -> 67
    //   120: getstatic 29	o/EH:ˏ	I
    //   123: bipush 121
    //   125: iadd
    //   126: istore_2
    //   127: iload_2
    //   128: sipush 128
    //   131: irem
    //   132: putstatic 31	o/EH:ॱ	I
    //   135: iload_2
    //   136: iconst_2
    //   137: irem
    //   138: ifne +6 -> 144
    //   141: goto -138 -> 3
    //   144: goto +111 -> 255
    //   147: iload_2
    //   148: lookupswitch	default:+28->176, 21:+-81->67, 74:+-28->120
    //   176: goto -109 -> 67
    //   179: aload_0
    //   180: getfield 237	o/EH:customData	Lo/EH$If;
    //   183: aload_1
    //   184: getfield 237	o/EH:customData	Lo/EH$If;
    //   187: invokestatic 249	o/vq:ˊ	(Ljava/lang/Object;Ljava/lang/Object;)Z
    //   190: ifeq +6 -> 196
    //   193: goto -159 -> 34
    //   196: goto -129 -> 67
    //   199: getstatic 31	o/EH:ॱ	I
    //   202: bipush 107
    //   204: iadd
    //   205: istore_2
    //   206: iload_2
    //   207: sipush 128
    //   210: irem
    //   211: putstatic 29	o/EH:ˏ	I
    //   214: iload_2
    //   215: iconst_2
    //   216: irem
    //   217: ifeq +6 -> 223
    //   220: goto +84 -> 304
    //   223: goto +118 -> 341
    //   226: iconst_0
    //   227: ireturn
    //   228: iload_2
    //   229: tableswitch	default:+23->252, 0:+-136->93, 1:+183->412
    //   252: goto -159 -> 93
    //   255: iconst_1
    //   256: istore_2
    //   257: goto -29 -> 228
    //   260: bipush 76
    //   262: istore_2
    //   263: goto +44 -> 307
    //   266: astore_1
    //   267: aload_1
    //   268: athrow
    //   269: aload_1
    //   270: checkcast 2	o/EH
    //   273: astore_1
    //   274: aload_0
    //   275: getfield 231	o/EH:paymentAppInstanceId	Ljava/lang/String;
    //   278: astore 4
    //   280: aload 4
    //   282: aload_1
    //   283: getfield 231	o/EH:paymentAppInstanceId	Ljava/lang/String;
    //   286: invokestatic 249	o/vq:ˊ	(Ljava/lang/Object;Ljava/lang/Object;)Z
    //   289: ifeq +6 -> 295
    //   292: goto -264 -> 28
    //   295: bipush 21
    //   297: istore_2
    //   298: goto -151 -> 147
    //   301: goto -102 -> 199
    //   304: goto +37 -> 341
    //   307: iload_2
    //   308: lookupswitch	default:+28->336, 76:+44->352, 80:+-241->67
    //   336: goto +16 -> 352
    //   339: iconst_1
    //   340: ireturn
    //   341: aload_0
    //   342: aload_1
    //   343: if_acmpeq +6 -> 349
    //   346: goto +96 -> 442
    //   349: goto -259 -> 90
    //   352: getstatic 31	o/EH:ॱ	I
    //   355: bipush 71
    //   357: iadd
    //   358: istore_2
    //   359: iload_2
    //   360: sipush 128
    //   363: irem
    //   364: putstatic 29	o/EH:ˏ	I
    //   367: iload_2
    //   368: iconst_2
    //   369: irem
    //   370: ifeq +6 -> 376
    //   373: goto +85 -> 458
    //   376: goto -368 -> 8
    //   379: goto -309 -> 70
    //   382: goto -156 -> 226
    //   385: getstatic 29	o/EH:ˏ	I
    //   388: bipush 11
    //   390: iadd
    //   391: istore_2
    //   392: iload_2
    //   393: sipush 128
    //   396: irem
    //   397: putstatic 31	o/EH:ॱ	I
    //   400: iload_2
    //   401: iconst_2
    //   402: irem
    //   403: ifne +6 -> 409
    //   406: goto -24 -> 382
    //   409: goto -183 -> 226
    //   412: aload_0
    //   413: getfield 233	o/EH:applicationVersion	Ljava/lang/String;
    //   416: astore 5
    //   418: aload_1
    //   419: getfield 233	o/EH:applicationVersion	Ljava/lang/String;
    //   422: astore 4
    //   424: aload 5
    //   426: aload 4
    //   428: invokestatic 249	o/vq:ˊ	(Ljava/lang/Object;Ljava/lang/Object;)Z
    //   431: istore_3
    //   432: iload_3
    //   433: ifeq +6 -> 439
    //   436: goto -176 -> 260
    //   439: goto -378 -> 61
    //   442: aload_1
    //   443: instanceof 2
    //   446: ifeq +6 -> 452
    //   449: goto -180 -> 269
    //   452: goto -385 -> 67
    //   455: astore_1
    //   456: aload_1
    //   457: athrow
    //   458: aload_0
    //   459: getfield 235	o/EH:applicationID	Ljava/lang/String;
    //   462: aload_1
    //   463: getfield 235	o/EH:applicationID	Ljava/lang/String;
    //   466: invokestatic 249	o/vq:ˊ	(Ljava/lang/Object;Ljava/lang/Object;)Z
    //   469: pop
    //   470: new 251	java/lang/NullPointerException
    //   473: dup
    //   474: invokespecial 252	java/lang/NullPointerException:<init>	()V
    //   477: athrow
    // Local variable table:
    //   start	length	slot	name	signature
    //   0	478	0	this	EH
    //   0	478	1	paramObject	Object
    //   4	399	2	i	int
    //   104	329	3	bool	boolean
    //   278	149	4	str1	String
    //   416	9	5	str2	String
    // Exception table:
    //   from	to	target	type
    //   412	418	266	java/lang/Exception
    //   424	432	266	java/lang/Exception
    //   269	274	455	java/lang/Exception
    //   274	280	455	java/lang/Exception
    //   418	424	455	java/lang/Exception
  }
  
  public int hashCode()
  {
    break label378;
    int k = 0;
    break label413;
    Object localObject;
    int n = localObject.hashCode();
    for (;;)
    {
      break label55;
      n = 84;
      break label213;
      int i;
      label55:
      label72:
      do
      {
        i = ˏ + 49;
        ॱ = i % 128;
        if (i % 2 == 0) {
          break label386;
        }
        break label424;
        localObject = this.applicationID;
        if (localObject != null) {
          break label128;
        }
        break;
        localObject = this.paymentAppInstanceId;
      } while (localObject != null);
      break label416;
      label89:
      int m = 73;
      label128:
      label213:
      label297:
      label378:
      label381:
      label386:
      label389:
      label413:
      label416:
      label421:
      label424:
      label433:
      label442:
      do
      {
        for (;;)
        {
          try
          {
            j = ˏ + 107;
            ॱ = j % 128;
            if (j % 2 != 0)
            {
              break label433;
              j = 1;
              continue;
              k = localObject.hashCode();
              continue;
              localObject = this.deviceInfo;
              if (localObject == null)
              {
                break;
                localObject = this.applicationVersion;
                if (localObject != null) {
                  break label381;
                }
                continue;
                m = 3;
                continue;
                switch (j)
                {
                case 0: 
                default: 
                  break;
                }
                try
                {
                  m = localObject.hashCode();
                }
                catch (Exception localException1)
                {
                  throw localException1;
                }
              }
            }
            switch (n)
            {
            case 32: 
            default: 
              break label442;
              switch (m)
              {
              case 3: 
              default: 
                continue;
                j = 0;
                break;
              }
              m = 0;
              continue;
              int i1 = 3 / 5;
              break label389;
              break label55;
              localObject = this.customData;
              if (localObject != null) {
                continue;
              }
              break label89;
              n = 32;
              continue;
              i1 = ॱ + 73;
              ˏ = i1 % 128;
              if (i1 % 2 != 0) {
                continue;
              }
              break label421;
              break label55;
              i = localException1.hashCode();
              throw new NullPointerException();
            }
          }
          catch (Exception localException2)
          {
            throw localException2;
          }
          break label72;
          int j = 0;
          continue;
          break label424;
          for (;;)
          {
            return (((i * 31 + j) * 31 + k) * 31 + m) * 31 + n;
            break label297;
            i = 0;
            break;
          }
          i = localException2.hashCode();
          continue;
          j = localException2.hashCode();
          continue;
          n = 0;
        }
        k = ˏ + 93;
        ॱ = k % 128;
      } while (k % 2 == 0);
    }
  }
  
  public String toString()
  {
    break label36;
    String str1;
    return str1;
    for (;;)
    {
      try
      {
        int i = ˏ;
        i += 111;
        ॱ = i % 128;
        if (i % 2 == 0) {
          break;
        }
        return str1;
      }
      catch (Exception localException)
      {
        throw localException;
      }
      label36:
      String str2 = ˊ(71, 33855, 38).intern() + this.paymentAppInstanceId + ˊ(109, 37771, 21).intern() + this.applicationVersion + ˊ(130, 45871, 16).intern() + this.applicationID + ˊ(146, '\000', 13).intern() + this.customData + ˊ(159, '\000', 13).intern() + this.deviceInfo + ˊ(172, '\000', 1).intern();
    }
  }
  
  public static final class If
  {
    private static int ˊ = 1;
    private static long ˎ = -4074238170929412845L;
    private static int ॱ = 0;
    private final String CustomerID;
    private final String cardID;
    private final String cvv;
    
    public If(String paramString1, String paramString2, String paramString3)
    {
      this.cardID = paramString1;
      this.CustomerID = paramString2;
      this.cvv = paramString3;
    }
    
    private static String ˋ(char[] paramArrayOfChar)
    {
      break label58;
      int j = 1;
      for (;;)
      {
        char[] arrayOfChar;
        arrayOfChar[(j - 1)] = ((char)(int)(paramArrayOfChar[j] ^ j * i ^ ˎ));
        j += 1;
        break label162;
        label35:
        i = 0;
        break label87;
        i = 1;
        break label87;
        paramArrayOfChar = new String(arrayOfChar);
        break label215;
        for (;;)
        {
          label58:
          k = 75;
          break label183;
          for (;;)
          {
            arrayOfChar = paramArrayOfChar;
            i = arrayOfChar[0];
            arrayOfChar = new char[arrayOfChar.length - 1];
            break;
            label87:
            switch (i)
            {
            }
          }
          try
          {
            i = ˊ + 121;
            ॱ = i % 128;
            if (i % 2 != 0) {
              break label35;
            }
          }
          catch (Exception paramArrayOfChar)
          {
            throw paramArrayOfChar;
          }
          arrayOfChar = paramArrayOfChar;
          i = arrayOfChar[1];
          arrayOfChar = new char[arrayOfChar.length + 0];
          break;
          label162:
          if (j >= paramArrayOfChar.length) {
            break label174;
          }
        }
        label174:
        int k = 24;
        label183:
        switch (k)
        {
        }
      }
      label215:
      int i = ˊ + 99;
      ॱ = i % 128;
      if (i % 2 != 0) {
        return paramArrayOfChar;
      }
      return paramArrayOfChar;
    }
    
    public boolean equals(Object paramObject)
    {
      break label165;
      return true;
      label5:
      int i;
      for (;;)
      {
        paramObject = (If)paramObject;
        if (vq.ˊ(this.cardID, paramObject.cardID)) {
          break label140;
        }
        break;
        i = 0;
        break label168;
        i = 1;
        break label238;
        label40:
        i = 1;
        break label82;
        label45:
        i = ॱ + 55;
        ˊ = i % 128;
        if (i % 2 == 0) {
          break label235;
        }
      }
      for (;;)
      {
        label72:
        return false;
        label74:
        break label205;
        for (;;)
        {
          i = 0;
          break label238;
          label82:
          switch (i)
          {
          }
          break label45;
          if (vq.ˊ(this.cvv, paramObject.cvv)) {
            break label74;
          }
          break label72;
          label127:
          if (this != paramObject) {
            break label166;
          }
          i = 1;
          break label168;
          label140:
          if (vq.ˊ(this.CustomerID, paramObject.CustomerID)) {
            break;
          }
        }
        label165:
        label166:
        label168:
        do
        {
          i = 0;
          break label82;
          break label127;
          break;
          switch (i)
          {
          }
        } while ((paramObject instanceof If));
        break label40;
        label205:
        i = ॱ + 89;
        ˊ = i % 128;
        if (i % 2 != 0) {
          break;
        }
        break;
        label235:
        break label5;
        label238:
        switch (i)
        {
        }
      }
    }
    
    /* Error */
    public int hashCode()
    {
      // Byte code:
      //   0: goto +105 -> 105
      //   3: goto +82 -> 85
      //   6: astore 4
      //   8: aload 4
      //   10: athrow
      //   11: iload_3
      //   12: lookupswitch	default:+28->40, 3:+183->195, 38:+48->60
      //   40: goto +20 -> 60
      //   43: aload_0
      //   44: getfield 70	o/EH$If:cardID	Ljava/lang/String;
      //   47: astore 4
      //   49: aload 4
      //   51: ifnull +6 -> 57
      //   54: goto +81 -> 135
      //   57: goto +214 -> 271
      //   60: aload 4
      //   62: invokevirtual 88	java/lang/Object:hashCode	()I
      //   65: istore_3
      //   66: goto +193 -> 259
      //   69: iconst_1
      //   70: istore_1
      //   71: goto +157 -> 228
      //   74: aload 4
      //   76: invokevirtual 88	java/lang/Object:hashCode	()I
      //   79: istore_1
      //   80: bipush 59
      //   82: iconst_0
      //   83: idiv
      //   84: istore_3
      //   85: aload_0
      //   86: getfield 74	o/EH$If:cvv	Ljava/lang/String;
      //   89: astore 4
      //   91: aload 4
      //   93: ifnull +6 -> 99
      //   96: goto +114 -> 210
      //   99: goto +177 -> 276
      //   102: goto +157 -> 259
      //   105: goto -62 -> 43
      //   108: getstatic 20	o/EH$If:ॱ	I
      //   111: bipush 121
      //   113: iadd
      //   114: istore_1
      //   115: iload_1
      //   116: sipush 128
      //   119: irem
      //   120: putstatic 22	o/EH$If:ˊ	I
      //   123: iload_1
      //   124: iconst_2
      //   125: irem
      //   126: ifne +6 -> 132
      //   129: goto +59 -> 188
      //   132: goto +26 -> 158
      //   135: aload 4
      //   137: invokevirtual 88	java/lang/Object:hashCode	()I
      //   140: istore_2
      //   141: aload_0
      //   142: getfield 72	o/EH$If:CustomerID	Ljava/lang/String;
      //   145: astore 4
      //   147: aload 4
      //   149: ifnull +6 -> 155
      //   152: goto +9 -> 161
      //   155: goto +50 -> 205
      //   158: goto -17 -> 141
      //   161: getstatic 22	o/EH$If:ˊ	I
      //   164: bipush 81
      //   166: iadd
      //   167: istore_1
      //   168: iload_1
      //   169: sipush 128
      //   172: irem
      //   173: putstatic 20	o/EH$If:ॱ	I
      //   176: iload_1
      //   177: iconst_2
      //   178: irem
      //   179: ifeq +6 -> 185
      //   182: goto -113 -> 69
      //   185: goto +40 -> 225
      //   188: iconst_5
      //   189: iconst_4
      //   190: idiv
      //   191: istore_1
      //   192: goto -51 -> 141
      //   195: iconst_0
      //   196: istore_3
      //   197: goto -95 -> 102
      //   200: astore 4
      //   202: aload 4
      //   204: athrow
      //   205: iconst_0
      //   206: istore_1
      //   207: goto -204 -> 3
      //   210: bipush 38
      //   212: istore_3
      //   213: goto -202 -> 11
      //   216: aload 4
      //   218: invokevirtual 88	java/lang/Object:hashCode	()I
      //   221: istore_1
      //   222: goto -137 -> 85
      //   225: bipush 76
      //   227: istore_1
      //   228: iload_1
      //   229: lookupswitch	default:+27->256, 1:+-155->74, 76:+-13->216
      //   256: goto -40 -> 216
      //   259: iload_2
      //   260: bipush 31
      //   262: imul
      //   263: iload_1
      //   264: iadd
      //   265: bipush 31
      //   267: imul
      //   268: iload_3
      //   269: iadd
      //   270: ireturn
      //   271: iconst_0
      //   272: istore_2
      //   273: goto -165 -> 108
      //   276: iconst_3
      //   277: istore_3
      //   278: goto -267 -> 11
      // Local variable table:
      //   start	length	slot	name	signature
      //   0	281	0	this	If
      //   70	195	1	i	int
      //   140	133	2	j	int
      //   11	267	3	k	int
      //   6	3	4	localException1	Exception
      //   47	101	4	str	String
      //   200	17	4	localException2	Exception
      // Exception table:
      //   from	to	target	type
      //   108	115	6	java/lang/Exception
      //   115	123	6	java/lang/Exception
      //   135	141	200	java/lang/Exception
    }
    
    public String toString()
    {
      String str = ˋ(new char[] { -22443, -4859, 5580, -16993, -7117, 3285, -19328, -8444, 2010, -20582, -10720, 32412, -22900, -14045, 29127, -26228, -16374, 26866, -28460 }).intern() + this.cardID + ˋ(new char[] { -5673, -21272, -26979, -1835, -7622, -11181, 15981, 8605, 3014, 32249, 26375, 18791, -19645, -25915 }).intern() + this.CustomerID + ˋ(new char[] { -725, -18412, -16539, -19727, -20023, -19278, -21972 }).intern() + this.cvv + ˋ(new char[] { 12781, 29911 }).intern();
      int i = ˊ + 87;
      ॱ = i % 128;
      if (i % 2 != 0) {
        return str;
      }
      return str;
    }
  }
  
  public static final class ˊ
  {
    private static char[] ˊ = { -22834, -20772, -18701, -16662, -30988, -29054, 16302, 14268, 12171, 10126, 8075, 6132, 4092, 1996, 32735, -4959, -7001, -848, -2906, -13162, -15111, -8966, -11057, -21293, -23340, -6962, -4927, -2880, -791, -15119, -13175, -11088, -9047, -23369, -21327, 115, 2155, 4206, 6211, 8281, 10282, 12314, 14359, 16413, 18460, 20713, 22760, -29854, -31899, -25750, -27837, -21638, -23773, -17613, -19694, -13541, -15608, -19966, -17909, -24062, -21975, -28120, -26032, -32192, -30137, -3484, -1428, -7531, -5499, -11594, -9557, -15654, -13628, 13032, 68, 2155, 4202, 6211, 8283, 10275, 12317, 14348, 16406, 18449, 20644, 22773, 24795, 26872, 28837, 30911, -32635, -30509, 44, 2094, 4211, 6233, 8302, 10275, 12326, 14353, 16409, 18449, 20706, 22695, 44, 2094, 4210, 6220, 8283, 10245, 12341, 14354, 16401, 18460, 20704, 22783, 24725, 44, 2094, 4216, 6223, 8270, 10287, 12343, 14343, 16446, 18463, 20705, 22783, 24725, 44, 2094, 4207, 6223, 8266, 10287, 12341, 14350, 16446, 18443, 20705, 22776, 24781, 26820, 28921, 44, 2094, 4218, 6213, 8266, 10283, 12306, 14339, 16403, 18442, 20707, 22760, 24725, 44, 2094, 4207, 6238, 8279, 10292, 12341, 14341, 16405, 18474, 20713, 22777, 24768, 26840, 28843, 30910, -32625, -30583, -28539, -26313, 41 };
    private static long ˋ;
    private static int ˏ;
    private static int ॱ = 0;
    private final String deviceName;
    private final String formFactor;
    private final String nfcCapable;
    private final String osName;
    private final String osVersion;
    private final String serialNumber;
    private final String storageTechnology;
    
    static
    {
      ˏ = 1;
      ˋ = -3557671278846539762L;
    }
    
    public ˊ(String paramString1, String paramString2, String paramString3, String paramString4, String paramString5, String paramString6, String paramString7)
    {
      this.osName = paramString1;
      this.osVersion = paramString2;
      this.nfcCapable = paramString3;
      this.deviceName = paramString4;
      this.serialNumber = paramString5;
      this.formFactor = paramString6;
      this.storageTechnology = paramString7;
    }
    
    private static String ˊ(int paramInt1, char paramChar, int paramInt2)
    {
      break label147;
      return new String(arrayOfChar);
      char[] arrayOfChar = new char[paramInt2];
      int i = 0;
      label99:
      label140:
      label147:
      for (;;)
      {
        i = ॱ + 31;
        ˏ = i % 128;
        if (i % 2 != 0) {
          break label99;
        }
        for (;;)
        {
          if (i < paramInt2) {
            break label140;
          }
          break label150;
          arrayOfChar = new char[paramInt2];
          i = 0;
          continue;
          for (;;)
          {
            switch (i)
            {
            }
            break;
            i = 1;
            continue;
            i = 0;
          }
          arrayOfChar[i] = ((char)(int)(ˊ[(paramInt1 + i)] ^ i * ˋ ^ paramChar));
          i += 1;
        }
        j = 56;
        break label190;
      }
      label150:
      int j = 44;
      for (;;)
      {
        j = ॱ + 69;
        ˏ = j % 128;
        if (j % 2 != 0) {
          break;
        }
        break;
        label190:
        switch (j)
        {
        }
      }
    }
    
    /* Error */
    public boolean equals(Object paramObject)
    {
      // Byte code:
      //   0: goto +462 -> 462
      //   3: goto +72 -> 75
      //   6: iconst_0
      //   7: ireturn
      //   8: getstatic 27	o/EH$ˊ:ˏ	I
      //   11: bipush 25
      //   13: iadd
      //   14: istore_2
      //   15: iload_2
      //   16: sipush 128
      //   19: irem
      //   20: putstatic 25	o/EH$ˊ:ॱ	I
      //   23: iload_2
      //   24: iconst_2
      //   25: irem
      //   26: ifeq +6 -> 32
      //   29: goto +259 -> 288
      //   32: goto +314 -> 346
      //   35: aload_0
      //   36: getfield 218	o/EH$ˊ:serialNumber	Ljava/lang/String;
      //   39: astore_1
      //   40: aload 5
      //   42: getfield 218	o/EH$ˊ:serialNumber	Ljava/lang/String;
      //   45: astore 4
      //   47: aload_1
      //   48: aload 4
      //   50: invokestatic 232	o/vq:ˊ	(Ljava/lang/Object;Ljava/lang/Object;)Z
      //   53: istore_3
      //   54: iload_3
      //   55: ifeq +6 -> 61
      //   58: goto +79 -> 137
      //   61: goto -58 -> 3
      //   64: aload_0
      //   65: aload_1
      //   66: if_acmpeq +6 -> 72
      //   69: goto -61 -> 8
      //   72: goto +182 -> 254
      //   75: getstatic 27	o/EH$ˊ:ˏ	I
      //   78: bipush 85
      //   80: iadd
      //   81: istore_2
      //   82: iload_2
      //   83: sipush 128
      //   86: irem
      //   87: putstatic 25	o/EH$ˊ:ॱ	I
      //   90: iload_2
      //   91: iconst_2
      //   92: irem
      //   93: ifeq +6 -> 99
      //   96: goto +297 -> 393
      //   99: goto +352 -> 451
      //   102: aload_0
      //   103: getfield 212	o/EH$ˊ:osVersion	Ljava/lang/String;
      //   106: aload 5
      //   108: getfield 212	o/EH$ˊ:osVersion	Ljava/lang/String;
      //   111: invokestatic 232	o/vq:ˊ	(Ljava/lang/Object;Ljava/lang/Object;)Z
      //   114: ifeq +6 -> 120
      //   117: goto +218 -> 335
      //   120: goto +336 -> 456
      //   123: aconst_null
      //   124: arraylength
      //   125: istore_2
      //   126: aload_0
      //   127: aload_1
      //   128: if_acmpeq +6 -> 134
      //   131: goto +236 -> 367
      //   134: goto +228 -> 362
      //   137: aload_0
      //   138: getfield 220	o/EH$ˊ:formFactor	Ljava/lang/String;
      //   141: aload 5
      //   143: getfield 220	o/EH$ˊ:formFactor	Ljava/lang/String;
      //   146: invokestatic 232	o/vq:ˊ	(Ljava/lang/Object;Ljava/lang/Object;)Z
      //   149: ifeq +6 -> 155
      //   152: goto +6 -> 158
      //   155: goto -152 -> 3
      //   158: aload_0
      //   159: getfield 222	o/EH$ˊ:storageTechnology	Ljava/lang/String;
      //   162: aload 5
      //   164: getfield 222	o/EH$ˊ:storageTechnology	Ljava/lang/String;
      //   167: invokestatic 232	o/vq:ˊ	(Ljava/lang/Object;Ljava/lang/Object;)Z
      //   170: ifeq +6 -> 176
      //   173: goto +81 -> 254
      //   176: goto -173 -> 3
      //   179: aload_0
      //   180: getfield 214	o/EH$ˊ:nfcCapable	Ljava/lang/String;
      //   183: aload 5
      //   185: getfield 214	o/EH$ˊ:nfcCapable	Ljava/lang/String;
      //   188: invokestatic 232	o/vq:ˊ	(Ljava/lang/Object;Ljava/lang/Object;)Z
      //   191: ifeq +6 -> 197
      //   194: goto +178 -> 372
      //   197: goto -194 -> 3
      //   200: aload_1
      //   201: checkcast 2	o/EH$ˊ
      //   204: astore 5
      //   206: aload_0
      //   207: getfield 210	o/EH$ˊ:osName	Ljava/lang/String;
      //   210: aload 5
      //   212: getfield 210	o/EH$ˊ:osName	Ljava/lang/String;
      //   215: invokestatic 232	o/vq:ˊ	(Ljava/lang/Object;Ljava/lang/Object;)Z
      //   218: ifeq +6 -> 224
      //   221: goto -119 -> 102
      //   224: goto -221 -> 3
      //   227: getstatic 27	o/EH$ˊ:ˏ	I
      //   230: bipush 125
      //   232: iadd
      //   233: istore_2
      //   234: iload_2
      //   235: sipush 128
      //   238: irem
      //   239: putstatic 25	o/EH$ˊ:ॱ	I
      //   242: iload_2
      //   243: iconst_2
      //   244: irem
      //   245: ifeq +6 -> 251
      //   248: goto +111 -> 359
      //   251: goto -216 -> 35
      //   254: iconst_1
      //   255: ireturn
      //   256: getstatic 25	o/EH$ˊ:ॱ	I
      //   259: istore_2
      //   260: iload_2
      //   261: bipush 11
      //   263: iadd
      //   264: istore_2
      //   265: iload_2
      //   266: sipush 128
      //   269: irem
      //   270: putstatic 27	o/EH$ˊ:ˏ	I
      //   273: iload_2
      //   274: iconst_2
      //   275: irem
      //   276: ifne +6 -> 282
      //   279: goto -156 -> 123
      //   282: goto -218 -> 64
      //   285: astore_1
      //   286: aload_1
      //   287: athrow
      //   288: aload_1
      //   289: instanceof 2
      //   292: istore_3
      //   293: aconst_null
      //   294: arraylength
      //   295: istore_2
      //   296: iload_3
      //   297: ifeq +6 -> 303
      //   300: goto -100 -> 200
      //   303: goto -300 -> 3
      //   306: iload_2
      //   307: lookupswitch	default:+25->332, 39:+-304->3, 45:+-128->179
      //   332: goto -329 -> 3
      //   335: bipush 45
      //   337: istore_2
      //   338: goto -32 -> 306
      //   341: aconst_null
      //   342: arraylength
      //   343: istore_2
      //   344: iconst_0
      //   345: ireturn
      //   346: aload_1
      //   347: instanceof 2
      //   350: ifeq +6 -> 356
      //   353: goto -153 -> 200
      //   356: goto -353 -> 3
      //   359: goto -324 -> 35
      //   362: iconst_1
      //   363: istore_2
      //   364: goto +34 -> 398
      //   367: iconst_0
      //   368: istore_2
      //   369: goto +29 -> 398
      //   372: aload_0
      //   373: getfield 216	o/EH$ˊ:deviceName	Ljava/lang/String;
      //   376: aload 5
      //   378: getfield 216	o/EH$ˊ:deviceName	Ljava/lang/String;
      //   381: invokestatic 232	o/vq:ˊ	(Ljava/lang/Object;Ljava/lang/Object;)Z
      //   384: ifeq +6 -> 390
      //   387: goto -160 -> 227
      //   390: goto -387 -> 3
      //   393: iconst_1
      //   394: istore_2
      //   395: goto +31 -> 426
      //   398: iload_2
      //   399: tableswitch	default:+21->420, 0:+-391->8, 1:+-145->254
      //   420: goto -412 -> 8
      //   423: astore_1
      //   424: aload_1
      //   425: athrow
      //   426: iload_2
      //   427: tableswitch	default:+21->448, 0:+-421->6, 1:+-86->341
      //   448: goto -442 -> 6
      //   451: iconst_0
      //   452: istore_2
      //   453: goto -27 -> 426
      //   456: bipush 39
      //   458: istore_2
      //   459: goto -153 -> 306
      //   462: goto -206 -> 256
      // Local variable table:
      //   start	length	slot	name	signature
      //   0	465	0	this	ˊ
      //   0	465	1	paramObject	Object
      //   14	445	2	i	int
      //   53	244	3	bool	boolean
      //   45	4	4	str	String
      //   40	337	5	localˊ	ˊ
      // Exception table:
      //   from	to	target	type
      //   35	40	285	java/lang/Exception
      //   40	47	285	java/lang/Exception
      //   47	54	285	java/lang/Exception
      //   256	260	285	java/lang/Exception
      //   265	273	285	java/lang/Exception
      //   40	47	423	java/lang/Exception
    }
    
    /* Error */
    public int hashCode()
    {
      // Byte code:
      //   0: goto +246 -> 246
      //   3: iload_1
      //   4: lookupswitch	default:+28->32, 36:+595->599, 71:+622->626
      //   32: goto +594 -> 626
      //   35: bipush 78
      //   37: istore_2
      //   38: goto +231 -> 269
      //   41: aload_0
      //   42: getfield 210	o/EH$ˊ:osName	Ljava/lang/String;
      //   45: astore 9
      //   47: aload 9
      //   49: ifnull +6 -> 55
      //   52: goto +274 -> 326
      //   55: goto +209 -> 264
      //   58: bipush 6
      //   60: istore_3
      //   61: goto +126 -> 187
      //   64: iconst_0
      //   65: istore_3
      //   66: goto +312 -> 378
      //   69: bipush 63
      //   71: istore_1
      //   72: goto +85 -> 157
      //   75: iconst_0
      //   76: istore 6
      //   78: goto +418 -> 496
      //   81: iconst_0
      //   82: istore 7
      //   84: goto +135 -> 219
      //   87: iconst_0
      //   88: istore 4
      //   90: goto +285 -> 375
      //   93: iload_1
      //   94: tableswitch	default:+22->116, 0:+614->708, 1:+-7->87
      //   116: goto -29 -> 87
      //   119: goto +549 -> 668
      //   122: getstatic 25	o/EH$ˊ:ॱ	I
      //   125: iconst_3
      //   126: iadd
      //   127: istore_3
      //   128: iload_3
      //   129: sipush 128
      //   132: irem
      //   133: putstatic 27	o/EH$ˊ:ˏ	I
      //   136: iload_3
      //   137: iconst_2
      //   138: irem
      //   139: ifne +6 -> 145
      //   142: goto +329 -> 471
      //   145: goto +491 -> 636
      //   148: aload 9
      //   150: invokevirtual 236	java/lang/Object:hashCode	()I
      //   153: istore_1
      //   154: goto +388 -> 542
      //   157: iload_1
      //   158: lookupswitch	default:+26->184, 63:+-10->148, 78:+301->459
      //   184: goto +275 -> 459
      //   187: iload_3
      //   188: lookupswitch	default:+28->216, 3:+-124->64, 6:+-66->122
      //   216: goto -152 -> 64
      //   219: getstatic 25	o/EH$ˊ:ॱ	I
      //   222: bipush 7
      //   224: iadd
      //   225: istore_3
      //   226: iload_3
      //   227: sipush 128
      //   230: irem
      //   231: putstatic 27	o/EH$ˊ:ˏ	I
      //   234: iload_3
      //   235: iconst_2
      //   236: irem
      //   237: ifne +6 -> 243
      //   240: goto +179 -> 419
      //   243: goto -124 -> 119
      //   246: goto -205 -> 41
      //   249: iconst_1
      //   250: istore_3
      //   251: goto +262 -> 513
      //   254: astore 9
      //   256: aload 9
      //   258: athrow
      //   259: iconst_0
      //   260: istore_3
      //   261: goto +171 -> 432
      //   264: iconst_1
      //   265: istore_1
      //   266: goto -173 -> 93
      //   269: iload_2
      //   270: lookupswitch	default:+26->296, 41:+61->331, 78:+393->663
      //   296: goto +35 -> 331
      //   299: bipush 71
      //   301: istore_1
      //   302: goto -299 -> 3
      //   305: aload 9
      //   307: invokevirtual 236	java/lang/Object:hashCode	()I
      //   310: istore 5
      //   312: goto +227 -> 539
      //   315: iconst_0
      //   316: istore 5
      //   318: goto +40 -> 358
      //   321: iconst_3
      //   322: istore_3
      //   323: goto -136 -> 187
      //   326: iconst_0
      //   327: istore_1
      //   328: goto -235 -> 93
      //   331: getstatic 27	o/EH$ˊ:ˏ	I
      //   334: bipush 53
      //   336: iadd
      //   337: istore_2
      //   338: iload_2
      //   339: sipush 128
      //   342: irem
      //   343: putstatic 25	o/EH$ˊ:ॱ	I
      //   346: iload_2
      //   347: iconst_2
      //   348: irem
      //   349: ifeq +6 -> 355
      //   352: goto +342 -> 694
      //   355: goto +330 -> 685
      //   358: aload_0
      //   359: getfield 218	o/EH$ˊ:serialNumber	Ljava/lang/String;
      //   362: astore 9
      //   364: aload 9
      //   366: ifnull +6 -> 372
      //   369: goto -120 -> 249
      //   372: goto +259 -> 631
      //   375: goto +184 -> 559
      //   378: iload 4
      //   380: bipush 31
      //   382: imul
      //   383: iload_1
      //   384: iadd
      //   385: bipush 31
      //   387: imul
      //   388: iload_2
      //   389: iadd
      //   390: bipush 31
      //   392: imul
      //   393: iload 5
      //   395: iadd
      //   396: bipush 31
      //   398: imul
      //   399: iload 6
      //   401: iadd
      //   402: bipush 31
      //   404: imul
      //   405: iload 7
      //   407: iadd
      //   408: bipush 31
      //   410: imul
      //   411: iload_3
      //   412: iadd
      //   413: ireturn
      //   414: astore 9
      //   416: aload 9
      //   418: athrow
      //   419: goto +249 -> 668
      //   422: aload 9
      //   424: invokevirtual 236	java/lang/Object:hashCode	()I
      //   427: istore 6
      //   429: goto +67 -> 496
      //   432: iload_3
      //   433: tableswitch	default:+23->456, 0:+-352->81, 1:+220->653
      //   456: goto -375 -> 81
      //   459: aload 9
      //   461: invokevirtual 236	java/lang/Object:hashCode	()I
      //   464: istore_1
      //   465: aconst_null
      //   466: arraylength
      //   467: istore_2
      //   468: goto +74 -> 542
      //   471: aload 9
      //   473: invokevirtual 236	java/lang/Object:hashCode	()I
      //   476: istore_3
      //   477: aconst_null
      //   478: arraylength
      //   479: istore 8
      //   481: goto -103 -> 378
      //   484: bipush 41
      //   486: istore_2
      //   487: goto -218 -> 269
      //   490: bipush 36
      //   492: istore_1
      //   493: goto -490 -> 3
      //   496: aload_0
      //   497: getfield 220	o/EH$ˊ:formFactor	Ljava/lang/String;
      //   500: astore 9
      //   502: aload 9
      //   504: ifnull +6 -> 510
      //   507: goto +141 -> 648
      //   510: goto -251 -> 259
      //   513: iload_3
      //   514: tableswitch	default:+22->536, 0:+-439->75, 1:+-92->422
      //   536: goto -461 -> 75
      //   539: goto -181 -> 358
      //   542: aload_0
      //   543: getfield 214	o/EH$ˊ:nfcCapable	Ljava/lang/String;
      //   546: astore 9
      //   548: aload 9
      //   550: ifnull +6 -> 556
      //   553: goto -69 -> 484
      //   556: goto -521 -> 35
      //   559: aload_0
      //   560: getfield 212	o/EH$ˊ:osVersion	Ljava/lang/String;
      //   563: astore 9
      //   565: aload 9
      //   567: ifnull +6 -> 573
      //   570: goto -80 -> 490
      //   573: goto -274 -> 299
      //   576: aload_0
      //   577: getfield 216	o/EH$ˊ:deviceName	Ljava/lang/String;
      //   580: astore 9
      //   582: aload 9
      //   584: ifnull +6 -> 590
      //   587: goto -282 -> 305
      //   590: goto -275 -> 315
      //   593: bipush 78
      //   595: istore_1
      //   596: goto -439 -> 157
      //   599: getstatic 27	o/EH$ˊ:ˏ	I
      //   602: bipush 25
      //   604: iadd
      //   605: istore_1
      //   606: iload_1
      //   607: sipush 128
      //   610: irem
      //   611: putstatic 25	o/EH$ˊ:ॱ	I
      //   614: iload_1
      //   615: iconst_2
      //   616: irem
      //   617: ifeq +6 -> 623
      //   620: goto -27 -> 593
      //   623: goto -554 -> 69
      //   626: iconst_0
      //   627: istore_1
      //   628: goto +17 -> 645
      //   631: iconst_0
      //   632: istore_3
      //   633: goto -120 -> 513
      //   636: aload 9
      //   638: invokevirtual 236	java/lang/Object:hashCode	()I
      //   641: istore_3
      //   642: goto -264 -> 378
      //   645: goto -103 -> 542
      //   648: iconst_1
      //   649: istore_3
      //   650: goto -218 -> 432
      //   653: aload 9
      //   655: invokevirtual 236	java/lang/Object:hashCode	()I
      //   658: istore 7
      //   660: goto +8 -> 668
      //   663: iconst_0
      //   664: istore_2
      //   665: goto -89 -> 576
      //   668: aload_0
      //   669: getfield 222	o/EH$ˊ:storageTechnology	Ljava/lang/String;
      //   672: astore 9
      //   674: aload 9
      //   676: ifnull +6 -> 682
      //   679: goto -621 -> 58
      //   682: goto -361 -> 321
      //   685: aload 9
      //   687: invokevirtual 236	java/lang/Object:hashCode	()I
      //   690: istore_2
      //   691: goto -115 -> 576
      //   694: aload 9
      //   696: invokevirtual 236	java/lang/Object:hashCode	()I
      //   699: istore_2
      //   700: bipush 19
      //   702: iconst_0
      //   703: idiv
      //   704: istore_3
      //   705: goto -129 -> 576
      //   708: aload 9
      //   710: invokevirtual 236	java/lang/Object:hashCode	()I
      //   713: istore 4
      //   715: goto -156 -> 559
      // Local variable table:
      //   start	length	slot	name	signature
      //   0	718	0	this	ˊ
      //   3	625	1	i	int
      //   37	663	2	j	int
      //   60	645	3	k	int
      //   88	626	4	m	int
      //   310	86	5	n	int
      //   76	352	6	i1	int
      //   82	577	7	i2	int
      //   479	1	8	i3	int
      //   45	104	9	str1	String
      //   254	52	9	localException1	Exception
      //   362	3	9	str2	String
      //   414	58	9	localException2	Exception
      //   500	209	9	str3	String
      // Exception table:
      //   from	to	target	type
      //   668	674	254	java/lang/Exception
      //   653	660	414	java/lang/Exception
    }
    
    /* Error */
    public String toString()
    {
      // Byte code:
      //   0: goto +222 -> 222
      //   3: astore_2
      //   4: aload_2
      //   5: athrow
      //   6: astore_2
      //   7: aload_2
      //   8: athrow
      //   9: getstatic 27	o/EH$ˊ:ˏ	I
      //   12: bipush 105
      //   14: iadd
      //   15: istore_1
      //   16: iload_1
      //   17: sipush 128
      //   20: irem
      //   21: putstatic 25	o/EH$ˊ:ॱ	I
      //   24: iload_1
      //   25: iconst_2
      //   26: irem
      //   27: ifeq +5 -> 32
      //   30: aload_2
      //   31: areturn
      //   32: aload_2
      //   33: areturn
      //   34: new 239	java/lang/StringBuilder
      //   37: dup
      //   38: invokespecial 240	java/lang/StringBuilder:<init>	()V
      //   41: astore_2
      //   42: bipush 74
      //   44: iconst_0
      //   45: bipush 18
      //   47: invokestatic 190	o/EH$ˊ:ˊ	(ICI)Ljava/lang/String;
      //   50: astore_3
      //   51: aload_3
      //   52: invokevirtual 196	java/lang/String:intern	()Ljava/lang/String;
      //   55: astore_3
      //   56: aload_2
      //   57: aload_3
      //   58: invokevirtual 244	java/lang/StringBuilder:append	(Ljava/lang/String;)Ljava/lang/StringBuilder;
      //   61: astore_2
      //   62: aload_0
      //   63: getfield 210	o/EH$ˊ:osName	Ljava/lang/String;
      //   66: astore_3
      //   67: aload_2
      //   68: aload_3
      //   69: invokevirtual 244	java/lang/StringBuilder:append	(Ljava/lang/String;)Ljava/lang/StringBuilder;
      //   72: bipush 92
      //   74: iconst_0
      //   75: bipush 12
      //   77: invokestatic 190	o/EH$ˊ:ˊ	(ICI)Ljava/lang/String;
      //   80: invokevirtual 196	java/lang/String:intern	()Ljava/lang/String;
      //   83: invokevirtual 244	java/lang/StringBuilder:append	(Ljava/lang/String;)Ljava/lang/StringBuilder;
      //   86: aload_0
      //   87: getfield 212	o/EH$ˊ:osVersion	Ljava/lang/String;
      //   90: invokevirtual 244	java/lang/StringBuilder:append	(Ljava/lang/String;)Ljava/lang/StringBuilder;
      //   93: bipush 104
      //   95: iconst_0
      //   96: bipush 13
      //   98: invokestatic 190	o/EH$ˊ:ˊ	(ICI)Ljava/lang/String;
      //   101: invokevirtual 196	java/lang/String:intern	()Ljava/lang/String;
      //   104: invokevirtual 244	java/lang/StringBuilder:append	(Ljava/lang/String;)Ljava/lang/StringBuilder;
      //   107: aload_0
      //   108: getfield 214	o/EH$ˊ:nfcCapable	Ljava/lang/String;
      //   111: invokevirtual 244	java/lang/StringBuilder:append	(Ljava/lang/String;)Ljava/lang/StringBuilder;
      //   114: bipush 117
      //   116: iconst_0
      //   117: bipush 13
      //   119: invokestatic 190	o/EH$ˊ:ˊ	(ICI)Ljava/lang/String;
      //   122: invokevirtual 196	java/lang/String:intern	()Ljava/lang/String;
      //   125: invokevirtual 244	java/lang/StringBuilder:append	(Ljava/lang/String;)Ljava/lang/StringBuilder;
      //   128: aload_0
      //   129: getfield 216	o/EH$ˊ:deviceName	Ljava/lang/String;
      //   132: invokevirtual 244	java/lang/StringBuilder:append	(Ljava/lang/String;)Ljava/lang/StringBuilder;
      //   135: sipush 130
      //   138: iconst_0
      //   139: bipush 15
      //   141: invokestatic 190	o/EH$ˊ:ˊ	(ICI)Ljava/lang/String;
      //   144: invokevirtual 196	java/lang/String:intern	()Ljava/lang/String;
      //   147: invokevirtual 244	java/lang/StringBuilder:append	(Ljava/lang/String;)Ljava/lang/StringBuilder;
      //   150: aload_0
      //   151: getfield 218	o/EH$ˊ:serialNumber	Ljava/lang/String;
      //   154: invokevirtual 244	java/lang/StringBuilder:append	(Ljava/lang/String;)Ljava/lang/StringBuilder;
      //   157: sipush 145
      //   160: iconst_0
      //   161: bipush 13
      //   163: invokestatic 190	o/EH$ˊ:ˊ	(ICI)Ljava/lang/String;
      //   166: invokevirtual 196	java/lang/String:intern	()Ljava/lang/String;
      //   169: invokevirtual 244	java/lang/StringBuilder:append	(Ljava/lang/String;)Ljava/lang/StringBuilder;
      //   172: aload_0
      //   173: getfield 220	o/EH$ˊ:formFactor	Ljava/lang/String;
      //   176: invokevirtual 244	java/lang/StringBuilder:append	(Ljava/lang/String;)Ljava/lang/StringBuilder;
      //   179: sipush 158
      //   182: iconst_0
      //   183: bipush 20
      //   185: invokestatic 190	o/EH$ˊ:ˊ	(ICI)Ljava/lang/String;
      //   188: invokevirtual 196	java/lang/String:intern	()Ljava/lang/String;
      //   191: invokevirtual 244	java/lang/StringBuilder:append	(Ljava/lang/String;)Ljava/lang/StringBuilder;
      //   194: aload_0
      //   195: getfield 222	o/EH$ˊ:storageTechnology	Ljava/lang/String;
      //   198: invokevirtual 244	java/lang/StringBuilder:append	(Ljava/lang/String;)Ljava/lang/StringBuilder;
      //   201: sipush 178
      //   204: iconst_0
      //   205: iconst_1
      //   206: invokestatic 190	o/EH$ˊ:ˊ	(ICI)Ljava/lang/String;
      //   209: invokevirtual 196	java/lang/String:intern	()Ljava/lang/String;
      //   212: invokevirtual 244	java/lang/StringBuilder:append	(Ljava/lang/String;)Ljava/lang/StringBuilder;
      //   215: invokevirtual 246	java/lang/StringBuilder:toString	()Ljava/lang/String;
      //   218: astore_2
      //   219: goto -210 -> 9
      //   222: goto -188 -> 34
      // Local variable table:
      //   start	length	slot	name	signature
      //   0	225	0	this	ˊ
      //   15	12	1	i	int
      //   3	2	2	localException1	Exception
      //   6	27	2	localException2	Exception
      //   41	178	2	localObject	Object
      //   50	19	3	str	String
      // Exception table:
      //   from	to	target	type
      //   42	51	3	java/lang/Exception
      //   42	51	6	java/lang/Exception
      //   51	56	6	java/lang/Exception
      //   56	62	6	java/lang/Exception
      //   62	67	6	java/lang/Exception
      //   67	219	6	java/lang/Exception
    }
  }
}
