package o;

public final class EJ
{
  private static char[] ˊ = { 55, 105, 104, 109, 97, 94, 109, 116, 114, 143, 277, 273, 276, 272, 257, 258, 281, 286, 136, 275, 284, 282, 273, 278, 279, 279, 264, 260, 44, 112, 132, 131, 136, 124, 121, 136, 143, 141, 103, 101, 138, 139, 117, 119, 134, 135, 142, 137, 131, 129, 118, 118, 134, 124, 30, 91, 111, 88, 87, 102, 106, 103, 107, 114, 72, 38, 30, 86, 106, 106, 91, 87, 100, 102, 111, 109, 100, 66, 38, 20 };
  private static int ˋ;
  private static int ॱ = 0;
  private final EE deviceInfo;
  private final String publicKey;
  private final String pushToken;
  
  static
  {
    ˋ = 1;
  }
  
  /* Error */
  public EJ(String arg1, String arg2, EE arg3)
  {
    // Byte code:
    //   0: goto +6 -> 6
    //   3: astore_1
    //   4: aload_1
    //   5: athrow
    //   6: iconst_4
    //   7: newarray int
    //   9: dup
    //   10: iconst_0
    //   11: iconst_0
    //   12: iastore
    //   13: dup
    //   14: iconst_1
    //   15: bipush 9
    //   17: iastore
    //   18: dup
    //   19: iconst_2
    //   20: iconst_0
    //   21: iastore
    //   22: dup
    //   23: iconst_3
    //   24: iconst_0
    //   25: iastore
    //   26: bipush 9
    //   28: newarray byte
    //   30: dup
    //   31: iconst_0
    //   32: ldc 86
    //   34: bastore
    //   35: dup
    //   36: iconst_1
    //   37: ldc 87
    //   39: bastore
    //   40: dup
    //   41: iconst_2
    //   42: ldc 86
    //   44: bastore
    //   45: dup
    //   46: iconst_3
    //   47: ldc 86
    //   49: bastore
    //   50: dup
    //   51: iconst_4
    //   52: ldc 87
    //   54: bastore
    //   55: dup
    //   56: iconst_5
    //   57: ldc 86
    //   59: bastore
    //   60: dup
    //   61: bipush 6
    //   63: ldc 87
    //   65: bastore
    //   66: dup
    //   67: bipush 7
    //   69: ldc 86
    //   71: bastore
    //   72: dup
    //   73: bipush 8
    //   75: ldc 87
    //   77: bastore
    //   78: iconst_1
    //   79: invokestatic 90	o/EJ:ˋ	([I[BZ)Ljava/lang/String;
    //   82: astore 4
    //   84: aload 4
    //   86: invokevirtual 96	java/lang/String:intern	()Ljava/lang/String;
    //   89: astore 4
    //   91: aload_1
    //   92: aload 4
    //   94: invokestatic 102	o/vq:ˎ	(Ljava/lang/Object;Ljava/lang/String;)V
    //   97: aload_2
    //   98: iconst_4
    //   99: newarray int
    //   101: dup
    //   102: iconst_0
    //   103: bipush 9
    //   105: iastore
    //   106: dup
    //   107: iconst_1
    //   108: bipush 9
    //   110: iastore
    //   111: dup
    //   112: iconst_2
    //   113: sipush 170
    //   116: iastore
    //   117: dup
    //   118: iconst_3
    //   119: bipush 8
    //   121: iastore
    //   122: bipush 9
    //   124: newarray byte
    //   126: dup
    //   127: iconst_0
    //   128: ldc 87
    //   130: bastore
    //   131: dup
    //   132: iconst_1
    //   133: ldc 87
    //   135: bastore
    //   136: dup
    //   137: iconst_2
    //   138: ldc 86
    //   140: bastore
    //   141: dup
    //   142: iconst_3
    //   143: ldc 87
    //   145: bastore
    //   146: dup
    //   147: iconst_4
    //   148: ldc 86
    //   150: bastore
    //   151: dup
    //   152: iconst_5
    //   153: ldc 86
    //   155: bastore
    //   156: dup
    //   157: bipush 6
    //   159: ldc 86
    //   161: bastore
    //   162: dup
    //   163: bipush 7
    //   165: ldc 86
    //   167: bastore
    //   168: dup
    //   169: bipush 8
    //   171: ldc 87
    //   173: bastore
    //   174: iconst_0
    //   175: invokestatic 90	o/EJ:ˋ	([I[BZ)Ljava/lang/String;
    //   178: invokevirtual 96	java/lang/String:intern	()Ljava/lang/String;
    //   181: invokestatic 102	o/vq:ˎ	(Ljava/lang/Object;Ljava/lang/String;)V
    //   184: aload_3
    //   185: iconst_4
    //   186: newarray int
    //   188: dup
    //   189: iconst_0
    //   190: bipush 18
    //   192: iastore
    //   193: dup
    //   194: iconst_1
    //   195: bipush 10
    //   197: iastore
    //   198: dup
    //   199: iconst_2
    //   200: sipush 173
    //   203: iastore
    //   204: dup
    //   205: iconst_3
    //   206: iconst_5
    //   207: iastore
    //   208: bipush 10
    //   210: newarray byte
    //   212: dup
    //   213: iconst_0
    //   214: ldc 86
    //   216: bastore
    //   217: dup
    //   218: iconst_1
    //   219: ldc 86
    //   221: bastore
    //   222: dup
    //   223: iconst_2
    //   224: ldc 87
    //   226: bastore
    //   227: dup
    //   228: iconst_3
    //   229: ldc 87
    //   231: bastore
    //   232: dup
    //   233: iconst_4
    //   234: ldc 87
    //   236: bastore
    //   237: dup
    //   238: iconst_5
    //   239: ldc 87
    //   241: bastore
    //   242: dup
    //   243: bipush 6
    //   245: ldc 87
    //   247: bastore
    //   248: dup
    //   249: bipush 7
    //   251: ldc 86
    //   253: bastore
    //   254: dup
    //   255: bipush 8
    //   257: ldc 87
    //   259: bastore
    //   260: dup
    //   261: bipush 9
    //   263: ldc 86
    //   265: bastore
    //   266: iconst_1
    //   267: invokestatic 90	o/EJ:ˋ	([I[BZ)Ljava/lang/String;
    //   270: invokevirtual 96	java/lang/String:intern	()Ljava/lang/String;
    //   273: invokestatic 102	o/vq:ˎ	(Ljava/lang/Object;Ljava/lang/String;)V
    //   276: aload_0
    //   277: invokespecial 104	java/lang/Object:<init>	()V
    //   280: aload_0
    //   281: aload_1
    //   282: putfield 106	o/EJ:pushToken	Ljava/lang/String;
    //   285: aload_0
    //   286: aload_2
    //   287: putfield 108	o/EJ:publicKey	Ljava/lang/String;
    //   290: aload_0
    //   291: aload_3
    //   292: putfield 110	o/EJ:deviceInfo	Lo/EE;
    //   295: return
    //   296: astore_1
    //   297: aload_1
    //   298: athrow
    // Exception table:
    //   from	to	target	type
    //   6	84	3	java/lang/Exception
    //   84	91	3	java/lang/Exception
    //   91	97	3	java/lang/Exception
    //   97	295	3	java/lang/Exception
  }
  
  private static String ˋ(int[] paramArrayOfInt, byte[] paramArrayOfByte, boolean paramBoolean)
  {
    break label349;
    label3:
    int i = paramArrayOfInt[0];
    int m = paramArrayOfInt[1];
    int n = paramArrayOfInt[2];
    int i1 = paramArrayOfInt[3];
    Object localObject = ˊ;
    char[] arrayOfChar = new char[m];
    System.arraycopy(localObject, i, arrayOfChar, 0, m);
    if (paramArrayOfByte == null) {
      break label119;
    }
    for (;;)
    {
      label119:
      int k;
      try
      {
        i = ˋ + 123;
        try
        {
          ॱ = i % 128;
          if (i % 2 != 0) {
            continue;
          }
          continue;
          localObject[j] = ((char)((arrayOfChar[j] << '\001') - i));
          break label699;
          localObject[j] = ((char)((arrayOfChar[j] << '\001') + 1 - i));
          continue;
          i = 59;
          continue;
          if (i < m) {
            continue;
          }
          continue;
          break label699;
          paramArrayOfByte = new char[m];
          System.arraycopy(localObject, 0, paramArrayOfByte, 0, m);
          System.arraycopy(paramArrayOfByte, 0, localObject, m - i1, i1);
          System.arraycopy(paramArrayOfByte, i1, localObject, 0, m - i1);
          continue;
          if (i >= m)
          {
            continue;
            localObject[j] = ((char)((arrayOfChar[j] << '\001') + 0 + i));
            continue;
            i = 93;
            continue;
            k = ॱ + 79;
            ˋ = k % 128;
            if (k % 2 == 0) {
              break label689;
            }
          }
          switch (i)
          {
          default: 
            continue;
            localObject = arrayOfChar;
            switch (i)
            {
            case 33: 
            default: 
              continue;
              if (paramArrayOfByte[j] == 1) {
                continue;
              }
              continue;
              continue;
              if (paramBoolean) {
                continue;
              }
              continue;
              continue;
              break label3;
              k = 78;
              continue;
              if (n <= 0) {
                continue;
              }
              i = 0;
            }
            break;
          case 10: 
            label349:
            localObject = new char[m];
            i = 0;
            j = 0;
            continue;
            i = 10;
            continue;
            continue;
            if (i1 > 0) {
              continue;
            }
            continue;
            paramArrayOfByte[i] = localObject[(m - i - 1)];
            i += 1;
            continue;
            paramArrayOfByte = new char[m];
            i = 0;
            continue;
            switch (i)
            {
            }
            continue;
            paramArrayOfByte = (byte[])localObject;
            switch (i)
            {
            case 11: 
            default: 
              paramArrayOfByte = (byte[])localObject;
              continue;
              switch (k)
              {
              }
              continue;
              continue;
              i = 11;
              continue;
              i = 4;
              continue;
              i = 33;
              continue;
              return new String(paramArrayOfByte);
            }
            break;
          }
        }
        catch (Exception paramArrayOfInt)
        {
          throw paramArrayOfInt;
        }
        continue;
        if (j < m) {
          continue;
        }
      }
      catch (Exception paramArrayOfInt)
      {
        throw paramArrayOfInt;
      }
      i = 58;
      continue;
      paramArrayOfByte[i] = ((char)(paramArrayOfByte[i] - paramArrayOfInt[2]));
      i += 1;
      continue;
      i = 27;
      continue;
      localObject = new char[m];
      i = 0;
      int j = 0;
      continue;
      i = ˋ;
      i += 53;
      ॱ = i % 128;
      if (i % 2 == 0)
      {
        continue;
        j = ˋ + 73;
        ॱ = j % 128;
        if (j % 2 == 0)
        {
          continue;
          label689:
          k = 79;
          continue;
          continue;
          label699:
          i = localObject[j];
          j += 1;
        }
      }
    }
  }
  
  /* Error */
  public boolean equals(Object paramObject)
  {
    // Byte code:
    //   0: goto +325 -> 325
    //   3: goto +302 -> 305
    //   6: astore_1
    //   7: aload_1
    //   8: athrow
    //   9: iload_2
    //   10: tableswitch	default:+22->32, 0:+115->125, 1:+80->90
    //   32: goto +93 -> 125
    //   35: getstatic 20	o/EJ:ˋ	I
    //   38: bipush 63
    //   40: iadd
    //   41: istore_2
    //   42: iload_2
    //   43: sipush 128
    //   46: irem
    //   47: putstatic 18	o/EJ:ॱ	I
    //   50: iload_2
    //   51: iconst_2
    //   52: irem
    //   53: ifeq +6 -> 59
    //   56: goto +272 -> 328
    //   59: goto +58 -> 117
    //   62: aload_1
    //   63: instanceof 2
    //   66: ifeq +6 -> 72
    //   69: goto +58 -> 127
    //   72: goto +53 -> 125
    //   75: bipush 46
    //   77: istore_2
    //   78: goto +186 -> 264
    //   81: goto +161 -> 242
    //   84: bipush 88
    //   86: istore_2
    //   87: goto +177 -> 264
    //   90: getstatic 20	o/EJ:ˋ	I
    //   93: bipush 31
    //   95: iadd
    //   96: istore_2
    //   97: iload_2
    //   98: sipush 128
    //   101: irem
    //   102: putstatic 18	o/EJ:ॱ	I
    //   105: iload_2
    //   106: iconst_2
    //   107: irem
    //   108: ifeq +6 -> 114
    //   111: goto -108 -> 3
    //   114: goto +191 -> 305
    //   117: iconst_0
    //   118: istore_2
    //   119: goto +35 -> 154
    //   122: goto +60 -> 182
    //   125: iconst_0
    //   126: ireturn
    //   127: getstatic 20	o/EJ:ˋ	I
    //   130: bipush 7
    //   132: iadd
    //   133: istore_2
    //   134: iload_2
    //   135: sipush 128
    //   138: irem
    //   139: putstatic 18	o/EJ:ॱ	I
    //   142: iload_2
    //   143: iconst_2
    //   144: irem
    //   145: ifeq +6 -> 151
    //   148: goto -26 -> 122
    //   151: goto +31 -> 182
    //   154: iload_2
    //   155: tableswitch	default:+21->176, 0:+89->244, 1:+63->218
    //   176: goto +68 -> 244
    //   179: astore_1
    //   180: aload_1
    //   181: athrow
    //   182: aload_1
    //   183: checkcast 2	o/EJ
    //   186: astore_3
    //   187: aload_0
    //   188: getfield 106	o/EJ:pushToken	Ljava/lang/String;
    //   191: aload_3
    //   192: getfield 106	o/EJ:pushToken	Ljava/lang/String;
    //   195: invokestatic 124	o/vq:ˊ	(Ljava/lang/Object;Ljava/lang/Object;)Z
    //   198: ifeq +6 -> 204
    //   201: goto +99 -> 300
    //   204: goto +91 -> 295
    //   207: aload_0
    //   208: aload_1
    //   209: if_acmpeq +6 -> 215
    //   212: goto -128 -> 84
    //   215: goto -140 -> 75
    //   218: aload_0
    //   219: getfield 110	o/EJ:deviceInfo	Lo/EE;
    //   222: astore_1
    //   223: aload_3
    //   224: getfield 110	o/EJ:deviceInfo	Lo/EE;
    //   227: astore_3
    //   228: aload_1
    //   229: aload_3
    //   230: invokestatic 124	o/vq:ˊ	(Ljava/lang/Object;Ljava/lang/Object;)Z
    //   233: pop
    //   234: new 126	java/lang/NullPointerException
    //   237: dup
    //   238: invokespecial 127	java/lang/NullPointerException:<init>	()V
    //   241: athrow
    //   242: iconst_1
    //   243: ireturn
    //   244: aload_0
    //   245: getfield 110	o/EJ:deviceInfo	Lo/EE;
    //   248: aload_3
    //   249: getfield 110	o/EJ:deviceInfo	Lo/EE;
    //   252: invokestatic 124	o/vq:ˊ	(Ljava/lang/Object;Ljava/lang/Object;)Z
    //   255: ifeq +6 -> 261
    //   258: goto -177 -> 81
    //   261: goto -136 -> 125
    //   264: iload_2
    //   265: lookupswitch	default:+27->292, 46:+-184->81, 88:+-203->62
    //   292: goto -230 -> 62
    //   295: iconst_0
    //   296: istore_2
    //   297: goto -288 -> 9
    //   300: iconst_1
    //   301: istore_2
    //   302: goto -293 -> 9
    //   305: aload_0
    //   306: getfield 108	o/EJ:publicKey	Ljava/lang/String;
    //   309: aload_3
    //   310: getfield 108	o/EJ:publicKey	Ljava/lang/String;
    //   313: invokestatic 124	o/vq:ˊ	(Ljava/lang/Object;Ljava/lang/Object;)Z
    //   316: ifeq +6 -> 322
    //   319: goto -284 -> 35
    //   322: goto -197 -> 125
    //   325: goto -118 -> 207
    //   328: iconst_1
    //   329: istore_2
    //   330: goto -176 -> 154
    // Local variable table:
    //   start	length	slot	name	signature
    //   0	333	0	this	EJ
    //   0	333	1	paramObject	Object
    //   9	321	2	i	int
    //   186	124	3	localObject	Object
    // Exception table:
    //   from	to	target	type
    //   223	228	6	java/lang/Exception
    //   218	223	179	java/lang/Exception
    //   223	228	179	java/lang/Exception
    //   228	242	179	java/lang/Exception
  }
  
  /* Error */
  public int hashCode()
  {
    // Byte code:
    //   0: goto +49 -> 49
    //   3: aload_0
    //   4: getfield 108	o/EJ:publicKey	Ljava/lang/String;
    //   7: astore 5
    //   9: aload 5
    //   11: ifnull +6 -> 17
    //   14: goto +102 -> 116
    //   17: goto +194 -> 211
    //   20: aload_0
    //   21: getfield 106	o/EJ:pushToken	Ljava/lang/String;
    //   24: astore 5
    //   26: aload 5
    //   28: ifnull +6 -> 34
    //   31: goto +6 -> 37
    //   34: goto +9 -> 43
    //   37: bipush 37
    //   39: istore_1
    //   40: goto +131 -> 171
    //   43: bipush 50
    //   45: istore_1
    //   46: goto +125 -> 171
    //   49: goto +199 -> 248
    //   52: aload 5
    //   54: invokevirtual 131	java/lang/Object:hashCode	()I
    //   57: istore_3
    //   58: goto +16 -> 74
    //   61: iconst_0
    //   62: istore_1
    //   63: goto -60 -> 3
    //   66: astore 5
    //   68: aload 5
    //   70: athrow
    //   71: goto +33 -> 104
    //   74: getstatic 18	o/EJ:ॱ	I
    //   77: bipush 105
    //   79: iadd
    //   80: istore 4
    //   82: iload 4
    //   84: sipush 128
    //   87: irem
    //   88: putstatic 20	o/EJ:ˋ	I
    //   91: iload 4
    //   93: iconst_2
    //   94: irem
    //   95: ifne +6 -> 101
    //   98: goto +119 -> 217
    //   101: goto +50 -> 151
    //   104: iload_1
    //   105: bipush 31
    //   107: imul
    //   108: iload_2
    //   109: iadd
    //   110: bipush 31
    //   112: imul
    //   113: iload_3
    //   114: iadd
    //   115: ireturn
    //   116: bipush 99
    //   118: istore_2
    //   119: iload_2
    //   120: lookupswitch	default:+28->148, 7:+118->238, 99:+100->220
    //   148: goto +72 -> 220
    //   151: goto -47 -> 104
    //   154: aload_0
    //   155: getfield 110	o/EJ:deviceInfo	Lo/EE;
    //   158: astore 5
    //   160: aload 5
    //   162: ifnull +6 -> 168
    //   165: goto -113 -> 52
    //   168: goto +75 -> 243
    //   171: iload_1
    //   172: lookupswitch	default:+28->200, 37:+57->229, 50:+-111->61
    //   200: goto -139 -> 61
    //   203: astore 5
    //   205: aload 5
    //   207: athrow
    //   208: goto -188 -> 20
    //   211: bipush 7
    //   213: istore_2
    //   214: goto -95 -> 119
    //   217: goto -66 -> 151
    //   220: aload 5
    //   222: invokevirtual 131	java/lang/Object:hashCode	()I
    //   225: istore_2
    //   226: goto -72 -> 154
    //   229: aload 5
    //   231: invokevirtual 131	java/lang/Object:hashCode	()I
    //   234: istore_1
    //   235: goto -232 -> 3
    //   238: iconst_0
    //   239: istore_2
    //   240: goto -86 -> 154
    //   243: iconst_0
    //   244: istore_3
    //   245: goto -174 -> 71
    //   248: getstatic 20	o/EJ:ˋ	I
    //   251: bipush 117
    //   253: iadd
    //   254: istore_1
    //   255: iload_1
    //   256: sipush 128
    //   259: irem
    //   260: putstatic 18	o/EJ:ॱ	I
    //   263: iload_1
    //   264: iconst_2
    //   265: irem
    //   266: ifeq +6 -> 272
    //   269: goto -61 -> 208
    //   272: goto -252 -> 20
    // Local variable table:
    //   start	length	slot	name	signature
    //   0	275	0	this	EJ
    //   39	227	1	i	int
    //   108	132	2	j	int
    //   57	188	3	k	int
    //   80	15	4	m	int
    //   7	46	5	str	String
    //   66	3	5	localException1	Exception
    //   158	3	5	localEE	EE
    //   203	27	5	localException2	Exception
    // Exception table:
    //   from	to	target	type
    //   74	82	66	java/lang/Exception
    //   82	91	66	java/lang/Exception
    //   20	26	203	java/lang/Exception
  }
  
  /* Error */
  public String toString()
  {
    // Byte code:
    //   0: goto +546 -> 546
    //   3: new 134	java/lang/StringBuilder
    //   6: dup
    //   7: invokespecial 135	java/lang/StringBuilder:<init>	()V
    //   10: iconst_4
    //   11: newarray int
    //   13: dup
    //   14: iconst_0
    //   15: bipush 28
    //   17: iastore
    //   18: dup
    //   19: iconst_1
    //   20: bipush 26
    //   22: iastore
    //   23: dup
    //   24: iconst_2
    //   25: bipush 27
    //   27: iastore
    //   28: dup
    //   29: iconst_3
    //   30: iconst_0
    //   31: iastore
    //   32: bipush 26
    //   34: newarray byte
    //   36: dup
    //   37: iconst_0
    //   38: ldc 86
    //   40: bastore
    //   41: dup
    //   42: iconst_1
    //   43: ldc 87
    //   45: bastore
    //   46: dup
    //   47: iconst_2
    //   48: ldc 87
    //   50: bastore
    //   51: dup
    //   52: iconst_3
    //   53: ldc 86
    //   55: bastore
    //   56: dup
    //   57: iconst_4
    //   58: ldc 86
    //   60: bastore
    //   61: dup
    //   62: iconst_5
    //   63: ldc 87
    //   65: bastore
    //   66: dup
    //   67: bipush 6
    //   69: ldc 86
    //   71: bastore
    //   72: dup
    //   73: bipush 7
    //   75: ldc 87
    //   77: bastore
    //   78: dup
    //   79: bipush 8
    //   81: ldc 86
    //   83: bastore
    //   84: dup
    //   85: bipush 9
    //   87: ldc 87
    //   89: bastore
    //   90: dup
    //   91: bipush 10
    //   93: ldc 86
    //   95: bastore
    //   96: dup
    //   97: bipush 11
    //   99: ldc 87
    //   101: bastore
    //   102: dup
    //   103: bipush 12
    //   105: ldc 87
    //   107: bastore
    //   108: dup
    //   109: bipush 13
    //   111: ldc 87
    //   113: bastore
    //   114: dup
    //   115: bipush 14
    //   117: ldc 87
    //   119: bastore
    //   120: dup
    //   121: bipush 15
    //   123: ldc 86
    //   125: bastore
    //   126: dup
    //   127: bipush 16
    //   129: ldc 87
    //   131: bastore
    //   132: dup
    //   133: bipush 17
    //   135: ldc 87
    //   137: bastore
    //   138: dup
    //   139: bipush 18
    //   141: ldc 87
    //   143: bastore
    //   144: dup
    //   145: bipush 19
    //   147: ldc 86
    //   149: bastore
    //   150: dup
    //   151: bipush 20
    //   153: ldc 86
    //   155: bastore
    //   156: dup
    //   157: bipush 21
    //   159: ldc 86
    //   161: bastore
    //   162: dup
    //   163: bipush 22
    //   165: ldc 87
    //   167: bastore
    //   168: dup
    //   169: bipush 23
    //   171: ldc 87
    //   173: bastore
    //   174: dup
    //   175: bipush 24
    //   177: ldc 87
    //   179: bastore
    //   180: dup
    //   181: bipush 25
    //   183: ldc 86
    //   185: bastore
    //   186: iconst_1
    //   187: invokestatic 90	o/EJ:ˋ	([I[BZ)Ljava/lang/String;
    //   190: invokevirtual 96	java/lang/String:intern	()Ljava/lang/String;
    //   193: invokevirtual 139	java/lang/StringBuilder:append	(Ljava/lang/String;)Ljava/lang/StringBuilder;
    //   196: aload_0
    //   197: getfield 106	o/EJ:pushToken	Ljava/lang/String;
    //   200: invokevirtual 139	java/lang/StringBuilder:append	(Ljava/lang/String;)Ljava/lang/StringBuilder;
    //   203: iconst_4
    //   204: newarray int
    //   206: dup
    //   207: iconst_0
    //   208: bipush 54
    //   210: iastore
    //   211: dup
    //   212: iconst_1
    //   213: bipush 12
    //   215: iastore
    //   216: dup
    //   217: iconst_2
    //   218: iconst_0
    //   219: iastore
    //   220: dup
    //   221: iconst_3
    //   222: iconst_0
    //   223: iastore
    //   224: bipush 12
    //   226: newarray byte
    //   228: dup
    //   229: iconst_0
    //   230: ldc 87
    //   232: bastore
    //   233: dup
    //   234: iconst_1
    //   235: ldc 86
    //   237: bastore
    //   238: dup
    //   239: iconst_2
    //   240: ldc 86
    //   242: bastore
    //   243: dup
    //   244: iconst_3
    //   245: ldc 86
    //   247: bastore
    //   248: dup
    //   249: iconst_4
    //   250: ldc 86
    //   252: bastore
    //   253: dup
    //   254: iconst_5
    //   255: ldc 86
    //   257: bastore
    //   258: dup
    //   259: bipush 6
    //   261: ldc 87
    //   263: bastore
    //   264: dup
    //   265: bipush 7
    //   267: ldc 86
    //   269: bastore
    //   270: dup
    //   271: bipush 8
    //   273: ldc 87
    //   275: bastore
    //   276: dup
    //   277: bipush 9
    //   279: ldc 87
    //   281: bastore
    //   282: dup
    //   283: bipush 10
    //   285: ldc 86
    //   287: bastore
    //   288: dup
    //   289: bipush 11
    //   291: ldc 86
    //   293: bastore
    //   294: iconst_1
    //   295: invokestatic 90	o/EJ:ˋ	([I[BZ)Ljava/lang/String;
    //   298: invokevirtual 96	java/lang/String:intern	()Ljava/lang/String;
    //   301: invokevirtual 139	java/lang/StringBuilder:append	(Ljava/lang/String;)Ljava/lang/StringBuilder;
    //   304: aload_0
    //   305: getfield 108	o/EJ:publicKey	Ljava/lang/String;
    //   308: invokevirtual 139	java/lang/StringBuilder:append	(Ljava/lang/String;)Ljava/lang/StringBuilder;
    //   311: iconst_4
    //   312: newarray int
    //   314: dup
    //   315: iconst_0
    //   316: bipush 66
    //   318: iastore
    //   319: dup
    //   320: iconst_1
    //   321: bipush 13
    //   323: iastore
    //   324: dup
    //   325: iconst_2
    //   326: iconst_0
    //   327: iastore
    //   328: dup
    //   329: iconst_3
    //   330: iconst_0
    //   331: iastore
    //   332: bipush 13
    //   334: newarray byte
    //   336: dup
    //   337: iconst_0
    //   338: ldc 87
    //   340: bastore
    //   341: dup
    //   342: iconst_1
    //   343: ldc 86
    //   345: bastore
    //   346: dup
    //   347: iconst_2
    //   348: ldc 87
    //   350: bastore
    //   351: dup
    //   352: iconst_3
    //   353: ldc 86
    //   355: bastore
    //   356: dup
    //   357: iconst_4
    //   358: ldc 87
    //   360: bastore
    //   361: dup
    //   362: iconst_5
    //   363: ldc 86
    //   365: bastore
    //   366: dup
    //   367: bipush 6
    //   369: ldc 86
    //   371: bastore
    //   372: dup
    //   373: bipush 7
    //   375: ldc 86
    //   377: bastore
    //   378: dup
    //   379: bipush 8
    //   381: ldc 87
    //   383: bastore
    //   384: dup
    //   385: bipush 9
    //   387: ldc 87
    //   389: bastore
    //   390: dup
    //   391: bipush 10
    //   393: ldc 87
    //   395: bastore
    //   396: dup
    //   397: bipush 11
    //   399: ldc 86
    //   401: bastore
    //   402: dup
    //   403: bipush 12
    //   405: ldc 86
    //   407: bastore
    //   408: iconst_1
    //   409: invokestatic 90	o/EJ:ˋ	([I[BZ)Ljava/lang/String;
    //   412: invokevirtual 96	java/lang/String:intern	()Ljava/lang/String;
    //   415: invokevirtual 139	java/lang/StringBuilder:append	(Ljava/lang/String;)Ljava/lang/StringBuilder;
    //   418: aload_0
    //   419: getfield 110	o/EJ:deviceInfo	Lo/EE;
    //   422: invokevirtual 142	java/lang/StringBuilder:append	(Ljava/lang/Object;)Ljava/lang/StringBuilder;
    //   425: iconst_4
    //   426: newarray int
    //   428: dup
    //   429: iconst_0
    //   430: bipush 79
    //   432: iastore
    //   433: dup
    //   434: iconst_1
    //   435: iconst_1
    //   436: iastore
    //   437: dup
    //   438: iconst_2
    //   439: iconst_0
    //   440: iastore
    //   441: dup
    //   442: iconst_3
    //   443: iconst_1
    //   444: iastore
    //   445: iconst_1
    //   446: newarray byte
    //   448: dup
    //   449: iconst_0
    //   450: ldc 87
    //   452: bastore
    //   453: iconst_0
    //   454: invokestatic 90	o/EJ:ˋ	([I[BZ)Ljava/lang/String;
    //   457: invokevirtual 96	java/lang/String:intern	()Ljava/lang/String;
    //   460: invokevirtual 139	java/lang/StringBuilder:append	(Ljava/lang/String;)Ljava/lang/StringBuilder;
    //   463: invokevirtual 144	java/lang/StringBuilder:toString	()Ljava/lang/String;
    //   466: astore_2
    //   467: goto +50 -> 517
    //   470: iload_1
    //   471: lookupswitch	default:+25->496, 17:+32->503, 23:+27->498
    //   496: aload_2
    //   497: areturn
    //   498: aconst_null
    //   499: arraylength
    //   500: istore_1
    //   501: aload_2
    //   502: areturn
    //   503: aload_2
    //   504: areturn
    //   505: bipush 17
    //   507: istore_1
    //   508: goto -38 -> 470
    //   511: astore_2
    //   512: aload_2
    //   513: athrow
    //   514: astore_2
    //   515: aload_2
    //   516: athrow
    //   517: getstatic 18	o/EJ:ॱ	I
    //   520: istore_1
    //   521: iload_1
    //   522: bipush 113
    //   524: iadd
    //   525: istore_1
    //   526: iload_1
    //   527: sipush 128
    //   530: irem
    //   531: putstatic 20	o/EJ:ˋ	I
    //   534: iload_1
    //   535: iconst_2
    //   536: irem
    //   537: ifne +6 -> 543
    //   540: goto +9 -> 549
    //   543: goto -38 -> 505
    //   546: goto -543 -> 3
    //   549: bipush 23
    //   551: istore_1
    //   552: goto -82 -> 470
    // Local variable table:
    //   start	length	slot	name	signature
    //   0	555	0	this	EJ
    //   470	82	1	i	int
    //   466	38	2	str	String
    //   511	2	2	localException1	Exception
    //   514	2	2	localException2	Exception
    // Exception table:
    //   from	to	target	type
    //   517	521	511	java/lang/Exception
    //   526	534	514	java/lang/Exception
  }
}
