package o;

public final class EM
{
  private static char[] ˊ = { 67, 97, 114, 100, 77, 101, 116, 82, 115, 112, 111, 110, 40, 121, 109, 73, 117, 61, 41, 68, 69, 70, 71, 72, 74 };
  private static int ˋ = 0;
  private static char ˎ = '\005';
  private static int ˏ = 1;
  private final ˊ paymentInstrument;
  
  private static String ˎ(char[] paramArrayOfChar, int paramInt, byte paramByte)
  {
    break label392;
    int i = 1;
    break label651;
    label65:
    int j;
    label82:
    label90:
    byte b2;
    int k;
    byte b1;
    int m;
    char[] arrayOfChar2;
    char[] arrayOfChar1;
    for (;;)
    {
      try
      {
        paramInt = ˋ + 29;
        ˏ = paramInt % 128;
        if (paramInt % 2 == 0) {
          break label604;
        }
      }
      catch (Exception paramArrayOfChar)
      {
        int n;
        label249:
        label278:
        label285:
        label344:
        label351:
        label354:
        label384:
        label392:
        label444:
        throw paramArrayOfChar;
      }
      n = ˏ + 71;
      ˋ = n % 128;
      if (n % 2 == 0)
      {
        continue;
        j = 55;
        continue;
        break label516;
        j = 25;
        break label773;
        continue;
        paramInt = null.length;
        return paramArrayOfChar;
      }
      switch (j)
      {
      default: 
        break label581;
        b2 = oO.ˊ(b2, k);
        b1 = oO.ˊ(b1, k);
        b2 = oO.ˏ(m, b2, k);
        j = oO.ˏ(j, b1, k);
        arrayOfChar2[i] = arrayOfChar1[b2];
        arrayOfChar2[(i + 1)] = arrayOfChar1[j];
        continue;
        m = oO.ˊ(m, k);
        j = oO.ˊ(j, k);
        b2 = oO.ˏ(m, b2, k);
        j = oO.ˏ(j, b1, k);
        arrayOfChar2[i] = arrayOfChar1[b2];
        arrayOfChar2[(i + 1)] = arrayOfChar1[j];
        break label714;
        paramArrayOfChar = new String(arrayOfChar2);
        if (m != j)
        {
          break label533;
          j = 64;
          continue;
          i = 0;
          break label516;
          b2 = paramArrayOfChar[i];
          b1 = paramArrayOfChar[(i + 1)];
          if (b2 == b1) {
            break label527;
          }
          continue;
          paramInt = ˋ + 107;
          ˏ = paramInt % 128;
          if (paramInt % 2 != 0)
          {
            return paramArrayOfChar;
            continue;
            j = 76;
          }
        }
        break;
      case 57: 
        try
        {
          j = ˋ + 65;
          ˏ = j % 128;
          if (j % 2 == 0) {
            continue;
          }
        }
        catch (Exception paramArrayOfChar)
        {
          throw paramArrayOfChar;
        }
        i = 0;
        break label651;
        continue;
        break label744;
        m = oO.ॱ(b2, k);
        b2 = oO.ˋ(b2, k);
        j = oO.ॱ(b1, k);
        b1 = oO.ˋ(b1, k);
        if (b2 != b1)
        {
          continue;
          j = 57;
          continue;
          paramInt = i;
          switch (j)
          {
          }
        }
        break;
      }
    }
    for (;;)
    {
      i += 2;
      break;
      arrayOfChar2[i] = ((char)(b2 - paramByte));
      arrayOfChar2[(i + 1)] = ((char)(b1 - paramByte));
      continue;
      label516:
      if (i < paramInt) {
        break label354;
      }
      break label249;
      label527:
      j = 0;
      break label773;
      label533:
      b1 = oO.ˏ(m, b1, k);
      j = oO.ˏ(j, b2, k);
      arrayOfChar2[i] = arrayOfChar1[b1];
      arrayOfChar2[(i + 1)] = arrayOfChar1[j];
      continue;
      label581:
      arrayOfChar2[i] = ((char)(b2 << paramByte));
      arrayOfChar2[(i >>> 1)] = ((char)(b1 % paramByte));
    }
    label604:
    paramInt = i - 1;
    arrayOfChar2[paramInt] = ((char)(paramArrayOfChar[paramInt] - paramByte));
    for (;;)
    {
      j = ˋ + 103;
      ˏ = j % 128;
      if (j % 2 == 0) {
        break label344;
      }
      break label444;
      label651:
      switch (i)
      {
      }
      i = ˋ + 85;
      ˏ = i % 128;
      if (i % 2 == 0) {
        break label90;
      }
      break label285;
      if (paramInt > 1) {
        break;
      }
      break label384;
      label714:
      j = ˏ + 15;
      ˋ = j % 128;
      if (j % 2 != 0) {
        break label82;
      }
      break label351;
      label744:
      arrayOfChar1 = ˊ;
      i = paramInt;
      k = ˎ;
      arrayOfChar2 = new char[i];
      if (i % 2 != 0) {
        break label278;
      }
      break label65;
      label773:
      switch (j)
      {
      }
    }
  }
  
  /* Error */
  public boolean equals(Object paramObject)
  {
    // Byte code:
    //   0: goto +45 -> 45
    //   3: iconst_1
    //   4: ireturn
    //   5: getstatic 24	o/EM:ˏ	I
    //   8: bipush 119
    //   10: iadd
    //   11: istore_2
    //   12: iload_2
    //   13: sipush 128
    //   16: irem
    //   17: putstatic 22	o/EM:ˋ	I
    //   20: iload_2
    //   21: iconst_2
    //   22: irem
    //   23: ifeq +6 -> 29
    //   26: goto +181 -> 207
    //   29: goto +19 -> 48
    //   32: iconst_0
    //   33: ireturn
    //   34: iconst_0
    //   35: istore_2
    //   36: goto +85 -> 121
    //   39: bipush 94
    //   41: istore_2
    //   42: goto +134 -> 176
    //   45: goto +38 -> 83
    //   48: aload_1
    //   49: checkcast 2	o/EM
    //   52: astore 4
    //   54: aload_0
    //   55: getfield 80	o/EM:paymentInstrument	Lo/EM$ˊ;
    //   58: astore_1
    //   59: aload 4
    //   61: getfield 80	o/EM:paymentInstrument	Lo/EM$ˊ;
    //   64: astore 4
    //   66: aload_1
    //   67: aload 4
    //   69: invokestatic 85	o/vq:ˊ	(Ljava/lang/Object;Ljava/lang/Object;)Z
    //   72: istore_3
    //   73: iload_3
    //   74: ifeq +6 -> 80
    //   77: goto -38 -> 39
    //   80: goto +35 -> 115
    //   83: getstatic 22	o/EM:ˋ	I
    //   86: bipush 79
    //   88: iadd
    //   89: istore_2
    //   90: iload_2
    //   91: sipush 128
    //   94: irem
    //   95: putstatic 24	o/EM:ˏ	I
    //   98: iload_2
    //   99: iconst_2
    //   100: irem
    //   101: ifne +6 -> 107
    //   104: goto +53 -> 157
    //   107: goto +103 -> 210
    //   110: iconst_1
    //   111: istore_2
    //   112: goto +9 -> 121
    //   115: bipush 89
    //   117: istore_2
    //   118: goto +58 -> 176
    //   121: iload_2
    //   122: tableswitch	default:+22->144, 0:+-119->3, 1:+22->144
    //   144: aload_1
    //   145: instanceof 2
    //   148: ifeq +6 -> 154
    //   151: goto -146 -> 5
    //   154: goto -122 -> 32
    //   157: bipush 28
    //   159: iconst_0
    //   160: idiv
    //   161: istore_2
    //   162: aload_0
    //   163: aload_1
    //   164: if_acmpeq +6 -> 170
    //   167: goto -57 -> 110
    //   170: goto -136 -> 34
    //   173: astore_1
    //   174: aload_1
    //   175: athrow
    //   176: iload_2
    //   177: lookupswitch	default:+27->204, 89:+-145->32, 94:+-174->3
    //   204: goto -201 -> 3
    //   207: goto -159 -> 48
    //   210: aload_0
    //   211: aload_1
    //   212: if_acmpeq +6 -> 218
    //   215: goto -71 -> 144
    //   218: goto -215 -> 3
    //   221: astore_1
    //   222: aload_1
    //   223: athrow
    // Local variable table:
    //   start	length	slot	name	signature
    //   0	224	0	this	EM
    //   0	224	1	paramObject	Object
    //   11	166	2	i	int
    //   72	2	3	bool	boolean
    //   52	16	4	localObject	Object
    // Exception table:
    //   from	to	target	type
    //   48	54	173	java/lang/Exception
    //   54	59	173	java/lang/Exception
    //   59	66	173	java/lang/Exception
    //   66	73	173	java/lang/Exception
    //   54	59	221	java/lang/Exception
  }
  
  public int hashCode()
  {
    break label105;
    int j = 95;
    break label47;
    break label137;
    label12:
    ˊ localˊ;
    int i = localˊ.hashCode();
    for (;;)
    {
      switch (i)
      {
      case 0: 
      default: 
        break label12;
        switch (j)
        {
        default: 
          break label143;
          for (;;)
          {
            localˊ = this.paymentInstrument;
            if (localˊ == null) {
              break label149;
            }
            i = 0;
            break;
            j = 56;
            break label47;
          }
          j = ˋ + 101;
          ˏ = j % 128;
          if (j % 2 == 0) {
            break;
          }
          break;
        case 95: 
          return i;
          break;
          break;
        case 56: 
          label47:
          label99:
          label105:
          label137:
          label140:
          label143:
          j = 5 / 0;
          return i;
          label149:
          i = 1;
        }
        break;
      }
    }
    for (;;)
    {
      j = ˋ + 91;
      ˏ = j % 128;
      if (j % 2 == 0) {
        break label99;
      }
      break;
      i = 0;
      break label140;
    }
  }
  
  public String toString()
  {
    Object localObject1 = new StringBuilder();
    try
    {
      Object localObject2 = ˎ(new char[] { 1, 2, 3, 4, 0, 9, 11, 6, 4, 2, 11, 6, 8, 6, 9, 5, 11, 12, 9, 6, 14, 7, 3, 11, 10, 9, 16, 11, 16, 10, 9, 7, 1, 17, 10, 9, 16, 11, 87 }, 39, (byte)26);
      localObject2 = ((String)localObject2).intern();
      try
      {
        localObject1 = ((StringBuilder)localObject1).append((String)localObject2);
        localObject2 = this.paymentInstrument;
        localObject1 = localObject2 + ˎ(new char[] { 105 }, 1, (byte)64).intern();
      }
      catch (Exception localException1)
      {
        throw localException1;
      }
      i = ˋ + 15;
    }
    catch (Exception localException2)
    {
      throw localException2;
    }
    int i;
    ˏ = i % 128;
    if (i % 2 == 0) {
      return localException2;
    }
    return localException2;
  }
  
  public final ˊ ˎ()
  {
    break label41;
    int i;
    switch (i)
    {
    default: 
      break;
    }
    for (;;)
    {
      i = 0;
      break;
      i = 1;
      break;
      label41:
      break label56;
      ˊ localˊ = this.paymentInstrument;
      i = 30 / 0;
      return localˊ;
      try
      {
        label56:
        i = ˏ + 91;
        try
        {
          ˋ = i % 128;
          if (i % 2 != 0) {
            continue;
          }
        }
        catch (Exception localException1)
        {
          throw localException1;
        }
        return this.paymentInstrument;
      }
      catch (Exception localException2)
      {
        throw localException2;
      }
    }
  }
  
  public static final class If
  {
    private static int ʼ;
    private static char ˊ = '៛';
    private static char ˋ;
    private static char ˎ = 37919;
    private static char ˏ;
    private static int ॱ = 0;
    private final String month;
    private final String year;
    
    static
    {
      ʼ = 1;
      ˋ = 52658;
      ˏ = 'ʴ';
    }
    
    /* Error */
    private static String ˋ(char[] paramArrayOfChar)
    {
      // Byte code:
      //   0: goto +16 -> 16
      //   3: new 40	java/lang/String
      //   6: dup
      //   7: aload_3
      //   8: iconst_1
      //   9: aload_3
      //   10: iconst_0
      //   11: caload
      //   12: invokespecial 44	java/lang/String:<init>	([CII)V
      //   15: areturn
      //   16: goto +77 -> 93
      //   19: aload 4
      //   21: iconst_0
      //   22: aload_0
      //   23: iload_1
      //   24: caload
      //   25: castore
      //   26: aload 4
      //   28: iconst_1
      //   29: aload_0
      //   30: iload_1
      //   31: iconst_1
      //   32: iadd
      //   33: caload
      //   34: castore
      //   35: aload 4
      //   37: getstatic 34	o/EM$If:ˎ	C
      //   40: getstatic 29	o/EM$If:ˏ	C
      //   43: getstatic 31	o/EM$If:ˊ	C
      //   46: getstatic 27	o/EM$If:ˋ	C
      //   49: invokestatic 49	o/oP:ˏ	([CCCCC)V
      //   52: aload_3
      //   53: iload_1
      //   54: aload 4
      //   56: iconst_0
      //   57: caload
      //   58: castore
      //   59: aload_3
      //   60: iload_1
      //   61: iconst_1
      //   62: iadd
      //   63: aload 4
      //   65: iconst_1
      //   66: caload
      //   67: castore
      //   68: iload_1
      //   69: iconst_2
      //   70: iadd
      //   71: istore_1
      //   72: goto +67 -> 139
      //   75: iload_1
      //   76: aload_0
      //   77: arraylength
      //   78: if_icmpge +6 -> 84
      //   81: goto +6 -> 87
      //   84: goto +85 -> 169
      //   87: bipush 17
      //   89: istore_2
      //   90: goto +18 -> 108
      //   93: aload_0
      //   94: arraylength
      //   95: newarray char
      //   97: astore_3
      //   98: iconst_0
      //   99: istore_1
      //   100: iconst_2
      //   101: newarray char
      //   103: astore 4
      //   105: goto -30 -> 75
      //   108: iload_2
      //   109: lookupswitch	default:+27->136, 17:+72->181, 90:+-106->3
      //   136: goto -133 -> 3
      //   139: getstatic 22	o/EM$If:ॱ	I
      //   142: bipush 49
      //   144: iadd
      //   145: istore_2
      //   146: iload_2
      //   147: sipush 128
      //   150: irem
      //   151: putstatic 24	o/EM$If:ʼ	I
      //   154: iload_2
      //   155: iconst_2
      //   156: irem
      //   157: ifne +6 -> 163
      //   160: goto +15 -> 175
      //   163: goto +48 -> 211
      //   166: goto -147 -> 19
      //   169: bipush 90
      //   171: istore_2
      //   172: goto -64 -> 108
      //   175: goto +36 -> 211
      //   178: astore_0
      //   179: aload_0
      //   180: athrow
      //   181: getstatic 24	o/EM$If:ʼ	I
      //   184: bipush 55
      //   186: iadd
      //   187: istore_2
      //   188: iload_2
      //   189: sipush 128
      //   192: irem
      //   193: putstatic 22	o/EM$If:ॱ	I
      //   196: iload_2
      //   197: iconst_2
      //   198: irem
      //   199: ifeq +6 -> 205
      //   202: goto -36 -> 166
      //   205: goto -186 -> 19
      //   208: astore_0
      //   209: aload_0
      //   210: athrow
      //   211: goto -136 -> 75
      // Local variable table:
      //   start	length	slot	name	signature
      //   0	214	0	paramArrayOfChar	char[]
      //   23	77	1	i	int
      //   89	110	2	j	int
      //   7	91	3	arrayOfChar1	char[]
      //   19	85	4	arrayOfChar2	char[]
      // Exception table:
      //   from	to	target	type
      //   181	188	178	java/lang/Exception
      //   188	196	178	java/lang/Exception
      //   188	196	208	java/lang/Exception
    }
    
    public boolean equals(Object paramObject)
    {
      break label30;
      label3:
      int i = ʼ + 17;
      ॱ = i % 128;
      if (i % 2 == 0)
      {
        break label79;
        label30:
        if (this == paramObject) {
          break label166;
        }
        switch (i)
        {
        default: 
          break;
        case 19: 
          for (;;)
          {
            label41:
            i = 19;
            break label41;
            return true;
            label79:
            return false;
            label87:
            label119:
            label122:
            do
            {
              i = 20;
              break label41;
              for (i = 68;; i = 66) {
                switch (i)
                {
                default: 
                  break;
                case 68: 
                  break label3;
                }
              }
            } while ((paramObject instanceof If));
          }
        }
      }
      for (;;)
      {
        paramObject = (If)paramObject;
        if (!vq.ˊ(this.month, paramObject.month))
        {
          break label119;
          label166:
          break;
          break label79;
        }
        if (vq.ˊ(this.year, paramObject.year)) {
          break label122;
        }
        break label87;
        do
        {
          break;
          i = ॱ + 9;
          ʼ = i % 128;
        } while (i % 2 == 0);
      }
    }
    
    /* Error */
    public int hashCode()
    {
      // Byte code:
      //   0: goto +6 -> 6
      //   3: astore_3
      //   4: aload_3
      //   5: athrow
      //   6: aload_0
      //   7: getfield 53	o/EM$If:month	Ljava/lang/String;
      //   10: astore_3
      //   11: aload_3
      //   12: ifnull +6 -> 18
      //   15: goto +113 -> 128
      //   18: goto +94 -> 112
      //   21: iconst_0
      //   22: istore_2
      //   23: goto +102 -> 125
      //   26: bipush 94
      //   28: istore_1
      //   29: goto +119 -> 148
      //   32: getstatic 24	o/EM$If:ʼ	I
      //   35: bipush 21
      //   37: iadd
      //   38: istore_2
      //   39: iload_2
      //   40: sipush 128
      //   43: irem
      //   44: putstatic 22	o/EM$If:ॱ	I
      //   47: iload_2
      //   48: iconst_2
      //   49: irem
      //   50: ifeq +6 -> 56
      //   53: goto +45 -> 98
      //   56: goto +61 -> 117
      //   59: getstatic 22	o/EM$If:ॱ	I
      //   62: bipush 53
      //   64: iadd
      //   65: istore_1
      //   66: iload_1
      //   67: sipush 128
      //   70: irem
      //   71: putstatic 24	o/EM$If:ʼ	I
      //   74: iload_1
      //   75: iconst_2
      //   76: irem
      //   77: ifne +6 -> 83
      //   80: goto +6 -> 86
      //   83: goto -57 -> 26
      //   86: iconst_3
      //   87: istore_1
      //   88: goto +60 -> 148
      //   91: iload_1
      //   92: bipush 31
      //   94: imul
      //   95: iload_2
      //   96: iadd
      //   97: ireturn
      //   98: goto +19 -> 117
      //   101: aload_3
      //   102: invokevirtual 64	java/lang/Object:hashCode	()I
      //   105: istore_1
      //   106: aconst_null
      //   107: arraylength
      //   108: istore_2
      //   109: goto +24 -> 133
      //   112: iconst_0
      //   113: istore_1
      //   114: goto +70 -> 184
      //   117: aload_3
      //   118: invokevirtual 64	java/lang/Object:hashCode	()I
      //   121: istore_2
      //   122: goto -31 -> 91
      //   125: goto -34 -> 91
      //   128: iconst_1
      //   129: istore_1
      //   130: goto +54 -> 184
      //   133: aload_0
      //   134: getfield 60	o/EM$If:year	Ljava/lang/String;
      //   137: astore_3
      //   138: aload_3
      //   139: ifnull +6 -> 145
      //   142: goto -110 -> 32
      //   145: goto -124 -> 21
      //   148: iload_1
      //   149: lookupswitch	default:+27->176, 3:+-48->101, 94:+27->176
      //   176: aload_3
      //   177: invokevirtual 64	java/lang/Object:hashCode	()I
      //   180: istore_1
      //   181: goto -48 -> 133
      //   184: iload_1
      //   185: tableswitch	default:+23->208, 0:+26->211, 1:+-126->59
      //   208: goto -149 -> 59
      //   211: iconst_0
      //   212: istore_1
      //   213: goto -80 -> 133
      // Local variable table:
      //   start	length	slot	name	signature
      //   0	216	0	this	If
      //   28	185	1	i	int
      //   22	100	2	j	int
      //   3	2	3	localException	Exception
      //   10	167	3	str	String
      // Exception table:
      //   from	to	target	type
      //   133	138	3	java/lang/Exception
    }
    
    public String toString()
    {
      for (;;)
      {
        int i = ʼ + 17;
        ॱ = i % 128;
        if (i % 2 != 0) {
          return str;
        }
        return str;
        String str = ˋ(new char[] { 27527, 4791, -23907, -27986, 3199, -11866, 26105, 15032, -32744, -18881, 19156, -12801, 26105, 15032, 16408, 16358, 31362, 534, 6365, 28513, -156, -14201 }).intern() + this.month + ˋ(new char[] { 19085, -11832, 29886, -8644, -11812, 31871, -21383, 5621 }).intern() + this.year + ˋ(new char[] { 7205, 5860 }).intern();
      }
    }
    
    /* Error */
    public final String ˎ()
    {
      // Byte code:
      //   0: goto +71 -> 71
      //   3: aload_0
      //   4: getfield 60	o/EM$If:year	Ljava/lang/String;
      //   7: astore_2
      //   8: goto +35 -> 43
      //   11: astore_2
      //   12: aload_2
      //   13: athrow
      //   14: astore_2
      //   15: aload_2
      //   16: athrow
      //   17: getstatic 22	o/EM$If:ॱ	I
      //   20: iconst_3
      //   21: iadd
      //   22: istore_1
      //   23: iload_1
      //   24: sipush 128
      //   27: irem
      //   28: putstatic 24	o/EM$If:ʼ	I
      //   31: iload_1
      //   32: iconst_2
      //   33: irem
      //   34: ifne +6 -> 40
      //   37: goto +31 -> 68
      //   40: goto -37 -> 3
      //   43: getstatic 24	o/EM$If:ʼ	I
      //   46: bipush 83
      //   48: iadd
      //   49: istore_1
      //   50: iload_1
      //   51: sipush 128
      //   54: irem
      //   55: putstatic 22	o/EM$If:ॱ	I
      //   58: iload_1
      //   59: iconst_2
      //   60: irem
      //   61: ifeq +5 -> 66
      //   64: aload_2
      //   65: areturn
      //   66: aload_2
      //   67: areturn
      //   68: goto -65 -> 3
      //   71: goto -54 -> 17
      // Local variable table:
      //   start	length	slot	name	signature
      //   0	74	0	this	If
      //   22	39	1	i	int
      //   7	1	2	str	String
      //   11	2	2	localException1	Exception
      //   14	53	2	localException2	Exception
      // Exception table:
      //   from	to	target	type
      //   17	23	11	java/lang/Exception
      //   23	31	11	java/lang/Exception
      //   23	31	14	java/lang/Exception
    }
    
    public final String ˏ()
    {
      for (;;)
      {
        int i;
        String str;
        switch (i)
        {
        default: 
          return str;
          i = 1;
          break;
        case 1: 
        case 0: 
          for (;;)
          {
            try
            {
              i = ʼ + 51;
              ॱ = i % 128;
              if (i % 2 != 0) {
                break label110;
              }
            }
            catch (Exception localException)
            {
              throw localException;
            }
            return str;
            throw new NullPointerException();
            i = ॱ + 37;
            ʼ = i % 128;
            if (i % 2 != 0) {}
            str = this.month;
          }
          label110:
          i = 0;
        }
      }
    }
  }
  
  public static final class ˊ
  {
    private static char[] ˊ = { 26204, 19868, 12695, -6734, -13907, -16937, 25054, 21970, 14826, -4858, -12014, -31451, 26933, 23900, 327, -2691, -9880, -29403, 28818, 9358, 2219, -835, -24434, -27498, 18157, 27920, 4422, -14998, -5771, -25315, 16661, 30007, 6461, -12847, -3644, -23052, 18889, 32157, 8603, -10821, -1556, 41 };
    private static int ˋ = 0;
    private static int ˎ = 1;
    private static long ˏ = -2769932785503294479L;
    private final EM.If expirationDate;
    private final String last4;
    
    private static String ˏ(int paramInt1, char paramChar, int paramInt2)
    {
      break label51;
      char[] arrayOfChar = new char[paramInt2];
      int i = 0;
      label13:
      int j;
      label51:
      label59:
      label89:
      label99:
      for (;;)
      {
        arrayOfChar[i] = ((char)(int)(ˊ[(paramInt1 + i)] ^ i * ˏ ^ paramChar));
        j = i + 1;
        break label59;
        i = j;
        break;
        break label189;
        for (;;)
        {
          i = 0;
          break;
          i = ˋ + 7;
          ˎ = i % 128;
          if (i % 2 == 0) {
            break label216;
          }
        }
        for (;;)
        {
          break;
          arrayOfChar = new char[paramInt2];
          i = 1;
        }
      }
      for (;;)
      {
        if (i < paramInt2) {
          break label183;
        }
        break;
        label113:
        i = j;
      }
      for (;;)
      {
        j = ˎ + 117;
        ˋ = j % 128;
        if (j % 2 != 0) {
          break label99;
        }
        break label13;
        j = 0;
        break label231;
        for (;;)
        {
          switch (i)
          {
          }
          break label113;
          label183:
          j = 1;
          break label231;
          label189:
          i = ˎ + 101;
          ˋ = i % 128;
          if (i % 2 != 0) {
            break label89;
          }
          break;
          label216:
          i = 1;
        }
        return new String(arrayOfChar);
        label231:
        switch (j)
        {
        }
      }
    }
    
    /* Error */
    public boolean equals(Object paramObject)
    {
      // Byte code:
      //   0: goto +263 -> 263
      //   3: aload_0
      //   4: getfield 85	o/EM$ˊ:expirationDate	Lo/EM$If;
      //   7: aload_1
      //   8: getfield 85	o/EM$ˊ:expirationDate	Lo/EM$If;
      //   11: invokestatic 90	o/vq:ˊ	(Ljava/lang/Object;Ljava/lang/Object;)Z
      //   14: ifeq +6 -> 20
      //   17: goto +225 -> 242
      //   20: goto +240 -> 260
      //   23: aload_1
      //   24: checkcast 2	o/EM$ˊ
      //   27: astore_1
      //   28: aload_0
      //   29: getfield 92	o/EM$ˊ:last4	Ljava/lang/String;
      //   32: aload_1
      //   33: getfield 92	o/EM$ˊ:last4	Ljava/lang/String;
      //   36: invokestatic 90	o/vq:ˊ	(Ljava/lang/Object;Ljava/lang/Object;)Z
      //   39: ifeq +6 -> 45
      //   42: goto +76 -> 118
      //   45: goto +84 -> 129
      //   48: new 94	java/lang/NullPointerException
      //   51: dup
      //   52: invokespecial 96	java/lang/NullPointerException:<init>	()V
      //   55: athrow
      //   56: iload_2
      //   57: lookupswitch	default:+27->84, 37:+-9->48, 57:+290->347
      //   84: goto -36 -> 48
      //   87: iload_2
      //   88: tableswitch	default:+24->112, 0:+154->242, 1:+141->229
      //   112: goto +117 -> 229
      //   115: astore_1
      //   116: aload_1
      //   117: athrow
      //   118: iconst_1
      //   119: istore_2
      //   120: goto +146 -> 266
      //   123: bipush 57
      //   125: istore_2
      //   126: goto -70 -> 56
      //   129: iconst_0
      //   130: istore_2
      //   131: goto +135 -> 266
      //   134: iload_2
      //   135: tableswitch	default:+21->156, 0:+24->159, 1:+109->244
      //   156: goto +88 -> 244
      //   159: bipush 32
      //   161: iconst_0
      //   162: idiv
      //   163: istore_2
      //   164: aload_0
      //   165: aload_1
      //   166: if_acmpeq +6 -> 172
      //   169: goto +60 -> 229
      //   172: goto +70 -> 242
      //   175: astore_1
      //   176: aload_1
      //   177: athrow
      //   178: getstatic 21	o/EM$ˊ:ˋ	I
      //   181: bipush 23
      //   183: iadd
      //   184: istore_2
      //   185: iload_2
      //   186: sipush 128
      //   189: irem
      //   190: putstatic 23	o/EM$ˊ:ˎ	I
      //   193: iload_2
      //   194: iconst_2
      //   195: irem
      //   196: ifne +6 -> 202
      //   199: goto +9 -> 208
      //   202: goto +53 -> 255
      //   205: goto -202 -> 3
      //   208: iconst_0
      //   209: istore_2
      //   210: goto -76 -> 134
      //   213: iconst_1
      //   214: istore_2
      //   215: goto -128 -> 87
      //   218: bipush 37
      //   220: istore_2
      //   221: goto -165 -> 56
      //   224: iconst_0
      //   225: istore_2
      //   226: goto -139 -> 87
      //   229: aload_1
      //   230: instanceof 2
      //   233: ifeq +6 -> 239
      //   236: goto -213 -> 23
      //   239: goto +21 -> 260
      //   242: iconst_1
      //   243: ireturn
      //   244: aload_0
      //   245: aload_1
      //   246: if_acmpeq +6 -> 252
      //   249: goto -36 -> 213
      //   252: goto -28 -> 224
      //   255: iconst_1
      //   256: istore_2
      //   257: goto -123 -> 134
      //   260: goto +31 -> 291
      //   263: goto -85 -> 178
      //   266: iload_2
      //   267: tableswitch	default:+21->288, 0:+-7->260, 1:+51->318
      //   288: goto -28 -> 260
      //   291: getstatic 23	o/EM$ˊ:ˎ	I
      //   294: bipush 57
      //   296: iadd
      //   297: istore_2
      //   298: iload_2
      //   299: sipush 128
      //   302: irem
      //   303: putstatic 21	o/EM$ˊ:ˋ	I
      //   306: iload_2
      //   307: iconst_2
      //   308: irem
      //   309: ifeq +6 -> 315
      //   312: goto -94 -> 218
      //   315: goto -192 -> 123
      //   318: getstatic 21	o/EM$ˊ:ˋ	I
      //   321: istore_2
      //   322: iload_2
      //   323: bipush 53
      //   325: iadd
      //   326: istore_2
      //   327: iload_2
      //   328: sipush 128
      //   331: irem
      //   332: putstatic 23	o/EM$ˊ:ˎ	I
      //   335: iload_2
      //   336: iconst_2
      //   337: irem
      //   338: ifne +6 -> 344
      //   341: goto -136 -> 205
      //   344: goto -341 -> 3
      //   347: iconst_0
      //   348: ireturn
      // Local variable table:
      //   start	length	slot	name	signature
      //   0	349	0	this	ˊ
      //   0	349	1	paramObject	Object
      //   56	282	2	i	int
      // Exception table:
      //   from	to	target	type
      //   318	322	115	java/lang/Exception
      //   327	335	175	java/lang/Exception
    }
    
    /* Error */
    public int hashCode()
    {
      // Byte code:
      //   0: goto +179 -> 179
      //   3: goto +187 -> 190
      //   6: iconst_5
      //   7: istore_2
      //   8: goto +46 -> 54
      //   11: iconst_1
      //   12: istore_1
      //   13: goto +141 -> 154
      //   16: aload_3
      //   17: invokevirtual 100	java/lang/Object:hashCode	()I
      //   20: istore_1
      //   21: goto +15 -> 36
      //   24: iconst_0
      //   25: istore_1
      //   26: goto +128 -> 154
      //   29: iload_1
      //   30: bipush 31
      //   32: imul
      //   33: iload_2
      //   34: iadd
      //   35: ireturn
      //   36: aload_0
      //   37: getfield 85	o/EM$ˊ:expirationDate	Lo/EM$If;
      //   40: astore_3
      //   41: aload_3
      //   42: ifnull +6 -> 48
      //   45: goto -39 -> 6
      //   48: goto +160 -> 208
      //   51: astore_3
      //   52: aload_3
      //   53: athrow
      //   54: iload_2
      //   55: lookupswitch	default:+25->80, 5:+33->88, 38:+62->117
      //   80: goto +8 -> 88
      //   83: iconst_0
      //   84: istore_1
      //   85: goto -49 -> 36
      //   88: getstatic 23	o/EM$ˊ:ˎ	I
      //   91: istore_2
      //   92: iload_2
      //   93: bipush 99
      //   95: iadd
      //   96: istore_2
      //   97: iload_2
      //   98: sipush 128
      //   101: irem
      //   102: putstatic 21	o/EM$ˊ:ˋ	I
      //   105: iload_2
      //   106: iconst_2
      //   107: irem
      //   108: ifeq +6 -> 114
      //   111: goto +103 -> 214
      //   114: goto +68 -> 182
      //   117: iconst_0
      //   118: istore_2
      //   119: goto +32 -> 151
      //   122: getstatic 23	o/EM$ˊ:ˎ	I
      //   125: istore_1
      //   126: iload_1
      //   127: bipush 97
      //   129: iadd
      //   130: istore_1
      //   131: iload_1
      //   132: sipush 128
      //   135: irem
      //   136: putstatic 21	o/EM$ˊ:ˋ	I
      //   139: iload_1
      //   140: iconst_2
      //   141: irem
      //   142: ifeq +6 -> 148
      //   145: goto -142 -> 3
      //   148: goto +42 -> 190
      //   151: goto -122 -> 29
      //   154: iload_1
      //   155: tableswitch	default:+21->176, 0:+-72->83, 1:+-139->16
      //   176: goto -93 -> 83
      //   179: goto -57 -> 122
      //   182: aload_3
      //   183: invokevirtual 100	java/lang/Object:hashCode	()I
      //   186: istore_2
      //   187: goto -158 -> 29
      //   190: aload_0
      //   191: getfield 92	o/EM$ˊ:last4	Ljava/lang/String;
      //   194: astore_3
      //   195: aload_3
      //   196: ifnull +6 -> 202
      //   199: goto -188 -> 11
      //   202: goto -178 -> 24
      //   205: astore_3
      //   206: aload_3
      //   207: athrow
      //   208: bipush 38
      //   210: istore_2
      //   211: goto -157 -> 54
      //   214: goto -32 -> 182
      // Local variable table:
      //   start	length	slot	name	signature
      //   0	217	0	this	ˊ
      //   12	143	1	i	int
      //   7	204	2	j	int
      //   16	26	3	localIf	EM.If
      //   51	132	3	localException1	Exception
      //   194	2	3	str	String
      //   205	2	3	localException2	Exception
      // Exception table:
      //   from	to	target	type
      //   97	105	51	java/lang/Exception
      //   122	126	51	java/lang/Exception
      //   88	92	205	java/lang/Exception
      //   131	139	205	java/lang/Exception
    }
    
    public String toString()
    {
      for (;;)
      {
        int i = ˋ + 115;
        ˎ = i % 128;
        if (i % 2 == 0) {
          return str;
        }
        return str;
        String str = ˏ(0, '昌', 24).intern() + this.last4 + ˏ(24, '䛁', 17).intern() + this.expirationDate + ˏ(41, '\000', 1).intern();
      }
    }
    
    public final String ˊ()
    {
      for (;;)
      {
        int i = ˎ + 99;
        ˋ = i % 128;
        if (i % 2 == 0) {
          break label74;
        }
        label74:
        for (i = 0;; i = 1)
        {
          switch (i)
          {
          default: 
            break;
          case 0: 
            String str = this.last4;
            i = null.length;
            return str;
          }
          return this.last4;
        }
      }
    }
    
    /* Error */
    public final EM.If ˏ()
    {
      // Byte code:
      //   0: goto +40 -> 40
      //   3: astore_2
      //   4: aload_2
      //   5: athrow
      //   6: aload_2
      //   7: areturn
      //   8: getstatic 21	o/EM$ˊ:ˋ	I
      //   11: istore_1
      //   12: iload_1
      //   13: bipush 9
      //   15: iadd
      //   16: istore_1
      //   17: iload_1
      //   18: sipush 128
      //   21: irem
      //   22: putstatic 23	o/EM$ˊ:ˎ	I
      //   25: iload_1
      //   26: iconst_2
      //   27: irem
      //   28: ifne +6 -> 34
      //   31: goto +6 -> 37
      //   34: goto +9 -> 43
      //   37: goto +6 -> 43
      //   40: goto -32 -> 8
      //   43: aload_0
      //   44: getfield 85	o/EM$ˊ:expirationDate	Lo/EM$If;
      //   47: astore_2
      //   48: getstatic 23	o/EM$ˊ:ˎ	I
      //   51: istore_1
      //   52: iload_1
      //   53: bipush 11
      //   55: iadd
      //   56: istore_1
      //   57: iload_1
      //   58: sipush 128
      //   61: irem
      //   62: putstatic 21	o/EM$ˊ:ˋ	I
      //   65: iload_1
      //   66: iconst_2
      //   67: irem
      //   68: ifeq +6 -> 74
      //   71: goto -65 -> 6
      //   74: aload_2
      //   75: areturn
      // Local variable table:
      //   start	length	slot	name	signature
      //   0	76	0	this	ˊ
      //   11	57	1	i	int
      //   3	4	2	localException	Exception
      //   47	28	2	localIf	EM.If
      // Exception table:
      //   from	to	target	type
      //   8	12	3	java/lang/Exception
      //   17	25	3	java/lang/Exception
      //   48	52	3	java/lang/Exception
      //   57	65	3	java/lang/Exception
    }
  }
}
