package o;

import java.util.List;

public final class En
{
  private static int ˊ = 0;
  private static boolean ˋ;
  private static boolean ˎ;
  private static int ˏ = 99;
  private static char[] ॱ;
  private static int ॱॱ = 1;
  private final List<Ec> cardAndInstancesAssociations;
  
  static
  {
    ˋ = true;
    ˎ = true;
    ॱ = new char[] { 168, 209, 213, 210, 207, 200, 199, 166, 196, 214, 181, 211, 139, 198, 164, 172, 215, 204, 160, 140 };
  }
  
  /* Error */
  private static String ˏ(byte[] paramArrayOfByte, int[] paramArrayOfInt, char[] paramArrayOfChar, int paramInt)
  {
    // Byte code:
    //   0: goto +513 -> 513
    //   3: iload 5
    //   5: tableswitch	default:+23->28, 0:+161->166, 1:+23->28
    //   28: new 56	java/lang/String
    //   31: dup
    //   32: aload_1
    //   33: invokespecial 60	java/lang/String:<init>	([C)V
    //   36: areturn
    //   37: goto +209 -> 246
    //   40: new 56	java/lang/String
    //   43: dup
    //   44: aload_0
    //   45: invokespecial 60	java/lang/String:<init>	([C)V
    //   48: areturn
    //   49: iconst_1
    //   50: istore 4
    //   52: goto +315 -> 367
    //   55: iload 5
    //   57: lookupswitch	default:+27->84, 22:+257->314, 56:+143->200
    //   84: goto +230 -> 314
    //   87: iconst_1
    //   88: istore 5
    //   90: goto -87 -> 3
    //   93: aload_0
    //   94: arraylength
    //   95: istore 7
    //   97: iload 7
    //   99: newarray char
    //   101: astore_1
    //   102: iconst_0
    //   103: istore 5
    //   105: goto +111 -> 216
    //   108: iload 4
    //   110: iload 5
    //   112: if_icmpge +6 -> 118
    //   115: goto +314 -> 429
    //   118: goto -78 -> 40
    //   121: aload_2
    //   122: arraylength
    //   123: istore 5
    //   125: iload 5
    //   127: newarray char
    //   129: astore_0
    //   130: iconst_0
    //   131: istore 4
    //   133: goto -25 -> 108
    //   136: getstatic 20	o/En:ˊ	I
    //   139: bipush 99
    //   141: iadd
    //   142: istore 4
    //   144: iload 4
    //   146: sipush 128
    //   149: irem
    //   150: putstatic 22	o/En:ॱॱ	I
    //   153: iload 4
    //   155: iconst_2
    //   156: irem
    //   157: ifne +6 -> 163
    //   160: goto +363 -> 523
    //   163: goto -70 -> 93
    //   166: aload_1
    //   167: iload 4
    //   169: aload 9
    //   171: aload_0
    //   172: iload 7
    //   174: iconst_1
    //   175: isub
    //   176: iload 4
    //   178: isub
    //   179: baload
    //   180: iload_3
    //   181: iadd
    //   182: caload
    //   183: iload 6
    //   185: isub
    //   186: i2c
    //   187: castore
    //   188: iload 4
    //   190: iconst_1
    //   191: iadd
    //   192: istore 4
    //   194: goto +207 -> 401
    //   197: astore_0
    //   198: aload_0
    //   199: athrow
    //   200: new 56	java/lang/String
    //   203: dup
    //   204: aload_0
    //   205: invokespecial 60	java/lang/String:<init>	([C)V
    //   208: areturn
    //   209: bipush 13
    //   211: istore 4
    //   213: goto +53 -> 266
    //   216: getstatic 20	o/En:ˊ	I
    //   219: bipush 123
    //   221: iadd
    //   222: istore 4
    //   224: iload 4
    //   226: sipush 128
    //   229: irem
    //   230: putstatic 22	o/En:ॱॱ	I
    //   233: iload 4
    //   235: iconst_2
    //   236: irem
    //   237: ifne +6 -> 243
    //   240: goto -191 -> 49
    //   243: goto +180 -> 423
    //   246: iload 4
    //   248: iload 7
    //   250: if_icmpge +6 -> 256
    //   253: goto +6 -> 259
    //   256: goto +270 -> 526
    //   259: bipush 22
    //   261: istore 5
    //   263: goto -208 -> 55
    //   266: iload 4
    //   268: lookupswitch	default:+28->296, 0:+199->467, 13:+-132->136
    //   296: goto +171 -> 467
    //   299: aload_1
    //   300: arraylength
    //   301: istore 7
    //   303: iload 7
    //   305: newarray char
    //   307: astore_0
    //   308: iconst_0
    //   309: istore 4
    //   311: goto -274 -> 37
    //   314: aload_0
    //   315: iload 4
    //   317: aload 9
    //   319: aload_1
    //   320: iload 7
    //   322: iconst_1
    //   323: isub
    //   324: iload 4
    //   326: isub
    //   327: iaload
    //   328: iload_3
    //   329: isub
    //   330: caload
    //   331: iload 6
    //   333: isub
    //   334: i2c
    //   335: castore
    //   336: iload 4
    //   338: iconst_1
    //   339: iadd
    //   340: istore 4
    //   342: goto +141 -> 483
    //   345: getstatic 48	o/En:ॱ	[C
    //   348: astore 9
    //   350: getstatic 50	o/En:ˏ	I
    //   353: istore 6
    //   355: getstatic 24	o/En:ˋ	Z
    //   358: ifeq +6 -> 364
    //   361: goto -152 -> 209
    //   364: goto +50 -> 414
    //   367: iload 4
    //   369: tableswitch	default:+23->392, 0:+147->516, 1:+91->460
    //   392: goto +68 -> 460
    //   395: iconst_0
    //   396: istore 5
    //   398: goto -395 -> 3
    //   401: iload 4
    //   403: iload 7
    //   405: if_icmpge +6 -> 411
    //   408: goto -13 -> 395
    //   411: goto -324 -> 87
    //   414: iconst_0
    //   415: istore 4
    //   417: goto -151 -> 266
    //   420: goto -174 -> 246
    //   423: iconst_0
    //   424: istore 4
    //   426: goto -59 -> 367
    //   429: aload_0
    //   430: iload 4
    //   432: aload 9
    //   434: aload_2
    //   435: iload 5
    //   437: iconst_1
    //   438: isub
    //   439: iload 4
    //   441: isub
    //   442: caload
    //   443: iload_3
    //   444: isub
    //   445: caload
    //   446: iload 6
    //   448: isub
    //   449: i2c
    //   450: castore
    //   451: iload 4
    //   453: iconst_1
    //   454: iadd
    //   455: istore 4
    //   457: goto -349 -> 108
    //   460: iload 5
    //   462: istore 4
    //   464: goto -63 -> 401
    //   467: getstatic 26	o/En:ˎ	Z
    //   470: istore 8
    //   472: iload 8
    //   474: ifeq +6 -> 480
    //   477: goto -356 -> 121
    //   480: goto -181 -> 299
    //   483: getstatic 22	o/En:ॱॱ	I
    //   486: bipush 65
    //   488: iadd
    //   489: istore 5
    //   491: iload 5
    //   493: sipush 128
    //   496: irem
    //   497: putstatic 20	o/En:ˊ	I
    //   500: iload 5
    //   502: iconst_2
    //   503: irem
    //   504: ifeq +6 -> 510
    //   507: goto +26 -> 533
    //   510: goto -90 -> 420
    //   513: goto -168 -> 345
    //   516: iload 5
    //   518: istore 4
    //   520: goto -119 -> 401
    //   523: goto -430 -> 93
    //   526: bipush 56
    //   528: istore 5
    //   530: goto -475 -> 55
    //   533: goto -287 -> 246
    // Local variable table:
    //   start	length	slot	name	signature
    //   0	536	0	paramArrayOfByte	byte[]
    //   0	536	1	paramArrayOfInt	int[]
    //   0	536	2	paramArrayOfChar	char[]
    //   0	536	3	paramInt	int
    //   50	469	4	i	int
    //   3	526	5	j	int
    //   183	266	6	k	int
    //   95	311	7	m	int
    //   470	3	8	bool	boolean
    //   169	264	9	arrayOfChar	char[]
    // Exception table:
    //   from	to	target	type
    //   467	472	197	java/lang/Exception
  }
  
  /* Error */
  public boolean equals(Object paramObject)
  {
    // Byte code:
    //   0: goto +119 -> 119
    //   3: iload_2
    //   4: tableswitch	default:+24->28, 0:+79->83, 1:+46->50
    //   28: goto +55 -> 83
    //   31: bipush 97
    //   33: istore_2
    //   34: goto +90 -> 124
    //   37: aload_1
    //   38: instanceof 2
    //   41: ifeq +6 -> 47
    //   44: goto +148 -> 192
    //   47: goto +108 -> 155
    //   50: aload_1
    //   51: checkcast 2	o/En
    //   54: astore_1
    //   55: aload_0
    //   56: getfield 64	o/En:cardAndInstancesAssociations	Ljava/util/List;
    //   59: aload_1
    //   60: getfield 64	o/En:cardAndInstancesAssociations	Ljava/util/List;
    //   63: invokestatic 69	o/vq:ˊ	(Ljava/lang/Object;Ljava/lang/Object;)Z
    //   66: pop
    //   67: new 71	java/lang/NullPointerException
    //   70: dup
    //   71: invokespecial 73	java/lang/NullPointerException:<init>	()V
    //   74: athrow
    //   75: goto +147 -> 222
    //   78: iconst_1
    //   79: istore_2
    //   80: goto -77 -> 3
    //   83: aload_1
    //   84: checkcast 2	o/En
    //   87: astore_1
    //   88: aload_0
    //   89: getfield 64	o/En:cardAndInstancesAssociations	Ljava/util/List;
    //   92: aload_1
    //   93: getfield 64	o/En:cardAndInstancesAssociations	Ljava/util/List;
    //   96: invokestatic 69	o/vq:ˊ	(Ljava/lang/Object;Ljava/lang/Object;)Z
    //   99: ifeq +6 -> 105
    //   102: goto +117 -> 219
    //   105: goto +50 -> 155
    //   108: bipush 9
    //   110: istore_2
    //   111: goto +13 -> 124
    //   114: astore_1
    //   115: aload_1
    //   116: athrow
    //   117: iconst_1
    //   118: ireturn
    //   119: goto +44 -> 163
    //   122: iconst_0
    //   123: ireturn
    //   124: iload_2
    //   125: lookupswitch	default:+27->152, 9:+-88->37, 97:+94->219
    //   152: goto +67 -> 219
    //   155: goto -33 -> 122
    //   158: iconst_0
    //   159: istore_2
    //   160: goto -157 -> 3
    //   163: getstatic 20	o/En:ˊ	I
    //   166: istore_2
    //   167: iload_2
    //   168: bipush 39
    //   170: iadd
    //   171: istore_2
    //   172: iload_2
    //   173: sipush 128
    //   176: irem
    //   177: putstatic 22	o/En:ॱॱ	I
    //   180: iload_2
    //   181: iconst_2
    //   182: irem
    //   183: ifne +6 -> 189
    //   186: goto -111 -> 75
    //   189: goto +33 -> 222
    //   192: getstatic 22	o/En:ॱॱ	I
    //   195: bipush 15
    //   197: iadd
    //   198: istore_2
    //   199: iload_2
    //   200: sipush 128
    //   203: irem
    //   204: putstatic 20	o/En:ˊ	I
    //   207: iload_2
    //   208: iconst_2
    //   209: irem
    //   210: ifeq +6 -> 216
    //   213: goto -135 -> 78
    //   216: goto -58 -> 158
    //   219: goto -102 -> 117
    //   222: aload_0
    //   223: aload_1
    //   224: if_acmpeq +6 -> 230
    //   227: goto -119 -> 108
    //   230: goto -199 -> 31
    // Local variable table:
    //   start	length	slot	name	signature
    //   0	233	0	this	En
    //   0	233	1	paramObject	Object
    //   3	207	2	i	int
    // Exception table:
    //   from	to	target	type
    //   163	167	114	java/lang/Exception
    //   172	180	114	java/lang/Exception
  }
  
  /* Error */
  public int hashCode()
  {
    // Byte code:
    //   0: goto +72 -> 72
    //   3: goto +100 -> 103
    //   6: getstatic 20	o/En:ˊ	I
    //   9: bipush 83
    //   11: iadd
    //   12: istore_1
    //   13: iload_1
    //   14: sipush 128
    //   17: irem
    //   18: putstatic 22	o/En:ॱॱ	I
    //   21: iload_1
    //   22: iconst_2
    //   23: irem
    //   24: ifne +6 -> 30
    //   27: goto +89 -> 116
    //   30: goto +8 -> 38
    //   33: iconst_1
    //   34: istore_1
    //   35: goto +40 -> 75
    //   38: iload_2
    //   39: ireturn
    //   40: astore_3
    //   41: aload_3
    //   42: athrow
    //   43: getstatic 22	o/En:ॱॱ	I
    //   46: istore_1
    //   47: iload_1
    //   48: bipush 23
    //   50: iadd
    //   51: istore_1
    //   52: iload_1
    //   53: sipush 128
    //   56: irem
    //   57: putstatic 20	o/En:ˊ	I
    //   60: iload_1
    //   61: iconst_2
    //   62: irem
    //   63: ifeq +6 -> 69
    //   66: goto -63 -> 3
    //   69: goto +34 -> 103
    //   72: goto +67 -> 139
    //   75: iload_1
    //   76: tableswitch	default:+24->100, 0:+-33->43, 1:+38->114
    //   100: goto +14 -> 114
    //   103: aload_3
    //   104: invokevirtual 77	java/lang/Object:hashCode	()I
    //   107: istore_2
    //   108: goto -102 -> 6
    //   111: astore_3
    //   112: aload_3
    //   113: athrow
    //   114: iconst_0
    //   115: ireturn
    //   116: goto -78 -> 38
    //   119: iconst_0
    //   120: istore_1
    //   121: goto -46 -> 75
    //   124: aload_0
    //   125: getfield 64	o/En:cardAndInstancesAssociations	Ljava/util/List;
    //   128: astore_3
    //   129: aload_3
    //   130: ifnull +6 -> 136
    //   133: goto -14 -> 119
    //   136: goto -103 -> 33
    //   139: getstatic 20	o/En:ˊ	I
    //   142: istore_1
    //   143: iload_1
    //   144: bipush 93
    //   146: iadd
    //   147: istore_1
    //   148: iload_1
    //   149: sipush 128
    //   152: irem
    //   153: putstatic 22	o/En:ॱॱ	I
    //   156: iload_1
    //   157: iconst_2
    //   158: irem
    //   159: ifne +6 -> 165
    //   162: goto -38 -> 124
    //   165: goto -41 -> 124
    // Local variable table:
    //   start	length	slot	name	signature
    //   0	168	0	this	En
    //   12	147	1	i	int
    //   38	70	2	j	int
    //   40	64	3	localException1	Exception
    //   111	2	3	localException2	Exception
    //   128	2	3	localList	List
    // Exception table:
    //   from	to	target	type
    //   52	60	40	java/lang/Exception
    //   148	156	40	java/lang/Exception
    //   43	47	111	java/lang/Exception
    //   139	143	111	java/lang/Exception
  }
  
  public String toString()
  {
    break label406;
    int i = 0;
    break label409;
    label8:
    i = 1;
    break label409;
    String str;
    label406:
    for (;;)
    {
      str = ˏ(new byte[] { -109, -118, -126, -124, -110, -111, -119, -110, -114, -124, -118, -118, -113, -118, -122, -114, -126, -119, -111, -118, -126, -112, -121, -126, -113, -121, -125, -119, -114, -115, -122, -118, -126, -124, -116, -118, -122, -117, -118, -121, -125, -119, -120, -121, -122, -123, -123, -124, -125, -126, -127 }, null, null, 127).intern() + this.cardAndInstancesAssociations + ˏ(new byte[] { -108 }, null, null, 127).intern();
      i = ˊ + 19;
      ॱॱ = i % 128;
      if (i % 2 == 0) {
        break;
      }
      break label8;
      return str;
      throw new NullPointerException();
    }
    label409:
    switch (i)
    {
    }
    return str;
  }
  
  /* Error */
  public final List<Ec> ˋ()
  {
    // Byte code:
    //   0: goto +111 -> 111
    //   3: getstatic 22	o/En:ॱॱ	I
    //   6: bipush 111
    //   8: iadd
    //   9: istore_1
    //   10: iload_1
    //   11: sipush 128
    //   14: irem
    //   15: putstatic 20	o/En:ˊ	I
    //   18: iload_1
    //   19: iconst_2
    //   20: irem
    //   21: ifeq +6 -> 27
    //   24: goto +47 -> 71
    //   27: iconst_1
    //   28: istore_1
    //   29: goto +9 -> 38
    //   32: astore_2
    //   33: aload_2
    //   34: athrow
    //   35: astore_2
    //   36: aload_2
    //   37: athrow
    //   38: iload_1
    //   39: tableswitch	default:+21->60, 0:+37->76, 1:+24->63
    //   60: goto +16 -> 76
    //   63: aload_0
    //   64: getfield 64	o/En:cardAndInstancesAssociations	Ljava/util/List;
    //   67: astore_2
    //   68: goto +18 -> 86
    //   71: iconst_0
    //   72: istore_1
    //   73: goto -35 -> 38
    //   76: aload_0
    //   77: getfield 64	o/En:cardAndInstancesAssociations	Ljava/util/List;
    //   80: astore_2
    //   81: bipush 42
    //   83: iconst_0
    //   84: idiv
    //   85: istore_1
    //   86: getstatic 22	o/En:ॱॱ	I
    //   89: bipush 45
    //   91: iadd
    //   92: istore_1
    //   93: iload_1
    //   94: sipush 128
    //   97: irem
    //   98: putstatic 20	o/En:ˊ	I
    //   101: iload_1
    //   102: iconst_2
    //   103: irem
    //   104: ifeq +5 -> 109
    //   107: aload_2
    //   108: areturn
    //   109: aload_2
    //   110: areturn
    //   111: goto -108 -> 3
    // Local variable table:
    //   start	length	slot	name	signature
    //   0	114	0	this	En
    //   9	95	1	i	int
    //   32	2	2	localException1	Exception
    //   35	2	2	localException2	Exception
    //   67	43	2	localList	List
    // Exception table:
    //   from	to	target	type
    //   76	86	32	java/lang/Exception
    //   3	10	35	java/lang/Exception
    //   10	18	35	java/lang/Exception
  }
}
