package o;

public final class EN
{
  private static char[] ˊ = { 9823, 16106, 5952, 28605, 17412, 23690, -18974, -30116, -7475, -1217, -11383, 10291, 365, 6596, 32302, 22186, -20734, -31640, -25369, -2815, -12892, 8714, 14996, 5091, 26715, 16597, 22831, -20093, -26971, 44, 6327, 12621, 18860, 25146, 31438, -27789, -29720, -24062, -9479, -3733, -5687, 184, 16155, 22490, 44, 6327, 12638, 18871, 25139, 31383, -27649, -21438, -15156, -8959, -2681, 3600, 10097, 16278, 44, 6327, 12621, 18857, 25141, 31382, -27676, -21419, -15114, -8914, -2677, 3608, 10025, 28752, 26827, 16673, 14801, 4687, 2813, -7294, -9203, -19291, -21155, -31321, -25712, -31989, -21791, -11763, -1663, -7877, 2115, 14318, 24377, -5619, -3434, -9363, -23667, -30701, -28527, 31198, 18034, 12011, 14091, 8105, -7105, -12980, -10825, 44, 6327, 12619, 18877, 25132, 31386, -27656, -21440, -15156, -8922, -2679, 3603, 10064, 16330, 22582, 28860, -30387, 19195, 21088, 31642, 883, 10489, 12352, -9964, -6510, -29174, -26634, -16571, 17603, 28069, 29973, 4848, 14972, -15462, 44, 6327, 12634, 18876, 25132, 31382, -27721, -2431, -4582, -14368, -16631, -27517, -29638, 25935, 23267, 12921, 11142, 814, -1886, -11785, -13977, -20862, -31215, 32736, 20495 };
  private static int ˋ;
  private static int ˎ = 0;
  private static long ॱ;
  private final String binCurrency;
  private final String cardIdentifier;
  private final String cardholderName;
  private final String cif;
  private final String clientName;
  private final String expirationDate;
  private final EA productName;
  private final Eh scheme;
  private final String shortPan;
  private final El status;
  private final ˋ turnover;
  private final Ei type;
  
  static
  {
    ˋ = 1;
    ॱ = 588023385825220759L;
  }
  
  /* Error */
  private static String ॱ(int paramInt1, char paramChar, int paramInt2)
  {
    // Byte code:
    //   0: goto +56 -> 56
    //   3: getstatic 37	o/EN:ˋ	I
    //   6: istore_0
    //   7: iload_0
    //   8: bipush 103
    //   10: iadd
    //   11: istore_0
    //   12: iload_0
    //   13: sipush 128
    //   16: irem
    //   17: putstatic 35	o/EN:ˎ	I
    //   20: iload_0
    //   21: iconst_2
    //   22: irem
    //   23: ifeq +6 -> 29
    //   26: goto +211 -> 237
    //   29: aload 11
    //   31: areturn
    //   32: iconst_0
    //   33: istore_3
    //   34: goto +25 -> 59
    //   37: astore 11
    //   39: aload 11
    //   41: athrow
    //   42: new 201	java/lang/String
    //   45: dup
    //   46: aload 11
    //   48: invokespecial 205	java/lang/String:<init>	([C)V
    //   51: astore 11
    //   53: goto -50 -> 3
    //   56: goto +69 -> 125
    //   59: iload_3
    //   60: tableswitch	default:+24->84, 0:+76->136, 1:+59->119
    //   84: goto +35 -> 119
    //   87: astore 11
    //   89: aload 11
    //   91: athrow
    //   92: iload 4
    //   94: tableswitch	default:+22->116, 0:+48->142, 1:+95->189
    //   116: goto +26 -> 142
    //   119: iload 4
    //   121: istore_3
    //   122: goto +56 -> 178
    //   125: iload_2
    //   126: newarray char
    //   128: astore 11
    //   130: iconst_0
    //   131: istore 4
    //   133: goto +107 -> 240
    //   136: iload 4
    //   138: istore_3
    //   139: goto +39 -> 178
    //   142: aload 11
    //   144: iload_3
    //   145: getstatic 195	o/EN:ˊ	[C
    //   148: iload_0
    //   149: iload_3
    //   150: iadd
    //   151: caload
    //   152: i2l
    //   153: iload_3
    //   154: i2l
    //   155: getstatic 41	o/EN:ॱ	J
    //   158: lmul
    //   159: lxor
    //   160: iload_1
    //   161: i2l
    //   162: lxor
    //   163: l2i
    //   164: i2c
    //   165: castore
    //   166: iload_3
    //   167: iconst_1
    //   168: iadd
    //   169: istore_3
    //   170: goto +8 -> 178
    //   173: iconst_1
    //   174: istore_3
    //   175: goto -116 -> 59
    //   178: iload_3
    //   179: iload_2
    //   180: if_icmpge +6 -> 186
    //   183: goto +84 -> 267
    //   186: goto -144 -> 42
    //   189: getstatic 195	o/EN:ˊ	[C
    //   192: astore 12
    //   194: aload 12
    //   196: iload_0
    //   197: iload_3
    //   198: irem
    //   199: caload
    //   200: i2l
    //   201: lstore 5
    //   203: iload_3
    //   204: i2l
    //   205: lstore 7
    //   207: getstatic 41	o/EN:ॱ	J
    //   210: lstore 9
    //   212: aload 11
    //   214: iload_3
    //   215: lload 5
    //   217: lload 7
    //   219: lload 9
    //   221: lrem
    //   222: lxor
    //   223: iload_1
    //   224: i2l
    //   225: lrem
    //   226: l2i
    //   227: i2c
    //   228: castore
    //   229: iload_3
    //   230: bipush 77
    //   232: iadd
    //   233: istore_3
    //   234: goto -56 -> 178
    //   237: aload 11
    //   239: areturn
    //   240: getstatic 37	o/EN:ˋ	I
    //   243: bipush 69
    //   245: iadd
    //   246: istore_3
    //   247: iload_3
    //   248: sipush 128
    //   251: irem
    //   252: putstatic 35	o/EN:ˎ	I
    //   255: iload_3
    //   256: iconst_2
    //   257: irem
    //   258: ifeq +6 -> 264
    //   261: goto -88 -> 173
    //   264: goto -232 -> 32
    //   267: getstatic 35	o/EN:ˎ	I
    //   270: bipush 73
    //   272: iadd
    //   273: istore 4
    //   275: iload 4
    //   277: sipush 128
    //   280: irem
    //   281: putstatic 37	o/EN:ˋ	I
    //   284: iload 4
    //   286: iconst_2
    //   287: irem
    //   288: ifne +6 -> 294
    //   291: goto +9 -> 300
    //   294: iconst_0
    //   295: istore 4
    //   297: goto -205 -> 92
    //   300: iconst_1
    //   301: istore 4
    //   303: goto -211 -> 92
    // Local variable table:
    //   start	length	slot	name	signature
    //   0	306	0	paramInt1	int
    //   0	306	1	paramChar	char
    //   0	306	2	paramInt2	int
    //   33	225	3	i	int
    //   92	210	4	j	int
    //   201	15	5	l1	long
    //   205	13	7	l2	long
    //   210	10	9	l3	long
    //   29	1	11	str1	String
    //   37	10	11	localException1	Exception
    //   51	1	11	str2	String
    //   87	3	11	localException2	Exception
    //   128	110	11	arrayOfChar1	char[]
    //   192	3	12	arrayOfChar2	char[]
    // Exception table:
    //   from	to	target	type
    //   189	194	37	java/lang/Exception
    //   267	275	37	java/lang/Exception
    //   275	284	37	java/lang/Exception
    //   3	7	87	java/lang/Exception
    //   207	212	87	java/lang/Exception
  }
  
  /* Error */
  public boolean equals(Object paramObject)
  {
    // Byte code:
    //   0: goto +404 -> 404
    //   3: aload_0
    //   4: getfield 209	o/EN:binCurrency	Ljava/lang/String;
    //   7: aload_1
    //   8: getfield 209	o/EN:binCurrency	Ljava/lang/String;
    //   11: invokestatic 214	o/vq:ˊ	(Ljava/lang/Object;Ljava/lang/Object;)Z
    //   14: ifeq +6 -> 20
    //   17: goto +426 -> 443
    //   20: goto +669 -> 689
    //   23: getstatic 35	o/EN:ˎ	I
    //   26: bipush 77
    //   28: iadd
    //   29: istore_2
    //   30: iload_2
    //   31: sipush 128
    //   34: irem
    //   35: putstatic 37	o/EN:ˋ	I
    //   38: iload_2
    //   39: iconst_2
    //   40: irem
    //   41: ifne +6 -> 47
    //   44: goto +84 -> 128
    //   47: goto +549 -> 596
    //   50: getstatic 37	o/EN:ˋ	I
    //   53: iconst_5
    //   54: iadd
    //   55: istore_2
    //   56: iload_2
    //   57: sipush 128
    //   60: irem
    //   61: putstatic 35	o/EN:ˎ	I
    //   64: iload_2
    //   65: iconst_2
    //   66: irem
    //   67: ifeq +6 -> 73
    //   70: goto +457 -> 527
    //   73: goto +339 -> 412
    //   76: bipush 76
    //   78: istore_2
    //   79: goto +78 -> 157
    //   82: getstatic 37	o/EN:ˋ	I
    //   85: iconst_1
    //   86: iadd
    //   87: istore_2
    //   88: iload_2
    //   89: sipush 128
    //   92: irem
    //   93: putstatic 35	o/EN:ˎ	I
    //   96: iload_2
    //   97: iconst_2
    //   98: irem
    //   99: ifeq +6 -> 105
    //   102: goto +85 -> 187
    //   105: goto +344 -> 449
    //   108: aload_0
    //   109: getfield 216	o/EN:cardIdentifier	Ljava/lang/String;
    //   112: aload_1
    //   113: getfield 216	o/EN:cardIdentifier	Ljava/lang/String;
    //   116: invokestatic 214	o/vq:ˊ	(Ljava/lang/Object;Ljava/lang/Object;)Z
    //   119: ifeq +6 -> 125
    //   122: goto +198 -> 320
    //   125: goto +26 -> 151
    //   128: goto +468 -> 596
    //   131: aload_0
    //   132: getfield 218	o/EN:scheme	Lo/Eh;
    //   135: aload_1
    //   136: getfield 218	o/EN:scheme	Lo/Eh;
    //   139: invokestatic 214	o/vq:ˊ	(Ljava/lang/Object;Ljava/lang/Object;)Z
    //   142: ifeq +6 -> 148
    //   145: goto +503 -> 648
    //   148: goto +167 -> 315
    //   151: bipush 93
    //   153: istore_2
    //   154: goto +260 -> 414
    //   157: iload_2
    //   158: lookupswitch	default:+26->184, 76:+593->751, 79:+-27->131
    //   184: goto -53 -> 131
    //   187: iconst_0
    //   188: istore_2
    //   189: goto +100 -> 289
    //   192: iload_2
    //   193: lookupswitch	default:+27->220, 10:+558->751, 21:+-111->82
    //   220: goto +531 -> 751
    //   223: iload_2
    //   224: lookupswitch	default:+28->252, 51:+527->751, 81:+102->326
    //   252: goto +499 -> 751
    //   255: goto -205 -> 50
    //   258: iconst_1
    //   259: istore_2
    //   260: goto +242 -> 502
    //   263: goto +219 -> 482
    //   266: aload_0
    //   267: getfield 220	o/EN:status	Lo/El;
    //   270: aload_1
    //   271: getfield 220	o/EN:status	Lo/El;
    //   274: invokestatic 214	o/vq:ˊ	(Ljava/lang/Object;Ljava/lang/Object;)Z
    //   277: ifeq +6 -> 283
    //   280: goto -277 -> 3
    //   283: goto +468 -> 751
    //   286: astore_1
    //   287: aload_1
    //   288: athrow
    //   289: iload_2
    //   290: tableswitch	default:+22->312, 0:+89->379, 1:+164->454
    //   312: goto +142 -> 454
    //   315: iconst_1
    //   316: istore_2
    //   317: goto +36 -> 353
    //   320: bipush 28
    //   322: istore_2
    //   323: goto +91 -> 414
    //   326: getstatic 37	o/EN:ˋ	I
    //   329: bipush 91
    //   331: iadd
    //   332: istore_2
    //   333: iload_2
    //   334: sipush 128
    //   337: irem
    //   338: putstatic 35	o/EN:ˎ	I
    //   341: iload_2
    //   342: iconst_2
    //   343: irem
    //   344: ifeq +6 -> 350
    //   347: goto -84 -> 263
    //   350: goto +132 -> 482
    //   353: iload_2
    //   354: tableswitch	default:+22->376, 0:+274->628, 1:+397->751
    //   376: goto +375 -> 751
    //   379: aload_0
    //   380: getfield 222	o/EN:cardholderName	Ljava/lang/String;
    //   383: aload_1
    //   384: getfield 222	o/EN:cardholderName	Ljava/lang/String;
    //   387: invokestatic 214	o/vq:ˊ	(Ljava/lang/Object;Ljava/lang/Object;)Z
    //   390: istore_3
    //   391: aconst_null
    //   392: arraylength
    //   393: istore_2
    //   394: iload_3
    //   395: ifeq +6 -> 401
    //   398: goto -143 -> 255
    //   401: goto +350 -> 751
    //   404: goto +154 -> 558
    //   407: iconst_0
    //   408: istore_2
    //   409: goto +93 -> 502
    //   412: iconst_1
    //   413: ireturn
    //   414: iload_2
    //   415: lookupswitch	default:+25->440, 28:+280->695, 93:+336->751
    //   440: goto +255 -> 695
    //   443: bipush 81
    //   445: istore_2
    //   446: goto -223 -> 223
    //   449: iconst_1
    //   450: istore_2
    //   451: goto -162 -> 289
    //   454: aload_0
    //   455: getfield 222	o/EN:cardholderName	Ljava/lang/String;
    //   458: astore 4
    //   460: aload_1
    //   461: getfield 222	o/EN:cardholderName	Ljava/lang/String;
    //   464: astore_1
    //   465: aload 4
    //   467: aload_1
    //   468: invokestatic 214	o/vq:ˊ	(Ljava/lang/Object;Ljava/lang/Object;)Z
    //   471: istore_3
    //   472: iload_3
    //   473: ifeq +6 -> 479
    //   476: goto -221 -> 255
    //   479: goto +272 -> 751
    //   482: aload_0
    //   483: getfield 224	o/EN:expirationDate	Ljava/lang/String;
    //   486: aload_1
    //   487: getfield 224	o/EN:expirationDate	Ljava/lang/String;
    //   490: invokestatic 214	o/vq:ˊ	(Ljava/lang/Object;Ljava/lang/Object;)Z
    //   493: ifeq +6 -> 499
    //   496: goto -388 -> 108
    //   499: goto +252 -> 751
    //   502: iload_2
    //   503: tableswitch	default:+21->524, 0:+248->751, 1:+225->728
    //   524: goto +227 -> 751
    //   527: new 226	java/lang/NullPointerException
    //   530: dup
    //   531: invokespecial 228	java/lang/NullPointerException:<init>	()V
    //   534: athrow
    //   535: astore_1
    //   536: aload_1
    //   537: athrow
    //   538: aload_0
    //   539: getfield 230	o/EN:clientName	Ljava/lang/String;
    //   542: aload_1
    //   543: getfield 230	o/EN:clientName	Ljava/lang/String;
    //   546: invokestatic 214	o/vq:ˊ	(Ljava/lang/Object;Ljava/lang/Object;)Z
    //   549: ifeq +6 -> 555
    //   552: goto -294 -> 258
    //   555: goto -148 -> 407
    //   558: aload_0
    //   559: aload_1
    //   560: if_acmpeq +6 -> 566
    //   563: goto +152 -> 715
    //   566: goto -311 -> 255
    //   569: getstatic 37	o/EN:ˋ	I
    //   572: bipush 15
    //   574: iadd
    //   575: istore_2
    //   576: iload_2
    //   577: sipush 128
    //   580: irem
    //   581: putstatic 35	o/EN:ˎ	I
    //   584: iload_2
    //   585: iconst_2
    //   586: irem
    //   587: ifeq +6 -> 593
    //   590: goto +71 -> 661
    //   593: goto -327 -> 266
    //   596: aload_0
    //   597: getfield 232	o/EN:cif	Ljava/lang/String;
    //   600: aload_1
    //   601: getfield 232	o/EN:cif	Ljava/lang/String;
    //   604: invokestatic 214	o/vq:ˊ	(Ljava/lang/Object;Ljava/lang/Object;)Z
    //   607: ifeq +6 -> 613
    //   610: goto +6 -> 616
    //   613: goto -537 -> 76
    //   616: bipush 79
    //   618: istore_2
    //   619: goto -462 -> 157
    //   622: bipush 21
    //   624: istore_2
    //   625: goto -433 -> 192
    //   628: aload_0
    //   629: getfield 234	o/EN:productName	Lo/EA;
    //   632: aload_1
    //   633: getfield 234	o/EN:productName	Lo/EA;
    //   636: invokestatic 214	o/vq:ˊ	(Ljava/lang/Object;Ljava/lang/Object;)Z
    //   639: ifeq +6 -> 645
    //   642: goto -104 -> 538
    //   645: goto +106 -> 751
    //   648: iconst_0
    //   649: istore_2
    //   650: goto -297 -> 353
    //   653: iconst_0
    //   654: ireturn
    //   655: bipush 10
    //   657: istore_2
    //   658: goto -466 -> 192
    //   661: goto -395 -> 266
    //   664: aload_1
    //   665: checkcast 2	o/EN
    //   668: astore_1
    //   669: aload_0
    //   670: getfield 236	o/EN:turnover	Lo/EN$ˋ;
    //   673: aload_1
    //   674: getfield 236	o/EN:turnover	Lo/EN$ˋ;
    //   677: invokestatic 214	o/vq:ˊ	(Ljava/lang/Object;Ljava/lang/Object;)Z
    //   680: ifeq +6 -> 686
    //   683: goto -660 -> 23
    //   686: goto +65 -> 751
    //   689: bipush 51
    //   691: istore_2
    //   692: goto -469 -> 223
    //   695: aload_0
    //   696: getfield 238	o/EN:type	Lo/Ei;
    //   699: aload_1
    //   700: getfield 238	o/EN:type	Lo/Ei;
    //   703: invokestatic 214	o/vq:ˊ	(Ljava/lang/Object;Ljava/lang/Object;)Z
    //   706: ifeq +6 -> 712
    //   709: goto -87 -> 622
    //   712: goto -57 -> 655
    //   715: aload_1
    //   716: instanceof 2
    //   719: ifeq +6 -> 725
    //   722: goto -58 -> 664
    //   725: goto +26 -> 751
    //   728: aload_0
    //   729: getfield 240	o/EN:shortPan	Ljava/lang/String;
    //   732: astore 4
    //   734: aload 4
    //   736: aload_1
    //   737: getfield 240	o/EN:shortPan	Ljava/lang/String;
    //   740: invokestatic 214	o/vq:ˊ	(Ljava/lang/Object;Ljava/lang/Object;)Z
    //   743: istore_3
    //   744: iload_3
    //   745: ifeq +6 -> 751
    //   748: goto -179 -> 569
    //   751: goto -98 -> 653
    // Local variable table:
    //   start	length	slot	name	signature
    //   0	754	0	this	EN
    //   0	754	1	paramObject	Object
    //   29	663	2	i	int
    //   390	355	3	bool	boolean
    //   458	277	4	str	String
    // Exception table:
    //   from	to	target	type
    //   454	460	286	java/lang/Exception
    //   460	465	286	java/lang/Exception
    //   465	472	286	java/lang/Exception
    //   734	744	286	java/lang/Exception
    //   460	465	535	java/lang/Exception
    //   728	734	535	java/lang/Exception
  }
  
  /* Error */
  public int hashCode()
  {
    // Byte code:
    //   0: goto +191 -> 191
    //   3: bipush 11
    //   5: istore 8
    //   7: goto +850 -> 857
    //   10: getstatic 37	o/EN:ˋ	I
    //   13: bipush 55
    //   15: iadd
    //   16: istore 8
    //   18: iload 8
    //   20: sipush 128
    //   23: irem
    //   24: putstatic 35	o/EN:ˎ	I
    //   27: iload 8
    //   29: iconst_2
    //   30: irem
    //   31: ifeq +6 -> 37
    //   34: goto +469 -> 503
    //   37: goto +62 -> 99
    //   40: aload 14
    //   42: invokevirtual 244	java/lang/Object:hashCode	()I
    //   45: istore 8
    //   47: goto +439 -> 486
    //   50: iconst_0
    //   51: istore 12
    //   53: goto +357 -> 410
    //   56: iconst_1
    //   57: istore 11
    //   59: goto +745 -> 804
    //   62: aload 14
    //   64: invokevirtual 244	java/lang/Object:hashCode	()I
    //   67: istore 7
    //   69: goto -59 -> 10
    //   72: getstatic 37	o/EN:ˋ	I
    //   75: bipush 115
    //   77: iadd
    //   78: istore_1
    //   79: iload_1
    //   80: sipush 128
    //   83: irem
    //   84: putstatic 35	o/EN:ˎ	I
    //   87: iload_1
    //   88: iconst_2
    //   89: irem
    //   90: ifeq +6 -> 96
    //   93: goto +187 -> 280
    //   96: goto +628 -> 724
    //   99: goto +502 -> 601
    //   102: aload 14
    //   104: invokevirtual 244	java/lang/Object:hashCode	()I
    //   107: istore 4
    //   109: goto +85 -> 194
    //   112: getstatic 37	o/EN:ˋ	I
    //   115: bipush 113
    //   117: iadd
    //   118: istore 6
    //   120: iload 6
    //   122: sipush 128
    //   125: irem
    //   126: putstatic 35	o/EN:ˎ	I
    //   129: iload 6
    //   131: iconst_2
    //   132: irem
    //   133: ifeq +6 -> 139
    //   136: goto +701 -> 837
    //   139: goto +553 -> 692
    //   142: iconst_0
    //   143: istore 8
    //   145: goto +341 -> 486
    //   148: aload 14
    //   150: invokevirtual 244	java/lang/Object:hashCode	()I
    //   153: istore 10
    //   155: goto +503 -> 658
    //   158: iload 6
    //   160: lookupswitch	default:+28->188, 20:+198->358, 57:+602->762
    //   188: goto +170 -> 358
    //   191: goto +554 -> 745
    //   194: aload_0
    //   195: getfield 234	o/EN:productName	Lo/EA;
    //   198: astore 14
    //   200: aload 14
    //   202: ifnull +6 -> 208
    //   205: goto +107 -> 312
    //   208: goto +119 -> 327
    //   211: aload 14
    //   213: invokevirtual 244	java/lang/Object:hashCode	()I
    //   216: istore 12
    //   218: goto +295 -> 513
    //   221: aload 14
    //   223: invokevirtual 244	java/lang/Object:hashCode	()I
    //   226: istore_2
    //   227: goto +223 -> 450
    //   230: aload_0
    //   231: getfield 230	o/EN:clientName	Ljava/lang/String;
    //   234: astore 14
    //   236: aload 14
    //   238: ifnull +6 -> 244
    //   241: goto -169 -> 72
    //   244: goto +496 -> 740
    //   247: getstatic 37	o/EN:ˋ	I
    //   250: bipush 121
    //   252: iadd
    //   253: istore_1
    //   254: iload_1
    //   255: sipush 128
    //   258: irem
    //   259: putstatic 35	o/EN:ˎ	I
    //   262: iload_1
    //   263: iconst_2
    //   264: irem
    //   265: ifeq +6 -> 271
    //   268: goto +353 -> 621
    //   271: goto +78 -> 349
    //   274: iconst_0
    //   275: istore 9
    //   277: goto +307 -> 584
    //   280: aload 14
    //   282: invokevirtual 244	java/lang/Object:hashCode	()I
    //   285: istore_1
    //   286: bipush 35
    //   288: iconst_0
    //   289: idiv
    //   290: istore 6
    //   292: goto -180 -> 112
    //   295: aload_0
    //   296: getfield 218	o/EN:scheme	Lo/Eh;
    //   299: astore 14
    //   301: aload 14
    //   303: ifnull +6 -> 309
    //   306: goto -204 -> 102
    //   309: goto +522 -> 831
    //   312: aload 14
    //   314: invokevirtual 244	java/lang/Object:hashCode	()I
    //   317: istore 5
    //   319: goto -89 -> 230
    //   322: iconst_0
    //   323: istore_2
    //   324: goto +463 -> 787
    //   327: iconst_0
    //   328: istore 5
    //   330: goto -100 -> 230
    //   333: aload 14
    //   335: invokevirtual 244	java/lang/Object:hashCode	()I
    //   338: istore 11
    //   340: goto +335 -> 675
    //   343: iconst_0
    //   344: istore 11
    //   346: goto +458 -> 804
    //   349: aload 14
    //   351: invokevirtual 244	java/lang/Object:hashCode	()I
    //   354: istore_3
    //   355: goto -60 -> 295
    //   358: getstatic 37	o/EN:ˋ	I
    //   361: bipush 11
    //   363: iadd
    //   364: istore 6
    //   366: iload 6
    //   368: sipush 128
    //   371: irem
    //   372: putstatic 35	o/EN:ˎ	I
    //   375: iload 6
    //   377: iconst_2
    //   378: irem
    //   379: ifeq +6 -> 385
    //   382: goto +515 -> 897
    //   385: goto +15 -> 400
    //   388: iconst_0
    //   389: istore 11
    //   391: goto +284 -> 675
    //   394: iconst_0
    //   395: istore 7
    //   397: goto +204 -> 601
    //   400: aload 14
    //   402: invokevirtual 244	java/lang/Object:hashCode	()I
    //   405: istore 6
    //   407: goto +433 -> 840
    //   410: getstatic 37	o/EN:ˋ	I
    //   413: bipush 87
    //   415: iadd
    //   416: istore 13
    //   418: iload 13
    //   420: sipush 128
    //   423: irem
    //   424: putstatic 35	o/EN:ˎ	I
    //   427: iload 13
    //   429: iconst_2
    //   430: irem
    //   431: ifeq +6 -> 437
    //   434: goto +261 -> 695
    //   437: goto +181 -> 618
    //   440: astore 14
    //   442: aload 14
    //   444: athrow
    //   445: iconst_1
    //   446: istore_1
    //   447: goto +453 -> 900
    //   450: goto +337 -> 787
    //   453: getstatic 35	o/EN:ˎ	I
    //   456: bipush 73
    //   458: iadd
    //   459: istore 10
    //   461: iload 10
    //   463: sipush 128
    //   466: irem
    //   467: putstatic 37	o/EN:ˋ	I
    //   470: iload 10
    //   472: iconst_2
    //   473: irem
    //   474: ifne +6 -> 480
    //   477: goto +291 -> 768
    //   480: goto -332 -> 148
    //   483: goto -421 -> 62
    //   486: aload_0
    //   487: getfield 224	o/EN:expirationDate	Ljava/lang/String;
    //   490: astore 14
    //   492: aload 14
    //   494: ifnull +6 -> 500
    //   497: goto +390 -> 887
    //   500: goto -226 -> 274
    //   503: goto -404 -> 99
    //   506: bipush 20
    //   508: istore 6
    //   510: goto -352 -> 158
    //   513: iload_2
    //   514: bipush 31
    //   516: imul
    //   517: iload_3
    //   518: iadd
    //   519: bipush 31
    //   521: imul
    //   522: iload 4
    //   524: iadd
    //   525: bipush 31
    //   527: imul
    //   528: iload 5
    //   530: iadd
    //   531: bipush 31
    //   533: imul
    //   534: iload_1
    //   535: iadd
    //   536: bipush 31
    //   538: imul
    //   539: iload 6
    //   541: iadd
    //   542: bipush 31
    //   544: imul
    //   545: iload 7
    //   547: iadd
    //   548: bipush 31
    //   550: imul
    //   551: iload 8
    //   553: iadd
    //   554: bipush 31
    //   556: imul
    //   557: iload 9
    //   559: iadd
    //   560: bipush 31
    //   562: imul
    //   563: iload 10
    //   565: iadd
    //   566: bipush 31
    //   568: imul
    //   569: iload 11
    //   571: iadd
    //   572: bipush 31
    //   574: imul
    //   575: iload 12
    //   577: iadd
    //   578: ireturn
    //   579: astore 14
    //   581: aload 14
    //   583: athrow
    //   584: aload_0
    //   585: getfield 216	o/EN:cardIdentifier	Ljava/lang/String;
    //   588: astore 14
    //   590: aload 14
    //   592: ifnull +6 -> 598
    //   595: goto -142 -> 453
    //   598: goto +329 -> 927
    //   601: aload_0
    //   602: getfield 209	o/EN:binCurrency	Ljava/lang/String;
    //   605: astore 14
    //   607: aload 14
    //   609: ifnull +6 -> 615
    //   612: goto -609 -> 3
    //   615: goto +118 -> 733
    //   618: goto -105 -> 513
    //   621: goto -272 -> 349
    //   624: getstatic 37	o/EN:ˋ	I
    //   627: istore 7
    //   629: iload 7
    //   631: bipush 77
    //   633: iadd
    //   634: istore 7
    //   636: iload 7
    //   638: sipush 128
    //   641: irem
    //   642: putstatic 35	o/EN:ˎ	I
    //   645: iload 7
    //   647: iconst_2
    //   648: irem
    //   649: ifeq +6 -> 655
    //   652: goto -169 -> 483
    //   655: goto -593 -> 62
    //   658: aload_0
    //   659: getfield 238	o/EN:type	Lo/Ei;
    //   662: astore 14
    //   664: aload 14
    //   666: ifnull +6 -> 672
    //   669: goto -613 -> 56
    //   672: goto -329 -> 343
    //   675: aload_0
    //   676: getfield 222	o/EN:cardholderName	Ljava/lang/String;
    //   679: astore 14
    //   681: aload 14
    //   683: ifnull +6 -> 689
    //   686: goto -475 -> 211
    //   689: goto -639 -> 50
    //   692: goto +6 -> 698
    //   695: goto -182 -> 513
    //   698: aload_0
    //   699: getfield 240	o/EN:shortPan	Ljava/lang/String;
    //   702: astore 14
    //   704: aload 14
    //   706: ifnull +6 -> 712
    //   709: goto -203 -> 506
    //   712: bipush 57
    //   714: istore 6
    //   716: goto -558 -> 158
    //   719: iconst_0
    //   720: istore_1
    //   721: goto +179 -> 900
    //   724: aload 14
    //   726: invokevirtual 244	java/lang/Object:hashCode	()I
    //   729: istore_1
    //   730: goto -618 -> 112
    //   733: bipush 67
    //   735: istore 8
    //   737: goto +120 -> 857
    //   740: iconst_0
    //   741: istore_1
    //   742: goto -44 -> 698
    //   745: aload_0
    //   746: getfield 236	o/EN:turnover	Lo/EN$ˋ;
    //   749: astore 14
    //   751: aload 14
    //   753: ifnull +6 -> 759
    //   756: goto -311 -> 445
    //   759: goto -40 -> 719
    //   762: iconst_0
    //   763: istore 6
    //   765: goto +75 -> 840
    //   768: aload 14
    //   770: invokevirtual 244	java/lang/Object:hashCode	()I
    //   773: istore_1
    //   774: new 226	java/lang/NullPointerException
    //   777: dup
    //   778: invokespecial 228	java/lang/NullPointerException:<init>	()V
    //   781: athrow
    //   782: iconst_0
    //   783: istore_3
    //   784: goto -489 -> 295
    //   787: aload_0
    //   788: getfield 232	o/EN:cif	Ljava/lang/String;
    //   791: astore 14
    //   793: aload 14
    //   795: ifnull +6 -> 801
    //   798: goto -551 -> 247
    //   801: goto -19 -> 782
    //   804: iload 11
    //   806: tableswitch	default:+22->828, 0:+-418->388, 1:+-473->333
    //   828: goto -440 -> 388
    //   831: iconst_0
    //   832: istore 4
    //   834: goto -640 -> 194
    //   837: goto -145 -> 692
    //   840: aload_0
    //   841: getfield 220	o/EN:status	Lo/El;
    //   844: astore 14
    //   846: aload 14
    //   848: ifnull +6 -> 854
    //   851: goto -227 -> 624
    //   854: goto -460 -> 394
    //   857: iload 8
    //   859: lookupswitch	default:+25->884, 11:+-819->40, 67:+-717->142
    //   884: goto -742 -> 142
    //   887: aload 14
    //   889: invokevirtual 244	java/lang/Object:hashCode	()I
    //   892: istore 9
    //   894: goto -310 -> 584
    //   897: goto -497 -> 400
    //   900: iload_1
    //   901: tableswitch	default:+23->924, 0:+-579->322, 1:+-680->221
    //   924: goto -602 -> 322
    //   927: iconst_0
    //   928: istore 10
    //   930: goto -272 -> 658
    // Local variable table:
    //   start	length	slot	name	signature
    //   0	933	0	this	EN
    //   78	823	1	i	int
    //   226	291	2	j	int
    //   354	430	3	k	int
    //   107	726	4	m	int
    //   317	214	5	n	int
    //   118	646	6	i1	int
    //   67	582	7	i2	int
    //   5	853	8	i3	int
    //   275	618	9	i4	int
    //   153	776	10	i5	int
    //   57	748	11	i6	int
    //   51	527	12	i7	int
    //   416	15	13	i8	int
    //   40	361	14	localObject1	Object
    //   440	3	14	localException1	Exception
    //   490	3	14	str	String
    //   579	3	14	localException2	Exception
    //   588	300	14	localObject2	Object
    // Exception table:
    //   from	to	target	type
    //   624	629	440	java/lang/Exception
    //   675	681	440	java/lang/Exception
    //   148	155	579	java/lang/Exception
    //   221	227	579	java/lang/Exception
    //   636	645	579	java/lang/Exception
  }
  
  /* Error */
  public String toString()
  {
    // Byte code:
    //   0: goto +320 -> 320
    //   3: new 226	java/lang/NullPointerException
    //   6: dup
    //   7: invokespecial 228	java/lang/NullPointerException:<init>	()V
    //   10: athrow
    //   11: bipush 19
    //   13: istore_1
    //   14: goto +344 -> 358
    //   17: new 248	java/lang/StringBuilder
    //   20: dup
    //   21: invokespecial 249	java/lang/StringBuilder:<init>	()V
    //   24: iconst_0
    //   25: sipush 9756
    //   28: bipush 29
    //   30: invokestatic 251	o/EN:ॱ	(ICI)Ljava/lang/String;
    //   33: invokevirtual 254	java/lang/String:intern	()Ljava/lang/String;
    //   36: invokevirtual 258	java/lang/StringBuilder:append	(Ljava/lang/String;)Ljava/lang/StringBuilder;
    //   39: aload_0
    //   40: getfield 236	o/EN:turnover	Lo/EN$ˋ;
    //   43: invokevirtual 261	java/lang/StringBuilder:append	(Ljava/lang/Object;)Ljava/lang/StringBuilder;
    //   46: bipush 29
    //   48: iconst_0
    //   49: bipush 6
    //   51: invokestatic 251	o/EN:ॱ	(ICI)Ljava/lang/String;
    //   54: invokevirtual 254	java/lang/String:intern	()Ljava/lang/String;
    //   57: invokevirtual 258	java/lang/StringBuilder:append	(Ljava/lang/String;)Ljava/lang/StringBuilder;
    //   60: aload_0
    //   61: getfield 232	o/EN:cif	Ljava/lang/String;
    //   64: invokevirtual 258	java/lang/StringBuilder:append	(Ljava/lang/String;)Ljava/lang/StringBuilder;
    //   67: bipush 35
    //   69: ldc_w 262
    //   72: bipush 9
    //   74: invokestatic 251	o/EN:ॱ	(ICI)Ljava/lang/String;
    //   77: invokevirtual 254	java/lang/String:intern	()Ljava/lang/String;
    //   80: invokevirtual 258	java/lang/StringBuilder:append	(Ljava/lang/String;)Ljava/lang/StringBuilder;
    //   83: aload_0
    //   84: getfield 218	o/EN:scheme	Lo/Eh;
    //   87: invokevirtual 261	java/lang/StringBuilder:append	(Ljava/lang/Object;)Ljava/lang/StringBuilder;
    //   90: bipush 44
    //   92: iconst_0
    //   93: bipush 14
    //   95: invokestatic 251	o/EN:ॱ	(ICI)Ljava/lang/String;
    //   98: invokevirtual 254	java/lang/String:intern	()Ljava/lang/String;
    //   101: invokevirtual 258	java/lang/StringBuilder:append	(Ljava/lang/String;)Ljava/lang/StringBuilder;
    //   104: aload_0
    //   105: getfield 234	o/EN:productName	Lo/EA;
    //   108: invokevirtual 261	java/lang/StringBuilder:append	(Ljava/lang/Object;)Ljava/lang/StringBuilder;
    //   111: bipush 58
    //   113: iconst_0
    //   114: bipush 13
    //   116: invokestatic 251	o/EN:ॱ	(ICI)Ljava/lang/String;
    //   119: invokevirtual 254	java/lang/String:intern	()Ljava/lang/String;
    //   122: invokevirtual 258	java/lang/StringBuilder:append	(Ljava/lang/String;)Ljava/lang/StringBuilder;
    //   125: aload_0
    //   126: getfield 230	o/EN:clientName	Ljava/lang/String;
    //   129: invokevirtual 258	java/lang/StringBuilder:append	(Ljava/lang/String;)Ljava/lang/StringBuilder;
    //   132: bipush 71
    //   134: sipush 28796
    //   137: bipush 11
    //   139: invokestatic 251	o/EN:ॱ	(ICI)Ljava/lang/String;
    //   142: invokevirtual 254	java/lang/String:intern	()Ljava/lang/String;
    //   145: invokevirtual 258	java/lang/StringBuilder:append	(Ljava/lang/String;)Ljava/lang/StringBuilder;
    //   148: aload_0
    //   149: getfield 240	o/EN:shortPan	Ljava/lang/String;
    //   152: invokevirtual 258	java/lang/StringBuilder:append	(Ljava/lang/String;)Ljava/lang/StringBuilder;
    //   155: bipush 82
    //   157: ldc_w 263
    //   160: bipush 9
    //   162: invokestatic 251	o/EN:ॱ	(ICI)Ljava/lang/String;
    //   165: invokevirtual 254	java/lang/String:intern	()Ljava/lang/String;
    //   168: invokevirtual 258	java/lang/StringBuilder:append	(Ljava/lang/String;)Ljava/lang/StringBuilder;
    //   171: aload_0
    //   172: getfield 220	o/EN:status	Lo/El;
    //   175: invokevirtual 261	java/lang/StringBuilder:append	(Ljava/lang/Object;)Ljava/lang/StringBuilder;
    //   178: bipush 91
    //   180: ldc_w 264
    //   183: bipush 14
    //   185: invokestatic 251	o/EN:ॱ	(ICI)Ljava/lang/String;
    //   188: invokevirtual 254	java/lang/String:intern	()Ljava/lang/String;
    //   191: invokevirtual 258	java/lang/StringBuilder:append	(Ljava/lang/String;)Ljava/lang/StringBuilder;
    //   194: aload_0
    //   195: getfield 209	o/EN:binCurrency	Ljava/lang/String;
    //   198: invokevirtual 258	java/lang/StringBuilder:append	(Ljava/lang/String;)Ljava/lang/StringBuilder;
    //   201: bipush 105
    //   203: iconst_0
    //   204: bipush 17
    //   206: invokestatic 251	o/EN:ॱ	(ICI)Ljava/lang/String;
    //   209: invokevirtual 254	java/lang/String:intern	()Ljava/lang/String;
    //   212: invokevirtual 258	java/lang/StringBuilder:append	(Ljava/lang/String;)Ljava/lang/StringBuilder;
    //   215: aload_0
    //   216: getfield 224	o/EN:expirationDate	Ljava/lang/String;
    //   219: invokevirtual 258	java/lang/StringBuilder:append	(Ljava/lang/String;)Ljava/lang/StringBuilder;
    //   222: bipush 122
    //   224: sipush 19159
    //   227: bipush 17
    //   229: invokestatic 251	o/EN:ॱ	(ICI)Ljava/lang/String;
    //   232: invokevirtual 254	java/lang/String:intern	()Ljava/lang/String;
    //   235: invokevirtual 258	java/lang/StringBuilder:append	(Ljava/lang/String;)Ljava/lang/StringBuilder;
    //   238: aload_0
    //   239: getfield 216	o/EN:cardIdentifier	Ljava/lang/String;
    //   242: invokevirtual 258	java/lang/StringBuilder:append	(Ljava/lang/String;)Ljava/lang/StringBuilder;
    //   245: sipush 139
    //   248: iconst_0
    //   249: bipush 7
    //   251: invokestatic 251	o/EN:ॱ	(ICI)Ljava/lang/String;
    //   254: invokevirtual 254	java/lang/String:intern	()Ljava/lang/String;
    //   257: invokevirtual 258	java/lang/StringBuilder:append	(Ljava/lang/String;)Ljava/lang/StringBuilder;
    //   260: aload_0
    //   261: getfield 238	o/EN:type	Lo/Ei;
    //   264: invokevirtual 261	java/lang/StringBuilder:append	(Ljava/lang/Object;)Ljava/lang/StringBuilder;
    //   267: sipush 146
    //   270: ldc_w 265
    //   273: bipush 17
    //   275: invokestatic 251	o/EN:ॱ	(ICI)Ljava/lang/String;
    //   278: invokevirtual 254	java/lang/String:intern	()Ljava/lang/String;
    //   281: invokevirtual 258	java/lang/StringBuilder:append	(Ljava/lang/String;)Ljava/lang/StringBuilder;
    //   284: aload_0
    //   285: getfield 222	o/EN:cardholderName	Ljava/lang/String;
    //   288: invokevirtual 258	java/lang/StringBuilder:append	(Ljava/lang/String;)Ljava/lang/StringBuilder;
    //   291: sipush 163
    //   294: sipush 20518
    //   297: iconst_1
    //   298: invokestatic 251	o/EN:ॱ	(ICI)Ljava/lang/String;
    //   301: invokevirtual 254	java/lang/String:intern	()Ljava/lang/String;
    //   304: invokevirtual 258	java/lang/StringBuilder:append	(Ljava/lang/String;)Ljava/lang/StringBuilder;
    //   307: invokevirtual 267	java/lang/StringBuilder:toString	()Ljava/lang/String;
    //   310: astore_2
    //   311: goto +20 -> 331
    //   314: bipush 42
    //   316: istore_1
    //   317: goto +41 -> 358
    //   320: goto -303 -> 17
    //   323: astore_2
    //   324: aload_2
    //   325: athrow
    //   326: astore_2
    //   327: aload_2
    //   328: athrow
    //   329: aload_2
    //   330: areturn
    //   331: getstatic 35	o/EN:ˎ	I
    //   334: bipush 37
    //   336: iadd
    //   337: istore_1
    //   338: iload_1
    //   339: sipush 128
    //   342: irem
    //   343: putstatic 37	o/EN:ˋ	I
    //   346: iload_1
    //   347: iconst_2
    //   348: irem
    //   349: ifne +6 -> 355
    //   352: goto -38 -> 314
    //   355: goto -344 -> 11
    //   358: iload_1
    //   359: lookupswitch	default:+25->384, 19:+-30->329, 42:+-356->3
    //   384: aload_2
    //   385: areturn
    // Local variable table:
    //   start	length	slot	name	signature
    //   0	386	0	this	EN
    //   13	346	1	i	int
    //   310	1	2	str	String
    //   323	2	2	localException1	Exception
    //   326	59	2	localException2	Exception
    // Exception table:
    //   from	to	target	type
    //   331	338	323	java/lang/Exception
    //   338	346	323	java/lang/Exception
    //   338	346	326	java/lang/Exception
  }
  
  public final String ˎ()
  {
    String str;
    for (;;)
    {
      int i;
      switch (i)
      {
      default: 
        return str;
        i = ˋ + 17;
        ˎ = i % 128;
        if (i % 2 == 0) {
          break label110;
        }
        break;
      case 0: 
        label30:
        i = 30 / 0;
        return str;
        for (;;)
        {
          str = this.binCurrency;
          break label30;
          i = 0;
          break;
          do
          {
            break;
            i = ˎ + 55;
            ˋ = i % 128;
          } while (i % 2 == 0);
        }
        label110:
        i = 1;
      }
    }
    return str;
  }
  
  public final ˋ ˏ()
  {
    int i;
    for (;;)
    {
      throw new NullPointerException();
      i = 1;
      break label103;
      break label76;
      ˋ localˋ = this.turnover;
      for (;;)
      {
        i = 9;
        break label131;
        localˋ = this.turnover;
        i = null.length;
        break label49;
        label44:
        i = 0;
        try
        {
          label49:
          i = ˋ + 39;
          ˎ = i % 128;
          if (i % 2 != 0) {
            break label44;
          }
        }
        catch (Exception localException)
        {
          label76:
          throw localException;
        }
        i = ˋ + 113;
        ˎ = i % 128;
        if (i % 2 != 0) {
          break label168;
        }
      }
      label103:
      switch (i)
      {
      }
    }
    for (;;)
    {
      label131:
      switch (i)
      {
      }
      break;
      return localException;
      label168:
      i = 83;
    }
  }
  
  public static final class ˋ
  {
    private static char[] ˊ = { -29778, 31770, 25762, 27947, 21953, 24165, 18145, 20123, 14202, 16298, 8257, 10483, 4463, 6406, 425, 2604, -3433, -417, 2502, 4395, 6313, 8262, 11254, 13156, 15123, 17086, 18986, 21916, 44, -2123, -4281, -6448, -8646, -10851, -13034, -14977, -17199, -19456, 6492, -4411, -2503, -67, -14527, -13059, -11161, -9193, -23148, -21212, -19761, -17794, -31752, -29732, -10334, 8251, 14528, 12612, 2495, 547, 6801, 4841, 27459, 25486, -23004, 20925, 18755, 16578, 30760, 29582, 27419, 25466, 6868, 4688, 3518, 1362, 44, -2123, -4277, -6455, -8651, -10880, -13038, -14990, -17206, -19375, -21577, -23770, -25967, -27906, -30125, -32299, 31012, 28888, 44, -2123, -4262, -6448, -8643, -10873, -13046, -15008, -17259, 44, -2123, -4280, -6445, -8645, -10870, -13035, -14986, -17204, -19332, -21569, -23800, -25975, -27905, -30126, -32378, 15975, -13826, -12012, -10112, -8074, -5170, -3236, -1246, -32122, -30190, -27228, 41 };
    private static int ˋ = 0;
    private static int ˏ = 1;
    private static long ॱ = 2400237038854928277L;
    private final double automated;
    private final double availableAmount;
    private final double blockedAmount;
    private final double creditLimit;
    private final long dueDate;
    private final double minimum;
    private final double monthly;
    private final double points;
    private final double realised;
    private final double utilized;
    
    /* Error */
    private static String ˏ(int paramInt1, char paramChar, int paramInt2)
    {
      // Byte code:
      //   0: goto +121 -> 121
      //   3: getstatic 158	o/EN$ˋ:ˊ	[C
      //   6: astore 10
      //   8: aload 10
      //   10: iload 4
      //   12: iload_0
      //   13: imul
      //   14: caload
      //   15: i2l
      //   16: lstore 5
      //   18: iload_0
      //   19: i2l
      //   20: lstore 7
      //   22: aload 9
      //   24: iload_0
      //   25: lload 5
      //   27: lload 7
      //   29: getstatic 34	o/EN$ˋ:ॱ	J
      //   32: land
      //   33: lmul
      //   34: iload_3
      //   35: i2l
      //   36: lor
      //   37: l2i
      //   38: i2c
      //   39: castore
      //   40: iload_0
      //   41: bipush 86
      //   43: iadd
      //   44: istore_0
      //   45: goto +79 -> 124
      //   48: iload_2
      //   49: newarray char
      //   51: astore 9
      //   53: goto +172 -> 225
      //   56: iload_1
      //   57: tableswitch	default:+23->80, 0:+78->135, 1:+158->215
      //   80: goto +135 -> 215
      //   83: aload 9
      //   85: iload_0
      //   86: getstatic 158	o/EN$ˋ:ˊ	[C
      //   89: iload 4
      //   91: iload_0
      //   92: iadd
      //   93: caload
      //   94: i2l
      //   95: iload_0
      //   96: i2l
      //   97: getstatic 34	o/EN$ˋ:ॱ	J
      //   100: lmul
      //   101: lxor
      //   102: iload_3
      //   103: i2l
      //   104: lxor
      //   105: l2i
      //   106: i2c
      //   107: castore
      //   108: iload_0
      //   109: iconst_1
      //   110: iadd
      //   111: istore_0
      //   112: goto +12 -> 124
      //   115: bipush 66
      //   117: istore_3
      //   118: goto +68 -> 186
      //   121: goto +114 -> 235
      //   124: iload_0
      //   125: iload_2
      //   126: if_icmpge +6 -> 132
      //   129: goto +133 -> 262
      //   132: goto +49 -> 181
      //   135: getstatic 28	o/EN$ˋ:ˋ	I
      //   138: bipush 15
      //   140: iadd
      //   141: istore_1
      //   142: iload_1
      //   143: sipush 128
      //   146: irem
      //   147: putstatic 30	o/EN$ˋ:ˏ	I
      //   150: iload_1
      //   151: iconst_2
      //   152: irem
      //   153: ifne +6 -> 159
      //   156: goto -153 -> 3
      //   159: goto -76 -> 83
      //   162: bipush 11
      //   164: istore_3
      //   165: goto +21 -> 186
      //   168: astore 9
      //   170: aload 9
      //   172: athrow
      //   173: iload_2
      //   174: newarray char
      //   176: astore 9
      //   178: goto +47 -> 225
      //   181: iconst_1
      //   182: istore_1
      //   183: goto -127 -> 56
      //   186: iload_3
      //   187: lookupswitch	default:+25->212, 11:+-14->173, 66:+-139->48
      //   212: goto -164 -> 48
      //   215: new 164	java/lang/String
      //   218: dup
      //   219: aload 9
      //   221: invokespecial 168	java/lang/String:<init>	([C)V
      //   224: areturn
      //   225: iload_1
      //   226: istore_3
      //   227: iload_0
      //   228: istore 4
      //   230: iconst_0
      //   231: istore_0
      //   232: goto -108 -> 124
      //   235: getstatic 30	o/EN$ˋ:ˏ	I
      //   238: bipush 31
      //   240: iadd
      //   241: istore_3
      //   242: iload_3
      //   243: sipush 128
      //   246: irem
      //   247: putstatic 28	o/EN$ˋ:ˋ	I
      //   250: iload_3
      //   251: iconst_2
      //   252: irem
      //   253: ifeq +6 -> 259
      //   256: goto -94 -> 162
      //   259: goto -144 -> 115
      //   262: iconst_0
      //   263: istore_1
      //   264: goto -208 -> 56
      //   267: astore 9
      //   269: aload 9
      //   271: athrow
      // Local variable table:
      //   start	length	slot	name	signature
      //   0	272	0	paramInt1	int
      //   0	272	1	paramChar	char
      //   0	272	2	paramInt2	int
      //   34	219	3	i	int
      //   10	219	4	j	int
      //   16	10	5	l1	long
      //   20	8	7	l2	long
      //   22	62	9	arrayOfChar1	char[]
      //   168	3	9	localException1	Exception
      //   176	44	9	arrayOfChar2	char[]
      //   267	3	9	localException2	Exception
      //   6	3	10	arrayOfChar3	char[]
      // Exception table:
      //   from	to	target	type
      //   3	8	168	java/lang/Exception
      //   22	40	267	java/lang/Exception
    }
    
    /* Error */
    public boolean equals(Object paramObject)
    {
      // Byte code:
      //   0: goto +733 -> 733
      //   3: bipush 98
      //   5: istore 6
      //   7: goto +475 -> 482
      //   10: aload_0
      //   11: getfield 172	o/EN$ˋ:dueDate	J
      //   14: aload_1
      //   15: getfield 172	o/EN$ˋ:dueDate	J
      //   18: lcmp
      //   19: ifne +6 -> 25
      //   22: goto +6 -> 28
      //   25: goto +351 -> 376
      //   28: getstatic 30	o/EN$ˋ:ˏ	I
      //   31: bipush 47
      //   33: iadd
      //   34: istore 6
      //   36: iload 6
      //   38: sipush 128
      //   41: irem
      //   42: putstatic 28	o/EN$ˋ:ˋ	I
      //   45: iload 6
      //   47: iconst_2
      //   48: irem
      //   49: ifeq +6 -> 55
      //   52: goto +92 -> 144
      //   55: goto +540 -> 595
      //   58: bipush 35
      //   60: istore 6
      //   62: goto +123 -> 185
      //   65: goto +629 -> 694
      //   68: bipush 6
      //   70: istore 6
      //   72: goto +149 -> 221
      //   75: getstatic 28	o/EN$ˋ:ˋ	I
      //   78: bipush 103
      //   80: iadd
      //   81: istore 6
      //   83: iload 6
      //   85: sipush 128
      //   88: irem
      //   89: putstatic 30	o/EN$ˋ:ˏ	I
      //   92: iload 6
      //   94: iconst_2
      //   95: irem
      //   96: ifne +6 -> 102
      //   99: goto +58 -> 157
      //   102: goto +572 -> 674
      //   105: bipush 69
      //   107: istore 6
      //   109: goto +373 -> 482
      //   112: getstatic 28	o/EN$ˋ:ˋ	I
      //   115: bipush 85
      //   117: iadd
      //   118: istore 6
      //   120: iload 6
      //   122: sipush 128
      //   125: irem
      //   126: putstatic 30	o/EN$ˋ:ˏ	I
      //   129: iload 6
      //   131: iconst_2
      //   132: irem
      //   133: ifne +6 -> 139
      //   136: goto +210 -> 346
      //   139: goto +249 -> 388
      //   142: iconst_0
      //   143: ireturn
      //   144: goto +451 -> 595
      //   147: goto -5 -> 142
      //   150: bipush 10
      //   152: istore 6
      //   154: goto +254 -> 408
      //   157: aload_0
      //   158: getfield 174	o/EN$ˋ:realised	D
      //   161: aload_1
      //   162: getfield 174	o/EN$ˋ:realised	D
      //   165: invokestatic 180	java/lang/Double:compare	(DD)I
      //   168: istore 6
      //   170: aconst_null
      //   171: arraylength
      //   172: istore 7
      //   174: iload 6
      //   176: ifne +6 -> 182
      //   179: goto +368 -> 547
      //   182: goto -35 -> 147
      //   185: iload 6
      //   187: lookupswitch	default:+25->212, 4:+64->251, 35:+-40->147
      //   212: goto +39 -> 251
      //   215: iconst_1
      //   216: istore 6
      //   218: goto +349 -> 567
      //   221: iload 6
      //   223: lookupswitch	default:+25->248, 6:+324->547, 20:+-76->147
      //   248: goto +299 -> 547
      //   251: aload_0
      //   252: getfield 182	o/EN$ˋ:blockedAmount	D
      //   255: dstore_2
      //   256: aload_1
      //   257: getfield 182	o/EN$ˋ:blockedAmount	D
      //   260: dstore 4
      //   262: dload_2
      //   263: dload 4
      //   265: invokestatic 180	java/lang/Double:compare	(DD)I
      //   268: ifne +6 -> 274
      //   271: goto -268 -> 3
      //   274: goto -169 -> 105
      //   277: iconst_1
      //   278: ireturn
      //   279: iconst_4
      //   280: istore 6
      //   282: goto +233 -> 515
      //   285: iload 6
      //   287: ifeq +6 -> 293
      //   290: goto +36 -> 326
      //   293: goto -146 -> 147
      //   296: goto -19 -> 277
      //   299: bipush 85
      //   301: istore 6
      //   303: goto +105 -> 408
      //   306: aload_0
      //   307: getfield 184	o/EN$ˋ:points	D
      //   310: aload_1
      //   311: getfield 184	o/EN$ˋ:points	D
      //   314: invokestatic 180	java/lang/Double:compare	(DD)I
      //   317: ifne +6 -> 323
      //   320: goto +149 -> 469
      //   323: goto -265 -> 58
      //   326: aload_0
      //   327: getfield 186	o/EN$ˋ:automated	D
      //   330: aload_1
      //   331: getfield 186	o/EN$ˋ:automated	D
      //   334: invokestatic 180	java/lang/Double:compare	(DD)I
      //   337: ifne +6 -> 343
      //   340: goto +264 -> 604
      //   343: goto -196 -> 147
      //   346: aload_0
      //   347: getfield 188	o/EN$ˋ:utilized	D
      //   350: aload_1
      //   351: getfield 188	o/EN$ˋ:utilized	D
      //   354: invokestatic 180	java/lang/Double:compare	(DD)I
      //   357: istore 6
      //   359: bipush 36
      //   361: iconst_0
      //   362: idiv
      //   363: istore 7
      //   365: iload 6
      //   367: ifne +6 -> 373
      //   370: goto -74 -> 296
      //   373: goto -226 -> 147
      //   376: iconst_0
      //   377: istore 6
      //   379: goto -94 -> 285
      //   382: iconst_0
      //   383: istore 6
      //   385: goto +182 -> 567
      //   388: aload_0
      //   389: getfield 188	o/EN$ˋ:utilized	D
      //   392: aload_1
      //   393: getfield 188	o/EN$ˋ:utilized	D
      //   396: invokestatic 180	java/lang/Double:compare	(DD)I
      //   399: ifne +6 -> 405
      //   402: goto -106 -> 296
      //   405: goto -258 -> 147
      //   408: iload 6
      //   410: lookupswitch	default:+26->436, 10:+-263->147, 85:+-400->10
      //   436: goto -426 -> 10
      //   439: getstatic 28	o/EN$ˋ:ˋ	I
      //   442: bipush 41
      //   444: iadd
      //   445: istore 6
      //   447: iload 6
      //   449: sipush 128
      //   452: irem
      //   453: putstatic 30	o/EN$ˋ:ˏ	I
      //   456: iload 6
      //   458: iconst_2
      //   459: irem
      //   460: ifne +6 -> 466
      //   463: goto -398 -> 65
      //   466: goto +228 -> 694
      //   469: iconst_4
      //   470: istore 6
      //   472: goto -287 -> 185
      //   475: bipush 20
      //   477: istore 6
      //   479: goto -258 -> 221
      //   482: iload 6
      //   484: lookupswitch	default:+28->512, 69:+-337->147, 98:+-372->112
      //   512: goto -400 -> 112
      //   515: iload 6
      //   517: lookupswitch	default:+27->544, 4:+-370->147, 27:+117->634
      //   544: goto +90 -> 634
      //   547: aload_0
      //   548: getfield 190	o/EN$ˋ:monthly	D
      //   551: aload_1
      //   552: getfield 190	o/EN$ˋ:monthly	D
      //   555: invokestatic 180	java/lang/Double:compare	(DD)I
      //   558: ifne +6 -> 564
      //   561: goto +93 -> 654
      //   564: goto -285 -> 279
      //   567: iload 6
      //   569: tableswitch	default:+23->592, 0:+92->661, 1:+-273->296
      //   592: goto -296 -> 296
      //   595: iconst_1
      //   596: istore 6
      //   598: goto -313 -> 285
      //   601: astore_1
      //   602: aload_1
      //   603: athrow
      //   604: aload_0
      //   605: getfield 192	o/EN$ˋ:availableAmount	D
      //   608: dstore_2
      //   609: aload_1
      //   610: getfield 192	o/EN$ˋ:availableAmount	D
      //   613: dstore 4
      //   615: dload_2
      //   616: dload 4
      //   618: invokestatic 180	java/lang/Double:compare	(DD)I
      //   621: istore 6
      //   623: iload 6
      //   625: ifne +6 -> 631
      //   628: goto -322 -> 306
      //   631: goto -484 -> 147
      //   634: aload_0
      //   635: getfield 194	o/EN$ˋ:creditLimit	D
      //   638: aload_1
      //   639: getfield 194	o/EN$ˋ:creditLimit	D
      //   642: invokestatic 180	java/lang/Double:compare	(DD)I
      //   645: ifne +6 -> 651
      //   648: goto -349 -> 299
      //   651: goto -501 -> 150
      //   654: bipush 27
      //   656: istore 6
      //   658: goto -143 -> 515
      //   661: aload_1
      //   662: instanceof 2
      //   665: ifeq +6 -> 671
      //   668: goto -229 -> 439
      //   671: goto -524 -> 147
      //   674: aload_0
      //   675: getfield 174	o/EN$ˋ:realised	D
      //   678: aload_1
      //   679: getfield 174	o/EN$ˋ:realised	D
      //   682: invokestatic 180	java/lang/Double:compare	(DD)I
      //   685: ifne +6 -> 691
      //   688: goto -620 -> 68
      //   691: goto -216 -> 475
      //   694: aload_1
      //   695: checkcast 2	o/EN$ˋ
      //   698: astore_1
      //   699: aload_0
      //   700: getfield 196	o/EN$ˋ:minimum	D
      //   703: aload_1
      //   704: getfield 196	o/EN$ˋ:minimum	D
      //   707: invokestatic 180	java/lang/Double:compare	(DD)I
      //   710: ifne +6 -> 716
      //   713: goto -638 -> 75
      //   716: goto -569 -> 147
      //   719: aload_0
      //   720: aload_1
      //   721: if_acmpeq +6 -> 727
      //   724: goto -342 -> 382
      //   727: goto -512 -> 215
      //   730: astore_1
      //   731: aload_1
      //   732: athrow
      //   733: goto -14 -> 719
      // Local variable table:
      //   start	length	slot	name	signature
      //   0	736	0	this	ˋ
      //   0	736	1	paramObject	Object
      //   255	361	2	d1	double
      //   260	357	4	d2	double
      //   5	652	6	i	int
      //   172	192	7	j	int
      // Exception table:
      //   from	to	target	type
      //   604	609	601	java/lang/Exception
      //   609	615	601	java/lang/Exception
      //   615	623	601	java/lang/Exception
      //   251	256	730	java/lang/Exception
      //   256	262	730	java/lang/Exception
    }
    
    public int hashCode()
    {
      break label278;
      int i = ˏ + 53;
      ˋ = i % 128;
      int j;
      if (i % 2 == 0) {
        return j;
      }
      for (;;)
      {
        long l = Double.doubleToLongBits(this.minimum);
        i = (int)(l ^ l >>> 32);
        l = Double.doubleToLongBits(this.realised);
        j = (int)(l ^ l >>> 32);
        l = Double.doubleToLongBits(this.monthly);
        int k = (int)(l ^ l >>> 32);
        l = Double.doubleToLongBits(this.creditLimit);
        int m = (int)(l ^ l >>> 32);
        l = this.dueDate;
        int n = (int)(l ^ l >>> 32);
        l = Double.doubleToLongBits(this.automated);
        int i1 = (int)(l ^ l >>> 32);
        l = Double.doubleToLongBits(this.availableAmount);
        int i2 = (int)(l ^ l >>> 32);
        l = Double.doubleToLongBits(this.points);
        int i3 = (int)(l ^ l >>> 32);
        l = Double.doubleToLongBits(this.blockedAmount);
        int i4 = (int)(l ^ l >>> 32);
        l = Double.doubleToLongBits(this.utilized);
        j = ((((((((i * 31 + j) * 31 + k) * 31 + m) * 31 + n) * 31 + i1) * 31 + i2) * 31 + i3) * 31 + i4) * 31 + (int)(l ^ l >>> 32);
        break;
        return j;
        label278:
        i = ˋ + 105;
        ˏ = i % 128;
        if (i % 2 == 0) {}
      }
    }
    
    public String toString()
    {
      String str = ˏ(0, 35834, 17).intern() + this.minimum + ˏ(17, 65139, 11).intern() + this.realised + ˏ(28, '\000', 10).intern() + this.monthly + ˏ(38, 'ᥰ', 14).intern() + this.creditLimit + ˏ(52, 55182, 10).intern() + this.dueDate + ˏ(62, 42504, 12).intern() + this.automated + ˏ(74, '\000', 18).intern() + this.availableAmount + ˏ(92, '\000', 9).intern() + this.points + ˏ(101, '\000', 16).intern() + this.blockedAmount + ˏ(117, '㹋', 11).intern() + this.utilized + ˏ(128, '\000', 1).intern();
      int i = ˋ + 111;
      ˏ = i % 128;
      if (i % 2 == 0) {
        return str;
      }
      return str;
    }
    
    public final double ˊ()
    {
      break label13;
      double d = this.monthly;
      int i = null.length;
      return d;
      label13:
      i = ˏ + 101;
      ˋ = i % 128;
      if (i % 2 == 0) {
        break label71;
      }
      for (;;)
      {
        switch (i)
        {
        case 28: 
        default: 
          break;
          i = 34;
          break;
        case 34: 
          label71:
          return this.monthly;
          i = 28;
        }
      }
    }
    
    /* Error */
    public final long ˋ()
    {
      // Byte code:
      //   0: goto +58 -> 58
      //   3: getstatic 30	o/EN$ˋ:ˏ	I
      //   6: bipush 23
      //   8: iadd
      //   9: istore_1
      //   10: iload_1
      //   11: sipush 128
      //   14: irem
      //   15: putstatic 28	o/EN$ˋ:ˋ	I
      //   18: iload_1
      //   19: iconst_2
      //   20: irem
      //   21: ifeq +6 -> 27
      //   24: goto +37 -> 61
      //   27: goto +18 -> 45
      //   30: astore 4
      //   32: aload 4
      //   34: athrow
      //   35: astore 4
      //   37: aload 4
      //   39: athrow
      //   40: iconst_0
      //   41: istore_1
      //   42: goto +29 -> 71
      //   45: aload_0
      //   46: getfield 172	o/EN$ˋ:dueDate	J
      //   49: lstore_2
      //   50: goto +48 -> 98
      //   53: iconst_1
      //   54: istore_1
      //   55: goto +16 -> 71
      //   58: goto -55 -> 3
      //   61: goto -16 -> 45
      //   64: aconst_null
      //   65: arraylength
      //   66: istore_1
      //   67: lload_2
      //   68: lreturn
      //   69: lload_2
      //   70: lreturn
      //   71: iload_1
      //   72: tableswitch	default:+24->96, 0:+-8->64, 1:+-3->69
      //   96: lload_2
      //   97: lreturn
      //   98: getstatic 30	o/EN$ˋ:ˏ	I
      //   101: bipush 41
      //   103: iadd
      //   104: istore_1
      //   105: iload_1
      //   106: sipush 128
      //   109: irem
      //   110: putstatic 28	o/EN$ˋ:ˋ	I
      //   113: iload_1
      //   114: iconst_2
      //   115: irem
      //   116: ifeq +6 -> 122
      //   119: goto -79 -> 40
      //   122: goto -69 -> 53
      // Local variable table:
      //   start	length	slot	name	signature
      //   0	125	0	this	ˋ
      //   9	107	1	i	int
      //   49	48	2	l	long
      //   30	3	4	localException1	Exception
      //   35	3	4	localException2	Exception
      // Exception table:
      //   from	to	target	type
      //   98	105	30	java/lang/Exception
      //   105	113	30	java/lang/Exception
      //   105	113	35	java/lang/Exception
    }
    
    public final double ˎ()
    {
      break label11;
      double d = this.creditLimit;
      break label14;
      label11:
      break label81;
      label14:
      int i = ˋ + 19;
      ˏ = i % 128;
      if (i % 2 != 0) {
        return d;
      }
      for (;;)
      {
        switch (i)
        {
        }
        d = this.creditLimit;
        throw new NullPointerException();
        label81:
        i = ˏ + 53;
        ˋ = i % 128;
        if (i % 2 == 0)
        {
          break label110;
          return d;
          label110:
          i = 86;
        }
        else
        {
          i = 94;
        }
      }
    }
    
    public final double ˏ()
    {
      break label13;
      int i = 1;
      break label122;
      label8:
      i = 0;
      break label122;
      label13:
      break label86;
      for (;;)
      {
        switch (i)
        {
        default: 
          break label112;
          label47:
          i = 20;
          continue;
          label53:
          i = 75;
        }
      }
      for (;;)
      {
        i = ˏ + 23;
        ˋ = i % 128;
        if (i % 2 != 0) {
          break label47;
        }
        break label53;
        label86:
        i = ˏ + 5;
        ˋ = i % 128;
        if (i % 2 != 0) {
          break label8;
        }
        break;
        label112:
        throw new NullPointerException();
        Object localObject;
        return localObject;
        label122:
        double d;
        switch (i)
        {
        case 0: 
        default: 
          d = this.realised;
          i = null.length;
          break;
        case 1: 
          d = this.realised;
        }
      }
    }
    
    /* Error */
    public final double ॱ()
    {
      // Byte code:
      //   0: goto +11 -> 11
      //   3: astore 4
      //   5: aload 4
      //   7: athrow
      //   8: goto +6 -> 14
      //   11: goto +11 -> 22
      //   14: aload_0
      //   15: getfield 196	o/EN$ˋ:minimum	D
      //   18: dstore_1
      //   19: goto +30 -> 49
      //   22: getstatic 28	o/EN$ˋ:ˋ	I
      //   25: bipush 23
      //   27: iadd
      //   28: istore_3
      //   29: iload_3
      //   30: sipush 128
      //   33: irem
      //   34: putstatic 30	o/EN$ˋ:ˏ	I
      //   37: iload_3
      //   38: iconst_2
      //   39: irem
      //   40: ifne +6 -> 46
      //   43: goto -35 -> 8
      //   46: goto -32 -> 14
      //   49: getstatic 30	o/EN$ˋ:ˏ	I
      //   52: bipush 17
      //   54: iadd
      //   55: istore_3
      //   56: iload_3
      //   57: sipush 128
      //   60: irem
      //   61: putstatic 28	o/EN$ˋ:ˋ	I
      //   64: iload_3
      //   65: iconst_2
      //   66: irem
      //   67: ifeq +5 -> 72
      //   70: dload_1
      //   71: dreturn
      //   72: dload_1
      //   73: dreturn
      // Local variable table:
      //   start	length	slot	name	signature
      //   0	74	0	this	ˋ
      //   18	55	1	d	double
      //   28	39	3	i	int
      //   3	3	4	localException	Exception
      // Exception table:
      //   from	to	target	type
      //   14	19	3	java/lang/Exception
    }
    
    /* Error */
    public final double ॱॱ()
    {
      // Byte code:
      //   0: goto +13 -> 13
      //   3: astore 4
      //   5: aload 4
      //   7: athrow
      //   8: aconst_null
      //   9: arraylength
      //   10: istore_3
      //   11: dload_1
      //   12: dreturn
      //   13: goto +46 -> 59
      //   16: iload_3
      //   17: lookupswitch	default:+27->44, 9:+-9->8, 60:+96->113
      //   44: goto -36 -> 8
      //   47: bipush 9
      //   49: istore_3
      //   50: goto -34 -> 16
      //   53: bipush 60
      //   55: istore_3
      //   56: goto -40 -> 16
      //   59: getstatic 30	o/EN$ˋ:ˏ	I
      //   62: bipush 101
      //   64: iadd
      //   65: istore_3
      //   66: iload_3
      //   67: sipush 128
      //   70: irem
      //   71: putstatic 28	o/EN$ˋ:ˋ	I
      //   74: iload_3
      //   75: iconst_2
      //   76: irem
      //   77: ifeq +6 -> 83
      //   80: goto +35 -> 115
      //   83: goto +32 -> 115
      //   86: getstatic 30	o/EN$ˋ:ˏ	I
      //   89: bipush 125
      //   91: iadd
      //   92: istore_3
      //   93: iload_3
      //   94: sipush 128
      //   97: irem
      //   98: putstatic 28	o/EN$ˋ:ˋ	I
      //   101: iload_3
      //   102: iconst_2
      //   103: irem
      //   104: ifeq +6 -> 110
      //   107: goto -60 -> 47
      //   110: goto -57 -> 53
      //   113: dload_1
      //   114: dreturn
      //   115: aload_0
      //   116: getfield 186	o/EN$ˋ:automated	D
      //   119: dstore_1
      //   120: goto -34 -> 86
      // Local variable table:
      //   start	length	slot	name	signature
      //   0	123	0	this	ˋ
      //   11	103	1	localObject	Object
      //   119	1	1	d	double
      //   10	94	3	i	int
      //   3	3	4	localException	Exception
      // Exception table:
      //   from	to	target	type
      //   115	120	3	java/lang/Exception
    }
  }
}
