package o;

public enum Er
{
  private static long ˊ;
  private static int ˏ = 0;
  private static int ॱ = 1;
  private String otpScope;
  
  /* Error */
  static
  {
    // Byte code:
    //   0: iconst_0
    //   1: putstatic 25	o/Er:ˏ	I
    //   4: iconst_1
    //   5: putstatic 27	o/Er:ॱ	I
    //   8: goto +6 -> 14
    //   11: astore_1
    //   12: aload_1
    //   13: athrow
    //   14: invokestatic 29	o/Er:ˏ	()V
    //   17: new 2	o/Er
    //   20: dup
    //   21: bipush 17
    //   23: newarray char
    //   25: dup
    //   26: iconst_0
    //   27: ldc 30
    //   29: castore
    //   30: dup
    //   31: iconst_1
    //   32: ldc 31
    //   34: castore
    //   35: dup
    //   36: iconst_2
    //   37: ldc 32
    //   39: castore
    //   40: dup
    //   41: iconst_3
    //   42: ldc 33
    //   44: castore
    //   45: dup
    //   46: iconst_4
    //   47: ldc 34
    //   49: castore
    //   50: dup
    //   51: iconst_5
    //   52: ldc 35
    //   54: castore
    //   55: dup
    //   56: bipush 6
    //   58: ldc 36
    //   60: castore
    //   61: dup
    //   62: bipush 7
    //   64: ldc 37
    //   66: castore
    //   67: dup
    //   68: bipush 8
    //   70: ldc 38
    //   72: castore
    //   73: dup
    //   74: bipush 9
    //   76: ldc 39
    //   78: castore
    //   79: dup
    //   80: bipush 10
    //   82: ldc 40
    //   84: castore
    //   85: dup
    //   86: bipush 11
    //   88: ldc 41
    //   90: castore
    //   91: dup
    //   92: bipush 12
    //   94: ldc 42
    //   96: castore
    //   97: dup
    //   98: bipush 13
    //   100: ldc 43
    //   102: castore
    //   103: dup
    //   104: bipush 14
    //   106: ldc 44
    //   108: castore
    //   109: dup
    //   110: bipush 15
    //   112: ldc 45
    //   114: castore
    //   115: dup
    //   116: bipush 16
    //   118: ldc 46
    //   120: castore
    //   121: invokestatic 49	o/Er:ˏ	([C)Ljava/lang/String;
    //   124: invokevirtual 55	java/lang/String:intern	()Ljava/lang/String;
    //   127: iconst_0
    //   128: bipush 17
    //   130: newarray char
    //   132: dup
    //   133: iconst_0
    //   134: ldc 30
    //   136: castore
    //   137: dup
    //   138: iconst_1
    //   139: ldc 31
    //   141: castore
    //   142: dup
    //   143: iconst_2
    //   144: ldc 32
    //   146: castore
    //   147: dup
    //   148: iconst_3
    //   149: ldc 33
    //   151: castore
    //   152: dup
    //   153: iconst_4
    //   154: ldc 34
    //   156: castore
    //   157: dup
    //   158: iconst_5
    //   159: ldc 35
    //   161: castore
    //   162: dup
    //   163: bipush 6
    //   165: ldc 36
    //   167: castore
    //   168: dup
    //   169: bipush 7
    //   171: ldc 37
    //   173: castore
    //   174: dup
    //   175: bipush 8
    //   177: ldc 38
    //   179: castore
    //   180: dup
    //   181: bipush 9
    //   183: ldc 39
    //   185: castore
    //   186: dup
    //   187: bipush 10
    //   189: ldc 40
    //   191: castore
    //   192: dup
    //   193: bipush 11
    //   195: ldc 41
    //   197: castore
    //   198: dup
    //   199: bipush 12
    //   201: ldc 42
    //   203: castore
    //   204: dup
    //   205: bipush 13
    //   207: ldc 43
    //   209: castore
    //   210: dup
    //   211: bipush 14
    //   213: ldc 44
    //   215: castore
    //   216: dup
    //   217: bipush 15
    //   219: ldc 45
    //   221: castore
    //   222: dup
    //   223: bipush 16
    //   225: ldc 46
    //   227: castore
    //   228: invokestatic 49	o/Er:ˏ	([C)Ljava/lang/String;
    //   231: invokevirtual 55	java/lang/String:intern	()Ljava/lang/String;
    //   234: invokespecial 59	o/Er:<init>	(Ljava/lang/String;ILjava/lang/String;)V
    //   237: astore_1
    //   238: aload_1
    //   239: putstatic 61	o/Er:PHONE_VALIDATION	Lo/Er;
    //   242: new 2	o/Er
    //   245: dup
    //   246: bipush 17
    //   248: newarray char
    //   250: dup
    //   251: iconst_0
    //   252: ldc 62
    //   254: castore
    //   255: dup
    //   256: iconst_1
    //   257: ldc 63
    //   259: castore
    //   260: dup
    //   261: iconst_2
    //   262: ldc 64
    //   264: castore
    //   265: dup
    //   266: iconst_3
    //   267: ldc 65
    //   269: castore
    //   270: dup
    //   271: iconst_4
    //   272: ldc 66
    //   274: castore
    //   275: dup
    //   276: iconst_5
    //   277: ldc 67
    //   279: castore
    //   280: dup
    //   281: bipush 6
    //   283: ldc 68
    //   285: castore
    //   286: dup
    //   287: bipush 7
    //   289: ldc 69
    //   291: castore
    //   292: dup
    //   293: bipush 8
    //   295: ldc 70
    //   297: castore
    //   298: dup
    //   299: bipush 9
    //   301: ldc 71
    //   303: castore
    //   304: dup
    //   305: bipush 10
    //   307: ldc 72
    //   309: castore
    //   310: dup
    //   311: bipush 11
    //   313: ldc 73
    //   315: castore
    //   316: dup
    //   317: bipush 12
    //   319: ldc 74
    //   321: castore
    //   322: dup
    //   323: bipush 13
    //   325: ldc 75
    //   327: castore
    //   328: dup
    //   329: bipush 14
    //   331: ldc 76
    //   333: castore
    //   334: dup
    //   335: bipush 15
    //   337: ldc 77
    //   339: castore
    //   340: dup
    //   341: bipush 16
    //   343: ldc 78
    //   345: castore
    //   346: invokestatic 49	o/Er:ˏ	([C)Ljava/lang/String;
    //   349: invokevirtual 55	java/lang/String:intern	()Ljava/lang/String;
    //   352: iconst_1
    //   353: bipush 17
    //   355: newarray char
    //   357: dup
    //   358: iconst_0
    //   359: ldc 62
    //   361: castore
    //   362: dup
    //   363: iconst_1
    //   364: ldc 63
    //   366: castore
    //   367: dup
    //   368: iconst_2
    //   369: ldc 64
    //   371: castore
    //   372: dup
    //   373: iconst_3
    //   374: ldc 65
    //   376: castore
    //   377: dup
    //   378: iconst_4
    //   379: ldc 66
    //   381: castore
    //   382: dup
    //   383: iconst_5
    //   384: ldc 67
    //   386: castore
    //   387: dup
    //   388: bipush 6
    //   390: ldc 68
    //   392: castore
    //   393: dup
    //   394: bipush 7
    //   396: ldc 69
    //   398: castore
    //   399: dup
    //   400: bipush 8
    //   402: ldc 70
    //   404: castore
    //   405: dup
    //   406: bipush 9
    //   408: ldc 71
    //   410: castore
    //   411: dup
    //   412: bipush 10
    //   414: ldc 72
    //   416: castore
    //   417: dup
    //   418: bipush 11
    //   420: ldc 73
    //   422: castore
    //   423: dup
    //   424: bipush 12
    //   426: ldc 74
    //   428: castore
    //   429: dup
    //   430: bipush 13
    //   432: ldc 75
    //   434: castore
    //   435: dup
    //   436: bipush 14
    //   438: ldc 76
    //   440: castore
    //   441: dup
    //   442: bipush 15
    //   444: ldc 77
    //   446: castore
    //   447: dup
    //   448: bipush 16
    //   450: ldc 78
    //   452: castore
    //   453: invokestatic 49	o/Er:ˏ	([C)Ljava/lang/String;
    //   456: invokevirtual 55	java/lang/String:intern	()Ljava/lang/String;
    //   459: invokespecial 59	o/Er:<init>	(Ljava/lang/String;ILjava/lang/String;)V
    //   462: astore_2
    //   463: aload_2
    //   464: putstatic 80	o/Er:RESURRECT_WALLET	Lo/Er;
    //   467: new 2	o/Er
    //   470: dup
    //   471: bipush 35
    //   473: newarray char
    //   475: dup
    //   476: iconst_0
    //   477: ldc 81
    //   479: castore
    //   480: dup
    //   481: iconst_1
    //   482: ldc 82
    //   484: castore
    //   485: dup
    //   486: iconst_2
    //   487: ldc 83
    //   489: castore
    //   490: dup
    //   491: iconst_3
    //   492: ldc 84
    //   494: castore
    //   495: dup
    //   496: iconst_4
    //   497: ldc 85
    //   499: castore
    //   500: dup
    //   501: iconst_5
    //   502: ldc 86
    //   504: castore
    //   505: dup
    //   506: bipush 6
    //   508: ldc 87
    //   510: castore
    //   511: dup
    //   512: bipush 7
    //   514: ldc 88
    //   516: castore
    //   517: dup
    //   518: bipush 8
    //   520: ldc 89
    //   522: castore
    //   523: dup
    //   524: bipush 9
    //   526: ldc 90
    //   528: castore
    //   529: dup
    //   530: bipush 10
    //   532: ldc 91
    //   534: castore
    //   535: dup
    //   536: bipush 11
    //   538: ldc 92
    //   540: castore
    //   541: dup
    //   542: bipush 12
    //   544: ldc 93
    //   546: castore
    //   547: dup
    //   548: bipush 13
    //   550: ldc 94
    //   552: castore
    //   553: dup
    //   554: bipush 14
    //   556: ldc 95
    //   558: castore
    //   559: dup
    //   560: bipush 15
    //   562: ldc 96
    //   564: castore
    //   565: dup
    //   566: bipush 16
    //   568: ldc 97
    //   570: castore
    //   571: dup
    //   572: bipush 17
    //   574: ldc 98
    //   576: castore
    //   577: dup
    //   578: bipush 18
    //   580: ldc 99
    //   582: castore
    //   583: dup
    //   584: bipush 19
    //   586: ldc 100
    //   588: castore
    //   589: dup
    //   590: bipush 20
    //   592: ldc 101
    //   594: castore
    //   595: dup
    //   596: bipush 21
    //   598: ldc 102
    //   600: castore
    //   601: dup
    //   602: bipush 22
    //   604: ldc 103
    //   606: castore
    //   607: dup
    //   608: bipush 23
    //   610: ldc 104
    //   612: castore
    //   613: dup
    //   614: bipush 24
    //   616: ldc 105
    //   618: castore
    //   619: dup
    //   620: bipush 25
    //   622: ldc 106
    //   624: castore
    //   625: dup
    //   626: bipush 26
    //   628: ldc 107
    //   630: castore
    //   631: dup
    //   632: bipush 27
    //   634: ldc 108
    //   636: castore
    //   637: dup
    //   638: bipush 28
    //   640: ldc 109
    //   642: castore
    //   643: dup
    //   644: bipush 29
    //   646: ldc 110
    //   648: castore
    //   649: dup
    //   650: bipush 30
    //   652: ldc 111
    //   654: castore
    //   655: dup
    //   656: bipush 31
    //   658: ldc 112
    //   660: castore
    //   661: dup
    //   662: bipush 32
    //   664: ldc 113
    //   666: castore
    //   667: dup
    //   668: bipush 33
    //   670: ldc 114
    //   672: castore
    //   673: dup
    //   674: bipush 34
    //   676: ldc 115
    //   678: castore
    //   679: invokestatic 49	o/Er:ˏ	([C)Ljava/lang/String;
    //   682: invokevirtual 55	java/lang/String:intern	()Ljava/lang/String;
    //   685: iconst_2
    //   686: bipush 35
    //   688: newarray char
    //   690: dup
    //   691: iconst_0
    //   692: ldc 81
    //   694: castore
    //   695: dup
    //   696: iconst_1
    //   697: ldc 82
    //   699: castore
    //   700: dup
    //   701: iconst_2
    //   702: ldc 83
    //   704: castore
    //   705: dup
    //   706: iconst_3
    //   707: ldc 84
    //   709: castore
    //   710: dup
    //   711: iconst_4
    //   712: ldc 85
    //   714: castore
    //   715: dup
    //   716: iconst_5
    //   717: ldc 86
    //   719: castore
    //   720: dup
    //   721: bipush 6
    //   723: ldc 87
    //   725: castore
    //   726: dup
    //   727: bipush 7
    //   729: ldc 88
    //   731: castore
    //   732: dup
    //   733: bipush 8
    //   735: ldc 89
    //   737: castore
    //   738: dup
    //   739: bipush 9
    //   741: ldc 90
    //   743: castore
    //   744: dup
    //   745: bipush 10
    //   747: ldc 91
    //   749: castore
    //   750: dup
    //   751: bipush 11
    //   753: ldc 92
    //   755: castore
    //   756: dup
    //   757: bipush 12
    //   759: ldc 93
    //   761: castore
    //   762: dup
    //   763: bipush 13
    //   765: ldc 94
    //   767: castore
    //   768: dup
    //   769: bipush 14
    //   771: ldc 95
    //   773: castore
    //   774: dup
    //   775: bipush 15
    //   777: ldc 96
    //   779: castore
    //   780: dup
    //   781: bipush 16
    //   783: ldc 97
    //   785: castore
    //   786: dup
    //   787: bipush 17
    //   789: ldc 98
    //   791: castore
    //   792: dup
    //   793: bipush 18
    //   795: ldc 99
    //   797: castore
    //   798: dup
    //   799: bipush 19
    //   801: ldc 100
    //   803: castore
    //   804: dup
    //   805: bipush 20
    //   807: ldc 101
    //   809: castore
    //   810: dup
    //   811: bipush 21
    //   813: ldc 102
    //   815: castore
    //   816: dup
    //   817: bipush 22
    //   819: ldc 103
    //   821: castore
    //   822: dup
    //   823: bipush 23
    //   825: ldc 104
    //   827: castore
    //   828: dup
    //   829: bipush 24
    //   831: ldc 105
    //   833: castore
    //   834: dup
    //   835: bipush 25
    //   837: ldc 106
    //   839: castore
    //   840: dup
    //   841: bipush 26
    //   843: ldc 107
    //   845: castore
    //   846: dup
    //   847: bipush 27
    //   849: ldc 108
    //   851: castore
    //   852: dup
    //   853: bipush 28
    //   855: ldc 109
    //   857: castore
    //   858: dup
    //   859: bipush 29
    //   861: ldc 110
    //   863: castore
    //   864: dup
    //   865: bipush 30
    //   867: ldc 111
    //   869: castore
    //   870: dup
    //   871: bipush 31
    //   873: ldc 112
    //   875: castore
    //   876: dup
    //   877: bipush 32
    //   879: ldc 113
    //   881: castore
    //   882: dup
    //   883: bipush 33
    //   885: ldc 114
    //   887: castore
    //   888: dup
    //   889: bipush 34
    //   891: ldc 115
    //   893: castore
    //   894: invokestatic 49	o/Er:ˏ	([C)Ljava/lang/String;
    //   897: invokevirtual 55	java/lang/String:intern	()Ljava/lang/String;
    //   900: invokespecial 59	o/Er:<init>	(Ljava/lang/String;ILjava/lang/String;)V
    //   903: astore_3
    //   904: aload_3
    //   905: putstatic 117	o/Er:CARD_REGISTRATION_FROM_PRESENTMENT	Lo/Er;
    //   908: new 2	o/Er
    //   911: dup
    //   912: bipush 39
    //   914: newarray char
    //   916: dup
    //   917: iconst_0
    //   918: ldc 118
    //   920: castore
    //   921: dup
    //   922: iconst_1
    //   923: ldc 119
    //   925: castore
    //   926: dup
    //   927: iconst_2
    //   928: ldc 120
    //   930: castore
    //   931: dup
    //   932: iconst_3
    //   933: ldc 121
    //   935: castore
    //   936: dup
    //   937: iconst_4
    //   938: ldc 122
    //   940: castore
    //   941: dup
    //   942: iconst_5
    //   943: ldc 123
    //   945: castore
    //   946: dup
    //   947: bipush 6
    //   949: ldc 124
    //   951: castore
    //   952: dup
    //   953: bipush 7
    //   955: ldc 125
    //   957: castore
    //   958: dup
    //   959: bipush 8
    //   961: ldc 126
    //   963: castore
    //   964: dup
    //   965: bipush 9
    //   967: ldc 127
    //   969: castore
    //   970: dup
    //   971: bipush 10
    //   973: ldc -128
    //   975: castore
    //   976: dup
    //   977: bipush 11
    //   979: ldc -127
    //   981: castore
    //   982: dup
    //   983: bipush 12
    //   985: ldc -126
    //   987: castore
    //   988: dup
    //   989: bipush 13
    //   991: ldc -125
    //   993: castore
    //   994: dup
    //   995: bipush 14
    //   997: ldc -124
    //   999: castore
    //   1000: dup
    //   1001: bipush 15
    //   1003: ldc -123
    //   1005: castore
    //   1006: dup
    //   1007: bipush 16
    //   1009: ldc -122
    //   1011: castore
    //   1012: dup
    //   1013: bipush 17
    //   1015: ldc -121
    //   1017: castore
    //   1018: dup
    //   1019: bipush 18
    //   1021: ldc -120
    //   1023: castore
    //   1024: dup
    //   1025: bipush 19
    //   1027: ldc -119
    //   1029: castore
    //   1030: dup
    //   1031: bipush 20
    //   1033: ldc -118
    //   1035: castore
    //   1036: dup
    //   1037: bipush 21
    //   1039: ldc -117
    //   1041: castore
    //   1042: dup
    //   1043: bipush 22
    //   1045: ldc -116
    //   1047: castore
    //   1048: dup
    //   1049: bipush 23
    //   1051: ldc -115
    //   1053: castore
    //   1054: dup
    //   1055: bipush 24
    //   1057: ldc -114
    //   1059: castore
    //   1060: dup
    //   1061: bipush 25
    //   1063: ldc -113
    //   1065: castore
    //   1066: dup
    //   1067: bipush 26
    //   1069: ldc -112
    //   1071: castore
    //   1072: dup
    //   1073: bipush 27
    //   1075: ldc -111
    //   1077: castore
    //   1078: dup
    //   1079: bipush 28
    //   1081: ldc -110
    //   1083: castore
    //   1084: dup
    //   1085: bipush 29
    //   1087: ldc -109
    //   1089: castore
    //   1090: dup
    //   1091: bipush 30
    //   1093: ldc -108
    //   1095: castore
    //   1096: dup
    //   1097: bipush 31
    //   1099: ldc -107
    //   1101: castore
    //   1102: dup
    //   1103: bipush 32
    //   1105: ldc -106
    //   1107: castore
    //   1108: dup
    //   1109: bipush 33
    //   1111: ldc -105
    //   1113: castore
    //   1114: dup
    //   1115: bipush 34
    //   1117: ldc -104
    //   1119: castore
    //   1120: dup
    //   1121: bipush 35
    //   1123: ldc -103
    //   1125: castore
    //   1126: dup
    //   1127: bipush 36
    //   1129: ldc -102
    //   1131: castore
    //   1132: dup
    //   1133: bipush 37
    //   1135: ldc -101
    //   1137: castore
    //   1138: dup
    //   1139: bipush 38
    //   1141: ldc -100
    //   1143: castore
    //   1144: invokestatic 49	o/Er:ˏ	([C)Ljava/lang/String;
    //   1147: invokevirtual 55	java/lang/String:intern	()Ljava/lang/String;
    //   1150: iconst_3
    //   1151: bipush 39
    //   1153: newarray char
    //   1155: dup
    //   1156: iconst_0
    //   1157: ldc 118
    //   1159: castore
    //   1160: dup
    //   1161: iconst_1
    //   1162: ldc 119
    //   1164: castore
    //   1165: dup
    //   1166: iconst_2
    //   1167: ldc 120
    //   1169: castore
    //   1170: dup
    //   1171: iconst_3
    //   1172: ldc 121
    //   1174: castore
    //   1175: dup
    //   1176: iconst_4
    //   1177: ldc 122
    //   1179: castore
    //   1180: dup
    //   1181: iconst_5
    //   1182: ldc 123
    //   1184: castore
    //   1185: dup
    //   1186: bipush 6
    //   1188: ldc 124
    //   1190: castore
    //   1191: dup
    //   1192: bipush 7
    //   1194: ldc 125
    //   1196: castore
    //   1197: dup
    //   1198: bipush 8
    //   1200: ldc 126
    //   1202: castore
    //   1203: dup
    //   1204: bipush 9
    //   1206: ldc 127
    //   1208: castore
    //   1209: dup
    //   1210: bipush 10
    //   1212: ldc -128
    //   1214: castore
    //   1215: dup
    //   1216: bipush 11
    //   1218: ldc -127
    //   1220: castore
    //   1221: dup
    //   1222: bipush 12
    //   1224: ldc -126
    //   1226: castore
    //   1227: dup
    //   1228: bipush 13
    //   1230: ldc -125
    //   1232: castore
    //   1233: dup
    //   1234: bipush 14
    //   1236: ldc -124
    //   1238: castore
    //   1239: dup
    //   1240: bipush 15
    //   1242: ldc -123
    //   1244: castore
    //   1245: dup
    //   1246: bipush 16
    //   1248: ldc -122
    //   1250: castore
    //   1251: dup
    //   1252: bipush 17
    //   1254: ldc -121
    //   1256: castore
    //   1257: dup
    //   1258: bipush 18
    //   1260: ldc -120
    //   1262: castore
    //   1263: dup
    //   1264: bipush 19
    //   1266: ldc -119
    //   1268: castore
    //   1269: dup
    //   1270: bipush 20
    //   1272: ldc -118
    //   1274: castore
    //   1275: dup
    //   1276: bipush 21
    //   1278: ldc -117
    //   1280: castore
    //   1281: dup
    //   1282: bipush 22
    //   1284: ldc -116
    //   1286: castore
    //   1287: dup
    //   1288: bipush 23
    //   1290: ldc -115
    //   1292: castore
    //   1293: dup
    //   1294: bipush 24
    //   1296: ldc -114
    //   1298: castore
    //   1299: dup
    //   1300: bipush 25
    //   1302: ldc -113
    //   1304: castore
    //   1305: dup
    //   1306: bipush 26
    //   1308: ldc -112
    //   1310: castore
    //   1311: dup
    //   1312: bipush 27
    //   1314: ldc -111
    //   1316: castore
    //   1317: dup
    //   1318: bipush 28
    //   1320: ldc -110
    //   1322: castore
    //   1323: dup
    //   1324: bipush 29
    //   1326: ldc -109
    //   1328: castore
    //   1329: dup
    //   1330: bipush 30
    //   1332: ldc -108
    //   1334: castore
    //   1335: dup
    //   1336: bipush 31
    //   1338: ldc -107
    //   1340: castore
    //   1341: dup
    //   1342: bipush 32
    //   1344: ldc -106
    //   1346: castore
    //   1347: dup
    //   1348: bipush 33
    //   1350: ldc -105
    //   1352: castore
    //   1353: dup
    //   1354: bipush 34
    //   1356: ldc -104
    //   1358: castore
    //   1359: dup
    //   1360: bipush 35
    //   1362: ldc -103
    //   1364: castore
    //   1365: dup
    //   1366: bipush 36
    //   1368: ldc -102
    //   1370: castore
    //   1371: dup
    //   1372: bipush 37
    //   1374: ldc -101
    //   1376: castore
    //   1377: dup
    //   1378: bipush 38
    //   1380: ldc -100
    //   1382: castore
    //   1383: invokestatic 49	o/Er:ˏ	([C)Ljava/lang/String;
    //   1386: invokevirtual 55	java/lang/String:intern	()Ljava/lang/String;
    //   1389: invokespecial 59	o/Er:<init>	(Ljava/lang/String;ILjava/lang/String;)V
    //   1392: astore 4
    //   1394: aload 4
    //   1396: putstatic 158	o/Er:CARD_REGISTRATION_NOT_FROM_PRESENTMENT	Lo/Er;
    //   1399: iconst_4
    //   1400: anewarray 2	o/Er
    //   1403: dup
    //   1404: iconst_0
    //   1405: aload_1
    //   1406: aastore
    //   1407: dup
    //   1408: iconst_1
    //   1409: aload_2
    //   1410: aastore
    //   1411: dup
    //   1412: iconst_2
    //   1413: aload_3
    //   1414: aastore
    //   1415: dup
    //   1416: iconst_3
    //   1417: aload 4
    //   1419: aastore
    //   1420: putstatic 160	o/Er:$VALUES	[Lo/Er;
    //   1423: goto +6 -> 1429
    //   1426: astore_1
    //   1427: aload_1
    //   1428: athrow
    //   1429: getstatic 25	o/Er:ˏ	I
    //   1432: istore_0
    //   1433: iload_0
    //   1434: bipush 83
    //   1436: iadd
    //   1437: istore_0
    //   1438: iload_0
    //   1439: sipush 128
    //   1442: irem
    //   1443: putstatic 27	o/Er:ॱ	I
    //   1446: iload_0
    //   1447: iconst_2
    //   1448: irem
    //   1449: ifne +4 -> 1453
    //   1452: return
    //   1453: return
    // Local variable table:
    //   start	length	slot	name	signature
    //   1432	17	0	i	int
    //   11	2	1	localException1	Exception
    //   237	1169	1	localEr1	Er
    //   1426	2	1	localException2	Exception
    //   462	948	2	localEr2	Er
    //   903	511	3	localEr3	Er
    //   1392	26	4	localEr4	Er
    // Exception table:
    //   from	to	target	type
    //   1438	1446	11	java/lang/Exception
    //   1429	1433	1426	java/lang/Exception
  }
  
  /* Error */
  protected Er(String paramString)
  {
    // Byte code:
    //   0: goto +6 -> 6
    //   3: astore_1
    //   4: aload_1
    //   5: athrow
    //   6: bipush 9
    //   8: newarray char
    //   10: dup
    //   11: iconst_0
    //   12: ldc -94
    //   14: castore
    //   15: dup
    //   16: iconst_1
    //   17: ldc -93
    //   19: castore
    //   20: dup
    //   21: iconst_2
    //   22: ldc -92
    //   24: castore
    //   25: dup
    //   26: iconst_3
    //   27: ldc -91
    //   29: castore
    //   30: dup
    //   31: iconst_4
    //   32: ldc -90
    //   34: castore
    //   35: dup
    //   36: iconst_5
    //   37: ldc -89
    //   39: castore
    //   40: dup
    //   41: bipush 6
    //   43: ldc -88
    //   45: castore
    //   46: dup
    //   47: bipush 7
    //   49: ldc -87
    //   51: castore
    //   52: dup
    //   53: bipush 8
    //   55: ldc -86
    //   57: castore
    //   58: invokestatic 49	o/Er:ˏ	([C)Ljava/lang/String;
    //   61: astore 4
    //   63: aload 4
    //   65: invokevirtual 55	java/lang/String:intern	()Ljava/lang/String;
    //   68: astore 4
    //   70: aload_3
    //   71: aload 4
    //   73: invokestatic 176	o/vq:ˎ	(Ljava/lang/Object;Ljava/lang/String;)V
    //   76: aload_0
    //   77: aload_1
    //   78: iload_2
    //   79: invokespecial 179	java/lang/Enum:<init>	(Ljava/lang/String;I)V
    //   82: aload_0
    //   83: aload_3
    //   84: putfield 181	o/Er:otpScope	Ljava/lang/String;
    //   87: return
    //   88: astore_1
    //   89: aload_1
    //   90: athrow
    // Local variable table:
    //   start	length	slot	name	signature
    //   0	91	0	this	Er
    //   3	75	1	???	Exception
    //   88	2	1	localException	Exception
    //   78	1	2	i	int
    //   0	91	3	paramString	String
    //   61	11	4	str1	String
    // Exception table:
    //   from	to	target	type
    //   63	70	3	java/lang/Exception
    //   6	63	88	java/lang/Exception
    //   63	70	88	java/lang/Exception
    //   70	76	88	java/lang/Exception
    //   76	82	88	java/lang/Exception
    //   82	87	88	java/lang/Exception
  }
  
  private static String ˏ(char[] paramArrayOfChar)
  {
    break label128;
    int i;
    for (;;)
    {
      j = 43;
      break label131;
      i = ˏ + 51;
      ॱ = i % 128;
      if (i % 2 == 0) {
        break label92;
      }
      break;
      label36:
      if (i < paramArrayOfChar.length) {
        break label95;
      }
    }
    label48:
    int j = ॱ + 47;
    ˏ = j % 128;
    int k;
    char[] arrayOfChar;
    if (j % 2 == 0)
    {
      break label101;
      label92:
      for (;;)
      {
        k = paramArrayOfChar[0];
        arrayOfChar = new char[paramArrayOfChar.length - 1];
        i = 1;
        break;
      }
      label95:
      j = 90;
    }
    for (;;)
    {
      label101:
      arrayOfChar[(i - 1)] = ((char)(int)(paramArrayOfChar[i] ^ i * k ^ ˊ));
      i += 1;
      break label36;
      label128:
      break;
      switch (j)
      {
      case 90: 
      default: 
        label131:
        break label48;
      }
    }
    return new String(arrayOfChar);
  }
  
  static void ˏ()
  {
    ˊ = -3910913812534550177L;
  }
}
