package o;

import android.os.Parcel;
import android.os.Parcelable;
import android.os.Parcelable.Creator;
import java.util.ArrayList;
import java.util.Date;
import java.util.List;

public class Eu
  implements Parcelable
{
  public static final Parcelable.Creator<Eu> CREATOR;
  private static final String EXPIRATION_DATE_FORMAT = "MM/yy";
  public static final String EXTRA_CARD_CVV = "extra_card_cvv";
  public static final String EXTRA_CARD_INSTANCE_UUID = "extra_card_instance_uuid";
  public static final String EXTRA_PAYMENT_CARD = "extra_payment_card";
  private static final int MASKED_DISPLAY_DIGITS = 4;
  private static int ʻ = 0;
  private static boolean ˊ = false;
  private static boolean ˋ = false;
  private static char[] ˎ;
  private static int ˏ = 0;
  private static int ॱ = 0;
  public String cardIdentifier;
  public String cardName;
  @nQ
  @nT(ˋ="last4digits")
  public String cardNumber;
  @nQ
  @nT(ˋ="scheme")
  public Eh cardScheme;
  @nQ
  @nT(ˋ="cardStatus")
  public El cardStatus;
  @nQ
  @nT(ˋ="cardType")
  public Ei cardType;
  @nQ
  @nT(ˋ="cardholderName")
  public String cardholderName;
  @nQ
  @nT(ˋ="clientName")
  public String clientName;
  @nQ
  @nT(ˋ="currency")
  public Ep currency;
  public String customerCategory;
  @nQ
  @nT(ˋ="expirationDate")
  private long expirationDate;
  public String instanceUUID;
  private boolean isContactless;
  private boolean isEnrolled;
  public List<String> listOfOperationsAllowed = new ArrayList();
  @nQ
  @nT(ˋ="productName")
  public EA productName;
  @nQ
  @nT(ˋ="uuid")
  public String uuid;
  
  static
  {
    for (;;)
    {
      int i = ʻ + 61;
      ॱ = i % 128;
      if (i % 2 == 0) {
        return;
      }
      return;
      ॱ = 0;
      ʻ = 1;
      ˏॱ();
      CREATOR = new Parcelable.Creator()
      {
        public Eu[] ˊ(int paramAnonymousInt)
        {
          return new Eu[paramAnonymousInt];
        }
        
        public Eu ˎ(Parcel paramAnonymousParcel)
        {
          return new Eu(paramAnonymousParcel);
        }
      };
    }
  }
  
  public Eu() {}
  
  /* Error */
  public Eu(Parcel paramParcel)
  {
    // Byte code:
    //   0: goto +8 -> 8
    //   3: iconst_0
    //   4: istore_2
    //   5: goto +280 -> 285
    //   8: aload_0
    //   9: invokespecial 81	java/lang/Object:<init>	()V
    //   12: new 83	java/util/ArrayList
    //   15: dup
    //   16: invokespecial 84	java/util/ArrayList:<init>	()V
    //   19: astore 4
    //   21: aload_0
    //   22: aload 4
    //   24: putfield 86	o/Eu:listOfOperationsAllowed	Ljava/util/List;
    //   27: aload_1
    //   28: invokevirtual 95	android/os/Parcel:readString	()Ljava/lang/String;
    //   31: astore 4
    //   33: aload_0
    //   34: aload 4
    //   36: putfield 97	o/Eu:uuid	Ljava/lang/String;
    //   39: aload_0
    //   40: aload_1
    //   41: invokevirtual 95	android/os/Parcel:readString	()Ljava/lang/String;
    //   44: putfield 99	o/Eu:instanceUUID	Ljava/lang/String;
    //   47: aload_0
    //   48: aload_1
    //   49: invokevirtual 95	android/os/Parcel:readString	()Ljava/lang/String;
    //   52: putfield 101	o/Eu:cardIdentifier	Ljava/lang/String;
    //   55: aload_0
    //   56: aload_1
    //   57: invokevirtual 95	android/os/Parcel:readString	()Ljava/lang/String;
    //   60: putfield 103	o/Eu:cardName	Ljava/lang/String;
    //   63: aload_0
    //   64: aload_1
    //   65: invokevirtual 107	android/os/Parcel:readLong	()J
    //   68: putfield 109	o/Eu:expirationDate	J
    //   71: aload_0
    //   72: aload_1
    //   73: invokevirtual 95	android/os/Parcel:readString	()Ljava/lang/String;
    //   76: putfield 111	o/Eu:cardholderName	Ljava/lang/String;
    //   79: aload_0
    //   80: aload_1
    //   81: invokevirtual 95	android/os/Parcel:readString	()Ljava/lang/String;
    //   84: putfield 113	o/Eu:clientName	Ljava/lang/String;
    //   87: aload_0
    //   88: aload_1
    //   89: ldc 115
    //   91: invokevirtual 121	java/lang/Class:getClassLoader	()Ljava/lang/ClassLoader;
    //   94: invokevirtual 125	android/os/Parcel:readParcelable	(Ljava/lang/ClassLoader;)Landroid/os/Parcelable;
    //   97: checkcast 115	o/EA
    //   100: putfield 127	o/Eu:productName	Lo/EA;
    //   103: aload_0
    //   104: aload_1
    //   105: invokevirtual 95	android/os/Parcel:readString	()Ljava/lang/String;
    //   108: putfield 129	o/Eu:cardNumber	Ljava/lang/String;
    //   111: aload_0
    //   112: aload_1
    //   113: invokevirtual 95	android/os/Parcel:readString	()Ljava/lang/String;
    //   116: invokestatic 135	o/Ep:valueOf	(Ljava/lang/String;)Lo/Ep;
    //   119: putfield 137	o/Eu:currency	Lo/Ep;
    //   122: aload_0
    //   123: aload_1
    //   124: invokevirtual 95	android/os/Parcel:readString	()Ljava/lang/String;
    //   127: invokestatic 142	o/El:valueOf	(Ljava/lang/String;)Lo/El;
    //   130: putfield 144	o/Eu:cardStatus	Lo/El;
    //   133: aload_0
    //   134: aload_1
    //   135: invokevirtual 95	android/os/Parcel:readString	()Ljava/lang/String;
    //   138: invokestatic 149	o/Eh:valueOf	(Ljava/lang/String;)Lo/Eh;
    //   141: putfield 151	o/Eu:cardScheme	Lo/Eh;
    //   144: aload_0
    //   145: aload_1
    //   146: invokevirtual 95	android/os/Parcel:readString	()Ljava/lang/String;
    //   149: invokestatic 156	o/Ei:valueOf	(Ljava/lang/String;)Lo/Ei;
    //   152: putfield 158	o/Eu:cardType	Lo/Ei;
    //   155: aload_1
    //   156: invokevirtual 162	android/os/Parcel:readByte	()B
    //   159: istore_2
    //   160: iload_2
    //   161: ifeq +6 -> 167
    //   164: goto +161 -> 325
    //   167: goto +73 -> 240
    //   170: getstatic 69	o/Eu:ʻ	I
    //   173: istore_2
    //   174: iload_2
    //   175: bipush 75
    //   177: iadd
    //   178: istore_2
    //   179: iload_2
    //   180: sipush 128
    //   183: irem
    //   184: putstatic 71	o/Eu:ॱ	I
    //   187: iload_2
    //   188: iconst_2
    //   189: irem
    //   190: ifeq +6 -> 196
    //   193: goto +87 -> 280
    //   196: goto +52 -> 248
    //   199: iconst_1
    //   200: istore_3
    //   201: goto +52 -> 253
    //   204: return
    //   205: iload_2
    //   206: tableswitch	default:+22->228, 0:+115->321, 1:+-2->204
    //   228: return
    //   229: goto +98 -> 327
    //   232: iconst_0
    //   233: istore_2
    //   234: goto +149 -> 383
    //   237: goto +174 -> 411
    //   240: iconst_0
    //   241: istore_3
    //   242: goto +103 -> 345
    //   245: astore_1
    //   246: aload_1
    //   247: athrow
    //   248: iconst_1
    //   249: istore_2
    //   250: goto -45 -> 205
    //   253: getstatic 69	o/Eu:ʻ	I
    //   256: bipush 111
    //   258: iadd
    //   259: istore_2
    //   260: iload_2
    //   261: sipush 128
    //   264: irem
    //   265: putstatic 71	o/Eu:ॱ	I
    //   268: iload_2
    //   269: iconst_2
    //   270: irem
    //   271: ifeq +6 -> 277
    //   274: goto +42 -> 316
    //   277: goto -45 -> 232
    //   280: iconst_0
    //   281: istore_2
    //   282: goto -77 -> 205
    //   285: iload_2
    //   286: tableswitch	default:+22->308, 0:+86->372, 1:+-57->229
    //   308: goto -79 -> 229
    //   311: iconst_1
    //   312: istore_2
    //   313: goto -28 -> 285
    //   316: iconst_1
    //   317: istore_2
    //   318: goto +65 -> 383
    //   321: aconst_null
    //   322: arraylength
    //   323: istore_2
    //   324: return
    //   325: iconst_1
    //   326: istore_3
    //   327: aload_0
    //   328: iload_3
    //   329: putfield 164	o/Eu:isContactless	Z
    //   332: aload_1
    //   333: invokevirtual 162	android/os/Parcel:readByte	()B
    //   336: ifeq +6 -> 342
    //   339: goto -140 -> 199
    //   342: goto +36 -> 378
    //   345: getstatic 69	o/Eu:ʻ	I
    //   348: bipush 115
    //   350: iadd
    //   351: istore_2
    //   352: iload_2
    //   353: sipush 128
    //   356: irem
    //   357: putstatic 71	o/Eu:ॱ	I
    //   360: iload_2
    //   361: iconst_2
    //   362: irem
    //   363: ifeq +6 -> 369
    //   366: goto -363 -> 3
    //   369: goto -58 -> 311
    //   372: goto -45 -> 327
    //   375: astore_1
    //   376: aload_1
    //   377: athrow
    //   378: iconst_0
    //   379: istore_3
    //   380: goto +31 -> 411
    //   383: iload_2
    //   384: tableswitch	default:+24->408, 0:+51->435, 1:+-147->237
    //   408: goto +27 -> 435
    //   411: aload_0
    //   412: iload_3
    //   413: putfield 166	o/Eu:isEnrolled	Z
    //   416: aload_0
    //   417: aload_1
    //   418: invokevirtual 95	android/os/Parcel:readString	()Ljava/lang/String;
    //   421: putfield 168	o/Eu:customerCategory	Ljava/lang/String;
    //   424: aload_1
    //   425: aload_0
    //   426: getfield 86	o/Eu:listOfOperationsAllowed	Ljava/util/List;
    //   429: invokevirtual 172	android/os/Parcel:readStringList	(Ljava/util/List;)V
    //   432: goto -262 -> 170
    //   435: goto -24 -> 411
    // Local variable table:
    //   start	length	slot	name	signature
    //   0	438	0	this	Eu
    //   0	438	1	paramParcel	Parcel
    //   4	380	2	i	int
    //   200	213	3	bool	boolean
    //   19	16	4	localObject	Object
    // Exception table:
    //   from	to	target	type
    //   21	27	245	java/lang/Exception
    //   27	33	245	java/lang/Exception
    //   33	160	245	java/lang/Exception
    //   170	174	245	java/lang/Exception
    //   27	33	375	java/lang/Exception
    //   179	187	375	java/lang/Exception
  }
  
  public Eu(String paramString) {}
  
  private static String ˏ(byte[] paramArrayOfByte, int[] paramArrayOfInt, char[] paramArrayOfChar, int paramInt)
  {
    break label475;
    label3:
    int k = paramArrayOfInt.length;
    paramArrayOfByte = new char[k];
    int i = 0;
    break label191;
    boolean bool;
    try
    {
      bool = ˊ;
      if (bool) {
        break label376;
      }
    }
    catch (Exception paramArrayOfByte)
    {
      label34:
      throw paramArrayOfByte;
    }
    k = 93;
    break label442;
    label44:
    paramInt = ॱ + 111;
    ʻ = paramInt % 128;
    label79:
    int j;
    label91:
    label137:
    char[] arrayOfChar;
    int m;
    if (paramInt % 2 != 0)
    {
      return paramArrayOfByte;
      for (;;)
      {
        return new String(paramArrayOfByte);
        j = 0;
        break label256;
        i = 1;
        break label163;
        i = paramArrayOfByte.length;
        j = i;
        paramArrayOfInt = new char[i];
        break label323;
        for (;;)
        {
          j = ॱ + 53;
          ʻ = j % 128;
          if (j % 2 == 0) {
            break label478;
          }
          break label404;
          arrayOfChar = ˎ;
          m = ˏ;
          try
          {
            bool = ˋ;
            if (bool) {
              break label532;
            }
          }
          catch (Exception paramArrayOfByte)
          {
            label163:
            label191:
            label204:
            label210:
            label222:
            throw paramArrayOfByte;
          }
          switch (i)
          {
          case 1: 
          default: 
            break label3;
            if (i < k) {
              break label397;
            }
            break label435;
            j = 1;
            break label256;
            paramArrayOfByte = new String(paramArrayOfInt);
            break label44;
            paramArrayOfInt[i] = ((char)(arrayOfChar[(paramArrayOfByte[(j << 0 << i)] << paramInt)] - m));
            i += 4;
            break label512;
            label256:
            switch (j)
            {
            }
            break;
          }
        }
        return new String(paramArrayOfByte);
        label292:
        switch (j)
        {
        }
      }
      for (;;)
      {
        label323:
        i = 0;
        break;
        label329:
        i = paramArrayOfByte.length;
        j = i;
        paramArrayOfInt = new char[i];
      }
    }
    for (;;)
    {
      paramArrayOfInt[i] = ((char)(arrayOfChar[(paramArrayOfByte[(j - 1 - i)] + paramInt)] - m));
      i += 1;
      break label512;
      label376:
      i = 0;
      break label163;
      k = paramArrayOfChar.length;
      paramArrayOfByte = new char[k];
      i = 0;
      break label593;
      label397:
      j = 64;
      break label292;
      label404:
      paramArrayOfByte[i] = ((char)(arrayOfChar[(paramArrayOfChar[(k - 1 - i)] - paramInt)] - m));
      i += 1;
      break label593;
      label435:
      j = 63;
      break label292;
      for (;;)
      {
        switch (k)
        {
        case 93: 
        default: 
          label442:
          break label210;
          label475:
          break label137;
          label478:
          paramArrayOfByte[i] = ((char)(arrayOfChar[(paramArrayOfChar[((k << 1) - i)] >> paramInt)] / m));
          i += 19;
          break label593;
          return paramArrayOfByte;
          label512:
          if (i >= j) {
            break label34;
          }
          k = 70;
        }
      }
      label532:
      i = ॱ + 81;
      ʻ = i % 128;
      if (i % 2 == 0) {
        break label329;
      }
      break label91;
      paramArrayOfByte[i] = ((char)(arrayOfChar[(paramArrayOfInt[(k - 1 - i)] - paramInt)] - m));
      i += 1;
      break label191;
      label593:
      if (i < k) {
        break label79;
      }
      break label204;
      k = ʻ + 103;
      ॱ = k % 128;
      if (k % 2 != 0) {
        break label222;
      }
    }
  }
  
  static void ˏॱ()
  {
    ˋ = true;
    ˊ = true;
    ˎ = new char[] { 71, 8746, 51, 96, 66, 140, 123, 135, 131, 134, 77, 117, 116, 64, 120, 129, 65, 133, 127, 130, 138, 124, 137, 68, 118, 119, 121, 128, 122, 126 };
    ˏ = 19;
  }
  
  /* Error */
  public int describeContents()
  {
    // Byte code:
    //   0: goto +82 -> 82
    //   3: astore_2
    //   4: aload_2
    //   5: athrow
    //   6: getstatic 71	o/Eu:ॱ	I
    //   9: bipush 119
    //   11: iadd
    //   12: istore_1
    //   13: iload_1
    //   14: sipush 128
    //   17: irem
    //   18: putstatic 69	o/Eu:ʻ	I
    //   21: iload_1
    //   22: iconst_2
    //   23: irem
    //   24: ifne +6 -> 30
    //   27: goto +85 -> 112
    //   30: goto +29 -> 59
    //   33: iload_1
    //   34: tableswitch	default:+22->56, 0:+35->69, 1:+33->67
    //   56: goto +13 -> 69
    //   59: goto +26 -> 85
    //   62: iconst_1
    //   63: istore_1
    //   64: goto -31 -> 33
    //   67: iconst_0
    //   68: ireturn
    //   69: aconst_null
    //   70: arraylength
    //   71: istore_1
    //   72: iconst_0
    //   73: ireturn
    //   74: astore_2
    //   75: aload_2
    //   76: athrow
    //   77: iconst_0
    //   78: istore_1
    //   79: goto -46 -> 33
    //   82: goto -76 -> 6
    //   85: getstatic 71	o/Eu:ॱ	I
    //   88: bipush 31
    //   90: iadd
    //   91: istore_1
    //   92: iload_1
    //   93: sipush 128
    //   96: irem
    //   97: putstatic 69	o/Eu:ʻ	I
    //   100: iload_1
    //   101: iconst_2
    //   102: irem
    //   103: ifne +6 -> 109
    //   106: goto -29 -> 77
    //   109: goto -47 -> 62
    //   112: goto -53 -> 59
    // Local variable table:
    //   start	length	slot	name	signature
    //   0	115	0	this	Eu
    //   12	91	1	i	int
    //   3	2	2	localException1	Exception
    //   74	2	2	localException2	Exception
    // Exception table:
    //   from	to	target	type
    //   13	21	3	java/lang/Exception
    //   6	13	74	java/lang/Exception
    //   13	21	74	java/lang/Exception
  }
  
  /* Error */
  public void writeToParcel(Parcel paramParcel, int paramInt)
  {
    // Byte code:
    //   0: goto +157 -> 157
    //   3: aload_1
    //   4: iload_2
    //   5: i2b
    //   6: invokevirtual 241	android/os/Parcel:writeByte	(B)V
    //   9: aload_1
    //   10: aload_0
    //   11: getfield 168	o/Eu:customerCategory	Ljava/lang/String;
    //   14: invokevirtual 244	android/os/Parcel:writeString	(Ljava/lang/String;)V
    //   17: aload_1
    //   18: aload_0
    //   19: getfield 86	o/Eu:listOfOperationsAllowed	Ljava/util/List;
    //   22: invokevirtual 247	android/os/Parcel:writeStringList	(Ljava/util/List;)V
    //   25: goto +8 -> 33
    //   28: iconst_3
    //   29: istore_2
    //   30: goto +133 -> 163
    //   33: getstatic 71	o/Eu:ॱ	I
    //   36: bipush 31
    //   38: iadd
    //   39: istore_2
    //   40: iload_2
    //   41: sipush 128
    //   44: irem
    //   45: putstatic 69	o/Eu:ʻ	I
    //   48: iload_2
    //   49: iconst_2
    //   50: irem
    //   51: ifne +6 -> 57
    //   54: goto +75 -> 129
    //   57: return
    //   58: iconst_1
    //   59: istore_2
    //   60: goto -57 -> 3
    //   63: iload_2
    //   64: lookupswitch	default:+28->92, 36:+60->124, 40:+150->214
    //   92: goto +32 -> 124
    //   95: getstatic 69	o/Eu:ʻ	I
    //   98: istore_3
    //   99: iload_3
    //   100: bipush 97
    //   102: iadd
    //   103: istore_3
    //   104: iload_3
    //   105: sipush 128
    //   108: irem
    //   109: putstatic 71	o/Eu:ॱ	I
    //   112: iload_3
    //   113: iconst_2
    //   114: irem
    //   115: ifeq +6 -> 121
    //   118: goto +80 -> 198
    //   121: goto -118 -> 3
    //   124: iconst_0
    //   125: istore_2
    //   126: goto +263 -> 389
    //   129: return
    //   130: getstatic 69	o/Eu:ʻ	I
    //   133: bipush 65
    //   135: iadd
    //   136: istore_2
    //   137: iload_2
    //   138: sipush 128
    //   141: irem
    //   142: putstatic 71	o/Eu:ॱ	I
    //   145: iload_2
    //   146: iconst_2
    //   147: irem
    //   148: ifeq +6 -> 154
    //   151: goto +60 -> 211
    //   154: goto +71 -> 225
    //   157: goto +71 -> 228
    //   160: astore_1
    //   161: aload_1
    //   162: athrow
    //   163: iload_2
    //   164: lookupswitch	default:+28->192, 3:+42->206, 4:+-34->130
    //   192: goto +14 -> 206
    //   195: goto +163 -> 358
    //   198: goto -195 -> 3
    //   201: iconst_4
    //   202: istore_2
    //   203: goto -40 -> 163
    //   206: iconst_0
    //   207: istore_2
    //   208: goto -113 -> 95
    //   211: goto -153 -> 58
    //   214: iconst_1
    //   215: istore_2
    //   216: goto +142 -> 358
    //   219: bipush 40
    //   221: istore_2
    //   222: goto -159 -> 63
    //   225: goto -167 -> 58
    //   228: aload_1
    //   229: aload_0
    //   230: getfield 97	o/Eu:uuid	Ljava/lang/String;
    //   233: invokevirtual 244	android/os/Parcel:writeString	(Ljava/lang/String;)V
    //   236: aload_1
    //   237: aload_0
    //   238: getfield 99	o/Eu:instanceUUID	Ljava/lang/String;
    //   241: invokevirtual 244	android/os/Parcel:writeString	(Ljava/lang/String;)V
    //   244: aload_1
    //   245: aload_0
    //   246: getfield 101	o/Eu:cardIdentifier	Ljava/lang/String;
    //   249: invokevirtual 244	android/os/Parcel:writeString	(Ljava/lang/String;)V
    //   252: aload_1
    //   253: aload_0
    //   254: getfield 103	o/Eu:cardName	Ljava/lang/String;
    //   257: invokevirtual 244	android/os/Parcel:writeString	(Ljava/lang/String;)V
    //   260: aload_1
    //   261: aload_0
    //   262: getfield 109	o/Eu:expirationDate	J
    //   265: invokevirtual 251	android/os/Parcel:writeLong	(J)V
    //   268: aload_1
    //   269: aload_0
    //   270: getfield 111	o/Eu:cardholderName	Ljava/lang/String;
    //   273: invokevirtual 244	android/os/Parcel:writeString	(Ljava/lang/String;)V
    //   276: aload_1
    //   277: aload_0
    //   278: getfield 113	o/Eu:clientName	Ljava/lang/String;
    //   281: invokevirtual 244	android/os/Parcel:writeString	(Ljava/lang/String;)V
    //   284: aload_1
    //   285: aload_0
    //   286: getfield 127	o/Eu:productName	Lo/EA;
    //   289: iload_2
    //   290: invokevirtual 255	android/os/Parcel:writeParcelable	(Landroid/os/Parcelable;I)V
    //   293: aload_1
    //   294: aload_0
    //   295: getfield 129	o/Eu:cardNumber	Ljava/lang/String;
    //   298: invokevirtual 244	android/os/Parcel:writeString	(Ljava/lang/String;)V
    //   301: aload_1
    //   302: aload_0
    //   303: getfield 137	o/Eu:currency	Lo/Ep;
    //   306: invokevirtual 258	o/Ep:name	()Ljava/lang/String;
    //   309: invokevirtual 244	android/os/Parcel:writeString	(Ljava/lang/String;)V
    //   312: aload_1
    //   313: aload_0
    //   314: getfield 144	o/Eu:cardStatus	Lo/El;
    //   317: invokevirtual 259	o/El:name	()Ljava/lang/String;
    //   320: invokevirtual 244	android/os/Parcel:writeString	(Ljava/lang/String;)V
    //   323: aload_1
    //   324: aload_0
    //   325: getfield 151	o/Eu:cardScheme	Lo/Eh;
    //   328: invokevirtual 260	o/Eh:name	()Ljava/lang/String;
    //   331: invokevirtual 244	android/os/Parcel:writeString	(Ljava/lang/String;)V
    //   334: aload_1
    //   335: aload_0
    //   336: getfield 158	o/Eu:cardType	Lo/Ei;
    //   339: invokevirtual 261	o/Ei:name	()Ljava/lang/String;
    //   342: invokevirtual 244	android/os/Parcel:writeString	(Ljava/lang/String;)V
    //   345: aload_0
    //   346: getfield 164	o/Eu:isContactless	Z
    //   349: ifeq +6 -> 355
    //   352: goto -133 -> 219
    //   355: goto +28 -> 383
    //   358: aload_1
    //   359: iload_2
    //   360: i2b
    //   361: invokevirtual 241	android/os/Parcel:writeByte	(B)V
    //   364: aload_0
    //   365: getfield 166	o/Eu:isEnrolled	Z
    //   368: ifeq +6 -> 374
    //   371: goto -170 -> 201
    //   374: goto -346 -> 28
    //   377: goto -19 -> 358
    //   380: astore_1
    //   381: aload_1
    //   382: athrow
    //   383: bipush 36
    //   385: istore_2
    //   386: goto -323 -> 63
    //   389: getstatic 69	o/Eu:ʻ	I
    //   392: istore_3
    //   393: iload_3
    //   394: bipush 51
    //   396: iadd
    //   397: istore_3
    //   398: iload_3
    //   399: sipush 128
    //   402: irem
    //   403: putstatic 71	o/Eu:ॱ	I
    //   406: iload_3
    //   407: iconst_2
    //   408: irem
    //   409: ifeq +6 -> 415
    //   412: goto -217 -> 195
    //   415: goto -38 -> 377
    // Local variable table:
    //   start	length	slot	name	signature
    //   0	418	0	this	Eu
    //   0	418	1	paramParcel	Parcel
    //   0	418	2	paramInt	int
    //   98	311	3	i	int
    // Exception table:
    //   from	to	target	type
    //   95	99	160	java/lang/Exception
    //   104	112	160	java/lang/Exception
    //   398	406	160	java/lang/Exception
    //   389	393	380	java/lang/Exception
  }
  
  /* Error */
  public String ʻ()
  {
    // Byte code:
    //   0: goto +527 -> 527
    //   3: astore_2
    //   4: aload_2
    //   5: athrow
    //   6: iconst_0
    //   7: istore_1
    //   8: goto +491 -> 499
    //   11: new 263	java/lang/StringBuilder
    //   14: dup
    //   15: invokespecial 264	java/lang/StringBuilder:<init>	()V
    //   18: astore_2
    //   19: bipush 46
    //   21: newarray byte
    //   23: dup
    //   24: iconst_0
    //   25: ldc_w 265
    //   28: bastore
    //   29: dup
    //   30: iconst_1
    //   31: ldc_w 266
    //   34: bastore
    //   35: dup
    //   36: iconst_2
    //   37: ldc_w 267
    //   40: bastore
    //   41: dup
    //   42: iconst_3
    //   43: ldc_w 268
    //   46: bastore
    //   47: dup
    //   48: iconst_4
    //   49: ldc_w 269
    //   52: bastore
    //   53: dup
    //   54: iconst_5
    //   55: ldc_w 265
    //   58: bastore
    //   59: dup
    //   60: bipush 6
    //   62: ldc_w 270
    //   65: bastore
    //   66: dup
    //   67: bipush 7
    //   69: ldc_w 271
    //   72: bastore
    //   73: dup
    //   74: bipush 8
    //   76: ldc_w 265
    //   79: bastore
    //   80: dup
    //   81: bipush 9
    //   83: ldc_w 272
    //   86: bastore
    //   87: dup
    //   88: bipush 10
    //   90: ldc_w 273
    //   93: bastore
    //   94: dup
    //   95: bipush 11
    //   97: ldc_w 268
    //   100: bastore
    //   101: dup
    //   102: bipush 12
    //   104: ldc_w 265
    //   107: bastore
    //   108: dup
    //   109: bipush 13
    //   111: ldc_w 274
    //   114: bastore
    //   115: dup
    //   116: bipush 14
    //   118: ldc_w 275
    //   121: bastore
    //   122: dup
    //   123: bipush 15
    //   125: ldc_w 276
    //   128: bastore
    //   129: dup
    //   130: bipush 16
    //   132: ldc_w 276
    //   135: bastore
    //   136: dup
    //   137: bipush 17
    //   139: ldc_w 268
    //   142: bastore
    //   143: dup
    //   144: bipush 18
    //   146: ldc_w 277
    //   149: bastore
    //   150: dup
    //   151: bipush 19
    //   153: ldc_w 274
    //   156: bastore
    //   157: dup
    //   158: bipush 20
    //   160: ldc_w 278
    //   163: bastore
    //   164: dup
    //   165: bipush 21
    //   167: ldc_w 265
    //   170: bastore
    //   171: dup
    //   172: bipush 22
    //   174: ldc_w 279
    //   177: bastore
    //   178: dup
    //   179: bipush 23
    //   181: ldc_w 267
    //   184: bastore
    //   185: dup
    //   186: bipush 24
    //   188: ldc_w 280
    //   191: bastore
    //   192: dup
    //   193: bipush 25
    //   195: ldc_w 276
    //   198: bastore
    //   199: dup
    //   200: bipush 26
    //   202: ldc_w 267
    //   205: bastore
    //   206: dup
    //   207: bipush 27
    //   209: ldc_w 274
    //   212: bastore
    //   213: dup
    //   214: bipush 28
    //   216: ldc_w 278
    //   219: bastore
    //   220: dup
    //   221: bipush 29
    //   223: ldc_w 280
    //   226: bastore
    //   227: dup
    //   228: bipush 30
    //   230: ldc_w 281
    //   233: bastore
    //   234: dup
    //   235: bipush 31
    //   237: ldc_w 275
    //   240: bastore
    //   241: dup
    //   242: bipush 32
    //   244: ldc_w 282
    //   247: bastore
    //   248: dup
    //   249: bipush 33
    //   251: ldc_w 283
    //   254: bastore
    //   255: dup
    //   256: bipush 34
    //   258: ldc_w 268
    //   261: bastore
    //   262: dup
    //   263: bipush 35
    //   265: ldc_w 273
    //   268: bastore
    //   269: dup
    //   270: bipush 36
    //   272: ldc_w 274
    //   275: bastore
    //   276: dup
    //   277: bipush 37
    //   279: ldc_w 278
    //   282: bastore
    //   283: dup
    //   284: bipush 38
    //   286: ldc_w 265
    //   289: bastore
    //   290: dup
    //   291: bipush 39
    //   293: ldc_w 265
    //   296: bastore
    //   297: dup
    //   298: bipush 40
    //   300: ldc_w 284
    //   303: bastore
    //   304: dup
    //   305: bipush 41
    //   307: ldc_w 285
    //   310: bastore
    //   311: dup
    //   312: bipush 42
    //   314: ldc_w 273
    //   317: bastore
    //   318: dup
    //   319: bipush 43
    //   321: ldc_w 274
    //   324: bastore
    //   325: dup
    //   326: bipush 44
    //   328: ldc_w 274
    //   331: bastore
    //   332: dup
    //   333: bipush 45
    //   335: ldc_w 286
    //   338: bastore
    //   339: aconst_null
    //   340: aconst_null
    //   341: bipush 127
    //   343: invokestatic 180	o/Eu:ˏ	([B[I[CI)Ljava/lang/String;
    //   346: astore_3
    //   347: aload_3
    //   348: invokevirtual 185	java/lang/String:intern	()Ljava/lang/String;
    //   351: astore_3
    //   352: aload_2
    //   353: aload_3
    //   354: invokevirtual 290	java/lang/StringBuilder:append	(Ljava/lang/String;)Ljava/lang/StringBuilder;
    //   357: astore_2
    //   358: aload_2
    //   359: aload_0
    //   360: getfield 97	o/Eu:uuid	Ljava/lang/String;
    //   363: invokevirtual 290	java/lang/StringBuilder:append	(Ljava/lang/String;)Ljava/lang/StringBuilder;
    //   366: bipush 15
    //   368: newarray byte
    //   370: dup
    //   371: iconst_0
    //   372: ldc_w 275
    //   375: bastore
    //   376: dup
    //   377: iconst_1
    //   378: ldc_w 291
    //   381: bastore
    //   382: dup
    //   383: iconst_2
    //   384: ldc_w 268
    //   387: bastore
    //   388: dup
    //   389: iconst_3
    //   390: ldc_w 292
    //   393: bastore
    //   394: dup
    //   395: iconst_4
    //   396: ldc_w 272
    //   399: bastore
    //   400: dup
    //   401: iconst_5
    //   402: ldc_w 293
    //   405: bastore
    //   406: dup
    //   407: bipush 6
    //   409: ldc_w 269
    //   412: bastore
    //   413: dup
    //   414: bipush 7
    //   416: ldc_w 268
    //   419: bastore
    //   420: dup
    //   421: bipush 8
    //   423: ldc_w 278
    //   426: bastore
    //   427: dup
    //   428: bipush 9
    //   430: ldc_w 265
    //   433: bastore
    //   434: dup
    //   435: bipush 10
    //   437: ldc_w 266
    //   440: bastore
    //   441: dup
    //   442: bipush 11
    //   444: ldc_w 267
    //   447: bastore
    //   448: dup
    //   449: bipush 12
    //   451: ldc_w 268
    //   454: bastore
    //   455: dup
    //   456: bipush 13
    //   458: ldc_w 269
    //   461: bastore
    //   462: dup
    //   463: bipush 14
    //   465: ldc_w 265
    //   468: bastore
    //   469: aconst_null
    //   470: aconst_null
    //   471: bipush 127
    //   473: invokestatic 180	o/Eu:ˏ	([B[I[CI)Ljava/lang/String;
    //   476: invokevirtual 185	java/lang/String:intern	()Ljava/lang/String;
    //   479: invokevirtual 290	java/lang/StringBuilder:append	(Ljava/lang/String;)Ljava/lang/StringBuilder;
    //   482: invokevirtual 296	java/lang/StringBuilder:toString	()Ljava/lang/String;
    //   485: astore_2
    //   486: goto +44 -> 530
    //   489: aconst_null
    //   490: arraylength
    //   491: istore_1
    //   492: aload_2
    //   493: areturn
    //   494: astore_2
    //   495: aload_2
    //   496: athrow
    //   497: aload_2
    //   498: areturn
    //   499: iload_1
    //   500: tableswitch	default:+24->524, 0:+-11->489, 1:+-3->497
    //   524: goto -35 -> 489
    //   527: goto -516 -> 11
    //   530: getstatic 69	o/Eu:ʻ	I
    //   533: bipush 91
    //   535: iadd
    //   536: istore_1
    //   537: iload_1
    //   538: sipush 128
    //   541: irem
    //   542: putstatic 71	o/Eu:ॱ	I
    //   545: iload_1
    //   546: iconst_2
    //   547: irem
    //   548: ifeq +6 -> 554
    //   551: goto -545 -> 6
    //   554: iconst_1
    //   555: istore_1
    //   556: goto -57 -> 499
    // Exception table:
    //   from	to	target	type
    //   19	347	494	java/lang/Exception
    //   347	352	494	java/lang/Exception
    //   352	358	494	java/lang/Exception
    //   358	486	494	java/lang/Exception
  }
  
  public Ep ʼ()
  {
    break label6;
    break label35;
    label6:
    break label43;
    label9:
    int i = ॱ + 123;
    ʻ = i % 128;
    Ep localEp;
    if (i % 2 != 0)
    {
      return localEp;
      for (;;)
      {
        label35:
        localEp = this.currency;
        break label9;
        label43:
        i = ॱ + 107;
        ʻ = i % 128;
        if (i % 2 == 0) {
          break;
        }
      }
    }
    return localEp;
  }
  
  public String ʽ()
  {
    for (;;)
    {
      int i = ʻ + 55;
      ॱ = i % 128;
      if (i % 2 != 0) {
        return str;
      }
      return str;
      String str = ˏ(new byte[] { -123, -102, -110, -115, -103, -123, -104, -105, -123, -106, -119, -115, -123, -120, -113, -109, -109, -115, -107, -120, -116, -123, -108, -110, -111, -109, -110, -120, -116, -111, -112, -113, -114, -122, -115, -119, -120, -116, -123, -123, -117, -118, -119, -120, -120, -121 }, null, null, 127).intern() + this.uuid + ˏ(new byte[] { -113, -99, -115, -100, -106, -120, -112, -108, -110, -101, -123, -102, -110, -115, -103, -123 }, null, null, 127).intern();
    }
  }
  
  public String ˊ()
  {
    break label69;
    label3:
    int i = ʻ + 3;
    ॱ = i % 128;
    if (i % 2 == 0)
    {
      break label72;
      label29:
      return this.cardNumber;
    }
    for (;;)
    {
      switch (i)
      {
      case 56: 
      default: 
        break label29;
        i = 76;
        continue;
        label69:
        break label3;
        label72:
        i = 56;
      }
    }
    String str = this.cardNumber;
    i = null.length;
    return str;
  }
  
  public void ˊ(String paramString)
  {
    break label60;
    int i;
    long l;
    for (;;)
    {
      switch (i)
      {
      case 2: 
      default: 
        l = 0L;
        break label48;
        i = 2;
        continue;
        label42:
        i = 44;
      }
    }
    for (;;)
    {
      label48:
      this.expirationDate = l;
      return;
      for (;;)
      {
        i = 11;
        break label195;
        label60:
        break label107;
        break;
        label72:
        do
        {
          i = 17;
          break;
          i = ʻ + 99;
          ॱ = i % 128;
        } while (i % 2 != 0);
      }
      for (;;)
      {
        l = paramString.getTime();
        break label72;
        label107:
        paramString = ak.ˏ(paramString, ˏ(new byte[] { -122, -122, -123, -124, -124 }, null, null, 127).intern());
        if (paramString != null) {
          break label42;
        }
        break;
        do
        {
          break;
          i = ॱ + 25;
          ʻ = i % 128;
        } while (i % 2 == 0);
      }
      label195:
      switch (i)
      {
      }
    }
  }
  
  public void ˊ(boolean paramBoolean)
  {
    for (;;)
    {
      try
      {
        this.isEnrolled = paramBoolean;
        i = null.length;
        return;
      }
      catch (Exception localException)
      {
        throw localException;
      }
      this.isEnrolled = paramBoolean;
      return;
      do
      {
        i = 0;
        break;
        i = ʻ + 71;
        ॱ = i % 128;
      } while (i % 2 != 0);
      int i = 1;
      switch (i)
      {
      }
    }
  }
  
  public EA ˋ()
  {
    for (;;)
    {
      try
      {
        i = ॱ + 79;
      }
      catch (Exception localException1)
      {
        int i;
        EA localEA1;
        throw localException1;
      }
      try
      {
        ʻ = i % 128;
        if (i % 2 != 0) {
          return localEA1;
        }
        return localEA1;
      }
      catch (Exception localException2)
      {
        EA localEA2;
        throw localException2;
      }
      i = ʻ + 21;
      ॱ = i % 128;
      if (i % 2 == 0) {
        break label61;
      }
      label61:
      localEA2 = this.productName;
    }
  }
  
  /* Error */
  public void ˋ(long paramLong)
  {
    // Byte code:
    //   0: goto +8 -> 8
    //   3: astore 4
    //   5: aload 4
    //   7: athrow
    //   8: getstatic 69	o/Eu:ʻ	I
    //   11: bipush 7
    //   13: iadd
    //   14: istore_3
    //   15: iload_3
    //   16: sipush 128
    //   19: irem
    //   20: putstatic 71	o/Eu:ॱ	I
    //   23: iload_3
    //   24: iconst_2
    //   25: irem
    //   26: ifeq +6 -> 32
    //   29: goto +45 -> 74
    //   32: goto +33 -> 65
    //   35: astore 4
    //   37: aload 4
    //   39: athrow
    //   40: getstatic 71	o/Eu:ॱ	I
    //   43: bipush 9
    //   45: iadd
    //   46: istore_3
    //   47: iload_3
    //   48: sipush 128
    //   51: irem
    //   52: putstatic 69	o/Eu:ʻ	I
    //   55: iload_3
    //   56: iconst_2
    //   57: irem
    //   58: ifne +6 -> 64
    //   61: goto +12 -> 73
    //   64: return
    //   65: aload_0
    //   66: lload_1
    //   67: putfield 109	o/Eu:expirationDate	J
    //   70: goto -30 -> 40
    //   73: return
    //   74: goto -9 -> 65
    // Local variable table:
    //   start	length	slot	name	signature
    //   0	77	0	this	Eu
    //   0	77	1	paramLong	long
    //   14	44	3	i	int
    //   3	3	4	localException1	Exception
    //   35	3	4	localException2	Exception
    // Exception table:
    //   from	to	target	type
    //   8	15	3	java/lang/Exception
    //   15	23	3	java/lang/Exception
    //   40	47	3	java/lang/Exception
    //   47	55	3	java/lang/Exception
    //   15	23	35	java/lang/Exception
    //   65	70	35	java/lang/Exception
  }
  
  public void ˋ(Ei paramEi)
  {
    break label66;
    try
    {
      i = ʻ + 59;
      ॱ = i % 128;
      if (i % 2 != 0) {
        break label47;
      }
    }
    catch (Exception paramEi)
    {
      throw paramEi;
    }
    this.cardType = paramEi;
    break label72;
    int i = 34;
    break label98;
    label47:
    i = 6;
    for (;;)
    {
      try
      {
        this.cardType = paramEi;
        throw new NullPointerException();
      }
      catch (Exception paramEi)
      {
        label66:
        throw paramEi;
      }
      break;
      label72:
      i = ॱ + 123;
      ʻ = i % 128;
      if (i % 2 != 0) {
        return;
      }
      return;
      label98:
      switch (i)
      {
      }
    }
  }
  
  /* Error */
  public final String ˎ()
  {
    // Byte code:
    //   0: goto +6 -> 6
    //   3: goto +116 -> 119
    //   6: goto +48 -> 54
    //   9: aload_0
    //   10: getfield 129	o/Eu:cardNumber	Ljava/lang/String;
    //   13: invokevirtual 320	java/lang/String:length	()I
    //   16: iconst_4
    //   17: if_icmpgt +6 -> 23
    //   20: goto +11 -> 31
    //   23: goto +224 -> 247
    //   26: iconst_3
    //   27: istore_1
    //   28: goto +188 -> 216
    //   31: bipush 35
    //   33: istore_1
    //   34: goto +55 -> 89
    //   37: aload_0
    //   38: getfield 129	o/Eu:cardNumber	Ljava/lang/String;
    //   41: invokevirtual 320	java/lang/String:length	()I
    //   44: iconst_5
    //   45: if_icmpgt +6 -> 51
    //   48: goto +205 -> 253
    //   51: goto +239 -> 290
    //   54: getstatic 71	o/Eu:ॱ	I
    //   57: bipush 103
    //   59: iadd
    //   60: istore_1
    //   61: iload_1
    //   62: sipush 128
    //   65: irem
    //   66: putstatic 69	o/Eu:ʻ	I
    //   69: iload_1
    //   70: iconst_2
    //   71: irem
    //   72: ifne +6 -> 78
    //   75: goto -38 -> 37
    //   78: goto -69 -> 9
    //   81: aload_0
    //   82: getfield 129	o/Eu:cardNumber	Ljava/lang/String;
    //   85: astore_2
    //   86: goto +33 -> 119
    //   89: iload_1
    //   90: lookupswitch	default:+26->116, 35:+-9->81, 50:+206->296
    //   116: goto -35 -> 81
    //   119: new 263	java/lang/StringBuilder
    //   122: dup
    //   123: invokespecial 264	java/lang/StringBuilder:<init>	()V
    //   126: iconst_5
    //   127: newarray byte
    //   129: dup
    //   130: iconst_0
    //   131: ldc_w 321
    //   134: bastore
    //   135: dup
    //   136: iconst_1
    //   137: ldc_w 322
    //   140: bastore
    //   141: dup
    //   142: iconst_2
    //   143: ldc_w 322
    //   146: bastore
    //   147: dup
    //   148: iconst_3
    //   149: ldc_w 322
    //   152: bastore
    //   153: dup
    //   154: iconst_4
    //   155: ldc_w 322
    //   158: bastore
    //   159: aconst_null
    //   160: aconst_null
    //   161: bipush 127
    //   163: invokestatic 180	o/Eu:ˏ	([B[I[CI)Ljava/lang/String;
    //   166: invokevirtual 185	java/lang/String:intern	()Ljava/lang/String;
    //   169: invokevirtual 290	java/lang/StringBuilder:append	(Ljava/lang/String;)Ljava/lang/StringBuilder;
    //   172: aload_2
    //   173: invokevirtual 290	java/lang/StringBuilder:append	(Ljava/lang/String;)Ljava/lang/StringBuilder;
    //   176: invokevirtual 296	java/lang/StringBuilder:toString	()Ljava/lang/String;
    //   179: areturn
    //   180: astore_2
    //   181: aload_2
    //   182: athrow
    //   183: getstatic 69	o/Eu:ʻ	I
    //   186: bipush 49
    //   188: iadd
    //   189: istore_1
    //   190: iload_1
    //   191: sipush 128
    //   194: irem
    //   195: putstatic 71	o/Eu:ॱ	I
    //   198: iload_1
    //   199: iconst_2
    //   200: irem
    //   201: ifeq +6 -> 207
    //   204: goto +9 -> 213
    //   207: goto -181 -> 26
    //   210: goto -91 -> 119
    //   213: bipush 56
    //   215: istore_1
    //   216: iload_1
    //   217: lookupswitch	default:+27->244, 3:+-214->3, 56:+-7->210
    //   244: goto -34 -> 210
    //   247: bipush 50
    //   249: istore_1
    //   250: goto -161 -> 89
    //   253: bipush 48
    //   255: istore_1
    //   256: iload_1
    //   257: lookupswitch	default:+27->284, 48:+-176->81, 61:+39->296
    //   284: goto -203 -> 81
    //   287: astore_2
    //   288: aload_2
    //   289: athrow
    //   290: bipush 61
    //   292: istore_1
    //   293: goto -37 -> 256
    //   296: aload_0
    //   297: getfield 129	o/Eu:cardNumber	Ljava/lang/String;
    //   300: astore_2
    //   301: aload_2
    //   302: invokevirtual 320	java/lang/String:length	()I
    //   305: istore_1
    //   306: aload_0
    //   307: getfield 129	o/Eu:cardNumber	Ljava/lang/String;
    //   310: iload_1
    //   311: iconst_4
    //   312: isub
    //   313: iload_1
    //   314: invokevirtual 326	java/lang/String:substring	(II)Ljava/lang/String;
    //   317: astore_2
    //   318: goto -135 -> 183
    // Local variable table:
    //   start	length	slot	name	signature
    //   0	321	0	this	Eu
    //   27	287	1	i	int
    //   85	88	2	str1	String
    //   180	2	2	localException1	Exception
    //   287	2	2	localException2	Exception
    //   300	18	2	str2	String
    // Exception table:
    //   from	to	target	type
    //   306	318	180	java/lang/Exception
    //   183	190	287	java/lang/Exception
    //   190	198	287	java/lang/Exception
    //   296	301	287	java/lang/Exception
    //   301	306	287	java/lang/Exception
    //   306	318	287	java/lang/Exception
  }
  
  public void ˎ(String paramString)
  {
    break label53;
    this.uuid = paramString;
    int i = 44 / 0;
    return;
    for (;;)
    {
      this.uuid = paramString;
      return;
      i = 11;
      break label59;
      label53:
      for (;;)
      {
        i = ॱ + 39;
        ʻ = i % 128;
        if (i % 2 == 0) {
          break;
        }
        break label56;
      }
      label56:
      i = 35;
      label59:
      switch (i)
      {
      }
    }
  }
  
  public String ˏ()
  {
    break label79;
    return this.cardholderName;
    int i = 0;
    break label52;
    label13:
    String str = this.cardholderName;
    i = null.length;
    return str;
    label52:
    label79:
    for (;;)
    {
      i = ʻ + 47;
      ॱ = i % 128;
      if (i % 2 == 0) {
        break;
      }
      i = 1;
      switch (i)
      {
      }
      break label13;
    }
  }
  
  public void ˏ(String paramString)
  {
    break label39;
    this.cardholderName = paramString;
    int i = 31 / 0;
    return;
    switch (i)
    {
    case 0: 
    default: 
      label39:
      break;
    }
    for (;;)
    {
      i = 1;
      break;
      label47:
      i = 0;
      break;
      try
      {
        i = ʻ;
        i += 25;
        ॱ = i % 128;
        if (i % 2 != 0) {
          break label47;
        }
      }
      catch (Exception paramString)
      {
        throw paramString;
      }
    }
    this.cardholderName = paramString;
  }
  
  public void ˏ(EA paramEA)
  {
    for (;;)
    {
      try
      {
        this.productName = paramEA;
        return;
      }
      catch (Exception paramEA)
      {
        int i;
        throw paramEA;
      }
      switch (i)
      {
      case 1: 
      default: 
        continue;
        i = 1;
        continue;
        i = ʻ + 55;
        ॱ = i % 128;
        if (i % 2 != 0) {}
        break;
      case 0: 
        this.productName = paramEA;
        i = 69 / 0;
        return;
        i = 0;
      }
    }
  }
  
  public void ˏ(Ep paramEp)
  {
    break label64;
    label11:
    for (;;)
    {
      this.currency = paramEp;
      break;
    }
    label64:
    for (;;)
    {
      int i = ॱ + 85;
      ʻ = i % 128;
      if (i % 2 == 0) {
        break label11;
      }
      break;
      i = ॱ + 119;
      ʻ = i % 128;
      if (i % 2 == 0) {
        return;
      }
      return;
    }
  }
  
  /* Error */
  public String ͺ()
  {
    // Byte code:
    //   0: goto +9 -> 9
    //   3: astore_2
    //   4: aload_2
    //   5: athrow
    //   6: astore_2
    //   7: aload_2
    //   8: athrow
    //   9: goto +34 -> 43
    //   12: getstatic 69	o/Eu:ʻ	I
    //   15: bipush 7
    //   17: iadd
    //   18: istore_1
    //   19: iload_1
    //   20: sipush 128
    //   23: irem
    //   24: putstatic 71	o/Eu:ॱ	I
    //   27: iload_1
    //   28: iconst_2
    //   29: irem
    //   30: ifeq +6 -> 36
    //   33: goto +8 -> 41
    //   36: aload_2
    //   37: areturn
    //   38: goto +29 -> 67
    //   41: aload_2
    //   42: areturn
    //   43: getstatic 71	o/Eu:ॱ	I
    //   46: bipush 51
    //   48: iadd
    //   49: istore_1
    //   50: iload_1
    //   51: sipush 128
    //   54: irem
    //   55: putstatic 69	o/Eu:ʻ	I
    //   58: iload_1
    //   59: iconst_2
    //   60: irem
    //   61: ifne +6 -> 67
    //   64: goto -26 -> 38
    //   67: aload_0
    //   68: getfield 129	o/Eu:cardNumber	Ljava/lang/String;
    //   71: astore_2
    //   72: aload_0
    //   73: getfield 129	o/Eu:cardNumber	Ljava/lang/String;
    //   76: astore_3
    //   77: aload_3
    //   78: invokevirtual 320	java/lang/String:length	()I
    //   81: istore_1
    //   82: aload_2
    //   83: iload_1
    //   84: iconst_4
    //   85: isub
    //   86: invokevirtual 332	java/lang/String:substring	(I)Ljava/lang/String;
    //   89: astore_2
    //   90: goto -78 -> 12
    // Local variable table:
    //   start	length	slot	name	signature
    //   0	93	0	this	Eu
    //   18	68	1	i	int
    //   3	2	2	localException1	Exception
    //   6	36	2	localException2	Exception
    //   71	19	2	str1	String
    //   76	2	3	str2	String
    // Exception table:
    //   from	to	target	type
    //   50	58	3	java/lang/Exception
    //   43	50	6	java/lang/Exception
    //   50	58	6	java/lang/Exception
    //   67	72	6	java/lang/Exception
    //   72	77	6	java/lang/Exception
    //   77	82	6	java/lang/Exception
    //   82	90	6	java/lang/Exception
  }
  
  /* Error */
  public String ॱ()
  {
    // Byte code:
    //   0: goto +126 -> 126
    //   3: bipush 53
    //   5: istore_1
    //   6: goto +70 -> 76
    //   9: astore_2
    //   10: aload_2
    //   11: athrow
    //   12: astore_2
    //   13: aload_2
    //   14: athrow
    //   15: aload_0
    //   16: getfield 97	o/Eu:uuid	Ljava/lang/String;
    //   19: astore_2
    //   20: getstatic 69	o/Eu:ʻ	I
    //   23: istore_1
    //   24: iload_1
    //   25: iconst_1
    //   26: iadd
    //   27: istore_1
    //   28: iload_1
    //   29: sipush 128
    //   32: irem
    //   33: putstatic 71	o/Eu:ॱ	I
    //   36: iload_1
    //   37: iconst_2
    //   38: irem
    //   39: ifeq +6 -> 45
    //   42: goto +32 -> 74
    //   45: aload_2
    //   46: areturn
    //   47: getstatic 71	o/Eu:ॱ	I
    //   50: bipush 105
    //   52: iadd
    //   53: istore_1
    //   54: iload_1
    //   55: sipush 128
    //   58: irem
    //   59: putstatic 69	o/Eu:ʻ	I
    //   62: iload_1
    //   63: iconst_2
    //   64: irem
    //   65: ifne +6 -> 71
    //   68: goto +39 -> 107
    //   71: goto -68 -> 3
    //   74: aload_2
    //   75: areturn
    //   76: iload_1
    //   77: lookupswitch	default:+27->104, 25:+36->113, 53:+-62->15
    //   104: goto -89 -> 15
    //   107: bipush 25
    //   109: istore_1
    //   110: goto -34 -> 76
    //   113: aload_0
    //   114: getfield 97	o/Eu:uuid	Ljava/lang/String;
    //   117: astore_2
    //   118: bipush 35
    //   120: iconst_0
    //   121: idiv
    //   122: istore_1
    //   123: goto -103 -> 20
    //   126: goto -79 -> 47
    // Local variable table:
    //   start	length	slot	name	signature
    //   0	129	0	this	Eu
    //   5	118	1	i	int
    //   9	2	2	localException1	Exception
    //   12	2	2	localException2	Exception
    //   19	99	2	str	String
    // Exception table:
    //   from	to	target	type
    //   28	36	9	java/lang/Exception
    //   20	24	12	java/lang/Exception
  }
  
  public void ॱ(boolean paramBoolean)
  {
    break label46;
    int i = 0;
    break label58;
    label46:
    for (;;)
    {
      i = ʻ + 25;
      ॱ = i % 128;
      if (i % 2 != 0) {
        break;
      }
      break label55;
      this.isContactless = paramBoolean;
      i = 48 / 0;
      return;
    }
    for (;;)
    {
      this.isContactless = paramBoolean;
      return;
      label55:
      i = 17;
      label58:
      switch (i)
      {
      }
    }
  }
  
  /* Error */
  public Eh ॱॱ()
  {
    // Byte code:
    //   0: goto +24 -> 24
    //   3: astore_2
    //   4: aload_2
    //   5: athrow
    //   6: iconst_0
    //   7: istore_1
    //   8: goto +77 -> 85
    //   11: aload_0
    //   12: getfield 151	o/Eu:cardScheme	Lo/Eh;
    //   15: astore_2
    //   16: new 316	java/lang/NullPointerException
    //   19: dup
    //   20: invokespecial 317	java/lang/NullPointerException:<init>	()V
    //   23: athrow
    //   24: goto +33 -> 57
    //   27: aload_0
    //   28: getfield 151	o/Eu:cardScheme	Lo/Eh;
    //   31: astore_2
    //   32: getstatic 71	o/Eu:ॱ	I
    //   35: bipush 85
    //   37: iadd
    //   38: istore_1
    //   39: iload_1
    //   40: sipush 128
    //   43: irem
    //   44: putstatic 69	o/Eu:ʻ	I
    //   47: iload_1
    //   48: iconst_2
    //   49: irem
    //   50: ifne +5 -> 55
    //   53: aload_2
    //   54: areturn
    //   55: aload_2
    //   56: areturn
    //   57: getstatic 71	o/Eu:ॱ	I
    //   60: iconst_5
    //   61: iadd
    //   62: istore_1
    //   63: iload_1
    //   64: sipush 128
    //   67: irem
    //   68: putstatic 69	o/Eu:ʻ	I
    //   71: iload_1
    //   72: iconst_2
    //   73: irem
    //   74: ifne +6 -> 80
    //   77: goto +6 -> 83
    //   80: goto -74 -> 6
    //   83: iconst_1
    //   84: istore_1
    //   85: iload_1
    //   86: tableswitch	default:+22->108, 0:+-59->27, 1:+-75->11
    //   108: goto -81 -> 27
    // Local variable table:
    //   start	length	slot	name	signature
    //   0	111	0	this	Eu
    //   7	79	1	i	int
    //   3	2	2	localException	Exception
    //   15	41	2	localEh	Eh
    // Exception table:
    //   from	to	target	type
    //   11	16	3	java/lang/Exception
    //   57	63	3	java/lang/Exception
    //   63	71	3	java/lang/Exception
  }
  
  public String ᐝ()
  {
    break label56;
    int i = ʻ + 119;
    ॱ = i % 128;
    String str;
    if (i % 2 == 0)
    {
      return str;
      label56:
      for (;;)
      {
        i = ॱ + 99;
        ʻ = i % 128;
        if (i % 2 == 0) {
          break label115;
        }
        break;
      }
    }
    return str;
    label115:
    for (;;)
    {
      str = ak.ॱ(this.expirationDate, ˏ(new byte[] { -122, -122, -123, -124, -124 }, null, null, 127).intern());
      break;
    }
  }
}
