package o;

public final class Ey
{
  private static long ˊ = 4261628051043042005L;
  private static int ˋ = 0;
  private static char[] ˏ = { 84, -15686, -31295, 18458, 2874, -12704, -28528, 21429, 5831, -9899, -25562, 24392, 8599, -6988, -22584, 27179, 11569, -4021, -19799, 30138, 14530, -1249, -16857, -32421, 17349, 44, -15627, -31285, 18460, 2871, -12730, -28533, 21437, 5852, -9939, -25549, 24393, 8623, -7004, -22592, 27165, 11577, -4003, -19769, -15431, 352, 17995, -29819, -14166, 3545, 21253, -28669, -10939, 6808, 24494, -25408, -7664, 10105, -13796 };
  private static int ॱ = 1;
  private final String accountPanSuffix;
  private final String tokenExpiry;
  private final String tokenPanSuffix;
  
  /* Error */
  private static String ˏ(int paramInt1, char paramChar, int paramInt2)
  {
    // Byte code:
    //   0: goto +50 -> 50
    //   3: goto +33 -> 36
    //   6: getstatic 21	o/Ey:ॱ	I
    //   9: bipush 115
    //   11: iadd
    //   12: istore 4
    //   14: iload 4
    //   16: sipush 128
    //   19: irem
    //   20: putstatic 19	o/Ey:ˋ	I
    //   23: iload 4
    //   25: iconst_2
    //   26: irem
    //   27: ifeq +6 -> 33
    //   30: goto +236 -> 266
    //   33: goto +274 -> 307
    //   36: iload_3
    //   37: iload_2
    //   38: if_icmpge +6 -> 44
    //   41: goto +218 -> 259
    //   44: goto +229 -> 273
    //   47: goto -11 -> 36
    //   50: goto +123 -> 173
    //   53: astore 9
    //   55: aload 9
    //   57: athrow
    //   58: aload 9
    //   60: iload_3
    //   61: getstatic 86	o/Ey:ˏ	[C
    //   64: iload_0
    //   65: iload_3
    //   66: ishr
    //   67: caload
    //   68: i2l
    //   69: iload_3
    //   70: i2l
    //   71: getstatic 25	o/Ey:ˊ	J
    //   74: lrem
    //   75: lsub
    //   76: iload_1
    //   77: i2l
    //   78: lsub
    //   79: l2i
    //   80: i2c
    //   81: castore
    //   82: iload_3
    //   83: bipush 59
    //   85: iadd
    //   86: istore_3
    //   87: goto +41 -> 128
    //   90: iconst_1
    //   91: istore 4
    //   93: iload 4
    //   95: tableswitch	default:+21->116, 0:+-92->3, 1:+30->125
    //   116: goto -113 -> 3
    //   119: iconst_0
    //   120: istore 4
    //   122: goto -29 -> 93
    //   125: goto -89 -> 36
    //   128: getstatic 21	o/Ey:ॱ	I
    //   131: bipush 107
    //   133: iadd
    //   134: istore 4
    //   136: iload 4
    //   138: sipush 128
    //   141: irem
    //   142: putstatic 19	o/Ey:ˋ	I
    //   145: iload 4
    //   147: iconst_2
    //   148: irem
    //   149: ifeq +6 -> 155
    //   152: goto -33 -> 119
    //   155: goto -65 -> 90
    //   158: astore 9
    //   160: aload 9
    //   162: athrow
    //   163: new 92	java/lang/String
    //   166: dup
    //   167: aload 9
    //   169: invokespecial 96	java/lang/String:<init>	([C)V
    //   172: areturn
    //   173: iload_2
    //   174: newarray char
    //   176: astore 9
    //   178: iconst_0
    //   179: istore_3
    //   180: goto -133 -> 47
    //   183: getstatic 86	o/Ey:ˏ	[C
    //   186: iload_0
    //   187: iload_3
    //   188: iadd
    //   189: caload
    //   190: istore 4
    //   192: iload 4
    //   194: i2l
    //   195: lstore 5
    //   197: iload_3
    //   198: i2l
    //   199: lstore 7
    //   201: aload 9
    //   203: iload_3
    //   204: lload 5
    //   206: lload 7
    //   208: getstatic 25	o/Ey:ˊ	J
    //   211: lmul
    //   212: lxor
    //   213: iload_1
    //   214: i2l
    //   215: lxor
    //   216: l2i
    //   217: i2c
    //   218: castore
    //   219: iload_3
    //   220: iconst_1
    //   221: iadd
    //   222: istore_3
    //   223: goto -95 -> 128
    //   226: iload 4
    //   228: lookupswitch	default:+28->256, 41:+-170->58, 59:+-45->183
    //   256: goto -198 -> 58
    //   259: bipush 24
    //   261: istore 4
    //   263: goto +14 -> 277
    //   266: bipush 41
    //   268: istore 4
    //   270: goto -44 -> 226
    //   273: bipush 11
    //   275: istore 4
    //   277: iload 4
    //   279: lookupswitch	default:+25->304, 11:+-116->163, 24:+-273->6
    //   304: goto -298 -> 6
    //   307: bipush 59
    //   309: istore 4
    //   311: goto -85 -> 226
    // Local variable table:
    //   start	length	slot	name	signature
    //   0	314	0	paramInt1	int
    //   0	314	1	paramChar	char
    //   0	314	2	paramInt2	int
    //   36	187	3	i	int
    //   12	298	4	j	int
    //   195	10	5	l1	long
    //   199	8	7	l2	long
    //   53	6	9	localException1	Exception
    //   158	10	9	localException2	Exception
    //   176	26	9	arrayOfChar	char[]
    // Exception table:
    //   from	to	target	type
    //   128	136	53	java/lang/Exception
    //   136	145	53	java/lang/Exception
    //   6	23	158	java/lang/Exception
    //   183	192	158	java/lang/Exception
    //   201	219	158	java/lang/Exception
  }
  
  /* Error */
  public boolean equals(Object paramObject)
  {
    // Byte code:
    //   0: goto +145 -> 145
    //   3: getstatic 19	o/Ey:ˋ	I
    //   6: bipush 109
    //   8: iadd
    //   9: istore_2
    //   10: iload_2
    //   11: sipush 128
    //   14: irem
    //   15: putstatic 21	o/Ey:ॱ	I
    //   18: iload_2
    //   19: iconst_2
    //   20: irem
    //   21: ifne +6 -> 27
    //   24: goto +59 -> 83
    //   27: goto +225 -> 252
    //   30: iconst_1
    //   31: ireturn
    //   32: bipush 40
    //   34: istore_2
    //   35: goto +66 -> 101
    //   38: aload_0
    //   39: getfield 100	o/Ey:tokenExpiry	Ljava/lang/String;
    //   42: aload_1
    //   43: getfield 100	o/Ey:tokenExpiry	Ljava/lang/String;
    //   46: invokestatic 105	o/vq:ˊ	(Ljava/lang/Object;Ljava/lang/Object;)Z
    //   49: ifeq +6 -> 55
    //   52: goto -22 -> 30
    //   55: goto +93 -> 148
    //   58: aload_1
    //   59: checkcast 2	o/Ey
    //   62: astore_1
    //   63: aload_0
    //   64: getfield 107	o/Ey:tokenPanSuffix	Ljava/lang/String;
    //   67: aload_1
    //   68: getfield 107	o/Ey:tokenPanSuffix	Ljava/lang/String;
    //   71: invokestatic 105	o/vq:ˊ	(Ljava/lang/Object;Ljava/lang/Object;)Z
    //   74: ifeq +6 -> 80
    //   77: goto +101 -> 178
    //   80: goto +68 -> 148
    //   83: bipush 71
    //   85: iconst_0
    //   86: idiv
    //   87: istore_2
    //   88: iconst_0
    //   89: ireturn
    //   90: aload_0
    //   91: aload_1
    //   92: if_acmpeq +6 -> 98
    //   95: goto +165 -> 260
    //   98: goto -68 -> 30
    //   101: iload_2
    //   102: lookupswitch	default:+26->128, 23:+35->137, 40:+-12->90
    //   128: goto +9 -> 137
    //   131: goto -93 -> 38
    //   134: goto +98 -> 232
    //   137: new 109	java/lang/NullPointerException
    //   140: dup
    //   141: invokespecial 111	java/lang/NullPointerException:<init>	()V
    //   144: athrow
    //   145: goto +6 -> 151
    //   148: goto -145 -> 3
    //   151: getstatic 21	o/Ey:ॱ	I
    //   154: bipush 91
    //   156: iadd
    //   157: istore_2
    //   158: iload_2
    //   159: sipush 128
    //   162: irem
    //   163: putstatic 19	o/Ey:ˋ	I
    //   166: iload_2
    //   167: iconst_2
    //   168: irem
    //   169: ifeq +6 -> 175
    //   172: goto +82 -> 254
    //   175: goto -143 -> 32
    //   178: getstatic 21	o/Ey:ॱ	I
    //   181: bipush 67
    //   183: iadd
    //   184: istore_2
    //   185: iload_2
    //   186: sipush 128
    //   189: irem
    //   190: putstatic 19	o/Ey:ˋ	I
    //   193: iload_2
    //   194: iconst_2
    //   195: irem
    //   196: ifeq +6 -> 202
    //   199: goto -65 -> 134
    //   202: goto +30 -> 232
    //   205: getstatic 21	o/Ey:ॱ	I
    //   208: bipush 59
    //   210: iadd
    //   211: istore_2
    //   212: iload_2
    //   213: sipush 128
    //   216: irem
    //   217: putstatic 19	o/Ey:ˋ	I
    //   220: iload_2
    //   221: iconst_2
    //   222: irem
    //   223: ifeq +6 -> 229
    //   226: goto -95 -> 131
    //   229: goto -191 -> 38
    //   232: aload_0
    //   233: getfield 113	o/Ey:accountPanSuffix	Ljava/lang/String;
    //   236: aload_1
    //   237: getfield 113	o/Ey:accountPanSuffix	Ljava/lang/String;
    //   240: invokestatic 105	o/vq:ˊ	(Ljava/lang/Object;Ljava/lang/Object;)Z
    //   243: ifeq +6 -> 249
    //   246: goto -41 -> 205
    //   249: goto -101 -> 148
    //   252: iconst_0
    //   253: ireturn
    //   254: bipush 23
    //   256: istore_2
    //   257: goto -156 -> 101
    //   260: aload_1
    //   261: instanceof 2
    //   264: ifeq +6 -> 270
    //   267: goto -209 -> 58
    //   270: goto -122 -> 148
    //   273: astore_1
    //   274: aload_1
    //   275: athrow
    // Local variable table:
    //   start	length	slot	name	signature
    //   0	276	0	this	Ey
    //   0	276	1	paramObject	Object
    //   9	248	2	i	int
    // Exception table:
    //   from	to	target	type
    //   3	10	273	java/lang/Exception
    //   10	18	273	java/lang/Exception
  }
  
  public int hashCode()
  {
    break label8;
    int i = 1;
    break label201;
    label8:
    break label77;
    String str1;
    i = str1.hashCode();
    break label107;
    i = 0;
    break label201;
    label25:
    int j;
    int k;
    label37:
    label63:
    label77:
    label104:
    for (;;)
    {
      return (i * 31 + j) * 31 + k;
      switch (j)
      {
      default: 
        break label265;
        i = str1.hashCode();
        j = 77 / 0;
        break label107;
        try
        {
          str1 = this.tokenPanSuffix;
          if (str1 != null) {
            break;
          }
        }
        catch (Exception localException)
        {
          throw localException;
        }
      case 0: 
        j = 0;
        break label138;
      }
    }
    label107:
    String str2 = this.accountPanSuffix;
    if (str2 == null) {
      break label133;
    }
    for (;;)
    {
      j = str2.hashCode();
      break label138;
      label133:
      j = 0;
      break label37;
      label138:
      str2 = this.tokenExpiry;
      if (str2 == null) {
        break label227;
      }
      for (;;)
      {
        i = 0;
        break label107;
        k = str2.hashCode();
        break label232;
        i = ॱ + 7;
        ˋ = i % 128;
        if (i % 2 != 0) {
          break label63;
        }
        break;
        j = 1;
        break label37;
        label201:
        switch (i)
        {
        }
      }
      label227:
      k = 0;
      break label25;
      label232:
      int m = ॱ + 25;
      ˋ = m % 128;
      if (m % 2 != 0) {
        break label104;
      }
      break label25;
      label265:
      do
      {
        break;
        j = ˋ + 1;
        ॱ = j % 128;
      } while (j % 2 == 0);
    }
  }
  
  public String toString()
  {
    String str;
    for (;;)
    {
      int i = ॱ + 35;
      ˋ = i % 128;
      if (i % 2 != 0) {
        break;
      }
      return str;
      str = ˏ(0, '\000', 25).intern() + this.tokenPanSuffix + ˏ(25, '\000', 19).intern() + this.accountPanSuffix + ˏ(44, 50069, 14).intern() + this.tokenExpiry + ˏ(58, 51765, 1).intern();
    }
    return str;
  }
  
  /* Error */
  public final String ˊ()
  {
    // Byte code:
    //   0: goto +14 -> 14
    //   3: astore_2
    //   4: aload_2
    //   5: athrow
    //   6: iconst_0
    //   7: istore_1
    //   8: goto +38 -> 46
    //   11: astore_2
    //   12: aload_2
    //   13: athrow
    //   14: goto +56 -> 70
    //   17: getstatic 19	o/Ey:ˋ	I
    //   20: istore_1
    //   21: iload_1
    //   22: bipush 25
    //   24: iadd
    //   25: istore_1
    //   26: iload_1
    //   27: sipush 128
    //   30: irem
    //   31: putstatic 21	o/Ey:ॱ	I
    //   34: iload_1
    //   35: iconst_2
    //   36: irem
    //   37: ifne +6 -> 43
    //   40: goto -34 -> 6
    //   43: goto +72 -> 115
    //   46: iload_1
    //   47: tableswitch	default:+21->68, 0:+50->97, 1:+21->68
    //   68: aload_2
    //   69: areturn
    //   70: getstatic 21	o/Ey:ॱ	I
    //   73: bipush 31
    //   75: iadd
    //   76: istore_1
    //   77: iload_1
    //   78: sipush 128
    //   81: irem
    //   82: putstatic 19	o/Ey:ˋ	I
    //   85: iload_1
    //   86: iconst_2
    //   87: irem
    //   88: ifeq +6 -> 94
    //   91: goto +21 -> 112
    //   94: goto +10 -> 104
    //   97: bipush 47
    //   99: iconst_0
    //   100: idiv
    //   101: istore_1
    //   102: aload_2
    //   103: areturn
    //   104: aload_0
    //   105: getfield 107	o/Ey:tokenPanSuffix	Ljava/lang/String;
    //   108: astore_2
    //   109: goto -92 -> 17
    //   112: goto -8 -> 104
    //   115: iconst_1
    //   116: istore_1
    //   117: goto -71 -> 46
    // Local variable table:
    //   start	length	slot	name	signature
    //   0	120	0	this	Ey
    //   7	110	1	i	int
    //   3	2	2	localException1	Exception
    //   11	92	2	localException2	Exception
    //   108	1	2	str	String
    // Exception table:
    //   from	to	target	type
    //   26	34	3	java/lang/Exception
    //   17	21	11	java/lang/Exception
  }
}
