package o;

import android.content.Context;
import android.util.Log;
import ro.btrl.business.general.dao.NotificationHistoryDao;
import ro.btrl.business.general.dao.P2PSettingsDao;
import ro.btrl.business.general.dao.TermsAndConditionsDao;
import ro.btrl.business.general.dao.TransactionDetailsDao;

public class Fa
  extends zB
{
  public static final int SCHEMA_VERSION = 2;
  
  public Fa(zO paramZO)
  {
    super(paramZO, 2);
    ˎ(NotificationHistoryDao.class);
    ˎ(P2PSettingsDao.class);
    ˎ(TransactionDetailsDao.class);
    ˎ(TermsAndConditionsDao.class);
  }
  
  public static void ˋ(zO paramZO, boolean paramBoolean)
  {
    NotificationHistoryDao.ˏ(paramZO, paramBoolean);
    P2PSettingsDao.ˏ(paramZO, paramBoolean);
    TransactionDetailsDao.ˋ(paramZO, paramBoolean);
    TermsAndConditionsDao.ॱ(paramZO, paramBoolean);
  }
  
  public static void ॱ(zO paramZO, boolean paramBoolean)
  {
    NotificationHistoryDao.ˎ(paramZO, paramBoolean);
    P2PSettingsDao.ॱ(paramZO, paramBoolean);
    TransactionDetailsDao.ॱ(paramZO, paramBoolean);
    TermsAndConditionsDao.ˎ(paramZO, paramBoolean);
  }
  
  public Fb ˏ()
  {
    return new Fb(this.db, zZ.ˋ, this.daoConfigMap);
  }
  
  public static class if
    extends Fa.ˋ
  {
    private static int ʼ;
    private static int ˊ = -1299071747;
    private static short[] ˋ;
    private static int ˎ;
    private static int ˏ = 302300997;
    private static byte[] ॱ;
    private static int ॱॱ = 0;
    
    static
    {
      ʼ = 1;
      ˎ = 68;
      ॱ = new byte[] { -72, -89, -128, -77, -86, -99, -75, -107, -30, -23, -39, -28, -16, -46, 57, -106, -31, -32, -17, 41, -94, -41, -21, -32, -24, -45, 54, -100, -36, -24, -24, -26, -46, -18, -38, -2, -58, 16, 105, -112, 123, -116, -125, 111, -42, 54, -126, -115, -61, 59, 123, -121, 123, -126, -125, 127, -112, -58, 41, -103, -60, 0, 0, 0, 0 };
    }
    
    public if(Context paramContext, String paramString) {}
    
    /* Error */
    private static String ˋ(short paramShort, int paramInt1, byte paramByte, int paramInt2, int paramInt3)
    {
      // Byte code:
      //   0: goto +482 -> 482
      //   3: astore 9
      //   5: aload 9
      //   7: athrow
      //   8: iconst_0
      //   9: istore 6
      //   11: goto +560 -> 571
      //   14: goto +294 -> 308
      //   17: iload 4
      //   19: ifle +6 -> 25
      //   22: goto +567 -> 589
      //   25: goto +273 -> 298
      //   28: iload 4
      //   30: tableswitch	default:+22->52, 0:+353->383, 1:+153->183
      //   52: goto +331 -> 383
      //   55: aload 9
      //   57: iload 5
      //   59: invokevirtual 97	java/lang/StringBuilder:append	(C)Ljava/lang/StringBuilder;
      //   62: pop
      //   63: iload_3
      //   64: iconst_1
      //   65: iadd
      //   66: istore 6
      //   68: goto +85 -> 153
      //   71: iload 5
      //   73: istore 7
      //   75: iload 6
      //   77: istore_3
      //   78: goto +392 -> 470
      //   81: iconst_0
      //   82: istore 4
      //   84: goto -56 -> 28
      //   87: iload 7
      //   89: istore 4
      //   91: iload 8
      //   93: tableswitch	default:+23->116, 0:+33->126, 1:+-76->17
      //   116: goto +10 -> 126
      //   119: bipush 50
      //   121: istore 6
      //   123: goto +418 -> 541
      //   126: getstatic 77	o/Fa$if:ॱ	[B
      //   129: ifnull +6 -> 135
      //   132: goto +101 -> 233
      //   135: goto +128 -> 263
      //   138: aload 9
      //   140: invokevirtual 101	java/lang/StringBuilder:toString	()Ljava/lang/String;
      //   143: areturn
      //   144: goto +559 -> 703
      //   147: iconst_0
      //   148: istore 8
      //   150: goto -63 -> 87
      //   153: getstatic 21	o/Fa$if:ॱॱ	I
      //   156: bipush 89
      //   158: iadd
      //   159: istore_3
      //   160: iload_3
      //   161: sipush 128
      //   164: irem
      //   165: putstatic 23	o/Fa$if:ʼ	I
      //   168: iload_3
      //   169: iconst_2
      //   170: irem
      //   171: ifne +6 -> 177
      //   174: goto +53 -> 227
      //   177: goto +419 -> 596
      //   180: goto +305 -> 485
      //   183: iconst_0
      //   184: istore 4
      //   186: goto +200 -> 386
      //   189: new 93	java/lang/StringBuilder
      //   192: dup
      //   193: invokespecial 103	java/lang/StringBuilder:<init>	()V
      //   196: astore 9
      //   198: getstatic 25	o/Fa$if:ˎ	I
      //   201: iload 4
      //   203: iadd
      //   204: istore 4
      //   206: iload 4
      //   208: istore 7
      //   210: iload 4
      //   212: iconst_m1
      //   213: if_icmpne +6 -> 219
      //   216: goto +215 -> 431
      //   219: goto -211 -> 8
      //   222: astore 9
      //   224: aload 9
      //   226: athrow
      //   227: bipush 32
      //   229: istore_3
      //   230: goto +94 -> 324
      //   233: getstatic 23	o/Fa$if:ʼ	I
      //   236: bipush 57
      //   238: iadd
      //   239: istore 4
      //   241: iload 4
      //   243: sipush 128
      //   246: irem
      //   247: putstatic 21	o/Fa$if:ॱॱ	I
      //   250: iload 4
      //   252: iconst_2
      //   253: irem
      //   254: ifeq +6 -> 260
      //   257: goto -77 -> 180
      //   260: goto +225 -> 485
      //   263: getstatic 105	o/Fa$if:ˋ	[S
      //   266: astore 10
      //   268: getstatic 83	o/Fa$if:ˏ	I
      //   271: istore 4
      //   273: aload 10
      //   275: iload 4
      //   277: iload_1
      //   278: iadd
      //   279: saload
      //   280: istore 4
      //   282: getstatic 25	o/Fa$if:ˎ	I
      //   285: istore 7
      //   287: iload 4
      //   289: iload 7
      //   291: iadd
      //   292: i2s
      //   293: istore 4
      //   295: goto +420 -> 715
      //   298: bipush 77
      //   300: istore 7
      //   302: goto +370 -> 672
      //   305: goto +156 -> 461
      //   308: getstatic 83	o/Fa$if:ˏ	I
      //   311: istore 7
      //   313: iload 6
      //   315: ifeq +6 -> 321
      //   318: goto +290 -> 608
      //   321: goto +56 -> 377
      //   324: iload_3
      //   325: lookupswitch	default:+27->352, 32:+42->367, 92:+-254->71
      //   352: goto +15 -> 367
      //   355: iconst_1
      //   356: istore 4
      //   358: goto -330 -> 28
      //   361: iconst_1
      //   362: istore 8
      //   364: goto -277 -> 87
      //   367: iload 5
      //   369: istore 7
      //   371: iload 6
      //   373: istore_3
      //   374: goto +96 -> 470
      //   377: iconst_1
      //   378: istore 6
      //   380: goto +365 -> 745
      //   383: iconst_1
      //   384: istore 4
      //   386: iload 4
      //   388: istore 6
      //   390: goto +181 -> 571
      //   393: iload_1
      //   394: iload 4
      //   396: iadd
      //   397: iconst_2
      //   398: isub
      //   399: iload 7
      //   401: iadd
      //   402: iload 6
      //   404: iadd
      //   405: istore_1
      //   406: getstatic 80	o/Fa$if:ˊ	I
      //   409: iload_3
      //   410: iadd
      //   411: i2c
      //   412: istore 5
      //   414: aload 9
      //   416: iload 5
      //   418: invokevirtual 97	java/lang/StringBuilder:append	(C)Ljava/lang/StringBuilder;
      //   421: pop
      //   422: iconst_1
      //   423: istore_3
      //   424: iload 5
      //   426: istore 7
      //   428: goto +42 -> 470
      //   431: getstatic 21	o/Fa$if:ॱॱ	I
      //   434: bipush 37
      //   436: iadd
      //   437: istore 4
      //   439: iload 4
      //   441: sipush 128
      //   444: irem
      //   445: putstatic 23	o/Fa$if:ʼ	I
      //   448: iload 4
      //   450: iconst_2
      //   451: irem
      //   452: ifne +6 -> 458
      //   455: goto -100 -> 355
      //   458: goto -377 -> 81
      //   461: goto -444 -> 17
      //   464: iconst_1
      //   465: istore 6
      //   467: goto -74 -> 393
      //   470: iload_3
      //   471: iload 4
      //   473: if_icmpge +6 -> 479
      //   476: goto +106 -> 582
      //   479: goto -360 -> 119
      //   482: goto -293 -> 189
      //   485: getstatic 77	o/Fa$if:ॱ	[B
      //   488: getstatic 83	o/Fa$if:ˏ	I
      //   491: iload_1
      //   492: iadd
      //   493: baload
      //   494: getstatic 25	o/Fa$if:ˎ	I
      //   497: iadd
      //   498: i2b
      //   499: istore 4
      //   501: goto -484 -> 17
      //   504: iload 6
      //   506: istore_1
      //   507: goto -452 -> 55
      //   510: getstatic 105	o/Fa$if:ˋ	[S
      //   513: astore 10
      //   515: iload_1
      //   516: iconst_1
      //   517: isub
      //   518: istore 6
      //   520: aload 10
      //   522: iload_1
      //   523: saload
      //   524: iload_0
      //   525: iadd
      //   526: i2s
      //   527: iload_2
      //   528: ixor
      //   529: iload 7
      //   531: iadd
      //   532: i2c
      //   533: istore 5
      //   535: iload 6
      //   537: istore_1
      //   538: goto -483 -> 55
      //   541: iload 6
      //   543: lookupswitch	default:+25->568, 50:+-405->138, 82:+228->771
      //   568: goto -430 -> 138
      //   571: iload 6
      //   573: ifeq +6 -> 579
      //   576: goto -429 -> 147
      //   579: goto -218 -> 361
      //   582: bipush 82
      //   584: istore 6
      //   586: goto -45 -> 541
      //   589: bipush 34
      //   591: istore 7
      //   593: goto +79 -> 672
      //   596: bipush 92
      //   598: istore_3
      //   599: goto -275 -> 324
      //   602: iconst_0
      //   603: istore 6
      //   605: goto -212 -> 393
      //   608: iconst_0
      //   609: istore 6
      //   611: goto +134 -> 745
      //   614: getstatic 77	o/Fa$if:ॱ	[B
      //   617: astore 10
      //   619: iload_1
      //   620: iconst_1
      //   621: isub
      //   622: istore 6
      //   624: aload 10
      //   626: iload_1
      //   627: baload
      //   628: iload_0
      //   629: iadd
      //   630: i2b
      //   631: iload_2
      //   632: ixor
      //   633: iload 7
      //   635: iadd
      //   636: i2c
      //   637: istore 5
      //   639: goto -135 -> 504
      //   642: getstatic 23	o/Fa$if:ʼ	I
      //   645: bipush 75
      //   647: iadd
      //   648: istore 7
      //   650: iload 7
      //   652: sipush 128
      //   655: irem
      //   656: putstatic 21	o/Fa$if:ॱॱ	I
      //   659: iload 7
      //   661: iconst_2
      //   662: irem
      //   663: ifeq +6 -> 669
      //   666: goto -652 -> 14
      //   669: goto -361 -> 308
      //   672: iload 7
      //   674: lookupswitch	default:+26->700, 34:+-32->642, 77:+-536->138
      //   700: goto -562 -> 138
      //   703: getstatic 77	o/Fa$if:ॱ	[B
      //   706: ifnull +6 -> 712
      //   709: goto -95 -> 614
      //   712: goto -202 -> 510
      //   715: getstatic 21	o/Fa$if:ॱॱ	I
      //   718: bipush 75
      //   720: iadd
      //   721: istore 7
      //   723: iload 7
      //   725: sipush 128
      //   728: irem
      //   729: putstatic 23	o/Fa$if:ʼ	I
      //   732: iload 7
      //   734: iconst_2
      //   735: irem
      //   736: ifne +6 -> 742
      //   739: goto -434 -> 305
      //   742: goto -281 -> 461
      //   745: iload 6
      //   747: tableswitch	default:+21->768, 0:+-283->464, 1:+-145->602
      //   768: goto -166 -> 602
      //   771: getstatic 23	o/Fa$if:ʼ	I
      //   774: bipush 109
      //   776: iadd
      //   777: istore 6
      //   779: iload 6
      //   781: sipush 128
      //   784: irem
      //   785: putstatic 21	o/Fa$if:ॱॱ	I
      //   788: iload 6
      //   790: iconst_2
      //   791: irem
      //   792: ifeq +6 -> 798
      //   795: goto -651 -> 144
      //   798: goto -95 -> 703
      // Local variable table:
      //   start	length	slot	name	signature
      //   0	801	0	paramShort	short
      //   0	801	1	paramInt1	int
      //   0	801	2	paramByte	byte
      //   0	801	3	paramInt2	int
      //   0	801	4	paramInt3	int
      //   57	581	5	i	int
      //   9	783	6	j	int
      //   73	15	7	k	int
      //   208	528	7	m	int
      //   91	272	8	n	int
      //   3	136	9	localException1	Exception
      //   196	1	9	localStringBuilder	StringBuilder
      //   222	193	9	localException2	Exception
      //   266	359	10	localObject	Object
      // Exception table:
      //   from	to	target	type
      //   160	168	3	java/lang/Exception
      //   153	160	222	java/lang/Exception
      //   160	168	222	java/lang/Exception
      //   263	268	222	java/lang/Exception
      //   268	273	222	java/lang/Exception
      //   282	287	222	java/lang/Exception
    }
    
    /* Error */
    public void ˊ(zO paramZO, int paramInt1, int paramInt2)
    {
      // Byte code:
      //   0: goto +187 -> 187
      //   3: astore_1
      //   4: aload_1
      //   5: athrow
      //   6: return
      //   7: bipush 86
      //   9: ldc 107
      //   11: iconst_0
      //   12: ldc 108
      //   14: bipush -60
      //   16: invokestatic 110	o/Fa$if:ˋ	(SIBII)Ljava/lang/String;
      //   19: invokevirtual 115	java/lang/String:intern	()Ljava/lang/String;
      //   22: new 93	java/lang/StringBuilder
      //   25: dup
      //   26: invokespecial 103	java/lang/StringBuilder:<init>	()V
      //   29: bipush 29
      //   31: ldc 116
      //   33: iconst_0
      //   34: ldc 117
      //   36: bipush -38
      //   38: invokestatic 110	o/Fa$if:ˋ	(SIBII)Ljava/lang/String;
      //   41: invokevirtual 115	java/lang/String:intern	()Ljava/lang/String;
      //   44: invokevirtual 120	java/lang/StringBuilder:append	(Ljava/lang/String;)Ljava/lang/StringBuilder;
      //   47: iload_2
      //   48: invokevirtual 123	java/lang/StringBuilder:append	(I)Ljava/lang/StringBuilder;
      //   51: bipush -21
      //   53: ldc 124
      //   55: iconst_0
      //   56: ldc 125
      //   58: bipush -64
      //   60: invokestatic 110	o/Fa$if:ˋ	(SIBII)Ljava/lang/String;
      //   63: invokevirtual 115	java/lang/String:intern	()Ljava/lang/String;
      //   66: invokevirtual 120	java/lang/StringBuilder:append	(Ljava/lang/String;)Ljava/lang/StringBuilder;
      //   69: iload_3
      //   70: invokevirtual 123	java/lang/StringBuilder:append	(I)Ljava/lang/StringBuilder;
      //   73: bipush 126
      //   75: ldc 126
      //   77: iconst_0
      //   78: ldc 125
      //   80: bipush -45
      //   82: invokestatic 110	o/Fa$if:ˋ	(SIBII)Ljava/lang/String;
      //   85: invokevirtual 115	java/lang/String:intern	()Ljava/lang/String;
      //   88: invokevirtual 120	java/lang/StringBuilder:append	(Ljava/lang/String;)Ljava/lang/StringBuilder;
      //   91: invokevirtual 101	java/lang/StringBuilder:toString	()Ljava/lang/String;
      //   94: invokestatic 132	android/util/Log:i	(Ljava/lang/String;Ljava/lang/String;)I
      //   97: pop
      //   98: aload_1
      //   99: iconst_1
      //   100: invokestatic 135	o/Fa:ॱ	(Lo/zO;Z)V
      //   103: aload_0
      //   104: aload_1
      //   105: invokevirtual 138	o/Fa$if:ˊ	(Lo/zO;)V
      //   108: goto +39 -> 147
      //   111: iload_2
      //   112: lookupswitch	default:+28->140, 54:+62->174, 61:+-106->6
      //   140: return
      //   141: bipush 54
      //   143: istore_2
      //   144: goto -33 -> 111
      //   147: getstatic 21	o/Fa$if:ॱॱ	I
      //   150: bipush 19
      //   152: iadd
      //   153: istore_2
      //   154: iload_2
      //   155: sipush 128
      //   158: irem
      //   159: putstatic 23	o/Fa$if:ʼ	I
      //   162: iload_2
      //   163: iconst_2
      //   164: irem
      //   165: ifne +6 -> 171
      //   168: goto -27 -> 141
      //   171: goto +10 -> 181
      //   174: aconst_null
      //   175: arraylength
      //   176: istore_2
      //   177: return
      //   178: astore_1
      //   179: aload_1
      //   180: athrow
      //   181: bipush 61
      //   183: istore_2
      //   184: goto -73 -> 111
      //   187: goto -180 -> 7
      // Local variable table:
      //   start	length	slot	name	signature
      //   0	190	0	this	if
      //   0	190	1	paramZO	zO
      //   0	190	2	paramInt1	int
      //   0	190	3	paramInt2	int
      // Exception table:
      //   from	to	target	type
      //   154	162	3	java/lang/Exception
      //   147	154	178	java/lang/Exception
      //   154	162	178	java/lang/Exception
    }
  }
  
  public static abstract class ˋ
    extends zN
  {
    private static int ˊ = 0;
    private static long ˎ = 7796183361604921757L;
    private static int ॱ = 1;
    
    public ˋ(Context paramContext, String paramString)
    {
      super(paramString, 2);
    }
    
    /* Error */
    private static String ˏ(char[] paramArrayOfChar)
    {
      // Byte code:
      //   0: goto +175 -> 175
      //   3: astore_0
      //   4: aload_0
      //   5: athrow
      //   6: iconst_1
      //   7: istore_2
      //   8: goto +142 -> 150
      //   11: bipush 46
      //   13: istore_1
      //   14: goto +218 -> 232
      //   17: getstatic 18	o/Fa$ˋ:ॱ	I
      //   20: bipush 41
      //   22: iadd
      //   23: istore_1
      //   24: iload_1
      //   25: sipush 128
      //   28: irem
      //   29: putstatic 16	o/Fa$ˋ:ˊ	I
      //   32: iload_1
      //   33: iconst_2
      //   34: irem
      //   35: ifeq +6 -> 41
      //   38: goto +5 -> 43
      //   41: aload_0
      //   42: areturn
      //   43: bipush 36
      //   45: iconst_0
      //   46: idiv
      //   47: istore_1
      //   48: aload_0
      //   49: areturn
      //   50: aload_0
      //   51: iload_1
      //   52: caload
      //   53: aload_0
      //   54: iload_1
      //   55: iconst_4
      //   56: irem
      //   57: caload
      //   58: ixor
      //   59: i2l
      //   60: lstore_3
      //   61: iload_1
      //   62: iconst_4
      //   63: isub
      //   64: i2l
      //   65: lstore 5
      //   67: getstatic 22	o/Fa$ˋ:ˎ	J
      //   70: lstore 7
      //   72: aload_0
      //   73: iload_1
      //   74: lload_3
      //   75: lload 5
      //   77: lload 7
      //   79: lmul
      //   80: lxor
      //   81: l2i
      //   82: i2c
      //   83: castore
      //   84: iload_1
      //   85: iconst_1
      //   86: iadd
      //   87: istore_1
      //   88: goto +205 -> 293
      //   91: getstatic 16	o/Fa$ˋ:ˊ	I
      //   94: bipush 71
      //   96: iadd
      //   97: istore_2
      //   98: iload_2
      //   99: sipush 128
      //   102: irem
      //   103: putstatic 18	o/Fa$ˋ:ॱ	I
      //   106: iload_2
      //   107: iconst_2
      //   108: irem
      //   109: ifne +6 -> 115
      //   112: goto +66 -> 178
      //   115: goto -109 -> 6
      //   118: bipush 99
      //   120: istore_1
      //   121: goto +111 -> 232
      //   124: getstatic 22	o/Fa$ˋ:ˎ	J
      //   127: aload_0
      //   128: invokestatic 37	o/oL:ˋ	(J[C)[C
      //   131: astore_0
      //   132: iconst_5
      //   133: istore_1
      //   134: goto +159 -> 293
      //   137: getstatic 22	o/Fa$ˋ:ˎ	J
      //   140: aload_0
      //   141: invokestatic 37	o/oL:ˋ	(J[C)[C
      //   144: astore_0
      //   145: iconst_4
      //   146: istore_1
      //   147: goto +146 -> 293
      //   150: iload_2
      //   151: tableswitch	default:+21->172, 0:+32->183, 1:+-101->50
      //   172: goto -122 -> 50
      //   175: goto +91 -> 266
      //   178: iconst_0
      //   179: istore_2
      //   180: goto -30 -> 150
      //   183: aload_0
      //   184: iload_1
      //   185: aload_0
      //   186: iload_1
      //   187: caload
      //   188: aload_0
      //   189: iload_1
      //   190: iconst_2
      //   191: ishl
      //   192: caload
      //   193: ixor
      //   194: i2l
      //   195: iload_1
      //   196: iconst_3
      //   197: isub
      //   198: i2l
      //   199: getstatic 22	o/Fa$ˋ:ˎ	J
      //   202: lxor
      //   203: ladd
      //   204: l2i
      //   205: i2c
      //   206: castore
      //   207: iload_1
      //   208: bipush 108
      //   210: iadd
      //   211: istore_1
      //   212: goto +81 -> 293
      //   215: new 39	java/lang/String
      //   218: dup
      //   219: aload_0
      //   220: iconst_4
      //   221: aload_0
      //   222: arraylength
      //   223: iconst_4
      //   224: isub
      //   225: invokespecial 42	java/lang/String:<init>	([CII)V
      //   228: astore_0
      //   229: goto -212 -> 17
      //   232: iload_1
      //   233: lookupswitch	default:+27->260, 46:+-96->137, 99:+-109->124
      //   260: goto -136 -> 124
      //   263: astore_0
      //   264: aload_0
      //   265: athrow
      //   266: getstatic 18	o/Fa$ˋ:ॱ	I
      //   269: bipush 101
      //   271: iadd
      //   272: istore_1
      //   273: iload_1
      //   274: sipush 128
      //   277: irem
      //   278: putstatic 16	o/Fa$ˋ:ˊ	I
      //   281: iload_1
      //   282: iconst_2
      //   283: irem
      //   284: ifeq +6 -> 290
      //   287: goto -169 -> 118
      //   290: goto -279 -> 11
      //   293: iload_1
      //   294: aload_0
      //   295: arraylength
      //   296: if_icmpge +6 -> 302
      //   299: goto -208 -> 91
      //   302: goto -87 -> 215
      // Local variable table:
      //   start	length	slot	name	signature
      //   0	305	0	paramArrayOfChar	char[]
      //   13	284	1	i	int
      //   7	173	2	j	int
      //   60	15	3	l1	long
      //   65	11	5	l2	long
      //   70	8	7	l3	long
      // Exception table:
      //   from	to	target	type
      //   266	273	3	java/lang/Exception
      //   273	281	3	java/lang/Exception
      //   67	72	263	java/lang/Exception
    }
    
    public void ˊ(zO paramZO)
    {
      break label372;
      int i;
      for (;;)
      {
        i = 71;
        break;
        i = ˊ + 71;
        ॱ = i % 128;
        if (i % 2 != 0) {
          break label434;
        }
      }
      for (;;)
      {
        try
        {
          str = ˏ(new char[] { 22777, 22686, 16701, -20228, 23704, -5934, -7261, -24534, -285, 4456, 18707, -100 });
        }
        catch (Exception paramZO)
        {
          try
          {
            String str = str.intern();
            Log.i(str, ˏ(new char[] { 21825, 21762, 13743, -21022, -26149, -25536, -323, 25965, -3263, 26071, 21538, 15095, 6537, -15522, 3489, -12282, -22927, -22221, -5369, 27080, -13065, 30381, 16538, 3932, 5494, -9171, 16116, -23387, -19564, -23141, -27600, 31266, -10232, 788, 19959, 5041, 26254, -5892, 11032, -22114 }).intern());
            Fa.ˋ(paramZO, false);
            continue;
            label372:
            break;
            i = ˊ + 111;
            ॱ = i % 128;
            if (i % 2 == 0) {
              return;
            }
            return;
          }
          catch (Exception paramZO)
          {
            throw paramZO;
          }
          paramZO = paramZO;
          throw paramZO;
        }
        for (;;)
        {
          switch (i)
          {
          case 1: 
          default: 
            break label439;
            label434:
            i = 1;
          }
        }
        label439:
        Log.i(ˏ(new char[] { 22777, 22686, 16701, -20228, 23704, -5934, -7261, -24534, -285, 4456, 18707, -100 }).intern(), ˏ(new char[] { 21825, 21762, 13743, -21022, -26149, -25536, -323, 25965, -3263, 26071, 21538, 15095, 6537, -15522, 3489, -12282, -22927, -22221, -5369, 27080, -13065, 30381, 16538, 3932, 5494, -9171, 16116, -23387, -19564, -23141, -27600, 31266, -10232, 788, 19959, 5041, 26254, -5892, 11032, -22114 }).intern());
        Fa.ˋ(paramZO, true);
      }
    }
  }
}
