package o;

import java.math.BigDecimal;
import java.util.ArrayList;
import java.util.List;

public final class Fc
{
  private static int ˋ = 0;
  private static char[] ˎ = { 109, 246, 267, 264, 265, 268, 274, 266, 250, 257, 265, 256, 264, 271, 268, 263, 227, 228, 266, 270, 268, 269, 271, 266, 249, 256, 267, 264, 265, 268, 274, 266, 250, 51, 106, 107, 110, 116, 108, 92, 91, 100, 106, 71, 38, 52, 88, 22, 38, 71, 113, 114, 97, 92, 108, 116, 110, 107, 106, 109, 88, 22, 38, 72, 81, 81, 97, 92, 108, 116, 110, 107, 106, 109, 88, 31, 56, 88, 120, 121, 124, 128, 125, 118, 120, 110, 110, 126, 134, 128, 125, 124, 127, 109, 110, 131, 104, 20 };
  private static int ˏ = 1;
  private final if contactSettings;
  private final ˋ languageSettingsDto;
  private final ˊ nfcSettings;
  private final If otpSettings;
  private final List<FP> p2pSettings;
  
  /* Error */
  private static String ॱ(int[] paramArrayOfInt, byte[] paramArrayOfByte, boolean paramBoolean)
  {
    // Byte code:
    //   0: goto +535 -> 535
    //   3: astore_0
    //   4: aload_0
    //   5: athrow
    //   6: aload 9
    //   8: astore_1
    //   9: goto +219 -> 228
    //   12: goto +503 -> 515
    //   15: iload 4
    //   17: tableswitch	default:+23->40, 0:+-11->6, 1:+29->46
    //   40: goto +6 -> 46
    //   43: goto +208 -> 251
    //   46: aload 9
    //   48: iload_3
    //   49: aload_1
    //   50: iload 6
    //   52: iload_3
    //   53: isub
    //   54: iconst_1
    //   55: isub
    //   56: caload
    //   57: castore
    //   58: iload_3
    //   59: iconst_1
    //   60: iadd
    //   61: istore_3
    //   62: goto +101 -> 163
    //   65: getstatic 47	o/Fc:ˏ	I
    //   68: iconst_1
    //   69: iadd
    //   70: istore 5
    //   72: iload 5
    //   74: sipush 128
    //   77: irem
    //   78: putstatic 45	o/Fc:ˋ	I
    //   81: iload 5
    //   83: iconst_2
    //   84: irem
    //   85: ifeq +6 -> 91
    //   88: goto -76 -> 12
    //   91: goto +424 -> 515
    //   94: iload 5
    //   96: tableswitch	default:+24->120, 0:+-31->65, 1:+376->472
    //   120: goto +352 -> 472
    //   123: iload 8
    //   125: ifle +6 -> 131
    //   128: goto +275 -> 403
    //   131: goto +291 -> 422
    //   134: getstatic 45	o/Fc:ˋ	I
    //   137: istore_3
    //   138: iload_3
    //   139: bipush 87
    //   141: iadd
    //   142: istore_3
    //   143: iload_3
    //   144: sipush 128
    //   147: irem
    //   148: putstatic 47	o/Fc:ˏ	I
    //   151: iload_3
    //   152: iconst_2
    //   153: irem
    //   154: ifne +6 -> 160
    //   157: goto +237 -> 394
    //   160: goto +187 -> 347
    //   163: iload_3
    //   164: iload 6
    //   166: if_icmpge +6 -> 172
    //   169: goto +475 -> 644
    //   172: goto +163 -> 335
    //   175: aload 10
    //   177: iload 4
    //   179: caload
    //   180: istore_3
    //   181: iload 4
    //   183: iconst_1
    //   184: iadd
    //   185: istore 4
    //   187: goto +272 -> 459
    //   190: astore_0
    //   191: aload_0
    //   192: athrow
    //   193: iload 6
    //   195: newarray char
    //   197: astore 10
    //   199: iconst_0
    //   200: istore_3
    //   201: iconst_0
    //   202: istore 4
    //   204: goto +255 -> 459
    //   207: goto +368 -> 575
    //   210: aload_1
    //   211: iload_3
    //   212: aload_1
    //   213: iload_3
    //   214: caload
    //   215: aload_0
    //   216: iconst_2
    //   217: iaload
    //   218: isub
    //   219: i2c
    //   220: castore
    //   221: iload_3
    //   222: iconst_1
    //   223: iadd
    //   224: istore_3
    //   225: goto +14 -> 239
    //   228: iload 7
    //   230: ifle +6 -> 236
    //   233: goto +194 -> 427
    //   236: goto +260 -> 496
    //   239: iload_3
    //   240: iload 6
    //   242: if_icmpge +6 -> 248
    //   245: goto -35 -> 210
    //   248: goto +253 -> 501
    //   251: goto +287 -> 538
    //   254: aload_0
    //   255: iconst_0
    //   256: iaload
    //   257: istore_3
    //   258: aload_0
    //   259: iconst_1
    //   260: iaload
    //   261: istore 6
    //   263: aload_0
    //   264: iconst_2
    //   265: iaload
    //   266: istore 7
    //   268: aload_0
    //   269: iconst_3
    //   270: iaload
    //   271: istore 8
    //   273: getstatic 100	o/Fc:ˎ	[C
    //   276: astore 10
    //   278: iload 6
    //   280: newarray char
    //   282: astore 9
    //   284: aload 10
    //   286: iload_3
    //   287: aload 9
    //   289: iconst_0
    //   290: iload 6
    //   292: invokestatic 111	java/lang/System:arraycopy	(Ljava/lang/Object;ILjava/lang/Object;II)V
    //   295: aload_1
    //   296: ifnull +6 -> 302
    //   299: goto -106 -> 193
    //   302: aload 9
    //   304: astore_1
    //   305: goto -182 -> 123
    //   308: getstatic 45	o/Fc:ˋ	I
    //   311: bipush 15
    //   313: iadd
    //   314: istore_3
    //   315: iload_3
    //   316: sipush 128
    //   319: irem
    //   320: putstatic 47	o/Fc:ˏ	I
    //   323: iload_3
    //   324: iconst_2
    //   325: irem
    //   326: ifne +6 -> 332
    //   329: goto -122 -> 207
    //   332: goto +243 -> 575
    //   335: iconst_0
    //   336: istore 4
    //   338: goto -323 -> 15
    //   341: iconst_1
    //   342: istore 5
    //   344: goto -250 -> 94
    //   347: iload 6
    //   349: newarray char
    //   351: astore 9
    //   353: aload_1
    //   354: iconst_0
    //   355: aload 9
    //   357: iconst_0
    //   358: iload 6
    //   360: invokestatic 111	java/lang/System:arraycopy	(Ljava/lang/Object;ILjava/lang/Object;II)V
    //   363: aload 9
    //   365: iconst_0
    //   366: aload_1
    //   367: iload 6
    //   369: iload 8
    //   371: isub
    //   372: iload 8
    //   374: invokestatic 111	java/lang/System:arraycopy	(Ljava/lang/Object;ILjava/lang/Object;II)V
    //   377: aload 9
    //   379: iload 8
    //   381: aload_1
    //   382: iconst_0
    //   383: iload 6
    //   385: iload 8
    //   387: isub
    //   388: invokestatic 111	java/lang/System:arraycopy	(Ljava/lang/Object;ILjava/lang/Object;II)V
    //   391: goto +157 -> 548
    //   394: goto -47 -> 347
    //   397: aload 10
    //   399: astore_1
    //   400: goto -277 -> 123
    //   403: iconst_1
    //   404: istore_3
    //   405: goto +27 -> 432
    //   408: aload_1
    //   409: iload 4
    //   411: baload
    //   412: iconst_1
    //   413: if_icmpne +6 -> 419
    //   416: goto +74 -> 490
    //   419: goto -78 -> 341
    //   422: iconst_0
    //   423: istore_3
    //   424: goto +8 -> 432
    //   427: iconst_0
    //   428: istore_3
    //   429: goto +149 -> 578
    //   432: iload_3
    //   433: tableswitch	default:+23->456, 0:+105->538, 1:+-299->134
    //   456: goto -322 -> 134
    //   459: iload 4
    //   461: iload 6
    //   463: if_icmpge +6 -> 469
    //   466: goto -58 -> 408
    //   469: goto -72 -> 397
    //   472: aload 10
    //   474: iload 4
    //   476: aload 9
    //   478: iload 4
    //   480: caload
    //   481: iconst_1
    //   482: ishl
    //   483: iload_3
    //   484: isub
    //   485: i2c
    //   486: castore
    //   487: goto -179 -> 308
    //   490: iconst_0
    //   491: istore 5
    //   493: goto -399 -> 94
    //   496: iconst_1
    //   497: istore_3
    //   498: goto +80 -> 578
    //   501: new 113	java/lang/String
    //   504: dup
    //   505: aload_1
    //   506: invokespecial 117	java/lang/String:<init>	([C)V
    //   509: areturn
    //   510: iconst_0
    //   511: istore_3
    //   512: goto -273 -> 239
    //   515: aload 10
    //   517: iload 4
    //   519: aload 9
    //   521: iload 4
    //   523: caload
    //   524: iconst_1
    //   525: ishl
    //   526: iconst_1
    //   527: iadd
    //   528: iload_3
    //   529: isub
    //   530: i2c
    //   531: castore
    //   532: goto -357 -> 175
    //   535: goto +68 -> 603
    //   538: iload_2
    //   539: ifeq +6 -> 545
    //   542: goto +88 -> 630
    //   545: goto -317 -> 228
    //   548: getstatic 45	o/Fc:ˋ	I
    //   551: bipush 95
    //   553: iadd
    //   554: istore_3
    //   555: iload_3
    //   556: sipush 128
    //   559: irem
    //   560: putstatic 47	o/Fc:ˏ	I
    //   563: iload_3
    //   564: iconst_2
    //   565: irem
    //   566: ifne +6 -> 572
    //   569: goto -526 -> 43
    //   572: goto -321 -> 251
    //   575: goto -400 -> 175
    //   578: iload_3
    //   579: tableswitch	default:+21->600, 0:+-69->510, 1:+-78->501
    //   600: goto -90 -> 510
    //   603: getstatic 45	o/Fc:ˋ	I
    //   606: bipush 51
    //   608: iadd
    //   609: istore_3
    //   610: iload_3
    //   611: sipush 128
    //   614: irem
    //   615: putstatic 47	o/Fc:ˏ	I
    //   618: iload_3
    //   619: iconst_2
    //   620: irem
    //   621: ifne +6 -> 627
    //   624: goto +17 -> 641
    //   627: goto -373 -> 254
    //   630: iload 6
    //   632: newarray char
    //   634: astore 9
    //   636: iconst_0
    //   637: istore_3
    //   638: goto -475 -> 163
    //   641: goto -387 -> 254
    //   644: iconst_1
    //   645: istore 4
    //   647: goto -632 -> 15
    // Local variable table:
    //   start	length	slot	name	signature
    //   0	650	0	paramArrayOfInt	int[]
    //   0	650	1	paramArrayOfByte	byte[]
    //   0	650	2	paramBoolean	boolean
    //   48	590	3	i	int
    //   15	631	4	j	int
    //   70	422	5	k	int
    //   50	581	6	m	int
    //   228	39	7	n	int
    //   123	265	8	i1	int
    //   6	629	9	arrayOfChar1	char[]
    //   175	341	10	arrayOfChar2	char[]
    // Exception table:
    //   from	to	target	type
    //   548	555	3	java/lang/Exception
    //   555	563	3	java/lang/Exception
    //   134	138	190	java/lang/Exception
    //   603	610	190	java/lang/Exception
    //   610	618	190	java/lang/Exception
  }
  
  public boolean equals(Object paramObject)
  {
    break label254;
    int i = null.length;
    return false;
    Object localObject;
    for (;;)
    {
      i = 1;
      break;
      while (!vq.ˊ(this.nfcSettings, ((Fc)localObject).nfcSettings))
      {
        break label257;
        for (;;)
        {
          if (this != paramObject) {
            break label268;
          }
          break;
          switch (i)
          {
          default: 
            label45:
            break label407;
            label71:
            i = ˋ + 97;
            ˏ = i % 128;
            if (i % 2 == 0) {
              break label364;
            }
          }
        }
        label98:
        switch (i)
        {
        }
      }
      label123:
      if (vq.ˊ(this.p2pSettings, ((Fc)localObject).p2pSettings)) {
        break label303;
      }
    }
    for (;;)
    {
      switch (i)
      {
      default: 
        break label308;
        label254:
        label257:
        label263:
        label268:
        do
        {
          break label337;
          if (!(paramObject instanceof Fc))
          {
            break label372;
            i = 40;
            break label378;
            for (;;)
            {
              return false;
              i = 0;
              break label45;
              i = ˋ + 39;
              ˏ = i % 128;
              if (i % 2 == 0) {
                break;
              }
            }
            i = ˋ + 57;
            ˏ = i % 128;
            if (i % 2 != 0)
            {
              break label409;
              break label71;
              i = 23;
              break label378;
              i = 0;
              break label98;
              i = 1;
              break label45;
            }
            break label409;
          }
          i = ˏ + 35;
          ˋ = i % 128;
        } while (i % 2 != 0);
        break label337;
        label303:
        i = 0;
      }
    }
    for (;;)
    {
      try
      {
        label308:
        paramObject = this.languageSettingsDto;
        localObject = ((Fc)localObject).languageSettingsDto;
        boolean bool = vq.ˊ(paramObject, localObject);
        if (bool) {
          break label407;
        }
        continue;
        label337:
        localObject = (Fc)paramObject;
        if (!vq.ˊ(this.contactSettings, ((Fc)localObject).contactSettings))
        {
          break label263;
          label364:
          break;
        }
        i = 1;
        break label98;
      }
      catch (Exception paramObject)
      {
        label372:
        throw paramObject;
      }
      label378:
      switch (i)
      {
      }
      continue;
      label407:
      return true;
      label409:
      if (vq.ˊ(this.otpSettings, ((Fc)localObject).otpSettings)) {
        break label123;
      }
    }
  }
  
  /* Error */
  public int hashCode()
  {
    // Byte code:
    //   0: goto +224 -> 224
    //   3: iconst_0
    //   4: istore 5
    //   6: goto +89 -> 95
    //   9: getstatic 45	o/Fc:ˋ	I
    //   12: bipush 31
    //   14: iadd
    //   15: istore_3
    //   16: iload_3
    //   17: sipush 128
    //   20: irem
    //   21: putstatic 47	o/Fc:ˏ	I
    //   24: iload_3
    //   25: iconst_2
    //   26: irem
    //   27: ifne +6 -> 33
    //   30: goto +186 -> 216
    //   33: goto +328 -> 361
    //   36: aload_0
    //   37: getfield 130	o/Fc:languageSettingsDto	Lo/Fc$ˋ;
    //   40: astore 6
    //   42: aload 6
    //   44: ifnull +6 -> 50
    //   47: goto +14 -> 61
    //   50: goto +254 -> 304
    //   53: iconst_0
    //   54: istore_1
    //   55: goto +43 -> 98
    //   58: goto +286 -> 344
    //   61: bipush 29
    //   63: istore 5
    //   65: goto +72 -> 137
    //   68: aload_0
    //   69: getfield 134	o/Fc:otpSettings	Lo/Fc$If;
    //   72: astore 6
    //   74: aload 6
    //   76: ifnull +6 -> 82
    //   79: goto +178 -> 257
    //   82: goto +137 -> 219
    //   85: aload 6
    //   87: invokevirtual 138	java/lang/Object:hashCode	()I
    //   90: istore 5
    //   92: goto +278 -> 370
    //   95: goto +138 -> 233
    //   98: aload_0
    //   99: getfield 121	o/Fc:nfcSettings	Lo/Fc$ˊ;
    //   102: astore 6
    //   104: aload 6
    //   106: ifnull +6 -> 112
    //   109: goto +118 -> 227
    //   112: goto +267 -> 379
    //   115: iconst_0
    //   116: istore_3
    //   117: goto +3 -> 120
    //   120: aload_0
    //   121: getfield 128	o/Fc:p2pSettings	Ljava/util/List;
    //   124: astore 6
    //   126: aload 6
    //   128: ifnull +6 -> 134
    //   131: goto +131 -> 262
    //   134: goto +239 -> 373
    //   137: iload 5
    //   139: lookupswitch	default:+25->164, 29:+-54->85, 92:+-136->3
    //   164: goto -161 -> 3
    //   167: aload 6
    //   169: invokevirtual 138	java/lang/Object:hashCode	()I
    //   172: istore_1
    //   173: goto -75 -> 98
    //   176: goto -140 -> 36
    //   179: iload_2
    //   180: lookupswitch	default:+28->208, 25:+119->299, 69:+131->311
    //   208: goto +103 -> 311
    //   211: astore 6
    //   213: aload 6
    //   215: athrow
    //   216: goto +145 -> 361
    //   219: iconst_0
    //   220: istore_3
    //   221: goto +51 -> 272
    //   224: goto +96 -> 320
    //   227: bipush 69
    //   229: istore_2
    //   230: goto -51 -> 179
    //   233: iload_1
    //   234: bipush 31
    //   236: imul
    //   237: iload_2
    //   238: iadd
    //   239: bipush 31
    //   241: imul
    //   242: iload_3
    //   243: iadd
    //   244: bipush 31
    //   246: imul
    //   247: iload 4
    //   249: iadd
    //   250: bipush 31
    //   252: imul
    //   253: iload 5
    //   255: iadd
    //   256: ireturn
    //   257: iconst_1
    //   258: istore_3
    //   259: goto +13 -> 272
    //   262: aload 6
    //   264: invokevirtual 138	java/lang/Object:hashCode	()I
    //   267: istore 4
    //   269: goto -93 -> 176
    //   272: iload_3
    //   273: tableswitch	default:+23->296, 0:+-158->115, 1:+-264->9
    //   296: goto -287 -> 9
    //   299: iconst_0
    //   300: istore_2
    //   301: goto -233 -> 68
    //   304: bipush 92
    //   306: istore 5
    //   308: goto -171 -> 137
    //   311: aload 6
    //   313: invokevirtual 138	java/lang/Object:hashCode	()I
    //   316: istore_2
    //   317: goto -249 -> 68
    //   320: getstatic 47	o/Fc:ˏ	I
    //   323: bipush 71
    //   325: iadd
    //   326: istore_1
    //   327: iload_1
    //   328: sipush 128
    //   331: irem
    //   332: putstatic 45	o/Fc:ˋ	I
    //   335: iload_1
    //   336: iconst_2
    //   337: irem
    //   338: ifeq +6 -> 344
    //   341: goto -283 -> 58
    //   344: aload_0
    //   345: getfield 132	o/Fc:contactSettings	Lo/Fc$if;
    //   348: astore 6
    //   350: aload 6
    //   352: ifnull +6 -> 358
    //   355: goto -188 -> 167
    //   358: goto -305 -> 53
    //   361: aload 6
    //   363: invokevirtual 138	java/lang/Object:hashCode	()I
    //   366: istore_3
    //   367: goto -247 -> 120
    //   370: goto -137 -> 233
    //   373: iconst_0
    //   374: istore 4
    //   376: goto -340 -> 36
    //   379: bipush 25
    //   381: istore_2
    //   382: goto -203 -> 179
    // Local variable table:
    //   start	length	slot	name	signature
    //   0	385	0	this	Fc
    //   54	284	1	i	int
    //   179	203	2	j	int
    //   15	352	3	k	int
    //   247	128	4	m	int
    //   4	303	5	n	int
    //   40	128	6	localObject	Object
    //   211	101	6	localException	Exception
    //   348	14	6	localIf	if
    // Exception table:
    //   from	to	target	type
    //   320	327	211	java/lang/Exception
    //   327	335	211	java/lang/Exception
    //   344	350	211	java/lang/Exception
  }
  
  public String toString()
  {
    String str;
    for (;;)
    {
      str = ॱ(new int[] { 0, 33, 158, 0 }, new byte[] { 1, 0, 0, 1, 1, 1, 0, 1, 0, 1, 1, 0, 1, 0, 1, 0, 1, 1, 0, 1, 1, 1, 1, 0, 1, 1, 0, 1, 1, 1, 0, 1, 0 }, true).intern() + this.contactSettings + ॱ(new int[] { 33, 14, 0, 12 }, new byte[] { 1, 1, 1, 1, 0, 1, 0, 0, 1, 0, 0, 0, 1, 0 }, true).intern() + this.nfcSettings + ॱ(new int[] { 47, 14, 0, 0 }, new byte[] { 0, 0, 1, 1, 0, 1, 0, 1, 0, 1, 1, 1, 0, 0 }, false).intern() + this.otpSettings + ॱ(new int[] { 61, 14, 0, 14 }, new byte[] { 0, 0, 0, 0, 0, 1, 0, 1, 0, 1, 1, 1, 0, 0 }, false).intern() + this.p2pSettings + ॱ(new int[] { 75, 22, 18, 0 }, new byte[] { 0, 0, 0, 1, 1, 1, 0, 0, 0, 0, 0, 0, 1, 0, 1, 1, 1, 0, 1, 0, 1, 0 }, false).intern() + this.languageSettingsDto + ॱ(new int[] { 97, 1, 0, 0 }, new byte[] { 1 }, true).intern();
      break;
    }
    int i = ˋ + 43;
    ˏ = i % 128;
    if (i % 2 == 0) {
      return str;
    }
    return str;
  }
  
  public final List<FP> ˊ()
  {
    break label35;
    int i = 5;
    break label46;
    label35:
    List localList;
    for (;;)
    {
      i = ˏ + 97;
      ˋ = i % 128;
      if (i % 2 != 0) {
        break;
      }
      break label108;
      break label79;
      localList = this.p2pSettings;
    }
    for (;;)
    {
      switch (i)
      {
      case 5: 
      default: 
        i = 57 / 0;
        return localList;
        i = ˋ + 35;
        ˏ = i % 128;
        if (i % 2 == 0) {
          break;
        }
        break;
      case 73: 
        label46:
        label79:
        return localList;
        label108:
        i = 73;
      }
    }
  }
  
  public final if ˋ()
  {
    for (;;)
    {
      int i = ˏ + 19;
      ˋ = i % 128;
      if (i % 2 == 0)
      {
        i = 0;
        break label46;
        if localIf = this.contactSettings;
        i = 16 / 0;
        return localIf;
      }
      else
      {
        i = 1;
      }
      switch (i)
      {
      case 1: 
      default: 
        label46:
        break;
      }
      return this.contactSettings;
    }
  }
  
  /* Error */
  public final ˋ ˎ()
  {
    // Byte code:
    //   0: goto +52 -> 52
    //   3: iload_1
    //   4: tableswitch	default:+24->28, 0:+51->55, 1:+27->31
    //   28: goto +27 -> 55
    //   31: aload_0
    //   32: getfield 130	o/Fc:languageSettingsDto	Lo/Fc$ˋ;
    //   35: astore_2
    //   36: bipush 33
    //   38: iconst_0
    //   39: idiv
    //   40: istore_1
    //   41: goto +54 -> 95
    //   44: astore_2
    //   45: aload_2
    //   46: athrow
    //   47: iconst_0
    //   48: istore_1
    //   49: goto -46 -> 3
    //   52: goto +16 -> 68
    //   55: aload_0
    //   56: getfield 130	o/Fc:languageSettingsDto	Lo/Fc$ˋ;
    //   59: astore_2
    //   60: goto +35 -> 95
    //   63: iconst_1
    //   64: istore_1
    //   65: goto -62 -> 3
    //   68: getstatic 47	o/Fc:ˏ	I
    //   71: bipush 17
    //   73: iadd
    //   74: istore_1
    //   75: iload_1
    //   76: sipush 128
    //   79: irem
    //   80: putstatic 45	o/Fc:ˋ	I
    //   83: iload_1
    //   84: iconst_2
    //   85: irem
    //   86: ifeq +6 -> 92
    //   89: goto -26 -> 63
    //   92: goto -45 -> 47
    //   95: getstatic 45	o/Fc:ˋ	I
    //   98: bipush 61
    //   100: iadd
    //   101: istore_1
    //   102: iload_1
    //   103: sipush 128
    //   106: irem
    //   107: putstatic 47	o/Fc:ˏ	I
    //   110: iload_1
    //   111: iconst_2
    //   112: irem
    //   113: ifne +5 -> 118
    //   116: aload_2
    //   117: areturn
    //   118: aload_2
    //   119: areturn
    // Local variable table:
    //   start	length	slot	name	signature
    //   0	120	0	this	Fc
    //   3	110	1	i	int
    //   35	1	2	localˋ1	ˋ
    //   44	2	2	localException	Exception
    //   59	60	2	localˋ2	ˋ
    // Exception table:
    //   from	to	target	type
    //   55	60	44	java/lang/Exception
  }
  
  /* Error */
  public final If ˏ()
  {
    // Byte code:
    //   0: goto +23 -> 23
    //   3: aload_0
    //   4: getfield 134	o/Fc:otpSettings	Lo/Fc$If;
    //   7: areturn
    //   8: astore_2
    //   9: aload_2
    //   10: athrow
    //   11: aload_0
    //   12: getfield 134	o/Fc:otpSettings	Lo/Fc$If;
    //   15: astore_2
    //   16: bipush 50
    //   18: iconst_0
    //   19: idiv
    //   20: istore_1
    //   21: aload_2
    //   22: areturn
    //   23: goto +8 -> 31
    //   26: iconst_0
    //   27: istore_1
    //   28: goto +34 -> 62
    //   31: getstatic 45	o/Fc:ˋ	I
    //   34: istore_1
    //   35: iload_1
    //   36: bipush 41
    //   38: iadd
    //   39: istore_1
    //   40: iload_1
    //   41: sipush 128
    //   44: irem
    //   45: putstatic 47	o/Fc:ˏ	I
    //   48: iload_1
    //   49: iconst_2
    //   50: irem
    //   51: ifne +6 -> 57
    //   54: goto +6 -> 60
    //   57: goto -31 -> 26
    //   60: iconst_1
    //   61: istore_1
    //   62: iload_1
    //   63: tableswitch	default:+21->84, 0:+-60->3, 1:+-52->11
    //   84: goto -73 -> 11
    //   87: astore_2
    //   88: aload_2
    //   89: athrow
    // Local variable table:
    //   start	length	slot	name	signature
    //   0	90	0	this	Fc
    //   20	43	1	i	int
    //   8	2	2	localException1	Exception
    //   15	7	2	localIf	If
    //   87	2	2	localException2	Exception
    // Exception table:
    //   from	to	target	type
    //   40	48	8	java/lang/Exception
    //   31	35	87	java/lang/Exception
  }
  
  /* Error */
  public final ˊ ॱ()
  {
    // Byte code:
    //   0: goto +35 -> 35
    //   3: astore_2
    //   4: aload_2
    //   5: athrow
    //   6: goto +64 -> 70
    //   9: getstatic 45	o/Fc:ˋ	I
    //   12: bipush 65
    //   14: iadd
    //   15: istore_1
    //   16: iload_1
    //   17: sipush 128
    //   20: irem
    //   21: putstatic 47	o/Fc:ˏ	I
    //   24: iload_1
    //   25: iconst_2
    //   26: irem
    //   27: ifne +6 -> 33
    //   30: goto +8 -> 38
    //   33: aload_2
    //   34: areturn
    //   35: goto +5 -> 40
    //   38: aload_2
    //   39: areturn
    //   40: getstatic 45	o/Fc:ˋ	I
    //   43: bipush 103
    //   45: iadd
    //   46: istore_1
    //   47: iload_1
    //   48: sipush 128
    //   51: irem
    //   52: putstatic 47	o/Fc:ˏ	I
    //   55: iload_1
    //   56: iconst_2
    //   57: irem
    //   58: ifne +6 -> 64
    //   61: goto -55 -> 6
    //   64: goto +6 -> 70
    //   67: astore_2
    //   68: aload_2
    //   69: athrow
    //   70: aload_0
    //   71: getfield 121	o/Fc:nfcSettings	Lo/Fc$ˊ;
    //   74: astore_2
    //   75: goto -66 -> 9
    // Local variable table:
    //   start	length	slot	name	signature
    //   0	78	0	this	Fc
    //   15	43	1	i	int
    //   3	36	2	localException1	Exception
    //   67	2	2	localException2	Exception
    //   74	1	2	localˊ	ˊ
    // Exception table:
    //   from	to	target	type
    //   9	16	3	java/lang/Exception
    //   16	24	3	java/lang/Exception
    //   16	24	67	java/lang/Exception
  }
  
  public static final class If
  {
    private static char ˊ = '\004';
    private static int ˋ;
    private static char[] ˏ;
    private static int ॱ = 0;
    @nT(ˋ="otpScopedSettingsMap")
    private final If values;
    
    static
    {
      ˋ = 1;
      ˏ = new char[] { 79, 116, 112, 83, 101, 105, 110, 103, 115, 40, 118, 97, 108, 117, 61, 41 };
    }
    
    /* Error */
    private static String ॱ(char[] paramArrayOfChar, int paramInt, byte paramByte)
    {
      // Byte code:
      //   0: goto +66 -> 66
      //   3: iload 8
      //   5: iload 5
      //   7: invokestatic 58	o/oO:ˊ	(II)I
      //   10: istore 4
      //   12: iload 9
      //   14: iload 5
      //   16: invokestatic 58	o/oO:ˊ	(II)I
      //   19: istore 8
      //   21: iload 7
      //   23: iload 4
      //   25: iload 5
      //   27: invokestatic 61	o/oO:ˏ	(III)I
      //   30: istore 4
      //   32: iload 6
      //   34: iload 8
      //   36: iload 5
      //   38: invokestatic 61	o/oO:ˏ	(III)I
      //   41: istore 6
      //   43: aload 11
      //   45: iload_3
      //   46: aload 10
      //   48: iload 4
      //   50: caload
      //   51: castore
      //   52: aload 11
      //   54: iload_3
      //   55: iconst_1
      //   56: iadd
      //   57: aload 10
      //   59: iload 6
      //   61: caload
      //   62: castore
      //   63: goto +155 -> 218
      //   66: goto +104 -> 170
      //   69: getstatic 27	o/Fc$If:ॱ	I
      //   72: istore 4
      //   74: iload 4
      //   76: bipush 33
      //   78: iadd
      //   79: istore 4
      //   81: iload 4
      //   83: sipush 128
      //   86: irem
      //   87: putstatic 29	o/Fc$If:ˋ	I
      //   90: iload 4
      //   92: iconst_2
      //   93: irem
      //   94: ifne +6 -> 100
      //   97: goto +169 -> 266
      //   100: goto +97 -> 197
      //   103: iload_1
      //   104: iconst_1
      //   105: if_icmple +6 -> 111
      //   108: goto +418 -> 526
      //   111: goto +420 -> 531
      //   114: iload_3
      //   115: iload_1
      //   116: if_icmpge +6 -> 122
      //   119: goto +332 -> 451
      //   122: goto +409 -> 531
      //   125: iload_3
      //   126: iconst_2
      //   127: iadd
      //   128: istore_3
      //   129: goto -15 -> 114
      //   132: goto -7 -> 125
      //   135: getstatic 27	o/Fc$If:ॱ	I
      //   138: istore_3
      //   139: iload_3
      //   140: bipush 7
      //   142: iadd
      //   143: istore_3
      //   144: iload_3
      //   145: sipush 128
      //   148: irem
      //   149: putstatic 29	o/Fc$If:ˋ	I
      //   152: iload_3
      //   153: iconst_2
      //   154: irem
      //   155: ifne +6 -> 161
      //   158: goto +229 -> 387
      //   161: goto +258 -> 419
      //   164: iconst_1
      //   165: istore 4
      //   167: goto +226 -> 393
      //   170: getstatic 47	o/Fc$If:ˏ	[C
      //   173: astore 10
      //   175: getstatic 49	o/Fc$If:ˊ	C
      //   178: istore 5
      //   180: iload_1
      //   181: newarray char
      //   183: astore 11
      //   185: iload_1
      //   186: iconst_2
      //   187: irem
      //   188: ifeq +6 -> 194
      //   191: goto -56 -> 135
      //   194: goto -91 -> 103
      //   197: goto -83 -> 114
      //   200: iload_1
      //   201: bipush 95
      //   203: iadd
      //   204: istore_1
      //   205: aload 11
      //   207: iload_1
      //   208: aload_0
      //   209: iload_1
      //   210: caload
      //   211: iload_2
      //   212: ishr
      //   213: i2c
      //   214: castore
      //   215: goto +305 -> 520
      //   218: goto -93 -> 125
      //   221: iload 7
      //   223: iload 9
      //   225: iload 5
      //   227: invokestatic 61	o/oO:ˏ	(III)I
      //   230: istore 4
      //   232: iload 6
      //   234: iload 8
      //   236: iload 5
      //   238: invokestatic 61	o/oO:ˏ	(III)I
      //   241: istore 6
      //   243: aload 11
      //   245: iload_3
      //   246: aload 10
      //   248: iload 4
      //   250: caload
      //   251: castore
      //   252: aload 11
      //   254: iload_3
      //   255: iconst_1
      //   256: iadd
      //   257: aload 10
      //   259: iload 6
      //   261: caload
      //   262: castore
      //   263: goto -138 -> 125
      //   266: goto -69 -> 197
      //   269: iconst_0
      //   270: istore 4
      //   272: goto +121 -> 393
      //   275: iload 7
      //   277: iload 5
      //   279: invokestatic 58	o/oO:ˊ	(II)I
      //   282: istore 4
      //   284: iload 6
      //   286: iload 5
      //   288: invokestatic 58	o/oO:ˊ	(II)I
      //   291: istore 6
      //   293: iload 4
      //   295: iload 8
      //   297: iload 5
      //   299: invokestatic 61	o/oO:ˏ	(III)I
      //   302: istore 4
      //   304: iload 6
      //   306: iload 9
      //   308: iload 5
      //   310: invokestatic 61	o/oO:ˏ	(III)I
      //   313: istore 6
      //   315: aload 11
      //   317: iload_3
      //   318: aload 10
      //   320: iload 4
      //   322: caload
      //   323: castore
      //   324: aload 11
      //   326: iload_3
      //   327: iconst_1
      //   328: iadd
      //   329: aload 10
      //   331: iload 6
      //   333: caload
      //   334: castore
      //   335: goto -210 -> 125
      //   338: iload 6
      //   340: iload 5
      //   342: invokestatic 63	o/oO:ॱ	(II)I
      //   345: istore 7
      //   347: iload 6
      //   349: iload 5
      //   351: invokestatic 65	o/oO:ˋ	(II)I
      //   354: istore 8
      //   356: iload 4
      //   358: iload 5
      //   360: invokestatic 63	o/oO:ॱ	(II)I
      //   363: istore 6
      //   365: iload 4
      //   367: iload 5
      //   369: invokestatic 65	o/oO:ˋ	(II)I
      //   372: istore 9
      //   374: iload 8
      //   376: iload 9
      //   378: if_icmpne +6 -> 384
      //   381: goto -106 -> 275
      //   384: goto +123 -> 507
      //   387: bipush 22
      //   389: istore_3
      //   390: goto +86 -> 476
      //   393: iload 4
      //   395: tableswitch	default:+21->416, 0:+-392->3, 1:+-174->221
      //   416: goto -413 -> 3
      //   419: bipush 63
      //   421: istore_3
      //   422: goto +54 -> 476
      //   425: aload 11
      //   427: iload_3
      //   428: iload 6
      //   430: iload_2
      //   431: isub
      //   432: i2c
      //   433: castore
      //   434: aload 11
      //   436: iload_3
      //   437: iconst_1
      //   438: iadd
      //   439: iload 4
      //   441: iload_2
      //   442: isub
      //   443: i2c
      //   444: castore
      //   445: goto -313 -> 132
      //   448: astore_0
      //   449: aload_0
      //   450: athrow
      //   451: aload_0
      //   452: iload_3
      //   453: caload
      //   454: istore 6
      //   456: aload_0
      //   457: iload_3
      //   458: iconst_1
      //   459: iadd
      //   460: caload
      //   461: istore 4
      //   463: iload 6
      //   465: iload 4
      //   467: if_icmpne +6 -> 473
      //   470: goto -45 -> 425
      //   473: goto -135 -> 338
      //   476: iload_3
      //   477: lookupswitch	default:+27->504, 22:+-277->200, 63:+64->541
      //   504: goto +37 -> 541
      //   507: iload 7
      //   509: iload 6
      //   511: if_icmpne +6 -> 517
      //   514: goto -245 -> 269
      //   517: goto -353 -> 164
      //   520: goto -417 -> 103
      //   523: astore_0
      //   524: aload_0
      //   525: athrow
      //   526: iconst_0
      //   527: istore_3
      //   528: goto -459 -> 69
      //   531: new 67	java/lang/String
      //   534: dup
      //   535: aload 11
      //   537: invokespecial 71	java/lang/String:<init>	([C)V
      //   540: areturn
      //   541: iload_1
      //   542: iconst_1
      //   543: isub
      //   544: istore_1
      //   545: aload 11
      //   547: iload_1
      //   548: aload_0
      //   549: iload_1
      //   550: caload
      //   551: iload_2
      //   552: isub
      //   553: i2c
      //   554: castore
      //   555: goto -35 -> 520
      // Local variable table:
      //   start	length	slot	name	signature
      //   0	558	0	paramArrayOfChar	char[]
      //   0	558	1	paramInt	int
      //   0	558	2	paramByte	byte
      //   45	483	3	i	int
      //   10	458	4	b1	byte
      //   5	363	5	j	int
      //   32	480	6	b2	byte
      //   21	491	7	b3	byte
      //   3	376	8	k	int
      //   12	367	9	m	int
      //   46	284	10	arrayOfChar1	char[]
      //   43	503	11	arrayOfChar2	char[]
      // Exception table:
      //   from	to	target	type
      //   69	74	448	java/lang/Exception
      //   81	90	448	java/lang/Exception
      //   135	139	448	java/lang/Exception
      //   144	152	523	java/lang/Exception
    }
    
    public boolean equals(Object paramObject)
    {
      for (;;)
      {
        int i;
        try
        {
          If localIf = (If)paramObject;
          paramObject = this.values;
          boolean bool = vq.ˊ(paramObject, localIf.values);
          if (!bool) {
            continue;
          } else {
            switch (i)
            {
            default: 
              continue;
              i = null.length;
              return true;
            case 22: 
              continue;
              i = 1;
              continue;
              continue;
              i = 38;
            }
          }
        }
        catch (Exception paramObject)
        {
          throw paramObject;
        }
        try
        {
          i = ˋ;
          i += 107;
          ॱ = i % 128;
          if (i % 2 != 0) {
            break;
          }
          continue;
          i = 22;
          continue;
          i = 32;
          continue;
          return true;
          return false;
        }
        catch (Exception paramObject)
        {
          label221:
          throw paramObject;
        }
        if (!(paramObject instanceof If))
        {
          i = 3;
          break label221;
          i = 0;
          continue;
          i = ॱ + 7;
          ˋ = i % 128;
          if (i % 2 != 0)
          {
            continue;
            switch (i)
            {
            }
            continue;
            if (this == paramObject)
            {
              continue;
              switch (i)
              {
              }
            }
          }
        }
      }
      throw new NullPointerException();
    }
    
    public int hashCode()
    {
      for (;;)
      {
        If localIf;
        switch (i)
        {
        default: 
          break;
          localIf = this.values;
          i = null.length;
          if (localIf != null) {
            break label172;
          }
          break;
        }
        for (;;)
        {
          localIf = this.values;
          if (localIf == null)
          {
            break label80;
            break label113;
            break label167;
            i = 1;
            break;
            label75:
            i = 0;
            break label140;
            label80:
            return 0;
          }
          for (;;)
          {
            i = 1;
            break label140;
            i = ˋ + 1;
            ॱ = i % 128;
            if (i % 2 != 0) {
              break;
            }
            break;
            label113:
            i = ˋ + 115;
            ॱ = i % 128;
            if (i % 2 != 0) {
              break label75;
            }
          }
          label140:
          switch (i)
          {
          }
        }
        label167:
        return localIf.hashCode();
        label172:
        int i = 0;
      }
    }
    
    public String toString()
    {
      String str = ॱ(new char[] { 1, 2, 3, 0, 5, 0, 5, 9, 7, 4, 9, 10, 11, 8, 13, 14, 8, 12, 86 }, 19, (byte)25).intern() + this.values + ॱ(new char[] { 46 }, 1, (byte)5).intern();
      int i = ॱ + 27;
      ˋ = i % 128;
      if (i % 2 != 0) {
        return str;
      }
      return str;
    }
    
    public final If ˏ()
    {
      for (;;)
      {
        break label16;
        throw new NullPointerException();
        return localIf;
        label16:
        If localIf = this.values;
        break;
        try
        {
          i = ॱ + 81;
          ˋ = i % 128;
          if (i % 2 == 0) {}
        }
        catch (Exception localException)
        {
          label51:
          throw localException;
        }
      }
      for (int i = 1;; i = 0)
      {
        switch (i)
        {
        }
        break;
        i = ˋ + 43;
        ॱ = i % 128;
        if (i % 2 != 0) {
          break label51;
        }
      }
    }
    
    public static final class If
    {
      private static int ʽ;
      private static char ˊ;
      private static char ˋ = 52415;
      private static char ˎ;
      private static int ˏ = 0;
      private static char ॱ;
      @nT(ˋ="CARD_REGISTRATION_NOT_FROM_PRESENTMENT")
      private final Fc.If.if addManualCard;
      @nT(ˋ="CARD_REGISTRATION_FROM_PRESENTMENT")
      private final Fc.If.if cardPresentment;
      @nT(ˋ="PHONE_VALIDATION")
      private final Fc.If.if phoneValidation;
      
      static
      {
        ʽ = 1;
        ˎ = '繷';
        ˊ = 'ቾ';
        ॱ = '幓';
      }
      
      /* Error */
      private static String ˎ(char[] paramArrayOfChar)
      {
        // Byte code:
        //   0: goto +155 -> 155
        //   3: bipush 50
        //   5: istore_2
        //   6: iload_2
        //   7: lookupswitch	default:+25->32, 8:+175->182, 50:+61->68
        //   32: goto +150 -> 182
        //   35: getstatic 31	o/Fc$If$If:ʽ	I
        //   38: bipush 21
        //   40: iadd
        //   41: istore_1
        //   42: iload_1
        //   43: sipush 128
        //   46: irem
        //   47: putstatic 29	o/Fc$If$If:ˏ	I
        //   50: iload_1
        //   51: iconst_2
        //   52: irem
        //   53: ifeq +6 -> 59
        //   56: goto +25 -> 81
        //   59: goto +105 -> 164
        //   62: bipush 8
        //   64: istore_2
        //   65: goto -59 -> 6
        //   68: new 46	java/lang/String
        //   71: dup
        //   72: aload_3
        //   73: iconst_1
        //   74: aload_3
        //   75: iconst_0
        //   76: caload
        //   77: invokespecial 50	java/lang/String:<init>	([CII)V
        //   80: areturn
        //   81: goto +83 -> 164
        //   84: iload_1
        //   85: aload_0
        //   86: arraylength
        //   87: if_icmpge +6 -> 93
        //   90: goto -28 -> 62
        //   93: goto -90 -> 3
        //   96: astore_0
        //   97: aload_0
        //   98: athrow
        //   99: aload 4
        //   101: iconst_0
        //   102: aload_0
        //   103: iload_1
        //   104: caload
        //   105: castore
        //   106: aload 4
        //   108: iconst_1
        //   109: aload_0
        //   110: iload_1
        //   111: iconst_1
        //   112: iadd
        //   113: caload
        //   114: castore
        //   115: aload 4
        //   117: getstatic 40	o/Fc$If$If:ˋ	C
        //   120: getstatic 35	o/Fc$If$If:ˊ	C
        //   123: getstatic 37	o/Fc$If$If:ॱ	C
        //   126: getstatic 33	o/Fc$If$If:ˎ	C
        //   129: invokestatic 55	o/oP:ˏ	([CCCCC)V
        //   132: aload_3
        //   133: iload_1
        //   134: aload 4
        //   136: iconst_0
        //   137: caload
        //   138: castore
        //   139: aload_3
        //   140: iload_1
        //   141: iconst_1
        //   142: iadd
        //   143: aload 4
        //   145: iconst_1
        //   146: caload
        //   147: castore
        //   148: iload_1
        //   149: iconst_2
        //   150: iadd
        //   151: istore_1
        //   152: goto +9 -> 161
        //   155: goto -120 -> 35
        //   158: astore_0
        //   159: aload_0
        //   160: athrow
        //   161: goto -77 -> 84
        //   164: aload_0
        //   165: arraylength
        //   166: newarray char
        //   168: astore_3
        //   169: iconst_0
        //   170: istore_1
        //   171: iconst_2
        //   172: newarray char
        //   174: astore 4
        //   176: goto -92 -> 84
        //   179: goto -80 -> 99
        //   182: getstatic 31	o/Fc$If$If:ʽ	I
        //   185: bipush 17
        //   187: iadd
        //   188: istore_2
        //   189: iload_2
        //   190: sipush 128
        //   193: irem
        //   194: putstatic 29	o/Fc$If$If:ˏ	I
        //   197: iload_2
        //   198: iconst_2
        //   199: irem
        //   200: ifeq +6 -> 206
        //   203: goto -24 -> 179
        //   206: goto -107 -> 99
        // Local variable table:
        //   start	length	slot	name	signature
        //   0	209	0	paramArrayOfChar	char[]
        //   41	130	1	i	int
        //   5	195	2	j	int
        //   72	97	3	arrayOfChar1	char[]
        //   99	76	4	arrayOfChar2	char[]
        // Exception table:
        //   from	to	target	type
        //   189	197	96	java/lang/Exception
        //   182	189	158	java/lang/Exception
        //   189	197	158	java/lang/Exception
      }
      
      /* Error */
      public boolean equals(Object paramObject)
      {
        // Byte code:
        //   0: goto +41 -> 41
        //   3: bipush 61
        //   5: istore_2
        //   6: goto +256 -> 262
        //   9: iconst_0
        //   10: ireturn
        //   11: iconst_0
        //   12: istore_2
        //   13: goto +59 -> 72
        //   16: bipush 37
        //   18: istore_2
        //   19: goto +80 -> 99
        //   22: goto +269 -> 291
        //   25: goto +192 -> 217
        //   28: aload_1
        //   29: instanceof 2
        //   32: ifeq +6 -> 38
        //   35: goto -32 -> 3
        //   38: goto +255 -> 293
        //   41: aload_0
        //   42: aload_1
        //   43: if_acmpeq +6 -> 49
        //   46: goto +313 -> 359
        //   49: goto -38 -> 11
        //   52: aload_0
        //   53: getfield 59	o/Fc$If$If:addManualCard	Lo/Fc$If$if;
        //   56: aload_1
        //   57: getfield 59	o/Fc$If$If:addManualCard	Lo/Fc$If$if;
        //   60: invokestatic 64	o/vq:ˊ	(Ljava/lang/Object;Ljava/lang/Object;)Z
        //   63: pop
        //   64: new 66	java/lang/NullPointerException
        //   67: dup
        //   68: invokespecial 68	java/lang/NullPointerException:<init>	()V
        //   71: athrow
        //   72: iload_2
        //   73: tableswitch	default:+23->96, 0:+-51->22, 1:+58->131
        //   96: goto +35 -> 131
        //   99: iload_2
        //   100: lookupswitch	default:+28->128, 37:+-48->52, 42:+61->161
        //   128: goto +33 -> 161
        //   131: getstatic 29	o/Fc$If$If:ˏ	I
        //   134: bipush 97
        //   136: iadd
        //   137: istore_2
        //   138: iload_2
        //   139: sipush 128
        //   142: irem
        //   143: putstatic 31	o/Fc$If$If:ʽ	I
        //   146: iload_2
        //   147: iconst_2
        //   148: irem
        //   149: ifne +6 -> 155
        //   152: goto +32 -> 184
        //   155: goto -127 -> 28
        //   158: goto +79 -> 237
        //   161: aload_0
        //   162: getfield 59	o/Fc$If$If:addManualCard	Lo/Fc$If$if;
        //   165: aload_1
        //   166: getfield 59	o/Fc$If$If:addManualCard	Lo/Fc$If$if;
        //   169: invokestatic 64	o/vq:ˊ	(Ljava/lang/Object;Ljava/lang/Object;)Z
        //   172: ifeq +6 -> 178
        //   175: goto -153 -> 22
        //   178: goto +9 -> 187
        //   181: astore_1
        //   182: aload_1
        //   183: athrow
        //   184: goto -156 -> 28
        //   187: goto -178 -> 9
        //   190: getstatic 29	o/Fc$If$If:ˏ	I
        //   193: bipush 63
        //   195: iadd
        //   196: istore_2
        //   197: iload_2
        //   198: sipush 128
        //   201: irem
        //   202: putstatic 31	o/Fc$If$If:ʽ	I
        //   205: iload_2
        //   206: iconst_2
        //   207: irem
        //   208: ifne +6 -> 214
        //   211: goto -195 -> 16
        //   214: goto +139 -> 353
        //   217: aload_0
        //   218: getfield 70	o/Fc$If$If:cardPresentment	Lo/Fc$If$if;
        //   221: aload_1
        //   222: getfield 70	o/Fc$If$If:cardPresentment	Lo/Fc$If$if;
        //   225: invokestatic 64	o/vq:ˊ	(Ljava/lang/Object;Ljava/lang/Object;)Z
        //   228: ifeq +6 -> 234
        //   231: goto -41 -> 190
        //   234: goto -47 -> 187
        //   237: aload_1
        //   238: checkcast 2	o/Fc$If$If
        //   241: astore_1
        //   242: aload_0
        //   243: getfield 72	o/Fc$If$If:phoneValidation	Lo/Fc$If$if;
        //   246: aload_1
        //   247: getfield 72	o/Fc$If$If:phoneValidation	Lo/Fc$If$if;
        //   250: invokestatic 64	o/vq:ˊ	(Ljava/lang/Object;Ljava/lang/Object;)Z
        //   253: ifeq +6 -> 259
        //   256: goto +43 -> 299
        //   259: goto -72 -> 187
        //   262: iload_2
        //   263: lookupswitch	default:+25->288, 61:+63->326, 89:+-76->187
        //   288: goto +38 -> 326
        //   291: iconst_1
        //   292: ireturn
        //   293: bipush 89
        //   295: istore_2
        //   296: goto -34 -> 262
        //   299: getstatic 29	o/Fc$If$If:ˏ	I
        //   302: bipush 7
        //   304: iadd
        //   305: istore_2
        //   306: iload_2
        //   307: sipush 128
        //   310: irem
        //   311: putstatic 31	o/Fc$If$If:ʽ	I
        //   314: iload_2
        //   315: iconst_2
        //   316: irem
        //   317: ifne +6 -> 323
        //   320: goto -295 -> 25
        //   323: goto -106 -> 217
        //   326: getstatic 29	o/Fc$If$If:ˏ	I
        //   329: bipush 73
        //   331: iadd
        //   332: istore_2
        //   333: iload_2
        //   334: sipush 128
        //   337: irem
        //   338: putstatic 31	o/Fc$If$If:ʽ	I
        //   341: iload_2
        //   342: iconst_2
        //   343: irem
        //   344: ifne +6 -> 350
        //   347: goto -189 -> 158
        //   350: goto -113 -> 237
        //   353: bipush 42
        //   355: istore_2
        //   356: goto -257 -> 99
        //   359: iconst_1
        //   360: istore_2
        //   361: goto -289 -> 72
        //   364: astore_1
        //   365: aload_1
        //   366: athrow
        // Local variable table:
        //   start	length	slot	name	signature
        //   0	367	0	this	If
        //   0	367	1	paramObject	Object
        //   5	356	2	i	int
        // Exception table:
        //   from	to	target	type
        //   333	341	181	java/lang/Exception
        //   299	306	364	java/lang/Exception
        //   306	314	364	java/lang/Exception
        //   326	333	364	java/lang/Exception
        //   333	341	364	java/lang/Exception
      }
      
      /* Error */
      public int hashCode()
      {
        // Byte code:
        //   0: goto +106 -> 106
        //   3: iload_1
        //   4: bipush 31
        //   6: imul
        //   7: iload_2
        //   8: iadd
        //   9: bipush 31
        //   11: imul
        //   12: iload_3
        //   13: iadd
        //   14: ireturn
        //   15: aload 5
        //   17: invokevirtual 76	java/lang/Object:hashCode	()I
        //   20: istore_1
        //   21: goto +132 -> 153
        //   24: iconst_0
        //   25: istore_3
        //   26: goto +130 -> 156
        //   29: goto +68 -> 97
        //   32: iconst_0
        //   33: istore_1
        //   34: goto +83 -> 117
        //   37: goto -34 -> 3
        //   40: astore 5
        //   42: aload 5
        //   44: athrow
        //   45: iload_1
        //   46: lookupswitch	default:+26->72, 90:+-14->32, 94:+192->238
        //   72: goto +166 -> 238
        //   75: aload_0
        //   76: getfield 72	o/Fc$If$If:phoneValidation	Lo/Fc$If$if;
        //   79: astore 5
        //   81: aload 5
        //   83: ifnull +6 -> 89
        //   86: goto +61 -> 147
        //   89: goto +143 -> 232
        //   92: iconst_0
        //   93: istore_2
        //   94: goto +15 -> 109
        //   97: aload 5
        //   99: invokevirtual 76	java/lang/Object:hashCode	()I
        //   102: istore_2
        //   103: goto +112 -> 215
        //   106: goto -31 -> 75
        //   109: goto +106 -> 215
        //   112: iconst_0
        //   113: istore_3
        //   114: goto -111 -> 3
        //   117: aload_0
        //   118: getfield 70	o/Fc$If$If:cardPresentment	Lo/Fc$If$if;
        //   121: astore 5
        //   123: aload 5
        //   125: ifnull +6 -> 131
        //   128: goto +55 -> 183
        //   131: goto -39 -> 92
        //   134: astore 5
        //   136: aload 5
        //   138: athrow
        //   139: goto -136 -> 3
        //   142: iconst_1
        //   143: istore_3
        //   144: goto +12 -> 156
        //   147: bipush 94
        //   149: istore_1
        //   150: goto -105 -> 45
        //   153: goto -36 -> 117
        //   156: iload_3
        //   157: tableswitch	default:+23->180, 0:+138->295, 1:+-45->112
        //   180: goto +115 -> 295
        //   183: getstatic 29	o/Fc$If$If:ˏ	I
        //   186: istore_2
        //   187: iload_2
        //   188: bipush 29
        //   190: iadd
        //   191: istore_2
        //   192: iload_2
        //   193: sipush 128
        //   196: irem
        //   197: putstatic 31	o/Fc$If$If:ʽ	I
        //   200: iload_2
        //   201: iconst_2
        //   202: irem
        //   203: ifne +6 -> 209
        //   206: goto -177 -> 29
        //   209: goto -112 -> 97
        //   212: goto -197 -> 15
        //   215: aload_0
        //   216: getfield 59	o/Fc$If$If:addManualCard	Lo/Fc$If$if;
        //   219: astore 5
        //   221: aload 5
        //   223: ifnull +6 -> 229
        //   226: goto -202 -> 24
        //   229: goto -87 -> 142
        //   232: bipush 90
        //   234: istore_1
        //   235: goto -190 -> 45
        //   238: getstatic 29	o/Fc$If$If:ˏ	I
        //   241: bipush 31
        //   243: iadd
        //   244: istore_1
        //   245: iload_1
        //   246: sipush 128
        //   249: irem
        //   250: putstatic 31	o/Fc$If$If:ʽ	I
        //   253: iload_1
        //   254: iconst_2
        //   255: irem
        //   256: ifne +6 -> 262
        //   259: goto -47 -> 212
        //   262: goto -247 -> 15
        //   265: getstatic 29	o/Fc$If$If:ˏ	I
        //   268: bipush 31
        //   270: iadd
        //   271: istore 4
        //   273: iload 4
        //   275: sipush 128
        //   278: irem
        //   279: putstatic 31	o/Fc$If$If:ʽ	I
        //   282: iload 4
        //   284: iconst_2
        //   285: irem
        //   286: ifne +6 -> 292
        //   289: goto -150 -> 139
        //   292: goto -255 -> 37
        //   295: aload 5
        //   297: invokevirtual 76	java/lang/Object:hashCode	()I
        //   300: istore_3
        //   301: goto -36 -> 265
        // Local variable table:
        //   start	length	slot	name	signature
        //   0	304	0	this	If
        //   3	253	1	i	int
        //   7	196	2	j	int
        //   12	289	3	k	int
        //   271	15	4	m	int
        //   15	1	5	localObject	Object
        //   40	3	5	localException1	Exception
        //   79	45	5	localIf1	Fc.If.if
        //   134	3	5	localException2	Exception
        //   219	77	5	localIf2	Fc.If.if
        // Exception table:
        //   from	to	target	type
        //   192	200	40	java/lang/Exception
        //   265	273	40	java/lang/Exception
        //   273	282	40	java/lang/Exception
        //   183	187	134	java/lang/Exception
        //   295	301	134	java/lang/Exception
      }
      
      public String toString()
      {
        String str = ˎ(new char[] { 30860, -23377, 22482, -475, 15718, -13248, -5320, 9710, -23194, -11983, 29380, 19007, 1938, -18354, -18179, -29350, 6975, -6720, -7170, 4789, 12925, -31474, -22862, -9792, -12274, -31908, -6672, 30504, 785, -7340, 13580, -23671, -14842, 645, 28527, -22492, -16404, -24824 }).intern() + this.phoneValidation + ˎ(new char[] { 20077, 10382, 24065, -3010, -1300, -10096, -14585, -10661, -2485, 32427, -9555, 18582, -7239, -27919, 5474, 14372, -7239, -27919, -7118, 27247 }).intern() + this.cardPresentment + ˎ(new char[] { 19688, -15657, -18875, -29987, 6154, 11776, -7170, 4789, 23993, -22825, 785, -7340, 14505, 7006, 1755, 21167, -7118, 27247 }).intern() + this.addManualCard + ˎ(new char[] { 30350, -2130 }).intern();
        int i = ʽ + 119;
        ˏ = i % 128;
        if (i % 2 != 0) {
          return str;
        }
        return str;
      }
      
      /* Error */
      public final Fc.If.if ˊ()
      {
        // Byte code:
        //   0: goto +6 -> 6
        //   3: astore_2
        //   4: aload_2
        //   5: athrow
        //   6: goto +6 -> 12
        //   9: goto +39 -> 48
        //   12: getstatic 31	o/Fc$If$If:ʽ	I
        //   15: bipush 23
        //   17: iadd
        //   18: istore_1
        //   19: iload_1
        //   20: sipush 128
        //   23: irem
        //   24: putstatic 29	o/Fc$If$If:ˏ	I
        //   27: iload_1
        //   28: iconst_2
        //   29: irem
        //   30: ifeq +6 -> 36
        //   33: goto -24 -> 9
        //   36: goto +12 -> 48
        //   39: bipush 45
        //   41: istore_1
        //   42: goto +49 -> 91
        //   45: astore_2
        //   46: aload_2
        //   47: athrow
        //   48: aload_0
        //   49: getfield 70	o/Fc$If$If:cardPresentment	Lo/Fc$If$if;
        //   52: astore_2
        //   53: goto +9 -> 62
        //   56: bipush 11
        //   58: istore_1
        //   59: goto +32 -> 91
        //   62: getstatic 31	o/Fc$If$If:ʽ	I
        //   65: bipush 45
        //   67: iadd
        //   68: istore_1
        //   69: iload_1
        //   70: sipush 128
        //   73: irem
        //   74: putstatic 29	o/Fc$If$If:ˏ	I
        //   77: iload_1
        //   78: iconst_2
        //   79: irem
        //   80: ifeq +6 -> 86
        //   83: goto -27 -> 56
        //   86: goto -47 -> 39
        //   89: aload_2
        //   90: areturn
        //   91: iload_1
        //   92: lookupswitch	default:+28->120, 11:+28->120, 45:+-3->89
        //   120: aconst_null
        //   121: arraylength
        //   122: istore_1
        //   123: aload_2
        //   124: areturn
        // Local variable table:
        //   start	length	slot	name	signature
        //   0	125	0	this	If
        //   18	105	1	i	int
        //   3	2	2	localException1	Exception
        //   45	2	2	localException2	Exception
        //   52	72	2	localIf	Fc.If.if
        // Exception table:
        //   from	to	target	type
        //   19	27	3	java/lang/Exception
        //   12	19	45	java/lang/Exception
        //   19	27	45	java/lang/Exception
      }
      
      public final Fc.If.if ˋ()
      {
        break label126;
        int i;
        switch (i)
        {
        default: 
          break;
        }
        Fc.If.if localIf;
        for (;;)
        {
          i = 0;
          break;
          for (;;)
          {
            i = 0;
            break;
            return localIf;
            throw new NullPointerException();
            label56:
            do
            {
              i = 1;
              break;
              i = ˏ + 3;
              ʽ = i % 128;
            } while (i % 2 == 0);
          }
          localIf = this.phoneValidation;
          i = 1 / 0;
          label91:
          i = ʽ + 73;
          ˏ = i % 128;
          if (i % 2 == 0) {
            break label129;
          }
        }
        for (;;)
        {
          localIf = this.phoneValidation;
          break label91;
          label126:
          break label56;
          label129:
          i = 1;
          break;
          switch (i)
          {
          }
        }
      }
      
      public final Fc.If.if ˏ()
      {
        break label85;
        try
        {
          Fc.If.if localIf = this.addManualCard;
          i = 65 / 0;
          return localIf;
        }
        catch (Exception localException)
        {
          throw localException;
        }
        return this.addManualCard;
        label23:
        int i = ʽ + 35;
        ˏ = i % 128;
        if (i % 2 == 0) {
          break label79;
        }
        for (;;)
        {
          switch (i)
          {
          }
          break;
          label79:
          i = 47;
          continue;
          label85:
          break label23;
          i = 49;
        }
      }
    }
    
    public static final class if
    {
      private static int ˊ = 0;
      private static char ˋ;
      private static int ˎ = 0;
      private static long ˏ;
      private static int ॱ = 1;
      private final long cooldownThreshold;
      private final int counterThreshold;
      private final Er scope;
      
      static
      {
        ˋ = 'ᷘ';
        ˏ = 0L;
      }
      
      private static String ˎ(char[] paramArrayOfChar1, char paramChar, char[] paramArrayOfChar2, int paramInt, char[] paramArrayOfChar3)
      {
        break label294;
        paramInt = 75;
        break label297;
        label9:
        paramInt = 80;
        break label261;
        oJ.ˏ(paramArrayOfChar1, paramArrayOfChar3, paramChar);
        char[] arrayOfChar;
        arrayOfChar[paramChar] = ((char)(int)(paramArrayOfChar2[paramChar] ^ paramArrayOfChar1[((paramChar + '\003') % 4)] ^ ˏ ^ ˎ ^ ˋ));
        paramChar += '\001';
        for (;;)
        {
          oJ.ˏ(paramArrayOfChar1, paramArrayOfChar3, paramChar);
          arrayOfChar[paramChar] = ((char)(int)((paramArrayOfChar2[paramChar] | paramArrayOfChar1[(paramChar % '\005' / 2)]) % ˏ | ˎ | ˋ));
          paramChar += '\023';
          break label291;
          paramInt = 44;
          break label261;
          return new String(arrayOfChar);
          label124:
          paramArrayOfChar1 = (char[])paramArrayOfChar1.clone();
          paramArrayOfChar3 = (char[])paramArrayOfChar3.clone();
          paramArrayOfChar1[0] = ((char)(paramArrayOfChar1[0] ^ paramChar));
          paramArrayOfChar3[2] = ((char)(paramArrayOfChar3[2] + (char)paramInt));
          char c = paramArrayOfChar2.length;
          arrayOfChar = new char[c];
          paramChar = '\000';
          label208:
          label255:
          label261:
          label291:
          label292:
          label294:
          for (;;)
          {
            c = ॱ + 15;
            ˊ = c % '';
            if (c % '\002' == 0)
            {
              break label124;
              try
              {
                paramInt = ॱ;
                paramInt += 83;
                ˊ = paramInt % 128;
                if (paramInt % 2 != 0) {
                  break label255;
                }
              }
              catch (Exception paramArrayOfChar1)
              {
                throw paramArrayOfChar1;
              }
            }
            break label124;
            for (;;)
            {
              if (paramChar < c) {
                break label292;
              }
              break;
              paramInt = 67;
              break label297;
              switch (paramInt)
              {
              }
              break label208;
            }
            break label9;
          }
          label297:
          switch (paramInt)
          {
          }
        }
      }
      
      /* Error */
      public boolean equals(Object paramObject)
      {
        // Byte code:
        //   0: goto +286 -> 286
        //   3: iload_2
        //   4: tableswitch	default:+24->28, 0:+390->394, 1:+323->327
        //   28: goto +299 -> 327
        //   31: iconst_0
        //   32: istore_2
        //   33: goto +346 -> 379
        //   36: iconst_0
        //   37: istore_2
        //   38: goto +315 -> 353
        //   41: iconst_1
        //   42: ireturn
        //   43: goto +148 -> 191
        //   46: bipush 61
        //   48: istore_2
        //   49: goto +160 -> 209
        //   52: goto +139 -> 191
        //   55: aload_0
        //   56: getfield 59	o/Fc$If$if:cooldownThreshold	J
        //   59: lstore 4
        //   61: aload_1
        //   62: getfield 59	o/Fc$If$if:cooldownThreshold	J
        //   65: lstore 6
        //   67: aconst_null
        //   68: arraylength
        //   69: istore_2
        //   70: lload 4
        //   72: lload 6
        //   74: lcmp
        //   75: ifne +6 -> 81
        //   78: goto +211 -> 289
        //   81: goto +70 -> 151
        //   84: astore_1
        //   85: aload_1
        //   86: athrow
        //   87: iconst_1
        //   88: istore_2
        //   89: goto +264 -> 353
        //   92: iload_2
        //   93: tableswitch	default:+23->116, 0:+234->327, 1:+-52->41
        //   116: goto -75 -> 41
        //   119: iconst_0
        //   120: istore_2
        //   121: goto -29 -> 92
        //   124: getstatic 28	o/Fc$If$if:ॱ	I
        //   127: bipush 113
        //   129: iadd
        //   130: istore_3
        //   131: iload_3
        //   132: sipush 128
        //   135: irem
        //   136: putstatic 26	o/Fc$If$if:ˊ	I
        //   139: iload_3
        //   140: iconst_2
        //   141: irem
        //   142: ifeq +6 -> 148
        //   145: goto -102 -> 43
        //   148: goto -96 -> 52
        //   151: iconst_0
        //   152: istore_2
        //   153: goto -29 -> 124
        //   156: astore_1
        //   157: aload_1
        //   158: athrow
        //   159: iconst_1
        //   160: istore_2
        //   161: goto -158 -> 3
        //   164: getstatic 28	o/Fc$If$if:ॱ	I
        //   167: bipush 29
        //   169: iadd
        //   170: istore_2
        //   171: iload_2
        //   172: sipush 128
        //   175: irem
        //   176: putstatic 26	o/Fc$If$if:ˊ	I
        //   179: iload_2
        //   180: iconst_2
        //   181: irem
        //   182: ifeq +6 -> 188
        //   185: goto -98 -> 87
        //   188: goto -152 -> 36
        //   191: iload_2
        //   192: ifeq +6 -> 198
        //   195: goto +9 -> 204
        //   198: goto -79 -> 119
        //   201: goto +188 -> 389
        //   204: iconst_1
        //   205: istore_2
        //   206: goto -114 -> 92
        //   209: iload_2
        //   210: lookupswitch	default:+26->236, 61:+106->316, 91:+-179->31
        //   236: goto -205 -> 31
        //   239: aload_1
        //   240: instanceof 2
        //   243: ifeq +6 -> 249
        //   246: goto +6 -> 252
        //   249: goto -90 -> 159
        //   252: iconst_0
        //   253: istore_2
        //   254: goto -251 -> 3
        //   257: aload_0
        //   258: getfield 59	o/Fc$If$if:cooldownThreshold	J
        //   261: aload_1
        //   262: getfield 59	o/Fc$If$if:cooldownThreshold	J
        //   265: lcmp
        //   266: ifne +6 -> 272
        //   269: goto +20 -> 289
        //   272: goto -121 -> 151
        //   275: aload_0
        //   276: aload_1
        //   277: if_acmpeq +6 -> 283
        //   280: goto -41 -> 239
        //   283: goto -242 -> 41
        //   286: goto -11 -> 275
        //   289: getstatic 28	o/Fc$If$if:ॱ	I
        //   292: bipush 81
        //   294: iadd
        //   295: istore_2
        //   296: iload_2
        //   297: sipush 128
        //   300: irem
        //   301: putstatic 26	o/Fc$If$if:ˊ	I
        //   304: iload_2
        //   305: iconst_2
        //   306: irem
        //   307: ifeq +6 -> 313
        //   310: goto -109 -> 201
        //   313: goto +37 -> 350
        //   316: iconst_1
        //   317: istore_2
        //   318: goto +61 -> 379
        //   321: bipush 91
        //   323: istore_2
        //   324: goto -115 -> 209
        //   327: iconst_0
        //   328: ireturn
        //   329: aload_0
        //   330: getfield 61	o/Fc$If$if:counterThreshold	I
        //   333: istore_2
        //   334: aload_1
        //   335: getfield 61	o/Fc$If$if:counterThreshold	I
        //   338: istore_3
        //   339: iload_2
        //   340: iload_3
        //   341: if_icmpne +6 -> 347
        //   344: goto -298 -> 46
        //   347: goto -26 -> 321
        //   350: goto +39 -> 389
        //   353: iload_2
        //   354: tableswitch	default:+22->376, 0:+-97->257, 1:+-299->55
        //   376: goto -119 -> 257
        //   379: iload_2
        //   380: ifeq +6 -> 386
        //   383: goto -219 -> 164
        //   386: goto -59 -> 327
        //   389: iconst_1
        //   390: istore_2
        //   391: goto -200 -> 191
        //   394: aload_1
        //   395: checkcast 2	o/Fc$If$if
        //   398: astore_1
        //   399: aload_0
        //   400: getfield 63	o/Fc$If$if:scope	Lo/Er;
        //   403: aload_1
        //   404: getfield 63	o/Fc$If$if:scope	Lo/Er;
        //   407: invokestatic 68	o/vq:ˊ	(Ljava/lang/Object;Ljava/lang/Object;)Z
        //   410: ifeq +6 -> 416
        //   413: goto -84 -> 329
        //   416: goto -89 -> 327
        // Local variable table:
        //   start	length	slot	name	signature
        //   0	419	0	this	if
        //   0	419	1	paramObject	Object
        //   3	388	2	i	int
        //   130	212	3	j	int
        //   59	12	4	l1	long
        //   65	8	6	l2	long
        // Exception table:
        //   from	to	target	type
        //   334	339	84	java/lang/Exception
        //   289	296	156	java/lang/Exception
        //   296	304	156	java/lang/Exception
        //   329	334	156	java/lang/Exception
      }
      
      /* Error */
      public int hashCode()
      {
        // Byte code:
        //   0: goto +46 -> 46
        //   3: iconst_0
        //   4: istore_1
        //   5: goto +116 -> 121
        //   8: astore 5
        //   10: aload 5
        //   12: athrow
        //   13: goto +108 -> 121
        //   16: goto +105 -> 121
        //   19: getstatic 28	o/Fc$If$if:ॱ	I
        //   22: bipush 59
        //   24: iadd
        //   25: istore_1
        //   26: iload_1
        //   27: sipush 128
        //   30: irem
        //   31: putstatic 26	o/Fc$If$if:ˊ	I
        //   34: iload_1
        //   35: iconst_2
        //   36: irem
        //   37: ifeq +6 -> 43
        //   40: goto +234 -> 274
        //   43: goto +168 -> 211
        //   46: goto -27 -> 19
        //   49: aload 6
        //   51: astore 5
        //   53: iload_1
        //   54: tableswitch	default:+22->76, 0:+-51->3, 1:+34->88
        //   76: aload 6
        //   78: astore 5
        //   80: goto +8 -> 88
        //   83: iconst_1
        //   84: istore_1
        //   85: goto -36 -> 49
        //   88: aload 5
        //   90: invokevirtual 72	java/lang/Object:hashCode	()I
        //   93: istore_1
        //   94: goto +61 -> 155
        //   97: aload_0
        //   98: getfield 63	o/Fc$If$if:scope	Lo/Er;
        //   101: astore 6
        //   103: bipush 21
        //   105: iconst_0
        //   106: idiv
        //   107: istore_1
        //   108: aload 6
        //   110: ifnull +6 -> 116
        //   113: goto -30 -> 83
        //   116: iconst_0
        //   117: istore_1
        //   118: goto -69 -> 49
        //   121: aload_0
        //   122: getfield 61	o/Fc$If$if:counterThreshold	I
        //   125: istore_2
        //   126: aload_0
        //   127: getfield 59	o/Fc$If$if:cooldownThreshold	J
        //   130: lstore_3
        //   131: iload_1
        //   132: bipush 31
        //   134: imul
        //   135: iload_2
        //   136: iadd
        //   137: bipush 31
        //   139: imul
        //   140: lload_3
        //   141: lload_3
        //   142: bipush 32
        //   144: lushr
        //   145: lxor
        //   146: l2i
        //   147: iadd
        //   148: ireturn
        //   149: bipush 29
        //   151: istore_1
        //   152: goto +30 -> 182
        //   155: getstatic 28	o/Fc$If$if:ॱ	I
        //   158: bipush 103
        //   160: iadd
        //   161: istore_2
        //   162: iload_2
        //   163: sipush 128
        //   166: irem
        //   167: putstatic 26	o/Fc$If$if:ˊ	I
        //   170: iload_2
        //   171: iconst_2
        //   172: irem
        //   173: ifeq +6 -> 179
        //   176: goto -160 -> 16
        //   179: goto -166 -> 13
        //   182: iload_1
        //   183: lookupswitch	default:+25->208, 8:+-95->88, 29:+-180->3
        //   208: goto -205 -> 3
        //   211: bipush 26
        //   213: istore_1
        //   214: goto +8 -> 222
        //   217: astore 5
        //   219: aload 5
        //   221: athrow
        //   222: iload_1
        //   223: lookupswitch	default:+25->248, 4:+-126->97, 26:+28->251
        //   248: goto -151 -> 97
        //   251: aload_0
        //   252: getfield 63	o/Fc$If$if:scope	Lo/Er;
        //   255: astore 5
        //   257: aload 5
        //   259: ifnull +6 -> 265
        //   262: goto +6 -> 268
        //   265: goto -116 -> 149
        //   268: bipush 8
        //   270: istore_1
        //   271: goto -89 -> 182
        //   274: iconst_4
        //   275: istore_1
        //   276: goto -54 -> 222
        // Local variable table:
        //   start	length	slot	name	signature
        //   0	279	0	this	if
        //   4	272	1	i	int
        //   125	48	2	j	int
        //   130	12	3	l	long
        //   8	3	5	localException1	Exception
        //   51	38	5	localObject	Object
        //   217	3	5	localException2	Exception
        //   255	3	5	localEr1	Er
        //   49	60	6	localEr2	Er
        // Exception table:
        //   from	to	target	type
        //   251	257	8	java/lang/Exception
        //   155	162	217	java/lang/Exception
        //   162	170	217	java/lang/Exception
      }
      
      /* Error */
      public String toString()
      {
        // Byte code:
        //   0: goto +34 -> 34
        //   3: aload_2
        //   4: areturn
        //   5: iload_1
        //   6: tableswitch	default:+22->28, 0:+-3->3, 1:+719->725
        //   28: goto +697 -> 725
        //   31: astore_2
        //   32: aload_2
        //   33: athrow
        //   34: new 76	java/lang/StringBuilder
        //   37: dup
        //   38: invokespecial 78	java/lang/StringBuilder:<init>	()V
        //   41: astore_2
        //   42: aload_2
        //   43: iconst_4
        //   44: newarray char
        //   46: dup
        //   47: iconst_0
        //   48: ldc 79
        //   50: castore
        //   51: dup
        //   52: iconst_1
        //   53: ldc 80
        //   55: castore
        //   56: dup
        //   57: iconst_2
        //   58: ldc 81
        //   60: castore
        //   61: dup
        //   62: iconst_3
        //   63: ldc 82
        //   65: castore
        //   66: iconst_0
        //   67: bipush 24
        //   69: newarray char
        //   71: dup
        //   72: iconst_0
        //   73: ldc 83
        //   75: castore
        //   76: dup
        //   77: iconst_1
        //   78: ldc 84
        //   80: castore
        //   81: dup
        //   82: iconst_2
        //   83: ldc 85
        //   85: castore
        //   86: dup
        //   87: iconst_3
        //   88: ldc 86
        //   90: castore
        //   91: dup
        //   92: iconst_4
        //   93: ldc 87
        //   95: castore
        //   96: dup
        //   97: iconst_5
        //   98: ldc 88
        //   100: castore
        //   101: dup
        //   102: bipush 6
        //   104: ldc 89
        //   106: castore
        //   107: dup
        //   108: bipush 7
        //   110: ldc 90
        //   112: castore
        //   113: dup
        //   114: bipush 8
        //   116: ldc 91
        //   118: castore
        //   119: dup
        //   120: bipush 9
        //   122: ldc 92
        //   124: castore
        //   125: dup
        //   126: bipush 10
        //   128: ldc 93
        //   130: castore
        //   131: dup
        //   132: bipush 11
        //   134: ldc 94
        //   136: castore
        //   137: dup
        //   138: bipush 12
        //   140: ldc 95
        //   142: castore
        //   143: dup
        //   144: bipush 13
        //   146: ldc 96
        //   148: castore
        //   149: dup
        //   150: bipush 14
        //   152: ldc 97
        //   154: castore
        //   155: dup
        //   156: bipush 15
        //   158: ldc 98
        //   160: castore
        //   161: dup
        //   162: bipush 16
        //   164: ldc 99
        //   166: castore
        //   167: dup
        //   168: bipush 17
        //   170: ldc 100
        //   172: castore
        //   173: dup
        //   174: bipush 18
        //   176: ldc 101
        //   178: castore
        //   179: dup
        //   180: bipush 19
        //   182: ldc 102
        //   184: castore
        //   185: dup
        //   186: bipush 20
        //   188: ldc 103
        //   190: castore
        //   191: dup
        //   192: bipush 21
        //   194: ldc 104
        //   196: castore
        //   197: dup
        //   198: bipush 22
        //   200: ldc 105
        //   202: castore
        //   203: dup
        //   204: bipush 23
        //   206: ldc 106
        //   208: castore
        //   209: iconst_0
        //   210: iconst_4
        //   211: newarray char
        //   213: dup
        //   214: iconst_0
        //   215: ldc 107
        //   217: castore
        //   218: dup
        //   219: iconst_1
        //   220: ldc 107
        //   222: castore
        //   223: dup
        //   224: iconst_2
        //   225: ldc 107
        //   227: castore
        //   228: dup
        //   229: iconst_3
        //   230: ldc 107
        //   232: castore
        //   233: invokestatic 109	o/Fc$If$if:ˎ	([CC[CI[C)Ljava/lang/String;
        //   236: invokevirtual 112	java/lang/String:intern	()Ljava/lang/String;
        //   239: invokevirtual 116	java/lang/StringBuilder:append	(Ljava/lang/String;)Ljava/lang/StringBuilder;
        //   242: aload_0
        //   243: getfield 63	o/Fc$If$if:scope	Lo/Er;
        //   246: invokevirtual 119	java/lang/StringBuilder:append	(Ljava/lang/Object;)Ljava/lang/StringBuilder;
        //   249: iconst_4
        //   250: newarray char
        //   252: dup
        //   253: iconst_0
        //   254: ldc 120
        //   256: castore
        //   257: dup
        //   258: iconst_1
        //   259: ldc 121
        //   261: castore
        //   262: dup
        //   263: iconst_2
        //   264: ldc 122
        //   266: castore
        //   267: dup
        //   268: iconst_3
        //   269: ldc 123
        //   271: castore
        //   272: sipush 5235
        //   275: bipush 19
        //   277: newarray char
        //   279: dup
        //   280: iconst_0
        //   281: ldc 124
        //   283: castore
        //   284: dup
        //   285: iconst_1
        //   286: ldc 125
        //   288: castore
        //   289: dup
        //   290: iconst_2
        //   291: ldc 126
        //   293: castore
        //   294: dup
        //   295: iconst_3
        //   296: ldc 127
        //   298: castore
        //   299: dup
        //   300: iconst_4
        //   301: ldc -128
        //   303: castore
        //   304: dup
        //   305: iconst_5
        //   306: ldc -127
        //   308: castore
        //   309: dup
        //   310: bipush 6
        //   312: ldc -126
        //   314: castore
        //   315: dup
        //   316: bipush 7
        //   318: ldc -125
        //   320: castore
        //   321: dup
        //   322: bipush 8
        //   324: ldc -124
        //   326: castore
        //   327: dup
        //   328: bipush 9
        //   330: ldc -123
        //   332: castore
        //   333: dup
        //   334: bipush 10
        //   336: ldc -122
        //   338: castore
        //   339: dup
        //   340: bipush 11
        //   342: ldc -121
        //   344: castore
        //   345: dup
        //   346: bipush 12
        //   348: ldc -120
        //   350: castore
        //   351: dup
        //   352: bipush 13
        //   354: ldc -119
        //   356: castore
        //   357: dup
        //   358: bipush 14
        //   360: ldc -118
        //   362: castore
        //   363: dup
        //   364: bipush 15
        //   366: ldc -117
        //   368: castore
        //   369: dup
        //   370: bipush 16
        //   372: ldc -116
        //   374: castore
        //   375: dup
        //   376: bipush 17
        //   378: ldc -115
        //   380: castore
        //   381: dup
        //   382: bipush 18
        //   384: ldc -114
        //   386: castore
        //   387: ldc -113
        //   389: iconst_4
        //   390: newarray char
        //   392: dup
        //   393: iconst_0
        //   394: ldc 107
        //   396: castore
        //   397: dup
        //   398: iconst_1
        //   399: ldc 107
        //   401: castore
        //   402: dup
        //   403: iconst_2
        //   404: ldc 107
        //   406: castore
        //   407: dup
        //   408: iconst_3
        //   409: ldc 107
        //   411: castore
        //   412: invokestatic 109	o/Fc$If$if:ˎ	([CC[CI[C)Ljava/lang/String;
        //   415: invokevirtual 112	java/lang/String:intern	()Ljava/lang/String;
        //   418: invokevirtual 116	java/lang/StringBuilder:append	(Ljava/lang/String;)Ljava/lang/StringBuilder;
        //   421: aload_0
        //   422: getfield 61	o/Fc$If$if:counterThreshold	I
        //   425: invokevirtual 146	java/lang/StringBuilder:append	(I)Ljava/lang/StringBuilder;
        //   428: iconst_4
        //   429: newarray char
        //   431: dup
        //   432: iconst_0
        //   433: ldc -109
        //   435: castore
        //   436: dup
        //   437: iconst_1
        //   438: ldc -108
        //   440: castore
        //   441: dup
        //   442: iconst_2
        //   443: ldc -107
        //   445: castore
        //   446: dup
        //   447: iconst_3
        //   448: ldc -106
        //   450: castore
        //   451: iconst_0
        //   452: bipush 20
        //   454: newarray char
        //   456: dup
        //   457: iconst_0
        //   458: ldc -105
        //   460: castore
        //   461: dup
        //   462: iconst_1
        //   463: ldc -104
        //   465: castore
        //   466: dup
        //   467: iconst_2
        //   468: ldc -103
        //   470: castore
        //   471: dup
        //   472: iconst_3
        //   473: ldc -102
        //   475: castore
        //   476: dup
        //   477: iconst_4
        //   478: ldc -101
        //   480: castore
        //   481: dup
        //   482: iconst_5
        //   483: ldc -100
        //   485: castore
        //   486: dup
        //   487: bipush 6
        //   489: ldc -99
        //   491: castore
        //   492: dup
        //   493: bipush 7
        //   495: ldc -98
        //   497: castore
        //   498: dup
        //   499: bipush 8
        //   501: ldc -97
        //   503: castore
        //   504: dup
        //   505: bipush 9
        //   507: ldc -96
        //   509: castore
        //   510: dup
        //   511: bipush 10
        //   513: ldc -95
        //   515: castore
        //   516: dup
        //   517: bipush 11
        //   519: ldc -94
        //   521: castore
        //   522: dup
        //   523: bipush 12
        //   525: ldc -93
        //   527: castore
        //   528: dup
        //   529: bipush 13
        //   531: ldc -92
        //   533: castore
        //   534: dup
        //   535: bipush 14
        //   537: ldc -91
        //   539: castore
        //   540: dup
        //   541: bipush 15
        //   543: ldc -90
        //   545: castore
        //   546: dup
        //   547: bipush 16
        //   549: ldc -89
        //   551: castore
        //   552: dup
        //   553: bipush 17
        //   555: ldc -88
        //   557: castore
        //   558: dup
        //   559: bipush 18
        //   561: ldc -87
        //   563: castore
        //   564: dup
        //   565: bipush 19
        //   567: ldc -86
        //   569: castore
        //   570: iconst_0
        //   571: iconst_4
        //   572: newarray char
        //   574: dup
        //   575: iconst_0
        //   576: ldc 107
        //   578: castore
        //   579: dup
        //   580: iconst_1
        //   581: ldc 107
        //   583: castore
        //   584: dup
        //   585: iconst_2
        //   586: ldc 107
        //   588: castore
        //   589: dup
        //   590: iconst_3
        //   591: ldc 107
        //   593: castore
        //   594: invokestatic 109	o/Fc$If$if:ˎ	([CC[CI[C)Ljava/lang/String;
        //   597: invokevirtual 112	java/lang/String:intern	()Ljava/lang/String;
        //   600: invokevirtual 116	java/lang/StringBuilder:append	(Ljava/lang/String;)Ljava/lang/StringBuilder;
        //   603: aload_0
        //   604: getfield 59	o/Fc$If$if:cooldownThreshold	J
        //   607: invokevirtual 173	java/lang/StringBuilder:append	(J)Ljava/lang/StringBuilder;
        //   610: iconst_4
        //   611: newarray char
        //   613: dup
        //   614: iconst_0
        //   615: ldc -82
        //   617: castore
        //   618: dup
        //   619: iconst_1
        //   620: ldc -81
        //   622: castore
        //   623: dup
        //   624: iconst_2
        //   625: ldc -80
        //   627: castore
        //   628: dup
        //   629: iconst_3
        //   630: ldc -79
        //   632: castore
        //   633: sipush 7709
        //   636: iconst_1
        //   637: newarray char
        //   639: dup
        //   640: iconst_0
        //   641: ldc -78
        //   643: castore
        //   644: ldc -77
        //   646: iconst_4
        //   647: newarray char
        //   649: dup
        //   650: iconst_0
        //   651: ldc 107
        //   653: castore
        //   654: dup
        //   655: iconst_1
        //   656: ldc 107
        //   658: castore
        //   659: dup
        //   660: iconst_2
        //   661: ldc 107
        //   663: castore
        //   664: dup
        //   665: iconst_3
        //   666: ldc 107
        //   668: castore
        //   669: invokestatic 109	o/Fc$If$if:ˎ	([CC[CI[C)Ljava/lang/String;
        //   672: invokevirtual 112	java/lang/String:intern	()Ljava/lang/String;
        //   675: invokevirtual 116	java/lang/StringBuilder:append	(Ljava/lang/String;)Ljava/lang/StringBuilder;
        //   678: invokevirtual 181	java/lang/StringBuilder:toString	()Ljava/lang/String;
        //   681: astore_2
        //   682: goto +13 -> 695
        //   685: iconst_0
        //   686: istore_1
        //   687: goto -682 -> 5
        //   690: iconst_1
        //   691: istore_1
        //   692: goto -687 -> 5
        //   695: getstatic 28	o/Fc$If$if:ॱ	I
        //   698: bipush 19
        //   700: iadd
        //   701: istore_1
        //   702: iload_1
        //   703: sipush 128
        //   706: irem
        //   707: putstatic 26	o/Fc$If$if:ˊ	I
        //   710: iload_1
        //   711: iconst_2
        //   712: irem
        //   713: ifeq +6 -> 719
        //   716: goto -26 -> 690
        //   719: goto -34 -> 685
        //   722: astore_2
        //   723: aload_2
        //   724: athrow
        //   725: bipush 83
        //   727: iconst_0
        //   728: idiv
        //   729: istore_1
        //   730: aload_2
        //   731: areturn
        // Exception table:
        //   from	to	target	type
        //   42	682	722	java/lang/Exception
      }
      
      /* Error */
      public final int ˊ()
      {
        // Byte code:
        //   0: goto +120 -> 120
        //   3: iload_2
        //   4: ireturn
        //   5: astore_3
        //   6: aload_3
        //   7: athrow
        //   8: iload_1
        //   9: lookupswitch	default:+27->36, 43:+-6->3, 84:+61->70
        //   36: iload_2
        //   37: ireturn
        //   38: aload_0
        //   39: getfield 61	o/Fc$If$if:counterThreshold	I
        //   42: istore_2
        //   43: getstatic 26	o/Fc$If$if:ˊ	I
        //   46: bipush 89
        //   48: iadd
        //   49: istore_1
        //   50: iload_1
        //   51: sipush 128
        //   54: irem
        //   55: putstatic 28	o/Fc$If$if:ॱ	I
        //   58: iload_1
        //   59: iconst_2
        //   60: irem
        //   61: ifne +6 -> 67
        //   64: goto +11 -> 75
        //   67: goto +14 -> 81
        //   70: aconst_null
        //   71: arraylength
        //   72: istore_1
        //   73: iload_2
        //   74: ireturn
        //   75: bipush 84
        //   77: istore_1
        //   78: goto -70 -> 8
        //   81: bipush 43
        //   83: istore_1
        //   84: goto -76 -> 8
        //   87: getstatic 26	o/Fc$If$if:ˊ	I
        //   90: bipush 43
        //   92: iadd
        //   93: istore_1
        //   94: iload_1
        //   95: sipush 128
        //   98: irem
        //   99: putstatic 28	o/Fc$If$if:ॱ	I
        //   102: iload_1
        //   103: iconst_2
        //   104: irem
        //   105: ifne +6 -> 111
        //   108: goto +9 -> 117
        //   111: goto -73 -> 38
        //   114: astore_3
        //   115: aload_3
        //   116: athrow
        //   117: goto -79 -> 38
        //   120: goto -33 -> 87
        // Local variable table:
        //   start	length	slot	name	signature
        //   0	123	0	this	if
        //   8	97	1	i	int
        //   3	71	2	j	int
        //   5	2	3	localException1	Exception
        //   114	2	3	localException2	Exception
        // Exception table:
        //   from	to	target	type
        //   38	43	5	java/lang/Exception
        //   87	94	5	java/lang/Exception
        //   94	102	5	java/lang/Exception
        //   94	102	114	java/lang/Exception
      }
      
      /* Error */
      public final long ˋ()
      {
        // Byte code:
        //   0: goto +46 -> 46
        //   3: getstatic 26	o/Fc$If$if:ˊ	I
        //   6: bipush 17
        //   8: iadd
        //   9: istore_1
        //   10: iload_1
        //   11: sipush 128
        //   14: irem
        //   15: putstatic 28	o/Fc$If$if:ॱ	I
        //   18: iload_1
        //   19: iconst_2
        //   20: irem
        //   21: ifne +6 -> 27
        //   24: goto +19 -> 43
        //   27: goto +8 -> 35
        //   30: astore 4
        //   32: aload 4
        //   34: athrow
        //   35: aload_0
        //   36: getfield 59	o/Fc$If$if:cooldownThreshold	J
        //   39: lstore_2
        //   40: goto +9 -> 49
        //   43: goto -8 -> 35
        //   46: goto -43 -> 3
        //   49: getstatic 28	o/Fc$If$if:ॱ	I
        //   52: bipush 73
        //   54: iadd
        //   55: istore_1
        //   56: iload_1
        //   57: sipush 128
        //   60: irem
        //   61: putstatic 26	o/Fc$If$if:ˊ	I
        //   64: iload_1
        //   65: iconst_2
        //   66: irem
        //   67: ifeq +5 -> 72
        //   70: lload_2
        //   71: lreturn
        //   72: lload_2
        //   73: lreturn
        // Local variable table:
        //   start	length	slot	name	signature
        //   0	74	0	this	if
        //   9	58	1	i	int
        //   39	34	2	l	long
        //   30	3	4	localException	Exception
        // Exception table:
        //   from	to	target	type
        //   35	40	30	java/lang/Exception
      }
    }
  }
  
  public static final class if
  {
    private static int ˊ = 1;
    private static char[] ˋ = { 67, 111, 110, 116, 97, 99, 83, 101, 105, 103, 115, 40, 108, 114, 80, 104, 78, 117, 109, 98, 61, 44, 32, 69, 65, 100, 87, 70, 107, 41, 68, 71, 72, 73, 74, 75 };
    private static char ˎ = '\006';
    private static int ˏ = 0;
    private final String callCenterEmailAddress;
    private final String callCenterFacebook;
    private final String callCenterPhoneNumber;
    private final String callCenterWebsite;
    
    /* Error */
    private static String ˊ(char[] paramArrayOfChar, int paramInt, byte paramByte)
    {
      // Byte code:
      //   0: goto +358 -> 358
      //   3: goto +536 -> 539
      //   6: goto +389 -> 395
      //   9: iload_3
      //   10: lookupswitch	default:+26->36, 27:+296->306, 41:+361->371
      //   36: goto +270 -> 306
      //   39: iload 5
      //   41: istore 8
      //   43: iload 6
      //   45: istore 10
      //   47: iload 5
      //   49: istore 7
      //   51: iload 6
      //   53: istore 4
      //   55: iload 9
      //   57: tableswitch	default:+23->80, 0:+423->480, 1:+89->146
      //   80: iload 5
      //   82: istore 7
      //   84: iload 6
      //   86: istore 4
      //   88: goto +392 -> 480
      //   91: getstatic 25	o/Fc$if:ˊ	I
      //   94: bipush 117
      //   96: iadd
      //   97: istore_3
      //   98: iload_3
      //   99: sipush 128
      //   102: irem
      //   103: putstatic 23	o/Fc$if:ˏ	I
      //   106: iload_3
      //   107: iconst_2
      //   108: irem
      //   109: ifeq +6 -> 115
      //   112: goto -106 -> 6
      //   115: goto +280 -> 395
      //   118: astore_0
      //   119: aload_0
      //   120: athrow
      //   121: aload_0
      //   122: iload_3
      //   123: caload
      //   124: istore 5
      //   126: aload_0
      //   127: iload_3
      //   128: iconst_1
      //   129: iadd
      //   130: caload
      //   131: istore 6
      //   133: iload 5
      //   135: iload 6
      //   137: if_icmpne +6 -> 143
      //   140: goto +61 -> 201
      //   143: goto +331 -> 474
      //   146: aload 13
      //   148: iload_3
      //   149: iload 8
      //   151: iload_2
      //   152: isub
      //   153: i2c
      //   154: castore
      //   155: aload 13
      //   157: iload_3
      //   158: iconst_1
      //   159: iadd
      //   160: iload 10
      //   162: iload_2
      //   163: isub
      //   164: i2c
      //   165: castore
      //   166: goto -163 -> 3
      //   169: goto +423 -> 592
      //   172: getstatic 25	o/Fc$if:ˊ	I
      //   175: iconst_3
      //   176: iadd
      //   177: istore 4
      //   179: iload 4
      //   181: sipush 128
      //   184: irem
      //   185: putstatic 23	o/Fc$if:ˏ	I
      //   188: iload 4
      //   190: iconst_2
      //   191: irem
      //   192: ifeq +6 -> 198
      //   195: goto -74 -> 121
      //   198: goto +355 -> 553
      //   201: iconst_1
      //   202: istore 9
      //   204: goto -165 -> 39
      //   207: bipush 68
      //   209: istore 4
      //   211: iload 4
      //   213: lookupswitch	default:+27->240, 68:+209->422, 85:+393->606
      //   240: goto +366 -> 606
      //   243: iload 7
      //   245: iload 11
      //   247: invokestatic 74	o/oO:ˊ	(II)I
      //   250: istore 4
      //   252: iload 8
      //   254: iload 11
      //   256: invokestatic 74	o/oO:ˊ	(II)I
      //   259: istore 7
      //   261: iload 6
      //   263: iload 4
      //   265: iload 11
      //   267: invokestatic 77	o/oO:ˏ	(III)I
      //   270: istore 4
      //   272: iload 5
      //   274: iload 7
      //   276: iload 11
      //   278: invokestatic 77	o/oO:ˏ	(III)I
      //   281: istore 5
      //   283: aload 13
      //   285: iload_3
      //   286: aload 12
      //   288: iload 4
      //   290: caload
      //   291: castore
      //   292: aload 13
      //   294: iload_3
      //   295: iconst_1
      //   296: iadd
      //   297: aload 12
      //   299: iload 5
      //   301: caload
      //   302: castore
      //   303: goto +236 -> 539
      //   306: iload_1
      //   307: iconst_1
      //   308: isub
      //   309: istore_1
      //   310: aload 13
      //   312: iload_1
      //   313: aload_0
      //   314: iload_1
      //   315: caload
      //   316: iload_2
      //   317: isub
      //   318: i2c
      //   319: castore
      //   320: goto +349 -> 669
      //   323: goto -154 -> 169
      //   326: iconst_0
      //   327: istore_3
      //   328: goto +264 -> 592
      //   331: getstatic 25	o/Fc$if:ˊ	I
      //   334: bipush 121
      //   336: iadd
      //   337: istore_3
      //   338: iload_3
      //   339: sipush 128
      //   342: irem
      //   343: putstatic 23	o/Fc$if:ˏ	I
      //   346: iload_3
      //   347: iconst_2
      //   348: irem
      //   349: ifeq +6 -> 355
      //   352: goto +234 -> 586
      //   355: goto +34 -> 389
      //   358: goto -267 -> 91
      //   361: bipush 25
      //   363: istore 4
      //   365: goto +70 -> 435
      //   368: astore_0
      //   369: aload_0
      //   370: athrow
      //   371: iload_1
      //   372: bipush 118
      //   374: iadd
      //   375: istore_1
      //   376: aload 13
      //   378: iload_1
      //   379: aload_0
      //   380: iload_1
      //   381: caload
      //   382: iload_2
      //   383: idiv
      //   384: i2c
      //   385: castore
      //   386: goto +283 -> 669
      //   389: bipush 27
      //   391: istore_3
      //   392: goto -383 -> 9
      //   395: getstatic 63	o/Fc$if:ˋ	[C
      //   398: astore 12
      //   400: getstatic 65	o/Fc$if:ˎ	C
      //   403: istore 11
      //   405: iload_1
      //   406: newarray char
      //   408: astore 13
      //   410: iload_1
      //   411: iconst_2
      //   412: irem
      //   413: ifeq +6 -> 419
      //   416: goto -85 -> 331
      //   419: goto +250 -> 669
      //   422: iload 6
      //   424: iload 5
      //   426: if_icmpne +6 -> 432
      //   429: goto -186 -> 243
      //   432: goto +248 -> 680
      //   435: iload 4
      //   437: lookupswitch	default:+27->464, 19:+92->529, 25:+-265->172
      //   464: goto +65 -> 529
      //   467: bipush 19
      //   469: istore 4
      //   471: goto -36 -> 435
      //   474: iconst_0
      //   475: istore 9
      //   477: goto -438 -> 39
      //   480: iload 7
      //   482: iload 11
      //   484: invokestatic 80	o/oO:ॱ	(II)I
      //   487: istore 6
      //   489: iload 7
      //   491: iload 11
      //   493: invokestatic 82	o/oO:ˋ	(II)I
      //   496: istore 7
      //   498: iload 4
      //   500: iload 11
      //   502: invokestatic 80	o/oO:ॱ	(II)I
      //   505: istore 5
      //   507: iload 4
      //   509: iload 11
      //   511: invokestatic 82	o/oO:ˋ	(II)I
      //   514: istore 8
      //   516: iload 7
      //   518: iload 8
      //   520: if_icmpne +6 -> 526
      //   523: goto +23 -> 546
      //   526: goto -319 -> 207
      //   529: new 84	java/lang/String
      //   532: dup
      //   533: aload 13
      //   535: invokespecial 88	java/lang/String:<init>	([C)V
      //   538: areturn
      //   539: iload_3
      //   540: iconst_2
      //   541: iadd
      //   542: istore_3
      //   543: goto +182 -> 725
      //   546: bipush 85
      //   548: istore 4
      //   550: goto -339 -> 211
      //   553: aload_0
      //   554: iload_3
      //   555: caload
      //   556: istore 7
      //   558: aload_0
      //   559: iload_3
      //   560: iconst_1
      //   561: iadd
      //   562: caload
      //   563: istore 4
      //   565: iload 7
      //   567: iload 4
      //   569: if_icmpne +14 -> 583
      //   572: iload 7
      //   574: istore 8
      //   576: iload 4
      //   578: istore 10
      //   580: goto -434 -> 146
      //   583: goto -103 -> 480
      //   586: bipush 41
      //   588: istore_3
      //   589: goto -580 -> 9
      //   592: iload_3
      //   593: iload_1
      //   594: if_icmpge +6 -> 600
      //   597: goto -236 -> 361
      //   600: goto -133 -> 467
      //   603: goto -64 -> 539
      //   606: iload 6
      //   608: iload 11
      //   610: invokestatic 74	o/oO:ˊ	(II)I
      //   613: istore 4
      //   615: iload 5
      //   617: iload 11
      //   619: invokestatic 74	o/oO:ˊ	(II)I
      //   622: istore 5
      //   624: iload 4
      //   626: iload 7
      //   628: iload 11
      //   630: invokestatic 77	o/oO:ˏ	(III)I
      //   633: istore 4
      //   635: iload 5
      //   637: iload 8
      //   639: iload 11
      //   641: invokestatic 77	o/oO:ˏ	(III)I
      //   644: istore 5
      //   646: aload 13
      //   648: iload_3
      //   649: aload 12
      //   651: iload 4
      //   653: caload
      //   654: castore
      //   655: aload 13
      //   657: iload_3
      //   658: iconst_1
      //   659: iadd
      //   660: aload 12
      //   662: iload 5
      //   664: caload
      //   665: castore
      //   666: goto -127 -> 539
      //   669: iload_1
      //   670: iconst_1
      //   671: if_icmple +6 -> 677
      //   674: goto -348 -> 326
      //   677: goto -148 -> 529
      //   680: iload 6
      //   682: iload 8
      //   684: iload 11
      //   686: invokestatic 77	o/oO:ˏ	(III)I
      //   689: istore 4
      //   691: iload 5
      //   693: iload 7
      //   695: iload 11
      //   697: invokestatic 77	o/oO:ˏ	(III)I
      //   700: istore 5
      //   702: aload 13
      //   704: iload_3
      //   705: aload 12
      //   707: iload 4
      //   709: caload
      //   710: castore
      //   711: aload 13
      //   713: iload_3
      //   714: iconst_1
      //   715: iadd
      //   716: aload 12
      //   718: iload 5
      //   720: caload
      //   721: castore
      //   722: goto -119 -> 603
      //   725: getstatic 25	o/Fc$if:ˊ	I
      //   728: bipush 43
      //   730: iadd
      //   731: istore 4
      //   733: iload 4
      //   735: sipush 128
      //   738: irem
      //   739: putstatic 23	o/Fc$if:ˏ	I
      //   742: iload 4
      //   744: iconst_2
      //   745: irem
      //   746: ifeq +6 -> 752
      //   749: goto -426 -> 323
      //   752: goto -583 -> 169
      // Local variable table:
      //   start	length	slot	name	signature
      //   0	755	0	paramArrayOfChar	char[]
      //   0	755	1	paramInt	int
      //   0	755	2	paramByte	byte
      //   9	707	3	i	int
      //   53	693	4	b1	byte
      //   39	680	5	b2	byte
      //   43	638	6	b3	byte
      //   49	645	7	b4	byte
      //   41	642	8	b5	byte
      //   55	421	9	j	int
      //   45	534	10	b6	byte
      //   245	451	11	k	int
      //   286	431	12	arrayOfChar1	char[]
      //   146	566	13	arrayOfChar2	char[]
      // Exception table:
      //   from	to	target	type
      //   252	261	118	java/lang/Exception
      //   331	346	118	java/lang/Exception
      //   243	252	368	java/lang/Exception
      //   261	272	368	java/lang/Exception
      //   272	283	368	java/lang/Exception
    }
    
    public boolean equals(Object paramObject)
    {
      break label135;
      Object localObject;
      while (!vq.ˊ(this.callCenterWebsite, ((if)localObject).callCenterWebsite))
      {
        break label264;
        return true;
        try
        {
          paramObject = (if)paramObject;
          localObject = this.callCenterPhoneNumber;
          String str = paramObject.callCenterPhoneNumber;
          boolean bool = vq.ˊ(localObject, str);
          if (bool) {
            break label386;
          }
        }
        catch (Exception paramObject)
        {
          label61:
          throw paramObject;
        }
        return false;
        label66:
        if (!vq.ˊ(this.callCenterEmailAddress, ((if)localObject).callCenterEmailAddress))
        {
          break label264;
          label87:
          if (vq.ˊ(this.callCenterFacebook, ((if)localObject).callCenterFacebook)) {
            break label302;
          }
          break label374;
        }
      }
      int i;
      label135:
      label179:
      label217:
      label220:
      label251:
      label264:
      for (;;)
      {
        i = ˏ + 97;
        ˊ = i % 128;
        if (i % 2 != 0)
        {
          break label61;
          break label308;
        }
        for (;;)
        {
          i = 27;
          break label179;
          throw new NullPointerException();
          i = ˏ + 61;
          ˊ = i % 128;
          if (i % 2 == 0) {
            break label371;
          }
          break label87;
          switch (i)
          {
          default: 
            break label264;
            do
            {
              i = 26;
              break label179;
              break;
              switch (i)
              {
              case 80: 
              default: 
                break label264;
              }
            } while ((paramObject instanceof if));
          }
        }
      }
      for (;;)
      {
        localObject = paramObject;
        switch (i)
        {
        }
        localObject = paramObject;
        break label66;
        label302:
        i = 80;
        break label220;
        label308:
        if (this != paramObject) {
          break label251;
        }
        break label217;
        i = ˏ + 53;
        ˊ = i % 128;
        if (i % 2 != 0) {
          break;
        }
        paramObject = (if)paramObject;
        vq.ˊ(this.callCenterPhoneNumber, paramObject.callCenterPhoneNumber);
        throw new NullPointerException();
        label371:
        break label87;
        label374:
        i = 56;
        break label220;
        i = 38;
        continue;
        label386:
        i = 76;
      }
    }
    
    /* Error */
    public int hashCode()
    {
      // Byte code:
      //   0: goto +149 -> 149
      //   3: getstatic 25	o/Fc$if:ˊ	I
      //   6: bipush 33
      //   8: iadd
      //   9: istore_3
      //   10: iload_3
      //   11: sipush 128
      //   14: irem
      //   15: putstatic 23	o/Fc$if:ˏ	I
      //   18: iload_3
      //   19: iconst_2
      //   20: irem
      //   21: ifeq +6 -> 27
      //   24: goto +113 -> 137
      //   27: goto +212 -> 239
      //   30: bipush 37
      //   32: istore_1
      //   33: goto +271 -> 304
      //   36: iload_3
      //   37: lookupswitch	default:+27->64, 33:+315->352, 47:+-34->3
      //   64: goto +288 -> 352
      //   67: iconst_0
      //   68: istore_2
      //   69: goto +266 -> 335
      //   72: bipush 68
      //   74: istore 4
      //   76: goto +24 -> 100
      //   79: aload 6
      //   81: invokevirtual 111	java/lang/Object:hashCode	()I
      //   84: istore 4
      //   86: goto +162 -> 248
      //   89: astore 6
      //   91: aload 6
      //   93: athrow
      //   94: iconst_0
      //   95: istore 4
      //   97: goto +55 -> 152
      //   100: iload 4
      //   102: lookupswitch	default:+26->128, 66:+-8->94, 68:+-23->79
      //   128: goto -49 -> 79
      //   131: bipush 33
      //   133: istore_1
      //   134: goto +170 -> 304
      //   137: goto +102 -> 239
      //   140: goto +285 -> 425
      //   143: bipush 47
      //   145: istore_3
      //   146: goto -110 -> 36
      //   149: goto +64 -> 213
      //   152: iload_1
      //   153: bipush 31
      //   155: imul
      //   156: iload_2
      //   157: iadd
      //   158: bipush 31
      //   160: imul
      //   161: iload_3
      //   162: iadd
      //   163: bipush 31
      //   165: imul
      //   166: iload 4
      //   168: iadd
      //   169: ireturn
      //   170: getstatic 25	o/Fc$if:ˊ	I
      //   173: bipush 55
      //   175: iadd
      //   176: istore 4
      //   178: iload 4
      //   180: sipush 128
      //   183: irem
      //   184: putstatic 23	o/Fc$if:ˏ	I
      //   187: iload 4
      //   189: iconst_2
      //   190: irem
      //   191: ifeq +6 -> 197
      //   194: goto +6 -> 200
      //   197: goto +6 -> 203
      //   200: goto +87 -> 287
      //   203: goto +84 -> 287
      //   206: bipush 66
      //   208: istore 4
      //   210: goto -110 -> 100
      //   213: getstatic 25	o/Fc$if:ˊ	I
      //   216: iconst_1
      //   217: iadd
      //   218: istore_1
      //   219: iload_1
      //   220: sipush 128
      //   223: irem
      //   224: putstatic 23	o/Fc$if:ˏ	I
      //   227: iload_1
      //   228: iconst_2
      //   229: irem
      //   230: ifeq +6 -> 236
      //   233: goto -203 -> 30
      //   236: goto -105 -> 131
      //   239: aload 6
      //   241: invokevirtual 111	java/lang/Object:hashCode	()I
      //   244: istore_3
      //   245: goto +42 -> 287
      //   248: getstatic 23	o/Fc$if:ˏ	I
      //   251: bipush 23
      //   253: iadd
      //   254: istore 5
      //   256: iload 5
      //   258: sipush 128
      //   261: irem
      //   262: putstatic 25	o/Fc$if:ˊ	I
      //   265: iload 5
      //   267: iconst_2
      //   268: irem
      //   269: ifne +6 -> 275
      //   272: goto -132 -> 140
      //   275: goto +150 -> 425
      //   278: aload 6
      //   280: invokevirtual 111	java/lang/Object:hashCode	()I
      //   283: istore_1
      //   284: goto +124 -> 408
      //   287: aload_0
      //   288: getfield 103	o/Fc$if:callCenterFacebook	Ljava/lang/String;
      //   291: astore 6
      //   293: aload 6
      //   295: ifnull +6 -> 301
      //   298: goto -226 -> 72
      //   301: goto -95 -> 206
      //   304: iload_1
      //   305: lookupswitch	default:+27->332, 33:+86->391, 37:+72->377
      //   332: goto +59 -> 391
      //   335: aload_0
      //   336: getfield 92	o/Fc$if:callCenterWebsite	Ljava/lang/String;
      //   339: astore 6
      //   341: aload 6
      //   343: ifnull +6 -> 349
      //   346: goto -203 -> 143
      //   349: goto +22 -> 371
      //   352: iconst_0
      //   353: istore_3
      //   354: goto -184 -> 170
      //   357: aload 6
      //   359: invokevirtual 111	java/lang/Object:hashCode	()I
      //   362: istore_2
      //   363: goto -28 -> 335
      //   366: iconst_0
      //   367: istore_1
      //   368: goto +40 -> 408
      //   371: bipush 33
      //   373: istore_3
      //   374: goto -338 -> 36
      //   377: aload_0
      //   378: getfield 99	o/Fc$if:callCenterPhoneNumber	Ljava/lang/String;
      //   381: astore 6
      //   383: new 105	java/lang/NullPointerException
      //   386: dup
      //   387: invokespecial 107	java/lang/NullPointerException:<init>	()V
      //   390: athrow
      //   391: aload_0
      //   392: getfield 99	o/Fc$if:callCenterPhoneNumber	Ljava/lang/String;
      //   395: astore 6
      //   397: aload 6
      //   399: ifnull +6 -> 405
      //   402: goto -124 -> 278
      //   405: goto -39 -> 366
      //   408: aload_0
      //   409: getfield 101	o/Fc$if:callCenterEmailAddress	Ljava/lang/String;
      //   412: astore 6
      //   414: aload 6
      //   416: ifnull +6 -> 422
      //   419: goto -62 -> 357
      //   422: goto -355 -> 67
      //   425: goto -273 -> 152
      // Local variable table:
      //   start	length	slot	name	signature
      //   0	428	0	this	if
      //   32	336	1	i	int
      //   68	295	2	j	int
      //   9	365	3	k	int
      //   74	135	4	m	int
      //   254	15	5	n	int
      //   79	1	6	localObject	Object
      //   89	190	6	localException	Exception
      //   291	124	6	str	String
      // Exception table:
      //   from	to	target	type
      //   377	391	89	java/lang/Exception
    }
    
    public String toString()
    {
      String str;
      for (;;)
      {
        i = 0;
        switch (i)
        {
        default: 
          return str;
          break;
        case 0: 
          do
          {
            i = 1;
            break;
            return str;
            str = ˊ(new char[] { 1, 2, 3, 4, 5, 0, 0, 9, 9, 1, 2, 9, 3, 8, 11, 6, 0, 5, 174, 174, 1, 6, 3, 4, 13, 19, 15, 16, 2, 3, 10, 13, 12, 23, 25, 13, 14, 19 }, 38, (byte)66).intern() + this.callCenterPhoneNumber + ˊ(new char[] { 22, 23, 0, 5, 145, 145, 1, 6, 3, 4, 13, 19, 18, 19, 2, 10, 18, 30, 137, 137, 19, 13, 152, 152, 98 }, 25, (byte)37).intern() + this.callCenterEmailAddress + ˊ(new char[] { 22, 23, 0, 5, 132, 132, 1, 6, 3, 4, 13, 19, 25, 8, 22, 7, 9, 2, 8, 19 }, 20, (byte)24).intern() + this.callCenterWebsite + ˊ(new char[] { 22, 23, 0, 5, 113, 113, 1, 6, 3, 4, 13, 19, 28, 3, 1, 11, 25, 7, 4, 25, 66 }, 21, (byte)5).intern() + this.callCenterFacebook + ˊ(new char[] { 156 }, 1, (byte)115).intern();
            i = ˏ + 27;
            ˊ = i % 128;
          } while (i % 2 == 0);
        }
      }
      int i = 49 / 0;
      return str;
    }
    
    /* Error */
    public final String ˋ()
    {
      // Byte code:
      //   0: goto +69 -> 69
      //   3: astore_2
      //   4: aload_2
      //   5: athrow
      //   6: getstatic 25	o/Fc$if:ˊ	I
      //   9: bipush 113
      //   11: iadd
      //   12: istore_1
      //   13: iload_1
      //   14: sipush 128
      //   17: irem
      //   18: putstatic 23	o/Fc$if:ˏ	I
      //   21: iload_1
      //   22: iconst_2
      //   23: irem
      //   24: ifeq +6 -> 30
      //   27: goto +40 -> 67
      //   30: aload_2
      //   31: areturn
      //   32: getstatic 23	o/Fc$if:ˏ	I
      //   35: bipush 39
      //   37: iadd
      //   38: istore_1
      //   39: iload_1
      //   40: sipush 128
      //   43: irem
      //   44: putstatic 25	o/Fc$if:ˊ	I
      //   47: iload_1
      //   48: iconst_2
      //   49: irem
      //   50: ifne +6 -> 56
      //   53: goto +19 -> 72
      //   56: aload_0
      //   57: getfield 92	o/Fc$if:callCenterWebsite	Ljava/lang/String;
      //   60: astore_2
      //   61: goto -55 -> 6
      //   64: astore_2
      //   65: aload_2
      //   66: athrow
      //   67: aload_2
      //   68: areturn
      //   69: goto -37 -> 32
      //   72: goto -16 -> 56
      // Local variable table:
      //   start	length	slot	name	signature
      //   0	75	0	this	if
      //   12	38	1	i	int
      //   3	28	2	localException1	Exception
      //   60	1	2	str	String
      //   64	4	2	localException2	Exception
      // Exception table:
      //   from	to	target	type
      //   32	39	3	java/lang/Exception
      //   39	47	3	java/lang/Exception
      //   39	47	64	java/lang/Exception
    }
    
    public final String ˎ()
    {
      for (;;)
      {
        int i;
        switch (i)
        {
        case 66: 
        default: 
          try
          {
            String str1 = this.callCenterPhoneNumber;
            i = 62 / 0;
            return str1;
          }
          catch (Exception localException)
          {
            throw localException;
          }
          i = 82;
          continue;
          for (;;)
          {
            i = ˊ + 49;
            ˏ = i % 128;
            if (i % 2 != 0) {
              break label90;
            }
            break;
          }
        case 82: 
          String str2 = this.callCenterPhoneNumber;
          return str2;
          label90:
          i = 66;
        }
      }
    }
    
    public final String ˏ()
    {
      for (;;)
      {
        int i;
        try
        {
          String str1 = this.callCenterEmailAddress;
          return str1;
        }
        catch (Exception localException)
        {
          throw localException;
        }
        switch (i)
        {
        case 1: 
        default: 
          break;
        case 0: 
          String str2 = this.callCenterEmailAddress;
          i = null.length;
          return str2;
          i = ˏ + 117;
          ˊ = i % 128;
          if (i % 2 != 0) {
            i = 1;
          } else {
            i = 0;
          }
          break;
        }
      }
    }
    
    public final String ॱ()
    {
      break label101;
      int i = ˏ + 59;
      ˊ = i % 128;
      if (i % 2 != 0) {
        break label159;
      }
      for (;;)
      {
        try
        {
          i = ˏ;
          i += 111;
          ˊ = i % 128;
          if (i % 2 == 0) {
            break label154;
          }
        }
        catch (Exception localException)
        {
          label101:
          throw localException;
        }
        switch (i)
        {
        default: 
          continue;
          i = 26;
          break;
        case 0: 
          String str1 = this.callCenterFacebook;
          break;
          continue;
          i = null.length;
          return str1;
          switch (i)
          {
          }
          return str1;
        case 1: 
          String str2 = this.callCenterFacebook;
          i = 93 / 0;
          break;
          label154:
          i = 1;
          continue;
          label159:
          i = 13;
          continue;
          i = 0;
        }
      }
    }
  }
  
  public static final class ˊ
  {
    private static int ˊ = 0;
    private static int ˋ = 1;
    private static char[] ˎ = { 30, 88, 108, 109, 112, 102, 107, 79, 77, 109, 106, 107, 110, 116, 108, 92, 91, 100, 90, 20 };
    @nT(ˋ="nfcSchemesSettingsMap")
    private final if values;
    
    private static String ˋ(int[] paramArrayOfInt, byte[] paramArrayOfByte, boolean paramBoolean)
    {
      break label310;
      int i;
      int m;
      char[] arrayOfChar;
      int j;
      Object localObject;
      if (i >= m)
      {
        break label228;
        for (;;)
        {
          arrayOfChar[j] = ((char)((localObject[j] << '\001') - i));
          break label466;
          if (paramArrayOfByte[j] == 1) {
            break;
          }
        }
        for (;;)
        {
          break;
          localObject = paramArrayOfByte;
          switch (i)
          {
          default: 
            localObject = paramArrayOfByte;
            break label280;
            label82:
            if (i < m) {
              break label397;
            }
          }
        }
      }
      label109:
      label136:
      label139:
      label145:
      label148:
      label153:
      label183:
      label193:
      label228:
      label258:
      label261:
      label267:
      label280:
      label310:
      label360:
      label397:
      label427:
      label459:
      label466:
      label493:
      label518:
      label541:
      label544:
      label581:
      label635:
      for (;;)
      {
        i = arrayOfChar[j];
        j += 1;
        break label267;
        i = ˊ + 101;
        ˋ = i % 128;
        int n;
        int i1;
        if (i % 2 != 0)
        {
          break label581;
          break;
          i = 38;
          break label193;
          break label635;
          i = 0;
          break;
          int k;
          switch (k)
          {
          case 98: 
          default: 
            break label261;
            while (!paramBoolean)
            {
              break label427;
              switch (i)
              {
              }
            }
            i = 0;
            break;
            return new String((char[])localObject);
            arrayOfChar[j] = ((char)((localObject[j] << '\001') + 1 - i));
            continue;
            break;
          case 66: 
            paramArrayOfByte = arrayOfChar;
            break;
          }
          for (;;)
          {
            if (j >= m)
            {
              break label459;
              if (n > 0) {
                break label148;
              }
              break label228;
            }
            for (;;)
            {
              localObject[i] = paramArrayOfByte[(m - i - 1)];
              i += 1;
              break;
              break label109;
              localObject = new char[m];
              System.arraycopy(paramArrayOfByte, 0, localObject, 0, m);
              System.arraycopy(localObject, 0, paramArrayOfByte, m - i1, i1);
              System.arraycopy(localObject, i1, paramArrayOfByte, 0, m - i1);
              break label183;
              j = ˊ + 109;
              ˋ = j % 128;
              if (j % 2 == 0) {
                break label136;
              }
              break label541;
              k = 98;
              break label153;
              j = ˊ + 59;
              ˋ = j % 128;
              if (j % 2 == 0) {
                break label518;
              }
            }
            i = 1;
            break;
            i = ˋ + 55;
            ˊ = i % 128;
            if (i % 2 != 0) {
              break label258;
            }
            break label544;
            k = 66;
            break label153;
            i = ˋ + 33;
            ˊ = i % 128;
            if (i % 2 != 0) {
              break label145;
            }
            break label635;
            arrayOfChar = new char[m];
            i = 0;
            j = 0;
          }
        }
        for (;;)
        {
          if (i1 <= 0)
          {
            break label139;
            localObject[i] = paramArrayOfByte[(m - i >>> 1)];
            i += 86;
            break label82;
            break label581;
            break;
            localObject = new char[m];
            i = 0;
            break label82;
          }
          i = 14;
          break label193;
          localObject[i] = ((char)(localObject[i] - paramArrayOfInt[2]));
          i += 1;
          break label360;
          i = paramArrayOfInt[0];
          m = paramArrayOfInt[1];
          n = paramArrayOfInt[2];
          i1 = paramArrayOfInt[3];
          arrayOfChar = ˎ;
          localObject = new char[m];
          System.arraycopy(arrayOfChar, i, localObject, 0, m);
          if (paramArrayOfByte != null) {
            break label493;
          }
          paramArrayOfByte = (byte[])localObject;
        }
      }
    }
    
    public boolean equals(Object paramObject)
    {
      int i;
      for (;;)
      {
        if (!(paramObject instanceof ˊ))
        {
          break label95;
          for (;;)
          {
            try
            {
              Object localObject = (ˊ)paramObject;
              paramObject = this.values;
              localObject = ((ˊ)localObject).values;
              try
              {
                boolean bool = vq.ˊ(paramObject, localObject);
                if (bool) {
                  break label330;
                }
              }
              catch (Exception paramObject)
              {
                throw paramObject;
              }
              throw new NullPointerException();
            }
            catch (Exception paramObject)
            {
              throw paramObject;
            }
            i = ˊ + 25;
            ˋ = i % 128;
            if (i % 2 != 0) {}
          }
          label89:
          i = 33;
          break label120;
          label95:
          i = 0;
          break label151;
          i = 1;
          break label182;
          for (;;)
          {
            return false;
            if (this != paramObject) {
              break;
            }
            i = 0;
            break label182;
            label120:
            switch (i)
            {
            }
          }
          switch (i)
          {
          case 1: 
          default: 
            label151:
            break label250;
            break label303;
            label182:
            switch (i)
            {
            }
            continue;
            label207:
            label209:
            for (;;)
            {
              return true;
            }
          }
        }
      }
      for (;;)
      {
        switch (i)
        {
        case 78: 
        default: 
          break;
          i = 56 / 0;
          return false;
        case 16: 
          label250:
          break label264;
          i = 1;
          break label151;
          label264:
          i = ˊ + 17;
          ˋ = i % 128;
          if (i % 2 != 0) {
            break label89;
          }
          i = 45;
          break label120;
          i = 16;
          continue;
          label303:
          i = ˋ + 11;
          ˊ = i % 128;
          if (i % 2 != 0) {
            break label209;
          }
          break label207;
          label330:
          i = 78;
        }
      }
    }
    
    public int hashCode()
    {
      break label110;
      label3:
      int i = ˊ + 99;
      ˋ = i % 128;
      if (i % 2 != 0)
      {
        break label172;
        i = 98;
      }
      try
      {
        Object localObject;
        i = localObject.hashCode();
        int j = null.length;
      }
      catch (Exception localException)
      {
        throw localException;
      }
      return 0;
      for (;;)
      {
        switch (i)
        {
        case 0: 
        default: 
          break label113;
          switch (i)
          {
          case 98: 
          default: 
            break label3;
          }
          break;
        case 1: 
          label75:
          label110:
          label113:
          return 0;
          label115:
          i = 0;
        }
      }
      label120:
      return i;
      if localIf;
      for (;;)
      {
        i = 46;
        break label75;
        localIf = this.values;
        if (localIf != null) {
          break;
        }
      }
      for (;;)
      {
        i = ˋ + 77;
        ˊ = i % 128;
        if (i % 2 != 0) {
          break label115;
        }
        i = 1;
        break;
        label172:
        i = localIf.hashCode();
        break label120;
      }
    }
    
    public String toString()
    {
      String str;
      for (;;)
      {
        str = ˋ(new int[] { 0, 19, 0, 0 }, new byte[] { 1, 0, 0, 0, 1, 1, 1, 0, 1, 0, 1, 1, 1, 0, 1, 0, 0, 1, 0 }, true).intern() + this.values + ˋ(new int[] { 19, 1, 0, 1 }, new byte[] { 1 }, false).intern();
        break;
      }
      int i = ˊ + 97;
      ˋ = i % 128;
      if (i % 2 == 0) {
        return str;
      }
      return str;
    }
    
    public final if ॱ()
    {
      for (;;)
      {
        return this.values;
        int i = ˊ + 99;
        ˋ = i % 128;
        if (i % 2 != 0)
        {
          i = 1;
          break label52;
          if localIf = this.values;
          i = null.length;
          return localIf;
        }
        else
        {
          i = 0;
        }
        label52:
        switch (i)
        {
        }
      }
    }
    
    public static final class If
    {
      private static byte[] ˊ;
      private static int ˋ = 696150606;
      private static int ˎ;
      private static short[] ˏ;
      private static int ॱ;
      private static int ॱॱ = 0;
      private static int ᐝ = 1;
      private final int consecutiveTransactionsThreshold;
      @nT(ˋ="authorizationAmountThreshold")
      private final BigDecimal lowValueTransactionMaxThreshold;
      @nT(ˋ="paymentJourneyThreshold")
      private final BigDecimal lowValueTransactionThreshold;
      
      static
      {
        ॱ = 16;
        ˊ = new byte[] { -13, -44, -41, -63, -49, -54, -51, -58, -80, -8, -79, -80, -7, -39, -62, -49, -85, -66, -22, -65, -57, -23, -70, -23, -52, -61, -59, -59, -7, -60, -67, -128, 15, -56, -45, -65, -49, -68, -55, -82, -23, -39, -44, -60, -41, -65, -84, -52, -41, -76, 3, 34, 31, 85, 39, 76, 41, 80, 70, 52, 29, 84, 39, 75, 88, 44, 87, 79, 45, 60, 45, 42, 83, 81, 81, -3, 82, 89, -114, 38, -12, 21, 24, 30, 16, 39, 10, 35, 49, -4, 32, 22, 31, 16, 44, 27, 7, 32, 40, 6, 55, 6, 6, 40, 16, 22, 43, 23, 11, 32, 22, 41, 90, 17, 0, 0, 0, 0 };
        ˎ = -1515494925;
      }
      
      private static String ˎ(short paramShort, int paramInt1, byte paramByte, int paramInt2, int paramInt3)
      {
        break label171;
        Object localObject = ˏ;
        int j = paramInt1 - 1;
        int k;
        int i = (char)(((short)(localObject[paramInt1] + paramShort) ^ paramByte) + k);
        paramInt1 = j;
        break label435;
        j = 0;
        break label366;
        break label289;
        label43:
        j = ᐝ + 95;
        ॱॱ = j % 128;
        label73:
        label119:
        StringBuilder localStringBuilder;
        if (j % 2 == 0)
        {
          break label520;
          if (j == 0)
          {
            break label506;
            for (;;)
            {
              j = 30;
              switch (j)
              {
              }
              break label43;
              break label302;
              k = ˋ;
              if (j == 0)
              {
                break;
                label171:
                for (;;)
                {
                  localStringBuilder = new StringBuilder();
                  j = ॱ + paramInt3;
                  paramInt3 = j;
                  if (j == -1) {
                    break;
                  }
                  break label308;
                }
                if (ˊ == null) {
                  break label489;
                }
              }
            }
          }
        }
        label193:
        label289:
        label296:
        label302:
        label308:
        label314:
        label347:
        label366:
        label435:
        label454:
        label489:
        label506:
        label520:
        label556:
        label557:
        for (;;)
        {
          k = 78;
          break label314;
          k = ᐝ + 91;
          ॱॱ = k % 128;
          if (k % 2 == 0)
          {
            break label556;
            for (;;)
            {
              j = ॱॱ + 63;
              ᐝ = j % 128;
              if (j % 2 == 0) {
                break;
              }
              break;
              j = 1;
              break label366;
              j = ᐝ + 119;
              ॱॱ = j % 128;
              if (j % 2 != 0) {
                break label119;
              }
              break label302;
              k = i;
              break label347;
              return localStringBuilder.toString();
              j = 1;
              break label73;
              j = 0;
              break label73;
              for (;;)
              {
                switch (k)
                {
                }
                break label296;
                if (paramInt2 < paramInt3) {
                  break;
                }
                break label296;
                k = 20;
              }
              paramInt1 = paramInt1 + paramInt3 - 2 + k + j;
              i = (char)(ˎ + paramInt2);
              localStringBuilder.append(i);
              paramInt2 = 1;
            }
            try
            {
              localObject = ˊ;
              if (localObject == null) {
                break label454;
              }
              paramInt3 = (byte)(ˊ[(ˋ + paramInt1)] + ॱ);
              break label193;
              localStringBuilder.append(i);
              paramInt2 += 1;
              k = i;
              break label347;
              localObject = ˏ;
              try
              {
                paramInt3 = ˋ;
                paramInt3 = localObject[(paramInt3 + paramInt1)];
                k = ॱ;
                paramInt3 = (short)(paramInt3 + k);
              }
              catch (Exception localException1)
              {
                throw localException1;
              }
              j = 52;
            }
            catch (Exception localException2)
            {
              throw localException2;
            }
          }
          for (;;)
          {
            if (paramInt3 > 0) {
              break label557;
            }
            break;
            break label556;
            for (;;)
            {
              localObject = ˊ;
              j = paramInt1 - 1;
              paramInt1 = localObject[paramInt1];
              i = (char)(((byte)(paramInt1 + paramShort) ^ paramByte) + k);
              paramInt1 = j;
              break;
            }
          }
        }
      }
      
      public boolean equals(Object paramObject)
      {
        break label61;
        break label130;
        int i = 0;
        break label207;
        if (this.consecutiveTransactionsThreshold != paramObject.consecutiveTransactionsThreshold)
        {
          break label365;
          label28:
          i = 1;
          break label150;
          switch (i)
          {
          default: 
            break;
            return false;
            break label103;
            i = 67;
            break;
          case 1: 
            for (;;)
            {
              label33:
              label61:
              label64:
              label70:
              break;
              label73:
              switch (i)
              {
              }
            }
            label103:
            i = ᐝ + 117;
            ॱॱ = i % 128;
            if (i % 2 != 0) {}
            break;
          }
        }
        for (;;)
        {
          label130:
          if (!vq.ˊ(this.lowValueTransactionThreshold, paramObject.lowValueTransactionThreshold))
          {
            break label64;
            for (;;)
            {
              switch (i)
              {
              default: 
                label150:
                break label315;
                label175:
                i = 1;
                break label33;
                paramObject = (If)paramObject;
                if (vq.ˊ(this.lowValueTransactionMaxThreshold, paramObject.lowValueTransactionMaxThreshold)) {
                  break label251;
                }
                break label217;
                i = 1;
                label207:
                if (i != 0) {
                  break label315;
                }
                break label70;
                label217:
                i = 35;
                break label384;
                i = 55;
                break label330;
                i = 94;
                break label283;
                i = 32;
                break label283;
                label241:
                i = 0;
                break label33;
                label246:
                i = 0;
              }
            }
            label251:
            i = 89;
            break label384;
            i = ॱॱ + 5;
            ᐝ = i % 128;
            if (i % 2 == 0) {
              break;
            }
            continue;
            switch (i)
            {
            default: 
              label283:
              break label370;
            }
          }
        }
        for (;;)
        {
          label315:
          return true;
          label330:
          label365:
          label370:
          label384:
          do
          {
            if ((paramObject instanceof If)) {
              break label241;
            }
            break label175;
            for (;;)
            {
              switch (i)
              {
              }
              break;
              i = 31;
              break label73;
              i = 2;
            }
            i = null.length;
            if (this != paramObject) {
              break label28;
            }
            break label246;
            switch (i)
            {
            }
            break label70;
          } while (this != paramObject);
        }
      }
      
      /* Error */
      public int hashCode()
      {
        // Byte code:
        //   0: goto +193 -> 193
        //   3: getstatic 30	o/Fc$ˊ$If:ॱॱ	I
        //   6: bipush 119
        //   8: iadd
        //   9: istore_1
        //   10: iload_1
        //   11: sipush 128
        //   14: irem
        //   15: putstatic 32	o/Fc$ˊ$If:ᐝ	I
        //   18: iload_1
        //   19: iconst_2
        //   20: irem
        //   21: ifne +6 -> 27
        //   24: goto +163 -> 187
        //   27: goto +214 -> 241
        //   30: bipush 36
        //   32: istore_2
        //   33: goto +124 -> 157
        //   36: iload_1
        //   37: bipush 31
        //   39: imul
        //   40: iload_2
        //   41: iadd
        //   42: bipush 31
        //   44: imul
        //   45: aload_0
        //   46: getfield 149	o/Fc$ˊ$If:consecutiveTransactionsThreshold	I
        //   49: iadd
        //   50: ireturn
        //   51: aload 4
        //   53: invokevirtual 162	java/lang/Object:hashCode	()I
        //   56: istore_1
        //   57: goto +133 -> 190
        //   60: astore 4
        //   62: aload 4
        //   64: athrow
        //   65: astore 4
        //   67: aload 4
        //   69: athrow
        //   70: iload_1
        //   71: lookupswitch	default:+25->96, 36:+28->99, 49:+-20->51
        //   96: goto -45 -> 51
        //   99: iconst_0
        //   100: istore_1
        //   101: goto +14 -> 115
        //   104: iconst_0
        //   105: istore_2
        //   106: goto -70 -> 36
        //   109: bipush 36
        //   111: istore_1
        //   112: goto -42 -> 70
        //   115: getstatic 32	o/Fc$ˊ$If:ᐝ	I
        //   118: bipush 29
        //   120: iadd
        //   121: istore_2
        //   122: iload_2
        //   123: sipush 128
        //   126: irem
        //   127: putstatic 30	o/Fc$ˊ$If:ॱॱ	I
        //   130: iload_2
        //   131: iconst_2
        //   132: irem
        //   133: ifeq +6 -> 139
        //   136: goto +99 -> 235
        //   139: goto +87 -> 226
        //   142: aload 4
        //   144: invokevirtual 162	java/lang/Object:hashCode	()I
        //   147: istore_2
        //   148: goto +110 -> 258
        //   151: bipush 49
        //   153: istore_1
        //   154: goto -84 -> 70
        //   157: iload_2
        //   158: lookupswitch	default:+26->184, 36:+-54->104, 99:+41->199
        //   184: goto +15 -> 199
        //   187: goto +54 -> 241
        //   190: goto +95 -> 285
        //   193: goto -190 -> 3
        //   196: goto -160 -> 36
        //   199: getstatic 30	o/Fc$ˊ$If:ॱॱ	I
        //   202: bipush 33
        //   204: iadd
        //   205: istore_2
        //   206: iload_2
        //   207: sipush 128
        //   210: irem
        //   211: putstatic 32	o/Fc$ˊ$If:ᐝ	I
        //   214: iload_2
        //   215: iconst_2
        //   216: irem
        //   217: ifne +6 -> 223
        //   220: goto +18 -> 238
        //   223: goto -81 -> 142
        //   226: goto +59 -> 285
        //   229: bipush 99
        //   231: istore_2
        //   232: goto -75 -> 157
        //   235: goto -9 -> 226
        //   238: goto -96 -> 142
        //   241: aload_0
        //   242: getfield 158	o/Fc$ˊ$If:lowValueTransactionMaxThreshold	Ljava/math/BigDecimal;
        //   245: astore 4
        //   247: aload 4
        //   249: ifnull +6 -> 255
        //   252: goto -101 -> 151
        //   255: goto -146 -> 109
        //   258: getstatic 32	o/Fc$ˊ$If:ᐝ	I
        //   261: bipush 67
        //   263: iadd
        //   264: istore_3
        //   265: iload_3
        //   266: sipush 128
        //   269: irem
        //   270: putstatic 30	o/Fc$ˊ$If:ॱॱ	I
        //   273: iload_3
        //   274: iconst_2
        //   275: irem
        //   276: ifeq +6 -> 282
        //   279: goto +23 -> 302
        //   282: goto -86 -> 196
        //   285: aload_0
        //   286: getfield 151	o/Fc$ˊ$If:lowValueTransactionThreshold	Ljava/math/BigDecimal;
        //   289: astore 4
        //   291: aload 4
        //   293: ifnull +6 -> 299
        //   296: goto -67 -> 229
        //   299: goto -269 -> 30
        //   302: goto -266 -> 36
        // Local variable table:
        //   start	length	slot	name	signature
        //   0	305	0	this	If
        //   9	145	1	i	int
        //   32	200	2	j	int
        //   264	12	3	k	int
        //   51	1	4	localObject	Object
        //   60	3	4	localException1	Exception
        //   65	78	4	localException2	Exception
        //   245	47	4	localBigDecimal	BigDecimal
        // Exception table:
        //   from	to	target	type
        //   142	148	60	java/lang/Exception
        //   241	247	65	java/lang/Exception
        //   285	291	65	java/lang/Exception
      }
      
      public String toString()
      {
        for (;;)
        {
          int i = ᐝ + 113;
          ॱॱ = i % 128;
          if (i % 2 != 0) {
            return str;
          }
          return str;
          String str = ˎ((short)53, -696150606, (byte)-15, 1515495003, 35).intern() + this.lowValueTransactionMaxThreshold + ˎ((short)68, -696150556, (byte)-98, 1515494969, 15).intern() + this.lowValueTransactionThreshold + ˎ((short)-26, -696150526, (byte)3, 1515494969, 19).intern() + this.consecutiveTransactionsThreshold + ˎ((short)-69, -696150492, (byte)77, 1515494966, -15).intern();
        }
      }
      
      public final BigDecimal ˊ()
      {
        do
        {
          break;
          i = ॱॱ + 85;
          ᐝ = i % 128;
        } while (i % 2 == 0);
        BigDecimal localBigDecimal = this.lowValueTransactionThreshold;
        int i = ᐝ + 27;
        ॱॱ = i % 128;
        if (i % 2 != 0) {
          return localBigDecimal;
        }
        return localBigDecimal;
      }
      
      public final BigDecimal ˋ()
      {
        break label21;
        BigDecimal localBigDecimal = this.lowValueTransactionMaxThreshold;
        int i = 46 / 0;
        return localBigDecimal;
        for (;;)
        {
          i = 22;
          break label56;
          label21:
          i = ᐝ + 89;
          ॱॱ = i % 128;
          if (i % 2 != 0) {
            break;
          }
        }
        for (;;)
        {
          return this.lowValueTransactionMaxThreshold;
          i = 36;
          label56:
          switch (i)
          {
          }
        }
      }
      
      public final int ˏ()
      {
        for (;;)
        {
          int j = this.consecutiveTransactionsThreshold;
          break label39;
          break label89;
          label14:
          int i;
          for (;;)
          {
            switch (i)
            {
            default: 
              break;
              i = ॱॱ + 15;
              ᐝ = i % 128;
              if (i % 2 == 0) {}
              break;
            case 1: 
              label39:
              throw new NullPointerException();
              i = 1;
            }
          }
          label89:
          do
          {
            break;
            return j;
            i = 0;
            break label14;
            i = ॱॱ + 15;
            ᐝ = i % 128;
          } while (i % 2 == 0);
        }
      }
    }
    
    public static final class if
    {
      private static char[] ˎ = { 132, 276, 286, 277, 277, 287, 288, 291, 291, 286, 277, 278, 294, 302, 296, 293, 292, 295, 282, 273, 290, 262, 254, 288, 294, 270, 119 };
      private static int ˏ;
      private static int ॱ = 0;
      @nT(ˋ="ALL")
      private final Fc.ˊ.If all;
      
      static
      {
        ˏ = 1;
      }
      
      private static String ˏ(int[] paramArrayOfInt, byte[] paramArrayOfByte, boolean paramBoolean)
      {
        break label508;
        label3:
        break label163;
        break label630;
        label9:
        int i = 27;
        break label387;
        int k;
        Object localObject;
        int n;
        for (;;)
        {
          paramArrayOfByte = new char[k];
          System.arraycopy(localObject, 0, paramArrayOfByte, 0, k);
          System.arraycopy(paramArrayOfByte, 0, localObject, k - n, n);
          System.arraycopy(paramArrayOfByte, n, localObject, 0, k - n);
          break label620;
          label61:
          break;
          do
          {
            break;
            i = ˏ + 67;
            ॱ = i % 128;
            if (i % 2 != 0) {
              break label61;
            }
            break label565;
            i = ˏ + 37;
            ॱ = i % 128;
          } while (i % 2 != 0);
        }
        int j;
        for (;;)
        {
          switch (j)
          {
          default: 
            break label635;
            label151:
            if (i < k) {
              break label644;
            }
            break label562;
            for (;;)
            {
              label163:
              localObject = new char[k];
              j = 0;
              i = 0;
              for (;;)
              {
                break label151;
                break label476;
                label183:
                continue;
                label186:
                label219:
                label226:
                int m;
                switch (j)
                {
                case 18: 
                default: 
                  break label607;
                  j = 79;
                  break;
                  i = paramArrayOfInt[0];
                  k = paramArrayOfInt[1];
                  m = paramArrayOfInt[2];
                  n = paramArrayOfInt[3];
                }
                try
                {
                  localObject = ˎ;
                  arrayOfChar = new char[k];
                  System.arraycopy(localObject, i, arrayOfChar, 0, k);
                  if (paramArrayOfByte != null) {
                    break label9;
                  }
                  break label594;
                  label277:
                  break label540;
                  label280:
                  i = ˏ + 11;
                  ॱ = i % 128;
                  if (i % 2 != 0) {
                    break;
                  }
                  break;
                  label307:
                  localObject[i] = ((char)((arrayOfChar[i] << '\001') + 1 - j));
                  j = ॱ + 31;
                  ˏ = j % 128;
                  if (j % 2 == 0) {
                    break label600;
                  }
                }
                catch (Exception paramArrayOfInt)
                {
                  char[] arrayOfChar;
                  int i1;
                  label387:
                  throw paramArrayOfInt;
                }
                try
                {
                  i1 = ˏ;
                  i1 += 83;
                  ॱ = i1 % 128;
                  if (i1 % 2 != 0) {
                    break label183;
                  }
                }
                catch (Exception paramArrayOfInt)
                {
                  throw paramArrayOfInt;
                }
              }
              localObject = arrayOfChar;
              switch (i)
              {
              default: 
                localObject = arrayOfChar;
                break;
              case 27: 
                i = ॱ;
                i += 15;
                ˏ = i % 128;
                if (i % 2 == 0) {
                  break label3;
                }
              }
            }
            label456:
            j = 5;
          }
        }
        for (;;)
        {
          localObject[i] = ((char)((arrayOfChar[i] << '\001') - j));
          label476:
          j = localObject[i];
          i += 1;
          break label151;
          label489:
          if (i < k) {
            break label456;
          }
          break label219;
          j = 18;
          break label186;
          label508:
          break label226;
          label540:
          label562:
          label565:
          label594:
          label600:
          label607:
          label610:
          label620:
          label630:
          label633:
          for (;;)
          {
            localObject[i] = ((char)(localObject[i] - paramArrayOfInt[2]));
            i += 1;
            for (;;)
            {
              if (i < k) {
                break label633;
              }
              for (;;)
              {
                if (m > 0) {
                  break label280;
                }
                break label610;
                while (n <= 0) {
                  break label620;
                }
                paramArrayOfByte = new char[k];
                i = 0;
                break label489;
                paramArrayOfByte[i] = localObject[(k - i - 1)];
                i += 1;
                break label489;
                i = 8;
                break label387;
                j = 95;
                break label186;
                break label476;
                return new String((char[])localObject);
                if (paramBoolean) {
                  break;
                }
              }
              i = 0;
            }
          }
          label635:
          localObject = paramArrayOfByte;
          break label277;
          label644:
          if (paramArrayOfByte[i] == 1) {
            break label307;
          }
        }
      }
      
      /* Error */
      public boolean equals(Object paramObject)
      {
        // Byte code:
        //   0: goto +251 -> 251
        //   3: bipush 32
        //   5: istore_2
        //   6: goto +112 -> 118
        //   9: iconst_1
        //   10: ireturn
        //   11: astore_1
        //   12: aload_1
        //   13: athrow
        //   14: getstatic 26	o/Fc$ˊ$if:ˏ	I
        //   17: bipush 75
        //   19: iadd
        //   20: istore_2
        //   21: iload_2
        //   22: sipush 128
        //   25: irem
        //   26: putstatic 24	o/Fc$ˊ$if:ॱ	I
        //   29: iload_2
        //   30: iconst_2
        //   31: irem
        //   32: ifeq +6 -> 38
        //   35: goto +55 -> 90
        //   38: goto -29 -> 9
        //   41: iconst_0
        //   42: ireturn
        //   43: getstatic 24	o/Fc$ˊ$if:ॱ	I
        //   46: istore_2
        //   47: iload_2
        //   48: bipush 37
        //   50: iadd
        //   51: istore_2
        //   52: iload_2
        //   53: sipush 128
        //   56: irem
        //   57: putstatic 26	o/Fc$ˊ$if:ˏ	I
        //   60: iload_2
        //   61: iconst_2
        //   62: irem
        //   63: ifne +6 -> 69
        //   66: goto +118 -> 184
        //   69: goto +146 -> 215
        //   72: iconst_5
        //   73: istore_2
        //   74: goto +44 -> 118
        //   77: aload_1
        //   78: instanceof 2
        //   81: ifeq +6 -> 87
        //   84: goto +73 -> 157
        //   87: goto -46 -> 41
        //   90: goto -81 -> 9
        //   93: aload_1
        //   94: checkcast 2	o/Fc$ˊ$if
        //   97: astore_1
        //   98: aload_0
        //   99: getfield 69	o/Fc$ˊ$if:all	Lo/Fc$ˊ$If;
        //   102: aload_1
        //   103: getfield 69	o/Fc$ˊ$if:all	Lo/Fc$ˊ$If;
        //   106: invokestatic 74	o/vq:ˊ	(Ljava/lang/Object;Ljava/lang/Object;)Z
        //   109: pop
        //   110: new 76	java/lang/NullPointerException
        //   113: dup
        //   114: invokespecial 78	java/lang/NullPointerException:<init>	()V
        //   117: athrow
        //   118: iload_2
        //   119: lookupswitch	default:+25->144, 5:+135->254, 32:+-42->77
        //   144: goto -67 -> 77
        //   147: iconst_1
        //   148: istore_2
        //   149: goto +38 -> 187
        //   152: iconst_0
        //   153: istore_2
        //   154: goto +33 -> 187
        //   157: getstatic 24	o/Fc$ˊ$if:ॱ	I
        //   160: bipush 33
        //   162: iadd
        //   163: istore_2
        //   164: iload_2
        //   165: sipush 128
        //   168: irem
        //   169: putstatic 26	o/Fc$ˊ$if:ˏ	I
        //   172: iload_2
        //   173: iconst_2
        //   174: irem
        //   175: ifne +6 -> 181
        //   178: goto -85 -> 93
        //   181: goto +45 -> 226
        //   184: goto +31 -> 215
        //   187: iload_2
        //   188: tableswitch	default:+24->212, 0:+66->254, 1:+-147->41
        //   212: goto -171 -> 41
        //   215: aload_0
        //   216: aload_1
        //   217: if_acmpeq +6 -> 223
        //   220: goto -217 -> 3
        //   223: goto -151 -> 72
        //   226: aload_1
        //   227: checkcast 2	o/Fc$ˊ$if
        //   230: astore_1
        //   231: aload_0
        //   232: getfield 69	o/Fc$ˊ$if:all	Lo/Fc$ˊ$If;
        //   235: aload_1
        //   236: getfield 69	o/Fc$ˊ$if:all	Lo/Fc$ˊ$If;
        //   239: invokestatic 74	o/vq:ˊ	(Ljava/lang/Object;Ljava/lang/Object;)Z
        //   242: ifeq +6 -> 248
        //   245: goto -93 -> 152
        //   248: goto -101 -> 147
        //   251: goto -208 -> 43
        //   254: goto -240 -> 14
        //   257: astore_1
        //   258: aload_1
        //   259: athrow
        // Local variable table:
        //   start	length	slot	name	signature
        //   0	260	0	this	if
        //   0	260	1	paramObject	Object
        //   5	183	2	i	int
        // Exception table:
        //   from	to	target	type
        //   43	47	11	java/lang/Exception
        //   52	60	257	java/lang/Exception
      }
      
      public int hashCode()
      {
        break label140;
        for (;;)
        {
          i = 24;
          break label80;
          try
          {
            label9:
            Fc.ˊ.If localIf = this.all;
            if (localIf != null) {
              break label65;
            }
          }
          catch (Exception localException)
          {
            throw localException;
          }
        }
        int i = 81;
        break label180;
        label65:
        label71:
        label77:
        label80:
        label140:
        for (;;)
        {
          i = ॱ + 47;
          ˏ = i % 128;
          if (i % 2 != 0)
          {
            break;
            i = 0;
            break label77;
            i = 89;
            break label80;
            i = 92;
            break label180;
          }
          switch (i)
          {
          case 24: 
          default: 
            break label151;
            int j = ॱ + 37;
            ˏ = j % 128;
            if (j % 2 == 0) {
              break label178;
            }
            return i;
            break label9;
          }
        }
        for (;;)
        {
          i = localException.hashCode();
          break label77;
          label151:
          i = ˏ + 41;
          ॱ = i % 128;
          if (i % 2 != 0) {
            break;
          }
          break label71;
          label178:
          return i;
          label180:
          switch (i)
          {
          }
        }
        i = localException.hashCode();
        throw new NullPointerException();
      }
      
      public String toString()
      {
        String str;
        for (;;)
        {
          str = ˏ(new int[] { 0, 26, 186, 0 }, new byte[] { 0, 0, 1, 0, 0, 1, 1, 0, 0, 1, 1, 0, 1, 0, 1, 1, 1, 0, 0, 0, 1, 0, 1, 1, 0, 1 }, false).intern() + this.all + ˏ(new int[] { 26, 1, 198, 0 }, new byte[] { 1 }, false).intern();
          break;
        }
        int i = ॱ + 61;
        ˏ = i % 128;
        if (i % 2 == 0) {
          return str;
        }
        return str;
      }
      
      public final Fc.ˊ.If ˊ()
      {
        int i;
        for (;;)
        {
          try
          {
            i = ॱ + 51;
            try
            {
              ˏ = i % 128;
              if (i % 2 == 0) {
                break;
              }
            }
            catch (Exception localException1)
            {
              label33:
              Fc.ˊ.If localIf;
              throw localException1;
            }
          }
          catch (Exception localException2)
          {
            label44:
            throw localException2;
          }
          localIf = this.all;
        }
        label47:
        throw new NullPointerException();
        for (;;)
        {
          switch (i)
          {
          case 1: 
          default: 
            break label47;
            i = 0;
            continue;
            i = ॱ + 17;
            ˏ = i % 128;
            if (i % 2 == 0) {
              break label44;
            }
            break label33;
            i = 1;
          }
        }
        return localException2;
      }
    }
  }
  
  public static final class ˋ
  {
    private static int ˊ = 0;
    private static char[] ˋ = { 5306, 32461, -16340, 11167, -16917, 1877, 27277, -795, 18037, -22087, 13062, -31396, -5977, 29194, -15235, 12227, -20098, 7008, 28355, -4042, 23449, -21023, 14123, -25977, -4893, 30316, -9801, 9210, -19091, 6315, 25103, -2946, 24514, -24290, 2939, -24955, -8594 };
    private static long ˏ;
    private static int ॱ = 1;
    private final ArrayList<ˋ> languagePerCountry;
    
    static
    {
      ˏ = -2648296107695576486L;
    }
    
    private static String ˋ(int paramInt1, char paramChar, int paramInt2)
    {
      break label300;
      int i;
      label14:
      int j;
      if (i >= paramInt2)
      {
        for (;;)
        {
          switch (j)
          {
          default: 
            break label107;
            j = ˊ + 73;
            ॱ = j % 128;
            if (j % 2 == 0) {
              break label238;
            }
            break label260;
            j = 0;
          }
        }
        switch (j)
        {
        default: 
          label79:
          break;
          label107:
          j = ˊ + 111;
          ॱ = j % 128;
          if (j % 2 == 0) {}
          break;
        }
      }
      label212:
      label238:
      label260:
      label300:
      for (;;)
      {
        i = ˊ + 107;
        ॱ = i % 128;
        if (i % 2 != 0) {
          break label212;
        }
        char[] arrayOfChar2;
        for (;;)
        {
          try
          {
            char[] arrayOfChar1 = ˋ;
            long l1 = arrayOfChar1[(paramInt1 >>> i)];
            long l2 = i;
            try
            {
              long l3 = ˏ;
              arrayOfChar2[i] = ((char)(int)(l1 + (l2 - l3) - paramChar));
              i += 116;
            }
            catch (Exception localException1)
            {
              throw localException1;
            }
            arrayOfChar2 = new char[paramInt2];
            i = 0;
          }
          catch (Exception localException2)
          {
            throw localException2;
          }
          j = 0;
          break label79;
          return new String(arrayOfChar2);
          break label260;
        }
        j = 1;
        break label79;
        break;
        arrayOfChar2[i] = ((char)(int)(ˋ[(paramInt1 + i)] ^ i * ˏ ^ paramChar));
        i += 1;
        break;
        j = 1;
        break label14;
      }
    }
    
    /* Error */
    public boolean equals(Object paramObject)
    {
      // Byte code:
      //   0: goto +28 -> 28
      //   3: astore_1
      //   4: aload_1
      //   5: athrow
      //   6: bipush 32
      //   8: istore_2
      //   9: goto +27 -> 36
      //   12: aload_0
      //   13: aload_1
      //   14: if_acmpeq +6 -> 20
      //   17: goto +102 -> 119
      //   20: goto +65 -> 85
      //   23: goto +68 -> 91
      //   26: iconst_0
      //   27: ireturn
      //   28: goto -16 -> 12
      //   31: astore_1
      //   32: aload_1
      //   33: athrow
      //   34: iconst_1
      //   35: ireturn
      //   36: iload_2
      //   37: lookupswitch	default:+27->64, 32:+-3->34, 65:+98->135
      //   64: goto +71 -> 135
      //   67: aload_1
      //   68: instanceof 2
      //   71: istore_3
      //   72: aconst_null
      //   73: arraylength
      //   74: istore_2
      //   75: iload_3
      //   76: ifeq +6 -> 82
      //   79: goto +86 -> 165
      //   82: goto +53 -> 135
      //   85: bipush 94
      //   87: istore_2
      //   88: goto +106 -> 194
      //   91: aload_1
      //   92: checkcast 2	o/Fc$ˋ
      //   95: astore_1
      //   96: aload_0
      //   97: getfield 81	o/Fc$ˋ:languagePerCountry	Ljava/util/ArrayList;
      //   100: aload_1
      //   101: getfield 81	o/Fc$ˋ:languagePerCountry	Ljava/util/ArrayList;
      //   104: invokestatic 86	o/vq:ˊ	(Ljava/lang/Object;Ljava/lang/Object;)Z
      //   107: ifeq +6 -> 113
      //   110: goto -104 -> 6
      //   113: bipush 65
      //   115: istore_2
      //   116: goto -80 -> 36
      //   119: bipush 46
      //   121: istore_2
      //   122: goto +72 -> 194
      //   125: aload_1
      //   126: instanceof 2
      //   129: ifeq +6 -> 135
      //   132: goto +33 -> 165
      //   135: goto -109 -> 26
      //   138: getstatic 24	o/Fc$ˋ:ॱ	I
      //   141: bipush 119
      //   143: iadd
      //   144: istore_2
      //   145: iload_2
      //   146: sipush 128
      //   149: irem
      //   150: putstatic 22	o/Fc$ˋ:ˊ	I
      //   153: iload_2
      //   154: iconst_2
      //   155: irem
      //   156: ifeq +6 -> 162
      //   159: goto -92 -> 67
      //   162: goto -37 -> 125
      //   165: getstatic 24	o/Fc$ˋ:ॱ	I
      //   168: istore_2
      //   169: iload_2
      //   170: bipush 99
      //   172: iadd
      //   173: istore_2
      //   174: iload_2
      //   175: sipush 128
      //   178: irem
      //   179: putstatic 22	o/Fc$ˋ:ˊ	I
      //   182: iload_2
      //   183: iconst_2
      //   184: irem
      //   185: ifeq +6 -> 191
      //   188: goto -165 -> 23
      //   191: goto -100 -> 91
      //   194: iload_2
      //   195: lookupswitch	default:+25->220, 46:+-57->138, 94:+-161->34
      //   220: goto -82 -> 138
      // Local variable table:
      //   start	length	slot	name	signature
      //   0	223	0	this	ˋ
      //   0	223	1	paramObject	Object
      //   8	187	2	i	int
      //   71	5	3	bool	boolean
      // Exception table:
      //   from	to	target	type
      //   145	153	3	java/lang/Exception
      //   165	169	3	java/lang/Exception
      //   174	182	3	java/lang/Exception
      //   138	145	31	java/lang/Exception
      //   145	153	31	java/lang/Exception
    }
    
    /* Error */
    public int hashCode()
    {
      // Byte code:
      //   0: goto +167 -> 167
      //   3: iload_1
      //   4: lookupswitch	default:+28->32, 27:+150->154, 94:+60->64
      //   32: goto +32 -> 64
      //   35: astore_3
      //   36: aload_3
      //   37: athrow
      //   38: getstatic 24	o/Fc$ˋ:ॱ	I
      //   41: iconst_5
      //   42: iadd
      //   43: istore_1
      //   44: iload_1
      //   45: sipush 128
      //   48: irem
      //   49: putstatic 22	o/Fc$ˋ:ˊ	I
      //   52: iload_1
      //   53: iconst_2
      //   54: irem
      //   55: ifeq +6 -> 61
      //   58: goto +88 -> 146
      //   61: goto +46 -> 107
      //   64: aload_3
      //   65: invokevirtual 90	java/lang/Object:hashCode	()I
      //   68: istore_1
      //   69: aconst_null
      //   70: arraylength
      //   71: istore_2
      //   72: goto +33 -> 105
      //   75: getstatic 24	o/Fc$ˋ:ॱ	I
      //   78: bipush 93
      //   80: iadd
      //   81: istore_1
      //   82: iload_1
      //   83: sipush 128
      //   86: irem
      //   87: putstatic 22	o/Fc$ˋ:ˊ	I
      //   90: iload_1
      //   91: iconst_2
      //   92: irem
      //   93: ifeq +6 -> 99
      //   96: goto +80 -> 176
      //   99: goto +71 -> 170
      //   102: astore_3
      //   103: aload_3
      //   104: athrow
      //   105: iload_1
      //   106: ireturn
      //   107: bipush 27
      //   109: istore_1
      //   110: goto -107 -> 3
      //   113: iload_1
      //   114: lookupswitch	default:+26->140, 25:+47->161, 84:+38->152
      //   140: goto +21 -> 161
      //   143: goto -68 -> 75
      //   146: bipush 94
      //   148: istore_1
      //   149: goto -146 -> 3
      //   152: iconst_0
      //   153: ireturn
      //   154: aload_3
      //   155: invokevirtual 90	java/lang/Object:hashCode	()I
      //   158: istore_1
      //   159: iload_1
      //   160: ireturn
      //   161: iconst_3
      //   162: iconst_3
      //   163: idiv
      //   164: istore_1
      //   165: iconst_0
      //   166: ireturn
      //   167: goto +15 -> 182
      //   170: bipush 84
      //   172: istore_1
      //   173: goto -60 -> 113
      //   176: bipush 25
      //   178: istore_1
      //   179: goto -66 -> 113
      //   182: aload_0
      //   183: getfield 81	o/Fc$ˋ:languagePerCountry	Ljava/util/ArrayList;
      //   186: astore_3
      //   187: aload_3
      //   188: ifnull +6 -> 194
      //   191: goto -153 -> 38
      //   194: goto -51 -> 143
      // Local variable table:
      //   start	length	slot	name	signature
      //   0	197	0	this	ˋ
      //   3	176	1	i	int
      //   71	1	2	j	int
      //   35	30	3	localException1	Exception
      //   102	53	3	localException2	Exception
      //   186	2	3	localArrayList	ArrayList
      // Exception table:
      //   from	to	target	type
      //   38	44	35	java/lang/Exception
      //   44	52	35	java/lang/Exception
      //   154	159	102	java/lang/Exception
    }
    
    /* Error */
    public String toString()
    {
      // Byte code:
      //   0: goto +109 -> 109
      //   3: astore_2
      //   4: aload_2
      //   5: athrow
      //   6: bipush 13
      //   8: istore_1
      //   9: goto +106 -> 115
      //   12: new 94	java/lang/StringBuilder
      //   15: dup
      //   16: invokespecial 96	java/lang/StringBuilder:<init>	()V
      //   19: astore_2
      //   20: iconst_0
      //   21: sipush 5366
      //   24: bipush 36
      //   26: invokestatic 98	o/Fc$ˋ:ˋ	(ICI)Ljava/lang/String;
      //   29: astore_3
      //   30: aload_3
      //   31: invokevirtual 101	java/lang/String:intern	()Ljava/lang/String;
      //   34: astore_3
      //   35: aload_2
      //   36: aload_3
      //   37: invokevirtual 105	java/lang/StringBuilder:append	(Ljava/lang/String;)Ljava/lang/StringBuilder;
      //   40: astore_2
      //   41: aload_0
      //   42: getfield 81	o/Fc$ˋ:languagePerCountry	Ljava/util/ArrayList;
      //   45: astore_3
      //   46: aload_2
      //   47: aload_3
      //   48: invokevirtual 108	java/lang/StringBuilder:append	(Ljava/lang/Object;)Ljava/lang/StringBuilder;
      //   51: bipush 36
      //   53: ldc 109
      //   55: iconst_1
      //   56: invokestatic 98	o/Fc$ˋ:ˋ	(ICI)Ljava/lang/String;
      //   59: invokevirtual 101	java/lang/String:intern	()Ljava/lang/String;
      //   62: invokevirtual 105	java/lang/StringBuilder:append	(Ljava/lang/String;)Ljava/lang/StringBuilder;
      //   65: invokevirtual 111	java/lang/StringBuilder:toString	()Ljava/lang/String;
      //   68: astore_2
      //   69: getstatic 24	o/Fc$ˋ:ॱ	I
      //   72: bipush 37
      //   74: iadd
      //   75: istore_1
      //   76: iload_1
      //   77: sipush 128
      //   80: irem
      //   81: putstatic 22	o/Fc$ˋ:ˊ	I
      //   84: iload_1
      //   85: iconst_2
      //   86: irem
      //   87: ifeq +6 -> 93
      //   90: goto -84 -> 6
      //   93: bipush 26
      //   95: istore_1
      //   96: goto +19 -> 115
      //   99: new 113	java/lang/NullPointerException
      //   102: dup
      //   103: invokespecial 114	java/lang/NullPointerException:<init>	()V
      //   106: athrow
      //   107: aload_2
      //   108: areturn
      //   109: goto -97 -> 12
      //   112: astore_2
      //   113: aload_2
      //   114: athrow
      //   115: iload_1
      //   116: lookupswitch	default:+28->144, 13:+-17->99, 26:+-9->107
      //   144: goto -45 -> 99
      // Local variable table:
      //   start	length	slot	name	signature
      //   0	147	0	this	ˋ
      //   8	108	1	i	int
      //   3	2	2	localException1	Exception
      //   19	89	2	localObject1	Object
      //   112	2	2	localException2	Exception
      //   29	19	3	localObject2	Object
      // Exception table:
      //   from	to	target	type
      //   20	30	3	java/lang/Exception
      //   30	35	112	java/lang/Exception
      //   35	41	112	java/lang/Exception
      //   41	46	112	java/lang/Exception
      //   46	69	112	java/lang/Exception
    }
    
    public final ArrayList<ˋ> ˏ()
    {
      break label76;
      ArrayList localArrayList = this.languagePerCountry;
      int i = null.length;
      return localArrayList;
      i = 1;
      break label20;
      label18:
      i = 0;
      label20:
      switch (i)
      {
      }
      return this.languagePerCountry;
      label76:
      for (;;)
      {
        i = ॱ + 27;
        ˊ = i % 128;
        if (i % 2 != 0) {
          break;
        }
        break label18;
      }
    }
    
    public static final class ˋ
    {
      private static int ʼ;
      private static char ˊ;
      private static char ˋ;
      private static char ˎ = 'ᚱ';
      private static int ˏ = 0;
      private static char ॱ;
      private final String countryCode;
      private final String languageTag;
      
      static
      {
        ʼ = 1;
        ˋ = 62680;
        ˊ = '䵴';
        ॱ = 'ڣ';
      }
      
      /* Error */
      private static String ˋ(char[] paramArrayOfChar)
      {
        // Byte code:
        //   0: goto +127 -> 127
        //   3: iload 5
        //   5: tableswitch	default:+23->28, 0:+77->82, 1:+185->190
        //   28: goto +54 -> 82
        //   31: astore_0
        //   32: aload_0
        //   33: athrow
        //   34: iconst_1
        //   35: istore 5
        //   37: goto -34 -> 3
        //   40: iconst_1
        //   41: istore 6
        //   43: goto +56 -> 99
        //   46: goto +174 -> 220
        //   49: astore_0
        //   50: aload_0
        //   51: athrow
        //   52: getstatic 25	o/Fc$ˋ$ˋ:ʼ	I
        //   55: bipush 45
        //   57: iadd
        //   58: istore 5
        //   60: iload 5
        //   62: sipush 128
        //   65: irem
        //   66: putstatic 23	o/Fc$ˋ$ˋ:ˏ	I
        //   69: iload 5
        //   71: iconst_2
        //   72: irem
        //   73: ifeq +6 -> 79
        //   76: goto +54 -> 130
        //   79: goto -45 -> 34
        //   82: aload_0
        //   83: arraylength
        //   84: newarray char
        //   86: astore 7
        //   88: iconst_1
        //   89: istore 5
        //   91: iconst_4
        //   92: newarray char
        //   94: astore 8
        //   96: goto +61 -> 157
        //   99: iload 6
        //   101: tableswitch	default:+23->124, 0:+35->136, 1:+59->160
        //   124: goto +12 -> 136
        //   127: goto -75 -> 52
        //   130: iconst_0
        //   131: istore 5
        //   133: goto -130 -> 3
        //   136: new 40	java/lang/String
        //   139: dup
        //   140: aload 7
        //   142: iconst_1
        //   143: aload 7
        //   145: iconst_0
        //   146: caload
        //   147: invokespecial 44	java/lang/String:<init>	([CII)V
        //   150: areturn
        //   151: iconst_0
        //   152: istore 6
        //   154: goto -55 -> 99
        //   157: goto +50 -> 207
        //   160: getstatic 23	o/Fc$ˋ$ˋ:ˏ	I
        //   163: bipush 43
        //   165: iadd
        //   166: istore 6
        //   168: iload 6
        //   170: sipush 128
        //   173: irem
        //   174: putstatic 25	o/Fc$ˋ$ˋ:ʼ	I
        //   177: iload 6
        //   179: iconst_2
        //   180: irem
        //   181: ifne +6 -> 187
        //   184: goto -138 -> 46
        //   187: goto +33 -> 220
        //   190: aload_0
        //   191: arraylength
        //   192: newarray char
        //   194: astore 7
        //   196: iconst_0
        //   197: istore 5
        //   199: iconst_2
        //   200: newarray char
        //   202: astore 8
        //   204: goto -47 -> 157
        //   207: iload 5
        //   209: aload_0
        //   210: arraylength
        //   211: if_icmpge +6 -> 217
        //   214: goto -174 -> 40
        //   217: goto -66 -> 151
        //   220: aload 8
        //   222: iconst_0
        //   223: aload_0
        //   224: iload 5
        //   226: caload
        //   227: castore
        //   228: aload 8
        //   230: iconst_1
        //   231: aload_0
        //   232: iload 5
        //   234: iconst_1
        //   235: iadd
        //   236: caload
        //   237: castore
        //   238: getstatic 34	o/Fc$ˋ$ˋ:ˎ	C
        //   241: istore_1
        //   242: getstatic 30	o/Fc$ˋ$ˋ:ˊ	C
        //   245: istore_2
        //   246: getstatic 32	o/Fc$ˋ$ˋ:ॱ	C
        //   249: istore_3
        //   250: getstatic 28	o/Fc$ˋ$ˋ:ˋ	C
        //   253: istore 4
        //   255: aload 8
        //   257: iload_1
        //   258: iload_2
        //   259: iload_3
        //   260: iload 4
        //   262: invokestatic 49	o/oP:ˏ	([CCCCC)V
        //   265: aload 7
        //   267: iload 5
        //   269: aload 8
        //   271: iconst_0
        //   272: caload
        //   273: castore
        //   274: aload 7
        //   276: iload 5
        //   278: iconst_1
        //   279: iadd
        //   280: aload 8
        //   282: iconst_1
        //   283: caload
        //   284: castore
        //   285: iload 5
        //   287: iconst_2
        //   288: iadd
        //   289: istore 5
        //   291: goto -84 -> 207
        // Local variable table:
        //   start	length	slot	name	signature
        //   0	294	0	paramArrayOfChar	char[]
        //   241	17	1	c1	char
        //   245	14	2	c2	char
        //   249	11	3	c3	char
        //   253	8	4	c4	char
        //   3	287	5	i	int
        //   41	140	6	j	int
        //   86	189	7	arrayOfChar1	char[]
        //   94	187	8	arrayOfChar2	char[]
        // Exception table:
        //   from	to	target	type
        //   246	250	31	java/lang/Exception
        //   238	242	49	java/lang/Exception
        //   242	246	49	java/lang/Exception
        //   246	250	49	java/lang/Exception
        //   250	255	49	java/lang/Exception
        //   255	265	49	java/lang/Exception
      }
      
      public boolean equals(Object paramObject)
      {
        break label54;
        break label116;
        Object localObject;
        label27:
        label54:
        boolean bool;
        int i;
        while (!vq.ˊ(this.languageTag, ((ˋ)localObject).languageTag))
        {
          break label345;
          localObject = (ˋ)paramObject;
          if (vq.ˊ(this.countryCode, ((ˋ)localObject).countryCode)) {
            break label334;
          }
          break label348;
          break label267;
          do
          {
            try
            {
              paramObject = this.languageTag;
              localObject = ((ˋ)localObject).languageTag;
              bool = vq.ˊ(paramObject, localObject);
              i = null.length;
              if (bool) {
                break;
              }
            }
            catch (Exception paramObject)
            {
              throw paramObject;
            }
            i = ʼ + 113;
            ˏ = i % 128;
          } while (i % 2 != 0);
        }
        for (;;)
        {
          label116:
          return false;
          do
          {
            i = 72;
            break;
            i = ˏ + 99;
            ʼ = i % 128;
            if (i % 2 == 0) {
              break label388;
            }
          } while ((paramObject instanceof ˋ));
          break label219;
          i = ˏ + 17;
          ʼ = i % 128;
          if (i % 2 == 0) {
            break;
          }
        }
        for (;;)
        {
          i = 1;
          for (;;)
          {
            switch (i)
            {
            case 1: 
            default: 
              label193:
              break;
              label219:
              i = 66;
              break;
            }
            return true;
            for (;;)
            {
              if (this == paramObject) {
                switch (i)
                {
                case 0: 
                default: 
                  break label27;
                  label267:
                  i = ʼ + 33;
                  ˏ = i % 128;
                  if (i % 2 == 0)
                  {
                    continue;
                    i = 0;
                    break label193;
                  }
                  switch (i)
                  {
                  case 72: 
                  default: 
                    break label27;
                    continue;
                    label334:
                    i = 38;
                    break label351;
                  }
                  break;
                }
              }
            }
            i = 1;
          }
          for (;;)
          {
            label345:
            break;
            label348:
            i = 10;
            label351:
            switch (i)
            {
            }
          }
          label388:
          do
          {
            i = 0;
            break;
            bool = paramObject instanceof ˋ;
            i = 13 / 0;
          } while (bool);
        }
      }
      
      public int hashCode()
      {
        break label120;
        int j = ʼ + 81;
        ˏ = j % 128;
        if (j % 2 == 0) {
          break label45;
        }
        String str;
        label45:
        label56:
        label62:
        int i;
        label69:
        label98:
        label104:
        label109:
        label120:
        for (;;)
        {
          str = this.countryCode;
          if (str != null) {
            break label202;
          }
          break label167;
          j = str.hashCode();
          break label199;
          break label109;
          j = 49;
          break label138;
          for (;;)
          {
            return i * 31 + j;
            switch (i)
            {
            default: 
              break label207;
              break label45;
              j = 85;
              break label138;
              j = 0;
            }
          }
          break;
          i = str.hashCode();
          break label172;
        }
        for (;;)
        {
          str = this.languageTag;
          if (str != null) {
            break label56;
          }
          break label98;
          label138:
          switch (j)
          {
          }
          break label104;
          label167:
          i = 0;
          break label69;
          label172:
          j = ˏ + 67;
          ʼ = j % 128;
          if (j % 2 == 0) {
            break;
          }
          break;
          label199:
          break label62;
          label202:
          i = 1;
          break label69;
          label207:
          i = 0;
        }
      }
      
      /* Error */
      public String toString()
      {
        // Byte code:
        //   0: goto +349 -> 349
        //   3: new 68	java/lang/StringBuilder
        //   6: dup
        //   7: invokespecial 70	java/lang/StringBuilder:<init>	()V
        //   10: bipush 26
        //   12: newarray char
        //   14: dup
        //   15: iconst_0
        //   16: ldc 71
        //   18: castore
        //   19: dup
        //   20: iconst_1
        //   21: ldc 72
        //   23: castore
        //   24: dup
        //   25: iconst_2
        //   26: ldc 73
        //   28: castore
        //   29: dup
        //   30: iconst_3
        //   31: ldc 74
        //   33: castore
        //   34: dup
        //   35: iconst_4
        //   36: ldc 75
        //   38: castore
        //   39: dup
        //   40: iconst_5
        //   41: ldc 76
        //   43: castore
        //   44: dup
        //   45: bipush 6
        //   47: ldc 77
        //   49: castore
        //   50: dup
        //   51: bipush 7
        //   53: ldc 78
        //   55: castore
        //   56: dup
        //   57: bipush 8
        //   59: ldc 79
        //   61: castore
        //   62: dup
        //   63: bipush 9
        //   65: ldc 80
        //   67: castore
        //   68: dup
        //   69: bipush 10
        //   71: ldc 81
        //   73: castore
        //   74: dup
        //   75: bipush 11
        //   77: ldc 82
        //   79: castore
        //   80: dup
        //   81: bipush 12
        //   83: ldc 83
        //   85: castore
        //   86: dup
        //   87: bipush 13
        //   89: ldc 84
        //   91: castore
        //   92: dup
        //   93: bipush 14
        //   95: ldc 85
        //   97: castore
        //   98: dup
        //   99: bipush 15
        //   101: ldc 86
        //   103: castore
        //   104: dup
        //   105: bipush 16
        //   107: ldc 87
        //   109: castore
        //   110: dup
        //   111: bipush 17
        //   113: ldc 88
        //   115: castore
        //   116: dup
        //   117: bipush 18
        //   119: ldc 89
        //   121: castore
        //   122: dup
        //   123: bipush 19
        //   125: ldc 90
        //   127: castore
        //   128: dup
        //   129: bipush 20
        //   131: ldc 91
        //   133: castore
        //   134: dup
        //   135: bipush 21
        //   137: ldc 92
        //   139: castore
        //   140: dup
        //   141: bipush 22
        //   143: ldc 93
        //   145: castore
        //   146: dup
        //   147: bipush 23
        //   149: ldc 94
        //   151: castore
        //   152: dup
        //   153: bipush 24
        //   155: ldc 95
        //   157: castore
        //   158: dup
        //   159: bipush 25
        //   161: ldc 96
        //   163: castore
        //   164: invokestatic 98	o/Fc$ˋ$ˋ:ˋ	([C)Ljava/lang/String;
        //   167: invokevirtual 101	java/lang/String:intern	()Ljava/lang/String;
        //   170: invokevirtual 105	java/lang/StringBuilder:append	(Ljava/lang/String;)Ljava/lang/StringBuilder;
        //   173: aload_0
        //   174: getfield 60	o/Fc$ˋ$ˋ:countryCode	Ljava/lang/String;
        //   177: invokevirtual 105	java/lang/StringBuilder:append	(Ljava/lang/String;)Ljava/lang/StringBuilder;
        //   180: bipush 16
        //   182: newarray char
        //   184: dup
        //   185: iconst_0
        //   186: ldc 106
        //   188: castore
        //   189: dup
        //   190: iconst_1
        //   191: ldc 107
        //   193: castore
        //   194: dup
        //   195: iconst_2
        //   196: ldc 108
        //   198: castore
        //   199: dup
        //   200: iconst_3
        //   201: ldc 109
        //   203: castore
        //   204: dup
        //   205: iconst_4
        //   206: ldc 73
        //   208: castore
        //   209: dup
        //   210: iconst_5
        //   211: ldc 74
        //   213: castore
        //   214: dup
        //   215: bipush 6
        //   217: ldc 75
        //   219: castore
        //   220: dup
        //   221: bipush 7
        //   223: ldc 76
        //   225: castore
        //   226: dup
        //   227: bipush 8
        //   229: ldc 77
        //   231: castore
        //   232: dup
        //   233: bipush 9
        //   235: ldc 78
        //   237: castore
        //   238: dup
        //   239: bipush 10
        //   241: ldc 110
        //   243: castore
        //   244: dup
        //   245: bipush 11
        //   247: ldc 111
        //   249: castore
        //   250: dup
        //   251: bipush 12
        //   253: ldc 77
        //   255: castore
        //   256: dup
        //   257: bipush 13
        //   259: ldc 78
        //   261: castore
        //   262: dup
        //   263: bipush 14
        //   265: ldc 112
        //   267: castore
        //   268: dup
        //   269: bipush 15
        //   271: ldc 113
        //   273: castore
        //   274: invokestatic 98	o/Fc$ˋ$ˋ:ˋ	([C)Ljava/lang/String;
        //   277: invokevirtual 101	java/lang/String:intern	()Ljava/lang/String;
        //   280: invokevirtual 105	java/lang/StringBuilder:append	(Ljava/lang/String;)Ljava/lang/StringBuilder;
        //   283: aload_0
        //   284: getfield 53	o/Fc$ˋ$ˋ:languageTag	Ljava/lang/String;
        //   287: invokevirtual 105	java/lang/StringBuilder:append	(Ljava/lang/String;)Ljava/lang/StringBuilder;
        //   290: iconst_2
        //   291: newarray char
        //   293: dup
        //   294: iconst_0
        //   295: ldc 114
        //   297: castore
        //   298: dup
        //   299: iconst_1
        //   300: ldc 115
        //   302: castore
        //   303: invokestatic 98	o/Fc$ˋ$ˋ:ˋ	([C)Ljava/lang/String;
        //   306: invokevirtual 101	java/lang/String:intern	()Ljava/lang/String;
        //   309: invokevirtual 105	java/lang/StringBuilder:append	(Ljava/lang/String;)Ljava/lang/StringBuilder;
        //   312: invokevirtual 117	java/lang/StringBuilder:toString	()Ljava/lang/String;
        //   315: astore_2
        //   316: goto +6 -> 322
        //   319: astore_2
        //   320: aload_2
        //   321: athrow
        //   322: getstatic 23	o/Fc$ˋ$ˋ:ˏ	I
        //   325: istore_1
        //   326: iload_1
        //   327: bipush 87
        //   329: iadd
        //   330: istore_1
        //   331: iload_1
        //   332: sipush 128
        //   335: irem
        //   336: putstatic 25	o/Fc$ˋ$ˋ:ʼ	I
        //   339: iload_1
        //   340: iconst_2
        //   341: irem
        //   342: ifne +5 -> 347
        //   345: aload_2
        //   346: areturn
        //   347: aload_2
        //   348: areturn
        //   349: goto -346 -> 3
        // Local variable table:
        //   start	length	slot	name	signature
        //   0	352	0	this	ˋ
        //   325	17	1	i	int
        //   315	1	2	str	String
        //   319	29	2	localException	Exception
        // Exception table:
        //   from	to	target	type
        //   322	326	319	java/lang/Exception
        //   331	339	319	java/lang/Exception
      }
      
      public final String ˊ()
      {
        for (;;)
        {
          int i = 6;
          break label22;
          String str = this.countryCode;
          i = 26 / 0;
          switch (i)
          {
          case 55: 
          default: 
            label22:
            break;
            label51:
            i = ˏ + 111;
            ʼ = i % 128;
            if (i % 2 == 0) {
              return str;
            }
            return str;
          }
          do
          {
            i = 55;
            break;
            str = this.countryCode;
            break label51;
            i = ʼ + 73;
            ˏ = i % 128;
          } while (i % 2 != 0);
        }
      }
      
      /* Error */
      public final String ˏ()
      {
        // Byte code:
        //   0: goto +66 -> 66
        //   3: goto +66 -> 69
        //   6: getstatic 25	o/Fc$ˋ$ˋ:ʼ	I
        //   9: bipush 33
        //   11: iadd
        //   12: istore_1
        //   13: iload_1
        //   14: sipush 128
        //   17: irem
        //   18: putstatic 23	o/Fc$ˋ$ˋ:ˏ	I
        //   21: iload_1
        //   22: iconst_2
        //   23: irem
        //   24: ifeq +6 -> 30
        //   27: goto +37 -> 64
        //   30: aload_2
        //   31: areturn
        //   32: astore_2
        //   33: aload_2
        //   34: athrow
        //   35: getstatic 23	o/Fc$ˋ$ˋ:ˏ	I
        //   38: istore_1
        //   39: iload_1
        //   40: bipush 81
        //   42: iadd
        //   43: istore_1
        //   44: iload_1
        //   45: sipush 128
        //   48: irem
        //   49: putstatic 25	o/Fc$ˋ$ˋ:ʼ	I
        //   52: iload_1
        //   53: iconst_2
        //   54: irem
        //   55: ifne +6 -> 61
        //   58: goto -55 -> 3
        //   61: goto +8 -> 69
        //   64: aload_2
        //   65: areturn
        //   66: goto -31 -> 35
        //   69: aload_0
        //   70: getfield 53	o/Fc$ˋ$ˋ:languageTag	Ljava/lang/String;
        //   73: astore_2
        //   74: goto -68 -> 6
        //   77: astore_2
        //   78: aload_2
        //   79: athrow
        // Local variable table:
        //   start	length	slot	name	signature
        //   0	80	0	this	ˋ
        //   12	43	1	i	int
        //   30	1	2	str1	String
        //   32	33	2	localException1	Exception
        //   73	1	2	str2	String
        //   77	2	2	localException2	Exception
        // Exception table:
        //   from	to	target	type
        //   35	39	32	java/lang/Exception
        //   44	52	77	java/lang/Exception
      }
    }
  }
}
