package o;

public final class FL
{
  private static int ˊ = 0;
  private static int ˋ = 1;
  private static char ˎ = '\005';
  private static char[] ॱ = { 79, 102, 101, 114, 67, 111, 117, 110, 116, 121, 40, 105, 100, 61, 44, 32, 99, 97, 109, 115, 112, 41, 80, 81, 82 };
  private final String code;
  private final String description;
  private final String name;
  private final String uuid;
  
  /* Error */
  private static String ॱ(char[] paramArrayOfChar, int paramInt, byte paramByte)
  {
    // Byte code:
    //   0: goto +218 -> 218
    //   3: iload 7
    //   5: iload 9
    //   7: iload 5
    //   9: invokestatic 61	o/oO:ˏ	(III)I
    //   12: istore 4
    //   14: iload 6
    //   16: iload 8
    //   18: iload 5
    //   20: invokestatic 61	o/oO:ˏ	(III)I
    //   23: istore 6
    //   25: aload 11
    //   27: iload_3
    //   28: aload 10
    //   30: iload 4
    //   32: caload
    //   33: castore
    //   34: aload 11
    //   36: iload_3
    //   37: iconst_1
    //   38: iadd
    //   39: aload 10
    //   41: iload 6
    //   43: caload
    //   44: castore
    //   45: goto +294 -> 339
    //   48: goto +519 -> 567
    //   51: iload 7
    //   53: iload 5
    //   55: invokestatic 64	o/oO:ˊ	(II)I
    //   58: istore 4
    //   60: iload 6
    //   62: iload 5
    //   64: invokestatic 64	o/oO:ˊ	(II)I
    //   67: istore 6
    //   69: iload 4
    //   71: iload 8
    //   73: iload 5
    //   75: invokestatic 61	o/oO:ˏ	(III)I
    //   78: istore 4
    //   80: iload 6
    //   82: iload 9
    //   84: iload 5
    //   86: invokestatic 61	o/oO:ˏ	(III)I
    //   89: istore 6
    //   91: aload 11
    //   93: iload_3
    //   94: aload 10
    //   96: iload 4
    //   98: caload
    //   99: castore
    //   100: aload 11
    //   102: iload_3
    //   103: iconst_1
    //   104: iadd
    //   105: aload 10
    //   107: iload 6
    //   109: caload
    //   110: castore
    //   111: goto +228 -> 339
    //   114: aload 11
    //   116: iload_3
    //   117: iload 6
    //   119: iload_2
    //   120: isub
    //   121: i2c
    //   122: castore
    //   123: aload 11
    //   125: iload_3
    //   126: iconst_1
    //   127: iadd
    //   128: iload 9
    //   130: iload_2
    //   131: isub
    //   132: i2c
    //   133: castore
    //   134: goto +346 -> 480
    //   137: iconst_0
    //   138: istore_3
    //   139: goto +431 -> 570
    //   142: iload 6
    //   144: iload 5
    //   146: invokestatic 66	o/oO:ॱ	(II)I
    //   149: istore 7
    //   151: iload 6
    //   153: iload 5
    //   155: invokestatic 68	o/oO:ˋ	(II)I
    //   158: istore 8
    //   160: iload 9
    //   162: iload 5
    //   164: invokestatic 66	o/oO:ॱ	(II)I
    //   167: istore 6
    //   169: iload 9
    //   171: iload 5
    //   173: invokestatic 68	o/oO:ˋ	(II)I
    //   176: istore 9
    //   178: iload 8
    //   180: iload 9
    //   182: if_icmpne +6 -> 188
    //   185: goto +282 -> 467
    //   188: goto +39 -> 227
    //   191: iload_1
    //   192: iconst_1
    //   193: if_icmple +6 -> 199
    //   196: goto +180 -> 376
    //   199: goto +22 -> 221
    //   202: iconst_0
    //   203: istore 4
    //   205: goto +29 -> 234
    //   208: new 70	java/lang/String
    //   211: dup
    //   212: aload 11
    //   214: invokespecial 74	java/lang/String:<init>	([C)V
    //   217: areturn
    //   218: goto +171 -> 389
    //   221: bipush 27
    //   223: istore_3
    //   224: goto +54 -> 278
    //   227: bipush 14
    //   229: istore 4
    //   231: goto +76 -> 307
    //   234: iload 4
    //   236: tableswitch	default:+24->260, 0:+337->573, 1:+-28->208
    //   260: goto +313 -> 573
    //   263: iconst_2
    //   264: istore 4
    //   266: goto +170 -> 436
    //   269: goto +241 -> 510
    //   272: astore_0
    //   273: aload_0
    //   274: athrow
    //   275: goto -161 -> 114
    //   278: iload_3
    //   279: lookupswitch	default:+25->304, 27:+-71->208, 66:+-142->137
    //   304: goto -167 -> 137
    //   307: iload 4
    //   309: lookupswitch	default:+27->336, 14:+212->521, 70:+-258->51
    //   336: goto -285 -> 51
    //   339: iload_3
    //   340: iconst_2
    //   341: iadd
    //   342: istore_3
    //   343: goto +194 -> 537
    //   346: getstatic 22	o/FL:ˋ	I
    //   349: bipush 31
    //   351: iadd
    //   352: istore 4
    //   354: iload 4
    //   356: sipush 128
    //   359: irem
    //   360: putstatic 20	o/FL:ˊ	I
    //   363: iload 4
    //   365: iconst_2
    //   366: irem
    //   367: ifeq +6 -> 373
    //   370: goto -95 -> 275
    //   373: goto -259 -> 114
    //   376: bipush 66
    //   378: istore_3
    //   379: goto -101 -> 278
    //   382: bipush 68
    //   384: istore 4
    //   386: goto +50 -> 436
    //   389: getstatic 49	o/FL:ॱ	[C
    //   392: astore 10
    //   394: getstatic 51	o/FL:ˎ	C
    //   397: istore 5
    //   399: iload_1
    //   400: newarray char
    //   402: astore 11
    //   404: iload_1
    //   405: iconst_2
    //   406: irem
    //   407: ifeq +6 -> 413
    //   410: goto +6 -> 416
    //   413: goto -222 -> 191
    //   416: iload_1
    //   417: iconst_1
    //   418: isub
    //   419: istore_1
    //   420: aload 11
    //   422: iload_1
    //   423: aload_0
    //   424: iload_1
    //   425: caload
    //   426: iload_2
    //   427: isub
    //   428: i2c
    //   429: castore
    //   430: goto -239 -> 191
    //   433: goto -164 -> 269
    //   436: iload 4
    //   438: lookupswitch	default:+26->464, 2:+-296->142, 68:+-92->346
    //   464: goto -322 -> 142
    //   467: bipush 70
    //   469: istore 4
    //   471: goto -164 -> 307
    //   474: iconst_1
    //   475: istore 4
    //   477: goto -243 -> 234
    //   480: getstatic 22	o/FL:ˋ	I
    //   483: bipush 109
    //   485: iadd
    //   486: istore 4
    //   488: iload 4
    //   490: sipush 128
    //   493: irem
    //   494: putstatic 20	o/FL:ˊ	I
    //   497: iload 4
    //   499: iconst_2
    //   500: irem
    //   501: ifeq +6 -> 507
    //   504: goto -456 -> 48
    //   507: goto +60 -> 567
    //   510: iload_3
    //   511: iload_1
    //   512: if_icmpge +6 -> 518
    //   515: goto -313 -> 202
    //   518: goto -44 -> 474
    //   521: iload 7
    //   523: iload 6
    //   525: if_icmpne +6 -> 531
    //   528: goto +70 -> 598
    //   531: goto -528 -> 3
    //   534: astore_0
    //   535: aload_0
    //   536: athrow
    //   537: getstatic 20	o/FL:ˊ	I
    //   540: bipush 37
    //   542: iadd
    //   543: istore 4
    //   545: iload 4
    //   547: sipush 128
    //   550: irem
    //   551: putstatic 22	o/FL:ˋ	I
    //   554: iload 4
    //   556: iconst_2
    //   557: irem
    //   558: ifne +6 -> 564
    //   561: goto -128 -> 433
    //   564: goto -295 -> 269
    //   567: goto -228 -> 339
    //   570: goto -60 -> 510
    //   573: aload_0
    //   574: iload_3
    //   575: caload
    //   576: istore 6
    //   578: aload_0
    //   579: iload_3
    //   580: iconst_1
    //   581: iadd
    //   582: caload
    //   583: istore 9
    //   585: iload 6
    //   587: iload 9
    //   589: if_icmpne +6 -> 595
    //   592: goto -210 -> 382
    //   595: goto -332 -> 263
    //   598: iload 8
    //   600: iload 5
    //   602: invokestatic 64	o/oO:ˊ	(II)I
    //   605: istore 4
    //   607: iload 9
    //   609: iload 5
    //   611: invokestatic 64	o/oO:ˊ	(II)I
    //   614: istore 8
    //   616: iload 7
    //   618: iload 4
    //   620: iload 5
    //   622: invokestatic 61	o/oO:ˏ	(III)I
    //   625: istore 4
    //   627: iload 6
    //   629: iload 8
    //   631: iload 5
    //   633: invokestatic 61	o/oO:ˏ	(III)I
    //   636: istore 6
    //   638: aload 11
    //   640: iload_3
    //   641: aload 10
    //   643: iload 4
    //   645: caload
    //   646: castore
    //   647: aload 11
    //   649: iload_3
    //   650: iconst_1
    //   651: iadd
    //   652: aload 10
    //   654: iload 6
    //   656: caload
    //   657: castore
    //   658: goto -319 -> 339
    // Local variable table:
    //   start	length	slot	name	signature
    //   0	661	0	paramArrayOfChar	char[]
    //   0	661	1	paramInt	int
    //   0	661	2	paramByte	byte
    //   27	625	3	i	int
    //   12	632	4	j	int
    //   7	625	5	k	int
    //   14	641	6	b1	byte
    //   3	614	7	b2	byte
    //   16	614	8	b3	byte
    //   5	603	9	b4	byte
    //   28	625	10	arrayOfChar1	char[]
    //   25	623	11	arrayOfChar2	char[]
    // Exception table:
    //   from	to	target	type
    //   354	363	272	java/lang/Exception
    //   346	354	534	java/lang/Exception
    //   354	363	534	java/lang/Exception
    //   537	545	534	java/lang/Exception
    //   545	554	534	java/lang/Exception
  }
  
  /* Error */
  public boolean equals(Object paramObject)
  {
    // Byte code:
    //   0: goto +352 -> 352
    //   3: aload_1
    //   4: checkcast 2	o/FL
    //   7: astore_1
    //   8: aload_0
    //   9: getfield 78	o/FL:uuid	Ljava/lang/String;
    //   12: aload_1
    //   13: getfield 78	o/FL:uuid	Ljava/lang/String;
    //   16: invokestatic 83	o/vq:ˊ	(Ljava/lang/Object;Ljava/lang/Object;)Z
    //   19: ifeq +6 -> 25
    //   22: goto +12 -> 34
    //   25: goto +59 -> 84
    //   28: astore_1
    //   29: aload_1
    //   30: athrow
    //   31: astore_1
    //   32: aload_1
    //   33: athrow
    //   34: aload_0
    //   35: getfield 85	o/FL:code	Ljava/lang/String;
    //   38: aload_1
    //   39: getfield 85	o/FL:code	Ljava/lang/String;
    //   42: invokestatic 83	o/vq:ˊ	(Ljava/lang/Object;Ljava/lang/Object;)Z
    //   45: ifeq +6 -> 51
    //   48: goto +99 -> 147
    //   51: goto +304 -> 355
    //   54: bipush 38
    //   56: istore_2
    //   57: goto +156 -> 213
    //   60: aload_0
    //   61: getfield 87	o/FL:name	Ljava/lang/String;
    //   64: aload_1
    //   65: getfield 87	o/FL:name	Ljava/lang/String;
    //   68: invokestatic 83	o/vq:ˊ	(Ljava/lang/Object;Ljava/lang/Object;)Z
    //   71: istore_3
    //   72: bipush 56
    //   74: iconst_0
    //   75: idiv
    //   76: istore_2
    //   77: iload_3
    //   78: ifeq +6 -> 84
    //   81: goto +194 -> 275
    //   84: goto +122 -> 206
    //   87: goto +312 -> 399
    //   90: getstatic 22	o/FL:ˋ	I
    //   93: istore_2
    //   94: iload_2
    //   95: bipush 61
    //   97: iadd
    //   98: istore_2
    //   99: iload_2
    //   100: sipush 128
    //   103: irem
    //   104: putstatic 20	o/FL:ˊ	I
    //   107: iload_2
    //   108: iconst_2
    //   109: irem
    //   110: ifeq +6 -> 116
    //   113: goto +248 -> 361
    //   116: goto +218 -> 334
    //   119: iload_2
    //   120: tableswitch	default:+24->144, 0:+123->243, 1:+-30->90
    //   144: goto +99 -> 243
    //   147: bipush 25
    //   149: istore_2
    //   150: iload_2
    //   151: lookupswitch	default:+25->176, 25:+144->295, 35:+-67->84
    //   176: goto +119 -> 295
    //   179: getstatic 20	o/FL:ˊ	I
    //   182: bipush 37
    //   184: iadd
    //   185: istore_2
    //   186: iload_2
    //   187: sipush 128
    //   190: irem
    //   191: putstatic 22	o/FL:ˋ	I
    //   194: iload_2
    //   195: iconst_2
    //   196: irem
    //   197: ifne +6 -> 203
    //   200: goto -113 -> 87
    //   203: goto +196 -> 399
    //   206: iconst_0
    //   207: ireturn
    //   208: iconst_0
    //   209: istore_2
    //   210: goto -91 -> 119
    //   213: iload_2
    //   214: lookupswitch	default:+26->240, 38:+31->245, 85:+-154->60
    //   240: goto -180 -> 60
    //   243: iconst_1
    //   244: ireturn
    //   245: aload_0
    //   246: getfield 87	o/FL:name	Ljava/lang/String;
    //   249: astore 4
    //   251: aload_1
    //   252: getfield 87	o/FL:name	Ljava/lang/String;
    //   255: astore 5
    //   257: aload 4
    //   259: aload 5
    //   261: invokestatic 83	o/vq:ˊ	(Ljava/lang/Object;Ljava/lang/Object;)Z
    //   264: istore_3
    //   265: iload_3
    //   266: ifeq +6 -> 272
    //   269: goto +6 -> 275
    //   272: goto -188 -> 84
    //   275: aload_0
    //   276: getfield 89	o/FL:description	Ljava/lang/String;
    //   279: aload_1
    //   280: getfield 89	o/FL:description	Ljava/lang/String;
    //   283: invokestatic 83	o/vq:ˊ	(Ljava/lang/Object;Ljava/lang/Object;)Z
    //   286: ifeq +6 -> 292
    //   289: goto -46 -> 243
    //   292: goto -208 -> 84
    //   295: getstatic 20	o/FL:ˊ	I
    //   298: bipush 95
    //   300: iadd
    //   301: istore_2
    //   302: iload_2
    //   303: sipush 128
    //   306: irem
    //   307: putstatic 22	o/FL:ˋ	I
    //   310: iload_2
    //   311: iconst_2
    //   312: irem
    //   313: ifne +6 -> 319
    //   316: goto +12 -> 328
    //   319: goto -265 -> 54
    //   322: bipush 7
    //   324: istore_2
    //   325: goto +42 -> 367
    //   328: bipush 85
    //   330: istore_2
    //   331: goto -118 -> 213
    //   334: aload_1
    //   335: instanceof 2
    //   338: ifeq +6 -> 344
    //   341: goto -19 -> 322
    //   344: goto +20 -> 364
    //   347: iconst_1
    //   348: istore_2
    //   349: goto -230 -> 119
    //   352: goto -173 -> 179
    //   355: bipush 35
    //   357: istore_2
    //   358: goto -208 -> 150
    //   361: goto -27 -> 334
    //   364: bipush 57
    //   366: istore_2
    //   367: iload_2
    //   368: lookupswitch	default:+28->396, 7:+-365->3, 57:+-284->84
    //   396: goto -393 -> 3
    //   399: aload_0
    //   400: aload_1
    //   401: if_acmpeq +6 -> 407
    //   404: goto -57 -> 347
    //   407: goto -199 -> 208
    // Local variable table:
    //   start	length	slot	name	signature
    //   0	410	0	this	FL
    //   0	410	1	paramObject	Object
    //   56	312	2	i	int
    //   71	195	3	bool	boolean
    //   249	9	4	str1	String
    //   255	5	5	str2	String
    // Exception table:
    //   from	to	target	type
    //   245	251	28	java/lang/Exception
    //   251	257	28	java/lang/Exception
    //   257	265	28	java/lang/Exception
    //   90	94	31	java/lang/Exception
    //   99	107	31	java/lang/Exception
  }
  
  /* Error */
  public int hashCode()
  {
    // Byte code:
    //   0: goto +241 -> 241
    //   3: aload 6
    //   5: astore 5
    //   7: iload_1
    //   8: lookupswitch	default:+28->36, 37:+398->406, 97:+192->200
    //   36: aload 6
    //   38: astore 5
    //   40: goto +160 -> 200
    //   43: iconst_1
    //   44: istore_3
    //   45: goto +321 -> 366
    //   48: iload_2
    //   49: tableswitch	default:+23->72, 0:+183->232, 1:+305->354
    //   72: goto +282 -> 354
    //   75: goto +353 -> 428
    //   78: getstatic 22	o/FL:ˋ	I
    //   81: istore_2
    //   82: iload_2
    //   83: bipush 37
    //   85: iadd
    //   86: istore_2
    //   87: iload_2
    //   88: sipush 128
    //   91: irem
    //   92: putstatic 20	o/FL:ˊ	I
    //   95: iload_2
    //   96: iconst_2
    //   97: irem
    //   98: ifeq +6 -> 104
    //   101: goto +166 -> 267
    //   104: goto +37 -> 141
    //   107: bipush 37
    //   109: istore_1
    //   110: goto -107 -> 3
    //   113: iconst_0
    //   114: istore 4
    //   116: goto +133 -> 249
    //   119: aload_0
    //   120: getfield 85	o/FL:code	Ljava/lang/String;
    //   123: astore 5
    //   125: aload 5
    //   127: ifnull +6 -> 133
    //   130: goto -52 -> 78
    //   133: goto +184 -> 317
    //   136: iconst_0
    //   137: istore_3
    //   138: goto +228 -> 366
    //   141: iconst_0
    //   142: istore_2
    //   143: goto -95 -> 48
    //   146: getstatic 22	o/FL:ˋ	I
    //   149: bipush 35
    //   151: iadd
    //   152: istore_3
    //   153: iload_3
    //   154: sipush 128
    //   157: irem
    //   158: putstatic 20	o/FL:ˊ	I
    //   161: iload_3
    //   162: iconst_2
    //   163: irem
    //   164: ifeq +6 -> 170
    //   167: goto -92 -> 75
    //   170: goto +258 -> 428
    //   173: getstatic 20	o/FL:ˊ	I
    //   176: bipush 7
    //   178: iadd
    //   179: istore_1
    //   180: iload_1
    //   181: sipush 128
    //   184: irem
    //   185: putstatic 22	o/FL:ˋ	I
    //   188: iload_1
    //   189: iconst_2
    //   190: irem
    //   191: ifne +6 -> 197
    //   194: goto +33 -> 227
    //   197: goto +194 -> 391
    //   200: getstatic 22	o/FL:ˋ	I
    //   203: bipush 87
    //   205: iadd
    //   206: istore_1
    //   207: iload_1
    //   208: sipush 128
    //   211: irem
    //   212: putstatic 20	o/FL:ˊ	I
    //   215: iload_1
    //   216: iconst_2
    //   217: irem
    //   218: ifeq +6 -> 224
    //   221: goto +233 -> 454
    //   224: goto +84 -> 308
    //   227: iconst_0
    //   228: istore_1
    //   229: goto +270 -> 499
    //   232: aload 5
    //   234: invokevirtual 93	java/lang/Object:hashCode	()I
    //   237: istore_2
    //   238: goto -92 -> 146
    //   241: goto -68 -> 173
    //   244: astore 5
    //   246: aload 5
    //   248: athrow
    //   249: iload_1
    //   250: bipush 31
    //   252: imul
    //   253: iload_2
    //   254: iadd
    //   255: bipush 31
    //   257: imul
    //   258: iload_3
    //   259: iadd
    //   260: bipush 31
    //   262: imul
    //   263: iload 4
    //   265: iadd
    //   266: ireturn
    //   267: iconst_1
    //   268: istore_2
    //   269: goto -221 -> 48
    //   272: iload_1
    //   273: lookupswitch	default:+27->300, 38:+133->406, 92:+-73->200
    //   300: goto +106 -> 406
    //   303: astore 5
    //   305: aload 5
    //   307: athrow
    //   308: aload 5
    //   310: invokevirtual 93	java/lang/Object:hashCode	()I
    //   313: istore_1
    //   314: goto -195 -> 119
    //   317: iconst_0
    //   318: istore_2
    //   319: goto +112 -> 431
    //   322: aload_0
    //   323: getfield 87	o/FL:name	Ljava/lang/String;
    //   326: astore 5
    //   328: aload 5
    //   330: ifnull +6 -> 336
    //   333: goto -197 -> 136
    //   336: goto -293 -> 43
    //   339: bipush 92
    //   341: istore_1
    //   342: goto -70 -> 272
    //   345: aload 5
    //   347: invokevirtual 93	java/lang/Object:hashCode	()I
    //   350: istore_3
    //   351: goto +125 -> 476
    //   354: aload 5
    //   356: invokevirtual 93	java/lang/Object:hashCode	()I
    //   359: istore_2
    //   360: aconst_null
    //   361: arraylength
    //   362: istore_3
    //   363: goto -217 -> 146
    //   366: iload_3
    //   367: tableswitch	default:+21->388, 0:+-22->345, 1:+107->474
    //   388: goto -43 -> 345
    //   391: iconst_1
    //   392: istore_1
    //   393: goto +106 -> 499
    //   396: aload 5
    //   398: invokevirtual 93	java/lang/Object:hashCode	()I
    //   401: istore 4
    //   403: goto -154 -> 249
    //   406: iconst_0
    //   407: istore_1
    //   408: goto -289 -> 119
    //   411: aload_0
    //   412: getfield 78	o/FL:uuid	Ljava/lang/String;
    //   415: astore 5
    //   417: aload 5
    //   419: ifnull +6 -> 425
    //   422: goto -83 -> 339
    //   425: goto +43 -> 468
    //   428: goto -106 -> 322
    //   431: goto -109 -> 322
    //   434: aload_0
    //   435: getfield 78	o/FL:uuid	Ljava/lang/String;
    //   438: astore 6
    //   440: aconst_null
    //   441: arraylength
    //   442: istore_1
    //   443: aload 6
    //   445: ifnull +6 -> 451
    //   448: goto +45 -> 493
    //   451: goto -344 -> 107
    //   454: aload 5
    //   456: invokevirtual 93	java/lang/Object:hashCode	()I
    //   459: istore_1
    //   460: bipush 54
    //   462: iconst_0
    //   463: idiv
    //   464: istore_2
    //   465: goto -346 -> 119
    //   468: bipush 38
    //   470: istore_1
    //   471: goto -199 -> 272
    //   474: iconst_0
    //   475: istore_3
    //   476: aload_0
    //   477: getfield 89	o/FL:description	Ljava/lang/String;
    //   480: astore 5
    //   482: aload 5
    //   484: ifnull +6 -> 490
    //   487: goto -91 -> 396
    //   490: goto -377 -> 113
    //   493: bipush 97
    //   495: istore_1
    //   496: goto -493 -> 3
    //   499: iload_1
    //   500: tableswitch	default:+24->524, 0:+-66->434, 1:+-89->411
    //   524: goto -113 -> 411
    // Local variable table:
    //   start	length	slot	name	signature
    //   0	527	0	this	FL
    //   7	493	1	i	int
    //   48	417	2	j	int
    //   44	432	3	k	int
    //   114	288	4	m	int
    //   5	228	5	str1	String
    //   244	3	5	localException1	Exception
    //   303	6	5	localException2	Exception
    //   326	157	5	str2	String
    //   3	441	6	str3	String
    // Exception table:
    //   from	to	target	type
    //   78	82	244	java/lang/Exception
    //   119	125	244	java/lang/Exception
    //   232	238	244	java/lang/Exception
    //   322	328	303	java/lang/Exception
    //   434	443	303	java/lang/Exception
  }
  
  public String toString()
  {
    for (;;)
    {
      Object localObject = new StringBuilder();
      try
      {
        String str = ॱ(new char[] { 1, 2, 2, 3, 4, 0, 6, 7, 8, 9, 4, 8, 11, 5, 11, 16, 13, 14 }, 18, (byte)33);
        str = str.intern();
        localObject = ((StringBuilder)localObject).append(str);
        localObject = this.uuid + ॱ(new char[] { 10, 19, 15, 6, 17, 7, 77 }, 7, (byte)16).intern() + this.code + ॱ(new char[] { 10, 19, 12, 22, 17, 3, 79 }, 7, (byte)18).intern() + this.name + ॱ(new char[] { 10, 19, 17, 7, 15, 17, 1, 13, 23, 5, 10, 6, 8, 12 }, 14, (byte)2).intern() + this.description + ॱ(new char[] { 64 }, 1, (byte)23).intern();
        int i = ˊ + 85;
        ˋ = i % 128;
        if (i % 2 == 0) {
          break;
        }
        return localObject;
      }
      catch (Exception localException1)
      {
        throw localException1;
      }
      catch (Exception localException2)
      {
        throw localException2;
      }
    }
    return localException2;
  }
  
  public final String ˊ()
  {
    for (;;)
    {
      int i = ˋ + 83;
      ˊ = i % 128;
      if (i % 2 == 0) {
        break label58;
      }
      for (;;)
      {
        i = ˊ + 89;
        ˋ = i % 128;
        if (i % 2 == 0) {
          return str;
        }
        return str;
        label58:
        String str = this.code;
      }
    }
  }
}
