package o;

import java.util.concurrent.CopyOnWriteArrayList;

public final class GA
{
  private static int ʽ;
  private static final uA ˊ;
  private static long ˋ;
  private static char[] ˏ;
  public static final ˋ ॱ;
  private static int ॱॱ = 0;
  private final CopyOnWriteArrayList<Ik<?>> ˎ = new CopyOnWriteArrayList();
  
  static
  {
    ʽ = 1;
    ˏ();
    ॱ = new ˋ(null);
    ˊ = uC.ˋ((vh)ˊ.ˋ);
    int i;
    do
    {
      return;
      i = ॱॱ + 95;
      ʽ = i % 128;
    } while (i % 2 == 0);
  }
  
  public GA() {}
  
  private static String ˏ(int paramInt1, char paramChar, int paramInt2)
  {
    break label239;
    char[] arrayOfChar;
    int i;
    arrayOfChar[i] = ((char)(int)(ˏ[(paramInt1 + i)] ^ i * ˋ ^ paramChar));
    i += 1;
    break label80;
    int j = ʽ + 21;
    ॱॱ = j % 128;
    if (j % 2 == 0) {
      j = 0;
    }
    for (;;)
    {
      break label80;
      return new String(arrayOfChar);
      label80:
      if (i >= paramInt2)
      {
        break label242;
        for (;;)
        {
          switch (j)
          {
          case 0: 
          default: 
            break;
            arrayOfChar = new char[paramInt2];
            i = 0;
            break;
          case 1: 
            label119:
            arrayOfChar[i] = ((char)(int)(ˏ[(paramInt1 * i)] * (i + ˋ) ^ paramChar));
            i += 127;
            break label80;
            j = 1;
          }
        }
      }
      j = 95;
      break label207;
      j = ʽ + 71;
      ॱॱ = j % 128;
      if (j % 2 == 0) {}
    }
    for (;;)
    {
      label207:
      switch (j)
      {
      }
      break;
      label239:
      break label119;
      label242:
      j = 66;
    }
  }
  
  static void ˏ()
  {
    ˋ = 351779912144384372L;
    ˏ = new char[] { 97, -3836, -7551, -11233, -14927, -18648, -22316, -26034, -29759, 32119, 28387, 78, -3823, -7524, -11221, -14913, -18634, -22317, -22806, 22459, 17447, 29330, 25375, 4559, 3666, 15607, 11618, -9220, -14270, -1733, -2121, -7123, -28014, -31996, -20096, -20929, 23796, 19806, 31695, 26695, 6515, 6069, 1070, 12942, 8982, -11790, -12696, -773, -4845, -25650, -30641, -18118, -18515, -23549, 21138, 17161, 29178, 28258, 7417, 3333, 15235, 2479, -1905, -5368, -8717, -13269, -16733, -24238, -27773, -32162, 29934, 26466, 22022, 22682, 82, -3823, -7547, -11213, -14938, -18655, -22308, -26100, -29727, 32100, 28385, 24511, 20753, 17032, 13364, 9646, 5921, 2263, -1469, -5188, -8857, -12563, -16500, -20220, -23872, -27610, -31315, 30541, 26821, 23105, 19435, 15736, 11936, 8093, 4364, 697, -3010, -6736, -10415, -14134, -17847, -21519, -25222, -29114, 32720, -20617, 24133, 19917, 31588, 27370, 6195, 1947, 13587, 9362, -11677, -15954, -3874, -446, -4666, -25750, 19345, -17687, -22156, -24614, -29113, -818, -7362, 83, -3840, -7543, -11218, -14940, -18643, -22314, -26037, -29824, 32096, 28391, 24540, 20739, 17029, 13366, 9637, 5940, 2269, -1454, -5127, -8912, -12554, -16483, -20195, -23915, -27599, -31301, 30536, 26819, 109, -3785, -7543, -11216, -14916, -18650, -22311, -26033, -29749, 32069, 28413, 24473, 20741, 17025, 13430, 9637, 5940, 2257, -1446, -5123, -8860, -12565, -16502, -20156, -23863, 24097, -20638, -17161, -30134, -25662, -5820, -2398, -15311, -10828, 9031, 12474, 511, 3946, 7380, 27210, 31699, 18783, 22181, -23494, -19060, -31992, -28457, -7684, -4234, -793, -13745, -9317, 10557, 13990, 1062, 5534, 25370, 28800, 16883, 20283, 23750, -21945, -17454, -30427, -26965, -7110, -2687, -15598, -12182, 8689, 12077, 15499, 82, -3823, -7548, -11207, -14927, -18633, -22319, -26046, -29753, 32052, 28410, 24473, 20739, 17044, 13367, 9634, 5939, 2257, -1528, -5126, -8862, -12565, -16491, -20148, -23916, -27588, -31315, 30492, 26816, 23117, 19432, 15721, 11936, 8091, 4358, 764, -3055, -6732, -10415, -14097, -17855, -21512, -25244, -29154, 32657, 28935, 25267, 21612, 17847, 14173, 10460, 6772, 2992, -650, -4579, -8291, -12011, -15695, -19397, -23096, -26864, 9308, -10971, -14664, -4089, -7791, -27880, -29461, -16784, -20496, 22867, 19079, 31721, -9885, 10272, 15272, 3352, 7300, 28166, 29181, 17262, 21169, -23471, -18479, -31060, -30667, -25611, -4856, -881, -12780, -11867, 9077, 13000, 1095, 6081, 26345, 26676, 31679, 19781, 23688, -20872, -19996, -31904, -27956, -7147, 41, -3762, -7480, 32, -3751, -7480, -11253, -14919, -18640, -22320, -26100, -29742, 32113, 28409, 24457, 20757, 17047, 13356, 9708, 5929, 2256, -1459, -5134, -8860, -12563, -16482, -20219, -23931, -27610, -31246, 30492, 105, -3840 };
  }
  
  /* Error */
  public final void ˊ(android.content.Context paramContext)
  {
    // Byte code:
    //   0: goto +466 -> 466
    //   3: aload 5
    //   5: invokeinterface 440 1 0
    //   10: checkcast 442	o/Ik
    //   13: astore_1
    //   14: aload_1
    //   15: invokevirtual 445	o/Ik:ʽ	()Landroid/content/Context;
    //   18: pop
    //   19: new 447	java/lang/NullPointerException
    //   22: dup
    //   23: invokespecial 448	java/lang/NullPointerException:<init>	()V
    //   26: athrow
    //   27: getstatic 31	o/GA:ʽ	I
    //   30: bipush 33
    //   32: iadd
    //   33: istore_2
    //   34: iload_2
    //   35: sipush 128
    //   38: irem
    //   39: putstatic 29	o/GA:ॱॱ	I
    //   42: iload_2
    //   43: iconst_2
    //   44: irem
    //   45: ifeq +6 -> 51
    //   48: goto -45 -> 3
    //   51: goto +44 -> 95
    //   54: iload_2
    //   55: tableswitch	default:+21->76, 0:+404->459, 1:+679->734
    //   76: goto +383 -> 459
    //   79: aload 5
    //   81: invokeinterface 452 1 0
    //   86: ifeq +6 -> 92
    //   89: goto +648 -> 737
    //   92: goto +651 -> 743
    //   95: aload 5
    //   97: invokeinterface 440 1 0
    //   102: astore_3
    //   103: aload_3
    //   104: checkcast 442	o/Ik
    //   107: astore_3
    //   108: aload_3
    //   109: invokevirtual 445	o/Ik:ʽ	()Landroid/content/Context;
    //   112: astore 6
    //   114: aload 6
    //   116: ifnonnull +6 -> 122
    //   119: goto +350 -> 469
    //   122: goto +636 -> 758
    //   125: iload_2
    //   126: lookupswitch	default:+26->152, 14:+-99->27, 59:+454->580
    //   152: goto -125 -> 27
    //   155: astore_1
    //   156: aload_1
    //   157: athrow
    //   158: goto -79 -> 79
    //   161: bipush 11
    //   163: iconst_0
    //   164: bipush 7
    //   166: invokestatic 454	o/GA:ˏ	(ICI)Ljava/lang/String;
    //   169: invokevirtual 458	java/lang/String:intern	()Ljava/lang/String;
    //   172: astore 4
    //   174: aload_1
    //   175: sipush 134
    //   178: sipush 19442
    //   181: bipush 7
    //   183: invokestatic 454	o/GA:ˏ	(ICI)Ljava/lang/String;
    //   186: invokevirtual 458	java/lang/String:intern	()Ljava/lang/String;
    //   189: invokestatic 463	o/vq:ˎ	(Ljava/lang/Object;Ljava/lang/String;)V
    //   192: sipush 141
    //   195: iconst_0
    //   196: bipush 29
    //   198: invokestatic 454	o/GA:ˏ	(ICI)Ljava/lang/String;
    //   201: invokevirtual 458	java/lang/String:intern	()Ljava/lang/String;
    //   204: astore_3
    //   205: goto +17 -> 222
    //   208: astore_3
    //   209: aload_3
    //   210: invokevirtual 469	java/lang/Throwable:getCause	()Ljava/lang/Throwable;
    //   213: astore_1
    //   214: aload_1
    //   215: ifnull +5 -> 220
    //   218: aload_1
    //   219: athrow
    //   220: aload_3
    //   221: athrow
    //   222: iconst_4
    //   223: bipush 42
    //   225: ldc_w 470
    //   228: invokestatic 475	o/O:ˋ	(IIC)Ljava/lang/Object;
    //   231: checkcast 477	java/lang/Class
    //   234: ldc_w 478
    //   237: iconst_2
    //   238: anewarray 477	java/lang/Class
    //   241: dup
    //   242: iconst_0
    //   243: ldc 66
    //   245: aastore
    //   246: dup
    //   247: iconst_1
    //   248: ldc 66
    //   250: aastore
    //   251: invokevirtual 482	java/lang/Class:getMethod	(Ljava/lang/String;[Ljava/lang/Class;)Ljava/lang/reflect/Method;
    //   254: aconst_null
    //   255: iconst_2
    //   256: anewarray 4	java/lang/Object
    //   259: dup
    //   260: iconst_0
    //   261: aload 4
    //   263: aastore
    //   264: dup
    //   265: iconst_1
    //   266: aload_3
    //   267: aastore
    //   268: invokevirtual 488	java/lang/reflect/Method:invoke	(Ljava/lang/Object;[Ljava/lang/Object;)Ljava/lang/Object;
    //   271: pop
    //   272: aload_0
    //   273: getfield 59	o/GA:ˎ	Ljava/util/concurrent/CopyOnWriteArrayList;
    //   276: invokevirtual 492	java/util/concurrent/CopyOnWriteArrayList:iterator	()Ljava/util/Iterator;
    //   279: astore 5
    //   281: aload 5
    //   283: sipush 170
    //   286: iconst_0
    //   287: bipush 25
    //   289: invokestatic 454	o/GA:ˏ	(ICI)Ljava/lang/String;
    //   292: invokevirtual 458	java/lang/String:intern	()Ljava/lang/String;
    //   295: invokestatic 494	o/vq:ˋ	(Ljava/lang/Object;Ljava/lang/String;)V
    //   298: goto -219 -> 79
    //   301: iconst_0
    //   302: istore_2
    //   303: goto -249 -> 54
    //   306: getstatic 31	o/GA:ʽ	I
    //   309: bipush 93
    //   311: iadd
    //   312: istore_2
    //   313: iload_2
    //   314: sipush 128
    //   317: irem
    //   318: putstatic 29	o/GA:ॱॱ	I
    //   321: iload_2
    //   322: iconst_2
    //   323: irem
    //   324: ifeq +6 -> 330
    //   327: goto -26 -> 301
    //   330: goto +607 -> 937
    //   333: new 496	java/lang/StringBuilder
    //   336: dup
    //   337: invokespecial 497	java/lang/StringBuilder:<init>	()V
    //   340: sipush 242
    //   343: iconst_0
    //   344: bipush 61
    //   346: invokestatic 454	o/GA:ˏ	(ICI)Ljava/lang/String;
    //   349: invokevirtual 458	java/lang/String:intern	()Ljava/lang/String;
    //   352: invokevirtual 501	java/lang/StringBuilder:append	(Ljava/lang/String;)Ljava/lang/StringBuilder;
    //   355: sipush 303
    //   358: sipush 9269
    //   361: bipush 12
    //   363: invokestatic 454	o/GA:ˏ	(ICI)Ljava/lang/String;
    //   366: invokevirtual 458	java/lang/String:intern	()Ljava/lang/String;
    //   369: invokevirtual 501	java/lang/StringBuilder:append	(Ljava/lang/String;)Ljava/lang/StringBuilder;
    //   372: aload_3
    //   373: invokevirtual 503	o/Ik:ˋ	()Ljava/lang/String;
    //   376: invokevirtual 501	java/lang/StringBuilder:append	(Ljava/lang/String;)Ljava/lang/StringBuilder;
    //   379: invokevirtual 506	java/lang/StringBuilder:toString	()Ljava/lang/String;
    //   382: astore 6
    //   384: goto +17 -> 401
    //   387: astore_3
    //   388: aload_3
    //   389: invokevirtual 469	java/lang/Throwable:getCause	()Ljava/lang/Throwable;
    //   392: astore_1
    //   393: aload_1
    //   394: ifnull +5 -> 399
    //   397: aload_1
    //   398: athrow
    //   399: aload_3
    //   400: athrow
    //   401: iconst_4
    //   402: bipush 42
    //   404: ldc_w 470
    //   407: invokestatic 475	o/O:ˋ	(IIC)Ljava/lang/Object;
    //   410: checkcast 477	java/lang/Class
    //   413: ldc_w 478
    //   416: iconst_2
    //   417: anewarray 477	java/lang/Class
    //   420: dup
    //   421: iconst_0
    //   422: ldc 66
    //   424: aastore
    //   425: dup
    //   426: iconst_1
    //   427: ldc 66
    //   429: aastore
    //   430: invokevirtual 482	java/lang/Class:getMethod	(Ljava/lang/String;[Ljava/lang/Class;)Ljava/lang/reflect/Method;
    //   433: aconst_null
    //   434: iconst_2
    //   435: anewarray 4	java/lang/Object
    //   438: dup
    //   439: iconst_0
    //   440: aload 4
    //   442: aastore
    //   443: dup
    //   444: iconst_1
    //   445: aload 6
    //   447: aastore
    //   448: invokevirtual 488	java/lang/reflect/Method:invoke	(Ljava/lang/Object;[Ljava/lang/Object;)Ljava/lang/Object;
    //   451: pop
    //   452: aload_3
    //   453: invokevirtual 509	o/Ik:ʼ	()V
    //   456: goto -298 -> 158
    //   459: iconst_5
    //   460: iconst_2
    //   461: idiv
    //   462: istore_2
    //   463: goto +312 -> 775
    //   466: goto -305 -> 161
    //   469: new 496	java/lang/StringBuilder
    //   472: dup
    //   473: invokespecial 497	java/lang/StringBuilder:<init>	()V
    //   476: sipush 195
    //   479: sipush 24179
    //   482: bipush 47
    //   484: invokestatic 454	o/GA:ˏ	(ICI)Ljava/lang/String;
    //   487: invokevirtual 458	java/lang/String:intern	()Ljava/lang/String;
    //   490: invokevirtual 501	java/lang/StringBuilder:append	(Ljava/lang/String;)Ljava/lang/StringBuilder;
    //   493: aload_3
    //   494: invokevirtual 503	o/Ik:ˋ	()Ljava/lang/String;
    //   497: invokevirtual 501	java/lang/StringBuilder:append	(Ljava/lang/String;)Ljava/lang/StringBuilder;
    //   500: invokevirtual 506	java/lang/StringBuilder:toString	()Ljava/lang/String;
    //   503: astore 6
    //   505: goto +17 -> 522
    //   508: astore_3
    //   509: aload_3
    //   510: invokevirtual 469	java/lang/Throwable:getCause	()Ljava/lang/Throwable;
    //   513: astore_1
    //   514: aload_1
    //   515: ifnull +5 -> 520
    //   518: aload_1
    //   519: athrow
    //   520: aload_3
    //   521: athrow
    //   522: iconst_4
    //   523: bipush 42
    //   525: ldc_w 470
    //   528: invokestatic 475	o/O:ˋ	(IIC)Ljava/lang/Object;
    //   531: checkcast 477	java/lang/Class
    //   534: ldc_w 478
    //   537: iconst_2
    //   538: anewarray 477	java/lang/Class
    //   541: dup
    //   542: iconst_0
    //   543: ldc 66
    //   545: aastore
    //   546: dup
    //   547: iconst_1
    //   548: ldc 66
    //   550: aastore
    //   551: invokevirtual 482	java/lang/Class:getMethod	(Ljava/lang/String;[Ljava/lang/Class;)Ljava/lang/reflect/Method;
    //   554: aconst_null
    //   555: iconst_2
    //   556: anewarray 4	java/lang/Object
    //   559: dup
    //   560: iconst_0
    //   561: aload 4
    //   563: aastore
    //   564: dup
    //   565: iconst_1
    //   566: aload 6
    //   568: aastore
    //   569: invokevirtual 488	java/lang/reflect/Method:invoke	(Ljava/lang/Object;[Ljava/lang/Object;)Ljava/lang/Object;
    //   572: pop
    //   573: aload_3
    //   574: invokevirtual 510	o/Ik:ˏ	()V
    //   577: goto -419 -> 158
    //   580: new 496	java/lang/StringBuilder
    //   583: dup
    //   584: invokespecial 497	java/lang/StringBuilder:<init>	()V
    //   587: sipush 315
    //   590: ldc_w 511
    //   593: bipush 32
    //   595: invokestatic 454	o/GA:ˏ	(ICI)Ljava/lang/String;
    //   598: invokevirtual 458	java/lang/String:intern	()Ljava/lang/String;
    //   601: invokevirtual 501	java/lang/StringBuilder:append	(Ljava/lang/String;)Ljava/lang/StringBuilder;
    //   604: aload_0
    //   605: getfield 59	o/GA:ˎ	Ljava/util/concurrent/CopyOnWriteArrayList;
    //   608: invokevirtual 515	java/util/concurrent/CopyOnWriteArrayList:size	()I
    //   611: invokevirtual 518	java/lang/StringBuilder:append	(I)Ljava/lang/StringBuilder;
    //   614: sipush 347
    //   617: iconst_0
    //   618: iconst_3
    //   619: invokestatic 454	o/GA:ˏ	(ICI)Ljava/lang/String;
    //   622: invokevirtual 458	java/lang/String:intern	()Ljava/lang/String;
    //   625: invokevirtual 501	java/lang/StringBuilder:append	(Ljava/lang/String;)Ljava/lang/StringBuilder;
    //   628: invokevirtual 506	java/lang/StringBuilder:toString	()Ljava/lang/String;
    //   631: astore_1
    //   632: goto +17 -> 649
    //   635: astore_3
    //   636: aload_3
    //   637: invokevirtual 469	java/lang/Throwable:getCause	()Ljava/lang/Throwable;
    //   640: astore_1
    //   641: aload_1
    //   642: ifnull +5 -> 647
    //   645: aload_1
    //   646: athrow
    //   647: aload_3
    //   648: athrow
    //   649: iconst_4
    //   650: bipush 42
    //   652: ldc_w 470
    //   655: invokestatic 475	o/O:ˋ	(IIC)Ljava/lang/Object;
    //   658: checkcast 477	java/lang/Class
    //   661: ldc_w 478
    //   664: iconst_2
    //   665: anewarray 477	java/lang/Class
    //   668: dup
    //   669: iconst_0
    //   670: ldc 66
    //   672: aastore
    //   673: dup
    //   674: iconst_1
    //   675: ldc 66
    //   677: aastore
    //   678: invokevirtual 482	java/lang/Class:getMethod	(Ljava/lang/String;[Ljava/lang/Class;)Ljava/lang/reflect/Method;
    //   681: aconst_null
    //   682: iconst_2
    //   683: anewarray 4	java/lang/Object
    //   686: dup
    //   687: iconst_0
    //   688: aload 4
    //   690: aastore
    //   691: dup
    //   692: iconst_1
    //   693: aload_1
    //   694: aastore
    //   695: invokevirtual 488	java/lang/reflect/Method:invoke	(Ljava/lang/Object;[Ljava/lang/Object;)Ljava/lang/Object;
    //   698: pop
    //   699: aload_0
    //   700: getfield 59	o/GA:ˎ	Ljava/util/concurrent/CopyOnWriteArrayList;
    //   703: checkcast 520	java/lang/Iterable
    //   706: astore_3
    //   707: new 522	java/util/ArrayList
    //   710: dup
    //   711: aload_3
    //   712: bipush 10
    //   714: invokestatic 527	o/uQ:ॱ	(Ljava/lang/Iterable;I)I
    //   717: invokespecial 530	java/util/ArrayList:<init>	(I)V
    //   720: checkcast 532	java/util/Collection
    //   723: astore_1
    //   724: aload_3
    //   725: invokeinterface 533 1 0
    //   730: astore_3
    //   731: goto +44 -> 775
    //   734: goto +41 -> 775
    //   737: bipush 14
    //   739: istore_2
    //   740: goto -615 -> 125
    //   743: bipush 59
    //   745: istore_2
    //   746: goto -621 -> 125
    //   749: aload_1
    //   750: checkcast 535	java/util/List
    //   753: astore_1
    //   754: return
    //   755: astore_1
    //   756: aload_1
    //   757: athrow
    //   758: aload_3
    //   759: invokevirtual 445	o/Ik:ʽ	()Landroid/content/Context;
    //   762: aload_1
    //   763: invokestatic 538	o/vq:ˊ	(Ljava/lang/Object;Ljava/lang/Object;)Z
    //   766: ifeq +6 -> 772
    //   769: goto -436 -> 333
    //   772: goto -614 -> 158
    //   775: aload_3
    //   776: invokeinterface 452 1 0
    //   781: ifeq +6 -> 787
    //   784: goto +6 -> 790
    //   787: goto -38 -> 749
    //   790: aload_3
    //   791: invokeinterface 440 1 0
    //   796: checkcast 442	o/Ik
    //   799: astore 6
    //   801: new 496	java/lang/StringBuilder
    //   804: dup
    //   805: invokespecial 497	java/lang/StringBuilder:<init>	()V
    //   808: sipush 350
    //   811: iconst_0
    //   812: bipush 28
    //   814: invokestatic 454	o/GA:ˏ	(ICI)Ljava/lang/String;
    //   817: invokevirtual 458	java/lang/String:intern	()Ljava/lang/String;
    //   820: invokevirtual 501	java/lang/StringBuilder:append	(Ljava/lang/String;)Ljava/lang/StringBuilder;
    //   823: astore 5
    //   825: aload 6
    //   827: sipush 378
    //   830: iconst_0
    //   831: iconst_2
    //   832: invokestatic 454	o/GA:ˏ	(ICI)Ljava/lang/String;
    //   835: invokevirtual 458	java/lang/String:intern	()Ljava/lang/String;
    //   838: invokestatic 494	o/vq:ˋ	(Ljava/lang/Object;Ljava/lang/String;)V
    //   841: aload 5
    //   843: aload 6
    //   845: invokevirtual 503	o/Ik:ˋ	()Ljava/lang/String;
    //   848: invokevirtual 501	java/lang/StringBuilder:append	(Ljava/lang/String;)Ljava/lang/StringBuilder;
    //   851: invokevirtual 506	java/lang/StringBuilder:toString	()Ljava/lang/String;
    //   854: astore 5
    //   856: goto +17 -> 873
    //   859: astore_3
    //   860: aload_3
    //   861: invokevirtual 469	java/lang/Throwable:getCause	()Ljava/lang/Throwable;
    //   864: astore_1
    //   865: aload_1
    //   866: ifnull +5 -> 871
    //   869: aload_1
    //   870: athrow
    //   871: aload_3
    //   872: athrow
    //   873: iconst_4
    //   874: bipush 42
    //   876: ldc_w 470
    //   879: invokestatic 475	o/O:ˋ	(IIC)Ljava/lang/Object;
    //   882: checkcast 477	java/lang/Class
    //   885: ldc_w 478
    //   888: iconst_2
    //   889: anewarray 477	java/lang/Class
    //   892: dup
    //   893: iconst_0
    //   894: ldc 66
    //   896: aastore
    //   897: dup
    //   898: iconst_1
    //   899: ldc 66
    //   901: aastore
    //   902: invokevirtual 482	java/lang/Class:getMethod	(Ljava/lang/String;[Ljava/lang/Class;)Ljava/lang/reflect/Method;
    //   905: aconst_null
    //   906: iconst_2
    //   907: anewarray 4	java/lang/Object
    //   910: dup
    //   911: iconst_0
    //   912: aload 4
    //   914: aastore
    //   915: dup
    //   916: iconst_1
    //   917: aload 5
    //   919: aastore
    //   920: invokevirtual 488	java/lang/reflect/Method:invoke	(Ljava/lang/Object;[Ljava/lang/Object;)Ljava/lang/Object;
    //   923: pop
    //   924: aload_1
    //   925: getstatic 543	o/uJ:ˏ	Lo/uJ;
    //   928: invokeinterface 547 2 0
    //   933: pop
    //   934: goto -628 -> 306
    //   937: iconst_1
    //   938: istore_2
    //   939: goto -885 -> 54
    // Local variable table:
    //   start	length	slot	name	signature
    //   0	942	0	this	GA
    //   0	942	1	paramContext	android.content.Context
    //   33	906	2	i	int
    //   102	103	3	localObject1	Object
    //   208	165	3	localObject2	Object
    //   387	107	3	localObject3	Object
    //   508	66	3	localObject4	Object
    //   635	13	3	localObject5	Object
    //   706	85	3	localObject6	Object
    //   859	13	3	localObject7	Object
    //   172	741	4	str	String
    //   3	915	5	localObject8	Object
    //   112	732	6	localObject9	Object
    // Exception table:
    //   from	to	target	type
    //   95	103	155	java/lang/Exception
    //   108	114	155	java/lang/Exception
    //   161	205	155	java/lang/Exception
    //   209	214	155	java/lang/Exception
    //   218	220	155	java/lang/Exception
    //   220	222	155	java/lang/Exception
    //   272	298	155	java/lang/Exception
    //   749	754	155	java/lang/Exception
    //   222	272	208	finally
    //   401	452	387	finally
    //   522	573	508	finally
    //   649	699	635	finally
    //   103	108	755	java/lang/Exception
    //   873	924	859	finally
  }
  
  /* Error */
  public final void ˎ(Ik<?> paramIk)
  {
    // Byte code:
    //   0: goto +27 -> 27
    //   3: getstatic 31	o/GA:ʽ	I
    //   6: iconst_5
    //   7: iadd
    //   8: istore_2
    //   9: iload_2
    //   10: sipush 128
    //   13: irem
    //   14: putstatic 29	o/GA:ॱॱ	I
    //   17: iload_2
    //   18: iconst_2
    //   19: irem
    //   20: ifeq +6 -> 26
    //   23: goto +158 -> 181
    //   26: return
    //   27: aload_1
    //   28: iconst_0
    //   29: iconst_0
    //   30: bipush 11
    //   32: invokestatic 454	o/GA:ˏ	(ICI)Ljava/lang/String;
    //   35: invokevirtual 458	java/lang/String:intern	()Ljava/lang/String;
    //   38: invokestatic 463	o/vq:ˎ	(Ljava/lang/Object;Ljava/lang/String;)V
    //   41: bipush 11
    //   43: iconst_0
    //   44: bipush 7
    //   46: invokestatic 454	o/GA:ˏ	(ICI)Ljava/lang/String;
    //   49: invokevirtual 458	java/lang/String:intern	()Ljava/lang/String;
    //   52: astore_3
    //   53: new 496	java/lang/StringBuilder
    //   56: dup
    //   57: invokespecial 497	java/lang/StringBuilder:<init>	()V
    //   60: bipush 74
    //   62: iconst_0
    //   63: bipush 45
    //   65: invokestatic 454	o/GA:ˏ	(ICI)Ljava/lang/String;
    //   68: invokevirtual 458	java/lang/String:intern	()Ljava/lang/String;
    //   71: invokevirtual 501	java/lang/StringBuilder:append	(Ljava/lang/String;)Ljava/lang/StringBuilder;
    //   74: aload_1
    //   75: invokevirtual 503	o/Ik:ˋ	()Ljava/lang/String;
    //   78: invokevirtual 501	java/lang/StringBuilder:append	(Ljava/lang/String;)Ljava/lang/StringBuilder;
    //   81: bipush 119
    //   83: ldc_w 549
    //   86: bipush 15
    //   88: invokestatic 454	o/GA:ˏ	(ICI)Ljava/lang/String;
    //   91: invokevirtual 458	java/lang/String:intern	()Ljava/lang/String;
    //   94: invokevirtual 501	java/lang/StringBuilder:append	(Ljava/lang/String;)Ljava/lang/StringBuilder;
    //   97: invokevirtual 506	java/lang/StringBuilder:toString	()Ljava/lang/String;
    //   100: astore 4
    //   102: goto +17 -> 119
    //   105: astore_1
    //   106: aload_1
    //   107: invokevirtual 469	java/lang/Throwable:getCause	()Ljava/lang/Throwable;
    //   110: astore_3
    //   111: aload_3
    //   112: ifnull +5 -> 117
    //   115: aload_3
    //   116: athrow
    //   117: aload_1
    //   118: athrow
    //   119: iconst_4
    //   120: bipush 42
    //   122: ldc_w 470
    //   125: invokestatic 475	o/O:ˋ	(IIC)Ljava/lang/Object;
    //   128: checkcast 477	java/lang/Class
    //   131: ldc_w 478
    //   134: iconst_2
    //   135: anewarray 477	java/lang/Class
    //   138: dup
    //   139: iconst_0
    //   140: ldc 66
    //   142: aastore
    //   143: dup
    //   144: iconst_1
    //   145: ldc 66
    //   147: aastore
    //   148: invokevirtual 482	java/lang/Class:getMethod	(Ljava/lang/String;[Ljava/lang/Class;)Ljava/lang/reflect/Method;
    //   151: aconst_null
    //   152: iconst_2
    //   153: anewarray 4	java/lang/Object
    //   156: dup
    //   157: iconst_0
    //   158: aload_3
    //   159: aastore
    //   160: dup
    //   161: iconst_1
    //   162: aload 4
    //   164: aastore
    //   165: invokevirtual 488	java/lang/reflect/Method:invoke	(Ljava/lang/Object;[Ljava/lang/Object;)Ljava/lang/Object;
    //   168: pop
    //   169: aload_0
    //   170: getfield 59	o/GA:ˎ	Ljava/util/concurrent/CopyOnWriteArrayList;
    //   173: aload_1
    //   174: invokevirtual 552	java/util/concurrent/CopyOnWriteArrayList:remove	(Ljava/lang/Object;)Z
    //   177: pop
    //   178: goto -175 -> 3
    //   181: return
    // Local variable table:
    //   start	length	slot	name	signature
    //   0	182	0	this	GA
    //   0	182	1	paramIk	Ik<?>
    //   8	12	2	i	int
    //   52	107	3	localObject	Object
    //   100	63	4	str	String
    // Exception table:
    //   from	to	target	type
    //   119	169	105	finally
  }
  
  /* Error */
  public final void ˏ(Ik<?> paramIk)
  {
    // Byte code:
    //   0: goto +6 -> 6
    //   3: goto +6 -> 9
    //   6: goto +72 -> 78
    //   9: return
    //   10: bipush 44
    //   12: istore_2
    //   13: goto +30 -> 43
    //   16: getstatic 29	o/GA:ॱॱ	I
    //   19: bipush 93
    //   21: iadd
    //   22: istore_2
    //   23: iload_2
    //   24: sipush 128
    //   27: irem
    //   28: putstatic 31	o/GA:ʽ	I
    //   31: iload_2
    //   32: iconst_2
    //   33: irem
    //   34: ifne +6 -> 40
    //   37: goto -34 -> 3
    //   40: goto -31 -> 9
    //   43: iload_2
    //   44: lookupswitch	default:+28->72, 0:+240->284, 44:+211->255
    //   72: goto +212 -> 284
    //   75: astore_1
    //   76: aload_1
    //   77: athrow
    //   78: getstatic 31	o/GA:ʽ	I
    //   81: bipush 55
    //   83: iadd
    //   84: istore_2
    //   85: iload_2
    //   86: sipush 128
    //   89: irem
    //   90: putstatic 29	o/GA:ॱॱ	I
    //   93: iload_2
    //   94: iconst_2
    //   95: irem
    //   96: ifeq +6 -> 102
    //   99: goto -89 -> 10
    //   102: goto +6 -> 108
    //   105: astore_1
    //   106: aload_1
    //   107: athrow
    //   108: iconst_0
    //   109: istore_2
    //   110: goto -67 -> 43
    //   113: bipush 11
    //   115: iconst_0
    //   116: bipush 7
    //   118: invokestatic 454	o/GA:ˏ	(ICI)Ljava/lang/String;
    //   121: invokevirtual 458	java/lang/String:intern	()Ljava/lang/String;
    //   124: astore_3
    //   125: new 496	java/lang/StringBuilder
    //   128: dup
    //   129: invokespecial 497	java/lang/StringBuilder:<init>	()V
    //   132: bipush 18
    //   134: ldc_w 555
    //   137: bipush 43
    //   139: invokestatic 454	o/GA:ˏ	(ICI)Ljava/lang/String;
    //   142: invokevirtual 458	java/lang/String:intern	()Ljava/lang/String;
    //   145: invokevirtual 501	java/lang/StringBuilder:append	(Ljava/lang/String;)Ljava/lang/StringBuilder;
    //   148: aload_1
    //   149: invokevirtual 503	o/Ik:ˋ	()Ljava/lang/String;
    //   152: invokevirtual 501	java/lang/StringBuilder:append	(Ljava/lang/String;)Ljava/lang/StringBuilder;
    //   155: bipush 61
    //   157: sipush 2447
    //   160: bipush 13
    //   162: invokestatic 454	o/GA:ˏ	(ICI)Ljava/lang/String;
    //   165: invokevirtual 458	java/lang/String:intern	()Ljava/lang/String;
    //   168: invokevirtual 501	java/lang/StringBuilder:append	(Ljava/lang/String;)Ljava/lang/StringBuilder;
    //   171: invokevirtual 506	java/lang/StringBuilder:toString	()Ljava/lang/String;
    //   174: astore 4
    //   176: goto +17 -> 193
    //   179: astore_1
    //   180: aload_1
    //   181: invokevirtual 469	java/lang/Throwable:getCause	()Ljava/lang/Throwable;
    //   184: astore_3
    //   185: aload_3
    //   186: ifnull +5 -> 191
    //   189: aload_3
    //   190: athrow
    //   191: aload_1
    //   192: athrow
    //   193: iconst_4
    //   194: bipush 42
    //   196: ldc_w 470
    //   199: invokestatic 475	o/O:ˋ	(IIC)Ljava/lang/Object;
    //   202: checkcast 477	java/lang/Class
    //   205: ldc_w 478
    //   208: iconst_2
    //   209: anewarray 477	java/lang/Class
    //   212: dup
    //   213: iconst_0
    //   214: ldc 66
    //   216: aastore
    //   217: dup
    //   218: iconst_1
    //   219: ldc 66
    //   221: aastore
    //   222: invokevirtual 482	java/lang/Class:getMethod	(Ljava/lang/String;[Ljava/lang/Class;)Ljava/lang/reflect/Method;
    //   225: aconst_null
    //   226: iconst_2
    //   227: anewarray 4	java/lang/Object
    //   230: dup
    //   231: iconst_0
    //   232: aload_3
    //   233: aastore
    //   234: dup
    //   235: iconst_1
    //   236: aload 4
    //   238: aastore
    //   239: invokevirtual 488	java/lang/reflect/Method:invoke	(Ljava/lang/Object;[Ljava/lang/Object;)Ljava/lang/Object;
    //   242: pop
    //   243: aload_0
    //   244: getfield 59	o/GA:ˎ	Ljava/util/concurrent/CopyOnWriteArrayList;
    //   247: aload_1
    //   248: invokevirtual 556	java/util/concurrent/CopyOnWriteArrayList:add	(Ljava/lang/Object;)Z
    //   251: pop
    //   252: goto -236 -> 16
    //   255: aload_1
    //   256: iconst_0
    //   257: iconst_0
    //   258: bipush 101
    //   260: invokestatic 454	o/GA:ˏ	(ICI)Ljava/lang/String;
    //   263: invokevirtual 458	java/lang/String:intern	()Ljava/lang/String;
    //   266: invokestatic 463	o/vq:ˎ	(Ljava/lang/Object;Ljava/lang/String;)V
    //   269: aload_0
    //   270: getfield 59	o/GA:ˎ	Ljava/util/concurrent/CopyOnWriteArrayList;
    //   273: aload_1
    //   274: invokevirtual 559	java/util/concurrent/CopyOnWriteArrayList:contains	(Ljava/lang/Object;)Z
    //   277: ifne +6 -> 283
    //   280: goto -167 -> 113
    //   283: return
    //   284: aload_1
    //   285: iconst_0
    //   286: iconst_0
    //   287: bipush 11
    //   289: invokestatic 454	o/GA:ˏ	(ICI)Ljava/lang/String;
    //   292: invokevirtual 458	java/lang/String:intern	()Ljava/lang/String;
    //   295: invokestatic 463	o/vq:ˎ	(Ljava/lang/Object;Ljava/lang/String;)V
    //   298: aload_0
    //   299: getfield 59	o/GA:ˎ	Ljava/util/concurrent/CopyOnWriteArrayList;
    //   302: aload_1
    //   303: invokevirtual 559	java/util/concurrent/CopyOnWriteArrayList:contains	(Ljava/lang/Object;)Z
    //   306: ifne +6 -> 312
    //   309: goto -196 -> 113
    //   312: return
    // Local variable table:
    //   start	length	slot	name	signature
    //   0	313	0	this	GA
    //   0	313	1	paramIk	Ik<?>
    //   12	98	2	i	int
    //   124	109	3	localObject	Object
    //   174	63	4	str	String
    // Exception table:
    //   from	to	target	type
    //   16	23	75	java/lang/Exception
    //   23	31	75	java/lang/Exception
    //   23	31	105	java/lang/Exception
    //   193	243	179	finally
  }
  
  static final class If
  {
    private static final GA ˎ = new GA();
    public static final If ॱ = new If();
    
    private If() {}
    
    public final GA ˋ()
    {
      return ˎ;
    }
  }
  
  static final class ˊ
    extends vs
    implements vh<GA>
  {
    public static final ˊ ˋ = new ˊ();
    
    ˊ()
    {
      super();
    }
    
    public final GA ॱ()
    {
      return GA.If.ॱ.ˋ();
    }
  }
  
  public static final class ˋ
  {
    private static long ˋ;
    private static int ˎ;
    private static int ˏ = 0;
    
    static
    {
      ˎ = 1;
      ॱ();
      ˊ = new vF[] { (vF)vu.ˋ(new vr(vu.ˋ(ˋ.class), ˋ(new char[] { 3722, 3811, 3165, 598, -27005, -30150, -4728, -14637, 14207, 19402, -9209, -30418 }).intern(), ˋ(new char[] { 3488, 3527, -25144, -27704, 26768, 29742, 27310, 16840, 13402, -9662, 8708, 3596, 32486, 7206, -1095, -2863, -24267, 9893, -16934, -17110, -5153, 26911, 30528, 31651, 4648, -19538, 18659, 8658, 21685, -1416, 515, -4505, -24865, 15510, -9319, -11035, -16016, 18081, -25299, -25342, 3061, -30427, 22201, 23458, 12806, -11318, 10449, 56, 29842, 6760, -7569, -12736, -16606, 23730, -17451, -19263, -7859, 26473, 32001, 32115, 11228, -22055, 13993, 15259, 21047 }).intern())) };
      int i = ˏ + 39;
      ˎ = i % 128;
      if (i % 2 == 0) {}
    }
    
    private ˋ() {}
    
    /* Error */
    private static String ˋ(char[] paramArrayOfChar)
    {
      // Byte code:
      //   0: goto +39 -> 39
      //   3: bipush 57
      //   5: istore_2
      //   6: goto +185 -> 191
      //   9: getstatic 19	o/GA$ˋ:ˎ	I
      //   12: bipush 117
      //   14: iadd
      //   15: istore_2
      //   16: iload_2
      //   17: sipush 128
      //   20: irem
      //   21: putstatic 17	o/GA$ˋ:ˏ	I
      //   24: iload_2
      //   25: iconst_2
      //   26: irem
      //   27: ifeq +6 -> 33
      //   30: goto +158 -> 188
      //   33: goto +190 -> 223
      //   36: astore_0
      //   37: aload_0
      //   38: athrow
      //   39: goto +58 -> 97
      //   42: iload_1
      //   43: aload_0
      //   44: arraylength
      //   45: if_icmpge +6 -> 51
      //   48: goto -45 -> 3
      //   51: goto +35 -> 86
      //   54: iconst_0
      //   55: istore_1
      //   56: iload_1
      //   57: tableswitch	default:+23->80, 0:+35->92, 1:+80->137
      //   80: goto +57 -> 137
      //   83: astore_0
      //   84: aload_0
      //   85: athrow
      //   86: bipush 87
      //   88: istore_2
      //   89: goto +102 -> 191
      //   92: iload_2
      //   93: istore_1
      //   94: goto -52 -> 42
      //   97: getstatic 19	o/GA$ˋ:ˎ	I
      //   100: bipush 53
      //   102: iadd
      //   103: istore_1
      //   104: iload_1
      //   105: sipush 128
      //   108: irem
      //   109: putstatic 17	o/GA$ˋ:ˏ	I
      //   112: iload_1
      //   113: iconst_2
      //   114: irem
      //   115: ifeq +6 -> 121
      //   118: goto +16 -> 134
      //   121: getstatic 135	o/GA$ˋ:ˋ	J
      //   124: aload_0
      //   125: invokestatic 140	o/oL:ˋ	(J[C)[C
      //   128: astore_0
      //   129: iconst_4
      //   130: istore_1
      //   131: goto -89 -> 42
      //   134: goto -13 -> 121
      //   137: iload_2
      //   138: istore_1
      //   139: goto -97 -> 42
      //   142: getstatic 19	o/GA$ˋ:ˎ	I
      //   145: bipush 101
      //   147: iadd
      //   148: istore_1
      //   149: iload_1
      //   150: sipush 128
      //   153: irem
      //   154: putstatic 17	o/GA$ˋ:ˏ	I
      //   157: iload_1
      //   158: iconst_2
      //   159: irem
      //   160: ifeq +6 -> 166
      //   163: goto +20 -> 183
      //   166: goto -112 -> 54
      //   169: new 48	java/lang/String
      //   172: dup
      //   173: aload_0
      //   174: iconst_4
      //   175: aload_0
      //   176: arraylength
      //   177: iconst_4
      //   178: isub
      //   179: invokespecial 143	java/lang/String:<init>	([CII)V
      //   182: areturn
      //   183: iconst_1
      //   184: istore_1
      //   185: goto -129 -> 56
      //   188: goto +35 -> 223
      //   191: iload_2
      //   192: lookupswitch	default:+28->220, 57:+-183->9, 87:+-23->169
      //   220: goto -211 -> 9
      //   223: aload_0
      //   224: iload_1
      //   225: caload
      //   226: aload_0
      //   227: iload_1
      //   228: iconst_4
      //   229: irem
      //   230: caload
      //   231: ixor
      //   232: i2l
      //   233: lstore_3
      //   234: iload_1
      //   235: iconst_4
      //   236: isub
      //   237: i2l
      //   238: lstore 5
      //   240: getstatic 135	o/GA$ˋ:ˋ	J
      //   243: lstore 7
      //   245: aload_0
      //   246: iload_1
      //   247: lload_3
      //   248: lload 5
      //   250: lload 7
      //   252: lmul
      //   253: lxor
      //   254: l2i
      //   255: i2c
      //   256: castore
      //   257: iload_1
      //   258: iconst_1
      //   259: iadd
      //   260: istore_2
      //   261: goto -119 -> 142
      // Local variable table:
      //   start	length	slot	name	signature
      //   0	264	0	paramArrayOfChar	char[]
      //   42	218	1	i	int
      //   5	256	2	j	int
      //   233	15	3	l1	long
      //   238	11	5	l2	long
      //   243	8	7	l3	long
      // Exception table:
      //   from	to	target	type
      //   142	149	36	java/lang/Exception
      //   149	157	36	java/lang/Exception
      //   240	245	36	java/lang/Exception
      //   149	157	83	java/lang/Exception
    }
    
    static void ॱ()
    {
      ˋ = 3512019267992489573L;
    }
    
    public final GA ˏ()
    {
      int i = ˏ + 117;
      ˎ = i % 128;
      if (i % 2 != 0) {
        break label50;
      }
      for (;;)
      {
        localUA = GA.ॱ();
        localVF = ˊ[0];
        return (GA)localUA.ˋ();
        label50:
        i = 1;
        break label57;
        i = 0;
        label57:
        switch (i)
        {
        }
      }
      uA localUA = GA.ॱ();
      vF localVF = ˊ[1];
      return (GA)localUA.ˋ();
    }
  }
}
