package o;

import java.math.BigDecimal;

public final class Gd
{
  private static long ˊ = 0L;
  private static char ˋ;
  private static int ˎ;
  private static int ˏ = 571447006;
  private static int ॱ = 0;
  private String accumulatedPoints;
  private BigDecimal availableAmount;
  private String blockedAccountAmount;
  private String blockedCardAmount;
  private BigDecimal points;
  private String utilizedAmount;
  
  static
  {
    ˎ = 1;
    ˋ = '\000';
  }
  
  /* Error */
  private static String ˋ(char[] paramArrayOfChar1, char paramChar, char[] paramArrayOfChar2, int paramInt, char[] paramArrayOfChar3)
  {
    // Byte code:
    //   0: goto +312 -> 312
    //   3: iload_1
    //   4: iload 5
    //   6: if_icmpge +6 -> 12
    //   9: goto +204 -> 213
    //   12: iconst_1
    //   13: istore_3
    //   14: goto +301 -> 315
    //   17: getstatic 24	o/Gd:ॱ	I
    //   20: bipush 35
    //   22: iadd
    //   23: istore_3
    //   24: iload_3
    //   25: sipush 128
    //   28: irem
    //   29: putstatic 26	o/Gd:ˎ	I
    //   32: iload_3
    //   33: iconst_2
    //   34: irem
    //   35: ifne +6 -> 41
    //   38: goto +234 -> 272
    //   41: goto +78 -> 119
    //   44: getstatic 26	o/Gd:ˎ	I
    //   47: bipush 67
    //   49: iadd
    //   50: istore 5
    //   52: iload 5
    //   54: sipush 128
    //   57: irem
    //   58: putstatic 24	o/Gd:ॱ	I
    //   61: iload 5
    //   63: iconst_2
    //   64: irem
    //   65: ifeq +6 -> 71
    //   68: goto +11 -> 79
    //   71: goto +147 -> 218
    //   74: iload_3
    //   75: istore_1
    //   76: goto -73 -> 3
    //   79: goto +139 -> 218
    //   82: getstatic 26	o/Gd:ˎ	I
    //   85: iconst_3
    //   86: iadd
    //   87: istore_1
    //   88: iload_1
    //   89: sipush 128
    //   92: irem
    //   93: putstatic 24	o/Gd:ॱ	I
    //   96: iload_1
    //   97: iconst_2
    //   98: irem
    //   99: ifeq +6 -> 105
    //   102: goto +9 -> 111
    //   105: goto +172 -> 277
    //   108: astore_0
    //   109: aload_0
    //   110: athrow
    //   111: iconst_0
    //   112: istore_1
    //   113: goto +11 -> 124
    //   116: astore_0
    //   117: aload_0
    //   118: athrow
    //   119: iconst_0
    //   120: istore_3
    //   121: goto +161 -> 282
    //   124: iload_1
    //   125: tableswitch	default:+23->148, 0:+-51->74, 1:+182->307
    //   148: goto +159 -> 307
    //   151: aload_0
    //   152: aload 4
    //   154: iload_1
    //   155: invokestatic 42	o/oJ:ˏ	([C[CI)V
    //   158: aload_2
    //   159: iload_1
    //   160: caload
    //   161: aload_0
    //   162: iload_1
    //   163: iconst_3
    //   164: iadd
    //   165: iconst_4
    //   166: irem
    //   167: caload
    //   168: ixor
    //   169: i2l
    //   170: lstore 6
    //   172: getstatic 30	o/Gd:ˊ	J
    //   175: lstore 8
    //   177: getstatic 33	o/Gd:ˏ	I
    //   180: istore_3
    //   181: iload_3
    //   182: i2l
    //   183: lstore 10
    //   185: getstatic 28	o/Gd:ˋ	C
    //   188: istore_3
    //   189: aload 12
    //   191: iload_1
    //   192: lload 6
    //   194: lload 8
    //   196: lxor
    //   197: lload 10
    //   199: lxor
    //   200: iload_3
    //   201: i2l
    //   202: lxor
    //   203: l2i
    //   204: i2c
    //   205: castore
    //   206: iload_1
    //   207: iconst_1
    //   208: iadd
    //   209: istore_1
    //   210: goto -207 -> 3
    //   213: iconst_0
    //   214: istore_3
    //   215: goto +100 -> 315
    //   218: aload_0
    //   219: invokevirtual 48	[C:clone	()Ljava/lang/Object;
    //   222: checkcast 44	[C
    //   225: astore_0
    //   226: aload 4
    //   228: invokevirtual 48	[C:clone	()Ljava/lang/Object;
    //   231: checkcast 44	[C
    //   234: astore 4
    //   236: aload_0
    //   237: iconst_0
    //   238: aload_0
    //   239: iconst_0
    //   240: caload
    //   241: iload_1
    //   242: ixor
    //   243: i2c
    //   244: castore
    //   245: aload 4
    //   247: iconst_2
    //   248: aload 4
    //   250: iconst_2
    //   251: caload
    //   252: iload_3
    //   253: i2c
    //   254: iadd
    //   255: i2c
    //   256: castore
    //   257: aload_2
    //   258: arraylength
    //   259: istore 5
    //   261: iload 5
    //   263: newarray char
    //   265: astore 12
    //   267: iconst_0
    //   268: istore_3
    //   269: goto -187 -> 82
    //   272: iconst_1
    //   273: istore_3
    //   274: goto +8 -> 282
    //   277: iconst_1
    //   278: istore_1
    //   279: goto -155 -> 124
    //   282: iload_3
    //   283: tableswitch	default:+21->304, 0:+-132->151, 1:+70->353
    //   304: goto +49 -> 353
    //   307: iload_3
    //   308: istore_1
    //   309: goto -306 -> 3
    //   312: goto -268 -> 44
    //   315: iload_3
    //   316: tableswitch	default:+24->340, 0:+-299->17, 1:+27->343
    //   340: goto -323 -> 17
    //   343: new 50	java/lang/String
    //   346: dup
    //   347: aload 12
    //   349: invokespecial 54	java/lang/String:<init>	([C)V
    //   352: areturn
    //   353: aload_0
    //   354: aload 4
    //   356: iload_1
    //   357: invokestatic 42	o/oJ:ˏ	([C[CI)V
    //   360: aload 12
    //   362: iload_1
    //   363: aload_2
    //   364: iload_1
    //   365: caload
    //   366: aload_0
    //   367: iload_1
    //   368: iconst_3
    //   369: iushr
    //   370: iconst_4
    //   371: iadd
    //   372: caload
    //   373: iand
    //   374: i2l
    //   375: getstatic 30	o/Gd:ˊ	J
    //   378: ladd
    //   379: getstatic 33	o/Gd:ˏ	I
    //   382: i2l
    //   383: ladd
    //   384: getstatic 28	o/Gd:ˋ	C
    //   387: i2l
    //   388: lmul
    //   389: l2i
    //   390: i2c
    //   391: castore
    //   392: iload_1
    //   393: bipush 58
    //   395: iadd
    //   396: istore_1
    //   397: goto -394 -> 3
    // Local variable table:
    //   start	length	slot	name	signature
    //   0	400	0	paramArrayOfChar1	char[]
    //   0	400	1	paramChar	char
    //   0	400	2	paramArrayOfChar2	char[]
    //   0	400	3	paramInt	int
    //   0	400	4	paramArrayOfChar3	char[]
    //   4	258	5	c	char
    //   170	23	6	l1	long
    //   175	20	8	l2	long
    //   183	15	10	l3	long
    //   189	172	12	arrayOfChar	char[]
    // Exception table:
    //   from	to	target	type
    //   17	32	108	java/lang/Exception
    //   151	158	108	java/lang/Exception
    //   172	177	116	java/lang/Exception
    //   177	181	116	java/lang/Exception
    //   185	189	116	java/lang/Exception
  }
  
  /* Error */
  public boolean equals(Object paramObject)
  {
    // Byte code:
    //   0: goto +107 -> 107
    //   3: getstatic 26	o/Gd:ˎ	I
    //   6: bipush 21
    //   8: iadd
    //   9: istore_2
    //   10: iload_2
    //   11: sipush 128
    //   14: irem
    //   15: putstatic 24	o/Gd:ॱ	I
    //   18: iload_2
    //   19: iconst_2
    //   20: irem
    //   21: ifeq +6 -> 27
    //   24: goto +213 -> 237
    //   27: aload_0
    //   28: getfield 58	o/Gd:accumulatedPoints	Ljava/lang/String;
    //   31: aload_1
    //   32: getfield 58	o/Gd:accumulatedPoints	Ljava/lang/String;
    //   35: invokestatic 63	o/vq:ˊ	(Ljava/lang/Object;Ljava/lang/Object;)Z
    //   38: ifeq +6 -> 44
    //   41: goto +122 -> 163
    //   44: goto +89 -> 133
    //   47: iload_2
    //   48: tableswitch	default:+24->72, 0:+169->217, 1:+120->168
    //   72: goto +145 -> 217
    //   75: iload_2
    //   76: lookupswitch	default:+28->104, 27:+92->168, 51:+301->377
    //   104: goto +64 -> 168
    //   107: goto +243 -> 350
    //   110: aload_0
    //   111: getfield 65	o/Gd:points	Ljava/math/BigDecimal;
    //   114: aload_1
    //   115: getfield 65	o/Gd:points	Ljava/math/BigDecimal;
    //   118: invokestatic 63	o/vq:ˊ	(Ljava/lang/Object;Ljava/lang/Object;)Z
    //   121: ifeq +6 -> 127
    //   124: goto -121 -> 3
    //   127: goto +41 -> 168
    //   130: astore_1
    //   131: aload_1
    //   132: athrow
    //   133: iconst_1
    //   134: istore_2
    //   135: goto -88 -> 47
    //   138: iload_2
    //   139: tableswitch	default:+21->160, 0:+32->171, 1:+159->298
    //   160: goto +138 -> 298
    //   163: iconst_0
    //   164: istore_2
    //   165: goto -118 -> 47
    //   168: goto +99 -> 267
    //   171: aload_1
    //   172: checkcast 2	o/Gd
    //   175: astore_1
    //   176: aload_0
    //   177: getfield 67	o/Gd:availableAmount	Ljava/math/BigDecimal;
    //   180: astore 4
    //   182: aload_1
    //   183: getfield 67	o/Gd:availableAmount	Ljava/math/BigDecimal;
    //   186: astore 5
    //   188: aload 4
    //   190: aload 5
    //   192: invokestatic 63	o/vq:ˊ	(Ljava/lang/Object;Ljava/lang/Object;)Z
    //   195: istore_3
    //   196: iload_3
    //   197: ifeq +6 -> 203
    //   200: goto +130 -> 330
    //   203: goto -35 -> 168
    //   206: bipush 51
    //   208: istore_2
    //   209: goto -134 -> 75
    //   212: iconst_1
    //   213: istore_2
    //   214: goto -76 -> 138
    //   217: aload_0
    //   218: getfield 69	o/Gd:blockedAccountAmount	Ljava/lang/String;
    //   221: aload_1
    //   222: getfield 69	o/Gd:blockedAccountAmount	Ljava/lang/String;
    //   225: invokestatic 63	o/vq:ˊ	(Ljava/lang/Object;Ljava/lang/Object;)Z
    //   228: ifeq +6 -> 234
    //   231: goto -25 -> 206
    //   234: goto +53 -> 287
    //   237: goto -210 -> 27
    //   240: getstatic 24	o/Gd:ॱ	I
    //   243: bipush 55
    //   245: iadd
    //   246: istore_2
    //   247: iload_2
    //   248: sipush 128
    //   251: irem
    //   252: putstatic 26	o/Gd:ˎ	I
    //   255: iload_2
    //   256: iconst_2
    //   257: irem
    //   258: ifne +6 -> 264
    //   261: goto -49 -> 212
    //   264: goto +18 -> 282
    //   267: iconst_0
    //   268: ireturn
    //   269: aload_1
    //   270: instanceof 2
    //   273: ifeq +6 -> 279
    //   276: goto -36 -> 240
    //   279: goto -111 -> 168
    //   282: iconst_0
    //   283: istore_2
    //   284: goto -146 -> 138
    //   287: bipush 27
    //   289: istore_2
    //   290: goto -215 -> 75
    //   293: astore_1
    //   294: aload_1
    //   295: athrow
    //   296: iconst_1
    //   297: ireturn
    //   298: aload_1
    //   299: checkcast 2	o/Gd
    //   302: astore_1
    //   303: aload_0
    //   304: getfield 67	o/Gd:availableAmount	Ljava/math/BigDecimal;
    //   307: aload_1
    //   308: getfield 67	o/Gd:availableAmount	Ljava/math/BigDecimal;
    //   311: invokestatic 63	o/vq:ˊ	(Ljava/lang/Object;Ljava/lang/Object;)Z
    //   314: istore_3
    //   315: bipush 95
    //   317: iconst_0
    //   318: idiv
    //   319: istore_2
    //   320: iload_3
    //   321: ifeq +6 -> 327
    //   324: goto +6 -> 330
    //   327: goto -159 -> 168
    //   330: aload_0
    //   331: getfield 71	o/Gd:utilizedAmount	Ljava/lang/String;
    //   334: aload_1
    //   335: getfield 71	o/Gd:utilizedAmount	Ljava/lang/String;
    //   338: invokestatic 63	o/vq:ˊ	(Ljava/lang/Object;Ljava/lang/Object;)Z
    //   341: ifeq +6 -> 347
    //   344: goto -234 -> 110
    //   347: goto -179 -> 168
    //   350: getstatic 24	o/Gd:ॱ	I
    //   353: bipush 19
    //   355: iadd
    //   356: istore_2
    //   357: iload_2
    //   358: sipush 128
    //   361: irem
    //   362: putstatic 26	o/Gd:ˎ	I
    //   365: iload_2
    //   366: iconst_2
    //   367: irem
    //   368: ifne +6 -> 374
    //   371: goto +26 -> 397
    //   374: goto +23 -> 397
    //   377: aload_0
    //   378: getfield 73	o/Gd:blockedCardAmount	Ljava/lang/String;
    //   381: aload_1
    //   382: getfield 73	o/Gd:blockedCardAmount	Ljava/lang/String;
    //   385: invokestatic 63	o/vq:ˊ	(Ljava/lang/Object;Ljava/lang/Object;)Z
    //   388: ifeq +6 -> 394
    //   391: goto -95 -> 296
    //   394: goto -226 -> 168
    //   397: aload_0
    //   398: aload_1
    //   399: if_acmpeq +6 -> 405
    //   402: goto -133 -> 269
    //   405: goto -109 -> 296
    // Local variable table:
    //   start	length	slot	name	signature
    //   0	408	0	this	Gd
    //   0	408	1	paramObject	Object
    //   9	359	2	i	int
    //   195	126	3	bool	boolean
    //   180	9	4	localBigDecimal1	BigDecimal
    //   186	5	5	localBigDecimal2	BigDecimal
    // Exception table:
    //   from	to	target	type
    //   171	176	130	java/lang/Exception
    //   176	182	130	java/lang/Exception
    //   182	188	130	java/lang/Exception
    //   188	196	130	java/lang/Exception
    //   176	182	293	java/lang/Exception
    //   298	303	293	java/lang/Exception
  }
  
  /* Error */
  public int hashCode()
  {
    // Byte code:
    //   0: goto +383 -> 383
    //   3: iload_2
    //   4: tableswitch	default:+24->28, 0:+442->446, 1:+35->39
    //   28: goto +418 -> 446
    //   31: goto +403 -> 434
    //   34: iconst_0
    //   35: istore_2
    //   36: goto +442 -> 478
    //   39: iconst_0
    //   40: istore 5
    //   42: goto +324 -> 366
    //   45: aload 7
    //   47: invokevirtual 77	java/lang/Object:hashCode	()I
    //   50: istore_2
    //   51: goto +151 -> 202
    //   54: aload 7
    //   56: invokevirtual 77	java/lang/Object:hashCode	()I
    //   59: istore 6
    //   61: goto +330 -> 391
    //   64: iconst_1
    //   65: istore_2
    //   66: goto +412 -> 478
    //   69: astore 7
    //   71: aload 7
    //   73: athrow
    //   74: bipush 46
    //   76: istore 6
    //   78: goto +141 -> 219
    //   81: iconst_0
    //   82: istore 4
    //   84: goto +64 -> 148
    //   87: iconst_0
    //   88: istore 6
    //   90: goto +75 -> 165
    //   93: aload_0
    //   94: getfield 58	o/Gd:accumulatedPoints	Ljava/lang/String;
    //   97: astore 7
    //   99: aload 7
    //   101: ifnull +6 -> 107
    //   104: goto +369 -> 473
    //   107: goto +279 -> 386
    //   110: astore 7
    //   112: aload 7
    //   114: athrow
    //   115: getstatic 24	o/Gd:ॱ	I
    //   118: iconst_1
    //   119: iadd
    //   120: istore_2
    //   121: iload_2
    //   122: sipush 128
    //   125: irem
    //   126: putstatic 26	o/Gd:ˎ	I
    //   129: iload_2
    //   130: iconst_2
    //   131: irem
    //   132: ifne +6 -> 138
    //   135: goto +159 -> 294
    //   138: goto -93 -> 45
    //   141: bipush 8
    //   143: istore 6
    //   145: goto +74 -> 219
    //   148: aload_0
    //   149: getfield 65	o/Gd:points	Ljava/math/BigDecimal;
    //   152: astore 7
    //   154: aload 7
    //   156: ifnull +6 -> 162
    //   159: goto +153 -> 312
    //   162: goto +232 -> 394
    //   165: goto +96 -> 261
    //   168: aload 7
    //   170: invokevirtual 77	java/lang/Object:hashCode	()I
    //   173: istore_1
    //   174: aconst_null
    //   175: arraylength
    //   176: istore_2
    //   177: goto -84 -> 93
    //   180: iconst_0
    //   181: istore_2
    //   182: goto +109 -> 291
    //   185: aload_0
    //   186: getfield 71	o/Gd:utilizedAmount	Ljava/lang/String;
    //   189: astore 7
    //   191: aload 7
    //   193: ifnull +6 -> 199
    //   196: goto +160 -> 356
    //   199: goto -118 -> 81
    //   202: aload_0
    //   203: getfield 73	o/Gd:blockedCardAmount	Ljava/lang/String;
    //   206: astore 7
    //   208: aload 7
    //   210: ifnull +6 -> 216
    //   213: goto -139 -> 74
    //   216: goto -75 -> 141
    //   219: iload 6
    //   221: lookupswitch	default:+27->248, 8:+-134->87, 46:+-167->54
    //   248: goto -161 -> 87
    //   251: aload 7
    //   253: invokevirtual 77	java/lang/Object:hashCode	()I
    //   256: istore 5
    //   258: goto +108 -> 366
    //   261: iload_3
    //   262: bipush 31
    //   264: imul
    //   265: iload 4
    //   267: iadd
    //   268: bipush 31
    //   270: imul
    //   271: iload_1
    //   272: iadd
    //   273: bipush 31
    //   275: imul
    //   276: iload 5
    //   278: iadd
    //   279: bipush 31
    //   281: imul
    //   282: iload_2
    //   283: iadd
    //   284: bipush 31
    //   286: imul
    //   287: iload 6
    //   289: iadd
    //   290: ireturn
    //   291: goto -89 -> 202
    //   294: aload 7
    //   296: invokevirtual 77	java/lang/Object:hashCode	()I
    //   299: istore_2
    //   300: aconst_null
    //   301: arraylength
    //   302: istore 6
    //   304: goto -102 -> 202
    //   307: iconst_0
    //   308: istore_3
    //   309: goto -124 -> 185
    //   312: getstatic 26	o/Gd:ˎ	I
    //   315: bipush 49
    //   317: iadd
    //   318: istore_1
    //   319: iload_1
    //   320: sipush 128
    //   323: irem
    //   324: putstatic 24	o/Gd:ॱ	I
    //   327: iload_1
    //   328: iconst_2
    //   329: irem
    //   330: ifeq +6 -> 336
    //   333: goto -165 -> 168
    //   336: goto +63 -> 399
    //   339: aload_0
    //   340: getfield 67	o/Gd:availableAmount	Ljava/math/BigDecimal;
    //   343: astore 7
    //   345: aload 7
    //   347: ifnull +6 -> 353
    //   350: goto +58 -> 408
    //   353: goto -46 -> 307
    //   356: aload 7
    //   358: invokevirtual 77	java/lang/Object:hashCode	()I
    //   361: istore 4
    //   363: goto -215 -> 148
    //   366: aload_0
    //   367: getfield 69	o/Gd:blockedAccountAmount	Ljava/lang/String;
    //   370: astore 7
    //   372: aload 7
    //   374: ifnull +6 -> 380
    //   377: goto -313 -> 64
    //   380: goto -346 -> 34
    //   383: goto -44 -> 339
    //   386: iconst_1
    //   387: istore_2
    //   388: goto -385 -> 3
    //   391: goto -130 -> 261
    //   394: iconst_0
    //   395: istore_1
    //   396: goto -303 -> 93
    //   399: aload 7
    //   401: invokevirtual 77	java/lang/Object:hashCode	()I
    //   404: istore_1
    //   405: goto -312 -> 93
    //   408: getstatic 24	o/Gd:ॱ	I
    //   411: istore_1
    //   412: iload_1
    //   413: bipush 15
    //   415: iadd
    //   416: istore_1
    //   417: iload_1
    //   418: sipush 128
    //   421: irem
    //   422: putstatic 26	o/Gd:ˎ	I
    //   425: iload_1
    //   426: iconst_2
    //   427: irem
    //   428: ifne +6 -> 434
    //   431: goto -400 -> 31
    //   434: aload 7
    //   436: invokevirtual 77	java/lang/Object:hashCode	()I
    //   439: istore_3
    //   440: goto -255 -> 185
    //   443: goto -192 -> 251
    //   446: getstatic 26	o/Gd:ˎ	I
    //   449: bipush 81
    //   451: iadd
    //   452: istore_2
    //   453: iload_2
    //   454: sipush 128
    //   457: irem
    //   458: putstatic 24	o/Gd:ॱ	I
    //   461: iload_2
    //   462: iconst_2
    //   463: irem
    //   464: ifeq +6 -> 470
    //   467: goto -24 -> 443
    //   470: goto -219 -> 251
    //   473: iconst_0
    //   474: istore_2
    //   475: goto -472 -> 3
    //   478: iload_2
    //   479: tableswitch	default:+21->500, 0:+-299->180, 1:+-364->115
    //   500: goto -320 -> 180
    // Local variable table:
    //   start	length	slot	name	signature
    //   0	503	0	this	Gd
    //   173	255	1	i	int
    //   3	476	2	j	int
    //   261	179	3	k	int
    //   82	280	4	m	int
    //   40	239	5	n	int
    //   59	244	6	i1	int
    //   45	10	7	localObject1	Object
    //   69	3	7	localException1	Exception
    //   97	3	7	str	String
    //   110	3	7	localException2	Exception
    //   152	283	7	localObject2	Object
    // Exception table:
    //   from	to	target	type
    //   399	405	69	java/lang/Exception
    //   417	425	69	java/lang/Exception
    //   185	191	110	java/lang/Exception
    //   408	412	110	java/lang/Exception
    //   434	440	110	java/lang/Exception
  }
  
  public String toString()
  {
    break label1239;
    int i = ॱ + 15;
    ˎ = i % 128;
    String str;
    if (i % 2 != 0) {
      return str;
    }
    label1239:
    for (;;)
    {
      str = ˋ(new char[] { 8346, -334, -11833, -9883 }, '\000', new char[] { 9391, -17837, -27000, -25376, 12172, -15169, -32586, -24087, -17238, -29657, -7297, 28769, 24680, -9942, 28904, -27010, 1040, 25129, -5866, -29156, 11790, -28785, 15984, -24618, 14802, -20814, 10998, -602, 14491, 31109, -3782, 9247, 28436, 18284, 31805, -14 }, 0, new char[] { 0, 0, 0, 0 }).intern() + this.availableAmount + ˋ(new char[] { -23869, 10659, -15403, -3191 }, 35267, new char[] { -14872, 31351, 8457, -27240, -19538, 12596, 16733, 14836, 2997, -15322, -1257, -25653, -14083, -18900, 6199, 27715, -21893 }, -718691422, new char[] { 0, 0, 0, 0 }).intern() + this.utilizedAmount + ˋ(new char[] { -5516, -8847, 20749, -16333 }, '\000', new char[] { -30019, -26482, -8620, -7181, -13445, 26380, -13199, -26681, -5534 }, 232616426, new char[] { 0, 0, 0, 0 }).intern() + this.points + ˋ(new char[] { 20828, -14286, 868, 26688 }, '\000', new char[] { -11692, -5945, 5752, -29839, -28882, 11546, -5441, 22771, -11600, -31003, -7902, -32315, -21728, -27745, -5130, -15122, 1631, -3132, 236, 11995 }, 0, new char[] { 0, 0, 0, 0 }).intern() + this.accumulatedPoints + ˋ(new char[] { -9623, 13429, 7721, 7039 }, '\000', new char[] { 11408, -18, -29013, -31061, 10448, -24021, 302, 10907, 19015, 6378, 12113, -31193, -15231, -4699, -30747, -4400, -21918, -9818, 26481, 11012, -6346, -14071, 28444 }, 691303898, new char[] { 0, 0, 0, 0 }).intern() + this.blockedAccountAmount + ˋ(new char[] { -28058, -12206, 8542, 4668 }, '\000', new char[] { 10200, 22504, 17374, -20238, 11376, -31893, 27723, 22697, 19593, 17011, -23301, 23275, -21495, 8736, -801, -22079, 25665, 8167, -32606, -21936 }, 0, new char[] { 0, 0, 0, 0 }).intern() + this.blockedCardAmount + ˋ(new char[] { -2225, -23232, -20365, 6607 }, 53168, new char[] { 11626 }, 1940209911, new char[] { 0, 0, 0, 0 }).intern();
      break;
      return str;
    }
  }
  
  public final BigDecimal ˎ()
  {
    break label43;
    break label99;
    int i = 0;
    break label46;
    BigDecimal localBigDecimal;
    label43:
    for (;;)
    {
      i = ॱ + 49;
      ˎ = i % 128;
      if (i % 2 == 0) {
        break;
      }
      break;
      i = null.length;
      return localBigDecimal;
    }
    for (;;)
    {
      switch (i)
      {
      case 1: 
      default: 
        label46:
        return localBigDecimal;
      }
      for (;;)
      {
        i = ॱ + 23;
        ˎ = i % 128;
        if (i % 2 != 0)
        {
          break;
          return localBigDecimal;
          try
          {
            label99:
            localBigDecimal = this.points;
          }
          catch (Exception localException)
          {
            throw localException;
          }
        }
      }
      i = 1;
    }
  }
  
  public final BigDecimal ॱ()
  {
    BigDecimal localBigDecimal;
    for (;;)
    {
      int i = ॱ + 121;
      ˎ = i % 128;
      if (i % 2 == 0) {
        break;
      }
      return localBigDecimal;
      for (;;)
      {
        i = ॱ + 45;
        ˎ = i % 128;
        if (i % 2 == 0) {
          break;
        }
        break;
      }
      localBigDecimal = this.availableAmount;
    }
    return localBigDecimal;
  }
}
