package o;

public final class GE
{
  private static int ˊ = 0;
  private static int ˋ = 1;
  private static char ˎ = 62964;
  private static long ˏ = 0L;
  private static int ॱ = 0;
  
  /* Error */
  private static String ˊ(char[] paramArrayOfChar1, char paramChar, char[] paramArrayOfChar2, int paramInt, char[] paramArrayOfChar3)
  {
    // Byte code:
    //   0: goto +179 -> 179
    //   3: new 31	java/lang/String
    //   6: dup
    //   7: aload 6
    //   9: invokespecial 35	java/lang/String:<init>	([C)V
    //   12: areturn
    //   13: getstatic 16	o/GE:ˊ	I
    //   16: bipush 119
    //   18: iadd
    //   19: istore 5
    //   21: iload 5
    //   23: sipush 128
    //   26: irem
    //   27: putstatic 18	o/GE:ˋ	I
    //   30: iload 5
    //   32: iconst_2
    //   33: irem
    //   34: ifne +6 -> 40
    //   37: goto +139 -> 176
    //   40: goto +70 -> 110
    //   43: bipush 29
    //   45: istore_3
    //   46: goto +139 -> 185
    //   49: iload_1
    //   50: iload 5
    //   52: if_icmpge +6 -> 58
    //   55: goto +127 -> 182
    //   58: goto -15 -> 43
    //   61: aload_0
    //   62: aload 4
    //   64: iload_1
    //   65: invokestatic 40	o/oJ:ˏ	([C[CI)V
    //   68: aload 6
    //   70: iload_1
    //   71: aload_2
    //   72: iload_1
    //   73: caload
    //   74: aload_0
    //   75: iload_1
    //   76: iconst_3
    //   77: iadd
    //   78: iconst_4
    //   79: irem
    //   80: caload
    //   81: ixor
    //   82: i2l
    //   83: getstatic 23	o/GE:ˏ	J
    //   86: lxor
    //   87: getstatic 25	o/GE:ॱ	I
    //   90: i2l
    //   91: lxor
    //   92: getstatic 21	o/GE:ˎ	C
    //   95: i2l
    //   96: lxor
    //   97: l2i
    //   98: i2c
    //   99: castore
    //   100: iload_1
    //   101: iconst_1
    //   102: iadd
    //   103: istore_1
    //   104: goto -55 -> 49
    //   107: astore_0
    //   108: aload_0
    //   109: athrow
    //   110: aload_0
    //   111: invokevirtual 46	[C:clone	()Ljava/lang/Object;
    //   114: astore_0
    //   115: aload_0
    //   116: checkcast 42	[C
    //   119: astore_0
    //   120: aload 4
    //   122: invokevirtual 46	[C:clone	()Ljava/lang/Object;
    //   125: astore 4
    //   127: aload 4
    //   129: checkcast 42	[C
    //   132: astore 4
    //   134: aload_0
    //   135: iconst_0
    //   136: aload_0
    //   137: iconst_0
    //   138: caload
    //   139: iload_1
    //   140: ixor
    //   141: i2c
    //   142: castore
    //   143: aload 4
    //   145: iconst_2
    //   146: aload 4
    //   148: iconst_2
    //   149: caload
    //   150: iload_3
    //   151: i2c
    //   152: iadd
    //   153: i2c
    //   154: castore
    //   155: aload_2
    //   156: arraylength
    //   157: istore 5
    //   159: iload 5
    //   161: newarray char
    //   163: astore 6
    //   165: iconst_0
    //   166: istore_1
    //   167: goto -118 -> 49
    //   170: astore_0
    //   171: aload_0
    //   172: athrow
    //   173: goto -112 -> 61
    //   176: goto -66 -> 110
    //   179: goto -166 -> 13
    //   182: bipush 49
    //   184: istore_3
    //   185: iload_3
    //   186: lookupswitch	default:+26->212, 29:+-183->3, 49:+29->215
    //   212: goto -209 -> 3
    //   215: getstatic 18	o/GE:ˋ	I
    //   218: bipush 85
    //   220: iadd
    //   221: istore_3
    //   222: iload_3
    //   223: sipush 128
    //   226: irem
    //   227: putstatic 16	o/GE:ˊ	I
    //   230: iload_3
    //   231: iconst_2
    //   232: irem
    //   233: ifeq +6 -> 239
    //   236: goto -63 -> 173
    //   239: goto -178 -> 61
    // Local variable table:
    //   start	length	slot	name	signature
    //   0	242	0	paramArrayOfChar1	char[]
    //   0	242	1	paramChar	char
    //   0	242	2	paramArrayOfChar2	char[]
    //   0	242	3	paramInt	int
    //   0	242	4	paramArrayOfChar3	char[]
    //   19	141	5	c	char
    //   7	157	6	arrayOfChar	char[]
    // Exception table:
    //   from	to	target	type
    //   115	120	107	java/lang/Exception
    //   110	115	170	java/lang/Exception
    //   115	120	170	java/lang/Exception
    //   120	127	170	java/lang/Exception
    //   127	134	170	java/lang/Exception
    //   155	165	170	java/lang/Exception
  }
  
  /* Error */
  private static final void ˎ(android.content.Context arg0, String arg1, boolean arg2)
  {
    // Byte code:
    //   0: goto +517 -> 517
    //   3: iconst_4
    //   4: newarray char
    //   6: dup
    //   7: iconst_0
    //   8: ldc 48
    //   10: castore
    //   11: dup
    //   12: iconst_1
    //   13: ldc 49
    //   15: castore
    //   16: dup
    //   17: iconst_2
    //   18: ldc 50
    //   20: castore
    //   21: dup
    //   22: iconst_3
    //   23: ldc 51
    //   25: castore
    //   26: sipush 25766
    //   29: bipush 6
    //   31: newarray char
    //   33: dup
    //   34: iconst_0
    //   35: ldc 52
    //   37: castore
    //   38: dup
    //   39: iconst_1
    //   40: ldc 53
    //   42: castore
    //   43: dup
    //   44: iconst_2
    //   45: ldc 54
    //   47: castore
    //   48: dup
    //   49: iconst_3
    //   50: ldc 55
    //   52: castore
    //   53: dup
    //   54: iconst_4
    //   55: ldc 56
    //   57: castore
    //   58: dup
    //   59: iconst_5
    //   60: ldc 57
    //   62: castore
    //   63: iconst_0
    //   64: iconst_4
    //   65: newarray char
    //   67: dup
    //   68: iconst_0
    //   69: ldc 58
    //   71: castore
    //   72: dup
    //   73: iconst_1
    //   74: ldc 58
    //   76: castore
    //   77: dup
    //   78: iconst_2
    //   79: ldc 58
    //   81: castore
    //   82: dup
    //   83: iconst_3
    //   84: ldc 58
    //   86: castore
    //   87: invokestatic 60	o/GE:ˊ	([CC[CI[C)Ljava/lang/String;
    //   90: invokevirtual 64	java/lang/String:intern	()Ljava/lang/String;
    //   93: astore 5
    //   95: iconst_4
    //   96: newarray char
    //   98: dup
    //   99: iconst_0
    //   100: ldc 65
    //   102: castore
    //   103: dup
    //   104: iconst_1
    //   105: ldc 66
    //   107: castore
    //   108: dup
    //   109: iconst_2
    //   110: ldc 67
    //   112: castore
    //   113: dup
    //   114: iconst_3
    //   115: ldc 68
    //   117: castore
    //   118: iconst_0
    //   119: bipush 46
    //   121: newarray char
    //   123: dup
    //   124: iconst_0
    //   125: ldc 69
    //   127: castore
    //   128: dup
    //   129: iconst_1
    //   130: ldc 70
    //   132: castore
    //   133: dup
    //   134: iconst_2
    //   135: ldc 71
    //   137: castore
    //   138: dup
    //   139: iconst_3
    //   140: ldc 72
    //   142: castore
    //   143: dup
    //   144: iconst_4
    //   145: ldc 73
    //   147: castore
    //   148: dup
    //   149: iconst_5
    //   150: ldc 74
    //   152: castore
    //   153: dup
    //   154: bipush 6
    //   156: ldc 75
    //   158: castore
    //   159: dup
    //   160: bipush 7
    //   162: ldc 76
    //   164: castore
    //   165: dup
    //   166: bipush 8
    //   168: ldc 77
    //   170: castore
    //   171: dup
    //   172: bipush 9
    //   174: ldc 78
    //   176: castore
    //   177: dup
    //   178: bipush 10
    //   180: ldc 79
    //   182: castore
    //   183: dup
    //   184: bipush 11
    //   186: ldc 80
    //   188: castore
    //   189: dup
    //   190: bipush 12
    //   192: ldc 81
    //   194: castore
    //   195: dup
    //   196: bipush 13
    //   198: ldc 82
    //   200: castore
    //   201: dup
    //   202: bipush 14
    //   204: ldc 83
    //   206: castore
    //   207: dup
    //   208: bipush 15
    //   210: ldc 84
    //   212: castore
    //   213: dup
    //   214: bipush 16
    //   216: ldc 85
    //   218: castore
    //   219: dup
    //   220: bipush 17
    //   222: ldc 86
    //   224: castore
    //   225: dup
    //   226: bipush 18
    //   228: ldc 87
    //   230: castore
    //   231: dup
    //   232: bipush 19
    //   234: ldc 88
    //   236: castore
    //   237: dup
    //   238: bipush 20
    //   240: ldc 89
    //   242: castore
    //   243: dup
    //   244: bipush 21
    //   246: ldc 90
    //   248: castore
    //   249: dup
    //   250: bipush 22
    //   252: ldc 91
    //   254: castore
    //   255: dup
    //   256: bipush 23
    //   258: ldc 92
    //   260: castore
    //   261: dup
    //   262: bipush 24
    //   264: ldc 93
    //   266: castore
    //   267: dup
    //   268: bipush 25
    //   270: ldc 94
    //   272: castore
    //   273: dup
    //   274: bipush 26
    //   276: ldc 95
    //   278: castore
    //   279: dup
    //   280: bipush 27
    //   282: ldc 96
    //   284: castore
    //   285: dup
    //   286: bipush 28
    //   288: ldc 97
    //   290: castore
    //   291: dup
    //   292: bipush 29
    //   294: ldc 98
    //   296: castore
    //   297: dup
    //   298: bipush 30
    //   300: ldc 99
    //   302: castore
    //   303: dup
    //   304: bipush 31
    //   306: ldc 100
    //   308: castore
    //   309: dup
    //   310: bipush 32
    //   312: ldc 101
    //   314: castore
    //   315: dup
    //   316: bipush 33
    //   318: ldc 102
    //   320: castore
    //   321: dup
    //   322: bipush 34
    //   324: ldc 103
    //   326: castore
    //   327: dup
    //   328: bipush 35
    //   330: ldc 104
    //   332: castore
    //   333: dup
    //   334: bipush 36
    //   336: ldc 105
    //   338: castore
    //   339: dup
    //   340: bipush 37
    //   342: ldc 106
    //   344: castore
    //   345: dup
    //   346: bipush 38
    //   348: ldc 107
    //   350: castore
    //   351: dup
    //   352: bipush 39
    //   354: ldc 108
    //   356: castore
    //   357: dup
    //   358: bipush 40
    //   360: ldc 109
    //   362: castore
    //   363: dup
    //   364: bipush 41
    //   366: ldc 110
    //   368: castore
    //   369: dup
    //   370: bipush 42
    //   372: ldc 111
    //   374: castore
    //   375: dup
    //   376: bipush 43
    //   378: ldc 112
    //   380: castore
    //   381: dup
    //   382: bipush 44
    //   384: ldc 113
    //   386: castore
    //   387: dup
    //   388: bipush 45
    //   390: ldc 114
    //   392: castore
    //   393: iconst_0
    //   394: iconst_4
    //   395: newarray char
    //   397: dup
    //   398: iconst_0
    //   399: ldc 58
    //   401: castore
    //   402: dup
    //   403: iconst_1
    //   404: ldc 58
    //   406: castore
    //   407: dup
    //   408: iconst_2
    //   409: ldc 58
    //   411: castore
    //   412: dup
    //   413: iconst_3
    //   414: ldc 58
    //   416: castore
    //   417: invokestatic 60	o/GE:ˊ	([CC[CI[C)Ljava/lang/String;
    //   420: invokevirtual 64	java/lang/String:intern	()Ljava/lang/String;
    //   423: astore 4
    //   425: goto +17 -> 442
    //   428: astore_0
    //   429: aload_0
    //   430: invokevirtual 120	java/lang/Throwable:getCause	()Ljava/lang/Throwable;
    //   433: astore_1
    //   434: aload_1
    //   435: ifnull +5 -> 440
    //   438: aload_1
    //   439: athrow
    //   440: aload_0
    //   441: athrow
    //   442: iconst_4
    //   443: bipush 42
    //   445: ldc 121
    //   447: invokestatic 126	o/O:ˋ	(IIC)Ljava/lang/Object;
    //   450: checkcast 128	java/lang/Class
    //   453: ldc -127
    //   455: iconst_2
    //   456: anewarray 128	java/lang/Class
    //   459: dup
    //   460: iconst_0
    //   461: ldc 31
    //   463: aastore
    //   464: dup
    //   465: iconst_1
    //   466: ldc 31
    //   468: aastore
    //   469: invokevirtual 133	java/lang/Class:getMethod	(Ljava/lang/String;[Ljava/lang/Class;)Ljava/lang/reflect/Method;
    //   472: aconst_null
    //   473: iconst_2
    //   474: anewarray 4	java/lang/Object
    //   477: dup
    //   478: iconst_0
    //   479: aload 5
    //   481: aastore
    //   482: dup
    //   483: iconst_1
    //   484: aload 4
    //   486: aastore
    //   487: invokevirtual 139	java/lang/reflect/Method:invoke	(Ljava/lang/Object;[Ljava/lang/Object;)Ljava/lang/Object;
    //   490: pop
    //   491: new 141	o/IR
    //   494: dup
    //   495: aload_0
    //   496: getstatic 146	o/Gu$ˏ:security_compromised	I
    //   499: aload_1
    //   500: getstatic 149	o/Gu$ˏ:uninstall_app	I
    //   503: iload_2
    //   504: invokespecial 152	o/IR:<init>	(Landroid/content/Context;ILjava/lang/String;IZ)V
    //   507: invokevirtual 155	o/IR:ˏ	()Lo/ᐸ;
    //   510: pop
    //   511: goto +41 -> 552
    //   514: astore_0
    //   515: aload_0
    //   516: athrow
    //   517: goto -514 -> 3
    //   520: astore_0
    //   521: aload_0
    //   522: athrow
    //   523: iload_3
    //   524: tableswitch	default:+24->548, 0:+27->551, 1:+62->586
    //   548: goto +38 -> 586
    //   551: return
    //   552: getstatic 16	o/GE:ˊ	I
    //   555: bipush 47
    //   557: iadd
    //   558: istore_3
    //   559: iload_3
    //   560: sipush 128
    //   563: irem
    //   564: putstatic 18	o/GE:ˋ	I
    //   567: iload_3
    //   568: iconst_2
    //   569: irem
    //   570: ifne +6 -> 576
    //   573: goto +8 -> 581
    //   576: iconst_0
    //   577: istore_3
    //   578: goto -55 -> 523
    //   581: iconst_1
    //   582: istore_3
    //   583: goto -60 -> 523
    //   586: new 157	java/lang/NullPointerException
    //   589: dup
    //   590: invokespecial 159	java/lang/NullPointerException:<init>	()V
    //   593: athrow
    // Exception table:
    //   from	to	target	type
    //   442	491	428	finally
    //   3	425	514	java/lang/Exception
    //   429	434	514	java/lang/Exception
    //   438	440	514	java/lang/Exception
    //   440	442	514	java/lang/Exception
    //   491	511	514	java/lang/Exception
  }
}
