package o;

import com.insidesecure.hce.MatrixHCECard;
import java.util.Comparator;

public final class GK
  implements Comparator<MatrixHCECard>
{
  private static int ˋ = 1;
  private static long ˎ = -1109325366871861560L;
  private static int ˏ = 0;
  
  public GK() {}
  
  /* Error */
  private static String ॱ(char[] paramArrayOfChar)
  {
    // Byte code:
    //   0: goto +146 -> 146
    //   3: astore_0
    //   4: aload_0
    //   5: athrow
    //   6: bipush 95
    //   8: istore_2
    //   9: goto +102 -> 111
    //   12: aload_0
    //   13: iload_1
    //   14: aload_0
    //   15: iload_1
    //   16: caload
    //   17: aload_0
    //   18: iload_1
    //   19: iconst_4
    //   20: irem
    //   21: caload
    //   22: ixor
    //   23: i2l
    //   24: iload_1
    //   25: iconst_4
    //   26: isub
    //   27: i2l
    //   28: getstatic 22	o/GK:ˎ	J
    //   31: lmul
    //   32: lxor
    //   33: l2i
    //   34: i2c
    //   35: castore
    //   36: iload_1
    //   37: iconst_1
    //   38: iadd
    //   39: istore_1
    //   40: goto +35 -> 75
    //   43: getstatic 22	o/GK:ˎ	J
    //   46: lstore_3
    //   47: lload_3
    //   48: aload_0
    //   49: invokestatic 35	o/oL:ˋ	(J[C)[C
    //   52: astore_0
    //   53: iconst_4
    //   54: istore_1
    //   55: goto +121 -> 176
    //   58: new 37	java/lang/String
    //   61: dup
    //   62: aload_0
    //   63: iconst_4
    //   64: aload_0
    //   65: arraylength
    //   66: iconst_4
    //   67: isub
    //   68: invokespecial 40	java/lang/String:<init>	([CII)V
    //   71: astore_0
    //   72: goto +77 -> 149
    //   75: getstatic 18	o/GK:ˋ	I
    //   78: bipush 49
    //   80: iadd
    //   81: istore_2
    //   82: iload_2
    //   83: sipush 128
    //   86: irem
    //   87: putstatic 16	o/GK:ˏ	I
    //   90: iload_2
    //   91: iconst_2
    //   92: irem
    //   93: ifeq +6 -> 99
    //   96: goto +12 -> 108
    //   99: goto +89 -> 188
    //   102: bipush 69
    //   104: istore_2
    //   105: goto +6 -> 111
    //   108: goto +80 -> 188
    //   111: iload_2
    //   112: lookupswitch	default:+28->140, 69:+-100->12, 95:+-54->58
    //   140: goto -82 -> 58
    //   143: astore_0
    //   144: aload_0
    //   145: athrow
    //   146: goto -103 -> 43
    //   149: getstatic 18	o/GK:ˋ	I
    //   152: istore_1
    //   153: iload_1
    //   154: bipush 61
    //   156: iadd
    //   157: istore_1
    //   158: iload_1
    //   159: sipush 128
    //   162: irem
    //   163: putstatic 16	o/GK:ˏ	I
    //   166: iload_1
    //   167: iconst_2
    //   168: irem
    //   169: ifeq +5 -> 174
    //   172: aload_0
    //   173: areturn
    //   174: aload_0
    //   175: areturn
    //   176: iload_1
    //   177: aload_0
    //   178: arraylength
    //   179: if_icmpge +6 -> 185
    //   182: goto -80 -> 102
    //   185: goto -179 -> 6
    //   188: goto -12 -> 176
    // Local variable table:
    //   start	length	slot	name	signature
    //   0	191	0	paramArrayOfChar	char[]
    //   13	167	1	i	int
    //   8	104	2	j	int
    //   46	2	3	l	long
    // Exception table:
    //   from	to	target	type
    //   43	47	3	java/lang/Exception
    //   47	53	3	java/lang/Exception
    //   149	153	143	java/lang/Exception
    //   158	166	143	java/lang/Exception
  }
  
  /* Error */
  public int ˊ(MatrixHCECard arg1, MatrixHCECard arg2)
  {
    // Byte code:
    //   0: goto +109 -> 109
    //   3: goto +121 -> 124
    //   6: bipush 43
    //   8: istore_3
    //   9: goto +6 -> 15
    //   12: goto +768 -> 780
    //   15: iload_3
    //   16: lookupswitch	default:+28->44, 43:+-4->12, 75:+31->47
    //   44: goto -32 -> 12
    //   47: getstatic 18	o/GK:ˋ	I
    //   50: bipush 39
    //   52: iadd
    //   53: istore_3
    //   54: iload_3
    //   55: sipush 128
    //   58: irem
    //   59: putstatic 16	o/GK:ˏ	I
    //   62: iload_3
    //   63: iconst_2
    //   64: irem
    //   65: ifeq +6 -> 71
    //   68: goto +35 -> 103
    //   71: goto -68 -> 3
    //   74: iload_3
    //   75: lookupswitch	default:+25->100, 11:+703->778, 75:+732->807
    //   100: goto +678 -> 778
    //   103: goto -100 -> 3
    //   106: astore_1
    //   107: aload_1
    //   108: athrow
    //   109: goto +17 -> 126
    //   112: bipush 11
    //   114: istore_3
    //   115: goto -41 -> 74
    //   118: bipush 75
    //   120: istore_3
    //   121: goto -47 -> 74
    //   124: iconst_1
    //   125: ireturn
    //   126: bipush 12
    //   128: newarray char
    //   130: dup
    //   131: iconst_0
    //   132: ldc 52
    //   134: castore
    //   135: dup
    //   136: iconst_1
    //   137: ldc 53
    //   139: castore
    //   140: dup
    //   141: iconst_2
    //   142: ldc 54
    //   144: castore
    //   145: dup
    //   146: iconst_3
    //   147: ldc 55
    //   149: castore
    //   150: dup
    //   151: iconst_4
    //   152: ldc 56
    //   154: castore
    //   155: dup
    //   156: iconst_5
    //   157: ldc 57
    //   159: castore
    //   160: dup
    //   161: bipush 6
    //   163: ldc 58
    //   165: castore
    //   166: dup
    //   167: bipush 7
    //   169: ldc 59
    //   171: castore
    //   172: dup
    //   173: bipush 8
    //   175: ldc 60
    //   177: castore
    //   178: dup
    //   179: bipush 9
    //   181: ldc 61
    //   183: castore
    //   184: dup
    //   185: bipush 10
    //   187: ldc 62
    //   189: castore
    //   190: dup
    //   191: bipush 11
    //   193: ldc 63
    //   195: castore
    //   196: invokestatic 65	o/GK:ॱ	([C)Ljava/lang/String;
    //   199: astore 8
    //   201: aload 8
    //   203: invokevirtual 69	java/lang/String:intern	()Ljava/lang/String;
    //   206: astore 8
    //   208: aload_1
    //   209: aload 8
    //   211: invokestatic 74	o/vq:ˎ	(Ljava/lang/Object;Ljava/lang/String;)V
    //   214: aload_2
    //   215: bipush 13
    //   217: newarray char
    //   219: dup
    //   220: iconst_0
    //   221: ldc 75
    //   223: castore
    //   224: dup
    //   225: iconst_1
    //   226: ldc 76
    //   228: castore
    //   229: dup
    //   230: iconst_2
    //   231: ldc 77
    //   233: castore
    //   234: dup
    //   235: iconst_3
    //   236: ldc 78
    //   238: castore
    //   239: dup
    //   240: iconst_4
    //   241: ldc 79
    //   243: castore
    //   244: dup
    //   245: iconst_5
    //   246: ldc 80
    //   248: castore
    //   249: dup
    //   250: bipush 6
    //   252: ldc 81
    //   254: castore
    //   255: dup
    //   256: bipush 7
    //   258: ldc 82
    //   260: castore
    //   261: dup
    //   262: bipush 8
    //   264: ldc 83
    //   266: castore
    //   267: dup
    //   268: bipush 9
    //   270: ldc 84
    //   272: castore
    //   273: dup
    //   274: bipush 10
    //   276: ldc 85
    //   278: castore
    //   279: dup
    //   280: bipush 11
    //   282: ldc 86
    //   284: castore
    //   285: dup
    //   286: bipush 12
    //   288: ldc 87
    //   290: castore
    //   291: invokestatic 65	o/GK:ॱ	([C)Ljava/lang/String;
    //   294: invokevirtual 69	java/lang/String:intern	()Ljava/lang/String;
    //   297: invokestatic 74	o/vq:ˎ	(Ljava/lang/Object;Ljava/lang/String;)V
    //   300: aload_1
    //   301: invokestatic 92	o/HQ:ˏ	(Lcom/insidesecure/hce/MatrixHCECard;)Lo/HQ;
    //   304: astore_1
    //   305: aload_1
    //   306: bipush 35
    //   308: newarray char
    //   310: dup
    //   311: iconst_0
    //   312: ldc 93
    //   314: castore
    //   315: dup
    //   316: iconst_1
    //   317: ldc 94
    //   319: castore
    //   320: dup
    //   321: iconst_2
    //   322: ldc 95
    //   324: castore
    //   325: dup
    //   326: iconst_3
    //   327: ldc 96
    //   329: castore
    //   330: dup
    //   331: iconst_4
    //   332: ldc 97
    //   334: castore
    //   335: dup
    //   336: iconst_5
    //   337: ldc 98
    //   339: castore
    //   340: dup
    //   341: bipush 6
    //   343: ldc 99
    //   345: castore
    //   346: dup
    //   347: bipush 7
    //   349: ldc 100
    //   351: castore
    //   352: dup
    //   353: bipush 8
    //   355: ldc 101
    //   357: castore
    //   358: dup
    //   359: bipush 9
    //   361: ldc 102
    //   363: castore
    //   364: dup
    //   365: bipush 10
    //   367: ldc 103
    //   369: castore
    //   370: dup
    //   371: bipush 11
    //   373: ldc 104
    //   375: castore
    //   376: dup
    //   377: bipush 12
    //   379: ldc 105
    //   381: castore
    //   382: dup
    //   383: bipush 13
    //   385: ldc 106
    //   387: castore
    //   388: dup
    //   389: bipush 14
    //   391: ldc 107
    //   393: castore
    //   394: dup
    //   395: bipush 15
    //   397: ldc 108
    //   399: castore
    //   400: dup
    //   401: bipush 16
    //   403: ldc 109
    //   405: castore
    //   406: dup
    //   407: bipush 17
    //   409: ldc 110
    //   411: castore
    //   412: dup
    //   413: bipush 18
    //   415: ldc 111
    //   417: castore
    //   418: dup
    //   419: bipush 19
    //   421: ldc 112
    //   423: castore
    //   424: dup
    //   425: bipush 20
    //   427: ldc 113
    //   429: castore
    //   430: dup
    //   431: bipush 21
    //   433: ldc 114
    //   435: castore
    //   436: dup
    //   437: bipush 22
    //   439: ldc 115
    //   441: castore
    //   442: dup
    //   443: bipush 23
    //   445: ldc 116
    //   447: castore
    //   448: dup
    //   449: bipush 24
    //   451: ldc 117
    //   453: castore
    //   454: dup
    //   455: bipush 25
    //   457: ldc 118
    //   459: castore
    //   460: dup
    //   461: bipush 26
    //   463: ldc 119
    //   465: castore
    //   466: dup
    //   467: bipush 27
    //   469: ldc 120
    //   471: castore
    //   472: dup
    //   473: bipush 28
    //   475: ldc 121
    //   477: castore
    //   478: dup
    //   479: bipush 29
    //   481: ldc 122
    //   483: castore
    //   484: dup
    //   485: bipush 30
    //   487: ldc 123
    //   489: castore
    //   490: dup
    //   491: bipush 31
    //   493: ldc 124
    //   495: castore
    //   496: dup
    //   497: bipush 32
    //   499: ldc 125
    //   501: castore
    //   502: dup
    //   503: bipush 33
    //   505: ldc 126
    //   507: castore
    //   508: dup
    //   509: bipush 34
    //   511: ldc 127
    //   513: castore
    //   514: invokestatic 65	o/GK:ॱ	([C)Ljava/lang/String;
    //   517: invokevirtual 69	java/lang/String:intern	()Ljava/lang/String;
    //   520: invokestatic 129	o/vq:ˋ	(Ljava/lang/Object;Ljava/lang/String;)V
    //   523: aload_1
    //   524: invokevirtual 133	o/HQ:ʼ	()J
    //   527: lstore 4
    //   529: aload_2
    //   530: invokestatic 92	o/HQ:ˏ	(Lcom/insidesecure/hce/MatrixHCECard;)Lo/HQ;
    //   533: astore_1
    //   534: aload_1
    //   535: bipush 36
    //   537: newarray char
    //   539: dup
    //   540: iconst_0
    //   541: ldc -122
    //   543: castore
    //   544: dup
    //   545: iconst_1
    //   546: ldc -121
    //   548: castore
    //   549: dup
    //   550: iconst_2
    //   551: ldc -120
    //   553: castore
    //   554: dup
    //   555: iconst_3
    //   556: ldc -119
    //   558: castore
    //   559: dup
    //   560: iconst_4
    //   561: ldc -118
    //   563: castore
    //   564: dup
    //   565: iconst_5
    //   566: ldc -117
    //   568: castore
    //   569: dup
    //   570: bipush 6
    //   572: ldc -116
    //   574: castore
    //   575: dup
    //   576: bipush 7
    //   578: ldc -115
    //   580: castore
    //   581: dup
    //   582: bipush 8
    //   584: ldc -114
    //   586: castore
    //   587: dup
    //   588: bipush 9
    //   590: ldc -113
    //   592: castore
    //   593: dup
    //   594: bipush 10
    //   596: ldc -112
    //   598: castore
    //   599: dup
    //   600: bipush 11
    //   602: ldc -111
    //   604: castore
    //   605: dup
    //   606: bipush 12
    //   608: ldc -110
    //   610: castore
    //   611: dup
    //   612: bipush 13
    //   614: ldc -109
    //   616: castore
    //   617: dup
    //   618: bipush 14
    //   620: ldc -108
    //   622: castore
    //   623: dup
    //   624: bipush 15
    //   626: ldc -107
    //   628: castore
    //   629: dup
    //   630: bipush 16
    //   632: ldc -106
    //   634: castore
    //   635: dup
    //   636: bipush 17
    //   638: ldc -105
    //   640: castore
    //   641: dup
    //   642: bipush 18
    //   644: ldc -104
    //   646: castore
    //   647: dup
    //   648: bipush 19
    //   650: ldc -103
    //   652: castore
    //   653: dup
    //   654: bipush 20
    //   656: ldc -102
    //   658: castore
    //   659: dup
    //   660: bipush 21
    //   662: ldc -101
    //   664: castore
    //   665: dup
    //   666: bipush 22
    //   668: ldc -100
    //   670: castore
    //   671: dup
    //   672: bipush 23
    //   674: ldc -99
    //   676: castore
    //   677: dup
    //   678: bipush 24
    //   680: ldc -98
    //   682: castore
    //   683: dup
    //   684: bipush 25
    //   686: ldc -97
    //   688: castore
    //   689: dup
    //   690: bipush 26
    //   692: ldc -96
    //   694: castore
    //   695: dup
    //   696: bipush 27
    //   698: ldc -95
    //   700: castore
    //   701: dup
    //   702: bipush 28
    //   704: ldc -94
    //   706: castore
    //   707: dup
    //   708: bipush 29
    //   710: ldc -93
    //   712: castore
    //   713: dup
    //   714: bipush 30
    //   716: ldc -92
    //   718: castore
    //   719: dup
    //   720: bipush 31
    //   722: ldc -91
    //   724: castore
    //   725: dup
    //   726: bipush 32
    //   728: ldc -90
    //   730: castore
    //   731: dup
    //   732: bipush 33
    //   734: ldc -89
    //   736: castore
    //   737: dup
    //   738: bipush 34
    //   740: ldc -88
    //   742: castore
    //   743: dup
    //   744: bipush 35
    //   746: ldc -87
    //   748: castore
    //   749: invokestatic 65	o/GK:ॱ	([C)Ljava/lang/String;
    //   752: invokevirtual 69	java/lang/String:intern	()Ljava/lang/String;
    //   755: invokestatic 129	o/vq:ˋ	(Ljava/lang/Object;Ljava/lang/String;)V
    //   758: aload_1
    //   759: invokevirtual 133	o/HQ:ʼ	()J
    //   762: lstore 6
    //   764: lload 4
    //   766: lload 6
    //   768: lcmp
    //   769: ifle +6 -> 775
    //   772: goto +37 -> 809
    //   775: goto -769 -> 6
    //   778: iconst_m1
    //   779: ireturn
    //   780: getstatic 18	o/GK:ˋ	I
    //   783: bipush 125
    //   785: iadd
    //   786: istore_3
    //   787: iload_3
    //   788: sipush 128
    //   791: irem
    //   792: putstatic 16	o/GK:ˏ	I
    //   795: iload_3
    //   796: iconst_2
    //   797: irem
    //   798: ifeq +6 -> 804
    //   801: goto -683 -> 118
    //   804: goto -692 -> 112
    //   807: iconst_m1
    //   808: ireturn
    //   809: bipush 75
    //   811: istore_3
    //   812: goto -797 -> 15
    //   815: astore_1
    //   816: aload_1
    //   817: athrow
    // Exception table:
    //   from	to	target	type
    //   126	201	106	java/lang/Exception
    //   201	208	106	java/lang/Exception
    //   208	214	106	java/lang/Exception
    //   214	764	106	java/lang/Exception
  }
}
