package o;

public enum Gm
{
  private static int ˋ = 0;
  private static int ˎ = 1;
  private static char[] ˏ;
  private static long ॱ;
  
  /* Error */
  static
  {
    // Byte code:
    //   0: iconst_0
    //   1: putstatic 26	o/Gm:ˋ	I
    //   4: iconst_1
    //   5: putstatic 28	o/Gm:ˎ	I
    //   8: goto +31 -> 39
    //   11: getstatic 28	o/Gm:ˎ	I
    //   14: bipush 45
    //   16: iadd
    //   17: istore_0
    //   18: iload_0
    //   19: sipush 128
    //   22: irem
    //   23: putstatic 26	o/Gm:ˋ	I
    //   26: iload_0
    //   27: iconst_2
    //   28: irem
    //   29: ifeq +6 -> 35
    //   32: goto +176 -> 208
    //   35: return
    //   36: astore_1
    //   37: aload_1
    //   38: athrow
    //   39: invokestatic 30	o/Gm:ˏ	()V
    //   42: iconst_0
    //   43: sipush 11088
    //   46: bipush 28
    //   48: invokestatic 33	o/Gm:ˋ	(ICI)Ljava/lang/String;
    //   51: astore_1
    //   52: aload_1
    //   53: invokevirtual 39	java/lang/String:intern	()Ljava/lang/String;
    //   56: astore_1
    //   57: new 2	o/Gm
    //   60: dup
    //   61: aload_1
    //   62: iconst_0
    //   63: invokespecial 43	o/Gm:<init>	(Ljava/lang/String;I)V
    //   66: astore_1
    //   67: aload_1
    //   68: putstatic 45	o/Gm:APPLICATION_GENERAL_SETTINGS	Lo/Gm;
    //   71: new 2	o/Gm
    //   74: dup
    //   75: bipush 28
    //   77: sipush 18780
    //   80: bipush 28
    //   82: invokestatic 33	o/Gm:ˋ	(ICI)Ljava/lang/String;
    //   85: invokevirtual 39	java/lang/String:intern	()Ljava/lang/String;
    //   88: iconst_1
    //   89: invokespecial 43	o/Gm:<init>	(Ljava/lang/String;I)V
    //   92: astore_2
    //   93: aload_2
    //   94: putstatic 47	o/Gm:APPLICATION_PAYMENT_SETTINGS	Lo/Gm;
    //   97: new 2	o/Gm
    //   100: dup
    //   101: bipush 56
    //   103: iconst_0
    //   104: bipush 21
    //   106: invokestatic 33	o/Gm:ˋ	(ICI)Ljava/lang/String;
    //   109: invokevirtual 39	java/lang/String:intern	()Ljava/lang/String;
    //   112: iconst_2
    //   113: invokespecial 43	o/Gm:<init>	(Ljava/lang/String;I)V
    //   116: astore_3
    //   117: aload_3
    //   118: putstatic 49	o/Gm:PAYMENT_CARD_SETTINGS	Lo/Gm;
    //   121: new 2	o/Gm
    //   124: dup
    //   125: bipush 77
    //   127: ldc 50
    //   129: bipush 21
    //   131: invokestatic 33	o/Gm:ˋ	(ICI)Ljava/lang/String;
    //   134: invokevirtual 39	java/lang/String:intern	()Ljava/lang/String;
    //   137: iconst_3
    //   138: invokespecial 43	o/Gm:<init>	(Ljava/lang/String;I)V
    //   141: astore 4
    //   143: aload 4
    //   145: putstatic 52	o/Gm:USER_PROFILE_SETTINGS	Lo/Gm;
    //   148: new 2	o/Gm
    //   151: dup
    //   152: bipush 98
    //   154: sipush 19968
    //   157: bipush 34
    //   159: invokestatic 33	o/Gm:ˋ	(ICI)Ljava/lang/String;
    //   162: invokevirtual 39	java/lang/String:intern	()Ljava/lang/String;
    //   165: iconst_4
    //   166: invokespecial 43	o/Gm:<init>	(Ljava/lang/String;I)V
    //   169: astore 5
    //   171: aload 5
    //   173: putstatic 54	o/Gm:APPLICATION_NOTIFICATIONS_SETTINGS	Lo/Gm;
    //   176: iconst_5
    //   177: anewarray 2	o/Gm
    //   180: dup
    //   181: iconst_0
    //   182: aload_1
    //   183: aastore
    //   184: dup
    //   185: iconst_1
    //   186: aload_2
    //   187: aastore
    //   188: dup
    //   189: iconst_2
    //   190: aload_3
    //   191: aastore
    //   192: dup
    //   193: iconst_3
    //   194: aload 4
    //   196: aastore
    //   197: dup
    //   198: iconst_4
    //   199: aload 5
    //   201: aastore
    //   202: putstatic 56	o/Gm:$VALUES	[Lo/Gm;
    //   205: goto -194 -> 11
    //   208: return
    // Local variable table:
    //   start	length	slot	name	signature
    //   17	12	0	i	int
    //   36	2	1	localException	Exception
    //   51	132	1	localObject	Object
    //   92	95	2	localGm1	Gm
    //   116	75	3	localGm2	Gm
    //   141	54	4	localGm3	Gm
    //   169	31	5	localGm4	Gm
    // Exception table:
    //   from	to	target	type
    //   39	42	36	java/lang/Exception
    //   42	52	36	java/lang/Exception
    //   52	57	36	java/lang/Exception
    //   57	205	36	java/lang/Exception
  }
  
  protected Gm() {}
  
  /* Error */
  private static String ˋ(int paramInt1, char paramChar, int paramInt2)
  {
    // Byte code:
    //   0: goto +39 -> 39
    //   3: iconst_0
    //   4: istore_3
    //   5: goto +190 -> 195
    //   8: aload 5
    //   10: iload_3
    //   11: getstatic 77	o/Gm:ˏ	[C
    //   14: iload_0
    //   15: iload_3
    //   16: iadd
    //   17: caload
    //   18: i2l
    //   19: iload_3
    //   20: i2l
    //   21: getstatic 79	o/Gm:ॱ	J
    //   24: lmul
    //   25: lxor
    //   26: iload_1
    //   27: i2l
    //   28: lxor
    //   29: l2i
    //   30: i2c
    //   31: castore
    //   32: iload_3
    //   33: iconst_1
    //   34: iadd
    //   35: istore_3
    //   36: goto +121 -> 157
    //   39: goto +129 -> 168
    //   42: iload 4
    //   44: tableswitch	default:+24->68, 0:+-36->8, 1:+46->90
    //   68: goto +22 -> 90
    //   71: iload_2
    //   72: newarray char
    //   74: astore 5
    //   76: goto +79 -> 155
    //   79: iconst_0
    //   80: istore 4
    //   82: goto -40 -> 42
    //   85: astore 5
    //   87: aload 5
    //   89: athrow
    //   90: new 35	java/lang/String
    //   93: dup
    //   94: aload 5
    //   96: invokespecial 82	java/lang/String:<init>	([C)V
    //   99: astore 5
    //   101: goto +27 -> 128
    //   104: iconst_1
    //   105: istore 4
    //   107: goto -65 -> 42
    //   110: iload_2
    //   111: newarray char
    //   113: astore 5
    //   115: goto +40 -> 155
    //   118: iconst_1
    //   119: istore_3
    //   120: goto +75 -> 195
    //   123: astore 5
    //   125: aload 5
    //   127: athrow
    //   128: getstatic 26	o/Gm:ˋ	I
    //   131: bipush 113
    //   133: iadd
    //   134: istore_0
    //   135: iload_0
    //   136: sipush 128
    //   139: irem
    //   140: putstatic 28	o/Gm:ˎ	I
    //   143: iload_0
    //   144: iconst_2
    //   145: irem
    //   146: ifne +6 -> 152
    //   149: aload 5
    //   151: areturn
    //   152: aload 5
    //   154: areturn
    //   155: iconst_0
    //   156: istore_3
    //   157: iload_3
    //   158: iload_2
    //   159: if_icmpge +6 -> 165
    //   162: goto -83 -> 79
    //   165: goto -61 -> 104
    //   168: getstatic 26	o/Gm:ˋ	I
    //   171: bipush 101
    //   173: iadd
    //   174: istore_3
    //   175: iload_3
    //   176: sipush 128
    //   179: irem
    //   180: putstatic 28	o/Gm:ˎ	I
    //   183: iload_3
    //   184: iconst_2
    //   185: irem
    //   186: ifne +6 -> 192
    //   189: goto -71 -> 118
    //   192: goto -189 -> 3
    //   195: iload_3
    //   196: tableswitch	default:+24->220, 0:+-125->71, 1:+-86->110
    //   220: goto -110 -> 110
    // Local variable table:
    //   start	length	slot	name	signature
    //   0	223	0	paramInt1	int
    //   0	223	1	paramChar	char
    //   0	223	2	paramInt2	int
    //   4	192	3	i	int
    //   42	64	4	j	int
    //   8	67	5	arrayOfChar	char[]
    //   85	10	5	localException1	Exception
    //   99	15	5	localObject	Object
    //   123	30	5	localException2	Exception
    // Exception table:
    //   from	to	target	type
    //   175	183	85	java/lang/Exception
    //   168	175	123	java/lang/Exception
    //   175	183	123	java/lang/Exception
  }
  
  static void ˏ()
  {
    ॱ = 1573349926475310310L;
    ˏ = new char[] { 11025, -28698, 25292, -14930, -18303, 4973, -2443, -22194, 3113, -6391, 23522, 16109, -28193, 29883, 12170, -32145, 25954, -10153, -19664, 5661, -13573, -21045, 192, -1106, 24201, 12648, -27573, 20289, 18717, -4630, 192, -22622, -9587, 29025, -27527, -13502, 28197, -31483, 14830, 23777, -3132, 5811, 19857, -8085, 1913, -17836, -11996, 29713, -22281, -12345, 25292, -26206, 15493, 21348, -2489, 11597, 80, -23385, 18837, -4353, -27683, 14384, -8912, -32235, 10099, -13225, 28846, 5542, -17769, 24573, 1233, -22226, 20020, -3313, -26526, 15701, -7765, -14384, 25392, -29172, 10597, 21570, -85, 6835, 17792, -7949, 3034, -18635, -11742, 32018, -26504, -15532, 28331, -30287, 13450, 24551, -1328, 9774, 20033, -5450, 1948, -24322, -8751, 30269, -27867, -13282, 27001, -32167, 16050, 23485, -2938, 4577, 19136, -6349, 38, -17137, -10641, 29523, -20564, -14185, 25995, -24860, 15299, 21545, -3825, 10759, 18300, -8102, 7357, -18028, -11641, 4085 };
  }
}
