package o;

import java.util.List;

public final class Gp
{
  private static int ˊ = 1;
  private static int[] ˋ = { -1244255874, -1371694783, -1023346072, 39481881, 810528769, -1409259257, -1376774655, -872859054, -745225727, -785734115, -919649671, -187483232, -489583046, 1620011016, 1397729706, -1805267701, -1103726715, 1004897632 };
  private static int ˎ = 0;
  @nT(ˋ="activities-steps")
  private final List<iF> activitiesSteps;
  
  private static String ˊ(int[] paramArrayOfInt, int paramInt)
  {
    for (;;)
    {
      char[] arrayOfChar1 = new char[4];
      char[] arrayOfChar2 = new char[paramArrayOfInt.length << 1];
      int[] arrayOfInt = (int[])ˋ.clone();
      int i = 0;
      break label215;
      arrayOfChar1[0] = ((char)(paramArrayOfInt[i] >> 16));
      arrayOfChar1[1] = ((char)paramArrayOfInt[i]);
      arrayOfChar1[2] = ((char)(paramArrayOfInt[(i + 1)] >> 16));
      arrayOfChar1[3] = ((char)paramArrayOfInt[(i + 1)]);
      oN.ˏ(arrayOfChar1, arrayOfInt, false);
      arrayOfChar2[(i << 1)] = arrayOfChar1[0];
      arrayOfChar2[((i << 1) + 1)] = arrayOfChar1[1];
      arrayOfChar2[((i << 1) + 2)] = arrayOfChar1[2];
      arrayOfChar2[((i << 1) + 3)] = arrayOfChar1[3];
      i += 2;
      break label215;
      int j = 70;
      label145:
      label215:
      label236:
      do
      {
        break;
        paramArrayOfInt = new String(arrayOfChar2, 0, paramInt);
        for (;;)
        {
          switch (j)
          {
          }
          break label145;
          paramInt = ˊ + 5;
          ˎ = paramInt % 128;
          if (paramInt % 2 != 0) {
            return paramArrayOfInt;
          }
          return paramArrayOfInt;
          if (i >= paramArrayOfInt.length)
          {
            break;
            break label236;
          }
          j = 14;
        }
        i = ˎ + 91;
        ˊ = i % 128;
      } while (i % 2 == 0);
    }
  }
  
  public boolean equals(Object paramObject)
  {
    break label209;
    boolean bool = paramObject instanceof Gp;
    throw new NullPointerException();
    break label133;
    int i = 6;
    for (;;)
    {
      paramObject = (Gp)paramObject;
      if (vq.ˊ(this.activitiesSteps, paramObject.activitiesSteps)) {
        break;
      }
      break label168;
      switch (i)
      {
      case 32: 
      default: 
        label50:
        break;
      }
      label133:
      label168:
      label183:
      label186:
      label197:
      label203:
      label209:
      for (;;)
      {
        i = ˎ + 75;
        ˊ = i % 128;
        if (i % 2 != 0) {}
        while (this != paramObject)
        {
          i = ˊ + 73;
          ˎ = i % 128;
          if (i % 2 == 0)
          {
            break label197;
            i = ˊ + 29;
            ˎ = i % 128;
            if (i % 2 != 0) {
              break label183;
            }
          }
          for (;;)
          {
            return true;
            i = 32;
            break label50;
            break label186;
            return false;
            if ((paramObject instanceof Gp)) {
              break label203;
            }
            break;
          }
        }
        break;
        i = 97;
        break label50;
        i = 31;
        break label212;
      }
      label212:
      switch (i)
      {
      }
    }
  }
  
  public int hashCode()
  {
    break label148;
    int j = ˊ + 45;
    ˎ = j % 128;
    label30:
    label32:
    int i;
    if (j % 2 == 0)
    {
      break label159;
      j = 1;
      switch (j)
      {
      default: 
        break;
        i = 0;
        break;
      case 1: 
        label106:
        label148:
        label151:
        label156:
        for (;;)
        {
          List localList = this.activitiesSteps;
          if (localList == null)
          {
            break label170;
            j = ˊ + 77;
            ˎ = j % 128;
            if (j % 2 != 0) {
              break label151;
            }
            break label30;
          }
          try
          {
            i = localList.hashCode();
          }
          catch (Exception localException)
          {
            throw localException;
          }
          i = 1;
          break label172;
          for (;;)
          {
            i = ˊ + 101;
            ˎ = i % 128;
            if (i % 2 != 0) {
              break label156;
            }
            break;
            return i;
          }
          j = 0;
          break label32;
        }
      }
    }
    for (;;)
    {
      label159:
      break label199;
      throw new NullPointerException();
      label170:
      i = 0;
      label172:
      switch (i)
      {
      }
      break label106;
      label199:
      break;
    }
  }
  
  public String toString()
  {
    String str;
    for (;;)
    {
      str = ˊ(new int[] { 1510427117, 1501243447, -167546500, -1763070882, -1748593712, 253690703, -734356846, -398709671, 1880498278, 796433163, -2141414970, -782581913, 1285647080, -95129798 }, 28).intern() + this.activitiesSteps + ˊ(new int[] { 1809861101, -1435434558 }, 1).intern();
      break label178;
      for (;;)
      {
        switch (i)
        {
        default: 
          return str;
          label166:
          i = 1;
        }
      }
      return str;
      for (;;)
      {
        i = 0;
        break;
        label178:
        i = ˎ + 35;
        ˊ = i % 128;
        if (i % 2 == 0) {
          break label166;
        }
      }
    }
    int i = null.length;
    return str;
  }
  
  /* Error */
  public final List<iF> ˏ()
  {
    // Byte code:
    //   0: goto +139 -> 139
    //   3: bipush 21
    //   5: iconst_0
    //   6: idiv
    //   7: istore_1
    //   8: aload_2
    //   9: areturn
    //   10: iload_1
    //   11: tableswitch	default:+21->32, 0:+138->149, 1:+146->157
    //   32: goto +125 -> 157
    //   35: iconst_0
    //   36: istore_1
    //   37: goto -27 -> 10
    //   40: getstatic 21	o/Gp:ˎ	I
    //   43: bipush 17
    //   45: iadd
    //   46: istore_1
    //   47: iload_1
    //   48: sipush 128
    //   51: irem
    //   52: putstatic 23	o/Gp:ˊ	I
    //   55: iload_1
    //   56: iconst_2
    //   57: irem
    //   58: ifne +6 -> 64
    //   61: goto +12 -> 73
    //   64: goto +78 -> 142
    //   67: astore_2
    //   68: aload_2
    //   69: athrow
    //   70: astore_2
    //   71: aload_2
    //   72: athrow
    //   73: iconst_0
    //   74: istore_1
    //   75: goto +37 -> 112
    //   78: iconst_1
    //   79: istore_1
    //   80: goto -70 -> 10
    //   83: getstatic 21	o/Gp:ˎ	I
    //   86: istore_1
    //   87: iload_1
    //   88: bipush 65
    //   90: iadd
    //   91: istore_1
    //   92: iload_1
    //   93: sipush 128
    //   96: irem
    //   97: putstatic 23	o/Gp:ˊ	I
    //   100: iload_1
    //   101: iconst_2
    //   102: irem
    //   103: ifne +6 -> 109
    //   106: goto -28 -> 78
    //   109: goto -74 -> 35
    //   112: iload_1
    //   113: tableswitch	default:+23->136, 0:+-110->3, 1:+34->147
    //   136: goto -133 -> 3
    //   139: goto -56 -> 83
    //   142: iconst_1
    //   143: istore_1
    //   144: goto -32 -> 112
    //   147: aload_2
    //   148: areturn
    //   149: aload_0
    //   150: getfield 70	o/Gp:activitiesSteps	Ljava/util/List;
    //   153: astore_2
    //   154: goto -114 -> 40
    //   157: aload_0
    //   158: getfield 70	o/Gp:activitiesSteps	Ljava/util/List;
    //   161: astore_2
    //   162: aconst_null
    //   163: arraylength
    //   164: istore_1
    //   165: goto -125 -> 40
    // Local variable table:
    //   start	length	slot	name	signature
    //   0	168	0	this	Gp
    //   7	158	1	i	int
    //   8	1	2	localList	List<iF>
    //   67	2	2	localException1	Exception
    //   70	78	2	localException2	Exception
    //   153	9	2	localList1	List
    // Exception table:
    //   from	to	target	type
    //   157	162	67	java/lang/Exception
    //   83	87	70	java/lang/Exception
    //   92	100	70	java/lang/Exception
  }
  
  public static final class iF
  {
    private static int ʻ = 0;
    private static int ʽ = 1;
    private static short[] ˊ;
    private static int ˋ = 1159132722;
    private static byte[] ˎ;
    private static int ˏ = 33;
    private static int ॱ = -393390645;
    private final String dateTime;
    private final String value;
    
    static
    {
      ˎ = new byte[] { -18, -100, -68, 64, 81, -85, -75, 87, -71, 120, -15, 71, 79, -75, 101, -25, 115, 91, -94, -96, 64, -3, 95, -32 };
    }
    
    /* Error */
    private static String ˎ(short paramShort, int paramInt1, byte paramByte, int paramInt2, int paramInt3)
    {
      // Byte code:
      //   0: goto +454 -> 454
      //   3: bipush 19
      //   5: istore 6
      //   7: goto +308 -> 315
      //   10: getstatic 64	o/Gp$iF:ˊ	[S
      //   13: getstatic 58	o/Gp$iF:ॱ	I
      //   16: iload_1
      //   17: iadd
      //   18: saload
      //   19: getstatic 28	o/Gp$iF:ˏ	I
      //   22: iadd
      //   23: i2s
      //   24: istore 4
      //   26: goto +361 -> 387
      //   29: iload_3
      //   30: iload 4
      //   32: if_icmpge +6 -> 38
      //   35: goto -32 -> 3
      //   38: goto +593 -> 631
      //   41: getstatic 64	o/Gp$iF:ˊ	[S
      //   44: astore 10
      //   46: iload_1
      //   47: iconst_1
      //   48: isub
      //   49: istore 6
      //   51: aload 10
      //   53: iload_1
      //   54: saload
      //   55: iload_0
      //   56: iadd
      //   57: i2s
      //   58: iload_2
      //   59: ixor
      //   60: iload 7
      //   62: iadd
      //   63: i2c
      //   64: istore 5
      //   66: iload 6
      //   68: istore_1
      //   69: goto +208 -> 277
      //   72: iconst_1
      //   73: istore 6
      //   75: goto +146 -> 221
      //   78: bipush 95
      //   80: istore 8
      //   82: goto +459 -> 541
      //   85: new 66	java/lang/StringBuilder
      //   88: dup
      //   89: invokespecial 69	java/lang/StringBuilder:<init>	()V
      //   92: astore 9
      //   94: getstatic 28	o/Gp$iF:ˏ	I
      //   97: iload 4
      //   99: iadd
      //   100: istore 6
      //   102: iload 6
      //   104: istore 4
      //   106: iload 6
      //   108: iconst_m1
      //   109: if_icmpne +6 -> 115
      //   112: goto +6 -> 118
      //   115: goto +50 -> 165
      //   118: bipush 86
      //   120: istore 6
      //   122: goto +479 -> 601
      //   125: getstatic 26	o/Gp$iF:ʽ	I
      //   128: istore 7
      //   130: iload 7
      //   132: bipush 117
      //   134: iadd
      //   135: istore 7
      //   137: iload 7
      //   139: sipush 128
      //   142: irem
      //   143: putstatic 24	o/Gp$iF:ʻ	I
      //   146: iload 7
      //   148: iconst_2
      //   149: irem
      //   150: ifeq +6 -> 156
      //   153: goto +381 -> 534
      //   156: goto +153 -> 309
      //   159: iconst_0
      //   160: istore 6
      //   162: goto +196 -> 358
      //   165: bipush 95
      //   167: istore 6
      //   169: goto +432 -> 601
      //   172: astore 9
      //   174: aload 9
      //   176: athrow
      //   177: iconst_1
      //   178: istore 8
      //   180: iload 7
      //   182: istore_1
      //   183: iload 7
      //   185: istore 6
      //   187: iload 8
      //   189: tableswitch	default:+23->212, 0:+26->215, 1:+268->457
      //   212: iload 7
      //   214: istore_1
      //   215: iconst_1
      //   216: istore 6
      //   218: goto +275 -> 493
      //   221: goto +302 -> 523
      //   224: getstatic 24	o/Gp$iF:ʻ	I
      //   227: bipush 89
      //   229: iadd
      //   230: istore 4
      //   232: iload 4
      //   234: sipush 128
      //   237: irem
      //   238: putstatic 26	o/Gp$iF:ʽ	I
      //   241: iload 4
      //   243: iconst_2
      //   244: irem
      //   245: ifne +6 -> 251
      //   248: goto +150 -> 398
      //   251: goto +331 -> 582
      //   254: iload_1
      //   255: iload 4
      //   257: iushr
      //   258: iconst_3
      //   259: isub
      //   260: getstatic 58	o/Gp$iF:ॱ	I
      //   263: iushr
      //   264: istore 7
      //   266: iload 6
      //   268: ifeq +6 -> 274
      //   271: goto -193 -> 78
      //   274: goto +320 -> 594
      //   277: aload 9
      //   279: iload 5
      //   281: invokevirtual 73	java/lang/StringBuilder:append	(C)Ljava/lang/StringBuilder;
      //   284: pop
      //   285: iload_3
      //   286: iconst_1
      //   287: iadd
      //   288: istore_3
      //   289: iload 5
      //   291: istore 7
      //   293: goto -264 -> 29
      //   296: iload 5
      //   298: istore 7
      //   300: goto -271 -> 29
      //   303: iconst_1
      //   304: istore 6
      //   306: goto +52 -> 358
      //   309: iconst_5
      //   310: istore 7
      //   312: goto +361 -> 673
      //   315: iload 6
      //   317: lookupswitch	default:+27->344, 19:+94->411, 59:+321->638
      //   344: goto +294 -> 638
      //   347: iconst_0
      //   348: istore 8
      //   350: goto -170 -> 180
      //   353: astore 9
      //   355: aload 9
      //   357: athrow
      //   358: iload 6
      //   360: tableswitch	default:+24->384, 0:+63->423, 1:+-319->41
      //   384: goto -343 -> 41
      //   387: iload 4
      //   389: ifle +6 -> 395
      //   392: goto -267 -> 125
      //   395: goto +243 -> 638
      //   398: getstatic 52	o/Gp$iF:ˎ	[B
      //   401: astore 9
      //   403: new 75	java/lang/NullPointerException
      //   406: dup
      //   407: invokespecial 76	java/lang/NullPointerException:<init>	()V
      //   410: athrow
      //   411: getstatic 52	o/Gp$iF:ˎ	[B
      //   414: ifnull +6 -> 420
      //   417: goto -258 -> 159
      //   420: goto -117 -> 303
      //   423: getstatic 52	o/Gp$iF:ˎ	[B
      //   426: astore 10
      //   428: iload_1
      //   429: iconst_1
      //   430: isub
      //   431: istore 6
      //   433: aload 10
      //   435: iload_1
      //   436: baload
      //   437: iload_0
      //   438: iadd
      //   439: i2b
      //   440: iload_2
      //   441: ixor
      //   442: iload 7
      //   444: iadd
      //   445: i2c
      //   446: istore 5
      //   448: iload 6
      //   450: istore_1
      //   451: goto -174 -> 277
      //   454: goto -369 -> 85
      //   457: iconst_0
      //   458: istore 7
      //   460: iload 6
      //   462: istore_1
      //   463: iload 7
      //   465: istore 6
      //   467: goto +26 -> 493
      //   470: iload_1
      //   471: iload 4
      //   473: iadd
      //   474: iconst_2
      //   475: isub
      //   476: getstatic 58	o/Gp$iF:ॱ	I
      //   479: iadd
      //   480: istore 7
      //   482: iload 6
      //   484: ifeq +6 -> 490
      //   487: goto -140 -> 347
      //   490: goto -313 -> 177
      //   493: iload_1
      //   494: iload 6
      //   496: iadd
      //   497: istore_1
      //   498: getstatic 55	o/Gp$iF:ˋ	I
      //   501: istore 6
      //   503: iload 6
      //   505: iload_3
      //   506: iadd
      //   507: i2c
      //   508: istore 5
      //   510: aload 9
      //   512: iload 5
      //   514: invokevirtual 73	java/lang/StringBuilder:append	(C)Ljava/lang/StringBuilder;
      //   517: pop
      //   518: iconst_1
      //   519: istore_3
      //   520: goto -224 -> 296
      //   523: iload 6
      //   525: ifeq +6 -> 531
      //   528: goto -304 -> 224
      //   531: goto -144 -> 387
      //   534: bipush 57
      //   536: istore 7
      //   538: goto +135 -> 673
      //   541: iload 7
      //   543: istore_1
      //   544: iload 7
      //   546: istore 6
      //   548: iload 8
      //   550: lookupswitch	default:+26->576, 14:+-93->457, 95:+-335->215
      //   576: iload 7
      //   578: istore_1
      //   579: goto -364 -> 215
      //   582: getstatic 52	o/Gp$iF:ˎ	[B
      //   585: ifnull +6 -> 591
      //   588: goto +66 -> 654
      //   591: goto -581 -> 10
      //   594: bipush 14
      //   596: istore 8
      //   598: goto -57 -> 541
      //   601: iload 6
      //   603: lookupswitch	default:+25->628, 86:+-531->72, 95:+45->648
      //   628: goto +20 -> 648
      //   631: bipush 59
      //   633: istore 6
      //   635: goto -320 -> 315
      //   638: aload 9
      //   640: invokevirtual 80	java/lang/StringBuilder:toString	()Ljava/lang/String;
      //   643: astore 9
      //   645: aload 9
      //   647: areturn
      //   648: iconst_0
      //   649: istore 6
      //   651: goto -128 -> 523
      //   654: getstatic 52	o/Gp$iF:ˎ	[B
      //   657: getstatic 58	o/Gp$iF:ॱ	I
      //   660: iload_1
      //   661: iadd
      //   662: baload
      //   663: getstatic 28	o/Gp$iF:ˏ	I
      //   666: iadd
      //   667: i2b
      //   668: istore 4
      //   670: goto -283 -> 387
      //   673: iload 7
      //   675: lookupswitch	default:+25->700, 5:+-205->470, 57:+-421->254
      //   700: goto -230 -> 470
      // Local variable table:
      //   start	length	slot	name	signature
      //   0	703	0	paramShort	short
      //   0	703	1	paramInt1	int
      //   0	703	2	paramByte	byte
      //   0	703	3	paramInt2	int
      //   0	703	4	paramInt3	int
      //   64	449	5	i	int
      //   5	645	6	j	int
      //   60	614	7	k	int
      //   80	517	8	m	int
      //   92	1	9	localStringBuilder	StringBuilder
      //   172	106	9	localException1	Exception
      //   353	3	9	localException2	Exception
      //   401	245	9	localObject1	Object
      //   44	390	10	localObject2	Object
      // Exception table:
      //   from	to	target	type
      //   125	130	172	java/lang/Exception
      //   498	503	172	java/lang/Exception
      //   510	518	172	java/lang/Exception
      //   638	645	172	java/lang/Exception
      //   137	146	353	java/lang/Exception
    }
    
    public boolean equals(Object paramObject)
    {
      label11:
      label40:
      label65:
      label204:
      label209:
      label242:
      label248:
      label254:
      label265:
      label280:
      for (;;)
      {
        return true;
        int i;
        for (;;)
        {
          i = 41;
          break label209;
          i = ʽ + 77;
          ʻ = i % 128;
          if (i % 2 != 0) {
            break label248;
          }
          break label254;
          for (;;)
          {
            return false;
            paramObject = (iF)paramObject;
            if (vq.ˊ(this.dateTime, paramObject.dateTime)) {
              break;
            }
            continue;
            if ((paramObject instanceof iF)) {
              break label204;
            }
          }
          if (!vq.ˊ(this.value, paramObject.value)) {
            break label242;
          }
        }
        for (;;)
        {
          try
          {
            i = ʻ + 31;
            try
            {
              ʽ = i % 128;
              if (i % 2 == 0) {
                break label265;
              }
            }
            catch (Exception paramObject)
            {
              boolean bool;
              throw paramObject;
            }
            switch (i)
            {
            }
            bool = vq.ˊ(this.value, paramObject.value);
            i = 61 / 0;
            if (bool) {
              break label280;
            }
          }
          catch (Exception paramObject)
          {
            throw paramObject;
          }
          i = ʽ + 105;
          ʻ = i % 128;
          if (i % 2 == 0)
          {
            break label65;
            break label40;
          }
          switch (i)
          {
          case 14: 
          default: 
            break label280;
            i = 14;
            continue;
            break label254;
            break label11;
            if (this == paramObject)
            {
              break label280;
              i = 75;
              continue;
              break label65;
              i = 53;
            }
            break;
          }
        }
      }
    }
    
    public int hashCode()
    {
      break label42;
      int j = 67;
      break label157;
      j = ʻ + 117;
      ʽ = j % 128;
      int i;
      label42:
      label45:
      label48:
      String str;
      if (j % 2 != 0)
      {
        break label144;
        for (;;)
        {
          i = 30;
          break label187;
          break label48;
          break label106;
          str = this.dateTime;
          if (str == null)
          {
            i = 0;
            label62:
            str = this.value;
            if (str != null) {
              break;
            }
            break label124;
          }
          i = ʻ + 5;
          ʽ = i % 128;
          if (i % 2 == 0) {
            break label130;
          }
        }
      }
      else
      {
        break label144;
        label106:
        return i * 31 + j;
        i = str.hashCode();
        j = null.length;
        break label141;
        label124:
        j = 54;
        break label157;
        label130:
        i = 23;
        break label187;
      }
      for (;;)
      {
        i = str.hashCode();
        label141:
        break label62;
        label144:
        j = str.hashCode();
        break label45;
        j = 0;
        break label106;
        label157:
        switch (j)
        {
        }
        break;
        label187:
        switch (i)
        {
        }
      }
    }
    
    public String toString()
    {
      break label5;
      String str;
      return str;
      for (;;)
      {
        label5:
        int i = ʻ + 109;
        ʽ = i % 128;
        if (i % 2 == 0) {
          break;
        }
        return str;
        str = ˎ((short)0, 393390645, (byte)68, -1159132639, -34).intern() + this.dateTime + ˎ((short)0, 393390660, (byte)-85, -1159132678, -34).intern() + this.value + ˎ((short)0, 393390668, (byte)69, -1159132681, -34).intern();
      }
    }
    
    /* Error */
    public final String ˏ()
    {
      // Byte code:
      //   0: goto +35 -> 35
      //   3: astore_2
      //   4: aload_2
      //   5: athrow
      //   6: getstatic 26	o/Gp$iF:ʽ	I
      //   9: istore_1
      //   10: iload_1
      //   11: bipush 13
      //   13: iadd
      //   14: istore_1
      //   15: iload_1
      //   16: sipush 128
      //   19: irem
      //   20: putstatic 24	o/Gp$iF:ʻ	I
      //   23: iload_1
      //   24: iconst_2
      //   25: irem
      //   26: ifeq +6 -> 32
      //   29: goto +9 -> 38
      //   32: goto +60 -> 92
      //   35: goto +9 -> 44
      //   38: bipush 40
      //   40: istore_1
      //   41: goto +60 -> 101
      //   44: getstatic 24	o/Gp$iF:ʻ	I
      //   47: bipush 57
      //   49: iadd
      //   50: istore_1
      //   51: iload_1
      //   52: sipush 128
      //   55: irem
      //   56: putstatic 26	o/Gp$iF:ʽ	I
      //   59: iload_1
      //   60: iconst_2
      //   61: irem
      //   62: ifne +6 -> 68
      //   65: goto +33 -> 98
      //   68: goto +8 -> 76
      //   71: astore_2
      //   72: aload_2
      //   73: athrow
      //   74: aload_2
      //   75: areturn
      //   76: aload_0
      //   77: getfield 91	o/Gp$iF:value	Ljava/lang/String;
      //   80: astore_2
      //   81: goto -75 -> 6
      //   84: new 75	java/lang/NullPointerException
      //   87: dup
      //   88: invokespecial 76	java/lang/NullPointerException:<init>	()V
      //   91: athrow
      //   92: bipush 8
      //   94: istore_1
      //   95: goto +6 -> 101
      //   98: goto -22 -> 76
      //   101: iload_1
      //   102: lookupswitch	default:+26->128, 8:+-28->74, 40:+-18->84
      //   128: aload_2
      //   129: areturn
      // Local variable table:
      //   start	length	slot	name	signature
      //   0	130	0	this	iF
      //   9	93	1	i	int
      //   3	2	2	localException1	Exception
      //   71	4	2	localException2	Exception
      //   80	49	2	str	String
      // Exception table:
      //   from	to	target	type
      //   15	23	3	java/lang/Exception
      //   6	10	71	java/lang/Exception
    }
  }
}
