package o;

import android.content.res.Resources;
import android.databinding.ViewDataBinding;
import android.databinding.ViewDataBinding.If;
import android.text.TextUtils;
import android.util.SparseIntArray;
import android.widget.ImageView;
import android.widget.RelativeLayout;
import android.widget.TextView;
import java.io.UnsupportedEncodingException;

public class GV
  extends ViewDataBinding
{
  private static final ViewDataBinding.If ʻ;
  private static int ʼॱ;
  private static final SparseIntArray ʽ;
  private static int ʽॱ;
  private static int ʾ;
  private static byte ᐝॱ;
  private int ʻॱ;
  private final RelativeLayout ʼ;
  public final TextView ˊ;
  private String ˊॱ;
  private int ˋॱ;
  public final Ґ ˎ;
  private String ˏॱ;
  private FC ͺ;
  public final ﹾ ॱ;
  private String ॱˊ;
  private long ॱˋ;
  private int ॱˎ;
  public final ImageView ॱॱ;
  private ˍ ॱᐝ;
  private final TextView ᐝ;
  
  /* Error */
  static
  {
    // Byte code:
    //   0: goto +6 -> 6
    //   3: astore_1
    //   4: aload_1
    //   5: athrow
    //   6: iconst_0
    //   7: putstatic 46	o/GV:ʼॱ	I
    //   10: iconst_1
    //   11: putstatic 48	o/GV:ʽॱ	I
    //   14: invokestatic 50	o/GV:ॱᐝ	()V
    //   17: invokestatic 52	o/GV:ॱˋ	()V
    //   20: aconst_null
    //   21: putstatic 54	o/GV:ʻ	Landroid/databinding/ViewDataBinding$If;
    //   24: aconst_null
    //   25: putstatic 56	o/GV:ʽ	Landroid/util/SparseIntArray;
    //   28: getstatic 46	o/GV:ʼॱ	I
    //   31: bipush 61
    //   33: iadd
    //   34: istore_0
    //   35: iload_0
    //   36: sipush 128
    //   39: irem
    //   40: putstatic 48	o/GV:ʽॱ	I
    //   43: iload_0
    //   44: iconst_2
    //   45: irem
    //   46: ifne +4 -> 50
    //   49: return
    //   50: return
    // Local variable table:
    //   start	length	slot	name	signature
    //   34	12	0	i	int
    //   3	2	1	localException	Exception
    // Exception table:
    //   from	to	target	type
    //   28	35	3	java/lang/Exception
    //   35	43	3	java/lang/Exception
  }
  
  /* Error */
  public GV(ˉ paramˉ, android.view.View paramView)
  {
    // Byte code:
    //   0: goto +6 -> 6
    //   3: astore_1
    //   4: aload_1
    //   5: athrow
    //   6: aload_0
    //   7: aload_1
    //   8: aload_2
    //   9: iconst_0
    //   10: invokespecial 62	android/databinding/ViewDataBinding:<init>	(Lo/ˉ;Landroid/view/View;I)V
    //   13: new 6	o/GV$2
    //   16: dup
    //   17: aload_0
    //   18: invokespecial 65	o/GV$2:<init>	(Lo/GV;)V
    //   21: astore_3
    //   22: aload_0
    //   23: aload_3
    //   24: putfield 67	o/GV:ॱᐝ	Lo/ˍ;
    //   27: aload_0
    //   28: ldc2_w 68
    //   31: putfield 71	o/GV:ॱˋ	J
    //   34: getstatic 54	o/GV:ʻ	Landroid/databinding/ViewDataBinding$If;
    //   37: astore_3
    //   38: aload_1
    //   39: aload_2
    //   40: bipush 6
    //   42: aload_3
    //   43: getstatic 56	o/GV:ʽ	Landroid/util/SparseIntArray;
    //   46: invokestatic 74	o/GV:ॱ	(Lo/ˉ;Landroid/view/View;ILandroid/databinding/ViewDataBinding$If;Landroid/util/SparseIntArray;)[Ljava/lang/Object;
    //   49: astore_1
    //   50: aload_0
    //   51: aload_1
    //   52: iconst_2
    //   53: aaload
    //   54: checkcast 76	o/Ґ
    //   57: putfield 78	o/GV:ˎ	Lo/Ґ;
    //   60: aload_0
    //   61: getfield 78	o/GV:ˎ	Lo/Ґ;
    //   64: aconst_null
    //   65: invokevirtual 82	o/Ґ:setTag	(Ljava/lang/Object;)V
    //   68: aload_0
    //   69: aload_1
    //   70: iconst_1
    //   71: aaload
    //   72: checkcast 84	o/ﹾ
    //   75: putfield 86	o/GV:ॱ	Lo/ﹾ;
    //   78: aload_0
    //   79: getfield 86	o/GV:ॱ	Lo/ﹾ;
    //   82: aconst_null
    //   83: invokevirtual 87	o/ﹾ:setTag	(Ljava/lang/Object;)V
    //   86: aload_0
    //   87: aload_1
    //   88: iconst_0
    //   89: aaload
    //   90: checkcast 89	android/widget/RelativeLayout
    //   93: putfield 91	o/GV:ʼ	Landroid/widget/RelativeLayout;
    //   96: aload_0
    //   97: getfield 91	o/GV:ʼ	Landroid/widget/RelativeLayout;
    //   100: aconst_null
    //   101: invokevirtual 92	android/widget/RelativeLayout:setTag	(Ljava/lang/Object;)V
    //   104: aload_0
    //   105: aload_1
    //   106: iconst_5
    //   107: aaload
    //   108: checkcast 94	android/widget/TextView
    //   111: putfield 96	o/GV:ᐝ	Landroid/widget/TextView;
    //   114: aload_0
    //   115: getfield 96	o/GV:ᐝ	Landroid/widget/TextView;
    //   118: aconst_null
    //   119: invokevirtual 97	android/widget/TextView:setTag	(Ljava/lang/Object;)V
    //   122: aload_0
    //   123: aload_1
    //   124: iconst_4
    //   125: aaload
    //   126: checkcast 94	android/widget/TextView
    //   129: putfield 99	o/GV:ˊ	Landroid/widget/TextView;
    //   132: aload_0
    //   133: getfield 99	o/GV:ˊ	Landroid/widget/TextView;
    //   136: aconst_null
    //   137: invokevirtual 97	android/widget/TextView:setTag	(Ljava/lang/Object;)V
    //   140: aload_0
    //   141: aload_1
    //   142: iconst_3
    //   143: aaload
    //   144: checkcast 101	android/widget/ImageView
    //   147: putfield 103	o/GV:ॱॱ	Landroid/widget/ImageView;
    //   150: aload_0
    //   151: getfield 103	o/GV:ॱॱ	Landroid/widget/ImageView;
    //   154: aconst_null
    //   155: invokevirtual 104	android/widget/ImageView:setTag	(Ljava/lang/Object;)V
    //   158: aload_0
    //   159: aload_2
    //   160: invokevirtual 108	o/GV:ˋ	(Landroid/view/View;)V
    //   163: aload_0
    //   164: invokevirtual 110	o/GV:ˊॱ	()V
    //   167: return
    //   168: astore_1
    //   169: aload_1
    //   170: athrow
    // Local variable table:
    //   start	length	slot	name	signature
    //   0	171	0	this	GV
    //   0	171	1	paramˉ	ˉ
    //   0	171	2	paramView	android.view.View
    //   21	22	3	localObject	Object
    // Exception table:
    //   from	to	target	type
    //   27	34	3	java/lang/Exception
    //   22	27	168	java/lang/Exception
    //   27	34	168	java/lang/Exception
    //   34	38	168	java/lang/Exception
    //   38	167	168	java/lang/Exception
  }
  
  private String ˋ(String paramString)
  {
    for (;;)
    {
      try
      {
        paramString[i] = ((byte)(arrayOfByte[(arrayOfByte.length - i - 1)] ^ ᐝॱ));
        i += 1;
      }
      catch (UnsupportedEncodingException paramString)
      {
        throw new RuntimeException(paramString);
      }
      byte[] arrayOfByte = paramString.getBytes(ˎ(6, 44, new char[] { -2, -6, -3, -3, -14, 20, 24, 14, -10, -14 }, 115, false).intern());
      paramString = new byte[arrayOfByte.length];
      int i = 1;
      break label326;
      i = 13;
      switch (i)
      {
      case 13: 
      default: 
        label129:
        continue;
        paramString = new String(paramString, ˎ(122, 5, new char[] { 16, 17, -12, -23, 2 }, 2, true).intern());
        return paramString;
      }
      int j;
      label326:
      label371:
      label377:
      label383:
      do
      {
        paramString[i] = ((byte)(arrayOfByte[(arrayOfByte.length % i << 1)] & ᐝॱ));
        i += 71;
        do
        {
          j = 60;
          break;
          arrayOfByte = paramString.getBytes(ˎ(113, 10, new char[] { -2, -6, -3, -3, -14, 20, 24, 14, -10, -14 }, 8, true).intern());
          paramString = new byte[arrayOfByte.length];
          i = 0;
          j = arrayOfByte.length;
        } while (i < j);
        break label371;
        for (;;)
        {
          i = ʼॱ + 55;
          ʽॱ = i % 128;
          if (i % 2 == 0) {
            break;
          }
          break label377;
        }
        j = 12;
        break label383;
        i = 62;
        break label129;
        switch (j)
        {
        case 12: 
        default: 
          break;
        case 60: 
          j = ʼॱ + 115;
          ʽॱ = j % 128;
        }
      } while (j % 2 == 0);
    }
  }
  
  /* Error */
  private static String ˎ(int paramInt1, int paramInt2, char[] paramArrayOfChar, int paramInt3, boolean paramBoolean)
  {
    // Byte code:
    //   0: goto +171 -> 171
    //   3: iload_3
    //   4: ifle +6 -> 10
    //   7: goto +18 -> 25
    //   10: goto +290 -> 300
    //   13: new 128	java/lang/String
    //   16: dup
    //   17: aload_2
    //   18: invokespecial 152	java/lang/String:<init>	([C)V
    //   21: areturn
    //   22: goto +42 -> 64
    //   25: getstatic 48	o/GV:ʽॱ	I
    //   28: bipush 105
    //   30: iadd
    //   31: istore_0
    //   32: iload_0
    //   33: sipush 128
    //   36: irem
    //   37: putstatic 46	o/GV:ʼॱ	I
    //   40: iload_0
    //   41: iconst_2
    //   42: irem
    //   43: ifeq +6 -> 49
    //   46: goto +251 -> 297
    //   49: goto +283 -> 332
    //   52: iload 5
    //   54: iload_1
    //   55: if_icmpge +6 -> 61
    //   58: goto +83 -> 141
    //   61: goto +221 -> 282
    //   64: iload_0
    //   65: iload_1
    //   66: if_icmpge +6 -> 72
    //   69: goto +132 -> 201
    //   72: goto +301 -> 373
    //   75: aload 8
    //   77: iload 5
    //   79: iload_0
    //   80: aload_2
    //   81: iload 5
    //   83: caload
    //   84: iadd
    //   85: i2c
    //   86: castore
    //   87: aload 8
    //   89: iload 5
    //   91: caload
    //   92: istore 6
    //   94: getstatic 154	o/GV:ʾ	I
    //   97: istore 7
    //   99: aload 8
    //   101: iload 5
    //   103: iload 6
    //   105: iload 7
    //   107: isub
    //   108: i2c
    //   109: castore
    //   110: iload 5
    //   112: iconst_1
    //   113: iadd
    //   114: istore 5
    //   116: goto -64 -> 52
    //   119: astore_2
    //   120: aload_2
    //   121: athrow
    //   122: aload_2
    //   123: iload_0
    //   124: aload 8
    //   126: iload_1
    //   127: iload_0
    //   128: iadd
    //   129: iconst_1
    //   130: irem
    //   131: caload
    //   132: castore
    //   133: iload_0
    //   134: bipush 11
    //   136: iadd
    //   137: istore_0
    //   138: goto -116 -> 22
    //   141: iconst_1
    //   142: istore 6
    //   144: iload 6
    //   146: tableswitch	default:+22->168, 0:+-143->3, 1:+-71->75
    //   168: goto -93 -> 75
    //   171: goto +100 -> 271
    //   174: getstatic 46	o/GV:ʼॱ	I
    //   177: bipush 125
    //   179: iadd
    //   180: istore_0
    //   181: iload_0
    //   182: sipush 128
    //   185: irem
    //   186: putstatic 48	o/GV:ʽॱ	I
    //   189: iload_0
    //   190: iconst_2
    //   191: irem
    //   192: ifne +6 -> 198
    //   195: goto +99 -> 294
    //   198: goto +172 -> 370
    //   201: getstatic 46	o/GV:ʼॱ	I
    //   204: bipush 95
    //   206: iadd
    //   207: istore_3
    //   208: iload_3
    //   209: sipush 128
    //   212: irem
    //   213: putstatic 48	o/GV:ʽॱ	I
    //   216: iload_3
    //   217: iconst_2
    //   218: irem
    //   219: ifne +6 -> 225
    //   222: goto +154 -> 376
    //   225: goto +63 -> 288
    //   228: iload_3
    //   229: lookupswitch	default:+27->256, 31:+-107->122, 56:+85->314
    //   256: goto -134 -> 122
    //   259: astore_2
    //   260: aload_2
    //   261: athrow
    //   262: iload_1
    //   263: newarray char
    //   265: astore_2
    //   266: iconst_0
    //   267: istore_0
    //   268: goto -204 -> 64
    //   271: iload_1
    //   272: newarray char
    //   274: astore 8
    //   276: iconst_0
    //   277: istore 5
    //   279: goto -227 -> 52
    //   282: iconst_0
    //   283: istore 6
    //   285: goto -141 -> 144
    //   288: bipush 56
    //   290: istore_3
    //   291: goto -63 -> 228
    //   294: goto +76 -> 370
    //   297: goto +35 -> 332
    //   300: iload 4
    //   302: ifeq +6 -> 308
    //   305: goto -43 -> 262
    //   308: aload 8
    //   310: astore_2
    //   311: goto -298 -> 13
    //   314: aload_2
    //   315: iload_0
    //   316: aload 8
    //   318: iload_1
    //   319: iload_0
    //   320: isub
    //   321: iconst_1
    //   322: isub
    //   323: caload
    //   324: castore
    //   325: iload_0
    //   326: iconst_1
    //   327: iadd
    //   328: istore_0
    //   329: goto -307 -> 22
    //   332: iload_1
    //   333: newarray char
    //   335: astore_2
    //   336: aload 8
    //   338: iconst_0
    //   339: aload_2
    //   340: iconst_0
    //   341: iload_1
    //   342: invokestatic 160	java/lang/System:arraycopy	(Ljava/lang/Object;ILjava/lang/Object;II)V
    //   345: aload_2
    //   346: iconst_0
    //   347: aload 8
    //   349: iload_1
    //   350: iload_3
    //   351: isub
    //   352: iload_3
    //   353: invokestatic 160	java/lang/System:arraycopy	(Ljava/lang/Object;ILjava/lang/Object;II)V
    //   356: aload_2
    //   357: iload_3
    //   358: aload 8
    //   360: iconst_0
    //   361: iload_1
    //   362: iload_3
    //   363: isub
    //   364: invokestatic 160	java/lang/System:arraycopy	(Ljava/lang/Object;ILjava/lang/Object;II)V
    //   367: goto -193 -> 174
    //   370: goto -70 -> 300
    //   373: goto -360 -> 13
    //   376: bipush 31
    //   378: istore_3
    //   379: goto -151 -> 228
    // Local variable table:
    //   start	length	slot	name	signature
    //   0	382	0	paramInt1	int
    //   0	382	1	paramInt2	int
    //   0	382	2	paramArrayOfChar	char[]
    //   0	382	3	paramInt3	int
    //   0	382	4	paramBoolean	boolean
    //   52	226	5	i	int
    //   92	192	6	j	int
    //   97	11	7	k	int
    //   75	284	8	arrayOfChar	char[]
    // Exception table:
    //   from	to	target	type
    //   201	208	119	java/lang/Exception
    //   208	216	119	java/lang/Exception
    //   94	99	259	java/lang/Exception
  }
  
  static void ॱˋ()
  {
    break label111;
    ᐝॱ = -102;
    label106:
    label111:
    for (;;)
    {
      int i;
      try
      {
        i = ʽॱ;
        i += 73;
        try
        {
          ʼॱ = i % 128;
          if (i % 2 != 0) {
            return;
          }
          return;
        }
        catch (Exception localException1)
        {
          throw localException1;
        }
        i = ʽॱ + 55;
        ʼॱ = i % 128;
        if (i % 2 != 0) {
          break label106;
        }
      }
      catch (Exception localException2)
      {
        throw localException2;
      }
      switch (i)
      {
      case 0: 
      default: 
        break;
        i = 0;
        break;
      case 1: 
        ᐝॱ = 51;
        continue;
        i = 1;
      }
    }
  }
  
  static void ॱᐝ()
  {
    ʾ = 54;
  }
  
  public void ˊॱ()
  {
    try
    {
      this.ॱˋ = 128L;
    }
    finally
    {
      localObject = finally;
      throw localObject;
    }
    ʽ();
  }
  
  public void ˋ(int paramInt)
  {
    this.ॱˎ = paramInt;
    try
    {
      this.ॱˋ |= 0x40;
    }
    finally
    {
      localObject = finally;
      throw localObject;
    }
    ˊ(91);
    super.ʽ();
  }
  
  public void ˋ(FC paramFC)
  {
    this.ͺ = paramFC;
    try
    {
      this.ॱˋ |= 0x8;
    }
    finally
    {
      paramFC = finally;
      throw paramFC;
    }
    ˊ(133);
    super.ʽ();
  }
  
  /* Error */
  public int ˋॱ()
  {
    // Byte code:
    //   0: goto +56 -> 56
    //   3: getstatic 46	o/GV:ʼॱ	I
    //   6: bipush 69
    //   8: iadd
    //   9: istore_1
    //   10: iload_1
    //   11: sipush 128
    //   14: irem
    //   15: putstatic 48	o/GV:ʽॱ	I
    //   18: iload_1
    //   19: iconst_2
    //   20: irem
    //   21: ifne +6 -> 27
    //   24: goto +35 -> 59
    //   27: iload_2
    //   28: ireturn
    //   29: getstatic 46	o/GV:ʼॱ	I
    //   32: bipush 11
    //   34: iadd
    //   35: istore_1
    //   36: iload_1
    //   37: sipush 128
    //   40: irem
    //   41: putstatic 48	o/GV:ʽॱ	I
    //   44: iload_1
    //   45: iconst_2
    //   46: irem
    //   47: ifne +6 -> 53
    //   50: goto +14 -> 64
    //   53: goto +11 -> 64
    //   56: goto -27 -> 29
    //   59: iload_2
    //   60: ireturn
    //   61: astore_3
    //   62: aload_3
    //   63: athrow
    //   64: aload_0
    //   65: getfield 188	o/GV:ˋॱ	I
    //   68: istore_2
    //   69: goto -66 -> 3
    // Local variable table:
    //   start	length	slot	name	signature
    //   0	72	0	this	GV
    //   9	38	1	i	int
    //   27	42	2	j	int
    //   61	2	3	localException	Exception
    // Exception table:
    //   from	to	target	type
    //   64	69	61	java/lang/Exception
  }
  
  public void ˎ(int paramInt)
  {
    this.ʻॱ = paramInt;
    try
    {
      this.ॱˋ |= 0x20;
    }
    finally
    {
      localObject = finally;
      throw localObject;
    }
    ˊ(53);
    super.ʽ();
  }
  
  public void ˎ(String paramString)
  {
    this.ˊॱ = paramString;
    try
    {
      this.ॱˋ |= 0x2;
    }
    finally
    {
      paramString = finally;
      throw paramString;
    }
    ˊ(52);
    super.ʽ();
  }
  
  public void ˏ()
  {
    try
    {
      l2 = this.ॱˋ;
      this.ॱˋ = 0L;
    }
    finally
    {
      localObject1 = finally;
      throw localObject1;
    }
    int k = 0;
    int j = 0;
    int i2 = 0;
    Object localObject3 = this.ॱˊ;
    Object localObject2 = this.ˊॱ;
    int m = 0;
    float f = 0.0F;
    String str = this.ˏॱ;
    FC localFC = this.ͺ;
    String[] arrayOfString = null;
    int i3 = this.ˋॱ;
    int i = 0;
    int i4 = this.ʻॱ;
    int n = 0;
    int i5 = this.ॱˎ;
    boolean bool = false;
    int i1 = 0;
    long l1 = l2;
    if ((0x81 & l2) != 0L)
    {
      if (!TextUtils.isEmpty((CharSequence)localObject3)) {
        i = 1;
      } else {
        i = 0;
      }
      l1 = l2;
      if ((0x81 & l2) != 0L) {
        if (i != 0) {
          l1 = l2 | 0x2000 | 0x8000;
        } else {
          l1 = l2 | 0x1000 | 0x4000;
        }
      }
      if (i != 0) {
        f = this.ˎ.getResources().getDimension(2131165312);
      } else {
        f = this.ˎ.getResources().getDimension(2131165323);
      }
      if (i != 0) {
        i = 0;
      } else {
        i = 8;
      }
    }
    long l2 = l1;
    if ((0x88 & l1) != 0L)
    {
      j = i2;
      if (localFC != null)
      {
        j = localFC.validationErrorStringRes;
        bool = localFC.isValid;
      }
      l2 = l1;
      if ((0x88 & l1) != 0L) {
        if (bool) {
          l2 = l1 | 0x200 | 0x800 | 0x20000 | 0x80000;
        } else {
          l2 = l1 | 0x100 | 0x400 | 0x10000 | 0x40000;
        }
      }
      if (bool) {
        k = ˋ(this.ॱॱ, 2131099680);
      } else {
        k = ˋ(this.ॱॱ, 2131099780);
      }
      if (bool) {
        m = ˋ(this.ˎ, 2131099680);
      } else {
        m = ˋ(this.ˎ, 2131099780);
      }
      if (bool) {
        n = ˋ(this.ˊ, 2131099680);
      } else {
        n = ˋ(this.ˊ, 2131099780);
      }
      if (bool) {
        i1 = 4;
      } else {
        i1 = 0;
      }
    }
    if ((0xD0 & l2) != 0L) {
      arrayOfString = aq.ˏ(new String[] { String.valueOf(i3), String.valueOf(i5) });
    }
    if (((0xA0 & l2) != 0L) && (ˊ() >= 3)) {
      this.ˎ.setInputType(i4);
    }
    if ((0x81 & l2) != 0L)
    {
      ՙ.ˏ(this.ˎ, f);
      ՙ.ॱ(this.ˎ, f);
      this.ॱॱ.setVisibility(i);
    }
    if ((0x82 & l2) != 0L) {
      ʹ.ˊ(this.ˎ, (CharSequence)localObject2);
    }
    if ((0x88 & l2) != 0L)
    {
      this.ˎ.setTextColor(m);
      z.ॱ(this.ᐝ, j);
      this.ᐝ.setVisibility(i1);
      this.ˊ.setTextColor(n);
      r.ˋ(this.ॱॱ, null, k);
    }
    if ((0x80 & l2) != 0L) {
      ʹ.ˏ(this.ˎ, null, null, null, this.ॱᐝ);
    }
    if ((0x84 & l2) != 0L) {
      this.ॱ.setHint(str);
    }
    if ((0xD0 & l2) != 0L)
    {
      localObject3 = this.ˊ;
      str = this.ˊ.getResources().getString(2131755163);
      localObject2 = str;
      if (str.startsWith(ˎ(67, 4, new char[] { -2, -1, -8, 13 }, 2, false).intern())) {
        localObject2 = ˋ(str.substring(4)).intern();
      }
      z.ॱ((TextView)localObject3, (String)localObject2, arrayOfString);
    }
  }
  
  public void ˏ(String paramString)
  {
    this.ˏॱ = paramString;
    try
    {
      this.ॱˋ |= 0x4;
    }
    finally
    {
      paramString = finally;
      throw paramString;
    }
    ˊ(47);
    super.ʽ();
  }
  
  public boolean ˏ(int paramInt1, Object paramObject, int paramInt2)
  {
    for (;;)
    {
      paramInt1 = ʽॱ + 29;
      ʼॱ = paramInt1 % 128;
      if (paramInt1 % 2 == 0)
      {
        break label62;
        return false;
      }
      for (;;)
      {
        try
        {
          paramInt1 = ʼॱ + 73;
          ʽॱ = paramInt1 % 128;
          if (paramInt1 % 2 == 0) {
            break;
          }
        }
        catch (Exception paramObject)
        {
          label62:
          throw paramObject;
        }
      }
    }
  }
  
  /* Error */
  public int ˏॱ()
  {
    // Byte code:
    //   0: goto +18 -> 18
    //   3: bipush 79
    //   5: iconst_0
    //   6: idiv
    //   7: istore_1
    //   8: iload_2
    //   9: ireturn
    //   10: iload_2
    //   11: ireturn
    //   12: bipush 61
    //   14: istore_1
    //   15: goto +9 -> 24
    //   18: goto +44 -> 62
    //   21: astore_3
    //   22: aload_3
    //   23: athrow
    //   24: iload_1
    //   25: lookupswitch	default:+27->52, 50:+-22->3, 61:+-15->10
    //   52: iload_2
    //   53: ireturn
    //   54: aload_0
    //   55: getfield 175	o/GV:ॱˎ	I
    //   58: istore_2
    //   59: goto +33 -> 92
    //   62: getstatic 48	o/GV:ʽॱ	I
    //   65: bipush 67
    //   67: iadd
    //   68: istore_1
    //   69: iload_1
    //   70: sipush 128
    //   73: irem
    //   74: putstatic 46	o/GV:ʼॱ	I
    //   77: iload_1
    //   78: iconst_2
    //   79: irem
    //   80: ifeq +6 -> 86
    //   83: goto +6 -> 89
    //   86: goto -32 -> 54
    //   89: goto -35 -> 54
    //   92: getstatic 48	o/GV:ʽॱ	I
    //   95: bipush 43
    //   97: iadd
    //   98: istore_1
    //   99: iload_1
    //   100: sipush 128
    //   103: irem
    //   104: putstatic 46	o/GV:ʼॱ	I
    //   107: iload_1
    //   108: iconst_2
    //   109: irem
    //   110: ifeq +6 -> 116
    //   113: goto +6 -> 119
    //   116: goto -104 -> 12
    //   119: bipush 50
    //   121: istore_1
    //   122: goto -98 -> 24
    // Local variable table:
    //   start	length	slot	name	signature
    //   0	125	0	this	GV
    //   7	115	1	i	int
    //   8	51	2	j	int
    //   21	2	3	localException	Exception
    // Exception table:
    //   from	to	target	type
    //   54	59	21	java/lang/Exception
  }
  
  /* Error */
  public String ͺ()
  {
    // Byte code:
    //   0: goto +3 -> 3
    //   3: goto +31 -> 34
    //   6: goto +58 -> 64
    //   9: getstatic 48	o/GV:ʽॱ	I
    //   12: bipush 55
    //   14: iadd
    //   15: istore_1
    //   16: iload_1
    //   17: sipush 128
    //   20: irem
    //   21: putstatic 46	o/GV:ʼॱ	I
    //   24: iload_1
    //   25: iconst_2
    //   26: irem
    //   27: ifeq +5 -> 32
    //   30: aload_2
    //   31: areturn
    //   32: aload_2
    //   33: areturn
    //   34: getstatic 46	o/GV:ʼॱ	I
    //   37: bipush 49
    //   39: iadd
    //   40: istore_1
    //   41: iload_1
    //   42: sipush 128
    //   45: irem
    //   46: putstatic 48	o/GV:ʽॱ	I
    //   49: iload_1
    //   50: iconst_2
    //   51: irem
    //   52: ifne +6 -> 58
    //   55: goto -49 -> 6
    //   58: goto +6 -> 64
    //   61: astore_2
    //   62: aload_2
    //   63: athrow
    //   64: aload_0
    //   65: getfield 197	o/GV:ॱˊ	Ljava/lang/String;
    //   68: astore_2
    //   69: goto -60 -> 9
    // Local variable table:
    //   start	length	slot	name	signature
    //   0	72	0	this	GV
    //   15	37	1	i	int
    //   30	3	2	str1	String
    //   61	2	2	localException	Exception
    //   68	1	2	str2	String
    // Exception table:
    //   from	to	target	type
    //   64	69	61	java/lang/Exception
  }
  
  public void ॱ(int paramInt)
  {
    this.ˋॱ = paramInt;
    try
    {
      this.ॱˋ |= 0x10;
    }
    finally
    {
      localObject = finally;
      throw localObject;
    }
    ˊ(51);
    super.ʽ();
  }
  
  public void ॱ(String paramString)
  {
    this.ॱˊ = paramString;
    try
    {
      this.ॱˋ |= 1L;
    }
    finally
    {
      paramString = finally;
      throw paramString;
    }
    ˊ(126);
    super.ʽ();
  }
  
  public boolean ॱ()
  {
    try
    {
      long l = this.ॱˋ;
      if (l != 0L) {
        return true;
      }
    }
    finally
    {
      localObject = finally;
      throw localObject;
    }
    return false;
  }
  
  public String ॱˊ()
  {
    break label175;
    int i;
    switch (i)
    {
    default: 
      break;
    }
    label136:
    label175:
    for (;;)
    {
      try
      {
        String str = this.ˊॱ;
        continue;
        i = 91;
        break;
        str = this.ˊॱ;
        throw new NullPointerException();
        i = null.length;
        return str;
        i = ʼॱ + 79;
        ʽॱ = i % 128;
        if (i % 2 != 0)
        {
          continue;
          i = 98;
          break label136;
        }
        i = 34;
      }
      catch (Exception localException)
      {
        throw localException;
      }
      i = ʼॱ + 11;
      ʽॱ = i % 128;
      if (i % 2 != 0) {
        for (;;)
        {
          switch (i)
          {
          }
          break;
          return localException;
          i = 34;
        }
      }
    }
  }
}
