package o;

import android.content.Context;
import java.util.concurrent.Callable;

public final class Gz
  extends GD
{
  private static int ʻ;
  private static long ˊ;
  private static char[] ˋ;
  public static final ˊ ˎ;
  private static boolean ˏ;
  private static int ॱॱ;
  private final Context ॱ;
  
  /* Error */
  static
  {
    // Byte code:
    //   0: goto +50 -> 50
    //   3: getstatic 51	o/Gz:ʻ	I
    //   6: istore_0
    //   7: iload_0
    //   8: bipush 40
    //   10: ixor
    //   11: iload_0
    //   12: bipush 40
    //   14: iand
    //   15: iconst_1
    //   16: ishl
    //   17: iadd
    //   18: iconst_1
    //   19: isub
    //   20: istore_0
    //   21: iload_0
    //   22: sipush 128
    //   25: irem
    //   26: putstatic 53	o/Gz:ॱॱ	I
    //   29: iload_0
    //   30: iconst_2
    //   31: irem
    //   32: ifeq +6 -> 38
    //   35: goto +6 -> 41
    //   38: goto +81 -> 119
    //   41: bipush 77
    //   43: istore_0
    //   44: goto +44 -> 88
    //   47: astore_1
    //   48: aload_1
    //   49: athrow
    //   50: iconst_0
    //   51: putstatic 53	o/Gz:ॱॱ	I
    //   54: iconst_1
    //   55: putstatic 51	o/Gz:ʻ	I
    //   58: invokestatic 56	o/Gz:ʽ	()V
    //   61: new 16	o/Gz$ˊ
    //   64: dup
    //   65: aconst_null
    //   66: invokespecial 60	o/Gz$ˊ:<init>	(Lo/vn;)V
    //   69: astore_1
    //   70: goto -67 -> 3
    //   73: aload_1
    //   74: putstatic 62	o/Gz:ˎ	Lo/Gz$ˊ;
    //   77: return
    //   78: aload_1
    //   79: putstatic 62	o/Gz:ˎ	Lo/Gz$ˊ;
    //   82: bipush 42
    //   84: iconst_0
    //   85: idiv
    //   86: istore_0
    //   87: return
    //   88: iload_0
    //   89: lookupswitch	default:+27->116, 15:+-16->73, 77:+-11->78
    //   116: goto -43 -> 73
    //   119: bipush 15
    //   121: istore_0
    //   122: goto -34 -> 88
    //   125: astore_1
    //   126: aload_1
    //   127: athrow
    // Local variable table:
    //   start	length	slot	name	signature
    //   6	116	0	i	int
    //   47	2	1	localRuntimeException	RuntimeException
    //   69	10	1	localˊ	ˊ
    //   125	2	1	localNumberFormatException	NumberFormatException
    // Exception table:
    //   from	to	target	type
    //   54	58	47	java/lang/RuntimeException
    //   58	61	47	java/lang/ArrayStoreException
    //   78	87	47	java/lang/NumberFormatException
    //   3	7	125	java/lang/NumberFormatException
    //   21	29	125	java/lang/NullPointerException
    //   50	54	125	java/lang/IllegalStateException
    //   54	58	125	java/lang/IllegalStateException
    //   58	61	125	java/lang/IllegalStateException
    //   61	70	125	java/lang/IllegalStateException
    //   73	77	125	java/lang/UnsupportedOperationException
  }
  
  /* Error */
  private Gz(Context paramContext)
  {
    // Byte code:
    //   0: goto +6 -> 6
    //   3: astore_1
    //   4: aload_1
    //   5: athrow
    //   6: aload_0
    //   7: invokespecial 68	o/GD:<init>	()V
    //   10: aload_0
    //   11: aload_1
    //   12: putfield 70	o/Gz:ॱ	Landroid/content/Context;
    //   15: return
    // Local variable table:
    //   start	length	slot	name	signature
    //   0	16	0	this	Gz
    //   0	16	1	paramContext	Context
    // Exception table:
    //   from	to	target	type
    //   10	15	3	java/lang/Exception
  }
  
  private final st<Object> ʼ(int paramInt)
  {
    for (;;)
    {
      try
      {
        localObject1 = st.ˏ((Callable)localObject1);
      }
      catch (IndexOutOfBoundsException localIndexOutOfBoundsException)
      {
        Object localObject1;
        String str;
        throw localIndexOutOfBoundsException;
      }
      try
      {
        str = ˋ(38, 57865, 50);
        str = str.intern();
        vq.ˋ(localObject1, str);
      }
      catch (ClassCastException|IndexOutOfBoundsException|NumberFormatException|RuntimeException|IllegalArgumentException localClassCastException)
      {
        int i;
        throw localClassCastException;
      }
      continue;
      break;
      label47:
      continue;
      i = ॱॱ;
      paramInt = (i | 0x51) << 1;
      i = -(i & 0xFFFFFFAE | (i ^ 0xFFFFFFFF) & 0x51);
      paramInt = ((paramInt | i) << 1) - (paramInt ^ i);
      ʻ = paramInt % 128;
      if (paramInt % 2 == 0) {}
    }
    for (;;)
    {
      i = ʻ;
      paramInt = i & 0x2F;
      i = i & 0x2F | i ^ 0x2F;
      paramInt = ((paramInt | i) << 1) - (paramInt ^ i);
      ॱॱ = paramInt % 128;
      if (paramInt % 2 != 0) {
        break label47;
      }
      break;
      Object localObject2 = new aux(this, paramInt);
      localObject2 = (Callable)localObject2;
    }
    paramInt = ʻ;
    paramInt = (paramInt & 0xF) + (paramInt | 0xF);
    ॱॱ = paramInt % 128;
    if (paramInt % 2 != 0) {
      return localClassCastException;
    }
    return localClassCastException;
  }
  
  private final st<Object> ʽ(int paramInt)
  {
    break label240;
    label35:
    st localSt;
    switch (paramInt)
    {
    default: 
      break;
      localSt = st.ˏ((Callable)new ˎ(this, paramInt));
      break;
    }
    for (;;)
    {
      label55:
      label93:
      String str;
      switch (paramInt)
      {
      default: 
        return localSt;
        paramInt = 14;
        break;
        paramInt = 51;
        break label169;
        str = ˋ(47, 57865, 60).intern();
        break;
      case 30: 
        for (;;)
        {
          try
          {
            i = ʻ;
            paramInt = i & 0xFFFFFFFE | (i ^ 0xFFFFFFFF) & 0x1;
            i = (i & 0x1) << 1;
            paramInt = ((paramInt | i) << 1) - (paramInt ^ i);
          }
          catch (UnsupportedOperationException|NumberFormatException|IllegalStateException|ArrayStoreException|NullPointerException localUnsupportedOperationException)
          {
            try
            {
              ॱॱ = paramInt % 128;
              if (paramInt % 2 != 0) {
                break label351;
              }
              continue;
              paramInt = 83;
              switch (paramInt)
              {
              case 83: 
              default: 
                break;
                throw new NullPointerException();
              case 51: 
                str = ˋ(38, 57865, 50);
                str = str.intern();
                continue;
                vq.ˋ(localSt, str);
                break;
              }
              paramInt = 78;
              break label55;
              break label35;
              paramInt = 98;
              break;
              paramInt = ʻ;
              paramInt = paramInt + 58 - 1;
              ॱॱ = paramInt % 128;
              if (paramInt % 2 != 0) {
                continue;
              }
            }
            catch (IndexOutOfBoundsException|ArrayStoreException|NumberFormatException|NullPointerException localIndexOutOfBoundsException)
            {
              int i;
              throw localIndexOutOfBoundsException;
            }
            localUnsupportedOperationException = localUnsupportedOperationException;
            throw localUnsupportedOperationException;
          }
          i = ॱॱ;
          paramInt = (i | 0x23) << 1;
          i ^= 0x23;
          paramInt = (-i ^ paramInt) + ((paramInt & -i) << 1);
          ʻ = paramInt % 128;
          if (paramInt % 2 != 0)
          {
            break label93;
            vq.ˋ(localSt, localUnsupportedOperationException);
            paramInt = 99 / 0;
          }
        }
      case 78: 
        label169:
        label240:
        return localSt;
        label351:
        paramInt = 30;
      }
    }
  }
  
  static void ʽ()
  {
    ˊ = 6983180543846677979L;
    ˋ = new char[] { 83, 32190, -1067, 31204, -2274, 29998, -3242, 28804, 68, 32162, -1064, 31216, -2303, 29998, -3263, 28893, -4421, 27867, -5397, 26634, -6609, 25708, -7718, 24500, -8740, 23545, -9981, 22304, -10888, 21134, -12046, 20191, -13059, 18957, -14256, 18032, -15462, 16808, -7610, -24656, 6604, -25603, 5399, -26824, 4426, -28010, 3261, -28961, 2217, -30204, 1064, -31120, 918, -16978, 16273, -17927, 15205, -19096, 14133, -20258, 13051, -21372, 3751, -22454, 10775, -23504, 8669, -23578, 23939, -8276, 22857, -9393, 21814, -10510, 20709, -11634, 19627, -12684, 18449, -13766, 18375, -15904, 17293, -682, 32627, -1764, 31588, -2869, 78, 32180, -1064, 31220, 67, 32190, -1084, 31205, -2299, 29985, -3253, 28830, -4423, 27847, -5397, 26697, -6617, 25719, -7781, 24507, -8745, 23534, -9982, 22368, 4156, 28150, -5248, 27084, -6318, 25938, -7362, 24814, -318, 31915, -1385, 30773, 69, 32182, -1085, 31229, -2291, 30003, -3251, 28815, -4360, 27863, -5397, 26653, -6623, 25724, -7794, 24496, -8748, 23466, 5234, 27016, -4126, 28114, -7363, 24854, -6283, 25769, -1406, 30944, -360, 31802, -3556, 28744, -2642, 19343, -13853, 20441, -12943, -2793, -30483, 3719, -29513, 600, -32653, 1552, -31284, 7143, -26235, 8189, -25255, 4984, -28382, 5319, -21789, 10368, -20820, 11344, -23946, 8302, -18487, -13771, 19544, -12677, 16589, -15705, 17623, -14584, 22840, -9391, 23911, -8307, 20897, -11329, -25960, -6302, 24860, -7388, 28115, -4098, 27102, -5549, 29803, -2560, 28710, -3376, 31996, -286, 10499, 21693, -11539, 20674, -8662, 23559, -9611, 22971, -14433, 17840, -15390, 16641, -12473, 19786, -14152, 30362, -2842, 29389, -3995, 32351, -993, 46, 32251, -1033, 31218, -2280, 30002, -3261, 28817, -4360, 27900, -5435, 26697, -6606, 25726, -7786, 24480, -8747, 23467, -9893, 22369, 27623, 5694, -28606, 4674, -25448, 7861, -26421, 6931, -31425, 1819, -32420, 967, -29257, 4075, -30200, 13372, -18850, 12396, -19768, 15525, -16647, 14593, -17605, 9550, -30930, 8593, -23599, 11766, -22528, 10794, -11186, 22106, -12141, 21214, -8971, 24324, -9922, 23374, -14986, 18340, -15897, 17379, -12772, 18470, -13754, 29843, -2369, 28888, -3357, 32066, 68, 32190, -1088, 31224, -2289, 29986, -3217, 28828, -4426, 27858, -5399, 26636, -6602, 25649, -7779, 24496, -8764, 23459, -9905, 16489, 15801, -17469, 14835, -18623, 13608, -19648, 12432, -20804, 11422, -21794, 10270, -22987, 9333, -24169, 8113, -25187, 7150, -26358, 5936, -27278, 4757, -28507, 3718, -29459, 2575, -30641, 1655, -31850, 440, -123, 32166, -1207, 31065, -2201, 29845, -3396, 28813, -18326, -14919, 17346, -15899, 20234, -13017, 19264, 98, 32183, -1065, 31218, -2297, 29963, -3253, 28814, -4436, 27873, -5397, 26632, -6601, 25712, -7788, 68, 32190, -1088, 31224, -2289, 29986, 66, 32183, -1065, 31218, -2297, 29995, -3253, 28814, -4436, 27866, -5408, 26638, -6556, 25723, -7777, 24483, -8743, 23528, -9981, 22369, -10882, 21138, -12111, 20172, -13059, 18960, -14245, 17977, -15461, 16809, -16502, 15863, -17659, 14682, -18587, 13470, -19806, 12445, -20830, 65, 32149, -1038, 31171, -2269, 29966, -3226, 77, 32148, -1036, 31192, -2272, 29954, 8225, 24027, -9307, 22941, -10390, 21831, -11510, 20729, -12589, 19639, -13684, 18537, -14765, 17492, -15880, 32725, -607, 31686, -1750, 30474, -2787, 29431, -3903, 28321, -4978, 27235, -6130, 26130, -7176, 25051, -24646, 7557, -25780, 6426, 67, 32183, -1069, 31216, -2274, 29998, -3252, 28826, -4360, 27858, -5406, 26629, -6556, 25724, -7781, 24487, -8748, 23544, -9914, 22311, -10898, 21144, -12097, 20109, -13083, 18946, -14262, 18027, -15459, 16823, -16502, 15853, -17661, 14686, -18634, 13461, -19795, 12499, -20765, 11327, -21927, 10336, -23157, 29173, 3119, -30133, 2149, -31095, 1203 };
  }
  
  /* Error */
  private static String ˋ(int paramInt1, char paramChar, int paramInt2)
  {
    // Byte code:
    //   0: goto +270 -> 270
    //   3: iload_3
    //   4: iload_2
    //   5: if_icmpge +6 -> 11
    //   8: goto +35 -> 43
    //   11: goto +85 -> 96
    //   14: iload 4
    //   16: tableswitch	default:+24->40, 0:+135->151, 1:+207->223
    //   40: goto +183 -> 223
    //   43: bipush 61
    //   45: istore 4
    //   47: goto +145 -> 192
    //   50: iconst_0
    //   51: istore 4
    //   53: goto -39 -> 14
    //   56: goto -53 -> 3
    //   59: goto +77 -> 136
    //   62: getstatic 51	o/Gz:ʻ	I
    //   65: istore 4
    //   67: iload 4
    //   69: bipush 53
    //   71: iadd
    //   72: istore 4
    //   74: iload 4
    //   76: sipush 128
    //   79: irem
    //   80: putstatic 53	o/Gz:ॱॱ	I
    //   83: iload 4
    //   85: iconst_2
    //   86: irem
    //   87: ifeq +6 -> 93
    //   90: goto -40 -> 50
    //   93: goto +37 -> 130
    //   96: bipush 98
    //   98: istore 4
    //   100: goto +92 -> 192
    //   103: getstatic 53	o/Gz:ॱॱ	I
    //   106: bipush 117
    //   108: iadd
    //   109: istore_3
    //   110: iload_3
    //   111: sipush 128
    //   114: irem
    //   115: putstatic 51	o/Gz:ʻ	I
    //   118: iload_3
    //   119: iconst_2
    //   120: irem
    //   121: ifne +6 -> 127
    //   124: goto -65 -> 59
    //   127: goto +9 -> 136
    //   130: iconst_1
    //   131: istore 4
    //   133: goto -119 -> 14
    //   136: iload_2
    //   137: newarray char
    //   139: astore 11
    //   141: iconst_0
    //   142: istore_3
    //   143: goto -140 -> 3
    //   146: astore 11
    //   148: aload 11
    //   150: athrow
    //   151: getstatic 596	o/Gz:ˋ	[C
    //   154: astore 12
    //   156: aload 11
    //   158: iload_3
    //   159: aload 12
    //   161: iload_0
    //   162: iload_3
    //   163: iushr
    //   164: caload
    //   165: i2l
    //   166: iload_3
    //   167: i2l
    //   168: getstatic 114	o/Gz:ˊ	J
    //   171: ladd
    //   172: ladd
    //   173: iload_1
    //   174: i2l
    //   175: ldiv
    //   176: l2i
    //   177: i2c
    //   178: castore
    //   179: iload_3
    //   180: bipush 61
    //   182: iadd
    //   183: istore_3
    //   184: goto -128 -> 56
    //   187: astore 11
    //   189: aload 11
    //   191: athrow
    //   192: iload 4
    //   194: lookupswitch	default:+26->220, 61:+-132->62, 98:+79->273
    //   220: goto -158 -> 62
    //   223: getstatic 596	o/Gz:ˋ	[C
    //   226: astore 12
    //   228: aload 12
    //   230: iload_0
    //   231: iload_3
    //   232: iadd
    //   233: caload
    //   234: i2l
    //   235: lstore 5
    //   237: iload_3
    //   238: i2l
    //   239: lstore 7
    //   241: getstatic 114	o/Gz:ˊ	J
    //   244: lstore 9
    //   246: aload 11
    //   248: iload_3
    //   249: lload 5
    //   251: lload 7
    //   253: lload 9
    //   255: lmul
    //   256: lxor
    //   257: iload_1
    //   258: i2l
    //   259: lxor
    //   260: l2i
    //   261: i2c
    //   262: castore
    //   263: iload_3
    //   264: iconst_1
    //   265: iadd
    //   266: istore_3
    //   267: goto -211 -> 56
    //   270: goto -167 -> 103
    //   273: new 92	java/lang/String
    //   276: dup
    //   277: aload 11
    //   279: invokespecial 599	java/lang/String:<init>	([C)V
    //   282: areturn
    // Local variable table:
    //   start	length	slot	name	signature
    //   0	283	0	paramInt1	int
    //   0	283	1	paramChar	char
    //   0	283	2	paramInt2	int
    //   3	264	3	i	int
    //   14	179	4	j	int
    //   235	15	5	l1	long
    //   239	13	7	l2	long
    //   244	10	9	l3	long
    //   139	1	11	arrayOfChar1	char[]
    //   146	11	11	localException1	Exception
    //   187	91	11	localException2	Exception
    //   154	75	12	arrayOfChar2	char[]
    // Exception table:
    //   from	to	target	type
    //   62	67	146	java/lang/Exception
    //   74	83	146	java/lang/Exception
    //   151	156	146	java/lang/Exception
    //   223	228	146	java/lang/Exception
    //   241	246	187	java/lang/Exception
  }
  
  /* Error */
  private final boolean ˋ(int paramInt)
  {
    // Byte code:
    //   0: goto +259 -> 259
    //   3: iconst_1
    //   4: istore_2
    //   5: goto +116 -> 121
    //   8: bipush 11
    //   10: istore_1
    //   11: goto +331 -> 342
    //   14: astore 5
    //   16: aload 5
    //   18: athrow
    //   19: bipush 40
    //   21: istore_3
    //   22: goto +557 -> 579
    //   25: aload_0
    //   26: getfield 70	o/Gz:ॱ	Landroid/content/Context;
    //   29: astore 5
    //   31: aload_0
    //   32: aload 5
    //   34: bipush 7
    //   36: sipush 139
    //   39: sipush 173
    //   42: invokestatic 605	o/O:ˋ	(IIC)Ljava/lang/Object;
    //   45: checkcast 607	java/lang/Class
    //   48: ldc_w 608
    //   51: invokevirtual 612	java/lang/Class:getField	(Ljava/lang/String;)Ljava/lang/reflect/Field;
    //   54: aconst_null
    //   55: invokevirtual 618	java/lang/reflect/Field:get	(Ljava/lang/Object;)Ljava/lang/Object;
    //   58: checkcast 620	java/lang/Enum
    //   61: iload_1
    //   62: iload 4
    //   64: invokespecial 624	o/Gz:ॱ$32e4e300	(Landroid/content/Context;Ljava/lang/Enum;II)V
    //   67: goto +456 -> 523
    //   70: getstatic 51	o/Gz:ʻ	I
    //   73: istore_2
    //   74: iload_2
    //   75: bipush 71
    //   77: iand
    //   78: iconst_m1
    //   79: ixor
    //   80: iload_2
    //   81: bipush 71
    //   83: ior
    //   84: iand
    //   85: istore_1
    //   86: iload_2
    //   87: bipush 71
    //   89: iand
    //   90: iconst_1
    //   91: ishl
    //   92: istore_2
    //   93: iload_1
    //   94: iload_2
    //   95: iand
    //   96: iload_1
    //   97: iload_2
    //   98: ior
    //   99: iadd
    //   100: istore_1
    //   101: iload_1
    //   102: sipush 128
    //   105: irem
    //   106: putstatic 53	o/Gz:ॱॱ	I
    //   109: iload_1
    //   110: iconst_2
    //   111: irem
    //   112: ifeq +6 -> 118
    //   115: goto +43 -> 158
    //   118: goto +253 -> 371
    //   121: iload_2
    //   122: tableswitch	default:+22->144, 0:+41->163, 1:+290->412
    //   144: goto +268 -> 412
    //   147: iconst_0
    //   148: istore_2
    //   149: goto -28 -> 121
    //   152: bipush 19
    //   154: istore_1
    //   155: goto +187 -> 342
    //   158: iconst_0
    //   159: istore_1
    //   160: goto +102 -> 262
    //   163: aload_0
    //   164: getfield 70	o/Gz:ॱ	Landroid/content/Context;
    //   167: astore 5
    //   169: goto +23 -> 192
    //   172: astore 5
    //   174: aload 5
    //   176: invokevirtual 630	java/lang/Throwable:getCause	()Ljava/lang/Throwable;
    //   179: astore 6
    //   181: aload 6
    //   183: ifnull +6 -> 189
    //   186: aload 6
    //   188: athrow
    //   189: aload 5
    //   191: athrow
    //   192: iconst_4
    //   193: bipush 46
    //   195: iconst_0
    //   196: invokestatic 605	o/O:ˋ	(IIC)Ljava/lang/Object;
    //   199: checkcast 607	java/lang/Class
    //   202: ldc_w 608
    //   205: iconst_2
    //   206: anewarray 607	java/lang/Class
    //   209: dup
    //   210: iconst_0
    //   211: ldc_w 632
    //   214: aastore
    //   215: dup
    //   216: iconst_1
    //   217: getstatic 638	java/lang/Integer:TYPE	Ljava/lang/Class;
    //   220: aastore
    //   221: invokevirtual 642	java/lang/Class:getMethod	(Ljava/lang/String;[Ljava/lang/Class;)Ljava/lang/reflect/Method;
    //   224: aconst_null
    //   225: iconst_2
    //   226: anewarray 644	java/lang/Object
    //   229: dup
    //   230: iconst_0
    //   231: aload 5
    //   233: aastore
    //   234: dup
    //   235: iconst_1
    //   236: iload_1
    //   237: invokestatic 648	java/lang/Integer:valueOf	(I)Ljava/lang/Integer;
    //   240: aastore
    //   241: invokevirtual 654	java/lang/reflect/Method:invoke	(Ljava/lang/Object;[Ljava/lang/Object;)Ljava/lang/Object;
    //   244: checkcast 634	java/lang/Integer
    //   247: invokevirtual 658	java/lang/Integer:intValue	()I
    //   250: istore_1
    //   251: new 41	java/lang/NullPointerException
    //   254: dup
    //   255: invokespecial 110	java/lang/NullPointerException:<init>	()V
    //   258: athrow
    //   259: goto +117 -> 376
    //   262: iload_1
    //   263: tableswitch	default:+21->284, 0:+26->289, 1:+77->340
    //   284: goto +5 -> 289
    //   287: iconst_1
    //   288: ireturn
    //   289: aconst_null
    //   290: arraylength
    //   291: istore_1
    //   292: iconst_0
    //   293: ireturn
    //   294: getstatic 51	o/Gz:ʻ	I
    //   297: istore_2
    //   298: iload_2
    //   299: bipush 56
    //   301: iand
    //   302: iconst_1
    //   303: ishl
    //   304: iload_2
    //   305: bipush 56
    //   307: ixor
    //   308: iadd
    //   309: istore_2
    //   310: iload_2
    //   311: iconst_m1
    //   312: ixor
    //   313: iload_2
    //   314: iconst_m1
    //   315: iand
    //   316: iconst_1
    //   317: ishl
    //   318: iadd
    //   319: istore_2
    //   320: iload_2
    //   321: sipush 128
    //   324: irem
    //   325: putstatic 53	o/Gz:ॱॱ	I
    //   328: iload_2
    //   329: iconst_2
    //   330: irem
    //   331: ifeq +6 -> 337
    //   334: goto +183 -> 517
    //   337: goto -312 -> 25
    //   340: iconst_0
    //   341: ireturn
    //   342: iload_1
    //   343: lookupswitch	default:+25->368, 11:+177->520, 19:+276->619
    //   368: goto +152 -> 520
    //   371: iconst_1
    //   372: istore_1
    //   373: goto -111 -> 262
    //   376: getstatic 51	o/Gz:ʻ	I
    //   379: istore_2
    //   380: iload_2
    //   381: bipush 74
    //   383: iand
    //   384: iload_2
    //   385: bipush 74
    //   387: ior
    //   388: iadd
    //   389: iconst_1
    //   390: isub
    //   391: istore_2
    //   392: iload_2
    //   393: sipush 128
    //   396: irem
    //   397: putstatic 53	o/Gz:ॱॱ	I
    //   400: iload_2
    //   401: iconst_2
    //   402: irem
    //   403: ifeq +6 -> 409
    //   406: goto -259 -> 147
    //   409: goto -406 -> 3
    //   412: aload_0
    //   413: getfield 70	o/Gz:ॱ	Landroid/content/Context;
    //   416: astore 5
    //   418: goto +23 -> 441
    //   421: astore 5
    //   423: aload 5
    //   425: invokevirtual 630	java/lang/Throwable:getCause	()Ljava/lang/Throwable;
    //   428: astore 6
    //   430: aload 6
    //   432: ifnull +6 -> 438
    //   435: aload 6
    //   437: athrow
    //   438: aload 5
    //   440: athrow
    //   441: iconst_4
    //   442: bipush 46
    //   444: iconst_0
    //   445: invokestatic 605	o/O:ˋ	(IIC)Ljava/lang/Object;
    //   448: checkcast 607	java/lang/Class
    //   451: ldc_w 608
    //   454: iconst_2
    //   455: anewarray 607	java/lang/Class
    //   458: dup
    //   459: iconst_0
    //   460: ldc_w 632
    //   463: aastore
    //   464: dup
    //   465: iconst_1
    //   466: getstatic 638	java/lang/Integer:TYPE	Ljava/lang/Class;
    //   469: aastore
    //   470: invokevirtual 642	java/lang/Class:getMethod	(Ljava/lang/String;[Ljava/lang/Class;)Ljava/lang/reflect/Method;
    //   473: aconst_null
    //   474: iconst_2
    //   475: anewarray 644	java/lang/Object
    //   478: dup
    //   479: iconst_0
    //   480: aload 5
    //   482: aastore
    //   483: dup
    //   484: iconst_1
    //   485: iload_1
    //   486: invokestatic 648	java/lang/Integer:valueOf	(I)Ljava/lang/Integer;
    //   489: aastore
    //   490: invokevirtual 654	java/lang/reflect/Method:invoke	(Ljava/lang/Object;[Ljava/lang/Object;)Ljava/lang/Object;
    //   493: checkcast 634	java/lang/Integer
    //   496: invokevirtual 658	java/lang/Integer:intValue	()I
    //   499: istore_2
    //   500: iload_2
    //   501: iload_1
    //   502: if_icmpeq +6 -> 508
    //   505: goto +6 -> 511
    //   508: goto -489 -> 19
    //   511: bipush 28
    //   513: istore_3
    //   514: goto +65 -> 579
    //   517: goto -492 -> 25
    //   520: goto -233 -> 287
    //   523: getstatic 53	o/Gz:ॱॱ	I
    //   526: istore_2
    //   527: iload_2
    //   528: bipush 7
    //   530: iand
    //   531: iconst_m1
    //   532: ixor
    //   533: iload_2
    //   534: bipush 7
    //   536: ior
    //   537: iand
    //   538: istore_1
    //   539: iload_2
    //   540: bipush 7
    //   542: iand
    //   543: iconst_1
    //   544: ishl
    //   545: istore_2
    //   546: iload_1
    //   547: iload_2
    //   548: ior
    //   549: iconst_1
    //   550: ishl
    //   551: iload_1
    //   552: iload_2
    //   553: ixor
    //   554: isub
    //   555: istore_1
    //   556: iload_1
    //   557: sipush 128
    //   560: irem
    //   561: putstatic 51	o/Gz:ʻ	I
    //   564: iload_1
    //   565: iconst_2
    //   566: irem
    //   567: ifne +6 -> 573
    //   570: goto -562 -> 8
    //   573: goto -421 -> 152
    //   576: goto -506 -> 70
    //   579: iload_2
    //   580: istore 4
    //   582: iload_3
    //   583: lookupswitch	default:+25->608, 28:+-289->294, 40:+-7->576
    //   608: iload_2
    //   609: istore 4
    //   611: goto -317 -> 294
    //   614: astore 5
    //   616: aload 5
    //   618: athrow
    //   619: goto -332 -> 287
    // Local variable table:
    //   start	length	slot	name	signature
    //   0	622	0	this	Gz
    //   0	622	1	paramInt	int
    //   4	605	2	i	int
    //   21	562	3	j	int
    //   62	548	4	k	int
    //   14	3	5	localException	Exception
    //   29	139	5	localContext1	Context
    //   172	60	5	localObject1	Object
    //   416	1	5	localContext2	Context
    //   421	60	5	localObject2	Object
    //   614	3	5	localUnsupportedOperationException	UnsupportedOperationException
    //   179	257	6	localThrowable	Throwable
    // Exception table:
    //   from	to	target	type
    //   31	67	14	java/lang/Exception
    //   70	74	14	java/lang/NumberFormatException
    //   101	109	14	java/lang/NumberFormatException
    //   376	380	14	java/lang/IllegalArgumentException
    //   392	400	14	java/lang/IllegalArgumentException
    //   392	400	14	java/lang/NullPointerException
    //   556	564	14	java/lang/ClassCastException
    //   192	251	172	finally
    //   441	500	421	finally
    //   25	31	614	java/lang/UnsupportedOperationException
    //   101	109	614	java/lang/Exception
    //   294	298	614	java/lang/IndexOutOfBoundsException
    //   320	328	614	java/lang/ArrayStoreException
    //   523	527	614	java/lang/Exception
  }
  
  /* Error */
  public static final Gz ˏ(Context paramContext)
  {
    // Byte code:
    //   0: goto +152 -> 152
    //   3: getstatic 53	o/Gz:ॱॱ	I
    //   6: istore_1
    //   7: iload_1
    //   8: bipush 92
    //   10: ior
    //   11: iload_1
    //   12: bipush 92
    //   14: iand
    //   15: iadd
    //   16: istore_1
    //   17: iload_1
    //   18: iconst_m1
    //   19: ixor
    //   20: iload_1
    //   21: iconst_m1
    //   22: iand
    //   23: iconst_1
    //   24: ishl
    //   25: iadd
    //   26: istore_1
    //   27: iload_1
    //   28: sipush 128
    //   31: irem
    //   32: putstatic 51	o/Gz:ʻ	I
    //   35: iload_1
    //   36: iconst_2
    //   37: irem
    //   38: ifne +6 -> 44
    //   41: goto +82 -> 123
    //   44: goto +90 -> 134
    //   47: getstatic 51	o/Gz:ʻ	I
    //   50: istore_1
    //   51: iload_1
    //   52: bipush 55
    //   54: ior
    //   55: iconst_1
    //   56: ishl
    //   57: iload_1
    //   58: bipush 55
    //   60: ixor
    //   61: isub
    //   62: istore_1
    //   63: iload_1
    //   64: sipush 128
    //   67: irem
    //   68: putstatic 53	o/Gz:ॱॱ	I
    //   71: iload_1
    //   72: iconst_2
    //   73: irem
    //   74: ifeq +6 -> 80
    //   77: goto +49 -> 126
    //   80: goto +67 -> 147
    //   83: bipush 81
    //   85: iconst_0
    //   86: idiv
    //   87: istore_1
    //   88: aload_0
    //   89: areturn
    //   90: astore_0
    //   91: aload_0
    //   92: athrow
    //   93: aload_0
    //   94: areturn
    //   95: iload_1
    //   96: tableswitch	default:+24->120, 0:+-3->93, 1:+-13->83
    //   120: goto -37 -> 83
    //   123: goto +11 -> 134
    //   126: iconst_1
    //   127: istore_1
    //   128: goto -33 -> 95
    //   131: astore_0
    //   132: aload_0
    //   133: athrow
    //   134: getstatic 62	o/Gz:ˎ	Lo/Gz$ˊ;
    //   137: astore_2
    //   138: aload_2
    //   139: aload_0
    //   140: invokevirtual 666	o/Gz$ˊ:ˎ	(Landroid/content/Context;)Lo/Gz;
    //   143: astore_0
    //   144: goto -97 -> 47
    //   147: iconst_0
    //   148: istore_1
    //   149: goto -54 -> 95
    //   152: goto -149 -> 3
    // Local variable table:
    //   start	length	slot	name	signature
    //   0	155	0	paramContext	Context
    //   6	143	1	i	int
    //   137	2	2	localˊ	ˊ
    // Exception table:
    //   from	to	target	type
    //   3	7	90	java/lang/IllegalArgumentException
    //   27	35	90	java/lang/Exception
    //   47	51	90	java/lang/Exception
    //   63	71	90	java/lang/Exception
    //   134	138	90	java/lang/ArrayStoreException
    //   138	144	90	java/lang/NullPointerException
    //   63	71	131	java/lang/ArrayStoreException
  }
  
  /* Error */
  private final boolean ˏ(int paramInt)
  {
    // Byte code:
    //   0: goto +166 -> 166
    //   3: goto +674 -> 677
    //   6: aload_0
    //   7: getfield 70	o/Gz:ॱ	Landroid/content/Context;
    //   10: astore 5
    //   12: goto +23 -> 35
    //   15: astore 6
    //   17: aload 6
    //   19: invokevirtual 630	java/lang/Throwable:getCause	()Ljava/lang/Throwable;
    //   22: astore 5
    //   24: aload 5
    //   26: ifnull +6 -> 32
    //   29: aload 5
    //   31: athrow
    //   32: aload 6
    //   34: athrow
    //   35: iconst_4
    //   36: bipush 87
    //   38: ldc_w 667
    //   41: invokestatic 605	o/O:ˋ	(IIC)Ljava/lang/Object;
    //   44: checkcast 607	java/lang/Class
    //   47: ldc_w 668
    //   50: iconst_2
    //   51: anewarray 607	java/lang/Class
    //   54: dup
    //   55: iconst_0
    //   56: ldc_w 632
    //   59: aastore
    //   60: dup
    //   61: iconst_1
    //   62: getstatic 638	java/lang/Integer:TYPE	Ljava/lang/Class;
    //   65: aastore
    //   66: invokevirtual 642	java/lang/Class:getMethod	(Ljava/lang/String;[Ljava/lang/Class;)Ljava/lang/reflect/Method;
    //   69: aconst_null
    //   70: iconst_2
    //   71: anewarray 644	java/lang/Object
    //   74: dup
    //   75: iconst_0
    //   76: aload 5
    //   78: aastore
    //   79: dup
    //   80: iconst_1
    //   81: iload_1
    //   82: invokestatic 648	java/lang/Integer:valueOf	(I)Ljava/lang/Integer;
    //   85: aastore
    //   86: invokevirtual 654	java/lang/reflect/Method:invoke	(Ljava/lang/Object;[Ljava/lang/Object;)Ljava/lang/Object;
    //   89: checkcast 634	java/lang/Integer
    //   92: invokevirtual 658	java/lang/Integer:intValue	()I
    //   95: istore_3
    //   96: iload_3
    //   97: iload_1
    //   98: if_icmpeq +6 -> 104
    //   101: goto +401 -> 502
    //   104: goto +435 -> 539
    //   107: getstatic 53	o/Gz:ॱॱ	I
    //   110: istore 4
    //   112: iload 4
    //   114: bipush 55
    //   116: ior
    //   117: iconst_1
    //   118: ishl
    //   119: istore_3
    //   120: iload 4
    //   122: bipush 55
    //   124: ixor
    //   125: istore 4
    //   127: iload 4
    //   129: ineg
    //   130: iload_3
    //   131: ior
    //   132: iconst_1
    //   133: ishl
    //   134: iload_3
    //   135: iload 4
    //   137: ineg
    //   138: ixor
    //   139: isub
    //   140: istore_3
    //   141: iload_3
    //   142: sipush 128
    //   145: irem
    //   146: putstatic 51	o/Gz:ʻ	I
    //   149: iload_3
    //   150: iconst_2
    //   151: irem
    //   152: ifne +6 -> 158
    //   155: goto +390 -> 545
    //   158: goto +392 -> 550
    //   161: iconst_1
    //   162: istore_2
    //   163: goto +351 -> 514
    //   166: goto +428 -> 594
    //   169: aload_0
    //   170: aload_0
    //   171: getfield 70	o/Gz:ॱ	Landroid/content/Context;
    //   174: bipush 7
    //   176: sipush 139
    //   179: sipush 173
    //   182: invokestatic 605	o/O:ˋ	(IIC)Ljava/lang/Object;
    //   185: checkcast 607	java/lang/Class
    //   188: ldc_w 669
    //   191: invokevirtual 612	java/lang/Class:getField	(Ljava/lang/String;)Ljava/lang/reflect/Field;
    //   194: aconst_null
    //   195: invokevirtual 618	java/lang/reflect/Field:get	(Ljava/lang/Object;)Ljava/lang/Object;
    //   198: checkcast 620	java/lang/Enum
    //   201: iload_1
    //   202: iload_2
    //   203: invokespecial 624	o/Gz:ॱ$32e4e300	(Landroid/content/Context;Ljava/lang/Enum;II)V
    //   206: new 41	java/lang/NullPointerException
    //   209: dup
    //   210: invokespecial 110	java/lang/NullPointerException:<init>	()V
    //   213: athrow
    //   214: getstatic 53	o/Gz:ॱॱ	I
    //   217: istore_2
    //   218: iload_2
    //   219: bipush 111
    //   221: iand
    //   222: istore_1
    //   223: iload_2
    //   224: bipush 111
    //   226: ixor
    //   227: iload_2
    //   228: bipush 111
    //   230: iand
    //   231: ior
    //   232: ineg
    //   233: istore_2
    //   234: iload_2
    //   235: ineg
    //   236: iload_1
    //   237: iand
    //   238: iload_1
    //   239: iload_2
    //   240: ineg
    //   241: ior
    //   242: iadd
    //   243: istore_1
    //   244: iload_1
    //   245: sipush 128
    //   248: irem
    //   249: putstatic 51	o/Gz:ʻ	I
    //   252: iload_1
    //   253: iconst_2
    //   254: irem
    //   255: ifne +6 -> 261
    //   258: goto +90 -> 348
    //   261: goto +537 -> 798
    //   264: iload_3
    //   265: istore_2
    //   266: iload 4
    //   268: lookupswitch	default:+28->296, 17:+-161->107, 28:+67->335
    //   296: iload_3
    //   297: istore_2
    //   298: goto -191 -> 107
    //   301: new 41	java/lang/NullPointerException
    //   304: dup
    //   305: invokespecial 110	java/lang/NullPointerException:<init>	()V
    //   308: athrow
    //   309: iload_3
    //   310: tableswitch	default:+22->332, 0:+327->637, 1:+-141->169
    //   332: goto +305 -> 637
    //   335: goto -121 -> 214
    //   338: iconst_1
    //   339: istore_1
    //   340: goto +127 -> 467
    //   343: iconst_0
    //   344: istore_1
    //   345: goto +122 -> 467
    //   348: iconst_0
    //   349: istore_1
    //   350: goto +415 -> 765
    //   353: bipush 17
    //   355: istore 4
    //   357: goto -93 -> 264
    //   360: aload_0
    //   361: getfield 70	o/Gz:ॱ	Landroid/content/Context;
    //   364: astore 5
    //   366: goto +23 -> 389
    //   369: astore 6
    //   371: aload 6
    //   373: invokevirtual 630	java/lang/Throwable:getCause	()Ljava/lang/Throwable;
    //   376: astore 5
    //   378: aload 5
    //   380: ifnull +6 -> 386
    //   383: aload 5
    //   385: athrow
    //   386: aload 6
    //   388: athrow
    //   389: iconst_4
    //   390: bipush 87
    //   392: ldc_w 667
    //   395: invokestatic 605	o/O:ˋ	(IIC)Ljava/lang/Object;
    //   398: checkcast 607	java/lang/Class
    //   401: ldc_w 668
    //   404: iconst_2
    //   405: anewarray 607	java/lang/Class
    //   408: dup
    //   409: iconst_0
    //   410: ldc_w 632
    //   413: aastore
    //   414: dup
    //   415: iconst_1
    //   416: getstatic 638	java/lang/Integer:TYPE	Ljava/lang/Class;
    //   419: aastore
    //   420: invokevirtual 642	java/lang/Class:getMethod	(Ljava/lang/String;[Ljava/lang/Class;)Ljava/lang/reflect/Method;
    //   423: aconst_null
    //   424: iconst_2
    //   425: anewarray 644	java/lang/Object
    //   428: dup
    //   429: iconst_0
    //   430: aload 5
    //   432: aastore
    //   433: dup
    //   434: iconst_1
    //   435: iload_1
    //   436: invokestatic 648	java/lang/Integer:valueOf	(I)Ljava/lang/Integer;
    //   439: aastore
    //   440: invokevirtual 654	java/lang/reflect/Method:invoke	(Ljava/lang/Object;[Ljava/lang/Object;)Ljava/lang/Object;
    //   443: checkcast 634	java/lang/Integer
    //   446: invokevirtual 658	java/lang/Integer:intValue	()I
    //   449: istore_3
    //   450: aconst_null
    //   451: arraylength
    //   452: istore_2
    //   453: iload_3
    //   454: iload_1
    //   455: if_icmpeq +6 -> 461
    //   458: goto -105 -> 353
    //   461: goto +34 -> 495
    //   464: goto +213 -> 677
    //   467: iload_1
    //   468: tableswitch	default:+24->492, 0:+-4->464, 1:+-465->3
    //   492: goto -28 -> 464
    //   495: bipush 28
    //   497: istore 4
    //   499: goto -235 -> 264
    //   502: bipush 56
    //   504: istore 4
    //   506: goto +222 -> 728
    //   509: astore 5
    //   511: aload 5
    //   513: athrow
    //   514: iload_2
    //   515: tableswitch	default:+21->536, 0:+-509->6, 1:+-155->360
    //   536: goto -530 -> 6
    //   539: iconst_0
    //   540: istore 4
    //   542: goto +186 -> 728
    //   545: iconst_1
    //   546: istore_3
    //   547: goto -238 -> 309
    //   550: iconst_0
    //   551: istore_3
    //   552: goto -243 -> 309
    //   555: getstatic 53	o/Gz:ॱॱ	I
    //   558: istore_1
    //   559: iload_1
    //   560: bipush 99
    //   562: iand
    //   563: iload_1
    //   564: bipush 99
    //   566: ixor
    //   567: iload_1
    //   568: bipush 99
    //   570: iand
    //   571: ior
    //   572: iadd
    //   573: istore_1
    //   574: iload_1
    //   575: sipush 128
    //   578: irem
    //   579: putstatic 51	o/Gz:ʻ	I
    //   582: iload_1
    //   583: iconst_2
    //   584: irem
    //   585: ifne +6 -> 591
    //   588: goto -250 -> 338
    //   591: goto -248 -> 343
    //   594: getstatic 51	o/Gz:ʻ	I
    //   597: istore_2
    //   598: iload_2
    //   599: bipush -18
    //   601: iand
    //   602: iload_2
    //   603: iconst_m1
    //   604: ixor
    //   605: bipush 17
    //   607: iand
    //   608: ior
    //   609: iload_2
    //   610: bipush 17
    //   612: iand
    //   613: iconst_1
    //   614: ishl
    //   615: iadd
    //   616: istore_2
    //   617: iload_2
    //   618: sipush 128
    //   621: irem
    //   622: putstatic 53	o/Gz:ॱॱ	I
    //   625: iload_2
    //   626: iconst_2
    //   627: irem
    //   628: ifeq +6 -> 634
    //   631: goto -470 -> 161
    //   634: goto +89 -> 723
    //   637: aload_0
    //   638: aload_0
    //   639: getfield 70	o/Gz:ॱ	Landroid/content/Context;
    //   642: bipush 7
    //   644: sipush 139
    //   647: sipush 173
    //   650: invokestatic 605	o/O:ˋ	(IIC)Ljava/lang/Object;
    //   653: checkcast 607	java/lang/Class
    //   656: ldc_w 669
    //   659: invokevirtual 612	java/lang/Class:getField	(Ljava/lang/String;)Ljava/lang/reflect/Field;
    //   662: aconst_null
    //   663: invokevirtual 618	java/lang/reflect/Field:get	(Ljava/lang/Object;)Ljava/lang/Object;
    //   666: checkcast 620	java/lang/Enum
    //   669: iload_1
    //   670: iload_2
    //   671: invokespecial 624	o/Gz:ॱ$32e4e300	(Landroid/content/Context;Ljava/lang/Enum;II)V
    //   674: goto -119 -> 555
    //   677: getstatic 51	o/Gz:ʻ	I
    //   680: istore_1
    //   681: iload_1
    //   682: bipush 60
    //   684: iand
    //   685: iconst_1
    //   686: ishl
    //   687: iload_1
    //   688: bipush 60
    //   690: ixor
    //   691: iadd
    //   692: istore_1
    //   693: iload_1
    //   694: iconst_m1
    //   695: ixor
    //   696: iload_1
    //   697: iconst_m1
    //   698: iand
    //   699: iconst_1
    //   700: ishl
    //   701: iadd
    //   702: istore_1
    //   703: iload_1
    //   704: sipush 128
    //   707: irem
    //   708: putstatic 53	o/Gz:ॱॱ	I
    //   711: iload_1
    //   712: iconst_2
    //   713: irem
    //   714: ifeq +6 -> 720
    //   717: goto +88 -> 805
    //   720: goto +83 -> 803
    //   723: iconst_0
    //   724: istore_2
    //   725: goto -211 -> 514
    //   728: iload_3
    //   729: istore_2
    //   730: iload 4
    //   732: lookupswitch	default:+28->760, 0:+-397->335, 56:+-625->107
    //   760: iload_3
    //   761: istore_2
    //   762: goto -655 -> 107
    //   765: iload_1
    //   766: tableswitch	default:+22->788, 0:+-465->301, 1:+30->796
    //   788: goto -487 -> 301
    //   791: astore 5
    //   793: aload 5
    //   795: athrow
    //   796: iconst_0
    //   797: ireturn
    //   798: iconst_1
    //   799: istore_1
    //   800: goto -35 -> 765
    //   803: iconst_1
    //   804: ireturn
    //   805: goto -2 -> 803
    // Local variable table:
    //   start	length	slot	name	signature
    //   0	808	0	this	Gz
    //   0	808	1	paramInt	int
    //   162	600	2	i	int
    //   95	666	3	j	int
    //   110	621	4	k	int
    //   10	421	5	localObject1	Object
    //   509	3	5	localNullPointerException1	NullPointerException
    //   791	3	5	localNullPointerException2	NullPointerException
    //   15	18	6	localObject2	Object
    //   369	18	6	localObject3	Object
    // Exception table:
    //   from	to	target	type
    //   35	96	15	finally
    //   389	450	369	finally
    //   6	12	509	java/lang/NullPointerException
    //   17	24	509	java/lang/NullPointerException
    //   29	32	509	java/lang/NullPointerException
    //   32	35	509	java/lang/NullPointerException
    //   360	366	509	java/lang/IllegalStateException
    //   371	378	509	java/lang/IllegalStateException
    //   371	378	509	java/lang/ClassCastException
    //   383	386	509	java/lang/IllegalStateException
    //   383	386	509	java/lang/ClassCastException
    //   386	389	509	java/lang/IllegalStateException
    //   386	389	509	java/lang/ClassCastException
    //   450	453	509	java/lang/IllegalStateException
    //   450	453	509	java/lang/ClassCastException
    //   555	559	509	java/lang/RuntimeException
    //   574	582	509	java/lang/RuntimeException
    //   574	582	509	java/lang/UnsupportedOperationException
    //   17	24	791	java/lang/NullPointerException
    //   29	32	791	java/lang/NullPointerException
    //   32	35	791	java/lang/NullPointerException
    //   214	218	791	java/lang/IllegalStateException
    //   244	252	791	java/lang/IllegalStateException
    //   244	252	791	java/lang/NumberFormatException
    //   594	598	791	java/lang/ArrayStoreException
    //   617	625	791	java/lang/ArrayStoreException
    //   617	625	791	java/lang/NumberFormatException
  }
  
  /* Error */
  private final void ॱ$32e4e300(Context paramContext, Enum paramEnum, int paramInt1, int paramInt2)
  {
    // Byte code:
    //   0: goto +158 -> 158
    //   3: aload 7
    //   5: sipush 210
    //   8: sipush 10531
    //   11: bipush 21
    //   13: invokestatic 90	o/Gz:ˋ	(ICI)Ljava/lang/String;
    //   16: invokevirtual 96	java/lang/String:intern	()Ljava/lang/String;
    //   19: invokevirtual 675	java/lang/StringBuilder:append	(Ljava/lang/String;)Ljava/lang/StringBuilder;
    //   22: iload_3
    //   23: invokevirtual 678	java/lang/StringBuilder:append	(I)Ljava/lang/StringBuilder;
    //   26: astore 7
    //   28: sipush 231
    //   31: iconst_0
    //   32: bipush 20
    //   34: invokestatic 90	o/Gz:ˋ	(ICI)Ljava/lang/String;
    //   37: astore 8
    //   39: goto +940 -> 979
    //   42: bipush 52
    //   44: istore 5
    //   46: goto +359 -> 405
    //   49: bipush 95
    //   51: istore 5
    //   53: goto +968 -> 1021
    //   56: bipush 112
    //   58: sipush 4221
    //   61: bipush 12
    //   63: invokestatic 90	o/Gz:ˋ	(ICI)Ljava/lang/String;
    //   66: invokevirtual 96	java/lang/String:intern	()Ljava/lang/String;
    //   69: astore 7
    //   71: goto +90 -> 161
    //   74: goto +81 -> 155
    //   77: getstatic 51	o/Gz:ʻ	I
    //   80: bipush 92
    //   82: iadd
    //   83: iconst_0
    //   84: iadd
    //   85: iconst_1
    //   86: isub
    //   87: istore 5
    //   89: iload 5
    //   91: sipush 128
    //   94: irem
    //   95: putstatic 53	o/Gz:ॱॱ	I
    //   98: iload 5
    //   100: iconst_2
    //   101: irem
    //   102: ifeq +6 -> 108
    //   105: goto +2534 -> 2639
    //   108: goto +1663 -> 1771
    //   111: goto +2052 -> 2163
    //   114: goto +141 -> 255
    //   117: goto +138 -> 255
    //   120: iconst_0
    //   121: istore_3
    //   122: goto +2686 -> 2808
    //   125: iload 5
    //   127: lookupswitch	default:+25->152, 21:+2314->2441, 52:+2408->2535
    //   152: goto +2383 -> 2535
    //   155: goto +2008 -> 2163
    //   158: goto +314 -> 472
    //   161: getstatic 53	o/Gz:ॱॱ	I
    //   164: istore 5
    //   166: iload 5
    //   168: bipush 62
    //   170: ixor
    //   171: iload 5
    //   173: bipush 62
    //   175: iand
    //   176: iconst_1
    //   177: ishl
    //   178: iadd
    //   179: iconst_0
    //   180: iadd
    //   181: iconst_1
    //   182: isub
    //   183: istore 5
    //   185: iload 5
    //   187: sipush 128
    //   190: irem
    //   191: putstatic 51	o/Gz:ʻ	I
    //   194: iload 5
    //   196: iconst_2
    //   197: irem
    //   198: ifne +6 -> 204
    //   201: goto +370 -> 571
    //   204: goto +1165 -> 1369
    //   207: getstatic 53	o/Gz:ॱॱ	I
    //   210: istore 5
    //   212: iload 5
    //   214: bipush 20
    //   216: iand
    //   217: iload 5
    //   219: bipush 20
    //   221: ior
    //   222: iadd
    //   223: iconst_1
    //   224: isub
    //   225: istore 5
    //   227: iload 5
    //   229: sipush 128
    //   232: irem
    //   233: putstatic 51	o/Gz:ʻ	I
    //   236: iload 5
    //   238: iconst_2
    //   239: irem
    //   240: ifne +6 -> 246
    //   243: goto -194 -> 49
    //   246: goto +2043 -> 2289
    //   249: iconst_1
    //   250: istore 5
    //   252: goto +1529 -> 1781
    //   255: new 671	java/lang/StringBuilder
    //   258: dup
    //   259: invokespecial 679	java/lang/StringBuilder:<init>	()V
    //   262: ldc_w 681
    //   265: invokevirtual 675	java/lang/StringBuilder:append	(Ljava/lang/String;)Ljava/lang/StringBuilder;
    //   268: aload 7
    //   270: invokevirtual 675	java/lang/StringBuilder:append	(Ljava/lang/String;)Ljava/lang/StringBuilder;
    //   273: astore 7
    //   275: goto +870 -> 1145
    //   278: getstatic 687	o/Fh:BLR_DEVICE_ROOTED	Lo/Fh;
    //   281: astore_2
    //   282: goto +2096 -> 2378
    //   285: sipush 210
    //   288: sipush 10531
    //   291: bipush 54
    //   293: invokestatic 90	o/Gz:ˋ	(ICI)Ljava/lang/String;
    //   296: astore 8
    //   298: aload 8
    //   300: invokevirtual 96	java/lang/String:intern	()Ljava/lang/String;
    //   303: astore 8
    //   305: aload 7
    //   307: aload 8
    //   309: invokevirtual 675	java/lang/StringBuilder:append	(Ljava/lang/String;)Ljava/lang/StringBuilder;
    //   312: astore 7
    //   314: aload 7
    //   316: iload_3
    //   317: invokevirtual 678	java/lang/StringBuilder:append	(I)Ljava/lang/StringBuilder;
    //   320: astore 7
    //   322: sipush 5765
    //   325: iconst_0
    //   326: bipush 108
    //   328: invokestatic 90	o/Gz:ˋ	(ICI)Ljava/lang/String;
    //   331: astore 8
    //   333: goto +646 -> 979
    //   336: getstatic 53	o/Gz:ॱॱ	I
    //   339: istore 6
    //   341: iload 6
    //   343: bipush 89
    //   345: iand
    //   346: istore 5
    //   348: iload 6
    //   350: bipush 89
    //   352: ixor
    //   353: iload 6
    //   355: bipush 89
    //   357: iand
    //   358: ior
    //   359: ineg
    //   360: istore 6
    //   362: iload 6
    //   364: ineg
    //   365: iload 5
    //   367: ixor
    //   368: iload 5
    //   370: iload 6
    //   372: ineg
    //   373: iand
    //   374: iconst_1
    //   375: ishl
    //   376: iadd
    //   377: istore 5
    //   379: iload 5
    //   381: sipush 128
    //   384: irem
    //   385: putstatic 51	o/Gz:ʻ	I
    //   388: iload 5
    //   390: iconst_2
    //   391: irem
    //   392: ifne +6 -> 398
    //   395: goto +2340 -> 2735
    //   398: goto +740 -> 1138
    //   401: return
    //   402: goto +1761 -> 2163
    //   405: iload 5
    //   407: lookupswitch	default:+25->432, 52:+-290->117, 64:+1706->2113
    //   432: goto +1681 -> 2113
    //   435: aload 7
    //   437: aload 8
    //   439: invokestatic 101	o/vq:ˋ	(Ljava/lang/Object;Ljava/lang/String;)V
    //   442: aload_0
    //   443: aload_1
    //   444: aload 7
    //   446: aload_2
    //   447: invokevirtual 690	o/Gz:ˊ	(Landroid/content/Context;Ljava/lang/String;Lo/Fh;)V
    //   450: goto +87 -> 537
    //   453: sipush 161
    //   456: ldc_w 691
    //   459: bipush 21
    //   461: invokestatic 90	o/Gz:ˋ	(ICI)Ljava/lang/String;
    //   464: invokevirtual 96	java/lang/String:intern	()Ljava/lang/String;
    //   467: astore 7
    //   469: goto +1602 -> 2071
    //   472: getstatic 51	o/Gz:ʻ	I
    //   475: istore 6
    //   477: iload 6
    //   479: bipush 67
    //   481: iand
    //   482: istore 5
    //   484: iload 6
    //   486: bipush 67
    //   488: iand
    //   489: iload 6
    //   491: bipush 67
    //   493: ixor
    //   494: ior
    //   495: istore 6
    //   497: iload 5
    //   499: iload 6
    //   501: ior
    //   502: iconst_1
    //   503: ishl
    //   504: iload 5
    //   506: iload 6
    //   508: ixor
    //   509: isub
    //   510: istore 5
    //   512: iload 5
    //   514: sipush 128
    //   517: irem
    //   518: putstatic 53	o/Gz:ॱॱ	I
    //   521: iload 5
    //   523: iconst_2
    //   524: irem
    //   525: ifeq +6 -> 531
    //   528: goto +143 -> 671
    //   531: goto +1416 -> 1947
    //   534: goto +1629 -> 2163
    //   537: getstatic 51	o/Gz:ʻ	I
    //   540: istore_3
    //   541: iload_3
    //   542: bipush 101
    //   544: iand
    //   545: iload_3
    //   546: bipush 101
    //   548: ior
    //   549: iadd
    //   550: istore_3
    //   551: iload_3
    //   552: sipush 128
    //   555: irem
    //   556: putstatic 53	o/Gz:ॱॱ	I
    //   559: iload_3
    //   560: iconst_2
    //   561: irem
    //   562: ifeq +6 -> 568
    //   565: goto +1137 -> 1702
    //   568: goto +630 -> 1198
    //   571: iconst_1
    //   572: istore 5
    //   574: goto +1767 -> 2341
    //   577: getstatic 53	o/Gz:ॱॱ	I
    //   580: istore 6
    //   582: iload 6
    //   584: iconst_1
    //   585: ixor
    //   586: iload 6
    //   588: iconst_1
    //   589: iand
    //   590: ior
    //   591: iconst_1
    //   592: ishl
    //   593: istore 5
    //   595: iload 6
    //   597: iconst_1
    //   598: ixor
    //   599: ineg
    //   600: istore 6
    //   602: iload 5
    //   604: iload 6
    //   606: ior
    //   607: iconst_1
    //   608: ishl
    //   609: iload 5
    //   611: iload 6
    //   613: ixor
    //   614: isub
    //   615: istore 5
    //   617: iload 5
    //   619: sipush 128
    //   622: irem
    //   623: putstatic 51	o/Gz:ʻ	I
    //   626: iload 5
    //   628: iconst_2
    //   629: irem
    //   630: ifne +6 -> 636
    //   633: goto +1302 -> 1935
    //   636: goto -522 -> 114
    //   639: goto +1524 -> 2163
    //   642: iload 5
    //   644: tableswitch	default:+24->668, 0:+-5->639, 1:+-242->402
    //   668: goto -29 -> 639
    //   671: iconst_1
    //   672: istore 5
    //   674: goto +432 -> 1106
    //   677: bipush 63
    //   679: istore 5
    //   681: goto +1058 -> 1739
    //   684: getstatic 696	o/Gx:ॱ	[I
    //   687: astore 7
    //   689: goto +17 -> 706
    //   692: astore_1
    //   693: aload_1
    //   694: invokevirtual 630	java/lang/Throwable:getCause	()Ljava/lang/Throwable;
    //   697: astore_2
    //   698: aload_2
    //   699: ifnull +5 -> 704
    //   702: aload_2
    //   703: athrow
    //   704: aload_1
    //   705: athrow
    //   706: bipush 7
    //   708: sipush 139
    //   711: sipush 173
    //   714: invokestatic 605	o/O:ˋ	(IIC)Ljava/lang/Object;
    //   717: checkcast 607	java/lang/Class
    //   720: ldc_w 698
    //   723: aconst_null
    //   724: invokevirtual 642	java/lang/Class:getMethod	(Ljava/lang/String;[Ljava/lang/Class;)Ljava/lang/reflect/Method;
    //   727: aload_2
    //   728: aconst_null
    //   729: invokevirtual 654	java/lang/reflect/Method:invoke	(Ljava/lang/Object;[Ljava/lang/Object;)Ljava/lang/Object;
    //   732: checkcast 634	java/lang/Integer
    //   735: invokevirtual 658	java/lang/Integer:intValue	()I
    //   738: istore 5
    //   740: aload 7
    //   742: iload 5
    //   744: iaload
    //   745: tableswitch	default:+47->792, 1:+1208->1953, 2:+2039->2784, 3:+-689->56, 4:+1974->2719, 5:+1793->2538, 6:+-292->453, 7:+527->1272, 8:+211->956
    //   792: goto +939 -> 1731
    //   795: aload 8
    //   797: invokevirtual 96	java/lang/String:intern	()Ljava/lang/String;
    //   800: astore 8
    //   802: goto +17 -> 819
    //   805: astore_1
    //   806: aload_1
    //   807: invokevirtual 630	java/lang/Throwable:getCause	()Ljava/lang/Throwable;
    //   810: astore_2
    //   811: aload_2
    //   812: ifnull +5 -> 817
    //   815: aload_2
    //   816: athrow
    //   817: aload_1
    //   818: athrow
    //   819: iconst_4
    //   820: bipush 42
    //   822: ldc_w 699
    //   825: invokestatic 605	o/O:ˋ	(IIC)Ljava/lang/Object;
    //   828: checkcast 607	java/lang/Class
    //   831: ldc_w 700
    //   834: iconst_2
    //   835: anewarray 607	java/lang/Class
    //   838: dup
    //   839: iconst_0
    //   840: ldc 92
    //   842: aastore
    //   843: dup
    //   844: iconst_1
    //   845: ldc 92
    //   847: aastore
    //   848: invokevirtual 642	java/lang/Class:getMethod	(Ljava/lang/String;[Ljava/lang/Class;)Ljava/lang/reflect/Method;
    //   851: aconst_null
    //   852: iconst_2
    //   853: anewarray 644	java/lang/Object
    //   856: dup
    //   857: iconst_0
    //   858: aload 8
    //   860: aastore
    //   861: dup
    //   862: iconst_1
    //   863: aload 7
    //   865: aastore
    //   866: invokevirtual 654	java/lang/reflect/Method:invoke	(Ljava/lang/Object;[Ljava/lang/Object;)Ljava/lang/Object;
    //   869: pop
    //   870: getstatic 705	o/vw:ˊ	Lo/vw;
    //   873: astore 7
    //   875: aload_0
    //   876: getstatic 710	o/Gu$ˏ:device_rooted_security_problems	I
    //   879: invokevirtual 713	o/Gz:ˎ	(I)Ljava/lang/String;
    //   882: astore 9
    //   884: goto +958 -> 1842
    //   887: iconst_5
    //   888: iconst_2
    //   889: idiv
    //   890: istore 5
    //   892: goto +1271 -> 2163
    //   895: iconst_3
    //   896: istore 5
    //   898: goto +1232 -> 2130
    //   901: getstatic 53	o/Gz:ॱॱ	I
    //   904: istore 5
    //   906: iload 5
    //   908: bipush 78
    //   910: ior
    //   911: iconst_1
    //   912: ishl
    //   913: iload 5
    //   915: bipush 78
    //   917: ixor
    //   918: isub
    //   919: istore 5
    //   921: iload 5
    //   923: iconst_m1
    //   924: ixor
    //   925: iload 5
    //   927: iconst_m1
    //   928: iand
    //   929: iconst_1
    //   930: ishl
    //   931: iadd
    //   932: istore 5
    //   934: iload 5
    //   936: sipush 128
    //   939: irem
    //   940: putstatic 51	o/Gz:ʻ	I
    //   943: iload 5
    //   945: iconst_2
    //   946: irem
    //   947: ifne +6 -> 953
    //   950: goto +1680 -> 2630
    //   953: goto +825 -> 1778
    //   956: sipush 196
    //   959: ldc_w 714
    //   962: bipush 14
    //   964: invokestatic 90	o/Gz:ˋ	(ICI)Ljava/lang/String;
    //   967: invokevirtual 96	java/lang/String:intern	()Ljava/lang/String;
    //   970: astore 7
    //   972: goto +1513 -> 2485
    //   975: aconst_null
    //   976: arraylength
    //   977: istore_3
    //   978: return
    //   979: aload 7
    //   981: aload 8
    //   983: invokevirtual 96	java/lang/String:intern	()Ljava/lang/String;
    //   986: invokevirtual 675	java/lang/StringBuilder:append	(Ljava/lang/String;)Ljava/lang/StringBuilder;
    //   989: iload 4
    //   991: invokevirtual 678	java/lang/StringBuilder:append	(I)Ljava/lang/StringBuilder;
    //   994: invokevirtual 717	java/lang/StringBuilder:toString	()Ljava/lang/String;
    //   997: astore 7
    //   999: iconst_0
    //   1000: iconst_0
    //   1001: bipush 8
    //   1003: invokestatic 90	o/Gz:ˋ	(ICI)Ljava/lang/String;
    //   1006: astore 8
    //   1008: goto +1638 -> 2646
    //   1011: astore_1
    //   1012: aload_1
    //   1013: athrow
    //   1014: getstatic 720	o/Fh:BLR_APK_UNTRUSTED_SOURCE	Lo/Fh;
    //   1017: astore_2
    //   1018: goto +1284 -> 2302
    //   1021: iload 5
    //   1023: lookupswitch	default:+25->1048, 76:+1780->2803, 95:+362->1385
    //   1048: goto +337 -> 1385
    //   1051: goto -796 -> 255
    //   1054: goto +1109 -> 2163
    //   1057: getstatic 51	o/Gz:ʻ	I
    //   1060: istore 5
    //   1062: iload 5
    //   1064: bipush 69
    //   1066: ior
    //   1067: iconst_1
    //   1068: ishl
    //   1069: iload 5
    //   1071: bipush 69
    //   1073: ixor
    //   1074: isub
    //   1075: istore 5
    //   1077: iload 5
    //   1079: sipush 128
    //   1082: irem
    //   1083: putstatic 53	o/Gz:ॱॱ	I
    //   1086: iload 5
    //   1088: iconst_2
    //   1089: irem
    //   1090: ifeq +6 -> 1096
    //   1093: goto +208 -> 1301
    //   1096: goto +1682 -> 2778
    //   1099: bipush 58
    //   1101: istore 5
    //   1103: goto +1346 -> 2449
    //   1106: iload 5
    //   1108: tableswitch	default:+24->1132, 0:+-424->684, 1:+468->1576
    //   1132: goto +444 -> 1576
    //   1135: goto +1498 -> 2633
    //   1138: bipush 68
    //   1140: istore 5
    //   1142: goto +896 -> 2038
    //   1145: getstatic 53	o/Gz:ॱॱ	I
    //   1148: istore 5
    //   1150: iload 5
    //   1152: bipush 11
    //   1154: iand
    //   1155: iload 5
    //   1157: bipush 11
    //   1159: ixor
    //   1160: iload 5
    //   1162: bipush 11
    //   1164: iand
    //   1165: ior
    //   1166: iadd
    //   1167: istore 5
    //   1169: iload 5
    //   1171: sipush 128
    //   1174: irem
    //   1175: putstatic 51	o/Gz:ʻ	I
    //   1178: iload 5
    //   1180: iconst_2
    //   1181: irem
    //   1182: ifne +6 -> 1188
    //   1185: goto +931 -> 2116
    //   1188: goto -89 -> 1099
    //   1191: getstatic 720	o/Fh:BLR_APK_UNTRUSTED_SOURCE	Lo/Fh;
    //   1194: astore_2
    //   1195: goto -859 -> 336
    //   1198: iconst_0
    //   1199: istore_3
    //   1200: goto +504 -> 1704
    //   1203: getstatic 53	o/Gz:ॱॱ	I
    //   1206: istore 6
    //   1208: iload 6
    //   1210: bipush 79
    //   1212: iand
    //   1213: iconst_m1
    //   1214: ixor
    //   1215: iload 6
    //   1217: bipush 79
    //   1219: ior
    //   1220: iand
    //   1221: istore 5
    //   1223: iload 6
    //   1225: bipush 79
    //   1227: iand
    //   1228: iconst_1
    //   1229: ishl
    //   1230: istore 6
    //   1232: iload 5
    //   1234: iload 6
    //   1236: ixor
    //   1237: iload 5
    //   1239: iload 6
    //   1241: iand
    //   1242: iconst_1
    //   1243: ishl
    //   1244: iadd
    //   1245: istore 5
    //   1247: iload 5
    //   1249: sipush 128
    //   1252: irem
    //   1253: putstatic 51	o/Gz:ʻ	I
    //   1256: iload 5
    //   1258: iconst_2
    //   1259: irem
    //   1260: ifne +6 -> 1266
    //   1263: goto -1189 -> 74
    //   1266: goto -1111 -> 155
    //   1269: goto -474 -> 795
    //   1272: sipush 182
    //   1275: ldc_w 721
    //   1278: bipush 14
    //   1280: invokestatic 90	o/Gz:ˋ	(ICI)Ljava/lang/String;
    //   1283: invokevirtual 96	java/lang/String:intern	()Ljava/lang/String;
    //   1286: astore 7
    //   1288: goto -231 -> 1057
    //   1291: goto +872 -> 2163
    //   1294: bipush 84
    //   1296: istore 5
    //   1298: goto +832 -> 2130
    //   1301: iconst_0
    //   1302: istore 5
    //   1304: goto -662 -> 642
    //   1307: getstatic 53	o/Gz:ॱॱ	I
    //   1310: istore 6
    //   1312: iload 6
    //   1314: bipush 13
    //   1316: iand
    //   1317: istore 5
    //   1319: iload 6
    //   1321: bipush 13
    //   1323: iand
    //   1324: iload 6
    //   1326: bipush 13
    //   1328: ixor
    //   1329: ior
    //   1330: istore 6
    //   1332: iload 5
    //   1334: iload 6
    //   1336: ior
    //   1337: iconst_1
    //   1338: ishl
    //   1339: iload 5
    //   1341: iload 6
    //   1343: ixor
    //   1344: isub
    //   1345: istore 5
    //   1347: iload 5
    //   1349: sipush 128
    //   1352: irem
    //   1353: putstatic 51	o/Gz:ʻ	I
    //   1356: iload 5
    //   1358: iconst_2
    //   1359: irem
    //   1360: ifne +6 -> 1366
    //   1363: goto -1114 -> 249
    //   1366: goto +930 -> 2296
    //   1369: iconst_0
    //   1370: istore 5
    //   1372: goto +969 -> 2341
    //   1375: getstatic 724	o/Fh:BLR_DEVICE_FRAUD_SUSPECTED	Lo/Fh;
    //   1378: astore_2
    //   1379: goto -478 -> 901
    //   1382: astore_1
    //   1383: aload_1
    //   1384: athrow
    //   1385: goto -1130 -> 255
    //   1388: goto -1133 -> 255
    //   1391: getstatic 51	o/Gz:ʻ	I
    //   1394: istore 6
    //   1396: iload 6
    //   1398: iconst_1
    //   1399: ixor
    //   1400: istore 5
    //   1402: iload 6
    //   1404: iconst_1
    //   1405: iand
    //   1406: iconst_1
    //   1407: ishl
    //   1408: istore 6
    //   1410: iload 5
    //   1412: iload 6
    //   1414: iand
    //   1415: iload 5
    //   1417: iload 6
    //   1419: ior
    //   1420: iadd
    //   1421: istore 5
    //   1423: iload 5
    //   1425: sipush 128
    //   1428: irem
    //   1429: putstatic 53	o/Gz:ॱॱ	I
    //   1432: iload 5
    //   1434: iconst_2
    //   1435: irem
    //   1436: ifeq +6 -> 1442
    //   1439: goto -1397 -> 42
    //   1442: goto +840 -> 2282
    //   1445: aload 7
    //   1447: sipush 301
    //   1450: iconst_0
    //   1451: bipush 19
    //   1453: invokestatic 90	o/Gz:ˋ	(ICI)Ljava/lang/String;
    //   1456: invokevirtual 96	java/lang/String:intern	()Ljava/lang/String;
    //   1459: invokestatic 101	o/vq:ˋ	(Ljava/lang/Object;Ljava/lang/String;)V
    //   1462: goto +17 -> 1479
    //   1465: astore_1
    //   1466: aload_1
    //   1467: invokevirtual 630	java/lang/Throwable:getCause	()Ljava/lang/Throwable;
    //   1470: astore_2
    //   1471: aload_2
    //   1472: ifnull +5 -> 1477
    //   1475: aload_2
    //   1476: athrow
    //   1477: aload_1
    //   1478: athrow
    //   1479: iconst_3
    //   1480: iconst_0
    //   1481: ldc_w 725
    //   1484: invokestatic 605	o/O:ˋ	(IIC)Ljava/lang/Object;
    //   1487: checkcast 607	java/lang/Class
    //   1490: ldc_w 608
    //   1493: aconst_null
    //   1494: invokevirtual 642	java/lang/Class:getMethod	(Ljava/lang/String;[Ljava/lang/Class;)Ljava/lang/reflect/Method;
    //   1497: aload 7
    //   1499: aconst_null
    //   1500: invokevirtual 654	java/lang/reflect/Method:invoke	(Ljava/lang/Object;[Ljava/lang/Object;)Ljava/lang/Object;
    //   1503: astore 7
    //   1505: aload 8
    //   1507: iconst_0
    //   1508: aload 7
    //   1510: aastore
    //   1511: goto +371 -> 1882
    //   1514: getstatic 53	o/Gz:ॱॱ	I
    //   1517: istore 6
    //   1519: iload 6
    //   1521: bipush 93
    //   1523: iand
    //   1524: istore 5
    //   1526: iload 6
    //   1528: bipush 93
    //   1530: iand
    //   1531: iload 6
    //   1533: bipush 93
    //   1535: ixor
    //   1536: ior
    //   1537: istore 6
    //   1539: iload 5
    //   1541: iload 6
    //   1543: ixor
    //   1544: iload 5
    //   1546: iload 6
    //   1548: iand
    //   1549: iconst_1
    //   1550: ishl
    //   1551: iadd
    //   1552: istore 5
    //   1554: iload 5
    //   1556: sipush 128
    //   1559: irem
    //   1560: putstatic 51	o/Gz:ʻ	I
    //   1563: iload 5
    //   1565: iconst_2
    //   1566: irem
    //   1567: ifne +6 -> 1573
    //   1570: goto +553 -> 2123
    //   1573: goto -896 -> 677
    //   1576: getstatic 696	o/Gx:ॱ	[I
    //   1579: astore 7
    //   1581: goto +17 -> 1598
    //   1584: astore_1
    //   1585: aload_1
    //   1586: invokevirtual 630	java/lang/Throwable:getCause	()Ljava/lang/Throwable;
    //   1589: astore_2
    //   1590: aload_2
    //   1591: ifnull +5 -> 1596
    //   1594: aload_2
    //   1595: athrow
    //   1596: aload_1
    //   1597: athrow
    //   1598: bipush 7
    //   1600: sipush 139
    //   1603: sipush 173
    //   1606: invokestatic 605	o/O:ˋ	(IIC)Ljava/lang/Object;
    //   1609: checkcast 607	java/lang/Class
    //   1612: ldc_w 698
    //   1615: aconst_null
    //   1616: invokevirtual 642	java/lang/Class:getMethod	(Ljava/lang/String;[Ljava/lang/Class;)Ljava/lang/reflect/Method;
    //   1619: aload_2
    //   1620: aconst_null
    //   1621: invokevirtual 654	java/lang/reflect/Method:invoke	(Ljava/lang/Object;[Ljava/lang/Object;)Ljava/lang/Object;
    //   1624: checkcast 634	java/lang/Integer
    //   1627: invokevirtual 658	java/lang/Integer:intValue	()I
    //   1630: istore 5
    //   1632: aload 7
    //   1634: iload 5
    //   1636: iaload
    //   1637: istore 5
    //   1639: aconst_null
    //   1640: arraylength
    //   1641: istore 6
    //   1643: iload 5
    //   1645: tableswitch	default:+47->1692, 1:+308->1953, 2:+1139->2784, 3:+-1589->56, 4:+1074->2719, 5:+893->2538, 6:+-1192->453, 7:+-373->1272, 8:+-689->956
    //   1692: goto +39 -> 1731
    //   1695: getstatic 724	o/Fh:BLR_DEVICE_FRAUD_SUSPECTED	Lo/Fh;
    //   1698: astore_2
    //   1699: goto -1492 -> 207
    //   1702: iconst_1
    //   1703: istore_3
    //   1704: iload_3
    //   1705: tableswitch	default:+23->1728, 0:+-1304->401, 1:+-730->975
    //   1728: goto -753 -> 975
    //   1731: new 727	o/uE
    //   1734: dup
    //   1735: invokespecial 728	o/uE:<init>	()V
    //   1738: athrow
    //   1739: iload 5
    //   1741: lookupswitch	default:+27->1768, 49:+1059->2800, 63:+-1630->111
    //   1768: goto -1657 -> 111
    //   1771: bipush 52
    //   1773: istore 5
    //   1775: goto -1650 -> 125
    //   1778: goto -1523 -> 255
    //   1781: iload 5
    //   1783: tableswitch	default:+21->1804, 0:+853->2636, 1:+-1249->534
    //   1804: goto -1270 -> 534
    //   1807: getstatic 53	o/Gz:ॱॱ	I
    //   1810: bipush 96
    //   1812: iadd
    //   1813: iconst_1
    //   1814: isub
    //   1815: istore 5
    //   1817: iload 5
    //   1819: sipush 128
    //   1822: irem
    //   1823: putstatic 51	o/Gz:ʻ	I
    //   1826: iload 5
    //   1828: iconst_2
    //   1829: irem
    //   1830: ifne +6 -> 1836
    //   1833: goto -698 -> 1135
    //   1836: goto +797 -> 2633
    //   1839: goto +324 -> 2163
    //   1842: getstatic 51	o/Gz:ʻ	I
    //   1845: bipush 40
    //   1847: iadd
    //   1848: istore_3
    //   1849: iload_3
    //   1850: iconst_m1
    //   1851: ior
    //   1852: iconst_1
    //   1853: ishl
    //   1854: iload_3
    //   1855: iconst_m1
    //   1856: ixor
    //   1857: isub
    //   1858: istore_3
    //   1859: iload_3
    //   1860: sipush 128
    //   1863: irem
    //   1864: putstatic 53	o/Gz:ॱॱ	I
    //   1867: iload_3
    //   1868: iconst_2
    //   1869: irem
    //   1870: ifeq +6 -> 1876
    //   1873: goto +933 -> 2806
    //   1876: goto -1756 -> 120
    //   1879: goto +863 -> 2742
    //   1882: getstatic 51	o/Gz:ʻ	I
    //   1885: istore_3
    //   1886: iload_3
    //   1887: bipush 32
    //   1889: iand
    //   1890: iconst_1
    //   1891: ishl
    //   1892: iload_3
    //   1893: bipush 32
    //   1895: ixor
    //   1896: iadd
    //   1897: istore_3
    //   1898: iload_3
    //   1899: iconst_m1
    //   1900: ixor
    //   1901: iload_3
    //   1902: iconst_m1
    //   1903: iand
    //   1904: iconst_1
    //   1905: ishl
    //   1906: iadd
    //   1907: istore_3
    //   1908: iload_3
    //   1909: sipush 128
    //   1912: irem
    //   1913: putstatic 53	o/Gz:ॱॱ	I
    //   1916: iload_3
    //   1917: iconst_2
    //   1918: irem
    //   1919: ifeq +6 -> 1925
    //   1922: goto -43 -> 1879
    //   1925: goto +817 -> 2742
    //   1928: getstatic 724	o/Fh:BLR_DEVICE_FRAUD_SUSPECTED	Lo/Fh;
    //   1931: astore_2
    //   1932: goto -541 -> 1391
    //   1935: goto -1821 -> 114
    //   1938: goto -99 -> 1839
    //   1941: goto -1686 -> 255
    //   1944: goto -1689 -> 255
    //   1947: iconst_0
    //   1948: istore 5
    //   1950: goto -844 -> 1106
    //   1953: bipush 88
    //   1955: iconst_0
    //   1956: iconst_4
    //   1957: invokestatic 90	o/Gz:ˋ	(ICI)Ljava/lang/String;
    //   1960: invokevirtual 96	java/lang/String:intern	()Ljava/lang/String;
    //   1963: astore 7
    //   1965: goto -158 -> 1807
    //   1968: aload 9
    //   1970: sipush 251
    //   1973: sipush 27520
    //   1976: bipush 50
    //   1978: invokestatic 90	o/Gz:ˋ	(ICI)Ljava/lang/String;
    //   1981: invokevirtual 96	java/lang/String:intern	()Ljava/lang/String;
    //   1984: invokestatic 101	o/vq:ˋ	(Ljava/lang/Object;Ljava/lang/String;)V
    //   1987: iconst_1
    //   1988: anewarray 644	java/lang/Object
    //   1991: astore 8
    //   1993: goto +17 -> 2010
    //   1996: astore_1
    //   1997: aload_1
    //   1998: invokevirtual 630	java/lang/Throwable:getCause	()Ljava/lang/Throwable;
    //   2001: astore_2
    //   2002: aload_2
    //   2003: ifnull +5 -> 2008
    //   2006: aload_2
    //   2007: athrow
    //   2008: aload_1
    //   2009: athrow
    //   2010: iconst_3
    //   2011: iconst_0
    //   2012: ldc_w 725
    //   2015: invokestatic 605	o/O:ˋ	(IIC)Ljava/lang/Object;
    //   2018: checkcast 607	java/lang/Class
    //   2021: ldc_w 729
    //   2024: aconst_null
    //   2025: invokevirtual 642	java/lang/Class:getMethod	(Ljava/lang/String;[Ljava/lang/Class;)Ljava/lang/reflect/Method;
    //   2028: aconst_null
    //   2029: aconst_null
    //   2030: invokevirtual 654	java/lang/reflect/Method:invoke	(Ljava/lang/Object;[Ljava/lang/Object;)Ljava/lang/Object;
    //   2033: astore 7
    //   2035: goto -590 -> 1445
    //   2038: iload 5
    //   2040: lookupswitch	default:+28->2068, 43:+-652->1388, 68:+-989->1051
    //   2068: goto -680 -> 1388
    //   2071: getstatic 51	o/Gz:ʻ	I
    //   2074: istore 5
    //   2076: iload 5
    //   2078: bipush 25
    //   2080: ixor
    //   2081: iload 5
    //   2083: bipush 25
    //   2085: iand
    //   2086: iconst_1
    //   2087: ishl
    //   2088: iadd
    //   2089: istore 5
    //   2091: iload 5
    //   2093: sipush 128
    //   2096: irem
    //   2097: putstatic 53	o/Gz:ॱॱ	I
    //   2100: iload 5
    //   2102: iconst_2
    //   2103: irem
    //   2104: ifeq +6 -> 2110
    //   2107: goto +375 -> 2482
    //   2110: goto -1056 -> 1054
    //   2113: goto -1858 -> 255
    //   2116: bipush 36
    //   2118: istore 5
    //   2120: goto +329 -> 2449
    //   2123: bipush 49
    //   2125: istore 5
    //   2127: goto -388 -> 1739
    //   2130: iload 5
    //   2132: lookupswitch	default:+28->2160, 3:+495->2627, 84:+-191->1941
    //   2160: goto +467 -> 2627
    //   2163: getstatic 731	o/Gx:ˋ	[I
    //   2166: astore 8
    //   2168: goto +17 -> 2185
    //   2171: astore_1
    //   2172: aload_1
    //   2173: invokevirtual 630	java/lang/Throwable:getCause	()Ljava/lang/Throwable;
    //   2176: astore_2
    //   2177: aload_2
    //   2178: ifnull +5 -> 2183
    //   2181: aload_2
    //   2182: athrow
    //   2183: aload_1
    //   2184: athrow
    //   2185: bipush 7
    //   2187: sipush 139
    //   2190: sipush 173
    //   2193: invokestatic 605	o/O:ˋ	(IIC)Ljava/lang/Object;
    //   2196: checkcast 607	java/lang/Class
    //   2199: ldc_w 698
    //   2202: aconst_null
    //   2203: invokevirtual 642	java/lang/Class:getMethod	(Ljava/lang/String;[Ljava/lang/Class;)Ljava/lang/reflect/Method;
    //   2206: aload_2
    //   2207: aconst_null
    //   2208: invokevirtual 654	java/lang/reflect/Method:invoke	(Ljava/lang/Object;[Ljava/lang/Object;)Ljava/lang/Object;
    //   2211: checkcast 634	java/lang/Integer
    //   2214: invokevirtual 658	java/lang/Integer:intValue	()I
    //   2217: istore 5
    //   2219: aload 8
    //   2221: iload 5
    //   2223: iaload
    //   2224: tableswitch	default:+48->2272, 1:+110->2334, 2:+-1210->1014, 3:+-1033->1191, 4:+-1946->278, 5:+-849->1375, 6:+-296->1928, 7:+-529->1695, 8:+51->2275
    //   2272: goto +98 -> 2370
    //   2275: getstatic 687	o/Fh:BLR_DEVICE_ROOTED	Lo/Fh;
    //   2278: astore_2
    //   2279: goto -2202 -> 77
    //   2282: bipush 64
    //   2284: istore 5
    //   2286: goto -1881 -> 405
    //   2289: bipush 76
    //   2291: istore 5
    //   2293: goto -1272 -> 1021
    //   2296: iconst_0
    //   2297: istore 5
    //   2299: goto -518 -> 1781
    //   2302: getstatic 53	o/Gz:ॱॱ	I
    //   2305: bipush 52
    //   2307: iadd
    //   2308: iconst_1
    //   2309: isub
    //   2310: istore 5
    //   2312: iload 5
    //   2314: sipush 128
    //   2317: irem
    //   2318: putstatic 51	o/Gz:ʻ	I
    //   2321: iload 5
    //   2323: iconst_2
    //   2324: irem
    //   2325: ifne +6 -> 2331
    //   2328: goto -1034 -> 1294
    //   2331: goto -1436 -> 895
    //   2334: getstatic 734	o/Fh:BLR_DEVICE_NONE	Lo/Fh;
    //   2337: astore_2
    //   2338: goto -1761 -> 577
    //   2341: iload 5
    //   2343: tableswitch	default:+21->2364, 0:+-1052->1291, 1:+-1456->887
    //   2364: goto -1477 -> 887
    //   2367: goto -1932 -> 435
    //   2370: new 727	o/uE
    //   2373: dup
    //   2374: invokespecial 728	o/uE:<init>	()V
    //   2377: athrow
    //   2378: getstatic 53	o/Gz:ॱॱ	I
    //   2381: istore 6
    //   2383: iload 6
    //   2385: bipush 15
    //   2387: ixor
    //   2388: iload 6
    //   2390: bipush 15
    //   2392: iand
    //   2393: ior
    //   2394: iconst_1
    //   2395: ishl
    //   2396: istore 5
    //   2398: iload 6
    //   2400: bipush 15
    //   2402: ixor
    //   2403: ineg
    //   2404: istore 6
    //   2406: iload 5
    //   2408: iload 6
    //   2410: iand
    //   2411: iload 5
    //   2413: iload 6
    //   2415: ior
    //   2416: iadd
    //   2417: istore 5
    //   2419: iload 5
    //   2421: sipush 128
    //   2424: irem
    //   2425: putstatic 51	o/Gz:ʻ	I
    //   2428: iload 5
    //   2430: iconst_2
    //   2431: irem
    //   2432: ifne +6 -> 2438
    //   2435: goto +44 -> 2479
    //   2438: goto -494 -> 1944
    //   2441: iconst_2
    //   2442: iconst_3
    //   2443: idiv
    //   2444: istore 5
    //   2446: goto -2191 -> 255
    //   2449: iload 5
    //   2451: lookupswitch	default:+25->2476, 36:+-2166->285, 58:+-2448->3
    //   2476: goto -2191 -> 285
    //   2479: goto -535 -> 1944
    //   2482: goto -1428 -> 1054
    //   2485: getstatic 53	o/Gz:ॱॱ	I
    //   2488: istore 5
    //   2490: iload 5
    //   2492: bipush -8
    //   2494: iand
    //   2495: iload 5
    //   2497: iconst_m1
    //   2498: ixor
    //   2499: bipush 7
    //   2501: iand
    //   2502: ior
    //   2503: iload 5
    //   2505: bipush 7
    //   2507: iand
    //   2508: iconst_1
    //   2509: ishl
    //   2510: iadd
    //   2511: istore 5
    //   2513: iload 5
    //   2515: sipush 128
    //   2518: irem
    //   2519: putstatic 51	o/Gz:ʻ	I
    //   2522: iload 5
    //   2524: iconst_2
    //   2525: irem
    //   2526: ifne +6 -> 2532
    //   2529: goto -591 -> 1938
    //   2532: goto -693 -> 1839
    //   2535: goto -2280 -> 255
    //   2538: sipush 142
    //   2541: sipush 5174
    //   2544: bipush 19
    //   2546: invokestatic 90	o/Gz:ˋ	(ICI)Ljava/lang/String;
    //   2549: invokevirtual 96	java/lang/String:intern	()Ljava/lang/String;
    //   2552: astore 7
    //   2554: goto -1351 -> 1203
    //   2557: aload 9
    //   2559: sipush 251
    //   2562: sipush 27520
    //   2565: bipush 116
    //   2567: invokestatic 90	o/Gz:ˋ	(ICI)Ljava/lang/String;
    //   2570: invokevirtual 96	java/lang/String:intern	()Ljava/lang/String;
    //   2573: invokestatic 101	o/vq:ˋ	(Ljava/lang/Object;Ljava/lang/String;)V
    //   2576: iconst_1
    //   2577: anewarray 644	java/lang/Object
    //   2580: astore 8
    //   2582: goto +17 -> 2599
    //   2585: astore_1
    //   2586: aload_1
    //   2587: invokevirtual 630	java/lang/Throwable:getCause	()Ljava/lang/Throwable;
    //   2590: astore_2
    //   2591: aload_2
    //   2592: ifnull +5 -> 2597
    //   2595: aload_2
    //   2596: athrow
    //   2597: aload_1
    //   2598: athrow
    //   2599: iconst_3
    //   2600: iconst_0
    //   2601: ldc_w 725
    //   2604: invokestatic 605	o/O:ˋ	(IIC)Ljava/lang/Object;
    //   2607: checkcast 607	java/lang/Class
    //   2610: ldc_w 729
    //   2613: aconst_null
    //   2614: invokevirtual 642	java/lang/Class:getMethod	(Ljava/lang/String;[Ljava/lang/Class;)Ljava/lang/reflect/Method;
    //   2617: aconst_null
    //   2618: aconst_null
    //   2619: invokevirtual 654	java/lang/reflect/Method:invoke	(Ljava/lang/Object;[Ljava/lang/Object;)Ljava/lang/Object;
    //   2622: astore 7
    //   2624: goto -1179 -> 1445
    //   2627: goto -2372 -> 255
    //   2630: goto -852 -> 1778
    //   2633: goto -470 -> 2163
    //   2636: goto -473 -> 2163
    //   2639: bipush 21
    //   2641: istore 5
    //   2643: goto -2518 -> 125
    //   2646: getstatic 51	o/Gz:ʻ	I
    //   2649: bipush 111
    //   2651: iadd
    //   2652: iconst_1
    //   2653: isub
    //   2654: istore_3
    //   2655: iload_3
    //   2656: iconst_m1
    //   2657: ior
    //   2658: iconst_1
    //   2659: ishl
    //   2660: iload_3
    //   2661: iconst_m1
    //   2662: ixor
    //   2663: isub
    //   2664: istore_3
    //   2665: iload_3
    //   2666: sipush 128
    //   2669: irem
    //   2670: putstatic 53	o/Gz:ॱॱ	I
    //   2673: iload_3
    //   2674: iconst_2
    //   2675: irem
    //   2676: ifeq +6 -> 2682
    //   2679: goto -1410 -> 1269
    //   2682: goto -1887 -> 795
    //   2685: getstatic 51	o/Gz:ʻ	I
    //   2688: istore_3
    //   2689: iload_3
    //   2690: iconst_1
    //   2691: ixor
    //   2692: iload_3
    //   2693: iconst_1
    //   2694: iand
    //   2695: iconst_1
    //   2696: ishl
    //   2697: iadd
    //   2698: istore_3
    //   2699: iload_3
    //   2700: sipush 128
    //   2703: irem
    //   2704: putstatic 53	o/Gz:ॱॱ	I
    //   2707: iload_3
    //   2708: iconst_2
    //   2709: irem
    //   2710: ifeq +6 -> 2716
    //   2713: goto -346 -> 2367
    //   2716: goto -2281 -> 435
    //   2719: bipush 124
    //   2721: iconst_0
    //   2722: bipush 18
    //   2724: invokestatic 90	o/Gz:ˋ	(ICI)Ljava/lang/String;
    //   2727: invokevirtual 96	java/lang/String:intern	()Ljava/lang/String;
    //   2730: astore 7
    //   2732: goto -1218 -> 1514
    //   2735: bipush 43
    //   2737: istore 5
    //   2739: goto -701 -> 2038
    //   2742: aload 8
    //   2744: arraylength
    //   2745: istore_3
    //   2746: aload 9
    //   2748: aload 8
    //   2750: iconst_1
    //   2751: invokestatic 740	java/util/Arrays:copyOf	([Ljava/lang/Object;I)[Ljava/lang/Object;
    //   2754: invokestatic 744	java/lang/String:format	(Ljava/lang/String;[Ljava/lang/Object;)Ljava/lang/String;
    //   2757: astore 7
    //   2759: sipush 320
    //   2762: sipush 16387
    //   2765: bipush 38
    //   2767: invokestatic 90	o/Gz:ˋ	(ICI)Ljava/lang/String;
    //   2770: invokevirtual 96	java/lang/String:intern	()Ljava/lang/String;
    //   2773: astore 8
    //   2775: goto -90 -> 2685
    //   2778: iconst_1
    //   2779: istore 5
    //   2781: goto -2139 -> 642
    //   2784: bipush 92
    //   2786: iconst_0
    //   2787: bipush 20
    //   2789: invokestatic 90	o/Gz:ˋ	(ICI)Ljava/lang/String;
    //   2792: invokevirtual 96	java/lang/String:intern	()Ljava/lang/String;
    //   2795: astore 7
    //   2797: goto -1490 -> 1307
    //   2800: goto -637 -> 2163
    //   2803: goto -2548 -> 255
    //   2806: iconst_1
    //   2807: istore_3
    //   2808: iload_3
    //   2809: tableswitch	default:+23->2832, 0:+-841->1968, 1:+-252->2557
    //   2832: goto -864 -> 1968
    // Local variable table:
    //   start	length	slot	name	signature
    //   0	2835	0	this	Gz
    //   0	2835	1	paramContext	Context
    //   0	2835	2	paramEnum	Enum
    //   0	2835	3	paramInt1	int
    //   0	2835	4	paramInt2	int
    //   44	2736	5	i	int
    //   339	2077	6	j	int
    //   3	2793	7	localObject1	Object
    //   37	2737	8	localObject2	Object
    //   882	1865	9	str	String
    // Exception table:
    //   from	to	target	type
    //   706	740	692	finally
    //   819	870	805	finally
    //   298	305	1011	java/lang/NullPointerException
    //   305	314	1011	java/lang/NullPointerException
    //   305	314	1011	java/lang/UnsupportedOperationException
    //   314	322	1011	java/lang/NullPointerException
    //   314	322	1011	java/lang/NumberFormatException
    //   322	333	1011	java/lang/NullPointerException
    //   806	811	1011	java/lang/Exception
    //   815	817	1011	java/lang/Exception
    //   817	819	1011	java/lang/Exception
    //   870	875	1011	java/lang/IndexOutOfBoundsException
    //   875	884	1011	java/lang/Exception
    //   285	298	1382	java/lang/RuntimeException
    //   322	333	1382	java/lang/ClassCastException
    //   795	802	1382	java/lang/ArrayStoreException
    //   806	811	1382	java/lang/ArrayStoreException
    //   815	817	1382	java/lang/ArrayStoreException
    //   817	819	1382	java/lang/ArrayStoreException
    //   870	875	1382	java/lang/ArrayStoreException
    //   875	884	1382	java/lang/ArrayStoreException
    //   1479	1505	1465	finally
    //   1598	1632	1584	finally
    //   2010	2035	1996	finally
    //   2185	2219	2171	finally
    //   2599	2624	2585	finally
  }
  
  public final Context ʼ()
  {
    for (;;)
    {
      switch (i)
      {
      default: 
        break;
      case 0: 
        for (;;)
        {
          i = 1;
          break;
          try
          {
            Context localContext1 = this.ॱ;
            i = null.length;
            return localContext1;
          }
          catch (ClassCastException|NumberFormatException|Exception localClassCastException)
          {
            throw localClassCastException;
          }
          i = ʻ;
          i = (i & 0x1A) + (i | 0x1A) - 1;
          ॱॱ = i % 128;
          if (i % 2 != 0) {
            break label92;
          }
        }
      }
      Context localContext2 = this.ॱ;
      return localContext2;
      label92:
      int i = 0;
    }
  }
  
  public final void ˊ(Context paramContext, String paramString, Fh paramFh)
  {
    throw new Runtime("d2j fail translate: java.lang.RuntimeException: can not merge I and Z\n\tat com.googlecode.dex2jar.ir.TypeClass.merge(TypeClass.java:100)\n\tat com.googlecode.dex2jar.ir.ts.TypeTransformer$TypeRef.updateTypeClass(TypeTransformer.java:174)\n\tat com.googlecode.dex2jar.ir.ts.TypeTransformer$TypeAnalyze.copyTypes(TypeTransformer.java:311)\n\tat com.googlecode.dex2jar.ir.ts.TypeTransformer$TypeAnalyze.fixTypes(TypeTransformer.java:226)\n\tat com.googlecode.dex2jar.ir.ts.TypeTransformer$TypeAnalyze.analyze(TypeTransformer.java:207)\n\tat com.googlecode.dex2jar.ir.ts.TypeTransformer.transform(TypeTransformer.java:44)\n\tat com.googlecode.d2j.dex.Dex2jar$2.optimize(Dex2jar.java:162)\n\tat com.googlecode.d2j.dex.Dex2Asm.convertCode(Dex2Asm.java:414)\n\tat com.googlecode.d2j.dex.ExDex2Asm.convertCode(ExDex2Asm.java:42)\n\tat com.googlecode.d2j.dex.Dex2jar$2.convertCode(Dex2jar.java:128)\n\tat com.googlecode.d2j.dex.Dex2Asm.convertMethod(Dex2Asm.java:509)\n\tat com.googlecode.d2j.dex.Dex2Asm.convertClass(Dex2Asm.java:406)\n\tat com.googlecode.d2j.dex.Dex2Asm.convertDex(Dex2Asm.java:422)\n\tat com.googlecode.d2j.dex.Dex2jar.doTranslate(Dex2jar.java:172)\n\tat com.googlecode.d2j.dex.Dex2jar.to(Dex2jar.java:272)\n\tat com.googlecode.dex2jar.tools.Dex2jarCmd.doCommandLine(Dex2jarCmd.java:108)\n\tat com.googlecode.dex2jar.tools.BaseCmd.doMain(BaseCmd.java:288)\n\tat com.googlecode.dex2jar.tools.Dex2jarCmd.main(Dex2jarCmd.java:32)\n");
  }
  
  /* Error */
  public final boolean ˊ(int paramInt)
  {
    // Byte code:
    //   0: goto +153 -> 153
    //   3: goto +719 -> 722
    //   6: bipush 21
    //   8: istore_3
    //   9: goto +456 -> 465
    //   12: goto +511 -> 523
    //   15: iconst_1
    //   16: ireturn
    //   17: aload_0
    //   18: getfield 70	o/Gz:ॱ	Landroid/content/Context;
    //   21: astore 5
    //   23: goto +23 -> 46
    //   26: astore 5
    //   28: aload 5
    //   30: invokevirtual 630	java/lang/Throwable:getCause	()Ljava/lang/Throwable;
    //   33: astore 6
    //   35: aload 6
    //   37: ifnull +6 -> 43
    //   40: aload 6
    //   42: athrow
    //   43: aload 5
    //   45: athrow
    //   46: iconst_4
    //   47: bipush 54
    //   49: ldc_w 755
    //   52: invokestatic 605	o/O:ˋ	(IIC)Ljava/lang/Object;
    //   55: checkcast 607	java/lang/Class
    //   58: ldc_w 729
    //   61: iconst_2
    //   62: anewarray 607	java/lang/Class
    //   65: dup
    //   66: iconst_0
    //   67: ldc_w 632
    //   70: aastore
    //   71: dup
    //   72: iconst_1
    //   73: getstatic 638	java/lang/Integer:TYPE	Ljava/lang/Class;
    //   76: aastore
    //   77: invokevirtual 642	java/lang/Class:getMethod	(Ljava/lang/String;[Ljava/lang/Class;)Ljava/lang/reflect/Method;
    //   80: aconst_null
    //   81: iconst_2
    //   82: anewarray 644	java/lang/Object
    //   85: dup
    //   86: iconst_0
    //   87: aload 5
    //   89: aastore
    //   90: dup
    //   91: iconst_1
    //   92: iload_1
    //   93: invokestatic 648	java/lang/Integer:valueOf	(I)Ljava/lang/Integer;
    //   96: aastore
    //   97: invokevirtual 654	java/lang/reflect/Method:invoke	(Ljava/lang/Object;[Ljava/lang/Object;)Ljava/lang/Object;
    //   100: checkcast 634	java/lang/Integer
    //   103: invokevirtual 658	java/lang/Integer:intValue	()I
    //   106: istore_2
    //   107: iload_2
    //   108: iload_1
    //   109: if_icmpeq +6 -> 115
    //   112: goto +6 -> 118
    //   115: goto +94 -> 209
    //   118: iconst_1
    //   119: istore_3
    //   120: goto +375 -> 495
    //   123: iload_3
    //   124: istore_2
    //   125: iload 4
    //   127: tableswitch	default:+21->148, 0:+29->156, 1:+399->526
    //   148: iload_3
    //   149: istore_2
    //   150: goto +376 -> 526
    //   153: goto +168 -> 321
    //   156: goto +265 -> 421
    //   159: iconst_0
    //   160: istore_2
    //   161: goto +411 -> 572
    //   164: aload_0
    //   165: aload_0
    //   166: getfield 70	o/Gz:ॱ	Landroid/content/Context;
    //   169: bipush 7
    //   171: sipush 139
    //   174: sipush 173
    //   177: invokestatic 605	o/O:ˋ	(IIC)Ljava/lang/Object;
    //   180: checkcast 607	java/lang/Class
    //   183: ldc_w 756
    //   186: invokevirtual 612	java/lang/Class:getField	(Ljava/lang/String;)Ljava/lang/reflect/Field;
    //   189: aconst_null
    //   190: invokevirtual 618	java/lang/reflect/Field:get	(Ljava/lang/Object;)Ljava/lang/Object;
    //   193: checkcast 620	java/lang/Enum
    //   196: iload_1
    //   197: iload_2
    //   198: invokespecial 624	o/Gz:ॱ$32e4e300	(Landroid/content/Context;Ljava/lang/Enum;II)V
    //   201: goto +463 -> 664
    //   204: astore 5
    //   206: aload 5
    //   208: athrow
    //   209: iconst_0
    //   210: istore_3
    //   211: goto +284 -> 495
    //   214: aload_0
    //   215: getfield 70	o/Gz:ॱ	Landroid/content/Context;
    //   218: astore 5
    //   220: goto +23 -> 243
    //   223: astore 5
    //   225: aload 5
    //   227: invokevirtual 630	java/lang/Throwable:getCause	()Ljava/lang/Throwable;
    //   230: astore 6
    //   232: aload 6
    //   234: ifnull +6 -> 240
    //   237: aload 6
    //   239: athrow
    //   240: aload 5
    //   242: athrow
    //   243: iconst_4
    //   244: bipush 54
    //   246: ldc_w 755
    //   249: invokestatic 605	o/O:ˋ	(IIC)Ljava/lang/Object;
    //   252: checkcast 607	java/lang/Class
    //   255: ldc_w 729
    //   258: iconst_2
    //   259: anewarray 607	java/lang/Class
    //   262: dup
    //   263: iconst_0
    //   264: ldc_w 632
    //   267: aastore
    //   268: dup
    //   269: iconst_1
    //   270: getstatic 638	java/lang/Integer:TYPE	Ljava/lang/Class;
    //   273: aastore
    //   274: invokevirtual 642	java/lang/Class:getMethod	(Ljava/lang/String;[Ljava/lang/Class;)Ljava/lang/reflect/Method;
    //   277: aconst_null
    //   278: iconst_2
    //   279: anewarray 644	java/lang/Object
    //   282: dup
    //   283: iconst_0
    //   284: aload 5
    //   286: aastore
    //   287: dup
    //   288: iconst_1
    //   289: iload_1
    //   290: invokestatic 648	java/lang/Integer:valueOf	(I)Ljava/lang/Integer;
    //   293: aastore
    //   294: invokevirtual 654	java/lang/reflect/Method:invoke	(Ljava/lang/Object;[Ljava/lang/Object;)Ljava/lang/Object;
    //   297: checkcast 634	java/lang/Integer
    //   300: invokevirtual 658	java/lang/Integer:intValue	()I
    //   303: istore_3
    //   304: aconst_null
    //   305: arraylength
    //   306: istore_2
    //   307: iload_3
    //   308: iload_1
    //   309: if_icmpeq +6 -> 315
    //   312: goto +103 -> 415
    //   315: goto +409 -> 724
    //   318: goto -303 -> 15
    //   321: getstatic 51	o/Gz:ʻ	I
    //   324: istore_3
    //   325: iload_3
    //   326: bipush 79
    //   328: ior
    //   329: iconst_1
    //   330: ishl
    //   331: istore_2
    //   332: iload_3
    //   333: bipush 79
    //   335: ior
    //   336: iload_3
    //   337: bipush 79
    //   339: iand
    //   340: iconst_m1
    //   341: ixor
    //   342: iand
    //   343: istore_3
    //   344: iload_3
    //   345: ineg
    //   346: iload_2
    //   347: ixor
    //   348: iload_2
    //   349: iload_3
    //   350: ineg
    //   351: iand
    //   352: iconst_1
    //   353: ishl
    //   354: iadd
    //   355: istore_2
    //   356: iload_2
    //   357: sipush 128
    //   360: irem
    //   361: putstatic 53	o/Gz:ॱॱ	I
    //   364: iload_2
    //   365: iconst_2
    //   366: irem
    //   367: ifeq +6 -> 373
    //   370: goto +283 -> 653
    //   373: goto -214 -> 159
    //   376: getstatic 51	o/Gz:ʻ	I
    //   379: istore_1
    //   380: iload_1
    //   381: bipush 77
    //   383: iand
    //   384: iload_1
    //   385: bipush 77
    //   387: ixor
    //   388: iload_1
    //   389: bipush 77
    //   391: iand
    //   392: ior
    //   393: iadd
    //   394: istore_1
    //   395: iload_1
    //   396: sipush 128
    //   399: irem
    //   400: putstatic 53	o/Gz:ॱॱ	I
    //   403: iload_1
    //   404: iconst_2
    //   405: irem
    //   406: ifeq +6 -> 412
    //   409: goto -91 -> 318
    //   412: goto -397 -> 15
    //   415: iconst_1
    //   416: istore 4
    //   418: goto -295 -> 123
    //   421: getstatic 51	o/Gz:ʻ	I
    //   424: istore_1
    //   425: iload_1
    //   426: bipush 120
    //   428: ior
    //   429: iload_1
    //   430: bipush 120
    //   432: iand
    //   433: iadd
    //   434: istore_1
    //   435: iload_1
    //   436: iconst_m1
    //   437: ixor
    //   438: iload_1
    //   439: iconst_m1
    //   440: iand
    //   441: iconst_1
    //   442: ishl
    //   443: iadd
    //   444: istore_1
    //   445: iload_1
    //   446: sipush 128
    //   449: irem
    //   450: putstatic 53	o/Gz:ॱॱ	I
    //   453: iload_1
    //   454: iconst_2
    //   455: irem
    //   456: ifeq +6 -> 462
    //   459: goto -456 -> 3
    //   462: goto +260 -> 722
    //   465: iload_3
    //   466: lookupswitch	default:+26->492, 21:+133->599, 38:+-302->164
    //   492: goto +107 -> 599
    //   495: iload_3
    //   496: tableswitch	default:+24->520, 0:+-340->156, 1:+30->526
    //   520: goto -364 -> 156
    //   523: goto -147 -> 376
    //   526: getstatic 51	o/Gz:ʻ	I
    //   529: istore_3
    //   530: iload_3
    //   531: bipush 50
    //   533: iand
    //   534: iconst_1
    //   535: ishl
    //   536: iload_3
    //   537: bipush 50
    //   539: ixor
    //   540: iadd
    //   541: istore_3
    //   542: iload_3
    //   543: iconst_m1
    //   544: ixor
    //   545: iload_3
    //   546: iconst_m1
    //   547: iand
    //   548: iconst_1
    //   549: ishl
    //   550: iadd
    //   551: istore_3
    //   552: iload_3
    //   553: sipush 128
    //   556: irem
    //   557: putstatic 53	o/Gz:ॱॱ	I
    //   560: iload_3
    //   561: iconst_2
    //   562: irem
    //   563: ifeq +6 -> 569
    //   566: goto -560 -> 6
    //   569: goto +89 -> 658
    //   572: iload_2
    //   573: tableswitch	default:+23->596, 0:+-556->17, 1:+-359->214
    //   596: goto -579 -> 17
    //   599: aload_0
    //   600: getfield 70	o/Gz:ॱ	Landroid/content/Context;
    //   603: astore 5
    //   605: aload_0
    //   606: aload 5
    //   608: bipush 7
    //   610: sipush 139
    //   613: sipush 173
    //   616: invokestatic 605	o/O:ˋ	(IIC)Ljava/lang/Object;
    //   619: checkcast 607	java/lang/Class
    //   622: ldc_w 756
    //   625: invokevirtual 612	java/lang/Class:getField	(Ljava/lang/String;)Ljava/lang/reflect/Field;
    //   628: aconst_null
    //   629: invokevirtual 618	java/lang/reflect/Field:get	(Ljava/lang/Object;)Ljava/lang/Object;
    //   632: checkcast 620	java/lang/Enum
    //   635: iload_1
    //   636: iload_2
    //   637: invokespecial 624	o/Gz:ॱ$32e4e300	(Landroid/content/Context;Ljava/lang/Enum;II)V
    //   640: bipush 98
    //   642: iconst_0
    //   643: idiv
    //   644: istore_1
    //   645: goto +19 -> 664
    //   648: astore 5
    //   650: aload 5
    //   652: athrow
    //   653: iconst_1
    //   654: istore_2
    //   655: goto -83 -> 572
    //   658: bipush 38
    //   660: istore_3
    //   661: goto -196 -> 465
    //   664: getstatic 53	o/Gz:ॱॱ	I
    //   667: istore_2
    //   668: iload_2
    //   669: bipush 57
    //   671: ixor
    //   672: iload_2
    //   673: bipush 57
    //   675: iand
    //   676: ior
    //   677: iconst_1
    //   678: ishl
    //   679: istore_1
    //   680: iload_2
    //   681: iconst_m1
    //   682: ixor
    //   683: bipush 57
    //   685: iand
    //   686: iload_2
    //   687: bipush -58
    //   689: iand
    //   690: ior
    //   691: istore_2
    //   692: iload_2
    //   693: ineg
    //   694: iload_1
    //   695: iand
    //   696: iload_1
    //   697: iload_2
    //   698: ineg
    //   699: ior
    //   700: iadd
    //   701: istore_1
    //   702: iload_1
    //   703: sipush 128
    //   706: irem
    //   707: putstatic 51	o/Gz:ʻ	I
    //   710: iload_1
    //   711: iconst_2
    //   712: irem
    //   713: ifne +6 -> 719
    //   716: goto -704 -> 12
    //   719: goto -196 -> 523
    //   722: iconst_0
    //   723: ireturn
    //   724: iconst_0
    //   725: istore 4
    //   727: goto -604 -> 123
    // Local variable table:
    //   start	length	slot	name	signature
    //   0	730	0	this	Gz
    //   0	730	1	paramInt	int
    //   106	592	2	i	int
    //   8	653	3	j	int
    //   125	601	4	k	int
    //   21	1	5	localContext1	Context
    //   26	62	5	localObject1	Object
    //   204	3	5	localRuntimeException	RuntimeException
    //   218	1	5	localContext2	Context
    //   223	62	5	localObject2	Object
    //   603	4	5	localContext3	Context
    //   648	3	5	localNumberFormatException	NumberFormatException
    //   33	205	6	localThrowable	Throwable
    // Exception table:
    //   from	to	target	type
    //   46	107	26	finally
    //   225	232	204	java/lang/RuntimeException
    //   237	240	204	java/lang/RuntimeException
    //   240	243	204	java/lang/RuntimeException
    //   304	307	204	java/lang/RuntimeException
    //   356	364	204	java/lang/ArrayStoreException
    //   376	380	204	java/lang/RuntimeException
    //   395	403	204	java/lang/ClassCastException
    //   605	645	204	java/lang/IllegalArgumentException
    //   243	304	223	finally
    //   214	220	648	java/lang/NumberFormatException
    //   225	232	648	java/lang/NumberFormatException
    //   237	240	648	java/lang/NumberFormatException
    //   240	243	648	java/lang/NumberFormatException
    //   304	307	648	java/lang/NumberFormatException
    //   321	325	648	java/lang/NumberFormatException
    //   599	605	648	java/lang/ArrayStoreException
    //   605	645	648	java/lang/ArrayStoreException
    //   664	668	648	java/lang/IndexOutOfBoundsException
    //   702	710	648	java/lang/IndexOutOfBoundsException
    //   702	710	648	java/lang/Exception
  }
  
  /* Error */
  public final void ˋ()
  {
    // Byte code:
    //   0: goto +408 -> 408
    //   3: return
    //   4: iload_1
    //   5: tableswitch	default:+23->28, 0:+604->609, 1:+634->639
    //   28: goto +581 -> 609
    //   31: getstatic 53	o/Gz:ॱॱ	I
    //   34: bipush 100
    //   36: iadd
    //   37: istore_1
    //   38: iload_1
    //   39: iconst_m1
    //   40: iand
    //   41: iload_1
    //   42: iconst_m1
    //   43: ior
    //   44: iadd
    //   45: istore_1
    //   46: iload_1
    //   47: sipush 128
    //   50: irem
    //   51: putstatic 51	o/Gz:ʻ	I
    //   54: iload_1
    //   55: iconst_2
    //   56: irem
    //   57: ifne +6 -> 63
    //   60: goto +65 -> 125
    //   63: goto +398 -> 461
    //   66: iconst_0
    //   67: istore_1
    //   68: goto -64 -> 4
    //   71: goto +432 -> 503
    //   74: getstatic 51	o/Gz:ʻ	I
    //   77: istore_2
    //   78: iload_2
    //   79: bipush 119
    //   81: iand
    //   82: iconst_m1
    //   83: ixor
    //   84: iload_2
    //   85: bipush 119
    //   87: ior
    //   88: iand
    //   89: istore_1
    //   90: iload_2
    //   91: bipush 119
    //   93: iand
    //   94: iconst_1
    //   95: ishl
    //   96: istore_2
    //   97: iload_1
    //   98: iload_2
    //   99: iand
    //   100: iload_1
    //   101: iload_2
    //   102: ior
    //   103: iadd
    //   104: istore_1
    //   105: iload_1
    //   106: sipush 128
    //   109: irem
    //   110: putstatic 53	o/Gz:ॱॱ	I
    //   113: iload_1
    //   114: iconst_2
    //   115: irem
    //   116: ifeq +6 -> 122
    //   119: goto +120 -> 239
    //   122: goto +401 -> 523
    //   125: bipush 45
    //   127: istore_1
    //   128: goto +283 -> 411
    //   131: iload_1
    //   132: tableswitch	default:+24->156, 0:+314->446, 1:+492->624
    //   156: goto +468 -> 624
    //   159: aload_0
    //   160: iload_2
    //   161: invokespecial 758	o/Gz:ʼ	(I)Lo/st;
    //   164: astore_3
    //   165: aload_0
    //   166: ldc_w 759
    //   169: ldc_w 760
    //   172: invokestatic 765	o/at:ˊ	(II)I
    //   175: invokespecial 767	o/Gz:ʽ	(I)Lo/st;
    //   178: astore_3
    //   179: new 41	java/lang/NullPointerException
    //   182: dup
    //   183: invokespecial 110	java/lang/NullPointerException:<init>	()V
    //   186: athrow
    //   187: bipush 79
    //   189: istore_1
    //   190: iload_1
    //   191: lookupswitch	default:+25->216, 79:+34->225, 86:+-188->3
    //   216: goto +9 -> 225
    //   219: bipush 86
    //   221: istore_1
    //   222: goto -32 -> 190
    //   225: new 41	java/lang/NullPointerException
    //   228: dup
    //   229: invokespecial 110	java/lang/NullPointerException:<init>	()V
    //   232: athrow
    //   233: bipush 97
    //   235: istore_1
    //   236: goto +57 -> 293
    //   239: goto +284 -> 523
    //   242: aload 4
    //   244: aload_3
    //   245: invokevirtual 770	o/st:ˎ	(Lo/sy;)Lo/st;
    //   248: invokestatic 775	o/sB:ˋ	()Lo/sy;
    //   251: invokevirtual 777	o/st:ˊ	(Lo/sy;)Lo/st;
    //   254: astore_3
    //   255: new 24	o/Gz$ˏ
    //   258: dup
    //   259: aload_0
    //   260: invokespecial 780	o/Gz$ˏ:<init>	(Lo/Gz;)V
    //   263: astore 4
    //   265: goto +202 -> 467
    //   268: getstatic 62	o/Gz:ˎ	Lo/Gz$ˊ;
    //   271: astore_3
    //   272: aload_3
    //   273: iconst_1
    //   274: invokevirtual 782	o/Gz$ˊ:ॱ	(Z)V
    //   277: ldc_w 783
    //   280: ldc_w 784
    //   283: invokestatic 765	o/at:ˊ	(II)I
    //   286: istore_2
    //   287: goto -256 -> 31
    //   290: goto -219 -> 71
    //   293: iload_1
    //   294: lookupswitch	default:+26->320, 36:+212->506, 97:+-26->268
    //   320: goto -52 -> 268
    //   323: getstatic 51	o/Gz:ʻ	I
    //   326: bipush 108
    //   328: iadd
    //   329: iconst_1
    //   330: isub
    //   331: istore_1
    //   332: iload_1
    //   333: sipush 128
    //   336: irem
    //   337: putstatic 53	o/Gz:ॱॱ	I
    //   340: iload_1
    //   341: iconst_2
    //   342: irem
    //   343: ifeq +6 -> 349
    //   346: goto +51 -> 397
    //   349: goto +6 -> 355
    //   352: goto +387 -> 739
    //   355: iconst_0
    //   356: istore_1
    //   357: goto -226 -> 131
    //   360: getstatic 51	o/Gz:ʻ	I
    //   363: bipush 104
    //   365: iadd
    //   366: istore_1
    //   367: iload_1
    //   368: iconst_m1
    //   369: ixor
    //   370: iload_1
    //   371: iconst_m1
    //   372: iand
    //   373: iconst_1
    //   374: ishl
    //   375: iadd
    //   376: istore_1
    //   377: iload_1
    //   378: sipush 128
    //   381: irem
    //   382: putstatic 53	o/Gz:ॱॱ	I
    //   385: iload_1
    //   386: iconst_2
    //   387: irem
    //   388: ifeq +6 -> 394
    //   391: goto -39 -> 352
    //   394: goto +345 -> 739
    //   397: iconst_1
    //   398: istore_1
    //   399: goto -268 -> 131
    //   402: bipush 36
    //   404: istore_1
    //   405: goto -112 -> 293
    //   408: goto -85 -> 323
    //   411: iload_1
    //   412: lookupswitch	default:+28->440, 45:+-253->159, 95:+242->654
    //   440: goto +214 -> 654
    //   443: astore_3
    //   444: aload_3
    //   445: athrow
    //   446: getstatic 62	o/Gz:ˎ	Lo/Gz$ˊ;
    //   449: invokevirtual 786	o/Gz$ˊ:ˎ	()Z
    //   452: ifne +6 -> 458
    //   455: goto -222 -> 233
    //   458: goto -56 -> 402
    //   461: bipush 95
    //   463: istore_1
    //   464: goto -53 -> 411
    //   467: getstatic 53	o/Gz:ॱॱ	I
    //   470: istore_1
    //   471: iload_1
    //   472: bipush 49
    //   474: ixor
    //   475: iload_1
    //   476: bipush 49
    //   478: iand
    //   479: iconst_1
    //   480: ishl
    //   481: iadd
    //   482: istore_1
    //   483: iload_1
    //   484: sipush 128
    //   487: irem
    //   488: putstatic 51	o/Gz:ʻ	I
    //   491: iload_1
    //   492: iconst_2
    //   493: irem
    //   494: ifne +6 -> 500
    //   497: goto -431 -> 66
    //   500: goto +178 -> 678
    //   503: goto +180 -> 683
    //   506: iconst_0
    //   507: iconst_0
    //   508: bipush 8
    //   510: invokestatic 90	o/Gz:ˋ	(ICI)Ljava/lang/String;
    //   513: invokevirtual 96	java/lang/String:intern	()Ljava/lang/String;
    //   516: astore_3
    //   517: goto -443 -> 74
    //   520: goto -17 -> 503
    //   523: bipush 8
    //   525: iconst_0
    //   526: bipush 30
    //   528: invokestatic 90	o/Gz:ˋ	(ICI)Ljava/lang/String;
    //   531: invokevirtual 96	java/lang/String:intern	()Ljava/lang/String;
    //   534: astore 4
    //   536: goto +20 -> 556
    //   539: astore_3
    //   540: aload_3
    //   541: invokevirtual 630	java/lang/Throwable:getCause	()Ljava/lang/Throwable;
    //   544: astore 4
    //   546: aload 4
    //   548: ifnull +6 -> 554
    //   551: aload 4
    //   553: athrow
    //   554: aload_3
    //   555: athrow
    //   556: iconst_4
    //   557: bipush 42
    //   559: ldc_w 699
    //   562: invokestatic 605	o/O:ˋ	(IIC)Ljava/lang/Object;
    //   565: checkcast 607	java/lang/Class
    //   568: ldc_w 608
    //   571: iconst_2
    //   572: anewarray 607	java/lang/Class
    //   575: dup
    //   576: iconst_0
    //   577: ldc 92
    //   579: aastore
    //   580: dup
    //   581: iconst_1
    //   582: ldc 92
    //   584: aastore
    //   585: invokevirtual 642	java/lang/Class:getMethod	(Ljava/lang/String;[Ljava/lang/Class;)Ljava/lang/reflect/Method;
    //   588: aconst_null
    //   589: iconst_2
    //   590: anewarray 644	java/lang/Object
    //   593: dup
    //   594: iconst_0
    //   595: aload_3
    //   596: aastore
    //   597: dup
    //   598: iconst_1
    //   599: aload 4
    //   601: aastore
    //   602: invokevirtual 654	java/lang/reflect/Method:invoke	(Ljava/lang/Object;[Ljava/lang/Object;)Ljava/lang/Object;
    //   605: pop
    //   606: goto +160 -> 766
    //   609: aload_3
    //   610: aload 4
    //   612: checkcast 788	o/sx
    //   615: invokevirtual 791	o/st:ॱ	(Lo/sx;)V
    //   618: aconst_null
    //   619: arraylength
    //   620: istore_1
    //   621: goto -101 -> 520
    //   624: getstatic 62	o/Gz:ˎ	Lo/Gz$ˊ;
    //   627: invokevirtual 786	o/Gz$ˊ:ˎ	()Z
    //   630: pop
    //   631: new 41	java/lang/NullPointerException
    //   634: dup
    //   635: invokespecial 110	java/lang/NullPointerException:<init>	()V
    //   638: athrow
    //   639: aload_3
    //   640: aload 4
    //   642: checkcast 788	o/sx
    //   645: invokevirtual 791	o/st:ॱ	(Lo/sx;)V
    //   648: goto -128 -> 520
    //   651: astore_3
    //   652: aload_3
    //   653: athrow
    //   654: aload_0
    //   655: iload_2
    //   656: invokespecial 758	o/Gz:ʼ	(I)Lo/st;
    //   659: astore_3
    //   660: aload_0
    //   661: ldc_w 759
    //   664: ldc_w 760
    //   667: invokestatic 765	o/at:ˊ	(II)I
    //   670: invokespecial 767	o/Gz:ʽ	(I)Lo/st;
    //   673: astore 4
    //   675: goto -315 -> 360
    //   678: iconst_1
    //   679: istore_1
    //   680: goto -676 -> 4
    //   683: getstatic 51	o/Gz:ʻ	I
    //   686: istore_2
    //   687: iload_2
    //   688: bipush -52
    //   690: iand
    //   691: iload_2
    //   692: iconst_m1
    //   693: ixor
    //   694: bipush 51
    //   696: iand
    //   697: ior
    //   698: istore_1
    //   699: iload_2
    //   700: bipush 51
    //   702: iand
    //   703: iconst_1
    //   704: ishl
    //   705: ineg
    //   706: istore_2
    //   707: iload_2
    //   708: ineg
    //   709: iload_1
    //   710: ior
    //   711: iconst_1
    //   712: ishl
    //   713: iload_1
    //   714: iload_2
    //   715: ineg
    //   716: ixor
    //   717: isub
    //   718: istore_1
    //   719: iload_1
    //   720: sipush 128
    //   723: irem
    //   724: putstatic 53	o/Gz:ॱॱ	I
    //   727: iload_1
    //   728: iconst_2
    //   729: irem
    //   730: ifeq +6 -> 736
    //   733: goto -546 -> 187
    //   736: goto -517 -> 219
    //   739: aload 4
    //   741: checkcast 793	o/sw
    //   744: astore 4
    //   746: aload_3
    //   747: checkcast 793	o/sw
    //   750: astore_3
    //   751: aload 4
    //   753: aload_3
    //   754: invokestatic 796	o/st:ˏ	(Lo/sw;Lo/sw;)Lo/st;
    //   757: astore 4
    //   759: invokestatic 800	o/ur:ॱ	()Lo/sy;
    //   762: astore_3
    //   763: goto -521 -> 242
    //   766: getstatic 51	o/Gz:ʻ	I
    //   769: istore_1
    //   770: iload_1
    //   771: bipush 113
    //   773: ixor
    //   774: iload_1
    //   775: bipush 113
    //   777: iand
    //   778: ior
    //   779: iconst_1
    //   780: ishl
    //   781: iload_1
    //   782: bipush -114
    //   784: iand
    //   785: iload_1
    //   786: iconst_m1
    //   787: ixor
    //   788: bipush 113
    //   790: iand
    //   791: ior
    //   792: ineg
    //   793: iconst_m1
    //   794: ixor
    //   795: isub
    //   796: iconst_1
    //   797: isub
    //   798: istore_1
    //   799: iload_1
    //   800: sipush 128
    //   803: irem
    //   804: putstatic 53	o/Gz:ॱॱ	I
    //   807: iload_1
    //   808: iconst_2
    //   809: irem
    //   810: ifeq +6 -> 816
    //   813: goto -523 -> 290
    //   816: goto -745 -> 71
    // Local variable table:
    //   start	length	slot	name	signature
    //   0	819	0	this	Gz
    //   4	806	1	i	int
    //   77	638	2	j	int
    //   164	109	3	localObject1	Object
    //   443	2	3	localRuntimeException	RuntimeException
    //   516	1	3	str	String
    //   539	101	3	localObject2	Object
    //   651	2	3	localUnsupportedOperationException	UnsupportedOperationException
    //   659	104	3	localObject3	Object
    //   242	516	4	localObject4	Object
    // Exception table:
    //   from	to	target	type
    //   268	272	443	java/lang/RuntimeException
    //   272	277	443	java/lang/RuntimeException
    //   277	287	443	java/lang/RuntimeException
    //   639	648	443	java/lang/IllegalStateException
    //   739	746	443	java/lang/NullPointerException
    //   746	751	443	java/lang/RuntimeException
    //   751	759	443	java/lang/Exception
    //   759	763	443	java/lang/Exception
    //   759	763	443	java/lang/UnsupportedOperationException
    //   556	606	539	finally
    //   272	277	651	java/lang/UnsupportedOperationException
    //   277	287	651	java/lang/NumberFormatException
  }
  
  /* Error */
  public final boolean ˎ()
  {
    // Byte code:
    //   0: goto +427 -> 427
    //   3: iconst_1
    //   4: istore_1
    //   5: goto +465 -> 470
    //   8: iconst_0
    //   9: istore_1
    //   10: goto +226 -> 236
    //   13: iload_1
    //   14: tableswitch	default:+22->36, 0:+544->558, 1:+555->569
    //   36: goto +533 -> 569
    //   39: goto +456 -> 495
    //   42: goto +131 -> 173
    //   45: iconst_1
    //   46: istore_1
    //   47: goto -34 -> 13
    //   50: aload_0
    //   51: ldc_w 801
    //   54: ldc_w 802
    //   57: invokestatic 765	o/at:ˊ	(II)I
    //   60: invokespecial 804	o/Gz:ˋ	(I)Z
    //   63: ifeq +6 -> 69
    //   66: goto +482 -> 548
    //   69: goto +225 -> 294
    //   72: getstatic 51	o/Gz:ʻ	I
    //   75: istore_1
    //   76: iload_1
    //   77: bipush 101
    //   79: ixor
    //   80: iload_1
    //   81: bipush 101
    //   83: iand
    //   84: iconst_1
    //   85: ishl
    //   86: iconst_m1
    //   87: ixor
    //   88: isub
    //   89: iconst_1
    //   90: isub
    //   91: istore_1
    //   92: iload_1
    //   93: sipush 128
    //   96: irem
    //   97: putstatic 53	o/Gz:ॱॱ	I
    //   100: iload_1
    //   101: iconst_2
    //   102: irem
    //   103: ifeq +6 -> 109
    //   106: goto +349 -> 455
    //   109: goto +273 -> 382
    //   112: getstatic 53	o/Gz:ॱॱ	I
    //   115: istore_2
    //   116: iload_2
    //   117: bipush 123
    //   119: ixor
    //   120: iload_2
    //   121: bipush 123
    //   123: iand
    //   124: ior
    //   125: iconst_1
    //   126: ishl
    //   127: istore_1
    //   128: iload_2
    //   129: bipush 123
    //   131: ior
    //   132: iload_2
    //   133: bipush 123
    //   135: iand
    //   136: iconst_m1
    //   137: ixor
    //   138: iand
    //   139: istore_2
    //   140: iload_2
    //   141: ineg
    //   142: iload_1
    //   143: iand
    //   144: iload_1
    //   145: iload_2
    //   146: ineg
    //   147: ior
    //   148: iadd
    //   149: istore_1
    //   150: iload_1
    //   151: sipush 128
    //   154: irem
    //   155: putstatic 51	o/Gz:ʻ	I
    //   158: iload_1
    //   159: iconst_2
    //   160: irem
    //   161: ifne +6 -> 167
    //   164: goto +99 -> 263
    //   167: goto +375 -> 542
    //   170: goto +63 -> 233
    //   173: getstatic 53	o/Gz:ॱॱ	I
    //   176: istore_1
    //   177: iload_1
    //   178: bipush 111
    //   180: ixor
    //   181: iload_1
    //   182: bipush 111
    //   184: iand
    //   185: iconst_1
    //   186: ishl
    //   187: iadd
    //   188: istore_1
    //   189: iload_1
    //   190: sipush 128
    //   193: irem
    //   194: putstatic 51	o/Gz:ʻ	I
    //   197: iload_1
    //   198: iconst_2
    //   199: irem
    //   200: ifne +6 -> 206
    //   203: goto +174 -> 377
    //   206: goto -161 -> 45
    //   209: aload_0
    //   210: ldc_w 805
    //   213: ldc_w 806
    //   216: invokestatic 765	o/at:ˊ	(II)I
    //   219: invokespecial 808	o/Gz:ˏ	(I)Z
    //   222: istore_3
    //   223: iload_3
    //   224: ifeq +6 -> 230
    //   227: goto +326 -> 553
    //   230: goto -227 -> 3
    //   233: goto -161 -> 72
    //   236: iload_1
    //   237: tableswitch	default:+23->260, 0:+-195->42, 1:+32->269
    //   260: goto +9 -> 269
    //   263: bipush 75
    //   265: istore_1
    //   266: goto +33 -> 299
    //   269: goto -96 -> 173
    //   272: aload_0
    //   273: ldc_w 801
    //   276: ldc_w 802
    //   279: invokestatic 765	o/at:ˊ	(II)I
    //   282: invokespecial 804	o/Gz:ˋ	(I)Z
    //   285: pop
    //   286: new 41	java/lang/NullPointerException
    //   289: dup
    //   290: invokespecial 110	java/lang/NullPointerException:<init>	()V
    //   293: athrow
    //   294: iconst_0
    //   295: istore_1
    //   296: goto +134 -> 430
    //   299: iload_1
    //   300: lookupswitch	default:+28->328, 51:+-250->50, 75:+-28->272
    //   328: goto -56 -> 272
    //   331: getstatic 53	o/Gz:ॱॱ	I
    //   334: istore_1
    //   335: iload_1
    //   336: bipush 36
    //   338: ior
    //   339: iconst_1
    //   340: ishl
    //   341: iload_1
    //   342: bipush 36
    //   344: ixor
    //   345: isub
    //   346: istore_1
    //   347: iload_1
    //   348: iconst_m1
    //   349: ixor
    //   350: iload_1
    //   351: iconst_m1
    //   352: iand
    //   353: iconst_1
    //   354: ishl
    //   355: iadd
    //   356: istore_1
    //   357: iload_1
    //   358: sipush 128
    //   361: irem
    //   362: putstatic 51	o/Gz:ʻ	I
    //   365: iload_1
    //   366: iconst_2
    //   367: irem
    //   368: ifne +6 -> 374
    //   371: goto -201 -> 170
    //   374: goto -141 -> 233
    //   377: iconst_0
    //   378: istore_1
    //   379: goto -366 -> 13
    //   382: iconst_0
    //   383: ireturn
    //   384: getstatic 53	o/Gz:ॱॱ	I
    //   387: istore_1
    //   388: iload_1
    //   389: bipush 73
    //   391: iand
    //   392: iconst_m1
    //   393: ixor
    //   394: iload_1
    //   395: bipush 73
    //   397: ior
    //   398: iand
    //   399: iload_1
    //   400: bipush 73
    //   402: iand
    //   403: iconst_1
    //   404: ishl
    //   405: iadd
    //   406: istore_1
    //   407: iload_1
    //   408: sipush 128
    //   411: irem
    //   412: putstatic 51	o/Gz:ʻ	I
    //   415: iload_1
    //   416: iconst_2
    //   417: irem
    //   418: ifne +6 -> 424
    //   421: goto -413 -> 8
    //   424: goto +41 -> 465
    //   427: goto -315 -> 112
    //   430: iload_1
    //   431: tableswitch	default:+21->452, 0:+-222->209, 1:+-100->331
    //   452: goto -243 -> 209
    //   455: goto -73 -> 382
    //   458: iconst_1
    //   459: ireturn
    //   460: astore 4
    //   462: aload 4
    //   464: athrow
    //   465: iconst_1
    //   466: istore_1
    //   467: goto -231 -> 236
    //   470: iload_1
    //   471: tableswitch	default:+21->492, 0:+-87->384, 1:+-432->39
    //   492: goto -108 -> 384
    //   495: getstatic 53	o/Gz:ॱॱ	I
    //   498: istore_1
    //   499: iload_1
    //   500: bipush 91
    //   502: iand
    //   503: iconst_m1
    //   504: ixor
    //   505: iload_1
    //   506: bipush 91
    //   508: ior
    //   509: iand
    //   510: iload_1
    //   511: bipush 91
    //   513: iand
    //   514: iconst_1
    //   515: ishl
    //   516: iconst_m1
    //   517: ixor
    //   518: isub
    //   519: iconst_1
    //   520: isub
    //   521: istore_1
    //   522: iload_1
    //   523: sipush 128
    //   526: irem
    //   527: putstatic 51	o/Gz:ʻ	I
    //   530: iload_1
    //   531: iconst_2
    //   532: irem
    //   533: ifne +6 -> 539
    //   536: goto -78 -> 458
    //   539: goto -81 -> 458
    //   542: bipush 51
    //   544: istore_1
    //   545: goto -246 -> 299
    //   548: iconst_1
    //   549: istore_1
    //   550: goto -120 -> 430
    //   553: iconst_0
    //   554: istore_1
    //   555: goto -85 -> 470
    //   558: iconst_3
    //   559: iconst_0
    //   560: idiv
    //   561: istore_1
    //   562: iconst_0
    //   563: ireturn
    //   564: astore 4
    //   566: aload 4
    //   568: athrow
    //   569: iconst_0
    //   570: ireturn
    // Local variable table:
    //   start	length	slot	name	signature
    //   0	571	0	this	Gz
    //   4	558	1	i	int
    //   115	31	2	j	int
    //   222	2	3	bool	boolean
    //   460	3	4	localClassCastException1	ClassCastException
    //   564	3	4	localClassCastException2	ClassCastException
    // Exception table:
    //   from	to	target	type
    //   72	76	460	java/lang/ClassCastException
    //   92	100	460	java/lang/ClassCastException
    //   173	177	460	java/lang/ArrayStoreException
    //   209	223	460	java/lang/Exception
    //   331	335	460	java/lang/Exception
    //   495	499	460	java/lang/Exception
    //   522	530	460	java/lang/ArrayStoreException
    //   189	197	564	java/lang/ClassCastException
    //   209	223	564	java/lang/NumberFormatException
    //   357	365	564	java/lang/RuntimeException
  }
  
  /* Error */
  public final boolean ॱ(int paramInt)
  {
    // Byte code:
    //   0: goto +253 -> 253
    //   3: iconst_1
    //   4: istore_1
    //   5: goto +169 -> 174
    //   8: getstatic 53	o/Gz:ॱॱ	I
    //   11: istore_2
    //   12: iload_2
    //   13: bipush 119
    //   15: iand
    //   16: istore_1
    //   17: iload_2
    //   18: bipush 119
    //   20: iand
    //   21: iload_2
    //   22: bipush 119
    //   24: ixor
    //   25: ior
    //   26: istore_2
    //   27: iload_1
    //   28: iload_2
    //   29: ixor
    //   30: iload_1
    //   31: iload_2
    //   32: iand
    //   33: iconst_1
    //   34: ishl
    //   35: iadd
    //   36: istore_1
    //   37: iload_1
    //   38: sipush 128
    //   41: irem
    //   42: putstatic 51	o/Gz:ʻ	I
    //   45: iload_1
    //   46: iconst_2
    //   47: irem
    //   48: ifne +6 -> 54
    //   51: goto +148 -> 199
    //   54: goto -51 -> 3
    //   57: astore 6
    //   59: aload 6
    //   61: athrow
    //   62: iconst_0
    //   63: istore 5
    //   65: goto -57 -> 8
    //   68: new 41	java/lang/NullPointerException
    //   71: dup
    //   72: invokespecial 110	java/lang/NullPointerException:<init>	()V
    //   75: athrow
    //   76: aload_0
    //   77: getfield 70	o/Gz:ॱ	Landroid/content/Context;
    //   80: astore 6
    //   82: goto +23 -> 105
    //   85: astore 6
    //   87: aload 6
    //   89: invokevirtual 630	java/lang/Throwable:getCause	()Ljava/lang/Throwable;
    //   92: astore 7
    //   94: aload 7
    //   96: ifnull +6 -> 102
    //   99: aload 7
    //   101: athrow
    //   102: aload 6
    //   104: athrow
    //   105: iconst_4
    //   106: bipush 76
    //   108: ldc_w 809
    //   111: invokestatic 605	o/O:ˋ	(IIC)Ljava/lang/Object;
    //   114: checkcast 607	java/lang/Class
    //   117: ldc_w 729
    //   120: iconst_2
    //   121: anewarray 607	java/lang/Class
    //   124: dup
    //   125: iconst_0
    //   126: ldc_w 632
    //   129: aastore
    //   130: dup
    //   131: iconst_1
    //   132: getstatic 638	java/lang/Integer:TYPE	Ljava/lang/Class;
    //   135: aastore
    //   136: invokevirtual 642	java/lang/Class:getMethod	(Ljava/lang/String;[Ljava/lang/Class;)Ljava/lang/reflect/Method;
    //   139: aconst_null
    //   140: iconst_2
    //   141: anewarray 644	java/lang/Object
    //   144: dup
    //   145: iconst_0
    //   146: aload 6
    //   148: aastore
    //   149: dup
    //   150: iconst_1
    //   151: iload_1
    //   152: invokestatic 648	java/lang/Integer:valueOf	(I)Ljava/lang/Integer;
    //   155: aastore
    //   156: invokevirtual 654	java/lang/reflect/Method:invoke	(Ljava/lang/Object;[Ljava/lang/Object;)Ljava/lang/Object;
    //   159: checkcast 634	java/lang/Integer
    //   162: invokevirtual 658	java/lang/Integer:intValue	()I
    //   165: istore_1
    //   166: new 41	java/lang/NullPointerException
    //   169: dup
    //   170: invokespecial 110	java/lang/NullPointerException:<init>	()V
    //   173: athrow
    //   174: iload_1
    //   175: tableswitch	default:+21->196, 0:+-107->68, 1:+205->380
    //   196: iload 5
    //   198: ireturn
    //   199: iconst_0
    //   200: istore_1
    //   201: goto -27 -> 174
    //   204: iload_2
    //   205: tableswitch	default:+23->228, 0:+51->256, 1:+-129->76
    //   228: goto +28 -> 256
    //   231: iconst_0
    //   232: istore_2
    //   233: goto -29 -> 204
    //   236: astore 6
    //   238: aload 6
    //   240: athrow
    //   241: bipush 88
    //   243: istore_3
    //   244: goto +225 -> 469
    //   247: bipush 75
    //   249: istore_3
    //   250: goto +219 -> 469
    //   253: goto +358 -> 611
    //   256: aload_0
    //   257: getfield 70	o/Gz:ॱ	Landroid/content/Context;
    //   260: astore 6
    //   262: goto +23 -> 285
    //   265: astore 7
    //   267: aload 7
    //   269: invokevirtual 630	java/lang/Throwable:getCause	()Ljava/lang/Throwable;
    //   272: astore 6
    //   274: aload 6
    //   276: ifnull +6 -> 282
    //   279: aload 6
    //   281: athrow
    //   282: aload 7
    //   284: athrow
    //   285: iconst_4
    //   286: bipush 76
    //   288: ldc_w 809
    //   291: invokestatic 605	o/O:ˋ	(IIC)Ljava/lang/Object;
    //   294: checkcast 607	java/lang/Class
    //   297: ldc_w 729
    //   300: iconst_2
    //   301: anewarray 607	java/lang/Class
    //   304: dup
    //   305: iconst_0
    //   306: ldc_w 632
    //   309: aastore
    //   310: dup
    //   311: iconst_1
    //   312: getstatic 638	java/lang/Integer:TYPE	Ljava/lang/Class;
    //   315: aastore
    //   316: invokevirtual 642	java/lang/Class:getMethod	(Ljava/lang/String;[Ljava/lang/Class;)Ljava/lang/reflect/Method;
    //   319: aconst_null
    //   320: iconst_2
    //   321: anewarray 644	java/lang/Object
    //   324: dup
    //   325: iconst_0
    //   326: aload 6
    //   328: aastore
    //   329: dup
    //   330: iconst_1
    //   331: iload_1
    //   332: invokestatic 648	java/lang/Integer:valueOf	(I)Ljava/lang/Integer;
    //   335: aastore
    //   336: invokevirtual 654	java/lang/reflect/Method:invoke	(Ljava/lang/Object;[Ljava/lang/Object;)Ljava/lang/Object;
    //   339: checkcast 634	java/lang/Integer
    //   342: invokevirtual 658	java/lang/Integer:intValue	()I
    //   345: istore_2
    //   346: iload_2
    //   347: iload_1
    //   348: if_icmpeq +6 -> 354
    //   351: goto -110 -> 241
    //   354: goto -107 -> 247
    //   357: iconst_1
    //   358: istore 5
    //   360: goto -352 -> 8
    //   363: iconst_1
    //   364: istore_2
    //   365: goto -161 -> 204
    //   368: bipush 17
    //   370: istore_1
    //   371: goto +12 -> 383
    //   374: bipush 57
    //   376: istore_1
    //   377: goto +6 -> 383
    //   380: iload 5
    //   382: ireturn
    //   383: iload_1
    //   384: lookupswitch	default:+28->412, 17:+-322->62, 57:+-27->357
    //   412: goto -350 -> 62
    //   415: goto +6 -> 421
    //   418: goto +49 -> 467
    //   421: getstatic 53	o/Gz:ॱॱ	I
    //   424: istore_2
    //   425: iload_2
    //   426: bipush 71
    //   428: iand
    //   429: istore_1
    //   430: iload_2
    //   431: bipush 71
    //   433: iand
    //   434: iload_2
    //   435: bipush 71
    //   437: ixor
    //   438: ior
    //   439: istore_2
    //   440: iload_1
    //   441: iload_2
    //   442: ixor
    //   443: iload_1
    //   444: iload_2
    //   445: iand
    //   446: iconst_1
    //   447: ishl
    //   448: iadd
    //   449: istore_1
    //   450: iload_1
    //   451: sipush 128
    //   454: irem
    //   455: putstatic 51	o/Gz:ʻ	I
    //   458: iload_1
    //   459: iconst_2
    //   460: irem
    //   461: ifne +6 -> 467
    //   464: goto -46 -> 418
    //   467: iconst_0
    //   468: ireturn
    //   469: iload_2
    //   470: istore 4
    //   472: iload_3
    //   473: lookupswitch	default:+27->500, 75:+-58->415, 88:+93->566
    //   500: iload_2
    //   501: istore 4
    //   503: goto +63 -> 566
    //   506: getstatic 51	o/Gz:ʻ	I
    //   509: istore_2
    //   510: iload_2
    //   511: bipush 31
    //   513: ixor
    //   514: iload_2
    //   515: bipush 31
    //   517: iand
    //   518: ior
    //   519: iconst_1
    //   520: ishl
    //   521: istore_1
    //   522: iload_2
    //   523: iconst_m1
    //   524: ixor
    //   525: bipush 31
    //   527: iand
    //   528: iload_2
    //   529: bipush -32
    //   531: iand
    //   532: ior
    //   533: istore_2
    //   534: iload_2
    //   535: ineg
    //   536: iload_1
    //   537: ixor
    //   538: iload_1
    //   539: iload_2
    //   540: ineg
    //   541: iand
    //   542: iconst_1
    //   543: ishl
    //   544: iadd
    //   545: istore_1
    //   546: iload_1
    //   547: sipush 128
    //   550: irem
    //   551: putstatic 53	o/Gz:ॱॱ	I
    //   554: iload_1
    //   555: iconst_2
    //   556: irem
    //   557: ifeq +6 -> 563
    //   560: goto -192 -> 368
    //   563: goto -189 -> 374
    //   566: aload_0
    //   567: getfield 70	o/Gz:ॱ	Landroid/content/Context;
    //   570: astore 6
    //   572: aload_0
    //   573: aload 6
    //   575: bipush 7
    //   577: sipush 139
    //   580: sipush 173
    //   583: invokestatic 605	o/O:ˋ	(IIC)Ljava/lang/Object;
    //   586: checkcast 607	java/lang/Class
    //   589: ldc_w 756
    //   592: invokevirtual 612	java/lang/Class:getField	(Ljava/lang/String;)Ljava/lang/reflect/Field;
    //   595: aconst_null
    //   596: invokevirtual 618	java/lang/reflect/Field:get	(Ljava/lang/Object;)Ljava/lang/Object;
    //   599: checkcast 620	java/lang/Enum
    //   602: iload_1
    //   603: iload 4
    //   605: invokespecial 624	o/Gz:ॱ$32e4e300	(Landroid/content/Context;Ljava/lang/Enum;II)V
    //   608: goto -102 -> 506
    //   611: getstatic 51	o/Gz:ʻ	I
    //   614: istore_2
    //   615: iload_2
    //   616: bipush 118
    //   618: ior
    //   619: iload_2
    //   620: bipush 118
    //   622: iand
    //   623: iadd
    //   624: istore_2
    //   625: iload_2
    //   626: iconst_m1
    //   627: iand
    //   628: iload_2
    //   629: iconst_m1
    //   630: ior
    //   631: iadd
    //   632: istore_2
    //   633: iload_2
    //   634: sipush 128
    //   637: irem
    //   638: putstatic 53	o/Gz:ॱॱ	I
    //   641: iload_2
    //   642: iconst_2
    //   643: irem
    //   644: ifeq +6 -> 650
    //   647: goto -284 -> 363
    //   650: goto -419 -> 231
    // Local variable table:
    //   start	length	slot	name	signature
    //   0	653	0	this	Gz
    //   0	653	1	paramInt	int
    //   11	633	2	i	int
    //   243	230	3	j	int
    //   470	134	4	k	int
    //   63	318	5	bool	boolean
    //   57	3	6	localException	Exception
    //   80	1	6	localContext	Context
    //   85	62	6	localObject1	Object
    //   236	3	6	localNumberFormatException	NumberFormatException
    //   260	314	6	localObject2	Object
    //   92	8	7	localThrowable	Throwable
    //   265	18	7	localObject3	Object
    // Exception table:
    //   from	to	target	type
    //   8	12	57	java/lang/Exception
    //   37	45	57	java/lang/Exception
    //   37	45	57	java/lang/RuntimeException
    //   76	82	57	java/lang/IllegalStateException
    //   421	425	57	java/lang/ArrayStoreException
    //   566	572	57	java/lang/NullPointerException
    //   633	641	57	java/lang/Exception
    //   105	166	85	finally
    //   87	94	236	java/lang/NumberFormatException
    //   99	102	236	java/lang/NumberFormatException
    //   102	105	236	java/lang/NumberFormatException
    //   166	174	236	java/lang/NumberFormatException
    //   450	458	236	java/lang/Exception
    //   572	608	236	java/lang/ArrayStoreException
    //   611	615	236	java/lang/IndexOutOfBoundsException
    //   285	346	265	finally
  }
  
  public static final class IF
    extends Ik<Void>
  {
    private static int ʼ = 0;
    private static int ˋ = -1020211560;
    private static int ˎ;
    private static byte[] ˏ;
    private static int ॱ;
    private static int ॱॱ = 1;
    private static short[] ᐝ;
    
    static
    {
      ॱ = 73;
      ˏ = new byte[] { 21, -19, -28, 6, 54, 103, 105, -103, -110, 101, -103, -112, -102, 109, -110, -38, 63, -107, -104, 111, -105, 107, -104, -106, -102, -104, 118, -102, -53, 53, -118, 114, -49, 35, -102, 98, 107, -119, -71, 0, 0 };
      ˎ = 559430562;
    }
    
    /* Error */
    IF(Context paramContext1, Context paramContext2)
    {
      // Byte code:
      //   0: goto +6 -> 6
      //   3: astore_1
      //   4: aload_1
      //   5: athrow
      //   6: aload_0
      //   7: aload_1
      //   8: putfield 76	o/Gz$IF:ˊ	Landroid/content/Context;
      //   11: aload_0
      //   12: aload_2
      //   13: invokespecial 79	o/Ik:<init>	(Landroid/content/Context;)V
      //   16: return
      // Local variable table:
      //   start	length	slot	name	signature
      //   0	17	0	this	IF
      //   0	17	1	paramContext1	Context
      //   0	17	2	paramContext2	Context
      // Exception table:
      //   from	to	target	type
      //   6	16	3	java/lang/IllegalStateException
    }
    
    private static String ˏ(short paramShort, int paramInt1, byte paramByte, int paramInt2, int paramInt3)
    {
      break label382;
      break label136;
      Object localObject = ˏ;
      int j = paramInt1 - 1;
      int k;
      int i = (char)(((byte)(localObject[paramInt1] + paramShort) ^ paramByte) + k);
      break label193;
      j = 63;
      break label332;
      switch (paramInt3)
      {
      default: 
        label41:
        break label265;
        label67:
        if (ˏ == null) {
          break label187;
        }
        label79:
        break;
      }
      for (;;)
      {
        paramInt1 = paramInt1 + paramInt3 - 2 + k + j;
        i = (char)(ˎ + paramInt2);
        localStringBuilder.append(i);
        paramInt2 = 1;
        k = i;
        break label441;
        try
        {
          label120:
          k = ˋ;
          if (j != 0) {
            break label545;
          }
        }
        catch (Exception localException1)
        {
          label136:
          label150:
          label180:
          label187:
          label193:
          label220:
          throw localException1;
        }
        if (j == 0)
        {
          break label242;
          do
          {
            break;
            k = ʼ + 77;
            ॱॱ = k % 128;
          } while (k % 2 == 0);
          break;
          j = 17;
          break label332;
          paramInt3 = 1;
          break label41;
          paramInt1 = ॱॱ + 7;
          ʼ = paramInt1 % 128;
          if (paramInt1 % 2 == 0)
          {
            break label539;
            localObject = ˏ;
            paramInt3 = 73 / 0;
            if (localObject == null) {
              break label520;
            }
          }
        }
        for (;;)
        {
          label242:
          if (paramInt3 > 0) {
            break label537;
          }
          break label435;
          label253:
          if (ˏ != null) {
            break;
          }
          try
          {
            label265:
            localObject = ˏ;
            paramInt3 = localObject[(ˋ + paramInt1)];
            k = ॱ;
            paramInt3 = (byte)(paramInt3 + k);
          }
          catch (Exception localException2)
          {
            label299:
            label332:
            label382:
            label393:
            label435:
            label441:
            label520:
            label537:
            label539:
            label545:
            throw localException2;
          }
        }
        break label539;
        StringBuilder localStringBuilder = new StringBuilder();
        j = ॱ + paramInt3;
        paramInt3 = j;
        if (j != -1)
        {
          break label393;
          switch (j)
          {
          default: 
            break;
          }
        }
        for (;;)
        {
          localStringBuilder.append(i);
          paramInt2 += 1;
          k = i;
          break label441;
          break label299;
          do
          {
            break label253;
            j = 0;
            break label79;
            paramInt3 = 0;
            break label41;
            paramInt3 = ॱॱ + 99;
            ʼ = paramInt3 % 128;
            if (paramInt3 % 2 != 0) {
              break label220;
            }
            break label67;
            return localException1.toString();
            if (paramInt2 < paramInt3) {
              break label180;
            }
            break;
            j = ॱॱ + 101;
            ʼ = j % 128;
          } while (j % 2 != 0);
          break label253;
          localObject = ᐝ;
          j = paramInt1 - 1;
          i = (char)(((short)(localObject[paramInt1] + paramShort) ^ paramByte) + k);
          paramInt1 = j;
          continue;
          j = 1;
          break label150;
          paramInt3 = (short)(ᐝ[(ˋ + paramInt1)] + ॱ);
          break label242;
          break label120;
          paramInt1 = j;
        }
        j = 1;
        continue;
        j = 0;
      }
    }
    
    /* Error */
    protected void ˎ(Void paramVoid)
    {
      // Byte code:
      //   0: goto +227 -> 227
      //   3: getstatic 27	o/Gz$IF:ॱॱ	I
      //   6: istore 5
      //   8: iload 5
      //   10: bipush 93
      //   12: ixor
      //   13: iload 5
      //   15: bipush 93
      //   17: iand
      //   18: ior
      //   19: iconst_1
      //   20: ishl
      //   21: istore 4
      //   23: iload 5
      //   25: bipush 93
      //   27: ior
      //   28: iload 5
      //   30: bipush 93
      //   32: iand
      //   33: iconst_m1
      //   34: ixor
      //   35: iand
      //   36: istore 5
      //   38: iload 5
      //   40: ineg
      //   41: iload 4
      //   43: iand
      //   44: iload 4
      //   46: iload 5
      //   48: ineg
      //   49: ior
      //   50: iadd
      //   51: istore 4
      //   53: iload 4
      //   55: sipush 128
      //   58: irem
      //   59: putstatic 25	o/Gz$IF:ʼ	I
      //   62: iload 4
      //   64: iconst_2
      //   65: irem
      //   66: ifeq +6 -> 72
      //   69: goto +112 -> 181
      //   72: goto +217 -> 289
      //   75: getstatic 27	o/Gz$IF:ॱॱ	I
      //   78: istore 4
      //   80: iload 4
      //   82: bipush 27
      //   84: ixor
      //   85: iload 4
      //   87: bipush 27
      //   89: iand
      //   90: ior
      //   91: iconst_1
      //   92: ishl
      //   93: istore_3
      //   94: iload 4
      //   96: bipush -28
      //   98: iand
      //   99: iload 4
      //   101: iconst_m1
      //   102: ixor
      //   103: bipush 27
      //   105: iand
      //   106: ior
      //   107: ineg
      //   108: istore 4
      //   110: iload_3
      //   111: iload 4
      //   113: iand
      //   114: iload_3
      //   115: iload 4
      //   117: ior
      //   118: iadd
      //   119: istore_3
      //   120: iload_3
      //   121: sipush 128
      //   124: irem
      //   125: putstatic 25	o/Gz$IF:ʼ	I
      //   128: iload_3
      //   129: iconst_2
      //   130: irem
      //   131: ifeq +6 -> 137
      //   134: goto +41 -> 175
      //   137: goto +242 -> 379
      //   140: iconst_1
      //   141: istore_3
      //   142: goto +59 -> 201
      //   145: iload_3
      //   146: lookupswitch	default:+26->172, 9:+272->418, 94:+127->273
      //   172: goto +246 -> 418
      //   175: bipush 94
      //   177: istore_3
      //   178: goto -33 -> 145
      //   181: goto +108 -> 289
      //   184: astore_1
      //   185: aload_1
      //   186: athrow
      //   187: aload_1
      //   188: invokevirtual 114	java/lang/String:intern	()Ljava/lang/String;
      //   191: astore_1
      //   192: bipush 65
      //   194: istore_2
      //   195: bipush 37
      //   197: istore_3
      //   198: goto -195 -> 3
      //   201: iload_3
      //   202: tableswitch	default:+22->224, 0:+-15->187, 1:+232->434
      //   224: goto +210 -> 434
      //   227: goto -152 -> 75
      //   230: getstatic 27	o/Gz$IF:ॱॱ	I
      //   233: istore_3
      //   234: iload_3
      //   235: bipush 53
      //   237: iand
      //   238: iload_3
      //   239: bipush 53
      //   241: iand
      //   242: iload_3
      //   243: bipush 53
      //   245: ixor
      //   246: ior
      //   247: iconst_m1
      //   248: ixor
      //   249: isub
      //   250: iconst_1
      //   251: isub
      //   252: istore_3
      //   253: iload_3
      //   254: sipush 128
      //   257: irem
      //   258: putstatic 25	o/Gz$IF:ʼ	I
      //   261: iload_3
      //   262: iconst_2
      //   263: irem
      //   264: ifeq +6 -> 270
      //   267: goto +118 -> 385
      //   270: goto -130 -> 140
      //   273: iconst_1
      //   274: ldc 115
      //   276: bipush 101
      //   278: ldc 116
      //   280: bipush 15
      //   282: invokestatic 118	o/Gz$IF:ˏ	(SIBII)Ljava/lang/String;
      //   285: astore_1
      //   286: goto -56 -> 230
      //   289: iconst_0
      //   290: ldc 119
      //   292: iload_2
      //   293: ldc 116
      //   295: iload_3
      //   296: invokestatic 118	o/Gz$IF:ˏ	(SIBII)Ljava/lang/String;
      //   299: astore 6
      //   301: aload 6
      //   303: invokevirtual 114	java/lang/String:intern	()Ljava/lang/String;
      //   306: astore 6
      //   308: goto +20 -> 328
      //   311: astore_1
      //   312: aload_1
      //   313: invokevirtual 125	java/lang/Throwable:getCause	()Ljava/lang/Throwable;
      //   316: astore 6
      //   318: aload 6
      //   320: ifnull +6 -> 326
      //   323: aload 6
      //   325: athrow
      //   326: aload_1
      //   327: athrow
      //   328: iconst_4
      //   329: bipush 42
      //   331: ldc 126
      //   333: invokestatic 131	o/O:ˋ	(IIC)Ljava/lang/Object;
      //   336: checkcast 133	java/lang/Class
      //   339: ldc -122
      //   341: iconst_2
      //   342: anewarray 133	java/lang/Class
      //   345: dup
      //   346: iconst_0
      //   347: ldc 111
      //   349: aastore
      //   350: dup
      //   351: iconst_1
      //   352: ldc 111
      //   354: aastore
      //   355: invokevirtual 138	java/lang/Class:getMethod	(Ljava/lang/String;[Ljava/lang/Class;)Ljava/lang/reflect/Method;
      //   358: aconst_null
      //   359: iconst_2
      //   360: anewarray 140	java/lang/Object
      //   363: dup
      //   364: iconst_0
      //   365: aload_1
      //   366: aastore
      //   367: dup
      //   368: iconst_1
      //   369: aload 6
      //   371: aastore
      //   372: invokevirtual 146	java/lang/reflect/Method:invoke	(Ljava/lang/Object;[Ljava/lang/Object;)Ljava/lang/Object;
      //   375: pop
      //   376: goto +14 -> 390
      //   379: bipush 9
      //   381: istore_3
      //   382: goto -237 -> 145
      //   385: iconst_0
      //   386: istore_3
      //   387: goto -186 -> 201
      //   390: getstatic 25	o/Gz$IF:ʼ	I
      //   393: bipush 58
      //   395: iadd
      //   396: iconst_1
      //   397: isub
      //   398: istore_3
      //   399: iload_3
      //   400: sipush 128
      //   403: irem
      //   404: putstatic 27	o/Gz$IF:ॱॱ	I
      //   407: iload_3
      //   408: iconst_2
      //   409: irem
      //   410: ifne +4 -> 414
      //   413: return
      //   414: return
      //   415: astore_1
      //   416: aload_1
      //   417: athrow
      //   418: iconst_0
      //   419: ldc 115
      //   421: bipush 23
      //   423: ldc 116
      //   425: bipush -67
      //   427: invokestatic 118	o/Gz$IF:ˏ	(SIBII)Ljava/lang/String;
      //   430: astore_1
      //   431: goto -201 -> 230
      //   434: aload_1
      //   435: invokevirtual 114	java/lang/String:intern	()Ljava/lang/String;
      //   438: astore_1
      //   439: bipush -104
      //   441: istore_2
      //   442: bipush -38
      //   444: istore_3
      //   445: goto -442 -> 3
      // Local variable table:
      //   start	length	slot	name	signature
      //   0	448	0	this	IF
      //   0	448	1	paramVoid	Void
      //   194	248	2	b	byte
      //   93	352	3	i	int
      //   21	97	4	j	int
      //   6	41	5	k	int
      //   299	71	6	localObject	Object
      // Exception table:
      //   from	to	target	type
      //   3	8	184	java/lang/IndexOutOfBoundsException
      //   53	62	184	java/lang/IllegalArgumentException
      //   187	192	184	java/lang/NullPointerException
      //   312	318	184	java/lang/UnsupportedOperationException
      //   323	326	184	java/lang/UnsupportedOperationException
      //   326	328	184	java/lang/UnsupportedOperationException
      //   328	376	311	finally
      //   230	234	415	java/lang/NullPointerException
      //   253	261	415	java/lang/IndexOutOfBoundsException
      //   289	301	415	java/lang/ClassCastException
      //   301	308	415	java/lang/ClassCastException
      //   301	308	415	java/lang/RuntimeException
      //   312	318	415	java/lang/ClassCastException
      //   312	318	415	java/lang/RuntimeException
      //   323	326	415	java/lang/ClassCastException
      //   323	326	415	java/lang/RuntimeException
      //   326	328	415	java/lang/ClassCastException
      //   326	328	415	java/lang/RuntimeException
    }
  }
  
  static final class aux<V>
    implements Callable<sw<? extends T>>
  {
    private static int ˋ = 1;
    private static int ॱ = 0;
    
    aux(Gz paramGz, int paramInt) {}
    
    /* Error */
    public final st<Object> ॱ()
    {
      // Byte code:
      //   0: goto +153 -> 153
      //   3: bipush 49
      //   5: istore_1
      //   6: goto +592 -> 598
      //   9: goto +200 -> 209
      //   12: getstatic 59	o/Gz$ˋ:ˎ	Lo/Gz$ˋ;
      //   15: astore_3
      //   16: bipush 7
      //   18: sipush 139
      //   21: sipush 173
      //   24: invokestatic 64	o/O:ˋ	(IIC)Ljava/lang/Object;
      //   27: checkcast 66	java/lang/Class
      //   30: ldc 67
      //   32: invokevirtual 71	java/lang/Class:getField	(Ljava/lang/String;)Ljava/lang/reflect/Field;
      //   35: aconst_null
      //   36: invokevirtual 77	java/lang/reflect/Field:get	(Ljava/lang/Object;)Ljava/lang/Object;
      //   39: astore 4
      //   41: aload_0
      //   42: getfield 35	o/Gz$aux:ˏ	I
      //   45: istore_2
      //   46: goto +20 -> 66
      //   49: astore_3
      //   50: aload_3
      //   51: invokevirtual 83	java/lang/Throwable:getCause	()Ljava/lang/Throwable;
      //   54: astore 4
      //   56: aload 4
      //   58: ifnull +6 -> 64
      //   61: aload 4
      //   63: athrow
      //   64: aload_3
      //   65: athrow
      //   66: bipush 7
      //   68: sipush 153
      //   71: iconst_0
      //   72: invokestatic 64	o/O:ˋ	(IIC)Ljava/lang/Object;
      //   75: checkcast 66	java/lang/Class
      //   78: iconst_4
      //   79: anewarray 66	java/lang/Class
      //   82: dup
      //   83: iconst_0
      //   84: ldc 55
      //   86: aastore
      //   87: dup
      //   88: iconst_1
      //   89: bipush 7
      //   91: sipush 139
      //   94: sipush 173
      //   97: invokestatic 64	o/O:ˋ	(IIC)Ljava/lang/Object;
      //   100: checkcast 66	java/lang/Class
      //   103: aastore
      //   104: dup
      //   105: iconst_2
      //   106: getstatic 89	java/lang/Integer:TYPE	Ljava/lang/Class;
      //   109: aastore
      //   110: dup
      //   111: iconst_3
      //   112: getstatic 89	java/lang/Integer:TYPE	Ljava/lang/Class;
      //   115: aastore
      //   116: invokevirtual 93	java/lang/Class:getDeclaredConstructor	([Ljava/lang/Class;)Ljava/lang/reflect/Constructor;
      //   119: iconst_4
      //   120: anewarray 5	java/lang/Object
      //   123: dup
      //   124: iconst_0
      //   125: aload_3
      //   126: aastore
      //   127: dup
      //   128: iconst_1
      //   129: aload 4
      //   131: aastore
      //   132: dup
      //   133: iconst_2
      //   134: iload_2
      //   135: invokestatic 97	java/lang/Integer:valueOf	(I)Ljava/lang/Integer;
      //   138: aastore
      //   139: dup
      //   140: iconst_3
      //   141: iload_1
      //   142: invokestatic 97	java/lang/Integer:valueOf	(I)Ljava/lang/Integer;
      //   145: aastore
      //   146: invokevirtual 103	java/lang/reflect/Constructor:newInstance	([Ljava/lang/Object;)Ljava/lang/Object;
      //   149: astore_3
      //   150: goto +477 -> 627
      //   153: getstatic 24	o/Gz$aux:ˋ	I
      //   156: istore_2
      //   157: iload_2
      //   158: bipush 37
      //   160: ixor
      //   161: iload_2
      //   162: bipush 37
      //   164: iand
      //   165: ior
      //   166: iconst_1
      //   167: ishl
      //   168: istore_1
      //   169: iload_2
      //   170: bipush 37
      //   172: ixor
      //   173: istore_2
      //   174: iload_2
      //   175: ineg
      //   176: iload_1
      //   177: ior
      //   178: iconst_1
      //   179: ishl
      //   180: iload_1
      //   181: iload_2
      //   182: ineg
      //   183: ixor
      //   184: isub
      //   185: istore_1
      //   186: iload_1
      //   187: sipush 128
      //   190: irem
      //   191: putstatic 22	o/Gz$aux:ॱ	I
      //   194: iload_1
      //   195: iconst_2
      //   196: irem
      //   197: ifeq +6 -> 203
      //   200: goto +26 -> 226
      //   203: goto +493 -> 696
      //   206: astore_3
      //   207: aload_3
      //   208: athrow
      //   209: aload_3
      //   210: invokestatic 108	o/st:ˏ	(Ljava/lang/Object;)Lo/st;
      //   213: astore_3
      //   214: goto +290 -> 504
      //   217: bipush 75
      //   219: istore_1
      //   220: goto +315 -> 535
      //   223: goto -14 -> 209
      //   226: iconst_1
      //   227: istore_1
      //   228: goto +339 -> 567
      //   231: getstatic 59	o/Gz$ˋ:ˎ	Lo/Gz$ˋ;
      //   234: astore_3
      //   235: bipush 7
      //   237: sipush 139
      //   240: sipush 173
      //   243: invokestatic 64	o/O:ˋ	(IIC)Ljava/lang/Object;
      //   246: checkcast 66	java/lang/Class
      //   249: ldc 109
      //   251: invokevirtual 71	java/lang/Class:getField	(Ljava/lang/String;)Ljava/lang/reflect/Field;
      //   254: aconst_null
      //   255: invokevirtual 77	java/lang/reflect/Field:get	(Ljava/lang/Object;)Ljava/lang/Object;
      //   258: astore 4
      //   260: aload_0
      //   261: getfield 35	o/Gz$aux:ˏ	I
      //   264: istore_2
      //   265: goto +20 -> 285
      //   268: astore_3
      //   269: aload_3
      //   270: invokevirtual 83	java/lang/Throwable:getCause	()Ljava/lang/Throwable;
      //   273: astore 4
      //   275: aload 4
      //   277: ifnull +6 -> 283
      //   280: aload 4
      //   282: athrow
      //   283: aload_3
      //   284: athrow
      //   285: bipush 7
      //   287: sipush 153
      //   290: iconst_0
      //   291: invokestatic 64	o/O:ˋ	(IIC)Ljava/lang/Object;
      //   294: checkcast 66	java/lang/Class
      //   297: iconst_4
      //   298: anewarray 66	java/lang/Class
      //   301: dup
      //   302: iconst_0
      //   303: ldc 55
      //   305: aastore
      //   306: dup
      //   307: iconst_1
      //   308: bipush 7
      //   310: sipush 139
      //   313: sipush 173
      //   316: invokestatic 64	o/O:ˋ	(IIC)Ljava/lang/Object;
      //   319: checkcast 66	java/lang/Class
      //   322: aastore
      //   323: dup
      //   324: iconst_2
      //   325: getstatic 89	java/lang/Integer:TYPE	Ljava/lang/Class;
      //   328: aastore
      //   329: dup
      //   330: iconst_3
      //   331: getstatic 89	java/lang/Integer:TYPE	Ljava/lang/Class;
      //   334: aastore
      //   335: invokevirtual 93	java/lang/Class:getDeclaredConstructor	([Ljava/lang/Class;)Ljava/lang/reflect/Constructor;
      //   338: iconst_4
      //   339: anewarray 5	java/lang/Object
      //   342: dup
      //   343: iconst_0
      //   344: aload_3
      //   345: aastore
      //   346: dup
      //   347: iconst_1
      //   348: aload 4
      //   350: aastore
      //   351: dup
      //   352: iconst_2
      //   353: iload_2
      //   354: invokestatic 97	java/lang/Integer:valueOf	(I)Ljava/lang/Integer;
      //   357: aastore
      //   358: dup
      //   359: iconst_3
      //   360: iload_1
      //   361: invokestatic 97	java/lang/Integer:valueOf	(I)Ljava/lang/Integer;
      //   364: aastore
      //   365: invokevirtual 103	java/lang/reflect/Constructor:newInstance	([Ljava/lang/Object;)Ljava/lang/Object;
      //   368: astore_3
      //   369: getstatic 22	o/Gz$aux:ॱ	I
      //   372: istore_1
      //   373: iload_1
      //   374: bipush 84
      //   376: ior
      //   377: iload_1
      //   378: bipush 84
      //   380: iand
      //   381: iadd
      //   382: istore_1
      //   383: iload_1
      //   384: iconst_m1
      //   385: ixor
      //   386: iload_1
      //   387: iconst_m1
      //   388: iand
      //   389: iconst_1
      //   390: ishl
      //   391: iadd
      //   392: istore_1
      //   393: iload_1
      //   394: sipush 128
      //   397: irem
      //   398: putstatic 24	o/Gz$aux:ˋ	I
      //   401: iload_1
      //   402: iconst_2
      //   403: irem
      //   404: ifne +6 -> 410
      //   407: goto +6 -> 413
      //   410: goto -193 -> 217
      //   413: bipush 82
      //   415: istore_1
      //   416: goto +119 -> 535
      //   419: astore_3
      //   420: aload_3
      //   421: athrow
      //   422: goto +20 -> 442
      //   425: astore_3
      //   426: aload_3
      //   427: invokevirtual 83	java/lang/Throwable:getCause	()Ljava/lang/Throwable;
      //   430: astore 4
      //   432: aload 4
      //   434: ifnull +6 -> 440
      //   437: aload 4
      //   439: athrow
      //   440: aload_3
      //   441: athrow
      //   442: iconst_4
      //   443: bipush 65
      //   445: ldc 110
      //   447: invokestatic 64	o/O:ˋ	(IIC)Ljava/lang/Object;
      //   450: checkcast 66	java/lang/Class
      //   453: ldc 111
      //   455: iconst_1
      //   456: anewarray 66	java/lang/Class
      //   459: dup
      //   460: iconst_0
      //   461: getstatic 89	java/lang/Integer:TYPE	Ljava/lang/Class;
      //   464: aastore
      //   465: invokevirtual 115	java/lang/Class:getMethod	(Ljava/lang/String;[Ljava/lang/Class;)Ljava/lang/reflect/Method;
      //   468: aconst_null
      //   469: iconst_1
      //   470: anewarray 5	java/lang/Object
      //   473: dup
      //   474: iconst_0
      //   475: iload_1
      //   476: invokestatic 97	java/lang/Integer:valueOf	(I)Ljava/lang/Integer;
      //   479: aastore
      //   480: invokevirtual 121	java/lang/reflect/Method:invoke	(Ljava/lang/Object;[Ljava/lang/Object;)Ljava/lang/Object;
      //   483: checkcast 85	java/lang/Integer
      //   486: invokevirtual 125	java/lang/Integer:intValue	()I
      //   489: istore_1
      //   490: iload_1
      //   491: aload_0
      //   492: getfield 35	o/Gz$aux:ˏ	I
      //   495: if_icmpeq +6 -> 501
      //   498: goto -486 -> 12
      //   501: goto -270 -> 231
      //   504: getstatic 22	o/Gz$aux:ॱ	I
      //   507: bipush 73
      //   509: iadd
      //   510: istore_1
      //   511: iload_1
      //   512: sipush 128
      //   515: irem
      //   516: putstatic 24	o/Gz$aux:ˋ	I
      //   519: iload_1
      //   520: iconst_2
      //   521: irem
      //   522: ifne +5 -> 527
      //   525: aload_3
      //   526: areturn
      //   527: aload_3
      //   528: areturn
      //   529: bipush 44
      //   531: istore_1
      //   532: goto +66 -> 598
      //   535: iload_1
      //   536: lookupswitch	default:+28->564, 75:+59->595, 82:+157->693
      //   564: goto +129 -> 693
      //   567: iload_1
      //   568: tableswitch	default:+24->592, 0:+112->680, 1:+133->701
      //   592: goto +88 -> 680
      //   595: goto -386 -> 209
      //   598: iload_1
      //   599: lookupswitch	default:+25->624, 44:+-590->9, 49:+-376->223
      //   624: goto -615 -> 9
      //   627: getstatic 24	o/Gz$aux:ˋ	I
      //   630: istore_1
      //   631: iload_1
      //   632: bipush 109
      //   634: ixor
      //   635: iload_1
      //   636: bipush 109
      //   638: iand
      //   639: ior
      //   640: iconst_1
      //   641: ishl
      //   642: iload_1
      //   643: bipush -110
      //   645: iand
      //   646: iload_1
      //   647: iconst_m1
      //   648: ixor
      //   649: bipush 109
      //   651: iand
      //   652: ior
      //   653: ineg
      //   654: iconst_m1
      //   655: ixor
      //   656: isub
      //   657: iconst_1
      //   658: isub
      //   659: istore_1
      //   660: iload_1
      //   661: sipush 128
      //   664: irem
      //   665: putstatic 22	o/Gz$aux:ॱ	I
      //   668: iload_1
      //   669: iconst_2
      //   670: irem
      //   671: ifeq +6 -> 677
      //   674: goto -671 -> 3
      //   677: goto -148 -> 529
      //   680: aload_0
      //   681: getfield 33	o/Gz$aux:ˊ	Lo/Gz;
      //   684: astore_3
      //   685: aload_0
      //   686: getfield 35	o/Gz$aux:ˏ	I
      //   689: istore_1
      //   690: goto -268 -> 422
      //   693: goto -484 -> 209
      //   696: iconst_0
      //   697: istore_1
      //   698: goto -131 -> 567
      //   701: aload_0
      //   702: getfield 33	o/Gz$aux:ˊ	Lo/Gz;
      //   705: astore_3
      //   706: aload_0
      //   707: getfield 35	o/Gz$aux:ˏ	I
      //   710: istore_1
      //   711: aconst_null
      //   712: arraylength
      //   713: istore_2
      //   714: goto -292 -> 422
      // Local variable table:
      //   start	length	slot	name	signature
      //   0	717	0	this	aux
      //   5	706	1	i	int
      //   45	669	2	j	int
      //   15	1	3	localˋ	Gz.ˋ
      //   49	77	3	localObject1	Object
      //   149	1	3	localObject2	Object
      //   206	4	3	localIllegalStateException	IllegalStateException
      //   213	22	3	localObject3	Object
      //   268	77	3	localObject4	Object
      //   368	1	3	localObject5	Object
      //   419	2	3	localIllegalArgumentException	IllegalArgumentException
      //   425	103	3	localSt	st<Object>
      //   684	22	3	localGz	Gz
      //   39	399	4	localObject6	Object
      // Exception table:
      //   from	to	target	type
      //   66	150	49	finally
      //   209	214	206	java/lang/IllegalStateException
      //   235	260	206	java/lang/RuntimeException
      //   504	511	206	java/lang/NullPointerException
      //   511	519	206	java/lang/NullPointerException
      //   627	631	206	java/lang/ArrayStoreException
      //   660	668	206	java/lang/NullPointerException
      //   285	369	268	finally
      //   231	235	419	java/lang/IllegalArgumentException
      //   260	265	419	java/lang/RuntimeException
      //   680	685	419	java/lang/IndexOutOfBoundsException
      //   685	690	419	java/lang/NullPointerException
      //   442	490	425	finally
    }
  }
  
  public static final class ˊ
  {
    private static int ˊ = 0;
    private static char ˎ = '\003';
    private static int ˏ = 1;
    private static char[] ॱ = { 99, 111, 110, 116, 101, 120, 100, 102, 103 };
    
    private ˊ() {}
    
    /* Error */
    private static String ॱ(char[] paramArrayOfChar, int paramInt, byte paramByte)
    {
      // Byte code:
      //   0: goto +377 -> 377
      //   3: iload_3
      //   4: iconst_1
      //   5: isub
      //   6: istore_1
      //   7: aload 11
      //   9: iload_1
      //   10: aload_0
      //   11: iload_1
      //   12: caload
      //   13: iload_2
      //   14: isub
      //   15: i2c
      //   16: castore
      //   17: goto +76 -> 93
      //   20: iload 8
      //   22: iload 5
      //   24: invokestatic 46	o/oO:ˊ	(II)I
      //   27: istore 4
      //   29: iload 9
      //   31: iload 5
      //   33: invokestatic 46	o/oO:ˊ	(II)I
      //   36: istore 8
      //   38: iload 7
      //   40: iload 4
      //   42: iload 5
      //   44: invokestatic 49	o/oO:ˏ	(III)I
      //   47: istore 4
      //   49: iload 6
      //   51: iload 8
      //   53: iload 5
      //   55: invokestatic 49	o/oO:ˏ	(III)I
      //   58: istore 6
      //   60: aload 11
      //   62: iload_3
      //   63: aload 10
      //   65: iload 4
      //   67: caload
      //   68: castore
      //   69: aload 11
      //   71: iload_3
      //   72: iconst_1
      //   73: iadd
      //   74: aload 10
      //   76: iload 6
      //   78: caload
      //   79: castore
      //   80: goto +683 -> 763
      //   83: bipush 40
      //   85: istore 4
      //   87: goto +59 -> 146
      //   90: goto +147 -> 237
      //   93: goto +85 -> 178
      //   96: astore_0
      //   97: aload_0
      //   98: athrow
      //   99: new 51	java/lang/String
      //   102: dup
      //   103: aload 11
      //   105: invokespecial 54	java/lang/String:<init>	([C)V
      //   108: areturn
      //   109: bipush 19
      //   111: istore 4
      //   113: goto +33 -> 146
      //   116: getstatic 17	o/Gz$ˊ:ˊ	I
      //   119: bipush 9
      //   121: iadd
      //   122: istore 4
      //   124: iload 4
      //   126: sipush 128
      //   129: irem
      //   130: putstatic 19	o/Gz$ˊ:ˏ	I
      //   133: iload 4
      //   135: iconst_2
      //   136: irem
      //   137: ifne +6 -> 143
      //   140: goto +655 -> 795
      //   143: goto -123 -> 20
      //   146: iload_3
      //   147: istore_1
      //   148: iload 4
      //   150: lookupswitch	default:+26->176, 19:+28->178, 40:+547->697
      //   176: iload_3
      //   177: istore_1
      //   178: iload_1
      //   179: iconst_1
      //   180: if_icmple +6 -> 186
      //   183: goto +167 -> 350
      //   186: goto -87 -> 99
      //   189: goto +581 -> 770
      //   192: iload 7
      //   194: iload 9
      //   196: iload 5
      //   198: invokestatic 49	o/oO:ˏ	(III)I
      //   201: istore 4
      //   203: iload 6
      //   205: iload 8
      //   207: iload 5
      //   209: invokestatic 49	o/oO:ˏ	(III)I
      //   212: istore 6
      //   214: aload 11
      //   216: iload_3
      //   217: aload 10
      //   219: iload 4
      //   221: caload
      //   222: castore
      //   223: aload 11
      //   225: iload_3
      //   226: iconst_1
      //   227: iadd
      //   228: aload 10
      //   230: iload 6
      //   232: caload
      //   233: castore
      //   234: goto +529 -> 763
      //   237: iload_3
      //   238: iload_1
      //   239: if_icmpge +6 -> 245
      //   242: goto +353 -> 595
      //   245: goto -146 -> 99
      //   248: bipush 16
      //   250: istore 4
      //   252: goto +406 -> 658
      //   255: iload 7
      //   257: iload 6
      //   259: if_icmpne +6 -> 265
      //   262: goto -146 -> 116
      //   265: goto -73 -> 192
      //   268: goto -31 -> 237
      //   271: iload 6
      //   273: iload 5
      //   275: invokestatic 56	o/oO:ॱ	(II)I
      //   278: istore 7
      //   280: iload 6
      //   282: iload 5
      //   284: invokestatic 59	o/oO:ˋ	(II)I
      //   287: istore 8
      //   289: iload 9
      //   291: iload 5
      //   293: invokestatic 56	o/oO:ॱ	(II)I
      //   296: istore 6
      //   298: iload 9
      //   300: iload 5
      //   302: invokestatic 59	o/oO:ˋ	(II)I
      //   305: istore 9
      //   307: iload 8
      //   309: iload 9
      //   311: if_icmpne +6 -> 317
      //   314: goto +102 -> 416
      //   317: goto +374 -> 691
      //   320: getstatic 17	o/Gz$ˊ:ˊ	I
      //   323: bipush 121
      //   325: iadd
      //   326: istore 4
      //   328: iload 4
      //   330: sipush 128
      //   333: irem
      //   334: putstatic 19	o/Gz$ˊ:ˏ	I
      //   337: iload 4
      //   339: iconst_2
      //   340: irem
      //   341: ifne +6 -> 347
      //   344: goto +141 -> 485
      //   347: goto +75 -> 422
      //   350: getstatic 17	o/Gz$ˊ:ˊ	I
      //   353: bipush 61
      //   355: iadd
      //   356: istore_3
      //   357: iload_3
      //   358: sipush 128
      //   361: irem
      //   362: putstatic 19	o/Gz$ˊ:ˏ	I
      //   365: iload_3
      //   366: iconst_2
      //   367: irem
      //   368: ifne +6 -> 374
      //   371: goto +254 -> 625
      //   374: goto +353 -> 727
      //   377: goto +10 -> 387
      //   380: bipush 83
      //   382: istore 4
      //   384: goto +348 -> 732
      //   387: getstatic 30	o/Gz$ˊ:ॱ	[C
      //   390: astore 10
      //   392: iload_1
      //   393: istore_3
      //   394: getstatic 32	o/Gz$ˊ:ˎ	C
      //   397: istore 5
      //   399: iload_3
      //   400: newarray char
      //   402: astore 11
      //   404: iload_3
      //   405: iconst_2
      //   406: irem
      //   407: ifeq +6 -> 413
      //   410: goto -327 -> 83
      //   413: goto -304 -> 109
      //   416: iconst_1
      //   417: istore 4
      //   419: goto +147 -> 566
      //   422: iload 7
      //   424: iload 5
      //   426: invokestatic 46	o/oO:ˊ	(II)I
      //   429: istore 4
      //   431: iload 6
      //   433: iload 5
      //   435: invokestatic 46	o/oO:ˊ	(II)I
      //   438: istore 6
      //   440: iload 4
      //   442: iload 8
      //   444: iload 5
      //   446: invokestatic 49	o/oO:ˏ	(III)I
      //   449: istore 4
      //   451: iload 6
      //   453: iload 9
      //   455: iload 5
      //   457: invokestatic 49	o/oO:ˏ	(III)I
      //   460: istore 6
      //   462: aload 11
      //   464: iload_3
      //   465: aload 10
      //   467: iload 4
      //   469: caload
      //   470: castore
      //   471: aload 11
      //   473: iload_3
      //   474: iconst_1
      //   475: iadd
      //   476: aload 10
      //   478: iload 6
      //   480: caload
      //   481: castore
      //   482: goto +281 -> 763
      //   485: goto -63 -> 422
      //   488: getstatic 19	o/Gz$ˊ:ˏ	I
      //   491: bipush 99
      //   493: iadd
      //   494: istore 4
      //   496: iload 4
      //   498: sipush 128
      //   501: irem
      //   502: putstatic 17	o/Gz$ˊ:ˊ	I
      //   505: iload 4
      //   507: iconst_2
      //   508: irem
      //   509: ifeq +6 -> 515
      //   512: goto -132 -> 380
      //   515: goto +113 -> 628
      //   518: iload_3
      //   519: bipush 122
      //   521: iadd
      //   522: istore_1
      //   523: aload 11
      //   525: iload_1
      //   526: aload_0
      //   527: iload_1
      //   528: caload
      //   529: iload_2
      //   530: idiv
      //   531: i2c
      //   532: castore
      //   533: goto -440 -> 93
      //   536: bipush 9
      //   538: istore 4
      //   540: goto +118 -> 658
      //   543: aload 11
      //   545: iload_3
      //   546: iload 6
      //   548: iload_2
      //   549: imul
      //   550: i2c
      //   551: castore
      //   552: aload 11
      //   554: iload_3
      //   555: iconst_1
      //   556: imul
      //   557: iload 9
      //   559: iload_2
      //   560: ishl
      //   561: i2c
      //   562: castore
      //   563: goto +200 -> 763
      //   566: iload 4
      //   568: tableswitch	default:+24->592, 0:+-313->255, 1:+-248->320
      //   592: goto -272 -> 320
      //   595: getstatic 17	o/Gz$ˊ:ˊ	I
      //   598: bipush 73
      //   600: iadd
      //   601: istore 4
      //   603: iload 4
      //   605: sipush 128
      //   608: irem
      //   609: putstatic 19	o/Gz$ˊ:ˏ	I
      //   612: iload 4
      //   614: iconst_2
      //   615: irem
      //   616: ifne +6 -> 622
      //   619: goto -430 -> 189
      //   622: goto +148 -> 770
      //   625: goto +102 -> 727
      //   628: bipush 62
      //   630: istore 4
      //   632: goto +100 -> 732
      //   635: aload 11
      //   637: iload_3
      //   638: iload 6
      //   640: iload_2
      //   641: isub
      //   642: i2c
      //   643: castore
      //   644: aload 11
      //   646: iload_3
      //   647: iconst_1
      //   648: iadd
      //   649: iload 9
      //   651: iload_2
      //   652: isub
      //   653: i2c
      //   654: castore
      //   655: goto +108 -> 763
      //   658: iload 4
      //   660: lookupswitch	default:+28->688, 9:+-389->271, 16:+-172->488
      //   688: goto -417 -> 271
      //   691: iconst_0
      //   692: istore 4
      //   694: goto -128 -> 566
      //   697: getstatic 19	o/Gz$ˊ:ˏ	I
      //   700: bipush 81
      //   702: iadd
      //   703: istore_1
      //   704: iload_1
      //   705: sipush 128
      //   708: irem
      //   709: putstatic 17	o/Gz$ˊ:ˊ	I
      //   712: iload_1
      //   713: iconst_2
      //   714: irem
      //   715: ifeq +6 -> 721
      //   718: goto -200 -> 518
      //   721: goto -718 -> 3
      //   724: astore_0
      //   725: aload_0
      //   726: athrow
      //   727: iconst_0
      //   728: istore_3
      //   729: goto -461 -> 268
      //   732: iload 4
      //   734: lookupswitch	default:+26->760, 62:+-99->635, 83:+-191->543
      //   760: goto -217 -> 543
      //   763: iload_3
      //   764: iconst_2
      //   765: iadd
      //   766: istore_3
      //   767: goto -677 -> 90
      //   770: aload_0
      //   771: iload_3
      //   772: caload
      //   773: istore 6
      //   775: aload_0
      //   776: iload_3
      //   777: iconst_1
      //   778: iadd
      //   779: caload
      //   780: istore 9
      //   782: iload 6
      //   784: iload 9
      //   786: if_icmpne +6 -> 792
      //   789: goto -541 -> 248
      //   792: goto -256 -> 536
      //   795: goto -775 -> 20
      // Local variable table:
      //   start	length	slot	name	signature
      //   0	798	0	paramArrayOfChar	char[]
      //   0	798	1	paramInt	int
      //   0	798	2	paramByte	byte
      //   3	776	3	i	int
      //   27	706	4	j	int
      //   22	434	5	k	int
      //   49	738	6	b1	byte
      //   38	385	7	m	int
      //   20	423	8	n	int
      //   29	758	9	b2	byte
      //   63	414	10	arrayOfChar1	char[]
      //   7	638	11	arrayOfChar2	char[]
      // Exception table:
      //   from	to	target	type
      //   192	203	96	java/lang/Exception
      //   203	214	96	java/lang/Exception
      //   350	357	724	java/lang/Exception
      //   357	365	724	java/lang/Exception
      //   422	462	724	java/lang/Exception
    }
    
    public final Gz ˎ(Context paramContext)
    {
      for (;;)
      {
        paramContext = new Gz(paramContext, null);
        break label65;
        for (;;)
        {
          try
          {
            i = ˏ;
            i = (i ^ 0x51) - ((i & 0x51) << 1 ^ 0xFFFFFFFF) - 1;
          }
          catch (ClassCastException|Exception|RuntimeException paramContext)
          {
            try
            {
              ˊ = i % 128;
              if (i % 2 != 0) {
                break;
              }
            }
            catch (ClassCastException|NumberFormatException|IllegalStateException|ArrayStoreException|UnsupportedOperationException paramContext)
            {
              int i;
              throw paramContext;
            }
            paramContext = paramContext;
            throw paramContext;
          }
        }
        label65:
        i = ˏ;
        i = (i & 0xFFFFFFDA | (i ^ 0xFFFFFFFF) & 0x25) - ((i & 0x25) << 1 ^ 0xFFFFFFFF) - 1;
        ˊ = i % 128;
        if (i % 2 != 0) {
          return paramContext;
        }
        return paramContext;
        String str = ॱ(new char[] { 1, 2, 0, 5, 5, 3, 146 }, 7, (byte)30);
        str = str.intern();
        vq.ˎ(paramContext, str);
      }
      return paramContext;
    }
    
    public final boolean ˎ()
    {
      boolean bool;
      int i;
      for (;;)
      {
        try
        {
          bool = Gz.ᐝ();
          i = null.length;
        }
        catch (RuntimeException|NumberFormatException|IllegalStateException localRuntimeException)
        {
          try
          {
            i = ˏ;
            i = (i & 0x36) + (i | 0x36) - 1;
            ˊ = i % 128;
            if (i % 2 == 0)
            {
              break;
              i = ˏ;
              i = (i ^ 0x55) + ((i & 0x55) << 1);
              ˊ = i % 128;
              if (i % 2 != 0) {
                return bool;
              }
              return bool;
              continue;
            }
            i = 1;
          }
          catch (NullPointerException|Exception|ClassCastException localNullPointerException)
          {
            throw localNullPointerException;
          }
          localRuntimeException = localRuntimeException;
          throw localRuntimeException;
        }
        bool = Gz.ᐝ();
      }
      for (;;)
      {
        switch (i)
        {
        }
        break;
        i = 0;
      }
      return bool;
    }
    
    public final void ॱ(boolean paramBoolean)
    {
      for (;;)
      {
        try
        {
          i = ˏ;
          i = (i & 0xFFFFFFE0 | (i ^ 0xFFFFFFFF) & 0x1F) - (--((i & 0x1F) << 1) ^ 0xFFFFFFFF) - 1;
          ˊ = i % 128;
          if (i % 2 != 0) {
            break;
          }
        }
        catch (RuntimeException|ArrayStoreException localRuntimeException)
        {
          throw localRuntimeException;
        }
      }
      int i = 0;
      break label87;
      i = 7;
      for (;;)
      {
        try
        {
          Gz.ˎ(paramBoolean);
          i = 81 / 0;
          return;
        }
        catch (NullPointerException|UnsupportedOperationException localNullPointerException)
        {
          throw localNullPointerException;
        }
        Gz.ˎ(paramBoolean);
        return;
        label87:
        switch (i)
        {
        }
      }
    }
  }
  
  public static enum ˋ
  {
    private static int ʻ;
    private static char[] ʼ;
    private static boolean ʽ;
    private static int ˋॱ;
    private static boolean ॱॱ;
    private static int ᐝ = 0;
    
    /* Error */
    static
    {
      // Byte code:
      //   0: iconst_0
      //   1: putstatic 43	o/Gz$ˋ:ᐝ	I
      //   4: iconst_1
      //   5: putstatic 45	o/Gz$ˋ:ˋॱ	I
      //   8: goto +423 -> 431
      //   11: getstatic 43	o/Gz$ˋ:ᐝ	I
      //   14: istore_0
      //   15: iload_0
      //   16: bipush 18
      //   18: iand
      //   19: iconst_1
      //   20: ishl
      //   21: iload_0
      //   22: bipush 18
      //   24: ixor
      //   25: iadd
      //   26: istore_0
      //   27: iload_0
      //   28: iconst_m1
      //   29: iand
      //   30: iload_0
      //   31: iconst_m1
      //   32: ior
      //   33: iadd
      //   34: istore_0
      //   35: iload_0
      //   36: sipush 128
      //   39: irem
      //   40: putstatic 45	o/Gz$ˋ:ˋॱ	I
      //   43: iload_0
      //   44: iconst_2
      //   45: irem
      //   46: ifne +6 -> 52
      //   49: goto +287 -> 336
      //   52: goto +251 -> 303
      //   55: aload_3
      //   56: putstatic 47	o/Gz$ˋ:ॱ	Lo/Gz$ˋ;
      //   59: new 2	o/Gz$ˋ
      //   62: dup
      //   63: bipush 10
      //   65: newarray byte
      //   67: dup
      //   68: iconst_0
      //   69: ldc 48
      //   71: bastore
      //   72: dup
      //   73: iconst_1
      //   74: ldc 49
      //   76: bastore
      //   77: dup
      //   78: iconst_2
      //   79: ldc 50
      //   81: bastore
      //   82: dup
      //   83: iconst_3
      //   84: ldc 51
      //   86: bastore
      //   87: dup
      //   88: iconst_4
      //   89: ldc 49
      //   91: bastore
      //   92: dup
      //   93: iconst_5
      //   94: ldc 52
      //   96: bastore
      //   97: dup
      //   98: bipush 6
      //   100: ldc 53
      //   102: bastore
      //   103: dup
      //   104: bipush 7
      //   106: ldc 54
      //   108: bastore
      //   109: dup
      //   110: bipush 8
      //   112: ldc 54
      //   114: bastore
      //   115: dup
      //   116: bipush 9
      //   118: ldc 55
      //   120: bastore
      //   121: aconst_null
      //   122: aconst_null
      //   123: bipush 127
      //   125: invokestatic 58	o/Gz$ˋ:ˊ	([B[I[CI)Ljava/lang/String;
      //   128: invokevirtual 64	java/lang/String:intern	()Ljava/lang/String;
      //   131: iconst_2
      //   132: invokespecial 68	o/Gz$ˋ:<init>	(Ljava/lang/String;I)V
      //   135: astore_2
      //   136: goto +54 -> 190
      //   139: getstatic 43	o/Gz$ˋ:ᐝ	I
      //   142: istore_1
      //   143: iload_1
      //   144: bipush 33
      //   146: iand
      //   147: iconst_m1
      //   148: ixor
      //   149: iload_1
      //   150: bipush 33
      //   152: ior
      //   153: iand
      //   154: istore_0
      //   155: iload_1
      //   156: bipush 33
      //   158: iand
      //   159: iconst_1
      //   160: ishl
      //   161: istore_1
      //   162: iload_0
      //   163: iload_1
      //   164: ixor
      //   165: iload_0
      //   166: iload_1
      //   167: iand
      //   168: iconst_1
      //   169: ishl
      //   170: iadd
      //   171: istore_0
      //   172: iload_0
      //   173: sipush 128
      //   176: irem
      //   177: putstatic 45	o/Gz$ˋ:ˋॱ	I
      //   180: iload_0
      //   181: iconst_2
      //   182: irem
      //   183: ifne +6 -> 189
      //   186: goto +244 -> 430
      //   189: return
      //   190: aload_2
      //   191: putstatic 70	o/Gz$ˋ:ˊ	Lo/Gz$ˋ;
      //   194: bipush 14
      //   196: newarray byte
      //   198: dup
      //   199: iconst_0
      //   200: ldc 48
      //   202: bastore
      //   203: dup
      //   204: iconst_1
      //   205: ldc 49
      //   207: bastore
      //   208: dup
      //   209: iconst_2
      //   210: ldc 50
      //   212: bastore
      //   213: dup
      //   214: iconst_3
      //   215: ldc 51
      //   217: bastore
      //   218: dup
      //   219: iconst_4
      //   220: ldc 49
      //   222: bastore
      //   223: dup
      //   224: iconst_5
      //   225: ldc 52
      //   227: bastore
      //   228: dup
      //   229: bipush 6
      //   231: ldc 55
      //   233: bastore
      //   234: dup
      //   235: bipush 7
      //   237: ldc 54
      //   239: bastore
      //   240: dup
      //   241: bipush 8
      //   243: ldc 53
      //   245: bastore
      //   246: dup
      //   247: bipush 9
      //   249: ldc 71
      //   251: bastore
      //   252: dup
      //   253: bipush 10
      //   255: ldc 72
      //   257: bastore
      //   258: dup
      //   259: bipush 11
      //   261: ldc 73
      //   263: bastore
      //   264: dup
      //   265: bipush 12
      //   267: ldc 74
      //   269: bastore
      //   270: dup
      //   271: bipush 13
      //   273: ldc 50
      //   275: bastore
      //   276: aconst_null
      //   277: aconst_null
      //   278: bipush 127
      //   280: invokestatic 58	o/Gz$ˋ:ˊ	([B[I[CI)Ljava/lang/String;
      //   283: astore 5
      //   285: new 2	o/Gz$ˋ
      //   288: dup
      //   289: aload 5
      //   291: invokevirtual 64	java/lang/String:intern	()Ljava/lang/String;
      //   294: iconst_3
      //   295: invokespecial 68	o/Gz$ˋ:<init>	(Ljava/lang/String;I)V
      //   298: astore 5
      //   300: goto -289 -> 11
      //   303: aload 5
      //   305: putstatic 76	o/Gz$ˋ:ˋ	Lo/Gz$ˋ;
      //   308: iconst_4
      //   309: anewarray 2	o/Gz$ˋ
      //   312: dup
      //   313: iconst_0
      //   314: aload 4
      //   316: aastore
      //   317: dup
      //   318: iconst_1
      //   319: aload_3
      //   320: aastore
      //   321: dup
      //   322: iconst_2
      //   323: aload_2
      //   324: aastore
      //   325: dup
      //   326: iconst_3
      //   327: aload 5
      //   329: aastore
      //   330: putstatic 78	o/Gz$ˋ:ˏ	[Lo/Gz$ˋ;
      //   333: goto -194 -> 139
      //   336: goto -33 -> 303
      //   339: aload 4
      //   341: putstatic 80	o/Gz$ˋ:ˎ	Lo/Gz$ˋ;
      //   344: new 2	o/Gz$ˋ
      //   347: dup
      //   348: bipush 11
      //   350: newarray byte
      //   352: dup
      //   353: iconst_0
      //   354: ldc 48
      //   356: bastore
      //   357: dup
      //   358: iconst_1
      //   359: ldc 49
      //   361: bastore
      //   362: dup
      //   363: iconst_2
      //   364: ldc 50
      //   366: bastore
      //   367: dup
      //   368: iconst_3
      //   369: ldc 51
      //   371: bastore
      //   372: dup
      //   373: iconst_4
      //   374: ldc 49
      //   376: bastore
      //   377: dup
      //   378: iconst_5
      //   379: ldc 52
      //   381: bastore
      //   382: dup
      //   383: bipush 6
      //   385: ldc 81
      //   387: bastore
      //   388: dup
      //   389: bipush 7
      //   391: ldc 73
      //   393: bastore
      //   394: dup
      //   395: bipush 8
      //   397: ldc 82
      //   399: bastore
      //   400: dup
      //   401: bipush 9
      //   403: ldc 50
      //   405: bastore
      //   406: dup
      //   407: bipush 10
      //   409: ldc 83
      //   411: bastore
      //   412: aconst_null
      //   413: aconst_null
      //   414: bipush 127
      //   416: invokestatic 58	o/Gz$ˋ:ˊ	([B[I[CI)Ljava/lang/String;
      //   419: invokevirtual 64	java/lang/String:intern	()Ljava/lang/String;
      //   422: iconst_1
      //   423: invokespecial 68	o/Gz$ˋ:<init>	(Ljava/lang/String;I)V
      //   426: astore_3
      //   427: goto -372 -> 55
      //   430: return
      //   431: invokestatic 85	o/Gz$ˋ:ˊ	()V
      //   434: bipush 10
      //   436: newarray byte
      //   438: dup
      //   439: iconst_0
      //   440: ldc 48
      //   442: bastore
      //   443: dup
      //   444: iconst_1
      //   445: ldc 49
      //   447: bastore
      //   448: dup
      //   449: iconst_2
      //   450: ldc 50
      //   452: bastore
      //   453: dup
      //   454: iconst_3
      //   455: ldc 51
      //   457: bastore
      //   458: dup
      //   459: iconst_4
      //   460: ldc 49
      //   462: bastore
      //   463: dup
      //   464: iconst_5
      //   465: ldc 52
      //   467: bastore
      //   468: dup
      //   469: bipush 6
      //   471: ldc 48
      //   473: bastore
      //   474: dup
      //   475: bipush 7
      //   477: ldc 54
      //   479: bastore
      //   480: dup
      //   481: bipush 8
      //   483: ldc 54
      //   485: bastore
      //   486: dup
      //   487: bipush 9
      //   489: ldc 51
      //   491: bastore
      //   492: aconst_null
      //   493: aconst_null
      //   494: bipush 127
      //   496: invokestatic 58	o/Gz$ˋ:ˊ	([B[I[CI)Ljava/lang/String;
      //   499: astore_2
      //   500: new 2	o/Gz$ˋ
      //   503: dup
      //   504: aload_2
      //   505: invokevirtual 64	java/lang/String:intern	()Ljava/lang/String;
      //   508: iconst_0
      //   509: invokespecial 68	o/Gz$ˋ:<init>	(Ljava/lang/String;I)V
      //   512: astore 4
      //   514: goto -175 -> 339
      //   517: astore_2
      //   518: aload_2
      //   519: athrow
      //   520: astore_2
      //   521: aload_2
      //   522: athrow
      // Local variable table:
      //   start	length	slot	name	signature
      //   14	169	0	i	int
      //   142	26	1	j	int
      //   135	370	2	localObject1	Object
      //   517	2	2	localIllegalStateException	IllegalStateException
      //   520	2	2	localIllegalArgumentException	IllegalArgumentException
      //   55	372	3	localˋ1	ˋ
      //   314	199	4	localˋ2	ˋ
      //   283	45	5	localObject2	Object
      // Exception table:
      //   from	to	target	type
      //   172	180	517	java/lang/IllegalStateException
      //   190	194	517	java/lang/UnsupportedOperationException
      //   194	285	517	java/lang/IndexOutOfBoundsException
      //   194	285	517	java/lang/ClassCastException
      //   285	300	517	java/lang/IndexOutOfBoundsException
      //   434	500	517	java/lang/UnsupportedOperationException
      //   434	500	517	java/lang/IndexOutOfBoundsException
      //   500	514	517	java/lang/UnsupportedOperationException
      //   139	143	520	java/lang/IllegalArgumentException
      //   431	434	520	java/lang/RuntimeException
      //   434	500	520	java/lang/Exception
      //   500	514	520	java/lang/Exception
      //   500	514	520	java/lang/NullPointerException
    }
    
    protected ˋ() {}
    
    private static String ˊ(byte[] paramArrayOfByte, int[] paramArrayOfInt, char[] paramArrayOfChar, int paramInt)
    {
      break label261;
      int m;
      label52:
      int j;
      for (;;)
      {
        switch (i)
        {
        default: 
          break label460;
          if (i < m) {
            break label511;
          }
          break label303;
          switch (j)
          {
          default: 
            break label191;
            switch (i)
            {
            default: 
              label79:
              break label114;
              i = 54;
            }
            break;
          }
          break;
        }
      }
      label114:
      int i = ᐝ + 75;
      ˋॱ = i % 128;
      if (i % 2 != 0)
      {
        break label147;
        label144:
        break label402;
        label147:
        j = paramArrayOfByte.length;
        paramArrayOfInt = new char[j];
        i = 0;
      }
      for (;;)
      {
        try
        {
          m = ᐝ + 1;
          try
          {
            ˋॱ = m % 128;
            if (m % 2 != 0)
            {
              continue;
              label191:
              paramArrayOfByte = new String(paramArrayOfByte);
              continue;
              if (i < j) {
                continue;
              }
              continue;
            }
            switch (j)
            {
            default: 
              break label584;
              continue;
              m = paramArrayOfInt.length;
              paramArrayOfByte = new char[m];
              i = 0;
              continue;
              continue;
              i = ᐝ + 15;
              ˋॱ = i % 128;
              if (i % 2 == 0) {
                break;
              }
              break;
            case 1: 
              label261:
              return new String(paramArrayOfByte);
              label303:
              j = 0;
              break label52;
              paramArrayOfInt[i] = ((char)(arrayOfChar[(paramArrayOfByte[(j - 1 - i)] + paramInt)] - k));
              i += 1;
              continue;
              i = 1;
              break label79;
              i = 76;
            }
          }
          catch (Exception paramArrayOfByte)
          {
            throw paramArrayOfByte;
          }
          j = 0;
          continue;
          i = 0;
        }
        catch (Exception paramArrayOfByte)
        {
          char[] arrayOfChar;
          int k;
          label402:
          label460:
          label511:
          throw paramArrayOfByte;
        }
        m = paramArrayOfChar.length;
        paramArrayOfByte = new char[m];
        j = 0;
        continue;
        arrayOfChar = ʼ;
        k = ʻ;
        if (!ॱॱ)
        {
          continue;
          paramArrayOfByte[i] = ((char)(arrayOfChar[(paramArrayOfInt[(m - 1 - i)] - paramInt)] - k));
          i += 1;
          continue;
          break label147;
          return new String(paramArrayOfInt);
          i = 4 / 5;
          i = j;
          break;
          i = j;
          break;
          if (i >= m)
          {
            continue;
            paramArrayOfByte[i] = ((char)(arrayOfChar[(paramArrayOfChar[(m - 1 - i)] - paramInt)] - k));
            i += 1;
            break;
            j = 1;
            break label52;
            paramInt = ᐝ + 39;
            ˋॱ = paramInt % 128;
            if (paramInt % 2 == 0) {
              return paramArrayOfByte;
            }
            return paramArrayOfByte;
            j = 1;
            continue;
            continue;
            i = ˋॱ + 9;
            ᐝ = i % 128;
            if (i % 2 == 0)
            {
              continue;
              label584:
              j = ˋॱ;
              j += 99;
              ᐝ = j % 128;
              if (j % 2 != 0) {
                break label144;
              }
              continue;
              if (ʽ) {}
            }
          }
        }
      }
    }
    
    static void ˊ()
    {
      ॱॱ = true;
      ʽ = true;
      ʼ = new char[] { 174, 181, 177, 197, 169, 171, 170, 168, 187, 173, 184, 186, 179, 178, 167 };
      ʻ = 102;
    }
  }
  
  static final class ˎ<V>
    implements Callable<sw<? extends T>>
  {
    private static int ˊ = 0;
    private static int ˏ = 1;
    
    /* Error */
    ˎ(Gz paramGz, int paramInt)
    {
      // Byte code:
      //   0: goto +6 -> 6
      //   3: astore_1
      //   4: aload_1
      //   5: athrow
      //   6: aload_0
      //   7: aload_1
      //   8: putfield 33	o/Gz$ˎ:ॱ	Lo/Gz;
      //   11: aload_0
      //   12: iload_2
      //   13: putfield 35	o/Gz$ˎ:ˋ	I
      //   16: goto +3 -> 19
      //   19: aload_0
      //   20: invokespecial 37	java/lang/Object:<init>	()V
      //   23: return
      //   24: astore_1
      //   25: aload_1
      //   26: athrow
      // Local variable table:
      //   start	length	slot	name	signature
      //   0	27	0	this	ˎ
      //   0	27	1	paramGz	Gz
      //   0	27	2	paramInt	int
      // Exception table:
      //   from	to	target	type
      //   6	11	3	java/lang/IndexOutOfBoundsException
      //   11	16	3	java/lang/IndexOutOfBoundsException
      //   11	16	24	java/lang/NumberFormatException
    }
    
    /* Error */
    public final st<Object> ˎ()
    {
      // Byte code:
      //   0: goto +63 -> 63
      //   3: aconst_null
      //   4: arraylength
      //   5: istore_1
      //   6: aload 5
      //   8: areturn
      //   9: goto +1050 -> 1059
      //   12: iload_3
      //   13: aload_0
      //   14: getfield 35	o/Gz$ˎ:ˋ	I
      //   17: if_icmpeq +6 -> 23
      //   20: goto +146 -> 166
      //   23: goto +831 -> 854
      //   26: getstatic 22	o/Gz$ˎ:ˊ	I
      //   29: bipush 87
      //   31: iadd
      //   32: iconst_1
      //   33: isub
      //   34: istore_1
      //   35: iload_1
      //   36: iconst_m1
      //   37: iand
      //   38: iload_1
      //   39: iconst_m1
      //   40: ior
      //   41: iadd
      //   42: istore_1
      //   43: iload_1
      //   44: sipush 128
      //   47: irem
      //   48: putstatic 24	o/Gz$ˎ:ˏ	I
      //   51: iload_1
      //   52: iconst_2
      //   53: irem
      //   54: ifne +6 -> 60
      //   57: goto +999 -> 1056
      //   60: goto +791 -> 851
      //   63: goto +947 -> 1010
      //   66: getstatic 24	o/Gz$ˎ:ˏ	I
      //   69: istore_3
      //   70: iload_3
      //   71: bipush 19
      //   73: iand
      //   74: istore_2
      //   75: iload_3
      //   76: bipush 19
      //   78: ixor
      //   79: iload_3
      //   80: bipush 19
      //   82: iand
      //   83: ior
      //   84: ineg
      //   85: istore_3
      //   86: iload_3
      //   87: ineg
      //   88: iload_2
      //   89: ior
      //   90: iconst_1
      //   91: ishl
      //   92: iload_2
      //   93: iload_3
      //   94: ineg
      //   95: ixor
      //   96: isub
      //   97: istore_2
      //   98: iload_2
      //   99: sipush 128
      //   102: irem
      //   103: putstatic 22	o/Gz$ˎ:ˊ	I
      //   106: iload_2
      //   107: iconst_2
      //   108: irem
      //   109: ifeq +6 -> 115
      //   112: goto +387 -> 499
      //   115: goto +384 -> 499
      //   118: astore 5
      //   120: aload 5
      //   122: athrow
      //   123: iload_1
      //   124: lookupswitch	default:+28->152, 17:+294->418, 50:+572->696
      //   152: goto +544 -> 696
      //   155: bipush 17
      //   157: istore_1
      //   158: goto -35 -> 123
      //   161: iconst_0
      //   162: istore_1
      //   163: goto +500 -> 663
      //   166: getstatic 58	o/Gz$ˋ:ॱ	Lo/Gz$ˋ;
      //   169: astore 5
      //   171: bipush 7
      //   173: sipush 139
      //   176: sipush 173
      //   179: invokestatic 63	o/O:ˋ	(IIC)Ljava/lang/Object;
      //   182: checkcast 65	java/lang/Class
      //   185: ldc 66
      //   187: invokevirtual 70	java/lang/Class:getField	(Ljava/lang/String;)Ljava/lang/reflect/Field;
      //   190: aconst_null
      //   191: invokevirtual 76	java/lang/reflect/Field:get	(Ljava/lang/Object;)Ljava/lang/Object;
      //   194: astore 6
      //   196: aload_0
      //   197: getfield 35	o/Gz$ˎ:ˋ	I
      //   200: istore_1
      //   201: goto +23 -> 224
      //   204: astore 5
      //   206: aload 5
      //   208: invokevirtual 82	java/lang/Throwable:getCause	()Ljava/lang/Throwable;
      //   211: astore 6
      //   213: aload 6
      //   215: ifnull +6 -> 221
      //   218: aload 6
      //   220: athrow
      //   221: aload 5
      //   223: athrow
      //   224: bipush 7
      //   226: sipush 153
      //   229: iconst_0
      //   230: invokestatic 63	o/O:ˋ	(IIC)Ljava/lang/Object;
      //   233: checkcast 65	java/lang/Class
      //   236: iconst_4
      //   237: anewarray 65	java/lang/Class
      //   240: dup
      //   241: iconst_0
      //   242: ldc 55
      //   244: aastore
      //   245: dup
      //   246: iconst_1
      //   247: bipush 7
      //   249: sipush 139
      //   252: sipush 173
      //   255: invokestatic 63	o/O:ˋ	(IIC)Ljava/lang/Object;
      //   258: checkcast 65	java/lang/Class
      //   261: aastore
      //   262: dup
      //   263: iconst_2
      //   264: getstatic 88	java/lang/Integer:TYPE	Ljava/lang/Class;
      //   267: aastore
      //   268: dup
      //   269: iconst_3
      //   270: getstatic 88	java/lang/Integer:TYPE	Ljava/lang/Class;
      //   273: aastore
      //   274: invokevirtual 92	java/lang/Class:getDeclaredConstructor	([Ljava/lang/Class;)Ljava/lang/reflect/Constructor;
      //   277: iconst_4
      //   278: anewarray 5	java/lang/Object
      //   281: dup
      //   282: iconst_0
      //   283: aload 5
      //   285: aastore
      //   286: dup
      //   287: iconst_1
      //   288: aload 6
      //   290: aastore
      //   291: dup
      //   292: iconst_2
      //   293: iload_1
      //   294: invokestatic 96	java/lang/Integer:valueOf	(I)Ljava/lang/Integer;
      //   297: aastore
      //   298: dup
      //   299: iconst_3
      //   300: iload_2
      //   301: invokestatic 96	java/lang/Integer:valueOf	(I)Ljava/lang/Integer;
      //   304: aastore
      //   305: invokevirtual 102	java/lang/reflect/Constructor:newInstance	([Ljava/lang/Object;)Ljava/lang/Object;
      //   308: astore 5
      //   310: goto -284 -> 26
      //   313: aload 5
      //   315: invokestatic 107	o/st:ˏ	(Ljava/lang/Object;)Lo/st;
      //   318: astore 5
      //   320: goto +45 -> 365
      //   323: iload_1
      //   324: lookupswitch	default:+28->352, 15:+459->783, 19:+677->1001
      //   352: goto +431 -> 783
      //   355: astore 5
      //   357: aload 5
      //   359: athrow
      //   360: iconst_1
      //   361: istore_1
      //   362: goto +354 -> 716
      //   365: getstatic 24	o/Gz$ˎ:ˏ	I
      //   368: istore_1
      //   369: iload_1
      //   370: bipush 91
      //   372: ixor
      //   373: iload_1
      //   374: bipush 91
      //   376: iand
      //   377: ior
      //   378: iconst_1
      //   379: ishl
      //   380: iload_1
      //   381: bipush -92
      //   383: iand
      //   384: iload_1
      //   385: iconst_m1
      //   386: ixor
      //   387: bipush 91
      //   389: iand
      //   390: ior
      //   391: ineg
      //   392: iconst_m1
      //   393: ixor
      //   394: isub
      //   395: iconst_1
      //   396: isub
      //   397: istore_1
      //   398: iload_1
      //   399: sipush 128
      //   402: irem
      //   403: putstatic 22	o/Gz$ˎ:ˊ	I
      //   406: iload_1
      //   407: iconst_2
      //   408: irem
      //   409: ifeq +6 -> 415
      //   412: goto +279 -> 691
      //   415: goto -254 -> 161
      //   418: iload_2
      //   419: aload_0
      //   420: getfield 35	o/Gz$ˎ:ˋ	I
      //   423: if_icmpne +6 -> 429
      //   426: goto +317 -> 743
      //   429: goto -69 -> 360
      //   432: getstatic 24	o/Gz$ˎ:ˏ	I
      //   435: istore 4
      //   437: iload 4
      //   439: bipush 47
      //   441: ixor
      //   442: iload 4
      //   444: bipush 47
      //   446: iand
      //   447: ior
      //   448: iconst_1
      //   449: ishl
      //   450: istore_1
      //   451: iload 4
      //   453: bipush 47
      //   455: iand
      //   456: iconst_m1
      //   457: ixor
      //   458: iload 4
      //   460: bipush 47
      //   462: ior
      //   463: iand
      //   464: ineg
      //   465: istore 4
      //   467: iload_1
      //   468: iload 4
      //   470: ixor
      //   471: iload_1
      //   472: iload 4
      //   474: iand
      //   475: iconst_1
      //   476: ishl
      //   477: iadd
      //   478: istore_1
      //   479: iload_1
      //   480: sipush 128
      //   483: irem
      //   484: putstatic 22	o/Gz$ˎ:ˊ	I
      //   487: iload_1
      //   488: iconst_2
      //   489: irem
      //   490: ifeq +6 -> 496
      //   493: goto +557 -> 1050
      //   496: goto -341 -> 155
      //   499: goto +23 -> 522
      //   502: astore 5
      //   504: aload 5
      //   506: invokevirtual 82	java/lang/Throwable:getCause	()Ljava/lang/Throwable;
      //   509: astore 6
      //   511: aload 6
      //   513: ifnull +6 -> 519
      //   516: aload 6
      //   518: athrow
      //   519: aload 5
      //   521: athrow
      //   522: iconst_4
      //   523: bipush 50
      //   525: iconst_0
      //   526: invokestatic 63	o/O:ˋ	(IIC)Ljava/lang/Object;
      //   529: checkcast 65	java/lang/Class
      //   532: ldc 108
      //   534: iconst_2
      //   535: anewarray 65	java/lang/Class
      //   538: dup
      //   539: iconst_0
      //   540: ldc 110
      //   542: aastore
      //   543: dup
      //   544: iconst_1
      //   545: getstatic 88	java/lang/Integer:TYPE	Ljava/lang/Class;
      //   548: aastore
      //   549: invokevirtual 114	java/lang/Class:getMethod	(Ljava/lang/String;[Ljava/lang/Class;)Ljava/lang/reflect/Method;
      //   552: aconst_null
      //   553: iconst_2
      //   554: anewarray 5	java/lang/Object
      //   557: dup
      //   558: iconst_0
      //   559: aload 5
      //   561: aastore
      //   562: dup
      //   563: iconst_1
      //   564: iload_1
      //   565: invokestatic 96	java/lang/Integer:valueOf	(I)Ljava/lang/Integer;
      //   568: aastore
      //   569: invokevirtual 120	java/lang/reflect/Method:invoke	(Ljava/lang/Object;[Ljava/lang/Object;)Ljava/lang/Object;
      //   572: checkcast 84	java/lang/Integer
      //   575: invokevirtual 124	java/lang/Integer:intValue	()I
      //   578: istore_2
      //   579: aload_0
      //   580: getfield 35	o/Gz$ˎ:ˋ	I
      //   583: istore_1
      //   584: goto +23 -> 607
      //   587: astore 5
      //   589: aload 5
      //   591: invokevirtual 82	java/lang/Throwable:getCause	()Ljava/lang/Throwable;
      //   594: astore 6
      //   596: aload 6
      //   598: ifnull +6 -> 604
      //   601: aload 6
      //   603: athrow
      //   604: aload 5
      //   606: athrow
      //   607: iconst_4
      //   608: bipush 50
      //   610: iconst_0
      //   611: invokestatic 63	o/O:ˋ	(IIC)Ljava/lang/Object;
      //   614: checkcast 65	java/lang/Class
      //   617: ldc 125
      //   619: iconst_1
      //   620: anewarray 65	java/lang/Class
      //   623: dup
      //   624: iconst_0
      //   625: getstatic 88	java/lang/Integer:TYPE	Ljava/lang/Class;
      //   628: aastore
      //   629: invokevirtual 114	java/lang/Class:getMethod	(Ljava/lang/String;[Ljava/lang/Class;)Ljava/lang/reflect/Method;
      //   632: aconst_null
      //   633: iconst_1
      //   634: anewarray 5	java/lang/Object
      //   637: dup
      //   638: iconst_0
      //   639: iload_1
      //   640: invokestatic 96	java/lang/Integer:valueOf	(I)Ljava/lang/Integer;
      //   643: aastore
      //   644: invokevirtual 120	java/lang/reflect/Method:invoke	(Ljava/lang/Object;[Ljava/lang/Object;)Ljava/lang/Object;
      //   647: checkcast 84	java/lang/Integer
      //   650: invokevirtual 124	java/lang/Integer:intValue	()I
      //   653: istore_3
      //   654: goto -222 -> 432
      //   657: bipush 15
      //   659: istore_1
      //   660: goto -337 -> 323
      //   663: iload_1
      //   664: tableswitch	default:+24->688, 0:+412->1076, 1:+-661->3
      //   688: aload 5
      //   690: areturn
      //   691: iconst_1
      //   692: istore_1
      //   693: goto -30 -> 663
      //   696: aload_0
      //   697: getfield 35	o/Gz$ˎ:ˋ	I
      //   700: istore_1
      //   701: aconst_null
      //   702: arraylength
      //   703: istore 4
      //   705: iload_2
      //   706: iload_1
      //   707: if_icmpne +6 -> 713
      //   710: goto +135 -> 845
      //   713: goto +291 -> 1004
      //   716: iload_1
      //   717: tableswitch	default:+23->740, 0:+-705->12, 1:+-551->166
      //   740: goto -728 -> 12
      //   743: iconst_0
      //   744: istore_1
      //   745: goto -29 -> 716
      //   748: bipush 19
      //   750: istore_1
      //   751: goto -428 -> 323
      //   754: iload_1
      //   755: lookupswitch	default:+25->780, 29:+-743->12, 51:+-589->166
      //   780: goto -768 -> 12
      //   783: goto -470 -> 313
      //   786: getstatic 24	o/Gz$ˎ:ˏ	I
      //   789: istore_2
      //   790: iload_2
      //   791: bipush 111
      //   793: ixor
      //   794: iload_2
      //   795: bipush 111
      //   797: iand
      //   798: ior
      //   799: iconst_1
      //   800: ishl
      //   801: istore_1
      //   802: iload_2
      //   803: bipush 111
      //   805: iand
      //   806: iconst_m1
      //   807: ixor
      //   808: iload_2
      //   809: bipush 111
      //   811: ior
      //   812: iand
      //   813: ineg
      //   814: istore_2
      //   815: iload_1
      //   816: iload_2
      //   817: ixor
      //   818: iload_1
      //   819: iload_2
      //   820: iand
      //   821: iconst_1
      //   822: ishl
      //   823: iadd
      //   824: istore_1
      //   825: iload_1
      //   826: sipush 128
      //   829: irem
      //   830: putstatic 22	o/Gz$ˎ:ˊ	I
      //   833: iload_1
      //   834: iconst_2
      //   835: irem
      //   836: ifeq +6 -> 842
      //   839: goto -91 -> 748
      //   842: goto -185 -> 657
      //   845: bipush 29
      //   847: istore_1
      //   848: goto -94 -> 754
      //   851: goto -538 -> 313
      //   854: getstatic 58	o/Gz$ˋ:ॱ	Lo/Gz$ˋ;
      //   857: astore 5
      //   859: bipush 7
      //   861: sipush 139
      //   864: sipush 173
      //   867: invokestatic 63	o/O:ˋ	(IIC)Ljava/lang/Object;
      //   870: checkcast 65	java/lang/Class
      //   873: ldc 126
      //   875: invokevirtual 70	java/lang/Class:getField	(Ljava/lang/String;)Ljava/lang/reflect/Field;
      //   878: aconst_null
      //   879: invokevirtual 76	java/lang/reflect/Field:get	(Ljava/lang/Object;)Ljava/lang/Object;
      //   882: astore 6
      //   884: aload_0
      //   885: getfield 35	o/Gz$ˎ:ˋ	I
      //   888: istore_1
      //   889: goto +23 -> 912
      //   892: astore 5
      //   894: aload 5
      //   896: invokevirtual 82	java/lang/Throwable:getCause	()Ljava/lang/Throwable;
      //   899: astore 6
      //   901: aload 6
      //   903: ifnull +6 -> 909
      //   906: aload 6
      //   908: athrow
      //   909: aload 5
      //   911: athrow
      //   912: bipush 7
      //   914: sipush 153
      //   917: iconst_0
      //   918: invokestatic 63	o/O:ˋ	(IIC)Ljava/lang/Object;
      //   921: checkcast 65	java/lang/Class
      //   924: iconst_4
      //   925: anewarray 65	java/lang/Class
      //   928: dup
      //   929: iconst_0
      //   930: ldc 55
      //   932: aastore
      //   933: dup
      //   934: iconst_1
      //   935: bipush 7
      //   937: sipush 139
      //   940: sipush 173
      //   943: invokestatic 63	o/O:ˋ	(IIC)Ljava/lang/Object;
      //   946: checkcast 65	java/lang/Class
      //   949: aastore
      //   950: dup
      //   951: iconst_2
      //   952: getstatic 88	java/lang/Integer:TYPE	Ljava/lang/Class;
      //   955: aastore
      //   956: dup
      //   957: iconst_3
      //   958: getstatic 88	java/lang/Integer:TYPE	Ljava/lang/Class;
      //   961: aastore
      //   962: invokevirtual 92	java/lang/Class:getDeclaredConstructor	([Ljava/lang/Class;)Ljava/lang/reflect/Constructor;
      //   965: iconst_4
      //   966: anewarray 5	java/lang/Object
      //   969: dup
      //   970: iconst_0
      //   971: aload 5
      //   973: aastore
      //   974: dup
      //   975: iconst_1
      //   976: aload 6
      //   978: aastore
      //   979: dup
      //   980: iconst_2
      //   981: iload_1
      //   982: invokestatic 96	java/lang/Integer:valueOf	(I)Ljava/lang/Integer;
      //   985: aastore
      //   986: dup
      //   987: iconst_3
      //   988: iload_2
      //   989: invokestatic 96	java/lang/Integer:valueOf	(I)Ljava/lang/Integer;
      //   992: aastore
      //   993: invokevirtual 102	java/lang/reflect/Constructor:newInstance	([Ljava/lang/Object;)Ljava/lang/Object;
      //   996: astore 5
      //   998: goto -212 -> 786
      //   1001: goto -688 -> 313
      //   1004: bipush 51
      //   1006: istore_1
      //   1007: goto -253 -> 754
      //   1010: getstatic 22	o/Gz$ˎ:ˊ	I
      //   1013: istore_1
      //   1014: iload_1
      //   1015: bipush 120
      //   1017: ior
      //   1018: iconst_1
      //   1019: ishl
      //   1020: iload_1
      //   1021: bipush 120
      //   1023: ixor
      //   1024: isub
      //   1025: iconst_0
      //   1026: iadd
      //   1027: iconst_1
      //   1028: isub
      //   1029: istore_1
      //   1030: iload_1
      //   1031: sipush 128
      //   1034: irem
      //   1035: putstatic 24	o/Gz$ˎ:ˏ	I
      //   1038: iload_1
      //   1039: iconst_2
      //   1040: irem
      //   1041: ifne +6 -> 1047
      //   1044: goto -1035 -> 9
      //   1047: goto +12 -> 1059
      //   1050: bipush 50
      //   1052: istore_1
      //   1053: goto -930 -> 123
      //   1056: goto -205 -> 851
      //   1059: aload_0
      //   1060: getfield 33	o/Gz$ˎ:ॱ	Lo/Gz;
      //   1063: invokevirtual 130	o/Gz:ʼ	()Landroid/content/Context;
      //   1066: astore 5
      //   1068: aload_0
      //   1069: getfield 35	o/Gz$ˎ:ˋ	I
      //   1072: istore_1
      //   1073: goto -1007 -> 66
      //   1076: aload 5
      //   1078: areturn
      // Local variable table:
      //   start	length	slot	name	signature
      //   0	1079	0	this	ˎ
      //   5	1068	1	i	int
      //   74	915	2	j	int
      //   12	642	3	k	int
      //   435	269	4	m	int
      //   6	1	5	localSt1	st<Object>
      //   118	3	5	localNullPointerException1	NullPointerException
      //   169	1	5	localˋ1	Gz.ˋ
      //   204	80	5	localObject1	Object
      //   308	11	5	localObject2	Object
      //   355	3	5	localNullPointerException2	NullPointerException
      //   502	58	5	localObject3	Object
      //   587	102	5	localSt2	st<Object>
      //   857	1	5	localˋ2	Gz.ˋ
      //   892	80	5	localObject4	Object
      //   996	81	5	localObject5	Object
      //   194	783	6	localObject6	Object
      // Exception table:
      //   from	to	target	type
      //   66	70	118	java/lang/NullPointerException
      //   98	106	118	java/lang/NullPointerException
      //   98	106	118	java/lang/ArrayStoreException
      //   313	320	118	java/lang/ClassCastException
      //   1010	1014	118	java/lang/IndexOutOfBoundsException
      //   224	310	204	finally
      //   166	171	355	java/lang/NullPointerException
      //   171	196	355	java/lang/NullPointerException
      //   196	201	355	java/lang/NullPointerException
      //   196	201	355	java/lang/Exception
      //   206	213	355	java/lang/NullPointerException
      //   218	221	355	java/lang/NullPointerException
      //   221	224	355	java/lang/NullPointerException
      //   365	369	355	java/lang/UnsupportedOperationException
      //   398	406	355	java/lang/Exception
      //   1030	1038	355	java/lang/NumberFormatException
      //   522	579	502	finally
      //   607	654	587	finally
      //   912	998	892	finally
    }
  }
  
  public final class ˏ
    implements sx<Object>
  {
    private static int ˊ = 0;
    private static int[] ˏ = { 449099452, -1761902763, 482886120, -1258207564, -1741572523, 70398143, 1797236952, -1018252976, 469980982, -1644909879, -1462141172, -1965731716, 1779000664, -1415795291, -1247087263, 481589249, -2122106483, 1163370849 };
    private static int ॱ = 1;
    
    /* Error */
    public ˏ()
    {
      // Byte code:
      //   0: goto +6 -> 6
      //   3: astore_1
      //   4: aload_1
      //   5: athrow
      //   6: aload_0
      //   7: aload_1
      //   8: putfield 49	o/Gz$ˏ:ˎ	Lo/Gz;
      //   11: aload_0
      //   12: invokespecial 51	java/lang/Object:<init>	()V
      //   15: return
      // Local variable table:
      //   start	length	slot	name	signature
      //   0	16	0	this	ˏ
      //   0	16	1	this$1	Gz
      // Exception table:
      //   from	to	target	type
      //   6	11	3	java/lang/UnsupportedOperationException
    }
    
    private static String ˎ(int[] paramArrayOfInt, int paramInt)
    {
      break label259;
      int j = 69;
      break label227;
      label9:
      char[] arrayOfChar1;
      int i;
      arrayOfChar1[0] = ((char)(paramArrayOfInt[i] >> 16));
      arrayOfChar1[1] = ((char)paramArrayOfInt[i]);
      arrayOfChar1[2] = ((char)(paramArrayOfInt[(i + 1)] >> 16));
      arrayOfChar1[3] = ((char)paramArrayOfInt[(i + 1)]);
      int[] arrayOfInt;
      oN.ˏ(arrayOfChar1, arrayOfInt, false);
      char[] arrayOfChar2;
      arrayOfChar2[(i << 1)] = arrayOfChar1[0];
      arrayOfChar2[((i << 1) + 1)] = arrayOfChar1[1];
      arrayOfChar2[((i << 1) + 2)] = arrayOfChar1[2];
      arrayOfChar2[((i << 1) + 3)] = arrayOfChar1[3];
      i += 2;
      break label222;
      label142:
      label168:
      label180:
      for (;;)
      {
        arrayOfChar1 = new char[4];
        arrayOfChar2 = new char[paramArrayOfInt.length << 1];
        arrayOfInt = (int[])ˏ.clone();
        i = 0;
        break label168;
        j = ॱ + 1;
        ˊ = j % 128;
        if (j % 2 != 0) {
          break label9;
        }
        break label9;
        if (i < paramArrayOfInt.length) {
          break label225;
        }
        break;
      }
      label222:
      label225:
      label227:
      label259:
      for (;;)
      {
        i = ˊ + 91;
        ॱ = i % 128;
        if (i % 2 == 0) {
          break label180;
        }
        break;
        return new String(arrayOfChar2, 0, paramInt);
        break label168;
        j = 4;
        switch (j)
        {
        }
        break label142;
      }
    }
    
    /* Error */
    public void ˊ(sH paramSH)
    {
      // Byte code:
      //   0: goto +526 -> 526
      //   3: getstatic 22	o/Gz$ˏ:ॱ	I
      //   6: istore_2
      //   7: iload_2
      //   8: bipush 91
      //   10: ixor
      //   11: iload_2
      //   12: bipush 91
      //   14: iand
      //   15: iconst_1
      //   16: ishl
      //   17: iadd
      //   18: istore_2
      //   19: iload_2
      //   20: sipush 128
      //   23: irem
      //   24: putstatic 20	o/Gz$ˏ:ˊ	I
      //   27: iload_2
      //   28: iconst_2
      //   29: irem
      //   30: ifeq +6 -> 36
      //   33: goto +496 -> 529
      //   36: goto +142 -> 178
      //   39: goto +55 -> 94
      //   42: getstatic 22	o/Gz$ˏ:ॱ	I
      //   45: istore_3
      //   46: iload_3
      //   47: bipush 121
      //   49: ior
      //   50: iconst_1
      //   51: ishl
      //   52: istore_2
      //   53: iload_3
      //   54: bipush -122
      //   56: iand
      //   57: iload_3
      //   58: iconst_m1
      //   59: ixor
      //   60: bipush 121
      //   62: iand
      //   63: ior
      //   64: ineg
      //   65: istore_3
      //   66: iload_2
      //   67: iload_3
      //   68: ixor
      //   69: iload_2
      //   70: iload_3
      //   71: iand
      //   72: iconst_1
      //   73: ishl
      //   74: iadd
      //   75: istore_2
      //   76: iload_2
      //   77: sipush 128
      //   80: irem
      //   81: putstatic 20	o/Gz$ˏ:ˊ	I
      //   84: iload_2
      //   85: iconst_2
      //   86: irem
      //   87: ifeq +6 -> 93
      //   90: goto +53 -> 143
      //   93: return
      //   94: aload_1
      //   95: bipush 6
      //   97: newarray int
      //   99: dup
      //   100: iconst_0
      //   101: ldc 80
      //   103: iastore
      //   104: dup
      //   105: iconst_1
      //   106: ldc 81
      //   108: iastore
      //   109: dup
      //   110: iconst_2
      //   111: ldc 82
      //   113: iastore
      //   114: dup
      //   115: iconst_3
      //   116: ldc 83
      //   118: iastore
      //   119: dup
      //   120: iconst_4
      //   121: ldc 84
      //   123: iastore
      //   124: dup
      //   125: iconst_5
      //   126: ldc 85
      //   128: iastore
      //   129: bipush 10
      //   131: invokestatic 87	o/Gz$ˏ:ˎ	([II)Ljava/lang/String;
      //   134: invokevirtual 91	java/lang/String:intern	()Ljava/lang/String;
      //   137: invokestatic 96	o/vq:ˎ	(Ljava/lang/Object;Ljava/lang/String;)V
      //   140: goto +337 -> 477
      //   143: return
      //   144: getstatic 22	o/Gz$ˏ:ॱ	I
      //   147: istore_2
      //   148: iload_2
      //   149: bipush 111
      //   151: iand
      //   152: iload_2
      //   153: bipush 111
      //   155: ior
      //   156: iadd
      //   157: istore_2
      //   158: iload_2
      //   159: sipush 128
      //   162: irem
      //   163: putstatic 20	o/Gz$ˏ:ˊ	I
      //   166: iload_2
      //   167: iconst_2
      //   168: irem
      //   169: ifeq +6 -> 175
      //   172: goto -133 -> 39
      //   175: goto -81 -> 94
      //   178: aload 6
      //   180: iload 4
      //   182: invokevirtual 102	java/lang/StringBuilder:append	(Z)Ljava/lang/StringBuilder;
      //   185: invokevirtual 105	java/lang/StringBuilder:toString	()Ljava/lang/String;
      //   188: astore_1
      //   189: goto +20 -> 209
      //   192: astore_1
      //   193: aload_1
      //   194: invokevirtual 111	java/lang/Throwable:getCause	()Ljava/lang/Throwable;
      //   197: astore 5
      //   199: aload 5
      //   201: ifnull +6 -> 207
      //   204: aload 5
      //   206: athrow
      //   207: aload_1
      //   208: athrow
      //   209: iconst_4
      //   210: bipush 42
      //   212: ldc 112
      //   214: invokestatic 118	o/O:ˋ	(IIC)Ljava/lang/Object;
      //   217: checkcast 120	java/lang/Class
      //   220: ldc 121
      //   222: iconst_2
      //   223: anewarray 120	java/lang/Class
      //   226: dup
      //   227: iconst_0
      //   228: ldc 65
      //   230: aastore
      //   231: dup
      //   232: iconst_1
      //   233: ldc 65
      //   235: aastore
      //   236: invokevirtual 125	java/lang/Class:getMethod	(Ljava/lang/String;[Ljava/lang/Class;)Ljava/lang/reflect/Method;
      //   239: aconst_null
      //   240: iconst_2
      //   241: anewarray 5	java/lang/Object
      //   244: dup
      //   245: iconst_0
      //   246: aload 5
      //   248: aastore
      //   249: dup
      //   250: iconst_1
      //   251: aload_1
      //   252: aastore
      //   253: invokevirtual 131	java/lang/reflect/Method:invoke	(Ljava/lang/Object;[Ljava/lang/Object;)Ljava/lang/Object;
      //   256: pop
      //   257: goto -215 -> 42
      //   260: bipush 22
      //   262: newarray int
      //   264: dup
      //   265: iconst_0
      //   266: ldc -124
      //   268: iastore
      //   269: dup
      //   270: iconst_1
      //   271: ldc -123
      //   273: iastore
      //   274: dup
      //   275: iconst_2
      //   276: ldc -122
      //   278: iastore
      //   279: dup
      //   280: iconst_3
      //   281: ldc -121
      //   283: iastore
      //   284: dup
      //   285: iconst_4
      //   286: ldc -120
      //   288: iastore
      //   289: dup
      //   290: iconst_5
      //   291: ldc -119
      //   293: iastore
      //   294: dup
      //   295: bipush 6
      //   297: ldc -118
      //   299: iastore
      //   300: dup
      //   301: bipush 7
      //   303: ldc -117
      //   305: iastore
      //   306: dup
      //   307: bipush 8
      //   309: ldc -116
      //   311: iastore
      //   312: dup
      //   313: bipush 9
      //   315: ldc -115
      //   317: iastore
      //   318: dup
      //   319: bipush 10
      //   321: ldc -114
      //   323: iastore
      //   324: dup
      //   325: bipush 11
      //   327: ldc -113
      //   329: iastore
      //   330: dup
      //   331: bipush 12
      //   333: ldc -112
      //   335: iastore
      //   336: dup
      //   337: bipush 13
      //   339: ldc -111
      //   341: iastore
      //   342: dup
      //   343: bipush 14
      //   345: ldc -110
      //   347: iastore
      //   348: dup
      //   349: bipush 15
      //   351: ldc -109
      //   353: iastore
      //   354: dup
      //   355: bipush 16
      //   357: ldc -108
      //   359: iastore
      //   360: dup
      //   361: bipush 17
      //   363: ldc -107
      //   365: iastore
      //   366: dup
      //   367: bipush 18
      //   369: ldc -106
      //   371: iastore
      //   372: dup
      //   373: bipush 19
      //   375: ldc -105
      //   377: iastore
      //   378: dup
      //   379: bipush 20
      //   381: ldc -104
      //   383: iastore
      //   384: dup
      //   385: bipush 21
      //   387: ldc -103
      //   389: iastore
      //   390: bipush 43
      //   392: invokestatic 87	o/Gz$ˏ:ˎ	([II)Ljava/lang/String;
      //   395: astore 7
      //   397: aload 7
      //   399: invokevirtual 91	java/lang/String:intern	()Ljava/lang/String;
      //   402: astore 7
      //   404: aload 6
      //   406: aload 7
      //   408: invokevirtual 156	java/lang/StringBuilder:append	(Ljava/lang/String;)Ljava/lang/StringBuilder;
      //   411: astore 6
      //   413: aload_1
      //   414: invokeinterface 161 1 0
      //   419: istore 4
      //   421: goto -418 -> 3
      //   424: getstatic 22	o/Gz$ˏ:ॱ	I
      //   427: istore_2
      //   428: iload_2
      //   429: bipush -96
      //   431: iand
      //   432: iload_2
      //   433: iconst_m1
      //   434: ixor
      //   435: bipush 95
      //   437: iand
      //   438: ior
      //   439: iload_2
      //   440: bipush 95
      //   442: iand
      //   443: iconst_1
      //   444: ishl
      //   445: iconst_m1
      //   446: ixor
      //   447: isub
      //   448: iconst_1
      //   449: isub
      //   450: istore_2
      //   451: iload_2
      //   452: sipush 128
      //   455: irem
      //   456: putstatic 20	o/Gz$ˏ:ˊ	I
      //   459: iload_2
      //   460: iconst_2
      //   461: irem
      //   462: ifeq +6 -> 468
      //   465: goto +9 -> 474
      //   468: goto -208 -> 260
      //   471: astore_1
      //   472: aload_1
      //   473: athrow
      //   474: goto -214 -> 260
      //   477: iconst_4
      //   478: newarray int
      //   480: dup
      //   481: iconst_0
      //   482: ldc -94
      //   484: iastore
      //   485: dup
      //   486: iconst_1
      //   487: ldc -93
      //   489: iastore
      //   490: dup
      //   491: iconst_2
      //   492: ldc -92
      //   494: iastore
      //   495: dup
      //   496: iconst_3
      //   497: ldc -91
      //   499: iastore
      //   500: bipush 8
      //   502: invokestatic 87	o/Gz$ˏ:ˎ	([II)Ljava/lang/String;
      //   505: astore 5
      //   507: aload 5
      //   509: invokevirtual 91	java/lang/String:intern	()Ljava/lang/String;
      //   512: astore 5
      //   514: new 98	java/lang/StringBuilder
      //   517: dup
      //   518: invokespecial 166	java/lang/StringBuilder:<init>	()V
      //   521: astore 6
      //   523: goto -99 -> 424
      //   526: goto -382 -> 144
      //   529: goto -351 -> 178
      //   532: astore_1
      //   533: aload_1
      //   534: athrow
      // Local variable table:
      //   start	length	slot	name	signature
      //   0	535	0	this	ˏ
      //   0	535	1	paramSH	sH
      //   6	456	2	i	int
      //   45	27	3	j	int
      //   180	240	4	bool	boolean
      //   197	316	5	localObject	Object
      //   178	344	6	localStringBuilder	StringBuilder
      //   395	12	7	str	String
      // Exception table:
      //   from	to	target	type
      //   209	257	192	finally
      //   3	7	471	java/lang/UnsupportedOperationException
      //   260	397	471	java/lang/ArrayStoreException
      //   413	421	471	java/lang/ClassCastException
      //   424	428	471	java/lang/ArrayStoreException
      //   451	459	471	java/lang/ArrayStoreException
      //   477	507	471	java/lang/Exception
      //   507	514	471	java/lang/Exception
      //   507	514	471	java/lang/ClassCastException
      //   514	523	471	java/lang/Exception
      //   397	404	532	java/lang/NumberFormatException
      //   404	413	532	java/lang/NumberFormatException
      //   413	421	532	java/lang/NumberFormatException
      //   451	459	532	java/lang/IllegalArgumentException
    }
    
    public void ˋ$2b6e2c62(Object paramObject)
    {
      throw new Runtime("d2j fail translate: java.lang.RuntimeException: can not merge I and Z\n\tat com.googlecode.dex2jar.ir.TypeClass.merge(TypeClass.java:100)\n\tat com.googlecode.dex2jar.ir.ts.TypeTransformer$TypeRef.updateTypeClass(TypeTransformer.java:174)\n\tat com.googlecode.dex2jar.ir.ts.TypeTransformer$TypeAnalyze.copyTypes(TypeTransformer.java:311)\n\tat com.googlecode.dex2jar.ir.ts.TypeTransformer$TypeAnalyze.fixTypes(TypeTransformer.java:226)\n\tat com.googlecode.dex2jar.ir.ts.TypeTransformer$TypeAnalyze.analyze(TypeTransformer.java:207)\n\tat com.googlecode.dex2jar.ir.ts.TypeTransformer.transform(TypeTransformer.java:44)\n\tat com.googlecode.d2j.dex.Dex2jar$2.optimize(Dex2jar.java:162)\n\tat com.googlecode.d2j.dex.Dex2Asm.convertCode(Dex2Asm.java:414)\n\tat com.googlecode.d2j.dex.ExDex2Asm.convertCode(ExDex2Asm.java:42)\n\tat com.googlecode.d2j.dex.Dex2jar$2.convertCode(Dex2jar.java:128)\n\tat com.googlecode.d2j.dex.Dex2Asm.convertMethod(Dex2Asm.java:509)\n\tat com.googlecode.d2j.dex.Dex2Asm.convertClass(Dex2Asm.java:406)\n\tat com.googlecode.d2j.dex.Dex2Asm.convertDex(Dex2Asm.java:422)\n\tat com.googlecode.d2j.dex.Dex2jar.doTranslate(Dex2jar.java:172)\n\tat com.googlecode.d2j.dex.Dex2jar.to(Dex2jar.java:272)\n\tat com.googlecode.dex2jar.tools.Dex2jarCmd.doCommandLine(Dex2jarCmd.java:108)\n\tat com.googlecode.dex2jar.tools.BaseCmd.doMain(BaseCmd.java:288)\n\tat com.googlecode.dex2jar.tools.Dex2jarCmd.main(Dex2jarCmd.java:32)\n");
    }
    
    /* Error */
    public void ˏ()
    {
      // Byte code:
      //   0: goto +303 -> 303
      //   3: getstatic 20	o/Gz$ˏ:ˊ	I
      //   6: istore_1
      //   7: iload_1
      //   8: bipush 117
      //   10: ixor
      //   11: iload_1
      //   12: bipush 117
      //   14: iand
      //   15: ior
      //   16: iconst_1
      //   17: ishl
      //   18: iload_1
      //   19: bipush -118
      //   21: iand
      //   22: iload_1
      //   23: iconst_m1
      //   24: ixor
      //   25: bipush 117
      //   27: iand
      //   28: ior
      //   29: isub
      //   30: istore_1
      //   31: iload_1
      //   32: sipush 128
      //   35: irem
      //   36: putstatic 22	o/Gz$ˏ:ॱ	I
      //   39: iload_1
      //   40: iconst_2
      //   41: irem
      //   42: ifne +6 -> 48
      //   45: goto +374 -> 419
      //   48: goto +261 -> 309
      //   51: bipush 85
      //   53: istore_1
      //   54: goto +127 -> 181
      //   57: getstatic 22	o/Gz$ˏ:ॱ	I
      //   60: istore_1
      //   61: iload_1
      //   62: bipush 17
      //   64: iand
      //   65: iload_1
      //   66: bipush 17
      //   68: ixor
      //   69: iload_1
      //   70: bipush 17
      //   72: iand
      //   73: ior
      //   74: iadd
      //   75: istore_1
      //   76: iload_1
      //   77: sipush 128
      //   80: irem
      //   81: putstatic 20	o/Gz$ˏ:ˊ	I
      //   84: iload_1
      //   85: iconst_2
      //   86: irem
      //   87: ifeq +6 -> 93
      //   90: goto +121 -> 211
      //   93: goto -42 -> 51
      //   96: aload_3
      //   97: bipush 24
      //   99: invokestatic 87	o/Gz$ˏ:ˎ	([II)Ljava/lang/String;
      //   102: invokevirtual 91	java/lang/String:intern	()Ljava/lang/String;
      //   105: astore_3
      //   106: goto +17 -> 123
      //   109: astore_2
      //   110: aload_2
      //   111: invokevirtual 111	java/lang/Throwable:getCause	()Ljava/lang/Throwable;
      //   114: astore_3
      //   115: aload_3
      //   116: ifnull +5 -> 121
      //   119: aload_3
      //   120: athrow
      //   121: aload_2
      //   122: athrow
      //   123: iconst_4
      //   124: bipush 42
      //   126: ldc 112
      //   128: invokestatic 118	o/O:ˋ	(IIC)Ljava/lang/Object;
      //   131: checkcast 120	java/lang/Class
      //   134: ldc 121
      //   136: iconst_2
      //   137: anewarray 120	java/lang/Class
      //   140: dup
      //   141: iconst_0
      //   142: ldc 65
      //   144: aastore
      //   145: dup
      //   146: iconst_1
      //   147: ldc 65
      //   149: aastore
      //   150: invokevirtual 125	java/lang/Class:getMethod	(Ljava/lang/String;[Ljava/lang/Class;)Ljava/lang/reflect/Method;
      //   153: aconst_null
      //   154: iconst_2
      //   155: anewarray 5	java/lang/Object
      //   158: dup
      //   159: iconst_0
      //   160: aload_2
      //   161: aastore
      //   162: dup
      //   163: iconst_1
      //   164: aload_3
      //   165: aastore
      //   166: invokevirtual 131	java/lang/reflect/Method:invoke	(Ljava/lang/Object;[Ljava/lang/Object;)Ljava/lang/Object;
      //   169: pop
      //   170: getstatic 184	o/Gz:ˎ	Lo/Gz$ˊ;
      //   173: iconst_0
      //   174: invokevirtual 189	o/Gz$ˊ:ॱ	(Z)V
      //   177: return
      //   178: astore_2
      //   179: aload_2
      //   180: athrow
      //   181: iload_1
      //   182: lookupswitch	default:+26->208, 64:+35->217, 85:+-86->96
      //   208: goto +9 -> 217
      //   211: bipush 64
      //   213: istore_1
      //   214: goto -33 -> 181
      //   217: aload_3
      //   218: bipush 24
      //   220: invokestatic 87	o/Gz$ˏ:ˎ	([II)Ljava/lang/String;
      //   223: astore_3
      //   224: aload_3
      //   225: invokevirtual 91	java/lang/String:intern	()Ljava/lang/String;
      //   228: astore_3
      //   229: goto +17 -> 246
      //   232: astore_2
      //   233: aload_2
      //   234: invokevirtual 111	java/lang/Throwable:getCause	()Ljava/lang/Throwable;
      //   237: astore_3
      //   238: aload_3
      //   239: ifnull +5 -> 244
      //   242: aload_3
      //   243: athrow
      //   244: aload_2
      //   245: athrow
      //   246: iconst_4
      //   247: bipush 42
      //   249: ldc 112
      //   251: invokestatic 118	o/O:ˋ	(IIC)Ljava/lang/Object;
      //   254: checkcast 120	java/lang/Class
      //   257: ldc 121
      //   259: iconst_2
      //   260: anewarray 120	java/lang/Class
      //   263: dup
      //   264: iconst_0
      //   265: ldc 65
      //   267: aastore
      //   268: dup
      //   269: iconst_1
      //   270: ldc 65
      //   272: aastore
      //   273: invokevirtual 125	java/lang/Class:getMethod	(Ljava/lang/String;[Ljava/lang/Class;)Ljava/lang/reflect/Method;
      //   276: aconst_null
      //   277: iconst_2
      //   278: anewarray 5	java/lang/Object
      //   281: dup
      //   282: iconst_0
      //   283: aload_2
      //   284: aastore
      //   285: dup
      //   286: iconst_1
      //   287: aload_3
      //   288: aastore
      //   289: invokevirtual 131	java/lang/reflect/Method:invoke	(Ljava/lang/Object;[Ljava/lang/Object;)Ljava/lang/Object;
      //   292: pop
      //   293: getstatic 184	o/Gz:ˎ	Lo/Gz$ˊ;
      //   296: astore_2
      //   297: aload_2
      //   298: iconst_0
      //   299: invokevirtual 189	o/Gz$ˊ:ॱ	(Z)V
      //   302: return
      //   303: goto -300 -> 3
      //   306: astore_2
      //   307: aload_2
      //   308: athrow
      //   309: iconst_4
      //   310: newarray int
      //   312: dup
      //   313: iconst_0
      //   314: ldc -94
      //   316: iastore
      //   317: dup
      //   318: iconst_1
      //   319: ldc -93
      //   321: iastore
      //   322: dup
      //   323: iconst_2
      //   324: ldc -92
      //   326: iastore
      //   327: dup
      //   328: iconst_3
      //   329: ldc -91
      //   331: iastore
      //   332: bipush 8
      //   334: invokestatic 87	o/Gz$ˏ:ˎ	([II)Ljava/lang/String;
      //   337: astore_2
      //   338: aload_2
      //   339: invokevirtual 91	java/lang/String:intern	()Ljava/lang/String;
      //   342: astore_2
      //   343: bipush 12
      //   345: newarray int
      //   347: astore_3
      //   348: aload_3
      //   349: dup
      //   350: iconst_0
      //   351: ldc -124
      //   353: iastore
      //   354: dup
      //   355: iconst_1
      //   356: ldc -123
      //   358: iastore
      //   359: dup
      //   360: iconst_2
      //   361: ldc -122
      //   363: iastore
      //   364: dup
      //   365: iconst_3
      //   366: ldc -121
      //   368: iastore
      //   369: dup
      //   370: iconst_4
      //   371: ldc -120
      //   373: iastore
      //   374: dup
      //   375: iconst_5
      //   376: ldc -119
      //   378: iastore
      //   379: dup
      //   380: bipush 6
      //   382: ldc -66
      //   384: iastore
      //   385: dup
      //   386: bipush 7
      //   388: ldc -65
      //   390: iastore
      //   391: dup
      //   392: bipush 8
      //   394: ldc -64
      //   396: iastore
      //   397: dup
      //   398: bipush 9
      //   400: ldc -63
      //   402: iastore
      //   403: dup
      //   404: bipush 10
      //   406: ldc -62
      //   408: iastore
      //   409: dup
      //   410: bipush 11
      //   412: ldc -61
      //   414: iastore
      //   415: pop
      //   416: goto -359 -> 57
      //   419: goto -110 -> 309
      // Local variable table:
      //   start	length	slot	name	signature
      //   0	422	0	this	ˏ
      //   6	208	1	i	int
      //   109	52	2	localObject1	Object
      //   178	2	2	localIllegalArgumentException	IllegalArgumentException
      //   232	52	2	localObject2	Object
      //   296	2	2	localˊ	Gz.ˊ
      //   306	2	2	localArrayStoreException	ArrayStoreException
      //   337	6	2	str	String
      //   96	253	3	localObject3	Object
      // Exception table:
      //   from	to	target	type
      //   123	170	109	finally
      //   217	224	178	java/lang/IllegalArgumentException
      //   224	229	178	java/lang/IllegalStateException
      //   233	238	178	java/lang/IllegalStateException
      //   233	238	178	java/lang/RuntimeException
      //   242	244	178	java/lang/IllegalStateException
      //   242	244	178	java/lang/RuntimeException
      //   244	246	178	java/lang/IllegalStateException
      //   244	246	178	java/lang/RuntimeException
      //   293	297	178	java/lang/IllegalStateException
      //   297	302	178	java/lang/IllegalStateException
      //   297	302	178	java/lang/UnsupportedOperationException
      //   246	293	232	finally
      //   3	7	306	java/lang/ArrayStoreException
      //   31	39	306	java/lang/ArrayStoreException
      //   31	39	306	java/lang/NullPointerException
      //   293	297	306	java/lang/ClassCastException
      //   297	302	306	java/lang/ClassCastException
      //   309	338	306	java/lang/Exception
      //   338	416	306	java/lang/ClassCastException
    }
    
    /* Error */
    public void ˏ(Throwable paramThrowable)
    {
      // Byte code:
      //   0: goto +171 -> 171
      //   3: getstatic 20	o/Gz$ˏ:ˊ	I
      //   6: istore_2
      //   7: iload_2
      //   8: bipush 46
      //   10: iadd
      //   11: iconst_1
      //   12: isub
      //   13: istore_2
      //   14: iload_2
      //   15: sipush 128
      //   18: irem
      //   19: putstatic 22	o/Gz$ˏ:ॱ	I
      //   22: iload_2
      //   23: iconst_2
      //   24: irem
      //   25: ifne +6 -> 31
      //   28: goto +217 -> 245
      //   31: goto +427 -> 458
      //   34: astore_1
      //   35: aload_1
      //   36: athrow
      //   37: iconst_4
      //   38: newarray int
      //   40: dup
      //   41: iconst_0
      //   42: ldc -54
      //   44: iastore
      //   45: dup
      //   46: iconst_1
      //   47: ldc -53
      //   49: iastore
      //   50: dup
      //   51: iconst_2
      //   52: ldc -52
      //   54: iastore
      //   55: dup
      //   56: iconst_3
      //   57: ldc -51
      //   59: iastore
      //   60: iconst_5
      //   61: invokestatic 87	o/Gz$ˏ:ˎ	([II)Ljava/lang/String;
      //   64: astore_3
      //   65: aload_3
      //   66: invokevirtual 91	java/lang/String:intern	()Ljava/lang/String;
      //   69: astore_3
      //   70: aload_1
      //   71: aload_3
      //   72: invokestatic 96	o/vq:ˎ	(Ljava/lang/Object;Ljava/lang/String;)V
      //   75: iconst_4
      //   76: newarray int
      //   78: astore_3
      //   79: aload_3
      //   80: dup
      //   81: iconst_0
      //   82: ldc -94
      //   84: iastore
      //   85: dup
      //   86: iconst_1
      //   87: ldc -93
      //   89: iastore
      //   90: dup
      //   91: iconst_2
      //   92: ldc -92
      //   94: iastore
      //   95: dup
      //   96: iconst_3
      //   97: ldc -91
      //   99: iastore
      //   100: pop
      //   101: bipush 8
      //   103: istore_2
      //   104: goto +294 -> 398
      //   107: aload 4
      //   109: aload 5
      //   111: bipush 10
      //   113: invokestatic 87	o/Gz$ˏ:ˎ	([II)Ljava/lang/String;
      //   116: invokevirtual 91	java/lang/String:intern	()Ljava/lang/String;
      //   119: invokevirtual 156	java/lang/StringBuilder:append	(Ljava/lang/String;)Ljava/lang/StringBuilder;
      //   122: aload_1
      //   123: invokevirtual 208	java/lang/Throwable:getMessage	()Ljava/lang/String;
      //   126: invokevirtual 156	java/lang/StringBuilder:append	(Ljava/lang/String;)Ljava/lang/StringBuilder;
      //   129: astore_1
      //   130: aconst_null
      //   131: arraylength
      //   132: istore_2
      //   133: goto +193 -> 326
      //   136: iconst_0
      //   137: istore_2
      //   138: goto +326 -> 464
      //   141: aload 5
      //   143: bipush 10
      //   145: invokestatic 87	o/Gz$ˏ:ˎ	([II)Ljava/lang/String;
      //   148: astore 5
      //   150: aload 4
      //   152: aload 5
      //   154: invokevirtual 91	java/lang/String:intern	()Ljava/lang/String;
      //   157: invokevirtual 156	java/lang/StringBuilder:append	(Ljava/lang/String;)Ljava/lang/StringBuilder;
      //   160: aload_1
      //   161: invokevirtual 208	java/lang/Throwable:getMessage	()Ljava/lang/String;
      //   164: invokevirtual 156	java/lang/StringBuilder:append	(Ljava/lang/String;)Ljava/lang/StringBuilder;
      //   167: astore_1
      //   168: goto +158 -> 326
      //   171: goto -168 -> 3
      //   174: iconst_1
      //   175: istore_2
      //   176: goto +288 -> 464
      //   179: aload_1
      //   180: iconst_4
      //   181: newarray int
      //   183: dup
      //   184: iconst_0
      //   185: ldc -54
      //   187: iastore
      //   188: dup
      //   189: iconst_1
      //   190: ldc -53
      //   192: iastore
      //   193: dup
      //   194: iconst_2
      //   195: ldc -52
      //   197: iastore
      //   198: dup
      //   199: iconst_3
      //   200: ldc -51
      //   202: iastore
      //   203: iconst_2
      //   204: invokestatic 87	o/Gz$ˏ:ˎ	([II)Ljava/lang/String;
      //   207: invokevirtual 91	java/lang/String:intern	()Ljava/lang/String;
      //   210: invokestatic 96	o/vq:ˎ	(Ljava/lang/Object;Ljava/lang/String;)V
      //   213: iconst_4
      //   214: newarray int
      //   216: astore_3
      //   217: aload_3
      //   218: dup
      //   219: iconst_0
      //   220: ldc -94
      //   222: iastore
      //   223: dup
      //   224: iconst_1
      //   225: ldc -93
      //   227: iastore
      //   228: dup
      //   229: iconst_2
      //   230: ldc -92
      //   232: iastore
      //   233: dup
      //   234: iconst_3
      //   235: ldc -91
      //   237: iastore
      //   238: pop
      //   239: bipush 81
      //   241: istore_2
      //   242: goto +156 -> 398
      //   245: bipush 92
      //   247: istore_2
      //   248: goto +46 -> 294
      //   251: getstatic 22	o/Gz$ˏ:ॱ	I
      //   254: istore_2
      //   255: iload_2
      //   256: bipush 83
      //   258: iand
      //   259: iload_2
      //   260: bipush 83
      //   262: iand
      //   263: iload_2
      //   264: bipush 83
      //   266: ixor
      //   267: ior
      //   268: iconst_m1
      //   269: ixor
      //   270: isub
      //   271: iconst_1
      //   272: isub
      //   273: istore_2
      //   274: iload_2
      //   275: sipush 128
      //   278: irem
      //   279: putstatic 20	o/Gz$ˏ:ˊ	I
      //   282: iload_2
      //   283: iconst_2
      //   284: irem
      //   285: ifeq +6 -> 291
      //   288: goto -152 -> 136
      //   291: goto -117 -> 174
      //   294: iload_2
      //   295: lookupswitch	default:+25->320, 90:+-258->37, 92:+-116->179
      //   320: goto -141 -> 179
      //   323: astore_1
      //   324: aload_1
      //   325: athrow
      //   326: aload_1
      //   327: invokevirtual 105	java/lang/StringBuilder:toString	()Ljava/lang/String;
      //   330: astore_1
      //   331: goto +17 -> 348
      //   334: astore_1
      //   335: aload_1
      //   336: invokevirtual 111	java/lang/Throwable:getCause	()Ljava/lang/Throwable;
      //   339: astore_3
      //   340: aload_3
      //   341: ifnull +5 -> 346
      //   344: aload_3
      //   345: athrow
      //   346: aload_1
      //   347: athrow
      //   348: iconst_4
      //   349: bipush 42
      //   351: ldc 112
      //   353: invokestatic 118	o/O:ˋ	(IIC)Ljava/lang/Object;
      //   356: checkcast 120	java/lang/Class
      //   359: ldc 121
      //   361: iconst_2
      //   362: anewarray 120	java/lang/Class
      //   365: dup
      //   366: iconst_0
      //   367: ldc 65
      //   369: aastore
      //   370: dup
      //   371: iconst_1
      //   372: ldc 65
      //   374: aastore
      //   375: invokevirtual 125	java/lang/Class:getMethod	(Ljava/lang/String;[Ljava/lang/Class;)Ljava/lang/reflect/Method;
      //   378: aconst_null
      //   379: iconst_2
      //   380: anewarray 5	java/lang/Object
      //   383: dup
      //   384: iconst_0
      //   385: aload_3
      //   386: aastore
      //   387: dup
      //   388: iconst_1
      //   389: aload_1
      //   390: aastore
      //   391: invokevirtual 131	java/lang/reflect/Method:invoke	(Ljava/lang/Object;[Ljava/lang/Object;)Ljava/lang/Object;
      //   394: pop
      //   395: goto +96 -> 491
      //   398: aload_3
      //   399: iload_2
      //   400: invokestatic 87	o/Gz$ˏ:ˎ	([II)Ljava/lang/String;
      //   403: invokevirtual 91	java/lang/String:intern	()Ljava/lang/String;
      //   406: astore_3
      //   407: new 98	java/lang/StringBuilder
      //   410: dup
      //   411: invokespecial 166	java/lang/StringBuilder:<init>	()V
      //   414: astore 4
      //   416: bipush 6
      //   418: newarray int
      //   420: astore 5
      //   422: aload 5
      //   424: dup
      //   425: iconst_0
      //   426: ldc -47
      //   428: iastore
      //   429: dup
      //   430: iconst_1
      //   431: ldc -46
      //   433: iastore
      //   434: dup
      //   435: iconst_2
      //   436: ldc -45
      //   438: iastore
      //   439: dup
      //   440: iconst_3
      //   441: ldc -44
      //   443: iastore
      //   444: dup
      //   445: iconst_4
      //   446: ldc -43
      //   448: iastore
      //   449: dup
      //   450: iconst_5
      //   451: ldc -42
      //   453: iastore
      //   454: pop
      //   455: goto -204 -> 251
      //   458: bipush 90
      //   460: istore_2
      //   461: goto -167 -> 294
      //   464: iload_2
      //   465: tableswitch	default:+23->488, 0:+-358->107, 1:+-324->141
      //   488: goto -381 -> 107
      //   491: getstatic 22	o/Gz$ˏ:ॱ	I
      //   494: istore_2
      //   495: iload_2
      //   496: bipush 119
      //   498: iand
      //   499: iload_2
      //   500: bipush 119
      //   502: ior
      //   503: iadd
      //   504: istore_2
      //   505: iload_2
      //   506: sipush 128
      //   509: irem
      //   510: putstatic 20	o/Gz$ˏ:ˊ	I
      //   513: iload_2
      //   514: iconst_2
      //   515: irem
      //   516: ifeq +6 -> 522
      //   519: goto +4 -> 523
      //   522: return
      //   523: return
      // Local variable table:
      //   start	length	slot	name	signature
      //   0	524	0	this	ˏ
      //   0	524	1	paramThrowable	Throwable
      //   6	510	2	i	int
      //   64	343	3	localObject1	Object
      //   107	308	4	localStringBuilder	StringBuilder
      //   109	314	5	localObject2	Object
      // Exception table:
      //   from	to	target	type
      //   3	7	34	java/lang/Exception
      //   14	22	34	java/lang/IllegalStateException
      //   37	65	34	java/lang/ClassCastException
      //   141	150	34	java/lang/IndexOutOfBoundsException
      //   274	282	34	java/lang/NumberFormatException
      //   37	65	323	java/lang/IndexOutOfBoundsException
      //   65	70	323	java/lang/IndexOutOfBoundsException
      //   65	70	323	java/lang/ClassCastException
      //   70	75	323	java/lang/IndexOutOfBoundsException
      //   70	75	323	java/lang/ClassCastException
      //   70	75	323	java/lang/NullPointerException
      //   75	101	323	java/lang/IndexOutOfBoundsException
      //   75	101	323	java/lang/ClassCastException
      //   75	101	323	java/lang/NullPointerException
      //   251	255	323	java/lang/IndexOutOfBoundsException
      //   348	395	334	finally
    }
  }
}
