package o;

import android.content.Context;
import ro.btrl.commons.di.module.CommonsModule;

public final class He
  implements qo<Context>
{
  private static int ˎ = 1;
  private static int ˏ = 0;
  private static long ॱ = 8769764876051659914L;
  private final CommonsModule ˊ;
  
  /* Error */
  public static Context ˊ(CommonsModule arg0)
  {
    // Byte code:
    //   0: goto +468 -> 468
    //   3: aconst_null
    //   4: arraylength
    //   5: istore_1
    //   6: aload_0
    //   7: areturn
    //   8: getstatic 20	o/He:ˎ	I
    //   11: bipush 15
    //   13: iadd
    //   14: istore_1
    //   15: iload_1
    //   16: sipush 128
    //   19: irem
    //   20: putstatic 18	o/He:ˏ	I
    //   23: iload_1
    //   24: iconst_2
    //   25: irem
    //   26: ifeq +6 -> 32
    //   29: goto +431 -> 460
    //   32: goto +389 -> 421
    //   35: aload_0
    //   36: invokevirtual 33	ro/btrl/commons/di/module/CommonsModule:ॱ	()Landroid/content/Context;
    //   39: astore_0
    //   40: bipush 60
    //   42: newarray char
    //   44: dup
    //   45: iconst_0
    //   46: ldc 34
    //   48: castore
    //   49: dup
    //   50: iconst_1
    //   51: ldc 35
    //   53: castore
    //   54: dup
    //   55: iconst_2
    //   56: ldc 36
    //   58: castore
    //   59: dup
    //   60: iconst_3
    //   61: ldc 37
    //   63: castore
    //   64: dup
    //   65: iconst_4
    //   66: ldc 38
    //   68: castore
    //   69: dup
    //   70: iconst_5
    //   71: ldc 39
    //   73: castore
    //   74: dup
    //   75: bipush 6
    //   77: ldc 40
    //   79: castore
    //   80: dup
    //   81: bipush 7
    //   83: ldc 41
    //   85: castore
    //   86: dup
    //   87: bipush 8
    //   89: ldc 42
    //   91: castore
    //   92: dup
    //   93: bipush 9
    //   95: ldc 43
    //   97: castore
    //   98: dup
    //   99: bipush 10
    //   101: ldc 44
    //   103: castore
    //   104: dup
    //   105: bipush 11
    //   107: ldc 45
    //   109: castore
    //   110: dup
    //   111: bipush 12
    //   113: ldc 46
    //   115: castore
    //   116: dup
    //   117: bipush 13
    //   119: ldc 47
    //   121: castore
    //   122: dup
    //   123: bipush 14
    //   125: ldc 48
    //   127: castore
    //   128: dup
    //   129: bipush 15
    //   131: ldc 49
    //   133: castore
    //   134: dup
    //   135: bipush 16
    //   137: ldc 50
    //   139: castore
    //   140: dup
    //   141: bipush 17
    //   143: ldc 51
    //   145: castore
    //   146: dup
    //   147: bipush 18
    //   149: ldc 52
    //   151: castore
    //   152: dup
    //   153: bipush 19
    //   155: ldc 53
    //   157: castore
    //   158: dup
    //   159: bipush 20
    //   161: ldc 54
    //   163: castore
    //   164: dup
    //   165: bipush 21
    //   167: ldc 55
    //   169: castore
    //   170: dup
    //   171: bipush 22
    //   173: ldc 56
    //   175: castore
    //   176: dup
    //   177: bipush 23
    //   179: ldc 57
    //   181: castore
    //   182: dup
    //   183: bipush 24
    //   185: ldc 58
    //   187: castore
    //   188: dup
    //   189: bipush 25
    //   191: ldc 59
    //   193: castore
    //   194: dup
    //   195: bipush 26
    //   197: ldc 60
    //   199: castore
    //   200: dup
    //   201: bipush 27
    //   203: ldc 61
    //   205: castore
    //   206: dup
    //   207: bipush 28
    //   209: ldc 62
    //   211: castore
    //   212: dup
    //   213: bipush 29
    //   215: ldc 63
    //   217: castore
    //   218: dup
    //   219: bipush 30
    //   221: ldc 64
    //   223: castore
    //   224: dup
    //   225: bipush 31
    //   227: ldc 65
    //   229: castore
    //   230: dup
    //   231: bipush 32
    //   233: ldc 66
    //   235: castore
    //   236: dup
    //   237: bipush 33
    //   239: ldc 67
    //   241: castore
    //   242: dup
    //   243: bipush 34
    //   245: ldc 68
    //   247: castore
    //   248: dup
    //   249: bipush 35
    //   251: ldc 69
    //   253: castore
    //   254: dup
    //   255: bipush 36
    //   257: ldc 70
    //   259: castore
    //   260: dup
    //   261: bipush 37
    //   263: ldc 71
    //   265: castore
    //   266: dup
    //   267: bipush 38
    //   269: ldc 72
    //   271: castore
    //   272: dup
    //   273: bipush 39
    //   275: ldc 73
    //   277: castore
    //   278: dup
    //   279: bipush 40
    //   281: ldc 74
    //   283: castore
    //   284: dup
    //   285: bipush 41
    //   287: ldc 75
    //   289: castore
    //   290: dup
    //   291: bipush 42
    //   293: ldc 76
    //   295: castore
    //   296: dup
    //   297: bipush 43
    //   299: ldc 77
    //   301: castore
    //   302: dup
    //   303: bipush 44
    //   305: ldc 78
    //   307: castore
    //   308: dup
    //   309: bipush 45
    //   311: ldc 79
    //   313: castore
    //   314: dup
    //   315: bipush 46
    //   317: ldc 80
    //   319: castore
    //   320: dup
    //   321: bipush 47
    //   323: ldc 81
    //   325: castore
    //   326: dup
    //   327: bipush 48
    //   329: ldc 82
    //   331: castore
    //   332: dup
    //   333: bipush 49
    //   335: ldc 83
    //   337: castore
    //   338: dup
    //   339: bipush 50
    //   341: ldc 84
    //   343: castore
    //   344: dup
    //   345: bipush 51
    //   347: ldc 85
    //   349: castore
    //   350: dup
    //   351: bipush 52
    //   353: ldc 86
    //   355: castore
    //   356: dup
    //   357: bipush 53
    //   359: ldc 87
    //   361: castore
    //   362: dup
    //   363: bipush 54
    //   365: ldc 88
    //   367: castore
    //   368: dup
    //   369: bipush 55
    //   371: ldc 89
    //   373: castore
    //   374: dup
    //   375: bipush 56
    //   377: ldc 90
    //   379: castore
    //   380: dup
    //   381: bipush 57
    //   383: ldc 91
    //   385: castore
    //   386: dup
    //   387: bipush 58
    //   389: ldc 92
    //   391: castore
    //   392: dup
    //   393: bipush 59
    //   395: ldc 93
    //   397: castore
    //   398: invokestatic 97	o/He:ˋ	([C)Ljava/lang/String;
    //   401: astore_2
    //   402: aload_2
    //   403: invokevirtual 103	java/lang/String:intern	()Ljava/lang/String;
    //   406: astore_2
    //   407: aload_0
    //   408: aload_2
    //   409: invokestatic 108	o/qn:ॱ	(Ljava/lang/Object;Ljava/lang/String;)Ljava/lang/Object;
    //   412: astore_0
    //   413: aload_0
    //   414: checkcast 110	android/content/Context
    //   417: astore_0
    //   418: goto -410 -> 8
    //   421: bipush 16
    //   423: istore_1
    //   424: goto +47 -> 471
    //   427: astore_0
    //   428: aload_0
    //   429: athrow
    //   430: getstatic 20	o/He:ˎ	I
    //   433: bipush 15
    //   435: iadd
    //   436: istore_1
    //   437: iload_1
    //   438: sipush 128
    //   441: irem
    //   442: putstatic 18	o/He:ˏ	I
    //   445: iload_1
    //   446: iconst_2
    //   447: irem
    //   448: ifeq +6 -> 454
    //   451: goto +52 -> 503
    //   454: goto -419 -> 35
    //   457: astore_0
    //   458: aload_0
    //   459: athrow
    //   460: bipush 94
    //   462: istore_1
    //   463: goto +8 -> 471
    //   466: aload_0
    //   467: areturn
    //   468: goto -38 -> 430
    //   471: iload_1
    //   472: lookupswitch	default:+28->500, 16:+-6->466, 94:+-469->3
    //   500: goto -497 -> 3
    //   503: goto -468 -> 35
    // Exception table:
    //   from	to	target	type
    //   35	40	457	java/lang/Exception
    //   40	402	457	java/lang/Exception
    //   402	407	457	java/lang/Exception
    //   407	413	457	java/lang/Exception
    //   413	418	457	java/lang/Exception
  }
  
  /* Error */
  private static String ˋ(char[] paramArrayOfChar)
  {
    // Byte code:
    //   0: goto +42 -> 42
    //   3: iload_1
    //   4: aload_0
    //   5: arraylength
    //   6: if_icmpge +6 -> 12
    //   9: goto +71 -> 80
    //   12: goto +169 -> 181
    //   15: getstatic 20	o/He:ˎ	I
    //   18: bipush 91
    //   20: iadd
    //   21: istore_2
    //   22: iload_2
    //   23: sipush 128
    //   26: irem
    //   27: putstatic 18	o/He:ˏ	I
    //   30: iload_2
    //   31: iconst_2
    //   32: irem
    //   33: ifeq +6 -> 39
    //   36: goto +12 -> 48
    //   39: goto +172 -> 211
    //   42: goto +75 -> 117
    //   45: astore_0
    //   46: aload_0
    //   47: athrow
    //   48: goto +163 -> 211
    //   51: getstatic 20	o/He:ˎ	I
    //   54: bipush 57
    //   56: iadd
    //   57: istore_1
    //   58: iload_1
    //   59: sipush 128
    //   62: irem
    //   63: putstatic 18	o/He:ˏ	I
    //   66: iload_1
    //   67: iconst_2
    //   68: irem
    //   69: ifeq +6 -> 75
    //   72: goto +43 -> 115
    //   75: aload_0
    //   76: areturn
    //   77: goto -74 -> 3
    //   80: iconst_1
    //   81: istore_2
    //   82: goto +101 -> 183
    //   85: astore_0
    //   86: aload_0
    //   87: athrow
    //   88: getstatic 18	o/He:ˏ	I
    //   91: bipush 51
    //   93: iadd
    //   94: istore_2
    //   95: iload_2
    //   96: sipush 128
    //   99: irem
    //   100: putstatic 20	o/He:ˎ	I
    //   103: iload_2
    //   104: iconst_2
    //   105: irem
    //   106: ifne +6 -> 112
    //   109: goto +69 -> 178
    //   112: goto +35 -> 147
    //   115: aload_0
    //   116: areturn
    //   117: getstatic 24	o/He:ॱ	J
    //   120: aload_0
    //   121: invokestatic 115	o/oL:ˋ	(J[C)[C
    //   124: astore_0
    //   125: iconst_4
    //   126: istore_1
    //   127: goto -50 -> 77
    //   130: new 99	java/lang/String
    //   133: dup
    //   134: aload_0
    //   135: iconst_4
    //   136: aload_0
    //   137: arraylength
    //   138: iconst_4
    //   139: isub
    //   140: invokespecial 119	java/lang/String:<init>	([CII)V
    //   143: astore_0
    //   144: goto -93 -> 51
    //   147: aload_0
    //   148: iload_1
    //   149: aload_0
    //   150: iload_1
    //   151: caload
    //   152: aload_0
    //   153: iload_1
    //   154: iconst_4
    //   155: irem
    //   156: caload
    //   157: ixor
    //   158: i2l
    //   159: iload_1
    //   160: iconst_4
    //   161: isub
    //   162: i2l
    //   163: getstatic 24	o/He:ॱ	J
    //   166: lmul
    //   167: lxor
    //   168: l2i
    //   169: i2c
    //   170: castore
    //   171: iload_1
    //   172: iconst_1
    //   173: iadd
    //   174: istore_1
    //   175: goto -160 -> 15
    //   178: goto -31 -> 147
    //   181: iconst_0
    //   182: istore_2
    //   183: iload_2
    //   184: tableswitch	default:+24->208, 0:+-54->130, 1:+-96->88
    //   208: goto -78 -> 130
    //   211: goto -208 -> 3
    // Local variable table:
    //   start	length	slot	name	signature
    //   0	214	0	paramArrayOfChar	char[]
    //   3	172	1	i	int
    //   21	163	2	j	int
    // Exception table:
    //   from	to	target	type
    //   95	103	45	java/lang/Exception
    //   88	95	85	java/lang/Exception
    //   95	103	85	java/lang/Exception
  }
  
  public Context ॱ()
  {
    for (;;)
    {
      Context localContext = (Context)qn.ॱ(this.ˊ.ॱ(), ˋ(new char[] { 28660, 28599, -17966, 1337, 12087, -30436, -25104, 22093, -21505, 15697, -17172, -25768, -29822, -23145, 2908, -23184, -18015, -27109, 6575, -20337, -22661, -32641, 6105, 17076, -10995, 29188, 26108, 19626, -15578, 27747, 28711, 24077, -3903, 24246, 20001, 26644, -382, 18591, 23669, 31315, -4931, 15015, -21932, 1482, 6759, 14195, -18277, 6061, 2169, 8466, -18715, 8671, 13860, 4979, -31532, 13303, 9163, 3523, -27842, 15662 }).intern());
      break label439;
      return localContext;
      throw new NullPointerException();
      int i = 29;
      break label403;
      break label469;
      for (;;)
      {
        label403:
        switch (i)
        {
        }
        return localContext;
        label434:
        i = 4;
      }
      label439:
      label469:
      do
      {
        try
        {
          i = ˎ + 57;
          ˏ = i % 128;
          if (i % 2 != 0) {
            break label434;
          }
        }
        catch (Exception localException)
        {
          throw localException;
        }
        break;
        i = ˎ + 109;
        ˏ = i % 128;
      } while (i % 2 != 0);
    }
  }
}
