package o;

import java.io.UnsupportedEncodingException;

@Deprecated
public class Hh
  implements Fi
{
  private static int ʽ;
  private static boolean ˊ;
  private static byte ˋ;
  private static char[] ˎ;
  private static boolean ˏ;
  private static int ॱ;
  private static int ᐝ;
  
  static
  {
    break label31;
    return;
    for (;;)
    {
      i = ʽ + 35;
      ᐝ = i % 128;
      if (i % 2 != 0) {
        break;
      }
      break label84;
      label31:
      ᐝ = 0;
      ʽ = 1;
      ॱ();
      ˋ = -102;
    }
    label84:
    for (int i = 44;; i = 78)
    {
      switch (i)
      {
      }
      i = null.length;
      return;
    }
  }
  
  public Hh() {}
  
  private static String ˋ(byte[] paramArrayOfByte, int[] paramArrayOfInt, char[] paramArrayOfChar, int paramInt)
  {
    break label503;
    char[] arrayOfChar;
    int j;
    int m;
    label40:
    label45:
    label76:
    for (;;)
    {
      paramArrayOfByte[i] = ((char)(arrayOfChar[(paramArrayOfChar[(j - 1 - i)] - paramInt)] - m));
      i += 1;
      break;
      i = 0;
      break label477;
      for (;;)
      {
        break;
        return paramArrayOfByte;
        i = paramArrayOfByte.length;
        j = i;
        paramArrayOfInt = new char[i];
        i = 0;
      }
      paramArrayOfByte = new String(paramArrayOfByte);
      break label196;
    }
    label79:
    int k = 0;
    break label345;
    int i = ʽ + 25;
    ᐝ = i % 128;
    if (i % 2 == 0) {
      break label326;
    }
    label115:
    while (i >= j)
    {
      break label455;
      i = paramArrayOfChar.length;
      j = i;
      paramArrayOfByte = new char[i];
      i = 0;
    }
    label147:
    paramArrayOfInt[i] = ((char)(arrayOfChar[(paramArrayOfByte[(j - 1 - i)] + paramInt)] - m));
    i += 1;
    break label298;
    label178:
    if (!ˊ)
    {
      break label402;
      label196:
      do
      {
        paramInt = 36;
        break;
        paramInt = ʽ + 63;
        ᐝ = paramInt % 128;
      } while (paramInt % 2 != 0);
      break label301;
      switch (paramInt)
      {
      case 42: 
      default: 
        label223:
        return paramArrayOfByte;
      }
      paramInt = null.length;
      return paramArrayOfByte;
    }
    for (;;)
    {
      return new String(paramArrayOfInt);
      label268:
      k = ʽ + 67;
      ᐝ = k % 128;
      if (k % 2 != 0) {
        break label76;
      }
      break;
      label298:
      break label461;
      label301:
      paramInt = 42;
      break label223;
      i = paramArrayOfByte.length;
      j = i;
      paramArrayOfInt = new char[i];
      i = 1;
      break label40;
      label326:
      i = paramArrayOfChar.length;
      j = i;
      paramArrayOfByte = new char[i];
      i = 0;
      break label115;
      break label79;
      for (;;)
      {
        label345:
        switch (k)
        {
        }
        break label268;
        paramArrayOfByte[i] = ((char)(arrayOfChar[(paramArrayOfInt[(k - 1 - i)] - paramInt)] - m));
        i += 1;
        break label506;
        label402:
        k = paramArrayOfInt.length;
        paramArrayOfByte = new char[k];
        i = 0;
        break label506;
        return new String(paramArrayOfByte);
        label426:
        arrayOfChar = ˎ;
        m = ॱ;
        if (ˏ) {
          break label519;
        }
        break label178;
        break;
        label448:
        j = 49;
        break label549;
        label455:
        k = 1;
      }
      label461:
      if (i < j) {
        break label147;
      }
    }
    for (;;)
    {
      i = 1;
      label477:
      switch (i)
      {
      }
      break label45;
      label503:
      break label426;
      label506:
      if (i < k) {
        break label448;
      }
      break label579;
      label519:
      i = ʽ + 83;
      ᐝ = i % 128;
      if (i % 2 != 0) {
        break;
      }
    }
    for (;;)
    {
      label549:
      switch (j)
      {
      }
      break;
      label579:
      j = 63;
    }
  }
  
  private String ˏ(String paramString)
  {
    break label135;
    int i = 1 / 0;
    return paramString;
    for (;;)
    {
      byte[] arrayOfByte;
      label60:
      int j;
      try
      {
        paramString = new String(arrayOfByte, ˋ(new byte[] { -119, -120, -113, -114, -115 }, null, null, 127).intern());
      }
      catch (UnsupportedEncodingException paramString)
      {
        label89:
        throw new RuntimeException(paramString);
      }
      try
      {
        j = ʽ;
        j += 75;
        ᐝ = j % 128;
        if (j % 2 != 0) {
          break label176;
        }
      }
      catch (Exception paramString)
      {
        label135:
        throw paramString;
      }
      switch (i)
      {
      case 69: 
      default: 
        break;
        do
        {
          i = 69;
          break label89;
          break label253;
          for (;;)
          {
            switch (j)
            {
            default: 
              break label196;
              j = 33;
              continue;
              j = 35;
            }
          }
          j = paramString.length;
          if (i < j) {
            break label60;
          }
          break;
          arrayOfByte[i] = ((byte)(paramString[((paramString.length + i) % 0)] | ˋ));
          i += 103;
          break label250;
          i = ʽ + 95;
          ᐝ = i % 128;
        } while (i % 2 != 0);
        break;
      case 45: 
        label176:
        label196:
        return paramString;
        for (;;)
        {
          label250:
          break;
          label253:
          paramString = paramString.getBytes(ˋ(new byte[] { -116, -120, -117, -118, -119, -119, -120, -121, -122, -123 }, null, null, 127).intern());
          arrayOfByte = new byte[paramString.length];
          i = 0;
          break;
          arrayOfByte[i] = ((byte)(paramString[(paramString.length - i - 1)] ^ ˋ));
          i += 1;
        }
        i = 45;
      }
    }
  }
  
  static void ॱ()
  {
    ˏ = true;
    ˊ = true;
    ˎ = new char[] { 90, 111, 96, 97, 158, 168, 164, 130, 141, 138, 142, 134, 170, 169, 155 };
    ॱ = 85;
  }
  
  /* Error */
  public void ˏ(android.content.Context paramContext, Fd paramFd)
  {
    // Byte code:
    //   0: goto +107 -> 107
    //   3: getstatic 101	o/Gu$ˏ:security_compromised	I
    //   6: istore_3
    //   7: getstatic 104	o/Gu$ˏ:we_detected_security_problems	I
    //   10: istore 4
    //   12: aload_1
    //   13: iload 4
    //   15: invokevirtual 110	android/content/Context:getString	(I)Ljava/lang/String;
    //   18: astore_2
    //   19: aload_2
    //   20: iconst_4
    //   21: newarray byte
    //   23: dup
    //   24: iconst_0
    //   25: ldc 111
    //   27: bastore
    //   28: dup
    //   29: iconst_1
    //   30: ldc 112
    //   32: bastore
    //   33: dup
    //   34: iconst_2
    //   35: ldc 113
    //   37: bastore
    //   38: dup
    //   39: iconst_3
    //   40: ldc 114
    //   42: bastore
    //   43: aconst_null
    //   44: aconst_null
    //   45: bipush 127
    //   47: invokestatic 58	o/Hh:ˋ	([B[I[CI)Ljava/lang/String;
    //   50: invokevirtual 62	java/lang/String:intern	()Ljava/lang/String;
    //   53: invokevirtual 118	java/lang/String:startsWith	(Ljava/lang/String;)Z
    //   56: istore 5
    //   58: iload 5
    //   60: ifeq +6 -> 66
    //   63: goto +25 -> 88
    //   66: new 120	o/IR
    //   69: dup
    //   70: aload_1
    //   71: iload_3
    //   72: aload_2
    //   73: getstatic 123	o/Gu$ˏ:uninstall_app	I
    //   76: iconst_1
    //   77: invokespecial 126	o/IR:<init>	(Landroid/content/Context;ILjava/lang/String;IZ)V
    //   80: invokevirtual 129	o/IR:ˏ	()Lo/ᐸ;
    //   83: pop
    //   84: return
    //   85: astore_1
    //   86: aload_1
    //   87: athrow
    //   88: aload_0
    //   89: aload_2
    //   90: iconst_4
    //   91: invokevirtual 132	java/lang/String:substring	(I)Ljava/lang/String;
    //   94: invokespecial 134	o/Hh:ˏ	(Ljava/lang/String;)Ljava/lang/String;
    //   97: invokevirtual 62	java/lang/String:intern	()Ljava/lang/String;
    //   100: astore_2
    //   101: goto -35 -> 66
    //   104: astore_1
    //   105: aload_1
    //   106: athrow
    //   107: goto -104 -> 3
    // Local variable table:
    //   start	length	slot	name	signature
    //   0	110	0	this	Hh
    //   0	110	1	paramContext	android.content.Context
    //   0	110	2	paramFd	Fd
    //   6	66	3	i	int
    //   10	4	4	j	int
    //   56	3	5	bool	boolean
    // Exception table:
    //   from	to	target	type
    //   3	7	85	java/lang/Exception
    //   12	19	85	java/lang/Exception
    //   7	12	104	java/lang/Exception
    //   19	58	104	java/lang/Exception
  }
}
