package o;

import com.insidesecure.hce.MatrixHCECard;
import java.io.UnsupportedEncodingException;

public class HL
  extends Ik<EQ>
{
  private static byte ˊ;
  private static int ˋ;
  private static int ˎ;
  private static long ˏ;
  private static char[] ॱ;
  private final String mCardIdentifier;
  private final Eu mPaymentCard;
  private final MatrixHCECard matrixHCECard;
  
  static
  {
    for (;;)
    {
      int i;
      switch (i)
      {
      default: 
        return;
        ˋ = 0;
        ˎ = 1;
        ˊ();
        ˊ = -102;
        i = ˎ + 31;
        ˋ = i % 128;
        if (i % 2 == 0) {
          i = 0;
        }
        break;
      case 1: 
        i = null.length;
        return;
      case 0: 
        return;
        i = 1;
      }
    }
  }
  
  public HL(Eu paramEu, MatrixHCECard paramMatrixHCECard, String paramString) {}
  
  private String ˊ(String paramString)
  {
    label257:
    label282:
    for (;;)
    {
      int i;
      byte[] arrayOfByte;
      try
      {
        i = ˎ;
        i += 121;
        try
        {
          ˋ = i % 128;
          if (i % 2 != 0) {
            continue;
          }
        }
        catch (Exception paramString)
        {
          throw paramString;
        }
        try
        {
          arrayOfByte = paramString.getBytes(ˎ(330, '\000', 10).intern());
          paramString = new byte[arrayOfByte.length];
          i = 0;
        }
        catch (UnsupportedEncodingException paramString)
        {
          int j;
          throw new RuntimeException(paramString);
        }
        switch (j)
        {
        default: 
          break label257;
          continue;
          arrayOfByte = paramString.getBytes(ˎ(4233, '\000', 3).intern());
          paramString = new byte[arrayOfByte.length];
          i = 1;
          break label282;
          switch (i)
          {
          }
          continue;
          j = arrayOfByte.length;
          if (i >= j)
          {
            continue;
            i = 2;
          }
          break;
        case 1: 
          paramString = new String(paramString, ˎ(340, '殯', 5).intern());
          continue;
          j = 0;
          continue;
          j = 1;
          continue;
          i = ˎ + 15;
          ˋ = i % 128;
          if (i % 2 == 0)
          {
            return paramString;
            i = 66;
            continue;
          }
          return paramString;
        }
      }
      catch (Exception paramString)
      {
        throw paramString;
      }
      paramString[i] = ((byte)(arrayOfByte[(arrayOfByte.length - i - 1)] ^ ˊ));
      i += 1;
    }
  }
  
  static void ˊ()
  {
    ˏ = -6054036203924359223L;
    ॱ = new char[] { 114, -2132, -4127, -6354, -8376, -10599, -23421, 21351, 19250, 17397, 31639, 29251, 27147, 25305, 6907, 4799, 2418, 266, 14952, -12925, -10805, -8940, -6865, -4958, -2828, -973, -31734, -29618, -26728, -24590, -22746, -20630, -18756, -16765, 18133, 20050, 22138, 22965, 25084, 26933, 28936, 31063, 128, 2218, 4135, 6263, 9125, 11214, 2558, -456, -6548, 77, -2131, -4105, -6360, -8444, -10615, -12577, -14824, -16863, -18843, -21069, -23079, -25331, -27327, -29545, -31576, 31998, 29817, 27716, 25482, 23517, 21265, 19235, 17259, 15094, 12929, 10783, 8797, 6551, 4522, 2553, 313, -1792, -3956, -5952, -8183, -10197, -12161, 5, -2093, -4199, -6313, -1988, 4089, 6051, 8048, 10014, 11978, 13981, 15886, 18032, 20011, 22001, 23983, 25927, 27928, 29896, 31990, -31576, -29650, -27601, -25702, -23656, -21674, -19605, -17607, -7519, -13663, -11705, -9719, -7728, -5654, -3650, -1690, 268, 2259, 4274, 6221, 8309, 10278, 16364, 18354, 20313, 22287, 24265, 26307, 28342, 30328, 32307, -31273, -29283, -27377, -8007, 6009, 3875, 2044, 16336, 13917, 11787, 9932, 24309, 22193, 19815, 17677, 32217, 30101, 27715, 25724, -25558, -27475, -29552, -31906, -17655, -19515, -21513, -23617, -9684, -11774, -13609, -15725, -1728, -3791, 67, -2136, -4128, -6337, -8444, -10615, -12577, -14824, -16863, -18843, -21069, -23079, -25339, -27301, -29543, -31513, 31993, 29751, 27716, 25476, 23444, 21268, 19253, 17199, 15016, 12992, 10756, 8723, 6593, 4581, 1468, -3463, -5514, -7516, -9505, -11496, -13496, -15430, -17482, -19480, -22469, -24506, -26471, -28425, -30453, -32463, 31077, 29115, 27095, 26133, 24135, 22152, 20214, 18082, 16232, 8262, -10364, -12332, -14519, -211, -2336, -4427, -6537, -25074, -27062, -29284, 84, -2143, -4105, -6277, -8377, -10612, -12604, -14821, -16792, -18842, -21061, -23088, -25268, -27306, -29556, -31582, 31985, 29741, 27719, 25487, 23444, 21276, 19240, 17259, 15096, 13010, 10763, 8773, 6553, 4513, 2478, 318, -1708, -3890, -5951, -8101, -10208, -12188, -14415, -16394, -18660, -20648, -22912, -24918, -26910, -29134, -31170, 32142, 30174, 27935, 25901, -6954, 4898, 2888, 921, 15346, 12851, 10851, 8880, 23216, 21195, 18707, 16764, 939, -2962, -5088, -6929, -9077, -10925, -13000, -14854, -16949, -19052, -20867, -23017, -24882, 109, -2166, -4109, -6359, -8384, -10588, -12590, -14822, -16858, -18843, -21069, -23099, -25339, -27312, -29556, 73, -2150, -4131, -6282, -8420, -10539, -12669, -14778, -16795, -18912, 27642, -25550, -31621, -29479, -19277 };
  }
  
  private static String ˎ(int paramInt1, char paramChar, int paramInt2)
  {
    break label168;
    for (;;)
    {
      label9:
      Object localObject;
      int i;
      label70:
      label97:
      label108:
      int j;
      switch (paramInt1)
      {
      default: 
        return localObject;
        for (;;)
        {
          localObject[i] = ((char)(int)(ॱ[(paramInt1 + i)] ^ i * ˏ ^ paramChar));
          i += 1;
          break label97;
          paramInt1 = ˎ + 45;
          ˋ = paramInt1 % 128;
          if (paramInt1 % 2 != 0) {
            break;
          }
          break label280;
          if (i < paramInt2) {
            break label242;
          }
          break label218;
          switch (j)
          {
          }
        }
        i = ˋ + 65;
        ˎ = i % 128;
        if (i % 2 == 0) {
          break;
        }
        break;
      case 72: 
        for (;;)
        {
          j = 1;
          break label108;
          break label135;
          localObject[i] = ((char)(int)(ॱ[(paramInt1 >>> i)] % (i | ˏ) + paramChar));
          i += 108;
          break;
          do
          {
            j = 0;
            break label108;
            return localObject;
            paramInt1 = 13;
            break label9;
            localObject = new String((char[])localObject);
            break label70;
            localObject = new char[paramInt2];
            i = 0;
            break;
            j = ˋ + 95;
            ˎ = j % 128;
          } while (j % 2 == 0);
        }
      case 13: 
        label135:
        label168:
        label218:
        label242:
        throw new NullPointerException();
        label280:
        paramInt1 = 72;
      }
    }
  }
  
  /* Error */
  private final void ˎ(MatrixHCECard paramMatrixHCECard, EQ paramEQ)
  {
    // Byte code:
    //   0: goto +9 -> 9
    //   3: bipush 60
    //   5: istore_3
    //   6: goto +408 -> 414
    //   9: goto +160 -> 169
    //   12: getstatic 434	o/HP:$EnumSwitchMapping$0	[I
    //   15: aload_1
    //   16: invokevirtual 440	com/insidesecure/hce/MatrixHCEError:ordinal	()I
    //   19: iaload
    //   20: tableswitch	default:+20->40, 1:+55->75
    //   40: goto +348 -> 388
    //   43: iconst_0
    //   44: istore_3
    //   45: goto +445 -> 490
    //   48: getstatic 24	o/HL:ˋ	I
    //   51: bipush 57
    //   53: iadd
    //   54: istore_3
    //   55: iload_3
    //   56: sipush 128
    //   59: irem
    //   60: putstatic 26	o/HL:ˎ	I
    //   63: iload_3
    //   64: iconst_2
    //   65: irem
    //   66: ifne +6 -> 72
    //   69: goto +374 -> 443
    //   72: goto -29 -> 43
    //   75: bipush 6
    //   77: ldc_w 441
    //   80: bipush 12
    //   82: invokestatic 39	o/HL:ˎ	(ICI)Ljava/lang/String;
    //   85: invokevirtual 45	java/lang/String:intern	()Ljava/lang/String;
    //   88: astore_2
    //   89: sipush 239
    //   92: iconst_0
    //   93: bipush 51
    //   95: invokestatic 39	o/HL:ˎ	(ICI)Ljava/lang/String;
    //   98: invokevirtual 45	java/lang/String:intern	()Ljava/lang/String;
    //   101: astore_1
    //   102: goto +17 -> 119
    //   105: astore_1
    //   106: aload_1
    //   107: invokevirtual 447	java/lang/Throwable:getCause	()Ljava/lang/Throwable;
    //   110: astore_2
    //   111: aload_2
    //   112: ifnull +5 -> 117
    //   115: aload_2
    //   116: athrow
    //   117: aload_1
    //   118: athrow
    //   119: iconst_4
    //   120: bipush 42
    //   122: ldc_w 448
    //   125: invokestatic 453	o/O:ˋ	(IIC)Ljava/lang/Object;
    //   128: checkcast 455	java/lang/Class
    //   131: ldc_w 456
    //   134: iconst_2
    //   135: anewarray 455	java/lang/Class
    //   138: dup
    //   139: iconst_0
    //   140: ldc 41
    //   142: aastore
    //   143: dup
    //   144: iconst_1
    //   145: ldc 41
    //   147: aastore
    //   148: invokevirtual 460	java/lang/Class:getMethod	(Ljava/lang/String;[Ljava/lang/Class;)Ljava/lang/reflect/Method;
    //   151: aconst_null
    //   152: iconst_2
    //   153: anewarray 462	java/lang/Object
    //   156: dup
    //   157: iconst_0
    //   158: aload_2
    //   159: aastore
    //   160: dup
    //   161: iconst_1
    //   162: aload_1
    //   163: aastore
    //   164: invokevirtual 468	java/lang/reflect/Method:invoke	(Ljava/lang/Object;[Ljava/lang/Object;)Ljava/lang/Object;
    //   167: pop
    //   168: return
    //   169: new 470	com/insidesecure/hce/CardDigitizingInfo
    //   172: dup
    //   173: aload_0
    //   174: getfield 67	o/HL:mPaymentCard	Lo/Eu;
    //   177: invokevirtual 475	o/Eu:ͺ	()Ljava/lang/String;
    //   180: aload_2
    //   181: invokevirtual 479	o/EQ:ˎ	()Ljava/lang/String;
    //   184: aload_2
    //   185: invokevirtual 482	o/EQ:ॱ	()Lo/Ey;
    //   188: invokevirtual 486	o/Ey:ˊ	()Ljava/lang/String;
    //   191: invokespecial 489	com/insidesecure/hce/CardDigitizingInfo:<init>	(Ljava/lang/String;Ljava/lang/String;Ljava/lang/String;)V
    //   194: astore 4
    //   196: bipush 6
    //   198: ldc_w 441
    //   201: bipush 12
    //   203: invokestatic 39	o/HL:ˎ	(ICI)Ljava/lang/String;
    //   206: invokevirtual 45	java/lang/String:intern	()Ljava/lang/String;
    //   209: astore 5
    //   211: new 491	java/lang/StringBuilder
    //   214: dup
    //   215: invokespecial 492	java/lang/StringBuilder:<init>	()V
    //   218: sipush 173
    //   221: iconst_0
    //   222: bipush 30
    //   224: invokestatic 39	o/HL:ˎ	(ICI)Ljava/lang/String;
    //   227: invokevirtual 45	java/lang/String:intern	()Ljava/lang/String;
    //   230: invokevirtual 496	java/lang/StringBuilder:append	(Ljava/lang/String;)Ljava/lang/StringBuilder;
    //   233: aload 4
    //   235: getfield 499	com/insidesecure/hce/CardDigitizingInfo:accountPanSuffix	Ljava/lang/String;
    //   238: invokevirtual 496	java/lang/StringBuilder:append	(Ljava/lang/String;)Ljava/lang/StringBuilder;
    //   241: sipush 203
    //   244: sipush 1424
    //   247: bipush 25
    //   249: invokestatic 39	o/HL:ˎ	(ICI)Ljava/lang/String;
    //   252: invokevirtual 45	java/lang/String:intern	()Ljava/lang/String;
    //   255: invokevirtual 496	java/lang/StringBuilder:append	(Ljava/lang/String;)Ljava/lang/StringBuilder;
    //   258: ldc_w 501
    //   261: invokevirtual 496	java/lang/StringBuilder:append	(Ljava/lang/String;)Ljava/lang/StringBuilder;
    //   264: aload 4
    //   266: getfield 504	com/insidesecure/hce/CardDigitizingInfo:tokenUniqueId	Ljava/lang/String;
    //   269: invokevirtual 496	java/lang/StringBuilder:append	(Ljava/lang/String;)Ljava/lang/StringBuilder;
    //   272: sipush 228
    //   275: sipush 8294
    //   278: bipush 11
    //   280: invokestatic 39	o/HL:ˎ	(ICI)Ljava/lang/String;
    //   283: invokevirtual 45	java/lang/String:intern	()Ljava/lang/String;
    //   286: invokevirtual 496	java/lang/StringBuilder:append	(Ljava/lang/String;)Ljava/lang/StringBuilder;
    //   289: aload 4
    //   291: getfield 507	com/insidesecure/hce/CardDigitizingInfo:tokenPanSuffix	Ljava/lang/String;
    //   294: invokevirtual 496	java/lang/StringBuilder:append	(Ljava/lang/String;)Ljava/lang/StringBuilder;
    //   297: invokevirtual 510	java/lang/StringBuilder:toString	()Ljava/lang/String;
    //   300: astore_2
    //   301: goto +17 -> 318
    //   304: astore_1
    //   305: aload_1
    //   306: invokevirtual 447	java/lang/Throwable:getCause	()Ljava/lang/Throwable;
    //   309: astore_2
    //   310: aload_2
    //   311: ifnull +5 -> 316
    //   314: aload_2
    //   315: athrow
    //   316: aload_1
    //   317: athrow
    //   318: iconst_4
    //   319: bipush 42
    //   321: ldc_w 448
    //   324: invokestatic 453	o/O:ˋ	(IIC)Ljava/lang/Object;
    //   327: checkcast 455	java/lang/Class
    //   330: ldc_w 456
    //   333: iconst_2
    //   334: anewarray 455	java/lang/Class
    //   337: dup
    //   338: iconst_0
    //   339: ldc 41
    //   341: aastore
    //   342: dup
    //   343: iconst_1
    //   344: ldc 41
    //   346: aastore
    //   347: invokevirtual 460	java/lang/Class:getMethod	(Ljava/lang/String;[Ljava/lang/Class;)Ljava/lang/reflect/Method;
    //   350: aconst_null
    //   351: iconst_2
    //   352: anewarray 462	java/lang/Object
    //   355: dup
    //   356: iconst_0
    //   357: aload 5
    //   359: aastore
    //   360: dup
    //   361: iconst_1
    //   362: aload_2
    //   363: aastore
    //   364: invokevirtual 468	java/lang/reflect/Method:invoke	(Ljava/lang/Object;[Ljava/lang/Object;)Ljava/lang/Object;
    //   367: pop
    //   368: aload_1
    //   369: aload 4
    //   371: invokeinterface 516 2 0
    //   376: astore_1
    //   377: aload_1
    //   378: ifnonnull +6 -> 384
    //   381: goto -378 -> 3
    //   384: goto +67 -> 451
    //   387: return
    //   388: aload_0
    //   389: new 518	o/Fg
    //   392: dup
    //   393: aload_1
    //   394: invokevirtual 440	com/insidesecure/hce/MatrixHCEError:ordinal	()I
    //   397: aload_1
    //   398: invokevirtual 521	com/insidesecure/hce/MatrixHCEError:name	()Ljava/lang/String;
    //   401: aload_1
    //   402: invokevirtual 521	com/insidesecure/hce/MatrixHCEError:name	()Ljava/lang/String;
    //   405: invokespecial 524	o/Fg:<init>	(ILjava/lang/String;Ljava/lang/String;)V
    //   408: invokevirtual 527	o/HL:ˊ	(Lo/Fg;)V
    //   411: goto +46 -> 457
    //   414: iload_3
    //   415: lookupswitch	default:+25->440, 28:+-403->12, 60:+-367->48
    //   440: goto -428 -> 12
    //   443: iconst_1
    //   444: istore_3
    //   445: goto +45 -> 490
    //   448: goto +39 -> 487
    //   451: bipush 28
    //   453: istore_3
    //   454: goto -40 -> 414
    //   457: getstatic 24	o/HL:ˋ	I
    //   460: bipush 93
    //   462: iadd
    //   463: istore_3
    //   464: iload_3
    //   465: sipush 128
    //   468: irem
    //   469: putstatic 26	o/HL:ˎ	I
    //   472: iload_3
    //   473: iconst_2
    //   474: irem
    //   475: ifne +6 -> 481
    //   478: goto +6 -> 484
    //   481: goto -94 -> 387
    //   484: goto -97 -> 387
    //   487: goto -99 -> 388
    //   490: iload_3
    //   491: tableswitch	default:+21->512, 0:+-43->448, 1:+21->512
    //   512: new 425	java/lang/NullPointerException
    //   515: dup
    //   516: invokespecial 427	java/lang/NullPointerException:<init>	()V
    //   519: athrow
    // Local variable table:
    //   start	length	slot	name	signature
    //   0	520	0	this	HL
    //   0	520	1	paramMatrixHCECard	MatrixHCECard
    //   0	520	2	paramEQ	EQ
    //   5	486	3	i	int
    //   194	176	4	localCardDigitizingInfo	com.insidesecure.hce.CardDigitizingInfo
    //   209	149	5	str	String
    // Exception table:
    //   from	to	target	type
    //   119	168	105	finally
    //   318	368	304	finally
  }
  
  /* Error */
  private final String ˏ(String paramString)
  {
    // Byte code:
    //   0: goto +216 -> 216
    //   3: astore_1
    //   4: aload_1
    //   5: athrow
    //   6: goto +341 -> 347
    //   9: bipush 6
    //   11: ldc_w 441
    //   14: bipush 12
    //   16: invokestatic 39	o/HL:ˎ	(ICI)Ljava/lang/String;
    //   19: invokevirtual 45	java/lang/String:intern	()Ljava/lang/String;
    //   22: astore_1
    //   23: bipush 51
    //   25: iconst_0
    //   26: bipush 38
    //   28: invokestatic 39	o/HL:ˎ	(ICI)Ljava/lang/String;
    //   31: invokevirtual 45	java/lang/String:intern	()Ljava/lang/String;
    //   34: astore_3
    //   35: goto +17 -> 52
    //   38: astore_1
    //   39: aload_1
    //   40: invokevirtual 447	java/lang/Throwable:getCause	()Ljava/lang/Throwable;
    //   43: astore_3
    //   44: aload_3
    //   45: ifnull +5 -> 50
    //   48: aload_3
    //   49: athrow
    //   50: aload_1
    //   51: athrow
    //   52: iconst_4
    //   53: bipush 42
    //   55: ldc_w 448
    //   58: invokestatic 453	o/O:ˋ	(IIC)Ljava/lang/Object;
    //   61: checkcast 455	java/lang/Class
    //   64: ldc_w 528
    //   67: iconst_2
    //   68: anewarray 455	java/lang/Class
    //   71: dup
    //   72: iconst_0
    //   73: ldc 41
    //   75: aastore
    //   76: dup
    //   77: iconst_1
    //   78: ldc 41
    //   80: aastore
    //   81: invokevirtual 460	java/lang/Class:getMethod	(Ljava/lang/String;[Ljava/lang/Class;)Ljava/lang/reflect/Method;
    //   84: aconst_null
    //   85: iconst_2
    //   86: anewarray 462	java/lang/Object
    //   89: dup
    //   90: iconst_0
    //   91: aload_1
    //   92: aastore
    //   93: dup
    //   94: iconst_1
    //   95: aload_3
    //   96: aastore
    //   97: invokevirtual 468	java/lang/reflect/Method:invoke	(Ljava/lang/Object;[Ljava/lang/Object;)Ljava/lang/Object;
    //   100: pop
    //   101: aload_0
    //   102: invokevirtual 532	o/HL:ʽ	()Landroid/content/Context;
    //   105: getstatic 537	o/Gu$ˏ:error_add_card_response_internal_error	I
    //   108: invokevirtual 541	android/content/Context:getString	(I)Ljava/lang/String;
    //   111: astore_3
    //   112: aload_3
    //   113: bipush 89
    //   115: iconst_0
    //   116: iconst_4
    //   117: invokestatic 39	o/HL:ˎ	(ICI)Ljava/lang/String;
    //   120: invokevirtual 45	java/lang/String:intern	()Ljava/lang/String;
    //   123: invokevirtual 545	java/lang/String:startsWith	(Ljava/lang/String;)Z
    //   126: ifeq +6 -> 132
    //   129: goto +419 -> 548
    //   132: goto +136 -> 268
    //   135: iload_2
    //   136: lookupswitch	default:+28->164, 32:+231->367, 77:+285->421
    //   164: goto +203 -> 367
    //   167: aload_1
    //   168: checkcast 547	java/lang/CharSequence
    //   171: invokestatic 553	android/text/TextUtils:isEmpty	(Ljava/lang/CharSequence;)Z
    //   174: ifeq +6 -> 180
    //   177: goto +42 -> 219
    //   180: goto +30 -> 210
    //   183: getstatic 26	o/HL:ˎ	I
    //   186: bipush 69
    //   188: iadd
    //   189: istore_2
    //   190: iload_2
    //   191: sipush 128
    //   194: irem
    //   195: putstatic 24	o/HL:ˋ	I
    //   198: iload_2
    //   199: iconst_2
    //   200: irem
    //   201: ifeq +6 -> 207
    //   204: goto +110 -> 314
    //   207: goto +52 -> 259
    //   210: bipush 77
    //   212: istore_2
    //   213: goto -78 -> 135
    //   216: goto -49 -> 167
    //   219: bipush 32
    //   221: istore_2
    //   222: goto -87 -> 135
    //   225: aload_3
    //   226: astore_1
    //   227: iload_2
    //   228: lookupswitch	default:+28->256, 88:+-45->183, 94:+119->347
    //   256: goto -73 -> 183
    //   259: bipush 96
    //   261: istore_2
    //   262: goto +55 -> 317
    //   265: goto +129 -> 394
    //   268: bipush 94
    //   270: istore_2
    //   271: goto -46 -> 225
    //   274: aload_0
    //   275: aload_3
    //   276: iconst_4
    //   277: invokevirtual 556	java/lang/String:substring	(I)Ljava/lang/String;
    //   280: invokespecial 558	o/HL:ˊ	(Ljava/lang/String;)Ljava/lang/String;
    //   283: invokevirtual 45	java/lang/String:intern	()Ljava/lang/String;
    //   286: astore_1
    //   287: bipush 41
    //   289: iconst_0
    //   290: idiv
    //   291: istore_2
    //   292: goto -286 -> 6
    //   295: aload_0
    //   296: aload_3
    //   297: iconst_4
    //   298: invokevirtual 556	java/lang/String:substring	(I)Ljava/lang/String;
    //   301: invokespecial 558	o/HL:ˊ	(Ljava/lang/String;)Ljava/lang/String;
    //   304: invokevirtual 45	java/lang/String:intern	()Ljava/lang/String;
    //   307: astore_1
    //   308: goto -302 -> 6
    //   311: goto -302 -> 9
    //   314: bipush 39
    //   316: istore_2
    //   317: iload_2
    //   318: lookupswitch	default:+26->344, 39:+-44->274, 96:+-23->295
    //   344: goto -49 -> 295
    //   347: aload_1
    //   348: bipush 93
    //   350: ldc_w 559
    //   353: bipush 50
    //   355: invokestatic 39	o/HL:ˎ	(ICI)Ljava/lang/String;
    //   358: invokevirtual 45	java/lang/String:intern	()Ljava/lang/String;
    //   361: invokestatic 561	o/vq:ˋ	(Ljava/lang/Object;Ljava/lang/String;)V
    //   364: goto -99 -> 265
    //   367: getstatic 24	o/HL:ˋ	I
    //   370: bipush 67
    //   372: iadd
    //   373: istore_2
    //   374: iload_2
    //   375: sipush 128
    //   378: irem
    //   379: putstatic 26	o/HL:ˎ	I
    //   382: iload_2
    //   383: iconst_2
    //   384: irem
    //   385: ifne +6 -> 391
    //   388: goto -77 -> 311
    //   391: goto -382 -> 9
    //   394: getstatic 26	o/HL:ˎ	I
    //   397: iconst_3
    //   398: iadd
    //   399: istore_2
    //   400: iload_2
    //   401: sipush 128
    //   404: irem
    //   405: putstatic 24	o/HL:ˋ	I
    //   408: iload_2
    //   409: iconst_2
    //   410: irem
    //   411: ifeq +5 -> 416
    //   414: aload_1
    //   415: areturn
    //   416: aload_1
    //   417: areturn
    //   418: astore_1
    //   419: aload_1
    //   420: athrow
    //   421: bipush 6
    //   423: ldc_w 441
    //   426: bipush 12
    //   428: invokestatic 39	o/HL:ˎ	(ICI)Ljava/lang/String;
    //   431: astore_3
    //   432: aload_3
    //   433: invokevirtual 45	java/lang/String:intern	()Ljava/lang/String;
    //   436: astore_3
    //   437: new 491	java/lang/StringBuilder
    //   440: dup
    //   441: invokespecial 492	java/lang/StringBuilder:<init>	()V
    //   444: astore 4
    //   446: sipush 143
    //   449: ldc_w 562
    //   452: bipush 30
    //   454: invokestatic 39	o/HL:ˎ	(ICI)Ljava/lang/String;
    //   457: astore 5
    //   459: aload 4
    //   461: aload 5
    //   463: invokevirtual 45	java/lang/String:intern	()Ljava/lang/String;
    //   466: invokevirtual 496	java/lang/StringBuilder:append	(Ljava/lang/String;)Ljava/lang/StringBuilder;
    //   469: aload_1
    //   470: invokevirtual 496	java/lang/StringBuilder:append	(Ljava/lang/String;)Ljava/lang/StringBuilder;
    //   473: invokevirtual 510	java/lang/StringBuilder:toString	()Ljava/lang/String;
    //   476: astore 4
    //   478: goto +17 -> 495
    //   481: astore_1
    //   482: aload_1
    //   483: invokevirtual 447	java/lang/Throwable:getCause	()Ljava/lang/Throwable;
    //   486: astore_3
    //   487: aload_3
    //   488: ifnull +5 -> 493
    //   491: aload_3
    //   492: athrow
    //   493: aload_1
    //   494: athrow
    //   495: iconst_4
    //   496: bipush 42
    //   498: ldc_w 448
    //   501: invokestatic 453	o/O:ˋ	(IIC)Ljava/lang/Object;
    //   504: checkcast 455	java/lang/Class
    //   507: ldc_w 528
    //   510: iconst_2
    //   511: anewarray 455	java/lang/Class
    //   514: dup
    //   515: iconst_0
    //   516: ldc 41
    //   518: aastore
    //   519: dup
    //   520: iconst_1
    //   521: ldc 41
    //   523: aastore
    //   524: invokevirtual 460	java/lang/Class:getMethod	(Ljava/lang/String;[Ljava/lang/Class;)Ljava/lang/reflect/Method;
    //   527: aconst_null
    //   528: iconst_2
    //   529: anewarray 462	java/lang/Object
    //   532: dup
    //   533: iconst_0
    //   534: aload_3
    //   535: aastore
    //   536: dup
    //   537: iconst_1
    //   538: aload 4
    //   540: aastore
    //   541: invokevirtual 468	java/lang/reflect/Method:invoke	(Ljava/lang/Object;[Ljava/lang/Object;)Ljava/lang/Object;
    //   544: pop
    //   545: goto -280 -> 265
    //   548: bipush 88
    //   550: istore_2
    //   551: goto -326 -> 225
    // Local variable table:
    //   start	length	slot	name	signature
    //   0	554	0	this	HL
    //   0	554	1	paramString	String
    //   135	416	2	i	int
    //   34	501	3	localObject1	Object
    //   444	95	4	localObject2	Object
    //   457	5	5	str	String
    // Exception table:
    //   from	to	target	type
    //   421	432	3	java/lang/Exception
    //   432	446	3	java/lang/Exception
    //   446	459	3	java/lang/Exception
    //   459	478	3	java/lang/Exception
    //   482	487	3	java/lang/Exception
    //   491	493	3	java/lang/Exception
    //   493	495	3	java/lang/Exception
    //   52	101	38	finally
    //   421	432	418	java/lang/Exception
    //   495	545	481	finally
  }
  
  /* Error */
  protected void ˏ(EQ paramEQ)
  {
    // Byte code:
    //   0: goto +266 -> 266
    //   3: return
    //   4: getstatic 24	o/HL:ˋ	I
    //   7: bipush 55
    //   9: iadd
    //   10: istore_2
    //   11: iload_2
    //   12: sipush 128
    //   15: irem
    //   16: putstatic 26	o/HL:ˎ	I
    //   19: iload_2
    //   20: iconst_2
    //   21: irem
    //   22: ifne +6 -> 28
    //   25: goto +211 -> 236
    //   28: goto +171 -> 199
    //   31: bipush 6
    //   33: ldc_w 441
    //   36: bipush 12
    //   38: invokestatic 39	o/HL:ˎ	(ICI)Ljava/lang/String;
    //   41: invokevirtual 45	java/lang/String:intern	()Ljava/lang/String;
    //   44: astore 4
    //   46: new 491	java/lang/StringBuilder
    //   49: dup
    //   50: invokespecial 492	java/lang/StringBuilder:<init>	()V
    //   53: bipush 18
    //   55: sipush 14891
    //   58: bipush 30
    //   60: invokestatic 39	o/HL:ˎ	(ICI)Ljava/lang/String;
    //   63: invokevirtual 45	java/lang/String:intern	()Ljava/lang/String;
    //   66: invokevirtual 496	java/lang/StringBuilder:append	(Ljava/lang/String;)Ljava/lang/StringBuilder;
    //   69: aload_0
    //   70: getfield 69	o/HL:matrixHCECard	Lcom/insidesecure/hce/MatrixHCECard;
    //   73: invokeinterface 569 1 0
    //   78: invokevirtual 496	java/lang/StringBuilder:append	(Ljava/lang/String;)Ljava/lang/StringBuilder;
    //   81: bipush 48
    //   83: sipush 2526
    //   86: iconst_3
    //   87: invokestatic 39	o/HL:ˎ	(ICI)Ljava/lang/String;
    //   90: invokevirtual 45	java/lang/String:intern	()Ljava/lang/String;
    //   93: invokevirtual 496	java/lang/StringBuilder:append	(Ljava/lang/String;)Ljava/lang/StringBuilder;
    //   96: aload_0
    //   97: getfield 69	o/HL:matrixHCECard	Lcom/insidesecure/hce/MatrixHCECard;
    //   100: invokeinterface 572 1 0
    //   105: invokevirtual 496	java/lang/StringBuilder:append	(Ljava/lang/String;)Ljava/lang/StringBuilder;
    //   108: invokevirtual 510	java/lang/StringBuilder:toString	()Ljava/lang/String;
    //   111: astore 5
    //   113: goto +20 -> 133
    //   116: astore_1
    //   117: aload_1
    //   118: invokevirtual 447	java/lang/Throwable:getCause	()Ljava/lang/Throwable;
    //   121: astore 4
    //   123: aload 4
    //   125: ifnull +6 -> 131
    //   128: aload 4
    //   130: athrow
    //   131: aload_1
    //   132: athrow
    //   133: iconst_4
    //   134: bipush 42
    //   136: ldc_w 448
    //   139: invokestatic 453	o/O:ˋ	(IIC)Ljava/lang/Object;
    //   142: checkcast 455	java/lang/Class
    //   145: ldc_w 573
    //   148: iconst_2
    //   149: anewarray 455	java/lang/Class
    //   152: dup
    //   153: iconst_0
    //   154: ldc 41
    //   156: aastore
    //   157: dup
    //   158: iconst_1
    //   159: ldc 41
    //   161: aastore
    //   162: invokevirtual 460	java/lang/Class:getMethod	(Ljava/lang/String;[Ljava/lang/Class;)Ljava/lang/reflect/Method;
    //   165: aconst_null
    //   166: iconst_2
    //   167: anewarray 462	java/lang/Object
    //   170: dup
    //   171: iconst_0
    //   172: aload 4
    //   174: aastore
    //   175: dup
    //   176: iconst_1
    //   177: aload 5
    //   179: aastore
    //   180: invokevirtual 468	java/lang/reflect/Method:invoke	(Ljava/lang/Object;[Ljava/lang/Object;)Ljava/lang/Object;
    //   183: pop
    //   184: aload_0
    //   185: aload_0
    //   186: getfield 69	o/HL:matrixHCECard	Lcom/insidesecure/hce/MatrixHCECard;
    //   189: aload_1
    //   190: invokespecial 575	o/HL:ˎ	(Lcom/insidesecure/hce/MatrixHCECard;Lo/EQ;)V
    //   193: goto +110 -> 303
    //   196: astore_1
    //   197: aload_1
    //   198: athrow
    //   199: iconst_0
    //   200: iconst_0
    //   201: bipush 6
    //   203: invokestatic 39	o/HL:ˎ	(ICI)Ljava/lang/String;
    //   206: astore 4
    //   208: aload 4
    //   210: invokevirtual 45	java/lang/String:intern	()Ljava/lang/String;
    //   213: astore 4
    //   215: aload_1
    //   216: aload 4
    //   218: invokestatic 50	o/vq:ˎ	(Ljava/lang/Object;Ljava/lang/String;)V
    //   221: aload_1
    //   222: invokevirtual 578	o/EQ:ˋ	()Z
    //   225: istore_3
    //   226: iload_3
    //   227: ifne +6 -> 233
    //   230: goto -199 -> 31
    //   233: goto +36 -> 269
    //   236: goto -37 -> 199
    //   239: getstatic 26	o/HL:ˎ	I
    //   242: bipush 89
    //   244: iadd
    //   245: istore_2
    //   246: iload_2
    //   247: sipush 128
    //   250: irem
    //   251: putstatic 24	o/HL:ˋ	I
    //   254: iload_2
    //   255: iconst_2
    //   256: irem
    //   257: ifeq +6 -> 263
    //   260: goto +40 -> 300
    //   263: goto -260 -> 3
    //   266: goto -262 -> 4
    //   269: aload_0
    //   270: new 518	o/Fg
    //   273: dup
    //   274: iconst_0
    //   275: aload_0
    //   276: aload_1
    //   277: invokevirtual 580	o/EQ:ˏ	()Ljava/lang/String;
    //   280: invokespecial 582	o/HL:ˏ	(Ljava/lang/String;)Ljava/lang/String;
    //   283: aload_0
    //   284: aload_1
    //   285: invokevirtual 580	o/EQ:ˏ	()Ljava/lang/String;
    //   288: invokespecial 582	o/HL:ˏ	(Ljava/lang/String;)Ljava/lang/String;
    //   291: invokespecial 524	o/Fg:<init>	(ILjava/lang/String;Ljava/lang/String;)V
    //   294: invokevirtual 527	o/HL:ˊ	(Lo/Fg;)V
    //   297: goto -58 -> 239
    //   300: goto -297 -> 3
    //   303: return
    // Local variable table:
    //   start	length	slot	name	signature
    //   0	304	0	this	HL
    //   0	304	1	paramEQ	EQ
    //   10	247	2	i	int
    //   225	2	3	bool	boolean
    //   44	173	4	localObject	Object
    //   111	67	5	str	String
    // Exception table:
    //   from	to	target	type
    //   133	184	116	finally
    //   199	208	196	java/lang/Exception
    //   208	215	196	java/lang/Exception
    //   215	221	196	java/lang/Exception
    //   221	226	196	java/lang/Exception
  }
}
