package o;

import com.insidesecure.hce.CustomNetworkOperationProvider;
import com.insidesecure.hce.CustomNetworkOperationProvider.HttpRequestMethod;
import com.insidesecure.hce.MatrixHCECard;
import java.util.HashMap;
import java.util.Map;

public final class Hq
  extends Ht
{
  private static int ʼ = 0;
  private static int ʽ = 1;
  private static long ˋ = -1715575040326953908L;
  private static char[] ˏ = { 111, 5180, 10493, 15510, 20817, 25864, 31137, -29061, -24050, -15479, -10264, -5326, -192, -28023, -22824, -17793, 19896, 25049, 29960, 2394, 7399, 80, 5182, 10487, 15506, 20825, 25871, 31137, -29061, -24050, -18804, -13685, -8399, -3085, 1983, 7245, 12295, 17587, 22818, 28024, -32265, -27260, -21933, -16646, -11587, -6322, -1269, 3992, 9328, 14392, 19705, 24776, 30019, -30239, -25184, -19852, -14847, -9532, -4388, 804, 6129, 11158, 16457, 21524, 26852, 32096, -28363, -23098, 77, 5165, 10476, 15510, 20825, 25860, 31104, -29065, -24059, -18719, -13671, -8406, -3087, 1979, 7245, 12294, 17646, 22891, 27965, -32304, -27176, -21995, 13154, 9986, 7107, 4025, 25206, 22059, 19119, -17032, -28406, -31296, -1610, -5095, -16165, 13495, 12134, 815, 30606, 27149, 24080, -19730, -22869, -26309, -29238, -7754, -11154, -14281, 15589, 5954, 2823, 32763, 21380, 18014, -17684, -20862, -32443, -2769, -5706, 114, 5161, 10473, 15505, 20821, 25871, 31164, -29091, -24050, -18742, -13673, 25242, 30426, 18971, 24161, 13230, 2035, 7031, -4960, -16174, -11240, -22418, -16959, -28413, -31115, -28107, -20748, -17778, -10431, -7396, -104, 2127, 9277, 12535, 19585, 22830, 30188, -32384, -26031, -18920, -15687, 114, 5161, 10494, 15501, 20828, 25872, 23648, 18444, 29940, 24733, 3407, 14616, 9661, -11695, -466, -5404, -26954, -31960, -20497, 23477, 8346, 13524, 2077, 7288, 29107, 17893, 22859, -20847, -32028, 99, 5177, 10475, 15504, 20831, 25873, 31149, -29082, -24023, -18744, 99, 5178, 10478 };
  private String ˊ;
  private final MatrixHCECard ˎ;
  private String ॱ;
  
  public Hq(MatrixHCECard paramMatrixHCECard)
  {
    super(ˋ(188, '⃪', 9).intern());
    this.ˎ = paramMatrixHCECard;
  }
  
  public Hq(MatrixHCECard paramMatrixHCECard, String paramString1, String paramString2)
  {
    this(paramMatrixHCECard);
    this.ˊ = paramString1;
    this.ॱ = paramString2;
  }
  
  /* Error */
  private final void ˊ(MatrixHCECard paramMatrixHCECard)
  {
    // Byte code:
    //   0: goto +190 -> 190
    //   3: iconst_1
    //   4: istore_2
    //   5: iload_2
    //   6: tableswitch	default:+22->28, 0:+81->87, 1:+120->126
    //   28: goto +98 -> 126
    //   31: astore_1
    //   32: aload_1
    //   33: athrow
    //   34: getstatic 24	o/Hq:ʼ	I
    //   37: bipush 115
    //   39: iadd
    //   40: istore_2
    //   41: iload_2
    //   42: sipush 128
    //   45: irem
    //   46: putstatic 26	o/Hq:ʽ	I
    //   49: iload_2
    //   50: iconst_2
    //   51: irem
    //   52: ifne +6 -> 58
    //   55: goto +4 -> 59
    //   58: return
    //   59: return
    //   60: getstatic 26	o/Hq:ʽ	I
    //   63: bipush 59
    //   65: iadd
    //   66: istore_2
    //   67: iload_2
    //   68: sipush 128
    //   71: irem
    //   72: putstatic 24	o/Hq:ʼ	I
    //   75: iload_2
    //   76: iconst_2
    //   77: irem
    //   78: ifeq +6 -> 84
    //   81: goto +34 -> 115
    //   84: goto -81 -> 3
    //   87: aload_1
    //   88: invokeinterface 269 1 0
    //   93: getstatic 275	com/insidesecure/hce/MatrixHCEPaymentScheme:MASTERCARD	Lcom/insidesecure/hce/MatrixHCEPaymentScheme;
    //   96: invokestatic 278	o/vq:ˊ	(Ljava/lang/Object;Ljava/lang/Object;)Z
    //   99: istore_3
    //   100: bipush 72
    //   102: iconst_0
    //   103: idiv
    //   104: istore_2
    //   105: iload_3
    //   106: ifeq +6 -> 112
    //   109: goto +38 -> 147
    //   112: goto +11 -> 123
    //   115: iconst_0
    //   116: istore_2
    //   117: goto -112 -> 5
    //   120: astore_1
    //   121: aload_1
    //   122: athrow
    //   123: goto -89 -> 34
    //   126: aload_1
    //   127: invokeinterface 269 1 0
    //   132: getstatic 275	com/insidesecure/hce/MatrixHCEPaymentScheme:MASTERCARD	Lcom/insidesecure/hce/MatrixHCEPaymentScheme;
    //   135: invokestatic 278	o/vq:ˊ	(Ljava/lang/Object;Ljava/lang/Object;)Z
    //   138: ifeq +6 -> 144
    //   141: goto +6 -> 147
    //   144: goto -21 -> 123
    //   147: sipush 168
    //   150: iconst_0
    //   151: bipush 6
    //   153: invokestatic 237	o/Hq:ˋ	(ICI)Ljava/lang/String;
    //   156: astore 4
    //   158: new 8	o/Hq$ˊ
    //   161: dup
    //   162: aload 4
    //   164: invokevirtual 243	java/lang/String:intern	()Ljava/lang/String;
    //   167: invokespecial 279	o/Hq$ˊ:<init>	(Ljava/lang/String;)V
    //   170: astore 4
    //   172: aload 4
    //   174: checkcast 281	com/insidesecure/hce/MatrixHCENetworkOperationCallback
    //   177: astore 4
    //   179: aload_1
    //   180: aload 4
    //   182: invokeinterface 285 2 0
    //   187: goto -64 -> 123
    //   190: goto -130 -> 60
    // Local variable table:
    //   start	length	slot	name	signature
    //   0	193	0	this	Hq
    //   0	193	1	paramMatrixHCECard	MatrixHCECard
    //   4	113	2	i	int
    //   99	7	3	bool	boolean
    //   156	25	4	localObject	Object
    // Exception table:
    //   from	to	target	type
    //   147	158	31	java/lang/Exception
    //   158	172	31	java/lang/Exception
    //   172	179	31	java/lang/Exception
    //   179	187	31	java/lang/Exception
    //   172	179	120	java/lang/Exception
  }
  
  private static String ˋ(int paramInt1, char paramChar, int paramInt2)
  {
    label3:
    int i;
    if (i >= paramInt2)
    {
      Object localObject = new String((char[])localObject);
      break label34;
      label25:
      i = 50;
      break label157;
      break label269;
      try
      {
        label34:
        paramInt1 = ʽ;
        paramInt1 += 81;
        i = 48;
      }
      catch (Exception localException1)
      {
        try
        {
          ʼ = paramInt1 % 128;
          if (paramInt1 % 2 != 0) {
            break label255;
          }
          return localObject;
        }
        catch (Exception localException2)
        {
          throw localException2;
        }
        localException1 = localException1;
        throw localException1;
      }
      label68:
      break label225;
    }
    for (;;)
    {
      i = ʼ + 83;
      ʽ = i % 128;
      if (i % 2 != 0)
      {
        break label68;
        i = j;
        break;
      }
      for (;;)
      {
        i = 5 / 2;
        i = j;
        break;
        i = 21;
        break label225;
        for (;;)
        {
          i = ʽ;
          i += 25;
          ʼ = i % 128;
          if (i % 2 != 0) {
            break label25;
          }
          i = 8;
          switch (i)
          {
          case 50: 
          default: 
            label157:
            break label263;
            i = j;
            break label3;
            localException2[i] = ((char)(int)(ˏ[(paramInt1 + i)] ^ i * ˋ ^ paramChar));
            j = i + 1;
          }
        }
        label225:
        switch (i)
        {
        }
      }
      label255:
      paramInt1 = 12 / 0;
      return localException2;
      label263:
      i = j;
      break;
      label269:
      char[] arrayOfChar = new char[paramInt2];
      int j = 0;
    }
  }
  
  /* Error */
  public CustomNetworkOperationProvider onPrepareCall(com.insidesecure.hce.NetworkOperationPreparationInfo paramNetworkOperationPreparationInfo)
  {
    // Byte code:
    //   0: goto +8 -> 8
    //   3: astore_1
    //   4: aload_1
    //   5: athrow
    //   6: aload_1
    //   7: areturn
    //   8: goto +60 -> 68
    //   11: iload_2
    //   12: tableswitch	default:+24->36, 0:+90->102, 1:+-6->6
    //   36: goto +66 -> 102
    //   39: getstatic 24	o/Hq:ʼ	I
    //   42: istore_2
    //   43: iload_2
    //   44: bipush 67
    //   46: iadd
    //   47: istore_2
    //   48: iload_2
    //   49: sipush 128
    //   52: irem
    //   53: putstatic 26	o/Hq:ʽ	I
    //   56: iload_2
    //   57: iconst_2
    //   58: irem
    //   59: ifne +6 -> 65
    //   62: goto +56 -> 118
    //   65: goto +45 -> 110
    //   68: bipush 127
    //   70: iconst_0
    //   71: bipush 11
    //   73: invokestatic 237	o/Hq:ˋ	(ICI)Ljava/lang/String;
    //   76: astore_3
    //   77: aload_3
    //   78: invokevirtual 243	java/lang/String:intern	()Ljava/lang/String;
    //   81: astore_3
    //   82: aload_1
    //   83: aload_3
    //   84: invokestatic 248	o/vq:ˎ	(Ljava/lang/Object;Ljava/lang/String;)V
    //   87: new 6	o/Hq$if
    //   90: dup
    //   91: aload_0
    //   92: invokespecial 293	o/Hq$if:<init>	(Lo/Hq;)V
    //   95: checkcast 295	com/insidesecure/hce/CustomNetworkOperationProvider
    //   98: astore_1
    //   99: goto -60 -> 39
    //   102: new 297	java/lang/NullPointerException
    //   105: dup
    //   106: invokespecial 299	java/lang/NullPointerException:<init>	()V
    //   109: athrow
    //   110: iconst_1
    //   111: istore_2
    //   112: goto -101 -> 11
    //   115: astore_1
    //   116: aload_1
    //   117: athrow
    //   118: iconst_0
    //   119: istore_2
    //   120: goto -109 -> 11
    // Local variable table:
    //   start	length	slot	name	signature
    //   0	123	0	this	Hq
    //   0	123	1	paramNetworkOperationPreparationInfo	com.insidesecure.hce.NetworkOperationPreparationInfo
    //   11	109	2	i	int
    //   76	8	3	str	String
    // Exception table:
    //   from	to	target	type
    //   39	43	3	java/lang/Exception
    //   68	77	3	java/lang/Exception
    //   48	56	115	java/lang/Exception
    //   77	82	115	java/lang/Exception
  }
  
  public final MatrixHCECard ˊ()
  {
    for (;;)
    {
      MatrixHCECard localMatrixHCECard;
      switch (i)
      {
      default: 
        break;
        localMatrixHCECard = this.ˎ;
        i = 14 / 0;
        break label95;
        localMatrixHCECard = this.ˎ;
        break;
      case 67: 
        label48:
        i = null.length;
        return localMatrixHCECard;
        for (;;)
        {
          i = 15;
          break;
          switch (i)
          {
          }
          break label48;
          label95:
          i = ʼ + 111;
          ʽ = i % 128;
          if (i % 2 == 0) {
            break label164;
          }
        }
      }
      return localMatrixHCECard;
      for (;;)
      {
        i = 0;
        break;
        do
        {
          i = 1;
          break;
          i = ʼ + 19;
          ʽ = i % 128;
        } while (i % 2 == 0);
      }
      label164:
      int i = 67;
    }
  }
  
  /* Error */
  public final void ˎ(MatrixHCECard paramMatrixHCECard)
  {
    // Byte code:
    //   0: goto +107 -> 107
    //   3: getstatic 24	o/Hq:ʼ	I
    //   6: bipush 53
    //   8: iadd
    //   9: istore_2
    //   10: iload_2
    //   11: sipush 128
    //   14: irem
    //   15: putstatic 26	o/Hq:ʽ	I
    //   18: iload_2
    //   19: iconst_2
    //   20: irem
    //   21: ifne +6 -> 27
    //   24: goto +100 -> 124
    //   27: goto +83 -> 110
    //   30: iload_2
    //   31: lookupswitch	default:+25->56, 45:+300->331, 64:+99->130
    //   56: goto +275 -> 331
    //   59: bipush 29
    //   61: istore_2
    //   62: goto +239 -> 301
    //   65: bipush 45
    //   67: istore_2
    //   68: goto -38 -> 30
    //   71: astore_1
    //   72: aload_1
    //   73: athrow
    //   74: bipush 62
    //   76: istore_2
    //   77: goto +224 -> 301
    //   80: getstatic 24	o/Hq:ʼ	I
    //   83: bipush 25
    //   85: iadd
    //   86: istore_2
    //   87: iload_2
    //   88: sipush 128
    //   91: irem
    //   92: putstatic 26	o/Hq:ʽ	I
    //   95: iload_2
    //   96: iconst_2
    //   97: irem
    //   98: ifne +6 -> 104
    //   101: goto +170 -> 271
    //   104: goto +23 -> 127
    //   107: goto +233 -> 340
    //   110: aload 4
    //   112: invokevirtual 304	o/HQ:ˎ	()Lcom/insidesecure/hce/MatrixHCECard;
    //   115: invokeinterface 308 1 0
    //   120: pop
    //   121: goto -41 -> 80
    //   124: goto -14 -> 110
    //   127: goto +4 -> 131
    //   130: return
    //   131: iconst_4
    //   132: sipush 230
    //   135: sipush 10024
    //   138: invokestatic 313	o/O:ˋ	(IIC)Ljava/lang/Object;
    //   141: checkcast 315	java/lang/Class
    //   144: ldc_w 316
    //   147: invokevirtual 320	java/lang/Class:getField	(Ljava/lang/String;)Ljava/lang/reflect/Field;
    //   150: aconst_null
    //   151: invokevirtual 326	java/lang/reflect/Field:get	(Ljava/lang/Object;)Ljava/lang/Object;
    //   154: astore 4
    //   156: goto +20 -> 176
    //   159: astore_1
    //   160: aload_1
    //   161: invokevirtual 332	java/lang/Throwable:getCause	()Ljava/lang/Throwable;
    //   164: astore 4
    //   166: aload 4
    //   168: ifnull +6 -> 174
    //   171: aload 4
    //   173: athrow
    //   174: aload_1
    //   175: athrow
    //   176: bipush 7
    //   178: sipush 234
    //   181: ldc_w 333
    //   184: invokestatic 313	o/O:ˋ	(IIC)Ljava/lang/Object;
    //   187: checkcast 315	java/lang/Class
    //   190: ldc_w 334
    //   193: aconst_null
    //   194: invokevirtual 338	java/lang/Class:getMethod	(Ljava/lang/String;[Ljava/lang/Class;)Ljava/lang/reflect/Method;
    //   197: aload 4
    //   199: aconst_null
    //   200: invokevirtual 344	java/lang/reflect/Method:invoke	(Ljava/lang/Object;[Ljava/lang/Object;)Ljava/lang/Object;
    //   203: astore 4
    //   205: goto +20 -> 225
    //   208: astore_1
    //   209: aload_1
    //   210: invokevirtual 332	java/lang/Throwable:getCause	()Ljava/lang/Throwable;
    //   213: astore 4
    //   215: aload 4
    //   217: ifnull +6 -> 223
    //   220: aload 4
    //   222: athrow
    //   223: aload_1
    //   224: athrow
    //   225: iconst_4
    //   226: sipush 230
    //   229: sipush 10024
    //   232: invokestatic 313	o/O:ˋ	(IIC)Ljava/lang/Object;
    //   235: checkcast 315	java/lang/Class
    //   238: ldc_w 345
    //   241: iconst_1
    //   242: anewarray 315	java/lang/Class
    //   245: dup
    //   246: iconst_0
    //   247: ldc_w 265
    //   250: aastore
    //   251: invokevirtual 338	java/lang/Class:getMethod	(Ljava/lang/String;[Ljava/lang/Class;)Ljava/lang/reflect/Method;
    //   254: aload 4
    //   256: iconst_1
    //   257: anewarray 347	java/lang/Object
    //   260: dup
    //   261: iconst_0
    //   262: aload_1
    //   263: aastore
    //   264: invokevirtual 344	java/lang/reflect/Method:invoke	(Ljava/lang/Object;[Ljava/lang/Object;)Ljava/lang/Object;
    //   267: pop
    //   268: goto +6 -> 274
    //   271: goto -144 -> 127
    //   274: getstatic 26	o/Hq:ʽ	I
    //   277: bipush 37
    //   279: iadd
    //   280: istore_2
    //   281: iload_2
    //   282: sipush 128
    //   285: irem
    //   286: putstatic 24	o/Hq:ʼ	I
    //   289: iload_2
    //   290: iconst_2
    //   291: irem
    //   292: ifeq +6 -> 298
    //   295: goto -230 -> 65
    //   298: goto +318 -> 616
    //   301: iload_2
    //   302: lookupswitch	default:+26->328, 29:+-171->131, 62:+-299->3
    //   328: goto -325 -> 3
    //   331: bipush 81
    //   333: iconst_0
    //   334: idiv
    //   335: istore_2
    //   336: return
    //   337: astore_1
    //   338: aload_1
    //   339: athrow
    //   340: aload_1
    //   341: sipush 138
    //   344: sipush 25335
    //   347: bipush 13
    //   349: invokestatic 237	o/Hq:ˋ	(ICI)Ljava/lang/String;
    //   352: invokevirtual 243	java/lang/String:intern	()Ljava/lang/String;
    //   355: invokestatic 248	o/vq:ˎ	(Ljava/lang/Object;Ljava/lang/String;)V
    //   358: aload_1
    //   359: invokestatic 350	o/HQ:ˏ	(Lcom/insidesecure/hce/MatrixHCECard;)Lo/HQ;
    //   362: astore 4
    //   364: aload_0
    //   365: aload_1
    //   366: invokespecial 352	o/Hq:ˊ	(Lcom/insidesecure/hce/MatrixHCECard;)V
    //   369: goto +20 -> 389
    //   372: astore_1
    //   373: aload_1
    //   374: invokevirtual 332	java/lang/Throwable:getCause	()Ljava/lang/Throwable;
    //   377: astore 4
    //   379: aload 4
    //   381: ifnull +6 -> 387
    //   384: aload 4
    //   386: athrow
    //   387: aload_1
    //   388: athrow
    //   389: iconst_4
    //   390: sipush 267
    //   393: sipush 14788
    //   396: invokestatic 313	o/O:ˋ	(IIC)Ljava/lang/Object;
    //   399: checkcast 315	java/lang/Class
    //   402: ldc_w 316
    //   405: aconst_null
    //   406: invokevirtual 338	java/lang/Class:getMethod	(Ljava/lang/String;[Ljava/lang/Class;)Ljava/lang/reflect/Method;
    //   409: aconst_null
    //   410: aconst_null
    //   411: invokevirtual 344	java/lang/reflect/Method:invoke	(Ljava/lang/Object;[Ljava/lang/Object;)Ljava/lang/Object;
    //   414: astore 5
    //   416: aload 4
    //   418: sipush 151
    //   421: ldc_w 353
    //   424: bipush 17
    //   426: invokestatic 237	o/Hq:ˋ	(ICI)Ljava/lang/String;
    //   429: invokevirtual 243	java/lang/String:intern	()Ljava/lang/String;
    //   432: invokestatic 355	o/vq:ˋ	(Ljava/lang/Object;Ljava/lang/String;)V
    //   435: aload 4
    //   437: invokevirtual 304	o/HQ:ˎ	()Lcom/insidesecure/hce/MatrixHCECard;
    //   440: astore 6
    //   442: goto +20 -> 462
    //   445: astore_1
    //   446: aload_1
    //   447: invokevirtual 332	java/lang/Throwable:getCause	()Ljava/lang/Throwable;
    //   450: astore 4
    //   452: aload 4
    //   454: ifnull +6 -> 460
    //   457: aload 4
    //   459: athrow
    //   460: aload_1
    //   461: athrow
    //   462: iconst_4
    //   463: sipush 267
    //   466: sipush 14788
    //   469: invokestatic 313	o/O:ˋ	(IIC)Ljava/lang/Object;
    //   472: checkcast 315	java/lang/Class
    //   475: ldc_w 356
    //   478: iconst_1
    //   479: anewarray 315	java/lang/Class
    //   482: dup
    //   483: iconst_0
    //   484: ldc_w 265
    //   487: aastore
    //   488: invokevirtual 338	java/lang/Class:getMethod	(Ljava/lang/String;[Ljava/lang/Class;)Ljava/lang/reflect/Method;
    //   491: aload 5
    //   493: iconst_1
    //   494: anewarray 347	java/lang/Object
    //   497: dup
    //   498: iconst_0
    //   499: aload 6
    //   501: aastore
    //   502: invokevirtual 344	java/lang/reflect/Method:invoke	(Ljava/lang/Object;[Ljava/lang/Object;)Ljava/lang/Object;
    //   505: pop
    //   506: goto +20 -> 526
    //   509: astore_1
    //   510: aload_1
    //   511: invokevirtual 332	java/lang/Throwable:getCause	()Ljava/lang/Throwable;
    //   514: astore 4
    //   516: aload 4
    //   518: ifnull +6 -> 524
    //   521: aload 4
    //   523: athrow
    //   524: aload_1
    //   525: athrow
    //   526: iconst_4
    //   527: sipush 267
    //   530: sipush 14788
    //   533: invokestatic 313	o/O:ˋ	(IIC)Ljava/lang/Object;
    //   536: checkcast 315	java/lang/Class
    //   539: ldc_w 316
    //   542: aconst_null
    //   543: invokevirtual 338	java/lang/Class:getMethod	(Ljava/lang/String;[Ljava/lang/Class;)Ljava/lang/reflect/Method;
    //   546: aconst_null
    //   547: aconst_null
    //   548: invokevirtual 344	java/lang/reflect/Method:invoke	(Ljava/lang/Object;[Ljava/lang/Object;)Ljava/lang/Object;
    //   551: astore 5
    //   553: goto +20 -> 573
    //   556: astore_1
    //   557: aload_1
    //   558: invokevirtual 332	java/lang/Throwable:getCause	()Ljava/lang/Throwable;
    //   561: astore 4
    //   563: aload 4
    //   565: ifnull +6 -> 571
    //   568: aload 4
    //   570: athrow
    //   571: aload_1
    //   572: athrow
    //   573: iconst_4
    //   574: sipush 267
    //   577: sipush 14788
    //   580: invokestatic 313	o/O:ˋ	(IIC)Ljava/lang/Object;
    //   583: checkcast 315	java/lang/Class
    //   586: ldc_w 358
    //   589: aconst_null
    //   590: invokevirtual 338	java/lang/Class:getMethod	(Ljava/lang/String;[Ljava/lang/Class;)Ljava/lang/reflect/Method;
    //   593: aload 5
    //   595: aconst_null
    //   596: invokevirtual 344	java/lang/reflect/Method:invoke	(Ljava/lang/Object;[Ljava/lang/Object;)Ljava/lang/Object;
    //   599: checkcast 360	java/lang/Boolean
    //   602: invokevirtual 363	java/lang/Boolean:booleanValue	()Z
    //   605: istore_3
    //   606: iload_3
    //   607: ifne +6 -> 613
    //   610: goto -536 -> 74
    //   613: goto -554 -> 59
    //   616: bipush 64
    //   618: istore_2
    //   619: goto -589 -> 30
    // Local variable table:
    //   start	length	slot	name	signature
    //   0	622	0	this	Hq
    //   0	622	1	paramMatrixHCECard	MatrixHCECard
    //   9	610	2	i	int
    //   605	2	3	bool	boolean
    //   110	459	4	localObject1	Object
    //   414	180	5	localObject2	Object
    //   440	60	6	localMatrixHCECard	MatrixHCECard
    // Exception table:
    //   from	to	target	type
    //   10	18	71	java/lang/Exception
    //   176	205	159	finally
    //   225	268	208	finally
    //   3	10	337	java/lang/Exception
    //   10	18	337	java/lang/Exception
    //   389	416	372	finally
    //   462	506	445	finally
    //   526	553	509	finally
    //   573	606	556	finally
  }
  
  /* Error */
  public void ˎ(com.insidesecure.hce.NetworkOperationPreparationInfo.NetworkOperation paramNetworkOperation, boolean paramBoolean)
  {
    // Byte code:
    //   0: goto +140 -> 140
    //   3: iconst_0
    //   4: istore_3
    //   5: goto +712 -> 717
    //   8: iconst_1
    //   9: istore_3
    //   10: goto +87 -> 97
    //   13: getstatic 26	o/Hq:ʽ	I
    //   16: bipush 47
    //   18: iadd
    //   19: istore_3
    //   20: iload_3
    //   21: sipush 128
    //   24: irem
    //   25: putstatic 24	o/Hq:ʼ	I
    //   28: iload_3
    //   29: iconst_2
    //   30: irem
    //   31: ifeq +6 -> 37
    //   34: goto +451 -> 485
    //   37: goto +30 -> 67
    //   40: iload_3
    //   41: tableswitch	default:+23->64, 0:+-33->8, 1:+416->457
    //   64: goto +393 -> 457
    //   67: aload_0
    //   68: aload_0
    //   69: getfield 253	o/Hq:ˎ	Lcom/insidesecure/hce/MatrixHCECard;
    //   72: invokevirtual 366	o/Hq:ˎ	(Lcom/insidesecure/hce/MatrixHCECard;)V
    //   75: goto +9 -> 84
    //   78: iconst_0
    //   79: istore 4
    //   81: goto +26 -> 107
    //   84: goto +400 -> 484
    //   87: iload_3
    //   88: ifne +6 -> 94
    //   91: goto +412 -> 503
    //   94: goto +390 -> 484
    //   97: iload_2
    //   98: ifeq +6 -> 104
    //   101: goto +605 -> 706
    //   104: goto -26 -> 78
    //   107: iload 4
    //   109: tableswitch	default:+23->132, 0:+-22->87, 1:+70->179
    //   132: goto -45 -> 87
    //   135: iconst_0
    //   136: istore_3
    //   137: goto -40 -> 97
    //   140: aload_1
    //   141: iconst_0
    //   142: iconst_0
    //   143: bipush 9
    //   145: invokestatic 237	o/Hq:ˋ	(ICI)Ljava/lang/String;
    //   148: invokevirtual 243	java/lang/String:intern	()Ljava/lang/String;
    //   151: invokestatic 248	o/vq:ˎ	(Ljava/lang/Object;Ljava/lang/String;)V
    //   154: getstatic 372	com/insidesecure/hce/NetworkOperationPreparationInfo$NetworkOperation:MASTERCARD_NOTIFY_PROVISION	Lcom/insidesecure/hce/NetworkOperationPreparationInfo$NetworkOperation;
    //   157: astore 5
    //   159: getstatic 375	com/insidesecure/hce/NetworkOperationPreparationInfo$NetworkOperation:VISA_PROVISION_CONFIRM	Lcom/insidesecure/hce/NetworkOperationPreparationInfo$NetworkOperation;
    //   162: astore 6
    //   164: aload_1
    //   165: aload 5
    //   167: invokestatic 278	o/vq:ˊ	(Ljava/lang/Object;Ljava/lang/Object;)Z
    //   170: ifne +6 -> 176
    //   173: goto +513 -> 686
    //   176: goto +536 -> 712
    //   179: bipush 9
    //   181: ldc_w 376
    //   184: bipush 12
    //   186: invokestatic 237	o/Hq:ˋ	(ICI)Ljava/lang/String;
    //   189: invokevirtual 243	java/lang/String:intern	()Ljava/lang/String;
    //   192: astore 5
    //   194: bipush 21
    //   196: iconst_0
    //   197: bipush 47
    //   199: invokestatic 237	o/Hq:ˋ	(ICI)Ljava/lang/String;
    //   202: invokevirtual 243	java/lang/String:intern	()Ljava/lang/String;
    //   205: astore_1
    //   206: goto +20 -> 226
    //   209: astore 5
    //   211: aload 5
    //   213: invokevirtual 332	java/lang/Throwable:getCause	()Ljava/lang/Throwable;
    //   216: astore_1
    //   217: aload_1
    //   218: ifnull +5 -> 223
    //   221: aload_1
    //   222: athrow
    //   223: aload 5
    //   225: athrow
    //   226: iconst_4
    //   227: bipush 42
    //   229: ldc_w 377
    //   232: invokestatic 313	o/O:ˋ	(IIC)Ljava/lang/Object;
    //   235: checkcast 315	java/lang/Class
    //   238: ldc_w 316
    //   241: iconst_2
    //   242: anewarray 315	java/lang/Class
    //   245: dup
    //   246: iconst_0
    //   247: ldc -17
    //   249: aastore
    //   250: dup
    //   251: iconst_1
    //   252: ldc -17
    //   254: aastore
    //   255: invokevirtual 338	java/lang/Class:getMethod	(Ljava/lang/String;[Ljava/lang/Class;)Ljava/lang/reflect/Method;
    //   258: aconst_null
    //   259: iconst_2
    //   260: anewarray 347	java/lang/Object
    //   263: dup
    //   264: iconst_0
    //   265: aload 5
    //   267: aastore
    //   268: dup
    //   269: iconst_1
    //   270: aload_1
    //   271: aastore
    //   272: invokevirtual 344	java/lang/reflect/Method:invoke	(Ljava/lang/Object;[Ljava/lang/Object;)Ljava/lang/Object;
    //   275: pop
    //   276: aload_0
    //   277: getfield 253	o/Hq:ˎ	Lcom/insidesecure/hce/MatrixHCECard;
    //   280: astore_1
    //   281: goto +20 -> 301
    //   284: astore_1
    //   285: aload_1
    //   286: invokevirtual 332	java/lang/Throwable:getCause	()Ljava/lang/Throwable;
    //   289: astore 5
    //   291: aload 5
    //   293: ifnull +6 -> 299
    //   296: aload 5
    //   298: athrow
    //   299: aload_1
    //   300: athrow
    //   301: iconst_4
    //   302: sipush 267
    //   305: sipush 14788
    //   308: invokestatic 313	o/O:ˋ	(IIC)Ljava/lang/Object;
    //   311: checkcast 315	java/lang/Class
    //   314: ldc_w 316
    //   317: aconst_null
    //   318: invokevirtual 338	java/lang/Class:getMethod	(Ljava/lang/String;[Ljava/lang/Class;)Ljava/lang/reflect/Method;
    //   321: aconst_null
    //   322: aconst_null
    //   323: invokevirtual 344	java/lang/reflect/Method:invoke	(Ljava/lang/Object;[Ljava/lang/Object;)Ljava/lang/Object;
    //   326: astore 5
    //   328: aload 5
    //   330: bipush 68
    //   332: iconst_0
    //   333: bipush 22
    //   335: invokestatic 237	o/Hq:ˋ	(ICI)Ljava/lang/String;
    //   338: invokevirtual 243	java/lang/String:intern	()Ljava/lang/String;
    //   341: invokestatic 355	o/vq:ˋ	(Ljava/lang/Object;Ljava/lang/String;)V
    //   344: goto +20 -> 364
    //   347: astore 5
    //   349: aload 5
    //   351: invokevirtual 332	java/lang/Throwable:getCause	()Ljava/lang/Throwable;
    //   354: astore_1
    //   355: aload_1
    //   356: ifnull +5 -> 361
    //   359: aload_1
    //   360: athrow
    //   361: aload 5
    //   363: athrow
    //   364: iconst_4
    //   365: sipush 267
    //   368: sipush 14788
    //   371: invokestatic 313	o/O:ˋ	(IIC)Ljava/lang/Object;
    //   374: checkcast 315	java/lang/Class
    //   377: ldc_w 379
    //   380: aconst_null
    //   381: invokevirtual 338	java/lang/Class:getMethod	(Ljava/lang/String;[Ljava/lang/Class;)Ljava/lang/reflect/Method;
    //   384: aload 5
    //   386: aconst_null
    //   387: invokevirtual 344	java/lang/reflect/Method:invoke	(Ljava/lang/Object;[Ljava/lang/Object;)Ljava/lang/Object;
    //   390: checkcast 381	[B
    //   393: astore 5
    //   395: aload_1
    //   396: aload 5
    //   398: invokeinterface 385 2 0
    //   403: pop
    //   404: aload_0
    //   405: getfield 253	o/Hq:ˎ	Lcom/insidesecure/hce/MatrixHCECard;
    //   408: invokestatic 350	o/HQ:ˏ	(Lcom/insidesecure/hce/MatrixHCECard;)Lo/HQ;
    //   411: astore_1
    //   412: aload_1
    //   413: bipush 90
    //   415: sipush 13103
    //   418: bipush 37
    //   420: invokestatic 237	o/Hq:ˋ	(ICI)Ljava/lang/String;
    //   423: invokevirtual 243	java/lang/String:intern	()Ljava/lang/String;
    //   426: invokestatic 355	o/vq:ˋ	(Ljava/lang/Object;Ljava/lang/String;)V
    //   429: aload_1
    //   430: aload_0
    //   431: getfield 253	o/Hq:ˎ	Lcom/insidesecure/hce/MatrixHCECard;
    //   434: invokeinterface 388 1 0
    //   439: invokevirtual 390	o/HQ:ˎ	(Ljava/lang/String;)V
    //   442: iload_3
    //   443: ifne +6 -> 449
    //   446: goto -433 -> 13
    //   449: goto -365 -> 84
    //   452: iconst_1
    //   453: istore_3
    //   454: goto +263 -> 717
    //   457: getstatic 26	o/Hq:ʽ	I
    //   460: bipush 15
    //   462: iadd
    //   463: istore_3
    //   464: iload_3
    //   465: sipush 128
    //   468: irem
    //   469: putstatic 24	o/Hq:ʼ	I
    //   472: iload_3
    //   473: iconst_2
    //   474: irem
    //   475: ifeq +6 -> 481
    //   478: goto -26 -> 452
    //   481: goto -478 -> 3
    //   484: return
    //   485: goto -418 -> 67
    //   488: aload_1
    //   489: aload 6
    //   491: invokestatic 278	o/vq:ˊ	(Ljava/lang/Object;Ljava/lang/Object;)Z
    //   494: pop
    //   495: new 297	java/lang/NullPointerException
    //   498: dup
    //   499: invokespecial 299	java/lang/NullPointerException:<init>	()V
    //   502: athrow
    //   503: iconst_4
    //   504: sipush 230
    //   507: sipush 10024
    //   510: invokestatic 313	o/O:ˋ	(IIC)Ljava/lang/Object;
    //   513: checkcast 315	java/lang/Class
    //   516: ldc_w 316
    //   519: invokevirtual 320	java/lang/Class:getField	(Ljava/lang/String;)Ljava/lang/reflect/Field;
    //   522: aconst_null
    //   523: invokevirtual 326	java/lang/reflect/Field:get	(Ljava/lang/Object;)Ljava/lang/Object;
    //   526: astore_1
    //   527: goto +20 -> 547
    //   530: astore_1
    //   531: aload_1
    //   532: invokevirtual 332	java/lang/Throwable:getCause	()Ljava/lang/Throwable;
    //   535: astore 5
    //   537: aload 5
    //   539: ifnull +6 -> 545
    //   542: aload 5
    //   544: athrow
    //   545: aload_1
    //   546: athrow
    //   547: bipush 7
    //   549: sipush 234
    //   552: ldc_w 333
    //   555: invokestatic 313	o/O:ˋ	(IIC)Ljava/lang/Object;
    //   558: checkcast 315	java/lang/Class
    //   561: ldc_w 334
    //   564: aconst_null
    //   565: invokevirtual 338	java/lang/Class:getMethod	(Ljava/lang/String;[Ljava/lang/Class;)Ljava/lang/reflect/Method;
    //   568: aload_1
    //   569: aconst_null
    //   570: invokevirtual 344	java/lang/reflect/Method:invoke	(Ljava/lang/Object;[Ljava/lang/Object;)Ljava/lang/Object;
    //   573: astore_1
    //   574: iconst_4
    //   575: sipush 283
    //   578: iconst_0
    //   579: invokestatic 313	o/O:ˋ	(IIC)Ljava/lang/Object;
    //   582: checkcast 315	java/lang/Class
    //   585: ldc_w 391
    //   588: invokevirtual 320	java/lang/Class:getField	(Ljava/lang/String;)Ljava/lang/reflect/Field;
    //   591: aconst_null
    //   592: invokevirtual 326	java/lang/reflect/Field:get	(Ljava/lang/Object;)Ljava/lang/Object;
    //   595: astore 6
    //   597: aload_0
    //   598: getfield 253	o/Hq:ˎ	Lcom/insidesecure/hce/MatrixHCECard;
    //   601: astore 5
    //   603: goto +20 -> 623
    //   606: astore_1
    //   607: aload_1
    //   608: invokevirtual 332	java/lang/Throwable:getCause	()Ljava/lang/Throwable;
    //   611: astore 5
    //   613: aload 5
    //   615: ifnull +6 -> 621
    //   618: aload 5
    //   620: athrow
    //   621: aload_1
    //   622: athrow
    //   623: iconst_4
    //   624: sipush 230
    //   627: sipush 10024
    //   630: invokestatic 313	o/O:ˋ	(IIC)Ljava/lang/Object;
    //   633: checkcast 315	java/lang/Class
    //   636: ldc_w 391
    //   639: iconst_2
    //   640: anewarray 315	java/lang/Class
    //   643: dup
    //   644: iconst_0
    //   645: iconst_4
    //   646: sipush 283
    //   649: iconst_0
    //   650: invokestatic 313	o/O:ˋ	(IIC)Ljava/lang/Object;
    //   653: checkcast 315	java/lang/Class
    //   656: aastore
    //   657: dup
    //   658: iconst_1
    //   659: ldc_w 265
    //   662: aastore
    //   663: invokevirtual 338	java/lang/Class:getMethod	(Ljava/lang/String;[Ljava/lang/Class;)Ljava/lang/reflect/Method;
    //   666: aload_1
    //   667: iconst_2
    //   668: anewarray 347	java/lang/Object
    //   671: dup
    //   672: iconst_0
    //   673: aload 6
    //   675: aastore
    //   676: dup
    //   677: iconst_1
    //   678: aload 5
    //   680: aastore
    //   681: invokevirtual 344	java/lang/reflect/Method:invoke	(Ljava/lang/Object;[Ljava/lang/Object;)Ljava/lang/Object;
    //   684: pop
    //   685: return
    //   686: iconst_1
    //   687: istore_3
    //   688: goto -648 -> 40
    //   691: aload_1
    //   692: aload 6
    //   694: invokestatic 278	o/vq:ˊ	(Ljava/lang/Object;Ljava/lang/Object;)Z
    //   697: ifeq +6 -> 703
    //   700: goto -692 -> 8
    //   703: goto -568 -> 135
    //   706: iconst_1
    //   707: istore 4
    //   709: goto -602 -> 107
    //   712: iconst_0
    //   713: istore_3
    //   714: goto -674 -> 40
    //   717: iload_3
    //   718: tableswitch	default:+22->740, 0:+-27->691, 1:+-230->488
    //   740: goto -49 -> 691
    // Local variable table:
    //   start	length	slot	name	signature
    //   0	743	0	this	Hq
    //   0	743	1	paramNetworkOperation	com.insidesecure.hce.NetworkOperationPreparationInfo.NetworkOperation
    //   0	743	2	paramBoolean	boolean
    //   4	714	3	i	int
    //   79	629	4	j	int
    //   157	36	5	localObject1	Object
    //   209	57	5	localObject2	Object
    //   289	40	5	localObject3	Object
    //   347	38	5	localObject4	Object
    //   393	286	5	localObject5	Object
    //   162	531	6	localObject6	Object
    // Exception table:
    //   from	to	target	type
    //   226	276	209	finally
    //   301	328	284	finally
    //   364	395	347	finally
    //   547	574	530	finally
    //   623	685	606	finally
  }
  
  public static final class if
    implements CustomNetworkOperationProvider
  {
    private static long ˊ = 0L;
    private static char ˋ;
    private static int ˎ = 0;
    private static int ॱ = 0;
    private static int ॱॱ = 1;
    
    static
    {
      ˋ = '熮';
    }
    
    if() {}
    
    /* Error */
    private static String ˊ(char[] paramArrayOfChar1, char paramChar, char[] paramArrayOfChar2, int paramInt, char[] paramArrayOfChar3)
    {
      // Byte code:
      //   0: goto +25 -> 25
      //   3: new 46	java/lang/String
      //   6: dup
      //   7: aload 12
      //   9: invokespecial 49	java/lang/String:<init>	([C)V
      //   12: astore_0
      //   13: goto +72 -> 85
      //   16: goto +274 -> 290
      //   19: bipush 15
      //   21: istore_3
      //   22: goto +151 -> 173
      //   25: goto +346 -> 371
      //   28: astore_0
      //   29: aload_0
      //   30: athrow
      //   31: iconst_1
      //   32: istore_1
      //   33: goto +313 -> 346
      //   36: aload_0
      //   37: aload 4
      //   39: iload_1
      //   40: invokestatic 54	o/oJ:ˏ	([C[CI)V
      //   43: aload 12
      //   45: iload_1
      //   46: aload_2
      //   47: iload_1
      //   48: caload
      //   49: aload_0
      //   50: iload_1
      //   51: iconst_5
      //   52: iadd
      //   53: iconst_3
      //   54: iushr
      //   55: caload
      //   56: ixor
      //   57: i2l
      //   58: getstatic 31	o/Hq$if:ˊ	J
      //   61: lsub
      //   62: getstatic 33	o/Hq$if:ˎ	I
      //   65: i2l
      //   66: lrem
      //   67: getstatic 29	o/Hq$if:ˋ	C
      //   70: i2l
      //   71: lrem
      //   72: l2i
      //   73: i2c
      //   74: castore
      //   75: iload_1
      //   76: bipush 57
      //   78: iadd
      //   79: istore_1
      //   80: goto +157 -> 237
      //   83: aload_0
      //   84: areturn
      //   85: getstatic 27	o/Hq$if:ॱॱ	I
      //   88: bipush 17
      //   90: iadd
      //   91: istore_1
      //   92: iload_1
      //   93: sipush 128
      //   96: irem
      //   97: putstatic 25	o/Hq$if:ॱ	I
      //   100: iload_1
      //   101: iconst_2
      //   102: irem
      //   103: ifeq +6 -> 109
      //   106: goto -23 -> 83
      //   109: aload_0
      //   110: areturn
      //   111: aload_0
      //   112: aload 4
      //   114: iload_1
      //   115: invokestatic 54	o/oJ:ˏ	([C[CI)V
      //   118: aload_2
      //   119: iload_1
      //   120: caload
      //   121: aload_0
      //   122: iload_1
      //   123: iconst_3
      //   124: iadd
      //   125: iconst_4
      //   126: irem
      //   127: caload
      //   128: ixor
      //   129: i2l
      //   130: lstore 6
      //   132: getstatic 31	o/Hq$if:ˊ	J
      //   135: lstore 8
      //   137: getstatic 33	o/Hq$if:ˎ	I
      //   140: istore_3
      //   141: iload_3
      //   142: i2l
      //   143: lstore 10
      //   145: getstatic 29	o/Hq$if:ˋ	C
      //   148: istore_3
      //   149: aload 12
      //   151: iload_1
      //   152: lload 6
      //   154: lload 8
      //   156: lxor
      //   157: lload 10
      //   159: lxor
      //   160: iload_3
      //   161: i2l
      //   162: lxor
      //   163: l2i
      //   164: i2c
      //   165: castore
      //   166: iload_1
      //   167: iconst_1
      //   168: iadd
      //   169: istore_1
      //   170: goto +67 -> 237
      //   173: iload_3
      //   174: lookupswitch	default:+26->200, 15:+-171->3, 70:+86->260
      //   200: goto +60 -> 260
      //   203: iload_3
      //   204: istore_1
      //   205: goto +32 -> 237
      //   208: getstatic 25	o/Hq$if:ॱ	I
      //   211: istore_1
      //   212: iload_1
      //   213: bipush 123
      //   215: iadd
      //   216: istore_1
      //   217: iload_1
      //   218: sipush 128
      //   221: irem
      //   222: putstatic 27	o/Hq$if:ॱॱ	I
      //   225: iload_1
      //   226: iconst_2
      //   227: irem
      //   228: ifne +6 -> 234
      //   231: goto +113 -> 344
      //   234: goto -203 -> 31
      //   237: iload_1
      //   238: iload 5
      //   240: if_icmpge +6 -> 246
      //   243: goto +11 -> 254
      //   246: goto -227 -> 19
      //   249: iload_3
      //   250: istore_1
      //   251: goto -14 -> 237
      //   254: bipush 70
      //   256: istore_3
      //   257: goto -84 -> 173
      //   260: getstatic 27	o/Hq$if:ॱॱ	I
      //   263: bipush 25
      //   265: iadd
      //   266: istore_3
      //   267: iload_3
      //   268: sipush 128
      //   271: irem
      //   272: putstatic 25	o/Hq$if:ॱ	I
      //   275: iload_3
      //   276: iconst_2
      //   277: irem
      //   278: ifeq +6 -> 284
      //   281: goto -245 -> 36
      //   284: goto -173 -> 111
      //   287: astore_0
      //   288: aload_0
      //   289: athrow
      //   290: aload_0
      //   291: invokevirtual 60	[C:clone	()Ljava/lang/Object;
      //   294: checkcast 56	[C
      //   297: astore_0
      //   298: aload 4
      //   300: invokevirtual 60	[C:clone	()Ljava/lang/Object;
      //   303: checkcast 56	[C
      //   306: astore 4
      //   308: aload_0
      //   309: iconst_0
      //   310: aload_0
      //   311: iconst_0
      //   312: caload
      //   313: iload_1
      //   314: ixor
      //   315: i2c
      //   316: castore
      //   317: aload 4
      //   319: iconst_2
      //   320: aload 4
      //   322: iconst_2
      //   323: caload
      //   324: iload_3
      //   325: i2c
      //   326: iadd
      //   327: i2c
      //   328: castore
      //   329: aload_2
      //   330: arraylength
      //   331: istore 5
      //   333: iload 5
      //   335: newarray char
      //   337: astore 12
      //   339: iconst_0
      //   340: istore_3
      //   341: goto -133 -> 208
      //   344: iconst_0
      //   345: istore_1
      //   346: iload_1
      //   347: tableswitch	default:+21->368, 0:+-98->249, 1:+-144->203
      //   368: goto -119 -> 249
      //   371: getstatic 27	o/Hq$if:ॱॱ	I
      //   374: bipush 27
      //   376: iadd
      //   377: istore 5
      //   379: iload 5
      //   381: sipush 128
      //   384: irem
      //   385: putstatic 25	o/Hq$if:ॱ	I
      //   388: iload 5
      //   390: iconst_2
      //   391: irem
      //   392: ifeq +6 -> 398
      //   395: goto -379 -> 16
      //   398: goto -108 -> 290
      // Local variable table:
      //   start	length	slot	name	signature
      //   0	401	0	paramArrayOfChar1	char[]
      //   0	401	1	paramChar	char
      //   0	401	2	paramArrayOfChar2	char[]
      //   0	401	3	paramInt	int
      //   0	401	4	paramArrayOfChar3	char[]
      //   238	154	5	c	char
      //   130	23	6	l1	long
      //   135	20	8	l2	long
      //   143	15	10	l3	long
      //   7	331	12	arrayOfChar	char[]
      // Exception table:
      //   from	to	target	type
      //   132	137	28	java/lang/Exception
      //   137	141	28	java/lang/Exception
      //   145	149	28	java/lang/Exception
      //   111	118	287	java/lang/Exception
      //   208	212	287	java/lang/Exception
    }
    
    /* Error */
    public String getCustomData()
    {
      // Byte code:
      //   0: goto +993 -> 993
      //   3: aload_0
      //   4: getfield 38	o/Hq$if:ˏ	Lo/Hq;
      //   7: invokevirtual 67	o/Hq:ˊ	()Lcom/insidesecure/hce/MatrixHCECard;
      //   10: invokestatic 72	o/HQ:ˏ	(Lcom/insidesecure/hce/MatrixHCECard;)Lo/HQ;
      //   13: astore 4
      //   15: new 74	org/json/JSONObject
      //   18: dup
      //   19: invokespecial 75	org/json/JSONObject:<init>	()V
      //   22: astore_3
      //   23: iconst_4
      //   24: newarray char
      //   26: dup
      //   27: iconst_0
      //   28: ldc 76
      //   30: castore
      //   31: dup
      //   32: iconst_1
      //   33: ldc 77
      //   35: castore
      //   36: dup
      //   37: iconst_2
      //   38: ldc 78
      //   40: castore
      //   41: dup
      //   42: iconst_3
      //   43: ldc 79
      //   45: castore
      //   46: ldc 80
      //   48: bipush 6
      //   50: newarray char
      //   52: dup
      //   53: iconst_0
      //   54: ldc 81
      //   56: castore
      //   57: dup
      //   58: iconst_1
      //   59: ldc 82
      //   61: castore
      //   62: dup
      //   63: iconst_2
      //   64: ldc 83
      //   66: castore
      //   67: dup
      //   68: iconst_3
      //   69: ldc 84
      //   71: castore
      //   72: dup
      //   73: iconst_4
      //   74: ldc 85
      //   76: castore
      //   77: dup
      //   78: iconst_5
      //   79: ldc 86
      //   81: castore
      //   82: iconst_0
      //   83: iconst_4
      //   84: newarray char
      //   86: dup
      //   87: iconst_0
      //   88: ldc 87
      //   90: castore
      //   91: dup
      //   92: iconst_1
      //   93: ldc 87
      //   95: castore
      //   96: dup
      //   97: iconst_2
      //   98: ldc 87
      //   100: castore
      //   101: dup
      //   102: iconst_3
      //   103: ldc 87
      //   105: castore
      //   106: invokestatic 89	o/Hq$if:ˊ	([CC[CI[C)Ljava/lang/String;
      //   109: invokevirtual 92	java/lang/String:intern	()Ljava/lang/String;
      //   112: astore 5
      //   114: aload 4
      //   116: iconst_4
      //   117: newarray char
      //   119: dup
      //   120: iconst_0
      //   121: ldc 93
      //   123: castore
      //   124: dup
      //   125: iconst_1
      //   126: ldc 94
      //   128: castore
      //   129: dup
      //   130: iconst_2
      //   131: ldc 95
      //   133: castore
      //   134: dup
      //   135: iconst_3
      //   136: ldc 96
      //   138: castore
      //   139: ldc 97
      //   141: bipush 17
      //   143: newarray char
      //   145: dup
      //   146: iconst_0
      //   147: ldc 98
      //   149: castore
      //   150: dup
      //   151: iconst_1
      //   152: ldc 99
      //   154: castore
      //   155: dup
      //   156: iconst_2
      //   157: ldc 100
      //   159: castore
      //   160: dup
      //   161: iconst_3
      //   162: ldc 101
      //   164: castore
      //   165: dup
      //   166: iconst_4
      //   167: ldc 102
      //   169: castore
      //   170: dup
      //   171: iconst_5
      //   172: ldc 103
      //   174: castore
      //   175: dup
      //   176: bipush 6
      //   178: ldc 104
      //   180: castore
      //   181: dup
      //   182: bipush 7
      //   184: ldc 105
      //   186: castore
      //   187: dup
      //   188: bipush 8
      //   190: ldc 106
      //   192: castore
      //   193: dup
      //   194: bipush 9
      //   196: ldc 107
      //   198: castore
      //   199: dup
      //   200: bipush 10
      //   202: ldc 108
      //   204: castore
      //   205: dup
      //   206: bipush 11
      //   208: ldc 109
      //   210: castore
      //   211: dup
      //   212: bipush 12
      //   214: ldc 110
      //   216: castore
      //   217: dup
      //   218: bipush 13
      //   220: ldc 111
      //   222: castore
      //   223: dup
      //   224: bipush 14
      //   226: ldc 112
      //   228: castore
      //   229: dup
      //   230: bipush 15
      //   232: ldc 113
      //   234: castore
      //   235: dup
      //   236: bipush 16
      //   238: ldc 114
      //   240: castore
      //   241: ldc 115
      //   243: iconst_4
      //   244: newarray char
      //   246: dup
      //   247: iconst_0
      //   248: ldc 87
      //   250: castore
      //   251: dup
      //   252: iconst_1
      //   253: ldc 87
      //   255: castore
      //   256: dup
      //   257: iconst_2
      //   258: ldc 87
      //   260: castore
      //   261: dup
      //   262: iconst_3
      //   263: ldc 87
      //   265: castore
      //   266: invokestatic 89	o/Hq$if:ˊ	([CC[CI[C)Ljava/lang/String;
      //   269: invokevirtual 92	java/lang/String:intern	()Ljava/lang/String;
      //   272: invokestatic 120	o/vq:ˋ	(Ljava/lang/Object;Ljava/lang/String;)V
      //   275: aload_3
      //   276: aload 5
      //   278: aload 4
      //   280: invokevirtual 123	o/HQ:ॱˋ	()Ljava/lang/String;
      //   283: invokevirtual 127	org/json/JSONObject:put	(Ljava/lang/String;Ljava/lang/Object;)Lorg/json/JSONObject;
      //   286: pop
      //   287: aload_0
      //   288: getfield 38	o/Hq$if:ˏ	Lo/Hq;
      //   291: invokestatic 130	o/Hq:ˊ	(Lo/Hq;)Ljava/lang/String;
      //   294: checkcast 132	java/lang/CharSequence
      //   297: invokestatic 138	android/text/TextUtils:isEmpty	(Ljava/lang/CharSequence;)Z
      //   300: istore_2
      //   301: iload_2
      //   302: ifne +6 -> 308
      //   305: goto +780 -> 1085
      //   308: goto +721 -> 1029
      //   311: astore 5
      //   313: iconst_4
      //   314: newarray char
      //   316: dup
      //   317: iconst_0
      //   318: ldc -117
      //   320: castore
      //   321: dup
      //   322: iconst_1
      //   323: ldc -116
      //   325: castore
      //   326: dup
      //   327: iconst_2
      //   328: ldc -115
      //   330: castore
      //   331: dup
      //   332: iconst_3
      //   333: ldc -114
      //   335: castore
      //   336: iconst_0
      //   337: bipush 7
      //   339: newarray char
      //   341: dup
      //   342: iconst_0
      //   343: ldc -113
      //   345: castore
      //   346: dup
      //   347: iconst_1
      //   348: ldc -112
      //   350: castore
      //   351: dup
      //   352: iconst_2
      //   353: ldc -111
      //   355: castore
      //   356: dup
      //   357: iconst_3
      //   358: ldc -110
      //   360: castore
      //   361: dup
      //   362: iconst_4
      //   363: ldc -109
      //   365: castore
      //   366: dup
      //   367: iconst_5
      //   368: ldc -108
      //   370: castore
      //   371: dup
      //   372: bipush 6
      //   374: ldc -107
      //   376: castore
      //   377: ldc -106
      //   379: iconst_4
      //   380: newarray char
      //   382: dup
      //   383: iconst_0
      //   384: ldc 87
      //   386: castore
      //   387: dup
      //   388: iconst_1
      //   389: ldc 87
      //   391: castore
      //   392: dup
      //   393: iconst_2
      //   394: ldc 87
      //   396: castore
      //   397: dup
      //   398: iconst_3
      //   399: ldc 87
      //   401: castore
      //   402: invokestatic 89	o/Hq$if:ˊ	([CC[CI[C)Ljava/lang/String;
      //   405: invokevirtual 92	java/lang/String:intern	()Ljava/lang/String;
      //   408: astore 4
      //   410: aload 5
      //   412: invokevirtual 153	org/json/JSONException:getMessage	()Ljava/lang/String;
      //   415: astore 5
      //   417: goto +20 -> 437
      //   420: astore_3
      //   421: aload_3
      //   422: invokevirtual 159	java/lang/Throwable:getCause	()Ljava/lang/Throwable;
      //   425: astore 4
      //   427: aload 4
      //   429: ifnull +6 -> 435
      //   432: aload 4
      //   434: athrow
      //   435: aload_3
      //   436: athrow
      //   437: iconst_4
      //   438: bipush 42
      //   440: ldc -96
      //   442: invokestatic 165	o/O:ˋ	(IIC)Ljava/lang/Object;
      //   445: checkcast 167	java/lang/Class
      //   448: ldc -88
      //   450: iconst_2
      //   451: anewarray 167	java/lang/Class
      //   454: dup
      //   455: iconst_0
      //   456: ldc 46
      //   458: aastore
      //   459: dup
      //   460: iconst_1
      //   461: ldc 46
      //   463: aastore
      //   464: invokevirtual 172	java/lang/Class:getMethod	(Ljava/lang/String;[Ljava/lang/Class;)Ljava/lang/reflect/Method;
      //   467: aconst_null
      //   468: iconst_2
      //   469: anewarray 4	java/lang/Object
      //   472: dup
      //   473: iconst_0
      //   474: aload 4
      //   476: aastore
      //   477: dup
      //   478: iconst_1
      //   479: aload 5
      //   481: aastore
      //   482: invokevirtual 178	java/lang/reflect/Method:invoke	(Ljava/lang/Object;[Ljava/lang/Object;)Ljava/lang/Object;
      //   485: pop
      //   486: goto +68 -> 554
      //   489: iload_1
      //   490: tableswitch	default:+22->512, 0:+37->527, 1:+31->521
      //   512: goto +15 -> 527
      //   515: bipush 61
      //   517: istore_1
      //   518: goto +439 -> 957
      //   521: goto +33 -> 554
      //   524: goto +220 -> 744
      //   527: getstatic 27	o/Hq$if:ॱॱ	I
      //   530: bipush 97
      //   532: iadd
      //   533: istore_1
      //   534: iload_1
      //   535: sipush 128
      //   538: irem
      //   539: putstatic 25	o/Hq$if:ॱ	I
      //   542: iload_1
      //   543: iconst_2
      //   544: irem
      //   545: ifeq +6 -> 551
      //   548: goto +448 -> 996
      //   551: goto +483 -> 1034
      //   554: aload_3
      //   555: invokevirtual 181	org/json/JSONObject:toString	()Ljava/lang/String;
      //   558: astore_3
      //   559: aload_3
      //   560: iconst_4
      //   561: newarray char
      //   563: dup
      //   564: iconst_0
      //   565: ldc -74
      //   567: castore
      //   568: dup
      //   569: iconst_1
      //   570: ldc -73
      //   572: castore
      //   573: dup
      //   574: iconst_2
      //   575: ldc -72
      //   577: castore
      //   578: dup
      //   579: iconst_3
      //   580: ldc -71
      //   582: castore
      //   583: iconst_0
      //   584: bipush 21
      //   586: newarray char
      //   588: dup
      //   589: iconst_0
      //   590: ldc -70
      //   592: castore
      //   593: dup
      //   594: iconst_1
      //   595: ldc -69
      //   597: castore
      //   598: dup
      //   599: iconst_2
      //   600: ldc -68
      //   602: castore
      //   603: dup
      //   604: iconst_3
      //   605: ldc -67
      //   607: castore
      //   608: dup
      //   609: iconst_4
      //   610: ldc -66
      //   612: castore
      //   613: dup
      //   614: iconst_5
      //   615: ldc -65
      //   617: castore
      //   618: dup
      //   619: bipush 6
      //   621: ldc -64
      //   623: castore
      //   624: dup
      //   625: bipush 7
      //   627: ldc -63
      //   629: castore
      //   630: dup
      //   631: bipush 8
      //   633: ldc -62
      //   635: castore
      //   636: dup
      //   637: bipush 9
      //   639: ldc -61
      //   641: castore
      //   642: dup
      //   643: bipush 10
      //   645: ldc -60
      //   647: castore
      //   648: dup
      //   649: bipush 11
      //   651: ldc -59
      //   653: castore
      //   654: dup
      //   655: bipush 12
      //   657: ldc -58
      //   659: castore
      //   660: dup
      //   661: bipush 13
      //   663: ldc -57
      //   665: castore
      //   666: dup
      //   667: bipush 14
      //   669: ldc -56
      //   671: castore
      //   672: dup
      //   673: bipush 15
      //   675: ldc -55
      //   677: castore
      //   678: dup
      //   679: bipush 16
      //   681: ldc -54
      //   683: castore
      //   684: dup
      //   685: bipush 17
      //   687: ldc -53
      //   689: castore
      //   690: dup
      //   691: bipush 18
      //   693: ldc -52
      //   695: castore
      //   696: dup
      //   697: bipush 19
      //   699: ldc -51
      //   701: castore
      //   702: dup
      //   703: bipush 20
      //   705: ldc -50
      //   707: castore
      //   708: ldc -49
      //   710: iconst_4
      //   711: newarray char
      //   713: dup
      //   714: iconst_0
      //   715: ldc 87
      //   717: castore
      //   718: dup
      //   719: iconst_1
      //   720: ldc 87
      //   722: castore
      //   723: dup
      //   724: iconst_2
      //   725: ldc 87
      //   727: castore
      //   728: dup
      //   729: iconst_3
      //   730: ldc 87
      //   732: castore
      //   733: invokestatic 89	o/Hq$if:ˊ	([CC[CI[C)Ljava/lang/String;
      //   736: invokevirtual 92	java/lang/String:intern	()Ljava/lang/String;
      //   739: invokestatic 120	o/vq:ˋ	(Ljava/lang/Object;Ljava/lang/String;)V
      //   742: aload_3
      //   743: areturn
      //   744: aload_3
      //   745: iconst_4
      //   746: newarray char
      //   748: dup
      //   749: iconst_0
      //   750: ldc -48
      //   752: castore
      //   753: dup
      //   754: iconst_1
      //   755: ldc -47
      //   757: castore
      //   758: dup
      //   759: iconst_2
      //   760: ldc -46
      //   762: castore
      //   763: dup
      //   764: iconst_3
      //   765: ldc -45
      //   767: castore
      //   768: iconst_0
      //   769: bipush 10
      //   771: newarray char
      //   773: dup
      //   774: iconst_0
      //   775: ldc -44
      //   777: castore
      //   778: dup
      //   779: iconst_1
      //   780: ldc -43
      //   782: castore
      //   783: dup
      //   784: iconst_2
      //   785: ldc -42
      //   787: castore
      //   788: dup
      //   789: iconst_3
      //   790: ldc -41
      //   792: castore
      //   793: dup
      //   794: iconst_4
      //   795: ldc -40
      //   797: castore
      //   798: dup
      //   799: iconst_5
      //   800: ldc -39
      //   802: castore
      //   803: dup
      //   804: bipush 6
      //   806: ldc -38
      //   808: castore
      //   809: dup
      //   810: bipush 7
      //   812: ldc -37
      //   814: castore
      //   815: dup
      //   816: bipush 8
      //   818: ldc -36
      //   820: castore
      //   821: dup
      //   822: bipush 9
      //   824: ldc -35
      //   826: castore
      //   827: iconst_0
      //   828: iconst_4
      //   829: newarray char
      //   831: dup
      //   832: iconst_0
      //   833: ldc 87
      //   835: castore
      //   836: dup
      //   837: iconst_1
      //   838: ldc 87
      //   840: castore
      //   841: dup
      //   842: iconst_2
      //   843: ldc 87
      //   845: castore
      //   846: dup
      //   847: iconst_3
      //   848: ldc 87
      //   850: castore
      //   851: invokestatic 89	o/Hq$if:ˊ	([CC[CI[C)Ljava/lang/String;
      //   854: invokevirtual 92	java/lang/String:intern	()Ljava/lang/String;
      //   857: aload_0
      //   858: getfield 38	o/Hq$if:ˏ	Lo/Hq;
      //   861: invokestatic 130	o/Hq:ˊ	(Lo/Hq;)Ljava/lang/String;
      //   864: invokevirtual 127	org/json/JSONObject:put	(Ljava/lang/String;Ljava/lang/Object;)Lorg/json/JSONObject;
      //   867: pop
      //   868: aload_3
      //   869: iconst_4
      //   870: newarray char
      //   872: dup
      //   873: iconst_0
      //   874: ldc -34
      //   876: castore
      //   877: dup
      //   878: iconst_1
      //   879: ldc -33
      //   881: castore
      //   882: dup
      //   883: iconst_2
      //   884: ldc -32
      //   886: castore
      //   887: dup
      //   888: iconst_3
      //   889: ldc -31
      //   891: castore
      //   892: ldc -30
      //   894: iconst_3
      //   895: newarray char
      //   897: dup
      //   898: iconst_0
      //   899: ldc -29
      //   901: castore
      //   902: dup
      //   903: iconst_1
      //   904: ldc -28
      //   906: castore
      //   907: dup
      //   908: iconst_2
      //   909: ldc -27
      //   911: castore
      //   912: ldc -26
      //   914: iconst_4
      //   915: newarray char
      //   917: dup
      //   918: iconst_0
      //   919: ldc 87
      //   921: castore
      //   922: dup
      //   923: iconst_1
      //   924: ldc 87
      //   926: castore
      //   927: dup
      //   928: iconst_2
      //   929: ldc 87
      //   931: castore
      //   932: dup
      //   933: iconst_3
      //   934: ldc 87
      //   936: castore
      //   937: invokestatic 89	o/Hq$if:ˊ	([CC[CI[C)Ljava/lang/String;
      //   940: invokevirtual 92	java/lang/String:intern	()Ljava/lang/String;
      //   943: aload_0
      //   944: getfield 38	o/Hq$if:ˏ	Lo/Hq;
      //   947: invokestatic 232	o/Hq:ˎ	(Lo/Hq;)Ljava/lang/String;
      //   950: invokevirtual 127	org/json/JSONObject:put	(Ljava/lang/String;Ljava/lang/Object;)Lorg/json/JSONObject;
      //   953: pop
      //   954: goto +48 -> 1002
      //   957: iload_1
      //   958: lookupswitch	default:+26->984, 61:+100->1058, 92:+-437->521
      //   984: goto -463 -> 521
      //   987: bipush 92
      //   989: istore_1
      //   990: goto -33 -> 957
      //   993: goto -990 -> 3
      //   996: goto +38 -> 1034
      //   999: goto -478 -> 521
      //   1002: getstatic 27	o/Hq$if:ॱॱ	I
      //   1005: bipush 95
      //   1007: iadd
      //   1008: istore_1
      //   1009: iload_1
      //   1010: sipush 128
      //   1013: irem
      //   1014: putstatic 25	o/Hq$if:ॱ	I
      //   1017: iload_1
      //   1018: iconst_2
      //   1019: irem
      //   1020: ifeq +6 -> 1026
      //   1023: goto -24 -> 999
      //   1026: goto -27 -> 999
      //   1029: iconst_1
      //   1030: istore_1
      //   1031: goto -542 -> 489
      //   1034: aload_0
      //   1035: getfield 38	o/Hq$if:ˏ	Lo/Hq;
      //   1038: invokestatic 232	o/Hq:ˎ	(Lo/Hq;)Ljava/lang/String;
      //   1041: checkcast 132	java/lang/CharSequence
      //   1044: invokestatic 138	android/text/TextUtils:isEmpty	(Ljava/lang/CharSequence;)Z
      //   1047: istore_2
      //   1048: iload_2
      //   1049: ifne +6 -> 1055
      //   1052: goto -537 -> 515
      //   1055: goto -68 -> 987
      //   1058: getstatic 27	o/Hq$if:ॱॱ	I
      //   1061: bipush 111
      //   1063: iadd
      //   1064: istore_1
      //   1065: iload_1
      //   1066: sipush 128
      //   1069: irem
      //   1070: putstatic 25	o/Hq$if:ॱ	I
      //   1073: iload_1
      //   1074: iconst_2
      //   1075: irem
      //   1076: ifeq +6 -> 1082
      //   1079: goto -555 -> 524
      //   1082: goto -338 -> 744
      //   1085: iconst_0
      //   1086: istore_1
      //   1087: goto -598 -> 489
      // Local variable table:
      //   start	length	slot	name	signature
      //   0	1090	0	this	if
      //   489	598	1	i	int
      //   300	749	2	bool	boolean
      //   22	254	3	localJSONObject	org.json.JSONObject
      //   420	135	3	localObject1	Object
      //   558	311	3	str1	String
      //   13	462	4	localObject2	Object
      //   112	165	5	str2	String
      //   311	100	5	localJSONException	org.json.JSONException
      //   415	65	5	str3	String
      // Exception table:
      //   from	to	target	type
      //   23	301	311	org/json/JSONException
      //   744	954	311	org/json/JSONException
      //   1034	1048	311	org/json/JSONException
      //   437	486	420	finally
    }
    
    public Map<String, String> getHeaders()
    {
      Map localMap;
      for (;;)
      {
        localMap = (Map)new HashMap();
        int i = ॱॱ + 85;
        ॱ = i % 128;
        if (i % 2 != 0) {
          break;
        }
        return localMap;
      }
      return localMap;
    }
    
    public CustomNetworkOperationProvider.HttpRequestMethod getHttpMethod()
    {
      break label9;
      int i = 30;
      for (;;)
      {
        label9:
        switch (i)
        {
        default: 
          break label70;
          i = ॱ + 65;
          ॱॱ = i % 128;
          if (i % 2 == 0) {}
          break;
        case 30: 
          return CustomNetworkOperationProvider.HttpRequestMethod.DEFAULT;
        case 14: 
          label70:
          CustomNetworkOperationProvider.HttpRequestMethod localHttpRequestMethod = CustomNetworkOperationProvider.HttpRequestMethod.DEFAULT;
          i = null.length;
          return localHttpRequestMethod;
          i = 14;
        }
      }
    }
    
    /* Error */
    public String getUri()
    {
      // Byte code:
      //   0: goto +70 -> 70
      //   3: getstatic 25	o/Hq$if:ॱ	I
      //   6: iconst_5
      //   7: iadd
      //   8: istore_1
      //   9: iload_1
      //   10: sipush 128
      //   13: irem
      //   14: putstatic 27	o/Hq$if:ॱॱ	I
      //   17: iload_1
      //   18: iconst_2
      //   19: irem
      //   20: ifne +6 -> 26
      //   23: goto +44 -> 67
      //   26: ldc -5
      //   28: areturn
      //   29: goto -26 -> 3
      //   32: goto -3 -> 29
      //   35: astore_2
      //   36: aload_2
      //   37: athrow
      //   38: getstatic 25	o/Hq$if:ॱ	I
      //   41: istore_1
      //   42: iload_1
      //   43: bipush 13
      //   45: iadd
      //   46: istore_1
      //   47: iload_1
      //   48: sipush 128
      //   51: irem
      //   52: putstatic 27	o/Hq$if:ॱॱ	I
      //   55: iload_1
      //   56: iconst_2
      //   57: irem
      //   58: ifne +6 -> 64
      //   61: goto -29 -> 32
      //   64: goto -35 -> 29
      //   67: ldc -5
      //   69: areturn
      //   70: goto -32 -> 38
      //   73: astore_2
      //   74: aload_2
      //   75: athrow
      // Local variable table:
      //   start	length	slot	name	signature
      //   0	76	0	this	if
      //   8	50	1	i	int
      //   35	2	2	localException1	Exception
      //   73	2	2	localException2	Exception
      // Exception table:
      //   from	to	target	type
      //   47	55	35	java/lang/Exception
      //   38	42	73	java/lang/Exception
    }
  }
  
  public static final class ˊ
    extends Ht
  {
    private static int ʻ = 1;
    private static int ˊ = 0;
    private static boolean ˋ = true;
    private static boolean ˎ = true;
    private static char[] ˏ = { 216, 203, 217, 214, 213, 212, 175, 204, 170, 207, 205, 218, 224, 199, 184, 210, 134, 219, 201, 147, 202 };
    private static int ॱ = 102;
    
    ˊ(String paramString) {}
    
    /* Error */
    private static String ˋ(byte[] paramArrayOfByte, int[] paramArrayOfInt, char[] paramArrayOfChar, int paramInt)
    {
      // Byte code:
      //   0: goto +136 -> 136
      //   3: aload_1
      //   4: iload 4
      //   6: aload 9
      //   8: aload_0
      //   9: iload 7
      //   11: iconst_1
      //   12: isub
      //   13: iload 4
      //   15: isub
      //   16: baload
      //   17: iload_3
      //   18: iadd
      //   19: caload
      //   20: iload 6
      //   22: isub
      //   23: i2c
      //   24: castore
      //   25: iload 4
      //   27: iconst_1
      //   28: iadd
      //   29: istore 4
      //   31: goto +308 -> 339
      //   34: aload_2
      //   35: arraylength
      //   36: istore 7
      //   38: iload 7
      //   40: newarray char
      //   42: astore_0
      //   43: iconst_0
      //   44: istore 4
      //   46: goto +309 -> 355
      //   49: aload_0
      //   50: arraylength
      //   51: istore 7
      //   53: iload 7
      //   55: newarray char
      //   57: astore_1
      //   58: iconst_0
      //   59: istore 4
      //   61: goto +278 -> 339
      //   64: aload_0
      //   65: iload 4
      //   67: aload 9
      //   69: aload_1
      //   70: iload 5
      //   72: iconst_1
      //   73: isub
      //   74: iload 4
      //   76: isub
      //   77: iaload
      //   78: iload_3
      //   79: isub
      //   80: caload
      //   81: iload 6
      //   83: isub
      //   84: i2c
      //   85: castore
      //   86: iload 4
      //   88: iconst_1
      //   89: iadd
      //   90: istore 4
      //   92: goto +178 -> 270
      //   95: iload 4
      //   97: tableswitch	default:+23->120, 0:+271->368, 1:+69->166
      //   120: goto +46 -> 166
      //   123: iload 4
      //   125: iload 5
      //   127: if_icmpge +6 -> 133
      //   130: goto -66 -> 64
      //   133: goto +261 -> 394
      //   136: goto +140 -> 276
      //   139: new 62	java/lang/String
      //   142: dup
      //   143: aload_0
      //   144: invokespecial 65	java/lang/String:<init>	([C)V
      //   147: areturn
      //   148: goto -25 -> 123
      //   151: aload_1
      //   152: arraylength
      //   153: istore 5
      //   155: iload 5
      //   157: newarray char
      //   159: astore_0
      //   160: iconst_0
      //   161: istore 4
      //   163: goto -15 -> 148
      //   166: iload 5
      //   168: istore 4
      //   170: goto +185 -> 355
      //   173: getstatic 21	o/Hq$ˊ:ˊ	I
      //   176: bipush 105
      //   178: iadd
      //   179: istore 4
      //   181: iload 4
      //   183: sipush 128
      //   186: irem
      //   187: putstatic 23	o/Hq$ˊ:ʻ	I
      //   190: iload 4
      //   192: iconst_2
      //   193: irem
      //   194: ifne +6 -> 200
      //   197: goto +67 -> 264
      //   200: goto +203 -> 403
      //   203: getstatic 23	o/Hq$ˊ:ʻ	I
      //   206: bipush 107
      //   208: iadd
      //   209: istore 5
      //   211: iload 5
      //   213: sipush 128
      //   216: irem
      //   217: putstatic 21	o/Hq$ˊ:ˊ	I
      //   220: iload 5
      //   222: iconst_2
      //   223: irem
      //   224: ifeq +6 -> 230
      //   227: goto +164 -> 391
      //   230: goto -227 -> 3
      //   233: aload_0
      //   234: iload 4
      //   236: aload 9
      //   238: aload_2
      //   239: iload 7
      //   241: iconst_1
      //   242: isub
      //   243: iload 4
      //   245: isub
      //   246: caload
      //   247: iload_3
      //   248: isub
      //   249: caload
      //   250: iload 6
      //   252: isub
      //   253: i2c
      //   254: castore
      //   255: iload 4
      //   257: iconst_1
      //   258: iadd
      //   259: istore 5
      //   261: goto -88 -> 173
      //   264: iconst_1
      //   265: istore 4
      //   267: goto -172 -> 95
      //   270: goto -147 -> 123
      //   273: astore_0
      //   274: aload_0
      //   275: athrow
      //   276: getstatic 50	o/Hq$ˊ:ˏ	[C
      //   279: astore 9
      //   281: getstatic 52	o/Hq$ˊ:ॱ	I
      //   284: istore 6
      //   286: getstatic 25	o/Hq$ˊ:ˋ	Z
      //   289: ifeq +6 -> 295
      //   292: goto -243 -> 49
      //   295: goto +80 -> 375
      //   298: iconst_0
      //   299: istore 5
      //   301: goto +12 -> 313
      //   304: new 62	java/lang/String
      //   307: dup
      //   308: aload_1
      //   309: invokespecial 65	java/lang/String:<init>	([C)V
      //   312: areturn
      //   313: iload 5
      //   315: tableswitch	default:+21->336, 0:+-112->203, 1:+-11->304
      //   336: goto -32 -> 304
      //   339: iload 4
      //   341: iload 7
      //   343: if_icmpge +6 -> 349
      //   346: goto -48 -> 298
      //   349: iconst_1
      //   350: istore 5
      //   352: goto -39 -> 313
      //   355: iload 4
      //   357: iload 7
      //   359: if_icmpge +6 -> 365
      //   362: goto -129 -> 233
      //   365: goto -226 -> 139
      //   368: iload 5
      //   370: istore 4
      //   372: goto -17 -> 355
      //   375: getstatic 27	o/Hq$ˊ:ˎ	Z
      //   378: istore 8
      //   380: iload 8
      //   382: ifeq +6 -> 388
      //   385: goto -351 -> 34
      //   388: goto -237 -> 151
      //   391: goto -388 -> 3
      //   394: new 62	java/lang/String
      //   397: dup
      //   398: aload_0
      //   399: invokespecial 65	java/lang/String:<init>	([C)V
      //   402: areturn
      //   403: iconst_0
      //   404: istore 4
      //   406: goto -311 -> 95
      // Local variable table:
      //   start	length	slot	name	signature
      //   0	409	0	paramArrayOfByte	byte[]
      //   0	409	1	paramArrayOfInt	int[]
      //   0	409	2	paramArrayOfChar	char[]
      //   0	409	3	paramInt	int
      //   4	401	4	i	int
      //   70	299	5	j	int
      //   20	265	6	k	int
      //   9	351	7	m	int
      //   378	3	8	bool	boolean
      //   6	274	9	arrayOfChar	char[]
      // Exception table:
      //   from	to	target	type
      //   375	380	273	java/lang/Exception
    }
    
    /* Error */
    public void onError(com.insidesecure.hce.NetworkOperationResponseInfo paramNetworkOperationResponseInfo)
    {
      // Byte code:
      //   0: goto +489 -> 489
      //   3: getstatic 21	o/Hq$ˊ:ˊ	I
      //   6: bipush 107
      //   8: iadd
      //   9: istore_2
      //   10: iload_2
      //   11: sipush 128
      //   14: irem
      //   15: putstatic 23	o/Hq$ˊ:ʻ	I
      //   18: iload_2
      //   19: iconst_2
      //   20: irem
      //   21: ifne +6 -> 27
      //   24: goto +464 -> 488
      //   27: return
      //   28: aload_1
      //   29: bipush 12
      //   31: newarray byte
      //   33: dup
      //   34: iconst_0
      //   35: ldc 68
      //   37: bastore
      //   38: dup
      //   39: iconst_1
      //   40: ldc 69
      //   42: bastore
      //   43: dup
      //   44: iconst_2
      //   45: ldc 70
      //   47: bastore
      //   48: dup
      //   49: iconst_3
      //   50: ldc 71
      //   52: bastore
      //   53: dup
      //   54: iconst_4
      //   55: ldc 72
      //   57: bastore
      //   58: dup
      //   59: iconst_5
      //   60: ldc 73
      //   62: bastore
      //   63: dup
      //   64: bipush 6
      //   66: ldc 70
      //   68: bastore
      //   69: dup
      //   70: bipush 7
      //   72: ldc 68
      //   74: bastore
      //   75: dup
      //   76: bipush 8
      //   78: ldc 74
      //   80: bastore
      //   81: dup
      //   82: bipush 9
      //   84: ldc 73
      //   86: bastore
      //   87: dup
      //   88: bipush 10
      //   90: ldc 72
      //   92: bastore
      //   93: dup
      //   94: bipush 11
      //   96: ldc 75
      //   98: bastore
      //   99: aconst_null
      //   100: aconst_null
      //   101: bipush 127
      //   103: invokestatic 77	o/Hq$ˊ:ˋ	([B[I[CI)Ljava/lang/String;
      //   106: invokevirtual 81	java/lang/String:intern	()Ljava/lang/String;
      //   109: invokestatic 86	o/vq:ˎ	(Ljava/lang/Object;Ljava/lang/String;)V
      //   112: bipush 12
      //   114: newarray byte
      //   116: dup
      //   117: iconst_0
      //   118: ldc 70
      //   120: bastore
      //   121: dup
      //   122: iconst_1
      //   123: ldc 68
      //   125: bastore
      //   126: dup
      //   127: iconst_2
      //   128: ldc 87
      //   130: bastore
      //   131: dup
      //   132: iconst_3
      //   133: ldc 88
      //   135: bastore
      //   136: dup
      //   137: iconst_4
      //   138: ldc 89
      //   140: bastore
      //   141: dup
      //   142: iconst_5
      //   143: ldc 90
      //   145: bastore
      //   146: dup
      //   147: bipush 6
      //   149: ldc 87
      //   151: bastore
      //   152: dup
      //   153: bipush 7
      //   155: ldc 88
      //   157: bastore
      //   158: dup
      //   159: bipush 8
      //   161: ldc 87
      //   163: bastore
      //   164: dup
      //   165: bipush 9
      //   167: ldc 91
      //   169: bastore
      //   170: dup
      //   171: bipush 10
      //   173: ldc 87
      //   175: bastore
      //   176: dup
      //   177: bipush 11
      //   179: ldc 92
      //   181: bastore
      //   182: aconst_null
      //   183: aconst_null
      //   184: bipush 127
      //   186: invokestatic 77	o/Hq$ˊ:ˋ	([B[I[CI)Ljava/lang/String;
      //   189: invokevirtual 81	java/lang/String:intern	()Ljava/lang/String;
      //   192: astore_3
      //   193: new 94	java/lang/StringBuilder
      //   196: dup
      //   197: invokespecial 96	java/lang/StringBuilder:<init>	()V
      //   200: bipush 15
      //   202: newarray byte
      //   204: dup
      //   205: iconst_0
      //   206: ldc 97
      //   208: bastore
      //   209: dup
      //   210: iconst_1
      //   211: ldc 98
      //   213: bastore
      //   214: dup
      //   215: iconst_2
      //   216: ldc 97
      //   218: bastore
      //   219: dup
      //   220: iconst_3
      //   221: ldc 75
      //   223: bastore
      //   224: dup
      //   225: iconst_4
      //   226: ldc 68
      //   228: bastore
      //   229: dup
      //   230: iconst_5
      //   231: ldc 75
      //   233: bastore
      //   234: dup
      //   235: bipush 6
      //   237: ldc 75
      //   239: bastore
      //   240: dup
      //   241: bipush 7
      //   243: ldc 72
      //   245: bastore
      //   246: dup
      //   247: bipush 8
      //   249: ldc 97
      //   251: bastore
      //   252: dup
      //   253: bipush 9
      //   255: ldc 99
      //   257: bastore
      //   258: dup
      //   259: bipush 10
      //   261: ldc 99
      //   263: bastore
      //   264: dup
      //   265: bipush 11
      //   267: ldc 87
      //   269: bastore
      //   270: dup
      //   271: bipush 12
      //   273: ldc 69
      //   275: bastore
      //   276: dup
      //   277: bipush 13
      //   279: ldc 72
      //   281: bastore
      //   282: dup
      //   283: bipush 14
      //   285: ldc 100
      //   287: bastore
      //   288: aconst_null
      //   289: aconst_null
      //   290: bipush 127
      //   292: invokestatic 77	o/Hq$ˊ:ˋ	([B[I[CI)Ljava/lang/String;
      //   295: invokevirtual 81	java/lang/String:intern	()Ljava/lang/String;
      //   298: invokevirtual 104	java/lang/StringBuilder:append	(Ljava/lang/String;)Ljava/lang/StringBuilder;
      //   301: aload_1
      //   302: getfield 110	com/insidesecure/hce/NetworkOperationResponseInfo:responseData	Ljava/lang/String;
      //   305: invokevirtual 104	java/lang/StringBuilder:append	(Ljava/lang/String;)Ljava/lang/StringBuilder;
      //   308: bipush 14
      //   310: newarray byte
      //   312: dup
      //   313: iconst_0
      //   314: ldc 97
      //   316: bastore
      //   317: dup
      //   318: iconst_1
      //   319: ldc 98
      //   321: bastore
      //   322: dup
      //   323: iconst_2
      //   324: ldc 97
      //   326: bastore
      //   327: dup
      //   328: iconst_3
      //   329: ldc 72
      //   331: bastore
      //   332: dup
      //   333: iconst_4
      //   334: ldc 111
      //   336: bastore
      //   337: dup
      //   338: iconst_5
      //   339: ldc 68
      //   341: bastore
      //   342: dup
      //   343: bipush 6
      //   345: ldc 112
      //   347: bastore
      //   348: dup
      //   349: bipush 7
      //   351: ldc 97
      //   353: bastore
      //   354: dup
      //   355: bipush 8
      //   357: ldc 75
      //   359: bastore
      //   360: dup
      //   361: bipush 9
      //   363: ldc 68
      //   365: bastore
      //   366: dup
      //   367: bipush 10
      //   369: ldc 75
      //   371: bastore
      //   372: dup
      //   373: bipush 11
      //   375: ldc 75
      //   377: bastore
      //   378: dup
      //   379: bipush 12
      //   381: ldc 72
      //   383: bastore
      //   384: dup
      //   385: bipush 13
      //   387: ldc 97
      //   389: bastore
      //   390: aconst_null
      //   391: aconst_null
      //   392: bipush 127
      //   394: invokestatic 77	o/Hq$ˊ:ˋ	([B[I[CI)Ljava/lang/String;
      //   397: invokevirtual 81	java/lang/String:intern	()Ljava/lang/String;
      //   400: invokevirtual 104	java/lang/StringBuilder:append	(Ljava/lang/String;)Ljava/lang/StringBuilder;
      //   403: aload_1
      //   404: getfield 116	com/insidesecure/hce/NetworkOperationResponseInfo:errorCode	Lcom/insidesecure/hce/MatrixHCEError;
      //   407: invokevirtual 119	java/lang/StringBuilder:append	(Ljava/lang/Object;)Ljava/lang/StringBuilder;
      //   410: invokevirtual 122	java/lang/StringBuilder:toString	()Ljava/lang/String;
      //   413: astore 4
      //   415: goto +17 -> 432
      //   418: astore_1
      //   419: aload_1
      //   420: invokevirtual 128	java/lang/Throwable:getCause	()Ljava/lang/Throwable;
      //   423: astore_3
      //   424: aload_3
      //   425: ifnull +5 -> 430
      //   428: aload_3
      //   429: athrow
      //   430: aload_1
      //   431: athrow
      //   432: iconst_4
      //   433: bipush 42
      //   435: ldc -127
      //   437: invokestatic 134	o/O:ˋ	(IIC)Ljava/lang/Object;
      //   440: checkcast 136	java/lang/Class
      //   443: ldc -119
      //   445: iconst_2
      //   446: anewarray 136	java/lang/Class
      //   449: dup
      //   450: iconst_0
      //   451: ldc 62
      //   453: aastore
      //   454: dup
      //   455: iconst_1
      //   456: ldc 62
      //   458: aastore
      //   459: invokevirtual 141	java/lang/Class:getMethod	(Ljava/lang/String;[Ljava/lang/Class;)Ljava/lang/reflect/Method;
      //   462: aconst_null
      //   463: iconst_2
      //   464: anewarray 143	java/lang/Object
      //   467: dup
      //   468: iconst_0
      //   469: aload_3
      //   470: aastore
      //   471: dup
      //   472: iconst_1
      //   473: aload 4
      //   475: aastore
      //   476: invokevirtual 149	java/lang/reflect/Method:invoke	(Ljava/lang/Object;[Ljava/lang/Object;)Ljava/lang/Object;
      //   479: pop
      //   480: aload_0
      //   481: aload_1
      //   482: invokespecial 151	o/Ht:onError	(Lcom/insidesecure/hce/NetworkOperationResponseInfo;)V
      //   485: goto -482 -> 3
      //   488: return
      //   489: goto -461 -> 28
      // Local variable table:
      //   start	length	slot	name	signature
      //   0	492	0	this	ˊ
      //   0	492	1	paramNetworkOperationResponseInfo	com.insidesecure.hce.NetworkOperationResponseInfo
      //   9	12	2	i	int
      //   192	278	3	localObject	Object
      //   413	61	4	str	String
      // Exception table:
      //   from	to	target	type
      //   432	480	418	finally
    }
    
    /* Error */
    public void onFailure(com.insidesecure.hce.FailureInfo paramFailureInfo)
    {
      // Byte code:
      //   0: goto +68 -> 68
      //   3: bipush 22
      //   5: istore_2
      //   6: goto +5 -> 11
      //   9: iconst_4
      //   10: istore_2
      //   11: iload_2
      //   12: lookupswitch	default:+28->40, 4:+60->72, 22:+59->71
      //   40: return
      //   41: getstatic 21	o/Hq$ˊ:ˊ	I
      //   44: bipush 97
      //   46: iadd
      //   47: istore_2
      //   48: iload_2
      //   49: sipush 128
      //   52: irem
      //   53: putstatic 23	o/Hq$ˊ:ʻ	I
      //   56: iload_2
      //   57: iconst_2
      //   58: irem
      //   59: ifne +6 -> 65
      //   62: goto -53 -> 9
      //   65: goto -62 -> 3
      //   68: goto +12 -> 80
      //   71: return
      //   72: new 155	java/lang/NullPointerException
      //   75: dup
      //   76: invokespecial 156	java/lang/NullPointerException:<init>	()V
      //   79: athrow
      //   80: aload_1
      //   81: bipush 6
      //   83: newarray byte
      //   85: dup
      //   86: iconst_0
      //   87: ldc 70
      //   89: bastore
      //   90: dup
      //   91: iconst_1
      //   92: ldc 68
      //   94: bastore
      //   95: dup
      //   96: iconst_2
      //   97: ldc 73
      //   99: bastore
      //   100: dup
      //   101: iconst_3
      //   102: ldc 89
      //   104: bastore
      //   105: dup
      //   106: iconst_4
      //   107: ldc 72
      //   109: bastore
      //   110: dup
      //   111: iconst_5
      //   112: ldc 75
      //   114: bastore
      //   115: aconst_null
      //   116: aconst_null
      //   117: bipush 127
      //   119: invokestatic 77	o/Hq$ˊ:ˋ	([B[I[CI)Ljava/lang/String;
      //   122: invokevirtual 81	java/lang/String:intern	()Ljava/lang/String;
      //   125: invokestatic 86	o/vq:ˎ	(Ljava/lang/Object;Ljava/lang/String;)V
      //   128: bipush 12
      //   130: newarray byte
      //   132: dup
      //   133: iconst_0
      //   134: ldc 70
      //   136: bastore
      //   137: dup
      //   138: iconst_1
      //   139: ldc 68
      //   141: bastore
      //   142: dup
      //   143: iconst_2
      //   144: ldc 87
      //   146: bastore
      //   147: dup
      //   148: iconst_3
      //   149: ldc 88
      //   151: bastore
      //   152: dup
      //   153: iconst_4
      //   154: ldc 89
      //   156: bastore
      //   157: dup
      //   158: iconst_5
      //   159: ldc 90
      //   161: bastore
      //   162: dup
      //   163: bipush 6
      //   165: ldc 87
      //   167: bastore
      //   168: dup
      //   169: bipush 7
      //   171: ldc 88
      //   173: bastore
      //   174: dup
      //   175: bipush 8
      //   177: ldc 87
      //   179: bastore
      //   180: dup
      //   181: bipush 9
      //   183: ldc 91
      //   185: bastore
      //   186: dup
      //   187: bipush 10
      //   189: ldc 87
      //   191: bastore
      //   192: dup
      //   193: bipush 11
      //   195: ldc 92
      //   197: bastore
      //   198: aconst_null
      //   199: aconst_null
      //   200: bipush 127
      //   202: invokestatic 77	o/Hq$ˊ:ˋ	([B[I[CI)Ljava/lang/String;
      //   205: invokevirtual 81	java/lang/String:intern	()Ljava/lang/String;
      //   208: astore 4
      //   210: new 94	java/lang/StringBuilder
      //   213: dup
      //   214: invokespecial 96	java/lang/StringBuilder:<init>	()V
      //   217: bipush 15
      //   219: newarray byte
      //   221: dup
      //   222: iconst_0
      //   223: ldc 97
      //   225: bastore
      //   226: dup
      //   227: iconst_1
      //   228: ldc 98
      //   230: bastore
      //   231: dup
      //   232: iconst_2
      //   233: ldc 97
      //   235: bastore
      //   236: dup
      //   237: iconst_3
      //   238: ldc 75
      //   240: bastore
      //   241: dup
      //   242: iconst_4
      //   243: ldc 68
      //   245: bastore
      //   246: dup
      //   247: iconst_5
      //   248: ldc 75
      //   250: bastore
      //   251: dup
      //   252: bipush 6
      //   254: ldc 75
      //   256: bastore
      //   257: dup
      //   258: bipush 7
      //   260: ldc 72
      //   262: bastore
      //   263: dup
      //   264: bipush 8
      //   266: ldc 97
      //   268: bastore
      //   269: dup
      //   270: bipush 9
      //   272: ldc 99
      //   274: bastore
      //   275: dup
      //   276: bipush 10
      //   278: ldc 99
      //   280: bastore
      //   281: dup
      //   282: bipush 11
      //   284: ldc 87
      //   286: bastore
      //   287: dup
      //   288: bipush 12
      //   290: ldc 69
      //   292: bastore
      //   293: dup
      //   294: bipush 13
      //   296: ldc 72
      //   298: bastore
      //   299: dup
      //   300: bipush 14
      //   302: ldc 100
      //   304: bastore
      //   305: aconst_null
      //   306: aconst_null
      //   307: bipush 127
      //   309: invokestatic 77	o/Hq$ˊ:ˋ	([B[I[CI)Ljava/lang/String;
      //   312: invokevirtual 81	java/lang/String:intern	()Ljava/lang/String;
      //   315: invokevirtual 104	java/lang/StringBuilder:append	(Ljava/lang/String;)Ljava/lang/StringBuilder;
      //   318: aload_1
      //   319: getfield 161	com/insidesecure/hce/FailureInfo:reason	Ljava/lang/String;
      //   322: invokevirtual 104	java/lang/StringBuilder:append	(Ljava/lang/String;)Ljava/lang/StringBuilder;
      //   325: bipush 9
      //   327: newarray byte
      //   329: dup
      //   330: iconst_0
      //   331: ldc 97
      //   333: bastore
      //   334: dup
      //   335: iconst_1
      //   336: ldc 98
      //   338: bastore
      //   339: dup
      //   340: iconst_2
      //   341: ldc 97
      //   343: bastore
      //   344: dup
      //   345: iconst_3
      //   346: ldc 75
      //   348: bastore
      //   349: dup
      //   350: iconst_4
      //   351: ldc 68
      //   353: bastore
      //   354: dup
      //   355: iconst_5
      //   356: ldc 75
      //   358: bastore
      //   359: dup
      //   360: bipush 6
      //   362: ldc 75
      //   364: bastore
      //   365: dup
      //   366: bipush 7
      //   368: ldc 72
      //   370: bastore
      //   371: dup
      //   372: bipush 8
      //   374: ldc 97
      //   376: bastore
      //   377: aconst_null
      //   378: aconst_null
      //   379: bipush 127
      //   381: invokestatic 77	o/Hq$ˊ:ˋ	([B[I[CI)Ljava/lang/String;
      //   384: invokevirtual 81	java/lang/String:intern	()Ljava/lang/String;
      //   387: invokevirtual 104	java/lang/StringBuilder:append	(Ljava/lang/String;)Ljava/lang/StringBuilder;
      //   390: aload_1
      //   391: getfield 164	com/insidesecure/hce/FailureInfo:error	Lcom/insidesecure/hce/MatrixHCEError;
      //   394: invokevirtual 169	com/insidesecure/hce/MatrixHCEError:name	()Ljava/lang/String;
      //   397: invokevirtual 104	java/lang/StringBuilder:append	(Ljava/lang/String;)Ljava/lang/StringBuilder;
      //   400: invokevirtual 122	java/lang/StringBuilder:toString	()Ljava/lang/String;
      //   403: astore_3
      //   404: goto +17 -> 421
      //   407: astore_3
      //   408: aload_3
      //   409: invokevirtual 128	java/lang/Throwable:getCause	()Ljava/lang/Throwable;
      //   412: astore_1
      //   413: aload_1
      //   414: ifnull +5 -> 419
      //   417: aload_1
      //   418: athrow
      //   419: aload_3
      //   420: athrow
      //   421: iconst_4
      //   422: bipush 42
      //   424: ldc -127
      //   426: invokestatic 134	o/O:ˋ	(IIC)Ljava/lang/Object;
      //   429: checkcast 136	java/lang/Class
      //   432: ldc -119
      //   434: iconst_2
      //   435: anewarray 136	java/lang/Class
      //   438: dup
      //   439: iconst_0
      //   440: ldc 62
      //   442: aastore
      //   443: dup
      //   444: iconst_1
      //   445: ldc 62
      //   447: aastore
      //   448: invokevirtual 141	java/lang/Class:getMethod	(Ljava/lang/String;[Ljava/lang/Class;)Ljava/lang/reflect/Method;
      //   451: aconst_null
      //   452: iconst_2
      //   453: anewarray 143	java/lang/Object
      //   456: dup
      //   457: iconst_0
      //   458: aload 4
      //   460: aastore
      //   461: dup
      //   462: iconst_1
      //   463: aload_3
      //   464: aastore
      //   465: invokevirtual 149	java/lang/reflect/Method:invoke	(Ljava/lang/Object;[Ljava/lang/Object;)Ljava/lang/Object;
      //   468: pop
      //   469: aload_0
      //   470: aload_1
      //   471: invokespecial 171	o/Ht:onFailure	(Lcom/insidesecure/hce/FailureInfo;)V
      //   474: goto -433 -> 41
      // Local variable table:
      //   start	length	slot	name	signature
      //   0	477	0	this	ˊ
      //   0	477	1	paramFailureInfo	com.insidesecure.hce.FailureInfo
      //   5	54	2	i	int
      //   403	1	3	str1	String
      //   407	57	3	localObject	Object
      //   208	251	4	str2	String
      // Exception table:
      //   from	to	target	type
      //   421	469	407	finally
    }
    
    /* Error */
    public void onSuccess(com.insidesecure.hce.NetworkOperationResponseInfo paramNetworkOperationResponseInfo)
    {
      // Byte code:
      //   0: goto +368 -> 368
      //   3: aload_1
      //   4: bipush 12
      //   6: newarray byte
      //   8: dup
      //   9: iconst_0
      //   10: ldc 68
      //   12: bastore
      //   13: dup
      //   14: iconst_1
      //   15: ldc 69
      //   17: bastore
      //   18: dup
      //   19: iconst_2
      //   20: ldc 70
      //   22: bastore
      //   23: dup
      //   24: iconst_3
      //   25: ldc 71
      //   27: bastore
      //   28: dup
      //   29: iconst_4
      //   30: ldc 72
      //   32: bastore
      //   33: dup
      //   34: iconst_5
      //   35: ldc 73
      //   37: bastore
      //   38: dup
      //   39: bipush 6
      //   41: ldc 70
      //   43: bastore
      //   44: dup
      //   45: bipush 7
      //   47: ldc 68
      //   49: bastore
      //   50: dup
      //   51: bipush 8
      //   53: ldc 74
      //   55: bastore
      //   56: dup
      //   57: bipush 9
      //   59: ldc 73
      //   61: bastore
      //   62: dup
      //   63: bipush 10
      //   65: ldc 72
      //   67: bastore
      //   68: dup
      //   69: bipush 11
      //   71: ldc 75
      //   73: bastore
      //   74: aconst_null
      //   75: aconst_null
      //   76: bipush 127
      //   78: invokestatic 77	o/Hq$ˊ:ˋ	([B[I[CI)Ljava/lang/String;
      //   81: invokevirtual 81	java/lang/String:intern	()Ljava/lang/String;
      //   84: invokestatic 86	o/vq:ˎ	(Ljava/lang/Object;Ljava/lang/String;)V
      //   87: bipush 12
      //   89: newarray byte
      //   91: dup
      //   92: iconst_0
      //   93: ldc 70
      //   95: bastore
      //   96: dup
      //   97: iconst_1
      //   98: ldc 68
      //   100: bastore
      //   101: dup
      //   102: iconst_2
      //   103: ldc 87
      //   105: bastore
      //   106: dup
      //   107: iconst_3
      //   108: ldc 88
      //   110: bastore
      //   111: dup
      //   112: iconst_4
      //   113: ldc 89
      //   115: bastore
      //   116: dup
      //   117: iconst_5
      //   118: ldc 90
      //   120: bastore
      //   121: dup
      //   122: bipush 6
      //   124: ldc 87
      //   126: bastore
      //   127: dup
      //   128: bipush 7
      //   130: ldc 88
      //   132: bastore
      //   133: dup
      //   134: bipush 8
      //   136: ldc 87
      //   138: bastore
      //   139: dup
      //   140: bipush 9
      //   142: ldc 91
      //   144: bastore
      //   145: dup
      //   146: bipush 10
      //   148: ldc 87
      //   150: bastore
      //   151: dup
      //   152: bipush 11
      //   154: ldc 92
      //   156: bastore
      //   157: aconst_null
      //   158: aconst_null
      //   159: bipush 127
      //   161: invokestatic 77	o/Hq$ˊ:ˋ	([B[I[CI)Ljava/lang/String;
      //   164: invokevirtual 81	java/lang/String:intern	()Ljava/lang/String;
      //   167: astore_3
      //   168: bipush 14
      //   170: newarray byte
      //   172: dup
      //   173: iconst_0
      //   174: ldc 73
      //   176: bastore
      //   177: dup
      //   178: iconst_1
      //   179: ldc 73
      //   181: bastore
      //   182: dup
      //   183: iconst_2
      //   184: ldc 72
      //   186: bastore
      //   187: dup
      //   188: iconst_3
      //   189: ldc 112
      //   191: bastore
      //   192: dup
      //   193: iconst_4
      //   194: ldc 112
      //   196: bastore
      //   197: dup
      //   198: iconst_5
      //   199: ldc -83
      //   201: bastore
      //   202: dup
      //   203: bipush 6
      //   205: ldc 73
      //   207: bastore
      //   208: dup
      //   209: bipush 7
      //   211: ldc 97
      //   213: bastore
      //   214: dup
      //   215: bipush 8
      //   217: ldc 99
      //   219: bastore
      //   220: dup
      //   221: bipush 9
      //   223: ldc 99
      //   225: bastore
      //   226: dup
      //   227: bipush 10
      //   229: ldc 87
      //   231: bastore
      //   232: dup
      //   233: bipush 11
      //   235: ldc 69
      //   237: bastore
      //   238: dup
      //   239: bipush 12
      //   241: ldc 72
      //   243: bastore
      //   244: dup
      //   245: bipush 13
      //   247: ldc 100
      //   249: bastore
      //   250: aconst_null
      //   251: aconst_null
      //   252: bipush 127
      //   254: invokestatic 77	o/Hq$ˊ:ˋ	([B[I[CI)Ljava/lang/String;
      //   257: invokevirtual 81	java/lang/String:intern	()Ljava/lang/String;
      //   260: astore 4
      //   262: goto +17 -> 279
      //   265: astore_1
      //   266: aload_1
      //   267: invokevirtual 128	java/lang/Throwable:getCause	()Ljava/lang/Throwable;
      //   270: astore_3
      //   271: aload_3
      //   272: ifnull +5 -> 277
      //   275: aload_3
      //   276: athrow
      //   277: aload_1
      //   278: athrow
      //   279: iconst_4
      //   280: bipush 42
      //   282: ldc -127
      //   284: invokestatic 134	o/O:ˋ	(IIC)Ljava/lang/Object;
      //   287: checkcast 136	java/lang/Class
      //   290: ldc -119
      //   292: iconst_2
      //   293: anewarray 136	java/lang/Class
      //   296: dup
      //   297: iconst_0
      //   298: ldc 62
      //   300: aastore
      //   301: dup
      //   302: iconst_1
      //   303: ldc 62
      //   305: aastore
      //   306: invokevirtual 141	java/lang/Class:getMethod	(Ljava/lang/String;[Ljava/lang/Class;)Ljava/lang/reflect/Method;
      //   309: aconst_null
      //   310: iconst_2
      //   311: anewarray 143	java/lang/Object
      //   314: dup
      //   315: iconst_0
      //   316: aload_3
      //   317: aastore
      //   318: dup
      //   319: iconst_1
      //   320: aload 4
      //   322: aastore
      //   323: invokevirtual 149	java/lang/reflect/Method:invoke	(Ljava/lang/Object;[Ljava/lang/Object;)Ljava/lang/Object;
      //   326: pop
      //   327: aload_0
      //   328: aload_1
      //   329: invokespecial 175	o/Ht:onSuccess	(Lcom/insidesecure/hce/NetworkOperationResponseInfo;)V
      //   332: getstatic 21	o/Hq$ˊ:ˊ	I
      //   335: istore_2
      //   336: iload_2
      //   337: bipush 81
      //   339: iadd
      //   340: istore_2
      //   341: iload_2
      //   342: sipush 128
      //   345: irem
      //   346: putstatic 23	o/Hq$ˊ:ʻ	I
      //   349: iload_2
      //   350: iconst_2
      //   351: irem
      //   352: ifne +6 -> 358
      //   355: goto +40 -> 395
      //   358: return
      //   359: goto -356 -> 3
      //   362: astore_1
      //   363: aload_1
      //   364: athrow
      //   365: astore_1
      //   366: aload_1
      //   367: athrow
      //   368: getstatic 23	o/Hq$ˊ:ʻ	I
      //   371: bipush 123
      //   373: iadd
      //   374: istore_2
      //   375: iload_2
      //   376: sipush 128
      //   379: irem
      //   380: putstatic 21	o/Hq$ˊ:ˊ	I
      //   383: iload_2
      //   384: iconst_2
      //   385: irem
      //   386: ifeq +6 -> 392
      //   389: goto -30 -> 359
      //   392: goto -389 -> 3
      //   395: return
      // Local variable table:
      //   start	length	slot	name	signature
      //   0	396	0	this	ˊ
      //   0	396	1	paramNetworkOperationResponseInfo	com.insidesecure.hce.NetworkOperationResponseInfo
      //   335	51	2	i	int
      //   167	150	3	localObject	Object
      //   260	61	4	str	String
      // Exception table:
      //   from	to	target	type
      //   279	327	265	finally
      //   341	349	362	java/lang/Exception
      //   332	336	365	java/lang/Exception
    }
  }
}
