package o;

import com.insidesecure.hce.FailureInfo;
import com.insidesecure.hce.MatrixHCECard;

public abstract class Hu
  extends Ik<Void>
{
  private static int ʻ;
  private static long ˊ;
  private static int ˋ;
  private static char ˎ;
  private static byte ˏ;
  private static int ᐝ = 0;
  private final String ॱ;
  
  static
  {
    ʻ = 1;
    ˊ();
    ˏ = -102;
    int i = ʻ + 39;
    ᐝ = i % 128;
    if (i % 2 != 0) {}
  }
  
  /* Error */
  public Hu(android.content.Context paramContext, String paramString)
  {
    // Byte code:
    //   0: goto +6 -> 6
    //   3: astore_1
    //   4: aload_1
    //   5: athrow
    //   6: aload_1
    //   7: iconst_4
    //   8: newarray char
    //   10: dup
    //   11: iconst_0
    //   12: ldc 35
    //   14: castore
    //   15: dup
    //   16: iconst_1
    //   17: ldc 36
    //   19: castore
    //   20: dup
    //   21: iconst_2
    //   22: ldc 37
    //   24: castore
    //   25: dup
    //   26: iconst_3
    //   27: ldc 38
    //   29: castore
    //   30: iconst_0
    //   31: bipush 7
    //   33: newarray char
    //   35: dup
    //   36: iconst_0
    //   37: ldc 39
    //   39: castore
    //   40: dup
    //   41: iconst_1
    //   42: ldc 40
    //   44: castore
    //   45: dup
    //   46: iconst_2
    //   47: ldc 41
    //   49: castore
    //   50: dup
    //   51: iconst_3
    //   52: ldc 42
    //   54: castore
    //   55: dup
    //   56: iconst_4
    //   57: ldc 43
    //   59: castore
    //   60: dup
    //   61: iconst_5
    //   62: ldc 44
    //   64: castore
    //   65: dup
    //   66: bipush 6
    //   68: ldc 45
    //   70: castore
    //   71: ldc 46
    //   73: iconst_4
    //   74: newarray char
    //   76: dup
    //   77: iconst_0
    //   78: ldc 47
    //   80: castore
    //   81: dup
    //   82: iconst_1
    //   83: ldc 48
    //   85: castore
    //   86: dup
    //   87: iconst_2
    //   88: ldc 49
    //   90: castore
    //   91: dup
    //   92: iconst_3
    //   93: ldc 50
    //   95: castore
    //   96: invokestatic 53	o/Hu:ˋ	([CC[CI[C)Ljava/lang/String;
    //   99: invokevirtual 59	java/lang/String:intern	()Ljava/lang/String;
    //   102: invokestatic 64	o/vq:ˎ	(Ljava/lang/Object;Ljava/lang/String;)V
    //   105: aload_2
    //   106: iconst_4
    //   107: newarray char
    //   109: dup
    //   110: iconst_0
    //   111: ldc 65
    //   113: castore
    //   114: dup
    //   115: iconst_1
    //   116: ldc 66
    //   118: castore
    //   119: dup
    //   120: iconst_2
    //   121: ldc 67
    //   123: castore
    //   124: dup
    //   125: iconst_3
    //   126: ldc 68
    //   128: castore
    //   129: ldc 69
    //   131: bipush 16
    //   133: newarray char
    //   135: dup
    //   136: iconst_0
    //   137: ldc 70
    //   139: castore
    //   140: dup
    //   141: iconst_1
    //   142: ldc 71
    //   144: castore
    //   145: dup
    //   146: iconst_2
    //   147: ldc 72
    //   149: castore
    //   150: dup
    //   151: iconst_3
    //   152: ldc 73
    //   154: castore
    //   155: dup
    //   156: iconst_4
    //   157: ldc 74
    //   159: castore
    //   160: dup
    //   161: iconst_5
    //   162: ldc 75
    //   164: castore
    //   165: dup
    //   166: bipush 6
    //   168: ldc 76
    //   170: castore
    //   171: dup
    //   172: bipush 7
    //   174: ldc 77
    //   176: castore
    //   177: dup
    //   178: bipush 8
    //   180: ldc 78
    //   182: castore
    //   183: dup
    //   184: bipush 9
    //   186: ldc 79
    //   188: castore
    //   189: dup
    //   190: bipush 10
    //   192: ldc 80
    //   194: castore
    //   195: dup
    //   196: bipush 11
    //   198: ldc 81
    //   200: castore
    //   201: dup
    //   202: bipush 12
    //   204: ldc 82
    //   206: castore
    //   207: dup
    //   208: bipush 13
    //   210: ldc 83
    //   212: castore
    //   213: dup
    //   214: bipush 14
    //   216: ldc 84
    //   218: castore
    //   219: dup
    //   220: bipush 15
    //   222: ldc 85
    //   224: castore
    //   225: iconst_0
    //   226: iconst_4
    //   227: newarray char
    //   229: dup
    //   230: iconst_0
    //   231: ldc 47
    //   233: castore
    //   234: dup
    //   235: iconst_1
    //   236: ldc 48
    //   238: castore
    //   239: dup
    //   240: iconst_2
    //   241: ldc 49
    //   243: castore
    //   244: dup
    //   245: iconst_3
    //   246: ldc 50
    //   248: castore
    //   249: invokestatic 53	o/Hu:ˋ	([CC[CI[C)Ljava/lang/String;
    //   252: invokevirtual 59	java/lang/String:intern	()Ljava/lang/String;
    //   255: invokestatic 64	o/vq:ˎ	(Ljava/lang/Object;Ljava/lang/String;)V
    //   258: aload_0
    //   259: aload_1
    //   260: invokespecial 88	o/Ik:<init>	(Landroid/content/Context;)V
    //   263: aload_0
    //   264: aload_2
    //   265: putfield 90	o/Hu:ॱ	Ljava/lang/String;
    //   268: return
    // Local variable table:
    //   start	length	slot	name	signature
    //   0	269	0	this	Hu
    //   0	269	1	paramContext	android.content.Context
    //   0	269	2	paramString	String
    // Exception table:
    //   from	to	target	type
    //   6	268	3	java/lang/Exception
  }
  
  static void ˊ()
  {
    ˎ = '\000';
    ˊ = 5261911432114118109L;
    ˋ = 0;
  }
  
  /* Error */
  private static String ˋ(char[] paramArrayOfChar1, char paramChar, char[] paramArrayOfChar2, int paramInt, char[] paramArrayOfChar3)
  {
    // Byte code:
    //   0: goto +230 -> 230
    //   3: iload_1
    //   4: lookupswitch	default:+28->32, 56:+75->79, 93:+80->84
    //   32: goto +47 -> 79
    //   35: astore_0
    //   36: aload_0
    //   37: athrow
    //   38: bipush 56
    //   40: istore_1
    //   41: goto -38 -> 3
    //   44: goto +45 -> 89
    //   47: iload_3
    //   48: lookupswitch	default:+28->76, 3:+131->179, 58:+185->233
    //   76: goto +103 -> 179
    //   79: iload_3
    //   80: istore_1
    //   81: goto +220 -> 301
    //   84: iload_3
    //   85: istore_1
    //   86: goto +215 -> 301
    //   89: aload_0
    //   90: invokevirtual 104	[C:clone	()Ljava/lang/Object;
    //   93: checkcast 100	[C
    //   96: astore_0
    //   97: aload 4
    //   99: invokevirtual 104	[C:clone	()Ljava/lang/Object;
    //   102: checkcast 100	[C
    //   105: astore 4
    //   107: aload_0
    //   108: iconst_0
    //   109: aload_0
    //   110: iconst_0
    //   111: caload
    //   112: iload_1
    //   113: ixor
    //   114: i2c
    //   115: castore
    //   116: aload 4
    //   118: iconst_2
    //   119: aload 4
    //   121: iconst_2
    //   122: caload
    //   123: iload_3
    //   124: i2c
    //   125: iadd
    //   126: i2c
    //   127: castore
    //   128: aload_2
    //   129: arraylength
    //   130: istore 5
    //   132: iload 5
    //   134: newarray char
    //   136: astore 13
    //   138: iconst_0
    //   139: istore_1
    //   140: goto +161 -> 301
    //   143: bipush 93
    //   145: istore_1
    //   146: goto -143 -> 3
    //   149: getstatic 25	o/Hu:ʻ	I
    //   152: bipush 57
    //   154: iadd
    //   155: istore 5
    //   157: iload 5
    //   159: sipush 128
    //   162: irem
    //   163: putstatic 23	o/Hu:ᐝ	I
    //   166: iload 5
    //   168: iconst_2
    //   169: irem
    //   170: ifeq +6 -> 176
    //   173: goto -129 -> 44
    //   176: goto -87 -> 89
    //   179: new 55	java/lang/String
    //   182: dup
    //   183: aload 13
    //   185: invokespecial 107	java/lang/String:<init>	([C)V
    //   188: areturn
    //   189: getstatic 23	o/Hu:ᐝ	I
    //   192: bipush 117
    //   194: iadd
    //   195: istore_1
    //   196: iload_1
    //   197: sipush 128
    //   200: irem
    //   201: putstatic 25	o/Hu:ʻ	I
    //   204: iload_1
    //   205: iconst_2
    //   206: irem
    //   207: ifne +6 -> 213
    //   210: goto -67 -> 143
    //   213: goto -175 -> 38
    //   216: astore_0
    //   217: aload_0
    //   218: athrow
    //   219: iconst_3
    //   220: istore_3
    //   221: goto -174 -> 47
    //   224: bipush 58
    //   226: istore_3
    //   227: goto -180 -> 47
    //   230: goto -81 -> 149
    //   233: aload_0
    //   234: aload 4
    //   236: iload_1
    //   237: invokestatic 112	o/oJ:ˏ	([C[CI)V
    //   240: aload_2
    //   241: iload_1
    //   242: caload
    //   243: istore_3
    //   244: aload_0
    //   245: iload_1
    //   246: iconst_3
    //   247: iadd
    //   248: iconst_4
    //   249: irem
    //   250: caload
    //   251: istore 6
    //   253: iload_3
    //   254: iload 6
    //   256: ixor
    //   257: i2l
    //   258: lstore 7
    //   260: getstatic 96	o/Hu:ˊ	J
    //   263: lstore 9
    //   265: getstatic 98	o/Hu:ˋ	I
    //   268: istore_3
    //   269: iload_3
    //   270: i2l
    //   271: lstore 11
    //   273: getstatic 92	o/Hu:ˎ	C
    //   276: istore_3
    //   277: aload 13
    //   279: iload_1
    //   280: lload 7
    //   282: lload 9
    //   284: lxor
    //   285: lload 11
    //   287: lxor
    //   288: iload_3
    //   289: i2l
    //   290: lxor
    //   291: l2i
    //   292: i2c
    //   293: castore
    //   294: iload_1
    //   295: iconst_1
    //   296: iadd
    //   297: istore_3
    //   298: goto -109 -> 189
    //   301: iload_1
    //   302: iload 5
    //   304: if_icmpge +6 -> 310
    //   307: goto -83 -> 224
    //   310: goto -91 -> 219
    // Local variable table:
    //   start	length	slot	name	signature
    //   0	313	0	paramArrayOfChar1	char[]
    //   0	313	1	paramChar	char
    //   0	313	2	paramArrayOfChar2	char[]
    //   0	313	3	paramInt	int
    //   0	313	4	paramArrayOfChar3	char[]
    //   130	175	5	c	char
    //   251	6	6	i	int
    //   258	23	7	l1	long
    //   263	20	9	l2	long
    //   271	15	11	l3	long
    //   136	142	13	arrayOfChar	char[]
    // Exception table:
    //   from	to	target	type
    //   233	240	35	java/lang/Exception
    //   260	265	35	java/lang/Exception
    //   265	269	35	java/lang/Exception
    //   273	277	35	java/lang/Exception
    //   260	265	216	java/lang/Exception
  }
  
  /* Error */
  private String ˏ(String paramString)
  {
    // Byte code:
    //   0: goto +28 -> 28
    //   3: astore_1
    //   4: new 117	java/lang/RuntimeException
    //   7: dup
    //   8: aload_1
    //   9: invokespecial 120	java/lang/RuntimeException:<init>	(Ljava/lang/Throwable;)V
    //   12: athrow
    //   13: aload 4
    //   15: arraylength
    //   16: istore_3
    //   17: iload_2
    //   18: iload_3
    //   19: if_icmpge +6 -> 25
    //   22: goto +514 -> 536
    //   25: goto +342 -> 367
    //   28: getstatic 25	o/Hu:ʻ	I
    //   31: bipush 125
    //   33: iadd
    //   34: istore_2
    //   35: iload_2
    //   36: sipush 128
    //   39: irem
    //   40: putstatic 23	o/Hu:ᐝ	I
    //   43: iload_2
    //   44: iconst_2
    //   45: irem
    //   46: ifeq +6 -> 52
    //   49: goto +6 -> 55
    //   52: goto +325 -> 377
    //   55: aload_1
    //   56: iconst_4
    //   57: newarray char
    //   59: dup
    //   60: iconst_0
    //   61: ldc 121
    //   63: castore
    //   64: dup
    //   65: iconst_1
    //   66: ldc 122
    //   68: castore
    //   69: dup
    //   70: iconst_2
    //   71: ldc 123
    //   73: castore
    //   74: dup
    //   75: iconst_3
    //   76: ldc 124
    //   78: castore
    //   79: iconst_0
    //   80: bipush 10
    //   82: newarray char
    //   84: dup
    //   85: iconst_0
    //   86: ldc 125
    //   88: castore
    //   89: dup
    //   90: iconst_1
    //   91: ldc 126
    //   93: castore
    //   94: dup
    //   95: iconst_2
    //   96: ldc 127
    //   98: castore
    //   99: dup
    //   100: iconst_3
    //   101: ldc -128
    //   103: castore
    //   104: dup
    //   105: iconst_4
    //   106: ldc -127
    //   108: castore
    //   109: dup
    //   110: iconst_5
    //   111: ldc -126
    //   113: castore
    //   114: dup
    //   115: bipush 6
    //   117: ldc -125
    //   119: castore
    //   120: dup
    //   121: bipush 7
    //   123: ldc -124
    //   125: castore
    //   126: dup
    //   127: bipush 8
    //   129: ldc -123
    //   131: castore
    //   132: dup
    //   133: bipush 9
    //   135: ldc -122
    //   137: castore
    //   138: iconst_1
    //   139: iconst_4
    //   140: newarray char
    //   142: dup
    //   143: iconst_0
    //   144: ldc 47
    //   146: castore
    //   147: dup
    //   148: iconst_1
    //   149: ldc 48
    //   151: castore
    //   152: dup
    //   153: iconst_2
    //   154: ldc 49
    //   156: castore
    //   157: dup
    //   158: iconst_3
    //   159: ldc 50
    //   161: castore
    //   162: invokestatic 53	o/Hu:ˋ	([CC[CI[C)Ljava/lang/String;
    //   165: invokevirtual 59	java/lang/String:intern	()Ljava/lang/String;
    //   168: invokevirtual 138	java/lang/String:getBytes	(Ljava/lang/String;)[B
    //   171: astore 4
    //   173: aload 4
    //   175: arraylength
    //   176: newarray byte
    //   178: astore_1
    //   179: iconst_0
    //   180: istore_2
    //   181: goto -168 -> 13
    //   184: iload_3
    //   185: tableswitch	default:+23->208, 0:+321->506, 1:+58->243
    //   208: goto +298 -> 506
    //   211: getstatic 25	o/Hu:ʻ	I
    //   214: bipush 111
    //   216: iadd
    //   217: istore_2
    //   218: iload_2
    //   219: sipush 128
    //   222: irem
    //   223: putstatic 23	o/Hu:ᐝ	I
    //   226: iload_2
    //   227: iconst_2
    //   228: irem
    //   229: ifeq +6 -> 235
    //   232: goto +6 -> 238
    //   235: goto +306 -> 541
    //   238: iconst_1
    //   239: istore_2
    //   240: goto +99 -> 339
    //   243: new 55	java/lang/String
    //   246: dup
    //   247: aload_1
    //   248: iconst_4
    //   249: newarray char
    //   251: dup
    //   252: iconst_0
    //   253: ldc -117
    //   255: castore
    //   256: dup
    //   257: iconst_1
    //   258: ldc -116
    //   260: castore
    //   261: dup
    //   262: iconst_2
    //   263: ldc -115
    //   265: castore
    //   266: dup
    //   267: iconst_3
    //   268: ldc -114
    //   270: castore
    //   271: sipush 28947
    //   274: iconst_5
    //   275: newarray char
    //   277: dup
    //   278: iconst_0
    //   279: ldc -113
    //   281: castore
    //   282: dup
    //   283: iconst_1
    //   284: ldc -112
    //   286: castore
    //   287: dup
    //   288: iconst_2
    //   289: ldc -111
    //   291: castore
    //   292: dup
    //   293: iconst_3
    //   294: ldc -110
    //   296: castore
    //   297: dup
    //   298: iconst_4
    //   299: ldc -109
    //   301: castore
    //   302: ldc -108
    //   304: iconst_4
    //   305: newarray char
    //   307: dup
    //   308: iconst_0
    //   309: ldc 47
    //   311: castore
    //   312: dup
    //   313: iconst_1
    //   314: ldc 48
    //   316: castore
    //   317: dup
    //   318: iconst_2
    //   319: ldc 49
    //   321: castore
    //   322: dup
    //   323: iconst_3
    //   324: ldc 50
    //   326: castore
    //   327: invokestatic 53	o/Hu:ˋ	([CC[CI[C)Ljava/lang/String;
    //   330: invokevirtual 59	java/lang/String:intern	()Ljava/lang/String;
    //   333: invokespecial 151	java/lang/String:<init>	([BLjava/lang/String;)V
    //   336: astore_1
    //   337: aload_1
    //   338: areturn
    //   339: iload_2
    //   340: tableswitch	default:+24->364, 0:+32->372, 1:+191->531
    //   364: goto +167 -> 531
    //   367: iconst_1
    //   368: istore_3
    //   369: goto -185 -> 184
    //   372: iload_3
    //   373: istore_2
    //   374: goto -361 -> 13
    //   377: aload_1
    //   378: iconst_4
    //   379: newarray char
    //   381: dup
    //   382: iconst_0
    //   383: ldc 121
    //   385: castore
    //   386: dup
    //   387: iconst_1
    //   388: ldc 122
    //   390: castore
    //   391: dup
    //   392: iconst_2
    //   393: ldc 123
    //   395: castore
    //   396: dup
    //   397: iconst_3
    //   398: ldc 124
    //   400: castore
    //   401: iconst_0
    //   402: bipush 10
    //   404: newarray char
    //   406: dup
    //   407: iconst_0
    //   408: ldc 125
    //   410: castore
    //   411: dup
    //   412: iconst_1
    //   413: ldc 126
    //   415: castore
    //   416: dup
    //   417: iconst_2
    //   418: ldc 127
    //   420: castore
    //   421: dup
    //   422: iconst_3
    //   423: ldc -128
    //   425: castore
    //   426: dup
    //   427: iconst_4
    //   428: ldc -127
    //   430: castore
    //   431: dup
    //   432: iconst_5
    //   433: ldc -126
    //   435: castore
    //   436: dup
    //   437: bipush 6
    //   439: ldc -125
    //   441: castore
    //   442: dup
    //   443: bipush 7
    //   445: ldc -124
    //   447: castore
    //   448: dup
    //   449: bipush 8
    //   451: ldc -123
    //   453: castore
    //   454: dup
    //   455: bipush 9
    //   457: ldc -122
    //   459: castore
    //   460: iconst_0
    //   461: iconst_4
    //   462: newarray char
    //   464: dup
    //   465: iconst_0
    //   466: ldc 47
    //   468: castore
    //   469: dup
    //   470: iconst_1
    //   471: ldc 48
    //   473: castore
    //   474: dup
    //   475: iconst_2
    //   476: ldc 49
    //   478: castore
    //   479: dup
    //   480: iconst_3
    //   481: ldc 50
    //   483: castore
    //   484: invokestatic 53	o/Hu:ˋ	([CC[CI[C)Ljava/lang/String;
    //   487: invokevirtual 59	java/lang/String:intern	()Ljava/lang/String;
    //   490: invokevirtual 138	java/lang/String:getBytes	(Ljava/lang/String;)[B
    //   493: astore 4
    //   495: aload 4
    //   497: arraylength
    //   498: newarray byte
    //   500: astore_1
    //   501: iconst_0
    //   502: istore_2
    //   503: goto -490 -> 13
    //   506: aload_1
    //   507: iload_2
    //   508: aload 4
    //   510: aload 4
    //   512: arraylength
    //   513: iload_2
    //   514: isub
    //   515: iconst_1
    //   516: isub
    //   517: baload
    //   518: getstatic 29	o/Hu:ˏ	B
    //   521: ixor
    //   522: i2b
    //   523: bastore
    //   524: iload_2
    //   525: iconst_1
    //   526: iadd
    //   527: istore_3
    //   528: goto -317 -> 211
    //   531: iload_3
    //   532: istore_2
    //   533: goto -520 -> 13
    //   536: iconst_0
    //   537: istore_3
    //   538: goto -354 -> 184
    //   541: iconst_0
    //   542: istore_2
    //   543: goto -204 -> 339
    // Local variable table:
    //   start	length	slot	name	signature
    //   0	546	0	this	Hu
    //   0	546	1	paramString	String
    //   17	526	2	i	int
    //   16	522	3	j	int
    //   13	498	4	arrayOfByte	byte[]
    // Exception table:
    //   from	to	target	type
    //   13	17	3	java/io/UnsupportedEncodingException
    //   55	179	3	java/io/UnsupportedEncodingException
    //   243	337	3	java/io/UnsupportedEncodingException
    //   377	501	3	java/io/UnsupportedEncodingException
    //   506	524	3	java/io/UnsupportedEncodingException
  }
  
  public final String ˎ()
  {
    for (;;)
    {
      String str = this.ॱ;
      int i = ʻ + 81;
      ᐝ = i % 128;
      if (i % 2 != 0) {
        return str;
      }
      return str;
      i = ʻ + 35;
      ᐝ = i % 128;
      if (i % 2 != 0) {}
    }
  }
  
  public abstract void ˎ(MatrixHCECard paramMatrixHCECard);
  
  /* Error */
  public void ˎ(Cv<Void> paramCv, Fg paramFg)
  {
    // Byte code:
    //   0: goto +9 -> 9
    //   3: goto +214 -> 217
    //   6: astore_1
    //   7: aload_1
    //   8: athrow
    //   9: getstatic 23	o/Hu:ᐝ	I
    //   12: bipush 33
    //   14: iadd
    //   15: istore_3
    //   16: iload_3
    //   17: sipush 128
    //   20: irem
    //   21: putstatic 25	o/Hu:ʻ	I
    //   24: iload_3
    //   25: iconst_2
    //   26: irem
    //   27: ifne +6 -> 33
    //   30: goto +221 -> 251
    //   33: goto +274 -> 307
    //   36: iconst_0
    //   37: istore_3
    //   38: goto +9 -> 47
    //   41: bipush 93
    //   43: istore_3
    //   44: goto +232 -> 276
    //   47: aload_2
    //   48: astore_1
    //   49: iload_3
    //   50: tableswitch	default:+22->72, 0:+184->234, 1:+273->323
    //   72: goto +162 -> 234
    //   75: bipush 7
    //   77: istore_3
    //   78: iload_3
    //   79: lookupswitch	default:+25->104, 7:+171->250, 26:+287->366
    //   104: goto +262 -> 366
    //   107: aload_0
    //   108: invokevirtual 157	o/Hu:ʽ	()Landroid/content/Context;
    //   111: astore_1
    //   112: getstatic 162	o/DY$If:an_error_occurred	I
    //   115: istore_3
    //   116: aload_1
    //   117: iload_3
    //   118: invokevirtual 168	android/content/Context:getString	(I)Ljava/lang/String;
    //   121: astore_2
    //   122: aload_2
    //   123: iconst_4
    //   124: newarray char
    //   126: dup
    //   127: iconst_0
    //   128: ldc -87
    //   130: castore
    //   131: dup
    //   132: iconst_1
    //   133: ldc -86
    //   135: castore
    //   136: dup
    //   137: iconst_2
    //   138: ldc -85
    //   140: castore
    //   141: dup
    //   142: iconst_3
    //   143: ldc -84
    //   145: castore
    //   146: ldc -83
    //   148: iconst_4
    //   149: newarray char
    //   151: dup
    //   152: iconst_0
    //   153: ldc -82
    //   155: castore
    //   156: dup
    //   157: iconst_1
    //   158: ldc -81
    //   160: castore
    //   161: dup
    //   162: iconst_2
    //   163: ldc -80
    //   165: castore
    //   166: dup
    //   167: iconst_3
    //   168: ldc -79
    //   170: castore
    //   171: iconst_0
    //   172: iconst_4
    //   173: newarray char
    //   175: dup
    //   176: iconst_0
    //   177: ldc 47
    //   179: castore
    //   180: dup
    //   181: iconst_1
    //   182: ldc 48
    //   184: castore
    //   185: dup
    //   186: iconst_2
    //   187: ldc 49
    //   189: castore
    //   190: dup
    //   191: iconst_3
    //   192: ldc 50
    //   194: castore
    //   195: invokestatic 53	o/Hu:ˋ	([CC[CI[C)Ljava/lang/String;
    //   198: invokevirtual 59	java/lang/String:intern	()Ljava/lang/String;
    //   201: invokevirtual 181	java/lang/String:startsWith	(Ljava/lang/String;)Z
    //   204: istore 4
    //   206: iload 4
    //   208: ifeq +6 -> 214
    //   211: goto -175 -> 36
    //   214: goto +117 -> 331
    //   217: goto +122 -> 339
    //   220: aload_0
    //   221: aload_2
    //   222: getfield 187	o/Fg:error	Lo/Fd;
    //   225: getfield 192	o/Fd:message	Ljava/lang/String;
    //   228: invokevirtual 195	o/Hu:ॱ	(Ljava/lang/String;)V
    //   231: goto -14 -> 217
    //   234: aload_0
    //   235: aload_2
    //   236: iconst_4
    //   237: invokevirtual 198	java/lang/String:substring	(I)Ljava/lang/String;
    //   240: invokespecial 200	o/Hu:ˏ	(Ljava/lang/String;)Ljava/lang/String;
    //   243: invokevirtual 59	java/lang/String:intern	()Ljava/lang/String;
    //   246: astore_1
    //   247: goto +76 -> 323
    //   250: return
    //   251: aload_0
    //   252: aload_1
    //   253: aload_2
    //   254: invokespecial 202	o/Ik:ˎ	(Lo/Cv;Lo/Fg;)V
    //   257: aconst_null
    //   258: arraylength
    //   259: istore_3
    //   260: aload_2
    //   261: ifnull +6 -> 267
    //   264: goto -44 -> 220
    //   267: goto -160 -> 107
    //   270: bipush 26
    //   272: istore_3
    //   273: goto -195 -> 78
    //   276: iload_3
    //   277: lookupswitch	default:+27->304, 84:+-57->220, 93:+-170->107
    //   304: goto -197 -> 107
    //   307: aload_0
    //   308: aload_1
    //   309: aload_2
    //   310: invokespecial 202	o/Ik:ˎ	(Lo/Cv;Lo/Fg;)V
    //   313: aload_2
    //   314: ifnull +6 -> 320
    //   317: goto +55 -> 372
    //   320: goto -279 -> 41
    //   323: aload_0
    //   324: aload_1
    //   325: invokevirtual 195	o/Hu:ॱ	(Ljava/lang/String;)V
    //   328: goto -325 -> 3
    //   331: iconst_1
    //   332: istore_3
    //   333: goto -286 -> 47
    //   336: astore_1
    //   337: aload_1
    //   338: athrow
    //   339: getstatic 23	o/Hu:ᐝ	I
    //   342: bipush 59
    //   344: iadd
    //   345: istore_3
    //   346: iload_3
    //   347: sipush 128
    //   350: irem
    //   351: putstatic 25	o/Hu:ʻ	I
    //   354: iload_3
    //   355: iconst_2
    //   356: irem
    //   357: ifne +6 -> 363
    //   360: goto -90 -> 270
    //   363: goto -288 -> 75
    //   366: bipush 61
    //   368: iconst_0
    //   369: idiv
    //   370: istore_3
    //   371: return
    //   372: bipush 84
    //   374: istore_3
    //   375: goto -99 -> 276
    // Local variable table:
    //   start	length	slot	name	signature
    //   0	378	0	this	Hu
    //   0	378	1	paramCv	Cv<Void>
    //   0	378	2	paramFg	Fg
    //   15	360	3	i	int
    //   204	3	4	bool	boolean
    // Exception table:
    //   from	to	target	type
    //   112	116	6	java/lang/Exception
    //   9	16	336	java/lang/Exception
    //   16	24	336	java/lang/Exception
    //   107	112	336	java/lang/Exception
    //   116	206	336	java/lang/Exception
  }
  
  public abstract void ॱ(String paramString);
  
  /* Error */
  protected void ॱ(final Void paramVoid)
  {
    // Byte code:
    //   0: goto +628 -> 628
    //   3: goto +631 -> 634
    //   6: aload_1
    //   7: invokeinterface 216 1 0
    //   12: getstatic 222	com/insidesecure/hce/MatrixHCECardState:UNINITIALIZED	Lcom/insidesecure/hce/MatrixHCECardState;
    //   15: invokestatic 225	o/vq:ˊ	(Ljava/lang/Object;Ljava/lang/Object;)Z
    //   18: iconst_1
    //   19: iand
    //   20: ifeq +6 -> 26
    //   23: goto +6 -> 29
    //   26: goto +293 -> 319
    //   29: aload_1
    //   30: new 7	o/Hu$If
    //   33: dup
    //   34: aload_0
    //   35: aload_1
    //   36: iconst_4
    //   37: newarray char
    //   39: dup
    //   40: iconst_0
    //   41: ldc -30
    //   43: castore
    //   44: dup
    //   45: iconst_1
    //   46: ldc -29
    //   48: castore
    //   49: dup
    //   50: iconst_2
    //   51: ldc -28
    //   53: castore
    //   54: dup
    //   55: iconst_3
    //   56: ldc -27
    //   58: castore
    //   59: sipush 16188
    //   62: bipush 6
    //   64: newarray char
    //   66: dup
    //   67: iconst_0
    //   68: ldc -26
    //   70: castore
    //   71: dup
    //   72: iconst_1
    //   73: ldc -25
    //   75: castore
    //   76: dup
    //   77: iconst_2
    //   78: ldc -24
    //   80: castore
    //   81: dup
    //   82: iconst_3
    //   83: ldc -23
    //   85: castore
    //   86: dup
    //   87: iconst_4
    //   88: ldc -22
    //   90: castore
    //   91: dup
    //   92: iconst_5
    //   93: ldc -21
    //   95: castore
    //   96: iconst_0
    //   97: iconst_4
    //   98: newarray char
    //   100: dup
    //   101: iconst_0
    //   102: ldc 47
    //   104: castore
    //   105: dup
    //   106: iconst_1
    //   107: ldc 48
    //   109: castore
    //   110: dup
    //   111: iconst_2
    //   112: ldc 49
    //   114: castore
    //   115: dup
    //   116: iconst_3
    //   117: ldc 50
    //   119: castore
    //   120: invokestatic 53	o/Hu:ˋ	([CC[CI[C)Ljava/lang/String;
    //   123: invokevirtual 59	java/lang/String:intern	()Ljava/lang/String;
    //   126: invokespecial 238	o/Hu$If:<init>	(Lo/Hu;Lcom/insidesecure/hce/MatrixHCECard;Ljava/lang/String;)V
    //   129: checkcast 240	com/insidesecure/hce/MatrixHCENetworkOperationCallback
    //   132: iconst_4
    //   133: newarray char
    //   135: dup
    //   136: iconst_0
    //   137: ldc -15
    //   139: castore
    //   140: dup
    //   141: iconst_1
    //   142: ldc -14
    //   144: castore
    //   145: dup
    //   146: iconst_2
    //   147: ldc -13
    //   149: castore
    //   150: dup
    //   151: iconst_3
    //   152: ldc -12
    //   154: castore
    //   155: sipush 23444
    //   158: bipush 18
    //   160: newarray char
    //   162: dup
    //   163: iconst_0
    //   164: ldc -11
    //   166: castore
    //   167: dup
    //   168: iconst_1
    //   169: ldc -10
    //   171: castore
    //   172: dup
    //   173: iconst_2
    //   174: ldc -9
    //   176: castore
    //   177: dup
    //   178: iconst_3
    //   179: ldc -8
    //   181: castore
    //   182: dup
    //   183: iconst_4
    //   184: ldc -7
    //   186: castore
    //   187: dup
    //   188: iconst_5
    //   189: ldc -6
    //   191: castore
    //   192: dup
    //   193: bipush 6
    //   195: ldc -5
    //   197: castore
    //   198: dup
    //   199: bipush 7
    //   201: ldc -4
    //   203: castore
    //   204: dup
    //   205: bipush 8
    //   207: ldc -3
    //   209: castore
    //   210: dup
    //   211: bipush 9
    //   213: ldc -2
    //   215: castore
    //   216: dup
    //   217: bipush 10
    //   219: ldc -1
    //   221: castore
    //   222: dup
    //   223: bipush 11
    //   225: ldc_w 256
    //   228: castore
    //   229: dup
    //   230: bipush 12
    //   232: ldc_w 257
    //   235: castore
    //   236: dup
    //   237: bipush 13
    //   239: ldc_w 258
    //   242: castore
    //   243: dup
    //   244: bipush 14
    //   246: ldc_w 259
    //   249: castore
    //   250: dup
    //   251: bipush 15
    //   253: ldc_w 260
    //   256: castore
    //   257: dup
    //   258: bipush 16
    //   260: ldc_w 261
    //   263: castore
    //   264: dup
    //   265: bipush 17
    //   267: ldc_w 262
    //   270: castore
    //   271: iconst_0
    //   272: iconst_4
    //   273: newarray char
    //   275: dup
    //   276: iconst_0
    //   277: ldc 47
    //   279: castore
    //   280: dup
    //   281: iconst_1
    //   282: ldc 48
    //   284: castore
    //   285: dup
    //   286: iconst_2
    //   287: ldc 49
    //   289: castore
    //   290: dup
    //   291: iconst_3
    //   292: ldc 50
    //   294: castore
    //   295: invokestatic 53	o/Hu:ˋ	([CC[CI[C)Ljava/lang/String;
    //   298: invokevirtual 59	java/lang/String:intern	()Ljava/lang/String;
    //   301: aconst_null
    //   302: invokeinterface 266 4 0
    //   307: goto +262 -> 569
    //   310: bipush 58
    //   312: istore_2
    //   313: goto +18 -> 331
    //   316: astore_1
    //   317: aload_1
    //   318: athrow
    //   319: aload_0
    //   320: aload_1
    //   321: invokevirtual 268	o/Hu:ˎ	(Lcom/insidesecure/hce/MatrixHCECard;)V
    //   324: return
    //   325: bipush 85
    //   327: istore_2
    //   328: goto +268 -> 596
    //   331: iload_2
    //   332: lookupswitch	default:+28->360, 19:+295->627, 58:+210->542
    //   360: return
    //   361: bipush 19
    //   363: istore_2
    //   364: goto -33 -> 331
    //   367: getstatic 23	o/Hu:ᐝ	I
    //   370: bipush 89
    //   372: iadd
    //   373: istore_2
    //   374: iload_2
    //   375: sipush 128
    //   378: irem
    //   379: putstatic 25	o/Hu:ʻ	I
    //   382: iload_2
    //   383: iconst_2
    //   384: irem
    //   385: ifne +6 -> 391
    //   388: goto +243 -> 631
    //   391: goto +32 -> 423
    //   394: aload_1
    //   395: invokeinterface 216 1 0
    //   400: getstatic 222	com/insidesecure/hce/MatrixHCECardState:UNINITIALIZED	Lcom/insidesecure/hce/MatrixHCECardState;
    //   403: invokestatic 225	o/vq:ˊ	(Ljava/lang/Object;Ljava/lang/Object;)Z
    //   406: iconst_1
    //   407: ixor
    //   408: ifeq +6 -> 414
    //   411: goto -382 -> 29
    //   414: goto -95 -> 319
    //   417: bipush 36
    //   419: istore_2
    //   420: goto +176 -> 596
    //   423: goto +17 -> 440
    //   426: astore_1
    //   427: aload_1
    //   428: invokevirtual 274	java/lang/Throwable:getCause	()Ljava/lang/Throwable;
    //   431: astore_3
    //   432: aload_3
    //   433: ifnull +5 -> 438
    //   436: aload_3
    //   437: athrow
    //   438: aload_1
    //   439: athrow
    //   440: iconst_4
    //   441: sipush 267
    //   444: sipush 14788
    //   447: invokestatic 279	o/O:ˋ	(IIC)Ljava/lang/Object;
    //   450: checkcast 281	java/lang/Class
    //   453: ldc_w 282
    //   456: aconst_null
    //   457: invokevirtual 286	java/lang/Class:getMethod	(Ljava/lang/String;[Ljava/lang/Class;)Ljava/lang/reflect/Method;
    //   460: aconst_null
    //   461: aconst_null
    //   462: invokevirtual 292	java/lang/reflect/Method:invoke	(Ljava/lang/Object;[Ljava/lang/Object;)Ljava/lang/Object;
    //   465: astore_1
    //   466: aload_0
    //   467: getfield 90	o/Hu:ॱ	Ljava/lang/String;
    //   470: astore_3
    //   471: goto +17 -> 488
    //   474: astore_1
    //   475: aload_1
    //   476: invokevirtual 274	java/lang/Throwable:getCause	()Ljava/lang/Throwable;
    //   479: astore_3
    //   480: aload_3
    //   481: ifnull +5 -> 486
    //   484: aload_3
    //   485: athrow
    //   486: aload_1
    //   487: athrow
    //   488: iconst_4
    //   489: sipush 267
    //   492: sipush 14788
    //   495: invokestatic 279	o/O:ˋ	(IIC)Ljava/lang/Object;
    //   498: checkcast 281	java/lang/Class
    //   501: ldc_w 293
    //   504: iconst_1
    //   505: anewarray 281	java/lang/Class
    //   508: dup
    //   509: iconst_0
    //   510: ldc 55
    //   512: aastore
    //   513: invokevirtual 286	java/lang/Class:getMethod	(Ljava/lang/String;[Ljava/lang/Class;)Ljava/lang/reflect/Method;
    //   516: aload_1
    //   517: iconst_1
    //   518: anewarray 295	java/lang/Object
    //   521: dup
    //   522: iconst_0
    //   523: aload_3
    //   524: aastore
    //   525: invokevirtual 292	java/lang/reflect/Method:invoke	(Ljava/lang/Object;[Ljava/lang/Object;)Ljava/lang/Object;
    //   528: checkcast 212	com/insidesecure/hce/MatrixHCECard
    //   531: astore_1
    //   532: aload_1
    //   533: ifnull +6 -> 539
    //   536: goto -226 -> 310
    //   539: goto -178 -> 361
    //   542: getstatic 25	o/Hu:ʻ	I
    //   545: bipush 61
    //   547: iadd
    //   548: istore_2
    //   549: iload_2
    //   550: sipush 128
    //   553: irem
    //   554: putstatic 23	o/Hu:ᐝ	I
    //   557: iload_2
    //   558: iconst_2
    //   559: irem
    //   560: ifeq +6 -> 566
    //   563: goto -238 -> 325
    //   566: goto -149 -> 417
    //   569: getstatic 25	o/Hu:ʻ	I
    //   572: bipush 123
    //   574: iadd
    //   575: istore_2
    //   576: iload_2
    //   577: sipush 128
    //   580: irem
    //   581: putstatic 23	o/Hu:ᐝ	I
    //   584: iload_2
    //   585: iconst_2
    //   586: irem
    //   587: ifeq +6 -> 593
    //   590: goto -587 -> 3
    //   593: goto +41 -> 634
    //   596: iload_2
    //   597: lookupswitch	default:+27->624, 36:+-203->394, 85:+-591->6
    //   624: goto -618 -> 6
    //   627: return
    //   628: goto -261 -> 367
    //   631: goto -208 -> 423
    //   634: return
    //   635: astore_1
    //   636: aload_1
    //   637: athrow
    // Local variable table:
    //   start	length	slot	name	signature
    //   0	638	0	this	Hu
    //   0	638	1	paramVoid	Void
    //   312	285	2	i	int
    //   431	93	3	localObject	Object
    // Exception table:
    //   from	to	target	type
    //   29	307	316	java/lang/Exception
    //   440	466	426	finally
    //   488	532	474	finally
    //   29	307	635	java/lang/Exception
    //   367	374	635	java/lang/Exception
    //   374	382	635	java/lang/Exception
  }
  
  public static final class If
    extends Ht
  {
    private static int ˊ = 0;
    private static long ˎ = 244523987554909130L;
    private static int ˏ = 1;
    
    If(MatrixHCECard paramMatrixHCECard, String paramString)
    {
      super();
    }
    
    private static String ˎ(char[] paramArrayOfChar)
    {
      break label112;
      char[] arrayOfChar;
      int i;
      label29:
      int j;
      do
      {
        k = 84;
        break;
        arrayOfChar = paramArrayOfChar;
        i = arrayOfChar[0];
        arrayOfChar = new char[arrayOfChar.length - 1];
        break label115;
      } while (j < paramArrayOfChar.length);
      int k = 6;
      switch (k)
      {
      default: 
        break label201;
        i = 78;
        break;
        label77:
        i = 2;
        break;
      }
      for (;;)
      {
        label82:
        arrayOfChar[(j - 1)] = ((char)(int)(paramArrayOfChar[j] ^ j * i ^ ˎ));
        j += 1;
        label112:
        label115:
        label201:
        do
        {
          break label82;
          for (;;)
          {
            j = 1;
            break label29;
            switch (i)
            {
            case 78: 
            default: 
              break;
              i = ˊ + 79;
              ˏ = i % 128;
              if (i % 2 == 0) {
                break label77;
              }
              break;
            case 2: 
              arrayOfChar = paramArrayOfChar;
              i = arrayOfChar[1];
              arrayOfChar = new char[arrayOfChar.length % 0];
            }
          }
          break label29;
          return new String(arrayOfChar);
          k = ˏ + 105;
          ˊ = k % 128;
        } while (k % 2 != 0);
      }
    }
    
    /* Error */
    public void onError(com.insidesecure.hce.NetworkOperationResponseInfo paramNetworkOperationResponseInfo)
    {
      // Byte code:
      //   0: goto +8 -> 8
      //   3: iconst_1
      //   4: istore_2
      //   5: goto +184 -> 189
      //   8: goto +141 -> 149
      //   11: getstatic 23	o/Hu$If:ˏ	I
      //   14: bipush 43
      //   16: iadd
      //   17: istore_2
      //   18: iload_2
      //   19: sipush 128
      //   22: irem
      //   23: putstatic 21	o/Hu$If:ˊ	I
      //   26: iload_2
      //   27: iconst_2
      //   28: irem
      //   29: ifeq +6 -> 35
      //   32: goto -29 -> 3
      //   35: goto +152 -> 187
      //   38: astore_1
      //   39: aload_1
      //   40: athrow
      //   41: aload_1
      //   42: bipush 13
      //   44: newarray char
      //   46: dup
      //   47: iconst_0
      //   48: ldc 50
      //   50: castore
      //   51: dup
      //   52: iconst_1
      //   53: ldc 51
      //   55: castore
      //   56: dup
      //   57: iconst_2
      //   58: ldc 52
      //   60: castore
      //   61: dup
      //   62: iconst_3
      //   63: ldc 53
      //   65: castore
      //   66: dup
      //   67: iconst_4
      //   68: ldc 54
      //   70: castore
      //   71: dup
      //   72: iconst_5
      //   73: ldc 55
      //   75: castore
      //   76: dup
      //   77: bipush 6
      //   79: ldc 56
      //   81: castore
      //   82: dup
      //   83: bipush 7
      //   85: ldc 57
      //   87: castore
      //   88: dup
      //   89: bipush 8
      //   91: ldc 58
      //   93: castore
      //   94: dup
      //   95: bipush 9
      //   97: ldc 59
      //   99: castore
      //   100: dup
      //   101: bipush 10
      //   103: ldc 60
      //   105: castore
      //   106: dup
      //   107: bipush 11
      //   109: ldc 61
      //   111: castore
      //   112: dup
      //   113: bipush 12
      //   115: ldc 62
      //   117: castore
      //   118: invokestatic 64	o/Hu$If:ˎ	([C)Ljava/lang/String;
      //   121: invokevirtual 68	java/lang/String:intern	()Ljava/lang/String;
      //   124: invokestatic 73	o/vq:ˎ	(Ljava/lang/Object;Ljava/lang/String;)V
      //   127: aload_0
      //   128: aload_1
      //   129: invokespecial 75	o/Ht:onError	(Lcom/insidesecure/hce/NetworkOperationResponseInfo;)V
      //   132: aload_0
      //   133: getfield 32	o/Hu$If:ˋ	Lo/Hu;
      //   136: aload_1
      //   137: getfield 81	com/insidesecure/hce/NetworkOperationResponseInfo:responseData	Ljava/lang/String;
      //   140: invokevirtual 83	o/Hu:ॱ	(Ljava/lang/String;)V
      //   143: goto -132 -> 11
      //   146: goto -105 -> 41
      //   149: getstatic 21	o/Hu$If:ˊ	I
      //   152: istore_2
      //   153: iload_2
      //   154: bipush 97
      //   156: iadd
      //   157: istore_2
      //   158: iload_2
      //   159: sipush 128
      //   162: irem
      //   163: putstatic 23	o/Hu$If:ˏ	I
      //   166: iload_2
      //   167: iconst_2
      //   168: irem
      //   169: ifne +6 -> 175
      //   172: goto -26 -> 146
      //   175: goto -134 -> 41
      //   178: new 85	java/lang/NullPointerException
      //   181: dup
      //   182: invokespecial 87	java/lang/NullPointerException:<init>	()V
      //   185: athrow
      //   186: return
      //   187: iconst_0
      //   188: istore_2
      //   189: iload_2
      //   190: tableswitch	default:+22->212, 0:+-4->186, 1:+-12->178
      //   212: goto -34 -> 178
      // Local variable table:
      //   start	length	slot	name	signature
      //   0	215	0	this	If
      //   0	215	1	paramNetworkOperationResponseInfo	com.insidesecure.hce.NetworkOperationResponseInfo
      //   4	186	2	i	int
      // Exception table:
      //   from	to	target	type
      //   149	153	38	java/lang/Exception
      //   158	166	38	java/lang/Exception
    }
    
    public void onFailure(FailureInfo paramFailureInfo)
    {
      break label137;
      int i = 1;
      break label112;
      label8:
      i = ˏ + 117;
      ˊ = i % 128;
      if (i % 2 == 0) {
        break label35;
      }
      label35:
      vq.ˎ(paramFailureInfo, ˎ(new char[] { 19661, -2187, 8757, 24012, -30579, 15268, 30570 }).intern());
      super.onFailure(paramFailureInfo);
      this.ˋ.ॱ(paramFailureInfo.reason);
      break label140;
      i = 0 / 0;
      return;
      return;
      for (;;)
      {
        i = 0;
        label112:
        switch (i)
        {
        }
        return;
        label137:
        break label8;
        label140:
        i = ˊ + 11;
        ˏ = i % 128;
        if (i % 2 == 0) {
          break;
        }
      }
    }
    
    /* Error */
    public void onSuccess(com.insidesecure.hce.NetworkOperationResponseInfo paramNetworkOperationResponseInfo)
    {
      // Byte code:
      //   0: goto +716 -> 716
      //   3: iconst_4
      //   4: sipush 362
      //   7: ldc 105
      //   9: invokestatic 110	o/O:ˋ	(IIC)Ljava/lang/Object;
      //   12: checkcast 112	java/lang/Class
      //   15: ldc 113
      //   17: invokevirtual 117	java/lang/Class:getField	(Ljava/lang/String;)Ljava/lang/reflect/Field;
      //   20: aconst_null
      //   21: invokevirtual 123	java/lang/reflect/Field:get	(Ljava/lang/Object;)Ljava/lang/Object;
      //   24: astore_1
      //   25: goto +17 -> 42
      //   28: astore_3
      //   29: aload_3
      //   30: invokevirtual 129	java/lang/Throwable:getCause	()Ljava/lang/Throwable;
      //   33: astore_1
      //   34: aload_1
      //   35: ifnull +5 -> 40
      //   38: aload_1
      //   39: athrow
      //   40: aload_3
      //   41: athrow
      //   42: bipush 7
      //   44: sipush 366
      //   47: iconst_0
      //   48: invokestatic 110	o/O:ˋ	(IIC)Ljava/lang/Object;
      //   51: checkcast 112	java/lang/Class
      //   54: ldc -126
      //   56: aconst_null
      //   57: invokevirtual 134	java/lang/Class:getMethod	(Ljava/lang/String;[Ljava/lang/Class;)Ljava/lang/reflect/Method;
      //   60: aload_1
      //   61: aconst_null
      //   62: invokevirtual 140	java/lang/reflect/Method:invoke	(Ljava/lang/Object;[Ljava/lang/Object;)Ljava/lang/Object;
      //   65: astore_1
      //   66: aload_0
      //   67: getfield 32	o/Hu$If:ˋ	Lo/Hu;
      //   70: invokevirtual 142	o/Hu:ˎ	()Ljava/lang/String;
      //   73: astore_3
      //   74: goto +17 -> 91
      //   77: astore_1
      //   78: aload_1
      //   79: invokevirtual 129	java/lang/Throwable:getCause	()Ljava/lang/Throwable;
      //   82: astore_3
      //   83: aload_3
      //   84: ifnull +5 -> 89
      //   87: aload_3
      //   88: athrow
      //   89: aload_1
      //   90: athrow
      //   91: iconst_4
      //   92: sipush 362
      //   95: ldc 105
      //   97: invokestatic 110	o/O:ˋ	(IIC)Ljava/lang/Object;
      //   100: checkcast 112	java/lang/Class
      //   103: ldc -112
      //   105: iconst_1
      //   106: anewarray 112	java/lang/Class
      //   109: dup
      //   110: iconst_0
      //   111: ldc 42
      //   113: aastore
      //   114: invokevirtual 134	java/lang/Class:getMethod	(Ljava/lang/String;[Ljava/lang/Class;)Ljava/lang/reflect/Method;
      //   117: aload_1
      //   118: iconst_1
      //   119: anewarray 146	java/lang/Object
      //   122: dup
      //   123: iconst_0
      //   124: aload_3
      //   125: aastore
      //   126: invokevirtual 140	java/lang/reflect/Method:invoke	(Ljava/lang/Object;[Ljava/lang/Object;)Ljava/lang/Object;
      //   129: pop
      //   130: aload_0
      //   131: getfield 32	o/Hu$If:ˋ	Lo/Hu;
      //   134: aload_0
      //   135: getfield 34	o/Hu$If:ॱ	Lcom/insidesecure/hce/MatrixHCECard;
      //   138: invokevirtual 149	o/Hu:ˎ	(Lcom/insidesecure/hce/MatrixHCECard;)V
      //   141: goto +294 -> 435
      //   144: aload_0
      //   145: getfield 34	o/Hu$If:ॱ	Lcom/insidesecure/hce/MatrixHCECard;
      //   148: invokestatic 154	o/HQ:ˏ	(Lcom/insidesecure/hce/MatrixHCECard;)Lo/HQ;
      //   151: astore_1
      //   152: aload_1
      //   153: bipush 37
      //   155: newarray char
      //   157: dup
      //   158: iconst_0
      //   159: ldc -101
      //   161: castore
      //   162: dup
      //   163: iconst_1
      //   164: ldc -100
      //   166: castore
      //   167: dup
      //   168: iconst_2
      //   169: ldc -99
      //   171: castore
      //   172: dup
      //   173: iconst_3
      //   174: ldc -98
      //   176: castore
      //   177: dup
      //   178: iconst_4
      //   179: ldc -97
      //   181: castore
      //   182: dup
      //   183: iconst_5
      //   184: ldc -96
      //   186: castore
      //   187: dup
      //   188: bipush 6
      //   190: ldc -95
      //   192: castore
      //   193: dup
      //   194: bipush 7
      //   196: ldc -94
      //   198: castore
      //   199: dup
      //   200: bipush 8
      //   202: ldc -93
      //   204: castore
      //   205: dup
      //   206: bipush 9
      //   208: ldc -92
      //   210: castore
      //   211: dup
      //   212: bipush 10
      //   214: ldc -91
      //   216: castore
      //   217: dup
      //   218: bipush 11
      //   220: ldc -90
      //   222: castore
      //   223: dup
      //   224: bipush 12
      //   226: ldc -89
      //   228: castore
      //   229: dup
      //   230: bipush 13
      //   232: ldc -88
      //   234: castore
      //   235: dup
      //   236: bipush 14
      //   238: ldc -87
      //   240: castore
      //   241: dup
      //   242: bipush 15
      //   244: ldc -86
      //   246: castore
      //   247: dup
      //   248: bipush 16
      //   250: ldc -85
      //   252: castore
      //   253: dup
      //   254: bipush 17
      //   256: ldc -84
      //   258: castore
      //   259: dup
      //   260: bipush 18
      //   262: ldc -83
      //   264: castore
      //   265: dup
      //   266: bipush 19
      //   268: ldc -82
      //   270: castore
      //   271: dup
      //   272: bipush 20
      //   274: ldc -81
      //   276: castore
      //   277: dup
      //   278: bipush 21
      //   280: ldc -80
      //   282: castore
      //   283: dup
      //   284: bipush 22
      //   286: ldc -79
      //   288: castore
      //   289: dup
      //   290: bipush 23
      //   292: ldc -78
      //   294: castore
      //   295: dup
      //   296: bipush 24
      //   298: ldc -77
      //   300: castore
      //   301: dup
      //   302: bipush 25
      //   304: ldc -76
      //   306: castore
      //   307: dup
      //   308: bipush 26
      //   310: ldc -75
      //   312: castore
      //   313: dup
      //   314: bipush 27
      //   316: ldc -74
      //   318: castore
      //   319: dup
      //   320: bipush 28
      //   322: ldc -73
      //   324: castore
      //   325: dup
      //   326: bipush 29
      //   328: ldc -72
      //   330: castore
      //   331: dup
      //   332: bipush 30
      //   334: ldc -71
      //   336: castore
      //   337: dup
      //   338: bipush 31
      //   340: ldc -70
      //   342: castore
      //   343: dup
      //   344: bipush 32
      //   346: ldc -69
      //   348: castore
      //   349: dup
      //   350: bipush 33
      //   352: ldc -68
      //   354: castore
      //   355: dup
      //   356: bipush 34
      //   358: ldc -67
      //   360: castore
      //   361: dup
      //   362: bipush 35
      //   364: ldc -66
      //   366: castore
      //   367: dup
      //   368: bipush 36
      //   370: ldc -65
      //   372: castore
      //   373: invokestatic 64	o/Hu$If:ˎ	([C)Ljava/lang/String;
      //   376: invokevirtual 68	java/lang/String:intern	()Ljava/lang/String;
      //   379: invokestatic 193	o/vq:ˋ	(Ljava/lang/Object;Ljava/lang/String;)V
      //   382: aload_1
      //   383: invokevirtual 197	o/HQ:ˏॱ	()Lo/Eh;
      //   386: getstatic 203	o/Eh:VISA	Lo/Eh;
      //   389: invokestatic 206	o/vq:ˊ	(Ljava/lang/Object;Ljava/lang/Object;)Z
      //   392: ifeq +6 -> 398
      //   395: goto -392 -> 3
      //   398: goto +37 -> 435
      //   401: bipush 11
      //   403: istore_2
      //   404: iload_2
      //   405: lookupswitch	default:+27->432, 11:+340->745, 94:+72->477
      //   432: goto +313 -> 745
      //   435: return
      //   436: getstatic 21	o/Hu$If:ˊ	I
      //   439: bipush 13
      //   441: iadd
      //   442: istore_2
      //   443: iload_2
      //   444: sipush 128
      //   447: irem
      //   448: putstatic 23	o/Hu$If:ˏ	I
      //   451: iload_2
      //   452: iconst_2
      //   453: irem
      //   454: ifne +6 -> 460
      //   457: goto +14 -> 471
      //   460: goto -59 -> 401
      //   463: goto -319 -> 144
      //   466: iconst_1
      //   467: istore_2
      //   468: goto +215 -> 683
      //   471: bipush 94
      //   473: istore_2
      //   474: goto -70 -> 404
      //   477: aload_1
      //   478: bipush 29
      //   480: newarray char
      //   482: dup
      //   483: iconst_0
      //   484: ldc -49
      //   486: castore
      //   487: dup
      //   488: iconst_1
      //   489: ldc -48
      //   491: castore
      //   492: dup
      //   493: iconst_2
      //   494: ldc -47
      //   496: castore
      //   497: dup
      //   498: iconst_3
      //   499: ldc -46
      //   501: castore
      //   502: dup
      //   503: iconst_4
      //   504: ldc -45
      //   506: castore
      //   507: dup
      //   508: iconst_5
      //   509: ldc -44
      //   511: castore
      //   512: dup
      //   513: bipush 6
      //   515: ldc -43
      //   517: castore
      //   518: dup
      //   519: bipush 7
      //   521: ldc -42
      //   523: castore
      //   524: dup
      //   525: bipush 8
      //   527: ldc -41
      //   529: castore
      //   530: dup
      //   531: bipush 9
      //   533: ldc -40
      //   535: castore
      //   536: dup
      //   537: bipush 10
      //   539: ldc -39
      //   541: castore
      //   542: dup
      //   543: bipush 11
      //   545: ldc -38
      //   547: castore
      //   548: dup
      //   549: bipush 12
      //   551: ldc -37
      //   553: castore
      //   554: dup
      //   555: bipush 13
      //   557: ldc -36
      //   559: castore
      //   560: dup
      //   561: bipush 14
      //   563: ldc -35
      //   565: castore
      //   566: dup
      //   567: bipush 15
      //   569: ldc -34
      //   571: castore
      //   572: dup
      //   573: bipush 16
      //   575: ldc -33
      //   577: castore
      //   578: dup
      //   579: bipush 17
      //   581: ldc -32
      //   583: castore
      //   584: dup
      //   585: bipush 18
      //   587: ldc -31
      //   589: castore
      //   590: dup
      //   591: bipush 19
      //   593: ldc -30
      //   595: castore
      //   596: dup
      //   597: bipush 20
      //   599: ldc -29
      //   601: castore
      //   602: dup
      //   603: bipush 21
      //   605: ldc -28
      //   607: castore
      //   608: dup
      //   609: bipush 22
      //   611: ldc -27
      //   613: castore
      //   614: dup
      //   615: bipush 23
      //   617: ldc -26
      //   619: castore
      //   620: dup
      //   621: bipush 24
      //   623: ldc -25
      //   625: castore
      //   626: dup
      //   627: bipush 25
      //   629: ldc -24
      //   631: castore
      //   632: dup
      //   633: bipush 26
      //   635: ldc -23
      //   637: castore
      //   638: dup
      //   639: bipush 27
      //   641: ldc -22
      //   643: castore
      //   644: dup
      //   645: bipush 28
      //   647: ldc -21
      //   649: castore
      //   650: invokestatic 64	o/Hu$If:ˎ	([C)Ljava/lang/String;
      //   653: invokevirtual 68	java/lang/String:intern	()Ljava/lang/String;
      //   656: invokestatic 73	o/vq:ˎ	(Ljava/lang/Object;Ljava/lang/String;)V
      //   659: aload_0
      //   660: aload_1
      //   661: invokespecial 237	o/Ht:onSuccess	(Lcom/insidesecure/hce/NetworkOperationResponseInfo;)V
      //   664: aload_1
      //   665: getfield 241	com/insidesecure/hce/NetworkOperationResponseInfo:operation	Lcom/insidesecure/hce/NetworkOperationPreparationInfo$NetworkOperation;
      //   668: getstatic 246	com/insidesecure/hce/NetworkOperationPreparationInfo$NetworkOperation:MASTERCARD_DELETE	Lcom/insidesecure/hce/NetworkOperationPreparationInfo$NetworkOperation;
      //   671: invokestatic 206	o/vq:ˊ	(Ljava/lang/Object;Ljava/lang/Object;)Z
      //   674: pop
      //   675: new 85	java/lang/NullPointerException
      //   678: dup
      //   679: invokespecial 87	java/lang/NullPointerException:<init>	()V
      //   682: athrow
      //   683: iload_2
      //   684: tableswitch	default:+24->708, 0:+-681->3, 1:+35->719
      //   708: goto +11 -> 719
      //   711: iconst_0
      //   712: istore_2
      //   713: goto -30 -> 683
      //   716: goto -280 -> 436
      //   719: getstatic 23	o/Hu$If:ˏ	I
      //   722: iconst_5
      //   723: iadd
      //   724: istore_2
      //   725: iload_2
      //   726: sipush 128
      //   729: irem
      //   730: putstatic 21	o/Hu$If:ˊ	I
      //   733: iload_2
      //   734: iconst_2
      //   735: irem
      //   736: ifeq +6 -> 742
      //   739: goto -276 -> 463
      //   742: goto -598 -> 144
      //   745: aload_1
      //   746: bipush 29
      //   748: newarray char
      //   750: dup
      //   751: iconst_0
      //   752: ldc -49
      //   754: castore
      //   755: dup
      //   756: iconst_1
      //   757: ldc -48
      //   759: castore
      //   760: dup
      //   761: iconst_2
      //   762: ldc -47
      //   764: castore
      //   765: dup
      //   766: iconst_3
      //   767: ldc -46
      //   769: castore
      //   770: dup
      //   771: iconst_4
      //   772: ldc -45
      //   774: castore
      //   775: dup
      //   776: iconst_5
      //   777: ldc -44
      //   779: castore
      //   780: dup
      //   781: bipush 6
      //   783: ldc -43
      //   785: castore
      //   786: dup
      //   787: bipush 7
      //   789: ldc -42
      //   791: castore
      //   792: dup
      //   793: bipush 8
      //   795: ldc -41
      //   797: castore
      //   798: dup
      //   799: bipush 9
      //   801: ldc -40
      //   803: castore
      //   804: dup
      //   805: bipush 10
      //   807: ldc -39
      //   809: castore
      //   810: dup
      //   811: bipush 11
      //   813: ldc -38
      //   815: castore
      //   816: dup
      //   817: bipush 12
      //   819: ldc -37
      //   821: castore
      //   822: dup
      //   823: bipush 13
      //   825: ldc -36
      //   827: castore
      //   828: dup
      //   829: bipush 14
      //   831: ldc -35
      //   833: castore
      //   834: dup
      //   835: bipush 15
      //   837: ldc -34
      //   839: castore
      //   840: dup
      //   841: bipush 16
      //   843: ldc -33
      //   845: castore
      //   846: dup
      //   847: bipush 17
      //   849: ldc -32
      //   851: castore
      //   852: dup
      //   853: bipush 18
      //   855: ldc -31
      //   857: castore
      //   858: dup
      //   859: bipush 19
      //   861: ldc -30
      //   863: castore
      //   864: dup
      //   865: bipush 20
      //   867: ldc -29
      //   869: castore
      //   870: dup
      //   871: bipush 21
      //   873: ldc -28
      //   875: castore
      //   876: dup
      //   877: bipush 22
      //   879: ldc -27
      //   881: castore
      //   882: dup
      //   883: bipush 23
      //   885: ldc -26
      //   887: castore
      //   888: dup
      //   889: bipush 24
      //   891: ldc -25
      //   893: castore
      //   894: dup
      //   895: bipush 25
      //   897: ldc -24
      //   899: castore
      //   900: dup
      //   901: bipush 26
      //   903: ldc -23
      //   905: castore
      //   906: dup
      //   907: bipush 27
      //   909: ldc -22
      //   911: castore
      //   912: dup
      //   913: bipush 28
      //   915: ldc -21
      //   917: castore
      //   918: invokestatic 64	o/Hu$If:ˎ	([C)Ljava/lang/String;
      //   921: invokevirtual 68	java/lang/String:intern	()Ljava/lang/String;
      //   924: invokestatic 73	o/vq:ˎ	(Ljava/lang/Object;Ljava/lang/String;)V
      //   927: aload_0
      //   928: aload_1
      //   929: invokespecial 237	o/Ht:onSuccess	(Lcom/insidesecure/hce/NetworkOperationResponseInfo;)V
      //   932: aload_1
      //   933: getfield 241	com/insidesecure/hce/NetworkOperationResponseInfo:operation	Lcom/insidesecure/hce/NetworkOperationPreparationInfo$NetworkOperation;
      //   936: getstatic 246	com/insidesecure/hce/NetworkOperationPreparationInfo$NetworkOperation:MASTERCARD_DELETE	Lcom/insidesecure/hce/NetworkOperationPreparationInfo$NetworkOperation;
      //   939: invokestatic 206	o/vq:ˊ	(Ljava/lang/Object;Ljava/lang/Object;)Z
      //   942: ifne +6 -> 948
      //   945: goto -479 -> 466
      //   948: goto -237 -> 711
      // Local variable table:
      //   start	length	slot	name	signature
      //   0	951	0	this	If
      //   0	951	1	paramNetworkOperationResponseInfo	com.insidesecure.hce.NetworkOperationResponseInfo
      //   403	333	2	i	int
      //   28	13	3	localObject1	Object
      //   73	52	3	localObject2	Object
      // Exception table:
      //   from	to	target	type
      //   42	66	28	finally
      //   91	130	77	finally
    }
  }
}
