package o;

import java.util.Map;

public enum HZ
{
  private static final Map<Integer, HZ> ʾ;
  private static long ʿ;
  private static char[] ˈ;
  private static int ˉ;
  private static int ˊˋ = 0;
  public static final ˊ ॱᐝ;
  private final int ʼॱ;
  
  /* Error */
  static
  {
    // Byte code:
    //   0: iconst_0
    //   1: putstatic 48	o/HZ:ˊˋ	I
    //   4: iconst_1
    //   5: putstatic 50	o/HZ:ˉ	I
    //   8: goto +169 -> 177
    //   11: astore_3
    //   12: aload_3
    //   13: athrow
    //   14: iload_0
    //   15: tableswitch	default:+21->36, 0:+157->172, 1:+916->931
    //   36: goto +136 -> 172
    //   39: getstatic 50	o/HZ:ˉ	I
    //   42: bipush 21
    //   44: iadd
    //   45: istore_1
    //   46: iload_1
    //   47: sipush 128
    //   50: irem
    //   51: putstatic 48	o/HZ:ˊˋ	I
    //   54: iload_1
    //   55: iconst_2
    //   56: irem
    //   57: ifeq +6 -> 63
    //   60: goto +23 -> 83
    //   63: goto +52 -> 115
    //   66: goto +854 -> 920
    //   69: astore_3
    //   70: aload_3
    //   71: athrow
    //   72: iconst_0
    //   73: istore_0
    //   74: goto -60 -> 14
    //   77: aload 5
    //   79: putstatic 52	o/HZ:ʾ	Ljava/util/Map;
    //   82: return
    //   83: goto +32 -> 115
    //   86: iload_1
    //   87: lookupswitch	default:+25->112, 46:+-48->39, 73:+-10->77
    //   112: goto -35 -> 77
    //   115: aload 4
    //   117: iload_0
    //   118: aaload
    //   119: astore_3
    //   120: aload 5
    //   122: aload_3
    //   123: checkcast 2	o/HZ
    //   126: getfield 54	o/HZ:ʼॱ	I
    //   129: invokestatic 60	java/lang/Integer:valueOf	(I)Ljava/lang/Integer;
    //   132: aload_3
    //   133: invokeinterface 66 3 0
    //   138: pop
    //   139: iload_0
    //   140: iconst_1
    //   141: iadd
    //   142: istore_1
    //   143: getstatic 48	o/HZ:ˊˋ	I
    //   146: bipush 39
    //   148: iadd
    //   149: istore_0
    //   150: iload_0
    //   151: sipush 128
    //   154: irem
    //   155: putstatic 50	o/HZ:ˉ	I
    //   158: iload_0
    //   159: iconst_2
    //   160: irem
    //   161: ifne +6 -> 167
    //   164: goto -92 -> 72
    //   167: iconst_1
    //   168: istore_0
    //   169: goto -155 -> 14
    //   172: iload_1
    //   173: istore_0
    //   174: goto +746 -> 920
    //   177: invokestatic 68	o/HZ:ˏ	()V
    //   180: new 2	o/HZ
    //   183: dup
    //   184: iconst_0
    //   185: sipush 21815
    //   188: bipush 34
    //   190: invokestatic 71	o/HZ:ॱ	(ICI)Ljava/lang/String;
    //   193: invokevirtual 77	java/lang/String:intern	()Ljava/lang/String;
    //   196: iconst_0
    //   197: bipush 10
    //   199: invokespecial 81	o/HZ:<init>	(Ljava/lang/String;II)V
    //   202: astore_3
    //   203: aload_3
    //   204: putstatic 83	o/HZ:ॱ	Lo/HZ;
    //   207: new 2	o/HZ
    //   210: dup
    //   211: bipush 34
    //   213: ldc 84
    //   215: bipush 27
    //   217: invokestatic 71	o/HZ:ॱ	(ICI)Ljava/lang/String;
    //   220: invokevirtual 77	java/lang/String:intern	()Ljava/lang/String;
    //   223: iconst_1
    //   224: bipush 20
    //   226: invokespecial 81	o/HZ:<init>	(Ljava/lang/String;II)V
    //   229: astore 4
    //   231: aload 4
    //   233: putstatic 86	o/HZ:ˋ	Lo/HZ;
    //   236: new 2	o/HZ
    //   239: dup
    //   240: bipush 61
    //   242: iconst_0
    //   243: bipush 24
    //   245: invokestatic 71	o/HZ:ॱ	(ICI)Ljava/lang/String;
    //   248: invokevirtual 77	java/lang/String:intern	()Ljava/lang/String;
    //   251: iconst_2
    //   252: bipush 21
    //   254: invokespecial 81	o/HZ:<init>	(Ljava/lang/String;II)V
    //   257: astore 5
    //   259: aload 5
    //   261: putstatic 88	o/HZ:ˊ	Lo/HZ;
    //   264: new 2	o/HZ
    //   267: dup
    //   268: bipush 85
    //   270: ldc 89
    //   272: bipush 24
    //   274: invokestatic 71	o/HZ:ॱ	(ICI)Ljava/lang/String;
    //   277: invokevirtual 77	java/lang/String:intern	()Ljava/lang/String;
    //   280: iconst_3
    //   281: bipush 22
    //   283: invokespecial 81	o/HZ:<init>	(Ljava/lang/String;II)V
    //   286: astore 6
    //   288: aload 6
    //   290: putstatic 91	o/HZ:ˏ	Lo/HZ;
    //   293: new 2	o/HZ
    //   296: dup
    //   297: bipush 109
    //   299: sipush 7304
    //   302: bipush 24
    //   304: invokestatic 71	o/HZ:ॱ	(ICI)Ljava/lang/String;
    //   307: invokevirtual 77	java/lang/String:intern	()Ljava/lang/String;
    //   310: iconst_4
    //   311: bipush 23
    //   313: invokespecial 81	o/HZ:<init>	(Ljava/lang/String;II)V
    //   316: astore 7
    //   318: aload 7
    //   320: putstatic 93	o/HZ:ˎ	Lo/HZ;
    //   323: new 2	o/HZ
    //   326: dup
    //   327: sipush 133
    //   330: sipush 4697
    //   333: bipush 23
    //   335: invokestatic 71	o/HZ:ॱ	(ICI)Ljava/lang/String;
    //   338: invokevirtual 77	java/lang/String:intern	()Ljava/lang/String;
    //   341: iconst_5
    //   342: bipush 24
    //   344: invokespecial 81	o/HZ:<init>	(Ljava/lang/String;II)V
    //   347: astore 8
    //   349: aload 8
    //   351: putstatic 95	o/HZ:ॱॱ	Lo/HZ;
    //   354: new 2	o/HZ
    //   357: dup
    //   358: sipush 156
    //   361: sipush 13023
    //   364: bipush 43
    //   366: invokestatic 71	o/HZ:ॱ	(ICI)Ljava/lang/String;
    //   369: invokevirtual 77	java/lang/String:intern	()Ljava/lang/String;
    //   372: bipush 6
    //   374: bipush 25
    //   376: invokespecial 81	o/HZ:<init>	(Ljava/lang/String;II)V
    //   379: astore 9
    //   381: aload 9
    //   383: putstatic 97	o/HZ:ʽ	Lo/HZ;
    //   386: new 2	o/HZ
    //   389: dup
    //   390: sipush 199
    //   393: iconst_0
    //   394: bipush 35
    //   396: invokestatic 71	o/HZ:ॱ	(ICI)Ljava/lang/String;
    //   399: invokevirtual 77	java/lang/String:intern	()Ljava/lang/String;
    //   402: bipush 7
    //   404: bipush 26
    //   406: invokespecial 81	o/HZ:<init>	(Ljava/lang/String;II)V
    //   409: astore 10
    //   411: aload 10
    //   413: putstatic 99	o/HZ:ᐝ	Lo/HZ;
    //   416: new 2	o/HZ
    //   419: dup
    //   420: sipush 234
    //   423: ldc 100
    //   425: bipush 29
    //   427: invokestatic 71	o/HZ:ॱ	(ICI)Ljava/lang/String;
    //   430: invokevirtual 77	java/lang/String:intern	()Ljava/lang/String;
    //   433: bipush 8
    //   435: bipush 27
    //   437: invokespecial 81	o/HZ:<init>	(Ljava/lang/String;II)V
    //   440: astore 11
    //   442: aload 11
    //   444: putstatic 102	o/HZ:ʻ	Lo/HZ;
    //   447: new 2	o/HZ
    //   450: dup
    //   451: sipush 263
    //   454: iconst_0
    //   455: bipush 32
    //   457: invokestatic 71	o/HZ:ॱ	(ICI)Ljava/lang/String;
    //   460: invokevirtual 77	java/lang/String:intern	()Ljava/lang/String;
    //   463: bipush 9
    //   465: bipush 28
    //   467: invokespecial 81	o/HZ:<init>	(Ljava/lang/String;II)V
    //   470: astore 12
    //   472: aload 12
    //   474: putstatic 104	o/HZ:ʼ	Lo/HZ;
    //   477: new 2	o/HZ
    //   480: dup
    //   481: sipush 295
    //   484: ldc 105
    //   486: bipush 43
    //   488: invokestatic 71	o/HZ:ॱ	(ICI)Ljava/lang/String;
    //   491: invokevirtual 77	java/lang/String:intern	()Ljava/lang/String;
    //   494: bipush 10
    //   496: bipush 29
    //   498: invokespecial 81	o/HZ:<init>	(Ljava/lang/String;II)V
    //   501: astore 13
    //   503: aload 13
    //   505: putstatic 107	o/HZ:ॱˊ	Lo/HZ;
    //   508: new 2	o/HZ
    //   511: dup
    //   512: sipush 338
    //   515: iconst_0
    //   516: bipush 30
    //   518: invokestatic 71	o/HZ:ॱ	(ICI)Ljava/lang/String;
    //   521: invokevirtual 77	java/lang/String:intern	()Ljava/lang/String;
    //   524: bipush 11
    //   526: bipush 30
    //   528: invokespecial 81	o/HZ:<init>	(Ljava/lang/String;II)V
    //   531: astore 14
    //   533: aload 14
    //   535: putstatic 109	o/HZ:ͺ	Lo/HZ;
    //   538: new 2	o/HZ
    //   541: dup
    //   542: sipush 368
    //   545: iconst_0
    //   546: bipush 22
    //   548: invokestatic 71	o/HZ:ॱ	(ICI)Ljava/lang/String;
    //   551: invokevirtual 77	java/lang/String:intern	()Ljava/lang/String;
    //   554: bipush 12
    //   556: bipush 31
    //   558: invokespecial 81	o/HZ:<init>	(Ljava/lang/String;II)V
    //   561: astore 15
    //   563: aload 15
    //   565: putstatic 111	o/HZ:ˋॱ	Lo/HZ;
    //   568: new 2	o/HZ
    //   571: dup
    //   572: sipush 390
    //   575: iconst_0
    //   576: bipush 35
    //   578: invokestatic 71	o/HZ:ॱ	(ICI)Ljava/lang/String;
    //   581: invokevirtual 77	java/lang/String:intern	()Ljava/lang/String;
    //   584: bipush 13
    //   586: bipush 32
    //   588: invokespecial 81	o/HZ:<init>	(Ljava/lang/String;II)V
    //   591: astore 16
    //   593: aload 16
    //   595: putstatic 113	o/HZ:ˏॱ	Lo/HZ;
    //   598: new 2	o/HZ
    //   601: dup
    //   602: sipush 425
    //   605: ldc 114
    //   607: bipush 19
    //   609: invokestatic 71	o/HZ:ॱ	(ICI)Ljava/lang/String;
    //   612: invokevirtual 77	java/lang/String:intern	()Ljava/lang/String;
    //   615: bipush 14
    //   617: bipush 33
    //   619: invokespecial 81	o/HZ:<init>	(Ljava/lang/String;II)V
    //   622: astore 17
    //   624: aload 17
    //   626: putstatic 116	o/HZ:ˊॱ	Lo/HZ;
    //   629: new 2	o/HZ
    //   632: dup
    //   633: sipush 444
    //   636: iconst_0
    //   637: bipush 19
    //   639: invokestatic 71	o/HZ:ॱ	(ICI)Ljava/lang/String;
    //   642: invokevirtual 77	java/lang/String:intern	()Ljava/lang/String;
    //   645: bipush 15
    //   647: bipush 34
    //   649: invokespecial 81	o/HZ:<init>	(Ljava/lang/String;II)V
    //   652: astore 18
    //   654: aload 18
    //   656: putstatic 118	o/HZ:ʻॱ	Lo/HZ;
    //   659: new 2	o/HZ
    //   662: dup
    //   663: sipush 463
    //   666: ldc 119
    //   668: bipush 25
    //   670: invokestatic 71	o/HZ:ॱ	(ICI)Ljava/lang/String;
    //   673: invokevirtual 77	java/lang/String:intern	()Ljava/lang/String;
    //   676: bipush 16
    //   678: bipush 35
    //   680: invokespecial 81	o/HZ:<init>	(Ljava/lang/String;II)V
    //   683: astore 19
    //   685: aload 19
    //   687: putstatic 121	o/HZ:ॱˎ	Lo/HZ;
    //   690: new 2	o/HZ
    //   693: dup
    //   694: sipush 488
    //   697: iconst_0
    //   698: bipush 45
    //   700: invokestatic 71	o/HZ:ॱ	(ICI)Ljava/lang/String;
    //   703: invokevirtual 77	java/lang/String:intern	()Ljava/lang/String;
    //   706: bipush 17
    //   708: bipush 36
    //   710: invokespecial 81	o/HZ:<init>	(Ljava/lang/String;II)V
    //   713: astore 20
    //   715: aload 20
    //   717: putstatic 123	o/HZ:ॱˋ	Lo/HZ;
    //   720: new 2	o/HZ
    //   723: dup
    //   724: sipush 533
    //   727: iconst_0
    //   728: iconst_5
    //   729: invokestatic 71	o/HZ:ॱ	(ICI)Ljava/lang/String;
    //   732: invokevirtual 77	java/lang/String:intern	()Ljava/lang/String;
    //   735: bipush 18
    //   737: iconst_0
    //   738: invokespecial 81	o/HZ:<init>	(Ljava/lang/String;II)V
    //   741: astore 21
    //   743: aload 21
    //   745: putstatic 125	o/HZ:ᐝॱ	Lo/HZ;
    //   748: bipush 19
    //   750: anewarray 2	o/HZ
    //   753: dup
    //   754: iconst_0
    //   755: aload_3
    //   756: aastore
    //   757: dup
    //   758: iconst_1
    //   759: aload 4
    //   761: aastore
    //   762: dup
    //   763: iconst_2
    //   764: aload 5
    //   766: aastore
    //   767: dup
    //   768: iconst_3
    //   769: aload 6
    //   771: aastore
    //   772: dup
    //   773: iconst_4
    //   774: aload 7
    //   776: aastore
    //   777: dup
    //   778: iconst_5
    //   779: aload 8
    //   781: aastore
    //   782: dup
    //   783: bipush 6
    //   785: aload 9
    //   787: aastore
    //   788: dup
    //   789: bipush 7
    //   791: aload 10
    //   793: aastore
    //   794: dup
    //   795: bipush 8
    //   797: aload 11
    //   799: aastore
    //   800: dup
    //   801: bipush 9
    //   803: aload 12
    //   805: aastore
    //   806: dup
    //   807: bipush 10
    //   809: aload 13
    //   811: aastore
    //   812: dup
    //   813: bipush 11
    //   815: aload 14
    //   817: aastore
    //   818: dup
    //   819: bipush 12
    //   821: aload 15
    //   823: aastore
    //   824: dup
    //   825: bipush 13
    //   827: aload 16
    //   829: aastore
    //   830: dup
    //   831: bipush 14
    //   833: aload 17
    //   835: aastore
    //   836: dup
    //   837: bipush 15
    //   839: aload 18
    //   841: aastore
    //   842: dup
    //   843: bipush 16
    //   845: aload 19
    //   847: aastore
    //   848: dup
    //   849: bipush 17
    //   851: aload 20
    //   853: aastore
    //   854: dup
    //   855: bipush 18
    //   857: aload 21
    //   859: aastore
    //   860: putstatic 127	o/HZ:ʽॱ	[Lo/HZ;
    //   863: new 7	o/HZ$ˊ
    //   866: dup
    //   867: aconst_null
    //   868: invokespecial 130	o/HZ$ˊ:<init>	(Lo/vn;)V
    //   871: putstatic 132	o/HZ:ॱᐝ	Lo/HZ$ˊ;
    //   874: invokestatic 136	o/HZ:values	()[Lo/HZ;
    //   877: checkcast 138	[Ljava/lang/Object;
    //   880: astore 4
    //   882: new 140	java/util/LinkedHashMap
    //   885: dup
    //   886: aload 4
    //   888: arraylength
    //   889: invokestatic 145	o/vd:ˎ	(I)I
    //   892: bipush 16
    //   894: invokestatic 150	o/vD:ˋ	(II)I
    //   897: invokespecial 153	java/util/LinkedHashMap:<init>	(I)V
    //   900: checkcast 62	java/util/Map
    //   903: astore 5
    //   905: aload 4
    //   907: arraylength
    //   908: istore_2
    //   909: iconst_0
    //   910: istore_0
    //   911: goto -845 -> 66
    //   914: bipush 46
    //   916: istore_1
    //   917: goto -831 -> 86
    //   920: iload_0
    //   921: iload_2
    //   922: if_icmpge +6 -> 928
    //   925: goto -11 -> 914
    //   928: goto +8 -> 936
    //   931: iload_1
    //   932: istore_0
    //   933: goto -13 -> 920
    //   936: bipush 73
    //   938: istore_1
    //   939: goto -853 -> 86
    // Local variable table:
    //   start	length	slot	name	signature
    //   14	919	0	i	int
    //   45	894	1	j	int
    //   908	15	2	k	int
    //   11	2	3	localException1	Exception
    //   69	2	3	localException2	Exception
    //   119	637	3	localObject1	Object
    //   115	791	4	localObject2	Object
    //   77	827	5	localObject3	Object
    //   286	484	6	localHZ1	HZ
    //   316	459	7	localHZ2	HZ
    //   347	433	8	localHZ3	HZ
    //   379	407	9	localHZ4	HZ
    //   409	383	10	localHZ5	HZ
    //   440	358	11	localHZ6	HZ
    //   470	334	12	localHZ7	HZ
    //   501	309	13	localHZ8	HZ
    //   531	285	14	localHZ9	HZ
    //   561	261	15	localHZ10	HZ
    //   591	237	16	localHZ11	HZ
    //   622	212	17	localHZ12	HZ
    //   652	188	18	localHZ13	HZ
    //   683	163	19	localHZ14	HZ
    //   713	139	20	localHZ15	HZ
    //   741	117	21	localHZ16	HZ
    // Exception table:
    //   from	to	target	type
    //   150	158	11	java/lang/Exception
    //   143	150	69	java/lang/Exception
    //   150	158	69	java/lang/Exception
  }
  
  protected HZ(int paramInt)
  {
    this.ʼॱ = paramInt;
  }
  
  static void ˏ()
  {
    ʿ = -4547814918668429285L;
    ˈ = new char[] { 21886, -29342, -6848, -8923, 13583, 28153, 17859, -16945, -27216, -12908, 9329, 7249, 29757, -21459, -31726, -788, -11054, 3249, 25747, 24435, -18567, -4257, -14549, 16149, 6123, 20445, -22577, -24665, -2176, 11897, 1609, 32315, 22040, -29182, -25787, 17212, 11123, 4891, -1235, -23616, -29706, 29670, 23454, 935, -5544, -11672, -17896, 25093, 18977, 13023, 6884, -15723, -21827, -28325, 31070, 8558, 2306, -3780, -9766, -32269, 27119, 80, -10199, -20378, -30706, 24632, 14549, 4323, -5901, -16245, -26446, 29005, 18813, 8461, -1776, -11980, -22070, -32271, 22920, 12709, 2628, -7604, -17821, -28137, 27177, -3689, 10734, 16801, 31177, -28161, -14062, -7900, 6452, 12620, 26997, -32630, -18246, -12086, 2263, 8435, 22541, 28724, -22451, -16273, -1147, 5022, 19388, 25552, -25618, 7384, -15199, -21266, -27514, 31920, 9309, 3179, -2949, -9213, -31686, 28101, 22005, 15749, -6760, -12868, -19134, -25220, 17670, 11565, 5829, -291, -22799, -29025, 30369, 4617, -13712, -24001, -26025, 29281, 10892, 698, -1366, -11566, -29973, 25364, 23332, 13140, -5303, -15507, -17517, -27732, 19402, 9199, 6161, -4073, -22485, -32689, 12956, -5499, -32069, -17718, 21228, 2568, 8751, -9683, -3503, -21915, 17282, 31679, 5076, -13362, -7188, -25852, -19672, 27467, 895, 14495, -12150, -30556, -24366, 22769, 28694, 10286, -16347, -1959, -28552, 18837, 24993, 6606, 12790, -5654, -32498, -18115, 20812, 2425, 9886, -8554, -2386, -20797, 18175, 67, -10150, -20380, -30699, 24627, 14551, 4336, -5902, -16242, -26438, 29021, 18784, 8459, -1775, -11981, -22053, -32265, 22932, 12704, 2624, -7595, -17797, -28147, 27199, 17101, 6903, -3348, -13696, -23893, 31566, 21353, 11025, 809, -9420, -19496, -7570, 14967, 21065, 27192, -32226, -9478, -3363, 2783, 8867, 31383, -27792, -21683, -15578, 6972, 13086, 19446, 25562, -17479, -11379, -6035, 120, 22614, 28704, -30719, -24346, -1830, 4314, 10427, 16535, 67, -10150, -20380, -30699, 24627, 14551, 4336, -5902, -16242, -26438, 29021, 18784, 8459, -1775, -11981, -22053, -32265, 22932, 12725, 2644, -7585, -17804, -28137, 27198, 17115, 6908, -3329, -13670, -23904, 31558, 21349, 11019, -30795, 24511, 14218, 4089, -6196, -16596, -26861, 28423, 18299, 8023, -2398, -12672, -22796, 32488, 22234, 11823, 1562, -8578, -18874, -29270, 26022, 15766, 5618, -4642, -15068, -25339, 29982, 19811, 9538, -849, -11109, -21260, -31540, 23760, 13364, 3079, -7050, -17341, -27740, 27564, 17300, 7161, -3131, 80, -10150, -20369, -30692, 24617, 14537, 4342, -5918, -16226, -26446, 28999, 18789, 8465, -1779, -11969, -22070, -32268, 22926, 12704, 2624, -7607, -17797, -28154, 27186, 17097, 6880, -3350, -13680, -23877, 31553, 80, -10150, -20369, -30692, 24617, 14537, 4342, -5918, -16244, -26438, 28995, 18796, 8459, -1782, -11986, -22070, -32271, 22920, 12722, 2632, -7597, -17799, 80, -10150, -20369, -30692, 24617, 14537, 4342, -5918, -16226, -26438, 28992, 18784, 8471, -1769, -11969, -22063, -32273, 22943, 12724, 2624, -7598, -17820, -28141, 27182, 17116, 6890, -3343, -13673, -23893, 31566, 21353, 11025, 809, -9420, -19496, -15515, 7036, 29506, 19251, -23787, -1051, -11327, 11215, 959, 23452, -19868, -30116, -7619, 14904, 4639, 27367, 17119, -25950, -3442, 67, -10150, -20380, -30699, 24627, 14531, 4327, -5903, -16227, -26457, 29003, 18797, 8475, -1762, -11975, -22079, -32263, 22916, 12712, -4445, 14010, 24196, 26357, -28973, -10700, -490, 1564, 11884, 30294, -24655, -22646, -12308, 6142, 16340, 18226, 28437, -18577, -8359, -7008, 3263, 21635, 31995, -31550, -21466, 80, -10150, -20369, -30692, 24617, 14537, 4342, -5918, -16226, -26446, 28999, 18789, 8465, -1779, -11969, -22070, -32286, 22926, 12727, 2644, -7595, -17819, -28137, 27198, 17111, 6887, -3333, -13681, -23875, 31564, 21359, 11034, 821, -9419, -19494, -29698, 25487, 15276, 5213, -5028, -15237, -25593, 29735, 19654, 9450, 68, -10162, -20357, -30692, 24629 };
  }
  
  private static String ॱ(int paramInt1, char paramChar, int paramInt2)
  {
    break label179;
    label6:
    int j;
    int i;
    char[] arrayOfChar;
    label72:
    label99:
    label143:
    for (;;)
    {
      break;
      i = j;
      break;
      for (;;)
      {
        arrayOfChar[i] = ((char)(int)(ˈ[(paramInt1 + i)] ^ i * ʿ ^ paramChar));
        i += 1;
        j = ˊˋ + 91;
        ˉ = j % 128;
        if (j % 2 == 0) {
          break label143;
        }
        break;
        i = 0;
        switch (i)
        {
        case 0: 
        default: 
          break label6;
          switch (j)
          {
          }
          break;
        }
      }
      return new String(arrayOfChar);
      i = j;
      break;
    }
    for (;;)
    {
      i = 1;
      break label72;
      label179:
      for (;;)
      {
        arrayOfChar = new char[paramInt2];
        j = 0;
        break label188;
        if (i >= paramInt2) {
          break label182;
        }
        j = 0;
        break;
      }
      label182:
      j = 1;
      break label99;
      label188:
      i = ˉ + 113;
      ˊˋ = i % 128;
      if (i % 2 != 0) {
        break;
      }
    }
  }
  
  /* Error */
  public final int ॱ()
  {
    // Byte code:
    //   0: goto +101 -> 101
    //   3: astore_3
    //   4: aload_3
    //   5: athrow
    //   6: bipush 64
    //   8: istore_1
    //   9: goto +61 -> 70
    //   12: aload_0
    //   13: getfield 54	o/HZ:ʼॱ	I
    //   16: istore_1
    //   17: aconst_null
    //   18: arraylength
    //   19: istore_2
    //   20: goto +23 -> 43
    //   23: bipush 95
    //   25: istore_2
    //   26: goto +104 -> 130
    //   29: aload_0
    //   30: getfield 54	o/HZ:ʼॱ	I
    //   33: istore_1
    //   34: goto +9 -> 43
    //   37: bipush 84
    //   39: istore_2
    //   40: goto +90 -> 130
    //   43: getstatic 50	o/HZ:ˉ	I
    //   46: bipush 123
    //   48: iadd
    //   49: istore_2
    //   50: iload_2
    //   51: sipush 128
    //   54: irem
    //   55: putstatic 48	o/HZ:ˊˋ	I
    //   58: iload_2
    //   59: iconst_2
    //   60: irem
    //   61: ifeq +6 -> 67
    //   64: goto -41 -> 23
    //   67: goto -30 -> 37
    //   70: iload_1
    //   71: lookupswitch	default:+25->96, 4:+-42->29, 64:+-59->12
    //   96: goto -67 -> 29
    //   99: iload_1
    //   100: ireturn
    //   101: getstatic 50	o/HZ:ˉ	I
    //   104: istore_1
    //   105: iload_1
    //   106: bipush 37
    //   108: iadd
    //   109: istore_1
    //   110: iload_1
    //   111: sipush 128
    //   114: irem
    //   115: putstatic 48	o/HZ:ˊˋ	I
    //   118: iload_1
    //   119: iconst_2
    //   120: irem
    //   121: ifeq +6 -> 127
    //   124: goto -118 -> 6
    //   127: goto +37 -> 164
    //   130: iload_2
    //   131: lookupswitch	default:+25->156, 84:+-32->99, 95:+25->156
    //   156: aconst_null
    //   157: arraylength
    //   158: istore_2
    //   159: iload_1
    //   160: ireturn
    //   161: astore_3
    //   162: aload_3
    //   163: athrow
    //   164: iconst_4
    //   165: istore_1
    //   166: goto -96 -> 70
    // Local variable table:
    //   start	length	slot	name	signature
    //   0	169	0	this	HZ
    //   8	158	1	i	int
    //   19	140	2	j	int
    //   3	2	3	localException1	Exception
    //   161	2	3	localException2	Exception
    // Exception table:
    //   from	to	target	type
    //   12	20	3	java/lang/Exception
    //   43	50	161	java/lang/Exception
    //   50	58	161	java/lang/Exception
    //   101	105	161	java/lang/Exception
    //   110	118	161	java/lang/Exception
  }
  
  public static final class ˊ
  {
    private ˊ() {}
    
    private final Map<Integer, HZ> ˏ()
    {
      return HZ.ˊ();
    }
    
    public final HZ ˏ(int paramInt)
    {
      return (HZ)((ˊ)this).ˏ().get(Integer.valueOf(paramInt));
    }
  }
}
