package o;

import java.io.UnsupportedEncodingException;

public abstract class I
  extends J
{
  private static int ˊ;
  private static int ˋ;
  private static char ˎ;
  private static byte ˏ;
  private static char[] ॱ;
  
  /* Error */
  static
  {
    // Byte code:
    //   0: goto +77 -> 77
    //   3: bipush 62
    //   5: iconst_0
    //   6: idiv
    //   7: istore_0
    //   8: return
    //   9: astore_1
    //   10: aload_1
    //   11: athrow
    //   12: getstatic 19	o/I:ˊ	I
    //   15: istore_0
    //   16: iload_0
    //   17: bipush 87
    //   19: iadd
    //   20: istore_0
    //   21: iload_0
    //   22: sipush 128
    //   25: irem
    //   26: putstatic 21	o/I:ˋ	I
    //   29: iload_0
    //   30: iconst_2
    //   31: irem
    //   32: ifne +6 -> 38
    //   35: goto +9 -> 44
    //   38: bipush 34
    //   40: istore_0
    //   41: goto +6 -> 47
    //   44: bipush 61
    //   46: istore_0
    //   47: iload_0
    //   48: lookupswitch	default:+28->76, 34:+28->76, 61:+-45->3
    //   76: return
    //   77: iconst_0
    //   78: putstatic 19	o/I:ˊ	I
    //   81: iconst_1
    //   82: putstatic 21	o/I:ˋ	I
    //   85: invokestatic 24	o/I:ʻᐝ	()V
    //   88: bipush -102
    //   90: putstatic 26	o/I:ˏ	B
    //   93: goto -81 -> 12
    //   96: astore_1
    //   97: aload_1
    //   98: athrow
    // Local variable table:
    //   start	length	slot	name	signature
    //   7	41	0	i	int
    //   9	2	1	localException1	Exception
    //   96	2	1	localException2	Exception
    // Exception table:
    //   from	to	target	type
    //   21	29	9	java/lang/Exception
    //   12	16	96	java/lang/Exception
  }
  
  public I() {}
  
  static void ʻᐝ()
  {
    ॱ = new char[] { 5, 26, 11, 12, 103, 101, 116, 83, 114, 105, 110, 40, 115, 82, 41, 73, 79, 45, 56, 53, 57, 49, 85, 84, 70 };
    ˎ = '\005';
  }
  
  /* Error */
  private static String ॱ(int paramInt, char[] paramArrayOfChar, byte paramByte)
  {
    // Byte code:
    //   0: goto +745 -> 745
    //   3: getstatic 21	o/I:ˋ	I
    //   6: bipush 65
    //   8: iadd
    //   9: istore 7
    //   11: iload 7
    //   13: sipush 128
    //   16: irem
    //   17: putstatic 19	o/I:ˊ	I
    //   20: iload 7
    //   22: iconst_2
    //   23: irem
    //   24: ifeq +6 -> 30
    //   27: goto +587 -> 614
    //   30: goto +298 -> 328
    //   33: getstatic 21	o/I:ˋ	I
    //   36: bipush 7
    //   38: iadd
    //   39: istore_2
    //   40: iload_2
    //   41: sipush 128
    //   44: irem
    //   45: putstatic 19	o/I:ˊ	I
    //   48: iload_2
    //   49: iconst_2
    //   50: irem
    //   51: ifeq +6 -> 57
    //   54: goto +18 -> 72
    //   57: goto +248 -> 305
    //   60: bipush 51
    //   62: istore_2
    //   63: goto +289 -> 352
    //   66: bipush 96
    //   68: istore_3
    //   69: goto +435 -> 504
    //   72: goto +233 -> 305
    //   75: iload 7
    //   77: iload 9
    //   79: iload_3
    //   80: invokestatic 65	o/oO:ˏ	(III)I
    //   83: istore_2
    //   84: iload 6
    //   86: iload 8
    //   88: iload_3
    //   89: invokestatic 65	o/oO:ˏ	(III)I
    //   92: istore 6
    //   94: aload 11
    //   96: iload_0
    //   97: aload 10
    //   99: iload_2
    //   100: caload
    //   101: castore
    //   102: aload 11
    //   104: iload_0
    //   105: iconst_1
    //   106: iadd
    //   107: aload 10
    //   109: iload 6
    //   111: caload
    //   112: castore
    //   113: goto +384 -> 497
    //   116: getstatic 57	o/I:ॱ	[C
    //   119: astore 14
    //   121: iload_0
    //   122: istore 4
    //   124: getstatic 59	o/I:ˎ	C
    //   127: istore 6
    //   129: iload 4
    //   131: newarray char
    //   133: astore 15
    //   135: iload 4
    //   137: iconst_2
    //   138: irem
    //   139: ifeq +6 -> 145
    //   142: goto +583 -> 725
    //   145: goto +451 -> 596
    //   148: goto +583 -> 731
    //   151: iload 6
    //   153: istore_3
    //   154: aload 14
    //   156: astore 10
    //   158: aload 15
    //   160: astore 11
    //   162: iload 6
    //   164: istore 5
    //   166: aload 14
    //   168: astore 12
    //   170: aload 15
    //   172: astore 13
    //   174: iload 7
    //   176: tableswitch	default:+24->200, 0:+107->283, 1:+268->444
    //   200: iload 6
    //   202: istore 5
    //   204: aload 14
    //   206: astore 12
    //   208: aload 15
    //   210: astore 13
    //   212: goto +232 -> 444
    //   215: iload 7
    //   217: iload 6
    //   219: if_icmpne +6 -> 225
    //   222: goto +242 -> 464
    //   225: goto +380 -> 605
    //   228: iload_0
    //   229: iload 4
    //   231: if_icmpge +6 -> 237
    //   234: goto -201 -> 33
    //   237: goto +58 -> 295
    //   240: iload 6
    //   242: iload_3
    //   243: invokestatic 68	o/oO:ॱ	(II)I
    //   246: istore 7
    //   248: iload 6
    //   250: iload_3
    //   251: invokestatic 70	o/oO:ˋ	(II)I
    //   254: istore 8
    //   256: iload_2
    //   257: iload_3
    //   258: invokestatic 68	o/oO:ॱ	(II)I
    //   261: istore 6
    //   263: iload_2
    //   264: iload_3
    //   265: invokestatic 70	o/oO:ˋ	(II)I
    //   268: istore 9
    //   270: iload 8
    //   272: iload 9
    //   274: if_icmpne +6 -> 280
    //   277: goto -217 -> 60
    //   280: goto +103 -> 383
    //   283: iload_2
    //   284: istore 5
    //   286: iload 4
    //   288: iconst_1
    //   289: if_icmple +6 -> 295
    //   292: goto +383 -> 675
    //   295: new 72	java/lang/String
    //   298: dup
    //   299: aload 11
    //   301: invokespecial 75	java/lang/String:<init>	([C)V
    //   304: areturn
    //   305: aload_1
    //   306: iload_0
    //   307: caload
    //   308: istore 6
    //   310: aload_1
    //   311: iload_0
    //   312: iconst_1
    //   313: iadd
    //   314: caload
    //   315: istore_2
    //   316: iload 6
    //   318: iload_2
    //   319: if_icmpne +6 -> 325
    //   322: goto -319 -> 3
    //   325: goto -85 -> 240
    //   328: aload 11
    //   330: iload_0
    //   331: iload 6
    //   333: iload 5
    //   335: isub
    //   336: i2c
    //   337: castore
    //   338: aload 11
    //   340: iload_0
    //   341: iconst_1
    //   342: iadd
    //   343: iload_2
    //   344: iload 5
    //   346: isub
    //   347: i2c
    //   348: castore
    //   349: goto +262 -> 611
    //   352: iload_2
    //   353: lookupswitch	default:+27->380, 30:+-138->215, 51:+36->389
    //   380: goto +9 -> 389
    //   383: bipush 30
    //   385: istore_2
    //   386: goto -34 -> 352
    //   389: iload 7
    //   391: iload_3
    //   392: invokestatic 77	o/oO:ˊ	(II)I
    //   395: istore_2
    //   396: iload 6
    //   398: iload_3
    //   399: invokestatic 77	o/oO:ˊ	(II)I
    //   402: istore 6
    //   404: iload_2
    //   405: iload 8
    //   407: iload_3
    //   408: invokestatic 65	o/oO:ˏ	(III)I
    //   411: istore_2
    //   412: iload 6
    //   414: iload 9
    //   416: iload_3
    //   417: invokestatic 65	o/oO:ˏ	(III)I
    //   420: istore 6
    //   422: aload 11
    //   424: iload_0
    //   425: aload 10
    //   427: iload_2
    //   428: caload
    //   429: castore
    //   430: aload 11
    //   432: iload_0
    //   433: iconst_1
    //   434: iadd
    //   435: aload 10
    //   437: iload 6
    //   439: caload
    //   440: castore
    //   441: goto +56 -> 497
    //   444: iload_0
    //   445: iconst_1
    //   446: isub
    //   447: istore 4
    //   449: aload 13
    //   451: iload 4
    //   453: aload_1
    //   454: iload 4
    //   456: caload
    //   457: iload_2
    //   458: isub
    //   459: i2c
    //   460: castore
    //   461: goto +9 -> 470
    //   464: bipush 21
    //   466: istore_2
    //   467: goto +179 -> 646
    //   470: getstatic 21	o/I:ˋ	I
    //   473: bipush 21
    //   475: iadd
    //   476: istore_0
    //   477: iload_0
    //   478: sipush 128
    //   481: irem
    //   482: putstatic 19	o/I:ˊ	I
    //   485: iload_0
    //   486: iconst_2
    //   487: irem
    //   488: ifeq +6 -> 494
    //   491: goto -343 -> 148
    //   494: goto +237 -> 731
    //   497: iload_0
    //   498: iconst_2
    //   499: iadd
    //   500: istore_0
    //   501: goto -273 -> 228
    //   504: iload_3
    //   505: lookupswitch	default:+27->532, 58:+175->680, 96:+-389->116
    //   532: goto -416 -> 116
    //   535: iload 8
    //   537: iload_3
    //   538: invokestatic 77	o/oO:ˊ	(II)I
    //   541: istore_2
    //   542: iload 9
    //   544: iload_3
    //   545: invokestatic 77	o/oO:ˊ	(II)I
    //   548: istore 8
    //   550: iload 7
    //   552: iload_2
    //   553: iload_3
    //   554: invokestatic 65	o/oO:ˏ	(III)I
    //   557: istore_2
    //   558: iload 6
    //   560: iload 8
    //   562: iload_3
    //   563: invokestatic 65	o/oO:ˏ	(III)I
    //   566: istore 6
    //   568: aload 11
    //   570: iload_0
    //   571: aload 10
    //   573: iload_2
    //   574: caload
    //   575: castore
    //   576: aload 11
    //   578: iload_0
    //   579: iconst_1
    //   580: iadd
    //   581: aload 10
    //   583: iload 6
    //   585: caload
    //   586: castore
    //   587: goto -90 -> 497
    //   590: bipush 58
    //   592: istore_3
    //   593: goto -89 -> 504
    //   596: iconst_0
    //   597: istore 7
    //   599: goto -448 -> 151
    //   602: astore_1
    //   603: aload_1
    //   604: athrow
    //   605: bipush 63
    //   607: istore_2
    //   608: goto +38 -> 646
    //   611: goto -114 -> 497
    //   614: goto -286 -> 328
    //   617: getstatic 21	o/I:ˋ	I
    //   620: istore_3
    //   621: iload_3
    //   622: bipush 79
    //   624: iadd
    //   625: istore_3
    //   626: iload_3
    //   627: sipush 128
    //   630: irem
    //   631: putstatic 19	o/I:ˊ	I
    //   634: iload_3
    //   635: iconst_2
    //   636: irem
    //   637: ifeq +6 -> 643
    //   640: goto -50 -> 590
    //   643: goto -577 -> 66
    //   646: iload_2
    //   647: lookupswitch	default:+25->672, 21:+-112->535, 63:+-572->75
    //   672: goto -597 -> 75
    //   675: iconst_0
    //   676: istore_0
    //   677: goto -449 -> 228
    //   680: getstatic 57	o/I:ॱ	[C
    //   683: astore 10
    //   685: iload_0
    //   686: istore 4
    //   688: getstatic 59	o/I:ˎ	C
    //   691: istore_3
    //   692: iload 4
    //   694: newarray char
    //   696: astore 11
    //   698: iload 4
    //   700: iconst_4
    //   701: ishl
    //   702: ifeq +17 -> 719
    //   705: iload_3
    //   706: istore 5
    //   708: aload 10
    //   710: astore 12
    //   712: aload 11
    //   714: astore 13
    //   716: goto -272 -> 444
    //   719: goto -436 -> 283
    //   722: astore_1
    //   723: aload_1
    //   724: athrow
    //   725: iconst_1
    //   726: istore 7
    //   728: goto -577 -> 151
    //   731: iload 5
    //   733: istore_3
    //   734: aload 12
    //   736: astore 10
    //   738: aload 13
    //   740: astore 11
    //   742: goto -459 -> 283
    //   745: goto -128 -> 617
    // Local variable table:
    //   start	length	slot	name	signature
    //   0	748	0	paramInt	int
    //   0	748	1	paramArrayOfChar	char[]
    //   0	748	2	paramByte	byte
    //   68	666	3	b1	byte
    //   122	580	4	i	int
    //   164	568	5	b2	byte
    //   84	500	6	b3	byte
    //   9	718	7	j	int
    //   86	475	8	k	int
    //   77	466	9	m	int
    //   97	640	10	localObject1	Object
    //   94	647	11	localObject2	Object
    //   168	567	12	localObject3	Object
    //   172	567	13	localObject4	Object
    //   119	86	14	arrayOfChar1	char[]
    //   133	76	15	arrayOfChar2	char[]
    // Exception table:
    //   from	to	target	type
    //   617	621	602	java/lang/Exception
    //   626	634	722	java/lang/Exception
    //   680	685	722	java/lang/Exception
    //   688	698	722	java/lang/Exception
  }
  
  private String ॱ(String paramString)
  {
    for (;;)
    {
      try
      {
        i = ˊ + 1;
        ˋ = i % 128;
        if (i % 2 != 0)
        {
          i = 1;
        }
        else
        {
          try
          {
            arrayOfByte = paramString.getBytes(ॱ(10, new char[] { 17, 5, 17, 18, 126, 126, 15, 24, 16, 22 }, (byte)70).intern());
            paramString = new byte[arrayOfByte.length];
            i = 0;
          }
          catch (UnsupportedEncodingException paramString)
          {
            throw new RuntimeException(paramString);
          }
          i = 0;
          continue;
          return paramString;
          paramString = new String(paramString, ॱ(5, new char[] { 23, 24, 22, 19, 106 }, (byte)50).intern());
          continue;
          i = 0;
          continue;
          break label423;
        }
        switch (i)
        {
        case 1: 
        default: 
          return paramString;
          j = 6;
          continue;
          i = 1;
          break;
        case 0: 
          throw new NullPointerException();
          paramString[i] = ((byte)(arrayOfByte[(arrayOfByte.length - i - 1)] ^ ˏ));
          i += 1;
          break;
        }
        switch (j)
        {
        }
        continue;
        byte[] arrayOfByte = paramString.getBytes(ॱ(14, new char[] { 17, 5, 17, 18, 126, 126, 15, 24, 16, 22 }, (byte)116).intern());
        paramString = new byte[arrayOfByte.length];
        i = 1;
        break label402;
        switch (i)
        {
        }
        continue;
        j = arrayOfByte.length;
      }
      catch (Exception paramString)
      {
        throw paramString;
      }
      label402:
      if (i >= j) {}
      int j = 83;
      continue;
      label423:
      int i = ˋ + 113;
      ˊ = i % 128;
      if (i % 2 != 0) {}
    }
  }
  
  /* Error */
  protected String ʼ(int paramInt)
  {
    // Byte code:
    //   0: goto +479 -> 479
    //   3: bipush 15
    //   5: istore_1
    //   6: goto +35 -> 41
    //   9: getstatic 19	o/I:ˊ	I
    //   12: bipush 69
    //   14: iadd
    //   15: istore_1
    //   16: iload_1
    //   17: sipush 128
    //   20: irem
    //   21: putstatic 21	o/I:ˋ	I
    //   24: iload_1
    //   25: iconst_2
    //   26: irem
    //   27: ifne +6 -> 33
    //   30: goto -27 -> 3
    //   33: goto +438 -> 471
    //   36: iconst_0
    //   37: istore_1
    //   38: goto +408 -> 446
    //   41: iload_1
    //   42: lookupswitch	default:+26->68, 15:+277->319, 20:+435->477
    //   68: goto +251 -> 319
    //   71: aload_3
    //   72: bipush 20
    //   74: bipush 20
    //   76: newarray char
    //   78: dup
    //   79: iconst_0
    //   80: ldc 114
    //   82: castore
    //   83: dup
    //   84: iconst_1
    //   85: ldc 115
    //   87: castore
    //   88: dup
    //   89: iconst_2
    //   90: ldc 116
    //   92: castore
    //   93: dup
    //   94: iconst_3
    //   95: ldc 117
    //   97: castore
    //   98: dup
    //   99: iconst_4
    //   100: ldc 116
    //   102: castore
    //   103: dup
    //   104: iconst_5
    //   105: ldc 115
    //   107: castore
    //   108: dup
    //   109: bipush 6
    //   111: ldc 31
    //   113: castore
    //   114: dup
    //   115: bipush 7
    //   117: ldc 118
    //   119: castore
    //   120: dup
    //   121: bipush 8
    //   123: ldc 119
    //   125: castore
    //   126: dup
    //   127: bipush 9
    //   129: ldc 118
    //   131: castore
    //   132: dup
    //   133: bipush 10
    //   135: ldc 33
    //   137: castore
    //   138: dup
    //   139: bipush 11
    //   141: ldc 116
    //   143: castore
    //   144: dup
    //   145: bipush 12
    //   147: ldc 115
    //   149: castore
    //   150: dup
    //   151: bipush 13
    //   153: ldc 31
    //   155: castore
    //   156: dup
    //   157: bipush 14
    //   159: ldc 118
    //   161: castore
    //   162: dup
    //   163: bipush 15
    //   165: ldc 114
    //   167: castore
    //   168: dup
    //   169: bipush 16
    //   171: ldc 120
    //   173: castore
    //   174: dup
    //   175: bipush 17
    //   177: ldc 117
    //   179: castore
    //   180: dup
    //   181: bipush 18
    //   183: ldc 121
    //   185: castore
    //   186: dup
    //   187: bipush 19
    //   189: ldc 120
    //   191: castore
    //   192: bipush 54
    //   194: invokestatic 89	o/I:ॱ	(I[CB)Ljava/lang/String;
    //   197: invokevirtual 93	java/lang/String:intern	()Ljava/lang/String;
    //   200: invokestatic 126	o/vq:ˋ	(Ljava/lang/Object;Ljava/lang/String;)V
    //   203: goto +20 -> 223
    //   206: astore_3
    //   207: aload_3
    //   208: invokevirtual 132	java/lang/Throwable:getCause	()Ljava/lang/Throwable;
    //   211: astore 4
    //   213: aload 4
    //   215: ifnull +6 -> 221
    //   218: aload 4
    //   220: athrow
    //   221: aload_3
    //   222: athrow
    //   223: iconst_3
    //   224: iconst_3
    //   225: iconst_0
    //   226: invokestatic 137	o/O:ˋ	(IIC)Ljava/lang/Object;
    //   229: checkcast 139	java/lang/Class
    //   232: ldc -116
    //   234: iconst_1
    //   235: anewarray 139	java/lang/Class
    //   238: dup
    //   239: iconst_0
    //   240: ldc 72
    //   242: aastore
    //   243: invokevirtual 144	java/lang/Class:getMethod	(Ljava/lang/String;[Ljava/lang/Class;)Ljava/lang/reflect/Method;
    //   246: aload 4
    //   248: iconst_1
    //   249: anewarray 146	java/lang/Object
    //   252: dup
    //   253: iconst_0
    //   254: aload_3
    //   255: aastore
    //   256: invokevirtual 152	java/lang/reflect/Method:invoke	(Ljava/lang/Object;[Ljava/lang/Object;)Ljava/lang/Object;
    //   259: checkcast 72	java/lang/String
    //   262: astore_3
    //   263: goto -254 -> 9
    //   266: astore_3
    //   267: aload_3
    //   268: athrow
    //   269: astore_3
    //   270: aload_3
    //   271: athrow
    //   272: getstatic 19	o/I:ˊ	I
    //   275: bipush 11
    //   277: iadd
    //   278: istore_1
    //   279: iload_1
    //   280: sipush 128
    //   283: irem
    //   284: putstatic 21	o/I:ˋ	I
    //   287: iload_1
    //   288: iconst_2
    //   289: irem
    //   290: ifne +6 -> 296
    //   293: goto -257 -> 36
    //   296: goto +148 -> 444
    //   299: aload_3
    //   300: iconst_4
    //   301: invokevirtual 155	java/lang/String:substring	(I)Ljava/lang/String;
    //   304: astore_3
    //   305: aload_0
    //   306: aload_3
    //   307: invokespecial 157	o/I:ॱ	(Ljava/lang/String;)Ljava/lang/String;
    //   310: astore_3
    //   311: aload_3
    //   312: invokevirtual 93	java/lang/String:intern	()Ljava/lang/String;
    //   315: astore_3
    //   316: goto -245 -> 71
    //   319: bipush 97
    //   321: iconst_0
    //   322: idiv
    //   323: istore_1
    //   324: aload_3
    //   325: areturn
    //   326: iconst_3
    //   327: iconst_3
    //   328: iconst_0
    //   329: invokestatic 137	o/O:ˋ	(IIC)Ljava/lang/Object;
    //   332: checkcast 139	java/lang/Class
    //   335: ldc -98
    //   337: invokevirtual 162	java/lang/Class:getField	(Ljava/lang/String;)Ljava/lang/reflect/Field;
    //   340: aconst_null
    //   341: invokevirtual 168	java/lang/reflect/Field:get	(Ljava/lang/Object;)Ljava/lang/Object;
    //   344: astore_3
    //   345: goto +20 -> 365
    //   348: astore_3
    //   349: aload_3
    //   350: invokevirtual 132	java/lang/Throwable:getCause	()Ljava/lang/Throwable;
    //   353: astore 4
    //   355: aload 4
    //   357: ifnull +6 -> 363
    //   360: aload 4
    //   362: athrow
    //   363: aload_3
    //   364: athrow
    //   365: bipush 6
    //   367: bipush 6
    //   369: sipush 10540
    //   372: invokestatic 137	o/O:ˋ	(IIC)Ljava/lang/Object;
    //   375: checkcast 139	java/lang/Class
    //   378: ldc -87
    //   380: aconst_null
    //   381: invokevirtual 144	java/lang/Class:getMethod	(Ljava/lang/String;[Ljava/lang/Class;)Ljava/lang/reflect/Method;
    //   384: aload_3
    //   385: aconst_null
    //   386: invokevirtual 152	java/lang/reflect/Method:invoke	(Ljava/lang/Object;[Ljava/lang/Object;)Ljava/lang/Object;
    //   389: astore 4
    //   391: aload_0
    //   392: iload_1
    //   393: invokevirtual 171	o/I:ˋ	(I)Ljava/lang/String;
    //   396: astore_3
    //   397: aload_3
    //   398: iconst_4
    //   399: iconst_4
    //   400: newarray char
    //   402: dup
    //   403: iconst_0
    //   404: ldc 119
    //   406: castore
    //   407: dup
    //   408: iconst_1
    //   409: ldc -84
    //   411: castore
    //   412: dup
    //   413: iconst_2
    //   414: ldc -83
    //   416: castore
    //   417: dup
    //   418: iconst_3
    //   419: ldc -82
    //   421: castore
    //   422: bipush 61
    //   424: invokestatic 89	o/I:ॱ	(I[CB)Ljava/lang/String;
    //   427: invokevirtual 93	java/lang/String:intern	()Ljava/lang/String;
    //   430: invokevirtual 178	java/lang/String:startsWith	(Ljava/lang/String;)Z
    //   433: istore_2
    //   434: iload_2
    //   435: ifeq +6 -> 441
    //   438: goto -166 -> 272
    //   441: goto -370 -> 71
    //   444: iconst_1
    //   445: istore_1
    //   446: iload_1
    //   447: tableswitch	default:+21->468, 0:+35->482, 1:+-148->299
    //   468: goto +14 -> 482
    //   471: bipush 20
    //   473: istore_1
    //   474: goto -433 -> 41
    //   477: aload_3
    //   478: areturn
    //   479: goto -153 -> 326
    //   482: aload_0
    //   483: aload_3
    //   484: iconst_4
    //   485: invokevirtual 155	java/lang/String:substring	(I)Ljava/lang/String;
    //   488: invokespecial 157	o/I:ॱ	(Ljava/lang/String;)Ljava/lang/String;
    //   491: invokevirtual 93	java/lang/String:intern	()Ljava/lang/String;
    //   494: astore_3
    //   495: bipush 43
    //   497: iconst_0
    //   498: idiv
    //   499: istore_1
    //   500: goto -429 -> 71
    // Local variable table:
    //   start	length	slot	name	signature
    //   0	503	0	this	I
    //   0	503	1	paramInt	int
    //   433	2	2	bool	boolean
    //   71	1	3	localObject1	Object
    //   206	49	3	localObject2	Object
    //   262	1	3	str1	String
    //   266	2	3	localException1	Exception
    //   269	31	3	localException2	Exception
    //   304	41	3	localObject3	Object
    //   348	37	3	localObject4	Object
    //   396	99	3	str2	String
    //   211	179	4	localObject5	Object
    // Exception table:
    //   from	to	target	type
    //   223	263	206	finally
    //   349	355	266	java/lang/Exception
    //   360	363	266	java/lang/Exception
    //   363	365	266	java/lang/Exception
    //   299	305	269	java/lang/Exception
    //   311	316	269	java/lang/Exception
    //   326	345	269	java/lang/Exception
    //   349	355	269	java/lang/Exception
    //   360	363	269	java/lang/Exception
    //   363	365	269	java/lang/Exception
    //   391	434	269	java/lang/Exception
    //   365	391	348	finally
  }
}
