package o;

import android.annotation.SuppressLint;
import android.content.Context;
import android.content.DialogInterface;
import android.content.DialogInterface.OnCancelListener;
import android.content.pm.ApplicationInfo;
import android.content.res.Resources;
import android.databinding.ViewDataBinding;
import android.view.View;
import android.view.View.OnClickListener;
import android.widget.FrameLayout.LayoutParams;
import android.widget.RelativeLayout;

@Deprecated
@SuppressLint({"Registered"})
public abstract class IB<VDB extends ViewDataBinding>
  extends l<VDB>
{
  private static byte ʼॱ;
  private static long ʽॱ;
  private static char[] ʾ;
  private static int ʿ;
  private static int ˊˋ;
  private boolean ˈ = false;
  protected boolean ॱˋ = true;
  protected View ॱˎ;
  protected RelativeLayout ॱᐝ;
  
  static
  {
    break label62;
    return;
    for (;;)
    {
      int i;
      switch (i)
      {
      case 1: 
      default: 
        break label87;
        for (;;)
        {
          i = ˊˋ + 93;
          ʿ = i % 128;
          if (i % 2 != 0) {
            break;
          }
          break label95;
          ʿ = 0;
          ˊˋ = 1;
          ʿ();
          ʼॱ = -102;
        }
        i = 27;
        break;
      case 27: 
        label62:
        label87:
        throw new NullPointerException();
        label95:
        i = 1;
      }
    }
  }
  
  public IB() {}
  
  /* Error */
  private void ʻॱ()
  {
    // Byte code:
    //   0: goto +311 -> 311
    //   3: return
    //   4: aload_0
    //   5: invokespecial 61	o/IB:ॱˋ	()V
    //   8: goto +485 -> 493
    //   11: iconst_0
    //   12: istore_1
    //   13: goto +271 -> 284
    //   16: goto +504 -> 520
    //   19: bipush 26
    //   21: istore_1
    //   22: goto +197 -> 219
    //   25: bipush 30
    //   27: iconst_0
    //   28: idiv
    //   29: istore_1
    //   30: return
    //   31: goto +17 -> 48
    //   34: astore_2
    //   35: aload_2
    //   36: invokevirtual 67	java/lang/Throwable:getCause	()Ljava/lang/Throwable;
    //   39: astore_3
    //   40: aload_3
    //   41: ifnull +5 -> 46
    //   44: aload_3
    //   45: athrow
    //   46: aload_2
    //   47: athrow
    //   48: aload_0
    //   49: invokevirtual 73	android/content/Context:getPackageName	()Ljava/lang/String;
    //   52: invokevirtual 79	java/lang/String:length	()I
    //   55: bipush 7
    //   57: isub
    //   58: aload_0
    //   59: invokevirtual 83	android/content/Context:getResources	()Landroid/content/res/Resources;
    //   62: ldc 84
    //   64: invokevirtual 90	android/content/res/Resources:getString	(I)Ljava/lang/String;
    //   67: iconst_0
    //   68: bipush 22
    //   70: invokevirtual 94	java/lang/String:substring	(II)Ljava/lang/String;
    //   73: bipush 16
    //   75: invokevirtual 98	java/lang/String:codePointAt	(I)I
    //   78: bipush 14
    //   80: iadd
    //   81: aload_0
    //   82: invokevirtual 102	android/content/Context:getApplicationInfo	()Landroid/content/pm/ApplicationInfo;
    //   85: getfield 107	android/content/pm/ApplicationInfo:targetSdkVersion	I
    //   88: sipush 14763
    //   91: iadd
    //   92: i2c
    //   93: invokestatic 113	o/O:ˋ	(IIC)Ljava/lang/Object;
    //   96: checkcast 115	java/lang/Class
    //   99: ldc 116
    //   101: aconst_null
    //   102: invokevirtual 120	java/lang/Class:getMethod	(Ljava/lang/String;[Ljava/lang/Class;)Ljava/lang/reflect/Method;
    //   105: aconst_null
    //   106: aconst_null
    //   107: invokevirtual 126	java/lang/reflect/Method:invoke	(Ljava/lang/Object;[Ljava/lang/Object;)Ljava/lang/Object;
    //   110: astore_2
    //   111: goto +17 -> 128
    //   114: astore_2
    //   115: aload_2
    //   116: invokevirtual 67	java/lang/Throwable:getCause	()Ljava/lang/Throwable;
    //   119: astore_3
    //   120: aload_3
    //   121: ifnull +5 -> 126
    //   124: aload_3
    //   125: athrow
    //   126: aload_2
    //   127: athrow
    //   128: aload_0
    //   129: invokevirtual 73	android/content/Context:getPackageName	()Ljava/lang/String;
    //   132: invokevirtual 79	java/lang/String:length	()I
    //   135: bipush 7
    //   137: isub
    //   138: aload_0
    //   139: invokevirtual 83	android/content/Context:getResources	()Landroid/content/res/Resources;
    //   142: ldc 127
    //   144: invokevirtual 90	android/content/res/Resources:getString	(I)Ljava/lang/String;
    //   147: iconst_0
    //   148: bipush 8
    //   150: invokevirtual 94	java/lang/String:substring	(II)Ljava/lang/String;
    //   153: invokevirtual 79	java/lang/String:length	()I
    //   156: sipush 259
    //   159: iadd
    //   160: aload_0
    //   161: invokevirtual 73	android/content/Context:getPackageName	()Ljava/lang/String;
    //   164: invokevirtual 79	java/lang/String:length	()I
    //   167: sipush 14777
    //   170: iadd
    //   171: i2c
    //   172: invokestatic 113	o/O:ˋ	(IIC)Ljava/lang/Object;
    //   175: checkcast 115	java/lang/Class
    //   178: ldc -127
    //   180: iconst_1
    //   181: anewarray 115	java/lang/Class
    //   184: dup
    //   185: iconst_0
    //   186: ldc -125
    //   188: aastore
    //   189: invokevirtual 120	java/lang/Class:getMethod	(Ljava/lang/String;[Ljava/lang/Class;)Ljava/lang/reflect/Method;
    //   192: aload_2
    //   193: iconst_1
    //   194: anewarray 133	java/lang/Object
    //   197: dup
    //   198: iconst_0
    //   199: aload_0
    //   200: aastore
    //   201: invokevirtual 126	java/lang/reflect/Method:invoke	(Ljava/lang/Object;[Ljava/lang/Object;)Ljava/lang/Object;
    //   204: pop
    //   205: goto +315 -> 520
    //   208: bipush 93
    //   210: istore_1
    //   211: goto +8 -> 219
    //   214: iconst_1
    //   215: istore_1
    //   216: goto +68 -> 284
    //   219: iload_1
    //   220: lookupswitch	default:+28->248, 26:+-217->3, 93:+-195->25
    //   248: goto -223 -> 25
    //   251: astore_2
    //   252: aload_2
    //   253: athrow
    //   254: goto -250 -> 4
    //   257: getstatic 39	o/IB:ˊˋ	I
    //   260: bipush 77
    //   262: iadd
    //   263: istore_1
    //   264: iload_1
    //   265: sipush 128
    //   268: irem
    //   269: putstatic 41	o/IB:ʿ	I
    //   272: iload_1
    //   273: iconst_2
    //   274: irem
    //   275: ifeq +6 -> 281
    //   278: goto -70 -> 208
    //   281: goto -262 -> 19
    //   284: iload_1
    //   285: tableswitch	default:+23->308, 0:+238->523, 1:+-254->31
    //   308: goto -277 -> 31
    //   311: getstatic 139	o/Gw:INACTIVE_PHONE_NUMBER	Lo/Gw;
    //   314: astore_2
    //   315: goto +17 -> 332
    //   318: astore_2
    //   319: aload_2
    //   320: invokevirtual 67	java/lang/Throwable:getCause	()Ljava/lang/Throwable;
    //   323: astore_3
    //   324: aload_3
    //   325: ifnull +5 -> 330
    //   328: aload_3
    //   329: athrow
    //   330: aload_2
    //   331: athrow
    //   332: aload_0
    //   333: invokevirtual 73	android/content/Context:getPackageName	()Ljava/lang/String;
    //   336: bipush 9
    //   338: invokevirtual 98	java/lang/String:codePointAt	(I)I
    //   341: bipush 93
    //   343: isub
    //   344: aload_0
    //   345: invokevirtual 73	android/content/Context:getPackageName	()Ljava/lang/String;
    //   348: invokevirtual 79	java/lang/String:length	()I
    //   351: sipush 402
    //   354: iadd
    //   355: aload_0
    //   356: invokevirtual 83	android/content/Context:getResources	()Landroid/content/res/Resources;
    //   359: ldc -116
    //   361: invokevirtual 90	android/content/res/Resources:getString	(I)Ljava/lang/String;
    //   364: iconst_0
    //   365: iconst_5
    //   366: invokevirtual 94	java/lang/String:substring	(II)Ljava/lang/String;
    //   369: invokevirtual 79	java/lang/String:length	()I
    //   372: sipush 30248
    //   375: iadd
    //   376: i2c
    //   377: invokestatic 113	o/O:ˋ	(IIC)Ljava/lang/Object;
    //   380: checkcast 115	java/lang/Class
    //   383: ldc -114
    //   385: aconst_null
    //   386: invokevirtual 120	java/lang/Class:getMethod	(Ljava/lang/String;[Ljava/lang/Class;)Ljava/lang/reflect/Method;
    //   389: aconst_null
    //   390: aconst_null
    //   391: invokevirtual 126	java/lang/reflect/Method:invoke	(Ljava/lang/Object;[Ljava/lang/Object;)Ljava/lang/Object;
    //   394: astore_3
    //   395: goto +17 -> 412
    //   398: astore_2
    //   399: aload_2
    //   400: invokevirtual 67	java/lang/Throwable:getCause	()Ljava/lang/Throwable;
    //   403: astore_3
    //   404: aload_3
    //   405: ifnull +5 -> 410
    //   408: aload_3
    //   409: athrow
    //   410: aload_2
    //   411: athrow
    //   412: aload_0
    //   413: invokevirtual 102	android/content/Context:getApplicationInfo	()Landroid/content/pm/ApplicationInfo;
    //   416: getfield 107	android/content/pm/ApplicationInfo:targetSdkVersion	I
    //   419: bipush 21
    //   421: isub
    //   422: aload_0
    //   423: invokevirtual 83	android/content/Context:getResources	()Landroid/content/res/Resources;
    //   426: ldc -113
    //   428: invokevirtual 90	android/content/res/Resources:getString	(I)Ljava/lang/String;
    //   431: bipush 52
    //   433: bipush 59
    //   435: invokevirtual 94	java/lang/String:substring	(II)Ljava/lang/String;
    //   438: iconst_2
    //   439: invokevirtual 98	java/lang/String:codePointAt	(I)I
    //   442: sipush 158
    //   445: iadd
    //   446: aload_0
    //   447: invokevirtual 102	android/content/Context:getApplicationInfo	()Landroid/content/pm/ApplicationInfo;
    //   450: getfield 107	android/content/pm/ApplicationInfo:targetSdkVersion	I
    //   453: sipush 30228
    //   456: iadd
    //   457: i2c
    //   458: invokestatic 113	o/O:ˋ	(IIC)Ljava/lang/Object;
    //   461: checkcast 115	java/lang/Class
    //   464: ldc -111
    //   466: aconst_null
    //   467: invokevirtual 120	java/lang/Class:getMethod	(Ljava/lang/String;[Ljava/lang/Class;)Ljava/lang/reflect/Method;
    //   470: aload_3
    //   471: aconst_null
    //   472: invokevirtual 126	java/lang/reflect/Method:invoke	(Ljava/lang/Object;[Ljava/lang/Object;)Ljava/lang/Object;
    //   475: astore_3
    //   476: aload_2
    //   477: aload_3
    //   478: invokevirtual 149	o/Gw:equals	(Ljava/lang/Object;)Z
    //   481: ifeq +6 -> 487
    //   484: goto -473 -> 11
    //   487: goto -273 -> 214
    //   490: goto +30 -> 520
    //   493: getstatic 39	o/IB:ˊˋ	I
    //   496: bipush 107
    //   498: iadd
    //   499: istore_1
    //   500: iload_1
    //   501: sipush 128
    //   504: irem
    //   505: putstatic 41	o/IB:ʿ	I
    //   508: iload_1
    //   509: iconst_2
    //   510: irem
    //   511: ifeq +6 -> 517
    //   514: goto -498 -> 16
    //   517: goto -27 -> 490
    //   520: goto -263 -> 257
    //   523: getstatic 41	o/IB:ʿ	I
    //   526: istore_1
    //   527: iload_1
    //   528: bipush 13
    //   530: iadd
    //   531: istore_1
    //   532: iload_1
    //   533: sipush 128
    //   536: irem
    //   537: putstatic 39	o/IB:ˊˋ	I
    //   540: iload_1
    //   541: iconst_2
    //   542: irem
    //   543: ifne +6 -> 549
    //   546: goto -292 -> 254
    //   549: goto -545 -> 4
    // Local variable table:
    //   start	length	slot	name	signature
    //   0	552	0	this	IB
    //   12	531	1	i	int
    //   34	13	2	localObject1	Object
    //   110	1	2	localObject2	Object
    //   114	79	2	localObject3	Object
    //   251	2	2	localException	Exception
    //   314	1	2	localGw	Gw
    //   318	13	2	localObject4	Object
    //   398	79	2	localObject5	Object
    //   39	439	3	localObject6	Object
    // Exception table:
    //   from	to	target	type
    //   48	111	34	finally
    //   128	205	114	finally
    //   523	527	251	java/lang/Exception
    //   532	540	251	java/lang/Exception
    //   332	395	318	finally
    //   412	476	398	finally
  }
  
  /* Error */
  private void ʾ()
  {
    // Byte code:
    //   0: goto +861 -> 861
    //   3: bipush 30
    //   5: iconst_0
    //   6: idiv
    //   7: istore_1
    //   8: return
    //   9: aload_0
    //   10: invokevirtual 73	android/content/Context:getPackageName	()Ljava/lang/String;
    //   13: invokevirtual 79	java/lang/String:length	()I
    //   16: bipush 86
    //   18: iadd
    //   19: aload_0
    //   20: invokevirtual 83	android/content/Context:getResources	()Landroid/content/res/Resources;
    //   23: ldc -106
    //   25: invokevirtual 90	android/content/res/Resources:getString	(I)Ljava/lang/String;
    //   28: iconst_0
    //   29: iconst_4
    //   30: invokevirtual 94	java/lang/String:substring	(II)Ljava/lang/String;
    //   33: invokevirtual 79	java/lang/String:length	()I
    //   36: iconst_4
    //   37: isub
    //   38: i2c
    //   39: aload_0
    //   40: invokevirtual 83	android/content/Context:getResources	()Landroid/content/res/Resources;
    //   43: ldc -105
    //   45: invokevirtual 90	android/content/res/Resources:getString	(I)Ljava/lang/String;
    //   48: iconst_0
    //   49: iconst_4
    //   50: invokevirtual 94	java/lang/String:substring	(II)Ljava/lang/String;
    //   53: iconst_2
    //   54: invokevirtual 98	java/lang/String:codePointAt	(I)I
    //   57: iconst_4
    //   58: isub
    //   59: invokestatic 155	o/IB:ॱ	(ICI)Ljava/lang/String;
    //   62: invokevirtual 158	java/lang/String:intern	()Ljava/lang/String;
    //   65: astore_3
    //   66: aload_0
    //   67: invokevirtual 73	android/content/Context:getPackageName	()Ljava/lang/String;
    //   70: iconst_5
    //   71: invokevirtual 98	java/lang/String:codePointAt	(I)I
    //   74: bipush 10
    //   76: isub
    //   77: aload_0
    //   78: invokevirtual 102	android/content/Context:getApplicationInfo	()Landroid/content/pm/ApplicationInfo;
    //   81: getfield 107	android/content/pm/ApplicationInfo:targetSdkVersion	I
    //   84: ldc -97
    //   86: iadd
    //   87: i2c
    //   88: aload_0
    //   89: invokevirtual 73	android/content/Context:getPackageName	()Ljava/lang/String;
    //   92: invokevirtual 79	java/lang/String:length	()I
    //   95: bipush 11
    //   97: iadd
    //   98: invokestatic 155	o/IB:ॱ	(ICI)Ljava/lang/String;
    //   101: invokevirtual 158	java/lang/String:intern	()Ljava/lang/String;
    //   104: astore 4
    //   106: goto +20 -> 126
    //   109: astore_3
    //   110: aload_3
    //   111: invokevirtual 67	java/lang/Throwable:getCause	()Ljava/lang/Throwable;
    //   114: astore 4
    //   116: aload 4
    //   118: ifnull +6 -> 124
    //   121: aload 4
    //   123: athrow
    //   124: aload_3
    //   125: athrow
    //   126: aload_0
    //   127: invokevirtual 102	android/content/Context:getApplicationInfo	()Landroid/content/pm/ApplicationInfo;
    //   130: getfield 107	android/content/pm/ApplicationInfo:targetSdkVersion	I
    //   133: bipush 21
    //   135: isub
    //   136: aload_0
    //   137: invokevirtual 102	android/content/Context:getApplicationInfo	()Landroid/content/pm/ApplicationInfo;
    //   140: getfield 107	android/content/pm/ApplicationInfo:targetSdkVersion	I
    //   143: bipush 17
    //   145: iadd
    //   146: aload_0
    //   147: invokevirtual 102	android/content/Context:getApplicationInfo	()Landroid/content/pm/ApplicationInfo;
    //   150: getfield 107	android/content/pm/ApplicationInfo:targetSdkVersion	I
    //   153: ldc -96
    //   155: iadd
    //   156: i2c
    //   157: invokestatic 113	o/O:ˋ	(IIC)Ljava/lang/Object;
    //   160: checkcast 115	java/lang/Class
    //   163: ldc 116
    //   165: iconst_2
    //   166: anewarray 115	java/lang/Class
    //   169: dup
    //   170: iconst_0
    //   171: ldc 75
    //   173: aastore
    //   174: dup
    //   175: iconst_1
    //   176: ldc 75
    //   178: aastore
    //   179: invokevirtual 120	java/lang/Class:getMethod	(Ljava/lang/String;[Ljava/lang/Class;)Ljava/lang/reflect/Method;
    //   182: aconst_null
    //   183: iconst_2
    //   184: anewarray 133	java/lang/Object
    //   187: dup
    //   188: iconst_0
    //   189: aload_3
    //   190: aastore
    //   191: dup
    //   192: iconst_1
    //   193: aload 4
    //   195: aastore
    //   196: invokevirtual 126	java/lang/reflect/Method:invoke	(Ljava/lang/Object;[Ljava/lang/Object;)Ljava/lang/Object;
    //   199: pop
    //   200: goto +20 -> 220
    //   203: astore_3
    //   204: aload_3
    //   205: invokevirtual 67	java/lang/Throwable:getCause	()Ljava/lang/Throwable;
    //   208: astore 4
    //   210: aload 4
    //   212: ifnull +6 -> 218
    //   215: aload 4
    //   217: athrow
    //   218: aload_3
    //   219: athrow
    //   220: aload_0
    //   221: invokevirtual 102	android/content/Context:getApplicationInfo	()Landroid/content/pm/ApplicationInfo;
    //   224: getfield 107	android/content/pm/ApplicationInfo:targetSdkVersion	I
    //   227: bipush 21
    //   229: isub
    //   230: aload_0
    //   231: invokevirtual 73	android/content/Context:getPackageName	()Ljava/lang/String;
    //   234: bipush 10
    //   236: invokevirtual 98	java/lang/String:codePointAt	(I)I
    //   239: bipush 14
    //   241: iadd
    //   242: aload_0
    //   243: invokevirtual 83	android/content/Context:getResources	()Landroid/content/res/Resources;
    //   246: ldc -95
    //   248: invokevirtual 90	android/content/res/Resources:getString	(I)Ljava/lang/String;
    //   251: iconst_0
    //   252: iconst_4
    //   253: invokevirtual 94	java/lang/String:substring	(II)Ljava/lang/String;
    //   256: invokevirtual 79	java/lang/String:length	()I
    //   259: ldc -94
    //   261: iadd
    //   262: i2c
    //   263: invokestatic 113	o/O:ˋ	(IIC)Ljava/lang/Object;
    //   266: checkcast 115	java/lang/Class
    //   269: ldc 116
    //   271: aconst_null
    //   272: invokevirtual 120	java/lang/Class:getMethod	(Ljava/lang/String;[Ljava/lang/Class;)Ljava/lang/reflect/Method;
    //   275: aconst_null
    //   276: aconst_null
    //   277: invokevirtual 126	java/lang/reflect/Method:invoke	(Ljava/lang/Object;[Ljava/lang/Object;)Ljava/lang/Object;
    //   280: checkcast 164	o/It
    //   283: astore_3
    //   284: aload_3
    //   285: invokeinterface 168 1 0
    //   290: new 9	o/IB$2
    //   293: dup
    //   294: aload_0
    //   295: aload_0
    //   296: invokespecial 171	o/IB$2:<init>	(Lo/IB;Landroid/content/Context;)V
    //   299: invokeinterface 176 2 0
    //   304: aload_0
    //   305: iconst_1
    //   306: putfield 54	o/IB:ˈ	Z
    //   309: goto +232 -> 541
    //   312: aload_0
    //   313: invokespecial 178	o/IB:ʻॱ	()V
    //   316: goto +472 -> 788
    //   319: goto +20 -> 339
    //   322: astore_3
    //   323: aload_3
    //   324: invokevirtual 67	java/lang/Throwable:getCause	()Ljava/lang/Throwable;
    //   327: astore 4
    //   329: aload 4
    //   331: ifnull +6 -> 337
    //   334: aload 4
    //   336: athrow
    //   337: aload_3
    //   338: athrow
    //   339: aload_0
    //   340: invokevirtual 73	android/content/Context:getPackageName	()Ljava/lang/String;
    //   343: invokevirtual 79	java/lang/String:length	()I
    //   346: bipush 7
    //   348: isub
    //   349: aload_0
    //   350: invokevirtual 83	android/content/Context:getResources	()Landroid/content/res/Resources;
    //   353: ldc -77
    //   355: invokevirtual 90	android/content/res/Resources:getString	(I)Ljava/lang/String;
    //   358: iconst_0
    //   359: iconst_4
    //   360: invokevirtual 94	java/lang/String:substring	(II)Ljava/lang/String;
    //   363: iconst_3
    //   364: invokevirtual 98	java/lang/String:codePointAt	(I)I
    //   367: sipush 401
    //   370: iadd
    //   371: aload_0
    //   372: invokevirtual 83	android/content/Context:getResources	()Landroid/content/res/Resources;
    //   375: ldc -76
    //   377: invokevirtual 90	android/content/res/Resources:getString	(I)Ljava/lang/String;
    //   380: bipush 7
    //   382: bipush 15
    //   384: invokevirtual 94	java/lang/String:substring	(II)Ljava/lang/String;
    //   387: bipush 6
    //   389: invokevirtual 98	java/lang/String:codePointAt	(I)I
    //   392: sipush 30020
    //   395: iadd
    //   396: i2c
    //   397: invokestatic 113	o/O:ˋ	(IIC)Ljava/lang/Object;
    //   400: checkcast 115	java/lang/Class
    //   403: ldc -114
    //   405: aconst_null
    //   406: invokevirtual 120	java/lang/Class:getMethod	(Ljava/lang/String;[Ljava/lang/Class;)Ljava/lang/reflect/Method;
    //   409: aconst_null
    //   410: aconst_null
    //   411: invokevirtual 126	java/lang/reflect/Method:invoke	(Ljava/lang/Object;[Ljava/lang/Object;)Ljava/lang/Object;
    //   414: astore_3
    //   415: goto +20 -> 435
    //   418: astore_3
    //   419: aload_3
    //   420: invokevirtual 67	java/lang/Throwable:getCause	()Ljava/lang/Throwable;
    //   423: astore 4
    //   425: aload 4
    //   427: ifnull +6 -> 433
    //   430: aload 4
    //   432: athrow
    //   433: aload_3
    //   434: athrow
    //   435: aload_0
    //   436: invokevirtual 83	android/content/Context:getResources	()Landroid/content/res/Resources;
    //   439: ldc -75
    //   441: invokevirtual 90	android/content/res/Resources:getString	(I)Ljava/lang/String;
    //   444: iconst_0
    //   445: iconst_5
    //   446: invokevirtual 94	java/lang/String:substring	(II)Ljava/lang/String;
    //   449: invokevirtual 79	java/lang/String:length	()I
    //   452: iconst_1
    //   453: isub
    //   454: aload_0
    //   455: invokevirtual 102	android/content/Context:getApplicationInfo	()Landroid/content/pm/ApplicationInfo;
    //   458: getfield 107	android/content/pm/ApplicationInfo:targetSdkVersion	I
    //   461: sipush 388
    //   464: iadd
    //   465: aload_0
    //   466: invokevirtual 83	android/content/Context:getResources	()Landroid/content/res/Resources;
    //   469: ldc -74
    //   471: invokevirtual 90	android/content/res/Resources:getString	(I)Ljava/lang/String;
    //   474: iconst_0
    //   475: iconst_4
    //   476: invokevirtual 94	java/lang/String:substring	(II)Ljava/lang/String;
    //   479: invokevirtual 79	java/lang/String:length	()I
    //   482: sipush 30249
    //   485: iadd
    //   486: i2c
    //   487: invokestatic 113	o/O:ˋ	(IIC)Ljava/lang/Object;
    //   490: checkcast 115	java/lang/Class
    //   493: ldc -111
    //   495: aconst_null
    //   496: invokevirtual 120	java/lang/Class:getMethod	(Ljava/lang/String;[Ljava/lang/Class;)Ljava/lang/reflect/Method;
    //   499: aload_3
    //   500: aconst_null
    //   501: invokevirtual 126	java/lang/reflect/Method:invoke	(Ljava/lang/Object;[Ljava/lang/Object;)Ljava/lang/Object;
    //   504: checkcast 135	o/Gw
    //   507: astore_3
    //   508: getstatic 139	o/Gw:INACTIVE_PHONE_NUMBER	Lo/Gw;
    //   511: astore 4
    //   513: aload_3
    //   514: iconst_2
    //   515: anewarray 135	o/Gw
    //   518: dup
    //   519: iconst_0
    //   520: getstatic 185	o/Gw:ACTIVE_REGISTERED	Lo/Gw;
    //   523: aastore
    //   524: dup
    //   525: iconst_1
    //   526: aload 4
    //   528: aastore
    //   529: invokevirtual 189	o/Gw:ˎ	([Lo/Gw;)Z
    //   532: ifeq +6 -> 538
    //   535: goto -526 -> 9
    //   538: goto -226 -> 312
    //   541: getstatic 41	o/IB:ʿ	I
    //   544: bipush 35
    //   546: iadd
    //   547: istore_1
    //   548: iload_1
    //   549: sipush 128
    //   552: irem
    //   553: putstatic 39	o/IB:ˊˋ	I
    //   556: iload_1
    //   557: iconst_2
    //   558: irem
    //   559: ifne +6 -> 565
    //   562: goto +208 -> 770
    //   565: goto +226 -> 791
    //   568: goto +20 -> 588
    //   571: astore_3
    //   572: aload_3
    //   573: invokevirtual 67	java/lang/Throwable:getCause	()Ljava/lang/Throwable;
    //   576: astore 4
    //   578: aload 4
    //   580: ifnull +6 -> 586
    //   583: aload 4
    //   585: athrow
    //   586: aload_3
    //   587: athrow
    //   588: aload_0
    //   589: invokevirtual 83	android/content/Context:getResources	()Landroid/content/res/Resources;
    //   592: ldc -66
    //   594: invokevirtual 90	android/content/res/Resources:getString	(I)Ljava/lang/String;
    //   597: iconst_0
    //   598: iconst_4
    //   599: invokevirtual 94	java/lang/String:substring	(II)Ljava/lang/String;
    //   602: iconst_0
    //   603: invokevirtual 98	java/lang/String:codePointAt	(I)I
    //   606: iconst_2
    //   607: isub
    //   608: aload_0
    //   609: invokevirtual 73	android/content/Context:getPackageName	()Ljava/lang/String;
    //   612: bipush 7
    //   614: invokevirtual 98	java/lang/String:codePointAt	(I)I
    //   617: bipush 22
    //   619: isub
    //   620: aload_0
    //   621: invokevirtual 83	android/content/Context:getResources	()Landroid/content/res/Resources;
    //   624: ldc -65
    //   626: invokevirtual 90	android/content/res/Resources:getString	(I)Ljava/lang/String;
    //   629: iconst_0
    //   630: iconst_5
    //   631: invokevirtual 94	java/lang/String:substring	(II)Ljava/lang/String;
    //   634: iconst_3
    //   635: invokevirtual 98	java/lang/String:codePointAt	(I)I
    //   638: bipush 12
    //   640: isub
    //   641: i2c
    //   642: invokestatic 113	o/O:ˋ	(IIC)Ljava/lang/Object;
    //   645: checkcast 115	java/lang/Class
    //   648: ldc -64
    //   650: aconst_null
    //   651: invokevirtual 120	java/lang/Class:getMethod	(Ljava/lang/String;[Ljava/lang/Class;)Ljava/lang/reflect/Method;
    //   654: aconst_null
    //   655: aconst_null
    //   656: invokevirtual 126	java/lang/reflect/Method:invoke	(Ljava/lang/Object;[Ljava/lang/Object;)Ljava/lang/Object;
    //   659: astore_3
    //   660: goto +20 -> 680
    //   663: astore_3
    //   664: aload_3
    //   665: invokevirtual 67	java/lang/Throwable:getCause	()Ljava/lang/Throwable;
    //   668: astore 4
    //   670: aload 4
    //   672: ifnull +6 -> 678
    //   675: aload 4
    //   677: athrow
    //   678: aload_3
    //   679: athrow
    //   680: aload_0
    //   681: invokevirtual 102	android/content/Context:getApplicationInfo	()Landroid/content/pm/ApplicationInfo;
    //   684: getfield 107	android/content/pm/ApplicationInfo:targetSdkVersion	I
    //   687: bipush 22
    //   689: isub
    //   690: aload_0
    //   691: invokevirtual 102	android/content/Context:getApplicationInfo	()Landroid/content/pm/ApplicationInfo;
    //   694: getfield 107	android/content/pm/ApplicationInfo:targetSdkVersion	I
    //   697: iconst_1
    //   698: isub
    //   699: aload_0
    //   700: invokevirtual 83	android/content/Context:getResources	()Landroid/content/res/Resources;
    //   703: ldc -63
    //   705: invokevirtual 90	android/content/res/Resources:getString	(I)Ljava/lang/String;
    //   708: iconst_0
    //   709: iconst_5
    //   710: invokevirtual 94	java/lang/String:substring	(II)Ljava/lang/String;
    //   713: iconst_3
    //   714: invokevirtual 98	java/lang/String:codePointAt	(I)I
    //   717: bipush 12
    //   719: isub
    //   720: i2c
    //   721: invokestatic 113	o/O:ˋ	(IIC)Ljava/lang/Object;
    //   724: checkcast 115	java/lang/Class
    //   727: ldc -64
    //   729: iconst_1
    //   730: anewarray 115	java/lang/Class
    //   733: dup
    //   734: iconst_0
    //   735: ldc 69
    //   737: aastore
    //   738: invokevirtual 120	java/lang/Class:getMethod	(Ljava/lang/String;[Ljava/lang/Class;)Ljava/lang/reflect/Method;
    //   741: aload_3
    //   742: iconst_1
    //   743: anewarray 133	java/lang/Object
    //   746: dup
    //   747: iconst_0
    //   748: aload_0
    //   749: aastore
    //   750: invokevirtual 126	java/lang/reflect/Method:invoke	(Ljava/lang/Object;[Ljava/lang/Object;)Ljava/lang/Object;
    //   753: checkcast 195	java/lang/Boolean
    //   756: invokevirtual 199	java/lang/Boolean:booleanValue	()Z
    //   759: istore_2
    //   760: iload_2
    //   761: ifeq +6 -> 767
    //   764: goto +345 -> 1109
    //   767: goto +35 -> 802
    //   770: goto +18 -> 788
    //   773: aload_0
    //   774: getfield 54	o/IB:ˈ	Z
    //   777: istore_2
    //   778: iload_2
    //   779: ifne +6 -> 785
    //   782: goto +300 -> 1082
    //   785: goto -473 -> 312
    //   788: goto +326 -> 1114
    //   791: goto -3 -> 788
    //   794: iconst_1
    //   795: istore_1
    //   796: goto +41 -> 837
    //   799: astore_3
    //   800: aload_3
    //   801: athrow
    //   802: iconst_1
    //   803: istore_1
    //   804: goto +4 -> 808
    //   807: return
    //   808: iload_1
    //   809: tableswitch	default:+23->832, 0:+-36->773, 1:+-497->312
    //   832: goto -59 -> 773
    //   835: iconst_0
    //   836: istore_1
    //   837: iload_1
    //   838: tableswitch	default:+22->860, 0:+-835->3, 1:+-31->807
    //   860: return
    //   861: goto -293 -> 568
    //   864: goto +20 -> 884
    //   867: astore_3
    //   868: aload_3
    //   869: invokevirtual 67	java/lang/Throwable:getCause	()Ljava/lang/Throwable;
    //   872: astore 4
    //   874: aload 4
    //   876: ifnull +6 -> 882
    //   879: aload 4
    //   881: athrow
    //   882: aload_3
    //   883: athrow
    //   884: aload_0
    //   885: invokevirtual 102	android/content/Context:getApplicationInfo	()Landroid/content/pm/ApplicationInfo;
    //   888: getfield 107	android/content/pm/ApplicationInfo:targetSdkVersion	I
    //   891: bipush 21
    //   893: isub
    //   894: aload_0
    //   895: invokevirtual 83	android/content/Context:getResources	()Landroid/content/res/Resources;
    //   898: ldc -56
    //   900: invokevirtual 90	android/content/res/Resources:getString	(I)Ljava/lang/String;
    //   903: iconst_0
    //   904: iconst_4
    //   905: invokevirtual 94	java/lang/String:substring	(II)Ljava/lang/String;
    //   908: iconst_3
    //   909: invokevirtual 98	java/lang/String:codePointAt	(I)I
    //   912: sipush 401
    //   915: iadd
    //   916: aload_0
    //   917: invokevirtual 83	android/content/Context:getResources	()Landroid/content/res/Resources;
    //   920: ldc -76
    //   922: invokevirtual 90	android/content/res/Resources:getString	(I)Ljava/lang/String;
    //   925: bipush 7
    //   927: bipush 15
    //   929: invokevirtual 94	java/lang/String:substring	(II)Ljava/lang/String;
    //   932: invokevirtual 79	java/lang/String:length	()I
    //   935: sipush 30245
    //   938: iadd
    //   939: i2c
    //   940: invokestatic 113	o/O:ˋ	(IIC)Ljava/lang/Object;
    //   943: checkcast 115	java/lang/Class
    //   946: ldc -114
    //   948: aconst_null
    //   949: invokevirtual 120	java/lang/Class:getMethod	(Ljava/lang/String;[Ljava/lang/Class;)Ljava/lang/reflect/Method;
    //   952: aconst_null
    //   953: aconst_null
    //   954: invokevirtual 126	java/lang/reflect/Method:invoke	(Ljava/lang/Object;[Ljava/lang/Object;)Ljava/lang/Object;
    //   957: astore_3
    //   958: goto +20 -> 978
    //   961: astore_3
    //   962: aload_3
    //   963: invokevirtual 67	java/lang/Throwable:getCause	()Ljava/lang/Throwable;
    //   966: astore 4
    //   968: aload 4
    //   970: ifnull +6 -> 976
    //   973: aload 4
    //   975: athrow
    //   976: aload_3
    //   977: athrow
    //   978: aload_0
    //   979: invokevirtual 102	android/content/Context:getApplicationInfo	()Landroid/content/pm/ApplicationInfo;
    //   982: getfield 107	android/content/pm/ApplicationInfo:targetSdkVersion	I
    //   985: bipush 21
    //   987: isub
    //   988: aload_0
    //   989: invokevirtual 83	android/content/Context:getResources	()Landroid/content/res/Resources;
    //   992: ldc -55
    //   994: invokevirtual 90	android/content/res/Resources:getString	(I)Ljava/lang/String;
    //   997: iconst_0
    //   998: iconst_1
    //   999: invokevirtual 94	java/lang/String:substring	(II)Ljava/lang/String;
    //   1002: invokevirtual 79	java/lang/String:length	()I
    //   1005: sipush 412
    //   1008: iadd
    //   1009: aload_0
    //   1010: invokevirtual 83	android/content/Context:getResources	()Landroid/content/res/Resources;
    //   1013: ldc -54
    //   1015: invokevirtual 90	android/content/res/Resources:getString	(I)Ljava/lang/String;
    //   1018: iconst_0
    //   1019: iconst_4
    //   1020: invokevirtual 94	java/lang/String:substring	(II)Ljava/lang/String;
    //   1023: iconst_1
    //   1024: invokevirtual 98	java/lang/String:codePointAt	(I)I
    //   1027: sipush 30227
    //   1030: iadd
    //   1031: i2c
    //   1032: invokestatic 113	o/O:ˋ	(IIC)Ljava/lang/Object;
    //   1035: checkcast 115	java/lang/Class
    //   1038: ldc -111
    //   1040: aconst_null
    //   1041: invokevirtual 120	java/lang/Class:getMethod	(Ljava/lang/String;[Ljava/lang/Class;)Ljava/lang/reflect/Method;
    //   1044: aload_3
    //   1045: aconst_null
    //   1046: invokevirtual 126	java/lang/reflect/Method:invoke	(Ljava/lang/Object;[Ljava/lang/Object;)Ljava/lang/Object;
    //   1049: checkcast 135	o/Gw
    //   1052: astore_3
    //   1053: aload_3
    //   1054: iconst_2
    //   1055: anewarray 135	o/Gw
    //   1058: dup
    //   1059: iconst_0
    //   1060: getstatic 139	o/Gw:INACTIVE_PHONE_NUMBER	Lo/Gw;
    //   1063: aastore
    //   1064: dup
    //   1065: iconst_1
    //   1066: getstatic 185	o/Gw:ACTIVE_REGISTERED	Lo/Gw;
    //   1069: aastore
    //   1070: invokevirtual 189	o/Gw:ˎ	([Lo/Gw;)Z
    //   1073: ifeq +6 -> 1079
    //   1076: goto -1067 -> 9
    //   1079: goto -767 -> 312
    //   1082: getstatic 39	o/IB:ˊˋ	I
    //   1085: bipush 123
    //   1087: iadd
    //   1088: istore_1
    //   1089: iload_1
    //   1090: sipush 128
    //   1093: irem
    //   1094: putstatic 41	o/IB:ʿ	I
    //   1097: iload_1
    //   1098: iconst_2
    //   1099: irem
    //   1100: ifeq +6 -> 1106
    //   1103: goto -784 -> 319
    //   1106: goto -242 -> 864
    //   1109: iconst_0
    //   1110: istore_1
    //   1111: goto -303 -> 808
    //   1114: getstatic 39	o/IB:ˊˋ	I
    //   1117: bipush 33
    //   1119: iadd
    //   1120: istore_1
    //   1121: iload_1
    //   1122: sipush 128
    //   1125: irem
    //   1126: putstatic 41	o/IB:ʿ	I
    //   1129: iload_1
    //   1130: iconst_2
    //   1131: irem
    //   1132: ifeq +6 -> 1138
    //   1135: goto -300 -> 835
    //   1138: goto -344 -> 794
    // Local variable table:
    //   start	length	slot	name	signature
    //   0	1141	0	this	IB
    //   7	1125	1	i	int
    //   759	20	2	bool	boolean
    //   65	1	3	str	String
    //   109	81	3	localObject1	Object
    //   203	16	3	localObject2	Object
    //   283	2	3	localIt	It
    //   322	16	3	localObject3	Object
    //   414	1	3	localObject4	Object
    //   418	82	3	localObject5	Object
    //   507	7	3	localGw1	Gw
    //   571	16	3	localObject6	Object
    //   659	1	3	localObject7	Object
    //   663	79	3	localObject8	Object
    //   799	2	3	localException	Exception
    //   867	16	3	localObject9	Object
    //   957	1	3	localObject10	Object
    //   961	84	3	localObject11	Object
    //   1052	2	3	localGw2	Gw
    //   104	870	4	localObject12	Object
    // Exception table:
    //   from	to	target	type
    //   126	200	109	finally
    //   220	284	203	finally
    //   339	415	322	finally
    //   435	508	418	finally
    //   588	660	571	finally
    //   680	760	663	finally
    //   773	778	799	java/lang/Exception
    //   884	958	867	finally
    //   978	1053	961	finally
  }
  
  static void ʿ()
  {
    ʽॱ = -5988924624432716376L;
    ʾ = new char[] { 30932, 23879, 13296, 2073, -4540, -15188, -26288, 32633, 21984, 10780, 101, -6452, -17649, -28294, 30681, 19513, 8812, -1912, -8928, -19559, -30265, 28205, 17628, 6840, -204, -10880, -21515, -32744, 26258, 15591, 4447, -2132, -12896, -23973, 30904, 23831, 13141, 2468, -4588, -15304, -25950, 32525, 21808, 11225, 64, -6566, -17195, -28364, 30561, 19932, 8761, -1906, -8507, -19708, -30319, 28641, 17455, 6813, -3868, -10984, -21620, -32279, 26185, 15543, 4853, -2212, 5, 9650, 19291, 28916, -12576, -5276, -31351, -16857, 22628, 29341, 12053, -13962, -7256, 8282, 1502, 27443, 20637, -18722, -25561, -15929, 10215, 3380, 29338, 22695, -16822, -7291, -13843, 12104, 5309, 31405, -24545, 78, 9677, 19236, 28815, -26929, -17350, -7781, -17432, -24981, -3938, -13520, 11616, 1930, 23093, -17324, -26933, -5836, -15526, 9727, 30759, 21062, -19217, -28845, -7869, 15334, 7706, 28863, 19199, -21237, 2898, 11992, 16427, 31624, -25145, -18628, -5495, 67, 9664, 19249, 28822, -26937, -17375, -7778, 2047, 11616, 21129, 30944, -25016, -15424, -5660, 3921, 13494, 23271, -32675, -23119, -13537, -3771, 5864, 15364, 25207, -30752, 13435, 4553, 32557, 17639, -23894, -30654, -10761, 13203, 6495, 26347, 85, 9724, 19222, 28885, -26984 };
  }
  
  private static String ॱ(int paramInt1, char paramChar, int paramInt2)
  {
    break label14;
    int j = paramChar;
    int k = paramInt1;
    int i;
    paramInt1 = i;
    break label27;
    label14:
    break label269;
    char[] arrayOfChar;
    return new String(arrayOfChar);
    label27:
    if (paramInt1 >= paramInt2)
    {
      break label296;
      label38:
      paramChar = ';';
    }
    for (;;)
    {
      switch (paramChar)
      {
      case '\000': 
      default: 
        break;
        switch (i)
        {
        }
        break;
      case '\001': 
        for (;;)
        {
          label71:
          switch (paramChar)
          {
          default: 
            break label230;
            i = 1;
            break label71;
            arrayOfChar = new char[paramInt2];
            i = 0;
            break;
            arrayOfChar = new char[paramInt2];
            i = 1;
            break;
            paramChar = ˊˋ + 11;
            ʿ = paramChar % '';
            if (paramChar % '\002' != 0) {
              break label38;
            }
            break;
          case 'L': 
            label131:
            arrayOfChar[paramInt1] = ((char)(int)(ʾ[(k + paramInt1)] ^ paramInt1 * ʽॱ ^ j));
            paramInt1 += 1;
            break label227;
            paramChar = 'L';
          }
        }
        paramChar = '\001';
        continue;
        for (;;)
        {
          label227:
          break;
          label230:
          arrayOfChar[paramInt1] = ((char)(int)((ʾ[(k % paramInt1)] | paramInt1 ^ ʽॱ) & j));
          paramInt1 += 82;
        }
        for (;;)
        {
          i = 0;
          break;
          label269:
          i = ʿ + 69;
          ˊˋ = i % 128;
          if (i % 2 == 0) {
            break label131;
          }
        }
        label296:
        paramChar = '\000';
      }
    }
  }
  
  /* Error */
  private String ॱ(String paramString)
  {
    // Byte code:
    //   0: goto +17 -> 17
    //   3: goto +84 -> 87
    //   6: iconst_1
    //   7: istore_3
    //   8: goto +52 -> 60
    //   11: astore_1
    //   12: aload_1
    //   13: athrow
    //   14: astore_1
    //   15: aload_1
    //   16: athrow
    //   17: goto +195 -> 212
    //   20: getstatic 39	o/IB:ˊˋ	I
    //   23: bipush 47
    //   25: iadd
    //   26: istore_3
    //   27: iload_3
    //   28: sipush 128
    //   31: irem
    //   32: putstatic 41	o/IB:ʿ	I
    //   35: iload_3
    //   36: iconst_2
    //   37: irem
    //   38: ifeq +6 -> 44
    //   41: goto -38 -> 3
    //   44: goto +43 -> 87
    //   47: goto +191 -> 238
    //   50: astore_1
    //   51: new 395	java/lang/RuntimeException
    //   54: dup
    //   55: aload_1
    //   56: invokespecial 398	java/lang/RuntimeException:<init>	(Ljava/lang/Throwable;)V
    //   59: athrow
    //   60: iload_3
    //   61: tableswitch	default:+23->84, 0:+50->111, 1:+-41->20
    //   84: goto +27 -> 111
    //   87: aload 4
    //   89: iload_2
    //   90: aload_1
    //   91: aload_1
    //   92: arraylength
    //   93: iload_2
    //   94: isub
    //   95: iconst_1
    //   96: isub
    //   97: baload
    //   98: getstatic 45	o/IB:ʼॱ	B
    //   101: ixor
    //   102: i2b
    //   103: bastore
    //   104: iload_2
    //   105: iconst_1
    //   106: iadd
    //   107: istore_2
    //   108: goto +90 -> 198
    //   111: new 75	java/lang/String
    //   114: dup
    //   115: aload 4
    //   117: aload_0
    //   118: invokevirtual 83	android/content/Context:getResources	()Landroid/content/res/Resources;
    //   121: ldc_w 399
    //   124: invokevirtual 90	android/content/res/Resources:getString	(I)Ljava/lang/String;
    //   127: iconst_0
    //   128: iconst_5
    //   129: invokevirtual 94	java/lang/String:substring	(II)Ljava/lang/String;
    //   132: invokevirtual 79	java/lang/String:length	()I
    //   135: sipush 163
    //   138: iadd
    //   139: aload_0
    //   140: invokevirtual 83	android/content/Context:getResources	()Landroid/content/res/Resources;
    //   143: ldc_w 400
    //   146: invokevirtual 90	android/content/res/Resources:getString	(I)Ljava/lang/String;
    //   149: iconst_0
    //   150: iconst_5
    //   151: invokevirtual 94	java/lang/String:substring	(II)Ljava/lang/String;
    //   154: invokevirtual 79	java/lang/String:length	()I
    //   157: iconst_5
    //   158: isub
    //   159: i2c
    //   160: aload_0
    //   161: invokevirtual 83	android/content/Context:getResources	()Landroid/content/res/Resources;
    //   164: ldc_w 401
    //   167: invokevirtual 90	android/content/res/Resources:getString	(I)Ljava/lang/String;
    //   170: iconst_0
    //   171: iconst_4
    //   172: invokevirtual 94	java/lang/String:substring	(II)Ljava/lang/String;
    //   175: iconst_0
    //   176: invokevirtual 98	java/lang/String:codePointAt	(I)I
    //   179: iconst_0
    //   180: iadd
    //   181: invokestatic 155	o/IB:ॱ	(ICI)Ljava/lang/String;
    //   184: invokevirtual 158	java/lang/String:intern	()Ljava/lang/String;
    //   187: invokespecial 404	java/lang/String:<init>	([BLjava/lang/String;)V
    //   190: astore_1
    //   191: aload_1
    //   192: areturn
    //   193: iconst_0
    //   194: istore_3
    //   195: goto -135 -> 60
    //   198: aload_1
    //   199: arraylength
    //   200: istore_3
    //   201: iload_2
    //   202: iload_3
    //   203: if_icmpge +6 -> 209
    //   206: goto -200 -> 6
    //   209: goto -16 -> 193
    //   212: getstatic 39	o/IB:ˊˋ	I
    //   215: istore_2
    //   216: iload_2
    //   217: bipush 101
    //   219: iadd
    //   220: istore_2
    //   221: iload_2
    //   222: sipush 128
    //   225: irem
    //   226: putstatic 41	o/IB:ʿ	I
    //   229: iload_2
    //   230: iconst_2
    //   231: irem
    //   232: ifeq +6 -> 238
    //   235: goto -188 -> 47
    //   238: aload_1
    //   239: aload_0
    //   240: invokevirtual 73	android/content/Context:getPackageName	()Ljava/lang/String;
    //   243: invokevirtual 79	java/lang/String:length	()I
    //   246: sipush 147
    //   249: iadd
    //   250: aload_0
    //   251: invokevirtual 83	android/content/Context:getResources	()Landroid/content/res/Resources;
    //   254: ldc_w 405
    //   257: invokevirtual 90	android/content/res/Resources:getString	(I)Ljava/lang/String;
    //   260: iconst_0
    //   261: iconst_4
    //   262: invokevirtual 94	java/lang/String:substring	(II)Ljava/lang/String;
    //   265: iconst_2
    //   266: invokevirtual 98	java/lang/String:codePointAt	(I)I
    //   269: sipush 13351
    //   272: iadd
    //   273: i2c
    //   274: aload_0
    //   275: invokevirtual 102	android/content/Context:getApplicationInfo	()Landroid/content/pm/ApplicationInfo;
    //   278: getfield 107	android/content/pm/ApplicationInfo:targetSdkVersion	I
    //   281: bipush 15
    //   283: isub
    //   284: invokestatic 155	o/IB:ॱ	(ICI)Ljava/lang/String;
    //   287: invokevirtual 158	java/lang/String:intern	()Ljava/lang/String;
    //   290: invokevirtual 409	java/lang/String:getBytes	(Ljava/lang/String;)[B
    //   293: astore_1
    //   294: aload_1
    //   295: arraylength
    //   296: newarray byte
    //   298: astore 4
    //   300: iconst_0
    //   301: istore_2
    //   302: goto -104 -> 198
    // Local variable table:
    //   start	length	slot	name	signature
    //   0	305	0	this	IB
    //   0	305	1	paramString	String
    //   89	213	2	i	int
    //   7	197	3	j	int
    //   87	212	4	arrayOfByte	byte[]
    // Exception table:
    //   from	to	target	type
    //   20	27	11	java/lang/Exception
    //   27	35	11	java/lang/Exception
    //   27	35	14	java/lang/Exception
    //   212	216	14	java/lang/Exception
    //   221	229	14	java/lang/Exception
    //   87	104	50	java/io/UnsupportedEncodingException
    //   111	191	50	java/io/UnsupportedEncodingException
    //   198	201	50	java/io/UnsupportedEncodingException
    //   238	300	50	java/io/UnsupportedEncodingException
  }
  
  /* Error */
  private void ॱˋ()
  {
    // Byte code:
    //   0: goto +334 -> 334
    //   3: astore_3
    //   4: aload_3
    //   5: athrow
    //   6: goto +3 -> 9
    //   9: getstatic 41	o/IB:ʿ	I
    //   12: bipush 71
    //   14: iadd
    //   15: istore_1
    //   16: iload_1
    //   17: sipush 128
    //   20: irem
    //   21: putstatic 39	o/IB:ˊˋ	I
    //   24: iload_1
    //   25: iconst_2
    //   26: irem
    //   27: ifne +6 -> 33
    //   30: goto +589 -> 619
    //   33: return
    //   34: goto +20 -> 54
    //   37: astore_3
    //   38: aload_3
    //   39: invokevirtual 67	java/lang/Throwable:getCause	()Ljava/lang/Throwable;
    //   42: astore 4
    //   44: aload 4
    //   46: ifnull +6 -> 52
    //   49: aload 4
    //   51: athrow
    //   52: aload_3
    //   53: athrow
    //   54: aload_0
    //   55: invokevirtual 102	android/content/Context:getApplicationInfo	()Landroid/content/pm/ApplicationInfo;
    //   58: getfield 107	android/content/pm/ApplicationInfo:targetSdkVersion	I
    //   61: bipush 21
    //   63: isub
    //   64: aload_0
    //   65: invokevirtual 102	android/content/Context:getApplicationInfo	()Landroid/content/pm/ApplicationInfo;
    //   68: getfield 107	android/content/pm/ApplicationInfo:targetSdkVersion	I
    //   71: sipush 242
    //   74: iadd
    //   75: aload_0
    //   76: invokevirtual 83	android/content/Context:getResources	()Landroid/content/res/Resources;
    //   79: ldc_w 410
    //   82: invokevirtual 90	android/content/res/Resources:getString	(I)Ljava/lang/String;
    //   85: iconst_0
    //   86: iconst_5
    //   87: invokevirtual 94	java/lang/String:substring	(II)Ljava/lang/String;
    //   90: iconst_1
    //   91: invokevirtual 98	java/lang/String:codePointAt	(I)I
    //   94: sipush 14762
    //   97: iadd
    //   98: i2c
    //   99: invokestatic 113	o/O:ˋ	(IIC)Ljava/lang/Object;
    //   102: checkcast 115	java/lang/Class
    //   105: ldc 116
    //   107: aconst_null
    //   108: invokevirtual 120	java/lang/Class:getMethod	(Ljava/lang/String;[Ljava/lang/Class;)Ljava/lang/reflect/Method;
    //   111: aconst_null
    //   112: aconst_null
    //   113: invokevirtual 126	java/lang/reflect/Method:invoke	(Ljava/lang/Object;[Ljava/lang/Object;)Ljava/lang/Object;
    //   116: astore_3
    //   117: goto +20 -> 137
    //   120: astore_3
    //   121: aload_3
    //   122: invokevirtual 67	java/lang/Throwable:getCause	()Ljava/lang/Throwable;
    //   125: astore 4
    //   127: aload 4
    //   129: ifnull +6 -> 135
    //   132: aload 4
    //   134: athrow
    //   135: aload_3
    //   136: athrow
    //   137: aload_0
    //   138: invokevirtual 83	android/content/Context:getResources	()Landroid/content/res/Resources;
    //   141: ldc_w 411
    //   144: invokevirtual 90	android/content/res/Resources:getString	(I)Ljava/lang/String;
    //   147: iconst_0
    //   148: iconst_4
    //   149: invokevirtual 94	java/lang/String:substring	(II)Ljava/lang/String;
    //   152: invokevirtual 79	java/lang/String:length	()I
    //   155: iconst_0
    //   156: iadd
    //   157: aload_0
    //   158: invokevirtual 73	android/content/Context:getPackageName	()Ljava/lang/String;
    //   161: bipush 8
    //   163: invokevirtual 98	java/lang/String:codePointAt	(I)I
    //   166: sipush 155
    //   169: iadd
    //   170: aload_0
    //   171: invokevirtual 83	android/content/Context:getResources	()Landroid/content/res/Resources;
    //   174: ldc_w 412
    //   177: invokevirtual 90	android/content/res/Resources:getString	(I)Ljava/lang/String;
    //   180: iconst_0
    //   181: iconst_4
    //   182: invokevirtual 94	java/lang/String:substring	(II)Ljava/lang/String;
    //   185: invokevirtual 79	java/lang/String:length	()I
    //   188: sipush 14784
    //   191: iadd
    //   192: i2c
    //   193: invokestatic 113	o/O:ˋ	(IIC)Ljava/lang/Object;
    //   196: checkcast 115	java/lang/Class
    //   199: ldc_w 413
    //   202: aconst_null
    //   203: invokevirtual 120	java/lang/Class:getMethod	(Ljava/lang/String;[Ljava/lang/Class;)Ljava/lang/reflect/Method;
    //   206: aload_3
    //   207: aconst_null
    //   208: invokevirtual 126	java/lang/reflect/Method:invoke	(Ljava/lang/Object;[Ljava/lang/Object;)Ljava/lang/Object;
    //   211: pop
    //   212: aload_0
    //   213: getfield 56	o/IB:ॱˋ	Z
    //   216: istore_2
    //   217: iload_2
    //   218: ifeq +6 -> 224
    //   221: goto +402 -> 623
    //   224: goto +75 -> 299
    //   227: getstatic 41	o/IB:ʿ	I
    //   230: bipush 21
    //   232: iadd
    //   233: istore_1
    //   234: iload_1
    //   235: sipush 128
    //   238: irem
    //   239: putstatic 39	o/IB:ˊˋ	I
    //   242: iload_1
    //   243: iconst_2
    //   244: irem
    //   245: ifne +6 -> 251
    //   248: goto +48 -> 296
    //   251: goto -217 -> 34
    //   254: goto +29 -> 283
    //   257: iload_1
    //   258: tableswitch	default:+22->280, 0:+-252->6, 1:+46->304
    //   280: goto -274 -> 6
    //   283: aload_0
    //   284: getfield 416	o/IB:ᐝॱ	Z
    //   287: ifeq +6 -> 293
    //   290: goto +47 -> 337
    //   293: goto -287 -> 6
    //   296: goto -262 -> 34
    //   299: iconst_0
    //   300: istore_1
    //   301: goto -44 -> 257
    //   304: getstatic 39	o/IB:ˊˋ	I
    //   307: bipush 125
    //   309: iadd
    //   310: istore_1
    //   311: iload_1
    //   312: sipush 128
    //   315: irem
    //   316: putstatic 41	o/IB:ʿ	I
    //   319: iload_1
    //   320: iconst_2
    //   321: irem
    //   322: ifeq +6 -> 328
    //   325: goto -71 -> 254
    //   328: goto -45 -> 283
    //   331: goto -325 -> 6
    //   334: goto -107 -> 227
    //   337: aload_0
    //   338: invokevirtual 83	android/content/Context:getResources	()Landroid/content/res/Resources;
    //   341: ldc_w 417
    //   344: invokevirtual 90	android/content/res/Resources:getString	(I)Ljava/lang/String;
    //   347: iconst_0
    //   348: bipush 7
    //   350: invokevirtual 94	java/lang/String:substring	(II)Ljava/lang/String;
    //   353: invokevirtual 79	java/lang/String:length	()I
    //   356: iconst_3
    //   357: isub
    //   358: aload_0
    //   359: invokevirtual 102	android/content/Context:getApplicationInfo	()Landroid/content/pm/ApplicationInfo;
    //   362: getfield 107	android/content/pm/ApplicationInfo:targetSdkVersion	I
    //   365: sipush 337
    //   368: iadd
    //   369: aload_0
    //   370: invokevirtual 83	android/content/Context:getResources	()Landroid/content/res/Resources;
    //   373: ldc_w 418
    //   376: invokevirtual 90	android/content/res/Resources:getString	(I)Ljava/lang/String;
    //   379: iconst_0
    //   380: iconst_4
    //   381: invokevirtual 94	java/lang/String:substring	(II)Ljava/lang/String;
    //   384: invokevirtual 79	java/lang/String:length	()I
    //   387: ldc_w 419
    //   390: iadd
    //   391: i2c
    //   392: invokestatic 113	o/O:ˋ	(IIC)Ljava/lang/Object;
    //   395: checkcast 115	java/lang/Class
    //   398: ldc -64
    //   400: invokevirtual 423	java/lang/Class:getField	(Ljava/lang/String;)Ljava/lang/reflect/Field;
    //   403: aconst_null
    //   404: invokevirtual 429	java/lang/reflect/Field:get	(Ljava/lang/Object;)Ljava/lang/Object;
    //   407: astore_3
    //   408: goto +20 -> 428
    //   411: astore_3
    //   412: aload_3
    //   413: invokevirtual 67	java/lang/Throwable:getCause	()Ljava/lang/Throwable;
    //   416: astore 4
    //   418: aload 4
    //   420: ifnull +6 -> 426
    //   423: aload 4
    //   425: athrow
    //   426: aload_3
    //   427: athrow
    //   428: aload_0
    //   429: invokevirtual 73	android/content/Context:getPackageName	()Ljava/lang/String;
    //   432: bipush 10
    //   434: invokevirtual 98	java/lang/String:codePointAt	(I)I
    //   437: bipush 114
    //   439: isub
    //   440: aload_0
    //   441: invokevirtual 83	android/content/Context:getResources	()Landroid/content/res/Resources;
    //   444: ldc_w 430
    //   447: invokevirtual 90	android/content/res/Resources:getString	(I)Ljava/lang/String;
    //   450: iconst_0
    //   451: bipush 9
    //   453: invokevirtual 94	java/lang/String:substring	(II)Ljava/lang/String;
    //   456: bipush 7
    //   458: invokevirtual 98	java/lang/String:codePointAt	(I)I
    //   461: bipush 117
    //   463: iadd
    //   464: aload_0
    //   465: invokevirtual 83	android/content/Context:getResources	()Landroid/content/res/Resources;
    //   468: ldc -76
    //   470: invokevirtual 90	android/content/res/Resources:getString	(I)Ljava/lang/String;
    //   473: bipush 7
    //   475: bipush 15
    //   477: invokevirtual 94	java/lang/String:substring	(II)Ljava/lang/String;
    //   480: invokevirtual 79	java/lang/String:length	()I
    //   483: bipush 8
    //   485: isub
    //   486: i2c
    //   487: invokestatic 113	o/O:ˋ	(IIC)Ljava/lang/Object;
    //   490: checkcast 115	java/lang/Class
    //   493: ldc 116
    //   495: aconst_null
    //   496: invokevirtual 120	java/lang/Class:getMethod	(Ljava/lang/String;[Ljava/lang/Class;)Ljava/lang/reflect/Method;
    //   499: aload_3
    //   500: aconst_null
    //   501: invokevirtual 126	java/lang/reflect/Method:invoke	(Ljava/lang/Object;[Ljava/lang/Object;)Ljava/lang/Object;
    //   504: astore_3
    //   505: goto +20 -> 525
    //   508: astore_3
    //   509: aload_3
    //   510: invokevirtual 67	java/lang/Throwable:getCause	()Ljava/lang/Throwable;
    //   513: astore 4
    //   515: aload 4
    //   517: ifnull +6 -> 523
    //   520: aload 4
    //   522: athrow
    //   523: aload_3
    //   524: athrow
    //   525: aload_0
    //   526: invokevirtual 73	android/content/Context:getPackageName	()Ljava/lang/String;
    //   529: invokevirtual 79	java/lang/String:length	()I
    //   532: bipush 7
    //   534: isub
    //   535: aload_0
    //   536: invokevirtual 83	android/content/Context:getResources	()Landroid/content/res/Resources;
    //   539: ldc_w 431
    //   542: invokevirtual 90	android/content/res/Resources:getString	(I)Ljava/lang/String;
    //   545: iconst_0
    //   546: iconst_4
    //   547: invokevirtual 94	java/lang/String:substring	(II)Ljava/lang/String;
    //   550: iconst_2
    //   551: invokevirtual 98	java/lang/String:codePointAt	(I)I
    //   554: sipush 351
    //   557: iadd
    //   558: aload_0
    //   559: invokevirtual 83	android/content/Context:getResources	()Landroid/content/res/Resources;
    //   562: ldc_w 432
    //   565: invokevirtual 90	android/content/res/Resources:getString	(I)Ljava/lang/String;
    //   568: iconst_0
    //   569: iconst_4
    //   570: invokevirtual 94	java/lang/String:substring	(II)Ljava/lang/String;
    //   573: invokevirtual 79	java/lang/String:length	()I
    //   576: ldc_w 419
    //   579: iadd
    //   580: i2c
    //   581: invokestatic 113	o/O:ˋ	(IIC)Ljava/lang/Object;
    //   584: checkcast 115	java/lang/Class
    //   587: ldc_w 434
    //   590: aconst_null
    //   591: invokevirtual 120	java/lang/Class:getMethod	(Ljava/lang/String;[Ljava/lang/Class;)Ljava/lang/reflect/Method;
    //   594: aload_3
    //   595: aconst_null
    //   596: invokevirtual 126	java/lang/reflect/Method:invoke	(Ljava/lang/Object;[Ljava/lang/Object;)Ljava/lang/Object;
    //   599: checkcast 75	java/lang/String
    //   602: astore_3
    //   603: new 436	o/IE
    //   606: dup
    //   607: aload_0
    //   608: aload_3
    //   609: invokespecial 439	o/IE:<init>	(Landroid/content/Context;Ljava/lang/String;)V
    //   612: invokevirtual 442	o/IE:ˏ	()Lo/ᐸ;
    //   615: pop
    //   616: goto -285 -> 331
    //   619: return
    //   620: astore_3
    //   621: aload_3
    //   622: athrow
    //   623: iconst_1
    //   624: istore_1
    //   625: goto -368 -> 257
    // Local variable table:
    //   start	length	slot	name	signature
    //   0	628	0	this	IB
    //   15	610	1	i	int
    //   216	2	2	bool	boolean
    //   3	2	3	localException1	Exception
    //   37	16	3	localObject1	Object
    //   116	1	3	localObject2	Object
    //   120	87	3	localObject3	Object
    //   407	1	3	localObject4	Object
    //   411	89	3	localObject5	Object
    //   504	1	3	localObject6	Object
    //   508	87	3	localObject7	Object
    //   602	7	3	str	String
    //   620	2	3	localException2	Exception
    //   42	479	4	localThrowable	Throwable
    // Exception table:
    //   from	to	target	type
    //   16	24	3	java/lang/Exception
    //   54	117	37	finally
    //   137	212	120	finally
    //   428	505	411	finally
    //   525	603	508	finally
    //   9	16	620	java/lang/Exception
    //   16	24	620	java/lang/Exception
    //   38	44	620	java/lang/Exception
    //   49	52	620	java/lang/Exception
    //   52	54	620	java/lang/Exception
    //   121	127	620	java/lang/Exception
    //   132	135	620	java/lang/Exception
    //   135	137	620	java/lang/Exception
    //   212	217	620	java/lang/Exception
  }
  
  public Resources getResources()
  {
    break label69;
    Resources localResources = oH.ˊ(super.getResources());
    label69:
    for (;;)
    {
      int i = ˊˋ + 47;
      ʿ = i % 128;
      if (i % 2 == 0) {
        break;
      }
      break;
      i = ʿ + 55;
      ˊˋ = i % 128;
      if (i % 2 == 0) {
        return localResources;
      }
      return localResources;
    }
  }
  
  /* Error */
  public void onActivityResult(int paramInt1, int paramInt2, android.content.Intent paramIntent)
  {
    // Byte code:
    //   0: goto +442 -> 442
    //   3: iconst_1
    //   4: istore 4
    //   6: goto +530 -> 536
    //   9: iload_1
    //   10: tableswitch	default:+22->32, 0:+53->63, 1:+328->338
    //   32: goto +31 -> 63
    //   35: goto +398 -> 433
    //   38: iload_1
    //   39: tableswitch	default:+21->60, 0:+30->69, 1:+326->365
    //   60: goto +9 -> 69
    //   63: iconst_0
    //   64: istore 4
    //   66: goto +585 -> 651
    //   69: iconst_0
    //   70: istore 4
    //   72: goto +464 -> 536
    //   75: goto +150 -> 225
    //   78: iconst_1
    //   79: istore 4
    //   81: goto +570 -> 651
    //   84: iload_2
    //   85: iconst_m1
    //   86: if_icmpne +6 -> 92
    //   89: goto +441 -> 530
    //   92: goto +144 -> 236
    //   95: iconst_1
    //   96: istore 4
    //   98: goto +438 -> 536
    //   101: iload_1
    //   102: lookupswitch	default:+26->128, 37:+401->503, 64:+343->445
    //   128: goto +317 -> 445
    //   131: goto +20 -> 151
    //   134: astore_3
    //   135: aload_3
    //   136: invokevirtual 67	java/lang/Throwable:getCause	()Ljava/lang/Throwable;
    //   139: astore 5
    //   141: aload 5
    //   143: ifnull +6 -> 149
    //   146: aload 5
    //   148: athrow
    //   149: aload_3
    //   150: athrow
    //   151: aload_0
    //   152: invokevirtual 83	android/content/Context:getResources	()Landroid/content/res/Resources;
    //   155: ldc_w 452
    //   158: invokevirtual 90	android/content/res/Resources:getString	(I)Ljava/lang/String;
    //   161: iconst_0
    //   162: iconst_4
    //   163: invokevirtual 94	java/lang/String:substring	(II)Ljava/lang/String;
    //   166: iconst_2
    //   167: invokevirtual 98	java/lang/String:codePointAt	(I)I
    //   170: bipush 7
    //   172: isub
    //   173: aload_0
    //   174: invokevirtual 73	android/content/Context:getPackageName	()Ljava/lang/String;
    //   177: iconst_3
    //   178: invokevirtual 98	java/lang/String:codePointAt	(I)I
    //   181: bipush 124
    //   183: iadd
    //   184: aload_0
    //   185: invokevirtual 102	android/content/Context:getApplicationInfo	()Landroid/content/pm/ApplicationInfo;
    //   188: getfield 107	android/content/pm/ApplicationInfo:targetSdkVersion	I
    //   191: bipush 25
    //   193: isub
    //   194: i2c
    //   195: invokestatic 113	o/O:ˋ	(IIC)Ljava/lang/Object;
    //   198: checkcast 115	java/lang/Class
    //   201: ldc_w 453
    //   204: aconst_null
    //   205: invokevirtual 120	java/lang/Class:getMethod	(Ljava/lang/String;[Ljava/lang/Class;)Ljava/lang/reflect/Method;
    //   208: aconst_null
    //   209: aconst_null
    //   210: invokevirtual 126	java/lang/reflect/Method:invoke	(Ljava/lang/Object;[Ljava/lang/Object;)Ljava/lang/Object;
    //   213: astore_3
    //   214: iload_2
    //   215: iconst_m1
    //   216: if_icmpne +6 -> 222
    //   219: goto +31 -> 250
    //   222: goto +206 -> 428
    //   225: iconst_1
    //   226: istore 4
    //   228: goto +205 -> 433
    //   231: iconst_0
    //   232: istore_1
    //   233: goto -224 -> 9
    //   236: bipush 64
    //   238: istore_1
    //   239: goto -138 -> 101
    //   242: aload_0
    //   243: invokevirtual 455	o/IB:ॱᐝ	()Z
    //   246: pop
    //   247: goto +529 -> 776
    //   250: iconst_1
    //   251: istore_1
    //   252: goto -214 -> 38
    //   255: goto +20 -> 275
    //   258: astore_3
    //   259: aload_3
    //   260: invokevirtual 67	java/lang/Throwable:getCause	()Ljava/lang/Throwable;
    //   263: astore 5
    //   265: aload 5
    //   267: ifnull +6 -> 273
    //   270: aload 5
    //   272: athrow
    //   273: aload_3
    //   274: athrow
    //   275: aload_0
    //   276: invokevirtual 102	android/content/Context:getApplicationInfo	()Landroid/content/pm/ApplicationInfo;
    //   279: getfield 107	android/content/pm/ApplicationInfo:targetSdkVersion	I
    //   282: bipush 21
    //   284: isub
    //   285: aload_0
    //   286: invokevirtual 73	android/content/Context:getPackageName	()Ljava/lang/String;
    //   289: iconst_3
    //   290: invokevirtual 98	java/lang/String:codePointAt	(I)I
    //   293: bipush 124
    //   295: iadd
    //   296: aload_0
    //   297: invokevirtual 73	android/content/Context:getPackageName	()Ljava/lang/String;
    //   300: iconst_1
    //   301: invokevirtual 98	java/lang/String:codePointAt	(I)I
    //   304: bipush 111
    //   306: isub
    //   307: i2c
    //   308: invokestatic 113	o/O:ˋ	(IIC)Ljava/lang/Object;
    //   311: checkcast 115	java/lang/Class
    //   314: ldc_w 453
    //   317: aconst_null
    //   318: invokevirtual 120	java/lang/Class:getMethod	(Ljava/lang/String;[Ljava/lang/Class;)Ljava/lang/reflect/Method;
    //   321: aconst_null
    //   322: aconst_null
    //   323: invokevirtual 126	java/lang/reflect/Method:invoke	(Ljava/lang/Object;[Ljava/lang/Object;)Ljava/lang/Object;
    //   326: astore_3
    //   327: iload_2
    //   328: iconst_m1
    //   329: if_icmpne +6 -> 335
    //   332: goto +439 -> 771
    //   335: goto -104 -> 231
    //   338: getstatic 41	o/IB:ʿ	I
    //   341: bipush 27
    //   343: iadd
    //   344: istore_1
    //   345: iload_1
    //   346: sipush 128
    //   349: irem
    //   350: putstatic 39	o/IB:ˊˋ	I
    //   353: iload_1
    //   354: iconst_2
    //   355: irem
    //   356: ifne +6 -> 362
    //   359: goto +36 -> 395
    //   362: goto -284 -> 78
    //   365: getstatic 39	o/IB:ˊˋ	I
    //   368: bipush 21
    //   370: iadd
    //   371: istore_1
    //   372: iload_1
    //   373: sipush 128
    //   376: irem
    //   377: putstatic 41	o/IB:ʿ	I
    //   380: iload_1
    //   381: iconst_2
    //   382: irem
    //   383: ifeq +6 -> 389
    //   386: goto -383 -> 3
    //   389: goto -294 -> 95
    //   392: goto +384 -> 776
    //   395: iconst_1
    //   396: istore 4
    //   398: goto +253 -> 651
    //   401: getstatic 39	o/IB:ˊˋ	I
    //   404: bipush 63
    //   406: iadd
    //   407: istore_1
    //   408: iload_1
    //   409: sipush 128
    //   412: irem
    //   413: putstatic 41	o/IB:ʿ	I
    //   416: iload_1
    //   417: iconst_2
    //   418: irem
    //   419: ifeq +6 -> 425
    //   422: goto -387 -> 35
    //   425: goto +343 -> 768
    //   428: iconst_0
    //   429: istore_1
    //   430: goto -392 -> 38
    //   433: aload_0
    //   434: iload 4
    //   436: invokevirtual 458	o/IB:ˋ	(Z)V
    //   439: goto -47 -> 392
    //   442: goto +9 -> 451
    //   445: iconst_0
    //   446: istore 4
    //   448: goto -47 -> 401
    //   451: aload_0
    //   452: iload_1
    //   453: iload_2
    //   454: aload_3
    //   455: invokespecial 460	o/l:onActivityResult	(IILandroid/content/Intent;)V
    //   458: iload_1
    //   459: lookupswitch	default:+41->500, 10:+-375->84, 11:+-217->242, 18:+-328->131, 25:+-204->255
    //   500: goto +276 -> 776
    //   503: getstatic 41	o/IB:ʿ	I
    //   506: bipush 95
    //   508: iadd
    //   509: istore_1
    //   510: iload_1
    //   511: sipush 128
    //   514: irem
    //   515: putstatic 39	o/IB:ˊˋ	I
    //   518: iload_1
    //   519: iconst_2
    //   520: irem
    //   521: ifne +6 -> 527
    //   524: goto -449 -> 75
    //   527: goto -302 -> 225
    //   530: bipush 37
    //   532: istore_1
    //   533: goto -432 -> 101
    //   536: goto +20 -> 556
    //   539: astore_3
    //   540: aload_3
    //   541: invokevirtual 67	java/lang/Throwable:getCause	()Ljava/lang/Throwable;
    //   544: astore 5
    //   546: aload 5
    //   548: ifnull +6 -> 554
    //   551: aload 5
    //   553: athrow
    //   554: aload_3
    //   555: athrow
    //   556: aload_0
    //   557: invokevirtual 83	android/content/Context:getResources	()Landroid/content/res/Resources;
    //   560: ldc_w 461
    //   563: invokevirtual 90	android/content/res/Resources:getString	(I)Ljava/lang/String;
    //   566: iconst_0
    //   567: iconst_4
    //   568: invokevirtual 94	java/lang/String:substring	(II)Ljava/lang/String;
    //   571: iconst_1
    //   572: invokevirtual 98	java/lang/String:codePointAt	(I)I
    //   575: bipush 22
    //   577: isub
    //   578: aload_0
    //   579: invokevirtual 73	android/content/Context:getPackageName	()Ljava/lang/String;
    //   582: invokevirtual 79	java/lang/String:length	()I
    //   585: sipush 211
    //   588: iadd
    //   589: aload_0
    //   590: invokevirtual 83	android/content/Context:getResources	()Landroid/content/res/Resources;
    //   593: ldc_w 462
    //   596: invokevirtual 90	android/content/res/Resources:getString	(I)Ljava/lang/String;
    //   599: iconst_0
    //   600: iconst_4
    //   601: invokevirtual 94	java/lang/String:substring	(II)Ljava/lang/String;
    //   604: invokevirtual 79	java/lang/String:length	()I
    //   607: iconst_4
    //   608: isub
    //   609: i2c
    //   610: invokestatic 113	o/O:ˋ	(IIC)Ljava/lang/Object;
    //   613: checkcast 115	java/lang/Class
    //   616: ldc -127
    //   618: iconst_1
    //   619: anewarray 115	java/lang/Class
    //   622: dup
    //   623: iconst_0
    //   624: getstatic 466	java/lang/Boolean:TYPE	Ljava/lang/Class;
    //   627: aastore
    //   628: invokevirtual 120	java/lang/Class:getMethod	(Ljava/lang/String;[Ljava/lang/Class;)Ljava/lang/reflect/Method;
    //   631: aload_3
    //   632: iconst_1
    //   633: anewarray 133	java/lang/Object
    //   636: dup
    //   637: iconst_0
    //   638: iload 4
    //   640: invokestatic 470	java/lang/Boolean:valueOf	(Z)Ljava/lang/Boolean;
    //   643: aastore
    //   644: invokevirtual 126	java/lang/reflect/Method:invoke	(Ljava/lang/Object;[Ljava/lang/Object;)Ljava/lang/Object;
    //   647: pop
    //   648: goto +128 -> 776
    //   651: goto +20 -> 671
    //   654: astore_3
    //   655: aload_3
    //   656: invokevirtual 67	java/lang/Throwable:getCause	()Ljava/lang/Throwable;
    //   659: astore 5
    //   661: aload 5
    //   663: ifnull +6 -> 669
    //   666: aload 5
    //   668: athrow
    //   669: aload_3
    //   670: athrow
    //   671: aload_0
    //   672: invokevirtual 73	android/content/Context:getPackageName	()Ljava/lang/String;
    //   675: bipush 8
    //   677: invokevirtual 98	java/lang/String:codePointAt	(I)I
    //   680: bipush 108
    //   682: isub
    //   683: aload_0
    //   684: invokevirtual 83	android/content/Context:getResources	()Landroid/content/res/Resources;
    //   687: ldc_w 471
    //   690: invokevirtual 90	android/content/res/Resources:getString	(I)Ljava/lang/String;
    //   693: iconst_0
    //   694: iconst_4
    //   695: invokevirtual 94	java/lang/String:substring	(II)Ljava/lang/String;
    //   698: invokevirtual 79	java/lang/String:length	()I
    //   701: sipush 218
    //   704: iadd
    //   705: aload_0
    //   706: invokevirtual 83	android/content/Context:getResources	()Landroid/content/res/Resources;
    //   709: ldc_w 472
    //   712: invokevirtual 90	android/content/res/Resources:getString	(I)Ljava/lang/String;
    //   715: iconst_0
    //   716: iconst_4
    //   717: invokevirtual 94	java/lang/String:substring	(II)Ljava/lang/String;
    //   720: iconst_0
    //   721: invokevirtual 98	java/lang/String:codePointAt	(I)I
    //   724: iconst_5
    //   725: isub
    //   726: i2c
    //   727: invokestatic 113	o/O:ˋ	(IIC)Ljava/lang/Object;
    //   730: checkcast 115	java/lang/Class
    //   733: ldc -127
    //   735: iconst_1
    //   736: anewarray 115	java/lang/Class
    //   739: dup
    //   740: iconst_0
    //   741: getstatic 466	java/lang/Boolean:TYPE	Ljava/lang/Class;
    //   744: aastore
    //   745: invokevirtual 120	java/lang/Class:getMethod	(Ljava/lang/String;[Ljava/lang/Class;)Ljava/lang/reflect/Method;
    //   748: aload_3
    //   749: iconst_1
    //   750: anewarray 133	java/lang/Object
    //   753: dup
    //   754: iconst_0
    //   755: iload 4
    //   757: invokestatic 470	java/lang/Boolean:valueOf	(Z)Ljava/lang/Boolean;
    //   760: aastore
    //   761: invokevirtual 126	java/lang/reflect/Method:invoke	(Ljava/lang/Object;[Ljava/lang/Object;)Ljava/lang/Object;
    //   764: pop
    //   765: goto +11 -> 776
    //   768: goto -335 -> 433
    //   771: iconst_1
    //   772: istore_1
    //   773: goto -764 -> 9
    //   776: return
    // Local variable table:
    //   start	length	slot	name	signature
    //   0	777	0	this	IB
    //   0	777	1	paramInt1	int
    //   0	777	2	paramInt2	int
    //   0	777	3	paramIntent	android.content.Intent
    //   4	752	4	bool	boolean
    //   139	528	5	localThrowable	Throwable
    // Exception table:
    //   from	to	target	type
    //   151	214	134	finally
    //   275	327	258	finally
    //   556	648	539	finally
    //   671	765	654	finally
  }
  
  /* Error */
  public void onCreate(android.os.Bundle paramBundle)
  {
    // Byte code:
    //   0: goto +237 -> 237
    //   3: astore_1
    //   4: aload_1
    //   5: athrow
    //   6: aload_0
    //   7: aload_1
    //   8: invokespecial 476	o/l:onCreate	(Landroid/os/Bundle;)V
    //   11: goto +17 -> 28
    //   14: astore_3
    //   15: aload_3
    //   16: invokevirtual 67	java/lang/Throwable:getCause	()Ljava/lang/Throwable;
    //   19: astore_1
    //   20: aload_1
    //   21: ifnull +5 -> 26
    //   24: aload_1
    //   25: athrow
    //   26: aload_3
    //   27: athrow
    //   28: aload_0
    //   29: invokevirtual 102	android/content/Context:getApplicationInfo	()Landroid/content/pm/ApplicationInfo;
    //   32: getfield 107	android/content/pm/ApplicationInfo:targetSdkVersion	I
    //   35: bipush 21
    //   37: isub
    //   38: aload_0
    //   39: invokevirtual 73	android/content/Context:getPackageName	()Ljava/lang/String;
    //   42: bipush 9
    //   44: invokevirtual 98	java/lang/String:codePointAt	(I)I
    //   47: sipush 305
    //   50: iadd
    //   51: aload_0
    //   52: invokevirtual 83	android/content/Context:getResources	()Landroid/content/res/Resources;
    //   55: ldc_w 477
    //   58: invokevirtual 90	android/content/res/Resources:getString	(I)Ljava/lang/String;
    //   61: iconst_0
    //   62: iconst_4
    //   63: invokevirtual 94	java/lang/String:substring	(II)Ljava/lang/String;
    //   66: invokevirtual 79	java/lang/String:length	()I
    //   69: iconst_4
    //   70: isub
    //   71: i2c
    //   72: invokestatic 113	o/O:ˋ	(IIC)Ljava/lang/Object;
    //   75: checkcast 115	java/lang/Class
    //   78: ldc -114
    //   80: aconst_null
    //   81: invokevirtual 120	java/lang/Class:getMethod	(Ljava/lang/String;[Ljava/lang/Class;)Ljava/lang/reflect/Method;
    //   84: aconst_null
    //   85: aconst_null
    //   86: invokevirtual 126	java/lang/reflect/Method:invoke	(Ljava/lang/Object;[Ljava/lang/Object;)Ljava/lang/Object;
    //   89: astore_1
    //   90: goto +17 -> 107
    //   93: astore_3
    //   94: aload_3
    //   95: invokevirtual 67	java/lang/Throwable:getCause	()Ljava/lang/Throwable;
    //   98: astore_1
    //   99: aload_1
    //   100: ifnull +5 -> 105
    //   103: aload_1
    //   104: athrow
    //   105: aload_3
    //   106: athrow
    //   107: aload_0
    //   108: invokevirtual 73	android/content/Context:getPackageName	()Ljava/lang/String;
    //   111: invokevirtual 79	java/lang/String:length	()I
    //   114: bipush 7
    //   116: isub
    //   117: aload_0
    //   118: invokevirtual 73	android/content/Context:getPackageName	()Ljava/lang/String;
    //   121: iconst_5
    //   122: invokevirtual 98	java/lang/String:codePointAt	(I)I
    //   125: sipush 288
    //   128: iadd
    //   129: aload_0
    //   130: invokevirtual 102	android/content/Context:getApplicationInfo	()Landroid/content/pm/ApplicationInfo;
    //   133: getfield 107	android/content/pm/ApplicationInfo:targetSdkVersion	I
    //   136: bipush 25
    //   138: isub
    //   139: i2c
    //   140: invokestatic 113	o/O:ˋ	(IIC)Ljava/lang/Object;
    //   143: checkcast 115	java/lang/Class
    //   146: ldc_w 478
    //   149: aconst_null
    //   150: invokevirtual 120	java/lang/Class:getMethod	(Ljava/lang/String;[Ljava/lang/Class;)Ljava/lang/reflect/Method;
    //   153: aload_1
    //   154: aconst_null
    //   155: invokevirtual 126	java/lang/reflect/Method:invoke	(Ljava/lang/Object;[Ljava/lang/Object;)Ljava/lang/Object;
    //   158: checkcast 75	java/lang/String
    //   161: astore_1
    //   162: aload_0
    //   163: aload_1
    //   164: invokevirtual 481	o/IB:ˋ	(Ljava/lang/String;)V
    //   167: invokestatic 486	o/w:ॱॱ	()V
    //   170: aload_0
    //   171: getfield 490	o/IB:ॱˊ	Landroid/databinding/ViewDataBinding;
    //   174: ifnull +6 -> 180
    //   177: goto +168 -> 345
    //   180: iconst_0
    //   181: istore_2
    //   182: goto +105 -> 287
    //   185: aload_0
    //   186: getfield 490	o/IB:ॱˊ	Landroid/databinding/ViewDataBinding;
    //   189: astore_1
    //   190: aload_1
    //   191: invokevirtual 495	android/databinding/ViewDataBinding:ᐝ	()Landroid/view/View;
    //   194: astore_1
    //   195: aload_1
    //   196: checkcast 497	android/widget/RelativeLayout
    //   199: astore_1
    //   200: aload_0
    //   201: aload_1
    //   202: putfield 499	o/IB:ॱᐝ	Landroid/widget/RelativeLayout;
    //   205: new 47	java/lang/NullPointerException
    //   208: dup
    //   209: invokespecial 50	java/lang/NullPointerException:<init>	()V
    //   212: athrow
    //   213: aload_0
    //   214: getfield 490	o/IB:ॱˊ	Landroid/databinding/ViewDataBinding;
    //   217: astore_1
    //   218: aload_1
    //   219: invokevirtual 495	android/databinding/ViewDataBinding:ᐝ	()Landroid/view/View;
    //   222: instanceof 497
    //   225: ifeq +6 -> 231
    //   228: goto +111 -> 339
    //   231: bipush 73
    //   233: istore_2
    //   234: goto +6 -> 240
    //   237: goto -231 -> 6
    //   240: iload_2
    //   241: lookupswitch	default:+27->268, 73:+30->271, 77:+109->350
    //   268: goto +82 -> 350
    //   271: return
    //   272: aload_0
    //   273: aload_0
    //   274: getfield 490	o/IB:ॱˊ	Landroid/databinding/ViewDataBinding;
    //   277: invokevirtual 495	android/databinding/ViewDataBinding:ᐝ	()Landroid/view/View;
    //   280: checkcast 497	android/widget/RelativeLayout
    //   283: putfield 499	o/IB:ॱᐝ	Landroid/widget/RelativeLayout;
    //   286: return
    //   287: iload_2
    //   288: tableswitch	default:+24->312, 0:+-17->271, 1:+24->312
    //   312: getstatic 41	o/IB:ʿ	I
    //   315: bipush 35
    //   317: iadd
    //   318: istore_2
    //   319: iload_2
    //   320: sipush 128
    //   323: irem
    //   324: putstatic 39	o/IB:ˊˋ	I
    //   327: iload_2
    //   328: iconst_2
    //   329: irem
    //   330: ifne +6 -> 336
    //   333: goto +47 -> 380
    //   336: goto -123 -> 213
    //   339: bipush 77
    //   341: istore_2
    //   342: goto -102 -> 240
    //   345: iconst_1
    //   346: istore_2
    //   347: goto -60 -> 287
    //   350: getstatic 39	o/IB:ˊˋ	I
    //   353: bipush 123
    //   355: iadd
    //   356: istore_2
    //   357: iload_2
    //   358: sipush 128
    //   361: irem
    //   362: putstatic 41	o/IB:ʿ	I
    //   365: iload_2
    //   366: iconst_2
    //   367: irem
    //   368: ifeq +6 -> 374
    //   371: goto -186 -> 185
    //   374: goto -102 -> 272
    //   377: astore_1
    //   378: aload_1
    //   379: athrow
    //   380: goto -167 -> 213
    // Local variable table:
    //   start	length	slot	name	signature
    //   0	383	0	this	IB
    //   0	383	1	paramBundle	android.os.Bundle
    //   181	187	2	i	int
    //   14	13	3	localObject1	Object
    //   93	13	3	localObject2	Object
    // Exception table:
    //   from	to	target	type
    //   185	190	3	java/lang/Exception
    //   190	195	3	java/lang/Exception
    //   195	200	3	java/lang/Exception
    //   200	205	3	java/lang/Exception
    //   205	213	3	java/lang/Exception
    //   28	90	14	finally
    //   107	162	93	finally
    //   195	200	377	java/lang/Exception
    //   213	218	377	java/lang/Exception
  }
  
  public void onDestroy()
  {
    for (;;)
    {
      super.onDestroy();
      w.ॱॱ();
      break;
      i = ˊˋ + 55;
      ʿ = i % 128;
      if (i % 2 == 0) {}
    }
    int i = ˊˋ + 59;
    ʿ = i % 128;
    if (i % 2 != 0) {}
  }
  
  /* Error */
  public void onPause()
  {
    // Byte code:
    //   0: goto +511 -> 511
    //   3: getstatic 39	o/IB:ˊˋ	I
    //   6: bipush 59
    //   8: iadd
    //   9: istore_1
    //   10: iload_1
    //   11: sipush 128
    //   14: irem
    //   15: putstatic 41	o/IB:ʿ	I
    //   18: iload_1
    //   19: iconst_2
    //   20: irem
    //   21: ifeq +6 -> 27
    //   24: goto +490 -> 514
    //   27: goto +493 -> 520
    //   30: aload_0
    //   31: invokespecial 505	o/l:onPause	()V
    //   34: goto +17 -> 51
    //   37: astore_2
    //   38: aload_2
    //   39: invokevirtual 67	java/lang/Throwable:getCause	()Ljava/lang/Throwable;
    //   42: astore_3
    //   43: aload_3
    //   44: ifnull +5 -> 49
    //   47: aload_3
    //   48: athrow
    //   49: aload_2
    //   50: athrow
    //   51: aload_0
    //   52: invokevirtual 102	android/content/Context:getApplicationInfo	()Landroid/content/pm/ApplicationInfo;
    //   55: getfield 107	android/content/pm/ApplicationInfo:targetSdkVersion	I
    //   58: bipush 21
    //   60: isub
    //   61: aload_0
    //   62: invokevirtual 83	android/content/Context:getResources	()Landroid/content/res/Resources;
    //   65: ldc_w 506
    //   68: invokevirtual 90	android/content/res/Resources:getString	(I)Ljava/lang/String;
    //   71: iconst_0
    //   72: iconst_4
    //   73: invokevirtual 94	java/lang/String:substring	(II)Ljava/lang/String;
    //   76: iconst_1
    //   77: invokevirtual 98	java/lang/String:codePointAt	(I)I
    //   80: sipush 241
    //   83: iadd
    //   84: aload_0
    //   85: invokevirtual 102	android/content/Context:getApplicationInfo	()Landroid/content/pm/ApplicationInfo;
    //   88: getfield 107	android/content/pm/ApplicationInfo:targetSdkVersion	I
    //   91: sipush 14763
    //   94: iadd
    //   95: i2c
    //   96: invokestatic 113	o/O:ˋ	(IIC)Ljava/lang/Object;
    //   99: checkcast 115	java/lang/Class
    //   102: ldc 116
    //   104: aconst_null
    //   105: invokevirtual 120	java/lang/Class:getMethod	(Ljava/lang/String;[Ljava/lang/Class;)Ljava/lang/reflect/Method;
    //   108: aconst_null
    //   109: aconst_null
    //   110: invokevirtual 126	java/lang/reflect/Method:invoke	(Ljava/lang/Object;[Ljava/lang/Object;)Ljava/lang/Object;
    //   113: astore_2
    //   114: goto +17 -> 131
    //   117: astore_2
    //   118: aload_2
    //   119: invokevirtual 67	java/lang/Throwable:getCause	()Ljava/lang/Throwable;
    //   122: astore_3
    //   123: aload_3
    //   124: ifnull +5 -> 129
    //   127: aload_3
    //   128: athrow
    //   129: aload_2
    //   130: athrow
    //   131: aload_0
    //   132: invokevirtual 102	android/content/Context:getApplicationInfo	()Landroid/content/pm/ApplicationInfo;
    //   135: getfield 107	android/content/pm/ApplicationInfo:targetSdkVersion	I
    //   138: bipush 21
    //   140: isub
    //   141: aload_0
    //   142: invokevirtual 102	android/content/Context:getApplicationInfo	()Landroid/content/pm/ApplicationInfo;
    //   145: getfield 107	android/content/pm/ApplicationInfo:targetSdkVersion	I
    //   148: sipush 242
    //   151: iadd
    //   152: aload_0
    //   153: invokevirtual 83	android/content/Context:getResources	()Landroid/content/res/Resources;
    //   156: ldc_w 507
    //   159: invokevirtual 90	android/content/res/Resources:getString	(I)Ljava/lang/String;
    //   162: iconst_0
    //   163: iconst_5
    //   164: invokevirtual 94	java/lang/String:substring	(II)Ljava/lang/String;
    //   167: iconst_1
    //   168: invokevirtual 98	java/lang/String:codePointAt	(I)I
    //   171: sipush 14762
    //   174: iadd
    //   175: i2c
    //   176: invokestatic 113	o/O:ˋ	(IIC)Ljava/lang/Object;
    //   179: checkcast 115	java/lang/Class
    //   182: ldc_w 453
    //   185: iconst_1
    //   186: anewarray 115	java/lang/Class
    //   189: dup
    //   190: iconst_0
    //   191: ldc -125
    //   193: aastore
    //   194: invokevirtual 120	java/lang/Class:getMethod	(Ljava/lang/String;[Ljava/lang/Class;)Ljava/lang/reflect/Method;
    //   197: aload_2
    //   198: iconst_1
    //   199: anewarray 133	java/lang/Object
    //   202: dup
    //   203: iconst_0
    //   204: aload_0
    //   205: aastore
    //   206: invokevirtual 126	java/lang/reflect/Method:invoke	(Ljava/lang/Object;[Ljava/lang/Object;)Ljava/lang/Object;
    //   209: pop
    //   210: invokestatic 512	o/zp:ॱ	()Lo/zp;
    //   213: aload_0
    //   214: invokevirtual 515	o/zp:ॱ	(Ljava/lang/Object;)V
    //   217: aconst_null
    //   218: arraylength
    //   219: istore_1
    //   220: goto +264 -> 484
    //   223: new 47	java/lang/NullPointerException
    //   226: dup
    //   227: invokespecial 50	java/lang/NullPointerException:<init>	()V
    //   230: athrow
    //   231: iload_1
    //   232: lookupswitch	default:+28->260, 23:+-202->30, 37:+36->268
    //   260: goto -230 -> 30
    //   263: iconst_1
    //   264: istore_1
    //   265: goto +261 -> 526
    //   268: aload_0
    //   269: invokespecial 505	o/l:onPause	()V
    //   272: goto +17 -> 289
    //   275: astore_3
    //   276: aload_3
    //   277: invokevirtual 67	java/lang/Throwable:getCause	()Ljava/lang/Throwable;
    //   280: astore_2
    //   281: aload_2
    //   282: ifnull +5 -> 287
    //   285: aload_2
    //   286: athrow
    //   287: aload_3
    //   288: athrow
    //   289: aload_0
    //   290: invokevirtual 73	android/content/Context:getPackageName	()Ljava/lang/String;
    //   293: invokevirtual 79	java/lang/String:length	()I
    //   296: bipush 7
    //   298: isub
    //   299: aload_0
    //   300: invokevirtual 73	android/content/Context:getPackageName	()Ljava/lang/String;
    //   303: iconst_2
    //   304: invokevirtual 98	java/lang/String:codePointAt	(I)I
    //   307: sipush 221
    //   310: iadd
    //   311: aload_0
    //   312: invokevirtual 83	android/content/Context:getResources	()Landroid/content/res/Resources;
    //   315: ldc_w 516
    //   318: invokevirtual 90	android/content/res/Resources:getString	(I)Ljava/lang/String;
    //   321: iconst_0
    //   322: iconst_5
    //   323: invokevirtual 94	java/lang/String:substring	(II)Ljava/lang/String;
    //   326: invokevirtual 79	java/lang/String:length	()I
    //   329: sipush 14783
    //   332: iadd
    //   333: i2c
    //   334: invokestatic 113	o/O:ˋ	(IIC)Ljava/lang/Object;
    //   337: checkcast 115	java/lang/Class
    //   340: ldc 116
    //   342: aconst_null
    //   343: invokevirtual 120	java/lang/Class:getMethod	(Ljava/lang/String;[Ljava/lang/Class;)Ljava/lang/reflect/Method;
    //   346: aconst_null
    //   347: aconst_null
    //   348: invokevirtual 126	java/lang/reflect/Method:invoke	(Ljava/lang/Object;[Ljava/lang/Object;)Ljava/lang/Object;
    //   351: astore_2
    //   352: goto +17 -> 369
    //   355: astore_2
    //   356: aload_2
    //   357: invokevirtual 67	java/lang/Throwable:getCause	()Ljava/lang/Throwable;
    //   360: astore_3
    //   361: aload_3
    //   362: ifnull +5 -> 367
    //   365: aload_3
    //   366: athrow
    //   367: aload_2
    //   368: athrow
    //   369: aload_0
    //   370: invokevirtual 83	android/content/Context:getResources	()Landroid/content/res/Resources;
    //   373: ldc_w 517
    //   376: invokevirtual 90	android/content/res/Resources:getString	(I)Ljava/lang/String;
    //   379: iconst_0
    //   380: iconst_4
    //   381: invokevirtual 94	java/lang/String:substring	(II)Ljava/lang/String;
    //   384: invokevirtual 79	java/lang/String:length	()I
    //   387: iconst_0
    //   388: iadd
    //   389: aload_0
    //   390: invokevirtual 83	android/content/Context:getResources	()Landroid/content/res/Resources;
    //   393: ldc_w 518
    //   396: invokevirtual 90	android/content/res/Resources:getString	(I)Ljava/lang/String;
    //   399: iconst_0
    //   400: iconst_4
    //   401: invokevirtual 94	java/lang/String:substring	(II)Ljava/lang/String;
    //   404: iconst_1
    //   405: invokevirtual 98	java/lang/String:codePointAt	(I)I
    //   408: sipush 241
    //   411: iadd
    //   412: aload_0
    //   413: invokevirtual 83	android/content/Context:getResources	()Landroid/content/res/Resources;
    //   416: ldc_w 519
    //   419: invokevirtual 90	android/content/res/Resources:getString	(I)Ljava/lang/String;
    //   422: iconst_0
    //   423: iconst_4
    //   424: invokevirtual 94	java/lang/String:substring	(II)Ljava/lang/String;
    //   427: invokevirtual 79	java/lang/String:length	()I
    //   430: sipush 14784
    //   433: iadd
    //   434: i2c
    //   435: invokestatic 113	o/O:ˋ	(IIC)Ljava/lang/Object;
    //   438: checkcast 115	java/lang/Class
    //   441: ldc_w 453
    //   444: iconst_1
    //   445: anewarray 115	java/lang/Class
    //   448: dup
    //   449: iconst_0
    //   450: ldc -125
    //   452: aastore
    //   453: invokevirtual 120	java/lang/Class:getMethod	(Ljava/lang/String;[Ljava/lang/Class;)Ljava/lang/reflect/Method;
    //   456: aload_2
    //   457: iconst_1
    //   458: anewarray 133	java/lang/Object
    //   461: dup
    //   462: iconst_0
    //   463: aload_0
    //   464: aastore
    //   465: invokevirtual 126	java/lang/reflect/Method:invoke	(Ljava/lang/Object;[Ljava/lang/Object;)Ljava/lang/Object;
    //   468: pop
    //   469: invokestatic 512	o/zp:ॱ	()Lo/zp;
    //   472: aload_0
    //   473: invokevirtual 515	o/zp:ॱ	(Ljava/lang/Object;)V
    //   476: goto +8 -> 484
    //   479: iconst_0
    //   480: istore_1
    //   481: goto +45 -> 526
    //   484: getstatic 41	o/IB:ʿ	I
    //   487: bipush 67
    //   489: iadd
    //   490: istore_1
    //   491: iload_1
    //   492: sipush 128
    //   495: irem
    //   496: putstatic 39	o/IB:ˊˋ	I
    //   499: iload_1
    //   500: iconst_2
    //   501: irem
    //   502: ifne +6 -> 508
    //   505: goto -242 -> 263
    //   508: goto -29 -> 479
    //   511: goto -508 -> 3
    //   514: bipush 23
    //   516: istore_1
    //   517: goto -286 -> 231
    //   520: bipush 37
    //   522: istore_1
    //   523: goto -292 -> 231
    //   526: iload_1
    //   527: tableswitch	default:+21->548, 0:+24->551, 1:+-304->223
    //   548: goto -325 -> 223
    //   551: return
    // Local variable table:
    //   start	length	slot	name	signature
    //   0	552	0	this	IB
    //   9	518	1	i	int
    //   37	13	2	localObject1	Object
    //   113	1	2	localObject2	Object
    //   117	81	2	localObject3	Object
    //   280	72	2	localObject4	Object
    //   355	102	2	localObject5	Object
    //   42	86	3	localThrowable1	Throwable
    //   275	13	3	localObject6	Object
    //   360	6	3	localThrowable2	Throwable
    // Exception table:
    //   from	to	target	type
    //   51	114	37	finally
    //   131	210	117	finally
    //   289	352	275	finally
    //   369	469	355	finally
  }
  
  public void onResume()
  {
    break label4;
    return;
    for (;;)
    {
      label4:
      i = ˊˋ + 115;
      ʿ = i % 128;
      if (i % 2 == 0) {
        break label90;
      }
      for (;;)
      {
        switch (i)
        {
        case 62: 
        default: 
          break label96;
          i = ʿ + 91;
          ˊˋ = i % 128;
          if (i % 2 == 0) {
            break label131;
          }
          break label108;
          i = 62;
          break;
        case 84: 
          label90:
          label96:
          i = 41 / 0;
          return;
          i = 84;
        }
      }
      label108:
      i = 1;
      break label157;
      super.onResume();
      zp.ॱ().ˋ(this);
      ʾ();
    }
    label131:
    int i = 0;
    for (;;)
    {
      super.onResume();
      zp.ॱ().ˋ(this);
      ʾ();
      i = null.length;
      break;
      label157:
      switch (i)
      {
      }
    }
  }
  
  /* Error */
  public void onStart()
  {
    // Byte code:
    //   0: goto +6 -> 6
    //   3: astore_2
    //   4: aload_2
    //   5: athrow
    //   6: getstatic 41	o/IB:ʿ	I
    //   9: bipush 119
    //   11: iadd
    //   12: istore_1
    //   13: iload_1
    //   14: sipush 128
    //   17: irem
    //   18: putstatic 39	o/IB:ˊˋ	I
    //   21: iload_1
    //   22: iconst_2
    //   23: irem
    //   24: ifne +6 -> 30
    //   27: goto +19 -> 46
    //   30: goto +59 -> 89
    //   33: aload_0
    //   34: invokespecial 529	o/l:onStart	()V
    //   37: aload_0
    //   38: invokevirtual 455	o/IB:ॱᐝ	()Z
    //   41: pop
    //   42: aconst_null
    //   43: arraylength
    //   44: istore_1
    //   45: return
    //   46: iconst_1
    //   47: istore_1
    //   48: goto +3 -> 51
    //   51: iload_1
    //   52: tableswitch	default:+24->76, 0:+27->79, 1:+-19->33
    //   76: goto -43 -> 33
    //   79: aload_0
    //   80: invokespecial 529	o/l:onStart	()V
    //   83: aload_0
    //   84: invokevirtual 455	o/IB:ॱᐝ	()Z
    //   87: pop
    //   88: return
    //   89: iconst_0
    //   90: istore_1
    //   91: goto -40 -> 51
    // Local variable table:
    //   start	length	slot	name	signature
    //   0	94	0	this	IB
    //   12	79	1	i	int
    //   3	2	2	localException	Exception
    // Exception table:
    //   from	to	target	type
    //   83	88	3	java/lang/Exception
  }
  
  /* Error */
  protected void ʼॱ()
  {
    // Byte code:
    //   0: goto +366 -> 366
    //   3: iload_1
    //   4: tableswitch	default:+24->28, 0:+195->199, 1:+681->685
    //   28: goto +171 -> 199
    //   31: aload_0
    //   32: aload 4
    //   34: iconst_4
    //   35: invokevirtual 531	java/lang/String:substring	(I)Ljava/lang/String;
    //   38: invokespecial 533	o/IB:ॱ	(Ljava/lang/String;)Ljava/lang/String;
    //   41: invokevirtual 158	java/lang/String:intern	()Ljava/lang/String;
    //   44: astore_3
    //   45: aconst_null
    //   46: arraylength
    //   47: istore_1
    //   48: goto +439 -> 487
    //   51: iconst_0
    //   52: istore_1
    //   53: goto +365 -> 418
    //   56: iconst_0
    //   57: istore_1
    //   58: goto -55 -> 3
    //   61: aload_0
    //   62: aload_3
    //   63: iconst_4
    //   64: invokevirtual 531	java/lang/String:substring	(I)Ljava/lang/String;
    //   67: invokespecial 533	o/IB:ॱ	(Ljava/lang/String;)Ljava/lang/String;
    //   70: invokevirtual 158	java/lang/String:intern	()Ljava/lang/String;
    //   73: astore_3
    //   74: goto +20 -> 94
    //   77: aload_0
    //   78: aload 4
    //   80: iconst_4
    //   81: invokevirtual 531	java/lang/String:substring	(I)Ljava/lang/String;
    //   84: invokespecial 533	o/IB:ॱ	(Ljava/lang/String;)Ljava/lang/String;
    //   87: invokevirtual 158	java/lang/String:intern	()Ljava/lang/String;
    //   90: astore_3
    //   91: goto +294 -> 385
    //   94: getstatic 39	o/IB:ˊˋ	I
    //   97: bipush 91
    //   99: iadd
    //   100: istore_1
    //   101: iload_1
    //   102: sipush 128
    //   105: irem
    //   106: putstatic 41	o/IB:ʿ	I
    //   109: iload_1
    //   110: iconst_2
    //   111: irem
    //   112: ifeq +6 -> 118
    //   115: goto -59 -> 56
    //   118: goto +243 -> 361
    //   121: aload 4
    //   123: aload_3
    //   124: invokevirtual 538	o/ᐸ$If:ˊ	(Ljava/lang/CharSequence;)Lo/ᐸ$If;
    //   127: astore 4
    //   129: aload_0
    //   130: getstatic 543	o/Gu$ˏ:nfc_not_enabled_message	I
    //   133: invokevirtual 544	o/IB:getString	(I)Ljava/lang/String;
    //   136: astore_3
    //   137: aload_3
    //   138: aload_0
    //   139: invokevirtual 73	android/content/Context:getPackageName	()Ljava/lang/String;
    //   142: iconst_5
    //   143: invokevirtual 98	java/lang/String:codePointAt	(I)I
    //   146: bipush 48
    //   148: isub
    //   149: aload_0
    //   150: invokevirtual 73	android/content/Context:getPackageName	()Ljava/lang/String;
    //   153: iconst_3
    //   154: invokevirtual 98	java/lang/String:codePointAt	(I)I
    //   157: bipush 98
    //   159: isub
    //   160: i2c
    //   161: aload_0
    //   162: invokevirtual 83	android/content/Context:getResources	()Landroid/content/res/Resources;
    //   165: ldc_w 545
    //   168: invokevirtual 90	android/content/res/Resources:getString	(I)Ljava/lang/String;
    //   171: iconst_0
    //   172: iconst_4
    //   173: invokevirtual 94	java/lang/String:substring	(II)Ljava/lang/String;
    //   176: invokevirtual 79	java/lang/String:length	()I
    //   179: iconst_0
    //   180: iadd
    //   181: invokestatic 155	o/IB:ॱ	(ICI)Ljava/lang/String;
    //   184: invokevirtual 158	java/lang/String:intern	()Ljava/lang/String;
    //   187: invokevirtual 549	java/lang/String:startsWith	(Ljava/lang/String;)Z
    //   190: ifeq +6 -> 196
    //   193: goto +195 -> 388
    //   196: goto +404 -> 600
    //   199: goto -78 -> 121
    //   202: astore_3
    //   203: aload_3
    //   204: athrow
    //   205: new 535	o/ᐸ$If
    //   208: dup
    //   209: aload_0
    //   210: invokespecial 552	o/ᐸ$If:<init>	(Landroid/content/Context;)V
    //   213: astore 4
    //   215: aload_0
    //   216: getstatic 555	o/Gu$ˏ:nfc_not_enabled	I
    //   219: invokevirtual 544	o/IB:getString	(I)Ljava/lang/String;
    //   222: astore_3
    //   223: aload_3
    //   224: aload_0
    //   225: invokevirtual 83	android/content/Context:getResources	()Landroid/content/res/Resources;
    //   228: ldc_w 556
    //   231: invokevirtual 90	android/content/res/Resources:getString	(I)Ljava/lang/String;
    //   234: sipush 244
    //   237: sipush 251
    //   240: invokevirtual 94	java/lang/String:substring	(II)Ljava/lang/String;
    //   243: invokevirtual 79	java/lang/String:length	()I
    //   246: bipush 59
    //   248: iadd
    //   249: aload_0
    //   250: invokevirtual 83	android/content/Context:getResources	()Landroid/content/res/Resources;
    //   253: ldc_w 557
    //   256: invokevirtual 90	android/content/res/Resources:getString	(I)Ljava/lang/String;
    //   259: iconst_0
    //   260: iconst_5
    //   261: invokevirtual 94	java/lang/String:substring	(II)Ljava/lang/String;
    //   264: iconst_2
    //   265: invokevirtual 98	java/lang/String:codePointAt	(I)I
    //   268: bipush 11
    //   270: isub
    //   271: i2c
    //   272: aload_0
    //   273: invokevirtual 83	android/content/Context:getResources	()Landroid/content/res/Resources;
    //   276: ldc_w 558
    //   279: invokevirtual 90	android/content/res/Resources:getString	(I)Ljava/lang/String;
    //   282: iconst_0
    //   283: bipush 9
    //   285: invokevirtual 94	java/lang/String:substring	(II)Ljava/lang/String;
    //   288: invokevirtual 79	java/lang/String:length	()I
    //   291: iconst_5
    //   292: isub
    //   293: invokestatic 155	o/IB:ॱ	(ICI)Ljava/lang/String;
    //   296: invokevirtual 158	java/lang/String:intern	()Ljava/lang/String;
    //   299: invokevirtual 549	java/lang/String:startsWith	(Ljava/lang/String;)Z
    //   302: ifeq +6 -> 308
    //   305: goto -244 -> 61
    //   308: goto -187 -> 121
    //   311: aload 4
    //   313: astore_3
    //   314: iload_1
    //   315: tableswitch	default:+21->336, 0:+140->455, 1:+172->487
    //   336: goto +119 -> 455
    //   339: aload 5
    //   341: aload_3
    //   342: invokevirtual 560	o/ᐸ$If:ॱ	(Ljava/lang/CharSequence;)Lo/ᐸ$If;
    //   345: new 7	o/IB$1
    //   348: dup
    //   349: aload_0
    //   350: invokespecial 562	o/IB$1:<init>	(Lo/IB;)V
    //   353: invokevirtual 565	o/ᐸ$If:ॱ	(Lo/ᐸ$ˏ;)Lo/ᐸ$If;
    //   356: invokevirtual 566	o/ᐸ$If:ˏ	()Lo/ᐸ;
    //   359: pop
    //   360: return
    //   361: iconst_1
    //   362: istore_1
    //   363: goto -360 -> 3
    //   366: goto -161 -> 205
    //   369: aload_0
    //   370: aload_3
    //   371: iconst_4
    //   372: invokevirtual 531	java/lang/String:substring	(I)Ljava/lang/String;
    //   375: invokespecial 533	o/IB:ॱ	(Ljava/lang/String;)Ljava/lang/String;
    //   378: invokevirtual 158	java/lang/String:intern	()Ljava/lang/String;
    //   381: astore_3
    //   382: goto +306 -> 688
    //   385: goto -46 -> 339
    //   388: getstatic 41	o/IB:ʿ	I
    //   391: bipush 21
    //   393: iadd
    //   394: istore_1
    //   395: iload_1
    //   396: sipush 128
    //   399: irem
    //   400: putstatic 39	o/IB:ˊˋ	I
    //   403: iload_1
    //   404: iconst_2
    //   405: irem
    //   406: ifne +6 -> 412
    //   409: goto +287 -> 696
    //   412: goto -43 -> 369
    //   415: astore_3
    //   416: aload_3
    //   417: athrow
    //   418: aload 4
    //   420: astore_3
    //   421: iload_1
    //   422: tableswitch	default:+22->444, 0:+-345->77, 1:+-83->339
    //   444: aload 4
    //   446: astore_3
    //   447: goto -108 -> 339
    //   450: iconst_1
    //   451: istore_1
    //   452: goto -141 -> 311
    //   455: getstatic 41	o/IB:ʿ	I
    //   458: bipush 85
    //   460: iadd
    //   461: istore_1
    //   462: iload_1
    //   463: sipush 128
    //   466: irem
    //   467: putstatic 39	o/IB:ˊˋ	I
    //   470: iload_1
    //   471: iconst_2
    //   472: irem
    //   473: ifne +6 -> 479
    //   476: goto -445 -> 31
    //   479: goto +104 -> 583
    //   482: iconst_1
    //   483: istore_1
    //   484: goto -66 -> 418
    //   487: aload 5
    //   489: aload_3
    //   490: invokevirtual 568	o/ᐸ$If:ˎ	(Ljava/lang/CharSequence;)Lo/ᐸ$If;
    //   493: astore 5
    //   495: aload_0
    //   496: getstatic 571	o/Gu$ˏ:cancel	I
    //   499: invokevirtual 544	o/IB:getString	(I)Ljava/lang/String;
    //   502: astore 4
    //   504: aload 4
    //   506: aload_0
    //   507: invokevirtual 83	android/content/Context:getResources	()Landroid/content/res/Resources;
    //   510: ldc_w 572
    //   513: invokevirtual 90	android/content/res/Resources:getString	(I)Ljava/lang/String;
    //   516: bipush 6
    //   518: bipush 7
    //   520: invokevirtual 94	java/lang/String:substring	(II)Ljava/lang/String;
    //   523: invokevirtual 79	java/lang/String:length	()I
    //   526: bipush 65
    //   528: iadd
    //   529: aload_0
    //   530: invokevirtual 73	android/content/Context:getPackageName	()Ljava/lang/String;
    //   533: invokevirtual 79	java/lang/String:length	()I
    //   536: bipush 11
    //   538: isub
    //   539: i2c
    //   540: aload_0
    //   541: invokevirtual 83	android/content/Context:getResources	()Landroid/content/res/Resources;
    //   544: ldc_w 573
    //   547: invokevirtual 90	android/content/res/Resources:getString	(I)Ljava/lang/String;
    //   550: bipush 7
    //   552: bipush 17
    //   554: invokevirtual 94	java/lang/String:substring	(II)Ljava/lang/String;
    //   557: iconst_0
    //   558: invokevirtual 98	java/lang/String:codePointAt	(I)I
    //   561: sipush 229
    //   564: isub
    //   565: invokestatic 155	o/IB:ॱ	(ICI)Ljava/lang/String;
    //   568: invokevirtual 158	java/lang/String:intern	()Ljava/lang/String;
    //   571: invokevirtual 549	java/lang/String:startsWith	(Ljava/lang/String;)Z
    //   574: ifeq +6 -> 580
    //   577: goto -526 -> 51
    //   580: goto -98 -> 482
    //   583: aload_0
    //   584: aload 4
    //   586: iconst_4
    //   587: invokevirtual 531	java/lang/String:substring	(I)Ljava/lang/String;
    //   590: invokespecial 533	o/IB:ॱ	(Ljava/lang/String;)Ljava/lang/String;
    //   593: invokevirtual 158	java/lang/String:intern	()Ljava/lang/String;
    //   596: astore_3
    //   597: goto -110 -> 487
    //   600: aload 4
    //   602: aload_3
    //   603: invokevirtual 575	o/ᐸ$If:ˋ	(Ljava/lang/CharSequence;)Lo/ᐸ$If;
    //   606: astore 5
    //   608: getstatic 578	o/Gu$ˏ:enable_nfc	I
    //   611: istore_1
    //   612: aload_0
    //   613: iload_1
    //   614: invokevirtual 544	o/IB:getString	(I)Ljava/lang/String;
    //   617: astore 4
    //   619: aload_0
    //   620: invokevirtual 83	android/content/Context:getResources	()Landroid/content/res/Resources;
    //   623: astore_3
    //   624: aload 4
    //   626: aload_3
    //   627: ldc_w 579
    //   630: invokevirtual 90	android/content/res/Resources:getString	(I)Ljava/lang/String;
    //   633: iconst_0
    //   634: iconst_4
    //   635: invokevirtual 94	java/lang/String:substring	(II)Ljava/lang/String;
    //   638: invokevirtual 79	java/lang/String:length	()I
    //   641: bipush 62
    //   643: iadd
    //   644: aload_0
    //   645: invokevirtual 73	android/content/Context:getPackageName	()Ljava/lang/String;
    //   648: invokevirtual 79	java/lang/String:length	()I
    //   651: bipush 11
    //   653: isub
    //   654: i2c
    //   655: aload_0
    //   656: invokevirtual 73	android/content/Context:getPackageName	()Ljava/lang/String;
    //   659: invokevirtual 79	java/lang/String:length	()I
    //   662: bipush 7
    //   664: isub
    //   665: invokestatic 155	o/IB:ॱ	(ICI)Ljava/lang/String;
    //   668: invokevirtual 158	java/lang/String:intern	()Ljava/lang/String;
    //   671: invokevirtual 549	java/lang/String:startsWith	(Ljava/lang/String;)Z
    //   674: istore_2
    //   675: iload_2
    //   676: ifeq +6 -> 682
    //   679: goto +12 -> 691
    //   682: goto -232 -> 450
    //   685: goto -564 -> 121
    //   688: goto -88 -> 600
    //   691: iconst_0
    //   692: istore_1
    //   693: goto -382 -> 311
    //   696: aload_0
    //   697: aload_3
    //   698: iconst_4
    //   699: invokevirtual 531	java/lang/String:substring	(I)Ljava/lang/String;
    //   702: invokespecial 533	o/IB:ॱ	(Ljava/lang/String;)Ljava/lang/String;
    //   705: invokevirtual 158	java/lang/String:intern	()Ljava/lang/String;
    //   708: astore_3
    //   709: aconst_null
    //   710: arraylength
    //   711: istore_1
    //   712: goto -24 -> 688
    // Local variable table:
    //   start	length	slot	name	signature
    //   0	715	0	this	IB
    //   3	709	1	i	int
    //   674	2	2	bool	boolean
    //   44	94	3	str	String
    //   202	2	3	localException1	Exception
    //   222	160	3	localObject1	Object
    //   415	2	3	localException2	Exception
    //   420	289	3	localObject2	Object
    //   32	593	4	localObject3	Object
    //   339	268	5	localIf	ᐸ.If
    // Exception table:
    //   from	to	target	type
    //   608	612	202	java/lang/Exception
    //   612	619	202	java/lang/Exception
    //   619	624	202	java/lang/Exception
    //   624	675	202	java/lang/Exception
    //   600	608	415	java/lang/Exception
  }
  
  protected void ʽॱ()
  {
    break label168;
    int i = 68;
    for (;;)
    {
      switch (i)
      {
      default: 
        break;
        for (;;)
        {
          switch (i)
          {
          default: 
            break label132;
            i = 53;
          }
        }
        for (;;)
        {
          i = 0;
          break;
          i = ʿ + 93;
          ˊˋ = i % 128;
          if (i % 2 == 0) {
            break label171;
          }
        }
      case 1: 
        label67:
        label78:
        label132:
        label168:
        for (;;)
        {
          i = ˊˋ + 19;
          ʿ = i % 128;
          if (i % 2 != 0) {
            break;
          }
          break label67;
          Ic.ˏ(this).ˊ().ˎ(10);
          break label78;
          i = 89 / 0;
          return;
          Ic.ˏ(this).ˊ().ˎ(21);
          break label78;
        }
        label171:
        i = 1;
      }
    }
  }
  
  /* Error */
  protected void ˈ()
  {
    // Byte code:
    //   0: goto +83 -> 83
    //   3: bipush 8
    //   5: istore_1
    //   6: goto +47 -> 53
    //   9: getstatic 41	o/IB:ʿ	I
    //   12: bipush 125
    //   14: iadd
    //   15: istore_1
    //   16: iload_1
    //   17: sipush 128
    //   20: irem
    //   21: putstatic 39	o/IB:ˊˋ	I
    //   24: iload_1
    //   25: iconst_2
    //   26: irem
    //   27: ifne +6 -> 33
    //   30: goto -27 -> 3
    //   33: goto +53 -> 86
    //   36: aload_0
    //   37: aload_3
    //   38: iconst_4
    //   39: invokevirtual 531	java/lang/String:substring	(I)Ljava/lang/String;
    //   42: invokespecial 533	o/IB:ॱ	(Ljava/lang/String;)Ljava/lang/String;
    //   45: invokevirtual 158	java/lang/String:intern	()Ljava/lang/String;
    //   48: astore 4
    //   50: goto +48 -> 98
    //   53: iload_1
    //   54: lookupswitch	default:+26->80, 8:+188->242, 11:+-18->36
    //   80: goto +162 -> 242
    //   83: goto +18 -> 101
    //   86: bipush 11
    //   88: istore_1
    //   89: goto -36 -> 53
    //   92: bipush 16
    //   94: istore_1
    //   95: goto +33 -> 128
    //   98: goto +170 -> 268
    //   101: getstatic 41	o/IB:ʿ	I
    //   104: bipush 103
    //   106: iadd
    //   107: istore_1
    //   108: iload_1
    //   109: sipush 128
    //   112: irem
    //   113: putstatic 39	o/IB:ˊˋ	I
    //   116: iload_1
    //   117: iconst_2
    //   118: irem
    //   119: ifne +6 -> 125
    //   122: goto +325 -> 447
    //   125: goto +41 -> 166
    //   128: aload_3
    //   129: astore 4
    //   131: iload_1
    //   132: lookupswitch	default:+28->160, 2:+136->268, 16:+-123->9
    //   160: aload_3
    //   161: astore 4
    //   163: goto +105 -> 268
    //   166: getstatic 595	o/Gu$ˏ:device_rooted_security_problems	I
    //   169: istore_1
    //   170: aload_0
    //   171: iload_1
    //   172: invokevirtual 544	o/IB:getString	(I)Ljava/lang/String;
    //   175: astore_3
    //   176: aload_0
    //   177: invokevirtual 102	android/content/Context:getApplicationInfo	()Landroid/content/pm/ApplicationInfo;
    //   180: astore 4
    //   182: aload 4
    //   184: getfield 107	android/content/pm/ApplicationInfo:targetSdkVersion	I
    //   187: istore_1
    //   188: aload_0
    //   189: invokevirtual 73	android/content/Context:getPackageName	()Ljava/lang/String;
    //   192: astore 4
    //   194: aload_3
    //   195: iload_1
    //   196: bipush 41
    //   198: iadd
    //   199: aload 4
    //   201: iconst_1
    //   202: invokevirtual 98	java/lang/String:codePointAt	(I)I
    //   205: bipush 111
    //   207: isub
    //   208: i2c
    //   209: aload_0
    //   210: invokevirtual 102	android/content/Context:getApplicationInfo	()Landroid/content/pm/ApplicationInfo;
    //   213: getfield 107	android/content/pm/ApplicationInfo:targetSdkVersion	I
    //   216: bipush 21
    //   218: isub
    //   219: invokestatic 155	o/IB:ॱ	(ICI)Ljava/lang/String;
    //   222: invokevirtual 158	java/lang/String:intern	()Ljava/lang/String;
    //   225: invokevirtual 549	java/lang/String:startsWith	(Ljava/lang/String;)Z
    //   228: istore_2
    //   229: iload_2
    //   230: ifeq +6 -> 236
    //   233: goto -141 -> 92
    //   236: goto +27 -> 263
    //   239: astore_3
    //   240: aload_3
    //   241: athrow
    //   242: aload_0
    //   243: aload_3
    //   244: iconst_4
    //   245: invokevirtual 531	java/lang/String:substring	(I)Ljava/lang/String;
    //   248: invokespecial 533	o/IB:ॱ	(Ljava/lang/String;)Ljava/lang/String;
    //   251: invokevirtual 158	java/lang/String:intern	()Ljava/lang/String;
    //   254: astore_3
    //   255: new 47	java/lang/NullPointerException
    //   258: dup
    //   259: invokespecial 50	java/lang/NullPointerException:<init>	()V
    //   262: athrow
    //   263: iconst_2
    //   264: istore_1
    //   265: goto -137 -> 128
    //   268: goto +20 -> 288
    //   271: astore_3
    //   272: aload_3
    //   273: invokevirtual 67	java/lang/Throwable:getCause	()Ljava/lang/Throwable;
    //   276: astore 4
    //   278: aload 4
    //   280: ifnull +6 -> 286
    //   283: aload 4
    //   285: athrow
    //   286: aload_3
    //   287: athrow
    //   288: aload_0
    //   289: invokevirtual 102	android/content/Context:getApplicationInfo	()Landroid/content/pm/ApplicationInfo;
    //   292: getfield 107	android/content/pm/ApplicationInfo:targetSdkVersion	I
    //   295: bipush 22
    //   297: isub
    //   298: aload_0
    //   299: invokevirtual 73	android/content/Context:getPackageName	()Ljava/lang/String;
    //   302: iconst_5
    //   303: invokevirtual 98	java/lang/String:codePointAt	(I)I
    //   306: bipush 114
    //   308: isub
    //   309: aload_0
    //   310: invokevirtual 83	android/content/Context:getResources	()Landroid/content/res/Resources;
    //   313: ldc_w 596
    //   316: invokevirtual 90	android/content/res/Resources:getString	(I)Ljava/lang/String;
    //   319: iconst_0
    //   320: iconst_5
    //   321: invokevirtual 94	java/lang/String:substring	(II)Ljava/lang/String;
    //   324: invokevirtual 79	java/lang/String:length	()I
    //   327: ldc_w 597
    //   330: iadd
    //   331: i2c
    //   332: invokestatic 113	o/O:ˋ	(IIC)Ljava/lang/Object;
    //   335: checkcast 115	java/lang/Class
    //   338: ldc -64
    //   340: aconst_null
    //   341: invokevirtual 120	java/lang/Class:getMethod	(Ljava/lang/String;[Ljava/lang/Class;)Ljava/lang/reflect/Method;
    //   344: aconst_null
    //   345: aconst_null
    //   346: invokevirtual 126	java/lang/reflect/Method:invoke	(Ljava/lang/Object;[Ljava/lang/Object;)Ljava/lang/Object;
    //   349: astore_3
    //   350: goto +20 -> 370
    //   353: astore 4
    //   355: aload 4
    //   357: invokevirtual 67	java/lang/Throwable:getCause	()Ljava/lang/Throwable;
    //   360: astore_3
    //   361: aload_3
    //   362: ifnull +5 -> 367
    //   365: aload_3
    //   366: athrow
    //   367: aload 4
    //   369: athrow
    //   370: aload_0
    //   371: invokevirtual 73	android/content/Context:getPackageName	()Ljava/lang/String;
    //   374: invokevirtual 79	java/lang/String:length	()I
    //   377: bipush 8
    //   379: isub
    //   380: aload_0
    //   381: invokevirtual 73	android/content/Context:getPackageName	()Ljava/lang/String;
    //   384: invokevirtual 79	java/lang/String:length	()I
    //   387: bipush 11
    //   389: isub
    //   390: aload_0
    //   391: invokevirtual 102	android/content/Context:getApplicationInfo	()Landroid/content/pm/ApplicationInfo;
    //   394: getfield 107	android/content/pm/ApplicationInfo:targetSdkVersion	I
    //   397: ldc_w 598
    //   400: iadd
    //   401: i2c
    //   402: invokestatic 113	o/O:ˋ	(IIC)Ljava/lang/Object;
    //   405: checkcast 115	java/lang/Class
    //   408: ldc 116
    //   410: aconst_null
    //   411: invokevirtual 120	java/lang/Class:getMethod	(Ljava/lang/String;[Ljava/lang/Class;)Ljava/lang/reflect/Method;
    //   414: aload_3
    //   415: aconst_null
    //   416: invokevirtual 126	java/lang/reflect/Method:invoke	(Ljava/lang/Object;[Ljava/lang/Object;)Ljava/lang/Object;
    //   419: astore_3
    //   420: aload 4
    //   422: iconst_1
    //   423: anewarray 133	java/lang/Object
    //   426: dup
    //   427: iconst_0
    //   428: aload_3
    //   429: aastore
    //   430: invokestatic 602	java/lang/String:format	(Ljava/lang/String;[Ljava/lang/Object;)Ljava/lang/String;
    //   433: astore_3
    //   434: aload_0
    //   435: invokestatic 607	o/Gz:ˏ	(Landroid/content/Context;)Lo/Gz;
    //   438: aload_0
    //   439: aload_3
    //   440: getstatic 613	o/Fh:BLR_DEVICE_ROOTED	Lo/Fh;
    //   443: invokevirtual 616	o/Gz:ˊ	(Landroid/content/Context;Ljava/lang/String;Lo/Fh;)V
    //   446: return
    //   447: goto -281 -> 166
    // Local variable table:
    //   start	length	slot	name	signature
    //   0	450	0	this	IB
    //   5	260	1	i	int
    //   228	2	2	bool	boolean
    //   37	158	3	str1	String
    //   239	5	3	localException	Exception
    //   254	1	3	str2	String
    //   271	16	3	localObject1	Object
    //   349	91	3	localObject2	Object
    //   48	236	4	localObject3	Object
    //   353	68	4	str3	String
    // Exception table:
    //   from	to	target	type
    //   166	170	239	java/lang/Exception
    //   170	176	239	java/lang/Exception
    //   176	182	239	java/lang/Exception
    //   182	188	239	java/lang/Exception
    //   188	194	239	java/lang/Exception
    //   194	229	239	java/lang/Exception
    //   288	350	271	finally
    //   370	420	353	finally
  }
  
  public void ˋ(View.OnClickListener paramOnClickListener)
  {
    break label231;
    int i = 92;
    break label74;
    i = null.length;
    return;
    for (;;)
    {
      i = ʿ + 43;
      ˊˋ = i % 128;
      if (i % 2 == 0) {
        break;
      }
      break label71;
      return;
    }
    label44:
    i = ʿ + 117;
    ˊˋ = i % 128;
    if (i % 2 != 0)
    {
      break label101;
      label71:
      i = 72;
      label74:
      switch (i)
      {
      }
      return;
    }
    for (;;)
    {
      try
      {
        label101:
        RelativeLayout localRelativeLayout = this.ॱᐝ;
        if (localRelativeLayout == null) {
          continue;
        }
        this.ॱˎ = new View(this);
        this.ॱˎ.setLayoutParams(new FrameLayout.LayoutParams(-1, -1));
        this.ॱˎ.setOnClickListener(paramOnClickListener);
        this.ॱᐝ.addView(this.ॱˎ);
        this.ॱˎ.bringToFront();
        break;
        throw new ClassCastException(ॱ(getResources().getString(2131755247).substring(0, 11).length() - 11, (char)(getApplicationInfo().targetSdkVersion + 30823), getPackageName().length() + 55).intern());
      }
      catch (Exception paramOnClickListener)
      {
        label231:
        throw paramOnClickListener;
      }
      break label44;
    }
  }
  
  /* Error */
  public void ˋ(String paramString)
  {
    // Byte code:
    //   0: goto +44 -> 44
    //   3: iconst_1
    //   4: istore_2
    //   5: goto +336 -> 341
    //   8: return
    //   9: astore_1
    //   10: aload_1
    //   11: athrow
    //   12: getstatic 39	o/IB:ˊˋ	I
    //   15: bipush 115
    //   17: iadd
    //   18: istore_2
    //   19: iload_2
    //   20: sipush 128
    //   23: irem
    //   24: putstatic 41	o/IB:ʿ	I
    //   27: iload_2
    //   28: iconst_2
    //   29: irem
    //   30: ifeq +6 -> 36
    //   33: goto +6 -> 39
    //   36: goto -33 -> 3
    //   39: iconst_0
    //   40: istore_2
    //   41: goto +300 -> 341
    //   44: aload_0
    //   45: invokevirtual 83	android/content/Context:getResources	()Landroid/content/res/Resources;
    //   48: astore_3
    //   49: aload_3
    //   50: ldc_w 647
    //   53: invokevirtual 90	android/content/res/Resources:getString	(I)Ljava/lang/String;
    //   56: iconst_0
    //   57: bipush 7
    //   59: invokevirtual 94	java/lang/String:substring	(II)Ljava/lang/String;
    //   62: iconst_1
    //   63: invokevirtual 98	java/lang/String:codePointAt	(I)I
    //   66: bipush 100
    //   68: iadd
    //   69: aload_0
    //   70: invokevirtual 102	android/content/Context:getApplicationInfo	()Landroid/content/pm/ApplicationInfo;
    //   73: getfield 107	android/content/pm/ApplicationInfo:targetSdkVersion	I
    //   76: sipush 2812
    //   79: iadd
    //   80: i2c
    //   81: aload_0
    //   82: invokevirtual 83	android/content/Context:getResources	()Landroid/content/res/Resources;
    //   85: ldc_w 648
    //   88: invokevirtual 90	android/content/res/Resources:getString	(I)Ljava/lang/String;
    //   91: iconst_0
    //   92: bipush 9
    //   94: invokevirtual 94	java/lang/String:substring	(II)Ljava/lang/String;
    //   97: bipush 7
    //   99: invokevirtual 98	java/lang/String:codePointAt	(I)I
    //   102: sipush 242
    //   105: isub
    //   106: invokestatic 155	o/IB:ॱ	(ICI)Ljava/lang/String;
    //   109: invokevirtual 158	java/lang/String:intern	()Ljava/lang/String;
    //   112: astore_3
    //   113: new 650	java/lang/StringBuilder
    //   116: dup
    //   117: invokespecial 651	java/lang/StringBuilder:<init>	()V
    //   120: aload_0
    //   121: invokevirtual 83	android/content/Context:getResources	()Landroid/content/res/Resources;
    //   124: ldc_w 516
    //   127: invokevirtual 90	android/content/res/Resources:getString	(I)Ljava/lang/String;
    //   130: iconst_0
    //   131: iconst_5
    //   132: invokevirtual 94	java/lang/String:substring	(II)Ljava/lang/String;
    //   135: iconst_3
    //   136: invokevirtual 98	java/lang/String:codePointAt	(I)I
    //   139: bipush 121
    //   141: iadd
    //   142: aload_0
    //   143: invokevirtual 102	android/content/Context:getApplicationInfo	()Landroid/content/pm/ApplicationInfo;
    //   146: getfield 107	android/content/pm/ApplicationInfo:targetSdkVersion	I
    //   149: bipush 25
    //   151: isub
    //   152: i2c
    //   153: aload_0
    //   154: invokevirtual 102	android/content/Context:getApplicationInfo	()Landroid/content/pm/ApplicationInfo;
    //   157: getfield 107	android/content/pm/ApplicationInfo:targetSdkVersion	I
    //   160: iconst_0
    //   161: iadd
    //   162: invokestatic 155	o/IB:ॱ	(ICI)Ljava/lang/String;
    //   165: invokevirtual 158	java/lang/String:intern	()Ljava/lang/String;
    //   168: invokevirtual 655	java/lang/StringBuilder:append	(Ljava/lang/String;)Ljava/lang/StringBuilder;
    //   171: aload_1
    //   172: invokevirtual 655	java/lang/StringBuilder:append	(Ljava/lang/String;)Ljava/lang/StringBuilder;
    //   175: invokevirtual 658	java/lang/StringBuilder:toString	()Ljava/lang/String;
    //   178: astore 4
    //   180: goto +17 -> 197
    //   183: astore_1
    //   184: aload_1
    //   185: invokevirtual 67	java/lang/Throwable:getCause	()Ljava/lang/Throwable;
    //   188: astore_3
    //   189: aload_3
    //   190: ifnull +5 -> 195
    //   193: aload_3
    //   194: athrow
    //   195: aload_1
    //   196: athrow
    //   197: aload_0
    //   198: invokevirtual 83	android/content/Context:getResources	()Landroid/content/res/Resources;
    //   201: ldc_w 659
    //   204: invokevirtual 90	android/content/res/Resources:getString	(I)Ljava/lang/String;
    //   207: iconst_0
    //   208: iconst_1
    //   209: invokevirtual 94	java/lang/String:substring	(II)Ljava/lang/String;
    //   212: iconst_0
    //   213: invokevirtual 98	java/lang/String:codePointAt	(I)I
    //   216: bipush 52
    //   218: isub
    //   219: aload_0
    //   220: invokevirtual 83	android/content/Context:getResources	()Landroid/content/res/Resources;
    //   223: ldc_w 660
    //   226: invokevirtual 90	android/content/res/Resources:getString	(I)Ljava/lang/String;
    //   229: iconst_0
    //   230: iconst_4
    //   231: invokevirtual 94	java/lang/String:substring	(II)Ljava/lang/String;
    //   234: invokevirtual 79	java/lang/String:length	()I
    //   237: bipush 38
    //   239: iadd
    //   240: aload_0
    //   241: invokevirtual 83	android/content/Context:getResources	()Landroid/content/res/Resources;
    //   244: ldc_w 661
    //   247: invokevirtual 90	android/content/res/Resources:getString	(I)Ljava/lang/String;
    //   250: iconst_0
    //   251: bipush 17
    //   253: invokevirtual 94	java/lang/String:substring	(II)Ljava/lang/String;
    //   256: iconst_4
    //   257: invokevirtual 98	java/lang/String:codePointAt	(I)I
    //   260: ldc_w 662
    //   263: iadd
    //   264: i2c
    //   265: invokestatic 113	o/O:ˋ	(IIC)Ljava/lang/Object;
    //   268: checkcast 115	java/lang/Class
    //   271: ldc -64
    //   273: iconst_2
    //   274: anewarray 115	java/lang/Class
    //   277: dup
    //   278: iconst_0
    //   279: ldc 75
    //   281: aastore
    //   282: dup
    //   283: iconst_1
    //   284: ldc 75
    //   286: aastore
    //   287: invokevirtual 120	java/lang/Class:getMethod	(Ljava/lang/String;[Ljava/lang/Class;)Ljava/lang/reflect/Method;
    //   290: aconst_null
    //   291: iconst_2
    //   292: anewarray 133	java/lang/Object
    //   295: dup
    //   296: iconst_0
    //   297: aload_3
    //   298: aastore
    //   299: dup
    //   300: iconst_1
    //   301: aload 4
    //   303: aastore
    //   304: invokevirtual 126	java/lang/reflect/Method:invoke	(Ljava/lang/Object;[Ljava/lang/Object;)Ljava/lang/Object;
    //   307: pop
    //   308: aload_0
    //   309: invokevirtual 663	o/IB:getResources	()Landroid/content/res/Resources;
    //   312: astore_3
    //   313: aload_3
    //   314: invokevirtual 667	android/content/res/Resources:getConfiguration	()Landroid/content/res/Configuration;
    //   317: astore 4
    //   319: aload 4
    //   321: aload_1
    //   322: invokestatic 672	o/aq:ᐝ	(Ljava/lang/String;)Ljava/util/Locale;
    //   325: invokevirtual 678	android/content/res/Configuration:setLocale	(Ljava/util/Locale;)V
    //   328: aload_3
    //   329: aload 4
    //   331: aload_3
    //   332: invokevirtual 682	android/content/res/Resources:getDisplayMetrics	()Landroid/util/DisplayMetrics;
    //   335: invokevirtual 686	android/content/res/Resources:updateConfiguration	(Landroid/content/res/Configuration;Landroid/util/DisplayMetrics;)V
    //   338: goto -326 -> 12
    //   341: iload_2
    //   342: tableswitch	default:+22->364, 0:+23->365, 1:+-334->8
    //   364: return
    //   365: new 47	java/lang/NullPointerException
    //   368: dup
    //   369: invokespecial 50	java/lang/NullPointerException:<init>	()V
    //   372: athrow
    // Local variable table:
    //   start	length	slot	name	signature
    //   0	373	0	this	IB
    //   0	373	1	paramString	String
    //   4	338	2	i	int
    //   48	284	3	localObject1	Object
    //   178	152	4	localObject2	Object
    // Exception table:
    //   from	to	target	type
    //   12	19	9	java/lang/Exception
    //   19	27	9	java/lang/Exception
    //   44	49	9	java/lang/Exception
    //   49	180	9	java/lang/Exception
    //   184	189	9	java/lang/Exception
    //   193	195	9	java/lang/Exception
    //   195	197	9	java/lang/Exception
    //   308	338	9	java/lang/Exception
    //   197	308	183	finally
  }
  
  /* Error */
  protected void ˋ(boolean paramBoolean)
  {
    // Byte code:
    //   0: goto +519 -> 519
    //   3: goto +20 -> 23
    //   6: astore_3
    //   7: aload_3
    //   8: invokevirtual 67	java/lang/Throwable:getCause	()Ljava/lang/Throwable;
    //   11: astore 4
    //   13: aload 4
    //   15: ifnull +6 -> 21
    //   18: aload 4
    //   20: athrow
    //   21: aload_3
    //   22: athrow
    //   23: aload_0
    //   24: invokevirtual 102	android/content/Context:getApplicationInfo	()Landroid/content/pm/ApplicationInfo;
    //   27: getfield 107	android/content/pm/ApplicationInfo:targetSdkVersion	I
    //   30: bipush 22
    //   32: isub
    //   33: aload_0
    //   34: invokevirtual 73	android/content/Context:getPackageName	()Ljava/lang/String;
    //   37: invokevirtual 79	java/lang/String:length	()I
    //   40: bipush 11
    //   42: isub
    //   43: aload_0
    //   44: invokevirtual 102	android/content/Context:getApplicationInfo	()Landroid/content/pm/ApplicationInfo;
    //   47: getfield 107	android/content/pm/ApplicationInfo:targetSdkVersion	I
    //   50: ldc_w 598
    //   53: iadd
    //   54: i2c
    //   55: invokestatic 113	o/O:ˋ	(IIC)Ljava/lang/Object;
    //   58: checkcast 115	java/lang/Class
    //   61: ldc -64
    //   63: aconst_null
    //   64: invokevirtual 120	java/lang/Class:getMethod	(Ljava/lang/String;[Ljava/lang/Class;)Ljava/lang/reflect/Method;
    //   67: aconst_null
    //   68: aconst_null
    //   69: invokevirtual 126	java/lang/reflect/Method:invoke	(Ljava/lang/Object;[Ljava/lang/Object;)Ljava/lang/Object;
    //   72: astore_3
    //   73: goto +20 -> 93
    //   76: astore_3
    //   77: aload_3
    //   78: invokevirtual 67	java/lang/Throwable:getCause	()Ljava/lang/Throwable;
    //   81: astore 4
    //   83: aload 4
    //   85: ifnull +6 -> 91
    //   88: aload 4
    //   90: athrow
    //   91: aload_3
    //   92: athrow
    //   93: aload_0
    //   94: invokevirtual 102	android/content/Context:getApplicationInfo	()Landroid/content/pm/ApplicationInfo;
    //   97: getfield 107	android/content/pm/ApplicationInfo:targetSdkVersion	I
    //   100: bipush 22
    //   102: isub
    //   103: aload_0
    //   104: invokevirtual 83	android/content/Context:getResources	()Landroid/content/res/Resources;
    //   107: ldc_w 687
    //   110: invokevirtual 90	android/content/res/Resources:getString	(I)Ljava/lang/String;
    //   113: iconst_0
    //   114: iconst_4
    //   115: invokevirtual 94	java/lang/String:substring	(II)Ljava/lang/String;
    //   118: iconst_1
    //   119: invokevirtual 98	java/lang/String:codePointAt	(I)I
    //   122: bipush 26
    //   124: isub
    //   125: aload_0
    //   126: invokevirtual 102	android/content/Context:getApplicationInfo	()Landroid/content/pm/ApplicationInfo;
    //   129: getfield 107	android/content/pm/ApplicationInfo:targetSdkVersion	I
    //   132: ldc_w 598
    //   135: iadd
    //   136: i2c
    //   137: invokestatic 113	o/O:ˋ	(IIC)Ljava/lang/Object;
    //   140: checkcast 115	java/lang/Class
    //   143: ldc_w 688
    //   146: aconst_null
    //   147: invokevirtual 120	java/lang/Class:getMethod	(Ljava/lang/String;[Ljava/lang/Class;)Ljava/lang/reflect/Method;
    //   150: aload_3
    //   151: aconst_null
    //   152: invokevirtual 126	java/lang/reflect/Method:invoke	(Ljava/lang/Object;[Ljava/lang/Object;)Ljava/lang/Object;
    //   155: checkcast 195	java/lang/Boolean
    //   158: invokevirtual 199	java/lang/Boolean:booleanValue	()Z
    //   161: istore_1
    //   162: aconst_null
    //   163: arraylength
    //   164: istore_2
    //   165: iload_1
    //   166: ifne +6 -> 172
    //   169: goto +298 -> 467
    //   172: return
    //   173: iload_2
    //   174: tableswitch	default:+22->196, 0:+-171->3, 1:+22->196
    //   196: goto +20 -> 216
    //   199: astore_3
    //   200: aload_3
    //   201: invokevirtual 67	java/lang/Throwable:getCause	()Ljava/lang/Throwable;
    //   204: astore 4
    //   206: aload 4
    //   208: ifnull +6 -> 214
    //   211: aload 4
    //   213: athrow
    //   214: aload_3
    //   215: athrow
    //   216: aload_0
    //   217: invokevirtual 83	android/content/Context:getResources	()Landroid/content/res/Resources;
    //   220: ldc_w 689
    //   223: invokevirtual 90	android/content/res/Resources:getString	(I)Ljava/lang/String;
    //   226: iconst_0
    //   227: iconst_5
    //   228: invokevirtual 94	java/lang/String:substring	(II)Ljava/lang/String;
    //   231: iconst_0
    //   232: invokevirtual 98	java/lang/String:codePointAt	(I)I
    //   235: iconst_2
    //   236: isub
    //   237: aload_0
    //   238: invokevirtual 83	android/content/Context:getResources	()Landroid/content/res/Resources;
    //   241: ldc_w 690
    //   244: invokevirtual 90	android/content/res/Resources:getString	(I)Ljava/lang/String;
    //   247: iconst_0
    //   248: iconst_4
    //   249: invokevirtual 94	java/lang/String:substring	(II)Ljava/lang/String;
    //   252: iconst_2
    //   253: invokevirtual 98	java/lang/String:codePointAt	(I)I
    //   256: bipush 11
    //   258: isub
    //   259: aload_0
    //   260: invokevirtual 102	android/content/Context:getApplicationInfo	()Landroid/content/pm/ApplicationInfo;
    //   263: getfield 107	android/content/pm/ApplicationInfo:targetSdkVersion	I
    //   266: ldc_w 598
    //   269: iadd
    //   270: i2c
    //   271: invokestatic 113	o/O:ˋ	(IIC)Ljava/lang/Object;
    //   274: checkcast 115	java/lang/Class
    //   277: ldc -64
    //   279: aconst_null
    //   280: invokevirtual 120	java/lang/Class:getMethod	(Ljava/lang/String;[Ljava/lang/Class;)Ljava/lang/reflect/Method;
    //   283: aconst_null
    //   284: aconst_null
    //   285: invokevirtual 126	java/lang/reflect/Method:invoke	(Ljava/lang/Object;[Ljava/lang/Object;)Ljava/lang/Object;
    //   288: astore_3
    //   289: goto +20 -> 309
    //   292: astore_3
    //   293: aload_3
    //   294: invokevirtual 67	java/lang/Throwable:getCause	()Ljava/lang/Throwable;
    //   297: astore 4
    //   299: aload 4
    //   301: ifnull +6 -> 307
    //   304: aload 4
    //   306: athrow
    //   307: aload_3
    //   308: athrow
    //   309: aload_0
    //   310: invokevirtual 83	android/content/Context:getResources	()Landroid/content/res/Resources;
    //   313: ldc_w 691
    //   316: invokevirtual 90	android/content/res/Resources:getString	(I)Ljava/lang/String;
    //   319: iconst_0
    //   320: bipush 9
    //   322: invokevirtual 94	java/lang/String:substring	(II)Ljava/lang/String;
    //   325: iconst_2
    //   326: invokevirtual 98	java/lang/String:codePointAt	(I)I
    //   329: bipush 8
    //   331: isub
    //   332: aload_0
    //   333: invokevirtual 83	android/content/Context:getResources	()Landroid/content/res/Resources;
    //   336: ldc_w 692
    //   339: invokevirtual 90	android/content/res/Resources:getString	(I)Ljava/lang/String;
    //   342: iconst_0
    //   343: iconst_5
    //   344: invokevirtual 94	java/lang/String:substring	(II)Ljava/lang/String;
    //   347: invokevirtual 79	java/lang/String:length	()I
    //   350: iconst_5
    //   351: isub
    //   352: aload_0
    //   353: invokevirtual 102	android/content/Context:getApplicationInfo	()Landroid/content/pm/ApplicationInfo;
    //   356: getfield 107	android/content/pm/ApplicationInfo:targetSdkVersion	I
    //   359: ldc_w 598
    //   362: iadd
    //   363: i2c
    //   364: invokestatic 113	o/O:ˋ	(IIC)Ljava/lang/Object;
    //   367: checkcast 115	java/lang/Class
    //   370: ldc_w 688
    //   373: aconst_null
    //   374: invokevirtual 120	java/lang/Class:getMethod	(Ljava/lang/String;[Ljava/lang/Class;)Ljava/lang/reflect/Method;
    //   377: aload_3
    //   378: aconst_null
    //   379: invokevirtual 126	java/lang/reflect/Method:invoke	(Ljava/lang/Object;[Ljava/lang/Object;)Ljava/lang/Object;
    //   382: checkcast 195	java/lang/Boolean
    //   385: invokevirtual 199	java/lang/Boolean:booleanValue	()Z
    //   388: istore_1
    //   389: iload_1
    //   390: ifne +6 -> 396
    //   393: goto +82 -> 475
    //   396: goto +65 -> 461
    //   399: return
    //   400: iconst_0
    //   401: istore_2
    //   402: goto -229 -> 173
    //   405: getstatic 41	o/IB:ʿ	I
    //   408: bipush 107
    //   410: iadd
    //   411: istore_2
    //   412: iload_2
    //   413: sipush 128
    //   416: irem
    //   417: putstatic 39	o/IB:ˊˋ	I
    //   420: iload_2
    //   421: iconst_2
    //   422: irem
    //   423: ifne +6 -> 429
    //   426: goto -26 -> 400
    //   429: goto +52 -> 481
    //   432: iload_2
    //   433: lookupswitch	default:+27->460, 43:+34->467, 86:+-34->399
    //   460: return
    //   461: bipush 86
    //   463: istore_2
    //   464: goto -32 -> 432
    //   467: aload_0
    //   468: invokevirtual 694	o/IB:ʼॱ	()V
    //   471: goto +18 -> 489
    //   474: return
    //   475: bipush 43
    //   477: istore_2
    //   478: goto -46 -> 432
    //   481: iconst_1
    //   482: istore_2
    //   483: goto -310 -> 173
    //   486: goto -12 -> 474
    //   489: getstatic 39	o/IB:ˊˋ	I
    //   492: bipush 17
    //   494: iadd
    //   495: istore_2
    //   496: iload_2
    //   497: sipush 128
    //   500: irem
    //   501: putstatic 41	o/IB:ʿ	I
    //   504: iload_2
    //   505: iconst_2
    //   506: irem
    //   507: ifeq +6 -> 513
    //   510: goto -24 -> 486
    //   513: goto -39 -> 474
    //   516: astore_3
    //   517: aload_3
    //   518: athrow
    //   519: goto -114 -> 405
    // Local variable table:
    //   start	length	slot	name	signature
    //   0	522	0	this	IB
    //   0	522	1	paramBoolean	boolean
    //   164	343	2	i	int
    //   6	16	3	localObject1	Object
    //   72	1	3	localObject2	Object
    //   76	75	3	localObject3	Object
    //   199	16	3	localObject4	Object
    //   288	1	3	localObject5	Object
    //   292	86	3	localObject6	Object
    //   516	2	3	localException	Exception
    //   11	294	4	localThrowable	Throwable
    // Exception table:
    //   from	to	target	type
    //   23	73	6	finally
    //   93	162	76	finally
    //   216	289	199	finally
    //   309	389	292	finally
    //   405	412	516	java/lang/Exception
    //   412	420	516	java/lang/Exception
  }
  
  /* Error */
  @zA(ˎ=org.greenrobot.eventbus.ThreadMode.MAIN)
  public void ˎ(HT paramHT)
  {
    // Byte code:
    //   0: goto +427 -> 427
    //   3: aload_0
    //   4: aload 4
    //   6: iconst_4
    //   7: invokevirtual 531	java/lang/String:substring	(I)Ljava/lang/String;
    //   10: invokespecial 533	o/IB:ॱ	(Ljava/lang/String;)Ljava/lang/String;
    //   13: invokevirtual 158	java/lang/String:intern	()Ljava/lang/String;
    //   16: astore_1
    //   17: new 47	java/lang/NullPointerException
    //   20: dup
    //   21: invokespecial 50	java/lang/NullPointerException:<init>	()V
    //   24: athrow
    //   25: aload 6
    //   27: aload 5
    //   29: invokevirtual 538	o/ᐸ$If:ˊ	(Ljava/lang/CharSequence;)Lo/ᐸ$If;
    //   32: aload_1
    //   33: getfield 703	o/HT:errorMessageRes	I
    //   36: invokevirtual 706	o/ᐸ$If:ˊ	(I)Lo/ᐸ$If;
    //   39: astore 5
    //   41: aload_0
    //   42: getstatic 709	o/Gu$ˏ:ok	I
    //   45: invokevirtual 544	o/IB:getString	(I)Ljava/lang/String;
    //   48: astore 4
    //   50: aload 4
    //   52: aload_0
    //   53: invokevirtual 83	android/content/Context:getResources	()Landroid/content/res/Resources;
    //   56: ldc_w 710
    //   59: invokevirtual 90	android/content/res/Resources:getString	(I)Ljava/lang/String;
    //   62: iconst_0
    //   63: iconst_4
    //   64: invokevirtual 94	java/lang/String:substring	(II)Ljava/lang/String;
    //   67: iconst_2
    //   68: invokevirtual 98	java/lang/String:codePointAt	(I)I
    //   71: bipush 55
    //   73: iadd
    //   74: aload_0
    //   75: invokevirtual 83	android/content/Context:getResources	()Landroid/content/res/Resources;
    //   78: ldc_w 711
    //   81: invokevirtual 90	android/content/res/Resources:getString	(I)Ljava/lang/String;
    //   84: iconst_0
    //   85: iconst_4
    //   86: invokevirtual 94	java/lang/String:substring	(II)Ljava/lang/String;
    //   89: iconst_3
    //   90: invokevirtual 98	java/lang/String:codePointAt	(I)I
    //   93: bipush 12
    //   95: isub
    //   96: i2c
    //   97: aload_0
    //   98: invokevirtual 83	android/content/Context:getResources	()Landroid/content/res/Resources;
    //   101: ldc_w 712
    //   104: invokevirtual 90	android/content/res/Resources:getString	(I)Ljava/lang/String;
    //   107: iconst_0
    //   108: iconst_4
    //   109: invokevirtual 94	java/lang/String:substring	(II)Ljava/lang/String;
    //   112: invokevirtual 79	java/lang/String:length	()I
    //   115: iconst_0
    //   116: iadd
    //   117: invokestatic 155	o/IB:ॱ	(ICI)Ljava/lang/String;
    //   120: invokevirtual 158	java/lang/String:intern	()Ljava/lang/String;
    //   123: invokevirtual 549	java/lang/String:startsWith	(Ljava/lang/String;)Z
    //   126: ifeq +6 -> 132
    //   129: goto +490 -> 619
    //   132: goto +370 -> 502
    //   135: astore_1
    //   136: aload_1
    //   137: athrow
    //   138: iload_2
    //   139: lookupswitch	default:+25->164, 71:+-136->3, 96:+60->199
    //   164: goto +35 -> 199
    //   167: aload 4
    //   169: astore_1
    //   170: iload_2
    //   171: lookupswitch	default:+25->196, 12:+454->625, 34:+193->364
    //   196: goto +429 -> 625
    //   199: aload_0
    //   200: aload 4
    //   202: iconst_4
    //   203: invokevirtual 531	java/lang/String:substring	(I)Ljava/lang/String;
    //   206: invokespecial 533	o/IB:ॱ	(Ljava/lang/String;)Ljava/lang/String;
    //   209: invokevirtual 158	java/lang/String:intern	()Ljava/lang/String;
    //   212: astore 5
    //   214: goto +147 -> 361
    //   217: getstatic 715	o/IB$5:ˋ	[I
    //   220: astore 4
    //   222: aload_1
    //   223: invokevirtual 719	o/HT:ॱ$3bf1754e	()Ljava/lang/Enum;
    //   226: astore 5
    //   228: goto +20 -> 248
    //   231: astore_1
    //   232: aload_1
    //   233: invokevirtual 67	java/lang/Throwable:getCause	()Ljava/lang/Throwable;
    //   236: astore 4
    //   238: aload 4
    //   240: ifnull +6 -> 246
    //   243: aload 4
    //   245: athrow
    //   246: aload_1
    //   247: athrow
    //   248: aload_0
    //   249: invokevirtual 102	android/content/Context:getApplicationInfo	()Landroid/content/pm/ApplicationInfo;
    //   252: getfield 107	android/content/pm/ApplicationInfo:targetSdkVersion	I
    //   255: bipush 21
    //   257: isub
    //   258: aload_0
    //   259: invokevirtual 102	android/content/Context:getApplicationInfo	()Landroid/content/pm/ApplicationInfo;
    //   262: getfield 107	android/content/pm/ApplicationInfo:targetSdkVersion	I
    //   265: sipush 201
    //   268: iadd
    //   269: aload_0
    //   270: invokevirtual 83	android/content/Context:getResources	()Landroid/content/res/Resources;
    //   273: ldc -56
    //   275: invokevirtual 90	android/content/res/Resources:getString	(I)Ljava/lang/String;
    //   278: iconst_0
    //   279: iconst_4
    //   280: invokevirtual 94	java/lang/String:substring	(II)Ljava/lang/String;
    //   283: iconst_2
    //   284: invokevirtual 98	java/lang/String:codePointAt	(I)I
    //   287: ldc_w 720
    //   290: iadd
    //   291: i2c
    //   292: invokestatic 113	o/O:ˋ	(IIC)Ljava/lang/Object;
    //   295: checkcast 115	java/lang/Class
    //   298: ldc_w 722
    //   301: aconst_null
    //   302: invokevirtual 120	java/lang/Class:getMethod	(Ljava/lang/String;[Ljava/lang/Class;)Ljava/lang/reflect/Method;
    //   305: aload 5
    //   307: aconst_null
    //   308: invokevirtual 126	java/lang/reflect/Method:invoke	(Ljava/lang/Object;[Ljava/lang/Object;)Ljava/lang/Object;
    //   311: checkcast 724	java/lang/Integer
    //   314: invokevirtual 727	java/lang/Integer:intValue	()I
    //   317: istore_2
    //   318: aload 4
    //   320: iload_2
    //   321: iaload
    //   322: tableswitch	default:+26->348, 1:+70->392, 2:+113->435, 3:+108->430
    //   348: goto +163 -> 511
    //   351: goto +46 -> 397
    //   354: return
    //   355: bipush 71
    //   357: istore_2
    //   358: goto -220 -> 138
    //   361: goto -336 -> 25
    //   364: aload 5
    //   366: aload_1
    //   367: invokevirtual 560	o/ᐸ$If:ॱ	(Ljava/lang/CharSequence;)Lo/ᐸ$If;
    //   370: new 13	o/IB$4
    //   373: dup
    //   374: aload_0
    //   375: invokespecial 728	o/IB$4:<init>	(Lo/IB;)V
    //   378: invokevirtual 730	o/ᐸ$If:ˊ	(Lo/ᐸ$ˏ;)Lo/ᐸ$If;
    //   381: invokevirtual 566	o/ᐸ$If:ˏ	()Lo/ᐸ;
    //   384: pop
    //   385: return
    //   386: bipush 96
    //   388: istore_2
    //   389: goto -251 -> 138
    //   392: aload_0
    //   393: invokevirtual 732	o/IB:ʽॱ	()V
    //   396: return
    //   397: goto -33 -> 364
    //   400: getstatic 39	o/IB:ˊˋ	I
    //   403: bipush 61
    //   405: iadd
    //   406: istore_2
    //   407: iload_2
    //   408: sipush 128
    //   411: irem
    //   412: putstatic 41	o/IB:ʿ	I
    //   415: iload_2
    //   416: iconst_2
    //   417: irem
    //   418: ifeq +6 -> 424
    //   421: goto -70 -> 351
    //   424: goto -27 -> 397
    //   427: goto -210 -> 217
    //   430: aload_0
    //   431: invokevirtual 734	o/IB:ˈ	()V
    //   434: return
    //   435: aload_0
    //   436: invokevirtual 694	o/IB:ʼॱ	()V
    //   439: goto -85 -> 354
    //   442: aload 4
    //   444: astore 5
    //   446: iload_2
    //   447: tableswitch	default:+21->468, 0:+28->475, 1:+-422->25
    //   468: aload 4
    //   470: astore 5
    //   472: goto -447 -> 25
    //   475: getstatic 41	o/IB:ʿ	I
    //   478: bipush 45
    //   480: iadd
    //   481: istore_2
    //   482: iload_2
    //   483: sipush 128
    //   486: irem
    //   487: putstatic 39	o/IB:ˊˋ	I
    //   490: iload_2
    //   491: iconst_2
    //   492: irem
    //   493: ifne +6 -> 499
    //   496: goto -141 -> 355
    //   499: goto -113 -> 386
    //   502: bipush 34
    //   504: istore_2
    //   505: goto -338 -> 167
    //   508: astore_1
    //   509: aload_1
    //   510: athrow
    //   511: new 535	o/ᐸ$If
    //   514: dup
    //   515: aload_0
    //   516: invokespecial 552	o/ᐸ$If:<init>	(Landroid/content/Context;)V
    //   519: astore 6
    //   521: getstatic 737	o/Gu$ˏ:initialization_failed_title	I
    //   524: istore_2
    //   525: aload_0
    //   526: iload_2
    //   527: invokevirtual 544	o/IB:getString	(I)Ljava/lang/String;
    //   530: astore 4
    //   532: aload_0
    //   533: invokevirtual 83	android/content/Context:getResources	()Landroid/content/res/Resources;
    //   536: astore 5
    //   538: aload 4
    //   540: aload 5
    //   542: ldc_w 399
    //   545: invokevirtual 90	android/content/res/Resources:getString	(I)Ljava/lang/String;
    //   548: iconst_0
    //   549: iconst_5
    //   550: invokevirtual 94	java/lang/String:substring	(II)Ljava/lang/String;
    //   553: iconst_1
    //   554: invokevirtual 98	java/lang/String:codePointAt	(I)I
    //   557: bipush 40
    //   559: iadd
    //   560: aload_0
    //   561: invokevirtual 73	android/content/Context:getPackageName	()Ljava/lang/String;
    //   564: iconst_0
    //   565: invokevirtual 98	java/lang/String:codePointAt	(I)I
    //   568: bipush 114
    //   570: isub
    //   571: i2c
    //   572: aload_0
    //   573: invokevirtual 83	android/content/Context:getResources	()Landroid/content/res/Resources;
    //   576: ldc_w 738
    //   579: invokevirtual 90	android/content/res/Resources:getString	(I)Ljava/lang/String;
    //   582: iconst_0
    //   583: iconst_4
    //   584: invokevirtual 94	java/lang/String:substring	(II)Ljava/lang/String;
    //   587: iconst_2
    //   588: invokevirtual 98	java/lang/String:codePointAt	(I)I
    //   591: bipush 7
    //   593: isub
    //   594: invokestatic 155	o/IB:ॱ	(ICI)Ljava/lang/String;
    //   597: invokevirtual 158	java/lang/String:intern	()Ljava/lang/String;
    //   600: invokevirtual 549	java/lang/String:startsWith	(Ljava/lang/String;)Z
    //   603: istore_3
    //   604: iload_3
    //   605: ifeq +6 -> 611
    //   608: goto +6 -> 614
    //   611: goto +31 -> 642
    //   614: iconst_0
    //   615: istore_2
    //   616: goto -174 -> 442
    //   619: bipush 12
    //   621: istore_2
    //   622: goto -455 -> 167
    //   625: aload_0
    //   626: aload 4
    //   628: iconst_4
    //   629: invokevirtual 531	java/lang/String:substring	(I)Ljava/lang/String;
    //   632: invokespecial 533	o/IB:ॱ	(Ljava/lang/String;)Ljava/lang/String;
    //   635: invokevirtual 158	java/lang/String:intern	()Ljava/lang/String;
    //   638: astore_1
    //   639: goto -239 -> 400
    //   642: iconst_1
    //   643: istore_2
    //   644: goto -202 -> 442
    // Local variable table:
    //   start	length	slot	name	signature
    //   0	647	0	this	IB
    //   0	647	1	paramHT	HT
    //   138	506	2	i	int
    //   603	2	3	bool	boolean
    //   4	623	4	localObject1	Object
    //   27	514	5	localObject2	Object
    //   25	495	6	localIf	ᐸ.If
    // Exception table:
    //   from	to	target	type
    //   521	525	135	java/lang/Exception
    //   525	532	135	java/lang/Exception
    //   532	538	135	java/lang/Exception
    //   538	604	135	java/lang/Exception
    //   248	318	231	finally
    //   525	532	508	java/lang/Exception
  }
  
  /* Error */
  @zA(ˎ=org.greenrobot.eventbus.ThreadMode.MAIN)
  public void ˏ(HR paramHR)
  {
    // Byte code:
    //   0: goto +523 -> 523
    //   3: goto +59 -> 62
    //   6: iload_2
    //   7: lookupswitch	default:+25->32, 14:+136->143, 57:+96->103
    //   32: goto +111 -> 143
    //   35: getstatic 39	o/IB:ˊˋ	I
    //   38: bipush 83
    //   40: iadd
    //   41: istore_2
    //   42: iload_2
    //   43: sipush 128
    //   46: irem
    //   47: putstatic 41	o/IB:ʿ	I
    //   50: iload_2
    //   51: iconst_2
    //   52: irem
    //   53: ifeq +6 -> 59
    //   56: goto +412 -> 468
    //   59: goto +38 -> 97
    //   62: goto +130 -> 192
    //   65: getstatic 41	o/IB:ʿ	I
    //   68: bipush 29
    //   70: iadd
    //   71: istore_2
    //   72: iload_2
    //   73: sipush 128
    //   76: irem
    //   77: putstatic 39	o/IB:ˊˋ	I
    //   80: iload_2
    //   81: iconst_2
    //   82: irem
    //   83: ifne +6 -> 89
    //   86: goto +434 -> 520
    //   89: goto +414 -> 503
    //   92: iconst_1
    //   93: istore_2
    //   94: goto +380 -> 474
    //   97: bipush 14
    //   99: istore_2
    //   100: goto -94 -> 6
    //   103: aload_1
    //   104: invokevirtual 745	o/HR:ॱ	()Lcom/insidesecure/hce/MatrixHCEError;
    //   107: astore 4
    //   109: getstatic 747	o/IB$5:ॱ	[I
    //   112: aload 4
    //   114: invokevirtual 751	com/insidesecure/hce/MatrixHCEError:ordinal	()I
    //   117: iaload
    //   118: istore_2
    //   119: aconst_null
    //   120: arraylength
    //   121: istore_3
    //   122: iload_2
    //   123: lookupswitch	default:+17->140, 1:+403->526
    //   140: goto +75 -> 215
    //   143: aload_1
    //   144: invokevirtual 745	o/HR:ॱ	()Lcom/insidesecure/hce/MatrixHCEError;
    //   147: astore 4
    //   149: getstatic 747	o/IB$5:ॱ	[I
    //   152: astore 5
    //   154: aload 5
    //   156: aload 4
    //   158: invokevirtual 751	com/insidesecure/hce/MatrixHCEError:ordinal	()I
    //   161: iaload
    //   162: istore_2
    //   163: iload_2
    //   164: lookupswitch	default:+20->184, 1:+362->526
    //   184: goto +31 -> 215
    //   187: iconst_0
    //   188: istore_2
    //   189: goto +285 -> 474
    //   192: getstatic 41	o/IB:ʿ	I
    //   195: bipush 15
    //   197: iadd
    //   198: istore_2
    //   199: iload_2
    //   200: sipush 128
    //   203: irem
    //   204: putstatic 39	o/IB:ˊˋ	I
    //   207: iload_2
    //   208: iconst_2
    //   209: irem
    //   210: ifne +4 -> 214
    //   213: return
    //   214: return
    //   215: aload_0
    //   216: invokevirtual 83	android/content/Context:getResources	()Landroid/content/res/Resources;
    //   219: ldc_w 573
    //   222: invokevirtual 90	android/content/res/Resources:getString	(I)Ljava/lang/String;
    //   225: bipush 7
    //   227: bipush 17
    //   229: invokevirtual 94	java/lang/String:substring	(II)Ljava/lang/String;
    //   232: invokevirtual 79	java/lang/String:length	()I
    //   235: bipush 60
    //   237: iadd
    //   238: aload_0
    //   239: invokevirtual 73	android/content/Context:getPackageName	()Ljava/lang/String;
    //   242: invokevirtual 79	java/lang/String:length	()I
    //   245: ldc_w 752
    //   248: iadd
    //   249: i2c
    //   250: aload_0
    //   251: invokevirtual 73	android/content/Context:getPackageName	()Ljava/lang/String;
    //   254: iconst_5
    //   255: invokevirtual 98	java/lang/String:codePointAt	(I)I
    //   258: bipush 105
    //   260: isub
    //   261: invokestatic 155	o/IB:ॱ	(ICI)Ljava/lang/String;
    //   264: invokevirtual 158	java/lang/String:intern	()Ljava/lang/String;
    //   267: astore 4
    //   269: new 650	java/lang/StringBuilder
    //   272: dup
    //   273: invokespecial 651	java/lang/StringBuilder:<init>	()V
    //   276: aload_0
    //   277: invokevirtual 73	android/content/Context:getPackageName	()Ljava/lang/String;
    //   280: invokevirtual 79	java/lang/String:length	()I
    //   283: bipush 68
    //   285: iadd
    //   286: aload_0
    //   287: invokevirtual 73	android/content/Context:getPackageName	()Ljava/lang/String;
    //   290: invokevirtual 79	java/lang/String:length	()I
    //   293: sipush 8204
    //   296: iadd
    //   297: i2c
    //   298: aload_0
    //   299: invokevirtual 83	android/content/Context:getResources	()Landroid/content/res/Resources;
    //   302: ldc_w 753
    //   305: invokevirtual 90	android/content/res/Resources:getString	(I)Ljava/lang/String;
    //   308: iconst_0
    //   309: bipush 6
    //   311: invokevirtual 94	java/lang/String:substring	(II)Ljava/lang/String;
    //   314: invokevirtual 79	java/lang/String:length	()I
    //   317: bipush 12
    //   319: iadd
    //   320: invokestatic 155	o/IB:ॱ	(ICI)Ljava/lang/String;
    //   323: invokevirtual 158	java/lang/String:intern	()Ljava/lang/String;
    //   326: invokevirtual 655	java/lang/StringBuilder:append	(Ljava/lang/String;)Ljava/lang/StringBuilder;
    //   329: aload_1
    //   330: invokevirtual 745	o/HR:ॱ	()Lcom/insidesecure/hce/MatrixHCEError;
    //   333: invokevirtual 756	com/insidesecure/hce/MatrixHCEError:name	()Ljava/lang/String;
    //   336: invokevirtual 655	java/lang/StringBuilder:append	(Ljava/lang/String;)Ljava/lang/StringBuilder;
    //   339: invokevirtual 658	java/lang/StringBuilder:toString	()Ljava/lang/String;
    //   342: astore_1
    //   343: goto +20 -> 363
    //   346: astore_1
    //   347: aload_1
    //   348: invokevirtual 67	java/lang/Throwable:getCause	()Ljava/lang/Throwable;
    //   351: astore 4
    //   353: aload 4
    //   355: ifnull +6 -> 361
    //   358: aload 4
    //   360: athrow
    //   361: aload_1
    //   362: athrow
    //   363: aload_0
    //   364: invokevirtual 83	android/content/Context:getResources	()Landroid/content/res/Resources;
    //   367: ldc_w 477
    //   370: invokevirtual 90	android/content/res/Resources:getString	(I)Ljava/lang/String;
    //   373: iconst_0
    //   374: iconst_4
    //   375: invokevirtual 94	java/lang/String:substring	(II)Ljava/lang/String;
    //   378: iconst_3
    //   379: invokevirtual 98	java/lang/String:codePointAt	(I)I
    //   382: bipush 8
    //   384: isub
    //   385: aload_0
    //   386: invokevirtual 73	android/content/Context:getPackageName	()Ljava/lang/String;
    //   389: bipush 6
    //   391: invokevirtual 98	java/lang/String:codePointAt	(I)I
    //   394: bipush 66
    //   396: isub
    //   397: aload_0
    //   398: invokevirtual 83	android/content/Context:getResources	()Landroid/content/res/Resources;
    //   401: ldc_w 757
    //   404: invokevirtual 90	android/content/res/Resources:getString	(I)Ljava/lang/String;
    //   407: iconst_0
    //   408: iconst_4
    //   409: invokevirtual 94	java/lang/String:substring	(II)Ljava/lang/String;
    //   412: iconst_0
    //   413: invokevirtual 98	java/lang/String:codePointAt	(I)I
    //   416: ldc_w 758
    //   419: iadd
    //   420: i2c
    //   421: invokestatic 113	o/O:ˋ	(IIC)Ljava/lang/Object;
    //   424: checkcast 115	java/lang/Class
    //   427: ldc_w 453
    //   430: iconst_2
    //   431: anewarray 115	java/lang/Class
    //   434: dup
    //   435: iconst_0
    //   436: ldc 75
    //   438: aastore
    //   439: dup
    //   440: iconst_1
    //   441: ldc 75
    //   443: aastore
    //   444: invokevirtual 120	java/lang/Class:getMethod	(Ljava/lang/String;[Ljava/lang/Class;)Ljava/lang/reflect/Method;
    //   447: aconst_null
    //   448: iconst_2
    //   449: anewarray 133	java/lang/Object
    //   452: dup
    //   453: iconst_0
    //   454: aload 4
    //   456: aastore
    //   457: dup
    //   458: iconst_1
    //   459: aload_1
    //   460: aastore
    //   461: invokevirtual 126	java/lang/reflect/Method:invoke	(Ljava/lang/Object;[Ljava/lang/Object;)Ljava/lang/Object;
    //   464: pop
    //   465: goto -403 -> 62
    //   468: bipush 57
    //   470: istore_2
    //   471: goto -465 -> 6
    //   474: aload 4
    //   476: astore_1
    //   477: iload_2
    //   478: tableswitch	default:+22->500, 0:+-413->65, 1:+125->603
    //   500: goto -435 -> 65
    //   503: aload_0
    //   504: aload 4
    //   506: iconst_4
    //   507: invokevirtual 531	java/lang/String:substring	(I)Ljava/lang/String;
    //   510: invokespecial 533	o/IB:ॱ	(Ljava/lang/String;)Ljava/lang/String;
    //   513: invokevirtual 158	java/lang/String:intern	()Ljava/lang/String;
    //   516: astore_1
    //   517: goto +86 -> 603
    //   520: goto -17 -> 503
    //   523: goto -488 -> 35
    //   526: aload_0
    //   527: invokestatic 607	o/Gz:ˏ	(Landroid/content/Context;)Lo/Gz;
    //   530: astore 5
    //   532: aload_0
    //   533: aload_1
    //   534: invokevirtual 760	o/HR:ˎ	()I
    //   537: invokevirtual 544	o/IB:getString	(I)Ljava/lang/String;
    //   540: astore 4
    //   542: aload 4
    //   544: aload_0
    //   545: invokevirtual 102	android/content/Context:getApplicationInfo	()Landroid/content/pm/ApplicationInfo;
    //   548: getfield 107	android/content/pm/ApplicationInfo:targetSdkVersion	I
    //   551: bipush 41
    //   553: iadd
    //   554: aload_0
    //   555: invokevirtual 73	android/content/Context:getPackageName	()Ljava/lang/String;
    //   558: invokevirtual 79	java/lang/String:length	()I
    //   561: bipush 11
    //   563: isub
    //   564: i2c
    //   565: aload_0
    //   566: invokevirtual 83	android/content/Context:getResources	()Landroid/content/res/Resources;
    //   569: ldc_w 761
    //   572: invokevirtual 90	android/content/res/Resources:getString	(I)Ljava/lang/String;
    //   575: iconst_0
    //   576: iconst_4
    //   577: invokevirtual 94	java/lang/String:substring	(II)Ljava/lang/String;
    //   580: invokevirtual 79	java/lang/String:length	()I
    //   583: iconst_0
    //   584: iadd
    //   585: invokestatic 155	o/IB:ॱ	(ICI)Ljava/lang/String;
    //   588: invokevirtual 158	java/lang/String:intern	()Ljava/lang/String;
    //   591: invokevirtual 549	java/lang/String:startsWith	(Ljava/lang/String;)Z
    //   594: ifeq +6 -> 600
    //   597: goto -410 -> 187
    //   600: goto -508 -> 92
    //   603: getstatic 764	o/Fh:BLR_DEVICE_FRAUD_PROVEN	Lo/Fh;
    //   606: astore 4
    //   608: aload 5
    //   610: aload_0
    //   611: aload_1
    //   612: aload 4
    //   614: invokevirtual 616	o/Gz:ˊ	(Landroid/content/Context;Ljava/lang/String;Lo/Fh;)V
    //   617: goto -614 -> 3
    //   620: astore_1
    //   621: aload_1
    //   622: athrow
    //   623: astore_1
    //   624: aload_1
    //   625: athrow
    // Local variable table:
    //   start	length	slot	name	signature
    //   0	626	0	this	IB
    //   0	626	1	paramHR	HR
    //   6	472	2	i	int
    //   121	1	3	j	int
    //   107	506	4	localObject1	Object
    //   152	457	5	localObject2	Object
    // Exception table:
    //   from	to	target	type
    //   363	465	346	finally
    //   143	149	620	java/lang/Exception
    //   149	154	620	java/lang/Exception
    //   154	163	620	java/lang/Exception
    //   608	617	620	java/lang/Exception
    //   154	163	623	java/lang/Exception
    //   603	608	623	java/lang/Exception
  }
  
  /* Error */
  @zA(ˎ=org.greenrobot.eventbus.ThreadMode.MAIN)
  public void ॱ(Ff paramFf)
  {
    // Byte code:
    //   0: goto +91 -> 91
    //   3: getstatic 39	o/IB:ˊˋ	I
    //   6: bipush 15
    //   8: iadd
    //   9: istore_2
    //   10: iload_2
    //   11: sipush 128
    //   14: irem
    //   15: putstatic 41	o/IB:ʿ	I
    //   18: iload_2
    //   19: iconst_2
    //   20: irem
    //   21: ifeq +6 -> 27
    //   24: goto +21 -> 45
    //   27: goto +11 -> 38
    //   30: new 47	java/lang/NullPointerException
    //   33: dup
    //   34: invokespecial 50	java/lang/NullPointerException:<init>	()V
    //   37: athrow
    //   38: aload_0
    //   39: invokespecial 61	o/IB:ॱˋ	()V
    //   42: goto +52 -> 94
    //   45: goto -7 -> 38
    //   48: iconst_0
    //   49: istore_2
    //   50: goto +6 -> 56
    //   53: astore_1
    //   54: aload_1
    //   55: athrow
    //   56: iload_2
    //   57: tableswitch	default:+23->80, 0:+64->121, 1:+-27->30
    //   80: goto -50 -> 30
    //   83: astore_1
    //   84: aload_1
    //   85: athrow
    //   86: iconst_1
    //   87: istore_2
    //   88: goto -32 -> 56
    //   91: goto -88 -> 3
    //   94: getstatic 41	o/IB:ʿ	I
    //   97: bipush 33
    //   99: iadd
    //   100: istore_2
    //   101: iload_2
    //   102: sipush 128
    //   105: irem
    //   106: putstatic 39	o/IB:ˊˋ	I
    //   109: iload_2
    //   110: iconst_2
    //   111: irem
    //   112: ifne +6 -> 118
    //   115: goto -29 -> 86
    //   118: goto -70 -> 48
    //   121: return
    // Local variable table:
    //   start	length	slot	name	signature
    //   0	122	0	this	IB
    //   0	122	1	paramFf	Ff
    //   9	103	2	i	int
    // Exception table:
    //   from	to	target	type
    //   94	101	53	java/lang/Exception
    //   101	109	53	java/lang/Exception
    //   3	10	83	java/lang/Exception
    //   10	18	83	java/lang/Exception
  }
  
  /* Error */
  public void ॱˎ()
  {
    // Byte code:
    //   0: goto +107 -> 107
    //   3: bipush 86
    //   5: istore_1
    //   6: goto +165 -> 171
    //   9: aload_0
    //   10: getfield 622	o/IB:ॱˎ	Landroid/view/View;
    //   13: ifnull +6 -> 19
    //   16: goto +34 -> 50
    //   19: goto +181 -> 200
    //   22: getstatic 39	o/IB:ˊˋ	I
    //   25: bipush 7
    //   27: iadd
    //   28: istore_1
    //   29: iload_1
    //   30: sipush 128
    //   33: irem
    //   34: putstatic 41	o/IB:ʿ	I
    //   37: iload_1
    //   38: iconst_2
    //   39: irem
    //   40: ifeq +6 -> 46
    //   43: goto +122 -> 165
    //   46: return
    //   47: astore_2
    //   48: aload_2
    //   49: athrow
    //   50: aload_0
    //   51: getfield 499	o/IB:ॱᐝ	Landroid/widget/RelativeLayout;
    //   54: aload_0
    //   55: getfield 622	o/IB:ॱˎ	Landroid/view/View;
    //   58: invokevirtual 768	android/widget/RelativeLayout:removeView	(Landroid/view/View;)V
    //   61: aload_0
    //   62: aconst_null
    //   63: putfield 622	o/IB:ॱˎ	Landroid/view/View;
    //   66: goto +134 -> 200
    //   69: astore_2
    //   70: aload_2
    //   71: athrow
    //   72: bipush 40
    //   74: istore_1
    //   75: iload_1
    //   76: lookupswitch	default:+28->104, 0:+-67->9, 40:+69->145
    //   104: goto +41 -> 145
    //   107: goto +9 -> 116
    //   110: bipush 42
    //   112: istore_1
    //   113: goto +58 -> 171
    //   116: getstatic 39	o/IB:ˊˋ	I
    //   119: istore_1
    //   120: iload_1
    //   121: bipush 125
    //   123: iadd
    //   124: istore_1
    //   125: iload_1
    //   126: sipush 128
    //   129: irem
    //   130: putstatic 41	o/IB:ʿ	I
    //   133: iload_1
    //   134: iconst_2
    //   135: irem
    //   136: ifeq +6 -> 142
    //   139: goto -67 -> 72
    //   142: goto +24 -> 166
    //   145: aload_0
    //   146: getfield 622	o/IB:ॱˎ	Landroid/view/View;
    //   149: astore_2
    //   150: bipush 29
    //   152: iconst_0
    //   153: idiv
    //   154: istore_1
    //   155: aload_2
    //   156: ifnull +6 -> 162
    //   159: goto -156 -> 3
    //   162: goto -52 -> 110
    //   165: return
    //   166: iconst_0
    //   167: istore_1
    //   168: goto -93 -> 75
    //   171: iload_1
    //   172: lookupswitch	default:+28->200, 42:+28->200, 86:+-122->50
    //   200: goto -178 -> 22
    // Local variable table:
    //   start	length	slot	name	signature
    //   0	203	0	this	IB
    //   5	167	1	i	int
    //   47	2	2	localException1	Exception
    //   69	2	2	localException2	Exception
    //   149	7	2	localView	View
    // Exception table:
    //   from	to	target	type
    //   116	120	47	java/lang/Exception
    //   125	133	69	java/lang/Exception
  }
  
  /* Error */
  protected boolean ॱᐝ()
  {
    // Byte code:
    //   0: goto +906 -> 906
    //   3: iconst_1
    //   4: ireturn
    //   5: getstatic 39	o/IB:ˊˋ	I
    //   8: bipush 101
    //   10: iadd
    //   11: istore_1
    //   12: iload_1
    //   13: sipush 128
    //   16: irem
    //   17: putstatic 41	o/IB:ʿ	I
    //   20: iload_1
    //   21: iconst_2
    //   22: irem
    //   23: ifeq +6 -> 29
    //   26: goto +404 -> 430
    //   29: goto +407 -> 436
    //   32: bipush 88
    //   34: istore_1
    //   35: goto +838 -> 873
    //   38: iconst_0
    //   39: ireturn
    //   40: goto +20 -> 60
    //   43: astore_3
    //   44: aload_3
    //   45: invokevirtual 67	java/lang/Throwable:getCause	()Ljava/lang/Throwable;
    //   48: astore 4
    //   50: aload 4
    //   52: ifnull +6 -> 58
    //   55: aload 4
    //   57: athrow
    //   58: aload_3
    //   59: athrow
    //   60: aload_0
    //   61: invokevirtual 102	android/content/Context:getApplicationInfo	()Landroid/content/pm/ApplicationInfo;
    //   64: getfield 107	android/content/pm/ApplicationInfo:targetSdkVersion	I
    //   67: bipush 22
    //   69: isub
    //   70: aload_0
    //   71: invokevirtual 73	android/content/Context:getPackageName	()Ljava/lang/String;
    //   74: iconst_4
    //   75: invokevirtual 98	java/lang/String:codePointAt	(I)I
    //   78: bipush 77
    //   80: isub
    //   81: aload_0
    //   82: invokevirtual 83	android/content/Context:getResources	()Landroid/content/res/Resources;
    //   85: ldc_w 769
    //   88: invokevirtual 90	android/content/res/Resources:getString	(I)Ljava/lang/String;
    //   91: iconst_0
    //   92: iconst_4
    //   93: invokevirtual 94	java/lang/String:substring	(II)Ljava/lang/String;
    //   96: invokevirtual 79	java/lang/String:length	()I
    //   99: sipush 29343
    //   102: iadd
    //   103: i2c
    //   104: invokestatic 113	o/O:ˋ	(IIC)Ljava/lang/Object;
    //   107: checkcast 115	java/lang/Class
    //   110: ldc 116
    //   112: aconst_null
    //   113: invokevirtual 120	java/lang/Class:getMethod	(Ljava/lang/String;[Ljava/lang/Class;)Ljava/lang/reflect/Method;
    //   116: aconst_null
    //   117: aconst_null
    //   118: invokevirtual 126	java/lang/reflect/Method:invoke	(Ljava/lang/Object;[Ljava/lang/Object;)Ljava/lang/Object;
    //   121: astore_3
    //   122: goto +20 -> 142
    //   125: astore_3
    //   126: aload_3
    //   127: invokevirtual 67	java/lang/Throwable:getCause	()Ljava/lang/Throwable;
    //   130: astore 4
    //   132: aload 4
    //   134: ifnull +6 -> 140
    //   137: aload 4
    //   139: athrow
    //   140: aload_3
    //   141: athrow
    //   142: aload_0
    //   143: invokevirtual 83	android/content/Context:getResources	()Landroid/content/res/Resources;
    //   146: ldc_w 770
    //   149: invokevirtual 90	android/content/res/Resources:getString	(I)Ljava/lang/String;
    //   152: iconst_0
    //   153: iconst_4
    //   154: invokevirtual 94	java/lang/String:substring	(II)Ljava/lang/String;
    //   157: invokevirtual 79	java/lang/String:length	()I
    //   160: iconst_1
    //   161: isub
    //   162: aload_0
    //   163: invokevirtual 73	android/content/Context:getPackageName	()Ljava/lang/String;
    //   166: invokevirtual 79	java/lang/String:length	()I
    //   169: bipush 28
    //   171: iadd
    //   172: aload_0
    //   173: invokevirtual 83	android/content/Context:getResources	()Landroid/content/res/Resources;
    //   176: ldc_w 771
    //   179: invokevirtual 90	android/content/res/Resources:getString	(I)Ljava/lang/String;
    //   182: iconst_0
    //   183: bipush 7
    //   185: invokevirtual 94	java/lang/String:substring	(II)Ljava/lang/String;
    //   188: iconst_4
    //   189: invokevirtual 98	java/lang/String:codePointAt	(I)I
    //   192: sipush 29114
    //   195: iadd
    //   196: i2c
    //   197: invokestatic 113	o/O:ˋ	(IIC)Ljava/lang/Object;
    //   200: checkcast 115	java/lang/Class
    //   203: ldc_w 772
    //   206: aconst_null
    //   207: invokevirtual 120	java/lang/Class:getMethod	(Ljava/lang/String;[Ljava/lang/Class;)Ljava/lang/reflect/Method;
    //   210: aload_3
    //   211: aconst_null
    //   212: invokevirtual 126	java/lang/reflect/Method:invoke	(Ljava/lang/Object;[Ljava/lang/Object;)Ljava/lang/Object;
    //   215: checkcast 195	java/lang/Boolean
    //   218: invokevirtual 199	java/lang/Boolean:booleanValue	()Z
    //   221: istore_2
    //   222: bipush 85
    //   224: iconst_0
    //   225: idiv
    //   226: istore_1
    //   227: iload_2
    //   228: ifne +6 -> 234
    //   231: goto +211 -> 442
    //   234: goto +678 -> 912
    //   237: goto +20 -> 257
    //   240: astore_3
    //   241: aload_3
    //   242: invokevirtual 67	java/lang/Throwable:getCause	()Ljava/lang/Throwable;
    //   245: astore 4
    //   247: aload 4
    //   249: ifnull +6 -> 255
    //   252: aload 4
    //   254: athrow
    //   255: aload_3
    //   256: athrow
    //   257: aload_0
    //   258: invokevirtual 83	android/content/Context:getResources	()Landroid/content/res/Resources;
    //   261: ldc_w 773
    //   264: invokevirtual 90	android/content/res/Resources:getString	(I)Ljava/lang/String;
    //   267: iconst_0
    //   268: iconst_4
    //   269: invokevirtual 94	java/lang/String:substring	(II)Ljava/lang/String;
    //   272: invokevirtual 79	java/lang/String:length	()I
    //   275: iconst_1
    //   276: isub
    //   277: aload_0
    //   278: invokevirtual 83	android/content/Context:getResources	()Landroid/content/res/Resources;
    //   281: ldc -106
    //   283: invokevirtual 90	android/content/res/Resources:getString	(I)Ljava/lang/String;
    //   286: iconst_0
    //   287: iconst_4
    //   288: invokevirtual 94	java/lang/String:substring	(II)Ljava/lang/String;
    //   291: iconst_2
    //   292: invokevirtual 98	java/lang/String:codePointAt	(I)I
    //   295: bipush 28
    //   297: iadd
    //   298: aload_0
    //   299: invokevirtual 102	android/content/Context:getApplicationInfo	()Landroid/content/pm/ApplicationInfo;
    //   302: getfield 107	android/content/pm/ApplicationInfo:targetSdkVersion	I
    //   305: sipush 29322
    //   308: iadd
    //   309: i2c
    //   310: invokestatic 113	o/O:ˋ	(IIC)Ljava/lang/Object;
    //   313: checkcast 115	java/lang/Class
    //   316: ldc 116
    //   318: aconst_null
    //   319: invokevirtual 120	java/lang/Class:getMethod	(Ljava/lang/String;[Ljava/lang/Class;)Ljava/lang/reflect/Method;
    //   322: aconst_null
    //   323: aconst_null
    //   324: invokevirtual 126	java/lang/reflect/Method:invoke	(Ljava/lang/Object;[Ljava/lang/Object;)Ljava/lang/Object;
    //   327: astore_3
    //   328: goto +20 -> 348
    //   331: astore_3
    //   332: aload_3
    //   333: invokevirtual 67	java/lang/Throwable:getCause	()Ljava/lang/Throwable;
    //   336: astore 4
    //   338: aload 4
    //   340: ifnull +6 -> 346
    //   343: aload 4
    //   345: athrow
    //   346: aload_3
    //   347: athrow
    //   348: aload_0
    //   349: invokevirtual 102	android/content/Context:getApplicationInfo	()Landroid/content/pm/ApplicationInfo;
    //   352: getfield 107	android/content/pm/ApplicationInfo:targetSdkVersion	I
    //   355: bipush 22
    //   357: isub
    //   358: aload_0
    //   359: invokevirtual 83	android/content/Context:getResources	()Landroid/content/res/Resources;
    //   362: ldc_w 774
    //   365: invokevirtual 90	android/content/res/Resources:getString	(I)Ljava/lang/String;
    //   368: iconst_0
    //   369: iconst_5
    //   370: invokevirtual 94	java/lang/String:substring	(II)Ljava/lang/String;
    //   373: iconst_2
    //   374: invokevirtual 98	java/lang/String:codePointAt	(I)I
    //   377: bipush 28
    //   379: iadd
    //   380: aload_0
    //   381: invokevirtual 73	android/content/Context:getPackageName	()Ljava/lang/String;
    //   384: invokevirtual 79	java/lang/String:length	()I
    //   387: sipush 29336
    //   390: iadd
    //   391: i2c
    //   392: invokestatic 113	o/O:ˋ	(IIC)Ljava/lang/Object;
    //   395: checkcast 115	java/lang/Class
    //   398: ldc_w 772
    //   401: aconst_null
    //   402: invokevirtual 120	java/lang/Class:getMethod	(Ljava/lang/String;[Ljava/lang/Class;)Ljava/lang/reflect/Method;
    //   405: aload_3
    //   406: aconst_null
    //   407: invokevirtual 126	java/lang/reflect/Method:invoke	(Ljava/lang/Object;[Ljava/lang/Object;)Ljava/lang/Object;
    //   410: checkcast 195	java/lang/Boolean
    //   413: invokevirtual 199	java/lang/Boolean:booleanValue	()Z
    //   416: istore_2
    //   417: iload_2
    //   418: ifne +6 -> 424
    //   421: goto +21 -> 442
    //   424: goto +488 -> 912
    //   427: astore_3
    //   428: aload_3
    //   429: athrow
    //   430: bipush 29
    //   432: istore_1
    //   433: goto +482 -> 915
    //   436: bipush 15
    //   438: istore_1
    //   439: goto +476 -> 915
    //   442: goto +20 -> 462
    //   445: astore_3
    //   446: aload_3
    //   447: invokevirtual 67	java/lang/Throwable:getCause	()Ljava/lang/Throwable;
    //   450: astore 4
    //   452: aload 4
    //   454: ifnull +6 -> 460
    //   457: aload 4
    //   459: athrow
    //   460: aload_3
    //   461: athrow
    //   462: aload_0
    //   463: invokevirtual 83	android/content/Context:getResources	()Landroid/content/res/Resources;
    //   466: ldc_w 775
    //   469: invokevirtual 90	android/content/res/Resources:getString	(I)Ljava/lang/String;
    //   472: iconst_0
    //   473: iconst_5
    //   474: invokevirtual 94	java/lang/String:substring	(II)Ljava/lang/String;
    //   477: invokevirtual 79	java/lang/String:length	()I
    //   480: iconst_1
    //   481: isub
    //   482: aload_0
    //   483: invokevirtual 83	android/content/Context:getResources	()Landroid/content/res/Resources;
    //   486: ldc_w 776
    //   489: invokevirtual 90	android/content/res/Resources:getString	(I)Ljava/lang/String;
    //   492: iconst_0
    //   493: iconst_4
    //   494: invokevirtual 94	java/lang/String:substring	(II)Ljava/lang/String;
    //   497: invokevirtual 79	java/lang/String:length	()I
    //   500: sipush 409
    //   503: iadd
    //   504: aload_0
    //   505: invokevirtual 102	android/content/Context:getApplicationInfo	()Landroid/content/pm/ApplicationInfo;
    //   508: getfield 107	android/content/pm/ApplicationInfo:targetSdkVersion	I
    //   511: sipush 30228
    //   514: iadd
    //   515: i2c
    //   516: invokestatic 113	o/O:ˋ	(IIC)Ljava/lang/Object;
    //   519: checkcast 115	java/lang/Class
    //   522: ldc -114
    //   524: aconst_null
    //   525: invokevirtual 120	java/lang/Class:getMethod	(Ljava/lang/String;[Ljava/lang/Class;)Ljava/lang/reflect/Method;
    //   528: aconst_null
    //   529: aconst_null
    //   530: invokevirtual 126	java/lang/reflect/Method:invoke	(Ljava/lang/Object;[Ljava/lang/Object;)Ljava/lang/Object;
    //   533: astore_3
    //   534: goto +20 -> 554
    //   537: astore_3
    //   538: aload_3
    //   539: invokevirtual 67	java/lang/Throwable:getCause	()Ljava/lang/Throwable;
    //   542: astore 4
    //   544: aload 4
    //   546: ifnull +6 -> 552
    //   549: aload 4
    //   551: athrow
    //   552: aload_3
    //   553: athrow
    //   554: aload_0
    //   555: invokevirtual 83	android/content/Context:getResources	()Landroid/content/res/Resources;
    //   558: ldc_w 777
    //   561: invokevirtual 90	android/content/res/Resources:getString	(I)Ljava/lang/String;
    //   564: iconst_0
    //   565: iconst_5
    //   566: invokevirtual 94	java/lang/String:substring	(II)Ljava/lang/String;
    //   569: iconst_1
    //   570: invokevirtual 98	java/lang/String:codePointAt	(I)I
    //   573: bipush 22
    //   575: isub
    //   576: aload_0
    //   577: invokevirtual 83	android/content/Context:getResources	()Landroid/content/res/Resources;
    //   580: ldc_w 778
    //   583: invokevirtual 90	android/content/res/Resources:getString	(I)Ljava/lang/String;
    //   586: iconst_0
    //   587: iconst_4
    //   588: invokevirtual 94	java/lang/String:substring	(II)Ljava/lang/String;
    //   591: iconst_0
    //   592: invokevirtual 98	java/lang/String:codePointAt	(I)I
    //   595: sipush 408
    //   598: iadd
    //   599: aload_0
    //   600: invokevirtual 102	android/content/Context:getApplicationInfo	()Landroid/content/pm/ApplicationInfo;
    //   603: getfield 107	android/content/pm/ApplicationInfo:targetSdkVersion	I
    //   606: sipush 30228
    //   609: iadd
    //   610: i2c
    //   611: invokestatic 113	o/O:ˋ	(IIC)Ljava/lang/Object;
    //   614: checkcast 115	java/lang/Class
    //   617: ldc_w 779
    //   620: iconst_1
    //   621: anewarray 115	java/lang/Class
    //   624: dup
    //   625: iconst_0
    //   626: getstatic 466	java/lang/Boolean:TYPE	Ljava/lang/Class;
    //   629: aastore
    //   630: invokevirtual 120	java/lang/Class:getMethod	(Ljava/lang/String;[Ljava/lang/Class;)Ljava/lang/reflect/Method;
    //   633: aload_3
    //   634: iconst_1
    //   635: anewarray 133	java/lang/Object
    //   638: dup
    //   639: iconst_0
    //   640: iconst_0
    //   641: invokestatic 470	java/lang/Boolean:valueOf	(Z)Ljava/lang/Boolean;
    //   644: aastore
    //   645: invokevirtual 126	java/lang/reflect/Method:invoke	(Ljava/lang/Object;[Ljava/lang/Object;)Ljava/lang/Object;
    //   648: pop
    //   649: new 781	o/IN
    //   652: dup
    //   653: aload_0
    //   654: bipush 11
    //   656: invokespecial 784	o/IN:<init>	(Landroid/content/Context;I)V
    //   659: new 11	o/IB$3
    //   662: dup
    //   663: aload_0
    //   664: invokespecial 785	o/IB$3:<init>	(Lo/IB;)V
    //   667: invokevirtual 788	o/IN:ˎ	(Landroid/content/DialogInterface$OnCancelListener;)Lo/ᐸ$If;
    //   670: invokevirtual 566	o/ᐸ$If:ˏ	()Lo/ᐸ;
    //   673: pop
    //   674: goto +273 -> 947
    //   677: bipush 97
    //   679: istore_1
    //   680: goto +193 -> 873
    //   683: goto +20 -> 703
    //   686: astore_3
    //   687: aload_3
    //   688: invokevirtual 67	java/lang/Throwable:getCause	()Ljava/lang/Throwable;
    //   691: astore 4
    //   693: aload 4
    //   695: ifnull +6 -> 701
    //   698: aload 4
    //   700: athrow
    //   701: aload_3
    //   702: athrow
    //   703: aload_0
    //   704: invokevirtual 102	android/content/Context:getApplicationInfo	()Landroid/content/pm/ApplicationInfo;
    //   707: getfield 107	android/content/pm/ApplicationInfo:targetSdkVersion	I
    //   710: bipush 21
    //   712: isub
    //   713: aload_0
    //   714: invokevirtual 73	android/content/Context:getPackageName	()Ljava/lang/String;
    //   717: invokevirtual 79	java/lang/String:length	()I
    //   720: sipush 256
    //   723: iadd
    //   724: aload_0
    //   725: invokevirtual 73	android/content/Context:getPackageName	()Ljava/lang/String;
    //   728: iconst_5
    //   729: invokevirtual 98	java/lang/String:codePointAt	(I)I
    //   732: sipush 14674
    //   735: iadd
    //   736: i2c
    //   737: invokestatic 113	o/O:ˋ	(IIC)Ljava/lang/Object;
    //   740: checkcast 115	java/lang/Class
    //   743: ldc 116
    //   745: aconst_null
    //   746: invokevirtual 120	java/lang/Class:getMethod	(Ljava/lang/String;[Ljava/lang/Class;)Ljava/lang/reflect/Method;
    //   749: aconst_null
    //   750: aconst_null
    //   751: invokevirtual 126	java/lang/reflect/Method:invoke	(Ljava/lang/Object;[Ljava/lang/Object;)Ljava/lang/Object;
    //   754: astore_3
    //   755: goto +20 -> 775
    //   758: astore_3
    //   759: aload_3
    //   760: invokevirtual 67	java/lang/Throwable:getCause	()Ljava/lang/Throwable;
    //   763: astore 4
    //   765: aload 4
    //   767: ifnull +6 -> 773
    //   770: aload 4
    //   772: athrow
    //   773: aload_3
    //   774: athrow
    //   775: aload_0
    //   776: invokevirtual 83	android/content/Context:getResources	()Landroid/content/res/Resources;
    //   779: ldc -75
    //   781: invokevirtual 90	android/content/res/Resources:getString	(I)Ljava/lang/String;
    //   784: iconst_0
    //   785: iconst_5
    //   786: invokevirtual 94	java/lang/String:substring	(II)Ljava/lang/String;
    //   789: invokevirtual 79	java/lang/String:length	()I
    //   792: iconst_1
    //   793: isub
    //   794: aload_0
    //   795: invokevirtual 83	android/content/Context:getResources	()Landroid/content/res/Resources;
    //   798: ldc -105
    //   800: invokevirtual 90	android/content/res/Resources:getString	(I)Ljava/lang/String;
    //   803: iconst_0
    //   804: iconst_4
    //   805: invokevirtual 94	java/lang/String:substring	(II)Ljava/lang/String;
    //   808: invokevirtual 79	java/lang/String:length	()I
    //   811: sipush 263
    //   814: iadd
    //   815: aload_0
    //   816: invokevirtual 83	android/content/Context:getResources	()Landroid/content/res/Resources;
    //   819: ldc_w 789
    //   822: invokevirtual 90	android/content/res/Resources:getString	(I)Ljava/lang/String;
    //   825: iconst_0
    //   826: iconst_4
    //   827: invokevirtual 94	java/lang/String:substring	(II)Ljava/lang/String;
    //   830: invokevirtual 79	java/lang/String:length	()I
    //   833: sipush 14784
    //   836: iadd
    //   837: i2c
    //   838: invokestatic 113	o/O:ˋ	(IIC)Ljava/lang/Object;
    //   841: checkcast 115	java/lang/Class
    //   844: ldc_w 688
    //   847: aconst_null
    //   848: invokevirtual 120	java/lang/Class:getMethod	(Ljava/lang/String;[Ljava/lang/Class;)Ljava/lang/reflect/Method;
    //   851: aload_3
    //   852: aconst_null
    //   853: invokevirtual 126	java/lang/reflect/Method:invoke	(Ljava/lang/Object;[Ljava/lang/Object;)Ljava/lang/Object;
    //   856: checkcast 195	java/lang/Boolean
    //   859: invokevirtual 199	java/lang/Boolean:booleanValue	()Z
    //   862: istore_2
    //   863: iload_2
    //   864: ifeq +6 -> 870
    //   867: goto -835 -> 32
    //   870: goto -193 -> 677
    //   873: iload_1
    //   874: lookupswitch	default:+26->900, 88:+-869->5, 97:+38->912
    //   900: goto -895 -> 5
    //   903: astore_3
    //   904: aload_3
    //   905: athrow
    //   906: goto -223 -> 683
    //   909: goto -906 -> 3
    //   912: goto -874 -> 38
    //   915: iload_1
    //   916: lookupswitch	default:+28->944, 15:+-679->237, 29:+-876->40
    //   944: goto -904 -> 40
    //   947: getstatic 41	o/IB:ʿ	I
    //   950: bipush 41
    //   952: iadd
    //   953: istore_1
    //   954: iload_1
    //   955: sipush 128
    //   958: irem
    //   959: putstatic 39	o/IB:ˊˋ	I
    //   962: iload_1
    //   963: iconst_2
    //   964: irem
    //   965: ifne +6 -> 971
    //   968: goto -59 -> 909
    //   971: goto -968 -> 3
    // Local variable table:
    //   start	length	slot	name	signature
    //   0	974	0	this	IB
    //   11	954	1	i	int
    //   221	643	2	bool	boolean
    //   43	16	3	localObject1	Object
    //   121	1	3	localObject2	Object
    //   125	86	3	localObject3	Object
    //   240	16	3	localObject4	Object
    //   327	1	3	localObject5	Object
    //   331	75	3	localObject6	Object
    //   427	2	3	localException1	Exception
    //   445	16	3	localObject7	Object
    //   533	1	3	localObject8	Object
    //   537	97	3	localObject9	Object
    //   686	16	3	localObject10	Object
    //   754	1	3	localObject11	Object
    //   758	94	3	localObject12	Object
    //   903	2	3	localException2	Exception
    //   48	723	4	localThrowable	Throwable
    // Exception table:
    //   from	to	target	type
    //   60	122	43	finally
    //   142	222	125	finally
    //   257	328	240	finally
    //   348	417	331	finally
    //   687	693	427	java/lang/Exception
    //   698	701	427	java/lang/Exception
    //   701	703	427	java/lang/Exception
    //   759	765	427	java/lang/Exception
    //   770	773	427	java/lang/Exception
    //   773	775	427	java/lang/Exception
    //   462	534	445	finally
    //   554	649	537	finally
    //   703	755	686	finally
    //   775	863	758	finally
    //   759	765	903	java/lang/Exception
    //   770	773	903	java/lang/Exception
    //   773	775	903	java/lang/Exception
  }
}
