package o;

import android.content.Context;
import android.content.DialogInterface;
import android.content.DialogInterface.OnCancelListener;
import java.io.UnsupportedEncodingException;

public class IC
  extends aa
  implements Iu.if
{
  private static int ʻ;
  private static char[] ˊ;
  private static int ˋ;
  private static byte ˎ;
  private static long ॱ;
  private IM ˏ;
  
  static
  {
    for (;;)
    {
      int i = ˋ + 37;
      ʻ = i % 128;
      if (i % 2 == 0) {
        break;
      }
      return;
      ˋ = 0;
      ʻ = 1;
      ʻ();
      ˎ = -102;
    }
  }
  
  public IC(Context paramContext)
  {
    super(paramContext);
  }
  
  static void ʻ()
  {
    ॱ = -9023061654350411098L;
    ˊ = new char[] { 114, -13629, -27349, 24475, 10987, -2742, -16511, -29960, 21845, 8114, -5588, -19126, 32679, 18944, 5489, -8204, -21995, 30059, 16334, 2615, -11126, -21148, 26589, 14374, -3425, -26263, 21464, 3122, -14703, -19482, 27667, 9929, 5032, -13239, -31063, 29461, 11356, -6519, -11513, -29589, 18117, 13069, -5011, -22843, -25179, 22287, 2276, -15808, -18629, 26752, 8790, 5986, -14191, -32139, 30670, 10423, -7558, -10278, -30533, 16914, 14273, -5912, -24008, -26694, 18765, 556, -2064, -22203, 25144, 22423, 2356, -15835, -18560, 26967, 8919, 6062, -13964, -32049, 30648, 10539, -7439, -11173, -30463, 17145, 13380, -5854, -23905, -27584, 18791, 101, -13612, -27330, 24477, 10986, -2694, -16499, -29973, 21852, 8121, -5605, -19082, 32673, 18970, 5496, -8225, 99, -13625, -27358, 24465, 11005, -2734, -16472, -29981, 21827, 8098, -5607, -19124, 32685, 18972, 11236, -7865, -16713, 29710, 373, -8488, -27639, -24208, 99, -13623, -27358, 24454, 11005, -2746, -16496, -30044, 21847, 8115, -5624, -19087, 32700, 18972, 5501, -8236, -22009, 29998, 16382, 2684, -11125, -24598, 27190, 13443, -8266, -13756, -27469, 24557, 10844, -2901, -16624, -30139, 21683, 7939, -5521, -19257, 32554, 18839, 5328, -8397, -22097, 29926, 16206, 2445, -11030, -24766, 27057, 13335, -173, -13841, 27680, -22873, -1698, 13311, 18079, -26305, -11315, -6513, 14650, 29651, -31105, -9949, 5086, 9764, 30999, -19525, -14736, 6474, 21473, 106, -13625, -27334, 24467, 10934, -2734, -16507, -29980, 21847, 8184, -5585, -19114, 32698, 18951, 5498, -8227, -21938, 30048, 16323, 2592, -11115, -24577, 27184, 13506, -10, -13735, -27474, 24559, 10825, -2886, -16552, -30150, 21738, 7943, -5506, -19243, 32555, 18903, 73, -13579, -27389, 24543, 10912, -2810, -16431, -30029, 21789, 8167, 85, -13582, -27382, 24543, 10912 };
  }
  
  private static String ˊ(int paramInt1, char paramChar, int paramInt2)
  {
    break label6;
    Object localObject;
    return localObject;
    label6:
    int i = ˋ + 75;
    ʻ = i % 128;
    int j;
    if (i % 2 != 0)
    {
      localObject = new char[paramInt2];
      i = 0;
      break label212;
      i = j;
      break label212;
      label46:
      i = j;
      break label212;
      i = 43;
    }
    for (;;)
    {
      paramInt1 = ˋ + 63;
      ʻ = paramInt1 % 128;
      if (paramInt1 % 2 != 0)
      {
        break label180;
        label85:
        switch (i)
        {
        }
        break label46;
      }
      for (;;)
      {
        switch (paramInt1)
        {
        }
        throw new NullPointerException();
        label148:
        localObject[i] = ((char)(int)(ˊ[(paramInt1 + i)] ^ i * ॱ ^ paramChar));
        j = i + 1;
        break;
        label180:
        paramInt1 = 1;
        continue;
        paramInt1 = 0;
      }
      break;
      label193:
      localObject = new String((char[])localObject);
    }
    for (;;)
    {
      i = 5;
      break label85;
      label212:
      if (i < paramInt2) {
        break label148;
      }
      break label193;
      i = ʻ + 17;
      ˋ = i % 128;
      if (i % 2 != 0) {
        break;
      }
    }
  }
  
  private String ॱ(String paramString)
  {
    break label38;
    int j = 79;
    for (;;)
    {
      byte[] arrayOfByte;
      int i;
      try
      {
        arrayOfByte = paramString.getBytes(ˊ(234, '\000', 10).intern());
        paramString = new byte[arrayOfByte.length];
        i = 0;
      }
      catch (UnsupportedEncodingException paramString)
      {
        try
        {
          label38:
          i = ʻ;
          i += 7;
          ˋ = i % 128;
          if (i % 2 != 0) {
            continue;
          }
        }
        catch (Exception paramString)
        {
          throw paramString;
        }
        paramString = paramString;
        throw new RuntimeException(paramString);
      }
      continue;
      j = ˋ + 39;
      ʻ = j % 128;
      if (j % 2 != 0)
      {
        break label201;
        i = 23;
        break label254;
        paramString = new String(paramString, ˊ(244, '\000', 5).intern());
        return paramString;
        for (;;)
        {
          paramString[i] = ((byte)(arrayOfByte[(arrayOfByte.length - i - 1)] ^ ˎ));
          i += 1;
          break;
          label163:
          switch (j)
          {
          }
        }
      }
      for (;;)
      {
        j = 38;
        break label163;
        label201:
        break label239;
        i = 87;
        break label254;
        break label239;
        arrayOfByte = paramString.getBytes(ˊ(5462, '\000', 17).intern());
        paramString = new byte[arrayOfByte.length];
        i = 0;
        label239:
        j = arrayOfByte.length;
        if (i < j) {
          break;
        }
      }
      label254:
      switch (i)
      {
      }
    }
  }
  
  public void A_()
  {
    break label8;
    int i = 3;
    for (;;)
    {
      label8:
      switch (i)
      {
      default: 
        break;
      }
      for (;;)
      {
        new D(ˏ(), false).ˏ();
        break label147;
        i = ʻ + 101;
        ˋ = i % 128;
        if (i % 2 != 0) {
          break label150;
        }
        break;
        if (ˏ() == null)
        {
          break label147;
          Context localContext = ˏ();
          i = 34 / 0;
          if (localContext == null) {
            break label147;
          }
        }
      }
      label147:
      for (;;)
      {
        i = ˋ + 51;
        ʻ = i % 128;
        if (i % 2 == 0) {
          break;
        }
        return;
      }
      label150:
      i = 98;
    }
  }
  
  /* Error */
  public void v_()
  {
    // Byte code:
    //   0: goto +183 -> 183
    //   3: iconst_1
    //   4: istore_1
    //   5: goto +150 -> 155
    //   8: getstatic 27	o/IC:ˋ	I
    //   11: istore_1
    //   12: iload_1
    //   13: bipush 111
    //   15: iadd
    //   16: istore_1
    //   17: iload_1
    //   18: sipush 128
    //   21: irem
    //   22: putstatic 29	o/IC:ʻ	I
    //   25: iload_1
    //   26: iconst_2
    //   27: irem
    //   28: ifne +4 -> 32
    //   31: return
    //   32: return
    //   33: iconst_1
    //   34: istore_1
    //   35: goto +95 -> 130
    //   38: goto -30 -> 8
    //   41: aload_0
    //   42: invokevirtual 323	o/IC:ˏ	()Landroid/content/Context;
    //   45: pop
    //   46: new 287	java/lang/NullPointerException
    //   49: dup
    //   50: invokespecial 289	java/lang/NullPointerException:<init>	()V
    //   53: athrow
    //   54: aload_0
    //   55: invokevirtual 323	o/IC:ˏ	()Landroid/content/Context;
    //   58: instanceof 332
    //   61: ifeq +6 -> 67
    //   64: goto +39 -> 103
    //   67: goto -29 -> 38
    //   70: getstatic 29	o/IC:ʻ	I
    //   73: bipush 123
    //   75: iadd
    //   76: istore_1
    //   77: iload_1
    //   78: sipush 128
    //   81: irem
    //   82: putstatic 27	o/IC:ˋ	I
    //   85: iload_1
    //   86: iconst_2
    //   87: irem
    //   88: ifeq +6 -> 94
    //   91: goto -58 -> 33
    //   94: goto +92 -> 186
    //   97: astore_2
    //   98: aload_2
    //   99: athrow
    //   100: astore_2
    //   101: aload_2
    //   102: athrow
    //   103: getstatic 29	o/IC:ʻ	I
    //   106: bipush 45
    //   108: iadd
    //   109: istore_1
    //   110: iload_1
    //   111: sipush 128
    //   114: irem
    //   115: putstatic 27	o/IC:ˋ	I
    //   118: iload_1
    //   119: iconst_2
    //   120: irem
    //   121: ifeq +6 -> 127
    //   124: goto +80 -> 204
    //   127: goto +193 -> 320
    //   130: iload_1
    //   131: tableswitch	default:+21->152, 0:+60->191, 1:+-90->41
    //   152: goto -111 -> 41
    //   155: iload_1
    //   156: tableswitch	default:+24->180, 0:+-118->38, 1:+-102->54
    //   180: goto -142 -> 38
    //   183: goto -113 -> 70
    //   186: iconst_0
    //   187: istore_1
    //   188: goto -58 -> 130
    //   191: aload_0
    //   192: invokevirtual 323	o/IC:ˏ	()Landroid/content/Context;
    //   195: ifnull +6 -> 201
    //   198: goto -195 -> 3
    //   201: goto +232 -> 433
    //   204: goto +17 -> 221
    //   207: astore_2
    //   208: aload_2
    //   209: invokevirtual 338	java/lang/Throwable:getCause	()Ljava/lang/Throwable;
    //   212: astore_3
    //   213: aload_3
    //   214: ifnull +5 -> 219
    //   217: aload_3
    //   218: athrow
    //   219: aload_2
    //   220: athrow
    //   221: iconst_4
    //   222: sipush 267
    //   225: sipush 14788
    //   228: invokestatic 343	o/O:ˋ	(IIC)Ljava/lang/Object;
    //   231: checkcast 345	java/lang/Class
    //   234: ldc_w 346
    //   237: aconst_null
    //   238: invokevirtual 350	java/lang/Class:getMethod	(Ljava/lang/String;[Ljava/lang/Class;)Ljava/lang/reflect/Method;
    //   241: aconst_null
    //   242: aconst_null
    //   243: invokevirtual 356	java/lang/reflect/Method:invoke	(Ljava/lang/Object;[Ljava/lang/Object;)Ljava/lang/Object;
    //   246: astore_2
    //   247: aload_0
    //   248: invokevirtual 323	o/IC:ˏ	()Landroid/content/Context;
    //   251: checkcast 332	android/app/Activity
    //   254: astore_3
    //   255: goto +17 -> 272
    //   258: astore_3
    //   259: aload_3
    //   260: invokevirtual 338	java/lang/Throwable:getCause	()Ljava/lang/Throwable;
    //   263: astore_2
    //   264: aload_2
    //   265: ifnull +5 -> 270
    //   268: aload_2
    //   269: athrow
    //   270: aload_3
    //   271: athrow
    //   272: iconst_4
    //   273: sipush 267
    //   276: sipush 14788
    //   279: invokestatic 343	o/O:ˋ	(IIC)Ljava/lang/Object;
    //   282: checkcast 345	java/lang/Class
    //   285: ldc_w 357
    //   288: iconst_1
    //   289: anewarray 345	java/lang/Class
    //   292: dup
    //   293: iconst_0
    //   294: ldc_w 332
    //   297: aastore
    //   298: invokevirtual 350	java/lang/Class:getMethod	(Ljava/lang/String;[Ljava/lang/Class;)Ljava/lang/reflect/Method;
    //   301: aload_2
    //   302: iconst_1
    //   303: anewarray 359	java/lang/Object
    //   306: dup
    //   307: iconst_0
    //   308: aload_3
    //   309: aastore
    //   310: invokevirtual 356	java/lang/reflect/Method:invoke	(Ljava/lang/Object;[Ljava/lang/Object;)Ljava/lang/Object;
    //   313: pop
    //   314: aconst_null
    //   315: arraylength
    //   316: istore_1
    //   317: goto -279 -> 38
    //   320: goto +17 -> 337
    //   323: astore_2
    //   324: aload_2
    //   325: invokevirtual 338	java/lang/Throwable:getCause	()Ljava/lang/Throwable;
    //   328: astore_3
    //   329: aload_3
    //   330: ifnull +5 -> 335
    //   333: aload_3
    //   334: athrow
    //   335: aload_2
    //   336: athrow
    //   337: iconst_4
    //   338: sipush 267
    //   341: sipush 14788
    //   344: invokestatic 343	o/O:ˋ	(IIC)Ljava/lang/Object;
    //   347: checkcast 345	java/lang/Class
    //   350: ldc_w 346
    //   353: aconst_null
    //   354: invokevirtual 350	java/lang/Class:getMethod	(Ljava/lang/String;[Ljava/lang/Class;)Ljava/lang/reflect/Method;
    //   357: aconst_null
    //   358: aconst_null
    //   359: invokevirtual 356	java/lang/reflect/Method:invoke	(Ljava/lang/Object;[Ljava/lang/Object;)Ljava/lang/Object;
    //   362: astore_2
    //   363: aload_0
    //   364: invokevirtual 323	o/IC:ˏ	()Landroid/content/Context;
    //   367: checkcast 332	android/app/Activity
    //   370: astore_3
    //   371: goto +17 -> 388
    //   374: astore_2
    //   375: aload_2
    //   376: invokevirtual 338	java/lang/Throwable:getCause	()Ljava/lang/Throwable;
    //   379: astore_3
    //   380: aload_3
    //   381: ifnull +5 -> 386
    //   384: aload_3
    //   385: athrow
    //   386: aload_2
    //   387: athrow
    //   388: iconst_4
    //   389: sipush 267
    //   392: sipush 14788
    //   395: invokestatic 343	o/O:ˋ	(IIC)Ljava/lang/Object;
    //   398: checkcast 345	java/lang/Class
    //   401: ldc_w 357
    //   404: iconst_1
    //   405: anewarray 345	java/lang/Class
    //   408: dup
    //   409: iconst_0
    //   410: ldc_w 332
    //   413: aastore
    //   414: invokevirtual 350	java/lang/Class:getMethod	(Ljava/lang/String;[Ljava/lang/Class;)Ljava/lang/reflect/Method;
    //   417: aload_2
    //   418: iconst_1
    //   419: anewarray 359	java/lang/Object
    //   422: dup
    //   423: iconst_0
    //   424: aload_3
    //   425: aastore
    //   426: invokevirtual 356	java/lang/reflect/Method:invoke	(Ljava/lang/Object;[Ljava/lang/Object;)Ljava/lang/Object;
    //   429: pop
    //   430: goto -392 -> 38
    //   433: iconst_0
    //   434: istore_1
    //   435: goto -280 -> 155
    // Local variable table:
    //   start	length	slot	name	signature
    //   0	438	0	this	IC
    //   4	431	1	i	int
    //   97	2	2	localException1	Exception
    //   100	2	2	localException2	Exception
    //   207	13	2	localObject1	Object
    //   246	56	2	localObject2	Object
    //   323	13	2	localObject3	Object
    //   362	1	2	localObject4	Object
    //   374	44	2	localObject5	Object
    //   212	43	3	localObject6	Object
    //   258	51	3	localObject7	Object
    //   328	97	3	localObject8	Object
    // Exception table:
    //   from	to	target	type
    //   17	25	97	java/lang/Exception
    //   8	12	100	java/lang/Exception
    //   221	247	207	finally
    //   272	314	258	finally
    //   337	363	323	finally
    //   388	430	374	finally
  }
  
  /* Error */
  public void w_()
  {
    // Byte code:
    //   0: goto +106 -> 106
    //   3: goto +88 -> 91
    //   6: getstatic 27	o/IC:ˋ	I
    //   9: bipush 37
    //   11: iadd
    //   12: istore_1
    //   13: iload_1
    //   14: sipush 128
    //   17: irem
    //   18: putstatic 29	o/IC:ʻ	I
    //   21: iload_1
    //   22: iconst_2
    //   23: irem
    //   24: ifne +6 -> 30
    //   27: goto +58 -> 85
    //   30: goto +144 -> 174
    //   33: astore_2
    //   34: aload_2
    //   35: athrow
    //   36: getstatic 29	o/IC:ʻ	I
    //   39: bipush 101
    //   41: iadd
    //   42: istore_1
    //   43: iload_1
    //   44: sipush 128
    //   47: irem
    //   48: putstatic 27	o/IC:ˋ	I
    //   51: iload_1
    //   52: iconst_2
    //   53: irem
    //   54: ifeq +4 -> 58
    //   57: return
    //   58: return
    //   59: new 362	o/II
    //   62: dup
    //   63: aload_0
    //   64: invokevirtual 323	o/IC:ˏ	()Landroid/content/Context;
    //   67: invokespecial 363	o/II:<init>	(Landroid/content/Context;)V
    //   70: astore_2
    //   71: aload_2
    //   72: invokevirtual 364	o/II:ˏ	()Lo/ᐸ;
    //   75: pop
    //   76: goto -70 -> 6
    //   79: goto +30 -> 109
    //   82: astore_2
    //   83: aload_2
    //   84: athrow
    //   85: bipush 60
    //   87: istore_1
    //   88: goto +27 -> 115
    //   91: aload_0
    //   92: invokevirtual 323	o/IC:ˏ	()Landroid/content/Context;
    //   95: astore_2
    //   96: aload_2
    //   97: ifnull +6 -> 103
    //   100: goto -41 -> 59
    //   103: goto +6 -> 109
    //   106: goto +41 -> 147
    //   109: goto -73 -> 36
    //   112: goto -3 -> 109
    //   115: iload_1
    //   116: lookupswitch	default:+28->144, 52:+-37->79, 60:+-4->112
    //   144: goto -32 -> 112
    //   147: getstatic 27	o/IC:ˋ	I
    //   150: bipush 115
    //   152: iadd
    //   153: istore_1
    //   154: iload_1
    //   155: sipush 128
    //   158: irem
    //   159: putstatic 29	o/IC:ʻ	I
    //   162: iload_1
    //   163: iconst_2
    //   164: irem
    //   165: ifne +6 -> 171
    //   168: goto -165 -> 3
    //   171: goto -80 -> 91
    //   174: bipush 52
    //   176: istore_1
    //   177: goto -62 -> 115
    // Local variable table:
    //   start	length	slot	name	signature
    //   0	180	0	this	IC
    //   12	165	1	i	int
    //   33	2	2	localException1	Exception
    //   70	2	2	localII	II
    //   82	2	2	localException2	Exception
    //   95	2	2	localContext	Context
    // Exception table:
    //   from	to	target	type
    //   59	71	33	java/lang/Exception
    //   71	76	33	java/lang/Exception
    //   147	154	33	java/lang/Exception
    //   154	162	33	java/lang/Exception
    //   91	96	82	java/lang/Exception
  }
  
  public void x_()
  {
    break label156;
    Context localContext = ˏ();
    int i = Gu.ˏ.security_compromised;
    Object localObject = ˏ().getString(Gu.ˏ.we_detected_security_problems);
    if (!((String)localObject).startsWith(ˊ(21, 44385, 4).intern()))
    {
      new IR(localContext, i, (String)localObject, Gu.ˏ.uninstall_app, true).ˏ();
      break label138;
      label66:
      break label141;
    }
    for (;;)
    {
      i = ˋ + 105;
      ʻ = i % 128;
      if (i % 2 == 0) {
        break label66;
      }
      break label141;
      label138:
      for (;;)
      {
        i = ˋ + 89;
        ʻ = i % 128;
        if (i % 2 == 0) {
          return;
        }
        return;
        for (;;)
        {
          break;
          localObject = ॱ(((String)localObject).substring(4)).intern();
        }
      }
      try
      {
        label141:
        localObject = ˏ();
        if (localObject != null) {
          break;
        }
      }
      catch (Exception localException)
      {
        label156:
        throw localException;
      }
    }
  }
  
  public void y_()
  {
    break label25;
    int i = null.length;
    return;
    new IL(ˏ()).ˏ();
    for (;;)
    {
      label25:
      Context localContext = ˏ();
      i = null.length;
      if (localContext != null) {
        break;
      }
      break label166;
      for (;;)
      {
        i = 0;
        break label175;
        try
        {
          i = ʻ + 111;
        }
        catch (Exception localException1)
        {
          throw localException1;
        }
        try
        {
          ˋ = i % 128;
          if (i % 2 != 0) {
            break label161;
          }
        }
        catch (Exception localException2)
        {
          throw localException2;
        }
      }
      if (ˏ() != null) {
        break;
      }
      break label166;
      for (;;)
      {
        i = 37;
        break;
        i = ˋ + 73;
        ʻ = i % 128;
        if (i % 2 == 0) {
          break label169;
        }
      }
      for (;;)
      {
        switch (i)
        {
        case 56: 
        default: 
          return;
        }
        return;
        label161:
        i = 1;
        break label175;
        label166:
        break;
        label169:
        i = 56;
      }
      label175:
      switch (i)
      {
      }
    }
  }
  
  public void z_()
  {
    for (;;)
    {
      label3:
      break label33;
      int i = ʻ + 11;
      ˋ = i % 128;
      if (i % 2 == 0)
      {
        break label96;
        label33:
        i = ˋ + 61;
        ʻ = i % 128;
        if (i % 2 == 0) {
          break label106;
        }
        return;
      }
      for (;;)
      {
        switch (i)
        {
        default: 
          break;
        case 0: 
          if (ˏ() != null) {
            break label127;
          }
          break label3;
          label96:
          i = 0;
          continue;
          i = 1;
        }
      }
      label106:
      return;
      Context localContext = ˏ();
      i = 48 / 0;
      if (localContext == null) {}
      label127:
      new IG(ˏ(), false).ˏ();
    }
  }
  
  /* Error */
  public void ʼ()
  {
    // Byte code:
    //   0: goto +6 -> 6
    //   3: goto +381 -> 384
    //   6: goto +337 -> 343
    //   9: goto -6 -> 3
    //   12: getstatic 414	o/vw:ˊ	Lo/vw;
    //   15: astore_2
    //   16: aload_0
    //   17: invokevirtual 323	o/IC:ˏ	()Landroid/content/Context;
    //   20: getstatic 417	o/Gu$ˏ:device_rooted_security_problems	I
    //   23: invokevirtual 379	android/content/Context:getString	(I)Ljava/lang/String;
    //   26: astore_3
    //   27: aload_3
    //   28: bipush 21
    //   30: ldc_w 380
    //   33: iconst_4
    //   34: invokestatic 301	o/IC:ˊ	(ICI)Ljava/lang/String;
    //   37: invokevirtual 305	java/lang/String:intern	()Ljava/lang/String;
    //   40: invokevirtual 384	java/lang/String:startsWith	(Ljava/lang/String;)Z
    //   43: ifeq +6 -> 49
    //   46: goto +33 -> 79
    //   49: goto +371 -> 420
    //   52: getstatic 27	o/IC:ˋ	I
    //   55: bipush 91
    //   57: iadd
    //   58: istore_1
    //   59: iload_1
    //   60: sipush 128
    //   63: irem
    //   64: putstatic 29	o/IC:ʻ	I
    //   67: iload_1
    //   68: iconst_2
    //   69: irem
    //   70: ifne +6 -> 76
    //   73: goto -64 -> 9
    //   76: goto -73 -> 3
    //   79: bipush 61
    //   81: istore_1
    //   82: goto +352 -> 434
    //   85: astore_2
    //   86: aload_2
    //   87: athrow
    //   88: goto +239 -> 327
    //   91: aload_2
    //   92: bipush 127
    //   94: iconst_0
    //   95: bipush 50
    //   97: invokestatic 301	o/IC:ˊ	(ICI)Ljava/lang/String;
    //   100: invokevirtual 305	java/lang/String:intern	()Ljava/lang/String;
    //   103: invokestatic 422	o/vq:ˋ	(Ljava/lang/Object;Ljava/lang/String;)V
    //   106: iconst_1
    //   107: anewarray 359	java/lang/Object
    //   110: astore_3
    //   111: goto +17 -> 128
    //   114: astore_2
    //   115: aload_2
    //   116: invokevirtual 338	java/lang/Throwable:getCause	()Ljava/lang/Throwable;
    //   119: astore_3
    //   120: aload_3
    //   121: ifnull +5 -> 126
    //   124: aload_3
    //   125: athrow
    //   126: aload_2
    //   127: athrow
    //   128: iconst_3
    //   129: iconst_0
    //   130: ldc_w 423
    //   133: invokestatic 343	o/O:ˋ	(IIC)Ljava/lang/Object;
    //   136: checkcast 345	java/lang/Class
    //   139: ldc_w 424
    //   142: aconst_null
    //   143: invokevirtual 350	java/lang/Class:getMethod	(Ljava/lang/String;[Ljava/lang/Class;)Ljava/lang/reflect/Method;
    //   146: aconst_null
    //   147: aconst_null
    //   148: invokevirtual 356	java/lang/reflect/Method:invoke	(Ljava/lang/Object;[Ljava/lang/Object;)Ljava/lang/Object;
    //   151: astore 4
    //   153: aload 4
    //   155: sipush 177
    //   158: sipush 27748
    //   161: bipush 19
    //   163: invokestatic 301	o/IC:ˊ	(ICI)Ljava/lang/String;
    //   166: invokevirtual 305	java/lang/String:intern	()Ljava/lang/String;
    //   169: invokestatic 422	o/vq:ˋ	(Ljava/lang/Object;Ljava/lang/String;)V
    //   172: goto +17 -> 189
    //   175: astore_2
    //   176: aload_2
    //   177: invokevirtual 338	java/lang/Throwable:getCause	()Ljava/lang/Throwable;
    //   180: astore_3
    //   181: aload_3
    //   182: ifnull +5 -> 187
    //   185: aload_3
    //   186: athrow
    //   187: aload_2
    //   188: athrow
    //   189: iconst_3
    //   190: iconst_0
    //   191: ldc_w 423
    //   194: invokestatic 343	o/O:ˋ	(IIC)Ljava/lang/Object;
    //   197: checkcast 345	java/lang/Class
    //   200: ldc_w 346
    //   203: aconst_null
    //   204: invokevirtual 350	java/lang/Class:getMethod	(Ljava/lang/String;[Ljava/lang/Class;)Ljava/lang/reflect/Method;
    //   207: aload 4
    //   209: aconst_null
    //   210: invokevirtual 356	java/lang/reflect/Method:invoke	(Ljava/lang/Object;[Ljava/lang/Object;)Ljava/lang/Object;
    //   213: astore 4
    //   215: aload_3
    //   216: iconst_0
    //   217: aload 4
    //   219: aastore
    //   220: aload_3
    //   221: arraylength
    //   222: istore_1
    //   223: aload_2
    //   224: aload_3
    //   225: iconst_1
    //   226: invokestatic 430	java/util/Arrays:copyOf	([Ljava/lang/Object;I)[Ljava/lang/Object;
    //   229: invokestatic 434	java/lang/String:format	(Ljava/lang/String;[Ljava/lang/Object;)Ljava/lang/String;
    //   232: astore_2
    //   233: aload_2
    //   234: sipush 196
    //   237: iconst_0
    //   238: bipush 38
    //   240: invokestatic 301	o/IC:ˊ	(ICI)Ljava/lang/String;
    //   243: invokevirtual 305	java/lang/String:intern	()Ljava/lang/String;
    //   246: invokestatic 422	o/vq:ˋ	(Ljava/lang/Object;Ljava/lang/String;)V
    //   249: getstatic 439	o/Gz:ˎ	Lo/Gz$ˊ;
    //   252: aload_0
    //   253: invokevirtual 323	o/IC:ˏ	()Landroid/content/Context;
    //   256: invokevirtual 444	o/Gz$ˊ:ˎ	(Landroid/content/Context;)Lo/Gz;
    //   259: aload_0
    //   260: invokevirtual 323	o/IC:ˏ	()Landroid/content/Context;
    //   263: aload_2
    //   264: getstatic 450	o/Fh:BLR_DEVICE_ROOTED	Lo/Fh;
    //   267: invokevirtual 453	o/Gz:ˊ	(Landroid/content/Context;Ljava/lang/String;Lo/Fh;)V
    //   270: goto -218 -> 52
    //   273: getstatic 29	o/IC:ʻ	I
    //   276: bipush 111
    //   278: iadd
    //   279: istore_1
    //   280: iload_1
    //   281: sipush 128
    //   284: irem
    //   285: putstatic 27	o/IC:ˋ	I
    //   288: iload_1
    //   289: iconst_2
    //   290: irem
    //   291: ifeq +6 -> 297
    //   294: goto -206 -> 88
    //   297: goto +30 -> 327
    //   300: getstatic 27	o/IC:ˋ	I
    //   303: bipush 67
    //   305: iadd
    //   306: istore_1
    //   307: iload_1
    //   308: sipush 128
    //   311: irem
    //   312: putstatic 29	o/IC:ʻ	I
    //   315: iload_1
    //   316: iconst_2
    //   317: irem
    //   318: ifne +6 -> 324
    //   321: goto +105 -> 426
    //   324: goto +91 -> 415
    //   327: aload_0
    //   328: aload_3
    //   329: iconst_4
    //   330: invokevirtual 396	java/lang/String:substring	(I)Ljava/lang/String;
    //   333: invokespecial 398	o/IC:ॱ	(Ljava/lang/String;)Ljava/lang/String;
    //   336: invokevirtual 305	java/lang/String:intern	()Ljava/lang/String;
    //   339: astore_2
    //   340: goto -40 -> 300
    //   343: aload_0
    //   344: invokevirtual 323	o/IC:ˏ	()Landroid/content/Context;
    //   347: ifnull +6 -> 353
    //   350: goto -338 -> 12
    //   353: goto +31 -> 384
    //   356: goto -265 -> 91
    //   359: getstatic 27	o/IC:ˋ	I
    //   362: istore_1
    //   363: iload_1
    //   364: bipush 49
    //   366: iadd
    //   367: istore_1
    //   368: iload_1
    //   369: sipush 128
    //   372: irem
    //   373: putstatic 29	o/IC:ʻ	I
    //   376: iload_1
    //   377: iconst_2
    //   378: irem
    //   379: ifne +4 -> 383
    //   382: return
    //   383: return
    //   384: goto -25 -> 359
    //   387: iload_1
    //   388: tableswitch	default:+24->412, 0:+-32->356, 1:+-297->91
    //   412: goto -56 -> 356
    //   415: iconst_1
    //   416: istore_1
    //   417: goto -30 -> 387
    //   420: bipush 33
    //   422: istore_1
    //   423: goto +11 -> 434
    //   426: iconst_0
    //   427: istore_1
    //   428: goto -41 -> 387
    //   431: astore_2
    //   432: aload_2
    //   433: athrow
    //   434: aload_3
    //   435: astore_2
    //   436: iload_1
    //   437: lookupswitch	default:+27->464, 33:+-346->91, 61:+-164->273
    //   464: goto -191 -> 273
    // Local variable table:
    //   start	length	slot	name	signature
    //   0	467	0	this	IC
    //   58	379	1	i	int
    //   15	1	2	localVw	vw
    //   85	7	2	localException1	Exception
    //   114	13	2	localObject1	Object
    //   175	49	2	str1	String
    //   232	108	2	str2	String
    //   431	2	2	localException2	Exception
    //   435	1	2	localObject2	Object
    //   26	409	3	localObject3	Object
    //   151	67	4	localObject4	Object
    // Exception table:
    //   from	to	target	type
    //   359	363	85	java/lang/Exception
    //   128	153	114	finally
    //   189	215	175	finally
    //   368	376	431	java/lang/Exception
  }
  
  public void ˊ()
  {
    break label11;
    break label199;
    label6:
    int i = 0;
    break label115;
    label11:
    break label143;
    label19:
    label60:
    IM localIM;
    for (;;)
    {
      i = 0;
      break;
      i = 3;
      break label279;
      switch (i)
      {
      case 39: 
      default: 
        break label172;
        do
        {
          i = 1;
          break label84;
          i = 39;
          break;
          localIM = this.ˏ;
          i = null.length;
        } while (localIM != null);
      }
    }
    switch (i)
    {
    default: 
      return;
      this.ˏ = null;
      return;
    case 0: 
      for (;;)
      {
        label84:
        label109:
        switch (i)
        {
        case 1: 
        default: 
          label115:
          break label244;
          label143:
          i = ʻ + 3;
          ˋ = i % 128;
          if (i % 2 == 0)
          {
            break label6;
            break label109;
            label172:
            i = ˋ + 13;
            ʻ = i % 128;
            if (i % 2 != 0) {
              break label19;
            }
            for (;;)
            {
              label199:
              localIM.ʻ();
              break label109;
              return;
              i = 5;
              break label279;
              i = ˋ + 49;
              ʻ = i % 128;
              if (i % 2 == 0) {
                break;
              }
            }
          }
          i = 1;
        }
      }
      label244:
      if (this.ˏ == null) {
        return;
      }
      break;
    }
    for (;;)
    {
      break label109;
      localIM = this.ˏ;
      if (localIM == null) {
        break label60;
      }
      i = 22;
      break;
      label279:
      switch (i)
      {
      }
    }
  }
  
  /* Error */
  public void ˊ(int paramInt)
  {
    // Byte code:
    //   0: goto +204 -> 204
    //   3: bipush 76
    //   5: istore_2
    //   6: goto +233 -> 239
    //   9: aload_0
    //   10: getfield 455	o/IC:ˏ	Lo/IM;
    //   13: ifnonnull +6 -> 19
    //   16: goto +167 -> 183
    //   19: goto +391 -> 410
    //   22: getstatic 29	o/IC:ʻ	I
    //   25: bipush 105
    //   27: iadd
    //   28: istore_1
    //   29: iload_1
    //   30: sipush 128
    //   33: irem
    //   34: putstatic 27	o/IC:ˋ	I
    //   37: iload_1
    //   38: iconst_2
    //   39: irem
    //   40: ifeq +6 -> 46
    //   43: goto +228 -> 271
    //   46: goto +421 -> 467
    //   49: aload_0
    //   50: getfield 455	o/IC:ˏ	Lo/IM;
    //   53: astore_3
    //   54: bipush 59
    //   56: iconst_0
    //   57: idiv
    //   58: istore_2
    //   59: aload_3
    //   60: ifnonnull +6 -> 66
    //   63: goto +120 -> 183
    //   66: goto +344 -> 410
    //   69: iload_2
    //   70: lookupswitch	default:+26->96, 33:+396->466, 36:+38->108
    //   96: goto +370 -> 466
    //   99: bipush 26
    //   101: istore_2
    //   102: goto +137 -> 239
    //   105: goto +361 -> 466
    //   108: getstatic 27	o/IC:ˋ	I
    //   111: bipush 81
    //   113: iadd
    //   114: istore_2
    //   115: iload_2
    //   116: sipush 128
    //   119: irem
    //   120: putstatic 29	o/IC:ʻ	I
    //   123: iload_2
    //   124: iconst_2
    //   125: irem
    //   126: ifne +6 -> 132
    //   129: goto +326 -> 455
    //   132: goto +67 -> 199
    //   135: bipush 25
    //   137: istore_1
    //   138: goto +287 -> 425
    //   141: goto -36 -> 105
    //   144: aload_0
    //   145: invokevirtual 323	o/IC:ˏ	()Landroid/content/Context;
    //   148: astore_3
    //   149: bipush 87
    //   151: iconst_0
    //   152: idiv
    //   153: istore_2
    //   154: aload_3
    //   155: ifnull +6 -> 161
    //   158: goto -50 -> 108
    //   161: goto +305 -> 466
    //   164: astore_3
    //   165: aload_3
    //   166: athrow
    //   167: invokestatic 461	o/vq:ˎ	()V
    //   170: goto +227 -> 397
    //   173: aload_3
    //   174: ifnonnull +6 -> 180
    //   177: goto +35 -> 212
    //   180: goto +217 -> 397
    //   183: aload_0
    //   184: invokevirtual 323	o/IC:ˏ	()Landroid/content/Context;
    //   187: ifnull +6 -> 193
    //   190: goto +184 -> 374
    //   193: goto +217 -> 410
    //   196: astore_3
    //   197: aload_3
    //   198: athrow
    //   199: iconst_1
    //   200: istore_2
    //   201: goto +137 -> 338
    //   204: goto +104 -> 308
    //   207: aconst_null
    //   208: astore_3
    //   209: goto -36 -> 173
    //   212: getstatic 27	o/IC:ˋ	I
    //   215: bipush 123
    //   217: iadd
    //   218: istore_1
    //   219: iload_1
    //   220: sipush 128
    //   223: irem
    //   224: putstatic 29	o/IC:ʻ	I
    //   227: iload_1
    //   228: iconst_2
    //   229: irem
    //   230: ifne +6 -> 236
    //   233: goto +102 -> 335
    //   236: goto -69 -> 167
    //   239: iload_2
    //   240: lookupswitch	default:+28->268, 26:+-96->144, 76:+34->274
    //   268: goto -124 -> 144
    //   271: goto +196 -> 467
    //   274: aload_0
    //   275: invokevirtual 323	o/IC:ˏ	()Landroid/content/Context;
    //   278: ifnull +6 -> 284
    //   281: goto +6 -> 287
    //   284: goto +189 -> 473
    //   287: bipush 36
    //   289: istore_2
    //   290: goto -221 -> 69
    //   293: aload_0
    //   294: getfield 455	o/IC:ˏ	Lo/IM;
    //   297: astore_3
    //   298: aload_3
    //   299: ifnull +6 -> 305
    //   302: goto -280 -> 22
    //   305: goto -164 -> 141
    //   308: getstatic 27	o/IC:ˋ	I
    //   311: bipush 43
    //   313: iadd
    //   314: istore_2
    //   315: iload_2
    //   316: sipush 128
    //   319: irem
    //   320: putstatic 29	o/IC:ʻ	I
    //   323: iload_2
    //   324: iconst_2
    //   325: irem
    //   326: ifne +6 -> 332
    //   329: goto -230 -> 99
    //   332: goto -329 -> 3
    //   335: goto -168 -> 167
    //   338: iload_2
    //   339: tableswitch	default:+21->360, 0:+-290->49, 1:+-330->9
    //   360: goto -311 -> 49
    //   363: aload_3
    //   364: invokevirtual 464	o/IM:ˊ	()Z
    //   367: invokestatic 470	java/lang/Boolean:valueOf	(Z)Ljava/lang/Boolean;
    //   370: astore_3
    //   371: goto -198 -> 173
    //   374: aload_0
    //   375: invokevirtual 323	o/IC:ˏ	()Landroid/content/Context;
    //   378: astore_3
    //   379: new 457	o/IM
    //   382: dup
    //   383: aload_3
    //   384: iload_1
    //   385: invokespecial 473	o/IM:<init>	(Landroid/content/Context;I)V
    //   388: astore_3
    //   389: aload_0
    //   390: aload_3
    //   391: putfield 455	o/IC:ˏ	Lo/IM;
    //   394: goto +16 -> 410
    //   397: aload_3
    //   398: invokevirtual 476	java/lang/Boolean:booleanValue	()Z
    //   401: ifne +6 -> 407
    //   404: goto -111 -> 293
    //   407: goto +59 -> 466
    //   410: aload_0
    //   411: getfield 455	o/IC:ˏ	Lo/IM;
    //   414: astore_3
    //   415: aload_3
    //   416: ifnull +6 -> 422
    //   419: goto +41 -> 460
    //   422: goto -287 -> 135
    //   425: iload_1
    //   426: lookupswitch	default:+26->452, 25:+-219->207, 47:+-63->363
    //   452: goto -89 -> 363
    //   455: iconst_0
    //   456: istore_2
    //   457: goto -119 -> 338
    //   460: bipush 47
    //   462: istore_1
    //   463: goto -38 -> 425
    //   466: return
    //   467: aload_3
    //   468: invokevirtual 477	o/IM:ˏ	()Lo/ᐸ;
    //   471: pop
    //   472: return
    //   473: bipush 33
    //   475: istore_2
    //   476: goto -407 -> 69
    // Local variable table:
    //   start	length	slot	name	signature
    //   0	479	0	this	IC
    //   0	479	1	paramInt	int
    //   5	471	2	i	int
    //   53	102	3	localObject1	Object
    //   164	10	3	localException1	Exception
    //   196	2	3	localException2	Exception
    //   208	260	3	localObject2	Object
    // Exception table:
    //   from	to	target	type
    //   49	54	164	java/lang/Exception
    //   389	394	164	java/lang/Exception
    //   293	298	196	java/lang/Exception
    //   374	379	196	java/lang/Exception
    //   410	415	196	java/lang/Exception
  }
  
  public void ˋ()
  {
    break label70;
    break label12;
    label6:
    int i = 71;
    break label406;
    label12:
    break label501;
    Object localObject3;
    label70:
    label406:
    String str;
    for (;;)
    {
      try
      {
        Object localObject1 = (CharSequence)localObject1;
        localObject3 = localIf.ˊ((CharSequence)localObject1);
        try
        {
          localObject1 = ˏ();
          i = Gu.ˏ.nfc_not_enabled_message;
          localObject1 = ((Context)localObject1).getString(i);
          boolean bool = ((String)localObject1).startsWith(ˊ(21, 44385, 4).intern());
          if (bool) {
            break label469;
          }
        }
        catch (Exception localException1)
        {
          throw localException1;
        }
        continue;
        localObject1 = ॱ(((String)localObject1).substring(4)).intern();
        i = 30 / 0;
        continue;
        i = 0;
        continue;
        i = ˋ + 29;
        ʻ = i % 128;
        if (i % 2 == 0) {
          break;
        }
        break;
        ᐸ.If localIf = new ᐸ.If(ˏ());
        localObject3 = ˏ().getString(Gu.ˏ.nfc_not_enabled);
        if (!((String)localObject3).startsWith(ˊ(21, 44385, 4).intern())) {
          break label6;
        }
        i = 52;
        continue;
        Object localObject2;
        switch (i)
        {
        case 1: 
        default: 
          continue;
          if (ˏ() != null) {
            continue;
          }
          return;
          continue;
          localObject2 = ॱ(((String)localObject3).substring(4)).intern();
          break;
        case 0: 
          localObject2 = ॱ(((String)localObject2).substring(4)).intern();
          continue;
          localObject3 = ((ᐸ.If)localObject3).ˋ((CharSequence)localObject2);
          localObject2 = ˏ().getString(Gu.ˏ.enable_nfc);
          if (!((String)localObject2).startsWith(ˊ(21, 44385, 4).intern())) {
            continue;
          }
          i = ˋ + 7;
          ʻ = i % 128;
          if (i % 2 == 0) {
            break label464;
          }
          continue;
          localObject3 = ((ᐸ.If)localObject3).ˎ((CharSequence)localObject2);
          localObject2 = ˏ().getString(Gu.ˏ.cancel);
          if (((String)localObject2).startsWith(ˊ(21, 44385, 4).intern())) {
            break label485;
          }
          break;
        }
        i = ʻ + 29;
        ˋ = i % 128;
        if (i % 2 == 0)
        {
          continue;
          localObject2 = localObject3;
          switch (i)
          {
          }
          continue;
        }
        str = ॱ(((String)localObject3).substring(4)).intern();
      }
      catch (Exception localException2)
      {
        throw localException2;
      }
      throw new NullPointerException();
      label464:
      i = 1;
      continue;
      label469:
      str = ॱ(str.substring(4)).intern();
      continue;
      label485:
      str = ॱ(str.substring(4)).intern();
    }
    label501:
    ((ᐸ.If)localObject3).ॱ((CharSequence)str).ॱ((ᐸ.ˏ)new ˊ(this)).ˏ();
  }
  
  /* Error */
  public void ˎ()
  {
    // Byte code:
    //   0: goto +51 -> 51
    //   3: iload_1
    //   4: tableswitch	default:+24->28, 0:+46->50, 1:+50->54
    //   28: goto +26 -> 54
    //   31: goto +80 -> 111
    //   34: aload_0
    //   35: invokevirtual 323	o/IC:ˏ	()Landroid/content/Context;
    //   38: ifnull +6 -> 44
    //   41: goto +92 -> 133
    //   44: goto +94 -> 138
    //   47: goto -13 -> 34
    //   50: return
    //   51: goto +33 -> 84
    //   54: getstatic 29	o/IC:ʻ	I
    //   57: bipush 95
    //   59: iadd
    //   60: istore_1
    //   61: iload_1
    //   62: sipush 128
    //   65: irem
    //   66: putstatic 27	o/IC:ˋ	I
    //   69: iload_1
    //   70: iconst_2
    //   71: irem
    //   72: ifeq +6 -> 78
    //   75: goto -44 -> 31
    //   78: goto +33 -> 111
    //   81: astore_2
    //   82: aload_2
    //   83: athrow
    //   84: getstatic 27	o/IC:ˋ	I
    //   87: bipush 93
    //   89: iadd
    //   90: istore_1
    //   91: iload_1
    //   92: sipush 128
    //   95: irem
    //   96: putstatic 29	o/IC:ʻ	I
    //   99: iload_1
    //   100: iconst_2
    //   101: irem
    //   102: ifne +6 -> 108
    //   105: goto -58 -> 47
    //   108: goto -74 -> 34
    //   111: aload_0
    //   112: invokevirtual 323	o/IC:ˏ	()Landroid/content/Context;
    //   115: invokestatic 517	o/Ic:ˏ	(Landroid/content/Context;)Lo/Ic;
    //   118: invokevirtual 520	o/Ic:ˊ	()Lo/j;
    //   121: bipush 10
    //   123: invokevirtual 524	o/j:ˎ	(I)V
    //   126: goto +6 -> 132
    //   129: astore_2
    //   130: aload_2
    //   131: athrow
    //   132: return
    //   133: iconst_1
    //   134: istore_1
    //   135: goto -132 -> 3
    //   138: iconst_0
    //   139: istore_1
    //   140: goto -137 -> 3
    // Local variable table:
    //   start	length	slot	name	signature
    //   0	143	0	this	IC
    //   3	137	1	i	int
    //   81	2	2	localException1	Exception
    //   129	2	2	localException2	Exception
    // Exception table:
    //   from	to	target	type
    //   54	61	81	java/lang/Exception
    //   61	69	81	java/lang/Exception
    //   61	69	129	java/lang/Exception
  }
  
  /* Error */
  public void ˎ(int paramInt, ᐸ.ˏ paramˏ)
  {
    // Byte code:
    //   0: goto +247 -> 247
    //   3: bipush 78
    //   5: istore_3
    //   6: goto +210 -> 216
    //   9: aload_2
    //   10: bipush 22
    //   12: sipush 11144
    //   15: bipush 117
    //   17: invokestatic 301	o/IC:ˊ	(ICI)Ljava/lang/String;
    //   20: invokevirtual 305	java/lang/String:intern	()Ljava/lang/String;
    //   23: invokestatic 527	o/vq:ˎ	(Ljava/lang/Object;Ljava/lang/String;)V
    //   26: aload_0
    //   27: invokevirtual 323	o/IC:ˏ	()Landroid/content/Context;
    //   30: ifnull +6 -> 36
    //   33: goto +93 -> 126
    //   36: goto +435 -> 471
    //   39: astore_2
    //   40: aload_2
    //   41: athrow
    //   42: aload 7
    //   44: aload 5
    //   46: checkcast 479	java/lang/CharSequence
    //   49: invokevirtual 484	o/ᐸ$If:ˊ	(Ljava/lang/CharSequence;)Lo/ᐸ$If;
    //   52: iload_1
    //   53: invokevirtual 530	o/ᐸ$If:ˊ	(I)Lo/ᐸ$If;
    //   56: astore 7
    //   58: aload_0
    //   59: invokevirtual 323	o/IC:ˏ	()Landroid/content/Context;
    //   62: getstatic 533	o/Gu$ˏ:ok	I
    //   65: invokevirtual 379	android/content/Context:getString	(I)Ljava/lang/String;
    //   68: astore 6
    //   70: aload 6
    //   72: bipush 21
    //   74: ldc_w 380
    //   77: iconst_4
    //   78: invokestatic 301	o/IC:ˊ	(ICI)Ljava/lang/String;
    //   81: invokevirtual 305	java/lang/String:intern	()Ljava/lang/String;
    //   84: invokevirtual 384	java/lang/String:startsWith	(Ljava/lang/String;)Z
    //   87: ifeq +6 -> 93
    //   90: goto +244 -> 334
    //   93: goto +379 -> 472
    //   96: aload_2
    //   97: bipush 119
    //   99: sipush 11144
    //   102: bipush 8
    //   104: invokestatic 301	o/IC:ˊ	(ICI)Ljava/lang/String;
    //   107: invokevirtual 305	java/lang/String:intern	()Ljava/lang/String;
    //   110: invokestatic 527	o/vq:ˎ	(Ljava/lang/Object;Ljava/lang/String;)V
    //   113: aload_0
    //   114: invokevirtual 323	o/IC:ˏ	()Landroid/content/Context;
    //   117: ifnull +6 -> 123
    //   120: goto +6 -> 126
    //   123: goto +348 -> 471
    //   126: new 481	o/ᐸ$If
    //   129: dup
    //   130: aload_0
    //   131: invokevirtual 323	o/IC:ˏ	()Landroid/content/Context;
    //   134: invokespecial 488	o/ᐸ$If:<init>	(Landroid/content/Context;)V
    //   137: astore 7
    //   139: aload_0
    //   140: invokevirtual 323	o/IC:ˏ	()Landroid/content/Context;
    //   143: astore 5
    //   145: getstatic 536	o/Gu$ˏ:initialization_failed_title	I
    //   148: istore_3
    //   149: aload 5
    //   151: iload_3
    //   152: invokevirtual 379	android/content/Context:getString	(I)Ljava/lang/String;
    //   155: astore 6
    //   157: aload 6
    //   159: bipush 21
    //   161: ldc_w 380
    //   164: iconst_4
    //   165: invokestatic 301	o/IC:ˊ	(ICI)Ljava/lang/String;
    //   168: invokevirtual 305	java/lang/String:intern	()Ljava/lang/String;
    //   171: invokevirtual 384	java/lang/String:startsWith	(Ljava/lang/String;)Z
    //   174: istore 4
    //   176: iload 4
    //   178: ifeq +6 -> 184
    //   181: goto +142 -> 323
    //   184: goto +187 -> 371
    //   187: getstatic 27	o/IC:ˋ	I
    //   190: iconst_1
    //   191: iadd
    //   192: istore_3
    //   193: iload_3
    //   194: sipush 128
    //   197: irem
    //   198: putstatic 29	o/IC:ʻ	I
    //   201: iload_3
    //   202: iconst_2
    //   203: irem
    //   204: ifne +6 -> 210
    //   207: goto +107 -> 314
    //   210: bipush 24
    //   212: istore_3
    //   213: goto +129 -> 342
    //   216: iload_3
    //   217: lookupswitch	default:+27->244, 78:+162->379, 97:+203->420
    //   244: goto +176 -> 420
    //   247: goto -60 -> 187
    //   250: aload 6
    //   252: astore 5
    //   254: iload_3
    //   255: tableswitch	default:+21->276, 0:+-213->42, 1:+250->505
    //   276: aload 6
    //   278: astore 5
    //   280: goto -238 -> 42
    //   283: aload 7
    //   285: aload 5
    //   287: checkcast 479	java/lang/CharSequence
    //   290: invokevirtual 503	o/ᐸ$If:ॱ	(Ljava/lang/CharSequence;)Lo/ᐸ$If;
    //   293: new 8	o/IC$If
    //   296: dup
    //   297: aload_2
    //   298: invokespecial 539	o/IC$If:<init>	(Lo/ᐸ$ˏ;)V
    //   301: checkcast 508	o/ᐸ$ˏ
    //   304: invokevirtual 541	o/ᐸ$If:ˊ	(Lo/ᐸ$ˏ;)Lo/ᐸ$If;
    //   307: invokevirtual 512	o/ᐸ$If:ˏ	()Lo/ᐸ;
    //   310: pop
    //   311: goto +160 -> 471
    //   314: bipush 45
    //   316: istore_3
    //   317: goto +25 -> 342
    //   320: goto -37 -> 283
    //   323: iconst_1
    //   324: istore_3
    //   325: goto -75 -> 250
    //   328: bipush 97
    //   330: istore_3
    //   331: goto -115 -> 216
    //   334: iconst_0
    //   335: istore_1
    //   336: goto +102 -> 438
    //   339: astore_2
    //   340: aload_2
    //   341: athrow
    //   342: iload_3
    //   343: lookupswitch	default:+25->368, 24:+-247->96, 45:+-334->9
    //   368: goto -272 -> 96
    //   371: iconst_0
    //   372: istore_3
    //   373: goto -123 -> 250
    //   376: goto -56 -> 320
    //   379: aload_0
    //   380: aload 6
    //   382: iconst_4
    //   383: invokevirtual 396	java/lang/String:substring	(I)Ljava/lang/String;
    //   386: invokespecial 398	o/IC:ॱ	(Ljava/lang/String;)Ljava/lang/String;
    //   389: invokevirtual 305	java/lang/String:intern	()Ljava/lang/String;
    //   392: astore 5
    //   394: bipush 98
    //   396: iconst_0
    //   397: idiv
    //   398: istore_3
    //   399: goto -357 -> 42
    //   402: aload_0
    //   403: aload 6
    //   405: iconst_4
    //   406: invokevirtual 396	java/lang/String:substring	(I)Ljava/lang/String;
    //   409: invokespecial 398	o/IC:ॱ	(Ljava/lang/String;)Ljava/lang/String;
    //   412: invokevirtual 305	java/lang/String:intern	()Ljava/lang/String;
    //   415: astore 5
    //   417: goto +61 -> 478
    //   420: aload_0
    //   421: aload 6
    //   423: iconst_4
    //   424: invokevirtual 396	java/lang/String:substring	(I)Ljava/lang/String;
    //   427: invokespecial 398	o/IC:ॱ	(Ljava/lang/String;)Ljava/lang/String;
    //   430: invokevirtual 305	java/lang/String:intern	()Ljava/lang/String;
    //   433: astore 5
    //   435: goto -393 -> 42
    //   438: aload 6
    //   440: astore 5
    //   442: iload_1
    //   443: lookupswitch	default:+25->468, 0:+-41->402, 45:+-160->283
    //   468: goto -66 -> 402
    //   471: return
    //   472: bipush 45
    //   474: istore_1
    //   475: goto -37 -> 438
    //   478: getstatic 29	o/IC:ʻ	I
    //   481: bipush 125
    //   483: iadd
    //   484: istore_1
    //   485: iload_1
    //   486: sipush 128
    //   489: irem
    //   490: putstatic 27	o/IC:ˋ	I
    //   493: iload_1
    //   494: iconst_2
    //   495: irem
    //   496: ifeq +6 -> 502
    //   499: goto -123 -> 376
    //   502: goto -182 -> 320
    //   505: getstatic 27	o/IC:ˋ	I
    //   508: bipush 33
    //   510: iadd
    //   511: istore_3
    //   512: iload_3
    //   513: sipush 128
    //   516: irem
    //   517: putstatic 29	o/IC:ʻ	I
    //   520: iload_3
    //   521: iconst_2
    //   522: irem
    //   523: ifne +6 -> 529
    //   526: goto -523 -> 3
    //   529: goto -201 -> 328
    // Local variable table:
    //   start	length	slot	name	signature
    //   0	532	0	this	IC
    //   0	532	1	paramInt	int
    //   0	532	2	paramˏ	ᐸ.ˏ
    //   5	518	3	i	int
    //   174	3	4	bool	boolean
    //   44	397	5	localObject	Object
    //   68	371	6	str	String
    //   42	242	7	localIf	ᐸ.If
    // Exception table:
    //   from	to	target	type
    //   126	139	39	java/lang/Exception
    //   139	145	39	java/lang/Exception
    //   145	149	39	java/lang/Exception
    //   149	157	39	java/lang/Exception
    //   157	176	39	java/lang/Exception
    //   139	145	339	java/lang/Exception
  }
  
  /* Error */
  public void ˎ(DialogInterface.OnCancelListener paramOnCancelListener)
  {
    // Byte code:
    //   0: goto +103 -> 103
    //   3: new 544	o/IN
    //   6: dup
    //   7: aload_0
    //   8: invokevirtual 323	o/IC:ˏ	()Landroid/content/Context;
    //   11: bipush 11
    //   13: invokespecial 545	o/IN:<init>	(Landroid/content/Context;I)V
    //   16: astore_3
    //   17: new 10	o/IC$iF
    //   20: dup
    //   21: aload_1
    //   22: invokespecial 547	o/IC$iF:<init>	(Landroid/content/DialogInterface$OnCancelListener;)V
    //   25: astore_1
    //   26: aload_1
    //   27: checkcast 549	android/content/DialogInterface$OnCancelListener
    //   30: astore_1
    //   31: aload_3
    //   32: aload_1
    //   33: invokevirtual 552	o/IN:ˎ	(Landroid/content/DialogInterface$OnCancelListener;)Lo/ᐸ$If;
    //   36: astore_1
    //   37: aload_1
    //   38: invokevirtual 512	o/ᐸ$If:ˏ	()Lo/ᐸ;
    //   41: pop
    //   42: goto +8 -> 50
    //   45: iconst_1
    //   46: istore_2
    //   47: goto +30 -> 77
    //   50: getstatic 29	o/IC:ʻ	I
    //   53: bipush 121
    //   55: iadd
    //   56: istore_2
    //   57: iload_2
    //   58: sipush 128
    //   61: irem
    //   62: putstatic 27	o/IC:ˋ	I
    //   65: iload_2
    //   66: iconst_2
    //   67: irem
    //   68: ifeq +6 -> 74
    //   71: goto +120 -> 191
    //   74: goto +117 -> 191
    //   77: iload_2
    //   78: tableswitch	default:+22->100, 0:+52->130, 1:+78->156
    //   100: goto +56 -> 156
    //   103: getstatic 27	o/IC:ˋ	I
    //   106: bipush 85
    //   108: iadd
    //   109: istore_2
    //   110: iload_2
    //   111: sipush 128
    //   114: irem
    //   115: putstatic 29	o/IC:ʻ	I
    //   118: iload_2
    //   119: iconst_2
    //   120: irem
    //   121: ifne +6 -> 127
    //   124: goto -79 -> 45
    //   127: goto +59 -> 186
    //   130: aload_1
    //   131: bipush 105
    //   133: iconst_0
    //   134: bipush 14
    //   136: invokestatic 301	o/IC:ˊ	(ICI)Ljava/lang/String;
    //   139: invokevirtual 305	java/lang/String:intern	()Ljava/lang/String;
    //   142: invokestatic 527	o/vq:ˎ	(Ljava/lang/Object;Ljava/lang/String;)V
    //   145: aload_0
    //   146: invokevirtual 323	o/IC:ˏ	()Landroid/content/Context;
    //   149: ifnull +6 -> 155
    //   152: goto -149 -> 3
    //   155: return
    //   156: aload_1
    //   157: iconst_0
    //   158: iconst_0
    //   159: bipush 7
    //   161: invokestatic 301	o/IC:ˊ	(ICI)Ljava/lang/String;
    //   164: invokevirtual 305	java/lang/String:intern	()Ljava/lang/String;
    //   167: invokestatic 527	o/vq:ˎ	(Ljava/lang/Object;Ljava/lang/String;)V
    //   170: aload_0
    //   171: invokevirtual 323	o/IC:ˏ	()Landroid/content/Context;
    //   174: astore_3
    //   175: aload_3
    //   176: ifnull +6 -> 182
    //   179: goto -176 -> 3
    //   182: return
    //   183: astore_1
    //   184: aload_1
    //   185: athrow
    //   186: iconst_0
    //   187: istore_2
    //   188: goto -111 -> 77
    //   191: return
    //   192: astore_1
    //   193: aload_1
    //   194: athrow
    // Local variable table:
    //   start	length	slot	name	signature
    //   0	195	0	this	IC
    //   0	195	1	paramOnCancelListener	DialogInterface.OnCancelListener
    //   46	142	2	i	int
    //   16	160	3	localObject	Object
    // Exception table:
    //   from	to	target	type
    //   3	26	183	java/lang/Exception
    //   26	31	183	java/lang/Exception
    //   31	37	183	java/lang/Exception
    //   37	42	183	java/lang/Exception
    //   156	175	183	java/lang/Exception
    //   26	31	192	java/lang/Exception
  }
  
  public void ˎ(Fd paramFd)
  {
    break label116;
    Object localObject1 = paramFd.userMessage;
    vq.ˋ(localObject1, ˊ(25, 39180, 19).intern());
    break label611;
    label30:
    break label621;
    label33:
    int i = 88;
    break label229;
    paramFd = paramFd.code;
    break label530;
    label47:
    Object localObject2;
    label76:
    label111:
    label116:
    label119:
    label172:
    String str;
    for (;;)
    {
      try
      {
        localObject2 = EF.BTW_OTP_ENTER_EXPIRED_OTP;
        try
        {
          localObject2 = ((EF)localObject2).ˏ();
          boolean bool = vq.ˊ(paramFd, localObject2);
          if (!bool)
          {
            continue;
            localObject1 = localObject2;
            switch (i)
            {
            default: 
              localObject1 = localObject2;
              break label509;
              i = 0;
              continue;
              break label489;
              break label530;
              continue;
              localObject1 = (CharSequence)localObject1;
              if (localObject1 != null) {
                break label549;
              }
              break label33;
              if (paramFd == null)
              {
                break label605;
                if (vq.ˊ(paramFd, EF.BTW_OTP_ENTER_EXCEEDED_THRESHOLD.ˏ())) {
                  break label621;
                }
                continue;
                str = ˏ().getString(Gu.ˏ.oops);
                if (!str.startsWith(ˊ(21, 44385, 4).intern()))
                {
                  continue;
                  if (((CharSequence)localObject1).length() != 0)
                  {
                    break label689;
                    continue;
                    switch (i)
                    {
                    case 22: 
                    default: 
                      label229:
                      continue;
                      i = 94;
                    }
                  }
                }
              }
              break;
            }
          }
        }
        catch (Exception paramFd)
        {
          throw paramFd;
        }
      }
      catch (Exception paramFd)
      {
        label268:
        label298:
        label304:
        label361:
        throw paramFd;
      }
      switch (i)
      {
      case 1: 
      default: 
        break label504;
        continue;
        vq.ˎ();
        continue;
        i = ˋ + 47;
        ʻ = i % 128;
        if (i % 2 != 0)
        {
          continue;
          i = 1;
          continue;
          vq.ˋ(str, ˊ(89, '\000', 16).intern());
          ˎ(str, (String)localObject1);
          return;
          i = ˋ + 75;
          ʻ = i % 128;
          if (i % 2 == 0) {
            continue;
          }
          continue;
          i = ˋ + 5;
          ʻ = i % 128;
          if (i % 2 != 0)
          {
            i = 33;
            break label555;
            localObject1 = ॱ(((String)localObject2).substring(4)).intern();
            break label509;
            break label621;
            str = ॱ(str.substring(4)).intern();
            continue;
            localObject1 = paramFd.userMessage;
          }
        }
        break;
      }
    }
    for (;;)
    {
      if (i != 0)
      {
        break label646;
        break label172;
        label478:
        i = 1;
        break label268;
        break;
        label489:
        localObject1 = ˏ();
        if (localObject1 != null) {
          break label361;
        }
        return;
        label504:
        paramFd = null;
        break label119;
        label509:
        vq.ˋ(localObject1, ˊ(44, 40390, 45).intern());
        break label611;
        label530:
        if (vq.ˊ(paramFd, EF.BTW_OTP_INCORRECT_ENTERED_OTP.ˏ())) {
          break label30;
        }
        break label47;
        label549:
        i = 22;
        break label229;
      }
      switch (i)
      {
      case 33: 
      default: 
        label555:
        break label602;
        if (paramFd == null) {
          break label298;
        }
        break;
      }
      label602:
      label605:
      label611:
      label621:
      label646:
      do
      {
        i = 1;
        break label76;
        break;
        localObject1 = null;
        break label304;
        if (paramFd != null) {
          break label478;
        }
        break label684;
        vq.ˋ(str, ˊ(89, '\000', 16).intern());
        ˎ(str, (String)localObject1);
        return;
        localObject2 = ˏ().getString(Gu.ˏ.an_error_occurred);
      } while (((String)localObject2).startsWith(ˊ(21, 44385, 4).intern()));
      break label111;
      label684:
      i = 0;
      break label268;
      label689:
      i = 0;
    }
  }
  
  public void ˏ(String paramString)
  {
    break label135;
    label55:
    label63:
    for (;;)
    {
      i = ʻ + 49;
      ˋ = i % 128;
      if (i % 2 == 0)
      {
        break;
        new IE(ˏ(), paramString).ˏ();
      }
      else
      {
        i = 36;
        break label103;
        throw new NullPointerException();
      }
    }
    label66:
    break label76;
    return;
    int i = 22;
    for (;;)
    {
      label76:
      vq.ˎ(paramString, ˊ(0, '\000', 21).intern());
      if (ˏ() != null) {
        break;
      }
      break label63;
      label103:
      switch (i)
      {
      }
      break label55;
      label135:
      i = ʻ + 39;
      ˋ = i % 128;
      if (i % 2 != 0) {
        break label66;
      }
    }
  }
  
  static final class If
    implements ᐸ.ˏ
  {
    private static long ˊ = 1422888802071354673L;
    private static int ˎ = 0;
    private static int ˏ = 1;
    
    If(ᐸ.ˏ paramˏ) {}
    
    private static String ˏ(char[] paramArrayOfChar)
    {
      break label139;
      int i;
      char[] arrayOfChar;
      int k;
      int j;
      for (;;)
      {
        i = 0;
        break label150;
        for (;;)
        {
          arrayOfChar[(i + 1)] = ((char)(int)(paramArrayOfChar[i] | i / k | ˊ));
          i += 28;
          break label142;
          return paramArrayOfChar;
          try
          {
            j = ˎ;
            j += 71;
            ˏ = j % 128;
            if (j % 2 == 0) {}
          }
          catch (Exception paramArrayOfChar)
          {
            throw paramArrayOfChar;
          }
        }
        if (i < paramArrayOfChar.length) {
          break label145;
        }
        break label174;
        label82:
        i = ˏ + 73;
        ˎ = i % 128;
        if (i % 2 != 0) {
          break label203;
        }
      }
      label126:
      label139:
      for (;;)
      {
        k = paramArrayOfChar[0];
        arrayOfChar = new char[paramArrayOfChar.length - 1];
        i = 1;
        break;
        paramArrayOfChar = new String(arrayOfChar);
        break label82;
      }
      for (;;)
      {
        label142:
        break;
        label145:
        j = 1;
        for (;;)
        {
          switch (i)
          {
          case 0: 
          default: 
            label150:
            return paramArrayOfChar;
            label174:
            j = 0;
            switch (j)
            {
            }
            break label126;
            label203:
            i = 1;
          }
        }
        throw new NullPointerException();
        arrayOfChar[(i - 1)] = ((char)(int)(paramArrayOfChar[i] ^ i * k ^ ˊ));
        i += 1;
      }
    }
    
    public final void ˋ(ᐸ paramᐸ, ะ paramะ)
    {
      for (;;)
      {
        switch (i)
        {
        default: 
          break;
        case 29: 
          for (;;)
          {
            i = ˎ + 101;
            ˏ = i % 128;
            if (i % 2 != 0)
            {
              break label177;
              vq.ˎ(paramᐸ, ˏ(new char[] { -21783, -18500, 18570, 7659, -18695, 19411, 7200 }).intern());
              vq.ˎ(paramะ, ˏ(new char[] { -27705, -29055, 15063, -23027, 21070, -70 }).intern());
              this.ॱ.ˋ(paramᐸ, paramะ);
              return;
            }
            i = 82;
            break;
          }
          label177:
          i = 29;
        }
      }
      vq.ˎ(paramᐸ, ˏ(new char[] { -21783, -18500, 18570, 7659, -18695, 19411, 7200 }).intern());
      vq.ˎ(paramะ, ˏ(new char[] { -27705, -29055, 15063, -23027, 21070, -70 }).intern());
      this.ॱ.ˋ(paramᐸ, paramะ);
      int i = 22 / 0;
    }
  }
  
  static final class iF
    implements DialogInterface.OnCancelListener
  {
    iF(DialogInterface.OnCancelListener paramOnCancelListener) {}
    
    public final void onCancel(DialogInterface paramDialogInterface)
    {
      this.ˏ.onCancel(paramDialogInterface);
    }
  }
  
  static final class ˊ
    implements ᐸ.ˏ
  {
    private static char[] ˊ = { 105, 228, 253, 260, 260, 265, 265, 260, 264, 266, 223, 222, 254, 255, 255, 253, 255, 258, 258, 257, 223, 190, 205, 30, 78, 103, 110, 110, 115, 115, 110, 114, 116, 73, 72, 104, 105, 105, 103, 105, 108, 108, 107, 73, 40, 55 };
    private static int ˋ;
    private static int ॱ = 0;
    
    static
    {
      ˋ = 1;
    }
    
    ˊ(IC paramIC) {}
    
    /* Error */
    private static String ˋ(int[] paramArrayOfInt, byte[] paramArrayOfByte, boolean paramBoolean)
    {
      // Byte code:
      //   0: goto +167 -> 167
      //   3: aload_1
      //   4: iload_3
      //   5: aload 9
      //   7: iload 6
      //   9: iload_3
      //   10: isub
      //   11: iconst_1
      //   12: isub
      //   13: caload
      //   14: castore
      //   15: iload_3
      //   16: iconst_1
      //   17: iadd
      //   18: istore_3
      //   19: goto +55 -> 74
      //   22: aload 9
      //   24: iload_3
      //   25: aload 10
      //   27: iload_3
      //   28: caload
      //   29: iconst_1
      //   30: ishl
      //   31: iload 4
      //   33: isub
      //   34: i2c
      //   35: castore
      //   36: goto +410 -> 446
      //   39: astore_0
      //   40: aload_0
      //   41: athrow
      //   42: bipush 62
      //   44: istore_3
      //   45: goto +156 -> 201
      //   48: goto +428 -> 476
      //   51: iload_2
      //   52: ifeq +6 -> 58
      //   55: goto +237 -> 292
      //   58: aload 9
      //   60: astore_1
      //   61: goto +426 -> 487
      //   64: bipush 72
      //   66: istore 5
      //   68: goto +492 -> 560
      //   71: goto +21 -> 92
      //   74: iload_3
      //   75: iload 6
      //   77: if_icmpge +6 -> 83
      //   80: goto -77 -> 3
      //   83: goto +360 -> 443
      //   86: bipush 87
      //   88: istore_3
      //   89: goto +112 -> 201
      //   92: iload 6
      //   94: newarray char
      //   96: astore_1
      //   97: aload 9
      //   99: iconst_0
      //   100: aload_1
      //   101: iconst_0
      //   102: iload 6
      //   104: invokestatic 69	java/lang/System:arraycopy	(Ljava/lang/Object;ILjava/lang/Object;II)V
      //   107: aload_1
      //   108: iconst_0
      //   109: aload 9
      //   111: iload 6
      //   113: iload 8
      //   115: isub
      //   116: iload 8
      //   118: invokestatic 69	java/lang/System:arraycopy	(Ljava/lang/Object;ILjava/lang/Object;II)V
      //   121: aload_1
      //   122: iload 8
      //   124: aload 9
      //   126: iconst_0
      //   127: iload 6
      //   129: iload 8
      //   131: isub
      //   132: invokestatic 69	java/lang/System:arraycopy	(Ljava/lang/Object;ILjava/lang/Object;II)V
      //   135: goto -84 -> 51
      //   138: goto +32 -> 170
      //   141: iload 6
      //   143: newarray char
      //   145: astore 9
      //   147: iconst_0
      //   148: istore 4
      //   150: iconst_0
      //   151: istore_3
      //   152: goto +28 -> 180
      //   155: iconst_0
      //   156: istore_3
      //   157: goto +148 -> 305
      //   160: bipush 14
      //   162: istore 5
      //   164: goto +183 -> 347
      //   167: goto +212 -> 379
      //   170: aload 9
      //   172: iload_3
      //   173: caload
      //   174: istore 4
      //   176: iload_3
      //   177: iconst_1
      //   178: iadd
      //   179: istore_3
      //   180: iload_3
      //   181: iload 6
      //   183: if_icmpge +6 -> 189
      //   186: goto -122 -> 64
      //   189: goto +361 -> 550
      //   192: new 71	java/lang/String
      //   195: dup
      //   196: aload_1
      //   197: invokespecial 74	java/lang/String:<init>	([C)V
      //   200: areturn
      //   201: aload 10
      //   203: astore 9
      //   205: iload_3
      //   206: lookupswitch	default:+26->232, 62:+-65->141, 87:+270->476
      //   232: goto -91 -> 141
      //   235: aload 9
      //   237: iload_3
      //   238: aload 10
      //   240: iload_3
      //   241: caload
      //   242: iconst_1
      //   243: ishl
      //   244: iconst_1
      //   245: iadd
      //   246: iload 4
      //   248: isub
      //   249: i2c
      //   250: castore
      //   251: goto +51 -> 302
      //   254: getstatic 22	o/IC$ˊ:ˋ	I
      //   257: bipush 47
      //   259: iadd
      //   260: istore_3
      //   261: iload_3
      //   262: sipush 128
      //   265: irem
      //   266: putstatic 20	o/IC$ˊ:ॱ	I
      //   269: iload_3
      //   270: iconst_2
      //   271: irem
      //   272: ifeq +6 -> 278
      //   275: goto -204 -> 71
      //   278: goto -186 -> 92
      //   281: goto -143 -> 138
      //   284: astore_0
      //   285: aload_0
      //   286: athrow
      //   287: iconst_1
      //   288: istore_3
      //   289: goto +30 -> 319
      //   292: iload 6
      //   294: newarray char
      //   296: astore_1
      //   297: iconst_0
      //   298: istore_3
      //   299: goto -225 -> 74
      //   302: goto -132 -> 170
      //   305: iload_3
      //   306: iload 6
      //   308: if_icmpge +6 -> 314
      //   311: goto +187 -> 498
      //   314: goto -122 -> 192
      //   317: iconst_0
      //   318: istore_3
      //   319: iload_3
      //   320: tableswitch	default:+24->344, 0:+-66->254, 1:+-269->51
      //   344: goto -90 -> 254
      //   347: iload 5
      //   349: lookupswitch	default:+27->376, 14:+-327->22, 76:+-114->235
      //   376: goto -141 -> 235
      //   379: aload_0
      //   380: iconst_0
      //   381: iaload
      //   382: istore_3
      //   383: aload_0
      //   384: iconst_1
      //   385: iaload
      //   386: istore 6
      //   388: aload_0
      //   389: iconst_2
      //   390: iaload
      //   391: istore 7
      //   393: aload_0
      //   394: iconst_3
      //   395: iaload
      //   396: istore 8
      //   398: getstatic 53	o/IC$ˊ:ˊ	[C
      //   401: astore 9
      //   403: iload 6
      //   405: newarray char
      //   407: astore 10
      //   409: aload 9
      //   411: iload_3
      //   412: aload 10
      //   414: iconst_0
      //   415: iload 6
      //   417: invokestatic 69	java/lang/System:arraycopy	(Ljava/lang/Object;ILjava/lang/Object;II)V
      //   420: aload_1
      //   421: ifnull +6 -> 427
      //   424: goto -382 -> 42
      //   427: goto -341 -> 86
      //   430: aload_1
      //   431: iload_3
      //   432: baload
      //   433: iconst_1
      //   434: if_icmpne +6 -> 440
      //   437: goto +79 -> 516
      //   440: goto -280 -> 160
      //   443: goto +44 -> 487
      //   446: getstatic 22	o/IC$ˊ:ˋ	I
      //   449: bipush 67
      //   451: iadd
      //   452: istore 4
      //   454: iload 4
      //   456: sipush 128
      //   459: irem
      //   460: putstatic 20	o/IC$ˊ:ॱ	I
      //   463: iload 4
      //   465: iconst_2
      //   466: irem
      //   467: ifeq +6 -> 473
      //   470: goto -189 -> 281
      //   473: goto -335 -> 138
      //   476: iload 8
      //   478: ifle +6 -> 484
      //   481: goto -164 -> 317
      //   484: goto -197 -> 287
      //   487: iload 7
      //   489: ifle +6 -> 495
      //   492: goto +31 -> 523
      //   495: goto -303 -> 192
      //   498: aload_1
      //   499: iload_3
      //   500: aload_1
      //   501: iload_3
      //   502: caload
      //   503: aload_0
      //   504: iconst_2
      //   505: iaload
      //   506: isub
      //   507: i2c
      //   508: castore
      //   509: iload_3
      //   510: iconst_1
      //   511: iadd
      //   512: istore_3
      //   513: goto -208 -> 305
      //   516: bipush 76
      //   518: istore 5
      //   520: goto -173 -> 347
      //   523: getstatic 22	o/IC$ˊ:ˋ	I
      //   526: bipush 73
      //   528: iadd
      //   529: istore_3
      //   530: iload_3
      //   531: sipush 128
      //   534: irem
      //   535: putstatic 20	o/IC$ˊ:ॱ	I
      //   538: iload_3
      //   539: iconst_2
      //   540: irem
      //   541: ifeq +6 -> 547
      //   544: goto +13 -> 557
      //   547: goto -392 -> 155
      //   550: bipush 43
      //   552: istore 5
      //   554: goto +6 -> 560
      //   557: goto -402 -> 155
      //   560: iload 5
      //   562: lookupswitch	default:+26->588, 43:+-514->48, 72:+-132->430
      //   588: goto -540 -> 48
      // Local variable table:
      //   start	length	slot	name	signature
      //   0	591	0	paramArrayOfInt	int[]
      //   0	591	1	paramArrayOfByte	byte[]
      //   0	591	2	paramBoolean	boolean
      //   4	537	3	i	int
      //   31	436	4	j	int
      //   66	495	5	k	int
      //   7	409	6	m	int
      //   391	97	7	n	int
      //   113	364	8	i1	int
      //   5	405	9	localObject	Object
      //   25	388	10	arrayOfChar	char[]
      // Exception table:
      //   from	to	target	type
      //   261	269	39	java/lang/Exception
      //   254	261	284	java/lang/Exception
      //   261	269	284	java/lang/Exception
    }
    
    /* Error */
    public final void ˋ(ᐸ arg1, ะ arg2)
    {
      // Byte code:
      //   0: goto +81 -> 81
      //   3: getstatic 22	o/IC$ˊ:ˋ	I
      //   6: bipush 89
      //   8: iadd
      //   9: istore_3
      //   10: iload_3
      //   11: sipush 128
      //   14: irem
      //   15: putstatic 20	o/IC$ˊ:ॱ	I
      //   18: iload_3
      //   19: iconst_2
      //   20: irem
      //   21: ifeq +6 -> 27
      //   24: goto +434 -> 458
      //   27: goto +60 -> 87
      //   30: new 77	java/lang/NullPointerException
      //   33: dup
      //   34: invokespecial 78	java/lang/NullPointerException:<init>	()V
      //   37: athrow
      //   38: iload_3
      //   39: lookupswitch	default:+25->64, 40:+35->74, 80:+-9->30
      //   64: return
      //   65: astore_1
      //   66: aload_1
      //   67: athrow
      //   68: bipush 80
      //   70: istore_3
      //   71: goto -33 -> 38
      //   74: return
      //   75: bipush 40
      //   77: istore_3
      //   78: goto -40 -> 38
      //   81: goto -78 -> 3
      //   84: astore_1
      //   85: aload_1
      //   86: athrow
      //   87: iconst_4
      //   88: newarray int
      //   90: dup
      //   91: iconst_0
      //   92: iconst_0
      //   93: iastore
      //   94: dup
      //   95: iconst_1
      //   96: bipush 23
      //   98: iastore
      //   99: dup
      //   100: iconst_2
      //   101: sipush 150
      //   104: iastore
      //   105: dup
      //   106: iconst_3
      //   107: iconst_0
      //   108: iastore
      //   109: bipush 23
      //   111: newarray byte
      //   113: dup
      //   114: iconst_0
      //   115: ldc 79
      //   117: bastore
      //   118: dup
      //   119: iconst_1
      //   120: ldc 80
      //   122: bastore
      //   123: dup
      //   124: iconst_2
      //   125: ldc 80
      //   127: bastore
      //   128: dup
      //   129: iconst_3
      //   130: ldc 80
      //   132: bastore
      //   133: dup
      //   134: iconst_4
      //   135: ldc 80
      //   137: bastore
      //   138: dup
      //   139: iconst_5
      //   140: ldc 80
      //   142: bastore
      //   143: dup
      //   144: bipush 6
      //   146: ldc 79
      //   148: bastore
      //   149: dup
      //   150: bipush 7
      //   152: ldc 79
      //   154: bastore
      //   155: dup
      //   156: bipush 8
      //   158: ldc 79
      //   160: bastore
      //   161: dup
      //   162: bipush 9
      //   164: ldc 79
      //   166: bastore
      //   167: dup
      //   168: bipush 10
      //   170: ldc 80
      //   172: bastore
      //   173: dup
      //   174: bipush 11
      //   176: ldc 79
      //   178: bastore
      //   179: dup
      //   180: bipush 12
      //   182: ldc 80
      //   184: bastore
      //   185: dup
      //   186: bipush 13
      //   188: ldc 80
      //   190: bastore
      //   191: dup
      //   192: bipush 14
      //   194: ldc 80
      //   196: bastore
      //   197: dup
      //   198: bipush 15
      //   200: ldc 79
      //   202: bastore
      //   203: dup
      //   204: bipush 16
      //   206: ldc 79
      //   208: bastore
      //   209: dup
      //   210: bipush 17
      //   212: ldc 80
      //   214: bastore
      //   215: dup
      //   216: bipush 18
      //   218: ldc 80
      //   220: bastore
      //   221: dup
      //   222: bipush 19
      //   224: ldc 80
      //   226: bastore
      //   227: dup
      //   228: bipush 20
      //   230: ldc 79
      //   232: bastore
      //   233: dup
      //   234: bipush 21
      //   236: ldc 79
      //   238: bastore
      //   239: dup
      //   240: bipush 22
      //   242: ldc 79
      //   244: bastore
      //   245: iconst_0
      //   246: invokestatic 82	o/IC$ˊ:ˋ	([I[BZ)Ljava/lang/String;
      //   249: astore 4
      //   251: aload 4
      //   253: invokevirtual 86	java/lang/String:intern	()Ljava/lang/String;
      //   256: astore 4
      //   258: aload_1
      //   259: aload 4
      //   261: invokestatic 92	o/vq:ˎ	(Ljava/lang/Object;Ljava/lang/String;)V
      //   264: aload_2
      //   265: iconst_4
      //   266: newarray int
      //   268: dup
      //   269: iconst_0
      //   270: bipush 23
      //   272: iastore
      //   273: dup
      //   274: iconst_1
      //   275: bipush 23
      //   277: iastore
      //   278: dup
      //   279: iconst_2
      //   280: iconst_0
      //   281: iastore
      //   282: dup
      //   283: iconst_3
      //   284: iconst_0
      //   285: iastore
      //   286: bipush 23
      //   288: newarray byte
      //   290: dup
      //   291: iconst_0
      //   292: ldc 79
      //   294: bastore
      //   295: dup
      //   296: iconst_1
      //   297: ldc 80
      //   299: bastore
      //   300: dup
      //   301: iconst_2
      //   302: ldc 80
      //   304: bastore
      //   305: dup
      //   306: iconst_3
      //   307: ldc 80
      //   309: bastore
      //   310: dup
      //   311: iconst_4
      //   312: ldc 80
      //   314: bastore
      //   315: dup
      //   316: iconst_5
      //   317: ldc 80
      //   319: bastore
      //   320: dup
      //   321: bipush 6
      //   323: ldc 79
      //   325: bastore
      //   326: dup
      //   327: bipush 7
      //   329: ldc 79
      //   331: bastore
      //   332: dup
      //   333: bipush 8
      //   335: ldc 79
      //   337: bastore
      //   338: dup
      //   339: bipush 9
      //   341: ldc 79
      //   343: bastore
      //   344: dup
      //   345: bipush 10
      //   347: ldc 80
      //   349: bastore
      //   350: dup
      //   351: bipush 11
      //   353: ldc 79
      //   355: bastore
      //   356: dup
      //   357: bipush 12
      //   359: ldc 80
      //   361: bastore
      //   362: dup
      //   363: bipush 13
      //   365: ldc 80
      //   367: bastore
      //   368: dup
      //   369: bipush 14
      //   371: ldc 80
      //   373: bastore
      //   374: dup
      //   375: bipush 15
      //   377: ldc 79
      //   379: bastore
      //   380: dup
      //   381: bipush 16
      //   383: ldc 79
      //   385: bastore
      //   386: dup
      //   387: bipush 17
      //   389: ldc 80
      //   391: bastore
      //   392: dup
      //   393: bipush 18
      //   395: ldc 80
      //   397: bastore
      //   398: dup
      //   399: bipush 19
      //   401: ldc 80
      //   403: bastore
      //   404: dup
      //   405: bipush 20
      //   407: ldc 79
      //   409: bastore
      //   410: dup
      //   411: bipush 21
      //   413: ldc 80
      //   415: bastore
      //   416: dup
      //   417: bipush 22
      //   419: ldc 80
      //   421: bastore
      //   422: iconst_0
      //   423: invokestatic 82	o/IC$ˊ:ˋ	([I[BZ)Ljava/lang/String;
      //   426: invokevirtual 86	java/lang/String:intern	()Ljava/lang/String;
      //   429: invokestatic 92	o/vq:ˎ	(Ljava/lang/Object;Ljava/lang/String;)V
      //   432: aload_0
      //   433: getfield 58	o/IC$ˊ:ˏ	Lo/IC;
      //   436: invokevirtual 95	o/IC:ˏ	()Landroid/content/Context;
      //   439: invokestatic 100	o/Ic:ˏ	(Landroid/content/Context;)Lo/Ic;
      //   442: invokevirtual 103	o/Ic:ˋ	()Lo/j;
      //   445: ldc 104
      //   447: invokevirtual 109	o/j:ॱ	(I)Lo/j;
      //   450: bipush 9
      //   452: invokevirtual 112	o/j:ˎ	(I)V
      //   455: goto +6 -> 461
      //   458: goto -371 -> 87
      //   461: getstatic 22	o/IC$ˊ:ˋ	I
      //   464: bipush 31
      //   466: iadd
      //   467: istore_3
      //   468: iload_3
      //   469: sipush 128
      //   472: irem
      //   473: putstatic 20	o/IC$ˊ:ॱ	I
      //   476: iload_3
      //   477: iconst_2
      //   478: irem
      //   479: ifeq +6 -> 485
      //   482: goto -414 -> 68
      //   485: goto -410 -> 75
      // Exception table:
      //   from	to	target	type
      //   87	251	84	java/lang/Exception
      //   251	258	84	java/lang/Exception
      //   258	264	84	java/lang/Exception
      //   264	455	84	java/lang/Exception
    }
  }
}
