package o;

import android.content.ComponentName;
import android.content.Context;
import android.content.Intent;
import android.net.Uri;
import com.insidesecure.hce.MatrixHCEPaymentScheme;

public final class Ic
{
  private static long ˋ;
  private static char[] ˎ;
  private static int ˏ;
  private static byte ॱ;
  private static int ॱॱ;
  private final Context ˊ;
  
  /* Error */
  static
  {
    // Byte code:
    //   0: goto +74 -> 74
    //   3: iload_0
    //   4: tableswitch	default:+24->28, 0:+89->93, 1:+24->28
    //   28: aconst_null
    //   29: arraylength
    //   30: istore_0
    //   31: return
    //   32: iconst_1
    //   33: istore_0
    //   34: goto -31 -> 3
    //   37: astore_1
    //   38: aload_1
    //   39: athrow
    //   40: astore_1
    //   41: aload_1
    //   42: athrow
    //   43: iconst_0
    //   44: istore_0
    //   45: goto -42 -> 3
    //   48: getstatic 21	o/Ic:ˏ	I
    //   51: iconst_5
    //   52: iadd
    //   53: istore_0
    //   54: iload_0
    //   55: sipush 128
    //   58: irem
    //   59: putstatic 23	o/Ic:ॱॱ	I
    //   62: iload_0
    //   63: iconst_2
    //   64: irem
    //   65: ifne +6 -> 71
    //   68: goto -36 -> 32
    //   71: goto -28 -> 43
    //   74: iconst_0
    //   75: putstatic 21	o/Ic:ˏ	I
    //   78: iconst_1
    //   79: putstatic 23	o/Ic:ॱॱ	I
    //   82: invokestatic 26	o/Ic:ˍ	()V
    //   85: bipush -102
    //   87: putstatic 28	o/Ic:ॱ	B
    //   90: goto -42 -> 48
    //   93: return
    // Local variable table:
    //   start	length	slot	name	signature
    //   3	62	0	i	int
    //   37	2	1	localException1	Exception
    //   40	2	1	localException2	Exception
    // Exception table:
    //   from	to	target	type
    //   78	82	37	java/lang/Exception
    //   74	78	40	java/lang/Exception
    //   78	82	40	java/lang/Exception
    //   82	85	40	java/lang/Exception
    //   85	90	40	java/lang/Exception
  }
  
  /* Error */
  private Ic(Context paramContext)
  {
    // Byte code:
    //   0: goto +6 -> 6
    //   3: astore_1
    //   4: aload_1
    //   5: athrow
    //   6: aload_0
    //   7: invokespecial 33	java/lang/Object:<init>	()V
    //   10: aload_0
    //   11: aload_1
    //   12: putfield 35	o/Ic:ˊ	Landroid/content/Context;
    //   15: return
    // Local variable table:
    //   start	length	slot	name	signature
    //   0	16	0	this	Ic
    //   0	16	1	paramContext	Context
    // Exception table:
    //   from	to	target	type
    //   10	15	3	java/lang/Exception
  }
  
  static void ˍ()
  {
    ˋ = 4186484318772330035L;
    ˎ = new char[] { 99, -420, -1013, -1353, -1883, -2415, -2751, -3316, -3588, -4178, -4723, -5036, -5625, -5918, -6472, -7016, -7394, -7925, -8203, -8788, -9262, -9658, -10228, -10527, -11091, -11627, -11942, -12465, -12836, -13436, -13889, -14222, -14804, -15142, -15744, -16196, -16529, -17146, -17455, -18039, -18499, -18828, -19430, -19756, -20344, -20814, -21122, -21736, -22065, -22639, -23117, -23432, -24055, -24378, -24944, -25424, -25748, 99, -420, -1013, -1353, -1883, -2415, -2751, -3316, -3588, -4178, -4723, -5036, -5625, -5918, -6472, -7016, -7394, -7925, -8203, -8788, -9262, -9658, -10228, -10527, -11091, -11627, -11942, -12465, -12836, -13436, -13889, -14222, -14798, -15139, -15723, -16218, -16520, -17136, -17447, -18048, -18506, -18828, -19445, -19775, -20352, -20810, -21122, -21736, -22060, -20873, 20559, 21020, 21721, 22192, 22657, 23391, 23838, 24536, 16826, 17280, 16963, 17438, 104, -432, -1021, -1338, -1875, -2404, -2735, -3318, -3603, -4187, -4726, -5010, -5622, -5898, -6489, -7016, 9800, -10131, -9669, -9006, -8566, -12103, -11395, -10949, -10340, -13902, -13440, -13734, -13284, -12567, -16193, -15741, -15019, -14590, -1543, -1107, -609, -929, -503, -3861, -3413, -2914, -2230, 101, -437, -1006, -1301, -1875, -2400, -2750, -3324, -3615, -4186, -4709, -5025, -5616, -5944, -6487, -7012, -7358, -7929, 101, -437, -1006, -1301, -1875, -2400, -2735, -3324, -3606, -4177, -4703, -5038, -5614, -5919, 114, -420, -952, -1285, -1864, -2419, -2722, -3253, -3608, -4182, -4729, -5089, -5623, -5898, -6466, -7025, -7335, -7909, -8194, -8790, -9319, -9727, -10223, -10512, -11078, -11635, -11961, -12542, -12815, -13335, -13902, -14226, -14811, -15150, -15690, -16227, -16551, -17140, -17417, -17993, -18546, -18878, -19395, -19724, 97, -419, -1022, -1301, -1885, -2410, -2730, -3253, -3594, -4179, -4707, -5089, -5625, -5898, -6472, -7015, -7339, -7922, -8221, -8795, -9315, -9637, -10229, -10502, -11098, -11563, -11953, -12542, -12832, -13394, -13931, -14269, -14770, -15150, -15739, -16211, -16539, -17136, -17444, -18022, -18501, -18845, -19425, -19745, -20349, -20814, -21131, -21735, -22059, -22651, -23113, -23428, -24048, -24357, -21034, 21479, 20903, 22345, 21790, 23333, 22773, 24233, 112, -430, -993, -1292, -1879, -2415, -2746, -23691, 23882, 24349, 23039, 23477, 21895, 22081, 20509, 21242, 14284, -13856, -13404, -12964, -30697, 30251, 29812, 29341, 28885, 32480, 32032, 31549, 31133, 26584, 26108, 25651, 25211, 24719, 28379, 27896, 27496, 26971, 22438, 22012, 21461, 21002, 20561, 24247, 23786, 23236, 22806, 18256, 17841, 97, -419, -1022, -1301, -1885, -2410, -2730, -3253, -3605, -4178, -4726, -5051, -5619, -5895, -6483, -7026, -7394, -7888, -8237, -8803, -9304, -9626, -10196, -10542, -11109, 97, -419, -1022, -1301, -1885, -2410, -2730, -3253, -3605, -4178, -4726, -5051, -5619, -5895, -6483, -7026, -7394, -7888, -8237, -8822, -9303, -9603, -10197, -10559, -11119, -11612, -11907, -12508, -12864, -13421, -13901, -14237, -14809, -15168, 97, -419, -1022, -1301, -1885, -2410, -2730, -3253, -3599, -4187, -4726, -5036, -5622, -5917, -6428, -7012, -7341, -7913, -8193, -8794, -9326, -9727, -10191, -10544, -11130, -11585, -11910, -12498, 116, -426, -994, -1299, -1821, -2417, -2722, -3324, -3599, -4187, -13321, 13768, 14229, 12655, 13090, 15626, 16018, 28604, -28288, -27681, -27338, -26754, -26293, -25973, -25450, -25044, -32648, -32169, -31863, -31273, -30914, -30407, -29883, -29547, -28982, -20423, -19851, -19441, -19017, -18446, -18167, -17572, -17046, 99, -420, -1013, -1353, -1878, -2402, -2735, -3328, -3590, -4188, -4719, -5030, -5558, -5892, -6485, -7031, -7343, -7923, -8201, 32552, -32481, -31982, -31240, -30803, -30249, -30179, -29624, -29005, -28430, -27947, -27875, -27321, -26698, -26144, -25646, -25582, -25086, -24386, -23880, -23334, -23277, -22711, -22083, -21573, 97, -419, -1022, -1301, -1885, -2410, -2730, -3253, -3599, -4187, -4726, -5036, -5622, -5917, -6428, -7012, -7341, -7913, -8193, -8794, -9326, -9727, -10188, -10532, -11123, -11604, 97, -419, -1022, -1301, -1885, -2410, -2730, -3253, -3599, -4187, -4726, -5036, -5622, -5917, -6428, -7012, -7341, -7913, -8193, -8794, -9326, -9727, -10202, -10532, -11127, -11593, 116, -426, -1014, -1373, 98, -441, -1007, -1288, -1888, -2413, -2729, -3311, -3658, -4193, -4687, -5020, -5578, -5944, -6517, -6978, -7324, -7894, -8256, -8832, -9304, -9610, 98, -441, -1007, -1288, -1888, -2413, -2729, -3311, -3658, -4193, -4688, -5006, -5573, -5930, -6519, -6999, -7303, -7883, -8225, -8803, -9307, 98, -441, -1007, -1288, -1888, -2413, -2729, -3311, -3658, -4214, -4678, -5003, -5573, -5945, -6517, -7004, -7299, -7898, -8232, -8803, -9309, -9620, -10205, -10553, -11124, -11612, -11921, -12510, -12864, -13426, -13908, -14236, -14796, -15158, 30188, -29758, -30309, -28830, -29404, -31959, -32552, -31091, -31645, -26074, -26584, -26159, -24701, -25235, -27849, -28395, -26921, -27511, -21894, -22497, -20992, -20525, -21118, -23688, -7387, 7424, 8022, 6591, 7143, 5588, 5648, 4182, 4849, 3292, 3832, 3887, 2414, 2965, 1475, 2030, 40, 613, 15506, 16090, 14578, 14654, 15212, 13702, 14294, 20643, -20851, -21292, -21971, -22421, -22938, -23162, -23610, -24273, -16520, -17071, -17275, -17721, -18398, -18861, -19366, -19581, -20015, -28872, -29334, -29868, -30051, -30515, -31184, -31633, -32183, -32383, -24632, -25284, -25762, -26278, -26471, -26935, -27592, -28065, -28589, -4219, -4614, -5313, -5796, -6323, -6514, -6934, -7630, -8089, -417, 13746, -13412, -13883, -12484, -12934, -15497, -16233, -14633, -15298, -9623, -10176, -9836, -8234, -8909, -11454, -11957, -10606, -11072, -5591, -6021, -4539, -4212, -4644, -7391, -7810, -6312, -7024, -1319, -2003, 98, -441, -1007, -1288, -1888, -2413, -2729, -3311, -3658, -4200, -4690, -4995, -5595, -5948, -6526, -7006, -7325, -7904, -8252, -8820, -9287, -9631, -10179, -10540, -11125, -11601, -11929, -12489, -12835, -13421, -13917, 11732, -11279, -11865, -10418, -10986, -9435, -10015, -8537, -9216, -15831, -16358, -15930, -14436, -14990, -13510, -14066, -12588, -13174, -3475, -4048, -2556, -2084, -2675, -1156, -1729, -242, -820, -7522, -8076, -6600, -7144, -6718, 9094, -8797, -8203, -9956, -9404, -10889, -10573, -12043, -11694, -13189, -12728, -12396, -13874, -13536, -15000, -14500, -16250, -15656, -961, -414, -1962, -1650, -1057, -2770, -2200, -3750, -3426, -4924, -4551, -6033, -5555, -5226, -6715, -6348, -7818, -7340, -25442, -24846, -26590, -25992, 101, -437, -1006, -1301, -1875, -2400, -2746, -3305, -3591, -4187, -4723, -5040, -5625, -5917, -6493, -7022, -7330, -7876, -8219, -8790, -9325, -9633, -10233, 98, -441, -1007, -1288, -1888, -2413, -2729, -3311, -3658, -4197, -4681, -5006, -5585, -5944, -6519, -6990, -7298, -7881, -8233, -8822, -9304, -9616, -10190, -10544, -11110, -11608, -11935, -12497, -12853, -13434, -13895, -14215, -14807, -15163, -15729, -16211, -16523, 22718, -22885, -23347, -24028, -24452, -20913, -21109, -21555, -22166, -18604, -19091, -19293, -19714, -20478, -16828, -17300, -17485, -17940, -30961, -31397, -31900, -32084, -32525, -29178, -29606, -30110, -30293, -26654, -27383, -27816, -28302, -28488, -24854, -25594, -26034, -26500, 1240, -1290, -1873, -426, -1008, -3555, -3614, -2121, -2741, -5357, -5830, -5933, -4435, -5032, -7658, -8146, -6146, -6728, -9394, -9978, -8418, -8460, -9040, -11686, -12264, -10727, -10761, -13383, -13987, -12517, -13010, -13060, -15698, -183, 364, 826, 1491, 1931, 2488, 2684, 3130, 3741, 4259, 4762, 4948, 5385, 6133, 6579, 7067, 7236, 7706, 8440, 8883, 9346, 9537, 10010, 10730, 11196, 11677, 11850, 12292, 13050, 13493, 13966, 14151, 14600, 15340, 15780, 16260, 16462, 16928, 17632, 98, -441, -1007, -1288, -1888, -2413, -2729, -3311, -3658, -4216, -4696, -5017, -5573, -5930, -6519, -6999, -7303, -7883, -8225, -8803, -9307, 98, -441, -1007, -1288, -1888, -2413, -2729, -3311, -3658, -4197, -4681, -5006, -5585, -5944, -6523, -6999, -7328, -7876, -8231, -8807, -9304, -9626, -10195, -10533, -11113, -11590, -11923, -12491, -12835, -13423, -13901, -14215, -14791, -21779, 21699, 22170, 20579, 21029, 23592, 24533, 22937, 23392, 17692, 18181, 18138, 16515, 17007, 19495, 97, -419, -1022, -1301, -1885, -2410, -2730, -3253, -3605, -4178, -4726, -5051, -5619, -5895, -6483, -7026, -7394, -7902, -8250, -8807, -9296, -9626, -10207, -10540, -11108, -11598, -11935, -12497, -12853, -13437, -13889, -14215, -14815, -15142, -15734, -16214, -16525, -17140, -17449, -18031, -18516, -18846, -19440, -19754, -20329, 112, -430, -1019, -1294, -1875, -2408, -2729, 9162, -8721, -8263, -9904, -9464, -10949, -10497, -12103, -11746, -13280, -12777, -12341, -13944, -13472, -15054, -14585, -16163, -15720, -901, -465, -2048, -1590, -1137, -2701, -2252, -3828, -3385, -4982, -4504, -6106, -5628, -5172, -6756, -6302, 15145, -15092, -14502, -15949, -15381, -12840, -12772, -14246, -13571, -11067, -10501, -10450, -11926, -11378, -8738, -8218, -10189, -9625, -7021, -6457, -7960, -7894, -7300, -4717, -4159, -5643, -5577, -2955, -2402, -3889, -3355, -3281, -643, -111, -1575, -1045, 98, -441, -1007, -1288, -1888, -2413, -2729, -3311, -3658, -4197, -4681, -5006, -5585, -5944, -6519, -6990, -7323, -7891, -8254, -8805, -9307, -9616, -10190, -10553, -11123, -11587, -11929, -12487, -12853, -13434, -13895, -14215, -14807, -15163, -15729, -16211, -16523, -3367, 3324, 3754, 2115, 2587, 1064, 2028, 426, 781, 7475, 7946, 7876, 6297, 6757, 5155, 5643, 4554, 5004, 11620, 12093, 10505, 10443, 10904, 9325, 9767, 8201, 9155, 15763, 16251, 14629, 12589, -12541, -12966, -13405, -13851, -14360, -15332, -15804, -16222, -8464, -9022, -8922, -9393, -9808, -10260, -10797, -11759, -12199, -4429, -4896, -5440, -5362, -5819, -6221, -6689, -7225, -8189, -431, -856, -17464, 17894, 18367, 16710, 17152, 19725, 20216, 18599, 19050, 21522, 22076, 22467, 20921, 21339, 23838, 24381, 22776, 23200, 25679, 26171, 24624, 25057, 25531, 27985, 28435, 26943, 27383, 29877, 101, -437, -1006, -1301, -1875, -2400, -2751, -3328, -3589, -4188, -4720, -5035, -5573, -5900, -6491, -7021, -7338, -7926, -8220, -8796, -9315, -9637, -10229, -10502, -11098, -11612, -11942, -12540, -12820, -13389, -26984, 26806, 27375, 27670, 28240, 24669, 25531, 26096, 26380, 31044, 31591, 31379, 31994, 32261, 28761, 29286, 30116, 30700, 18694, 19285, 19829, 19643, 20208, 16390, 17002, 17522, 18358, 23012, 23325, 101, -437, -1006, -1301, -1875, -2400, -2735, -3324, -3606, -4177, -4703, -5054, -5625, -5889, -6481, -7024, -7339, -20782, 20727, 21153, 21576, 22032, 22563, 23527, 23969, 24326, 16702, 17152, 17109, 17553, 18037, 18469, 18946, 19924, 20355, 29049, 29496, 29967, 29899, 30363, 30835, 31281, 31775, 32711, 945, -627, -46, -1733, -1165, -2746, -2426, -3941, -3543, -5013, -4514, -4145, -5675, -5340, -6802, -6332, -8049, -7459, -9112, -8630, -10135, -9813, -9235, -10997, -10403, -11908, -11615, -13087, -12795, -14268, -13703, -13398, -14849, -14575, -16046, 98, -441, -1007, -1288, -1888, -2413, -2729, -3311, -3658, -4214, -4675, -5006, -5599, -5945, -6498, -7006, -7325, -7898, -8232, -8819, -9309, -9630, -10195, -10533, -11123, -11614, -11919, -12512, -12841, -13421, -13901, -14213, -14807, -15161, -15713, 23841, -23804, -24238, -22597, -23069, -21552, -22508, -20910, -21259, -19749, -20232, -20186, -18573, -19043, -17465, -17927, -16864, -17281, -32108, -32567, -30997, -30939, -31369, -29793, -30241, -28703, 101, -437, -1006, -1301, -1875, -2400, -2751, -3328, -3604, -4161, -4713, -5025, -5629, -5916, -6507, -7010, -7343, -7913, -8205, -8786, -9325, -9635, -10213, 98, -441, -1007, -1288, -1888, -2413, -2729, -3311, -3658, -4214, -4675, -5006, -5599, -5945, -6498, -7006, -7326, -7898, -8249, -8804, -9287, -9604, -10186, -10550, -11131, -11596, -11936, -12508, -12851, -13416, -13893, -14226, -14796, -15142, -15728, -16208, -16520, -17146, -22265, 22313, 21872, 21385, 20943, 24514, 23603, 23142, 22664, 18125, 17603, 17723, 17257, 16793, 20428, 19962, 18976, 18526, 30362, 29898, 29427, 29480, -30571, 30384, 29926, 29199, 28759, 32356, 32160, 31718, 31041, 26485, 25927, 25746, 25302, 24626, 28258, 27721, 27526, 27078, 22309, 21869, 21332, 21132, 20679, 24099, 23665, 23135, 22943, 18387, 17713, 17263, 16708, 16532, 20167, 19505, 19045, 18525, 14212, 13801, 13094, 12646, 16198, 16010, 15584, 14898, 14442, 98, -441, -1007, -1288, -1888, -2413, -2729, -3311, -3658, -4222, -4688, -5019, -5599, -5947, -6507, -6978, -7311, -7887, -8238, -8806, -9309, -9605, -10192, -10540, -11130, -11608, -11928, -12508, -12858, -13416, -13890, -14232, -14796, -15150, -15729, -16203, -16513, -17152, -17453, -18042, -18516, -18846, -19448, -19752, -20336, -20818, 9889, -10108, -9518, -9157, -8605, -12208, -11372, -10798, -10379, -13992, -13452, -13647, -13076, -12789, -16310, -15745, -14943, -14364, -1782, -1205, -644, -840, -280, -4096, -3518, -2964, -2124, -30210, 30683, 30093, 29540, 28988, 32527, 31947, 31373, 30762, 26132, 25635, 26111, 25532, 24916, 28443, 27950, 27390, 26810, 22101, 21532, 21038, 21493, 20913, 24411, 23833, 23334, 22758, 18100, 17479, 16917, 16441, 16880, 20415, 19803, 19219, 18739, 14073, 13463, 12887, 101, -437, -1006, -1301, -1875, -2400, -2735, -3324, -3606, -4177, -4703, -5025, -5627, -5894, -6481, 98, -441, -1007, -1288, -1888, -2413, -2729, -3311, -3658, -4210, -4688, -5019, -5599, -5947, -6507, -6977, -7303, -7887, -8254, -8831, -9309, -9621, -10205, -10559, -11123, -11612, -11921, -12510, -12864, -13426, -13908, -14236, -14796, -15158, 98, -441, -1007, -1288, -1888, -2413, -2729, -3311, -3658, -4197, -4693, -5022, -5588, -5944, -6524, -6990, -7324, -7894, -8240, -8832, -9281, -9618, -10186, -10532, -11129, -11595, -11919, -12503, -12843, -13431, -13890, -14239, -14807, -15139, -15743, -16218, -16531, -17124, -17466, -18036, -18514, -18846, -19446, -19768, 98, -441, -1007, -1288, -1888, -2413, -2729, -3311, -3658, -4214, -4676, -4994, -5583, -5949, -6507, -6980, -7309, -7881, -8225, -8801, -9291, -9605, -10181, -23609, 23978, 24555, 22806, -22576, 23029, 23459, 23882, 24338, 20769, 21221, 21667, 22020, 18478, 18953, 19393, 19849, 20341, 16697, 17160, 17607, 18062, 30829, 31285, 31770, 32216, 32642, 29033, 29499, 29957, 30403, 26770, 27237, 27681, 28161, 28617, 24987, 25461, 25901, 101, -437, -1006, -1301, -1875, -2400, -2747, -3328, -3590, -4204, -4726, -5032, -5616, -5893, -6481, 3299, -3379, -3948, -2451, -3029, -1498, -1597, -122, -644, -7406, -7923, -7995, -6514, 98, -441, -1007, -1288, -1888, -2413, -2729, -3311, -3658, -4216, -4673, -5021, -5600, -5944, -6514, -6984, -7324, -7902, -8225, -8827, -9297, -9616, -10205, -10538, -11108, -11598, -11912, -12504, -12864, -13410, 98, -441, -1007, -1288, -1888, -2413, -2729, -3311, -3658, -4216, -4687, -4993, -5584, -5930, -6519, -6999, -7313, -7897, -8237, -8803, -9283, -9626, -10194, -10554, -11113, -11590, -11923, -12491, -12835, -13423, -13901, -14215, -14791, 98, -441, -1007, -1288, -1888, -2413, -2729, -3311, -3658, -4219, -4687, -5019, -5587, -5935, -6525, -6978, -7311, -7881, -8225, -8826, -9294, -9616, -10194, -10532, -11109, -11601, -11919, -12512, -12841, -13421, -13901, -14213, -14807, -15161, -15713, 98, -441, -1007, -1288, -1888, -2413, -2729, -3311, -3658, -4219, -4687, -5019, -5587, -5935, -6525, -6978, -7311, -7881, -8225, -8826, -9294, -9616, -10202, -10544, -11108, -11590, -11929, -12499, -12857, -13416, -13893, -14226, -14796, -15142, -15728, -16208, -16520, -17146, 101, -437, -1006, -1301, -1875, -2400, -2724, -3318, -3604, -4190, -4712, -5032, -5625, -5898, -6466, -7020, -7329, -7923, -8247, -8799, -9323, -9636, -10218, -10502, -11078, -11646, 13294, -12853, -12387, -13964, -13524, -15073, -14629, -16227, -15814, -9208, -8652, -8197, -9811, -9399, -10983, -10435, -12043, -11588, -5042, -4582, -6095, -5664, -5190, -6832, -6382, -7874, -7434, -844, -30569, 30386, 29924, 29197, 28757, 32358, 32162, 31716, 31043, 26481, 25933, 25730, 25300, 24624, 28256, 27726, 27524, 27072, 22316, 21870, 21312, 21134, 20690, 24115, 23650, 23119, 22936, 18368, 17704, 17252, 16710, 16524, 20172, 98, -441, -1007, -1288, -1888, -2413, -2729, -3311, -3658, -4220, -4680, -5001, -5599, -5947, -6507, -6983, -7307, -7881, -8233, -8832, -9296, -9604, -10179, -10540, -11125, -11601, -11929, -12489, -12835, -13421, -13917, -9715, 9251, 9850, 8323, 8901, 11464, 12085, 10603, 11158, 13766, 14308, 13830, 12409, 12938, 15563, 16113, -6427, 6336, 6806, 7295, 7719, 4116, 5072, 5526, 5937, 2307, 2879, 2800, 3238, 3650, 18, 569, 1534, 1968, 14664, 15121, 15674, 15595, 16049, 12379, 12825, 13365, 14333, 10687, 73, -416, -983, -1356, -1804, -2361, -2809, -3236, -3659, -4102, 85, -409, -992, -1356, -1804 };
  }
  
  private static String ˎ(int paramInt1, char paramChar, int paramInt2)
  {
    break label191;
    int i;
    label62:
    label69:
    char[] arrayOfChar;
    for (;;)
    {
      switch (j)
      {
      default: 
        break label128;
        i = ॱॱ + 17;
        ˏ = i % 128;
        if (i % 2 == 0)
        {
          break label69;
          j = 76;
          continue;
        }
        arrayOfChar = new char[paramInt2];
        i = 0;
        break label194;
        return new String(arrayOfChar);
      case 83: 
        arrayOfChar[i] = ((char)(int)(ˎ[(paramInt1 >>> i)] * (i % ˋ) + paramChar));
        i += 64;
        break label194;
        label121:
        j = 83;
      }
    }
    label128:
    arrayOfChar[i] = ((char)(int)(ˎ[(paramInt1 + i)] ^ i * ˋ ^ paramChar));
    i += 1;
    label159:
    for (int j = 1;; j = 0) {
      switch (j)
      {
      case 0: 
      default: 
        break label205;
        break;
        if (i < paramInt2) {
          break label159;
        }
        break;
      case 1: 
        label191:
        label194:
        label205:
        j = ॱॱ + 11;
        ˏ = j % 128;
        if (j % 2 != 0) {
          break label121;
        }
        break label62;
      }
    }
  }
  
  public static Ic ˏ(Context paramContext)
  {
    break label27;
    int i = 1;
    break label30;
    paramContext = new Ic(paramContext);
    break label62;
    for (;;)
    {
      i = 50 / 0;
      return paramContext;
      label27:
      break;
      label30:
      switch (i)
      {
      }
    }
    for (;;)
    {
      i = 0;
      break label30;
      return paramContext;
      label62:
      i = ˏ + 109;
      ॱॱ = i % 128;
      if (i % 2 == 0) {
        break;
      }
    }
  }
  
  /* Error */
  private String ॱॱ(String paramString)
  {
    // Byte code:
    //   0: goto +101 -> 101
    //   3: astore_1
    //   4: new 1648	java/lang/RuntimeException
    //   7: dup
    //   8: aload_1
    //   9: invokespecial 1651	java/lang/RuntimeException:<init>	(Ljava/lang/Throwable;)V
    //   12: athrow
    //   13: getstatic 23	o/Ic:ॱॱ	I
    //   16: bipush 9
    //   18: iadd
    //   19: istore_3
    //   20: iload_3
    //   21: sipush 128
    //   24: irem
    //   25: putstatic 21	o/Ic:ˏ	I
    //   28: iload_3
    //   29: iconst_2
    //   30: irem
    //   31: ifeq +6 -> 37
    //   34: goto +128 -> 162
    //   37: aload 4
    //   39: iload_2
    //   40: aload_1
    //   41: aload_1
    //   42: arraylength
    //   43: iload_2
    //   44: isub
    //   45: iconst_1
    //   46: isub
    //   47: baload
    //   48: getstatic 28	o/Ic:ॱ	B
    //   51: ixor
    //   52: i2b
    //   53: bastore
    //   54: iload_2
    //   55: iconst_1
    //   56: iadd
    //   57: istore_2
    //   58: goto +51 -> 109
    //   61: aload_1
    //   62: sipush 2286
    //   65: iconst_0
    //   66: bipush 10
    //   68: invokestatic 1653	o/Ic:ˎ	(ICI)Ljava/lang/String;
    //   71: invokevirtual 1657	java/lang/String:intern	()Ljava/lang/String;
    //   74: invokevirtual 1661	java/lang/String:getBytes	(Ljava/lang/String;)[B
    //   77: astore_1
    //   78: aload_1
    //   79: arraylength
    //   80: newarray byte
    //   82: astore 4
    //   84: iconst_0
    //   85: istore_2
    //   86: goto +23 -> 109
    //   89: iconst_0
    //   90: istore_3
    //   91: goto +37 -> 128
    //   94: iconst_1
    //   95: istore_3
    //   96: goto +32 -> 128
    //   99: aload_1
    //   100: areturn
    //   101: goto -40 -> 61
    //   104: iconst_0
    //   105: istore_2
    //   106: goto +86 -> 192
    //   109: aload_1
    //   110: arraylength
    //   111: istore_3
    //   112: iload_2
    //   113: iload_3
    //   114: if_icmpge +6 -> 120
    //   117: goto -28 -> 89
    //   120: goto -26 -> 94
    //   123: iconst_1
    //   124: istore_2
    //   125: goto +67 -> 192
    //   128: iload_3
    //   129: tableswitch	default:+23->152, 0:+-116->13, 1:+89->218
    //   152: goto -139 -> 13
    //   155: bipush 60
    //   157: iconst_0
    //   158: idiv
    //   159: istore_2
    //   160: aload_1
    //   161: areturn
    //   162: goto -125 -> 37
    //   165: getstatic 23	o/Ic:ॱॱ	I
    //   168: bipush 37
    //   170: iadd
    //   171: istore_2
    //   172: iload_2
    //   173: sipush 128
    //   176: irem
    //   177: putstatic 21	o/Ic:ˏ	I
    //   180: iload_2
    //   181: iconst_2
    //   182: irem
    //   183: ifeq +6 -> 189
    //   186: goto -63 -> 123
    //   189: goto -85 -> 104
    //   192: iload_2
    //   193: tableswitch	default:+23->216, 0:+-94->99, 1:+-38->155
    //   216: aload_1
    //   217: areturn
    //   218: new 1637	java/lang/String
    //   221: dup
    //   222: aload 4
    //   224: sipush 2296
    //   227: iconst_0
    //   228: iconst_5
    //   229: invokestatic 1653	o/Ic:ˎ	(ICI)Ljava/lang/String;
    //   232: invokevirtual 1657	java/lang/String:intern	()Ljava/lang/String;
    //   235: invokespecial 1664	java/lang/String:<init>	([BLjava/lang/String;)V
    //   238: astore_1
    //   239: goto -74 -> 165
    // Local variable table:
    //   start	length	slot	name	signature
    //   0	242	0	this	Ic
    //   0	242	1	paramString	String
    //   39	154	2	i	int
    //   19	110	3	j	int
    //   37	186	4	arrayOfByte	byte[]
    // Exception table:
    //   from	to	target	type
    //   37	54	3	java/io/UnsupportedEncodingException
    //   61	84	3	java/io/UnsupportedEncodingException
    //   109	112	3	java/io/UnsupportedEncodingException
    //   218	239	3	java/io/UnsupportedEncodingException
  }
  
  public j ʻ()
  {
    for (;;)
    {
      j localJ = j.ˏ(this.ˊ, ˎ(374, '\000', 34).intern());
      int i = ॱॱ + 91;
      ˏ = i % 128;
      if (i % 2 != 0) {
        return localJ;
      }
      return localJ;
      i = ॱॱ + 103;
      ˏ = i % 128;
      if (i % 2 != 0) {
        break;
      }
    }
  }
  
  public j ʻ(String paramString)
  {
    break label147;
    return j.ˏ(this.ˊ, ˎ(19078, 35228, 83).intern()).ˋ(ˎ(21856, '\000', 72).intern(), paramString);
    return j.ˏ(this.ˊ, ˎ(1766, 35228, 39).intern()).ˋ(ˎ(1805, '\000', 15).intern(), paramString);
    label112:
    label115:
    label147:
    for (;;)
    {
      int i = ॱॱ + 123;
      ˏ = i % 128;
      if (i % 2 == 0) {
        break label112;
      }
      i = 27;
      break label115;
      i = 15;
      switch (i)
      {
      }
      break;
    }
  }
  
  public j ʻॱ()
  {
    break label66;
    j localJ = new j(this.ˊ, new Intent(ˎ(1469, 'ϐ', 35).intern()));
    label39:
    for (int i = 0;; i = 1) {
      switch (i)
      {
      case 1: 
      default: 
        return localJ;
        break;
      case 0: 
        label66:
        i = 78 / 0;
        return localJ;
        i = ॱॱ + 47;
        ˏ = i % 128;
        if (i % 2 != 0) {
          break label39;
        }
      }
    }
  }
  
  /* Error */
  public j ʼ()
  {
    // Byte code:
    //   0: goto +36 -> 36
    //   3: iload_1
    //   4: tableswitch	default:+24->28, 0:+40->44, 1:+63->67
    //   28: goto +39 -> 67
    //   31: iconst_1
    //   32: istore_1
    //   33: goto -30 -> 3
    //   36: goto +51 -> 87
    //   39: iconst_0
    //   40: istore_1
    //   41: goto -38 -> 3
    //   44: aload_0
    //   45: getfield 35	o/Ic:ˊ	Landroid/content/Context;
    //   48: sipush 22641
    //   51: iconst_0
    //   52: bipush 99
    //   54: invokestatic 1653	o/Ic:ˎ	(ICI)Ljava/lang/String;
    //   57: invokevirtual 1657	java/lang/String:intern	()Ljava/lang/String;
    //   60: invokestatic 1671	o/j:ˏ	(Landroid/content/Context;Ljava/lang/String;)Lo/j;
    //   63: areturn
    //   64: astore_2
    //   65: aload_2
    //   66: athrow
    //   67: aload_0
    //   68: getfield 35	o/Ic:ˊ	Landroid/content/Context;
    //   71: sipush 579
    //   74: iconst_0
    //   75: bipush 22
    //   77: invokestatic 1653	o/Ic:ˎ	(ICI)Ljava/lang/String;
    //   80: invokevirtual 1657	java/lang/String:intern	()Ljava/lang/String;
    //   83: invokestatic 1671	o/j:ˏ	(Landroid/content/Context;Ljava/lang/String;)Lo/j;
    //   86: areturn
    //   87: getstatic 23	o/Ic:ॱॱ	I
    //   90: istore_1
    //   91: iload_1
    //   92: bipush 77
    //   94: iadd
    //   95: istore_1
    //   96: iload_1
    //   97: sipush 128
    //   100: irem
    //   101: putstatic 21	o/Ic:ˏ	I
    //   104: iload_1
    //   105: iconst_2
    //   106: irem
    //   107: ifeq +6 -> 113
    //   110: goto -71 -> 39
    //   113: goto -82 -> 31
    // Local variable table:
    //   start	length	slot	name	signature
    //   0	116	0	this	Ic
    //   3	104	1	i	int
    //   64	2	2	localException	Exception
    // Exception table:
    //   from	to	target	type
    //   87	91	64	java/lang/Exception
    //   96	104	64	java/lang/Exception
  }
  
  /* Error */
  public j ʼ(String paramString)
  {
    // Byte code:
    //   0: goto +159 -> 159
    //   3: getstatic 21	o/Ic:ˏ	I
    //   6: bipush 111
    //   8: iadd
    //   9: istore_2
    //   10: iload_2
    //   11: sipush 128
    //   14: irem
    //   15: putstatic 23	o/Ic:ॱॱ	I
    //   18: iload_2
    //   19: iconst_2
    //   20: irem
    //   21: ifne +6 -> 27
    //   24: goto +91 -> 115
    //   27: goto +55 -> 82
    //   30: astore_1
    //   31: aload_1
    //   32: athrow
    //   33: aload_0
    //   34: getfield 35	o/Ic:ˊ	Landroid/content/Context;
    //   37: astore_3
    //   38: sipush 21465
    //   41: iconst_0
    //   42: iconst_4
    //   43: invokestatic 1653	o/Ic:ˎ	(ICI)Ljava/lang/String;
    //   46: astore 4
    //   48: aload 4
    //   50: invokevirtual 1657	java/lang/String:intern	()Ljava/lang/String;
    //   53: astore 4
    //   55: aload_3
    //   56: aload 4
    //   58: invokestatic 1671	o/j:ˏ	(Landroid/content/Context;Ljava/lang/String;)Lo/j;
    //   61: sipush 29441
    //   64: sipush 30089
    //   67: bipush 84
    //   69: invokestatic 1653	o/Ic:ˎ	(ICI)Ljava/lang/String;
    //   72: invokevirtual 1657	java/lang/String:intern	()Ljava/lang/String;
    //   75: aload_1
    //   76: invokevirtual 1676	o/j:ˋ	(Ljava/lang/String;Ljava/lang/String;)Lo/j;
    //   79: astore_1
    //   80: aload_1
    //   81: areturn
    //   82: iconst_2
    //   83: istore_2
    //   84: iload_2
    //   85: lookupswitch	default:+27->112, 2:+36->121, 8:+-52->33
    //   112: goto +9 -> 121
    //   115: bipush 8
    //   117: istore_2
    //   118: goto -34 -> 84
    //   121: aload_0
    //   122: getfield 35	o/Ic:ˊ	Landroid/content/Context;
    //   125: sipush 1988
    //   128: iconst_0
    //   129: bipush 30
    //   131: invokestatic 1653	o/Ic:ˎ	(ICI)Ljava/lang/String;
    //   134: invokevirtual 1657	java/lang/String:intern	()Ljava/lang/String;
    //   137: invokestatic 1671	o/j:ˏ	(Landroid/content/Context;Ljava/lang/String;)Lo/j;
    //   140: sipush 656
    //   143: sipush 30089
    //   146: bipush 24
    //   148: invokestatic 1653	o/Ic:ˎ	(ICI)Ljava/lang/String;
    //   151: invokevirtual 1657	java/lang/String:intern	()Ljava/lang/String;
    //   154: aload_1
    //   155: invokevirtual 1676	o/j:ˋ	(Ljava/lang/String;Ljava/lang/String;)Lo/j;
    //   158: areturn
    //   159: goto -156 -> 3
    //   162: astore_1
    //   163: aload_1
    //   164: athrow
    // Local variable table:
    //   start	length	slot	name	signature
    //   0	165	0	this	Ic
    //   0	165	1	paramString	String
    //   9	109	2	i	int
    //   37	19	3	localContext	Context
    //   46	11	4	str	String
    // Exception table:
    //   from	to	target	type
    //   48	55	30	java/lang/Exception
    //   33	38	162	java/lang/Exception
    //   38	48	162	java/lang/Exception
    //   48	55	162	java/lang/Exception
    //   55	80	162	java/lang/Exception
  }
  
  public j ʼॱ()
  {
    break label8;
    label3:
    int i = 0;
    break label33;
    label8:
    break label59;
    return j.ˏ(this.ˊ, ˎ(3229, 35063, 19).intern());
    for (;;)
    {
      switch (i)
      {
      case 1: 
      default: 
        label33:
        break label91;
        label59:
        i = ˏ + 13;
        ॱॱ = i % 128;
        if (i % 2 != 0) {
          break label3;
        }
        i = 1;
      }
    }
    label91:
    return j.ˏ(this.ˊ, ˎ(1648, 35063, 45).intern());
  }
  
  /* Error */
  public j ʽ()
  {
    // Byte code:
    //   0: goto +6 -> 6
    //   3: goto +65 -> 68
    //   6: goto +9 -> 15
    //   9: astore_2
    //   10: aload_2
    //   11: athrow
    //   12: astore_2
    //   13: aload_2
    //   14: athrow
    //   15: getstatic 21	o/Ic:ˏ	I
    //   18: bipush 73
    //   20: iadd
    //   21: istore_1
    //   22: iload_1
    //   23: sipush 128
    //   26: irem
    //   27: putstatic 23	o/Ic:ॱॱ	I
    //   30: iload_1
    //   31: iconst_2
    //   32: irem
    //   33: ifne +6 -> 39
    //   36: goto -33 -> 3
    //   39: goto +29 -> 68
    //   42: getstatic 23	o/Ic:ॱॱ	I
    //   45: bipush 71
    //   47: iadd
    //   48: istore_1
    //   49: iload_1
    //   50: sipush 128
    //   53: irem
    //   54: putstatic 21	o/Ic:ˏ	I
    //   57: iload_1
    //   58: iconst_2
    //   59: irem
    //   60: ifeq +6 -> 66
    //   63: goto +30 -> 93
    //   66: aload_2
    //   67: areturn
    //   68: aload_0
    //   69: getfield 35	o/Ic:ˊ	Landroid/content/Context;
    //   72: astore_2
    //   73: aload_2
    //   74: sipush 601
    //   77: iconst_0
    //   78: bipush 21
    //   80: invokestatic 1653	o/Ic:ˎ	(ICI)Ljava/lang/String;
    //   83: invokevirtual 1657	java/lang/String:intern	()Ljava/lang/String;
    //   86: invokestatic 1671	o/j:ˏ	(Landroid/content/Context;Ljava/lang/String;)Lo/j;
    //   89: astore_2
    //   90: goto -48 -> 42
    //   93: aload_2
    //   94: areturn
    // Local variable table:
    //   start	length	slot	name	signature
    //   0	95	0	this	Ic
    //   21	39	1	i	int
    //   9	2	2	localException1	Exception
    //   12	55	2	localException2	Exception
    //   72	22	2	localObject	Object
    // Exception table:
    //   from	to	target	type
    //   42	49	9	java/lang/Exception
    //   49	57	9	java/lang/Exception
    //   73	90	9	java/lang/Exception
    //   49	57	12	java/lang/Exception
    //   68	73	12	java/lang/Exception
  }
  
  /* Error */
  public j ʽ(String paramString)
  {
    // Byte code:
    //   0: goto +79 -> 79
    //   3: bipush 26
    //   5: istore_2
    //   6: goto +44 -> 50
    //   9: astore_1
    //   10: aload_1
    //   11: athrow
    //   12: aload_0
    //   13: getfield 35	o/Ic:ˊ	Landroid/content/Context;
    //   16: sipush 5988
    //   19: iconst_0
    //   20: bipush 19
    //   22: invokestatic 1653	o/Ic:ˎ	(ICI)Ljava/lang/String;
    //   25: invokevirtual 1657	java/lang/String:intern	()Ljava/lang/String;
    //   28: invokestatic 1671	o/j:ˏ	(Landroid/content/Context;Ljava/lang/String;)Lo/j;
    //   31: sipush 21852
    //   34: ldc_w 1690
    //   37: bipush 95
    //   39: invokestatic 1653	o/Ic:ˎ	(ICI)Ljava/lang/String;
    //   42: invokevirtual 1657	java/lang/String:intern	()Ljava/lang/String;
    //   45: aload_1
    //   46: invokevirtual 1676	o/j:ˋ	(Ljava/lang/String;Ljava/lang/String;)Lo/j;
    //   49: areturn
    //   50: iload_2
    //   51: lookupswitch	default:+25->76, 26:+31->82, 59:+-39->12
    //   76: goto -64 -> 12
    //   79: goto +58 -> 137
    //   82: aload_0
    //   83: getfield 35	o/Ic:ˊ	Landroid/content/Context;
    //   86: astore_3
    //   87: sipush 2211
    //   90: iconst_0
    //   91: bipush 31
    //   93: invokestatic 1653	o/Ic:ˎ	(ICI)Ljava/lang/String;
    //   96: astore 4
    //   98: aload_3
    //   99: aload 4
    //   101: invokevirtual 1657	java/lang/String:intern	()Ljava/lang/String;
    //   104: invokestatic 1671	o/j:ˏ	(Landroid/content/Context;Ljava/lang/String;)Lo/j;
    //   107: sipush 2242
    //   110: ldc_w 1690
    //   113: bipush 16
    //   115: invokestatic 1653	o/Ic:ˎ	(ICI)Ljava/lang/String;
    //   118: invokevirtual 1657	java/lang/String:intern	()Ljava/lang/String;
    //   121: aload_1
    //   122: invokevirtual 1676	o/j:ˋ	(Ljava/lang/String;Ljava/lang/String;)Lo/j;
    //   125: astore_1
    //   126: aload_1
    //   127: areturn
    //   128: astore_1
    //   129: aload_1
    //   130: athrow
    //   131: bipush 59
    //   133: istore_2
    //   134: goto -84 -> 50
    //   137: getstatic 21	o/Ic:ˏ	I
    //   140: istore_2
    //   141: iload_2
    //   142: bipush 107
    //   144: iadd
    //   145: istore_2
    //   146: iload_2
    //   147: sipush 128
    //   150: irem
    //   151: putstatic 23	o/Ic:ॱॱ	I
    //   154: iload_2
    //   155: iconst_2
    //   156: irem
    //   157: ifne +6 -> 163
    //   160: goto -29 -> 131
    //   163: goto -160 -> 3
    // Local variable table:
    //   start	length	slot	name	signature
    //   0	166	0	this	Ic
    //   0	166	1	paramString	String
    //   5	152	2	i	int
    //   86	13	3	localContext	Context
    //   96	4	4	str	String
    // Exception table:
    //   from	to	target	type
    //   82	87	9	java/lang/Exception
    //   87	98	9	java/lang/Exception
    //   98	126	9	java/lang/Exception
    //   87	98	128	java/lang/Exception
    //   137	141	128	java/lang/Exception
    //   146	154	128	java/lang/Exception
  }
  
  public j ʽॱ()
  {
    for (;;)
    {
      int i = 32;
      label46:
      label81:
      label101:
      do
      {
        i = 88;
        break label46;
        try
        {
          Object localObject = this.ˊ;
          String str = ˎ(1820, '\000', 34);
          str = str.intern();
          switch (i)
          {
          }
        }
        catch (Exception localException1)
        {
          try
          {
            localObject = j.ˏ((Context)localObject, str);
            return localObject;
          }
          catch (Exception localException2)
          {
            throw localException2;
          }
          localException1 = localException1;
          throw localException1;
        }
        break label81;
        break label101;
        return j.ˏ(this.ˊ, ˎ(26768, '\000', 70).intern());
        i = ˏ + 51;
        ॱॱ = i % 128;
      } while (i % 2 == 0);
    }
  }
  
  public j ʾ()
  {
    break label69;
    throw new NullPointerException();
    int i = 70;
    break label134;
    j localJ;
    for (;;)
    {
      switch (i)
      {
      case 4: 
      default: 
        localJ = j.ˏ(this.ˊ, ˎ(10648, '⛃', 109).intern());
        break label162;
        i = ॱॱ + 71;
        ˏ = i % 128;
        if (i % 2 == 0) {
          i = 40;
        }
        break;
      case 40: 
        label69:
        localJ = j.ˏ(this.ˊ, ˎ(1739, '⛃', 27).intern());
        break label162;
        i = 4;
      }
    }
    return localJ;
    for (;;)
    {
      i = 31;
      label134:
      switch (i)
      {
      }
      return localJ;
      label162:
      i = ॱॱ + 63;
      ˏ = i % 128;
      if (i % 2 != 0) {
        break;
      }
    }
  }
  
  public j ʿ()
  {
    label28:
    label66:
    label95:
    label122:
    label127:
    for (;;)
    {
      j localJ = j.ˏ(this.ˊ, ˎ(1588, '\000', 38).intern());
      break label95;
      return localJ;
      int i = 2;
      for (;;)
      {
        i = 19;
        break label66;
        i = ˏ + 23;
        ॱॱ = i % 128;
        if (i % 2 == 0) {
          break label127;
        }
        break;
        switch (i)
        {
        case 19: 
        default: 
          break label122;
          i = ॱॱ + 19;
          ˏ = i % 128;
          if (i % 2 != 0) {
            break label28;
          }
        }
      }
      i = null.length;
      return localJ;
    }
  }
  
  public j ˈ()
  {
    break label84;
    int i;
    j localJ;
    for (;;)
    {
      i = ˏ + 83;
      ॱॱ = i % 128;
      if (i % 2 == 0) {
        break;
      }
      return localJ;
      localJ = j.ˏ(this.ˊ, ˎ(1693, '\000', 46).intern());
    }
    return localJ;
    label84:
    for (;;)
    {
      i = ˏ + 103;
      ॱॱ = i % 128;
      if (i % 2 != 0) {
        break;
      }
      break;
    }
  }
  
  /* Error */
  public j ˉ()
  {
    // Byte code:
    //   0: goto +158 -> 158
    //   3: getstatic 23	o/Ic:ॱॱ	I
    //   6: istore_1
    //   7: iload_1
    //   8: bipush 45
    //   10: iadd
    //   11: istore_1
    //   12: iload_1
    //   13: sipush 128
    //   16: irem
    //   17: putstatic 21	o/Ic:ˏ	I
    //   20: iload_1
    //   21: iconst_2
    //   22: irem
    //   23: ifeq +6 -> 29
    //   26: goto +127 -> 153
    //   29: iconst_1
    //   30: istore_1
    //   31: goto +139 -> 170
    //   34: aload_2
    //   35: areturn
    //   36: aload_0
    //   37: getfield 35	o/Ic:ˊ	Landroid/content/Context;
    //   40: sipush 21447
    //   43: iconst_0
    //   44: bipush 33
    //   46: invokestatic 1653	o/Ic:ˎ	(ICI)Ljava/lang/String;
    //   49: invokevirtual 1657	java/lang/String:intern	()Ljava/lang/String;
    //   52: invokestatic 1671	o/j:ˏ	(Landroid/content/Context;Ljava/lang/String;)Lo/j;
    //   55: astore_2
    //   56: goto +32 -> 88
    //   59: aconst_null
    //   60: arraylength
    //   61: istore_1
    //   62: aload_2
    //   63: areturn
    //   64: aload_0
    //   65: getfield 35	o/Ic:ˊ	Landroid/content/Context;
    //   68: astore_2
    //   69: sipush 2018
    //   72: iconst_0
    //   73: bipush 33
    //   75: invokestatic 1653	o/Ic:ˎ	(ICI)Ljava/lang/String;
    //   78: astore_3
    //   79: aload_2
    //   80: aload_3
    //   81: invokevirtual 1657	java/lang/String:intern	()Ljava/lang/String;
    //   84: invokestatic 1671	o/j:ˏ	(Landroid/content/Context;Ljava/lang/String;)Lo/j;
    //   87: astore_2
    //   88: getstatic 23	o/Ic:ॱॱ	I
    //   91: bipush 15
    //   93: iadd
    //   94: istore_1
    //   95: iload_1
    //   96: sipush 128
    //   99: irem
    //   100: putstatic 21	o/Ic:ˏ	I
    //   103: iload_1
    //   104: iconst_2
    //   105: irem
    //   106: ifeq +6 -> 112
    //   109: goto +38 -> 147
    //   112: goto +52 -> 164
    //   115: astore_2
    //   116: aload_2
    //   117: athrow
    //   118: iload_1
    //   119: lookupswitch	default:+25->144, 22:+-60->59, 53:+-85->34
    //   144: goto -85 -> 59
    //   147: bipush 22
    //   149: istore_1
    //   150: goto -32 -> 118
    //   153: iconst_0
    //   154: istore_1
    //   155: goto +15 -> 170
    //   158: goto -155 -> 3
    //   161: astore_2
    //   162: aload_2
    //   163: athrow
    //   164: bipush 53
    //   166: istore_1
    //   167: goto -49 -> 118
    //   170: iload_1
    //   171: tableswitch	default:+21->192, 0:+-135->36, 1:+-107->64
    //   192: goto -156 -> 36
    // Local variable table:
    //   start	length	slot	name	signature
    //   0	195	0	this	Ic
    //   6	165	1	i	int
    //   34	54	2	localObject	Object
    //   115	2	2	localException1	Exception
    //   161	2	2	localException2	Exception
    //   78	3	3	str	String
    // Exception table:
    //   from	to	target	type
    //   3	7	115	java/lang/Exception
    //   12	20	115	java/lang/Exception
    //   64	69	161	java/lang/Exception
    //   69	79	161	java/lang/Exception
    //   79	88	161	java/lang/Exception
  }
  
  public j ˊ()
  {
    int i;
    for (;;)
    {
      ComponentName localComponentName = new ComponentName(this.ˊ, ˎ(194, '\000', 44).intern());
      j localJ = j.ˏ(this.ˊ, ˎ(238, '\000', 54).intern());
      localJ.ˋ(ˎ(292, 44469, 8).intern(), ˎ(300, '\000', 7).intern());
      localJ.ˎ(ˎ(307, 41750, 9).intern(), localComponentName);
      break;
      i = 1;
      switch (i)
      {
      case 0: 
      default: 
        label103:
        return localJ;
      }
      throw new NullPointerException();
    }
    for (;;)
    {
      i = 0;
      break label103;
      i = ॱॱ + 47;
      ˏ = i % 128;
      if (i % 2 != 0) {
        break;
      }
    }
  }
  
  /* Error */
  public j ˊ(String paramString)
  {
    // Byte code:
    //   0: goto +35 -> 35
    //   3: aload 5
    //   5: astore 4
    //   7: iload_2
    //   8: tableswitch	default:+24->32, 0:+30->38, 1:+103->111
    //   32: goto +6 -> 38
    //   35: goto +35 -> 70
    //   38: getstatic 23	o/Ic:ॱॱ	I
    //   41: istore_2
    //   42: iload_2
    //   43: bipush 59
    //   45: iadd
    //   46: istore_2
    //   47: iload_2
    //   48: sipush 128
    //   51: irem
    //   52: putstatic 21	o/Ic:ˏ	I
    //   55: iload_2
    //   56: iconst_2
    //   57: irem
    //   58: ifeq +6 -> 64
    //   61: goto +6 -> 67
    //   64: goto +69 -> 133
    //   67: goto +66 -> 133
    //   70: getstatic 23	o/Ic:ॱॱ	I
    //   73: bipush 39
    //   75: iadd
    //   76: istore_2
    //   77: iload_2
    //   78: sipush 128
    //   81: irem
    //   82: putstatic 21	o/Ic:ˏ	I
    //   85: iload_2
    //   86: iconst_2
    //   87: irem
    //   88: ifeq +6 -> 94
    //   91: goto +201 -> 292
    //   94: goto +57 -> 151
    //   97: astore_1
    //   98: aload_1
    //   99: athrow
    //   100: astore_1
    //   101: aload_1
    //   102: athrow
    //   103: goto +8 -> 111
    //   106: iconst_0
    //   107: istore_2
    //   108: goto -105 -> 3
    //   111: aload 6
    //   113: aload 4
    //   115: aload_1
    //   116: invokevirtual 1714	android/app/KeyguardManager:createConfirmDeviceCredentialIntent	(Ljava/lang/CharSequence;Ljava/lang/CharSequence;)Landroid/content/Intent;
    //   119: astore_1
    //   120: new 1668	o/j
    //   123: dup
    //   124: aload_0
    //   125: getfield 35	o/Ic:ˊ	Landroid/content/Context;
    //   128: aload_1
    //   129: invokespecial 1685	o/j:<init>	(Landroid/content/Context;Landroid/content/Intent;)V
    //   132: areturn
    //   133: aload_0
    //   134: aload 5
    //   136: iconst_4
    //   137: invokevirtual 1718	java/lang/String:substring	(I)Ljava/lang/String;
    //   140: invokespecial 1720	o/Ic:ॱॱ	(Ljava/lang/String;)Ljava/lang/String;
    //   143: invokevirtual 1657	java/lang/String:intern	()Ljava/lang/String;
    //   146: astore 4
    //   148: goto -45 -> 103
    //   151: goto +20 -> 171
    //   154: astore_1
    //   155: aload_1
    //   156: invokevirtual 1726	java/lang/Throwable:getCause	()Ljava/lang/Throwable;
    //   159: astore 4
    //   161: aload 4
    //   163: ifnull +6 -> 169
    //   166: aload 4
    //   168: athrow
    //   169: aload_1
    //   170: athrow
    //   171: iconst_3
    //   172: bipush 39
    //   174: sipush 29347
    //   177: invokestatic 1731	o/O:ˋ	(IIC)Ljava/lang/Object;
    //   180: checkcast 1733	java/lang/Class
    //   183: ldc_w 1734
    //   186: aconst_null
    //   187: invokevirtual 1738	java/lang/Class:getMethod	(Ljava/lang/String;[Ljava/lang/Class;)Ljava/lang/reflect/Method;
    //   190: aconst_null
    //   191: aconst_null
    //   192: invokevirtual 1744	java/lang/reflect/Method:invoke	(Ljava/lang/Object;[Ljava/lang/Object;)Ljava/lang/Object;
    //   195: astore 4
    //   197: goto +20 -> 217
    //   200: astore_1
    //   201: aload_1
    //   202: invokevirtual 1726	java/lang/Throwable:getCause	()Ljava/lang/Throwable;
    //   205: astore 4
    //   207: aload 4
    //   209: ifnull +6 -> 215
    //   212: aload 4
    //   214: athrow
    //   215: aload_1
    //   216: athrow
    //   217: iconst_3
    //   218: bipush 39
    //   220: sipush 29347
    //   223: invokestatic 1731	o/O:ˋ	(IIC)Ljava/lang/Object;
    //   226: checkcast 1733	java/lang/Class
    //   229: ldc_w 1745
    //   232: aconst_null
    //   233: invokevirtual 1738	java/lang/Class:getMethod	(Ljava/lang/String;[Ljava/lang/Class;)Ljava/lang/reflect/Method;
    //   236: aload 4
    //   238: aconst_null
    //   239: invokevirtual 1744	java/lang/reflect/Method:invoke	(Ljava/lang/Object;[Ljava/lang/Object;)Ljava/lang/Object;
    //   242: checkcast 1710	android/app/KeyguardManager
    //   245: astore 6
    //   247: aload_0
    //   248: getfield 35	o/Ic:ˊ	Landroid/content/Context;
    //   251: astore 4
    //   253: aload 4
    //   255: getstatic 1750	o/Gu$ˏ:authentication_required	I
    //   258: invokevirtual 1755	android/content/Context:getString	(I)Ljava/lang/String;
    //   261: astore 5
    //   263: aload 5
    //   265: sipush 316
    //   268: sipush 14281
    //   271: iconst_4
    //   272: invokestatic 1653	o/Ic:ˎ	(ICI)Ljava/lang/String;
    //   275: invokevirtual 1657	java/lang/String:intern	()Ljava/lang/String;
    //   278: invokevirtual 1759	java/lang/String:startsWith	(Ljava/lang/String;)Z
    //   281: istore_3
    //   282: iload_3
    //   283: ifeq +6 -> 289
    //   286: goto -180 -> 106
    //   289: goto +6 -> 295
    //   292: goto -141 -> 151
    //   295: iconst_1
    //   296: istore_2
    //   297: goto -294 -> 3
    // Local variable table:
    //   start	length	slot	name	signature
    //   0	300	0	this	Ic
    //   0	300	1	paramString	String
    //   7	290	2	i	int
    //   281	2	3	bool	boolean
    //   5	249	4	localObject	Object
    //   3	261	5	str	String
    //   111	135	6	localKeyguardManager	android.app.KeyguardManager
    // Exception table:
    //   from	to	target	type
    //   38	42	97	java/lang/Exception
    //   47	55	97	java/lang/Exception
    //   201	207	97	java/lang/Exception
    //   212	215	97	java/lang/Exception
    //   215	217	97	java/lang/Exception
    //   247	253	97	java/lang/Exception
    //   253	282	97	java/lang/Exception
    //   155	161	100	java/lang/Exception
    //   166	169	100	java/lang/Exception
    //   169	171	100	java/lang/Exception
    //   171	197	154	finally
    //   217	247	200	finally
  }
  
  public j ˊ(String paramString1, String paramString2, String paramString3, MatrixHCEPaymentScheme paramMatrixHCEPaymentScheme, boolean paramBoolean)
  {
    break label49;
    int i = 63;
    break label14;
    label10:
    i = 44;
    switch (i)
    {
    default: 
      break;
    case 44: 
      label14:
      return paramString1;
      for (;;)
      {
        label49:
        i = ॱॱ + 101;
        ˏ = i % 128;
        if (i % 2 != 0) {
          break;
        }
        break label10;
        Intent localIntent = new Intent(ˎ(1279, 62139, 30).intern());
        localIntent.putExtra(ˎ(1309, 'ㅈ', 29).intern(), paramString1);
        localIntent.putExtra(ˎ(1366, '\000', 30).intern(), paramString2);
        localIntent.putExtra(ˎ(1396, 38653, 29).intern(), paramString3);
        localIntent.putExtra(ˎ(1425, '\000', 17).intern(), paramMatrixHCEPaymentScheme);
        localIntent.putExtra(ˎ(1338, 48045, 28).intern(), paramBoolean);
        paramString1 = new j(this.ˊ, localIntent);
      }
    }
    throw new NullPointerException();
  }
  
  /* Error */
  public j ˊ(FG paramFG)
  {
    // Byte code:
    //   0: goto +150 -> 150
    //   3: aload_1
    //   4: areturn
    //   5: aload_0
    //   6: getfield 35	o/Ic:ˊ	Landroid/content/Context;
    //   9: sipush 2086
    //   12: iconst_0
    //   13: bipush 38
    //   15: invokestatic 1653	o/Ic:ˎ	(ICI)Ljava/lang/String;
    //   18: invokevirtual 1657	java/lang/String:intern	()Ljava/lang/String;
    //   21: invokestatic 1671	o/j:ˏ	(Landroid/content/Context;Ljava/lang/String;)Lo/j;
    //   24: sipush 2124
    //   27: iconst_0
    //   28: bipush 26
    //   30: invokestatic 1653	o/Ic:ˎ	(ICI)Ljava/lang/String;
    //   33: invokevirtual 1657	java/lang/String:intern	()Ljava/lang/String;
    //   36: aload_1
    //   37: invokevirtual 1708	o/j:ˎ	(Ljava/lang/String;Landroid/os/Parcelable;)Lo/j;
    //   40: astore_1
    //   41: goto +38 -> 79
    //   44: getstatic 21	o/Ic:ˏ	I
    //   47: bipush 51
    //   49: iadd
    //   50: istore_2
    //   51: iload_2
    //   52: sipush 128
    //   55: irem
    //   56: putstatic 23	o/Ic:ॱॱ	I
    //   59: iload_2
    //   60: iconst_2
    //   61: irem
    //   62: ifne +6 -> 68
    //   65: goto +88 -> 153
    //   68: goto -63 -> 5
    //   71: iconst_2
    //   72: istore_2
    //   73: goto +46 -> 119
    //   76: astore_1
    //   77: aload_1
    //   78: athrow
    //   79: getstatic 21	o/Ic:ˏ	I
    //   82: istore_2
    //   83: iload_2
    //   84: bipush 71
    //   86: iadd
    //   87: istore_2
    //   88: iload_2
    //   89: sipush 128
    //   92: irem
    //   93: putstatic 23	o/Ic:ॱॱ	I
    //   96: iload_2
    //   97: iconst_2
    //   98: irem
    //   99: ifne +6 -> 105
    //   102: goto +54 -> 156
    //   105: goto -34 -> 71
    //   108: new 1694	java/lang/NullPointerException
    //   111: dup
    //   112: invokespecial 1695	java/lang/NullPointerException:<init>	()V
    //   115: athrow
    //   116: astore_1
    //   117: aload_1
    //   118: athrow
    //   119: iload_2
    //   120: lookupswitch	default:+28->148, 2:+-117->3, 82:+-12->108
    //   148: aload_1
    //   149: areturn
    //   150: goto -106 -> 44
    //   153: goto -148 -> 5
    //   156: bipush 82
    //   158: istore_2
    //   159: goto -40 -> 119
    // Local variable table:
    //   start	length	slot	name	signature
    //   0	162	0	this	Ic
    //   0	162	1	paramFG	FG
    //   50	109	2	i	int
    // Exception table:
    //   from	to	target	type
    //   79	83	76	java/lang/Exception
    //   88	96	116	java/lang/Exception
  }
  
  public j ˊ(Is paramIs)
  {
    for (;;)
    {
      try
      {
        Object localObject = ˎ(1012, 65323, 39);
        localObject = ((String)localObject).intern();
        localObject = new Intent((String)localObject);
        String str = ˎ(979, 'ҽ', 33);
        ((Intent)localObject).putExtra(str.intern(), paramIs);
        paramIs = new j(this.ˊ, (Intent)localObject);
      }
      catch (Exception paramIs)
      {
        throw paramIs;
      }
    }
    int i = ॱॱ + 17;
    ˏ = i % 128;
    if (i % 2 != 0) {
      return paramIs;
    }
    return paramIs;
  }
  
  public j ˊˊ()
  {
    label91:
    label93:
    for (;;)
    {
      try
      {
        localObject = this.ˊ;
      }
      catch (Exception localException1)
      {
        try
        {
          String str = ˎ(2051, '\000', 35);
          str = str.intern();
          Object localObject = j.ˏ((Context)localObject, str);
          continue;
          int i = ˏ + 29;
          ॱॱ = i % 128;
          if (i % 2 == 0) {
            break label93;
          }
          continue;
          i = ˏ + 75;
          ॱॱ = i % 128;
          if (i % 2 == 0) {
            break label91;
          }
          return localObject;
        }
        catch (Exception localException2)
        {
          throw localException2;
        }
        localException1 = localException1;
        throw localException1;
      }
      return localException2;
    }
  }
  
  public j ˊˋ()
  {
    j localJ;
    label31:
    int i;
    label37:
    for (;;)
    {
      localJ = j.ˏ(this.ˊ, ˎ(2150, '㎌', 28).intern());
      break label110;
      break;
      i = 11;
      break label79;
    }
    for (;;)
    {
      i = 8;
      break label79;
      i = 3 / 0;
      return localJ;
      i = ॱॱ + 17;
      ˏ = i % 128;
      if (i % 2 != 0) {
        break label37;
      }
      break;
      label79:
      switch (i)
      {
      }
      return localJ;
      label110:
      i = ˏ + 33;
      ॱॱ = i % 128;
      if (i % 2 == 0) {
        break label31;
      }
    }
  }
  
  public j ˊॱ()
  {
    Object localObject;
    for (;;)
    {
      switch (i)
      {
      default: 
        return localObject;
        i = ˏ + 111;
        ॱॱ = i % 128;
        if (i % 2 != 0) {
          break label105;
        }
        i = 0;
        break;
      case 1: 
        return localObject;
        for (;;)
        {
          localObject = new Intent(ˎ(943, '壜', 36).intern());
          localObject = new j(this.ˊ, (Intent)localObject);
          break;
        }
        label105:
        i = 1;
      }
    }
    int i = 20 / 0;
    return localObject;
  }
  
  public j ˊᐝ()
  {
    break label89;
    j localJ;
    label26:
    int i;
    for (;;)
    {
      localJ = j.ˏ(this.ˊ, ˎ(1854, '\000', 44).intern());
      break;
      i = ˏ + 125;
      ॱॱ = i % 128;
      if (i % 2 == 0) {
        break label125;
      }
    }
    for (;;)
    {
      switch (i)
      {
      default: 
        return localJ;
      case 84: 
        i = 63 / 0;
        return localJ;
        break label26;
        do
        {
          i = 84;
          break;
          i = ॱॱ + 41;
          ˏ = i % 128;
        } while (i % 2 != 0);
        break;
      case 25: 
        label89:
        label125:
        return localJ;
        i = 25;
      }
    }
  }
  
  public j ˋ()
  {
    break label55;
    int i = 1;
    break label30;
    label8:
    return j.ˏ(this.ˊ, ˎ(26607, 34934, 38).intern());
    for (;;)
    {
      switch (i)
      {
      case 0: 
      default: 
        break label8;
        i = ˏ + 99;
        ॱॱ = i % 128;
        if (i % 2 == 0) {}
        break;
      case 1: 
        label30:
        label55:
        return j.ˏ(this.ˊ, ˎ(320, 34934, 29).intern());
        i = 0;
      }
    }
  }
  
  public j ˋ(String paramString)
  {
    break label52;
    int i = 1;
    break label94;
    return paramString;
    for (;;)
    {
      i = 0;
      break label94;
      i = ॱॱ + 29;
      ˏ = i % 128;
      if (i % 2 != 0) {
        break;
      }
    }
    label42:
    break label55;
    i = 73 / 0;
    return paramString;
    for (;;)
    {
      label52:
      label55:
      paramString = j.ˏ(this.ˊ, paramString);
      break;
      i = ॱॱ + 53;
      ˏ = i % 128;
      if (i % 2 != 0) {
        break label42;
      }
    }
    label94:
    switch (i)
    {
    }
    return paramString;
  }
  
  /* Error */
  public j ˋ(String paramString1, String paramString2)
  {
    // Byte code:
    //   0: goto +6 -> 6
    //   3: astore_1
    //   4: aload_1
    //   5: athrow
    //   6: goto +237 -> 243
    //   9: getstatic 23	o/Ic:ॱॱ	I
    //   12: bipush 65
    //   14: iadd
    //   15: istore_3
    //   16: iload_3
    //   17: sipush 128
    //   20: irem
    //   21: putstatic 21	o/Ic:ˏ	I
    //   24: iload_3
    //   25: iconst_2
    //   26: irem
    //   27: ifeq +6 -> 33
    //   30: goto +6 -> 36
    //   33: goto +16 -> 49
    //   36: iconst_0
    //   37: istore_3
    //   38: goto +153 -> 191
    //   41: goto +111 -> 152
    //   44: aload_1
    //   45: areturn
    //   46: astore_1
    //   47: aload_1
    //   48: athrow
    //   49: iconst_1
    //   50: istore_3
    //   51: goto +140 -> 191
    //   54: aload_0
    //   55: getfield 35	o/Ic:ˊ	Landroid/content/Context;
    //   58: astore 4
    //   60: sipush 1925
    //   63: ldc_w 1785
    //   66: bipush 35
    //   68: invokestatic 1653	o/Ic:ˎ	(ICI)Ljava/lang/String;
    //   71: astore 5
    //   73: aload 5
    //   75: invokevirtual 1657	java/lang/String:intern	()Ljava/lang/String;
    //   78: astore 5
    //   80: aload 4
    //   82: aload 5
    //   84: invokestatic 1671	o/j:ˏ	(Landroid/content/Context;Ljava/lang/String;)Lo/j;
    //   87: sipush 1960
    //   90: iconst_0
    //   91: bipush 15
    //   93: invokestatic 1653	o/Ic:ˎ	(ICI)Ljava/lang/String;
    //   96: invokevirtual 1657	java/lang/String:intern	()Ljava/lang/String;
    //   99: aload_1
    //   100: invokevirtual 1676	o/j:ˋ	(Ljava/lang/String;Ljava/lang/String;)Lo/j;
    //   103: sipush 1975
    //   106: sipush 3206
    //   109: bipush 13
    //   111: invokestatic 1653	o/Ic:ˎ	(ICI)Ljava/lang/String;
    //   114: invokevirtual 1657	java/lang/String:intern	()Ljava/lang/String;
    //   117: aload_2
    //   118: invokevirtual 1676	o/j:ˋ	(Ljava/lang/String;Ljava/lang/String;)Lo/j;
    //   121: astore_1
    //   122: goto -113 -> 9
    //   125: aload_0
    //   126: getfield 35	o/Ic:ˊ	Landroid/content/Context;
    //   129: sipush 523
    //   132: iconst_0
    //   133: bipush 26
    //   135: invokestatic 1653	o/Ic:ˎ	(ICI)Ljava/lang/String;
    //   138: invokevirtual 1657	java/lang/String:intern	()Ljava/lang/String;
    //   141: invokestatic 1671	o/j:ˏ	(Landroid/content/Context;Ljava/lang/String;)Lo/j;
    //   144: aload_2
    //   145: invokestatic 1791	android/net/Uri:parse	(Ljava/lang/String;)Landroid/net/Uri;
    //   148: invokevirtual 1794	o/j:ˊ	(Landroid/net/Uri;)Lo/j;
    //   151: areturn
    //   152: aload_2
    //   153: sipush 1921
    //   156: ldc_w 1795
    //   159: iconst_4
    //   160: invokestatic 1653	o/Ic:ˎ	(ICI)Ljava/lang/String;
    //   163: invokevirtual 1657	java/lang/String:intern	()Ljava/lang/String;
    //   166: invokevirtual 1798	java/lang/String:endsWith	(Ljava/lang/String;)Z
    //   169: ifeq +6 -> 175
    //   172: goto +6 -> 178
    //   175: goto +95 -> 270
    //   178: iconst_0
    //   179: istore_3
    //   180: goto +38 -> 218
    //   183: new 1694	java/lang/NullPointerException
    //   186: dup
    //   187: invokespecial 1695	java/lang/NullPointerException:<init>	()V
    //   190: athrow
    //   191: iload_3
    //   192: tableswitch	default:+24->216, 0:+-9->183, 1:+-148->44
    //   216: aload_1
    //   217: areturn
    //   218: iload_3
    //   219: tableswitch	default:+21->240, 0:+-94->125, 1:+-165->54
    //   240: goto -186 -> 54
    //   243: getstatic 23	o/Ic:ॱॱ	I
    //   246: bipush 95
    //   248: iadd
    //   249: istore_3
    //   250: iload_3
    //   251: sipush 128
    //   254: irem
    //   255: putstatic 21	o/Ic:ˏ	I
    //   258: iload_3
    //   259: iconst_2
    //   260: irem
    //   261: ifeq +6 -> 267
    //   264: goto -223 -> 41
    //   267: goto -115 -> 152
    //   270: iconst_1
    //   271: istore_3
    //   272: goto -54 -> 218
    // Local variable table:
    //   start	length	slot	name	signature
    //   0	275	0	this	Ic
    //   0	275	1	paramString1	String
    //   0	275	2	paramString2	String
    //   15	257	3	i	int
    //   58	23	4	localContext	Context
    //   71	12	5	str	String
    // Exception table:
    //   from	to	target	type
    //   54	60	3	java/lang/Exception
    //   60	73	3	java/lang/Exception
    //   73	80	3	java/lang/Exception
    //   80	122	3	java/lang/Exception
    //   60	73	46	java/lang/Exception
  }
  
  public j ˋ(FT paramFT)
  {
    int i;
    for (;;)
    {
      i = 14;
      try
      {
        i = ˏ + 39;
        ॱॱ = i % 128;
        if (i % 2 != 0)
        {
          continue;
          label36:
          break;
          return paramFT;
          break label132;
        }
        else
        {
          for (;;)
          {
            switch (i)
            {
            case 14: 
            default: 
              return paramFT;
              i = 29;
            }
          }
          throw new NullPointerException();
        }
      }
      catch (Exception paramFT)
      {
        throw paramFT;
      }
    }
    for (;;)
    {
      paramFT = j.ˏ(this.ˊ, ˎ(843, '⏤', 40).intern()).ˊ(ˎ(883, '\000', 23).intern(), paramFT);
      break;
      label132:
      i = ॱॱ + 23;
      ˏ = i % 128;
      if (i % 2 != 0) {
        break label36;
      }
    }
  }
  
  public j ˋ(Gm paramGm)
  {
    int i;
    switch (i)
    {
    default: 
      break;
      i = 33 / 0;
      return paramGm;
    case 69: 
      paramGm = j.ˏ(this.ˊ, ˎ(14484, '嵃', 79).intern()).ˋ(ˎ(1280, '\000', 127).intern(), paramGm.name());
      break label178;
      label86:
      i = 28;
      break label95;
      label92:
      i = 86;
      switch (i)
      {
      case 28: 
      default: 
        label95:
        return paramGm;
      }
      break;
    }
    for (;;)
    {
      i = 39;
      break;
      return paramGm;
      paramGm = j.ˏ(this.ˊ, ˎ(1539, '嵃', 26).intern()).ˋ(ˎ(1565, '\000', 23).intern(), paramGm.name());
      label178:
      i = ॱॱ + 123;
      ˏ = i % 128;
      if (i % 2 != 0) {
        break label86;
      }
      break label92;
      do
      {
        i = 69;
        break;
        i = ˏ + 33;
        ॱॱ = i % 128;
      } while (i % 2 == 0);
    }
  }
  
  public j ˋˊ()
  {
    for (;;)
    {
      int i = ॱॱ + 69;
      ˏ = i % 128;
      if (i % 2 == 0) {
        return localJ;
      }
      return localJ;
      i = ॱॱ + 49;
      ˏ = i % 128;
      if (i % 2 == 0) {
        break label58;
      }
      label58:
      j localJ = j.ˏ(this.ˊ, ˎ(1898, '\000', 23).intern());
    }
  }
  
  /* Error */
  public j ˋˋ()
  {
    // Byte code:
    //   0: goto +38 -> 38
    //   3: bipush 65
    //   5: istore_1
    //   6: iload_1
    //   7: lookupswitch	default:+25->32, 51:+61->68, 65:+69->76
    //   32: goto +36 -> 68
    //   35: astore_2
    //   36: aload_2
    //   37: athrow
    //   38: goto +49 -> 87
    //   41: getstatic 23	o/Ic:ॱॱ	I
    //   44: bipush 117
    //   46: iadd
    //   47: istore_1
    //   48: iload_1
    //   49: sipush 128
    //   52: irem
    //   53: putstatic 21	o/Ic:ˏ	I
    //   56: iload_1
    //   57: iconst_2
    //   58: irem
    //   59: ifeq +6 -> 65
    //   62: goto +16 -> 78
    //   65: goto -62 -> 3
    //   68: new 1694	java/lang/NullPointerException
    //   71: dup
    //   72: invokespecial 1695	java/lang/NullPointerException:<init>	()V
    //   75: athrow
    //   76: aload_2
    //   77: areturn
    //   78: bipush 51
    //   80: istore_1
    //   81: goto -75 -> 6
    //   84: goto +27 -> 111
    //   87: getstatic 21	o/Ic:ˏ	I
    //   90: bipush 61
    //   92: iadd
    //   93: istore_1
    //   94: iload_1
    //   95: sipush 128
    //   98: irem
    //   99: putstatic 23	o/Ic:ॱॱ	I
    //   102: iload_1
    //   103: iconst_2
    //   104: irem
    //   105: ifne +6 -> 111
    //   108: goto -24 -> 84
    //   111: aload_0
    //   112: getfield 35	o/Ic:ˊ	Landroid/content/Context;
    //   115: sipush 2178
    //   118: ldc_w 1811
    //   121: bipush 33
    //   123: invokestatic 1653	o/Ic:ˎ	(ICI)Ljava/lang/String;
    //   126: invokevirtual 1657	java/lang/String:intern	()Ljava/lang/String;
    //   129: invokestatic 1671	o/j:ˏ	(Landroid/content/Context;Ljava/lang/String;)Lo/j;
    //   132: astore_2
    //   133: goto -92 -> 41
    // Local variable table:
    //   start	length	slot	name	signature
    //   0	136	0	this	Ic
    //   5	100	1	i	int
    //   35	42	2	localException	Exception
    //   132	1	2	localJ	j
    // Exception table:
    //   from	to	target	type
    //   87	94	35	java/lang/Exception
    //   94	102	35	java/lang/Exception
  }
  
  public j ˋॱ()
  {
    break label107;
    for (;;)
    {
      Object localObject = new Intent();
      try
      {
        str = ˎ(1120, '\000', 45);
        str = str.intern();
      }
      catch (Exception localException1)
      {
        try
        {
          String str;
          ((Intent)localObject).setAction(str);
          ((Intent)localObject).setData(Uri.fromParts(ˎ(1165, '\000', 7).intern(), this.ˊ.getPackageName(), null));
          localObject = new j(this.ˊ, (Intent)localObject);
          int i = ˏ + 101;
          ॱॱ = i % 128;
          if (i % 2 == 0) {
            return localObject;
          }
          return localObject;
        }
        catch (Exception localException2)
        {
          throw localException2;
        }
        localException1 = localException1;
        throw localException1;
      }
    }
  }
  
  /* Error */
  public j ˋᐝ()
  {
    // Byte code:
    //   0: goto +90 -> 90
    //   3: iconst_0
    //   4: istore_1
    //   5: goto +31 -> 36
    //   8: astore_2
    //   9: aload_2
    //   10: athrow
    //   11: aload_0
    //   12: getfield 35	o/Ic:ˊ	Landroid/content/Context;
    //   15: sipush 18583
    //   18: ldc_w 1830
    //   21: bipush 125
    //   23: invokestatic 1653	o/Ic:ˎ	(ICI)Ljava/lang/String;
    //   26: invokevirtual 1657	java/lang/String:intern	()Ljava/lang/String;
    //   29: invokestatic 1671	o/j:ˏ	(Landroid/content/Context;Ljava/lang/String;)Lo/j;
    //   32: astore_2
    //   33: goto +30 -> 63
    //   36: iload_1
    //   37: tableswitch	default:+23->60, 0:+-26->11, 1:+56->93
    //   60: goto +33 -> 93
    //   63: getstatic 21	o/Ic:ˏ	I
    //   66: istore_1
    //   67: iload_1
    //   68: bipush 103
    //   70: iadd
    //   71: istore_1
    //   72: iload_1
    //   73: sipush 128
    //   76: irem
    //   77: putstatic 23	o/Ic:ॱॱ	I
    //   80: iload_1
    //   81: iconst_2
    //   82: irem
    //   83: ifne +5 -> 88
    //   86: aload_2
    //   87: areturn
    //   88: aload_2
    //   89: areturn
    //   90: goto +33 -> 123
    //   93: aload_0
    //   94: getfield 35	o/Ic:ˊ	Landroid/content/Context;
    //   97: sipush 2258
    //   100: ldc_w 1830
    //   103: bipush 28
    //   105: invokestatic 1653	o/Ic:ˎ	(ICI)Ljava/lang/String;
    //   108: invokevirtual 1657	java/lang/String:intern	()Ljava/lang/String;
    //   111: invokestatic 1671	o/j:ˏ	(Landroid/content/Context;Ljava/lang/String;)Lo/j;
    //   114: astore_2
    //   115: goto -52 -> 63
    //   118: iconst_1
    //   119: istore_1
    //   120: goto -84 -> 36
    //   123: getstatic 21	o/Ic:ˏ	I
    //   126: bipush 85
    //   128: iadd
    //   129: istore_1
    //   130: iload_1
    //   131: sipush 128
    //   134: irem
    //   135: putstatic 23	o/Ic:ॱॱ	I
    //   138: iload_1
    //   139: iconst_2
    //   140: irem
    //   141: ifne +6 -> 147
    //   144: goto -141 -> 3
    //   147: goto -29 -> 118
    // Local variable table:
    //   start	length	slot	name	signature
    //   0	150	0	this	Ic
    //   4	137	1	i	int
    //   8	2	2	localException	Exception
    //   32	83	2	localJ	j
    // Exception table:
    //   from	to	target	type
    //   63	67	8	java/lang/Exception
    //   72	80	8	java/lang/Exception
  }
  
  /* Error */
  public j ˎ()
  {
    // Byte code:
    //   0: goto +91 -> 91
    //   3: iload_1
    //   4: lookupswitch	default:+28->32, 10:+31->35, 78:+96->100
    //   32: goto +68 -> 100
    //   35: aload_0
    //   36: getfield 35	o/Ic:ˊ	Landroid/content/Context;
    //   39: sipush 24353
    //   42: iconst_0
    //   43: bipush 95
    //   45: invokestatic 1653	o/Ic:ˎ	(ICI)Ljava/lang/String;
    //   48: invokevirtual 1657	java/lang/String:intern	()Ljava/lang/String;
    //   51: invokestatic 1671	o/j:ˏ	(Landroid/content/Context;Ljava/lang/String;)Lo/j;
    //   54: areturn
    //   55: getstatic 21	o/Ic:ˏ	I
    //   58: bipush 99
    //   60: iadd
    //   61: istore_1
    //   62: iload_1
    //   63: sipush 128
    //   66: irem
    //   67: putstatic 23	o/Ic:ॱॱ	I
    //   70: iload_1
    //   71: iconst_2
    //   72: irem
    //   73: ifne +6 -> 79
    //   76: goto +9 -> 85
    //   79: goto +15 -> 94
    //   82: astore_2
    //   83: aload_2
    //   84: athrow
    //   85: bipush 10
    //   87: istore_1
    //   88: goto -85 -> 3
    //   91: goto -36 -> 55
    //   94: bipush 78
    //   96: istore_1
    //   97: goto -94 -> 3
    //   100: aload_0
    //   101: getfield 35	o/Ic:ˊ	Landroid/content/Context;
    //   104: astore_2
    //   105: sipush 349
    //   108: iconst_0
    //   109: bipush 25
    //   111: invokestatic 1653	o/Ic:ˎ	(ICI)Ljava/lang/String;
    //   114: astore_3
    //   115: aload_3
    //   116: invokevirtual 1657	java/lang/String:intern	()Ljava/lang/String;
    //   119: astore_3
    //   120: aload_2
    //   121: aload_3
    //   122: invokestatic 1671	o/j:ˏ	(Landroid/content/Context;Ljava/lang/String;)Lo/j;
    //   125: astore_2
    //   126: aload_2
    //   127: areturn
    //   128: astore_2
    //   129: aload_2
    //   130: athrow
    // Local variable table:
    //   start	length	slot	name	signature
    //   0	131	0	this	Ic
    //   3	94	1	i	int
    //   82	2	2	localException1	Exception
    //   104	23	2	localObject	Object
    //   128	2	2	localException2	Exception
    //   114	8	3	str	String
    // Exception table:
    //   from	to	target	type
    //   105	115	82	java/lang/Exception
    //   115	120	82	java/lang/Exception
    //   120	126	82	java/lang/Exception
    //   100	105	128	java/lang/Exception
  }
  
  public j ˎ(String paramString)
  {
    for (;;)
    {
      int i;
      switch (i)
      {
      default: 
        break label140;
        i = ॱॱ + 121;
        ˏ = i % 128;
        if (i % 2 != 0) {}
        break;
      case 0: 
        return paramString;
        for (;;)
        {
          Intent localIntent = new Intent(ˎ(549, '\000', 26).intern());
          localIntent.setData(Uri.parse(ˎ(575, '\000', 4).intern() + paramString));
          paramString = new j(this.ˊ, localIntent);
          break;
        }
        i = 1;
        break;
      case 1: 
        label140:
        i = null.length;
        return paramString;
        i = 0;
      }
    }
  }
  
  /* Error */
  public j ˎ(Eu paramEu)
  {
    // Byte code:
    //   0: goto +6 -> 6
    //   3: astore_1
    //   4: aload_1
    //   5: athrow
    //   6: goto +15 -> 21
    //   9: bipush 92
    //   11: istore_2
    //   12: goto +36 -> 48
    //   15: bipush 81
    //   17: istore_2
    //   18: goto +192 -> 210
    //   21: getstatic 21	o/Ic:ˏ	I
    //   24: bipush 121
    //   26: iadd
    //   27: istore_2
    //   28: iload_2
    //   29: sipush 128
    //   32: irem
    //   33: putstatic 23	o/Ic:ॱॱ	I
    //   36: iload_2
    //   37: iconst_2
    //   38: irem
    //   39: ifne +6 -> 45
    //   42: goto -33 -> 9
    //   45: goto +34 -> 79
    //   48: iload_2
    //   49: lookupswitch	default:+27->76, 51:+110->159, 92:+36->85
    //   76: goto +9 -> 85
    //   79: bipush 51
    //   81: istore_2
    //   82: goto -34 -> 48
    //   85: aload_0
    //   86: getfield 35	o/Ic:ˊ	Landroid/content/Context;
    //   89: sipush 17703
    //   92: iconst_0
    //   93: bipush 90
    //   95: invokestatic 1653	o/Ic:ˎ	(ICI)Ljava/lang/String;
    //   98: invokevirtual 1657	java/lang/String:intern	()Ljava/lang/String;
    //   101: invokestatic 1671	o/j:ˏ	(Landroid/content/Context;Ljava/lang/String;)Lo/j;
    //   104: sipush 31422
    //   107: iconst_0
    //   108: iconst_1
    //   109: invokestatic 1653	o/Ic:ˎ	(ICI)Ljava/lang/String;
    //   112: invokevirtual 1657	java/lang/String:intern	()Ljava/lang/String;
    //   115: aload_1
    //   116: invokevirtual 1708	o/j:ˎ	(Ljava/lang/String;Landroid/os/Parcelable;)Lo/j;
    //   119: astore_1
    //   120: getstatic 23	o/Ic:ॱॱ	I
    //   123: iconst_3
    //   124: iadd
    //   125: istore_2
    //   126: iload_2
    //   127: sipush 128
    //   130: irem
    //   131: putstatic 21	o/Ic:ˏ	I
    //   134: iload_2
    //   135: iconst_2
    //   136: irem
    //   137: ifeq +6 -> 143
    //   140: goto +98 -> 238
    //   143: goto -128 -> 15
    //   146: new 1694	java/lang/NullPointerException
    //   149: dup
    //   150: invokespecial 1695	java/lang/NullPointerException:<init>	()V
    //   153: athrow
    //   154: aload_1
    //   155: areturn
    //   156: astore_1
    //   157: aload_1
    //   158: athrow
    //   159: aload_0
    //   160: getfield 35	o/Ic:ˊ	Landroid/content/Context;
    //   163: astore_3
    //   164: sipush 1051
    //   167: iconst_0
    //   168: bipush 21
    //   170: invokestatic 1653	o/Ic:ˎ	(ICI)Ljava/lang/String;
    //   173: astore 4
    //   175: aload 4
    //   177: invokevirtual 1657	java/lang/String:intern	()Ljava/lang/String;
    //   180: astore 4
    //   182: aload_3
    //   183: aload 4
    //   185: invokestatic 1671	o/j:ˏ	(Landroid/content/Context;Ljava/lang/String;)Lo/j;
    //   188: astore_3
    //   189: aload_3
    //   190: sipush 162
    //   193: iconst_0
    //   194: bipush 18
    //   196: invokestatic 1653	o/Ic:ˎ	(ICI)Ljava/lang/String;
    //   199: invokevirtual 1657	java/lang/String:intern	()Ljava/lang/String;
    //   202: aload_1
    //   203: invokevirtual 1708	o/j:ˎ	(Ljava/lang/String;Landroid/os/Parcelable;)Lo/j;
    //   206: astore_1
    //   207: goto -87 -> 120
    //   210: iload_2
    //   211: lookupswitch	default:+25->236, 49:+-65->146, 81:+-57->154
    //   236: aload_1
    //   237: areturn
    //   238: bipush 49
    //   240: istore_2
    //   241: goto -31 -> 210
    // Local variable table:
    //   start	length	slot	name	signature
    //   0	244	0	this	Ic
    //   0	244	1	paramEu	Eu
    //   11	230	2	i	int
    //   163	27	3	localObject	Object
    //   173	11	4	str	String
    // Exception table:
    //   from	to	target	type
    //   159	164	3	java/lang/Exception
    //   164	175	156	java/lang/Exception
    //   175	182	156	java/lang/Exception
    //   182	189	156	java/lang/Exception
    //   189	207	156	java/lang/Exception
  }
  
  public j ˎ(Eu paramEu, Er paramEr, String paramString)
  {
    for (;;)
    {
      int i = ˏ + 43;
      ॱॱ = i % 128;
      if (i % 2 != 0) {
        break label65;
      }
      for (;;)
      {
        i = ˏ + 55;
        ॱॱ = i % 128;
        if (i % 2 == 0) {
          break;
        }
        return paramEu;
        label65:
        paramEu = j.ˏ(this.ˊ, ˎ(1072, '\000', 33).intern()).ˎ(ˎ(162, '\000', 18).intern(), paramEu).ˊ(ˎ(1105, 43656, 15).intern(), paramEr).ˋ(ˎ(180, '\000', 14).intern(), paramString);
      }
    }
    return paramEu;
  }
  
  /* Error */
  public j ˎ(Is paramIs)
  {
    // Byte code:
    //   0: goto +97 -> 97
    //   3: getstatic 21	o/Ic:ˏ	I
    //   6: bipush 55
    //   8: iadd
    //   9: istore_2
    //   10: iload_2
    //   11: sipush 128
    //   14: irem
    //   15: putstatic 23	o/Ic:ॱॱ	I
    //   18: iload_2
    //   19: iconst_2
    //   20: irem
    //   21: ifne +6 -> 27
    //   24: goto +76 -> 100
    //   27: aload_1
    //   28: areturn
    //   29: astore_1
    //   30: aload_1
    //   31: athrow
    //   32: astore_1
    //   33: aload_1
    //   34: athrow
    //   35: sipush 943
    //   38: sipush 22748
    //   41: bipush 36
    //   43: invokestatic 1653	o/Ic:ˎ	(ICI)Ljava/lang/String;
    //   46: astore_3
    //   47: aload_3
    //   48: invokevirtual 1657	java/lang/String:intern	()Ljava/lang/String;
    //   51: astore_3
    //   52: new 1679	android/content/Intent
    //   55: dup
    //   56: aload_3
    //   57: invokespecial 1682	android/content/Intent:<init>	(Ljava/lang/String;)V
    //   60: astore_3
    //   61: aload_3
    //   62: sipush 979
    //   65: sipush 1213
    //   68: bipush 33
    //   70: invokestatic 1653	o/Ic:ˎ	(ICI)Ljava/lang/String;
    //   73: invokevirtual 1657	java/lang/String:intern	()Ljava/lang/String;
    //   76: aload_1
    //   77: invokevirtual 1779	android/content/Intent:putExtra	(Ljava/lang/String;Landroid/os/Parcelable;)Landroid/content/Intent;
    //   80: pop
    //   81: new 1668	o/j
    //   84: dup
    //   85: aload_0
    //   86: getfield 35	o/Ic:ˊ	Landroid/content/Context;
    //   89: aload_3
    //   90: invokespecial 1685	o/j:<init>	(Landroid/content/Context;Landroid/content/Intent;)V
    //   93: astore_1
    //   94: goto -91 -> 3
    //   97: goto -62 -> 35
    //   100: aload_1
    //   101: areturn
    // Local variable table:
    //   start	length	slot	name	signature
    //   0	102	0	this	Ic
    //   0	102	1	paramIs	Is
    //   9	12	2	i	int
    //   46	44	3	localObject	Object
    // Exception table:
    //   from	to	target	type
    //   61	94	29	java/lang/Exception
    //   35	47	32	java/lang/Exception
    //   47	52	32	java/lang/Exception
    //   52	61	32	java/lang/Exception
    //   61	94	32	java/lang/Exception
  }
  
  /* Error */
  public j ˏ()
  {
    // Byte code:
    //   0: goto +6 -> 6
    //   3: astore_2
    //   4: aload_2
    //   5: athrow
    //   6: getstatic 21	o/Ic:ˏ	I
    //   9: bipush 99
    //   11: iadd
    //   12: istore_1
    //   13: iload_1
    //   14: sipush 128
    //   17: irem
    //   18: putstatic 23	o/Ic:ॱॱ	I
    //   21: iload_1
    //   22: iconst_2
    //   23: irem
    //   24: ifne +6 -> 30
    //   27: goto +89 -> 116
    //   30: goto +6 -> 36
    //   33: astore_2
    //   34: aload_2
    //   35: athrow
    //   36: aload_0
    //   37: getfield 35	o/Ic:ˊ	Landroid/content/Context;
    //   40: bipush 57
    //   42: iconst_0
    //   43: bipush 49
    //   45: invokestatic 1653	o/Ic:ˎ	(ICI)Ljava/lang/String;
    //   48: invokevirtual 1657	java/lang/String:intern	()Ljava/lang/String;
    //   51: invokestatic 1671	o/j:ˏ	(Landroid/content/Context;Ljava/lang/String;)Lo/j;
    //   54: bipush 106
    //   56: ldc_w 1844
    //   59: bipush 13
    //   61: invokestatic 1653	o/Ic:ˎ	(ICI)Ljava/lang/String;
    //   64: invokevirtual 1657	java/lang/String:intern	()Ljava/lang/String;
    //   67: ldc_w 1846
    //   70: invokevirtual 1676	o/j:ˋ	(Ljava/lang/String;Ljava/lang/String;)Lo/j;
    //   73: bipush 119
    //   75: iconst_0
    //   76: bipush 16
    //   78: invokestatic 1653	o/Ic:ˎ	(ICI)Ljava/lang/String;
    //   81: invokevirtual 1657	java/lang/String:intern	()Ljava/lang/String;
    //   84: ldc_w 1846
    //   87: invokevirtual 1676	o/j:ˋ	(Ljava/lang/String;Ljava/lang/String;)Lo/j;
    //   90: astore_2
    //   91: getstatic 21	o/Ic:ˏ	I
    //   94: bipush 47
    //   96: iadd
    //   97: istore_1
    //   98: iload_1
    //   99: sipush 128
    //   102: irem
    //   103: putstatic 23	o/Ic:ॱॱ	I
    //   106: iload_1
    //   107: iconst_2
    //   108: irem
    //   109: ifne +5 -> 114
    //   112: aload_2
    //   113: areturn
    //   114: aload_2
    //   115: areturn
    //   116: goto -80 -> 36
    // Local variable table:
    //   start	length	slot	name	signature
    //   0	119	0	this	Ic
    //   12	97	1	i	int
    //   3	2	2	localException1	Exception
    //   33	2	2	localException2	Exception
    //   90	25	2	localJ	j
    // Exception table:
    //   from	to	target	type
    //   91	98	3	java/lang/Exception
    //   98	106	3	java/lang/Exception
    //   98	106	33	java/lang/Exception
  }
  
  /* Error */
  public j ˏ(String paramString)
  {
    // Byte code:
    //   0: goto +158 -> 158
    //   3: goto +9 -> 12
    //   6: bipush 12
    //   8: istore_2
    //   9: goto +152 -> 161
    //   12: new 1679	android/content/Intent
    //   15: dup
    //   16: sipush 523
    //   19: iconst_0
    //   20: bipush 26
    //   22: invokestatic 1653	o/Ic:ˎ	(ICI)Ljava/lang/String;
    //   25: invokevirtual 1657	java/lang/String:intern	()Ljava/lang/String;
    //   28: aload_1
    //   29: invokespecial 1851	android/content/Intent:<init>	(Ljava/lang/String;Landroid/net/Uri;)V
    //   32: astore_1
    //   33: new 1668	o/j
    //   36: dup
    //   37: aload_0
    //   38: getfield 35	o/Ic:ˊ	Landroid/content/Context;
    //   41: aload_1
    //   42: invokespecial 1685	o/j:<init>	(Landroid/content/Context;Landroid/content/Intent;)V
    //   45: areturn
    //   46: bipush 93
    //   48: istore_2
    //   49: goto +112 -> 161
    //   52: getstatic 21	o/Ic:ˏ	I
    //   55: bipush 47
    //   57: iadd
    //   58: istore_2
    //   59: iload_2
    //   60: sipush 128
    //   63: irem
    //   64: putstatic 23	o/Ic:ॱॱ	I
    //   67: iload_2
    //   68: iconst_2
    //   69: irem
    //   70: ifne +6 -> 76
    //   73: goto -67 -> 6
    //   76: goto -30 -> 46
    //   79: goto -67 -> 12
    //   82: astore_1
    //   83: aload_3
    //   84: invokestatic 1791	android/net/Uri:parse	(Ljava/lang/String;)Landroid/net/Uri;
    //   87: astore_1
    //   88: goto -76 -> 12
    //   91: aload_1
    //   92: invokestatic 1855	o/aq:ʻ	(Ljava/lang/String;)Ljava/lang/String;
    //   95: astore_3
    //   96: aload_0
    //   97: getfield 35	o/Ic:ˊ	Landroid/content/Context;
    //   100: invokevirtual 1859	android/content/Context:getPackageManager	()Landroid/content/pm/PackageManager;
    //   103: sipush 479
    //   106: iconst_0
    //   107: bipush 19
    //   109: invokestatic 1653	o/Ic:ˎ	(ICI)Ljava/lang/String;
    //   112: invokevirtual 1657	java/lang/String:intern	()Ljava/lang/String;
    //   115: iconst_0
    //   116: invokevirtual 1865	android/content/pm/PackageManager:getPackageInfo	(Ljava/lang/String;I)Landroid/content/pm/PackageInfo;
    //   119: pop
    //   120: new 1832	java/lang/StringBuilder
    //   123: dup
    //   124: invokespecial 1833	java/lang/StringBuilder:<init>	()V
    //   127: sipush 498
    //   130: sipush 32590
    //   133: bipush 25
    //   135: invokestatic 1653	o/Ic:ˎ	(ICI)Ljava/lang/String;
    //   138: invokevirtual 1657	java/lang/String:intern	()Ljava/lang/String;
    //   141: invokevirtual 1837	java/lang/StringBuilder:append	(Ljava/lang/String;)Ljava/lang/StringBuilder;
    //   144: aload_3
    //   145: invokevirtual 1837	java/lang/StringBuilder:append	(Ljava/lang/String;)Ljava/lang/StringBuilder;
    //   148: invokevirtual 1840	java/lang/StringBuilder:toString	()Ljava/lang/String;
    //   151: invokestatic 1791	android/net/Uri:parse	(Ljava/lang/String;)Landroid/net/Uri;
    //   154: astore_1
    //   155: goto -103 -> 52
    //   158: goto -67 -> 91
    //   161: iload_2
    //   162: lookupswitch	default:+26->188, 12:+-159->3, 93:+-83->79
    //   188: goto -109 -> 79
    // Local variable table:
    //   start	length	slot	name	signature
    //   0	191	0	this	Ic
    //   0	191	1	paramString	String
    //   8	154	2	i	int
    //   83	62	3	str	String
    // Exception table:
    //   from	to	target	type
    //   96	155	82	android/content/pm/PackageManager$NameNotFoundException
  }
  
  /* Error */
  public j ˏ(FT paramFT)
  {
    // Byte code:
    //   0: goto +47 -> 47
    //   3: new 1694	java/lang/NullPointerException
    //   6: dup
    //   7: invokespecial 1695	java/lang/NullPointerException:<init>	()V
    //   10: athrow
    //   11: astore_1
    //   12: aload_1
    //   13: athrow
    //   14: bipush 20
    //   16: istore_2
    //   17: iload_2
    //   18: lookupswitch	default:+26->44, 20:+128->146, 57:+-15->3
    //   44: goto -41 -> 3
    //   47: goto +36 -> 83
    //   50: getstatic 21	o/Ic:ˏ	I
    //   53: bipush 89
    //   55: iadd
    //   56: istore_2
    //   57: iload_2
    //   58: sipush 128
    //   61: irem
    //   62: putstatic 23	o/Ic:ॱॱ	I
    //   65: iload_2
    //   66: iconst_2
    //   67: irem
    //   68: ifne +6 -> 74
    //   71: goto +6 -> 77
    //   74: goto -60 -> 14
    //   77: bipush 57
    //   79: istore_2
    //   80: goto -63 -> 17
    //   83: sipush 906
    //   86: iconst_0
    //   87: bipush 37
    //   89: invokestatic 1653	o/Ic:ˎ	(ICI)Ljava/lang/String;
    //   92: astore_3
    //   93: aload_3
    //   94: invokevirtual 1657	java/lang/String:intern	()Ljava/lang/String;
    //   97: astore_3
    //   98: new 1679	android/content/Intent
    //   101: dup
    //   102: aload_3
    //   103: invokespecial 1682	android/content/Intent:<init>	(Ljava/lang/String;)V
    //   106: astore 4
    //   108: sipush 883
    //   111: iconst_0
    //   112: bipush 23
    //   114: invokestatic 1653	o/Ic:ˎ	(ICI)Ljava/lang/String;
    //   117: astore_3
    //   118: aload 4
    //   120: aload_3
    //   121: invokevirtual 1657	java/lang/String:intern	()Ljava/lang/String;
    //   124: aload_1
    //   125: invokevirtual 1769	android/content/Intent:putExtra	(Ljava/lang/String;Ljava/io/Serializable;)Landroid/content/Intent;
    //   128: pop
    //   129: new 1668	o/j
    //   132: dup
    //   133: aload_0
    //   134: getfield 35	o/Ic:ˊ	Landroid/content/Context;
    //   137: aload 4
    //   139: invokespecial 1685	o/j:<init>	(Landroid/content/Context;Landroid/content/Intent;)V
    //   142: astore_1
    //   143: goto -93 -> 50
    //   146: aload_1
    //   147: areturn
    // Local variable table:
    //   start	length	slot	name	signature
    //   0	148	0	this	Ic
    //   0	148	1	paramFT	FT
    //   16	64	2	i	int
    //   92	29	3	str	String
    //   106	32	4	localIntent	Intent
    // Exception table:
    //   from	to	target	type
    //   83	93	11	java/lang/Exception
    //   93	98	11	java/lang/Exception
    //   108	118	11	java/lang/Exception
  }
  
  public j ˏ(HQ paramHQ)
  {
    break label111;
    paramHQ = ˎ(paramHQ.ॱ()).ˋ(ˎ(656, '疉', 24).intern(), paramHQ.ॱॱ());
    for (;;)
    {
      throw new NullPointerException();
      label44:
      int i = 3;
      break label114;
      label49:
      break;
      label111:
      for (;;)
      {
        i = ॱॱ + 83;
        ˏ = i % 128;
        if (i % 2 != 0) {
          break label49;
        }
        break;
        i = ॱॱ + 73;
        ˏ = i % 128;
        if (i % 2 != 0) {
          break label44;
        }
        i = 84;
        break label114;
        return paramHQ;
      }
      label114:
      switch (i)
      {
      }
    }
  }
  
  /* Error */
  public j ˏ(boolean paramBoolean1, boolean paramBoolean2)
  {
    // Byte code:
    //   0: goto +195 -> 195
    //   3: iload_2
    //   4: ifeq +6 -> 10
    //   7: goto +199 -> 206
    //   10: aload 4
    //   12: areturn
    //   13: bipush 27
    //   15: istore_3
    //   16: goto +117 -> 133
    //   19: aload 4
    //   21: sipush 705
    //   24: sipush 20678
    //   27: bipush 46
    //   29: invokestatic 1653	o/Ic:ˎ	(ICI)Ljava/lang/String;
    //   32: invokevirtual 1657	java/lang/String:intern	()Ljava/lang/String;
    //   35: iconst_1
    //   36: invokevirtual 1879	o/j:ˏ	(Ljava/lang/String;Z)Lo/j;
    //   39: iconst_1
    //   40: newarray int
    //   42: dup
    //   43: iconst_0
    //   44: ldc_w 1880
    //   47: iastore
    //   48: invokevirtual 1883	o/j:ˏ	([I)Lo/j;
    //   51: pop
    //   52: goto +228 -> 280
    //   55: bipush 31
    //   57: istore_3
    //   58: goto +75 -> 133
    //   61: aload_0
    //   62: getfield 35	o/Ic:ˊ	Landroid/content/Context;
    //   65: sipush 680
    //   68: ldc_w 1884
    //   71: bipush 25
    //   73: invokestatic 1653	o/Ic:ˎ	(ICI)Ljava/lang/String;
    //   76: invokevirtual 1657	java/lang/String:intern	()Ljava/lang/String;
    //   79: invokestatic 1671	o/j:ˏ	(Landroid/content/Context;Ljava/lang/String;)Lo/j;
    //   82: astore 4
    //   84: iload_1
    //   85: ifeq +6 -> 91
    //   88: goto +225 -> 313
    //   91: goto -88 -> 3
    //   94: bipush 20
    //   96: istore_3
    //   97: goto +66 -> 163
    //   100: getstatic 23	o/Ic:ॱॱ	I
    //   103: bipush 43
    //   105: iadd
    //   106: istore_3
    //   107: iload_3
    //   108: sipush 128
    //   111: irem
    //   112: putstatic 21	o/Ic:ˏ	I
    //   115: iload_3
    //   116: iconst_2
    //   117: irem
    //   118: ifeq +6 -> 124
    //   121: goto +82 -> 203
    //   124: goto -63 -> 61
    //   127: aconst_null
    //   128: arraylength
    //   129: istore_3
    //   130: aload 4
    //   132: areturn
    //   133: iload_3
    //   134: lookupswitch	default:+26->160, 27:+206->340, 31:+-7->127
    //   160: goto -33 -> 127
    //   163: iload_3
    //   164: lookupswitch	default:+28->192, 20:+71->235, 21:+-145->19
    //   192: goto +43 -> 235
    //   195: goto -95 -> 100
    //   198: astore 4
    //   200: aload 4
    //   202: athrow
    //   203: goto -142 -> 61
    //   206: aload 4
    //   208: sipush 751
    //   211: sipush 13783
    //   214: bipush 29
    //   216: invokestatic 1653	o/Ic:ˎ	(ICI)Ljava/lang/String;
    //   219: invokevirtual 1657	java/lang/String:intern	()Ljava/lang/String;
    //   222: iconst_1
    //   223: invokevirtual 1879	o/j:ˏ	(Ljava/lang/String;Z)Lo/j;
    //   226: pop
    //   227: aload 4
    //   229: areturn
    //   230: astore 4
    //   232: aload 4
    //   234: athrow
    //   235: sipush 1824
    //   238: sipush 20678
    //   241: bipush 50
    //   243: invokestatic 1653	o/Ic:ˎ	(ICI)Ljava/lang/String;
    //   246: astore 5
    //   248: aload 5
    //   250: invokevirtual 1657	java/lang/String:intern	()Ljava/lang/String;
    //   253: astore 5
    //   255: aload 4
    //   257: aload 5
    //   259: iconst_0
    //   260: invokevirtual 1879	o/j:ˏ	(Ljava/lang/String;Z)Lo/j;
    //   263: astore 5
    //   265: aload 5
    //   267: iconst_1
    //   268: newarray int
    //   270: dup
    //   271: iconst_0
    //   272: ldc_w 1880
    //   275: iastore
    //   276: invokevirtual 1883	o/j:ˏ	([I)Lo/j;
    //   279: pop
    //   280: getstatic 23	o/Ic:ॱॱ	I
    //   283: bipush 85
    //   285: iadd
    //   286: istore_3
    //   287: iload_3
    //   288: sipush 128
    //   291: irem
    //   292: putstatic 21	o/Ic:ˏ	I
    //   295: iload_3
    //   296: iconst_2
    //   297: irem
    //   298: ifeq +6 -> 304
    //   301: goto -246 -> 55
    //   304: goto -291 -> 13
    //   307: bipush 21
    //   309: istore_3
    //   310: goto -147 -> 163
    //   313: getstatic 21	o/Ic:ˏ	I
    //   316: bipush 83
    //   318: iadd
    //   319: istore_3
    //   320: iload_3
    //   321: sipush 128
    //   324: irem
    //   325: putstatic 23	o/Ic:ॱॱ	I
    //   328: iload_3
    //   329: iconst_2
    //   330: irem
    //   331: ifne +6 -> 337
    //   334: goto -240 -> 94
    //   337: goto -30 -> 307
    //   340: aload 4
    //   342: areturn
    // Local variable table:
    //   start	length	slot	name	signature
    //   0	343	0	this	Ic
    //   0	343	1	paramBoolean1	boolean
    //   0	343	2	paramBoolean2	boolean
    //   15	316	3	i	int
    //   10	121	4	localJ	j
    //   198	30	4	localException1	Exception
    //   230	111	4	localException2	Exception
    //   246	20	5	localObject	Object
    // Exception table:
    //   from	to	target	type
    //   248	255	198	java/lang/Exception
    //   235	248	230	java/lang/Exception
    //   248	255	230	java/lang/Exception
    //   255	265	230	java/lang/Exception
    //   265	280	230	java/lang/Exception
  }
  
  /* Error */
  public j ˏॱ()
  {
    // Byte code:
    //   0: goto +6 -> 6
    //   3: astore_2
    //   4: aload_2
    //   5: athrow
    //   6: goto +35 -> 41
    //   9: getstatic 23	o/Ic:ॱॱ	I
    //   12: bipush 117
    //   14: iadd
    //   15: istore_1
    //   16: iload_1
    //   17: sipush 128
    //   20: irem
    //   21: putstatic 21	o/Ic:ˏ	I
    //   24: iload_1
    //   25: iconst_2
    //   26: irem
    //   27: ifeq +6 -> 33
    //   30: goto +6 -> 36
    //   33: goto +66 -> 99
    //   36: iconst_0
    //   37: istore_1
    //   38: goto +63 -> 101
    //   41: getstatic 21	o/Ic:ˏ	I
    //   44: bipush 55
    //   46: iadd
    //   47: istore_1
    //   48: iload_1
    //   49: sipush 128
    //   52: irem
    //   53: putstatic 23	o/Ic:ॱॱ	I
    //   56: iload_1
    //   57: iconst_2
    //   58: irem
    //   59: ifne +6 -> 65
    //   62: goto +6 -> 68
    //   65: goto +3 -> 68
    //   68: aload_0
    //   69: getfield 35	o/Ic:ˊ	Landroid/content/Context;
    //   72: astore_2
    //   73: sipush 811
    //   76: sipush 11702
    //   79: bipush 32
    //   81: invokestatic 1653	o/Ic:ˎ	(ICI)Ljava/lang/String;
    //   84: astore_3
    //   85: aload_3
    //   86: invokevirtual 1657	java/lang/String:intern	()Ljava/lang/String;
    //   89: astore_3
    //   90: aload_2
    //   91: aload_3
    //   92: invokestatic 1671	o/j:ˏ	(Landroid/content/Context;Ljava/lang/String;)Lo/j;
    //   95: astore_2
    //   96: goto -87 -> 9
    //   99: iconst_3
    //   100: istore_1
    //   101: iload_1
    //   102: lookupswitch	default:+26->128, 0:+31->133, 3:+39->141
    //   128: aload_2
    //   129: areturn
    //   130: astore_2
    //   131: aload_2
    //   132: athrow
    //   133: new 1694	java/lang/NullPointerException
    //   136: dup
    //   137: invokespecial 1695	java/lang/NullPointerException:<init>	()V
    //   140: athrow
    //   141: aload_2
    //   142: areturn
    // Local variable table:
    //   start	length	slot	name	signature
    //   0	143	0	this	Ic
    //   15	87	1	i	int
    //   3	2	2	localException1	Exception
    //   72	57	2	localObject	Object
    //   130	12	2	localException2	Exception
    //   84	8	3	str	String
    // Exception table:
    //   from	to	target	type
    //   73	85	3	java/lang/Exception
    //   68	73	130	java/lang/Exception
    //   73	85	130	java/lang/Exception
    //   85	90	130	java/lang/Exception
    //   90	96	130	java/lang/Exception
  }
  
  /* Error */
  public j ͺ()
  {
    // Byte code:
    //   0: goto +87 -> 87
    //   3: aload_0
    //   4: getfield 35	o/Ic:ˊ	Landroid/content/Context;
    //   7: sipush 678
    //   10: sipush 9128
    //   13: bipush 48
    //   15: invokestatic 1653	o/Ic:ˎ	(ICI)Ljava/lang/String;
    //   18: invokevirtual 1657	java/lang/String:intern	()Ljava/lang/String;
    //   21: invokestatic 1671	o/j:ˏ	(Landroid/content/Context;Ljava/lang/String;)Lo/j;
    //   24: astore_2
    //   25: goto +37 -> 62
    //   28: bipush 50
    //   30: istore_1
    //   31: goto +95 -> 126
    //   34: aload_0
    //   35: getfield 35	o/Ic:ˊ	Landroid/content/Context;
    //   38: astore_2
    //   39: sipush 1172
    //   42: sipush 9128
    //   45: bipush 34
    //   47: invokestatic 1653	o/Ic:ˎ	(ICI)Ljava/lang/String;
    //   50: astore_3
    //   51: aload_3
    //   52: invokevirtual 1657	java/lang/String:intern	()Ljava/lang/String;
    //   55: astore_3
    //   56: aload_2
    //   57: aload_3
    //   58: invokestatic 1671	o/j:ˏ	(Landroid/content/Context;Ljava/lang/String;)Lo/j;
    //   61: astore_2
    //   62: getstatic 21	o/Ic:ˏ	I
    //   65: bipush 103
    //   67: iadd
    //   68: istore_1
    //   69: iload_1
    //   70: sipush 128
    //   73: irem
    //   74: putstatic 23	o/Ic:ॱॱ	I
    //   77: iload_1
    //   78: iconst_2
    //   79: irem
    //   80: ifne +5 -> 85
    //   83: aload_2
    //   84: areturn
    //   85: aload_2
    //   86: areturn
    //   87: goto +12 -> 99
    //   90: astore_2
    //   91: aload_2
    //   92: athrow
    //   93: bipush 30
    //   95: istore_1
    //   96: goto +30 -> 126
    //   99: getstatic 23	o/Ic:ॱॱ	I
    //   102: bipush 67
    //   104: iadd
    //   105: istore_1
    //   106: iload_1
    //   107: sipush 128
    //   110: irem
    //   111: putstatic 21	o/Ic:ˏ	I
    //   114: iload_1
    //   115: iconst_2
    //   116: irem
    //   117: ifeq +6 -> 123
    //   120: goto -27 -> 93
    //   123: goto -95 -> 28
    //   126: iload_1
    //   127: lookupswitch	default:+25->152, 30:+-124->3, 50:+-93->34
    //   152: goto -118 -> 34
    //   155: astore_2
    //   156: aload_2
    //   157: athrow
    // Local variable table:
    //   start	length	slot	name	signature
    //   0	158	0	this	Ic
    //   30	97	1	i	int
    //   24	62	2	localObject	Object
    //   90	2	2	localException1	Exception
    //   155	2	2	localException2	Exception
    //   50	8	3	str	String
    // Exception table:
    //   from	to	target	type
    //   39	51	90	java/lang/Exception
    //   34	39	155	java/lang/Exception
    //   39	51	155	java/lang/Exception
    //   51	56	155	java/lang/Exception
    //   56	62	155	java/lang/Exception
  }
  
  public j ॱ()
  {
    break label36;
    int i = 62;
    break label81;
    label36:
    for (;;)
    {
      i = ॱॱ + 9;
      ˏ = i % 128;
      if (i % 2 != 0) {
        break;
      }
      break label75;
    }
    return j.ˏ(this.ˊ, ˎ(0, '\000', 57).intern());
    for (;;)
    {
      return j.ˏ(this.ˊ, ˎ(0, '\000', 58).intern());
      label75:
      i = 89;
      label81:
      switch (i)
      {
      }
    }
  }
  
  public j ॱ(Uri paramUri)
  {
    for (;;)
    {
      paramUri = new Intent(ˎ(523, '\000', 26).intern(), paramUri);
      paramUri = new j(this.ˊ, paramUri);
      int i = ˏ + 33;
      ॱॱ = i % 128;
      if (i % 2 == 0) {
        return paramUri;
      }
      return paramUri;
    }
  }
  
  /* Error */
  public j ॱ(String paramString)
  {
    // Byte code:
    //   0: goto +234 -> 234
    //   3: goto +234 -> 237
    //   6: bipush 13
    //   8: istore_2
    //   9: iload_2
    //   10: lookupswitch	default:+26->36, 13:+48->58, 49:+-7->3
    //   36: goto +22 -> 58
    //   39: aload_0
    //   40: aload_1
    //   41: iconst_4
    //   42: invokevirtual 1718	java/lang/String:substring	(I)Ljava/lang/String;
    //   45: invokespecial 1720	o/Ic:ॱॱ	(Ljava/lang/String;)Ljava/lang/String;
    //   48: invokevirtual 1657	java/lang/String:intern	()Ljava/lang/String;
    //   51: astore_1
    //   52: goto +12 -> 64
    //   55: astore_1
    //   56: aload_1
    //   57: athrow
    //   58: goto +179 -> 237
    //   61: astore_1
    //   62: aload_1
    //   63: athrow
    //   64: getstatic 23	o/Ic:ॱॱ	I
    //   67: bipush 23
    //   69: iadd
    //   70: istore_2
    //   71: iload_2
    //   72: sipush 128
    //   75: irem
    //   76: putstatic 21	o/Ic:ˏ	I
    //   79: iload_2
    //   80: iconst_2
    //   81: irem
    //   82: ifeq +6 -> 88
    //   85: goto -79 -> 6
    //   88: goto +165 -> 253
    //   91: sipush 408
    //   94: iconst_0
    //   95: bipush 28
    //   97: invokestatic 1653	o/Ic:ˎ	(ICI)Ljava/lang/String;
    //   100: astore 4
    //   102: new 1679	android/content/Intent
    //   105: dup
    //   106: aload 4
    //   108: invokevirtual 1657	java/lang/String:intern	()Ljava/lang/String;
    //   111: invokespecial 1682	android/content/Intent:<init>	(Ljava/lang/String;)V
    //   114: astore 4
    //   116: sipush 436
    //   119: iconst_0
    //   120: bipush 10
    //   122: invokestatic 1653	o/Ic:ˎ	(ICI)Ljava/lang/String;
    //   125: astore 5
    //   127: aload 4
    //   129: aload 5
    //   131: invokevirtual 1657	java/lang/String:intern	()Ljava/lang/String;
    //   134: invokevirtual 1889	android/content/Intent:setType	(Ljava/lang/String;)Landroid/content/Intent;
    //   137: pop
    //   138: aload 4
    //   140: sipush 446
    //   143: ldc_w 1890
    //   146: bipush 7
    //   148: invokestatic 1653	o/Ic:ˎ	(ICI)Ljava/lang/String;
    //   151: invokevirtual 1657	java/lang/String:intern	()Ljava/lang/String;
    //   154: invokestatic 1791	android/net/Uri:parse	(Ljava/lang/String;)Landroid/net/Uri;
    //   157: invokevirtual 1828	android/content/Intent:setData	(Landroid/net/Uri;)Landroid/content/Intent;
    //   160: pop
    //   161: aload 4
    //   163: sipush 453
    //   166: sipush 28637
    //   169: bipush 26
    //   171: invokestatic 1653	o/Ic:ˎ	(ICI)Ljava/lang/String;
    //   174: invokevirtual 1657	java/lang/String:intern	()Ljava/lang/String;
    //   177: iconst_1
    //   178: anewarray 1637	java/lang/String
    //   181: dup
    //   182: iconst_0
    //   183: aload_1
    //   184: aastore
    //   185: invokevirtual 1893	android/content/Intent:putExtra	(Ljava/lang/String;[Ljava/lang/String;)Landroid/content/Intent;
    //   188: pop
    //   189: aload_0
    //   190: getfield 35	o/Ic:ˊ	Landroid/content/Context;
    //   193: astore 5
    //   195: aload_0
    //   196: getfield 35	o/Ic:ˊ	Landroid/content/Context;
    //   199: getstatic 1896	o/Gu$ˏ:support_email_address	I
    //   202: invokevirtual 1755	android/content/Context:getString	(I)Ljava/lang/String;
    //   205: astore_1
    //   206: aload_1
    //   207: sipush 316
    //   210: sipush 14281
    //   213: iconst_4
    //   214: invokestatic 1653	o/Ic:ˎ	(ICI)Ljava/lang/String;
    //   217: invokevirtual 1657	java/lang/String:intern	()Ljava/lang/String;
    //   220: invokevirtual 1759	java/lang/String:startsWith	(Ljava/lang/String;)Z
    //   223: istore_3
    //   224: iload_3
    //   225: ifeq +6 -> 231
    //   228: goto -189 -> 39
    //   231: goto +6 -> 237
    //   234: goto -143 -> 91
    //   237: new 1668	o/j
    //   240: dup
    //   241: aload 5
    //   243: aload 4
    //   245: aload_1
    //   246: invokestatic 1900	android/content/Intent:createChooser	(Landroid/content/Intent;Ljava/lang/CharSequence;)Landroid/content/Intent;
    //   249: invokespecial 1685	o/j:<init>	(Landroid/content/Context;Landroid/content/Intent;)V
    //   252: areturn
    //   253: bipush 49
    //   255: istore_2
    //   256: goto -247 -> 9
    // Local variable table:
    //   start	length	slot	name	signature
    //   0	259	0	this	Ic
    //   0	259	1	paramString	String
    //   8	248	2	i	int
    //   223	2	3	bool	boolean
    //   100	144	4	localObject1	Object
    //   125	117	5	localObject2	Object
    // Exception table:
    //   from	to	target	type
    //   102	116	55	java/lang/Exception
    //   91	102	61	java/lang/Exception
    //   102	116	61	java/lang/Exception
    //   116	127	61	java/lang/Exception
    //   127	224	61	java/lang/Exception
  }
  
  public j ॱ(String paramString, boolean paramBoolean)
  {
    for (;;)
    {
      Intent localIntent = new Intent(ˎ(1279, 62139, 30).intern());
      localIntent.putExtra(ˎ(1309, 'ㅈ', 29).intern(), paramString);
      localIntent.putExtra(ˎ(1338, 48045, 28).intern(), paramBoolean);
      paramString = new j(this.ˊ, localIntent);
      break label137;
      int i;
      for (;;)
      {
        switch (i)
        {
        default: 
          break;
        case 54: 
          return paramString;
          label117:
          i = 78;
        }
      }
      for (;;)
      {
        i = 54;
        break;
        throw new NullPointerException();
        label137:
        i = ॱॱ + 99;
        ˏ = i % 128;
        if (i % 2 != 0) {
          break label117;
        }
      }
    }
  }
  
  public j ॱ(Eu paramEu, String paramString)
  {
    for (;;)
    {
      switch (i)
      {
      default: 
        return paramEu;
        break;
      case 89: 
        return paramEu;
      case 92: 
        i = null.length;
        return paramEu;
      }
      int i = ॱॱ + 63;
      ˏ = i % 128;
      if (i % 2 == 0)
      {
        break label97;
        i = ˏ + 5;
        ॱॱ = i % 128;
        if (i % 2 == 0) {
          break label163;
        }
        break label157;
      }
      for (;;)
      {
        label97:
        paramEu = j.ˏ(this.ˊ, ˎ(135, '☪', 27).intern()).ˎ(ˎ(162, '\000', 18).intern(), paramEu).ˋ(ˎ(180, '\000', 14).intern(), paramString);
        break;
      }
      label157:
      i = 89;
      continue;
      label163:
      i = 92;
    }
  }
  
  /* Error */
  public j ॱ(Gm paramGm, String paramString)
  {
    // Byte code:
    //   0: goto +129 -> 129
    //   3: getstatic 21	o/Ic:ˏ	I
    //   6: bipush 73
    //   8: iadd
    //   9: istore_3
    //   10: iload_3
    //   11: sipush 128
    //   14: irem
    //   15: putstatic 23	o/Ic:ॱॱ	I
    //   18: iload_3
    //   19: iconst_2
    //   20: irem
    //   21: ifne +6 -> 27
    //   24: goto +9 -> 33
    //   27: goto +40 -> 67
    //   30: astore_1
    //   31: aload_1
    //   32: athrow
    //   33: goto +34 -> 67
    //   36: getstatic 23	o/Ic:ॱॱ	I
    //   39: istore_3
    //   40: iload_3
    //   41: bipush 81
    //   43: iadd
    //   44: istore_3
    //   45: iload_3
    //   46: sipush 128
    //   49: irem
    //   50: putstatic 21	o/Ic:ˏ	I
    //   53: iload_3
    //   54: iconst_2
    //   55: irem
    //   56: ifeq +6 -> 62
    //   59: goto +73 -> 132
    //   62: aload_1
    //   63: areturn
    //   64: astore_1
    //   65: aload_1
    //   66: athrow
    //   67: aload_0
    //   68: getfield 35	o/Ic:ˊ	Landroid/content/Context;
    //   71: sipush 1539
    //   74: sipush 23875
    //   77: bipush 26
    //   79: invokestatic 1653	o/Ic:ˎ	(ICI)Ljava/lang/String;
    //   82: invokevirtual 1657	java/lang/String:intern	()Ljava/lang/String;
    //   85: invokestatic 1671	o/j:ˏ	(Landroid/content/Context;Ljava/lang/String;)Lo/j;
    //   88: sipush 1565
    //   91: iconst_0
    //   92: bipush 23
    //   94: invokestatic 1653	o/Ic:ˎ	(ICI)Ljava/lang/String;
    //   97: invokevirtual 1657	java/lang/String:intern	()Ljava/lang/String;
    //   100: aload_1
    //   101: invokevirtual 1808	o/Gm:name	()Ljava/lang/String;
    //   104: invokevirtual 1676	o/j:ˋ	(Ljava/lang/String;Ljava/lang/String;)Lo/j;
    //   107: sipush 1626
    //   110: ldc_w 1903
    //   113: bipush 22
    //   115: invokestatic 1653	o/Ic:ˎ	(ICI)Ljava/lang/String;
    //   118: invokevirtual 1657	java/lang/String:intern	()Ljava/lang/String;
    //   121: aload_2
    //   122: invokevirtual 1676	o/j:ˋ	(Ljava/lang/String;Ljava/lang/String;)Lo/j;
    //   125: astore_1
    //   126: goto -90 -> 36
    //   129: goto -126 -> 3
    //   132: aload_1
    //   133: areturn
    // Local variable table:
    //   start	length	slot	name	signature
    //   0	134	0	this	Ic
    //   0	134	1	paramGm	Gm
    //   0	134	2	paramString	String
    //   9	47	3	i	int
    // Exception table:
    //   from	to	target	type
    //   36	40	30	java/lang/Exception
    //   45	53	64	java/lang/Exception
  }
  
  /* Error */
  public j ॱˊ()
  {
    // Byte code:
    //   0: goto +6 -> 6
    //   3: astore_2
    //   4: aload_2
    //   5: athrow
    //   6: sipush 1012
    //   9: ldc_w 1776
    //   12: bipush 39
    //   14: invokestatic 1653	o/Ic:ˎ	(ICI)Ljava/lang/String;
    //   17: astore_2
    //   18: aload_2
    //   19: invokevirtual 1657	java/lang/String:intern	()Ljava/lang/String;
    //   22: astore_2
    //   23: new 1679	android/content/Intent
    //   26: dup
    //   27: aload_2
    //   28: invokespecial 1682	android/content/Intent:<init>	(Ljava/lang/String;)V
    //   31: astore_2
    //   32: new 1668	o/j
    //   35: dup
    //   36: aload_0
    //   37: getfield 35	o/Ic:ˊ	Landroid/content/Context;
    //   40: aload_2
    //   41: invokespecial 1685	o/j:<init>	(Landroid/content/Context;Landroid/content/Intent;)V
    //   44: astore_2
    //   45: goto +3 -> 48
    //   48: getstatic 23	o/Ic:ॱॱ	I
    //   51: bipush 91
    //   53: iadd
    //   54: istore_1
    //   55: iload_1
    //   56: sipush 128
    //   59: irem
    //   60: putstatic 21	o/Ic:ˏ	I
    //   63: iload_1
    //   64: iconst_2
    //   65: irem
    //   66: ifeq +5 -> 71
    //   69: aload_2
    //   70: areturn
    //   71: aload_2
    //   72: areturn
    //   73: astore_2
    //   74: aload_2
    //   75: athrow
    // Local variable table:
    //   start	length	slot	name	signature
    //   0	76	0	this	Ic
    //   54	12	1	i	int
    //   3	2	2	localException1	Exception
    //   17	55	2	localObject	Object
    //   73	2	2	localException2	Exception
    // Exception table:
    //   from	to	target	type
    //   6	18	3	java/lang/Exception
    //   18	23	3	java/lang/Exception
    //   23	32	3	java/lang/Exception
    //   32	45	3	java/lang/Exception
    //   18	23	73	java/lang/Exception
  }
  
  public j ॱˋ()
  {
    break label199;
    int i = 61 / 0;
    j localJ;
    return localJ;
    label70:
    label97:
    label134:
    label163:
    label169:
    label199:
    for (;;)
    {
      i = ॱॱ + 17;
      ˏ = i % 128;
      if (i % 2 == 0)
      {
        break label97;
        localJ = j.ˏ(this.ˊ, ˎ(22091, 44720, 122).intern());
        do
        {
          i = 89;
          break;
          return localJ;
          i = ˏ + 95;
          ॱॱ = i % 128;
        } while (i % 2 == 0);
        break label163;
        i = 52;
        break label134;
        switch (i)
        {
        }
        return localJ;
      }
      for (;;)
      {
        switch (i)
        {
        case 5: 
        default: 
          break label169;
          i = 88;
          break;
        case 52: 
          localJ = j.ˏ(this.ˊ, ˎ(1442, 44720, 27).intern());
          break label70;
          i = 5;
        }
      }
    }
  }
  
  public j ॱˎ()
  {
    for (;;)
    {
      int i = 0;
      break label36;
      i = 1;
      break label36;
      break label80;
      return j.ˏ(this.ˊ, ˎ(1242, '\000', 37).intern());
      label36:
      switch (i)
      {
      }
      return j.ˏ(this.ˊ, ˎ(32356, '\000', 37).intern());
      try
      {
        label80:
        i = ˏ + 101;
        ॱॱ = i % 128;
        if (i % 2 == 0) {}
      }
      catch (Exception localException)
      {
        throw localException;
      }
    }
  }
  
  public j ॱॱ()
  {
    break label204;
    int i = 27 / 0;
    Object localObject;
    return localObject;
    i = 52;
    break label135;
    label16:
    i = ˏ + 119;
    ॱॱ = i % 128;
    if (i % 2 != 0) {
      break label98;
    }
    for (;;)
    {
      try
      {
        localObject = this.ˊ;
        str = ˎ(780, '\000', 31);
      }
      catch (Exception localException1)
      {
        String str;
        label98:
        label126:
        throw localException1;
      }
      try
      {
        str = str.intern();
        localObject = j.ˏ((Context)localObject, str);
      }
      catch (Exception localException2)
      {
        label135:
        throw localException2;
      }
      switch (i)
      {
      case 0: 
      default: 
        return localObject;
        i = 1;
        continue;
        localObject = j.ˏ(this.ˊ, ˎ(9646, '\000', 111).intern());
        break label16;
        i = 37;
        switch (i)
        {
        }
        continue;
        i = 0;
      }
    }
    label204:
    for (;;)
    {
      i = ˏ + 103;
      ॱॱ = i % 128;
      if (i % 2 == 0) {
        break;
      }
      break label126;
      return localException2;
    }
  }
  
  public j ॱᐝ()
  {
    break label136;
    j localJ = j.ˏ(this.ˊ, ˎ(9153, '㭋', 85).intern());
    break label171;
    return localJ;
    for (;;)
    {
      int i = 85;
      break label66;
      i = ˏ + 43;
      ॱॱ = i % 128;
      if (i % 2 != 0) {
        break label130;
      }
      label66:
      label130:
      label136:
      label139:
      label171:
      do
      {
        i = 55;
        switch (i)
        {
        case 85: 
        default: 
          return localJ;
          i = 65;
          break;
        }
        for (;;)
        {
          localJ = j.ˏ(this.ˊ, ˎ(1206, '㭋', 36).intern());
          break label171;
          i = null.length;
          return localJ;
          i = 57;
          break label139;
          break;
          switch (i)
          {
          }
        }
        i = ˏ + 37;
        ॱॱ = i % 128;
      } while (i % 2 == 0);
    }
  }
  
  /* Error */
  public j ᐝ()
  {
    // Byte code:
    //   0: goto +43 -> 43
    //   3: astore_2
    //   4: aload_2
    //   5: athrow
    //   6: iconst_0
    //   7: istore_1
    //   8: goto +92 -> 100
    //   11: getstatic 23	o/Ic:ॱॱ	I
    //   14: bipush 65
    //   16: iadd
    //   17: istore_1
    //   18: iload_1
    //   19: sipush 128
    //   22: irem
    //   23: putstatic 21	o/Ic:ˏ	I
    //   26: iload_1
    //   27: iconst_2
    //   28: irem
    //   29: ifeq +6 -> 35
    //   32: goto +65 -> 97
    //   35: goto +11 -> 46
    //   38: aconst_null
    //   39: arraylength
    //   40: istore_1
    //   41: aload_2
    //   42: areturn
    //   43: goto -32 -> 11
    //   46: aload_0
    //   47: getfield 35	o/Ic:ˊ	Landroid/content/Context;
    //   50: sipush 622
    //   53: iconst_0
    //   54: bipush 34
    //   56: invokestatic 1653	o/Ic:ˎ	(ICI)Ljava/lang/String;
    //   59: invokevirtual 1657	java/lang/String:intern	()Ljava/lang/String;
    //   62: invokestatic 1671	o/j:ˏ	(Landroid/content/Context;Ljava/lang/String;)Lo/j;
    //   65: astore_2
    //   66: getstatic 21	o/Ic:ˏ	I
    //   69: istore_1
    //   70: iload_1
    //   71: bipush 105
    //   73: iadd
    //   74: istore_1
    //   75: iload_1
    //   76: sipush 128
    //   79: irem
    //   80: putstatic 23	o/Ic:ॱॱ	I
    //   83: iload_1
    //   84: iconst_2
    //   85: irem
    //   86: ifne +6 -> 92
    //   89: goto -83 -> 6
    //   92: goto +38 -> 130
    //   95: aload_2
    //   96: areturn
    //   97: goto -51 -> 46
    //   100: iload_1
    //   101: tableswitch	default:+23->124, 0:+-63->38, 1:+-6->95
    //   124: goto -86 -> 38
    //   127: astore_2
    //   128: aload_2
    //   129: athrow
    //   130: iconst_1
    //   131: istore_1
    //   132: goto -32 -> 100
    // Local variable table:
    //   start	length	slot	name	signature
    //   0	135	0	this	Ic
    //   7	125	1	i	int
    //   3	39	2	localException1	Exception
    //   65	31	2	localJ	j
    //   127	2	2	localException2	Exception
    // Exception table:
    //   from	to	target	type
    //   66	70	3	java/lang/Exception
    //   75	83	127	java/lang/Exception
  }
  
  public j ᐝ(String paramString)
  {
    break label50;
    paramString = aq.ʻ(paramString);
    paramString = new Intent(ˎ(523, '\000', 26).intern(), Uri.parse(paramString));
    paramString = new j(this.ˊ, paramString);
    label50:
    int i;
    do
    {
      return paramString;
      break;
      i = ˏ + 85;
      ॱॱ = i % 128;
    } while (i % 2 == 0);
    return paramString;
  }
  
  /* Error */
  public j ᐝॱ()
  {
    // Byte code:
    //   0: goto +8 -> 8
    //   3: astore_2
    //   4: aload_2
    //   5: athrow
    //   6: aload_2
    //   7: areturn
    //   8: goto +103 -> 111
    //   11: goto +42 -> 53
    //   14: iconst_1
    //   15: istore_1
    //   16: goto +70 -> 86
    //   19: getstatic 23	o/Ic:ॱॱ	I
    //   22: istore_1
    //   23: iload_1
    //   24: bipush 87
    //   26: iadd
    //   27: istore_1
    //   28: iload_1
    //   29: sipush 128
    //   32: irem
    //   33: putstatic 21	o/Ic:ˏ	I
    //   36: iload_1
    //   37: iconst_2
    //   38: irem
    //   39: ifeq +6 -> 45
    //   42: goto +6 -> 48
    //   45: goto -31 -> 14
    //   48: iconst_0
    //   49: istore_1
    //   50: goto +36 -> 86
    //   53: aload_0
    //   54: getfield 35	o/Ic:ˊ	Landroid/content/Context;
    //   57: sipush 1504
    //   60: iconst_0
    //   61: bipush 35
    //   63: invokestatic 1653	o/Ic:ˎ	(ICI)Ljava/lang/String;
    //   66: invokevirtual 1657	java/lang/String:intern	()Ljava/lang/String;
    //   69: invokestatic 1671	o/j:ˏ	(Landroid/content/Context;Ljava/lang/String;)Lo/j;
    //   72: astore_2
    //   73: goto -54 -> 19
    //   76: bipush 99
    //   78: iconst_0
    //   79: idiv
    //   80: istore_1
    //   81: aload_2
    //   82: areturn
    //   83: astore_2
    //   84: aload_2
    //   85: athrow
    //   86: iload_1
    //   87: tableswitch	default:+21->108, 0:+-11->76, 1:+-81->6
    //   108: goto -32 -> 76
    //   111: getstatic 23	o/Ic:ॱॱ	I
    //   114: bipush 89
    //   116: iadd
    //   117: istore_1
    //   118: iload_1
    //   119: sipush 128
    //   122: irem
    //   123: putstatic 21	o/Ic:ˏ	I
    //   126: iload_1
    //   127: iconst_2
    //   128: irem
    //   129: ifeq +6 -> 135
    //   132: goto -121 -> 11
    //   135: goto -82 -> 53
    // Local variable table:
    //   start	length	slot	name	signature
    //   0	138	0	this	Ic
    //   15	114	1	i	int
    //   3	4	2	localException1	Exception
    //   72	10	2	localJ	j
    //   83	2	2	localException2	Exception
    // Exception table:
    //   from	to	target	type
    //   19	23	3	java/lang/Exception
    //   28	36	83	java/lang/Exception
  }
}
