package o;

import android.os.Parcelable;

public final class IE
  extends x
{
  private static byte ߺ = -102;
  private static int ॱˈ;
  private static int ॱˉ;
  private static byte[] ॱˌ;
  private static short[] ॱˍ;
  private static int ॱˑ;
  private static int ॱـ;
  private static int ॱꓸ;
  
  /* Error */
  static
  {
    // Byte code:
    //   0: goto +35 -> 35
    //   3: astore_1
    //   4: aload_1
    //   5: athrow
    //   6: astore_1
    //   7: aload_1
    //   8: athrow
    //   9: getstatic 26	o/IE:ॱـ	I
    //   12: bipush 113
    //   14: iadd
    //   15: istore_0
    //   16: iload_0
    //   17: sipush 128
    //   20: irem
    //   21: putstatic 28	o/IE:ॱꓸ	I
    //   24: iload_0
    //   25: iconst_2
    //   26: irem
    //   27: ifne +6 -> 33
    //   30: goto +4 -> 34
    //   33: return
    //   34: return
    //   35: iconst_0
    //   36: putstatic 26	o/IE:ॱـ	I
    //   39: iconst_1
    //   40: putstatic 28	o/IE:ॱꓸ	I
    //   43: invokestatic 31	o/IE:ˎ	()V
    //   46: bipush -102
    //   48: putstatic 33	o/IE:ߺ	B
    //   51: goto -42 -> 9
    // Local variable table:
    //   start	length	slot	name	signature
    //   15	12	0	i	int
    //   3	2	1	localException1	Exception
    //   6	2	1	localException2	Exception
    // Exception table:
    //   from	to	target	type
    //   35	39	3	java/lang/Exception
    //   39	43	3	java/lang/Exception
    //   43	46	3	java/lang/Exception
    //   46	51	3	java/lang/Exception
    //   9	24	6	java/lang/Exception
  }
  
  /* Error */
  public IE(android.content.Context paramContext, final String paramString)
  {
    // Byte code:
    //   0: goto +347 -> 347
    //   3: getstatic 28	o/IE:ॱꓸ	I
    //   6: bipush 31
    //   8: iadd
    //   9: istore_3
    //   10: iload_3
    //   11: sipush 128
    //   14: irem
    //   15: putstatic 26	o/IE:ॱـ	I
    //   18: iload_3
    //   19: iconst_2
    //   20: irem
    //   21: ifeq +6 -> 27
    //   24: goto +98 -> 122
    //   27: goto +273 -> 300
    //   30: aload_0
    //   31: aload 5
    //   33: checkcast 38	java/lang/CharSequence
    //   36: invokevirtual 42	o/IE:ˊ	(Ljava/lang/CharSequence;)Lo/ᐸ$If;
    //   39: pop
    //   40: getstatic 47	o/vw:ˊ	Lo/vw;
    //   43: astore 5
    //   45: aload_0
    //   46: getfield 51	o/IE:ˏ	Landroid/content/Context;
    //   49: getstatic 56	o/Gu$ˏ:wallet_inactive_dialog_content	I
    //   52: invokevirtual 62	android/content/Context:getString	(I)Ljava/lang/String;
    //   55: astore 6
    //   57: aload 6
    //   59: bipush 44
    //   61: ldc 63
    //   63: iconst_0
    //   64: ldc 64
    //   66: sipush 63042
    //   69: invokestatic 67	o/IE:ˎ	(SIBII)Ljava/lang/String;
    //   72: invokevirtual 73	java/lang/String:intern	()Ljava/lang/String;
    //   75: invokevirtual 77	java/lang/String:startsWith	(Ljava/lang/String;)Z
    //   78: ifeq +6 -> 84
    //   81: goto +209 -> 290
    //   84: goto +211 -> 295
    //   87: goto +385 -> 472
    //   90: iload_3
    //   91: lookupswitch	default:+25->116, 51:+28->119, 85:+569->660
    //   116: goto +544 -> 660
    //   119: goto +119 -> 238
    //   122: bipush 85
    //   124: istore_3
    //   125: goto -35 -> 90
    //   128: bipush 72
    //   130: istore_3
    //   131: goto +178 -> 309
    //   134: astore_1
    //   135: aload_1
    //   136: athrow
    //   137: aload_0
    //   138: aload 5
    //   140: iconst_4
    //   141: invokevirtual 80	java/lang/String:substring	(I)Ljava/lang/String;
    //   144: invokespecial 84	o/IE:ॱ	(Ljava/lang/String;)Ljava/lang/String;
    //   147: invokevirtual 73	java/lang/String:intern	()Ljava/lang/String;
    //   150: astore 5
    //   152: goto +59 -> 211
    //   155: aload_0
    //   156: aload 5
    //   158: checkcast 38	java/lang/CharSequence
    //   161: invokevirtual 86	o/IE:ॱ	(Ljava/lang/CharSequence;)Lo/ᐸ$If;
    //   164: pop
    //   165: aload_0
    //   166: iconst_0
    //   167: invokevirtual 89	o/IE:ˎ	(Z)Lo/ᐸ$If;
    //   170: pop
    //   171: aload_0
    //   172: new 8	o/IE$3
    //   175: dup
    //   176: aload_0
    //   177: aload_2
    //   178: invokespecial 92	o/IE$3:<init>	(Lo/IE;Ljava/lang/String;)V
    //   181: checkcast 94	o/ᐸ$ˏ
    //   184: invokevirtual 97	o/IE:ॱ	(Lo/ᐸ$ˏ;)Lo/ᐸ$If;
    //   187: pop
    //   188: aload_0
    //   189: new 6	o/IE$2
    //   192: dup
    //   193: aload_1
    //   194: invokespecial 100	o/IE$2:<init>	(Landroid/content/Context;)V
    //   197: checkcast 94	o/ᐸ$ˏ
    //   200: invokevirtual 102	o/IE:ˊ	(Lo/ᐸ$ˏ;)Lo/ᐸ$If;
    //   203: pop
    //   204: return
    //   205: goto -50 -> 155
    //   208: goto -53 -> 155
    //   211: getstatic 26	o/IE:ॱـ	I
    //   214: bipush 77
    //   216: iadd
    //   217: istore_3
    //   218: iload_3
    //   219: sipush 128
    //   222: irem
    //   223: putstatic 28	o/IE:ॱꓸ	I
    //   226: iload_3
    //   227: iconst_2
    //   228: irem
    //   229: ifne +6 -> 235
    //   232: goto -27 -> 205
    //   235: goto -27 -> 208
    //   238: aload_0
    //   239: aload 5
    //   241: checkcast 38	java/lang/CharSequence
    //   244: invokevirtual 104	o/IE:ˎ	(Ljava/lang/CharSequence;)Lo/ᐸ$If;
    //   247: pop
    //   248: aload_0
    //   249: getfield 51	o/IE:ˏ	Landroid/content/Context;
    //   252: getstatic 107	o/Gu$ˏ:cancel	I
    //   255: invokevirtual 62	android/content/Context:getString	(I)Ljava/lang/String;
    //   258: astore 5
    //   260: aload 5
    //   262: bipush 44
    //   264: ldc 63
    //   266: iconst_0
    //   267: ldc 64
    //   269: sipush 63042
    //   272: invokestatic 67	o/IE:ˎ	(SIBII)Ljava/lang/String;
    //   275: invokevirtual 73	java/lang/String:intern	()Ljava/lang/String;
    //   278: invokevirtual 77	java/lang/String:startsWith	(Ljava/lang/String;)Z
    //   281: ifeq +6 -> 287
    //   284: goto -147 -> 137
    //   287: goto -132 -> 155
    //   290: iconst_1
    //   291: istore_3
    //   292: goto +150 -> 442
    //   295: iconst_0
    //   296: istore_3
    //   297: goto +145 -> 442
    //   300: bipush 51
    //   302: istore_3
    //   303: goto -213 -> 90
    //   306: bipush 7
    //   308: istore_3
    //   309: aload 6
    //   311: astore 5
    //   313: iload_3
    //   314: lookupswitch	default:+26->340, 7:+-76->238, 72:+310->624
    //   340: aload 6
    //   342: astore 5
    //   344: goto -106 -> 238
    //   347: aload_1
    //   348: bipush -119
    //   350: ldc 108
    //   352: iconst_0
    //   353: ldc 109
    //   355: sipush 63041
    //   358: invokestatic 67	o/IE:ˎ	(SIBII)Ljava/lang/String;
    //   361: invokevirtual 73	java/lang/String:intern	()Ljava/lang/String;
    //   364: invokestatic 114	o/vq:ˎ	(Ljava/lang/Object;Ljava/lang/String;)V
    //   367: aload_2
    //   368: bipush -112
    //   370: ldc 115
    //   372: iconst_0
    //   373: ldc 116
    //   375: sipush 63049
    //   378: invokestatic 67	o/IE:ˎ	(SIBII)Ljava/lang/String;
    //   381: invokevirtual 73	java/lang/String:intern	()Ljava/lang/String;
    //   384: invokestatic 114	o/vq:ˎ	(Ljava/lang/Object;Ljava/lang/String;)V
    //   387: aload_0
    //   388: aload_1
    //   389: invokespecial 117	o/x:<init>	(Landroid/content/Context;)V
    //   392: aload_0
    //   393: getstatic 122	o/Gu$If:ic_error	I
    //   396: invokevirtual 125	o/IE:ˎ	(I)Lo/ᐸ$If;
    //   399: pop
    //   400: aload_0
    //   401: getfield 51	o/IE:ˏ	Landroid/content/Context;
    //   404: getstatic 128	o/Gu$ˏ:wallet_inactive_dialog_title	I
    //   407: invokevirtual 62	android/content/Context:getString	(I)Ljava/lang/String;
    //   410: astore 5
    //   412: aload 5
    //   414: bipush 44
    //   416: ldc 63
    //   418: iconst_0
    //   419: ldc 64
    //   421: sipush 63042
    //   424: invokestatic 67	o/IE:ˎ	(SIBII)Ljava/lang/String;
    //   427: invokevirtual 73	java/lang/String:intern	()Ljava/lang/String;
    //   430: invokevirtual 77	java/lang/String:startsWith	(Ljava/lang/String;)Z
    //   433: ifeq +6 -> 439
    //   436: goto +206 -> 642
    //   439: goto -409 -> 30
    //   442: aload 6
    //   444: astore 5
    //   446: iload_3
    //   447: tableswitch	default:+21->468, 0:+25->472, 1:+159->606
    //   468: aload 6
    //   470: astore 5
    //   472: bipush -103
    //   474: ldc -127
    //   476: iconst_0
    //   477: ldc 109
    //   479: sipush 63088
    //   482: invokestatic 67	o/IE:ˎ	(SIBII)Ljava/lang/String;
    //   485: astore 6
    //   487: aload 6
    //   489: invokevirtual 73	java/lang/String:intern	()Ljava/lang/String;
    //   492: astore 6
    //   494: aload 5
    //   496: aload 6
    //   498: invokestatic 132	o/vq:ˋ	(Ljava/lang/Object;Ljava/lang/String;)V
    //   501: iconst_1
    //   502: anewarray 134	java/lang/Object
    //   505: astore 6
    //   507: aload 6
    //   509: iconst_0
    //   510: aload_2
    //   511: aastore
    //   512: aload 6
    //   514: arraylength
    //   515: istore_3
    //   516: aload 5
    //   518: aload 6
    //   520: iconst_1
    //   521: invokestatic 140	java/util/Arrays:copyOf	([Ljava/lang/Object;I)[Ljava/lang/Object;
    //   524: invokestatic 144	java/lang/String:format	(Ljava/lang/String;[Ljava/lang/Object;)Ljava/lang/String;
    //   527: astore 5
    //   529: aload 5
    //   531: bipush 23
    //   533: ldc -111
    //   535: iconst_0
    //   536: ldc -110
    //   538: sipush 63076
    //   541: invokestatic 67	o/IE:ˎ	(SIBII)Ljava/lang/String;
    //   544: invokevirtual 73	java/lang/String:intern	()Ljava/lang/String;
    //   547: invokestatic 132	o/vq:ˋ	(Ljava/lang/Object;Ljava/lang/String;)V
    //   550: aload_0
    //   551: aload 5
    //   553: invokestatic 152	o/aq:ʼ	(Ljava/lang/String;)Ljava/lang/CharSequence;
    //   556: invokevirtual 154	o/IE:ˋ	(Ljava/lang/CharSequence;)Lo/ᐸ$If;
    //   559: pop
    //   560: aload_0
    //   561: getfield 51	o/IE:ˏ	Landroid/content/Context;
    //   564: getstatic 157	o/Gu$ˏ:continue_label	I
    //   567: invokevirtual 62	android/content/Context:getString	(I)Ljava/lang/String;
    //   570: astore 6
    //   572: aload 6
    //   574: bipush 44
    //   576: ldc 63
    //   578: iconst_0
    //   579: ldc 64
    //   581: sipush 63042
    //   584: invokestatic 67	o/IE:ˎ	(SIBII)Ljava/lang/String;
    //   587: invokevirtual 73	java/lang/String:intern	()Ljava/lang/String;
    //   590: invokevirtual 77	java/lang/String:startsWith	(Ljava/lang/String;)Z
    //   593: istore 4
    //   595: iload 4
    //   597: ifeq +6 -> 603
    //   600: goto -472 -> 128
    //   603: goto -297 -> 306
    //   606: aload_0
    //   607: aload 6
    //   609: iconst_4
    //   610: invokevirtual 80	java/lang/String:substring	(I)Ljava/lang/String;
    //   613: invokespecial 84	o/IE:ॱ	(Ljava/lang/String;)Ljava/lang/String;
    //   616: invokevirtual 73	java/lang/String:intern	()Ljava/lang/String;
    //   619: astore 5
    //   621: goto -534 -> 87
    //   624: aload_0
    //   625: aload 6
    //   627: iconst_4
    //   628: invokevirtual 80	java/lang/String:substring	(I)Ljava/lang/String;
    //   631: invokespecial 84	o/IE:ॱ	(Ljava/lang/String;)Ljava/lang/String;
    //   634: invokevirtual 73	java/lang/String:intern	()Ljava/lang/String;
    //   637: astore 5
    //   639: goto -636 -> 3
    //   642: aload_0
    //   643: aload 5
    //   645: iconst_4
    //   646: invokevirtual 80	java/lang/String:substring	(I)Ljava/lang/String;
    //   649: invokespecial 84	o/IE:ॱ	(Ljava/lang/String;)Ljava/lang/String;
    //   652: invokevirtual 73	java/lang/String:intern	()Ljava/lang/String;
    //   655: astore 5
    //   657: goto -627 -> 30
    //   660: goto -422 -> 238
    // Local variable table:
    //   start	length	slot	name	signature
    //   0	663	0	this	IE
    //   0	663	1	paramContext	android.content.Context
    //   0	663	2	paramString	String
    //   9	507	3	i	int
    //   593	3	4	bool	boolean
    //   31	625	5	localObject1	Object
    //   55	571	6	localObject2	Object
    // Exception table:
    //   from	to	target	type
    //   472	487	134	java/lang/Exception
    //   487	494	134	java/lang/Exception
    //   494	501	134	java/lang/Exception
    //   501	507	134	java/lang/Exception
    //   512	595	134	java/lang/Exception
  }
  
  /* Error */
  private static String ˎ(short paramShort, int paramInt1, byte paramByte, int paramInt2, int paramInt3)
  {
    // Byte code:
    //   0: goto +365 -> 365
    //   3: iload 6
    //   5: tableswitch	default:+23->28, 0:+233->238, 1:+500->505
    //   28: goto +477 -> 505
    //   31: bipush 86
    //   33: istore_0
    //   34: goto +71 -> 105
    //   37: getstatic 28	o/IE:ॱꓸ	I
    //   40: bipush 7
    //   42: iadd
    //   43: istore 6
    //   45: iload 6
    //   47: sipush 128
    //   50: irem
    //   51: putstatic 26	o/IE:ॱـ	I
    //   54: iload 6
    //   56: iconst_2
    //   57: irem
    //   58: ifeq +6 -> 64
    //   61: goto +650 -> 711
    //   64: goto +94 -> 158
    //   67: getstatic 26	o/IE:ॱـ	I
    //   70: bipush 15
    //   72: iadd
    //   73: istore_0
    //   74: iload_0
    //   75: sipush 128
    //   78: irem
    //   79: putstatic 28	o/IE:ॱꓸ	I
    //   82: iload_0
    //   83: iconst_2
    //   84: irem
    //   85: ifne +6 -> 91
    //   88: goto -57 -> 31
    //   91: goto +493 -> 584
    //   94: iload 4
    //   96: ifle +6 -> 102
    //   99: goto +547 -> 646
    //   102: goto +475 -> 577
    //   105: iload_0
    //   106: lookupswitch	default:+26->132, 83:+484->590, 86:+566->672
    //   132: aload 9
    //   134: areturn
    //   135: astore 9
    //   137: aload 9
    //   139: athrow
    //   140: iconst_1
    //   141: istore 6
    //   143: goto +305 -> 448
    //   146: iload_3
    //   147: iload 4
    //   149: if_icmpge +6 -> 155
    //   152: goto +98 -> 250
    //   155: goto +326 -> 481
    //   158: getstatic 159	o/IE:ॱˌ	[B
    //   161: ifnull +6 -> 167
    //   164: goto +246 -> 410
    //   167: goto +167 -> 334
    //   170: iload_1
    //   171: iload 4
    //   173: iushr
    //   174: iconst_5
    //   175: irem
    //   176: getstatic 161	o/IE:ॱˈ	I
    //   179: ishl
    //   180: istore 7
    //   182: iload 6
    //   184: ifeq +6 -> 190
    //   187: goto +254 -> 441
    //   190: goto +449 -> 639
    //   193: iload 7
    //   195: lookupswitch	default:+25->220, 46:+300->495, 85:+352->547
    //   220: goto +327 -> 547
    //   223: aload 9
    //   225: iload 5
    //   227: invokevirtual 167	java/lang/StringBuilder:append	(C)Ljava/lang/StringBuilder;
    //   230: pop
    //   231: iload_3
    //   232: iconst_1
    //   233: iadd
    //   234: istore_3
    //   235: goto +253 -> 488
    //   238: iconst_0
    //   239: istore 6
    //   241: goto +381 -> 622
    //   244: iconst_0
    //   245: istore 6
    //   247: goto -244 -> 3
    //   250: bipush 14
    //   252: istore 6
    //   254: goto +426 -> 680
    //   257: iload_1
    //   258: iload 6
    //   260: iadd
    //   261: istore_1
    //   262: getstatic 169	o/IE:ॱˉ	I
    //   265: iload_3
    //   266: iadd
    //   267: i2c
    //   268: istore 5
    //   270: aload 9
    //   272: iload 5
    //   274: invokevirtual 167	java/lang/StringBuilder:append	(C)Ljava/lang/StringBuilder;
    //   277: pop
    //   278: iconst_1
    //   279: istore_3
    //   280: iload 5
    //   282: istore 7
    //   284: goto -138 -> 146
    //   287: getstatic 159	o/IE:ॱˌ	[B
    //   290: getstatic 161	o/IE:ॱˈ	I
    //   293: iload_1
    //   294: iadd
    //   295: baload
    //   296: getstatic 171	o/IE:ॱˑ	I
    //   299: iadd
    //   300: i2b
    //   301: istore 4
    //   303: goto +241 -> 544
    //   306: goto -49 -> 257
    //   309: iload_1
    //   310: iload 4
    //   312: iadd
    //   313: iconst_2
    //   314: isub
    //   315: getstatic 161	o/IE:ॱˈ	I
    //   318: iadd
    //   319: istore_1
    //   320: iload 6
    //   322: ifeq +6 -> 328
    //   325: goto -185 -> 140
    //   328: iload_1
    //   329: istore 6
    //   331: goto +262 -> 593
    //   334: getstatic 173	o/IE:ॱˍ	[S
    //   337: astore 10
    //   339: iload_1
    //   340: iconst_1
    //   341: isub
    //   342: istore 6
    //   344: aload 10
    //   346: iload_1
    //   347: saload
    //   348: iload_0
    //   349: iadd
    //   350: i2s
    //   351: iload_2
    //   352: ixor
    //   353: iload 7
    //   355: iadd
    //   356: i2c
    //   357: istore 5
    //   359: iload 6
    //   361: istore_1
    //   362: goto -139 -> 223
    //   365: goto +146 -> 511
    //   368: iload 7
    //   370: istore_1
    //   371: iload 7
    //   373: istore 6
    //   375: iload 8
    //   377: lookupswitch	default:+27->404, 8:+216->593, 17:+-237->140
    //   404: iload 7
    //   406: istore_1
    //   407: goto -267 -> 140
    //   410: getstatic 159	o/IE:ॱˌ	[B
    //   413: astore 10
    //   415: iload_1
    //   416: iconst_1
    //   417: isub
    //   418: istore 6
    //   420: aload 10
    //   422: iload_1
    //   423: baload
    //   424: iload_0
    //   425: iadd
    //   426: i2b
    //   427: iload_2
    //   428: ixor
    //   429: iload 7
    //   431: iadd
    //   432: i2c
    //   433: istore 5
    //   435: iload 6
    //   437: istore_1
    //   438: goto -215 -> 223
    //   441: bipush 17
    //   443: istore 8
    //   445: goto -77 -> 368
    //   448: getstatic 26	o/IE:ॱـ	I
    //   451: bipush 43
    //   453: iadd
    //   454: istore 7
    //   456: iload 7
    //   458: sipush 128
    //   461: irem
    //   462: putstatic 28	o/IE:ॱꓸ	I
    //   465: iload 7
    //   467: iconst_2
    //   468: irem
    //   469: ifne +6 -> 475
    //   472: goto +6 -> 478
    //   475: goto -169 -> 306
    //   478: goto -172 -> 306
    //   481: bipush 18
    //   483: istore 6
    //   485: goto +195 -> 680
    //   488: iload 5
    //   490: istore 7
    //   492: goto -346 -> 146
    //   495: aload 9
    //   497: invokevirtual 176	java/lang/StringBuilder:toString	()Ljava/lang/String;
    //   500: astore 9
    //   502: goto -435 -> 67
    //   505: iconst_1
    //   506: istore 6
    //   508: goto +114 -> 622
    //   511: new 163	java/lang/StringBuilder
    //   514: dup
    //   515: invokespecial 178	java/lang/StringBuilder:<init>	()V
    //   518: astore 9
    //   520: getstatic 171	o/IE:ॱˑ	I
    //   523: iload 4
    //   525: iadd
    //   526: istore 6
    //   528: iload 6
    //   530: istore 4
    //   532: iload 6
    //   534: iconst_m1
    //   535: if_icmpne +6 -> 541
    //   538: goto +95 -> 633
    //   541: goto -297 -> 244
    //   544: goto -450 -> 94
    //   547: getstatic 28	o/IE:ॱꓸ	I
    //   550: bipush 67
    //   552: iadd
    //   553: istore 7
    //   555: iload 7
    //   557: sipush 128
    //   560: irem
    //   561: putstatic 26	o/IE:ॱـ	I
    //   564: iload 7
    //   566: iconst_2
    //   567: irem
    //   568: ifeq +6 -> 574
    //   571: goto -401 -> 170
    //   574: goto -265 -> 309
    //   577: bipush 46
    //   579: istore 7
    //   581: goto -388 -> 193
    //   584: bipush 83
    //   586: istore_0
    //   587: goto -482 -> 105
    //   590: aload 9
    //   592: areturn
    //   593: iconst_0
    //   594: istore 7
    //   596: iload 6
    //   598: istore_1
    //   599: iload 7
    //   601: istore 6
    //   603: goto -346 -> 257
    //   606: getstatic 159	o/IE:ॱˌ	[B
    //   609: astore 10
    //   611: aload 10
    //   613: ifnull +6 -> 619
    //   616: goto -329 -> 287
    //   619: goto +34 -> 653
    //   622: iload 6
    //   624: ifeq +6 -> 630
    //   627: goto -21 -> 606
    //   630: goto -536 -> 94
    //   633: iconst_1
    //   634: istore 6
    //   636: goto -633 -> 3
    //   639: bipush 8
    //   641: istore 8
    //   643: goto -275 -> 368
    //   646: bipush 85
    //   648: istore 7
    //   650: goto -457 -> 193
    //   653: getstatic 173	o/IE:ॱˍ	[S
    //   656: getstatic 161	o/IE:ॱˈ	I
    //   659: iload_1
    //   660: iadd
    //   661: saload
    //   662: getstatic 171	o/IE:ॱˑ	I
    //   665: iadd
    //   666: i2s
    //   667: istore 4
    //   669: goto -575 -> 94
    //   672: bipush 41
    //   674: iconst_0
    //   675: idiv
    //   676: istore_0
    //   677: aload 9
    //   679: areturn
    //   680: iload 6
    //   682: lookupswitch	default:+26->708, 14:+-645->37, 18:+-187->495
    //   708: goto -671 -> 37
    //   711: goto -553 -> 158
    // Local variable table:
    //   start	length	slot	name	signature
    //   0	714	0	paramShort	short
    //   0	714	1	paramInt1	int
    //   0	714	2	paramByte	byte
    //   0	714	3	paramInt2	int
    //   0	714	4	paramInt3	int
    //   225	264	5	i	int
    //   3	678	6	j	int
    //   180	469	7	k	int
    //   375	267	8	m	int
    //   132	1	9	str	String
    //   135	361	9	localException	Exception
    //   500	178	9	localObject1	Object
    //   337	275	10	localObject2	Object
    // Exception table:
    //   from	to	target	type
    //   606	611	135	java/lang/Exception
  }
  
  static void ˎ()
  {
    ॱˑ = 2498;
    ॱˉ = 2062782648;
    ॱˍ = new short[] { 123, 136, 125, 115, 101, 104, 151, 89, 103, 111, 119, 104, -43, -59, -23, 28, 109, 112, 88, 109, 102, 115, 107, 95, 95, 106, 114, 95, 108, 108, 97, 86, 116, 92, 120, 105, 90, 108, 113, -8032, 8228, 94, 101, 104, 172, 67, 145, 40, 96, 108, 94, 101, 136, 70, 118, 101, 160, 33, 99, 122, 88, 109, 102, 115, -97, -11, -34, -6, 32, -13, -35, -95, -4, -35, -28, -20, -14, 39, -99, -4, -35, -28, -20, -14, 33, -80, -30, -18, -32, -25, 10, 14, -80, -30, -10, -34, 39, -74, -44, -2, -32, -79, -95, -79, -86, -83, -72, -117, -87, -73, 130, 94, 105, 118, 0, 0, 0, 0, 0, 0, 0 };
    ॱˈ = -574724465;
  }
  
  /* Error */
  private String ॱ(String paramString)
  {
    // Byte code:
    //   0: goto +263 -> 263
    //   3: getstatic 26	o/IE:ॱـ	I
    //   6: bipush 47
    //   8: iadd
    //   9: istore_2
    //   10: iload_2
    //   11: sipush 128
    //   14: irem
    //   15: putstatic 28	o/IE:ॱꓸ	I
    //   18: iload_2
    //   19: iconst_2
    //   20: irem
    //   21: ifne +6 -> 27
    //   24: goto +189 -> 213
    //   27: goto +113 -> 140
    //   30: iload_2
    //   31: lookupswitch	default:+25->56, 53:+94->125, 60:+142->173
    //   56: goto +117 -> 173
    //   59: aload_1
    //   60: bipush 83
    //   62: ldc_w 264
    //   65: iconst_0
    //   66: ldc_w 265
    //   69: sipush 63048
    //   72: invokestatic 67	o/IE:ˎ	(SIBII)Ljava/lang/String;
    //   75: invokevirtual 73	java/lang/String:intern	()Ljava/lang/String;
    //   78: invokevirtual 269	java/lang/String:getBytes	(Ljava/lang/String;)[B
    //   81: astore 4
    //   83: aload 4
    //   85: arraylength
    //   86: newarray byte
    //   88: astore_1
    //   89: iconst_0
    //   90: istore_2
    //   91: goto +157 -> 248
    //   94: bipush 53
    //   96: istore_2
    //   97: goto -67 -> 30
    //   100: aload_1
    //   101: iload_2
    //   102: aload 4
    //   104: aload 4
    //   106: arraylength
    //   107: iload_2
    //   108: isub
    //   109: iconst_1
    //   110: isub
    //   111: baload
    //   112: getstatic 33	o/IE:ߺ	B
    //   115: ixor
    //   116: i2b
    //   117: bastore
    //   118: iload_2
    //   119: iconst_1
    //   120: iadd
    //   121: istore_3
    //   122: goto +24 -> 146
    //   125: iconst_2
    //   126: iconst_3
    //   127: idiv
    //   128: istore_2
    //   129: iload_3
    //   130: istore_2
    //   131: goto +117 -> 248
    //   134: bipush 60
    //   136: istore_2
    //   137: goto -107 -> 30
    //   140: bipush 78
    //   142: istore_2
    //   143: goto +123 -> 266
    //   146: getstatic 28	o/IE:ॱꓸ	I
    //   149: bipush 27
    //   151: iadd
    //   152: istore_2
    //   153: iload_2
    //   154: sipush 128
    //   157: irem
    //   158: putstatic 26	o/IE:ॱـ	I
    //   161: iload_2
    //   162: iconst_2
    //   163: irem
    //   164: ifeq +6 -> 170
    //   167: goto -73 -> 94
    //   170: goto -36 -> 134
    //   173: iload_3
    //   174: istore_2
    //   175: goto +73 -> 248
    //   178: aload_1
    //   179: bipush 126
    //   181: ldc_w 264
    //   184: iconst_0
    //   185: ldc_w 265
    //   188: sipush 16626
    //   191: invokestatic 67	o/IE:ˎ	(SIBII)Ljava/lang/String;
    //   194: invokevirtual 73	java/lang/String:intern	()Ljava/lang/String;
    //   197: invokevirtual 269	java/lang/String:getBytes	(Ljava/lang/String;)[B
    //   200: astore 4
    //   202: aload 4
    //   204: arraylength
    //   205: newarray byte
    //   207: astore_1
    //   208: iconst_0
    //   209: istore_2
    //   210: goto +38 -> 248
    //   213: bipush 74
    //   215: istore_2
    //   216: goto +50 -> 266
    //   219: new 69	java/lang/String
    //   222: dup
    //   223: aload_1
    //   224: bipush -119
    //   226: ldc_w 270
    //   229: iconst_0
    //   230: ldc_w 271
    //   233: sipush 63043
    //   236: invokestatic 67	o/IE:ˎ	(SIBII)Ljava/lang/String;
    //   239: invokevirtual 73	java/lang/String:intern	()Ljava/lang/String;
    //   242: invokespecial 274	java/lang/String:<init>	([BLjava/lang/String;)V
    //   245: astore_1
    //   246: aload_1
    //   247: areturn
    //   248: aload 4
    //   250: arraylength
    //   251: istore_3
    //   252: iload_2
    //   253: iload_3
    //   254: if_icmpge +6 -> 260
    //   257: goto -157 -> 100
    //   260: goto -41 -> 219
    //   263: goto -260 -> 3
    //   266: iload_2
    //   267: lookupswitch	default:+25->292, 74:+-89->178, 78:+-208->59
    //   292: goto -233 -> 59
    //   295: astore_1
    //   296: new 276	java/lang/RuntimeException
    //   299: dup
    //   300: aload_1
    //   301: invokespecial 279	java/lang/RuntimeException:<init>	(Ljava/lang/Throwable;)V
    //   304: athrow
    // Local variable table:
    //   start	length	slot	name	signature
    //   0	305	0	this	IE
    //   0	305	1	paramString	String
    //   9	258	2	i	int
    //   121	134	3	j	int
    //   81	168	4	arrayOfByte	byte[]
    // Exception table:
    //   from	to	target	type
    //   59	89	295	java/io/UnsupportedEncodingException
    //   100	118	295	java/io/UnsupportedEncodingException
    //   178	208	295	java/io/UnsupportedEncodingException
    //   219	246	295	java/io/UnsupportedEncodingException
    //   248	252	295	java/io/UnsupportedEncodingException
  }
}
