package o;

import java.util.concurrent.Callable;
import ro.btrl.business.general.dao.TermsAndConditionsDao;

public final class Ih
  implements Ij
{
  private static char[] ˊ = { 55, 103, 100, 102, 107, 80, 74, 102, 108, 78, 40, 54, 82, 106, 106, 87, 87, 50, 107, 77, 81, 77, 57, 94, 107, 106, 105, 104, 73, 76, 111, 4173, 4165, 107, 117, 93, 91, 111, 106, 104, 100, 107, 77, 40, 43, 81, 113, 107, 109, 115, 109, 70, 40, 41, 36, 78, 83, 62, 94, 107, 106, 105, 104, 73, 73, 100, 101 };
  private static int ˋ = 0;
  private static int ॱ = 1;
  
  public Ih() {}
  
  private static String ॱ(int[] paramArrayOfInt, byte[] paramArrayOfByte, boolean paramBoolean)
  {
    break label273;
    int k = 32;
    break label438;
    label10:
    Object localObject;
    int i;
    localObject[i] = ((char)(localObject[i] - paramArrayOfInt[2]));
    i += 1;
    break label258;
    label30:
    label40:
    int m;
    label56:
    label68:
    int j;
    label82:
    char[] arrayOfChar;
    if (!paramBoolean)
    {
      break label485;
      localObject[i] = paramArrayOfByte[(m - i - 1)];
      i += 1;
      if (i >= m)
      {
        break label134;
        if (paramArrayOfByte[j] == 1) {
          break label418;
        }
        break label240;
        i = arrayOfChar[j];
        j += 1;
        break label306;
      }
    }
    for (;;)
    {
      label123:
      int i1;
      label134:
      label137:
      label175:
      int n;
      switch (i)
      {
      default: 
        break label575;
        if (i1 <= 0)
        {
          break label562;
          break label270;
          paramArrayOfInt = new String((char[])localObject);
          i = ॱ + 75;
          ˋ = i % 128;
          if (i % 2 != 0) {
            return paramArrayOfInt;
          }
          return paramArrayOfInt;
          i = paramArrayOfInt[0];
          m = paramArrayOfInt[1];
          n = paramArrayOfInt[2];
          i1 = paramArrayOfInt[3];
        }
      case 0: 
        try
        {
          arrayOfChar = ˊ;
          localObject = new char[m];
          System.arraycopy(arrayOfChar, i, localObject, 0, m);
          if (paramArrayOfByte == null)
          {
            paramArrayOfByte = (byte[])localObject;
            break label123;
            localObject = new char[m];
            i = 0;
            break label56;
            arrayOfChar[j] = ((char)((localObject[j] << '\001') - i));
            break label82;
            if (i < m) {
              break label10;
            }
            break label137;
            break label490;
            break label175;
            j = ॱ + 45;
            ˋ = j % 128;
            if (j % 2 != 0) {
              break label333;
            }
            break label40;
          }
          while (j >= m)
          {
            break label568;
            arrayOfChar = new char[m];
            i = 0;
            j = 0;
          }
          localObject[i] = paramArrayOfByte[(m % i >>> 0)];
          i += 63;
          break label56;
          for (;;)
          {
            localObject = paramArrayOfByte;
            switch (i)
            {
            case 0: 
            default: 
              localObject = paramArrayOfByte;
              break label490;
              i = 0;
            }
          }
          for (;;)
          {
            i = ॱ + 89;
            ˋ = i % 128;
            if (i % 2 != 0) {
              break label580;
            }
            break label638;
            arrayOfChar[j] = ((char)((localObject[j] << '\001') + 1 - i));
            break label82;
            switch (k)
            {
            case 32: 
            default: 
              break label68;
              i = 0;
              break label258;
              break label123;
              i = 47;
              break label504;
              i = 1;
              break label353;
              if (n <= 0) {
                break label498;
              }
            }
          }
        }
        catch (Exception paramArrayOfInt)
        {
          throw paramArrayOfInt;
        }
        switch (i)
        {
        }
        break;
      case 1: 
        for (;;)
        {
          label240:
          label258:
          label270:
          label273:
          label306:
          label333:
          label353:
          label418:
          label438:
          label476:
          label485:
          label490:
          label498:
          label504:
          i = ॱ + 119;
          ˋ = i % 128;
          if (i % 2 != 0) {
            break label123;
          }
          break label476;
          label562:
          i = 40;
          break label504;
          label568:
          k = 23;
          break label438;
          label575:
          i = 0;
          break label258;
          label580:
          i = 0;
          break;
          paramArrayOfByte = arrayOfChar;
        }
        localObject = new char[m];
        System.arraycopy(paramArrayOfByte, 0, localObject, 0, m);
        System.arraycopy(localObject, 0, paramArrayOfByte, m - i1, i1);
        System.arraycopy(localObject, i1, paramArrayOfByte, 0, m - i1);
        break label30;
        label638:
        i = 1;
      }
    }
  }
  
  /* Error */
  public sz<Gn> ॱ()
  {
    // Byte code:
    //   0: goto +536 -> 536
    //   3: goto +17 -> 20
    //   6: astore_2
    //   7: aload_2
    //   8: invokevirtual 85	java/lang/Throwable:getCause	()Ljava/lang/Throwable;
    //   11: astore_3
    //   12: aload_3
    //   13: ifnull +5 -> 18
    //   16: aload_3
    //   17: athrow
    //   18: aload_2
    //   19: athrow
    //   20: iconst_4
    //   21: sipush 160
    //   24: iconst_0
    //   25: invokestatic 90	o/O:ˋ	(IIC)Ljava/lang/Object;
    //   28: checkcast 92	java/lang/Class
    //   31: ldc 94
    //   33: aconst_null
    //   34: invokevirtual 98	java/lang/Class:getMethod	(Ljava/lang/String;[Ljava/lang/Class;)Ljava/lang/reflect/Method;
    //   37: aconst_null
    //   38: aconst_null
    //   39: invokevirtual 104	java/lang/reflect/Method:invoke	(Ljava/lang/Object;[Ljava/lang/Object;)Ljava/lang/Object;
    //   42: checkcast 106	o/Fb
    //   45: astore_2
    //   46: iconst_4
    //   47: newarray int
    //   49: dup
    //   50: iconst_0
    //   51: iconst_0
    //   52: iastore
    //   53: dup
    //   54: iconst_1
    //   55: bipush 17
    //   57: iastore
    //   58: dup
    //   59: iconst_2
    //   60: iconst_0
    //   61: iastore
    //   62: dup
    //   63: iconst_3
    //   64: bipush 11
    //   66: iastore
    //   67: bipush 17
    //   69: newarray byte
    //   71: dup
    //   72: iconst_0
    //   73: ldc 107
    //   75: bastore
    //   76: dup
    //   77: iconst_1
    //   78: ldc 108
    //   80: bastore
    //   81: dup
    //   82: iconst_2
    //   83: ldc 107
    //   85: bastore
    //   86: dup
    //   87: iconst_3
    //   88: ldc 107
    //   90: bastore
    //   91: dup
    //   92: iconst_4
    //   93: ldc 108
    //   95: bastore
    //   96: dup
    //   97: iconst_5
    //   98: ldc 107
    //   100: bastore
    //   101: dup
    //   102: bipush 6
    //   104: ldc 108
    //   106: bastore
    //   107: dup
    //   108: bipush 7
    //   110: ldc 107
    //   112: bastore
    //   113: dup
    //   114: bipush 8
    //   116: ldc 108
    //   118: bastore
    //   119: dup
    //   120: bipush 9
    //   122: ldc 107
    //   124: bastore
    //   125: dup
    //   126: bipush 10
    //   128: ldc 108
    //   130: bastore
    //   131: dup
    //   132: bipush 11
    //   134: ldc 108
    //   136: bastore
    //   137: dup
    //   138: bipush 12
    //   140: ldc 108
    //   142: bastore
    //   143: dup
    //   144: bipush 13
    //   146: ldc 108
    //   148: bastore
    //   149: dup
    //   150: bipush 14
    //   152: ldc 108
    //   154: bastore
    //   155: dup
    //   156: bipush 15
    //   158: ldc 107
    //   160: bastore
    //   161: dup
    //   162: bipush 16
    //   164: ldc 107
    //   166: bastore
    //   167: iconst_0
    //   168: invokestatic 110	o/Ih:ॱ	([I[BZ)Ljava/lang/String;
    //   171: astore_3
    //   172: aload_3
    //   173: invokevirtual 114	java/lang/String:intern	()Ljava/lang/String;
    //   176: astore_3
    //   177: aload_2
    //   178: aload_3
    //   179: invokestatic 119	o/vq:ˋ	(Ljava/lang/Object;Ljava/lang/String;)V
    //   182: new 8	o/Ih$ˊ
    //   185: dup
    //   186: aload_2
    //   187: invokevirtual 122	o/Fb:ˊ	()Lro/btrl/business/general/dao/TermsAndConditionsDao;
    //   190: invokespecial 125	o/Ih$ˊ:<init>	(Lro/btrl/business/general/dao/TermsAndConditionsDao;)V
    //   193: checkcast 127	java/util/concurrent/Callable
    //   196: invokestatic 133	o/sz:ˏ	(Ljava/util/concurrent/Callable;)Lo/sz;
    //   199: astore_2
    //   200: aload_2
    //   201: iconst_4
    //   202: newarray int
    //   204: dup
    //   205: iconst_0
    //   206: bipush 17
    //   208: iastore
    //   209: dup
    //   210: iconst_1
    //   211: bipush 50
    //   213: iastore
    //   214: dup
    //   215: iconst_2
    //   216: iconst_0
    //   217: iastore
    //   218: dup
    //   219: iconst_3
    //   220: bipush 40
    //   222: iastore
    //   223: bipush 50
    //   225: newarray byte
    //   227: dup
    //   228: iconst_0
    //   229: ldc 108
    //   231: bastore
    //   232: dup
    //   233: iconst_1
    //   234: ldc 108
    //   236: bastore
    //   237: dup
    //   238: iconst_2
    //   239: ldc 107
    //   241: bastore
    //   242: dup
    //   243: iconst_3
    //   244: ldc 108
    //   246: bastore
    //   247: dup
    //   248: iconst_4
    //   249: ldc 108
    //   251: bastore
    //   252: dup
    //   253: iconst_5
    //   254: ldc 108
    //   256: bastore
    //   257: dup
    //   258: bipush 6
    //   260: ldc 107
    //   262: bastore
    //   263: dup
    //   264: bipush 7
    //   266: ldc 108
    //   268: bastore
    //   269: dup
    //   270: bipush 8
    //   272: ldc 108
    //   274: bastore
    //   275: dup
    //   276: bipush 9
    //   278: ldc 108
    //   280: bastore
    //   281: dup
    //   282: bipush 10
    //   284: ldc 108
    //   286: bastore
    //   287: dup
    //   288: bipush 11
    //   290: ldc 108
    //   292: bastore
    //   293: dup
    //   294: bipush 12
    //   296: ldc 107
    //   298: bastore
    //   299: dup
    //   300: bipush 13
    //   302: ldc 108
    //   304: bastore
    //   305: dup
    //   306: bipush 14
    //   308: ldc 108
    //   310: bastore
    //   311: dup
    //   312: bipush 15
    //   314: ldc 108
    //   316: bastore
    //   317: dup
    //   318: bipush 16
    //   320: ldc 108
    //   322: bastore
    //   323: dup
    //   324: bipush 17
    //   326: ldc 108
    //   328: bastore
    //   329: dup
    //   330: bipush 18
    //   332: ldc 108
    //   334: bastore
    //   335: dup
    //   336: bipush 19
    //   338: ldc 108
    //   340: bastore
    //   341: dup
    //   342: bipush 20
    //   344: ldc 107
    //   346: bastore
    //   347: dup
    //   348: bipush 21
    //   350: ldc 108
    //   352: bastore
    //   353: dup
    //   354: bipush 22
    //   356: ldc 107
    //   358: bastore
    //   359: dup
    //   360: bipush 23
    //   362: ldc 108
    //   364: bastore
    //   365: dup
    //   366: bipush 24
    //   368: ldc 108
    //   370: bastore
    //   371: dup
    //   372: bipush 25
    //   374: ldc 107
    //   376: bastore
    //   377: dup
    //   378: bipush 26
    //   380: ldc 108
    //   382: bastore
    //   383: dup
    //   384: bipush 27
    //   386: ldc 108
    //   388: bastore
    //   389: dup
    //   390: bipush 28
    //   392: ldc 108
    //   394: bastore
    //   395: dup
    //   396: bipush 29
    //   398: ldc 108
    //   400: bastore
    //   401: dup
    //   402: bipush 30
    //   404: ldc 108
    //   406: bastore
    //   407: dup
    //   408: bipush 31
    //   410: ldc 107
    //   412: bastore
    //   413: dup
    //   414: bipush 32
    //   416: ldc 107
    //   418: bastore
    //   419: dup
    //   420: bipush 33
    //   422: ldc 107
    //   424: bastore
    //   425: dup
    //   426: bipush 34
    //   428: ldc 108
    //   430: bastore
    //   431: dup
    //   432: bipush 35
    //   434: ldc 108
    //   436: bastore
    //   437: dup
    //   438: bipush 36
    //   440: ldc 107
    //   442: bastore
    //   443: dup
    //   444: bipush 37
    //   446: ldc 108
    //   448: bastore
    //   449: dup
    //   450: bipush 38
    //   452: ldc 108
    //   454: bastore
    //   455: dup
    //   456: bipush 39
    //   458: ldc 107
    //   460: bastore
    //   461: dup
    //   462: bipush 40
    //   464: ldc 107
    //   466: bastore
    //   467: dup
    //   468: bipush 41
    //   470: ldc 107
    //   472: bastore
    //   473: dup
    //   474: bipush 42
    //   476: ldc 108
    //   478: bastore
    //   479: dup
    //   480: bipush 43
    //   482: ldc 108
    //   484: bastore
    //   485: dup
    //   486: bipush 44
    //   488: ldc 108
    //   490: bastore
    //   491: dup
    //   492: bipush 45
    //   494: ldc 108
    //   496: bastore
    //   497: dup
    //   498: bipush 46
    //   500: ldc 108
    //   502: bastore
    //   503: dup
    //   504: bipush 47
    //   506: ldc 107
    //   508: bastore
    //   509: dup
    //   510: bipush 48
    //   512: ldc 108
    //   514: bastore
    //   515: dup
    //   516: bipush 49
    //   518: ldc 108
    //   520: bastore
    //   521: iconst_0
    //   522: invokestatic 110	o/Ih:ॱ	([I[BZ)Ljava/lang/String;
    //   525: invokevirtual 114	java/lang/String:intern	()Ljava/lang/String;
    //   528: invokestatic 119	o/vq:ˋ	(Ljava/lang/Object;Ljava/lang/String;)V
    //   531: goto +29 -> 560
    //   534: aload_2
    //   535: areturn
    //   536: goto -533 -> 3
    //   539: aconst_null
    //   540: arraylength
    //   541: istore_1
    //   542: aload_2
    //   543: areturn
    //   544: astore_2
    //   545: aload_2
    //   546: athrow
    //   547: iconst_1
    //   548: istore_1
    //   549: goto +38 -> 587
    //   552: iconst_0
    //   553: istore_1
    //   554: goto +33 -> 587
    //   557: astore_2
    //   558: aload_2
    //   559: athrow
    //   560: getstatic 19	o/Ih:ॱ	I
    //   563: bipush 111
    //   565: iadd
    //   566: istore_1
    //   567: iload_1
    //   568: sipush 128
    //   571: irem
    //   572: putstatic 17	o/Ih:ˋ	I
    //   575: iload_1
    //   576: iconst_2
    //   577: irem
    //   578: ifeq +6 -> 584
    //   581: goto -34 -> 547
    //   584: goto -32 -> 552
    //   587: iload_1
    //   588: tableswitch	default:+24->612, 0:+-54->534, 1:+-49->539
    //   612: aload_2
    //   613: areturn
    // Local variable table:
    //   start	length	slot	name	signature
    //   0	614	0	this	Ih
    //   541	47	1	i	int
    //   6	13	2	localObject1	Object
    //   45	498	2	localObject2	Object
    //   544	2	2	localException1	Exception
    //   557	56	2	localException2	Exception
    //   11	168	3	localObject3	Object
    // Exception table:
    //   from	to	target	type
    //   20	46	6	finally
    //   46	172	544	java/lang/Exception
    //   7	12	557	java/lang/Exception
    //   16	18	557	java/lang/Exception
    //   18	20	557	java/lang/Exception
    //   46	172	557	java/lang/Exception
    //   172	177	557	java/lang/Exception
    //   177	531	557	java/lang/Exception
  }
  
  static final class ˊ<V>
    implements Callable<sE<? extends T>>
  {
    ˊ(TermsAndConditionsDao paramTermsAndConditionsDao) {}
    
    public final sz<Gn> ˏ()
    {
      return sz.ॱ(this.ˎ.ᐝ().ˋ());
    }
  }
}
