package o;

import android.content.Context;
import java.io.UnsupportedEncodingException;
import java.lang.ref.WeakReference;
import java.net.URI;

@Deprecated
public abstract class Ik<T>
  implements Cx<T>
{
  private static int ˊ = 0;
  private static byte ˋ;
  private static long ˎ;
  private static int ˏ = 1;
  private static char[] ॱ;
  private Cv<T> mCall;
  private WeakReference<Context> mContextWeakReference;
  private Fg mErrorResponse;
  private boolean mIsIgnoreContext;
  private CG<T> mResponse;
  private int mRetryCount;
  
  static
  {
    ʻ();
    ˋ = -102;
    int i = ˏ + 87;
    ˊ = i % 128;
    if (i % 2 != 0) {}
  }
  
  /* Error */
  public Ik(Context paramContext)
  {
    // Byte code:
    //   0: goto +6 -> 6
    //   3: astore_1
    //   4: aload_1
    //   5: athrow
    //   6: aload_0
    //   7: invokespecial 55	java/lang/Object:<init>	()V
    //   10: aload_0
    //   11: iconst_1
    //   12: putfield 57	o/Ik:mRetryCount	I
    //   15: new 59	java/lang/ref/WeakReference
    //   18: dup
    //   19: aload_1
    //   20: invokespecial 62	java/lang/ref/WeakReference:<init>	(Ljava/lang/Object;)V
    //   23: astore_1
    //   24: aload_0
    //   25: aload_1
    //   26: putfield 64	o/Ik:mContextWeakReference	Ljava/lang/ref/WeakReference;
    //   29: return
    //   30: astore_1
    //   31: aload_1
    //   32: athrow
    // Local variable table:
    //   start	length	slot	name	signature
    //   0	33	0	this	Ik
    //   0	33	1	paramContext	Context
    // Exception table:
    //   from	to	target	type
    //   24	29	3	java/lang/Exception
    //   10	15	30	java/lang/Exception
  }
  
  static void ʻ()
  {
    ˎ = 8713785937335117333L;
    ॱ = new char[] { 10340, 20058, -7052, 6754, -20463, -10703, 19519, 72, 26228, -13244, 12891, -26568, -512, 25616, -13580, 12424, -26929, -841, 25238, -14199, 12148, -27307, -1201, 24938, -14523, -28004, 3397, 27495, -16052, 16221, -27354, -3315, 26909, -14428, 31070, 7951, -19141, 19236, -7847, -30921, 7534, -19582, 18850, -4125, -31292, 7160, -19980, 22026, -5000, -32218, 6209, -16779, 21616, -5484, -32606, 9907, -17264, 21234, -5900, -32429, 10047, -17114, 21340, -5781, -28819, 9613, -17494, 20971, 8905, 17618, -4380, 4336, -17786, -9044, 18106, -6115, 4648, -19340, -8703, 16398, -5573, 3551, -18455, -9751, 17301, -6778, 4021, -20159, -9360, 32124, -6378, 2359, -19592, -9584, 31906, 32, 26227, -13237, 12886, -26568, -500, 25626, -13645, 12511, -26924, -858, 25231, -14138, 12081, 16666, 10040, -29433, 29455, -9863, -16618, 9538, -29789, 29075, -10361, -16969, 9112, 8109, 31225, -11319, 11734, -30727, -7807, 31617, -10900, 12106, -30398, -7297, 32007, -10476, 12527, -29992, -6953, 32442, -10099, 13005, -29662, 12967, 21637, -341, 184, -21800, -13067, 22245, -2047, 615, -23448, 117, 26235, -13247, 12881, -26565, -482, 25616, 69, 26215, -13224, 12880, -26586, -439, 25623, -13571, 12424, -26929, -841, 25238, -14199, 12148, -27307, -1201, 24938, -14523, 9009, 17723, -4331, 4359, 73, 26182, -13211, 12818, -26516, -431, 25675, -13654, 12421, -26996, 85, 26177, -13204, 12818, -26516 };
  }
  
  /* Error */
  private void ˊ(Cv<T> paramCv)
  {
    // Byte code:
    //   0: goto +232 -> 232
    //   3: iconst_0
    //   4: istore_2
    //   5: goto +30 -> 35
    //   8: getstatic 41	o/Ik:ˊ	I
    //   11: bipush 59
    //   13: iadd
    //   14: istore_2
    //   15: iload_2
    //   16: sipush 128
    //   19: irem
    //   20: putstatic 43	o/Ik:ˏ	I
    //   23: iload_2
    //   24: iconst_2
    //   25: irem
    //   26: ifne +6 -> 32
    //   29: goto -26 -> 3
    //   32: goto +204 -> 236
    //   35: iload_2
    //   36: tableswitch	default:+24->60, 0:+192->228, 1:+199->235
    //   60: goto +168 -> 228
    //   63: iconst_0
    //   64: sipush 10282
    //   67: bipush 7
    //   69: invokestatic 255	o/Ik:ˋ	(ICI)Ljava/lang/String;
    //   72: invokevirtual 261	java/lang/String:intern	()Ljava/lang/String;
    //   75: astore_3
    //   76: new 263	java/lang/StringBuilder
    //   79: dup
    //   80: invokespecial 264	java/lang/StringBuilder:<init>	()V
    //   83: sipush 141
    //   86: sipush 13045
    //   89: bipush 10
    //   91: invokestatic 255	o/Ik:ˋ	(ICI)Ljava/lang/String;
    //   94: invokevirtual 261	java/lang/String:intern	()Ljava/lang/String;
    //   97: invokevirtual 268	java/lang/StringBuilder:append	(Ljava/lang/String;)Ljava/lang/StringBuilder;
    //   100: aload_1
    //   101: invokeinterface 273 1 0
    //   106: invokevirtual 277	o/xG:ˎ	()Ljava/lang/String;
    //   109: invokevirtual 268	java/lang/StringBuilder:append	(Ljava/lang/String;)Ljava/lang/StringBuilder;
    //   112: bipush 25
    //   114: ldc_w 278
    //   117: iconst_1
    //   118: invokestatic 255	o/Ik:ˋ	(ICI)Ljava/lang/String;
    //   121: invokevirtual 261	java/lang/String:intern	()Ljava/lang/String;
    //   124: invokevirtual 268	java/lang/StringBuilder:append	(Ljava/lang/String;)Ljava/lang/StringBuilder;
    //   127: aload_1
    //   128: invokeinterface 273 1 0
    //   133: invokevirtual 281	o/xG:ˋ	()Lo/xy;
    //   136: invokevirtual 284	java/lang/StringBuilder:append	(Ljava/lang/Object;)Ljava/lang/StringBuilder;
    //   139: invokevirtual 287	java/lang/StringBuilder:toString	()Ljava/lang/String;
    //   142: astore 4
    //   144: goto +17 -> 161
    //   147: astore_1
    //   148: aload_1
    //   149: invokevirtual 293	java/lang/Throwable:getCause	()Ljava/lang/Throwable;
    //   152: astore_3
    //   153: aload_3
    //   154: ifnull +5 -> 159
    //   157: aload_3
    //   158: athrow
    //   159: aload_1
    //   160: athrow
    //   161: iconst_4
    //   162: bipush 42
    //   164: ldc_w 294
    //   167: invokestatic 299	o/O:ˋ	(IIC)Ljava/lang/Object;
    //   170: checkcast 301	java/lang/Class
    //   173: ldc_w 302
    //   176: iconst_2
    //   177: anewarray 301	java/lang/Class
    //   180: dup
    //   181: iconst_0
    //   182: ldc_w 257
    //   185: aastore
    //   186: dup
    //   187: iconst_1
    //   188: ldc_w 257
    //   191: aastore
    //   192: invokevirtual 306	java/lang/Class:getMethod	(Ljava/lang/String;[Ljava/lang/Class;)Ljava/lang/reflect/Method;
    //   195: aconst_null
    //   196: iconst_2
    //   197: anewarray 5	java/lang/Object
    //   200: dup
    //   201: iconst_0
    //   202: aload_3
    //   203: aastore
    //   204: dup
    //   205: iconst_1
    //   206: aload 4
    //   208: aastore
    //   209: invokevirtual 312	java/lang/reflect/Method:invoke	(Ljava/lang/Object;[Ljava/lang/Object;)Ljava/lang/Object;
    //   212: pop
    //   213: aload_1
    //   214: invokeinterface 315 1 0
    //   219: aload_0
    //   220: invokeinterface 318 2 0
    //   225: goto -217 -> 8
    //   228: aconst_null
    //   229: arraylength
    //   230: istore_2
    //   231: return
    //   232: goto -169 -> 63
    //   235: return
    //   236: iconst_1
    //   237: istore_2
    //   238: goto -203 -> 35
    // Local variable table:
    //   start	length	slot	name	signature
    //   0	241	0	this	Ik
    //   0	241	1	paramCv	Cv<T>
    //   4	234	2	i	int
    //   75	128	3	localObject	Object
    //   142	65	4	str	String
    // Exception table:
    //   from	to	target	type
    //   161	213	147	finally
  }
  
  /* Error */
  private void ˊ(final Cv<T> paramCv, boolean paramBoolean, Fg paramFg)
  {
    // Byte code:
    //   0: goto +6 -> 6
    //   3: goto +497 -> 500
    //   6: goto +688 -> 694
    //   9: new 323	o/B
    //   12: dup
    //   13: aload_3
    //   14: aload 7
    //   16: aload 6
    //   18: aload_1
    //   19: invokespecial 326	o/B:<init>	(Landroid/content/Context;Ljava/lang/String;Ljava/lang/String;Ljava/lang/String;)V
    //   22: iconst_1
    //   23: invokevirtual 329	o/B:ˋ	(Z)Lo/ᐸ$If;
    //   26: iconst_0
    //   27: invokevirtual 333	o/ᐸ$If:ˎ	(Z)Lo/ᐸ$If;
    //   30: new 9	o/Ik$3
    //   33: dup
    //   34: aload_0
    //   35: invokespecial 336	o/Ik$3:<init>	(Lo/Ik;)V
    //   38: invokevirtual 339	o/ᐸ$If:ॱ	(Lo/ᐸ$ˏ;)Lo/ᐸ$If;
    //   41: invokevirtual 342	o/ᐸ$If:ˏ	()Lo/ᐸ;
    //   44: pop
    //   45: return
    //   46: iconst_0
    //   47: istore 4
    //   49: goto +259 -> 308
    //   52: goto +538 -> 590
    //   55: goto +372 -> 427
    //   58: aload_0
    //   59: invokevirtual 346	o/Ik:ʽ	()Landroid/content/Context;
    //   62: astore_3
    //   63: aload_0
    //   64: invokevirtual 346	o/Ik:ʽ	()Landroid/content/Context;
    //   67: getstatic 351	o/Gu$ˏ:ok	I
    //   70: invokevirtual 357	android/content/Context:getString	(I)Ljava/lang/String;
    //   73: astore_1
    //   74: aload_1
    //   75: aload 9
    //   77: invokevirtual 361	java/lang/String:startsWith	(Ljava/lang/String;)Z
    //   80: ifeq +6 -> 86
    //   83: goto +704 -> 787
    //   86: goto -77 -> 9
    //   89: getstatic 43	o/Ik:ˏ	I
    //   92: bipush 125
    //   94: iadd
    //   95: istore 4
    //   97: iload 4
    //   99: sipush 128
    //   102: irem
    //   103: putstatic 41	o/Ik:ˊ	I
    //   106: iload 4
    //   108: iconst_2
    //   109: irem
    //   110: ifeq +6 -> 116
    //   113: goto +362 -> 475
    //   116: goto +293 -> 409
    //   119: aload_3
    //   120: getfield 367	o/Fg:error	Lo/Fd;
    //   123: getfield 373	o/Fd:code	Ljava/lang/String;
    //   126: getstatic 379	o/EF:BTW_OTP_INCORRECT_ENTERED_OTP	Lo/EF;
    //   129: invokevirtual 381	o/EF:ˏ	()Ljava/lang/String;
    //   132: invokevirtual 385	java/lang/String:equals	(Ljava/lang/Object;)Z
    //   135: ifne +6 -> 141
    //   138: goto +806 -> 944
    //   141: goto -83 -> 58
    //   144: iconst_1
    //   145: istore 4
    //   147: goto +161 -> 308
    //   150: aload_0
    //   151: aload 8
    //   153: iconst_4
    //   154: invokevirtual 388	java/lang/String:substring	(I)Ljava/lang/String;
    //   157: invokespecial 391	o/Ik:ˋ	(Ljava/lang/String;)Ljava/lang/String;
    //   160: invokevirtual 261	java/lang/String:intern	()Ljava/lang/String;
    //   163: astore 6
    //   165: goto +175 -> 340
    //   168: iload_2
    //   169: ifeq +6 -> 175
    //   172: goto +492 -> 664
    //   175: aload_0
    //   176: invokevirtual 346	o/Ik:ʽ	()Landroid/content/Context;
    //   179: getstatic 394	o/Gu$ˏ:an_error_occurred	I
    //   182: invokevirtual 357	android/content/Context:getString	(I)Ljava/lang/String;
    //   185: astore 8
    //   187: aload 8
    //   189: aload 9
    //   191: invokevirtual 361	java/lang/String:startsWith	(Ljava/lang/String;)Z
    //   194: ifeq +6 -> 200
    //   197: goto -151 -> 46
    //   200: goto -56 -> 144
    //   203: aload_3
    //   204: getfield 367	o/Fg:error	Lo/Fd;
    //   207: getfield 397	o/Fd:userMessage	Ljava/lang/String;
    //   210: astore 6
    //   212: goto +411 -> 623
    //   215: aload_0
    //   216: invokevirtual 346	o/Ik:ʽ	()Landroid/content/Context;
    //   219: getstatic 351	o/Gu$ˏ:ok	I
    //   222: invokevirtual 357	android/content/Context:getString	(I)Ljava/lang/String;
    //   225: astore 8
    //   227: aload 8
    //   229: aload 9
    //   231: invokevirtual 361	java/lang/String:startsWith	(Ljava/lang/String;)Z
    //   234: ifeq +6 -> 240
    //   237: goto +208 -> 445
    //   240: goto +260 -> 500
    //   243: aload_3
    //   244: getfield 367	o/Fg:error	Lo/Fd;
    //   247: getfield 397	o/Fd:userMessage	Ljava/lang/String;
    //   250: astore 6
    //   252: aconst_null
    //   253: arraylength
    //   254: istore 4
    //   256: aload 6
    //   258: ifnull +6 -> 264
    //   261: goto +372 -> 633
    //   264: goto -89 -> 175
    //   267: aload_3
    //   268: getfield 367	o/Fg:error	Lo/Fd;
    //   271: getfield 373	o/Fd:code	Ljava/lang/String;
    //   274: getstatic 400	o/EF:BTW_OTP_ENTER_EXCEEDED_THRESHOLD	Lo/EF;
    //   277: invokevirtual 381	o/EF:ˏ	()Ljava/lang/String;
    //   280: invokevirtual 385	java/lang/String:equals	(Ljava/lang/Object;)Z
    //   283: ifeq +6 -> 289
    //   286: goto -228 -> 58
    //   289: goto +590 -> 879
    //   292: aload_0
    //   293: aload_3
    //   294: iconst_4
    //   295: invokevirtual 388	java/lang/String:substring	(I)Ljava/lang/String;
    //   298: invokespecial 391	o/Ik:ˋ	(Ljava/lang/String;)Ljava/lang/String;
    //   301: invokevirtual 261	java/lang/String:intern	()Ljava/lang/String;
    //   304: astore_3
    //   305: goto +498 -> 803
    //   308: aload 8
    //   310: astore 6
    //   312: iload 4
    //   314: tableswitch	default:+22->336, 0:+-164->150, 1:+26->340
    //   336: aload 8
    //   338: astore 6
    //   340: goto +283 -> 623
    //   343: sipush 176
    //   346: sipush 9012
    //   349: iconst_4
    //   350: invokestatic 255	o/Ik:ˋ	(ICI)Ljava/lang/String;
    //   353: invokevirtual 261	java/lang/String:intern	()Ljava/lang/String;
    //   356: astore 9
    //   358: aload_0
    //   359: invokevirtual 346	o/Ik:ʽ	()Landroid/content/Context;
    //   362: getstatic 403	o/Gu$ˏ:oops	I
    //   365: invokevirtual 357	android/content/Context:getString	(I)Ljava/lang/String;
    //   368: astore 7
    //   370: aload 7
    //   372: aload 9
    //   374: invokevirtual 361	java/lang/String:startsWith	(Ljava/lang/String;)Z
    //   377: ifeq +6 -> 383
    //   380: goto -291 -> 89
    //   383: goto -215 -> 168
    //   386: aload_3
    //   387: getfield 367	o/Fg:error	Lo/Fd;
    //   390: getfield 397	o/Fd:userMessage	Ljava/lang/String;
    //   393: astore_1
    //   394: new 405	java/lang/NullPointerException
    //   397: dup
    //   398: invokespecial 406	java/lang/NullPointerException:<init>	()V
    //   401: athrow
    //   402: bipush 47
    //   404: istore 4
    //   406: goto +351 -> 757
    //   409: aload_0
    //   410: aload 7
    //   412: iconst_4
    //   413: invokevirtual 388	java/lang/String:substring	(I)Ljava/lang/String;
    //   416: invokespecial 391	o/Ik:ˋ	(Ljava/lang/String;)Ljava/lang/String;
    //   419: invokevirtual 261	java/lang/String:intern	()Ljava/lang/String;
    //   422: astore 7
    //   424: goto -256 -> 168
    //   427: aload_0
    //   428: aload 8
    //   430: iconst_4
    //   431: invokevirtual 388	java/lang/String:substring	(I)Ljava/lang/String;
    //   434: invokespecial 391	o/Ik:ˋ	(Ljava/lang/String;)Ljava/lang/String;
    //   437: invokevirtual 261	java/lang/String:intern	()Ljava/lang/String;
    //   440: astore 8
    //   442: goto -439 -> 3
    //   445: getstatic 41	o/Ik:ˊ	I
    //   448: bipush 115
    //   450: iadd
    //   451: istore 4
    //   453: iload 4
    //   455: sipush 128
    //   458: irem
    //   459: putstatic 43	o/Ik:ˏ	I
    //   462: iload 4
    //   464: iconst_2
    //   465: irem
    //   466: ifne +6 -> 472
    //   469: goto -414 -> 55
    //   472: goto -45 -> 427
    //   475: aload_0
    //   476: aload 7
    //   478: iconst_4
    //   479: invokevirtual 388	java/lang/String:substring	(I)Ljava/lang/String;
    //   482: invokespecial 391	o/Ik:ˋ	(Ljava/lang/String;)Ljava/lang/String;
    //   485: invokevirtual 261	java/lang/String:intern	()Ljava/lang/String;
    //   488: astore_1
    //   489: new 405	java/lang/NullPointerException
    //   492: dup
    //   493: invokespecial 406	java/lang/NullPointerException:<init>	()V
    //   496: athrow
    //   497: astore_1
    //   498: aload_1
    //   499: athrow
    //   500: new 408	o/E
    //   503: dup
    //   504: aload 10
    //   506: aload 7
    //   508: aload 6
    //   510: aload_3
    //   511: aload 8
    //   513: invokespecial 411	o/E:<init>	(Landroid/content/Context;Ljava/lang/String;Ljava/lang/String;Ljava/lang/String;Ljava/lang/String;)V
    //   516: iconst_1
    //   517: invokevirtual 412	o/E:ˋ	(Z)Lo/ᐸ$If;
    //   520: iconst_0
    //   521: invokevirtual 333	o/ᐸ$If:ˎ	(Z)Lo/ᐸ$If;
    //   524: new 11	o/Ik$4
    //   527: dup
    //   528: aload_0
    //   529: aload_1
    //   530: invokespecial 415	o/Ik$4:<init>	(Lo/Ik;Lo/Cv;)V
    //   533: invokevirtual 339	o/ᐸ$If:ॱ	(Lo/ᐸ$ˏ;)Lo/ᐸ$If;
    //   536: new 13	o/Ik$5
    //   539: dup
    //   540: aload_0
    //   541: invokespecial 416	o/Ik$5:<init>	(Lo/Ik;)V
    //   544: invokevirtual 418	o/ᐸ$If:ˊ	(Lo/ᐸ$ˏ;)Lo/ᐸ$If;
    //   547: invokevirtual 342	o/ᐸ$If:ˏ	()Lo/ᐸ;
    //   550: pop
    //   551: return
    //   552: bipush 38
    //   554: istore 4
    //   556: goto +201 -> 757
    //   559: aload_3
    //   560: getfield 367	o/Fg:error	Lo/Fd;
    //   563: getfield 373	o/Fd:code	Ljava/lang/String;
    //   566: getstatic 400	o/EF:BTW_OTP_ENTER_EXCEEDED_THRESHOLD	Lo/EF;
    //   569: invokevirtual 381	o/EF:ˏ	()Ljava/lang/String;
    //   572: invokevirtual 385	java/lang/String:equals	(Ljava/lang/Object;)Z
    //   575: istore_2
    //   576: aconst_null
    //   577: arraylength
    //   578: istore 4
    //   580: iload_2
    //   581: ifeq +6 -> 587
    //   584: goto -526 -> 58
    //   587: goto +292 -> 879
    //   590: goto -375 -> 215
    //   593: getstatic 41	o/Ik:ˊ	I
    //   596: bipush 89
    //   598: iadd
    //   599: istore 4
    //   601: iload 4
    //   603: sipush 128
    //   606: irem
    //   607: putstatic 43	o/Ik:ˏ	I
    //   610: iload 4
    //   612: iconst_2
    //   613: irem
    //   614: ifne +6 -> 620
    //   617: goto -231 -> 386
    //   620: goto -417 -> 203
    //   623: iload_2
    //   624: ifeq +6 -> 630
    //   627: goto +287 -> 914
    //   630: goto +249 -> 879
    //   633: aload_3
    //   634: getfield 367	o/Fg:error	Lo/Fd;
    //   637: astore 6
    //   639: aload 6
    //   641: getfield 397	o/Fd:userMessage	Ljava/lang/String;
    //   644: astore 6
    //   646: aload 6
    //   648: invokevirtual 422	java/lang/String:isEmpty	()Z
    //   651: istore 5
    //   653: iload 5
    //   655: ifne +6 -> 661
    //   658: goto -65 -> 593
    //   661: goto -486 -> 175
    //   664: getstatic 43	o/Ik:ˏ	I
    //   667: bipush 121
    //   669: iadd
    //   670: istore 4
    //   672: iload 4
    //   674: sipush 128
    //   677: irem
    //   678: putstatic 41	o/Ik:ˊ	I
    //   681: iload 4
    //   683: iconst_2
    //   684: irem
    //   685: ifeq +6 -> 691
    //   688: goto -445 -> 243
    //   691: goto +172 -> 863
    //   694: getstatic 41	o/Ik:ˊ	I
    //   697: bipush 79
    //   699: iadd
    //   700: istore 4
    //   702: iload 4
    //   704: sipush 128
    //   707: irem
    //   708: putstatic 43	o/Ik:ˏ	I
    //   711: iload 4
    //   713: iconst_2
    //   714: irem
    //   715: ifne +6 -> 721
    //   718: goto +193 -> 911
    //   721: goto -378 -> 343
    //   724: aload_3
    //   725: getfield 367	o/Fg:error	Lo/Fd;
    //   728: getfield 373	o/Fd:code	Ljava/lang/String;
    //   731: getstatic 379	o/EF:BTW_OTP_INCORRECT_ENTERED_OTP	Lo/EF;
    //   734: invokevirtual 381	o/EF:ˏ	()Ljava/lang/String;
    //   737: invokevirtual 385	java/lang/String:equals	(Ljava/lang/Object;)Z
    //   740: istore_2
    //   741: bipush 41
    //   743: iconst_0
    //   744: idiv
    //   745: istore 4
    //   747: iload_2
    //   748: ifne +6 -> 754
    //   751: goto +193 -> 944
    //   754: goto -696 -> 58
    //   757: iload 4
    //   759: lookupswitch	default:+25->784, 38:+-640->119, 47:+-35->724
    //   784: goto -665 -> 119
    //   787: aload_0
    //   788: aload_1
    //   789: iconst_4
    //   790: invokevirtual 388	java/lang/String:substring	(I)Ljava/lang/String;
    //   793: invokespecial 391	o/Ik:ˋ	(Ljava/lang/String;)Ljava/lang/String;
    //   796: invokevirtual 261	java/lang/String:intern	()Ljava/lang/String;
    //   799: astore_1
    //   800: goto -791 -> 9
    //   803: getstatic 43	o/Ik:ˏ	I
    //   806: bipush 121
    //   808: iadd
    //   809: istore 4
    //   811: iload 4
    //   813: sipush 128
    //   816: irem
    //   817: putstatic 41	o/Ik:ˊ	I
    //   820: iload 4
    //   822: iconst_2
    //   823: irem
    //   824: ifeq +6 -> 830
    //   827: goto -775 -> 52
    //   830: goto -240 -> 590
    //   833: getstatic 43	o/Ik:ˏ	I
    //   836: bipush 9
    //   838: iadd
    //   839: istore 4
    //   841: iload 4
    //   843: sipush 128
    //   846: irem
    //   847: putstatic 41	o/Ik:ˊ	I
    //   850: iload 4
    //   852: iconst_2
    //   853: irem
    //   854: ifeq +6 -> 860
    //   857: goto -298 -> 559
    //   860: goto -593 -> 267
    //   863: aload_3
    //   864: getfield 367	o/Fg:error	Lo/Fd;
    //   867: getfield 397	o/Fd:userMessage	Ljava/lang/String;
    //   870: ifnull +6 -> 876
    //   873: goto -240 -> 633
    //   876: goto -701 -> 175
    //   879: aload_0
    //   880: invokevirtual 346	o/Ik:ʽ	()Landroid/content/Context;
    //   883: astore 10
    //   885: aload_0
    //   886: invokevirtual 346	o/Ik:ʽ	()Landroid/content/Context;
    //   889: getstatic 425	o/Gu$ˏ:retry	I
    //   892: invokevirtual 357	android/content/Context:getString	(I)Ljava/lang/String;
    //   895: astore_3
    //   896: aload_3
    //   897: aload 9
    //   899: invokevirtual 361	java/lang/String:startsWith	(Ljava/lang/String;)Z
    //   902: ifeq +6 -> 908
    //   905: goto -613 -> 292
    //   908: goto -693 -> 215
    //   911: goto -568 -> 343
    //   914: getstatic 43	o/Ik:ˏ	I
    //   917: bipush 77
    //   919: iadd
    //   920: istore 4
    //   922: iload 4
    //   924: sipush 128
    //   927: irem
    //   928: putstatic 41	o/Ik:ˊ	I
    //   931: iload 4
    //   933: iconst_2
    //   934: irem
    //   935: ifeq +6 -> 941
    //   938: goto -536 -> 402
    //   941: goto -389 -> 552
    //   944: aload_3
    //   945: getfield 367	o/Fg:error	Lo/Fd;
    //   948: getfield 373	o/Fd:code	Ljava/lang/String;
    //   951: getstatic 428	o/EF:BTW_OTP_ENTER_EXPIRED_OTP	Lo/EF;
    //   954: invokevirtual 381	o/EF:ˏ	()Ljava/lang/String;
    //   957: invokevirtual 385	java/lang/String:equals	(Ljava/lang/Object;)Z
    //   960: ifne +6 -> 966
    //   963: goto -130 -> 833
    //   966: goto -908 -> 58
    // Local variable table:
    //   start	length	slot	name	signature
    //   0	969	0	this	Ik
    //   0	969	1	paramCv	Cv<T>
    //   0	969	2	paramBoolean	boolean
    //   0	969	3	paramFg	Fg
    //   47	888	4	i	int
    //   651	3	5	bool	boolean
    //   16	631	6	localObject	Object
    //   14	493	7	str1	String
    //   151	361	8	str2	String
    //   75	823	9	str3	String
    //   504	380	10	localContext	Context
    // Exception table:
    //   from	to	target	type
    //   633	639	497	java/lang/Exception
    //   639	646	497	java/lang/Exception
    //   646	653	497	java/lang/Exception
    //   833	841	497	java/lang/Exception
    //   841	850	497	java/lang/Exception
  }
  
  private boolean ˊ()
  {
    break label241;
    label16:
    if (ʽ() == null) {
      break label294;
    }
    label19:
    int i;
    for (;;)
    {
      switch (i)
      {
      case 0: 
      default: 
        return false;
      }
      for (;;)
      {
        return true;
        switch (i)
        {
        case 56: 
        default: 
          break label163;
          if ((this.mContextWeakReference.get() instanceof l)) {
            break label222;
          }
          break label190;
          do
          {
            break label244;
            i = ˏ + 115;
            ˊ = i % 128;
            if (i % 2 != 0) {
              break label160;
            }
            break;
            i = ˊ + 57;
            ˏ = i % 128;
          } while (i % 2 == 0);
          break label244;
          i = 0;
          break label266;
          break;
        case 79: 
          label79:
          label101:
          label160:
          label163:
          i = ˊ + 47;
          ˏ = i % 128;
          if (i % 2 == 0) {
            break label291;
          }
          break label16;
          label190:
          i = 0;
          break label19;
          i = ˏ + 63;
          ˊ = i % 128;
          if (i % 2 != 0) {
            break label239;
          }
        }
      }
      label222:
      i = 1;
    }
    for (;;)
    {
      i = 56;
      break;
      label239:
      label241:
      label244:
      do
      {
        i = 79;
        break;
        return true;
        break label101;
      } while (((l)this.mContextWeakReference.get()).ˋॱ());
    }
    for (;;)
    {
      label266:
      switch (i)
      {
      }
      break label79;
      label291:
      break;
      label294:
      i = 1;
    }
  }
  
  /* Error */
  private static String ˋ(int paramInt1, char paramChar, int paramInt2)
  {
    // Byte code:
    //   0: goto +8 -> 8
    //   3: astore 5
    //   5: aload 5
    //   7: athrow
    //   8: goto +86 -> 94
    //   11: astore 5
    //   13: aload 5
    //   15: athrow
    //   16: iconst_1
    //   17: istore 4
    //   19: goto +43 -> 62
    //   22: iload_2
    //   23: newarray char
    //   25: astore 5
    //   27: iconst_1
    //   28: istore_3
    //   29: goto +62 -> 91
    //   32: getstatic 43	o/Ik:ˏ	I
    //   35: bipush 9
    //   37: iadd
    //   38: istore 4
    //   40: iload 4
    //   42: sipush 128
    //   45: irem
    //   46: putstatic 41	o/Ik:ˊ	I
    //   49: iload 4
    //   51: iconst_2
    //   52: irem
    //   53: ifeq +6 -> 59
    //   56: goto +162 -> 218
    //   59: goto +120 -> 179
    //   62: iload 4
    //   64: tableswitch	default:+24->88, 0:+72->136, 1:+-32->32
    //   88: goto +48 -> 136
    //   91: goto +116 -> 207
    //   94: getstatic 43	o/Ik:ˏ	I
    //   97: istore_3
    //   98: iload_3
    //   99: bipush 125
    //   101: iadd
    //   102: istore_3
    //   103: iload_3
    //   104: sipush 128
    //   107: irem
    //   108: putstatic 41	o/Ik:ˊ	I
    //   111: iload_3
    //   112: iconst_2
    //   113: irem
    //   114: ifeq +6 -> 120
    //   117: goto +29 -> 146
    //   120: bipush 92
    //   122: istore_3
    //   123: goto +26 -> 149
    //   126: iload_2
    //   127: newarray char
    //   129: astore 5
    //   131: iconst_0
    //   132: istore_3
    //   133: goto -42 -> 91
    //   136: new 257	java/lang/String
    //   139: dup
    //   140: aload 5
    //   142: invokespecial 441	java/lang/String:<init>	([C)V
    //   145: areturn
    //   146: bipush 86
    //   148: istore_3
    //   149: iload_3
    //   150: lookupswitch	default:+26->176, 86:+-128->22, 92:+-24->126
    //   176: goto -154 -> 22
    //   179: aload 5
    //   181: iload_3
    //   182: getstatic 251	o/Ik:ॱ	[C
    //   185: iload_0
    //   186: iload_3
    //   187: iadd
    //   188: caload
    //   189: i2l
    //   190: iload_3
    //   191: i2l
    //   192: getstatic 68	o/Ik:ˎ	J
    //   195: lmul
    //   196: lxor
    //   197: iload_1
    //   198: i2l
    //   199: lxor
    //   200: l2i
    //   201: i2c
    //   202: castore
    //   203: iload_3
    //   204: iconst_1
    //   205: iadd
    //   206: istore_3
    //   207: iload_3
    //   208: iload_2
    //   209: if_icmpge +6 -> 215
    //   212: goto -196 -> 16
    //   215: goto +6 -> 221
    //   218: goto -39 -> 179
    //   221: iconst_0
    //   222: istore 4
    //   224: goto -162 -> 62
    // Local variable table:
    //   start	length	slot	name	signature
    //   0	227	0	paramInt1	int
    //   0	227	1	paramChar	char
    //   0	227	2	paramInt2	int
    //   28	182	3	i	int
    //   17	206	4	j	int
    //   3	3	5	localException1	Exception
    //   11	3	5	localException2	Exception
    //   25	155	5	arrayOfChar	char[]
    // Exception table:
    //   from	to	target	type
    //   94	98	3	java/lang/Exception
    //   103	111	11	java/lang/Exception
  }
  
  private String ˋ(String paramString)
  {
    break label43;
    break label189;
    int j = 78;
    break label127;
    int i;
    for (;;)
    {
      try
      {
        paramString = paramString.getBytes(ˋ(180, '\000', 10).intern());
        arrayOfByte = new byte[paramString.length];
        i = 0;
        continue;
        break;
        label43:
        continue;
        arrayOfByte[i] = ((byte)(paramString[(paramString.length - i - 1)] ^ ˋ));
        i += 1;
        break;
        continue;
        j = ˏ + 77;
        ˊ = j % 128;
        if (j % 2 != 0) {
          continue;
        }
      }
      catch (UnsupportedEncodingException paramString)
      {
        byte[] arrayOfByte;
        throw new RuntimeException(paramString);
      }
      j = ˏ + 95;
      ˊ = j % 128;
      if (j % 2 != 0) {}
    }
    for (;;)
    {
      label127:
      switch (j)
      {
      }
      paramString = new String(arrayOfByte, ˋ(190, '\000', 5).intern());
      return paramString;
      label189:
      j = paramString.length;
      if (i < j) {
        break;
      }
      j = 43;
    }
  }
  
  /* Error */
  private boolean ॱ(String paramString)
  {
    // Byte code:
    //   0: goto +206 -> 206
    //   3: getstatic 43	o/Ik:ˏ	I
    //   6: bipush 75
    //   8: iadd
    //   9: istore_2
    //   10: iload_2
    //   11: sipush 128
    //   14: irem
    //   15: putstatic 41	o/Ik:ˊ	I
    //   18: iload_2
    //   19: iconst_2
    //   20: irem
    //   21: ifeq +6 -> 27
    //   24: goto +176 -> 200
    //   27: goto +182 -> 209
    //   30: aload_1
    //   31: getstatic 460	o/EF:BTW_INACTIVE_WALLET	Lo/EF;
    //   34: invokevirtual 381	o/EF:ˏ	()Ljava/lang/String;
    //   37: invokevirtual 463	java/lang/String:equalsIgnoreCase	(Ljava/lang/String;)Z
    //   40: ifeq +6 -> 46
    //   43: goto +6 -> 49
    //   46: goto +157 -> 203
    //   49: goto +17 -> 66
    //   52: astore_1
    //   53: aload_1
    //   54: invokevirtual 293	java/lang/Throwable:getCause	()Ljava/lang/Throwable;
    //   57: astore_3
    //   58: aload_3
    //   59: ifnull +5 -> 64
    //   62: aload_3
    //   63: athrow
    //   64: aload_1
    //   65: athrow
    //   66: iconst_4
    //   67: sipush 413
    //   70: sipush 30253
    //   73: invokestatic 299	o/O:ˋ	(IIC)Ljava/lang/Object;
    //   76: checkcast 301	java/lang/Class
    //   79: ldc_w 465
    //   82: aconst_null
    //   83: invokevirtual 306	java/lang/Class:getMethod	(Ljava/lang/String;[Ljava/lang/Class;)Ljava/lang/reflect/Method;
    //   86: aconst_null
    //   87: aconst_null
    //   88: invokevirtual 312	java/lang/reflect/Method:invoke	(Ljava/lang/Object;[Ljava/lang/Object;)Ljava/lang/Object;
    //   91: astore_1
    //   92: getstatic 471	o/Gw:INACTIVE_PHONE_NUMBER	Lo/Gw;
    //   95: astore_3
    //   96: goto +17 -> 113
    //   99: astore_1
    //   100: aload_1
    //   101: invokevirtual 293	java/lang/Throwable:getCause	()Ljava/lang/Throwable;
    //   104: astore_3
    //   105: aload_3
    //   106: ifnull +5 -> 111
    //   109: aload_3
    //   110: athrow
    //   111: aload_1
    //   112: athrow
    //   113: iconst_4
    //   114: sipush 413
    //   117: sipush 30253
    //   120: invokestatic 299	o/O:ˋ	(IIC)Ljava/lang/Object;
    //   123: checkcast 301	java/lang/Class
    //   126: ldc_w 302
    //   129: iconst_1
    //   130: anewarray 301	java/lang/Class
    //   133: dup
    //   134: iconst_0
    //   135: ldc_w 467
    //   138: aastore
    //   139: invokevirtual 306	java/lang/Class:getMethod	(Ljava/lang/String;[Ljava/lang/Class;)Ljava/lang/reflect/Method;
    //   142: aload_1
    //   143: iconst_1
    //   144: anewarray 5	java/lang/Object
    //   147: dup
    //   148: iconst_0
    //   149: aload_3
    //   150: aastore
    //   151: invokevirtual 312	java/lang/reflect/Method:invoke	(Ljava/lang/Object;[Ljava/lang/Object;)Ljava/lang/Object;
    //   154: pop
    //   155: invokestatic 476	o/zp:ॱ	()Lo/zp;
    //   158: new 478	o/Ff
    //   161: dup
    //   162: invokespecial 479	o/Ff:<init>	()V
    //   165: invokevirtual 481	o/zp:ˎ	(Ljava/lang/Object;)V
    //   168: iconst_1
    //   169: ireturn
    //   170: getstatic 41	o/Ik:ˊ	I
    //   173: bipush 85
    //   175: iadd
    //   176: istore_2
    //   177: iload_2
    //   178: sipush 128
    //   181: irem
    //   182: putstatic 43	o/Ik:ˏ	I
    //   185: iload_2
    //   186: iconst_2
    //   187: irem
    //   188: ifne +6 -> 194
    //   191: goto +6 -> 197
    //   194: goto -164 -> 30
    //   197: goto -167 -> 30
    //   200: goto +9 -> 209
    //   203: goto -200 -> 3
    //   206: goto -36 -> 170
    //   209: iconst_0
    //   210: ireturn
    // Local variable table:
    //   start	length	slot	name	signature
    //   0	211	0	this	Ik
    //   0	211	1	paramString	String
    //   9	179	2	i	int
    //   57	93	3	localObject	Object
    // Exception table:
    //   from	to	target	type
    //   66	92	52	finally
    //   113	155	99	finally
  }
  
  /* Error */
  public boolean equals(Object paramObject)
  {
    // Byte code:
    //   0: goto +377 -> 377
    //   3: getstatic 43	o/Ik:ˏ	I
    //   6: bipush 11
    //   8: iadd
    //   9: istore_2
    //   10: iload_2
    //   11: sipush 128
    //   14: irem
    //   15: putstatic 41	o/Ik:ˊ	I
    //   18: iload_2
    //   19: iconst_2
    //   20: irem
    //   21: ifeq +6 -> 27
    //   24: goto +356 -> 380
    //   27: bipush 26
    //   29: istore_2
    //   30: goto +125 -> 155
    //   33: bipush 28
    //   35: istore_2
    //   36: goto +69 -> 105
    //   39: new 405	java/lang/NullPointerException
    //   42: dup
    //   43: invokespecial 406	java/lang/NullPointerException:<init>	()V
    //   46: athrow
    //   47: iconst_0
    //   48: ireturn
    //   49: iconst_1
    //   50: ireturn
    //   51: getstatic 43	o/Ik:ˏ	I
    //   54: bipush 11
    //   56: iadd
    //   57: istore_2
    //   58: iload_2
    //   59: sipush 128
    //   62: irem
    //   63: putstatic 41	o/Ik:ˊ	I
    //   66: iload_2
    //   67: iconst_2
    //   68: irem
    //   69: ifeq +6 -> 75
    //   72: goto -33 -> 39
    //   75: goto +66 -> 141
    //   78: getstatic 41	o/Ik:ˊ	I
    //   81: bipush 43
    //   83: iadd
    //   84: istore_2
    //   85: iload_2
    //   86: sipush 128
    //   89: irem
    //   90: putstatic 43	o/Ik:ˏ	I
    //   93: iload_2
    //   94: iconst_2
    //   95: irem
    //   96: ifne +6 -> 102
    //   99: goto +53 -> 152
    //   102: goto -55 -> 47
    //   105: iload_2
    //   106: lookupswitch	default:+26->132, 28:+216->322, 34:+207->313
    //   132: goto +181 -> 313
    //   135: astore_1
    //   136: aload_1
    //   137: athrow
    //   138: goto +144 -> 282
    //   141: aload_0
    //   142: aload_1
    //   143: if_acmpne +6 -> 149
    //   146: goto +226 -> 372
    //   149: goto +111 -> 260
    //   152: goto -105 -> 47
    //   155: iload_2
    //   156: lookupswitch	default:+28->184, 26:+128->284, 67:+31->187
    //   184: goto +100 -> 284
    //   187: aload_0
    //   188: invokevirtual 483	o/Ik:ˋ	()Ljava/lang/String;
    //   191: aload 4
    //   193: invokevirtual 483	o/Ik:ˋ	()Ljava/lang/String;
    //   196: invokevirtual 385	java/lang/String:equals	(Ljava/lang/Object;)Z
    //   199: istore_3
    //   200: bipush 81
    //   202: iconst_0
    //   203: idiv
    //   204: istore_2
    //   205: iload_3
    //   206: ifeq +6 -> 212
    //   209: goto +48 -> 257
    //   212: goto -74 -> 138
    //   215: aload_1
    //   216: ifnull +6 -> 222
    //   219: goto +6 -> 225
    //   222: goto +91 -> 313
    //   225: getstatic 41	o/Ik:ˊ	I
    //   228: istore_2
    //   229: iload_2
    //   230: bipush 123
    //   232: iadd
    //   233: istore_2
    //   234: iload_2
    //   235: sipush 128
    //   238: irem
    //   239: putstatic 43	o/Ik:ˏ	I
    //   242: iload_2
    //   243: iconst_2
    //   244: irem
    //   245: ifne +6 -> 251
    //   248: goto +121 -> 369
    //   251: goto +14 -> 265
    //   254: astore_1
    //   255: aload_1
    //   256: athrow
    //   257: goto +110 -> 367
    //   260: iconst_0
    //   261: istore_2
    //   262: goto +79 -> 341
    //   265: aload_0
    //   266: invokevirtual 487	java/lang/Object:getClass	()Ljava/lang/Class;
    //   269: aload_1
    //   270: invokevirtual 487	java/lang/Object:getClass	()Ljava/lang/Class;
    //   273: if_acmpeq +6 -> 279
    //   276: goto +40 -> 316
    //   279: goto -246 -> 33
    //   282: iconst_0
    //   283: ireturn
    //   284: aload_0
    //   285: invokevirtual 483	o/Ik:ˋ	()Ljava/lang/String;
    //   288: astore_1
    //   289: aload 4
    //   291: invokevirtual 483	o/Ik:ˋ	()Ljava/lang/String;
    //   294: astore 4
    //   296: aload_1
    //   297: aload 4
    //   299: invokevirtual 385	java/lang/String:equals	(Ljava/lang/Object;)Z
    //   302: istore_3
    //   303: iload_3
    //   304: ifeq +6 -> 310
    //   307: goto -50 -> 257
    //   310: goto -172 -> 138
    //   313: goto -235 -> 78
    //   316: bipush 34
    //   318: istore_2
    //   319: goto -214 -> 105
    //   322: aload_1
    //   323: checkcast 2	o/Ik
    //   326: astore 4
    //   328: aload_0
    //   329: getfield 489	o/Ik:mCall	Lo/Cv;
    //   332: ifnull +6 -> 338
    //   335: goto -332 -> 3
    //   338: goto -200 -> 138
    //   341: iload_2
    //   342: tableswitch	default:+22->364, 0:+-127->215, 1:+-293->49
    //   364: goto -149 -> 215
    //   367: iconst_1
    //   368: ireturn
    //   369: goto -104 -> 265
    //   372: iconst_1
    //   373: istore_2
    //   374: goto -33 -> 341
    //   377: goto -326 -> 51
    //   380: bipush 67
    //   382: istore_2
    //   383: goto -228 -> 155
    // Local variable table:
    //   start	length	slot	name	signature
    //   0	386	0	this	Ik
    //   0	386	1	paramObject	Object
    //   9	374	2	i	int
    //   199	105	3	bool	boolean
    //   191	136	4	localObject	Object
    // Exception table:
    //   from	to	target	type
    //   225	229	135	java/lang/Exception
    //   284	289	135	java/lang/Exception
    //   289	296	135	java/lang/Exception
    //   296	303	135	java/lang/Exception
    //   234	242	254	java/lang/Exception
  }
  
  /* Error */
  public int hashCode()
  {
    // Byte code:
    //   0: goto +17 -> 17
    //   3: goto +129 -> 132
    //   6: iconst_0
    //   7: istore_1
    //   8: goto +73 -> 81
    //   11: bipush 33
    //   13: istore_1
    //   14: goto +73 -> 87
    //   17: goto +102 -> 119
    //   20: getstatic 43	o/Ik:ˏ	I
    //   23: bipush 43
    //   25: iadd
    //   26: istore_1
    //   27: iload_1
    //   28: sipush 128
    //   31: irem
    //   32: putstatic 41	o/Ik:ˊ	I
    //   35: iload_1
    //   36: iconst_2
    //   37: irem
    //   38: ifeq +6 -> 44
    //   41: goto -38 -> 3
    //   44: goto +88 -> 132
    //   47: astore_3
    //   48: aload_3
    //   49: athrow
    //   50: getstatic 41	o/Ik:ˊ	I
    //   53: bipush 77
    //   55: iadd
    //   56: istore_2
    //   57: iload_2
    //   58: sipush 128
    //   61: irem
    //   62: putstatic 43	o/Ik:ˏ	I
    //   65: iload_2
    //   66: iconst_2
    //   67: irem
    //   68: ifne +5 -> 73
    //   71: iload_1
    //   72: ireturn
    //   73: iload_1
    //   74: ireturn
    //   75: bipush 13
    //   77: istore_1
    //   78: goto +9 -> 87
    //   81: goto -31 -> 50
    //   84: astore_3
    //   85: aload_3
    //   86: athrow
    //   87: iload_1
    //   88: lookupswitch	default:+28->116, 13:+-68->20, 33:+-82->6
    //   116: goto -110 -> 6
    //   119: aload_0
    //   120: getfield 489	o/Ik:mCall	Lo/Cv;
    //   123: ifnull +6 -> 129
    //   126: goto -51 -> 75
    //   129: goto -118 -> 11
    //   132: aload_0
    //   133: getfield 489	o/Ik:mCall	Lo/Cv;
    //   136: astore_3
    //   137: aload_3
    //   138: invokevirtual 493	java/lang/Object:hashCode	()I
    //   141: istore_1
    //   142: goto -61 -> 81
    // Local variable table:
    //   start	length	slot	name	signature
    //   0	145	0	this	Ik
    //   7	135	1	i	int
    //   56	12	2	j	int
    //   47	2	3	localException1	Exception
    //   84	2	3	localException2	Exception
    //   136	2	3	localCv	Cv
    // Exception table:
    //   from	to	target	type
    //   132	137	47	java/lang/Exception
    //   137	142	84	java/lang/Exception
  }
  
  public void ʼ()
  {
    int i;
    for (;;)
    {
      try
      {
        Cv localCv1 = this.mCall;
        if (localCv1 != null) {
          break label107;
        }
      }
      catch (Exception localException2)
      {
        throw localException2;
      }
      i = ˏ;
      i += 71;
      try
      {
        ˊ = i % 128;
        if (i % 2 != 0) {
          break label102;
        }
      }
      catch (Exception localException1)
      {
        throw localException1;
      }
      i = 25;
      label102:
      label107:
      label134:
      do
      {
        i = 4;
        switch (i)
        {
        default: 
          return;
          for (;;)
          {
            if (this.mResponse != null) {
              break label224;
            }
            break label200;
            i = 0;
            break;
            i = ˊ + 75;
            ˏ = i % 128;
            if (i % 2 == 0) {
              break label221;
            }
          }
          i = ˏ;
          i += 81;
          ˊ = i % 128;
        }
      } while (i % 2 != 0);
      continue;
      continue;
      label166:
      switch (i)
      {
      }
    }
    return;
    throw new NullPointerException();
    for (;;)
    {
      label200:
      break label134;
      Cv localCv2 = this.mCall;
      throw new NullPointerException();
      i = 1;
      break label166;
      label221:
      break;
      label224:
      ˋ(this.mCall, this.mResponse);
    }
  }
  
  /* Error */
  public Context ʽ()
  {
    // Byte code:
    //   0: goto +62 -> 62
    //   3: astore_2
    //   4: aload_2
    //   5: athrow
    //   6: iload_1
    //   7: lookupswitch	default:+25->32, 36:+163->170, 78:+152->159
    //   32: goto +127 -> 159
    //   35: getstatic 43	o/Ik:ˏ	I
    //   38: bipush 15
    //   40: iadd
    //   41: istore_1
    //   42: iload_1
    //   43: sipush 128
    //   46: irem
    //   47: putstatic 41	o/Ik:ˊ	I
    //   50: iload_1
    //   51: iconst_2
    //   52: irem
    //   53: ifeq +6 -> 59
    //   56: goto +9 -> 65
    //   59: goto +74 -> 133
    //   62: goto +77 -> 139
    //   65: bipush 36
    //   67: istore_1
    //   68: goto -62 -> 6
    //   71: getstatic 41	o/Ik:ˊ	I
    //   74: bipush 69
    //   76: iadd
    //   77: istore_1
    //   78: iload_1
    //   79: sipush 128
    //   82: irem
    //   83: putstatic 43	o/Ik:ˏ	I
    //   86: iload_1
    //   87: iconst_2
    //   88: irem
    //   89: ifne +6 -> 95
    //   92: goto +60 -> 152
    //   95: goto +93 -> 188
    //   98: goto -27 -> 71
    //   101: astore_2
    //   102: aload_2
    //   103: athrow
    //   104: iload_1
    //   105: tableswitch	default:+23->128, 0:+52->157, 1:+26->131
    //   128: goto +29 -> 157
    //   131: aconst_null
    //   132: areturn
    //   133: bipush 78
    //   135: istore_1
    //   136: goto -130 -> 6
    //   139: aload_0
    //   140: getfield 64	o/Ik:mContextWeakReference	Ljava/lang/ref/WeakReference;
    //   143: ifnull +6 -> 149
    //   146: goto -111 -> 35
    //   149: goto -51 -> 98
    //   152: iconst_1
    //   153: istore_1
    //   154: goto -50 -> 104
    //   157: aconst_null
    //   158: areturn
    //   159: aload_0
    //   160: getfield 64	o/Ik:mContextWeakReference	Ljava/lang/ref/WeakReference;
    //   163: invokevirtual 433	java/lang/ref/WeakReference:get	()Ljava/lang/Object;
    //   166: checkcast 353	android/content/Context
    //   169: areturn
    //   170: aload_0
    //   171: getfield 64	o/Ik:mContextWeakReference	Ljava/lang/ref/WeakReference;
    //   174: invokevirtual 433	java/lang/ref/WeakReference:get	()Ljava/lang/Object;
    //   177: checkcast 353	android/content/Context
    //   180: astore_2
    //   181: bipush 39
    //   183: iconst_0
    //   184: idiv
    //   185: istore_1
    //   186: aload_2
    //   187: areturn
    //   188: iconst_0
    //   189: istore_1
    //   190: goto -86 -> 104
    // Local variable table:
    //   start	length	slot	name	signature
    //   0	193	0	this	Ik
    //   6	184	1	i	int
    //   3	2	2	localException1	Exception
    //   101	2	2	localException2	Exception
    //   180	7	2	localContext	Context
    // Exception table:
    //   from	to	target	type
    //   35	42	3	java/lang/Exception
    //   42	50	3	java/lang/Exception
    //   42	50	101	java/lang/Exception
  }
  
  protected void ˊ(Fg paramFg)
  {
    for (;;)
    {
      int i = 4;
      switch (i)
      {
      default: 
        break;
      }
      label89:
      label93:
      do
      {
        try
        {
          ˎ(null, paramFg);
          for (;;)
          {
            i = ˏ + 53;
            ˊ = i % 128;
            if (i % 2 != 0) {
              break label89;
            }
            return;
            i = 82;
            break;
            break label93;
            ˎ(null, paramFg);
            i = 13 / 0;
          }
          return;
        }
        catch (Exception paramFg)
        {
          throw paramFg;
        }
        i = ˊ + 23;
        ˏ = i % 128;
      } while (i % 2 == 0);
    }
  }
  
  public String ˋ()
  {
    break label170;
    int i;
    String str1;
    switch (i)
    {
    default: 
      break;
    case 0: 
      return str1;
    }
    for (;;)
    {
      label33:
      if (this.mCall == null)
      {
        str1 = ˋ(151, '\000', 7).intern();
        break label72;
        label59:
        i = 0;
        break;
      }
      label72:
      label170:
      do
      {
        break label33;
        do
        {
          i = 1;
          break;
          i = ˊ + 7;
          ˏ = i % 128;
        } while (i % 2 == 0);
        break label59;
        str1 = this.mCall.ˎ().ˋ().ˋ().getPath();
        String str2 = this.mCall.ˎ().ˎ();
        return str2 + ˋ(25, 37564, 1).intern() + str1;
        i = null.length;
        return str1;
        i = ˏ + 29;
        ˊ = i % 128;
      } while (i % 2 != 0);
    }
  }
  
  /* Error */
  public void ˋ(Cv<T> paramCv, CG<T> paramCG)
  {
    // Byte code:
    //   0: goto +751 -> 751
    //   3: astore_1
    //   4: aload_1
    //   5: athrow
    //   6: iconst_0
    //   7: istore_3
    //   8: goto +386 -> 394
    //   11: aload_2
    //   12: invokevirtual 522	o/CG:ˎ	()Lo/xF;
    //   15: invokevirtual 526	o/xF:ʻ	()Ljava/lang/String;
    //   18: astore 5
    //   20: aload_0
    //   21: new 528	o/nD
    //   24: dup
    //   25: invokespecial 529	o/nD:<init>	()V
    //   28: invokevirtual 532	o/nD:ˎ	()Lo/nD;
    //   31: invokevirtual 535	o/nD:ˏ	()Lo/nw;
    //   34: aload 5
    //   36: ldc_w 363
    //   39: invokevirtual 540	o/nw:ˏ	(Ljava/lang/String;Ljava/lang/Class;)Ljava/lang/Object;
    //   42: checkcast 363	o/Fg
    //   45: putfield 542	o/Ik:mErrorResponse	Lo/Fg;
    //   48: aload_0
    //   49: getfield 542	o/Ik:mErrorResponse	Lo/Fg;
    //   52: astore 5
    //   54: aload 5
    //   56: ifnull +6 -> 62
    //   59: goto +735 -> 794
    //   62: goto +778 -> 840
    //   65: iconst_1
    //   66: istore_3
    //   67: goto +327 -> 394
    //   70: astore 5
    //   72: iconst_0
    //   73: sipush 10282
    //   76: bipush 7
    //   78: invokestatic 255	o/Ik:ˋ	(ICI)Ljava/lang/String;
    //   81: invokevirtual 261	java/lang/String:intern	()Ljava/lang/String;
    //   84: astore 6
    //   86: aload 5
    //   88: invokevirtual 545	java/lang/Exception:getMessage	()Ljava/lang/String;
    //   91: astore 7
    //   93: goto +17 -> 110
    //   96: astore_1
    //   97: aload_1
    //   98: invokevirtual 293	java/lang/Throwable:getCause	()Ljava/lang/Throwable;
    //   101: astore_2
    //   102: aload_2
    //   103: ifnull +5 -> 108
    //   106: aload_2
    //   107: athrow
    //   108: aload_1
    //   109: athrow
    //   110: iconst_4
    //   111: bipush 42
    //   113: ldc_w 294
    //   116: invokestatic 299	o/O:ˋ	(IIC)Ljava/lang/Object;
    //   119: checkcast 301	java/lang/Class
    //   122: ldc_w 546
    //   125: iconst_2
    //   126: anewarray 301	java/lang/Class
    //   129: dup
    //   130: iconst_0
    //   131: ldc_w 257
    //   134: aastore
    //   135: dup
    //   136: iconst_1
    //   137: ldc_w 257
    //   140: aastore
    //   141: invokevirtual 306	java/lang/Class:getMethod	(Ljava/lang/String;[Ljava/lang/Class;)Ljava/lang/reflect/Method;
    //   144: aconst_null
    //   145: iconst_2
    //   146: anewarray 5	java/lang/Object
    //   149: dup
    //   150: iconst_0
    //   151: aload 6
    //   153: aastore
    //   154: dup
    //   155: iconst_1
    //   156: aload 7
    //   158: aastore
    //   159: invokevirtual 312	java/lang/reflect/Method:invoke	(Ljava/lang/Object;[Ljava/lang/Object;)Ljava/lang/Object;
    //   162: pop
    //   163: aload_0
    //   164: aload_1
    //   165: new 363	o/Fg
    //   168: dup
    //   169: aload_2
    //   170: invokevirtual 548	o/CG:ˏ	()I
    //   173: aload 5
    //   175: invokevirtual 545	java/lang/Exception:getMessage	()Ljava/lang/String;
    //   178: ldc_w 550
    //   181: invokespecial 553	o/Fg:<init>	(ILjava/lang/String;Ljava/lang/String;)V
    //   184: invokevirtual 503	o/Ik:ˎ	(Lo/Cv;Lo/Fg;)V
    //   187: goto +662 -> 849
    //   190: iconst_0
    //   191: sipush 10282
    //   194: bipush 7
    //   196: invokestatic 255	o/Ik:ˋ	(ICI)Ljava/lang/String;
    //   199: astore 5
    //   201: aload 5
    //   203: invokevirtual 261	java/lang/String:intern	()Ljava/lang/String;
    //   206: astore 5
    //   208: new 263	java/lang/StringBuilder
    //   211: dup
    //   212: invokespecial 264	java/lang/StringBuilder:<init>	()V
    //   215: astore 6
    //   217: bipush 7
    //   219: iconst_0
    //   220: bipush 18
    //   222: invokestatic 255	o/Ik:ˋ	(ICI)Ljava/lang/String;
    //   225: astore 7
    //   227: aload 6
    //   229: aload 7
    //   231: invokevirtual 261	java/lang/String:intern	()Ljava/lang/String;
    //   234: invokevirtual 268	java/lang/StringBuilder:append	(Ljava/lang/String;)Ljava/lang/StringBuilder;
    //   237: aload_1
    //   238: invokeinterface 273 1 0
    //   243: invokevirtual 277	o/xG:ˎ	()Ljava/lang/String;
    //   246: invokevirtual 268	java/lang/StringBuilder:append	(Ljava/lang/String;)Ljava/lang/StringBuilder;
    //   249: bipush 25
    //   251: ldc_w 278
    //   254: iconst_1
    //   255: invokestatic 255	o/Ik:ˋ	(ICI)Ljava/lang/String;
    //   258: invokevirtual 261	java/lang/String:intern	()Ljava/lang/String;
    //   261: invokevirtual 268	java/lang/StringBuilder:append	(Ljava/lang/String;)Ljava/lang/StringBuilder;
    //   264: aload_1
    //   265: invokeinterface 273 1 0
    //   270: invokevirtual 281	o/xG:ˋ	()Lo/xy;
    //   273: invokevirtual 284	java/lang/StringBuilder:append	(Ljava/lang/Object;)Ljava/lang/StringBuilder;
    //   276: invokevirtual 287	java/lang/StringBuilder:toString	()Ljava/lang/String;
    //   279: astore 6
    //   281: goto +17 -> 298
    //   284: astore_1
    //   285: aload_1
    //   286: invokevirtual 293	java/lang/Throwable:getCause	()Ljava/lang/Throwable;
    //   289: astore_2
    //   290: aload_2
    //   291: ifnull +5 -> 296
    //   294: aload_2
    //   295: athrow
    //   296: aload_1
    //   297: athrow
    //   298: iconst_4
    //   299: bipush 42
    //   301: ldc_w 294
    //   304: invokestatic 299	o/O:ˋ	(IIC)Ljava/lang/Object;
    //   307: checkcast 301	java/lang/Class
    //   310: ldc_w 554
    //   313: iconst_2
    //   314: anewarray 301	java/lang/Class
    //   317: dup
    //   318: iconst_0
    //   319: ldc_w 257
    //   322: aastore
    //   323: dup
    //   324: iconst_1
    //   325: ldc_w 257
    //   328: aastore
    //   329: invokevirtual 306	java/lang/Class:getMethod	(Ljava/lang/String;[Ljava/lang/Class;)Ljava/lang/reflect/Method;
    //   332: aconst_null
    //   333: iconst_2
    //   334: anewarray 5	java/lang/Object
    //   337: dup
    //   338: iconst_0
    //   339: aload 5
    //   341: aastore
    //   342: dup
    //   343: iconst_1
    //   344: aload 6
    //   346: aastore
    //   347: invokevirtual 312	java/lang/reflect/Method:invoke	(Ljava/lang/Object;[Ljava/lang/Object;)Ljava/lang/Object;
    //   350: pop
    //   351: aload_0
    //   352: aload_1
    //   353: putfield 489	o/Ik:mCall	Lo/Cv;
    //   356: aload_0
    //   357: aload_2
    //   358: putfield 496	o/Ik:mResponse	Lo/CG;
    //   361: getstatic 559	o/GA:ॱ	Lo/GA$ˋ;
    //   364: invokevirtual 564	o/GA$ˋ:ˏ	()Lo/GA;
    //   367: aload_0
    //   368: invokevirtual 566	o/GA:ˏ	(Lo/Ik;)V
    //   371: aload_0
    //   372: getfield 568	o/Ik:mIsIgnoreContext	Z
    //   375: istore 4
    //   377: iload 4
    //   379: ifne +6 -> 385
    //   382: goto +472 -> 854
    //   385: goto +442 -> 827
    //   388: astore_1
    //   389: aload_1
    //   390: athrow
    //   391: goto +230 -> 621
    //   394: iload_3
    //   395: tableswitch	default:+21->416, 0:+359->754, 1:+-384->11
    //   416: goto -405 -> 11
    //   419: goto +430 -> 849
    //   422: iconst_0
    //   423: sipush 10282
    //   426: bipush 7
    //   428: invokestatic 255	o/Ik:ˋ	(ICI)Ljava/lang/String;
    //   431: invokevirtual 261	java/lang/String:intern	()Ljava/lang/String;
    //   434: astore_2
    //   435: new 263	java/lang/StringBuilder
    //   438: dup
    //   439: invokespecial 264	java/lang/StringBuilder:<init>	()V
    //   442: bipush 26
    //   444: sipush 3351
    //   447: bipush 8
    //   449: invokestatic 255	o/Ik:ˋ	(ICI)Ljava/lang/String;
    //   452: invokevirtual 261	java/lang/String:intern	()Ljava/lang/String;
    //   455: invokevirtual 268	java/lang/StringBuilder:append	(Ljava/lang/String;)Ljava/lang/StringBuilder;
    //   458: aload_1
    //   459: invokeinterface 273 1 0
    //   464: invokevirtual 277	o/xG:ˎ	()Ljava/lang/String;
    //   467: invokevirtual 268	java/lang/StringBuilder:append	(Ljava/lang/String;)Ljava/lang/StringBuilder;
    //   470: bipush 25
    //   472: ldc_w 278
    //   475: iconst_1
    //   476: invokestatic 255	o/Ik:ˋ	(ICI)Ljava/lang/String;
    //   479: invokevirtual 261	java/lang/String:intern	()Ljava/lang/String;
    //   482: invokevirtual 268	java/lang/StringBuilder:append	(Ljava/lang/String;)Ljava/lang/StringBuilder;
    //   485: aload_1
    //   486: invokeinterface 273 1 0
    //   491: invokevirtual 281	o/xG:ˋ	()Lo/xy;
    //   494: invokevirtual 284	java/lang/StringBuilder:append	(Ljava/lang/Object;)Ljava/lang/StringBuilder;
    //   497: bipush 34
    //   499: sipush 31102
    //   502: bipush 34
    //   504: invokestatic 255	o/Ik:ˋ	(ICI)Ljava/lang/String;
    //   507: invokevirtual 261	java/lang/String:intern	()Ljava/lang/String;
    //   510: invokevirtual 268	java/lang/StringBuilder:append	(Ljava/lang/String;)Ljava/lang/StringBuilder;
    //   513: bipush 68
    //   515: sipush 8864
    //   518: bipush 27
    //   520: invokestatic 255	o/Ik:ˋ	(ICI)Ljava/lang/String;
    //   523: invokevirtual 261	java/lang/String:intern	()Ljava/lang/String;
    //   526: invokevirtual 268	java/lang/StringBuilder:append	(Ljava/lang/String;)Ljava/lang/StringBuilder;
    //   529: aload_0
    //   530: getfield 568	o/Ik:mIsIgnoreContext	Z
    //   533: invokevirtual 571	java/lang/StringBuilder:append	(Z)Ljava/lang/StringBuilder;
    //   536: invokevirtual 287	java/lang/StringBuilder:toString	()Ljava/lang/String;
    //   539: astore_1
    //   540: goto +17 -> 557
    //   543: astore_1
    //   544: aload_1
    //   545: invokevirtual 293	java/lang/Throwable:getCause	()Ljava/lang/Throwable;
    //   548: astore_2
    //   549: aload_2
    //   550: ifnull +5 -> 555
    //   553: aload_2
    //   554: athrow
    //   555: aload_1
    //   556: athrow
    //   557: iconst_4
    //   558: bipush 42
    //   560: ldc_w 294
    //   563: invokestatic 299	o/O:ˋ	(IIC)Ljava/lang/Object;
    //   566: checkcast 301	java/lang/Class
    //   569: ldc_w 302
    //   572: iconst_2
    //   573: anewarray 301	java/lang/Class
    //   576: dup
    //   577: iconst_0
    //   578: ldc_w 257
    //   581: aastore
    //   582: dup
    //   583: iconst_1
    //   584: ldc_w 257
    //   587: aastore
    //   588: invokevirtual 306	java/lang/Class:getMethod	(Ljava/lang/String;[Ljava/lang/Class;)Ljava/lang/reflect/Method;
    //   591: aconst_null
    //   592: iconst_2
    //   593: anewarray 5	java/lang/Object
    //   596: dup
    //   597: iconst_0
    //   598: aload_2
    //   599: aastore
    //   600: dup
    //   601: iconst_1
    //   602: aload_1
    //   603: aastore
    //   604: invokevirtual 312	java/lang/reflect/Method:invoke	(Ljava/lang/Object;[Ljava/lang/Object;)Ljava/lang/Object;
    //   607: pop
    //   608: return
    //   609: aload_0
    //   610: aload_1
    //   611: aload_0
    //   612: getfield 542	o/Ik:mErrorResponse	Lo/Fg;
    //   615: invokevirtual 503	o/Ik:ˎ	(Lo/Cv;Lo/Fg;)V
    //   618: goto +231 -> 849
    //   621: aload_0
    //   622: aload_2
    //   623: invokevirtual 573	o/CG:ˋ	()Ljava/lang/Object;
    //   626: invokevirtual 575	o/Ik:ˏ	(Ljava/lang/Object;)V
    //   629: goto +17 -> 646
    //   632: astore_1
    //   633: aload_1
    //   634: invokevirtual 293	java/lang/Throwable:getCause	()Ljava/lang/Throwable;
    //   637: astore_2
    //   638: aload_2
    //   639: ifnull +5 -> 644
    //   642: aload_2
    //   643: athrow
    //   644: aload_1
    //   645: athrow
    //   646: iconst_4
    //   647: sipush 413
    //   650: sipush 30253
    //   653: invokestatic 299	o/O:ˋ	(IIC)Ljava/lang/Object;
    //   656: checkcast 301	java/lang/Class
    //   659: ldc_w 465
    //   662: aconst_null
    //   663: invokevirtual 306	java/lang/Class:getMethod	(Ljava/lang/String;[Ljava/lang/Class;)Ljava/lang/reflect/Method;
    //   666: aconst_null
    //   667: aconst_null
    //   668: invokevirtual 312	java/lang/reflect/Method:invoke	(Ljava/lang/Object;[Ljava/lang/Object;)Ljava/lang/Object;
    //   671: astore_1
    //   672: goto +17 -> 689
    //   675: astore_1
    //   676: aload_1
    //   677: invokevirtual 293	java/lang/Throwable:getCause	()Ljava/lang/Throwable;
    //   680: astore_2
    //   681: aload_2
    //   682: ifnull +5 -> 687
    //   685: aload_2
    //   686: athrow
    //   687: aload_1
    //   688: athrow
    //   689: iconst_4
    //   690: sipush 413
    //   693: sipush 30253
    //   696: invokestatic 299	o/O:ˋ	(IIC)Ljava/lang/Object;
    //   699: checkcast 301	java/lang/Class
    //   702: ldc_w 576
    //   705: iconst_1
    //   706: anewarray 301	java/lang/Class
    //   709: dup
    //   710: iconst_0
    //   711: getstatic 582	java/lang/Boolean:TYPE	Ljava/lang/Class;
    //   714: aastore
    //   715: invokevirtual 306	java/lang/Class:getMethod	(Ljava/lang/String;[Ljava/lang/Class;)Ljava/lang/reflect/Method;
    //   718: aload_1
    //   719: iconst_1
    //   720: anewarray 5	java/lang/Object
    //   723: dup
    //   724: iconst_0
    //   725: iconst_0
    //   726: invokestatic 586	java/lang/Boolean:valueOf	(Z)Ljava/lang/Boolean;
    //   729: aastore
    //   730: invokevirtual 312	java/lang/reflect/Method:invoke	(Ljava/lang/Object;[Ljava/lang/Object;)Ljava/lang/Object;
    //   733: pop
    //   734: goto -315 -> 419
    //   737: aload_0
    //   738: getfield 542	o/Ik:mErrorResponse	Lo/Fg;
    //   741: aload_2
    //   742: invokevirtual 548	o/CG:ˏ	()I
    //   745: putfield 589	o/Fg:httpStatusCode	I
    //   748: goto -139 -> 609
    //   751: goto -561 -> 190
    //   754: getstatic 41	o/Ik:ˊ	I
    //   757: bipush 59
    //   759: iadd
    //   760: istore_3
    //   761: iload_3
    //   762: sipush 128
    //   765: irem
    //   766: putstatic 43	o/Ik:ˏ	I
    //   769: iload_3
    //   770: iconst_2
    //   771: irem
    //   772: ifne +6 -> 778
    //   775: goto -384 -> 391
    //   778: goto -157 -> 621
    //   781: aload_0
    //   782: invokespecial 591	o/Ik:ˊ	()Z
    //   785: ifeq +6 -> 791
    //   788: goto +39 -> 827
    //   791: goto -369 -> 422
    //   794: bipush 99
    //   796: istore_3
    //   797: iload_3
    //   798: lookupswitch	default:+26->824, 53:+-189->609, 99:+-61->737
    //   824: goto -215 -> 609
    //   827: aload_2
    //   828: invokevirtual 592	o/CG:ˊ	()Z
    //   831: ifeq +6 -> 837
    //   834: goto -828 -> 6
    //   837: goto -772 -> 65
    //   840: bipush 53
    //   842: istore_3
    //   843: goto -46 -> 797
    //   846: goto -65 -> 781
    //   849: aload_0
    //   850: invokevirtual 594	o/Ik:ˏ	()V
    //   853: return
    //   854: getstatic 43	o/Ik:ˏ	I
    //   857: bipush 15
    //   859: iadd
    //   860: istore_3
    //   861: iload_3
    //   862: sipush 128
    //   865: irem
    //   866: putstatic 41	o/Ik:ˊ	I
    //   869: iload_3
    //   870: iconst_2
    //   871: irem
    //   872: ifeq +6 -> 878
    //   875: goto -29 -> 846
    //   878: goto -97 -> 781
    // Local variable table:
    //   start	length	slot	name	signature
    //   0	881	0	this	Ik
    //   0	881	1	paramCv	Cv<T>
    //   0	881	2	paramCG	CG<T>
    //   7	865	3	i	int
    //   375	3	4	bool	boolean
    //   18	37	5	localObject1	Object
    //   70	104	5	localIOException	java.io.IOException
    //   199	141	5	str1	String
    //   84	261	6	localObject2	Object
    //   91	139	7	str2	String
    // Exception table:
    //   from	to	target	type
    //   201	217	3	java/lang/Exception
    //   11	54	70	java/io/IOException
    //   11	54	70	o/nM
    //   609	618	70	java/io/IOException
    //   609	618	70	o/nM
    //   737	748	70	java/io/IOException
    //   737	748	70	o/nM
    //   110	163	96	finally
    //   298	351	284	finally
    //   190	201	388	java/lang/Exception
    //   201	217	388	java/lang/Exception
    //   217	227	388	java/lang/Exception
    //   227	281	388	java/lang/Exception
    //   285	290	388	java/lang/Exception
    //   294	296	388	java/lang/Exception
    //   296	298	388	java/lang/Exception
    //   351	377	388	java/lang/Exception
    //   557	608	543	finally
    //   646	672	632	finally
    //   689	734	675	finally
  }
  
  /* Error */
  public void ˎ(Cv<T> paramCv, Throwable paramThrowable)
  {
    // Byte code:
    //   0: goto +760 -> 760
    //   3: iconst_0
    //   4: sipush 10282
    //   7: bipush 7
    //   9: invokestatic 255	o/Ik:ˋ	(ICI)Ljava/lang/String;
    //   12: invokevirtual 261	java/lang/String:intern	()Ljava/lang/String;
    //   15: astore 5
    //   17: new 263	java/lang/StringBuilder
    //   20: dup
    //   21: invokespecial 264	java/lang/StringBuilder:<init>	()V
    //   24: bipush 26
    //   26: sipush 3351
    //   29: bipush 8
    //   31: invokestatic 255	o/Ik:ˋ	(ICI)Ljava/lang/String;
    //   34: invokevirtual 261	java/lang/String:intern	()Ljava/lang/String;
    //   37: invokevirtual 268	java/lang/StringBuilder:append	(Ljava/lang/String;)Ljava/lang/StringBuilder;
    //   40: aload_1
    //   41: invokeinterface 273 1 0
    //   46: invokevirtual 277	o/xG:ˎ	()Ljava/lang/String;
    //   49: invokevirtual 268	java/lang/StringBuilder:append	(Ljava/lang/String;)Ljava/lang/StringBuilder;
    //   52: bipush 25
    //   54: ldc_w 278
    //   57: iconst_1
    //   58: invokestatic 255	o/Ik:ˋ	(ICI)Ljava/lang/String;
    //   61: invokevirtual 261	java/lang/String:intern	()Ljava/lang/String;
    //   64: invokevirtual 268	java/lang/StringBuilder:append	(Ljava/lang/String;)Ljava/lang/StringBuilder;
    //   67: aload_1
    //   68: invokeinterface 273 1 0
    //   73: invokevirtual 281	o/xG:ˋ	()Lo/xy;
    //   76: invokevirtual 284	java/lang/StringBuilder:append	(Ljava/lang/Object;)Ljava/lang/StringBuilder;
    //   79: bipush 95
    //   81: iconst_0
    //   82: bipush 14
    //   84: invokestatic 255	o/Ik:ˋ	(ICI)Ljava/lang/String;
    //   87: invokevirtual 261	java/lang/String:intern	()Ljava/lang/String;
    //   90: invokevirtual 268	java/lang/StringBuilder:append	(Ljava/lang/String;)Ljava/lang/StringBuilder;
    //   93: invokevirtual 287	java/lang/StringBuilder:toString	()Ljava/lang/String;
    //   96: astore_2
    //   97: goto +17 -> 114
    //   100: astore_1
    //   101: aload_1
    //   102: invokevirtual 293	java/lang/Throwable:getCause	()Ljava/lang/Throwable;
    //   105: astore_2
    //   106: aload_2
    //   107: ifnull +5 -> 112
    //   110: aload_2
    //   111: athrow
    //   112: aload_1
    //   113: athrow
    //   114: iconst_4
    //   115: bipush 42
    //   117: ldc_w 294
    //   120: invokestatic 299	o/O:ˋ	(IIC)Ljava/lang/Object;
    //   123: checkcast 301	java/lang/Class
    //   126: ldc_w 302
    //   129: iconst_2
    //   130: anewarray 301	java/lang/Class
    //   133: dup
    //   134: iconst_0
    //   135: ldc_w 257
    //   138: aastore
    //   139: dup
    //   140: iconst_1
    //   141: ldc_w 257
    //   144: aastore
    //   145: invokevirtual 306	java/lang/Class:getMethod	(Ljava/lang/String;[Ljava/lang/Class;)Ljava/lang/reflect/Method;
    //   148: aconst_null
    //   149: iconst_2
    //   150: anewarray 5	java/lang/Object
    //   153: dup
    //   154: iconst_0
    //   155: aload 5
    //   157: aastore
    //   158: dup
    //   159: iconst_1
    //   160: aload_2
    //   161: aastore
    //   162: invokevirtual 312	java/lang/reflect/Method:invoke	(Ljava/lang/Object;[Ljava/lang/Object;)Ljava/lang/Object;
    //   165: pop
    //   166: iconst_0
    //   167: sipush 10282
    //   170: bipush 7
    //   172: invokestatic 255	o/Ik:ˋ	(ICI)Ljava/lang/String;
    //   175: invokevirtual 261	java/lang/String:intern	()Ljava/lang/String;
    //   178: astore 5
    //   180: new 263	java/lang/StringBuilder
    //   183: dup
    //   184: invokespecial 264	java/lang/StringBuilder:<init>	()V
    //   187: bipush 109
    //   189: sipush 16735
    //   192: bipush 12
    //   194: invokestatic 255	o/Ik:ˋ	(ICI)Ljava/lang/String;
    //   197: invokevirtual 261	java/lang/String:intern	()Ljava/lang/String;
    //   200: invokevirtual 268	java/lang/StringBuilder:append	(Ljava/lang/String;)Ljava/lang/StringBuilder;
    //   203: aload_0
    //   204: getfield 542	o/Ik:mErrorResponse	Lo/Fg;
    //   207: getfield 367	o/Fg:error	Lo/Fd;
    //   210: getfield 373	o/Fd:code	Ljava/lang/String;
    //   213: invokevirtual 268	java/lang/StringBuilder:append	(Ljava/lang/String;)Ljava/lang/StringBuilder;
    //   216: bipush 121
    //   218: sipush 8077
    //   221: bipush 20
    //   223: invokestatic 255	o/Ik:ˋ	(ICI)Ljava/lang/String;
    //   226: invokevirtual 261	java/lang/String:intern	()Ljava/lang/String;
    //   229: invokevirtual 268	java/lang/StringBuilder:append	(Ljava/lang/String;)Ljava/lang/StringBuilder;
    //   232: aload_0
    //   233: getfield 542	o/Ik:mErrorResponse	Lo/Fg;
    //   236: getfield 367	o/Fg:error	Lo/Fd;
    //   239: getfield 599	o/Fd:message	Ljava/lang/String;
    //   242: invokevirtual 268	java/lang/StringBuilder:append	(Ljava/lang/String;)Ljava/lang/StringBuilder;
    //   245: invokevirtual 287	java/lang/StringBuilder:toString	()Ljava/lang/String;
    //   248: astore_2
    //   249: goto +17 -> 266
    //   252: astore_1
    //   253: aload_1
    //   254: invokevirtual 293	java/lang/Throwable:getCause	()Ljava/lang/Throwable;
    //   257: astore_2
    //   258: aload_2
    //   259: ifnull +5 -> 264
    //   262: aload_2
    //   263: athrow
    //   264: aload_1
    //   265: athrow
    //   266: iconst_4
    //   267: bipush 42
    //   269: ldc_w 294
    //   272: invokestatic 299	o/O:ˋ	(IIC)Ljava/lang/Object;
    //   275: checkcast 301	java/lang/Class
    //   278: ldc_w 302
    //   281: iconst_2
    //   282: anewarray 301	java/lang/Class
    //   285: dup
    //   286: iconst_0
    //   287: ldc_w 257
    //   290: aastore
    //   291: dup
    //   292: iconst_1
    //   293: ldc_w 257
    //   296: aastore
    //   297: invokevirtual 306	java/lang/Class:getMethod	(Ljava/lang/String;[Ljava/lang/Class;)Ljava/lang/reflect/Method;
    //   300: aconst_null
    //   301: iconst_2
    //   302: anewarray 5	java/lang/Object
    //   305: dup
    //   306: iconst_0
    //   307: aload 5
    //   309: aastore
    //   310: dup
    //   311: iconst_1
    //   312: aload_2
    //   313: aastore
    //   314: invokevirtual 312	java/lang/reflect/Method:invoke	(Ljava/lang/Object;[Ljava/lang/Object;)Ljava/lang/Object;
    //   317: pop
    //   318: goto +73 -> 391
    //   321: iload_3
    //   322: lookupswitch	default:+26->348, 44:+29->351, 98:+354->676
    //   348: goto +328 -> 676
    //   351: aload_0
    //   352: invokespecial 591	o/Ik:ˊ	()Z
    //   355: ifeq +6 -> 361
    //   358: goto +448 -> 806
    //   361: goto +151 -> 512
    //   364: getstatic 43	o/Ik:ˏ	I
    //   367: bipush 37
    //   369: iadd
    //   370: istore_3
    //   371: iload_3
    //   372: sipush 128
    //   375: irem
    //   376: putstatic 41	o/Ik:ˊ	I
    //   379: iload_3
    //   380: iconst_2
    //   381: irem
    //   382: ifeq +6 -> 388
    //   385: goto +450 -> 835
    //   388: goto +168 -> 556
    //   391: goto +17 -> 408
    //   394: astore_1
    //   395: aload_1
    //   396: invokevirtual 293	java/lang/Throwable:getCause	()Ljava/lang/Throwable;
    //   399: astore_2
    //   400: aload_2
    //   401: ifnull +5 -> 406
    //   404: aload_2
    //   405: athrow
    //   406: aload_1
    //   407: athrow
    //   408: iconst_3
    //   409: bipush 24
    //   411: iconst_0
    //   412: invokestatic 299	o/O:ˋ	(IIC)Ljava/lang/Object;
    //   415: checkcast 301	java/lang/Class
    //   418: ldc_w 576
    //   421: aconst_null
    //   422: invokevirtual 306	java/lang/Class:getMethod	(Ljava/lang/String;[Ljava/lang/Class;)Ljava/lang/reflect/Method;
    //   425: aconst_null
    //   426: aconst_null
    //   427: invokevirtual 312	java/lang/reflect/Method:invoke	(Ljava/lang/Object;[Ljava/lang/Object;)Ljava/lang/Object;
    //   430: astore 5
    //   432: aload_0
    //   433: invokevirtual 346	o/Ik:ʽ	()Landroid/content/Context;
    //   436: astore_2
    //   437: goto +17 -> 454
    //   440: astore_2
    //   441: aload_2
    //   442: invokevirtual 293	java/lang/Throwable:getCause	()Ljava/lang/Throwable;
    //   445: astore_1
    //   446: aload_1
    //   447: ifnull +5 -> 452
    //   450: aload_1
    //   451: athrow
    //   452: aload_2
    //   453: athrow
    //   454: iconst_3
    //   455: bipush 24
    //   457: iconst_0
    //   458: invokestatic 299	o/O:ˋ	(IIC)Ljava/lang/Object;
    //   461: checkcast 301	java/lang/Class
    //   464: ldc_w 576
    //   467: iconst_1
    //   468: anewarray 301	java/lang/Class
    //   471: dup
    //   472: iconst_0
    //   473: ldc_w 353
    //   476: aastore
    //   477: invokevirtual 306	java/lang/Class:getMethod	(Ljava/lang/String;[Ljava/lang/Class;)Ljava/lang/reflect/Method;
    //   480: aload 5
    //   482: iconst_1
    //   483: anewarray 5	java/lang/Object
    //   486: dup
    //   487: iconst_0
    //   488: aload_2
    //   489: aastore
    //   490: invokevirtual 312	java/lang/reflect/Method:invoke	(Ljava/lang/Object;[Ljava/lang/Object;)Ljava/lang/Object;
    //   493: checkcast 578	java/lang/Boolean
    //   496: invokevirtual 602	java/lang/Boolean:booleanValue	()Z
    //   499: istore 4
    //   501: iload 4
    //   503: ifeq +6 -> 509
    //   506: goto +332 -> 838
    //   509: goto +41 -> 550
    //   512: iconst_1
    //   513: istore_3
    //   514: goto +294 -> 808
    //   517: aload_2
    //   518: invokevirtual 603	java/lang/Throwable:getMessage	()Ljava/lang/String;
    //   521: astore_2
    //   522: aload_0
    //   523: new 363	o/Fg
    //   526: dup
    //   527: sipush 500
    //   530: aload_2
    //   531: ldc_w 550
    //   534: invokespecial 553	o/Fg:<init>	(ILjava/lang/String;Ljava/lang/String;)V
    //   537: putfield 542	o/Ik:mErrorResponse	Lo/Fg;
    //   540: aload_1
    //   541: ifnull +6 -> 547
    //   544: goto -541 -> 3
    //   547: goto -156 -> 391
    //   550: bipush 44
    //   552: istore_3
    //   553: goto -232 -> 321
    //   556: goto +239 -> 795
    //   559: goto +17 -> 576
    //   562: astore_2
    //   563: aload_2
    //   564: invokevirtual 293	java/lang/Throwable:getCause	()Ljava/lang/Throwable;
    //   567: astore_1
    //   568: aload_1
    //   569: ifnull +5 -> 574
    //   572: aload_1
    //   573: athrow
    //   574: aload_2
    //   575: athrow
    //   576: iconst_3
    //   577: bipush 24
    //   579: iconst_0
    //   580: invokestatic 299	o/O:ˋ	(IIC)Ljava/lang/Object;
    //   583: checkcast 301	java/lang/Class
    //   586: ldc_w 576
    //   589: aconst_null
    //   590: invokevirtual 306	java/lang/Class:getMethod	(Ljava/lang/String;[Ljava/lang/Class;)Ljava/lang/reflect/Method;
    //   593: aconst_null
    //   594: aconst_null
    //   595: invokevirtual 312	java/lang/reflect/Method:invoke	(Ljava/lang/Object;[Ljava/lang/Object;)Ljava/lang/Object;
    //   598: astore_2
    //   599: aload_0
    //   600: invokevirtual 346	o/Ik:ʽ	()Landroid/content/Context;
    //   603: astore_1
    //   604: goto +17 -> 621
    //   607: astore_2
    //   608: aload_2
    //   609: invokevirtual 293	java/lang/Throwable:getCause	()Ljava/lang/Throwable;
    //   612: astore_1
    //   613: aload_1
    //   614: ifnull +5 -> 619
    //   617: aload_1
    //   618: athrow
    //   619: aload_2
    //   620: athrow
    //   621: iconst_3
    //   622: bipush 24
    //   624: iconst_0
    //   625: invokestatic 299	o/O:ˋ	(IIC)Ljava/lang/Object;
    //   628: checkcast 301	java/lang/Class
    //   631: ldc_w 546
    //   634: iconst_2
    //   635: anewarray 301	java/lang/Class
    //   638: dup
    //   639: iconst_0
    //   640: ldc_w 353
    //   643: aastore
    //   644: dup
    //   645: iconst_1
    //   646: getstatic 582	java/lang/Boolean:TYPE	Ljava/lang/Class;
    //   649: aastore
    //   650: invokevirtual 306	java/lang/Class:getMethod	(Ljava/lang/String;[Ljava/lang/Class;)Ljava/lang/reflect/Method;
    //   653: aload_2
    //   654: iconst_2
    //   655: anewarray 5	java/lang/Object
    //   658: dup
    //   659: iconst_0
    //   660: aload_1
    //   661: aastore
    //   662: dup
    //   663: iconst_1
    //   664: iconst_0
    //   665: invokestatic 586	java/lang/Boolean:valueOf	(Z)Ljava/lang/Boolean;
    //   668: aastore
    //   669: invokevirtual 312	java/lang/reflect/Method:invoke	(Ljava/lang/Object;[Ljava/lang/Object;)Ljava/lang/Object;
    //   672: pop
    //   673: goto -309 -> 364
    //   676: getstatic 41	o/Ik:ˊ	I
    //   679: bipush 57
    //   681: iadd
    //   682: istore_3
    //   683: iload_3
    //   684: sipush 128
    //   687: irem
    //   688: putstatic 43	o/Ik:ˏ	I
    //   691: iload_3
    //   692: iconst_2
    //   693: irem
    //   694: ifne +6 -> 700
    //   697: goto +29 -> 726
    //   700: aload_0
    //   701: getfield 57	o/Ik:mRetryCount	I
    //   704: ifle +6 -> 710
    //   707: goto +93 -> 800
    //   710: goto +156 -> 866
    //   713: aload_0
    //   714: invokespecial 591	o/Ik:ˊ	()Z
    //   717: ifeq +6 -> 723
    //   720: goto +127 -> 847
    //   723: goto +72 -> 795
    //   726: aload_0
    //   727: getfield 57	o/Ik:mRetryCount	I
    //   730: istore_3
    //   731: new 405	java/lang/NullPointerException
    //   734: dup
    //   735: invokespecial 406	java/lang/NullPointerException:<init>	()V
    //   738: athrow
    //   739: astore_1
    //   740: aload_1
    //   741: athrow
    //   742: aload_0
    //   743: getfield 57	o/Ik:mRetryCount	I
    //   746: istore_3
    //   747: aload_0
    //   748: iload_3
    //   749: iconst_1
    //   750: isub
    //   751: putfield 57	o/Ik:mRetryCount	I
    //   754: aload_0
    //   755: aload_1
    //   756: invokespecial 457	o/Ik:ˊ	(Lo/Cv;)V
    //   759: return
    //   760: goto -243 -> 517
    //   763: iload_3
    //   764: lookupswitch	default:+28->792, 8:+-22->742, 17:+-51->713
    //   792: goto -50 -> 742
    //   795: aload_0
    //   796: invokevirtual 594	o/Ik:ˏ	()V
    //   799: return
    //   800: bipush 8
    //   802: istore_3
    //   803: goto -40 -> 763
    //   806: iconst_0
    //   807: istore_3
    //   808: iload_3
    //   809: tableswitch	default:+23->832, 0:+-250->559, 1:+-14->795
    //   832: goto -273 -> 559
    //   835: goto -279 -> 556
    //   838: bipush 98
    //   840: istore_3
    //   841: goto -520 -> 321
    //   844: astore_1
    //   845: aload_1
    //   846: athrow
    //   847: new 605	o/IG
    //   850: dup
    //   851: aload_0
    //   852: invokevirtual 346	o/Ik:ʽ	()Landroid/content/Context;
    //   855: iconst_0
    //   856: invokespecial 608	o/IG:<init>	(Landroid/content/Context;Z)V
    //   859: invokevirtual 609	o/IG:ˏ	()Lo/ᐸ;
    //   862: pop
    //   863: goto -68 -> 795
    //   866: bipush 17
    //   868: istore_3
    //   869: goto -106 -> 763
    // Local variable table:
    //   start	length	slot	name	signature
    //   0	872	0	this	Ik
    //   0	872	1	paramCv	Cv<T>
    //   0	872	2	paramThrowable	Throwable
    //   321	548	3	i	int
    //   499	3	4	bool	boolean
    //   15	466	5	localObject	Object
    // Exception table:
    //   from	to	target	type
    //   114	166	100	finally
    //   266	318	252	finally
    //   408	432	394	finally
    //   454	501	440	finally
    //   576	599	562	finally
    //   621	673	607	finally
    //   726	739	739	java/lang/Exception
    //   517	522	844	java/lang/Exception
    //   522	540	844	java/lang/Exception
    //   742	747	844	java/lang/Exception
    //   747	759	844	java/lang/Exception
  }
  
  /* Error */
  protected void ˎ(Cv<T> paramCv, Fg paramFg)
  {
    // Byte code:
    //   0: goto +395 -> 395
    //   3: aload_2
    //   4: invokevirtual 613	o/Fg:ˎ	()Lo/Fd;
    //   7: astore 5
    //   9: aload 5
    //   11: invokevirtual 615	o/Fd:ॱ	()Ljava/lang/String;
    //   14: astore 5
    //   16: aload_0
    //   17: aload 5
    //   19: invokespecial 617	o/Ik:ॱ	(Ljava/lang/String;)Z
    //   22: ifeq +6 -> 28
    //   25: goto +87 -> 112
    //   28: goto +205 -> 233
    //   31: iload 4
    //   33: ifeq +6 -> 39
    //   36: goto +250 -> 286
    //   39: goto +385 -> 424
    //   42: getstatic 43	o/Ik:ˏ	I
    //   45: bipush 15
    //   47: iadd
    //   48: istore_3
    //   49: iload_3
    //   50: sipush 128
    //   53: irem
    //   54: putstatic 41	o/Ik:ˊ	I
    //   57: iload_3
    //   58: iconst_2
    //   59: irem
    //   60: ifeq +6 -> 66
    //   63: goto +209 -> 272
    //   66: goto -63 -> 3
    //   69: aload_2
    //   70: invokevirtual 613	o/Fg:ˎ	()Lo/Fd;
    //   73: ifnull +6 -> 79
    //   76: goto +249 -> 325
    //   79: goto +196 -> 275
    //   82: iload_3
    //   83: tableswitch	default:+21->104, 0:+169->252, 1:+-14->69
    //   104: goto -35 -> 69
    //   107: iconst_1
    //   108: istore_3
    //   109: goto -27 -> 82
    //   112: iconst_0
    //   113: sipush 10282
    //   116: bipush 7
    //   118: invokestatic 255	o/Ik:ˋ	(ICI)Ljava/lang/String;
    //   121: invokevirtual 261	java/lang/String:intern	()Ljava/lang/String;
    //   124: astore_1
    //   125: new 263	java/lang/StringBuilder
    //   128: dup
    //   129: invokespecial 264	java/lang/StringBuilder:<init>	()V
    //   132: sipush 158
    //   135: iconst_0
    //   136: bipush 18
    //   138: invokestatic 255	o/Ik:ˋ	(ICI)Ljava/lang/String;
    //   141: invokevirtual 261	java/lang/String:intern	()Ljava/lang/String;
    //   144: invokevirtual 268	java/lang/StringBuilder:append	(Ljava/lang/String;)Ljava/lang/StringBuilder;
    //   147: aload_2
    //   148: invokevirtual 613	o/Fg:ˎ	()Lo/Fd;
    //   151: invokevirtual 618	o/Fd:ˎ	()Ljava/lang/String;
    //   154: invokevirtual 268	java/lang/StringBuilder:append	(Ljava/lang/String;)Ljava/lang/StringBuilder;
    //   157: invokevirtual 287	java/lang/StringBuilder:toString	()Ljava/lang/String;
    //   160: astore_2
    //   161: goto +17 -> 178
    //   164: astore_1
    //   165: aload_1
    //   166: invokevirtual 293	java/lang/Throwable:getCause	()Ljava/lang/Throwable;
    //   169: astore_2
    //   170: aload_2
    //   171: ifnull +5 -> 176
    //   174: aload_2
    //   175: athrow
    //   176: aload_1
    //   177: athrow
    //   178: iconst_4
    //   179: bipush 42
    //   181: ldc_w 294
    //   184: invokestatic 299	o/O:ˋ	(IIC)Ljava/lang/Object;
    //   187: checkcast 301	java/lang/Class
    //   190: ldc_w 554
    //   193: iconst_2
    //   194: anewarray 301	java/lang/Class
    //   197: dup
    //   198: iconst_0
    //   199: ldc_w 257
    //   202: aastore
    //   203: dup
    //   204: iconst_1
    //   205: ldc_w 257
    //   208: aastore
    //   209: invokevirtual 306	java/lang/Class:getMethod	(Ljava/lang/String;[Ljava/lang/Class;)Ljava/lang/reflect/Method;
    //   212: aconst_null
    //   213: iconst_2
    //   214: anewarray 5	java/lang/Object
    //   217: dup
    //   218: iconst_0
    //   219: aload_1
    //   220: aastore
    //   221: dup
    //   222: iconst_1
    //   223: aload_2
    //   224: aastore
    //   225: invokevirtual 312	java/lang/reflect/Method:invoke	(Ljava/lang/Object;[Ljava/lang/Object;)Ljava/lang/Object;
    //   228: pop
    //   229: return
    //   230: astore_1
    //   231: aload_1
    //   232: athrow
    //   233: aload_0
    //   234: invokespecial 591	o/Ik:ˊ	()Z
    //   237: ifeq +6 -> 243
    //   240: goto -209 -> 31
    //   243: return
    //   244: iconst_0
    //   245: istore_3
    //   246: goto +250 -> 496
    //   249: goto +181 -> 430
    //   252: aload_2
    //   253: invokevirtual 613	o/Fg:ˎ	()Lo/Fd;
    //   256: astore 5
    //   258: aconst_null
    //   259: arraylength
    //   260: istore_3
    //   261: aload 5
    //   263: ifnull +6 -> 269
    //   266: goto -22 -> 244
    //   269: goto +12 -> 281
    //   272: goto -269 -> 3
    //   275: iconst_0
    //   276: istore 4
    //   278: goto -29 -> 249
    //   281: iconst_1
    //   282: istore_3
    //   283: goto +213 -> 496
    //   286: bipush 9
    //   288: istore_3
    //   289: goto +69 -> 358
    //   292: bipush 75
    //   294: istore_3
    //   295: goto +146 -> 441
    //   298: getstatic 41	o/Ik:ˊ	I
    //   301: bipush 79
    //   303: iadd
    //   304: istore_3
    //   305: iload_3
    //   306: sipush 128
    //   309: irem
    //   310: putstatic 43	o/Ik:ˏ	I
    //   313: iload_3
    //   314: iconst_2
    //   315: irem
    //   316: ifne +6 -> 322
    //   319: goto +68 -> 387
    //   322: goto +149 -> 471
    //   325: iconst_1
    //   326: istore 4
    //   328: goto +102 -> 430
    //   331: getstatic 43	o/Ik:ˏ	I
    //   334: bipush 103
    //   336: iadd
    //   337: istore_3
    //   338: iload_3
    //   339: sipush 128
    //   342: irem
    //   343: putstatic 41	o/Ik:ˊ	I
    //   346: iload_3
    //   347: iconst_2
    //   348: irem
    //   349: ifeq +6 -> 355
    //   352: goto +67 -> 419
    //   355: goto -248 -> 107
    //   358: iload_3
    //   359: lookupswitch	default:+25->384, 9:+39->398, 75:+122->481
    //   384: goto +14 -> 398
    //   387: new 405	java/lang/NullPointerException
    //   390: dup
    //   391: invokespecial 406	java/lang/NullPointerException:<init>	()V
    //   394: athrow
    //   395: goto -97 -> 298
    //   398: invokestatic 623	o/Il:ˋ	()Lo/Il;
    //   401: aload_0
    //   402: invokevirtual 346	o/Ik:ʽ	()Landroid/content/Context;
    //   405: aload_2
    //   406: invokevirtual 613	o/Fg:ˎ	()Lo/Fd;
    //   409: invokevirtual 626	o/Il:ˊ	(Landroid/content/Context;Lo/Fd;)Z
    //   412: ifeq +4 -> 416
    //   415: return
    //   416: goto +65 -> 481
    //   419: iconst_0
    //   420: istore_3
    //   421: goto -339 -> 82
    //   424: bipush 75
    //   426: istore_3
    //   427: goto -69 -> 358
    //   430: iload 4
    //   432: ifeq +6 -> 438
    //   435: goto -393 -> 42
    //   438: goto -205 -> 233
    //   441: iload_3
    //   442: lookupswitch	default:+26->468, 72:+-167->275, 75:+-111->331
    //   468: goto -193 -> 275
    //   471: aload_2
    //   472: ifnull +6 -> 478
    //   475: goto -183 -> 292
    //   478: goto +12 -> 490
    //   481: aload_0
    //   482: aload_1
    //   483: iload 4
    //   485: aload_2
    //   486: invokespecial 628	o/Ik:ˊ	(Lo/Cv;ZLo/Fg;)V
    //   489: return
    //   490: bipush 72
    //   492: istore_3
    //   493: goto -52 -> 441
    //   496: iload_3
    //   497: tableswitch	default:+23->520, 0:+-172->325, 1:+-222->275
    //   520: goto -245 -> 275
    //   523: astore_1
    //   524: aload_1
    //   525: athrow
    // Local variable table:
    //   start	length	slot	name	signature
    //   0	526	0	this	Ik
    //   0	526	1	paramCv	Cv<T>
    //   0	526	2	paramFg	Fg
    //   48	449	3	i	int
    //   31	453	4	bool	boolean
    //   7	255	5	localObject	Object
    // Exception table:
    //   from	to	target	type
    //   178	229	164	finally
    //   3	9	230	java/lang/Exception
    //   42	49	230	java/lang/Exception
    //   49	57	230	java/lang/Exception
    //   9	16	523	java/lang/Exception
  }
  
  /* Error */
  public void ˏ()
  {
    // Byte code:
    //   0: goto +97 -> 97
    //   3: bipush 53
    //   5: istore_1
    //   6: goto +26 -> 32
    //   9: getstatic 559	o/GA:ॱ	Lo/GA$ˋ;
    //   12: invokevirtual 564	o/GA$ˋ:ˏ	()Lo/GA;
    //   15: aload_0
    //   16: invokevirtual 631	o/GA:ˎ	(Lo/Ik;)V
    //   19: aload_0
    //   20: aconst_null
    //   21: putfield 489	o/Ik:mCall	Lo/Cv;
    //   24: aload_0
    //   25: aconst_null
    //   26: putfield 496	o/Ik:mResponse	Lo/CG;
    //   29: goto +41 -> 70
    //   32: iload_1
    //   33: lookupswitch	default:+27->60, 2:+28->61, 53:+102->135
    //   60: return
    //   61: bipush 78
    //   63: iconst_0
    //   64: idiv
    //   65: istore_1
    //   66: return
    //   67: astore_2
    //   68: aload_2
    //   69: athrow
    //   70: getstatic 41	o/Ik:ˊ	I
    //   73: bipush 15
    //   75: iadd
    //   76: istore_1
    //   77: iload_1
    //   78: sipush 128
    //   81: irem
    //   82: putstatic 43	o/Ik:ˏ	I
    //   85: iload_1
    //   86: iconst_2
    //   87: irem
    //   88: ifne +6 -> 94
    //   91: goto +9 -> 100
    //   94: goto -91 -> 3
    //   97: goto +8 -> 105
    //   100: iconst_2
    //   101: istore_1
    //   102: goto -70 -> 32
    //   105: getstatic 43	o/Ik:ˏ	I
    //   108: bipush 59
    //   110: iadd
    //   111: istore_1
    //   112: iload_1
    //   113: sipush 128
    //   116: irem
    //   117: putstatic 41	o/Ik:ˊ	I
    //   120: iload_1
    //   121: iconst_2
    //   122: irem
    //   123: ifeq +6 -> 129
    //   126: goto -117 -> 9
    //   129: goto -120 -> 9
    //   132: astore_2
    //   133: aload_2
    //   134: athrow
    //   135: return
    // Local variable table:
    //   start	length	slot	name	signature
    //   0	136	0	this	Ik
    //   5	118	1	i	int
    //   67	2	2	localException1	Exception
    //   132	2	2	localException2	Exception
    // Exception table:
    //   from	to	target	type
    //   105	112	67	java/lang/Exception
    //   112	120	67	java/lang/Exception
    //   112	120	132	java/lang/Exception
  }
  
  protected abstract void ˏ(T paramT);
  
  protected void ॱ()
  {
    for (;;)
    {
      int i = ˏ + 33;
      ˊ = i % 128;
      if (i % 2 == 0) {
        return;
      } else {
        return;
      }
    }
  }
  
  /* Error */
  protected Fg ॱॱ()
  {
    // Byte code:
    //   0: goto +21 -> 21
    //   3: aload_0
    //   4: getfield 542	o/Ik:mErrorResponse	Lo/Fg;
    //   7: astore_2
    //   8: goto +42 -> 50
    //   11: astore_2
    //   12: aload_2
    //   13: athrow
    //   14: aload_2
    //   15: areturn
    //   16: iconst_0
    //   17: istore_1
    //   18: goto +61 -> 79
    //   21: getstatic 41	o/Ik:ˊ	I
    //   24: istore_1
    //   25: iload_1
    //   26: bipush 57
    //   28: iadd
    //   29: istore_1
    //   30: iload_1
    //   31: sipush 128
    //   34: irem
    //   35: putstatic 43	o/Ik:ˏ	I
    //   38: iload_1
    //   39: iconst_2
    //   40: irem
    //   41: ifne +6 -> 47
    //   44: goto +63 -> 107
    //   47: goto -44 -> 3
    //   50: getstatic 41	o/Ik:ˊ	I
    //   53: bipush 11
    //   55: iadd
    //   56: istore_1
    //   57: iload_1
    //   58: sipush 128
    //   61: irem
    //   62: putstatic 43	o/Ik:ˏ	I
    //   65: iload_1
    //   66: iconst_2
    //   67: irem
    //   68: ifne +6 -> 74
    //   71: goto +6 -> 77
    //   74: goto -58 -> 16
    //   77: iconst_1
    //   78: istore_1
    //   79: iload_1
    //   80: tableswitch	default:+24->104, 0:+-66->14, 1:+30->110
    //   104: goto +6 -> 110
    //   107: goto -104 -> 3
    //   110: bipush 40
    //   112: iconst_0
    //   113: idiv
    //   114: istore_1
    //   115: aload_2
    //   116: areturn
    //   117: astore_2
    //   118: aload_2
    //   119: athrow
    // Local variable table:
    //   start	length	slot	name	signature
    //   0	120	0	this	Ik
    //   17	98	1	i	int
    //   7	1	2	localFg	Fg
    //   11	105	2	localException1	Exception
    //   117	2	2	localException2	Exception
    // Exception table:
    //   from	to	target	type
    //   21	25	11	java/lang/Exception
    //   3	8	117	java/lang/Exception
    //   30	38	117	java/lang/Exception
  }
  
  /* Error */
  public Ik<T> ᐝ()
  {
    // Byte code:
    //   0: goto +115 -> 115
    //   3: astore_2
    //   4: aload_2
    //   5: athrow
    //   6: aload_0
    //   7: astore_2
    //   8: getstatic 41	o/Ik:ˊ	I
    //   11: bipush 89
    //   13: iadd
    //   14: istore_1
    //   15: iload_1
    //   16: sipush 128
    //   19: irem
    //   20: putstatic 43	o/Ik:ˏ	I
    //   23: iload_1
    //   24: iconst_2
    //   25: irem
    //   26: ifne +5 -> 31
    //   29: aload_2
    //   30: areturn
    //   31: aload_2
    //   32: areturn
    //   33: aload_0
    //   34: iconst_0
    //   35: putfield 568	o/Ik:mIsIgnoreContext	Z
    //   38: goto -32 -> 6
    //   41: iload_1
    //   42: lookupswitch	default:+26->68, 42:+29->71, 91:+-9->33
    //   68: goto -35 -> 33
    //   71: aload_0
    //   72: iconst_1
    //   73: putfield 568	o/Ik:mIsIgnoreContext	Z
    //   76: goto -70 -> 6
    //   79: bipush 42
    //   81: istore_1
    //   82: goto -41 -> 41
    //   85: getstatic 43	o/Ik:ˏ	I
    //   88: bipush 51
    //   90: iadd
    //   91: istore_1
    //   92: iload_1
    //   93: sipush 128
    //   96: irem
    //   97: putstatic 41	o/Ik:ˊ	I
    //   100: iload_1
    //   101: iconst_2
    //   102: irem
    //   103: ifeq +6 -> 109
    //   106: goto +12 -> 118
    //   109: goto -30 -> 79
    //   112: astore_2
    //   113: aload_2
    //   114: athrow
    //   115: goto -30 -> 85
    //   118: bipush 91
    //   120: istore_1
    //   121: goto -80 -> 41
    // Local variable table:
    //   start	length	slot	name	signature
    //   0	124	0	this	Ik
    //   14	107	1	i	int
    //   3	2	2	localException1	Exception
    //   7	25	2	localIk	Ik
    //   112	2	2	localException2	Exception
    // Exception table:
    //   from	to	target	type
    //   8	15	3	java/lang/Exception
    //   15	23	3	java/lang/Exception
    //   33	38	112	java/lang/Exception
  }
}
