package o;

public class IN
  extends IQ
  implements ᐸ.ˏ
{
  private static char ॱˉ;
  private static char ॱˌ;
  private static byte ॱˍ;
  private static char ॱˑ;
  private static char ॱـ;
  private static int ॱᶥ;
  private static int ॱꓸ;
  private int ߺ;
  
  /* Error */
  static
  {
    // Byte code:
    //   0: goto +31 -> 31
    //   3: getstatic 25	o/IN:ॱꓸ	I
    //   6: bipush 21
    //   8: iadd
    //   9: istore_0
    //   10: iload_0
    //   11: sipush 128
    //   14: irem
    //   15: putstatic 27	o/IN:ॱᶥ	I
    //   18: iload_0
    //   19: iconst_2
    //   20: irem
    //   21: ifeq +6 -> 27
    //   24: goto +29 -> 53
    //   27: return
    //   28: astore_1
    //   29: aload_1
    //   30: athrow
    //   31: iconst_0
    //   32: putstatic 27	o/IN:ॱᶥ	I
    //   35: iconst_1
    //   36: putstatic 25	o/IN:ॱꓸ	I
    //   39: invokestatic 30	o/IN:ᐝ	()V
    //   42: bipush -102
    //   44: putstatic 32	o/IN:ॱˍ	B
    //   47: goto -44 -> 3
    //   50: astore_1
    //   51: aload_1
    //   52: athrow
    //   53: return
    // Local variable table:
    //   start	length	slot	name	signature
    //   9	12	0	i	int
    //   28	2	1	localException1	Exception
    //   50	2	1	localException2	Exception
    // Exception table:
    //   from	to	target	type
    //   31	35	28	java/lang/Exception
    //   35	39	28	java/lang/Exception
    //   39	42	28	java/lang/Exception
    //   42	47	28	java/lang/Exception
    //   42	47	50	java/lang/Exception
  }
  
  /* Error */
  public IN(android.content.Context paramContext, int paramInt)
  {
    // Byte code:
    //   0: goto +230 -> 230
    //   3: aload_0
    //   4: aload 6
    //   6: iconst_4
    //   7: invokevirtual 41	java/lang/String:substring	(I)Ljava/lang/String;
    //   10: invokespecial 45	o/IN:ˊ	(Ljava/lang/String;)Ljava/lang/String;
    //   13: invokevirtual 49	java/lang/String:intern	()Ljava/lang/String;
    //   16: astore 6
    //   18: goto +412 -> 430
    //   21: aload_0
    //   22: aload_1
    //   23: invokevirtual 53	o/IN:ॱ	(Ljava/lang/CharSequence;)Lo/ᐸ$If;
    //   26: pop
    //   27: aload_0
    //   28: iconst_1
    //   29: invokevirtual 57	o/IN:ˋ	(Z)Lo/ᐸ$If;
    //   32: pop
    //   33: aload_0
    //   34: aload_0
    //   35: invokevirtual 60	o/IN:ॱ	(Lo/ᐸ$ˏ;)Lo/ᐸ$If;
    //   38: pop
    //   39: aload_0
    //   40: aload_0
    //   41: invokevirtual 62	o/IN:ˊ	(Lo/ᐸ$ˏ;)Lo/ᐸ$If;
    //   44: pop
    //   45: aload_0
    //   46: iload_2
    //   47: putfield 64	o/IN:ߺ	I
    //   50: goto +347 -> 397
    //   53: new 66	java/lang/NullPointerException
    //   56: dup
    //   57: invokespecial 68	java/lang/NullPointerException:<init>	()V
    //   60: athrow
    //   61: astore_1
    //   62: aload_1
    //   63: athrow
    //   64: astore_1
    //   65: aload_1
    //   66: athrow
    //   67: iload_2
    //   68: tableswitch	default:+24->92, 0:+358->426, 1:+-15->53
    //   92: return
    //   93: iconst_0
    //   94: istore_3
    //   95: goto +82 -> 177
    //   98: aload_0
    //   99: aload 6
    //   101: iconst_4
    //   102: invokevirtual 41	java/lang/String:substring	(I)Ljava/lang/String;
    //   105: invokespecial 45	o/IN:ˊ	(Ljava/lang/String;)Ljava/lang/String;
    //   108: invokevirtual 49	java/lang/String:intern	()Ljava/lang/String;
    //   111: astore_1
    //   112: goto +38 -> 150
    //   115: iload_3
    //   116: lookupswitch	default:+28->144, 12:+106->222, 67:+31->147
    //   144: goto +78 -> 222
    //   147: goto +180 -> 327
    //   150: getstatic 27	o/IN:ॱᶥ	I
    //   153: bipush 77
    //   155: iadd
    //   156: istore_3
    //   157: iload_3
    //   158: sipush 128
    //   161: irem
    //   162: putstatic 25	o/IN:ॱꓸ	I
    //   165: iload_3
    //   166: iconst_2
    //   167: irem
    //   168: ifne +6 -> 174
    //   171: goto +256 -> 427
    //   174: goto +145 -> 319
    //   177: aload 6
    //   179: astore_1
    //   180: iload_3
    //   181: tableswitch	default:+23->204, 0:+-160->21, 1:+-83->98
    //   204: aload 6
    //   206: astore_1
    //   207: goto -186 -> 21
    //   210: bipush 67
    //   212: istore_3
    //   213: goto -98 -> 115
    //   216: bipush 12
    //   218: istore_3
    //   219: goto -104 -> 115
    //   222: goto +105 -> 327
    //   225: iconst_1
    //   226: istore_2
    //   227: goto -160 -> 67
    //   230: getstatic 73	o/Gu$If:img_security_enroll	I
    //   233: istore_3
    //   234: getstatic 78	o/Gu$ˏ:security_setup_title	I
    //   237: istore 4
    //   239: aload_0
    //   240: aload_1
    //   241: iload_3
    //   242: iload 4
    //   244: getstatic 81	o/Gu$ˏ:security_setup_message	I
    //   247: invokespecial 84	o/IQ:<init>	(Landroid/content/Context;III)V
    //   250: getstatic 87	o/Gu$ˏ:continue_label	I
    //   253: istore_3
    //   254: aload_1
    //   255: iload_3
    //   256: invokevirtual 92	android/content/Context:getString	(I)Ljava/lang/String;
    //   259: astore 6
    //   261: aload 6
    //   263: bipush 6
    //   265: newarray char
    //   267: dup
    //   268: iconst_0
    //   269: ldc 93
    //   271: castore
    //   272: dup
    //   273: iconst_1
    //   274: ldc 94
    //   276: castore
    //   277: dup
    //   278: iconst_2
    //   279: ldc 95
    //   281: castore
    //   282: dup
    //   283: iconst_3
    //   284: ldc 96
    //   286: castore
    //   287: dup
    //   288: iconst_4
    //   289: ldc 97
    //   291: castore
    //   292: dup
    //   293: iconst_5
    //   294: ldc 98
    //   296: castore
    //   297: invokestatic 101	o/IN:ˊ	([C)Ljava/lang/String;
    //   300: invokevirtual 49	java/lang/String:intern	()Ljava/lang/String;
    //   303: invokevirtual 105	java/lang/String:startsWith	(Ljava/lang/String;)Z
    //   306: istore 5
    //   308: iload 5
    //   310: ifeq +6 -> 316
    //   313: goto -310 -> 3
    //   316: goto +11 -> 327
    //   319: goto -298 -> 21
    //   322: iconst_1
    //   323: istore_3
    //   324: goto -147 -> 177
    //   327: aload_0
    //   328: aload 6
    //   330: invokevirtual 108	o/IN:ˎ	(Ljava/lang/CharSequence;)Lo/ᐸ$If;
    //   333: pop
    //   334: aload_1
    //   335: getstatic 111	o/Gu$ˏ:cancel	I
    //   338: invokevirtual 92	android/content/Context:getString	(I)Ljava/lang/String;
    //   341: astore 6
    //   343: aload 6
    //   345: bipush 6
    //   347: newarray char
    //   349: dup
    //   350: iconst_0
    //   351: ldc 93
    //   353: castore
    //   354: dup
    //   355: iconst_1
    //   356: ldc 94
    //   358: castore
    //   359: dup
    //   360: iconst_2
    //   361: ldc 95
    //   363: castore
    //   364: dup
    //   365: iconst_3
    //   366: ldc 96
    //   368: castore
    //   369: dup
    //   370: iconst_4
    //   371: ldc 97
    //   373: castore
    //   374: dup
    //   375: iconst_5
    //   376: ldc 98
    //   378: castore
    //   379: invokestatic 101	o/IN:ˊ	([C)Ljava/lang/String;
    //   382: invokevirtual 49	java/lang/String:intern	()Ljava/lang/String;
    //   385: invokevirtual 105	java/lang/String:startsWith	(Ljava/lang/String;)Z
    //   388: ifeq +6 -> 394
    //   391: goto -69 -> 322
    //   394: goto -301 -> 93
    //   397: getstatic 25	o/IN:ॱꓸ	I
    //   400: bipush 35
    //   402: iadd
    //   403: istore_2
    //   404: iload_2
    //   405: sipush 128
    //   408: irem
    //   409: putstatic 27	o/IN:ॱᶥ	I
    //   412: iload_2
    //   413: iconst_2
    //   414: irem
    //   415: ifeq +6 -> 421
    //   418: goto -193 -> 225
    //   421: iconst_0
    //   422: istore_2
    //   423: goto -356 -> 67
    //   426: return
    //   427: goto -108 -> 319
    //   430: getstatic 27	o/IN:ॱᶥ	I
    //   433: bipush 47
    //   435: iadd
    //   436: istore_3
    //   437: iload_3
    //   438: sipush 128
    //   441: irem
    //   442: putstatic 25	o/IN:ॱꓸ	I
    //   445: iload_3
    //   446: iconst_2
    //   447: irem
    //   448: ifne +6 -> 454
    //   451: goto -241 -> 210
    //   454: goto -238 -> 216
    // Local variable table:
    //   start	length	slot	name	signature
    //   0	457	0	this	IN
    //   0	457	1	paramContext	android.content.Context
    //   0	457	2	paramInt	int
    //   94	354	3	i	int
    //   237	6	4	j	int
    //   306	3	5	bool	boolean
    //   4	340	6	str	String
    // Exception table:
    //   from	to	target	type
    //   250	254	61	java/lang/Exception
    //   230	234	64	java/lang/Exception
    //   234	239	64	java/lang/Exception
    //   239	250	64	java/lang/Exception
    //   250	254	64	java/lang/Exception
    //   254	261	64	java/lang/Exception
    //   261	308	64	java/lang/Exception
  }
  
  /* Error */
  private String ˊ(String paramString)
  {
    // Byte code:
    //   0: goto +175 -> 175
    //   3: getstatic 25	o/IN:ॱꓸ	I
    //   6: bipush 77
    //   8: iadd
    //   9: istore_3
    //   10: iload_3
    //   11: sipush 128
    //   14: irem
    //   15: putstatic 27	o/IN:ॱᶥ	I
    //   18: iload_3
    //   19: iconst_2
    //   20: irem
    //   21: ifeq +6 -> 27
    //   24: goto +45 -> 69
    //   27: goto +72 -> 99
    //   30: astore_1
    //   31: new 115	java/lang/RuntimeException
    //   34: dup
    //   35: aload_1
    //   36: invokespecial 118	java/lang/RuntimeException:<init>	(Ljava/lang/Throwable;)V
    //   39: athrow
    //   40: getstatic 27	o/IN:ॱᶥ	I
    //   43: istore_2
    //   44: iload_2
    //   45: bipush 67
    //   47: iadd
    //   48: istore_2
    //   49: iload_2
    //   50: sipush 128
    //   53: irem
    //   54: putstatic 25	o/IN:ॱꓸ	I
    //   57: iload_2
    //   58: iconst_2
    //   59: irem
    //   60: ifne +6 -> 66
    //   63: goto +115 -> 178
    //   66: goto +129 -> 195
    //   69: goto +30 -> 99
    //   72: iload_3
    //   73: tableswitch	default:+23->96, 0:+-70->3, 1:+50->123
    //   96: goto +27 -> 123
    //   99: aload 4
    //   101: iload_2
    //   102: aload_1
    //   103: aload_1
    //   104: arraylength
    //   105: iload_2
    //   106: isub
    //   107: iconst_1
    //   108: isub
    //   109: baload
    //   110: getstatic 32	o/IN:ॱˍ	B
    //   113: ixor
    //   114: i2b
    //   115: bastore
    //   116: iload_2
    //   117: iconst_1
    //   118: iadd
    //   119: istore_2
    //   120: goto +61 -> 181
    //   123: new 37	java/lang/String
    //   126: dup
    //   127: aload 4
    //   129: bipush 6
    //   131: newarray char
    //   133: dup
    //   134: iconst_0
    //   135: ldc 119
    //   137: castore
    //   138: dup
    //   139: iconst_1
    //   140: ldc 120
    //   142: castore
    //   143: dup
    //   144: iconst_2
    //   145: ldc 121
    //   147: castore
    //   148: dup
    //   149: iconst_3
    //   150: ldc 122
    //   152: castore
    //   153: dup
    //   154: iconst_4
    //   155: ldc 123
    //   157: castore
    //   158: dup
    //   159: iconst_5
    //   160: ldc 124
    //   162: castore
    //   163: invokestatic 101	o/IN:ˊ	([C)Ljava/lang/String;
    //   166: invokevirtual 49	java/lang/String:intern	()Ljava/lang/String;
    //   169: invokespecial 127	java/lang/String:<init>	([BLjava/lang/String;)V
    //   172: astore_1
    //   173: aload_1
    //   174: areturn
    //   175: goto -135 -> 40
    //   178: goto +17 -> 195
    //   181: aload_1
    //   182: arraylength
    //   183: istore_3
    //   184: iload_2
    //   185: iload_3
    //   186: if_icmpge +6 -> 192
    //   189: goto +106 -> 295
    //   192: goto +98 -> 290
    //   195: aload_1
    //   196: bipush 12
    //   198: newarray char
    //   200: dup
    //   201: iconst_0
    //   202: ldc -128
    //   204: castore
    //   205: dup
    //   206: iconst_1
    //   207: ldc -127
    //   209: castore
    //   210: dup
    //   211: iconst_2
    //   212: ldc -126
    //   214: castore
    //   215: dup
    //   216: iconst_3
    //   217: ldc -125
    //   219: castore
    //   220: dup
    //   221: iconst_4
    //   222: ldc 123
    //   224: castore
    //   225: dup
    //   226: iconst_5
    //   227: ldc 124
    //   229: castore
    //   230: dup
    //   231: bipush 6
    //   233: ldc -124
    //   235: castore
    //   236: dup
    //   237: bipush 7
    //   239: ldc -123
    //   241: castore
    //   242: dup
    //   243: bipush 8
    //   245: ldc -122
    //   247: castore
    //   248: dup
    //   249: bipush 9
    //   251: ldc -121
    //   253: castore
    //   254: dup
    //   255: bipush 10
    //   257: ldc -120
    //   259: castore
    //   260: dup
    //   261: bipush 11
    //   263: ldc -119
    //   265: castore
    //   266: invokestatic 101	o/IN:ˊ	([C)Ljava/lang/String;
    //   269: invokevirtual 49	java/lang/String:intern	()Ljava/lang/String;
    //   272: invokevirtual 141	java/lang/String:getBytes	(Ljava/lang/String;)[B
    //   275: astore_1
    //   276: aload_1
    //   277: arraylength
    //   278: newarray byte
    //   280: astore 4
    //   282: iconst_0
    //   283: istore_2
    //   284: goto -103 -> 181
    //   287: astore_1
    //   288: aload_1
    //   289: athrow
    //   290: iconst_1
    //   291: istore_3
    //   292: goto -220 -> 72
    //   295: iconst_0
    //   296: istore_3
    //   297: goto -225 -> 72
    // Local variable table:
    //   start	length	slot	name	signature
    //   0	300	0	this	IN
    //   0	300	1	paramString	String
    //   43	241	2	i	int
    //   9	288	3	j	int
    //   99	182	4	arrayOfByte	byte[]
    // Exception table:
    //   from	to	target	type
    //   99	116	30	java/io/UnsupportedEncodingException
    //   123	173	30	java/io/UnsupportedEncodingException
    //   181	184	30	java/io/UnsupportedEncodingException
    //   195	282	30	java/io/UnsupportedEncodingException
    //   40	44	287	java/lang/Exception
    //   49	57	287	java/lang/Exception
  }
  
  private static String ˊ(char[] paramArrayOfChar)
  {
    break label64;
    int i;
    char[] arrayOfChar1;
    label28:
    int j;
    if (i >= paramArrayOfChar.length)
    {
      break label123;
      return new String(arrayOfChar1, 1, arrayOfChar1[0]);
      break label175;
    }
    else
    {
      j = 6;
      break label144;
    }
    for (;;)
    {
      j = ॱꓸ + 37;
      ॱᶥ = j % 128;
      if (j % 2 != 0) {
        break label178;
      }
      break label67;
      label64:
      break label184;
      label67:
      arrayOfChar2[0] = paramArrayOfChar[i];
      arrayOfChar2[1] = paramArrayOfChar[(i + 1)];
      oP.ˏ(arrayOfChar2, ॱˉ, ॱˑ, ॱـ, ॱˌ);
      arrayOfChar1[i] = arrayOfChar2[0];
      arrayOfChar1[(i + 1)] = arrayOfChar2[1];
      i += 2;
      break;
      label123:
      j = 46;
      break label144;
      label129:
      arrayOfChar1 = new char[paramArrayOfChar.length];
      i = 0;
      char[] arrayOfChar2 = new char[2];
      break label211;
      label144:
      switch (j)
      {
      }
    }
    for (;;)
    {
      label175:
      break;
      label178:
      break label67;
      label184:
      do
      {
        break;
        i = ॱꓸ + 117;
        ॱᶥ = i % 128;
      } while (i % 2 != 0);
      break label129;
      label211:
      j = ॱꓸ + 75;
      ॱᶥ = j % 128;
      if (j % 2 != 0) {
        break label28;
      }
    }
  }
  
  static void ᐝ()
  {
    ॱˌ = '句';
    ॱˑ = 56118;
    ॱـ = 64785;
    ॱˉ = 54798;
  }
  
  /* Error */
  public void ˋ(ᐸ paramᐸ, ะ paramะ)
  {
    // Byte code:
    //   0: goto +203 -> 203
    //   3: astore_1
    //   4: aload_1
    //   5: athrow
    //   6: getstatic 27	o/IN:ॱᶥ	I
    //   9: bipush 49
    //   11: iadd
    //   12: istore_3
    //   13: iload_3
    //   14: sipush 128
    //   17: irem
    //   18: putstatic 25	o/IN:ॱꓸ	I
    //   21: iload_3
    //   22: iconst_2
    //   23: irem
    //   24: ifne +6 -> 30
    //   27: goto +100 -> 127
    //   30: goto +176 -> 206
    //   33: astore_1
    //   34: aload_1
    //   35: athrow
    //   36: bipush 34
    //   38: istore_3
    //   39: goto +176 -> 215
    //   42: iload_3
    //   43: tableswitch	default:+21->64, 0:+115->158, 1:+50->93
    //   64: goto +29 -> 93
    //   67: aload_0
    //   68: invokevirtual 165	o/IN:ˋ	()Landroid/content/Context;
    //   71: invokestatic 170	o/Ic:ˏ	(Landroid/content/Context;)Lo/Ic;
    //   74: invokevirtual 174	o/Ic:ʻॱ	()Lo/j;
    //   77: aload_0
    //   78: getfield 64	o/IN:ߺ	I
    //   81: invokevirtual 179	o/j:ˎ	(I)V
    //   84: goto +116 -> 200
    //   87: bipush 77
    //   89: istore_3
    //   90: goto +125 -> 215
    //   93: getstatic 182	o/IN$2:ˊ	[I
    //   96: astore_1
    //   97: aload_2
    //   98: invokevirtual 188	o/ะ:ordinal	()I
    //   101: istore_3
    //   102: aload_1
    //   103: iload_3
    //   104: iaload
    //   105: lookupswitch	default:+19->124, 1:+-38->67
    //   124: goto +76 -> 200
    //   127: iconst_0
    //   128: istore_3
    //   129: goto -87 -> 42
    //   132: getstatic 27	o/IN:ॱᶥ	I
    //   135: iconst_5
    //   136: iadd
    //   137: istore_3
    //   138: iload_3
    //   139: sipush 128
    //   142: irem
    //   143: putstatic 25	o/IN:ॱꓸ	I
    //   146: iload_3
    //   147: iconst_2
    //   148: irem
    //   149: ifne +6 -> 155
    //   152: goto -116 -> 36
    //   155: goto -68 -> 87
    //   158: getstatic 182	o/IN$2:ˊ	[I
    //   161: astore_1
    //   162: aload_1
    //   163: aload_2
    //   164: invokevirtual 188	o/ะ:ordinal	()I
    //   167: iaload
    //   168: istore_3
    //   169: bipush 18
    //   171: iconst_0
    //   172: idiv
    //   173: istore 4
    //   175: iload_3
    //   176: lookupswitch	default:+20->196, 1:+-109->67
    //   196: goto +4 -> 200
    //   199: return
    //   200: goto -68 -> 132
    //   203: goto -197 -> 6
    //   206: iconst_1
    //   207: istore_3
    //   208: goto -166 -> 42
    //   211: aconst_null
    //   212: arraylength
    //   213: istore_3
    //   214: return
    //   215: iload_3
    //   216: lookupswitch	default:+28->244, 34:+-5->211, 77:+-17->199
    //   244: return
    // Local variable table:
    //   start	length	slot	name	signature
    //   0	245	0	this	IN
    //   0	245	1	paramᐸ	ᐸ
    //   0	245	2	paramะ	ะ
    //   12	204	3	i	int
    //   173	1	4	j	int
    // Exception table:
    //   from	to	target	type
    //   97	102	3	java/lang/Exception
    //   93	97	33	java/lang/Exception
    //   97	102	33	java/lang/Exception
    //   158	162	33	java/lang/Exception
    //   162	175	33	java/lang/Exception
  }
  
  public int ˎ()
  {
    int i;
    for (;;)
    {
      i = 0;
      break label55;
      i = Gu.ˊ.dialog_simple_tutorial;
      int j = 92 / 0;
      return i;
      i = ॱꓸ + 111;
      ॱᶥ = i % 128;
      if (i % 2 != 0) {
        break;
      }
    }
    for (;;)
    {
      return Gu.ˊ.dialog_simple_tutorial;
      i = 1;
      label55:
      switch (i)
      {
      }
    }
  }
  
  /* Error */
  public void ॱ(String paramString)
  {
    // Byte code:
    //   0: goto +132 -> 132
    //   3: return
    //   4: astore_1
    //   5: aload_1
    //   6: athrow
    //   7: astore_1
    //   8: aload_1
    //   9: athrow
    //   10: new 66	java/lang/NullPointerException
    //   13: dup
    //   14: invokespecial 68	java/lang/NullPointerException:<init>	()V
    //   17: athrow
    //   18: bipush 72
    //   20: istore_2
    //   21: goto +81 -> 102
    //   24: getstatic 25	o/IN:ॱꓸ	I
    //   27: bipush 45
    //   29: iadd
    //   30: istore_2
    //   31: iload_2
    //   32: sipush 128
    //   35: irem
    //   36: putstatic 27	o/IN:ॱᶥ	I
    //   39: iload_2
    //   40: iconst_2
    //   41: irem
    //   42: ifeq +6 -> 48
    //   45: goto +24 -> 69
    //   48: goto -30 -> 18
    //   51: aload_0
    //   52: getfield 198	o/IN:ॱˈ	Landroid/databinding/ViewDataBinding;
    //   55: astore_3
    //   56: aload_3
    //   57: checkcast 200	o/GP
    //   60: astore_3
    //   61: aload_3
    //   62: aload_1
    //   63: invokevirtual 202	o/GP:ˏ	(Ljava/lang/String;)V
    //   66: goto -42 -> 24
    //   69: bipush 23
    //   71: istore_2
    //   72: goto +30 -> 102
    //   75: getstatic 25	o/IN:ॱꓸ	I
    //   78: bipush 73
    //   80: iadd
    //   81: istore_2
    //   82: iload_2
    //   83: sipush 128
    //   86: irem
    //   87: putstatic 27	o/IN:ॱᶥ	I
    //   90: iload_2
    //   91: iconst_2
    //   92: irem
    //   93: ifeq +6 -> 99
    //   96: goto +33 -> 129
    //   99: goto -48 -> 51
    //   102: iload_2
    //   103: lookupswitch	default:+25->128, 23:+-93->10, 72:+-100->3
    //   128: return
    //   129: goto -78 -> 51
    //   132: goto -57 -> 75
    // Local variable table:
    //   start	length	slot	name	signature
    //   0	135	0	this	IN
    //   0	135	1	paramString	String
    //   20	83	2	i	int
    //   55	7	3	localObject	Object
    // Exception table:
    //   from	to	target	type
    //   56	61	4	java/lang/Exception
    //   51	56	7	java/lang/Exception
    //   61	66	7	java/lang/Exception
  }
}
