package o;

import android.databinding.ViewDataBinding;
import android.os.Bundle;

public abstract class IP<I extends Iu.iF, VDB extends ViewDataBinding>
  extends Z<I, VDB>
  implements Iu.if
{
  private static int ʻ = 1;
  private static int ˋ = 0;
  private static char[] ˎ = { 109, 86, 105, 101, 119, 68, 108, 103, 97, 116, 60, 115, 45, 63, 62, 114, 100, 80, 104, 111, 110, 78, 117, 98, 112 };
  private static char ॱ = '\005';
  public IC ˊ;
  
  public IP() {}
  
  /* Error */
  private static String ˊ(char[] paramArrayOfChar, int paramInt, byte paramByte)
  {
    // Byte code:
    //   0: goto +568 -> 568
    //   3: aload_0
    //   4: iload_3
    //   5: caload
    //   6: istore 5
    //   8: aload_0
    //   9: iload_3
    //   10: iconst_1
    //   11: iadd
    //   12: caload
    //   13: istore 6
    //   15: iload 5
    //   17: iload 6
    //   19: if_icmpne +6 -> 25
    //   22: goto +343 -> 365
    //   25: goto +6 -> 31
    //   28: goto +314 -> 342
    //   31: iconst_2
    //   32: istore 10
    //   34: goto +113 -> 147
    //   37: iload_3
    //   38: iconst_2
    //   39: iadd
    //   40: istore_3
    //   41: goto +190 -> 231
    //   44: getstatic 22	o/IP:ʻ	I
    //   47: istore 4
    //   49: iload 4
    //   51: bipush 29
    //   53: iadd
    //   54: istore 4
    //   56: iload 4
    //   58: sipush 128
    //   61: irem
    //   62: putstatic 20	o/IP:ˋ	I
    //   65: iload 4
    //   67: iconst_2
    //   68: irem
    //   69: ifeq +6 -> 75
    //   72: goto +368 -> 440
    //   75: goto -72 -> 3
    //   78: astore_0
    //   79: aload_0
    //   80: athrow
    //   81: iload_3
    //   82: iconst_1
    //   83: isub
    //   84: istore_1
    //   85: aload 13
    //   87: iload_1
    //   88: aload_0
    //   89: iload_1
    //   90: caload
    //   91: iload_2
    //   92: isub
    //   93: i2c
    //   94: castore
    //   95: goto +432 -> 527
    //   98: iload 7
    //   100: iload 11
    //   102: invokestatic 63	o/oO:ॱ	(II)I
    //   105: istore 6
    //   107: iload 7
    //   109: iload 11
    //   111: invokestatic 65	o/oO:ˋ	(II)I
    //   114: istore 7
    //   116: iload 4
    //   118: iload 11
    //   120: invokestatic 63	o/oO:ॱ	(II)I
    //   123: istore 5
    //   125: iload 4
    //   127: iload 11
    //   129: invokestatic 65	o/oO:ˋ	(II)I
    //   132: istore 4
    //   134: iload 7
    //   136: iload 4
    //   138: if_icmpne +6 -> 144
    //   141: goto +231 -> 372
    //   144: goto +74 -> 218
    //   147: iload 5
    //   149: istore 7
    //   151: iload 6
    //   153: istore 4
    //   155: iload 5
    //   157: istore 8
    //   159: iload 6
    //   161: istore 9
    //   163: iload 10
    //   165: lookupswitch	default:+27->192, 2:+-67->98, 38:+373->538
    //   192: iload 5
    //   194: istore 8
    //   196: iload 6
    //   198: istore 9
    //   200: goto +338 -> 538
    //   203: bipush 70
    //   205: istore 4
    //   207: goto +195 -> 402
    //   210: goto -173 -> 37
    //   213: iconst_0
    //   214: istore_3
    //   215: goto +287 -> 502
    //   218: iload 6
    //   220: iload 5
    //   222: if_icmpne +6 -> 228
    //   225: goto +346 -> 571
    //   228: goto +69 -> 297
    //   231: goto +271 -> 502
    //   234: iload 6
    //   236: iload 11
    //   238: invokestatic 67	o/oO:ˊ	(II)I
    //   241: istore 6
    //   243: iload 5
    //   245: iload 11
    //   247: invokestatic 67	o/oO:ˊ	(II)I
    //   250: istore 5
    //   252: iload 6
    //   254: iload 7
    //   256: iload 11
    //   258: invokestatic 71	o/oO:ˏ	(III)I
    //   261: istore 6
    //   263: iload 5
    //   265: iload 4
    //   267: iload 11
    //   269: invokestatic 71	o/oO:ˏ	(III)I
    //   272: istore 4
    //   274: aload 13
    //   276: iload_3
    //   277: aload 12
    //   279: iload 6
    //   281: caload
    //   282: castore
    //   283: aload 13
    //   285: iload_3
    //   286: iconst_1
    //   287: iadd
    //   288: aload 12
    //   290: iload 4
    //   292: caload
    //   293: castore
    //   294: goto -257 -> 37
    //   297: iload 6
    //   299: iload 4
    //   301: iload 11
    //   303: invokestatic 71	o/oO:ˏ	(III)I
    //   306: istore 4
    //   308: iload 5
    //   310: iload 7
    //   312: iload 11
    //   314: invokestatic 71	o/oO:ˏ	(III)I
    //   317: istore 5
    //   319: aload 13
    //   321: iload_3
    //   322: aload 12
    //   324: iload 4
    //   326: caload
    //   327: castore
    //   328: aload 13
    //   330: iload_3
    //   331: iconst_1
    //   332: iadd
    //   333: aload 12
    //   335: iload 5
    //   337: caload
    //   338: castore
    //   339: goto -302 -> 37
    //   342: aload 13
    //   344: iload_3
    //   345: iload 8
    //   347: iload_2
    //   348: isub
    //   349: i2c
    //   350: castore
    //   351: aload 13
    //   353: iload_3
    //   354: iconst_1
    //   355: iadd
    //   356: iload 9
    //   358: iload_2
    //   359: isub
    //   360: i2c
    //   361: castore
    //   362: goto -325 -> 37
    //   365: bipush 38
    //   367: istore 10
    //   369: goto -222 -> 147
    //   372: getstatic 22	o/IP:ʻ	I
    //   375: bipush 63
    //   377: iadd
    //   378: istore 8
    //   380: iload 8
    //   382: sipush 128
    //   385: irem
    //   386: putstatic 20	o/IP:ˋ	I
    //   389: iload 8
    //   391: iconst_2
    //   392: irem
    //   393: ifeq +6 -> 399
    //   396: goto +41 -> 437
    //   399: goto -165 -> 234
    //   402: iload_3
    //   403: istore_1
    //   404: iload 4
    //   406: lookupswitch	default:+26->432, 27:+121->527, 70:+-325->81
    //   432: iload_3
    //   433: istore_1
    //   434: goto +93 -> 527
    //   437: goto -203 -> 234
    //   440: aload_0
    //   441: iload_3
    //   442: caload
    //   443: istore 7
    //   445: aload_0
    //   446: iload_3
    //   447: iconst_1
    //   448: isub
    //   449: caload
    //   450: istore 4
    //   452: iload 7
    //   454: iload 4
    //   456: if_icmpne +14 -> 470
    //   459: iload 7
    //   461: istore 8
    //   463: iload 4
    //   465: istore 9
    //   467: goto +71 -> 538
    //   470: goto -372 -> 98
    //   473: getstatic 49	o/IP:ˎ	[C
    //   476: astore 12
    //   478: iload_1
    //   479: istore_3
    //   480: getstatic 51	o/IP:ॱ	C
    //   483: istore 11
    //   485: iload_3
    //   486: newarray char
    //   488: astore 13
    //   490: iload_3
    //   491: iconst_2
    //   492: irem
    //   493: ifeq +6 -> 499
    //   496: goto -293 -> 203
    //   499: goto +21 -> 520
    //   502: iload_3
    //   503: iload_1
    //   504: if_icmpge +6 -> 510
    //   507: goto -463 -> 44
    //   510: new 73	java/lang/String
    //   513: dup
    //   514: aload 13
    //   516: invokespecial 76	java/lang/String:<init>	([C)V
    //   519: areturn
    //   520: bipush 27
    //   522: istore 4
    //   524: goto -122 -> 402
    //   527: iload_1
    //   528: iconst_1
    //   529: if_icmple +6 -> 535
    //   532: goto -319 -> 213
    //   535: goto -25 -> 510
    //   538: getstatic 22	o/IP:ʻ	I
    //   541: bipush 43
    //   543: iadd
    //   544: istore 4
    //   546: iload 4
    //   548: sipush 128
    //   551: irem
    //   552: putstatic 20	o/IP:ˋ	I
    //   555: iload 4
    //   557: iconst_2
    //   558: irem
    //   559: ifeq +6 -> 565
    //   562: goto -534 -> 28
    //   565: goto -223 -> 342
    //   568: goto -95 -> 473
    //   571: iload 7
    //   573: iload 11
    //   575: invokestatic 67	o/oO:ˊ	(II)I
    //   578: istore 7
    //   580: iload 4
    //   582: iload 11
    //   584: invokestatic 67	o/oO:ˊ	(II)I
    //   587: istore 4
    //   589: iload 6
    //   591: iload 7
    //   593: iload 11
    //   595: invokestatic 71	o/oO:ˏ	(III)I
    //   598: istore 6
    //   600: iload 5
    //   602: iload 4
    //   604: iload 11
    //   606: invokestatic 71	o/oO:ˏ	(III)I
    //   609: istore 4
    //   611: aload 13
    //   613: iload_3
    //   614: aload 12
    //   616: iload 6
    //   618: caload
    //   619: castore
    //   620: aload 13
    //   622: iload_3
    //   623: iconst_1
    //   624: iadd
    //   625: aload 12
    //   627: iload 4
    //   629: caload
    //   630: castore
    //   631: goto -421 -> 210
    //   634: astore_0
    //   635: aload_0
    //   636: athrow
    // Local variable table:
    //   start	length	slot	name	signature
    //   0	637	0	paramArrayOfChar	char[]
    //   0	637	1	paramInt	int
    //   0	637	2	paramByte	byte
    //   4	621	3	i	int
    //   47	581	4	b1	byte
    //   6	595	5	b2	byte
    //   13	604	6	b3	byte
    //   98	494	7	b4	byte
    //   157	305	8	b5	byte
    //   161	305	9	b6	byte
    //   32	336	10	j	int
    //   100	505	11	k	int
    //   277	349	12	arrayOfChar1	char[]
    //   85	536	13	arrayOfChar2	char[]
    // Exception table:
    //   from	to	target	type
    //   44	49	78	java/lang/Exception
    //   473	478	78	java/lang/Exception
    //   56	65	634	java/lang/Exception
    //   297	308	634	java/lang/Exception
    //   308	319	634	java/lang/Exception
  }
  
  /* Error */
  public void A_()
  {
    // Byte code:
    //   0: goto +43 -> 43
    //   3: getstatic 22	o/IP:ʻ	I
    //   6: bipush 107
    //   8: iadd
    //   9: istore_1
    //   10: iload_1
    //   11: sipush 128
    //   14: irem
    //   15: putstatic 20	o/IP:ˋ	I
    //   18: iload_1
    //   19: iconst_2
    //   20: irem
    //   21: ifeq +6 -> 27
    //   24: goto +55 -> 79
    //   27: return
    //   28: astore_2
    //   29: aload_2
    //   30: athrow
    //   31: aload_0
    //   32: invokevirtual 81	o/IP:ﹳ	()Lo/IC;
    //   35: astore_2
    //   36: aload_2
    //   37: invokevirtual 85	o/IC:A_	()V
    //   40: goto -37 -> 3
    //   43: goto +6 -> 49
    //   46: goto -15 -> 31
    //   49: getstatic 22	o/IP:ʻ	I
    //   52: bipush 57
    //   54: iadd
    //   55: istore_1
    //   56: iload_1
    //   57: sipush 128
    //   60: irem
    //   61: putstatic 20	o/IP:ˋ	I
    //   64: iload_1
    //   65: iconst_2
    //   66: irem
    //   67: ifeq +6 -> 73
    //   70: goto -24 -> 46
    //   73: goto -42 -> 31
    //   76: astore_2
    //   77: aload_2
    //   78: athrow
    //   79: return
    // Local variable table:
    //   start	length	slot	name	signature
    //   0	80	0	this	IP
    //   9	58	1	i	int
    //   28	2	2	localException1	Exception
    //   35	2	2	localIC	IC
    //   76	2	2	localException2	Exception
    // Exception table:
    //   from	to	target	type
    //   31	36	28	java/lang/Exception
    //   36	40	28	java/lang/Exception
    //   36	40	76	java/lang/Exception
  }
  
  public void v_()
  {
    break label56;
    int i;
    for (;;)
    {
      break;
      i = ˋ + 39;
      ʻ = i % 128;
      if (i % 2 != 0) {
        break;
      }
    }
    for (;;)
    {
      i = ˋ + 107;
      ʻ = i % 128;
      if (i % 2 == 0) {
        return;
      }
      return;
      label56:
      break;
      ﹳ().v_();
    }
  }
  
  public void w_()
  {
    for (;;)
    {
      try
      {
        int i = ʻ + 5;
        try
        {
          ˋ = i % 128;
          if (i % 2 != 0) {
            continue;
          }
        }
        catch (Exception localException1)
        {
          throw localException1;
        }
        i = ʻ + 125;
        ˋ = i % 128;
        if (i % 2 == 0) {
          return;
        }
        return;
      }
      catch (Exception localException2)
      {
        throw localException2;
      }
      ﹳ().w_();
    }
  }
  
  /* Error */
  public void x_()
  {
    // Byte code:
    //   0: goto +53 -> 53
    //   3: astore_2
    //   4: aload_2
    //   5: athrow
    //   6: bipush 25
    //   8: istore_1
    //   9: goto +3 -> 12
    //   12: iload_1
    //   13: lookupswitch	default:+27->40, 25:+70->83, 73:+30->43
    //   40: goto +43 -> 83
    //   43: aload_0
    //   44: invokevirtual 81	o/IP:ﹳ	()Lo/IC;
    //   47: astore_2
    //   48: aload_2
    //   49: invokevirtual 94	o/IC:x_	()V
    //   52: return
    //   53: getstatic 20	o/IP:ˋ	I
    //   56: bipush 107
    //   58: iadd
    //   59: istore_1
    //   60: iload_1
    //   61: sipush 128
    //   64: irem
    //   65: putstatic 22	o/IP:ʻ	I
    //   68: iload_1
    //   69: iconst_2
    //   70: irem
    //   71: ifne +6 -> 77
    //   74: goto -68 -> 6
    //   77: bipush 73
    //   79: istore_1
    //   80: goto -68 -> 12
    //   83: aload_0
    //   84: invokevirtual 81	o/IP:ﹳ	()Lo/IC;
    //   87: invokevirtual 94	o/IC:x_	()V
    //   90: aconst_null
    //   91: arraylength
    //   92: istore_1
    //   93: return
    // Local variable table:
    //   start	length	slot	name	signature
    //   0	94	0	this	IP
    //   8	85	1	i	int
    //   3	2	2	localException	Exception
    //   47	2	2	localIC	IC
    // Exception table:
    //   from	to	target	type
    //   43	48	3	java/lang/Exception
    //   48	52	3	java/lang/Exception
  }
  
  /* Error */
  public void y_()
  {
    // Byte code:
    //   0: goto +44 -> 44
    //   3: astore_2
    //   4: aload_2
    //   5: athrow
    //   6: aload_0
    //   7: invokevirtual 81	o/IP:ﹳ	()Lo/IC;
    //   10: invokevirtual 97	o/IC:y_	()V
    //   13: goto +3 -> 16
    //   16: getstatic 20	o/IP:ˋ	I
    //   19: istore_1
    //   20: iload_1
    //   21: bipush 23
    //   23: iadd
    //   24: istore_1
    //   25: iload_1
    //   26: sipush 128
    //   29: irem
    //   30: putstatic 22	o/IP:ʻ	I
    //   33: iload_1
    //   34: iconst_2
    //   35: irem
    //   36: ifne +4 -> 40
    //   39: return
    //   40: return
    //   41: goto -35 -> 6
    //   44: goto +6 -> 50
    //   47: astore_2
    //   48: aload_2
    //   49: athrow
    //   50: getstatic 22	o/IP:ʻ	I
    //   53: bipush 13
    //   55: iadd
    //   56: istore_1
    //   57: iload_1
    //   58: sipush 128
    //   61: irem
    //   62: putstatic 20	o/IP:ˋ	I
    //   65: iload_1
    //   66: iconst_2
    //   67: irem
    //   68: ifeq +6 -> 74
    //   71: goto -30 -> 41
    //   74: goto -68 -> 6
    // Local variable table:
    //   start	length	slot	name	signature
    //   0	77	0	this	IP
    //   19	49	1	i	int
    //   3	2	2	localException1	Exception
    //   47	2	2	localException2	Exception
    // Exception table:
    //   from	to	target	type
    //   25	33	3	java/lang/Exception
    //   16	20	47	java/lang/Exception
  }
  
  public void z_()
  {
    break label38;
    int i = 16;
    for (;;)
    {
      try
      {
        i = ˋ;
        i += 93;
      }
      catch (Exception localException1)
      {
        label38:
        throw localException1;
      }
      try
      {
        ʻ = i % 128;
        if (i % 2 == 0) {
          break label164;
        }
      }
      catch (Exception localException2)
      {
        throw localException2;
      }
      break label82;
      i = 30;
      switch (i)
      {
      default: 
        break label159;
        i = ʻ;
        i += 125;
        ˋ = i % 128;
        if (i % 2 == 0) {}
        for (;;)
        {
          ﹳ().z_();
          i = null.length;
          break;
          i = 92;
          switch (i)
          {
          }
        }
      case 20: 
        i = null.length;
        return;
      case 16: 
        label82:
        label159:
        return;
        label164:
        i = 20;
        continue;
        ﹳ().z_();
      }
    }
  }
  
  public void ˊ(IC paramIC)
  {
    try
    {
      int i = ʻ + 29;
      ˋ = i % 128;
      if (i % 2 == 0) {
        break label27;
      }
      for (;;)
      {
        label27:
        vq.ˎ(paramIC, ˊ(new char[] { 11, 12, 4, 8, 13, 14, 143 }, 7, (byte)81).intern());
        this.ˊ = paramIC;
        break;
      }
      i = ʻ + 105;
      ˋ = i % 128;
      if (i % 2 != 0) {
        return;
      }
      return;
    }
    catch (Exception paramIC)
    {
      throw paramIC;
    }
  }
  
  /* Error */
  public void ˎ(android.content.DialogInterface.OnCancelListener paramOnCancelListener)
  {
    // Byte code:
    //   0: goto +35 -> 35
    //   3: goto +35 -> 38
    //   6: astore_1
    //   7: aload_1
    //   8: athrow
    //   9: getstatic 20	o/IP:ˋ	I
    //   12: bipush 51
    //   14: iadd
    //   15: istore_2
    //   16: iload_2
    //   17: sipush 128
    //   20: irem
    //   21: putstatic 22	o/IP:ʻ	I
    //   24: iload_2
    //   25: iconst_2
    //   26: irem
    //   27: ifne +6 -> 33
    //   30: goto +4 -> 34
    //   33: return
    //   34: return
    //   35: goto +74 -> 109
    //   38: aload_1
    //   39: bipush 8
    //   41: newarray char
    //   43: dup
    //   44: iconst_0
    //   45: ldc -127
    //   47: castore
    //   48: dup
    //   49: iconst_1
    //   50: ldc -126
    //   52: castore
    //   53: dup
    //   54: iconst_2
    //   55: ldc 107
    //   57: castore
    //   58: dup
    //   59: iconst_3
    //   60: ldc -125
    //   62: castore
    //   63: dup
    //   64: iconst_4
    //   65: ldc -124
    //   67: castore
    //   68: dup
    //   69: iconst_5
    //   70: ldc -123
    //   72: castore
    //   73: dup
    //   74: bipush 6
    //   76: ldc -124
    //   78: castore
    //   79: dup
    //   80: bipush 7
    //   82: ldc -122
    //   84: castore
    //   85: bipush 8
    //   87: bipush 35
    //   89: invokestatic 110	o/IP:ˊ	([CIB)Ljava/lang/String;
    //   92: invokevirtual 114	java/lang/String:intern	()Ljava/lang/String;
    //   95: invokestatic 119	o/vq:ˎ	(Ljava/lang/Object;Ljava/lang/String;)V
    //   98: aload_0
    //   99: invokevirtual 81	o/IP:ﹳ	()Lo/IC;
    //   102: aload_1
    //   103: invokevirtual 136	o/IC:ˎ	(Landroid/content/DialogInterface$OnCancelListener;)V
    //   106: goto -97 -> 9
    //   109: getstatic 20	o/IP:ˋ	I
    //   112: istore_2
    //   113: iload_2
    //   114: bipush 121
    //   116: iadd
    //   117: istore_2
    //   118: iload_2
    //   119: sipush 128
    //   122: irem
    //   123: putstatic 22	o/IP:ʻ	I
    //   126: iload_2
    //   127: iconst_2
    //   128: irem
    //   129: ifne +6 -> 135
    //   132: goto -129 -> 3
    //   135: goto -97 -> 38
    // Local variable table:
    //   start	length	slot	name	signature
    //   0	138	0	this	IP
    //   0	138	1	paramOnCancelListener	android.content.DialogInterface.OnCancelListener
    //   15	114	2	i	int
    // Exception table:
    //   from	to	target	type
    //   109	113	6	java/lang/Exception
    //   118	126	6	java/lang/Exception
  }
  
  public void ˎ(Fd paramFd)
  {
    break label31;
    break label35;
    label6:
    int i = ˋ + 63;
    ʻ = i % 128;
    if (i % 2 != 0) {
      return;
    } else {
      label31:
      return;
    }
    for (;;)
    {
      label35:
      ﹳ().ˎ(paramFd);
      break label6;
      i = ˋ + 7;
      ʻ = i % 128;
      if (i % 2 == 0) {
        break;
      }
    }
  }
  
  /* Error */
  public void ˏ(String paramString)
  {
    // Byte code:
    //   0: goto +74 -> 74
    //   3: iload_2
    //   4: lookupswitch	default:+28->32, 72:+222->226, 87:+223->227
    //   32: return
    //   33: astore_1
    //   34: aload_1
    //   35: athrow
    //   36: goto +41 -> 77
    //   39: getstatic 22	o/IP:ʻ	I
    //   42: istore_2
    //   43: iload_2
    //   44: bipush 77
    //   46: iadd
    //   47: istore_2
    //   48: iload_2
    //   49: sipush 128
    //   52: irem
    //   53: putstatic 20	o/IP:ˋ	I
    //   56: iload_2
    //   57: iconst_2
    //   58: irem
    //   59: ifeq +6 -> 65
    //   62: goto -26 -> 36
    //   65: goto +12 -> 77
    //   68: bipush 72
    //   70: istore_2
    //   71: goto -68 -> 3
    //   74: goto -35 -> 39
    //   77: aload_1
    //   78: bipush 21
    //   80: newarray char
    //   82: dup
    //   83: iconst_0
    //   84: ldc -122
    //   86: castore
    //   87: dup
    //   88: iconst_1
    //   89: ldc -124
    //   91: castore
    //   92: dup
    //   93: iconst_2
    //   94: ldc 103
    //   96: castore
    //   97: dup
    //   98: iconst_3
    //   99: ldc -127
    //   101: castore
    //   102: dup
    //   103: iconst_4
    //   104: ldc 107
    //   106: castore
    //   107: dup
    //   108: iconst_5
    //   109: ldc -125
    //   111: castore
    //   112: dup
    //   113: bipush 6
    //   115: ldc -124
    //   117: castore
    //   118: dup
    //   119: bipush 7
    //   121: ldc -122
    //   123: castore
    //   124: dup
    //   125: bipush 8
    //   127: ldc -126
    //   129: castore
    //   130: dup
    //   131: bipush 9
    //   133: ldc -122
    //   135: castore
    //   136: dup
    //   137: bipush 10
    //   139: ldc -122
    //   141: castore
    //   142: dup
    //   143: bipush 11
    //   145: ldc -115
    //   147: castore
    //   148: dup
    //   149: bipush 12
    //   151: ldc -114
    //   153: castore
    //   154: dup
    //   155: bipush 13
    //   157: ldc -113
    //   159: castore
    //   160: dup
    //   161: bipush 14
    //   163: ldc -126
    //   165: castore
    //   166: dup
    //   167: bipush 15
    //   169: ldc -123
    //   171: castore
    //   172: dup
    //   173: bipush 16
    //   175: ldc -112
    //   177: castore
    //   178: dup
    //   179: bipush 17
    //   181: ldc -111
    //   183: castore
    //   184: dup
    //   185: bipush 18
    //   187: ldc -110
    //   189: castore
    //   190: dup
    //   191: bipush 19
    //   193: ldc 105
    //   195: castore
    //   196: dup
    //   197: bipush 20
    //   199: ldc -109
    //   201: castore
    //   202: bipush 21
    //   204: bipush 65
    //   206: invokestatic 110	o/IP:ˊ	([CIB)Ljava/lang/String;
    //   209: invokevirtual 114	java/lang/String:intern	()Ljava/lang/String;
    //   212: invokestatic 119	o/vq:ˎ	(Ljava/lang/Object;Ljava/lang/String;)V
    //   215: aload_0
    //   216: invokevirtual 81	o/IP:ﹳ	()Lo/IC;
    //   219: aload_1
    //   220: invokevirtual 149	o/IC:ˏ	(Ljava/lang/String;)V
    //   223: goto +21 -> 244
    //   226: return
    //   227: new 124	java/lang/NullPointerException
    //   230: dup
    //   231: invokespecial 125	java/lang/NullPointerException:<init>	()V
    //   234: athrow
    //   235: bipush 87
    //   237: istore_2
    //   238: goto -235 -> 3
    //   241: astore_1
    //   242: aload_1
    //   243: athrow
    //   244: getstatic 22	o/IP:ʻ	I
    //   247: bipush 17
    //   249: iadd
    //   250: istore_2
    //   251: iload_2
    //   252: sipush 128
    //   255: irem
    //   256: putstatic 20	o/IP:ˋ	I
    //   259: iload_2
    //   260: iconst_2
    //   261: irem
    //   262: ifeq +6 -> 268
    //   265: goto -30 -> 235
    //   268: goto -200 -> 68
    // Local variable table:
    //   start	length	slot	name	signature
    //   0	271	0	this	IP
    //   0	271	1	paramString	String
    //   3	259	2	i	int
    // Exception table:
    //   from	to	target	type
    //   48	56	33	java/lang/Exception
    //   39	43	241	java/lang/Exception
  }
  
  public void ॱ(Bundle paramBundle)
  {
    break label72;
    int i;
    for (;;)
    {
      switch (i)
      {
      case 23: 
      default: 
        return;
        i = 23;
        continue;
        label39:
        i = 85;
      }
    }
    for (;;)
    {
      try
      {
        i = ˋ + 109;
      }
      catch (Exception paramBundle)
      {
        label72:
        throw paramBundle;
      }
      try
      {
        ʻ = i % 128;
        if (i % 2 == 0) {
          break label39;
        }
      }
      catch (Exception paramBundle)
      {
        throw paramBundle;
      }
      super.ॱ(paramBundle);
      ˊ(new IC(ˏॱ()));
    }
    throw new NullPointerException();
  }
  
  /* Error */
  protected IC ﹳ()
  {
    // Byte code:
    //   0: goto +146 -> 146
    //   3: iload_1
    //   4: lookupswitch	default:+28->32, 52:+169->173, 65:+34->38
    //   32: goto +141 -> 173
    //   35: goto +20 -> 55
    //   38: aload_2
    //   39: areturn
    //   40: astore_2
    //   41: aload_2
    //   42: athrow
    //   43: bipush 65
    //   45: istore_1
    //   46: goto -43 -> 3
    //   49: bipush 52
    //   51: istore_1
    //   52: goto -49 -> 3
    //   55: bipush 13
    //   57: newarray char
    //   59: dup
    //   60: iconst_0
    //   61: ldc -126
    //   63: castore
    //   64: dup
    //   65: iconst_1
    //   66: ldc -111
    //   68: castore
    //   69: dup
    //   70: iconst_2
    //   71: ldc -110
    //   73: castore
    //   74: dup
    //   75: iconst_3
    //   76: ldc 104
    //   78: castore
    //   79: dup
    //   80: iconst_4
    //   81: ldc -124
    //   83: castore
    //   84: dup
    //   85: iconst_5
    //   86: ldc -94
    //   88: castore
    //   89: dup
    //   90: bipush 6
    //   92: ldc -126
    //   94: castore
    //   95: dup
    //   96: bipush 7
    //   98: ldc 105
    //   100: castore
    //   101: dup
    //   102: bipush 8
    //   104: ldc -111
    //   106: castore
    //   107: dup
    //   108: bipush 9
    //   110: ldc 105
    //   112: castore
    //   113: dup
    //   114: bipush 10
    //   116: ldc -94
    //   118: castore
    //   119: dup
    //   120: bipush 11
    //   122: ldc -93
    //   124: castore
    //   125: dup
    //   126: bipush 12
    //   128: ldc -92
    //   130: castore
    //   131: bipush 13
    //   133: bipush 23
    //   135: invokestatic 110	o/IP:ˊ	([CIB)Ljava/lang/String;
    //   138: invokevirtual 114	java/lang/String:intern	()Ljava/lang/String;
    //   141: invokestatic 166	o/vq:ˊ	(Ljava/lang/String;)V
    //   144: aload_2
    //   145: areturn
    //   146: getstatic 22	o/IP:ʻ	I
    //   149: bipush 63
    //   151: iadd
    //   152: istore_1
    //   153: iload_1
    //   154: sipush 128
    //   157: irem
    //   158: putstatic 20	o/IP:ˋ	I
    //   161: iload_1
    //   162: iconst_2
    //   163: irem
    //   164: ifeq +6 -> 170
    //   167: goto +33 -> 200
    //   170: goto +36 -> 206
    //   173: getstatic 20	o/IP:ˋ	I
    //   176: bipush 61
    //   178: iadd
    //   179: istore_1
    //   180: iload_1
    //   181: sipush 128
    //   184: irem
    //   185: putstatic 22	o/IP:ʻ	I
    //   188: iload_1
    //   189: iconst_2
    //   190: irem
    //   191: ifne +6 -> 197
    //   194: goto -159 -> 35
    //   197: goto -142 -> 55
    //   200: goto +6 -> 206
    //   203: astore_2
    //   204: aload_2
    //   205: athrow
    //   206: aload_0
    //   207: getfield 121	o/IP:ˊ	Lo/IC;
    //   210: astore_2
    //   211: aload_2
    //   212: ifnonnull +6 -> 218
    //   215: goto -166 -> 49
    //   218: goto -175 -> 43
    // Local variable table:
    //   start	length	slot	name	signature
    //   0	221	0	this	IP
    //   3	188	1	i	int
    //   38	1	2	localIC1	IC
    //   40	105	2	localException1	Exception
    //   203	2	2	localException2	Exception
    //   210	2	2	localIC2	IC
    // Exception table:
    //   from	to	target	type
    //   146	153	40	java/lang/Exception
    //   153	161	40	java/lang/Exception
    //   153	161	203	java/lang/Exception
  }
}
