package o;

public final class Ip
{
  public static final ˊ Companion;
  private static final String HMAC_SHA_256 = "HmacSHA256";
  private static int ˋ = 0;
  private static int ˏ = 1;
  
  /* Error */
  static
  {
    // Byte code:
    //   0: iconst_0
    //   1: putstatic 25	o/Ip:ˋ	I
    //   4: iconst_1
    //   5: putstatic 27	o/Ip:ˏ	I
    //   8: goto +12 -> 20
    //   11: astore_2
    //   12: aload_2
    //   13: athrow
    //   14: bipush 50
    //   16: istore_0
    //   17: goto +74 -> 91
    //   20: new 6	o/Ip$ˊ
    //   23: dup
    //   24: aconst_null
    //   25: invokespecial 31	o/Ip$ˊ:<init>	(Lo/vn;)V
    //   28: astore_2
    //   29: aload_2
    //   30: putstatic 33	o/Ip:Companion	Lo/Ip$ˊ;
    //   33: goto +4 -> 37
    //   36: return
    //   37: getstatic 25	o/Ip:ˋ	I
    //   40: istore_1
    //   41: iload_1
    //   42: bipush 121
    //   44: ixor
    //   45: iload_1
    //   46: bipush 121
    //   48: iand
    //   49: ior
    //   50: iconst_1
    //   51: ishl
    //   52: istore_0
    //   53: iload_1
    //   54: bipush 121
    //   56: ixor
    //   57: istore_1
    //   58: iload_1
    //   59: ineg
    //   60: iload_0
    //   61: iand
    //   62: iload_0
    //   63: iload_1
    //   64: ineg
    //   65: ior
    //   66: iadd
    //   67: istore_0
    //   68: iload_0
    //   69: sipush 128
    //   72: irem
    //   73: putstatic 27	o/Ip:ˏ	I
    //   76: iload_0
    //   77: iconst_2
    //   78: irem
    //   79: ifne +6 -> 85
    //   82: goto -68 -> 14
    //   85: goto +39 -> 124
    //   88: astore_2
    //   89: aload_2
    //   90: athrow
    //   91: iload_0
    //   92: lookupswitch	default:+28->120, 29:+-56->36, 50:+28->120
    //   120: aconst_null
    //   121: arraylength
    //   122: istore_0
    //   123: return
    //   124: bipush 29
    //   126: istore_0
    //   127: goto -36 -> 91
    // Local variable table:
    //   start	length	slot	name	signature
    //   16	111	0	i	int
    //   40	24	1	j	int
    //   11	2	2	localIndexOutOfBoundsException1	IndexOutOfBoundsException
    //   28	2	2	localˊ	ˊ
    //   88	2	2	localIndexOutOfBoundsException2	IndexOutOfBoundsException
    // Exception table:
    //   from	to	target	type
    //   68	76	11	java/lang/IndexOutOfBoundsException
    //   29	33	88	java/lang/IndexOutOfBoundsException
    //   37	41	88	java/lang/UnsupportedOperationException
    //   68	76	88	java/lang/UnsupportedOperationException
  }
  
  public Ip() {}
  
  public static final class ˊ
  {
    private static int ˊ;
    private static char[] ˋ = { 19739, 6444, -6824, -20100, 7564, -5702, -18979, 99, 21583, -22478, -1006, 20709, -23348, -1887, 19604, -24215, -2737, 18734, -25303, -3612, 13817, 25028, -25184, -13944, 25924, -28349, -13056, 30980, -27423, -16191, 31908, -22370, 85, 21620, -22522, -947, 20664, 11156, 32662, -31747, -10282, 31521, -28910, -11393, 84, 21576, -22491, -960, 20723, -23355, -1870, 19606, -24219, -2734, 18784, -25328, -3595, 17858, -26196, -4727, 16995, -27136, -5589, 15877, -27911, -6528, 15017, -29037, -7392, 14149, -29907, -8432, 13300, -30759, -9247, 117, 21588, -22490, -936, 20675, -23352, -1887, 19602, -24205, -2747, 18740, -19136, -7813, 7426, 18722, -6770, 4589, 19855, -1632, 5184, 16481, -998, 10350, 17612, -3861, 11470, 22701, -2225, 9085, 24346, -29842, 10202, 21473, -28722, 15264, 22081, -32160, 15939, 27168, -31013, 13026, 28290, -25874, 12634, 28023, -26338, 13611, 24974, -25116, -13937, 26040, -28593, -13280, 30722, -27601, -16192, 31977, -22336, -15203, 29530, -20612, -9465, 30496, -23607, 15501, 26865, -27507, -16212, 27734, -26587, -15356, 28726, -25211, -13841, 30084, -24141, -12988, 31019, -23287, -11996, 32459, -21790, -10549, 662, -20911, -9609, 1548, -19925, -8254, 2988, -18485, -7262, 3904, -17551, -6361, 4924, -18223, -6944, 4246, -17171, -6074, 5229, 16388, -5065, 6614, 17888, -3695, 7660, 72, 21581, -22495, -1021, 20691, -23320, -1919, 19666, -24267, -2794, -32725, -11224, 10330, 31852, -12065, 9469, 30855, -13076, 8455, 29994, -14010, 7533, 29068, -14965, 6600, 28154, -15860, 5759, 27165, -16863, 4763, 26280, -17698, 3777, 25348, -18648, 2890, 24352, 10, 11354, 30827, -31733, -12233, 31954, -30472, -11110, 24751, -29358, -9868, 25877, -20108, -8751, 27112, -19052, -15947, 28160, -17861, -14824, 4659, -16678, -13591, 5768, -23874, -12465, 6950, -22738, -3313, 8189, -21578, -2109, 6868, 20181, -19802, -6503, 19059, -16811, -7651, 22033, -17410, -4143, 21431, -30827, -5278, 24350, -31945, -2283, 22756, -29544, -3847, 5745, 16990, -16844, -5630, 18175, -19751, -4428, -9356, -28863, 29473, 98, 21589, -22490, -1018, 20709, -23342, -1810, 19602, -24219, -2751, 18724, -25293, -3596, 17874, -26199, -4722, 16999, -27128, -5582, 15877, -27919, -6443, 15013, -29037, -15578, 14164, -29915, -8434, 13300, -30732, -9287, 12176, -31643, -10232, 11369, -32703, -11103, 10382, 31907, -12152, 9569, 31058, -13005, 8453, 30196, -13944, 7657, 29121, -14815, 6665 };
    private static int ˏ = 0;
    private static long ॱ;
    
    static
    {
      ˊ = 1;
      ॱ = -3733796713839766496L;
    }
    
    private ˊ() {}
    
    private static String ˊ(int paramInt1, char paramChar, int paramInt2)
    {
      break label92;
      int i = 1;
      break label95;
      label8:
      i = j;
      break label31;
      label14:
      break label24;
      label17:
      int j = 82;
      for (;;)
      {
        label24:
        char[] arrayOfChar = new char[paramInt2];
        i = 0;
        label31:
        if (i >= paramInt2)
        {
          break label79;
          label42:
          i = 0;
          break label95;
        }
        for (;;)
        {
          arrayOfChar[i] = ((char)(int)(ˋ[(paramInt1 + i)] ^ i * ॱ ^ paramChar));
          j = i + 1;
          break label123;
          label79:
          j = 21;
          break label150;
          i = j;
          break label31;
          break label17;
          label92:
          break label193;
          label95:
          switch (i)
          {
          }
          break label8;
          label123:
          i = ˊ + 43;
          ˏ = i % 128;
          if (i % 2 != 0) {
            break label42;
          }
          break;
          label150:
          switch (j)
          {
          }
        }
        return new String(arrayOfChar);
        label193:
        i = ˏ + 81;
        ˊ = i % 128;
        if (i % 2 == 0) {
          break label14;
        }
      }
    }
    
    /* Error */
    private final String ˊ(xG paramXG, String paramString1, String paramString2)
    {
      // Byte code:
      //   0: goto +115 -> 115
      //   3: goto +546 -> 549
      //   6: goto +154 -> 160
      //   9: aload_2
      //   10: aload 5
      //   12: invokevirtual 383	java/lang/StringBuilder:append	(Ljava/lang/String;)Ljava/lang/StringBuilder;
      //   15: getstatic 388	o/Gv:ˊ	Lo/Gv$If;
      //   18: invokevirtual 394	o/Gv$If:ˎ	()Lo/Gv;
      //   21: invokevirtual 398	o/Gv:ˏॱ	()Ljava/lang/String;
      //   24: invokevirtual 383	java/lang/StringBuilder:append	(Ljava/lang/String;)Ljava/lang/StringBuilder;
      //   27: aload 5
      //   29: invokevirtual 383	java/lang/StringBuilder:append	(Ljava/lang/String;)Ljava/lang/StringBuilder;
      //   32: astore_2
      //   33: goto +17 -> 50
      //   36: astore_1
      //   37: aload_1
      //   38: invokevirtual 404	java/lang/Throwable:getCause	()Ljava/lang/Throwable;
      //   41: astore_2
      //   42: aload_2
      //   43: ifnull +5 -> 48
      //   46: aload_2
      //   47: athrow
      //   48: aload_1
      //   49: athrow
      //   50: iconst_3
      //   51: iconst_0
      //   52: ldc_w 405
      //   55: invokestatic 410	o/O:ˋ	(IIC)Ljava/lang/Object;
      //   58: checkcast 412	java/lang/Class
      //   61: ldc_w 413
      //   64: aconst_null
      //   65: invokevirtual 417	java/lang/Class:getMethod	(Ljava/lang/String;[Ljava/lang/Class;)Ljava/lang/reflect/Method;
      //   68: aconst_null
      //   69: aconst_null
      //   70: invokevirtual 423	java/lang/reflect/Method:invoke	(Ljava/lang/Object;[Ljava/lang/Object;)Ljava/lang/Object;
      //   73: astore_3
      //   74: goto +375 -> 449
      //   77: aload 6
      //   79: aload 5
      //   81: invokevirtual 383	java/lang/StringBuilder:append	(Ljava/lang/String;)Ljava/lang/StringBuilder;
      //   84: aload_0
      //   85: checkcast 2	o/Ip$ˊ
      //   88: aload_1
      //   89: invokevirtual 428	o/xG:ॱ	()Lo/xH;
      //   92: invokespecial 431	o/Ip$ˊ:ˊ	(Lo/xH;)Ljava/lang/String;
      //   95: invokevirtual 383	java/lang/StringBuilder:append	(Ljava/lang/String;)Ljava/lang/StringBuilder;
      //   98: aload 5
      //   100: invokevirtual 383	java/lang/StringBuilder:append	(Ljava/lang/String;)Ljava/lang/StringBuilder;
      //   103: astore 6
      //   105: goto +13 -> 118
      //   108: bipush 71
      //   110: istore 4
      //   112: goto +237 -> 349
      //   115: goto +296 -> 411
      //   118: getstatic 19	o/Ip$ˊ:ˊ	I
      //   121: istore 4
      //   123: iload 4
      //   125: bipush 101
      //   127: ixor
      //   128: iload 4
      //   130: bipush 101
      //   132: iand
      //   133: iconst_1
      //   134: ishl
      //   135: iadd
      //   136: istore 4
      //   138: iload 4
      //   140: sipush 128
      //   143: irem
      //   144: putstatic 17	o/Ip$ˊ:ˏ	I
      //   147: iload 4
      //   149: iconst_2
      //   150: irem
      //   151: ifeq +6 -> 157
      //   154: goto +388 -> 542
      //   157: goto -49 -> 108
      //   160: aload_2
      //   161: aload_1
      //   162: invokevirtual 434	o/xG:ˋ	()Lo/xy;
      //   165: invokevirtual 438	o/xy:ˎ	()Ljava/lang/String;
      //   168: invokevirtual 383	java/lang/StringBuilder:append	(Ljava/lang/String;)Ljava/lang/StringBuilder;
      //   171: sipush 279
      //   174: ldc_w 439
      //   177: iconst_3
      //   178: invokestatic 441	o/Ip$ˊ:ˊ	(ICI)Ljava/lang/String;
      //   181: invokevirtual 444	java/lang/String:intern	()Ljava/lang/String;
      //   184: invokevirtual 383	java/lang/StringBuilder:append	(Ljava/lang/String;)Ljava/lang/StringBuilder;
      //   187: astore_2
      //   188: aload_1
      //   189: invokevirtual 434	o/xG:ˋ	()Lo/xy;
      //   192: astore_3
      //   193: getstatic 17	o/Ip$ˊ:ˏ	I
      //   196: istore 4
      //   198: iload 4
      //   200: bipush 46
      //   202: ixor
      //   203: iload 4
      //   205: bipush 46
      //   207: iand
      //   208: iconst_1
      //   209: ishl
      //   210: iadd
      //   211: iconst_1
      //   212: isub
      //   213: istore 4
      //   215: iload 4
      //   217: sipush 128
      //   220: irem
      //   221: putstatic 19	o/Ip$ˊ:ˊ	I
      //   224: iload 4
      //   226: iconst_2
      //   227: irem
      //   228: ifne +6 -> 234
      //   231: goto -228 -> 3
      //   234: goto +315 -> 549
      //   237: aload_3
      //   238: sipush 253
      //   241: sipush 6800
      //   244: bipush 19
      //   246: invokestatic 441	o/Ip$ˊ:ˊ	(ICI)Ljava/lang/String;
      //   249: invokevirtual 444	java/lang/String:intern	()Ljava/lang/String;
      //   252: invokestatic 449	o/vq:ˋ	(Ljava/lang/Object;Ljava/lang/String;)V
      //   255: goto +17 -> 272
      //   258: astore_1
      //   259: aload_1
      //   260: invokevirtual 404	java/lang/Throwable:getCause	()Ljava/lang/Throwable;
      //   263: astore_2
      //   264: aload_2
      //   265: ifnull +5 -> 270
      //   268: aload_2
      //   269: athrow
      //   270: aload_1
      //   271: athrow
      //   272: iconst_3
      //   273: iconst_0
      //   274: ldc_w 405
      //   277: invokestatic 410	o/O:ˋ	(IIC)Ljava/lang/Object;
      //   280: checkcast 412	java/lang/Class
      //   283: ldc_w 450
      //   286: aconst_null
      //   287: invokevirtual 417	java/lang/Class:getMethod	(Ljava/lang/String;[Ljava/lang/Class;)Ljava/lang/reflect/Method;
      //   290: aload_3
      //   291: aconst_null
      //   292: invokevirtual 423	java/lang/reflect/Method:invoke	(Ljava/lang/Object;[Ljava/lang/Object;)Ljava/lang/Object;
      //   295: checkcast 357	java/lang/String
      //   298: astore_3
      //   299: aload_2
      //   300: aload_3
      //   301: invokevirtual 383	java/lang/StringBuilder:append	(Ljava/lang/String;)Ljava/lang/StringBuilder;
      //   304: aload 5
      //   306: invokevirtual 383	java/lang/StringBuilder:append	(Ljava/lang/String;)Ljava/lang/StringBuilder;
      //   309: astore_2
      //   310: goto +493 -> 803
      //   313: aload_2
      //   314: sipush 272
      //   317: sipush 5680
      //   320: bipush 64
      //   322: invokestatic 441	o/Ip$ˊ:ˊ	(ICI)Ljava/lang/String;
      //   325: invokevirtual 444	java/lang/String:intern	()Ljava/lang/String;
      //   328: invokevirtual 383	java/lang/StringBuilder:append	(Ljava/lang/String;)Ljava/lang/StringBuilder;
      //   331: aload 5
      //   333: invokevirtual 383	java/lang/StringBuilder:append	(Ljava/lang/String;)Ljava/lang/StringBuilder;
      //   336: iconst_2
      //   337: invokevirtual 453	java/lang/StringBuilder:append	(I)Ljava/lang/StringBuilder;
      //   340: aload 5
      //   342: invokevirtual 383	java/lang/StringBuilder:append	(Ljava/lang/String;)Ljava/lang/StringBuilder;
      //   345: astore_2
      //   346: goto +302 -> 648
      //   349: iload 4
      //   351: lookupswitch	default:+25->376, 70:+391->742, 71:+254->605
      //   376: goto +366 -> 742
      //   379: goto -302 -> 77
      //   382: iload 4
      //   384: tableswitch	default:+24->408, 0:+-71->313, 1:+322->706
      //   408: goto +298 -> 706
      //   411: sipush 221
      //   414: iconst_0
      //   415: iconst_1
      //   416: invokestatic 441	o/Ip$ˊ:ˊ	(ICI)Ljava/lang/String;
      //   419: invokevirtual 444	java/lang/String:intern	()Ljava/lang/String;
      //   422: astore 5
      //   424: new 379	java/lang/StringBuilder
      //   427: dup
      //   428: invokespecial 454	java/lang/StringBuilder:<init>	()V
      //   431: aload_1
      //   432: invokevirtual 455	o/xG:ˎ	()Ljava/lang/String;
      //   435: invokevirtual 383	java/lang/StringBuilder:append	(Ljava/lang/String;)Ljava/lang/StringBuilder;
      //   438: astore 6
      //   440: goto +49 -> 489
      //   443: iconst_1
      //   444: istore 4
      //   446: goto -64 -> 382
      //   449: getstatic 19	o/Ip$ˊ:ˊ	I
      //   452: bipush 56
      //   454: iadd
      //   455: iconst_0
      //   456: iadd
      //   457: iconst_1
      //   458: isub
      //   459: istore 4
      //   461: iload 4
      //   463: sipush 128
      //   466: irem
      //   467: putstatic 17	o/Ip$ˊ:ˏ	I
      //   470: iload 4
      //   472: iconst_2
      //   473: irem
      //   474: ifeq +6 -> 480
      //   477: goto +6 -> 483
      //   480: goto -243 -> 237
      //   483: goto -246 -> 237
      //   486: astore_1
      //   487: aload_1
      //   488: athrow
      //   489: getstatic 19	o/Ip$ˊ:ˊ	I
      //   492: istore 4
      //   494: iload 4
      //   496: bipush 112
      //   498: ior
      //   499: iconst_1
      //   500: ishl
      //   501: iload 4
      //   503: bipush 112
      //   505: ixor
      //   506: isub
      //   507: istore 4
      //   509: iload 4
      //   511: iconst_m1
      //   512: iand
      //   513: iload 4
      //   515: iconst_m1
      //   516: ior
      //   517: iadd
      //   518: istore 4
      //   520: iload 4
      //   522: sipush 128
      //   525: irem
      //   526: putstatic 17	o/Ip$ˊ:ˏ	I
      //   529: iload 4
      //   531: iconst_2
      //   532: irem
      //   533: ifeq +6 -> 539
      //   536: goto -157 -> 379
      //   539: goto -462 -> 77
      //   542: bipush 70
      //   544: istore 4
      //   546: goto -197 -> 349
      //   549: aload_2
      //   550: aload_3
      //   551: invokevirtual 458	o/xy:ॱॱ	()Ljava/lang/String;
      //   554: invokevirtual 383	java/lang/StringBuilder:append	(Ljava/lang/String;)Ljava/lang/StringBuilder;
      //   557: aload_1
      //   558: invokevirtual 434	o/xG:ˋ	()Lo/xy;
      //   561: invokevirtual 461	o/xy:ʼ	()Ljava/lang/String;
      //   564: invokevirtual 383	java/lang/StringBuilder:append	(Ljava/lang/String;)Ljava/lang/StringBuilder;
      //   567: invokevirtual 464	java/lang/StringBuilder:toString	()Ljava/lang/String;
      //   570: astore_1
      //   571: getstatic 17	o/Ip$ˊ:ˏ	I
      //   574: bipush 88
      //   576: iadd
      //   577: iconst_1
      //   578: isub
      //   579: istore 4
      //   581: iload 4
      //   583: sipush 128
      //   586: irem
      //   587: putstatic 19	o/Ip$ˊ:ˊ	I
      //   590: iload 4
      //   592: iconst_2
      //   593: irem
      //   594: ifne +6 -> 600
      //   597: goto +49 -> 646
      //   600: aload_1
      //   601: areturn
      //   602: astore_1
      //   603: aload_1
      //   604: athrow
      //   605: aload 6
      //   607: sipush 222
      //   610: sipush 11323
      //   613: bipush 31
      //   615: invokestatic 441	o/Ip$ˊ:ˊ	(ICI)Ljava/lang/String;
      //   618: invokevirtual 444	java/lang/String:intern	()Ljava/lang/String;
      //   621: invokevirtual 383	java/lang/StringBuilder:append	(Ljava/lang/String;)Ljava/lang/StringBuilder;
      //   624: aload 5
      //   626: invokevirtual 383	java/lang/StringBuilder:append	(Ljava/lang/String;)Ljava/lang/StringBuilder;
      //   629: aload_3
      //   630: invokevirtual 383	java/lang/StringBuilder:append	(Ljava/lang/String;)Ljava/lang/StringBuilder;
      //   633: aload 5
      //   635: invokevirtual 383	java/lang/StringBuilder:append	(Ljava/lang/String;)Ljava/lang/StringBuilder;
      //   638: aload_2
      //   639: invokevirtual 383	java/lang/StringBuilder:append	(Ljava/lang/String;)Ljava/lang/StringBuilder;
      //   642: astore_2
      //   643: goto -634 -> 9
      //   646: aload_1
      //   647: areturn
      //   648: getstatic 17	o/Ip$ˊ:ˏ	I
      //   651: istore 4
      //   653: iload 4
      //   655: bipush 41
      //   657: iand
      //   658: iload 4
      //   660: bipush 41
      //   662: ixor
      //   663: iload 4
      //   665: bipush 41
      //   667: iand
      //   668: ior
      //   669: ineg
      //   670: ineg
      //   671: iconst_m1
      //   672: ixor
      //   673: isub
      //   674: iconst_1
      //   675: isub
      //   676: istore 4
      //   678: iload 4
      //   680: sipush 128
      //   683: irem
      //   684: putstatic 19	o/Ip$ˊ:ˊ	I
      //   687: iload 4
      //   689: iconst_2
      //   690: irem
      //   691: ifne +6 -> 697
      //   694: goto -688 -> 6
      //   697: goto -537 -> 160
      //   700: iconst_0
      //   701: istore 4
      //   703: goto -321 -> 382
      //   706: aload_2
      //   707: sipush 272
      //   710: sipush 5680
      //   713: bipush 7
      //   715: invokestatic 441	o/Ip$ˊ:ˊ	(ICI)Ljava/lang/String;
      //   718: invokevirtual 444	java/lang/String:intern	()Ljava/lang/String;
      //   721: invokevirtual 383	java/lang/StringBuilder:append	(Ljava/lang/String;)Ljava/lang/StringBuilder;
      //   724: aload 5
      //   726: invokevirtual 383	java/lang/StringBuilder:append	(Ljava/lang/String;)Ljava/lang/StringBuilder;
      //   729: iconst_5
      //   730: invokevirtual 453	java/lang/StringBuilder:append	(I)Ljava/lang/StringBuilder;
      //   733: aload 5
      //   735: invokevirtual 383	java/lang/StringBuilder:append	(Ljava/lang/String;)Ljava/lang/StringBuilder;
      //   738: astore_2
      //   739: goto -91 -> 648
      //   742: sipush 222
      //   745: sipush 11323
      //   748: bipush 55
      //   750: invokestatic 441	o/Ip$ˊ:ˊ	(ICI)Ljava/lang/String;
      //   753: astore 7
      //   755: aload 7
      //   757: invokevirtual 444	java/lang/String:intern	()Ljava/lang/String;
      //   760: astore 7
      //   762: aload 6
      //   764: aload 7
      //   766: invokevirtual 383	java/lang/StringBuilder:append	(Ljava/lang/String;)Ljava/lang/StringBuilder;
      //   769: astore 6
      //   771: aload 6
      //   773: aload 5
      //   775: invokevirtual 383	java/lang/StringBuilder:append	(Ljava/lang/String;)Ljava/lang/StringBuilder;
      //   778: astore 6
      //   780: aload 6
      //   782: aload_3
      //   783: invokevirtual 383	java/lang/StringBuilder:append	(Ljava/lang/String;)Ljava/lang/StringBuilder;
      //   786: astore_3
      //   787: aload_3
      //   788: aload 5
      //   790: invokevirtual 383	java/lang/StringBuilder:append	(Ljava/lang/String;)Ljava/lang/StringBuilder;
      //   793: astore_3
      //   794: aload_3
      //   795: aload_2
      //   796: invokevirtual 383	java/lang/StringBuilder:append	(Ljava/lang/String;)Ljava/lang/StringBuilder;
      //   799: astore_2
      //   800: goto -791 -> 9
      //   803: getstatic 17	o/Ip$ˊ:ˏ	I
      //   806: istore 4
      //   808: iload 4
      //   810: bipush 37
      //   812: ixor
      //   813: iload 4
      //   815: bipush 37
      //   817: iand
      //   818: iconst_1
      //   819: ishl
      //   820: iadd
      //   821: istore 4
      //   823: iload 4
      //   825: sipush 128
      //   828: irem
      //   829: putstatic 19	o/Ip$ˊ:ˊ	I
      //   832: iload 4
      //   834: iconst_2
      //   835: irem
      //   836: ifne +6 -> 842
      //   839: goto -139 -> 700
      //   842: goto -399 -> 443
      // Local variable table:
      //   start	length	slot	name	signature
      //   0	845	0	this	ˊ
      //   0	845	1	paramXG	xG
      //   0	845	2	paramString1	String
      //   0	845	3	paramString2	String
      //   110	726	4	i	int
      //   10	779	5	str1	String
      //   77	704	6	localStringBuilder	StringBuilder
      //   753	12	7	str2	String
      // Exception table:
      //   from	to	target	type
      //   50	74	36	finally
      //   272	299	258	finally
      //   118	123	486	java/lang/NullPointerException
      //   138	147	486	java/lang/IllegalArgumentException
      //   549	571	486	java/lang/UnsupportedOperationException
      //   755	762	486	java/lang/ClassCastException
      //   762	771	486	java/lang/ClassCastException
      //   771	780	486	java/lang/ClassCastException
      //   771	780	486	java/lang/ArrayStoreException
      //   780	787	486	java/lang/ClassCastException
      //   787	794	486	java/lang/ClassCastException
      //   794	800	486	java/lang/ClassCastException
      //   742	755	602	java/lang/NullPointerException
      //   755	762	602	java/lang/NullPointerException
      //   762	771	602	java/lang/NullPointerException
      //   762	771	602	java/lang/RuntimeException
      //   771	780	602	java/lang/NullPointerException
      //   771	780	602	java/lang/RuntimeException
      //   780	787	602	java/lang/NullPointerException
      //   780	787	602	java/lang/RuntimeException
      //   780	787	602	java/lang/IllegalStateException
      //   787	794	602	java/lang/NullPointerException
      //   787	794	602	java/lang/RuntimeException
      //   787	794	602	java/lang/IllegalStateException
      //   794	800	602	java/lang/NullPointerException
      //   794	800	602	java/lang/RuntimeException
      //   794	800	602	java/lang/IllegalStateException
      //   794	800	602	java/lang/NumberFormatException
    }
    
    /* Error */
    private final String ˊ(xH paramXH)
    {
      // Byte code:
      //   0: goto +975 -> 975
      //   3: bipush 83
      //   5: istore_2
      //   6: goto +937 -> 943
      //   9: getstatic 17	o/Ip$ˊ:ˏ	I
      //   12: istore_3
      //   13: iload_3
      //   14: bipush 75
      //   16: ior
      //   17: iconst_1
      //   18: ishl
      //   19: istore_2
      //   20: iload_3
      //   21: iconst_m1
      //   22: ixor
      //   23: bipush 75
      //   25: iand
      //   26: iload_3
      //   27: bipush -76
      //   29: iand
      //   30: ior
      //   31: istore_3
      //   32: iload_3
      //   33: ineg
      //   34: iload_2
      //   35: ixor
      //   36: iload_2
      //   37: iload_3
      //   38: ineg
      //   39: iand
      //   40: iconst_1
      //   41: ishl
      //   42: iadd
      //   43: istore_2
      //   44: iload_2
      //   45: sipush 128
      //   48: irem
      //   49: putstatic 19	o/Ip$ˊ:ˊ	I
      //   52: iload_2
      //   53: iconst_2
      //   54: irem
      //   55: ifne +6 -> 61
      //   58: goto +160 -> 218
      //   61: goto +1031 -> 1092
      //   64: aload 6
      //   66: aload_1
      //   67: invokevirtual 473	o/yW:ˋ	(Ljava/nio/charset/Charset;)Ljava/lang/String;
      //   70: astore_1
      //   71: sipush 282
      //   74: iconst_0
      //   75: bipush 50
      //   77: invokestatic 441	o/Ip$ˊ:ˊ	(ICI)Ljava/lang/String;
      //   80: astore 6
      //   82: getstatic 19	o/Ip$ˊ:ˊ	I
      //   85: bipush 107
      //   87: iadd
      //   88: iconst_1
      //   89: isub
      //   90: istore_2
      //   91: iload_2
      //   92: iconst_m1
      //   93: iand
      //   94: iload_2
      //   95: iconst_m1
      //   96: ior
      //   97: iadd
      //   98: istore_2
      //   99: iload_2
      //   100: sipush 128
      //   103: irem
      //   104: putstatic 17	o/Ip$ˊ:ˏ	I
      //   107: iload_2
      //   108: iconst_2
      //   109: irem
      //   110: ifeq +6 -> 116
      //   113: goto +616 -> 729
      //   116: goto +704 -> 820
      //   119: getstatic 17	o/Ip$ˊ:ˏ	I
      //   122: istore_3
      //   123: iload_3
      //   124: bipush 91
      //   126: iand
      //   127: istore_2
      //   128: iload_3
      //   129: bipush 91
      //   131: ior
      //   132: ineg
      //   133: istore_3
      //   134: iload_3
      //   135: ineg
      //   136: iload_2
      //   137: ixor
      //   138: iload_2
      //   139: iload_3
      //   140: ineg
      //   141: iand
      //   142: iconst_1
      //   143: ishl
      //   144: iadd
      //   145: istore_2
      //   146: iload_2
      //   147: sipush 128
      //   150: irem
      //   151: putstatic 19	o/Ip$ˊ:ˊ	I
      //   154: iload_2
      //   155: iconst_2
      //   156: irem
      //   157: ifne +6 -> 163
      //   160: goto +364 -> 524
      //   163: goto +434 -> 597
      //   166: bipush 60
      //   168: istore_2
      //   169: goto +15 -> 184
      //   172: aload_1
      //   173: areturn
      //   174: iconst_1
      //   175: istore_2
      //   176: goto +942 -> 1118
      //   179: iconst_0
      //   180: istore_2
      //   181: goto +426 -> 607
      //   184: iload_2
      //   185: lookupswitch	default:+27->212, 27:+205->390, 60:+650->835
      //   212: goto +623 -> 835
      //   215: goto +880 -> 1095
      //   218: goto +874 -> 1092
      //   221: goto -157 -> 64
      //   224: aload_1
      //   225: invokevirtual 478	o/xH:ˊ	()J
      //   228: lstore 4
      //   230: lload 4
      //   232: lconst_0
      //   233: lcmp
      //   234: ifeq +6 -> 240
      //   237: goto +849 -> 1086
      //   240: goto -237 -> 3
      //   243: iload_2
      //   244: tableswitch	default:+24->268, 0:+859->1103, 1:+496->740
      //   268: goto +472 -> 740
      //   271: getstatic 19	o/Ip$ˊ:ˊ	I
      //   274: istore_3
      //   275: iload_3
      //   276: bipush 123
      //   278: iand
      //   279: iconst_m1
      //   280: ixor
      //   281: iload_3
      //   282: bipush 123
      //   284: ior
      //   285: iand
      //   286: istore_2
      //   287: iload_3
      //   288: bipush 123
      //   290: iand
      //   291: iconst_1
      //   292: ishl
      //   293: ineg
      //   294: istore_3
      //   295: iload_3
      //   296: ineg
      //   297: iload_2
      //   298: ior
      //   299: iconst_1
      //   300: ishl
      //   301: iload_2
      //   302: iload_3
      //   303: ineg
      //   304: ixor
      //   305: isub
      //   306: istore_2
      //   307: iload_2
      //   308: sipush 128
      //   311: irem
      //   312: putstatic 17	o/Ip$ˊ:ˏ	I
      //   315: iload_2
      //   316: iconst_2
      //   317: irem
      //   318: ifeq +6 -> 324
      //   321: goto +58 -> 379
      //   324: goto +209 -> 533
      //   327: invokestatic 480	o/vq:ˎ	()V
      //   330: goto -321 -> 9
      //   333: iload_2
      //   334: lookupswitch	default:+26->360, 6:+-110->224, 88:+26->360
      //   360: aload_1
      //   361: invokevirtual 478	o/xH:ˊ	()J
      //   364: lstore 4
      //   366: lload 4
      //   368: lconst_0
      //   369: lcmp
      //   370: ifeq +6 -> 376
      //   373: goto -199 -> 174
      //   376: goto +705 -> 1081
      //   379: goto +154 -> 533
      //   382: aload_1
      //   383: invokestatic 485	o/zq:ॱ	(Ljava/lang/String;)Ljava/lang/String;
      //   386: astore_1
      //   387: goto +260 -> 647
      //   390: new 470	o/yW
      //   393: dup
      //   394: invokespecial 486	o/yW:<init>	()V
      //   397: astore 6
      //   399: aload 6
      //   401: checkcast 488	o/yS
      //   404: astore 7
      //   406: goto -135 -> 271
      //   409: getstatic 19	o/Ip$ˊ:ˊ	I
      //   412: istore_2
      //   413: iload_2
      //   414: bipush 17
      //   416: ixor
      //   417: iload_2
      //   418: bipush 17
      //   420: iand
      //   421: iconst_1
      //   422: ishl
      //   423: iadd
      //   424: istore_2
      //   425: iload_2
      //   426: sipush 128
      //   429: irem
      //   430: putstatic 17	o/Ip$ˊ:ˏ	I
      //   433: iload_2
      //   434: iconst_2
      //   435: irem
      //   436: ifeq +6 -> 442
      //   439: goto +152 -> 591
      //   442: goto +633 -> 1075
      //   445: iload_2
      //   446: lookupswitch	default:+26->472, 3:+-37->409, 11:+389->835
      //   472: goto -63 -> 409
      //   475: goto -148 -> 327
      //   478: iload_2
      //   479: lookupswitch	default:+25->504, 39:+209->688, 45:+-415->64
      //   504: goto -440 -> 64
      //   507: aload_1
      //   508: invokevirtual 491	o/xH:ˏ	()Lo/xC;
      //   511: astore 6
      //   513: aload 6
      //   515: ifnonnull +6 -> 521
      //   518: goto -352 -> 166
      //   521: goto +202 -> 723
      //   524: goto +73 -> 597
      //   527: bipush 97
      //   529: istore_2
      //   530: goto +482 -> 1012
      //   533: aload_1
      //   534: aload 7
      //   536: invokevirtual 494	o/xH:ॱ	(Lo/yS;)V
      //   539: aload_1
      //   540: invokevirtual 491	o/xH:ˏ	()Lo/xC;
      //   543: astore_1
      //   544: aload_1
      //   545: ifnonnull +6 -> 551
      //   548: goto +187 -> 735
      //   551: goto +427 -> 978
      //   554: iload_2
      //   555: lookupswitch	default:+25->580, 12:+121->676, 30:+488->1043
      //   580: goto +463 -> 1043
      //   583: goto +249 -> 832
      //   586: iconst_1
      //   587: istore_2
      //   588: goto +19 -> 607
      //   591: bipush 6
      //   593: istore_2
      //   594: goto -261 -> 333
      //   597: aload_1
      //   598: ifnull +6 -> 604
      //   601: goto +247 -> 848
      //   604: goto +465 -> 1069
      //   607: iload_2
      //   608: tableswitch	default:+24->632, 0:+-436->172, 1:+490->1098
      //   632: goto +466 -> 1098
      //   635: astore_1
      //   636: aload_1
      //   637: athrow
      //   638: invokestatic 480	o/vq:ˎ	()V
      //   641: aconst_null
      //   642: arraylength
      //   643: istore_2
      //   644: goto -423 -> 221
      //   647: getstatic 17	o/Ip$ˊ:ˏ	I
      //   650: bipush 74
      //   652: iadd
      //   653: iconst_1
      //   654: isub
      //   655: istore_2
      //   656: iload_2
      //   657: sipush 128
      //   660: irem
      //   661: putstatic 19	o/Ip$ˊ:ˊ	I
      //   664: iload_2
      //   665: iconst_2
      //   666: irem
      //   667: ifne +6 -> 673
      //   670: goto -84 -> 586
      //   673: goto -494 -> 179
      //   676: aload_1
      //   677: aload 6
      //   679: invokevirtual 444	java/lang/String:intern	()Ljava/lang/String;
      //   682: invokestatic 449	o/vq:ˋ	(Ljava/lang/Object;Ljava/lang/String;)V
      //   685: goto +82 -> 767
      //   688: getstatic 17	o/Ip$ˊ:ˏ	I
      //   691: bipush 58
      //   693: iadd
      //   694: iconst_1
      //   695: isub
      //   696: istore_2
      //   697: iload_2
      //   698: sipush 128
      //   701: irem
      //   702: putstatic 19	o/Ip$ˊ:ˊ	I
      //   705: iload_2
      //   706: iconst_2
      //   707: irem
      //   708: ifne +6 -> 714
      //   711: goto +6 -> 717
      //   714: goto -187 -> 527
      //   717: bipush 87
      //   719: istore_2
      //   720: goto +292 -> 1012
      //   723: bipush 27
      //   725: istore_2
      //   726: goto -542 -> 184
      //   729: bipush 30
      //   731: istore_2
      //   732: goto -178 -> 554
      //   735: iconst_1
      //   736: istore_2
      //   737: goto -494 -> 243
      //   740: getstatic 17	o/Ip$ˊ:ˏ	I
      //   743: bipush 83
      //   745: iadd
      //   746: istore_2
      //   747: iload_2
      //   748: sipush 128
      //   751: irem
      //   752: putstatic 19	o/Ip$ˊ:ˊ	I
      //   755: iload_2
      //   756: iconst_2
      //   757: irem
      //   758: ifne +6 -> 764
      //   761: goto -286 -> 475
      //   764: goto -437 -> 327
      //   767: getstatic 17	o/Ip$ˊ:ˏ	I
      //   770: istore_2
      //   771: iload_2
      //   772: bipush 79
      //   774: ixor
      //   775: iload_2
      //   776: bipush 79
      //   778: iand
      //   779: ior
      //   780: iconst_1
      //   781: ishl
      //   782: iload_2
      //   783: bipush -80
      //   785: iand
      //   786: iload_2
      //   787: iconst_m1
      //   788: ixor
      //   789: bipush 79
      //   791: iand
      //   792: ior
      //   793: ineg
      //   794: iconst_m1
      //   795: ixor
      //   796: isub
      //   797: iconst_1
      //   798: isub
      //   799: istore_2
      //   800: iload_2
      //   801: sipush 128
      //   804: irem
      //   805: putstatic 19	o/Ip$ˊ:ˊ	I
      //   808: iload_2
      //   809: iconst_2
      //   810: irem
      //   811: ifne +6 -> 817
      //   814: goto -231 -> 583
      //   817: goto +15 -> 832
      //   820: bipush 12
      //   822: istore_2
      //   823: goto -269 -> 554
      //   826: invokestatic 480	o/vq:ˎ	()V
      //   829: goto -608 -> 221
      //   832: goto -450 -> 382
      //   835: ldc_w 496
      //   838: astore_1
      //   839: goto +144 -> 983
      //   842: bipush 45
      //   844: istore_2
      //   845: goto -367 -> 478
      //   848: iconst_3
      //   849: istore_2
      //   850: goto -405 -> 445
      //   853: astore 6
      //   855: ldc_w 498
      //   858: invokevirtual 501	java/lang/Class:getSimpleName	()Ljava/lang/String;
      //   861: astore_1
      //   862: aload 6
      //   864: invokevirtual 504	java/io/IOException:getMessage	()Ljava/lang/String;
      //   867: astore 6
      //   869: goto +20 -> 889
      //   872: astore 6
      //   874: aload 6
      //   876: invokevirtual 404	java/lang/Throwable:getCause	()Ljava/lang/Throwable;
      //   879: astore_1
      //   880: aload_1
      //   881: ifnull +5 -> 886
      //   884: aload_1
      //   885: athrow
      //   886: aload 6
      //   888: athrow
      //   889: iconst_4
      //   890: bipush 42
      //   892: ldc_w 505
      //   895: invokestatic 410	o/O:ˋ	(IIC)Ljava/lang/Object;
      //   898: checkcast 412	java/lang/Class
      //   901: ldc_w 506
      //   904: iconst_2
      //   905: anewarray 412	java/lang/Class
      //   908: dup
      //   909: iconst_0
      //   910: ldc_w 357
      //   913: aastore
      //   914: dup
      //   915: iconst_1
      //   916: ldc_w 357
      //   919: aastore
      //   920: invokevirtual 417	java/lang/Class:getMethod	(Ljava/lang/String;[Ljava/lang/Class;)Ljava/lang/reflect/Method;
      //   923: aconst_null
      //   924: iconst_2
      //   925: anewarray 4	java/lang/Object
      //   928: dup
      //   929: iconst_0
      //   930: aload_1
      //   931: aastore
      //   932: dup
      //   933: iconst_1
      //   934: aload 6
      //   936: aastore
      //   937: invokevirtual 423	java/lang/reflect/Method:invoke	(Ljava/lang/Object;[Ljava/lang/Object;)Ljava/lang/Object;
      //   940: pop
      //   941: aconst_null
      //   942: areturn
      //   943: iload_2
      //   944: lookupswitch	default:+28->972, 83:+-109->835, 92:+-437->507
      //   972: goto -137 -> 835
      //   975: goto -856 -> 119
      //   978: iconst_0
      //   979: istore_2
      //   980: goto -737 -> 243
      //   983: getstatic 19	o/Ip$ˊ:ˊ	I
      //   986: bipush 14
      //   988: iadd
      //   989: iconst_1
      //   990: isub
      //   991: istore_2
      //   992: iload_2
      //   993: sipush 128
      //   996: irem
      //   997: putstatic 17	o/Ip$ˊ:ˏ	I
      //   1000: iload_2
      //   1001: iconst_2
      //   1002: irem
      //   1003: ifeq +6 -> 1009
      //   1006: goto -791 -> 215
      //   1009: goto +86 -> 1095
      //   1012: iload_2
      //   1013: lookupswitch	default:+27->1040, 87:+-375->638, 97:+-187->826
      //   1040: goto -402 -> 638
      //   1043: aload_1
      //   1044: aload 6
      //   1046: invokevirtual 444	java/lang/String:intern	()Ljava/lang/String;
      //   1049: invokestatic 449	o/vq:ˋ	(Ljava/lang/Object;Ljava/lang/String;)V
      //   1052: new 363	java/lang/NullPointerException
      //   1055: dup
      //   1056: invokespecial 507	java/lang/NullPointerException:<init>	()V
      //   1059: athrow
      //   1060: bipush 39
      //   1062: istore_2
      //   1063: goto -585 -> 478
      //   1066: astore_1
      //   1067: aload_1
      //   1068: athrow
      //   1069: bipush 11
      //   1071: istore_2
      //   1072: goto -627 -> 445
      //   1075: bipush 88
      //   1077: istore_2
      //   1078: goto -745 -> 333
      //   1081: iconst_0
      //   1082: istore_2
      //   1083: goto +35 -> 1118
      //   1086: bipush 92
      //   1088: istore_2
      //   1089: goto -146 -> 943
      //   1092: goto +11 -> 1103
      //   1095: goto -713 -> 382
      //   1098: aconst_null
      //   1099: arraylength
      //   1100: istore_2
      //   1101: aload_1
      //   1102: areturn
      //   1103: aload_1
      //   1104: invokevirtual 512	o/xC:ˎ	()Ljava/nio/charset/Charset;
      //   1107: astore_1
      //   1108: aload_1
      //   1109: ifnonnull +6 -> 1115
      //   1112: goto -52 -> 1060
      //   1115: goto -273 -> 842
      //   1118: iload_2
      //   1119: tableswitch	default:+21->1140, 0:+-284->835, 1:+-612->507
      //   1140: goto -305 -> 835
      // Local variable table:
      //   start	length	slot	name	signature
      //   0	1143	0	this	ˊ
      //   0	1143	1	paramXH	xH
      //   5	1114	2	i	int
      //   12	291	3	j	int
      //   228	139	4	l	long
      //   64	614	6	localObject1	Object
      //   853	10	6	localIOException	java.io.IOException
      //   867	1	6	str	String
      //   872	173	6	localObject2	Object
      //   404	131	7	localYS	yS
      // Exception table:
      //   from	to	target	type
      //   119	123	635	java/lang/NullPointerException
      //   146	154	635	java/lang/NullPointerException
      //   146	154	635	java/lang/IllegalArgumentException
      //   271	275	635	java/lang/IllegalStateException
      //   307	315	635	java/lang/IllegalStateException
      //   656	664	635	java/lang/IllegalStateException
      //   767	771	635	java/lang/NumberFormatException
      //   800	808	635	java/lang/NumberFormatException
      //   800	808	635	java/lang/NullPointerException
      //   64	82	853	java/io/IOException
      //   224	230	853	java/io/IOException
      //   327	330	853	java/io/IOException
      //   360	366	853	java/io/IOException
      //   382	387	853	java/io/IOException
      //   390	406	853	java/io/IOException
      //   507	513	853	java/io/IOException
      //   533	544	853	java/io/IOException
      //   638	644	853	java/io/IOException
      //   676	685	853	java/io/IOException
      //   826	829	853	java/io/IOException
      //   1043	1060	853	java/io/IOException
      //   1103	1108	853	java/io/IOException
      //   889	941	872	finally
      //   307	315	1066	java/lang/Exception
      //   409	413	1066	java/lang/UnsupportedOperationException
      //   425	433	1066	java/lang/NullPointerException
      //   647	656	1066	java/lang/IllegalArgumentException
      //   656	664	1066	java/lang/IllegalArgumentException
    }
    
    /* Error */
    private final String ॱ(String paramString1, String paramString2)
    {
      // Byte code:
      //   0: goto +1780 -> 1780
      //   3: getstatic 17	o/Ip$ˊ:ˏ	I
      //   6: bipush 110
      //   8: iadd
      //   9: iconst_1
      //   10: isub
      //   11: istore_3
      //   12: iload_3
      //   13: sipush 128
      //   16: irem
      //   17: putstatic 19	o/Ip$ˊ:ˊ	I
      //   20: iload_3
      //   21: iconst_2
      //   22: irem
      //   23: ifne +6 -> 29
      //   26: goto +1449 -> 1475
      //   29: goto +801 -> 830
      //   32: getstatic 19	o/Ip$ˊ:ˊ	I
      //   35: istore_3
      //   36: iload_3
      //   37: bipush -86
      //   39: iand
      //   40: iload_3
      //   41: iconst_m1
      //   42: ixor
      //   43: bipush 85
      //   45: iand
      //   46: ior
      //   47: iload_3
      //   48: bipush 85
      //   50: iand
      //   51: iconst_1
      //   52: ishl
      //   53: iadd
      //   54: istore_3
      //   55: iload_3
      //   56: sipush 128
      //   59: irem
      //   60: putstatic 17	o/Ip$ˊ:ˏ	I
      //   63: iload_3
      //   64: iconst_2
      //   65: irem
      //   66: ifeq +6 -> 72
      //   69: goto +1706 -> 1775
      //   72: goto +539 -> 611
      //   75: aload_2
      //   76: sipush 139
      //   79: sipush 15525
      //   82: bipush 11
      //   84: invokestatic 441	o/Ip$ˊ:ˊ	(ICI)Ljava/lang/String;
      //   87: invokevirtual 444	java/lang/String:intern	()Ljava/lang/String;
      //   90: invokestatic 449	o/vq:ˋ	(Ljava/lang/Object;Ljava/lang/String;)V
      //   93: goto +523 -> 616
      //   96: astore_1
      //   97: aload_1
      //   98: athrow
      //   99: iload_3
      //   100: tableswitch	default:+24->124, 0:+317->417, 1:+1571->1671
      //   124: goto +1547 -> 1671
      //   127: iconst_1
      //   128: istore_3
      //   129: goto -30 -> 99
      //   132: aload_1
      //   133: invokestatic 522	o/zl:ॱ	([B)[B
      //   136: astore_1
      //   137: sipush 193
      //   140: istore_3
      //   141: goto +1656 -> 1797
      //   144: bipush 37
      //   146: sipush 11219
      //   149: bipush 7
      //   151: invokestatic 441	o/Ip$ˊ:ˊ	(ICI)Ljava/lang/String;
      //   154: invokevirtual 444	java/lang/String:intern	()Ljava/lang/String;
      //   157: astore 9
      //   159: goto +201 -> 360
      //   162: getstatic 17	o/Ip$ˊ:ˏ	I
      //   165: istore 4
      //   167: iload 4
      //   169: bipush 103
      //   171: iand
      //   172: istore_3
      //   173: iload 4
      //   175: bipush 103
      //   177: ixor
      //   178: iload 4
      //   180: bipush 103
      //   182: iand
      //   183: ior
      //   184: ineg
      //   185: istore 4
      //   187: iload 4
      //   189: ineg
      //   190: iload_3
      //   191: ior
      //   192: iconst_1
      //   193: ishl
      //   194: iload_3
      //   195: iload 4
      //   197: ineg
      //   198: ixor
      //   199: isub
      //   200: istore_3
      //   201: iload_3
      //   202: sipush 128
      //   205: irem
      //   206: putstatic 19	o/Ip$ˊ:ˊ	I
      //   209: iload_3
      //   210: iconst_2
      //   211: irem
      //   212: ifne +6 -> 218
      //   215: goto +634 -> 849
      //   218: goto +1421 -> 1639
      //   221: goto +1042 -> 1263
      //   224: iload_3
      //   225: lookupswitch	default:+27->252, 4:+1052->1277, 38:+745->970
      //   252: goto +718 -> 970
      //   255: getstatic 17	o/Ip$ˊ:ˏ	I
      //   258: istore_3
      //   259: iload_3
      //   260: bipush 46
      //   262: ior
      //   263: iconst_1
      //   264: ishl
      //   265: iload_3
      //   266: bipush 46
      //   268: ixor
      //   269: isub
      //   270: istore_3
      //   271: iload_3
      //   272: iconst_m1
      //   273: ior
      //   274: iconst_1
      //   275: ishl
      //   276: iload_3
      //   277: iconst_m1
      //   278: ixor
      //   279: isub
      //   280: istore_3
      //   281: iload_3
      //   282: sipush 128
      //   285: irem
      //   286: putstatic 19	o/Ip$ˊ:ˊ	I
      //   289: iload_3
      //   290: iconst_2
      //   291: irem
      //   292: ifne +6 -> 298
      //   295: goto +691 -> 986
      //   298: goto +1321 -> 1619
      //   301: iload_3
      //   302: lookupswitch	default:+26->328, 94:+929->1231, 99:+1323->1625
      //   328: goto +903 -> 1231
      //   331: new 524	o/uH
      //   334: dup
      //   335: bipush 86
      //   337: ldc_w 525
      //   340: bipush 53
      //   342: invokestatic 441	o/Ip$ˊ:ˊ	(ICI)Ljava/lang/String;
      //   345: invokevirtual 444	java/lang/String:intern	()Ljava/lang/String;
      //   348: invokespecial 528	o/uH:<init>	(Ljava/lang/String;)V
      //   351: athrow
      //   352: iconst_0
      //   353: istore_3
      //   354: goto +1393 -> 1747
      //   357: goto +292 -> 649
      //   360: getstatic 17	o/Ip$ˊ:ˏ	I
      //   363: istore 4
      //   365: iload 4
      //   367: bipush 113
      //   369: iand
      //   370: istore_3
      //   371: iload 4
      //   373: bipush 113
      //   375: ixor
      //   376: iload 4
      //   378: bipush 113
      //   380: iand
      //   381: ior
      //   382: ineg
      //   383: istore 4
      //   385: iload 4
      //   387: ineg
      //   388: iload_3
      //   389: iand
      //   390: iload_3
      //   391: iload 4
      //   393: ineg
      //   394: ior
      //   395: iadd
      //   396: istore_3
      //   397: iload_3
      //   398: sipush 128
      //   401: irem
      //   402: putstatic 19	o/Ip$ˊ:ˊ	I
      //   405: iload_3
      //   406: iconst_2
      //   407: irem
      //   408: ifne +6 -> 414
      //   411: goto +433 -> 844
      //   414: goto +762 -> 1176
      //   417: aload_1
      //   418: ldc_w 496
      //   421: invokestatic 531	o/vq:ˊ	(Ljava/lang/Object;Ljava/lang/Object;)Z
      //   424: istore 6
      //   426: iconst_2
      //   427: iconst_0
      //   428: idiv
      //   429: istore_3
      //   430: iload 6
      //   432: ifeq +6 -> 438
      //   435: goto +427 -> 862
      //   438: goto +964 -> 1402
      //   441: astore_1
      //   442: aload_1
      //   443: athrow
      //   444: new 533	javax/crypto/spec/SecretKeySpec
      //   447: dup
      //   448: aload 9
      //   450: aload_1
      //   451: invokespecial 536	javax/crypto/spec/SecretKeySpec:<init>	([BLjava/lang/String;)V
      //   454: astore 9
      //   456: sipush 183
      //   459: iconst_0
      //   460: bipush 10
      //   462: invokestatic 441	o/Ip$ˊ:ˊ	(ICI)Ljava/lang/String;
      //   465: invokevirtual 444	java/lang/String:intern	()Ljava/lang/String;
      //   468: invokestatic 542	javax/crypto/Mac:getInstance	(Ljava/lang/String;)Ljavax/crypto/Mac;
      //   471: astore_1
      //   472: aload_1
      //   473: aload 9
      //   475: checkcast 544	java/security/Key
      //   478: invokevirtual 548	javax/crypto/Mac:init	(Ljava/security/Key;)V
      //   481: aload_2
      //   482: ifnonnull +6 -> 488
      //   485: goto -154 -> 331
      //   488: goto +635 -> 1123
      //   491: astore_2
      //   492: ldc_w 498
      //   495: invokevirtual 501	java/lang/Class:getSimpleName	()Ljava/lang/String;
      //   498: astore_1
      //   499: aload_2
      //   500: invokevirtual 549	java/security/InvalidKeyException:getMessage	()Ljava/lang/String;
      //   503: astore_2
      //   504: goto +17 -> 521
      //   507: astore_1
      //   508: aload_1
      //   509: invokevirtual 404	java/lang/Throwable:getCause	()Ljava/lang/Throwable;
      //   512: astore_2
      //   513: aload_2
      //   514: ifnull +5 -> 519
      //   517: aload_2
      //   518: athrow
      //   519: aload_1
      //   520: athrow
      //   521: iconst_4
      //   522: bipush 42
      //   524: ldc_w 505
      //   527: invokestatic 410	o/O:ˋ	(IIC)Ljava/lang/Object;
      //   530: checkcast 412	java/lang/Class
      //   533: ldc_w 506
      //   536: iconst_2
      //   537: anewarray 412	java/lang/Class
      //   540: dup
      //   541: iconst_0
      //   542: ldc_w 357
      //   545: aastore
      //   546: dup
      //   547: iconst_1
      //   548: ldc_w 357
      //   551: aastore
      //   552: invokevirtual 417	java/lang/Class:getMethod	(Ljava/lang/String;[Ljava/lang/Class;)Ljava/lang/reflect/Method;
      //   555: aconst_null
      //   556: iconst_2
      //   557: anewarray 4	java/lang/Object
      //   560: dup
      //   561: iconst_0
      //   562: aload_1
      //   563: aastore
      //   564: dup
      //   565: iconst_1
      //   566: aload_2
      //   567: aastore
      //   568: invokevirtual 423	java/lang/reflect/Method:invoke	(Ljava/lang/Object;[Ljava/lang/Object;)Ljava/lang/Object;
      //   571: pop
      //   572: aload 7
      //   574: astore_1
      //   575: goto +688 -> 1263
      //   578: iload 4
      //   580: lookupswitch	default:+28->608, 25:+873->1453, 69:+45->625
      //   608: goto +845 -> 1453
      //   611: iconst_1
      //   612: istore_3
      //   613: goto +1074 -> 1687
      //   616: aload_1
      //   617: aload_2
      //   618: invokevirtual 552	javax/crypto/Mac:doFinal	([B)[B
      //   621: astore_1
      //   622: goto -590 -> 32
      //   625: aload_1
      //   626: iload_3
      //   627: ldc_w 553
      //   630: bipush 28
      //   632: invokestatic 441	o/Ip$ˊ:ˊ	(ICI)Ljava/lang/String;
      //   635: invokevirtual 444	java/lang/String:intern	()Ljava/lang/String;
      //   638: invokestatic 449	o/vq:ˋ	(Ljava/lang/Object;Ljava/lang/String;)V
      //   641: goto +1142 -> 1783
      //   644: iconst_1
      //   645: istore_3
      //   646: goto +999 -> 1645
      //   649: aload 9
      //   651: sipush 139
      //   654: sipush 15525
      //   657: bipush 44
      //   659: invokestatic 441	o/Ip$ˊ:ˊ	(ICI)Ljava/lang/String;
      //   662: invokevirtual 444	java/lang/String:intern	()Ljava/lang/String;
      //   665: invokestatic 449	o/vq:ˋ	(Ljava/lang/Object;Ljava/lang/String;)V
      //   668: goto +668 -> 1336
      //   671: getstatic 19	o/Ip$ˊ:ˊ	I
      //   674: istore 4
      //   676: iload 4
      //   678: bipush 39
      //   680: ixor
      //   681: iload 4
      //   683: bipush 39
      //   685: iand
      //   686: ior
      //   687: iconst_1
      //   688: ishl
      //   689: istore_3
      //   690: iload 4
      //   692: bipush 39
      //   694: ior
      //   695: iload 4
      //   697: bipush 39
      //   699: iand
      //   700: iconst_m1
      //   701: ixor
      //   702: iand
      //   703: istore 4
      //   705: iload 4
      //   707: ineg
      //   708: iload_3
      //   709: iand
      //   710: iload_3
      //   711: iload 4
      //   713: ineg
      //   714: ior
      //   715: iadd
      //   716: istore_3
      //   717: iload_3
      //   718: sipush 128
      //   721: irem
      //   722: putstatic 17	o/Ip$ˊ:ˏ	I
      //   725: iload_3
      //   726: iconst_2
      //   727: irem
      //   728: ifeq +6 -> 734
      //   731: goto +107 -> 838
      //   734: goto +710 -> 1444
      //   737: bipush 90
      //   739: iconst_0
      //   740: bipush 77
      //   742: invokestatic 441	o/Ip$ˊ:ˊ	(ICI)Ljava/lang/String;
      //   745: invokevirtual 444	java/lang/String:intern	()Ljava/lang/String;
      //   748: astore 7
      //   750: goto +287 -> 1037
      //   753: bipush 32
      //   755: iconst_0
      //   756: iconst_5
      //   757: invokestatic 441	o/Ip$ˊ:ˊ	(ICI)Ljava/lang/String;
      //   760: astore 7
      //   762: aload 7
      //   764: invokevirtual 444	java/lang/String:intern	()Ljava/lang/String;
      //   767: astore 7
      //   769: aload 7
      //   771: invokestatic 559	java/nio/charset/Charset:forName	(Ljava/lang/String;)Ljava/nio/charset/Charset;
      //   774: astore 8
      //   776: goto +303 -> 1079
      //   779: getstatic 17	o/Ip$ˊ:ˏ	I
      //   782: istore_3
      //   783: iload_3
      //   784: bipush 109
      //   786: ior
      //   787: iconst_1
      //   788: ishl
      //   789: iload_3
      //   790: bipush -110
      //   792: iand
      //   793: iload_3
      //   794: iconst_m1
      //   795: ixor
      //   796: bipush 109
      //   798: iand
      //   799: ior
      //   800: ineg
      //   801: iconst_m1
      //   802: ixor
      //   803: isub
      //   804: iconst_1
      //   805: isub
      //   806: istore_3
      //   807: iload_3
      //   808: sipush 128
      //   811: irem
      //   812: putstatic 19	o/Ip$ˊ:ˊ	I
      //   815: iload_3
      //   816: iconst_2
      //   817: irem
      //   818: ifne +6 -> 824
      //   821: goto +629 -> 1450
      //   824: goto -680 -> 144
      //   827: goto +436 -> 1263
      //   830: goto -668 -> 162
      //   833: iconst_4
      //   834: istore_3
      //   835: goto -611 -> 224
      //   838: bipush 30
      //   840: istore_3
      //   841: goto +749 -> 1590
      //   844: iconst_0
      //   845: istore_3
      //   846: goto +392 -> 1238
      //   849: bipush 38
      //   851: istore_3
      //   852: goto +350 -> 1202
      //   855: bipush 25
      //   857: istore 4
      //   859: goto -281 -> 578
      //   862: bipush 76
      //   864: istore_3
      //   865: goto +850 -> 1715
      //   868: goto -115 -> 753
      //   871: new 524	o/uH
      //   874: dup
      //   875: bipush 86
      //   877: ldc_w 525
      //   880: bipush 53
      //   882: invokestatic 441	o/Ip$ˊ:ˊ	(ICI)Ljava/lang/String;
      //   885: invokevirtual 444	java/lang/String:intern	()Ljava/lang/String;
      //   888: invokespecial 528	o/uH:<init>	(Ljava/lang/String;)V
      //   891: athrow
      //   892: goto +17 -> 909
      //   895: astore_1
      //   896: aload_1
      //   897: invokevirtual 404	java/lang/Throwable:getCause	()Ljava/lang/Throwable;
      //   900: astore_2
      //   901: aload_2
      //   902: ifnull +5 -> 907
      //   905: aload_2
      //   906: athrow
      //   907: aload_1
      //   908: athrow
      //   909: iconst_4
      //   910: bipush 42
      //   912: ldc_w 505
      //   915: invokestatic 410	o/O:ˋ	(IIC)Ljava/lang/Object;
      //   918: checkcast 412	java/lang/Class
      //   921: ldc_w 506
      //   924: iconst_2
      //   925: anewarray 412	java/lang/Class
      //   928: dup
      //   929: iconst_0
      //   930: ldc_w 357
      //   933: aastore
      //   934: dup
      //   935: iconst_1
      //   936: ldc_w 357
      //   939: aastore
      //   940: invokevirtual 417	java/lang/Class:getMethod	(Ljava/lang/String;[Ljava/lang/Class;)Ljava/lang/reflect/Method;
      //   943: aconst_null
      //   944: iconst_2
      //   945: anewarray 4	java/lang/Object
      //   948: dup
      //   949: iconst_0
      //   950: aload 9
      //   952: aastore
      //   953: dup
      //   954: iconst_1
      //   955: aload 7
      //   957: aastore
      //   958: invokevirtual 423	java/lang/reflect/Method:invoke	(Ljava/lang/Object;[Ljava/lang/Object;)Ljava/lang/Object;
      //   961: pop
      //   962: goto -291 -> 671
      //   965: iconst_1
      //   966: istore_3
      //   967: goto +780 -> 1747
      //   970: sipush 13035
      //   973: iconst_0
      //   974: bipush 123
      //   976: invokestatic 441	o/Ip$ˊ:ˊ	(ICI)Ljava/lang/String;
      //   979: invokevirtual 444	java/lang/String:intern	()Ljava/lang/String;
      //   982: astore_1
      //   983: goto -539 -> 444
      //   986: bipush 94
      //   988: istore_3
      //   989: goto -688 -> 301
      //   992: getstatic 19	o/Ip$ˊ:ˊ	I
      //   995: istore_3
      //   996: iload_3
      //   997: bipush 77
      //   999: iand
      //   1000: iload_3
      //   1001: bipush 77
      //   1003: ixor
      //   1004: iload_3
      //   1005: bipush 77
      //   1007: iand
      //   1008: ior
      //   1009: ineg
      //   1010: ineg
      //   1011: iconst_m1
      //   1012: ixor
      //   1013: isub
      //   1014: iconst_1
      //   1015: isub
      //   1016: istore_3
      //   1017: iload_3
      //   1018: sipush 128
      //   1021: irem
      //   1022: putstatic 17	o/Ip$ˊ:ˏ	I
      //   1025: iload_3
      //   1026: iconst_2
      //   1027: irem
      //   1028: ifeq +6 -> 1034
      //   1031: goto -163 -> 868
      //   1034: goto -281 -> 753
      //   1037: getstatic 19	o/Ip$ˊ:ˊ	I
      //   1040: istore_3
      //   1041: iload_3
      //   1042: bipush 47
      //   1044: iand
      //   1045: iload_3
      //   1046: bipush 47
      //   1048: ior
      //   1049: iadd
      //   1050: istore_3
      //   1051: iload_3
      //   1052: sipush 128
      //   1055: irem
      //   1056: putstatic 17	o/Ip$ˊ:ˏ	I
      //   1059: iload_3
      //   1060: iconst_2
      //   1061: irem
      //   1062: ifeq +6 -> 1068
      //   1065: goto +268 -> 1333
      //   1068: goto -176 -> 892
      //   1071: iconst_0
      //   1072: istore_3
      //   1073: goto -974 -> 99
      //   1076: goto +332 -> 1408
      //   1079: getstatic 19	o/Ip$ˊ:ˊ	I
      //   1082: istore_3
      //   1083: iload_3
      //   1084: bipush 124
      //   1086: ior
      //   1087: iconst_1
      //   1088: ishl
      //   1089: iload_3
      //   1090: bipush 124
      //   1092: ixor
      //   1093: isub
      //   1094: iconst_1
      //   1095: isub
      //   1096: istore_3
      //   1097: iload_3
      //   1098: sipush 128
      //   1101: irem
      //   1102: putstatic 17	o/Ip$ˊ:ˏ	I
      //   1105: iload_3
      //   1106: iconst_2
      //   1107: irem
      //   1108: ifeq +6 -> 1114
      //   1111: goto -40 -> 1071
      //   1114: goto -987 -> 127
      //   1117: bipush 38
      //   1119: istore_3
      //   1120: goto -896 -> 224
      //   1123: aload_2
      //   1124: aload 8
      //   1126: invokevirtual 563	java/lang/String:getBytes	(Ljava/nio/charset/Charset;)[B
      //   1129: astore_2
      //   1130: goto +163 -> 1293
      //   1133: getstatic 19	o/Ip$ˊ:ˊ	I
      //   1136: istore_3
      //   1137: iload_3
      //   1138: bipush 77
      //   1140: iand
      //   1141: iload_3
      //   1142: bipush 77
      //   1144: iand
      //   1145: iload_3
      //   1146: bipush 77
      //   1148: ixor
      //   1149: ior
      //   1150: iconst_m1
      //   1151: ixor
      //   1152: isub
      //   1153: iconst_1
      //   1154: isub
      //   1155: istore_3
      //   1156: iload_3
      //   1157: sipush 128
      //   1160: irem
      //   1161: putstatic 17	o/Ip$ˊ:ˏ	I
      //   1164: iload_3
      //   1165: iconst_2
      //   1166: irem
      //   1167: ifeq +6 -> 1173
      //   1170: goto -813 -> 357
      //   1173: goto -524 -> 649
      //   1176: iconst_1
      //   1177: istore_3
      //   1178: goto +60 -> 1238
      //   1181: aload_2
      //   1182: sipush 139
      //   1185: sipush 15525
      //   1188: bipush 44
      //   1190: invokestatic 441	o/Ip$ˊ:ˊ	(ICI)Ljava/lang/String;
      //   1193: invokevirtual 444	java/lang/String:intern	()Ljava/lang/String;
      //   1196: invokestatic 449	o/vq:ˋ	(Ljava/lang/Object;Ljava/lang/String;)V
      //   1199: goto -583 -> 616
      //   1202: iload_3
      //   1203: lookupswitch	default:+25->1228, 10:+-376->827, 38:+-982->221
      //   1228: goto -1007 -> 221
      //   1231: bipush 35
      //   1233: iconst_0
      //   1234: idiv
      //   1235: istore_3
      //   1236: aload_1
      //   1237: areturn
      //   1238: iload_3
      //   1239: tableswitch	default:+21->1260, 0:+-502->737, 1:+331->1570
      //   1260: goto -523 -> 737
      //   1263: goto -1008 -> 255
      //   1266: aload_1
      //   1267: aload 8
      //   1269: invokevirtual 563	java/lang/String:getBytes	(Ljava/nio/charset/Charset;)[B
      //   1272: astore 9
      //   1274: goto -141 -> 1133
      //   1277: sipush 183
      //   1280: iconst_0
      //   1281: bipush 10
      //   1283: invokestatic 441	o/Ip$ˊ:ˊ	(ICI)Ljava/lang/String;
      //   1286: invokevirtual 444	java/lang/String:intern	()Ljava/lang/String;
      //   1289: astore_1
      //   1290: goto -846 -> 444
      //   1293: getstatic 17	o/Ip$ˊ:ˏ	I
      //   1296: istore_3
      //   1297: iload_3
      //   1298: bipush 121
      //   1300: ixor
      //   1301: iload_3
      //   1302: bipush 121
      //   1304: iand
      //   1305: iconst_1
      //   1306: ishl
      //   1307: iconst_m1
      //   1308: ixor
      //   1309: isub
      //   1310: iconst_1
      //   1311: isub
      //   1312: istore_3
      //   1313: iload_3
      //   1314: sipush 128
      //   1317: irem
      //   1318: putstatic 19	o/Ip$ˊ:ˊ	I
      //   1321: iload_3
      //   1322: iconst_2
      //   1323: irem
      //   1324: ifne +6 -> 1330
      //   1327: goto -683 -> 644
      //   1330: goto +235 -> 1565
      //   1333: goto -441 -> 892
      //   1336: getstatic 17	o/Ip$ˊ:ˏ	I
      //   1339: istore 4
      //   1341: iload 4
      //   1343: bipush 43
      //   1345: ixor
      //   1346: iload 4
      //   1348: bipush 43
      //   1350: iand
      //   1351: ior
      //   1352: iconst_1
      //   1353: ishl
      //   1354: istore_3
      //   1355: iload 4
      //   1357: bipush 43
      //   1359: ior
      //   1360: iload 4
      //   1362: bipush 43
      //   1364: iand
      //   1365: iconst_m1
      //   1366: ixor
      //   1367: iand
      //   1368: istore 4
      //   1370: iload 4
      //   1372: ineg
      //   1373: iload_3
      //   1374: iand
      //   1375: iload_3
      //   1376: iload 4
      //   1378: ineg
      //   1379: ior
      //   1380: iadd
      //   1381: istore_3
      //   1382: iload_3
      //   1383: sipush 128
      //   1386: irem
      //   1387: putstatic 19	o/Ip$ˊ:ˊ	I
      //   1390: iload_3
      //   1391: iconst_2
      //   1392: irem
      //   1393: ifne +6 -> 1399
      //   1396: goto -279 -> 1117
      //   1399: goto -566 -> 833
      //   1402: bipush 68
      //   1404: istore_3
      //   1405: goto +310 -> 1715
      //   1408: aconst_null
      //   1409: astore 7
      //   1411: aload 8
      //   1413: bipush 75
      //   1415: iconst_0
      //   1416: bipush 11
      //   1418: invokestatic 441	o/Ip$ˊ:ˊ	(ICI)Ljava/lang/String;
      //   1421: invokevirtual 444	java/lang/String:intern	()Ljava/lang/String;
      //   1424: invokestatic 449	o/vq:ˋ	(Ljava/lang/Object;Ljava/lang/String;)V
      //   1427: aload_1
      //   1428: ifnonnull +6 -> 1434
      //   1431: goto -560 -> 871
      //   1434: goto -168 -> 1266
      //   1437: bipush 69
      //   1439: istore 4
      //   1441: goto -863 -> 578
      //   1444: bipush 18
      //   1446: istore_3
      //   1447: goto +143 -> 1590
      //   1450: goto -1306 -> 144
      //   1453: aload_1
      //   1454: iload_3
      //   1455: ldc_w 553
      //   1458: bipush 106
      //   1460: invokestatic 441	o/Ip$ˊ:ˊ	(ICI)Ljava/lang/String;
      //   1463: invokevirtual 444	java/lang/String:intern	()Ljava/lang/String;
      //   1466: invokestatic 449	o/vq:ˋ	(Ljava/lang/Object;Ljava/lang/String;)V
      //   1469: goto +314 -> 1783
      //   1472: goto -64 -> 1408
      //   1475: goto -645 -> 830
      //   1478: astore_2
      //   1479: ldc_w 498
      //   1482: invokevirtual 501	java/lang/Class:getSimpleName	()Ljava/lang/String;
      //   1485: astore_1
      //   1486: aload_2
      //   1487: invokevirtual 564	java/security/NoSuchAlgorithmException:getMessage	()Ljava/lang/String;
      //   1490: astore_2
      //   1491: goto +17 -> 1508
      //   1494: astore_1
      //   1495: aload_1
      //   1496: invokevirtual 404	java/lang/Throwable:getCause	()Ljava/lang/Throwable;
      //   1499: astore_2
      //   1500: aload_2
      //   1501: ifnull +5 -> 1506
      //   1504: aload_2
      //   1505: athrow
      //   1506: aload_1
      //   1507: athrow
      //   1508: iconst_4
      //   1509: bipush 42
      //   1511: ldc_w 505
      //   1514: invokestatic 410	o/O:ˋ	(IIC)Ljava/lang/Object;
      //   1517: checkcast 412	java/lang/Class
      //   1520: ldc_w 506
      //   1523: iconst_2
      //   1524: anewarray 412	java/lang/Class
      //   1527: dup
      //   1528: iconst_0
      //   1529: ldc_w 357
      //   1532: aastore
      //   1533: dup
      //   1534: iconst_1
      //   1535: ldc_w 357
      //   1538: aastore
      //   1539: invokevirtual 417	java/lang/Class:getMethod	(Ljava/lang/String;[Ljava/lang/Class;)Ljava/lang/reflect/Method;
      //   1542: aconst_null
      //   1543: iconst_2
      //   1544: anewarray 4	java/lang/Object
      //   1547: dup
      //   1548: iconst_0
      //   1549: aload_1
      //   1550: aastore
      //   1551: dup
      //   1552: iconst_1
      //   1553: aload_2
      //   1554: aastore
      //   1555: invokevirtual 423	java/lang/reflect/Method:invoke	(Ljava/lang/Object;[Ljava/lang/Object;)Ljava/lang/Object;
      //   1558: pop
      //   1559: aload 7
      //   1561: astore_1
      //   1562: goto -299 -> 1263
      //   1565: iconst_0
      //   1566: istore_3
      //   1567: goto +78 -> 1645
      //   1570: bipush 44
      //   1572: iconst_0
      //   1573: bipush 31
      //   1575: invokestatic 441	o/Ip$ˊ:ˊ	(ICI)Ljava/lang/String;
      //   1578: astore 7
      //   1580: aload 7
      //   1582: invokevirtual 444	java/lang/String:intern	()Ljava/lang/String;
      //   1585: astore 7
      //   1587: goto -550 -> 1037
      //   1590: iload_3
      //   1591: lookupswitch	default:+25->1616, 18:+-119->1472, 30:+-515->1076
      //   1616: goto -540 -> 1076
      //   1619: bipush 99
      //   1621: istore_3
      //   1622: goto -1321 -> 301
      //   1625: aload_1
      //   1626: areturn
      //   1627: aload_1
      //   1628: invokestatic 522	o/zl:ॱ	([B)[B
      //   1631: astore_1
      //   1632: sipush 21522
      //   1635: istore_3
      //   1636: goto +161 -> 1797
      //   1639: bipush 10
      //   1641: istore_3
      //   1642: goto -440 -> 1202
      //   1645: iload_3
      //   1646: tableswitch	default:+22->1668, 0:+-465->1181, 1:+-1571->75
      //   1668: goto -487 -> 1181
      //   1671: aload_1
      //   1672: ldc_w 496
      //   1675: invokestatic 531	o/vq:ˊ	(Ljava/lang/Object;Ljava/lang/Object;)Z
      //   1678: ifeq +6 -> 1684
      //   1681: goto -1329 -> 352
      //   1684: goto -719 -> 965
      //   1687: iload_3
      //   1688: tableswitch	default:+24->1712, 0:+-61->1627, 1:+-1556->132
      //   1712: goto -1580 -> 132
      //   1715: iload_3
      //   1716: lookupswitch	default:+28->1744, 68:+-308->1408, 76:+-937->779
      //   1744: goto -336 -> 1408
      //   1747: iload_3
      //   1748: tableswitch	default:+24->1772, 0:+-969->779, 1:+-340->1408
      //   1772: goto -993 -> 779
      //   1775: iconst_0
      //   1776: istore_3
      //   1777: goto -90 -> 1687
      //   1780: goto -788 -> 992
      //   1783: new 357	java/lang/String
      //   1786: dup
      //   1787: aload_1
      //   1788: aload 8
      //   1790: invokespecial 567	java/lang/String:<init>	([BLjava/nio/charset/Charset;)V
      //   1793: astore_1
      //   1794: goto -1791 -> 3
      //   1797: getstatic 19	o/Ip$ˊ:ˊ	I
      //   1800: istore 5
      //   1802: iload 5
      //   1804: iconst_5
      //   1805: iand
      //   1806: istore 4
      //   1808: iload 5
      //   1810: iconst_5
      //   1811: ior
      //   1812: istore 5
      //   1814: iload 4
      //   1816: iload 5
      //   1818: ixor
      //   1819: iload 4
      //   1821: iload 5
      //   1823: iand
      //   1824: iconst_1
      //   1825: ishl
      //   1826: iadd
      //   1827: istore 4
      //   1829: iload 4
      //   1831: sipush 128
      //   1834: irem
      //   1835: putstatic 17	o/Ip$ˊ:ˏ	I
      //   1838: iload 4
      //   1840: iconst_2
      //   1841: irem
      //   1842: ifeq +6 -> 1848
      //   1845: goto -990 -> 855
      //   1848: goto -411 -> 1437
      // Local variable table:
      //   start	length	slot	name	signature
      //   0	1851	0	this	ˊ
      //   0	1851	1	paramString1	String
      //   0	1851	2	paramString2	String
      //   11	1766	3	i	int
      //   165	1677	4	j	int
      //   1800	24	5	k	int
      //   424	7	6	bool	boolean
      //   572	1014	7	str	String
      //   774	1015	8	localCharset	java.nio.charset.Charset
      //   157	1116	9	localObject	Object
      // Exception table:
      //   from	to	target	type
      //   753	762	96	java/lang/NumberFormatException
      //   769	776	96	java/lang/ClassCastException
      //   992	996	96	java/lang/ClassCastException
      //   1017	1025	96	java/lang/ClassCastException
      //   1580	1587	96	java/lang/RuntimeException
      //   360	365	441	java/lang/ClassCastException
      //   397	405	441	java/lang/ClassCastException
      //   762	769	441	java/lang/NullPointerException
      //   1570	1580	441	java/lang/ClassCastException
      //   1580	1587	441	java/lang/ClassCastException
      //   75	93	491	java/security/InvalidKeyException
      //   132	137	491	java/security/InvalidKeyException
      //   331	352	491	java/security/InvalidKeyException
      //   444	481	491	java/security/InvalidKeyException
      //   616	622	491	java/security/InvalidKeyException
      //   625	641	491	java/security/InvalidKeyException
      //   649	668	491	java/security/InvalidKeyException
      //   871	892	491	java/security/InvalidKeyException
      //   970	983	491	java/security/InvalidKeyException
      //   1123	1130	491	java/security/InvalidKeyException
      //   1181	1199	491	java/security/InvalidKeyException
      //   1266	1274	491	java/security/InvalidKeyException
      //   1277	1290	491	java/security/InvalidKeyException
      //   1411	1427	491	java/security/InvalidKeyException
      //   1453	1469	491	java/security/InvalidKeyException
      //   1627	1632	491	java/security/InvalidKeyException
      //   1783	1794	491	java/security/InvalidKeyException
      //   521	572	507	finally
      //   909	962	895	finally
      //   75	93	1478	java/security/NoSuchAlgorithmException
      //   132	137	1478	java/security/NoSuchAlgorithmException
      //   331	352	1478	java/security/NoSuchAlgorithmException
      //   444	481	1478	java/security/NoSuchAlgorithmException
      //   616	622	1478	java/security/NoSuchAlgorithmException
      //   625	641	1478	java/security/NoSuchAlgorithmException
      //   649	668	1478	java/security/NoSuchAlgorithmException
      //   871	892	1478	java/security/NoSuchAlgorithmException
      //   970	983	1478	java/security/NoSuchAlgorithmException
      //   1123	1130	1478	java/security/NoSuchAlgorithmException
      //   1181	1199	1478	java/security/NoSuchAlgorithmException
      //   1266	1274	1478	java/security/NoSuchAlgorithmException
      //   1277	1290	1478	java/security/NoSuchAlgorithmException
      //   1411	1427	1478	java/security/NoSuchAlgorithmException
      //   1453	1469	1478	java/security/NoSuchAlgorithmException
      //   1627	1632	1478	java/security/NoSuchAlgorithmException
      //   1783	1794	1478	java/security/NoSuchAlgorithmException
      //   1508	1559	1494	finally
    }
    
    /* Error */
    public final String ˏ(xG paramXG, String paramString1, String paramString2, boolean paramBoolean)
    {
      // Byte code:
      //   0: goto +134 -> 134
      //   3: goto +769 -> 772
      //   6: getstatic 17	o/Ip$ˊ:ˏ	I
      //   9: istore 6
      //   11: iload 6
      //   13: bipush 37
      //   15: ixor
      //   16: iload 6
      //   18: bipush 37
      //   20: iand
      //   21: ior
      //   22: iconst_1
      //   23: ishl
      //   24: istore 5
      //   26: iload 6
      //   28: bipush -38
      //   30: iand
      //   31: iload 6
      //   33: iconst_m1
      //   34: ixor
      //   35: bipush 37
      //   37: iand
      //   38: ior
      //   39: ineg
      //   40: istore 6
      //   42: iload 5
      //   44: iload 6
      //   46: ixor
      //   47: iload 5
      //   49: iload 6
      //   51: iand
      //   52: iconst_1
      //   53: ishl
      //   54: iadd
      //   55: istore 5
      //   57: iload 5
      //   59: sipush 128
      //   62: irem
      //   63: putstatic 19	o/Ip$ˊ:ˊ	I
      //   66: iload 5
      //   68: iconst_2
      //   69: irem
      //   70: ifne +6 -> 76
      //   73: goto +138 -> 211
      //   76: goto +86 -> 162
      //   79: getstatic 19	o/Ip$ˊ:ˊ	I
      //   82: istore 5
      //   84: iload 5
      //   86: bipush 11
      //   88: ior
      //   89: iconst_1
      //   90: ishl
      //   91: iload 5
      //   93: bipush 11
      //   95: ior
      //   96: iload 5
      //   98: bipush 11
      //   100: iand
      //   101: iconst_m1
      //   102: ixor
      //   103: iand
      //   104: ineg
      //   105: iconst_m1
      //   106: ixor
      //   107: isub
      //   108: iconst_1
      //   109: isub
      //   110: istore 5
      //   112: iload 5
      //   114: sipush 128
      //   117: irem
      //   118: putstatic 17	o/Ip$ˊ:ˏ	I
      //   121: iload 5
      //   123: iconst_2
      //   124: irem
      //   125: ifeq +6 -> 131
      //   128: goto +142 -> 270
      //   131: goto +851 -> 982
      //   134: goto +335 -> 469
      //   137: iconst_1
      //   138: istore 5
      //   140: goto +652 -> 792
      //   143: aload_1
      //   144: aload 7
      //   146: invokestatic 572	o/vq:ˎ	(Ljava/lang/Object;Ljava/lang/String;)V
      //   149: bipush 7
      //   151: iconst_0
      //   152: bipush 13
      //   154: invokestatic 441	o/Ip$ˊ:ˊ	(ICI)Ljava/lang/String;
      //   157: astore 7
      //   159: goto -153 -> 6
      //   162: aload 7
      //   164: invokevirtual 444	java/lang/String:intern	()Ljava/lang/String;
      //   167: astore 7
      //   169: aload_2
      //   170: aload 7
      //   172: invokestatic 572	o/vq:ˎ	(Ljava/lang/Object;Ljava/lang/String;)V
      //   175: goto -96 -> 79
      //   178: iload 5
      //   180: lookupswitch	default:+28->208, 24:+157->337, 86:+546->726
      //   208: goto +129 -> 337
      //   211: goto -49 -> 162
      //   214: bipush 86
      //   216: istore 5
      //   218: goto -40 -> 178
      //   221: astore_1
      //   222: aload_1
      //   223: athrow
      //   224: getstatic 19	o/Ip$ˊ:ˊ	I
      //   227: istore 5
      //   229: iload 5
      //   231: bipush 61
      //   233: iand
      //   234: iload 5
      //   236: bipush 61
      //   238: ixor
      //   239: iload 5
      //   241: bipush 61
      //   243: iand
      //   244: ior
      //   245: iadd
      //   246: istore 5
      //   248: iload 5
      //   250: sipush 128
      //   253: irem
      //   254: putstatic 17	o/Ip$ˊ:ˏ	I
      //   257: iload 5
      //   259: iconst_2
      //   260: irem
      //   261: ifeq +6 -> 267
      //   264: goto +303 -> 567
      //   267: goto +692 -> 959
      //   270: goto +712 -> 982
      //   273: goto +499 -> 772
      //   276: bipush 25
      //   278: istore 5
      //   280: goto +362 -> 642
      //   283: astore_1
      //   284: aload_1
      //   285: athrow
      //   286: getstatic 19	o/Ip$ˊ:ˊ	I
      //   289: istore 5
      //   291: iload 5
      //   293: iconst_4
      //   294: ixor
      //   295: iload 5
      //   297: iconst_4
      //   298: iand
      //   299: iconst_1
      //   300: ishl
      //   301: iadd
      //   302: iconst_0
      //   303: iadd
      //   304: iconst_1
      //   305: isub
      //   306: istore 5
      //   308: iload 5
      //   310: sipush 128
      //   313: irem
      //   314: putstatic 17	o/Ip$ˊ:ˏ	I
      //   317: iload 5
      //   319: iconst_2
      //   320: irem
      //   321: ifeq +6 -> 327
      //   324: goto +252 -> 576
      //   327: goto +301 -> 628
      //   330: bipush 45
      //   332: istore 5
      //   334: goto +308 -> 642
      //   337: iconst_4
      //   338: sipush 362
      //   341: ldc_w 573
      //   344: invokestatic 410	o/O:ˋ	(IIC)Ljava/lang/Object;
      //   347: checkcast 412	java/lang/Class
      //   350: ldc_w 413
      //   353: invokevirtual 577	java/lang/Class:getField	(Ljava/lang/String;)Ljava/lang/reflect/Field;
      //   356: aconst_null
      //   357: invokevirtual 583	java/lang/reflect/Field:get	(Ljava/lang/Object;)Ljava/lang/Object;
      //   360: astore 7
      //   362: goto +17 -> 379
      //   365: astore_1
      //   366: aload_1
      //   367: invokevirtual 404	java/lang/Throwable:getCause	()Ljava/lang/Throwable;
      //   370: astore_2
      //   371: aload_2
      //   372: ifnull +5 -> 377
      //   375: aload_2
      //   376: athrow
      //   377: aload_1
      //   378: athrow
      //   379: bipush 7
      //   381: sipush 366
      //   384: iconst_0
      //   385: invokestatic 410	o/O:ˋ	(IIC)Ljava/lang/Object;
      //   388: checkcast 412	java/lang/Class
      //   391: ldc_w 450
      //   394: aconst_null
      //   395: invokevirtual 417	java/lang/Class:getMethod	(Ljava/lang/String;[Ljava/lang/Class;)Ljava/lang/reflect/Method;
      //   398: aload 7
      //   400: aconst_null
      //   401: invokevirtual 423	java/lang/reflect/Method:invoke	(Ljava/lang/Object;[Ljava/lang/Object;)Ljava/lang/Object;
      //   404: astore 7
      //   406: goto +17 -> 423
      //   409: astore_1
      //   410: aload_1
      //   411: invokevirtual 404	java/lang/Throwable:getCause	()Ljava/lang/Throwable;
      //   414: astore_2
      //   415: aload_2
      //   416: ifnull +5 -> 421
      //   419: aload_2
      //   420: athrow
      //   421: aload_1
      //   422: athrow
      //   423: iconst_4
      //   424: sipush 362
      //   427: ldc_w 573
      //   430: invokestatic 410	o/O:ˋ	(IIC)Ljava/lang/Object;
      //   433: checkcast 412	java/lang/Class
      //   436: ldc_w 450
      //   439: aconst_null
      //   440: invokevirtual 417	java/lang/Class:getMethod	(Ljava/lang/String;[Ljava/lang/Class;)Ljava/lang/reflect/Method;
      //   443: aload 7
      //   445: aconst_null
      //   446: invokevirtual 423	java/lang/reflect/Method:invoke	(Ljava/lang/Object;[Ljava/lang/Object;)Ljava/lang/Object;
      //   449: checkcast 357	java/lang/String
      //   452: astore 7
      //   454: goto -168 -> 286
      //   457: aload 8
      //   459: aload 7
      //   461: aload_1
      //   462: invokespecial 585	o/Ip$ˊ:ॱ	(Ljava/lang/String;Ljava/lang/String;)Ljava/lang/String;
      //   465: areturn
      //   466: goto +306 -> 772
      //   469: getstatic 19	o/Ip$ˊ:ˊ	I
      //   472: bipush 99
      //   474: iadd
      //   475: istore 5
      //   477: iload 5
      //   479: sipush 128
      //   482: irem
      //   483: putstatic 17	o/Ip$ˊ:ˏ	I
      //   486: iload 5
      //   488: iconst_2
      //   489: irem
      //   490: ifeq +6 -> 496
      //   493: goto -217 -> 276
      //   496: goto -166 -> 330
      //   499: iload 5
      //   501: lookupswitch	default:+27->528, 72:+-498->3, 80:+-35->466
      //   528: goto -62 -> 466
      //   531: getstatic 17	o/Ip$ˊ:ˏ	I
      //   534: bipush 97
      //   536: iadd
      //   537: iconst_1
      //   538: isub
      //   539: iconst_0
      //   540: iadd
      //   541: iconst_1
      //   542: isub
      //   543: istore 5
      //   545: iload 5
      //   547: sipush 128
      //   550: irem
      //   551: putstatic 19	o/Ip$ˊ:ˊ	I
      //   554: iload 5
      //   556: iconst_2
      //   557: irem
      //   558: ifne +6 -> 564
      //   561: goto +114 -> 675
      //   564: goto -421 -> 143
      //   567: iconst_1
      //   568: istore 5
      //   570: goto +13 -> 583
      //   573: goto +246 -> 819
      //   576: bipush 80
      //   578: istore 5
      //   580: goto -81 -> 499
      //   583: iload 5
      //   585: tableswitch	default:+23->608, 0:+-312->273, 1:+354->939
      //   608: goto -335 -> 273
      //   611: iconst_0
      //   612: sipush 19817
      //   615: bipush 7
      //   617: invokestatic 441	o/Ip$ˊ:ˊ	(ICI)Ljava/lang/String;
      //   620: invokevirtual 444	java/lang/String:intern	()Ljava/lang/String;
      //   623: astore 7
      //   625: goto -94 -> 531
      //   628: bipush 72
      //   630: istore 5
      //   632: goto -133 -> 499
      //   635: bipush 24
      //   637: istore 5
      //   639: goto -461 -> 178
      //   642: iload 5
      //   644: lookupswitch	default:+28->672, 25:+321->965, 45:+-33->611
      //   672: goto -61 -> 611
      //   675: goto -532 -> 143
      //   678: iconst_0
      //   679: istore 5
      //   681: goto +111 -> 792
      //   684: getstatic 17	o/Ip$ˊ:ˏ	I
      //   687: istore 5
      //   689: iload 5
      //   691: bipush 73
      //   693: ixor
      //   694: iload 5
      //   696: bipush 73
      //   698: iand
      //   699: iconst_1
      //   700: ishl
      //   701: iadd
      //   702: istore 5
      //   704: iload 5
      //   706: sipush 128
      //   709: irem
      //   710: putstatic 19	o/Ip$ˊ:ˊ	I
      //   713: iload 5
      //   715: iconst_2
      //   716: irem
      //   717: ifne +6 -> 723
      //   720: goto -42 -> 678
      //   723: goto -586 -> 137
      //   726: getstatic 19	o/Ip$ˊ:ˊ	I
      //   729: istore 5
      //   731: iload 5
      //   733: bipush 6
      //   735: ixor
      //   736: iload 5
      //   738: bipush 6
      //   740: iand
      //   741: iconst_1
      //   742: ishl
      //   743: iadd
      //   744: iconst_0
      //   745: iadd
      //   746: iconst_1
      //   747: isub
      //   748: istore 5
      //   750: iload 5
      //   752: sipush 128
      //   755: irem
      //   756: putstatic 17	o/Ip$ˊ:ˏ	I
      //   759: iload 5
      //   761: iconst_2
      //   762: irem
      //   763: ifeq +6 -> 769
      //   766: goto -193 -> 573
      //   769: goto +50 -> 819
      //   772: aload_0
      //   773: checkcast 2	o/Ip$ˊ
      //   776: astore 8
      //   778: aload_0
      //   779: checkcast 2	o/Ip$ˊ
      //   782: aload_1
      //   783: aload_2
      //   784: aload_3
      //   785: invokespecial 587	o/Ip$ˊ:ˊ	(Lo/xG;Ljava/lang/String;Ljava/lang/String;)Ljava/lang/String;
      //   788: astore_1
      //   789: goto -105 -> 684
      //   792: iload 5
      //   794: tableswitch	default:+22->816, 0:+148->942, 1:+-337->457
      //   816: goto +126 -> 942
      //   819: iconst_4
      //   820: sipush 362
      //   823: ldc_w 573
      //   826: invokestatic 410	o/O:ˋ	(IIC)Ljava/lang/Object;
      //   829: checkcast 412	java/lang/Class
      //   832: ldc_w 413
      //   835: invokevirtual 577	java/lang/Class:getField	(Ljava/lang/String;)Ljava/lang/reflect/Field;
      //   838: aconst_null
      //   839: invokevirtual 583	java/lang/reflect/Field:get	(Ljava/lang/Object;)Ljava/lang/Object;
      //   842: astore 7
      //   844: goto +17 -> 861
      //   847: astore_1
      //   848: aload_1
      //   849: invokevirtual 404	java/lang/Throwable:getCause	()Ljava/lang/Throwable;
      //   852: astore_2
      //   853: aload_2
      //   854: ifnull +5 -> 859
      //   857: aload_2
      //   858: athrow
      //   859: aload_1
      //   860: athrow
      //   861: bipush 7
      //   863: sipush 366
      //   866: iconst_0
      //   867: invokestatic 410	o/O:ˋ	(IIC)Ljava/lang/Object;
      //   870: checkcast 412	java/lang/Class
      //   873: ldc_w 450
      //   876: aconst_null
      //   877: invokevirtual 417	java/lang/Class:getMethod	(Ljava/lang/String;[Ljava/lang/Class;)Ljava/lang/reflect/Method;
      //   880: aload 7
      //   882: aconst_null
      //   883: invokevirtual 423	java/lang/reflect/Method:invoke	(Ljava/lang/Object;[Ljava/lang/Object;)Ljava/lang/Object;
      //   886: astore 7
      //   888: goto +17 -> 905
      //   891: astore_1
      //   892: aload_1
      //   893: invokevirtual 404	java/lang/Throwable:getCause	()Ljava/lang/Throwable;
      //   896: astore_2
      //   897: aload_2
      //   898: ifnull +5 -> 903
      //   901: aload_2
      //   902: athrow
      //   903: aload_1
      //   904: athrow
      //   905: iconst_4
      //   906: sipush 362
      //   909: ldc_w 573
      //   912: invokestatic 410	o/O:ˋ	(IIC)Ljava/lang/Object;
      //   915: checkcast 412	java/lang/Class
      //   918: ldc_w 588
      //   921: aconst_null
      //   922: invokevirtual 417	java/lang/Class:getMethod	(Ljava/lang/String;[Ljava/lang/Class;)Ljava/lang/reflect/Method;
      //   925: aload 7
      //   927: aconst_null
      //   928: invokevirtual 423	java/lang/reflect/Method:invoke	(Ljava/lang/Object;[Ljava/lang/Object;)Ljava/lang/Object;
      //   931: checkcast 357	java/lang/String
      //   934: astore 7
      //   936: goto -712 -> 224
      //   939: goto -167 -> 772
      //   942: aload 8
      //   944: aload 7
      //   946: aload_1
      //   947: invokespecial 585	o/Ip$ˊ:ॱ	(Ljava/lang/String;Ljava/lang/String;)Ljava/lang/String;
      //   950: astore_1
      //   951: bipush 79
      //   953: iconst_0
      //   954: idiv
      //   955: istore 5
      //   957: aload_1
      //   958: areturn
      //   959: iconst_0
      //   960: istore 5
      //   962: goto -379 -> 583
      //   965: iconst_0
      //   966: sipush 19817
      //   969: bipush 114
      //   971: invokestatic 441	o/Ip$ˊ:ˊ	(ICI)Ljava/lang/String;
      //   974: invokevirtual 444	java/lang/String:intern	()Ljava/lang/String;
      //   977: astore 7
      //   979: goto -448 -> 531
      //   982: bipush 20
      //   984: sipush 13709
      //   987: bipush 12
      //   989: invokestatic 441	o/Ip$ˊ:ˊ	(ICI)Ljava/lang/String;
      //   992: astore 7
      //   994: aload 7
      //   996: invokevirtual 444	java/lang/String:intern	()Ljava/lang/String;
      //   999: astore 7
      //   1001: aload_3
      //   1002: aload 7
      //   1004: invokestatic 572	o/vq:ˎ	(Ljava/lang/Object;Ljava/lang/String;)V
      //   1007: iload 4
      //   1009: ifeq +6 -> 1015
      //   1012: goto -798 -> 214
      //   1015: goto -380 -> 635
      // Local variable table:
      //   start	length	slot	name	signature
      //   0	1018	0	this	ˊ
      //   0	1018	1	paramXG	xG
      //   0	1018	2	paramString1	String
      //   0	1018	3	paramString2	String
      //   0	1018	4	paramBoolean	boolean
      //   24	937	5	i	int
      //   9	43	6	j	int
      //   144	859	7	localObject	Object
      //   457	486	8	localˊ	ˊ
      // Exception table:
      //   from	to	target	type
      //   469	477	221	java/lang/IllegalStateException
      //   477	486	221	java/lang/IllegalStateException
      //   684	689	221	java/lang/IndexOutOfBoundsException
      //   704	713	221	java/lang/IndexOutOfBoundsException
      //   162	169	283	java/lang/IllegalArgumentException
      //   169	175	283	java/lang/IllegalStateException
      //   477	486	283	java/lang/NumberFormatException
      //   982	994	283	java/lang/NullPointerException
      //   994	1001	283	java/lang/NullPointerException
      //   994	1001	283	java/lang/IllegalStateException
      //   1001	1007	283	java/lang/NullPointerException
      //   1001	1007	283	java/lang/NumberFormatException
      //   379	406	365	finally
      //   423	454	409	finally
      //   861	888	847	finally
      //   905	936	891	finally
    }
  }
}
