package o;

import android.annotation.SuppressLint;
import android.util.Base64;
import java.nio.charset.Charset;
import java.security.Key;
import java.security.KeyFactory;
import java.security.KeyPair;
import java.security.KeyPairGenerator;
import java.security.spec.KeySpec;
import java.security.spec.X509EncodedKeySpec;
import javax.crypto.Cipher;
import javax.crypto.spec.SecretKeySpec;

@SuppressLint({"GetInstance"})
public final class Iq
{
  private static final String ALGORITHM_DES = "DESede";
  private static final String ALGORITHM_RSA = "RSA/NONE/OAEPPADDING";
  private static final String BOUNCY_CASTLE = "BC";
  public static final ˊ Companion;
  public static final int KEY_SIZE_2048 = 2048;
  public static final String RSA = "RSA";
  private static int ˎ = 0;
  private static int ˏ = 1;
  
  /* Error */
  static
  {
    // Byte code:
    //   0: iconst_0
    //   1: putstatic 40	o/Iq:ˎ	I
    //   4: iconst_1
    //   5: putstatic 42	o/Iq:ˏ	I
    //   8: goto +57 -> 65
    //   11: astore_2
    //   12: aload_2
    //   13: athrow
    //   14: getstatic 42	o/Iq:ˏ	I
    //   17: istore_1
    //   18: iload_1
    //   19: bipush 123
    //   21: iand
    //   22: istore_0
    //   23: iload_1
    //   24: bipush 123
    //   26: iand
    //   27: iload_1
    //   28: bipush 123
    //   30: ixor
    //   31: ior
    //   32: istore_1
    //   33: iload_0
    //   34: iload_1
    //   35: ior
    //   36: iconst_1
    //   37: ishl
    //   38: iload_0
    //   39: iload_1
    //   40: ixor
    //   41: isub
    //   42: istore_0
    //   43: iload_0
    //   44: sipush 128
    //   47: irem
    //   48: putstatic 40	o/Iq:ˎ	I
    //   51: iload_0
    //   52: iconst_2
    //   53: irem
    //   54: ifeq +6 -> 60
    //   57: goto +4 -> 61
    //   60: return
    //   61: return
    //   62: astore_2
    //   63: aload_2
    //   64: athrow
    //   65: new 6	o/Iq$ˊ
    //   68: dup
    //   69: aconst_null
    //   70: invokespecial 46	o/Iq$ˊ:<init>	(Lo/vn;)V
    //   73: astore_2
    //   74: aload_2
    //   75: putstatic 48	o/Iq:Companion	Lo/Iq$ˊ;
    //   78: goto -64 -> 14
    // Local variable table:
    //   start	length	slot	name	signature
    //   22	32	0	i	int
    //   17	24	1	j	int
    //   11	2	2	localIllegalArgumentException	IllegalArgumentException
    //   62	2	2	localIndexOutOfBoundsException	IndexOutOfBoundsException
    //   73	2	2	localˊ	ˊ
    // Exception table:
    //   from	to	target	type
    //   74	78	11	java/lang/IllegalArgumentException
    //   14	18	62	java/lang/IndexOutOfBoundsException
    //   43	51	62	java/lang/IndexOutOfBoundsException
    //   43	51	62	java/lang/UnsupportedOperationException
  }
  
  public Iq() {}
  
  public static final class ˊ
  {
    private static int ˊ = 1;
    private static long ˎ = 8514256049792017964L;
    private static char[] ˏ = { 109, -6583, -13269, -19721, -26415, 32443, 25965, -2734, 4991, 14617, 18423, 28149, -29810, -28578, -16783, -15310, -7428, 2285, 5798, 16220, 17781, 25387, -30209, -26747, -16971, -9606, -8187, 3619, 5337, 13022, 22752, 68, -6551, -13301, -19743, -26412, 32441, 14306, -11808, -1144, -31382, -20612, 18715, 21188, 31983, 1704, 8273, -13698, -11201, -617, -30734, -24156, 19273, 21792, 32555, 6338, 8857, -13128, -10661, -4094, -26056, -31825, 19882, 22403, 28996, 6957, 9501, -12596, -5982, -3475, -25536, -23006, 20356, 27063, 29586, 7492, 10099, -16084, -5417, -2832, -24903, -18340, 16990, 27684, 30148, 8129, 14828, -28836, 22526, -20013, -25675, -6843, -12461, 10546, 13037, 7380, 26249, 16464, -21946, -19455, -25110, -6191, -15984, 11133, 13575, 7941, 30957, 17034, -21347, -18845, -28639, -1458, -15464, 110, -6567, -13260, -19736, -26480, 32447, 25961, 19290, 12558, 6115, -564, -7228, -13710, -20391, -27064, 31991, 25249, 18591, 12140, 5476, -1276, -7693, -14360, -21094, -27569, 31266, 24661, 18122, 11429, 4752, -1724, -8332, -14860, -21547, -28248, 30817, 24080, 17462, 10985, 4290, -2431, -8926, -15539, -22256, -28679, 30160, 23494, 16983, 10287, 3584, -2828, -9567, -16237, -22680, -29407, 29467, 22990, 16368, 9644, 3098, 24003, -17420, -28263, -4283, -15043, 8978, 14532, 5879, 27811, 19022, -24479, -16791, -26657, -4620, -13339, 8538, 16140, 5426, 29377, 18633, -22871, -17314, -26043, -4041, -13854, 10127, 15864, 7015, 28936, 20285, -23319, -32039, -26535, -2440, -13307, 9676, 957, 6554, 30538, 19821, -21727, -32568, -24837, -2841, -11652, 10339, 1591, 8152, 30100, 21501, -22175, -30889, 5500, -3237, -9950, -22545, -29232, 27573, 28773, 24136, 9245, 728, -5948, -2418, -8326, -23228, -31978, 27112, 30619, 23948, 14965, 56, -4582, -1742, 7956, 13689, 19389, 24964, -30721, 66, -6579, -13269, -19743, -26490, 32488, 25894, 19281, 12558, 6127, -553, -7296, -13707, -20460, -27109, 31981, 25261, 18561, 12157, 5424, -1278, -7691, -14421, -21057, -19450, 31330, 24605, 18122, 11443, 4755, -1716, -8399, -14876, -21632, -28168, 30790, 24145, 17455, 10989, 4226, -2348, -8926, -15498, -22229, -28721, 30187, 23482, 16981, 10256, 3653, 4314, -2313, -9071, 110, -6567, -13260, -19736, -26480, 32447, 25961, 19290, 12558, 6115, -564, -7228, -13710, -20391, -27064, 31991, 25249, 18591, 12140, 5476, -1276, -7693, -14360, -21094, -27569, 31266, 24661, 18122, 11429, 4752, -1724, -8332, -14860, -21547, -28248, 30817, 24080, 17462, 10985, 4290, -2431, -8926, -15532, -22267, -28674, 30171, 23494, 16967, 10292, 3614, -2831, -9558, -16233, 6979, -717, -10405, -22138, -31832, 26007, 32258, 20524, 10795, 3213, -6478, -1799, -12006, -21639, -29329, 26526, 31173, 21472, 13405, 3708, -8081, -1403, -9014, -18703, -28884, 24846, 31549, 23976, 14302, 2531, -7679, -15290, -8545, -20318, -30016, 25415, 17720, 24415, 12674, 2989, -4616, -14846, -10201, -19930, -6533, 86, 10800, 21634, 32471, -26438, -31889, -21160, -10394, -3606, 7120, 1416, 11369, 22085, 28672, -25863, -31571, -20852, -13953, -3286, 66, -6545, 3249, -5473, -16134, -16869, -27640, 29305, 27050, 18307, 15832, 6969, -3829, -4326, -14713, -17242, -25863, 28685, 28228, 17523, 9114, 6618, -2069, -4843, -13492, -24207, -26441, 30390, 27790, 18992, 8265, 7807, -2640, -11327, -14065, -22747, -25267, 29843, 21173, 18654, 9746, 7207, -1505, 66, -6579, -13269, -19743, -26490, 32488, 25894, 19281, 12558, 6127, -553, -7296, -13707, -20376, -27129, 31943, 25268, 18590, 12145, 5418, -1257, -7756, -14421, -21091, -19450, 31241, 24598, 18119, 11455, 4760, -1715, -8400, -14935, -21632, -28168, 30790, 24145, 17455, 10989, 4226, -2348, -8926, -15498, -22229, -28721, 30187, 23482, 16981, 10256, 3653, 23475, -17003, -26632, -5828, -15611, 9598, 16118, 4224, 27359, 19482, -23039, -18342, -28255, -5248, -12912, 10029, 14718, 4940, 29885, 20192, -24350, -17867, -25492, -2495, -12413, 8629, 99, -6587, -13272, -19732, -26411, 32430, 25894, 19280, 12559, 6090, -559, -7286, -13711, -20400, -27072, 31958, 25249, 18591, 12157, 5490, -1212, -7758, -14420, -21103, -19450, 31288, 24586, 18125, 11443, 4791, -1715, -8403, -14932, -21620, -28262, 30821, 24131, 17465, 10942, 4224, -2354, -8894, -15497, -22213, -28729, 30190, 23465, 16964, 10345, 3653, 1828, -7927, -13445, -19018, -24695, 31212, 25148, 97, -6592, -13249, -19733, -26430, 32437, 25980, 19292, 12557, -20876, 18518, 25150, 7388, 14026, -12115, -13511, -6836, -24806, -17923, 21484, 19870, 25718, 7795, 14358, -11550, -13139, -6437, -32466 };
    private static int ॱ = 0;
    
    private ˊ() {}
    
    /* Error */
    private final byte[] ˊ(String paramString, Key paramKey)
    {
      // Byte code:
      //   0: goto +635 -> 635
      //   3: aload 5
      //   5: iconst_1
      //   6: aload_2
      //   7: invokevirtual 585	javax/crypto/Cipher:init	(ILjava/security/Key;)V
      //   10: getstatic 590	o/vS:ˊ	Ljava/nio/charset/Charset;
      //   13: astore_2
      //   14: goto +93 -> 107
      //   17: getstatic 19	o/Iq$ˊ:ˊ	I
      //   20: istore 4
      //   22: iload 4
      //   24: bipush -20
      //   26: iand
      //   27: iload 4
      //   29: iconst_m1
      //   30: ixor
      //   31: bipush 19
      //   33: iand
      //   34: ior
      //   35: istore_3
      //   36: iload 4
      //   38: bipush 19
      //   40: iand
      //   41: iconst_1
      //   42: ishl
      //   43: ineg
      //   44: istore 4
      //   46: iload 4
      //   48: ineg
      //   49: iload_3
      //   50: ior
      //   51: iconst_1
      //   52: ishl
      //   53: iload_3
      //   54: iload 4
      //   56: ineg
      //   57: ixor
      //   58: isub
      //   59: istore_3
      //   60: iload_3
      //   61: sipush 128
      //   64: irem
      //   65: putstatic 17	o/Iq$ˊ:ॱ	I
      //   68: iload_3
      //   69: iconst_2
      //   70: irem
      //   71: ifeq +6 -> 77
      //   74: goto +309 -> 383
      //   77: goto +57 -> 134
      //   80: iload_3
      //   81: tableswitch	default:+23->104, 0:+586->667, 1:+412->493
      //   104: goto +389 -> 493
      //   107: aload_1
      //   108: ifnonnull +6 -> 114
      //   111: goto +427 -> 538
      //   114: goto +8 -> 122
      //   117: iconst_4
      //   118: istore_3
      //   119: goto +519 -> 638
      //   122: aload_1
      //   123: aload_2
      //   124: invokevirtual 596	java/lang/String:getBytes	(Ljava/nio/charset/Charset;)[B
      //   127: astore_1
      //   128: goto +299 -> 427
      //   131: astore_1
      //   132: aload_1
      //   133: athrow
      //   134: bipush 89
      //   136: istore_3
      //   137: goto +128 -> 265
      //   140: aload_1
      //   141: sipush 358
      //   144: sipush 7019
      //   147: bipush 40
      //   149: invokestatic 600	o/Iq$ˊ:ˋ	(ICI)Ljava/lang/String;
      //   152: invokevirtual 604	java/lang/String:intern	()Ljava/lang/String;
      //   155: invokestatic 609	o/vq:ˋ	(Ljava/lang/Object;Ljava/lang/String;)V
      //   158: goto +57 -> 215
      //   161: getstatic 17	o/Iq$ˊ:ॱ	I
      //   164: istore 4
      //   166: iload 4
      //   168: bipush 123
      //   170: iand
      //   171: istore_3
      //   172: iload 4
      //   174: bipush 123
      //   176: iand
      //   177: iload 4
      //   179: bipush 123
      //   181: ixor
      //   182: ior
      //   183: istore 4
      //   185: iload_3
      //   186: iload 4
      //   188: iand
      //   189: iload_3
      //   190: iload 4
      //   192: ior
      //   193: iadd
      //   194: istore_3
      //   195: iload_3
      //   196: sipush 128
      //   199: irem
      //   200: putstatic 19	o/Iq$ˊ:ˊ	I
      //   203: iload_3
      //   204: iconst_2
      //   205: irem
      //   206: ifne +6 -> 212
      //   209: goto +188 -> 397
      //   212: goto +366 -> 578
      //   215: aload 5
      //   217: aload_1
      //   218: invokevirtual 613	javax/crypto/Cipher:doFinal	([B)[B
      //   221: astore_2
      //   222: goto +477 -> 699
      //   225: aload_2
      //   226: areturn
      //   227: bipush 50
      //   229: istore_3
      //   230: goto +408 -> 638
      //   233: iconst_0
      //   234: istore_3
      //   235: goto +167 -> 402
      //   238: getstatic 19	o/Iq$ˊ:ˊ	I
      //   241: bipush 55
      //   243: iadd
      //   244: istore_3
      //   245: iload_3
      //   246: sipush 128
      //   249: irem
      //   250: putstatic 17	o/Iq$ˊ:ॱ	I
      //   253: iload_3
      //   254: iconst_2
      //   255: irem
      //   256: ifeq +6 -> 262
      //   259: goto +119 -> 378
      //   262: goto +92 -> 354
      //   265: iload_3
      //   266: lookupswitch	default:+26->292, 60:+355->621, 89:+-263->3
      //   292: goto +329 -> 621
      //   295: iload_3
      //   296: lookupswitch	default:+28->324, 2:+96->392, 66:+-71->225
      //   324: goto +68 -> 392
      //   327: bipush 31
      //   329: iconst_0
      //   330: bipush 6
      //   332: invokestatic 600	o/Iq$ˊ:ˋ	(ICI)Ljava/lang/String;
      //   335: astore 5
      //   337: aload 5
      //   339: invokevirtual 604	java/lang/String:intern	()Ljava/lang/String;
      //   342: astore 5
      //   344: aload 5
      //   346: invokestatic 617	javax/crypto/Cipher:getInstance	(Ljava/lang/String;)Ljavax/crypto/Cipher;
      //   349: astore 5
      //   351: goto -334 -> 17
      //   354: bipush 66
      //   356: istore_3
      //   357: goto -62 -> 295
      //   360: sipush 515
      //   363: sipush 23504
      //   366: bipush 74
      //   368: invokestatic 600	o/Iq$ˊ:ˋ	(ICI)Ljava/lang/String;
      //   371: invokevirtual 604	java/lang/String:intern	()Ljava/lang/String;
      //   374: astore_1
      //   375: goto -214 -> 161
      //   378: iconst_2
      //   379: istore_3
      //   380: goto -85 -> 295
      //   383: bipush 60
      //   385: istore_3
      //   386: goto -121 -> 265
      //   389: astore_1
      //   390: aload_1
      //   391: athrow
      //   392: aconst_null
      //   393: arraylength
      //   394: istore_3
      //   395: aload_2
      //   396: areturn
      //   397: iconst_1
      //   398: istore_3
      //   399: goto -319 -> 80
      //   402: iload_3
      //   403: tableswitch	default:+21->424, 0:+155->558, 1:+-43->360
      //   424: goto +134 -> 558
      //   427: getstatic 17	o/Iq$ˊ:ॱ	I
      //   430: istore 4
      //   432: iload 4
      //   434: bipush 45
      //   436: ixor
      //   437: iload 4
      //   439: bipush 45
      //   441: iand
      //   442: ior
      //   443: iconst_1
      //   444: ishl
      //   445: istore_3
      //   446: iload 4
      //   448: bipush 45
      //   450: ior
      //   451: iload 4
      //   453: bipush 45
      //   455: iand
      //   456: iconst_m1
      //   457: ixor
      //   458: iand
      //   459: istore 4
      //   461: iload 4
      //   463: ineg
      //   464: iload_3
      //   465: iand
      //   466: iload_3
      //   467: iload 4
      //   469: ineg
      //   470: ior
      //   471: iadd
      //   472: istore_3
      //   473: iload_3
      //   474: sipush 128
      //   477: irem
      //   478: putstatic 19	o/Iq$ˊ:ˊ	I
      //   481: iload_3
      //   482: iconst_2
      //   483: irem
      //   484: ifne +6 -> 490
      //   487: goto +124 -> 611
      //   490: goto +126 -> 616
      //   493: aload_2
      //   494: aload_1
      //   495: invokestatic 609	o/vq:ˋ	(Ljava/lang/Object;Ljava/lang/String;)V
      //   498: aconst_null
      //   499: arraylength
      //   500: istore_3
      //   501: goto -263 -> 238
      //   504: getstatic 17	o/Iq$ˊ:ॱ	I
      //   507: istore_3
      //   508: iload_3
      //   509: bipush 121
      //   511: iand
      //   512: iload_3
      //   513: bipush 121
      //   515: ior
      //   516: iadd
      //   517: istore_3
      //   518: iload_3
      //   519: sipush 128
      //   522: irem
      //   523: putstatic 19	o/Iq$ˊ:ˊ	I
      //   526: iload_3
      //   527: iconst_2
      //   528: irem
      //   529: ifne +6 -> 535
      //   532: goto -415 -> 117
      //   535: goto -308 -> 227
      //   538: new 619	o/uH
      //   541: dup
      //   542: sipush 305
      //   545: iconst_0
      //   546: bipush 53
      //   548: invokestatic 600	o/Iq$ˊ:ˋ	(ICI)Ljava/lang/String;
      //   551: invokevirtual 604	java/lang/String:intern	()Ljava/lang/String;
      //   554: invokespecial 622	o/uH:<init>	(Ljava/lang/String;)V
      //   557: athrow
      //   558: sipush 515
      //   561: sipush 23504
      //   564: bipush 26
      //   566: invokestatic 600	o/Iq$ˊ:ˋ	(ICI)Ljava/lang/String;
      //   569: astore_1
      //   570: aload_1
      //   571: invokevirtual 604	java/lang/String:intern	()Ljava/lang/String;
      //   574: astore_1
      //   575: goto -414 -> 161
      //   578: iconst_0
      //   579: istore_3
      //   580: goto -500 -> 80
      //   583: iload_3
      //   584: tableswitch	default:+24->608, 0:+151->735, 1:+-444->140
      //   608: goto +127 -> 735
      //   611: iconst_1
      //   612: istore_3
      //   613: goto -30 -> 583
      //   616: iconst_0
      //   617: istore_3
      //   618: goto -35 -> 583
      //   621: aload 5
      //   623: iconst_0
      //   624: aload_2
      //   625: invokevirtual 585	javax/crypto/Cipher:init	(ILjava/security/Key;)V
      //   628: getstatic 590	o/vS:ˊ	Ljava/nio/charset/Charset;
      //   631: astore_2
      //   632: goto -525 -> 107
      //   635: goto -131 -> 504
      //   638: iload_3
      //   639: lookupswitch	default:+25->664, 4:+36->675, 50:+-312->327
      //   664: goto +11 -> 675
      //   667: aload_2
      //   668: aload_1
      //   669: invokestatic 609	o/vq:ˋ	(Ljava/lang/Object;Ljava/lang/String;)V
      //   672: goto -434 -> 238
      //   675: bipush 31
      //   677: iconst_0
      //   678: bipush 16
      //   680: invokestatic 600	o/Iq$ˊ:ˋ	(ICI)Ljava/lang/String;
      //   683: invokevirtual 604	java/lang/String:intern	()Ljava/lang/String;
      //   686: invokestatic 617	javax/crypto/Cipher:getInstance	(Ljava/lang/String;)Ljavax/crypto/Cipher;
      //   689: astore 5
      //   691: goto -674 -> 17
      //   694: iconst_1
      //   695: istore_3
      //   696: goto -294 -> 402
      //   699: getstatic 17	o/Iq$ˊ:ॱ	I
      //   702: istore_3
      //   703: iload_3
      //   704: bipush 39
      //   706: ixor
      //   707: iload_3
      //   708: bipush 39
      //   710: iand
      //   711: iconst_1
      //   712: ishl
      //   713: iadd
      //   714: istore_3
      //   715: iload_3
      //   716: sipush 128
      //   719: irem
      //   720: putstatic 19	o/Iq$ˊ:ˊ	I
      //   723: iload_3
      //   724: iconst_2
      //   725: irem
      //   726: ifne +6 -> 732
      //   729: goto -35 -> 694
      //   732: goto -499 -> 233
      //   735: aload_1
      //   736: sipush 358
      //   739: sipush 7019
      //   742: bipush 44
      //   744: invokestatic 600	o/Iq$ˊ:ˋ	(ICI)Ljava/lang/String;
      //   747: invokevirtual 604	java/lang/String:intern	()Ljava/lang/String;
      //   750: invokestatic 609	o/vq:ˋ	(Ljava/lang/Object;Ljava/lang/String;)V
      //   753: goto -538 -> 215
      // Local variable table:
      //   start	length	slot	name	signature
      //   0	756	0	this	ˊ
      //   0	756	1	paramString	String
      //   0	756	2	paramKey	Key
      //   35	691	3	i	int
      //   20	448	4	j	int
      //   3	687	5	localObject	Object
      // Exception table:
      //   from	to	target	type
      //   327	337	131	java/lang/Exception
      //   344	351	131	java/lang/NullPointerException
      //   715	723	131	java/lang/NullPointerException
      //   17	22	389	java/lang/ArrayStoreException
      //   337	344	389	java/lang/IllegalStateException
      //   344	351	389	java/lang/IllegalStateException
      //   558	570	389	java/lang/RuntimeException
      //   570	575	389	java/lang/ArrayStoreException
      //   699	703	389	java/lang/UnsupportedOperationException
    }
    
    /* Error */
    private static String ˋ(int paramInt1, char paramChar, int paramInt2)
    {
      // Byte code:
      //   0: goto +130 -> 130
      //   3: astore 9
      //   5: aload 9
      //   7: athrow
      //   8: goto +225 -> 233
      //   11: getstatic 17	o/Iq$ˊ:ॱ	I
      //   14: bipush 83
      //   16: iadd
      //   17: istore 4
      //   19: iload 4
      //   21: sipush 128
      //   24: irem
      //   25: putstatic 19	o/Iq$ˊ:ˊ	I
      //   28: iload 4
      //   30: iconst_2
      //   31: irem
      //   32: ifne +6 -> 38
      //   35: goto -27 -> 8
      //   38: goto +195 -> 233
      //   41: bipush 91
      //   43: istore_0
      //   44: goto +124 -> 168
      //   47: getstatic 19	o/Iq$ˊ:ˊ	I
      //   50: bipush 111
      //   52: iadd
      //   53: istore_0
      //   54: iload_0
      //   55: sipush 128
      //   58: irem
      //   59: putstatic 17	o/Iq$ˊ:ॱ	I
      //   62: iload_0
      //   63: iconst_2
      //   64: irem
      //   65: ifeq +6 -> 71
      //   68: goto -27 -> 41
      //   71: goto +131 -> 202
      //   74: iload_2
      //   75: newarray char
      //   77: astore 9
      //   79: iconst_0
      //   80: istore_3
      //   81: goto +127 -> 208
      //   84: getstatic 17	o/Iq$ˊ:ॱ	I
      //   87: bipush 33
      //   89: iadd
      //   90: istore_3
      //   91: iload_3
      //   92: sipush 128
      //   95: irem
      //   96: putstatic 19	o/Iq$ˊ:ˊ	I
      //   99: iload_3
      //   100: iconst_2
      //   101: irem
      //   102: ifne +6 -> 108
      //   105: goto +94 -> 199
      //   108: goto -34 -> 74
      //   111: iconst_1
      //   112: istore 4
      //   114: goto +19 -> 133
      //   117: new 575	java/lang/NullPointerException
      //   120: dup
      //   121: invokespecial 623	java/lang/NullPointerException:<init>	()V
      //   124: athrow
      //   125: astore 9
      //   127: aload 9
      //   129: athrow
      //   130: goto -46 -> 84
      //   133: iload 4
      //   135: tableswitch	default:+21->156, 0:+-124->11, 1:+84->219
      //   156: goto +63 -> 219
      //   159: aload 9
      //   161: areturn
      //   162: iconst_0
      //   163: istore 4
      //   165: goto -32 -> 133
      //   168: iload_0
      //   169: lookupswitch	default:+27->196, 17:+-10->159, 91:+-52->117
      //   196: aload 9
      //   198: areturn
      //   199: goto -125 -> 74
      //   202: bipush 17
      //   204: istore_0
      //   205: goto -37 -> 168
      //   208: iload_3
      //   209: iload_2
      //   210: if_icmpge +6 -> 216
      //   213: goto -51 -> 162
      //   216: goto -105 -> 111
      //   219: new 592	java/lang/String
      //   222: dup
      //   223: aload 9
      //   225: invokespecial 626	java/lang/String:<init>	([C)V
      //   228: astore 9
      //   230: goto -183 -> 47
      //   233: getstatic 560	o/Iq$ˊ:ˏ	[C
      //   236: iload_0
      //   237: iload_3
      //   238: iadd
      //   239: caload
      //   240: istore 4
      //   242: iload 4
      //   244: i2l
      //   245: lstore 5
      //   247: iload_3
      //   248: i2l
      //   249: lstore 7
      //   251: aload 9
      //   253: iload_3
      //   254: lload 5
      //   256: lload 7
      //   258: getstatic 23	o/Iq$ˊ:ˎ	J
      //   261: lmul
      //   262: lxor
      //   263: iload_1
      //   264: i2l
      //   265: lxor
      //   266: l2i
      //   267: i2c
      //   268: castore
      //   269: iload_3
      //   270: iconst_1
      //   271: iadd
      //   272: istore_3
      //   273: goto -65 -> 208
      // Local variable table:
      //   start	length	slot	name	signature
      //   0	276	0	paramInt1	int
      //   0	276	1	paramChar	char
      //   0	276	2	paramInt2	int
      //   80	193	3	i	int
      //   17	226	4	j	int
      //   245	10	5	l1	long
      //   249	8	7	l2	long
      //   3	3	9	localException1	Exception
      //   77	1	9	arrayOfChar	char[]
      //   125	99	9	localException2	Exception
      //   228	24	9	str	String
      // Exception table:
      //   from	to	target	type
      //   84	91	3	java/lang/Exception
      //   91	99	3	java/lang/Exception
      //   233	242	125	java/lang/Exception
      //   251	269	125	java/lang/Exception
    }
    
    /* Error */
    private final String ˋ(String paramString1, String paramString2)
    {
      // Byte code:
      //   0: goto +602 -> 602
      //   3: getstatic 17	o/Iq$ˊ:ॱ	I
      //   6: istore_3
      //   7: iload_3
      //   8: bipush 84
      //   10: ior
      //   11: iconst_1
      //   12: ishl
      //   13: iload_3
      //   14: bipush 84
      //   16: ixor
      //   17: isub
      //   18: istore_3
      //   19: iload_3
      //   20: iconst_m1
      //   21: ixor
      //   22: iload_3
      //   23: iconst_m1
      //   24: iand
      //   25: iconst_1
      //   26: ishl
      //   27: iadd
      //   28: istore_3
      //   29: iload_3
      //   30: sipush 128
      //   33: irem
      //   34: putstatic 19	o/Iq$ˊ:ˊ	I
      //   37: iload_3
      //   38: iconst_2
      //   39: irem
      //   40: ifne +6 -> 46
      //   43: goto +562 -> 605
      //   46: goto +450 -> 496
      //   49: aload 5
      //   51: iconst_2
      //   52: aload_2
      //   53: invokevirtual 585	javax/crypto/Cipher:init	(ILjava/security/Key;)V
      //   56: aload 5
      //   58: aload_1
      //   59: iconst_2
      //   60: invokestatic 639	android/util/Base64:decode	(Ljava/lang/String;I)[B
      //   63: invokevirtual 613	javax/crypto/Cipher:doFinal	([B)[B
      //   66: astore_1
      //   67: goto +336 -> 403
      //   70: astore_1
      //   71: aload_1
      //   72: athrow
      //   73: getstatic 19	o/Iq$ˊ:ˊ	I
      //   76: istore_3
      //   77: iload_3
      //   78: bipush 46
      //   80: ior
      //   81: iconst_1
      //   82: ishl
      //   83: iload_3
      //   84: bipush 46
      //   86: ixor
      //   87: isub
      //   88: istore_3
      //   89: iload_3
      //   90: iconst_m1
      //   91: ixor
      //   92: iload_3
      //   93: iconst_m1
      //   94: iand
      //   95: iconst_1
      //   96: ishl
      //   97: iadd
      //   98: istore_3
      //   99: iload_3
      //   100: sipush 128
      //   103: irem
      //   104: putstatic 17	o/Iq$ˊ:ॱ	I
      //   107: iload_3
      //   108: iconst_2
      //   109: irem
      //   110: ifeq +6 -> 116
      //   113: goto +6 -> 119
      //   116: goto -67 -> 49
      //   119: goto -70 -> 49
      //   122: bipush 26
      //   124: istore_3
      //   125: goto +246 -> 371
      //   128: new 592	java/lang/String
      //   131: dup
      //   132: aload_1
      //   133: getstatic 590	o/vS:ˊ	Ljava/nio/charset/Charset;
      //   136: invokespecial 642	java/lang/String:<init>	([BLjava/nio/charset/Charset;)V
      //   139: astore_1
      //   140: goto +165 -> 305
      //   143: aload_1
      //   144: sipush 541
      //   147: iconst_0
      //   148: bipush 50
      //   150: invokestatic 600	o/Iq$ˊ:ˋ	(ICI)Ljava/lang/String;
      //   153: invokevirtual 604	java/lang/String:intern	()Ljava/lang/String;
      //   156: invokestatic 609	o/vq:ˋ	(Ljava/lang/Object;Ljava/lang/String;)V
      //   159: goto -31 -> 128
      //   162: getstatic 19	o/Iq$ˊ:ˊ	I
      //   165: istore_3
      //   166: iload_3
      //   167: bipush 82
      //   169: iadd
      //   170: iconst_1
      //   171: isub
      //   172: istore_3
      //   173: iload_3
      //   174: sipush 128
      //   177: irem
      //   178: putstatic 17	o/Iq$ˊ:ॱ	I
      //   181: iload_3
      //   182: iconst_2
      //   183: irem
      //   184: ifeq +6 -> 190
      //   187: goto -65 -> 122
      //   190: goto +178 -> 368
      //   193: sipush 402
      //   196: ldc_w 643
      //   199: bipush 20
      //   201: invokestatic 600	o/Iq$ˊ:ˋ	(ICI)Ljava/lang/String;
      //   204: astore 5
      //   206: aload 5
      //   208: invokevirtual 604	java/lang/String:intern	()Ljava/lang/String;
      //   211: astore 6
      //   213: sipush 422
      //   216: iconst_0
      //   217: iconst_2
      //   218: invokestatic 600	o/Iq$ˊ:ˋ	(ICI)Ljava/lang/String;
      //   221: astore 5
      //   223: goto +286 -> 509
      //   226: sipush 302
      //   229: sipush 4232
      //   232: iconst_3
      //   233: invokestatic 600	o/Iq$ˊ:ˋ	(ICI)Ljava/lang/String;
      //   236: invokevirtual 604	java/lang/String:intern	()Ljava/lang/String;
      //   239: invokestatic 648	java/security/KeyFactory:getInstance	(Ljava/lang/String;)Ljava/security/KeyFactory;
      //   242: astore 5
      //   244: goto +364 -> 608
      //   247: iconst_1
      //   248: istore_3
      //   249: goto +212 -> 461
      //   252: getstatic 19	o/Iq$ˊ:ˊ	I
      //   255: istore_3
      //   256: iload_3
      //   257: bipush 49
      //   259: ixor
      //   260: iload_3
      //   261: bipush 49
      //   263: iand
      //   264: ior
      //   265: iconst_1
      //   266: ishl
      //   267: iload_3
      //   268: iconst_m1
      //   269: ixor
      //   270: bipush 49
      //   272: iand
      //   273: iload_3
      //   274: bipush -50
      //   276: iand
      //   277: ior
      //   278: ineg
      //   279: iconst_m1
      //   280: ixor
      //   281: isub
      //   282: iconst_1
      //   283: isub
      //   284: istore_3
      //   285: iload_3
      //   286: sipush 128
      //   289: irem
      //   290: putstatic 17	o/Iq$ˊ:ॱ	I
      //   293: iload_3
      //   294: iconst_2
      //   295: irem
      //   296: ifeq +6 -> 302
      //   299: goto +268 -> 567
      //   302: goto -109 -> 193
      //   305: getstatic 19	o/Iq$ˊ:ˊ	I
      //   308: istore 4
      //   310: iload 4
      //   312: bipush 123
      //   314: iand
      //   315: iconst_m1
      //   316: ixor
      //   317: iload 4
      //   319: bipush 123
      //   321: ior
      //   322: iand
      //   323: istore_3
      //   324: iload 4
      //   326: bipush 123
      //   328: iand
      //   329: iconst_1
      //   330: ishl
      //   331: ineg
      //   332: istore 4
      //   334: iload 4
      //   336: ineg
      //   337: iload_3
      //   338: ior
      //   339: iconst_1
      //   340: ishl
      //   341: iload_3
      //   342: iload 4
      //   344: ineg
      //   345: ixor
      //   346: isub
      //   347: istore_3
      //   348: iload_3
      //   349: sipush 128
      //   352: irem
      //   353: putstatic 17	o/Iq$ˊ:ॱ	I
      //   356: iload_3
      //   357: iconst_2
      //   358: irem
      //   359: ifeq +6 -> 365
      //   362: goto -115 -> 247
      //   365: goto +126 -> 491
      //   368: bipush 48
      //   370: istore_3
      //   371: iload_3
      //   372: lookupswitch	default:+28->400, 26:+206->578, 48:+-146->226
      //   400: goto +178 -> 578
      //   403: getstatic 17	o/Iq$ˊ:ॱ	I
      //   406: istore 4
      //   408: iload 4
      //   410: bipush -6
      //   412: iand
      //   413: iload 4
      //   415: iconst_m1
      //   416: ixor
      //   417: iconst_5
      //   418: iand
      //   419: ior
      //   420: istore_3
      //   421: iload 4
      //   423: iconst_5
      //   424: iand
      //   425: iconst_1
      //   426: ishl
      //   427: istore 4
      //   429: iload_3
      //   430: iload 4
      //   432: ior
      //   433: iconst_1
      //   434: ishl
      //   435: iload_3
      //   436: iload 4
      //   438: ixor
      //   439: isub
      //   440: istore_3
      //   441: iload_3
      //   442: sipush 128
      //   445: irem
      //   446: putstatic 19	o/Iq$ˊ:ˊ	I
      //   449: iload_3
      //   450: iconst_2
      //   451: irem
      //   452: ifne +6 -> 458
      //   455: goto +31 -> 486
      //   458: goto -315 -> 143
      //   461: iload_3
      //   462: tableswitch	default:+22->484, 0:+27->489, 1:+108->570
      //   484: aload_1
      //   485: areturn
      //   486: goto -343 -> 143
      //   489: aload_1
      //   490: areturn
      //   491: iconst_0
      //   492: istore_3
      //   493: goto -32 -> 461
      //   496: aload 5
      //   498: aload_2
      //   499: checkcast 650	java/security/spec/KeySpec
      //   502: invokevirtual 654	java/security/KeyFactory:generatePrivate	(Ljava/security/spec/KeySpec;)Ljava/security/PrivateKey;
      //   505: astore_2
      //   506: goto -254 -> 252
      //   509: getstatic 17	o/Iq$ˊ:ॱ	I
      //   512: istore_3
      //   513: iload_3
      //   514: bipush 74
      //   516: iand
      //   517: iload_3
      //   518: bipush 74
      //   520: ior
      //   521: iadd
      //   522: iconst_0
      //   523: iadd
      //   524: iconst_1
      //   525: isub
      //   526: istore_3
      //   527: iload_3
      //   528: sipush 128
      //   531: irem
      //   532: putstatic 19	o/Iq$ˊ:ˊ	I
      //   535: iload_3
      //   536: iconst_2
      //   537: irem
      //   538: ifne +6 -> 544
      //   541: goto +58 -> 599
      //   544: aload 6
      //   546: aload 5
      //   548: invokevirtual 604	java/lang/String:intern	()Ljava/lang/String;
      //   551: invokestatic 657	javax/crypto/Cipher:getInstance	(Ljava/lang/String;Ljava/lang/String;)Ljavax/crypto/Cipher;
      //   554: astore 5
      //   556: aload_2
      //   557: checkcast 659	java/security/Key
      //   560: astore_2
      //   561: goto -488 -> 73
      //   564: astore_1
      //   565: aload_1
      //   566: athrow
      //   567: goto -374 -> 193
      //   570: new 575	java/lang/NullPointerException
      //   573: dup
      //   574: invokespecial 623	java/lang/NullPointerException:<init>	()V
      //   577: athrow
      //   578: sipush 27296
      //   581: sipush 4232
      //   584: iconst_2
      //   585: invokestatic 600	o/Iq$ˊ:ˋ	(ICI)Ljava/lang/String;
      //   588: invokevirtual 604	java/lang/String:intern	()Ljava/lang/String;
      //   591: invokestatic 648	java/security/KeyFactory:getInstance	(Ljava/lang/String;)Ljava/security/KeyFactory;
      //   594: astore 5
      //   596: goto +12 -> 608
      //   599: goto -55 -> 544
      //   602: goto -440 -> 162
      //   605: goto -109 -> 496
      //   608: new 661	java/security/spec/PKCS8EncodedKeySpec
      //   611: dup
      //   612: aload_2
      //   613: iconst_2
      //   614: invokestatic 639	android/util/Base64:decode	(Ljava/lang/String;I)[B
      //   617: invokespecial 664	java/security/spec/PKCS8EncodedKeySpec:<init>	([B)V
      //   620: astore_2
      //   621: goto -618 -> 3
      // Local variable table:
      //   start	length	slot	name	signature
      //   0	624	0	this	ˊ
      //   0	624	1	paramString1	String
      //   0	624	2	paramString2	String
      //   6	532	3	i	int
      //   308	131	4	j	int
      //   49	546	5	localObject	Object
      //   211	334	6	str	String
      // Exception table:
      //   from	to	target	type
      //   162	166	70	java/lang/UnsupportedOperationException
      //   173	181	70	java/lang/ClassCastException
      //   206	213	70	java/lang/IllegalStateException
      //   213	223	70	java/lang/IllegalStateException
      //   252	256	70	java/lang/NumberFormatException
      //   285	293	70	java/lang/UnsupportedOperationException
      //   193	206	564	java/lang/IllegalArgumentException
      //   206	213	564	java/lang/IllegalArgumentException
      //   213	223	564	java/lang/IllegalArgumentException
      //   213	223	564	java/lang/NumberFormatException
      //   305	310	564	java/lang/Exception
      //   348	356	564	java/lang/RuntimeException
    }
    
    /* Error */
    private final String ˎ(byte[] paramArrayOfByte, Key paramKey, Cipher paramCipher)
    {
      // Byte code:
      //   0: goto +190 -> 190
      //   3: getstatic 19	o/Iq$ˊ:ˊ	I
      //   6: istore 5
      //   8: iload 5
      //   10: bipush 99
      //   12: ixor
      //   13: iload 5
      //   15: bipush 99
      //   17: iand
      //   18: ior
      //   19: iconst_1
      //   20: ishl
      //   21: istore 4
      //   23: iload 5
      //   25: bipush 99
      //   27: ior
      //   28: iload 5
      //   30: bipush 99
      //   32: iand
      //   33: iconst_m1
      //   34: ixor
      //   35: iand
      //   36: istore 5
      //   38: iload 5
      //   40: ineg
      //   41: iload 4
      //   43: iand
      //   44: iload 4
      //   46: iload 5
      //   48: ineg
      //   49: ior
      //   50: iadd
      //   51: istore 4
      //   53: iload 4
      //   55: sipush 128
      //   58: irem
      //   59: putstatic 17	o/Iq$ˊ:ॱ	I
      //   62: iload 4
      //   64: iconst_2
      //   65: irem
      //   66: ifeq +6 -> 72
      //   69: goto +229 -> 298
      //   72: goto +233 -> 305
      //   75: aconst_null
      //   76: arraylength
      //   77: istore 4
      //   79: aload_1
      //   80: areturn
      //   81: sipush 591
      //   84: sipush 1856
      //   87: bipush 7
      //   89: invokestatic 600	o/Iq$ˊ:ˋ	(ICI)Ljava/lang/String;
      //   92: astore_2
      //   93: goto +159 -> 252
      //   96: iload 4
      //   98: tableswitch	default:+22->120, 0:+-23->75, 1:+180->278
      //   120: aload_1
      //   121: areturn
      //   122: getstatic 19	o/Iq$ˊ:ˊ	I
      //   125: istore 5
      //   127: iload 5
      //   129: bipush 75
      //   131: ior
      //   132: iconst_1
      //   133: ishl
      //   134: istore 4
      //   136: iload 5
      //   138: iconst_m1
      //   139: ixor
      //   140: bipush 75
      //   142: iand
      //   143: iload 5
      //   145: bipush -76
      //   147: iand
      //   148: ior
      //   149: istore 5
      //   151: iload 5
      //   153: ineg
      //   154: iload 4
      //   156: ior
      //   157: iconst_1
      //   158: ishl
      //   159: iload 4
      //   161: iload 5
      //   163: ineg
      //   164: ixor
      //   165: isub
      //   166: istore 4
      //   168: iload 4
      //   170: sipush 128
      //   173: irem
      //   174: putstatic 17	o/Iq$ˊ:ॱ	I
      //   177: iload 4
      //   179: iconst_2
      //   180: irem
      //   181: ifeq +6 -> 187
      //   184: goto +62 -> 246
      //   187: goto +6 -> 193
      //   190: goto -187 -> 3
      //   193: iconst_1
      //   194: istore 4
      //   196: goto -100 -> 96
      //   199: iload 4
      //   201: lookupswitch	default:+27->228, 71:+30->231, 81:+79->280
      //   228: goto +52 -> 280
      //   231: aload_3
      //   232: iconst_5
      //   233: aload_2
      //   234: invokevirtual 585	javax/crypto/Cipher:init	(ILjava/security/Key;)V
      //   237: aload_3
      //   238: aload_1
      //   239: invokevirtual 613	javax/crypto/Cipher:doFinal	([B)[B
      //   242: astore_1
      //   243: goto -162 -> 81
      //   246: iconst_0
      //   247: istore 4
      //   249: goto -153 -> 96
      //   252: aload_1
      //   253: aload_2
      //   254: invokevirtual 604	java/lang/String:intern	()Ljava/lang/String;
      //   257: invokestatic 609	o/vq:ˋ	(Ljava/lang/Object;Ljava/lang/String;)V
      //   260: new 592	java/lang/String
      //   263: dup
      //   264: aload_1
      //   265: getstatic 590	o/vS:ˊ	Ljava/nio/charset/Charset;
      //   268: invokespecial 642	java/lang/String:<init>	([BLjava/nio/charset/Charset;)V
      //   271: astore_1
      //   272: goto -150 -> 122
      //   275: astore_1
      //   276: aload_1
      //   277: athrow
      //   278: aload_1
      //   279: areturn
      //   280: aload_3
      //   281: iconst_2
      //   282: aload_2
      //   283: invokevirtual 585	javax/crypto/Cipher:init	(ILjava/security/Key;)V
      //   286: aload_3
      //   287: aload_1
      //   288: invokevirtual 613	javax/crypto/Cipher:doFinal	([B)[B
      //   291: astore_1
      //   292: goto -211 -> 81
      //   295: astore_1
      //   296: aload_1
      //   297: athrow
      //   298: bipush 71
      //   300: istore 4
      //   302: goto -103 -> 199
      //   305: bipush 81
      //   307: istore 4
      //   309: goto -110 -> 199
      // Local variable table:
      //   start	length	slot	name	signature
      //   0	312	0	this	ˊ
      //   0	312	1	paramArrayOfByte	byte[]
      //   0	312	2	paramKey	Key
      //   0	312	3	paramCipher	Cipher
      //   21	287	4	i	int
      //   6	156	5	j	int
      // Exception table:
      //   from	to	target	type
      //   3	8	275	java/lang/IllegalArgumentException
      //   53	62	275	java/lang/ArrayStoreException
      //   231	237	275	java/lang/NumberFormatException
      //   280	286	275	java/lang/NullPointerException
      //   286	292	275	java/lang/ArrayStoreException
      //   81	93	295	java/lang/IndexOutOfBoundsException
      //   81	93	295	java/lang/IllegalArgumentException
      //   122	127	295	java/lang/RuntimeException
      //   168	177	295	java/lang/ClassCastException
      //   237	243	295	java/lang/IllegalArgumentException
    }
    
    private final String ˏ(Key paramKey, String paramString)
    {
      break label250;
      paramKey = Base64.encode(paramKey.getEncoded(), 2);
      break label188;
      Object localObject2;
      vq.ˋ(paramString, (String)localObject2);
      paramString = ((KeyFactory)localObject1).generatePublic((KeySpec)new X509EncodedKeySpec(Base64.decode(paramString, 2)));
      Object localObject1 = Cipher.getInstance(ˋ(402, 58921, 20).intern(), ˋ(422, '\000', 2).intern());
      vq.ˋ(localObject1, ˋ(424, 'ೖ', 41).intern());
      ((Cipher)localObject1).init(1, (Key)paramString);
      paramKey = Base64.encodeToString(((Cipher)localObject1).doFinal(paramKey), 2);
      vq.ˋ(paramKey, ˋ(465, '\000', 50).intern());
      return paramKey;
      for (;;)
      {
        try
        {
          paramString = paramString.getBytes((Charset)localObject2);
          try
          {
            localObject2 = ˋ(358, '᭫', 44);
            localObject2 = ((String)localObject2).intern();
          }
          catch (UnsupportedOperationException|ClassCastException paramKey)
          {
            label188:
            label250:
            throw paramKey;
          }
        }
        catch (NullPointerException|IndexOutOfBoundsException|NumberFormatException|UnsupportedOperationException|ClassCastException paramKey)
        {
          throw paramKey;
        }
        vq.ˋ(paramKey, ˋ(252, '\000', 50).intern());
        int i = 302;
        continue;
        i = ॱ + 52 + 0 - 1;
        ˊ = i % 128;
        if (i % 2 != 0)
        {
          continue;
          localObject1 = KeyFactory.getInstance(ˋ(i, 'ႈ', 3).intern());
          localObject2 = vS.ˊ;
          if (paramString == null) {
            continue;
          }
          continue;
          i = ॱ;
          i = (i ^ 0x24) + ((i & 0x24) << 1) - 1;
          ˊ = i % 128;
          if (i % 2 == 0) {
            continue;
          }
          break;
          i = 1;
          break label355;
        }
        i = 0;
        break label355;
        localObject1 = ˋ(252, '\000', 61);
        vq.ˋ(paramKey, ((String)localObject1).intern());
        i = 19939;
        continue;
        paramKey = ˋ(305, '\000', 53);
        paramKey = paramKey.intern();
        throw new uH(paramKey);
        label355:
        switch (i)
        {
        }
      }
    }
    
    private final Key ॱ(String paramString1, String paramString2)
    {
      for (;;)
      {
        try
        {
          j = ˊ;
          i = j & 0x4F;
          j = -(j ^ 0x4F | j & 0x4F);
          i = (-j ^ i) + ((i & -j) << 1);
          ॱ = i % 128;
          if (i % 2 == 0)
          {
            continue;
            try
            {
              ˊ localˊ = (ˊ)this;
              paramString1 = localˊ.ˋ(paramString1, paramString2);
              paramString1 = Base64.decode(paramString1, 2);
            }
            catch (Exception|IllegalArgumentException|NullPointerException|IllegalStateException paramString1)
            {
              throw paramString1;
            }
            continue;
            paramString1 = (Key)paramString1;
            break;
            j = ॱ;
            i = j & 0x75;
            j = j & 0x75 | j ^ 0x75;
            i = (i & j) + (i | j);
            ˊ = i % 128;
            if (i % 2 != 0) {
              continue;
            }
            continue;
          }
        }
        catch (NumberFormatException|ClassCastException|ArrayStoreException|UnsupportedOperationException|RuntimeException paramString1)
        {
          throw paramString1;
        }
        continue;
        i = paramString1.length;
        paramString2 = ˋ(31, '\000', 6);
        paramString1 = new SecretKeySpec(paramString1, 0, i, paramString2.intern());
      }
      int j = ˊ;
      int i = j & 0x41;
      j |= 0x41;
      i = (i & j) + (i | j);
      ॱ = i % 128;
      if (i % 2 != 0) {
        return paramString1;
      }
      return paramString1;
    }
    
    /* Error */
    public final String ˊ(String paramString1, String paramString2)
    {
      // Byte code:
      //   0: goto +1455 -> 1455
      //   3: iload_3
      //   4: ifne +6 -> 10
      //   7: goto +1251 -> 1258
      //   10: goto +664 -> 674
      //   13: goto +259 -> 272
      //   16: goto -13 -> 3
      //   19: iconst_0
      //   20: istore_3
      //   21: goto +1943 -> 1964
      //   24: goto +289 -> 313
      //   27: iconst_1
      //   28: istore_3
      //   29: goto +614 -> 643
      //   32: iload_3
      //   33: tableswitch	default:+23->56, 0:+2068->2101, 1:+1810->1843
      //   56: goto +1787 -> 1843
      //   59: aload 7
      //   61: invokeinterface 703 1 0
      //   66: checkcast 592	java/lang/String
      //   69: astore_1
      //   70: goto +1943 -> 2013
      //   73: getstatic 19	o/Iq$ˊ:ˊ	I
      //   76: bipush 103
      //   78: iadd
      //   79: istore_3
      //   80: iload_3
      //   81: sipush 128
      //   84: irem
      //   85: putstatic 17	o/Iq$ˊ:ॱ	I
      //   88: iload_3
      //   89: iconst_2
      //   90: irem
      //   91: ifeq +6 -> 97
      //   94: goto +1943 -> 2037
      //   97: goto +1283 -> 1380
      //   100: goto -97 -> 3
      //   103: getstatic 17	o/Iq$ˊ:ॱ	I
      //   106: istore_3
      //   107: iload_3
      //   108: bipush 51
      //   110: ixor
      //   111: iload_3
      //   112: bipush 51
      //   114: iand
      //   115: iconst_1
      //   116: ishl
      //   117: iadd
      //   118: istore_3
      //   119: iload_3
      //   120: sipush 128
      //   123: irem
      //   124: putstatic 19	o/Iq$ˊ:ˊ	I
      //   127: iload_3
      //   128: iconst_2
      //   129: irem
      //   130: ifne +6 -> 136
      //   133: goto +2052 -> 2185
      //   136: goto +1313 -> 1449
      //   139: bipush 17
      //   141: istore_3
      //   142: goto +1386 -> 1528
      //   145: getstatic 19	o/Iq$ˊ:ˊ	I
      //   148: istore_3
      //   149: iload_3
      //   150: bipush 93
      //   152: ior
      //   153: iconst_1
      //   154: ishl
      //   155: iload_3
      //   156: bipush 93
      //   158: ixor
      //   159: ineg
      //   160: iconst_m1
      //   161: ixor
      //   162: isub
      //   163: iconst_1
      //   164: isub
      //   165: istore_3
      //   166: iload_3
      //   167: sipush 128
      //   170: irem
      //   171: putstatic 17	o/Iq$ˊ:ॱ	I
      //   174: iload_3
      //   175: iconst_2
      //   176: irem
      //   177: ifeq +6 -> 183
      //   180: goto +6 -> 186
      //   183: goto +1980 -> 2163
      //   186: goto +1977 -> 2163
      //   189: aload_2
      //   190: bipush 85
      //   192: sipush 22412
      //   195: bipush 59
      //   197: invokestatic 600	o/Iq$ˊ:ˋ	(ICI)Ljava/lang/String;
      //   200: invokevirtual 604	java/lang/String:intern	()Ljava/lang/String;
      //   203: invokestatic 705	o/vq:ˎ	(Ljava/lang/Object;Ljava/lang/String;)V
      //   206: goto +1456 -> 1662
      //   209: iconst_0
      //   210: istore_3
      //   211: goto -179 -> 32
      //   214: aload 8
      //   216: invokeinterface 711 1 0
      //   221: istore 6
      //   223: iload 6
      //   225: ifne +6 -> 231
      //   228: goto -19 -> 209
      //   231: goto +1949 -> 2180
      //   234: aload 8
      //   236: invokeinterface 711 1 0
      //   241: istore 6
      //   243: aconst_null
      //   244: arraylength
      //   245: istore_3
      //   246: iload 6
      //   248: ifne +6 -> 254
      //   251: goto +1621 -> 1872
      //   254: goto -227 -> 27
      //   257: aload_1
      //   258: iconst_5
      //   259: invokestatic 639	android/util/Base64:decode	(Ljava/lang/String;I)[B
      //   262: astore_1
      //   263: aload_0
      //   264: checkcast 2	o/Iq$ˊ
      //   267: astore 7
      //   269: goto +1189 -> 1458
      //   272: aload 8
      //   274: checkcast 713	java/lang/Iterable
      //   277: astore_1
      //   278: aload 7
      //   280: invokeinterface 717 1 0
      //   285: istore_3
      //   286: aload_1
      //   287: iload_3
      //   288: iconst_1
      //   289: ixor
      //   290: iload_3
      //   291: iconst_1
      //   292: iand
      //   293: ior
      //   294: iconst_1
      //   295: ishl
      //   296: iload_3
      //   297: iconst_1
      //   298: iand
      //   299: iconst_m1
      //   300: ixor
      //   301: iload_3
      //   302: iconst_1
      //   303: ior
      //   304: iand
      //   305: isub
      //   306: invokestatic 722	o/uQ:ˊ	(Ljava/lang/Iterable;I)Ljava/util/List;
      //   309: astore_1
      //   310: goto +888 -> 1198
      //   313: getstatic 17	o/Iq$ˊ:ॱ	I
      //   316: istore_3
      //   317: iload_3
      //   318: bipush 72
      //   320: ior
      //   321: iconst_1
      //   322: ishl
      //   323: iload_3
      //   324: bipush 72
      //   326: ixor
      //   327: isub
      //   328: istore_3
      //   329: iload_3
      //   330: iconst_m1
      //   331: ixor
      //   332: iload_3
      //   333: iconst_m1
      //   334: iand
      //   335: iconst_1
      //   336: ishl
      //   337: iadd
      //   338: istore_3
      //   339: iload_3
      //   340: sipush 128
      //   343: irem
      //   344: putstatic 19	o/Iq$ˊ:ˊ	I
      //   347: iload_3
      //   348: iconst_2
      //   349: irem
      //   350: ifne +6 -> 356
      //   353: goto +204 -> 557
      //   356: goto +954 -> 1310
      //   359: iconst_0
      //   360: istore_3
      //   361: goto +44 -> 405
      //   364: iconst_1
      //   365: istore_3
      //   366: goto +1598 -> 1964
      //   369: getstatic 19	o/Iq$ˊ:ˊ	I
      //   372: istore_3
      //   373: iload_3
      //   374: bipush 45
      //   376: ior
      //   377: iconst_1
      //   378: ishl
      //   379: iload_3
      //   380: bipush 45
      //   382: ixor
      //   383: isub
      //   384: istore_3
      //   385: iload_3
      //   386: sipush 128
      //   389: irem
      //   390: putstatic 17	o/Iq$ˊ:ॱ	I
      //   393: iload_3
      //   394: iconst_2
      //   395: irem
      //   396: ifeq +6 -> 402
      //   399: goto +1410 -> 1809
      //   402: goto +1629 -> 2031
      //   405: iload_3
      //   406: tableswitch	default:+22->428, 0:+536->942, 1:+1741->2147
      //   428: goto +1719 -> 2147
      //   431: bipush 29
      //   433: istore_3
      //   434: goto +1094 -> 1528
      //   437: getstatic 19	o/Iq$ˊ:ˊ	I
      //   440: bipush 58
      //   442: iadd
      //   443: istore 4
      //   445: iload 4
      //   447: iconst_m1
      //   448: ior
      //   449: iconst_1
      //   450: ishl
      //   451: iload 4
      //   453: iconst_m1
      //   454: ixor
      //   455: isub
      //   456: istore 4
      //   458: iload 4
      //   460: sipush 128
      //   463: irem
      //   464: putstatic 17	o/Iq$ˊ:ॱ	I
      //   467: iload 4
      //   469: iconst_2
      //   470: irem
      //   471: ifeq +6 -> 477
      //   474: goto +1616 -> 2090
      //   477: goto -461 -> 16
      //   480: getstatic 19	o/Iq$ˊ:ˊ	I
      //   483: istore_3
      //   484: iload_3
      //   485: bipush 95
      //   487: iand
      //   488: iload_3
      //   489: bipush 95
      //   491: iand
      //   492: iload_3
      //   493: bipush 95
      //   495: ixor
      //   496: ior
      //   497: iconst_m1
      //   498: ixor
      //   499: isub
      //   500: iconst_1
      //   501: isub
      //   502: istore_3
      //   503: iload_3
      //   504: sipush 128
      //   507: irem
      //   508: putstatic 17	o/Iq$ˊ:ॱ	I
      //   511: iload_3
      //   512: iconst_2
      //   513: irem
      //   514: ifeq +6 -> 520
      //   517: goto -504 -> 13
      //   520: goto -248 -> 272
      //   523: goto +1534 -> 2057
      //   526: astore_1
      //   527: aload_1
      //   528: athrow
      //   529: aload_1
      //   530: iconst_2
      //   531: invokestatic 639	android/util/Base64:decode	(Ljava/lang/String;I)[B
      //   534: astore_1
      //   535: aload_0
      //   536: checkcast 2	o/Iq$ˊ
      //   539: astore 7
      //   541: goto +917 -> 1458
      //   544: goto +818 -> 1362
      //   547: iconst_0
      //   548: istore_3
      //   549: goto +1266 -> 1815
      //   552: iconst_0
      //   553: istore_3
      //   554: goto +306 -> 860
      //   557: goto +753 -> 1310
      //   560: iload_3
      //   561: lookupswitch	default:+27->588, 10:+1098->1659, 72:+746->1307
      //   588: goto +719 -> 1307
      //   591: getstatic 17	o/Iq$ˊ:ॱ	I
      //   594: bipush 27
      //   596: iadd
      //   597: istore_3
      //   598: iload_3
      //   599: sipush 128
      //   602: irem
      //   603: putstatic 19	o/Iq$ˊ:ˊ	I
      //   606: iload_3
      //   607: iconst_2
      //   608: irem
      //   609: ifne +6 -> 615
      //   612: goto +290 -> 902
      //   615: goto +1343 -> 1958
      //   618: goto +1439 -> 2057
      //   621: new 619	o/uH
      //   624: dup
      //   625: sipush 173
      //   628: sipush 23981
      //   631: bipush 52
      //   633: invokestatic 600	o/Iq$ˊ:ˋ	(ICI)Ljava/lang/String;
      //   636: invokevirtual 604	java/lang/String:intern	()Ljava/lang/String;
      //   639: invokespecial 622	o/uH:<init>	(Ljava/lang/String;)V
      //   642: athrow
      //   643: iload_3
      //   644: tableswitch	default:+24->668, 0:+1457->2101, 1:+1199->1843
      //   668: goto +1175 -> 1843
      //   671: goto +1182 -> 1853
      //   674: bipush 22
      //   676: istore_3
      //   677: goto +420 -> 1097
      //   680: iload_3
      //   681: lookupswitch	default:+27->708, 9:+411->1092, 25:+-578->103
      //   708: goto +384 -> 1092
      //   711: new 619	o/uH
      //   714: dup
      //   715: bipush 113
      //   717: iconst_0
      //   718: bipush 60
      //   720: invokestatic 600	o/Iq$ˊ:ˋ	(ICI)Ljava/lang/String;
      //   723: invokevirtual 604	java/lang/String:intern	()Ljava/lang/String;
      //   726: invokespecial 622	o/uH:<init>	(Ljava/lang/String;)V
      //   729: athrow
      //   730: bipush 72
      //   732: istore_3
      //   733: goto -173 -> 560
      //   736: iconst_1
      //   737: istore_3
      //   738: goto +220 -> 958
      //   741: iload_3
      //   742: lookupswitch	default:+26->768, 57:+-723->19, 64:+-378->364
      //   768: goto -749 -> 19
      //   771: getstatic 17	o/Iq$ˊ:ॱ	I
      //   774: istore 4
      //   776: iload 4
      //   778: bipush 35
      //   780: iand
      //   781: iconst_m1
      //   782: ixor
      //   783: iload 4
      //   785: bipush 35
      //   787: ior
      //   788: iand
      //   789: istore_3
      //   790: iload 4
      //   792: bipush 35
      //   794: iand
      //   795: iconst_1
      //   796: ishl
      //   797: ineg
      //   798: istore 4
      //   800: iload 4
      //   802: ineg
      //   803: iload_3
      //   804: iand
      //   805: iload_3
      //   806: iload 4
      //   808: ineg
      //   809: ior
      //   810: iadd
      //   811: istore_3
      //   812: iload_3
      //   813: sipush 128
      //   816: irem
      //   817: putstatic 19	o/Iq$ˊ:ˊ	I
      //   820: iload_3
      //   821: iconst_2
      //   822: irem
      //   823: ifne +6 -> 829
      //   826: goto -279 -> 547
      //   829: goto +63 -> 892
      //   832: aload_0
      //   833: checkcast 2	o/Iq$ˊ
      //   836: aload 7
      //   838: aload_2
      //   839: invokespecial 724	o/Iq$ˊ:ॱ	(Ljava/lang/String;Ljava/lang/String;)Ljava/security/Key;
      //   842: astore_2
      //   843: bipush 86
      //   845: istore_3
      //   846: goto +181 -> 1027
      //   849: bipush 9
      //   851: istore_3
      //   852: goto -172 -> 680
      //   855: iconst_1
      //   856: istore_3
      //   857: goto -452 -> 405
      //   860: iload_3
      //   861: tableswitch	default:+23->884, 0:+1179->2040, 1:+-802->59
      //   884: goto -825 -> 59
      //   887: iconst_0
      //   888: istore_3
      //   889: goto +69 -> 958
      //   892: iconst_1
      //   893: istore_3
      //   894: goto +921 -> 1815
      //   897: iconst_0
      //   898: istore_3
      //   899: goto +1221 -> 2120
      //   902: bipush 15
      //   904: istore_3
      //   905: goto +359 -> 1264
      //   908: new 726	o/vR
      //   911: dup
      //   912: aload 7
      //   914: invokevirtual 604	java/lang/String:intern	()Ljava/lang/String;
      //   917: invokespecial 727	o/vR:<init>	(Ljava/lang/String;)V
      //   920: astore 7
      //   922: goto +61 -> 983
      //   925: aload_0
      //   926: checkcast 2	o/Iq$ˊ
      //   929: aload 7
      //   931: aload_2
      //   932: invokespecial 724	o/Iq$ˊ:ॱ	(Ljava/lang/String;Ljava/lang/String;)Ljava/security/Key;
      //   935: astore_2
      //   936: bipush 31
      //   938: istore_3
      //   939: goto +88 -> 1027
      //   942: sipush 19141
      //   945: sipush 5401
      //   948: bipush 55
      //   950: invokestatic 600	o/Iq$ˊ:ˋ	(ICI)Ljava/lang/String;
      //   953: astore 8
      //   955: goto +340 -> 1295
      //   958: iload_3
      //   959: tableswitch	default:+21->980, 0:+-725->234, 1:+-745->214
      //   980: goto -766 -> 214
      //   983: getstatic 17	o/Iq$ˊ:ॱ	I
      //   986: istore_3
      //   987: iload_3
      //   988: bipush 66
      //   990: ior
      //   991: iconst_1
      //   992: ishl
      //   993: iload_3
      //   994: bipush 66
      //   996: ixor
      //   997: isub
      //   998: istore_3
      //   999: iload_3
      //   1000: iconst_m1
      //   1001: iand
      //   1002: iload_3
      //   1003: iconst_m1
      //   1004: ior
      //   1005: iadd
      //   1006: istore_3
      //   1007: iload_3
      //   1008: sipush 128
      //   1011: irem
      //   1012: putstatic 19	o/Iq$ˊ:ˊ	I
      //   1015: iload_3
      //   1016: iconst_2
      //   1017: irem
      //   1018: ifne +6 -> 1024
      //   1021: goto +829 -> 1850
      //   1024: goto +1054 -> 2078
      //   1027: getstatic 17	o/Iq$ˊ:ॱ	I
      //   1030: istore 5
      //   1032: iload 5
      //   1034: bipush 89
      //   1036: ior
      //   1037: iconst_1
      //   1038: ishl
      //   1039: istore 4
      //   1041: iload 5
      //   1043: bipush -90
      //   1045: iand
      //   1046: iload 5
      //   1048: iconst_m1
      //   1049: ixor
      //   1050: bipush 89
      //   1052: iand
      //   1053: ior
      //   1054: ineg
      //   1055: istore 5
      //   1057: iload 4
      //   1059: iload 5
      //   1061: iand
      //   1062: iload 4
      //   1064: iload 5
      //   1066: ior
      //   1067: iadd
      //   1068: istore 4
      //   1070: iload 4
      //   1072: sipush 128
      //   1075: irem
      //   1076: putstatic 19	o/Iq$ˊ:ˊ	I
      //   1079: iload 4
      //   1081: iconst_2
      //   1082: irem
      //   1083: ifne +6 -> 1089
      //   1086: goto -542 -> 544
      //   1089: goto +273 -> 1362
      //   1092: iconst_0
      //   1093: istore_3
      //   1094: goto -657 -> 437
      //   1097: iload_3
      //   1098: lookupswitch	default:+26->1124, 22:+-1074->24, 63:+-618->480
      //   1124: goto -1100 -> 24
      //   1127: getstatic 17	o/Iq$ˊ:ॱ	I
      //   1130: istore_3
      //   1131: iload_3
      //   1132: bipush 48
      //   1134: iand
      //   1135: iload_3
      //   1136: bipush 48
      //   1138: ior
      //   1139: iadd
      //   1140: iconst_0
      //   1141: iadd
      //   1142: iconst_1
      //   1143: isub
      //   1144: istore_3
      //   1145: iload_3
      //   1146: sipush 128
      //   1149: irem
      //   1150: putstatic 19	o/Iq$ˊ:ˊ	I
      //   1153: iload_3
      //   1154: iconst_2
      //   1155: irem
      //   1156: ifne +6 -> 1162
      //   1159: goto -429 -> 730
      //   1162: goto +910 -> 2072
      //   1165: goto -547 -> 618
      //   1168: aload_1
      //   1169: iconst_0
      //   1170: anewarray 592	java/lang/String
      //   1173: invokeinterface 733 2 0
      //   1178: astore_1
      //   1179: goto -1106 -> 73
      //   1182: aload 7
      //   1184: invokeinterface 736 1 0
      //   1189: ifeq +6 -> 1195
      //   1192: goto -295 -> 897
      //   1195: goto +901 -> 2096
      //   1198: getstatic 17	o/Iq$ˊ:ॱ	I
      //   1201: istore 4
      //   1203: iload 4
      //   1205: bipush 35
      //   1207: ior
      //   1208: iconst_1
      //   1209: ishl
      //   1210: istore_3
      //   1211: iload 4
      //   1213: bipush 35
      //   1215: ior
      //   1216: iload 4
      //   1218: bipush 35
      //   1220: iand
      //   1221: iconst_m1
      //   1222: ixor
      //   1223: iand
      //   1224: istore 4
      //   1226: iload 4
      //   1228: ineg
      //   1229: iload_3
      //   1230: iand
      //   1231: iload_3
      //   1232: iload 4
      //   1234: ineg
      //   1235: ior
      //   1236: iadd
      //   1237: istore_3
      //   1238: iload_3
      //   1239: sipush 128
      //   1242: irem
      //   1243: putstatic 19	o/Iq$ˊ:ˊ	I
      //   1246: iload_3
      //   1247: iconst_2
      //   1248: irem
      //   1249: ifne +6 -> 1255
      //   1252: goto -87 -> 1165
      //   1255: goto -637 -> 618
      //   1258: bipush 63
      //   1260: istore_3
      //   1261: goto -164 -> 1097
      //   1264: iload_3
      //   1265: lookupswitch	default:+27->1292, 15:+233->1498, 95:+294->1559
      //   1292: goto +206 -> 1498
      //   1295: aload_1
      //   1296: aload 8
      //   1298: invokevirtual 604	java/lang/String:intern	()Ljava/lang/String;
      //   1301: invokestatic 609	o/vq:ˋ	(Ljava/lang/Object;Ljava/lang/String;)V
      //   1304: goto -713 -> 591
      //   1307: goto -125 -> 1182
      //   1310: goto -128 -> 1182
      //   1313: getstatic 19	o/Iq$ˊ:ˊ	I
      //   1316: istore_3
      //   1317: iload_3
      //   1318: bipush 69
      //   1320: iand
      //   1321: iconst_m1
      //   1322: ixor
      //   1323: iload_3
      //   1324: bipush 69
      //   1326: ior
      //   1327: iand
      //   1328: iload_3
      //   1329: bipush 69
      //   1331: iand
      //   1332: iconst_1
      //   1333: ishl
      //   1334: ineg
      //   1335: ineg
      //   1336: iconst_m1
      //   1337: ixor
      //   1338: isub
      //   1339: iconst_1
      //   1340: isub
      //   1341: istore_3
      //   1342: iload_3
      //   1343: sipush 128
      //   1346: irem
      //   1347: putstatic 17	o/Iq$ˊ:ॱ	I
      //   1350: iload_3
      //   1351: iconst_2
      //   1352: irem
      //   1353: ifeq +6 -> 1359
      //   1356: goto +654 -> 2010
      //   1359: goto -836 -> 523
      //   1362: iload_3
      //   1363: iconst_0
      //   1364: bipush 6
      //   1366: invokestatic 600	o/Iq$ˊ:ˋ	(ICI)Ljava/lang/String;
      //   1369: invokevirtual 604	java/lang/String:intern	()Ljava/lang/String;
      //   1372: invokestatic 617	javax/crypto/Cipher:getInstance	(Ljava/lang/String;)Ljavax/crypto/Cipher;
      //   1375: astore 9
      //   1377: goto -1008 -> 369
      //   1380: aload_1
      //   1381: ifnonnull +6 -> 1387
      //   1384: goto -763 -> 621
      //   1387: goto +490 -> 1877
      //   1390: getstatic 19	o/Iq$ˊ:ˊ	I
      //   1393: istore 4
      //   1395: iload 4
      //   1397: bipush 77
      //   1399: iand
      //   1400: istore_3
      //   1401: iload 4
      //   1403: bipush 77
      //   1405: ixor
      //   1406: iload 4
      //   1408: bipush 77
      //   1410: iand
      //   1411: ior
      //   1412: ineg
      //   1413: istore 4
      //   1415: iload 4
      //   1417: ineg
      //   1418: iload_3
      //   1419: ior
      //   1420: iconst_1
      //   1421: ishl
      //   1422: iload_3
      //   1423: iload 4
      //   1425: ineg
      //   1426: ixor
      //   1427: isub
      //   1428: istore_3
      //   1429: iload_3
      //   1430: sipush 128
      //   1433: irem
      //   1434: putstatic 17	o/Iq$ˊ:ॱ	I
      //   1437: iload_3
      //   1438: iconst_2
      //   1439: irem
      //   1440: ifeq +6 -> 1446
      //   1443: goto -891 -> 552
      //   1446: goto +135 -> 1581
      //   1449: bipush 64
      //   1451: istore_3
      //   1452: goto -711 -> 741
      //   1455: goto -1310 -> 145
      //   1458: getstatic 19	o/Iq$ˊ:ˊ	I
      //   1461: istore_3
      //   1462: iload_3
      //   1463: bipush 43
      //   1465: iand
      //   1466: iload_3
      //   1467: bipush 43
      //   1469: ior
      //   1470: iadd
      //   1471: istore_3
      //   1472: iload_3
      //   1473: sipush 128
      //   1476: irem
      //   1477: putstatic 17	o/Iq$ˊ:ॱ	I
      //   1480: iload_3
      //   1481: iconst_2
      //   1482: irem
      //   1483: ifeq +6 -> 1489
      //   1486: goto -1127 -> 359
      //   1489: goto -634 -> 855
      //   1492: bipush 25
      //   1494: istore_3
      //   1495: goto -815 -> 680
      //   1498: sipush 246
      //   1501: ldc_w 737
      //   1504: bipush 108
      //   1506: invokestatic 600	o/Iq$ˊ:ˋ	(ICI)Ljava/lang/String;
      //   1509: astore 8
      //   1511: aload 8
      //   1513: invokevirtual 604	java/lang/String:intern	()Ljava/lang/String;
      //   1516: astore 8
      //   1518: aload 9
      //   1520: aload 8
      //   1522: invokestatic 609	o/vq:ˋ	(Ljava/lang/Object;Ljava/lang/String;)V
      //   1525: goto +251 -> 1776
      //   1528: iload_3
      //   1529: lookupswitch	default:+27->1556, 17:+-1340->189, 29:+260->1789
      //   1556: goto +233 -> 1789
      //   1559: aload 9
      //   1561: sipush 246
      //   1564: ldc_w 737
      //   1567: bipush 6
      //   1569: invokestatic 600	o/Iq$ˊ:ˋ	(ICI)Ljava/lang/String;
      //   1572: invokevirtual 604	java/lang/String:intern	()Ljava/lang/String;
      //   1575: invokestatic 609	o/vq:ˋ	(Ljava/lang/Object;Ljava/lang/String;)V
      //   1578: goto +198 -> 1776
      //   1581: iconst_1
      //   1582: istore_3
      //   1583: goto -723 -> 860
      //   1586: getstatic 19	o/Iq$ˊ:ˊ	I
      //   1589: istore_3
      //   1590: iload_3
      //   1591: bipush 47
      //   1593: ixor
      //   1594: iload_3
      //   1595: bipush 47
      //   1597: iand
      //   1598: ior
      //   1599: iconst_1
      //   1600: ishl
      //   1601: iload_3
      //   1602: bipush 47
      //   1604: ixor
      //   1605: isub
      //   1606: istore_3
      //   1607: iload_3
      //   1608: sipush 128
      //   1611: irem
      //   1612: putstatic 17	o/Iq$ˊ:ॱ	I
      //   1615: iload_3
      //   1616: iconst_2
      //   1617: irem
      //   1618: ifeq +6 -> 1624
      //   1621: goto -1482 -> 139
      //   1624: goto -1193 -> 431
      //   1627: iload_3
      //   1628: lookupswitch	default:+28->1656, 46:+-1099->529, 48:+-1371->257
      //   1656: goto -1399 -> 257
      //   1659: goto -477 -> 1182
      //   1662: getstatic 17	o/Iq$ˊ:ॱ	I
      //   1665: istore_3
      //   1666: iload_3
      //   1667: bipush 49
      //   1669: iand
      //   1670: iconst_m1
      //   1671: ixor
      //   1672: iload_3
      //   1673: bipush 49
      //   1675: ior
      //   1676: iand
      //   1677: iload_3
      //   1678: bipush 49
      //   1680: iand
      //   1681: iconst_1
      //   1682: ishl
      //   1683: iconst_m1
      //   1684: ixor
      //   1685: isub
      //   1686: iconst_1
      //   1687: isub
      //   1688: istore_3
      //   1689: iload_3
      //   1690: sipush 128
      //   1693: irem
      //   1694: putstatic 19	o/Iq$ˊ:ˊ	I
      //   1697: iload_3
      //   1698: iconst_2
      //   1699: irem
      //   1700: ifne +6 -> 1706
      //   1703: goto -1032 -> 671
      //   1706: goto +147 -> 1853
      //   1709: getstatic 17	o/Iq$ˊ:ॱ	I
      //   1712: istore 4
      //   1714: iload 4
      //   1716: bipush 103
      //   1718: ixor
      //   1719: iload 4
      //   1721: bipush 103
      //   1723: iand
      //   1724: ior
      //   1725: iconst_1
      //   1726: ishl
      //   1727: istore_3
      //   1728: iload 4
      //   1730: bipush -104
      //   1732: iand
      //   1733: iload 4
      //   1735: iconst_m1
      //   1736: ixor
      //   1737: bipush 103
      //   1739: iand
      //   1740: ior
      //   1741: ineg
      //   1742: istore 4
      //   1744: iload_3
      //   1745: iload 4
      //   1747: ior
      //   1748: iconst_1
      //   1749: ishl
      //   1750: iload_3
      //   1751: iload 4
      //   1753: ixor
      //   1754: isub
      //   1755: istore_3
      //   1756: iload_3
      //   1757: sipush 128
      //   1760: irem
      //   1761: putstatic 19	o/Iq$ˊ:ˊ	I
      //   1764: iload_3
      //   1765: iconst_2
      //   1766: irem
      //   1767: ifne +6 -> 1773
      //   1770: goto -883 -> 887
      //   1773: goto -1037 -> 736
      //   1776: aload 7
      //   1778: aload_1
      //   1779: aload_2
      //   1780: aload 9
      //   1782: invokespecial 739	o/Iq$ˊ:ˎ	([BLjava/security/Key;Ljavax/crypto/Cipher;)Ljava/lang/String;
      //   1785: astore_1
      //   1786: goto +108 -> 1894
      //   1789: aload_2
      //   1790: bipush 88
      //   1792: sipush 22412
      //   1795: bipush 25
      //   1797: invokestatic 600	o/Iq$ˊ:ˋ	(ICI)Ljava/lang/String;
      //   1800: invokevirtual 604	java/lang/String:intern	()Ljava/lang/String;
      //   1803: invokestatic 705	o/vq:ˎ	(Ljava/lang/Object;Ljava/lang/String;)V
      //   1806: goto -144 -> 1662
      //   1809: bipush 48
      //   1811: istore_3
      //   1812: goto -185 -> 1627
      //   1815: iload_3
      //   1816: tableswitch	default:+24->1840, 0:+-984->832, 1:+-891->925
      //   1840: goto -915 -> 925
      //   1843: invokestatic 742	o/uQ:ॱ	()Ljava/util/List;
      //   1846: astore_1
      //   1847: goto -534 -> 1313
      //   1850: goto +228 -> 2078
      //   1853: aload_1
      //   1854: checkcast 744	java/lang/CharSequence
      //   1857: astore_1
      //   1858: bipush 87
      //   1860: ldc_w 745
      //   1863: iconst_1
      //   1864: invokestatic 600	o/Iq$ˊ:ˋ	(ICI)Ljava/lang/String;
      //   1867: astore 7
      //   1869: goto -961 -> 908
      //   1872: iconst_0
      //   1873: istore_3
      //   1874: goto -1231 -> 643
      //   1877: aload_1
      //   1878: checkcast 747	[Ljava/lang/String;
      //   1881: astore_1
      //   1882: aload_1
      //   1883: iconst_0
      //   1884: aaload
      //   1885: astore 7
      //   1887: aload_1
      //   1888: iconst_1
      //   1889: aaload
      //   1890: astore_1
      //   1891: goto -1120 -> 771
      //   1894: getstatic 17	o/Iq$ˊ:ॱ	I
      //   1897: istore 4
      //   1899: iload 4
      //   1901: iconst_3
      //   1902: ixor
      //   1903: iload 4
      //   1905: iconst_3
      //   1906: iand
      //   1907: ior
      //   1908: iconst_1
      //   1909: ishl
      //   1910: istore_3
      //   1911: iload 4
      //   1913: iconst_3
      //   1914: iand
      //   1915: iconst_m1
      //   1916: ixor
      //   1917: iload 4
      //   1919: iconst_3
      //   1920: ior
      //   1921: iand
      //   1922: ineg
      //   1923: istore 4
      //   1925: iload_3
      //   1926: iload 4
      //   1928: ior
      //   1929: iconst_1
      //   1930: ishl
      //   1931: iload_3
      //   1932: iload 4
      //   1934: ixor
      //   1935: isub
      //   1936: istore_3
      //   1937: iload_3
      //   1938: sipush 128
      //   1941: irem
      //   1942: putstatic 19	o/Iq$ˊ:ˊ	I
      //   1945: iload_3
      //   1946: iconst_2
      //   1947: irem
      //   1948: ifne +5 -> 1953
      //   1951: aload_1
      //   1952: areturn
      //   1953: aload_1
      //   1954: areturn
      //   1955: goto -1855 -> 100
      //   1958: bipush 95
      //   1960: istore_3
      //   1961: goto -697 -> 1264
      //   1964: getstatic 17	o/Iq$ˊ:ॱ	I
      //   1967: istore 4
      //   1969: iload 4
      //   1971: bipush 117
      //   1973: iand
      //   1974: iload 4
      //   1976: bipush 117
      //   1978: ixor
      //   1979: iload 4
      //   1981: bipush 117
      //   1983: iand
      //   1984: ior
      //   1985: iadd
      //   1986: istore 4
      //   1988: iload 4
      //   1990: sipush 128
      //   1993: irem
      //   1994: putstatic 19	o/Iq$ˊ:ˊ	I
      //   1997: iload 4
      //   1999: iconst_2
      //   2000: irem
      //   2001: ifne +6 -> 2007
      //   2004: goto -49 -> 1955
      //   2007: goto -1907 -> 100
      //   2010: goto -1487 -> 523
      //   2013: aload_1
      //   2014: checkcast 744	java/lang/CharSequence
      //   2017: invokeinterface 750 1 0
      //   2022: ifne +6 -> 2028
      //   2025: goto -533 -> 1492
      //   2028: goto -1179 -> 849
      //   2031: bipush 46
      //   2033: istore_3
      //   2034: goto -407 -> 1627
      //   2037: goto -657 -> 1380
      //   2040: aload 7
      //   2042: invokeinterface 703 1 0
      //   2047: checkcast 592	java/lang/String
      //   2050: astore_1
      //   2051: aconst_null
      //   2052: arraylength
      //   2053: istore_3
      //   2054: goto -41 -> 2013
      //   2057: aload_1
      //   2058: checkcast 729	java/util/Collection
      //   2061: astore_1
      //   2062: aload_1
      //   2063: ifnonnull +6 -> 2069
      //   2066: goto -1355 -> 711
      //   2069: goto -901 -> 1168
      //   2072: bipush 10
      //   2074: istore_3
      //   2075: goto -1515 -> 560
      //   2078: aload 7
      //   2080: aload_1
      //   2081: iconst_0
      //   2082: invokevirtual 753	o/vR:ॱ	(Ljava/lang/CharSequence;I)Ljava/util/List;
      //   2085: astore 8
      //   2087: goto -378 -> 1709
      //   2090: goto -2074 -> 16
      //   2093: astore_1
      //   2094: aload_1
      //   2095: athrow
      //   2096: iconst_1
      //   2097: istore_3
      //   2098: goto +22 -> 2120
      //   2101: aload 8
      //   2103: aload 8
      //   2105: invokeinterface 756 1 0
      //   2110: invokeinterface 760 2 0
      //   2115: astore 7
      //   2117: goto -990 -> 1127
      //   2120: iload_3
      //   2121: tableswitch	default:+23->2144, 0:+-731->1390, 1:+-278->1843
      //   2144: goto -754 -> 1390
      //   2147: sipush 225
      //   2150: sipush 5401
      //   2153: bipush 21
      //   2155: invokestatic 600	o/Iq$ˊ:ˋ	(ICI)Ljava/lang/String;
      //   2158: astore 8
      //   2160: goto -865 -> 1295
      //   2163: aload_1
      //   2164: iconst_0
      //   2165: iconst_0
      //   2166: bipush 7
      //   2168: invokestatic 600	o/Iq$ˊ:ˋ	(ICI)Ljava/lang/String;
      //   2171: invokevirtual 604	java/lang/String:intern	()Ljava/lang/String;
      //   2174: invokestatic 705	o/vq:ˎ	(Ljava/lang/Object;Ljava/lang/String;)V
      //   2177: goto -591 -> 1586
      //   2180: iconst_1
      //   2181: istore_3
      //   2182: goto -2150 -> 32
      //   2185: bipush 57
      //   2187: istore_3
      //   2188: goto -1447 -> 741
      // Local variable table:
      //   start	length	slot	name	signature
      //   0	2191	0	this	ˊ
      //   0	2191	1	paramString1	String
      //   0	2191	2	paramString2	String
      //   3	2185	3	i	int
      //   443	1558	4	j	int
      //   1030	37	5	k	int
      //   221	26	6	bool	boolean
      //   59	2057	7	localObject1	Object
      //   214	1945	8	localObject2	Object
      //   1375	406	9	localCipher	Cipher
      // Exception table:
      //   from	to	target	type
      //   1168	1179	526	java/lang/UnsupportedOperationException
      //   1168	1179	526	java/lang/NullPointerException
      //   1198	1203	526	java/lang/NullPointerException
      //   1238	1246	526	java/lang/UnsupportedOperationException
      //   1458	1462	526	java/lang/NumberFormatException
      //   1472	1480	526	java/lang/NumberFormatException
      //   1498	1511	526	java/lang/ArrayStoreException
      //   214	223	2093	java/lang/RuntimeException
      //   1498	1511	2093	java/lang/IndexOutOfBoundsException
      //   1511	1518	2093	java/lang/IndexOutOfBoundsException
      //   1511	1518	2093	java/lang/IllegalArgumentException
      //   1518	1525	2093	java/lang/IndexOutOfBoundsException
    }
    
    /* Error */
    public final String ˎ(String paramString1, String paramString2)
    {
      // Byte code:
      //   0: goto +308 -> 308
      //   3: aload_2
      //   4: astore 5
      //   6: getstatic 17	o/Iq$ˊ:ॱ	I
      //   9: istore 4
      //   11: iload 4
      //   13: bipush 105
      //   15: ior
      //   16: iconst_1
      //   17: ishl
      //   18: iload 4
      //   20: bipush 105
      //   22: ixor
      //   23: isub
      //   24: istore 4
      //   26: iload 4
      //   28: sipush 128
      //   31: irem
      //   32: putstatic 19	o/Iq$ˊ:ˊ	I
      //   35: iload 4
      //   37: iconst_2
      //   38: irem
      //   39: ifne +6 -> 45
      //   42: goto +12 -> 54
      //   45: goto +326 -> 371
      //   48: bipush 90
      //   50: istore_3
      //   51: goto +570 -> 621
      //   54: iconst_1
      //   55: istore 4
      //   57: goto +340 -> 397
      //   60: iload_3
      //   61: tableswitch	default:+23->84, 0:+401->462, 1:+125->186
      //   84: goto +102 -> 186
      //   87: aload 5
      //   89: iload_3
      //   90: ldc_w 761
      //   93: bipush 64
      //   95: invokestatic 600	o/Iq$ˊ:ˋ	(ICI)Ljava/lang/String;
      //   98: invokevirtual 604	java/lang/String:intern	()Ljava/lang/String;
      //   101: invokestatic 705	o/vq:ˎ	(Ljava/lang/Object;Ljava/lang/String;)V
      //   104: bipush 37
      //   106: istore_3
      //   107: goto +44 -> 151
      //   110: astore_1
      //   111: aload_1
      //   112: athrow
      //   113: getstatic 17	o/Iq$ˊ:ॱ	I
      //   116: istore_3
      //   117: iload_3
      //   118: bipush 41
      //   120: iand
      //   121: iload_3
      //   122: bipush 41
      //   124: ior
      //   125: iconst_m1
      //   126: ixor
      //   127: isub
      //   128: iconst_1
      //   129: isub
      //   130: istore_3
      //   131: iload_3
      //   132: sipush 128
      //   135: irem
      //   136: putstatic 19	o/Iq$ˊ:ˊ	I
      //   139: iload_3
      //   140: iconst_2
      //   141: irem
      //   142: ifne +6 -> 148
      //   145: goto +421 -> 566
      //   148: goto -100 -> 48
      //   151: getstatic 17	o/Iq$ˊ:ॱ	I
      //   154: bipush 26
      //   156: iadd
      //   157: iconst_1
      //   158: isub
      //   159: istore 4
      //   161: iload 4
      //   163: sipush 128
      //   166: irem
      //   167: putstatic 19	o/Iq$ˊ:ˊ	I
      //   170: iload 4
      //   172: iconst_2
      //   173: irem
      //   174: ifne +6 -> 180
      //   177: goto +6 -> 183
      //   180: goto +340 -> 520
      //   183: goto +337 -> 520
      //   186: bipush 37
      //   188: sipush 14249
      //   191: bipush 16
      //   193: invokestatic 600	o/Iq$ˊ:ˋ	(ICI)Ljava/lang/String;
      //   196: astore 5
      //   198: aload 6
      //   200: aload 5
      //   202: invokevirtual 604	java/lang/String:intern	()Ljava/lang/String;
      //   205: invokestatic 609	o/vq:ˋ	(Ljava/lang/Object;Ljava/lang/String;)V
      //   208: aload 6
      //   210: checkcast 659	java/security/Key
      //   213: astore 6
      //   215: aload_0
      //   216: checkcast 2	o/Iq$ˊ
      //   219: astore 5
      //   221: goto +31 -> 252
      //   224: iconst_0
      //   225: iconst_0
      //   226: bipush 7
      //   228: invokestatic 600	o/Iq$ˊ:ˋ	(ICI)Ljava/lang/String;
      //   231: astore 5
      //   233: aload 5
      //   235: invokevirtual 604	java/lang/String:intern	()Ljava/lang/String;
      //   238: astore 5
      //   240: aload_1
      //   241: aload 5
      //   243: invokestatic 705	o/vq:ˎ	(Ljava/lang/Object;Ljava/lang/String;)V
      //   246: bipush 7
      //   248: istore_3
      //   249: goto -246 -> 3
      //   252: aload 5
      //   254: aload_1
      //   255: aload 6
      //   257: invokespecial 763	o/Iq$ˊ:ˊ	(Ljava/lang/String;Ljava/security/Key;)[B
      //   260: iconst_2
      //   261: invokestatic 689	android/util/Base64:encodeToString	([BI)Ljava/lang/String;
      //   264: astore_1
      //   265: aload_0
      //   266: checkcast 2	o/Iq$ˊ
      //   269: astore 5
      //   271: goto +225 -> 496
      //   274: iload_3
      //   275: lookupswitch	default:+25->300, 5:+-51->224, 96:+102->377
      //   300: goto +77 -> 377
      //   303: iconst_5
      //   304: istore_3
      //   305: goto -31 -> 274
      //   308: goto +115 -> 423
      //   311: aload 5
      //   313: iload_3
      //   314: ldc_w 761
      //   317: bipush 24
      //   319: invokestatic 600	o/Iq$ˊ:ˋ	(ICI)Ljava/lang/String;
      //   322: invokevirtual 604	java/lang/String:intern	()Ljava/lang/String;
      //   325: invokestatic 705	o/vq:ˎ	(Ljava/lang/Object;Ljava/lang/String;)V
      //   328: bipush 31
      //   330: istore_3
      //   331: goto -180 -> 151
      //   334: aload_1
      //   335: invokevirtual 768	java/lang/StringBuilder:toString	()Ljava/lang/String;
      //   338: astore_1
      //   339: aload_1
      //   340: areturn
      //   341: aload_2
      //   342: bipush 87
      //   344: ldc_w 745
      //   347: iconst_1
      //   348: invokestatic 600	o/Iq$ˊ:ˋ	(ICI)Ljava/lang/String;
      //   351: invokevirtual 604	java/lang/String:intern	()Ljava/lang/String;
      //   354: invokevirtual 772	java/lang/StringBuilder:append	(Ljava/lang/String;)Ljava/lang/StringBuilder;
      //   357: aload_1
      //   358: invokevirtual 772	java/lang/StringBuilder:append	(Ljava/lang/String;)Ljava/lang/StringBuilder;
      //   361: astore_1
      //   362: goto -249 -> 113
      //   365: bipush 96
      //   367: istore_3
      //   368: goto -94 -> 274
      //   371: iconst_0
      //   372: istore 4
      //   374: goto +23 -> 397
      //   377: aload_1
      //   378: iconst_0
      //   379: iconst_0
      //   380: bipush 91
      //   382: invokestatic 600	o/Iq$ˊ:ˋ	(ICI)Ljava/lang/String;
      //   385: invokevirtual 604	java/lang/String:intern	()Ljava/lang/String;
      //   388: invokestatic 705	o/vq:ˎ	(Ljava/lang/Object;Ljava/lang/String;)V
      //   391: bipush 35
      //   393: istore_3
      //   394: goto -391 -> 3
      //   397: iload 4
      //   399: tableswitch	default:+21->420, 0:+-88->311, 1:+-312->87
      //   420: goto -109 -> 311
      //   423: getstatic 17	o/Iq$ˊ:ॱ	I
      //   426: istore_3
      //   427: iload_3
      //   428: bipush 51
      //   430: ior
      //   431: iconst_1
      //   432: ishl
      //   433: iload_3
      //   434: bipush 51
      //   436: ixor
      //   437: isub
      //   438: istore_3
      //   439: iload_3
      //   440: sipush 128
      //   443: irem
      //   444: putstatic 19	o/Iq$ˊ:ˊ	I
      //   447: iload_3
      //   448: iconst_2
      //   449: irem
      //   450: ifne +6 -> 456
      //   453: goto -88 -> 365
      //   456: goto -153 -> 303
      //   459: goto -118 -> 341
      //   462: aload 6
      //   464: bipush 37
      //   466: sipush 14249
      //   469: bipush 50
      //   471: invokestatic 600	o/Iq$ˊ:ˋ	(ICI)Ljava/lang/String;
      //   474: invokevirtual 604	java/lang/String:intern	()Ljava/lang/String;
      //   477: invokestatic 609	o/vq:ˋ	(Ljava/lang/Object;Ljava/lang/String;)V
      //   480: aload 6
      //   482: checkcast 659	java/security/Key
      //   485: astore 6
      //   487: aload_0
      //   488: checkcast 2	o/Iq$ˊ
      //   491: astore 5
      //   493: goto -241 -> 252
      //   496: aload 5
      //   498: aload 6
      //   500: aload_2
      //   501: invokespecial 774	o/Iq$ˊ:ˏ	(Ljava/security/Key;Ljava/lang/String;)Ljava/lang/String;
      //   504: astore_2
      //   505: new 765	java/lang/StringBuilder
      //   508: dup
      //   509: invokespecial 775	java/lang/StringBuilder:<init>	()V
      //   512: aload_2
      //   513: invokevirtual 772	java/lang/StringBuilder:append	(Ljava/lang/String;)Ljava/lang/StringBuilder;
      //   516: astore_2
      //   517: goto +134 -> 651
      //   520: iload_3
      //   521: iconst_0
      //   522: bipush 6
      //   524: invokestatic 600	o/Iq$ˊ:ˋ	(ICI)Ljava/lang/String;
      //   527: invokevirtual 604	java/lang/String:intern	()Ljava/lang/String;
      //   530: invokestatic 780	javax/crypto/KeyGenerator:getInstance	(Ljava/lang/String;)Ljavax/crypto/KeyGenerator;
      //   533: invokevirtual 784	javax/crypto/KeyGenerator:generateKey	()Ljavax/crypto/SecretKey;
      //   536: astore 6
      //   538: goto +34 -> 572
      //   541: aload_1
      //   542: invokevirtual 768	java/lang/StringBuilder:toString	()Ljava/lang/String;
      //   545: astore_1
      //   546: bipush 75
      //   548: iconst_0
      //   549: idiv
      //   550: istore_3
      //   551: aload_1
      //   552: areturn
      //   553: iconst_0
      //   554: istore_3
      //   555: goto -495 -> 60
      //   558: astore_1
      //   559: aload_1
      //   560: athrow
      //   561: iconst_1
      //   562: istore_3
      //   563: goto -503 -> 60
      //   566: bipush 89
      //   568: istore_3
      //   569: goto +52 -> 621
      //   572: getstatic 19	o/Iq$ˊ:ˊ	I
      //   575: istore_3
      //   576: iload_3
      //   577: bipush -120
      //   579: iand
      //   580: iload_3
      //   581: iconst_m1
      //   582: ixor
      //   583: bipush 119
      //   585: iand
      //   586: ior
      //   587: iload_3
      //   588: bipush 119
      //   590: iand
      //   591: iconst_1
      //   592: ishl
      //   593: ineg
      //   594: ineg
      //   595: iconst_m1
      //   596: ixor
      //   597: isub
      //   598: iconst_1
      //   599: isub
      //   600: istore_3
      //   601: iload_3
      //   602: sipush 128
      //   605: irem
      //   606: putstatic 17	o/Iq$ˊ:ॱ	I
      //   609: iload_3
      //   610: iconst_2
      //   611: irem
      //   612: ifeq +6 -> 618
      //   615: goto -54 -> 561
      //   618: goto -65 -> 553
      //   621: iload_3
      //   622: lookupswitch	default:+26->648, 89:+-81->541, 90:+-288->334
      //   648: goto -107 -> 541
      //   651: getstatic 17	o/Iq$ˊ:ॱ	I
      //   654: istore_3
      //   655: iload_3
      //   656: bipush 107
      //   658: iand
      //   659: iconst_m1
      //   660: ixor
      //   661: iload_3
      //   662: bipush 107
      //   664: ior
      //   665: iand
      //   666: iload_3
      //   667: bipush 107
      //   669: iand
      //   670: iconst_1
      //   671: ishl
      //   672: iadd
      //   673: istore_3
      //   674: iload_3
      //   675: sipush 128
      //   678: irem
      //   679: putstatic 19	o/Iq$ˊ:ˊ	I
      //   682: iload_3
      //   683: iconst_2
      //   684: irem
      //   685: ifne +6 -> 691
      //   688: goto -229 -> 459
      //   691: goto -350 -> 341
      // Local variable table:
      //   start	length	slot	name	signature
      //   0	694	0	this	ˊ
      //   0	694	1	paramString1	String
      //   0	694	2	paramString2	String
      //   50	635	3	i	int
      //   9	389	4	j	int
      //   4	493	5	localObject1	Object
      //   198	339	6	localObject2	Object
      // Exception table:
      //   from	to	target	type
      //   151	161	110	java/lang/NullPointerException
      //   161	170	110	java/lang/NullPointerException
      //   224	233	110	java/lang/UnsupportedOperationException
      //   224	233	110	java/lang/IllegalStateException
      //   233	240	110	java/lang/UnsupportedOperationException
      //   233	240	110	java/lang/IllegalStateException
      //   240	246	110	java/lang/UnsupportedOperationException
      //   240	246	110	java/lang/IllegalStateException
      //   113	117	558	java/lang/NullPointerException
      //   131	139	558	java/lang/NullPointerException
      //   131	139	558	java/lang/ArrayStoreException
      //   161	170	558	java/lang/IndexOutOfBoundsException
      //   186	198	558	java/lang/NullPointerException
      //   233	240	558	java/lang/IllegalArgumentException
      //   240	246	558	java/lang/IllegalArgumentException
      //   240	246	558	java/lang/RuntimeException
      //   334	339	558	java/lang/RuntimeException
    }
    
    public final KeyPair ˏ(String paramString, int paramInt)
    {
      break label274;
      switch (paramInt)
      {
      default: 
        break;
      }
      label35:
      String str;
      try
      {
        vq.ˎ(paramString, str);
        try
        {
          paramString = KeyPairGenerator.getInstance(paramString);
          paramString.initialize(paramInt);
        }
        catch (IndexOutOfBoundsException|IllegalStateException|UnsupportedOperationException|Exception paramString)
        {
          int j;
          throw paramString;
        }
        j = ॱ;
        i = (j | 0x27) << 1;
        j = (j | 0x27) & (j & 0x27 ^ 0xFFFFFFFF);
        i = (-j & i) + (i | -j);
        ˊ = i % 128;
        if (i % 2 == 0) {
          break label294;
        }
      }
      catch (ClassCastException|ArrayStoreException|NullPointerException|NumberFormatException paramString)
      {
        throw paramString;
      }
      paramString = paramString.genKeyPair();
      paramInt = 607;
      int i = 19;
      for (;;)
      {
        switch (i)
        {
        default: 
          break label277;
          vq.ˋ(paramString, ˋ(paramInt, 44575, i).intern());
          break label300;
          for (;;)
          {
            paramInt = 84;
            break;
            paramString = paramString.genKeyPair();
            paramInt = 16580;
            i = 83;
            break label163;
            paramInt = ॱ;
            paramInt = (paramInt ^ 0x40) + ((paramInt & 0x40) << 1) + 0 - 1;
            ˊ = paramInt % 128;
            if (paramInt % 2 == 0) {
              break label242;
            }
          }
          paramInt = 59;
          break;
          i = 30;
          break;
        case 30: 
          str = ˋ(598, '\000', 9).intern();
          break label35;
          break;
        case 43: 
          label163:
          label242:
          label274:
          label277:
          str = ˋ(23587, '\000', 32).intern();
          break label35;
          label294:
          i = 43;
        }
      }
      label300:
      i = ॱ;
      paramInt = i & 0x4B;
      i = i & 0x4B | i ^ 0x4B;
      paramInt = ((paramInt | i) << 1) - (paramInt ^ i);
      ˊ = paramInt % 128;
      if (paramInt % 2 == 0) {
        return paramString;
      }
      return paramString;
    }
  }
}
