package o;

public final class Ir
  implements xx
{
  private static final String BLACKLIST_DEVICE_URI = "/fraudprevention/deviceid";
  private static final String CONTENT_TYPE_IMAGE = "image/png";
  public static final if Companion;
  private static final String PREREGISTER_PATH = "/btwallet/api/v1/wallet";
  private static int ˊ = 0;
  private static char[] ˋ;
  private static long ˎ = 0L;
  private static int ॱ = 0;
  
  /* Error */
  static
  {
    // Byte code:
    //   0: goto +77 -> 77
    //   3: new 8	o/Ir$if
    //   6: dup
    //   7: aconst_null
    //   8: invokespecial 45	o/Ir$if:<init>	(Lo/vn;)V
    //   11: astore_1
    //   12: aload_1
    //   13: putstatic 47	o/Ir:Companion	Lo/Ir$if;
    //   16: goto +6 -> 22
    //   19: astore_1
    //   20: aload_1
    //   21: athrow
    //   22: getstatic 49	o/Ir:ˊ	I
    //   25: istore_0
    //   26: iload_0
    //   27: bipush 69
    //   29: ixor
    //   30: iload_0
    //   31: bipush 69
    //   33: iand
    //   34: ior
    //   35: iconst_1
    //   36: ishl
    //   37: iload_0
    //   38: bipush 69
    //   40: iand
    //   41: iconst_m1
    //   42: ixor
    //   43: iload_0
    //   44: bipush 69
    //   46: ior
    //   47: iand
    //   48: ineg
    //   49: iconst_m1
    //   50: ixor
    //   51: isub
    //   52: iconst_1
    //   53: isub
    //   54: istore_0
    //   55: iload_0
    //   56: sipush 128
    //   59: irem
    //   60: putstatic 51	o/Ir:ॱ	I
    //   63: iload_0
    //   64: iconst_2
    //   65: irem
    //   66: ifeq +6 -> 72
    //   69: goto +4 -> 73
    //   72: return
    //   73: return
    //   74: astore_1
    //   75: aload_1
    //   76: athrow
    //   77: iconst_0
    //   78: putstatic 51	o/Ir:ॱ	I
    //   81: iconst_1
    //   82: putstatic 49	o/Ir:ˊ	I
    //   85: invokestatic 53	o/Ir:ˊ	()V
    //   88: goto -85 -> 3
    // Local variable table:
    //   start	length	slot	name	signature
    //   25	41	0	i	int
    //   11	2	1	localIf	if
    //   19	2	1	localUnsupportedOperationException	UnsupportedOperationException
    //   74	2	1	localRuntimeException	RuntimeException
    // Exception table:
    //   from	to	target	type
    //   55	63	19	java/lang/UnsupportedOperationException
    //   77	81	19	java/lang/Exception
    //   81	85	19	java/lang/Exception
    //   81	85	19	java/lang/ArrayStoreException
    //   85	88	19	java/lang/Exception
    //   12	16	74	java/lang/RuntimeException
    //   22	26	74	java/lang/RuntimeException
    //   55	63	74	java/lang/RuntimeException
  }
  
  public Ir() {}
  
  static void ˊ()
  {
    ˎ = 5523666688134812356L;
    ˋ = new char[] { 99, 4780, 9705, 14373, 19326, 47, 4774, 9724, 14395, 19313, 23992, 28916, -31943, -27052, -22325, -17463, -12772, -7847, -3109, 1742, 6477, 11375, 16243, 20905, 25824, 30524, -30095, -25428, -6981, -2444, -16075, -8963, -20566, -18065, -27614, 26578, 29343, 19534, 24350, 47, 4770, 9722, 14381, 19301, 23984, 28904, -31954, -27067, -22382, -17459, -12798, -7868, -3171, 1751, 6418, 11375, 16224, 20909, 25850, 30521, -30089, -25411, -20491, -15868, 23769, 19978, 31058, 25746, 6110, 268, 11335, 114, 4769, 9721, 14393, 19317, 23975, 28908, -31970, -27051, -22387, -17468, -12792, -7851, -3194, 114, 4769, 9721, 14393, 19317, 23975, 28908, -31970, -27051, -22387, -17468, -12792, -7851, -3194, 1686, 6430, 11317, 16237, 20900, 25832, 30584, -30147, -12656, -9121, -5346, -2357, -31332, -27823, -16871, 19916, 22705, 26179, 30008, 232, 12208, 15716, -14274, -10243, -7433, -3708, -24748, -21995, -17983, 17540, 21087, 101, 4778, 9707, 14398, 19305, 23972, 28908, -31943, -27068, -22346, -17459, -12771, -7867, -3183, 1739, 6408, 11266, 16241, 20897, 25824, 30516, -30095, -25430, -20558, -15870, -10927, -6271, -1344, 3348, 8220, 13009, 32267, 27844, 23425, 17997, 13590, 9106, 3712, -698, -6105, -10513, -14939, -20383, -24772, -29260, 30901, 26490, 21067, 16670, 12249, 6804, 2380, -3047, -7468, -11866, -17299, -21699, -26123, -31583, 29547, 24104, 19655, 15293, 9884, 5444, 40, -4415, -8807, -14248, -18667, -23098, -28485, 32549, 67, 4779, 9702, 14392, 19317, 23994, 28908, -31887, -27020, -22371, -17448, -12791, 114, 4769, 9723, 14396, 19327, 23994, 28907, -31943, -27038, -22383, -17471, -12800, -7852, -3183, 1738, 19217, 22978, 28312, 29535, 28, 5849, 15240, -14246, -8959, -7182, -3934, -31389, -21961, -18190, 19881, 21041, 26433, 29714, 6850, 12163, 15447, -16033, -10350, -31755, -28390, -22969, -17536, -14140, -8675, -3256, 69, 4796, 9707, 14377, 19296, 23968, 28913, -31949, -27058, -22332, -17461, -12787, -7867, -3181, 1744, 6408, 11360, 16237, 20902, 25772, 30496, -30091, -25439, -20496, -15857, -10939, -6260, -1396, 3349, 8282, 12955, 17870, 22777, 27444, 32380, -28507, -23553, -18886, -14046, -9220, 99, 4780, 9705, 14373, 19326, 24058, 28904, -31954, -27057, -22393, -17459, -12791, -7852, -3108, 1738, 6425, 11313, 16241, 20909, 25855, 30500, -30122, -25427, -20491, -15860, -10944, -6259, -1314, 3422, 8278, 12941, 17877, 22764, 27424, 32288, -28443, -23623, 105, 4777, 9705, 14379, 19317, 24059, 28904, -31950, -27065, -9021, -12763, -1692, -6999, -26626, -32464, -21383, 24494, 19086, 29699, 26445, 4760, 15865, 12058, -9653, -14968, -3935, -7190, -29397, -18327, -21512, 22205, -10553, -15342, -3234, -4474, -25121, -29935, -22945, 21902, 16623, 32301, 28000, 6373, 14332, 9505, -12175, -12364, -1315, -5758, -30963, -19902, -24169, 23744, 18957, 31071, 5298, 959, 12571, 11358, -9328, -2369, -7066, 97, 4788, 9720, 14341, 19326, 23975, 28908, -31939, -27058, -22393, -17459, -12763, -7852, 99, 4779, 9722, 14398, 19317, 23992, 28921, -31960, -27063, -22389, -17466, -12763, -7852, 67, 4785, 9722, 14398, 19317, 23994, 28908, -31976, -27071, -22384, -17459, -31601, -27030, -24281, -17170, -12364, -30891, -27216, -23825, -16588, -13214, -9568, -2112, 1065, 68, 4769, 9726, 14373, 19315, 23985, 28885, -31939, -27058, -22395, -17457, -12791, -7870, -3110, 1759, 6425, 11316, 16172, 20961, 18754, 23463, 27896, 28963, 629, 5303, 14801, -13783, 65, 4746, 9676, 14366, 19295, 23965, 28892, 76, 4773, 9702, 14379, 19301, 23989, 28927, -31943, 77, 4779, 9706, 14373, 19324, 23985, 28889, -31956, -27056, -22350, -17459, -12770, -7869, -3171, 1751, 6418, -27588, -31038, -20096, -21427, -8418, -13873, -7038, 5953, 554, 114, 4769, 9723, 14396, 19327, 23994, 28907, -31943, -27038, -22389, -17460, -12779, -7819, -3174, 1755, 6414, 11321, 16244, 20924, 25833, 30516, -30137, -25428, -20498, -15863, -10934, -6257, 82, 4769, 9723, 14396, 19327, 23994, 28907, -31943, -27136, -22394, -17465, -12792, -7863, -3116, 1756, 6425, 11299, 16246, 20913, 25852, 30500, -30095, -25412, -20548, -15862, -10921, -6265, -1342, 3408, 8263, 12940, 17870, 22761, 27434, 32367, -28426, -23632, 83, 4784, 9705, 14370, 19316, 23989, 28906, -31944, -27037, -22388, -17463, -12770, -7869, -3183, 1740, 6415, 11374, 16209, 20892, 25802, 30479, -30164, -25354, -20494, -15871, -10935, -6259, -1404, 3417, 67, 4780, 9705, 14398, 19299, 23985, 28908, -31886, -27066, -22389, -17446, -12766, -7855, -3175, 1757, 6484, 11299, 16236, 20905, 25854, 30499, -30095, -25428, -20526, -15871, -10935, -6259, -1403, -17640, -22073, -24942, -31914, -4026, -6463, -13425, 14404, 11576, 5117, 170, 30010, 23076, 18663, -16914, -23959, -26793, -31743, -5430, -8230, -13230, 12557, 10126, 5252, 31097, 28220, 23731, 16820, -18829, -25810, -30238, -278, -7294, -12213, -15090, 11231, 6342, 3400, 29199, 24796, 21943, -17860, -20686, -25093, -32088, -2203, -7072, -13607, 16322, 11392, 4439, 1556, 29889, 40, 4784, 9696, 14373, 19299, 24052, 28921, -31953, -27136, -22386, -17463, -12774, -7855, -3110, 1748, 6429, 11310, 16227, 20966, 25823, 30500, -30106, -25423, -20494, -15865, -10995, -6202, -1333, 3349, 8256, 12986, 17861, 22772, 27425, 32379, -28444, -23565, -18884, -13959, -9298, -4397, 257, 5212, 9925, -23161, -18604, -32757, -25137, -4464, -1981, -10925, 9931, 13216, 3424, 7721, 27612, 17569, 22135, -23707, -17231, -30324, 82, 4769, 9721, 14393, 19317, 23975, 28908, -31876, -27070, -22389, -17460, -12779, -7920, -3170, 1739, 6419, 11310, 16164, 20923, 25848, 30498, -30083, -25418, -20485, -15782, -11004, 112, 4785, 9706, 14368, 19321, 23991, 28883, -31943, -27047, -22332, -21386, -16763, -30241, -27624, -6309, -3682, -9009, 12061, 14884, 1186, 6115, 25132, 19821, 24560, -21767, -19146, -32761, -27822, -619, -14120, -9472, 9813, 12440, 920, 28206, 31091, 19363, 22246, -24204, -29597, -24920, -5654, -2867, -14578, -11701, 15570, 3988 };
  }
  
  /* Error */
  private final void ˊ(xG paramXG, xG.if paramIf, boolean paramBoolean)
  {
    // Byte code:
    //   0: goto +640 -> 640
    //   3: iconst_0
    //   4: istore 4
    //   6: goto +838 -> 844
    //   9: iconst_0
    //   10: istore 4
    //   12: goto +1233 -> 1245
    //   15: goto +17 -> 32
    //   18: astore_1
    //   19: aload_1
    //   20: invokevirtual 740	java/lang/Throwable:getCause	()Ljava/lang/Throwable;
    //   23: astore_2
    //   24: aload_2
    //   25: ifnull +5 -> 30
    //   28: aload_2
    //   29: athrow
    //   30: aload_1
    //   31: athrow
    //   32: bipush 7
    //   34: sipush 406
    //   37: ldc_w 741
    //   40: invokestatic 746	o/O:ˋ	(IIC)Ljava/lang/Object;
    //   43: checkcast 748	java/lang/Class
    //   46: ldc_w 750
    //   49: aconst_null
    //   50: invokevirtual 754	java/lang/Class:getMethod	(Ljava/lang/String;[Ljava/lang/Class;)Ljava/lang/reflect/Method;
    //   53: aload 9
    //   55: aconst_null
    //   56: invokevirtual 760	java/lang/reflect/Method:invoke	(Ljava/lang/Object;[Ljava/lang/Object;)Ljava/lang/Object;
    //   59: astore 9
    //   61: goto +17 -> 78
    //   64: astore_2
    //   65: aload_2
    //   66: invokevirtual 740	java/lang/Throwable:getCause	()Ljava/lang/Throwable;
    //   69: astore_1
    //   70: aload_1
    //   71: ifnull +5 -> 76
    //   74: aload_1
    //   75: athrow
    //   76: aload_2
    //   77: athrow
    //   78: iconst_4
    //   79: sipush 402
    //   82: iconst_0
    //   83: invokestatic 746	o/O:ˋ	(IIC)Ljava/lang/Object;
    //   86: checkcast 748	java/lang/Class
    //   89: ldc_w 762
    //   92: aconst_null
    //   93: invokevirtual 754	java/lang/Class:getMethod	(Ljava/lang/String;[Ljava/lang/Class;)Ljava/lang/reflect/Method;
    //   96: aload 9
    //   98: aconst_null
    //   99: invokevirtual 760	java/lang/reflect/Method:invoke	(Ljava/lang/Object;[Ljava/lang/Object;)Ljava/lang/Object;
    //   102: checkcast 764	java/lang/String
    //   105: astore 9
    //   107: aload 7
    //   109: aload 8
    //   111: aload 9
    //   113: invokevirtual 769	o/xG$if:ˎ	(Ljava/lang/String;Ljava/lang/String;)Lo/xG$if;
    //   116: sipush 491
    //   119: iconst_0
    //   120: bipush 16
    //   122: invokestatic 772	o/Ir:ˏ	(ICI)Ljava/lang/String;
    //   125: invokevirtual 776	java/lang/String:intern	()Ljava/lang/String;
    //   128: iconst_5
    //   129: invokestatic 780	java/lang/String:valueOf	(I)Ljava/lang/String;
    //   132: invokevirtual 769	o/xG$if:ˎ	(Ljava/lang/String;Ljava/lang/String;)Lo/xG$if;
    //   135: astore 7
    //   137: sipush 507
    //   140: ldc_w 781
    //   143: bipush 9
    //   145: invokestatic 772	o/Ir:ˏ	(ICI)Ljava/lang/String;
    //   148: astore 8
    //   150: goto +295 -> 445
    //   153: astore_1
    //   154: aload_1
    //   155: athrow
    //   156: new 726	java/lang/NullPointerException
    //   159: dup
    //   160: invokespecial 782	java/lang/NullPointerException:<init>	()V
    //   163: athrow
    //   164: iconst_1
    //   165: istore 4
    //   167: goto +609 -> 776
    //   170: bipush 13
    //   172: istore 4
    //   174: goto +695 -> 869
    //   177: aload 7
    //   179: iload 4
    //   181: sipush 18694
    //   184: bipush 8
    //   186: invokestatic 772	o/Ir:ˏ	(ICI)Ljava/lang/String;
    //   189: invokevirtual 776	java/lang/String:intern	()Ljava/lang/String;
    //   192: sipush 476
    //   195: iconst_0
    //   196: bipush 7
    //   198: invokestatic 772	o/Ir:ˏ	(ICI)Ljava/lang/String;
    //   201: invokevirtual 776	java/lang/String:intern	()Ljava/lang/String;
    //   204: invokevirtual 769	o/xG$if:ˎ	(Ljava/lang/String;Ljava/lang/String;)Lo/xG$if;
    //   207: astore 7
    //   209: sipush 483
    //   212: iconst_0
    //   213: bipush 8
    //   215: invokestatic 772	o/Ir:ˏ	(ICI)Ljava/lang/String;
    //   218: invokevirtual 776	java/lang/String:intern	()Ljava/lang/String;
    //   221: astore 8
    //   223: iconst_4
    //   224: sipush 402
    //   227: iconst_0
    //   228: invokestatic 746	o/O:ˋ	(IIC)Ljava/lang/Object;
    //   231: checkcast 748	java/lang/Class
    //   234: ldc_w 783
    //   237: invokevirtual 787	java/lang/Class:getField	(Ljava/lang/String;)Ljava/lang/reflect/Field;
    //   240: aconst_null
    //   241: invokevirtual 793	java/lang/reflect/Field:get	(Ljava/lang/Object;)Ljava/lang/Object;
    //   244: astore 9
    //   246: goto +785 -> 1031
    //   249: getstatic 49	o/Ir:ˊ	I
    //   252: istore 5
    //   254: iload 5
    //   256: bipush 85
    //   258: iand
    //   259: iload 5
    //   261: bipush 85
    //   263: ixor
    //   264: iload 5
    //   266: bipush 85
    //   268: iand
    //   269: ior
    //   270: iadd
    //   271: istore 5
    //   273: iload 5
    //   275: sipush 128
    //   278: irem
    //   279: putstatic 51	o/Ir:ॱ	I
    //   282: iload 5
    //   284: iconst_2
    //   285: irem
    //   286: ifeq +6 -> 292
    //   289: goto +732 -> 1021
    //   292: goto -115 -> 177
    //   295: sipush 441
    //   298: ldc_w 794
    //   301: bipush 8
    //   303: invokestatic 772	o/Ir:ˏ	(ICI)Ljava/lang/String;
    //   306: astore 8
    //   308: aload 8
    //   310: invokevirtual 776	java/lang/String:intern	()Ljava/lang/String;
    //   313: astore 8
    //   315: goto +17 -> 332
    //   318: astore_1
    //   319: aload_1
    //   320: invokevirtual 740	java/lang/Throwable:getCause	()Ljava/lang/Throwable;
    //   323: astore_2
    //   324: aload_2
    //   325: ifnull +5 -> 330
    //   328: aload_2
    //   329: athrow
    //   330: aload_1
    //   331: athrow
    //   332: iconst_3
    //   333: iconst_0
    //   334: ldc_w 795
    //   337: invokestatic 746	o/O:ˋ	(IIC)Ljava/lang/Object;
    //   340: checkcast 748	java/lang/Class
    //   343: ldc_w 796
    //   346: aconst_null
    //   347: invokevirtual 754	java/lang/Class:getMethod	(Ljava/lang/String;[Ljava/lang/Class;)Ljava/lang/reflect/Method;
    //   350: aconst_null
    //   351: aconst_null
    //   352: invokevirtual 760	java/lang/reflect/Method:invoke	(Ljava/lang/Object;[Ljava/lang/Object;)Ljava/lang/Object;
    //   355: astore 9
    //   357: aload 9
    //   359: sipush 449
    //   362: iconst_0
    //   363: bipush 19
    //   365: invokestatic 772	o/Ir:ˏ	(ICI)Ljava/lang/String;
    //   368: invokevirtual 776	java/lang/String:intern	()Ljava/lang/String;
    //   371: invokestatic 801	o/vq:ˋ	(Ljava/lang/Object;Ljava/lang/String;)V
    //   374: goto +17 -> 391
    //   377: astore_1
    //   378: aload_1
    //   379: invokevirtual 740	java/lang/Throwable:getCause	()Ljava/lang/Throwable;
    //   382: astore_2
    //   383: aload_2
    //   384: ifnull +5 -> 389
    //   387: aload_2
    //   388: athrow
    //   389: aload_1
    //   390: athrow
    //   391: iconst_3
    //   392: iconst_0
    //   393: ldc_w 795
    //   396: invokestatic 746	o/O:ˋ	(IIC)Ljava/lang/Object;
    //   399: checkcast 748	java/lang/Class
    //   402: ldc_w 802
    //   405: aconst_null
    //   406: invokevirtual 754	java/lang/Class:getMethod	(Ljava/lang/String;[Ljava/lang/Class;)Ljava/lang/reflect/Method;
    //   409: aload 9
    //   411: aconst_null
    //   412: invokevirtual 760	java/lang/reflect/Method:invoke	(Ljava/lang/Object;[Ljava/lang/Object;)Ljava/lang/Object;
    //   415: checkcast 764	java/lang/String
    //   418: astore 9
    //   420: aload 7
    //   422: aload 8
    //   424: aload 9
    //   426: invokevirtual 769	o/xG$if:ˎ	(Ljava/lang/String;Ljava/lang/String;)Lo/xG$if;
    //   429: astore 7
    //   431: sipush 468
    //   434: istore 4
    //   436: goto -187 -> 249
    //   439: invokestatic 804	o/vq:ˎ	()V
    //   442: goto +757 -> 1199
    //   445: aload 8
    //   447: invokevirtual 776	java/lang/String:intern	()Ljava/lang/String;
    //   450: astore 8
    //   452: getstatic 809	o/Ip:Companion	Lo/Ip$ˊ;
    //   455: astore 9
    //   457: aload 6
    //   459: sipush 412
    //   462: iconst_0
    //   463: bipush 13
    //   465: invokestatic 772	o/Ir:ˏ	(ICI)Ljava/lang/String;
    //   468: invokevirtual 776	java/lang/String:intern	()Ljava/lang/String;
    //   471: invokestatic 801	o/vq:ˋ	(Ljava/lang/Object;Ljava/lang/String;)V
    //   474: aload 9
    //   476: aload_1
    //   477: aload 6
    //   479: aload_2
    //   480: iload_3
    //   481: invokevirtual 814	o/Ip$ˊ:ˏ	(Lo/xG;Ljava/lang/String;Ljava/lang/String;Z)Ljava/lang/String;
    //   484: astore_1
    //   485: aload_1
    //   486: ifnonnull +6 -> 492
    //   489: goto +1249 -> 1738
    //   492: goto +830 -> 1322
    //   495: bipush 96
    //   497: istore 4
    //   499: goto +370 -> 869
    //   502: goto +17 -> 519
    //   505: astore_1
    //   506: aload_1
    //   507: invokevirtual 740	java/lang/Throwable:getCause	()Ljava/lang/Throwable;
    //   510: astore_2
    //   511: aload_2
    //   512: ifnull +5 -> 517
    //   515: aload_2
    //   516: athrow
    //   517: aload_1
    //   518: athrow
    //   519: bipush 7
    //   521: sipush 406
    //   524: ldc_w 741
    //   527: invokestatic 746	o/O:ˋ	(IIC)Ljava/lang/Object;
    //   530: checkcast 748	java/lang/Class
    //   533: ldc_w 750
    //   536: aconst_null
    //   537: invokevirtual 754	java/lang/Class:getMethod	(Ljava/lang/String;[Ljava/lang/Class;)Ljava/lang/reflect/Method;
    //   540: aload 9
    //   542: aconst_null
    //   543: invokevirtual 760	java/lang/reflect/Method:invoke	(Ljava/lang/Object;[Ljava/lang/Object;)Ljava/lang/Object;
    //   546: astore 9
    //   548: goto +17 -> 565
    //   551: astore_2
    //   552: aload_2
    //   553: invokevirtual 740	java/lang/Throwable:getCause	()Ljava/lang/Throwable;
    //   556: astore_1
    //   557: aload_1
    //   558: ifnull +5 -> 563
    //   561: aload_1
    //   562: athrow
    //   563: aload_2
    //   564: athrow
    //   565: iconst_4
    //   566: sipush 402
    //   569: iconst_0
    //   570: invokestatic 746	o/O:ˋ	(IIC)Ljava/lang/Object;
    //   573: checkcast 748	java/lang/Class
    //   576: ldc_w 762
    //   579: aconst_null
    //   580: invokevirtual 754	java/lang/Class:getMethod	(Ljava/lang/String;[Ljava/lang/Class;)Ljava/lang/reflect/Method;
    //   583: aload 9
    //   585: aconst_null
    //   586: invokevirtual 760	java/lang/reflect/Method:invoke	(Ljava/lang/Object;[Ljava/lang/Object;)Ljava/lang/Object;
    //   589: checkcast 764	java/lang/String
    //   592: astore 9
    //   594: aload 7
    //   596: aload 8
    //   598: aload 9
    //   600: invokevirtual 769	o/xG$if:ˎ	(Ljava/lang/String;Ljava/lang/String;)Lo/xG$if;
    //   603: sipush 22605
    //   606: iconst_0
    //   607: bipush 26
    //   609: invokestatic 772	o/Ir:ˏ	(ICI)Ljava/lang/String;
    //   612: invokevirtual 776	java/lang/String:intern	()Ljava/lang/String;
    //   615: iconst_2
    //   616: invokestatic 780	java/lang/String:valueOf	(I)Ljava/lang/String;
    //   619: invokevirtual 769	o/xG$if:ˎ	(Ljava/lang/String;Ljava/lang/String;)Lo/xG$if;
    //   622: astore 7
    //   624: sipush 18261
    //   627: ldc_w 781
    //   630: bipush 121
    //   632: invokestatic 772	o/Ir:ˏ	(ICI)Ljava/lang/String;
    //   635: astore 8
    //   637: goto -192 -> 445
    //   640: goto +689 -> 1329
    //   643: invokestatic 820	java/util/UUID:randomUUID	()Ljava/util/UUID;
    //   646: invokevirtual 823	java/util/UUID:toString	()Ljava/lang/String;
    //   649: astore 6
    //   651: getstatic 828	o/Gv:ˊ	Lo/Gv$If;
    //   654: invokevirtual 833	o/Gv$If:ˎ	()Lo/Gv;
    //   657: invokevirtual 836	o/Gv:ˏॱ	()Ljava/lang/String;
    //   660: astore 7
    //   662: invokestatic 842	java/util/Calendar:getInstance	()Ljava/util/Calendar;
    //   665: astore 8
    //   667: aload 8
    //   669: sipush 346
    //   672: ldc_w 843
    //   675: bipush 22
    //   677: invokestatic 772	o/Ir:ˏ	(ICI)Ljava/lang/String;
    //   680: invokevirtual 776	java/lang/String:intern	()Ljava/lang/String;
    //   683: invokestatic 801	o/vq:ˋ	(Ljava/lang/Object;Ljava/lang/String;)V
    //   686: goto +303 -> 989
    //   689: getstatic 51	o/Ir:ॱ	I
    //   692: bipush 121
    //   694: iadd
    //   695: iconst_1
    //   696: isub
    //   697: istore 4
    //   699: iload 4
    //   701: iconst_m1
    //   702: iand
    //   703: iload 4
    //   705: iconst_m1
    //   706: ior
    //   707: iadd
    //   708: istore 4
    //   710: iload 4
    //   712: sipush 128
    //   715: irem
    //   716: putstatic 49	o/Ir:ˊ	I
    //   719: iload 4
    //   721: iconst_2
    //   722: irem
    //   723: ifne +6 -> 729
    //   726: goto +47 -> 773
    //   729: goto +74 -> 803
    //   732: aload 8
    //   734: sipush 399
    //   737: iconst_0
    //   738: bipush 13
    //   740: invokestatic 772	o/Ir:ˏ	(ICI)Ljava/lang/String;
    //   743: invokevirtual 776	java/lang/String:intern	()Ljava/lang/String;
    //   746: aload 7
    //   748: invokevirtual 769	o/xG$if:ˎ	(Ljava/lang/String;Ljava/lang/String;)Lo/xG$if;
    //   751: sipush 412
    //   754: iconst_0
    //   755: bipush 13
    //   757: invokestatic 772	o/Ir:ˏ	(ICI)Ljava/lang/String;
    //   760: invokevirtual 776	java/lang/String:intern	()Ljava/lang/String;
    //   763: aload 6
    //   765: invokevirtual 769	o/xG$if:ˎ	(Ljava/lang/String;Ljava/lang/String;)Lo/xG$if;
    //   768: astore 7
    //   770: goto -81 -> 689
    //   773: goto +30 -> 803
    //   776: iload 4
    //   778: tableswitch	default:+22->800, 0:+861->1639, 1:+912->1690
    //   800: goto +890 -> 1690
    //   803: aload 7
    //   805: sipush 425
    //   808: iconst_0
    //   809: bipush 11
    //   811: invokestatic 772	o/Ir:ˏ	(ICI)Ljava/lang/String;
    //   814: invokevirtual 776	java/lang/String:intern	()Ljava/lang/String;
    //   817: aload_2
    //   818: invokevirtual 769	o/xG$if:ˎ	(Ljava/lang/String;Ljava/lang/String;)Lo/xG$if;
    //   821: sipush 436
    //   824: ldc_w 844
    //   827: iconst_5
    //   828: invokestatic 772	o/Ir:ˏ	(ICI)Ljava/lang/String;
    //   831: invokevirtual 776	java/lang/String:intern	()Ljava/lang/String;
    //   834: aload 6
    //   836: invokevirtual 769	o/xG$if:ˎ	(Ljava/lang/String;Ljava/lang/String;)Lo/xG$if;
    //   839: astore 7
    //   841: goto +238 -> 1079
    //   844: iload 4
    //   846: tableswitch	default:+22->868, 0:+-690->156, 1:+531->1377
    //   868: return
    //   869: iload 4
    //   871: lookupswitch	default:+25->896, 13:+-228->643, 96:+507->1378
    //   896: goto -253 -> 643
    //   899: getstatic 51	o/Ir:ॱ	I
    //   902: istore 5
    //   904: iload 5
    //   906: bipush -14
    //   908: iand
    //   909: iload 5
    //   911: iconst_m1
    //   912: ixor
    //   913: bipush 13
    //   915: iand
    //   916: ior
    //   917: istore 4
    //   919: iload 5
    //   921: bipush 13
    //   923: iand
    //   924: iconst_1
    //   925: ishl
    //   926: ineg
    //   927: istore 5
    //   929: iload 5
    //   931: ineg
    //   932: iload 4
    //   934: ior
    //   935: iconst_1
    //   936: ishl
    //   937: iload 4
    //   939: iload 5
    //   941: ineg
    //   942: ixor
    //   943: isub
    //   944: istore 4
    //   946: iload 4
    //   948: sipush 128
    //   951: irem
    //   952: putstatic 49	o/Ir:ˊ	I
    //   955: iload 4
    //   957: iconst_2
    //   958: irem
    //   959: ifne +6 -> 965
    //   962: goto +309 -> 1271
    //   965: goto -526 -> 439
    //   968: aload 7
    //   970: aload 8
    //   972: aload_1
    //   973: invokevirtual 769	o/xG$if:ˎ	(Ljava/lang/String;Ljava/lang/String;)Lo/xG$if;
    //   976: pop
    //   977: goto +155 -> 1132
    //   980: goto -12 -> 968
    //   983: iconst_1
    //   984: istore 4
    //   986: goto -142 -> 844
    //   989: getstatic 51	o/Ir:ॱ	I
    //   992: bipush 30
    //   994: iadd
    //   995: iconst_1
    //   996: isub
    //   997: istore 4
    //   999: iload 4
    //   1001: sipush 128
    //   1004: irem
    //   1005: putstatic 49	o/Ir:ˊ	I
    //   1008: iload 4
    //   1010: iconst_2
    //   1011: irem
    //   1012: ifne +6 -> 1018
    //   1015: goto -851 -> 164
    //   1018: goto +262 -> 1280
    //   1021: goto -844 -> 177
    //   1024: bipush 19
    //   1026: istore 4
    //   1028: goto +539 -> 1567
    //   1031: getstatic 51	o/Ir:ॱ	I
    //   1034: istore 4
    //   1036: iload 4
    //   1038: bipush 41
    //   1040: ixor
    //   1041: iload 4
    //   1043: bipush 41
    //   1045: iand
    //   1046: ior
    //   1047: iconst_1
    //   1048: ishl
    //   1049: iload 4
    //   1051: bipush 41
    //   1053: ixor
    //   1054: isub
    //   1055: istore 4
    //   1057: iload 4
    //   1059: sipush 128
    //   1062: irem
    //   1063: putstatic 49	o/Ir:ˊ	I
    //   1066: iload 4
    //   1068: iconst_2
    //   1069: irem
    //   1070: ifne +6 -> 1076
    //   1073: goto +526 -> 1599
    //   1076: goto -52 -> 1024
    //   1079: getstatic 49	o/Ir:ˊ	I
    //   1082: istore 4
    //   1084: iload 4
    //   1086: bipush 125
    //   1088: ixor
    //   1089: iload 4
    //   1091: bipush 125
    //   1093: iand
    //   1094: ior
    //   1095: iconst_1
    //   1096: ishl
    //   1097: iload 4
    //   1099: bipush 125
    //   1101: ixor
    //   1102: ineg
    //   1103: iconst_m1
    //   1104: ixor
    //   1105: isub
    //   1106: iconst_1
    //   1107: isub
    //   1108: istore 4
    //   1110: iload 4
    //   1112: sipush 128
    //   1115: irem
    //   1116: putstatic 51	o/Ir:ॱ	I
    //   1119: iload 4
    //   1121: iconst_2
    //   1122: irem
    //   1123: ifeq +6 -> 1129
    //   1126: goto -1117 -> 9
    //   1129: goto +145 -> 1274
    //   1132: getstatic 51	o/Ir:ॱ	I
    //   1135: istore 5
    //   1137: iload 5
    //   1139: bipush 111
    //   1141: iand
    //   1142: iconst_m1
    //   1143: ixor
    //   1144: iload 5
    //   1146: bipush 111
    //   1148: ior
    //   1149: iand
    //   1150: istore 4
    //   1152: iload 5
    //   1154: bipush 111
    //   1156: iand
    //   1157: iconst_1
    //   1158: ishl
    //   1159: istore 5
    //   1161: iload 4
    //   1163: iload 5
    //   1165: iand
    //   1166: iload 4
    //   1168: iload 5
    //   1170: ior
    //   1171: iadd
    //   1172: istore 4
    //   1174: iload 4
    //   1176: sipush 128
    //   1179: irem
    //   1180: putstatic 49	o/Ir:ˊ	I
    //   1183: iload 4
    //   1185: iconst_2
    //   1186: irem
    //   1187: ifne +6 -> 1193
    //   1190: goto -1187 -> 3
    //   1193: goto -210 -> 983
    //   1196: goto -464 -> 732
    //   1199: getstatic 51	o/Ir:ॱ	I
    //   1202: istore 4
    //   1204: iload 4
    //   1206: bipush 117
    //   1208: iand
    //   1209: iload 4
    //   1211: bipush 117
    //   1213: ixor
    //   1214: iload 4
    //   1216: bipush 117
    //   1218: iand
    //   1219: ior
    //   1220: iadd
    //   1221: istore 4
    //   1223: iload 4
    //   1225: sipush 128
    //   1228: irem
    //   1229: putstatic 49	o/Ir:ˊ	I
    //   1232: iload 4
    //   1234: iconst_2
    //   1235: irem
    //   1236: ifne +6 -> 1242
    //   1239: goto +448 -> 1687
    //   1242: goto -262 -> 980
    //   1245: iload 4
    //   1247: tableswitch	default:+21->1268, 0:+177->1424, 1:+-952->295
    //   1268: goto +156 -> 1424
    //   1271: goto -832 -> 439
    //   1274: iconst_1
    //   1275: istore 4
    //   1277: goto -32 -> 1245
    //   1280: iconst_0
    //   1281: istore 4
    //   1283: goto -507 -> 776
    //   1286: getstatic 51	o/Ir:ॱ	I
    //   1289: istore 4
    //   1291: iload 4
    //   1293: bipush 84
    //   1295: iadd
    //   1296: iconst_1
    //   1297: isub
    //   1298: istore 4
    //   1300: iload 4
    //   1302: sipush 128
    //   1305: irem
    //   1306: putstatic 49	o/Ir:ˊ	I
    //   1309: iload 4
    //   1311: iconst_2
    //   1312: irem
    //   1313: ifne +6 -> 1319
    //   1316: goto -120 -> 1196
    //   1319: goto -587 -> 732
    //   1322: bipush 41
    //   1324: istore 4
    //   1326: goto +280 -> 1606
    //   1329: getstatic 51	o/Ir:ॱ	I
    //   1332: istore 4
    //   1334: iload 4
    //   1336: bipush 75
    //   1338: ixor
    //   1339: iload 4
    //   1341: bipush 75
    //   1343: iand
    //   1344: ior
    //   1345: iconst_1
    //   1346: ishl
    //   1347: iload 4
    //   1349: bipush 75
    //   1351: ixor
    //   1352: isub
    //   1353: istore 4
    //   1355: iload 4
    //   1357: sipush 128
    //   1360: irem
    //   1361: putstatic 49	o/Ir:ˊ	I
    //   1364: iload 4
    //   1366: iconst_2
    //   1367: irem
    //   1368: ifne +6 -> 1374
    //   1371: goto -876 -> 495
    //   1374: goto -1204 -> 170
    //   1377: return
    //   1378: invokestatic 820	java/util/UUID:randomUUID	()Ljava/util/UUID;
    //   1381: invokevirtual 823	java/util/UUID:toString	()Ljava/lang/String;
    //   1384: astore 6
    //   1386: getstatic 828	o/Gv:ˊ	Lo/Gv$If;
    //   1389: invokevirtual 833	o/Gv$If:ˎ	()Lo/Gv;
    //   1392: invokevirtual 836	o/Gv:ˏॱ	()Ljava/lang/String;
    //   1395: astore 7
    //   1397: invokestatic 842	java/util/Calendar:getInstance	()Ljava/util/Calendar;
    //   1400: astore 8
    //   1402: aload 8
    //   1404: sipush 15285
    //   1407: ldc_w 843
    //   1410: bipush 26
    //   1412: invokestatic 772	o/Ir:ˏ	(ICI)Ljava/lang/String;
    //   1415: invokevirtual 776	java/lang/String:intern	()Ljava/lang/String;
    //   1418: invokestatic 801	o/vq:ˋ	(Ljava/lang/Object;Ljava/lang/String;)V
    //   1421: goto -432 -> 989
    //   1424: sipush 441
    //   1427: ldc_w 794
    //   1430: bipush 56
    //   1432: invokestatic 772	o/Ir:ˏ	(ICI)Ljava/lang/String;
    //   1435: invokevirtual 776	java/lang/String:intern	()Ljava/lang/String;
    //   1438: astore 8
    //   1440: goto +17 -> 1457
    //   1443: astore_2
    //   1444: aload_2
    //   1445: invokevirtual 740	java/lang/Throwable:getCause	()Ljava/lang/Throwable;
    //   1448: astore_1
    //   1449: aload_1
    //   1450: ifnull +5 -> 1455
    //   1453: aload_1
    //   1454: athrow
    //   1455: aload_2
    //   1456: athrow
    //   1457: iconst_3
    //   1458: iconst_0
    //   1459: ldc_w 795
    //   1462: invokestatic 746	o/O:ˋ	(IIC)Ljava/lang/Object;
    //   1465: checkcast 748	java/lang/Class
    //   1468: ldc_w 796
    //   1471: aconst_null
    //   1472: invokevirtual 754	java/lang/Class:getMethod	(Ljava/lang/String;[Ljava/lang/Class;)Ljava/lang/reflect/Method;
    //   1475: aconst_null
    //   1476: aconst_null
    //   1477: invokevirtual 760	java/lang/reflect/Method:invoke	(Ljava/lang/Object;[Ljava/lang/Object;)Ljava/lang/Object;
    //   1480: astore 9
    //   1482: aload 9
    //   1484: sipush 19933
    //   1487: iconst_0
    //   1488: bipush 22
    //   1490: invokestatic 772	o/Ir:ˏ	(ICI)Ljava/lang/String;
    //   1493: invokevirtual 776	java/lang/String:intern	()Ljava/lang/String;
    //   1496: invokestatic 801	o/vq:ˋ	(Ljava/lang/Object;Ljava/lang/String;)V
    //   1499: goto +17 -> 1516
    //   1502: astore_1
    //   1503: aload_1
    //   1504: invokevirtual 740	java/lang/Throwable:getCause	()Ljava/lang/Throwable;
    //   1507: astore_2
    //   1508: aload_2
    //   1509: ifnull +5 -> 1514
    //   1512: aload_2
    //   1513: athrow
    //   1514: aload_1
    //   1515: athrow
    //   1516: iconst_3
    //   1517: iconst_0
    //   1518: ldc_w 795
    //   1521: invokestatic 746	o/O:ˋ	(IIC)Ljava/lang/Object;
    //   1524: checkcast 748	java/lang/Class
    //   1527: ldc_w 802
    //   1530: aconst_null
    //   1531: invokevirtual 754	java/lang/Class:getMethod	(Ljava/lang/String;[Ljava/lang/Class;)Ljava/lang/reflect/Method;
    //   1534: aload 9
    //   1536: aconst_null
    //   1537: invokevirtual 760	java/lang/reflect/Method:invoke	(Ljava/lang/Object;[Ljava/lang/Object;)Ljava/lang/Object;
    //   1540: checkcast 764	java/lang/String
    //   1543: astore 9
    //   1545: aload 7
    //   1547: aload 8
    //   1549: aload 9
    //   1551: invokevirtual 769	o/xG$if:ˎ	(Ljava/lang/String;Ljava/lang/String;)Lo/xG$if;
    //   1554: astore 7
    //   1556: sipush 25246
    //   1559: istore 4
    //   1561: goto -1312 -> 249
    //   1564: astore_1
    //   1565: aload_1
    //   1566: athrow
    //   1567: iload 4
    //   1569: lookupswitch	default:+27->1596, 19:+-1554->15, 35:+-1067->502
    //   1596: goto -1581 -> 15
    //   1599: bipush 35
    //   1601: istore 4
    //   1603: goto -36 -> 1567
    //   1606: iload 4
    //   1608: lookupswitch	default:+28->1636, 41:+-640->968, 67:+-709->899
    //   1636: goto -737 -> 899
    //   1639: aload 8
    //   1641: invokevirtual 848	java/util/Calendar:getTimeInMillis	()J
    //   1644: invokestatic 851	java/lang/String:valueOf	(J)Ljava/lang/String;
    //   1647: astore 9
    //   1649: aload_2
    //   1650: sipush 203
    //   1653: iconst_0
    //   1654: bipush 12
    //   1656: invokestatic 772	o/Ir:ˏ	(ICI)Ljava/lang/String;
    //   1659: invokevirtual 776	java/lang/String:intern	()Ljava/lang/String;
    //   1662: sipush 368
    //   1665: ldc_w 852
    //   1668: bipush 31
    //   1670: invokestatic 772	o/Ir:ˏ	(ICI)Ljava/lang/String;
    //   1673: invokevirtual 776	java/lang/String:intern	()Ljava/lang/String;
    //   1676: invokevirtual 769	o/xG$if:ˎ	(Ljava/lang/String;Ljava/lang/String;)Lo/xG$if;
    //   1679: astore 8
    //   1681: aload 9
    //   1683: astore_2
    //   1684: goto -398 -> 1286
    //   1687: goto -707 -> 980
    //   1690: aload 8
    //   1692: invokevirtual 848	java/util/Calendar:getTimeInMillis	()J
    //   1695: invokestatic 851	java/lang/String:valueOf	(J)Ljava/lang/String;
    //   1698: astore 9
    //   1700: aload_2
    //   1701: sipush 2901
    //   1704: iconst_0
    //   1705: bipush 40
    //   1707: invokestatic 772	o/Ir:ˏ	(ICI)Ljava/lang/String;
    //   1710: invokevirtual 776	java/lang/String:intern	()Ljava/lang/String;
    //   1713: sipush 2928
    //   1716: ldc_w 852
    //   1719: bipush 30
    //   1721: invokestatic 772	o/Ir:ˏ	(ICI)Ljava/lang/String;
    //   1724: invokevirtual 776	java/lang/String:intern	()Ljava/lang/String;
    //   1727: invokevirtual 769	o/xG$if:ˎ	(Ljava/lang/String;Ljava/lang/String;)Lo/xG$if;
    //   1730: astore 8
    //   1732: aload 9
    //   1734: astore_2
    //   1735: goto -449 -> 1286
    //   1738: bipush 67
    //   1740: istore 4
    //   1742: goto -136 -> 1606
    // Local variable table:
    //   start	length	slot	name	signature
    //   0	1745	0	this	Ir
    //   0	1745	1	paramXG	xG
    //   0	1745	2	paramIf	xG.if
    //   0	1745	3	paramBoolean	boolean
    //   4	1737	4	i	int
    //   252	919	5	j	int
    //   457	928	6	localObject1	Object
    //   107	1448	7	localObject2	Object
    //   109	1622	8	localObject3	Object
    //   53	1680	9	localObject4	Object
    // Exception table:
    //   from	to	target	type
    //   32	61	18	finally
    //   78	107	64	finally
    //   249	254	153	java/lang/NullPointerException
    //   273	282	153	java/lang/NullPointerException
    //   295	308	153	java/lang/IndexOutOfBoundsException
    //   1031	1036	153	java/lang/ClassCastException
    //   1057	1066	153	java/lang/ClassCastException
    //   1079	1084	153	java/lang/IllegalArgumentException
    //   1110	1119	153	java/lang/IndexOutOfBoundsException
    //   332	357	318	finally
    //   391	420	377	finally
    //   519	548	505	finally
    //   565	594	551	finally
    //   1457	1482	1443	finally
    //   1516	1545	1502	finally
    //   273	282	1564	java/lang/NumberFormatException
    //   308	315	1564	java/lang/IllegalArgumentException
    //   319	324	1564	java/lang/IllegalArgumentException
    //   328	330	1564	java/lang/IllegalArgumentException
    //   330	332	1564	java/lang/IllegalArgumentException
    //   357	374	1564	java/lang/IllegalArgumentException
    //   378	383	1564	java/lang/IllegalArgumentException
    //   387	389	1564	java/lang/IllegalArgumentException
    //   389	391	1564	java/lang/IllegalArgumentException
    //   420	431	1564	java/lang/IllegalArgumentException
    //   1286	1291	1564	java/lang/ClassCastException
    //   1300	1309	1564	java/lang/NumberFormatException
  }
  
  private final String ˋ(xH paramXH, boolean paramBoolean)
  {
    break label127;
    int j;
    int i = j;
    break label469;
    i = 1;
    break label995;
    i = 0;
    break label195;
    label19:
    yW localYW = new yW();
    if (paramXH != null)
    {
      break label147;
      i = 1;
      break label645;
      label43:
      i = 1;
      break label753;
      switch (i)
      {
      default: 
        label48:
        break;
        label75:
        i = 0;
        break;
      }
    }
    for (;;)
    {
      label80:
      paramXH = "";
      break label671;
      label87:
      label99:
      label124:
      label127:
      label147:
      label153:
      label159:
      label162:
      label165:
      label195:
      label223:
      label255:
      for (;;)
      {
        j = 1;
        break label419;
        break label124;
        break label124;
        i = 78;
        break label582;
        i = null.length;
        if (paramXH == null) {
          break label275;
        }
        break;
        for (;;)
        {
          i = j;
          break label469;
          break label306;
          break label530;
          paramXH = localYW.ᐝॱ();
          i = 734;
          j = 17;
          break label280;
          i = 91;
          break;
          i = 84;
          break label375;
          break label820;
          i = 85;
          switch (i)
          {
          }
        }
        switch (i)
        {
        default: 
          break label480;
          switch (i)
          {
          default: 
            break label708;
          }
          break;
        }
      }
      label275:
      label280:
      label306:
      label375:
      label407:
      label419:
      label469:
      label480:
      label530:
      label582:
      label614:
      label645:
      label671:
      label708:
      label753:
      label779:
      label820:
      label953:
      label983:
      label990:
      label995:
      label1023:
      do
      {
        for (;;)
        {
          int k;
          try
          {
            paramXH = localYW.ᐝॱ();
            i = 20347;
            j = 66;
            continue;
            i = 1;
            break label195;
            vq.ˋ(paramXH, ˏ(i, 42469, j).intern());
            paramXH = ˎ(paramXH, paramBoolean);
            continue;
            i = ॱ + 122 - 1;
            ˊ = i % 128;
            if (i % 2 == 0) {
              return paramXH;
            }
            return paramXH;
            break label80;
            i = j;
            continue;
            i = 6;
            switch (i)
            {
            default: 
              break label1023;
              switch (i)
              {
              case 48: 
              default: 
                break label983;
                i = 67;
                break label165;
                i = 75;
                break label953;
                k = ॱ;
                i = k & 0x69;
                k |= 0x69;
                i = ((i | k) << 1) - (i ^ k);
                ˊ = i % 128;
                if (i % 2 == 0) {
                  break label43;
                }
                break label75;
                if (i != 1)
                {
                  continue;
                  j = 0;
                }
                else
                {
                  try
                  {
                    i = ˊ;
                    i = (i & 0x6E) + (i | 0x6E) - 1;
                    ॱ = i % 128;
                    if (i % 2 != 0) {
                      break label153;
                    }
                    i = 48;
                  }
                  catch (IllegalArgumentException|ArrayStoreException|IndexOutOfBoundsException paramXH)
                  {
                    throw paramXH;
                  }
                  i = 0;
                  continue;
                  i = ˊ;
                  i = (i & 0x7D) - ((i & 0x7D | i ^ 0x7D) ^ 0xFFFFFFFF) - 1;
                  ॱ = i % 128;
                  if (i % 2 == 0)
                  {
                    break label99;
                    i = 62;
                    continue;
                    switch (i)
                    {
                    }
                  }
                }
                break;
              }
              break;
            case 6: 
              break label19;
              i = ˊ;
              i = i + 92 - 1;
              ॱ = i % 128;
              if (i % 2 == 0)
              {
                break label990;
                switch (i)
                {
                case 1: 
                default: 
                  continue;
                  i = ॱ;
                  i = (i & 0x33) + (i | 0x33);
                  ˊ = i % 128;
                  if (i % 2 == 0) {
                    break;
                  }
                  break;
                case 0: 
                  break label124;
                  i = ॱ;
                  i = (i & 0x9) - (--(i ^ 0x9 | i & 0x9) ^ 0xFFFFFFFF) - 1;
                  ˊ = i % 128;
                  if (i % 2 != 0)
                  {
                    continue;
                    switch (i)
                    {
                    case 0: 
                    default: 
                      break;
                      i = 0;
                      break label995;
                      i = 58;
                      break label223;
                      i = 76;
                      break;
                    case 1: 
                      i = 3 / 5;
                      i = j;
                      continue;
                      vq.ˎ();
                    }
                  }
                  break;
                }
              }
              break;
            }
          }
          catch (Exception|ClassCastException|IndexOutOfBoundsException|IllegalStateException|NumberFormatException paramXH)
          {
            throw paramXH;
          }
          for (;;)
          {
            throw new NullPointerException();
            yS localYS = (yS)localYW;
            paramXH.ॱ(localYS);
            break label614;
            i = ॱ;
            i = ((i | 0x1F) << 1) - (i ^ 0x1F);
            ˊ = i % 128;
            if (i % 2 == 0) {
              break label255;
            }
            break label87;
            if (paramXH == null) {
              break label779;
            }
            break;
            k = ॱ;
            i = k & 0x5D;
            k = k & 0x5D | k ^ 0x5D;
            i = (i & k) + (i | k);
            ˊ = i % 128;
            if (i % 2 == 0) {
              break label162;
            }
            break label407;
            vq.ˎ();
            break label159;
            i = 58;
            break label953;
            i = 0;
            break label48;
            switch (i)
            {
            }
          }
          i = 2 / 5;
          break label124;
          i = 1;
          break label48;
          switch (i)
          {
          }
        }
        i = ˊ;
        i = (i & 0x1E) + (i | 0x1E) - 1;
        ॱ = i % 128;
      } while (i % 2 != 0);
    }
  }
  
  private final void ˋ(xG paramXG, xG.if paramIf, boolean paramBoolean)
  {
    break label243;
    String str = paramXG.ˎ();
    Object localObject = paramXG.ॱ();
    for (;;)
    {
      try
      {
        label18:
        label21:
        paramXG = paramXG.ॱ();
        paramXG = ˋ(paramXG, paramBoolean);
      }
      catch (IllegalStateException|ClassCastException|ArrayStoreException|IllegalArgumentException|IndexOutOfBoundsException paramXG)
      {
        label46:
        label125:
        label139:
        throw paramXG;
      }
      try
      {
        paramXG = xH.ˋ((xC)localObject, paramXG);
      }
      catch (IllegalStateException|NullPointerException|IndexOutOfBoundsException paramXG)
      {
        throw paramXG;
      }
      break;
      int i = 7;
      break label447;
      int j = ॱ;
      i = j & 0x55;
      j = -(j ^ 0x55 | j & 0x55);
      i = (-j & i) + (i | -j);
      ˊ = i % 128;
      if (i % 2 != 0)
      {
        break;
        i = 0;
        break label217;
        break label288;
        break label18;
        if (localObject == null)
        {
          continue;
          i = ˊ;
          i = ((i ^ 0x35 | i & 0x35) << 1) - (i & 0xFFFFFFCA | (i ^ 0xFFFFFFFF) & 0x35);
          ॱ = i % 128;
          if (i % 2 != 0) {
            break label363;
          }
          break label210;
          label198:
          break label288;
          label204:
          i = 0;
          break label255;
          label210:
          i = 49;
          break label302;
          switch (i)
          {
          default: 
            label217:
            break label611;
            label243:
            continue;
            label246:
            i = 1;
            break;
          }
        }
        label255:
        label288:
        label302:
        label338:
        label363:
        label447:
        label535:
        label611:
        label621:
        do
        {
          break label21;
          switch (i)
          {
          }
          throw new NullPointerException();
          if (yf.ˏ(str)) {
            break label46;
          }
          break label338;
          switch (i)
          {
          }
          break label198;
          for (;;)
          {
            break label621;
            i = 80;
            break label447;
            localObject = null;
            do
            {
              break;
              i = 1;
              break label217;
              do
              {
                break label535;
                i = 14;
                break;
                i = ॱ;
                i = i + 35 - 1;
                i = (i & 0xFFFFFFFF) + (i | 0xFFFFFFFF);
                ˊ = i % 128;
              } while (i % 2 == 0);
              break label535;
              i = ˊ + 119;
              ॱ = i % 128;
            } while (i % 2 != 0);
            break;
            switch (i)
            {
            case 80: 
            default: 
              continue;
              for (;;)
              {
                i = ˊ;
                i = ((i & 0x25 ^ 0xFFFFFFFF) & (i | 0x25)) - (--((i & 0x25) << 1) ^ 0xFFFFFFFF) - 1;
                ॱ = i % 128;
                if (i % 2 != 0) {
                  break label125;
                }
                break;
                paramIf.ˋ(str, paramXG);
              }
              j = ॱ;
              i = (j ^ 0x75 | j & 0x75) << 1;
              j = -(j ^ 0x75);
              i = ((i | j) << 1) - (i ^ j);
              ˊ = i % 128;
              if (i % 2 == 0) {
                break label204;
              }
              break label246;
              localObject = ((xH)localObject).ˏ();
              break label139;
            }
          }
          j = ˊ;
          i = j ^ 0x43;
          j = -((j & 0x43) << 1);
          i = (-j ^ i) + ((i & -j) << 1);
          ॱ = i % 128;
          if (i % 2 != 0) {
            return;
          }
          return;
          i = ॱ + 88 - 1;
          ˊ = i % 128;
        } while (i % 2 == 0);
      }
    }
  }
  
  /* Error */
  private final void ˋ(xJ paramXJ, xJ.ˊ paramˊ, boolean paramBoolean)
  {
    // Byte code:
    //   0: goto +51 -> 51
    //   3: getstatic 51	o/Ir:ॱ	I
    //   6: bipush 97
    //   8: iadd
    //   9: iconst_1
    //   10: isub
    //   11: istore 4
    //   13: iload 4
    //   15: iconst_m1
    //   16: ior
    //   17: iconst_1
    //   18: ishl
    //   19: iload 4
    //   21: iconst_m1
    //   22: ixor
    //   23: isub
    //   24: istore 4
    //   26: iload 4
    //   28: sipush 128
    //   31: irem
    //   32: putstatic 49	o/Ir:ˊ	I
    //   35: iload 4
    //   37: iconst_2
    //   38: irem
    //   39: ifne +6 -> 45
    //   42: goto +1045 -> 1087
    //   45: goto +896 -> 941
    //   48: goto +807 -> 855
    //   51: goto +229 -> 280
    //   54: iload 4
    //   56: lookupswitch	default:+28->84, 40:+370->426, 59:+48->104
    //   84: goto +20 -> 104
    //   87: goto +961 -> 1048
    //   90: goto +685 -> 775
    //   93: iconst_5
    //   94: iconst_5
    //   95: idiv
    //   96: istore 4
    //   98: goto +757 -> 855
    //   101: astore_1
    //   102: aload_1
    //   103: athrow
    //   104: getstatic 49	o/Ir:ˊ	I
    //   107: istore 5
    //   109: iload 5
    //   111: bipush 83
    //   113: ior
    //   114: iconst_1
    //   115: ishl
    //   116: istore 4
    //   118: iload 5
    //   120: iconst_m1
    //   121: ixor
    //   122: bipush 83
    //   124: iand
    //   125: iload 5
    //   127: bipush -84
    //   129: iand
    //   130: ior
    //   131: istore 5
    //   133: iload 5
    //   135: ineg
    //   136: iload 4
    //   138: ixor
    //   139: iload 4
    //   141: iload 5
    //   143: ineg
    //   144: iand
    //   145: iconst_1
    //   146: ishl
    //   147: iadd
    //   148: istore 4
    //   150: iload 4
    //   152: sipush 128
    //   155: irem
    //   156: putstatic 51	o/Ir:ॱ	I
    //   159: iload 4
    //   161: iconst_2
    //   162: irem
    //   163: ifeq +6 -> 169
    //   166: goto +812 -> 978
    //   169: goto +856 -> 1025
    //   172: iconst_1
    //   173: istore 4
    //   175: goto +158 -> 333
    //   178: getstatic 51	o/Ir:ॱ	I
    //   181: bipush 47
    //   183: iadd
    //   184: iconst_1
    //   185: isub
    //   186: istore 4
    //   188: iload 4
    //   190: iconst_m1
    //   191: ixor
    //   192: iload 4
    //   194: iconst_m1
    //   195: iand
    //   196: iconst_1
    //   197: ishl
    //   198: iadd
    //   199: istore 4
    //   201: iload 4
    //   203: sipush 128
    //   206: irem
    //   207: putstatic 49	o/Ir:ˊ	I
    //   210: iload 4
    //   212: iconst_2
    //   213: irem
    //   214: ifne +6 -> 220
    //   217: goto -130 -> 87
    //   220: goto +828 -> 1048
    //   223: getstatic 51	o/Ir:ॱ	I
    //   226: istore 4
    //   228: iload 4
    //   230: bipush 49
    //   232: ixor
    //   233: iload 4
    //   235: bipush 49
    //   237: iand
    //   238: iconst_1
    //   239: ishl
    //   240: iadd
    //   241: istore 4
    //   243: iload 4
    //   245: sipush 128
    //   248: irem
    //   249: putstatic 49	o/Ir:ˊ	I
    //   252: iload 4
    //   254: iconst_2
    //   255: irem
    //   256: ifne +6 -> 262
    //   259: goto +487 -> 746
    //   262: return
    //   263: aload_1
    //   264: invokevirtual 903	o/xJ:ॱॱ	()Lo/xF;
    //   267: astore 9
    //   269: aload 9
    //   271: ifnull +6 -> 277
    //   274: goto +741 -> 1015
    //   277: goto +250 -> 527
    //   280: getstatic 49	o/Ir:ˊ	I
    //   283: istore 4
    //   285: iload 4
    //   287: bipush 114
    //   289: ior
    //   290: iload 4
    //   292: bipush 114
    //   294: iand
    //   295: iadd
    //   296: istore 4
    //   298: iload 4
    //   300: iconst_m1
    //   301: ixor
    //   302: iload 4
    //   304: iconst_m1
    //   305: iand
    //   306: iconst_1
    //   307: ishl
    //   308: iadd
    //   309: istore 4
    //   311: iload 4
    //   313: sipush 128
    //   316: irem
    //   317: putstatic 51	o/Ir:ॱ	I
    //   320: iload 4
    //   322: iconst_2
    //   323: irem
    //   324: ifeq +6 -> 330
    //   327: goto +539 -> 866
    //   330: goto -67 -> 263
    //   333: iload 4
    //   335: tableswitch	default:+21->356, 0:+138->473, 1:+91->426
    //   356: goto +117 -> 473
    //   359: iconst_0
    //   360: istore 4
    //   362: goto +625 -> 987
    //   365: getstatic 49	o/Ir:ˊ	I
    //   368: istore 5
    //   370: iload 5
    //   372: bipush 61
    //   374: ixor
    //   375: istore 4
    //   377: iload 5
    //   379: bipush 61
    //   381: iand
    //   382: iconst_1
    //   383: ishl
    //   384: ineg
    //   385: istore 5
    //   387: iload 5
    //   389: ineg
    //   390: iload 4
    //   392: ior
    //   393: iconst_1
    //   394: ishl
    //   395: iload 4
    //   397: iload 5
    //   399: ineg
    //   400: ixor
    //   401: isub
    //   402: istore 4
    //   404: iload 4
    //   406: sipush 128
    //   409: irem
    //   410: putstatic 51	o/Ir:ॱ	I
    //   413: iload 4
    //   415: iconst_2
    //   416: irem
    //   417: ifeq +6 -> 423
    //   420: goto +269 -> 689
    //   423: goto +608 -> 1031
    //   426: aload 8
    //   428: invokevirtual 908	java/lang/Long:longValue	()J
    //   431: lstore 6
    //   433: aload_0
    //   434: aload 9
    //   436: iload_3
    //   437: invokespecial 911	o/Ir:ॱ	(Lo/xF;Z)Ljava/io/InputStream;
    //   440: invokestatic 916	o/yX:ˋ	(Ljava/io/InputStream;)Lo/zh;
    //   443: invokestatic 919	o/yX:ˏ	(Lo/zh;)Lo/yT;
    //   446: astore 8
    //   448: goto +421 -> 869
    //   451: iconst_1
    //   452: istore 4
    //   454: goto +493 -> 947
    //   457: aload_2
    //   458: aload_1
    //   459: lload 6
    //   461: aload 8
    //   463: invokestatic 924	o/xF:ˊ	(Lo/xC;JLo/yT;)Lo/xF;
    //   466: invokevirtual 929	o/xJ$ˊ:ˋ	(Lo/xF;)Lo/xJ$ˊ;
    //   469: pop
    //   470: goto -247 -> 223
    //   473: goto -47 -> 426
    //   476: aconst_null
    //   477: astore_1
    //   478: goto +220 -> 698
    //   481: bipush 40
    //   483: istore 4
    //   485: goto -431 -> 54
    //   488: bipush 59
    //   490: istore 4
    //   492: goto -438 -> 54
    //   495: iload 4
    //   497: lookupswitch	default:+27->524, 10:+-319->178, 41:+-21->476
    //   524: goto -48 -> 476
    //   527: bipush 41
    //   529: istore 4
    //   531: goto -36 -> 495
    //   534: goto +241 -> 775
    //   537: aload_2
    //   538: aload_1
    //   539: lload 6
    //   541: aload 8
    //   543: invokestatic 924	o/xF:ˊ	(Lo/xC;JLo/yT;)Lo/xF;
    //   546: invokevirtual 929	o/xJ$ˊ:ˋ	(Lo/xF;)Lo/xJ$ˊ;
    //   549: pop
    //   550: new 726	java/lang/NullPointerException
    //   553: dup
    //   554: invokespecial 782	java/lang/NullPointerException:<init>	()V
    //   557: athrow
    //   558: iconst_1
    //   559: istore 4
    //   561: goto +426 -> 987
    //   564: getstatic 51	o/Ir:ॱ	I
    //   567: istore 4
    //   569: iload 4
    //   571: bipush 47
    //   573: ior
    //   574: iconst_1
    //   575: ishl
    //   576: iload 4
    //   578: bipush 47
    //   580: ixor
    //   581: isub
    //   582: istore 4
    //   584: iload 4
    //   586: sipush 128
    //   589: irem
    //   590: putstatic 49	o/Ir:ˊ	I
    //   593: iload 4
    //   595: iconst_2
    //   596: irem
    //   597: ifne +6 -> 603
    //   600: goto +186 -> 786
    //   603: goto +325 -> 928
    //   606: aconst_null
    //   607: astore 8
    //   609: goto -45 -> 564
    //   612: iload 4
    //   614: tableswitch	default:+22->636, 0:+129->743, 1:+-566->48
    //   636: goto -588 -> 48
    //   639: getstatic 49	o/Ir:ˊ	I
    //   642: istore 4
    //   644: iload 4
    //   646: bipush 125
    //   648: ior
    //   649: iconst_1
    //   650: ishl
    //   651: iload 4
    //   653: bipush 125
    //   655: iand
    //   656: iconst_m1
    //   657: ixor
    //   658: iload 4
    //   660: bipush 125
    //   662: ior
    //   663: iand
    //   664: isub
    //   665: istore 4
    //   667: iload 4
    //   669: sipush 128
    //   672: irem
    //   673: putstatic 51	o/Ir:ॱ	I
    //   676: iload 4
    //   678: iconst_2
    //   679: irem
    //   680: ifeq +6 -> 686
    //   683: goto -125 -> 558
    //   686: goto -327 -> 359
    //   689: goto +342 -> 1031
    //   692: iconst_0
    //   693: istore 4
    //   695: goto +252 -> 947
    //   698: getstatic 51	o/Ir:ॱ	I
    //   701: istore 4
    //   703: iload 4
    //   705: bipush 91
    //   707: ixor
    //   708: iload 4
    //   710: bipush 91
    //   712: iand
    //   713: iconst_1
    //   714: ishl
    //   715: iadd
    //   716: istore 4
    //   718: iload 4
    //   720: sipush 128
    //   723: irem
    //   724: putstatic 49	o/Ir:ˊ	I
    //   727: iload 4
    //   729: iconst_2
    //   730: irem
    //   731: ifne +6 -> 737
    //   734: goto +241 -> 975
    //   737: goto -203 -> 534
    //   740: goto +115 -> 855
    //   743: goto +112 -> 855
    //   746: return
    //   747: iload 4
    //   749: tableswitch	default:+23->772, 0:+-384->365, 1:+-143->606
    //   772: goto -166 -> 606
    //   775: aload 9
    //   777: ifnull +6 -> 783
    //   780: goto +142 -> 922
    //   783: goto +198 -> 981
    //   786: bipush 7
    //   788: istore 4
    //   790: goto +267 -> 1057
    //   793: getstatic 49	o/Ir:ˊ	I
    //   796: istore 5
    //   798: iload 5
    //   800: bipush 109
    //   802: ior
    //   803: iconst_1
    //   804: ishl
    //   805: istore 4
    //   807: iload 5
    //   809: bipush 109
    //   811: ixor
    //   812: ineg
    //   813: istore 5
    //   815: iload 4
    //   817: iload 5
    //   819: ixor
    //   820: iload 4
    //   822: iload 5
    //   824: iand
    //   825: iconst_1
    //   826: ishl
    //   827: iadd
    //   828: istore 4
    //   830: iload 4
    //   832: sipush 128
    //   835: irem
    //   836: putstatic 51	o/Ir:ॱ	I
    //   839: iload 4
    //   841: iconst_2
    //   842: irem
    //   843: ifeq +6 -> 849
    //   846: goto +89 -> 935
    //   849: goto -677 -> 172
    //   852: goto -77 -> 775
    //   855: aload 8
    //   857: ifnonnull +6 -> 863
    //   860: goto -372 -> 488
    //   863: goto -382 -> 481
    //   866: goto -603 -> 263
    //   869: getstatic 49	o/Ir:ˊ	I
    //   872: istore 4
    //   874: iload 4
    //   876: bipush 54
    //   878: ior
    //   879: iload 4
    //   881: bipush 54
    //   883: iand
    //   884: iadd
    //   885: istore 4
    //   887: iload 4
    //   889: iconst_m1
    //   890: ixor
    //   891: iload 4
    //   893: iconst_m1
    //   894: iand
    //   895: iconst_1
    //   896: ishl
    //   897: iadd
    //   898: istore 4
    //   900: iload 4
    //   902: sipush 128
    //   905: irem
    //   906: putstatic 51	o/Ir:ॱ	I
    //   909: iload 4
    //   911: iconst_2
    //   912: irem
    //   913: ifeq +6 -> 919
    //   916: goto -224 -> 692
    //   919: goto -468 -> 451
    //   922: iconst_0
    //   923: istore 4
    //   925: goto -178 -> 747
    //   928: bipush 43
    //   930: istore 4
    //   932: goto +125 -> 1057
    //   935: iconst_0
    //   936: istore 4
    //   938: goto -605 -> 333
    //   941: iconst_0
    //   942: istore 4
    //   944: goto -332 -> 612
    //   947: iload 4
    //   949: tableswitch	default:+23->972, 0:+-412->537, 1:+-492->457
    //   972: goto -435 -> 537
    //   975: goto -441 -> 534
    //   978: goto +47 -> 1025
    //   981: iconst_1
    //   982: istore 4
    //   984: goto -237 -> 747
    //   987: iload 4
    //   989: tableswitch	default:+23->1012, 0:+-899->90, 1:+-137->852
    //   1012: goto -922 -> 90
    //   1015: bipush 10
    //   1017: istore 4
    //   1019: goto -524 -> 495
    //   1022: astore_1
    //   1023: aload_1
    //   1024: athrow
    //   1025: invokestatic 804	o/vq:ˎ	()V
    //   1028: goto -235 -> 793
    //   1031: aload 9
    //   1033: invokevirtual 931	o/xF:ˎ	()J
    //   1036: lstore 6
    //   1038: lload 6
    //   1040: invokestatic 934	java/lang/Long:valueOf	(J)Ljava/lang/Long;
    //   1043: astore 8
    //   1045: goto -1042 -> 3
    //   1048: aload 9
    //   1050: invokevirtual 935	o/xF:ˏ	()Lo/xC;
    //   1053: astore_1
    //   1054: goto -415 -> 639
    //   1057: iload 4
    //   1059: lookupswitch	default:+25->1084, 7:+-966->93, 43:+-319->740
    //   1084: goto -344 -> 740
    //   1087: iconst_1
    //   1088: istore 4
    //   1090: goto -478 -> 612
    // Local variable table:
    //   start	length	slot	name	signature
    //   0	1093	0	this	Ir
    //   0	1093	1	paramXJ	xJ
    //   0	1093	2	paramˊ	xJ.ˊ
    //   0	1093	3	paramBoolean	boolean
    //   11	1078	4	i	int
    //   107	718	5	j	int
    //   431	608	6	l	long
    //   426	618	8	localObject	Object
    //   267	782	9	localXF	xF
    // Exception table:
    //   from	to	target	type
    //   365	370	101	java/lang/ClassCastException
    //   404	413	101	java/lang/ClassCastException
    //   404	413	101	java/lang/IllegalStateException
    //   639	644	101	java/lang/ArrayStoreException
    //   667	676	101	java/lang/ArrayStoreException
    //   667	676	101	java/lang/IllegalStateException
    //   1048	1054	101	java/lang/ClassCastException
    //   223	228	1022	java/lang/IllegalArgumentException
    //   243	252	1022	java/lang/UnsupportedOperationException
    //   869	874	1022	java/lang/Exception
    //   1031	1038	1022	java/lang/ArrayStoreException
  }
  
  /* Error */
  private final String ˎ(String paramString, boolean paramBoolean)
  {
    // Byte code:
    //   0: goto +1126 -> 1126
    //   3: iconst_0
    //   4: istore_3
    //   5: goto +282 -> 287
    //   8: getstatic 51	o/Ir:ॱ	I
    //   11: istore 4
    //   13: iload 4
    //   15: bipush 7
    //   17: ior
    //   18: iconst_1
    //   19: ishl
    //   20: istore_3
    //   21: iload 4
    //   23: bipush 7
    //   25: iand
    //   26: iconst_m1
    //   27: ixor
    //   28: iload 4
    //   30: bipush 7
    //   32: ior
    //   33: iand
    //   34: ineg
    //   35: istore 4
    //   37: iload_3
    //   38: iload 4
    //   40: ixor
    //   41: iload_3
    //   42: iload 4
    //   44: iand
    //   45: iconst_1
    //   46: ishl
    //   47: iadd
    //   48: istore_3
    //   49: iload_3
    //   50: sipush 128
    //   53: irem
    //   54: putstatic 49	o/Ir:ˊ	I
    //   57: iload_3
    //   58: iconst_2
    //   59: irem
    //   60: ifne +6 -> 66
    //   63: goto +413 -> 476
    //   66: goto +1713 -> 1779
    //   69: iconst_5
    //   70: iconst_4
    //   71: idiv
    //   72: istore_3
    //   73: goto +765 -> 838
    //   76: iload_3
    //   77: lookupswitch	default:+27->104, 31:+297->374, 62:+1811->1888
    //   104: goto +1784 -> 1888
    //   107: goto +20 -> 127
    //   110: astore 5
    //   112: aload 5
    //   114: invokevirtual 740	java/lang/Throwable:getCause	()Ljava/lang/Throwable;
    //   117: astore_1
    //   118: aload_1
    //   119: ifnull +5 -> 124
    //   122: aload_1
    //   123: athrow
    //   124: aload 5
    //   126: athrow
    //   127: iconst_4
    //   128: bipush 42
    //   130: ldc_w 936
    //   133: invokestatic 746	o/O:ˋ	(IIC)Ljava/lang/Object;
    //   136: checkcast 748	java/lang/Class
    //   139: ldc_w 783
    //   142: iconst_2
    //   143: anewarray 748	java/lang/Class
    //   146: dup
    //   147: iconst_0
    //   148: ldc_w 764
    //   151: aastore
    //   152: dup
    //   153: iconst_1
    //   154: ldc_w 764
    //   157: aastore
    //   158: invokevirtual 754	java/lang/Class:getMethod	(Ljava/lang/String;[Ljava/lang/Class;)Ljava/lang/reflect/Method;
    //   161: aconst_null
    //   162: iconst_2
    //   163: anewarray 4	java/lang/Object
    //   166: dup
    //   167: iconst_0
    //   168: aload 7
    //   170: aastore
    //   171: dup
    //   172: iconst_1
    //   173: aload 6
    //   175: aastore
    //   176: invokevirtual 760	java/lang/reflect/Method:invoke	(Ljava/lang/Object;[Ljava/lang/Object;)Ljava/lang/Object;
    //   179: pop
    //   180: getstatic 941	o/Iq:Companion	Lo/Iq$ˊ;
    //   183: aload_1
    //   184: aload 5
    //   186: invokevirtual 946	o/Iq$ˊ:ˎ	(Ljava/lang/String;Ljava/lang/String;)Ljava/lang/String;
    //   189: astore 5
    //   191: goto +9 -> 200
    //   194: bipush 54
    //   196: istore_3
    //   197: goto +486 -> 683
    //   200: sipush 253
    //   203: ldc_w 947
    //   206: bipush 7
    //   208: invokestatic 772	o/Ir:ˏ	(ICI)Ljava/lang/String;
    //   211: invokevirtual 776	java/lang/String:intern	()Ljava/lang/String;
    //   214: astore_1
    //   215: new 949	java/lang/StringBuilder
    //   218: dup
    //   219: invokespecial 950	java/lang/StringBuilder:<init>	()V
    //   222: astore 6
    //   224: getstatic 49	o/Ir:ˊ	I
    //   227: istore 4
    //   229: iload 4
    //   231: bipush 71
    //   233: iand
    //   234: iconst_m1
    //   235: ixor
    //   236: iload 4
    //   238: bipush 71
    //   240: ior
    //   241: iand
    //   242: istore_3
    //   243: iload 4
    //   245: bipush 71
    //   247: iand
    //   248: iconst_1
    //   249: ishl
    //   250: ineg
    //   251: istore 4
    //   253: iload 4
    //   255: ineg
    //   256: iload_3
    //   257: ixor
    //   258: iload_3
    //   259: iload 4
    //   261: ineg
    //   262: iand
    //   263: iconst_1
    //   264: ishl
    //   265: iadd
    //   266: istore_3
    //   267: iload_3
    //   268: sipush 128
    //   271: irem
    //   272: putstatic 51	o/Ir:ॱ	I
    //   275: iload_3
    //   276: iconst_2
    //   277: irem
    //   278: ifeq +6 -> 284
    //   281: goto +1594 -> 1875
    //   284: goto +976 -> 1260
    //   287: iload_3
    //   288: tableswitch	default:+24->312, 0:+1558->1846, 1:+1329->1617
    //   312: goto +1305 -> 1617
    //   315: bipush 70
    //   317: istore_3
    //   318: goto +1398 -> 1716
    //   321: getstatic 49	o/Ir:ˊ	I
    //   324: istore 4
    //   326: iload 4
    //   328: bipush 55
    //   330: iand
    //   331: istore_3
    //   332: iload 4
    //   334: bipush 55
    //   336: ior
    //   337: ineg
    //   338: istore 4
    //   340: iload 4
    //   342: ineg
    //   343: iload_3
    //   344: ixor
    //   345: iload_3
    //   346: iload 4
    //   348: ineg
    //   349: iand
    //   350: iconst_1
    //   351: ishl
    //   352: iadd
    //   353: istore_3
    //   354: iload_3
    //   355: sipush 128
    //   358: irem
    //   359: putstatic 51	o/Ir:ॱ	I
    //   362: iload_3
    //   363: iconst_2
    //   364: irem
    //   365: ifeq +6 -> 371
    //   368: goto +1417 -> 1785
    //   371: goto +464 -> 835
    //   374: aload 6
    //   376: aload 7
    //   378: invokevirtual 954	java/lang/StringBuilder:append	(Ljava/lang/String;)Ljava/lang/StringBuilder;
    //   381: aload 5
    //   383: invokevirtual 954	java/lang/StringBuilder:append	(Ljava/lang/String;)Ljava/lang/StringBuilder;
    //   386: invokevirtual 955	java/lang/StringBuilder:toString	()Ljava/lang/String;
    //   389: astore 5
    //   391: goto +20 -> 411
    //   394: astore 5
    //   396: aload 5
    //   398: invokevirtual 740	java/lang/Throwable:getCause	()Ljava/lang/Throwable;
    //   401: astore_1
    //   402: aload_1
    //   403: ifnull +5 -> 408
    //   406: aload_1
    //   407: athrow
    //   408: aload 5
    //   410: athrow
    //   411: iconst_4
    //   412: bipush 42
    //   414: ldc_w 936
    //   417: invokestatic 746	o/O:ˋ	(IIC)Ljava/lang/Object;
    //   420: checkcast 748	java/lang/Class
    //   423: ldc_w 802
    //   426: iconst_2
    //   427: anewarray 748	java/lang/Class
    //   430: dup
    //   431: iconst_0
    //   432: ldc_w 764
    //   435: aastore
    //   436: dup
    //   437: iconst_1
    //   438: ldc_w 764
    //   441: aastore
    //   442: invokevirtual 754	java/lang/Class:getMethod	(Ljava/lang/String;[Ljava/lang/Class;)Ljava/lang/reflect/Method;
    //   445: aconst_null
    //   446: iconst_2
    //   447: anewarray 4	java/lang/Object
    //   450: dup
    //   451: iconst_0
    //   452: aload_1
    //   453: aastore
    //   454: dup
    //   455: iconst_1
    //   456: aload 5
    //   458: aastore
    //   459: invokevirtual 760	java/lang/reflect/Method:invoke	(Ljava/lang/Object;[Ljava/lang/Object;)Ljava/lang/Object;
    //   462: pop
    //   463: new 726	java/lang/NullPointerException
    //   466: dup
    //   467: invokespecial 782	java/lang/NullPointerException:<init>	()V
    //   470: athrow
    //   471: iconst_0
    //   472: istore_3
    //   473: goto +312 -> 785
    //   476: bipush 73
    //   478: istore_3
    //   479: goto +1268 -> 1747
    //   482: bipush 94
    //   484: istore_3
    //   485: goto +198 -> 683
    //   488: iconst_0
    //   489: istore_3
    //   490: goto +447 -> 937
    //   493: iconst_4
    //   494: sipush 362
    //   497: ldc_w 956
    //   500: invokestatic 746	o/O:ˋ	(IIC)Ljava/lang/Object;
    //   503: checkcast 748	java/lang/Class
    //   506: ldc_w 796
    //   509: invokevirtual 787	java/lang/Class:getField	(Ljava/lang/String;)Ljava/lang/reflect/Field;
    //   512: aconst_null
    //   513: invokevirtual 793	java/lang/reflect/Field:get	(Ljava/lang/Object;)Ljava/lang/Object;
    //   516: astore 5
    //   518: goto +20 -> 538
    //   521: astore_1
    //   522: aload_1
    //   523: invokevirtual 740	java/lang/Throwable:getCause	()Ljava/lang/Throwable;
    //   526: astore 5
    //   528: aload 5
    //   530: ifnull +6 -> 536
    //   533: aload 5
    //   535: athrow
    //   536: aload_1
    //   537: athrow
    //   538: bipush 7
    //   540: sipush 366
    //   543: iconst_0
    //   544: invokestatic 746	o/O:ˋ	(IIC)Ljava/lang/Object;
    //   547: checkcast 748	java/lang/Class
    //   550: ldc_w 802
    //   553: aconst_null
    //   554: invokevirtual 754	java/lang/Class:getMethod	(Ljava/lang/String;[Ljava/lang/Class;)Ljava/lang/reflect/Method;
    //   557: aload 5
    //   559: aconst_null
    //   560: invokevirtual 760	java/lang/reflect/Method:invoke	(Ljava/lang/Object;[Ljava/lang/Object;)Ljava/lang/Object;
    //   563: astore 5
    //   565: goto +20 -> 585
    //   568: astore 5
    //   570: aload 5
    //   572: invokevirtual 740	java/lang/Throwable:getCause	()Ljava/lang/Throwable;
    //   575: astore_1
    //   576: aload_1
    //   577: ifnull +5 -> 582
    //   580: aload_1
    //   581: athrow
    //   582: aload 5
    //   584: athrow
    //   585: iconst_4
    //   586: sipush 362
    //   589: ldc_w 956
    //   592: invokestatic 746	o/O:ˋ	(IIC)Ljava/lang/Object;
    //   595: checkcast 748	java/lang/Class
    //   598: ldc_w 750
    //   601: aconst_null
    //   602: invokevirtual 754	java/lang/Class:getMethod	(Ljava/lang/String;[Ljava/lang/Class;)Ljava/lang/reflect/Method;
    //   605: aload 5
    //   607: aconst_null
    //   608: invokevirtual 760	java/lang/reflect/Method:invoke	(Ljava/lang/Object;[Ljava/lang/Object;)Ljava/lang/Object;
    //   611: checkcast 764	java/lang/String
    //   614: astore 5
    //   616: goto +1049 -> 1665
    //   619: sipush 253
    //   622: ldc_w 947
    //   625: bipush 7
    //   627: invokestatic 772	o/Ir:ˏ	(ICI)Ljava/lang/String;
    //   630: invokevirtual 776	java/lang/String:intern	()Ljava/lang/String;
    //   633: astore 6
    //   635: new 949	java/lang/StringBuilder
    //   638: dup
    //   639: invokespecial 950	java/lang/StringBuilder:<init>	()V
    //   642: astore 5
    //   644: goto +419 -> 1063
    //   647: aload 6
    //   649: sipush 777
    //   652: iconst_0
    //   653: bipush 10
    //   655: invokestatic 772	o/Ir:ˏ	(ICI)Ljava/lang/String;
    //   658: invokevirtual 776	java/lang/String:intern	()Ljava/lang/String;
    //   661: invokevirtual 954	java/lang/StringBuilder:append	(Ljava/lang/String;)Ljava/lang/StringBuilder;
    //   664: aload 5
    //   666: invokevirtual 954	java/lang/StringBuilder:append	(Ljava/lang/String;)Ljava/lang/StringBuilder;
    //   669: invokevirtual 955	java/lang/StringBuilder:toString	()Ljava/lang/String;
    //   672: astore 6
    //   674: goto -567 -> 107
    //   677: aconst_null
    //   678: arraylength
    //   679: istore_3
    //   680: aload 5
    //   682: areturn
    //   683: iload_3
    //   684: lookupswitch	default:+28->712, 54:+-191->493, 94:+595->1279
    //   712: goto +567 -> 1279
    //   715: getstatic 51	o/Ir:ॱ	I
    //   718: istore 4
    //   720: iload 4
    //   722: bipush 65
    //   724: ixor
    //   725: iload 4
    //   727: bipush 65
    //   729: iand
    //   730: ior
    //   731: iconst_1
    //   732: ishl
    //   733: istore_3
    //   734: iload 4
    //   736: bipush 65
    //   738: ixor
    //   739: ineg
    //   740: istore 4
    //   742: iload_3
    //   743: iload 4
    //   745: ior
    //   746: iconst_1
    //   747: ishl
    //   748: iload_3
    //   749: iload 4
    //   751: ixor
    //   752: isub
    //   753: istore_3
    //   754: iload_3
    //   755: sipush 128
    //   758: irem
    //   759: putstatic 49	o/Ir:ˊ	I
    //   762: iload_3
    //   763: iconst_2
    //   764: irem
    //   765: ifne +6 -> 771
    //   768: goto +163 -> 931
    //   771: bipush 75
    //   773: istore_3
    //   774: goto +853 -> 1627
    //   777: new 726	java/lang/NullPointerException
    //   780: dup
    //   781: invokespecial 782	java/lang/NullPointerException:<init>	()V
    //   784: athrow
    //   785: iload_3
    //   786: tableswitch	default:+22->808, 0:+97->883, 1:+628->1414
    //   808: goto +606 -> 1414
    //   811: iconst_0
    //   812: istore_3
    //   813: goto +92 -> 905
    //   816: bipush 62
    //   818: istore_3
    //   819: goto -743 -> 76
    //   822: iconst_1
    //   823: istore_3
    //   824: goto +81 -> 905
    //   827: astore_1
    //   828: aload_1
    //   829: athrow
    //   830: iconst_1
    //   831: istore_3
    //   832: goto +105 -> 937
    //   835: goto +612 -> 1447
    //   838: sipush 253
    //   841: ldc_w 947
    //   844: bipush 7
    //   846: invokestatic 772	o/Ir:ˏ	(ICI)Ljava/lang/String;
    //   849: invokevirtual 776	java/lang/String:intern	()Ljava/lang/String;
    //   852: astore 7
    //   854: goto +670 -> 1524
    //   857: iload_3
    //   858: tableswitch	default:+22->880, 0:+578->1436, 1:+-81->777
    //   880: goto -103 -> 777
    //   883: aload 5
    //   885: sipush 751
    //   888: iconst_0
    //   889: bipush 26
    //   891: invokestatic 772	o/Ir:ˏ	(ICI)Ljava/lang/String;
    //   894: invokevirtual 776	java/lang/String:intern	()Ljava/lang/String;
    //   897: invokevirtual 954	java/lang/StringBuilder:append	(Ljava/lang/String;)Ljava/lang/StringBuilder;
    //   900: astore 5
    //   902: goto +61 -> 963
    //   905: iload_3
    //   906: tableswitch	default:+22->928, 0:+538->1444, 1:+-68->838
    //   928: goto -90 -> 838
    //   931: bipush 81
    //   933: istore_3
    //   934: goto +693 -> 1627
    //   937: iload_3
    //   938: tableswitch	default:+22->960, 0:+598->1536, 1:+-261->677
    //   960: goto -283 -> 677
    //   963: aload 5
    //   965: aload_1
    //   966: invokevirtual 954	java/lang/StringBuilder:append	(Ljava/lang/String;)Ljava/lang/StringBuilder;
    //   969: invokevirtual 955	java/lang/StringBuilder:toString	()Ljava/lang/String;
    //   972: astore 5
    //   974: goto +20 -> 994
    //   977: astore_1
    //   978: aload_1
    //   979: invokevirtual 740	java/lang/Throwable:getCause	()Ljava/lang/Throwable;
    //   982: astore 5
    //   984: aload 5
    //   986: ifnull +6 -> 992
    //   989: aload 5
    //   991: athrow
    //   992: aload_1
    //   993: athrow
    //   994: iconst_4
    //   995: bipush 42
    //   997: ldc_w 936
    //   1000: invokestatic 746	o/O:ˋ	(IIC)Ljava/lang/Object;
    //   1003: checkcast 748	java/lang/Class
    //   1006: ldc_w 802
    //   1009: iconst_2
    //   1010: anewarray 748	java/lang/Class
    //   1013: dup
    //   1014: iconst_0
    //   1015: ldc_w 764
    //   1018: aastore
    //   1019: dup
    //   1020: iconst_1
    //   1021: ldc_w 764
    //   1024: aastore
    //   1025: invokevirtual 754	java/lang/Class:getMethod	(Ljava/lang/String;[Ljava/lang/Class;)Ljava/lang/reflect/Method;
    //   1028: aconst_null
    //   1029: iconst_2
    //   1030: anewarray 4	java/lang/Object
    //   1033: dup
    //   1034: iconst_0
    //   1035: aload 6
    //   1037: aastore
    //   1038: dup
    //   1039: iconst_1
    //   1040: aload 5
    //   1042: aastore
    //   1043: invokevirtual 760	java/lang/reflect/Method:invoke	(Ljava/lang/Object;[Ljava/lang/Object;)Ljava/lang/Object;
    //   1046: pop
    //   1047: aload_1
    //   1048: ldc_w 860
    //   1051: invokestatic 959	o/vq:ˊ	(Ljava/lang/Object;Ljava/lang/Object;)Z
    //   1054: ifeq +6 -> 1060
    //   1057: goto -1054 -> 3
    //   1060: goto +818 -> 1878
    //   1063: getstatic 49	o/Ir:ˊ	I
    //   1066: istore 4
    //   1068: iload 4
    //   1070: bipush -68
    //   1072: iand
    //   1073: iload 4
    //   1075: iconst_m1
    //   1076: ixor
    //   1077: bipush 67
    //   1079: iand
    //   1080: ior
    //   1081: istore_3
    //   1082: iload 4
    //   1084: bipush 67
    //   1086: iand
    //   1087: iconst_1
    //   1088: ishl
    //   1089: ineg
    //   1090: istore 4
    //   1092: iload 4
    //   1094: ineg
    //   1095: iload_3
    //   1096: ixor
    //   1097: iload_3
    //   1098: iload 4
    //   1100: ineg
    //   1101: iand
    //   1102: iconst_1
    //   1103: ishl
    //   1104: iadd
    //   1105: istore_3
    //   1106: iload_3
    //   1107: sipush 128
    //   1110: irem
    //   1111: putstatic 51	o/Ir:ॱ	I
    //   1114: iload_3
    //   1115: iconst_2
    //   1116: irem
    //   1117: ifeq +6 -> 1123
    //   1120: goto +135 -> 1255
    //   1123: goto -652 -> 471
    //   1126: goto -507 -> 619
    //   1129: iconst_4
    //   1130: sipush 362
    //   1133: ldc_w 956
    //   1136: invokestatic 746	o/O:ˋ	(IIC)Ljava/lang/Object;
    //   1139: checkcast 748	java/lang/Class
    //   1142: ldc_w 796
    //   1145: invokevirtual 787	java/lang/Class:getField	(Ljava/lang/String;)Ljava/lang/reflect/Field;
    //   1148: aconst_null
    //   1149: invokevirtual 793	java/lang/reflect/Field:get	(Ljava/lang/Object;)Ljava/lang/Object;
    //   1152: astore 5
    //   1154: goto +20 -> 1174
    //   1157: astore_1
    //   1158: aload_1
    //   1159: invokevirtual 740	java/lang/Throwable:getCause	()Ljava/lang/Throwable;
    //   1162: astore 5
    //   1164: aload 5
    //   1166: ifnull +6 -> 1172
    //   1169: aload 5
    //   1171: athrow
    //   1172: aload_1
    //   1173: athrow
    //   1174: bipush 7
    //   1176: sipush 366
    //   1179: iconst_0
    //   1180: invokestatic 746	o/O:ˋ	(IIC)Ljava/lang/Object;
    //   1183: checkcast 748	java/lang/Class
    //   1186: ldc_w 802
    //   1189: aconst_null
    //   1190: invokevirtual 754	java/lang/Class:getMethod	(Ljava/lang/String;[Ljava/lang/Class;)Ljava/lang/reflect/Method;
    //   1193: aload 5
    //   1195: aconst_null
    //   1196: invokevirtual 760	java/lang/reflect/Method:invoke	(Ljava/lang/Object;[Ljava/lang/Object;)Ljava/lang/Object;
    //   1199: astore 5
    //   1201: goto +20 -> 1221
    //   1204: astore 5
    //   1206: aload 5
    //   1208: invokevirtual 740	java/lang/Throwable:getCause	()Ljava/lang/Throwable;
    //   1211: astore_1
    //   1212: aload_1
    //   1213: ifnull +5 -> 1218
    //   1216: aload_1
    //   1217: athrow
    //   1218: aload 5
    //   1220: athrow
    //   1221: iconst_4
    //   1222: sipush 362
    //   1225: ldc_w 956
    //   1228: invokestatic 746	o/O:ˋ	(IIC)Ljava/lang/Object;
    //   1231: checkcast 748	java/lang/Class
    //   1234: ldc_w 802
    //   1237: aconst_null
    //   1238: invokevirtual 754	java/lang/Class:getMethod	(Ljava/lang/String;[Ljava/lang/Class;)Ljava/lang/reflect/Method;
    //   1241: aload 5
    //   1243: aconst_null
    //   1244: invokevirtual 760	java/lang/reflect/Method:invoke	(Ljava/lang/Object;[Ljava/lang/Object;)Ljava/lang/Object;
    //   1247: checkcast 764	java/lang/String
    //   1250: astore 5
    //   1252: goto -1244 -> 8
    //   1255: iconst_1
    //   1256: istore_3
    //   1257: goto -472 -> 785
    //   1260: sipush 787
    //   1263: ldc_w 960
    //   1266: bipush 37
    //   1268: invokestatic 772	o/Ir:ˏ	(ICI)Ljava/lang/String;
    //   1271: invokevirtual 776	java/lang/String:intern	()Ljava/lang/String;
    //   1274: astore 7
    //   1276: goto +263 -> 1539
    //   1279: iconst_4
    //   1280: sipush 362
    //   1283: ldc_w 956
    //   1286: invokestatic 746	o/O:ˋ	(IIC)Ljava/lang/Object;
    //   1289: checkcast 748	java/lang/Class
    //   1292: ldc_w 796
    //   1295: invokevirtual 787	java/lang/Class:getField	(Ljava/lang/String;)Ljava/lang/reflect/Field;
    //   1298: aconst_null
    //   1299: invokevirtual 793	java/lang/reflect/Field:get	(Ljava/lang/Object;)Ljava/lang/Object;
    //   1302: astore 5
    //   1304: goto +20 -> 1324
    //   1307: astore_1
    //   1308: aload_1
    //   1309: invokevirtual 740	java/lang/Throwable:getCause	()Ljava/lang/Throwable;
    //   1312: astore 5
    //   1314: aload 5
    //   1316: ifnull +6 -> 1322
    //   1319: aload 5
    //   1321: athrow
    //   1322: aload_1
    //   1323: athrow
    //   1324: bipush 7
    //   1326: sipush 366
    //   1329: iconst_0
    //   1330: invokestatic 746	o/O:ˋ	(IIC)Ljava/lang/Object;
    //   1333: checkcast 748	java/lang/Class
    //   1336: ldc_w 802
    //   1339: aconst_null
    //   1340: invokevirtual 754	java/lang/Class:getMethod	(Ljava/lang/String;[Ljava/lang/Class;)Ljava/lang/reflect/Method;
    //   1343: aload 5
    //   1345: aconst_null
    //   1346: invokevirtual 760	java/lang/reflect/Method:invoke	(Ljava/lang/Object;[Ljava/lang/Object;)Ljava/lang/Object;
    //   1349: astore 5
    //   1351: goto +20 -> 1371
    //   1354: astore 5
    //   1356: aload 5
    //   1358: invokevirtual 740	java/lang/Throwable:getCause	()Ljava/lang/Throwable;
    //   1361: astore_1
    //   1362: aload_1
    //   1363: ifnull +5 -> 1368
    //   1366: aload_1
    //   1367: athrow
    //   1368: aload 5
    //   1370: athrow
    //   1371: iconst_4
    //   1372: sipush 362
    //   1375: ldc_w 956
    //   1378: invokestatic 746	o/O:ˋ	(IIC)Ljava/lang/Object;
    //   1381: checkcast 748	java/lang/Class
    //   1384: ldc_w 750
    //   1387: aconst_null
    //   1388: invokevirtual 754	java/lang/Class:getMethod	(Ljava/lang/String;[Ljava/lang/Class;)Ljava/lang/reflect/Method;
    //   1391: aload 5
    //   1393: aconst_null
    //   1394: invokevirtual 760	java/lang/reflect/Method:invoke	(Ljava/lang/Object;[Ljava/lang/Object;)Ljava/lang/Object;
    //   1397: checkcast 764	java/lang/String
    //   1400: astore 5
    //   1402: aconst_null
    //   1403: arraylength
    //   1404: istore_3
    //   1405: goto +260 -> 1665
    //   1408: bipush 24
    //   1410: istore_3
    //   1411: goto +305 -> 1716
    //   1414: aload 5
    //   1416: sipush 2304
    //   1419: iconst_0
    //   1420: bipush 57
    //   1422: invokestatic 772	o/Ir:ˏ	(ICI)Ljava/lang/String;
    //   1425: invokevirtual 776	java/lang/String:intern	()Ljava/lang/String;
    //   1428: invokevirtual 954	java/lang/StringBuilder:append	(Ljava/lang/String;)Ljava/lang/StringBuilder;
    //   1431: astore 5
    //   1433: goto -470 -> 963
    //   1436: goto +59 -> 1495
    //   1439: iconst_1
    //   1440: istore_3
    //   1441: goto -584 -> 857
    //   1444: goto -606 -> 838
    //   1447: getstatic 49	o/Ir:ˊ	I
    //   1450: istore_3
    //   1451: iload_3
    //   1452: bipush 109
    //   1454: ixor
    //   1455: iload_3
    //   1456: bipush 109
    //   1458: iand
    //   1459: ior
    //   1460: iconst_1
    //   1461: ishl
    //   1462: iload_3
    //   1463: bipush 109
    //   1465: iand
    //   1466: iconst_m1
    //   1467: ixor
    //   1468: iload_3
    //   1469: bipush 109
    //   1471: ior
    //   1472: iand
    //   1473: isub
    //   1474: istore_3
    //   1475: iload_3
    //   1476: sipush 128
    //   1479: irem
    //   1480: putstatic 51	o/Ir:ॱ	I
    //   1483: iload_3
    //   1484: iconst_2
    //   1485: irem
    //   1486: ifeq +6 -> 1492
    //   1489: goto -659 -> 830
    //   1492: goto -1004 -> 488
    //   1495: getstatic 49	o/Ir:ˊ	I
    //   1498: bipush 13
    //   1500: iadd
    //   1501: iconst_1
    //   1502: isub
    //   1503: iconst_1
    //   1504: isub
    //   1505: istore_3
    //   1506: iload_3
    //   1507: sipush 128
    //   1510: irem
    //   1511: putstatic 51	o/Ir:ॱ	I
    //   1514: iload_3
    //   1515: iconst_2
    //   1516: irem
    //   1517: ifeq +5 -> 1522
    //   1520: aload_1
    //   1521: areturn
    //   1522: aload_1
    //   1523: areturn
    //   1524: new 949	java/lang/StringBuilder
    //   1527: dup
    //   1528: invokespecial 950	java/lang/StringBuilder:<init>	()V
    //   1531: astore 6
    //   1533: goto -818 -> 715
    //   1536: aload 5
    //   1538: areturn
    //   1539: getstatic 49	o/Ir:ˊ	I
    //   1542: istore_3
    //   1543: iload_3
    //   1544: iconst_2
    //   1545: ixor
    //   1546: iload_3
    //   1547: iconst_2
    //   1548: iand
    //   1549: iconst_1
    //   1550: ishl
    //   1551: iadd
    //   1552: iconst_1
    //   1553: isub
    //   1554: istore_3
    //   1555: iload_3
    //   1556: sipush 128
    //   1559: irem
    //   1560: putstatic 51	o/Ir:ॱ	I
    //   1563: iload_3
    //   1564: iconst_2
    //   1565: irem
    //   1566: ifeq +6 -> 1572
    //   1569: goto +90 -> 1659
    //   1572: goto -756 -> 816
    //   1575: sipush 777
    //   1578: iconst_0
    //   1579: bipush 10
    //   1581: invokestatic 772	o/Ir:ˏ	(ICI)Ljava/lang/String;
    //   1584: astore_1
    //   1585: aload_1
    //   1586: invokevirtual 776	java/lang/String:intern	()Ljava/lang/String;
    //   1589: astore_1
    //   1590: aload 6
    //   1592: aload_1
    //   1593: invokevirtual 954	java/lang/StringBuilder:append	(Ljava/lang/String;)Ljava/lang/StringBuilder;
    //   1596: astore_1
    //   1597: aload_1
    //   1598: aload 5
    //   1600: invokevirtual 954	java/lang/StringBuilder:append	(Ljava/lang/String;)Ljava/lang/StringBuilder;
    //   1603: astore_1
    //   1604: aload_1
    //   1605: invokevirtual 955	java/lang/StringBuilder:toString	()Ljava/lang/String;
    //   1608: astore_1
    //   1609: new 726	java/lang/NullPointerException
    //   1612: dup
    //   1613: invokespecial 782	java/lang/NullPointerException:<init>	()V
    //   1616: athrow
    //   1617: iload_2
    //   1618: ifeq +6 -> 1624
    //   1621: goto -213 -> 1408
    //   1624: goto -1309 -> 315
    //   1627: iload_3
    //   1628: lookupswitch	default:+28->1656, 75:+-981->647, 81:+-53->1575
    //   1656: goto -81 -> 1575
    //   1659: bipush 31
    //   1661: istore_3
    //   1662: goto -1586 -> 76
    //   1665: getstatic 49	o/Ir:ˊ	I
    //   1668: istore_3
    //   1669: iload_3
    //   1670: bipush 81
    //   1672: iand
    //   1673: iload_3
    //   1674: bipush 81
    //   1676: ixor
    //   1677: iload_3
    //   1678: bipush 81
    //   1680: iand
    //   1681: ior
    //   1682: ineg
    //   1683: ineg
    //   1684: iconst_m1
    //   1685: ixor
    //   1686: isub
    //   1687: iconst_1
    //   1688: isub
    //   1689: istore_3
    //   1690: iload_3
    //   1691: sipush 128
    //   1694: irem
    //   1695: putstatic 51	o/Ir:ॱ	I
    //   1698: iload_3
    //   1699: iconst_2
    //   1700: irem
    //   1701: ifeq +6 -> 1707
    //   1704: goto -882 -> 822
    //   1707: goto -896 -> 811
    //   1710: goto -872 -> 838
    //   1713: astore_1
    //   1714: aload_1
    //   1715: athrow
    //   1716: iload_3
    //   1717: lookupswitch	default:+27->1744, 24:+71->1788, 70:+-588->1129
    //   1744: goto +44 -> 1788
    //   1747: iload_3
    //   1748: lookupswitch	default:+28->1776, 62:+-38->1710, 73:+-1679->69
    //   1776: goto -66 -> 1710
    //   1779: bipush 62
    //   1781: istore_3
    //   1782: goto -35 -> 1747
    //   1785: goto -950 -> 835
    //   1788: getstatic 49	o/Ir:ˊ	I
    //   1791: istore 4
    //   1793: iload 4
    //   1795: bipush 51
    //   1797: iand
    //   1798: iconst_m1
    //   1799: ixor
    //   1800: iload 4
    //   1802: bipush 51
    //   1804: ior
    //   1805: iand
    //   1806: istore_3
    //   1807: iload 4
    //   1809: bipush 51
    //   1811: iand
    //   1812: iconst_1
    //   1813: ishl
    //   1814: istore 4
    //   1816: iload_3
    //   1817: iload 4
    //   1819: iand
    //   1820: iload_3
    //   1821: iload 4
    //   1823: ior
    //   1824: iadd
    //   1825: istore_3
    //   1826: iload_3
    //   1827: sipush 128
    //   1830: irem
    //   1831: putstatic 51	o/Ir:ॱ	I
    //   1834: iload_3
    //   1835: iconst_2
    //   1836: irem
    //   1837: ifeq +6 -> 1843
    //   1840: goto -1358 -> 482
    //   1843: goto -1649 -> 194
    //   1846: getstatic 51	o/Ir:ॱ	I
    //   1849: bipush 126
    //   1851: iadd
    //   1852: iconst_1
    //   1853: isub
    //   1854: istore_3
    //   1855: iload_3
    //   1856: sipush 128
    //   1859: irem
    //   1860: putstatic 49	o/Ir:ˊ	I
    //   1863: iload_3
    //   1864: iconst_2
    //   1865: irem
    //   1866: ifne +6 -> 1872
    //   1869: goto -430 -> 1439
    //   1872: goto +11 -> 1883
    //   1875: goto -615 -> 1260
    //   1878: iconst_1
    //   1879: istore_3
    //   1880: goto -1593 -> 287
    //   1883: iconst_0
    //   1884: istore_3
    //   1885: goto -1028 -> 857
    //   1888: aload 6
    //   1890: aload 7
    //   1892: invokevirtual 954	java/lang/StringBuilder:append	(Ljava/lang/String;)Ljava/lang/StringBuilder;
    //   1895: aload 5
    //   1897: invokevirtual 954	java/lang/StringBuilder:append	(Ljava/lang/String;)Ljava/lang/StringBuilder;
    //   1900: invokevirtual 955	java/lang/StringBuilder:toString	()Ljava/lang/String;
    //   1903: astore 6
    //   1905: goto +20 -> 1925
    //   1908: astore_1
    //   1909: aload_1
    //   1910: invokevirtual 740	java/lang/Throwable:getCause	()Ljava/lang/Throwable;
    //   1913: astore 5
    //   1915: aload 5
    //   1917: ifnull +6 -> 1923
    //   1920: aload 5
    //   1922: athrow
    //   1923: aload_1
    //   1924: athrow
    //   1925: iconst_4
    //   1926: bipush 42
    //   1928: ldc_w 936
    //   1931: invokestatic 746	o/O:ˋ	(IIC)Ljava/lang/Object;
    //   1934: checkcast 748	java/lang/Class
    //   1937: ldc_w 802
    //   1940: iconst_2
    //   1941: anewarray 748	java/lang/Class
    //   1944: dup
    //   1945: iconst_0
    //   1946: ldc_w 764
    //   1949: aastore
    //   1950: dup
    //   1951: iconst_1
    //   1952: ldc_w 764
    //   1955: aastore
    //   1956: invokevirtual 754	java/lang/Class:getMethod	(Ljava/lang/String;[Ljava/lang/Class;)Ljava/lang/reflect/Method;
    //   1959: aconst_null
    //   1960: iconst_2
    //   1961: anewarray 4	java/lang/Object
    //   1964: dup
    //   1965: iconst_0
    //   1966: aload_1
    //   1967: aastore
    //   1968: dup
    //   1969: iconst_1
    //   1970: aload 6
    //   1972: aastore
    //   1973: invokevirtual 760	java/lang/reflect/Method:invoke	(Ljava/lang/Object;[Ljava/lang/Object;)Ljava/lang/Object;
    //   1976: pop
    //   1977: goto -1656 -> 321
    // Local variable table:
    //   start	length	slot	name	signature
    //   0	1980	0	this	Ir
    //   0	1980	1	paramString	String
    //   0	1980	2	paramBoolean	boolean
    //   4	1881	3	i	int
    //   11	1813	4	j	int
    //   110	75	5	str1	String
    //   189	201	5	str2	String
    //   394	63	5	localObject1	Object
    //   516	48	5	localObject2	Object
    //   568	38	5	localObject3	Object
    //   614	586	5	localObject4	Object
    //   1204	38	5	localObject5	Object
    //   1250	100	5	localObject6	Object
    //   1354	38	5	localObject7	Object
    //   1400	521	5	localObject8	Object
    //   173	1798	6	localObject9	Object
    //   168	1723	7	str3	String
    // Exception table:
    //   from	to	target	type
    //   127	180	110	finally
    //   411	463	394	finally
    //   538	565	521	finally
    //   585	616	568	finally
    //   1447	1451	827	java/lang/IllegalArgumentException
    //   1475	1483	827	java/lang/RuntimeException
    //   1575	1585	827	java/lang/Exception
    //   1585	1590	827	java/lang/Exception
    //   1585	1590	827	java/lang/IndexOutOfBoundsException
    //   1590	1597	827	java/lang/Exception
    //   1590	1597	827	java/lang/IndexOutOfBoundsException
    //   1597	1604	827	java/lang/Exception
    //   1597	1604	827	java/lang/IndexOutOfBoundsException
    //   1604	1609	827	java/lang/Exception
    //   1604	1609	827	java/lang/IndexOutOfBoundsException
    //   1609	1617	827	java/lang/Exception
    //   1609	1617	827	java/lang/IndexOutOfBoundsException
    //   1855	1863	827	java/lang/RuntimeException
    //   994	1047	977	finally
    //   1174	1201	1157	finally
    //   1221	1252	1204	finally
    //   1324	1351	1307	finally
    //   1371	1402	1354	finally
    //   1129	1154	1713	java/lang/IllegalArgumentException
    //   1590	1597	1713	java/lang/NullPointerException
    //   1597	1604	1713	java/lang/NullPointerException
    //   1604	1609	1713	java/lang/NullPointerException
    //   1604	1609	1713	java/lang/RuntimeException
    //   1609	1617	1713	java/lang/NullPointerException
    //   1846	1855	1713	java/lang/NullPointerException
    //   1855	1863	1713	java/lang/NullPointerException
    //   1925	1977	1908	finally
  }
  
  /* Error */
  private final boolean ˎ(String paramString)
  {
    // Byte code:
    //   0: goto +536 -> 536
    //   3: getstatic 51	o/Ir:ॱ	I
    //   6: istore_3
    //   7: iload_3
    //   8: bipush 7
    //   10: ixor
    //   11: iload_3
    //   12: bipush 7
    //   14: iand
    //   15: ior
    //   16: iconst_1
    //   17: ishl
    //   18: istore_2
    //   19: iload_3
    //   20: bipush 7
    //   22: ixor
    //   23: ineg
    //   24: istore_3
    //   25: iload_2
    //   26: iload_3
    //   27: iand
    //   28: iload_2
    //   29: iload_3
    //   30: ior
    //   31: iadd
    //   32: istore_2
    //   33: iload_2
    //   34: sipush 128
    //   37: irem
    //   38: putstatic 49	o/Ir:ˊ	I
    //   41: iload_2
    //   42: iconst_2
    //   43: irem
    //   44: ifne +6 -> 50
    //   47: goto +319 -> 366
    //   50: goto +247 -> 297
    //   53: new 726	java/lang/NullPointerException
    //   56: dup
    //   57: invokespecial 782	java/lang/NullPointerException:<init>	()V
    //   60: athrow
    //   61: goto -58 -> 3
    //   64: astore_1
    //   65: aload_1
    //   66: athrow
    //   67: iload 4
    //   69: ireturn
    //   70: goto -9 -> 61
    //   73: iload_2
    //   74: lookupswitch	default:+26->100, 68:+-21->53, 71:+-7->67
    //   100: goto -47 -> 53
    //   103: iconst_0
    //   104: istore_2
    //   105: goto +489 -> 594
    //   108: bipush 72
    //   110: istore_2
    //   111: goto +89 -> 200
    //   114: aload_1
    //   115: checkcast 962	java/lang/CharSequence
    //   118: astore_1
    //   119: sipush 337
    //   122: iconst_0
    //   123: bipush 9
    //   125: invokestatic 772	o/Ir:ˏ	(ICI)Ljava/lang/String;
    //   128: astore 5
    //   130: goto +414 -> 544
    //   133: iload_2
    //   134: lookupswitch	default:+26->160, 80:+229->363, 95:+180->314
    //   160: goto +203 -> 363
    //   163: getstatic 49	o/Ir:ˊ	I
    //   166: bipush 26
    //   168: iadd
    //   169: istore_2
    //   170: iload_2
    //   171: iconst_m1
    //   172: ixor
    //   173: iload_2
    //   174: iconst_m1
    //   175: iand
    //   176: iconst_1
    //   177: ishl
    //   178: iadd
    //   179: istore_2
    //   180: iload_2
    //   181: sipush 128
    //   184: irem
    //   185: putstatic 51	o/Ir:ॱ	I
    //   188: iload_2
    //   189: iconst_2
    //   190: irem
    //   191: ifeq +6 -> 197
    //   194: goto +289 -> 483
    //   197: goto +328 -> 525
    //   200: iload_2
    //   201: lookupswitch	default:+27->228, 26:+107->308, 72:+-87->114
    //   228: goto +80 -> 308
    //   231: iload_2
    //   232: lookupswitch	default:+28->260, 92:+-162->70, 95:+352->584
    //   260: goto +324 -> 584
    //   263: goto +168 -> 431
    //   266: iload_2
    //   267: tableswitch	default:+21->288, 0:+41->308, 1:+-153->114
    //   288: goto -174 -> 114
    //   291: bipush 80
    //   293: istore_2
    //   294: goto -161 -> 133
    //   297: bipush 71
    //   299: istore_2
    //   300: goto -227 -> 73
    //   303: iconst_1
    //   304: istore_2
    //   305: goto -39 -> 266
    //   308: iconst_0
    //   309: istore 4
    //   311: goto -148 -> 163
    //   314: goto +153 -> 467
    //   317: iconst_1
    //   318: istore_2
    //   319: goto +275 -> 594
    //   322: bipush 58
    //   324: iconst_0
    //   325: idiv
    //   326: istore_2
    //   327: aload_1
    //   328: ifnull +6 -> 334
    //   331: goto -223 -> 108
    //   334: goto +244 -> 578
    //   337: iload_2
    //   338: tableswitch	default:+22->360, 0:+-30->308, 1:+40->378
    //   360: goto -52 -> 308
    //   363: goto +104 -> 467
    //   366: bipush 68
    //   368: istore_2
    //   369: goto -296 -> 73
    //   372: bipush 95
    //   374: istore_2
    //   375: goto -242 -> 133
    //   378: getstatic 51	o/Ir:ॱ	I
    //   381: istore_3
    //   382: iload_3
    //   383: bipush 51
    //   385: iand
    //   386: iconst_m1
    //   387: ixor
    //   388: iload_3
    //   389: bipush 51
    //   391: ior
    //   392: iand
    //   393: istore_2
    //   394: iload_3
    //   395: bipush 51
    //   397: iand
    //   398: iconst_1
    //   399: ishl
    //   400: istore_3
    //   401: iload_2
    //   402: iload_3
    //   403: ior
    //   404: iconst_1
    //   405: ishl
    //   406: iload_2
    //   407: iload_3
    //   408: ixor
    //   409: isub
    //   410: istore_2
    //   411: iload_2
    //   412: sipush 128
    //   415: irem
    //   416: putstatic 49	o/Ir:ˊ	I
    //   419: iload_2
    //   420: iconst_2
    //   421: irem
    //   422: ifne +6 -> 428
    //   425: goto -134 -> 291
    //   428: goto -56 -> 372
    //   431: aload 5
    //   433: invokevirtual 776	java/lang/String:intern	()Ljava/lang/String;
    //   436: astore 5
    //   438: aload 5
    //   440: checkcast 962	java/lang/CharSequence
    //   443: astore 5
    //   445: aload_1
    //   446: aload 5
    //   448: iconst_0
    //   449: iconst_2
    //   450: aconst_null
    //   451: invokestatic 967	o/vT:ˊ	(Ljava/lang/CharSequence;Ljava/lang/CharSequence;ZILjava/lang/Object;)Z
    //   454: istore 4
    //   456: iload 4
    //   458: ifeq +6 -> 464
    //   461: goto +70 -> 531
    //   464: goto +155 -> 619
    //   467: iconst_1
    //   468: istore 4
    //   470: goto -409 -> 61
    //   473: aload_1
    //   474: ifnull +6 -> 480
    //   477: goto -174 -> 303
    //   480: goto +59 -> 539
    //   483: bipush 95
    //   485: istore_2
    //   486: goto -255 -> 231
    //   489: getstatic 51	o/Ir:ॱ	I
    //   492: istore_2
    //   493: iload_2
    //   494: bipush 91
    //   496: ixor
    //   497: iload_2
    //   498: bipush 91
    //   500: iand
    //   501: iconst_1
    //   502: ishl
    //   503: iadd
    //   504: istore_2
    //   505: iload_2
    //   506: sipush 128
    //   509: irem
    //   510: putstatic 49	o/Ir:ˊ	I
    //   513: iload_2
    //   514: iconst_2
    //   515: irem
    //   516: ifne +6 -> 522
    //   519: goto -202 -> 317
    //   522: goto -419 -> 103
    //   525: bipush 92
    //   527: istore_2
    //   528: goto -297 -> 231
    //   531: iconst_1
    //   532: istore_2
    //   533: goto -196 -> 337
    //   536: goto -47 -> 489
    //   539: iconst_0
    //   540: istore_2
    //   541: goto -275 -> 266
    //   544: getstatic 51	o/Ir:ॱ	I
    //   547: istore_2
    //   548: iload_2
    //   549: bipush 33
    //   551: iand
    //   552: iload_2
    //   553: bipush 33
    //   555: ior
    //   556: iadd
    //   557: istore_2
    //   558: iload_2
    //   559: sipush 128
    //   562: irem
    //   563: putstatic 49	o/Ir:ˊ	I
    //   566: iload_2
    //   567: iconst_2
    //   568: irem
    //   569: ifne +6 -> 575
    //   572: goto -309 -> 263
    //   575: goto -144 -> 431
    //   578: bipush 26
    //   580: istore_2
    //   581: goto -381 -> 200
    //   584: iconst_2
    //   585: iconst_3
    //   586: idiv
    //   587: istore_2
    //   588: goto -527 -> 61
    //   591: astore_1
    //   592: aload_1
    //   593: athrow
    //   594: iload_2
    //   595: tableswitch	default:+21->616, 0:+-122->473, 1:+-273->322
    //   616: goto -143 -> 473
    //   619: iconst_0
    //   620: istore_2
    //   621: goto -284 -> 337
    // Local variable table:
    //   start	length	slot	name	signature
    //   0	624	0	this	Ir
    //   0	624	1	paramString	String
    //   18	603	2	i	int
    //   6	403	3	j	int
    //   67	402	4	bool	boolean
    //   128	319	5	localObject	Object
    // Exception table:
    //   from	to	target	type
    //   431	438	64	java/lang/IndexOutOfBoundsException
    //   445	456	64	java/lang/RuntimeException
    //   3	7	591	java/lang/IllegalArgumentException
    //   33	41	591	java/lang/IllegalArgumentException
    //   33	41	591	java/lang/IndexOutOfBoundsException
    //   114	119	591	java/lang/RuntimeException
    //   119	130	591	java/lang/NumberFormatException
    //   119	130	591	java/lang/RuntimeException
    //   378	382	591	java/lang/RuntimeException
    //   411	419	591	java/lang/RuntimeException
    //   438	445	591	java/lang/IndexOutOfBoundsException
    //   445	456	591	java/lang/IndexOutOfBoundsException
  }
  
  private static String ˏ(int paramInt1, char paramChar, int paramInt2)
  {
    break label198;
    int j = 0;
    break label231;
    char[] arrayOfChar;
    int i;
    arrayOfChar[i] = ((char)(int)(ˋ[(paramInt1 >>> i)] + (i - ˎ) - paramChar));
    i += 127;
    break label259;
    label78:
    label81:
    label118:
    label155:
    label158:
    label165:
    label198:
    for (;;)
    {
      i = ˊ + 55;
      ॱ = i % 128;
      if (i % 2 == 0)
      {
        break label270;
        return new String(arrayOfChar);
        break label259;
        arrayOfChar[i] = ((char)(int)(ˋ[(paramInt1 + i)] ^ i * ˎ ^ paramChar));
        i += 1;
        break label259;
        do
        {
          j = 1;
          break label231;
          for (j = 11;; j = 18) {
            switch (j)
            {
            case 11: 
            default: 
              break label165;
              break label78;
            }
          }
          j = ˊ + 43;
          ॱ = j % 128;
        } while (j % 2 != 0);
        break;
      }
      break label270;
    }
    for (;;)
    {
      j = ˊ + 115;
      ॱ = j % 128;
      if (j % 2 != 0) {
        break label155;
      }
      break;
      label231:
      switch (j)
      {
      }
      break label81;
      label259:
      if (i < paramInt2) {
        break label158;
      }
      break label118;
      label270:
      arrayOfChar = new char[paramInt2];
      i = 0;
    }
  }
  
  /* Error */
  private final java.io.InputStream ॱ(xF paramXF, boolean paramBoolean)
  {
    // Byte code:
    //   0: goto +862 -> 862
    //   3: iconst_4
    //   4: sipush 362
    //   7: ldc_w 956
    //   10: invokestatic 746	o/O:ˋ	(IIC)Ljava/lang/Object;
    //   13: checkcast 748	java/lang/Class
    //   16: ldc_w 796
    //   19: invokevirtual 787	java/lang/Class:getField	(Ljava/lang/String;)Ljava/lang/reflect/Field;
    //   22: aconst_null
    //   23: invokevirtual 793	java/lang/reflect/Field:get	(Ljava/lang/Object;)Ljava/lang/Object;
    //   26: astore_1
    //   27: goto +20 -> 47
    //   30: astore_1
    //   31: aload_1
    //   32: invokevirtual 740	java/lang/Throwable:getCause	()Ljava/lang/Throwable;
    //   35: astore 5
    //   37: aload 5
    //   39: ifnull +6 -> 45
    //   42: aload 5
    //   44: athrow
    //   45: aload_1
    //   46: athrow
    //   47: bipush 7
    //   49: sipush 366
    //   52: iconst_0
    //   53: invokestatic 746	o/O:ˋ	(IIC)Ljava/lang/Object;
    //   56: checkcast 748	java/lang/Class
    //   59: ldc_w 802
    //   62: aconst_null
    //   63: invokevirtual 754	java/lang/Class:getMethod	(Ljava/lang/String;[Ljava/lang/Class;)Ljava/lang/reflect/Method;
    //   66: aload_1
    //   67: aconst_null
    //   68: invokevirtual 760	java/lang/reflect/Method:invoke	(Ljava/lang/Object;[Ljava/lang/Object;)Ljava/lang/Object;
    //   71: astore_1
    //   72: goto +20 -> 92
    //   75: astore_1
    //   76: aload_1
    //   77: invokevirtual 740	java/lang/Throwable:getCause	()Ljava/lang/Throwable;
    //   80: astore 5
    //   82: aload 5
    //   84: ifnull +6 -> 90
    //   87: aload 5
    //   89: athrow
    //   90: aload_1
    //   91: athrow
    //   92: iconst_4
    //   93: sipush 362
    //   96: ldc_w 956
    //   99: invokestatic 746	o/O:ˋ	(IIC)Ljava/lang/Object;
    //   102: checkcast 748	java/lang/Class
    //   105: ldc_w 783
    //   108: aconst_null
    //   109: invokevirtual 754	java/lang/Class:getMethod	(Ljava/lang/String;[Ljava/lang/Class;)Ljava/lang/reflect/Method;
    //   112: aload_1
    //   113: aconst_null
    //   114: invokevirtual 760	java/lang/reflect/Method:invoke	(Ljava/lang/Object;[Ljava/lang/Object;)Ljava/lang/Object;
    //   117: checkcast 764	java/lang/String
    //   120: astore_1
    //   121: new 726	java/lang/NullPointerException
    //   124: dup
    //   125: invokespecial 782	java/lang/NullPointerException:<init>	()V
    //   128: athrow
    //   129: getstatic 49	o/Ir:ˊ	I
    //   132: bipush 106
    //   134: iadd
    //   135: iconst_1
    //   136: isub
    //   137: istore_3
    //   138: iload_3
    //   139: sipush 128
    //   142: irem
    //   143: putstatic 51	o/Ir:ॱ	I
    //   146: iload_3
    //   147: iconst_2
    //   148: irem
    //   149: ifeq +6 -> 155
    //   152: goto +485 -> 637
    //   155: goto +448 -> 603
    //   158: new 949	java/lang/StringBuilder
    //   161: dup
    //   162: invokespecial 950	java/lang/StringBuilder:<init>	()V
    //   165: astore 5
    //   167: aload 6
    //   169: invokevirtual 975	java/io/BufferedReader:readLine	()Ljava/lang/String;
    //   172: astore_1
    //   173: goto +374 -> 547
    //   176: iconst_1
    //   177: istore_3
    //   178: goto +687 -> 865
    //   181: goto +929 -> 1110
    //   184: sipush 253
    //   187: ldc_w 947
    //   190: bipush 7
    //   192: invokestatic 772	o/Ir:ˏ	(ICI)Ljava/lang/String;
    //   195: invokevirtual 776	java/lang/String:intern	()Ljava/lang/String;
    //   198: astore 5
    //   200: new 949	java/lang/StringBuilder
    //   203: dup
    //   204: invokespecial 950	java/lang/StringBuilder:<init>	()V
    //   207: astore 6
    //   209: goto +197 -> 406
    //   212: iconst_4
    //   213: sipush 362
    //   216: ldc_w 956
    //   219: invokestatic 746	o/O:ˋ	(IIC)Ljava/lang/Object;
    //   222: checkcast 748	java/lang/Class
    //   225: ldc_w 796
    //   228: invokevirtual 787	java/lang/Class:getField	(Ljava/lang/String;)Ljava/lang/reflect/Field;
    //   231: aconst_null
    //   232: invokevirtual 793	java/lang/reflect/Field:get	(Ljava/lang/Object;)Ljava/lang/Object;
    //   235: astore_1
    //   236: goto +20 -> 256
    //   239: astore 5
    //   241: aload 5
    //   243: invokevirtual 740	java/lang/Throwable:getCause	()Ljava/lang/Throwable;
    //   246: astore_1
    //   247: aload_1
    //   248: ifnull +5 -> 253
    //   251: aload_1
    //   252: athrow
    //   253: aload 5
    //   255: athrow
    //   256: bipush 7
    //   258: sipush 366
    //   261: iconst_0
    //   262: invokestatic 746	o/O:ˋ	(IIC)Ljava/lang/Object;
    //   265: checkcast 748	java/lang/Class
    //   268: ldc_w 802
    //   271: aconst_null
    //   272: invokevirtual 754	java/lang/Class:getMethod	(Ljava/lang/String;[Ljava/lang/Class;)Ljava/lang/reflect/Method;
    //   275: aload_1
    //   276: aconst_null
    //   277: invokevirtual 760	java/lang/reflect/Method:invoke	(Ljava/lang/Object;[Ljava/lang/Object;)Ljava/lang/Object;
    //   280: astore_1
    //   281: goto +20 -> 301
    //   284: astore 5
    //   286: aload 5
    //   288: invokevirtual 740	java/lang/Throwable:getCause	()Ljava/lang/Throwable;
    //   291: astore_1
    //   292: aload_1
    //   293: ifnull +5 -> 298
    //   296: aload_1
    //   297: athrow
    //   298: aload 5
    //   300: athrow
    //   301: iconst_4
    //   302: sipush 362
    //   305: ldc_w 956
    //   308: invokestatic 746	o/O:ˋ	(IIC)Ljava/lang/Object;
    //   311: checkcast 748	java/lang/Class
    //   314: ldc_w 783
    //   317: aconst_null
    //   318: invokevirtual 754	java/lang/Class:getMethod	(Ljava/lang/String;[Ljava/lang/Class;)Ljava/lang/reflect/Method;
    //   321: aload_1
    //   322: aconst_null
    //   323: invokevirtual 760	java/lang/reflect/Method:invoke	(Ljava/lang/Object;[Ljava/lang/Object;)Ljava/lang/Object;
    //   326: checkcast 764	java/lang/String
    //   329: astore_1
    //   330: goto +327 -> 657
    //   333: goto +309 -> 642
    //   336: iload_3
    //   337: tableswitch	default:+23->360, 0:+904->1241, 1:+-4->333
    //   360: goto +881 -> 1241
    //   363: aload_1
    //   364: aload 5
    //   366: invokevirtual 979	java/lang/String:getBytes	(Ljava/nio/charset/Charset;)[B
    //   369: astore 5
    //   371: sipush 690
    //   374: iconst_0
    //   375: bipush 44
    //   377: invokestatic 772	o/Ir:ˏ	(ICI)Ljava/lang/String;
    //   380: astore_1
    //   381: goto +130 -> 511
    //   384: new 981	o/uH
    //   387: dup
    //   388: sipush 637
    //   391: ldc_w 982
    //   394: bipush 53
    //   396: invokestatic 772	o/Ir:ˏ	(ICI)Ljava/lang/String;
    //   399: invokevirtual 776	java/lang/String:intern	()Ljava/lang/String;
    //   402: invokespecial 985	o/uH:<init>	(Ljava/lang/String;)V
    //   405: athrow
    //   406: getstatic 49	o/Ir:ˊ	I
    //   409: bipush 52
    //   411: iadd
    //   412: iconst_0
    //   413: iadd
    //   414: iconst_1
    //   415: isub
    //   416: istore_3
    //   417: iload_3
    //   418: sipush 128
    //   421: irem
    //   422: putstatic 51	o/Ir:ॱ	I
    //   425: iload_3
    //   426: iconst_2
    //   427: irem
    //   428: ifeq +6 -> 434
    //   431: goto +296 -> 727
    //   434: goto +235 -> 669
    //   437: getstatic 49	o/Ir:ˊ	I
    //   440: istore 4
    //   442: iload 4
    //   444: bipush 97
    //   446: ixor
    //   447: iload 4
    //   449: bipush 97
    //   451: iand
    //   452: ior
    //   453: iconst_1
    //   454: ishl
    //   455: istore_3
    //   456: iload 4
    //   458: bipush -98
    //   460: iand
    //   461: iload 4
    //   463: iconst_m1
    //   464: ixor
    //   465: bipush 97
    //   467: iand
    //   468: ior
    //   469: ineg
    //   470: istore 4
    //   472: iload_3
    //   473: iload 4
    //   475: iand
    //   476: iload_3
    //   477: iload 4
    //   479: ior
    //   480: iadd
    //   481: istore_3
    //   482: iload_3
    //   483: sipush 128
    //   486: irem
    //   487: putstatic 51	o/Ir:ॱ	I
    //   490: iload_3
    //   491: iconst_2
    //   492: irem
    //   493: ifeq +6 -> 499
    //   496: goto +609 -> 1105
    //   499: goto -323 -> 176
    //   502: goto +106 -> 608
    //   505: bipush 75
    //   507: istore_3
    //   508: goto +754 -> 1262
    //   511: aload 5
    //   513: aload_1
    //   514: invokevirtual 776	java/lang/String:intern	()Ljava/lang/String;
    //   517: invokestatic 801	o/vq:ˋ	(Ljava/lang/Object;Ljava/lang/String;)V
    //   520: new 987	java/io/ByteArrayInputStream
    //   523: dup
    //   524: aload 5
    //   526: invokespecial 990	java/io/ByteArrayInputStream:<init>	([B)V
    //   529: checkcast 992	java/io/InputStream
    //   532: astore_1
    //   533: aload_1
    //   534: areturn
    //   535: aload 6
    //   537: invokevirtual 975	java/io/BufferedReader:readLine	()Ljava/lang/String;
    //   540: astore_1
    //   541: aconst_null
    //   542: arraylength
    //   543: istore_3
    //   544: goto +381 -> 925
    //   547: getstatic 49	o/Ir:ˊ	I
    //   550: istore_3
    //   551: iload_3
    //   552: bipush 115
    //   554: ior
    //   555: iconst_1
    //   556: ishl
    //   557: iload_3
    //   558: bipush 115
    //   560: ixor
    //   561: isub
    //   562: istore_3
    //   563: iload_3
    //   564: sipush 128
    //   567: irem
    //   568: putstatic 51	o/Ir:ॱ	I
    //   571: iload_3
    //   572: iconst_2
    //   573: irem
    //   574: ifeq +6 -> 580
    //   577: goto +23 -> 600
    //   580: goto -399 -> 181
    //   583: aload 6
    //   585: invokevirtual 975	java/io/BufferedReader:readLine	()Ljava/lang/String;
    //   588: astore_1
    //   589: goto +336 -> 925
    //   592: astore_1
    //   593: aload_1
    //   594: athrow
    //   595: iconst_1
    //   596: istore_3
    //   597: goto -261 -> 336
    //   600: goto -419 -> 181
    //   603: iconst_1
    //   604: istore_3
    //   605: goto +286 -> 891
    //   608: aload 6
    //   610: sipush 516
    //   613: iconst_0
    //   614: bipush 27
    //   616: invokestatic 772	o/Ir:ˏ	(ICI)Ljava/lang/String;
    //   619: invokevirtual 776	java/lang/String:intern	()Ljava/lang/String;
    //   622: invokestatic 801	o/vq:ˋ	(Ljava/lang/Object;Ljava/lang/String;)V
    //   625: aload 5
    //   627: aload 6
    //   629: aload_1
    //   630: invokevirtual 994	o/Iq$ˊ:ˊ	(Ljava/lang/String;Ljava/lang/String;)Ljava/lang/String;
    //   633: astore_1
    //   634: goto -450 -> 184
    //   637: iconst_0
    //   638: istore_3
    //   639: goto +252 -> 891
    //   642: aload 5
    //   644: invokevirtual 955	java/lang/StringBuilder:toString	()Ljava/lang/String;
    //   647: astore 6
    //   649: getstatic 941	o/Iq:Companion	Lo/Iq$ˊ;
    //   652: astore 5
    //   654: goto +637 -> 1291
    //   657: goto -15 -> 642
    //   660: astore_1
    //   661: aload_1
    //   662: athrow
    //   663: bipush 29
    //   665: istore_3
    //   666: goto +596 -> 1262
    //   669: aload 6
    //   671: sipush 543
    //   674: iconst_0
    //   675: bipush 37
    //   677: invokestatic 772	o/Ir:ˏ	(ICI)Ljava/lang/String;
    //   680: invokevirtual 776	java/lang/String:intern	()Ljava/lang/String;
    //   683: invokevirtual 954	java/lang/StringBuilder:append	(Ljava/lang/String;)Ljava/lang/StringBuilder;
    //   686: aload_1
    //   687: invokevirtual 954	java/lang/StringBuilder:append	(Ljava/lang/String;)Ljava/lang/StringBuilder;
    //   690: invokevirtual 955	java/lang/StringBuilder:toString	()Ljava/lang/String;
    //   693: astore 6
    //   695: goto +35 -> 730
    //   698: iload_3
    //   699: lookupswitch	default:+25->724, 43:+421->1120, 83:+-570->129
    //   724: goto +396 -> 1120
    //   727: goto -58 -> 669
    //   730: goto +20 -> 750
    //   733: astore 5
    //   735: aload 5
    //   737: invokevirtual 740	java/lang/Throwable:getCause	()Ljava/lang/Throwable;
    //   740: astore_1
    //   741: aload_1
    //   742: ifnull +5 -> 747
    //   745: aload_1
    //   746: athrow
    //   747: aload 5
    //   749: athrow
    //   750: iconst_4
    //   751: bipush 42
    //   753: ldc_w 936
    //   756: invokestatic 746	o/O:ˋ	(IIC)Ljava/lang/Object;
    //   759: checkcast 748	java/lang/Class
    //   762: ldc_w 802
    //   765: iconst_2
    //   766: anewarray 748	java/lang/Class
    //   769: dup
    //   770: iconst_0
    //   771: ldc_w 764
    //   774: aastore
    //   775: dup
    //   776: iconst_1
    //   777: ldc_w 764
    //   780: aastore
    //   781: invokevirtual 754	java/lang/Class:getMethod	(Ljava/lang/String;[Ljava/lang/Class;)Ljava/lang/reflect/Method;
    //   784: aconst_null
    //   785: iconst_2
    //   786: anewarray 4	java/lang/Object
    //   789: dup
    //   790: iconst_0
    //   791: aload 5
    //   793: aastore
    //   794: dup
    //   795: iconst_1
    //   796: aload 6
    //   798: aastore
    //   799: invokevirtual 760	java/lang/reflect/Method:invoke	(Ljava/lang/Object;[Ljava/lang/Object;)Ljava/lang/Object;
    //   802: pop
    //   803: getstatic 1000	java/nio/charset/StandardCharsets:UTF_8	Ljava/nio/charset/Charset;
    //   806: invokevirtual 1005	java/nio/charset/Charset:name	()Ljava/lang/String;
    //   809: astore 5
    //   811: aload 5
    //   813: sipush 580
    //   816: iconst_0
    //   817: bipush 29
    //   819: invokestatic 772	o/Ir:ˏ	(ICI)Ljava/lang/String;
    //   822: invokevirtual 776	java/lang/String:intern	()Ljava/lang/String;
    //   825: invokestatic 801	o/vq:ˋ	(Ljava/lang/Object;Ljava/lang/String;)V
    //   828: aload 5
    //   830: invokestatic 1009	java/nio/charset/Charset:forName	(Ljava/lang/String;)Ljava/nio/charset/Charset;
    //   833: astore 5
    //   835: aload 5
    //   837: sipush 609
    //   840: iconst_0
    //   841: bipush 28
    //   843: invokestatic 772	o/Ir:ˏ	(ICI)Ljava/lang/String;
    //   846: invokevirtual 776	java/lang/String:intern	()Ljava/lang/String;
    //   849: invokestatic 801	o/vq:ˋ	(Ljava/lang/Object;Ljava/lang/String;)V
    //   852: aload_1
    //   853: ifnonnull +6 -> 859
    //   856: goto -472 -> 384
    //   859: goto -496 -> 363
    //   862: goto +82 -> 944
    //   865: iload_3
    //   866: tableswitch	default:+22->888, 0:+-331->535, 1:+-283->583
    //   888: goto -305 -> 583
    //   891: iload_3
    //   892: tableswitch	default:+24->916, 0:+-889->3, 1:+-680->212
    //   916: goto -704 -> 212
    //   919: bipush 43
    //   921: istore_3
    //   922: goto -224 -> 698
    //   925: goto +185 -> 1110
    //   928: astore_1
    //   929: new 1011	java/io/IOException
    //   932: dup
    //   933: aload_1
    //   934: checkcast 736	java/lang/Throwable
    //   937: invokespecial 1014	java/io/IOException:<init>	(Ljava/lang/Throwable;)V
    //   940: checkcast 736	java/lang/Throwable
    //   943: athrow
    //   944: new 972	java/io/BufferedReader
    //   947: dup
    //   948: new 1016	java/io/InputStreamReader
    //   951: dup
    //   952: aload_1
    //   953: invokevirtual 1019	o/xF:ˊ	()Ljava/io/InputStream;
    //   956: invokespecial 1022	java/io/InputStreamReader:<init>	(Ljava/io/InputStream;)V
    //   959: checkcast 1024	java/io/Reader
    //   962: invokespecial 1027	java/io/BufferedReader:<init>	(Ljava/io/Reader;)V
    //   965: astore 6
    //   967: goto -809 -> 158
    //   970: bipush 83
    //   972: istore_3
    //   973: goto -275 -> 698
    //   976: iconst_0
    //   977: istore_3
    //   978: goto -642 -> 336
    //   981: getstatic 49	o/Ir:ˊ	I
    //   984: istore_3
    //   985: iload_3
    //   986: bipush 105
    //   988: ixor
    //   989: iload_3
    //   990: bipush 105
    //   992: iand
    //   993: ior
    //   994: iconst_1
    //   995: ishl
    //   996: iload_3
    //   997: bipush 105
    //   999: iand
    //   1000: iconst_m1
    //   1001: ixor
    //   1002: iload_3
    //   1003: bipush 105
    //   1005: ior
    //   1006: iand
    //   1007: isub
    //   1008: istore_3
    //   1009: iload_3
    //   1010: sipush 128
    //   1013: irem
    //   1014: putstatic 51	o/Ir:ॱ	I
    //   1017: iload_3
    //   1018: iconst_2
    //   1019: irem
    //   1020: ifeq +6 -> 1026
    //   1023: goto -47 -> 976
    //   1026: goto -431 -> 595
    //   1029: getstatic 49	o/Ir:ˊ	I
    //   1032: istore 4
    //   1034: iload 4
    //   1036: bipush 17
    //   1038: ixor
    //   1039: iload 4
    //   1041: bipush 17
    //   1043: iand
    //   1044: ior
    //   1045: iconst_1
    //   1046: ishl
    //   1047: istore_3
    //   1048: iload 4
    //   1050: bipush 17
    //   1052: ior
    //   1053: iload 4
    //   1055: bipush 17
    //   1057: iand
    //   1058: iconst_m1
    //   1059: ixor
    //   1060: iand
    //   1061: istore 4
    //   1063: iload 4
    //   1065: ineg
    //   1066: iload_3
    //   1067: iand
    //   1068: iload_3
    //   1069: iload 4
    //   1071: ineg
    //   1072: ior
    //   1073: iadd
    //   1074: istore_3
    //   1075: iload_3
    //   1076: sipush 128
    //   1079: irem
    //   1080: putstatic 51	o/Ir:ॱ	I
    //   1083: iload_3
    //   1084: iconst_2
    //   1085: irem
    //   1086: ifeq +6 -> 1092
    //   1089: goto +170 -> 1259
    //   1092: goto +152 -> 1244
    //   1095: iload_2
    //   1096: ifeq +6 -> 1102
    //   1099: goto -129 -> 970
    //   1102: goto -183 -> 919
    //   1105: iconst_0
    //   1106: istore_3
    //   1107: goto -242 -> 865
    //   1110: aload_1
    //   1111: ifnull +6 -> 1117
    //   1114: goto -609 -> 505
    //   1117: goto -454 -> 663
    //   1120: iconst_4
    //   1121: sipush 362
    //   1124: ldc_w 956
    //   1127: invokestatic 746	o/O:ˋ	(IIC)Ljava/lang/Object;
    //   1130: checkcast 748	java/lang/Class
    //   1133: ldc_w 796
    //   1136: invokevirtual 787	java/lang/Class:getField	(Ljava/lang/String;)Ljava/lang/reflect/Field;
    //   1139: aconst_null
    //   1140: invokevirtual 793	java/lang/reflect/Field:get	(Ljava/lang/Object;)Ljava/lang/Object;
    //   1143: astore_1
    //   1144: goto +20 -> 1164
    //   1147: astore_1
    //   1148: aload_1
    //   1149: invokevirtual 740	java/lang/Throwable:getCause	()Ljava/lang/Throwable;
    //   1152: astore 5
    //   1154: aload 5
    //   1156: ifnull +6 -> 1162
    //   1159: aload 5
    //   1161: athrow
    //   1162: aload_1
    //   1163: athrow
    //   1164: bipush 7
    //   1166: sipush 366
    //   1169: iconst_0
    //   1170: invokestatic 746	o/O:ˋ	(IIC)Ljava/lang/Object;
    //   1173: checkcast 748	java/lang/Class
    //   1176: ldc_w 802
    //   1179: aconst_null
    //   1180: invokevirtual 754	java/lang/Class:getMethod	(Ljava/lang/String;[Ljava/lang/Class;)Ljava/lang/reflect/Method;
    //   1183: aload_1
    //   1184: aconst_null
    //   1185: invokevirtual 760	java/lang/reflect/Method:invoke	(Ljava/lang/Object;[Ljava/lang/Object;)Ljava/lang/Object;
    //   1188: astore_1
    //   1189: goto +20 -> 1209
    //   1192: astore 5
    //   1194: aload 5
    //   1196: invokevirtual 740	java/lang/Throwable:getCause	()Ljava/lang/Throwable;
    //   1199: astore_1
    //   1200: aload_1
    //   1201: ifnull +5 -> 1206
    //   1204: aload_1
    //   1205: athrow
    //   1206: aload 5
    //   1208: athrow
    //   1209: iconst_4
    //   1210: sipush 362
    //   1213: ldc_w 956
    //   1216: invokestatic 746	o/O:ˋ	(IIC)Ljava/lang/Object;
    //   1219: checkcast 748	java/lang/Class
    //   1222: ldc_w 1028
    //   1225: aconst_null
    //   1226: invokevirtual 754	java/lang/Class:getMethod	(Ljava/lang/String;[Ljava/lang/Class;)Ljava/lang/reflect/Method;
    //   1229: aload_1
    //   1230: aconst_null
    //   1231: invokevirtual 760	java/lang/reflect/Method:invoke	(Ljava/lang/Object;[Ljava/lang/Object;)Ljava/lang/Object;
    //   1234: checkcast 764	java/lang/String
    //   1237: astore_1
    //   1238: goto -257 -> 981
    //   1241: goto -599 -> 642
    //   1244: aload 5
    //   1246: aload_1
    //   1247: invokevirtual 954	java/lang/StringBuilder:append	(Ljava/lang/String;)Ljava/lang/StringBuilder;
    //   1250: bipush 10
    //   1252: invokevirtual 1031	java/lang/StringBuilder:append	(C)Ljava/lang/StringBuilder;
    //   1255: pop
    //   1256: goto -819 -> 437
    //   1259: goto -15 -> 1244
    //   1262: iload_3
    //   1263: lookupswitch	default:+25->1288, 29:+-168->1095, 75:+-234->1029
    //   1288: goto -193 -> 1095
    //   1291: getstatic 49	o/Ir:ˊ	I
    //   1294: istore 4
    //   1296: iload 4
    //   1298: bipush 115
    //   1300: ixor
    //   1301: iload 4
    //   1303: bipush 115
    //   1305: iand
    //   1306: ior
    //   1307: iconst_1
    //   1308: ishl
    //   1309: istore_3
    //   1310: iload 4
    //   1312: bipush 115
    //   1314: iand
    //   1315: iconst_m1
    //   1316: ixor
    //   1317: iload 4
    //   1319: bipush 115
    //   1321: ior
    //   1322: iand
    //   1323: ineg
    //   1324: istore 4
    //   1326: iload_3
    //   1327: iload 4
    //   1329: ixor
    //   1330: iload_3
    //   1331: iload 4
    //   1333: iand
    //   1334: iconst_1
    //   1335: ishl
    //   1336: iadd
    //   1337: istore_3
    //   1338: iload_3
    //   1339: sipush 128
    //   1342: irem
    //   1343: putstatic 51	o/Ir:ॱ	I
    //   1346: iload_3
    //   1347: iconst_2
    //   1348: irem
    //   1349: ifeq +6 -> 1355
    //   1352: goto -850 -> 502
    //   1355: goto -747 -> 608
    // Local variable table:
    //   start	length	slot	name	signature
    //   0	1358	0	this	Ir
    //   0	1358	1	paramXF	xF
    //   0	1358	2	paramBoolean	boolean
    //   137	1212	3	i	int
    //   440	894	4	j	int
    //   35	164	5	localObject1	Object
    //   239	15	5	localObject2	Object
    //   284	81	5	localCharset	java.nio.charset.Charset
    //   369	284	5	localObject3	Object
    //   733	59	5	localObject4	Object
    //   809	351	5	localObject5	Object
    //   1192	53	5	localObject6	Object
    //   167	799	6	localObject7	Object
    // Exception table:
    //   from	to	target	type
    //   47	72	30	finally
    //   92	121	75	finally
    //   256	281	239	finally
    //   301	330	284	finally
    //   129	138	592	java/lang/NumberFormatException
    //   138	146	592	java/lang/NumberFormatException
    //   138	146	592	java/lang/IndexOutOfBoundsException
    //   406	417	592	java/lang/NullPointerException
    //   417	425	592	java/lang/NullPointerException
    //   417	425	592	java/lang/IllegalArgumentException
    //   437	442	592	java/lang/RuntimeException
    //   482	490	592	java/lang/ArrayStoreException
    //   1029	1034	592	java/lang/NumberFormatException
    //   1075	1083	592	java/lang/NumberFormatException
    //   1075	1083	592	java/lang/IndexOutOfBoundsException
    //   547	551	660	java/lang/NullPointerException
    //   563	571	660	java/lang/NullPointerException
    //   563	571	660	java/lang/ArrayStoreException
    //   750	803	733	finally
    //   3	27	928	java/lang/Exception
    //   31	37	928	java/lang/Exception
    //   42	45	928	java/lang/Exception
    //   45	47	928	java/lang/Exception
    //   76	82	928	java/lang/Exception
    //   87	90	928	java/lang/Exception
    //   90	92	928	java/lang/Exception
    //   121	129	928	java/lang/Exception
    //   158	173	928	java/lang/Exception
    //   184	209	928	java/lang/Exception
    //   212	236	928	java/lang/Exception
    //   241	247	928	java/lang/Exception
    //   251	253	928	java/lang/Exception
    //   253	256	928	java/lang/Exception
    //   286	292	928	java/lang/Exception
    //   296	298	928	java/lang/Exception
    //   298	301	928	java/lang/Exception
    //   363	381	928	java/lang/Exception
    //   384	406	928	java/lang/Exception
    //   511	533	928	java/lang/Exception
    //   535	544	928	java/lang/Exception
    //   583	589	928	java/lang/Exception
    //   608	634	928	java/lang/Exception
    //   642	654	928	java/lang/Exception
    //   669	695	928	java/lang/Exception
    //   735	741	928	java/lang/Exception
    //   745	747	928	java/lang/Exception
    //   747	750	928	java/lang/Exception
    //   803	852	928	java/lang/Exception
    //   944	967	928	java/lang/Exception
    //   1120	1144	928	java/lang/Exception
    //   1148	1154	928	java/lang/Exception
    //   1159	1162	928	java/lang/Exception
    //   1162	1164	928	java/lang/Exception
    //   1194	1200	928	java/lang/Exception
    //   1204	1206	928	java/lang/Exception
    //   1206	1209	928	java/lang/Exception
    //   1244	1256	928	java/lang/Exception
    //   1164	1189	1147	finally
    //   1209	1238	1192	finally
  }
  
  /* Error */
  public xJ ˋ(xx.if paramIf)
  {
    // Byte code:
    //   0: goto +1942 -> 1942
    //   3: iconst_1
    //   4: istore_2
    //   5: goto +2180 -> 2185
    //   8: aload 12
    //   10: invokevirtual 1035	o/xG:ˏ	()Lo/xG$if;
    //   13: astore 9
    //   15: aload 9
    //   17: astore 8
    //   19: bipush 107
    //   21: ldc_w 1036
    //   24: bipush 23
    //   26: invokestatic 772	o/Ir:ˏ	(ICI)Ljava/lang/String;
    //   29: astore 10
    //   31: goto +729 -> 760
    //   34: getstatic 51	o/Ir:ॱ	I
    //   37: istore_2
    //   38: iload_2
    //   39: bipush 63
    //   41: ixor
    //   42: iload_2
    //   43: bipush 63
    //   45: iand
    //   46: iconst_1
    //   47: ishl
    //   48: iconst_m1
    //   49: ixor
    //   50: isub
    //   51: iconst_1
    //   52: isub
    //   53: istore_2
    //   54: iload_2
    //   55: sipush 128
    //   58: irem
    //   59: putstatic 49	o/Ir:ˊ	I
    //   62: iload_2
    //   63: iconst_2
    //   64: irem
    //   65: ifne +6 -> 71
    //   68: goto +935 -> 1003
    //   71: goto +1410 -> 1481
    //   74: iconst_0
    //   75: istore_2
    //   76: goto +58 -> 134
    //   79: goto +2937 -> 3016
    //   82: goto +2129 -> 2211
    //   85: iload_2
    //   86: lookupswitch	default:+26->112, 5:+940->1026, 77:+1120->1206
    //   112: goto +1094 -> 1206
    //   115: iconst_1
    //   116: istore_2
    //   117: goto +2794 -> 2911
    //   120: aload 10
    //   122: invokevirtual 1040	o/xJ:ʼ	()Lo/xJ$ˊ;
    //   125: astore 8
    //   127: aload 8
    //   129: astore 9
    //   131: goto +665 -> 796
    //   134: iload_2
    //   135: tableswitch	default:+21->156, 0:+1891->2026, 1:+3046->3181
    //   156: goto +3025 -> 3181
    //   159: iconst_1
    //   160: istore_2
    //   161: goto +817 -> 978
    //   164: bipush 64
    //   166: istore_2
    //   167: goto +1684 -> 1851
    //   170: iload_2
    //   171: tableswitch	default:+21->192, 0:+252->423, 1:+2108->2279
    //   192: goto +231 -> 423
    //   195: aload 12
    //   197: aload 9
    //   199: lload 4
    //   201: aload 8
    //   203: invokestatic 916	o/yX:ˋ	(Ljava/io/InputStream;)Lo/zh;
    //   206: invokestatic 919	o/yX:ˏ	(Lo/zh;)Lo/yT;
    //   209: invokestatic 924	o/xF:ˊ	(Lo/xC;JLo/yT;)Lo/xF;
    //   212: invokevirtual 929	o/xJ$ˊ:ˋ	(Lo/xF;)Lo/xJ$ˊ;
    //   215: pop
    //   216: aload 12
    //   218: invokevirtual 1043	o/xJ$ˊ:ˊ	()Lo/xJ;
    //   221: astore 8
    //   223: goto +1541 -> 1764
    //   226: aload 8
    //   228: sipush 130
    //   231: iconst_0
    //   232: bipush 31
    //   234: invokestatic 772	o/Ir:ˏ	(ICI)Ljava/lang/String;
    //   237: invokevirtual 776	java/lang/String:intern	()Ljava/lang/String;
    //   240: invokestatic 801	o/vq:ˋ	(Ljava/lang/Object;Ljava/lang/String;)V
    //   243: aload_1
    //   244: aload 8
    //   246: invokeinterface 1048 2 0
    //   251: astore 10
    //   253: goto +910 -> 1163
    //   256: goto -30 -> 226
    //   259: goto +2943 -> 3202
    //   262: getstatic 49	o/Ir:ˊ	I
    //   265: istore_3
    //   266: iload_3
    //   267: bipush 7
    //   269: iand
    //   270: istore_2
    //   271: iload_3
    //   272: bipush 7
    //   274: iand
    //   275: iload_3
    //   276: bipush 7
    //   278: ixor
    //   279: ior
    //   280: istore_3
    //   281: iload_2
    //   282: iload_3
    //   283: ior
    //   284: iconst_1
    //   285: ishl
    //   286: iload_2
    //   287: iload_3
    //   288: ixor
    //   289: isub
    //   290: istore_2
    //   291: iload_2
    //   292: sipush 128
    //   295: irem
    //   296: putstatic 51	o/Ir:ॱ	I
    //   299: iload_2
    //   300: iconst_2
    //   301: irem
    //   302: ifeq +6 -> 308
    //   305: goto +2761 -> 3066
    //   308: goto +271 -> 579
    //   311: iconst_1
    //   312: istore_2
    //   313: goto +824 -> 1137
    //   316: aload 10
    //   318: invokevirtual 1040	o/xJ:ʼ	()Lo/xJ$ˊ;
    //   321: astore 12
    //   323: aload 10
    //   325: invokevirtual 903	o/xJ:ॱॱ	()Lo/xF;
    //   328: astore 8
    //   330: goto +1796 -> 2126
    //   333: aconst_null
    //   334: astore 8
    //   336: goto +2454 -> 2790
    //   339: goto +2677 -> 3016
    //   342: goto +2029 -> 2371
    //   345: bipush 65
    //   347: istore_2
    //   348: goto +95 -> 443
    //   351: iload_2
    //   352: iconst_0
    //   353: bipush 38
    //   355: invokestatic 772	o/Ir:ˏ	(ICI)Ljava/lang/String;
    //   358: invokevirtual 776	java/lang/String:intern	()Ljava/lang/String;
    //   361: checkcast 962	java/lang/CharSequence
    //   364: astore 9
    //   366: iconst_4
    //   367: istore_2
    //   368: goto +1236 -> 1604
    //   371: aload 9
    //   373: aload 12
    //   375: invokestatic 801	o/vq:ˋ	(Ljava/lang/Object;Ljava/lang/String;)V
    //   378: aload_0
    //   379: aload 10
    //   381: aload 9
    //   383: iload 6
    //   385: invokespecial 1050	o/Ir:ˋ	(Lo/xJ;Lo/xJ$ˊ;Z)V
    //   388: aload 8
    //   390: invokevirtual 1043	o/xJ$ˊ:ˊ	()Lo/xJ;
    //   393: astore 9
    //   395: goto +2637 -> 3032
    //   398: iload_3
    //   399: tableswitch	default:+21->420, 0:+-48->351, 1:+1546->1945
    //   420: goto -69 -> 351
    //   423: aload 9
    //   425: aload 8
    //   427: invokestatic 801	o/vq:ˋ	(Ljava/lang/Object;Ljava/lang/String;)V
    //   430: new 726	java/lang/NullPointerException
    //   433: dup
    //   434: invokespecial 782	java/lang/NullPointerException:<init>	()V
    //   437: athrow
    //   438: iconst_0
    //   439: istore_2
    //   440: goto +2934 -> 3374
    //   443: iload_2
    //   444: lookupswitch	default:+28->472, 23:+2656->3100, 65:+267->711
    //   472: goto +2628 -> 3100
    //   475: sipush 230
    //   478: sipush 19299
    //   481: bipush 23
    //   483: invokestatic 772	o/Ir:ˏ	(ICI)Ljava/lang/String;
    //   486: invokevirtual 776	java/lang/String:intern	()Ljava/lang/String;
    //   489: astore 8
    //   491: goto +2448 -> 2939
    //   494: iload_2
    //   495: tableswitch	default:+21->516, 0:+474->969, 1:+2503->2998
    //   516: goto +453 -> 969
    //   519: iconst_0
    //   520: istore_2
    //   521: goto +2797 -> 3318
    //   524: getstatic 51	o/Ir:ॱ	I
    //   527: istore_3
    //   528: iload_3
    //   529: bipush 45
    //   531: iand
    //   532: istore_2
    //   533: iload_3
    //   534: bipush 45
    //   536: ixor
    //   537: iload_3
    //   538: bipush 45
    //   540: iand
    //   541: ior
    //   542: ineg
    //   543: istore_3
    //   544: iload_3
    //   545: ineg
    //   546: iload_2
    //   547: ixor
    //   548: iload_2
    //   549: iload_3
    //   550: ineg
    //   551: iand
    //   552: iconst_1
    //   553: ishl
    //   554: iadd
    //   555: istore_2
    //   556: iload_2
    //   557: sipush 128
    //   560: irem
    //   561: putstatic 49	o/Ir:ˊ	I
    //   564: iload_2
    //   565: iconst_2
    //   566: irem
    //   567: ifne +6 -> 573
    //   570: goto +1135 -> 1705
    //   573: goto +2618 -> 3191
    //   576: astore_1
    //   577: aload_1
    //   578: athrow
    //   579: iconst_0
    //   580: istore_2
    //   581: goto +1244 -> 1825
    //   584: getstatic 49	o/Ir:ˊ	I
    //   587: bipush 103
    //   589: iadd
    //   590: iconst_1
    //   591: isub
    //   592: iconst_1
    //   593: isub
    //   594: istore_2
    //   595: iload_2
    //   596: sipush 128
    //   599: irem
    //   600: putstatic 51	o/Ir:ॱ	I
    //   603: iload_2
    //   604: iconst_2
    //   605: irem
    //   606: ifeq +6 -> 612
    //   609: goto -527 -> 82
    //   612: goto +1599 -> 2211
    //   615: iload_2
    //   616: lookupswitch	default:+28->644, 12:+1618->2234, 85:+1136->1752
    //   644: goto +1590 -> 2234
    //   647: iload_2
    //   648: lookupswitch	default:+28->676, 39:+611->1259, 48:+456->1104
    //   676: goto +428 -> 1104
    //   679: iload_2
    //   680: lookupswitch	default:+28->708, 6:+772->1452, 34:+-672->8
    //   708: goto +744 -> 1452
    //   711: getstatic 49	o/Ir:ˊ	I
    //   714: istore_3
    //   715: iload_3
    //   716: bipush 93
    //   718: iand
    //   719: istore_2
    //   720: iload_3
    //   721: bipush 93
    //   723: iand
    //   724: iload_3
    //   725: bipush 93
    //   727: ixor
    //   728: ior
    //   729: istore_3
    //   730: iload_2
    //   731: iload_3
    //   732: ior
    //   733: iconst_1
    //   734: ishl
    //   735: iload_2
    //   736: iload_3
    //   737: ixor
    //   738: isub
    //   739: istore_2
    //   740: iload_2
    //   741: sipush 128
    //   744: irem
    //   745: putstatic 51	o/Ir:ॱ	I
    //   748: iload_2
    //   749: iconst_2
    //   750: irem
    //   751: ifeq +6 -> 757
    //   754: goto +2256 -> 3010
    //   757: goto +1643 -> 2400
    //   760: aload 8
    //   762: aload 10
    //   764: invokevirtual 776	java/lang/String:intern	()Ljava/lang/String;
    //   767: invokestatic 801	o/vq:ˋ	(Ljava/lang/Object;Ljava/lang/String;)V
    //   770: aload_0
    //   771: aload 12
    //   773: aload 8
    //   775: iload 6
    //   777: invokespecial 1052	o/Ir:ˊ	(Lo/xG;Lo/xG$if;Z)V
    //   780: aload 9
    //   782: invokevirtual 1055	o/xG$if:ˎ	()Lo/xG;
    //   785: astore 8
    //   787: goto +924 -> 1711
    //   790: bipush 72
    //   792: istore_2
    //   793: goto +504 -> 1297
    //   796: sipush 215
    //   799: iconst_0
    //   800: bipush 15
    //   802: invokestatic 772	o/Ir:ˏ	(ICI)Ljava/lang/String;
    //   805: invokevirtual 776	java/lang/String:intern	()Ljava/lang/String;
    //   808: astore 12
    //   810: goto +1268 -> 2078
    //   813: astore 9
    //   815: sipush 253
    //   818: ldc_w 947
    //   821: bipush 7
    //   823: invokestatic 772	o/Ir:ˏ	(ICI)Ljava/lang/String;
    //   826: invokevirtual 776	java/lang/String:intern	()Ljava/lang/String;
    //   829: astore 8
    //   831: new 949	java/lang/StringBuilder
    //   834: dup
    //   835: invokespecial 950	java/lang/StringBuilder:<init>	()V
    //   838: sipush 260
    //   841: iconst_0
    //   842: bipush 40
    //   844: invokestatic 772	o/Ir:ˏ	(ICI)Ljava/lang/String;
    //   847: invokevirtual 776	java/lang/String:intern	()Ljava/lang/String;
    //   850: invokevirtual 954	java/lang/StringBuilder:append	(Ljava/lang/String;)Ljava/lang/StringBuilder;
    //   853: aload 9
    //   855: invokevirtual 1058	java/lang/Exception:getMessage	()Ljava/lang/String;
    //   858: invokevirtual 954	java/lang/StringBuilder:append	(Ljava/lang/String;)Ljava/lang/StringBuilder;
    //   861: invokevirtual 955	java/lang/StringBuilder:toString	()Ljava/lang/String;
    //   864: astore 9
    //   866: goto +20 -> 886
    //   869: astore_1
    //   870: aload_1
    //   871: invokevirtual 740	java/lang/Throwable:getCause	()Ljava/lang/Throwable;
    //   874: astore 8
    //   876: aload 8
    //   878: ifnull +6 -> 884
    //   881: aload 8
    //   883: athrow
    //   884: aload_1
    //   885: athrow
    //   886: iconst_4
    //   887: bipush 42
    //   889: ldc_w 936
    //   892: invokestatic 746	o/O:ˋ	(IIC)Ljava/lang/Object;
    //   895: checkcast 748	java/lang/Class
    //   898: ldc_w 783
    //   901: iconst_2
    //   902: anewarray 748	java/lang/Class
    //   905: dup
    //   906: iconst_0
    //   907: ldc_w 764
    //   910: aastore
    //   911: dup
    //   912: iconst_1
    //   913: ldc_w 764
    //   916: aastore
    //   917: invokevirtual 754	java/lang/Class:getMethod	(Ljava/lang/String;[Ljava/lang/Class;)Ljava/lang/reflect/Method;
    //   920: aconst_null
    //   921: iconst_2
    //   922: anewarray 4	java/lang/Object
    //   925: dup
    //   926: iconst_0
    //   927: aload 8
    //   929: aastore
    //   930: dup
    //   931: iconst_1
    //   932: aload 9
    //   934: aastore
    //   935: invokevirtual 760	java/lang/reflect/Method:invoke	(Ljava/lang/Object;[Ljava/lang/Object;)Ljava/lang/Object;
    //   938: pop
    //   939: aload_1
    //   940: aload 11
    //   942: invokevirtual 1055	o/xG$if:ˎ	()Lo/xG;
    //   945: invokeinterface 1048 2 0
    //   950: astore_1
    //   951: aload_1
    //   952: sipush 300
    //   955: iconst_0
    //   956: bipush 37
    //   958: invokestatic 772	o/Ir:ˏ	(ICI)Ljava/lang/String;
    //   961: invokevirtual 776	java/lang/String:intern	()Ljava/lang/String;
    //   964: invokestatic 801	o/vq:ˋ	(Ljava/lang/Object;Ljava/lang/String;)V
    //   967: aload_1
    //   968: areturn
    //   969: iconst_0
    //   970: istore 6
    //   972: goto +2427 -> 3399
    //   975: goto +847 -> 1822
    //   978: iload_2
    //   979: tableswitch	default:+21->1000, 0:+-395->584, 1:+-646->333
    //   1000: goto -416 -> 584
    //   1003: goto +478 -> 1481
    //   1006: bipush 12
    //   1008: istore_2
    //   1009: goto -394 -> 615
    //   1012: aconst_null
    //   1013: arraylength
    //   1014: istore_2
    //   1015: aload 8
    //   1017: ifnull +6 -> 1023
    //   1020: goto -14 -> 1006
    //   1023: goto +1761 -> 2784
    //   1026: aload 8
    //   1028: aload 9
    //   1030: invokevirtual 776	java/lang/String:intern	()Ljava/lang/String;
    //   1033: invokestatic 801	o/vq:ˋ	(Ljava/lang/Object;Ljava/lang/String;)V
    //   1036: aload 8
    //   1038: checkcast 962	java/lang/CharSequence
    //   1041: astore 8
    //   1043: bipush 39
    //   1045: istore_2
    //   1046: goto +2177 -> 3223
    //   1049: getstatic 49	o/Ir:ˊ	I
    //   1052: istore_3
    //   1053: iload_3
    //   1054: bipush 23
    //   1056: iand
    //   1057: istore_2
    //   1058: iload_3
    //   1059: bipush 23
    //   1061: ixor
    //   1062: iload_3
    //   1063: bipush 23
    //   1065: iand
    //   1066: ior
    //   1067: ineg
    //   1068: istore_3
    //   1069: iload_3
    //   1070: ineg
    //   1071: iload_2
    //   1072: ixor
    //   1073: iload_2
    //   1074: iload_3
    //   1075: ineg
    //   1076: iand
    //   1077: iconst_1
    //   1078: ishl
    //   1079: iadd
    //   1080: istore_2
    //   1081: iload_2
    //   1082: sipush 128
    //   1085: irem
    //   1086: putstatic 51	o/Ir:ॱ	I
    //   1089: iload_2
    //   1090: iconst_2
    //   1091: irem
    //   1092: ifeq +6 -> 1098
    //   1095: goto +1648 -> 2743
    //   1098: goto -579 -> 519
    //   1101: aload 9
    //   1103: areturn
    //   1104: aload 8
    //   1106: aload 9
    //   1108: invokevirtual 776	java/lang/String:intern	()Ljava/lang/String;
    //   1111: invokestatic 959	o/vq:ˊ	(Ljava/lang/Object;Ljava/lang/Object;)Z
    //   1114: istore 6
    //   1116: bipush 92
    //   1118: iconst_0
    //   1119: idiv
    //   1120: istore_2
    //   1121: iload 6
    //   1123: ifne +6 -> 1129
    //   1126: goto +1053 -> 2179
    //   1129: goto +469 -> 1598
    //   1132: iconst_0
    //   1133: istore_2
    //   1134: goto +831 -> 1965
    //   1137: iload_2
    //   1138: tableswitch	default:+22->1160, 0:+-1059->79, 1:+-799->339
    //   1160: goto -821 -> 339
    //   1163: getstatic 51	o/Ir:ॱ	I
    //   1166: istore_2
    //   1167: iload_2
    //   1168: iconst_3
    //   1169: ior
    //   1170: iconst_1
    //   1171: ishl
    //   1172: iload_2
    //   1173: iconst_3
    //   1174: iand
    //   1175: iconst_m1
    //   1176: ixor
    //   1177: iload_2
    //   1178: iconst_3
    //   1179: ior
    //   1180: iand
    //   1181: isub
    //   1182: istore_2
    //   1183: iload_2
    //   1184: sipush 128
    //   1187: irem
    //   1188: putstatic 49	o/Ir:ˊ	I
    //   1191: iload_2
    //   1192: iconst_2
    //   1193: irem
    //   1194: ifne +6 -> 1200
    //   1197: goto -855 -> 342
    //   1200: goto +1171 -> 2371
    //   1203: goto +1518 -> 2721
    //   1206: aload 8
    //   1208: aload 9
    //   1210: invokevirtual 776	java/lang/String:intern	()Ljava/lang/String;
    //   1213: invokestatic 801	o/vq:ˋ	(Ljava/lang/Object;Ljava/lang/String;)V
    //   1216: aload 8
    //   1218: checkcast 962	java/lang/CharSequence
    //   1221: astore 8
    //   1223: bipush 79
    //   1225: istore_2
    //   1226: goto +1997 -> 3223
    //   1229: goto +19 -> 1248
    //   1232: invokestatic 804	o/vq:ˎ	()V
    //   1235: aconst_null
    //   1236: arraylength
    //   1237: istore_2
    //   1238: goto +1892 -> 3130
    //   1241: iconst_5
    //   1242: iconst_4
    //   1243: idiv
    //   1244: istore_2
    //   1245: goto +1771 -> 3016
    //   1248: aload 8
    //   1250: ifnull +6 -> 1256
    //   1253: goto +1774 -> 3027
    //   1256: goto -1097 -> 159
    //   1259: aload 8
    //   1261: aload 9
    //   1263: invokevirtual 776	java/lang/String:intern	()Ljava/lang/String;
    //   1266: invokestatic 959	o/vq:ˊ	(Ljava/lang/Object;Ljava/lang/Object;)Z
    //   1269: ifne +6 -> 1275
    //   1272: goto +544 -> 1816
    //   1275: goto -485 -> 790
    //   1278: sipush 11080
    //   1281: sipush 19299
    //   1284: bipush 65
    //   1286: invokestatic 772	o/Ir:ˏ	(ICI)Ljava/lang/String;
    //   1289: invokevirtual 776	java/lang/String:intern	()Ljava/lang/String;
    //   1292: astore 8
    //   1294: goto +1645 -> 2939
    //   1297: iload_2
    //   1298: lookupswitch	default:+26->1324, 70:+378->1676, 72:+1700->2998
    //   1324: goto +1674 -> 2998
    //   1327: getstatic 49	o/Ir:ˊ	I
    //   1330: istore_2
    //   1331: iload_2
    //   1332: bipush 80
    //   1334: ior
    //   1335: iload_2
    //   1336: bipush 80
    //   1338: iand
    //   1339: iadd
    //   1340: istore_2
    //   1341: iload_2
    //   1342: iconst_m1
    //   1343: ior
    //   1344: iconst_1
    //   1345: ishl
    //   1346: iload_2
    //   1347: iconst_m1
    //   1348: ixor
    //   1349: isub
    //   1350: istore_2
    //   1351: iload_2
    //   1352: sipush 128
    //   1355: irem
    //   1356: putstatic 51	o/Ir:ॱ	I
    //   1359: iload_2
    //   1360: iconst_2
    //   1361: irem
    //   1362: ifeq +6 -> 1368
    //   1365: goto -927 -> 438
    //   1368: goto +255 -> 1623
    //   1371: iload_2
    //   1372: tableswitch	default:+24->1396, 0:+1291->2663, 1:+-1113->259
    //   1396: goto -1137 -> 259
    //   1399: getstatic 49	o/Ir:ˊ	I
    //   1402: istore_3
    //   1403: iload_3
    //   1404: bipush -106
    //   1406: iand
    //   1407: iload_3
    //   1408: iconst_m1
    //   1409: ixor
    //   1410: bipush 105
    //   1412: iand
    //   1413: ior
    //   1414: istore_2
    //   1415: iload_3
    //   1416: bipush 105
    //   1418: iand
    //   1419: iconst_1
    //   1420: ishl
    //   1421: istore_3
    //   1422: iload_2
    //   1423: iload_3
    //   1424: ior
    //   1425: iconst_1
    //   1426: ishl
    //   1427: iload_2
    //   1428: iload_3
    //   1429: ixor
    //   1430: isub
    //   1431: istore_2
    //   1432: iload_2
    //   1433: sipush 128
    //   1436: irem
    //   1437: putstatic 51	o/Ir:ॱ	I
    //   1440: iload_2
    //   1441: iconst_2
    //   1442: irem
    //   1443: ifeq +6 -> 1449
    //   1446: goto -1372 -> 74
    //   1449: goto +1998 -> 3447
    //   1452: aload 12
    //   1454: invokevirtual 1035	o/xG:ˏ	()Lo/xG$if;
    //   1457: astore 9
    //   1459: aload 9
    //   1461: astore 8
    //   1463: bipush 107
    //   1465: ldc_w 1036
    //   1468: bipush 53
    //   1470: invokestatic 772	o/Ir:ˏ	(ICI)Ljava/lang/String;
    //   1473: astore 10
    //   1475: goto -715 -> 760
    //   1478: goto +561 -> 2039
    //   1481: goto -1286 -> 195
    //   1484: aload 11
    //   1486: invokevirtual 1055	o/xG$if:ˎ	()Lo/xG;
    //   1489: astore 12
    //   1491: aload 12
    //   1493: bipush 85
    //   1495: iconst_0
    //   1496: bipush 22
    //   1498: invokestatic 772	o/Ir:ˏ	(ICI)Ljava/lang/String;
    //   1501: invokevirtual 776	java/lang/String:intern	()Ljava/lang/String;
    //   1504: invokestatic 801	o/vq:ˋ	(Ljava/lang/Object;Ljava/lang/String;)V
    //   1507: goto +376 -> 1883
    //   1510: goto +1692 -> 3202
    //   1513: goto +1558 -> 3071
    //   1516: getstatic 49	o/Ir:ˊ	I
    //   1519: istore_2
    //   1520: iload_2
    //   1521: bipush 76
    //   1523: iand
    //   1524: iconst_1
    //   1525: ishl
    //   1526: iload_2
    //   1527: bipush 76
    //   1529: ixor
    //   1530: iadd
    //   1531: istore_2
    //   1532: iload_2
    //   1533: iconst_m1
    //   1534: ior
    //   1535: iconst_1
    //   1536: ishl
    //   1537: iload_2
    //   1538: iconst_m1
    //   1539: ixor
    //   1540: isub
    //   1541: istore_2
    //   1542: iload_2
    //   1543: sipush 128
    //   1546: irem
    //   1547: putstatic 51	o/Ir:ॱ	I
    //   1550: iload_2
    //   1551: iconst_2
    //   1552: irem
    //   1553: ifeq +6 -> 1559
    //   1556: goto +140 -> 1696
    //   1559: goto +669 -> 2228
    //   1562: iconst_1
    //   1563: istore_2
    //   1564: goto -1394 -> 170
    //   1567: iconst_1
    //   1568: istore_2
    //   1569: iload_2
    //   1570: tableswitch	default:+22->1592, 0:+-243->1327, 1:+-1254->316
    //   1592: goto -1276 -> 316
    //   1595: goto +1421 -> 3016
    //   1598: bipush 45
    //   1600: istore_2
    //   1601: goto +1014 -> 2615
    //   1604: aload 8
    //   1606: aload 9
    //   1608: iconst_0
    //   1609: iload_2
    //   1610: aconst_null
    //   1611: invokestatic 967	o/vT:ˊ	(Ljava/lang/CharSequence;Ljava/lang/CharSequence;ZILjava/lang/Object;)Z
    //   1614: ifeq +6 -> 1620
    //   1617: goto +966 -> 2583
    //   1620: goto +71 -> 1691
    //   1623: iconst_1
    //   1624: istore_2
    //   1625: goto +1749 -> 3374
    //   1628: iload_2
    //   1629: lookupswitch	default:+27->1656, 39:+-397->1232, 41:+491->2120
    //   1656: goto +464 -> 2120
    //   1659: aload 10
    //   1661: invokevirtual 1040	o/xJ:ʼ	()Lo/xJ$ˊ;
    //   1664: astore 8
    //   1666: aload 8
    //   1668: astore 9
    //   1670: aconst_null
    //   1671: arraylength
    //   1672: istore_2
    //   1673: goto -877 -> 796
    //   1676: bipush 28
    //   1678: ldc_w 1059
    //   1681: bipush 11
    //   1683: invokestatic 772	o/Ir:ˏ	(ICI)Ljava/lang/String;
    //   1686: astore 9
    //   1688: goto +723 -> 2411
    //   1691: iconst_0
    //   1692: istore_2
    //   1693: goto -1199 -> 494
    //   1696: bipush 37
    //   1698: istore_2
    //   1699: goto +852 -> 2551
    //   1702: astore_1
    //   1703: aload_1
    //   1704: athrow
    //   1705: bipush 58
    //   1707: istore_2
    //   1708: goto +812 -> 2520
    //   1711: getstatic 51	o/Ir:ॱ	I
    //   1714: istore_2
    //   1715: iload_2
    //   1716: bipush 39
    //   1718: ixor
    //   1719: iload_2
    //   1720: bipush 39
    //   1722: iand
    //   1723: iconst_1
    //   1724: ishl
    //   1725: iadd
    //   1726: istore_2
    //   1727: iload_2
    //   1728: sipush 128
    //   1731: irem
    //   1732: putstatic 49	o/Ir:ˊ	I
    //   1735: iload_2
    //   1736: iconst_2
    //   1737: irem
    //   1738: ifne +6 -> 1744
    //   1741: goto -1485 -> 256
    //   1744: goto -1518 -> 226
    //   1747: iconst_0
    //   1748: istore_2
    //   1749: goto -1579 -> 170
    //   1752: aconst_null
    //   1753: astore 9
    //   1755: goto +993 -> 2748
    //   1758: bipush 6
    //   1760: istore_2
    //   1761: goto -1082 -> 679
    //   1764: getstatic 51	o/Ir:ॱ	I
    //   1767: istore_3
    //   1768: iload_3
    //   1769: bipush 71
    //   1771: ior
    //   1772: iconst_1
    //   1773: ishl
    //   1774: istore_2
    //   1775: iload_3
    //   1776: bipush 71
    //   1778: iand
    //   1779: iconst_m1
    //   1780: ixor
    //   1781: iload_3
    //   1782: bipush 71
    //   1784: ior
    //   1785: iand
    //   1786: ineg
    //   1787: istore_3
    //   1788: iload_2
    //   1789: iload_3
    //   1790: iand
    //   1791: iload_2
    //   1792: iload_3
    //   1793: ior
    //   1794: iadd
    //   1795: istore_2
    //   1796: iload_2
    //   1797: sipush 128
    //   1800: irem
    //   1801: putstatic 49	o/Ir:ˊ	I
    //   1804: iload_2
    //   1805: iconst_2
    //   1806: irem
    //   1807: ifne +6 -> 1813
    //   1810: goto -607 -> 1203
    //   1813: goto +908 -> 2721
    //   1816: bipush 70
    //   1818: istore_2
    //   1819: goto -522 -> 1297
    //   1822: goto -574 -> 1248
    //   1825: iload_2
    //   1826: tableswitch	default:+22->1848, 0:+-231->1595, 1:+-585->1241
    //   1848: goto -253 -> 1595
    //   1851: iload_2
    //   1852: lookupswitch	default:+28->1880, 7:+-840->1012, 64:+1455->3307
    //   1880: goto +1427 -> 3307
    //   1883: getstatic 51	o/Ir:ॱ	I
    //   1886: istore_3
    //   1887: iload_3
    //   1888: iconst_1
    //   1889: ixor
    //   1890: iload_3
    //   1891: iconst_1
    //   1892: iand
    //   1893: ior
    //   1894: iconst_1
    //   1895: ishl
    //   1896: istore_2
    //   1897: iload_3
    //   1898: bipush -2
    //   1900: iand
    //   1901: iload_3
    //   1902: iconst_m1
    //   1903: ixor
    //   1904: iconst_1
    //   1905: iand
    //   1906: ior
    //   1907: ineg
    //   1908: istore_3
    //   1909: iload_2
    //   1910: iload_3
    //   1911: ior
    //   1912: iconst_1
    //   1913: ishl
    //   1914: iload_2
    //   1915: iload_3
    //   1916: ixor
    //   1917: isub
    //   1918: istore_2
    //   1919: iload_2
    //   1920: sipush 128
    //   1923: irem
    //   1924: putstatic 49	o/Ir:ˊ	I
    //   1927: iload_2
    //   1928: iconst_2
    //   1929: irem
    //   1930: ifne +6 -> 1936
    //   1933: goto -175 -> 1758
    //   1936: bipush 34
    //   1938: istore_2
    //   1939: goto -1260 -> 679
    //   1942: goto +1510 -> 3452
    //   1945: iload_2
    //   1946: iconst_0
    //   1947: bipush 25
    //   1949: invokestatic 772	o/Ir:ˏ	(ICI)Ljava/lang/String;
    //   1952: invokevirtual 776	java/lang/String:intern	()Ljava/lang/String;
    //   1955: checkcast 962	java/lang/CharSequence
    //   1958: astore 9
    //   1960: iconst_2
    //   1961: istore_2
    //   1962: goto -358 -> 1604
    //   1965: iload_2
    //   1966: tableswitch	default:+22->1988, 0:+-567->1399, 1:+148->2114
    //   1988: goto -589 -> 1399
    //   1991: new 726	java/lang/NullPointerException
    //   1994: dup
    //   1995: invokespecial 782	java/lang/NullPointerException:<init>	()V
    //   1998: athrow
    //   1999: bipush 28
    //   2001: istore_2
    //   2002: goto +1273 -> 3275
    //   2005: iconst_0
    //   2006: istore_2
    //   2007: goto -870 -> 1137
    //   2010: bipush 23
    //   2012: istore_2
    //   2013: goto -1570 -> 443
    //   2016: iconst_0
    //   2017: istore_2
    //   2018: goto -647 -> 1371
    //   2021: iconst_1
    //   2022: istore_2
    //   2023: goto -652 -> 1371
    //   2026: aload 8
    //   2028: invokevirtual 1019	o/xF:ˊ	()Ljava/io/InputStream;
    //   2031: astore 8
    //   2033: aconst_null
    //   2034: arraylength
    //   2035: istore_2
    //   2036: goto +633 -> 2669
    //   2039: aload_0
    //   2040: aload 8
    //   2042: sipush 203
    //   2045: iconst_0
    //   2046: bipush 12
    //   2048: invokestatic 772	o/Ir:ˏ	(ICI)Ljava/lang/String;
    //   2051: invokevirtual 776	java/lang/String:intern	()Ljava/lang/String;
    //   2054: invokevirtual 1064	o/xz:ˊ	(Ljava/lang/String;)Ljava/lang/String;
    //   2057: invokespecial 1066	o/Ir:ˎ	(Ljava/lang/String;)Z
    //   2060: istore 7
    //   2062: iload 7
    //   2064: ifne +6 -> 2070
    //   2067: goto +591 -> 2658
    //   2070: goto -503 -> 1567
    //   2073: iconst_1
    //   2074: istore_2
    //   2075: goto -110 -> 1965
    //   2078: getstatic 49	o/Ir:ˊ	I
    //   2081: istore_2
    //   2082: iload_2
    //   2083: bipush 81
    //   2085: ixor
    //   2086: iload_2
    //   2087: bipush 81
    //   2089: iand
    //   2090: iconst_1
    //   2091: ishl
    //   2092: iadd
    //   2093: istore_2
    //   2094: iload_2
    //   2095: sipush 128
    //   2098: irem
    //   2099: putstatic 51	o/Ir:ॱ	I
    //   2102: iload_2
    //   2103: iconst_2
    //   2104: irem
    //   2105: ifeq +6 -> 2111
    //   2108: goto +1235 -> 3343
    //   2111: goto -1740 -> 371
    //   2114: aconst_null
    //   2115: astore 8
    //   2117: goto -2083 -> 34
    //   2120: invokestatic 804	o/vq:ˎ	()V
    //   2123: goto +1007 -> 3130
    //   2126: getstatic 51	o/Ir:ॱ	I
    //   2129: istore_2
    //   2130: iload_2
    //   2131: bipush 7
    //   2133: ixor
    //   2134: iload_2
    //   2135: bipush 7
    //   2137: iand
    //   2138: ior
    //   2139: iconst_1
    //   2140: ishl
    //   2141: iload_2
    //   2142: iconst_m1
    //   2143: ixor
    //   2144: bipush 7
    //   2146: iand
    //   2147: iload_2
    //   2148: bipush -8
    //   2150: iand
    //   2151: ior
    //   2152: ineg
    //   2153: iconst_m1
    //   2154: ixor
    //   2155: isub
    //   2156: iconst_1
    //   2157: isub
    //   2158: istore_2
    //   2159: iload_2
    //   2160: sipush 128
    //   2163: irem
    //   2164: putstatic 49	o/Ir:ˊ	I
    //   2167: iload_2
    //   2168: iconst_2
    //   2169: irem
    //   2170: ifne +6 -> 2176
    //   2173: goto +479 -> 2652
    //   2176: goto -2012 -> 164
    //   2179: bipush 54
    //   2181: istore_2
    //   2182: goto +433 -> 2615
    //   2185: iload_2
    //   2186: tableswitch	default:+22->2208, 0:+-1085->1101, 1:+-195->1991
    //   2208: goto -217 -> 1991
    //   2211: aload 8
    //   2213: invokevirtual 931	o/xF:ˎ	()J
    //   2216: lstore 4
    //   2218: lload 4
    //   2220: invokestatic 934	java/lang/Long:valueOf	(J)Ljava/lang/Long;
    //   2223: astore 8
    //   2225: goto -1963 -> 262
    //   2228: bipush 8
    //   2230: istore_2
    //   2231: goto +320 -> 2551
    //   2234: getstatic 51	o/Ir:ॱ	I
    //   2237: istore_2
    //   2238: iload_2
    //   2239: bipush 103
    //   2241: iand
    //   2242: iload_2
    //   2243: bipush 103
    //   2245: ixor
    //   2246: iload_2
    //   2247: bipush 103
    //   2249: iand
    //   2250: ior
    //   2251: ineg
    //   2252: ineg
    //   2253: iconst_m1
    //   2254: ixor
    //   2255: isub
    //   2256: iconst_1
    //   2257: isub
    //   2258: istore_2
    //   2259: iload_2
    //   2260: sipush 128
    //   2263: irem
    //   2264: putstatic 49	o/Ir:ˊ	I
    //   2267: iload_2
    //   2268: iconst_2
    //   2269: irem
    //   2270: ifne +6 -> 2276
    //   2273: goto -760 -> 1513
    //   2276: goto +795 -> 3071
    //   2279: aload 9
    //   2281: aload 8
    //   2283: invokestatic 801	o/vq:ˋ	(Ljava/lang/Object;Ljava/lang/String;)V
    //   2286: goto +302 -> 2588
    //   2289: getstatic 49	o/Ir:ˊ	I
    //   2292: istore_3
    //   2293: iload_3
    //   2294: bipush 45
    //   2296: ixor
    //   2297: iload_3
    //   2298: bipush 45
    //   2300: iand
    //   2301: ior
    //   2302: iconst_1
    //   2303: ishl
    //   2304: istore_2
    //   2305: iload_3
    //   2306: bipush -46
    //   2308: iand
    //   2309: iload_3
    //   2310: iconst_m1
    //   2311: ixor
    //   2312: bipush 45
    //   2314: iand
    //   2315: ior
    //   2316: ineg
    //   2317: istore_3
    //   2318: iload_2
    //   2319: iload_3
    //   2320: iand
    //   2321: iload_2
    //   2322: iload_3
    //   2323: ior
    //   2324: iadd
    //   2325: istore_2
    //   2326: iload_2
    //   2327: sipush 128
    //   2330: irem
    //   2331: putstatic 51	o/Ir:ॱ	I
    //   2334: iload_2
    //   2335: iconst_2
    //   2336: irem
    //   2337: ifeq +6 -> 2343
    //   2340: goto +932 -> 3272
    //   2343: goto -1114 -> 1229
    //   2346: aload_1
    //   2347: invokeinterface 1068 1 0
    //   2352: astore 10
    //   2354: aload 10
    //   2356: invokevirtual 1035	o/xG:ˏ	()Lo/xG$if;
    //   2359: astore 11
    //   2361: aload 10
    //   2363: invokevirtual 1071	o/xG:ˋ	()Lo/xy;
    //   2366: astore 8
    //   2368: goto +713 -> 3081
    //   2371: aload 10
    //   2373: sipush 161
    //   2376: sipush 32360
    //   2379: bipush 42
    //   2381: invokestatic 772	o/Ir:ˏ	(ICI)Ljava/lang/String;
    //   2384: invokevirtual 776	java/lang/String:intern	()Ljava/lang/String;
    //   2387: invokestatic 801	o/vq:ˋ	(Ljava/lang/Object;Ljava/lang/String;)V
    //   2390: aload 10
    //   2392: invokevirtual 1075	o/xJ:ʽ	()Lo/xz;
    //   2395: astore 8
    //   2397: goto +449 -> 2846
    //   2400: bipush 41
    //   2402: istore_2
    //   2403: goto -775 -> 1628
    //   2406: iconst_0
    //   2407: istore_2
    //   2408: goto +503 -> 2911
    //   2411: getstatic 51	o/Ir:ॱ	I
    //   2414: istore_2
    //   2415: iload_2
    //   2416: bipush 13
    //   2418: iand
    //   2419: iconst_m1
    //   2420: ixor
    //   2421: iload_2
    //   2422: bipush 13
    //   2424: ior
    //   2425: iand
    //   2426: iload_2
    //   2427: bipush 13
    //   2429: iand
    //   2430: iconst_1
    //   2431: ishl
    //   2432: ineg
    //   2433: ineg
    //   2434: iconst_m1
    //   2435: ixor
    //   2436: isub
    //   2437: iconst_1
    //   2438: isub
    //   2439: istore_2
    //   2440: iload_2
    //   2441: sipush 128
    //   2444: irem
    //   2445: putstatic 49	o/Ir:ˊ	I
    //   2448: iload_2
    //   2449: iconst_2
    //   2450: irem
    //   2451: ifne +6 -> 2457
    //   2454: goto +550 -> 3004
    //   2457: goto +740 -> 3197
    //   2460: getstatic 51	o/Ir:ॱ	I
    //   2463: istore_3
    //   2464: iload_3
    //   2465: bipush 121
    //   2467: ixor
    //   2468: iload_3
    //   2469: bipush 121
    //   2471: iand
    //   2472: ior
    //   2473: iconst_1
    //   2474: ishl
    //   2475: istore_2
    //   2476: iload_3
    //   2477: bipush 121
    //   2479: ior
    //   2480: iload_3
    //   2481: bipush 121
    //   2483: iand
    //   2484: iconst_m1
    //   2485: ixor
    //   2486: iand
    //   2487: istore_3
    //   2488: iload_3
    //   2489: ineg
    //   2490: iload_2
    //   2491: ior
    //   2492: iconst_1
    //   2493: ishl
    //   2494: iload_2
    //   2495: iload_3
    //   2496: ineg
    //   2497: ixor
    //   2498: isub
    //   2499: istore_2
    //   2500: iload_2
    //   2501: sipush 128
    //   2504: irem
    //   2505: putstatic 49	o/Ir:ˊ	I
    //   2508: iload_2
    //   2509: iconst_2
    //   2510: irem
    //   2511: ifne +6 -> 2517
    //   2514: goto +158 -> 2672
    //   2517: goto +749 -> 3266
    //   2520: iload_2
    //   2521: lookupswitch	default:+27->2548, 39:+171->2692, 58:+361->2882
    //   2548: goto +144 -> 2692
    //   2551: iload_2
    //   2552: lookupswitch	default:+28->2580, 8:+-1042->1510, 37:+126->2678
    //   2580: goto +98 -> 2678
    //   2583: iconst_1
    //   2584: istore_2
    //   2585: goto -2091 -> 494
    //   2588: getstatic 51	o/Ir:ॱ	I
    //   2591: bipush 81
    //   2593: iadd
    //   2594: istore_2
    //   2595: iload_2
    //   2596: sipush 128
    //   2599: irem
    //   2600: putstatic 49	o/Ir:ˊ	I
    //   2603: iload_2
    //   2604: iconst_2
    //   2605: irem
    //   2606: ifne +6 -> 2612
    //   2609: goto -2606 -> 3
    //   2612: goto +69 -> 2681
    //   2615: iload_2
    //   2616: lookupswitch	default:+28->2644, 45:+382->2998, 54:+-940->1676
    //   2644: goto +354 -> 2998
    //   2647: iconst_0
    //   2648: istore_3
    //   2649: goto -2251 -> 398
    //   2652: bipush 7
    //   2654: istore_2
    //   2655: goto -804 -> 1851
    //   2658: iconst_0
    //   2659: istore_2
    //   2660: goto -1091 -> 1569
    //   2663: goto +539 -> 3202
    //   2666: goto +316 -> 2982
    //   2669: goto -2474 -> 195
    //   2672: bipush 48
    //   2674: istore_2
    //   2675: goto -2028 -> 647
    //   2678: goto +524 -> 3202
    //   2681: iconst_0
    //   2682: istore_2
    //   2683: goto -498 -> 2185
    //   2686: bipush 15
    //   2688: istore_2
    //   2689: goto +586 -> 3275
    //   2692: aload 11
    //   2694: bipush 71
    //   2696: iconst_0
    //   2697: bipush 14
    //   2699: invokestatic 772	o/Ir:ˏ	(ICI)Ljava/lang/String;
    //   2702: invokevirtual 776	java/lang/String:intern	()Ljava/lang/String;
    //   2705: invokestatic 801	o/vq:ˋ	(Ljava/lang/Object;Ljava/lang/String;)V
    //   2708: aload_0
    //   2709: aload 10
    //   2711: aload 11
    //   2713: iload 6
    //   2715: invokespecial 1077	o/Ir:ˋ	(Lo/xG;Lo/xG$if;Z)V
    //   2718: goto -1234 -> 1484
    //   2721: aload 8
    //   2723: sipush 230
    //   2726: sipush 19299
    //   2729: bipush 23
    //   2731: invokestatic 772	o/Ir:ˏ	(ICI)Ljava/lang/String;
    //   2734: invokevirtual 776	java/lang/String:intern	()Ljava/lang/String;
    //   2737: invokestatic 801	o/vq:ˋ	(Ljava/lang/Object;Ljava/lang/String;)V
    //   2740: goto +393 -> 3133
    //   2743: iconst_1
    //   2744: istore_2
    //   2745: goto +573 -> 3318
    //   2748: getstatic 51	o/Ir:ॱ	I
    //   2751: istore_2
    //   2752: iload_2
    //   2753: bipush 117
    //   2755: ior
    //   2756: iconst_1
    //   2757: ishl
    //   2758: iload_2
    //   2759: bipush 117
    //   2761: ixor
    //   2762: isub
    //   2763: istore_2
    //   2764: iload_2
    //   2765: sipush 128
    //   2768: irem
    //   2769: putstatic 49	o/Ir:ˊ	I
    //   2772: iload_2
    //   2773: iconst_2
    //   2774: irem
    //   2775: ifne +6 -> 2781
    //   2778: goto -1803 -> 975
    //   2781: goto -959 -> 1822
    //   2784: bipush 85
    //   2786: istore_2
    //   2787: goto -2172 -> 615
    //   2790: getstatic 49	o/Ir:ˊ	I
    //   2793: istore_3
    //   2794: iload_3
    //   2795: bipush 117
    //   2797: iand
    //   2798: iconst_m1
    //   2799: ixor
    //   2800: iload_3
    //   2801: bipush 117
    //   2803: ior
    //   2804: iand
    //   2805: istore_2
    //   2806: iload_3
    //   2807: bipush 117
    //   2809: iand
    //   2810: iconst_1
    //   2811: ishl
    //   2812: ineg
    //   2813: istore_3
    //   2814: iload_3
    //   2815: ineg
    //   2816: iload_2
    //   2817: ixor
    //   2818: iload_2
    //   2819: iload_3
    //   2820: ineg
    //   2821: iand
    //   2822: iconst_1
    //   2823: ishl
    //   2824: iadd
    //   2825: istore_2
    //   2826: iload_2
    //   2827: sipush 128
    //   2830: irem
    //   2831: putstatic 51	o/Ir:ॱ	I
    //   2834: iload_2
    //   2835: iconst_2
    //   2836: irem
    //   2837: ifeq +6 -> 2843
    //   2840: goto -2529 -> 311
    //   2843: goto -838 -> 2005
    //   2846: getstatic 49	o/Ir:ˊ	I
    //   2849: istore_2
    //   2850: iload_2
    //   2851: bipush 75
    //   2853: ixor
    //   2854: iload_2
    //   2855: bipush 75
    //   2857: iand
    //   2858: iconst_1
    //   2859: ishl
    //   2860: iadd
    //   2861: istore_2
    //   2862: iload_2
    //   2863: sipush 128
    //   2866: irem
    //   2867: putstatic 51	o/Ir:ॱ	I
    //   2870: iload_2
    //   2871: iconst_2
    //   2872: irem
    //   2873: ifeq +6 -> 2879
    //   2876: goto -1398 -> 1478
    //   2879: goto -840 -> 2039
    //   2882: aload 11
    //   2884: bipush 11
    //   2886: iconst_0
    //   2887: bipush 8
    //   2889: invokestatic 772	o/Ir:ˏ	(ICI)Ljava/lang/String;
    //   2892: invokevirtual 776	java/lang/String:intern	()Ljava/lang/String;
    //   2895: invokestatic 801	o/vq:ˋ	(Ljava/lang/Object;Ljava/lang/String;)V
    //   2898: aload_0
    //   2899: aload 10
    //   2901: aload 11
    //   2903: iload 6
    //   2905: invokespecial 1077	o/Ir:ˋ	(Lo/xG;Lo/xG$if;Z)V
    //   2908: goto -1424 -> 1484
    //   2911: iload_2
    //   2912: tableswitch	default:+24->2936, 0:+-1160->1752, 1:+-678->2234
    //   2936: goto -702 -> 2234
    //   2939: getstatic 49	o/Ir:ˊ	I
    //   2942: istore_2
    //   2943: iload_2
    //   2944: bipush 59
    //   2946: iand
    //   2947: iload_2
    //   2948: bipush 59
    //   2950: iand
    //   2951: iload_2
    //   2952: bipush 59
    //   2954: ixor
    //   2955: ior
    //   2956: iconst_m1
    //   2957: ixor
    //   2958: isub
    //   2959: iconst_1
    //   2960: isub
    //   2961: istore_2
    //   2962: iload_2
    //   2963: sipush 128
    //   2966: irem
    //   2967: putstatic 51	o/Ir:ॱ	I
    //   2970: iload_2
    //   2971: iconst_2
    //   2972: irem
    //   2973: ifeq +6 -> 2979
    //   2976: goto -1229 -> 1747
    //   2979: goto -1417 -> 1562
    //   2982: aload_1
    //   2983: iconst_0
    //   2984: iconst_0
    //   2985: iconst_5
    //   2986: invokestatic 772	o/Ir:ˏ	(ICI)Ljava/lang/String;
    //   2989: invokevirtual 776	java/lang/String:intern	()Ljava/lang/String;
    //   2992: invokestatic 1079	o/vq:ˎ	(Ljava/lang/Object;Ljava/lang/String;)V
    //   2995: goto -1946 -> 1049
    //   2998: iconst_1
    //   2999: istore 6
    //   3001: goto -1485 -> 1516
    //   3004: bipush 77
    //   3006: istore_2
    //   3007: goto -2922 -> 85
    //   3010: bipush 39
    //   3012: istore_2
    //   3013: goto -1385 -> 1628
    //   3016: aload 8
    //   3018: ifnonnull +6 -> 3024
    //   3021: goto -2676 -> 345
    //   3024: goto -1014 -> 2010
    //   3027: iconst_0
    //   3028: istore_2
    //   3029: goto -2051 -> 978
    //   3032: getstatic 51	o/Ir:ॱ	I
    //   3035: istore_2
    //   3036: iload_2
    //   3037: bipush 85
    //   3039: iand
    //   3040: iload_2
    //   3041: bipush 85
    //   3043: ior
    //   3044: iadd
    //   3045: istore_2
    //   3046: iload_2
    //   3047: sipush 128
    //   3050: irem
    //   3051: putstatic 49	o/Ir:ˊ	I
    //   3054: iload_2
    //   3055: iconst_2
    //   3056: irem
    //   3057: ifne +6 -> 3063
    //   3060: goto -374 -> 2686
    //   3063: goto -1064 -> 1999
    //   3066: iconst_1
    //   3067: istore_2
    //   3068: goto -1243 -> 1825
    //   3071: aload 8
    //   3073: invokevirtual 935	o/xF:ˏ	()Lo/xC;
    //   3076: astore 9
    //   3078: goto -789 -> 2289
    //   3081: aload 8
    //   3083: invokevirtual 1083	o/xy:ʼ	()Ljava/lang/String;
    //   3086: astore 8
    //   3088: iconst_5
    //   3089: iconst_0
    //   3090: bipush 23
    //   3092: invokestatic 772	o/Ir:ˏ	(ICI)Ljava/lang/String;
    //   3095: astore 9
    //   3097: goto -637 -> 2460
    //   3100: aload 8
    //   3102: invokevirtual 908	java/lang/Long:longValue	()J
    //   3105: lstore 4
    //   3107: aload 10
    //   3109: invokevirtual 903	o/xJ:ॱॱ	()Lo/xF;
    //   3112: astore 8
    //   3114: aload 8
    //   3116: ifnull +6 -> 3122
    //   3119: goto -1987 -> 1132
    //   3122: goto -1049 -> 2073
    //   3125: iconst_1
    //   3126: istore_3
    //   3127: goto -2729 -> 398
    //   3130: goto -30 -> 3100
    //   3133: getstatic 49	o/Ir:ˊ	I
    //   3136: istore_2
    //   3137: iload_2
    //   3138: bipush 121
    //   3140: ixor
    //   3141: iload_2
    //   3142: bipush 121
    //   3144: iand
    //   3145: ior
    //   3146: iconst_1
    //   3147: ishl
    //   3148: iload_2
    //   3149: bipush 121
    //   3151: iand
    //   3152: iconst_m1
    //   3153: ixor
    //   3154: iload_2
    //   3155: bipush 121
    //   3157: ior
    //   3158: iand
    //   3159: isub
    //   3160: istore_2
    //   3161: iload_2
    //   3162: sipush 128
    //   3165: irem
    //   3166: putstatic 51	o/Ir:ॱ	I
    //   3169: iload_2
    //   3170: iconst_2
    //   3171: irem
    //   3172: ifeq +6 -> 3178
    //   3175: aload 8
    //   3177: areturn
    //   3178: aload 8
    //   3180: areturn
    //   3181: aload 8
    //   3183: invokevirtual 1019	o/xF:ˊ	()Ljava/io/InputStream;
    //   3186: astore 8
    //   3188: goto -519 -> 2669
    //   3191: bipush 39
    //   3193: istore_2
    //   3194: goto -674 -> 2520
    //   3197: iconst_5
    //   3198: istore_2
    //   3199: goto -3114 -> 85
    //   3202: aload 10
    //   3204: bipush 64
    //   3206: sipush 23723
    //   3209: bipush 7
    //   3211: invokestatic 772	o/Ir:ˏ	(ICI)Ljava/lang/String;
    //   3214: invokevirtual 776	java/lang/String:intern	()Ljava/lang/String;
    //   3217: invokestatic 801	o/vq:ˋ	(Ljava/lang/Object;Ljava/lang/String;)V
    //   3220: goto -2696 -> 524
    //   3223: getstatic 51	o/Ir:ॱ	I
    //   3226: istore_3
    //   3227: iload_3
    //   3228: bipush 7
    //   3230: iand
    //   3231: iconst_m1
    //   3232: ixor
    //   3233: iload_3
    //   3234: bipush 7
    //   3236: ior
    //   3237: iand
    //   3238: iload_3
    //   3239: bipush 7
    //   3241: iand
    //   3242: iconst_1
    //   3243: ishl
    //   3244: iadd
    //   3245: istore_3
    //   3246: iload_3
    //   3247: sipush 128
    //   3250: irem
    //   3251: putstatic 49	o/Ir:ˊ	I
    //   3254: iload_3
    //   3255: iconst_2
    //   3256: irem
    //   3257: ifne +6 -> 3263
    //   3260: goto -613 -> 2647
    //   3263: goto -138 -> 3125
    //   3266: bipush 39
    //   3268: istore_2
    //   3269: goto -2622 -> 647
    //   3272: goto -2043 -> 1229
    //   3275: iload_2
    //   3276: lookupswitch	default:+28->3304, 15:+-1998->1278, 28:+-2801->475
    //   3304: goto -2829 -> 475
    //   3307: aload 8
    //   3309: ifnull +6 -> 3315
    //   3312: goto -3197 -> 115
    //   3315: goto -909 -> 2406
    //   3318: iload_2
    //   3319: tableswitch	default:+21->3340, 0:+-973->2346, 1:+27->3346
    //   3340: goto -994 -> 2346
    //   3343: goto -2972 -> 371
    //   3346: aload_1
    //   3347: invokeinterface 1068 1 0
    //   3352: astore 8
    //   3354: aload 8
    //   3356: invokevirtual 1035	o/xG:ˏ	()Lo/xG$if;
    //   3359: astore_1
    //   3360: aload 8
    //   3362: invokevirtual 1071	o/xG:ˋ	()Lo/xy;
    //   3365: astore_1
    //   3366: new 726	java/lang/NullPointerException
    //   3369: dup
    //   3370: invokespecial 782	java/lang/NullPointerException:<init>	()V
    //   3373: athrow
    //   3374: iload_2
    //   3375: tableswitch	default:+21->3396, 0:+-1716->1659, 1:+-3255->120
    //   3396: goto -3276 -> 120
    //   3399: getstatic 51	o/Ir:ॱ	I
    //   3402: istore_2
    //   3403: iload_2
    //   3404: bipush 73
    //   3406: ixor
    //   3407: iload_2
    //   3408: bipush 73
    //   3410: iand
    //   3411: ior
    //   3412: iconst_1
    //   3413: ishl
    //   3414: iload_2
    //   3415: bipush -74
    //   3417: iand
    //   3418: iload_2
    //   3419: iconst_m1
    //   3420: ixor
    //   3421: bipush 73
    //   3423: iand
    //   3424: ior
    //   3425: isub
    //   3426: istore_2
    //   3427: iload_2
    //   3428: sipush 128
    //   3431: irem
    //   3432: putstatic 49	o/Ir:ˊ	I
    //   3435: iload_2
    //   3436: iconst_2
    //   3437: irem
    //   3438: ifne +6 -> 3444
    //   3441: goto -1420 -> 2021
    //   3444: goto -1428 -> 2016
    //   3447: iconst_1
    //   3448: istore_2
    //   3449: goto -3315 -> 134
    //   3452: getstatic 51	o/Ir:ॱ	I
    //   3455: bipush 121
    //   3457: iadd
    //   3458: iconst_1
    //   3459: isub
    //   3460: istore_2
    //   3461: iload_2
    //   3462: iconst_m1
    //   3463: ior
    //   3464: iconst_1
    //   3465: ishl
    //   3466: iload_2
    //   3467: iconst_m1
    //   3468: ixor
    //   3469: isub
    //   3470: istore_2
    //   3471: iload_2
    //   3472: sipush 128
    //   3475: irem
    //   3476: putstatic 49	o/Ir:ˊ	I
    //   3479: iload_2
    //   3480: iconst_2
    //   3481: irem
    //   3482: ifne +6 -> 3488
    //   3485: goto -819 -> 2666
    //   3488: goto -506 -> 2982
    // Local variable table:
    //   start	length	slot	name	signature
    //   0	3491	0	this	Ir
    //   0	3491	1	paramIf	xx.if
    //   4	3478	2	i	int
    //   265	2992	3	j	int
    //   199	1	4	localObject1	Object
    //   2216	890	4	l	long
    //   383	2617	6	bool1	boolean
    //   2060	3	7	bool2	boolean
    //   17	3344	8	localObject2	Object
    //   13	768	9	localObject3	Object
    //   813	41	9	localException	Exception
    //   864	2232	9	localObject4	Object
    //   29	3174	10	localObject5	Object
    //   940	1962	11	localIf	xG.if
    //   8	1484	12	localObject6	Object
    // Exception table:
    //   from	to	target	type
    //   34	38	576	java/lang/ArrayStoreException
    //   54	62	576	java/lang/ArrayStoreException
    //   1351	1359	576	java/lang/ArrayStoreException
    //   1676	1688	576	java/lang/NullPointerException
    //   2234	2238	576	java/lang/NullPointerException
    //   2259	2267	576	java/lang/IndexOutOfBoundsException
    //   3133	3137	576	java/lang/IndexOutOfBoundsException
    //   8	15	813	java/lang/Exception
    //   19	31	813	java/lang/Exception
    //   120	127	813	java/lang/Exception
    //   195	223	813	java/lang/Exception
    //   226	253	813	java/lang/Exception
    //   316	330	813	java/lang/Exception
    //   371	395	813	java/lang/Exception
    //   423	438	813	java/lang/Exception
    //   475	491	813	java/lang/Exception
    //   760	787	813	java/lang/Exception
    //   796	810	813	java/lang/Exception
    //   1012	1015	813	java/lang/Exception
    //   1232	1238	813	java/lang/Exception
    //   1278	1294	813	java/lang/Exception
    //   1452	1459	813	java/lang/Exception
    //   1463	1475	813	java/lang/Exception
    //   1484	1507	813	java/lang/Exception
    //   1659	1666	813	java/lang/Exception
    //   1670	1673	813	java/lang/Exception
    //   2026	2036	813	java/lang/Exception
    //   2039	2062	813	java/lang/Exception
    //   2120	2123	813	java/lang/Exception
    //   2211	2218	813	java/lang/Exception
    //   2279	2286	813	java/lang/Exception
    //   2371	2397	813	java/lang/Exception
    //   2692	2718	813	java/lang/Exception
    //   2721	2740	813	java/lang/Exception
    //   2882	2908	813	java/lang/Exception
    //   3071	3078	813	java/lang/Exception
    //   3100	3114	813	java/lang/Exception
    //   3181	3188	813	java/lang/Exception
    //   3202	3220	813	java/lang/Exception
    //   886	939	869	finally
    //   54	62	1702	java/lang/NullPointerException
    //   1327	1331	1702	java/lang/UnsupportedOperationException
    //   1351	1359	1702	java/lang/UnsupportedOperationException
    //   3161	3169	1702	java/lang/IllegalArgumentException
  }
  
  public static final class if
  {
    private if() {}
  }
}
