package o;

import android.content.Context;
import android.content.DialogInterface.OnCancelListener;
import android.os.Bundle;

public abstract class IT<I extends Iu.iF>
  extends ae<I>
  implements Iu.if
{
  private static int ˊ = 1;
  private static int ˎ = 0;
  private static long ˏ = 6328652872850693477L;
  public IC ॱ;
  
  public IT() {}
  
  private static String ˏ(char[] paramArrayOfChar)
  {
    break label175;
    break label66;
    int i;
    if (i >= paramArrayOfChar.length) {
      break label188;
    }
    for (;;)
    {
      long l1 = paramArrayOfChar[i] & paramArrayOfChar[(i % 2)];
      long l2 = i * 4;
      try
      {
        l3 = ˏ;
        paramArrayOfChar[i] = ((char)(int)(l1 ^ l2 - l3));
        i += 42;
      }
      catch (Exception paramArrayOfChar)
      {
        long l3;
        throw paramArrayOfChar;
      }
      int j = 17;
      break label146;
      for (;;)
      {
        label66:
        break;
        l1 = paramArrayOfChar[i] ^ paramArrayOfChar[(i % 4)];
        l2 = i - 4;
        try
        {
          l3 = ˏ;
          paramArrayOfChar[i] = ((char)(int)(l1 ^ l2 * l3));
          i += 1;
        }
        catch (Exception paramArrayOfChar)
        {
          label110:
          throw paramArrayOfChar;
        }
        j = ˎ + 49;
        ˊ = j % 128;
        if (j % 2 == 0) {
          break;
        }
      }
      label146:
      label175:
      label188:
      do
      {
        j = 46;
        break label243;
        for (;;)
        {
          switch (j)
          {
          default: 
            break label226;
            paramArrayOfChar = oL.ˋ(ˏ, paramArrayOfChar);
            i = 4;
            break label110;
            j = 76;
          }
        }
        j = ˊ;
        j += 71;
        ˎ = j % 128;
      } while (j % 2 != 0);
      break label240;
      label226:
      return new String(paramArrayOfChar, 4, paramArrayOfChar.length - 4);
      label240:
      j = 68;
      label243:
      switch (j)
      {
      }
    }
  }
  
  public void A_()
  {
    break label66;
    int i;
    for (;;)
    {
      i = ˊ + 103;
      ˎ = i % 128;
      if (i % 2 == 0) {
        return;
      }
      return;
      ʻᐝ().A_();
    }
    label66:
    for (;;)
    {
      i = ˊ + 45;
      ˎ = i % 128;
      if (i % 2 != 0) {
        break;
      }
      break;
    }
  }
  
  /* Error */
  public void v_()
  {
    // Byte code:
    //   0: goto +98 -> 98
    //   3: iconst_1
    //   4: istore_1
    //   5: goto +33 -> 38
    //   8: astore_2
    //   9: aload_2
    //   10: athrow
    //   11: getstatic 18	o/IT:ˎ	I
    //   14: bipush 113
    //   16: iadd
    //   17: istore_1
    //   18: iload_1
    //   19: sipush 128
    //   22: irem
    //   23: putstatic 20	o/IT:ˊ	I
    //   26: iload_1
    //   27: iconst_2
    //   28: irem
    //   29: ifne +6 -> 35
    //   32: goto +61 -> 93
    //   35: goto -32 -> 3
    //   38: iload_1
    //   39: tableswitch	default:+21->60, 0:+39->78, 1:+27->66
    //   60: goto +6 -> 66
    //   63: astore_2
    //   64: aload_2
    //   65: athrow
    //   66: aload_0
    //   67: invokevirtual 47	o/IT:ʻᐝ	()Lo/IC;
    //   70: astore_2
    //   71: aload_2
    //   72: invokevirtual 54	o/IC:v_	()V
    //   75: goto +26 -> 101
    //   78: aload_0
    //   79: invokevirtual 47	o/IT:ʻᐝ	()Lo/IC;
    //   82: invokevirtual 54	o/IC:v_	()V
    //   85: new 56	java/lang/NullPointerException
    //   88: dup
    //   89: invokespecial 57	java/lang/NullPointerException:<init>	()V
    //   92: athrow
    //   93: iconst_0
    //   94: istore_1
    //   95: goto -57 -> 38
    //   98: goto -87 -> 11
    //   101: getstatic 20	o/IT:ˊ	I
    //   104: bipush 63
    //   106: iadd
    //   107: istore_1
    //   108: iload_1
    //   109: sipush 128
    //   112: irem
    //   113: putstatic 18	o/IT:ˎ	I
    //   116: iload_1
    //   117: iconst_2
    //   118: irem
    //   119: ifeq +4 -> 123
    //   122: return
    //   123: return
    // Local variable table:
    //   start	length	slot	name	signature
    //   0	124	0	this	IT
    //   4	115	1	i	int
    //   8	2	2	localException1	Exception
    //   63	2	2	localException2	Exception
    //   70	2	2	localIC	IC
    // Exception table:
    //   from	to	target	type
    //   71	75	8	java/lang/Exception
    //   66	71	63	java/lang/Exception
    //   71	75	63	java/lang/Exception
  }
  
  /* Error */
  public void w_()
  {
    // Byte code:
    //   0: goto +12 -> 12
    //   3: astore_2
    //   4: aload_2
    //   5: athrow
    //   6: bipush 16
    //   8: istore_1
    //   9: goto +76 -> 85
    //   12: getstatic 18	o/IT:ˎ	I
    //   15: bipush 115
    //   17: iadd
    //   18: istore_1
    //   19: iload_1
    //   20: sipush 128
    //   23: irem
    //   24: putstatic 20	o/IT:ˊ	I
    //   27: iload_1
    //   28: iconst_2
    //   29: irem
    //   30: ifne +6 -> 36
    //   33: goto +86 -> 119
    //   36: goto +39 -> 75
    //   39: bipush 97
    //   41: istore_1
    //   42: goto +43 -> 85
    //   45: return
    //   46: getstatic 20	o/IT:ˊ	I
    //   49: istore_1
    //   50: iload_1
    //   51: bipush 61
    //   53: iadd
    //   54: istore_1
    //   55: iload_1
    //   56: sipush 128
    //   59: irem
    //   60: putstatic 18	o/IT:ˎ	I
    //   63: iload_1
    //   64: iconst_2
    //   65: irem
    //   66: ifeq +6 -> 72
    //   69: goto -63 -> 6
    //   72: goto -33 -> 39
    //   75: aload_0
    //   76: invokevirtual 47	o/IT:ʻᐝ	()Lo/IC;
    //   79: invokevirtual 60	o/IC:w_	()V
    //   82: goto -36 -> 46
    //   85: iload_1
    //   86: lookupswitch	default:+26->112, 16:+27->113, 97:+-41->45
    //   112: return
    //   113: bipush 94
    //   115: iconst_0
    //   116: idiv
    //   117: istore_1
    //   118: return
    //   119: goto -44 -> 75
    // Local variable table:
    //   start	length	slot	name	signature
    //   0	122	0	this	IT
    //   8	110	1	i	int
    //   3	2	2	localException	Exception
    // Exception table:
    //   from	to	target	type
    //   46	50	3	java/lang/Exception
    //   55	63	3	java/lang/Exception
  }
  
  public void x_()
  {
    break label13;
    int i = 1;
    break label16;
    label8:
    i = 5;
    break label103;
    label13:
    break label150;
    label16:
    switch (i)
    {
    }
    for (;;)
    {
      try
      {
        IC localIC = ʻᐝ();
        try
        {
          localIC.x_();
        }
        catch (Exception localException1)
        {
          throw localException1;
        }
        i = 46;
      }
      catch (Exception localException2)
      {
        throw localException2;
      }
      i = 0;
      break label16;
      i = 16 / 0;
      return;
      return;
      i = ˎ + 115;
      ˊ = i % 128;
      if (i % 2 == 0) {
        break label8;
      }
      continue;
      label103:
      switch (i)
      {
      }
      continue;
      ʻᐝ().x_();
      i = 86 / 0;
      continue;
      label150:
      i = ˊ + 67;
      ˎ = i % 128;
      if (i % 2 != 0) {
        break;
      }
    }
  }
  
  public void y_()
  {
    break label9;
    label3:
    int i = 27;
    for (;;)
    {
      label9:
      switch (i)
      {
      default: 
        break;
      case 27: 
        ʻᐝ().y_();
        return;
        i = ˊ + 23;
        ˎ = i % 128;
        if (i % 2 == 0) {
          break label3;
        }
        i = 34;
      }
    }
    ʻᐝ().y_();
    i = null.length;
  }
  
  /* Error */
  public void z_()
  {
    // Byte code:
    //   0: goto +15 -> 15
    //   3: bipush 10
    //   5: istore_1
    //   6: goto +47 -> 53
    //   9: bipush 16
    //   11: istore_1
    //   12: goto +41 -> 53
    //   15: getstatic 18	o/IT:ˎ	I
    //   18: bipush 43
    //   20: iadd
    //   21: istore_1
    //   22: iload_1
    //   23: sipush 128
    //   26: irem
    //   27: putstatic 20	o/IT:ˊ	I
    //   30: iload_1
    //   31: iconst_2
    //   32: irem
    //   33: ifne +6 -> 39
    //   36: goto -27 -> 9
    //   39: goto -36 -> 3
    //   42: aload_0
    //   43: invokevirtual 47	o/IT:ʻᐝ	()Lo/IC;
    //   46: invokevirtual 69	o/IC:z_	()V
    //   49: return
    //   50: astore_2
    //   51: aload_2
    //   52: athrow
    //   53: iload_1
    //   54: lookupswitch	default:+26->80, 10:+-12->42, 16:+29->83
    //   80: goto -38 -> 42
    //   83: aload_0
    //   84: invokevirtual 47	o/IT:ʻᐝ	()Lo/IC;
    //   87: astore_2
    //   88: aload_2
    //   89: invokevirtual 69	o/IC:z_	()V
    //   92: bipush 15
    //   94: iconst_0
    //   95: idiv
    //   96: istore_1
    //   97: return
    // Local variable table:
    //   start	length	slot	name	signature
    //   0	98	0	this	IT
    //   5	92	1	i	int
    //   50	2	2	localException	Exception
    //   87	2	2	localIC	IC
    // Exception table:
    //   from	to	target	type
    //   83	88	50	java/lang/Exception
    //   88	97	50	java/lang/Exception
  }
  
  protected IC ʻᐝ()
  {
    break label326;
    int i = 1;
    for (;;)
    {
      vq.ˊ(ˏ(new char[] { -1123, -1040, 32261, 9014, 3149, -18706, 32135, 26061, -29058, -21320, -31019, -4056, 4304, 14063, 4989, 32420, -25788 }).intern());
      break label309;
      vq.ˊ(ˏ(new char[] { -1123, -1040, 32261, 9014, 3149, -18706, 32135, 26061, -29058, -21320, -31019, -4056, 4304, 14063, 4989, 32420, -25788 }).intern());
      throw new NullPointerException();
      label237:
      i = 1;
      break label357;
      label242:
      i = ˊ + 23;
      ˎ = i % 128;
      if (i % 2 == 0) {
        break label311;
      }
      label309:
      IC localIC;
      for (;;)
      {
        i = ˊ + 83;
        ˎ = i % 128;
        if (i % 2 == 0)
        {
          break label237;
          break label311;
        }
        i = 0;
        break label357;
        label311:
        do
        {
          i = 0;
          break;
          return localIC;
          localIC = this.ॱ;
        } while (localIC == null);
        break;
        label326:
        break label242;
        switch (i)
        {
        }
      }
      return localIC;
      label357:
      switch (i)
      {
      }
    }
  }
  
  public void ˎ(DialogInterface.OnCancelListener paramOnCancelListener)
  {
    break label152;
    for (;;)
    {
      i = ˊ + 53;
      ˎ = i % 128;
      if (i % 2 != 0) {
        break;
      }
      break label189;
      vq.ˎ(paramOnCancelListener, ˏ(new char[] { -30765, -30785, -8795, -32599, 28365, -11148, -7858, -1771, -3550, 3890, -7089, 27903 }).intern());
      ʻᐝ().ˎ(paramOnCancelListener);
    }
    label152:
    for (;;)
    {
      i = ˊ + 15;
      ˎ = i % 128;
      if (i % 2 != 0) {
        break;
      }
      break;
      return;
    }
    int i = 1;
    break label166;
    i = 53 / 0;
    return;
    for (;;)
    {
      label166:
      switch (i)
      {
      }
      return;
      label189:
      i = 0;
    }
  }
  
  /* Error */
  public void ˎ(Fd paramFd)
  {
    // Byte code:
    //   0: goto +42 -> 42
    //   3: iload_2
    //   4: tableswitch	default:+24->28, 0:+51->55, 1:+50->54
    //   28: goto +27 -> 55
    //   31: aload_0
    //   32: invokevirtual 47	o/IT:ʻᐝ	()Lo/IC;
    //   35: aload_1
    //   36: invokevirtual 124	o/IC:ˎ	(Lo/Fd;)V
    //   39: goto +57 -> 96
    //   42: goto +17 -> 59
    //   45: astore_1
    //   46: aload_1
    //   47: athrow
    //   48: goto -17 -> 31
    //   51: astore_1
    //   52: aload_1
    //   53: athrow
    //   54: return
    //   55: aconst_null
    //   56: arraylength
    //   57: istore_2
    //   58: return
    //   59: getstatic 18	o/IT:ˎ	I
    //   62: bipush 113
    //   64: iadd
    //   65: istore_2
    //   66: iload_2
    //   67: sipush 128
    //   70: irem
    //   71: putstatic 20	o/IT:ˊ	I
    //   74: iload_2
    //   75: iconst_2
    //   76: irem
    //   77: ifne +6 -> 83
    //   80: goto -32 -> 48
    //   83: goto -52 -> 31
    //   86: iconst_1
    //   87: istore_2
    //   88: goto -85 -> 3
    //   91: iconst_0
    //   92: istore_2
    //   93: goto -90 -> 3
    //   96: getstatic 18	o/IT:ˎ	I
    //   99: bipush 15
    //   101: iadd
    //   102: istore_2
    //   103: iload_2
    //   104: sipush 128
    //   107: irem
    //   108: putstatic 20	o/IT:ˊ	I
    //   111: iload_2
    //   112: iconst_2
    //   113: irem
    //   114: ifne +6 -> 120
    //   117: goto -26 -> 91
    //   120: goto -34 -> 86
    // Local variable table:
    //   start	length	slot	name	signature
    //   0	123	0	this	IT
    //   0	123	1	paramFd	Fd
    //   3	111	2	i	int
    // Exception table:
    //   from	to	target	type
    //   66	74	45	java/lang/Exception
    //   59	66	51	java/lang/Exception
    //   66	74	51	java/lang/Exception
  }
  
  /* Error */
  public void ˏ(String arg1)
  {
    // Byte code:
    //   0: goto +6 -> 6
    //   3: astore_1
    //   4: aload_1
    //   5: athrow
    //   6: goto +189 -> 195
    //   9: astore_1
    //   10: aload_1
    //   11: athrow
    //   12: bipush 95
    //   14: istore_2
    //   15: goto +381 -> 396
    //   18: bipush 28
    //   20: istore_2
    //   21: goto +375 -> 396
    //   24: bipush 25
    //   26: newarray char
    //   28: dup
    //   29: iconst_0
    //   30: ldc 125
    //   32: castore
    //   33: dup
    //   34: iconst_1
    //   35: ldc 126
    //   37: castore
    //   38: dup
    //   39: iconst_2
    //   40: ldc 127
    //   42: castore
    //   43: dup
    //   44: iconst_3
    //   45: ldc -128
    //   47: castore
    //   48: dup
    //   49: iconst_4
    //   50: ldc -127
    //   52: castore
    //   53: dup
    //   54: iconst_5
    //   55: ldc -126
    //   57: castore
    //   58: dup
    //   59: bipush 6
    //   61: ldc -125
    //   63: castore
    //   64: dup
    //   65: bipush 7
    //   67: ldc -124
    //   69: castore
    //   70: dup
    //   71: bipush 8
    //   73: ldc -123
    //   75: castore
    //   76: dup
    //   77: bipush 9
    //   79: ldc -122
    //   81: castore
    //   82: dup
    //   83: bipush 10
    //   85: ldc -121
    //   87: castore
    //   88: dup
    //   89: bipush 11
    //   91: ldc -120
    //   93: castore
    //   94: dup
    //   95: bipush 12
    //   97: ldc -119
    //   99: castore
    //   100: dup
    //   101: bipush 13
    //   103: ldc -118
    //   105: castore
    //   106: dup
    //   107: bipush 14
    //   109: ldc -117
    //   111: castore
    //   112: dup
    //   113: bipush 15
    //   115: ldc -116
    //   117: castore
    //   118: dup
    //   119: bipush 16
    //   121: ldc -115
    //   123: castore
    //   124: dup
    //   125: bipush 17
    //   127: ldc -114
    //   129: castore
    //   130: dup
    //   131: bipush 18
    //   133: ldc -113
    //   135: castore
    //   136: dup
    //   137: bipush 19
    //   139: ldc -112
    //   141: castore
    //   142: dup
    //   143: bipush 20
    //   145: ldc -111
    //   147: castore
    //   148: dup
    //   149: bipush 21
    //   151: ldc -110
    //   153: castore
    //   154: dup
    //   155: bipush 22
    //   157: ldc -109
    //   159: castore
    //   160: dup
    //   161: bipush 23
    //   163: ldc -108
    //   165: castore
    //   166: dup
    //   167: bipush 24
    //   169: ldc -107
    //   171: castore
    //   172: invokestatic 88	o/IT:ˏ	([C)Ljava/lang/String;
    //   175: astore_3
    //   176: aload_3
    //   177: invokevirtual 92	java/lang/String:intern	()Ljava/lang/String;
    //   180: astore_3
    //   181: aload_1
    //   182: aload_3
    //   183: invokestatic 119	o/vq:ˎ	(Ljava/lang/Object;Ljava/lang/String;)V
    //   186: aload_0
    //   187: invokevirtual 47	o/IT:ʻᐝ	()Lo/IC;
    //   190: aload_1
    //   191: invokevirtual 151	o/IC:ˏ	(Ljava/lang/String;)V
    //   194: return
    //   195: getstatic 20	o/IT:ˊ	I
    //   198: bipush 23
    //   200: iadd
    //   201: istore_2
    //   202: iload_2
    //   203: sipush 128
    //   206: irem
    //   207: putstatic 18	o/IT:ˎ	I
    //   210: iload_2
    //   211: iconst_2
    //   212: irem
    //   213: ifeq +6 -> 219
    //   216: goto -204 -> 12
    //   219: goto -201 -> 18
    //   222: aload_1
    //   223: bipush 25
    //   225: newarray char
    //   227: dup
    //   228: iconst_0
    //   229: ldc 125
    //   231: castore
    //   232: dup
    //   233: iconst_1
    //   234: ldc 126
    //   236: castore
    //   237: dup
    //   238: iconst_2
    //   239: ldc 127
    //   241: castore
    //   242: dup
    //   243: iconst_3
    //   244: ldc -128
    //   246: castore
    //   247: dup
    //   248: iconst_4
    //   249: ldc -127
    //   251: castore
    //   252: dup
    //   253: iconst_5
    //   254: ldc -126
    //   256: castore
    //   257: dup
    //   258: bipush 6
    //   260: ldc -125
    //   262: castore
    //   263: dup
    //   264: bipush 7
    //   266: ldc -124
    //   268: castore
    //   269: dup
    //   270: bipush 8
    //   272: ldc -123
    //   274: castore
    //   275: dup
    //   276: bipush 9
    //   278: ldc -122
    //   280: castore
    //   281: dup
    //   282: bipush 10
    //   284: ldc -121
    //   286: castore
    //   287: dup
    //   288: bipush 11
    //   290: ldc -120
    //   292: castore
    //   293: dup
    //   294: bipush 12
    //   296: ldc -119
    //   298: castore
    //   299: dup
    //   300: bipush 13
    //   302: ldc -118
    //   304: castore
    //   305: dup
    //   306: bipush 14
    //   308: ldc -117
    //   310: castore
    //   311: dup
    //   312: bipush 15
    //   314: ldc -116
    //   316: castore
    //   317: dup
    //   318: bipush 16
    //   320: ldc -115
    //   322: castore
    //   323: dup
    //   324: bipush 17
    //   326: ldc -114
    //   328: castore
    //   329: dup
    //   330: bipush 18
    //   332: ldc -113
    //   334: castore
    //   335: dup
    //   336: bipush 19
    //   338: ldc -112
    //   340: castore
    //   341: dup
    //   342: bipush 20
    //   344: ldc -111
    //   346: castore
    //   347: dup
    //   348: bipush 21
    //   350: ldc -110
    //   352: castore
    //   353: dup
    //   354: bipush 22
    //   356: ldc -109
    //   358: castore
    //   359: dup
    //   360: bipush 23
    //   362: ldc -108
    //   364: castore
    //   365: dup
    //   366: bipush 24
    //   368: ldc -107
    //   370: castore
    //   371: invokestatic 88	o/IT:ˏ	([C)Ljava/lang/String;
    //   374: invokevirtual 92	java/lang/String:intern	()Ljava/lang/String;
    //   377: invokestatic 119	o/vq:ˎ	(Ljava/lang/Object;Ljava/lang/String;)V
    //   380: aload_0
    //   381: invokevirtual 47	o/IT:ʻᐝ	()Lo/IC;
    //   384: aload_1
    //   385: invokevirtual 151	o/IC:ˏ	(Ljava/lang/String;)V
    //   388: new 56	java/lang/NullPointerException
    //   391: dup
    //   392: invokespecial 57	java/lang/NullPointerException:<init>	()V
    //   395: athrow
    //   396: iload_2
    //   397: lookupswitch	default:+27->424, 28:+-373->24, 95:+-175->222
    //   424: goto -400 -> 24
    // Exception table:
    //   from	to	target	type
    //   24	176	9	java/lang/Exception
    //   176	181	9	java/lang/Exception
    //   181	186	9	java/lang/Exception
    //   186	194	9	java/lang/Exception
  }
  
  public void ॱ(Bundle paramBundle)
  {
    for (;;)
    {
      super.ॱ(paramBundle);
      ॱ(new IC((Context)ͺ()));
      int i = ˎ + 123;
      ˊ = i % 128;
      if (i % 2 != 0) {}
      for (i = 97;; i = 18) {
        switch (i)
        {
        case 18: 
        default: 
          throw new NullPointerException();
        }
      }
    }
  }
  
  /* Error */
  public void ॱ(IC paramIC)
  {
    // Byte code:
    //   0: goto +83 -> 83
    //   3: aload_1
    //   4: bipush 11
    //   6: newarray char
    //   8: dup
    //   9: iconst_0
    //   10: ldc -89
    //   12: castore
    //   13: dup
    //   14: iconst_1
    //   15: ldc -88
    //   17: castore
    //   18: dup
    //   19: iconst_2
    //   20: ldc -87
    //   22: castore
    //   23: dup
    //   24: iconst_3
    //   25: ldc -86
    //   27: castore
    //   28: dup
    //   29: iconst_4
    //   30: ldc -85
    //   32: castore
    //   33: dup
    //   34: iconst_5
    //   35: ldc -84
    //   37: castore
    //   38: dup
    //   39: bipush 6
    //   41: ldc -83
    //   43: castore
    //   44: dup
    //   45: bipush 7
    //   47: ldc -82
    //   49: castore
    //   50: dup
    //   51: bipush 8
    //   53: ldc -81
    //   55: castore
    //   56: dup
    //   57: bipush 9
    //   59: ldc -80
    //   61: castore
    //   62: dup
    //   63: bipush 10
    //   65: ldc -79
    //   67: castore
    //   68: invokestatic 88	o/IT:ˏ	([C)Ljava/lang/String;
    //   71: invokevirtual 92	java/lang/String:intern	()Ljava/lang/String;
    //   74: invokestatic 119	o/vq:ˎ	(Ljava/lang/Object;Ljava/lang/String;)V
    //   77: aload_0
    //   78: aload_1
    //   79: putfield 99	o/IT:ॱ	Lo/IC;
    //   82: return
    //   83: goto +41 -> 124
    //   86: iload_2
    //   87: lookupswitch	default:+25->112, 20:+-84->3, 74:+73->160
    //   112: goto -109 -> 3
    //   115: bipush 20
    //   117: istore_2
    //   118: goto -32 -> 86
    //   121: astore_1
    //   122: aload_1
    //   123: athrow
    //   124: getstatic 18	o/IT:ˎ	I
    //   127: bipush 89
    //   129: iadd
    //   130: istore_2
    //   131: iload_2
    //   132: sipush 128
    //   135: irem
    //   136: putstatic 20	o/IT:ˊ	I
    //   139: iload_2
    //   140: iconst_2
    //   141: irem
    //   142: ifne +6 -> 148
    //   145: goto +6 -> 151
    //   148: goto -33 -> 115
    //   151: bipush 74
    //   153: istore_2
    //   154: goto -68 -> 86
    //   157: astore_1
    //   158: aload_1
    //   159: athrow
    //   160: aload_1
    //   161: bipush 11
    //   163: newarray char
    //   165: dup
    //   166: iconst_0
    //   167: ldc -89
    //   169: castore
    //   170: dup
    //   171: iconst_1
    //   172: ldc -88
    //   174: castore
    //   175: dup
    //   176: iconst_2
    //   177: ldc -87
    //   179: castore
    //   180: dup
    //   181: iconst_3
    //   182: ldc -86
    //   184: castore
    //   185: dup
    //   186: iconst_4
    //   187: ldc -85
    //   189: castore
    //   190: dup
    //   191: iconst_5
    //   192: ldc -84
    //   194: castore
    //   195: dup
    //   196: bipush 6
    //   198: ldc -83
    //   200: castore
    //   201: dup
    //   202: bipush 7
    //   204: ldc -82
    //   206: castore
    //   207: dup
    //   208: bipush 8
    //   210: ldc -81
    //   212: castore
    //   213: dup
    //   214: bipush 9
    //   216: ldc -80
    //   218: castore
    //   219: dup
    //   220: bipush 10
    //   222: ldc -79
    //   224: castore
    //   225: invokestatic 88	o/IT:ˏ	([C)Ljava/lang/String;
    //   228: invokevirtual 92	java/lang/String:intern	()Ljava/lang/String;
    //   231: invokestatic 119	o/vq:ˎ	(Ljava/lang/Object;Ljava/lang/String;)V
    //   234: aload_0
    //   235: aload_1
    //   236: putfield 99	o/IT:ॱ	Lo/IC;
    //   239: bipush 65
    //   241: iconst_0
    //   242: idiv
    //   243: istore_2
    //   244: return
    // Local variable table:
    //   start	length	slot	name	signature
    //   0	245	0	this	IT
    //   0	245	1	paramIC	IC
    //   86	158	2	i	int
    // Exception table:
    //   from	to	target	type
    //   124	131	121	java/lang/Exception
    //   131	139	121	java/lang/Exception
    //   131	139	157	java/lang/Exception
  }
}
