package o;

import android.content.Context;
import android.content.Intent;
import android.content.pm.ApplicationInfo;
import android.content.res.Resources;
import android.os.Bundle;

public class Iw
  extends IB<GJ>
{
  private static int ʼॱ = 1;
  private static long ʽॱ = -1245137927880536529L;
  private static int ʿ = 0;
  private static char[] ˈ = { 101, -29097, 7210, -21761, 14557, -14668, 21884, -7392, 28938, -44, -29278, 7258, -21929, 14348, -14596, 21671, -7527, 29037, -221, -29412, 7128, -22094, 14437, -14761, 21559, -7453, 28835, -371, -29360, -13425, 17853, -10304, 24853, -3273, 3422, -24957, 10438, -17679, 13346, 18002, -10357, 24961, -3094, 3351, -24763, 10620, -17764, 13526, 18170, -12249, 25157, -3191, 3516, -24596, 10530, -17576, 13690, 18102, -12083, -15472, 19874, -8225, 26890, -1240, 1345, -26981, 8404, -19740, 15392, 20039, -8273, 27042, -1031, 1289, -26798, 8556, -19816, 15574, 20201, -10195, 27207, -1136, 1442, -26686, 8470, -19626, 15736, 20133, 101, -29097, 7210, -21761, 14557, -14668, 21881, -7384, 28938, -61, -29303, 7286, -21929, 14347, -14601, 21676, -7531, 101, -29097, 7210, -21761, 14557, -14668, 21865, -7386, 28941, -43, -29259, 7264, -21909, 14338, -14607, 21685, -7527, 29033, -217, -29431, 7125, -15383, 19931, -8282, 26995, -1199, 1336, -26895, 8362, -19797, 15455, 20021, -8234, 27080, -1138, 1383, -26848, 8473, -19715, 15542, 20142, -10175, 27188, -1038, 1500, -26734, 8562, -19650, 15616, -20541, 8669, -19532, 1395, -26806, 26902, -1283, 71, -29120, 7294, -21767, 14547, -14645, 21866, -7384, 28929, -54, -29261, 7275, -21952, 14403, -14605, 21666, -7548, 29046, -200, -29420, 7128, -22110, 14378, -14761, 21511, -7456, 28906, -299, -29369, 6972, -22036, 14295, -14967, 21629, -7597, 28684, -280, -29534, 6805, -22201, 14200, -14860, 21461, -7785, 28785, -474, -29668, 6785, -22346, 13974, -15040, 21300, -7681, 28627, -625, -29571, 23102, -11252, 18033, -3932, 25222, -25361, 3872, -18078, 11091, -23133, -10246, 17983, -4068, 25191, -25440, 3828, -18188, 11046, -23180, -10427, 16796, -3097, 25123, -25587, 3654, -18270, 11001, 65, -29057, 7182, -21843, 14539, -14710, 21865, -7319, 28945, -55, -29194, 7271, -21931, 14336, -14599, 21670, -7550, 29040, -197, -29421, 7112, -22025, 14378, -14764, 21511, -7455, 28835, -299, -29363, 6951, -22110, 14291, -14975, 21612, -7595, 28749, -280, -29532, 6874, -22197, 14137, -14876, 21469, -7806, 28774, -468, -29689, 6863, -22348, 14047, -15011, 21300, -7710, 28632, -625, -29639, 6699, -22504, 14024, -15181, 21357, -7871, 28431, -528, -29772, 6534, -22415, 13859, -15268, 21190, -8001, 28538, -693, -29946, 6641, -22624, 13780, -15286, 21025, -8031, 28374, -842, -29856, 6484, -22753, 13811, -15441, 20893, -29300, 914, -28189, 10080, -19194, 19271, -10076, 28324, -805, 29189, 111, -28184, 10128, -19008, 19327, -9874, 28508, -847, 29416, 215, -27117, 9337, -19022, 19354, -9791, 28534, -725, 29522, 156, -26899, 9275, -17828, 18507, -9813, 28573, -567, 29474, 366, -26857, 9351, -17670, 18468, -8675, 27713, -597, 29667, 478, -26856, 9588, -17571, 18573, -8528, 27698, -7659, 28757, 433, -26656, 9684, -17589, 18799, -8544, 27786, -7481, 28796, 1663, -27577, 9632, -17419, 18909, -8430, 27959, -7509, 28830 };
  private boolean ʾ = false;
  
  public Iw() {}
  
  private void ʻॱ()
  {
    break label149;
    int i;
    for (;;)
    {
      i = ʼॱ + 33;
      ʿ = i % 128;
      if (i % 2 != 0) {
        break;
      }
      return;
      Ic.ˏ(this).ˋ(getIntent().getStringExtra(ˊ(getResources().getString(2131755640).substring(0, 4).codePointAt(2) + 94, (char)(getApplicationInfo().targetSdkVersion - 25), getResources().getString(2131755304).substring(0, 5).codePointAt(1) - 5).intern())).ॱ(335544320).ʼ().ˎ();
      finish();
    }
    label149:
    for (;;)
    {
      i = ʿ + 15;
      ʼॱ = i % 128;
      if (i % 2 == 0) {
        break;
      }
      break;
      return;
    }
  }
  
  /* Error */
  private void ʾ()
  {
    // Byte code:
    //   0: goto +39 -> 39
    //   3: iload_1
    //   4: lookupswitch	default:+28->32, 56:+65->69, 73:+98->102
    //   32: return
    //   33: goto +80 -> 113
    //   36: astore_2
    //   37: aload_2
    //   38: athrow
    //   39: goto +31 -> 70
    //   42: getstatic 24	o/Iw:ʼॱ	I
    //   45: bipush 115
    //   47: iadd
    //   48: istore_1
    //   49: iload_1
    //   50: sipush 128
    //   53: irem
    //   54: putstatic 22	o/Iw:ʿ	I
    //   57: iload_1
    //   58: iconst_2
    //   59: irem
    //   60: ifeq +6 -> 66
    //   63: goto +33 -> 96
    //   66: goto +72 -> 138
    //   69: return
    //   70: getstatic 24	o/Iw:ʼॱ	I
    //   73: iconst_3
    //   74: iadd
    //   75: istore_1
    //   76: iload_1
    //   77: sipush 128
    //   80: irem
    //   81: putstatic 22	o/Iw:ʿ	I
    //   84: iload_1
    //   85: iconst_2
    //   86: irem
    //   87: ifeq +6 -> 93
    //   90: goto -57 -> 33
    //   93: goto +20 -> 113
    //   96: bipush 73
    //   98: istore_1
    //   99: goto -96 -> 3
    //   102: new 504	java/lang/NullPointerException
    //   105: dup
    //   106: invokespecial 505	java/lang/NullPointerException:<init>	()V
    //   109: athrow
    //   110: astore_2
    //   111: aload_2
    //   112: athrow
    //   113: aload_0
    //   114: invokestatic 429	o/Ic:ˏ	(Landroid/content/Context;)Lo/Ic;
    //   117: iconst_0
    //   118: iconst_0
    //   119: invokevirtual 508	o/Ic:ˏ	(ZZ)Lo/j;
    //   122: ldc_w 485
    //   125: invokevirtual 491	o/j:ॱ	(I)Lo/j;
    //   128: invokevirtual 498	o/j:ˎ	()V
    //   131: aload_0
    //   132: invokevirtual 501	o/Iw:finish	()V
    //   135: goto -93 -> 42
    //   138: bipush 56
    //   140: istore_1
    //   141: goto -138 -> 3
    // Local variable table:
    //   start	length	slot	name	signature
    //   0	144	0	this	Iw
    //   3	138	1	i	int
    //   36	2	2	localException1	Exception
    //   110	2	2	localException2	Exception
    // Exception table:
    //   from	to	target	type
    //   76	84	36	java/lang/Exception
    //   70	76	110	java/lang/Exception
    //   76	84	110	java/lang/Exception
  }
  
  private static String ˊ(int paramInt1, char paramChar, int paramInt2)
  {
    break label281;
    label3:
    label33:
    int i;
    char[] arrayOfChar;
    for (;;)
    {
      j = ʿ + 87;
      ʼॱ = j % 128;
      if (j % 2 == 0) {
        break label275;
      }
      break label161;
      if (i < paramInt2) {
        break label171;
      }
      break;
      return new String(arrayOfChar);
      arrayOfChar[i] = ((char)(int)((ˈ[(paramInt1 << i)] + i * ʽॱ) % paramChar));
      i += 26;
    }
    int j = 41;
    break label204;
    for (;;)
    {
      switch (j)
      {
      case 95: 
      default: 
        break;
        j = 57;
        break;
      case 57: 
        label123:
        arrayOfChar[i] = ((char)(int)(ˈ[(paramInt1 + i)] ^ i * ʽॱ ^ paramChar));
        i += 1;
        break label3;
        label161:
        break label33;
        label164:
        j = 95;
      }
    }
    label171:
    j = 9;
    label204:
    label235:
    label275:
    label281:
    for (;;)
    {
      i = ʼॱ + 5;
      ʿ = i % 128;
      if (i % 2 == 0)
      {
        break label235;
        switch (j)
        {
        case 41: 
        default: 
          break;
        }
      }
      for (;;)
      {
        arrayOfChar = new char[paramInt2];
        i = 0;
        break;
        j = ʼॱ + 97;
        ʿ = j % 128;
        if (j % 2 != 0) {
          break label164;
        }
        break label123;
        break;
      }
    }
  }
  
  /* Error */
  private void ˊ(Intent paramIntent)
  {
    // Byte code:
    //   0: goto +322 -> 322
    //   3: aload_1
    //   4: aload_0
    //   5: invokevirtual 460	android/content/Context:getApplicationInfo	()Landroid/content/pm/ApplicationInfo;
    //   8: getfield 465	android/content/pm/ApplicationInfo:targetSdkVersion	I
    //   11: bipush 25
    //   13: isub
    //   14: aload_0
    //   15: invokevirtual 439	android/content/Context:getResources	()Landroid/content/res/Resources;
    //   18: ldc_w 513
    //   21: invokevirtual 446	android/content/res/Resources:getString	(I)Ljava/lang/String;
    //   24: iconst_0
    //   25: iconst_4
    //   26: invokevirtual 452	java/lang/String:substring	(II)Ljava/lang/String;
    //   29: invokevirtual 517	java/lang/String:length	()I
    //   32: iconst_4
    //   33: isub
    //   34: i2c
    //   35: aload_0
    //   36: invokevirtual 439	android/content/Context:getResources	()Landroid/content/res/Resources;
    //   39: ldc_w 518
    //   42: invokevirtual 446	android/content/res/Resources:getString	(I)Ljava/lang/String;
    //   45: iconst_0
    //   46: iconst_4
    //   47: invokevirtual 452	java/lang/String:substring	(II)Ljava/lang/String;
    //   50: iconst_1
    //   51: invokevirtual 456	java/lang/String:codePointAt	(I)I
    //   54: iconst_3
    //   55: iadd
    //   56: invokestatic 470	o/Iw:ˊ	(ICI)Ljava/lang/String;
    //   59: invokevirtual 474	java/lang/String:intern	()Ljava/lang/String;
    //   62: invokevirtual 480	android/content/Intent:getStringExtra	(Ljava/lang/String;)Ljava/lang/String;
    //   65: ifnonnull +6 -> 71
    //   68: goto +365 -> 433
    //   71: goto +472 -> 543
    //   74: aload_0
    //   75: getfield 422	o/Iw:ॱˊ	Landroid/databinding/ViewDataBinding;
    //   78: checkcast 520	o/GJ
    //   81: aload_1
    //   82: aload_0
    //   83: invokevirtual 439	android/content/Context:getResources	()Landroid/content/res/Resources;
    //   86: ldc_w 521
    //   89: invokevirtual 446	android/content/res/Resources:getString	(I)Ljava/lang/String;
    //   92: iconst_0
    //   93: iconst_4
    //   94: invokevirtual 452	java/lang/String:substring	(II)Ljava/lang/String;
    //   97: invokevirtual 517	java/lang/String:length	()I
    //   100: bipush 55
    //   102: iadd
    //   103: aload_0
    //   104: invokevirtual 439	android/content/Context:getResources	()Landroid/content/res/Resources;
    //   107: ldc_w 522
    //   110: invokevirtual 446	android/content/res/Resources:getString	(I)Ljava/lang/String;
    //   113: iconst_0
    //   114: iconst_4
    //   115: invokevirtual 452	java/lang/String:substring	(II)Ljava/lang/String;
    //   118: invokevirtual 517	java/lang/String:length	()I
    //   121: ldc_w 523
    //   124: iadd
    //   125: i2c
    //   126: aload_0
    //   127: invokevirtual 439	android/content/Context:getResources	()Landroid/content/res/Resources;
    //   130: ldc_w 524
    //   133: invokevirtual 446	android/content/res/Resources:getString	(I)Ljava/lang/String;
    //   136: iconst_3
    //   137: iconst_4
    //   138: invokevirtual 452	java/lang/String:substring	(II)Ljava/lang/String;
    //   141: iconst_0
    //   142: invokevirtual 456	java/lang/String:codePointAt	(I)I
    //   145: iconst_3
    //   146: isub
    //   147: invokestatic 470	o/Iw:ˊ	(ICI)Ljava/lang/String;
    //   150: invokevirtual 474	java/lang/String:intern	()Ljava/lang/String;
    //   153: invokevirtual 480	android/content/Intent:getStringExtra	(Ljava/lang/String;)Ljava/lang/String;
    //   156: invokevirtual 527	o/GJ:ˊ	(Ljava/lang/String;)V
    //   159: goto +332 -> 491
    //   162: iload_2
    //   163: tableswitch	default:+21->184, 0:+328->491, 1:+-89->74
    //   184: goto +307 -> 491
    //   187: iload_2
    //   188: tableswitch	default:+24->212, 0:+244->432, 1:+25->213
    //   212: return
    //   213: aload_0
    //   214: getfield 422	o/Iw:ॱˊ	Landroid/databinding/ViewDataBinding;
    //   217: checkcast 520	o/GJ
    //   220: aload_1
    //   221: aload_0
    //   222: invokevirtual 439	android/content/Context:getResources	()Landroid/content/res/Resources;
    //   225: ldc_w 528
    //   228: invokevirtual 446	android/content/res/Resources:getString	(I)Ljava/lang/String;
    //   231: iconst_0
    //   232: iconst_4
    //   233: invokevirtual 452	java/lang/String:substring	(II)Ljava/lang/String;
    //   236: iconst_3
    //   237: invokevirtual 456	java/lang/String:codePointAt	(I)I
    //   240: bipush 76
    //   242: iadd
    //   243: aload_0
    //   244: invokevirtual 460	android/content/Context:getApplicationInfo	()Landroid/content/pm/ApplicationInfo;
    //   247: getfield 465	android/content/pm/ApplicationInfo:targetSdkVersion	I
    //   250: bipush 25
    //   252: isub
    //   253: i2c
    //   254: aload_0
    //   255: invokevirtual 439	android/content/Context:getResources	()Landroid/content/res/Resources;
    //   258: ldc_w 529
    //   261: invokevirtual 446	android/content/res/Resources:getString	(I)Ljava/lang/String;
    //   264: iconst_0
    //   265: iconst_5
    //   266: invokevirtual 452	java/lang/String:substring	(II)Ljava/lang/String;
    //   269: invokevirtual 517	java/lang/String:length	()I
    //   272: bipush 12
    //   274: iadd
    //   275: invokestatic 470	o/Iw:ˊ	(ICI)Ljava/lang/String;
    //   278: invokevirtual 474	java/lang/String:intern	()Ljava/lang/String;
    //   281: invokevirtual 533	android/content/Intent:getSerializableExtra	(Ljava/lang/String;)Ljava/io/Serializable;
    //   284: checkcast 535	com/insidesecure/hce/MatrixHCEPaymentScheme
    //   287: invokevirtual 538	o/GJ:ˋ	(Lcom/insidesecure/hce/MatrixHCEPaymentScheme;)V
    //   290: getstatic 24	o/Iw:ʼॱ	I
    //   293: bipush 81
    //   295: iadd
    //   296: istore_2
    //   297: iload_2
    //   298: sipush 128
    //   301: irem
    //   302: putstatic 22	o/Iw:ʿ	I
    //   305: iload_2
    //   306: iconst_2
    //   307: irem
    //   308: ifeq +6 -> 314
    //   311: goto +19 -> 330
    //   314: goto +11 -> 325
    //   317: iconst_1
    //   318: istore_2
    //   319: goto -132 -> 187
    //   322: goto +504 -> 826
    //   325: iconst_1
    //   326: istore_2
    //   327: goto +124 -> 451
    //   330: iconst_0
    //   331: istore_2
    //   332: goto +119 -> 451
    //   335: astore_1
    //   336: aload_1
    //   337: athrow
    //   338: aload_0
    //   339: getfield 422	o/Iw:ॱˊ	Landroid/databinding/ViewDataBinding;
    //   342: checkcast 520	o/GJ
    //   345: aload_1
    //   346: aload_0
    //   347: invokevirtual 460	android/content/Context:getApplicationInfo	()Landroid/content/pm/ApplicationInfo;
    //   350: getfield 465	android/content/pm/ApplicationInfo:targetSdkVersion	I
    //   353: iconst_4
    //   354: iadd
    //   355: aload_0
    //   356: invokevirtual 439	android/content/Context:getResources	()Landroid/content/res/Resources;
    //   359: ldc_w 518
    //   362: invokevirtual 446	android/content/res/Resources:getString	(I)Ljava/lang/String;
    //   365: iconst_0
    //   366: iconst_4
    //   367: invokevirtual 452	java/lang/String:substring	(II)Ljava/lang/String;
    //   370: invokevirtual 517	java/lang/String:length	()I
    //   373: ldc_w 539
    //   376: iadd
    //   377: i2c
    //   378: aload_0
    //   379: invokevirtual 542	android/content/Context:getPackageName	()Ljava/lang/String;
    //   382: bipush 6
    //   384: invokevirtual 456	java/lang/String:codePointAt	(I)I
    //   387: bipush 78
    //   389: isub
    //   390: invokestatic 470	o/Iw:ˊ	(ICI)Ljava/lang/String;
    //   393: invokevirtual 474	java/lang/String:intern	()Ljava/lang/String;
    //   396: invokevirtual 480	android/content/Intent:getStringExtra	(Ljava/lang/String;)Ljava/lang/String;
    //   399: invokevirtual 544	o/GJ:ˏ	(Ljava/lang/String;)V
    //   402: goto +265 -> 667
    //   405: getstatic 24	o/Iw:ʼॱ	I
    //   408: bipush 7
    //   410: iadd
    //   411: istore_2
    //   412: iload_2
    //   413: sipush 128
    //   416: irem
    //   417: putstatic 22	o/Iw:ʿ	I
    //   420: iload_2
    //   421: iconst_2
    //   422: irem
    //   423: ifeq +6 -> 429
    //   426: goto +53 -> 479
    //   429: goto -426 -> 3
    //   432: return
    //   433: new 546	java/lang/IllegalArgumentException
    //   436: dup
    //   437: invokespecial 547	java/lang/IllegalArgumentException:<init>	()V
    //   440: athrow
    //   441: iconst_0
    //   442: istore_2
    //   443: goto -256 -> 187
    //   446: iconst_1
    //   447: istore_2
    //   448: goto -286 -> 162
    //   451: iload_2
    //   452: tableswitch	default:+24->476, 0:+35->487, 1:+-20->432
    //   476: goto -44 -> 432
    //   479: goto -476 -> 3
    //   482: iconst_0
    //   483: istore_2
    //   484: goto -322 -> 162
    //   487: return
    //   488: goto +263 -> 751
    //   491: aload_1
    //   492: aload_0
    //   493: invokevirtual 542	android/content/Context:getPackageName	()Ljava/lang/String;
    //   496: invokevirtual 517	java/lang/String:length	()I
    //   499: bipush 77
    //   501: iadd
    //   502: aload_0
    //   503: invokevirtual 542	android/content/Context:getPackageName	()Ljava/lang/String;
    //   506: bipush 8
    //   508: invokevirtual 456	java/lang/String:codePointAt	(I)I
    //   511: bipush 112
    //   513: isub
    //   514: i2c
    //   515: aload_0
    //   516: invokevirtual 460	android/content/Context:getApplicationInfo	()Landroid/content/pm/ApplicationInfo;
    //   519: getfield 465	android/content/pm/ApplicationInfo:targetSdkVersion	I
    //   522: bipush 8
    //   524: isub
    //   525: invokestatic 470	o/Iw:ˊ	(ICI)Ljava/lang/String;
    //   528: invokevirtual 474	java/lang/String:intern	()Ljava/lang/String;
    //   531: invokevirtual 551	android/content/Intent:hasExtra	(Ljava/lang/String;)Z
    //   534: ifeq +6 -> 540
    //   537: goto -220 -> 317
    //   540: goto -99 -> 441
    //   543: aload_0
    //   544: getfield 422	o/Iw:ॱˊ	Landroid/databinding/ViewDataBinding;
    //   547: checkcast 520	o/GJ
    //   550: aload_1
    //   551: aload_0
    //   552: invokevirtual 439	android/content/Context:getResources	()Landroid/content/res/Resources;
    //   555: ldc_w 552
    //   558: invokevirtual 446	android/content/res/Resources:getString	(I)Ljava/lang/String;
    //   561: bipush 33
    //   563: bipush 34
    //   565: invokevirtual 452	java/lang/String:substring	(II)Ljava/lang/String;
    //   568: invokevirtual 517	java/lang/String:length	()I
    //   571: iconst_1
    //   572: isub
    //   573: aload_0
    //   574: invokevirtual 542	android/content/Context:getPackageName	()Ljava/lang/String;
    //   577: invokevirtual 517	java/lang/String:length	()I
    //   580: bipush 11
    //   582: isub
    //   583: i2c
    //   584: aload_0
    //   585: invokevirtual 439	android/content/Context:getResources	()Landroid/content/res/Resources;
    //   588: ldc_w 553
    //   591: invokevirtual 446	android/content/res/Resources:getString	(I)Ljava/lang/String;
    //   594: iconst_0
    //   595: iconst_4
    //   596: invokevirtual 452	java/lang/String:substring	(II)Ljava/lang/String;
    //   599: iconst_0
    //   600: invokevirtual 456	java/lang/String:codePointAt	(I)I
    //   603: bipush 24
    //   605: iadd
    //   606: invokestatic 470	o/Iw:ˊ	(ICI)Ljava/lang/String;
    //   609: invokevirtual 474	java/lang/String:intern	()Ljava/lang/String;
    //   612: invokevirtual 480	android/content/Intent:getStringExtra	(Ljava/lang/String;)Ljava/lang/String;
    //   615: invokevirtual 555	o/GJ:ˎ	(Ljava/lang/String;)V
    //   618: aload_1
    //   619: aload_0
    //   620: invokevirtual 542	android/content/Context:getPackageName	()Ljava/lang/String;
    //   623: invokevirtual 517	java/lang/String:length	()I
    //   626: bipush 18
    //   628: iadd
    //   629: aload_0
    //   630: invokevirtual 460	android/content/Context:getApplicationInfo	()Landroid/content/pm/ApplicationInfo;
    //   633: getfield 465	android/content/pm/ApplicationInfo:targetSdkVersion	I
    //   636: ldc_w 556
    //   639: iadd
    //   640: i2c
    //   641: aload_0
    //   642: invokevirtual 542	android/content/Context:getPackageName	()Ljava/lang/String;
    //   645: iconst_0
    //   646: invokevirtual 456	java/lang/String:codePointAt	(I)I
    //   649: bipush 84
    //   651: isub
    //   652: invokestatic 470	o/Iw:ˊ	(ICI)Ljava/lang/String;
    //   655: invokevirtual 474	java/lang/String:intern	()Ljava/lang/String;
    //   658: invokevirtual 551	android/content/Intent:hasExtra	(Ljava/lang/String;)Z
    //   661: ifeq +6 -> 667
    //   664: goto -326 -> 338
    //   667: aload_0
    //   668: invokevirtual 439	android/content/Context:getResources	()Landroid/content/res/Resources;
    //   671: astore 4
    //   673: aload 4
    //   675: ldc_w 557
    //   678: invokevirtual 446	android/content/res/Resources:getString	(I)Ljava/lang/String;
    //   681: astore 4
    //   683: aload_1
    //   684: aload 4
    //   686: iconst_0
    //   687: iconst_4
    //   688: invokevirtual 452	java/lang/String:substring	(II)Ljava/lang/String;
    //   691: iconst_2
    //   692: invokevirtual 456	java/lang/String:codePointAt	(I)I
    //   695: bipush 48
    //   697: iadd
    //   698: aload_0
    //   699: invokevirtual 439	android/content/Context:getResources	()Landroid/content/res/Resources;
    //   702: ldc_w 558
    //   705: invokevirtual 446	android/content/res/Resources:getString	(I)Ljava/lang/String;
    //   708: iconst_0
    //   709: iconst_4
    //   710: invokevirtual 452	java/lang/String:substring	(II)Ljava/lang/String;
    //   713: iconst_0
    //   714: invokevirtual 456	java/lang/String:codePointAt	(I)I
    //   717: ldc_w 559
    //   720: iadd
    //   721: i2c
    //   722: aload_0
    //   723: invokevirtual 460	android/content/Context:getApplicationInfo	()Landroid/content/pm/ApplicationInfo;
    //   726: getfield 465	android/content/pm/ApplicationInfo:targetSdkVersion	I
    //   729: iconst_4
    //   730: iadd
    //   731: invokestatic 470	o/Iw:ˊ	(ICI)Ljava/lang/String;
    //   734: invokevirtual 474	java/lang/String:intern	()Ljava/lang/String;
    //   737: invokevirtual 551	android/content/Intent:hasExtra	(Ljava/lang/String;)Z
    //   740: istore_3
    //   741: iload_3
    //   742: ifeq +6 -> 748
    //   745: goto -299 -> 446
    //   748: goto -266 -> 482
    //   751: aload_1
    //   752: aload_0
    //   753: invokevirtual 439	android/content/Context:getResources	()Landroid/content/res/Resources;
    //   756: ldc_w 560
    //   759: invokevirtual 446	android/content/res/Resources:getString	(I)Ljava/lang/String;
    //   762: iconst_0
    //   763: bipush 10
    //   765: invokevirtual 452	java/lang/String:substring	(II)Ljava/lang/String;
    //   768: iconst_3
    //   769: invokevirtual 456	java/lang/String:codePointAt	(I)I
    //   772: bipush 12
    //   774: isub
    //   775: aload_0
    //   776: invokevirtual 439	android/content/Context:getResources	()Landroid/content/res/Resources;
    //   779: ldc_w 561
    //   782: invokevirtual 446	android/content/res/Resources:getString	(I)Ljava/lang/String;
    //   785: iconst_0
    //   786: iconst_5
    //   787: invokevirtual 452	java/lang/String:substring	(II)Ljava/lang/String;
    //   790: iconst_1
    //   791: invokevirtual 456	java/lang/String:codePointAt	(I)I
    //   794: bipush 26
    //   796: isub
    //   797: i2c
    //   798: aload_0
    //   799: invokevirtual 542	android/content/Context:getPackageName	()Ljava/lang/String;
    //   802: invokevirtual 517	java/lang/String:length	()I
    //   805: bipush 18
    //   807: iadd
    //   808: invokestatic 470	o/Iw:ˊ	(ICI)Ljava/lang/String;
    //   811: invokevirtual 474	java/lang/String:intern	()Ljava/lang/String;
    //   814: invokevirtual 551	android/content/Intent:hasExtra	(Ljava/lang/String;)Z
    //   817: ifeq +6 -> 823
    //   820: goto -415 -> 405
    //   823: goto -280 -> 543
    //   826: getstatic 22	o/Iw:ʿ	I
    //   829: bipush 7
    //   831: iadd
    //   832: istore_2
    //   833: iload_2
    //   834: sipush 128
    //   837: irem
    //   838: putstatic 24	o/Iw:ʼॱ	I
    //   841: iload_2
    //   842: iconst_2
    //   843: irem
    //   844: ifne +6 -> 850
    //   847: goto -359 -> 488
    //   850: goto -99 -> 751
    //   853: astore_1
    //   854: aload_1
    //   855: athrow
    // Local variable table:
    //   start	length	slot	name	signature
    //   0	856	0	this	Iw
    //   0	856	1	paramIntent	Intent
    //   162	682	2	i	int
    //   740	2	3	bool	boolean
    //   671	14	4	localObject	Object
    // Exception table:
    //   from	to	target	type
    //   667	673	335	java/lang/Exception
    //   673	683	335	java/lang/Exception
    //   683	741	335	java/lang/Exception
    //   673	683	853	java/lang/Exception
  }
  
  /* Error */
  private void ॱˋ()
  {
    // Byte code:
    //   0: goto +588 -> 588
    //   3: getstatic 24	o/Iw:ʼॱ	I
    //   6: bipush 47
    //   8: iadd
    //   9: istore_1
    //   10: iload_1
    //   11: sipush 128
    //   14: irem
    //   15: putstatic 22	o/Iw:ʿ	I
    //   18: iload_1
    //   19: iconst_2
    //   20: irem
    //   21: ifeq +6 -> 27
    //   24: goto +343 -> 367
    //   27: goto +340 -> 367
    //   30: aload_0
    //   31: invokevirtual 433	o/Iw:getIntent	()Landroid/content/Intent;
    //   34: aload_0
    //   35: invokevirtual 439	android/content/Context:getResources	()Landroid/content/res/Resources;
    //   38: ldc_w 570
    //   41: invokevirtual 446	android/content/res/Resources:getString	(I)Ljava/lang/String;
    //   44: iconst_0
    //   45: iconst_4
    //   46: invokevirtual 452	java/lang/String:substring	(II)Ljava/lang/String;
    //   49: iconst_1
    //   50: invokevirtual 456	java/lang/String:codePointAt	(I)I
    //   53: bipush 79
    //   55: iadd
    //   56: aload_0
    //   57: invokevirtual 439	android/content/Context:getResources	()Landroid/content/res/Resources;
    //   60: ldc_w 571
    //   63: invokevirtual 446	android/content/res/Resources:getString	(I)Ljava/lang/String;
    //   66: iconst_0
    //   67: iconst_5
    //   68: invokevirtual 452	java/lang/String:substring	(II)Ljava/lang/String;
    //   71: iconst_3
    //   72: invokevirtual 456	java/lang/String:codePointAt	(I)I
    //   75: bipush 12
    //   77: isub
    //   78: i2c
    //   79: aload_0
    //   80: invokevirtual 439	android/content/Context:getResources	()Landroid/content/res/Resources;
    //   83: ldc_w 572
    //   86: invokevirtual 446	android/content/res/Resources:getString	(I)Ljava/lang/String;
    //   89: iconst_0
    //   90: iconst_4
    //   91: invokevirtual 452	java/lang/String:substring	(II)Ljava/lang/String;
    //   94: iconst_1
    //   95: invokevirtual 456	java/lang/String:codePointAt	(I)I
    //   98: iconst_5
    //   99: isub
    //   100: invokestatic 470	o/Iw:ˊ	(ICI)Ljava/lang/String;
    //   103: invokevirtual 474	java/lang/String:intern	()Ljava/lang/String;
    //   106: invokevirtual 480	android/content/Intent:getStringExtra	(Ljava/lang/String;)Ljava/lang/String;
    //   109: invokestatic 578	android/text/TextUtils:isEmpty	(Ljava/lang/CharSequence;)Z
    //   112: ifne +6 -> 118
    //   115: goto +787 -> 902
    //   118: goto +566 -> 684
    //   121: astore_2
    //   122: aload_2
    //   123: athrow
    //   124: iconst_1
    //   125: istore_1
    //   126: goto +620 -> 746
    //   129: aload_0
    //   130: invokevirtual 542	android/content/Context:getPackageName	()Ljava/lang/String;
    //   133: bipush 8
    //   135: invokevirtual 456	java/lang/String:codePointAt	(I)I
    //   138: bipush 42
    //   140: iadd
    //   141: aload_0
    //   142: invokevirtual 542	android/content/Context:getPackageName	()Ljava/lang/String;
    //   145: bipush 6
    //   147: invokevirtual 456	java/lang/String:codePointAt	(I)I
    //   150: ldc_w 579
    //   153: iadd
    //   154: i2c
    //   155: aload_0
    //   156: invokevirtual 460	android/content/Context:getApplicationInfo	()Landroid/content/pm/ApplicationInfo;
    //   159: getfield 465	android/content/pm/ApplicationInfo:targetSdkVersion	I
    //   162: bipush 18
    //   164: isub
    //   165: invokestatic 470	o/Iw:ˊ	(ICI)Ljava/lang/String;
    //   168: invokevirtual 474	java/lang/String:intern	()Ljava/lang/String;
    //   171: astore_2
    //   172: aload_0
    //   173: invokevirtual 460	android/content/Context:getApplicationInfo	()Landroid/content/pm/ApplicationInfo;
    //   176: getfield 465	android/content/pm/ApplicationInfo:targetSdkVersion	I
    //   179: sipush 307
    //   182: iadd
    //   183: aload_0
    //   184: invokevirtual 460	android/content/Context:getApplicationInfo	()Landroid/content/pm/ApplicationInfo;
    //   187: getfield 465	android/content/pm/ApplicationInfo:targetSdkVersion	I
    //   190: ldc_w 580
    //   193: iadd
    //   194: i2c
    //   195: aload_0
    //   196: invokevirtual 542	android/content/Context:getPackageName	()Ljava/lang/String;
    //   199: invokevirtual 517	java/lang/String:length	()I
    //   202: bipush 62
    //   204: iadd
    //   205: invokestatic 470	o/Iw:ˊ	(ICI)Ljava/lang/String;
    //   208: invokevirtual 474	java/lang/String:intern	()Ljava/lang/String;
    //   211: astore_3
    //   212: goto +17 -> 229
    //   215: astore_2
    //   216: aload_2
    //   217: invokevirtual 586	java/lang/Throwable:getCause	()Ljava/lang/Throwable;
    //   220: astore_3
    //   221: aload_3
    //   222: ifnull +5 -> 227
    //   225: aload_3
    //   226: athrow
    //   227: aload_2
    //   228: athrow
    //   229: aload_0
    //   230: invokevirtual 439	android/content/Context:getResources	()Landroid/content/res/Resources;
    //   233: ldc_w 587
    //   236: invokevirtual 446	android/content/res/Resources:getString	(I)Ljava/lang/String;
    //   239: iconst_0
    //   240: iconst_4
    //   241: invokevirtual 452	java/lang/String:substring	(II)Ljava/lang/String;
    //   244: invokevirtual 517	java/lang/String:length	()I
    //   247: iconst_0
    //   248: iadd
    //   249: aload_0
    //   250: invokevirtual 542	android/content/Context:getPackageName	()Ljava/lang/String;
    //   253: invokevirtual 517	java/lang/String:length	()I
    //   256: bipush 31
    //   258: iadd
    //   259: aload_0
    //   260: invokevirtual 439	android/content/Context:getResources	()Landroid/content/res/Resources;
    //   263: ldc_w 588
    //   266: invokevirtual 446	android/content/res/Resources:getString	(I)Ljava/lang/String;
    //   269: iconst_0
    //   270: bipush 9
    //   272: invokevirtual 452	java/lang/String:substring	(II)Ljava/lang/String;
    //   275: iconst_3
    //   276: invokevirtual 456	java/lang/String:codePointAt	(I)I
    //   279: ldc_w 589
    //   282: iadd
    //   283: i2c
    //   284: invokestatic 594	o/O:ˋ	(IIC)Ljava/lang/Object;
    //   287: checkcast 596	java/lang/Class
    //   290: ldc_w 597
    //   293: iconst_2
    //   294: anewarray 596	java/lang/Class
    //   297: dup
    //   298: iconst_0
    //   299: ldc_w 448
    //   302: aastore
    //   303: dup
    //   304: iconst_1
    //   305: ldc_w 448
    //   308: aastore
    //   309: invokevirtual 601	java/lang/Class:getMethod	(Ljava/lang/String;[Ljava/lang/Class;)Ljava/lang/reflect/Method;
    //   312: aconst_null
    //   313: iconst_2
    //   314: anewarray 603	java/lang/Object
    //   317: dup
    //   318: iconst_0
    //   319: aload_2
    //   320: aastore
    //   321: dup
    //   322: iconst_1
    //   323: aload_3
    //   324: aastore
    //   325: invokevirtual 609	java/lang/reflect/Method:invoke	(Ljava/lang/Object;[Ljava/lang/Object;)Ljava/lang/Object;
    //   328: pop
    //   329: aload_0
    //   330: iconst_m1
    //   331: invokevirtual 612	o/Iw:ॱ	(I)V
    //   334: goto +355 -> 689
    //   337: goto +570 -> 907
    //   340: iload_1
    //   341: tableswitch	default:+23->364, 0:+493->834, 1:+240->581
    //   364: goto +470 -> 834
    //   367: aload_0
    //   368: invokevirtual 460	android/content/Context:getApplicationInfo	()Landroid/content/pm/ApplicationInfo;
    //   371: getfield 465	android/content/pm/ApplicationInfo:targetSdkVersion	I
    //   374: sipush 129
    //   377: iadd
    //   378: aload_0
    //   379: invokevirtual 460	android/content/Context:getApplicationInfo	()Landroid/content/pm/ApplicationInfo;
    //   382: getfield 465	android/content/pm/ApplicationInfo:targetSdkVersion	I
    //   385: ldc_w 613
    //   388: iadd
    //   389: i2c
    //   390: aload_0
    //   391: invokevirtual 439	android/content/Context:getResources	()Landroid/content/res/Resources;
    //   394: ldc_w 614
    //   397: invokevirtual 446	android/content/res/Resources:getString	(I)Ljava/lang/String;
    //   400: iconst_0
    //   401: iconst_5
    //   402: invokevirtual 452	java/lang/String:substring	(II)Ljava/lang/String;
    //   405: invokevirtual 517	java/lang/String:length	()I
    //   408: iconst_2
    //   409: iadd
    //   410: invokestatic 470	o/Iw:ˊ	(ICI)Ljava/lang/String;
    //   413: invokevirtual 474	java/lang/String:intern	()Ljava/lang/String;
    //   416: astore_2
    //   417: aload_0
    //   418: invokevirtual 460	android/content/Context:getApplicationInfo	()Landroid/content/pm/ApplicationInfo;
    //   421: getfield 465	android/content/pm/ApplicationInfo:targetSdkVersion	I
    //   424: sipush 219
    //   427: iadd
    //   428: aload_0
    //   429: invokevirtual 460	android/content/Context:getApplicationInfo	()Landroid/content/pm/ApplicationInfo;
    //   432: getfield 465	android/content/pm/ApplicationInfo:targetSdkVersion	I
    //   435: bipush 25
    //   437: isub
    //   438: i2c
    //   439: aload_0
    //   440: invokevirtual 460	android/content/Context:getApplicationInfo	()Landroid/content/pm/ApplicationInfo;
    //   443: getfield 465	android/content/pm/ApplicationInfo:targetSdkVersion	I
    //   446: bipush 63
    //   448: iadd
    //   449: invokestatic 470	o/Iw:ˊ	(ICI)Ljava/lang/String;
    //   452: invokevirtual 474	java/lang/String:intern	()Ljava/lang/String;
    //   455: astore_3
    //   456: goto +17 -> 473
    //   459: astore_2
    //   460: aload_2
    //   461: invokevirtual 586	java/lang/Throwable:getCause	()Ljava/lang/Throwable;
    //   464: astore_3
    //   465: aload_3
    //   466: ifnull +5 -> 471
    //   469: aload_3
    //   470: athrow
    //   471: aload_2
    //   472: athrow
    //   473: aload_0
    //   474: invokevirtual 460	android/content/Context:getApplicationInfo	()Landroid/content/pm/ApplicationInfo;
    //   477: getfield 465	android/content/pm/ApplicationInfo:targetSdkVersion	I
    //   480: bipush 21
    //   482: isub
    //   483: aload_0
    //   484: invokevirtual 439	android/content/Context:getResources	()Landroid/content/res/Resources;
    //   487: ldc_w 615
    //   490: invokevirtual 446	android/content/res/Resources:getString	(I)Ljava/lang/String;
    //   493: iconst_0
    //   494: iconst_4
    //   495: invokevirtual 452	java/lang/String:substring	(II)Ljava/lang/String;
    //   498: iconst_1
    //   499: invokevirtual 456	java/lang/String:codePointAt	(I)I
    //   502: bipush 16
    //   504: iadd
    //   505: aload_0
    //   506: invokevirtual 460	android/content/Context:getApplicationInfo	()Landroid/content/pm/ApplicationInfo;
    //   509: getfield 465	android/content/pm/ApplicationInfo:targetSdkVersion	I
    //   512: ldc_w 616
    //   515: iadd
    //   516: i2c
    //   517: invokestatic 594	o/O:ˋ	(IIC)Ljava/lang/Object;
    //   520: checkcast 596	java/lang/Class
    //   523: ldc_w 597
    //   526: iconst_2
    //   527: anewarray 596	java/lang/Class
    //   530: dup
    //   531: iconst_0
    //   532: ldc_w 448
    //   535: aastore
    //   536: dup
    //   537: iconst_1
    //   538: ldc_w 448
    //   541: aastore
    //   542: invokevirtual 601	java/lang/Class:getMethod	(Ljava/lang/String;[Ljava/lang/Class;)Ljava/lang/reflect/Method;
    //   545: aconst_null
    //   546: iconst_2
    //   547: anewarray 603	java/lang/Object
    //   550: dup
    //   551: iconst_0
    //   552: aload_2
    //   553: aastore
    //   554: dup
    //   555: iconst_1
    //   556: aload_3
    //   557: aastore
    //   558: invokevirtual 609	java/lang/reflect/Method:invoke	(Ljava/lang/Object;[Ljava/lang/Object;)Ljava/lang/Object;
    //   561: pop
    //   562: aload_0
    //   563: iconst_m1
    //   564: invokevirtual 612	o/Iw:ॱ	(I)V
    //   567: aload_0
    //   568: iconst_1
    //   569: invokevirtual 620	o/Iw:moveTaskToBack	(Z)Z
    //   572: pop
    //   573: goto +116 -> 689
    //   576: iconst_0
    //   577: istore_1
    //   578: goto +168 -> 746
    //   581: aload_0
    //   582: invokespecial 622	o/Iw:ʻॱ	()V
    //   585: goto +104 -> 689
    //   588: goto +183 -> 771
    //   591: aload_0
    //   592: invokevirtual 433	o/Iw:getIntent	()Landroid/content/Intent;
    //   595: aload_0
    //   596: invokevirtual 439	android/content/Context:getResources	()Landroid/content/res/Resources;
    //   599: ldc_w 623
    //   602: invokevirtual 446	android/content/res/Resources:getString	(I)Ljava/lang/String;
    //   605: iconst_0
    //   606: iconst_4
    //   607: invokevirtual 452	java/lang/String:substring	(II)Ljava/lang/String;
    //   610: invokevirtual 517	java/lang/String:length	()I
    //   613: bipush 122
    //   615: iadd
    //   616: aload_0
    //   617: invokevirtual 460	android/content/Context:getApplicationInfo	()Landroid/content/pm/ApplicationInfo;
    //   620: getfield 465	android/content/pm/ApplicationInfo:targetSdkVersion	I
    //   623: ldc_w 624
    //   626: iadd
    //   627: i2c
    //   628: aload_0
    //   629: invokevirtual 542	android/content/Context:getPackageName	()Ljava/lang/String;
    //   632: invokevirtual 517	java/lang/String:length	()I
    //   635: bipush 17
    //   637: iadd
    //   638: invokestatic 470	o/Iw:ˊ	(ICI)Ljava/lang/String;
    //   641: invokevirtual 474	java/lang/String:intern	()Ljava/lang/String;
    //   644: iconst_0
    //   645: invokevirtual 628	android/content/Intent:getBooleanExtra	(Ljava/lang/String;Z)Z
    //   648: ifeq +6 -> 654
    //   651: goto +6 -> 657
    //   654: goto +36 -> 690
    //   657: getstatic 24	o/Iw:ʼॱ	I
    //   660: bipush 11
    //   662: iadd
    //   663: istore_1
    //   664: iload_1
    //   665: sipush 128
    //   668: irem
    //   669: putstatic 22	o/Iw:ʿ	I
    //   672: iload_1
    //   673: iconst_2
    //   674: irem
    //   675: ifeq +6 -> 681
    //   678: goto -341 -> 337
    //   681: goto +226 -> 907
    //   684: iconst_0
    //   685: istore_1
    //   686: goto -346 -> 340
    //   689: return
    //   690: aload_0
    //   691: invokevirtual 433	o/Iw:getIntent	()Landroid/content/Intent;
    //   694: aload_0
    //   695: invokevirtual 460	android/content/Context:getApplicationInfo	()Landroid/content/pm/ApplicationInfo;
    //   698: getfield 465	android/content/pm/ApplicationInfo:targetSdkVersion	I
    //   701: sipush 192
    //   704: iadd
    //   705: aload_0
    //   706: invokevirtual 542	android/content/Context:getPackageName	()Ljava/lang/String;
    //   709: invokevirtual 517	java/lang/String:length	()I
    //   712: sipush 23120
    //   715: iadd
    //   716: i2c
    //   717: aload_0
    //   718: invokevirtual 542	android/content/Context:getPackageName	()Ljava/lang/String;
    //   721: invokevirtual 517	java/lang/String:length	()I
    //   724: bipush 16
    //   726: iadd
    //   727: invokestatic 470	o/Iw:ˊ	(ICI)Ljava/lang/String;
    //   730: invokevirtual 474	java/lang/String:intern	()Ljava/lang/String;
    //   733: iconst_0
    //   734: invokevirtual 628	android/content/Intent:getBooleanExtra	(Ljava/lang/String;Z)Z
    //   737: ifeq +6 -> 743
    //   740: goto -737 -> 3
    //   743: goto -614 -> 129
    //   746: iload_1
    //   747: tableswitch	default:+21->768, 0:+-717->30, 1:+87->834
    //   768: goto -738 -> 30
    //   771: aload_0
    //   772: invokevirtual 433	o/Iw:getIntent	()Landroid/content/Intent;
    //   775: aload_0
    //   776: invokevirtual 460	android/content/Context:getApplicationInfo	()Landroid/content/pm/ApplicationInfo;
    //   779: getfield 465	android/content/pm/ApplicationInfo:targetSdkVersion	I
    //   782: bipush 80
    //   784: iadd
    //   785: aload_0
    //   786: invokevirtual 439	android/content/Context:getResources	()Landroid/content/res/Resources;
    //   789: ldc_w 629
    //   792: invokevirtual 446	android/content/res/Resources:getString	(I)Ljava/lang/String;
    //   795: iconst_0
    //   796: iconst_5
    //   797: invokevirtual 452	java/lang/String:substring	(II)Ljava/lang/String;
    //   800: invokevirtual 517	java/lang/String:length	()I
    //   803: iconst_5
    //   804: isub
    //   805: i2c
    //   806: aload_0
    //   807: invokevirtual 542	android/content/Context:getPackageName	()Ljava/lang/String;
    //   810: invokevirtual 517	java/lang/String:length	()I
    //   813: bipush 10
    //   815: iadd
    //   816: invokestatic 470	o/Iw:ˊ	(ICI)Ljava/lang/String;
    //   819: invokevirtual 474	java/lang/String:intern	()Ljava/lang/String;
    //   822: invokevirtual 551	android/content/Intent:hasExtra	(Ljava/lang/String;)Z
    //   825: ifeq +6 -> 831
    //   828: goto -252 -> 576
    //   831: goto -707 -> 124
    //   834: aload_0
    //   835: invokevirtual 433	o/Iw:getIntent	()Landroid/content/Intent;
    //   838: aload_0
    //   839: invokevirtual 542	android/content/Context:getPackageName	()Ljava/lang/String;
    //   842: iconst_5
    //   843: invokevirtual 456	java/lang/String:codePointAt	(I)I
    //   846: bipush 12
    //   848: iadd
    //   849: aload_0
    //   850: invokevirtual 439	android/content/Context:getResources	()Landroid/content/res/Resources;
    //   853: ldc_w 630
    //   856: invokevirtual 446	android/content/res/Resources:getString	(I)Ljava/lang/String;
    //   859: iconst_0
    //   860: iconst_5
    //   861: invokevirtual 452	java/lang/String:substring	(II)Ljava/lang/String;
    //   864: iconst_1
    //   865: invokevirtual 456	java/lang/String:codePointAt	(I)I
    //   868: ldc_w 631
    //   871: iadd
    //   872: i2c
    //   873: aload_0
    //   874: invokevirtual 542	android/content/Context:getPackageName	()Ljava/lang/String;
    //   877: iconst_1
    //   878: invokevirtual 456	java/lang/String:codePointAt	(I)I
    //   881: bipush 83
    //   883: isub
    //   884: invokestatic 470	o/Iw:ˊ	(ICI)Ljava/lang/String;
    //   887: invokevirtual 474	java/lang/String:intern	()Ljava/lang/String;
    //   890: invokevirtual 551	android/content/Intent:hasExtra	(Ljava/lang/String;)Z
    //   893: ifeq +6 -> 899
    //   896: goto -305 -> 591
    //   899: goto -209 -> 690
    //   902: iconst_1
    //   903: istore_1
    //   904: goto -564 -> 340
    //   907: aload_0
    //   908: invokevirtual 460	android/content/Context:getApplicationInfo	()Landroid/content/pm/ApplicationInfo;
    //   911: getfield 465	android/content/pm/ApplicationInfo:targetSdkVersion	I
    //   914: sipush 129
    //   917: iadd
    //   918: aload_0
    //   919: invokevirtual 460	android/content/Context:getApplicationInfo	()Landroid/content/pm/ApplicationInfo;
    //   922: getfield 465	android/content/pm/ApplicationInfo:targetSdkVersion	I
    //   925: ldc_w 613
    //   928: iadd
    //   929: i2c
    //   930: aload_0
    //   931: invokevirtual 439	android/content/Context:getResources	()Landroid/content/res/Resources;
    //   934: ldc_w 632
    //   937: invokevirtual 446	android/content/res/Resources:getString	(I)Ljava/lang/String;
    //   940: iconst_0
    //   941: iconst_4
    //   942: invokevirtual 452	java/lang/String:substring	(II)Ljava/lang/String;
    //   945: invokevirtual 517	java/lang/String:length	()I
    //   948: iconst_3
    //   949: iadd
    //   950: invokestatic 470	o/Iw:ˊ	(ICI)Ljava/lang/String;
    //   953: invokevirtual 474	java/lang/String:intern	()Ljava/lang/String;
    //   956: astore_2
    //   957: aload_0
    //   958: invokevirtual 542	android/content/Context:getPackageName	()Ljava/lang/String;
    //   961: invokevirtual 517	java/lang/String:length	()I
    //   964: sipush 150
    //   967: iadd
    //   968: aload_0
    //   969: invokevirtual 542	android/content/Context:getPackageName	()Ljava/lang/String;
    //   972: invokevirtual 517	java/lang/String:length	()I
    //   975: bipush 11
    //   977: isub
    //   978: i2c
    //   979: aload_0
    //   980: invokevirtual 439	android/content/Context:getResources	()Landroid/content/res/Resources;
    //   983: ldc_w 633
    //   986: invokevirtual 446	android/content/res/Resources:getString	(I)Ljava/lang/String;
    //   989: iconst_0
    //   990: bipush 9
    //   992: invokevirtual 452	java/lang/String:substring	(II)Ljava/lang/String;
    //   995: iconst_1
    //   996: invokevirtual 456	java/lang/String:codePointAt	(I)I
    //   999: bipush 30
    //   1001: iadd
    //   1002: invokestatic 470	o/Iw:ˊ	(ICI)Ljava/lang/String;
    //   1005: invokevirtual 474	java/lang/String:intern	()Ljava/lang/String;
    //   1008: astore_3
    //   1009: goto +17 -> 1026
    //   1012: astore_2
    //   1013: aload_2
    //   1014: invokevirtual 586	java/lang/Throwable:getCause	()Ljava/lang/Throwable;
    //   1017: astore_3
    //   1018: aload_3
    //   1019: ifnull +5 -> 1024
    //   1022: aload_3
    //   1023: athrow
    //   1024: aload_2
    //   1025: athrow
    //   1026: aload_0
    //   1027: invokevirtual 542	android/content/Context:getPackageName	()Ljava/lang/String;
    //   1030: invokevirtual 517	java/lang/String:length	()I
    //   1033: bipush 7
    //   1035: isub
    //   1036: aload_0
    //   1037: invokevirtual 460	android/content/Context:getApplicationInfo	()Landroid/content/pm/ApplicationInfo;
    //   1040: getfield 465	android/content/pm/ApplicationInfo:targetSdkVersion	I
    //   1043: bipush 17
    //   1045: iadd
    //   1046: aload_0
    //   1047: invokevirtual 542	android/content/Context:getPackageName	()Ljava/lang/String;
    //   1050: invokevirtual 517	java/lang/String:length	()I
    //   1053: ldc_w 634
    //   1056: iadd
    //   1057: i2c
    //   1058: invokestatic 594	o/O:ˋ	(IIC)Ljava/lang/Object;
    //   1061: checkcast 596	java/lang/Class
    //   1064: ldc_w 597
    //   1067: iconst_2
    //   1068: anewarray 596	java/lang/Class
    //   1071: dup
    //   1072: iconst_0
    //   1073: ldc_w 448
    //   1076: aastore
    //   1077: dup
    //   1078: iconst_1
    //   1079: ldc_w 448
    //   1082: aastore
    //   1083: invokevirtual 601	java/lang/Class:getMethod	(Ljava/lang/String;[Ljava/lang/Class;)Ljava/lang/reflect/Method;
    //   1086: aconst_null
    //   1087: iconst_2
    //   1088: anewarray 603	java/lang/Object
    //   1091: dup
    //   1092: iconst_0
    //   1093: aload_2
    //   1094: aastore
    //   1095: dup
    //   1096: iconst_1
    //   1097: aload_3
    //   1098: aastore
    //   1099: invokevirtual 609	java/lang/reflect/Method:invoke	(Ljava/lang/Object;[Ljava/lang/Object;)Ljava/lang/Object;
    //   1102: pop
    //   1103: aload_0
    //   1104: invokespecial 636	o/Iw:ʾ	()V
    //   1107: return
    //   1108: astore_2
    //   1109: aload_2
    //   1110: athrow
    // Local variable table:
    //   start	length	slot	name	signature
    //   0	1111	0	this	Iw
    //   9	895	1	i	int
    //   121	2	2	localException1	Exception
    //   171	1	2	str1	String
    //   215	105	2	localObject1	Object
    //   416	1	2	str2	String
    //   459	94	2	localObject2	Object
    //   956	1	2	str3	String
    //   1012	82	2	localObject3	Object
    //   1108	2	2	localException2	Exception
    //   211	887	3	localObject4	Object
    // Exception table:
    //   from	to	target	type
    //   657	664	121	java/lang/Exception
    //   664	672	121	java/lang/Exception
    //   229	329	215	finally
    //   473	562	459	finally
    //   1026	1103	1012	finally
    //   664	672	1108	java/lang/Exception
  }
  
  /* Error */
  public Resources getResources()
  {
    // Byte code:
    //   0: goto +131 -> 131
    //   3: astore_2
    //   4: aload_2
    //   5: athrow
    //   6: bipush 83
    //   8: istore_1
    //   9: goto +11 -> 20
    //   12: new 504	java/lang/NullPointerException
    //   15: dup
    //   16: invokespecial 505	java/lang/NullPointerException:<init>	()V
    //   19: athrow
    //   20: iload_1
    //   21: lookupswitch	default:+27->48, 83:+30->51, 94:+73->94
    //   48: goto +46 -> 94
    //   51: aload_0
    //   52: invokespecial 639	o/IB:getResources	()Landroid/content/res/Resources;
    //   55: invokestatic 644	o/oH:ˊ	(Landroid/content/res/Resources;)Landroid/content/res/Resources;
    //   58: astore_2
    //   59: aconst_null
    //   60: arraylength
    //   61: istore_1
    //   62: goto +40 -> 102
    //   65: iload_1
    //   66: lookupswitch	default:+26->92, 13:+63->129, 20:+-54->12
    //   92: aload_2
    //   93: areturn
    //   94: aload_0
    //   95: invokespecial 639	o/IB:getResources	()Landroid/content/res/Resources;
    //   98: invokestatic 644	o/oH:ˊ	(Landroid/content/res/Resources;)Landroid/content/res/Resources;
    //   101: astore_2
    //   102: getstatic 24	o/Iw:ʼॱ	I
    //   105: bipush 119
    //   107: iadd
    //   108: istore_1
    //   109: iload_1
    //   110: sipush 128
    //   113: irem
    //   114: putstatic 22	o/Iw:ʿ	I
    //   117: iload_1
    //   118: iconst_2
    //   119: irem
    //   120: ifeq +6 -> 126
    //   123: goto +11 -> 134
    //   126: goto +14 -> 140
    //   129: aload_2
    //   130: areturn
    //   131: goto +21 -> 152
    //   134: bipush 20
    //   136: istore_1
    //   137: goto -72 -> 65
    //   140: bipush 13
    //   142: istore_1
    //   143: goto -78 -> 65
    //   146: bipush 94
    //   148: istore_1
    //   149: goto -129 -> 20
    //   152: getstatic 22	o/Iw:ʿ	I
    //   155: bipush 39
    //   157: iadd
    //   158: istore_1
    //   159: iload_1
    //   160: sipush 128
    //   163: irem
    //   164: putstatic 24	o/Iw:ʼॱ	I
    //   167: iload_1
    //   168: iconst_2
    //   169: irem
    //   170: ifne +6 -> 176
    //   173: goto -167 -> 6
    //   176: goto -30 -> 146
    // Local variable table:
    //   start	length	slot	name	signature
    //   0	179	0	this	Iw
    //   8	162	1	i	int
    //   3	2	2	localException	Exception
    //   58	72	2	localResources	Resources
    // Exception table:
    //   from	to	target	type
    //   102	109	3	java/lang/Exception
    //   109	117	3	java/lang/Exception
  }
  
  public void onCreate(Bundle paramBundle)
  {
    break label91;
    int i;
    switch (i)
    {
    default: 
      break;
    }
    for (;;)
    {
      try
      {
        i = ʿ;
        i += 31;
        ʼॱ = i % 128;
        if (i % 2 == 0) {
          break label152;
        }
        i = 0;
      }
      catch (Exception paramBundle)
      {
        throw paramBundle;
      }
      i = 46 / 0;
      return;
      super.onCreate(paramBundle);
      ˊ(getIntent());
      continue;
      label91:
      do
      {
        i = 58;
        break;
        i = ʿ + 89;
        ʼॱ = i % 128;
      } while (i % 2 == 0);
      break label146;
      super.onCreate(paramBundle);
      ˊ(getIntent());
      i = null.length;
      continue;
      label146:
      i = 86;
      break;
      label152:
      i = 1;
      switch (i)
      {
      }
    }
  }
  
  /* Error */
  public void onStart()
  {
    // Byte code:
    //   0: goto +49 -> 49
    //   3: getstatic 22	o/Iw:ʿ	I
    //   6: bipush 91
    //   8: iadd
    //   9: istore_1
    //   10: iload_1
    //   11: sipush 128
    //   14: irem
    //   15: putstatic 24	o/Iw:ʼॱ	I
    //   18: iload_1
    //   19: iconst_2
    //   20: irem
    //   21: ifne +6 -> 27
    //   24: goto +18 -> 42
    //   27: goto +21 -> 48
    //   30: bipush 58
    //   32: istore_1
    //   33: goto +305 -> 338
    //   36: bipush 78
    //   38: istore_1
    //   39: goto +299 -> 338
    //   42: goto +6 -> 48
    //   45: goto +60 -> 105
    //   48: return
    //   49: goto +329 -> 378
    //   52: aload_0
    //   53: getfield 422	o/Iw:ॱˊ	Landroid/databinding/ViewDataBinding;
    //   56: checkcast 520	o/GJ
    //   59: getfield 654	o/GJ:ˊ	Landroid/widget/TextView;
    //   62: new 9	o/Iw$5
    //   65: dup
    //   66: aload_0
    //   67: invokespecial 656	o/Iw$5:<init>	(Lo/Iw;)V
    //   70: ldc2_w 657
    //   73: invokevirtual 664	android/widget/TextView:postDelayed	(Ljava/lang/Runnable;J)Z
    //   76: pop
    //   77: aload_0
    //   78: getfield 422	o/Iw:ॱˊ	Landroid/databinding/ViewDataBinding;
    //   81: checkcast 520	o/GJ
    //   84: getfield 667	o/GJ:ˎ	Lo/av;
    //   87: new 7	o/Iw$1
    //   90: dup
    //   91: aload_0
    //   92: invokespecial 668	o/Iw$1:<init>	(Lo/Iw;)V
    //   95: ldc2_w 669
    //   98: invokevirtual 673	o/av:postDelayed	(Ljava/lang/Runnable;J)Z
    //   101: pop
    //   102: goto -99 -> 3
    //   105: aload_0
    //   106: invokespecial 675	o/IB:onStart	()V
    //   109: goto +20 -> 129
    //   112: astore_3
    //   113: aload_3
    //   114: invokevirtual 586	java/lang/Throwable:getCause	()Ljava/lang/Throwable;
    //   117: astore 4
    //   119: aload 4
    //   121: ifnull +6 -> 127
    //   124: aload 4
    //   126: athrow
    //   127: aload_3
    //   128: athrow
    //   129: aload_0
    //   130: invokevirtual 542	android/content/Context:getPackageName	()Ljava/lang/String;
    //   133: iconst_2
    //   134: invokevirtual 456	java/lang/String:codePointAt	(I)I
    //   137: bipush 43
    //   139: isub
    //   140: aload_0
    //   141: invokevirtual 439	android/content/Context:getResources	()Landroid/content/res/Resources;
    //   144: ldc_w 676
    //   147: invokevirtual 446	android/content/res/Resources:getString	(I)Ljava/lang/String;
    //   150: iconst_0
    //   151: iconst_5
    //   152: invokevirtual 452	java/lang/String:substring	(II)Ljava/lang/String;
    //   155: iconst_3
    //   156: invokevirtual 456	java/lang/String:codePointAt	(I)I
    //   159: bipush 12
    //   161: isub
    //   162: aload_0
    //   163: invokevirtual 460	android/content/Context:getApplicationInfo	()Landroid/content/pm/ApplicationInfo;
    //   166: getfield 465	android/content/pm/ApplicationInfo:targetSdkVersion	I
    //   169: ldc_w 677
    //   172: iadd
    //   173: i2c
    //   174: invokestatic 594	o/O:ˋ	(IIC)Ljava/lang/Object;
    //   177: checkcast 596	java/lang/Class
    //   180: ldc_w 678
    //   183: aconst_null
    //   184: invokevirtual 601	java/lang/Class:getMethod	(Ljava/lang/String;[Ljava/lang/Class;)Ljava/lang/reflect/Method;
    //   187: aconst_null
    //   188: aconst_null
    //   189: invokevirtual 609	java/lang/reflect/Method:invoke	(Ljava/lang/Object;[Ljava/lang/Object;)Ljava/lang/Object;
    //   192: astore_3
    //   193: goto +20 -> 213
    //   196: astore_3
    //   197: aload_3
    //   198: invokevirtual 586	java/lang/Throwable:getCause	()Ljava/lang/Throwable;
    //   201: astore 4
    //   203: aload 4
    //   205: ifnull +6 -> 211
    //   208: aload 4
    //   210: athrow
    //   211: aload_3
    //   212: athrow
    //   213: aload_0
    //   214: invokevirtual 439	android/content/Context:getResources	()Landroid/content/res/Resources;
    //   217: ldc_w 679
    //   220: invokevirtual 446	android/content/res/Resources:getString	(I)Ljava/lang/String;
    //   223: iconst_0
    //   224: iconst_4
    //   225: invokevirtual 452	java/lang/String:substring	(II)Ljava/lang/String;
    //   228: iconst_2
    //   229: invokevirtual 456	java/lang/String:codePointAt	(I)I
    //   232: bipush 8
    //   234: isub
    //   235: aload_0
    //   236: invokevirtual 439	android/content/Context:getResources	()Landroid/content/res/Resources;
    //   239: ldc_w 680
    //   242: invokevirtual 446	android/content/res/Resources:getString	(I)Ljava/lang/String;
    //   245: iconst_0
    //   246: bipush 11
    //   248: invokevirtual 452	java/lang/String:substring	(II)Ljava/lang/String;
    //   251: bipush 9
    //   253: invokevirtual 456	java/lang/String:codePointAt	(I)I
    //   256: sipush 176
    //   259: isub
    //   260: aload_0
    //   261: invokevirtual 439	android/content/Context:getResources	()Landroid/content/res/Resources;
    //   264: ldc_w 681
    //   267: invokevirtual 446	android/content/res/Resources:getString	(I)Ljava/lang/String;
    //   270: iconst_0
    //   271: iconst_4
    //   272: invokevirtual 452	java/lang/String:substring	(II)Ljava/lang/String;
    //   275: invokevirtual 517	java/lang/String:length	()I
    //   278: ldc_w 682
    //   281: iadd
    //   282: i2c
    //   283: invokestatic 594	o/O:ˋ	(IIC)Ljava/lang/Object;
    //   286: checkcast 596	java/lang/Class
    //   289: ldc_w 683
    //   292: iconst_1
    //   293: anewarray 596	java/lang/Class
    //   296: dup
    //   297: iconst_0
    //   298: getstatic 689	java/lang/Integer:TYPE	Ljava/lang/Class;
    //   301: aastore
    //   302: invokevirtual 601	java/lang/Class:getMethod	(Ljava/lang/String;[Ljava/lang/Class;)Ljava/lang/reflect/Method;
    //   305: aload_3
    //   306: iconst_1
    //   307: anewarray 603	java/lang/Object
    //   310: dup
    //   311: iconst_0
    //   312: bipush 26
    //   314: invokestatic 693	java/lang/Integer:valueOf	(I)Ljava/lang/Integer;
    //   317: aastore
    //   318: invokevirtual 609	java/lang/reflect/Method:invoke	(Ljava/lang/Object;[Ljava/lang/Object;)Ljava/lang/Object;
    //   321: checkcast 695	java/lang/Boolean
    //   324: invokevirtual 699	java/lang/Boolean:booleanValue	()Z
    //   327: istore_2
    //   328: iload_2
    //   329: ifne +6 -> 335
    //   332: goto -296 -> 36
    //   335: goto -305 -> 30
    //   338: iload_1
    //   339: lookupswitch	default:+25->364, 58:+-287->52, 78:+28->367
    //   364: goto +3 -> 367
    //   367: aload_0
    //   368: getfield 701	o/Iw:ʻॱ	Z
    //   371: ifne +6 -> 377
    //   374: goto -322 -> 52
    //   377: return
    //   378: getstatic 24	o/Iw:ʼॱ	I
    //   381: bipush 65
    //   383: iadd
    //   384: istore_1
    //   385: iload_1
    //   386: sipush 128
    //   389: irem
    //   390: putstatic 22	o/Iw:ʿ	I
    //   393: iload_1
    //   394: iconst_2
    //   395: irem
    //   396: ifeq +6 -> 402
    //   399: goto -354 -> 45
    //   402: goto -297 -> 105
    // Local variable table:
    //   start	length	slot	name	signature
    //   0	405	0	this	Iw
    //   9	387	1	i	int
    //   327	2	2	bool	boolean
    //   112	16	3	localObject1	Object
    //   192	1	3	localObject2	Object
    //   196	110	3	localObject3	Object
    //   117	92	4	localThrowable	Throwable
    // Exception table:
    //   from	to	target	type
    //   129	193	112	finally
    //   213	328	196	finally
  }
  
  /* Error */
  public void onStop()
  {
    // Byte code:
    //   0: goto +279 -> 279
    //   3: getstatic 22	o/Iw:ʿ	I
    //   6: istore_1
    //   7: iload_1
    //   8: bipush 55
    //   10: iadd
    //   11: istore_1
    //   12: iload_1
    //   13: sipush 128
    //   16: irem
    //   17: putstatic 24	o/Iw:ʼॱ	I
    //   20: iload_1
    //   21: iconst_2
    //   22: irem
    //   23: ifne +6 -> 29
    //   26: goto +96 -> 122
    //   29: goto +92 -> 121
    //   32: aload_0
    //   33: iconst_0
    //   34: putfield 701	o/Iw:ʻॱ	Z
    //   37: goto +297 -> 334
    //   40: iload_1
    //   41: tableswitch	default:+23->64, 0:+292->333, 1:+53->94
    //   64: goto +30 -> 94
    //   67: bipush 37
    //   69: istore_1
    //   70: goto +90 -> 160
    //   73: astore_3
    //   74: aload_3
    //   75: athrow
    //   76: aload_0
    //   77: getfield 414	o/Iw:ʾ	Z
    //   80: istore_2
    //   81: iload_2
    //   82: ifne +6 -> 88
    //   85: goto +225 -> 310
    //   88: goto +247 -> 335
    //   91: goto +62 -> 153
    //   94: getstatic 22	o/Iw:ʿ	I
    //   97: bipush 95
    //   99: iadd
    //   100: istore_1
    //   101: iload_1
    //   102: sipush 128
    //   105: irem
    //   106: putstatic 24	o/Iw:ʼॱ	I
    //   109: iload_1
    //   110: iconst_2
    //   111: irem
    //   112: ifne +6 -> 118
    //   115: goto -24 -> 91
    //   118: goto +35 -> 153
    //   121: return
    //   122: goto -1 -> 121
    //   125: bipush 88
    //   127: istore_1
    //   128: goto +122 -> 250
    //   131: aload_0
    //   132: invokespecial 704	o/IB:onStop	()V
    //   135: aload_0
    //   136: getfield 701	o/Iw:ʻॱ	Z
    //   139: istore_2
    //   140: aconst_null
    //   141: arraylength
    //   142: istore_1
    //   143: iload_2
    //   144: ifne +6 -> 150
    //   147: goto +135 -> 282
    //   150: goto -25 -> 125
    //   153: aload_0
    //   154: invokespecial 569	o/Iw:ॱˋ	()V
    //   157: goto -154 -> 3
    //   160: iload_1
    //   161: lookupswitch	default:+27->188, 37:+-30->131, 84:+130->291
    //   188: goto -57 -> 131
    //   191: iload_1
    //   192: lookupswitch	default:+28->220, 9:+-116->76, 79:+-160->32
    //   220: goto -188 -> 32
    //   223: getstatic 24	o/Iw:ʼॱ	I
    //   226: bipush 47
    //   228: iadd
    //   229: istore_1
    //   230: iload_1
    //   231: sipush 128
    //   234: irem
    //   235: putstatic 22	o/Iw:ʿ	I
    //   238: iload_1
    //   239: iconst_2
    //   240: irem
    //   241: ifeq +6 -> 247
    //   244: goto -177 -> 67
    //   247: goto +68 -> 315
    //   250: iload_1
    //   251: lookupswitch	default:+25->276, 88:+-219->32, 99:+-175->76
    //   276: goto -200 -> 76
    //   279: goto -56 -> 223
    //   282: bipush 99
    //   284: istore_1
    //   285: goto -35 -> 250
    //   288: astore_3
    //   289: aload_3
    //   290: athrow
    //   291: aload_0
    //   292: invokespecial 704	o/IB:onStop	()V
    //   295: aload_0
    //   296: getfield 701	o/Iw:ʻॱ	Z
    //   299: istore_2
    //   300: iload_2
    //   301: ifne +6 -> 307
    //   304: goto +17 -> 321
    //   307: goto +20 -> 327
    //   310: iconst_1
    //   311: istore_1
    //   312: goto -272 -> 40
    //   315: bipush 84
    //   317: istore_1
    //   318: goto -158 -> 160
    //   321: bipush 9
    //   323: istore_1
    //   324: goto -133 -> 191
    //   327: bipush 79
    //   329: istore_1
    //   330: goto -139 -> 191
    //   333: return
    //   334: return
    //   335: iconst_0
    //   336: istore_1
    //   337: goto -297 -> 40
    // Local variable table:
    //   start	length	slot	name	signature
    //   0	340	0	this	Iw
    //   6	331	1	i	int
    //   80	221	2	bool	boolean
    //   73	2	3	localException1	Exception
    //   288	2	3	localException2	Exception
    // Exception table:
    //   from	to	target	type
    //   3	7	73	java/lang/Exception
    //   135	140	73	java/lang/Exception
    //   295	300	73	java/lang/Exception
    //   12	20	288	java/lang/Exception
    //   76	81	288	java/lang/Exception
  }
  
  /* Error */
  public int ˎ()
  {
    // Byte code:
    //   0: goto +102 -> 102
    //   3: aconst_null
    //   4: arraylength
    //   5: istore_1
    //   6: iload_2
    //   7: ireturn
    //   8: getstatic 22	o/Iw:ʿ	I
    //   11: istore_1
    //   12: iload_1
    //   13: bipush 35
    //   15: iadd
    //   16: istore_1
    //   17: iload_1
    //   18: sipush 128
    //   21: irem
    //   22: putstatic 24	o/Iw:ʼॱ	I
    //   25: iload_1
    //   26: iconst_2
    //   27: irem
    //   28: ifne +6 -> 34
    //   31: goto +74 -> 105
    //   34: goto +11 -> 45
    //   37: iload_2
    //   38: ireturn
    //   39: astore_3
    //   40: aload_3
    //   41: athrow
    //   42: astore_3
    //   43: aload_3
    //   44: athrow
    //   45: getstatic 709	o/Gu$ˊ:activity_confirmation	I
    //   48: istore_2
    //   49: getstatic 22	o/Iw:ʿ	I
    //   52: istore_1
    //   53: iload_1
    //   54: bipush 35
    //   56: iadd
    //   57: istore_1
    //   58: iload_1
    //   59: sipush 128
    //   62: irem
    //   63: putstatic 24	o/Iw:ʼॱ	I
    //   66: iload_1
    //   67: iconst_2
    //   68: irem
    //   69: ifne +6 -> 75
    //   72: goto +36 -> 108
    //   75: goto +38 -> 113
    //   78: iload_1
    //   79: tableswitch	default:+21->100, 0:+-76->3, 1:+-42->37
    //   100: iload_2
    //   101: ireturn
    //   102: goto -94 -> 8
    //   105: goto -60 -> 45
    //   108: iconst_0
    //   109: istore_1
    //   110: goto -32 -> 78
    //   113: iconst_1
    //   114: istore_1
    //   115: goto -37 -> 78
    // Local variable table:
    //   start	length	slot	name	signature
    //   0	118	0	this	Iw
    //   5	110	1	i	int
    //   6	95	2	j	int
    //   39	2	3	localException1	Exception
    //   42	2	3	localException2	Exception
    // Exception table:
    //   from	to	target	type
    //   8	12	39	java/lang/Exception
    //   17	25	39	java/lang/Exception
    //   49	53	39	java/lang/Exception
    //   45	49	42	java/lang/Exception
    //   58	66	42	java/lang/Exception
  }
}
