package o;

import android.content.Context;
import android.content.DialogInterface;
import android.content.DialogInterface.OnCancelListener;
import android.content.pm.ApplicationInfo;
import android.content.res.Resources;
import android.databinding.ViewDataBinding;
import android.widget.RelativeLayout;
import java.io.UnsupportedEncodingException;

public abstract class Ix<I extends Iu.iF, VDB extends ViewDataBinding>
  extends Y<I, VDB>
  implements Iu.if
{
  private static byte ʼॱ;
  private static char[] ʽॱ;
  private static int ʾ;
  private static long ʿ;
  private static int ˈ;
  public IC ॱˋ;
  private RelativeLayout ॱˎ;
  protected boolean ॱᐝ;
  
  static
  {
    for (;;)
    {
      int i = ʾ + 29;
      ˈ = i % 128;
      if (i % 2 != 0) {
        break;
      }
      return;
      ˈ = 0;
      ʾ = 1;
      ͺॱ();
      ʼॱ = -102;
    }
  }
  
  /* Error */
  public Ix()
  {
    // Byte code:
    //   0: goto +6 -> 6
    //   3: astore_1
    //   4: aload_1
    //   5: athrow
    //   6: aload_0
    //   7: invokespecial 45	o/Y:<init>	()V
    //   10: aload_0
    //   11: iconst_1
    //   12: putfield 47	o/Ix:ॱᐝ	Z
    //   15: return
    // Local variable table:
    //   start	length	slot	name	signature
    //   0	16	0	this	Ix
    //   3	2	1	localException	Exception
    // Exception table:
    //   from	to	target	type
    //   10	15	3	java/lang/Exception
  }
  
  /* Error */
  private final void ˋ(String paramString)
  {
    // Byte code:
    //   0: goto +29 -> 29
    //   3: getstatic 34	o/Ix:ˈ	I
    //   6: bipush 63
    //   8: iadd
    //   9: istore_2
    //   10: iload_2
    //   11: sipush 128
    //   14: irem
    //   15: putstatic 32	o/Ix:ʾ	I
    //   18: iload_2
    //   19: iconst_2
    //   20: irem
    //   21: ifne +6 -> 27
    //   24: goto +4 -> 28
    //   27: return
    //   28: return
    //   29: goto +6 -> 35
    //   32: astore_1
    //   33: aload_1
    //   34: athrow
    //   35: aload_0
    //   36: invokevirtual 55	android/content/Context:getApplicationInfo	()Landroid/content/pm/ApplicationInfo;
    //   39: getfield 60	android/content/pm/ApplicationInfo:targetSdkVersion	I
    //   42: sipush 184
    //   45: iadd
    //   46: aload_0
    //   47: invokevirtual 64	android/content/Context:getResources	()Landroid/content/res/Resources;
    //   50: ldc 65
    //   52: invokevirtual 71	android/content/res/Resources:getString	(I)Ljava/lang/String;
    //   55: iconst_0
    //   56: iconst_5
    //   57: invokevirtual 77	java/lang/String:substring	(II)Ljava/lang/String;
    //   60: invokevirtual 81	java/lang/String:length	()I
    //   63: iconst_5
    //   64: isub
    //   65: i2c
    //   66: aload_0
    //   67: invokevirtual 85	android/content/Context:getPackageName	()Ljava/lang/String;
    //   70: iconst_4
    //   71: invokevirtual 89	java/lang/String:codePointAt	(I)I
    //   74: bipush 109
    //   76: isub
    //   77: invokestatic 93	o/Ix:ॱ	(ICI)Ljava/lang/String;
    //   80: invokevirtual 96	java/lang/String:intern	()Ljava/lang/String;
    //   83: astore_3
    //   84: new 98	java/lang/StringBuilder
    //   87: dup
    //   88: invokespecial 99	java/lang/StringBuilder:<init>	()V
    //   91: aload_0
    //   92: invokevirtual 64	android/content/Context:getResources	()Landroid/content/res/Resources;
    //   95: ldc 100
    //   97: invokevirtual 71	android/content/res/Resources:getString	(I)Ljava/lang/String;
    //   100: iconst_0
    //   101: iconst_4
    //   102: invokevirtual 77	java/lang/String:substring	(II)Ljava/lang/String;
    //   105: invokevirtual 81	java/lang/String:length	()I
    //   108: sipush 212
    //   111: iadd
    //   112: aload_0
    //   113: invokevirtual 55	android/content/Context:getApplicationInfo	()Landroid/content/pm/ApplicationInfo;
    //   116: getfield 60	android/content/pm/ApplicationInfo:targetSdkVersion	I
    //   119: sipush 1305
    //   122: iadd
    //   123: i2c
    //   124: aload_0
    //   125: invokevirtual 55	android/content/Context:getApplicationInfo	()Landroid/content/pm/ApplicationInfo;
    //   128: getfield 60	android/content/pm/ApplicationInfo:targetSdkVersion	I
    //   131: iconst_0
    //   132: iadd
    //   133: invokestatic 93	o/Ix:ॱ	(ICI)Ljava/lang/String;
    //   136: invokevirtual 96	java/lang/String:intern	()Ljava/lang/String;
    //   139: invokevirtual 104	java/lang/StringBuilder:append	(Ljava/lang/String;)Ljava/lang/StringBuilder;
    //   142: aload_1
    //   143: invokevirtual 104	java/lang/StringBuilder:append	(Ljava/lang/String;)Ljava/lang/StringBuilder;
    //   146: invokevirtual 107	java/lang/StringBuilder:toString	()Ljava/lang/String;
    //   149: astore 4
    //   151: goto +17 -> 168
    //   154: astore_1
    //   155: aload_1
    //   156: invokevirtual 113	java/lang/Throwable:getCause	()Ljava/lang/Throwable;
    //   159: astore_3
    //   160: aload_3
    //   161: ifnull +5 -> 166
    //   164: aload_3
    //   165: athrow
    //   166: aload_1
    //   167: athrow
    //   168: aload_0
    //   169: invokevirtual 64	android/content/Context:getResources	()Landroid/content/res/Resources;
    //   172: ldc 114
    //   174: invokevirtual 71	android/content/res/Resources:getString	(I)Ljava/lang/String;
    //   177: iconst_0
    //   178: iconst_4
    //   179: invokevirtual 77	java/lang/String:substring	(II)Ljava/lang/String;
    //   182: iconst_1
    //   183: invokevirtual 89	java/lang/String:codePointAt	(I)I
    //   186: bipush 22
    //   188: isub
    //   189: aload_0
    //   190: invokevirtual 64	android/content/Context:getResources	()Landroid/content/res/Resources;
    //   193: ldc 115
    //   195: invokevirtual 71	android/content/res/Resources:getString	(I)Ljava/lang/String;
    //   198: iconst_0
    //   199: iconst_4
    //   200: invokevirtual 77	java/lang/String:substring	(II)Ljava/lang/String;
    //   203: iconst_1
    //   204: invokevirtual 89	java/lang/String:codePointAt	(I)I
    //   207: bipush 16
    //   209: iadd
    //   210: aload_0
    //   211: invokevirtual 64	android/content/Context:getResources	()Landroid/content/res/Resources;
    //   214: ldc 116
    //   216: invokevirtual 71	android/content/res/Resources:getString	(I)Ljava/lang/String;
    //   219: bipush 12
    //   221: bipush 19
    //   223: invokevirtual 77	java/lang/String:substring	(II)Ljava/lang/String;
    //   226: invokevirtual 81	java/lang/String:length	()I
    //   229: ldc 117
    //   231: iadd
    //   232: i2c
    //   233: invokestatic 122	o/O:ˋ	(IIC)Ljava/lang/Object;
    //   236: checkcast 124	java/lang/Class
    //   239: ldc 126
    //   241: iconst_2
    //   242: anewarray 124	java/lang/Class
    //   245: dup
    //   246: iconst_0
    //   247: ldc 73
    //   249: aastore
    //   250: dup
    //   251: iconst_1
    //   252: ldc 73
    //   254: aastore
    //   255: invokevirtual 130	java/lang/Class:getMethod	(Ljava/lang/String;[Ljava/lang/Class;)Ljava/lang/reflect/Method;
    //   258: aconst_null
    //   259: iconst_2
    //   260: anewarray 132	java/lang/Object
    //   263: dup
    //   264: iconst_0
    //   265: aload_3
    //   266: aastore
    //   267: dup
    //   268: iconst_1
    //   269: aload 4
    //   271: aastore
    //   272: invokevirtual 138	java/lang/reflect/Method:invoke	(Ljava/lang/Object;[Ljava/lang/Object;)Ljava/lang/Object;
    //   275: pop
    //   276: aload_0
    //   277: invokevirtual 139	o/Ix:getResources	()Landroid/content/res/Resources;
    //   280: astore_3
    //   281: aload_3
    //   282: aload_0
    //   283: invokevirtual 64	android/content/Context:getResources	()Landroid/content/res/Resources;
    //   286: ldc -116
    //   288: invokevirtual 71	android/content/res/Resources:getString	(I)Ljava/lang/String;
    //   291: iconst_0
    //   292: bipush 8
    //   294: invokevirtual 77	java/lang/String:substring	(II)Ljava/lang/String;
    //   297: bipush 6
    //   299: invokevirtual 89	java/lang/String:codePointAt	(I)I
    //   302: bipush 70
    //   304: iadd
    //   305: aload_0
    //   306: invokevirtual 55	android/content/Context:getApplicationInfo	()Landroid/content/pm/ApplicationInfo;
    //   309: getfield 60	android/content/pm/ApplicationInfo:targetSdkVersion	I
    //   312: bipush 25
    //   314: isub
    //   315: i2c
    //   316: aload_0
    //   317: invokevirtual 64	android/content/Context:getResources	()Landroid/content/res/Resources;
    //   320: ldc -115
    //   322: invokevirtual 71	android/content/res/Resources:getString	(I)Ljava/lang/String;
    //   325: iconst_0
    //   326: iconst_4
    //   327: invokevirtual 77	java/lang/String:substring	(II)Ljava/lang/String;
    //   330: iconst_0
    //   331: invokevirtual 89	java/lang/String:codePointAt	(I)I
    //   334: iconst_2
    //   335: isub
    //   336: invokestatic 93	o/Ix:ॱ	(ICI)Ljava/lang/String;
    //   339: invokevirtual 96	java/lang/String:intern	()Ljava/lang/String;
    //   342: invokestatic 146	o/vq:ˋ	(Ljava/lang/Object;Ljava/lang/String;)V
    //   345: aload_3
    //   346: invokevirtual 150	android/content/res/Resources:getConfiguration	()Landroid/content/res/Configuration;
    //   349: astore 4
    //   351: aload 4
    //   353: aload_1
    //   354: invokestatic 156	o/aq:ᐝ	(Ljava/lang/String;)Ljava/util/Locale;
    //   357: invokevirtual 162	android/content/res/Configuration:setLocale	(Ljava/util/Locale;)V
    //   360: aload_3
    //   361: aload 4
    //   363: aload_3
    //   364: invokevirtual 166	android/content/res/Resources:getDisplayMetrics	()Landroid/util/DisplayMetrics;
    //   367: invokevirtual 170	android/content/res/Resources:updateConfiguration	(Landroid/content/res/Configuration;Landroid/util/DisplayMetrics;)V
    //   370: goto -367 -> 3
    //   373: astore_1
    //   374: aload_1
    //   375: athrow
    // Local variable table:
    //   start	length	slot	name	signature
    //   0	376	0	this	Ix
    //   0	376	1	paramString	String
    //   9	12	2	i	int
    //   83	281	3	localObject1	Object
    //   149	213	4	localObject2	Object
    // Exception table:
    //   from	to	target	type
    //   10	18	32	java/lang/Exception
    //   168	276	154	finally
    //   3	10	373	java/lang/Exception
    //   10	18	373	java/lang/Exception
  }
  
  /* Error */
  private final void ˏ(boolean paramBoolean)
  {
    // Byte code:
    //   0: goto +326 -> 326
    //   3: aload_0
    //   4: invokevirtual 175	o/Ix:ˋˊ	()V
    //   7: aconst_null
    //   8: arraylength
    //   9: istore_2
    //   10: goto +346 -> 356
    //   13: bipush 23
    //   15: istore_2
    //   16: goto +278 -> 294
    //   19: goto +20 -> 39
    //   22: astore_3
    //   23: aload_3
    //   24: invokevirtual 113	java/lang/Throwable:getCause	()Ljava/lang/Throwable;
    //   27: astore 4
    //   29: aload 4
    //   31: ifnull +6 -> 37
    //   34: aload 4
    //   36: athrow
    //   37: aload_3
    //   38: athrow
    //   39: aload_0
    //   40: invokevirtual 64	android/content/Context:getResources	()Landroid/content/res/Resources;
    //   43: ldc -80
    //   45: invokevirtual 71	android/content/res/Resources:getString	(I)Ljava/lang/String;
    //   48: iconst_0
    //   49: iconst_4
    //   50: invokevirtual 77	java/lang/String:substring	(II)Ljava/lang/String;
    //   53: invokevirtual 81	java/lang/String:length	()I
    //   56: iconst_1
    //   57: isub
    //   58: aload_0
    //   59: invokevirtual 85	android/content/Context:getPackageName	()Ljava/lang/String;
    //   62: bipush 7
    //   64: invokevirtual 89	java/lang/String:codePointAt	(I)I
    //   67: bipush 46
    //   69: isub
    //   70: aload_0
    //   71: invokevirtual 55	android/content/Context:getApplicationInfo	()Landroid/content/pm/ApplicationInfo;
    //   74: getfield 60	android/content/pm/ApplicationInfo:targetSdkVersion	I
    //   77: ldc -79
    //   79: iadd
    //   80: i2c
    //   81: invokestatic 122	o/O:ˋ	(IIC)Ljava/lang/Object;
    //   84: checkcast 124	java/lang/Class
    //   87: ldc 126
    //   89: aconst_null
    //   90: invokevirtual 130	java/lang/Class:getMethod	(Ljava/lang/String;[Ljava/lang/Class;)Ljava/lang/reflect/Method;
    //   93: aconst_null
    //   94: aconst_null
    //   95: invokevirtual 138	java/lang/reflect/Method:invoke	(Ljava/lang/Object;[Ljava/lang/Object;)Ljava/lang/Object;
    //   98: astore_3
    //   99: aload_3
    //   100: aload_0
    //   101: invokevirtual 55	android/content/Context:getApplicationInfo	()Landroid/content/pm/ApplicationInfo;
    //   104: getfield 60	android/content/pm/ApplicationInfo:targetSdkVersion	I
    //   107: sipush 219
    //   110: iadd
    //   111: aload_0
    //   112: invokevirtual 64	android/content/Context:getResources	()Landroid/content/res/Resources;
    //   115: ldc -78
    //   117: invokevirtual 71	android/content/res/Resources:getString	(I)Ljava/lang/String;
    //   120: iconst_0
    //   121: iconst_4
    //   122: invokevirtual 77	java/lang/String:substring	(II)Ljava/lang/String;
    //   125: iconst_1
    //   126: invokevirtual 89	java/lang/String:codePointAt	(I)I
    //   129: bipush 26
    //   131: isub
    //   132: i2c
    //   133: aload_0
    //   134: invokevirtual 85	android/content/Context:getPackageName	()Ljava/lang/String;
    //   137: iconst_2
    //   138: invokevirtual 89	java/lang/String:codePointAt	(I)I
    //   141: bipush 27
    //   143: isub
    //   144: invokestatic 93	o/Ix:ॱ	(ICI)Ljava/lang/String;
    //   147: invokevirtual 96	java/lang/String:intern	()Ljava/lang/String;
    //   150: invokestatic 146	o/vq:ˋ	(Ljava/lang/Object;Ljava/lang/String;)V
    //   153: goto +20 -> 173
    //   156: astore_3
    //   157: aload_3
    //   158: invokevirtual 113	java/lang/Throwable:getCause	()Ljava/lang/Throwable;
    //   161: astore 4
    //   163: aload 4
    //   165: ifnull +6 -> 171
    //   168: aload 4
    //   170: athrow
    //   171: aload_3
    //   172: athrow
    //   173: aload_0
    //   174: invokevirtual 64	android/content/Context:getResources	()Landroid/content/res/Resources;
    //   177: ldc -77
    //   179: invokevirtual 71	android/content/res/Resources:getString	(I)Ljava/lang/String;
    //   182: iconst_0
    //   183: iconst_5
    //   184: invokevirtual 77	java/lang/String:substring	(II)Ljava/lang/String;
    //   187: invokevirtual 81	java/lang/String:length	()I
    //   190: iconst_2
    //   191: isub
    //   192: aload_0
    //   193: invokevirtual 64	android/content/Context:getResources	()Landroid/content/res/Resources;
    //   196: ldc -76
    //   198: invokevirtual 71	android/content/res/Resources:getString	(I)Ljava/lang/String;
    //   201: iconst_0
    //   202: iconst_5
    //   203: invokevirtual 77	java/lang/String:substring	(II)Ljava/lang/String;
    //   206: invokevirtual 81	java/lang/String:length	()I
    //   209: iconst_5
    //   210: isub
    //   211: aload_0
    //   212: invokevirtual 64	android/content/Context:getResources	()Landroid/content/res/Resources;
    //   215: ldc -75
    //   217: invokevirtual 71	android/content/res/Resources:getString	(I)Ljava/lang/String;
    //   220: iconst_0
    //   221: bipush 15
    //   223: invokevirtual 77	java/lang/String:substring	(II)Ljava/lang/String;
    //   226: invokevirtual 81	java/lang/String:length	()I
    //   229: ldc -74
    //   231: iadd
    //   232: i2c
    //   233: invokestatic 122	o/O:ˋ	(IIC)Ljava/lang/Object;
    //   236: checkcast 124	java/lang/Class
    //   239: ldc -73
    //   241: aconst_null
    //   242: invokevirtual 130	java/lang/Class:getMethod	(Ljava/lang/String;[Ljava/lang/Class;)Ljava/lang/reflect/Method;
    //   245: aload_3
    //   246: aconst_null
    //   247: invokevirtual 138	java/lang/reflect/Method:invoke	(Ljava/lang/Object;[Ljava/lang/Object;)Ljava/lang/Object;
    //   250: checkcast 185	java/lang/Boolean
    //   253: invokevirtual 189	java/lang/Boolean:booleanValue	()Z
    //   256: istore_1
    //   257: iload_1
    //   258: ifne +6 -> 264
    //   261: goto -248 -> 13
    //   264: goto +155 -> 419
    //   267: aload_0
    //   268: invokevirtual 175	o/Ix:ˋˊ	()V
    //   271: goto +85 -> 356
    //   274: bipush 88
    //   276: istore_2
    //   277: goto +110 -> 387
    //   280: bipush 64
    //   282: istore_2
    //   283: goto +104 -> 387
    //   286: iload_1
    //   287: ifeq +6 -> 293
    //   290: goto +39 -> 329
    //   293: return
    //   294: iload_2
    //   295: lookupswitch	default:+25->320, 23:+62->357, 98:+91->386
    //   320: goto +37 -> 357
    //   323: astore_3
    //   324: aload_3
    //   325: athrow
    //   326: goto -40 -> 286
    //   329: getstatic 32	o/Ix:ʾ	I
    //   332: bipush 51
    //   334: iadd
    //   335: istore_2
    //   336: iload_2
    //   337: sipush 128
    //   340: irem
    //   341: putstatic 34	o/Ix:ˈ	I
    //   344: iload_2
    //   345: iconst_2
    //   346: irem
    //   347: ifeq +6 -> 353
    //   350: goto +33 -> 383
    //   353: goto -334 -> 19
    //   356: return
    //   357: getstatic 32	o/Ix:ʾ	I
    //   360: iconst_3
    //   361: iadd
    //   362: istore_2
    //   363: iload_2
    //   364: sipush 128
    //   367: irem
    //   368: putstatic 34	o/Ix:ˈ	I
    //   371: iload_2
    //   372: iconst_2
    //   373: irem
    //   374: ifeq +6 -> 380
    //   377: goto -103 -> 274
    //   380: goto -100 -> 280
    //   383: goto -364 -> 19
    //   386: return
    //   387: iload_2
    //   388: lookupswitch	default:+28->416, 64:+-121->267, 88:+-385->3
    //   416: goto -413 -> 3
    //   419: bipush 98
    //   421: istore_2
    //   422: goto -128 -> 294
    // Local variable table:
    //   start	length	slot	name	signature
    //   0	425	0	this	Ix
    //   0	425	1	paramBoolean	boolean
    //   9	413	2	i	int
    //   22	16	3	localObject1	Object
    //   98	2	3	localObject2	Object
    //   156	90	3	localObject3	Object
    //   323	2	3	localException	Exception
    //   27	142	4	localThrowable	Throwable
    // Exception table:
    //   from	to	target	type
    //   39	99	22	finally
    //   173	257	156	finally
    //   3	7	323	java/lang/Exception
  }
  
  static void ͺॱ()
  {
    ʿ = -2004162781936934902L;
    ʽॱ = new char[] { 109, 8284, 16509, 24699, -32673, -24458, -16295, -8150, 53, 8253, 16389, 24602, -32739, 60, 8313, 16497, 24682, -32763, -24563, -16382, 109, 8264, 16509, 24688, -32692, -24485, -16302, -8159, 110, 8319, 16504, 24690, -32760, -24495, -16291, -8152, 62, 8245, 16400, 24654, -32742, -24345, -16212, -7947, 193, 8409, 16576, 24734, -32580, -24387, -16132, -8056, 159, 8340, 16681, 24928, -32403, -24242, -16064, -7914, 308, 8499, 16676, 24891, -32440, -24301, -16110, -7710, 482, 8693, 16845, 25034, -32362, -24139, -15963, -7758, 391, 8591, 16768, 25040, -32166, -23945, -15760, -7609, 580, 8787, 16946, 25131, -32236, -24061, -15851, -7655, 757, 8958, -780, -8965, -17153, -25358, 31957, 23748, 15553, 7340, 31454, 23235, 15071, 6875, -1289, -9494, -17675, -25960, 31385, 23186, 15000, 6826, -1349, -9664, -17851, -25996, 31353, 23147, 14970, 6775, -1514, 9071, 873, 25442, 17262, -23741, -31928, -7306, -15577, 9015, 785, 25352, 17167, -23787, -31763, -7170, -15371, 9174, 961, 25556, 17365, -23642, -31815, -7254, -15459, -16086, -7885, -32450, -24257, 16659, -23136, -31307, -6726, -14921, -28736, -20536, -12345, -4118, 4091, 12263, 20466, 28559, -28784, -20523, -12378, -4161, 4026, 12107, 20319, 28447, -28822, -20632, -12448, -4246, 3854, 12050, 20254, 28424, -28877, -20620, 77, 8299, 16480, 24684, -32703, -24502, -16268, -8187, 21, 4315, 12541, 20726, 28922, -28457, -20260, -12150, -3912, 4261, 12457, 20690, 28829, -28516, -20378, -12171, -3982, 4108, 12316, 71, 8303, 16506, 24699, -32678, -24493, -16304, 1393, 9552, 17735, 25922, -31363, -23191, -15008, -6893, 1346, 9481, 17702, 25900, -31382, -23076, -14881, -6710, 1525, 9709, 17895, 26091, -31329, -23104, -14950, -6725, 1506, 114, 8303, 16487, 68, 8303, 16482, 24695, -32693, -24489, -16271, -8153, 62, 8251, 16387, 24587, -32758, -24404, -16149, -7949, 212, 8322, 16541, 73, 8281, 16475, 24627, -32752, -24566, -16375, -8065, 125, 8299, -8816, -613, -25193, -16906, 24021 };
  }
  
  private static String ॱ(int paramInt1, char paramChar, int paramInt2)
  {
    break label244;
    Object localObject;
    int i;
    localObject[i] = ((char)(int)((ʽॱ[(paramInt1 << i)] ^ i % ʿ) - paramChar));
    i += 48;
    break label166;
    label35:
    label63:
    int j;
    switch (paramInt1)
    {
    default: 
      return localObject;
      for (;;)
      {
        switch (j)
        {
        default: 
          break label135;
          label95:
          j = ˈ + 89;
          ʾ = j % 128;
          if (j % 2 == 0) {
            break label284;
          }
          break label132;
          label125:
          j = 32;
        }
      }
    }
    label132:
    label135:
    label154:
    label166:
    label244:
    label274:
    label284:
    for (;;)
    {
      break label166;
      localObject = new String((char[])localObject);
      for (;;)
      {
        paramInt1 = 1;
        break label35;
        j = 59;
        break label63;
        do
        {
          paramInt1 = 0;
          break label35;
          for (;;)
          {
            if (i < paramInt2) {
              break label125;
            }
            break label154;
            paramInt1 = null.length;
            return localObject;
            j = ˈ + 77;
            ʾ = j % 128;
            if (j % 2 == 0) {
              break;
            }
            localObject[i] = ((char)(int)(ʽॱ[(paramInt1 + i)] ^ i * ʿ ^ paramChar));
            i += 1;
          }
          return localObject;
          break label274;
          paramInt1 = ʾ + 21;
          ˈ = paramInt1 % 128;
        } while (paramInt1 % 2 != 0);
      }
      localObject = new char[paramInt2];
      i = 0;
      break label95;
    }
  }
  
  private String ॱ(String paramString)
  {
    byte[] arrayOfByte;
    int i;
    label130:
    int j;
    for (;;)
    {
      try
      {
        paramString = paramString.getBytes(ॱ(getResources().getString(2131755435).substring(0, 4).length() + 259, (char)(getResources().getString(2131755500).substring(0, 4).length() - 4), getResources().getString(2131755183).substring(0, 10).codePointAt(8) - 176).intern());
        arrayOfByte = new byte[paramString.length];
        i = 0;
      }
      catch (UnsupportedEncodingException paramString)
      {
        throw new RuntimeException(paramString);
      }
      arrayOfByte[i] = ((byte)(paramString[(paramString.length - i - 1)] ^ ʼॱ));
      i += 1;
      break label272;
      break label165;
      j = 0;
      break label286;
      j = ʾ + 105;
      ˈ = j % 128;
      if (j % 2 != 0) {
        break;
      }
      continue;
      label165:
      do
      {
        break;
        i = ʾ + 33;
        ˈ = i % 128;
      } while (i % 2 != 0);
    }
    for (;;)
    {
      paramString = new String(arrayOfByte, ॱ(getResources().getString(2131755083).substring(0, 4).length() + 269, (char)(getPackageName().length() + 56762), getResources().getString(2131755377).substring(0, 1).length() + 4).intern());
      return paramString;
      break;
      label272:
      do
      {
        j = 1;
        break;
        j = paramString.length;
      } while (i < j);
      break label130;
      label286:
      switch (j)
      {
      }
    }
  }
  
  public void A_()
  {
    break label11;
    ˊᐝ().A_();
    return;
    label11:
    break label29;
    ˊᐝ().A_();
    throw new NullPointerException();
    label29:
    int i = ʾ + 103;
    ˈ = i % 128;
    if (i % 2 == 0) {
      break label88;
    }
    for (;;)
    {
      switch (i)
      {
      }
      break;
      i = 0;
      continue;
      label88:
      i = 1;
    }
  }
  
  /* Error */
  public Resources getResources()
  {
    // Byte code:
    //   0: goto +91 -> 91
    //   3: iconst_0
    //   4: istore_1
    //   5: goto +45 -> 50
    //   8: astore_2
    //   9: aload_2
    //   10: athrow
    //   11: aload_0
    //   12: invokespecial 503	o/Y:getResources	()Landroid/content/res/Resources;
    //   15: astore_2
    //   16: aload_2
    //   17: invokestatic 509	o/oH:ˊ	(Landroid/content/res/Resources;)Landroid/content/res/Resources;
    //   20: astore_2
    //   21: aload_2
    //   22: areturn
    //   23: getstatic 32	o/Ix:ʾ	I
    //   26: bipush 9
    //   28: iadd
    //   29: istore_1
    //   30: iload_1
    //   31: sipush 128
    //   34: irem
    //   35: putstatic 34	o/Ix:ˈ	I
    //   38: iload_1
    //   39: iconst_2
    //   40: irem
    //   41: ifeq +6 -> 47
    //   44: goto +50 -> 94
    //   47: goto -44 -> 3
    //   50: iload_1
    //   51: tableswitch	default:+21->72, 0:+-40->11, 1:+24->75
    //   72: goto -61 -> 11
    //   75: aload_0
    //   76: invokespecial 503	o/Y:getResources	()Landroid/content/res/Resources;
    //   79: invokestatic 509	o/oH:ˊ	(Landroid/content/res/Resources;)Landroid/content/res/Resources;
    //   82: pop
    //   83: new 501	java/lang/NullPointerException
    //   86: dup
    //   87: invokespecial 502	java/lang/NullPointerException:<init>	()V
    //   90: athrow
    //   91: goto -68 -> 23
    //   94: iconst_1
    //   95: istore_1
    //   96: goto -46 -> 50
    // Local variable table:
    //   start	length	slot	name	signature
    //   0	99	0	this	Ix
    //   4	92	1	i	int
    //   8	2	2	localException	Exception
    //   15	7	2	localResources	Resources
    // Exception table:
    //   from	to	target	type
    //   16	21	8	java/lang/Exception
  }
  
  /* Error */
  public void onActivityResult(int paramInt1, int paramInt2, android.content.Intent paramIntent)
  {
    // Byte code:
    //   0: goto +129 -> 129
    //   3: iconst_1
    //   4: istore 4
    //   6: goto +479 -> 485
    //   9: iconst_1
    //   10: istore 4
    //   12: goto +303 -> 315
    //   15: goto +470 -> 485
    //   18: bipush 43
    //   20: istore_1
    //   21: goto +265 -> 286
    //   24: astore_3
    //   25: aload_3
    //   26: athrow
    //   27: iconst_1
    //   28: istore 4
    //   30: goto +110 -> 140
    //   33: aload_0
    //   34: new 13	o/Ix$ˋ
    //   37: dup
    //   38: aload_0
    //   39: invokespecial 514	o/Ix$ˋ:<init>	(Lo/Ix;)V
    //   42: checkcast 516	android/content/DialogInterface$OnCancelListener
    //   45: invokevirtual 519	o/Ix:ˎ	(Landroid/content/DialogInterface$OnCancelListener;)V
    //   48: return
    //   49: getstatic 32	o/Ix:ʾ	I
    //   52: bipush 103
    //   54: iadd
    //   55: istore_1
    //   56: iload_1
    //   57: sipush 128
    //   60: irem
    //   61: putstatic 34	o/Ix:ˈ	I
    //   64: iload_1
    //   65: iconst_2
    //   66: irem
    //   67: ifeq +6 -> 73
    //   70: goto +47 -> 117
    //   73: goto -70 -> 3
    //   76: iconst_0
    //   77: istore 4
    //   79: goto +53 -> 132
    //   82: return
    //   83: iload_1
    //   84: tableswitch	default:+24->108, 0:+-57->27, 1:+39->123
    //   108: goto +15 -> 123
    //   111: iconst_0
    //   112: istore 4
    //   114: goto -99 -> 15
    //   117: goto -114 -> 3
    //   120: astore_3
    //   121: aload_3
    //   122: athrow
    //   123: iconst_0
    //   124: istore 4
    //   126: goto +14 -> 140
    //   129: goto +306 -> 435
    //   132: goto +183 -> 315
    //   135: iconst_0
    //   136: istore_1
    //   137: goto +149 -> 286
    //   140: aload_0
    //   141: iload 4
    //   143: invokespecial 521	o/Ix:ˏ	(Z)V
    //   146: return
    //   147: iconst_1
    //   148: istore_1
    //   149: goto -66 -> 83
    //   152: goto +20 -> 172
    //   155: astore_3
    //   156: aload_3
    //   157: invokevirtual 113	java/lang/Throwable:getCause	()Ljava/lang/Throwable;
    //   160: astore 5
    //   162: aload 5
    //   164: ifnull +6 -> 170
    //   167: aload 5
    //   169: athrow
    //   170: aload_3
    //   171: athrow
    //   172: aload_0
    //   173: invokevirtual 64	android/content/Context:getResources	()Landroid/content/res/Resources;
    //   176: ldc_w 522
    //   179: invokevirtual 71	android/content/res/Resources:getString	(I)Ljava/lang/String;
    //   182: iconst_0
    //   183: iconst_4
    //   184: invokevirtual 77	java/lang/String:substring	(II)Ljava/lang/String;
    //   187: invokevirtual 81	java/lang/String:length	()I
    //   190: iconst_0
    //   191: iadd
    //   192: aload_0
    //   193: invokevirtual 85	android/content/Context:getPackageName	()Ljava/lang/String;
    //   196: iconst_4
    //   197: invokevirtual 89	java/lang/String:codePointAt	(I)I
    //   200: bipush 106
    //   202: iadd
    //   203: aload_0
    //   204: invokevirtual 64	android/content/Context:getResources	()Landroid/content/res/Resources;
    //   207: ldc_w 523
    //   210: invokevirtual 71	android/content/res/Resources:getString	(I)Ljava/lang/String;
    //   213: iconst_0
    //   214: bipush 13
    //   216: invokevirtual 77	java/lang/String:substring	(II)Ljava/lang/String;
    //   219: bipush 9
    //   221: invokevirtual 89	java/lang/String:codePointAt	(I)I
    //   224: sipush 206
    //   227: isub
    //   228: i2c
    //   229: invokestatic 122	o/O:ˋ	(IIC)Ljava/lang/Object;
    //   232: checkcast 124	java/lang/Class
    //   235: ldc_w 524
    //   238: aconst_null
    //   239: invokevirtual 130	java/lang/Class:getMethod	(Ljava/lang/String;[Ljava/lang/Class;)Ljava/lang/reflect/Method;
    //   242: aconst_null
    //   243: aconst_null
    //   244: invokevirtual 138	java/lang/reflect/Method:invoke	(Ljava/lang/Object;[Ljava/lang/Object;)Ljava/lang/Object;
    //   247: astore_3
    //   248: iload_2
    //   249: iconst_m1
    //   250: if_icmpne +6 -> 256
    //   253: goto -244 -> 9
    //   256: goto -180 -> 76
    //   259: getstatic 32	o/Ix:ʾ	I
    //   262: bipush 23
    //   264: iadd
    //   265: istore_1
    //   266: iload_1
    //   267: sipush 128
    //   270: irem
    //   271: putstatic 34	o/Ix:ˈ	I
    //   274: iload_1
    //   275: iconst_2
    //   276: irem
    //   277: ifeq +6 -> 283
    //   280: goto -198 -> 82
    //   283: goto -201 -> 82
    //   286: iload_1
    //   287: lookupswitch	default:+25->312, 0:+-176->111, 43:+-238->49
    //   312: goto -201 -> 111
    //   315: goto +20 -> 335
    //   318: astore_3
    //   319: aload_3
    //   320: invokevirtual 113	java/lang/Throwable:getCause	()Ljava/lang/Throwable;
    //   323: astore 5
    //   325: aload 5
    //   327: ifnull +6 -> 333
    //   330: aload 5
    //   332: athrow
    //   333: aload_3
    //   334: athrow
    //   335: aload_0
    //   336: invokevirtual 55	android/content/Context:getApplicationInfo	()Landroid/content/pm/ApplicationInfo;
    //   339: getfield 60	android/content/pm/ApplicationInfo:targetSdkVersion	I
    //   342: bipush 21
    //   344: isub
    //   345: aload_0
    //   346: invokevirtual 85	android/content/Context:getPackageName	()Ljava/lang/String;
    //   349: invokevirtual 81	java/lang/String:length	()I
    //   352: sipush 211
    //   355: iadd
    //   356: aload_0
    //   357: invokevirtual 64	android/content/Context:getResources	()Landroid/content/res/Resources;
    //   360: ldc_w 525
    //   363: invokevirtual 71	android/content/res/Resources:getString	(I)Ljava/lang/String;
    //   366: iconst_0
    //   367: iconst_4
    //   368: invokevirtual 77	java/lang/String:substring	(II)Ljava/lang/String;
    //   371: iconst_2
    //   372: invokevirtual 89	java/lang/String:codePointAt	(I)I
    //   375: bipush 11
    //   377: isub
    //   378: i2c
    //   379: invokestatic 122	o/O:ˋ	(IIC)Ljava/lang/Object;
    //   382: checkcast 124	java/lang/Class
    //   385: ldc_w 526
    //   388: iconst_1
    //   389: anewarray 124	java/lang/Class
    //   392: dup
    //   393: iconst_0
    //   394: getstatic 530	java/lang/Boolean:TYPE	Ljava/lang/Class;
    //   397: aastore
    //   398: invokevirtual 130	java/lang/Class:getMethod	(Ljava/lang/String;[Ljava/lang/Class;)Ljava/lang/reflect/Method;
    //   401: aload_3
    //   402: iconst_1
    //   403: anewarray 132	java/lang/Object
    //   406: dup
    //   407: iconst_0
    //   408: iload 4
    //   410: invokestatic 534	java/lang/Boolean:valueOf	(Z)Ljava/lang/Boolean;
    //   413: aastore
    //   414: invokevirtual 138	java/lang/reflect/Method:invoke	(Ljava/lang/Object;[Ljava/lang/Object;)Ljava/lang/Object;
    //   417: pop
    //   418: return
    //   419: iconst_0
    //   420: istore_1
    //   421: goto -338 -> 83
    //   424: iload_2
    //   425: iconst_m1
    //   426: if_icmpne +6 -> 432
    //   429: goto -10 -> 419
    //   432: goto -285 -> 147
    //   435: aload_0
    //   436: iload_1
    //   437: iload_2
    //   438: aload_3
    //   439: invokespecial 536	o/Y:onActivityResult	(IILandroid/content/Intent;)V
    //   442: iload_1
    //   443: lookupswitch	default:+41->484, 10:+-19->424, 11:+-410->33, 18:+-291->152, 25:+159->602
    //   484: return
    //   485: goto +20 -> 505
    //   488: astore_3
    //   489: aload_3
    //   490: invokevirtual 113	java/lang/Throwable:getCause	()Ljava/lang/Throwable;
    //   493: astore 5
    //   495: aload 5
    //   497: ifnull +6 -> 503
    //   500: aload 5
    //   502: athrow
    //   503: aload_3
    //   504: athrow
    //   505: aload_0
    //   506: invokevirtual 85	android/content/Context:getPackageName	()Ljava/lang/String;
    //   509: invokevirtual 81	java/lang/String:length	()I
    //   512: bipush 7
    //   514: isub
    //   515: aload_0
    //   516: invokevirtual 64	android/content/Context:getResources	()Landroid/content/res/Resources;
    //   519: ldc_w 537
    //   522: invokevirtual 71	android/content/res/Resources:getString	(I)Ljava/lang/String;
    //   525: iconst_0
    //   526: bipush 8
    //   528: invokevirtual 77	java/lang/String:substring	(II)Ljava/lang/String;
    //   531: iconst_3
    //   532: invokevirtual 89	java/lang/String:codePointAt	(I)I
    //   535: sipush 210
    //   538: iadd
    //   539: aload_0
    //   540: invokevirtual 64	android/content/Context:getResources	()Landroid/content/res/Resources;
    //   543: ldc_w 538
    //   546: invokevirtual 71	android/content/res/Resources:getString	(I)Ljava/lang/String;
    //   549: iconst_0
    //   550: iconst_4
    //   551: invokevirtual 77	java/lang/String:substring	(II)Ljava/lang/String;
    //   554: invokevirtual 81	java/lang/String:length	()I
    //   557: iconst_4
    //   558: isub
    //   559: i2c
    //   560: invokestatic 122	o/O:ˋ	(IIC)Ljava/lang/Object;
    //   563: checkcast 124	java/lang/Class
    //   566: ldc_w 526
    //   569: iconst_1
    //   570: anewarray 124	java/lang/Class
    //   573: dup
    //   574: iconst_0
    //   575: getstatic 530	java/lang/Boolean:TYPE	Ljava/lang/Class;
    //   578: aastore
    //   579: invokevirtual 130	java/lang/Class:getMethod	(Ljava/lang/String;[Ljava/lang/Class;)Ljava/lang/reflect/Method;
    //   582: aload_3
    //   583: iconst_1
    //   584: anewarray 132	java/lang/Object
    //   587: dup
    //   588: iconst_0
    //   589: iload 4
    //   591: invokestatic 534	java/lang/Boolean:valueOf	(Z)Ljava/lang/Boolean;
    //   594: aastore
    //   595: invokevirtual 138	java/lang/reflect/Method:invoke	(Ljava/lang/Object;[Ljava/lang/Object;)Ljava/lang/Object;
    //   598: pop
    //   599: goto -340 -> 259
    //   602: goto +20 -> 622
    //   605: astore_3
    //   606: aload_3
    //   607: invokevirtual 113	java/lang/Throwable:getCause	()Ljava/lang/Throwable;
    //   610: astore 5
    //   612: aload 5
    //   614: ifnull +6 -> 620
    //   617: aload 5
    //   619: athrow
    //   620: aload_3
    //   621: athrow
    //   622: aload_0
    //   623: invokevirtual 64	android/content/Context:getResources	()Landroid/content/res/Resources;
    //   626: ldc_w 539
    //   629: invokevirtual 71	android/content/res/Resources:getString	(I)Ljava/lang/String;
    //   632: iconst_0
    //   633: iconst_5
    //   634: invokevirtual 77	java/lang/String:substring	(II)Ljava/lang/String;
    //   637: iconst_3
    //   638: invokevirtual 89	java/lang/String:codePointAt	(I)I
    //   641: bipush 8
    //   643: isub
    //   644: aload_0
    //   645: invokevirtual 64	android/content/Context:getResources	()Landroid/content/res/Resources;
    //   648: ldc_w 540
    //   651: invokevirtual 71	android/content/res/Resources:getString	(I)Ljava/lang/String;
    //   654: iconst_0
    //   655: iconst_4
    //   656: invokevirtual 77	java/lang/String:substring	(II)Ljava/lang/String;
    //   659: iconst_1
    //   660: invokevirtual 89	java/lang/String:codePointAt	(I)I
    //   663: sipush 196
    //   666: iadd
    //   667: aload_0
    //   668: invokevirtual 64	android/content/Context:getResources	()Landroid/content/res/Resources;
    //   671: ldc_w 541
    //   674: invokevirtual 71	android/content/res/Resources:getString	(I)Ljava/lang/String;
    //   677: iconst_0
    //   678: iconst_4
    //   679: invokevirtual 77	java/lang/String:substring	(II)Ljava/lang/String;
    //   682: iconst_0
    //   683: invokevirtual 89	java/lang/String:codePointAt	(I)I
    //   686: iconst_5
    //   687: isub
    //   688: i2c
    //   689: invokestatic 122	o/O:ˋ	(IIC)Ljava/lang/Object;
    //   692: checkcast 124	java/lang/Class
    //   695: ldc_w 524
    //   698: aconst_null
    //   699: invokevirtual 130	java/lang/Class:getMethod	(Ljava/lang/String;[Ljava/lang/Class;)Ljava/lang/reflect/Method;
    //   702: aconst_null
    //   703: aconst_null
    //   704: invokevirtual 138	java/lang/reflect/Method:invoke	(Ljava/lang/Object;[Ljava/lang/Object;)Ljava/lang/Object;
    //   707: astore_3
    //   708: iload_2
    //   709: iconst_m1
    //   710: if_icmpne +6 -> 716
    //   713: goto -695 -> 18
    //   716: goto -581 -> 135
    // Local variable table:
    //   start	length	slot	name	signature
    //   0	719	0	this	Ix
    //   0	719	1	paramInt1	int
    //   0	719	2	paramInt2	int
    //   0	719	3	paramIntent	android.content.Intent
    //   4	586	4	bool	boolean
    //   160	458	5	localThrowable	Throwable
    // Exception table:
    //   from	to	target	type
    //   489	495	24	java/lang/Exception
    //   500	503	24	java/lang/Exception
    //   503	505	24	java/lang/Exception
    //   606	612	120	java/lang/Exception
    //   617	620	120	java/lang/Exception
    //   620	622	120	java/lang/Exception
    //   172	248	155	finally
    //   335	418	318	finally
    //   505	599	488	finally
    //   622	708	605	finally
  }
  
  /* Error */
  public void onCreate(android.os.Bundle paramBundle)
  {
    // Byte code:
    //   0: goto +787 -> 787
    //   3: bipush 74
    //   5: istore_2
    //   6: goto +9 -> 15
    //   9: bipush 94
    //   11: istore_2
    //   12: goto +636 -> 648
    //   15: iload_2
    //   16: lookupswitch	default:+28->44, 0:+774->790, 74:+956->972
    //   44: goto +746 -> 790
    //   47: new 545	o/uH
    //   50: dup
    //   51: aload_0
    //   52: invokevirtual 85	android/content/Context:getPackageName	()Ljava/lang/String;
    //   55: bipush 8
    //   57: invokevirtual 89	java/lang/String:codePointAt	(I)I
    //   60: bipush 84
    //   62: isub
    //   63: aload_0
    //   64: invokevirtual 85	android/content/Context:getPackageName	()Ljava/lang/String;
    //   67: iconst_2
    //   68: invokevirtual 89	java/lang/String:codePointAt	(I)I
    //   71: bipush 46
    //   73: isub
    //   74: i2c
    //   75: aload_0
    //   76: invokevirtual 85	android/content/Context:getPackageName	()Ljava/lang/String;
    //   79: invokevirtual 81	java/lang/String:length	()I
    //   82: bipush 55
    //   84: iadd
    //   85: invokestatic 93	o/Ix:ॱ	(ICI)Ljava/lang/String;
    //   88: invokevirtual 96	java/lang/String:intern	()Ljava/lang/String;
    //   91: invokespecial 547	o/uH:<init>	(Ljava/lang/String;)V
    //   94: athrow
    //   95: aload_0
    //   96: aload_1
    //   97: invokespecial 549	o/Y:onCreate	(Landroid/os/Bundle;)V
    //   100: aload_0
    //   101: invokevirtual 55	android/content/Context:getApplicationInfo	()Landroid/content/pm/ApplicationInfo;
    //   104: getfield 60	android/content/pm/ApplicationInfo:targetSdkVersion	I
    //   107: bipush 21
    //   109: isub
    //   110: aload_0
    //   111: invokevirtual 55	android/content/Context:getApplicationInfo	()Landroid/content/pm/ApplicationInfo;
    //   114: getfield 60	android/content/pm/ApplicationInfo:targetSdkVersion	I
    //   117: sipush 377
    //   120: iadd
    //   121: aload_0
    //   122: invokevirtual 64	android/content/Context:getResources	()Landroid/content/res/Resources;
    //   125: ldc_w 550
    //   128: invokevirtual 71	android/content/res/Resources:getString	(I)Ljava/lang/String;
    //   131: iconst_0
    //   132: iconst_4
    //   133: invokevirtual 77	java/lang/String:substring	(II)Ljava/lang/String;
    //   136: iconst_1
    //   137: invokevirtual 89	java/lang/String:codePointAt	(I)I
    //   140: bipush 26
    //   142: isub
    //   143: i2c
    //   144: invokestatic 122	o/O:ˋ	(IIC)Ljava/lang/Object;
    //   147: checkcast 124	java/lang/Class
    //   150: ldc_w 524
    //   153: invokevirtual 554	java/lang/Class:getField	(Ljava/lang/String;)Ljava/lang/reflect/Field;
    //   156: aconst_null
    //   157: invokevirtual 560	java/lang/reflect/Field:get	(Ljava/lang/Object;)Ljava/lang/Object;
    //   160: astore_1
    //   161: goto +17 -> 178
    //   164: astore_1
    //   165: aload_1
    //   166: invokevirtual 113	java/lang/Throwable:getCause	()Ljava/lang/Throwable;
    //   169: astore_3
    //   170: aload_3
    //   171: ifnull +5 -> 176
    //   174: aload_3
    //   175: athrow
    //   176: aload_1
    //   177: athrow
    //   178: aload_0
    //   179: invokevirtual 64	android/content/Context:getResources	()Landroid/content/res/Resources;
    //   182: ldc_w 561
    //   185: invokevirtual 71	android/content/res/Resources:getString	(I)Ljava/lang/String;
    //   188: bipush 35
    //   190: bipush 40
    //   192: invokevirtual 77	java/lang/String:substring	(II)Ljava/lang/String;
    //   195: iconst_2
    //   196: invokevirtual 89	java/lang/String:codePointAt	(I)I
    //   199: sipush 232
    //   202: isub
    //   203: aload_0
    //   204: invokevirtual 55	android/content/Context:getApplicationInfo	()Landroid/content/pm/ApplicationInfo;
    //   207: getfield 60	android/content/pm/ApplicationInfo:targetSdkVersion	I
    //   210: sipush 381
    //   213: iadd
    //   214: aload_0
    //   215: invokevirtual 55	android/content/Context:getApplicationInfo	()Landroid/content/pm/ApplicationInfo;
    //   218: getfield 60	android/content/pm/ApplicationInfo:targetSdkVersion	I
    //   221: ldc_w 562
    //   224: iadd
    //   225: i2c
    //   226: invokestatic 122	o/O:ˋ	(IIC)Ljava/lang/Object;
    //   229: checkcast 124	java/lang/Class
    //   232: ldc_w 526
    //   235: aconst_null
    //   236: invokevirtual 130	java/lang/Class:getMethod	(Ljava/lang/String;[Ljava/lang/Class;)Ljava/lang/reflect/Method;
    //   239: aload_1
    //   240: aconst_null
    //   241: invokevirtual 138	java/lang/reflect/Method:invoke	(Ljava/lang/Object;[Ljava/lang/Object;)Ljava/lang/Object;
    //   244: astore_1
    //   245: goto +17 -> 262
    //   248: astore_1
    //   249: aload_1
    //   250: invokevirtual 113	java/lang/Throwable:getCause	()Ljava/lang/Throwable;
    //   253: astore_3
    //   254: aload_3
    //   255: ifnull +5 -> 260
    //   258: aload_3
    //   259: athrow
    //   260: aload_1
    //   261: athrow
    //   262: aload_0
    //   263: invokevirtual 55	android/content/Context:getApplicationInfo	()Landroid/content/pm/ApplicationInfo;
    //   266: getfield 60	android/content/pm/ApplicationInfo:targetSdkVersion	I
    //   269: bipush 21
    //   271: isub
    //   272: aload_0
    //   273: invokevirtual 55	android/content/Context:getApplicationInfo	()Landroid/content/pm/ApplicationInfo;
    //   276: getfield 60	android/content/pm/ApplicationInfo:targetSdkVersion	I
    //   279: sipush 377
    //   282: iadd
    //   283: aload_0
    //   284: invokevirtual 55	android/content/Context:getApplicationInfo	()Landroid/content/pm/ApplicationInfo;
    //   287: getfield 60	android/content/pm/ApplicationInfo:targetSdkVersion	I
    //   290: bipush 25
    //   292: isub
    //   293: i2c
    //   294: invokestatic 122	o/O:ˋ	(IIC)Ljava/lang/Object;
    //   297: checkcast 124	java/lang/Class
    //   300: ldc_w 564
    //   303: aconst_null
    //   304: invokevirtual 130	java/lang/Class:getMethod	(Ljava/lang/String;[Ljava/lang/Class;)Ljava/lang/reflect/Method;
    //   307: aload_1
    //   308: aconst_null
    //   309: invokevirtual 138	java/lang/reflect/Method:invoke	(Ljava/lang/Object;[Ljava/lang/Object;)Ljava/lang/Object;
    //   312: checkcast 73	java/lang/String
    //   315: astore_1
    //   316: aload_0
    //   317: aload_1
    //   318: invokespecial 566	o/Ix:ˋ	(Ljava/lang/String;)V
    //   321: aload_0
    //   322: getfield 570	o/Ix:ॱˊ	Landroid/databinding/ViewDataBinding;
    //   325: astore_1
    //   326: aconst_null
    //   327: arraylength
    //   328: istore_2
    //   329: aload_1
    //   330: ifnull +6 -> 336
    //   333: goto +303 -> 636
    //   336: goto +630 -> 966
    //   339: aload_0
    //   340: aload_1
    //   341: invokespecial 549	o/Y:onCreate	(Landroid/os/Bundle;)V
    //   344: aload_0
    //   345: invokevirtual 64	android/content/Context:getResources	()Landroid/content/res/Resources;
    //   348: ldc_w 571
    //   351: invokevirtual 71	android/content/res/Resources:getString	(I)Ljava/lang/String;
    //   354: iconst_0
    //   355: iconst_4
    //   356: invokevirtual 77	java/lang/String:substring	(II)Ljava/lang/String;
    //   359: invokevirtual 81	java/lang/String:length	()I
    //   362: iconst_0
    //   363: iadd
    //   364: aload_0
    //   365: invokevirtual 55	android/content/Context:getApplicationInfo	()Landroid/content/pm/ApplicationInfo;
    //   368: getfield 60	android/content/pm/ApplicationInfo:targetSdkVersion	I
    //   371: sipush 377
    //   374: iadd
    //   375: aload_0
    //   376: invokevirtual 64	android/content/Context:getResources	()Landroid/content/res/Resources;
    //   379: ldc_w 572
    //   382: invokevirtual 71	android/content/res/Resources:getString	(I)Ljava/lang/String;
    //   385: iconst_0
    //   386: iconst_4
    //   387: invokevirtual 77	java/lang/String:substring	(II)Ljava/lang/String;
    //   390: iconst_3
    //   391: invokevirtual 89	java/lang/String:codePointAt	(I)I
    //   394: bipush 12
    //   396: isub
    //   397: i2c
    //   398: invokestatic 122	o/O:ˋ	(IIC)Ljava/lang/Object;
    //   401: checkcast 124	java/lang/Class
    //   404: ldc_w 524
    //   407: invokevirtual 554	java/lang/Class:getField	(Ljava/lang/String;)Ljava/lang/reflect/Field;
    //   410: aconst_null
    //   411: invokevirtual 560	java/lang/reflect/Field:get	(Ljava/lang/Object;)Ljava/lang/Object;
    //   414: astore_1
    //   415: goto +17 -> 432
    //   418: astore_1
    //   419: aload_1
    //   420: invokevirtual 113	java/lang/Throwable:getCause	()Ljava/lang/Throwable;
    //   423: astore_3
    //   424: aload_3
    //   425: ifnull +5 -> 430
    //   428: aload_3
    //   429: athrow
    //   430: aload_1
    //   431: athrow
    //   432: aload_0
    //   433: invokevirtual 64	android/content/Context:getResources	()Landroid/content/res/Resources;
    //   436: ldc_w 573
    //   439: invokevirtual 71	android/content/res/Resources:getString	(I)Ljava/lang/String;
    //   442: iconst_0
    //   443: iconst_4
    //   444: invokevirtual 77	java/lang/String:substring	(II)Ljava/lang/String;
    //   447: iconst_2
    //   448: invokevirtual 89	java/lang/String:codePointAt	(I)I
    //   451: iconst_4
    //   452: isub
    //   453: aload_0
    //   454: invokevirtual 64	android/content/Context:getResources	()Landroid/content/res/Resources;
    //   457: ldc_w 574
    //   460: invokevirtual 71	android/content/res/Resources:getString	(I)Ljava/lang/String;
    //   463: bipush 22
    //   465: bipush 23
    //   467: invokevirtual 77	java/lang/String:substring	(II)Ljava/lang/String;
    //   470: iconst_0
    //   471: invokevirtual 89	java/lang/String:codePointAt	(I)I
    //   474: sipush 374
    //   477: iadd
    //   478: aload_0
    //   479: invokevirtual 64	android/content/Context:getResources	()Landroid/content/res/Resources;
    //   482: ldc_w 575
    //   485: invokevirtual 71	android/content/res/Resources:getString	(I)Ljava/lang/String;
    //   488: bipush 6
    //   490: bipush 16
    //   492: invokevirtual 77	java/lang/String:substring	(II)Ljava/lang/String;
    //   495: invokevirtual 81	java/lang/String:length	()I
    //   498: ldc_w 576
    //   501: iadd
    //   502: i2c
    //   503: invokestatic 122	o/O:ˋ	(IIC)Ljava/lang/Object;
    //   506: checkcast 124	java/lang/Class
    //   509: ldc_w 526
    //   512: aconst_null
    //   513: invokevirtual 130	java/lang/Class:getMethod	(Ljava/lang/String;[Ljava/lang/Class;)Ljava/lang/reflect/Method;
    //   516: aload_1
    //   517: aconst_null
    //   518: invokevirtual 138	java/lang/reflect/Method:invoke	(Ljava/lang/Object;[Ljava/lang/Object;)Ljava/lang/Object;
    //   521: astore_1
    //   522: goto +17 -> 539
    //   525: astore_1
    //   526: aload_1
    //   527: invokevirtual 113	java/lang/Throwable:getCause	()Ljava/lang/Throwable;
    //   530: astore_3
    //   531: aload_3
    //   532: ifnull +5 -> 537
    //   535: aload_3
    //   536: athrow
    //   537: aload_1
    //   538: athrow
    //   539: aload_0
    //   540: invokevirtual 64	android/content/Context:getResources	()Landroid/content/res/Resources;
    //   543: ldc_w 577
    //   546: invokevirtual 71	android/content/res/Resources:getString	(I)Ljava/lang/String;
    //   549: iconst_0
    //   550: bipush 10
    //   552: invokevirtual 77	java/lang/String:substring	(II)Ljava/lang/String;
    //   555: invokevirtual 81	java/lang/String:length	()I
    //   558: bipush 6
    //   560: isub
    //   561: aload_0
    //   562: invokevirtual 64	android/content/Context:getResources	()Landroid/content/res/Resources;
    //   565: ldc_w 578
    //   568: invokevirtual 71	android/content/res/Resources:getString	(I)Ljava/lang/String;
    //   571: bipush 20
    //   573: bipush 21
    //   575: invokevirtual 77	java/lang/String:substring	(II)Ljava/lang/String;
    //   578: invokevirtual 81	java/lang/String:length	()I
    //   581: sipush 401
    //   584: iadd
    //   585: aload_0
    //   586: invokevirtual 55	android/content/Context:getApplicationInfo	()Landroid/content/pm/ApplicationInfo;
    //   589: getfield 60	android/content/pm/ApplicationInfo:targetSdkVersion	I
    //   592: bipush 25
    //   594: isub
    //   595: i2c
    //   596: invokestatic 122	o/O:ˋ	(IIC)Ljava/lang/Object;
    //   599: checkcast 124	java/lang/Class
    //   602: ldc_w 564
    //   605: aconst_null
    //   606: invokevirtual 130	java/lang/Class:getMethod	(Ljava/lang/String;[Ljava/lang/Class;)Ljava/lang/reflect/Method;
    //   609: aload_1
    //   610: aconst_null
    //   611: invokevirtual 138	java/lang/reflect/Method:invoke	(Ljava/lang/Object;[Ljava/lang/Object;)Ljava/lang/Object;
    //   614: checkcast 73	java/lang/String
    //   617: astore_1
    //   618: aload_0
    //   619: aload_1
    //   620: invokespecial 566	o/Ix:ˋ	(Ljava/lang/String;)V
    //   623: aload_0
    //   624: getfield 570	o/Ix:ॱˊ	Landroid/databinding/ViewDataBinding;
    //   627: ifnull +6 -> 633
    //   630: goto +49 -> 679
    //   633: goto +339 -> 972
    //   636: bipush 8
    //   638: istore_2
    //   639: goto +116 -> 755
    //   642: goto +223 -> 865
    //   645: goto +327 -> 972
    //   648: iload_2
    //   649: lookupswitch	default:+27->676, 69:+-310->339, 94:+-554->95
    //   676: goto -581 -> 95
    //   679: aload_0
    //   680: getfield 570	o/Ix:ॱˊ	Landroid/databinding/ViewDataBinding;
    //   683: astore_1
    //   684: aload_1
    //   685: aload_0
    //   686: invokevirtual 64	android/content/Context:getResources	()Landroid/content/res/Resources;
    //   689: ldc_w 579
    //   692: invokevirtual 71	android/content/res/Resources:getString	(I)Ljava/lang/String;
    //   695: bipush 8
    //   697: bipush 13
    //   699: invokevirtual 77	java/lang/String:substring	(II)Ljava/lang/String;
    //   702: invokevirtual 81	java/lang/String:length	()I
    //   705: bipush 15
    //   707: iadd
    //   708: aload_0
    //   709: invokevirtual 85	android/content/Context:getPackageName	()Ljava/lang/String;
    //   712: iconst_5
    //   713: invokevirtual 89	java/lang/String:codePointAt	(I)I
    //   716: bipush 114
    //   718: isub
    //   719: i2c
    //   720: aload_0
    //   721: invokevirtual 55	android/content/Context:getApplicationInfo	()Landroid/content/pm/ApplicationInfo;
    //   724: getfield 60	android/content/pm/ApplicationInfo:targetSdkVersion	I
    //   727: bipush 17
    //   729: isub
    //   730: invokestatic 93	o/Ix:ॱ	(ICI)Ljava/lang/String;
    //   733: invokevirtual 96	java/lang/String:intern	()Ljava/lang/String;
    //   736: invokestatic 146	o/vq:ˋ	(Ljava/lang/Object;Ljava/lang/String;)V
    //   739: aload_1
    //   740: invokevirtual 584	android/databinding/ViewDataBinding:ᐝ	()Landroid/view/View;
    //   743: instanceof 586
    //   746: ifeq +6 -> 752
    //   749: goto +88 -> 837
    //   752: goto -749 -> 3
    //   755: iload_2
    //   756: lookupswitch	default:+28->784, 8:+-77->679, 99:+216->972
    //   784: goto -105 -> 679
    //   787: goto +152 -> 939
    //   790: getstatic 34	o/Ix:ˈ	I
    //   793: bipush 109
    //   795: iadd
    //   796: istore_2
    //   797: iload_2
    //   798: sipush 128
    //   801: irem
    //   802: putstatic 32	o/Ix:ʾ	I
    //   805: iload_2
    //   806: iconst_2
    //   807: irem
    //   808: ifne +6 -> 814
    //   811: goto -169 -> 642
    //   814: goto +51 -> 865
    //   817: astore_1
    //   818: aload_1
    //   819: athrow
    //   820: aload_0
    //   821: aload_1
    //   822: checkcast 586	android/widget/RelativeLayout
    //   825: putfield 588	o/Ix:ॱˎ	Landroid/widget/RelativeLayout;
    //   828: goto -183 -> 645
    //   831: bipush 69
    //   833: istore_2
    //   834: goto -186 -> 648
    //   837: iconst_0
    //   838: istore_2
    //   839: goto -824 -> 15
    //   842: getstatic 34	o/Ix:ˈ	I
    //   845: bipush 37
    //   847: iadd
    //   848: istore_2
    //   849: iload_2
    //   850: sipush 128
    //   853: irem
    //   854: putstatic 32	o/Ix:ʾ	I
    //   857: iload_2
    //   858: iconst_2
    //   859: irem
    //   860: ifne +4 -> 864
    //   863: return
    //   864: return
    //   865: aload_0
    //   866: getfield 570	o/Ix:ॱˊ	Landroid/databinding/ViewDataBinding;
    //   869: astore_1
    //   870: aload_0
    //   871: invokevirtual 64	android/content/Context:getResources	()Landroid/content/res/Resources;
    //   874: astore_3
    //   875: aload_1
    //   876: aload_3
    //   877: ldc_w 589
    //   880: invokevirtual 71	android/content/res/Resources:getString	(I)Ljava/lang/String;
    //   883: iconst_0
    //   884: iconst_4
    //   885: invokevirtual 77	java/lang/String:substring	(II)Ljava/lang/String;
    //   888: invokevirtual 81	java/lang/String:length	()I
    //   891: bipush 16
    //   893: iadd
    //   894: aload_0
    //   895: invokevirtual 85	android/content/Context:getPackageName	()Ljava/lang/String;
    //   898: invokevirtual 81	java/lang/String:length	()I
    //   901: bipush 11
    //   903: isub
    //   904: i2c
    //   905: aload_0
    //   906: invokevirtual 55	android/content/Context:getApplicationInfo	()Landroid/content/pm/ApplicationInfo;
    //   909: getfield 60	android/content/pm/ApplicationInfo:targetSdkVersion	I
    //   912: bipush 17
    //   914: isub
    //   915: invokestatic 93	o/Ix:ॱ	(ICI)Ljava/lang/String;
    //   918: invokevirtual 96	java/lang/String:intern	()Ljava/lang/String;
    //   921: invokestatic 146	o/vq:ˋ	(Ljava/lang/Object;Ljava/lang/String;)V
    //   924: aload_1
    //   925: invokevirtual 584	android/databinding/ViewDataBinding:ᐝ	()Landroid/view/View;
    //   928: astore_1
    //   929: aload_1
    //   930: ifnonnull +6 -> 936
    //   933: goto -886 -> 47
    //   936: goto -116 -> 820
    //   939: getstatic 34	o/Ix:ˈ	I
    //   942: bipush 63
    //   944: iadd
    //   945: istore_2
    //   946: iload_2
    //   947: sipush 128
    //   950: irem
    //   951: putstatic 32	o/Ix:ʾ	I
    //   954: iload_2
    //   955: iconst_2
    //   956: irem
    //   957: ifne +6 -> 963
    //   960: goto -951 -> 9
    //   963: goto -132 -> 831
    //   966: bipush 99
    //   968: istore_2
    //   969: goto -214 -> 755
    //   972: aload_0
    //   973: new 497	o/IC
    //   976: dup
    //   977: aload_0
    //   978: checkcast 51	android/content/Context
    //   981: invokespecial 592	o/IC:<init>	(Landroid/content/Context;)V
    //   984: invokevirtual 595	o/Ix:ॱ	(Lo/IC;)V
    //   987: goto -145 -> 842
    //   990: astore_1
    //   991: aload_1
    //   992: athrow
    // Local variable table:
    //   start	length	slot	name	signature
    //   0	993	0	this	Ix
    //   0	993	1	paramBundle	android.os.Bundle
    //   5	964	2	i	int
    //   169	708	3	localObject	Object
    // Exception table:
    //   from	to	target	type
    //   178	245	164	finally
    //   262	316	248	finally
    //   432	522	418	finally
    //   539	618	525	finally
    //   939	946	817	java/lang/Exception
    //   946	954	817	java/lang/Exception
    //   865	870	990	java/lang/Exception
    //   870	875	990	java/lang/Exception
  }
  
  /* Error */
  public void onPause()
  {
    // Byte code:
    //   0: goto +258 -> 258
    //   3: aload_0
    //   4: invokespecial 598	o/Y:onPause	()V
    //   7: goto +17 -> 24
    //   10: astore_2
    //   11: aload_2
    //   12: invokevirtual 113	java/lang/Throwable:getCause	()Ljava/lang/Throwable;
    //   15: astore_3
    //   16: aload_3
    //   17: ifnull +5 -> 22
    //   20: aload_3
    //   21: athrow
    //   22: aload_2
    //   23: athrow
    //   24: aload_0
    //   25: invokevirtual 64	android/content/Context:getResources	()Landroid/content/res/Resources;
    //   28: ldc_w 599
    //   31: invokevirtual 71	android/content/res/Resources:getString	(I)Ljava/lang/String;
    //   34: iconst_0
    //   35: iconst_5
    //   36: invokevirtual 77	java/lang/String:substring	(II)Ljava/lang/String;
    //   39: iconst_1
    //   40: invokevirtual 89	java/lang/String:codePointAt	(I)I
    //   43: bipush 93
    //   45: isub
    //   46: aload_0
    //   47: invokevirtual 64	android/content/Context:getResources	()Landroid/content/res/Resources;
    //   50: ldc_w 600
    //   53: invokevirtual 71	android/content/res/Resources:getString	(I)Ljava/lang/String;
    //   56: iconst_0
    //   57: bipush 8
    //   59: invokevirtual 77	java/lang/String:substring	(II)Ljava/lang/String;
    //   62: iconst_2
    //   63: invokevirtual 89	java/lang/String:codePointAt	(I)I
    //   66: sipush 256
    //   69: iadd
    //   70: aload_0
    //   71: invokevirtual 64	android/content/Context:getResources	()Landroid/content/res/Resources;
    //   74: ldc_w 601
    //   77: invokevirtual 71	android/content/res/Resources:getString	(I)Ljava/lang/String;
    //   80: iconst_0
    //   81: iconst_4
    //   82: invokevirtual 77	java/lang/String:substring	(II)Ljava/lang/String;
    //   85: iconst_2
    //   86: invokevirtual 89	java/lang/String:codePointAt	(I)I
    //   89: sipush 14777
    //   92: iadd
    //   93: i2c
    //   94: invokestatic 122	o/O:ˋ	(IIC)Ljava/lang/Object;
    //   97: checkcast 124	java/lang/Class
    //   100: ldc_w 602
    //   103: aconst_null
    //   104: invokevirtual 130	java/lang/Class:getMethod	(Ljava/lang/String;[Ljava/lang/Class;)Ljava/lang/reflect/Method;
    //   107: aconst_null
    //   108: aconst_null
    //   109: invokevirtual 138	java/lang/reflect/Method:invoke	(Ljava/lang/Object;[Ljava/lang/Object;)Ljava/lang/Object;
    //   112: astore_2
    //   113: aload_0
    //   114: checkcast 604	android/app/Activity
    //   117: astore_3
    //   118: goto +17 -> 135
    //   121: astore_2
    //   122: aload_2
    //   123: invokevirtual 113	java/lang/Throwable:getCause	()Ljava/lang/Throwable;
    //   126: astore_3
    //   127: aload_3
    //   128: ifnull +5 -> 133
    //   131: aload_3
    //   132: athrow
    //   133: aload_2
    //   134: athrow
    //   135: aload_0
    //   136: invokevirtual 64	android/content/Context:getResources	()Landroid/content/res/Resources;
    //   139: ldc_w 605
    //   142: invokevirtual 71	android/content/res/Resources:getString	(I)Ljava/lang/String;
    //   145: iconst_0
    //   146: iconst_4
    //   147: invokevirtual 77	java/lang/String:substring	(II)Ljava/lang/String;
    //   150: invokevirtual 81	java/lang/String:length	()I
    //   153: iconst_0
    //   154: iadd
    //   155: aload_0
    //   156: invokevirtual 55	android/content/Context:getApplicationInfo	()Landroid/content/pm/ApplicationInfo;
    //   159: getfield 60	android/content/pm/ApplicationInfo:targetSdkVersion	I
    //   162: sipush 242
    //   165: iadd
    //   166: aload_0
    //   167: invokevirtual 85	android/content/Context:getPackageName	()Ljava/lang/String;
    //   170: iconst_2
    //   171: invokevirtual 89	java/lang/String:codePointAt	(I)I
    //   174: sipush 14742
    //   177: iadd
    //   178: i2c
    //   179: invokestatic 122	o/O:ˋ	(IIC)Ljava/lang/Object;
    //   182: checkcast 124	java/lang/Class
    //   185: ldc_w 524
    //   188: iconst_1
    //   189: anewarray 124	java/lang/Class
    //   192: dup
    //   193: iconst_0
    //   194: ldc_w 604
    //   197: aastore
    //   198: invokevirtual 130	java/lang/Class:getMethod	(Ljava/lang/String;[Ljava/lang/Class;)Ljava/lang/reflect/Method;
    //   201: aload_2
    //   202: iconst_1
    //   203: anewarray 132	java/lang/Object
    //   206: dup
    //   207: iconst_0
    //   208: aload_3
    //   209: aastore
    //   210: invokevirtual 138	java/lang/reflect/Method:invoke	(Ljava/lang/Object;[Ljava/lang/Object;)Ljava/lang/Object;
    //   213: pop
    //   214: invokestatic 610	o/zp:ॱ	()Lo/zp;
    //   217: astore_2
    //   218: aload_2
    //   219: aload_0
    //   220: invokevirtual 613	o/zp:ॱ	(Ljava/lang/Object;)V
    //   223: goto +9 -> 232
    //   226: astore_2
    //   227: aload_2
    //   228: athrow
    //   229: goto -226 -> 3
    //   232: getstatic 32	o/Ix:ʾ	I
    //   235: bipush 17
    //   237: iadd
    //   238: istore_1
    //   239: iload_1
    //   240: sipush 128
    //   243: irem
    //   244: putstatic 34	o/Ix:ˈ	I
    //   247: iload_1
    //   248: iconst_2
    //   249: irem
    //   250: ifeq +6 -> 256
    //   253: goto +4 -> 257
    //   256: return
    //   257: return
    //   258: getstatic 32	o/Ix:ʾ	I
    //   261: bipush 43
    //   263: iadd
    //   264: istore_1
    //   265: iload_1
    //   266: sipush 128
    //   269: irem
    //   270: putstatic 34	o/Ix:ˈ	I
    //   273: iload_1
    //   274: iconst_2
    //   275: irem
    //   276: ifeq +6 -> 282
    //   279: goto -50 -> 229
    //   282: goto -279 -> 3
    //   285: astore_2
    //   286: aload_2
    //   287: athrow
    // Local variable table:
    //   start	length	slot	name	signature
    //   0	288	0	this	Ix
    //   238	38	1	i	int
    //   10	13	2	localObject1	Object
    //   112	1	2	localObject2	Object
    //   121	81	2	localObject3	Object
    //   217	2	2	localZp	zp
    //   226	2	2	localException1	Exception
    //   285	2	2	localException2	Exception
    //   15	194	3	localObject4	Object
    // Exception table:
    //   from	to	target	type
    //   24	113	10	finally
    //   135	214	121	finally
    //   11	16	226	java/lang/Exception
    //   20	22	226	java/lang/Exception
    //   22	24	226	java/lang/Exception
    //   113	118	226	java/lang/Exception
    //   122	127	285	java/lang/Exception
    //   131	133	285	java/lang/Exception
    //   133	135	285	java/lang/Exception
    //   214	218	285	java/lang/Exception
    //   218	223	285	java/lang/Exception
  }
  
  /* Error */
  public void onResume()
  {
    // Byte code:
    //   0: goto +155 -> 155
    //   3: astore_2
    //   4: aload_2
    //   5: athrow
    //   6: aload_0
    //   7: invokespecial 616	o/Y:onResume	()V
    //   10: invokestatic 610	o/zp:ॱ	()Lo/zp;
    //   13: astore_2
    //   14: aload_2
    //   15: aload_0
    //   16: invokevirtual 618	o/zp:ˋ	(Ljava/lang/Object;)V
    //   19: getstatic 623	o/Gz:ˎ	Lo/Gz$ˊ;
    //   22: astore_2
    //   23: aload_0
    //   24: checkcast 51	android/content/Context
    //   27: astore_3
    //   28: aload_2
    //   29: aload_3
    //   30: invokevirtual 628	o/Gz$ˊ:ˎ	(Landroid/content/Context;)Lo/Gz;
    //   33: astore_2
    //   34: aload_2
    //   35: invokevirtual 630	o/Gz:ˋ	()V
    //   38: aload_0
    //   39: invokevirtual 633	o/Ix:ॱˋ	()Lo/V;
    //   42: checkcast 635	o/Iu$iF
    //   45: invokeinterface 637 1 0
    //   50: return
    //   51: getstatic 34	o/Ix:ˈ	I
    //   54: bipush 11
    //   56: iadd
    //   57: istore_1
    //   58: iload_1
    //   59: sipush 128
    //   62: irem
    //   63: putstatic 32	o/Ix:ʾ	I
    //   66: iload_1
    //   67: iconst_2
    //   68: irem
    //   69: ifne +6 -> 75
    //   72: goto +6 -> 78
    //   75: goto +83 -> 158
    //   78: iconst_0
    //   79: istore_1
    //   80: goto +48 -> 128
    //   83: astore_2
    //   84: aload_2
    //   85: athrow
    //   86: aload_0
    //   87: invokespecial 616	o/Y:onResume	()V
    //   90: invokestatic 610	o/zp:ॱ	()Lo/zp;
    //   93: aload_0
    //   94: invokevirtual 618	o/zp:ˋ	(Ljava/lang/Object;)V
    //   97: getstatic 623	o/Gz:ˎ	Lo/Gz$ˊ;
    //   100: aload_0
    //   101: checkcast 51	android/content/Context
    //   104: invokevirtual 628	o/Gz$ˊ:ˎ	(Landroid/content/Context;)Lo/Gz;
    //   107: invokevirtual 630	o/Gz:ˋ	()V
    //   110: aload_0
    //   111: invokevirtual 633	o/Ix:ॱˋ	()Lo/V;
    //   114: checkcast 635	o/Iu$iF
    //   117: invokeinterface 637 1 0
    //   122: bipush 29
    //   124: iconst_0
    //   125: idiv
    //   126: istore_1
    //   127: return
    //   128: iload_1
    //   129: tableswitch	default:+23->152, 0:+-43->86, 1:+-123->6
    //   152: goto -66 -> 86
    //   155: goto -104 -> 51
    //   158: iconst_1
    //   159: istore_1
    //   160: goto -32 -> 128
    // Local variable table:
    //   start	length	slot	name	signature
    //   0	163	0	this	Ix
    //   57	103	1	i	int
    //   3	2	2	localException1	Exception
    //   13	22	2	localObject	Object
    //   83	2	2	localException2	Exception
    //   27	3	3	localContext	Context
    // Exception table:
    //   from	to	target	type
    //   19	23	3	java/lang/Exception
    //   10	14	83	java/lang/Exception
    //   14	19	83	java/lang/Exception
    //   19	23	83	java/lang/Exception
    //   23	28	83	java/lang/Exception
    //   28	34	83	java/lang/Exception
    //   34	50	83	java/lang/Exception
  }
  
  /* Error */
  public void onStart()
  {
    // Byte code:
    //   0: goto +6 -> 6
    //   3: astore_2
    //   4: aload_2
    //   5: athrow
    //   6: goto +10 -> 16
    //   9: bipush 53
    //   11: istore_1
    //   12: goto +34 -> 46
    //   15: return
    //   16: aload_0
    //   17: invokespecial 640	o/Y:onStart	()V
    //   20: aload_0
    //   21: invokevirtual 633	o/Ix:ॱˋ	()Lo/V;
    //   24: checkcast 635	o/Iu$iF
    //   27: new 9	o/Ix$iF
    //   30: dup
    //   31: aload_0
    //   32: invokespecial 641	o/Ix$iF:<init>	(Lo/Ix;)V
    //   35: checkcast 516	android/content/DialogInterface$OnCancelListener
    //   38: invokeinterface 643 2 0
    //   43: goto +45 -> 88
    //   46: iload_1
    //   47: lookupswitch	default:+25->72, 53:+-32->15, 75:+37->84
    //   72: goto +12 -> 84
    //   75: bipush 75
    //   77: istore_1
    //   78: goto -32 -> 46
    //   81: astore_2
    //   82: aload_2
    //   83: athrow
    //   84: aconst_null
    //   85: arraylength
    //   86: istore_1
    //   87: return
    //   88: getstatic 34	o/Ix:ˈ	I
    //   91: istore_1
    //   92: iload_1
    //   93: bipush 35
    //   95: iadd
    //   96: istore_1
    //   97: iload_1
    //   98: sipush 128
    //   101: irem
    //   102: putstatic 32	o/Ix:ʾ	I
    //   105: iload_1
    //   106: iconst_2
    //   107: irem
    //   108: ifne +6 -> 114
    //   111: goto -36 -> 75
    //   114: goto -105 -> 9
    // Local variable table:
    //   start	length	slot	name	signature
    //   0	117	0	this	Ix
    //   11	97	1	i	int
    //   3	2	2	localException1	Exception
    //   81	2	2	localException2	Exception
    // Exception table:
    //   from	to	target	type
    //   88	92	3	java/lang/Exception
    //   97	105	81	java/lang/Exception
  }
  
  public void v_()
  {
    break label61;
    int i = 0;
    break label10;
    label8:
    i = 1;
    switch (i)
    {
    default: 
      break;
      for (;;)
      {
        i = ˈ + 3;
        ʾ = i % 128;
        if (i % 2 == 0) {
          break label8;
        }
        break;
      }
    case 1: 
      label10:
      label61:
      ˊᐝ().v_();
      i = 89 / 0;
      return;
    }
    ˊᐝ().v_();
  }
  
  public void w_()
  {
    for (;;)
    {
      int i = 92 / 0;
      return;
      try
      {
        i = ˈ + 33;
        ʾ = i % 128;
        if (i % 2 != 0)
        {
          break;
          return;
          switch (i)
          {
          }
          continue;
        }
        for (;;)
        {
          ˊᐝ().w_();
          i = ˈ + 113;
          ʾ = i % 128;
          if (i % 2 != 0) {
            break label107;
          }
          i = 47;
          break;
          label107:
          i = 85;
          break;
        }
      }
      catch (Exception localException)
      {
        throw localException;
      }
    }
  }
  
  public void x_()
  {
    break label63;
    int i = 1;
    for (;;)
    {
      ˊᐝ().x_();
      i = null.length;
      break label36;
      i = 0;
      break label66;
      return;
      try
      {
        localIC = ˊᐝ();
      }
      catch (Exception localException1)
      {
        IC localIC;
        label36:
        label63:
        throw localException1;
      }
      try
      {
        localIC.x_();
        i = ˈ + 45;
        ʾ = i % 128;
        if (i % 2 == 0) {
          break;
        }
      }
      catch (Exception localException2)
      {
        throw localException2;
      }
      break label139;
      switch (i)
      {
      case 0: 
      default: 
        return;
        i = 1;
        break;
      case 1: 
        label66:
        throw new NullPointerException();
      }
      label105:
      switch (i)
      {
      }
    }
    for (;;)
    {
      i = 0;
      break label105;
      label139:
      i = ˈ + 43;
      ʾ = i % 128;
      if (i % 2 == 0) {
        break;
      }
    }
  }
  
  public void y_()
  {
    break label57;
    int i = 61;
    break label27;
    throw new NullPointerException();
    for (;;)
    {
      label17:
      i = 40;
      break label27;
      return;
      label27:
      switch (i)
      {
      }
      return;
      label57:
      i = ˈ + 93;
      ʾ = i % 128;
      if (i % 2 == 0) {
        break label17;
      }
      ˊᐝ().y_();
      i = ˈ + 59;
      ʾ = i % 128;
      if (i % 2 == 0) {
        break;
      }
    }
  }
  
  /* Error */
  public void z_()
  {
    // Byte code:
    //   0: goto +66 -> 66
    //   3: iconst_0
    //   4: istore_1
    //   5: goto +21 -> 26
    //   8: aload_0
    //   9: invokevirtual 495	o/Ix:ˊᐝ	()Lo/IC;
    //   12: invokevirtual 658	o/IC:z_	()V
    //   15: bipush 7
    //   17: iconst_0
    //   18: idiv
    //   19: istore_1
    //   20: goto +76 -> 96
    //   23: astore_2
    //   24: aload_2
    //   25: athrow
    //   26: iload_1
    //   27: tableswitch	default:+21->48, 0:+-19->8, 1:+24->51
    //   48: goto -40 -> 8
    //   51: aload_0
    //   52: invokevirtual 495	o/Ix:ˊᐝ	()Lo/IC;
    //   55: astore_2
    //   56: aload_2
    //   57: invokevirtual 658	o/IC:z_	()V
    //   60: goto +36 -> 96
    //   63: astore_2
    //   64: aload_2
    //   65: athrow
    //   66: getstatic 34	o/Ix:ˈ	I
    //   69: istore_1
    //   70: iload_1
    //   71: iconst_5
    //   72: iadd
    //   73: istore_1
    //   74: iload_1
    //   75: sipush 128
    //   78: irem
    //   79: putstatic 32	o/Ix:ʾ	I
    //   82: iload_1
    //   83: iconst_2
    //   84: irem
    //   85: ifne +6 -> 91
    //   88: goto -85 -> 3
    //   91: iconst_1
    //   92: istore_1
    //   93: goto -67 -> 26
    //   96: getstatic 32	o/Ix:ʾ	I
    //   99: bipush 39
    //   101: iadd
    //   102: istore_1
    //   103: iload_1
    //   104: sipush 128
    //   107: irem
    //   108: putstatic 34	o/Ix:ˈ	I
    //   111: iload_1
    //   112: iconst_2
    //   113: irem
    //   114: ifeq +4 -> 118
    //   117: return
    //   118: return
    // Local variable table:
    //   start	length	slot	name	signature
    //   0	119	0	this	Ix
    //   4	110	1	i	int
    //   23	2	2	localException1	Exception
    //   55	2	2	localIC	IC
    //   63	2	2	localException2	Exception
    // Exception table:
    //   from	to	target	type
    //   66	70	23	java/lang/Exception
    //   51	56	63	java/lang/Exception
    //   56	60	63	java/lang/Exception
    //   74	82	63	java/lang/Exception
  }
  
  /* Error */
  @zA(ˎ=org.greenrobot.eventbus.ThreadMode.MAIN)
  public final void ˊ(HR paramHR)
  {
    // Byte code:
    //   0: goto +278 -> 278
    //   3: aload_0
    //   4: invokevirtual 85	android/content/Context:getPackageName	()Ljava/lang/String;
    //   7: iconst_0
    //   8: invokevirtual 89	java/lang/String:codePointAt	(I)I
    //   11: bipush 68
    //   13: iadd
    //   14: aload_0
    //   15: invokevirtual 55	android/content/Context:getApplicationInfo	()Landroid/content/pm/ApplicationInfo;
    //   18: getfield 60	android/content/pm/ApplicationInfo:targetSdkVersion	I
    //   21: bipush 25
    //   23: isub
    //   24: i2c
    //   25: aload_0
    //   26: invokevirtual 64	android/content/Context:getResources	()Landroid/content/res/Resources;
    //   29: ldc_w 667
    //   32: invokevirtual 71	android/content/res/Resources:getString	(I)Ljava/lang/String;
    //   35: bipush 11
    //   37: bipush 16
    //   39: invokevirtual 77	java/lang/String:substring	(II)Ljava/lang/String;
    //   42: invokevirtual 81	java/lang/String:length	()I
    //   45: iconst_4
    //   46: iadd
    //   47: invokestatic 93	o/Ix:ॱ	(ICI)Ljava/lang/String;
    //   50: invokevirtual 96	java/lang/String:intern	()Ljava/lang/String;
    //   53: astore_3
    //   54: new 98	java/lang/StringBuilder
    //   57: dup
    //   58: invokespecial 99	java/lang/StringBuilder:<init>	()V
    //   61: aload_0
    //   62: invokevirtual 85	android/content/Context:getPackageName	()Ljava/lang/String;
    //   65: bipush 7
    //   67: invokevirtual 89	java/lang/String:codePointAt	(I)I
    //   70: sipush 145
    //   73: iadd
    //   74: aload_0
    //   75: invokevirtual 64	android/content/Context:getResources	()Landroid/content/res/Resources;
    //   78: ldc_w 668
    //   81: invokevirtual 71	android/content/res/Resources:getString	(I)Ljava/lang/String;
    //   84: iconst_0
    //   85: bipush 9
    //   87: invokevirtual 77	java/lang/String:substring	(II)Ljava/lang/String;
    //   90: invokevirtual 81	java/lang/String:length	()I
    //   93: sipush 4237
    //   96: iadd
    //   97: i2c
    //   98: aload_0
    //   99: invokevirtual 64	android/content/Context:getResources	()Landroid/content/res/Resources;
    //   102: ldc_w 669
    //   105: invokevirtual 71	android/content/res/Resources:getString	(I)Ljava/lang/String;
    //   108: iconst_0
    //   109: iconst_4
    //   110: invokevirtual 77	java/lang/String:substring	(II)Ljava/lang/String;
    //   113: iconst_2
    //   114: invokevirtual 89	java/lang/String:codePointAt	(I)I
    //   117: bipush 7
    //   119: iadd
    //   120: invokestatic 93	o/Ix:ॱ	(ICI)Ljava/lang/String;
    //   123: invokevirtual 96	java/lang/String:intern	()Ljava/lang/String;
    //   126: invokevirtual 104	java/lang/StringBuilder:append	(Ljava/lang/String;)Ljava/lang/StringBuilder;
    //   129: aload_1
    //   130: invokevirtual 674	o/HR:ॱ	()Lcom/insidesecure/hce/MatrixHCEError;
    //   133: invokevirtual 679	com/insidesecure/hce/MatrixHCEError:name	()Ljava/lang/String;
    //   136: invokevirtual 104	java/lang/StringBuilder:append	(Ljava/lang/String;)Ljava/lang/StringBuilder;
    //   139: invokevirtual 107	java/lang/StringBuilder:toString	()Ljava/lang/String;
    //   142: astore_1
    //   143: goto +17 -> 160
    //   146: astore_1
    //   147: aload_1
    //   148: invokevirtual 113	java/lang/Throwable:getCause	()Ljava/lang/Throwable;
    //   151: astore_3
    //   152: aload_3
    //   153: ifnull +5 -> 158
    //   156: aload_3
    //   157: athrow
    //   158: aload_1
    //   159: athrow
    //   160: aload_0
    //   161: invokevirtual 55	android/content/Context:getApplicationInfo	()Landroid/content/pm/ApplicationInfo;
    //   164: getfield 60	android/content/pm/ApplicationInfo:targetSdkVersion	I
    //   167: bipush 21
    //   169: isub
    //   170: aload_0
    //   171: invokevirtual 55	android/content/Context:getApplicationInfo	()Landroid/content/pm/ApplicationInfo;
    //   174: getfield 60	android/content/pm/ApplicationInfo:targetSdkVersion	I
    //   177: bipush 17
    //   179: iadd
    //   180: aload_0
    //   181: invokevirtual 55	android/content/Context:getApplicationInfo	()Landroid/content/pm/ApplicationInfo;
    //   184: getfield 60	android/content/pm/ApplicationInfo:targetSdkVersion	I
    //   187: ldc_w 680
    //   190: iadd
    //   191: i2c
    //   192: invokestatic 122	o/O:ˋ	(IIC)Ljava/lang/Object;
    //   195: checkcast 124	java/lang/Class
    //   198: ldc_w 524
    //   201: iconst_2
    //   202: anewarray 124	java/lang/Class
    //   205: dup
    //   206: iconst_0
    //   207: ldc 73
    //   209: aastore
    //   210: dup
    //   211: iconst_1
    //   212: ldc 73
    //   214: aastore
    //   215: invokevirtual 130	java/lang/Class:getMethod	(Ljava/lang/String;[Ljava/lang/Class;)Ljava/lang/reflect/Method;
    //   218: aconst_null
    //   219: iconst_2
    //   220: anewarray 132	java/lang/Object
    //   223: dup
    //   224: iconst_0
    //   225: aload_3
    //   226: aastore
    //   227: dup
    //   228: iconst_1
    //   229: aload_1
    //   230: aastore
    //   231: invokevirtual 138	java/lang/reflect/Method:invoke	(Ljava/lang/Object;[Ljava/lang/Object;)Ljava/lang/Object;
    //   234: pop
    //   235: goto +46 -> 281
    //   238: getstatic 34	o/Ix:ˈ	I
    //   241: istore_2
    //   242: iload_2
    //   243: bipush 11
    //   245: iadd
    //   246: istore_2
    //   247: iload_2
    //   248: sipush 128
    //   251: irem
    //   252: putstatic 32	o/Ix:ʾ	I
    //   255: iload_2
    //   256: iconst_2
    //   257: irem
    //   258: ifne +6 -> 264
    //   261: goto +6 -> 267
    //   264: goto +163 -> 427
    //   267: goto -3 -> 264
    //   270: astore_1
    //   271: aload_1
    //   272: athrow
    //   273: iconst_1
    //   274: istore_2
    //   275: goto +9 -> 284
    //   278: goto +49 -> 327
    //   281: goto +231 -> 512
    //   284: aload_3
    //   285: astore_1
    //   286: iload_2
    //   287: tableswitch	default:+21->308, 0:+140->427, 1:+24->311
    //   308: goto +3 -> 311
    //   311: aload_0
    //   312: aload_3
    //   313: iconst_4
    //   314: invokevirtual 682	java/lang/String:substring	(I)Ljava/lang/String;
    //   317: invokespecial 684	o/Ix:ॱ	(Ljava/lang/String;)Ljava/lang/String;
    //   320: invokevirtual 96	java/lang/String:intern	()Ljava/lang/String;
    //   323: astore_1
    //   324: goto -86 -> 238
    //   327: aload_1
    //   328: aload_0
    //   329: invokevirtual 55	android/content/Context:getApplicationInfo	()Landroid/content/pm/ApplicationInfo;
    //   332: getfield 60	android/content/pm/ApplicationInfo:targetSdkVersion	I
    //   335: bipush 122
    //   337: iadd
    //   338: aload_0
    //   339: invokevirtual 64	android/content/Context:getResources	()Landroid/content/res/Resources;
    //   342: ldc_w 685
    //   345: invokevirtual 71	android/content/res/Resources:getString	(I)Ljava/lang/String;
    //   348: iconst_0
    //   349: iconst_4
    //   350: invokevirtual 77	java/lang/String:substring	(II)Ljava/lang/String;
    //   353: iconst_1
    //   354: invokevirtual 89	java/lang/String:codePointAt	(I)I
    //   357: ldc_w 686
    //   360: iadd
    //   361: i2c
    //   362: aload_0
    //   363: invokevirtual 64	android/content/Context:getResources	()Landroid/content/res/Resources;
    //   366: ldc_w 687
    //   369: invokevirtual 71	android/content/res/Resources:getString	(I)Ljava/lang/String;
    //   372: iconst_0
    //   373: iconst_4
    //   374: invokevirtual 77	java/lang/String:substring	(II)Ljava/lang/String;
    //   377: invokevirtual 81	java/lang/String:length	()I
    //   380: iconst_1
    //   381: iadd
    //   382: invokestatic 93	o/Ix:ॱ	(ICI)Ljava/lang/String;
    //   385: invokevirtual 96	java/lang/String:intern	()Ljava/lang/String;
    //   388: invokestatic 689	o/vq:ˎ	(Ljava/lang/Object;Ljava/lang/String;)V
    //   391: aload_1
    //   392: invokevirtual 674	o/HR:ॱ	()Lcom/insidesecure/hce/MatrixHCEError;
    //   395: astore_3
    //   396: getstatic 694	o/Iv:ˎ	[I
    //   399: aload_3
    //   400: invokevirtual 697	com/insidesecure/hce/MatrixHCEError:ordinal	()I
    //   403: iaload
    //   404: tableswitch	default:+20->424, 1:+131->535
    //   424: goto -421 -> 3
    //   427: aload_1
    //   428: aload_0
    //   429: invokevirtual 64	android/content/Context:getResources	()Landroid/content/res/Resources;
    //   432: ldc 116
    //   434: invokevirtual 71	android/content/res/Resources:getString	(I)Ljava/lang/String;
    //   437: bipush 12
    //   439: bipush 19
    //   441: invokevirtual 77	java/lang/String:substring	(II)Ljava/lang/String;
    //   444: invokevirtual 81	java/lang/String:length	()I
    //   447: sipush 149
    //   450: iadd
    //   451: aload_0
    //   452: invokevirtual 55	android/content/Context:getApplicationInfo	()Landroid/content/pm/ApplicationInfo;
    //   455: getfield 60	android/content/pm/ApplicationInfo:targetSdkVersion	I
    //   458: ldc_w 698
    //   461: iadd
    //   462: i2c
    //   463: aload_0
    //   464: invokevirtual 64	android/content/Context:getResources	()Landroid/content/res/Resources;
    //   467: ldc_w 699
    //   470: invokevirtual 71	android/content/res/Resources:getString	(I)Ljava/lang/String;
    //   473: iconst_0
    //   474: iconst_4
    //   475: invokevirtual 77	java/lang/String:substring	(II)Ljava/lang/String;
    //   478: invokevirtual 81	java/lang/String:length	()I
    //   481: bipush 22
    //   483: iadd
    //   484: invokestatic 93	o/Ix:ॱ	(ICI)Ljava/lang/String;
    //   487: invokevirtual 96	java/lang/String:intern	()Ljava/lang/String;
    //   490: invokestatic 146	o/vq:ˋ	(Ljava/lang/Object;Ljava/lang/String;)V
    //   493: aload 4
    //   495: aload 5
    //   497: aload_1
    //   498: getstatic 705	o/Fh:BLR_DEVICE_FRAUD_PROVEN	Lo/Fh;
    //   501: invokevirtual 708	o/Gz:ˊ	(Landroid/content/Context;Ljava/lang/String;Lo/Fh;)V
    //   504: goto -223 -> 281
    //   507: iconst_0
    //   508: istore_2
    //   509: goto -225 -> 284
    //   512: getstatic 32	o/Ix:ʾ	I
    //   515: bipush 11
    //   517: iadd
    //   518: istore_2
    //   519: iload_2
    //   520: sipush 128
    //   523: irem
    //   524: putstatic 34	o/Ix:ˈ	I
    //   527: iload_2
    //   528: iconst_2
    //   529: irem
    //   530: ifeq +4 -> 534
    //   533: return
    //   534: return
    //   535: getstatic 623	o/Gz:ˎ	Lo/Gz$ˊ;
    //   538: aload_0
    //   539: checkcast 51	android/content/Context
    //   542: invokevirtual 628	o/Gz$ˊ:ˎ	(Landroid/content/Context;)Lo/Gz;
    //   545: astore 4
    //   547: aload_0
    //   548: checkcast 51	android/content/Context
    //   551: astore 5
    //   553: aload_0
    //   554: aload_1
    //   555: invokevirtual 710	o/HR:ˎ	()I
    //   558: invokevirtual 711	o/Ix:getString	(I)Ljava/lang/String;
    //   561: astore_3
    //   562: aload_3
    //   563: aload_0
    //   564: invokevirtual 85	android/content/Context:getPackageName	()Ljava/lang/String;
    //   567: bipush 8
    //   569: invokevirtual 89	java/lang/String:codePointAt	(I)I
    //   572: bipush 40
    //   574: iadd
    //   575: aload_0
    //   576: invokevirtual 55	android/content/Context:getApplicationInfo	()Landroid/content/pm/ApplicationInfo;
    //   579: getfield 60	android/content/pm/ApplicationInfo:targetSdkVersion	I
    //   582: ldc_w 712
    //   585: iadd
    //   586: i2c
    //   587: aload_0
    //   588: invokevirtual 64	android/content/Context:getResources	()Landroid/content/res/Resources;
    //   591: ldc_w 713
    //   594: invokevirtual 71	android/content/res/Resources:getString	(I)Ljava/lang/String;
    //   597: iconst_0
    //   598: iconst_4
    //   599: invokevirtual 77	java/lang/String:substring	(II)Ljava/lang/String;
    //   602: invokevirtual 81	java/lang/String:length	()I
    //   605: iconst_0
    //   606: iadd
    //   607: invokestatic 93	o/Ix:ॱ	(ICI)Ljava/lang/String;
    //   610: invokevirtual 96	java/lang/String:intern	()Ljava/lang/String;
    //   613: invokevirtual 717	java/lang/String:startsWith	(Ljava/lang/String;)Z
    //   616: ifeq +6 -> 622
    //   619: goto -346 -> 273
    //   622: goto -115 -> 507
    //   625: astore_1
    //   626: aload_1
    //   627: athrow
    // Local variable table:
    //   start	length	slot	name	signature
    //   0	628	0	this	Ix
    //   0	628	1	paramHR	HR
    //   241	289	2	i	int
    //   53	510	3	localObject	Object
    //   493	53	4	localGz	Gz
    //   495	57	5	localContext	Context
    // Exception table:
    //   from	to	target	type
    //   160	235	146	finally
    //   247	255	270	java/lang/Exception
    //   238	242	625	java/lang/Exception
  }
  
  protected IC ˊᐝ()
  {
    break label97;
    IC localIC3;
    IC localIC1 = localIC3;
    IC localIC2 = localIC3;
    int i;
    switch (i)
    {
    default: 
      localIC1 = localIC3;
    case 23: 
      label39:
      vq.ˊ(ॱ(getResources().getString(2131755146).substring(0, 4).codePointAt(3) - 12, (char)(getPackageName().codePointAt(2) - 46), getApplicationInfo().targetSdkVersion - 12).intern());
      localIC2 = localIC1;
      break;
      label97:
      break label112;
      i = 1;
      for (;;)
      {
        i = 52 / 0;
        return localIC2;
        label112:
        i = ʾ + 105;
        ˈ = i % 128;
        if (i % 2 != 0) {
          break label222;
        }
        break label153;
        label139:
        i = 23;
        break;
        return localIC2;
        label147:
        i = 27;
        break;
        label153:
        localIC1 = this.ॱˋ;
        if (localIC1 == null) {
          break label39;
        }
        localIC2 = localIC1;
        break label249;
        label170:
        switch (i)
        {
        }
      }
    }
    label222:
    label249:
    for (;;)
    {
      i = ˈ + 83;
      ʾ = i % 128;
      if (i % 2 != 0)
      {
        break;
        localIC3 = this.ॱˋ;
        i = 47 / 0;
        if (localIC3 == null) {
          break label139;
        }
        break label147;
      }
      i = 0;
      break label170;
    }
  }
  
  public void ˋ(int paramInt)
  {
    break label29;
    int i = 0;
    break label32;
    try
    {
      IC localIC = ˊᐝ();
      localIC.ˊ(paramInt);
      throw new NullPointerException();
    }
    catch (Exception localException)
    {
      throw localException;
    }
    for (;;)
    {
      label29:
      switch (i)
      {
      case 1: 
      default: 
        break label86;
        i = ˈ + 93;
        ʾ = i % 128;
        if (i % 2 == 0) {}
        break;
      case 0: 
        label32:
        label86:
        ˊᐝ().ˊ(paramInt);
        return;
        i = 1;
      }
    }
  }
  
  public void ˋˊ()
  {
    break label66;
    label13:
    for (;;)
    {
      ˊᐝ().ˋ();
      break;
    }
    label66:
    for (;;)
    {
      int i = ˈ + 77;
      ʾ = i % 128;
      if (i % 2 == 0) {
        break label13;
      }
      break;
      i = ʾ + 99;
      ˈ = i % 128;
      if (i % 2 != 0) {
        return;
      }
      return;
    }
  }
  
  public void ˋᐝ()
  {
    break label123;
    int i;
    switch (i)
    {
    default: 
      break;
      for (;;)
      {
        ˊᐝ().ʼ();
        for (;;)
        {
          i = ʾ + 105;
          ˈ = i % 128;
          if (i % 2 != 0) {
            break;
          }
          break label140;
          ˊᐝ().ʼ();
          i = 96 / 0;
        }
        label80:
        switch (i)
        {
        }
      }
    }
    for (;;)
    {
      i = 62;
      break label80;
      label123:
      label140:
      label145:
      do
      {
        i = 16;
        break label80;
        break label145;
        throw new NullPointerException();
        return;
        i = 0;
        break;
        i = 1;
        break;
        i = ʾ + 45;
        ˈ = i % 128;
      } while (i % 2 != 0);
    }
  }
  
  /* Error */
  public void ˍ()
  {
    // Byte code:
    //   0: goto +54 -> 54
    //   3: iconst_1
    //   4: istore_1
    //   5: goto +19 -> 24
    //   8: iconst_0
    //   9: istore_1
    //   10: goto +14 -> 24
    //   13: astore_2
    //   14: aload_2
    //   15: athrow
    //   16: aload_0
    //   17: invokevirtual 495	o/Ix:ˊᐝ	()Lo/IC;
    //   20: invokevirtual 734	o/IC:ˊ	()V
    //   23: return
    //   24: iload_1
    //   25: tableswitch	default:+23->48, 0:+-9->16, 1:+56->81
    //   48: goto -32 -> 16
    //   51: astore_2
    //   52: aload_2
    //   53: athrow
    //   54: getstatic 32	o/Ix:ʾ	I
    //   57: bipush 69
    //   59: iadd
    //   60: istore_1
    //   61: iload_1
    //   62: sipush 128
    //   65: irem
    //   66: putstatic 34	o/Ix:ˈ	I
    //   69: iload_1
    //   70: iconst_2
    //   71: irem
    //   72: ifeq +6 -> 78
    //   75: goto -72 -> 3
    //   78: goto -70 -> 8
    //   81: aload_0
    //   82: invokevirtual 495	o/Ix:ˊᐝ	()Lo/IC;
    //   85: astore_2
    //   86: aload_2
    //   87: invokevirtual 734	o/IC:ˊ	()V
    //   90: aconst_null
    //   91: arraylength
    //   92: istore_1
    //   93: return
    // Local variable table:
    //   start	length	slot	name	signature
    //   0	94	0	this	Ix
    //   4	89	1	i	int
    //   13	2	2	localException1	Exception
    //   51	2	2	localException2	Exception
    //   85	2	2	localIC	IC
    // Exception table:
    //   from	to	target	type
    //   81	86	13	java/lang/Exception
    //   86	93	13	java/lang/Exception
    //   86	93	51	java/lang/Exception
  }
  
  /* Error */
  public void ˎ(DialogInterface.OnCancelListener paramOnCancelListener)
  {
    // Byte code:
    //   0: goto +120 -> 120
    //   3: astore_1
    //   4: aload_1
    //   5: athrow
    //   6: astore_1
    //   7: aload_1
    //   8: athrow
    //   9: getstatic 34	o/Ix:ˈ	I
    //   12: istore_2
    //   13: iload_2
    //   14: bipush 15
    //   16: iadd
    //   17: istore_2
    //   18: iload_2
    //   19: sipush 128
    //   22: irem
    //   23: putstatic 32	o/Ix:ʾ	I
    //   26: iload_2
    //   27: iconst_2
    //   28: irem
    //   29: ifne +4 -> 33
    //   32: return
    //   33: return
    //   34: aload_0
    //   35: invokevirtual 85	android/content/Context:getPackageName	()Ljava/lang/String;
    //   38: astore_3
    //   39: aload_3
    //   40: iconst_4
    //   41: invokevirtual 89	java/lang/String:codePointAt	(I)I
    //   44: istore_2
    //   45: aload_1
    //   46: iload_2
    //   47: bipush 22
    //   49: isub
    //   50: aload_0
    //   51: invokevirtual 55	android/content/Context:getApplicationInfo	()Landroid/content/pm/ApplicationInfo;
    //   54: getfield 60	android/content/pm/ApplicationInfo:targetSdkVersion	I
    //   57: ldc_w 735
    //   60: iadd
    //   61: i2c
    //   62: aload_0
    //   63: invokevirtual 85	android/content/Context:getPackageName	()Ljava/lang/String;
    //   66: iconst_1
    //   67: invokevirtual 89	java/lang/String:codePointAt	(I)I
    //   70: bipush 103
    //   72: isub
    //   73: invokestatic 93	o/Ix:ॱ	(ICI)Ljava/lang/String;
    //   76: invokevirtual 96	java/lang/String:intern	()Ljava/lang/String;
    //   79: invokestatic 689	o/vq:ˎ	(Ljava/lang/Object;Ljava/lang/String;)V
    //   82: aload_0
    //   83: invokevirtual 495	o/Ix:ˊᐝ	()Lo/IC;
    //   86: aload_1
    //   87: invokevirtual 736	o/IC:ˎ	(Landroid/content/DialogInterface$OnCancelListener;)V
    //   90: goto -81 -> 9
    //   93: getstatic 34	o/Ix:ˈ	I
    //   96: bipush 115
    //   98: iadd
    //   99: istore_2
    //   100: iload_2
    //   101: sipush 128
    //   104: irem
    //   105: putstatic 32	o/Ix:ʾ	I
    //   108: iload_2
    //   109: iconst_2
    //   110: irem
    //   111: ifne +6 -> 117
    //   114: goto -80 -> 34
    //   117: goto -83 -> 34
    //   120: goto -27 -> 93
    // Local variable table:
    //   start	length	slot	name	signature
    //   0	123	0	this	Ix
    //   0	123	1	paramOnCancelListener	DialogInterface.OnCancelListener
    //   12	99	2	i	int
    //   38	2	3	str	String
    // Exception table:
    //   from	to	target	type
    //   34	39	3	java/lang/Exception
    //   39	45	3	java/lang/Exception
    //   45	90	3	java/lang/Exception
    //   9	13	6	java/lang/Exception
    //   18	26	6	java/lang/Exception
  }
  
  public void ˎ(Fd paramFd)
  {
    for (;;)
    {
      int i = ˈ + 9;
      ʾ = i % 128;
      if (i % 2 != 0)
      {
        i = 33;
        break label54;
        ˊᐝ().ˎ(paramFd);
        i = null.length;
        return;
        ˊᐝ().ˎ(paramFd);
        return;
      }
      for (;;)
      {
        label54:
        switch (i)
        {
        }
        break;
        i = 99;
      }
    }
  }
  
  /* Error */
  @zA(ˎ=org.greenrobot.eventbus.ThreadMode.MAIN)
  public final void ˎ(HT paramHT)
  {
    // Byte code:
    //   0: goto +104 -> 104
    //   3: aload_0
    //   4: invokevirtual 55	android/content/Context:getApplicationInfo	()Landroid/content/pm/ApplicationInfo;
    //   7: astore_3
    //   8: aload_1
    //   9: aload_3
    //   10: getfield 60	android/content/pm/ApplicationInfo:targetSdkVersion	I
    //   13: bipush 98
    //   15: iadd
    //   16: aload_0
    //   17: invokevirtual 85	android/content/Context:getPackageName	()Ljava/lang/String;
    //   20: invokevirtual 81	java/lang/String:length	()I
    //   23: sipush 8951
    //   26: iadd
    //   27: i2c
    //   28: aload_0
    //   29: invokevirtual 55	android/content/Context:getApplicationInfo	()Landroid/content/pm/ApplicationInfo;
    //   32: getfield 60	android/content/pm/ApplicationInfo:targetSdkVersion	I
    //   35: iconst_1
    //   36: isub
    //   37: invokestatic 93	o/Ix:ॱ	(ICI)Ljava/lang/String;
    //   40: invokevirtual 96	java/lang/String:intern	()Ljava/lang/String;
    //   43: invokestatic 689	o/vq:ˎ	(Ljava/lang/Object;Ljava/lang/String;)V
    //   46: aload_1
    //   47: invokevirtual 746	o/HT:ॱ$3bf1754e	()Ljava/lang/Enum;
    //   50: astore_3
    //   51: aload_3
    //   52: ifnonnull +6 -> 58
    //   55: goto +9 -> 64
    //   58: goto +221 -> 279
    //   61: goto -58 -> 3
    //   64: iconst_1
    //   65: istore_2
    //   66: goto +186 -> 252
    //   69: getstatic 32	o/Ix:ʾ	I
    //   72: bipush 39
    //   74: iadd
    //   75: istore_2
    //   76: iload_2
    //   77: sipush 128
    //   80: irem
    //   81: putstatic 34	o/Ix:ˈ	I
    //   84: iload_2
    //   85: iconst_2
    //   86: irem
    //   87: ifeq +6 -> 93
    //   90: goto +194 -> 284
    //   93: goto +139 -> 232
    //   96: astore_1
    //   97: aload_1
    //   98: athrow
    //   99: aload_0
    //   100: invokevirtual 749	o/Ix:ˑ	()V
    //   103: return
    //   104: goto +183 -> 287
    //   107: getstatic 751	o/Iv:ॱ	[I
    //   110: astore 4
    //   112: goto +17 -> 129
    //   115: astore_1
    //   116: aload_1
    //   117: invokevirtual 113	java/lang/Throwable:getCause	()Ljava/lang/Throwable;
    //   120: astore_3
    //   121: aload_3
    //   122: ifnull +5 -> 127
    //   125: aload_3
    //   126: athrow
    //   127: aload_1
    //   128: athrow
    //   129: aload_0
    //   130: invokevirtual 85	android/content/Context:getPackageName	()Ljava/lang/String;
    //   133: iconst_2
    //   134: invokevirtual 89	java/lang/String:codePointAt	(I)I
    //   137: bipush 42
    //   139: isub
    //   140: aload_0
    //   141: invokevirtual 55	android/content/Context:getApplicationInfo	()Landroid/content/pm/ApplicationInfo;
    //   144: getfield 60	android/content/pm/ApplicationInfo:targetSdkVersion	I
    //   147: sipush 201
    //   150: iadd
    //   151: aload_0
    //   152: invokevirtual 64	android/content/Context:getResources	()Landroid/content/res/Resources;
    //   155: ldc_w 752
    //   158: invokevirtual 71	android/content/res/Resources:getString	(I)Ljava/lang/String;
    //   161: bipush 11
    //   163: bipush 13
    //   165: invokevirtual 77	java/lang/String:substring	(II)Ljava/lang/String;
    //   168: iconst_0
    //   169: invokevirtual 89	java/lang/String:codePointAt	(I)I
    //   172: ldc_w 753
    //   175: iadd
    //   176: i2c
    //   177: invokestatic 122	o/O:ˋ	(IIC)Ljava/lang/Object;
    //   180: checkcast 124	java/lang/Class
    //   183: ldc_w 754
    //   186: aconst_null
    //   187: invokevirtual 130	java/lang/Class:getMethod	(Ljava/lang/String;[Ljava/lang/Class;)Ljava/lang/reflect/Method;
    //   190: aload_3
    //   191: aconst_null
    //   192: invokevirtual 138	java/lang/reflect/Method:invoke	(Ljava/lang/Object;[Ljava/lang/Object;)Ljava/lang/Object;
    //   195: checkcast 756	java/lang/Integer
    //   198: invokevirtual 759	java/lang/Integer:intValue	()I
    //   201: istore_2
    //   202: aload 4
    //   204: iload_2
    //   205: iaload
    //   206: tableswitch	default:+26->232, 1:+-107->99, 2:+119->325, 3:+114->320
    //   232: aload_0
    //   233: aload_1
    //   234: getfield 762	o/HT:errorMessageRes	I
    //   237: new 11	o/Ix$if
    //   240: dup
    //   241: aload_0
    //   242: invokespecial 763	o/Ix$if:<init>	(Lo/Ix;)V
    //   245: checkcast 765	o/ᐸ$ˏ
    //   248: invokevirtual 768	o/Ix:ॱ	(ILo/ᐸ$ˏ;)V
    //   251: return
    //   252: iload_2
    //   253: tableswitch	default:+23->276, 0:+-146->107, 1:+64->317
    //   276: goto -169 -> 107
    //   279: iconst_0
    //   280: istore_2
    //   281: goto -29 -> 252
    //   284: goto -191 -> 93
    //   287: getstatic 32	o/Ix:ʾ	I
    //   290: bipush 37
    //   292: iadd
    //   293: istore_2
    //   294: iload_2
    //   295: sipush 128
    //   298: irem
    //   299: putstatic 34	o/Ix:ˈ	I
    //   302: iload_2
    //   303: iconst_2
    //   304: irem
    //   305: ifeq +6 -> 311
    //   308: goto -247 -> 61
    //   311: goto -308 -> 3
    //   314: astore_1
    //   315: aload_1
    //   316: athrow
    //   317: goto -248 -> 69
    //   320: aload_0
    //   321: invokevirtual 770	o/Ix:ˋᐝ	()V
    //   324: return
    //   325: aload_0
    //   326: invokevirtual 175	o/Ix:ˋˊ	()V
    //   329: return
    // Local variable table:
    //   start	length	slot	name	signature
    //   0	330	0	this	Ix
    //   0	330	1	paramHT	HT
    //   65	240	2	i	int
    //   7	184	3	localObject	Object
    //   110	93	4	arrayOfInt	int[]
    // Exception table:
    //   from	to	target	type
    //   8	51	96	java/lang/Exception
    //   320	324	96	java/lang/Exception
    //   129	202	115	finally
    //   3	8	314	java/lang/Exception
    //   69	76	314	java/lang/Exception
    //   76	84	314	java/lang/Exception
  }
  
  public void ˏ(String paramString)
  {
    break label65;
    break label119;
    int i = ʾ + 43;
    ˈ = i % 128;
    if (i % 2 == 0)
    {
      break label202;
      label65:
      for (;;)
      {
        try
        {
          i = ʾ;
          i += 19;
          ˈ = i % 128;
          if (i % 2 != 0) {
            break;
          }
        }
        catch (Exception paramString)
        {
          throw paramString;
        }
      }
      label68:
      boolean bool = this.ᐝॱ;
      throw new NullPointerException();
    }
    else
    {
      break label202;
      label84:
      i = 72;
      break label211;
    }
    for (;;)
    {
      switch (i)
      {
      default: 
        break label243;
        vq.ˎ(paramString, ॱ(getPackageName().length() + 91, (char)(getPackageName().codePointAt(10) + 31283), getPackageName().codePointAt(5) - 93).intern());
        if (!this.ॱᐝ)
        {
          break label183;
          i = 46;
          break label211;
          i = 20;
        }
        break;
      case 20: 
      case 36: 
        for (;;)
        {
          label119:
          label177:
          label183:
          if (this.ᐝॱ) {
            break label84;
          }
          break label177;
          label202:
          ˊᐝ().ˏ(paramString);
          return;
          label211:
          switch (i)
          {
          }
          break;
          label243:
          i = ˈ + 31;
          ʾ = i % 128;
          if (i % 2 == 0) {
            break label68;
          }
        }
        i = 36;
      }
    }
  }
  
  /* Error */
  public void ˑ()
  {
    // Byte code:
    //   0: goto +46 -> 46
    //   3: aload_0
    //   4: invokevirtual 495	o/Ix:ˊᐝ	()Lo/IC;
    //   7: invokevirtual 776	o/IC:ˎ	()V
    //   10: return
    //   11: bipush 7
    //   13: istore_1
    //   14: goto +58 -> 72
    //   17: astore_2
    //   18: aload_2
    //   19: athrow
    //   20: aload_0
    //   21: invokevirtual 495	o/Ix:ˊᐝ	()Lo/IC;
    //   24: astore_2
    //   25: aload_2
    //   26: invokevirtual 776	o/IC:ˎ	()V
    //   29: new 501	java/lang/NullPointerException
    //   32: dup
    //   33: invokespecial 502	java/lang/NullPointerException:<init>	()V
    //   36: athrow
    //   37: bipush 10
    //   39: istore_1
    //   40: goto +32 -> 72
    //   43: astore_2
    //   44: aload_2
    //   45: athrow
    //   46: getstatic 34	o/Ix:ˈ	I
    //   49: iconst_1
    //   50: iadd
    //   51: istore_1
    //   52: iload_1
    //   53: sipush 128
    //   56: irem
    //   57: putstatic 32	o/Ix:ʾ	I
    //   60: iload_1
    //   61: iconst_2
    //   62: irem
    //   63: ifne +6 -> 69
    //   66: goto -55 -> 11
    //   69: goto -32 -> 37
    //   72: iload_1
    //   73: lookupswitch	default:+27->100, 7:+-53->20, 10:+-70->3
    //   100: goto -80 -> 20
    // Local variable table:
    //   start	length	slot	name	signature
    //   0	103	0	this	Ix
    //   13	60	1	i	int
    //   17	2	2	localException1	Exception
    //   24	2	2	localIC	IC
    //   43	2	2	localException2	Exception
    // Exception table:
    //   from	to	target	type
    //   25	29	17	java/lang/Exception
    //   20	25	43	java/lang/Exception
    //   46	52	43	java/lang/Exception
    //   52	60	43	java/lang/Exception
  }
  
  public void ॱ(int paramInt, ᐸ.ˏ paramˏ)
  {
    for (;;)
    {
      vq.ˎ(paramˏ, ॱ(getApplicationInfo().targetSdkVersion + 69, (char)(getResources().getString(2131755096).substring(0, 4).codePointAt(0) + 64659), getResources().getString(2131755546).substring(0, 4).codePointAt(2) - 3).intern());
      ˊᐝ().ˎ(paramInt, paramˏ);
      break;
      int i = ˈ + 65;
      ʾ = i % 128;
      if (i % 2 != 0) {}
    }
    paramInt = ˈ + 73;
    ʾ = paramInt % 128;
    if (paramInt % 2 == 0) {}
  }
  
  public void ॱ(IC paramIC)
  {
    break label180;
    int i;
    for (;;)
    {
      i = 76;
      switch (i)
      {
      default: 
        break label175;
        vq.ˎ(paramIC, ॱ(getResources().getString(2131755097).substring(0, 4).length() + 9, (char)(getPackageName().codePointAt(9) - 97), getResources().getString(2131755237).substring(0, 4).length() + 3).intern());
        this.ॱˋ = paramIC;
        do
        {
          i = 10;
          break;
          i = ˈ + 17;
          ʾ = i % 128;
        } while (i % 2 == 0);
      }
    }
    label175:
    label180:
    for (;;)
    {
      i = ˈ + 99;
      ʾ = i % 128;
      if (i % 2 == 0) {
        break;
      }
      break;
      i = null.length;
      return;
      return;
    }
  }
  
  static final class iF
    implements DialogInterface.OnCancelListener
  {
    iF(Ix paramIx) {}
    
    public final void onCancel(DialogInterface paramDialogInterface)
    {
      this.ˎ.finishAffinity();
    }
  }
  
  static final class if
    implements ᐸ.ˏ
  {
    private static int ˊ = 1;
    private static int ˏ = 0;
    private static char[] ॱ = { 31, 55, 40, 73, 107, 108, 108, 105, 103, 105, 105, 104, 72, 73, 116, 114, 110, 115, 115, 110, 110, 103, 78, 140, 282, 280, 276, 281, 281, 276, 276, 269, 244, 227, 221, 206, 239, 273, 274, 274, 271, 269, 271, 271, 270, 238 };
    
    if(Ix paramIx) {}
    
    /* Error */
    private static String ˏ(int[] paramArrayOfInt, byte[] paramArrayOfByte, boolean paramBoolean)
    {
      // Byte code:
      //   0: goto +537 -> 537
      //   3: iload 4
      //   5: lookupswitch	default:+27->32, 15:+399->404, 96:+437->442
      //   32: goto +410 -> 442
      //   35: iconst_3
      //   36: istore 5
      //   38: goto +605 -> 643
      //   41: iload 6
      //   43: newarray char
      //   45: astore_1
      //   46: aload 9
      //   48: iconst_0
      //   49: aload_1
      //   50: iconst_0
      //   51: iload 6
      //   53: invokestatic 72	java/lang/System:arraycopy	(Ljava/lang/Object;ILjava/lang/Object;II)V
      //   56: aload_1
      //   57: iconst_0
      //   58: aload 9
      //   60: iload 6
      //   62: iload 8
      //   64: isub
      //   65: iload 8
      //   67: invokestatic 72	java/lang/System:arraycopy	(Ljava/lang/Object;ILjava/lang/Object;II)V
      //   70: aload_1
      //   71: iload 8
      //   73: aload 9
      //   75: iconst_0
      //   76: iload 6
      //   78: iload 8
      //   80: isub
      //   81: invokestatic 72	java/lang/System:arraycopy	(Ljava/lang/Object;ILjava/lang/Object;II)V
      //   84: goto +591 -> 675
      //   87: getstatic 21	o/Ix$if:ˏ	I
      //   90: bipush 7
      //   92: iadd
      //   93: istore 4
      //   95: iload 4
      //   97: sipush 128
      //   100: irem
      //   101: putstatic 23	o/Ix$if:ˊ	I
      //   104: iload 4
      //   106: iconst_2
      //   107: irem
      //   108: ifne +6 -> 114
      //   111: goto +499 -> 610
      //   114: goto +186 -> 300
      //   117: aload_0
      //   118: iconst_0
      //   119: iaload
      //   120: istore_3
      //   121: aload_0
      //   122: iconst_1
      //   123: iaload
      //   124: istore 6
      //   126: aload_0
      //   127: iconst_2
      //   128: iaload
      //   129: istore 7
      //   131: aload_0
      //   132: iconst_3
      //   133: iaload
      //   134: istore 8
      //   136: getstatic 56	o/Ix$if:ॱ	[C
      //   139: astore 9
      //   141: iload 6
      //   143: newarray char
      //   145: astore 10
      //   147: aload 9
      //   149: iload_3
      //   150: aload 10
      //   152: iconst_0
      //   153: iload 6
      //   155: invokestatic 72	java/lang/System:arraycopy	(Ljava/lang/Object;ILjava/lang/Object;II)V
      //   158: aload_1
      //   159: ifnull +6 -> 165
      //   162: goto +466 -> 628
      //   165: goto +205 -> 370
      //   168: aload 9
      //   170: iload 4
      //   172: caload
      //   173: istore_3
      //   174: iload 4
      //   176: iconst_1
      //   177: iadd
      //   178: istore 4
      //   180: goto +505 -> 685
      //   183: goto +434 -> 617
      //   186: iload 6
      //   188: newarray char
      //   190: astore 9
      //   192: iconst_0
      //   193: istore_3
      //   194: iconst_0
      //   195: istore 4
      //   197: goto +327 -> 524
      //   200: iload 5
      //   202: tableswitch	default:+22->224, 0:+376->578, 1:+491->693
      //   224: goto +469 -> 693
      //   227: astore_0
      //   228: aload_0
      //   229: athrow
      //   230: getstatic 23	o/Ix$if:ˊ	I
      //   233: istore_3
      //   234: iload_3
      //   235: iconst_5
      //   236: iadd
      //   237: istore_3
      //   238: iload_3
      //   239: sipush 128
      //   242: irem
      //   243: putstatic 21	o/Ix$if:ˏ	I
      //   246: iload_3
      //   247: iconst_2
      //   248: irem
      //   249: ifeq +6 -> 255
      //   252: goto +340 -> 592
      //   255: goto -138 -> 117
      //   258: aload 10
      //   260: astore 9
      //   262: iload_3
      //   263: tableswitch	default:+21->284, 0:+-77->186, 1:+198->461
      //   284: aload 10
      //   286: astore 9
      //   288: goto +173 -> 461
      //   291: new 74	java/lang/String
      //   294: dup
      //   295: aload_1
      //   296: invokespecial 77	java/lang/String:<init>	([C)V
      //   299: areturn
      //   300: bipush 96
      //   302: istore 4
      //   304: goto -301 -> 3
      //   307: getstatic 21	o/Ix$if:ˏ	I
      //   310: bipush 93
      //   312: iadd
      //   313: istore_3
      //   314: iload_3
      //   315: sipush 128
      //   318: irem
      //   319: putstatic 23	o/Ix$if:ˊ	I
      //   322: iload_3
      //   323: iconst_2
      //   324: irem
      //   325: ifne +6 -> 331
      //   328: goto +247 -> 575
      //   331: goto -290 -> 41
      //   334: getstatic 21	o/Ix$if:ˏ	I
      //   337: bipush 29
      //   339: iadd
      //   340: istore 4
      //   342: iload 4
      //   344: sipush 128
      //   347: irem
      //   348: putstatic 23	o/Ix$if:ˊ	I
      //   351: iload 4
      //   353: iconst_2
      //   354: irem
      //   355: ifne +6 -> 361
      //   358: goto +126 -> 484
      //   361: goto +63 -> 424
      //   364: astore_0
      //   365: aload_0
      //   366: athrow
      //   367: goto -199 -> 168
      //   370: iconst_1
      //   371: istore_3
      //   372: goto -114 -> 258
      //   375: aload 9
      //   377: iload 4
      //   379: aload 10
      //   381: iload 4
      //   383: caload
      //   384: iconst_1
      //   385: ishl
      //   386: iconst_1
      //   387: iadd
      //   388: iload_3
      //   389: isub
      //   390: i2c
      //   391: castore
      //   392: goto -25 -> 367
      //   395: iconst_0
      //   396: istore 5
      //   398: goto -198 -> 200
      //   401: goto +60 -> 461
      //   404: aload_1
      //   405: iload_3
      //   406: aload 9
      //   408: iload 6
      //   410: iload_3
      //   411: isub
      //   412: iconst_0
      //   413: iadd
      //   414: caload
      //   415: castore
      //   416: iload_3
      //   417: bipush 122
      //   419: iadd
      //   420: istore_3
      //   421: goto +219 -> 640
      //   424: aload_1
      //   425: iload_3
      //   426: aload_1
      //   427: iload_3
      //   428: caload
      //   429: aload_0
      //   430: iconst_2
      //   431: iaload
      //   432: isub
      //   433: i2c
      //   434: castore
      //   435: iload_3
      //   436: iconst_1
      //   437: iadd
      //   438: istore_3
      //   439: goto +286 -> 725
      //   442: aload_1
      //   443: iload_3
      //   444: aload 9
      //   446: iload 6
      //   448: iload_3
      //   449: isub
      //   450: iconst_1
      //   451: isub
      //   452: caload
      //   453: castore
      //   454: iload_3
      //   455: iconst_1
      //   456: iadd
      //   457: istore_3
      //   458: goto +182 -> 640
      //   461: iload 8
      //   463: ifle +6 -> 469
      //   466: goto -159 -> 307
      //   469: goto +206 -> 675
      //   472: iload_3
      //   473: iload 6
      //   475: if_icmpge +6 -> 481
      //   478: goto -391 -> 87
      //   481: goto -298 -> 183
      //   484: goto -60 -> 424
      //   487: aload 9
      //   489: astore_1
      //   490: iload_3
      //   491: tableswitch	default:+21->512, 0:+126->617, 1:+109->600
      //   512: aload 9
      //   514: astore_1
      //   515: goto +102 -> 617
      //   518: iconst_1
      //   519: istore 5
      //   521: goto -321 -> 200
      //   524: iload 4
      //   526: iload 6
      //   528: if_icmpge +6 -> 534
      //   531: goto +14 -> 545
      //   534: goto -133 -> 401
      //   537: goto -307 -> 230
      //   540: iconst_0
      //   541: istore_3
      //   542: goto -55 -> 487
      //   545: getstatic 23	o/Ix$if:ˊ	I
      //   548: bipush 115
      //   550: iadd
      //   551: istore 5
      //   553: iload 5
      //   555: sipush 128
      //   558: irem
      //   559: putstatic 21	o/Ix$if:ˏ	I
      //   562: iload 5
      //   564: iconst_2
      //   565: irem
      //   566: ifeq +6 -> 572
      //   569: goto -174 -> 395
      //   572: goto -54 -> 518
      //   575: goto -534 -> 41
      //   578: aload_1
      //   579: iload 4
      //   581: baload
      //   582: iconst_1
      //   583: if_icmpne +6 -> 589
      //   586: goto -211 -> 375
      //   589: goto +118 -> 707
      //   592: goto -475 -> 117
      //   595: iconst_1
      //   596: istore_3
      //   597: goto -110 -> 487
      //   600: iload 6
      //   602: newarray char
      //   604: astore_1
      //   605: iconst_0
      //   606: istore_3
      //   607: goto -135 -> 472
      //   610: bipush 15
      //   612: istore 4
      //   614: goto -611 -> 3
      //   617: iload 7
      //   619: ifle +6 -> 625
      //   622: goto +66 -> 688
      //   625: goto -334 -> 291
      //   628: iconst_0
      //   629: istore_3
      //   630: goto -372 -> 258
      //   633: bipush 35
      //   635: istore 5
      //   637: goto +6 -> 643
      //   640: goto -168 -> 472
      //   643: iload 5
      //   645: lookupswitch	default:+27->672, 3:+-270->375, 35:+62->707
      //   672: goto +35 -> 707
      //   675: iload_2
      //   676: ifeq +6 -> 682
      //   679: goto -84 -> 595
      //   682: goto -142 -> 540
      //   685: goto -161 -> 524
      //   688: iconst_0
      //   689: istore_3
      //   690: goto +35 -> 725
      //   693: aload_1
      //   694: iload 4
      //   696: baload
      //   697: iconst_1
      //   698: if_icmpne +6 -> 704
      //   701: goto -666 -> 35
      //   704: goto -71 -> 633
      //   707: aload 9
      //   709: iload 4
      //   711: aload 10
      //   713: iload 4
      //   715: caload
      //   716: iconst_1
      //   717: ishl
      //   718: iload_3
      //   719: isub
      //   720: i2c
      //   721: castore
      //   722: goto -554 -> 168
      //   725: iload_3
      //   726: iload 6
      //   728: if_icmpge +6 -> 734
      //   731: goto -397 -> 334
      //   734: goto -443 -> 291
      // Local variable table:
      //   start	length	slot	name	signature
      //   0	737	0	paramArrayOfInt	int[]
      //   0	737	1	paramArrayOfByte	byte[]
      //   0	737	2	paramBoolean	boolean
      //   120	609	3	i	int
      //   3	711	4	j	int
      //   36	608	5	k	int
      //   41	688	6	m	int
      //   129	489	7	n	int
      //   62	400	8	i1	int
      //   46	662	9	localObject	Object
      //   145	567	10	arrayOfChar	char[]
      // Exception table:
      //   from	to	target	type
      //   307	314	227	java/lang/Exception
      //   314	322	227	java/lang/Exception
      //   230	234	364	java/lang/Exception
      //   238	246	364	java/lang/Exception
    }
    
    /* Error */
    public final void ˋ(ᐸ paramᐸ, ะ paramะ)
    {
      // Byte code:
      //   0: goto +68 -> 68
      //   3: bipush 65
      //   5: istore_3
      //   6: iload_3
      //   7: lookupswitch	default:+25->32, 65:+428->435, 87:+67->74
      //   32: goto +403 -> 435
      //   35: getstatic 23	o/Ix$if:ˊ	I
      //   38: bipush 101
      //   40: iadd
      //   41: istore_3
      //   42: iload_3
      //   43: sipush 128
      //   46: irem
      //   47: putstatic 21	o/Ix$if:ˏ	I
      //   50: iload_3
      //   51: iconst_2
      //   52: irem
      //   53: ifeq +6 -> 59
      //   56: goto +6 -> 62
      //   59: goto +370 -> 429
      //   62: bipush 37
      //   64: istore_3
      //   65: goto +759 -> 824
      //   68: goto -33 -> 35
      //   71: astore_1
      //   72: aload_1
      //   73: athrow
      //   74: return
      //   75: aload_1
      //   76: iconst_4
      //   77: newarray int
      //   79: dup
      //   80: iconst_0
      //   81: iconst_0
      //   82: iastore
      //   83: dup
      //   84: iconst_1
      //   85: bipush 23
      //   87: iastore
      //   88: dup
      //   89: iconst_2
      //   90: iconst_0
      //   91: iastore
      //   92: dup
      //   93: iconst_3
      //   94: iconst_0
      //   95: iastore
      //   96: bipush 23
      //   98: newarray byte
      //   100: dup
      //   101: iconst_0
      //   102: ldc 80
      //   104: bastore
      //   105: dup
      //   106: iconst_1
      //   107: ldc 80
      //   109: bastore
      //   110: dup
      //   111: iconst_2
      //   112: ldc 80
      //   114: bastore
      //   115: dup
      //   116: iconst_3
      //   117: ldc 80
      //   119: bastore
      //   120: dup
      //   121: iconst_4
      //   122: ldc 81
      //   124: bastore
      //   125: dup
      //   126: iconst_5
      //   127: ldc 81
      //   129: bastore
      //   130: dup
      //   131: bipush 6
      //   133: ldc 81
      //   135: bastore
      //   136: dup
      //   137: bipush 7
      //   139: ldc 80
      //   141: bastore
      //   142: dup
      //   143: bipush 8
      //   145: ldc 80
      //   147: bastore
      //   148: dup
      //   149: bipush 9
      //   151: ldc 81
      //   153: bastore
      //   154: dup
      //   155: bipush 10
      //   157: ldc 81
      //   159: bastore
      //   160: dup
      //   161: bipush 11
      //   163: ldc 81
      //   165: bastore
      //   166: dup
      //   167: bipush 12
      //   169: ldc 80
      //   171: bastore
      //   172: dup
      //   173: bipush 13
      //   175: ldc 81
      //   177: bastore
      //   178: dup
      //   179: bipush 14
      //   181: ldc 80
      //   183: bastore
      //   184: dup
      //   185: bipush 15
      //   187: ldc 80
      //   189: bastore
      //   190: dup
      //   191: bipush 16
      //   193: ldc 80
      //   195: bastore
      //   196: dup
      //   197: bipush 17
      //   199: ldc 80
      //   201: bastore
      //   202: dup
      //   203: bipush 18
      //   205: ldc 81
      //   207: bastore
      //   208: dup
      //   209: bipush 19
      //   211: ldc 81
      //   213: bastore
      //   214: dup
      //   215: bipush 20
      //   217: ldc 81
      //   219: bastore
      //   220: dup
      //   221: bipush 21
      //   223: ldc 81
      //   225: bastore
      //   226: dup
      //   227: bipush 22
      //   229: ldc 81
      //   231: bastore
      //   232: iconst_0
      //   233: invokestatic 83	o/Ix$if:ˏ	([I[BZ)Ljava/lang/String;
      //   236: invokevirtual 87	java/lang/String:intern	()Ljava/lang/String;
      //   239: invokestatic 92	o/vq:ˎ	(Ljava/lang/Object;Ljava/lang/String;)V
      //   242: aload_2
      //   243: iconst_4
      //   244: newarray int
      //   246: dup
      //   247: iconst_0
      //   248: bipush 23
      //   250: iastore
      //   251: dup
      //   252: iconst_1
      //   253: bipush 23
      //   255: iastore
      //   256: dup
      //   257: iconst_2
      //   258: sipush 166
      //   261: iastore
      //   262: dup
      //   263: iconst_3
      //   264: bipush 10
      //   266: iastore
      //   267: bipush 23
      //   269: newarray byte
      //   271: dup
      //   272: iconst_0
      //   273: ldc 81
      //   275: bastore
      //   276: dup
      //   277: iconst_1
      //   278: ldc 80
      //   280: bastore
      //   281: dup
      //   282: iconst_2
      //   283: ldc 80
      //   285: bastore
      //   286: dup
      //   287: iconst_3
      //   288: ldc 80
      //   290: bastore
      //   291: dup
      //   292: iconst_4
      //   293: ldc 80
      //   295: bastore
      //   296: dup
      //   297: iconst_5
      //   298: ldc 81
      //   300: bastore
      //   301: dup
      //   302: bipush 6
      //   304: ldc 81
      //   306: bastore
      //   307: dup
      //   308: bipush 7
      //   310: ldc 81
      //   312: bastore
      //   313: dup
      //   314: bipush 8
      //   316: ldc 81
      //   318: bastore
      //   319: dup
      //   320: bipush 9
      //   322: ldc 81
      //   324: bastore
      //   325: dup
      //   326: bipush 10
      //   328: ldc 80
      //   330: bastore
      //   331: dup
      //   332: bipush 11
      //   334: ldc 81
      //   336: bastore
      //   337: dup
      //   338: bipush 12
      //   340: ldc 81
      //   342: bastore
      //   343: dup
      //   344: bipush 13
      //   346: ldc 80
      //   348: bastore
      //   349: dup
      //   350: bipush 14
      //   352: ldc 81
      //   354: bastore
      //   355: dup
      //   356: bipush 15
      //   358: ldc 81
      //   360: bastore
      //   361: dup
      //   362: bipush 16
      //   364: ldc 81
      //   366: bastore
      //   367: dup
      //   368: bipush 17
      //   370: ldc 80
      //   372: bastore
      //   373: dup
      //   374: bipush 18
      //   376: ldc 80
      //   378: bastore
      //   379: dup
      //   380: bipush 19
      //   382: ldc 81
      //   384: bastore
      //   385: dup
      //   386: bipush 20
      //   388: ldc 81
      //   390: bastore
      //   391: dup
      //   392: bipush 21
      //   394: ldc 81
      //   396: bastore
      //   397: dup
      //   398: bipush 22
      //   400: ldc 80
      //   402: bastore
      //   403: iconst_0
      //   404: invokestatic 83	o/Ix$if:ˏ	([I[BZ)Ljava/lang/String;
      //   407: invokevirtual 87	java/lang/String:intern	()Ljava/lang/String;
      //   410: invokestatic 92	o/vq:ˎ	(Ljava/lang/Object;Ljava/lang/String;)V
      //   413: aload_0
      //   414: getfield 61	o/Ix$if:ˎ	Lo/Ix;
      //   417: invokevirtual 95	o/Ix:finish	()V
      //   420: goto +21 -> 441
      //   423: bipush 87
      //   425: istore_3
      //   426: goto -420 -> 6
      //   429: bipush 19
      //   431: istore_3
      //   432: goto +392 -> 824
      //   435: bipush 13
      //   437: iconst_0
      //   438: idiv
      //   439: istore_3
      //   440: return
      //   441: getstatic 21	o/Ix$if:ˏ	I
      //   444: bipush 115
      //   446: iadd
      //   447: istore_3
      //   448: iload_3
      //   449: sipush 128
      //   452: irem
      //   453: putstatic 23	o/Ix$if:ˊ	I
      //   456: iload_3
      //   457: iconst_2
      //   458: irem
      //   459: ifne +6 -> 465
      //   462: goto -459 -> 3
      //   465: goto -42 -> 423
      //   468: iconst_4
      //   469: newarray int
      //   471: dup
      //   472: iconst_0
      //   473: iconst_0
      //   474: iastore
      //   475: dup
      //   476: iconst_1
      //   477: bipush 23
      //   479: iastore
      //   480: dup
      //   481: iconst_2
      //   482: iconst_0
      //   483: iastore
      //   484: dup
      //   485: iconst_3
      //   486: iconst_0
      //   487: iastore
      //   488: bipush 23
      //   490: newarray byte
      //   492: dup
      //   493: iconst_0
      //   494: ldc 80
      //   496: bastore
      //   497: dup
      //   498: iconst_1
      //   499: ldc 80
      //   501: bastore
      //   502: dup
      //   503: iconst_2
      //   504: ldc 80
      //   506: bastore
      //   507: dup
      //   508: iconst_3
      //   509: ldc 80
      //   511: bastore
      //   512: dup
      //   513: iconst_4
      //   514: ldc 81
      //   516: bastore
      //   517: dup
      //   518: iconst_5
      //   519: ldc 81
      //   521: bastore
      //   522: dup
      //   523: bipush 6
      //   525: ldc 81
      //   527: bastore
      //   528: dup
      //   529: bipush 7
      //   531: ldc 80
      //   533: bastore
      //   534: dup
      //   535: bipush 8
      //   537: ldc 80
      //   539: bastore
      //   540: dup
      //   541: bipush 9
      //   543: ldc 81
      //   545: bastore
      //   546: dup
      //   547: bipush 10
      //   549: ldc 81
      //   551: bastore
      //   552: dup
      //   553: bipush 11
      //   555: ldc 81
      //   557: bastore
      //   558: dup
      //   559: bipush 12
      //   561: ldc 80
      //   563: bastore
      //   564: dup
      //   565: bipush 13
      //   567: ldc 81
      //   569: bastore
      //   570: dup
      //   571: bipush 14
      //   573: ldc 80
      //   575: bastore
      //   576: dup
      //   577: bipush 15
      //   579: ldc 80
      //   581: bastore
      //   582: dup
      //   583: bipush 16
      //   585: ldc 80
      //   587: bastore
      //   588: dup
      //   589: bipush 17
      //   591: ldc 80
      //   593: bastore
      //   594: dup
      //   595: bipush 18
      //   597: ldc 81
      //   599: bastore
      //   600: dup
      //   601: bipush 19
      //   603: ldc 81
      //   605: bastore
      //   606: dup
      //   607: bipush 20
      //   609: ldc 81
      //   611: bastore
      //   612: dup
      //   613: bipush 21
      //   615: ldc 81
      //   617: bastore
      //   618: dup
      //   619: bipush 22
      //   621: ldc 81
      //   623: bastore
      //   624: iconst_1
      //   625: invokestatic 83	o/Ix$if:ˏ	([I[BZ)Ljava/lang/String;
      //   628: astore 4
      //   630: aload 4
      //   632: invokevirtual 87	java/lang/String:intern	()Ljava/lang/String;
      //   635: astore 4
      //   637: aload_1
      //   638: aload 4
      //   640: invokestatic 92	o/vq:ˎ	(Ljava/lang/Object;Ljava/lang/String;)V
      //   643: aload_2
      //   644: iconst_4
      //   645: newarray int
      //   647: dup
      //   648: iconst_0
      //   649: bipush 23
      //   651: iastore
      //   652: dup
      //   653: iconst_1
      //   654: bipush 23
      //   656: iastore
      //   657: dup
      //   658: iconst_2
      //   659: sipush 166
      //   662: iastore
      //   663: dup
      //   664: iconst_3
      //   665: bipush 10
      //   667: iastore
      //   668: bipush 23
      //   670: newarray byte
      //   672: dup
      //   673: iconst_0
      //   674: ldc 81
      //   676: bastore
      //   677: dup
      //   678: iconst_1
      //   679: ldc 80
      //   681: bastore
      //   682: dup
      //   683: iconst_2
      //   684: ldc 80
      //   686: bastore
      //   687: dup
      //   688: iconst_3
      //   689: ldc 80
      //   691: bastore
      //   692: dup
      //   693: iconst_4
      //   694: ldc 80
      //   696: bastore
      //   697: dup
      //   698: iconst_5
      //   699: ldc 81
      //   701: bastore
      //   702: dup
      //   703: bipush 6
      //   705: ldc 81
      //   707: bastore
      //   708: dup
      //   709: bipush 7
      //   711: ldc 81
      //   713: bastore
      //   714: dup
      //   715: bipush 8
      //   717: ldc 81
      //   719: bastore
      //   720: dup
      //   721: bipush 9
      //   723: ldc 81
      //   725: bastore
      //   726: dup
      //   727: bipush 10
      //   729: ldc 80
      //   731: bastore
      //   732: dup
      //   733: bipush 11
      //   735: ldc 81
      //   737: bastore
      //   738: dup
      //   739: bipush 12
      //   741: ldc 81
      //   743: bastore
      //   744: dup
      //   745: bipush 13
      //   747: ldc 80
      //   749: bastore
      //   750: dup
      //   751: bipush 14
      //   753: ldc 81
      //   755: bastore
      //   756: dup
      //   757: bipush 15
      //   759: ldc 81
      //   761: bastore
      //   762: dup
      //   763: bipush 16
      //   765: ldc 81
      //   767: bastore
      //   768: dup
      //   769: bipush 17
      //   771: ldc 80
      //   773: bastore
      //   774: dup
      //   775: bipush 18
      //   777: ldc 80
      //   779: bastore
      //   780: dup
      //   781: bipush 19
      //   783: ldc 81
      //   785: bastore
      //   786: dup
      //   787: bipush 20
      //   789: ldc 81
      //   791: bastore
      //   792: dup
      //   793: bipush 21
      //   795: ldc 81
      //   797: bastore
      //   798: dup
      //   799: bipush 22
      //   801: ldc 80
      //   803: bastore
      //   804: iconst_1
      //   805: invokestatic 83	o/Ix$if:ˏ	([I[BZ)Ljava/lang/String;
      //   808: invokevirtual 87	java/lang/String:intern	()Ljava/lang/String;
      //   811: invokestatic 92	o/vq:ˎ	(Ljava/lang/Object;Ljava/lang/String;)V
      //   814: aload_0
      //   815: getfield 61	o/Ix$if:ˎ	Lo/Ix;
      //   818: invokevirtual 95	o/Ix:finish	()V
      //   821: goto -380 -> 441
      //   824: iload_3
      //   825: lookupswitch	default:+27->852, 19:+-357->468, 37:+-750->75
      //   852: goto -777 -> 75
      //   855: astore_1
      //   856: aload_1
      //   857: athrow
      // Local variable table:
      //   start	length	slot	name	signature
      //   0	858	0	this	if
      //   0	858	1	paramᐸ	ᐸ
      //   0	858	2	paramะ	ะ
      //   5	820	3	i	int
      //   628	11	4	str	String
      // Exception table:
      //   from	to	target	type
      //   468	630	71	java/lang/Exception
      //   630	637	855	java/lang/Exception
      //   637	821	855	java/lang/Exception
    }
  }
  
  static final class ˋ
    implements DialogInterface.OnCancelListener
  {
    ˋ(Ix paramIx) {}
    
    public final void onCancel(DialogInterface paramDialogInterface)
    {
      this.ˎ.finishAffinity();
    }
  }
}
