package o;

public class Iy<V extends Iu.if, R extends Ib>
  extends W
  implements Iu.iF
{
  private static int ʼ = 1;
  private static int ॱ = 100;
  private static int ᐝ = 0;
  private final R ˊ;
  private final L ˋ$4622a72;
  private final V ˎ;
  private boolean ˏ;
  
  /* Error */
  public Iy(V paramV, R paramR)
  {
    // Byte code:
    //   0: goto +3 -> 3
    //   3: aload_1
    //   4: sipush 204
    //   7: iconst_5
    //   8: iconst_5
    //   9: newarray char
    //   11: dup
    //   12: iconst_0
    //   13: ldc 43
    //   15: castore
    //   16: dup
    //   17: iconst_1
    //   18: ldc 44
    //   20: castore
    //   21: dup
    //   22: iconst_2
    //   23: ldc 45
    //   25: castore
    //   26: dup
    //   27: iconst_3
    //   28: ldc 46
    //   30: castore
    //   31: dup
    //   32: iconst_4
    //   33: ldc 47
    //   35: castore
    //   36: iconst_5
    //   37: iconst_0
    //   38: invokestatic 50	o/Iy:ॱ	(II[CIZ)Ljava/lang/String;
    //   41: invokevirtual 56	java/lang/String:intern	()Ljava/lang/String;
    //   44: invokestatic 61	o/vq:ˎ	(Ljava/lang/Object;Ljava/lang/String;)V
    //   47: aload_2
    //   48: sipush 208
    //   51: bipush 11
    //   53: bipush 11
    //   55: newarray char
    //   57: dup
    //   58: iconst_0
    //   59: ldc 62
    //   61: castore
    //   62: dup
    //   63: iconst_1
    //   64: ldc 63
    //   66: castore
    //   67: dup
    //   68: iconst_2
    //   69: ldc 45
    //   71: castore
    //   72: dup
    //   73: iconst_3
    //   74: ldc 64
    //   76: castore
    //   77: dup
    //   78: iconst_4
    //   79: ldc 65
    //   81: castore
    //   82: dup
    //   83: iconst_5
    //   84: ldc 66
    //   86: castore
    //   87: dup
    //   88: bipush 6
    //   90: ldc 67
    //   92: castore
    //   93: dup
    //   94: bipush 7
    //   96: ldc 68
    //   98: castore
    //   99: dup
    //   100: bipush 8
    //   102: ldc 46
    //   104: castore
    //   105: dup
    //   106: bipush 9
    //   108: ldc 69
    //   110: castore
    //   111: dup
    //   112: bipush 10
    //   114: ldc 67
    //   116: castore
    //   117: iconst_2
    //   118: iconst_0
    //   119: invokestatic 50	o/Iy:ॱ	(II[CIZ)Ljava/lang/String;
    //   122: invokevirtual 56	java/lang/String:intern	()Ljava/lang/String;
    //   125: invokestatic 61	o/vq:ˎ	(Ljava/lang/Object;Ljava/lang/String;)V
    //   128: aload_0
    //   129: invokespecial 71	o/W:<init>	()V
    //   132: aload_0
    //   133: aload_1
    //   134: putfield 73	o/Iy:ˎ	Lo/Iu$if;
    //   137: aload_0
    //   138: aload_2
    //   139: putfield 75	o/Iy:ˊ	Lo/Ib;
    //   142: new 9	o/Iy$3
    //   145: dup
    //   146: aload_0
    //   147: invokespecial 78	o/Iy$3:<init>	(Lo/Iy;)V
    //   150: checkcast 80	o/sW
    //   153: invokestatic 85	o/un:ˎ	(Lo/sW;)V
    //   156: goto +17 -> 173
    //   159: astore_1
    //   160: aload_1
    //   161: invokevirtual 91	java/lang/Throwable:getCause	()Ljava/lang/Throwable;
    //   164: astore_2
    //   165: aload_2
    //   166: ifnull +5 -> 171
    //   169: aload_2
    //   170: athrow
    //   171: aload_1
    //   172: athrow
    //   173: iconst_3
    //   174: bipush 24
    //   176: iconst_0
    //   177: invokestatic 97	o/O:ˋ	(IIC)Ljava/lang/Object;
    //   180: checkcast 99	java/lang/Class
    //   183: ldc 100
    //   185: aconst_null
    //   186: invokevirtual 104	java/lang/Class:getMethod	(Ljava/lang/String;[Ljava/lang/Class;)Ljava/lang/reflect/Method;
    //   189: aconst_null
    //   190: aconst_null
    //   191: invokevirtual 110	java/lang/reflect/Method:invoke	(Ljava/lang/Object;[Ljava/lang/Object;)Ljava/lang/Object;
    //   194: checkcast 112	o/L
    //   197: astore_1
    //   198: aload_1
    //   199: sipush 194
    //   202: bipush 20
    //   204: bipush 20
    //   206: newarray char
    //   208: dup
    //   209: iconst_0
    //   210: ldc 68
    //   212: castore
    //   213: dup
    //   214: iconst_1
    //   215: ldc 113
    //   217: castore
    //   218: dup
    //   219: iconst_2
    //   220: ldc 114
    //   222: castore
    //   223: dup
    //   224: iconst_3
    //   225: ldc 115
    //   227: castore
    //   228: dup
    //   229: iconst_4
    //   230: ldc 116
    //   232: castore
    //   233: dup
    //   234: iconst_5
    //   235: ldc 68
    //   237: castore
    //   238: dup
    //   239: bipush 6
    //   241: ldc 117
    //   243: castore
    //   244: dup
    //   245: bipush 7
    //   247: ldc 118
    //   249: castore
    //   250: dup
    //   251: bipush 8
    //   253: ldc 119
    //   255: castore
    //   256: dup
    //   257: bipush 9
    //   259: ldc 68
    //   261: castore
    //   262: dup
    //   263: bipush 10
    //   265: ldc 117
    //   267: castore
    //   268: dup
    //   269: bipush 11
    //   271: ldc 67
    //   273: castore
    //   274: dup
    //   275: bipush 12
    //   277: ldc 120
    //   279: castore
    //   280: dup
    //   281: bipush 13
    //   283: ldc 67
    //   285: castore
    //   286: dup
    //   287: bipush 14
    //   289: ldc 121
    //   291: castore
    //   292: dup
    //   293: bipush 15
    //   295: ldc 63
    //   297: castore
    //   298: dup
    //   299: bipush 16
    //   301: ldc 119
    //   303: castore
    //   304: dup
    //   305: bipush 17
    //   307: ldc 122
    //   309: castore
    //   310: dup
    //   311: bipush 18
    //   313: ldc 123
    //   315: castore
    //   316: dup
    //   317: bipush 19
    //   319: ldc 116
    //   321: castore
    //   322: iconst_2
    //   323: iconst_1
    //   324: invokestatic 50	o/Iy:ॱ	(II[CIZ)Ljava/lang/String;
    //   327: invokevirtual 56	java/lang/String:intern	()Ljava/lang/String;
    //   330: invokestatic 125	o/vq:ˋ	(Ljava/lang/Object;Ljava/lang/String;)V
    //   333: aload_0
    //   334: aload_1
    //   335: putfield 127	o/Iy:ˋ$4622a72	Lo/L;
    //   338: return
    // Local variable table:
    //   start	length	slot	name	signature
    //   0	339	0	this	Iy
    //   0	339	1	paramV	V
    //   0	339	2	paramR	R
    // Exception table:
    //   from	to	target	type
    //   173	198	159	finally
  }
  
  /* Error */
  private final void ˊ(Throwable paramThrowable)
  {
    // Byte code:
    //   0: goto +397 -> 397
    //   3: aload_1
    //   4: instanceof 136
    //   7: ifeq +6 -> 13
    //   10: goto +450 -> 460
    //   13: goto +514 -> 527
    //   16: bipush 39
    //   18: istore_2
    //   19: goto +549 -> 568
    //   22: bipush 81
    //   24: istore_2
    //   25: goto +473 -> 498
    //   28: aload_0
    //   29: invokevirtual 139	o/Iy:C_	()V
    //   32: return
    //   33: aload_3
    //   34: invokevirtual 144	o/xF:ʻ	()Ljava/lang/String;
    //   37: astore_3
    //   38: new 146	o/nD
    //   41: dup
    //   42: invokespecial 147	o/nD:<init>	()V
    //   45: invokevirtual 150	o/nD:ˎ	()Lo/nD;
    //   48: invokevirtual 153	o/nD:ˏ	()Lo/nw;
    //   51: aload_3
    //   52: ldc -101
    //   54: invokevirtual 160	o/nw:ˏ	(Ljava/lang/String;Ljava/lang/Class;)Ljava/lang/Object;
    //   57: checkcast 155	o/Fg
    //   60: astore_3
    //   61: aload_3
    //   62: ifnull +6 -> 68
    //   65: goto +368 -> 433
    //   68: goto +351 -> 419
    //   71: astore_3
    //   72: sipush 206
    //   75: bipush 7
    //   77: bipush 7
    //   79: newarray char
    //   81: dup
    //   82: iconst_0
    //   83: ldc -95
    //   85: castore
    //   86: dup
    //   87: iconst_1
    //   88: ldc -94
    //   90: castore
    //   91: dup
    //   92: iconst_2
    //   93: ldc -93
    //   95: castore
    //   96: dup
    //   97: iconst_3
    //   98: ldc 63
    //   100: castore
    //   101: dup
    //   102: iconst_4
    //   103: ldc 43
    //   105: castore
    //   106: dup
    //   107: iconst_5
    //   108: ldc 69
    //   110: castore
    //   111: dup
    //   112: bipush 6
    //   114: ldc 45
    //   116: castore
    //   117: bipush 7
    //   119: iconst_0
    //   120: invokestatic 50	o/Iy:ॱ	(II[CIZ)Ljava/lang/String;
    //   123: invokevirtual 56	java/lang/String:intern	()Ljava/lang/String;
    //   126: astore 4
    //   128: aload_3
    //   129: invokevirtual 166	java/io/IOException:getMessage	()Ljava/lang/String;
    //   132: astore 5
    //   134: goto +17 -> 151
    //   137: astore_1
    //   138: aload_1
    //   139: invokevirtual 91	java/lang/Throwable:getCause	()Ljava/lang/Throwable;
    //   142: astore_3
    //   143: aload_3
    //   144: ifnull +5 -> 149
    //   147: aload_3
    //   148: athrow
    //   149: aload_1
    //   150: athrow
    //   151: iconst_4
    //   152: bipush 42
    //   154: ldc -89
    //   156: invokestatic 97	o/O:ˋ	(IIC)Ljava/lang/Object;
    //   159: checkcast 99	java/lang/Class
    //   162: ldc -88
    //   164: iconst_2
    //   165: anewarray 99	java/lang/Class
    //   168: dup
    //   169: iconst_0
    //   170: ldc 52
    //   172: aastore
    //   173: dup
    //   174: iconst_1
    //   175: ldc 52
    //   177: aastore
    //   178: invokevirtual 104	java/lang/Class:getMethod	(Ljava/lang/String;[Ljava/lang/Class;)Ljava/lang/reflect/Method;
    //   181: aconst_null
    //   182: iconst_2
    //   183: anewarray 170	java/lang/Object
    //   186: dup
    //   187: iconst_0
    //   188: aload 4
    //   190: aastore
    //   191: dup
    //   192: iconst_1
    //   193: aload 5
    //   195: aastore
    //   196: invokevirtual 110	java/lang/reflect/Method:invoke	(Ljava/lang/Object;[Ljava/lang/Object;)Ljava/lang/Object;
    //   199: pop
    //   200: aload_0
    //   201: new 155	o/Fg
    //   204: dup
    //   205: aload_1
    //   206: invokevirtual 175	o/CG:ˏ	()I
    //   209: aload_3
    //   210: invokevirtual 166	java/io/IOException:getMessage	()Ljava/lang/String;
    //   213: ldc -79
    //   215: invokespecial 180	o/Fg:<init>	(ILjava/lang/String;Ljava/lang/String;)V
    //   218: invokespecial 183	o/Iy:ॱ	(Lo/Fg;)V
    //   221: goto +209 -> 430
    //   224: goto +206 -> 430
    //   227: aload_1
    //   228: invokevirtual 91	java/lang/Throwable:getCause	()Ljava/lang/Throwable;
    //   231: astore_1
    //   232: goto +311 -> 543
    //   235: aload_1
    //   236: checkcast 136	o/CE
    //   239: invokevirtual 186	o/CE:ˋ	()Lo/CG;
    //   242: astore_1
    //   243: aload_1
    //   244: sipush 199
    //   247: bipush 20
    //   249: bipush 20
    //   251: newarray char
    //   253: dup
    //   254: iconst_0
    //   255: ldc 62
    //   257: castore
    //   258: dup
    //   259: iconst_1
    //   260: ldc 122
    //   262: castore
    //   263: dup
    //   264: iconst_2
    //   265: ldc 63
    //   267: castore
    //   268: dup
    //   269: iconst_3
    //   270: ldc -69
    //   272: castore
    //   273: dup
    //   274: iconst_4
    //   275: ldc -68
    //   277: castore
    //   278: dup
    //   279: iconst_5
    //   280: ldc -67
    //   282: castore
    //   283: dup
    //   284: bipush 6
    //   286: ldc -69
    //   288: castore
    //   289: dup
    //   290: bipush 7
    //   292: ldc -66
    //   294: castore
    //   295: dup
    //   296: bipush 8
    //   298: ldc -65
    //   300: castore
    //   301: dup
    //   302: bipush 9
    //   304: ldc -69
    //   306: castore
    //   307: dup
    //   308: bipush 10
    //   310: ldc 120
    //   312: castore
    //   313: dup
    //   314: bipush 11
    //   316: ldc -64
    //   318: castore
    //   319: dup
    //   320: bipush 12
    //   322: ldc -63
    //   324: castore
    //   325: dup
    //   326: bipush 13
    //   328: ldc 63
    //   330: castore
    //   331: dup
    //   332: bipush 14
    //   334: ldc 120
    //   336: castore
    //   337: dup
    //   338: bipush 15
    //   340: ldc -69
    //   342: castore
    //   343: dup
    //   344: bipush 16
    //   346: ldc 47
    //   348: castore
    //   349: dup
    //   350: bipush 17
    //   352: ldc 114
    //   354: castore
    //   355: dup
    //   356: bipush 18
    //   358: ldc -64
    //   360: castore
    //   361: dup
    //   362: bipush 19
    //   364: ldc -63
    //   366: castore
    //   367: bipush 7
    //   369: iconst_1
    //   370: invokestatic 50	o/Iy:ॱ	(II[CIZ)Ljava/lang/String;
    //   373: invokevirtual 56	java/lang/String:intern	()Ljava/lang/String;
    //   376: invokestatic 125	o/vq:ˋ	(Ljava/lang/Object;Ljava/lang/String;)V
    //   379: aload_1
    //   380: invokevirtual 196	o/CG:ˎ	()Lo/xF;
    //   383: astore_3
    //   384: aload_3
    //   385: ifnull +6 -> 391
    //   388: goto -355 -> 33
    //   391: goto +161 -> 552
    //   394: goto -391 -> 3
    //   397: goto +9 -> 406
    //   400: bipush 67
    //   402: istore_2
    //   403: goto +165 -> 568
    //   406: aload_1
    //   407: instanceof 198
    //   410: ifeq +6 -> 416
    //   413: goto -13 -> 400
    //   416: goto -400 -> 16
    //   419: aload_0
    //   420: aload_3
    //   421: invokespecial 183	o/Iy:ॱ	(Lo/Fg;)V
    //   424: goto -200 -> 224
    //   427: goto -399 -> 28
    //   430: goto +346 -> 776
    //   433: getstatic 35	o/Iy:ᐝ	I
    //   436: bipush 57
    //   438: iadd
    //   439: istore_2
    //   440: iload_2
    //   441: sipush 128
    //   444: irem
    //   445: putstatic 37	o/Iy:ʼ	I
    //   448: iload_2
    //   449: iconst_2
    //   450: irem
    //   451: ifne +6 -> 457
    //   454: goto +86 -> 540
    //   457: goto +30 -> 487
    //   460: getstatic 35	o/Iy:ᐝ	I
    //   463: bipush 57
    //   465: iadd
    //   466: istore_2
    //   467: iload_2
    //   468: sipush 128
    //   471: irem
    //   472: putstatic 37	o/Iy:ʼ	I
    //   475: iload_2
    //   476: iconst_2
    //   477: irem
    //   478: ifne +6 -> 484
    //   481: goto +84 -> 565
    //   484: goto -249 -> 235
    //   487: aload_3
    //   488: aload_1
    //   489: invokevirtual 175	o/CG:ˏ	()I
    //   492: putfield 201	o/Fg:httpStatusCode	I
    //   495: goto -76 -> 419
    //   498: iload_2
    //   499: lookupswitch	default:+25->524, 57:+100->599, 81:+-471->28
    //   524: goto +75 -> 599
    //   527: aload_1
    //   528: instanceof 132
    //   531: ifeq +6 -> 537
    //   534: goto -107 -> 427
    //   537: goto +73 -> 610
    //   540: goto -53 -> 487
    //   543: goto -540 -> 3
    //   546: bipush 57
    //   548: istore_2
    //   549: goto -51 -> 498
    //   552: aload_0
    //   553: getfield 73	o/Iy:ˎ	Lo/Iu$if;
    //   556: aconst_null
    //   557: invokeinterface 206 2 0
    //   562: goto +214 -> 776
    //   565: goto -330 -> 235
    //   568: iload_2
    //   569: lookupswitch	default:+27->596, 39:+-175->394, 67:+-342->227
    //   596: goto -369 -> 227
    //   599: aload_0
    //   600: getfield 73	o/Iy:ˎ	Lo/Iu$if;
    //   603: aconst_null
    //   604: invokeinterface 206 2 0
    //   609: return
    //   610: aload_1
    //   611: instanceof 208
    //   614: ifeq +6 -> 620
    //   617: goto -595 -> 22
    //   620: goto -74 -> 546
    //   623: astore_3
    //   624: sipush 206
    //   627: bipush 7
    //   629: bipush 7
    //   631: newarray char
    //   633: dup
    //   634: iconst_0
    //   635: ldc -95
    //   637: castore
    //   638: dup
    //   639: iconst_1
    //   640: ldc -94
    //   642: castore
    //   643: dup
    //   644: iconst_2
    //   645: ldc -93
    //   647: castore
    //   648: dup
    //   649: iconst_3
    //   650: ldc 63
    //   652: castore
    //   653: dup
    //   654: iconst_4
    //   655: ldc 43
    //   657: castore
    //   658: dup
    //   659: iconst_5
    //   660: ldc 69
    //   662: castore
    //   663: dup
    //   664: bipush 6
    //   666: ldc 45
    //   668: castore
    //   669: bipush 7
    //   671: iconst_0
    //   672: invokestatic 50	o/Iy:ॱ	(II[CIZ)Ljava/lang/String;
    //   675: invokevirtual 56	java/lang/String:intern	()Ljava/lang/String;
    //   678: astore 4
    //   680: aload_3
    //   681: invokevirtual 209	o/nM:getMessage	()Ljava/lang/String;
    //   684: astore 5
    //   686: goto +17 -> 703
    //   689: astore_1
    //   690: aload_1
    //   691: invokevirtual 91	java/lang/Throwable:getCause	()Ljava/lang/Throwable;
    //   694: astore_3
    //   695: aload_3
    //   696: ifnull +5 -> 701
    //   699: aload_3
    //   700: athrow
    //   701: aload_1
    //   702: athrow
    //   703: iconst_4
    //   704: bipush 42
    //   706: ldc -89
    //   708: invokestatic 97	o/O:ˋ	(IIC)Ljava/lang/Object;
    //   711: checkcast 99	java/lang/Class
    //   714: ldc -88
    //   716: iconst_2
    //   717: anewarray 99	java/lang/Class
    //   720: dup
    //   721: iconst_0
    //   722: ldc 52
    //   724: aastore
    //   725: dup
    //   726: iconst_1
    //   727: ldc 52
    //   729: aastore
    //   730: invokevirtual 104	java/lang/Class:getMethod	(Ljava/lang/String;[Ljava/lang/Class;)Ljava/lang/reflect/Method;
    //   733: aconst_null
    //   734: iconst_2
    //   735: anewarray 170	java/lang/Object
    //   738: dup
    //   739: iconst_0
    //   740: aload 4
    //   742: aastore
    //   743: dup
    //   744: iconst_1
    //   745: aload 5
    //   747: aastore
    //   748: invokevirtual 110	java/lang/reflect/Method:invoke	(Ljava/lang/Object;[Ljava/lang/Object;)Ljava/lang/Object;
    //   751: pop
    //   752: aload_0
    //   753: new 155	o/Fg
    //   756: dup
    //   757: aload_1
    //   758: invokevirtual 175	o/CG:ˏ	()I
    //   761: aload_3
    //   762: invokevirtual 209	o/nM:getMessage	()Ljava/lang/String;
    //   765: ldc -79
    //   767: invokespecial 180	o/Fg:<init>	(ILjava/lang/String;Ljava/lang/String;)V
    //   770: invokespecial 183	o/Iy:ॱ	(Lo/Fg;)V
    //   773: goto -343 -> 430
    //   776: return
    // Local variable table:
    //   start	length	slot	name	signature
    //   0	777	0	this	Iy
    //   0	777	1	paramThrowable	Throwable
    //   18	551	2	i	int
    //   33	29	3	localObject1	Object
    //   71	58	3	localIOException	java.io.IOException
    //   142	346	3	localObject2	Object
    //   623	58	3	localNM	nM
    //   694	68	3	localThrowable	Throwable
    //   126	615	4	str1	String
    //   132	614	5	str2	String
    // Exception table:
    //   from	to	target	type
    //   33	61	71	java/io/IOException
    //   419	424	71	java/io/IOException
    //   487	495	71	java/io/IOException
    //   151	200	137	finally
    //   33	61	623	o/nM
    //   419	424	623	o/nM
    //   487	495	623	o/nM
    //   703	752	689	finally
  }
  
  /* Error */
  private static String ॱ(int paramInt1, int paramInt2, char[] paramArrayOfChar, int paramInt3, boolean paramBoolean)
  {
    // Byte code:
    //   0: goto +107 -> 107
    //   3: aload_2
    //   4: iload_0
    //   5: aload 7
    //   7: iload_3
    //   8: iload_0
    //   9: isub
    //   10: iconst_1
    //   11: isub
    //   12: caload
    //   13: castore
    //   14: iload_0
    //   15: iconst_1
    //   16: iadd
    //   17: istore_0
    //   18: goto +125 -> 143
    //   21: bipush 40
    //   23: istore_1
    //   24: goto +236 -> 260
    //   27: iload 5
    //   29: tableswitch	default:+23->52, 0:+329->358, 1:+168->197
    //   52: goto +145 -> 197
    //   55: getstatic 35	o/Iy:ᐝ	I
    //   58: bipush 13
    //   60: iadd
    //   61: istore 5
    //   63: iload 5
    //   65: sipush 128
    //   68: irem
    //   69: putstatic 37	o/Iy:ʼ	I
    //   72: iload 5
    //   74: iconst_2
    //   75: irem
    //   76: ifne +6 -> 82
    //   79: goto +218 -> 297
    //   82: goto +209 -> 291
    //   85: goto +77 -> 162
    //   88: aload_2
    //   89: iload_0
    //   90: aload 7
    //   92: iload_3
    //   93: iload_0
    //   94: idiv
    //   95: iconst_0
    //   96: iadd
    //   97: caload
    //   98: castore
    //   99: iload_0
    //   100: bipush 112
    //   102: iadd
    //   103: istore_0
    //   104: goto +39 -> 143
    //   107: goto -52 -> 55
    //   110: getstatic 37	o/Iy:ʼ	I
    //   113: bipush 29
    //   115: iadd
    //   116: istore_1
    //   117: iload_1
    //   118: sipush 128
    //   121: irem
    //   122: putstatic 35	o/Iy:ᐝ	I
    //   125: iload_1
    //   126: iconst_2
    //   127: irem
    //   128: ifeq +6 -> 134
    //   131: goto +6 -> 137
    //   134: goto -113 -> 21
    //   137: bipush 35
    //   139: istore_1
    //   140: goto +120 -> 260
    //   143: iload_0
    //   144: iload_3
    //   145: if_icmpge +6 -> 151
    //   148: goto -38 -> 110
    //   151: goto +190 -> 341
    //   154: iload_3
    //   155: istore 6
    //   157: iload_1
    //   158: istore_3
    //   159: goto +23 -> 182
    //   162: iload 4
    //   164: ifeq +6 -> 170
    //   167: goto +6 -> 173
    //   170: goto +38 -> 208
    //   173: iload_3
    //   174: newarray char
    //   176: astore_2
    //   177: iconst_0
    //   178: istore_0
    //   179: goto -36 -> 143
    //   182: iload 5
    //   184: iload_3
    //   185: if_icmpge +6 -> 191
    //   188: goto +115 -> 303
    //   191: goto +156 -> 347
    //   194: astore_2
    //   195: aload_2
    //   196: athrow
    //   197: iload_1
    //   198: newarray char
    //   200: astore 7
    //   202: iconst_0
    //   203: istore 5
    //   205: goto -51 -> 154
    //   208: new 52	java/lang/String
    //   211: dup
    //   212: aload 7
    //   214: invokespecial 217	java/lang/String:<init>	([C)V
    //   217: areturn
    //   218: iload_3
    //   219: newarray char
    //   221: astore_2
    //   222: aload 7
    //   224: iconst_0
    //   225: aload_2
    //   226: iconst_0
    //   227: iload_3
    //   228: invokestatic 223	java/lang/System:arraycopy	(Ljava/lang/Object;ILjava/lang/Object;II)V
    //   231: aload_2
    //   232: iconst_0
    //   233: aload 7
    //   235: iload_3
    //   236: iload 6
    //   238: isub
    //   239: iload 6
    //   241: invokestatic 223	java/lang/System:arraycopy	(Ljava/lang/Object;ILjava/lang/Object;II)V
    //   244: aload_2
    //   245: iload 6
    //   247: aload 7
    //   249: iconst_0
    //   250: iload_3
    //   251: iload 6
    //   253: isub
    //   254: invokestatic 223	java/lang/System:arraycopy	(Ljava/lang/Object;ILjava/lang/Object;II)V
    //   257: goto -172 -> 85
    //   260: iload_1
    //   261: lookupswitch	default:+27->288, 35:+-173->88, 40:+-258->3
    //   288: goto -200 -> 88
    //   291: iconst_1
    //   292: istore 5
    //   294: goto -267 -> 27
    //   297: iconst_0
    //   298: istore 5
    //   300: goto -273 -> 27
    //   303: aload 7
    //   305: iload 5
    //   307: iload_0
    //   308: aload_2
    //   309: iload 5
    //   311: caload
    //   312: iadd
    //   313: i2c
    //   314: castore
    //   315: aload 7
    //   317: iload 5
    //   319: caload
    //   320: istore_1
    //   321: aload 7
    //   323: iload 5
    //   325: iload_1
    //   326: getstatic 39	o/Iy:ॱ	I
    //   329: isub
    //   330: i2c
    //   331: castore
    //   332: iload 5
    //   334: iconst_1
    //   335: iadd
    //   336: istore 5
    //   338: goto -156 -> 182
    //   341: aload_2
    //   342: astore 7
    //   344: goto -136 -> 208
    //   347: iload 6
    //   349: ifle +6 -> 355
    //   352: goto -134 -> 218
    //   355: goto -193 -> 162
    //   358: iload_1
    //   359: newarray char
    //   361: astore 7
    //   363: iconst_1
    //   364: istore 5
    //   366: goto -212 -> 154
    // Local variable table:
    //   start	length	slot	name	signature
    //   0	369	0	paramInt1	int
    //   0	369	1	paramInt2	int
    //   0	369	2	paramArrayOfChar	char[]
    //   0	369	3	paramInt3	int
    //   0	369	4	paramBoolean	boolean
    //   27	338	5	i	int
    //   155	193	6	j	int
    //   5	357	7	arrayOfChar	char[]
    // Exception table:
    //   from	to	target	type
    //   321	332	194	java/lang/Exception
  }
  
  /* Error */
  private final void ॱ(Fg paramFg)
  {
    // Byte code:
    //   0: goto +529 -> 529
    //   3: aload 4
    //   5: getstatic 229	o/EF:MULTIPLE_WALLETS	Lo/EF;
    //   8: invokevirtual 231	o/EF:ˏ	()Ljava/lang/String;
    //   11: invokestatic 234	o/vq:ˊ	(Ljava/lang/Object;Ljava/lang/Object;)Z
    //   14: ifeq +6 -> 20
    //   17: goto +384 -> 401
    //   20: goto +234 -> 254
    //   23: aload 4
    //   25: getstatic 237	o/EF:BLACKLISTED_DEVICE	Lo/EF;
    //   28: invokevirtual 231	o/EF:ˏ	()Ljava/lang/String;
    //   31: invokestatic 234	o/vq:ˊ	(Ljava/lang/Object;Ljava/lang/Object;)Z
    //   34: ifeq +6 -> 40
    //   37: goto +1117 -> 1154
    //   40: goto +220 -> 260
    //   43: iconst_4
    //   44: sipush 413
    //   47: sipush 30253
    //   50: invokestatic 97	o/O:ˋ	(IIC)Ljava/lang/Object;
    //   53: checkcast 99	java/lang/Class
    //   56: ldc -18
    //   58: invokevirtual 242	java/lang/Class:getField	(Ljava/lang/String;)Ljava/lang/reflect/Field;
    //   61: aconst_null
    //   62: invokevirtual 248	java/lang/reflect/Field:get	(Ljava/lang/Object;)Ljava/lang/Object;
    //   65: astore 4
    //   67: goto +20 -> 87
    //   70: astore_1
    //   71: aload_1
    //   72: invokevirtual 91	java/lang/Throwable:getCause	()Ljava/lang/Throwable;
    //   75: astore 4
    //   77: aload 4
    //   79: ifnull +6 -> 85
    //   82: aload 4
    //   84: athrow
    //   85: aload_1
    //   86: athrow
    //   87: bipush 6
    //   89: sipush 417
    //   92: iconst_0
    //   93: invokestatic 97	o/O:ˋ	(IIC)Ljava/lang/Object;
    //   96: checkcast 99	java/lang/Class
    //   99: ldc -7
    //   101: aconst_null
    //   102: invokevirtual 104	java/lang/Class:getMethod	(Ljava/lang/String;[Ljava/lang/Class;)Ljava/lang/reflect/Method;
    //   105: aload 4
    //   107: aconst_null
    //   108: invokevirtual 110	java/lang/reflect/Method:invoke	(Ljava/lang/Object;[Ljava/lang/Object;)Ljava/lang/Object;
    //   111: astore 4
    //   113: goto +20 -> 133
    //   116: astore_1
    //   117: aload_1
    //   118: invokevirtual 91	java/lang/Throwable:getCause	()Ljava/lang/Throwable;
    //   121: astore 4
    //   123: aload 4
    //   125: ifnull +6 -> 131
    //   128: aload 4
    //   130: athrow
    //   131: aload_1
    //   132: athrow
    //   133: iconst_4
    //   134: sipush 413
    //   137: sipush 30253
    //   140: invokestatic 97	o/O:ˋ	(IIC)Ljava/lang/Object;
    //   143: checkcast 99	java/lang/Class
    //   146: ldc -5
    //   148: aconst_null
    //   149: invokevirtual 104	java/lang/Class:getMethod	(Ljava/lang/String;[Ljava/lang/Class;)Ljava/lang/reflect/Method;
    //   152: aload 4
    //   154: aconst_null
    //   155: invokevirtual 110	java/lang/reflect/Method:invoke	(Ljava/lang/Object;[Ljava/lang/Object;)Ljava/lang/Object;
    //   158: checkcast 253	java/lang/Boolean
    //   161: invokevirtual 257	java/lang/Boolean:booleanValue	()Z
    //   164: istore_3
    //   165: iload_3
    //   166: ifeq +6 -> 172
    //   169: goto +23 -> 192
    //   172: goto +207 -> 379
    //   175: aload_1
    //   176: invokevirtual 260	o/Fg:ˎ	()Lo/Fd;
    //   179: astore 4
    //   181: aload 4
    //   183: ifnull +6 -> 189
    //   186: goto +308 -> 494
    //   189: goto +281 -> 470
    //   192: aload_0
    //   193: getfield 75	o/Iy:ˊ	Lo/Ib;
    //   196: invokeinterface 265 1 0
    //   201: iconst_1
    //   202: invokeinterface 270 2 0
    //   207: aload_0
    //   208: getfield 73	o/Iy:ˎ	Lo/Iu$if;
    //   211: invokeinterface 273 1 0
    //   216: goto +254 -> 470
    //   219: aload_1
    //   220: invokevirtual 260	o/Fg:ˎ	()Lo/Fd;
    //   223: astore 5
    //   225: aconst_null
    //   226: arraylength
    //   227: istore_2
    //   228: aload 5
    //   230: ifnull +6 -> 236
    //   233: goto +288 -> 521
    //   236: goto +112 -> 348
    //   239: aload_0
    //   240: getfield 73	o/Iy:ˎ	Lo/Iu$if;
    //   243: invokeinterface 276 1 0
    //   248: goto +222 -> 470
    //   251: astore_1
    //   252: aload_1
    //   253: athrow
    //   254: bipush 73
    //   256: istore_2
    //   257: goto +36 -> 293
    //   260: getstatic 279	o/EF:BLACKLISTED_MOBILE_APP_VERSION	Lo/EF;
    //   263: astore 5
    //   265: aload 5
    //   267: invokevirtual 231	o/EF:ˏ	()Ljava/lang/String;
    //   270: astore 5
    //   272: aload 4
    //   274: aload 5
    //   276: invokestatic 234	o/vq:ˊ	(Ljava/lang/Object;Ljava/lang/Object;)Z
    //   279: istore_3
    //   280: iload_3
    //   281: ifeq +6 -> 287
    //   284: goto +843 -> 1127
    //   287: goto -284 -> 3
    //   290: goto -51 -> 239
    //   293: iload_2
    //   294: lookupswitch	default:+26->320, 69:+149->443, 73:+-251->43
    //   320: goto -277 -> 43
    //   323: getstatic 37	o/Iy:ʼ	I
    //   326: bipush 39
    //   328: iadd
    //   329: istore_2
    //   330: iload_2
    //   331: sipush 128
    //   334: irem
    //   335: putstatic 35	o/Iy:ᐝ	I
    //   338: iload_2
    //   339: iconst_2
    //   340: irem
    //   341: ifeq +6 -> 347
    //   344: goto +56 -> 400
    //   347: return
    //   348: iconst_0
    //   349: istore_2
    //   350: goto +57 -> 407
    //   353: iload_2
    //   354: tableswitch	default:+22->376, 0:+116->470, 1:+178->532
    //   376: goto +94 -> 470
    //   379: aload_0
    //   380: getfield 73	o/Iy:ˎ	Lo/Iu$if;
    //   383: aload_1
    //   384: getfield 283	o/Fg:error	Lo/Fd;
    //   387: invokeinterface 206 2 0
    //   392: goto +78 -> 470
    //   395: iconst_0
    //   396: istore_2
    //   397: goto -44 -> 353
    //   400: return
    //   401: bipush 69
    //   403: istore_2
    //   404: goto -111 -> 293
    //   407: aload 5
    //   409: astore 4
    //   411: iload_2
    //   412: tableswitch	default:+24->436, 0:+58->470, 1:+82->494
    //   436: aload 5
    //   438: astore 4
    //   440: goto +54 -> 494
    //   443: getstatic 35	o/Iy:ᐝ	I
    //   446: bipush 7
    //   448: iadd
    //   449: istore_2
    //   450: iload_2
    //   451: sipush 128
    //   454: irem
    //   455: putstatic 37	o/Iy:ʼ	I
    //   458: iload_2
    //   459: iconst_2
    //   460: irem
    //   461: ifne +6 -> 467
    //   464: goto -174 -> 290
    //   467: goto -228 -> 239
    //   470: goto -147 -> 323
    //   473: iconst_1
    //   474: istore_2
    //   475: goto -122 -> 353
    //   478: astore_1
    //   479: aload_1
    //   480: athrow
    //   481: aload_1
    //   482: ifnull +6 -> 488
    //   485: goto -12 -> 473
    //   488: goto -93 -> 395
    //   491: goto -21 -> 470
    //   494: aload 4
    //   496: getfield 289	o/Fd:code	Ljava/lang/String;
    //   499: astore 4
    //   501: aload 4
    //   503: getstatic 292	o/EF:BTW_INACTIVE_WALLET	Lo/EF;
    //   506: invokevirtual 231	o/EF:ˏ	()Ljava/lang/String;
    //   509: invokestatic 234	o/vq:ˊ	(Ljava/lang/Object;Ljava/lang/Object;)Z
    //   512: ifeq +6 -> 518
    //   515: goto +44 -> 559
    //   518: goto -495 -> 23
    //   521: iconst_1
    //   522: istore_2
    //   523: goto -116 -> 407
    //   526: goto +574 -> 1100
    //   529: goto -48 -> 481
    //   532: getstatic 37	o/Iy:ʼ	I
    //   535: bipush 41
    //   537: iadd
    //   538: istore_2
    //   539: iload_2
    //   540: sipush 128
    //   543: irem
    //   544: putstatic 35	o/Iy:ᐝ	I
    //   547: iload_2
    //   548: iconst_2
    //   549: irem
    //   550: ifeq +6 -> 556
    //   553: goto -334 -> 219
    //   556: goto -381 -> 175
    //   559: sipush 206
    //   562: bipush 7
    //   564: bipush 7
    //   566: newarray char
    //   568: dup
    //   569: iconst_0
    //   570: ldc -95
    //   572: castore
    //   573: dup
    //   574: iconst_1
    //   575: ldc -94
    //   577: castore
    //   578: dup
    //   579: iconst_2
    //   580: ldc -93
    //   582: castore
    //   583: dup
    //   584: iconst_3
    //   585: ldc 63
    //   587: castore
    //   588: dup
    //   589: iconst_4
    //   590: ldc 43
    //   592: castore
    //   593: dup
    //   594: iconst_5
    //   595: ldc 69
    //   597: castore
    //   598: dup
    //   599: bipush 6
    //   601: ldc 45
    //   603: castore
    //   604: bipush 7
    //   606: iconst_0
    //   607: invokestatic 50	o/Iy:ॱ	(II[CIZ)Ljava/lang/String;
    //   610: invokevirtual 56	java/lang/String:intern	()Ljava/lang/String;
    //   613: astore 4
    //   615: new 294	java/lang/StringBuilder
    //   618: dup
    //   619: invokespecial 295	java/lang/StringBuilder:<init>	()V
    //   622: sipush 192
    //   625: bipush 18
    //   627: bipush 18
    //   629: newarray char
    //   631: dup
    //   632: iconst_0
    //   633: ldc_w 296
    //   636: castore
    //   637: dup
    //   638: iconst_1
    //   639: ldc 116
    //   641: castore
    //   642: dup
    //   643: iconst_2
    //   644: ldc 116
    //   646: castore
    //   647: dup
    //   648: iconst_3
    //   649: ldc_w 297
    //   652: castore
    //   653: dup
    //   654: iconst_4
    //   655: ldc_w 298
    //   658: castore
    //   659: dup
    //   660: iconst_5
    //   661: ldc_w 299
    //   664: castore
    //   665: dup
    //   666: bipush 6
    //   668: ldc_w 300
    //   671: castore
    //   672: dup
    //   673: bipush 7
    //   675: ldc_w 301
    //   678: castore
    //   679: dup
    //   680: bipush 8
    //   682: ldc 117
    //   684: castore
    //   685: dup
    //   686: bipush 9
    //   688: ldc 123
    //   690: castore
    //   691: dup
    //   692: bipush 10
    //   694: ldc -67
    //   696: castore
    //   697: dup
    //   698: bipush 11
    //   700: ldc 117
    //   702: castore
    //   703: dup
    //   704: bipush 12
    //   706: ldc 116
    //   708: castore
    //   709: dup
    //   710: bipush 13
    //   712: ldc_w 298
    //   715: castore
    //   716: dup
    //   717: bipush 14
    //   719: ldc_w 302
    //   722: castore
    //   723: dup
    //   724: bipush 15
    //   726: ldc 63
    //   728: castore
    //   729: dup
    //   730: bipush 16
    //   732: ldc_w 298
    //   735: castore
    //   736: dup
    //   737: bipush 17
    //   739: ldc 116
    //   741: castore
    //   742: iconst_4
    //   743: iconst_1
    //   744: invokestatic 50	o/Iy:ॱ	(II[CIZ)Ljava/lang/String;
    //   747: invokevirtual 56	java/lang/String:intern	()Ljava/lang/String;
    //   750: invokevirtual 306	java/lang/StringBuilder:append	(Ljava/lang/String;)Ljava/lang/StringBuilder;
    //   753: aload_1
    //   754: invokevirtual 260	o/Fg:ˎ	()Lo/Fd;
    //   757: invokevirtual 308	o/Fd:ˎ	()Ljava/lang/String;
    //   760: invokevirtual 306	java/lang/StringBuilder:append	(Ljava/lang/String;)Ljava/lang/StringBuilder;
    //   763: invokevirtual 311	java/lang/StringBuilder:toString	()Ljava/lang/String;
    //   766: astore_1
    //   767: goto +20 -> 787
    //   770: astore_1
    //   771: aload_1
    //   772: invokevirtual 91	java/lang/Throwable:getCause	()Ljava/lang/Throwable;
    //   775: astore 4
    //   777: aload 4
    //   779: ifnull +6 -> 785
    //   782: aload 4
    //   784: athrow
    //   785: aload_1
    //   786: athrow
    //   787: iconst_4
    //   788: bipush 42
    //   790: ldc -89
    //   792: invokestatic 97	o/O:ˋ	(IIC)Ljava/lang/Object;
    //   795: checkcast 99	java/lang/Class
    //   798: ldc_w 312
    //   801: iconst_2
    //   802: anewarray 99	java/lang/Class
    //   805: dup
    //   806: iconst_0
    //   807: ldc 52
    //   809: aastore
    //   810: dup
    //   811: iconst_1
    //   812: ldc 52
    //   814: aastore
    //   815: invokevirtual 104	java/lang/Class:getMethod	(Ljava/lang/String;[Ljava/lang/Class;)Ljava/lang/reflect/Method;
    //   818: aconst_null
    //   819: iconst_2
    //   820: anewarray 170	java/lang/Object
    //   823: dup
    //   824: iconst_0
    //   825: aload 4
    //   827: aastore
    //   828: dup
    //   829: iconst_1
    //   830: aload_1
    //   831: aastore
    //   832: invokevirtual 110	java/lang/reflect/Method:invoke	(Ljava/lang/Object;[Ljava/lang/Object;)Ljava/lang/Object;
    //   835: pop
    //   836: iconst_4
    //   837: sipush 413
    //   840: sipush 30253
    //   843: invokestatic 97	o/O:ˋ	(IIC)Ljava/lang/Object;
    //   846: checkcast 99	java/lang/Class
    //   849: ldc -18
    //   851: invokevirtual 242	java/lang/Class:getField	(Ljava/lang/String;)Ljava/lang/reflect/Field;
    //   854: aconst_null
    //   855: invokevirtual 248	java/lang/reflect/Field:get	(Ljava/lang/Object;)Ljava/lang/Object;
    //   858: astore_1
    //   859: goto +20 -> 879
    //   862: astore_1
    //   863: aload_1
    //   864: invokevirtual 91	java/lang/Throwable:getCause	()Ljava/lang/Throwable;
    //   867: astore 4
    //   869: aload 4
    //   871: ifnull +6 -> 877
    //   874: aload 4
    //   876: athrow
    //   877: aload_1
    //   878: athrow
    //   879: bipush 6
    //   881: sipush 417
    //   884: iconst_0
    //   885: invokestatic 97	o/O:ˋ	(IIC)Ljava/lang/Object;
    //   888: checkcast 99	java/lang/Class
    //   891: ldc -7
    //   893: aconst_null
    //   894: invokevirtual 104	java/lang/Class:getMethod	(Ljava/lang/String;[Ljava/lang/Class;)Ljava/lang/reflect/Method;
    //   897: aload_1
    //   898: aconst_null
    //   899: invokevirtual 110	java/lang/reflect/Method:invoke	(Ljava/lang/Object;[Ljava/lang/Object;)Ljava/lang/Object;
    //   902: astore_1
    //   903: getstatic 318	o/Gw:INACTIVE_PHONE_NUMBER	Lo/Gw;
    //   906: astore 4
    //   908: goto +20 -> 928
    //   911: astore_1
    //   912: aload_1
    //   913: invokevirtual 91	java/lang/Throwable:getCause	()Ljava/lang/Throwable;
    //   916: astore 4
    //   918: aload 4
    //   920: ifnull +6 -> 926
    //   923: aload 4
    //   925: athrow
    //   926: aload_1
    //   927: athrow
    //   928: iconst_4
    //   929: sipush 413
    //   932: sipush 30253
    //   935: invokestatic 97	o/O:ˋ	(IIC)Ljava/lang/Object;
    //   938: checkcast 99	java/lang/Class
    //   941: ldc -18
    //   943: iconst_1
    //   944: anewarray 99	java/lang/Class
    //   947: dup
    //   948: iconst_0
    //   949: ldc_w 314
    //   952: aastore
    //   953: invokevirtual 104	java/lang/Class:getMethod	(Ljava/lang/String;[Ljava/lang/Class;)Ljava/lang/reflect/Method;
    //   956: aload_1
    //   957: iconst_1
    //   958: anewarray 170	java/lang/Object
    //   961: dup
    //   962: iconst_0
    //   963: aload 4
    //   965: aastore
    //   966: invokevirtual 110	java/lang/reflect/Method:invoke	(Ljava/lang/Object;[Ljava/lang/Object;)Ljava/lang/Object;
    //   969: pop
    //   970: iconst_4
    //   971: sipush 362
    //   974: ldc_w 319
    //   977: invokestatic 97	o/O:ˋ	(IIC)Ljava/lang/Object;
    //   980: checkcast 99	java/lang/Class
    //   983: ldc 100
    //   985: invokevirtual 242	java/lang/Class:getField	(Ljava/lang/String;)Ljava/lang/reflect/Field;
    //   988: aconst_null
    //   989: invokevirtual 248	java/lang/reflect/Field:get	(Ljava/lang/Object;)Ljava/lang/Object;
    //   992: astore_1
    //   993: goto +20 -> 1013
    //   996: astore_1
    //   997: aload_1
    //   998: invokevirtual 91	java/lang/Throwable:getCause	()Ljava/lang/Throwable;
    //   1001: astore 4
    //   1003: aload 4
    //   1005: ifnull +6 -> 1011
    //   1008: aload 4
    //   1010: athrow
    //   1011: aload_1
    //   1012: athrow
    //   1013: bipush 7
    //   1015: sipush 366
    //   1018: iconst_0
    //   1019: invokestatic 97	o/O:ˋ	(IIC)Ljava/lang/Object;
    //   1022: checkcast 99	java/lang/Class
    //   1025: ldc_w 312
    //   1028: aconst_null
    //   1029: invokevirtual 104	java/lang/Class:getMethod	(Ljava/lang/String;[Ljava/lang/Class;)Ljava/lang/reflect/Method;
    //   1032: aload_1
    //   1033: aconst_null
    //   1034: invokevirtual 110	java/lang/reflect/Method:invoke	(Ljava/lang/Object;[Ljava/lang/Object;)Ljava/lang/Object;
    //   1037: astore_1
    //   1038: goto +20 -> 1058
    //   1041: astore_1
    //   1042: aload_1
    //   1043: invokevirtual 91	java/lang/Throwable:getCause	()Ljava/lang/Throwable;
    //   1046: astore 4
    //   1048: aload 4
    //   1050: ifnull +6 -> 1056
    //   1053: aload 4
    //   1055: athrow
    //   1056: aload_1
    //   1057: athrow
    //   1058: iconst_4
    //   1059: sipush 362
    //   1062: ldc_w 319
    //   1065: invokestatic 97	o/O:ˋ	(IIC)Ljava/lang/Object;
    //   1068: checkcast 99	java/lang/Class
    //   1071: ldc_w 320
    //   1074: aconst_null
    //   1075: invokevirtual 104	java/lang/Class:getMethod	(Ljava/lang/String;[Ljava/lang/Class;)Ljava/lang/reflect/Method;
    //   1078: aload_1
    //   1079: aconst_null
    //   1080: invokevirtual 110	java/lang/reflect/Method:invoke	(Ljava/lang/Object;[Ljava/lang/Object;)Ljava/lang/Object;
    //   1083: checkcast 52	java/lang/String
    //   1086: astore_1
    //   1087: aload_0
    //   1088: getfield 73	o/Iy:ˎ	Lo/Iu$if;
    //   1091: aload_1
    //   1092: invokeinterface 323 2 0
    //   1097: goto -627 -> 470
    //   1100: aload_0
    //   1101: getfield 75	o/Iy:ˊ	Lo/Ib;
    //   1104: invokeinterface 265 1 0
    //   1109: iconst_1
    //   1110: invokeinterface 270 2 0
    //   1115: aload_0
    //   1116: getfield 73	o/Iy:ˎ	Lo/Iu$if;
    //   1119: invokeinterface 273 1 0
    //   1124: goto -633 -> 491
    //   1127: getstatic 35	o/Iy:ᐝ	I
    //   1130: bipush 109
    //   1132: iadd
    //   1133: istore_2
    //   1134: iload_2
    //   1135: sipush 128
    //   1138: irem
    //   1139: putstatic 37	o/Iy:ʼ	I
    //   1142: iload_2
    //   1143: iconst_2
    //   1144: irem
    //   1145: ifne +6 -> 1151
    //   1148: goto -622 -> 526
    //   1151: goto -51 -> 1100
    //   1154: aload_0
    //   1155: getfield 73	o/Iy:ˎ	Lo/Iu$if;
    //   1158: invokeinterface 326 1 0
    //   1163: goto -693 -> 470
    // Local variable table:
    //   start	length	slot	name	signature
    //   0	1166	0	this	Iy
    //   0	1166	1	paramFg	Fg
    //   227	918	2	i	int
    //   164	117	3	bool	boolean
    //   3	1051	4	localObject1	Object
    //   223	214	5	localObject2	Object
    // Exception table:
    //   from	to	target	type
    //   87	113	70	finally
    //   133	165	116	finally
    //   265	272	251	java/lang/Exception
    //   272	280	251	java/lang/Exception
    //   260	265	478	java/lang/Exception
    //   787	836	770	finally
    //   879	903	862	finally
    //   928	970	911	finally
    //   1013	1038	996	finally
    //   1058	1087	1041	finally
  }
  
  /* Error */
  public final void C_()
  {
    // Byte code:
    //   0: goto +198 -> 198
    //   3: aload_0
    //   4: getfield 73	o/Iy:ˎ	Lo/Iu$if;
    //   7: invokeinterface 332 1 0
    //   12: goto +192 -> 204
    //   15: bipush 37
    //   17: istore_1
    //   18: goto +18 -> 36
    //   21: aload_0
    //   22: getfield 73	o/Iy:ˎ	Lo/Iu$if;
    //   25: invokeinterface 335 1 0
    //   30: goto +174 -> 204
    //   33: bipush 78
    //   35: istore_1
    //   36: iload_1
    //   37: lookupswitch	default:+27->64, 37:+-16->21, 78:+195->232
    //   64: goto -43 -> 21
    //   67: goto +20 -> 87
    //   70: astore_3
    //   71: aload_3
    //   72: invokevirtual 91	java/lang/Throwable:getCause	()Ljava/lang/Throwable;
    //   75: astore 4
    //   77: aload 4
    //   79: ifnull +6 -> 85
    //   82: aload 4
    //   84: athrow
    //   85: aload_3
    //   86: athrow
    //   87: iconst_3
    //   88: bipush 24
    //   90: iconst_0
    //   91: invokestatic 97	o/O:ˋ	(IIC)Ljava/lang/Object;
    //   94: checkcast 99	java/lang/Class
    //   97: ldc 100
    //   99: aconst_null
    //   100: invokevirtual 104	java/lang/Class:getMethod	(Ljava/lang/String;[Ljava/lang/Class;)Ljava/lang/reflect/Method;
    //   103: aconst_null
    //   104: aconst_null
    //   105: invokevirtual 110	java/lang/reflect/Method:invoke	(Ljava/lang/Object;[Ljava/lang/Object;)Ljava/lang/Object;
    //   108: astore_3
    //   109: getstatic 340	o/Gv:ˊ	Lo/Gv$If;
    //   112: invokevirtual 345	o/Gv$If:ˎ	()Lo/Gv;
    //   115: checkcast 347	android/content/Context
    //   118: astore 4
    //   120: goto +20 -> 140
    //   123: astore_3
    //   124: aload_3
    //   125: invokevirtual 91	java/lang/Throwable:getCause	()Ljava/lang/Throwable;
    //   128: astore 4
    //   130: aload 4
    //   132: ifnull +6 -> 138
    //   135: aload 4
    //   137: athrow
    //   138: aload_3
    //   139: athrow
    //   140: iconst_3
    //   141: bipush 24
    //   143: iconst_0
    //   144: invokestatic 97	o/O:ˋ	(IIC)Ljava/lang/Object;
    //   147: checkcast 99	java/lang/Class
    //   150: ldc 100
    //   152: iconst_1
    //   153: anewarray 99	java/lang/Class
    //   156: dup
    //   157: iconst_0
    //   158: ldc_w 347
    //   161: aastore
    //   162: invokevirtual 104	java/lang/Class:getMethod	(Ljava/lang/String;[Ljava/lang/Class;)Ljava/lang/reflect/Method;
    //   165: aload_3
    //   166: iconst_1
    //   167: anewarray 170	java/lang/Object
    //   170: dup
    //   171: iconst_0
    //   172: aload 4
    //   174: aastore
    //   175: invokevirtual 110	java/lang/reflect/Method:invoke	(Ljava/lang/Object;[Ljava/lang/Object;)Ljava/lang/Object;
    //   178: checkcast 253	java/lang/Boolean
    //   181: invokevirtual 257	java/lang/Boolean:booleanValue	()Z
    //   184: istore_2
    //   185: iload_2
    //   186: ifeq +6 -> 192
    //   189: goto -156 -> 33
    //   192: goto -177 -> 15
    //   195: goto -192 -> 3
    //   198: goto +7 -> 205
    //   201: goto -134 -> 67
    //   204: return
    //   205: getstatic 37	o/Iy:ʼ	I
    //   208: bipush 97
    //   210: iadd
    //   211: istore_1
    //   212: iload_1
    //   213: sipush 128
    //   216: irem
    //   217: putstatic 35	o/Iy:ᐝ	I
    //   220: iload_1
    //   221: iconst_2
    //   222: irem
    //   223: ifeq +6 -> 229
    //   226: goto -25 -> 201
    //   229: goto -162 -> 67
    //   232: getstatic 37	o/Iy:ʼ	I
    //   235: bipush 59
    //   237: iadd
    //   238: istore_1
    //   239: iload_1
    //   240: sipush 128
    //   243: irem
    //   244: putstatic 35	o/Iy:ᐝ	I
    //   247: iload_1
    //   248: iconst_2
    //   249: irem
    //   250: ifeq +6 -> 256
    //   253: goto -58 -> 195
    //   256: goto -253 -> 3
    // Local variable table:
    //   start	length	slot	name	signature
    //   0	259	0	this	Iy
    //   17	233	1	i	int
    //   184	2	2	bool	boolean
    //   70	16	3	localObject1	Object
    //   108	1	3	localObject2	Object
    //   123	43	3	localObject3	Object
    //   75	98	4	localObject4	Object
    // Exception table:
    //   from	to	target	type
    //   87	109	70	finally
    //   140	185	123	finally
  }
  
  public final R ʼ()
  {
    int i;
    for (;;)
    {
      i = ʼ + 83;
      ᐝ = i % 128;
      if (i % 2 == 0) {
        break label82;
      }
      i = 1;
      break;
    }
    for (;;)
    {
      switch (i)
      {
      case 0: 
      default: 
        try
        {
          Ib localIb1 = this.ˊ;
          return localIb1;
        }
        catch (Exception localException)
        {
          throw localException;
        }
      }
      Ib localIb2 = this.ˊ;
      i = 36 / 0;
      return localIb2;
      label82:
      i = 0;
    }
  }
  
  public final V ʽ()
  {
    break label88;
    Iu.if localIf = this.ˎ;
    int i = null.length;
    return localIf;
    i = 0;
    label88:
    for (;;)
    {
      try
      {
        localIf = this.ˎ;
        return localIf;
      }
      catch (Exception localException)
      {
        throw localException;
      }
      i = ʼ + 103;
      ᐝ = i % 128;
      if (i % 2 == 0) {
        break;
      }
      for (;;)
      {
        switch (i)
        {
        }
        break;
        i = 1;
      }
    }
  }
  
  /* Error */
  public void ˊ(android.content.DialogInterface.OnCancelListener paramOnCancelListener)
  {
    // Byte code:
    //   0: goto +31 -> 31
    //   3: iload_2
    //   4: tableswitch	default:+24->28, 0:+362->366, 1:+210->214
    //   28: goto +338 -> 366
    //   31: aload_1
    //   32: sipush 208
    //   35: bipush 8
    //   37: bipush 8
    //   39: newarray char
    //   41: dup
    //   42: iconst_0
    //   43: ldc -69
    //   45: castore
    //   46: dup
    //   47: iconst_1
    //   48: ldc 65
    //   50: castore
    //   51: dup
    //   52: iconst_2
    //   53: ldc 69
    //   55: castore
    //   56: dup
    //   57: iconst_3
    //   58: ldc 68
    //   60: castore
    //   61: dup
    //   62: iconst_4
    //   63: ldc 46
    //   65: castore
    //   66: dup
    //   67: iconst_5
    //   68: ldc -68
    //   70: castore
    //   71: dup
    //   72: bipush 6
    //   74: ldc 62
    //   76: castore
    //   77: dup
    //   78: bipush 7
    //   80: ldc 65
    //   82: castore
    //   83: bipush 6
    //   85: iconst_1
    //   86: invokestatic 50	o/Iy:ॱ	(II[CIZ)Ljava/lang/String;
    //   89: invokevirtual 56	java/lang/String:intern	()Ljava/lang/String;
    //   92: invokestatic 61	o/vq:ˎ	(Ljava/lang/Object;Ljava/lang/String;)V
    //   95: goto +20 -> 115
    //   98: astore_1
    //   99: aload_1
    //   100: invokevirtual 91	java/lang/Throwable:getCause	()Ljava/lang/Throwable;
    //   103: astore 4
    //   105: aload 4
    //   107: ifnull +6 -> 113
    //   110: aload 4
    //   112: athrow
    //   113: aload_1
    //   114: athrow
    //   115: iconst_4
    //   116: sipush 267
    //   119: sipush 14788
    //   122: invokestatic 97	o/O:ˋ	(IIC)Ljava/lang/Object;
    //   125: checkcast 99	java/lang/Class
    //   128: ldc_w 312
    //   131: aconst_null
    //   132: invokevirtual 104	java/lang/Class:getMethod	(Ljava/lang/String;[Ljava/lang/Class;)Ljava/lang/reflect/Method;
    //   135: aconst_null
    //   136: aconst_null
    //   137: invokevirtual 110	java/lang/reflect/Method:invoke	(Ljava/lang/Object;[Ljava/lang/Object;)Ljava/lang/Object;
    //   140: astore 4
    //   142: goto +20 -> 162
    //   145: astore_1
    //   146: aload_1
    //   147: invokevirtual 91	java/lang/Throwable:getCause	()Ljava/lang/Throwable;
    //   150: astore 4
    //   152: aload 4
    //   154: ifnull +6 -> 160
    //   157: aload 4
    //   159: athrow
    //   160: aload_1
    //   161: athrow
    //   162: iconst_4
    //   163: sipush 267
    //   166: sipush 14788
    //   169: invokestatic 97	o/O:ˋ	(IIC)Ljava/lang/Object;
    //   172: checkcast 99	java/lang/Class
    //   175: ldc_w 355
    //   178: aconst_null
    //   179: invokevirtual 104	java/lang/Class:getMethod	(Ljava/lang/String;[Ljava/lang/Class;)Ljava/lang/reflect/Method;
    //   182: aload 4
    //   184: aconst_null
    //   185: invokevirtual 110	java/lang/reflect/Method:invoke	(Ljava/lang/Object;[Ljava/lang/Object;)Ljava/lang/Object;
    //   188: checkcast 253	java/lang/Boolean
    //   191: invokevirtual 257	java/lang/Boolean:booleanValue	()Z
    //   194: istore_3
    //   195: iload_3
    //   196: ifeq +6 -> 202
    //   199: goto +348 -> 547
    //   202: goto +513 -> 715
    //   205: aconst_null
    //   206: arraylength
    //   207: istore_2
    //   208: return
    //   209: iconst_0
    //   210: istore_2
    //   211: goto +476 -> 687
    //   214: iconst_4
    //   215: sipush 413
    //   218: sipush 30253
    //   221: invokestatic 97	o/O:ˋ	(IIC)Ljava/lang/Object;
    //   224: checkcast 99	java/lang/Class
    //   227: ldc -18
    //   229: invokevirtual 242	java/lang/Class:getField	(Ljava/lang/String;)Ljava/lang/reflect/Field;
    //   232: aconst_null
    //   233: invokevirtual 248	java/lang/reflect/Field:get	(Ljava/lang/Object;)Ljava/lang/Object;
    //   236: astore 4
    //   238: goto +20 -> 258
    //   241: astore_1
    //   242: aload_1
    //   243: invokevirtual 91	java/lang/Throwable:getCause	()Ljava/lang/Throwable;
    //   246: astore 4
    //   248: aload 4
    //   250: ifnull +6 -> 256
    //   253: aload 4
    //   255: athrow
    //   256: aload_1
    //   257: athrow
    //   258: bipush 6
    //   260: sipush 417
    //   263: iconst_0
    //   264: invokestatic 97	o/O:ˋ	(IIC)Ljava/lang/Object;
    //   267: checkcast 99	java/lang/Class
    //   270: ldc -7
    //   272: aconst_null
    //   273: invokevirtual 104	java/lang/Class:getMethod	(Ljava/lang/String;[Ljava/lang/Class;)Ljava/lang/reflect/Method;
    //   276: aload 4
    //   278: aconst_null
    //   279: invokevirtual 110	java/lang/reflect/Method:invoke	(Ljava/lang/Object;[Ljava/lang/Object;)Ljava/lang/Object;
    //   282: astore 4
    //   284: goto +20 -> 304
    //   287: astore_1
    //   288: aload_1
    //   289: invokevirtual 91	java/lang/Throwable:getCause	()Ljava/lang/Throwable;
    //   292: astore 4
    //   294: aload 4
    //   296: ifnull +6 -> 302
    //   299: aload 4
    //   301: athrow
    //   302: aload_1
    //   303: athrow
    //   304: iconst_4
    //   305: sipush 413
    //   308: sipush 30253
    //   311: invokestatic 97	o/O:ˋ	(IIC)Ljava/lang/Object;
    //   314: checkcast 99	java/lang/Class
    //   317: ldc -18
    //   319: iconst_1
    //   320: anewarray 99	java/lang/Class
    //   323: dup
    //   324: iconst_0
    //   325: getstatic 359	java/lang/Boolean:TYPE	Ljava/lang/Class;
    //   328: aastore
    //   329: invokevirtual 104	java/lang/Class:getMethod	(Ljava/lang/String;[Ljava/lang/Class;)Ljava/lang/reflect/Method;
    //   332: aload 4
    //   334: iconst_1
    //   335: anewarray 170	java/lang/Object
    //   338: dup
    //   339: iconst_0
    //   340: iconst_0
    //   341: invokestatic 363	java/lang/Boolean:valueOf	(Z)Ljava/lang/Boolean;
    //   344: aastore
    //   345: invokevirtual 110	java/lang/reflect/Method:invoke	(Ljava/lang/Object;[Ljava/lang/Object;)Ljava/lang/Object;
    //   348: pop
    //   349: aload_0
    //   350: getfield 73	o/Iy:ˎ	Lo/Iu$if;
    //   353: astore 4
    //   355: aload 4
    //   357: aload_1
    //   358: invokeinterface 365 2 0
    //   363: goto +355 -> 718
    //   366: iconst_4
    //   367: sipush 413
    //   370: sipush 30253
    //   373: invokestatic 97	o/O:ˋ	(IIC)Ljava/lang/Object;
    //   376: checkcast 99	java/lang/Class
    //   379: ldc -18
    //   381: invokevirtual 242	java/lang/Class:getField	(Ljava/lang/String;)Ljava/lang/reflect/Field;
    //   384: aconst_null
    //   385: invokevirtual 248	java/lang/reflect/Field:get	(Ljava/lang/Object;)Ljava/lang/Object;
    //   388: astore 4
    //   390: goto +20 -> 410
    //   393: astore_1
    //   394: aload_1
    //   395: invokevirtual 91	java/lang/Throwable:getCause	()Ljava/lang/Throwable;
    //   398: astore 4
    //   400: aload 4
    //   402: ifnull +6 -> 408
    //   405: aload 4
    //   407: athrow
    //   408: aload_1
    //   409: athrow
    //   410: bipush 6
    //   412: sipush 417
    //   415: iconst_0
    //   416: invokestatic 97	o/O:ˋ	(IIC)Ljava/lang/Object;
    //   419: checkcast 99	java/lang/Class
    //   422: ldc -7
    //   424: aconst_null
    //   425: invokevirtual 104	java/lang/Class:getMethod	(Ljava/lang/String;[Ljava/lang/Class;)Ljava/lang/reflect/Method;
    //   428: aload 4
    //   430: aconst_null
    //   431: invokevirtual 110	java/lang/reflect/Method:invoke	(Ljava/lang/Object;[Ljava/lang/Object;)Ljava/lang/Object;
    //   434: astore 4
    //   436: goto +20 -> 456
    //   439: astore_1
    //   440: aload_1
    //   441: invokevirtual 91	java/lang/Throwable:getCause	()Ljava/lang/Throwable;
    //   444: astore 4
    //   446: aload 4
    //   448: ifnull +6 -> 454
    //   451: aload 4
    //   453: athrow
    //   454: aload_1
    //   455: athrow
    //   456: iconst_4
    //   457: sipush 413
    //   460: sipush 30253
    //   463: invokestatic 97	o/O:ˋ	(IIC)Ljava/lang/Object;
    //   466: checkcast 99	java/lang/Class
    //   469: ldc -18
    //   471: iconst_1
    //   472: anewarray 99	java/lang/Class
    //   475: dup
    //   476: iconst_0
    //   477: getstatic 359	java/lang/Boolean:TYPE	Ljava/lang/Class;
    //   480: aastore
    //   481: invokevirtual 104	java/lang/Class:getMethod	(Ljava/lang/String;[Ljava/lang/Class;)Ljava/lang/reflect/Method;
    //   484: aload 4
    //   486: iconst_1
    //   487: anewarray 170	java/lang/Object
    //   490: dup
    //   491: iconst_0
    //   492: iconst_0
    //   493: invokestatic 363	java/lang/Boolean:valueOf	(Z)Ljava/lang/Boolean;
    //   496: aastore
    //   497: invokevirtual 110	java/lang/reflect/Method:invoke	(Ljava/lang/Object;[Ljava/lang/Object;)Ljava/lang/Object;
    //   500: pop
    //   501: aload_0
    //   502: getfield 73	o/Iy:ˎ	Lo/Iu$if;
    //   505: aload_1
    //   506: invokeinterface 365 2 0
    //   511: goto +207 -> 718
    //   514: iconst_1
    //   515: istore_2
    //   516: goto +171 -> 687
    //   519: astore_1
    //   520: aload_1
    //   521: athrow
    //   522: getstatic 35	o/Iy:ᐝ	I
    //   525: bipush 63
    //   527: iadd
    //   528: istore_2
    //   529: iload_2
    //   530: sipush 128
    //   533: irem
    //   534: putstatic 37	o/Iy:ʼ	I
    //   537: iload_2
    //   538: iconst_2
    //   539: irem
    //   540: ifne +6 -> 546
    //   543: goto -338 -> 205
    //   546: return
    //   547: goto +20 -> 567
    //   550: astore_1
    //   551: aload_1
    //   552: invokevirtual 91	java/lang/Throwable:getCause	()Ljava/lang/Throwable;
    //   555: astore 4
    //   557: aload 4
    //   559: ifnull +6 -> 565
    //   562: aload 4
    //   564: athrow
    //   565: aload_1
    //   566: athrow
    //   567: iconst_3
    //   568: bipush 39
    //   570: sipush 29347
    //   573: invokestatic 97	o/O:ˋ	(IIC)Ljava/lang/Object;
    //   576: checkcast 99	java/lang/Class
    //   579: ldc_w 312
    //   582: aconst_null
    //   583: invokevirtual 104	java/lang/Class:getMethod	(Ljava/lang/String;[Ljava/lang/Class;)Ljava/lang/reflect/Method;
    //   586: aconst_null
    //   587: aconst_null
    //   588: invokevirtual 110	java/lang/reflect/Method:invoke	(Ljava/lang/Object;[Ljava/lang/Object;)Ljava/lang/Object;
    //   591: astore 4
    //   593: goto +20 -> 613
    //   596: astore_1
    //   597: aload_1
    //   598: invokevirtual 91	java/lang/Throwable:getCause	()Ljava/lang/Throwable;
    //   601: astore 4
    //   603: aload 4
    //   605: ifnull +6 -> 611
    //   608: aload 4
    //   610: athrow
    //   611: aload_1
    //   612: athrow
    //   613: iconst_3
    //   614: bipush 39
    //   616: sipush 29347
    //   619: invokestatic 97	o/O:ˋ	(IIC)Ljava/lang/Object;
    //   622: checkcast 99	java/lang/Class
    //   625: ldc_w 366
    //   628: aconst_null
    //   629: invokevirtual 104	java/lang/Class:getMethod	(Ljava/lang/String;[Ljava/lang/Class;)Ljava/lang/reflect/Method;
    //   632: aload 4
    //   634: aconst_null
    //   635: invokevirtual 110	java/lang/reflect/Method:invoke	(Ljava/lang/Object;[Ljava/lang/Object;)Ljava/lang/Object;
    //   638: checkcast 253	java/lang/Boolean
    //   641: invokevirtual 257	java/lang/Boolean:booleanValue	()Z
    //   644: istore_3
    //   645: iload_3
    //   646: ifne +6 -> 652
    //   649: goto -135 -> 514
    //   652: goto -443 -> 209
    //   655: getstatic 37	o/Iy:ʼ	I
    //   658: bipush 113
    //   660: iadd
    //   661: istore_2
    //   662: iload_2
    //   663: sipush 128
    //   666: irem
    //   667: putstatic 35	o/Iy:ᐝ	I
    //   670: iload_2
    //   671: iconst_2
    //   672: irem
    //   673: ifeq +6 -> 679
    //   676: goto +6 -> 682
    //   679: goto +42 -> 721
    //   682: iconst_1
    //   683: istore_2
    //   684: goto -681 -> 3
    //   687: iload_2
    //   688: tableswitch	default:+24->712, 0:+27->715, 1:+-33->655
    //   712: goto -57 -> 655
    //   715: goto -193 -> 522
    //   718: goto -3 -> 715
    //   721: iconst_0
    //   722: istore_2
    //   723: goto -720 -> 3
    //   726: astore_1
    //   727: aload_1
    //   728: athrow
    // Local variable table:
    //   start	length	slot	name	signature
    //   0	729	0	this	Iy
    //   0	729	1	paramOnCancelListener	android.content.DialogInterface.OnCancelListener
    //   3	720	2	i	int
    //   194	452	3	bool	boolean
    //   103	530	4	localObject	Object
    // Exception table:
    //   from	to	target	type
    //   115	142	98	finally
    //   162	195	145	finally
    //   258	284	241	finally
    //   304	349	287	finally
    //   410	436	393	finally
    //   456	501	439	finally
    //   349	355	519	java/lang/Exception
    //   567	593	550	finally
    //   613	645	596	finally
    //   214	238	726	java/lang/Exception
    //   242	248	726	java/lang/Exception
    //   253	256	726	java/lang/Exception
    //   256	258	726	java/lang/Exception
    //   288	294	726	java/lang/Exception
    //   299	302	726	java/lang/Exception
    //   302	304	726	java/lang/Exception
    //   349	355	726	java/lang/Exception
    //   355	363	726	java/lang/Exception
  }
  
  /* Error */
  public void ᐝ()
  {
    // Byte code:
    //   0: goto +85 -> 85
    //   3: astore_3
    //   4: aload_3
    //   5: athrow
    //   6: astore_3
    //   7: aload_3
    //   8: athrow
    //   9: iload_1
    //   10: lookupswitch	default:+26->36, 6:+88->98, 43:+60->70
    //   36: goto +34 -> 70
    //   39: bipush 43
    //   41: istore_1
    //   42: goto -33 -> 9
    //   45: getstatic 37	o/Iy:ʼ	I
    //   48: bipush 79
    //   50: iadd
    //   51: istore_1
    //   52: iload_1
    //   53: sipush 128
    //   56: irem
    //   57: putstatic 35	o/Iy:ᐝ	I
    //   60: iload_1
    //   61: iconst_2
    //   62: irem
    //   63: ifeq +6 -> 69
    //   66: goto +31 -> 97
    //   69: return
    //   70: goto -25 -> 45
    //   73: bipush 84
    //   75: istore_1
    //   76: goto +49 -> 125
    //   79: bipush 6
    //   81: istore_1
    //   82: goto -73 -> 9
    //   85: goto +469 -> 554
    //   88: bipush 9
    //   90: istore_1
    //   91: goto +34 -> 125
    //   94: goto +61 -> 155
    //   97: return
    //   98: getstatic 35	o/Iy:ᐝ	I
    //   101: bipush 107
    //   103: iadd
    //   104: istore_1
    //   105: iload_1
    //   106: sipush 128
    //   109: irem
    //   110: putstatic 37	o/Iy:ʼ	I
    //   113: iload_1
    //   114: iconst_2
    //   115: irem
    //   116: ifne +6 -> 122
    //   119: goto -25 -> 94
    //   122: goto +33 -> 155
    //   125: iload_1
    //   126: lookupswitch	default:+26->152, 9:+-56->70, 84:+44->170
    //   152: goto -82 -> 70
    //   155: aload_0
    //   156: getfield 212	o/Iy:ˏ	Z
    //   159: istore_2
    //   160: iload_2
    //   161: ifne +6 -> 167
    //   164: goto -91 -> 73
    //   167: goto -79 -> 88
    //   170: aload_0
    //   171: getfield 75	o/Iy:ˊ	Lo/Ib;
    //   174: invokeinterface 265 1 0
    //   179: invokeinterface 370 1 0
    //   184: iconst_2
    //   185: anewarray 314	o/Gw
    //   188: dup
    //   189: iconst_0
    //   190: getstatic 318	o/Gw:INACTIVE_PHONE_NUMBER	Lo/Gw;
    //   193: aastore
    //   194: dup
    //   195: iconst_1
    //   196: getstatic 373	o/Gw:ACTIVE_REGISTERED	Lo/Gw;
    //   199: aastore
    //   200: invokevirtual 376	o/Gw:ˎ	([Lo/Gw;)Z
    //   203: ifeq +6 -> 209
    //   206: goto +6 -> 212
    //   209: goto -139 -> 70
    //   212: sipush 206
    //   215: bipush 7
    //   217: bipush 7
    //   219: newarray char
    //   221: dup
    //   222: iconst_0
    //   223: ldc -95
    //   225: castore
    //   226: dup
    //   227: iconst_1
    //   228: ldc -94
    //   230: castore
    //   231: dup
    //   232: iconst_2
    //   233: ldc -93
    //   235: castore
    //   236: dup
    //   237: iconst_3
    //   238: ldc 63
    //   240: castore
    //   241: dup
    //   242: iconst_4
    //   243: ldc 43
    //   245: castore
    //   246: dup
    //   247: iconst_5
    //   248: ldc 69
    //   250: castore
    //   251: dup
    //   252: bipush 6
    //   254: ldc 45
    //   256: castore
    //   257: bipush 7
    //   259: iconst_0
    //   260: invokestatic 50	o/Iy:ॱ	(II[CIZ)Ljava/lang/String;
    //   263: invokevirtual 56	java/lang/String:intern	()Ljava/lang/String;
    //   266: astore_3
    //   267: sipush 197
    //   270: bipush 22
    //   272: bipush 22
    //   274: newarray char
    //   276: dup
    //   277: iconst_0
    //   278: ldc_w 377
    //   281: castore
    //   282: dup
    //   283: iconst_1
    //   284: ldc 116
    //   286: castore
    //   287: dup
    //   288: iconst_2
    //   289: ldc -68
    //   291: castore
    //   292: dup
    //   293: iconst_3
    //   294: ldc -64
    //   296: castore
    //   297: dup
    //   298: iconst_4
    //   299: ldc -64
    //   301: castore
    //   302: dup
    //   303: iconst_5
    //   304: ldc 66
    //   306: castore
    //   307: dup
    //   308: bipush 6
    //   310: ldc_w 296
    //   313: castore
    //   314: dup
    //   315: bipush 7
    //   317: ldc_w 377
    //   320: castore
    //   321: dup
    //   322: bipush 8
    //   324: ldc 68
    //   326: castore
    //   327: dup
    //   328: bipush 9
    //   330: ldc 66
    //   332: castore
    //   333: dup
    //   334: bipush 10
    //   336: ldc -68
    //   338: castore
    //   339: dup
    //   340: bipush 11
    //   342: ldc -64
    //   344: castore
    //   345: dup
    //   346: bipush 12
    //   348: ldc_w 296
    //   351: castore
    //   352: dup
    //   353: bipush 13
    //   355: ldc 68
    //   357: castore
    //   358: dup
    //   359: bipush 14
    //   361: ldc_w 378
    //   364: castore
    //   365: dup
    //   366: bipush 15
    //   368: ldc 68
    //   370: castore
    //   371: dup
    //   372: bipush 16
    //   374: ldc 66
    //   376: castore
    //   377: dup
    //   378: bipush 17
    //   380: ldc -69
    //   382: castore
    //   383: dup
    //   384: bipush 18
    //   386: ldc -93
    //   388: castore
    //   389: dup
    //   390: bipush 19
    //   392: ldc 69
    //   394: castore
    //   395: dup
    //   396: bipush 20
    //   398: ldc 63
    //   400: castore
    //   401: dup
    //   402: bipush 21
    //   404: ldc 62
    //   406: castore
    //   407: bipush 14
    //   409: iconst_0
    //   410: invokestatic 50	o/Iy:ॱ	(II[CIZ)Ljava/lang/String;
    //   413: invokevirtual 56	java/lang/String:intern	()Ljava/lang/String;
    //   416: astore 4
    //   418: goto +20 -> 438
    //   421: astore_3
    //   422: aload_3
    //   423: invokevirtual 91	java/lang/Throwable:getCause	()Ljava/lang/Throwable;
    //   426: astore 4
    //   428: aload 4
    //   430: ifnull +6 -> 436
    //   433: aload 4
    //   435: athrow
    //   436: aload_3
    //   437: athrow
    //   438: iconst_4
    //   439: bipush 42
    //   441: ldc -89
    //   443: invokestatic 97	o/O:ˋ	(IIC)Ljava/lang/Object;
    //   446: checkcast 99	java/lang/Class
    //   449: ldc_w 312
    //   452: iconst_2
    //   453: anewarray 99	java/lang/Class
    //   456: dup
    //   457: iconst_0
    //   458: ldc 52
    //   460: aastore
    //   461: dup
    //   462: iconst_1
    //   463: ldc 52
    //   465: aastore
    //   466: invokevirtual 104	java/lang/Class:getMethod	(Ljava/lang/String;[Ljava/lang/Class;)Ljava/lang/reflect/Method;
    //   469: aconst_null
    //   470: iconst_2
    //   471: anewarray 170	java/lang/Object
    //   474: dup
    //   475: iconst_0
    //   476: aload_3
    //   477: aastore
    //   478: dup
    //   479: iconst_1
    //   480: aload 4
    //   482: aastore
    //   483: invokevirtual 110	java/lang/reflect/Method:invoke	(Ljava/lang/Object;[Ljava/lang/Object;)Ljava/lang/Object;
    //   486: pop
    //   487: aload_0
    //   488: getfield 75	o/Iy:ˊ	Lo/Ib;
    //   491: invokeinterface 381 1 0
    //   496: invokestatic 386	o/sB:ˋ	()Lo/sy;
    //   499: invokevirtual 391	o/st:ˊ	(Lo/sy;)Lo/st;
    //   502: new 17	o/Iy$ˋ
    //   505: dup
    //   506: aload_0
    //   507: invokespecial 392	o/Iy$ˋ:<init>	(Lo/Iy;)V
    //   510: checkcast 80	o/sW
    //   513: invokevirtual 395	o/st:ˏ	(Lo/sW;)Lo/st;
    //   516: new 13	o/Iy$if
    //   519: dup
    //   520: aload_0
    //   521: invokespecial 396	o/Iy$if:<init>	(Lo/Iy;)V
    //   524: checkcast 398	o/sR
    //   527: invokevirtual 401	o/st:ˊ	(Lo/sR;)Lo/st;
    //   530: new 15	o/Iy$ˊ
    //   533: dup
    //   534: aload_0
    //   535: invokespecial 402	o/Iy$ˊ:<init>	(Lo/Iy;)V
    //   538: checkcast 80	o/sW
    //   541: getstatic 405	o/Iy$If:ˊ	Lo/Iy$If;
    //   544: checkcast 80	o/sW
    //   547: invokevirtual 408	o/st:ˎ	(Lo/sW;Lo/sW;)Lo/sH;
    //   550: pop
    //   551: goto -481 -> 70
    //   554: aload_0
    //   555: getfield 127	o/Iy:ˋ$4622a72	Lo/L;
    //   558: astore_3
    //   559: getstatic 340	o/Gv:ˊ	Lo/Gv$If;
    //   562: invokevirtual 345	o/Gv$If:ˎ	()Lo/Gv;
    //   565: checkcast 347	android/content/Context
    //   568: astore 4
    //   570: goto +20 -> 590
    //   573: astore_3
    //   574: aload_3
    //   575: invokevirtual 91	java/lang/Throwable:getCause	()Ljava/lang/Throwable;
    //   578: astore 4
    //   580: aload 4
    //   582: ifnull +6 -> 588
    //   585: aload 4
    //   587: athrow
    //   588: aload_3
    //   589: athrow
    //   590: iconst_3
    //   591: bipush 24
    //   593: iconst_0
    //   594: invokestatic 97	o/O:ˋ	(IIC)Ljava/lang/Object;
    //   597: checkcast 99	java/lang/Class
    //   600: ldc 100
    //   602: iconst_1
    //   603: anewarray 99	java/lang/Class
    //   606: dup
    //   607: iconst_0
    //   608: ldc_w 347
    //   611: aastore
    //   612: invokevirtual 104	java/lang/Class:getMethod	(Ljava/lang/String;[Ljava/lang/Class;)Ljava/lang/reflect/Method;
    //   615: aload_3
    //   616: iconst_1
    //   617: anewarray 170	java/lang/Object
    //   620: dup
    //   621: iconst_0
    //   622: aload 4
    //   624: aastore
    //   625: invokevirtual 110	java/lang/reflect/Method:invoke	(Ljava/lang/Object;[Ljava/lang/Object;)Ljava/lang/Object;
    //   628: checkcast 253	java/lang/Boolean
    //   631: invokevirtual 257	java/lang/Boolean:booleanValue	()Z
    //   634: istore_2
    //   635: iload_2
    //   636: ifeq +6 -> 642
    //   639: goto -560 -> 79
    //   642: goto -603 -> 39
    // Local variable table:
    //   start	length	slot	name	signature
    //   0	645	0	this	Iy
    //   9	117	1	i	int
    //   159	477	2	bool	boolean
    //   3	2	3	localException1	Exception
    //   6	2	3	localException2	Exception
    //   266	1	3	str	String
    //   421	56	3	localObject1	Object
    //   558	1	3	localL	L
    //   573	43	3	localObject2	Object
    //   416	207	4	localObject3	Object
    // Exception table:
    //   from	to	target	type
    //   98	105	3	java/lang/Exception
    //   105	113	3	java/lang/Exception
    //   155	160	3	java/lang/Exception
    //   45	52	6	java/lang/Exception
    //   52	60	6	java/lang/Exception
    //   438	487	421	finally
    //   590	635	573	finally
  }
  
  static final class If<T>
    implements sW<Throwable>
  {
    public static final If ˊ = new If();
    
    If() {}
    
    public final void ˎ(Throwable paramThrowable)
    {
      paramThrowable = td.ʼ;
    }
  }
  
  static final class if
    implements sR
  {
    if(Iy paramIy) {}
    
    public final void ॱ()
    {
      Iy.ˋ(this.ˋ, false);
    }
  }
  
  static final class ˊ<T>
    implements sW<ES>
  {
    private static long ˊ = 2150246067088862933L;
    private static int ˋ = 0;
    private static int ॱ = 1;
    
    ˊ(Iy paramIy) {}
    
    /* Error */
    private static String ˏ(char[] paramArrayOfChar)
    {
      // Byte code:
      //   0: goto +98 -> 98
      //   3: getstatic 22	o/Iy$ˊ:ˋ	I
      //   6: bipush 49
      //   8: iadd
      //   9: istore_1
      //   10: iload_1
      //   11: sipush 128
      //   14: irem
      //   15: putstatic 24	o/Iy$ˊ:ॱ	I
      //   18: iload_1
      //   19: iconst_2
      //   20: irem
      //   21: ifne +6 -> 27
      //   24: goto +119 -> 143
      //   27: goto +8 -> 35
      //   30: iconst_1
      //   31: istore_3
      //   32: goto +216 -> 248
      //   35: bipush 31
      //   37: istore_1
      //   38: goto +114 -> 152
      //   41: astore_0
      //   42: aload_0
      //   43: athrow
      //   44: aload_0
      //   45: astore 4
      //   47: aload 4
      //   49: iconst_1
      //   50: caload
      //   51: istore_2
      //   52: aload 4
      //   54: arraylength
      //   55: iconst_0
      //   56: idiv
      //   57: newarray char
      //   59: astore 4
      //   61: iconst_0
      //   62: istore_1
      //   63: goto +62 -> 125
      //   66: iload_3
      //   67: istore_1
      //   68: goto +57 -> 125
      //   71: getstatic 22	o/Iy$ˊ:ˋ	I
      //   74: bipush 29
      //   76: iadd
      //   77: istore_3
      //   78: iload_3
      //   79: sipush 128
      //   82: irem
      //   83: putstatic 24	o/Iy$ˊ:ॱ	I
      //   86: iload_3
      //   87: iconst_2
      //   88: irem
      //   89: ifne +6 -> 95
      //   92: goto +57 -> 149
      //   95: goto +98 -> 193
      //   98: getstatic 22	o/Iy$ˊ:ˋ	I
      //   101: bipush 101
      //   103: iadd
      //   104: istore_1
      //   105: iload_1
      //   106: sipush 128
      //   109: irem
      //   110: putstatic 24	o/Iy$ˊ:ॱ	I
      //   113: iload_1
      //   114: iconst_2
      //   115: irem
      //   116: ifne +6 -> 122
      //   119: goto -75 -> 44
      //   122: goto +99 -> 221
      //   125: aload_0
      //   126: astore 5
      //   128: iload_1
      //   129: aload 5
      //   131: arraylength
      //   132: if_icmpge +6 -> 138
      //   135: goto -105 -> 30
      //   138: iconst_0
      //   139: istore_3
      //   140: goto +108 -> 248
      //   143: bipush 97
      //   145: istore_1
      //   146: goto +6 -> 152
      //   149: goto +44 -> 193
      //   152: iload_1
      //   153: lookupswitch	default:+27->180, 31:+90->243, 97:+-87->66
      //   180: goto +63 -> 243
      //   183: new 40	java/lang/String
      //   186: dup
      //   187: aload 4
      //   189: invokespecial 43	java/lang/String:<init>	([C)V
      //   192: areturn
      //   193: aload 4
      //   195: iload_1
      //   196: iconst_1
      //   197: isub
      //   198: aload 5
      //   200: iload_1
      //   201: caload
      //   202: iload_1
      //   203: iload_2
      //   204: imul
      //   205: ixor
      //   206: i2l
      //   207: getstatic 28	o/Iy$ˊ:ˊ	J
      //   210: lxor
      //   211: l2i
      //   212: i2c
      //   213: castore
      //   214: iload_1
      //   215: iconst_1
      //   216: iadd
      //   217: istore_3
      //   218: goto -215 -> 3
      //   221: aload_0
      //   222: astore 4
      //   224: aload 4
      //   226: iconst_0
      //   227: caload
      //   228: istore_2
      //   229: aload 4
      //   231: arraylength
      //   232: iconst_1
      //   233: isub
      //   234: newarray char
      //   236: astore 4
      //   238: iconst_1
      //   239: istore_1
      //   240: goto -115 -> 125
      //   243: iload_3
      //   244: istore_1
      //   245: goto -120 -> 125
      //   248: iload_3
      //   249: tableswitch	default:+23->272, 0:+-66->183, 1:+-178->71
      //   272: goto -89 -> 183
      // Local variable table:
      //   start	length	slot	name	signature
      //   0	275	0	paramArrayOfChar	char[]
      //   9	236	1	i	int
      //   51	178	2	j	int
      //   31	218	3	k	int
      //   45	192	4	arrayOfChar1	char[]
      //   126	73	5	arrayOfChar2	char[]
      // Exception table:
      //   from	to	target	type
      //   98	105	41	java/lang/Exception
      //   105	113	41	java/lang/Exception
    }
    
    /* Error */
    public final void ˋ(ES paramES)
    {
      // Byte code:
      //   0: goto +912 -> 912
      //   3: iconst_1
      //   4: istore_2
      //   5: goto +1084 -> 1089
      //   8: aload_1
      //   9: bipush 15
      //   11: newarray char
      //   13: dup
      //   14: iconst_0
      //   15: ldc 50
      //   17: castore
      //   18: dup
      //   19: iconst_1
      //   20: ldc 51
      //   22: castore
      //   23: dup
      //   24: iconst_2
      //   25: ldc 52
      //   27: castore
      //   28: dup
      //   29: iconst_3
      //   30: ldc 53
      //   32: castore
      //   33: dup
      //   34: iconst_4
      //   35: ldc 54
      //   37: castore
      //   38: dup
      //   39: iconst_5
      //   40: ldc 55
      //   42: castore
      //   43: dup
      //   44: bipush 6
      //   46: ldc 56
      //   48: castore
      //   49: dup
      //   50: bipush 7
      //   52: ldc 57
      //   54: castore
      //   55: dup
      //   56: bipush 8
      //   58: ldc 58
      //   60: castore
      //   61: dup
      //   62: bipush 9
      //   64: ldc 59
      //   66: castore
      //   67: dup
      //   68: bipush 10
      //   70: ldc 60
      //   72: castore
      //   73: dup
      //   74: bipush 11
      //   76: ldc 61
      //   78: castore
      //   79: dup
      //   80: bipush 12
      //   82: ldc 62
      //   84: castore
      //   85: dup
      //   86: bipush 13
      //   88: ldc 63
      //   90: castore
      //   91: dup
      //   92: bipush 14
      //   94: ldc 64
      //   96: castore
      //   97: invokestatic 66	o/Iy$ˊ:ˏ	([C)Ljava/lang/String;
      //   100: invokevirtual 70	java/lang/String:intern	()Ljava/lang/String;
      //   103: invokestatic 76	o/vq:ˎ	(Ljava/lang/Object;Ljava/lang/String;)V
      //   106: aload_0
      //   107: getfield 35	o/Iy$ˊ:ˏ	Lo/Iy;
      //   110: astore 4
      //   112: bipush 8
      //   114: newarray char
      //   116: dup
      //   117: iconst_0
      //   118: ldc 77
      //   120: castore
      //   121: dup
      //   122: iconst_1
      //   123: ldc 78
      //   125: castore
      //   126: dup
      //   127: iconst_2
      //   128: ldc 79
      //   130: castore
      //   131: dup
      //   132: iconst_3
      //   133: ldc 80
      //   135: castore
      //   136: dup
      //   137: iconst_4
      //   138: ldc 81
      //   140: castore
      //   141: dup
      //   142: iconst_5
      //   143: ldc 82
      //   145: castore
      //   146: dup
      //   147: bipush 6
      //   149: ldc 83
      //   151: castore
      //   152: dup
      //   153: bipush 7
      //   155: ldc 84
      //   157: castore
      //   158: invokestatic 66	o/Iy$ˊ:ˏ	([C)Ljava/lang/String;
      //   161: invokevirtual 70	java/lang/String:intern	()Ljava/lang/String;
      //   164: astore 5
      //   166: new 86	java/lang/StringBuilder
      //   169: dup
      //   170: invokespecial 87	java/lang/StringBuilder:<init>	()V
      //   173: bipush 36
      //   175: newarray char
      //   177: dup
      //   178: iconst_0
      //   179: ldc 88
      //   181: castore
      //   182: dup
      //   183: iconst_1
      //   184: ldc 89
      //   186: castore
      //   187: dup
      //   188: iconst_2
      //   189: ldc 90
      //   191: castore
      //   192: dup
      //   193: iconst_3
      //   194: ldc 91
      //   196: castore
      //   197: dup
      //   198: iconst_4
      //   199: ldc 92
      //   201: castore
      //   202: dup
      //   203: iconst_5
      //   204: ldc 93
      //   206: castore
      //   207: dup
      //   208: bipush 6
      //   210: ldc 94
      //   212: castore
      //   213: dup
      //   214: bipush 7
      //   216: ldc 95
      //   218: castore
      //   219: dup
      //   220: bipush 8
      //   222: ldc 96
      //   224: castore
      //   225: dup
      //   226: bipush 9
      //   228: ldc 97
      //   230: castore
      //   231: dup
      //   232: bipush 10
      //   234: ldc 98
      //   236: castore
      //   237: dup
      //   238: bipush 11
      //   240: ldc 99
      //   242: castore
      //   243: dup
      //   244: bipush 12
      //   246: ldc 100
      //   248: castore
      //   249: dup
      //   250: bipush 13
      //   252: ldc 101
      //   254: castore
      //   255: dup
      //   256: bipush 14
      //   258: ldc 102
      //   260: castore
      //   261: dup
      //   262: bipush 15
      //   264: ldc 103
      //   266: castore
      //   267: dup
      //   268: bipush 16
      //   270: ldc 104
      //   272: castore
      //   273: dup
      //   274: bipush 17
      //   276: ldc 105
      //   278: castore
      //   279: dup
      //   280: bipush 18
      //   282: ldc 106
      //   284: castore
      //   285: dup
      //   286: bipush 19
      //   288: ldc 107
      //   290: castore
      //   291: dup
      //   292: bipush 20
      //   294: ldc 108
      //   296: castore
      //   297: dup
      //   298: bipush 21
      //   300: ldc 109
      //   302: castore
      //   303: dup
      //   304: bipush 22
      //   306: ldc 110
      //   308: castore
      //   309: dup
      //   310: bipush 23
      //   312: ldc 111
      //   314: castore
      //   315: dup
      //   316: bipush 24
      //   318: ldc 112
      //   320: castore
      //   321: dup
      //   322: bipush 25
      //   324: ldc 113
      //   326: castore
      //   327: dup
      //   328: bipush 26
      //   330: ldc 114
      //   332: castore
      //   333: dup
      //   334: bipush 27
      //   336: ldc 115
      //   338: castore
      //   339: dup
      //   340: bipush 28
      //   342: ldc 116
      //   344: castore
      //   345: dup
      //   346: bipush 29
      //   348: ldc 117
      //   350: castore
      //   351: dup
      //   352: bipush 30
      //   354: ldc 118
      //   356: castore
      //   357: dup
      //   358: bipush 31
      //   360: ldc 119
      //   362: castore
      //   363: dup
      //   364: bipush 32
      //   366: ldc 120
      //   368: castore
      //   369: dup
      //   370: bipush 33
      //   372: ldc 121
      //   374: castore
      //   375: dup
      //   376: bipush 34
      //   378: ldc 122
      //   380: castore
      //   381: dup
      //   382: bipush 35
      //   384: ldc 123
      //   386: castore
      //   387: invokestatic 66	o/Iy$ˊ:ˏ	([C)Ljava/lang/String;
      //   390: invokevirtual 70	java/lang/String:intern	()Ljava/lang/String;
      //   393: invokevirtual 127	java/lang/StringBuilder:append	(Ljava/lang/String;)Ljava/lang/StringBuilder;
      //   396: aload_1
      //   397: invokevirtual 130	o/ES:toString	()Ljava/lang/String;
      //   400: invokevirtual 127	java/lang/StringBuilder:append	(Ljava/lang/String;)Ljava/lang/StringBuilder;
      //   403: invokevirtual 131	java/lang/StringBuilder:toString	()Ljava/lang/String;
      //   406: astore 6
      //   408: goto +20 -> 428
      //   411: astore 4
      //   413: aload 4
      //   415: invokevirtual 137	java/lang/Throwable:getCause	()Ljava/lang/Throwable;
      //   418: astore_1
      //   419: aload_1
      //   420: ifnull +5 -> 425
      //   423: aload_1
      //   424: athrow
      //   425: aload 4
      //   427: athrow
      //   428: iconst_4
      //   429: bipush 42
      //   431: ldc -118
      //   433: invokestatic 143	o/O:ˋ	(IIC)Ljava/lang/Object;
      //   436: checkcast 145	java/lang/Class
      //   439: ldc -110
      //   441: iconst_2
      //   442: anewarray 145	java/lang/Class
      //   445: dup
      //   446: iconst_0
      //   447: ldc 40
      //   449: aastore
      //   450: dup
      //   451: iconst_1
      //   452: ldc 40
      //   454: aastore
      //   455: invokevirtual 150	java/lang/Class:getMethod	(Ljava/lang/String;[Ljava/lang/Class;)Ljava/lang/reflect/Method;
      //   458: aconst_null
      //   459: iconst_2
      //   460: anewarray 5	java/lang/Object
      //   463: dup
      //   464: iconst_0
      //   465: aload 5
      //   467: aastore
      //   468: dup
      //   469: iconst_1
      //   470: aload 6
      //   472: aastore
      //   473: invokevirtual 156	java/lang/reflect/Method:invoke	(Ljava/lang/Object;[Ljava/lang/Object;)Ljava/lang/Object;
      //   476: pop
      //   477: aload 4
      //   479: invokevirtual 160	o/Iy:ʼ	()Lo/Ib;
      //   482: invokeinterface 165 1 0
      //   487: astore 5
      //   489: aload_1
      //   490: invokevirtual 168	o/ES:ˊ	()Z
      //   493: iconst_1
      //   494: if_icmpne +6 -> 500
      //   497: goto +6 -> 503
      //   500: goto +9 -> 509
      //   503: bipush 19
      //   505: istore_2
      //   506: goto +324 -> 830
      //   509: bipush 53
      //   511: istore_2
      //   512: goto +318 -> 830
      //   515: astore_1
      //   516: aload_1
      //   517: athrow
      //   518: getstatic 174	o/Gw:ACTIVE_REGISTERED	Lo/Gw;
      //   521: astore_1
      //   522: new 176	java/lang/NullPointerException
      //   525: dup
      //   526: invokespecial 177	java/lang/NullPointerException:<init>	()V
      //   529: athrow
      //   530: iconst_1
      //   531: istore_2
      //   532: goto +13 -> 545
      //   535: getstatic 174	o/Gw:ACTIVE_REGISTERED	Lo/Gw;
      //   538: astore_1
      //   539: goto +394 -> 933
      //   542: astore_1
      //   543: aload_1
      //   544: athrow
      //   545: iload_2
      //   546: tableswitch	default:+22->568, 0:+-28->518, 1:+-11->535
      //   568: goto -50 -> 518
      //   571: return
      //   572: goto +35 -> 607
      //   575: getstatic 22	o/Iy$ˊ:ˋ	I
      //   578: bipush 49
      //   580: iadd
      //   581: istore_2
      //   582: iload_2
      //   583: sipush 128
      //   586: irem
      //   587: putstatic 24	o/Iy$ˊ:ॱ	I
      //   590: iload_2
      //   591: iconst_2
      //   592: irem
      //   593: ifne +6 -> 599
      //   596: goto +483 -> 1079
      //   599: goto -28 -> 571
      //   602: iconst_0
      //   603: istore_2
      //   604: goto +485 -> 1089
      //   607: goto +20 -> 627
      //   610: astore_1
      //   611: aload_1
      //   612: invokevirtual 137	java/lang/Throwable:getCause	()Ljava/lang/Throwable;
      //   615: astore 4
      //   617: aload 4
      //   619: ifnull +6 -> 625
      //   622: aload 4
      //   624: athrow
      //   625: aload_1
      //   626: athrow
      //   627: iconst_4
      //   628: sipush 267
      //   631: sipush 14788
      //   634: invokestatic 143	o/O:ˋ	(IIC)Ljava/lang/Object;
      //   637: checkcast 145	java/lang/Class
      //   640: ldc -110
      //   642: aconst_null
      //   643: invokevirtual 150	java/lang/Class:getMethod	(Ljava/lang/String;[Ljava/lang/Class;)Ljava/lang/reflect/Method;
      //   646: aconst_null
      //   647: aconst_null
      //   648: invokevirtual 156	java/lang/reflect/Method:invoke	(Ljava/lang/Object;[Ljava/lang/Object;)Ljava/lang/Object;
      //   651: astore_1
      //   652: goto +20 -> 672
      //   655: astore 4
      //   657: aload 4
      //   659: invokevirtual 137	java/lang/Throwable:getCause	()Ljava/lang/Throwable;
      //   662: astore_1
      //   663: aload_1
      //   664: ifnull +5 -> 669
      //   667: aload_1
      //   668: athrow
      //   669: aload 4
      //   671: athrow
      //   672: iconst_4
      //   673: sipush 267
      //   676: sipush 14788
      //   679: invokestatic 143	o/O:ˋ	(IIC)Ljava/lang/Object;
      //   682: checkcast 145	java/lang/Class
      //   685: ldc -77
      //   687: aconst_null
      //   688: invokevirtual 150	java/lang/Class:getMethod	(Ljava/lang/String;[Ljava/lang/Class;)Ljava/lang/reflect/Method;
      //   691: aload_1
      //   692: aconst_null
      //   693: invokevirtual 156	java/lang/reflect/Method:invoke	(Ljava/lang/Object;[Ljava/lang/Object;)Ljava/lang/Object;
      //   696: pop
      //   697: aload 4
      //   699: invokevirtual 183	o/Iy:ʽ	()Lo/Iu$if;
      //   702: astore_1
      //   703: iconst_4
      //   704: sipush 362
      //   707: ldc -72
      //   709: invokestatic 143	o/O:ˋ	(IIC)Ljava/lang/Object;
      //   712: checkcast 145	java/lang/Class
      //   715: ldc -71
      //   717: invokevirtual 189	java/lang/Class:getField	(Ljava/lang/String;)Ljava/lang/reflect/Field;
      //   720: aconst_null
      //   721: invokevirtual 195	java/lang/reflect/Field:get	(Ljava/lang/Object;)Ljava/lang/Object;
      //   724: astore 4
      //   726: goto +20 -> 746
      //   729: astore_1
      //   730: aload_1
      //   731: invokevirtual 137	java/lang/Throwable:getCause	()Ljava/lang/Throwable;
      //   734: astore 4
      //   736: aload 4
      //   738: ifnull +6 -> 744
      //   741: aload 4
      //   743: athrow
      //   744: aload_1
      //   745: athrow
      //   746: bipush 7
      //   748: sipush 366
      //   751: iconst_0
      //   752: invokestatic 143	o/O:ˋ	(IIC)Ljava/lang/Object;
      //   755: checkcast 145	java/lang/Class
      //   758: ldc -110
      //   760: aconst_null
      //   761: invokevirtual 150	java/lang/Class:getMethod	(Ljava/lang/String;[Ljava/lang/Class;)Ljava/lang/reflect/Method;
      //   764: aload 4
      //   766: aconst_null
      //   767: invokevirtual 156	java/lang/reflect/Method:invoke	(Ljava/lang/Object;[Ljava/lang/Object;)Ljava/lang/Object;
      //   770: astore 4
      //   772: goto +20 -> 792
      //   775: astore_1
      //   776: aload_1
      //   777: invokevirtual 137	java/lang/Throwable:getCause	()Ljava/lang/Throwable;
      //   780: astore 4
      //   782: aload 4
      //   784: ifnull +6 -> 790
      //   787: aload 4
      //   789: athrow
      //   790: aload_1
      //   791: athrow
      //   792: iconst_4
      //   793: sipush 362
      //   796: ldc -72
      //   798: invokestatic 143	o/O:ˋ	(IIC)Ljava/lang/Object;
      //   801: checkcast 145	java/lang/Class
      //   804: ldc -60
      //   806: aconst_null
      //   807: invokevirtual 150	java/lang/Class:getMethod	(Ljava/lang/String;[Ljava/lang/Class;)Ljava/lang/reflect/Method;
      //   810: aload 4
      //   812: aconst_null
      //   813: invokevirtual 156	java/lang/reflect/Method:invoke	(Ljava/lang/Object;[Ljava/lang/Object;)Ljava/lang/Object;
      //   816: checkcast 40	java/lang/String
      //   819: astore 4
      //   821: aload_1
      //   822: aload 4
      //   824: invokeinterface 201 2 0
      //   829: return
      //   830: iload_2
      //   831: lookupswitch	default:+25->856, 19:+54->885, 53:+251->1082
      //   856: goto +29 -> 885
      //   859: getstatic 24	o/Iy$ˊ:ॱ	I
      //   862: iconst_3
      //   863: iadd
      //   864: istore_2
      //   865: iload_2
      //   866: sipush 128
      //   869: irem
      //   870: putstatic 22	o/Iy$ˊ:ˋ	I
      //   873: iload_2
      //   874: iconst_2
      //   875: irem
      //   876: ifeq +6 -> 882
      //   879: goto -307 -> 572
      //   882: goto -275 -> 607
      //   885: getstatic 22	o/Iy$ˊ:ˋ	I
      //   888: bipush 59
      //   890: iadd
      //   891: istore_2
      //   892: iload_2
      //   893: sipush 128
      //   896: irem
      //   897: putstatic 24	o/Iy$ˊ:ॱ	I
      //   900: iload_2
      //   901: iconst_2
      //   902: irem
      //   903: ifne +6 -> 909
      //   906: goto +9 -> 915
      //   909: goto -379 -> 530
      //   912: goto -904 -> 8
      //   915: iconst_0
      //   916: istore_2
      //   917: goto -372 -> 545
      //   920: aload 4
      //   922: invokevirtual 183	o/Iy:ʽ	()Lo/Iu$if;
      //   925: invokeinterface 204 1 0
      //   930: goto -355 -> 575
      //   933: aload 5
      //   935: aload_1
      //   936: invokeinterface 209 2 0
      //   941: getstatic 212	o/Gw:INACTIVE_PHONE_NUMBER	Lo/Gw;
      //   944: astore_1
      //   945: iconst_4
      //   946: sipush 413
      //   949: sipush 30253
      //   952: invokestatic 143	o/O:ˋ	(IIC)Ljava/lang/Object;
      //   955: checkcast 145	java/lang/Class
      //   958: ldc -43
      //   960: invokevirtual 189	java/lang/Class:getField	(Ljava/lang/String;)Ljava/lang/reflect/Field;
      //   963: aconst_null
      //   964: invokevirtual 195	java/lang/reflect/Field:get	(Ljava/lang/Object;)Ljava/lang/Object;
      //   967: astore 5
      //   969: goto +20 -> 989
      //   972: astore_1
      //   973: aload_1
      //   974: invokevirtual 137	java/lang/Throwable:getCause	()Ljava/lang/Throwable;
      //   977: astore 4
      //   979: aload 4
      //   981: ifnull +6 -> 987
      //   984: aload 4
      //   986: athrow
      //   987: aload_1
      //   988: athrow
      //   989: bipush 6
      //   991: sipush 417
      //   994: iconst_0
      //   995: invokestatic 143	o/O:ˋ	(IIC)Ljava/lang/Object;
      //   998: checkcast 145	java/lang/Class
      //   1001: ldc -42
      //   1003: aconst_null
      //   1004: invokevirtual 150	java/lang/Class:getMethod	(Ljava/lang/String;[Ljava/lang/Class;)Ljava/lang/reflect/Method;
      //   1007: aload 5
      //   1009: aconst_null
      //   1010: invokevirtual 156	java/lang/reflect/Method:invoke	(Ljava/lang/Object;[Ljava/lang/Object;)Ljava/lang/Object;
      //   1013: astore 5
      //   1015: goto +20 -> 1035
      //   1018: astore 4
      //   1020: aload 4
      //   1022: invokevirtual 137	java/lang/Throwable:getCause	()Ljava/lang/Throwable;
      //   1025: astore_1
      //   1026: aload_1
      //   1027: ifnull +5 -> 1032
      //   1030: aload_1
      //   1031: athrow
      //   1032: aload 4
      //   1034: athrow
      //   1035: iconst_4
      //   1036: sipush 413
      //   1039: sipush 30253
      //   1042: invokestatic 143	o/O:ˋ	(IIC)Ljava/lang/Object;
      //   1045: checkcast 145	java/lang/Class
      //   1048: ldc -40
      //   1050: aconst_null
      //   1051: invokevirtual 150	java/lang/Class:getMethod	(Ljava/lang/String;[Ljava/lang/Class;)Ljava/lang/reflect/Method;
      //   1054: aload 5
      //   1056: aconst_null
      //   1057: invokevirtual 156	java/lang/reflect/Method:invoke	(Ljava/lang/Object;[Ljava/lang/Object;)Ljava/lang/Object;
      //   1060: astore 5
      //   1062: aload_1
      //   1063: aload 5
      //   1065: invokestatic 219	o/vq:ˊ	(Ljava/lang/Object;Ljava/lang/Object;)Z
      //   1068: istore_3
      //   1069: iload_3
      //   1070: ifeq +6 -> 1076
      //   1073: goto -471 -> 602
      //   1076: goto -1073 -> 3
      //   1079: goto -508 -> 571
      //   1082: getstatic 212	o/Gw:INACTIVE_PHONE_NUMBER	Lo/Gw;
      //   1085: astore_1
      //   1086: goto -153 -> 933
      //   1089: iload_2
      //   1090: tableswitch	default:+22->1112, 0:+-231->859, 1:+-170->920
      //   1112: goto -192 -> 920
      // Local variable table:
      //   start	length	slot	name	signature
      //   0	1115	0	this	ˊ
      //   0	1115	1	paramES	ES
      //   4	1086	2	i	int
      //   1068	2	3	bool	boolean
      //   110	1	4	localIy	Iy
      //   411	67	4	localObject1	Object
      //   615	8	4	localThrowable	Throwable
      //   655	43	4	localObject2	Object
      //   724	261	4	localObject3	Object
      //   1018	15	4	localObject4	Object
      //   164	900	5	localObject5	Object
      //   406	65	6	str	String
      // Exception table:
      //   from	to	target	type
      //   428	477	411	finally
      //   933	941	515	java/lang/Exception
      //   941	945	515	java/lang/Exception
      //   945	969	515	java/lang/Exception
      //   973	979	515	java/lang/Exception
      //   984	987	515	java/lang/Exception
      //   987	989	515	java/lang/Exception
      //   1020	1026	515	java/lang/Exception
      //   1030	1032	515	java/lang/Exception
      //   1032	1035	515	java/lang/Exception
      //   1062	1069	515	java/lang/Exception
      //   941	945	542	java/lang/Exception
      //   1082	1086	542	java/lang/Exception
      //   627	652	610	finally
      //   672	697	655	finally
      //   746	772	729	finally
      //   792	821	775	finally
      //   989	1015	972	finally
      //   1035	1062	1018	finally
    }
  }
  
  static final class ˋ<T>
    implements sW<Throwable>
  {
    ˋ(Iy paramIy) {}
    
    public final void ˏ(Throwable paramThrowable)
    {
      Iy.ॱ(this.ˎ, paramThrowable);
    }
  }
}
