package o;

import android.app.Activity;
import android.content.Context;
import android.content.Intent;
import android.os.Parcelable;
import java.io.Serializable;

public final class j
{
  private static int ʻ = 1;
  private static long ˊ = 8810881135567119796L;
  private static int ˎ = 0;
  private static char[] ˏ = { -1594, -9105, -19777, -30515, 28434, 17784, 7162, -477, -11153, -21864, -32548, 26432, 15804, 5097, -2524, -13221, -23924, 31015, 24404, 13712, 3029, -4552, -15177, -25888, 28960, 22364, 11700, 44, -6544, -17227, -27938, 26890, 20301, 84, 9692, 19213, 28988, -26957, -17173, -7594, 1944, 11717, 21292, 31100, -24932, -15331, -5551, 4011, 13816, 23392, -32618, -22835, -13188, -3471, 6058, 15704, 25453, -30589, -20768, -11231, -1654, 8153, 17680, 27489, -28436, -18717, -9125, 390, 10216, 19765, 29564, -26420, 101, 9676, 19228, 29038, -26959, -17189, -7605, 1923, 11733, 21286, 31083, -24871, -15313, -5563, 4027, 13816, 23337, -32638, -22847, -13272, -3479 };
  private Intent ˋ;
  private Context ॱ;
  
  public j(Context paramContext, Intent paramIntent) {}
  
  private j(Context paramContext, Class paramClass)
  {
    this.ॱ = paramContext;
    this.ˋ = new Intent(paramContext, paramClass);
  }
  
  private j(Context paramContext, String paramString)
  {
    this.ॱ = paramContext;
    this.ˋ = new Intent(paramString);
  }
  
  public static j ˋ(Context paramContext, Class paramClass)
  {
    break label44;
    int i = ˎ + 57;
    ʻ = i % 128;
    if (i % 2 != 0) {
      return paramContext;
    }
    return paramContext;
    label44:
    for (;;)
    {
      paramContext = new j(paramContext, paramClass);
      break;
    }
  }
  
  private static String ˎ(char paramChar, int paramInt1, int paramInt2)
  {
    break label178;
    int i;
    int j;
    switch (i)
    {
    default: 
      break;
      j = ʻ + 63;
      ˎ = j % 128;
      if (j % 2 == 0) {
        break label253;
      }
      break;
    }
    label64:
    label85:
    label109:
    label140:
    label175:
    label178:
    label181:
    label221:
    label248:
    label253:
    for (;;)
    {
      char[] arrayOfChar;
      if (i >= paramInt2)
      {
        break label85;
        arrayOfChar = new char[paramInt2];
        i = 1;
        continue;
        j = 61;
      }
      else
      {
        j = 66;
        break label181;
        return new String(arrayOfChar);
        for (;;)
        {
          arrayOfChar[i] = ((char)(int)(ˏ[(paramInt1 + i)] ^ i * ˊ ^ paramChar));
          i += 1;
          break;
          j = ʻ + 83;
          ˎ = j % 128;
          if (j % 2 != 0) {
            break label175;
          }
        }
      }
      for (;;)
      {
        i = 1;
        break;
        break label109;
        break label221;
        switch (j)
        {
        }
        break label140;
        arrayOfChar = new char[paramInt2];
        i = 0;
        break label64;
        i = ʻ + 119;
        ˎ = i % 128;
        if (i % 2 != 0) {
          break label248;
        }
      }
      i = 0;
      break;
    }
  }
  
  /* Error */
  public static j ˏ(Context paramContext, String paramString)
  {
    // Byte code:
    //   0: goto +34 -> 34
    //   3: astore_0
    //   4: aload_0
    //   5: athrow
    //   6: getstatic 19	o/j:ˎ	I
    //   9: bipush 47
    //   11: iadd
    //   12: istore_2
    //   13: iload_2
    //   14: sipush 128
    //   17: irem
    //   18: putstatic 21	o/j:ʻ	I
    //   21: iload_2
    //   22: iconst_2
    //   23: irem
    //   24: ifne +6 -> 30
    //   27: goto +5 -> 32
    //   30: aload_0
    //   31: areturn
    //   32: aload_0
    //   33: areturn
    //   34: new 2	o/j
    //   37: dup
    //   38: aload_0
    //   39: aload_1
    //   40: invokespecial 150	o/j:<init>	(Landroid/content/Context;Ljava/lang/String;)V
    //   43: astore_0
    //   44: goto -38 -> 6
    //   47: astore_0
    //   48: aload_0
    //   49: athrow
    // Local variable table:
    //   start	length	slot	name	signature
    //   0	50	0	paramContext	Context
    //   0	50	1	paramString	String
    //   12	12	2	i	int
    // Exception table:
    //   from	to	target	type
    //   13	21	3	java/lang/Exception
    //   6	13	47	java/lang/Exception
    //   13	21	47	java/lang/Exception
  }
  
  /* Error */
  private void ˏ(Context paramContext, Intent paramIntent)
  {
    // Byte code:
    //   0: goto +66 -> 66
    //   3: aload 4
    //   5: invokeinterface 156 1 0
    //   10: checkcast 158	android/content/pm/ResolveInfo
    //   13: astore 5
    //   15: new 131	android/content/Intent
    //   18: dup
    //   19: aload_2
    //   20: invokespecial 161	android/content/Intent:<init>	(Landroid/content/Intent;)V
    //   23: astore 6
    //   25: aload 6
    //   27: new 163	android/content/ComponentName
    //   30: dup
    //   31: aload 5
    //   33: getfield 167	android/content/pm/ResolveInfo:activityInfo	Landroid/content/pm/ActivityInfo;
    //   36: getfield 173	android/content/pm/ActivityInfo:applicationInfo	Landroid/content/pm/ApplicationInfo;
    //   39: getfield 179	android/content/pm/ApplicationInfo:packageName	Ljava/lang/String;
    //   42: aload 5
    //   44: getfield 167	android/content/pm/ResolveInfo:activityInfo	Landroid/content/pm/ActivityInfo;
    //   47: getfield 182	android/content/pm/ActivityInfo:name	Ljava/lang/String;
    //   50: invokespecial 185	android/content/ComponentName:<init>	(Ljava/lang/String;Ljava/lang/String;)V
    //   53: invokevirtual 189	android/content/Intent:setComponent	(Landroid/content/ComponentName;)Landroid/content/Intent;
    //   56: pop
    //   57: aload_1
    //   58: aload 6
    //   60: invokevirtual 194	android/content/Context:sendBroadcast	(Landroid/content/Intent;)V
    //   63: goto +114 -> 177
    //   66: goto +65 -> 131
    //   69: iconst_1
    //   70: istore_3
    //   71: goto +33 -> 104
    //   74: goto +8 -> 82
    //   77: iconst_0
    //   78: istore_3
    //   79: goto +25 -> 104
    //   82: goto +95 -> 177
    //   85: aload_1
    //   86: invokevirtual 198	android/content/Context:getPackageManager	()Landroid/content/pm/PackageManager;
    //   89: aload_2
    //   90: iconst_0
    //   91: invokevirtual 204	android/content/pm/PackageManager:queryBroadcastReceivers	(Landroid/content/Intent;I)Ljava/util/List;
    //   94: invokeinterface 210 1 0
    //   99: astore 4
    //   101: goto +93 -> 194
    //   104: iload_3
    //   105: tableswitch	default:+23->128, 0:+53->158, 1:+-20->85
    //   128: goto -43 -> 85
    //   131: getstatic 21	o/j:ʻ	I
    //   134: bipush 7
    //   136: iadd
    //   137: istore_3
    //   138: iload_3
    //   139: sipush 128
    //   142: irem
    //   143: putstatic 19	o/j:ˎ	I
    //   146: iload_3
    //   147: iconst_2
    //   148: irem
    //   149: ifeq +6 -> 155
    //   152: goto -75 -> 77
    //   155: goto -86 -> 69
    //   158: aload_1
    //   159: invokevirtual 198	android/content/Context:getPackageManager	()Landroid/content/pm/PackageManager;
    //   162: aload_2
    //   163: iconst_1
    //   164: invokevirtual 204	android/content/pm/PackageManager:queryBroadcastReceivers	(Landroid/content/Intent;I)Ljava/util/List;
    //   167: invokeinterface 210 1 0
    //   172: astore 4
    //   174: goto +20 -> 194
    //   177: aload 4
    //   179: invokeinterface 214 1 0
    //   184: ifeq +6 -> 190
    //   187: goto -184 -> 3
    //   190: return
    //   191: astore_1
    //   192: aload_1
    //   193: athrow
    //   194: getstatic 19	o/j:ˎ	I
    //   197: istore_3
    //   198: iload_3
    //   199: bipush 109
    //   201: iadd
    //   202: istore_3
    //   203: iload_3
    //   204: sipush 128
    //   207: irem
    //   208: putstatic 21	o/j:ʻ	I
    //   211: iload_3
    //   212: iconst_2
    //   213: irem
    //   214: ifne +6 -> 220
    //   217: goto -143 -> 74
    //   220: goto -138 -> 82
    //   223: astore_1
    //   224: aload_1
    //   225: athrow
    // Local variable table:
    //   start	length	slot	name	signature
    //   0	226	0	this	j
    //   0	226	1	paramContext	Context
    //   0	226	2	paramIntent	Intent
    //   70	144	3	i	int
    //   3	175	4	localIterator	java.util.Iterator
    //   13	30	5	localResolveInfo	android.content.pm.ResolveInfo
    //   23	36	6	localIntent	Intent
    // Exception table:
    //   from	to	target	type
    //   194	198	191	java/lang/Exception
    //   131	138	223	java/lang/Exception
    //   138	146	223	java/lang/Exception
    //   203	211	223	java/lang/Exception
  }
  
  /* Error */
  public void ʻ()
  {
    // Byte code:
    //   0: goto +35 -> 35
    //   3: iload_1
    //   4: lookupswitch	default:+28->32, 10:+399->403, 75:+68->72
    //   32: goto +371 -> 403
    //   35: goto +6 -> 41
    //   38: goto +33 -> 71
    //   41: getstatic 21	o/j:ʻ	I
    //   44: bipush 117
    //   46: iadd
    //   47: istore_1
    //   48: iload_1
    //   49: sipush 128
    //   52: irem
    //   53: putstatic 19	o/j:ˎ	I
    //   56: iload_1
    //   57: iconst_2
    //   58: irem
    //   59: ifeq +6 -> 65
    //   62: goto +186 -> 248
    //   65: goto +45 -> 110
    //   68: goto -30 -> 38
    //   71: return
    //   72: aload_0
    //   73: getfield 126	o/j:ॱ	Landroid/content/Context;
    //   76: aload_0
    //   77: getfield 128	o/j:ˋ	Landroid/content/Intent;
    //   80: invokevirtual 194	android/content/Context:sendBroadcast	(Landroid/content/Intent;)V
    //   83: getstatic 21	o/j:ʻ	I
    //   86: bipush 15
    //   88: iadd
    //   89: istore_1
    //   90: iload_1
    //   91: sipush 128
    //   94: irem
    //   95: putstatic 19	o/j:ˎ	I
    //   98: iload_1
    //   99: iconst_2
    //   100: irem
    //   101: ifeq +6 -> 107
    //   104: goto -36 -> 68
    //   107: goto -69 -> 38
    //   110: goto +20 -> 130
    //   113: astore_3
    //   114: aload_3
    //   115: invokevirtual 220	java/lang/Throwable:getCause	()Ljava/lang/Throwable;
    //   118: astore 4
    //   120: aload 4
    //   122: ifnull +6 -> 128
    //   125: aload 4
    //   127: athrow
    //   128: aload_3
    //   129: athrow
    //   130: iconst_3
    //   131: iconst_0
    //   132: ldc -35
    //   134: invokestatic 226	o/O:ˋ	(IIC)Ljava/lang/Object;
    //   137: checkcast 228	java/lang/Class
    //   140: ldc -27
    //   142: aconst_null
    //   143: invokevirtual 233	java/lang/Class:getMethod	(Ljava/lang/String;[Ljava/lang/Class;)Ljava/lang/reflect/Method;
    //   146: aconst_null
    //   147: aconst_null
    //   148: invokevirtual 239	java/lang/reflect/Method:invoke	(Ljava/lang/Object;[Ljava/lang/Object;)Ljava/lang/Object;
    //   151: astore_3
    //   152: goto +20 -> 172
    //   155: astore_3
    //   156: aload_3
    //   157: invokevirtual 220	java/lang/Throwable:getCause	()Ljava/lang/Throwable;
    //   160: astore 4
    //   162: aload 4
    //   164: ifnull +6 -> 170
    //   167: aload 4
    //   169: athrow
    //   170: aload_3
    //   171: athrow
    //   172: iconst_3
    //   173: iconst_0
    //   174: ldc -35
    //   176: invokestatic 226	o/O:ˋ	(IIC)Ljava/lang/Object;
    //   179: checkcast 228	java/lang/Class
    //   182: ldc -16
    //   184: iconst_1
    //   185: anewarray 228	java/lang/Class
    //   188: dup
    //   189: iconst_0
    //   190: getstatic 246	java/lang/Integer:TYPE	Ljava/lang/Class;
    //   193: aastore
    //   194: invokevirtual 233	java/lang/Class:getMethod	(Ljava/lang/String;[Ljava/lang/Class;)Ljava/lang/reflect/Method;
    //   197: aload_3
    //   198: iconst_1
    //   199: anewarray 4	java/lang/Object
    //   202: dup
    //   203: iconst_0
    //   204: bipush 26
    //   206: invokestatic 250	java/lang/Integer:valueOf	(I)Ljava/lang/Integer;
    //   209: aastore
    //   210: invokevirtual 239	java/lang/reflect/Method:invoke	(Ljava/lang/Object;[Ljava/lang/Object;)Ljava/lang/Object;
    //   213: checkcast 252	java/lang/Boolean
    //   216: invokevirtual 255	java/lang/Boolean:booleanValue	()Z
    //   219: istore_2
    //   220: iload_2
    //   221: ifeq +6 -> 227
    //   224: goto +12 -> 236
    //   227: goto +141 -> 368
    //   230: bipush 97
    //   232: istore_1
    //   233: goto +141 -> 374
    //   236: bipush 10
    //   238: istore_1
    //   239: goto -236 -> 3
    //   242: bipush 91
    //   244: istore_1
    //   245: goto +129 -> 374
    //   248: goto +20 -> 268
    //   251: astore_3
    //   252: aload_3
    //   253: invokevirtual 220	java/lang/Throwable:getCause	()Ljava/lang/Throwable;
    //   256: astore 4
    //   258: aload 4
    //   260: ifnull +6 -> 266
    //   263: aload 4
    //   265: athrow
    //   266: aload_3
    //   267: athrow
    //   268: iconst_3
    //   269: iconst_0
    //   270: ldc -35
    //   272: invokestatic 226	o/O:ˋ	(IIC)Ljava/lang/Object;
    //   275: checkcast 228	java/lang/Class
    //   278: ldc -27
    //   280: aconst_null
    //   281: invokevirtual 233	java/lang/Class:getMethod	(Ljava/lang/String;[Ljava/lang/Class;)Ljava/lang/reflect/Method;
    //   284: aconst_null
    //   285: aconst_null
    //   286: invokevirtual 239	java/lang/reflect/Method:invoke	(Ljava/lang/Object;[Ljava/lang/Object;)Ljava/lang/Object;
    //   289: astore_3
    //   290: goto +20 -> 310
    //   293: astore_3
    //   294: aload_3
    //   295: invokevirtual 220	java/lang/Throwable:getCause	()Ljava/lang/Throwable;
    //   298: astore 4
    //   300: aload 4
    //   302: ifnull +6 -> 308
    //   305: aload 4
    //   307: athrow
    //   308: aload_3
    //   309: athrow
    //   310: iconst_3
    //   311: iconst_0
    //   312: ldc -35
    //   314: invokestatic 226	o/O:ˋ	(IIC)Ljava/lang/Object;
    //   317: checkcast 228	java/lang/Class
    //   320: ldc -16
    //   322: iconst_1
    //   323: anewarray 228	java/lang/Class
    //   326: dup
    //   327: iconst_0
    //   328: getstatic 246	java/lang/Integer:TYPE	Ljava/lang/Class;
    //   331: aastore
    //   332: invokevirtual 233	java/lang/Class:getMethod	(Ljava/lang/String;[Ljava/lang/Class;)Ljava/lang/reflect/Method;
    //   335: aload_3
    //   336: iconst_1
    //   337: anewarray 4	java/lang/Object
    //   340: dup
    //   341: iconst_0
    //   342: bipush 100
    //   344: invokestatic 250	java/lang/Integer:valueOf	(I)Ljava/lang/Integer;
    //   347: aastore
    //   348: invokevirtual 239	java/lang/reflect/Method:invoke	(Ljava/lang/Object;[Ljava/lang/Object;)Ljava/lang/Object;
    //   351: checkcast 252	java/lang/Boolean
    //   354: invokevirtual 255	java/lang/Boolean:booleanValue	()Z
    //   357: istore_2
    //   358: iload_2
    //   359: ifeq +6 -> 365
    //   362: goto -120 -> 242
    //   365: goto -135 -> 230
    //   368: bipush 75
    //   370: istore_1
    //   371: goto -368 -> 3
    //   374: iload_1
    //   375: lookupswitch	default:+25->400, 91:+28->403, 97:+-303->72
    //   400: goto -328 -> 72
    //   403: aload_0
    //   404: aload_0
    //   405: getfield 126	o/j:ॱ	Landroid/content/Context;
    //   408: aload_0
    //   409: getfield 128	o/j:ˋ	Landroid/content/Intent;
    //   412: invokespecial 257	o/j:ˏ	(Landroid/content/Context;Landroid/content/Intent;)V
    //   415: return
    // Local variable table:
    //   start	length	slot	name	signature
    //   0	416	0	this	j
    //   3	372	1	i	int
    //   219	140	2	bool	boolean
    //   113	16	3	localObject1	Object
    //   151	1	3	localObject2	Object
    //   155	43	3	localObject3	Object
    //   251	16	3	localObject4	Object
    //   289	1	3	localObject5	Object
    //   293	43	3	localObject6	Object
    //   118	188	4	localThrowable	Throwable
    // Exception table:
    //   from	to	target	type
    //   130	152	113	finally
    //   172	220	155	finally
    //   268	290	251	finally
    //   310	358	293	finally
  }
  
  /* Error */
  public j ʼ()
  {
    // Byte code:
    //   0: goto +170 -> 170
    //   3: astore_2
    //   4: aload_2
    //   5: athrow
    //   6: getstatic 21	o/j:ʻ	I
    //   9: bipush 79
    //   11: iadd
    //   12: istore_1
    //   13: iload_1
    //   14: sipush 128
    //   17: irem
    //   18: putstatic 19	o/j:ˎ	I
    //   21: iload_1
    //   22: iconst_2
    //   23: irem
    //   24: ifeq +6 -> 30
    //   27: goto +140 -> 167
    //   30: goto +92 -> 122
    //   33: iload_1
    //   34: tableswitch	default:+22->56, 0:+85->119, 1:+57->91
    //   56: goto +63 -> 119
    //   59: iconst_0
    //   60: istore_1
    //   61: goto +33 -> 94
    //   64: aload_0
    //   65: getfield 126	o/j:ॱ	Landroid/content/Context;
    //   68: checkcast 261	android/app/Activity
    //   71: invokevirtual 265	android/app/Activity:getIntent	()Landroid/content/Intent;
    //   74: iconst_0
    //   75: bipush 72
    //   77: bipush 21
    //   79: invokestatic 267	o/j:ˎ	(CII)Ljava/lang/String;
    //   82: invokevirtual 271	java/lang/String:intern	()Ljava/lang/String;
    //   85: invokevirtual 274	android/content/Intent:removeExtra	(Ljava/lang/String;)V
    //   88: goto +131 -> 219
    //   91: goto +25 -> 116
    //   94: iload_1
    //   95: tableswitch	default:+21->116, 0:+43->138, 1:+21->116
    //   116: goto +62 -> 178
    //   119: goto -3 -> 116
    //   122: aload_0
    //   123: getfield 126	o/j:ॱ	Landroid/content/Context;
    //   126: instanceof 261
    //   129: ifeq +6 -> 135
    //   132: goto -73 -> 59
    //   135: goto +72 -> 207
    //   138: getstatic 19	o/j:ˎ	I
    //   141: istore_1
    //   142: iload_1
    //   143: bipush 55
    //   145: iadd
    //   146: istore_1
    //   147: iload_1
    //   148: sipush 128
    //   151: irem
    //   152: putstatic 21	o/j:ʻ	I
    //   155: iload_1
    //   156: iconst_2
    //   157: irem
    //   158: ifne +6 -> 164
    //   161: goto +43 -> 204
    //   164: goto -100 -> 64
    //   167: goto -45 -> 122
    //   170: goto -164 -> 6
    //   173: iconst_1
    //   174: istore_1
    //   175: goto -142 -> 33
    //   178: getstatic 19	o/j:ˎ	I
    //   181: bipush 115
    //   183: iadd
    //   184: istore_1
    //   185: iload_1
    //   186: sipush 128
    //   189: irem
    //   190: putstatic 21	o/j:ʻ	I
    //   193: iload_1
    //   194: iconst_2
    //   195: irem
    //   196: ifne +6 -> 202
    //   199: goto +18 -> 217
    //   202: aload_0
    //   203: areturn
    //   204: goto -140 -> 64
    //   207: iconst_1
    //   208: istore_1
    //   209: goto -115 -> 94
    //   212: iconst_0
    //   213: istore_1
    //   214: goto -181 -> 33
    //   217: aload_0
    //   218: areturn
    //   219: getstatic 19	o/j:ˎ	I
    //   222: bipush 61
    //   224: iadd
    //   225: istore_1
    //   226: iload_1
    //   227: sipush 128
    //   230: irem
    //   231: putstatic 21	o/j:ʻ	I
    //   234: iload_1
    //   235: iconst_2
    //   236: irem
    //   237: ifne +6 -> 243
    //   240: goto -67 -> 173
    //   243: goto -31 -> 212
    // Local variable table:
    //   start	length	slot	name	signature
    //   0	246	0	this	j
    //   12	225	1	i	int
    //   3	2	2	localException	Exception
    // Exception table:
    //   from	to	target	type
    //   138	142	3	java/lang/Exception
    //   147	155	3	java/lang/Exception
  }
  
  /* Error */
  public j ˊ()
  {
    // Byte code:
    //   0: goto +45 -> 45
    //   3: astore_2
    //   4: aload_2
    //   5: athrow
    //   6: bipush 48
    //   8: iconst_0
    //   9: idiv
    //   10: istore_1
    //   11: aload_0
    //   12: areturn
    //   13: iload_1
    //   14: lookupswitch	default:+26->40, 28:+-8->6, 55:+29->43
    //   40: goto -34 -> 6
    //   43: aload_0
    //   44: areturn
    //   45: getstatic 21	o/j:ʻ	I
    //   48: istore_1
    //   49: iload_1
    //   50: bipush 19
    //   52: iadd
    //   53: istore_1
    //   54: iload_1
    //   55: sipush 128
    //   58: irem
    //   59: putstatic 19	o/j:ˎ	I
    //   62: iload_1
    //   63: iconst_2
    //   64: irem
    //   65: ifeq +6 -> 71
    //   68: goto +63 -> 131
    //   71: aload_0
    //   72: getfield 128	o/j:ˋ	Landroid/content/Intent;
    //   75: ldc_w 275
    //   78: iconst_0
    //   79: bipush 33
    //   81: invokestatic 267	o/j:ˎ	(CII)Ljava/lang/String;
    //   84: invokevirtual 271	java/lang/String:intern	()Ljava/lang/String;
    //   87: iconst_1
    //   88: invokevirtual 279	android/content/Intent:putExtra	(Ljava/lang/String;Z)Landroid/content/Intent;
    //   91: pop
    //   92: goto +9 -> 101
    //   95: bipush 55
    //   97: istore_1
    //   98: goto -85 -> 13
    //   101: getstatic 21	o/j:ʻ	I
    //   104: bipush 55
    //   106: iadd
    //   107: istore_1
    //   108: iload_1
    //   109: sipush 128
    //   112: irem
    //   113: putstatic 19	o/j:ˎ	I
    //   116: iload_1
    //   117: iconst_2
    //   118: irem
    //   119: ifeq +6 -> 125
    //   122: goto +12 -> 134
    //   125: goto -30 -> 95
    //   128: astore_2
    //   129: aload_2
    //   130: athrow
    //   131: goto -60 -> 71
    //   134: bipush 28
    //   136: istore_1
    //   137: goto -124 -> 13
    // Local variable table:
    //   start	length	slot	name	signature
    //   0	140	0	this	j
    //   10	127	1	i	int
    //   3	2	2	localException1	Exception
    //   128	2	2	localException2	Exception
    // Exception table:
    //   from	to	target	type
    //   54	62	3	java/lang/Exception
    //   45	49	128	java/lang/Exception
  }
  
  /* Error */
  public j ˊ(android.net.Uri paramUri)
  {
    // Byte code:
    //   0: goto +20 -> 20
    //   3: astore_1
    //   4: aload_1
    //   5: athrow
    //   6: aload_0
    //   7: getfield 128	o/j:ˋ	Landroid/content/Intent;
    //   10: astore_3
    //   11: aload_3
    //   12: aload_1
    //   13: invokevirtual 284	android/content/Intent:setData	(Landroid/net/Uri;)Landroid/content/Intent;
    //   16: pop
    //   17: goto +33 -> 50
    //   20: getstatic 19	o/j:ˎ	I
    //   23: bipush 89
    //   25: iadd
    //   26: istore_2
    //   27: iload_2
    //   28: sipush 128
    //   31: irem
    //   32: putstatic 21	o/j:ʻ	I
    //   35: iload_2
    //   36: iconst_2
    //   37: irem
    //   38: ifne +6 -> 44
    //   41: goto +6 -> 47
    //   44: goto -38 -> 6
    //   47: goto -41 -> 6
    //   50: getstatic 21	o/j:ʻ	I
    //   53: bipush 105
    //   55: iadd
    //   56: istore_2
    //   57: iload_2
    //   58: sipush 128
    //   61: irem
    //   62: putstatic 19	o/j:ˎ	I
    //   65: iload_2
    //   66: iconst_2
    //   67: irem
    //   68: ifeq +5 -> 73
    //   71: aload_0
    //   72: areturn
    //   73: aload_0
    //   74: areturn
    //   75: astore_1
    //   76: aload_1
    //   77: athrow
    // Local variable table:
    //   start	length	slot	name	signature
    //   0	78	0	this	j
    //   0	78	1	paramUri	android.net.Uri
    //   26	42	2	i	int
    //   10	2	3	localIntent	Intent
    // Exception table:
    //   from	to	target	type
    //   6	11	3	java/lang/Exception
    //   11	17	75	java/lang/Exception
  }
  
  /* Error */
  public j ˊ(android.os.Bundle paramBundle)
  {
    // Byte code:
    //   0: goto +81 -> 81
    //   3: astore_1
    //   4: aload_1
    //   5: athrow
    //   6: aload_0
    //   7: getfield 128	o/j:ˋ	Landroid/content/Intent;
    //   10: aload_1
    //   11: invokevirtual 289	android/content/Intent:putExtras	(Landroid/os/Bundle;)Landroid/content/Intent;
    //   14: pop
    //   15: goto +6 -> 21
    //   18: goto -12 -> 6
    //   21: getstatic 19	o/j:ˎ	I
    //   24: bipush 23
    //   26: iadd
    //   27: istore_2
    //   28: iload_2
    //   29: sipush 128
    //   32: irem
    //   33: putstatic 21	o/j:ʻ	I
    //   36: iload_2
    //   37: iconst_2
    //   38: irem
    //   39: ifne +6 -> 45
    //   42: goto +37 -> 79
    //   45: aload_0
    //   46: areturn
    //   47: astore_1
    //   48: aload_1
    //   49: athrow
    //   50: getstatic 21	o/j:ʻ	I
    //   53: istore_2
    //   54: iload_2
    //   55: bipush 73
    //   57: iadd
    //   58: istore_2
    //   59: iload_2
    //   60: sipush 128
    //   63: irem
    //   64: putstatic 19	o/j:ˎ	I
    //   67: iload_2
    //   68: iconst_2
    //   69: irem
    //   70: ifeq +6 -> 76
    //   73: goto -55 -> 18
    //   76: goto -70 -> 6
    //   79: aload_0
    //   80: areturn
    //   81: goto -31 -> 50
    // Local variable table:
    //   start	length	slot	name	signature
    //   0	84	0	this	j
    //   0	84	1	paramBundle	android.os.Bundle
    //   27	43	2	i	int
    // Exception table:
    //   from	to	target	type
    //   59	67	3	java/lang/Exception
    //   50	54	47	java/lang/Exception
  }
  
  public j ˊ(String paramString, Serializable paramSerializable)
  {
    break label40;
    int i = ʻ + 41;
    ˎ = i % 128;
    if (i % 2 == 0) {
      break label43;
    }
    for (;;)
    {
      i = 0;
      break label64;
      break label43;
      return this;
      label40:
      break;
      label43:
      this.ˋ.putExtra(paramString, paramSerializable);
      break label95;
      throw new NullPointerException();
      label64:
      switch (i)
      {
      }
      return this;
      label95:
      do
      {
        i = 1;
        break;
        i = ʻ + 95;
        ˎ = i % 128;
      } while (i % 2 != 0);
    }
  }
  
  public Intent ˋ()
  {
    for (;;)
    {
      int i = ʻ + 113;
      ˎ = i % 128;
      if (i % 2 == 0)
      {
        Intent localIntent;
        return localIntent;
        try
        {
          i = ʻ + 81;
          ˎ = i % 128;
          if (i % 2 == 0) {}
          for (;;)
          {
            localIntent = this.ˋ;
            break;
          }
          return localException;
        }
        catch (Exception localException)
        {
          throw localException;
        }
      }
    }
  }
  
  /* Error */
  public j ˋ(String paramString1, String paramString2)
  {
    // Byte code:
    //   0: goto +71 -> 71
    //   3: astore_1
    //   4: aload_1
    //   5: athrow
    //   6: aload_0
    //   7: getfield 128	o/j:ˋ	Landroid/content/Intent;
    //   10: aload_1
    //   11: aload_2
    //   12: invokevirtual 300	android/content/Intent:putExtra	(Ljava/lang/String;Ljava/lang/String;)Landroid/content/Intent;
    //   15: pop
    //   16: aload_0
    //   17: areturn
    //   18: aload_0
    //   19: getfield 128	o/j:ˋ	Landroid/content/Intent;
    //   22: astore 4
    //   24: aload 4
    //   26: aload_1
    //   27: aload_2
    //   28: invokevirtual 300	android/content/Intent:putExtra	(Ljava/lang/String;Ljava/lang/String;)Landroid/content/Intent;
    //   31: pop
    //   32: aconst_null
    //   33: arraylength
    //   34: istore_3
    //   35: aload_0
    //   36: areturn
    //   37: iconst_0
    //   38: istore_3
    //   39: goto +5 -> 44
    //   42: iconst_1
    //   43: istore_3
    //   44: iload_3
    //   45: tableswitch	default:+23->68, 0:+-39->6, 1:+-27->18
    //   68: goto -62 -> 6
    //   71: getstatic 21	o/j:ʻ	I
    //   74: bipush 57
    //   76: iadd
    //   77: istore_3
    //   78: iload_3
    //   79: sipush 128
    //   82: irem
    //   83: putstatic 19	o/j:ˎ	I
    //   86: iload_3
    //   87: iconst_2
    //   88: irem
    //   89: ifeq +6 -> 95
    //   92: goto -50 -> 42
    //   95: goto -58 -> 37
    // Local variable table:
    //   start	length	slot	name	signature
    //   0	98	0	this	j
    //   0	98	1	paramString1	String
    //   0	98	2	paramString2	String
    //   34	55	3	i	int
    //   22	3	4	localIntent	Intent
    // Exception table:
    //   from	to	target	type
    //   18	24	3	java/lang/Exception
    //   24	35	3	java/lang/Exception
  }
  
  public j ˎ(String paramString, Parcelable paramParcelable)
  {
    break label34;
    int i = 1;
    for (;;)
    {
      i = 0;
      switch (i)
      {
      default: 
        return this;
        try
        {
          localIntent = this.ˋ;
        }
        catch (Exception paramString)
        {
          Intent localIntent;
          throw paramString;
        }
      case 1: 
        try
        {
          label34:
          localIntent.putExtra(paramString, paramParcelable);
          i = 93 / 0;
        }
        catch (Exception paramString)
        {
          label107:
          throw paramString;
        }
        i = ʻ + 125;
        ˎ = i % 128;
        if (i % 2 == 0) {
          break label107;
        }
        i = 1;
        for (;;)
        {
          this.ˋ.putExtra(paramString, paramParcelable);
          break;
          i = 0;
          switch (i)
          {
          }
        }
        throw new NullPointerException();
      }
      return this;
      i = ʻ;
      i += 121;
      ˎ = i % 128;
      if (i % 2 != 0) {
        break;
      }
    }
  }
  
  public void ˎ()
  {
    for (;;)
    {
      int i = 0;
      break label274;
      switch (i)
      {
      default: 
        label8:
        return;
        break;
        label36:
        i = 38;
        break label170;
        label42:
        i = 57;
        break label238;
        i = 1;
        break;
      }
      try
      {
        label53:
        Object localObject = this.ॱ;
        try
        {
          Activity localActivity = (Activity)localObject;
          Intent localIntent = localActivity.getIntent();
          localObject = ˎ('\000', 105, 80);
          boolean bool = localIntent.hasExtra(((String)localObject).intern());
          if (!bool)
          {
            break label42;
            if ((this.ॱ instanceof Activity)) {
              break label304;
            }
            break;
          }
          i = 67;
          break label238;
          localActivity = (Activity)this.ॱ;
          if (localActivity.getIntent().hasExtra(ˎ('\000', 72, 21).intern())) {
            break label36;
          }
          break label167;
          throw new NullPointerException();
          label167:
          i = 94;
          label170:
          localObject = localActivity;
          switch (i)
          {
          default: 
            localObject = localActivity;
            break label351;
            for (;;)
            {
              i = 1;
              break;
              i = ʻ + 99;
              ˎ = i % 128;
              if (i % 2 != 0) {
                break label299;
              }
            }
            label238:
            localObject = localActivity;
            switch (i)
            {
            default: 
              localObject = localActivity;
              break label351;
              label274:
              switch (i)
              {
              }
              break label53;
              label299:
              i = 0;
              break label8;
              label304:
              i = ʻ + 5;
              ˎ = i % 128;
              if (i % 2 != 0) {
                continue;
              }
              break;
            }
            break;
          }
        }
        catch (Exception localException1)
        {
          throw localException1;
        }
        return;
      }
      catch (Exception localException2)
      {
        throw localException2;
      }
    }
    for (;;)
    {
      this.ॱ.startActivity(this.ˋ);
      break;
      label351:
      ˏ(localException2.getIntent().getStringExtra(ˎ('\000', 72, 21).intern()));
    }
  }
  
  /* Error */
  public void ˎ(int paramInt)
  {
    // Byte code:
    //   0: goto +143 -> 143
    //   3: astore 4
    //   5: aload 4
    //   7: athrow
    //   8: iconst_1
    //   9: istore_2
    //   10: goto +108 -> 118
    //   13: goto +133 -> 146
    //   16: iconst_0
    //   17: bipush 33
    //   19: bipush 39
    //   21: invokestatic 267	o/j:ˎ	(CII)Ljava/lang/String;
    //   24: astore 4
    //   26: new 321	java/lang/IllegalArgumentException
    //   29: dup
    //   30: aload 4
    //   32: invokevirtual 271	java/lang/String:intern	()Ljava/lang/String;
    //   35: invokespecial 322	java/lang/IllegalArgumentException:<init>	(Ljava/lang/String;)V
    //   38: athrow
    //   39: aload 4
    //   41: aload_0
    //   42: getfield 128	o/j:ˋ	Landroid/content/Intent;
    //   45: iload_1
    //   46: invokevirtual 326	android/app/Activity:startActivityForResult	(Landroid/content/Intent;I)V
    //   49: goto +46 -> 95
    //   52: getstatic 19	o/j:ˎ	I
    //   55: bipush 47
    //   57: iadd
    //   58: istore_2
    //   59: iload_2
    //   60: sipush 128
    //   63: irem
    //   64: putstatic 21	o/j:ʻ	I
    //   67: iload_2
    //   68: iconst_2
    //   69: irem
    //   70: ifne +6 -> 76
    //   73: goto -60 -> 13
    //   76: goto +70 -> 146
    //   79: aload_0
    //   80: getfield 126	o/j:ॱ	Landroid/content/Context;
    //   83: instanceof 261
    //   86: istore_3
    //   87: new 295	java/lang/NullPointerException
    //   90: dup
    //   91: invokespecial 296	java/lang/NullPointerException:<init>	()V
    //   94: athrow
    //   95: getstatic 21	o/j:ʻ	I
    //   98: bipush 115
    //   100: iadd
    //   101: istore_1
    //   102: iload_1
    //   103: sipush 128
    //   106: irem
    //   107: putstatic 19	o/j:ˎ	I
    //   110: iload_1
    //   111: iconst_2
    //   112: irem
    //   113: ifeq +4 -> 117
    //   116: return
    //   117: return
    //   118: iload_2
    //   119: tableswitch	default:+21->140, 0:+107->226, 1:+-40->79
    //   140: goto -61 -> 79
    //   143: goto +99 -> 242
    //   146: aload_0
    //   147: getfield 126	o/j:ॱ	Landroid/content/Context;
    //   150: astore 4
    //   152: aload 4
    //   154: checkcast 261	android/app/Activity
    //   157: astore 4
    //   159: aload 4
    //   161: invokevirtual 265	android/app/Activity:getIntent	()Landroid/content/Intent;
    //   164: iconst_0
    //   165: bipush 72
    //   167: bipush 21
    //   169: invokestatic 267	o/j:ˎ	(CII)Ljava/lang/String;
    //   172: invokevirtual 271	java/lang/String:intern	()Ljava/lang/String;
    //   175: invokevirtual 308	android/content/Intent:hasExtra	(Ljava/lang/String;)Z
    //   178: istore_3
    //   179: iload_3
    //   180: ifeq +6 -> 186
    //   183: goto +16 -> 199
    //   186: goto -147 -> 39
    //   189: iconst_0
    //   190: istore_2
    //   191: goto -73 -> 118
    //   194: astore 4
    //   196: aload 4
    //   198: athrow
    //   199: aload_0
    //   200: aload 4
    //   202: invokevirtual 265	android/app/Activity:getIntent	()Landroid/content/Intent;
    //   205: iconst_0
    //   206: bipush 72
    //   208: bipush 21
    //   210: invokestatic 267	o/j:ˎ	(CII)Ljava/lang/String;
    //   213: invokevirtual 271	java/lang/String:intern	()Ljava/lang/String;
    //   216: invokevirtual 315	android/content/Intent:getStringExtra	(Ljava/lang/String;)Ljava/lang/String;
    //   219: invokevirtual 318	o/j:ˏ	(Ljava/lang/String;)Lo/j;
    //   222: pop
    //   223: goto -184 -> 39
    //   226: aload_0
    //   227: getfield 126	o/j:ॱ	Landroid/content/Context;
    //   230: instanceof 261
    //   233: ifeq +6 -> 239
    //   236: goto -184 -> 52
    //   239: goto -223 -> 16
    //   242: getstatic 19	o/j:ˎ	I
    //   245: bipush 97
    //   247: iadd
    //   248: istore_2
    //   249: iload_2
    //   250: sipush 128
    //   253: irem
    //   254: putstatic 21	o/j:ʻ	I
    //   257: iload_2
    //   258: iconst_2
    //   259: irem
    //   260: ifne +6 -> 266
    //   263: goto -255 -> 8
    //   266: goto -77 -> 189
    // Local variable table:
    //   start	length	slot	name	signature
    //   0	269	0	this	j
    //   0	269	1	paramInt	int
    //   9	251	2	i	int
    //   86	94	3	bool	boolean
    //   3	3	4	localException1	Exception
    //   24	136	4	localObject	Object
    //   194	7	4	localException2	Exception
    // Exception table:
    //   from	to	target	type
    //   16	26	3	java/lang/Exception
    //   26	39	3	java/lang/Exception
    //   146	152	3	java/lang/Exception
    //   152	179	3	java/lang/Exception
    //   16	26	194	java/lang/Exception
  }
  
  /* Error */
  public j ˏ()
  {
    // Byte code:
    //   0: goto +135 -> 135
    //   3: astore_2
    //   4: aload_2
    //   5: athrow
    //   6: iconst_0
    //   7: istore_1
    //   8: goto +130 -> 138
    //   11: iconst_1
    //   12: istore_1
    //   13: goto +125 -> 138
    //   16: getstatic 21	o/j:ʻ	I
    //   19: bipush 77
    //   21: iadd
    //   22: istore_1
    //   23: iload_1
    //   24: sipush 128
    //   27: irem
    //   28: putstatic 19	o/j:ˎ	I
    //   31: iload_1
    //   32: iconst_2
    //   33: irem
    //   34: ifeq +6 -> 40
    //   37: goto -26 -> 11
    //   40: goto -34 -> 6
    //   43: aload_0
    //   44: areturn
    //   45: aload_0
    //   46: getfield 128	o/j:ˋ	Landroid/content/Intent;
    //   49: ldc_w 327
    //   52: invokevirtual 331	android/content/Intent:addFlags	(I)Landroid/content/Intent;
    //   55: pop
    //   56: aload_0
    //   57: getfield 126	o/j:ॱ	Landroid/content/Context;
    //   60: checkcast 261	android/app/Activity
    //   63: iconst_1
    //   64: iconst_0
    //   65: invokevirtual 335	android/app/Activity:overridePendingTransition	(II)V
    //   68: goto +31 -> 99
    //   71: aconst_null
    //   72: arraylength
    //   73: istore_1
    //   74: aload_0
    //   75: areturn
    //   76: aload_0
    //   77: getfield 128	o/j:ˋ	Landroid/content/Intent;
    //   80: ldc_w 327
    //   83: invokevirtual 331	android/content/Intent:addFlags	(I)Landroid/content/Intent;
    //   86: pop
    //   87: aload_0
    //   88: getfield 126	o/j:ॱ	Landroid/content/Context;
    //   91: checkcast 261	android/app/Activity
    //   94: iconst_0
    //   95: iconst_0
    //   96: invokevirtual 335	android/app/Activity:overridePendingTransition	(II)V
    //   99: goto -83 -> 16
    //   102: bipush 31
    //   104: istore_1
    //   105: iload_1
    //   106: lookupswitch	default:+26->132, 31:+-61->45, 88:+-30->76
    //   132: goto -56 -> 76
    //   135: goto +86 -> 221
    //   138: iload_1
    //   139: tableswitch	default:+21->160, 0:+-96->43, 1:+-68->71
    //   160: goto -89 -> 71
    //   163: getstatic 21	o/j:ʻ	I
    //   166: iconst_5
    //   167: iadd
    //   168: istore_1
    //   169: iload_1
    //   170: sipush 128
    //   173: irem
    //   174: putstatic 19	o/j:ˎ	I
    //   177: iload_1
    //   178: iconst_2
    //   179: irem
    //   180: ifeq +6 -> 186
    //   183: goto -81 -> 102
    //   186: goto +29 -> 215
    //   189: iconst_0
    //   190: bipush 33
    //   192: bipush 39
    //   194: invokestatic 267	o/j:ˎ	(CII)Ljava/lang/String;
    //   197: astore_2
    //   198: aload_2
    //   199: invokevirtual 271	java/lang/String:intern	()Ljava/lang/String;
    //   202: astore_2
    //   203: new 321	java/lang/IllegalArgumentException
    //   206: dup
    //   207: aload_2
    //   208: invokespecial 322	java/lang/IllegalArgumentException:<init>	(Ljava/lang/String;)V
    //   211: athrow
    //   212: astore_2
    //   213: aload_2
    //   214: athrow
    //   215: bipush 88
    //   217: istore_1
    //   218: goto -113 -> 105
    //   221: aload_0
    //   222: getfield 126	o/j:ॱ	Landroid/content/Context;
    //   225: astore_2
    //   226: aload_2
    //   227: instanceof 261
    //   230: ifeq +6 -> 236
    //   233: goto -70 -> 163
    //   236: goto -47 -> 189
    // Local variable table:
    //   start	length	slot	name	signature
    //   0	239	0	this	j
    //   7	211	1	i	int
    //   3	2	2	localException1	Exception
    //   197	11	2	str	String
    //   212	2	2	localException2	Exception
    //   225	2	2	localContext	Context
    // Exception table:
    //   from	to	target	type
    //   198	203	3	java/lang/Exception
    //   189	198	212	java/lang/Exception
    //   198	203	212	java/lang/Exception
    //   203	212	212	java/lang/Exception
    //   221	226	212	java/lang/Exception
  }
  
  /* Error */
  public j ˏ(String paramString)
  {
    // Byte code:
    //   0: goto +96 -> 96
    //   3: astore_1
    //   4: aload_1
    //   5: athrow
    //   6: aload_0
    //   7: getfield 128	o/j:ˋ	Landroid/content/Intent;
    //   10: astore_3
    //   11: iconst_0
    //   12: bipush 72
    //   14: bipush 21
    //   16: invokestatic 267	o/j:ˎ	(CII)Ljava/lang/String;
    //   19: astore 4
    //   21: aload_3
    //   22: aload 4
    //   24: invokevirtual 271	java/lang/String:intern	()Ljava/lang/String;
    //   27: aload_1
    //   28: invokevirtual 300	android/content/Intent:putExtra	(Ljava/lang/String;Ljava/lang/String;)Landroid/content/Intent;
    //   31: pop
    //   32: aload_0
    //   33: areturn
    //   34: astore_1
    //   35: aload_1
    //   36: athrow
    //   37: iconst_0
    //   38: istore_2
    //   39: goto +25 -> 64
    //   42: aload_0
    //   43: getfield 128	o/j:ˋ	Landroid/content/Intent;
    //   46: iconst_0
    //   47: bipush 56
    //   49: bipush 80
    //   51: invokestatic 267	o/j:ˎ	(CII)Ljava/lang/String;
    //   54: invokevirtual 271	java/lang/String:intern	()Ljava/lang/String;
    //   57: aload_1
    //   58: invokevirtual 300	android/content/Intent:putExtra	(Ljava/lang/String;Ljava/lang/String;)Landroid/content/Intent;
    //   61: pop
    //   62: aload_0
    //   63: areturn
    //   64: iload_2
    //   65: tableswitch	default:+23->88, 0:+-23->42, 1:+-59->6
    //   88: goto -82 -> 6
    //   91: iconst_1
    //   92: istore_2
    //   93: goto -29 -> 64
    //   96: getstatic 21	o/j:ʻ	I
    //   99: istore_2
    //   100: iload_2
    //   101: bipush 17
    //   103: iadd
    //   104: istore_2
    //   105: iload_2
    //   106: sipush 128
    //   109: irem
    //   110: putstatic 19	o/j:ˎ	I
    //   113: iload_2
    //   114: iconst_2
    //   115: irem
    //   116: ifeq +6 -> 122
    //   119: goto -82 -> 37
    //   122: goto -31 -> 91
    // Local variable table:
    //   start	length	slot	name	signature
    //   0	125	0	this	j
    //   0	125	1	paramString	String
    //   38	78	2	i	int
    //   10	12	3	localIntent	Intent
    //   19	4	4	str	String
    // Exception table:
    //   from	to	target	type
    //   6	11	3	java/lang/Exception
    //   11	21	3	java/lang/Exception
    //   21	32	3	java/lang/Exception
    //   11	21	34	java/lang/Exception
    //   96	100	34	java/lang/Exception
    //   105	113	34	java/lang/Exception
  }
  
  /* Error */
  public j ˏ(String paramString, Integer paramInteger)
  {
    // Byte code:
    //   0: goto +35 -> 35
    //   3: astore_1
    //   4: aload_1
    //   5: athrow
    //   6: aload_0
    //   7: getfield 128	o/j:ˋ	Landroid/content/Intent;
    //   10: aload_1
    //   11: aload_2
    //   12: invokevirtual 293	android/content/Intent:putExtra	(Ljava/lang/String;Ljava/io/Serializable;)Landroid/content/Intent;
    //   15: pop
    //   16: goto +54 -> 70
    //   19: new 295	java/lang/NullPointerException
    //   22: dup
    //   23: invokespecial 296	java/lang/NullPointerException:<init>	()V
    //   26: athrow
    //   27: aload_0
    //   28: areturn
    //   29: bipush 71
    //   31: istore_3
    //   32: goto +9 -> 41
    //   35: goto +64 -> 99
    //   38: goto -32 -> 6
    //   41: iload_3
    //   42: lookupswitch	default:+26->68, 55:+-15->27, 71:+-23->19
    //   68: aload_0
    //   69: areturn
    //   70: getstatic 19	o/j:ˎ	I
    //   73: istore_3
    //   74: iload_3
    //   75: bipush 113
    //   77: iadd
    //   78: istore_3
    //   79: iload_3
    //   80: sipush 128
    //   83: irem
    //   84: putstatic 21	o/j:ʻ	I
    //   87: iload_3
    //   88: iconst_2
    //   89: irem
    //   90: ifne +6 -> 96
    //   93: goto -64 -> 29
    //   96: goto +30 -> 126
    //   99: getstatic 19	o/j:ˎ	I
    //   102: bipush 11
    //   104: iadd
    //   105: istore_3
    //   106: iload_3
    //   107: sipush 128
    //   110: irem
    //   111: putstatic 21	o/j:ʻ	I
    //   114: iload_3
    //   115: iconst_2
    //   116: irem
    //   117: ifne +6 -> 123
    //   120: goto -82 -> 38
    //   123: goto -117 -> 6
    //   126: bipush 55
    //   128: istore_3
    //   129: goto -88 -> 41
    // Local variable table:
    //   start	length	slot	name	signature
    //   0	132	0	this	j
    //   0	132	1	paramString	String
    //   0	132	2	paramInteger	Integer
    //   31	98	3	i	int
    // Exception table:
    //   from	to	target	type
    //   70	74	3	java/lang/Exception
    //   79	87	3	java/lang/Exception
  }
  
  /* Error */
  public j ˏ(String paramString, boolean paramBoolean)
  {
    // Byte code:
    //   0: goto +127 -> 127
    //   3: astore_1
    //   4: aload_1
    //   5: athrow
    //   6: getstatic 21	o/j:ʻ	I
    //   9: bipush 93
    //   11: iadd
    //   12: istore_3
    //   13: iload_3
    //   14: sipush 128
    //   17: irem
    //   18: putstatic 19	o/j:ˎ	I
    //   21: iload_3
    //   22: iconst_2
    //   23: irem
    //   24: ifeq +6 -> 30
    //   27: goto +90 -> 117
    //   30: goto +8 -> 38
    //   33: iconst_1
    //   34: istore_3
    //   35: goto +20 -> 55
    //   38: aload_0
    //   39: getfield 128	o/j:ˋ	Landroid/content/Intent;
    //   42: astore 4
    //   44: aload 4
    //   46: aload_1
    //   47: iload_2
    //   48: invokevirtual 279	android/content/Intent:putExtra	(Ljava/lang/String;Z)Landroid/content/Intent;
    //   51: pop
    //   52: goto +38 -> 90
    //   55: iload_3
    //   56: tableswitch	default:+24->80, 0:+32->88, 1:+64->120
    //   80: goto +40 -> 120
    //   83: iconst_0
    //   84: istore_3
    //   85: goto -30 -> 55
    //   88: aload_0
    //   89: areturn
    //   90: getstatic 21	o/j:ʻ	I
    //   93: bipush 25
    //   95: iadd
    //   96: istore_3
    //   97: iload_3
    //   98: sipush 128
    //   101: irem
    //   102: putstatic 19	o/j:ˎ	I
    //   105: iload_3
    //   106: iconst_2
    //   107: irem
    //   108: ifeq +6 -> 114
    //   111: goto -78 -> 33
    //   114: goto -31 -> 83
    //   117: goto -79 -> 38
    //   120: bipush 53
    //   122: iconst_0
    //   123: idiv
    //   124: istore_3
    //   125: aload_0
    //   126: areturn
    //   127: goto -121 -> 6
    // Local variable table:
    //   start	length	slot	name	signature
    //   0	130	0	this	j
    //   0	130	1	paramString	String
    //   0	130	2	paramBoolean	boolean
    //   12	113	3	i	int
    //   42	3	4	localIntent	Intent
    // Exception table:
    //   from	to	target	type
    //   38	44	3	java/lang/Exception
    //   44	52	3	java/lang/Exception
  }
  
  /* Error */
  public j ˏ(int... paramVarArgs)
  {
    // Byte code:
    //   0: goto +59 -> 59
    //   3: iload_2
    //   4: iload 4
    //   6: if_icmpge +6 -> 12
    //   9: goto +93 -> 102
    //   12: goto +58 -> 70
    //   15: aload_1
    //   16: arraylength
    //   17: istore 4
    //   19: iconst_0
    //   20: istore_3
    //   21: goto +117 -> 138
    //   24: astore_1
    //   25: aload_1
    //   26: athrow
    //   27: getstatic 19	o/j:ˎ	I
    //   30: bipush 35
    //   32: iadd
    //   33: istore_2
    //   34: iload_2
    //   35: sipush 128
    //   38: irem
    //   39: putstatic 21	o/j:ʻ	I
    //   42: iload_2
    //   43: iconst_2
    //   44: irem
    //   45: ifne +6 -> 51
    //   48: goto +60 -> 108
    //   51: goto -36 -> 15
    //   54: iload_3
    //   55: istore_2
    //   56: goto -53 -> 3
    //   59: goto -32 -> 27
    //   62: aload_0
    //   63: areturn
    //   64: goto +18 -> 82
    //   67: astore_1
    //   68: aload_1
    //   69: athrow
    //   70: bipush 14
    //   72: istore_3
    //   73: goto +122 -> 195
    //   76: bipush 90
    //   78: istore_2
    //   79: goto +86 -> 165
    //   82: aload_1
    //   83: iload_2
    //   84: iaload
    //   85: istore_3
    //   86: aload_0
    //   87: getfield 128	o/j:ˋ	Landroid/content/Intent;
    //   90: iload_3
    //   91: invokevirtual 331	android/content/Intent:addFlags	(I)Landroid/content/Intent;
    //   94: pop
    //   95: iload_2
    //   96: iconst_1
    //   97: iadd
    //   98: istore_2
    //   99: goto -96 -> 3
    //   102: bipush 49
    //   104: istore_3
    //   105: goto +90 -> 195
    //   108: goto -93 -> 15
    //   111: getstatic 19	o/j:ˎ	I
    //   114: bipush 83
    //   116: iadd
    //   117: istore_3
    //   118: iload_3
    //   119: sipush 128
    //   122: irem
    //   123: putstatic 21	o/j:ʻ	I
    //   126: iload_3
    //   127: iconst_2
    //   128: irem
    //   129: ifne +6 -> 135
    //   132: goto -68 -> 64
    //   135: goto -53 -> 82
    //   138: getstatic 21	o/j:ʻ	I
    //   141: bipush 13
    //   143: iadd
    //   144: istore_2
    //   145: iload_2
    //   146: sipush 128
    //   149: irem
    //   150: putstatic 19	o/j:ˎ	I
    //   153: iload_2
    //   154: iconst_2
    //   155: irem
    //   156: ifeq +6 -> 162
    //   159: goto -83 -> 76
    //   162: goto +64 -> 226
    //   165: iload_2
    //   166: lookupswitch	default:+26->192, 82:+-112->54, 90:+66->232
    //   192: goto +40 -> 232
    //   195: iload_3
    //   196: lookupswitch	default:+28->224, 14:+-134->62, 49:+-85->111
    //   224: aload_0
    //   225: areturn
    //   226: bipush 82
    //   228: istore_2
    //   229: goto -64 -> 165
    //   232: iconst_5
    //   233: iconst_5
    //   234: idiv
    //   235: istore_2
    //   236: iload_3
    //   237: istore_2
    //   238: goto -235 -> 3
    // Local variable table:
    //   start	length	slot	name	signature
    //   0	241	0	this	j
    //   0	241	1	paramVarArgs	int[]
    //   3	235	2	i	int
    //   20	217	3	j	int
    //   4	14	4	k	int
    // Exception table:
    //   from	to	target	type
    //   111	118	24	java/lang/Exception
    //   118	126	24	java/lang/Exception
    //   138	145	67	java/lang/Exception
    //   145	153	67	java/lang/Exception
  }
  
  /* Error */
  public j ॱ(int paramInt)
  {
    // Byte code:
    //   0: goto +51 -> 51
    //   3: astore_3
    //   4: aload_3
    //   5: athrow
    //   6: iload_2
    //   7: lookupswitch	default:+25->32, 6:+28->35, 29:+56->63
    //   32: goto +31 -> 63
    //   35: aload_0
    //   36: getfield 128	o/j:ˋ	Landroid/content/Intent;
    //   39: astore_3
    //   40: aload_3
    //   41: iload_1
    //   42: invokevirtual 342	android/content/Intent:setFlags	(I)Landroid/content/Intent;
    //   45: pop
    //   46: aconst_null
    //   47: arraylength
    //   48: istore_1
    //   49: aload_0
    //   50: areturn
    //   51: goto +23 -> 74
    //   54: astore_3
    //   55: aload_3
    //   56: athrow
    //   57: bipush 29
    //   59: istore_2
    //   60: goto -54 -> 6
    //   63: aload_0
    //   64: getfield 128	o/j:ˋ	Landroid/content/Intent;
    //   67: iload_1
    //   68: invokevirtual 342	android/content/Intent:setFlags	(I)Landroid/content/Intent;
    //   71: pop
    //   72: aload_0
    //   73: areturn
    //   74: getstatic 19	o/j:ˎ	I
    //   77: bipush 101
    //   79: iadd
    //   80: istore_2
    //   81: iload_2
    //   82: sipush 128
    //   85: irem
    //   86: putstatic 21	o/j:ʻ	I
    //   89: iload_2
    //   90: iconst_2
    //   91: irem
    //   92: ifne +6 -> 98
    //   95: goto +6 -> 101
    //   98: goto -41 -> 57
    //   101: bipush 6
    //   103: istore_2
    //   104: goto -98 -> 6
    // Local variable table:
    //   start	length	slot	name	signature
    //   0	107	0	this	j
    //   0	107	1	paramInt	int
    //   6	98	2	i	int
    //   3	2	3	localException1	Exception
    //   39	2	3	localIntent	Intent
    //   54	2	3	localException2	Exception
    // Exception table:
    //   from	to	target	type
    //   40	49	3	java/lang/Exception
    //   35	40	54	java/lang/Exception
    //   40	49	54	java/lang/Exception
  }
  
  /* Error */
  public void ॱ()
  {
    // Byte code:
    //   0: goto +38 -> 38
    //   3: new 295	java/lang/NullPointerException
    //   6: dup
    //   7: invokespecial 296	java/lang/NullPointerException:<init>	()V
    //   10: athrow
    //   11: goto +12 -> 23
    //   14: astore_2
    //   15: aload_2
    //   16: athrow
    //   17: iconst_1
    //   18: istore_1
    //   19: goto +48 -> 67
    //   22: return
    //   23: aload_0
    //   24: getfield 126	o/j:ॱ	Landroid/content/Context;
    //   27: aload_0
    //   28: getfield 128	o/j:ˋ	Landroid/content/Intent;
    //   31: invokevirtual 346	android/content/Context:startService	(Landroid/content/Intent;)Landroid/content/ComponentName;
    //   34: pop
    //   35: goto +58 -> 93
    //   38: getstatic 19	o/j:ˎ	I
    //   41: istore_1
    //   42: iload_1
    //   43: bipush 11
    //   45: iadd
    //   46: istore_1
    //   47: iload_1
    //   48: sipush 128
    //   51: irem
    //   52: putstatic 21	o/j:ʻ	I
    //   55: iload_1
    //   56: iconst_2
    //   57: irem
    //   58: ifne +6 -> 64
    //   61: goto -50 -> 11
    //   64: goto -41 -> 23
    //   67: iload_1
    //   68: tableswitch	default:+24->92, 0:+-65->3, 1:+-46->22
    //   92: return
    //   93: getstatic 21	o/j:ʻ	I
    //   96: bipush 27
    //   98: iadd
    //   99: istore_1
    //   100: iload_1
    //   101: sipush 128
    //   104: irem
    //   105: putstatic 19	o/j:ˎ	I
    //   108: iload_1
    //   109: iconst_2
    //   110: irem
    //   111: ifeq +6 -> 117
    //   114: goto +6 -> 120
    //   117: goto -100 -> 17
    //   120: iconst_0
    //   121: istore_1
    //   122: goto -55 -> 67
    // Local variable table:
    //   start	length	slot	name	signature
    //   0	125	0	this	j
    //   18	104	1	i	int
    //   14	2	2	localException	Exception
    // Exception table:
    //   from	to	target	type
    //   38	42	14	java/lang/Exception
    //   47	55	14	java/lang/Exception
  }
}
