package o;

import android.content.Intent;
import android.net.Uri;
import com.crashlytics.android.Crashlytics;
import java.util.HashMap;
import java.util.Iterator;
import java.util.Map;

public final class JA
  extends Iy<JB.If, Jt>
  implements JB.ˊ
{
  private static int ˊॱ = 0;
  private static char[] ˋॱ = { -9778, 16786, -5865, 4257, -18390, 9163, 19307, -3344, 6758, -32194, 11650, 21821, -862, 25684, -28730, 14177, 24237, -14700, 28166, -30297, 12651, 22682, 67, -26607, 12434, -14028, 25056, -1420, -27963, 11108, -15391, 23449, -3060, -29533, 67, -26593, 12437, -14020, 24996, -1520, -27954, 11135, -15372, 23504, -3065, -29515, 9524, -17008, 22100, -4360, -30875, 8016, -18544, 20514, -5979, -32445, 6597, -19844, 19173, -7533, 31508, 5045, -21468, 17552, -8893, 30193, 3698, -23020, 16078, 67, -26593, 12437, -14020, 24996, -1520, -27954, 11135, -15372, 23504, -3054, -29515, 9524, -16958, 22089, -4363, -30858, 7957, -18496, 20516, -5976, -32427, 6528, -19843, 19169, -7548, 31506, 5049, -21448, 17552, -8893, 30193, 3698, -23020, 2545, -28253, 14643, -16241, 26629, -3090, -25756, 8832, -13730, 21025, -579, -31483, 11466, -19424, 10, 67, -26607, 12434, -14028, 25056, -1442, -27967, 11133, -15387, 23498, -3008, 23180, -15650, 27229, -27653, 15151, -24438, -14310, 29110, -26325, 261, -20849, 4547, -30331, 8466, -10078, 28709, -5154, -31916, 15024, -11693, 18981, -6741, -25341, 13562, -21488, -23352, 15543, -27608, 84, -26622, 12417, -14018, 25011, -1455, -27965, 11108, -15383, 23455, -3058, -29533, 9568, -16941, 22095, -4379, -30866, 7940, -18470, 20592, 77, -26607, 12440, -14023, 25005, -1467, -27955, 11056, -15373, 23449, -3058, -29513, 9516, -16939, 22016, -4380, -30862, 7953, -18546, 20515, -5983, -32429, 6612, -19847, 19183, -7522, 31552, 5041, -21459, 17631, -8875, 30206, 3700, -22966, 16064, -11700, 19003, -7507, 6918, -19567, 10344, 16605, -1702, 4566, -30301, 9787, 24202, -2291, 28577, -31637, 15552, 21868, -12997, 26029, -32250, 14993, 21352, -13385, 24582, 99, -26593, 12420, -14027, 70, -26599, 12436, -14030, 25001, -1468, 6777, -32218, 10923, -11507, 31638, -8069, -30529, 12617, -9762, 16806, -4557, -26998, 16155, -22609, 19563, -2880, -25313, 1326, -21078, 18971, -3433, -25760, 1005, -22458, 20677, -1878, 24959, 2498, -18862, 24241, -14529, 70, -26599, 12436, -14030, 25001, -1468, -28032, 11127, -15377, 23428, -3008, -29532, 9519, -16933, 22085, -4354, -30944, 8029, -18483, 20590, -5920, 70, -26599, 12436, -14030, 25001, -1468, -28032, 11126, -15391, 23449, -3060, -29515, 9508, -17008, 22087, -4363, -30860, 8016, -18540, 20543, -5973, -32427, 6606, -19920, 19117, -7459, 31582, 5104, 1512, -25209, 13595, -13127, 114, -26603, 12432, -14017, 25011, -1447, -27948, 11135, -15374, 23433, 27443, -3241, 23494, -23958, 2813, -28400, -1637, 16440, -22349, 12502, -24741, -6163, 20092, -10575, 15639, -31312, -5084, 29771, -9007, 15207, 104, -26620, 12436, -14048, 25011, -1526, -28017, 11071, -15369, 23431, -3049, -29442, 9510, -16935, 22100, -4366, -30871, 7940, -18482, 20531, -5969, -32419, 6543, -19841, 19169, -7547, 31508, 5048, -21390, 17567, -8895, 30181, 3700, -23016, 16015, -10462, 28585, 2122, -24379, 104, -26620, 12436, -14048, 25011, -1526, -28017, 11071, -15391, 23424, -3063, -29442, 9510, -16935, 22100, -4366, -30871, 7940, -18482, 20531, -5969, -32419, 6543, -19841, 19169, -7547, 31508, 5048, -21390, 17567, -8876, 30207, 3691, -23019, 16014, 50, -26558, 12451, -14074, 25078, -1417, -28570, 2071, -24442, 22885, -3598, 27141, 658, -17550, 21486, -13374, 25605, 7344, -19083, 11728, -14780, 32421, 5941, -28897, 10126, -16331, 30883, 4434, -30315, 8831, -9489, 29379, -5376, -31769, 15392, -11055, 19780, -6666, 97, -26605, 12436, -14023, 25014, -1447, -27948, 11113, -15456, 23448, -3067, -29519, 9522, -16956, 22098, -4367, -30860, 7957, -18496, 20512, -5966, -32417, 6598, -19847, 19180, -7531, 31552, 5052, -21457, 17619, -8895, 30180, 3689, -23009, 16014, 5818, -28971, 9801, -8196, 30563, -4978, -31736, 15795, -10946, 19712, -7547, -26059, 101, -26616, 12432, -14023, 25010, -1451, -27949, 11087, -15383, 23454, 29257, -5577, 17061, -17647, 4993 };
  private static long ˏॱ;
  private static int ͺ = 1;
  private final String ʻ;
  private final String ʼ;
  private final String ʽ;
  private final String ˊ;
  private final String ˋ;
  private final String ˎ;
  private final String ˏ;
  private wh ॱ;
  private final String ॱॱ;
  private final wk ᐝ;
  
  static
  {
    ˏॱ = -5735195609994782608L;
  }
  
  @uv
  public JA(JB.If paramIf, Jt paramJt, wk paramWk) {}
  
  private static String ˋ(int paramInt1, char paramChar, int paramInt2)
  {
    break label92;
    Object localObject;
    int i;
    localObject[i] = ((char)(int)(ˋॱ[(paramInt1 + i)] ^ i * ˏॱ ^ paramChar));
    i += 1;
    for (;;)
    {
      int j;
      if (i >= paramInt2)
      {
        break label86;
        j = ˊॱ + 55;
        ͺ = j % 128;
        if (j % 2 == 0) {
          break label127;
        }
        break;
      }
      for (;;)
      {
        localObject = new String((char[])localObject);
        break;
        label86:
        j = 1;
        break label98;
        label92:
        break label160;
        j = 0;
        label98:
        switch (j)
        {
        }
      }
      label127:
      break;
      paramInt1 = ͺ + 41;
      ˊॱ = paramInt1 % 128;
      if (paramInt1 % 2 == 0) {
        return localObject;
      }
      return localObject;
      label160:
      localObject = new char[paramInt2];
      i = 0;
    }
  }
  
  public void B_()
  {
    for (;;)
    {
      return;
      int i;
      for (;;)
      {
        i = ͺ + 59;
        ˊॱ = i % 128;
        if (i % 2 == 0) {
          break label40;
        }
        break label40;
        label34:
        break;
        break label41;
        label40:
        return;
        label41:
        vv.If localIf = new vv.If();
        try
        {
          localIf.ˎ = 0;
          wh localWh = this.ॱ;
          if (localWh == null) {}
          localWh.ˎ(this.ᐝ, (wh.ˋ)new if(this, localIf));
        }
        catch (Exception localException1)
        {
          throw localException1;
        }
      }
      try
      {
        i = ͺ;
        i += 49;
        ˊॱ = i % 128;
        if (i % 2 != 0) {
          break label34;
        }
      }
      catch (Exception localException2)
      {
        throw localException2;
      }
    }
  }
  
  public void ʻ()
  {
    label196:
    label199:
    label255:
    label271:
    label273:
    for (;;)
    {
      int i = ͺ + 23;
      ˊॱ = i % 128;
      Object localObject;
      if (i % 2 == 0)
      {
        return;
        for (;;)
        {
          if (ॱॱ())
          {
            break;
            localObject = null;
            break label196;
            continue;
            wj.If localIf = new wj.If((wm)localObject, this.ˏ, ˋ(236, '\000', 4).intern(), Uri.parse(this.ʽ));
            localObject = new HashMap();
            ((Map)localObject).put(this.ʼ, this.ʻ);
            localObject = localIf.ॱॱ(this.ॱॱ).ˏ((Map)localObject).ˊ();
            localObject = this.ᐝ.ˏ((wj)localObject);
            ((JB.If)ʽ()).ॱ((Intent)localObject);
          }
        }
      }
      for (;;)
      {
        i = 17;
        for (;;)
        {
          i = ˊॱ + 57;
          ͺ = i % 128;
          if (i % 2 != 0) {
            break;
          }
          break;
          return;
          i = 86;
          break label199;
          break label273;
          break label255;
          switch (i)
          {
          }
        }
        localObject = this.ॱ;
        if (localObject == null)
        {
          break;
          try
          {
            vq.ˎ();
          }
          catch (Exception localException)
          {
            throw localException;
          }
        }
        for (;;)
        {
          if (localException == null) {
            break label271;
          }
          break;
          wm localWm = localException.ॱ();
        }
      }
    }
  }
  
  /* Error */
  public void ˊ()
  {
    // Byte code:
    //   0: goto +8 -> 8
    //   3: iconst_0
    //   4: istore_1
    //   5: goto +76 -> 81
    //   8: goto +35 -> 43
    //   11: iload_1
    //   12: lookupswitch	default:+28->40, 61:+127->139, 80:+227->239
    //   40: goto +99 -> 139
    //   43: getstatic 41	o/JA:ͺ	I
    //   46: bipush 25
    //   48: iadd
    //   49: istore_1
    //   50: iload_1
    //   51: sipush 128
    //   54: irem
    //   55: putstatic 39	o/JA:ˊॱ	I
    //   58: iload_1
    //   59: iconst_2
    //   60: irem
    //   61: ifeq +6 -> 67
    //   64: goto +169 -> 233
    //   67: goto +66 -> 133
    //   70: iconst_1
    //   71: istore_1
    //   72: goto +9 -> 81
    //   75: bipush 65
    //   77: iconst_0
    //   78: idiv
    //   79: istore_1
    //   80: return
    //   81: iload_1
    //   82: tableswitch	default:+22->104, 0:+-7->75, 1:+50->132
    //   104: return
    //   105: getstatic 39	o/JA:ˊॱ	I
    //   108: bipush 55
    //   110: iadd
    //   111: istore_1
    //   112: iload_1
    //   113: sipush 128
    //   116: irem
    //   117: putstatic 41	o/JA:ͺ	I
    //   120: iload_1
    //   121: iconst_2
    //   122: irem
    //   123: ifne +6 -> 129
    //   126: goto -123 -> 3
    //   129: goto -59 -> 70
    //   132: return
    //   133: bipush 80
    //   135: istore_1
    //   136: goto -125 -> 11
    //   139: goto +17 -> 156
    //   142: astore_2
    //   143: aload_2
    //   144: invokevirtual 637	java/lang/Throwable:getCause	()Ljava/lang/Throwable;
    //   147: astore_3
    //   148: aload_3
    //   149: ifnull +5 -> 154
    //   152: aload_3
    //   153: athrow
    //   154: aload_2
    //   155: athrow
    //   156: iconst_4
    //   157: sipush 386
    //   160: ldc_w 638
    //   163: invokestatic 643	o/O:ˋ	(IIC)Ljava/lang/Object;
    //   166: checkcast 645	java/lang/Class
    //   169: ldc_w 646
    //   172: aconst_null
    //   173: invokevirtual 650	java/lang/Class:getMethod	(Ljava/lang/String;[Ljava/lang/Class;)Ljava/lang/reflect/Method;
    //   176: aconst_null
    //   177: aconst_null
    //   178: invokevirtual 656	java/lang/reflect/Method:invoke	(Ljava/lang/Object;[Ljava/lang/Object;)Ljava/lang/Object;
    //   181: astore_2
    //   182: goto +17 -> 199
    //   185: astore_2
    //   186: aload_2
    //   187: invokevirtual 637	java/lang/Throwable:getCause	()Ljava/lang/Throwable;
    //   190: astore_3
    //   191: aload_3
    //   192: ifnull +5 -> 197
    //   195: aload_3
    //   196: athrow
    //   197: aload_2
    //   198: athrow
    //   199: iconst_4
    //   200: sipush 386
    //   203: ldc_w 638
    //   206: invokestatic 643	o/O:ˋ	(IIC)Ljava/lang/Object;
    //   209: checkcast 645	java/lang/Class
    //   212: ldc_w 657
    //   215: aconst_null
    //   216: invokevirtual 650	java/lang/Class:getMethod	(Ljava/lang/String;[Ljava/lang/Class;)Ljava/lang/reflect/Method;
    //   219: aload_2
    //   220: aconst_null
    //   221: invokevirtual 656	java/lang/reflect/Method:invoke	(Ljava/lang/Object;[Ljava/lang/Object;)Ljava/lang/Object;
    //   224: pop
    //   225: new 659	java/lang/NullPointerException
    //   228: dup
    //   229: invokespecial 660	java/lang/NullPointerException:<init>	()V
    //   232: athrow
    //   233: bipush 61
    //   235: istore_1
    //   236: goto -225 -> 11
    //   239: goto +17 -> 256
    //   242: astore_3
    //   243: aload_3
    //   244: invokevirtual 637	java/lang/Throwable:getCause	()Ljava/lang/Throwable;
    //   247: astore_2
    //   248: aload_2
    //   249: ifnull +5 -> 254
    //   252: aload_2
    //   253: athrow
    //   254: aload_3
    //   255: athrow
    //   256: iconst_4
    //   257: sipush 386
    //   260: ldc_w 638
    //   263: invokestatic 643	o/O:ˋ	(IIC)Ljava/lang/Object;
    //   266: checkcast 645	java/lang/Class
    //   269: ldc_w 646
    //   272: aconst_null
    //   273: invokevirtual 650	java/lang/Class:getMethod	(Ljava/lang/String;[Ljava/lang/Class;)Ljava/lang/reflect/Method;
    //   276: aconst_null
    //   277: aconst_null
    //   278: invokevirtual 656	java/lang/reflect/Method:invoke	(Ljava/lang/Object;[Ljava/lang/Object;)Ljava/lang/Object;
    //   281: astore_2
    //   282: goto +17 -> 299
    //   285: astore_3
    //   286: aload_3
    //   287: invokevirtual 637	java/lang/Throwable:getCause	()Ljava/lang/Throwable;
    //   290: astore_2
    //   291: aload_2
    //   292: ifnull +5 -> 297
    //   295: aload_2
    //   296: athrow
    //   297: aload_3
    //   298: athrow
    //   299: iconst_4
    //   300: sipush 386
    //   303: ldc_w 638
    //   306: invokestatic 643	o/O:ˋ	(IIC)Ljava/lang/Object;
    //   309: checkcast 645	java/lang/Class
    //   312: ldc_w 657
    //   315: aconst_null
    //   316: invokevirtual 650	java/lang/Class:getMethod	(Ljava/lang/String;[Ljava/lang/Class;)Ljava/lang/reflect/Method;
    //   319: aload_2
    //   320: aconst_null
    //   321: invokevirtual 656	java/lang/reflect/Method:invoke	(Ljava/lang/Object;[Ljava/lang/Object;)Ljava/lang/Object;
    //   324: pop
    //   325: goto -220 -> 105
    // Local variable table:
    //   start	length	slot	name	signature
    //   0	328	0	this	JA
    //   4	232	1	i	int
    //   142	13	2	localObject1	Object
    //   181	1	2	localObject2	Object
    //   185	35	2	localObject3	Object
    //   247	73	2	localObject4	Object
    //   147	49	3	localThrowable	Throwable
    //   242	13	3	localObject5	Object
    //   285	13	3	localObject6	Object
    // Exception table:
    //   from	to	target	type
    //   156	182	142	finally
    //   199	225	185	finally
    //   256	282	242	finally
    //   299	325	285	finally
  }
  
  /* Error */
  public void ˊ(Intent paramIntent)
  {
    // Byte code:
    //   0: goto +67 -> 67
    //   3: iload_2
    //   4: lookupswitch	default:+28->32, 8:+166->170, 71:+105->109
    //   32: goto +77 -> 109
    //   35: goto +283 -> 318
    //   38: iload_2
    //   39: lookupswitch	default:+25->64, 24:+107->146, 47:+157->196
    //   64: goto +132 -> 196
    //   67: goto +69 -> 136
    //   70: aload_0
    //   71: getfield 543	o/JA:ᐝ	Lo/wk;
    //   74: aload_3
    //   75: invokevirtual 665	o/wi:ˊ	()Lo/wB;
    //   78: new 667	o/wo
    //   81: dup
    //   82: aload_0
    //   83: getfield 548	o/JA:ˊ	Ljava/lang/String;
    //   86: invokespecial 670	o/wo:<init>	(Ljava/lang/String;)V
    //   89: checkcast 672	o/wp
    //   92: new 9	o/JA$If
    //   95: dup
    //   96: aload_0
    //   97: invokespecial 675	o/JA$If:<init>	(Lo/JA;)V
    //   100: checkcast 677	o/wk$ˊ
    //   103: invokevirtual 680	o/wk:ˏ	(Lo/wB;Lo/wp;Lo/wk$ˊ;)V
    //   106: goto +61 -> 167
    //   109: getstatic 41	o/JA:ͺ	I
    //   112: bipush 53
    //   114: iadd
    //   115: istore_2
    //   116: iload_2
    //   117: sipush 128
    //   120: irem
    //   121: putstatic 39	o/JA:ˊॱ	I
    //   124: iload_2
    //   125: iconst_2
    //   126: irem
    //   127: ifeq +6 -> 133
    //   130: goto +60 -> 190
    //   133: goto +28 -> 161
    //   136: aload_1
    //   137: ifnonnull +6 -> 143
    //   140: goto +201 -> 341
    //   143: goto +12 -> 155
    //   146: invokestatic 628	o/vq:ˎ	()V
    //   149: aconst_null
    //   150: arraylength
    //   151: istore_2
    //   152: goto +18 -> 170
    //   155: bipush 8
    //   157: istore_2
    //   158: goto -155 -> 3
    //   161: bipush 47
    //   163: istore_2
    //   164: goto -126 -> 38
    //   167: goto -132 -> 35
    //   170: aload_1
    //   171: invokestatic 683	o/wi:ˎ	(Landroid/content/Intent;)Lo/wi;
    //   174: astore_3
    //   175: aload_1
    //   176: invokestatic 688	o/wf:ॱ	(Landroid/content/Intent;)Lo/wf;
    //   179: astore_1
    //   180: aload_3
    //   181: ifnull +6 -> 187
    //   184: goto -114 -> 70
    //   187: goto +15 -> 202
    //   190: bipush 24
    //   192: istore_2
    //   193: goto -155 -> 38
    //   196: invokestatic 628	o/vq:ˎ	()V
    //   199: goto -29 -> 170
    //   202: sipush 240
    //   205: iconst_0
    //   206: bipush 6
    //   208: invokestatic 524	o/JA:ˋ	(ICI)Ljava/lang/String;
    //   211: invokevirtual 529	java/lang/String:intern	()Ljava/lang/String;
    //   214: astore_3
    //   215: new 690	java/lang/StringBuilder
    //   218: dup
    //   219: invokespecial 691	java/lang/StringBuilder:<init>	()V
    //   222: sipush 246
    //   225: sipush 6719
    //   228: bipush 31
    //   230: invokestatic 524	o/JA:ˋ	(ICI)Ljava/lang/String;
    //   233: invokevirtual 529	java/lang/String:intern	()Ljava/lang/String;
    //   236: invokevirtual 695	java/lang/StringBuilder:append	(Ljava/lang/String;)Ljava/lang/StringBuilder;
    //   239: aload_1
    //   240: invokevirtual 698	java/lang/StringBuilder:append	(Ljava/lang/Object;)Ljava/lang/StringBuilder;
    //   243: invokevirtual 701	java/lang/StringBuilder:toString	()Ljava/lang/String;
    //   246: astore_1
    //   247: goto +17 -> 264
    //   250: astore_1
    //   251: aload_1
    //   252: invokevirtual 637	java/lang/Throwable:getCause	()Ljava/lang/Throwable;
    //   255: astore_3
    //   256: aload_3
    //   257: ifnull +5 -> 262
    //   260: aload_3
    //   261: athrow
    //   262: aload_1
    //   263: athrow
    //   264: iconst_4
    //   265: bipush 42
    //   267: ldc_w 702
    //   270: invokestatic 643	o/O:ˋ	(IIC)Ljava/lang/Object;
    //   273: checkcast 645	java/lang/Class
    //   276: ldc_w 646
    //   279: iconst_2
    //   280: anewarray 645	java/lang/Class
    //   283: dup
    //   284: iconst_0
    //   285: ldc_w 526
    //   288: aastore
    //   289: dup
    //   290: iconst_1
    //   291: ldc_w 526
    //   294: aastore
    //   295: invokevirtual 650	java/lang/Class:getMethod	(Ljava/lang/String;[Ljava/lang/Class;)Ljava/lang/reflect/Method;
    //   298: aconst_null
    //   299: iconst_2
    //   300: anewarray 704	java/lang/Object
    //   303: dup
    //   304: iconst_0
    //   305: aload_3
    //   306: aastore
    //   307: dup
    //   308: iconst_1
    //   309: aload_1
    //   310: aastore
    //   311: invokevirtual 656	java/lang/reflect/Method:invoke	(Ljava/lang/Object;[Ljava/lang/Object;)Ljava/lang/Object;
    //   314: pop
    //   315: goto -280 -> 35
    //   318: getstatic 41	o/JA:ͺ	I
    //   321: bipush 113
    //   323: iadd
    //   324: istore_2
    //   325: iload_2
    //   326: sipush 128
    //   329: irem
    //   330: putstatic 39	o/JA:ˊॱ	I
    //   333: iload_2
    //   334: iconst_2
    //   335: irem
    //   336: ifeq +4 -> 340
    //   339: return
    //   340: return
    //   341: bipush 71
    //   343: istore_2
    //   344: goto -341 -> 3
    // Local variable table:
    //   start	length	slot	name	signature
    //   0	347	0	this	JA
    //   0	347	1	paramIntent	Intent
    //   3	341	2	i	int
    //   74	232	3	localObject	Object
    // Exception table:
    //   from	to	target	type
    //   264	315	250	finally
  }
  
  /* Error */
  public void ˎ(wy paramWy, wf paramWf)
  {
    // Byte code:
    //   0: goto +553 -> 553
    //   3: getstatic 41	o/JA:ͺ	I
    //   6: bipush 61
    //   8: iadd
    //   9: istore_3
    //   10: iload_3
    //   11: sipush 128
    //   14: irem
    //   15: putstatic 39	o/JA:ˊॱ	I
    //   18: iload_3
    //   19: iconst_2
    //   20: irem
    //   21: ifeq +6 -> 27
    //   24: goto +132 -> 156
    //   27: goto +103 -> 130
    //   30: aload_1
    //   31: ifnull +6 -> 37
    //   34: goto +102 -> 136
    //   37: goto +309 -> 346
    //   40: iconst_0
    //   41: istore_3
    //   42: goto +33 -> 75
    //   45: iload_3
    //   46: lookupswitch	default:+26->72, 75:+90->136, 86:+300->346
    //   72: goto +274 -> 346
    //   75: iload_3
    //   76: tableswitch	default:+24->100, 0:+413->489, 1:+104->180
    //   100: goto +80 -> 180
    //   103: getstatic 41	o/JA:ͺ	I
    //   106: bipush 123
    //   108: iadd
    //   109: istore_3
    //   110: iload_3
    //   111: sipush 128
    //   114: irem
    //   115: putstatic 39	o/JA:ˊॱ	I
    //   118: iload_3
    //   119: iconst_2
    //   120: irem
    //   121: ifeq +6 -> 127
    //   124: goto +439 -> 563
    //   127: goto +207 -> 334
    //   130: bipush 42
    //   132: istore_3
    //   133: goto +385 -> 518
    //   136: aload_0
    //   137: getfield 521	o/JA:ॱ	Lo/wh;
    //   140: astore 4
    //   142: aload 4
    //   144: ifnull +6 -> 150
    //   147: goto -107 -> 40
    //   150: goto +185 -> 335
    //   153: astore_1
    //   154: aload_1
    //   155: athrow
    //   156: bipush 54
    //   158: istore_3
    //   159: goto +359 -> 518
    //   162: goto +24 -> 186
    //   165: aload_2
    //   166: invokevirtual 707	o/wh:ʻ	()Ljava/lang/String;
    //   169: astore_2
    //   170: aload_2
    //   171: ifnull +6 -> 177
    //   174: goto -12 -> 162
    //   177: goto +379 -> 556
    //   180: goto +280 -> 460
    //   183: astore_1
    //   184: aload_1
    //   185: athrow
    //   186: aload 4
    //   188: aload_2
    //   189: invokeinterface 709 2 0
    //   194: sipush 240
    //   197: iconst_0
    //   198: bipush 6
    //   200: invokestatic 524	o/JA:ˋ	(ICI)Ljava/lang/String;
    //   203: invokevirtual 529	java/lang/String:intern	()Ljava/lang/String;
    //   206: astore_2
    //   207: new 690	java/lang/StringBuilder
    //   210: dup
    //   211: invokespecial 691	java/lang/StringBuilder:<init>	()V
    //   214: sipush 277
    //   217: iconst_0
    //   218: bipush 21
    //   220: invokestatic 524	o/JA:ˋ	(ICI)Ljava/lang/String;
    //   223: invokevirtual 529	java/lang/String:intern	()Ljava/lang/String;
    //   226: invokevirtual 695	java/lang/StringBuilder:append	(Ljava/lang/String;)Ljava/lang/StringBuilder;
    //   229: aload_1
    //   230: getfield 712	o/wy:ˋ	Ljava/lang/String;
    //   233: invokevirtual 695	java/lang/StringBuilder:append	(Ljava/lang/String;)Ljava/lang/StringBuilder;
    //   236: invokevirtual 701	java/lang/StringBuilder:toString	()Ljava/lang/String;
    //   239: astore_1
    //   240: goto +17 -> 257
    //   243: astore_1
    //   244: aload_1
    //   245: invokevirtual 637	java/lang/Throwable:getCause	()Ljava/lang/Throwable;
    //   248: astore_2
    //   249: aload_2
    //   250: ifnull +5 -> 255
    //   253: aload_2
    //   254: athrow
    //   255: aload_1
    //   256: athrow
    //   257: iconst_4
    //   258: bipush 42
    //   260: ldc_w 702
    //   263: invokestatic 643	o/O:ˋ	(IIC)Ljava/lang/Object;
    //   266: checkcast 645	java/lang/Class
    //   269: ldc_w 646
    //   272: iconst_2
    //   273: anewarray 645	java/lang/Class
    //   276: dup
    //   277: iconst_0
    //   278: ldc_w 526
    //   281: aastore
    //   282: dup
    //   283: iconst_1
    //   284: ldc_w 526
    //   287: aastore
    //   288: invokevirtual 650	java/lang/Class:getMethod	(Ljava/lang/String;[Ljava/lang/Class;)Ljava/lang/reflect/Method;
    //   291: aconst_null
    //   292: iconst_2
    //   293: anewarray 704	java/lang/Object
    //   296: dup
    //   297: iconst_0
    //   298: aload_2
    //   299: aastore
    //   300: dup
    //   301: iconst_1
    //   302: aload_1
    //   303: aastore
    //   304: invokevirtual 656	java/lang/reflect/Method:invoke	(Ljava/lang/Object;[Ljava/lang/Object;)Ljava/lang/Object;
    //   307: pop
    //   308: return
    //   309: bipush 66
    //   311: iconst_0
    //   312: idiv
    //   313: istore_3
    //   314: aload_1
    //   315: ifnull +6 -> 321
    //   318: goto +229 -> 547
    //   321: goto +19 -> 340
    //   324: aload 4
    //   326: aload_1
    //   327: aload_2
    //   328: invokevirtual 714	o/wh:ˊ	(Lo/wy;Lo/wf;)V
    //   331: goto +129 -> 460
    //   334: return
    //   335: iconst_1
    //   336: istore_3
    //   337: goto -262 -> 75
    //   340: bipush 86
    //   342: istore_3
    //   343: goto -298 -> 45
    //   346: sipush 240
    //   349: iconst_0
    //   350: bipush 6
    //   352: invokestatic 524	o/JA:ˋ	(ICI)Ljava/lang/String;
    //   355: invokevirtual 529	java/lang/String:intern	()Ljava/lang/String;
    //   358: astore_1
    //   359: new 690	java/lang/StringBuilder
    //   362: dup
    //   363: invokespecial 691	java/lang/StringBuilder:<init>	()V
    //   366: sipush 298
    //   369: iconst_0
    //   370: bipush 28
    //   372: invokestatic 524	o/JA:ˋ	(ICI)Ljava/lang/String;
    //   375: invokevirtual 529	java/lang/String:intern	()Ljava/lang/String;
    //   378: invokevirtual 695	java/lang/StringBuilder:append	(Ljava/lang/String;)Ljava/lang/StringBuilder;
    //   381: aload_2
    //   382: invokevirtual 698	java/lang/StringBuilder:append	(Ljava/lang/Object;)Ljava/lang/StringBuilder;
    //   385: invokevirtual 701	java/lang/StringBuilder:toString	()Ljava/lang/String;
    //   388: astore_2
    //   389: goto +17 -> 406
    //   392: astore_1
    //   393: aload_1
    //   394: invokevirtual 637	java/lang/Throwable:getCause	()Ljava/lang/Throwable;
    //   397: astore_2
    //   398: aload_2
    //   399: ifnull +5 -> 404
    //   402: aload_2
    //   403: athrow
    //   404: aload_1
    //   405: athrow
    //   406: iconst_4
    //   407: bipush 42
    //   409: ldc_w 702
    //   412: invokestatic 643	o/O:ˋ	(IIC)Ljava/lang/Object;
    //   415: checkcast 645	java/lang/Class
    //   418: ldc_w 646
    //   421: iconst_2
    //   422: anewarray 645	java/lang/Class
    //   425: dup
    //   426: iconst_0
    //   427: ldc_w 526
    //   430: aastore
    //   431: dup
    //   432: iconst_1
    //   433: ldc_w 526
    //   436: aastore
    //   437: invokevirtual 650	java/lang/Class:getMethod	(Ljava/lang/String;[Ljava/lang/Class;)Ljava/lang/reflect/Method;
    //   440: aconst_null
    //   441: iconst_2
    //   442: anewarray 704	java/lang/Object
    //   445: dup
    //   446: iconst_0
    //   447: aload_1
    //   448: aastore
    //   449: dup
    //   450: iconst_1
    //   451: aload_2
    //   452: aastore
    //   453: invokevirtual 656	java/lang/reflect/Method:invoke	(Ljava/lang/Object;[Ljava/lang/Object;)Ljava/lang/Object;
    //   456: pop
    //   457: goto -354 -> 103
    //   460: aload_0
    //   461: invokevirtual 485	o/JA:ʼ	()Lo/Ib;
    //   464: checkcast 487	o/Jt
    //   467: invokeinterface 490 1 0
    //   472: astore 4
    //   474: aload_0
    //   475: getfield 521	o/JA:ॱ	Lo/wh;
    //   478: astore_2
    //   479: aload_2
    //   480: ifnull +6 -> 486
    //   483: goto -318 -> 165
    //   486: goto +70 -> 556
    //   489: getstatic 41	o/JA:ͺ	I
    //   492: istore_3
    //   493: iload_3
    //   494: bipush 79
    //   496: iadd
    //   497: istore_3
    //   498: iload_3
    //   499: sipush 128
    //   502: irem
    //   503: putstatic 39	o/JA:ˊॱ	I
    //   506: iload_3
    //   507: iconst_2
    //   508: irem
    //   509: ifeq +6 -> 515
    //   512: goto -188 -> 324
    //   515: goto -191 -> 324
    //   518: iload_3
    //   519: lookupswitch	default:+25->544, 42:+-489->30, 54:+-210->309
    //   544: goto -514 -> 30
    //   547: bipush 75
    //   549: istore_3
    //   550: goto -505 -> 45
    //   553: goto -550 -> 3
    //   556: ldc_w 716
    //   559: astore_2
    //   560: goto -374 -> 186
    //   563: iconst_3
    //   564: iconst_5
    //   565: idiv
    //   566: istore_3
    //   567: return
    // Local variable table:
    //   start	length	slot	name	signature
    //   0	568	0	this	JA
    //   0	568	1	paramWy	wy
    //   0	568	2	paramWf	wf
    //   9	558	3	i	int
    //   140	333	4	localObject	Object
    // Exception table:
    //   from	to	target	type
    //   324	331	153	java/lang/Exception
    //   489	493	153	java/lang/Exception
    //   498	506	183	java/lang/Exception
    //   257	308	243	finally
    //   406	457	392	finally
  }
  
  public void ˏ()
  {
    break label42;
    Crashlytics.ˊ().ᐝ();
    break label45;
    int i;
    label42:
    for (;;)
    {
      i = ˊॱ + 77;
      ͺ = i % 128;
      if (i % 2 != 0) {
        break;
      }
      break;
    }
    try
    {
      label45:
      i = ˊॱ;
      i += 39;
      ͺ = i % 128;
      if (i % 2 == 0) {
        return;
      }
      return;
    }
    catch (Exception localException)
    {
      throw localException;
    }
  }
  
  /* Error */
  public void ॱ()
  {
    // Byte code:
    //   0: goto +774 -> 774
    //   3: bipush 15
    //   5: istore_1
    //   6: goto +485 -> 491
    //   9: iload_1
    //   10: tableswitch	default:+22->32, 0:+404->414, 1:+706->716
    //   32: goto +382 -> 414
    //   35: new 690	java/lang/StringBuilder
    //   38: dup
    //   39: invokespecial 691	java/lang/StringBuilder:<init>	()V
    //   42: astore_2
    //   43: aload_2
    //   44: new 690	java/lang/StringBuilder
    //   47: dup
    //   48: invokespecial 691	java/lang/StringBuilder:<init>	()V
    //   51: bipush 103
    //   53: sipush 2480
    //   56: bipush 14
    //   58: invokestatic 524	o/JA:ˋ	(ICI)Ljava/lang/String;
    //   61: invokevirtual 529	java/lang/String:intern	()Ljava/lang/String;
    //   64: invokevirtual 695	java/lang/StringBuilder:append	(Ljava/lang/String;)Ljava/lang/StringBuilder;
    //   67: aload 5
    //   69: invokeinterface 728 1 0
    //   74: invokevirtual 695	java/lang/StringBuilder:append	(Ljava/lang/String;)Ljava/lang/StringBuilder;
    //   77: aload_3
    //   78: invokevirtual 695	java/lang/StringBuilder:append	(Ljava/lang/String;)Ljava/lang/StringBuilder;
    //   81: invokevirtual 701	java/lang/StringBuilder:toString	()Ljava/lang/String;
    //   84: invokevirtual 695	java/lang/StringBuilder:append	(Ljava/lang/String;)Ljava/lang/StringBuilder;
    //   87: pop
    //   88: aload_2
    //   89: new 690	java/lang/StringBuilder
    //   92: dup
    //   93: invokespecial 691	java/lang/StringBuilder:<init>	()V
    //   96: bipush 118
    //   98: iconst_0
    //   99: bipush 11
    //   101: invokestatic 524	o/JA:ˋ	(ICI)Ljava/lang/String;
    //   104: invokevirtual 529	java/lang/String:intern	()Ljava/lang/String;
    //   107: invokevirtual 695	java/lang/StringBuilder:append	(Ljava/lang/String;)Ljava/lang/StringBuilder;
    //   110: aload 4
    //   112: invokevirtual 733	o/HQ:ˊˋ	()Ljava/lang/String;
    //   115: invokevirtual 695	java/lang/StringBuilder:append	(Ljava/lang/String;)Ljava/lang/StringBuilder;
    //   118: aload_3
    //   119: invokevirtual 695	java/lang/StringBuilder:append	(Ljava/lang/String;)Ljava/lang/StringBuilder;
    //   122: invokevirtual 701	java/lang/StringBuilder:toString	()Ljava/lang/String;
    //   125: invokevirtual 695	java/lang/StringBuilder:append	(Ljava/lang/String;)Ljava/lang/StringBuilder;
    //   128: pop
    //   129: aload_2
    //   130: new 690	java/lang/StringBuilder
    //   133: dup
    //   134: invokespecial 691	java/lang/StringBuilder:<init>	()V
    //   137: sipush 129
    //   140: sipush 23247
    //   143: bipush 11
    //   145: invokestatic 524	o/JA:ˋ	(ICI)Ljava/lang/String;
    //   148: invokevirtual 529	java/lang/String:intern	()Ljava/lang/String;
    //   151: invokevirtual 695	java/lang/StringBuilder:append	(Ljava/lang/String;)Ljava/lang/StringBuilder;
    //   154: aload 4
    //   156: invokevirtual 735	o/HQ:ˊ	()Ljava/lang/String;
    //   159: invokevirtual 695	java/lang/StringBuilder:append	(Ljava/lang/String;)Ljava/lang/StringBuilder;
    //   162: aload_3
    //   163: invokevirtual 695	java/lang/StringBuilder:append	(Ljava/lang/String;)Ljava/lang/StringBuilder;
    //   166: invokevirtual 701	java/lang/StringBuilder:toString	()Ljava/lang/String;
    //   169: invokevirtual 695	java/lang/StringBuilder:append	(Ljava/lang/String;)Ljava/lang/StringBuilder;
    //   172: pop
    //   173: aload_2
    //   174: new 690	java/lang/StringBuilder
    //   177: dup
    //   178: invokespecial 691	java/lang/StringBuilder:<init>	()V
    //   181: sipush 140
    //   184: sipush 4480
    //   187: bipush 14
    //   189: invokestatic 524	o/JA:ˋ	(ICI)Ljava/lang/String;
    //   192: invokevirtual 529	java/lang/String:intern	()Ljava/lang/String;
    //   195: invokevirtual 695	java/lang/StringBuilder:append	(Ljava/lang/String;)Ljava/lang/StringBuilder;
    //   198: aload 5
    //   200: invokeinterface 739 1 0
    //   205: invokevirtual 742	java/lang/StringBuilder:append	(I)Ljava/lang/StringBuilder;
    //   208: sipush 154
    //   211: ldc_w 743
    //   214: iconst_3
    //   215: invokestatic 524	o/JA:ˋ	(ICI)Ljava/lang/String;
    //   218: invokevirtual 529	java/lang/String:intern	()Ljava/lang/String;
    //   221: invokevirtual 695	java/lang/StringBuilder:append	(Ljava/lang/String;)Ljava/lang/StringBuilder;
    //   224: aload 5
    //   226: invokeinterface 746 1 0
    //   231: invokevirtual 742	java/lang/StringBuilder:append	(I)Ljava/lang/StringBuilder;
    //   234: aload_3
    //   235: invokevirtual 695	java/lang/StringBuilder:append	(Ljava/lang/String;)Ljava/lang/StringBuilder;
    //   238: invokevirtual 701	java/lang/StringBuilder:toString	()Ljava/lang/String;
    //   241: invokevirtual 695	java/lang/StringBuilder:append	(Ljava/lang/String;)Ljava/lang/StringBuilder;
    //   244: pop
    //   245: aload_2
    //   246: new 690	java/lang/StringBuilder
    //   249: dup
    //   250: invokespecial 691	java/lang/StringBuilder:<init>	()V
    //   253: sipush 157
    //   256: iconst_0
    //   257: bipush 20
    //   259: invokestatic 524	o/JA:ˋ	(ICI)Ljava/lang/String;
    //   262: invokevirtual 529	java/lang/String:intern	()Ljava/lang/String;
    //   265: invokevirtual 695	java/lang/StringBuilder:append	(Ljava/lang/String;)Ljava/lang/StringBuilder;
    //   268: aload 4
    //   270: invokevirtual 748	o/HQ:ͺ	()I
    //   273: invokevirtual 742	java/lang/StringBuilder:append	(I)Ljava/lang/StringBuilder;
    //   276: sipush 154
    //   279: ldc_w 743
    //   282: iconst_3
    //   283: invokestatic 524	o/JA:ˋ	(ICI)Ljava/lang/String;
    //   286: invokevirtual 529	java/lang/String:intern	()Ljava/lang/String;
    //   289: invokevirtual 695	java/lang/StringBuilder:append	(Ljava/lang/String;)Ljava/lang/StringBuilder;
    //   292: aload 4
    //   294: invokevirtual 750	o/HQ:ˊॱ	()I
    //   297: invokevirtual 742	java/lang/StringBuilder:append	(I)Ljava/lang/StringBuilder;
    //   300: aload_3
    //   301: invokevirtual 695	java/lang/StringBuilder:append	(Ljava/lang/String;)Ljava/lang/StringBuilder;
    //   304: invokevirtual 701	java/lang/StringBuilder:toString	()Ljava/lang/String;
    //   307: invokevirtual 695	java/lang/StringBuilder:append	(Ljava/lang/String;)Ljava/lang/StringBuilder;
    //   310: pop
    //   311: aload_2
    //   312: new 690	java/lang/StringBuilder
    //   315: dup
    //   316: invokespecial 691	java/lang/StringBuilder:<init>	()V
    //   319: sipush 177
    //   322: iconst_0
    //   323: bipush 35
    //   325: invokestatic 524	o/JA:ˋ	(ICI)Ljava/lang/String;
    //   328: invokevirtual 529	java/lang/String:intern	()Ljava/lang/String;
    //   331: invokevirtual 695	java/lang/StringBuilder:append	(Ljava/lang/String;)Ljava/lang/StringBuilder;
    //   334: aload 4
    //   336: invokevirtual 753	o/HQ:ˋॱ	()D
    //   339: invokevirtual 756	java/lang/StringBuilder:append	(D)Ljava/lang/StringBuilder;
    //   342: aload_3
    //   343: invokevirtual 695	java/lang/StringBuilder:append	(Ljava/lang/String;)Ljava/lang/StringBuilder;
    //   346: invokevirtual 701	java/lang/StringBuilder:toString	()Ljava/lang/String;
    //   349: invokevirtual 695	java/lang/StringBuilder:append	(Ljava/lang/String;)Ljava/lang/StringBuilder;
    //   352: pop
    //   353: aload_0
    //   354: invokevirtual 575	o/JA:ʽ	()Lo/Iu$if;
    //   357: checkcast 577	o/JB$If
    //   360: astore_3
    //   361: bipush 22
    //   363: iconst_0
    //   364: bipush 12
    //   366: invokestatic 524	o/JA:ˋ	(ICI)Ljava/lang/String;
    //   369: invokevirtual 529	java/lang/String:intern	()Ljava/lang/String;
    //   372: astore 4
    //   374: aload_2
    //   375: invokevirtual 701	java/lang/StringBuilder:toString	()Ljava/lang/String;
    //   378: astore_2
    //   379: aload_2
    //   380: sipush 212
    //   383: ldc_w 757
    //   386: bipush 24
    //   388: invokestatic 524	o/JA:ˋ	(ICI)Ljava/lang/String;
    //   391: invokevirtual 529	java/lang/String:intern	()Ljava/lang/String;
    //   394: invokestatic 759	o/vq:ˋ	(Ljava/lang/Object;Ljava/lang/String;)V
    //   397: aload_3
    //   398: aload 4
    //   400: aload_2
    //   401: invokeinterface 762 3 0
    //   406: goto +123 -> 529
    //   409: return
    //   410: return
    //   411: astore_2
    //   412: aload_2
    //   413: athrow
    //   414: aload_0
    //   415: invokevirtual 575	o/JA:ʽ	()Lo/Iu$if;
    //   418: checkcast 577	o/JB$If
    //   421: bipush 22
    //   423: iconst_0
    //   424: bipush 12
    //   426: invokestatic 524	o/JA:ˋ	(ICI)Ljava/lang/String;
    //   429: invokevirtual 529	java/lang/String:intern	()Ljava/lang/String;
    //   432: bipush 69
    //   434: iconst_0
    //   435: bipush 34
    //   437: invokestatic 524	o/JA:ˋ	(ICI)Ljava/lang/String;
    //   440: invokevirtual 529	java/lang/String:intern	()Ljava/lang/String;
    //   443: invokeinterface 762 3 0
    //   448: goto -38 -> 410
    //   451: aload_0
    //   452: invokevirtual 575	o/JA:ʽ	()Lo/Iu$if;
    //   455: checkcast 577	o/JB$If
    //   458: bipush 22
    //   460: iconst_0
    //   461: bipush 12
    //   463: invokestatic 524	o/JA:ˋ	(ICI)Ljava/lang/String;
    //   466: invokevirtual 529	java/lang/String:intern	()Ljava/lang/String;
    //   469: bipush 34
    //   471: iconst_0
    //   472: bipush 35
    //   474: invokestatic 524	o/JA:ˋ	(ICI)Ljava/lang/String;
    //   477: invokevirtual 529	java/lang/String:intern	()Ljava/lang/String;
    //   480: invokeinterface 762 3 0
    //   485: return
    //   486: iconst_0
    //   487: istore_1
    //   488: goto -479 -> 9
    //   491: iload_1
    //   492: lookupswitch	default:+28->520, 15:+192->684, 80:+-457->35
    //   520: goto -485 -> 35
    //   523: bipush 80
    //   525: istore_1
    //   526: goto -35 -> 491
    //   529: getstatic 39	o/JA:ˊॱ	I
    //   532: bipush 19
    //   534: iadd
    //   535: istore_1
    //   536: iload_1
    //   537: sipush 128
    //   540: irem
    //   541: putstatic 41	o/JA:ͺ	I
    //   544: iload_1
    //   545: iconst_2
    //   546: irem
    //   547: ifne +6 -> 553
    //   550: goto +221 -> 771
    //   553: goto -144 -> 409
    //   556: bipush 117
    //   558: iconst_0
    //   559: iconst_1
    //   560: invokestatic 524	o/JA:ˋ	(ICI)Ljava/lang/String;
    //   563: invokevirtual 529	java/lang/String:intern	()Ljava/lang/String;
    //   566: astore_3
    //   567: goto +17 -> 584
    //   570: astore_2
    //   571: aload_2
    //   572: invokevirtual 637	java/lang/Throwable:getCause	()Ljava/lang/Throwable;
    //   575: astore_3
    //   576: aload_3
    //   577: ifnull +5 -> 582
    //   580: aload_3
    //   581: athrow
    //   582: aload_2
    //   583: athrow
    //   584: iconst_4
    //   585: sipush 267
    //   588: sipush 14788
    //   591: invokestatic 643	o/O:ˋ	(IIC)Ljava/lang/Object;
    //   594: checkcast 645	java/lang/Class
    //   597: ldc_w 763
    //   600: aconst_null
    //   601: invokevirtual 650	java/lang/Class:getMethod	(Ljava/lang/String;[Ljava/lang/Class;)Ljava/lang/reflect/Method;
    //   604: aconst_null
    //   605: aconst_null
    //   606: invokevirtual 656	java/lang/reflect/Method:invoke	(Ljava/lang/Object;[Ljava/lang/Object;)Ljava/lang/Object;
    //   609: astore_2
    //   610: aload_2
    //   611: iconst_0
    //   612: ldc_w 764
    //   615: bipush 22
    //   617: invokestatic 524	o/JA:ˋ	(ICI)Ljava/lang/String;
    //   620: invokevirtual 529	java/lang/String:intern	()Ljava/lang/String;
    //   623: invokestatic 759	o/vq:ˋ	(Ljava/lang/Object;Ljava/lang/String;)V
    //   626: goto +17 -> 643
    //   629: astore_2
    //   630: aload_2
    //   631: invokevirtual 637	java/lang/Throwable:getCause	()Ljava/lang/Throwable;
    //   634: astore_3
    //   635: aload_3
    //   636: ifnull +5 -> 641
    //   639: aload_3
    //   640: athrow
    //   641: aload_2
    //   642: athrow
    //   643: iconst_4
    //   644: sipush 267
    //   647: sipush 14788
    //   650: invokestatic 643	o/O:ˋ	(IIC)Ljava/lang/Object;
    //   653: checkcast 645	java/lang/Class
    //   656: ldc_w 766
    //   659: aconst_null
    //   660: invokevirtual 650	java/lang/Class:getMethod	(Ljava/lang/String;[Ljava/lang/Class;)Ljava/lang/reflect/Method;
    //   663: aload_2
    //   664: aconst_null
    //   665: invokevirtual 656	java/lang/reflect/Method:invoke	(Ljava/lang/Object;[Ljava/lang/Object;)Ljava/lang/Object;
    //   668: checkcast 730	o/HQ
    //   671: astore 4
    //   673: aload 4
    //   675: ifnonnull +6 -> 681
    //   678: goto -227 -> 451
    //   681: goto +72 -> 753
    //   684: getstatic 39	o/JA:ˊॱ	I
    //   687: bipush 17
    //   689: iadd
    //   690: istore_1
    //   691: iload_1
    //   692: sipush 128
    //   695: irem
    //   696: putstatic 41	o/JA:ͺ	I
    //   699: iload_1
    //   700: iconst_2
    //   701: irem
    //   702: ifne +6 -> 708
    //   705: goto +6 -> 711
    //   708: goto -222 -> 486
    //   711: iconst_1
    //   712: istore_1
    //   713: goto -704 -> 9
    //   716: aload_0
    //   717: invokevirtual 575	o/JA:ʽ	()Lo/Iu$if;
    //   720: checkcast 577	o/JB$If
    //   723: bipush 37
    //   725: iconst_0
    //   726: bipush 92
    //   728: invokestatic 524	o/JA:ˋ	(ICI)Ljava/lang/String;
    //   731: invokevirtual 529	java/lang/String:intern	()Ljava/lang/String;
    //   734: bipush 38
    //   736: iconst_0
    //   737: bipush 24
    //   739: invokestatic 524	o/JA:ˋ	(ICI)Ljava/lang/String;
    //   742: invokevirtual 529	java/lang/String:intern	()Ljava/lang/String;
    //   745: invokeinterface 762 3 0
    //   750: goto -340 -> 410
    //   753: aload 4
    //   755: invokevirtual 769	o/HQ:ˎ	()Lcom/insidesecure/hce/MatrixHCECard;
    //   758: astore 5
    //   760: aload 5
    //   762: ifnonnull +6 -> 768
    //   765: goto -762 -> 3
    //   768: goto -245 -> 523
    //   771: goto -362 -> 409
    //   774: goto -218 -> 556
    // Local variable table:
    //   start	length	slot	name	signature
    //   0	777	0	this	JA
    //   5	708	1	i	int
    //   42	359	2	localObject1	Object
    //   411	2	2	localException	Exception
    //   570	13	2	localObject2	Object
    //   609	2	2	localObject3	Object
    //   629	35	2	localObject4	Object
    //   77	563	3	localObject5	Object
    //   110	644	4	localObject6	Object
    //   67	694	5	localMatrixHCECard	com.insidesecure.hce.MatrixHCECard
    // Exception table:
    //   from	to	target	type
    //   753	760	411	java/lang/Exception
    //   584	610	570	finally
    //   643	673	629	finally
  }
  
  public boolean ॱॱ()
  {
    break label48;
    int i = ͺ + 29;
    ˊॱ = i % 128;
    if (i % 2 == 0) {}
    for (;;)
    {
      try
      {
        vq.ˎ();
        continue;
        i = 1;
        break label87;
        Object localObject;
        return localObject.ˊ();
      }
      catch (Exception localException1)
      {
        label48:
        throw localException1;
      }
      i = 0;
      break label87;
      break label60;
      continue;
      for (;;)
      {
        break;
        try
        {
          label60:
          i = ͺ + 71;
          ˊॱ = i % 128;
          if (i % 2 != 0) {}
        }
        catch (Exception localException2)
        {
          label87:
          throw localException2;
        }
      }
      switch (i)
      {
      }
      continue;
      wh localWh = this.ॱ;
      if (localWh == null) {}
    }
  }
  
  static final class If
    implements wk.ˊ
  {
    If(JA paramJA) {}
    
    public final void ॱ(wy paramWy, wf paramWf)
    {
      this.ˏ.ˎ(paramWy, paramWf);
    }
  }
  
  static final class if
    implements wh.ˋ
  {
    private static int ˎ = 1;
    private static long ˏ = -7859591040169922512L;
    private static int ॱ = 0;
    
    /* Error */
    if(JA paramJA, vv.If paramIf)
    {
      // Byte code:
      //   0: goto +6 -> 6
      //   3: astore_1
      //   4: aload_1
      //   5: athrow
      //   6: aload_0
      //   7: aload_1
      //   8: putfield 40	o/JA$if:ˋ	Lo/JA;
      //   11: aload_0
      //   12: aload_2
      //   13: putfield 42	o/JA$if:ˊ	Lo/vv$If;
      //   16: aload_0
      //   17: invokespecial 44	java/lang/Object:<init>	()V
      //   20: return
      // Local variable table:
      //   start	length	slot	name	signature
      //   0	21	0	this	if
      //   0	21	1	paramJA	JA
      //   0	21	2	paramIf	vv.If
      // Exception table:
      //   from	to	target	type
      //   6	11	3	java/lang/Exception
      //   11	20	3	java/lang/Exception
    }
    
    private static String ˏ(char[] paramArrayOfChar)
    {
      int j;
      label41:
      int i;
      switch (j)
      {
      default: 
        break;
      case 43: 
        for (;;)
        {
          break label230;
          if (i >= paramArrayOfChar.length)
          {
            break label113;
            paramArrayOfChar = new String(paramArrayOfChar, 4, paramArrayOfChar.length - 4);
          }
          try
          {
            i = ˎ + 87;
            ॱ = i % 128;
            if (i % 2 != 0) {
              break label233;
            }
            break label148;
            paramArrayOfChar = oL.ˋ(ˏ, paramArrayOfChar);
            i = 4;
            break label41;
            j = 48;
            break;
            label113:
            j = 43;
          }
          catch (Exception paramArrayOfChar)
          {
            label119:
            label148:
            throw paramArrayOfChar;
          }
          try
          {
            j = ˎ;
            j += 19;
            ॱ = j % 128;
            if (j % 2 != 0) {}
          }
          catch (Exception paramArrayOfChar)
          {
            throw paramArrayOfChar;
          }
        }
        i = 86;
        break label169;
        label160:
        i = 77 / 0;
        return paramArrayOfChar;
        return paramArrayOfChar;
      }
      for (;;)
      {
        label169:
        switch (i)
        {
        }
        break label160;
        paramArrayOfChar[i] = ((char)(int)(paramArrayOfChar[i] ^ paramArrayOfChar[(i % 4)] ^ (i - 4) * ˏ));
        i += 1;
        break label119;
        label230:
        break;
        label233:
        i = 70;
      }
    }
    
    /* Error */
    public final void ˊ(String paramString1, String paramString2, wf paramWf)
    {
      // Byte code:
      //   0: goto +6 -> 6
      //   3: astore_1
      //   4: aload_1
      //   5: athrow
      //   6: goto +37 -> 43
      //   9: getstatic 29	o/JA$if:ˎ	I
      //   12: bipush 117
      //   14: iadd
      //   15: istore 4
      //   17: iload 4
      //   19: sipush 128
      //   22: irem
      //   23: putstatic 27	o/JA$if:ॱ	I
      //   26: iload 4
      //   28: iconst_2
      //   29: irem
      //   30: ifeq +6 -> 36
      //   33: goto +213 -> 246
      //   36: return
      //   37: astore_1
      //   38: aload_1
      //   39: athrow
      //   40: goto +46 -> 86
      //   43: aload_0
      //   44: getfield 40	o/JA$if:ˋ	Lo/JA;
      //   47: invokevirtual 60	o/JA:ॱॱ	()Z
      //   50: ifeq +6 -> 56
      //   53: goto +36 -> 89
      //   56: goto +191 -> 247
      //   59: getstatic 27	o/JA$if:ॱ	I
      //   62: bipush 73
      //   64: iadd
      //   65: istore 4
      //   67: iload 4
      //   69: sipush 128
      //   72: irem
      //   73: putstatic 29	o/JA$if:ˎ	I
      //   76: iload 4
      //   78: iconst_2
      //   79: irem
      //   80: ifne +6 -> 86
      //   83: goto -43 -> 40
      //   86: goto +161 -> 247
      //   89: aload_0
      //   90: getfield 40	o/JA$if:ˋ	Lo/JA;
      //   93: astore_2
      //   94: aload_2
      //   95: invokestatic 63	o/JA:ˋ	(Lo/JA;)Lo/Jt;
      //   98: astore_2
      //   99: aload_2
      //   100: invokeinterface 68 1 0
      //   105: astore_2
      //   106: new 70	java/lang/StringBuilder
      //   109: dup
      //   110: invokespecial 71	java/lang/StringBuilder:<init>	()V
      //   113: astore_3
      //   114: bipush 11
      //   116: newarray char
      //   118: dup
      //   119: iconst_0
      //   120: ldc 72
      //   122: castore
      //   123: dup
      //   124: iconst_1
      //   125: ldc 73
      //   127: castore
      //   128: dup
      //   129: iconst_2
      //   130: ldc 74
      //   132: castore
      //   133: dup
      //   134: iconst_3
      //   135: ldc 75
      //   137: castore
      //   138: dup
      //   139: iconst_4
      //   140: ldc 76
      //   142: castore
      //   143: dup
      //   144: iconst_5
      //   145: ldc 77
      //   147: castore
      //   148: dup
      //   149: bipush 6
      //   151: ldc 78
      //   153: castore
      //   154: dup
      //   155: bipush 7
      //   157: ldc 79
      //   159: castore
      //   160: dup
      //   161: bipush 8
      //   163: ldc 80
      //   165: castore
      //   166: dup
      //   167: bipush 9
      //   169: ldc 81
      //   171: castore
      //   172: dup
      //   173: bipush 10
      //   175: ldc 82
      //   177: castore
      //   178: invokestatic 84	o/JA$if:ˏ	([C)Ljava/lang/String;
      //   181: astore 5
      //   183: aload_2
      //   184: aload_3
      //   185: aload 5
      //   187: invokevirtual 88	java/lang/String:intern	()Ljava/lang/String;
      //   190: invokevirtual 92	java/lang/StringBuilder:append	(Ljava/lang/String;)Ljava/lang/StringBuilder;
      //   193: aload_1
      //   194: invokevirtual 92	java/lang/StringBuilder:append	(Ljava/lang/String;)Ljava/lang/StringBuilder;
      //   197: invokevirtual 95	java/lang/StringBuilder:toString	()Ljava/lang/String;
      //   200: invokeinterface 100 2 0
      //   205: invokestatic 105	o/sB:ˋ	()Lo/sy;
      //   208: invokevirtual 110	o/st:ˊ	(Lo/sy;)Lo/st;
      //   211: invokestatic 114	o/ur:ॱ	()Lo/sy;
      //   214: invokevirtual 116	o/st:ˎ	(Lo/sy;)Lo/st;
      //   217: new 13	o/JA$if$2
      //   220: dup
      //   221: aload_0
      //   222: invokespecial 119	o/JA$if$2:<init>	(Lo/JA$if;)V
      //   225: checkcast 121	o/sW
      //   228: new 15	o/JA$if$4
      //   231: dup
      //   232: aload_0
      //   233: invokespecial 122	o/JA$if$4:<init>	(Lo/JA$if;)V
      //   236: checkcast 121	o/sW
      //   239: invokevirtual 125	o/st:ˎ	(Lo/sW;Lo/sW;)Lo/sH;
      //   242: pop
      //   243: goto -184 -> 59
      //   246: return
      //   247: goto -238 -> 9
      // Local variable table:
      //   start	length	slot	name	signature
      //   0	250	0	this	if
      //   0	250	1	paramString1	String
      //   0	250	2	paramString2	String
      //   0	250	3	paramWf	wf
      //   15	65	4	i	int
      //   181	5	5	str	String
      // Exception table:
      //   from	to	target	type
      //   94	99	3	java/lang/Exception
      //   89	94	37	java/lang/Exception
      //   94	99	37	java/lang/Exception
      //   99	114	37	java/lang/Exception
      //   114	183	37	java/lang/Exception
      //   183	243	37	java/lang/Exception
    }
  }
}
