package o;

import android.content.res.Resources;
import android.databinding.ViewDataBinding;
import android.databinding.ViewDataBinding.If;
import android.util.SparseIntArray;
import android.view.View;
import android.widget.Button;
import android.widget.ImageView;
import android.widget.LinearLayout;
import android.widget.ProgressBar;
import android.widget.RelativeLayout;
import android.widget.Space;
import android.widget.TextView;

public class JF
  extends ViewDataBinding
{
  private static final SparseIntArray ʽॱ;
  private static char[] ˊˋ;
  private static byte ˋˊ;
  private static int ˋˋ = 0;
  private static char ˋᐝ;
  private static int ˌ = 1;
  private static final ViewDataBinding.If ॱˋ;
  public final TextView ʻ;
  public final ImageView ʻॱ;
  public final TextView ʼ;
  private final LinearLayout ʼॱ;
  public final Lf ʽ;
  private final TextView ʾ;
  private final RelativeLayout ʿ;
  private boolean ˈ;
  private long ˉ = -1L;
  public final IY ˊ;
  private String ˊˊ;
  public final RelativeLayout ˊॱ;
  private boolean ˊᐝ;
  public final ProgressBar ˋॱ;
  public final Space ˎ;
  public final TextView ˏॱ;
  public final IX ͺ;
  public final Button ॱ;
  public final Lf ॱˊ;
  public final у ॱˎ;
  public final TextView ॱॱ;
  public final ImageView ॱᐝ;
  public final ImageView ᐝ;
  public final ImageView ᐝॱ;
  
  /* Error */
  static
  {
    // Byte code:
    //   0: iconst_0
    //   1: putstatic 61	o/JF:ˋˋ	I
    //   4: iconst_1
    //   5: putstatic 63	o/JF:ˌ	I
    //   8: invokestatic 65	o/JF:ͺ	()V
    //   11: invokestatic 67	o/JF:ॱˊ	()V
    //   14: aconst_null
    //   15: putstatic 69	o/JF:ॱˋ	Landroid/databinding/ViewDataBinding$If;
    //   18: new 71	android/util/SparseIntArray
    //   21: dup
    //   22: invokespecial 74	android/util/SparseIntArray:<init>	()V
    //   25: putstatic 76	o/JF:ʽॱ	Landroid/util/SparseIntArray;
    //   28: getstatic 76	o/JF:ʽॱ	Landroid/util/SparseIntArray;
    //   31: ldc 77
    //   33: bipush 14
    //   35: invokevirtual 81	android/util/SparseIntArray:put	(II)V
    //   38: getstatic 76	o/JF:ʽॱ	Landroid/util/SparseIntArray;
    //   41: ldc 82
    //   43: bipush 15
    //   45: invokevirtual 81	android/util/SparseIntArray:put	(II)V
    //   48: getstatic 76	o/JF:ʽॱ	Landroid/util/SparseIntArray;
    //   51: ldc 83
    //   53: bipush 16
    //   55: invokevirtual 81	android/util/SparseIntArray:put	(II)V
    //   58: getstatic 76	o/JF:ʽॱ	Landroid/util/SparseIntArray;
    //   61: ldc 84
    //   63: bipush 17
    //   65: invokevirtual 81	android/util/SparseIntArray:put	(II)V
    //   68: getstatic 76	o/JF:ʽॱ	Landroid/util/SparseIntArray;
    //   71: ldc 85
    //   73: bipush 18
    //   75: invokevirtual 81	android/util/SparseIntArray:put	(II)V
    //   78: getstatic 76	o/JF:ʽॱ	Landroid/util/SparseIntArray;
    //   81: ldc 86
    //   83: bipush 19
    //   85: invokevirtual 81	android/util/SparseIntArray:put	(II)V
    //   88: goto +9 -> 97
    //   91: astore_1
    //   92: aload_1
    //   93: athrow
    //   94: astore_1
    //   95: aload_1
    //   96: athrow
    //   97: getstatic 61	o/JF:ˋˋ	I
    //   100: istore_0
    //   101: iload_0
    //   102: bipush 51
    //   104: iadd
    //   105: istore_0
    //   106: iload_0
    //   107: sipush 128
    //   110: irem
    //   111: putstatic 63	o/JF:ˌ	I
    //   114: iload_0
    //   115: iconst_2
    //   116: irem
    //   117: ifne +4 -> 121
    //   120: return
    //   121: return
    // Local variable table:
    //   start	length	slot	name	signature
    //   100	17	0	i	int
    //   91	2	1	localException1	Exception
    //   94	2	1	localException2	Exception
    // Exception table:
    //   from	to	target	type
    //   0	4	91	java/lang/Exception
    //   4	8	91	java/lang/Exception
    //   8	88	91	java/lang/Exception
    //   106	114	91	java/lang/Exception
    //   97	101	94	java/lang/Exception
  }
  
  public JF(ˉ paramˉ, View paramView)
  {
    super(paramˉ, paramView, 0);
    paramˉ = ॱ(paramˉ, paramView, 20, ॱˋ, ʽॱ);
    this.ˊ = ((IY)paramˉ[4]);
    this.ˊ.setTag(null);
    this.ˎ = ((Space)paramˉ[16]);
    this.ॱ = ((Button)paramˉ[3]);
    this.ॱ.setTag(null);
    this.ʽ = ((Lf)paramˉ[10]);
    this.ʽ.setTag(null);
    this.ʼ = ((TextView)paramˉ[8]);
    this.ʼ.setTag(null);
    this.ॱॱ = ((TextView)paramˉ[5]);
    this.ॱॱ.setTag(null);
    this.ᐝ = ((ImageView)paramˉ[2]);
    this.ᐝ.setTag(null);
    this.ʻ = ((TextView)paramˉ[9]);
    this.ʻ.setTag(null);
    this.ˏॱ = ((TextView)paramˉ[6]);
    this.ˏॱ.setTag(null);
    this.ʿ = ((RelativeLayout)paramˉ[0]);
    this.ʿ.setTag(null);
    this.ʼॱ = ((LinearLayout)paramˉ[12]);
    this.ʼॱ.setTag(null);
    this.ʾ = ((TextView)paramˉ[13]);
    this.ʾ.setTag(null);
    this.ˊॱ = ((RelativeLayout)paramˉ[7]);
    this.ˊॱ.setTag(null);
    this.ͺ = ((IX)paramˉ[15]);
    this.ˋॱ = ((ProgressBar)paramˉ[19]);
    this.ॱˊ = ((Lf)paramˉ[11]);
    this.ॱˊ.setTag(null);
    this.ॱᐝ = ((ImageView)paramˉ[17]);
    this.ʻॱ = ((ImageView)paramˉ[18]);
    this.ॱˎ = ((у)paramˉ[1]);
    this.ॱˎ.setTag(null);
    this.ᐝॱ = ((ImageView)paramˉ[14]);
    ˋ(paramView);
    ˋॱ();
  }
  
  /* Error */
  private String ˊ(String paramString)
  {
    // Byte code:
    //   0: goto +447 -> 447
    //   3: aload_1
    //   4: iload_2
    //   5: aload 4
    //   7: aload 4
    //   9: arraylength
    //   10: iload_2
    //   11: isub
    //   12: iconst_1
    //   13: isub
    //   14: baload
    //   15: getstatic 182	o/JF:ˋˊ	B
    //   18: ixor
    //   19: i2b
    //   20: bastore
    //   21: iload_2
    //   22: iconst_1
    //   23: iadd
    //   24: istore_2
    //   25: goto +84 -> 109
    //   28: getstatic 61	o/JF:ˋˋ	I
    //   31: bipush 31
    //   33: iadd
    //   34: istore_3
    //   35: iload_3
    //   36: sipush 128
    //   39: irem
    //   40: putstatic 63	o/JF:ˌ	I
    //   43: iload_3
    //   44: iconst_2
    //   45: irem
    //   46: ifne +6 -> 52
    //   49: goto +258 -> 307
    //   52: goto -49 -> 3
    //   55: new 184	java/lang/String
    //   58: dup
    //   59: aload_1
    //   60: iconst_5
    //   61: newarray char
    //   63: dup
    //   64: iconst_0
    //   65: ldc -71
    //   67: castore
    //   68: dup
    //   69: iconst_1
    //   70: ldc -70
    //   72: castore
    //   73: dup
    //   74: iconst_2
    //   75: ldc -70
    //   77: castore
    //   78: dup
    //   79: iconst_3
    //   80: ldc -69
    //   82: castore
    //   83: dup
    //   84: iconst_4
    //   85: ldc -68
    //   87: castore
    //   88: iconst_5
    //   89: bipush 50
    //   91: invokestatic 191	o/JF:ˎ	([CIB)Ljava/lang/String;
    //   94: invokevirtual 195	java/lang/String:intern	()Ljava/lang/String;
    //   97: invokespecial 198	java/lang/String:<init>	([BLjava/lang/String;)V
    //   100: astore_1
    //   101: aload_1
    //   102: areturn
    //   103: bipush 25
    //   105: istore_3
    //   106: goto +29 -> 135
    //   109: getstatic 63	o/JF:ˌ	I
    //   112: iconst_1
    //   113: iadd
    //   114: istore_3
    //   115: iload_3
    //   116: sipush 128
    //   119: irem
    //   120: putstatic 61	o/JF:ˋˋ	I
    //   123: iload_3
    //   124: iconst_2
    //   125: irem
    //   126: ifeq +6 -> 132
    //   129: goto +204 -> 333
    //   132: goto +147 -> 279
    //   135: iload_3
    //   136: lookupswitch	default:+28->164, 25:+-81->55, 72:+-108->28
    //   164: goto -109 -> 55
    //   167: goto +171 -> 338
    //   170: getstatic 63	o/JF:ˌ	I
    //   173: bipush 51
    //   175: iadd
    //   176: istore_2
    //   177: iload_2
    //   178: sipush 128
    //   181: irem
    //   182: putstatic 61	o/JF:ˋˋ	I
    //   185: iload_2
    //   186: iconst_2
    //   187: irem
    //   188: ifeq +6 -> 194
    //   191: goto +168 -> 359
    //   194: aload_1
    //   195: bipush 10
    //   197: newarray char
    //   199: dup
    //   200: iconst_0
    //   201: ldc -57
    //   203: castore
    //   204: dup
    //   205: iconst_1
    //   206: ldc -56
    //   208: castore
    //   209: dup
    //   210: iconst_2
    //   211: ldc -55
    //   213: castore
    //   214: dup
    //   215: iconst_3
    //   216: ldc -54
    //   218: castore
    //   219: dup
    //   220: iconst_4
    //   221: ldc -53
    //   223: castore
    //   224: dup
    //   225: iconst_5
    //   226: ldc -53
    //   228: castore
    //   229: dup
    //   230: bipush 6
    //   232: ldc -52
    //   234: castore
    //   235: dup
    //   236: bipush 7
    //   238: ldc -51
    //   240: castore
    //   241: dup
    //   242: bipush 8
    //   244: ldc -50
    //   246: castore
    //   247: dup
    //   248: bipush 9
    //   250: ldc -49
    //   252: castore
    //   253: bipush 10
    //   255: bipush 97
    //   257: invokestatic 191	o/JF:ˎ	([CIB)Ljava/lang/String;
    //   260: invokevirtual 195	java/lang/String:intern	()Ljava/lang/String;
    //   263: invokevirtual 211	java/lang/String:getBytes	(Ljava/lang/String;)[B
    //   266: astore 4
    //   268: aload 4
    //   270: arraylength
    //   271: newarray byte
    //   273: astore_1
    //   274: iconst_0
    //   275: istore_2
    //   276: goto +62 -> 338
    //   279: iconst_1
    //   280: istore_3
    //   281: iload_3
    //   282: tableswitch	default:+22->304, 0:+162->444, 1:+-115->167
    //   304: goto +140 -> 444
    //   307: aload_1
    //   308: iload_2
    //   309: aload 4
    //   311: aload 4
    //   313: arraylength
    //   314: iload_2
    //   315: iushr
    //   316: iconst_0
    //   317: ishr
    //   318: baload
    //   319: getstatic 182	o/JF:ˋˊ	B
    //   322: ior
    //   323: i2b
    //   324: bastore
    //   325: iload_2
    //   326: bipush 80
    //   328: iadd
    //   329: istore_2
    //   330: goto -221 -> 109
    //   333: iconst_0
    //   334: istore_3
    //   335: goto -54 -> 281
    //   338: aload 4
    //   340: arraylength
    //   341: istore_3
    //   342: iload_2
    //   343: iload_3
    //   344: if_icmpge +6 -> 350
    //   347: goto +6 -> 353
    //   350: goto -247 -> 103
    //   353: bipush 72
    //   355: istore_3
    //   356: goto -221 -> 135
    //   359: aload_1
    //   360: bipush 10
    //   362: newarray char
    //   364: dup
    //   365: iconst_0
    //   366: ldc -57
    //   368: castore
    //   369: dup
    //   370: iconst_1
    //   371: ldc -56
    //   373: castore
    //   374: dup
    //   375: iconst_2
    //   376: ldc -55
    //   378: castore
    //   379: dup
    //   380: iconst_3
    //   381: ldc -54
    //   383: castore
    //   384: dup
    //   385: iconst_4
    //   386: ldc -53
    //   388: castore
    //   389: dup
    //   390: iconst_5
    //   391: ldc -53
    //   393: castore
    //   394: dup
    //   395: bipush 6
    //   397: ldc -52
    //   399: castore
    //   400: dup
    //   401: bipush 7
    //   403: ldc -51
    //   405: castore
    //   406: dup
    //   407: bipush 8
    //   409: ldc -50
    //   411: castore
    //   412: dup
    //   413: bipush 9
    //   415: ldc -49
    //   417: castore
    //   418: bipush 16
    //   420: bipush 45
    //   422: invokestatic 191	o/JF:ˎ	([CIB)Ljava/lang/String;
    //   425: invokevirtual 195	java/lang/String:intern	()Ljava/lang/String;
    //   428: invokevirtual 211	java/lang/String:getBytes	(Ljava/lang/String;)[B
    //   431: astore 4
    //   433: aload 4
    //   435: arraylength
    //   436: newarray byte
    //   438: astore_1
    //   439: iconst_1
    //   440: istore_2
    //   441: goto -103 -> 338
    //   444: goto -106 -> 338
    //   447: goto -277 -> 170
    //   450: astore_1
    //   451: new 213	java/lang/RuntimeException
    //   454: dup
    //   455: aload_1
    //   456: invokespecial 216	java/lang/RuntimeException:<init>	(Ljava/lang/Throwable;)V
    //   459: athrow
    // Local variable table:
    //   start	length	slot	name	signature
    //   0	460	0	this	JF
    //   0	460	1	paramString	String
    //   4	437	2	i	int
    //   34	322	3	j	int
    //   5	429	4	arrayOfByte	byte[]
    // Exception table:
    //   from	to	target	type
    //   3	21	450	java/io/UnsupportedEncodingException
    //   55	101	450	java/io/UnsupportedEncodingException
    //   194	274	450	java/io/UnsupportedEncodingException
    //   307	325	450	java/io/UnsupportedEncodingException
    //   338	342	450	java/io/UnsupportedEncodingException
    //   359	439	450	java/io/UnsupportedEncodingException
  }
  
  /* Error */
  private static String ˎ(char[] paramArrayOfChar, int paramInt, byte paramByte)
  {
    // Byte code:
    //   0: goto +406 -> 406
    //   3: bipush 73
    //   5: istore 4
    //   7: goto +341 -> 348
    //   10: iload 7
    //   12: iload 6
    //   14: if_icmpne +6 -> 20
    //   17: goto +498 -> 515
    //   20: goto -17 -> 3
    //   23: iload 7
    //   25: iload 9
    //   27: iload 5
    //   29: invokestatic 222	o/oO:ˏ	(III)I
    //   32: istore 4
    //   34: iload 6
    //   36: iload 8
    //   38: iload 5
    //   40: invokestatic 222	o/oO:ˏ	(III)I
    //   43: istore 6
    //   45: aload 11
    //   47: iload_3
    //   48: aload 10
    //   50: iload 4
    //   52: caload
    //   53: castore
    //   54: aload 11
    //   56: iload_3
    //   57: iconst_1
    //   58: iadd
    //   59: aload 10
    //   61: iload 6
    //   63: caload
    //   64: castore
    //   65: goto +188 -> 253
    //   68: iload_3
    //   69: lookupswitch	default:+27->96, 35:+203->272, 87:+63->132
    //   96: goto +36 -> 132
    //   99: getstatic 63	o/JF:ˌ	I
    //   102: bipush 7
    //   104: iadd
    //   105: istore 4
    //   107: iload 4
    //   109: sipush 128
    //   112: irem
    //   113: putstatic 61	o/JF:ˋˋ	I
    //   116: iload 4
    //   118: iconst_2
    //   119: irem
    //   120: ifeq +6 -> 126
    //   123: goto +127 -> 250
    //   126: goto +363 -> 489
    //   129: astore_0
    //   130: aload_0
    //   131: athrow
    //   132: iconst_0
    //   133: istore_3
    //   134: goto +355 -> 489
    //   137: aload 11
    //   139: iload_3
    //   140: iload 6
    //   142: iload_2
    //   143: isub
    //   144: i2c
    //   145: castore
    //   146: aload 11
    //   148: iload_3
    //   149: iconst_1
    //   150: iadd
    //   151: iload 4
    //   153: iload_2
    //   154: isub
    //   155: i2c
    //   156: castore
    //   157: getstatic 61	o/JF:ˋˋ	I
    //   160: bipush 51
    //   162: iadd
    //   163: istore 4
    //   165: iload 4
    //   167: sipush 128
    //   170: irem
    //   171: putstatic 63	o/JF:ˌ	I
    //   174: iload 4
    //   176: iconst_2
    //   177: irem
    //   178: ifne +6 -> 184
    //   181: goto +325 -> 506
    //   184: goto +76 -> 260
    //   187: iload 7
    //   189: iload 5
    //   191: invokestatic 225	o/oO:ˊ	(II)I
    //   194: istore 4
    //   196: iload 6
    //   198: iload 5
    //   200: invokestatic 225	o/oO:ˊ	(II)I
    //   203: istore 6
    //   205: iload 4
    //   207: iload 8
    //   209: iload 5
    //   211: invokestatic 222	o/oO:ˏ	(III)I
    //   214: istore 4
    //   216: iload 6
    //   218: iload 9
    //   220: iload 5
    //   222: invokestatic 222	o/oO:ˏ	(III)I
    //   225: istore 6
    //   227: aload 11
    //   229: iload_3
    //   230: aload 10
    //   232: iload 4
    //   234: caload
    //   235: castore
    //   236: aload 11
    //   238: iload_3
    //   239: iconst_1
    //   240: iadd
    //   241: aload 10
    //   243: iload 6
    //   245: caload
    //   246: castore
    //   247: goto +6 -> 253
    //   250: goto -124 -> 126
    //   253: iload_3
    //   254: iconst_2
    //   255: iadd
    //   256: istore_3
    //   257: goto -158 -> 99
    //   260: goto -7 -> 253
    //   263: bipush 87
    //   265: istore_3
    //   266: goto -198 -> 68
    //   269: astore_0
    //   270: aload_0
    //   271: athrow
    //   272: new 184	java/lang/String
    //   275: dup
    //   276: aload 11
    //   278: invokespecial 228	java/lang/String:<init>	([C)V
    //   281: areturn
    //   282: aload_0
    //   283: iload_3
    //   284: caload
    //   285: istore 6
    //   287: aload_0
    //   288: iload_3
    //   289: iconst_1
    //   290: iadd
    //   291: caload
    //   292: istore 4
    //   294: iload 6
    //   296: iload 4
    //   298: if_icmpne +6 -> 304
    //   301: goto -164 -> 137
    //   304: goto +218 -> 522
    //   307: iload_1
    //   308: iconst_1
    //   309: if_icmple +6 -> 315
    //   312: goto -49 -> 263
    //   315: goto +185 -> 500
    //   318: getstatic 61	o/JF:ˋˋ	I
    //   321: bipush 117
    //   323: iadd
    //   324: istore 4
    //   326: iload 4
    //   328: sipush 128
    //   331: irem
    //   332: putstatic 63	o/JF:ˌ	I
    //   335: iload 4
    //   337: iconst_2
    //   338: irem
    //   339: ifne +6 -> 345
    //   342: goto +167 -> 509
    //   345: goto -158 -> 187
    //   348: iload 4
    //   350: lookupswitch	default:+26->376, 27:+59->409, 73:+-327->23
    //   376: goto +33 -> 409
    //   379: getstatic 230	o/JF:ˊˋ	[C
    //   382: astore 10
    //   384: getstatic 232	o/JF:ˋᐝ	C
    //   387: istore 5
    //   389: iload_1
    //   390: newarray char
    //   392: astore 11
    //   394: iload_1
    //   395: iconst_2
    //   396: irem
    //   397: ifeq +6 -> 403
    //   400: goto +72 -> 472
    //   403: goto -96 -> 307
    //   406: goto -27 -> 379
    //   409: iload 8
    //   411: iload 5
    //   413: invokestatic 225	o/oO:ˊ	(II)I
    //   416: istore 4
    //   418: iload 9
    //   420: iload 5
    //   422: invokestatic 225	o/oO:ˊ	(II)I
    //   425: istore 8
    //   427: iload 7
    //   429: iload 4
    //   431: iload 5
    //   433: invokestatic 222	o/oO:ˏ	(III)I
    //   436: istore 4
    //   438: iload 6
    //   440: iload 8
    //   442: iload 5
    //   444: invokestatic 222	o/oO:ˏ	(III)I
    //   447: istore 6
    //   449: aload 11
    //   451: iload_3
    //   452: aload 10
    //   454: iload 4
    //   456: caload
    //   457: castore
    //   458: aload 11
    //   460: iload_3
    //   461: iconst_1
    //   462: iadd
    //   463: aload 10
    //   465: iload 6
    //   467: caload
    //   468: castore
    //   469: goto +43 -> 512
    //   472: iload_1
    //   473: iconst_1
    //   474: isub
    //   475: istore_1
    //   476: aload 11
    //   478: iload_1
    //   479: aload_0
    //   480: iload_1
    //   481: caload
    //   482: iload_2
    //   483: isub
    //   484: i2c
    //   485: castore
    //   486: goto -179 -> 307
    //   489: iload_3
    //   490: iload_1
    //   491: if_icmpge +6 -> 497
    //   494: goto -212 -> 282
    //   497: goto -225 -> 272
    //   500: bipush 35
    //   502: istore_3
    //   503: goto -435 -> 68
    //   506: goto -246 -> 260
    //   509: goto -322 -> 187
    //   512: goto -259 -> 253
    //   515: bipush 27
    //   517: istore 4
    //   519: goto -171 -> 348
    //   522: iload 6
    //   524: iload 5
    //   526: invokestatic 234	o/oO:ॱ	(II)I
    //   529: istore 7
    //   531: iload 6
    //   533: iload 5
    //   535: invokestatic 236	o/oO:ˋ	(II)I
    //   538: istore 8
    //   540: iload 4
    //   542: iload 5
    //   544: invokestatic 234	o/oO:ॱ	(II)I
    //   547: istore 6
    //   549: iload 4
    //   551: iload 5
    //   553: invokestatic 236	o/oO:ˋ	(II)I
    //   556: istore 9
    //   558: iload 8
    //   560: iload 9
    //   562: if_icmpne +6 -> 568
    //   565: goto -247 -> 318
    //   568: goto -558 -> 10
    // Local variable table:
    //   start	length	slot	name	signature
    //   0	571	0	paramArrayOfChar	char[]
    //   0	571	1	paramInt	int
    //   0	571	2	paramByte	byte
    //   47	456	3	i	int
    //   5	545	4	b1	byte
    //   27	525	5	j	int
    //   12	536	6	b2	byte
    //   10	520	7	k	int
    //   36	527	8	m	int
    //   25	538	9	n	int
    //   48	416	10	arrayOfChar1	char[]
    //   45	432	11	arrayOfChar2	char[]
    // Exception table:
    //   from	to	target	type
    //   418	427	129	java/lang/Exception
    //   409	418	269	java/lang/Exception
    //   418	427	269	java/lang/Exception
    //   427	438	269	java/lang/Exception
    //   438	449	269	java/lang/Exception
    //   522	558	269	java/lang/Exception
  }
  
  static void ͺ()
  {
    ˊˋ = new char[] { 5, 26, 11, 12, 104, 116, 112, 115, 58, 47, 98, 97, 121, 45, 101, 110, 46, 114, 108, 111, 119, 105, 118, 49, 103, 109, 73, 66, 65, 67, 75, 71, 82, 79, 85, 78, 68, 95, 77, 69, 83, 56, 53, 57, 84, 70, 6, 7, 8 };
    ˋᐝ = '\007';
  }
  
  static void ॱˊ()
  {
    break label76;
    int i;
    for (;;)
    {
      switch (i)
      {
      default: 
        break label111;
        i = 64;
      }
    }
    ˋˊ = 61;
    break label79;
    label76:
    for (;;)
    {
      i = ˌ + 87;
      ˋˋ = i % 128;
      if (i % 2 != 0) {
        break;
      }
      break label104;
    }
    for (;;)
    {
      label79:
      i = ˌ + 117;
      ˋˋ = i % 128;
      if (i % 2 == 0)
      {
        return;
        label104:
        i = 16;
        break;
      }
      return;
      label111:
      ˋˊ = -102;
    }
  }
  
  public void ˊ(boolean paramBoolean)
  {
    this.ˊᐝ = paramBoolean;
    try
    {
      this.ˉ |= 0x2;
    }
    finally
    {
      localObject = finally;
      throw localObject;
    }
    ˊ(66);
    super.ʽ();
  }
  
  public void ˋॱ()
  {
    try
    {
      this.ˉ = 8L;
    }
    finally
    {
      localObject = finally;
      throw localObject;
    }
    ʽ();
  }
  
  public void ˎ(boolean paramBoolean)
  {
    this.ˈ = paramBoolean;
    try
    {
      this.ˉ |= 1L;
    }
    finally
    {
      localObject = finally;
      throw localObject;
    }
    ˊ(70);
    super.ʽ();
  }
  
  public void ˏ()
  {
    String str2 = ˎ(new char[] { 1, 2, 3, 4 }, 4, (byte)61).intern();
    try
    {
      l2 = this.ˉ;
      this.ˉ = 0L;
    }
    finally
    {
      localObject1 = finally;
      throw localObject1;
    }
    int k = 0;
    boolean bool3 = this.ˈ;
    int m = 0;
    boolean bool1 = false;
    boolean bool2 = this.ˊᐝ;
    Object localObject2 = this.ˊˊ;
    int j = 0;
    long l1 = l2;
    if ((0x9 & l2) != 0L)
    {
      l1 = l2;
      if ((0x9 & l2) != 0L) {
        if (bool3) {
          l1 = l2 | 0x20;
        } else {
          l1 = l2 | 0x10;
        }
      }
      if (bool3) {
        i = 0;
      } else {
        i = 4;
      }
      if (!bool3)
      {
        bool1 = true;
        k = i;
      }
      else
      {
        bool1 = false;
        k = i;
      }
    }
    long l2 = l1;
    int i = m;
    if ((0xA & l1) != 0L)
    {
      l2 = l1;
      if ((0xA & l1) != 0L) {
        if (bool2) {
          l2 = l1 | 0x80;
        } else {
          l2 = l1 | 0x40;
        }
      }
      if (bool2) {
        i = 0;
      } else {
        i = 4;
      }
    }
    l1 = l2;
    if ((0xC & l2) != 0L)
    {
      if (localObject2 != null) {
        j = 1;
      } else {
        j = 0;
      }
      l1 = l2;
      if ((0xC & l2) != 0L) {
        if (j != 0) {
          l1 = l2 | 0x200;
        } else {
          l1 = l2 | 0x100;
        }
      }
      if (j != 0) {
        j = 0;
      } else {
        j = 4;
      }
    }
    if ((0x8 & l1) != 0L)
    {
      A.ॱ(this.ˊ, true);
      Object localObject3 = this.ॱ;
      String str1 = this.ॱ.getResources().getString(2131755103);
      localObject2 = str1;
      if (str1.startsWith(str2)) {
        localObject2 = ˊ(str1.substring(4)).intern();
      }
      ʹ.ˊ((TextView)localObject3, (CharSequence)localObject2);
      this.ʽ.setNumber(1);
      localObject3 = this.ʽ;
      str1 = this.ʽ.getResources().getString(2131755108);
      localObject2 = str1;
      if (str1.startsWith(str2)) {
        localObject2 = ˊ(str1.substring(4)).intern();
      }
      ((Lf)localObject3).setTitle((String)localObject2);
      localObject3 = this.ʼ;
      str1 = this.ʼ.getResources().getString(2131755105);
      localObject2 = str1;
      if (str1.startsWith(str2)) {
        localObject2 = ˊ(str1.substring(4)).intern();
      }
      ʹ.ˊ((TextView)localObject3, (CharSequence)localObject2);
      localObject3 = this.ॱॱ;
      str1 = this.ॱॱ.getResources().getString(2131755105);
      localObject2 = str1;
      if (str1.startsWith(str2)) {
        localObject2 = ˊ(str1.substring(4)).intern();
      }
      ʹ.ˊ((TextView)localObject3, (CharSequence)localObject2);
      r.ˊ(this.ᐝ, ˎ(new char[] { 5, 6, 6, 0, 8, 9, 58, 58, 12, 3, 4, 13, 13, 7, 15, 16, 17, 9, 3, 19, 19, 17, 18, 20, 10, 11, 6, 19, 18, 25, 19, 15, 2, 12, 13, 4, 23, 7, 23, 24, 10, 8, 19, 0, 0, 26, 17, 22, 8, 10, 6, 5, 18, 21, 19, 21, 32, 18, 21, 17, 13, 23, 29, 30, 31, 32, 33, 34, 28, 41, 37, 38, 24, 40, 29, 32, 80 }, 77, (byte)11).intern(), ॱ(this.ᐝ, 2131230823), true);
      localObject3 = this.ʻ;
      str1 = this.ʻ.getResources().getString(2131755106);
      localObject2 = str1;
      if (str1.startsWith(str2)) {
        localObject2 = ˊ(str1.substring(4)).intern();
      }
      ʹ.ˊ((TextView)localObject3, (CharSequence)localObject2);
      A.ॱ(this.ʻ, true);
      localObject3 = this.ˏॱ;
      str1 = this.ˏॱ.getResources().getString(2131755106);
      localObject2 = str1;
      if (str1.startsWith(str2)) {
        localObject2 = ˊ(str1.substring(4)).intern();
      }
      ʹ.ˊ((TextView)localObject3, (CharSequence)localObject2);
      localObject3 = this.ʾ;
      str1 = this.ʾ.getResources().getString(2131755246);
      localObject2 = str1;
      if (str1.startsWith(str2)) {
        localObject2 = ˊ(str1.substring(4)).intern();
      }
      ʹ.ˊ((TextView)localObject3, (CharSequence)localObject2);
      this.ॱˊ.setNumber(2);
      localObject3 = this.ॱˊ;
      str1 = this.ॱˊ.getResources().getString(2131755109);
      localObject2 = str1;
      if (str1.startsWith(str2)) {
        localObject2 = ˊ(str1.substring(4)).intern();
      }
      ((Lf)localObject3).setTitle((String)localObject2);
      A.ॱ(this.ॱˎ, true);
      localObject3 = this.ॱˎ;
      str1 = this.ॱˎ.getResources().getString(2131755107);
      localObject2 = str1;
      if (str1.startsWith(str2)) {
        localObject2 = ˊ(str1.substring(4)).intern();
      }
      ((у)localObject3).setTitle((CharSequence)localObject2);
    }
    if ((0x9 & l1) != 0L)
    {
      this.ॱ.setEnabled(bool1);
      this.ʼॱ.setVisibility(k);
    }
    if ((0xC & l1) != 0L)
    {
      this.ॱॱ.setVisibility(j);
      this.ˏॱ.setVisibility(j);
    }
    if ((0xA & l1) != 0L) {
      this.ˊॱ.setVisibility(i);
    }
  }
  
  public void ˏ(String paramString)
  {
    this.ˊˊ = paramString;
    try
    {
      this.ˉ |= 0x4;
    }
    finally
    {
      paramString = finally;
      throw paramString;
    }
    ˊ(17);
    super.ʽ();
  }
  
  public boolean ˏ(int paramInt1, Object paramObject, int paramInt2)
  {
    break label71;
    return true;
    return false;
    label7:
    paramInt1 = 0;
    break label44;
    label12:
    paramInt1 = 1;
    label44:
    label71:
    for (;;)
    {
      paramInt1 = ˌ + 39;
      ˋˋ = paramInt1 % 128;
      if (paramInt1 % 2 != 0) {
        break label7;
      }
      break label12;
      switch (paramInt1)
      {
      }
      break;
    }
  }
  
  public boolean ॱ()
  {
    try
    {
      long l = this.ˉ;
      if (l != 0L) {
        return true;
      }
    }
    finally
    {
      localObject = finally;
      throw localObject;
    }
    return false;
  }
}
