package o;

import android.content.res.Resources;
import android.databinding.ViewDataBinding;
import android.databinding.ViewDataBinding.If;
import android.util.SparseIntArray;
import android.widget.ImageView;
import android.widget.LinearLayout;
import android.widget.ProgressBar;
import android.widget.RelativeLayout;
import android.widget.TextView;

public class JJ
  extends ViewDataBinding
{
  private static int ʻॱ;
  private static int ʼॱ;
  private static final SparseIntArray ʽ;
  private static int ˈ = 0;
  private static boolean ॱˋ;
  private static boolean ॱˎ;
  private static byte ॱᐝ;
  private static final ViewDataBinding.If ᐝ;
  private static char[] ᐝॱ;
  public final ProgressBar ʻ;
  public final у ʼ;
  public final ImageView ˊ;
  private coN ˊॱ;
  private long ˋॱ;
  public final IZ ˎ;
  private final LinearLayout ˏॱ;
  private final TextView ͺ;
  public final Jh ॱ;
  private final RelativeLayout ॱˊ;
  public final TextView ॱॱ;
  
  static
  {
    ʼॱ = 1;
    ͺ();
    ˋॱ();
    ᐝ = null;
    ʽ = new SparseIntArray();
    ʽ.put(2131296600, 8);
    int i = ʼॱ + 13;
    ˈ = i % 128;
    if (i % 2 == 0) {}
  }
  
  /* Error */
  public JJ(ˉ paramˉ, android.view.View paramView)
  {
    // Byte code:
    //   0: goto +6 -> 6
    //   3: astore_1
    //   4: aload_1
    //   5: athrow
    //   6: aload_0
    //   7: aload_1
    //   8: aload_2
    //   9: iconst_1
    //   10: invokespecial 71	android/databinding/ViewDataBinding:<init>	(Lo/ˉ;Landroid/view/View;I)V
    //   13: aload_0
    //   14: ldc2_w 72
    //   17: putfield 75	o/JJ:ˋॱ	J
    //   20: getstatic 52	o/JJ:ᐝ	Landroid/databinding/ViewDataBinding$If;
    //   23: astore_3
    //   24: getstatic 59	o/JJ:ʽ	Landroid/util/SparseIntArray;
    //   27: astore 4
    //   29: aload_1
    //   30: aload_2
    //   31: bipush 9
    //   33: aload_3
    //   34: aload 4
    //   36: invokestatic 78	o/JJ:ॱ	(Lo/ˉ;Landroid/view/View;ILandroid/databinding/ViewDataBinding$If;Landroid/util/SparseIntArray;)[Ljava/lang/Object;
    //   39: astore_1
    //   40: aload_0
    //   41: aload_1
    //   42: bipush 7
    //   44: aaload
    //   45: checkcast 80	o/Jh
    //   48: putfield 82	o/JJ:ॱ	Lo/Jh;
    //   51: aload_0
    //   52: getfield 82	o/JJ:ॱ	Lo/Jh;
    //   55: aconst_null
    //   56: invokevirtual 86	o/Jh:setTag	(Ljava/lang/Object;)V
    //   59: aload_0
    //   60: aload_1
    //   61: iconst_4
    //   62: aaload
    //   63: checkcast 88	o/IZ
    //   66: putfield 90	o/JJ:ˎ	Lo/IZ;
    //   69: aload_0
    //   70: getfield 90	o/JJ:ˎ	Lo/IZ;
    //   73: aconst_null
    //   74: invokevirtual 91	o/IZ:setTag	(Ljava/lang/Object;)V
    //   77: aload_0
    //   78: aload_1
    //   79: iconst_1
    //   80: aaload
    //   81: checkcast 93	android/widget/ImageView
    //   84: putfield 95	o/JJ:ˊ	Landroid/widget/ImageView;
    //   87: aload_0
    //   88: getfield 95	o/JJ:ˊ	Landroid/widget/ImageView;
    //   91: aconst_null
    //   92: invokevirtual 96	android/widget/ImageView:setTag	(Ljava/lang/Object;)V
    //   95: aload_0
    //   96: aload_1
    //   97: iconst_3
    //   98: aaload
    //   99: checkcast 98	android/widget/TextView
    //   102: putfield 100	o/JJ:ॱॱ	Landroid/widget/TextView;
    //   105: aload_0
    //   106: getfield 100	o/JJ:ॱॱ	Landroid/widget/TextView;
    //   109: aconst_null
    //   110: invokevirtual 101	android/widget/TextView:setTag	(Ljava/lang/Object;)V
    //   113: aload_0
    //   114: aload_1
    //   115: iconst_0
    //   116: aaload
    //   117: checkcast 103	android/widget/RelativeLayout
    //   120: putfield 105	o/JJ:ॱˊ	Landroid/widget/RelativeLayout;
    //   123: aload_0
    //   124: getfield 105	o/JJ:ॱˊ	Landroid/widget/RelativeLayout;
    //   127: aconst_null
    //   128: invokevirtual 106	android/widget/RelativeLayout:setTag	(Ljava/lang/Object;)V
    //   131: aload_0
    //   132: aload_1
    //   133: iconst_5
    //   134: aaload
    //   135: checkcast 108	android/widget/LinearLayout
    //   138: putfield 110	o/JJ:ˏॱ	Landroid/widget/LinearLayout;
    //   141: aload_0
    //   142: getfield 110	o/JJ:ˏॱ	Landroid/widget/LinearLayout;
    //   145: aconst_null
    //   146: invokevirtual 111	android/widget/LinearLayout:setTag	(Ljava/lang/Object;)V
    //   149: aload_0
    //   150: aload_1
    //   151: bipush 6
    //   153: aaload
    //   154: checkcast 98	android/widget/TextView
    //   157: putfield 113	o/JJ:ͺ	Landroid/widget/TextView;
    //   160: aload_0
    //   161: getfield 113	o/JJ:ͺ	Landroid/widget/TextView;
    //   164: aconst_null
    //   165: invokevirtual 101	android/widget/TextView:setTag	(Ljava/lang/Object;)V
    //   168: aload_0
    //   169: aload_1
    //   170: bipush 8
    //   172: aaload
    //   173: checkcast 115	android/widget/ProgressBar
    //   176: putfield 117	o/JJ:ʻ	Landroid/widget/ProgressBar;
    //   179: aload_0
    //   180: aload_1
    //   181: iconst_2
    //   182: aaload
    //   183: checkcast 119	o/у
    //   186: putfield 121	o/JJ:ʼ	Lo/у;
    //   189: aload_0
    //   190: getfield 121	o/JJ:ʼ	Lo/у;
    //   193: aconst_null
    //   194: invokevirtual 122	o/у:setTag	(Ljava/lang/Object;)V
    //   197: aload_0
    //   198: aload_2
    //   199: invokevirtual 126	o/JJ:ˋ	(Landroid/view/View;)V
    //   202: aload_0
    //   203: invokevirtual 128	o/JJ:ˊॱ	()V
    //   206: return
    //   207: astore_1
    //   208: aload_1
    //   209: athrow
    // Local variable table:
    //   start	length	slot	name	signature
    //   0	210	0	this	JJ
    //   0	210	1	paramˉ	ˉ
    //   0	210	2	paramView	android.view.View
    //   23	11	3	localIf	ViewDataBinding.If
    //   27	8	4	localSparseIntArray	SparseIntArray
    // Exception table:
    //   from	to	target	type
    //   13	20	3	java/lang/Exception
    //   20	24	3	java/lang/Exception
    //   24	29	3	java/lang/Exception
    //   29	40	3	java/lang/Exception
    //   40	206	3	java/lang/Exception
    //   20	24	207	java/lang/Exception
  }
  
  /* Error */
  private String ˊ(String paramString)
  {
    // Byte code:
    //   0: goto +35 -> 35
    //   3: iconst_1
    //   4: istore_3
    //   5: goto +310 -> 315
    //   8: aload 4
    //   10: arraylength
    //   11: istore_3
    //   12: iload_2
    //   13: iload_3
    //   14: if_icmpge +6 -> 20
    //   17: goto -14 -> 3
    //   20: goto +184 -> 204
    //   23: astore_1
    //   24: aload_1
    //   25: athrow
    //   26: goto -18 -> 8
    //   29: bipush 44
    //   31: istore_2
    //   32: goto +252 -> 284
    //   35: goto +223 -> 258
    //   38: aload_1
    //   39: bipush 10
    //   41: newarray byte
    //   43: dup
    //   44: iconst_0
    //   45: ldc -124
    //   47: bastore
    //   48: dup
    //   49: iconst_1
    //   50: ldc -123
    //   52: bastore
    //   53: dup
    //   54: iconst_2
    //   55: ldc -122
    //   57: bastore
    //   58: dup
    //   59: iconst_3
    //   60: ldc -121
    //   62: bastore
    //   63: dup
    //   64: iconst_4
    //   65: ldc -120
    //   67: bastore
    //   68: dup
    //   69: iconst_5
    //   70: ldc -120
    //   72: bastore
    //   73: dup
    //   74: bipush 6
    //   76: ldc -123
    //   78: bastore
    //   79: dup
    //   80: bipush 7
    //   82: ldc -119
    //   84: bastore
    //   85: dup
    //   86: bipush 8
    //   88: ldc -118
    //   90: bastore
    //   91: dup
    //   92: bipush 9
    //   94: ldc -117
    //   96: bastore
    //   97: aconst_null
    //   98: aconst_null
    //   99: bipush 127
    //   101: invokestatic 142	o/JJ:ˋ	([B[I[CI)Ljava/lang/String;
    //   104: invokevirtual 148	java/lang/String:intern	()Ljava/lang/String;
    //   107: invokevirtual 152	java/lang/String:getBytes	(Ljava/lang/String;)[B
    //   110: astore 4
    //   112: aload 4
    //   114: arraylength
    //   115: newarray byte
    //   117: astore_1
    //   118: goto +225 -> 343
    //   121: aload_1
    //   122: bipush 10
    //   124: newarray byte
    //   126: dup
    //   127: iconst_0
    //   128: ldc -124
    //   130: bastore
    //   131: dup
    //   132: iconst_1
    //   133: ldc -123
    //   135: bastore
    //   136: dup
    //   137: iconst_2
    //   138: ldc -122
    //   140: bastore
    //   141: dup
    //   142: iconst_3
    //   143: ldc -121
    //   145: bastore
    //   146: dup
    //   147: iconst_4
    //   148: ldc -120
    //   150: bastore
    //   151: dup
    //   152: iconst_5
    //   153: ldc -120
    //   155: bastore
    //   156: dup
    //   157: bipush 6
    //   159: ldc -123
    //   161: bastore
    //   162: dup
    //   163: bipush 7
    //   165: ldc -119
    //   167: bastore
    //   168: dup
    //   169: bipush 8
    //   171: ldc -118
    //   173: bastore
    //   174: dup
    //   175: bipush 9
    //   177: ldc -117
    //   179: bastore
    //   180: aconst_null
    //   181: aconst_null
    //   182: bipush 123
    //   184: invokestatic 142	o/JJ:ˋ	([B[I[CI)Ljava/lang/String;
    //   187: invokevirtual 148	java/lang/String:intern	()Ljava/lang/String;
    //   190: invokevirtual 152	java/lang/String:getBytes	(Ljava/lang/String;)[B
    //   193: astore 4
    //   195: aload 4
    //   197: arraylength
    //   198: newarray byte
    //   200: astore_1
    //   201: goto +142 -> 343
    //   204: iconst_0
    //   205: istore_3
    //   206: goto +109 -> 315
    //   209: new 144	java/lang/String
    //   212: dup
    //   213: aload_1
    //   214: iconst_5
    //   215: newarray byte
    //   217: dup
    //   218: iconst_0
    //   219: ldc -120
    //   221: bastore
    //   222: dup
    //   223: iconst_1
    //   224: ldc -123
    //   226: bastore
    //   227: dup
    //   228: iconst_2
    //   229: ldc -103
    //   231: bastore
    //   232: dup
    //   233: iconst_3
    //   234: ldc -102
    //   236: bastore
    //   237: dup
    //   238: iconst_4
    //   239: ldc -101
    //   241: bastore
    //   242: aconst_null
    //   243: aconst_null
    //   244: bipush 127
    //   246: invokestatic 142	o/JJ:ˋ	([B[I[CI)Ljava/lang/String;
    //   249: invokevirtual 148	java/lang/String:intern	()Ljava/lang/String;
    //   252: invokespecial 158	java/lang/String:<init>	([BLjava/lang/String;)V
    //   255: astore_1
    //   256: aload_1
    //   257: areturn
    //   258: getstatic 44	o/JJ:ˈ	I
    //   261: bipush 93
    //   263: iadd
    //   264: istore_2
    //   265: iload_2
    //   266: sipush 128
    //   269: irem
    //   270: putstatic 46	o/JJ:ʼॱ	I
    //   273: iload_2
    //   274: iconst_2
    //   275: irem
    //   276: ifne +6 -> 282
    //   279: goto -250 -> 29
    //   282: iconst_4
    //   283: istore_2
    //   284: iload_2
    //   285: lookupswitch	default:+27->312, 4:+-247->38, 44:+-164->121
    //   312: goto -274 -> 38
    //   315: iload_3
    //   316: tableswitch	default:+24->340, 0:+-107->209, 1:+69->385
    //   340: goto -131 -> 209
    //   343: iconst_0
    //   344: istore_2
    //   345: getstatic 44	o/JJ:ˈ	I
    //   348: bipush 7
    //   350: iadd
    //   351: istore_3
    //   352: iload_3
    //   353: sipush 128
    //   356: irem
    //   357: putstatic 46	o/JJ:ʼॱ	I
    //   360: iload_3
    //   361: iconst_2
    //   362: irem
    //   363: ifne +6 -> 369
    //   366: goto +6 -> 372
    //   369: goto -343 -> 26
    //   372: goto -364 -> 8
    //   375: astore_1
    //   376: new 160	java/lang/RuntimeException
    //   379: dup
    //   380: aload_1
    //   381: invokespecial 163	java/lang/RuntimeException:<init>	(Ljava/lang/Throwable;)V
    //   384: athrow
    //   385: aload_1
    //   386: iload_2
    //   387: aload 4
    //   389: aload 4
    //   391: arraylength
    //   392: iload_2
    //   393: isub
    //   394: iconst_1
    //   395: isub
    //   396: baload
    //   397: getstatic 165	o/JJ:ॱᐝ	B
    //   400: ixor
    //   401: i2b
    //   402: bastore
    //   403: iload_2
    //   404: iconst_1
    //   405: iadd
    //   406: istore_2
    //   407: goto -399 -> 8
    // Local variable table:
    //   start	length	slot	name	signature
    //   0	410	0	this	JJ
    //   0	410	1	paramString	String
    //   12	395	2	i	int
    //   4	359	3	j	int
    //   8	382	4	arrayOfByte	byte[]
    // Exception table:
    //   from	to	target	type
    //   345	352	23	java/lang/Exception
    //   352	360	23	java/lang/Exception
    //   8	12	375	java/io/UnsupportedEncodingException
    //   38	118	375	java/io/UnsupportedEncodingException
    //   121	201	375	java/io/UnsupportedEncodingException
    //   209	256	375	java/io/UnsupportedEncodingException
    //   385	403	375	java/io/UnsupportedEncodingException
  }
  
  private boolean ˊ(coN paramCoN, int paramInt)
  {
    if (paramInt == 0)
    {
      try
      {
        this.ˋॱ |= 1L;
      }
      finally
      {
        paramCoN = finally;
        throw paramCoN;
      }
      return true;
    }
    return false;
  }
  
  /* Error */
  private static String ˋ(byte[] paramArrayOfByte, int[] paramArrayOfInt, char[] paramArrayOfChar, int paramInt)
  {
    // Byte code:
    //   0: goto +166 -> 166
    //   3: iconst_0
    //   4: istore 6
    //   6: goto +329 -> 335
    //   9: goto +360 -> 369
    //   12: aload_0
    //   13: iload 4
    //   15: aload 9
    //   17: aload_1
    //   18: iload 6
    //   20: iconst_0
    //   21: iadd
    //   22: iload 4
    //   24: ishl
    //   25: iaload
    //   26: iload_3
    //   27: idiv
    //   28: caload
    //   29: iload 7
    //   31: imul
    //   32: i2c
    //   33: castore
    //   34: iload 4
    //   36: bipush 80
    //   38: iadd
    //   39: istore 4
    //   41: goto +157 -> 198
    //   44: iconst_0
    //   45: istore 4
    //   47: goto +500 -> 547
    //   50: iload 5
    //   52: tableswitch	default:+24->76, 0:+544->596, 1:+-40->12
    //   76: goto -64 -> 12
    //   79: aload_0
    //   80: iload 4
    //   82: aload 9
    //   84: aload_2
    //   85: iload 5
    //   87: iconst_1
    //   88: isub
    //   89: iload 4
    //   91: isub
    //   92: caload
    //   93: iload_3
    //   94: isub
    //   95: caload
    //   96: iload 7
    //   98: isub
    //   99: i2c
    //   100: castore
    //   101: iload 4
    //   103: iconst_1
    //   104: iadd
    //   105: istore 4
    //   107: goto +405 -> 512
    //   110: new 144	java/lang/String
    //   113: dup
    //   114: aload_1
    //   115: invokespecial 169	java/lang/String:<init>	([C)V
    //   118: astore_0
    //   119: goto +50 -> 169
    //   122: iload 4
    //   124: iload 5
    //   126: if_icmpge +6 -> 132
    //   129: goto -50 -> 79
    //   132: goto +455 -> 587
    //   135: getstatic 171	o/JJ:ॱˎ	Z
    //   138: ifeq +6 -> 144
    //   141: goto -97 -> 44
    //   144: goto +93 -> 237
    //   147: aload_0
    //   148: arraylength
    //   149: istore 4
    //   151: iload 4
    //   153: istore 5
    //   155: iload 4
    //   157: newarray char
    //   159: astore_1
    //   160: iconst_1
    //   161: istore 4
    //   163: goto +290 -> 453
    //   166: goto +45 -> 211
    //   169: getstatic 44	o/JJ:ˈ	I
    //   172: bipush 13
    //   174: iadd
    //   175: istore_3
    //   176: iload_3
    //   177: sipush 128
    //   180: irem
    //   181: putstatic 46	o/JJ:ʼॱ	I
    //   184: iload_3
    //   185: iconst_2
    //   186: irem
    //   187: ifne +6 -> 193
    //   190: goto +209 -> 399
    //   193: aload_0
    //   194: areturn
    //   195: astore_0
    //   196: aload_0
    //   197: athrow
    //   198: iload 4
    //   200: iload 6
    //   202: if_icmpge +6 -> 208
    //   205: goto +196 -> 401
    //   208: goto +185 -> 393
    //   211: getstatic 173	o/JJ:ᐝॱ	[C
    //   214: astore 9
    //   216: getstatic 175	o/JJ:ʻॱ	I
    //   219: istore 7
    //   221: getstatic 177	o/JJ:ॱˋ	Z
    //   224: istore 8
    //   226: iload 8
    //   228: ifeq +6 -> 234
    //   231: goto +287 -> 518
    //   234: goto -99 -> 135
    //   237: iconst_1
    //   238: istore 4
    //   240: goto +307 -> 547
    //   243: iload 5
    //   245: tableswitch	default:+23->268, 0:+258->503, 1:+60->305
    //   268: goto +37 -> 305
    //   271: getstatic 44	o/JJ:ˈ	I
    //   274: istore 4
    //   276: iload 4
    //   278: bipush 113
    //   280: iadd
    //   281: istore 4
    //   283: iload 4
    //   285: sipush 128
    //   288: irem
    //   289: putstatic 46	o/JJ:ʼॱ	I
    //   292: iload 4
    //   294: iconst_2
    //   295: irem
    //   296: ifne +6 -> 302
    //   299: goto -290 -> 9
    //   302: goto +67 -> 369
    //   305: getstatic 46	o/JJ:ʼॱ	I
    //   308: bipush 61
    //   310: iadd
    //   311: istore 5
    //   313: iload 5
    //   315: sipush 128
    //   318: irem
    //   319: putstatic 44	o/JJ:ˈ	I
    //   322: iload 5
    //   324: iconst_2
    //   325: irem
    //   326: ifeq +6 -> 332
    //   329: goto +55 -> 384
    //   332: goto +31 -> 363
    //   335: iload 6
    //   337: tableswitch	default:+23->360, 0:+-227->110, 1:+70->407
    //   360: goto +47 -> 407
    //   363: iconst_0
    //   364: istore 5
    //   366: goto -316 -> 50
    //   369: aload_2
    //   370: arraylength
    //   371: istore 5
    //   373: iload 5
    //   375: newarray char
    //   377: astore_0
    //   378: iconst_0
    //   379: istore 4
    //   381: goto -259 -> 122
    //   384: iconst_1
    //   385: istore 5
    //   387: goto -337 -> 50
    //   390: astore_0
    //   391: aload_0
    //   392: athrow
    //   393: iconst_0
    //   394: istore 5
    //   396: goto -153 -> 243
    //   399: aload_0
    //   400: areturn
    //   401: iconst_1
    //   402: istore 5
    //   404: goto -161 -> 243
    //   407: getstatic 44	o/JJ:ˈ	I
    //   410: bipush 89
    //   412: iadd
    //   413: istore 6
    //   415: iload 6
    //   417: sipush 128
    //   420: irem
    //   421: putstatic 46	o/JJ:ʼॱ	I
    //   424: iload 6
    //   426: iconst_2
    //   427: irem
    //   428: ifne +6 -> 434
    //   431: goto +84 -> 515
    //   434: goto +32 -> 466
    //   437: aload_0
    //   438: arraylength
    //   439: istore 4
    //   441: iload 4
    //   443: istore 5
    //   445: iload 4
    //   447: newarray char
    //   449: astore_1
    //   450: iconst_0
    //   451: istore 4
    //   453: iload 4
    //   455: iload 5
    //   457: if_icmpge +6 -> 463
    //   460: goto +37 -> 497
    //   463: goto -460 -> 3
    //   466: aload_1
    //   467: iload 4
    //   469: aload 9
    //   471: aload_0
    //   472: iload 5
    //   474: iconst_1
    //   475: isub
    //   476: iload 4
    //   478: isub
    //   479: baload
    //   480: iload_3
    //   481: iadd
    //   482: caload
    //   483: iload 7
    //   485: isub
    //   486: i2c
    //   487: castore
    //   488: iload 4
    //   490: iconst_1
    //   491: iadd
    //   492: istore 4
    //   494: goto -41 -> 453
    //   497: iconst_1
    //   498: istore 6
    //   500: goto -165 -> 335
    //   503: new 144	java/lang/String
    //   506: dup
    //   507: aload_0
    //   508: invokespecial 169	java/lang/String:<init>	([C)V
    //   511: areturn
    //   512: goto -390 -> 122
    //   515: goto -49 -> 466
    //   518: getstatic 46	o/JJ:ʼॱ	I
    //   521: iconst_1
    //   522: iadd
    //   523: istore 4
    //   525: iload 4
    //   527: sipush 128
    //   530: irem
    //   531: putstatic 44	o/JJ:ˈ	I
    //   534: iload 4
    //   536: iconst_2
    //   537: irem
    //   538: ifeq +6 -> 544
    //   541: goto -394 -> 147
    //   544: goto -107 -> 437
    //   547: iload 4
    //   549: tableswitch	default:+23->572, 0:+-278->271, 1:+23->572
    //   572: aload_1
    //   573: arraylength
    //   574: istore 6
    //   576: iload 6
    //   578: newarray char
    //   580: astore_0
    //   581: iconst_0
    //   582: istore 4
    //   584: goto -386 -> 198
    //   587: new 144	java/lang/String
    //   590: dup
    //   591: aload_0
    //   592: invokespecial 169	java/lang/String:<init>	([C)V
    //   595: areturn
    //   596: aload_0
    //   597: iload 4
    //   599: aload 9
    //   601: aload_1
    //   602: iload 6
    //   604: iconst_1
    //   605: isub
    //   606: iload 4
    //   608: isub
    //   609: iaload
    //   610: iload_3
    //   611: isub
    //   612: caload
    //   613: iload 7
    //   615: isub
    //   616: i2c
    //   617: castore
    //   618: iload 4
    //   620: iconst_1
    //   621: iadd
    //   622: istore 4
    //   624: goto -426 -> 198
    // Local variable table:
    //   start	length	slot	name	signature
    //   0	627	0	paramArrayOfByte	byte[]
    //   0	627	1	paramArrayOfInt	int[]
    //   0	627	2	paramArrayOfChar	char[]
    //   0	627	3	paramInt	int
    //   13	610	4	i	int
    //   50	426	5	j	int
    //   4	602	6	k	int
    //   29	587	7	m	int
    //   224	3	8	bool	boolean
    //   15	585	9	arrayOfChar	char[]
    // Exception table:
    //   from	to	target	type
    //   211	216	195	java/lang/Exception
    //   271	276	195	java/lang/Exception
    //   216	221	390	java/lang/Exception
    //   221	226	390	java/lang/Exception
    //   283	292	390	java/lang/Exception
  }
  
  static void ˋॱ()
  {
    for (;;)
    {
      int i = ˈ + 71;
      ʼॱ = i % 128;
      if (i % 2 != 0)
      {
        i = 0;
        break label68;
        i = null.length;
        return;
        return;
      }
      switch (i)
      {
      case 1: 
      default: 
        ॱᐝ = -102;
        continue;
        for (;;)
        {
          switch (i)
          {
          }
          return;
          i = 0;
          break;
          break label111;
          i = 1;
        }
        for (;;)
        {
          i = 1;
          break;
          i = ˈ + 37;
          ʼॱ = i % 128;
          if (i % 2 == 0) {
            break label93;
          }
        }
      case 0: 
        label68:
        label93:
        label111:
        ॱᐝ = 69;
      }
    }
  }
  
  static void ͺ()
  {
    ॱˋ = true;
    ॱˎ = true;
    ᐝॱ = new char[] { 181, 202, 187, 188, 280, 292, 288, 291, 234, 223, 274, 273, 297, 221, 277, 286, 222, 290, 284, 287, 295, 281, 294, 225, 279, 285, 249, 242, 241, 243, 251, 247, 258, 255, 261, 254, 244, 271, 253, 245, 259, 232, 229, 233, 260, 246 };
    ʻॱ = 176;
  }
  
  public void ˊॱ()
  {
    try
    {
      this.ˋॱ = 2L;
    }
    finally
    {
      localObject = finally;
      throw localObject;
    }
    ʽ();
  }
  
  public void ˎ(coN paramCoN)
  {
    ˎ(0, paramCoN);
    this.ˊॱ = paramCoN;
    try
    {
      this.ˋॱ |= 1L;
    }
    finally
    {
      paramCoN = finally;
      throw paramCoN;
    }
    ˊ(70);
    super.ʽ();
  }
  
  public void ˏ()
  {
    String str2 = ˋ(new byte[] { -124, -125, -126, -127 }, null, null, 127).intern();
    long l2;
    try
    {
      l2 = this.ˋॱ;
      this.ˋॱ = 0L;
    }
    finally
    {
      localObject1 = finally;
      throw localObject1;
    }
    int i = 0;
    Object localObject2 = this.ˊॱ;
    boolean bool2 = false;
    boolean bool1 = false;
    long l1 = l2;
    if ((0x3 & l2) != 0L)
    {
      bool1 = bool2;
      if (localObject2 != null) {
        bool1 = ((coN)localObject2).ˊ();
      }
      l1 = l2;
      if ((0x3 & l2) != 0L) {
        if (bool1) {
          l1 = l2 | 0x8;
        } else {
          l1 = l2 | 0x4;
        }
      }
      if (bool1) {
        i = 0;
      } else {
        i = 4;
      }
      if (!bool1) {
        bool1 = true;
      } else {
        bool1 = false;
      }
    }
    if ((0x3 & l1) != 0L)
    {
      this.ॱ.setEnabled(bool1);
      this.ˎ.setActive(bool1);
      this.ˏॱ.setVisibility(i);
    }
    if ((0x2 & l1) != 0L)
    {
      Object localObject3 = this.ॱ;
      String str1 = this.ॱ.getResources().getString(2131755147);
      localObject2 = str1;
      if (str1.startsWith(str2)) {
        localObject2 = ˊ(str1.substring(4)).intern();
      }
      ʹ.ˊ((TextView)localObject3, (CharSequence)localObject2);
      localObject3 = this.ˎ;
      str1 = this.ˎ.getResources().getString(2131755073);
      localObject2 = str1;
      if (str1.startsWith(str2)) {
        localObject2 = ˊ(str1.substring(4)).intern();
      }
      ((IZ)localObject3).setHintText((String)localObject2);
      r.ˊ(this.ˊ, ˋ(new byte[] { -88, -96, -99, -89, -101, -90, -91, -92, -93, -94, -95, -96, -97, -98, -99, -100, -118, -113, -103, -116, -102, -101, -113, -102, -113, -123, -122, -118, -120, -103, -112, -106, -122, -122, -113, -120, -118, -104, -105, -118, -106, -121, -116, -118, -122, -113, -109, -109, -116, -107, -122, -117, -118, -108, -110, -111, -109, -110, -122, -117, -111, -112, -113, -114, -115, -116, -121, -122, -117, -118, -118, -119, -120, -121, -122, -122, -123 }, null, null, 127).intern(), ॱ(this.ˊ, 2131230823), true);
      localObject3 = this.ॱॱ;
      str1 = this.ॱॱ.getResources().getString(2131755191);
      localObject2 = str1;
      if (str1.startsWith(str2)) {
        localObject2 = ˊ(str1.substring(4)).intern();
      }
      ʹ.ˊ((TextView)localObject3, (CharSequence)localObject2);
      localObject3 = this.ͺ;
      str1 = this.ͺ.getResources().getString(2131755246);
      localObject2 = str1;
      if (str1.startsWith(str2)) {
        localObject2 = ˊ(str1.substring(4)).intern();
      }
      ʹ.ˊ((TextView)localObject3, (CharSequence)localObject2);
      localObject3 = this.ʼ;
      str1 = this.ʼ.getResources().getString(2131755050);
      localObject2 = str1;
      if (str1.startsWith(str2)) {
        localObject2 = ˊ(str1.substring(4)).intern();
      }
      ((у)localObject3).setTitle((CharSequence)localObject2);
    }
  }
  
  public boolean ˏ(int paramInt1, Object paramObject, int paramInt2)
  {
    break label119;
    do
    {
      paramInt1 = 1;
      break;
      paramInt1 = ˈ + 105;
      ʼॱ = paramInt1 % 128;
    } while (paramInt1 % 2 == 0);
    break label125;
    label35:
    int i = null.length;
    switch (paramInt1)
    {
    default: 
      break;
      paramInt1 = null.length;
      return false;
      return false;
    case 0: 
      label63:
      return ˊ((coN)paramObject, paramInt2);
      for (;;)
      {
        switch (i)
        {
        case 0: 
        default: 
          break label35;
          label107:
          i = 1;
          continue;
          label113:
          i = 0;
        }
      }
    }
    for (;;)
    {
      label119:
      break;
      label125:
      paramInt1 = 0;
      break label160;
      i = ˈ + 89;
      ʼॱ = i % 128;
      if (i % 2 == 0) {
        break label113;
      }
      break label107;
      label160:
      switch (paramInt1)
      {
      }
      break label63;
      switch (paramInt1)
      {
      }
    }
  }
  
  public boolean ॱ()
  {
    try
    {
      long l = this.ˋॱ;
      if (l != 0L) {
        return true;
      }
    }
    finally
    {
      localObject = finally;
      throw localObject;
    }
    return false;
  }
}
