package o;

import android.content.res.Resources;
import android.databinding.ViewDataBinding;
import android.databinding.ViewDataBinding.If;
import android.util.SparseIntArray;
import android.view.View;
import android.widget.ImageView;
import android.widget.LinearLayout;
import android.widget.RelativeLayout;
import android.widget.TextView;

public class JM
  extends ViewDataBinding
{
  private static final ViewDataBinding.If ʽॱ;
  private static final SparseIntArray ʾ;
  private static byte ˊˋ;
  private static int[] ˋˋ;
  private static int ˋᐝ;
  private static int ˎˎ;
  public final View ʻ;
  public final TextView ʻॱ;
  public final KZ ʼ;
  private final RelativeLayout ʼॱ;
  public final ImageView ʽ;
  public final KV ʿ;
  public final у ˈ;
  private long ˉ = -1L;
  public final ImageView ˊ;
  private boolean ˊˊ;
  public final KV ˊॱ;
  private boolean ˊᐝ;
  private final ImageView ˋˊ;
  public final aH ˋॱ;
  public final ImageView ˎ;
  public final ᵙ ˏॱ;
  public final KW ͺ;
  public final TextView ॱ;
  public final ImageView ॱˊ;
  public final ImageView ॱˋ;
  public final pR ॱˎ;
  public final View ॱॱ;
  public final LinearLayout ॱᐝ;
  public final ﮆ ᐝ;
  public final TextView ᐝॱ;
  
  static
  {
    break label4;
    return;
    label4:
    ˎˎ = 0;
    ˋᐝ = 1;
    ˏॱ();
    ˋॱ();
    ʽॱ = null;
    ʾ = new SparseIntArray();
    ʾ.put(2131296445, 12);
    ʾ.put(2131296713, 13);
    ʾ.put(2131296325, 14);
    ʾ.put(2131296316, 15);
    ʾ.put(2131296434, 16);
    ʾ.put(2131296581, 17);
    ʾ.put(2131296582, 18);
    ʾ.put(2131296604, 19);
    ʾ.put(2131296532, 20);
    ʾ.put(2131296531, 21);
    int i = ˎˎ + 49;
    ˋᐝ = i % 128;
    if (i % 2 != 0) {
      break label165;
    }
    for (;;)
    {
      i = 88 / 0;
      return;
      label165:
      i = 18;
      break label174;
      i = 33;
      label174:
      switch (i)
      {
      }
    }
  }
  
  public JM(ˉ paramˉ, View paramView)
  {
    super(paramˉ, paramView, 0);
    paramˉ = ॱ(paramˉ, paramView, 22, ʽॱ, ʾ);
    this.ˊ = ((ImageView)paramˉ[15]);
    this.ˎ = ((ImageView)paramˉ[14]);
    this.ॱ = ((TextView)paramˉ[9]);
    this.ॱ.setTag(null);
    this.ᐝ = ((ﮆ)paramˉ[0]);
    this.ᐝ.setTag(null);
    this.ʼ = ((KZ)paramˉ[4]);
    this.ʼ.setTag(null);
    this.ॱॱ = ((View)paramˉ[16]);
    this.ʻ = ((View)paramˉ[12]);
    this.ʽ = ((ImageView)paramˉ[11]);
    this.ʽ.setTag(null);
    this.ॱˊ = ((ImageView)paramˉ[2]);
    this.ॱˊ.setTag(null);
    this.ʼॱ = ((RelativeLayout)paramˉ[10]);
    this.ʼॱ.setTag(null);
    this.ˋˊ = ((ImageView)paramˉ[3]);
    this.ˋˊ.setTag(null);
    this.ˋॱ = ((aH)paramˉ[21]);
    this.ˏॱ = ((ᵙ)paramˉ[20]);
    this.ˊॱ = ((KV)paramˉ[6]);
    this.ˊॱ.setTag(null);
    this.ͺ = ((KW)paramˉ[7]);
    this.ͺ.setTag(null);
    this.ॱˋ = ((ImageView)paramˉ[1]);
    this.ॱˋ.setTag(null);
    this.ᐝॱ = ((TextView)paramˉ[8]);
    this.ᐝॱ.setTag(null);
    this.ॱᐝ = ((LinearLayout)paramˉ[17]);
    this.ʻॱ = ((TextView)paramˉ[18]);
    this.ॱˎ = ((pR)paramˉ[19]);
    this.ˈ = ((у)paramˉ[13]);
    this.ʿ = ((KV)paramˉ[5]);
    this.ʿ.setTag(null);
    ˋ(paramView);
    ˊॱ();
  }
  
  static void ˋॱ()
  {
    break label9;
    int i = 28;
    break label61;
    label9:
    break label119;
    for (;;)
    {
      i = ˎˎ + 97;
      ˋᐝ = i % 128;
      if (i % 2 != 0) {
        break;
      }
      i = 25;
      try
      {
        ˊˋ = 7;
      }
      catch (Exception localException)
      {
        throw localException;
      }
      ˊˋ = -102;
    }
    switch (i)
    {
    default: 
      return;
    case 28: 
      for (;;)
      {
        label61:
        switch (i)
        {
        }
        break;
        label119:
        i = ˋᐝ + 69;
        ˎˎ = i % 128;
        if (i % 2 == 0) {
          i = 23;
        } else {
          i = 17;
        }
      }
    }
    i = 60 / 0;
  }
  
  /* Error */
  private static String ˏ(int[] paramArrayOfInt, int paramInt)
  {
    // Byte code:
    //   0: goto +236 -> 236
    //   3: astore_0
    //   4: aload_0
    //   5: athrow
    //   6: iload_2
    //   7: lookupswitch	default:+25->32, 38:+232->239, 39:+60->67
    //   32: goto +35 -> 67
    //   35: bipush 39
    //   37: istore_2
    //   38: goto -32 -> 6
    //   41: iload_2
    //   42: tableswitch	default:+22->64, 0:+305->347, 1:+310->352
    //   64: goto +283 -> 347
    //   67: iconst_2
    //   68: newarray char
    //   70: astore 5
    //   72: aload_0
    //   73: arraylength
    //   74: iconst_1
    //   75: ishl
    //   76: newarray char
    //   78: astore 6
    //   80: getstatic 194	o/JM:ˋˋ	[I
    //   83: astore 4
    //   85: aload 4
    //   87: invokevirtual 199	[I:clone	()Ljava/lang/Object;
    //   90: astore 4
    //   92: aload 4
    //   94: checkcast 195	[I
    //   97: astore 4
    //   99: iconst_1
    //   100: istore_2
    //   101: goto +119 -> 220
    //   104: astore_0
    //   105: aload_0
    //   106: athrow
    //   107: aload 5
    //   109: iconst_0
    //   110: aload 7
    //   112: iload_2
    //   113: iaload
    //   114: bipush 16
    //   116: ishr
    //   117: i2c
    //   118: castore
    //   119: aload 5
    //   121: iconst_1
    //   122: aload 7
    //   124: iload_2
    //   125: iaload
    //   126: i2c
    //   127: castore
    //   128: aload 5
    //   130: iconst_2
    //   131: aload 7
    //   133: iload_2
    //   134: iconst_1
    //   135: iadd
    //   136: iaload
    //   137: bipush 16
    //   139: ishr
    //   140: i2c
    //   141: castore
    //   142: aload 5
    //   144: iconst_3
    //   145: aload 7
    //   147: iload_2
    //   148: iconst_1
    //   149: iadd
    //   150: iaload
    //   151: i2c
    //   152: castore
    //   153: aload 5
    //   155: aload 4
    //   157: iconst_0
    //   158: invokestatic 204	o/oN:ˏ	([C[IZ)[I
    //   161: pop
    //   162: aload 6
    //   164: iload_2
    //   165: iconst_1
    //   166: ishl
    //   167: aload 5
    //   169: iconst_0
    //   170: caload
    //   171: castore
    //   172: aload 6
    //   174: iload_2
    //   175: iconst_1
    //   176: ishl
    //   177: iconst_1
    //   178: iadd
    //   179: aload 5
    //   181: iconst_1
    //   182: caload
    //   183: castore
    //   184: aload 6
    //   186: iload_2
    //   187: iconst_1
    //   188: ishl
    //   189: iconst_2
    //   190: iadd
    //   191: aload 5
    //   193: iconst_2
    //   194: caload
    //   195: castore
    //   196: aload 6
    //   198: iload_2
    //   199: iconst_1
    //   200: ishl
    //   201: iconst_3
    //   202: iadd
    //   203: aload 5
    //   205: iconst_3
    //   206: caload
    //   207: castore
    //   208: iload_2
    //   209: iconst_2
    //   210: iadd
    //   211: istore_3
    //   212: goto +145 -> 357
    //   215: iconst_1
    //   216: istore_2
    //   217: goto -176 -> 41
    //   220: aload_0
    //   221: astore 7
    //   223: iload_2
    //   224: aload 7
    //   226: arraylength
    //   227: if_icmpge +6 -> 233
    //   230: goto +44 -> 274
    //   233: goto +75 -> 308
    //   236: goto +84 -> 320
    //   239: iconst_4
    //   240: newarray char
    //   242: astore 5
    //   244: aload_0
    //   245: arraylength
    //   246: iconst_1
    //   247: ishl
    //   248: newarray char
    //   250: astore 6
    //   252: getstatic 194	o/JM:ˋˋ	[I
    //   255: invokevirtual 199	[I:clone	()Ljava/lang/Object;
    //   258: checkcast 195	[I
    //   261: astore 4
    //   263: iconst_0
    //   264: istore_2
    //   265: goto -45 -> 220
    //   268: bipush 38
    //   270: istore_2
    //   271: goto -265 -> 6
    //   274: getstatic 59	o/JM:ˎˎ	I
    //   277: iconst_1
    //   278: iadd
    //   279: istore_3
    //   280: iload_3
    //   281: sipush 128
    //   284: irem
    //   285: putstatic 61	o/JM:ˋᐝ	I
    //   288: iload_3
    //   289: iconst_2
    //   290: irem
    //   291: ifne +6 -> 297
    //   294: goto +11 -> 305
    //   297: goto -190 -> 107
    //   300: iconst_0
    //   301: istore_2
    //   302: goto -261 -> 41
    //   305: goto -198 -> 107
    //   308: new 206	java/lang/String
    //   311: dup
    //   312: aload 6
    //   314: iconst_0
    //   315: iload_1
    //   316: invokespecial 209	java/lang/String:<init>	([CII)V
    //   319: areturn
    //   320: getstatic 61	o/JM:ˋᐝ	I
    //   323: bipush 81
    //   325: iadd
    //   326: istore_2
    //   327: iload_2
    //   328: sipush 128
    //   331: irem
    //   332: putstatic 59	o/JM:ˎˎ	I
    //   335: iload_2
    //   336: iconst_2
    //   337: irem
    //   338: ifeq +6 -> 344
    //   341: goto -306 -> 35
    //   344: goto -76 -> 268
    //   347: iload_3
    //   348: istore_2
    //   349: goto -129 -> 220
    //   352: iload_3
    //   353: istore_2
    //   354: goto -134 -> 220
    //   357: getstatic 59	o/JM:ˎˎ	I
    //   360: bipush 77
    //   362: iadd
    //   363: istore_2
    //   364: iload_2
    //   365: sipush 128
    //   368: irem
    //   369: putstatic 61	o/JM:ˋᐝ	I
    //   372: iload_2
    //   373: iconst_2
    //   374: irem
    //   375: ifne +6 -> 381
    //   378: goto -78 -> 300
    //   381: goto -166 -> 215
    // Local variable table:
    //   start	length	slot	name	signature
    //   0	384	0	paramArrayOfInt	int[]
    //   0	384	1	paramInt	int
    //   6	369	2	i	int
    //   211	142	3	j	int
    //   83	179	4	localObject	Object
    //   70	173	5	arrayOfChar1	char[]
    //   78	235	6	arrayOfChar2	char[]
    //   110	115	7	arrayOfInt	int[]
    // Exception table:
    //   from	to	target	type
    //   92	99	3	java/lang/Exception
    //   80	85	104	java/lang/Exception
    //   85	92	104	java/lang/Exception
    //   92	99	104	java/lang/Exception
    //   153	162	104	java/lang/Exception
  }
  
  static void ˏॱ()
  {
    ˋˋ = new int[] { 257091913, 1045955939, 1405392637, -267509578, -1566364339, 711629080, -1942181744, 120698701, 1302377766, -1959910445, 986315036, -1810727670, 811771160, -518446974, 1090686082, -729101199, -1853930272, -1665163788 };
  }
  
  /* Error */
  private String ॱ(String paramString)
  {
    // Byte code:
    //   0: goto +34 -> 34
    //   3: iload_2
    //   4: lookupswitch	default:+28->32, 32:+109->113, 62:+216->220
    //   32: aload_1
    //   33: areturn
    //   34: goto +193 -> 227
    //   37: getstatic 59	o/JM:ˎˎ	I
    //   40: bipush 43
    //   42: iadd
    //   43: istore_3
    //   44: iload_3
    //   45: sipush 128
    //   48: irem
    //   49: putstatic 61	o/JM:ˋᐝ	I
    //   52: iload_3
    //   53: iconst_2
    //   54: irem
    //   55: ifne +6 -> 61
    //   58: goto +132 -> 190
    //   61: goto +224 -> 285
    //   64: aload_1
    //   65: arraylength
    //   66: istore_3
    //   67: iload_2
    //   68: iload_3
    //   69: if_icmpge +6 -> 75
    //   72: goto +216 -> 288
    //   75: goto +106 -> 181
    //   78: bipush 32
    //   80: istore_2
    //   81: goto -78 -> 3
    //   84: getstatic 59	o/JM:ˎˎ	I
    //   87: istore_3
    //   88: iload_3
    //   89: bipush 63
    //   91: iadd
    //   92: istore_3
    //   93: iload_3
    //   94: sipush 128
    //   97: irem
    //   98: putstatic 61	o/JM:ˋᐝ	I
    //   101: iload_3
    //   102: iconst_2
    //   103: irem
    //   104: ifne +6 -> 110
    //   107: goto +80 -> 187
    //   110: goto +37 -> 147
    //   113: aload_1
    //   114: areturn
    //   115: iload_3
    //   116: lookupswitch	default:+28->144, 21:+181->297, 45:+-32->84
    //   144: goto -60 -> 84
    //   147: aload 4
    //   149: iload_2
    //   150: aload_1
    //   151: aload_1
    //   152: arraylength
    //   153: iload_2
    //   154: isub
    //   155: iconst_1
    //   156: isub
    //   157: baload
    //   158: getstatic 190	o/JM:ˊˋ	B
    //   161: ixor
    //   162: i2b
    //   163: bastore
    //   164: iload_2
    //   165: iconst_1
    //   166: iadd
    //   167: istore_2
    //   168: goto -131 -> 37
    //   171: astore_1
    //   172: new 232	java/lang/RuntimeException
    //   175: dup
    //   176: aload_1
    //   177: invokespecial 235	java/lang/RuntimeException:<init>	(Ljava/lang/Throwable;)V
    //   180: athrow
    //   181: bipush 21
    //   183: istore_3
    //   184: goto -69 -> 115
    //   187: goto -40 -> 147
    //   190: goto +95 -> 285
    //   193: getstatic 59	o/JM:ˎˎ	I
    //   196: bipush 57
    //   198: iadd
    //   199: istore_2
    //   200: iload_2
    //   201: sipush 128
    //   204: irem
    //   205: putstatic 61	o/JM:ˋᐝ	I
    //   208: iload_2
    //   209: iconst_2
    //   210: irem
    //   211: ifne +6 -> 217
    //   214: goto +126 -> 340
    //   217: goto -139 -> 78
    //   220: bipush 60
    //   222: iconst_0
    //   223: idiv
    //   224: istore_2
    //   225: aload_1
    //   226: areturn
    //   227: aload_1
    //   228: bipush 6
    //   230: newarray int
    //   232: dup
    //   233: iconst_0
    //   234: ldc -20
    //   236: iastore
    //   237: dup
    //   238: iconst_1
    //   239: ldc -19
    //   241: iastore
    //   242: dup
    //   243: iconst_2
    //   244: ldc -18
    //   246: iastore
    //   247: dup
    //   248: iconst_3
    //   249: ldc -17
    //   251: iastore
    //   252: dup
    //   253: iconst_4
    //   254: ldc -16
    //   256: iastore
    //   257: dup
    //   258: iconst_5
    //   259: ldc -15
    //   261: iastore
    //   262: bipush 10
    //   264: invokestatic 243	o/JM:ˏ	([II)Ljava/lang/String;
    //   267: invokevirtual 247	java/lang/String:intern	()Ljava/lang/String;
    //   270: invokevirtual 251	java/lang/String:getBytes	(Ljava/lang/String;)[B
    //   273: astore_1
    //   274: aload_1
    //   275: arraylength
    //   276: newarray byte
    //   278: astore 4
    //   280: iconst_0
    //   281: istore_2
    //   282: goto -218 -> 64
    //   285: goto -221 -> 64
    //   288: bipush 45
    //   290: istore_3
    //   291: goto -176 -> 115
    //   294: astore_1
    //   295: aload_1
    //   296: athrow
    //   297: new 206	java/lang/String
    //   300: dup
    //   301: aload 4
    //   303: iconst_4
    //   304: newarray int
    //   306: dup
    //   307: iconst_0
    //   308: ldc -4
    //   310: iastore
    //   311: dup
    //   312: iconst_1
    //   313: ldc -3
    //   315: iastore
    //   316: dup
    //   317: iconst_2
    //   318: ldc -2
    //   320: iastore
    //   321: dup
    //   322: iconst_3
    //   323: ldc -1
    //   325: iastore
    //   326: iconst_5
    //   327: invokestatic 243	o/JM:ˏ	([II)Ljava/lang/String;
    //   330: invokevirtual 247	java/lang/String:intern	()Ljava/lang/String;
    //   333: invokespecial 258	java/lang/String:<init>	([BLjava/lang/String;)V
    //   336: astore_1
    //   337: goto -144 -> 193
    //   340: bipush 62
    //   342: istore_2
    //   343: goto -340 -> 3
    //   346: astore_1
    //   347: aload_1
    //   348: athrow
    // Local variable table:
    //   start	length	slot	name	signature
    //   0	349	0	this	JM
    //   0	349	1	paramString	String
    //   3	340	2	i	int
    //   43	248	3	j	int
    //   147	155	4	arrayOfByte	byte[]
    // Exception table:
    //   from	to	target	type
    //   64	67	171	java/io/UnsupportedEncodingException
    //   147	164	171	java/io/UnsupportedEncodingException
    //   227	280	171	java/io/UnsupportedEncodingException
    //   297	337	171	java/io/UnsupportedEncodingException
    //   37	44	294	java/lang/Exception
    //   44	52	294	java/lang/Exception
    //   84	88	294	java/lang/Exception
    //   93	101	346	java/lang/Exception
  }
  
  public void ˊ(boolean paramBoolean)
  {
    this.ˊˊ = paramBoolean;
    try
    {
      this.ˉ |= 0x2;
    }
    finally
    {
      localObject = finally;
      throw localObject;
    }
    ˊ(60);
    super.ʽ();
  }
  
  public void ˊॱ()
  {
    try
    {
      this.ˉ = 4L;
    }
    finally
    {
      localObject = finally;
      throw localObject;
    }
    ʽ();
  }
  
  public void ˎ(boolean paramBoolean)
  {
    this.ˊᐝ = paramBoolean;
    try
    {
      this.ˉ |= 1L;
    }
    finally
    {
      localObject = finally;
      throw localObject;
    }
    ˊ(67);
    super.ʽ();
  }
  
  public void ˏ()
  {
    String str2 = ˏ(new int[] { -1387974745, 1642815459 }, 4).intern();
    long l2;
    try
    {
      l2 = this.ˉ;
      this.ˉ = 0L;
    }
    finally
    {
      localObject1 = finally;
      throw localObject1;
    }
    int j = 0;
    boolean bool2 = false;
    boolean bool3 = this.ˊᐝ;
    Object localObject2 = null;
    boolean bool4 = this.ˊˊ;
    long l3 = l2;
    Object localObject3;
    if ((0x5 & l2) != 0L)
    {
      long l1 = l2;
      if ((0x5 & l2) != 0L) {
        if (bool3) {
          l1 = l2 | 0x10 | 0x40;
        } else {
          l1 = l2 | 0x8 | 0x20;
        }
      }
      int i;
      if (bool3) {
        i = 4;
      } else {
        i = 0;
      }
      boolean bool1;
      if (!bool3) {
        bool1 = true;
      } else {
        bool1 = false;
      }
      if (bool3)
      {
        localObject3 = this.ʼ.getResources().getString(2131755189);
        localObject2 = localObject3;
        if (((String)localObject3).startsWith(str2)) {
          localObject2 = ॱ(((String)localObject3).substring(4)).intern();
        }
        l3 = l1;
        j = i;
        bool2 = bool1;
      }
      else
      {
        localObject3 = this.ʼ.getResources().getString(2131755190);
        l3 = l1;
        j = i;
        bool2 = bool1;
        localObject2 = localObject3;
        if (((String)localObject3).startsWith(str2))
        {
          localObject2 = ॱ(((String)localObject3).substring(4)).intern();
          bool2 = bool1;
          j = i;
          l3 = l1;
        }
      }
    }
    if ((0x4 & l3) != 0L)
    {
      Object localObject4 = this.ॱ;
      String str1 = this.ॱ.getResources().getString(2131755082);
      localObject3 = str1;
      if (str1.startsWith(str2)) {
        localObject3 = ॱ(str1.substring(4)).intern();
      }
      ʹ.ˊ((TextView)localObject4, (CharSequence)localObject3);
      r.ˊ(this.ʽ, ˏ(new int[] { -1848432101, -1986962681, -861620223, 2117901631, 69532248, 1861325853, -1936654556, 1240014958, 1875802895, 1583993101, 938574225, -335320327, -1870081768, -355232196, -837783140, 1648752092, -1410044252, 1367480671, 821000748, 357509130, -1047404979, 1849457779, -1983781592, -993433161, -247402743, -763958872, -953047304, 18650712, 487376151, 487971380, 1013208993, -35665836, -929669344, -570044550, -1216041357, 1544025428, -1887774157, -782565466, -1905285836, -2102975113 }, 77).intern(), ॱ(this.ʽ, 2131230827), true);
      r.ˊ(this.ॱˊ, ˏ(new int[] { -1848432101, -1986962681, -861620223, 2117901631, 69532248, 1861325853, -1936654556, 1240014958, 1875802895, 1583993101, 938574225, -335320327, -1870081768, -355232196, -837783140, 1648752092, -1410044252, 1367480671, 821000748, 357509130, -1047404979, 1849457779, -1983781592, -993433161, -247402743, -763958872, -953047304, 18650712, 487376151, 487971380, -1124927895, 196573027, 1008354001, 97484303, -1929412844, 1645659055, -1887774157, -782565466, -1905285836, -2102975113 }, 77).intern(), ॱ(this.ॱˊ, 2131230823), true);
      this.ˊॱ.setForegroundTint(ˏ(this.ˊॱ, 2131099727));
      this.ˊॱ.setIcon(ॱ(this.ˊॱ, 2131231178));
      this.ˊॱ.setInfo("");
      localObject4 = this.ˊॱ;
      str1 = this.ˊॱ.getResources().getString(2131755328);
      localObject3 = str1;
      if (str1.startsWith(str2)) {
        localObject3 = ॱ(str1.substring(4)).intern();
      }
      ((KV)localObject4).setTitle((String)localObject3);
      r.ˊ(this.ॱˋ, ˏ(new int[] { -1848432101, -1986962681, -861620223, 2117901631, 69532248, 1861325853, -1936654556, 1240014958, 1875802895, 1583993101, 938574225, -335320327, -1870081768, -355232196, -837783140, 1648752092, -1410044252, 1367480671, 821000748, 357509130, -1047404979, 1849457779, -1983781592, -993433161, -247402743, -763958872, -953047304, 18650712, 487376151, 487971380, 495855893, 69906371, -554018600, -795635882, 1256772044, -25643000, 1976126956, -954843342 }, 74).intern(), ॱ(this.ॱˋ, 2131230828), true);
      localObject4 = this.ᐝॱ;
      str1 = this.ᐝॱ.getResources().getString(2131755573);
      localObject3 = str1;
      if (str1.startsWith(str2)) {
        localObject3 = ॱ(str1.substring(4)).intern();
      }
      ʹ.ˊ((TextView)localObject4, (CharSequence)localObject3);
      this.ʿ.setForegroundTint(ˏ(this.ʿ, 2131099727));
      this.ʿ.setIcon(ॱ(this.ʿ, 2131231174));
      this.ʿ.setInfo("");
      localObject4 = this.ʿ;
      str1 = this.ʿ.getResources().getString(2131755610);
      localObject3 = str1;
      if (str1.startsWith(str2)) {
        localObject3 = ॱ(str1.substring(4)).intern();
      }
      ((KV)localObject4).setTitle((String)localObject3);
    }
    if ((0x5 & l3) != 0L)
    {
      this.ʼ.setPaymentHint((String)localObject2);
      this.ˋˊ.setVisibility(j);
      this.ʿ.setEnabled(bool2);
    }
    if ((0x6 & l3) != 0L) {
      this.ͺ.setDisabled(bool4);
    }
  }
  
  public boolean ˏ(int paramInt1, Object paramObject, int paramInt2)
  {
    for (;;)
    {
      break;
      paramInt1 = 35;
      break label18;
      break label82;
      break;
      label18:
      switch (paramInt1)
      {
      }
      continue;
      label47:
      return false;
    }
    for (;;)
    {
      paramInt1 = 46;
      break label18;
      paramInt1 = ˎˎ + 53;
      ˋᐝ = paramInt1 % 128;
      if (paramInt1 % 2 == 0) {
        break label47;
      }
      break label47;
      label82:
      paramInt1 = ˋᐝ + 91;
      ˎˎ = paramInt1 % 128;
      if (paramInt1 % 2 != 0) {
        break;
      }
    }
  }
  
  /* Error */
  public boolean ͺ()
  {
    // Byte code:
    //   0: goto +37 -> 37
    //   3: iload_2
    //   4: ireturn
    //   5: astore_3
    //   6: aload_3
    //   7: athrow
    //   8: iload_1
    //   9: tableswitch	default:+23->32, 0:+-6->3, 1:+73->82
    //   32: iload_2
    //   33: ireturn
    //   34: astore_3
    //   35: aload_3
    //   36: athrow
    //   37: getstatic 59	o/JM:ˎˎ	I
    //   40: bipush 55
    //   42: iadd
    //   43: istore_1
    //   44: iload_1
    //   45: sipush 128
    //   48: irem
    //   49: putstatic 61	o/JM:ˋᐝ	I
    //   52: iload_1
    //   53: iconst_2
    //   54: irem
    //   55: ifne +6 -> 61
    //   58: goto +16 -> 74
    //   61: aload_0
    //   62: getfield 261	o/JM:ˊˊ	Z
    //   65: istore_2
    //   66: goto +21 -> 87
    //   69: iconst_1
    //   70: istore_1
    //   71: goto -63 -> 8
    //   74: goto -13 -> 61
    //   77: iconst_0
    //   78: istore_1
    //   79: goto -71 -> 8
    //   82: aconst_null
    //   83: arraylength
    //   84: istore_1
    //   85: iload_2
    //   86: ireturn
    //   87: getstatic 59	o/JM:ˎˎ	I
    //   90: bipush 49
    //   92: iadd
    //   93: istore_1
    //   94: iload_1
    //   95: sipush 128
    //   98: irem
    //   99: putstatic 61	o/JM:ˋᐝ	I
    //   102: iload_1
    //   103: iconst_2
    //   104: irem
    //   105: ifne +6 -> 111
    //   108: goto -39 -> 69
    //   111: goto -34 -> 77
    // Local variable table:
    //   start	length	slot	name	signature
    //   0	114	0	this	JM
    //   8	97	1	i	int
    //   3	83	2	bool	boolean
    //   5	2	3	localException1	Exception
    //   34	2	3	localException2	Exception
    // Exception table:
    //   from	to	target	type
    //   87	94	5	java/lang/Exception
    //   94	102	5	java/lang/Exception
    //   94	102	34	java/lang/Exception
  }
  
  public boolean ॱ()
  {
    try
    {
      long l = this.ˉ;
      if (l != 0L) {
        return true;
      }
    }
    finally
    {
      localObject = finally;
      throw localObject;
    }
    return false;
  }
}
