package o;

import android.content.res.Resources;
import android.databinding.ViewDataBinding;
import android.databinding.ViewDataBinding.If;
import android.util.SparseIntArray;
import android.widget.ImageView;
import android.widget.ScrollView;
import android.widget.TextView;

public class JN
  extends ViewDataBinding
{
  private static char ˊˊ;
  private static char ˊˋ;
  private static char ˊᐝ;
  private static byte ˋˊ;
  private static int ˋᐝ;
  private static int ˍ;
  private static char ˎˎ;
  private static final ViewDataBinding.If ॱˊ;
  private static final SparseIntArray ॱˋ;
  public final TextView ʻ;
  private final TextView ʻॱ;
  public final TextView ʼ;
  private String ʼॱ;
  public final TextView ʽ;
  private String ʽॱ;
  private String ʾ;
  private coN ʿ;
  private String ˈ;
  private long ˉ;
  public final TextView ˊ;
  public final TextView ˊॱ;
  public final ImageView ˋॱ;
  public final TextView ˎ;
  public final TextView ˏॱ;
  public final TextView ͺ;
  public final TextView ॱ;
  private final ScrollView ॱˎ;
  public final TextView ॱॱ;
  private final TextView ॱᐝ;
  public final TextView ᐝ;
  private final TextView ᐝॱ;
  
  static
  {
    break label56;
    return;
    for (;;)
    {
      int i;
      switch (i)
      {
      case 1: 
      default: 
        return;
        for (;;)
        {
          i = ˋᐝ + 25;
          ˍ = i % 128;
          if (i % 2 != 0) {
            break label108;
          }
          break;
          ˍ = 0;
          ˋᐝ = 1;
          ˊॱ();
          ॱˊ();
          ॱˊ = null;
          ॱˋ = new SparseIntArray();
          ॱˋ.put(2131296752, 15);
        }
        i = 1;
        break;
      case 0: 
        label56:
        i = 15 / 0;
        return;
        label108:
        i = 0;
      }
    }
  }
  
  /* Error */
  public JN(ˉ paramˉ, android.view.View paramView)
  {
    // Byte code:
    //   0: aload_0
    //   1: aload_1
    //   2: aload_2
    //   3: iconst_1
    //   4: invokespecial 77	android/databinding/ViewDataBinding:<init>	(Lo/ˉ;Landroid/view/View;I)V
    //   7: aload_0
    //   8: ldc2_w 78
    //   11: putfield 81	o/JN:ˉ	J
    //   14: getstatic 58	o/JN:ॱˊ	Landroid/databinding/ViewDataBinding$If;
    //   17: astore_3
    //   18: getstatic 65	o/JN:ॱˋ	Landroid/util/SparseIntArray;
    //   21: astore 4
    //   23: aload_1
    //   24: aload_2
    //   25: bipush 16
    //   27: aload_3
    //   28: aload 4
    //   30: invokestatic 84	o/JN:ॱ	(Lo/ˉ;Landroid/view/View;ILandroid/databinding/ViewDataBinding$If;Landroid/util/SparseIntArray;)[Ljava/lang/Object;
    //   33: astore_1
    //   34: aload_0
    //   35: aload_1
    //   36: bipush 14
    //   38: aaload
    //   39: checkcast 86	android/widget/TextView
    //   42: putfield 88	o/JN:ॱ	Landroid/widget/TextView;
    //   45: aload_0
    //   46: getfield 88	o/JN:ॱ	Landroid/widget/TextView;
    //   49: aconst_null
    //   50: invokevirtual 92	android/widget/TextView:setTag	(Ljava/lang/Object;)V
    //   53: aload_0
    //   54: aload_1
    //   55: bipush 8
    //   57: aaload
    //   58: checkcast 86	android/widget/TextView
    //   61: putfield 94	o/JN:ˊ	Landroid/widget/TextView;
    //   64: aload_0
    //   65: getfield 94	o/JN:ˊ	Landroid/widget/TextView;
    //   68: aconst_null
    //   69: invokevirtual 92	android/widget/TextView:setTag	(Ljava/lang/Object;)V
    //   72: aload_0
    //   73: aload_1
    //   74: iconst_0
    //   75: aaload
    //   76: checkcast 96	android/widget/ScrollView
    //   79: putfield 98	o/JN:ॱˎ	Landroid/widget/ScrollView;
    //   82: aload_0
    //   83: getfield 98	o/JN:ॱˎ	Landroid/widget/ScrollView;
    //   86: aconst_null
    //   87: invokevirtual 99	android/widget/ScrollView:setTag	(Ljava/lang/Object;)V
    //   90: aload_0
    //   91: aload_1
    //   92: bipush 11
    //   94: aaload
    //   95: checkcast 86	android/widget/TextView
    //   98: putfield 101	o/JN:ᐝॱ	Landroid/widget/TextView;
    //   101: aload_0
    //   102: getfield 101	o/JN:ᐝॱ	Landroid/widget/TextView;
    //   105: aconst_null
    //   106: invokevirtual 92	android/widget/TextView:setTag	(Ljava/lang/Object;)V
    //   109: aload_0
    //   110: aload_1
    //   111: bipush 7
    //   113: aaload
    //   114: checkcast 86	android/widget/TextView
    //   117: putfield 103	o/JN:ʻॱ	Landroid/widget/TextView;
    //   120: aload_0
    //   121: getfield 103	o/JN:ʻॱ	Landroid/widget/TextView;
    //   124: aconst_null
    //   125: invokevirtual 92	android/widget/TextView:setTag	(Ljava/lang/Object;)V
    //   128: aload_0
    //   129: aload_1
    //   130: bipush 9
    //   132: aaload
    //   133: checkcast 86	android/widget/TextView
    //   136: putfield 105	o/JN:ॱᐝ	Landroid/widget/TextView;
    //   139: aload_0
    //   140: getfield 105	o/JN:ॱᐝ	Landroid/widget/TextView;
    //   143: aconst_null
    //   144: invokevirtual 92	android/widget/TextView:setTag	(Ljava/lang/Object;)V
    //   147: aload_0
    //   148: aload_1
    //   149: bipush 10
    //   151: aaload
    //   152: checkcast 86	android/widget/TextView
    //   155: putfield 107	o/JN:ˎ	Landroid/widget/TextView;
    //   158: aload_0
    //   159: getfield 107	o/JN:ˎ	Landroid/widget/TextView;
    //   162: aconst_null
    //   163: invokevirtual 92	android/widget/TextView:setTag	(Ljava/lang/Object;)V
    //   166: aload_0
    //   167: aload_1
    //   168: bipush 12
    //   170: aaload
    //   171: checkcast 86	android/widget/TextView
    //   174: putfield 109	o/JN:ʽ	Landroid/widget/TextView;
    //   177: aload_0
    //   178: getfield 109	o/JN:ʽ	Landroid/widget/TextView;
    //   181: aconst_null
    //   182: invokevirtual 92	android/widget/TextView:setTag	(Ljava/lang/Object;)V
    //   185: aload_0
    //   186: aload_1
    //   187: iconst_4
    //   188: aaload
    //   189: checkcast 86	android/widget/TextView
    //   192: putfield 111	o/JN:ᐝ	Landroid/widget/TextView;
    //   195: aload_0
    //   196: getfield 111	o/JN:ᐝ	Landroid/widget/TextView;
    //   199: aconst_null
    //   200: invokevirtual 92	android/widget/TextView:setTag	(Ljava/lang/Object;)V
    //   203: aload_0
    //   204: aload_1
    //   205: iconst_5
    //   206: aaload
    //   207: checkcast 86	android/widget/TextView
    //   210: putfield 113	o/JN:ॱॱ	Landroid/widget/TextView;
    //   213: aload_0
    //   214: getfield 113	o/JN:ॱॱ	Landroid/widget/TextView;
    //   217: aconst_null
    //   218: invokevirtual 92	android/widget/TextView:setTag	(Ljava/lang/Object;)V
    //   221: aload_0
    //   222: aload_1
    //   223: iconst_3
    //   224: aaload
    //   225: checkcast 86	android/widget/TextView
    //   228: putfield 115	o/JN:ʼ	Landroid/widget/TextView;
    //   231: aload_0
    //   232: getfield 115	o/JN:ʼ	Landroid/widget/TextView;
    //   235: aconst_null
    //   236: invokevirtual 92	android/widget/TextView:setTag	(Ljava/lang/Object;)V
    //   239: aload_0
    //   240: aload_1
    //   241: iconst_2
    //   242: aaload
    //   243: checkcast 86	android/widget/TextView
    //   246: putfield 117	o/JN:ʻ	Landroid/widget/TextView;
    //   249: aload_0
    //   250: getfield 117	o/JN:ʻ	Landroid/widget/TextView;
    //   253: aconst_null
    //   254: invokevirtual 92	android/widget/TextView:setTag	(Ljava/lang/Object;)V
    //   257: aload_0
    //   258: aload_1
    //   259: bipush 15
    //   261: aaload
    //   262: checkcast 119	android/widget/ImageView
    //   265: putfield 121	o/JN:ˋॱ	Landroid/widget/ImageView;
    //   268: aload_0
    //   269: aload_1
    //   270: bipush 13
    //   272: aaload
    //   273: checkcast 86	android/widget/TextView
    //   276: putfield 123	o/JN:ͺ	Landroid/widget/TextView;
    //   279: aload_0
    //   280: getfield 123	o/JN:ͺ	Landroid/widget/TextView;
    //   283: aconst_null
    //   284: invokevirtual 92	android/widget/TextView:setTag	(Ljava/lang/Object;)V
    //   287: aload_0
    //   288: aload_1
    //   289: bipush 6
    //   291: aaload
    //   292: checkcast 86	android/widget/TextView
    //   295: putfield 125	o/JN:ˊॱ	Landroid/widget/TextView;
    //   298: aload_0
    //   299: getfield 125	o/JN:ˊॱ	Landroid/widget/TextView;
    //   302: aconst_null
    //   303: invokevirtual 92	android/widget/TextView:setTag	(Ljava/lang/Object;)V
    //   306: aload_0
    //   307: aload_1
    //   308: iconst_1
    //   309: aaload
    //   310: checkcast 86	android/widget/TextView
    //   313: putfield 127	o/JN:ˏॱ	Landroid/widget/TextView;
    //   316: aload_0
    //   317: getfield 127	o/JN:ˏॱ	Landroid/widget/TextView;
    //   320: aconst_null
    //   321: invokevirtual 92	android/widget/TextView:setTag	(Ljava/lang/Object;)V
    //   324: aload_0
    //   325: aload_2
    //   326: invokevirtual 131	o/JN:ˋ	(Landroid/view/View;)V
    //   329: aload_0
    //   330: invokevirtual 133	o/JN:ˋॱ	()V
    //   333: return
    //   334: astore_1
    //   335: aload_1
    //   336: athrow
    //   337: astore_1
    //   338: aload_1
    //   339: athrow
    // Local variable table:
    //   start	length	slot	name	signature
    //   0	340	0	this	JN
    //   0	340	1	paramˉ	ˉ
    //   0	340	2	paramView	android.view.View
    //   17	11	3	localIf	ViewDataBinding.If
    //   21	8	4	localSparseIntArray	SparseIntArray
    // Exception table:
    //   from	to	target	type
    //   7	14	334	java/lang/Exception
    //   14	18	334	java/lang/Exception
    //   18	23	334	java/lang/Exception
    //   23	34	334	java/lang/Exception
    //   34	333	334	java/lang/Exception
    //   14	18	337	java/lang/Exception
  }
  
  /* Error */
  private String ˊ(String paramString)
  {
    // Byte code:
    //   0: goto +207 -> 207
    //   3: getstatic 50	o/JN:ˋᐝ	I
    //   6: bipush 57
    //   8: iadd
    //   9: istore_2
    //   10: iload_2
    //   11: sipush 128
    //   14: irem
    //   15: putstatic 52	o/JN:ˍ	I
    //   18: iload_2
    //   19: iconst_2
    //   20: irem
    //   21: ifeq +6 -> 27
    //   24: goto +149 -> 173
    //   27: goto +380 -> 407
    //   30: getstatic 50	o/JN:ˋᐝ	I
    //   33: bipush 51
    //   35: iadd
    //   36: istore_3
    //   37: iload_3
    //   38: sipush 128
    //   41: irem
    //   42: putstatic 52	o/JN:ˍ	I
    //   45: iload_3
    //   46: iconst_2
    //   47: irem
    //   48: ifeq +6 -> 54
    //   51: goto +159 -> 210
    //   54: goto +94 -> 148
    //   57: aload_1
    //   58: bipush 12
    //   60: newarray char
    //   62: dup
    //   63: iconst_0
    //   64: ldc -119
    //   66: castore
    //   67: dup
    //   68: iconst_1
    //   69: ldc -118
    //   71: castore
    //   72: dup
    //   73: iconst_2
    //   74: ldc -117
    //   76: castore
    //   77: dup
    //   78: iconst_3
    //   79: ldc -116
    //   81: castore
    //   82: dup
    //   83: iconst_4
    //   84: ldc -115
    //   86: castore
    //   87: dup
    //   88: iconst_5
    //   89: ldc -114
    //   91: castore
    //   92: dup
    //   93: bipush 6
    //   95: ldc -113
    //   97: castore
    //   98: dup
    //   99: bipush 7
    //   101: ldc -112
    //   103: castore
    //   104: dup
    //   105: bipush 8
    //   107: ldc -111
    //   109: castore
    //   110: dup
    //   111: bipush 9
    //   113: ldc -110
    //   115: castore
    //   116: dup
    //   117: bipush 10
    //   119: ldc -109
    //   121: castore
    //   122: dup
    //   123: bipush 11
    //   125: ldc -108
    //   127: castore
    //   128: invokestatic 152	o/JN:ˏ	([C)Ljava/lang/String;
    //   131: invokevirtual 158	java/lang/String:intern	()Ljava/lang/String;
    //   134: invokevirtual 162	java/lang/String:getBytes	(Ljava/lang/String;)[B
    //   137: astore 4
    //   139: aload 4
    //   141: arraylength
    //   142: newarray byte
    //   144: astore_1
    //   145: goto +182 -> 327
    //   148: aload_1
    //   149: iload_2
    //   150: aload 4
    //   152: aload 4
    //   154: arraylength
    //   155: iload_2
    //   156: isub
    //   157: iconst_1
    //   158: isub
    //   159: baload
    //   160: getstatic 164	o/JN:ˋˊ	B
    //   163: ixor
    //   164: i2b
    //   165: bastore
    //   166: iload_2
    //   167: iconst_1
    //   168: iadd
    //   169: istore_2
    //   170: goto +159 -> 329
    //   173: iconst_1
    //   174: istore_2
    //   175: goto +38 -> 213
    //   178: iload_3
    //   179: lookupswitch	default:+25->204, 27:+-149->30, 78:+171->350
    //   204: goto -174 -> 30
    //   207: goto -204 -> 3
    //   210: goto -62 -> 148
    //   213: iload_2
    //   214: tableswitch	default:+22->236, 0:+-157->57, 1:+25->239
    //   236: goto -179 -> 57
    //   239: aload_1
    //   240: bipush 12
    //   242: newarray char
    //   244: dup
    //   245: iconst_0
    //   246: ldc -119
    //   248: castore
    //   249: dup
    //   250: iconst_1
    //   251: ldc -118
    //   253: castore
    //   254: dup
    //   255: iconst_2
    //   256: ldc -117
    //   258: castore
    //   259: dup
    //   260: iconst_3
    //   261: ldc -116
    //   263: castore
    //   264: dup
    //   265: iconst_4
    //   266: ldc -115
    //   268: castore
    //   269: dup
    //   270: iconst_5
    //   271: ldc -114
    //   273: castore
    //   274: dup
    //   275: bipush 6
    //   277: ldc -113
    //   279: castore
    //   280: dup
    //   281: bipush 7
    //   283: ldc -112
    //   285: castore
    //   286: dup
    //   287: bipush 8
    //   289: ldc -111
    //   291: castore
    //   292: dup
    //   293: bipush 9
    //   295: ldc -110
    //   297: castore
    //   298: dup
    //   299: bipush 10
    //   301: ldc -109
    //   303: castore
    //   304: dup
    //   305: bipush 11
    //   307: ldc -108
    //   309: castore
    //   310: invokestatic 152	o/JN:ˏ	([C)Ljava/lang/String;
    //   313: invokevirtual 158	java/lang/String:intern	()Ljava/lang/String;
    //   316: invokevirtual 162	java/lang/String:getBytes	(Ljava/lang/String;)[B
    //   319: astore 4
    //   321: aload 4
    //   323: arraylength
    //   324: newarray byte
    //   326: astore_1
    //   327: iconst_0
    //   328: istore_2
    //   329: aload 4
    //   331: arraylength
    //   332: istore_3
    //   333: iload_2
    //   334: iload_3
    //   335: if_icmpge +6 -> 341
    //   338: goto +6 -> 344
    //   341: goto +60 -> 401
    //   344: bipush 27
    //   346: istore_3
    //   347: goto -169 -> 178
    //   350: new 154	java/lang/String
    //   353: dup
    //   354: aload_1
    //   355: bipush 6
    //   357: newarray char
    //   359: dup
    //   360: iconst_0
    //   361: ldc -91
    //   363: castore
    //   364: dup
    //   365: iconst_1
    //   366: ldc -90
    //   368: castore
    //   369: dup
    //   370: iconst_2
    //   371: ldc -89
    //   373: castore
    //   374: dup
    //   375: iconst_3
    //   376: ldc -88
    //   378: castore
    //   379: dup
    //   380: iconst_4
    //   381: ldc -115
    //   383: castore
    //   384: dup
    //   385: iconst_5
    //   386: ldc -114
    //   388: castore
    //   389: invokestatic 152	o/JN:ˏ	([C)Ljava/lang/String;
    //   392: invokevirtual 158	java/lang/String:intern	()Ljava/lang/String;
    //   395: invokespecial 171	java/lang/String:<init>	([BLjava/lang/String;)V
    //   398: astore_1
    //   399: aload_1
    //   400: areturn
    //   401: bipush 78
    //   403: istore_3
    //   404: goto -226 -> 178
    //   407: iconst_0
    //   408: istore_2
    //   409: goto -196 -> 213
    //   412: astore_1
    //   413: new 173	java/lang/RuntimeException
    //   416: dup
    //   417: aload_1
    //   418: invokespecial 176	java/lang/RuntimeException:<init>	(Ljava/lang/Throwable;)V
    //   421: athrow
    // Local variable table:
    //   start	length	slot	name	signature
    //   0	422	0	this	JN
    //   0	422	1	paramString	String
    //   9	400	2	i	int
    //   36	368	3	j	int
    //   137	193	4	arrayOfByte	byte[]
    // Exception table:
    //   from	to	target	type
    //   57	145	412	java/io/UnsupportedEncodingException
    //   148	166	412	java/io/UnsupportedEncodingException
    //   239	327	412	java/io/UnsupportedEncodingException
    //   329	333	412	java/io/UnsupportedEncodingException
    //   350	399	412	java/io/UnsupportedEncodingException
  }
  
  static void ˊॱ()
  {
    ˎˎ = '㗋';
    ˊᐝ = 60810;
    ˊˊ = 56640;
    ˊˋ = '⤿';
  }
  
  /* Error */
  private static String ˏ(char[] paramArrayOfChar)
  {
    // Byte code:
    //   0: goto +35 -> 35
    //   3: iload_2
    //   4: lookupswitch	default:+28->32, 21:+43->47, 54:+71->75
    //   32: goto +43 -> 75
    //   35: goto +123 -> 158
    //   38: astore_0
    //   39: aload_0
    //   40: athrow
    //   41: bipush 54
    //   43: istore_2
    //   44: goto -41 -> 3
    //   47: new 154	java/lang/String
    //   50: dup
    //   51: aload_3
    //   52: iconst_1
    //   53: aload_3
    //   54: iconst_0
    //   55: caload
    //   56: invokespecial 189	java/lang/String:<init>	([CII)V
    //   59: astore_0
    //   60: goto +139 -> 199
    //   63: iload_1
    //   64: aload_0
    //   65: arraylength
    //   66: if_icmpge +6 -> 72
    //   69: goto -28 -> 41
    //   72: goto +118 -> 190
    //   75: getstatic 52	o/JN:ˍ	I
    //   78: bipush 107
    //   80: iadd
    //   81: istore_2
    //   82: iload_2
    //   83: sipush 128
    //   86: irem
    //   87: putstatic 50	o/JN:ˋᐝ	I
    //   90: iload_2
    //   91: iconst_2
    //   92: irem
    //   93: ifne +6 -> 99
    //   96: goto +100 -> 196
    //   99: goto +3 -> 102
    //   102: aload 4
    //   104: iconst_0
    //   105: aload_0
    //   106: iload_1
    //   107: caload
    //   108: castore
    //   109: aload 4
    //   111: iconst_1
    //   112: aload_0
    //   113: iload_1
    //   114: iconst_1
    //   115: iadd
    //   116: caload
    //   117: castore
    //   118: aload 4
    //   120: getstatic 186	o/JN:ˊˋ	C
    //   123: getstatic 181	o/JN:ˊᐝ	C
    //   126: getstatic 184	o/JN:ˊˊ	C
    //   129: getstatic 178	o/JN:ˎˎ	C
    //   132: invokestatic 194	o/oP:ˏ	([CCCCC)V
    //   135: aload_3
    //   136: iload_1
    //   137: aload 4
    //   139: iconst_0
    //   140: caload
    //   141: castore
    //   142: aload_3
    //   143: iload_1
    //   144: iconst_1
    //   145: iadd
    //   146: aload 4
    //   148: iconst_1
    //   149: caload
    //   150: castore
    //   151: iload_1
    //   152: iconst_2
    //   153: iadd
    //   154: istore_1
    //   155: goto -92 -> 63
    //   158: getstatic 50	o/JN:ˋᐝ	I
    //   161: istore_1
    //   162: iload_1
    //   163: bipush 59
    //   165: iadd
    //   166: istore_1
    //   167: iload_1
    //   168: sipush 128
    //   171: irem
    //   172: putstatic 52	o/JN:ˍ	I
    //   175: iload_1
    //   176: iconst_2
    //   177: irem
    //   178: ifeq +6 -> 184
    //   181: goto +6 -> 187
    //   184: goto +40 -> 224
    //   187: goto +37 -> 224
    //   190: bipush 21
    //   192: istore_2
    //   193: goto -190 -> 3
    //   196: goto -94 -> 102
    //   199: getstatic 50	o/JN:ˋᐝ	I
    //   202: bipush 33
    //   204: iadd
    //   205: istore_1
    //   206: iload_1
    //   207: sipush 128
    //   210: irem
    //   211: putstatic 52	o/JN:ˍ	I
    //   214: iload_1
    //   215: iconst_2
    //   216: irem
    //   217: ifeq +5 -> 222
    //   220: aload_0
    //   221: areturn
    //   222: aload_0
    //   223: areturn
    //   224: aload_0
    //   225: arraylength
    //   226: newarray char
    //   228: astore_3
    //   229: iconst_0
    //   230: istore_1
    //   231: iconst_2
    //   232: newarray char
    //   234: astore 4
    //   236: goto -173 -> 63
    // Local variable table:
    //   start	length	slot	name	signature
    //   0	239	0	paramArrayOfChar	char[]
    //   63	168	1	i	int
    //   3	190	2	j	int
    //   51	178	3	arrayOfChar1	char[]
    //   102	133	4	arrayOfChar2	char[]
    // Exception table:
    //   from	to	target	type
    //   158	162	38	java/lang/Exception
    //   167	175	38	java/lang/Exception
  }
  
  private boolean ॱ(coN paramCoN, int paramInt)
  {
    if (paramInt == 0)
    {
      try
      {
        this.ˉ |= 1L;
      }
      finally
      {
        paramCoN = finally;
        throw paramCoN;
      }
      return true;
    }
    return false;
  }
  
  /* Error */
  static void ॱˊ()
  {
    // Byte code:
    //   0: goto +73 -> 73
    //   3: iconst_1
    //   4: istore_0
    //   5: goto +71 -> 76
    //   8: getstatic 52	o/JN:ˍ	I
    //   11: bipush 109
    //   13: iadd
    //   14: istore_0
    //   15: iload_0
    //   16: sipush 128
    //   19: irem
    //   20: putstatic 50	o/JN:ˋᐝ	I
    //   23: iload_0
    //   24: iconst_2
    //   25: irem
    //   26: ifne +6 -> 32
    //   29: goto -26 -> 3
    //   32: goto +6 -> 38
    //   35: astore_1
    //   36: aload_1
    //   37: athrow
    //   38: iconst_0
    //   39: istore_0
    //   40: goto +36 -> 76
    //   43: bipush 74
    //   45: putstatic 164	o/JN:ˋˊ	B
    //   48: getstatic 50	o/JN:ˋᐝ	I
    //   51: iconst_5
    //   52: iadd
    //   53: istore_0
    //   54: iload_0
    //   55: sipush 128
    //   58: irem
    //   59: putstatic 52	o/JN:ˍ	I
    //   62: iload_0
    //   63: iconst_2
    //   64: irem
    //   65: ifeq +6 -> 71
    //   68: goto +4 -> 72
    //   71: return
    //   72: return
    //   73: goto -65 -> 8
    //   76: iload_0
    //   77: tableswitch	default:+23->100, 0:+23->100, 1:+-34->43
    //   100: bipush -102
    //   102: putstatic 164	o/JN:ˋˊ	B
    //   105: goto -57 -> 48
    // Local variable table:
    //   start	length	slot	name	signature
    //   4	73	0	i	int
    //   35	2	1	localException	Exception
    // Exception table:
    //   from	to	target	type
    //   100	105	35	java/lang/Exception
  }
  
  public void ˋ(String paramString)
  {
    this.ʽॱ = paramString;
    try
    {
      this.ˉ |= 0x10;
    }
    finally
    {
      paramString = finally;
      throw paramString;
    }
    ˊ(122);
    super.ʽ();
  }
  
  public void ˋॱ()
  {
    try
    {
      this.ˉ = 64L;
    }
    finally
    {
      localObject = finally;
      throw localObject;
    }
    ʽ();
  }
  
  public void ˎ(String paramString)
  {
    this.ʾ = paramString;
    try
    {
      this.ˉ |= 0x4;
    }
    finally
    {
      paramString = finally;
      throw paramString;
    }
    ˊ(123);
    super.ʽ();
  }
  
  public void ˏ()
  {
    String str3 = ˏ(new char[] { -10236, -24300, -823, 12440, -725, -7105 }).intern();
    long l2;
    try
    {
      l2 = this.ˉ;
      this.ˉ = 0L;
    }
    finally
    {
      localObject1 = finally;
      throw localObject1;
    }
    String str4 = this.ʼॱ;
    String str2 = this.ʾ;
    int i = 0;
    Object localObject3 = this.ʽॱ;
    CharSequence localCharSequence2 = null;
    CharSequence localCharSequence3 = null;
    String str1 = this.ˈ;
    boolean bool = false;
    CharSequence localCharSequence1 = null;
    Object localObject2 = this.ʿ;
    if ((0x42 & l2) != 0L) {
      localCharSequence1 = aq.ʼ(str4);
    }
    if ((0x50 & l2) != 0L) {
      localCharSequence2 = aq.ʼ((String)localObject3);
    }
    if ((0x60 & l2) != 0L) {
      localCharSequence3 = aq.ʼ(str1);
    }
    long l1 = l2;
    if ((0x41 & l2) != 0L)
    {
      if (localObject2 != null) {
        bool = ((coN)localObject2).ˊ();
      }
      l1 = l2;
      if ((0x41 & l2) != 0L) {
        if (bool) {
          l1 = l2 | 0x100;
        } else {
          l1 = l2 | 0x80;
        }
      }
      if (bool) {
        i = 0;
      } else {
        i = 4;
      }
    }
    if ((0x40 & l1) != 0L)
    {
      localObject3 = this.ॱ;
      str1 = this.ॱ.getResources().getString(2131755617);
      localObject2 = str1;
      if (str1.startsWith(str3)) {
        localObject2 = ˊ(str1.substring(4)).intern();
      }
      ʹ.ˊ((TextView)localObject3, (CharSequence)localObject2);
      localObject3 = this.ᐝॱ;
      str1 = this.ᐝॱ.getResources().getString(2131755628);
      localObject2 = str1;
      if (str1.startsWith(str3)) {
        localObject2 = ˊ(str1.substring(4)).intern();
      }
      ʹ.ˊ((TextView)localObject3, (CharSequence)localObject2);
      localObject3 = this.ʻॱ;
      str1 = this.ʻॱ.getResources().getString(2131755621);
      localObject2 = str1;
      if (str1.startsWith(str3)) {
        localObject2 = ˊ(str1.substring(4)).intern();
      }
      ʹ.ˊ((TextView)localObject3, (CharSequence)localObject2);
      localObject3 = this.ॱᐝ;
      str1 = this.ॱᐝ.getResources().getString(2131755626);
      localObject2 = str1;
      if (str1.startsWith(str3)) {
        localObject2 = ˊ(str1.substring(4)).intern();
      }
      ʹ.ˊ((TextView)localObject3, (CharSequence)localObject2);
      localObject3 = this.ᐝ;
      str1 = this.ᐝ.getResources().getString(2131755614);
      localObject2 = str1;
      if (str1.startsWith(str3)) {
        localObject2 = ˊ(str1.substring(4)).intern();
      }
      ʹ.ˊ((TextView)localObject3, (CharSequence)localObject2);
      localObject3 = this.ॱॱ;
      str1 = this.ॱॱ.getResources().getString(2131755615);
      localObject2 = str1;
      if (str1.startsWith(str3)) {
        localObject2 = ˊ(str1.substring(4)).intern();
      }
      ʹ.ˊ((TextView)localObject3, (CharSequence)localObject2);
      localObject3 = this.ʼ;
      str1 = this.ʼ.getResources().getString(2131755616);
      localObject2 = str1;
      if (str1.startsWith(str3)) {
        localObject2 = ˊ(str1.substring(4)).intern();
      }
      ʹ.ˊ((TextView)localObject3, (CharSequence)localObject2);
      localObject3 = this.ʻ;
      str1 = this.ʻ.getResources().getString(2131755618);
      localObject2 = str1;
      if (str1.startsWith(str3)) {
        localObject2 = ˊ(str1.substring(4)).intern();
      }
      ʹ.ˊ((TextView)localObject3, (CharSequence)localObject2);
      localObject3 = this.ͺ;
      str1 = this.ͺ.getResources().getString(2131755622);
      localObject2 = str1;
      if (str1.startsWith(str3)) {
        localObject2 = ˊ(str1.substring(4)).intern();
      }
      ʹ.ˊ((TextView)localObject3, (CharSequence)localObject2);
      localObject3 = this.ˊॱ;
      str1 = this.ˊॱ.getResources().getString(2131755623);
      localObject2 = str1;
      if (str1.startsWith(str3)) {
        localObject2 = ˊ(str1.substring(4)).intern();
      }
      ʹ.ˊ((TextView)localObject3, (CharSequence)localObject2);
    }
    if ((0x60 & l1) != 0L) {
      ʹ.ˊ(this.ˊ, localCharSequence3);
    }
    if ((0x41 & l1) != 0L)
    {
      this.ᐝॱ.setVisibility(i);
      this.ʽ.setVisibility(i);
    }
    if ((0x42 & l1) != 0L) {
      ʹ.ˊ(this.ˎ, localCharSequence1);
    }
    if ((0x50 & l1) != 0L) {
      ʹ.ˊ(this.ʽ, localCharSequence2);
    }
    if ((0x44 & l1) != 0L) {
      ʹ.ˊ(this.ˏॱ, str2);
    }
  }
  
  public void ˏ(String paramString)
  {
    this.ʼॱ = paramString;
    try
    {
      this.ˉ |= 0x2;
    }
    finally
    {
      paramString = finally;
      throw paramString;
    }
    ˊ(114);
    super.ʽ();
  }
  
  public boolean ˏ(int paramInt1, Object paramObject, int paramInt2)
  {
    break label149;
    paramInt1 = 1;
    label74:
    label93:
    label149:
    for (;;)
    {
      switch (paramInt1)
      {
      default: 
        break;
      }
      boolean bool;
      for (;;)
      {
        paramInt1 = ˋᐝ + 83;
        ˍ = paramInt1 % 128;
        if (paramInt1 % 2 != 0) {
          break;
        }
        break label74;
        return false;
        try
        {
          bool = ॱ((coN)paramObject, paramInt2);
        }
        catch (Exception paramObject)
        {
          throw paramObject;
        }
        paramInt1 = 0;
        break label93;
      }
      for (;;)
      {
        throw new NullPointerException();
        switch (paramInt1)
        {
        }
      }
      paramInt1 = ˍ + 21;
      ˋᐝ = paramInt1 % 128;
      if (paramInt1 % 2 != 0) {
        return bool;
      }
      return bool;
    }
  }
  
  public void ॱ(String paramString)
  {
    this.ˈ = paramString;
    try
    {
      this.ˉ |= 0x20;
    }
    finally
    {
      paramString = finally;
      throw paramString;
    }
    ˊ(41);
    super.ʽ();
  }
  
  public void ॱ(coN paramCoN)
  {
    ˎ(0, paramCoN);
    this.ʿ = paramCoN;
    try
    {
      this.ˉ |= 1L;
    }
    finally
    {
      paramCoN = finally;
      throw paramCoN;
    }
    ˊ(83);
    super.ʽ();
  }
  
  public boolean ॱ()
  {
    try
    {
      long l = this.ˉ;
      if (l != 0L) {
        return true;
      }
    }
    finally
    {
      localObject = finally;
      throw localObject;
    }
    return false;
  }
}
