package o;

import ro.btrl.devoptions.di.module.DevOptionsModule;

public final class Jv
  implements qo<JB.ˊ>
{
  private static char[] ˎ = { 50, 105, 107, 110, 108, 105, 70, 73, 108, 100, 102, 111, 114, 112, 97, 72, 48, 66, 104, 103, 97, 102, 108, 112, 97, 71, 54, 77, 110, 110, 71, 64, 64, 70, 110, 112, 108, 67, 70, 108, 112, 113, 71, 71, 112, 115, 116, 108, 107, 73, 74, 113, 110, 110, 103, 82 };
  private static int ॱॱ = 0;
  private static int ᐝ = 1;
  private final uu<Jt> ˊ;
  private final uu<JB.If> ˋ;
  private final DevOptionsModule ˏ;
  private final uu<wk> ॱ;
  
  /* Error */
  public static JB.ˊ ˊ(DevOptionsModule paramDevOptionsModule, JB.If paramIf, Jt paramJt, wk paramWk)
  {
    // Byte code:
    //   0: goto +55 -> 55
    //   3: aconst_null
    //   4: arraylength
    //   5: istore 4
    //   7: aload_0
    //   8: areturn
    //   9: getstatic 27	o/Jv:ᐝ	I
    //   12: istore 4
    //   14: iload 4
    //   16: bipush 121
    //   18: iadd
    //   19: istore 4
    //   21: iload 4
    //   23: sipush 128
    //   26: irem
    //   27: putstatic 25	o/Jv:ॱॱ	I
    //   30: iload 4
    //   32: iconst_2
    //   33: irem
    //   34: ifeq +6 -> 40
    //   37: goto +6 -> 43
    //   40: goto +94 -> 134
    //   43: goto +91 -> 134
    //   46: aload_0
    //   47: areturn
    //   48: bipush 94
    //   50: istore 4
    //   52: goto +10 -> 62
    //   55: goto -46 -> 9
    //   58: bipush 66
    //   60: istore 4
    //   62: iload 4
    //   64: lookupswitch	default:+28->92, 66:+-61->3, 94:+-18->46
    //   92: aload_0
    //   93: areturn
    //   94: astore_0
    //   95: aload_0
    //   96: athrow
    //   97: astore_0
    //   98: aload_0
    //   99: athrow
    //   100: getstatic 25	o/Jv:ॱॱ	I
    //   103: istore 4
    //   105: iload 4
    //   107: bipush 11
    //   109: iadd
    //   110: istore 4
    //   112: iload 4
    //   114: sipush 128
    //   117: irem
    //   118: putstatic 27	o/Jv:ᐝ	I
    //   121: iload 4
    //   123: iconst_2
    //   124: irem
    //   125: ifne +6 -> 131
    //   128: goto -70 -> 58
    //   131: goto -83 -> 48
    //   134: aload_0
    //   135: aload_1
    //   136: aload_2
    //   137: aload_3
    //   138: invokevirtual 66	ro/btrl/devoptions/di/module/DevOptionsModule:ॱ	(Lo/JB$If;Lo/Jt;Lo/wk;)Lo/JB$ˊ;
    //   141: iconst_4
    //   142: newarray int
    //   144: dup
    //   145: iconst_0
    //   146: iconst_0
    //   147: iastore
    //   148: dup
    //   149: iconst_1
    //   150: bipush 56
    //   152: iastore
    //   153: dup
    //   154: iconst_2
    //   155: iconst_0
    //   156: iastore
    //   157: dup
    //   158: iconst_3
    //   159: iconst_0
    //   160: iastore
    //   161: bipush 56
    //   163: newarray byte
    //   165: dup
    //   166: iconst_0
    //   167: ldc 67
    //   169: bastore
    //   170: dup
    //   171: iconst_1
    //   172: ldc 68
    //   174: bastore
    //   175: dup
    //   176: iconst_2
    //   177: ldc 68
    //   179: bastore
    //   180: dup
    //   181: iconst_3
    //   182: ldc 67
    //   184: bastore
    //   185: dup
    //   186: iconst_4
    //   187: ldc 68
    //   189: bastore
    //   190: dup
    //   191: iconst_5
    //   192: ldc 67
    //   194: bastore
    //   195: dup
    //   196: bipush 6
    //   198: ldc 68
    //   200: bastore
    //   201: dup
    //   202: bipush 7
    //   204: ldc 68
    //   206: bastore
    //   207: dup
    //   208: bipush 8
    //   210: ldc 67
    //   212: bastore
    //   213: dup
    //   214: bipush 9
    //   216: ldc 68
    //   218: bastore
    //   219: dup
    //   220: bipush 10
    //   222: ldc 68
    //   224: bastore
    //   225: dup
    //   226: bipush 11
    //   228: ldc 68
    //   230: bastore
    //   231: dup
    //   232: bipush 12
    //   234: ldc 68
    //   236: bastore
    //   237: dup
    //   238: bipush 13
    //   240: ldc 68
    //   242: bastore
    //   243: dup
    //   244: bipush 14
    //   246: ldc 67
    //   248: bastore
    //   249: dup
    //   250: bipush 15
    //   252: ldc 67
    //   254: bastore
    //   255: dup
    //   256: bipush 16
    //   258: ldc 67
    //   260: bastore
    //   261: dup
    //   262: bipush 17
    //   264: ldc 68
    //   266: bastore
    //   267: dup
    //   268: bipush 18
    //   270: ldc 68
    //   272: bastore
    //   273: dup
    //   274: bipush 19
    //   276: ldc 67
    //   278: bastore
    //   279: dup
    //   280: bipush 20
    //   282: ldc 68
    //   284: bastore
    //   285: dup
    //   286: bipush 21
    //   288: ldc 68
    //   290: bastore
    //   291: dup
    //   292: bipush 22
    //   294: ldc 67
    //   296: bastore
    //   297: dup
    //   298: bipush 23
    //   300: ldc 68
    //   302: bastore
    //   303: dup
    //   304: bipush 24
    //   306: ldc 68
    //   308: bastore
    //   309: dup
    //   310: bipush 25
    //   312: ldc 67
    //   314: bastore
    //   315: dup
    //   316: bipush 26
    //   318: ldc 68
    //   320: bastore
    //   321: dup
    //   322: bipush 27
    //   324: ldc 68
    //   326: bastore
    //   327: dup
    //   328: bipush 28
    //   330: ldc 68
    //   332: bastore
    //   333: dup
    //   334: bipush 29
    //   336: ldc 68
    //   338: bastore
    //   339: dup
    //   340: bipush 30
    //   342: ldc 67
    //   344: bastore
    //   345: dup
    //   346: bipush 31
    //   348: ldc 68
    //   350: bastore
    //   351: dup
    //   352: bipush 32
    //   354: ldc 68
    //   356: bastore
    //   357: dup
    //   358: bipush 33
    //   360: ldc 68
    //   362: bastore
    //   363: dup
    //   364: bipush 34
    //   366: ldc 67
    //   368: bastore
    //   369: dup
    //   370: bipush 35
    //   372: ldc 68
    //   374: bastore
    //   375: dup
    //   376: bipush 36
    //   378: ldc 67
    //   380: bastore
    //   381: dup
    //   382: bipush 37
    //   384: ldc 67
    //   386: bastore
    //   387: dup
    //   388: bipush 38
    //   390: ldc 67
    //   392: bastore
    //   393: dup
    //   394: bipush 39
    //   396: ldc 67
    //   398: bastore
    //   399: dup
    //   400: bipush 40
    //   402: ldc 68
    //   404: bastore
    //   405: dup
    //   406: bipush 41
    //   408: ldc 68
    //   410: bastore
    //   411: dup
    //   412: bipush 42
    //   414: ldc 67
    //   416: bastore
    //   417: dup
    //   418: bipush 43
    //   420: ldc 67
    //   422: bastore
    //   423: dup
    //   424: bipush 44
    //   426: ldc 67
    //   428: bastore
    //   429: dup
    //   430: bipush 45
    //   432: ldc 68
    //   434: bastore
    //   435: dup
    //   436: bipush 46
    //   438: ldc 68
    //   440: bastore
    //   441: dup
    //   442: bipush 47
    //   444: ldc 68
    //   446: bastore
    //   447: dup
    //   448: bipush 48
    //   450: ldc 68
    //   452: bastore
    //   453: dup
    //   454: bipush 49
    //   456: ldc 67
    //   458: bastore
    //   459: dup
    //   460: bipush 50
    //   462: ldc 67
    //   464: bastore
    //   465: dup
    //   466: bipush 51
    //   468: ldc 68
    //   470: bastore
    //   471: dup
    //   472: bipush 52
    //   474: ldc 68
    //   476: bastore
    //   477: dup
    //   478: bipush 53
    //   480: ldc 67
    //   482: bastore
    //   483: dup
    //   484: bipush 54
    //   486: ldc 68
    //   488: bastore
    //   489: dup
    //   490: bipush 55
    //   492: ldc 67
    //   494: bastore
    //   495: iconst_1
    //   496: invokestatic 71	o/Jv:ˎ	([I[BZ)Ljava/lang/String;
    //   499: invokevirtual 77	java/lang/String:intern	()Ljava/lang/String;
    //   502: invokestatic 82	o/qn:ॱ	(Ljava/lang/Object;Ljava/lang/String;)Ljava/lang/Object;
    //   505: checkcast 84	o/JB$ˊ
    //   508: astore_0
    //   509: goto -409 -> 100
    // Local variable table:
    //   start	length	slot	name	signature
    //   0	512	0	paramDevOptionsModule	DevOptionsModule
    //   0	512	1	paramIf	JB.If
    //   0	512	2	paramJt	Jt
    //   0	512	3	paramWk	wk
    //   5	120	4	i	int
    // Exception table:
    //   from	to	target	type
    //   100	105	94	java/lang/Exception
    //   112	121	94	java/lang/Exception
    //   9	14	97	java/lang/Exception
    //   21	30	97	java/lang/Exception
  }
  
  /* Error */
  private static String ˎ(int[] paramArrayOfInt, byte[] paramArrayOfByte, boolean paramBoolean)
  {
    // Byte code:
    //   0: goto +459 -> 459
    //   3: goto +15 -> 18
    //   6: iconst_0
    //   7: istore 4
    //   9: goto +424 -> 433
    //   12: aload 10
    //   14: astore_1
    //   15: goto +224 -> 239
    //   18: aload 10
    //   20: iload 4
    //   22: caload
    //   23: istore_3
    //   24: iload 4
    //   26: iconst_1
    //   27: iadd
    //   28: istore 4
    //   30: goto +196 -> 226
    //   33: iconst_1
    //   34: istore 4
    //   36: goto +397 -> 433
    //   39: aload 9
    //   41: iload_3
    //   42: aload_1
    //   43: iload 6
    //   45: iload_3
    //   46: isub
    //   47: iconst_1
    //   48: isub
    //   49: caload
    //   50: castore
    //   51: iload_3
    //   52: iconst_1
    //   53: iadd
    //   54: istore_3
    //   55: goto +224 -> 279
    //   58: iload 5
    //   60: lookupswitch	default:+28->88, 29:+-48->12, 51:+271->331
    //   88: goto +243 -> 331
    //   91: iload 6
    //   93: newarray char
    //   95: astore 9
    //   97: iconst_0
    //   98: istore_3
    //   99: goto +180 -> 279
    //   102: bipush 29
    //   104: istore 5
    //   106: goto -48 -> 58
    //   109: iconst_0
    //   110: istore_3
    //   111: goto +42 -> 153
    //   114: iconst_0
    //   115: istore 4
    //   117: goto +239 -> 356
    //   120: getstatic 27	o/Jv:ᐝ	I
    //   123: bipush 11
    //   125: iadd
    //   126: istore 5
    //   128: iload 5
    //   130: sipush 128
    //   133: irem
    //   134: putstatic 25	o/Jv:ॱॱ	I
    //   137: iload 5
    //   139: iconst_2
    //   140: irem
    //   141: ifeq +6 -> 147
    //   144: goto +421 -> 565
    //   147: goto +483 -> 630
    //   150: goto +195 -> 345
    //   153: getstatic 27	o/Jv:ᐝ	I
    //   156: iconst_3
    //   157: iadd
    //   158: istore 4
    //   160: iload 4
    //   162: sipush 128
    //   165: irem
    //   166: putstatic 25	o/Jv:ॱॱ	I
    //   169: iload 4
    //   171: iconst_2
    //   172: irem
    //   173: ifeq +6 -> 179
    //   176: goto +47 -> 223
    //   179: goto +415 -> 594
    //   182: iload_2
    //   183: ifeq +6 -> 189
    //   186: goto +132 -> 318
    //   189: goto +137 -> 326
    //   192: new 73	java/lang/String
    //   195: dup
    //   196: aload 9
    //   198: invokespecial 88	java/lang/String:<init>	([C)V
    //   201: areturn
    //   202: goto +401 -> 603
    //   205: aload 10
    //   207: iload 4
    //   209: aload 9
    //   211: iload 4
    //   213: caload
    //   214: iconst_1
    //   215: ishl
    //   216: iload_3
    //   217: isub
    //   218: i2c
    //   219: castore
    //   220: goto -202 -> 18
    //   223: goto +371 -> 594
    //   226: iload 4
    //   228: iload 6
    //   230: if_icmpge +6 -> 236
    //   233: goto +78 -> 311
    //   236: goto -134 -> 102
    //   239: iload 8
    //   241: ifle +6 -> 247
    //   244: goto +139 -> 383
    //   247: goto -65 -> 182
    //   250: aload_1
    //   251: astore 9
    //   253: iload_3
    //   254: tableswitch	default:+22->276, 0:+-163->91, 1:+91->345
    //   276: goto -185 -> 91
    //   279: iload_3
    //   280: iload 6
    //   282: if_icmpge +6 -> 288
    //   285: goto +312 -> 597
    //   288: goto -174 -> 114
    //   291: aload 9
    //   293: iload_3
    //   294: aload 9
    //   296: iload_3
    //   297: caload
    //   298: aload_0
    //   299: iconst_2
    //   300: iaload
    //   301: isub
    //   302: i2c
    //   303: castore
    //   304: iload_3
    //   305: iconst_1
    //   306: iadd
    //   307: istore_3
    //   308: goto +274 -> 582
    //   311: bipush 51
    //   313: istore 5
    //   315: goto -257 -> 58
    //   318: iconst_0
    //   319: istore_3
    //   320: goto -70 -> 250
    //   323: astore_0
    //   324: aload_0
    //   325: athrow
    //   326: iconst_1
    //   327: istore_3
    //   328: goto -78 -> 250
    //   331: aload_1
    //   332: iload 4
    //   334: baload
    //   335: iconst_1
    //   336: if_icmpne +6 -> 342
    //   339: goto +174 -> 513
    //   342: goto -137 -> 205
    //   345: iload 7
    //   347: ifle +6 -> 353
    //   350: goto +183 -> 533
    //   353: goto -161 -> 192
    //   356: iload 4
    //   358: tableswitch	default:+22->380, 0:+-156->202, 1:+-319->39
    //   380: goto -341 -> 39
    //   383: iload 6
    //   385: newarray char
    //   387: astore 9
    //   389: aload_1
    //   390: iconst_0
    //   391: aload 9
    //   393: iconst_0
    //   394: iload 6
    //   396: invokestatic 94	java/lang/System:arraycopy	(Ljava/lang/Object;ILjava/lang/Object;II)V
    //   399: aload 9
    //   401: iconst_0
    //   402: aload_1
    //   403: iload 6
    //   405: iload 8
    //   407: isub
    //   408: iload 8
    //   410: invokestatic 94	java/lang/System:arraycopy	(Ljava/lang/Object;ILjava/lang/Object;II)V
    //   413: aload 9
    //   415: iload 8
    //   417: aload_1
    //   418: iconst_0
    //   419: iload 6
    //   421: iload 8
    //   423: isub
    //   424: invokestatic 94	java/lang/System:arraycopy	(Ljava/lang/Object;ILjava/lang/Object;II)V
    //   427: goto -245 -> 182
    //   430: goto -85 -> 345
    //   433: iload 4
    //   435: tableswitch	default:+21->456, 0:+-243->192, 1:+-144->291
    //   456: goto -165 -> 291
    //   459: aload_0
    //   460: iconst_0
    //   461: iaload
    //   462: istore_3
    //   463: aload_0
    //   464: iconst_1
    //   465: iaload
    //   466: istore 6
    //   468: aload_0
    //   469: iconst_2
    //   470: iaload
    //   471: istore 7
    //   473: aload_0
    //   474: iconst_3
    //   475: iaload
    //   476: istore 8
    //   478: getstatic 57	o/Jv:ˎ	[C
    //   481: astore 10
    //   483: iload 6
    //   485: newarray char
    //   487: astore 9
    //   489: aload 10
    //   491: iload_3
    //   492: aload 9
    //   494: iconst_0
    //   495: iload 6
    //   497: invokestatic 94	java/lang/System:arraycopy	(Ljava/lang/Object;ILjava/lang/Object;II)V
    //   500: aload_1
    //   501: ifnull +6 -> 507
    //   504: goto +64 -> 568
    //   507: aload 9
    //   509: astore_1
    //   510: goto -271 -> 239
    //   513: aload 10
    //   515: iload 4
    //   517: aload 9
    //   519: iload 4
    //   521: caload
    //   522: iconst_1
    //   523: ishl
    //   524: iconst_1
    //   525: iadd
    //   526: iload_3
    //   527: isub
    //   528: i2c
    //   529: castore
    //   530: goto -527 -> 3
    //   533: getstatic 25	o/Jv:ॱॱ	I
    //   536: istore_3
    //   537: iload_3
    //   538: bipush 73
    //   540: iadd
    //   541: istore_3
    //   542: iload_3
    //   543: sipush 128
    //   546: irem
    //   547: putstatic 27	o/Jv:ᐝ	I
    //   550: iload_3
    //   551: iconst_2
    //   552: irem
    //   553: ifne +6 -> 559
    //   556: goto +6 -> 562
    //   559: goto -450 -> 109
    //   562: goto -453 -> 109
    //   565: goto +65 -> 630
    //   568: iload 6
    //   570: newarray char
    //   572: astore 10
    //   574: iconst_0
    //   575: istore_3
    //   576: iconst_0
    //   577: istore 4
    //   579: goto -459 -> 120
    //   582: iload_3
    //   583: iload 6
    //   585: if_icmpge +6 -> 591
    //   588: goto -555 -> 33
    //   591: goto -585 -> 6
    //   594: goto -12 -> 582
    //   597: iconst_1
    //   598: istore 4
    //   600: goto -244 -> 356
    //   603: getstatic 27	o/Jv:ᐝ	I
    //   606: bipush 73
    //   608: iadd
    //   609: istore_3
    //   610: iload_3
    //   611: sipush 128
    //   614: irem
    //   615: putstatic 25	o/Jv:ॱॱ	I
    //   618: iload_3
    //   619: iconst_2
    //   620: irem
    //   621: ifeq +6 -> 627
    //   624: goto -474 -> 150
    //   627: goto -197 -> 430
    //   630: goto -404 -> 226
    // Local variable table:
    //   start	length	slot	name	signature
    //   0	633	0	paramArrayOfInt	int[]
    //   0	633	1	paramArrayOfByte	byte[]
    //   0	633	2	paramBoolean	boolean
    //   23	598	3	i	int
    //   7	592	4	j	int
    //   58	256	5	k	int
    //   43	543	6	m	int
    //   345	127	7	n	int
    //   239	238	8	i1	int
    //   39	479	9	localObject	Object
    //   12	561	10	arrayOfChar	char[]
    // Exception table:
    //   from	to	target	type
    //   533	537	323	java/lang/Exception
    //   542	550	323	java/lang/Exception
  }
  
  /* Error */
  public JB.ˊ ˎ()
  {
    // Byte code:
    //   0: goto +70 -> 70
    //   3: goto +91 -> 94
    //   6: iload_1
    //   7: lookupswitch	default:+25->32, 37:+509->516, 78:+25->32
    //   32: new 100	java/lang/NullPointerException
    //   35: dup
    //   36: invokespecial 102	java/lang/NullPointerException:<init>	()V
    //   39: athrow
    //   40: getstatic 25	o/Jv:ॱॱ	I
    //   43: bipush 81
    //   45: iadd
    //   46: istore_1
    //   47: iload_1
    //   48: sipush 128
    //   51: irem
    //   52: putstatic 27	o/Jv:ᐝ	I
    //   55: iload_1
    //   56: iconst_2
    //   57: irem
    //   58: ifne +6 -> 64
    //   61: goto +460 -> 521
    //   64: goto +463 -> 527
    //   67: astore_2
    //   68: aload_2
    //   69: athrow
    //   70: getstatic 25	o/Jv:ॱॱ	I
    //   73: bipush 75
    //   75: iadd
    //   76: istore_1
    //   77: iload_1
    //   78: sipush 128
    //   81: irem
    //   82: putstatic 27	o/Jv:ᐝ	I
    //   85: iload_1
    //   86: iconst_2
    //   87: irem
    //   88: ifne +6 -> 94
    //   91: goto -88 -> 3
    //   94: aload_0
    //   95: getfield 104	o/Jv:ˏ	Lro/btrl/devoptions/di/module/DevOptionsModule;
    //   98: astore_2
    //   99: aload_0
    //   100: getfield 106	o/Jv:ˋ	Lo/uu;
    //   103: astore_3
    //   104: aload_3
    //   105: invokeinterface 110 1 0
    //   110: astore_3
    //   111: aload_3
    //   112: checkcast 112	o/JB$If
    //   115: astore_3
    //   116: aload_2
    //   117: aload_3
    //   118: aload_0
    //   119: getfield 114	o/Jv:ˊ	Lo/uu;
    //   122: invokeinterface 110 1 0
    //   127: checkcast 116	o/Jt
    //   130: aload_0
    //   131: getfield 118	o/Jv:ॱ	Lo/uu;
    //   134: invokeinterface 110 1 0
    //   139: checkcast 120	o/wk
    //   142: invokevirtual 66	ro/btrl/devoptions/di/module/DevOptionsModule:ॱ	(Lo/JB$If;Lo/Jt;Lo/wk;)Lo/JB$ˊ;
    //   145: iconst_4
    //   146: newarray int
    //   148: dup
    //   149: iconst_0
    //   150: iconst_0
    //   151: iastore
    //   152: dup
    //   153: iconst_1
    //   154: bipush 56
    //   156: iastore
    //   157: dup
    //   158: iconst_2
    //   159: iconst_0
    //   160: iastore
    //   161: dup
    //   162: iconst_3
    //   163: iconst_0
    //   164: iastore
    //   165: bipush 56
    //   167: newarray byte
    //   169: dup
    //   170: iconst_0
    //   171: ldc 67
    //   173: bastore
    //   174: dup
    //   175: iconst_1
    //   176: ldc 68
    //   178: bastore
    //   179: dup
    //   180: iconst_2
    //   181: ldc 68
    //   183: bastore
    //   184: dup
    //   185: iconst_3
    //   186: ldc 67
    //   188: bastore
    //   189: dup
    //   190: iconst_4
    //   191: ldc 68
    //   193: bastore
    //   194: dup
    //   195: iconst_5
    //   196: ldc 67
    //   198: bastore
    //   199: dup
    //   200: bipush 6
    //   202: ldc 68
    //   204: bastore
    //   205: dup
    //   206: bipush 7
    //   208: ldc 68
    //   210: bastore
    //   211: dup
    //   212: bipush 8
    //   214: ldc 67
    //   216: bastore
    //   217: dup
    //   218: bipush 9
    //   220: ldc 68
    //   222: bastore
    //   223: dup
    //   224: bipush 10
    //   226: ldc 68
    //   228: bastore
    //   229: dup
    //   230: bipush 11
    //   232: ldc 68
    //   234: bastore
    //   235: dup
    //   236: bipush 12
    //   238: ldc 68
    //   240: bastore
    //   241: dup
    //   242: bipush 13
    //   244: ldc 68
    //   246: bastore
    //   247: dup
    //   248: bipush 14
    //   250: ldc 67
    //   252: bastore
    //   253: dup
    //   254: bipush 15
    //   256: ldc 67
    //   258: bastore
    //   259: dup
    //   260: bipush 16
    //   262: ldc 67
    //   264: bastore
    //   265: dup
    //   266: bipush 17
    //   268: ldc 68
    //   270: bastore
    //   271: dup
    //   272: bipush 18
    //   274: ldc 68
    //   276: bastore
    //   277: dup
    //   278: bipush 19
    //   280: ldc 67
    //   282: bastore
    //   283: dup
    //   284: bipush 20
    //   286: ldc 68
    //   288: bastore
    //   289: dup
    //   290: bipush 21
    //   292: ldc 68
    //   294: bastore
    //   295: dup
    //   296: bipush 22
    //   298: ldc 67
    //   300: bastore
    //   301: dup
    //   302: bipush 23
    //   304: ldc 68
    //   306: bastore
    //   307: dup
    //   308: bipush 24
    //   310: ldc 68
    //   312: bastore
    //   313: dup
    //   314: bipush 25
    //   316: ldc 67
    //   318: bastore
    //   319: dup
    //   320: bipush 26
    //   322: ldc 68
    //   324: bastore
    //   325: dup
    //   326: bipush 27
    //   328: ldc 68
    //   330: bastore
    //   331: dup
    //   332: bipush 28
    //   334: ldc 68
    //   336: bastore
    //   337: dup
    //   338: bipush 29
    //   340: ldc 68
    //   342: bastore
    //   343: dup
    //   344: bipush 30
    //   346: ldc 67
    //   348: bastore
    //   349: dup
    //   350: bipush 31
    //   352: ldc 68
    //   354: bastore
    //   355: dup
    //   356: bipush 32
    //   358: ldc 68
    //   360: bastore
    //   361: dup
    //   362: bipush 33
    //   364: ldc 68
    //   366: bastore
    //   367: dup
    //   368: bipush 34
    //   370: ldc 67
    //   372: bastore
    //   373: dup
    //   374: bipush 35
    //   376: ldc 68
    //   378: bastore
    //   379: dup
    //   380: bipush 36
    //   382: ldc 67
    //   384: bastore
    //   385: dup
    //   386: bipush 37
    //   388: ldc 67
    //   390: bastore
    //   391: dup
    //   392: bipush 38
    //   394: ldc 67
    //   396: bastore
    //   397: dup
    //   398: bipush 39
    //   400: ldc 67
    //   402: bastore
    //   403: dup
    //   404: bipush 40
    //   406: ldc 68
    //   408: bastore
    //   409: dup
    //   410: bipush 41
    //   412: ldc 68
    //   414: bastore
    //   415: dup
    //   416: bipush 42
    //   418: ldc 67
    //   420: bastore
    //   421: dup
    //   422: bipush 43
    //   424: ldc 67
    //   426: bastore
    //   427: dup
    //   428: bipush 44
    //   430: ldc 67
    //   432: bastore
    //   433: dup
    //   434: bipush 45
    //   436: ldc 68
    //   438: bastore
    //   439: dup
    //   440: bipush 46
    //   442: ldc 68
    //   444: bastore
    //   445: dup
    //   446: bipush 47
    //   448: ldc 68
    //   450: bastore
    //   451: dup
    //   452: bipush 48
    //   454: ldc 68
    //   456: bastore
    //   457: dup
    //   458: bipush 49
    //   460: ldc 67
    //   462: bastore
    //   463: dup
    //   464: bipush 50
    //   466: ldc 67
    //   468: bastore
    //   469: dup
    //   470: bipush 51
    //   472: ldc 68
    //   474: bastore
    //   475: dup
    //   476: bipush 52
    //   478: ldc 68
    //   480: bastore
    //   481: dup
    //   482: bipush 53
    //   484: ldc 67
    //   486: bastore
    //   487: dup
    //   488: bipush 54
    //   490: ldc 68
    //   492: bastore
    //   493: dup
    //   494: bipush 55
    //   496: ldc 67
    //   498: bastore
    //   499: iconst_1
    //   500: invokestatic 71	o/Jv:ˎ	([I[BZ)Ljava/lang/String;
    //   503: invokevirtual 77	java/lang/String:intern	()Ljava/lang/String;
    //   506: invokestatic 82	o/qn:ॱ	(Ljava/lang/Object;Ljava/lang/String;)Ljava/lang/Object;
    //   509: checkcast 84	o/JB$ˊ
    //   512: astore_2
    //   513: goto -473 -> 40
    //   516: aload_2
    //   517: areturn
    //   518: astore_2
    //   519: aload_2
    //   520: athrow
    //   521: bipush 78
    //   523: istore_1
    //   524: goto -518 -> 6
    //   527: bipush 37
    //   529: istore_1
    //   530: goto -524 -> 6
    // Local variable table:
    //   start	length	slot	name	signature
    //   0	533	0	this	Jv
    //   6	524	1	i	int
    //   67	2	2	localException1	Exception
    //   98	419	2	localObject1	Object
    //   518	2	2	localException2	Exception
    //   103	15	3	localObject2	Object
    // Exception table:
    //   from	to	target	type
    //   94	99	67	java/lang/Exception
    //   99	104	67	java/lang/Exception
    //   104	111	67	java/lang/Exception
    //   111	116	67	java/lang/Exception
    //   116	513	67	java/lang/Exception
    //   99	104	518	java/lang/Exception
  }
}
