package o;

import android.content.Context;
import android.content.Intent;
import android.content.res.Resources;
import android.os.Bundle;
import android.view.View;
import android.widget.Toast;
import java.util.List;

public class KA
  extends IB<JK>
{
  private static int ʼॱ;
  private static byte ʽॱ = -102;
  private static long ˈ;
  private static int ˊˊ;
  private Eo ʾ;
  private Eo ʿ;
  
  /* Error */
  static
  {
    // Byte code:
    //   0: goto +75 -> 75
    //   3: astore_1
    //   4: aload_1
    //   5: athrow
    //   6: iconst_0
    //   7: istore_0
    //   8: iload_0
    //   9: tableswitch	default:+23->32, 0:+27->36, 1:+60->69
    //   32: return
    //   33: astore_1
    //   34: aload_1
    //   35: athrow
    //   36: return
    //   37: getstatic 25	o/KA:ˊˊ	I
    //   40: bipush 39
    //   42: iadd
    //   43: istore_0
    //   44: iload_0
    //   45: sipush 128
    //   48: irem
    //   49: putstatic 27	o/KA:ʼॱ	I
    //   52: iload_0
    //   53: iconst_2
    //   54: irem
    //   55: ifeq +6 -> 61
    //   58: goto +6 -> 64
    //   61: goto -55 -> 6
    //   64: iconst_1
    //   65: istore_0
    //   66: goto -58 -> 8
    //   69: bipush 8
    //   71: iconst_0
    //   72: idiv
    //   73: istore_0
    //   74: return
    //   75: iconst_0
    //   76: putstatic 27	o/KA:ʼॱ	I
    //   79: iconst_1
    //   80: putstatic 25	o/KA:ˊˊ	I
    //   83: invokestatic 30	o/KA:ʻॱ	()V
    //   86: bipush -102
    //   88: putstatic 32	o/KA:ʽॱ	B
    //   91: goto -54 -> 37
    // Local variable table:
    //   start	length	slot	name	signature
    //   7	67	0	i	int
    //   3	2	1	localException1	Exception
    //   33	2	1	localException2	Exception
    // Exception table:
    //   from	to	target	type
    //   83	86	3	java/lang/Exception
    //   75	79	33	java/lang/Exception
    //   79	83	33	java/lang/Exception
    //   83	86	33	java/lang/Exception
    //   86	91	33	java/lang/Exception
  }
  
  public KA() {}
  
  static void ʻॱ()
  {
    ˈ = -8647650849489632094L;
  }
  
  private void ʾ()
  {
    for (;;)
    {
      int i;
      try
      {
        i = ˊˊ;
        i += 17;
      }
      catch (Exception localException1)
      {
        throw localException1;
      }
      try
      {
        ʼॱ = i % 128;
        if (i % 2 == 0) {
          return;
        }
        return;
      }
      catch (Exception localException2)
      {
        Eu localEu;
        throw localException2;
      }
      break label67;
      for (;;)
      {
        i = ˊˊ + 57;
        ʼॱ = i % 128;
        if (i % 2 != 0) {
          break;
        }
        break;
      }
      label67:
      localEu = (Eu)getIntent().getParcelableExtra(ˎ(new char[] { -29865, 20368, -11660, 26323, -5748, 31856, -32521, 2995, -24965, 8916, -19031, 14458, 19672, -10307, 23103, -4392, 29107, -31721, 2264 }).intern());
      ((JK)this.ॱˊ).ˏ(localEu);
    }
  }
  
  /* Error */
  private void ˉ()
  {
    // Byte code:
    //   0: goto +43 -> 43
    //   3: bipush 47
    //   5: iconst_0
    //   6: idiv
    //   7: istore_1
    //   8: return
    //   9: getstatic 25	o/KA:ˊˊ	I
    //   12: bipush 13
    //   14: iadd
    //   15: istore_1
    //   16: iload_1
    //   17: sipush 128
    //   20: irem
    //   21: putstatic 27	o/KA:ʼॱ	I
    //   24: iload_1
    //   25: iconst_2
    //   26: irem
    //   27: ifeq +6 -> 33
    //   30: goto +263 -> 293
    //   33: goto +4 -> 37
    //   36: return
    //   37: bipush 48
    //   39: istore_1
    //   40: goto +256 -> 296
    //   43: aload_0
    //   44: invokevirtual 44	o/KA:getIntent	()Landroid/content/Intent;
    //   47: bipush 19
    //   49: newarray char
    //   51: dup
    //   52: iconst_0
    //   53: ldc 45
    //   55: castore
    //   56: dup
    //   57: iconst_1
    //   58: ldc 46
    //   60: castore
    //   61: dup
    //   62: iconst_2
    //   63: ldc 47
    //   65: castore
    //   66: dup
    //   67: iconst_3
    //   68: ldc 48
    //   70: castore
    //   71: dup
    //   72: iconst_4
    //   73: ldc 49
    //   75: castore
    //   76: dup
    //   77: iconst_5
    //   78: ldc 50
    //   80: castore
    //   81: dup
    //   82: bipush 6
    //   84: ldc 51
    //   86: castore
    //   87: dup
    //   88: bipush 7
    //   90: ldc 52
    //   92: castore
    //   93: dup
    //   94: bipush 8
    //   96: ldc 53
    //   98: castore
    //   99: dup
    //   100: bipush 9
    //   102: ldc 54
    //   104: castore
    //   105: dup
    //   106: bipush 10
    //   108: ldc 55
    //   110: castore
    //   111: dup
    //   112: bipush 11
    //   114: ldc 56
    //   116: castore
    //   117: dup
    //   118: bipush 12
    //   120: ldc 57
    //   122: castore
    //   123: dup
    //   124: bipush 13
    //   126: ldc 58
    //   128: castore
    //   129: dup
    //   130: bipush 14
    //   132: ldc 59
    //   134: castore
    //   135: dup
    //   136: bipush 15
    //   138: ldc 60
    //   140: castore
    //   141: dup
    //   142: bipush 16
    //   144: ldc 61
    //   146: castore
    //   147: dup
    //   148: bipush 17
    //   150: ldc 62
    //   152: castore
    //   153: dup
    //   154: bipush 18
    //   156: ldc 63
    //   158: castore
    //   159: invokestatic 67	o/KA:ˎ	([C)Ljava/lang/String;
    //   162: invokevirtual 73	java/lang/String:intern	()Ljava/lang/String;
    //   165: invokevirtual 79	android/content/Intent:getParcelableExtra	(Ljava/lang/String;)Landroid/os/Parcelable;
    //   168: checkcast 81	o/Eu
    //   171: astore_2
    //   172: new 94	o/IM
    //   175: dup
    //   176: aload_0
    //   177: invokevirtual 97	o/KA:ॱˊ	()Landroid/content/Context;
    //   180: getstatic 102	o/Jy$IF:loading	I
    //   183: invokespecial 105	o/IM:<init>	(Landroid/content/Context;I)V
    //   186: astore_3
    //   187: aload_3
    //   188: invokevirtual 108	o/IM:ˏ	()Lo/ᐸ;
    //   191: pop
    //   192: goto +17 -> 209
    //   195: astore_2
    //   196: aload_2
    //   197: invokevirtual 114	java/lang/Throwable:getCause	()Ljava/lang/Throwable;
    //   200: astore_3
    //   201: aload_3
    //   202: ifnull +5 -> 207
    //   205: aload_3
    //   206: athrow
    //   207: aload_2
    //   208: athrow
    //   209: aload_0
    //   210: invokevirtual 120	android/content/Context:getApplicationInfo	()Landroid/content/pm/ApplicationInfo;
    //   213: getfield 125	android/content/pm/ApplicationInfo:targetSdkVersion	I
    //   216: bipush 21
    //   218: isub
    //   219: aload_0
    //   220: invokevirtual 120	android/content/Context:getApplicationInfo	()Landroid/content/pm/ApplicationInfo;
    //   223: getfield 125	android/content/pm/ApplicationInfo:targetSdkVersion	I
    //   226: bipush 110
    //   228: iadd
    //   229: aload_0
    //   230: invokevirtual 128	android/content/Context:getPackageName	()Ljava/lang/String;
    //   233: bipush 8
    //   235: invokevirtual 132	java/lang/String:codePointAt	(I)I
    //   238: ldc -123
    //   240: iadd
    //   241: i2c
    //   242: invokestatic 139	o/O:ˋ	(IIC)Ljava/lang/Object;
    //   245: checkcast 141	java/lang/Class
    //   248: ldc -114
    //   250: aconst_null
    //   251: invokevirtual 146	java/lang/Class:getMethod	(Ljava/lang/String;[Ljava/lang/Class;)Ljava/lang/reflect/Method;
    //   254: aconst_null
    //   255: aconst_null
    //   256: invokevirtual 152	java/lang/reflect/Method:invoke	(Ljava/lang/Object;[Ljava/lang/Object;)Ljava/lang/Object;
    //   259: checkcast 154	o/It
    //   262: astore 4
    //   264: aload 4
    //   266: aload_2
    //   267: invokevirtual 157	o/Eu:ॱ	()Ljava/lang/String;
    //   270: invokeinterface 160 2 0
    //   275: new 7	o/KA$1
    //   278: dup
    //   279: aload_0
    //   280: aload_0
    //   281: aload_3
    //   282: invokespecial 163	o/KA$1:<init>	(Lo/KA;Landroid/content/Context;Lo/IM;)V
    //   285: invokeinterface 168 2 0
    //   290: goto -281 -> 9
    //   293: bipush 54
    //   295: istore_1
    //   296: iload_1
    //   297: lookupswitch	default:+27->324, 48:+-261->36, 54:+-294->3
    //   324: return
    // Local variable table:
    //   start	length	slot	name	signature
    //   0	325	0	this	KA
    //   7	290	1	i	int
    //   171	1	2	localEu	Eu
    //   195	72	2	localObject1	Object
    //   186	96	3	localObject2	Object
    //   262	3	4	localIt	It
    // Exception table:
    //   from	to	target	type
    //   209	264	195	finally
  }
  
  /* Error */
  private String ˎ(String paramString)
  {
    // Byte code:
    //   0: goto +56 -> 56
    //   3: astore_1
    //   4: aload_1
    //   5: athrow
    //   6: goto +31 -> 37
    //   9: getstatic 25	o/KA:ˊˊ	I
    //   12: bipush 31
    //   14: iadd
    //   15: istore_2
    //   16: iload_2
    //   17: sipush 128
    //   20: irem
    //   21: putstatic 27	o/KA:ʼॱ	I
    //   24: iload_2
    //   25: iconst_2
    //   26: irem
    //   27: ifeq +6 -> 33
    //   30: goto +5 -> 35
    //   33: aload_1
    //   34: areturn
    //   35: aload_1
    //   36: areturn
    //   37: aload_1
    //   38: bipush 64
    //   40: invokevirtual 184	java/lang/String:indexOf	(I)I
    //   43: istore_2
    //   44: aload_1
    //   45: iconst_2
    //   46: iload_2
    //   47: bipush 42
    //   49: invokestatic 189	o/Ho:ˋ	(Ljava/lang/String;IIC)Ljava/lang/String;
    //   52: astore_1
    //   53: goto -44 -> 9
    //   56: getstatic 27	o/KA:ʼॱ	I
    //   59: bipush 23
    //   61: iadd
    //   62: istore_2
    //   63: iload_2
    //   64: sipush 128
    //   67: irem
    //   68: putstatic 25	o/KA:ˊˊ	I
    //   71: iload_2
    //   72: iconst_2
    //   73: irem
    //   74: ifne +6 -> 80
    //   77: goto -71 -> 6
    //   80: goto -43 -> 37
    // Local variable table:
    //   start	length	slot	name	signature
    //   0	83	0	this	KA
    //   0	83	1	paramString	String
    //   15	59	2	i	int
    // Exception table:
    //   from	to	target	type
    //   37	44	3	java/lang/Exception
    //   44	53	3	java/lang/Exception
  }
  
  /* Error */
  private static String ˎ(char[] paramArrayOfChar)
  {
    // Byte code:
    //   0: goto +51 -> 51
    //   3: iconst_0
    //   4: istore_2
    //   5: goto +6 -> 11
    //   8: goto +94 -> 102
    //   11: iload_2
    //   12: tableswitch	default:+24->36, 0:+77->89, 1:+42->54
    //   36: goto +53 -> 89
    //   39: iload_1
    //   40: aload_0
    //   41: arraylength
    //   42: if_icmpge +6 -> 48
    //   45: goto +36 -> 81
    //   48: goto -45 -> 3
    //   51: goto +71 -> 122
    //   54: aload 4
    //   56: iload_1
    //   57: iconst_1
    //   58: isub
    //   59: aload_0
    //   60: iload_1
    //   61: caload
    //   62: iload_1
    //   63: iload_3
    //   64: imul
    //   65: ixor
    //   66: i2l
    //   67: getstatic 40	o/KA:ˈ	J
    //   70: lxor
    //   71: l2i
    //   72: i2c
    //   73: castore
    //   74: iload_1
    //   75: iconst_1
    //   76: iadd
    //   77: istore_1
    //   78: goto -39 -> 39
    //   81: iconst_1
    //   82: istore_2
    //   83: goto -72 -> 11
    //   86: goto +87 -> 173
    //   89: new 69	java/lang/String
    //   92: dup
    //   93: aload 4
    //   95: invokespecial 192	java/lang/String:<init>	([C)V
    //   98: areturn
    //   99: astore_0
    //   100: aload_0
    //   101: athrow
    //   102: aload_0
    //   103: iconst_0
    //   104: caload
    //   105: istore_3
    //   106: aload_0
    //   107: arraylength
    //   108: iconst_1
    //   109: isub
    //   110: newarray char
    //   112: astore 4
    //   114: iconst_1
    //   115: istore_1
    //   116: goto +33 -> 149
    //   119: astore_0
    //   120: aload_0
    //   121: athrow
    //   122: getstatic 27	o/KA:ʼॱ	I
    //   125: bipush 111
    //   127: iadd
    //   128: istore_1
    //   129: iload_1
    //   130: sipush 128
    //   133: irem
    //   134: putstatic 25	o/KA:ˊˊ	I
    //   137: iload_1
    //   138: iconst_2
    //   139: irem
    //   140: ifne +6 -> 146
    //   143: goto -135 -> 8
    //   146: goto -44 -> 102
    //   149: getstatic 25	o/KA:ˊˊ	I
    //   152: bipush 51
    //   154: iadd
    //   155: istore_2
    //   156: iload_2
    //   157: sipush 128
    //   160: irem
    //   161: putstatic 27	o/KA:ʼॱ	I
    //   164: iload_2
    //   165: iconst_2
    //   166: irem
    //   167: ifeq +6 -> 173
    //   170: goto -84 -> 86
    //   173: goto -134 -> 39
    // Local variable table:
    //   start	length	slot	name	signature
    //   0	176	0	paramArrayOfChar	char[]
    //   39	101	1	i	int
    //   4	163	2	j	int
    //   63	43	3	k	int
    //   54	59	4	arrayOfChar	char[]
    // Exception table:
    //   from	to	target	type
    //   122	129	99	java/lang/Exception
    //   129	137	99	java/lang/Exception
    //   129	137	119	java/lang/Exception
  }
  
  private void ˎ(final Eq paramEq, final Eo paramEo)
  {
    break label425;
    ᐸ.If localIf;
    Object localObject2;
    for (;;)
    {
      localIf.ॱ((CharSequence)localObject1).ˋ(ॱ(paramEq, paramEo.ॱ())).ˏ(new ᐸ.if()
      {
        public void ˏ(ᐸ paramAnonymousᐸ, View paramAnonymousView, int paramAnonymousInt, CharSequence paramAnonymousCharSequence)
        {
          KA.ˊ(KA.this, paramEq, (String)((uB)paramEo.ॱ().get(paramAnonymousInt)).ˋ());
        }
      }).ˋ(true).ॱ(ᔆ.ˊ(ॱˊ(), Jy.if.black)).ˏ(ᔆ.ˊ(ॱˊ(), Jy.if.black)).ˏ();
      return;
      localObject1 = ॱ(((String)localObject2).substring(4)).intern();
    }
    break label175;
    label91:
    Object localObject1 = getString(Jy.IF.select_email_address);
    label148:
    int i;
    if (!((String)localObject1).startsWith(ˎ(new char[] { -14747, 706, 18546, -26746, -8902 }).intern())) {
      switch (i)
      {
      case 1: 
      default: 
        break label339;
        label175:
        localIf = ((ᐸ.If)localObject2).ˊ((CharSequence)localObject1);
        localObject2 = getString(Jy.IF.cancel);
        if (!((String)localObject2).startsWith(ˎ(new char[] { -14747, 706, 18546, -26746, -8902 }).intern()))
        {
          break label475;
          label241:
          i = ʼॱ + 17;
          ˊˊ = i % 128;
          if (i % 2 == 0) {}
        }
        break;
      }
    }
    for (;;)
    {
      switch (i)
      {
      case 14: 
      default: 
        break label91;
        break label175;
        break label368;
        i = 1;
        break label148;
        localObject1 = localObject2;
        switch (i)
        {
        }
        break;
        break;
      case 85: 
        try
        {
          label268:
          label299:
          label302:
          label310:
          label339:
          i = ʼॱ;
          i += 115;
          ˊˊ = i % 128;
          if (i % 2 == 0) {
            break label302;
          }
          label368:
          localObject1 = getString(Jy.IF.select_phone_number);
          if (!((String)localObject1).startsWith(ˎ(new char[] { -14747, 706, 18546, -26746, -8902 }).intern()))
          {
            break label175;
            label425:
            break label480;
            localObject1 = ॱ(((String)localObject1).substring(4)).intern();
            break label241;
          }
          localObject1 = ॱ(((String)localObject1).substring(4)).intern();
          break label299;
          for (;;)
          {
            i = 14;
            break label268;
            i = 0;
            break;
            label475:
            i = 0;
            break label310;
            label480:
            localObject2 = new ᐸ.If(this);
            if (paramEq == Eq.SMS) {
              break label511;
            }
          }
          i = 1;
        }
        catch (Exception paramEq)
        {
          throw paramEq;
        }
        label511:
        i = 85;
      }
    }
  }
  
  private String ˏ(String paramString)
  {
    break label71;
    label3:
    int i = ʼॱ + 51;
    ˊˊ = i % 128;
    if (i % 2 != 0)
    {
      i = 0;
      break label46;
      return Ho.ˋ(paramString, 3, paramString.length() - 2, '*');
    }
    for (;;)
    {
      switch (i)
      {
      case 0: 
      default: 
        label46:
        break label79;
        label71:
        break label3;
        i = 1;
      }
    }
    label79:
    return Ho.ˋ(paramString, 2, paramString.length() >> 2, '`');
  }
  
  /* Error */
  private String ॱ(String paramString)
  {
    // Byte code:
    //   0: goto +462 -> 462
    //   3: aload_1
    //   4: bipush 11
    //   6: newarray char
    //   8: dup
    //   9: iconst_0
    //   10: ldc_w 281
    //   13: castore
    //   14: dup
    //   15: iconst_1
    //   16: ldc_w 282
    //   19: castore
    //   20: dup
    //   21: iconst_2
    //   22: ldc_w 283
    //   25: castore
    //   26: dup
    //   27: iconst_3
    //   28: ldc_w 284
    //   31: castore
    //   32: dup
    //   33: iconst_4
    //   34: ldc_w 285
    //   37: castore
    //   38: dup
    //   39: iconst_5
    //   40: ldc_w 286
    //   43: castore
    //   44: dup
    //   45: bipush 6
    //   47: ldc_w 287
    //   50: castore
    //   51: dup
    //   52: bipush 7
    //   54: ldc_w 288
    //   57: castore
    //   58: dup
    //   59: bipush 8
    //   61: ldc_w 289
    //   64: castore
    //   65: dup
    //   66: bipush 9
    //   68: ldc_w 290
    //   71: castore
    //   72: dup
    //   73: bipush 10
    //   75: ldc_w 291
    //   78: castore
    //   79: invokestatic 67	o/KA:ˎ	([C)Ljava/lang/String;
    //   82: invokevirtual 73	java/lang/String:intern	()Ljava/lang/String;
    //   85: invokevirtual 295	java/lang/String:getBytes	(Ljava/lang/String;)[B
    //   88: astore 4
    //   90: aload 4
    //   92: arraylength
    //   93: newarray byte
    //   95: astore_1
    //   96: goto +189 -> 285
    //   99: astore_1
    //   100: aload_1
    //   101: athrow
    //   102: iload_3
    //   103: lookupswitch	default:+25->128, 4:+334->437, 12:+272->375
    //   128: goto +247 -> 375
    //   131: aload 4
    //   133: arraylength
    //   134: istore_3
    //   135: iload_2
    //   136: iload_3
    //   137: if_icmpge +6 -> 143
    //   140: goto +260 -> 400
    //   143: goto +322 -> 465
    //   146: aload_1
    //   147: bipush 11
    //   149: newarray char
    //   151: dup
    //   152: iconst_0
    //   153: ldc_w 281
    //   156: castore
    //   157: dup
    //   158: iconst_1
    //   159: ldc_w 282
    //   162: castore
    //   163: dup
    //   164: iconst_2
    //   165: ldc_w 283
    //   168: castore
    //   169: dup
    //   170: iconst_3
    //   171: ldc_w 284
    //   174: castore
    //   175: dup
    //   176: iconst_4
    //   177: ldc_w 285
    //   180: castore
    //   181: dup
    //   182: iconst_5
    //   183: ldc_w 286
    //   186: castore
    //   187: dup
    //   188: bipush 6
    //   190: ldc_w 287
    //   193: castore
    //   194: dup
    //   195: bipush 7
    //   197: ldc_w 288
    //   200: castore
    //   201: dup
    //   202: bipush 8
    //   204: ldc_w 289
    //   207: castore
    //   208: dup
    //   209: bipush 9
    //   211: ldc_w 290
    //   214: castore
    //   215: dup
    //   216: bipush 10
    //   218: ldc_w 291
    //   221: castore
    //   222: invokestatic 67	o/KA:ˎ	([C)Ljava/lang/String;
    //   225: invokevirtual 73	java/lang/String:intern	()Ljava/lang/String;
    //   228: invokevirtual 295	java/lang/String:getBytes	(Ljava/lang/String;)[B
    //   231: astore 4
    //   233: aload 4
    //   235: arraylength
    //   236: newarray byte
    //   238: astore_1
    //   239: goto +46 -> 285
    //   242: getstatic 27	o/KA:ʼॱ	I
    //   245: bipush 117
    //   247: iadd
    //   248: istore_2
    //   249: iload_2
    //   250: sipush 128
    //   253: irem
    //   254: putstatic 25	o/KA:ˊˊ	I
    //   257: iload_2
    //   258: iconst_2
    //   259: irem
    //   260: ifne +6 -> 266
    //   263: goto -260 -> 3
    //   266: goto -120 -> 146
    //   269: bipush 12
    //   271: istore_3
    //   272: goto -170 -> 102
    //   275: astore_1
    //   276: new 297	java/lang/RuntimeException
    //   279: dup
    //   280: aload_1
    //   281: invokespecial 300	java/lang/RuntimeException:<init>	(Ljava/lang/Throwable;)V
    //   284: athrow
    //   285: iconst_0
    //   286: istore_2
    //   287: goto -156 -> 131
    //   290: new 69	java/lang/String
    //   293: dup
    //   294: aload_1
    //   295: bipush 6
    //   297: newarray char
    //   299: dup
    //   300: iconst_0
    //   301: ldc_w 301
    //   304: castore
    //   305: dup
    //   306: iconst_1
    //   307: ldc_w 302
    //   310: castore
    //   311: dup
    //   312: iconst_2
    //   313: ldc_w 303
    //   316: castore
    //   317: dup
    //   318: iconst_3
    //   319: ldc_w 304
    //   322: castore
    //   323: dup
    //   324: iconst_4
    //   325: ldc_w 305
    //   328: castore
    //   329: dup
    //   330: iconst_5
    //   331: ldc_w 306
    //   334: castore
    //   335: invokestatic 67	o/KA:ˎ	([C)Ljava/lang/String;
    //   338: invokevirtual 73	java/lang/String:intern	()Ljava/lang/String;
    //   341: invokespecial 309	java/lang/String:<init>	([BLjava/lang/String;)V
    //   344: astore_1
    //   345: aload_1
    //   346: areturn
    //   347: iload_3
    //   348: tableswitch	default:+24->372, 0:+62->410, 1:+-58->290
    //   372: goto +38 -> 410
    //   375: aload_1
    //   376: iload_2
    //   377: aload 4
    //   379: aload 4
    //   381: arraylength
    //   382: iload_2
    //   383: isub
    //   384: iconst_1
    //   385: isub
    //   386: baload
    //   387: getstatic 32	o/KA:ʽॱ	B
    //   390: ixor
    //   391: i2b
    //   392: bastore
    //   393: iload_2
    //   394: iconst_1
    //   395: iadd
    //   396: istore_2
    //   397: goto -266 -> 131
    //   400: iconst_0
    //   401: istore_3
    //   402: goto -55 -> 347
    //   405: iconst_4
    //   406: istore_3
    //   407: goto -305 -> 102
    //   410: getstatic 25	o/KA:ˊˊ	I
    //   413: bipush 115
    //   415: iadd
    //   416: istore_3
    //   417: iload_3
    //   418: sipush 128
    //   421: irem
    //   422: putstatic 27	o/KA:ʼॱ	I
    //   425: iload_3
    //   426: iconst_2
    //   427: irem
    //   428: ifeq +6 -> 434
    //   431: goto -26 -> 405
    //   434: goto -165 -> 269
    //   437: aload_1
    //   438: iload_2
    //   439: aload 4
    //   441: aload 4
    //   443: arraylength
    //   444: iload_2
    //   445: iadd
    //   446: iconst_1
    //   447: ishl
    //   448: baload
    //   449: getstatic 32	o/KA:ʽॱ	B
    //   452: iand
    //   453: i2b
    //   454: bastore
    //   455: iload_2
    //   456: iconst_5
    //   457: iadd
    //   458: istore_2
    //   459: goto -328 -> 131
    //   462: goto -220 -> 242
    //   465: iconst_1
    //   466: istore_3
    //   467: goto -120 -> 347
    // Local variable table:
    //   start	length	slot	name	signature
    //   0	470	0	this	KA
    //   0	470	1	paramString	String
    //   135	324	2	i	int
    //   102	365	3	j	int
    //   88	354	4	arrayOfByte	byte[]
    // Exception table:
    //   from	to	target	type
    //   242	249	99	java/lang/Exception
    //   249	257	99	java/lang/Exception
    //   3	96	275	java/io/UnsupportedEncodingException
    //   131	135	275	java/io/UnsupportedEncodingException
    //   146	239	275	java/io/UnsupportedEncodingException
    //   290	345	275	java/io/UnsupportedEncodingException
    //   375	393	275	java/io/UnsupportedEncodingException
    //   437	455	275	java/io/UnsupportedEncodingException
  }
  
  /* Error */
  private List<String> ॱ(Eq paramEq, List<uB<String, String>> paramList)
  {
    // Byte code:
    //   0: goto +8 -> 8
    //   3: iconst_1
    //   4: istore_3
    //   5: goto +74 -> 79
    //   8: goto +191 -> 199
    //   11: iload_3
    //   12: lookupswitch	default:+28->40, 8:+122->134, 71:+267->279
    //   40: goto +94 -> 134
    //   43: bipush 71
    //   45: istore_3
    //   46: goto -35 -> 11
    //   49: aload 4
    //   51: aload_0
    //   52: aload_2
    //   53: invokevirtual 314	o/uB:ˎ	()Ljava/lang/Object;
    //   56: invokevirtual 319	java/lang/Object:toString	()Ljava/lang/String;
    //   59: invokespecial 321	o/KA:ˎ	(Ljava/lang/String;)Ljava/lang/String;
    //   62: invokeinterface 327 2 0
    //   67: pop
    //   68: goto +128 -> 196
    //   71: iconst_0
    //   72: istore_3
    //   73: goto +181 -> 254
    //   76: astore_1
    //   77: aload_1
    //   78: athrow
    //   79: iload_3
    //   80: tableswitch	default:+24->104, 0:+147->227, 1:+78->158
    //   104: goto +123 -> 227
    //   107: getstatic 25	o/KA:ˊˊ	I
    //   110: bipush 81
    //   112: iadd
    //   113: istore_3
    //   114: iload_3
    //   115: sipush 128
    //   118: irem
    //   119: putstatic 27	o/KA:ʼॱ	I
    //   122: iload_3
    //   123: iconst_2
    //   124: irem
    //   125: ifeq +6 -> 131
    //   128: goto +154 -> 282
    //   131: aload 4
    //   133: areturn
    //   134: aload 5
    //   136: invokeinterface 332 1 0
    //   141: checkcast 311	o/uB
    //   144: astore_2
    //   145: aload_1
    //   146: getstatic 274	o/Eq:SMS	Lo/Eq;
    //   149: if_acmpne +6 -> 155
    //   152: goto +162 -> 314
    //   155: goto -84 -> 71
    //   158: aload 4
    //   160: aload_0
    //   161: aload_2
    //   162: invokevirtual 314	o/uB:ˎ	()Ljava/lang/Object;
    //   165: invokevirtual 319	java/lang/Object:toString	()Ljava/lang/String;
    //   168: invokespecial 334	o/KA:ˏ	(Ljava/lang/String;)Ljava/lang/String;
    //   171: invokeinterface 327 2 0
    //   176: pop
    //   177: goto +47 -> 224
    //   180: aload 5
    //   182: invokeinterface 338 1 0
    //   187: ifeq +6 -> 193
    //   190: goto +129 -> 319
    //   193: goto -150 -> 43
    //   196: goto -16 -> 180
    //   199: new 340	java/util/ArrayList
    //   202: dup
    //   203: invokespecial 341	java/util/ArrayList:<init>	()V
    //   206: astore 4
    //   208: aload_2
    //   209: invokeinterface 345 1 0
    //   214: astore 5
    //   216: goto -36 -> 180
    //   219: iconst_0
    //   220: istore_3
    //   221: goto -142 -> 79
    //   224: goto -28 -> 196
    //   227: aload 4
    //   229: aload_0
    //   230: aload_2
    //   231: invokevirtual 314	o/uB:ˎ	()Ljava/lang/Object;
    //   234: invokevirtual 319	java/lang/Object:toString	()Ljava/lang/String;
    //   237: invokespecial 334	o/KA:ˏ	(Ljava/lang/String;)Ljava/lang/String;
    //   240: invokeinterface 327 2 0
    //   245: pop
    //   246: bipush 30
    //   248: iconst_0
    //   249: idiv
    //   250: istore_3
    //   251: goto -27 -> 224
    //   254: iload_3
    //   255: tableswitch	default:+21->276, 0:+-206->49, 1:+30->285
    //   276: goto -227 -> 49
    //   279: goto -172 -> 107
    //   282: aload 4
    //   284: areturn
    //   285: getstatic 27	o/KA:ʼॱ	I
    //   288: istore_3
    //   289: iload_3
    //   290: bipush 89
    //   292: iadd
    //   293: istore_3
    //   294: iload_3
    //   295: sipush 128
    //   298: irem
    //   299: putstatic 25	o/KA:ˊˊ	I
    //   302: iload_3
    //   303: iconst_2
    //   304: irem
    //   305: ifne +6 -> 311
    //   308: goto -89 -> 219
    //   311: goto -308 -> 3
    //   314: iconst_1
    //   315: istore_3
    //   316: goto -62 -> 254
    //   319: bipush 8
    //   321: istore_3
    //   322: goto -311 -> 11
    //   325: astore_1
    //   326: aload_1
    //   327: athrow
    // Local variable table:
    //   start	length	slot	name	signature
    //   0	328	0	this	KA
    //   0	328	1	paramEq	Eq
    //   0	328	2	paramList	List<uB<String, String>>
    //   4	318	3	i	int
    //   49	234	4	localObject	Object
    //   134	81	5	localIterator	java.util.Iterator
    // Exception table:
    //   from	to	target	type
    //   285	289	76	java/lang/Exception
    //   294	302	325	java/lang/Exception
  }
  
  /* Error */
  private void ॱ(Eq paramEq, String paramString)
  {
    // Byte code:
    //   0: goto +232 -> 232
    //   3: goto +17 -> 20
    //   6: astore_1
    //   7: aload_1
    //   8: invokevirtual 114	java/lang/Throwable:getCause	()Ljava/lang/Throwable;
    //   11: astore_2
    //   12: aload_2
    //   13: ifnull +5 -> 18
    //   16: aload_2
    //   17: athrow
    //   18: aload_1
    //   19: athrow
    //   20: aload_0
    //   21: invokevirtual 128	android/content/Context:getPackageName	()Ljava/lang/String;
    //   24: iconst_4
    //   25: invokevirtual 132	java/lang/String:codePointAt	(I)I
    //   28: bipush 113
    //   30: isub
    //   31: aload_0
    //   32: invokevirtual 351	android/content/Context:getResources	()Landroid/content/res/Resources;
    //   35: ldc_w 352
    //   38: invokevirtual 355	android/content/res/Resources:getString	(I)Ljava/lang/String;
    //   41: iconst_0
    //   42: iconst_4
    //   43: invokevirtual 358	java/lang/String:substring	(II)Ljava/lang/String;
    //   46: iconst_0
    //   47: invokevirtual 132	java/lang/String:codePointAt	(I)I
    //   50: bipush 19
    //   52: iadd
    //   53: aload_0
    //   54: invokevirtual 128	android/content/Context:getPackageName	()Ljava/lang/String;
    //   57: invokevirtual 278	java/lang/String:length	()I
    //   60: bipush 11
    //   62: isub
    //   63: i2c
    //   64: invokestatic 139	o/O:ˋ	(IIC)Ljava/lang/Object;
    //   67: checkcast 141	java/lang/Class
    //   70: ldc_w 359
    //   73: aconst_null
    //   74: invokevirtual 146	java/lang/Class:getMethod	(Ljava/lang/String;[Ljava/lang/Class;)Ljava/lang/reflect/Method;
    //   77: aconst_null
    //   78: aconst_null
    //   79: invokevirtual 152	java/lang/reflect/Method:invoke	(Ljava/lang/Object;[Ljava/lang/Object;)Ljava/lang/Object;
    //   82: astore 5
    //   84: goto +17 -> 101
    //   87: astore_1
    //   88: aload_1
    //   89: invokevirtual 114	java/lang/Throwable:getCause	()Ljava/lang/Throwable;
    //   92: astore_2
    //   93: aload_2
    //   94: ifnull +5 -> 99
    //   97: aload_2
    //   98: athrow
    //   99: aload_1
    //   100: athrow
    //   101: aload_0
    //   102: invokevirtual 128	android/content/Context:getPackageName	()Ljava/lang/String;
    //   105: bipush 9
    //   107: invokevirtual 132	java/lang/String:codePointAt	(I)I
    //   110: bipush 94
    //   112: isub
    //   113: aload_0
    //   114: invokevirtual 120	android/content/Context:getApplicationInfo	()Landroid/content/pm/ApplicationInfo;
    //   117: getfield 125	android/content/pm/ApplicationInfo:targetSdkVersion	I
    //   120: iconst_1
    //   121: isub
    //   122: aload_0
    //   123: invokevirtual 351	android/content/Context:getResources	()Landroid/content/res/Resources;
    //   126: ldc_w 360
    //   129: invokevirtual 355	android/content/res/Resources:getString	(I)Ljava/lang/String;
    //   132: bipush 8
    //   134: bipush 13
    //   136: invokevirtual 358	java/lang/String:substring	(II)Ljava/lang/String;
    //   139: iconst_1
    //   140: invokevirtual 132	java/lang/String:codePointAt	(I)I
    //   143: sipush 249
    //   146: isub
    //   147: i2c
    //   148: invokestatic 139	o/O:ˋ	(IIC)Ljava/lang/Object;
    //   151: checkcast 141	java/lang/Class
    //   154: ldc_w 361
    //   157: iconst_1
    //   158: anewarray 141	java/lang/Class
    //   161: dup
    //   162: iconst_0
    //   163: ldc 116
    //   165: aastore
    //   166: invokevirtual 146	java/lang/Class:getMethod	(Ljava/lang/String;[Ljava/lang/Class;)Ljava/lang/reflect/Method;
    //   169: aload 5
    //   171: iconst_1
    //   172: anewarray 316	java/lang/Object
    //   175: dup
    //   176: iconst_0
    //   177: aload_0
    //   178: aastore
    //   179: invokevirtual 152	java/lang/reflect/Method:invoke	(Ljava/lang/Object;[Ljava/lang/Object;)Ljava/lang/Object;
    //   182: checkcast 363	java/lang/Boolean
    //   185: invokevirtual 366	java/lang/Boolean:booleanValue	()Z
    //   188: istore 4
    //   190: iload 4
    //   192: ifeq +6 -> 198
    //   195: goto +103 -> 298
    //   198: goto +37 -> 235
    //   201: iload_3
    //   202: tableswitch	default:+22->224, 0:+63->265, 1:+66->268
    //   224: goto +41 -> 265
    //   227: iconst_1
    //   228: istore_3
    //   229: goto -28 -> 201
    //   232: goto -229 -> 3
    //   235: goto +40 -> 275
    //   238: getstatic 25	o/KA:ˊˊ	I
    //   241: bipush 53
    //   243: iadd
    //   244: istore_3
    //   245: iload_3
    //   246: sipush 128
    //   249: irem
    //   250: putstatic 27	o/KA:ʼॱ	I
    //   253: iload_3
    //   254: iconst_2
    //   255: irem
    //   256: ifeq +6 -> 262
    //   259: goto -32 -> 227
    //   262: goto +1190 -> 1452
    //   265: goto -30 -> 235
    //   268: iconst_4
    //   269: iconst_5
    //   270: idiv
    //   271: istore_3
    //   272: goto -37 -> 235
    //   275: getstatic 25	o/KA:ˊˊ	I
    //   278: bipush 61
    //   280: iadd
    //   281: istore_3
    //   282: iload_3
    //   283: sipush 128
    //   286: irem
    //   287: putstatic 27	o/KA:ʼॱ	I
    //   290: iload_3
    //   291: iconst_2
    //   292: irem
    //   293: ifeq +4 -> 297
    //   296: return
    //   297: return
    //   298: aload_0
    //   299: invokevirtual 44	o/KA:getIntent	()Landroid/content/Intent;
    //   302: bipush 19
    //   304: newarray char
    //   306: dup
    //   307: iconst_0
    //   308: ldc 45
    //   310: castore
    //   311: dup
    //   312: iconst_1
    //   313: ldc 46
    //   315: castore
    //   316: dup
    //   317: iconst_2
    //   318: ldc 47
    //   320: castore
    //   321: dup
    //   322: iconst_3
    //   323: ldc 48
    //   325: castore
    //   326: dup
    //   327: iconst_4
    //   328: ldc 49
    //   330: castore
    //   331: dup
    //   332: iconst_5
    //   333: ldc 50
    //   335: castore
    //   336: dup
    //   337: bipush 6
    //   339: ldc 51
    //   341: castore
    //   342: dup
    //   343: bipush 7
    //   345: ldc 52
    //   347: castore
    //   348: dup
    //   349: bipush 8
    //   351: ldc 53
    //   353: castore
    //   354: dup
    //   355: bipush 9
    //   357: ldc 54
    //   359: castore
    //   360: dup
    //   361: bipush 10
    //   363: ldc 55
    //   365: castore
    //   366: dup
    //   367: bipush 11
    //   369: ldc 56
    //   371: castore
    //   372: dup
    //   373: bipush 12
    //   375: ldc 57
    //   377: castore
    //   378: dup
    //   379: bipush 13
    //   381: ldc 58
    //   383: castore
    //   384: dup
    //   385: bipush 14
    //   387: ldc 59
    //   389: castore
    //   390: dup
    //   391: bipush 15
    //   393: ldc 60
    //   395: castore
    //   396: dup
    //   397: bipush 16
    //   399: ldc 61
    //   401: castore
    //   402: dup
    //   403: bipush 17
    //   405: ldc 62
    //   407: castore
    //   408: dup
    //   409: bipush 18
    //   411: ldc 63
    //   413: castore
    //   414: invokestatic 67	o/KA:ˎ	([C)Ljava/lang/String;
    //   417: invokevirtual 73	java/lang/String:intern	()Ljava/lang/String;
    //   420: invokevirtual 79	android/content/Intent:getParcelableExtra	(Ljava/lang/String;)Landroid/os/Parcelable;
    //   423: checkcast 81	o/Eu
    //   426: astore 5
    //   428: new 368	o/Em
    //   431: dup
    //   432: aload_0
    //   433: invokevirtual 44	o/KA:getIntent	()Landroid/content/Intent;
    //   436: bipush 16
    //   438: newarray char
    //   440: dup
    //   441: iconst_0
    //   442: ldc_w 369
    //   445: castore
    //   446: dup
    //   447: iconst_1
    //   448: ldc_w 370
    //   451: castore
    //   452: dup
    //   453: iconst_2
    //   454: ldc_w 371
    //   457: castore
    //   458: dup
    //   459: iconst_3
    //   460: ldc_w 372
    //   463: castore
    //   464: dup
    //   465: iconst_4
    //   466: ldc_w 373
    //   469: castore
    //   470: dup
    //   471: iconst_5
    //   472: ldc_w 374
    //   475: castore
    //   476: dup
    //   477: bipush 6
    //   479: ldc_w 375
    //   482: castore
    //   483: dup
    //   484: bipush 7
    //   486: ldc_w 376
    //   489: castore
    //   490: dup
    //   491: bipush 8
    //   493: ldc_w 377
    //   496: castore
    //   497: dup
    //   498: bipush 9
    //   500: ldc_w 378
    //   503: castore
    //   504: dup
    //   505: bipush 10
    //   507: ldc_w 379
    //   510: castore
    //   511: dup
    //   512: bipush 11
    //   514: ldc_w 380
    //   517: castore
    //   518: dup
    //   519: bipush 12
    //   521: ldc_w 381
    //   524: castore
    //   525: dup
    //   526: bipush 13
    //   528: ldc_w 382
    //   531: castore
    //   532: dup
    //   533: bipush 14
    //   535: ldc_w 383
    //   538: castore
    //   539: dup
    //   540: bipush 15
    //   542: ldc_w 384
    //   545: castore
    //   546: invokestatic 67	o/KA:ˎ	([C)Ljava/lang/String;
    //   549: invokevirtual 73	java/lang/String:intern	()Ljava/lang/String;
    //   552: invokevirtual 388	android/content/Intent:getSerializableExtra	(Ljava/lang/String;)Ljava/io/Serializable;
    //   555: checkcast 390	o/Er
    //   558: aload_1
    //   559: aload_2
    //   560: aload 5
    //   562: getfield 394	o/Eu:uuid	Ljava/lang/String;
    //   565: aconst_null
    //   566: invokespecial 397	o/Em:<init>	(Lo/Er;Lo/Eq;Ljava/lang/String;Ljava/lang/String;Ljava/lang/String;)V
    //   569: astore_1
    //   570: aload_0
    //   571: invokevirtual 44	o/KA:getIntent	()Landroid/content/Intent;
    //   574: bipush 25
    //   576: newarray char
    //   578: dup
    //   579: iconst_0
    //   580: ldc_w 398
    //   583: castore
    //   584: dup
    //   585: iconst_1
    //   586: ldc_w 399
    //   589: castore
    //   590: dup
    //   591: iconst_2
    //   592: ldc_w 400
    //   595: castore
    //   596: dup
    //   597: iconst_3
    //   598: ldc_w 401
    //   601: castore
    //   602: dup
    //   603: iconst_4
    //   604: ldc_w 402
    //   607: castore
    //   608: dup
    //   609: iconst_5
    //   610: ldc_w 403
    //   613: castore
    //   614: dup
    //   615: bipush 6
    //   617: ldc_w 404
    //   620: castore
    //   621: dup
    //   622: bipush 7
    //   624: ldc_w 405
    //   627: castore
    //   628: dup
    //   629: bipush 8
    //   631: ldc_w 406
    //   634: castore
    //   635: dup
    //   636: bipush 9
    //   638: ldc_w 407
    //   641: castore
    //   642: dup
    //   643: bipush 10
    //   645: ldc_w 408
    //   648: castore
    //   649: dup
    //   650: bipush 11
    //   652: ldc_w 409
    //   655: castore
    //   656: dup
    //   657: bipush 12
    //   659: ldc_w 410
    //   662: castore
    //   663: dup
    //   664: bipush 13
    //   666: ldc_w 411
    //   669: castore
    //   670: dup
    //   671: bipush 14
    //   673: ldc_w 412
    //   676: castore
    //   677: dup
    //   678: bipush 15
    //   680: ldc_w 413
    //   683: castore
    //   684: dup
    //   685: bipush 16
    //   687: ldc_w 414
    //   690: castore
    //   691: dup
    //   692: bipush 17
    //   694: ldc_w 415
    //   697: castore
    //   698: dup
    //   699: bipush 18
    //   701: ldc_w 416
    //   704: castore
    //   705: dup
    //   706: bipush 19
    //   708: ldc_w 417
    //   711: castore
    //   712: dup
    //   713: bipush 20
    //   715: ldc_w 418
    //   718: castore
    //   719: dup
    //   720: bipush 21
    //   722: ldc_w 419
    //   725: castore
    //   726: dup
    //   727: bipush 22
    //   729: ldc_w 420
    //   732: castore
    //   733: dup
    //   734: bipush 23
    //   736: ldc_w 421
    //   739: castore
    //   740: dup
    //   741: bipush 24
    //   743: ldc_w 422
    //   746: castore
    //   747: invokestatic 67	o/KA:ˎ	([C)Ljava/lang/String;
    //   750: invokevirtual 73	java/lang/String:intern	()Ljava/lang/String;
    //   753: invokevirtual 425	android/content/Intent:getStringExtra	(Ljava/lang/String;)Ljava/lang/String;
    //   756: astore_2
    //   757: aload_0
    //   758: invokestatic 430	o/Ic:ˏ	(Landroid/content/Context;)Lo/Ic;
    //   761: invokevirtual 433	o/Ic:ॱˋ	()Lo/j;
    //   764: bipush 20
    //   766: newarray char
    //   768: dup
    //   769: iconst_0
    //   770: ldc_w 434
    //   773: castore
    //   774: dup
    //   775: iconst_1
    //   776: ldc_w 435
    //   779: castore
    //   780: dup
    //   781: iconst_2
    //   782: ldc_w 436
    //   785: castore
    //   786: dup
    //   787: iconst_3
    //   788: ldc_w 437
    //   791: castore
    //   792: dup
    //   793: iconst_4
    //   794: ldc_w 438
    //   797: castore
    //   798: dup
    //   799: iconst_5
    //   800: ldc_w 439
    //   803: castore
    //   804: dup
    //   805: bipush 6
    //   807: ldc_w 440
    //   810: castore
    //   811: dup
    //   812: bipush 7
    //   814: ldc_w 441
    //   817: castore
    //   818: dup
    //   819: bipush 8
    //   821: ldc_w 442
    //   824: castore
    //   825: dup
    //   826: bipush 9
    //   828: ldc_w 443
    //   831: castore
    //   832: dup
    //   833: bipush 10
    //   835: ldc_w 444
    //   838: castore
    //   839: dup
    //   840: bipush 11
    //   842: ldc_w 445
    //   845: castore
    //   846: dup
    //   847: bipush 12
    //   849: ldc_w 446
    //   852: castore
    //   853: dup
    //   854: bipush 13
    //   856: ldc_w 447
    //   859: castore
    //   860: dup
    //   861: bipush 14
    //   863: ldc_w 448
    //   866: castore
    //   867: dup
    //   868: bipush 15
    //   870: ldc_w 449
    //   873: castore
    //   874: dup
    //   875: bipush 16
    //   877: ldc_w 450
    //   880: castore
    //   881: dup
    //   882: bipush 17
    //   884: ldc_w 451
    //   887: castore
    //   888: dup
    //   889: bipush 18
    //   891: ldc_w 452
    //   894: castore
    //   895: dup
    //   896: bipush 19
    //   898: ldc_w 453
    //   901: castore
    //   902: invokestatic 67	o/KA:ˎ	([C)Ljava/lang/String;
    //   905: invokevirtual 73	java/lang/String:intern	()Ljava/lang/String;
    //   908: aload_1
    //   909: invokevirtual 458	o/j:ˎ	(Ljava/lang/String;Landroid/os/Parcelable;)Lo/j;
    //   912: bipush 19
    //   914: newarray char
    //   916: dup
    //   917: iconst_0
    //   918: ldc 45
    //   920: castore
    //   921: dup
    //   922: iconst_1
    //   923: ldc 46
    //   925: castore
    //   926: dup
    //   927: iconst_2
    //   928: ldc 47
    //   930: castore
    //   931: dup
    //   932: iconst_3
    //   933: ldc 48
    //   935: castore
    //   936: dup
    //   937: iconst_4
    //   938: ldc 49
    //   940: castore
    //   941: dup
    //   942: iconst_5
    //   943: ldc 50
    //   945: castore
    //   946: dup
    //   947: bipush 6
    //   949: ldc 51
    //   951: castore
    //   952: dup
    //   953: bipush 7
    //   955: ldc 52
    //   957: castore
    //   958: dup
    //   959: bipush 8
    //   961: ldc 53
    //   963: castore
    //   964: dup
    //   965: bipush 9
    //   967: ldc 54
    //   969: castore
    //   970: dup
    //   971: bipush 10
    //   973: ldc 55
    //   975: castore
    //   976: dup
    //   977: bipush 11
    //   979: ldc 56
    //   981: castore
    //   982: dup
    //   983: bipush 12
    //   985: ldc 57
    //   987: castore
    //   988: dup
    //   989: bipush 13
    //   991: ldc 58
    //   993: castore
    //   994: dup
    //   995: bipush 14
    //   997: ldc 59
    //   999: castore
    //   1000: dup
    //   1001: bipush 15
    //   1003: ldc 60
    //   1005: castore
    //   1006: dup
    //   1007: bipush 16
    //   1009: ldc 61
    //   1011: castore
    //   1012: dup
    //   1013: bipush 17
    //   1015: ldc 62
    //   1017: castore
    //   1018: dup
    //   1019: bipush 18
    //   1021: ldc 63
    //   1023: castore
    //   1024: invokestatic 67	o/KA:ˎ	([C)Ljava/lang/String;
    //   1027: invokevirtual 73	java/lang/String:intern	()Ljava/lang/String;
    //   1030: aload 5
    //   1032: invokevirtual 458	o/j:ˎ	(Ljava/lang/String;Landroid/os/Parcelable;)Lo/j;
    //   1035: bipush 15
    //   1037: newarray char
    //   1039: dup
    //   1040: iconst_0
    //   1041: ldc_w 459
    //   1044: castore
    //   1045: dup
    //   1046: iconst_1
    //   1047: ldc_w 460
    //   1050: castore
    //   1051: dup
    //   1052: iconst_2
    //   1053: ldc_w 461
    //   1056: castore
    //   1057: dup
    //   1058: iconst_3
    //   1059: ldc_w 462
    //   1062: castore
    //   1063: dup
    //   1064: iconst_4
    //   1065: ldc_w 463
    //   1068: castore
    //   1069: dup
    //   1070: iconst_5
    //   1071: ldc_w 464
    //   1074: castore
    //   1075: dup
    //   1076: bipush 6
    //   1078: ldc_w 465
    //   1081: castore
    //   1082: dup
    //   1083: bipush 7
    //   1085: ldc_w 466
    //   1088: castore
    //   1089: dup
    //   1090: bipush 8
    //   1092: ldc_w 467
    //   1095: castore
    //   1096: dup
    //   1097: bipush 9
    //   1099: ldc_w 468
    //   1102: castore
    //   1103: dup
    //   1104: bipush 10
    //   1106: ldc_w 469
    //   1109: castore
    //   1110: dup
    //   1111: bipush 11
    //   1113: ldc_w 470
    //   1116: castore
    //   1117: dup
    //   1118: bipush 12
    //   1120: ldc_w 471
    //   1123: castore
    //   1124: dup
    //   1125: bipush 13
    //   1127: ldc_w 472
    //   1130: castore
    //   1131: dup
    //   1132: bipush 14
    //   1134: ldc_w 473
    //   1137: castore
    //   1138: invokestatic 67	o/KA:ˎ	([C)Ljava/lang/String;
    //   1141: invokevirtual 73	java/lang/String:intern	()Ljava/lang/String;
    //   1144: aload_0
    //   1145: invokevirtual 44	o/KA:getIntent	()Landroid/content/Intent;
    //   1148: bipush 15
    //   1150: newarray char
    //   1152: dup
    //   1153: iconst_0
    //   1154: ldc_w 459
    //   1157: castore
    //   1158: dup
    //   1159: iconst_1
    //   1160: ldc_w 460
    //   1163: castore
    //   1164: dup
    //   1165: iconst_2
    //   1166: ldc_w 461
    //   1169: castore
    //   1170: dup
    //   1171: iconst_3
    //   1172: ldc_w 462
    //   1175: castore
    //   1176: dup
    //   1177: iconst_4
    //   1178: ldc_w 463
    //   1181: castore
    //   1182: dup
    //   1183: iconst_5
    //   1184: ldc_w 464
    //   1187: castore
    //   1188: dup
    //   1189: bipush 6
    //   1191: ldc_w 465
    //   1194: castore
    //   1195: dup
    //   1196: bipush 7
    //   1198: ldc_w 466
    //   1201: castore
    //   1202: dup
    //   1203: bipush 8
    //   1205: ldc_w 467
    //   1208: castore
    //   1209: dup
    //   1210: bipush 9
    //   1212: ldc_w 468
    //   1215: castore
    //   1216: dup
    //   1217: bipush 10
    //   1219: ldc_w 469
    //   1222: castore
    //   1223: dup
    //   1224: bipush 11
    //   1226: ldc_w 470
    //   1229: castore
    //   1230: dup
    //   1231: bipush 12
    //   1233: ldc_w 471
    //   1236: castore
    //   1237: dup
    //   1238: bipush 13
    //   1240: ldc_w 472
    //   1243: castore
    //   1244: dup
    //   1245: bipush 14
    //   1247: ldc_w 473
    //   1250: castore
    //   1251: invokestatic 67	o/KA:ˎ	([C)Ljava/lang/String;
    //   1254: invokevirtual 73	java/lang/String:intern	()Ljava/lang/String;
    //   1257: invokevirtual 425	android/content/Intent:getStringExtra	(Ljava/lang/String;)Ljava/lang/String;
    //   1260: invokevirtual 476	o/j:ˋ	(Ljava/lang/String;Ljava/lang/String;)Lo/j;
    //   1263: bipush 25
    //   1265: newarray char
    //   1267: dup
    //   1268: iconst_0
    //   1269: ldc_w 398
    //   1272: castore
    //   1273: dup
    //   1274: iconst_1
    //   1275: ldc_w 399
    //   1278: castore
    //   1279: dup
    //   1280: iconst_2
    //   1281: ldc_w 400
    //   1284: castore
    //   1285: dup
    //   1286: iconst_3
    //   1287: ldc_w 401
    //   1290: castore
    //   1291: dup
    //   1292: iconst_4
    //   1293: ldc_w 402
    //   1296: castore
    //   1297: dup
    //   1298: iconst_5
    //   1299: ldc_w 403
    //   1302: castore
    //   1303: dup
    //   1304: bipush 6
    //   1306: ldc_w 404
    //   1309: castore
    //   1310: dup
    //   1311: bipush 7
    //   1313: ldc_w 405
    //   1316: castore
    //   1317: dup
    //   1318: bipush 8
    //   1320: ldc_w 406
    //   1323: castore
    //   1324: dup
    //   1325: bipush 9
    //   1327: ldc_w 407
    //   1330: castore
    //   1331: dup
    //   1332: bipush 10
    //   1334: ldc_w 408
    //   1337: castore
    //   1338: dup
    //   1339: bipush 11
    //   1341: ldc_w 409
    //   1344: castore
    //   1345: dup
    //   1346: bipush 12
    //   1348: ldc_w 410
    //   1351: castore
    //   1352: dup
    //   1353: bipush 13
    //   1355: ldc_w 411
    //   1358: castore
    //   1359: dup
    //   1360: bipush 14
    //   1362: ldc_w 412
    //   1365: castore
    //   1366: dup
    //   1367: bipush 15
    //   1369: ldc_w 413
    //   1372: castore
    //   1373: dup
    //   1374: bipush 16
    //   1376: ldc_w 414
    //   1379: castore
    //   1380: dup
    //   1381: bipush 17
    //   1383: ldc_w 415
    //   1386: castore
    //   1387: dup
    //   1388: bipush 18
    //   1390: ldc_w 416
    //   1393: castore
    //   1394: dup
    //   1395: bipush 19
    //   1397: ldc_w 417
    //   1400: castore
    //   1401: dup
    //   1402: bipush 20
    //   1404: ldc_w 418
    //   1407: castore
    //   1408: dup
    //   1409: bipush 21
    //   1411: ldc_w 419
    //   1414: castore
    //   1415: dup
    //   1416: bipush 22
    //   1418: ldc_w 420
    //   1421: castore
    //   1422: dup
    //   1423: bipush 23
    //   1425: ldc_w 421
    //   1428: castore
    //   1429: dup
    //   1430: bipush 24
    //   1432: ldc_w 422
    //   1435: castore
    //   1436: invokestatic 67	o/KA:ˎ	([C)Ljava/lang/String;
    //   1439: invokevirtual 73	java/lang/String:intern	()Ljava/lang/String;
    //   1442: aload_2
    //   1443: invokevirtual 476	o/j:ˋ	(Ljava/lang/String;Ljava/lang/String;)Lo/j;
    //   1446: invokevirtual 478	o/j:ˎ	()V
    //   1449: goto -1211 -> 238
    //   1452: iconst_0
    //   1453: istore_3
    //   1454: goto -1253 -> 201
    // Local variable table:
    //   start	length	slot	name	signature
    //   0	1457	0	this	KA
    //   0	1457	1	paramEq	Eq
    //   0	1457	2	paramString	String
    //   201	1253	3	i	int
    //   188	3	4	bool	boolean
    //   82	949	5	localObject	Object
    // Exception table:
    //   from	to	target	type
    //   20	84	6	finally
    //   101	190	87	finally
  }
  
  /* Error */
  private void ॱˋ()
  {
    // Byte code:
    //   0: goto +14 -> 14
    //   3: iconst_1
    //   4: istore_2
    //   5: goto +308 -> 313
    //   8: bipush 15
    //   10: istore_1
    //   11: goto +352 -> 363
    //   14: goto +780 -> 794
    //   17: astore_3
    //   18: aload_3
    //   19: athrow
    //   20: bipush 16
    //   22: istore_1
    //   23: goto +725 -> 748
    //   26: getstatic 27	o/KA:ʼॱ	I
    //   29: bipush 59
    //   31: iadd
    //   32: istore_1
    //   33: iload_1
    //   34: sipush 128
    //   37: irem
    //   38: putstatic 25	o/KA:ˊˊ	I
    //   41: iload_1
    //   42: iconst_2
    //   43: irem
    //   44: ifne +6 -> 50
    //   47: goto +97 -> 144
    //   50: goto +72 -> 122
    //   53: aload_0
    //   54: getstatic 481	o/Jy$IF:send_sms_to	I
    //   57: invokevirtual 248	o/KA:getString	(I)Ljava/lang/String;
    //   60: astore_3
    //   61: aload_3
    //   62: iconst_5
    //   63: newarray char
    //   65: dup
    //   66: iconst_0
    //   67: ldc -7
    //   69: castore
    //   70: dup
    //   71: iconst_1
    //   72: ldc -6
    //   74: castore
    //   75: dup
    //   76: iconst_2
    //   77: ldc -5
    //   79: castore
    //   80: dup
    //   81: iconst_3
    //   82: ldc -4
    //   84: castore
    //   85: dup
    //   86: iconst_4
    //   87: ldc -3
    //   89: castore
    //   90: invokestatic 67	o/KA:ˎ	([C)Ljava/lang/String;
    //   93: invokevirtual 73	java/lang/String:intern	()Ljava/lang/String;
    //   96: invokevirtual 257	java/lang/String:startsWith	(Ljava/lang/String;)Z
    //   99: ifeq +6 -> 105
    //   102: goto +611 -> 713
    //   105: goto +567 -> 672
    //   108: aload_0
    //   109: getfield 85	o/KA:ॱˊ	Landroid/databinding/ViewDataBinding;
    //   112: checkcast 87	o/JK
    //   115: aload_3
    //   116: invokevirtual 484	o/JK:ॱ	(Ljava/lang/String;)V
    //   119: goto +534 -> 653
    //   122: aload_0
    //   123: getfield 172	o/KA:ʿ	Lo/Eo;
    //   126: invokevirtual 205	o/Eo:ॱ	()Ljava/util/List;
    //   129: invokeinterface 487 1 0
    //   134: iconst_1
    //   135: if_icmple +6 -> 141
    //   138: goto +434 -> 572
    //   141: goto +282 -> 423
    //   144: goto -22 -> 122
    //   147: getstatic 27	o/KA:ʼॱ	I
    //   150: bipush 99
    //   152: iadd
    //   153: istore_1
    //   154: iload_1
    //   155: sipush 128
    //   158: irem
    //   159: putstatic 25	o/KA:ˊˊ	I
    //   162: iload_1
    //   163: iconst_2
    //   164: irem
    //   165: ifne +6 -> 171
    //   168: goto +619 -> 787
    //   171: goto +373 -> 544
    //   174: aload_0
    //   175: getstatic 490	o/Jy$IF:send_sms	I
    //   178: invokevirtual 248	o/KA:getString	(I)Ljava/lang/String;
    //   181: astore_3
    //   182: aload_3
    //   183: iconst_5
    //   184: newarray char
    //   186: dup
    //   187: iconst_0
    //   188: ldc -7
    //   190: castore
    //   191: dup
    //   192: iconst_1
    //   193: ldc -6
    //   195: castore
    //   196: dup
    //   197: iconst_2
    //   198: ldc -5
    //   200: castore
    //   201: dup
    //   202: iconst_3
    //   203: ldc -4
    //   205: castore
    //   206: dup
    //   207: iconst_4
    //   208: ldc -3
    //   210: castore
    //   211: invokestatic 67	o/KA:ˎ	([C)Ljava/lang/String;
    //   214: invokevirtual 73	java/lang/String:intern	()Ljava/lang/String;
    //   217: invokevirtual 257	java/lang/String:startsWith	(Ljava/lang/String;)Z
    //   220: ifeq +6 -> 226
    //   223: goto +58 -> 281
    //   226: goto +324 -> 550
    //   229: getstatic 25	o/KA:ˊˊ	I
    //   232: bipush 55
    //   234: iadd
    //   235: istore_1
    //   236: iload_1
    //   237: sipush 128
    //   240: irem
    //   241: putstatic 27	o/KA:ʼॱ	I
    //   244: iload_1
    //   245: iconst_2
    //   246: irem
    //   247: ifeq +6 -> 253
    //   250: goto +529 -> 779
    //   253: goto +44 -> 297
    //   256: aload_0
    //   257: getfield 194	o/KA:ʾ	Lo/Eo;
    //   260: invokevirtual 205	o/Eo:ॱ	()Ljava/util/List;
    //   263: invokestatic 495	o/an:ˏ	(Ljava/util/Collection;)Z
    //   266: pop
    //   267: new 497	java/lang/NullPointerException
    //   270: dup
    //   271: invokespecial 498	java/lang/NullPointerException:<init>	()V
    //   274: athrow
    //   275: bipush 42
    //   277: istore_1
    //   278: goto +470 -> 748
    //   281: aload_0
    //   282: aload_3
    //   283: iconst_4
    //   284: invokevirtual 240	java/lang/String:substring	(I)Ljava/lang/String;
    //   287: invokespecial 242	o/KA:ॱ	(Ljava/lang/String;)Ljava/lang/String;
    //   290: invokevirtual 73	java/lang/String:intern	()Ljava/lang/String;
    //   293: astore_3
    //   294: goto +256 -> 550
    //   297: aload_0
    //   298: aload_3
    //   299: iconst_4
    //   300: invokevirtual 240	java/lang/String:substring	(I)Ljava/lang/String;
    //   303: invokespecial 242	o/KA:ॱ	(Ljava/lang/String;)Ljava/lang/String;
    //   306: invokevirtual 73	java/lang/String:intern	()Ljava/lang/String;
    //   309: astore_3
    //   310: goto +237 -> 547
    //   313: aload_0
    //   314: getfield 85	o/KA:ॱˊ	Landroid/databinding/ViewDataBinding;
    //   317: checkcast 87	o/JK
    //   320: iload_2
    //   321: invokevirtual 501	o/JK:ॱ	(Z)V
    //   324: return
    //   325: bipush 23
    //   327: istore_1
    //   328: goto +35 -> 363
    //   331: iload_1
    //   332: lookupswitch	default:+28->360, 24:+-76->256, 36:+154->486
    //   360: goto +126 -> 486
    //   363: aload 4
    //   365: astore_3
    //   366: iload_1
    //   367: lookupswitch	default:+25->392, 15:+263->630, 23:+454->821
    //   392: aload 4
    //   394: astore_3
    //   395: goto +426 -> 821
    //   398: astore_3
    //   399: aload_3
    //   400: athrow
    //   401: aload_0
    //   402: getfield 194	o/KA:ʾ	Lo/Eo;
    //   405: invokevirtual 205	o/Eo:ॱ	()Ljava/util/List;
    //   408: invokeinterface 487 1 0
    //   413: iconst_1
    //   414: if_icmple +6 -> 420
    //   417: goto +449 -> 866
    //   420: goto +362 -> 782
    //   423: aload_0
    //   424: getstatic 504	o/Jy$IF:send_email_to	I
    //   427: invokevirtual 248	o/KA:getString	(I)Ljava/lang/String;
    //   430: astore 4
    //   432: aload 4
    //   434: iconst_5
    //   435: newarray char
    //   437: dup
    //   438: iconst_0
    //   439: ldc -7
    //   441: castore
    //   442: dup
    //   443: iconst_1
    //   444: ldc -6
    //   446: castore
    //   447: dup
    //   448: iconst_2
    //   449: ldc -5
    //   451: castore
    //   452: dup
    //   453: iconst_3
    //   454: ldc -4
    //   456: castore
    //   457: dup
    //   458: iconst_4
    //   459: ldc -3
    //   461: castore
    //   462: invokestatic 67	o/KA:ˎ	([C)Ljava/lang/String;
    //   465: invokevirtual 73	java/lang/String:intern	()Ljava/lang/String;
    //   468: invokevirtual 257	java/lang/String:startsWith	(Ljava/lang/String;)Z
    //   471: ifeq +6 -> 477
    //   474: goto -466 -> 8
    //   477: goto -152 -> 325
    //   480: goto +423 -> 903
    //   483: goto -309 -> 174
    //   486: aload_0
    //   487: getfield 194	o/KA:ʾ	Lo/Eo;
    //   490: astore_3
    //   491: aload_3
    //   492: invokevirtual 205	o/Eo:ॱ	()Ljava/util/List;
    //   495: astore_3
    //   496: aload_3
    //   497: invokestatic 495	o/an:ˏ	(Ljava/util/Collection;)Z
    //   500: istore_2
    //   501: iload_2
    //   502: ifne +6 -> 508
    //   505: goto -104 -> 401
    //   508: goto +145 -> 653
    //   511: bipush 24
    //   513: istore_1
    //   514: goto -183 -> 331
    //   517: getstatic 25	o/KA:ˊˊ	I
    //   520: bipush 45
    //   522: iadd
    //   523: istore_1
    //   524: iload_1
    //   525: sipush 128
    //   528: irem
    //   529: putstatic 27	o/KA:ʼॱ	I
    //   532: iload_1
    //   533: iconst_2
    //   534: irem
    //   535: ifeq +6 -> 541
    //   538: goto -55 -> 483
    //   541: goto -367 -> 174
    //   544: goto -231 -> 313
    //   547: goto -67 -> 480
    //   550: goto -442 -> 108
    //   553: aload_0
    //   554: getfield 194	o/KA:ʾ	Lo/Eo;
    //   557: invokevirtual 205	o/Eo:ॱ	()Ljava/util/List;
    //   560: invokestatic 495	o/an:ˏ	(Ljava/util/Collection;)Z
    //   563: ifeq +6 -> 569
    //   566: goto -546 -> 20
    //   569: goto -294 -> 275
    //   572: aload_0
    //   573: getstatic 507	o/Jy$IF:send_email	I
    //   576: invokevirtual 248	o/KA:getString	(I)Ljava/lang/String;
    //   579: astore_3
    //   580: aload_3
    //   581: iconst_5
    //   582: newarray char
    //   584: dup
    //   585: iconst_0
    //   586: ldc -7
    //   588: castore
    //   589: dup
    //   590: iconst_1
    //   591: ldc -6
    //   593: castore
    //   594: dup
    //   595: iconst_2
    //   596: ldc -5
    //   598: castore
    //   599: dup
    //   600: iconst_3
    //   601: ldc -4
    //   603: castore
    //   604: dup
    //   605: iconst_4
    //   606: ldc -3
    //   608: castore
    //   609: invokestatic 67	o/KA:ˎ	([C)Ljava/lang/String;
    //   612: invokevirtual 73	java/lang/String:intern	()Ljava/lang/String;
    //   615: invokevirtual 257	java/lang/String:startsWith	(Ljava/lang/String;)Z
    //   618: ifeq +6 -> 624
    //   621: goto -392 -> 229
    //   624: goto -77 -> 547
    //   627: goto +276 -> 903
    //   630: aload_0
    //   631: aload 4
    //   633: iconst_4
    //   634: invokevirtual 240	java/lang/String:substring	(I)Ljava/lang/String;
    //   637: invokespecial 242	o/KA:ॱ	(Ljava/lang/String;)Ljava/lang/String;
    //   640: invokevirtual 73	java/lang/String:intern	()Ljava/lang/String;
    //   643: astore_3
    //   644: goto +177 -> 821
    //   647: bipush 36
    //   649: istore_1
    //   650: goto -319 -> 331
    //   653: aload_0
    //   654: getfield 172	o/KA:ʿ	Lo/Eo;
    //   657: invokevirtual 205	o/Eo:ॱ	()Ljava/util/List;
    //   660: invokestatic 495	o/an:ˏ	(Ljava/util/Collection;)Z
    //   663: ifne +6 -> 669
    //   666: goto -640 -> 26
    //   669: goto -116 -> 553
    //   672: aload_3
    //   673: iconst_1
    //   674: anewarray 316	java/lang/Object
    //   677: dup
    //   678: iconst_0
    //   679: aload_0
    //   680: aload_0
    //   681: getfield 194	o/KA:ʾ	Lo/Eo;
    //   684: invokevirtual 205	o/Eo:ॱ	()Ljava/util/List;
    //   687: iconst_0
    //   688: invokeinterface 511 2 0
    //   693: checkcast 311	o/uB
    //   696: invokevirtual 314	o/uB:ˎ	()Ljava/lang/Object;
    //   699: checkcast 69	java/lang/String
    //   702: invokespecial 334	o/KA:ˏ	(Ljava/lang/String;)Ljava/lang/String;
    //   705: aastore
    //   706: invokestatic 515	java/lang/String:format	(Ljava/lang/String;[Ljava/lang/Object;)Ljava/lang/String;
    //   709: astore_3
    //   710: goto -602 -> 108
    //   713: aload_0
    //   714: aload_3
    //   715: iconst_4
    //   716: invokevirtual 240	java/lang/String:substring	(I)Ljava/lang/String;
    //   719: invokespecial 242	o/KA:ॱ	(Ljava/lang/String;)Ljava/lang/String;
    //   722: invokevirtual 73	java/lang/String:intern	()Ljava/lang/String;
    //   725: astore_3
    //   726: goto -54 -> 672
    //   729: aload_0
    //   730: getfield 172	o/KA:ʿ	Lo/Eo;
    //   733: invokevirtual 205	o/Eo:ॱ	()Ljava/util/List;
    //   736: invokestatic 495	o/an:ˏ	(Ljava/util/Collection;)Z
    //   739: ifne +6 -> 745
    //   742: goto -739 -> 3
    //   745: goto +126 -> 871
    //   748: iload_1
    //   749: lookupswitch	default:+27->776, 16:+-20->729, 42:+-746->3
    //   776: goto -47 -> 729
    //   779: goto -482 -> 297
    //   782: iconst_1
    //   783: istore_1
    //   784: goto +92 -> 876
    //   787: iconst_3
    //   788: iconst_3
    //   789: idiv
    //   790: istore_1
    //   791: goto -478 -> 313
    //   794: getstatic 25	o/KA:ˊˊ	I
    //   797: bipush 39
    //   799: iadd
    //   800: istore_1
    //   801: iload_1
    //   802: sipush 128
    //   805: irem
    //   806: putstatic 27	o/KA:ʼॱ	I
    //   809: iload_1
    //   810: iconst_2
    //   811: irem
    //   812: ifeq +6 -> 818
    //   815: goto -304 -> 511
    //   818: goto -171 -> 647
    //   821: aload_0
    //   822: getfield 172	o/KA:ʿ	Lo/Eo;
    //   825: astore 4
    //   827: aload_3
    //   828: iconst_1
    //   829: anewarray 316	java/lang/Object
    //   832: dup
    //   833: iconst_0
    //   834: aload_0
    //   835: aload 4
    //   837: invokevirtual 205	o/Eo:ॱ	()Ljava/util/List;
    //   840: iconst_0
    //   841: invokeinterface 511 2 0
    //   846: checkcast 311	o/uB
    //   849: invokevirtual 314	o/uB:ˎ	()Ljava/lang/Object;
    //   852: checkcast 69	java/lang/String
    //   855: invokespecial 321	o/KA:ˎ	(Ljava/lang/String;)Ljava/lang/String;
    //   858: aastore
    //   859: invokestatic 515	java/lang/String:format	(Ljava/lang/String;[Ljava/lang/Object;)Ljava/lang/String;
    //   862: astore_3
    //   863: goto -236 -> 627
    //   866: iconst_0
    //   867: istore_1
    //   868: goto +8 -> 876
    //   871: iconst_0
    //   872: istore_2
    //   873: goto -726 -> 147
    //   876: iload_1
    //   877: tableswitch	default:+23->900, 0:+-360->517, 1:+-824->53
    //   900: goto -383 -> 517
    //   903: aload_0
    //   904: getfield 85	o/KA:ॱˊ	Landroid/databinding/ViewDataBinding;
    //   907: checkcast 87	o/JK
    //   910: aload_3
    //   911: invokevirtual 517	o/JK:ˋ	(Ljava/lang/String;)V
    //   914: goto -361 -> 553
    // Local variable table:
    //   start	length	slot	name	signature
    //   0	917	0	this	KA
    //   10	867	1	i	int
    //   4	869	2	bool	boolean
    //   17	2	3	localException1	Exception
    //   60	335	3	localObject1	Object
    //   398	2	3	localException2	Exception
    //   490	421	3	localObject2	Object
    //   363	473	4	localObject3	Object
    // Exception table:
    //   from	to	target	type
    //   491	496	17	java/lang/Exception
    //   486	491	398	java/lang/Exception
    //   491	496	398	java/lang/Exception
    //   496	501	398	java/lang/Exception
    //   821	827	398	java/lang/Exception
  }
  
  public Resources getResources()
  {
    break label93;
    int i = 1;
    break label35;
    label8:
    i = ˊˊ + 59;
    ʼॱ = i % 128;
    label35:
    Resources localResources;
    if (i % 2 == 0) {
      switch (i)
      {
      default: 
        return localResources;
        label62:
        localResources = super.getResources();
      }
    }
    for (;;)
    {
      try
      {
        localResources = oH.ˊ(localResources);
      }
      catch (Exception localException)
      {
        label93:
        throw localException;
      }
      i = 0;
      break label35;
      break label62;
      return localResources;
      throw new NullPointerException();
      break label8;
      i = ʼॱ + 43;
      ˊˊ = i % 128;
      if (i % 2 == 0) {
        break;
      }
    }
  }
  
  /* Error */
  public void onCallClicked(View paramView)
  {
    // Byte code:
    //   0: goto +299 -> 299
    //   3: iload_2
    //   4: tableswitch	default:+24->28, 0:+301->305, 1:+508->512
    //   28: return
    //   29: getstatic 25	o/KA:ˊˊ	I
    //   32: bipush 109
    //   34: iadd
    //   35: istore_2
    //   36: iload_2
    //   37: sipush 128
    //   40: irem
    //   41: putstatic 27	o/KA:ʼॱ	I
    //   44: iload_2
    //   45: iconst_2
    //   46: irem
    //   47: ifeq +6 -> 53
    //   50: goto +244 -> 294
    //   53: goto +261 -> 314
    //   56: aload_0
    //   57: invokestatic 430	o/Ic:ˏ	(Landroid/content/Context;)Lo/Ic;
    //   60: astore_1
    //   61: goto +17 -> 78
    //   64: astore_1
    //   65: aload_1
    //   66: invokevirtual 114	java/lang/Throwable:getCause	()Ljava/lang/Throwable;
    //   69: astore_3
    //   70: aload_3
    //   71: ifnull +5 -> 76
    //   74: aload_3
    //   75: athrow
    //   76: aload_1
    //   77: athrow
    //   78: aload_0
    //   79: invokevirtual 351	android/content/Context:getResources	()Landroid/content/res/Resources;
    //   82: ldc_w 526
    //   85: invokevirtual 355	android/content/res/Resources:getString	(I)Ljava/lang/String;
    //   88: iconst_0
    //   89: iconst_4
    //   90: invokevirtual 358	java/lang/String:substring	(II)Ljava/lang/String;
    //   93: invokevirtual 278	java/lang/String:length	()I
    //   96: iconst_0
    //   97: iadd
    //   98: aload_0
    //   99: invokevirtual 351	android/content/Context:getResources	()Landroid/content/res/Resources;
    //   102: ldc_w 527
    //   105: invokevirtual 355	android/content/res/Resources:getString	(I)Ljava/lang/String;
    //   108: iconst_0
    //   109: iconst_4
    //   110: invokevirtual 358	java/lang/String:substring	(II)Ljava/lang/String;
    //   113: iconst_2
    //   114: invokevirtual 132	java/lang/String:codePointAt	(I)I
    //   117: sipush 391
    //   120: iadd
    //   121: aload_0
    //   122: invokevirtual 351	android/content/Context:getResources	()Landroid/content/res/Resources;
    //   125: ldc_w 528
    //   128: invokevirtual 355	android/content/res/Resources:getString	(I)Ljava/lang/String;
    //   131: iconst_0
    //   132: iconst_4
    //   133: invokevirtual 358	java/lang/String:substring	(II)Ljava/lang/String;
    //   136: iconst_2
    //   137: invokevirtual 132	java/lang/String:codePointAt	(I)I
    //   140: bipush 11
    //   142: isub
    //   143: i2c
    //   144: invokestatic 139	o/O:ˋ	(IIC)Ljava/lang/Object;
    //   147: checkcast 141	java/lang/Class
    //   150: ldc_w 529
    //   153: aconst_null
    //   154: invokevirtual 146	java/lang/Class:getMethod	(Ljava/lang/String;[Ljava/lang/Class;)Ljava/lang/reflect/Method;
    //   157: aconst_null
    //   158: aconst_null
    //   159: invokevirtual 152	java/lang/reflect/Method:invoke	(Ljava/lang/Object;[Ljava/lang/Object;)Ljava/lang/Object;
    //   162: astore_3
    //   163: goto +17 -> 180
    //   166: astore_1
    //   167: aload_1
    //   168: invokevirtual 114	java/lang/Throwable:getCause	()Ljava/lang/Throwable;
    //   171: astore_3
    //   172: aload_3
    //   173: ifnull +5 -> 178
    //   176: aload_3
    //   177: athrow
    //   178: aload_1
    //   179: athrow
    //   180: aload_0
    //   181: invokevirtual 351	android/content/Context:getResources	()Landroid/content/res/Resources;
    //   184: ldc_w 530
    //   187: invokevirtual 355	android/content/res/Resources:getString	(I)Ljava/lang/String;
    //   190: iconst_0
    //   191: iconst_4
    //   192: invokevirtual 358	java/lang/String:substring	(II)Ljava/lang/String;
    //   195: invokevirtual 278	java/lang/String:length	()I
    //   198: iconst_0
    //   199: iadd
    //   200: aload_0
    //   201: invokevirtual 120	android/content/Context:getApplicationInfo	()Landroid/content/pm/ApplicationInfo;
    //   204: getfield 125	android/content/pm/ApplicationInfo:targetSdkVersion	I
    //   207: sipush 377
    //   210: iadd
    //   211: aload_0
    //   212: invokevirtual 120	android/content/Context:getApplicationInfo	()Landroid/content/pm/ApplicationInfo;
    //   215: getfield 125	android/content/pm/ApplicationInfo:targetSdkVersion	I
    //   218: bipush 25
    //   220: isub
    //   221: i2c
    //   222: invokestatic 139	o/O:ˋ	(IIC)Ljava/lang/Object;
    //   225: checkcast 141	java/lang/Class
    //   228: ldc_w 532
    //   231: aconst_null
    //   232: invokevirtual 146	java/lang/Class:getMethod	(Ljava/lang/String;[Ljava/lang/Class;)Ljava/lang/reflect/Method;
    //   235: aload_3
    //   236: aconst_null
    //   237: invokevirtual 152	java/lang/reflect/Method:invoke	(Ljava/lang/Object;[Ljava/lang/Object;)Ljava/lang/Object;
    //   240: checkcast 69	java/lang/String
    //   243: astore_3
    //   244: aload_1
    //   245: aload_3
    //   246: invokevirtual 535	o/Ic:ˎ	(Ljava/lang/String;)Lo/j;
    //   249: astore_1
    //   250: aload_1
    //   251: invokevirtual 478	o/j:ˎ	()V
    //   254: bipush 54
    //   256: iconst_0
    //   257: idiv
    //   258: istore_2
    //   259: goto -230 -> 29
    //   262: getstatic 27	o/KA:ʼॱ	I
    //   265: bipush 33
    //   267: iadd
    //   268: istore_2
    //   269: iload_2
    //   270: sipush 128
    //   273: irem
    //   274: putstatic 25	o/KA:ˊˊ	I
    //   277: iload_2
    //   278: iconst_2
    //   279: irem
    //   280: ifne +6 -> 286
    //   283: goto +6 -> 289
    //   286: goto +220 -> 506
    //   289: iconst_5
    //   290: istore_2
    //   291: goto +222 -> 513
    //   294: iconst_0
    //   295: istore_2
    //   296: goto -293 -> 3
    //   299: goto -37 -> 262
    //   302: astore_1
    //   303: aload_1
    //   304: athrow
    //   305: bipush 62
    //   307: iconst_0
    //   308: idiv
    //   309: istore_2
    //   310: return
    //   311: astore_1
    //   312: aload_1
    //   313: athrow
    //   314: iconst_1
    //   315: istore_2
    //   316: goto -313 -> 3
    //   319: aload_0
    //   320: invokestatic 430	o/Ic:ˏ	(Landroid/content/Context;)Lo/Ic;
    //   323: astore_1
    //   324: goto +17 -> 341
    //   327: astore_1
    //   328: aload_1
    //   329: invokevirtual 114	java/lang/Throwable:getCause	()Ljava/lang/Throwable;
    //   332: astore_3
    //   333: aload_3
    //   334: ifnull +5 -> 339
    //   337: aload_3
    //   338: athrow
    //   339: aload_1
    //   340: athrow
    //   341: aload_0
    //   342: invokevirtual 128	android/content/Context:getPackageName	()Ljava/lang/String;
    //   345: invokevirtual 278	java/lang/String:length	()I
    //   348: bipush 7
    //   350: isub
    //   351: aload_0
    //   352: invokevirtual 351	android/content/Context:getResources	()Landroid/content/res/Resources;
    //   355: ldc_w 536
    //   358: invokevirtual 355	android/content/res/Resources:getString	(I)Ljava/lang/String;
    //   361: iconst_0
    //   362: iconst_4
    //   363: invokevirtual 358	java/lang/String:substring	(II)Ljava/lang/String;
    //   366: invokevirtual 278	java/lang/String:length	()I
    //   369: sipush 398
    //   372: iadd
    //   373: aload_0
    //   374: invokevirtual 351	android/content/Context:getResources	()Landroid/content/res/Resources;
    //   377: ldc_w 537
    //   380: invokevirtual 355	android/content/res/Resources:getString	(I)Ljava/lang/String;
    //   383: iconst_0
    //   384: iconst_5
    //   385: invokevirtual 358	java/lang/String:substring	(II)Ljava/lang/String;
    //   388: invokevirtual 278	java/lang/String:length	()I
    //   391: iconst_5
    //   392: isub
    //   393: i2c
    //   394: invokestatic 139	o/O:ˋ	(IIC)Ljava/lang/Object;
    //   397: checkcast 141	java/lang/Class
    //   400: ldc_w 529
    //   403: aconst_null
    //   404: invokevirtual 146	java/lang/Class:getMethod	(Ljava/lang/String;[Ljava/lang/Class;)Ljava/lang/reflect/Method;
    //   407: aconst_null
    //   408: aconst_null
    //   409: invokevirtual 152	java/lang/reflect/Method:invoke	(Ljava/lang/Object;[Ljava/lang/Object;)Ljava/lang/Object;
    //   412: astore_3
    //   413: goto +17 -> 430
    //   416: astore_1
    //   417: aload_1
    //   418: invokevirtual 114	java/lang/Throwable:getCause	()Ljava/lang/Throwable;
    //   421: astore_3
    //   422: aload_3
    //   423: ifnull +5 -> 428
    //   426: aload_3
    //   427: athrow
    //   428: aload_1
    //   429: athrow
    //   430: aload_0
    //   431: invokevirtual 120	android/content/Context:getApplicationInfo	()Landroid/content/pm/ApplicationInfo;
    //   434: getfield 125	android/content/pm/ApplicationInfo:targetSdkVersion	I
    //   437: bipush 21
    //   439: isub
    //   440: aload_0
    //   441: invokevirtual 351	android/content/Context:getResources	()Landroid/content/res/Resources;
    //   444: ldc_w 538
    //   447: invokevirtual 355	android/content/res/Resources:getString	(I)Ljava/lang/String;
    //   450: iconst_0
    //   451: iconst_4
    //   452: invokevirtual 358	java/lang/String:substring	(II)Ljava/lang/String;
    //   455: invokevirtual 278	java/lang/String:length	()I
    //   458: sipush 398
    //   461: iadd
    //   462: aload_0
    //   463: invokevirtual 120	android/content/Context:getApplicationInfo	()Landroid/content/pm/ApplicationInfo;
    //   466: getfield 125	android/content/pm/ApplicationInfo:targetSdkVersion	I
    //   469: bipush 25
    //   471: isub
    //   472: i2c
    //   473: invokestatic 139	o/O:ˋ	(IIC)Ljava/lang/Object;
    //   476: checkcast 141	java/lang/Class
    //   479: ldc_w 532
    //   482: aconst_null
    //   483: invokevirtual 146	java/lang/Class:getMethod	(Ljava/lang/String;[Ljava/lang/Class;)Ljava/lang/reflect/Method;
    //   486: aload_3
    //   487: aconst_null
    //   488: invokevirtual 152	java/lang/reflect/Method:invoke	(Ljava/lang/Object;[Ljava/lang/Object;)Ljava/lang/Object;
    //   491: checkcast 69	java/lang/String
    //   494: astore_3
    //   495: aload_1
    //   496: aload_3
    //   497: invokevirtual 535	o/Ic:ˎ	(Ljava/lang/String;)Lo/j;
    //   500: invokevirtual 478	o/j:ˎ	()V
    //   503: goto -474 -> 29
    //   506: bipush 47
    //   508: istore_2
    //   509: goto +4 -> 513
    //   512: return
    //   513: iload_2
    //   514: lookupswitch	default:+26->540, 5:+-458->56, 47:+-195->319
    //   540: goto -221 -> 319
    // Local variable table:
    //   start	length	slot	name	signature
    //   0	543	0	this	KA
    //   0	543	1	paramView	View
    //   3	511	2	i	int
    //   69	428	3	localObject	Object
    // Exception table:
    //   from	to	target	type
    //   78	163	64	finally
    //   180	244	166	finally
    //   56	61	302	java/lang/Exception
    //   65	70	311	java/lang/Exception
    //   74	76	311	java/lang/Exception
    //   76	78	311	java/lang/Exception
    //   167	172	311	java/lang/Exception
    //   176	178	311	java/lang/Exception
    //   178	180	311	java/lang/Exception
    //   244	250	311	java/lang/Exception
    //   250	259	311	java/lang/Exception
    //   341	413	327	finally
    //   430	495	416	finally
  }
  
  public void onCreate(Bundle paramBundle)
  {
    break label88;
    super.onCreate(paramBundle);
    ˊ(((JK)this.ॱˊ).ᐝ);
    ʾ();
    return;
    int i;
    for (;;)
    {
      switch (i)
      {
      case 23: 
      default: 
        break;
      case 35: 
        super.onCreate(paramBundle);
        ˊ(((JK)this.ॱˊ).ᐝ);
        ʾ();
        i = 13 / 0;
        return;
        try
        {
          label88:
          i = ˊˊ + 7;
          try
          {
            ʼॱ = i % 128;
            if (i % 2 == 0) {
              i = 23;
            }
          }
          catch (Exception paramBundle)
          {
            throw paramBundle;
          }
          i = 35;
        }
        catch (Exception paramBundle)
        {
          throw paramBundle;
        }
      }
    }
  }
  
  /* Error */
  public void onPause()
  {
    // Byte code:
    //   0: goto +60 -> 60
    //   3: getstatic 27	o/KA:ʼॱ	I
    //   6: bipush 57
    //   8: iadd
    //   9: istore_1
    //   10: iload_1
    //   11: sipush 128
    //   14: irem
    //   15: putstatic 25	o/KA:ˊˊ	I
    //   18: iload_1
    //   19: iconst_2
    //   20: irem
    //   21: ifne +6 -> 27
    //   24: goto +26 -> 50
    //   27: return
    //   28: aload_0
    //   29: invokespecial 554	o/IB:onPause	()V
    //   32: aload_0
    //   33: getfield 85	o/KA:ॱˊ	Landroid/databinding/ViewDataBinding;
    //   36: astore_2
    //   37: aload_2
    //   38: checkcast 87	o/JK
    //   41: astore_2
    //   42: aload_2
    //   43: iconst_0
    //   44: invokevirtual 501	o/JK:ॱ	(Z)V
    //   47: goto -44 -> 3
    //   50: return
    //   51: goto -23 -> 28
    //   54: astore_2
    //   55: aload_2
    //   56: athrow
    //   57: astore_2
    //   58: aload_2
    //   59: athrow
    //   60: getstatic 25	o/KA:ˊˊ	I
    //   63: bipush 23
    //   65: iadd
    //   66: istore_1
    //   67: iload_1
    //   68: sipush 128
    //   71: irem
    //   72: putstatic 27	o/KA:ʼॱ	I
    //   75: iload_1
    //   76: iconst_2
    //   77: irem
    //   78: ifeq +6 -> 84
    //   81: goto -30 -> 51
    //   84: goto -56 -> 28
    // Local variable table:
    //   start	length	slot	name	signature
    //   0	87	0	this	KA
    //   9	69	1	i	int
    //   36	7	2	localObject	Object
    //   54	2	2	localException1	Exception
    //   57	2	2	localException2	Exception
    // Exception table:
    //   from	to	target	type
    //   3	10	54	java/lang/Exception
    //   10	18	54	java/lang/Exception
    //   32	37	54	java/lang/Exception
    //   37	42	54	java/lang/Exception
    //   42	47	54	java/lang/Exception
    //   42	47	57	java/lang/Exception
  }
  
  public void onResume()
  {
    for (;;)
    {
      label3:
      int i = ʼॱ + 29;
      ˊˊ = i % 128;
      if (i % 2 != 0) {
        return;
      }
      return;
      for (;;)
      {
        switch (i)
        {
        default: 
          break;
          for (;;)
          {
            i = 23;
            break;
            i = ˊˊ + 35;
            ʼॱ = i % 128;
            if (i % 2 != 0) {
              break label109;
            }
          }
        case 27: 
          super.onResume();
          ˉ();
          i = null.length;
          break label3;
          label109:
          i = 27;
        }
      }
      super.onResume();
      ˉ();
    }
  }
  
  public void onSendEmailClicked(View paramView)
  {
    break label204;
    int i = ʼॱ + 25;
    ˊˊ = i % 128;
    label30:
    Object localObject;
    if (i % 2 != 0)
    {
      break label207;
      localObject = getString(Jy.IF.inactive_email);
      if (((String)localObject).startsWith(ˎ(new char[] { -14747, 706, 18546, -26746, -8902 }).intern())) {
        break label614;
      }
      break label287;
      label85:
      ˎ(Eq.EMAIL, this.ʿ);
      i = 79 / 0;
      break label110;
      label104:
      i = 27;
      break label525;
    }
    for (;;)
    {
      label110:
      i = ˊˊ + 67;
      ʼॱ = i % 128;
      if (i % 2 == 0)
      {
        break label224;
        i = ʼॱ + 121;
        ˊˊ = i % 128;
        if (i % 2 != 0) {
          break label457;
        }
      }
      try
      {
        label164:
        paramView = Eq.EMAIL;
        try
        {
          localObject = this.ʿ;
          localObject = ((Eo)localObject).ॱ();
          localObject = ((List)localObject).get(0);
          ॱ(paramView, (String)((uB)localObject).ˋ());
        }
        catch (Exception paramView)
        {
          label204:
          label207:
          throw paramView;
        }
      }
      catch (Exception paramView)
      {
        throw paramView;
      }
      i = 56;
      break label331;
      break label555;
      for (;;)
      {
        break label555;
        i = 0;
        break label395;
        label224:
        i = 1;
        break label302;
        if (this.ʿ.ॱ().size() > 1) {
          break label579;
        }
        break label164;
        label251:
        if (an.ˏ(this.ʿ.ॱ())) {
          break label104;
        }
        break label325;
        return;
        return;
        i = 58;
        break label331;
        label278:
        i = 78;
        break label363;
        label284:
        break label462;
        label287:
        i = 74;
        break label423;
        label293:
        i = 28;
        break label363;
        label302:
        switch (i)
        {
        }
        return;
        label325:
        i = 79;
        break label525;
        switch (i)
        {
        default: 
          label331:
          break label505;
          label363:
          switch (i)
          {
          }
          break label30;
          label395:
          switch (i)
          {
          }
          break;
        }
      }
      for (;;)
      {
        label423:
        paramView = (View)localObject;
        switch (i)
        {
        default: 
          paramView = (View)localObject;
          break label555;
          i = 1;
          break;
        case 78: 
          for (;;)
          {
            paramView = ॱ(((String)localObject).substring(4)).intern();
            break;
            i = ʼॱ + 55;
            ˊˊ = i % 128;
            if (i % 2 == 0) {
              break label284;
            }
          }
          paramView = this.ʿ;
          i = 42 / 0;
          if (paramView != null) {
            break label251;
          }
          break;
          switch (i)
          {
          }
          break;
        case 74: 
          label457:
          label462:
          label505:
          label525:
          label555:
          Toast.makeText(this, paramView, 0).show();
          return;
          if (this.ʿ != null) {
            break label278;
          }
          break label293;
          return;
          label579:
          i = ʼॱ + 107;
          ˊˊ = i % 128;
          if (i % 2 == 0) {
            break label85;
          }
          break label620;
          i = 0;
          break label302;
          label614:
          i = 78;
        }
      }
      label620:
      ˎ(Eq.EMAIL, this.ʿ);
    }
  }
  
  /* Error */
  public void onSendSmsClicked(View paramView)
  {
    // Byte code:
    //   0: goto +369 -> 369
    //   3: iconst_1
    //   4: istore_2
    //   5: goto +316 -> 321
    //   8: getstatic 583	o/Jy$IF:inactive_phone	I
    //   11: istore_2
    //   12: aload_0
    //   13: iload_2
    //   14: invokevirtual 248	o/KA:getString	(I)Ljava/lang/String;
    //   17: astore_1
    //   18: iconst_5
    //   19: newarray char
    //   21: dup
    //   22: iconst_0
    //   23: ldc -7
    //   25: castore
    //   26: dup
    //   27: iconst_1
    //   28: ldc -6
    //   30: castore
    //   31: dup
    //   32: iconst_2
    //   33: ldc -5
    //   35: castore
    //   36: dup
    //   37: iconst_3
    //   38: ldc -4
    //   40: castore
    //   41: dup
    //   42: iconst_4
    //   43: ldc -3
    //   45: castore
    //   46: invokestatic 67	o/KA:ˎ	([C)Ljava/lang/String;
    //   49: astore 4
    //   51: aload_1
    //   52: aload 4
    //   54: invokevirtual 73	java/lang/String:intern	()Ljava/lang/String;
    //   57: invokevirtual 257	java/lang/String:startsWith	(Ljava/lang/String;)Z
    //   60: istore_3
    //   61: iload_3
    //   62: ifeq +6 -> 68
    //   65: goto +360 -> 425
    //   68: goto +220 -> 288
    //   71: aload_0
    //   72: getfield 194	o/KA:ʾ	Lo/Eo;
    //   75: ifnull +6 -> 81
    //   78: goto +352 -> 430
    //   81: goto -73 -> 8
    //   84: iconst_0
    //   85: istore_2
    //   86: goto +235 -> 321
    //   89: aload_0
    //   90: getfield 194	o/KA:ʾ	Lo/Eo;
    //   93: invokevirtual 205	o/Eo:ॱ	()Ljava/util/List;
    //   96: invokeinterface 487 1 0
    //   101: iconst_1
    //   102: if_icmple +6 -> 108
    //   105: goto +406 -> 511
    //   108: bipush 63
    //   110: istore_2
    //   111: goto +31 -> 142
    //   114: return
    //   115: getstatic 25	o/KA:ˊˊ	I
    //   118: bipush 101
    //   120: iadd
    //   121: istore_2
    //   122: iload_2
    //   123: sipush 128
    //   126: irem
    //   127: putstatic 27	o/KA:ʼॱ	I
    //   130: iload_2
    //   131: iconst_2
    //   132: irem
    //   133: ifeq +6 -> 139
    //   136: goto -52 -> 84
    //   139: goto -136 -> 3
    //   142: iload_2
    //   143: lookupswitch	default:+25->168, 63:+28->171, 79:+251->394
    //   168: goto +226 -> 394
    //   171: aload_0
    //   172: getstatic 274	o/Eq:SMS	Lo/Eq;
    //   175: aload_0
    //   176: getfield 194	o/KA:ʾ	Lo/Eo;
    //   179: invokevirtual 205	o/Eo:ॱ	()Ljava/util/List;
    //   182: iconst_0
    //   183: invokeinterface 511 2 0
    //   188: checkcast 311	o/uB
    //   191: invokevirtual 570	o/uB:ˋ	()Ljava/lang/Object;
    //   194: checkcast 69	java/lang/String
    //   197: invokespecial 180	o/KA:ॱ	(Lo/Eq;Ljava/lang/String;)V
    //   200: return
    //   201: aload_1
    //   202: astore 4
    //   204: iload_2
    //   205: tableswitch	default:+23->228, 0:+29->234, 1:+209->414
    //   228: aload_1
    //   229: astore 4
    //   231: goto +183 -> 414
    //   234: getstatic 27	o/KA:ʼॱ	I
    //   237: bipush 93
    //   239: iadd
    //   240: istore_2
    //   241: iload_2
    //   242: sipush 128
    //   245: irem
    //   246: putstatic 25	o/KA:ˊˊ	I
    //   249: iload_2
    //   250: iconst_2
    //   251: irem
    //   252: ifne +6 -> 258
    //   255: goto +92 -> 347
    //   258: goto +114 -> 372
    //   261: bipush 97
    //   263: istore_2
    //   264: goto +29 -> 293
    //   267: aload_0
    //   268: getfield 194	o/KA:ʾ	Lo/Eo;
    //   271: astore_1
    //   272: bipush 84
    //   274: iconst_0
    //   275: idiv
    //   276: istore_2
    //   277: aload_1
    //   278: ifnull +6 -> 284
    //   281: goto +236 -> 517
    //   284: goto +124 -> 408
    //   287: return
    //   288: iconst_1
    //   289: istore_2
    //   290: goto -89 -> 201
    //   293: iload_2
    //   294: lookupswitch	default:+26->320, 69:+-7->287, 97:+-180->114
    //   320: return
    //   321: iload_2
    //   322: tableswitch	default:+22->344, 0:+-55->267, 1:+-251->71
    //   344: goto -273 -> 71
    //   347: aload_0
    //   348: aload_1
    //   349: iconst_4
    //   350: invokevirtual 240	java/lang/String:substring	(I)Ljava/lang/String;
    //   353: invokespecial 242	o/KA:ॱ	(Ljava/lang/String;)Ljava/lang/String;
    //   356: invokevirtual 73	java/lang/String:intern	()Ljava/lang/String;
    //   359: astore_1
    //   360: aconst_null
    //   361: arraylength
    //   362: istore_2
    //   363: goto +86 -> 449
    //   366: astore_1
    //   367: aload_1
    //   368: athrow
    //   369: goto -254 -> 115
    //   372: aload_0
    //   373: aload_1
    //   374: iconst_4
    //   375: invokevirtual 240	java/lang/String:substring	(I)Ljava/lang/String;
    //   378: invokespecial 242	o/KA:ॱ	(Ljava/lang/String;)Ljava/lang/String;
    //   381: invokevirtual 73	java/lang/String:intern	()Ljava/lang/String;
    //   384: astore_1
    //   385: goto +64 -> 449
    //   388: bipush 69
    //   390: istore_2
    //   391: goto -98 -> 293
    //   394: aload_0
    //   395: getstatic 274	o/Eq:SMS	Lo/Eq;
    //   398: aload_0
    //   399: getfield 194	o/KA:ʾ	Lo/Eo;
    //   402: invokespecial 568	o/KA:ˎ	(Lo/Eq;Lo/Eo;)V
    //   405: goto +50 -> 455
    //   408: bipush 40
    //   410: istore_2
    //   411: goto +71 -> 482
    //   414: aload_0
    //   415: aload 4
    //   417: iconst_0
    //   418: invokestatic 576	android/widget/Toast:makeText	(Landroid/content/Context;Ljava/lang/CharSequence;I)Landroid/widget/Toast;
    //   421: invokevirtual 579	android/widget/Toast:show	()V
    //   424: return
    //   425: iconst_0
    //   426: istore_2
    //   427: goto -226 -> 201
    //   430: aload_0
    //   431: getfield 194	o/KA:ʾ	Lo/Eo;
    //   434: invokevirtual 205	o/Eo:ॱ	()Ljava/util/List;
    //   437: invokestatic 495	o/an:ˏ	(Ljava/util/Collection;)Z
    //   440: ifeq +6 -> 446
    //   443: goto -435 -> 8
    //   446: goto -357 -> 89
    //   449: aload_1
    //   450: astore 4
    //   452: goto -38 -> 414
    //   455: getstatic 25	o/KA:ˊˊ	I
    //   458: bipush 43
    //   460: iadd
    //   461: istore_2
    //   462: iload_2
    //   463: sipush 128
    //   466: irem
    //   467: putstatic 27	o/KA:ʼॱ	I
    //   470: iload_2
    //   471: iconst_2
    //   472: irem
    //   473: ifeq +6 -> 479
    //   476: goto -215 -> 261
    //   479: goto -91 -> 388
    //   482: iload_2
    //   483: lookupswitch	default:+25->508, 40:+-475->8, 63:+-53->430
    //   508: goto -500 -> 8
    //   511: bipush 79
    //   513: istore_2
    //   514: goto -372 -> 142
    //   517: bipush 63
    //   519: istore_2
    //   520: goto -38 -> 482
    //   523: astore_1
    //   524: aload_1
    //   525: athrow
    // Local variable table:
    //   start	length	slot	name	signature
    //   0	526	0	this	KA
    //   0	526	1	paramView	View
    //   4	516	2	i	int
    //   60	2	3	bool	boolean
    //   49	402	4	localObject	Object
    // Exception table:
    //   from	to	target	type
    //   18	51	366	java/lang/Exception
    //   8	12	523	java/lang/Exception
    //   12	18	523	java/lang/Exception
    //   18	51	523	java/lang/Exception
    //   51	61	523	java/lang/Exception
  }
  
  public void ˋ(ز paramز)
  {
    for (;;)
    {
      try
      {
        paramز.ॱ(true);
        paramز.ˏ(true);
        continue;
        continue;
        continue;
        i = 44;
        switch (i)
        {
        default: 
          return;
          i = ˊˊ + 45;
          ʼॱ = i % 128;
          if (i % 2 != 0) {
            break label117;
          }
          break;
        case 44: 
          return;
          i = ʼॱ + 119;
          ˊˊ = i % 128;
          if (i % 2 == 0) {
            continue;
          }
          break;
        case 92: 
          i = 39 / 0;
        }
      }
      catch (Exception paramز)
      {
        throw paramز;
      }
      return;
      label117:
      int i = 92;
    }
  }
  
  /* Error */
  public int ˎ()
  {
    // Byte code:
    //   0: goto +76 -> 76
    //   3: iload_1
    //   4: lookupswitch	default:+28->32, 6:+81->85, 93:+92->96
    //   32: goto +53 -> 85
    //   35: bipush 6
    //   37: istore_1
    //   38: goto -35 -> 3
    //   41: astore_3
    //   42: aload_3
    //   43: athrow
    //   44: astore_3
    //   45: aload_3
    //   46: athrow
    //   47: getstatic 25	o/KA:ˊˊ	I
    //   50: istore_1
    //   51: iload_1
    //   52: bipush 19
    //   54: iadd
    //   55: istore_1
    //   56: iload_1
    //   57: sipush 128
    //   60: irem
    //   61: putstatic 27	o/KA:ʼॱ	I
    //   64: iload_1
    //   65: iconst_2
    //   66: irem
    //   67: ifeq +6 -> 73
    //   70: goto -35 -> 35
    //   73: goto +6 -> 79
    //   76: goto -29 -> 47
    //   79: bipush 93
    //   81: istore_1
    //   82: goto -79 -> 3
    //   85: getstatic 594	o/Jy$ˊ:activity_pick_otp_option	I
    //   88: istore_1
    //   89: iconst_3
    //   90: iconst_0
    //   91: idiv
    //   92: istore_2
    //   93: goto +10 -> 103
    //   96: getstatic 594	o/Jy$ˊ:activity_pick_otp_option	I
    //   99: istore_1
    //   100: goto +3 -> 103
    //   103: getstatic 25	o/KA:ˊˊ	I
    //   106: bipush 11
    //   108: iadd
    //   109: istore_2
    //   110: iload_2
    //   111: sipush 128
    //   114: irem
    //   115: putstatic 27	o/KA:ʼॱ	I
    //   118: iload_2
    //   119: iconst_2
    //   120: irem
    //   121: ifeq +5 -> 126
    //   124: iload_1
    //   125: ireturn
    //   126: iload_1
    //   127: ireturn
    // Local variable table:
    //   start	length	slot	name	signature
    //   0	128	0	this	KA
    //   3	124	1	i	int
    //   92	29	2	j	int
    //   41	2	3	localException1	Exception
    //   44	2	3	localException2	Exception
    // Exception table:
    //   from	to	target	type
    //   56	64	41	java/lang/Exception
    //   47	51	44	java/lang/Exception
  }
}
