package o;

import android.view.View;

public final class KD
  extends ID<Kl, KO.iF, If>
{
  private static int ˋ = 0;
  private static char[] ˎ = { 95, 183, 184, 186, 184, 192, 60, 117, 119, 112, 105, 80, 84, 119, 117, 119, 112, 105, 80, 67, 60, 41, 83, 116, 108, 110, 108, 107, 79, 73, 111, 109, 105, 108, 109, 110, 76, 80, 110, 104, 111, 115, 106, 108, 118, 108, 108, 116, 108, 108, 118, 112, 107, 106, 108, 106, 216, 218, 213, 209, 216, 52, 107, 109, 104, 100, 107, 80, 72, 101, 107, 105, 102, 107, 106, 50, 105, 97, 95, 103, 110, 111, 107, 109, 104, 100, 107, 80, 75, 110, 147, 279, 282, 292, 293, 293, 290, 298, 293, 292 };
  private static int ˏ = 1;
  private KO.iF ˊ;
  
  public KD(KO.iF paramIF)
  {
    this.ˊ = paramIF;
  }
  
  /* Error */
  private static String ˏ(int[] paramArrayOfInt, byte[] paramArrayOfByte, boolean paramBoolean)
  {
    // Byte code:
    //   0: goto +243 -> 243
    //   3: new 81	java/lang/String
    //   6: dup
    //   7: aload_1
    //   8: invokespecial 99	java/lang/String:<init>	([C)V
    //   11: areturn
    //   12: iconst_0
    //   13: istore_3
    //   14: goto +257 -> 271
    //   17: bipush 43
    //   19: istore_3
    //   20: goto +6 -> 26
    //   23: bipush 58
    //   25: istore_3
    //   26: iload_3
    //   27: lookupswitch	default:+25->52, 43:+532->559, 58:+-15->12
    //   52: goto +507 -> 559
    //   55: getstatic 21	o/KD:ˏ	I
    //   58: bipush 11
    //   60: iadd
    //   61: istore_3
    //   62: iload_3
    //   63: sipush 128
    //   66: irem
    //   67: putstatic 19	o/KD:ˋ	I
    //   70: iload_3
    //   71: iconst_2
    //   72: irem
    //   73: ifeq +6 -> 79
    //   76: goto -59 -> 17
    //   79: goto -56 -> 23
    //   82: bipush 81
    //   84: istore 4
    //   86: goto +388 -> 474
    //   89: getstatic 19	o/KD:ˋ	I
    //   92: bipush 39
    //   94: iadd
    //   95: istore 8
    //   97: iload 8
    //   99: sipush 128
    //   102: irem
    //   103: putstatic 21	o/KD:ˏ	I
    //   106: iload 8
    //   108: iconst_2
    //   109: irem
    //   110: ifne +6 -> 116
    //   113: goto +306 -> 419
    //   116: goto +504 -> 620
    //   119: aload_0
    //   120: iconst_0
    //   121: iaload
    //   122: istore_3
    //   123: aload_0
    //   124: iconst_1
    //   125: iaload
    //   126: istore 5
    //   128: aload_0
    //   129: iconst_2
    //   130: iaload
    //   131: istore 6
    //   133: aload_0
    //   134: iconst_3
    //   135: iaload
    //   136: istore 7
    //   138: getstatic 71	o/KD:ˎ	[C
    //   141: astore 10
    //   143: iload 5
    //   145: newarray char
    //   147: astore 9
    //   149: aload 10
    //   151: iload_3
    //   152: aload 9
    //   154: iconst_0
    //   155: iload 5
    //   157: invokestatic 105	java/lang/System:arraycopy	(Ljava/lang/Object;ILjava/lang/Object;II)V
    //   160: aload_1
    //   161: ifnull +6 -> 167
    //   164: goto +375 -> 539
    //   167: aload 9
    //   169: astore_1
    //   170: goto +394 -> 564
    //   173: aload 10
    //   175: iload 4
    //   177: aload 9
    //   179: iload 4
    //   181: caload
    //   182: iconst_1
    //   183: ishl
    //   184: iconst_1
    //   185: iadd
    //   186: iload_3
    //   187: isub
    //   188: i2c
    //   189: castore
    //   190: goto +391 -> 581
    //   193: aload_1
    //   194: iload 4
    //   196: baload
    //   197: ifne +6 -> 203
    //   200: goto -27 -> 173
    //   203: goto +192 -> 395
    //   206: goto +443 -> 649
    //   209: goto +421 -> 630
    //   212: iload 4
    //   214: lookupswitch	default:+26->240, 34:+-211->3, 80:+502->716
    //   240: goto +476 -> 716
    //   243: goto -124 -> 119
    //   246: aload 9
    //   248: iload_3
    //   249: aload_1
    //   250: iload 5
    //   252: iload_3
    //   253: isub
    //   254: iconst_1
    //   255: isub
    //   256: caload
    //   257: castore
    //   258: iload_3
    //   259: iconst_1
    //   260: iadd
    //   261: istore_3
    //   262: goto +163 -> 425
    //   265: bipush 85
    //   267: istore_3
    //   268: goto +239 -> 507
    //   271: getstatic 21	o/KD:ˏ	I
    //   274: bipush 31
    //   276: iadd
    //   277: istore 4
    //   279: iload 4
    //   281: sipush 128
    //   284: irem
    //   285: putstatic 19	o/KD:ˋ	I
    //   288: iload 4
    //   290: iconst_2
    //   291: irem
    //   292: ifeq +6 -> 298
    //   295: goto -89 -> 206
    //   298: goto +351 -> 649
    //   301: aload 9
    //   303: astore_1
    //   304: goto +20 -> 324
    //   307: iload 5
    //   309: newarray char
    //   311: astore 9
    //   313: iconst_0
    //   314: istore_3
    //   315: goto +315 -> 630
    //   318: goto +312 -> 630
    //   321: goto +14 -> 335
    //   324: iload 6
    //   326: ifle +6 -> 332
    //   329: goto -274 -> 55
    //   332: goto -329 -> 3
    //   335: iload 4
    //   337: iload 5
    //   339: if_icmpge +6 -> 345
    //   342: goto +310 -> 652
    //   345: goto +230 -> 575
    //   348: iload 5
    //   350: newarray char
    //   352: astore 9
    //   354: aload_1
    //   355: iconst_0
    //   356: aload 9
    //   358: iconst_0
    //   359: iload 5
    //   361: invokestatic 105	java/lang/System:arraycopy	(Ljava/lang/Object;ILjava/lang/Object;II)V
    //   364: aload 9
    //   366: iconst_0
    //   367: aload_1
    //   368: iload 5
    //   370: iload 7
    //   372: isub
    //   373: iload 7
    //   375: invokestatic 105	java/lang/System:arraycopy	(Ljava/lang/Object;ILjava/lang/Object;II)V
    //   378: aload 9
    //   380: iload 7
    //   382: aload_1
    //   383: iconst_0
    //   384: iload 5
    //   386: iload 7
    //   388: isub
    //   389: invokestatic 105	java/lang/System:arraycopy	(Ljava/lang/Object;ILjava/lang/Object;II)V
    //   392: goto +204 -> 596
    //   395: aload 10
    //   397: iload 4
    //   399: aload 9
    //   401: iload 4
    //   403: caload
    //   404: iconst_1
    //   405: ishl
    //   406: iload_3
    //   407: isub
    //   408: i2c
    //   409: castore
    //   410: goto +171 -> 581
    //   413: goto -92 -> 321
    //   416: astore_0
    //   417: aload_0
    //   418: athrow
    //   419: goto -84 -> 335
    //   422: astore_0
    //   423: aload_0
    //   424: athrow
    //   425: getstatic 21	o/KD:ˏ	I
    //   428: bipush 115
    //   430: iadd
    //   431: istore 4
    //   433: iload 4
    //   435: sipush 128
    //   438: irem
    //   439: putstatic 19	o/KD:ˋ	I
    //   442: iload 4
    //   444: iconst_2
    //   445: irem
    //   446: ifeq +6 -> 452
    //   449: goto -131 -> 318
    //   452: goto -243 -> 209
    //   455: bipush 34
    //   457: istore 4
    //   459: goto -247 -> 212
    //   462: iload_3
    //   463: iload 5
    //   465: if_icmpge +6 -> 471
    //   468: goto +155 -> 623
    //   471: goto -16 -> 455
    //   474: iload 4
    //   476: lookupswitch	default:+28->504, 6:+-230->246, 81:+-175->301
    //   504: goto -203 -> 301
    //   507: iload_3
    //   508: lookupswitch	default:+28->536, 23:+-160->348, 85:+88->596
    //   536: goto +60 -> 596
    //   539: iload 5
    //   541: newarray char
    //   543: astore 10
    //   545: iconst_0
    //   546: istore_3
    //   547: iconst_0
    //   548: istore 4
    //   550: goto -461 -> 89
    //   553: bipush 23
    //   555: istore_3
    //   556: goto -49 -> 507
    //   559: iconst_1
    //   560: istore_3
    //   561: goto -290 -> 271
    //   564: iload 7
    //   566: ifle +6 -> 572
    //   569: goto -16 -> 553
    //   572: goto -307 -> 265
    //   575: aload 10
    //   577: astore_1
    //   578: goto -14 -> 564
    //   581: aload 10
    //   583: iload 4
    //   585: caload
    //   586: istore_3
    //   587: iload 4
    //   589: iconst_1
    //   590: iadd
    //   591: istore 4
    //   593: goto +93 -> 686
    //   596: iload_2
    //   597: ifeq +6 -> 603
    //   600: goto -293 -> 307
    //   603: goto -279 -> 324
    //   606: aload_1
    //   607: iload 4
    //   609: baload
    //   610: iconst_1
    //   611: if_icmpne +6 -> 617
    //   614: goto -441 -> 173
    //   617: goto -222 -> 395
    //   620: goto -285 -> 335
    //   623: bipush 80
    //   625: istore 4
    //   627: goto -415 -> 212
    //   630: iload_3
    //   631: iload 5
    //   633: if_icmpge +6 -> 639
    //   636: goto +6 -> 642
    //   639: goto -557 -> 82
    //   642: bipush 6
    //   644: istore 4
    //   646: goto -172 -> 474
    //   649: goto -187 -> 462
    //   652: getstatic 19	o/KD:ˋ	I
    //   655: istore 8
    //   657: iload 8
    //   659: bipush 43
    //   661: iadd
    //   662: istore 8
    //   664: iload 8
    //   666: sipush 128
    //   669: irem
    //   670: putstatic 21	o/KD:ˏ	I
    //   673: iload 8
    //   675: iconst_2
    //   676: irem
    //   677: ifne +6 -> 683
    //   680: goto -487 -> 193
    //   683: goto -77 -> 606
    //   686: getstatic 21	o/KD:ˏ	I
    //   689: bipush 45
    //   691: iadd
    //   692: istore 8
    //   694: iload 8
    //   696: sipush 128
    //   699: irem
    //   700: putstatic 19	o/KD:ˋ	I
    //   703: iload 8
    //   705: iconst_2
    //   706: irem
    //   707: ifeq +6 -> 713
    //   710: goto -297 -> 413
    //   713: goto -392 -> 321
    //   716: aload_1
    //   717: iload_3
    //   718: aload_1
    //   719: iload_3
    //   720: caload
    //   721: aload_0
    //   722: iconst_2
    //   723: iaload
    //   724: isub
    //   725: i2c
    //   726: castore
    //   727: iload_3
    //   728: iconst_1
    //   729: iadd
    //   730: istore_3
    //   731: goto -269 -> 462
    // Local variable table:
    //   start	length	slot	name	signature
    //   0	734	0	paramArrayOfInt	int[]
    //   0	734	1	paramArrayOfByte	byte[]
    //   0	734	2	paramBoolean	boolean
    //   13	718	3	i	int
    //   84	561	4	j	int
    //   126	508	5	k	int
    //   131	194	6	m	int
    //   136	429	7	n	int
    //   95	612	8	i1	int
    //   147	253	9	arrayOfChar1	char[]
    //   141	441	10	arrayOfChar2	char[]
    // Exception table:
    //   from	to	target	type
    //   652	657	416	java/lang/Exception
    //   425	433	422	java/lang/Exception
    //   433	442	422	java/lang/Exception
    //   664	673	422	java/lang/Exception
  }
  
  /* Error */
  public void ˊ(If paramIf, int paramInt)
  {
    // Byte code:
    //   0: goto +6 -> 6
    //   3: astore_1
    //   4: aload_1
    //   5: athrow
    //   6: goto +503 -> 509
    //   9: aload_1
    //   10: iconst_4
    //   11: newarray int
    //   13: dup
    //   14: iconst_0
    //   15: bipush 55
    //   17: iastore
    //   18: dup
    //   19: iconst_1
    //   20: bipush 6
    //   22: iastore
    //   23: dup
    //   24: iconst_2
    //   25: bipush 109
    //   27: iastore
    //   28: dup
    //   29: iconst_3
    //   30: bipush 6
    //   32: iastore
    //   33: bipush 6
    //   35: newarray byte
    //   37: dup
    //   38: iconst_0
    //   39: ldc 76
    //   41: bastore
    //   42: dup
    //   43: iconst_1
    //   44: ldc 76
    //   46: bastore
    //   47: dup
    //   48: iconst_2
    //   49: ldc 76
    //   51: bastore
    //   52: dup
    //   53: iconst_3
    //   54: ldc 75
    //   56: bastore
    //   57: dup
    //   58: iconst_4
    //   59: ldc 76
    //   61: bastore
    //   62: dup
    //   63: iconst_5
    //   64: ldc 76
    //   66: bastore
    //   67: iconst_0
    //   68: invokestatic 79	o/KD:ˏ	([I[BZ)Ljava/lang/String;
    //   71: invokevirtual 85	java/lang/String:intern	()Ljava/lang/String;
    //   74: invokestatic 90	o/vq:ˎ	(Ljava/lang/Object;Ljava/lang/String;)V
    //   77: aload_0
    //   78: iload_2
    //   79: invokevirtual 110	o/KD:ॱ	(I)Ljava/lang/Object;
    //   82: checkcast 112	o/Kl
    //   85: astore 4
    //   87: aload_1
    //   88: invokevirtual 115	o/KD$If:ˋ	()Landroid/databinding/ViewDataBinding;
    //   91: checkcast 117	o/JW
    //   94: astore 5
    //   96: aload 5
    //   98: iconst_4
    //   99: newarray int
    //   101: dup
    //   102: iconst_0
    //   103: bipush 61
    //   105: iastore
    //   106: dup
    //   107: iconst_1
    //   108: bipush 14
    //   110: iastore
    //   111: dup
    //   112: iconst_2
    //   113: iconst_0
    //   114: iastore
    //   115: dup
    //   116: iconst_3
    //   117: iconst_0
    //   118: iastore
    //   119: bipush 14
    //   121: newarray byte
    //   123: dup
    //   124: iconst_0
    //   125: ldc 75
    //   127: bastore
    //   128: dup
    //   129: iconst_1
    //   130: ldc 76
    //   132: bastore
    //   133: dup
    //   134: iconst_2
    //   135: ldc 76
    //   137: bastore
    //   138: dup
    //   139: iconst_3
    //   140: ldc 75
    //   142: bastore
    //   143: dup
    //   144: iconst_4
    //   145: ldc 76
    //   147: bastore
    //   148: dup
    //   149: iconst_5
    //   150: ldc 76
    //   152: bastore
    //   153: dup
    //   154: bipush 6
    //   156: ldc 75
    //   158: bastore
    //   159: dup
    //   160: bipush 7
    //   162: ldc 75
    //   164: bastore
    //   165: dup
    //   166: bipush 8
    //   168: ldc 76
    //   170: bastore
    //   171: dup
    //   172: bipush 9
    //   174: ldc 76
    //   176: bastore
    //   177: dup
    //   178: bipush 10
    //   180: ldc 75
    //   182: bastore
    //   183: dup
    //   184: bipush 11
    //   186: ldc 76
    //   188: bastore
    //   189: dup
    //   190: bipush 12
    //   192: ldc 76
    //   194: bastore
    //   195: dup
    //   196: bipush 13
    //   198: ldc 76
    //   200: bastore
    //   201: iconst_0
    //   202: invokestatic 79	o/KD:ˏ	([I[BZ)Ljava/lang/String;
    //   205: invokevirtual 85	java/lang/String:intern	()Ljava/lang/String;
    //   208: invokestatic 119	o/vq:ˋ	(Ljava/lang/Object;Ljava/lang/String;)V
    //   211: aload 5
    //   213: aload 4
    //   215: invokevirtual 122	o/JW:ˊ	(Lo/Kl;)V
    //   218: aload_1
    //   219: invokevirtual 115	o/KD$If:ˋ	()Landroid/databinding/ViewDataBinding;
    //   222: checkcast 117	o/JW
    //   225: astore 5
    //   227: aload 5
    //   229: iconst_4
    //   230: newarray int
    //   232: dup
    //   233: iconst_0
    //   234: bipush 61
    //   236: iastore
    //   237: dup
    //   238: iconst_1
    //   239: bipush 14
    //   241: iastore
    //   242: dup
    //   243: iconst_2
    //   244: iconst_0
    //   245: iastore
    //   246: dup
    //   247: iconst_3
    //   248: iconst_0
    //   249: iastore
    //   250: bipush 14
    //   252: newarray byte
    //   254: dup
    //   255: iconst_0
    //   256: ldc 75
    //   258: bastore
    //   259: dup
    //   260: iconst_1
    //   261: ldc 76
    //   263: bastore
    //   264: dup
    //   265: iconst_2
    //   266: ldc 76
    //   268: bastore
    //   269: dup
    //   270: iconst_3
    //   271: ldc 75
    //   273: bastore
    //   274: dup
    //   275: iconst_4
    //   276: ldc 76
    //   278: bastore
    //   279: dup
    //   280: iconst_5
    //   281: ldc 76
    //   283: bastore
    //   284: dup
    //   285: bipush 6
    //   287: ldc 75
    //   289: bastore
    //   290: dup
    //   291: bipush 7
    //   293: ldc 75
    //   295: bastore
    //   296: dup
    //   297: bipush 8
    //   299: ldc 76
    //   301: bastore
    //   302: dup
    //   303: bipush 9
    //   305: ldc 76
    //   307: bastore
    //   308: dup
    //   309: bipush 10
    //   311: ldc 75
    //   313: bastore
    //   314: dup
    //   315: bipush 11
    //   317: ldc 76
    //   319: bastore
    //   320: dup
    //   321: bipush 12
    //   323: ldc 76
    //   325: bastore
    //   326: dup
    //   327: bipush 13
    //   329: ldc 76
    //   331: bastore
    //   332: iconst_0
    //   333: invokestatic 79	o/KD:ˏ	([I[BZ)Ljava/lang/String;
    //   336: invokevirtual 85	java/lang/String:intern	()Ljava/lang/String;
    //   339: invokestatic 119	o/vq:ˋ	(Ljava/lang/Object;Ljava/lang/String;)V
    //   342: aload 5
    //   344: aload_0
    //   345: invokevirtual 125	o/KD:ˏ	()Lo/KO$iF;
    //   348: invokevirtual 127	o/JW:ˋ	(Lo/KO$iF;)V
    //   351: aload_1
    //   352: getfield 130	o/KD$If:ॱ	Landroid/view/View;
    //   355: astore_1
    //   356: aload_1
    //   357: iconst_4
    //   358: newarray int
    //   360: dup
    //   361: iconst_0
    //   362: bipush 75
    //   364: iastore
    //   365: dup
    //   366: iconst_1
    //   367: bipush 15
    //   369: iastore
    //   370: dup
    //   371: iconst_2
    //   372: iconst_0
    //   373: iastore
    //   374: dup
    //   375: iconst_3
    //   376: bipush 6
    //   378: iastore
    //   379: bipush 15
    //   381: newarray byte
    //   383: dup
    //   384: iconst_0
    //   385: ldc 76
    //   387: bastore
    //   388: dup
    //   389: iconst_1
    //   390: ldc 75
    //   392: bastore
    //   393: dup
    //   394: iconst_2
    //   395: ldc 76
    //   397: bastore
    //   398: dup
    //   399: iconst_3
    //   400: ldc 76
    //   402: bastore
    //   403: dup
    //   404: iconst_4
    //   405: ldc 75
    //   407: bastore
    //   408: dup
    //   409: iconst_5
    //   410: ldc 75
    //   412: bastore
    //   413: dup
    //   414: bipush 6
    //   416: ldc 76
    //   418: bastore
    //   419: dup
    //   420: bipush 7
    //   422: ldc 76
    //   424: bastore
    //   425: dup
    //   426: bipush 8
    //   428: ldc 76
    //   430: bastore
    //   431: dup
    //   432: bipush 9
    //   434: ldc 75
    //   436: bastore
    //   437: dup
    //   438: bipush 10
    //   440: ldc 76
    //   442: bastore
    //   443: dup
    //   444: bipush 11
    //   446: ldc 76
    //   448: bastore
    //   449: dup
    //   450: bipush 12
    //   452: ldc 75
    //   454: bastore
    //   455: dup
    //   456: bipush 13
    //   458: ldc 76
    //   460: bastore
    //   461: dup
    //   462: bipush 14
    //   464: ldc 76
    //   466: bastore
    //   467: iconst_0
    //   468: invokestatic 79	o/KD:ˏ	([I[BZ)Ljava/lang/String;
    //   471: invokevirtual 85	java/lang/String:intern	()Ljava/lang/String;
    //   474: invokestatic 119	o/vq:ˋ	(Ljava/lang/Object;Ljava/lang/String;)V
    //   477: aload_1
    //   478: aload 4
    //   480: invokevirtual 136	android/view/View:setTag	(Ljava/lang/Object;)V
    //   483: getstatic 19	o/KD:ˋ	I
    //   486: bipush 37
    //   488: iadd
    //   489: istore_2
    //   490: iload_2
    //   491: sipush 128
    //   494: irem
    //   495: putstatic 21	o/KD:ˏ	I
    //   498: iload_2
    //   499: iconst_2
    //   500: irem
    //   501: ifne +4 -> 505
    //   504: return
    //   505: return
    //   506: goto -497 -> 9
    //   509: getstatic 21	o/KD:ˏ	I
    //   512: istore_3
    //   513: iload_3
    //   514: bipush 63
    //   516: iadd
    //   517: istore_3
    //   518: iload_3
    //   519: sipush 128
    //   522: irem
    //   523: putstatic 19	o/KD:ˋ	I
    //   526: iload_3
    //   527: iconst_2
    //   528: irem
    //   529: ifeq +6 -> 535
    //   532: goto -26 -> 506
    //   535: goto -526 -> 9
    //   538: astore_1
    //   539: aload_1
    //   540: athrow
    // Local variable table:
    //   start	length	slot	name	signature
    //   0	541	0	this	KD
    //   0	541	1	paramIf	If
    //   0	541	2	paramInt	int
    //   512	17	3	i	int
    //   85	394	4	localKl	Kl
    //   94	249	5	localJW	JW
    // Exception table:
    //   from	to	target	type
    //   9	483	3	java/lang/Exception
    //   518	526	3	java/lang/Exception
    //   509	513	538	java/lang/Exception
  }
  
  /* Error */
  public If ˎ(android.view.ViewGroup paramViewGroup, int paramInt)
  {
    // Byte code:
    //   0: goto +447 -> 447
    //   3: aload_1
    //   4: iconst_4
    //   5: newarray int
    //   7: dup
    //   8: iconst_0
    //   9: iconst_0
    //   10: iastore
    //   11: dup
    //   12: iconst_1
    //   13: bipush 6
    //   15: iastore
    //   16: dup
    //   17: iconst_2
    //   18: bipush 79
    //   20: iastore
    //   21: dup
    //   22: iconst_3
    //   23: iconst_0
    //   24: iastore
    //   25: bipush 6
    //   27: newarray byte
    //   29: dup
    //   30: iconst_0
    //   31: ldc 76
    //   33: bastore
    //   34: dup
    //   35: iconst_1
    //   36: ldc 76
    //   38: bastore
    //   39: dup
    //   40: iconst_2
    //   41: ldc 76
    //   43: bastore
    //   44: dup
    //   45: iconst_3
    //   46: ldc 76
    //   48: bastore
    //   49: dup
    //   50: iconst_4
    //   51: ldc 76
    //   53: bastore
    //   54: dup
    //   55: iconst_5
    //   56: ldc 75
    //   58: bastore
    //   59: iconst_0
    //   60: invokestatic 79	o/KD:ˏ	([I[BZ)Ljava/lang/String;
    //   63: invokevirtual 85	java/lang/String:intern	()Ljava/lang/String;
    //   66: invokestatic 90	o/vq:ˎ	(Ljava/lang/Object;Ljava/lang/String;)V
    //   69: aload_0
    //   70: aload_1
    //   71: getstatic 150	o/Jy$ˊ:layout_payment_transfer	I
    //   74: invokevirtual 153	o/KD:ॱ	(Landroid/view/ViewGroup;I)Landroid/view/View;
    //   77: astore_1
    //   78: aload_1
    //   79: iconst_4
    //   80: newarray int
    //   82: dup
    //   83: iconst_0
    //   84: bipush 6
    //   86: iastore
    //   87: dup
    //   88: iconst_1
    //   89: bipush 49
    //   91: iastore
    //   92: dup
    //   93: iconst_2
    //   94: iconst_3
    //   95: iastore
    //   96: dup
    //   97: iconst_3
    //   98: bipush 30
    //   100: iastore
    //   101: bipush 49
    //   103: newarray byte
    //   105: dup
    //   106: iconst_0
    //   107: ldc 75
    //   109: bastore
    //   110: dup
    //   111: iconst_1
    //   112: ldc 75
    //   114: bastore
    //   115: dup
    //   116: iconst_2
    //   117: ldc 75
    //   119: bastore
    //   120: dup
    //   121: iconst_3
    //   122: ldc 75
    //   124: bastore
    //   125: dup
    //   126: iconst_4
    //   127: ldc 76
    //   129: bastore
    //   130: dup
    //   131: iconst_5
    //   132: ldc 75
    //   134: bastore
    //   135: dup
    //   136: bipush 6
    //   138: ldc 75
    //   140: bastore
    //   141: dup
    //   142: bipush 7
    //   144: ldc 76
    //   146: bastore
    //   147: dup
    //   148: bipush 8
    //   150: ldc 75
    //   152: bastore
    //   153: dup
    //   154: bipush 9
    //   156: ldc 75
    //   158: bastore
    //   159: dup
    //   160: bipush 10
    //   162: ldc 75
    //   164: bastore
    //   165: dup
    //   166: bipush 11
    //   168: ldc 76
    //   170: bastore
    //   171: dup
    //   172: bipush 12
    //   174: ldc 75
    //   176: bastore
    //   177: dup
    //   178: bipush 13
    //   180: ldc 75
    //   182: bastore
    //   183: dup
    //   184: bipush 14
    //   186: ldc 75
    //   188: bastore
    //   189: dup
    //   190: bipush 15
    //   192: ldc 75
    //   194: bastore
    //   195: dup
    //   196: bipush 16
    //   198: ldc 75
    //   200: bastore
    //   201: dup
    //   202: bipush 17
    //   204: ldc 75
    //   206: bastore
    //   207: dup
    //   208: bipush 18
    //   210: ldc 76
    //   212: bastore
    //   213: dup
    //   214: bipush 19
    //   216: ldc 76
    //   218: bastore
    //   219: dup
    //   220: bipush 20
    //   222: ldc 76
    //   224: bastore
    //   225: dup
    //   226: bipush 21
    //   228: ldc 76
    //   230: bastore
    //   231: dup
    //   232: bipush 22
    //   234: ldc 75
    //   236: bastore
    //   237: dup
    //   238: bipush 23
    //   240: ldc 76
    //   242: bastore
    //   243: dup
    //   244: bipush 24
    //   246: ldc 76
    //   248: bastore
    //   249: dup
    //   250: bipush 25
    //   252: ldc 76
    //   254: bastore
    //   255: dup
    //   256: bipush 26
    //   258: ldc 76
    //   260: bastore
    //   261: dup
    //   262: bipush 27
    //   264: ldc 75
    //   266: bastore
    //   267: dup
    //   268: bipush 28
    //   270: ldc 75
    //   272: bastore
    //   273: dup
    //   274: bipush 29
    //   276: ldc 76
    //   278: bastore
    //   279: dup
    //   280: bipush 30
    //   282: ldc 75
    //   284: bastore
    //   285: dup
    //   286: bipush 31
    //   288: ldc 76
    //   290: bastore
    //   291: dup
    //   292: bipush 32
    //   294: ldc 76
    //   296: bastore
    //   297: dup
    //   298: bipush 33
    //   300: ldc 76
    //   302: bastore
    //   303: dup
    //   304: bipush 34
    //   306: ldc 76
    //   308: bastore
    //   309: dup
    //   310: bipush 35
    //   312: ldc 76
    //   314: bastore
    //   315: dup
    //   316: bipush 36
    //   318: ldc 76
    //   320: bastore
    //   321: dup
    //   322: bipush 37
    //   324: ldc 76
    //   326: bastore
    //   327: dup
    //   328: bipush 38
    //   330: ldc 75
    //   332: bastore
    //   333: dup
    //   334: bipush 39
    //   336: ldc 76
    //   338: bastore
    //   339: dup
    //   340: bipush 40
    //   342: ldc 76
    //   344: bastore
    //   345: dup
    //   346: bipush 41
    //   348: ldc 75
    //   350: bastore
    //   351: dup
    //   352: bipush 42
    //   354: ldc 76
    //   356: bastore
    //   357: dup
    //   358: bipush 43
    //   360: ldc 75
    //   362: bastore
    //   363: dup
    //   364: bipush 44
    //   366: ldc 75
    //   368: bastore
    //   369: dup
    //   370: bipush 45
    //   372: ldc 75
    //   374: bastore
    //   375: dup
    //   376: bipush 46
    //   378: ldc 76
    //   380: bastore
    //   381: dup
    //   382: bipush 47
    //   384: ldc 76
    //   386: bastore
    //   387: dup
    //   388: bipush 48
    //   390: ldc 76
    //   392: bastore
    //   393: iconst_1
    //   394: invokestatic 79	o/KD:ˏ	([I[BZ)Ljava/lang/String;
    //   397: invokevirtual 85	java/lang/String:intern	()Ljava/lang/String;
    //   400: invokestatic 119	o/vq:ˋ	(Ljava/lang/Object;Ljava/lang/String;)V
    //   403: new 7	o/KD$If
    //   406: dup
    //   407: aload_1
    //   408: invokespecial 156	o/KD$If:<init>	(Landroid/view/View;)V
    //   411: astore_1
    //   412: goto +59 -> 471
    //   415: bipush 25
    //   417: istore_2
    //   418: iload_2
    //   419: lookupswitch	default:+25->444, 25:+42->461, 49:+34->453
    //   444: goto +17 -> 461
    //   447: goto -444 -> 3
    //   450: astore_1
    //   451: aload_1
    //   452: athrow
    //   453: aload_1
    //   454: areturn
    //   455: bipush 49
    //   457: istore_2
    //   458: goto -40 -> 418
    //   461: bipush 18
    //   463: iconst_0
    //   464: idiv
    //   465: istore_2
    //   466: aload_1
    //   467: areturn
    //   468: astore_1
    //   469: aload_1
    //   470: athrow
    //   471: getstatic 21	o/KD:ˏ	I
    //   474: istore_2
    //   475: iload_2
    //   476: bipush 91
    //   478: iadd
    //   479: istore_2
    //   480: iload_2
    //   481: sipush 128
    //   484: irem
    //   485: putstatic 19	o/KD:ˋ	I
    //   488: iload_2
    //   489: iconst_2
    //   490: irem
    //   491: ifeq +6 -> 497
    //   494: goto -79 -> 415
    //   497: goto -42 -> 455
    // Local variable table:
    //   start	length	slot	name	signature
    //   0	500	0	this	KD
    //   0	500	1	paramViewGroup	android.view.ViewGroup
    //   0	500	2	paramInt	int
    // Exception table:
    //   from	to	target	type
    //   471	475	450	java/lang/Exception
    //   480	488	468	java/lang/Exception
  }
  
  protected KO.iF ˏ()
  {
    for (;;)
    {
      KO.iF localIF = this.ˊ;
      int i = ˋ + 109;
      ˏ = i % 128;
      if (i % 2 != 0) {
        return localIF;
      }
      try
      {
        i = ˋ + 99;
        ˏ = i % 128;
        if (i % 2 == 0) {}
      }
      catch (Exception localException)
      {
        throw localException;
      }
    }
    return localIF;
  }
  
  public static final class If
    extends p<JW>
  {
    private static long ˊॱ = -2738893063131104377L;
    private static int ˋॱ = 0;
    private static int ᐝॱ = 1;
    
    public If(View paramView)
    {
      super();
    }
    
    /* Error */
    private static String ˊ(char[] paramArrayOfChar)
    {
      // Byte code:
      //   0: goto +41 -> 41
      //   3: iload_1
      //   4: aload_0
      //   5: arraylength
      //   6: if_icmpge +6 -> 12
      //   9: goto +19 -> 28
      //   12: goto +21 -> 33
      //   15: new 37	java/lang/String
      //   18: dup
      //   19: aload 4
      //   21: invokespecial 54	java/lang/String:<init>	([C)V
      //   24: areturn
      //   25: goto +145 -> 170
      //   28: iconst_0
      //   29: istore_2
      //   30: goto +85 -> 115
      //   33: iconst_1
      //   34: istore_2
      //   35: goto +80 -> 115
      //   38: astore_0
      //   39: aload_0
      //   40: athrow
      //   41: goto +30 -> 71
      //   44: getstatic 19	o/KD$If:ᐝॱ	I
      //   47: bipush 119
      //   49: iadd
      //   50: istore_2
      //   51: iload_2
      //   52: sipush 128
      //   55: irem
      //   56: putstatic 17	o/KD$If:ˋॱ	I
      //   59: iload_2
      //   60: iconst_2
      //   61: irem
      //   62: ifeq +6 -> 68
      //   65: goto -40 -> 25
      //   68: goto +102 -> 170
      //   71: aload_0
      //   72: iconst_0
      //   73: caload
      //   74: istore_3
      //   75: aload_0
      //   76: arraylength
      //   77: iconst_1
      //   78: isub
      //   79: newarray char
      //   81: astore 4
      //   83: iconst_1
      //   84: istore_1
      //   85: goto -82 -> 3
      //   88: getstatic 17	o/KD$If:ˋॱ	I
      //   91: bipush 59
      //   93: iadd
      //   94: istore_2
      //   95: iload_2
      //   96: sipush 128
      //   99: irem
      //   100: putstatic 19	o/KD$If:ᐝॱ	I
      //   103: iload_2
      //   104: iconst_2
      //   105: irem
      //   106: ifne +6 -> 112
      //   109: goto +34 -> 143
      //   112: goto +31 -> 143
      //   115: iload_2
      //   116: tableswitch	default:+24->140, 0:+-28->88, 1:+-101->15
      //   140: goto -125 -> 15
      //   143: aload 4
      //   145: iload_1
      //   146: iconst_1
      //   147: isub
      //   148: aload_0
      //   149: iload_1
      //   150: caload
      //   151: iload_1
      //   152: iload_3
      //   153: imul
      //   154: ixor
      //   155: i2l
      //   156: getstatic 23	o/KD$If:ˊॱ	J
      //   159: lxor
      //   160: l2i
      //   161: i2c
      //   162: castore
      //   163: iload_1
      //   164: iconst_1
      //   165: iadd
      //   166: istore_1
      //   167: goto -123 -> 44
      //   170: goto -167 -> 3
      // Local variable table:
      //   start	length	slot	name	signature
      //   0	173	0	paramArrayOfChar	char[]
      //   3	164	1	i	int
      //   29	87	2	j	int
      //   74	80	3	k	int
      //   19	125	4	arrayOfChar	char[]
      // Exception table:
      //   from	to	target	type
      //   88	95	38	java/lang/Exception
      //   95	103	38	java/lang/Exception
    }
  }
}
