package o;

import android.databinding.ViewDataBinding;
import android.databinding.ViewDataBinding.If;
import android.util.SparseIntArray;
import android.widget.ImageView;
import android.widget.RelativeLayout;
import android.widget.TextView;
import java.math.BigDecimal;

public class Ke
  extends ViewDataBinding
{
  private static final ViewDataBinding.If ʼ;
  private static int ˋॱ;
  private static int ˏॱ;
  private static char[] ॱˊ;
  private static final SparseIntArray ॱॱ;
  public final TextView ʻ;
  public final TextView ʽ;
  public final TextView ˊ;
  private long ˊॱ;
  public final RelativeLayout ˎ;
  public final ImageView ॱ;
  private Kl ᐝ;
  
  static
  {
    int i;
    for (;;)
    {
      try
      {
        ˋॱ = 0;
        try
        {
          ˏॱ = 1;
          ˏॱ();
          ʼ = null;
          ॱॱ = null;
        }
        catch (Exception localException1)
        {
          throw localException1;
        }
        i = 0;
      }
      catch (Exception localException2)
      {
        throw localException2;
      }
      i = 1;
      break;
      i = 26 / 0;
      return;
      return;
      i = ˋॱ + 91;
      ˏॱ = i % 128;
      if (i % 2 == 0) {}
    }
    switch (i)
    {
    }
  }
  
  /* Error */
  public Ke(ˉ paramˉ, android.view.View paramView)
  {
    // Byte code:
    //   0: aload_0
    //   1: aload_1
    //   2: aload_2
    //   3: iconst_0
    //   4: invokespecial 45	android/databinding/ViewDataBinding:<init>	(Lo/ˉ;Landroid/view/View;I)V
    //   7: aload_0
    //   8: ldc2_w 46
    //   11: putfield 49	o/Ke:ˊॱ	J
    //   14: getstatic 37	o/Ke:ʼ	Landroid/databinding/ViewDataBinding$If;
    //   17: astore_3
    //   18: getstatic 39	o/Ke:ॱॱ	Landroid/util/SparseIntArray;
    //   21: astore 4
    //   23: aload_1
    //   24: aload_2
    //   25: iconst_5
    //   26: aload_3
    //   27: aload 4
    //   29: invokestatic 52	o/Ke:ॱ	(Lo/ˉ;Landroid/view/View;ILandroid/databinding/ViewDataBinding$If;Landroid/util/SparseIntArray;)[Ljava/lang/Object;
    //   32: astore_1
    //   33: aload_0
    //   34: aload_1
    //   35: iconst_0
    //   36: aaload
    //   37: checkcast 54	android/widget/RelativeLayout
    //   40: putfield 56	o/Ke:ˎ	Landroid/widget/RelativeLayout;
    //   43: aload_0
    //   44: getfield 56	o/Ke:ˎ	Landroid/widget/RelativeLayout;
    //   47: aconst_null
    //   48: invokevirtual 60	android/widget/RelativeLayout:setTag	(Ljava/lang/Object;)V
    //   51: aload_0
    //   52: aload_1
    //   53: iconst_2
    //   54: aaload
    //   55: checkcast 62	android/widget/TextView
    //   58: putfield 64	o/Ke:ˊ	Landroid/widget/TextView;
    //   61: aload_0
    //   62: getfield 64	o/Ke:ˊ	Landroid/widget/TextView;
    //   65: aconst_null
    //   66: invokevirtual 65	android/widget/TextView:setTag	(Ljava/lang/Object;)V
    //   69: aload_0
    //   70: aload_1
    //   71: iconst_1
    //   72: aaload
    //   73: checkcast 67	android/widget/ImageView
    //   76: putfield 69	o/Ke:ॱ	Landroid/widget/ImageView;
    //   79: aload_0
    //   80: getfield 69	o/Ke:ॱ	Landroid/widget/ImageView;
    //   83: aconst_null
    //   84: invokevirtual 70	android/widget/ImageView:setTag	(Ljava/lang/Object;)V
    //   87: aload_0
    //   88: aload_1
    //   89: iconst_3
    //   90: aaload
    //   91: checkcast 62	android/widget/TextView
    //   94: putfield 72	o/Ke:ʽ	Landroid/widget/TextView;
    //   97: aload_0
    //   98: getfield 72	o/Ke:ʽ	Landroid/widget/TextView;
    //   101: aconst_null
    //   102: invokevirtual 65	android/widget/TextView:setTag	(Ljava/lang/Object;)V
    //   105: aload_0
    //   106: aload_1
    //   107: iconst_4
    //   108: aaload
    //   109: checkcast 62	android/widget/TextView
    //   112: putfield 74	o/Ke:ʻ	Landroid/widget/TextView;
    //   115: aload_0
    //   116: getfield 74	o/Ke:ʻ	Landroid/widget/TextView;
    //   119: aconst_null
    //   120: invokevirtual 65	android/widget/TextView:setTag	(Ljava/lang/Object;)V
    //   123: aload_0
    //   124: aload_2
    //   125: invokevirtual 78	o/Ke:ˋ	(Landroid/view/View;)V
    //   128: aload_0
    //   129: invokevirtual 80	o/Ke:ˊॱ	()V
    //   132: return
    //   133: astore_1
    //   134: aload_1
    //   135: athrow
    //   136: astore_1
    //   137: aload_1
    //   138: athrow
    // Local variable table:
    //   start	length	slot	name	signature
    //   0	139	0	this	Ke
    //   0	139	1	paramˉ	ˉ
    //   0	139	2	paramView	android.view.View
    //   17	10	3	localIf	ViewDataBinding.If
    //   21	7	4	localSparseIntArray	SparseIntArray
    // Exception table:
    //   from	to	target	type
    //   14	18	133	java/lang/Exception
    //   18	23	133	java/lang/Exception
    //   23	33	133	java/lang/Exception
    //   33	132	133	java/lang/Exception
    //   7	14	136	java/lang/Exception
  }
  
  /* Error */
  private static String ˊ(int[] paramArrayOfInt, byte[] paramArrayOfByte, boolean paramBoolean)
  {
    // Byte code:
    //   0: goto +681 -> 681
    //   3: iload 5
    //   5: lookupswitch	default:+27->32, 11:+387->392, 17:+401->406
    //   32: goto +374 -> 406
    //   35: goto +422 -> 457
    //   38: aload 9
    //   40: iload 4
    //   42: caload
    //   43: istore_3
    //   44: iload 4
    //   46: iconst_1
    //   47: iadd
    //   48: istore 4
    //   50: goto +644 -> 694
    //   53: iload_3
    //   54: iload 6
    //   56: if_icmpge +6 -> 62
    //   59: goto +712 -> 771
    //   62: goto -27 -> 35
    //   65: new 83	java/lang/String
    //   68: dup
    //   69: aload_1
    //   70: invokespecial 86	java/lang/String:<init>	([C)V
    //   73: areturn
    //   74: iconst_1
    //   75: istore_3
    //   76: goto +238 -> 314
    //   79: getstatic 33	o/Ke:ˏॱ	I
    //   82: bipush 121
    //   84: iadd
    //   85: istore 4
    //   87: iload 4
    //   89: sipush 128
    //   92: irem
    //   93: putstatic 31	o/Ke:ˋॱ	I
    //   96: iload 4
    //   98: iconst_2
    //   99: irem
    //   100: ifeq +6 -> 106
    //   103: goto +555 -> 658
    //   106: goto +162 -> 268
    //   109: bipush 98
    //   111: istore 5
    //   113: goto +40 -> 153
    //   116: astore_0
    //   117: aload_0
    //   118: athrow
    //   119: getstatic 33	o/Ke:ˏॱ	I
    //   122: istore 5
    //   124: iload 5
    //   126: bipush 21
    //   128: iadd
    //   129: istore 5
    //   131: iload 5
    //   133: sipush 128
    //   136: irem
    //   137: putstatic 31	o/Ke:ˋॱ	I
    //   140: iload 5
    //   142: iconst_2
    //   143: irem
    //   144: ifeq +6 -> 150
    //   147: goto +42 -> 189
    //   150: goto +335 -> 485
    //   153: iload 5
    //   155: lookupswitch	default:+25->180, 73:+264->419, 98:+424->579
    //   180: goto +239 -> 419
    //   183: bipush 10
    //   185: istore_3
    //   186: goto +614 -> 800
    //   189: bipush 17
    //   191: istore 5
    //   193: goto -190 -> 3
    //   196: bipush 96
    //   198: istore_3
    //   199: goto +418 -> 617
    //   202: aload_0
    //   203: iconst_0
    //   204: iaload
    //   205: istore_3
    //   206: aload_0
    //   207: iconst_1
    //   208: iaload
    //   209: istore 6
    //   211: aload_0
    //   212: iconst_2
    //   213: iaload
    //   214: istore 7
    //   216: aload_0
    //   217: iconst_3
    //   218: iaload
    //   219: istore 8
    //   221: getstatic 88	o/Ke:ॱˊ	[C
    //   224: astore 9
    //   226: iload 6
    //   228: newarray char
    //   230: astore 10
    //   232: aload 9
    //   234: iload_3
    //   235: aload 10
    //   237: iconst_0
    //   238: iload 6
    //   240: invokestatic 94	java/lang/System:arraycopy	(Ljava/lang/Object;ILjava/lang/Object;II)V
    //   243: aload_1
    //   244: ifnull +6 -> 250
    //   247: goto -51 -> 196
    //   250: goto +27 -> 277
    //   253: iload_2
    //   254: ifeq +6 -> 260
    //   257: goto -74 -> 183
    //   260: goto +79 -> 339
    //   263: iconst_0
    //   264: istore_3
    //   265: goto +49 -> 314
    //   268: goto -215 -> 53
    //   271: iconst_1
    //   272: istore 4
    //   274: goto +276 -> 550
    //   277: bipush 6
    //   279: istore_3
    //   280: goto +337 -> 617
    //   283: goto -230 -> 53
    //   286: aload_1
    //   287: iload_3
    //   288: aload_1
    //   289: iload_3
    //   290: caload
    //   291: aload_0
    //   292: iconst_2
    //   293: iaload
    //   294: isub
    //   295: i2c
    //   296: castore
    //   297: iload_3
    //   298: iconst_1
    //   299: iadd
    //   300: istore_3
    //   301: goto +237 -> 538
    //   304: iload 6
    //   306: newarray char
    //   308: astore_1
    //   309: iconst_1
    //   310: istore_3
    //   311: goto -28 -> 283
    //   314: iload_3
    //   315: tableswitch	default:+21->336, 0:+-11->304, 1:+369->684
    //   336: goto -32 -> 304
    //   339: bipush 94
    //   341: istore_3
    //   342: goto +458 -> 800
    //   345: aload 9
    //   347: iload 4
    //   349: aload 10
    //   351: iload 4
    //   353: caload
    //   354: iconst_1
    //   355: ishl
    //   356: iconst_1
    //   357: iadd
    //   358: iload_3
    //   359: isub
    //   360: i2c
    //   361: castore
    //   362: goto -324 -> 38
    //   365: getstatic 31	o/Ke:ˋॱ	I
    //   368: bipush 75
    //   370: iadd
    //   371: istore_3
    //   372: iload_3
    //   373: sipush 128
    //   376: irem
    //   377: putstatic 33	o/Ke:ˏॱ	I
    //   380: iload_3
    //   381: iconst_2
    //   382: irem
    //   383: ifne +6 -> 389
    //   386: goto -123 -> 263
    //   389: goto -315 -> 74
    //   392: aload_1
    //   393: iload 4
    //   395: baload
    //   396: iconst_1
    //   397: if_icmpne +6 -> 403
    //   400: goto +393 -> 793
    //   403: goto -294 -> 109
    //   406: aload_1
    //   407: iload 4
    //   409: baload
    //   410: ifne +6 -> 416
    //   413: goto +6 -> 419
    //   416: goto +163 -> 579
    //   419: getstatic 33	o/Ke:ˏॱ	I
    //   422: iconst_5
    //   423: iadd
    //   424: istore 5
    //   426: iload 5
    //   428: sipush 128
    //   431: irem
    //   432: putstatic 31	o/Ke:ˋॱ	I
    //   435: iload 5
    //   437: iconst_2
    //   438: irem
    //   439: ifeq +6 -> 445
    //   442: goto +219 -> 661
    //   445: goto -100 -> 345
    //   448: goto +246 -> 694
    //   451: bipush 90
    //   453: istore_3
    //   454: goto +256 -> 710
    //   457: iload 7
    //   459: ifle +6 -> 465
    //   462: goto +277 -> 739
    //   465: goto -400 -> 65
    //   468: iload 8
    //   470: ifle +6 -> 476
    //   473: goto +6 -> 479
    //   476: goto -25 -> 451
    //   479: bipush 30
    //   481: istore_3
    //   482: goto +228 -> 710
    //   485: bipush 11
    //   487: istore 5
    //   489: goto -486 -> 3
    //   492: iload 6
    //   494: newarray char
    //   496: astore_1
    //   497: aload 9
    //   499: iconst_0
    //   500: aload_1
    //   501: iconst_0
    //   502: iload 6
    //   504: invokestatic 94	java/lang/System:arraycopy	(Ljava/lang/Object;ILjava/lang/Object;II)V
    //   507: aload_1
    //   508: iconst_0
    //   509: aload 9
    //   511: iload 6
    //   513: iload 8
    //   515: isub
    //   516: iload 8
    //   518: invokestatic 94	java/lang/System:arraycopy	(Ljava/lang/Object;ILjava/lang/Object;II)V
    //   521: aload_1
    //   522: iload 8
    //   524: aload 9
    //   526: iconst_0
    //   527: iload 6
    //   529: iload 8
    //   531: isub
    //   532: invokestatic 94	java/lang/System:arraycopy	(Ljava/lang/Object;ILjava/lang/Object;II)V
    //   535: goto -282 -> 253
    //   538: iload_3
    //   539: iload 6
    //   541: if_icmpge +6 -> 547
    //   544: goto +67 -> 611
    //   547: goto -276 -> 271
    //   550: iload 4
    //   552: tableswitch	default:+24->576, 0:+-266->286, 1:+-487->65
    //   576: goto -290 -> 286
    //   579: aload 9
    //   581: iload 4
    //   583: aload 10
    //   585: iload 4
    //   587: caload
    //   588: iconst_1
    //   589: ishl
    //   590: iload_3
    //   591: isub
    //   592: i2c
    //   593: castore
    //   594: goto +61 -> 655
    //   597: iload 6
    //   599: newarray char
    //   601: astore 9
    //   603: iconst_0
    //   604: istore_3
    //   605: iconst_0
    //   606: istore 4
    //   608: goto -160 -> 448
    //   611: iconst_0
    //   612: istore 4
    //   614: goto -64 -> 550
    //   617: aload 10
    //   619: astore 9
    //   621: iload_3
    //   622: lookupswitch	default:+26->648, 6:+-154->468, 96:+-25->597
    //   648: aload 10
    //   650: astore 9
    //   652: goto -184 -> 468
    //   655: goto -617 -> 38
    //   658: goto -390 -> 268
    //   661: aload 9
    //   663: iload 4
    //   665: aload 10
    //   667: iload 4
    //   669: caload
    //   670: iconst_0
    //   671: irem
    //   672: iconst_0
    //   673: iushr
    //   674: iload_3
    //   675: iadd
    //   676: i2c
    //   677: castore
    //   678: goto -640 -> 38
    //   681: goto +63 -> 744
    //   684: iload 6
    //   686: newarray char
    //   688: astore_1
    //   689: iconst_0
    //   690: istore_3
    //   691: goto -408 -> 283
    //   694: iload 4
    //   696: iload 6
    //   698: if_icmpge +6 -> 704
    //   701: goto -582 -> 119
    //   704: goto +131 -> 835
    //   707: goto -505 -> 202
    //   710: iload_3
    //   711: lookupswitch	default:+25->736, 30:+-219->492, 90:+-458->253
    //   736: goto -483 -> 253
    //   739: iconst_0
    //   740: istore_3
    //   741: goto -203 -> 538
    //   744: getstatic 33	o/Ke:ˏॱ	I
    //   747: bipush 9
    //   749: iadd
    //   750: istore_3
    //   751: iload_3
    //   752: sipush 128
    //   755: irem
    //   756: putstatic 31	o/Ke:ˋॱ	I
    //   759: iload_3
    //   760: iconst_2
    //   761: irem
    //   762: ifeq +6 -> 768
    //   765: goto -58 -> 707
    //   768: goto -566 -> 202
    //   771: aload_1
    //   772: iload_3
    //   773: aload 9
    //   775: iload 6
    //   777: iload_3
    //   778: isub
    //   779: iconst_1
    //   780: isub
    //   781: caload
    //   782: castore
    //   783: iload_3
    //   784: iconst_1
    //   785: iadd
    //   786: istore_3
    //   787: goto -708 -> 79
    //   790: astore_0
    //   791: aload_0
    //   792: athrow
    //   793: bipush 73
    //   795: istore 5
    //   797: goto -644 -> 153
    //   800: aload 9
    //   802: astore_1
    //   803: iload_3
    //   804: lookupswitch	default:+28->832, 10:+-439->365, 94:+-347->457
    //   832: goto -467 -> 365
    //   835: goto -367 -> 468
    // Local variable table:
    //   start	length	slot	name	signature
    //   0	838	0	paramArrayOfInt	int[]
    //   0	838	1	paramArrayOfByte	byte[]
    //   0	838	2	paramBoolean	boolean
    //   43	761	3	i	int
    //   40	659	4	j	int
    //   3	793	5	k	int
    //   54	725	6	m	int
    //   214	244	7	n	int
    //   219	313	8	i1	int
    //   38	763	9	localObject	Object
    //   230	436	10	arrayOfChar	char[]
    // Exception table:
    //   from	to	target	type
    //   119	124	116	java/lang/Exception
    //   131	140	116	java/lang/Exception
    //   497	507	116	java/lang/Exception
    //   507	521	116	java/lang/Exception
    //   521	535	790	java/lang/Exception
  }
  
  static void ˏॱ()
  {
    ॱˊ = new char[] { 16 };
  }
  
  public void ˊॱ()
  {
    try
    {
      this.ˊॱ = 2L;
    }
    finally
    {
      localObject = finally;
      throw localObject;
    }
    ʽ();
  }
  
  public void ˋ(Kl paramKl)
  {
    this.ᐝ = paramKl;
    try
    {
      this.ˊॱ |= 1L;
    }
    finally
    {
      paramKl = finally;
      throw paramKl;
    }
    ˊ(105);
    super.ʽ();
  }
  
  public void ˏ()
  {
    long l;
    try
    {
      l = this.ˊॱ;
      this.ˊॱ = 0L;
    }
    finally
    {
      localObject1 = finally;
      throw localObject1;
    }
    Object localObject5 = null;
    Object localObject2 = null;
    Object localObject8 = null;
    Object localObject3 = null;
    Object localObject7 = null;
    BigDecimal localBigDecimal = null;
    Object localObject4 = null;
    int i = 0;
    Object localObject6 = null;
    Kl localKl = this.ᐝ;
    if ((0x3 & l) != 0L)
    {
      localObject2 = localObject8;
      localObject3 = localObject7;
      localObject4 = localObject6;
      if (localKl != null)
      {
        localObject5 = localKl.ʽ();
        localObject2 = localKl.ˏ();
        localObject3 = localKl.ॱ();
        localBigDecimal = localKl.ˊ();
        localObject4 = localKl.ˋ();
      }
      i = ViewDataBinding.ˊ((Integer)localObject5);
      localObject5 = at.ˋ(localBigDecimal);
      localObject5 = (String)localObject5 + ˊ(new int[] { 0, 1, 0, 0 }, new byte[] { 0 }, true).intern();
      localObject4 = (String)localObject5 + (String)localObject4;
    }
    if ((0x3 & l) != 0L)
    {
      ʹ.ˊ(this.ˊ, (CharSequence)localObject4);
      r.ˋ(this.ॱ, i);
      ʹ.ˊ(this.ʽ, (CharSequence)localObject3);
      ʹ.ˊ(this.ʻ, (CharSequence)localObject2);
    }
  }
  
  public boolean ˏ(int paramInt1, Object paramObject, int paramInt2)
  {
    break label38;
    paramInt1 = ˏॱ + 99;
    ˋॱ = paramInt1 % 128;
    if (paramInt1 % 2 == 0) {
      break label36;
    }
    for (;;)
    {
      break;
      label36:
      return false;
      try
      {
        label38:
        paramInt1 = ˋॱ;
        paramInt1 += 13;
      }
      catch (Exception paramObject)
      {
        try
        {
          ˏॱ = paramInt1 % 128;
          if (paramInt1 % 2 != 0) {
            continue;
          }
        }
        catch (Exception paramObject)
        {
          throw paramObject;
        }
        paramObject = paramObject;
        throw paramObject;
      }
    }
  }
  
  public boolean ॱ()
  {
    try
    {
      long l = this.ˊॱ;
      if (l != 0L) {
        return true;
      }
    }
    finally
    {
      localObject = finally;
      throw localObject;
    }
    return false;
  }
}
