package o;

import java.io.UnsupportedEncodingException;

public class KH
  extends x
  implements ᐸ.ˏ
{
  private static int ߺ;
  private static byte ॱˈ;
  private static int ॱˉ;
  private static int ॱˌ;
  private static int ॱˍ;
  private static short[] ॱˑ;
  private static byte[] ॱـ;
  private static int ॱㆍ;
  
  static
  {
    for (;;)
    {
      int i = ॱˉ + 55;
      ॱㆍ = i % 128;
      if (i % 2 == 0) {
        return;
      }
      return;
      ॱˉ = 0;
      ॱㆍ = 1;
      ˎ();
      ॱˈ = -102;
    }
  }
  
  /* Error */
  public KH(android.content.Context paramContext)
  {
    // Byte code:
    //   0: goto +154 -> 154
    //   3: aload_0
    //   4: aload_1
    //   5: invokevirtual 40	o/KH:ॱ	(Ljava/lang/CharSequence;)Lo/ᐸ$If;
    //   8: pop
    //   9: aload_0
    //   10: aload_0
    //   11: invokevirtual 43	o/KH:ॱ	(Lo/ᐸ$ˏ;)Lo/ᐸ$If;
    //   14: pop
    //   15: aload_0
    //   16: aload_0
    //   17: invokevirtual 46	o/KH:ˊ	(Lo/ᐸ$ˏ;)Lo/ᐸ$If;
    //   20: pop
    //   21: aload_0
    //   22: iconst_0
    //   23: invokevirtual 50	o/KH:ˋ	(Z)Lo/ᐸ$If;
    //   26: pop
    //   27: return
    //   28: bipush 12
    //   30: istore_2
    //   31: goto +355 -> 386
    //   34: getstatic 26	o/KH:ॱㆍ	I
    //   37: bipush 35
    //   39: iadd
    //   40: istore_2
    //   41: iload_2
    //   42: sipush 128
    //   45: irem
    //   46: putstatic 24	o/KH:ॱˉ	I
    //   49: iload_2
    //   50: iconst_2
    //   51: irem
    //   52: ifeq +6 -> 58
    //   55: goto +96 -> 151
    //   58: aload 4
    //   60: iconst_4
    //   61: invokevirtual 56	java/lang/String:substring	(I)Ljava/lang/String;
    //   64: astore_3
    //   65: aload_0
    //   66: aload_3
    //   67: invokespecial 59	o/KH:ˊ	(Ljava/lang/String;)Ljava/lang/String;
    //   70: astore_3
    //   71: aload_3
    //   72: invokevirtual 63	java/lang/String:intern	()Ljava/lang/String;
    //   75: astore_3
    //   76: goto +242 -> 318
    //   79: aload_0
    //   80: aload_3
    //   81: iconst_4
    //   82: invokevirtual 56	java/lang/String:substring	(I)Ljava/lang/String;
    //   85: invokespecial 59	o/KH:ˊ	(Ljava/lang/String;)Ljava/lang/String;
    //   88: invokevirtual 63	java/lang/String:intern	()Ljava/lang/String;
    //   91: astore_3
    //   92: goto +333 -> 425
    //   95: getstatic 24	o/KH:ॱˉ	I
    //   98: bipush 125
    //   100: iadd
    //   101: istore_2
    //   102: iload_2
    //   103: sipush 128
    //   106: irem
    //   107: putstatic 26	o/KH:ॱㆍ	I
    //   110: iload_2
    //   111: iconst_2
    //   112: irem
    //   113: ifne +6 -> 119
    //   116: goto +80 -> 196
    //   119: goto +264 -> 383
    //   122: iload_2
    //   123: lookupswitch	default:+25->148, 30:+299->422, 75:+254->377
    //   148: goto +229 -> 377
    //   151: goto -93 -> 58
    //   154: aload_0
    //   155: aload_1
    //   156: invokespecial 65	o/x:<init>	(Landroid/content/Context;)V
    //   159: aload_1
    //   160: getstatic 70	o/Jy$IF:delete_transaction_dialog_title	I
    //   163: invokevirtual 75	android/content/Context:getString	(I)Ljava/lang/String;
    //   166: astore_3
    //   167: aload_3
    //   168: bipush 7
    //   170: ldc 76
    //   172: bipush 42
    //   174: ldc 77
    //   176: bipush -40
    //   178: invokestatic 80	o/KH:ˎ	(SIBII)Ljava/lang/String;
    //   181: invokevirtual 63	java/lang/String:intern	()Ljava/lang/String;
    //   184: invokevirtual 84	java/lang/String:startsWith	(Ljava/lang/String;)Z
    //   187: ifeq +6 -> 193
    //   190: goto -111 -> 79
    //   193: goto +76 -> 269
    //   196: goto +6 -> 202
    //   199: astore_1
    //   200: aload_1
    //   201: athrow
    //   202: aload_0
    //   203: aload_3
    //   204: invokevirtual 86	o/KH:ˋ	(Ljava/lang/CharSequence;)Lo/ᐸ$If;
    //   207: pop
    //   208: aload_1
    //   209: getstatic 89	o/Jy$IF:delete	I
    //   212: invokevirtual 75	android/content/Context:getString	(I)Ljava/lang/String;
    //   215: astore 4
    //   217: aload 4
    //   219: bipush 7
    //   221: ldc 76
    //   223: bipush 42
    //   225: ldc 77
    //   227: bipush -40
    //   229: invokestatic 80	o/KH:ˎ	(SIBII)Ljava/lang/String;
    //   232: invokevirtual 63	java/lang/String:intern	()Ljava/lang/String;
    //   235: invokevirtual 84	java/lang/String:startsWith	(Ljava/lang/String;)Z
    //   238: ifeq +6 -> 244
    //   241: goto +211 -> 452
    //   244: goto -216 -> 28
    //   247: bipush 75
    //   249: istore_2
    //   250: goto -128 -> 122
    //   253: aload_0
    //   254: aload_1
    //   255: iconst_4
    //   256: invokevirtual 56	java/lang/String:substring	(I)Ljava/lang/String;
    //   259: invokespecial 59	o/KH:ˊ	(Ljava/lang/String;)Ljava/lang/String;
    //   262: invokevirtual 63	java/lang/String:intern	()Ljava/lang/String;
    //   265: astore_1
    //   266: goto -263 -> 3
    //   269: aload_0
    //   270: aload_3
    //   271: invokevirtual 91	o/KH:ˊ	(Ljava/lang/CharSequence;)Lo/ᐸ$If;
    //   274: pop
    //   275: aload_1
    //   276: getstatic 94	o/Jy$IF:delete_transaction_dialog_message	I
    //   279: invokevirtual 75	android/content/Context:getString	(I)Ljava/lang/String;
    //   282: astore_3
    //   283: aload_3
    //   284: bipush 7
    //   286: ldc 76
    //   288: bipush 42
    //   290: ldc 77
    //   292: bipush -40
    //   294: invokestatic 80	o/KH:ˎ	(SIBII)Ljava/lang/String;
    //   297: invokevirtual 63	java/lang/String:intern	()Ljava/lang/String;
    //   300: invokevirtual 84	java/lang/String:startsWith	(Ljava/lang/String;)Z
    //   303: ifeq +6 -> 309
    //   306: goto +55 -> 361
    //   309: goto -107 -> 202
    //   312: bipush 30
    //   314: istore_2
    //   315: goto -193 -> 122
    //   318: aload_0
    //   319: aload_3
    //   320: invokevirtual 96	o/KH:ˎ	(Ljava/lang/CharSequence;)Lo/ᐸ$If;
    //   323: pop
    //   324: aload_1
    //   325: getstatic 99	o/Jy$IF:cancel	I
    //   328: invokevirtual 75	android/content/Context:getString	(I)Ljava/lang/String;
    //   331: astore_1
    //   332: aload_1
    //   333: bipush 7
    //   335: ldc 76
    //   337: bipush 42
    //   339: ldc 77
    //   341: bipush -40
    //   343: invokestatic 80	o/KH:ˎ	(SIBII)Ljava/lang/String;
    //   346: invokevirtual 63	java/lang/String:intern	()Ljava/lang/String;
    //   349: invokevirtual 84	java/lang/String:startsWith	(Ljava/lang/String;)Z
    //   352: ifeq +6 -> 358
    //   355: goto -102 -> 253
    //   358: goto -355 -> 3
    //   361: aload_0
    //   362: aload_3
    //   363: iconst_4
    //   364: invokevirtual 56	java/lang/String:substring	(I)Ljava/lang/String;
    //   367: invokespecial 59	o/KH:ˊ	(Ljava/lang/String;)Ljava/lang/String;
    //   370: invokevirtual 63	java/lang/String:intern	()Ljava/lang/String;
    //   373: astore_3
    //   374: goto -279 -> 95
    //   377: goto -108 -> 269
    //   380: astore_1
    //   381: aload_1
    //   382: athrow
    //   383: goto -181 -> 202
    //   386: aload 4
    //   388: astore_3
    //   389: iload_2
    //   390: lookupswitch	default:+26->416, 9:+-356->34, 12:+-72->318
    //   416: aload 4
    //   418: astore_3
    //   419: goto -101 -> 318
    //   422: goto -153 -> 269
    //   425: getstatic 26	o/KH:ॱㆍ	I
    //   428: bipush 99
    //   430: iadd
    //   431: istore_2
    //   432: iload_2
    //   433: sipush 128
    //   436: irem
    //   437: putstatic 24	o/KH:ॱˉ	I
    //   440: iload_2
    //   441: iconst_2
    //   442: irem
    //   443: ifeq +6 -> 449
    //   446: goto -199 -> 247
    //   449: goto -137 -> 312
    //   452: bipush 9
    //   454: istore_2
    //   455: goto -69 -> 386
    // Local variable table:
    //   start	length	slot	name	signature
    //   0	458	0	this	KH
    //   0	458	1	paramContext	android.content.Context
    //   30	425	2	i	int
    //   64	355	3	str1	String
    //   58	359	4	str2	String
    // Exception table:
    //   from	to	target	type
    //   58	65	199	java/lang/Exception
    //   95	102	199	java/lang/Exception
    //   102	110	199	java/lang/Exception
    //   71	76	380	java/lang/Exception
  }
  
  private String ˊ(String paramString)
  {
    break label171;
    label3:
    int i = 55;
    break label140;
    label9:
    int j;
    switch (j)
    {
    default: 
      break label227;
      label35:
      i = 75;
      break;
      label41:
      j = ॱㆍ + 113;
      ॱˉ = j % 128;
      if (j % 2 != 0) {}
      break;
    }
    for (;;)
    {
      try
      {
        paramString[i] = ((byte)(arrayOfByte[(arrayOfByte.length - i - 1)] ^ ॱˈ));
        i += 1;
        continue;
        arrayOfByte = paramString.getBytes(ˎ((short)66, 1409490355, (byte)21, 201773865, 0).intern());
        paramString = new byte[arrayOfByte.length];
        i = 1;
        break label41;
        j = arrayOfByte.length;
        if (i >= j) {
          continue;
        }
        switch (i)
        {
        case 55: 
        default: 
          label140:
          continue;
          label171:
          continue;
          j = 1;
          break label9;
          j = 0;
          break label9;
          continue;
          i = ॱˉ + 105;
          ॱㆍ = i % 128;
          if (i % 2 == 0) {
            break label3;
          }
          break label35;
          continue;
          paramString = new String(paramString, ˎ((short)124, 1409490365, (byte)105, 201773877, -40).intern());
        }
      }
      catch (UnsupportedEncodingException paramString)
      {
        throw new RuntimeException(paramString);
      }
      label227:
      return paramString;
      byte[] arrayOfByte = paramString.getBytes(ˎ((short)97, 1409490355, (byte)-32, 201773865, -40).intern());
      paramString = new byte[arrayOfByte.length];
      i = 0;
      break label41;
    }
  }
  
  /* Error */
  private static String ˎ(short paramShort, int paramInt1, byte paramByte, int paramInt2, int paramInt3)
  {
    // Byte code:
    //   0: goto +268 -> 268
    //   3: iconst_1
    //   4: istore 6
    //   6: goto +541 -> 547
    //   9: aconst_null
    //   10: arraylength
    //   11: istore_0
    //   12: aload 8
    //   14: areturn
    //   15: getstatic 26	o/KH:ॱㆍ	I
    //   18: bipush 39
    //   20: iadd
    //   21: istore 4
    //   23: iload 4
    //   25: sipush 128
    //   28: irem
    //   29: putstatic 24	o/KH:ॱˉ	I
    //   32: iload 4
    //   34: iconst_2
    //   35: irem
    //   36: ifeq +6 -> 42
    //   39: goto +49 -> 88
    //   42: goto +549 -> 591
    //   45: getstatic 24	o/KH:ॱˉ	I
    //   48: istore_1
    //   49: iload_1
    //   50: bipush 61
    //   52: iadd
    //   53: istore_1
    //   54: iload_1
    //   55: sipush 128
    //   58: irem
    //   59: putstatic 26	o/KH:ॱㆍ	I
    //   62: iload_1
    //   63: iconst_2
    //   64: irem
    //   65: ifne +6 -> 71
    //   68: goto +529 -> 597
    //   71: goto +514 -> 585
    //   74: bipush 84
    //   76: istore 6
    //   78: goto +45 -> 123
    //   81: bipush 63
    //   83: istore 6
    //   85: goto +38 -> 123
    //   88: bipush 6
    //   90: istore 4
    //   92: goto +394 -> 486
    //   95: getstatic 119	o/KH:ॱـ	[B
    //   98: getstatic 121	o/KH:ߺ	I
    //   101: iload_1
    //   102: iadd
    //   103: baload
    //   104: getstatic 123	o/KH:ॱˍ	I
    //   107: iadd
    //   108: i2b
    //   109: istore 4
    //   111: goto +364 -> 475
    //   114: goto +421 -> 535
    //   117: iload 6
    //   119: istore_1
    //   120: goto +327 -> 447
    //   123: iload 6
    //   125: lookupswitch	default:+27->152, 63:+81->206, 84:+117->242
    //   152: goto +54 -> 206
    //   155: getstatic 119	o/KH:ॱـ	[B
    //   158: ifnull +6 -> 164
    //   161: goto -66 -> 95
    //   164: goto +231 -> 395
    //   167: getstatic 119	o/KH:ॱـ	[B
    //   170: astore 9
    //   172: bipush 57
    //   174: iconst_0
    //   175: idiv
    //   176: istore 4
    //   178: aload 9
    //   180: ifnull +6 -> 186
    //   183: goto -88 -> 95
    //   186: goto +209 -> 395
    //   189: astore 8
    //   191: aload 8
    //   193: athrow
    //   194: iconst_0
    //   195: istore 6
    //   197: goto +454 -> 651
    //   200: iconst_1
    //   201: istore 6
    //   203: goto +316 -> 519
    //   206: getstatic 26	o/KH:ॱㆍ	I
    //   209: bipush 103
    //   211: iadd
    //   212: istore 6
    //   214: iload 6
    //   216: sipush 128
    //   219: irem
    //   220: putstatic 24	o/KH:ॱˉ	I
    //   223: iload 6
    //   225: iconst_2
    //   226: irem
    //   227: ifeq +6 -> 233
    //   230: goto -116 -> 114
    //   233: goto +302 -> 535
    //   236: iload 6
    //   238: istore_1
    //   239: goto +208 -> 447
    //   242: aload 8
    //   244: invokevirtual 128	java/lang/StringBuilder:toString	()Ljava/lang/String;
    //   247: astore 8
    //   249: goto +372 -> 621
    //   252: getstatic 121	o/KH:ߺ	I
    //   255: istore 7
    //   257: iload 6
    //   259: ifeq +6 -> 265
    //   262: goto +69 -> 331
    //   265: goto -71 -> 194
    //   268: goto +146 -> 414
    //   271: iload_1
    //   272: lookupswitch	default:+28->300, 12:+-36->236, 82:+-155->117
    //   300: goto -183 -> 117
    //   303: getstatic 130	o/KH:ॱˑ	[S
    //   306: astore 9
    //   308: iload_1
    //   309: iconst_1
    //   310: isub
    //   311: istore 6
    //   313: aload 9
    //   315: iload_1
    //   316: saload
    //   317: iload_0
    //   318: iadd
    //   319: i2s
    //   320: iload_2
    //   321: ixor
    //   322: iload 7
    //   324: iadd
    //   325: i2c
    //   326: istore 5
    //   328: goto -283 -> 45
    //   331: getstatic 26	o/KH:ॱㆍ	I
    //   334: bipush 9
    //   336: iadd
    //   337: istore 6
    //   339: iload 6
    //   341: sipush 128
    //   344: irem
    //   345: putstatic 24	o/KH:ॱˉ	I
    //   348: iload 6
    //   350: iconst_2
    //   351: irem
    //   352: ifeq +6 -> 358
    //   355: goto -352 -> 3
    //   358: goto +104 -> 462
    //   361: getstatic 24	o/KH:ॱˉ	I
    //   364: istore 7
    //   366: iload 7
    //   368: bipush 63
    //   370: iadd
    //   371: istore 7
    //   373: iload 7
    //   375: sipush 128
    //   378: irem
    //   379: putstatic 26	o/KH:ॱㆍ	I
    //   382: iload 7
    //   384: iconst_2
    //   385: irem
    //   386: ifne +6 -> 392
    //   389: goto +259 -> 648
    //   392: goto -140 -> 252
    //   395: getstatic 130	o/KH:ॱˑ	[S
    //   398: getstatic 121	o/KH:ߺ	I
    //   401: iload_1
    //   402: iadd
    //   403: saload
    //   404: getstatic 123	o/KH:ॱˍ	I
    //   407: iadd
    //   408: i2s
    //   409: istore 4
    //   411: goto +64 -> 475
    //   414: new 125	java/lang/StringBuilder
    //   417: dup
    //   418: invokespecial 132	java/lang/StringBuilder:<init>	()V
    //   421: astore 8
    //   423: getstatic 123	o/KH:ॱˍ	I
    //   426: iload 4
    //   428: iadd
    //   429: istore 6
    //   431: iload 6
    //   433: istore 4
    //   435: iload 6
    //   437: iconst_m1
    //   438: if_icmpne +6 -> 444
    //   441: goto -241 -> 200
    //   444: goto +171 -> 615
    //   447: aload 8
    //   449: iload 5
    //   451: invokevirtual 136	java/lang/StringBuilder:append	(C)Ljava/lang/StringBuilder;
    //   454: pop
    //   455: iload_3
    //   456: iconst_1
    //   457: iadd
    //   458: istore_3
    //   459: goto +9 -> 468
    //   462: iconst_1
    //   463: istore 6
    //   465: goto +82 -> 547
    //   468: iload 5
    //   470: istore 7
    //   472: goto +131 -> 603
    //   475: iload 4
    //   477: ifle +6 -> 483
    //   480: goto -119 -> 361
    //   483: goto -241 -> 242
    //   486: iload 4
    //   488: lookupswitch	default:+28->516, 5:+-333->155, 6:+-321->167
    //   516: goto -361 -> 155
    //   519: iload 6
    //   521: ifeq +6 -> 527
    //   524: goto -509 -> 15
    //   527: goto -52 -> 475
    //   530: astore 8
    //   532: aload 8
    //   534: athrow
    //   535: getstatic 119	o/KH:ॱـ	[B
    //   538: ifnull +6 -> 544
    //   541: goto +113 -> 654
    //   544: goto -241 -> 303
    //   547: iload_1
    //   548: iload 4
    //   550: iadd
    //   551: iconst_2
    //   552: isub
    //   553: iload 7
    //   555: iadd
    //   556: iload 6
    //   558: iadd
    //   559: istore_1
    //   560: getstatic 138	o/KH:ॱˌ	I
    //   563: iload_3
    //   564: iadd
    //   565: i2c
    //   566: istore 5
    //   568: aload 8
    //   570: iload 5
    //   572: invokevirtual 136	java/lang/StringBuilder:append	(C)Ljava/lang/StringBuilder;
    //   575: pop
    //   576: iconst_1
    //   577: istore_3
    //   578: iload 5
    //   580: istore 7
    //   582: goto +21 -> 603
    //   585: bipush 12
    //   587: istore_1
    //   588: goto -317 -> 271
    //   591: iconst_5
    //   592: istore 4
    //   594: goto -108 -> 486
    //   597: bipush 82
    //   599: istore_1
    //   600: goto -329 -> 271
    //   603: iload_3
    //   604: iload 4
    //   606: if_icmpge +6 -> 612
    //   609: goto -528 -> 81
    //   612: goto -538 -> 74
    //   615: iconst_0
    //   616: istore 6
    //   618: goto -99 -> 519
    //   621: getstatic 26	o/KH:ॱㆍ	I
    //   624: bipush 23
    //   626: iadd
    //   627: istore_0
    //   628: iload_0
    //   629: sipush 128
    //   632: irem
    //   633: putstatic 24	o/KH:ॱˉ	I
    //   636: iload_0
    //   637: iconst_2
    //   638: irem
    //   639: ifeq +6 -> 645
    //   642: goto -633 -> 9
    //   645: aload 8
    //   647: areturn
    //   648: goto -396 -> 252
    //   651: goto -104 -> 547
    //   654: getstatic 119	o/KH:ॱـ	[B
    //   657: astore 9
    //   659: iload_1
    //   660: iconst_1
    //   661: isub
    //   662: istore 6
    //   664: aload 9
    //   666: iload_1
    //   667: baload
    //   668: iload_0
    //   669: iadd
    //   670: i2b
    //   671: iload_2
    //   672: ixor
    //   673: iload 7
    //   675: iadd
    //   676: i2c
    //   677: istore 5
    //   679: iload 6
    //   681: istore_1
    //   682: goto -235 -> 447
    // Local variable table:
    //   start	length	slot	name	signature
    //   0	685	0	paramShort	short
    //   0	685	1	paramInt1	int
    //   0	685	2	paramByte	byte
    //   0	685	3	paramInt2	int
    //   0	685	4	paramInt3	int
    //   326	352	5	i	int
    //   4	676	6	j	int
    //   255	421	7	k	int
    //   12	1	8	str	String
    //   189	54	8	localException1	Exception
    //   247	201	8	localObject1	Object
    //   530	116	8	localException2	Exception
    //   170	495	9	localObject2	Object
    // Exception table:
    //   from	to	target	type
    //   252	257	189	java/lang/Exception
    //   361	366	189	java/lang/Exception
    //   45	49	530	java/lang/Exception
    //   54	62	530	java/lang/Exception
    //   373	382	530	java/lang/Exception
  }
  
  static void ˎ()
  {
    ॱˍ = 39;
    ॱـ = new byte[] { -35, 36, -44, 56, -29, -125, -77, -125, -68, 127, -118, -35, -69, -119, -34, -26, 18, 31, 26 };
    ॱˌ = -201773792;
    ߺ = -1409490351;
  }
  
  /* Error */
  public void ˋ(ᐸ paramᐸ, ะ paramะ)
  {
    // Byte code:
    //   0: goto +20 -> 20
    //   3: aload_1
    //   4: invokevirtual 163	o/ᐸ:dismiss	()V
    //   7: return
    //   8: goto +129 -> 137
    //   11: goto -8 -> 3
    //   14: goto -11 -> 3
    //   17: astore_1
    //   18: aload_1
    //   19: athrow
    //   20: goto +93 -> 113
    //   23: iload_3
    //   24: lookupswitch	default:+28->52, 50:+-10->14, 58:+-13->11
    //   52: goto -38 -> 14
    //   55: getstatic 26	o/KH:ॱㆍ	I
    //   58: bipush 71
    //   60: iadd
    //   61: istore_3
    //   62: iload_3
    //   63: sipush 128
    //   66: irem
    //   67: putstatic 24	o/KH:ॱˉ	I
    //   70: iload_3
    //   71: iconst_2
    //   72: irem
    //   73: ifeq +6 -> 79
    //   76: goto +9 -> 85
    //   79: goto +88 -> 167
    //   82: astore_1
    //   83: aload_1
    //   84: athrow
    //   85: bipush 58
    //   87: istore_3
    //   88: goto -65 -> 23
    //   91: invokestatic 168	o/zp:ॱ	()Lo/zp;
    //   94: astore_2
    //   95: new 170	o/FR
    //   98: dup
    //   99: invokespecial 171	o/FR:<init>	()V
    //   102: astore 4
    //   104: aload_2
    //   105: aload 4
    //   107: invokevirtual 174	o/zp:ˎ	(Ljava/lang/Object;)V
    //   110: goto -55 -> 55
    //   113: getstatic 26	o/KH:ॱㆍ	I
    //   116: bipush 65
    //   118: iadd
    //   119: istore_3
    //   120: iload_3
    //   121: sipush 128
    //   124: irem
    //   125: putstatic 24	o/KH:ॱˉ	I
    //   128: iload_3
    //   129: iconst_2
    //   130: irem
    //   131: ifeq +6 -> 137
    //   134: goto -126 -> 8
    //   137: getstatic 178	o/KH$3:ˏ	[I
    //   140: aload_2
    //   141: invokevirtual 184	o/ะ:ordinal	()I
    //   144: iaload
    //   145: lookupswitch	default:+19->164, 1:+-54->91
    //   164: goto -161 -> 3
    //   167: bipush 50
    //   169: istore_3
    //   170: goto -147 -> 23
    // Local variable table:
    //   start	length	slot	name	signature
    //   0	173	0	this	KH
    //   0	173	1	paramᐸ	ᐸ
    //   0	173	2	paramะ	ะ
    //   23	147	3	i	int
    //   102	4	4	localFR	FR
    // Exception table:
    //   from	to	target	type
    //   91	95	17	java/lang/Exception
    //   104	110	82	java/lang/Exception
  }
}
