package o;

import android.view.View;
import android.view.View.OnClickListener;
import java.io.UnsupportedEncodingException;

public final class KI
  extends F<JN>
  implements ᐸ.ˏ
{
  private static byte ߺ;
  private static int ॱˉ;
  private static long ॱˑ;
  private static int ॱـ = 0;
  
  static
  {
    ॱˉ = 1;
    ॱॱ();
    ߺ = -102;
    break label56;
    int i = null.length;
    return;
    label23:
    i = 1;
    for (;;)
    {
      i = 0;
      switch (i)
      {
      case 1: 
      default: 
        break;
      case 0: 
        return;
        label56:
        i = ॱˉ + 117;
        ॱـ = i % 128;
        if (i % 2 != 0) {
          break label23;
        }
      }
    }
  }
  
  /* Error */
  public KI(android.content.Context paramContext, double paramDouble, String paramString)
  {
    // Byte code:
    //   0: goto +181 -> 181
    //   3: getstatic 20	o/KI:ॱـ	I
    //   6: bipush 113
    //   8: iadd
    //   9: istore 5
    //   11: iload 5
    //   13: sipush 128
    //   16: irem
    //   17: putstatic 22	o/KI:ॱˉ	I
    //   20: iload 5
    //   22: iconst_2
    //   23: irem
    //   24: ifne +6 -> 30
    //   27: goto +331 -> 358
    //   30: goto +884 -> 914
    //   33: aload 7
    //   35: aload 4
    //   37: invokevirtual 38	o/JN:ˏ	(Ljava/lang/String;)V
    //   40: aload_0
    //   41: getfield 42	o/KI:ॱˈ	Landroid/databinding/ViewDataBinding;
    //   44: checkcast 34	o/JN
    //   47: astore 10
    //   49: aload_1
    //   50: getstatic 47	o/Jy$IF:tutorial_enrollment_third_step_limit	I
    //   53: invokevirtual 53	android/content/Context:getString	(I)Ljava/lang/String;
    //   56: astore 7
    //   58: aload 7
    //   60: aload 8
    //   62: invokevirtual 59	java/lang/String:startsWith	(Ljava/lang/String;)Z
    //   65: ifeq +6 -> 71
    //   68: goto +259 -> 327
    //   71: goto +320 -> 391
    //   74: aload_0
    //   75: aload_1
    //   76: invokevirtual 63	o/KI:ˎ	(Ljava/lang/CharSequence;)Lo/ᐸ$If;
    //   79: pop
    //   80: aload_0
    //   81: aload_0
    //   82: invokevirtual 67	o/KI:ॱ	(Lo/ᐸ$ˏ;)Lo/ᐸ$If;
    //   85: pop
    //   86: aload_0
    //   87: getfield 42	o/KI:ॱˈ	Landroid/databinding/ViewDataBinding;
    //   90: checkcast 34	o/JN
    //   93: getfield 70	o/JN:ॱ	Landroid/widget/TextView;
    //   96: new 9	o/KI$3
    //   99: dup
    //   100: aload_0
    //   101: invokespecial 73	o/KI$3:<init>	(Lo/KI;)V
    //   104: invokevirtual 79	android/widget/TextView:setOnClickListener	(Landroid/view/View$OnClickListener;)V
    //   107: return
    //   108: aload 9
    //   110: aload 7
    //   112: invokevirtual 81	o/JN:ˎ	(Ljava/lang/String;)V
    //   115: dload_2
    //   116: dconst_0
    //   117: dcmpl
    //   118: ifle +6 -> 124
    //   121: goto +659 -> 780
    //   124: goto +443 -> 567
    //   127: getstatic 20	o/KI:ॱـ	I
    //   130: bipush 93
    //   132: iadd
    //   133: istore 5
    //   135: iload 5
    //   137: sipush 128
    //   140: irem
    //   141: putstatic 22	o/KI:ॱˉ	I
    //   144: iload 5
    //   146: iconst_2
    //   147: irem
    //   148: ifne +6 -> 154
    //   151: goto +117 -> 268
    //   154: goto +551 -> 705
    //   157: iconst_1
    //   158: istore 5
    //   160: goto +569 -> 729
    //   163: aload_0
    //   164: aload 4
    //   166: iconst_4
    //   167: invokevirtual 84	java/lang/String:substring	(I)Ljava/lang/String;
    //   170: invokespecial 87	o/KI:ॱ	(Ljava/lang/String;)Ljava/lang/String;
    //   173: invokevirtual 91	java/lang/String:intern	()Ljava/lang/String;
    //   176: astore 4
    //   178: goto +155 -> 333
    //   181: iconst_5
    //   182: newarray char
    //   184: dup
    //   185: iconst_0
    //   186: ldc 92
    //   188: castore
    //   189: dup
    //   190: iconst_1
    //   191: ldc 93
    //   193: castore
    //   194: dup
    //   195: iconst_2
    //   196: ldc 94
    //   198: castore
    //   199: dup
    //   200: iconst_3
    //   201: ldc 95
    //   203: castore
    //   204: dup
    //   205: iconst_4
    //   206: ldc 96
    //   208: castore
    //   209: invokestatic 100	o/KI:ˊ	([C)Ljava/lang/String;
    //   212: astore 7
    //   214: aload 7
    //   216: invokevirtual 91	java/lang/String:intern	()Ljava/lang/String;
    //   219: astore 8
    //   221: aload_0
    //   222: aload_1
    //   223: invokespecial 103	o/F:<init>	(Landroid/content/Context;)V
    //   226: aload_0
    //   227: getfield 42	o/KI:ॱˈ	Landroid/databinding/ViewDataBinding;
    //   230: astore 7
    //   232: aload 7
    //   234: checkcast 34	o/JN
    //   237: astore 9
    //   239: aload_1
    //   240: getstatic 106	o/Jy$IF:tutorial_enrollment_title	I
    //   243: invokevirtual 53	android/content/Context:getString	(I)Ljava/lang/String;
    //   246: astore 7
    //   248: aload 7
    //   250: aload 8
    //   252: invokevirtual 59	java/lang/String:startsWith	(Ljava/lang/String;)Z
    //   255: istore 6
    //   257: iload 6
    //   259: ifeq +6 -> 265
    //   262: goto +197 -> 459
    //   265: goto -157 -> 108
    //   268: iconst_1
    //   269: istore 5
    //   271: goto +684 -> 955
    //   274: aload_0
    //   275: aload 4
    //   277: iconst_4
    //   278: invokevirtual 84	java/lang/String:substring	(I)Ljava/lang/String;
    //   281: invokespecial 87	o/KI:ॱ	(Ljava/lang/String;)Ljava/lang/String;
    //   284: invokevirtual 91	java/lang/String:intern	()Ljava/lang/String;
    //   287: astore_1
    //   288: bipush 48
    //   290: iconst_0
    //   291: idiv
    //   292: istore 5
    //   294: goto -220 -> 74
    //   297: aload 7
    //   299: astore 4
    //   301: iload 5
    //   303: tableswitch	default:+21->324, 0:+58->361, 1:+181->484
    //   324: goto +37 -> 361
    //   327: iconst_0
    //   328: istore 5
    //   330: goto -33 -> 297
    //   333: goto -300 -> 33
    //   336: aload_0
    //   337: aload 4
    //   339: iconst_4
    //   340: invokevirtual 84	java/lang/String:substring	(I)Ljava/lang/String;
    //   343: invokespecial 87	o/KI:ॱ	(Ljava/lang/String;)Ljava/lang/String;
    //   346: invokevirtual 91	java/lang/String:intern	()Ljava/lang/String;
    //   349: astore 4
    //   351: aconst_null
    //   352: arraylength
    //   353: istore 5
    //   355: goto +303 -> 658
    //   358: goto +556 -> 914
    //   361: getstatic 20	o/KI:ॱـ	I
    //   364: bipush 51
    //   366: iadd
    //   367: istore 5
    //   369: iload 5
    //   371: sipush 128
    //   374: irem
    //   375: putstatic 22	o/KI:ॱˉ	I
    //   378: iload 5
    //   380: iconst_2
    //   381: irem
    //   382: ifne +6 -> 388
    //   385: goto +251 -> 636
    //   388: goto +155 -> 543
    //   391: iconst_1
    //   392: istore 5
    //   394: goto -97 -> 297
    //   397: aload_1
    //   398: getstatic 109	o/Jy$IF:continue_label	I
    //   401: invokevirtual 53	android/content/Context:getString	(I)Ljava/lang/String;
    //   404: astore 4
    //   406: aload 4
    //   408: aload 8
    //   410: invokevirtual 59	java/lang/String:startsWith	(Ljava/lang/String;)Z
    //   413: ifeq +6 -> 419
    //   416: goto +145 -> 561
    //   419: goto -262 -> 157
    //   422: bipush 15
    //   424: istore 5
    //   426: goto +491 -> 917
    //   429: getstatic 20	o/KI:ॱـ	I
    //   432: bipush 63
    //   434: iadd
    //   435: istore 5
    //   437: iload 5
    //   439: sipush 128
    //   442: irem
    //   443: putstatic 22	o/KI:ॱˉ	I
    //   446: iload 5
    //   448: iconst_2
    //   449: irem
    //   450: ifne +6 -> 456
    //   453: goto -117 -> 336
    //   456: goto +255 -> 711
    //   459: aload_0
    //   460: aload 7
    //   462: iconst_4
    //   463: invokevirtual 84	java/lang/String:substring	(I)Ljava/lang/String;
    //   466: invokespecial 87	o/KI:ॱ	(Ljava/lang/String;)Ljava/lang/String;
    //   469: invokevirtual 91	java/lang/String:intern	()Ljava/lang/String;
    //   472: astore 7
    //   474: goto -366 -> 108
    //   477: bipush 84
    //   479: istore 5
    //   481: goto +436 -> 917
    //   484: aload 10
    //   486: aload 4
    //   488: iconst_1
    //   489: anewarray 111	java/lang/Object
    //   492: dup
    //   493: iconst_0
    //   494: aload 9
    //   496: aastore
    //   497: invokestatic 115	java/lang/String:format	(Ljava/lang/String;[Ljava/lang/Object;)Ljava/lang/String;
    //   500: invokevirtual 118	o/JN:ˋ	(Ljava/lang/String;)V
    //   503: goto -500 -> 3
    //   506: aload_0
    //   507: aload 7
    //   509: iconst_4
    //   510: invokevirtual 84	java/lang/String:substring	(I)Ljava/lang/String;
    //   513: invokespecial 87	o/KI:ॱ	(Ljava/lang/String;)Ljava/lang/String;
    //   516: invokevirtual 91	java/lang/String:intern	()Ljava/lang/String;
    //   519: astore 4
    //   521: aload 9
    //   523: aload 4
    //   525: invokevirtual 38	o/JN:ˏ	(Ljava/lang/String;)V
    //   528: aload_0
    //   529: getfield 42	o/KI:ॱˈ	Landroid/databinding/ViewDataBinding;
    //   532: checkcast 34	o/JN
    //   535: ldc 120
    //   537: invokevirtual 118	o/JN:ˋ	(Ljava/lang/String;)V
    //   540: goto -143 -> 397
    //   543: aload_0
    //   544: aload 7
    //   546: iconst_4
    //   547: invokevirtual 84	java/lang/String:substring	(I)Ljava/lang/String;
    //   550: invokespecial 87	o/KI:ॱ	(Ljava/lang/String;)Ljava/lang/String;
    //   553: invokevirtual 91	java/lang/String:intern	()Ljava/lang/String;
    //   556: astore 4
    //   558: goto -74 -> 484
    //   561: iconst_0
    //   562: istore 5
    //   564: goto +165 -> 729
    //   567: aload_0
    //   568: getfield 42	o/KI:ॱˈ	Landroid/databinding/ViewDataBinding;
    //   571: checkcast 34	o/JN
    //   574: new 122	o/coN
    //   577: dup
    //   578: iconst_0
    //   579: invokespecial 125	o/coN:<init>	(Z)V
    //   582: invokevirtual 128	o/JN:ॱ	(Lo/coN;)V
    //   585: aload_0
    //   586: getfield 42	o/KI:ॱˈ	Landroid/databinding/ViewDataBinding;
    //   589: checkcast 34	o/JN
    //   592: astore 7
    //   594: aload_1
    //   595: getstatic 131	o/Jy$IF:tutorial_enrollment_first_step	I
    //   598: invokevirtual 53	android/content/Context:getString	(I)Ljava/lang/String;
    //   601: astore 4
    //   603: aload 4
    //   605: aload 8
    //   607: invokevirtual 59	java/lang/String:startsWith	(Ljava/lang/String;)Z
    //   610: ifeq +6 -> 616
    //   613: goto -184 -> 429
    //   616: goto +42 -> 658
    //   619: aload_0
    //   620: aload 4
    //   622: iconst_4
    //   623: invokevirtual 84	java/lang/String:substring	(I)Ljava/lang/String;
    //   626: invokespecial 87	o/KI:ॱ	(Ljava/lang/String;)Ljava/lang/String;
    //   629: invokevirtual 91	java/lang/String:intern	()Ljava/lang/String;
    //   632: astore_1
    //   633: goto -559 -> 74
    //   636: aload_0
    //   637: aload 7
    //   639: iconst_4
    //   640: invokevirtual 84	java/lang/String:substring	(I)Ljava/lang/String;
    //   643: invokespecial 87	o/KI:ॱ	(Ljava/lang/String;)Ljava/lang/String;
    //   646: invokevirtual 91	java/lang/String:intern	()Ljava/lang/String;
    //   649: astore_1
    //   650: new 133	java/lang/NullPointerException
    //   653: dup
    //   654: invokespecial 135	java/lang/NullPointerException:<init>	()V
    //   657: athrow
    //   658: aload 7
    //   660: aload 4
    //   662: invokevirtual 137	o/JN:ॱ	(Ljava/lang/String;)V
    //   665: aload_0
    //   666: getfield 42	o/KI:ॱˈ	Landroid/databinding/ViewDataBinding;
    //   669: checkcast 34	o/JN
    //   672: astore 9
    //   674: aload_1
    //   675: getstatic 140	o/Jy$IF:tutorial_enrollment_second_step	I
    //   678: invokevirtual 53	android/content/Context:getString	(I)Ljava/lang/String;
    //   681: astore 7
    //   683: aload 7
    //   685: aload 8
    //   687: invokevirtual 59	java/lang/String:startsWith	(Ljava/lang/String;)Z
    //   690: ifeq +6 -> 696
    //   693: goto -271 -> 422
    //   696: goto -219 -> 477
    //   699: astore_1
    //   700: aload_1
    //   701: athrow
    //   702: astore_1
    //   703: aload_1
    //   704: athrow
    //   705: iconst_0
    //   706: istore 5
    //   708: goto +247 -> 955
    //   711: aload_0
    //   712: aload 4
    //   714: iconst_4
    //   715: invokevirtual 84	java/lang/String:substring	(I)Ljava/lang/String;
    //   718: invokespecial 87	o/KI:ॱ	(Ljava/lang/String;)Ljava/lang/String;
    //   721: invokevirtual 91	java/lang/String:intern	()Ljava/lang/String;
    //   724: astore 4
    //   726: goto -68 -> 658
    //   729: aload 4
    //   731: astore_1
    //   732: iload 5
    //   734: tableswitch	default:+22->756, 0:+-607->127, 1:+-660->74
    //   756: aload 4
    //   758: astore_1
    //   759: goto -685 -> 74
    //   762: aload_0
    //   763: aload 4
    //   765: iconst_4
    //   766: invokevirtual 84	java/lang/String:substring	(I)Ljava/lang/String;
    //   769: invokespecial 87	o/KI:ॱ	(Ljava/lang/String;)Ljava/lang/String;
    //   772: invokevirtual 91	java/lang/String:intern	()Ljava/lang/String;
    //   775: astore 4
    //   777: goto +96 -> 873
    //   780: aload_0
    //   781: getfield 42	o/KI:ॱˈ	Landroid/databinding/ViewDataBinding;
    //   784: checkcast 34	o/JN
    //   787: new 122	o/coN
    //   790: dup
    //   791: iconst_1
    //   792: invokespecial 125	o/coN:<init>	(Z)V
    //   795: invokevirtual 128	o/JN:ॱ	(Lo/coN;)V
    //   798: new 142	java/lang/StringBuilder
    //   801: dup
    //   802: invokespecial 143	java/lang/StringBuilder:<init>	()V
    //   805: dload_2
    //   806: d2l
    //   807: invokevirtual 147	java/lang/StringBuilder:append	(J)Ljava/lang/StringBuilder;
    //   810: iconst_2
    //   811: newarray char
    //   813: dup
    //   814: iconst_0
    //   815: ldc -108
    //   817: castore
    //   818: dup
    //   819: iconst_1
    //   820: ldc -107
    //   822: castore
    //   823: invokestatic 100	o/KI:ˊ	([C)Ljava/lang/String;
    //   826: invokevirtual 91	java/lang/String:intern	()Ljava/lang/String;
    //   829: invokevirtual 152	java/lang/StringBuilder:append	(Ljava/lang/String;)Ljava/lang/StringBuilder;
    //   832: aload 4
    //   834: invokevirtual 152	java/lang/StringBuilder:append	(Ljava/lang/String;)Ljava/lang/StringBuilder;
    //   837: invokevirtual 155	java/lang/StringBuilder:toString	()Ljava/lang/String;
    //   840: astore 9
    //   842: aload_0
    //   843: getfield 42	o/KI:ॱˈ	Landroid/databinding/ViewDataBinding;
    //   846: checkcast 34	o/JN
    //   849: astore 7
    //   851: aload_1
    //   852: getstatic 158	o/Jy$IF:tutorial_enrollment_first_step_limit	I
    //   855: invokevirtual 53	android/content/Context:getString	(I)Ljava/lang/String;
    //   858: astore 4
    //   860: aload 4
    //   862: aload 8
    //   864: invokevirtual 59	java/lang/String:startsWith	(Ljava/lang/String;)Z
    //   867: ifeq +6 -> 873
    //   870: goto -108 -> 762
    //   873: aload 7
    //   875: aload 4
    //   877: invokevirtual 137	o/JN:ॱ	(Ljava/lang/String;)V
    //   880: aload_0
    //   881: getfield 42	o/KI:ॱˈ	Landroid/databinding/ViewDataBinding;
    //   884: checkcast 34	o/JN
    //   887: astore 7
    //   889: aload_1
    //   890: getstatic 161	o/Jy$IF:tutorial_enrollment_second_step_limit	I
    //   893: invokevirtual 53	android/content/Context:getString	(I)Ljava/lang/String;
    //   896: astore 4
    //   898: aload 4
    //   900: aload 8
    //   902: invokevirtual 59	java/lang/String:startsWith	(Ljava/lang/String;)Z
    //   905: ifeq +6 -> 911
    //   908: goto -745 -> 163
    //   911: goto -878 -> 33
    //   914: goto -517 -> 397
    //   917: aload 7
    //   919: astore 4
    //   921: iload 5
    //   923: lookupswitch	default:+25->948, 15:+-417->506, 84:+-402->521
    //   948: aload 7
    //   950: astore 4
    //   952: goto -431 -> 521
    //   955: iload 5
    //   957: tableswitch	default:+23->980, 0:+-338->619, 1:+-683->274
    //   980: goto -361 -> 619
    // Local variable table:
    //   start	length	slot	name	signature
    //   0	983	0	this	KI
    //   0	983	1	paramContext	android.content.Context
    //   0	983	2	paramDouble	double
    //   0	983	4	paramString	String
    //   9	947	5	i	int
    //   255	3	6	bool	boolean
    //   33	916	7	localObject1	Object
    //   60	841	8	str	String
    //   108	733	9	localObject2	Object
    //   47	438	10	localJN	JN
    // Exception table:
    //   from	to	target	type
    //   181	214	699	java/lang/Exception
    //   214	226	699	java/lang/Exception
    //   226	232	699	java/lang/Exception
    //   232	257	699	java/lang/Exception
    //   214	226	702	java/lang/Exception
  }
  
  private static String ˊ(char[] paramArrayOfChar)
  {
    int j;
    label67:
    int k;
    char[] arrayOfChar;
    int i;
    try
    {
      j = ॱˉ;
      j += 9;
      ॱـ = j % 128;
      if (j % 2 == 0)
      {
        break label257;
        break label195;
        break label212;
        switch (j)
        {
        case 20: 
        default: 
          break;
          label84:
          for (;;)
          {
            k = paramArrayOfChar[0];
            arrayOfChar = new char[paramArrayOfChar.length - 1];
            i = 1;
            break;
          }
        }
        for (;;)
        {
          i = ॱˉ + 65;
          ॱـ = i % 128;
          if (i % 2 != 0) {
            break label245;
          }
          break;
          paramArrayOfChar = new String(arrayOfChar);
        }
        i = 32;
        break label166;
      }
      arrayOfChar[(i + 0)] = ((char)(int)((paramArrayOfChar[i] & i % k) % ॱˑ));
      i += 53;
    }
    catch (Exception paramArrayOfChar)
    {
      throw paramArrayOfChar;
    }
    return paramArrayOfChar;
    switch (i)
    {
    case 32: 
    default: 
      label166:
      break;
    }
    for (;;)
    {
      label195:
      if (i >= paramArrayOfChar.length)
      {
        break label251;
        i = null.length;
        return paramArrayOfChar;
        label212:
        i = ॱˉ + 121;
        ॱـ = i % 128;
        if (i % 2 != 0) {
          break label84;
        }
        break label67;
      }
      j = 20;
      break;
      label245:
      i = 52;
      break label166;
      label251:
      j = 28;
      break;
      label257:
      arrayOfChar[(i - 1)] = ((char)(int)(paramArrayOfChar[i] ^ i * k ^ ॱˑ));
      i += 1;
    }
  }
  
  private String ॱ(String paramString)
  {
    break label343;
    int j = 26;
    for (;;)
    {
      byte[] arrayOfByte;
      int i;
      try
      {
        arrayOfByte = paramString.getBytes(ˊ(new char[] { 13163, 120, 21983, -22188, -293, 12917, 2016, 21634, -22469, -588, 12613 }).intern());
        paramString = new byte[arrayOfByte.length];
        i = 0;
        continue;
        paramString = new String(paramString, ˊ(new char[] { 30539, 17476, -8808, 22269, -4517, 26389 }).intern());
        return paramString;
        i = j;
        continue;
        i = 0;
        continue;
        arrayOfByte = paramString.getBytes(ˊ(new char[] { 13163, 120, 21983, -22188, -293, 12917, 2016, 21634, -22469, -588, 12613 }).intern());
        paramString = new byte[arrayOfByte.length];
        i = 0;
        continue;
        i = ॱـ + 109;
        ॱˉ = i % 128;
        if (i % 2 != 0)
        {
          continue;
          i = ॱˉ + 119;
          ॱـ = i % 128;
          if (i % 2 != 0) {
            continue;
          }
          continue;
          i = j;
          j = arrayOfByte.length;
          if (i < j) {
            break;
          }
          break label386;
          switch (i)
          {
          }
          continue;
          label343:
          continue;
        }
        i = 1;
      }
      catch (UnsupportedEncodingException paramString)
      {
        throw new RuntimeException(paramString);
      }
      continue;
      paramString[i] = ((byte)(arrayOfByte[(arrayOfByte.length - i - 1)] ^ ߺ));
      j = i + 1;
      continue;
      label386:
      j = 7;
      switch (j)
      {
      }
    }
  }
  
  static void ॱॱ()
  {
    ॱˑ = 9089454399401374554L;
  }
  
  /* Error */
  public void ˋ(ᐸ paramᐸ, ะ paramะ)
  {
    // Byte code:
    //   0: goto +68 -> 68
    //   3: astore_1
    //   4: aload_1
    //   5: athrow
    //   6: invokestatic 205	o/zp:ॱ	()Lo/zp;
    //   9: new 207	o/HT
    //   12: dup
    //   13: iconst_4
    //   14: sipush 226
    //   17: ldc -48
    //   19: invokestatic 213	o/O:ˋ	(IIC)Ljava/lang/Object;
    //   22: checkcast 215	java/lang/Class
    //   25: ldc -40
    //   27: invokevirtual 220	java/lang/Class:getField	(Ljava/lang/String;)Ljava/lang/reflect/Field;
    //   30: aconst_null
    //   31: invokevirtual 226	java/lang/reflect/Field:get	(Ljava/lang/Object;)Ljava/lang/Object;
    //   34: checkcast 228	java/lang/Enum
    //   37: invokespecial 231	o/HT:<init>	(Ljava/lang/Enum;)V
    //   40: invokevirtual 234	o/zp:ˎ	(Ljava/lang/Object;)V
    //   43: getstatic 22	o/KI:ॱˉ	I
    //   46: bipush 41
    //   48: iadd
    //   49: istore_3
    //   50: iload_3
    //   51: sipush 128
    //   54: irem
    //   55: putstatic 20	o/KI:ॱـ	I
    //   58: iload_3
    //   59: iconst_2
    //   60: irem
    //   61: ifeq +6 -> 67
    //   64: goto +7 -> 71
    //   67: return
    //   68: goto -62 -> 6
    //   71: return
    // Local variable table:
    //   start	length	slot	name	signature
    //   0	72	0	this	KI
    //   0	72	1	paramᐸ	ᐸ
    //   0	72	2	paramะ	ะ
    //   49	12	3	i	int
    // Exception table:
    //   from	to	target	type
    //   43	50	3	java/lang/Exception
    //   50	58	3	java/lang/Exception
  }
  
  /* Error */
  public int ˎ()
  {
    // Byte code:
    //   0: goto +11 -> 11
    //   3: new 133	java/lang/NullPointerException
    //   6: dup
    //   7: invokespecial 135	java/lang/NullPointerException:<init>	()V
    //   10: athrow
    //   11: goto +84 -> 95
    //   14: astore_3
    //   15: aload_3
    //   16: athrow
    //   17: getstatic 240	o/Jy$ˊ:dialog_enrollment_tutorial	I
    //   20: istore_1
    //   21: goto +117 -> 138
    //   24: astore_3
    //   25: aload_3
    //   26: athrow
    //   27: iload_1
    //   28: tableswitch	default:+24->52, 0:+101->129, 1:+-11->17
    //   52: goto +77 -> 129
    //   55: iconst_0
    //   56: istore_2
    //   57: goto +13 -> 70
    //   60: iconst_1
    //   61: istore_2
    //   62: goto +8 -> 70
    //   65: iconst_1
    //   66: istore_1
    //   67: goto -40 -> 27
    //   70: iload_2
    //   71: tableswitch	default:+21->92, 0:+56->127, 1:+-68->3
    //   92: goto -89 -> 3
    //   95: getstatic 22	o/KI:ॱˉ	I
    //   98: bipush 13
    //   100: iadd
    //   101: istore_1
    //   102: iload_1
    //   103: sipush 128
    //   106: irem
    //   107: putstatic 20	o/KI:ॱـ	I
    //   110: iload_1
    //   111: iconst_2
    //   112: irem
    //   113: ifeq +6 -> 119
    //   116: goto +6 -> 122
    //   119: goto -54 -> 65
    //   122: iconst_0
    //   123: istore_1
    //   124: goto -97 -> 27
    //   127: iload_1
    //   128: ireturn
    //   129: getstatic 240	o/Jy$ˊ:dialog_enrollment_tutorial	I
    //   132: istore_1
    //   133: bipush 83
    //   135: iconst_0
    //   136: idiv
    //   137: istore_2
    //   138: getstatic 22	o/KI:ॱˉ	I
    //   141: istore_2
    //   142: iload_2
    //   143: bipush 35
    //   145: iadd
    //   146: istore_2
    //   147: iload_2
    //   148: sipush 128
    //   151: irem
    //   152: putstatic 20	o/KI:ॱـ	I
    //   155: iload_2
    //   156: iconst_2
    //   157: irem
    //   158: ifeq +6 -> 164
    //   161: goto -101 -> 60
    //   164: goto -109 -> 55
    // Local variable table:
    //   start	length	slot	name	signature
    //   0	167	0	this	KI
    //   20	113	1	i	int
    //   56	102	2	j	int
    //   14	2	3	localException1	Exception
    //   24	2	3	localException2	Exception
    // Exception table:
    //   from	to	target	type
    //   147	155	14	java/lang/Exception
    //   17	21	24	java/lang/Exception
    //   129	138	24	java/lang/Exception
    //   138	142	24	java/lang/Exception
  }
}
