package o;

import java.io.UnsupportedEncodingException;

public final class KJ
  extends x
{
  private static byte ॱˈ;
  private static int ॱˉ;
  private static int[] ॱˍ;
  private static int ॱـ;
  private final HQ ߺ;
  
  /* Error */
  static
  {
    // Byte code:
    //   0: goto +70 -> 70
    //   3: getstatic 19	o/KJ:ॱˉ	I
    //   6: bipush 13
    //   8: iadd
    //   9: istore_0
    //   10: iload_0
    //   11: sipush 128
    //   14: irem
    //   15: putstatic 21	o/KJ:ॱـ	I
    //   18: iload_0
    //   19: iconst_2
    //   20: irem
    //   21: ifeq +6 -> 27
    //   24: goto +6 -> 30
    //   27: goto +11 -> 38
    //   30: iconst_0
    //   31: istore_0
    //   32: goto +8 -> 40
    //   35: astore_1
    //   36: aload_1
    //   37: athrow
    //   38: iconst_1
    //   39: istore_0
    //   40: iload_0
    //   41: tableswitch	default:+23->64, 0:+24->65, 1:+28->69
    //   64: return
    //   65: aconst_null
    //   66: arraylength
    //   67: istore_0
    //   68: return
    //   69: return
    //   70: iconst_0
    //   71: putstatic 21	o/KJ:ॱـ	I
    //   74: iconst_1
    //   75: putstatic 19	o/KJ:ॱˉ	I
    //   78: invokestatic 24	o/KJ:ˎ	()V
    //   81: bipush -102
    //   83: putstatic 26	o/KJ:ॱˈ	B
    //   86: goto -83 -> 3
    //   89: astore_1
    //   90: aload_1
    //   91: athrow
    // Local variable table:
    //   start	length	slot	name	signature
    //   9	59	0	i	int
    //   35	2	1	localException1	Exception
    //   89	2	1	localException2	Exception
    // Exception table:
    //   from	to	target	type
    //   78	81	35	java/lang/Exception
    //   70	74	89	java/lang/Exception
    //   74	78	89	java/lang/Exception
    //   78	81	89	java/lang/Exception
    //   81	86	89	java/lang/Exception
  }
  
  /* Error */
  public KJ(android.content.Context paramContext, HQ paramHQ)
  {
    // Byte code:
    //   0: goto +30 -> 30
    //   3: getstatic 19	o/KJ:ॱˉ	I
    //   6: bipush 35
    //   8: iadd
    //   9: istore_3
    //   10: iload_3
    //   11: sipush 128
    //   14: irem
    //   15: putstatic 21	o/KJ:ॱـ	I
    //   18: iload_3
    //   19: iconst_2
    //   20: irem
    //   21: ifeq +6 -> 27
    //   24: goto +170 -> 194
    //   27: goto +194 -> 221
    //   30: aload_1
    //   31: iconst_4
    //   32: newarray int
    //   34: dup
    //   35: iconst_0
    //   36: ldc 30
    //   38: iastore
    //   39: dup
    //   40: iconst_1
    //   41: ldc 31
    //   43: iastore
    //   44: dup
    //   45: iconst_2
    //   46: ldc 32
    //   48: iastore
    //   49: dup
    //   50: iconst_3
    //   51: ldc 33
    //   53: iastore
    //   54: bipush 7
    //   56: invokestatic 37	o/KJ:ˏ	([II)Ljava/lang/String;
    //   59: invokevirtual 43	java/lang/String:intern	()Ljava/lang/String;
    //   62: invokestatic 48	o/vq:ˎ	(Ljava/lang/Object;Ljava/lang/String;)V
    //   65: aload_2
    //   66: iconst_4
    //   67: newarray int
    //   69: dup
    //   70: iconst_0
    //   71: ldc 49
    //   73: iastore
    //   74: dup
    //   75: iconst_1
    //   76: ldc 50
    //   78: iastore
    //   79: dup
    //   80: iconst_2
    //   81: ldc 51
    //   83: iastore
    //   84: dup
    //   85: iconst_3
    //   86: ldc 52
    //   88: iastore
    //   89: bipush 8
    //   91: invokestatic 37	o/KJ:ˏ	([II)Ljava/lang/String;
    //   94: invokevirtual 43	java/lang/String:intern	()Ljava/lang/String;
    //   97: invokestatic 48	o/vq:ˎ	(Ljava/lang/Object;Ljava/lang/String;)V
    //   100: aload_0
    //   101: aload_1
    //   102: invokespecial 55	o/x:<init>	(Landroid/content/Context;)V
    //   105: aload_0
    //   106: aload_2
    //   107: putfield 57	o/KJ:ߺ	Lo/HQ;
    //   110: aload_0
    //   111: getstatic 62	o/Jy$iF:ic_error	I
    //   114: invokevirtual 65	o/KJ:ˎ	(I)Lo/ᐸ$If;
    //   117: pop
    //   118: aload_0
    //   119: getfield 57	o/KJ:ߺ	Lo/HQ;
    //   122: invokevirtual 71	o/HQ:ˈ	()Z
    //   125: ifeq +6 -> 131
    //   128: goto +193 -> 321
    //   131: goto +370 -> 501
    //   134: aload_0
    //   135: aload_2
    //   136: iconst_4
    //   137: invokevirtual 75	java/lang/String:substring	(I)Ljava/lang/String;
    //   140: invokespecial 79	o/KJ:ˊ	(Ljava/lang/String;)Ljava/lang/String;
    //   143: invokevirtual 43	java/lang/String:intern	()Ljava/lang/String;
    //   146: astore_1
    //   147: goto +351 -> 498
    //   150: iconst_1
    //   151: istore_3
    //   152: goto +445 -> 597
    //   155: aload_1
    //   156: iload_3
    //   157: invokevirtual 84	android/content/Context:getString	(I)Ljava/lang/String;
    //   160: astore_2
    //   161: aload_2
    //   162: iconst_2
    //   163: newarray int
    //   165: dup
    //   166: iconst_0
    //   167: ldc 85
    //   169: iastore
    //   170: dup
    //   171: iconst_1
    //   172: ldc 86
    //   174: iastore
    //   175: iconst_4
    //   176: invokestatic 37	o/KJ:ˏ	([II)Ljava/lang/String;
    //   179: invokevirtual 43	java/lang/String:intern	()Ljava/lang/String;
    //   182: invokevirtual 90	java/lang/String:startsWith	(Ljava/lang/String;)Z
    //   185: ifeq +6 -> 191
    //   188: goto +345 -> 533
    //   191: goto +435 -> 626
    //   194: getstatic 95	o/Jy$IF:suspended_token_card_dialog_title	I
    //   197: istore_3
    //   198: bipush 91
    //   200: iconst_0
    //   201: idiv
    //   202: istore 4
    //   204: goto +419 -> 623
    //   207: bipush 36
    //   209: istore 4
    //   211: goto +216 -> 427
    //   214: bipush 89
    //   216: istore 4
    //   218: goto +209 -> 427
    //   221: getstatic 95	o/Jy$IF:suspended_token_card_dialog_title	I
    //   224: istore_3
    //   225: goto +398 -> 623
    //   228: iconst_0
    //   229: istore_3
    //   230: goto +367 -> 597
    //   233: getstatic 98	o/Jy$IF:expired_token_card_dialog_content	I
    //   236: istore 4
    //   238: goto -83 -> 155
    //   241: astore_1
    //   242: aload_1
    //   243: athrow
    //   244: aload_0
    //   245: aload_1
    //   246: checkcast 100	java/lang/CharSequence
    //   249: invokevirtual 104	o/KJ:ॱ	(Ljava/lang/CharSequence;)Lo/ᐸ$If;
    //   252: pop
    //   253: return
    //   254: getstatic 21	o/KJ:ॱـ	I
    //   257: bipush 99
    //   259: iadd
    //   260: istore_3
    //   261: iload_3
    //   262: sipush 128
    //   265: irem
    //   266: putstatic 19	o/KJ:ॱˉ	I
    //   269: iload_3
    //   270: iconst_2
    //   271: irem
    //   272: ifne +6 -> 278
    //   275: goto +274 -> 549
    //   278: goto +239 -> 517
    //   281: getstatic 19	o/KJ:ॱˉ	I
    //   284: bipush 25
    //   286: iadd
    //   287: istore 4
    //   289: iload 4
    //   291: sipush 128
    //   294: irem
    //   295: putstatic 21	o/KJ:ॱـ	I
    //   298: iload 4
    //   300: iconst_2
    //   301: irem
    //   302: ifeq +6 -> 308
    //   305: goto +173 -> 478
    //   308: goto +159 -> 467
    //   311: astore_1
    //   312: aload_1
    //   313: athrow
    //   314: getstatic 107	o/Jy$IF:uninitialized_card_dialog_title	I
    //   317: istore_3
    //   318: goto +93 -> 411
    //   321: getstatic 110	o/Jy$IF:expired_token_card_dialog_title	I
    //   324: istore_3
    //   325: goto +86 -> 411
    //   328: aload_2
    //   329: astore_1
    //   330: iload_3
    //   331: lookupswitch	default:+25->356, 58:+-197->134, 69:+-87->244
    //   356: aload_2
    //   357: astore_1
    //   358: goto -114 -> 244
    //   361: aload_0
    //   362: aload_2
    //   363: checkcast 100	java/lang/CharSequence
    //   366: invokevirtual 113	o/KJ:ˋ	(Ljava/lang/CharSequence;)Lo/ᐸ$If;
    //   369: pop
    //   370: aload_1
    //   371: getstatic 116	o/Jy$IF:cancel	I
    //   374: invokevirtual 84	android/content/Context:getString	(I)Ljava/lang/String;
    //   377: astore_2
    //   378: aload_2
    //   379: iconst_2
    //   380: newarray int
    //   382: dup
    //   383: iconst_0
    //   384: ldc 85
    //   386: iastore
    //   387: dup
    //   388: iconst_1
    //   389: ldc 86
    //   391: iastore
    //   392: iconst_4
    //   393: invokestatic 37	o/KJ:ˏ	([II)Ljava/lang/String;
    //   396: invokevirtual 43	java/lang/String:intern	()Ljava/lang/String;
    //   399: invokevirtual 90	java/lang/String:startsWith	(Ljava/lang/String;)Z
    //   402: ifeq +6 -> 408
    //   405: goto +87 -> 492
    //   408: goto +164 -> 572
    //   411: aload_0
    //   412: getfield 57	o/KJ:ߺ	Lo/HQ;
    //   415: invokevirtual 71	o/HQ:ˈ	()Z
    //   418: ifeq +6 -> 424
    //   421: goto -214 -> 207
    //   424: goto -210 -> 214
    //   427: iload 4
    //   429: lookupswitch	default:+27->456, 36:+-196->233, 89:+152->581
    //   456: goto -223 -> 233
    //   459: getstatic 119	o/Jy$IF:uninitialized_card_dialog_content	I
    //   462: istore 4
    //   464: goto +11 -> 475
    //   467: getstatic 122	o/Jy$IF:suspended_token_card_dialog_content	I
    //   470: istore 4
    //   472: goto +106 -> 578
    //   475: goto -320 -> 155
    //   478: getstatic 122	o/Jy$IF:suspended_token_card_dialog_content	I
    //   481: istore 4
    //   483: bipush 48
    //   485: iconst_0
    //   486: idiv
    //   487: istore 5
    //   489: goto +89 -> 578
    //   492: bipush 58
    //   494: istore_3
    //   495: goto -167 -> 328
    //   498: goto -254 -> 244
    //   501: aload_0
    //   502: getfield 57	o/KJ:ߺ	Lo/HQ;
    //   505: invokevirtual 125	o/HQ:ˋˊ	()Z
    //   508: ifeq +6 -> 514
    //   511: goto -283 -> 228
    //   514: goto -364 -> 150
    //   517: aload_0
    //   518: aload_2
    //   519: iconst_4
    //   520: invokevirtual 75	java/lang/String:substring	(I)Ljava/lang/String;
    //   523: invokespecial 79	o/KJ:ˊ	(Ljava/lang/String;)Ljava/lang/String;
    //   526: invokevirtual 43	java/lang/String:intern	()Ljava/lang/String;
    //   529: astore_2
    //   530: goto -169 -> 361
    //   533: aload_0
    //   534: aload_2
    //   535: iconst_4
    //   536: invokevirtual 75	java/lang/String:substring	(I)Ljava/lang/String;
    //   539: invokespecial 79	o/KJ:ˊ	(Ljava/lang/String;)Ljava/lang/String;
    //   542: invokevirtual 43	java/lang/String:intern	()Ljava/lang/String;
    //   545: astore_2
    //   546: goto +80 -> 626
    //   549: aload_0
    //   550: aload_2
    //   551: iconst_4
    //   552: invokevirtual 75	java/lang/String:substring	(I)Ljava/lang/String;
    //   555: invokespecial 79	o/KJ:ˊ	(Ljava/lang/String;)Ljava/lang/String;
    //   558: astore_1
    //   559: aload_1
    //   560: invokevirtual 43	java/lang/String:intern	()Ljava/lang/String;
    //   563: astore_1
    //   564: new 127	java/lang/NullPointerException
    //   567: dup
    //   568: invokespecial 129	java/lang/NullPointerException:<init>	()V
    //   571: athrow
    //   572: bipush 69
    //   574: istore_3
    //   575: goto -247 -> 328
    //   578: goto -423 -> 155
    //   581: aload_0
    //   582: getfield 57	o/KJ:ߺ	Lo/HQ;
    //   585: invokevirtual 125	o/HQ:ˋˊ	()Z
    //   588: ifeq +6 -> 594
    //   591: goto -310 -> 281
    //   594: goto -135 -> 459
    //   597: iload_3
    //   598: tableswitch	default:+22->620, 0:+-595->3, 1:+-284->314
    //   620: goto -617 -> 3
    //   623: goto -212 -> 411
    //   626: aload_0
    //   627: aload_2
    //   628: checkcast 100	java/lang/CharSequence
    //   631: invokevirtual 131	o/KJ:ˊ	(Ljava/lang/CharSequence;)Lo/ᐸ$If;
    //   634: pop
    //   635: aload_1
    //   636: iload 4
    //   638: invokevirtual 84	android/content/Context:getString	(I)Ljava/lang/String;
    //   641: astore_2
    //   642: aload_2
    //   643: iconst_2
    //   644: newarray int
    //   646: dup
    //   647: iconst_0
    //   648: ldc 85
    //   650: iastore
    //   651: dup
    //   652: iconst_1
    //   653: ldc 86
    //   655: iastore
    //   656: iconst_4
    //   657: invokestatic 37	o/KJ:ˏ	([II)Ljava/lang/String;
    //   660: invokevirtual 43	java/lang/String:intern	()Ljava/lang/String;
    //   663: invokevirtual 90	java/lang/String:startsWith	(Ljava/lang/String;)Z
    //   666: istore 6
    //   668: iload 6
    //   670: ifeq +6 -> 676
    //   673: goto -419 -> 254
    //   676: goto -315 -> 361
    // Local variable table:
    //   start	length	slot	name	signature
    //   0	679	0	this	KJ
    //   0	679	1	paramContext	android.content.Context
    //   0	679	2	paramHQ	HQ
    //   9	589	3	i	int
    //   202	435	4	j	int
    //   487	1	5	k	int
    //   666	3	6	bool	boolean
    // Exception table:
    //   from	to	target	type
    //   478	489	241	java/lang/Exception
    //   549	559	311	java/lang/Exception
    //   559	564	311	java/lang/Exception
    //   564	572	311	java/lang/Exception
    //   626	668	311	java/lang/Exception
  }
  
  private String ˊ(String paramString)
  {
    break label45;
    int i = 47;
    break label310;
    break label379;
    for (;;)
    {
      i = 54;
      break label339;
      label18:
      i = ॱˉ + 15;
      ॱـ = i % 128;
      if (i % 2 != 0) {
        break;
      }
    }
    label45:
    break label264;
    label48:
    byte[] arrayOfByte;
    int j;
    for (;;)
    {
      try
      {
        arrayOfByte = paramString.getBytes(ˏ(new int[] { 93826261, 1762692019, 1697152596, 223136944, -1303393897, 372192294 }, 28).intern());
        paramString = new byte[arrayOfByte.length];
        i = 1;
      }
      catch (UnsupportedEncodingException paramString)
      {
        label217:
        throw new RuntimeException(paramString);
      }
      i = ॱˉ + 81;
      ॱـ = i % 128;
      if (i % 2 != 0) {
        break label371;
      }
      return paramString;
      paramString[i] = ((byte)(arrayOfByte[(arrayOfByte.length - i - 1)] ^ ॱˈ));
      j = i + 1;
      break label18;
      arrayOfByte = paramString.getBytes(ˏ(new int[] { 93826261, 1762692019, 1697152596, 223136944, -1303393897, 372192294 }, 10).intern());
      paramString = new byte[arrayOfByte.length];
      i = 0;
      break;
      paramString = new String(paramString, ˏ(new int[] { 314666934, 1282815557, 1633632112, 1901901166 }, 5).intern());
    }
    for (;;)
    {
      i = j;
      break label379;
      label264:
      i = ॱˉ + 63;
      ॱـ = i % 128;
      if (i % 2 != 0) {
        break;
      }
      break label307;
      i = 23;
      break label339;
      label307:
      i = 67;
      label310:
      switch (i)
      {
      }
      break label48;
      label339:
      switch (i)
      {
      }
    }
    label371:
    throw new NullPointerException();
    for (;;)
    {
      label379:
      j = arrayOfByte.length;
      if (i < j) {
        break;
      }
      break label217;
      i = j;
    }
  }
  
  static void ˎ()
  {
    ॱˍ = new int[] { 1813121103, -2086794428, 621450595, -645898918, 1904838458, 1519858099, 1195120348, 349035801, 452677989, 984373008, -207603091, 1190754038, 1549057477, -429408886, 1676368443, 1280802749, -55063696, 1502566198 };
  }
  
  /* Error */
  private static String ˏ(int[] paramArrayOfInt, int paramInt)
  {
    // Byte code:
    //   0: goto +63 -> 63
    //   3: iload_3
    //   4: istore_2
    //   5: goto +263 -> 268
    //   8: new 39	java/lang/String
    //   11: dup
    //   12: aload 5
    //   14: iconst_0
    //   15: iload_1
    //   16: invokespecial 178	java/lang/String:<init>	([CII)V
    //   19: areturn
    //   20: astore_0
    //   21: aload_0
    //   22: athrow
    //   23: iconst_1
    //   24: istore_2
    //   25: goto +11 -> 36
    //   28: astore_0
    //   29: aload_0
    //   30: athrow
    //   31: iload_3
    //   32: istore_2
    //   33: goto +235 -> 268
    //   36: iload_2
    //   37: tableswitch	default:+23->60, 0:+-34->3, 1:+-6->31
    //   60: goto -57 -> 3
    //   63: iconst_4
    //   64: newarray char
    //   66: astore 4
    //   68: aload_0
    //   69: arraylength
    //   70: iconst_1
    //   71: ishl
    //   72: newarray char
    //   74: astore 5
    //   76: getstatic 175	o/KJ:ॱˍ	[I
    //   79: invokevirtual 183	[I:clone	()Ljava/lang/Object;
    //   82: checkcast 179	[I
    //   85: astore 6
    //   87: iconst_0
    //   88: istore_3
    //   89: goto +152 -> 241
    //   92: aload 4
    //   94: iconst_0
    //   95: aload_0
    //   96: iload_2
    //   97: iaload
    //   98: bipush 16
    //   100: ishr
    //   101: i2c
    //   102: castore
    //   103: aload 4
    //   105: iconst_1
    //   106: aload_0
    //   107: iload_2
    //   108: iaload
    //   109: i2c
    //   110: castore
    //   111: aload 4
    //   113: iconst_2
    //   114: aload_0
    //   115: iload_2
    //   116: iconst_1
    //   117: iadd
    //   118: iaload
    //   119: bipush 16
    //   121: ishr
    //   122: i2c
    //   123: castore
    //   124: aload 4
    //   126: iconst_3
    //   127: aload_0
    //   128: iload_2
    //   129: iconst_1
    //   130: iadd
    //   131: iaload
    //   132: i2c
    //   133: castore
    //   134: aload 4
    //   136: aload 6
    //   138: iconst_0
    //   139: invokestatic 188	o/oN:ˏ	([C[IZ)[I
    //   142: pop
    //   143: aload 5
    //   145: iload_2
    //   146: iconst_1
    //   147: ishl
    //   148: aload 4
    //   150: iconst_0
    //   151: caload
    //   152: castore
    //   153: aload 5
    //   155: iload_2
    //   156: iconst_1
    //   157: ishl
    //   158: iconst_1
    //   159: iadd
    //   160: aload 4
    //   162: iconst_1
    //   163: caload
    //   164: castore
    //   165: aload 5
    //   167: iload_2
    //   168: iconst_1
    //   169: ishl
    //   170: iconst_2
    //   171: iadd
    //   172: aload 4
    //   174: iconst_2
    //   175: caload
    //   176: castore
    //   177: aload 5
    //   179: iload_2
    //   180: iconst_1
    //   181: ishl
    //   182: iconst_3
    //   183: iadd
    //   184: aload 4
    //   186: iconst_3
    //   187: caload
    //   188: castore
    //   189: iload_2
    //   190: iconst_2
    //   191: iadd
    //   192: istore_2
    //   193: goto +75 -> 268
    //   196: iconst_0
    //   197: istore_3
    //   198: goto +82 -> 280
    //   201: goto -109 -> 92
    //   204: iconst_1
    //   205: istore_3
    //   206: goto +74 -> 280
    //   209: getstatic 19	o/KJ:ॱˉ	I
    //   212: bipush 49
    //   214: iadd
    //   215: istore_3
    //   216: iload_3
    //   217: sipush 128
    //   220: irem
    //   221: putstatic 21	o/KJ:ॱـ	I
    //   224: iload_3
    //   225: iconst_2
    //   226: irem
    //   227: ifeq +6 -> 233
    //   230: goto -29 -> 201
    //   233: goto -141 -> 92
    //   236: iconst_0
    //   237: istore_2
    //   238: goto -202 -> 36
    //   241: getstatic 19	o/KJ:ॱˉ	I
    //   244: bipush 15
    //   246: iadd
    //   247: istore_2
    //   248: iload_2
    //   249: sipush 128
    //   252: irem
    //   253: putstatic 21	o/KJ:ॱـ	I
    //   256: iload_2
    //   257: iconst_2
    //   258: irem
    //   259: ifeq +6 -> 265
    //   262: goto -239 -> 23
    //   265: goto -29 -> 236
    //   268: iload_2
    //   269: aload_0
    //   270: arraylength
    //   271: if_icmpge +6 -> 277
    //   274: goto -70 -> 204
    //   277: goto -81 -> 196
    //   280: iload_3
    //   281: tableswitch	default:+23->304, 0:+-273->8, 1:+-72->209
    //   304: goto -95 -> 209
    // Local variable table:
    //   start	length	slot	name	signature
    //   0	307	0	paramArrayOfInt	int[]
    //   0	307	1	paramInt	int
    //   4	268	2	i	int
    //   3	278	3	j	int
    //   66	119	4	arrayOfChar1	char[]
    //   12	166	5	arrayOfChar2	char[]
    //   85	52	6	arrayOfInt	int[]
    // Exception table:
    //   from	to	target	type
    //   134	143	20	java/lang/Exception
    //   241	248	28	java/lang/Exception
    //   248	256	28	java/lang/Exception
  }
}
