package o;

import android.content.Context;
import android.content.pm.ApplicationInfo;
import android.content.res.Resources;
import android.os.Handler;
import android.view.View;
import android.view.View.OnClickListener;
import android.view.animation.Animation;
import android.view.animation.Animation.AnimationListener;
import android.view.animation.AnimationUtils;
import android.widget.Button;
import android.widget.RelativeLayout;
import java.util.List;
import org.greenrobot.eventbus.ThreadMode;

public class Km
  extends IB<JF>
{
  private static int ˉ = 0;
  private static byte ˊˊ;
  private static int ˊˋ = 1;
  private static int ˋˊ;
  private Lc ʼॱ;
  private KF ʽॱ;
  protected Eu ʾ;
  private boolean ʿ = false;
  private ˊ ˈ;
  
  static
  {
    ॱˋ();
    ˊˊ = -102;
    int i = ˊˋ + 103;
    ˉ = i % 128;
    if (i % 2 == 0) {}
  }
  
  public Km() {}
  
  private void ʻॱ()
  {
    break label91;
    return;
    for (;;)
    {
      switch (i)
      {
      case 94: 
      default: 
        return;
        label33:
        i = 86;
      }
    }
    int i = 66 / 0;
    return;
    label91:
    for (;;)
    {
      final Animation localAnimation = AnimationUtils.loadAnimation(this, Jy.If.fade_in);
      localAnimation.setAnimationListener(new Animation.AnimationListener()
      {
        public void onAnimationEnd(Animation paramAnonymousAnimation)
        {
          Km.ˏ(Km.this, Km.ʽ(Km.this));
        }
        
        public void onAnimationRepeat(Animation paramAnonymousAnimation) {}
        
        public void onAnimationStart(Animation paramAnonymousAnimation)
        {
          ((JF)Km.ʼ(Km.this)).ˊ(Km.ˊ(Km.this));
        }
      });
      new Handler().postDelayed(new Runnable()
      {
        public void run()
        {
          ((JF)Km.ˏॱ(Km.this)).ˊॱ.startAnimation(localAnimation);
          Km.ˊ(Km.this, new Km.ˊ(Km.this, null));
          ((JF)Km.ॱˊ(Km.this)).ˊ.ˎ(Km.ʽ(Km.this));
        }
      }, 1000L);
      break;
    }
    for (;;)
    {
      i = 94;
      break;
      i = ˊˋ + 33;
      ˉ = i % 128;
      if (i % 2 != 0) {
        break label33;
      }
    }
  }
  
  private void ʾ()
  {
    for (;;)
    {
      return;
      int i = 70;
      for (;;)
      {
        ((JF)this.ॱˊ).ˎ(true);
        if (!this.ʿ) {
          break;
        }
        for (;;)
        {
          switch (i)
          {
          case 70: 
          default: 
            ˊᐝ();
            break label83;
            i = 54;
          }
        }
        label83:
        do
        {
          i = 50;
          break;
          i = ˉ + 37;
          ˊˋ = i % 128;
        } while (i % 2 == 0);
        break label137;
        i = ˊˋ + 13;
        ˉ = i % 128;
        if (i % 2 == 0)
        {
          continue;
          label137:
          i = 19;
          break label151;
        }
      }
      ˊˋ();
      return;
      label151:
      switch (i)
      {
      }
    }
  }
  
  /* Error */
  private void ˉ()
  {
    // Byte code:
    //   0: goto +91 -> 91
    //   3: astore_2
    //   4: aload_2
    //   5: athrow
    //   6: iconst_1
    //   7: istore_1
    //   8: goto +55 -> 63
    //   11: getstatic 42	o/Km:ˊˋ	I
    //   14: bipush 111
    //   16: iadd
    //   17: istore_1
    //   18: iload_1
    //   19: sipush 128
    //   22: irem
    //   23: putstatic 40	o/Km:ˉ	I
    //   26: iload_1
    //   27: iconst_2
    //   28: irem
    //   29: ifeq +6 -> 35
    //   32: goto -26 -> 6
    //   35: goto +3 -> 38
    //   38: iconst_0
    //   39: istore_1
    //   40: goto +23 -> 63
    //   43: astore_2
    //   44: aload_2
    //   45: athrow
    //   46: aload_0
    //   47: invokestatic 119	o/Ic:ˏ	(Landroid/content/Context;)Lo/Ic;
    //   50: astore_2
    //   51: aload_2
    //   52: invokevirtual 123	o/Ic:ᐝ	()Lo/j;
    //   55: astore_2
    //   56: aload_2
    //   57: bipush 13
    //   59: invokevirtual 128	o/j:ˎ	(I)V
    //   62: return
    //   63: iload_1
    //   64: tableswitch	default:+24->88, 0:+-18->46, 1:+30->94
    //   88: goto -42 -> 46
    //   91: goto -80 -> 11
    //   94: aload_0
    //   95: invokestatic 119	o/Ic:ˏ	(Landroid/content/Context;)Lo/Ic;
    //   98: invokevirtual 123	o/Ic:ᐝ	()Lo/j;
    //   101: bipush 125
    //   103: invokevirtual 128	o/j:ˎ	(I)V
    //   106: return
    // Local variable table:
    //   start	length	slot	name	signature
    //   0	107	0	this	Km
    //   7	57	1	i	int
    //   3	2	2	localException1	Exception
    //   43	2	2	localException2	Exception
    //   50	7	2	localObject	Object
    // Exception table:
    //   from	to	target	type
    //   11	18	3	java/lang/Exception
    //   18	26	3	java/lang/Exception
    //   46	51	3	java/lang/Exception
    //   18	26	43	java/lang/Exception
    //   51	56	43	java/lang/Exception
    //   56	62	43	java/lang/Exception
  }
  
  private void ˊ(List<Eu> paramList)
  {
    break label422;
    int i = 70;
    for (;;)
    {
      try
      {
        i = ˊˋ;
        i += 101;
        ˉ = i % 128;
        if (i % 2 == 0)
        {
          break label539;
          i = ˉ + 109;
          ˊˋ = i % 128;
          if (i % 2 != 0)
          {
            continue;
            i = 13;
            break label509;
            this.ʽॱ = new KF();
            ((JF)this.ॱˊ).ˊ.setAdapter(this.ʽॱ);
            ((JF)this.ॱˊ).ͺ.setupWithViewPager(((JF)this.ॱˊ).ˊ, true);
            if (!paramList.isEmpty()) {
              continue;
            }
            continue;
            localButton.setText((CharSequence)localObject);
            continue;
            i = ˉ + 25;
            ˊˋ = i % 128;
            if (i % 2 == 0) {
              continue;
            }
            continue;
          }
          else
          {
            continue;
          }
          Button localButton = ((JF)this.ॱˊ).ॱ;
          localObject = getString(Jy.IF.add_new_card);
          i = getResources().getString(2131755426).substring(0, 4).length();
          int j = getApplicationInfo().targetSdkVersion;
          int k = getPackageName().codePointAt(7);
          if (!((String)localObject).startsWith(ˏ(i + 109, j - 21, new char[] { -8, 13, -2, -1 }, k - 42, false).intern()))
          {
            continue;
            i = 51;
            continue;
            continue;
            continue;
            ˏ(paramList);
            return;
            i = 43;
            continue;
            i = 38;
          }
          switch (i)
          {
          case 38: 
          default: 
            continue;
            i = 81;
            break label509;
            i = ˉ + 107;
            ˊˋ = i % 128;
            if (i % 2 == 0) {
              continue;
            }
            break;
          case 51: 
            break;
          }
        }
        switch (i)
        {
        case 43: 
        default: 
          continue;
          break label539;
          continue;
          localObject = ˎ(((String)localObject).substring(4)).intern();
          continue;
          ((JF)this.ॱˊ).ˏ(((Eu)paramList.get(0)).ˏ());
          this.ˈ = new ˊ(null);
          ((JF)this.ॱˊ).ˊ.ˎ(this.ˈ);
          break;
        case 70: 
          label422:
          ʻॱ();
          break;
        }
        switch (i)
        {
        }
      }
      catch (Exception paramList)
      {
        throw paramList;
      }
      label509:
      continue;
      label539:
      if (this.ʿ) {
        break;
      }
      continue;
      Object localObject = ˎ(((String)localObject).substring(4)).intern();
      i = 67 / 0;
    }
  }
  
  /* Error */
  private void ˊˊ()
  {
    // Byte code:
    //   0: goto +103 -> 103
    //   3: bipush 18
    //   5: istore_1
    //   6: goto +127 -> 133
    //   9: bipush 85
    //   11: istore_1
    //   12: goto +121 -> 133
    //   15: return
    //   16: astore_2
    //   17: aload_2
    //   18: athrow
    //   19: bipush 27
    //   21: iconst_0
    //   22: idiv
    //   23: istore_1
    //   24: return
    //   25: goto +31 -> 56
    //   28: getstatic 42	o/Km:ˊˋ	I
    //   31: istore_1
    //   32: iload_1
    //   33: iconst_5
    //   34: iadd
    //   35: istore_1
    //   36: iload_1
    //   37: sipush 128
    //   40: irem
    //   41: putstatic 40	o/Km:ˉ	I
    //   44: iload_1
    //   45: iconst_2
    //   46: irem
    //   47: ifeq +6 -> 53
    //   50: goto -47 -> 3
    //   53: goto -44 -> 9
    //   56: aload_0
    //   57: aload_0
    //   58: getfield 135	o/Km:ʽॱ	Lo/KF;
    //   61: aload_0
    //   62: getfield 64	o/Km:ॱˊ	Landroid/databinding/ViewDataBinding;
    //   65: checkcast 104	o/JF
    //   68: getfield 138	o/JF:ˊ	Lo/IY;
    //   71: invokevirtual 261	o/IY:ॱ	()I
    //   74: invokevirtual 263	o/KF:ˎ	(I)Ljava/lang/Object;
    //   77: checkcast 243	o/Eu
    //   80: putfield 265	o/Km:ʾ	Lo/Eu;
    //   83: aload_0
    //   84: invokestatic 119	o/Ic:ˏ	(Landroid/content/Context;)Lo/Ic;
    //   87: aload_0
    //   88: getfield 265	o/Km:ʾ	Lo/Eu;
    //   91: invokevirtual 268	o/Ic:ˎ	(Lo/Eu;)Lo/j;
    //   94: invokevirtual 270	o/j:ˏ	()Lo/j;
    //   97: invokevirtual 272	o/j:ˎ	()V
    //   100: goto -72 -> 28
    //   103: getstatic 40	o/Km:ˉ	I
    //   106: bipush 41
    //   108: iadd
    //   109: istore_1
    //   110: iload_1
    //   111: sipush 128
    //   114: irem
    //   115: putstatic 42	o/Km:ˊˋ	I
    //   118: iload_1
    //   119: iconst_2
    //   120: irem
    //   121: ifne +6 -> 127
    //   124: goto -99 -> 25
    //   127: goto -71 -> 56
    //   130: astore_2
    //   131: aload_2
    //   132: athrow
    //   133: iload_1
    //   134: lookupswitch	default:+26->160, 18:+-115->19, 85:+-119->15
    //   160: goto -141 -> 19
    // Local variable table:
    //   start	length	slot	name	signature
    //   0	163	0	this	Km
    //   5	129	1	i	int
    //   16	2	2	localException1	Exception
    //   130	2	2	localException2	Exception
    // Exception table:
    //   from	to	target	type
    //   28	32	16	java/lang/Exception
    //   36	44	130	java/lang/Exception
  }
  
  /* Error */
  private void ˊˋ()
  {
    // Byte code:
    //   0: goto +130 -> 130
    //   3: astore_2
    //   4: aload_2
    //   5: athrow
    //   6: goto +17 -> 23
    //   9: astore_2
    //   10: aload_2
    //   11: invokevirtual 278	java/lang/Throwable:getCause	()Ljava/lang/Throwable;
    //   14: astore_3
    //   15: aload_3
    //   16: ifnull +5 -> 21
    //   19: aload_3
    //   20: athrow
    //   21: aload_2
    //   22: athrow
    //   23: aload_0
    //   24: invokevirtual 185	android/content/Context:getResources	()Landroid/content/res/Resources;
    //   27: ldc_w 279
    //   30: invokevirtual 189	android/content/res/Resources:getString	(I)Ljava/lang/String;
    //   33: iconst_0
    //   34: iconst_4
    //   35: invokevirtual 195	java/lang/String:substring	(II)Ljava/lang/String;
    //   38: iconst_0
    //   39: invokevirtual 216	java/lang/String:codePointAt	(I)I
    //   42: iconst_1
    //   43: isub
    //   44: aload_0
    //   45: invokevirtual 185	android/content/Context:getResources	()Landroid/content/res/Resources;
    //   48: ldc_w 280
    //   51: invokevirtual 189	android/content/res/Resources:getString	(I)Ljava/lang/String;
    //   54: bipush 7
    //   56: bipush 17
    //   58: invokevirtual 195	java/lang/String:substring	(II)Ljava/lang/String;
    //   61: invokevirtual 199	java/lang/String:length	()I
    //   64: bipush 125
    //   66: iadd
    //   67: aload_0
    //   68: invokevirtual 212	android/content/Context:getPackageName	()Ljava/lang/String;
    //   71: bipush 8
    //   73: invokevirtual 216	java/lang/String:codePointAt	(I)I
    //   76: ldc_w 281
    //   79: iadd
    //   80: i2c
    //   81: invokestatic 287	o/O:ˋ	(IIC)Ljava/lang/Object;
    //   84: checkcast 289	java/lang/Class
    //   87: ldc_w 290
    //   90: aconst_null
    //   91: invokevirtual 294	java/lang/Class:getMethod	(Ljava/lang/String;[Ljava/lang/Class;)Ljava/lang/reflect/Method;
    //   94: aconst_null
    //   95: aconst_null
    //   96: invokevirtual 300	java/lang/reflect/Method:invoke	(Ljava/lang/Object;[Ljava/lang/Object;)Ljava/lang/Object;
    //   99: checkcast 302	o/It
    //   102: astore_2
    //   103: aload_2
    //   104: invokeinterface 305 1 0
    //   109: astore_2
    //   110: new 9	o/Km$2
    //   113: dup
    //   114: aload_0
    //   115: aload_0
    //   116: invokespecial 308	o/Km$2:<init>	(Lo/Km;Landroid/content/Context;)V
    //   119: astore_3
    //   120: aload_2
    //   121: aload_3
    //   122: invokeinterface 313 2 0
    //   127: goto +6 -> 133
    //   130: goto -124 -> 6
    //   133: getstatic 42	o/Km:ˊˋ	I
    //   136: bipush 111
    //   138: iadd
    //   139: istore_1
    //   140: iload_1
    //   141: sipush 128
    //   144: irem
    //   145: putstatic 40	o/Km:ˉ	I
    //   148: iload_1
    //   149: iconst_2
    //   150: irem
    //   151: ifeq +4 -> 155
    //   154: return
    //   155: return
    //   156: astore_2
    //   157: aload_2
    //   158: athrow
    // Local variable table:
    //   start	length	slot	name	signature
    //   0	159	0	this	Km
    //   139	12	1	i	int
    //   3	2	2	localException1	Exception
    //   9	13	2	localObject1	Object
    //   102	19	2	localObject2	Object
    //   156	2	2	localException2	Exception
    //   14	108	3	localObject3	Object
    // Exception table:
    //   from	to	target	type
    //   10	15	3	java/lang/Exception
    //   19	21	3	java/lang/Exception
    //   21	23	3	java/lang/Exception
    //   103	110	3	java/lang/Exception
    //   110	120	3	java/lang/Exception
    //   120	127	3	java/lang/Exception
    //   23	103	9	finally
    //   120	127	156	java/lang/Exception
  }
  
  /* Error */
  private void ˊᐝ()
  {
    // Byte code:
    //   0: goto +29 -> 29
    //   3: getstatic 42	o/Km:ˊˋ	I
    //   6: bipush 57
    //   8: iadd
    //   9: istore_1
    //   10: iload_1
    //   11: sipush 128
    //   14: irem
    //   15: putstatic 40	o/Km:ˉ	I
    //   18: iload_1
    //   19: iconst_2
    //   20: irem
    //   21: ifeq +6 -> 27
    //   24: goto +4 -> 28
    //   27: return
    //   28: return
    //   29: goto +17 -> 46
    //   32: astore_2
    //   33: aload_2
    //   34: invokevirtual 278	java/lang/Throwable:getCause	()Ljava/lang/Throwable;
    //   37: astore_3
    //   38: aload_3
    //   39: ifnull +5 -> 44
    //   42: aload_3
    //   43: athrow
    //   44: aload_2
    //   45: athrow
    //   46: aload_0
    //   47: invokevirtual 185	android/content/Context:getResources	()Landroid/content/res/Resources;
    //   50: ldc_w 315
    //   53: invokevirtual 189	android/content/res/Resources:getString	(I)Ljava/lang/String;
    //   56: iconst_0
    //   57: iconst_4
    //   58: invokevirtual 195	java/lang/String:substring	(II)Ljava/lang/String;
    //   61: invokevirtual 199	java/lang/String:length	()I
    //   64: iconst_0
    //   65: iadd
    //   66: aload_0
    //   67: invokevirtual 203	android/content/Context:getApplicationInfo	()Landroid/content/pm/ApplicationInfo;
    //   70: getfield 208	android/content/pm/ApplicationInfo:targetSdkVersion	I
    //   73: bipush 110
    //   75: iadd
    //   76: aload_0
    //   77: invokevirtual 212	android/content/Context:getPackageName	()Ljava/lang/String;
    //   80: bipush 8
    //   82: invokevirtual 216	java/lang/String:codePointAt	(I)I
    //   85: ldc_w 281
    //   88: iadd
    //   89: i2c
    //   90: invokestatic 287	o/O:ˋ	(IIC)Ljava/lang/Object;
    //   93: checkcast 289	java/lang/Class
    //   96: ldc_w 290
    //   99: aconst_null
    //   100: invokevirtual 294	java/lang/Class:getMethod	(Ljava/lang/String;[Ljava/lang/Class;)Ljava/lang/reflect/Method;
    //   103: aconst_null
    //   104: aconst_null
    //   105: invokevirtual 300	java/lang/reflect/Method:invoke	(Ljava/lang/Object;[Ljava/lang/Object;)Ljava/lang/Object;
    //   108: checkcast 302	o/It
    //   111: astore_2
    //   112: aload_2
    //   113: invokeinterface 317 1 0
    //   118: new 7	o/Km$1
    //   121: dup
    //   122: aload_0
    //   123: aload_0
    //   124: invokespecial 318	o/Km$1:<init>	(Lo/Km;Landroid/content/Context;)V
    //   127: invokeinterface 313 2 0
    //   132: goto -129 -> 3
    // Local variable table:
    //   start	length	slot	name	signature
    //   0	135	0	this	Km
    //   9	12	1	i	int
    //   32	13	2	localObject	Object
    //   111	2	2	localIt	It
    //   37	6	3	localThrowable	Throwable
    // Exception table:
    //   from	to	target	type
    //   46	112	32	finally
  }
  
  /* Error */
  private void ˋˊ()
  {
    // Byte code:
    //   0: goto +52 -> 52
    //   3: aload_0
    //   4: invokespecial 322	o/Km:ˉ	()V
    //   7: bipush 55
    //   9: iconst_0
    //   10: idiv
    //   11: istore_1
    //   12: goto +116 -> 128
    //   15: iconst_0
    //   16: istore_1
    //   17: goto +38 -> 55
    //   20: getstatic 42	o/Km:ˊˋ	I
    //   23: bipush 125
    //   25: iadd
    //   26: istore_1
    //   27: iload_1
    //   28: sipush 128
    //   31: irem
    //   32: putstatic 40	o/Km:ˉ	I
    //   35: iload_1
    //   36: iconst_2
    //   37: irem
    //   38: ifeq +6 -> 44
    //   41: goto +136 -> 177
    //   44: goto +243 -> 287
    //   47: iconst_1
    //   48: istore_1
    //   49: goto +140 -> 189
    //   52: goto -32 -> 20
    //   55: iload_1
    //   56: tableswitch	default:+24->80, 0:+184->240, 1:+72->128
    //   80: goto +48 -> 128
    //   83: iload_1
    //   84: lookupswitch	default:+28->112, 21:+156->240, 24:+44->128
    //   112: goto +16 -> 128
    //   115: aload_0
    //   116: getfield 53	o/Km:ʿ	Z
    //   119: ifne +6 -> 125
    //   122: goto +7 -> 129
    //   125: goto +10 -> 135
    //   128: return
    //   129: bipush 21
    //   131: istore_1
    //   132: goto -49 -> 83
    //   135: bipush 24
    //   137: istore_1
    //   138: goto -55 -> 83
    //   141: iload_1
    //   142: tableswitch	default:+22->164, 0:+-27->115, 1:+73->215
    //   164: goto -49 -> 115
    //   167: astore 4
    //   169: aload 4
    //   171: athrow
    //   172: aload_0
    //   173: invokespecial 322	o/Km:ˉ	()V
    //   176: return
    //   177: iconst_1
    //   178: istore_1
    //   179: goto -38 -> 141
    //   182: iconst_1
    //   183: istore_1
    //   184: goto -129 -> 55
    //   187: iconst_0
    //   188: istore_1
    //   189: iload_1
    //   190: tableswitch	default:+22->212, 0:+102->292, 1:+107->297
    //   212: goto +80 -> 292
    //   215: aload_0
    //   216: getfield 53	o/Km:ʿ	Z
    //   219: istore_3
    //   220: bipush 13
    //   222: iconst_0
    //   223: idiv
    //   224: istore_1
    //   225: iload_3
    //   226: ifne +6 -> 232
    //   229: goto -214 -> 15
    //   232: goto -50 -> 182
    //   235: astore 4
    //   237: aload 4
    //   239: athrow
    //   240: aload_0
    //   241: getfield 64	o/Km:ॱˊ	Landroid/databinding/ViewDataBinding;
    //   244: astore 4
    //   246: aload 4
    //   248: checkcast 104	o/JF
    //   251: astore 4
    //   253: aload 4
    //   255: getfield 138	o/JF:ˊ	Lo/IY;
    //   258: astore 4
    //   260: aload 4
    //   262: invokevirtual 261	o/IY:ॱ	()I
    //   265: istore_1
    //   266: aload_0
    //   267: getfield 135	o/Km:ʽॱ	Lo/KF;
    //   270: invokevirtual 323	o/KF:ॱ	()I
    //   273: istore_2
    //   274: iload_1
    //   275: iload_2
    //   276: iconst_1
    //   277: isub
    //   278: if_icmpne +6 -> 284
    //   281: goto -234 -> 47
    //   284: goto -97 -> 187
    //   287: iconst_0
    //   288: istore_1
    //   289: goto -148 -> 141
    //   292: aload_0
    //   293: invokespecial 325	o/Km:ˊˊ	()V
    //   296: return
    //   297: getstatic 40	o/Km:ˉ	I
    //   300: bipush 85
    //   302: iadd
    //   303: istore_1
    //   304: iload_1
    //   305: sipush 128
    //   308: irem
    //   309: putstatic 42	o/Km:ˊˋ	I
    //   312: iload_1
    //   313: iconst_2
    //   314: irem
    //   315: ifne +6 -> 321
    //   318: goto -315 -> 3
    //   321: goto -149 -> 172
    // Local variable table:
    //   start	length	slot	name	signature
    //   0	324	0	this	Km
    //   11	304	1	i	int
    //   273	5	2	j	int
    //   219	7	3	bool	boolean
    //   167	3	4	localException1	Exception
    //   235	3	4	localException2	Exception
    //   244	17	4	localObject	Object
    // Exception table:
    //   from	to	target	type
    //   246	253	167	java/lang/Exception
    //   240	246	235	java/lang/Exception
    //   246	253	235	java/lang/Exception
    //   253	260	235	java/lang/Exception
    //   260	266	235	java/lang/Exception
    //   266	274	235	java/lang/Exception
  }
  
  /* Error */
  private String ˎ(String paramString)
  {
    // Byte code:
    //   0: goto +238 -> 238
    //   3: aload_0
    //   4: invokevirtual 212	android/content/Context:getPackageName	()Ljava/lang/String;
    //   7: iconst_4
    //   8: invokevirtual 216	java/lang/String:codePointAt	(I)I
    //   11: istore_2
    //   12: aload_0
    //   13: invokevirtual 203	android/content/Context:getApplicationInfo	()Landroid/content/pm/ApplicationInfo;
    //   16: getfield 208	android/content/pm/ApplicationInfo:targetSdkVersion	I
    //   19: istore_3
    //   20: aload_0
    //   21: invokevirtual 185	android/content/Context:getResources	()Landroid/content/res/Resources;
    //   24: ldc_w 329
    //   27: invokevirtual 189	android/content/res/Resources:getString	(I)Ljava/lang/String;
    //   30: iconst_0
    //   31: iconst_5
    //   32: invokevirtual 195	java/lang/String:substring	(II)Ljava/lang/String;
    //   35: iconst_1
    //   36: invokevirtual 216	java/lang/String:codePointAt	(I)I
    //   39: istore 4
    //   41: aload_1
    //   42: iload_2
    //   43: bipush 43
    //   45: iadd
    //   46: iload_3
    //   47: bipush 15
    //   49: isub
    //   50: bipush 10
    //   52: newarray char
    //   54: dup
    //   55: iconst_0
    //   56: ldc_w 330
    //   59: castore
    //   60: dup
    //   61: iconst_1
    //   62: ldc_w 331
    //   65: castore
    //   66: dup
    //   67: iconst_2
    //   68: ldc_w 332
    //   71: castore
    //   72: dup
    //   73: iconst_3
    //   74: ldc_w 333
    //   77: castore
    //   78: dup
    //   79: iconst_4
    //   80: ldc_w 334
    //   83: castore
    //   84: dup
    //   85: iconst_5
    //   86: ldc -37
    //   88: castore
    //   89: dup
    //   90: bipush 6
    //   92: ldc_w 335
    //   95: castore
    //   96: dup
    //   97: bipush 7
    //   99: ldc_w 336
    //   102: castore
    //   103: dup
    //   104: bipush 8
    //   106: ldc_w 336
    //   109: castore
    //   110: dup
    //   111: bipush 9
    //   113: ldc_w 334
    //   116: castore
    //   117: iload 4
    //   119: bipush 23
    //   121: isub
    //   122: iconst_1
    //   123: invokestatic 223	o/Km:ˏ	(II[CIZ)Ljava/lang/String;
    //   126: invokevirtual 226	java/lang/String:intern	()Ljava/lang/String;
    //   129: invokevirtual 340	java/lang/String:getBytes	(Ljava/lang/String;)[B
    //   132: astore_1
    //   133: aload_1
    //   134: arraylength
    //   135: newarray byte
    //   137: astore 5
    //   139: iconst_0
    //   140: istore_2
    //   141: goto +326 -> 467
    //   144: aload 5
    //   146: iload_2
    //   147: aload_1
    //   148: aload_1
    //   149: arraylength
    //   150: iload_2
    //   151: isub
    //   152: iconst_1
    //   153: isub
    //   154: baload
    //   155: getstatic 47	o/Km:ˊˊ	B
    //   158: ixor
    //   159: i2b
    //   160: bastore
    //   161: iload_2
    //   162: iconst_1
    //   163: iadd
    //   164: istore_2
    //   165: goto +150 -> 315
    //   168: aload 5
    //   170: iload_2
    //   171: aload_1
    //   172: aload_1
    //   173: arraylength
    //   174: iload_2
    //   175: imul
    //   176: iconst_1
    //   177: isub
    //   178: baload
    //   179: getstatic 47	o/Km:ˊˊ	B
    //   182: iand
    //   183: i2b
    //   184: bastore
    //   185: iload_2
    //   186: bipush 98
    //   188: iadd
    //   189: istore_2
    //   190: goto +125 -> 315
    //   193: astore_1
    //   194: new 342	java/lang/RuntimeException
    //   197: dup
    //   198: aload_1
    //   199: invokespecial 345	java/lang/RuntimeException:<init>	(Ljava/lang/Throwable;)V
    //   202: athrow
    //   203: iload_3
    //   204: lookupswitch	default:+28->232, 69:+114->318, 98:+78->282
    //   232: goto +50 -> 282
    //   235: astore_1
    //   236: aload_1
    //   237: athrow
    //   238: goto +9 -> 247
    //   241: bipush 69
    //   243: istore_3
    //   244: goto +192 -> 436
    //   247: getstatic 42	o/Km:ˊˋ	I
    //   250: istore_2
    //   251: iload_2
    //   252: bipush 35
    //   254: iadd
    //   255: istore_2
    //   256: iload_2
    //   257: sipush 128
    //   260: irem
    //   261: putstatic 40	o/Km:ˉ	I
    //   264: iload_2
    //   265: iconst_2
    //   266: irem
    //   267: ifeq +6 -> 273
    //   270: goto +163 -> 433
    //   273: goto -270 -> 3
    //   276: bipush 69
    //   278: istore_3
    //   279: goto -76 -> 203
    //   282: getstatic 40	o/Km:ˉ	I
    //   285: bipush 85
    //   287: iadd
    //   288: istore_3
    //   289: iload_3
    //   290: sipush 128
    //   293: irem
    //   294: putstatic 42	o/Km:ˊˋ	I
    //   297: iload_3
    //   298: iconst_2
    //   299: irem
    //   300: ifne +6 -> 306
    //   303: goto +6 -> 309
    //   306: goto -65 -> 241
    //   309: bipush 96
    //   311: istore_3
    //   312: goto +124 -> 436
    //   315: goto +152 -> 467
    //   318: aload_0
    //   319: invokevirtual 185	android/content/Context:getResources	()Landroid/content/res/Resources;
    //   322: ldc_w 346
    //   325: invokevirtual 189	android/content/res/Resources:getString	(I)Ljava/lang/String;
    //   328: iconst_0
    //   329: iconst_4
    //   330: invokevirtual 195	java/lang/String:substring	(II)Ljava/lang/String;
    //   333: iconst_1
    //   334: invokevirtual 216	java/lang/String:codePointAt	(I)I
    //   337: istore_2
    //   338: aload_0
    //   339: invokevirtual 185	android/content/Context:getResources	()Landroid/content/res/Resources;
    //   342: ldc_w 347
    //   345: invokevirtual 189	android/content/res/Resources:getString	(I)Ljava/lang/String;
    //   348: iconst_0
    //   349: iconst_5
    //   350: invokevirtual 195	java/lang/String:substring	(II)Ljava/lang/String;
    //   353: iconst_3
    //   354: invokevirtual 216	java/lang/String:codePointAt	(I)I
    //   357: istore_3
    //   358: aload_0
    //   359: invokevirtual 203	android/content/Context:getApplicationInfo	()Landroid/content/pm/ApplicationInfo;
    //   362: getfield 208	android/content/pm/ApplicationInfo:targetSdkVersion	I
    //   365: istore 4
    //   367: new 191	java/lang/String
    //   370: dup
    //   371: aload 5
    //   373: iload_2
    //   374: sipush 142
    //   377: iadd
    //   378: iload_3
    //   379: bipush 7
    //   381: isub
    //   382: iconst_5
    //   383: newarray char
    //   385: dup
    //   386: iconst_0
    //   387: ldc_w 348
    //   390: castore
    //   391: dup
    //   392: iconst_1
    //   393: ldc_w 349
    //   396: castore
    //   397: dup
    //   398: iconst_2
    //   399: ldc_w 350
    //   402: castore
    //   403: dup
    //   404: iconst_3
    //   405: ldc_w 351
    //   408: castore
    //   409: dup
    //   410: iconst_4
    //   411: ldc_w 352
    //   414: castore
    //   415: iload 4
    //   417: bipush 21
    //   419: isub
    //   420: iconst_0
    //   421: invokestatic 223	o/Km:ˏ	(II[CIZ)Ljava/lang/String;
    //   424: invokevirtual 226	java/lang/String:intern	()Ljava/lang/String;
    //   427: invokespecial 355	java/lang/String:<init>	([BLjava/lang/String;)V
    //   430: astore_1
    //   431: aload_1
    //   432: areturn
    //   433: goto -430 -> 3
    //   436: iload_3
    //   437: lookupswitch	default:+27->464, 69:+-293->144, 96:+-269->168
    //   464: goto -296 -> 168
    //   467: aload_1
    //   468: arraylength
    //   469: istore_3
    //   470: iload_2
    //   471: iload_3
    //   472: if_icmpge +6 -> 478
    //   475: goto +6 -> 481
    //   478: goto -202 -> 276
    //   481: bipush 98
    //   483: istore_3
    //   484: goto -281 -> 203
    // Local variable table:
    //   start	length	slot	name	signature
    //   0	487	0	this	Km
    //   0	487	1	paramString	String
    //   11	462	2	i	int
    //   19	465	3	j	int
    //   39	381	4	k	int
    //   137	235	5	arrayOfByte	byte[]
    // Exception table:
    //   from	to	target	type
    //   3	139	193	java/io/UnsupportedEncodingException
    //   144	161	193	java/io/UnsupportedEncodingException
    //   168	185	193	java/io/UnsupportedEncodingException
    //   318	431	193	java/io/UnsupportedEncodingException
    //   467	470	193	java/io/UnsupportedEncodingException
    //   247	251	235	java/lang/Exception
    //   256	264	235	java/lang/Exception
  }
  
  /* Error */
  private static String ˏ(int paramInt1, int paramInt2, char[] paramArrayOfChar, int paramInt3, boolean paramBoolean)
  {
    // Byte code:
    //   0: goto +264 -> 264
    //   3: iconst_0
    //   4: istore_0
    //   5: goto +418 -> 423
    //   8: iconst_1
    //   9: istore_3
    //   10: goto +451 -> 461
    //   13: aload_2
    //   14: iload_0
    //   15: aload 7
    //   17: iload_1
    //   18: iload_0
    //   19: isub
    //   20: iconst_1
    //   21: isub
    //   22: caload
    //   23: castore
    //   24: iload_0
    //   25: iconst_1
    //   26: iadd
    //   27: istore_3
    //   28: goto +209 -> 237
    //   31: iconst_1
    //   32: istore_0
    //   33: goto +390 -> 423
    //   36: aload 7
    //   38: iload 5
    //   40: iload_0
    //   41: aload_2
    //   42: iload 5
    //   44: caload
    //   45: iadd
    //   46: i2c
    //   47: castore
    //   48: aload 7
    //   50: iload 5
    //   52: aload 7
    //   54: iload 5
    //   56: caload
    //   57: getstatic 358	o/Km:ˋˊ	I
    //   60: isub
    //   61: i2c
    //   62: castore
    //   63: iload 5
    //   65: iconst_1
    //   66: iadd
    //   67: istore 6
    //   69: goto +324 -> 393
    //   72: goto +205 -> 277
    //   75: getstatic 40	o/Km:ˉ	I
    //   78: bipush 103
    //   80: iadd
    //   81: istore 6
    //   83: iload 6
    //   85: sipush 128
    //   88: irem
    //   89: putstatic 42	o/Km:ˊˋ	I
    //   92: iload 6
    //   94: iconst_2
    //   95: irem
    //   96: ifne +6 -> 102
    //   99: goto +87 -> 186
    //   102: goto -66 -> 36
    //   105: goto +250 -> 355
    //   108: aload 7
    //   110: astore_2
    //   111: iload_0
    //   112: tableswitch	default:+24->136, 0:+35->147, 1:+375->487
    //   136: aload 7
    //   138: astore_2
    //   139: goto +8 -> 147
    //   142: iconst_0
    //   143: istore_0
    //   144: goto -36 -> 108
    //   147: new 191	java/lang/String
    //   150: dup
    //   151: aload_2
    //   152: invokespecial 361	java/lang/String:<init>	([C)V
    //   155: areturn
    //   156: goto +121 -> 277
    //   159: iload_3
    //   160: istore_0
    //   161: goto +332 -> 493
    //   164: bipush 80
    //   166: istore 5
    //   168: goto +157 -> 325
    //   171: iload 5
    //   173: iload_1
    //   174: if_icmpge +6 -> 180
    //   177: goto -102 -> 75
    //   180: goto +9 -> 189
    //   183: astore_2
    //   184: aload_2
    //   185: athrow
    //   186: goto -150 -> 36
    //   189: iload_3
    //   190: ifle +6 -> 196
    //   193: goto +105 -> 298
    //   196: goto +81 -> 277
    //   199: iload_1
    //   200: newarray char
    //   202: astore 7
    //   204: iconst_0
    //   205: istore 5
    //   207: goto -36 -> 171
    //   210: getstatic 42	o/Km:ˊˋ	I
    //   213: bipush 67
    //   215: iadd
    //   216: istore_0
    //   217: iload_0
    //   218: sipush 128
    //   221: irem
    //   222: putstatic 40	o/Km:ˉ	I
    //   225: iload_0
    //   226: iconst_2
    //   227: irem
    //   228: ifeq +6 -> 234
    //   231: goto -75 -> 156
    //   234: goto -162 -> 72
    //   237: getstatic 42	o/Km:ˊˋ	I
    //   240: bipush 9
    //   242: iadd
    //   243: istore_0
    //   244: iload_0
    //   245: sipush 128
    //   248: irem
    //   249: putstatic 40	o/Km:ˉ	I
    //   252: iload_0
    //   253: iconst_2
    //   254: irem
    //   255: ifeq +6 -> 261
    //   258: goto -255 -> 3
    //   261: goto -230 -> 31
    //   264: goto -65 -> 199
    //   267: goto -120 -> 147
    //   270: iload 6
    //   272: istore 5
    //   274: goto -103 -> 171
    //   277: iload 4
    //   279: ifeq +6 -> 285
    //   282: goto +229 -> 511
    //   285: goto -143 -> 142
    //   288: iload_3
    //   289: istore_0
    //   290: goto +203 -> 493
    //   293: iconst_0
    //   294: istore_3
    //   295: goto +166 -> 461
    //   298: getstatic 42	o/Km:ˊˋ	I
    //   301: bipush 41
    //   303: iadd
    //   304: istore_0
    //   305: iload_0
    //   306: sipush 128
    //   309: irem
    //   310: putstatic 40	o/Km:ˉ	I
    //   313: iload_0
    //   314: iconst_2
    //   315: irem
    //   316: ifeq +6 -> 322
    //   319: goto -214 -> 105
    //   322: goto +33 -> 355
    //   325: iload 5
    //   327: lookupswitch	default:+25->352, 19:+177->504, 80:+-57->270
    //   352: goto +152 -> 504
    //   355: iload_1
    //   356: newarray char
    //   358: astore_2
    //   359: aload 7
    //   361: iconst_0
    //   362: aload_2
    //   363: iconst_0
    //   364: iload_1
    //   365: invokestatic 367	java/lang/System:arraycopy	(Ljava/lang/Object;ILjava/lang/Object;II)V
    //   368: aload_2
    //   369: iconst_0
    //   370: aload 7
    //   372: iload_1
    //   373: iload_3
    //   374: isub
    //   375: iload_3
    //   376: invokestatic 367	java/lang/System:arraycopy	(Ljava/lang/Object;ILjava/lang/Object;II)V
    //   379: aload_2
    //   380: iload_3
    //   381: aload 7
    //   383: iconst_0
    //   384: iload_1
    //   385: iload_3
    //   386: isub
    //   387: invokestatic 367	java/lang/System:arraycopy	(Ljava/lang/Object;ILjava/lang/Object;II)V
    //   390: goto -180 -> 210
    //   393: getstatic 40	o/Km:ˉ	I
    //   396: bipush 35
    //   398: iadd
    //   399: istore 5
    //   401: iload 5
    //   403: sipush 128
    //   406: irem
    //   407: putstatic 42	o/Km:ˊˋ	I
    //   410: iload 5
    //   412: iconst_2
    //   413: irem
    //   414: ifne +6 -> 420
    //   417: goto +34 -> 451
    //   420: goto -256 -> 164
    //   423: iload_0
    //   424: tableswitch	default:+24->448, 0:+-265->159, 1:+-136->288
    //   448: goto -160 -> 288
    //   451: bipush 19
    //   453: istore 5
    //   455: goto -130 -> 325
    //   458: astore_2
    //   459: aload_2
    //   460: athrow
    //   461: iload_3
    //   462: tableswitch	default:+22->484, 0:+-449->13, 1:+-195->267
    //   484: goto -217 -> 267
    //   487: iload_1
    //   488: newarray char
    //   490: astore_2
    //   491: iconst_0
    //   492: istore_0
    //   493: iload_0
    //   494: iload_1
    //   495: if_icmpge +6 -> 501
    //   498: goto -205 -> 293
    //   501: goto -493 -> 8
    //   504: iload 6
    //   506: istore 5
    //   508: goto -337 -> 171
    //   511: iconst_1
    //   512: istore_0
    //   513: goto -405 -> 108
    // Local variable table:
    //   start	length	slot	name	signature
    //   0	516	0	paramInt1	int
    //   0	516	1	paramInt2	int
    //   0	516	2	paramArrayOfChar	char[]
    //   0	516	3	paramInt3	int
    //   0	516	4	paramBoolean	boolean
    //   38	469	5	i	int
    //   67	438	6	j	int
    //   15	367	7	arrayOfChar	char[]
    // Exception table:
    //   from	to	target	type
    //   305	313	183	java/lang/Exception
    //   359	368	183	java/lang/Exception
    //   368	379	183	java/lang/Exception
    //   379	390	183	java/lang/Exception
    //   298	305	458	java/lang/Exception
    //   305	313	458	java/lang/Exception
  }
  
  /* Error */
  private void ˏ(String paramString)
  {
    // Byte code:
    //   0: goto +29 -> 29
    //   3: return
    //   4: getstatic 40	o/Km:ˉ	I
    //   7: bipush 81
    //   9: iadd
    //   10: istore_2
    //   11: iload_2
    //   12: sipush 128
    //   15: irem
    //   16: putstatic 42	o/Km:ˊˋ	I
    //   19: iload_2
    //   20: iconst_2
    //   21: irem
    //   22: ifne +6 -> 28
    //   25: goto -22 -> 3
    //   28: return
    //   29: goto +17 -> 46
    //   32: astore_1
    //   33: aload_1
    //   34: invokevirtual 278	java/lang/Throwable:getCause	()Ljava/lang/Throwable;
    //   37: astore_3
    //   38: aload_3
    //   39: ifnull +5 -> 44
    //   42: aload_3
    //   43: athrow
    //   44: aload_1
    //   45: athrow
    //   46: aload_0
    //   47: invokevirtual 212	android/content/Context:getPackageName	()Ljava/lang/String;
    //   50: iconst_1
    //   51: invokevirtual 216	java/lang/String:codePointAt	(I)I
    //   54: bipush 107
    //   56: isub
    //   57: aload_0
    //   58: invokevirtual 212	android/content/Context:getPackageName	()Ljava/lang/String;
    //   61: invokevirtual 199	java/lang/String:length	()I
    //   64: bipush 124
    //   66: iadd
    //   67: aload_0
    //   68: invokevirtual 212	android/content/Context:getPackageName	()Ljava/lang/String;
    //   71: iconst_5
    //   72: invokevirtual 216	java/lang/String:codePointAt	(I)I
    //   75: ldc_w 368
    //   78: iadd
    //   79: i2c
    //   80: invokestatic 287	o/O:ˋ	(IIC)Ljava/lang/Object;
    //   83: checkcast 289	java/lang/Class
    //   86: ldc_w 290
    //   89: aconst_null
    //   90: invokevirtual 294	java/lang/Class:getMethod	(Ljava/lang/String;[Ljava/lang/Class;)Ljava/lang/reflect/Method;
    //   93: aconst_null
    //   94: aconst_null
    //   95: invokevirtual 300	java/lang/reflect/Method:invoke	(Ljava/lang/Object;[Ljava/lang/Object;)Ljava/lang/Object;
    //   98: checkcast 302	o/It
    //   101: astore_3
    //   102: aload_3
    //   103: new 370	o/EB
    //   106: dup
    //   107: aload_1
    //   108: iconst_1
    //   109: invokespecial 373	o/EB:<init>	(Ljava/lang/String;Z)V
    //   112: invokeinterface 376 2 0
    //   117: new 13	o/Km$4
    //   120: dup
    //   121: aload_0
    //   122: aload_0
    //   123: invokespecial 377	o/Km$4:<init>	(Lo/Km;Landroid/content/Context;)V
    //   126: invokeinterface 313 2 0
    //   131: goto -127 -> 4
    // Local variable table:
    //   start	length	slot	name	signature
    //   0	134	0	this	Km
    //   0	134	1	paramString	String
    //   10	12	2	i	int
    //   37	66	3	localObject	Object
    // Exception table:
    //   from	to	target	type
    //   46	102	32	finally
  }
  
  /* Error */
  private void ˏ(List<Eu> paramList)
  {
    // Byte code:
    //   0: goto +133 -> 133
    //   3: aload_0
    //   4: getfield 135	o/Km:ʽॱ	Lo/KF;
    //   7: astore_3
    //   8: aload_3
    //   9: aload_1
    //   10: iconst_1
    //   11: invokevirtual 380	o/KF:ˏ	(Ljava/util/List;Z)V
    //   14: aload_0
    //   15: getfield 135	o/Km:ʽॱ	Lo/KF;
    //   18: astore_1
    //   19: new 382	o/Lc$ˊ
    //   22: dup
    //   23: aload_1
    //   24: invokespecial 385	o/Lc$ˊ:<init>	(Lo/n;)V
    //   27: astore_1
    //   28: aload_1
    //   29: invokevirtual 388	o/Lc$ˊ:ˋ	()Lo/Lc;
    //   32: astore_1
    //   33: aload_0
    //   34: aload_1
    //   35: putfield 390	o/Km:ʼॱ	Lo/Lc;
    //   38: aload_0
    //   39: getfield 64	o/Km:ॱˊ	Landroid/databinding/ViewDataBinding;
    //   42: checkcast 104	o/JF
    //   45: getfield 138	o/JF:ˊ	Lo/IY;
    //   48: iconst_1
    //   49: aload_0
    //   50: getfield 390	o/Km:ʼॱ	Lo/Lc;
    //   53: invokevirtual 394	o/IY:setPageTransformer	(ZLo/ڏ$aux;)V
    //   56: aload_0
    //   57: getfield 64	o/Km:ॱˊ	Landroid/databinding/ViewDataBinding;
    //   60: checkcast 104	o/JF
    //   63: getfield 138	o/JF:ˊ	Lo/IY;
    //   66: aload_0
    //   67: getfield 390	o/Km:ʼॱ	Lo/Lc;
    //   70: invokevirtual 254	o/IY:ˎ	(Lo/ڏ$ˏ;)V
    //   73: aload_0
    //   74: getfield 64	o/Km:ॱˊ	Landroid/databinding/ViewDataBinding;
    //   77: checkcast 104	o/JF
    //   80: getfield 138	o/JF:ˊ	Lo/IY;
    //   83: iconst_0
    //   84: iconst_1
    //   85: invokevirtual 398	o/IY:setCurrentItem	(IZ)V
    //   88: aload_0
    //   89: getfield 64	o/Km:ॱˊ	Landroid/databinding/ViewDataBinding;
    //   92: checkcast 104	o/JF
    //   95: getfield 148	o/JF:ͺ	Lo/IX;
    //   98: aload_0
    //   99: getfield 64	o/Km:ॱˊ	Landroid/databinding/ViewDataBinding;
    //   102: checkcast 104	o/JF
    //   105: getfield 138	o/JF:ˊ	Lo/IY;
    //   108: invokevirtual 401	o/IX:setupWithViewPager	(Lo/ڏ;)V
    //   111: aload_0
    //   112: getfield 64	o/Km:ॱˊ	Landroid/databinding/ViewDataBinding;
    //   115: checkcast 104	o/JF
    //   118: getfield 148	o/JF:ͺ	Lo/IX;
    //   121: invokevirtual 403	o/IX:ʻ	()V
    //   124: goto +15 -> 139
    //   127: bipush 55
    //   129: istore_2
    //   130: goto +54 -> 184
    //   133: goto -130 -> 3
    //   136: astore_1
    //   137: aload_1
    //   138: athrow
    //   139: getstatic 42	o/Km:ˊˋ	I
    //   142: bipush 59
    //   144: iadd
    //   145: istore_2
    //   146: iload_2
    //   147: sipush 128
    //   150: irem
    //   151: putstatic 40	o/Km:ˉ	I
    //   154: iload_2
    //   155: iconst_2
    //   156: irem
    //   157: ifeq +6 -> 163
    //   160: goto +6 -> 166
    //   163: goto -36 -> 127
    //   166: bipush 53
    //   168: istore_2
    //   169: goto +15 -> 184
    //   172: astore_1
    //   173: aload_1
    //   174: athrow
    //   175: new 59	java/lang/NullPointerException
    //   178: dup
    //   179: invokespecial 60	java/lang/NullPointerException:<init>	()V
    //   182: athrow
    //   183: return
    //   184: iload_2
    //   185: lookupswitch	default:+27->212, 53:+-10->175, 55:+-2->183
    //   212: return
    // Local variable table:
    //   start	length	slot	name	signature
    //   0	213	0	this	Km
    //   0	213	1	paramList	List<Eu>
    //   129	56	2	i	int
    //   7	2	3	localKF	KF
    // Exception table:
    //   from	to	target	type
    //   3	8	136	java/lang/Exception
    //   8	14	136	java/lang/Exception
    //   14	19	136	java/lang/Exception
    //   19	28	136	java/lang/Exception
    //   28	33	136	java/lang/Exception
    //   33	124	136	java/lang/Exception
    //   14	19	172	java/lang/Exception
  }
  
  static void ॱˋ()
  {
    ˋˊ = 100;
  }
  
  /* Error */
  public Resources getResources()
  {
    // Byte code:
    //   0: goto +123 -> 123
    //   3: aload_0
    //   4: invokespecial 417	o/IB:getResources	()Landroid/content/res/Resources;
    //   7: invokestatic 422	o/oH:ˊ	(Landroid/content/res/Resources;)Landroid/content/res/Resources;
    //   10: astore_2
    //   11: goto +8 -> 19
    //   14: iconst_0
    //   15: istore_1
    //   16: goto +128 -> 144
    //   19: getstatic 40	o/Km:ˉ	I
    //   22: bipush 17
    //   24: iadd
    //   25: istore_1
    //   26: iload_1
    //   27: sipush 128
    //   30: irem
    //   31: putstatic 42	o/Km:ˊˋ	I
    //   34: iload_1
    //   35: iconst_2
    //   36: irem
    //   37: ifne +6 -> 43
    //   40: goto +44 -> 84
    //   43: goto +47 -> 90
    //   46: iconst_1
    //   47: istore_1
    //   48: goto +96 -> 144
    //   51: astore_2
    //   52: aload_2
    //   53: athrow
    //   54: getstatic 42	o/Km:ˊˋ	I
    //   57: bipush 55
    //   59: iadd
    //   60: istore_1
    //   61: iload_1
    //   62: sipush 128
    //   65: irem
    //   66: putstatic 40	o/Km:ˉ	I
    //   69: iload_1
    //   70: iconst_2
    //   71: irem
    //   72: ifeq +6 -> 78
    //   75: goto -29 -> 46
    //   78: goto -64 -> 14
    //   81: astore_2
    //   82: aload_2
    //   83: athrow
    //   84: bipush 8
    //   86: istore_1
    //   87: goto +6 -> 93
    //   90: bipush 42
    //   92: istore_1
    //   93: iload_1
    //   94: lookupswitch	default:+26->120, 8:+77->171, 42:+48->142
    //   120: goto +51 -> 171
    //   123: goto -69 -> 54
    //   126: aload_0
    //   127: invokespecial 417	o/IB:getResources	()Landroid/content/res/Resources;
    //   130: invokestatic 422	o/oH:ˊ	(Landroid/content/res/Resources;)Landroid/content/res/Resources;
    //   133: astore_2
    //   134: bipush 63
    //   136: iconst_0
    //   137: idiv
    //   138: istore_1
    //   139: goto -120 -> 19
    //   142: aload_2
    //   143: areturn
    //   144: iload_1
    //   145: tableswitch	default:+23->168, 0:+-142->3, 1:+-19->126
    //   168: goto -42 -> 126
    //   171: aconst_null
    //   172: arraylength
    //   173: istore_1
    //   174: aload_2
    //   175: areturn
    // Local variable table:
    //   start	length	slot	name	signature
    //   0	176	0	this	Km
    //   15	159	1	i	int
    //   10	1	2	localResources1	Resources
    //   51	2	2	localException1	Exception
    //   81	2	2	localException2	Exception
    //   133	42	2	localResources2	Resources
    // Exception table:
    //   from	to	target	type
    //   61	69	51	java/lang/Exception
    //   54	61	81	java/lang/Exception
    //   61	69	81	java/lang/Exception
  }
  
  /* Error */
  public void onActivityResult(int paramInt1, int paramInt2, android.content.Intent paramIntent)
  {
    // Byte code:
    //   0: goto +173 -> 173
    //   3: return
    //   4: astore_3
    //   5: aload_3
    //   6: athrow
    //   7: iconst_0
    //   8: istore_1
    //   9: goto +97 -> 106
    //   12: aload_0
    //   13: iload_1
    //   14: iload_2
    //   15: aload_3
    //   16: invokespecial 426	o/IB:onActivityResult	(IILandroid/content/Intent;)V
    //   19: iload_1
    //   20: lookupswitch	default:+20->40, 13:+75->95
    //   40: return
    //   41: goto +90 -> 131
    //   44: aload_0
    //   45: iload_2
    //   46: invokevirtual 428	o/Km:ॱ	(I)V
    //   49: new 59	java/lang/NullPointerException
    //   52: dup
    //   53: invokespecial 60	java/lang/NullPointerException:<init>	()V
    //   56: athrow
    //   57: bipush 64
    //   59: istore_1
    //   60: goto +116 -> 176
    //   63: getstatic 42	o/Km:ˊˋ	I
    //   66: bipush 33
    //   68: iadd
    //   69: istore_1
    //   70: iload_1
    //   71: sipush 128
    //   74: irem
    //   75: putstatic 40	o/Km:ˉ	I
    //   78: iload_1
    //   79: iconst_2
    //   80: irem
    //   81: ifeq +6 -> 87
    //   84: goto -43 -> 41
    //   87: goto +44 -> 131
    //   90: iconst_1
    //   91: istore_1
    //   92: goto +14 -> 106
    //   95: iload_2
    //   96: iconst_m1
    //   97: if_icmpne +6 -> 103
    //   100: goto -10 -> 90
    //   103: goto -96 -> 7
    //   106: iload_1
    //   107: tableswitch	default:+21->128, 0:+-104->3, 1:+31->138
    //   128: goto +10 -> 138
    //   131: return
    //   132: bipush 6
    //   134: istore_1
    //   135: goto +41 -> 176
    //   138: getstatic 40	o/Km:ˉ	I
    //   141: bipush 47
    //   143: iadd
    //   144: istore_1
    //   145: iload_1
    //   146: sipush 128
    //   149: irem
    //   150: putstatic 42	o/Km:ˊˋ	I
    //   153: iload_1
    //   154: iconst_2
    //   155: irem
    //   156: ifne +6 -> 162
    //   159: goto -27 -> 132
    //   162: goto -105 -> 57
    //   165: aload_0
    //   166: iload_2
    //   167: invokevirtual 428	o/Km:ॱ	(I)V
    //   170: goto -107 -> 63
    //   173: goto -161 -> 12
    //   176: iload_1
    //   177: lookupswitch	default:+27->204, 6:+-133->44, 64:+-12->165
    //   204: goto -160 -> 44
    // Local variable table:
    //   start	length	slot	name	signature
    //   0	207	0	this	Km
    //   0	207	1	paramInt1	int
    //   0	207	2	paramInt2	int
    //   0	207	3	paramIntent	android.content.Intent
    // Exception table:
    //   from	to	target	type
    //   165	170	4	java/lang/Exception
  }
  
  public void onConfirmClick(View paramView)
  {
    break label71;
    label6:
    int i = ˊˋ + 69;
    ˉ = i % 128;
    if (i % 2 != 0) {
      return;
    }
    return;
    i = 1;
    break label46;
    ˋˊ();
    throw new NullPointerException();
    for (;;)
    {
      switch (i)
      {
      case 1: 
      default: 
        break label98;
        i = ˊˋ + 125;
        ˉ = i % 128;
        if (i % 2 != 0) {
          break;
        }
        break;
      case 0: 
        label46:
        label71:
        label98:
        ˋˊ();
        break label6;
        i = 0;
      }
    }
  }
  
  /* Error */
  public void onCreate(android.os.Bundle paramBundle)
  {
    // Byte code:
    //   0: goto +842 -> 842
    //   3: bipush 74
    //   5: istore_2
    //   6: goto +849 -> 855
    //   9: goto +20 -> 29
    //   12: astore_1
    //   13: aload_1
    //   14: invokevirtual 278	java/lang/Throwable:getCause	()Ljava/lang/Throwable;
    //   17: astore 4
    //   19: aload 4
    //   21: ifnull +6 -> 27
    //   24: aload 4
    //   26: athrow
    //   27: aload_1
    //   28: athrow
    //   29: aload_0
    //   30: invokevirtual 185	android/content/Context:getResources	()Landroid/content/res/Resources;
    //   33: ldc_w 435
    //   36: invokevirtual 189	android/content/res/Resources:getString	(I)Ljava/lang/String;
    //   39: iconst_0
    //   40: iconst_5
    //   41: invokevirtual 195	java/lang/String:substring	(II)Ljava/lang/String;
    //   44: invokevirtual 199	java/lang/String:length	()I
    //   47: iconst_1
    //   48: isub
    //   49: aload_0
    //   50: invokevirtual 203	android/content/Context:getApplicationInfo	()Landroid/content/pm/ApplicationInfo;
    //   53: getfield 208	android/content/pm/ApplicationInfo:targetSdkVersion	I
    //   56: sipush 388
    //   59: iadd
    //   60: aload_0
    //   61: invokevirtual 203	android/content/Context:getApplicationInfo	()Landroid/content/pm/ApplicationInfo;
    //   64: getfield 208	android/content/pm/ApplicationInfo:targetSdkVersion	I
    //   67: sipush 30228
    //   70: iadd
    //   71: i2c
    //   72: invokestatic 287	o/O:ˋ	(IIC)Ljava/lang/Object;
    //   75: checkcast 289	java/lang/Class
    //   78: ldc_w 436
    //   81: aconst_null
    //   82: invokevirtual 294	java/lang/Class:getMethod	(Ljava/lang/String;[Ljava/lang/Class;)Ljava/lang/reflect/Method;
    //   85: aconst_null
    //   86: aconst_null
    //   87: invokevirtual 300	java/lang/reflect/Method:invoke	(Ljava/lang/Object;[Ljava/lang/Object;)Ljava/lang/Object;
    //   90: astore_1
    //   91: ldc 2
    //   93: invokevirtual 439	java/lang/Class:getName	()Ljava/lang/String;
    //   96: astore 4
    //   98: goto +20 -> 118
    //   101: astore_1
    //   102: aload_1
    //   103: invokevirtual 278	java/lang/Throwable:getCause	()Ljava/lang/Throwable;
    //   106: astore 4
    //   108: aload 4
    //   110: ifnull +6 -> 116
    //   113: aload 4
    //   115: athrow
    //   116: aload_1
    //   117: athrow
    //   118: aload_0
    //   119: invokevirtual 185	android/content/Context:getResources	()Landroid/content/res/Resources;
    //   122: ldc_w 440
    //   125: invokevirtual 189	android/content/res/Resources:getString	(I)Ljava/lang/String;
    //   128: iconst_0
    //   129: bipush 10
    //   131: invokevirtual 195	java/lang/String:substring	(II)Ljava/lang/String;
    //   134: iconst_4
    //   135: invokevirtual 216	java/lang/String:codePointAt	(I)I
    //   138: sipush 229
    //   141: isub
    //   142: aload_0
    //   143: invokevirtual 185	android/content/Context:getResources	()Landroid/content/res/Resources;
    //   146: ldc_w 441
    //   149: invokevirtual 189	android/content/res/Resources:getString	(I)Ljava/lang/String;
    //   152: iconst_0
    //   153: iconst_4
    //   154: invokevirtual 195	java/lang/String:substring	(II)Ljava/lang/String;
    //   157: invokevirtual 199	java/lang/String:length	()I
    //   160: sipush 409
    //   163: iadd
    //   164: aload_0
    //   165: invokevirtual 185	android/content/Context:getResources	()Landroid/content/res/Resources;
    //   168: ldc_w 442
    //   171: invokevirtual 189	android/content/res/Resources:getString	(I)Ljava/lang/String;
    //   174: iconst_0
    //   175: iconst_4
    //   176: invokevirtual 195	java/lang/String:substring	(II)Ljava/lang/String;
    //   179: iconst_1
    //   180: invokevirtual 216	java/lang/String:codePointAt	(I)I
    //   183: sipush 30227
    //   186: iadd
    //   187: i2c
    //   188: invokestatic 287	o/O:ˋ	(IIC)Ljava/lang/Object;
    //   191: checkcast 289	java/lang/Class
    //   194: ldc_w 443
    //   197: iconst_1
    //   198: anewarray 289	java/lang/Class
    //   201: dup
    //   202: iconst_0
    //   203: ldc -65
    //   205: aastore
    //   206: invokevirtual 294	java/lang/Class:getMethod	(Ljava/lang/String;[Ljava/lang/Class;)Ljava/lang/reflect/Method;
    //   209: aload_1
    //   210: iconst_1
    //   211: anewarray 445	java/lang/Object
    //   214: dup
    //   215: iconst_0
    //   216: aload 4
    //   218: aastore
    //   219: invokevirtual 300	java/lang/reflect/Method:invoke	(Ljava/lang/Object;[Ljava/lang/Object;)Ljava/lang/Object;
    //   222: checkcast 447	java/lang/Boolean
    //   225: invokevirtual 450	java/lang/Boolean:booleanValue	()Z
    //   228: istore_3
    //   229: iload_3
    //   230: ifne +6 -> 236
    //   233: goto +601 -> 834
    //   236: goto +590 -> 826
    //   239: getstatic 40	o/Km:ˉ	I
    //   242: bipush 103
    //   244: iadd
    //   245: istore_2
    //   246: iload_2
    //   247: sipush 128
    //   250: irem
    //   251: putstatic 42	o/Km:ˊˋ	I
    //   254: iload_2
    //   255: iconst_2
    //   256: irem
    //   257: ifne +6 -> 263
    //   260: goto +6 -> 266
    //   263: goto +254 -> 517
    //   266: aload_0
    //   267: aload_1
    //   268: invokespecial 452	o/IB:onCreate	(Landroid/os/Bundle;)V
    //   271: aload_0
    //   272: getfield 64	o/Km:ॱˊ	Landroid/databinding/ViewDataBinding;
    //   275: astore_1
    //   276: aload_1
    //   277: checkcast 104	o/JF
    //   280: astore_1
    //   281: aload_1
    //   282: getfield 455	o/JF:ॱˎ	Lo/у;
    //   285: astore_1
    //   286: aload_0
    //   287: aload_1
    //   288: invokevirtual 458	o/Km:ˊ	(Lo/у;)V
    //   291: goto +20 -> 311
    //   294: astore_1
    //   295: aload_1
    //   296: invokevirtual 278	java/lang/Throwable:getCause	()Ljava/lang/Throwable;
    //   299: astore 4
    //   301: aload 4
    //   303: ifnull +6 -> 309
    //   306: aload 4
    //   308: athrow
    //   309: aload_1
    //   310: athrow
    //   311: aload_0
    //   312: invokevirtual 185	android/content/Context:getResources	()Landroid/content/res/Resources;
    //   315: ldc_w 459
    //   318: invokevirtual 189	android/content/res/Resources:getString	(I)Ljava/lang/String;
    //   321: iconst_0
    //   322: iconst_4
    //   323: invokevirtual 195	java/lang/String:substring	(II)Ljava/lang/String;
    //   326: invokevirtual 199	java/lang/String:length	()I
    //   329: iconst_0
    //   330: iadd
    //   331: aload_0
    //   332: invokevirtual 203	android/content/Context:getApplicationInfo	()Landroid/content/pm/ApplicationInfo;
    //   335: getfield 208	android/content/pm/ApplicationInfo:targetSdkVersion	I
    //   338: sipush 388
    //   341: iadd
    //   342: aload_0
    //   343: invokevirtual 185	android/content/Context:getResources	()Landroid/content/res/Resources;
    //   346: ldc_w 460
    //   349: invokevirtual 189	android/content/res/Resources:getString	(I)Ljava/lang/String;
    //   352: iconst_0
    //   353: bipush 15
    //   355: invokevirtual 195	java/lang/String:substring	(II)Ljava/lang/String;
    //   358: iconst_5
    //   359: invokevirtual 216	java/lang/String:codePointAt	(I)I
    //   362: sipush 30005
    //   365: iadd
    //   366: i2c
    //   367: invokestatic 287	o/O:ˋ	(IIC)Ljava/lang/Object;
    //   370: checkcast 289	java/lang/Class
    //   373: ldc_w 436
    //   376: aconst_null
    //   377: invokevirtual 294	java/lang/Class:getMethod	(Ljava/lang/String;[Ljava/lang/Class;)Ljava/lang/reflect/Method;
    //   380: aconst_null
    //   381: aconst_null
    //   382: invokevirtual 300	java/lang/reflect/Method:invoke	(Ljava/lang/Object;[Ljava/lang/Object;)Ljava/lang/Object;
    //   385: astore_1
    //   386: goto +20 -> 406
    //   389: astore_1
    //   390: aload_1
    //   391: invokevirtual 278	java/lang/Throwable:getCause	()Ljava/lang/Throwable;
    //   394: astore 4
    //   396: aload 4
    //   398: ifnull +6 -> 404
    //   401: aload 4
    //   403: athrow
    //   404: aload_1
    //   405: athrow
    //   406: aload_0
    //   407: invokevirtual 185	android/content/Context:getResources	()Landroid/content/res/Resources;
    //   410: ldc_w 461
    //   413: invokevirtual 189	android/content/res/Resources:getString	(I)Ljava/lang/String;
    //   416: iconst_0
    //   417: iconst_4
    //   418: invokevirtual 195	java/lang/String:substring	(II)Ljava/lang/String;
    //   421: invokevirtual 199	java/lang/String:length	()I
    //   424: iconst_0
    //   425: iadd
    //   426: aload_0
    //   427: invokevirtual 185	android/content/Context:getResources	()Landroid/content/res/Resources;
    //   430: ldc_w 462
    //   433: invokevirtual 189	android/content/res/Resources:getString	(I)Ljava/lang/String;
    //   436: iconst_0
    //   437: iconst_5
    //   438: invokevirtual 195	java/lang/String:substring	(II)Ljava/lang/String;
    //   441: iconst_3
    //   442: invokevirtual 216	java/lang/String:codePointAt	(I)I
    //   445: sipush 401
    //   448: iadd
    //   449: aload_0
    //   450: invokevirtual 185	android/content/Context:getResources	()Landroid/content/res/Resources;
    //   453: ldc_w 442
    //   456: invokevirtual 189	android/content/res/Resources:getString	(I)Ljava/lang/String;
    //   459: iconst_0
    //   460: iconst_4
    //   461: invokevirtual 195	java/lang/String:substring	(II)Ljava/lang/String;
    //   464: invokevirtual 199	java/lang/String:length	()I
    //   467: sipush 30249
    //   470: iadd
    //   471: i2c
    //   472: invokestatic 287	o/O:ˋ	(IIC)Ljava/lang/Object;
    //   475: checkcast 289	java/lang/Class
    //   478: ldc_w 463
    //   481: aconst_null
    //   482: invokevirtual 294	java/lang/Class:getMethod	(Ljava/lang/String;[Ljava/lang/Class;)Ljava/lang/reflect/Method;
    //   485: aload_1
    //   486: aconst_null
    //   487: invokevirtual 300	java/lang/reflect/Method:invoke	(Ljava/lang/Object;[Ljava/lang/Object;)Ljava/lang/Object;
    //   490: checkcast 447	java/lang/Boolean
    //   493: invokevirtual 450	java/lang/Boolean:booleanValue	()Z
    //   496: istore_3
    //   497: aconst_null
    //   498: arraylength
    //   499: istore_2
    //   500: iload_3
    //   501: ifeq +6 -> 507
    //   504: goto +253 -> 757
    //   507: goto -504 -> 3
    //   510: aconst_null
    //   511: arraylength
    //   512: istore_2
    //   513: return
    //   514: goto +240 -> 754
    //   517: aload_0
    //   518: aload_1
    //   519: invokespecial 452	o/IB:onCreate	(Landroid/os/Bundle;)V
    //   522: aload_0
    //   523: aload_0
    //   524: getfield 64	o/Km:ॱˊ	Landroid/databinding/ViewDataBinding;
    //   527: checkcast 104	o/JF
    //   530: getfield 455	o/JF:ॱˎ	Lo/у;
    //   533: invokevirtual 458	o/Km:ˊ	(Lo/у;)V
    //   536: goto +20 -> 556
    //   539: astore_1
    //   540: aload_1
    //   541: invokevirtual 278	java/lang/Throwable:getCause	()Ljava/lang/Throwable;
    //   544: astore 4
    //   546: aload 4
    //   548: ifnull +6 -> 554
    //   551: aload 4
    //   553: athrow
    //   554: aload_1
    //   555: athrow
    //   556: aload_0
    //   557: invokevirtual 212	android/content/Context:getPackageName	()Ljava/lang/String;
    //   560: invokevirtual 199	java/lang/String:length	()I
    //   563: bipush 7
    //   565: isub
    //   566: aload_0
    //   567: invokevirtual 185	android/content/Context:getResources	()Landroid/content/res/Resources;
    //   570: ldc_w 464
    //   573: invokevirtual 189	android/content/res/Resources:getString	(I)Ljava/lang/String;
    //   576: iconst_0
    //   577: iconst_4
    //   578: invokevirtual 195	java/lang/String:substring	(II)Ljava/lang/String;
    //   581: invokevirtual 199	java/lang/String:length	()I
    //   584: sipush 409
    //   587: iadd
    //   588: aload_0
    //   589: invokevirtual 212	android/content/Context:getPackageName	()Ljava/lang/String;
    //   592: iconst_3
    //   593: invokevirtual 216	java/lang/String:codePointAt	(I)I
    //   596: sipush 30155
    //   599: iadd
    //   600: i2c
    //   601: invokestatic 287	o/O:ˋ	(IIC)Ljava/lang/Object;
    //   604: checkcast 289	java/lang/Class
    //   607: ldc_w 436
    //   610: aconst_null
    //   611: invokevirtual 294	java/lang/Class:getMethod	(Ljava/lang/String;[Ljava/lang/Class;)Ljava/lang/reflect/Method;
    //   614: aconst_null
    //   615: aconst_null
    //   616: invokevirtual 300	java/lang/reflect/Method:invoke	(Ljava/lang/Object;[Ljava/lang/Object;)Ljava/lang/Object;
    //   619: astore_1
    //   620: goto +20 -> 640
    //   623: astore_1
    //   624: aload_1
    //   625: invokevirtual 278	java/lang/Throwable:getCause	()Ljava/lang/Throwable;
    //   628: astore 4
    //   630: aload 4
    //   632: ifnull +6 -> 638
    //   635: aload 4
    //   637: athrow
    //   638: aload_1
    //   639: athrow
    //   640: aload_0
    //   641: invokevirtual 185	android/content/Context:getResources	()Landroid/content/res/Resources;
    //   644: ldc_w 465
    //   647: invokevirtual 189	android/content/res/Resources:getString	(I)Ljava/lang/String;
    //   650: iconst_0
    //   651: iconst_4
    //   652: invokevirtual 195	java/lang/String:substring	(II)Ljava/lang/String;
    //   655: invokevirtual 199	java/lang/String:length	()I
    //   658: iconst_0
    //   659: iadd
    //   660: aload_0
    //   661: invokevirtual 185	android/content/Context:getResources	()Landroid/content/res/Resources;
    //   664: ldc_w 466
    //   667: invokevirtual 189	android/content/res/Resources:getString	(I)Ljava/lang/String;
    //   670: iconst_0
    //   671: iconst_4
    //   672: invokevirtual 195	java/lang/String:substring	(II)Ljava/lang/String;
    //   675: invokevirtual 199	java/lang/String:length	()I
    //   678: sipush 409
    //   681: iadd
    //   682: aload_0
    //   683: invokevirtual 203	android/content/Context:getApplicationInfo	()Landroid/content/pm/ApplicationInfo;
    //   686: getfield 208	android/content/pm/ApplicationInfo:targetSdkVersion	I
    //   689: sipush 30228
    //   692: iadd
    //   693: i2c
    //   694: invokestatic 287	o/O:ˋ	(IIC)Ljava/lang/Object;
    //   697: checkcast 289	java/lang/Class
    //   700: ldc_w 463
    //   703: aconst_null
    //   704: invokevirtual 294	java/lang/Class:getMethod	(Ljava/lang/String;[Ljava/lang/Class;)Ljava/lang/reflect/Method;
    //   707: aload_1
    //   708: aconst_null
    //   709: invokevirtual 300	java/lang/reflect/Method:invoke	(Ljava/lang/Object;[Ljava/lang/Object;)Ljava/lang/Object;
    //   712: checkcast 447	java/lang/Boolean
    //   715: invokevirtual 450	java/lang/Boolean:booleanValue	()Z
    //   718: istore_3
    //   719: iload_3
    //   720: ifeq +6 -> 726
    //   723: goto +164 -> 887
    //   726: goto +183 -> 909
    //   729: getstatic 40	o/Km:ˉ	I
    //   732: bipush 51
    //   734: iadd
    //   735: istore_2
    //   736: iload_2
    //   737: sipush 128
    //   740: irem
    //   741: putstatic 42	o/Km:ˊˋ	I
    //   744: iload_2
    //   745: iconst_2
    //   746: irem
    //   747: ifne +6 -> 753
    //   750: goto -240 -> 510
    //   753: return
    //   754: goto -25 -> 729
    //   757: bipush 73
    //   759: istore_2
    //   760: goto +95 -> 855
    //   763: iload_2
    //   764: tableswitch	default:+24->788, 0:+132->896, 1:+137->901
    //   788: goto +108 -> 896
    //   791: iload_2
    //   792: lookupswitch	default:+28->820, 22:+-783->9, 65:+53->845
    //   820: goto -811 -> 9
    //   823: goto -69 -> 754
    //   826: iconst_1
    //   827: istore_2
    //   828: goto -65 -> 763
    //   831: astore_1
    //   832: aload_1
    //   833: athrow
    //   834: iconst_0
    //   835: istore_2
    //   836: goto -73 -> 763
    //   839: goto +103 -> 942
    //   842: goto -603 -> 239
    //   845: aload_0
    //   846: invokestatic 472	java/util/Collections:emptyList	()Ljava/util/List;
    //   849: invokespecial 410	o/Km:ˊ	(Ljava/util/List;)V
    //   852: goto +63 -> 915
    //   855: iload_2
    //   856: lookupswitch	default:+28->884, 73:+-847->9, 74:+-11->845
    //   884: goto -39 -> 845
    //   887: bipush 22
    //   889: istore_2
    //   890: goto -99 -> 791
    //   893: goto -70 -> 823
    //   896: iconst_1
    //   897: istore_3
    //   898: goto -59 -> 839
    //   901: iconst_0
    //   902: istore_3
    //   903: goto +39 -> 942
    //   906: astore_1
    //   907: aload_1
    //   908: athrow
    //   909: bipush 65
    //   911: istore_2
    //   912: goto -121 -> 791
    //   915: getstatic 42	o/Km:ˊˋ	I
    //   918: bipush 45
    //   920: iadd
    //   921: istore_2
    //   922: iload_2
    //   923: sipush 128
    //   926: irem
    //   927: putstatic 40	o/Km:ˉ	I
    //   930: iload_2
    //   931: iconst_2
    //   932: irem
    //   933: ifeq +6 -> 939
    //   936: goto -43 -> 893
    //   939: goto -116 -> 823
    //   942: aload_0
    //   943: iload_3
    //   944: putfield 53	o/Km:ʿ	Z
    //   947: aload_0
    //   948: invokespecial 474	o/Km:ʾ	()V
    //   951: goto -437 -> 514
    // Local variable table:
    //   start	length	slot	name	signature
    //   0	954	0	this	Km
    //   0	954	1	paramBundle	android.os.Bundle
    //   5	928	2	i	int
    //   228	716	3	bool	boolean
    //   17	619	4	localObject	Object
    // Exception table:
    //   from	to	target	type
    //   29	91	12	finally
    //   118	229	101	finally
    //   311	386	294	finally
    //   406	497	389	finally
    //   556	620	539	finally
    //   640	719	623	finally
    //   239	246	831	java/lang/Exception
    //   246	254	831	java/lang/Exception
    //   271	276	906	java/lang/Exception
    //   276	281	906	java/lang/Exception
    //   281	286	906	java/lang/Exception
    //   286	291	906	java/lang/Exception
    //   295	301	906	java/lang/Exception
    //   306	309	906	java/lang/Exception
    //   309	311	906	java/lang/Exception
    //   390	396	906	java/lang/Exception
    //   401	404	906	java/lang/Exception
    //   404	406	906	java/lang/Exception
    //   497	500	906	java/lang/Exception
  }
  
  public void onEmptyPaymentCardClicked(View paramView)
  {
    for (;;)
    {
      i = ˊˋ + 1;
      ˉ = i % 128;
      if (i % 2 != 0) {
        break;
      }
      break;
    }
    ˋˊ();
    int i = ˉ + 103;
    ˊˋ = i % 128;
    if (i % 2 == 0) {}
  }
  
  public void ˋ(ز paramز)
  {
    for (;;)
    {
      int i = ˉ + 3;
      ˊˋ = i % 128;
      if (i % 2 != 0) {}
      for (;;)
      {
        super.ˋ(paramز);
        paramز.ॱ(true);
        paramز.ˏ(true);
        break label88;
        i = 87;
        break;
        return;
      }
      for (;;)
      {
        switch (i)
        {
        }
        throw new NullPointerException();
        label88:
        i = ˉ + 55;
        ˊˋ = i % 128;
        if (i % 2 != 0) {
          break;
        }
        i = 82;
      }
    }
  }
  
  public int ˎ()
  {
    int j;
    for (;;)
    {
      int i = ˊˋ + 1;
      ˉ = i % 128;
      if (i % 2 != 0) {
        break;
      }
      return j;
      for (;;)
      {
        break;
        i = ˊˋ + 23;
        ˉ = i % 128;
        if (i % 2 == 0) {
          break;
        }
      }
      j = Jy.ˊ.activity_card_presentment;
    }
    return j;
  }
  
  @zA(ˎ=ThreadMode.MAIN)
  public void ॱ(Eb paramEb)
  {
    int i;
    for (;;)
    {
      i = ˉ + 73;
      ˊˋ = i % 128;
      if (i % 2 == 0) {
        break label108;
      }
      break;
      i = 0;
      break label50;
      i = 1;
      break label50;
    }
    label50:
    label108:
    for (;;)
    {
      ˋˊ();
      switch (i)
      {
      case 1: 
      default: 
        return;
        i = ˊˋ + 95;
        ˉ = i % 128;
        if (i % 2 != 0) {
          break;
        }
        break;
      case 0: 
        throw new NullPointerException();
      }
    }
  }
  
  class ˊ
    implements View.OnClickListener, ڏ.ˏ
  {
    private static byte ˊ;
    private static int ˋ;
    private static int ˎ;
    private static char[] ˏ;
    
    static
    {
      for (;;)
      {
        int i = ˋ + 33;
        ˎ = i % 128;
        if (i % 2 != 0) {
          break label63;
        }
        for (;;)
        {
          switch (i)
          {
          default: 
            return;
            i = 20;
            continue;
            label63:
            i = 16;
          }
        }
        ˋ = 0;
        ˎ = 1;
        ˋ();
        ˊ = -102;
      }
      throw new NullPointerException();
    }
    
    private ˊ() {}
    
    /* Error */
    private void ˊ()
    {
      // Byte code:
      //   0: goto +65 -> 65
      //   3: aload_0
      //   4: getfield 40	o/Km$ˊ:ॱ	Lo/Km;
      //   7: iconst_0
      //   8: invokestatic 49	o/Km:ॱ	(Lo/Km;Z)Z
      //   11: pop
      //   12: aload_0
      //   13: getfield 40	o/Km$ˊ:ॱ	Lo/Km;
      //   16: invokestatic 52	o/Km:ॱॱ	(Lo/Km;)V
      //   19: aload_0
      //   20: getfield 40	o/Km$ˊ:ॱ	Lo/Km;
      //   23: getstatic 57	o/Jy$If:fade_out	I
      //   26: invokestatic 63	android/view/animation/AnimationUtils:loadAnimation	(Landroid/content/Context;I)Landroid/view/animation/Animation;
      //   29: astore_2
      //   30: aload_0
      //   31: getfield 40	o/Km$ˊ:ॱ	Lo/Km;
      //   34: invokestatic 67	o/Km:ᐝ	(Lo/Km;)Landroid/databinding/ViewDataBinding;
      //   37: checkcast 69	o/JF
      //   40: getfield 73	o/JF:ˊॱ	Landroid/widget/RelativeLayout;
      //   43: aload_2
      //   44: invokevirtual 79	android/widget/RelativeLayout:startAnimation	(Landroid/view/animation/Animation;)V
      //   47: aload_2
      //   48: new 13	o/Km$ˊ$1
      //   51: dup
      //   52: aload_0
      //   53: invokespecial 82	o/Km$ˊ$1:<init>	(Lo/Km$ˊ;)V
      //   56: invokevirtual 88	android/view/animation/Animation:setAnimationListener	(Landroid/view/animation/Animation$AnimationListener;)V
      //   59: goto +9 -> 68
      //   62: astore_2
      //   63: aload_2
      //   64: athrow
      //   65: goto -62 -> 3
      //   68: getstatic 27	o/Km$ˊ:ˎ	I
      //   71: istore_1
      //   72: iload_1
      //   73: bipush 45
      //   75: iadd
      //   76: istore_1
      //   77: iload_1
      //   78: sipush 128
      //   81: irem
      //   82: putstatic 25	o/Km$ˊ:ˋ	I
      //   85: iload_1
      //   86: iconst_2
      //   87: irem
      //   88: ifeq +4 -> 92
      //   91: return
      //   92: return
      //   93: astore_2
      //   94: aload_2
      //   95: athrow
      // Local variable table:
      //   start	length	slot	name	signature
      //   0	96	0	this	ˊ
      //   71	17	1	i	int
      //   29	19	2	localAnimation	Animation
      //   62	2	2	localException1	Exception
      //   93	2	2	localException2	Exception
      // Exception table:
      //   from	to	target	type
      //   77	85	62	java/lang/Exception
      //   68	72	93	java/lang/Exception
    }
    
    static void ˋ()
    {
      ˏ = new char[] { 162, 141, 148, 147, 41, 87, 90, 71, 59, 65, 63, 64, 60, 56, 28, 70, 84, 77, 57 };
    }
    
    /* Error */
    private String ˎ(String paramString)
    {
      // Byte code:
      //   0: goto +147 -> 147
      //   3: goto +374 -> 377
      //   6: getstatic 27	o/Km$ˊ:ˎ	I
      //   9: istore_3
      //   10: iload_3
      //   11: bipush 97
      //   13: iadd
      //   14: istore_3
      //   15: iload_3
      //   16: sipush 128
      //   19: irem
      //   20: putstatic 25	o/Km$ˊ:ˋ	I
      //   23: iload_3
      //   24: iconst_2
      //   25: irem
      //   26: ifeq +6 -> 32
      //   29: goto +36 -> 65
      //   32: goto +61 -> 93
      //   35: getstatic 27	o/Km$ˊ:ˎ	I
      //   38: bipush 105
      //   40: iadd
      //   41: istore_3
      //   42: iload_3
      //   43: sipush 128
      //   46: irem
      //   47: putstatic 25	o/Km$ˊ:ˋ	I
      //   50: iload_3
      //   51: iconst_2
      //   52: irem
      //   53: ifeq +6 -> 59
      //   56: goto +77 -> 133
      //   59: goto +312 -> 371
      //   62: astore_1
      //   63: aload_1
      //   64: athrow
      //   65: goto +28 -> 93
      //   68: aload 4
      //   70: iload_2
      //   71: aload_1
      //   72: aload_1
      //   73: arraylength
      //   74: iload_2
      //   75: imul
      //   76: iconst_0
      //   77: iadd
      //   78: baload
      //   79: getstatic 31	o/Km$ˊ:ˊ	B
      //   82: iand
      //   83: i2b
      //   84: bastore
      //   85: iload_2
      //   86: bipush 125
      //   88: iadd
      //   89: istore_2
      //   90: goto -87 -> 3
      //   93: goto +284 -> 377
      //   96: iconst_1
      //   97: istore_3
      //   98: iload_3
      //   99: tableswitch	default:+21->120, 0:+-64->35, 1:+150->249
      //   120: goto -85 -> 35
      //   123: astore_1
      //   124: new 114	java/lang/RuntimeException
      //   127: dup
      //   128: aload_1
      //   129: invokespecial 117	java/lang/RuntimeException:<init>	(Ljava/lang/Throwable;)V
      //   132: athrow
      //   133: bipush 14
      //   135: istore_3
      //   136: goto +204 -> 340
      //   139: iconst_0
      //   140: istore_3
      //   141: goto -43 -> 98
      //   144: astore_1
      //   145: aload_1
      //   146: athrow
      //   147: aload_1
      //   148: iconst_4
      //   149: newarray int
      //   151: dup
      //   152: iconst_0
      //   153: iconst_4
      //   154: iastore
      //   155: dup
      //   156: iconst_1
      //   157: bipush 10
      //   159: iastore
      //   160: dup
      //   161: iconst_2
      //   162: bipush 9
      //   164: iastore
      //   165: dup
      //   166: iconst_3
      //   167: iconst_0
      //   168: iastore
      //   169: bipush 10
      //   171: newarray byte
      //   173: dup
      //   174: iconst_0
      //   175: ldc 118
      //   177: bastore
      //   178: dup
      //   179: iconst_1
      //   180: ldc 118
      //   182: bastore
      //   183: dup
      //   184: iconst_2
      //   185: ldc 118
      //   187: bastore
      //   188: dup
      //   189: iconst_3
      //   190: ldc 118
      //   192: bastore
      //   193: dup
      //   194: iconst_4
      //   195: ldc 119
      //   197: bastore
      //   198: dup
      //   199: iconst_5
      //   200: ldc 118
      //   202: bastore
      //   203: dup
      //   204: bipush 6
      //   206: ldc 119
      //   208: bastore
      //   209: dup
      //   210: bipush 7
      //   212: ldc 118
      //   214: bastore
      //   215: dup
      //   216: bipush 8
      //   218: ldc 118
      //   220: bastore
      //   221: dup
      //   222: bipush 9
      //   224: ldc 118
      //   226: bastore
      //   227: iconst_0
      //   228: invokestatic 122	o/Km$ˊ:ˏ	([I[BZ)Ljava/lang/String;
      //   231: invokevirtual 128	java/lang/String:intern	()Ljava/lang/String;
      //   234: invokevirtual 132	java/lang/String:getBytes	(Ljava/lang/String;)[B
      //   237: astore_1
      //   238: aload_1
      //   239: arraylength
      //   240: newarray byte
      //   242: astore 4
      //   244: iconst_0
      //   245: istore_2
      //   246: goto -240 -> 6
      //   249: new 124	java/lang/String
      //   252: dup
      //   253: aload 4
      //   255: iconst_4
      //   256: newarray int
      //   258: dup
      //   259: iconst_0
      //   260: bipush 14
      //   262: iastore
      //   263: dup
      //   264: iconst_1
      //   265: iconst_5
      //   266: iastore
      //   267: dup
      //   268: iconst_2
      //   269: iconst_0
      //   270: iastore
      //   271: dup
      //   272: iconst_3
      //   273: iconst_1
      //   274: iastore
      //   275: iconst_5
      //   276: newarray byte
      //   278: dup
      //   279: iconst_0
      //   280: ldc 118
      //   282: bastore
      //   283: dup
      //   284: iconst_1
      //   285: ldc 119
      //   287: bastore
      //   288: dup
      //   289: iconst_2
      //   290: ldc 119
      //   292: bastore
      //   293: dup
      //   294: iconst_3
      //   295: ldc 118
      //   297: bastore
      //   298: dup
      //   299: iconst_4
      //   300: ldc 119
      //   302: bastore
      //   303: iconst_0
      //   304: invokestatic 122	o/Km$ˊ:ˏ	([I[BZ)Ljava/lang/String;
      //   307: invokevirtual 128	java/lang/String:intern	()Ljava/lang/String;
      //   310: invokespecial 135	java/lang/String:<init>	([BLjava/lang/String;)V
      //   313: astore_1
      //   314: aload_1
      //   315: areturn
      //   316: aload 4
      //   318: iload_2
      //   319: aload_1
      //   320: aload_1
      //   321: arraylength
      //   322: iload_2
      //   323: isub
      //   324: iconst_1
      //   325: isub
      //   326: baload
      //   327: getstatic 31	o/Km$ˊ:ˊ	B
      //   330: ixor
      //   331: i2b
      //   332: bastore
      //   333: iload_2
      //   334: iconst_1
      //   335: iadd
      //   336: istore_2
      //   337: goto -334 -> 3
      //   340: iload_3
      //   341: lookupswitch	default:+27->368, 9:+-25->316, 14:+-273->68
      //   368: goto -52 -> 316
      //   371: bipush 9
      //   373: istore_3
      //   374: goto -34 -> 340
      //   377: aload_1
      //   378: arraylength
      //   379: istore_3
      //   380: iload_2
      //   381: iload_3
      //   382: if_icmpge +6 -> 388
      //   385: goto -246 -> 139
      //   388: goto -292 -> 96
      // Local variable table:
      //   start	length	slot	name	signature
      //   0	391	0	this	ˊ
      //   0	391	1	paramString	String
      //   70	313	2	i	int
      //   9	374	3	j	int
      //   68	249	4	arrayOfByte	byte[]
      // Exception table:
      //   from	to	target	type
      //   6	10	62	java/lang/Exception
      //   68	85	123	java/io/UnsupportedEncodingException
      //   147	244	123	java/io/UnsupportedEncodingException
      //   249	314	123	java/io/UnsupportedEncodingException
      //   316	333	123	java/io/UnsupportedEncodingException
      //   377	380	123	java/io/UnsupportedEncodingException
      //   15	23	144	java/lang/Exception
    }
    
    /* Error */
    private static String ˏ(int[] paramArrayOfInt, byte[] paramArrayOfByte, boolean paramBoolean)
    {
      // Byte code:
      //   0: goto +498 -> 498
      //   3: astore_0
      //   4: aload_0
      //   5: athrow
      //   6: aload_1
      //   7: iload_3
      //   8: aload 9
      //   10: iload 5
      //   12: iload_3
      //   13: isub
      //   14: iconst_1
      //   15: isub
      //   16: caload
      //   17: castore
      //   18: iload_3
      //   19: iconst_1
      //   20: iadd
      //   21: istore_3
      //   22: goto +68 -> 90
      //   25: iload 5
      //   27: newarray char
      //   29: astore_1
      //   30: iconst_0
      //   31: istore_3
      //   32: goto +58 -> 90
      //   35: bipush 99
      //   37: istore_3
      //   38: goto +203 -> 241
      //   41: aload 10
      //   43: astore 9
      //   45: iload_3
      //   46: tableswitch	default:+22->68, 0:+120->166, 1:+613->659
      //   68: goto +98 -> 166
      //   71: aload_1
      //   72: iload 4
      //   74: baload
      //   75: ifne +6 -> 81
      //   78: goto +440 -> 518
      //   81: goto +502 -> 583
      //   84: goto +360 -> 444
      //   87: goto +572 -> 659
      //   90: iload_3
      //   91: iload 5
      //   93: if_icmpge +6 -> 99
      //   96: goto +342 -> 438
      //   99: goto +303 -> 402
      //   102: aload_0
      //   103: iconst_0
      //   104: iaload
      //   105: istore_3
      //   106: aload_0
      //   107: iconst_1
      //   108: iaload
      //   109: istore 5
      //   111: aload_0
      //   112: iconst_2
      //   113: iaload
      //   114: istore 6
      //   116: aload_0
      //   117: iconst_3
      //   118: iaload
      //   119: istore 7
      //   121: getstatic 109	o/Km$ˊ:ˏ	[C
      //   124: astore 9
      //   126: iload 5
      //   128: newarray char
      //   130: astore 10
      //   132: aload 9
      //   134: iload_3
      //   135: aload 10
      //   137: iconst_0
      //   138: iload 5
      //   140: invokestatic 141	java/lang/System:arraycopy	(Ljava/lang/Object;ILjava/lang/Object;II)V
      //   143: aload_1
      //   144: ifnull +6 -> 150
      //   147: goto +346 -> 493
      //   150: goto +504 -> 654
      //   153: iload 4
      //   155: iload 5
      //   157: if_icmpge +6 -> 163
      //   160: goto +248 -> 408
      //   163: goto -76 -> 87
      //   166: getstatic 27	o/Km$ˊ:ˎ	I
      //   169: bipush 49
      //   171: iadd
      //   172: istore_3
      //   173: iload_3
      //   174: sipush 128
      //   177: irem
      //   178: putstatic 25	o/Km$ˊ:ˋ	I
      //   181: iload_3
      //   182: iconst_2
      //   183: irem
      //   184: ifeq +6 -> 190
      //   187: goto +390 -> 577
      //   190: goto +381 -> 571
      //   193: iload 5
      //   195: newarray char
      //   197: astore 9
      //   199: iconst_0
      //   200: istore_3
      //   201: iconst_0
      //   202: istore 4
      //   204: goto -51 -> 153
      //   207: new 124	java/lang/String
      //   210: dup
      //   211: aload_1
      //   212: invokespecial 144	java/lang/String:<init>	([C)V
      //   215: areturn
      //   216: aload_1
      //   217: iload_3
      //   218: aload 9
      //   220: iload 5
      //   222: iload_3
      //   223: irem
      //   224: iconst_1
      //   225: iadd
      //   226: caload
      //   227: castore
      //   228: iload_3
      //   229: bipush 34
      //   231: iadd
      //   232: istore_3
      //   233: goto -143 -> 90
      //   236: iconst_0
      //   237: istore_3
      //   238: goto +404 -> 642
      //   241: iload_3
      //   242: lookupswitch	default:+26->268, 49:+-6->236, 99:+-35->207
      //   268: goto -61 -> 207
      //   271: goto +371 -> 642
      //   274: iload_2
      //   275: ifeq +6 -> 281
      //   278: goto -253 -> 25
      //   281: aload 9
      //   283: astore_1
      //   284: goto +160 -> 444
      //   287: iload 5
      //   289: newarray char
      //   291: astore_1
      //   292: aload 9
      //   294: iconst_0
      //   295: aload_1
      //   296: iconst_0
      //   297: iload 5
      //   299: invokestatic 141	java/lang/System:arraycopy	(Ljava/lang/Object;ILjava/lang/Object;II)V
      //   302: aload_1
      //   303: iconst_0
      //   304: aload 9
      //   306: iload 5
      //   308: iload 7
      //   310: isub
      //   311: iload 7
      //   313: invokestatic 141	java/lang/System:arraycopy	(Ljava/lang/Object;ILjava/lang/Object;II)V
      //   316: aload_1
      //   317: iload 7
      //   319: aload 9
      //   321: iconst_0
      //   322: iload 5
      //   324: iload 7
      //   326: isub
      //   327: invokestatic 141	java/lang/System:arraycopy	(Ljava/lang/Object;ILjava/lang/Object;II)V
      //   330: goto -56 -> 274
      //   333: iload 5
      //   335: newarray char
      //   337: astore 9
      //   339: iconst_1
      //   340: istore_3
      //   341: iconst_1
      //   342: istore 4
      //   344: goto -191 -> 153
      //   347: iload 4
      //   349: tableswitch	default:+23->372, 0:+23->372, 1:+-265->84
      //   372: getstatic 25	o/Km$ˊ:ˋ	I
      //   375: bipush 9
      //   377: iadd
      //   378: istore 4
      //   380: iload 4
      //   382: sipush 128
      //   385: irem
      //   386: putstatic 27	o/Km$ˊ:ˎ	I
      //   389: iload 4
      //   391: iconst_2
      //   392: irem
      //   393: ifne +6 -> 399
      //   396: goto -180 -> 216
      //   399: goto -393 -> 6
      //   402: iconst_1
      //   403: istore 4
      //   405: goto -58 -> 347
      //   408: getstatic 25	o/Km$ˊ:ˋ	I
      //   411: bipush 33
      //   413: iadd
      //   414: istore 8
      //   416: iload 8
      //   418: sipush 128
      //   421: irem
      //   422: putstatic 27	o/Km$ˊ:ˎ	I
      //   425: iload 8
      //   427: iconst_2
      //   428: irem
      //   429: ifne +6 -> 435
      //   432: goto -361 -> 71
      //   435: goto +66 -> 501
      //   438: iconst_0
      //   439: istore 4
      //   441: goto -94 -> 347
      //   444: iload 6
      //   446: ifle +6 -> 452
      //   449: goto +107 -> 556
      //   452: goto -417 -> 35
      //   455: iload_3
      //   456: lookupswitch	default:+28->484, 25:+-263->193, 39:+-123->333
      //   484: goto -151 -> 333
      //   487: iconst_1
      //   488: istore 4
      //   490: goto +111 -> 601
      //   493: iconst_0
      //   494: istore_3
      //   495: goto -454 -> 41
      //   498: goto -396 -> 102
      //   501: aload_1
      //   502: iload 4
      //   504: baload
      //   505: iconst_1
      //   506: if_icmpne +6 -> 512
      //   509: goto +9 -> 518
      //   512: goto +71 -> 583
      //   515: goto +112 -> 627
      //   518: aload 9
      //   520: iload 4
      //   522: aload 10
      //   524: iload 4
      //   526: caload
      //   527: iconst_1
      //   528: ishl
      //   529: iconst_1
      //   530: iadd
      //   531: iload_3
      //   532: isub
      //   533: i2c
      //   534: castore
      //   535: goto -20 -> 515
      //   538: aload_1
      //   539: iload_3
      //   540: aload_1
      //   541: iload_3
      //   542: caload
      //   543: aload_0
      //   544: iconst_2
      //   545: iaload
      //   546: isub
      //   547: i2c
      //   548: castore
      //   549: iload_3
      //   550: iconst_1
      //   551: iadd
      //   552: istore_3
      //   553: goto -282 -> 271
      //   556: bipush 49
      //   558: istore_3
      //   559: goto -318 -> 241
      //   562: astore_0
      //   563: aload_0
      //   564: athrow
      //   565: iconst_0
      //   566: istore 4
      //   568: goto +33 -> 601
      //   571: bipush 25
      //   573: istore_3
      //   574: goto -119 -> 455
      //   577: bipush 39
      //   579: istore_3
      //   580: goto -125 -> 455
      //   583: aload 9
      //   585: iload 4
      //   587: aload 10
      //   589: iload 4
      //   591: caload
      //   592: iconst_1
      //   593: ishl
      //   594: iload_3
      //   595: isub
      //   596: i2c
      //   597: castore
      //   598: goto +29 -> 627
      //   601: iload 4
      //   603: tableswitch	default:+21->624, 0:+-65->538, 1:+-396->207
      //   624: goto -417 -> 207
      //   627: aload 9
      //   629: iload 4
      //   631: caload
      //   632: istore_3
      //   633: iload 4
      //   635: iconst_1
      //   636: iadd
      //   637: istore 4
      //   639: goto -486 -> 153
      //   642: iload_3
      //   643: iload 5
      //   645: if_icmpge +6 -> 651
      //   648: goto -83 -> 565
      //   651: goto -164 -> 487
      //   654: iconst_1
      //   655: istore_3
      //   656: goto -615 -> 41
      //   659: iload 7
      //   661: ifle +6 -> 667
      //   664: goto -377 -> 287
      //   667: goto -393 -> 274
      // Local variable table:
      //   start	length	slot	name	signature
      //   0	670	0	paramArrayOfInt	int[]
      //   0	670	1	paramArrayOfByte	byte[]
      //   0	670	2	paramBoolean	boolean
      //   7	649	3	i	int
      //   72	566	4	j	int
      //   10	636	5	k	int
      //   114	331	6	m	int
      //   119	541	7	n	int
      //   414	15	8	i1	int
      //   8	620	9	localObject	Object
      //   41	547	10	arrayOfChar	char[]
      // Exception table:
      //   from	to	target	type
      //   302	316	3	java/lang/Exception
      //   292	302	562	java/lang/Exception
      //   302	316	562	java/lang/Exception
      //   316	330	562	java/lang/Exception
    }
    
    public void onClick(View paramView)
    {
      break label60;
      int i = ˋ + 105;
      ˎ = i % 128;
      if (i % 2 != 0)
      {
        break label53;
        label30:
        i = ˎ + 19;
        ˋ = i % 128;
        if (i % 2 != 0) {
          return;
        }
        return;
      }
      for (;;)
      {
        label53:
        ˊ();
        break label30;
        label60:
        break;
      }
    }
    
    /* Error */
    public void ˊ(int paramInt)
    {
      // Byte code:
      //   0: goto +31 -> 31
      //   3: aload_0
      //   4: getfield 40	o/Km$ˊ:ॱ	Lo/Km;
      //   7: invokestatic 152	o/Km:ˊ	(Lo/Km;)Z
      //   10: ifeq +6 -> 16
      //   13: goto +87 -> 100
      //   16: goto +444 -> 460
      //   19: goto +102 -> 121
      //   22: aload 4
      //   24: aload_3
      //   25: invokevirtual 158	android/widget/Button:setText	(Ljava/lang/CharSequence;)V
      //   28: goto +84 -> 112
      //   31: goto -28 -> 3
      //   34: aload_0
      //   35: invokespecial 148	o/Km$ˊ:ˊ	()V
      //   38: goto +204 -> 242
      //   41: iconst_1
      //   42: istore_1
      //   43: goto +308 -> 351
      //   46: getstatic 25	o/Km$ˊ:ˋ	I
      //   49: bipush 53
      //   51: iadd
      //   52: istore_1
      //   53: iload_1
      //   54: sipush 128
      //   57: irem
      //   58: putstatic 27	o/Km$ˊ:ˎ	I
      //   61: iload_1
      //   62: iconst_2
      //   63: irem
      //   64: ifne +6 -> 70
      //   67: goto +48 -> 115
      //   70: goto -36 -> 34
      //   73: getstatic 25	o/Km$ˊ:ˋ	I
      //   76: bipush 97
      //   78: iadd
      //   79: istore_1
      //   80: iload_1
      //   81: sipush 128
      //   84: irem
      //   85: putstatic 27	o/Km$ˊ:ˎ	I
      //   88: iload_1
      //   89: iconst_2
      //   90: irem
      //   91: ifne +6 -> 97
      //   94: goto +12 -> 106
      //   97: goto +72 -> 169
      //   100: bipush 60
      //   102: istore_1
      //   103: goto +216 -> 319
      //   106: goto +63 -> 169
      //   109: goto -87 -> 22
      //   112: goto -93 -> 19
      //   115: goto -81 -> 34
      //   118: astore_3
      //   119: aload_3
      //   120: athrow
      //   121: getstatic 27	o/Km$ˊ:ˎ	I
      //   124: bipush 57
      //   126: iadd
      //   127: istore_1
      //   128: iload_1
      //   129: sipush 128
      //   132: irem
      //   133: putstatic 25	o/Km$ˊ:ˋ	I
      //   136: iload_1
      //   137: iconst_2
      //   138: irem
      //   139: ifeq +6 -> 145
      //   142: goto +241 -> 383
      //   145: goto +19 -> 164
      //   148: aload_0
      //   149: aload_3
      //   150: iconst_4
      //   151: invokevirtual 162	java/lang/String:substring	(I)Ljava/lang/String;
      //   154: invokespecial 164	o/Km$ˊ:ˎ	(Ljava/lang/String;)Ljava/lang/String;
      //   157: invokevirtual 128	java/lang/String:intern	()Ljava/lang/String;
      //   160: astore_3
      //   161: goto +311 -> 472
      //   164: iconst_0
      //   165: istore_1
      //   166: goto +125 -> 291
      //   169: aload_0
      //   170: getfield 40	o/Km$ˊ:ॱ	Lo/Km;
      //   173: invokestatic 166	o/Km:ॱ	(Lo/Km;)Landroid/databinding/ViewDataBinding;
      //   176: checkcast 69	o/JF
      //   179: getfield 169	o/JF:ॱ	Landroid/widget/Button;
      //   182: astore 4
      //   184: aload_0
      //   185: getfield 40	o/Km$ˊ:ॱ	Lo/Km;
      //   188: getstatic 174	o/Jy$IF:add_another_card	I
      //   191: invokevirtual 177	o/Km:getString	(I)Ljava/lang/String;
      //   194: astore_3
      //   195: aload_3
      //   196: iconst_4
      //   197: newarray int
      //   199: dup
      //   200: iconst_0
      //   201: iconst_0
      //   202: iastore
      //   203: dup
      //   204: iconst_1
      //   205: iconst_4
      //   206: iastore
      //   207: dup
      //   208: iconst_2
      //   209: sipush 136
      //   212: iastore
      //   213: dup
      //   214: iconst_3
      //   215: iconst_2
      //   216: iastore
      //   217: aconst_null
      //   218: iconst_1
      //   219: invokestatic 122	o/Km$ˊ:ˏ	([I[BZ)Ljava/lang/String;
      //   222: invokevirtual 128	java/lang/String:intern	()Ljava/lang/String;
      //   225: invokevirtual 181	java/lang/String:startsWith	(Ljava/lang/String;)Z
      //   228: ifeq +6 -> 234
      //   231: goto +250 -> 481
      //   234: goto -212 -> 22
      //   237: iconst_2
      //   238: istore_1
      //   239: goto +112 -> 351
      //   242: aload_0
      //   243: getfield 40	o/Km$ˊ:ॱ	Lo/Km;
      //   246: astore_3
      //   247: aload_3
      //   248: invokestatic 183	o/Km:ˏ	(Lo/Km;)Landroid/databinding/ViewDataBinding;
      //   251: astore_3
      //   252: aload_3
      //   253: checkcast 69	o/JF
      //   256: astore_3
      //   257: aload_3
      //   258: getfield 186	o/JF:ˊ	Lo/IY;
      //   261: astore_3
      //   262: aload_3
      //   263: invokevirtual 191	o/IY:ॱ	()I
      //   266: istore_1
      //   267: aload_0
      //   268: getfield 40	o/Km$ˊ:ॱ	Lo/Km;
      //   271: invokestatic 194	o/Km:ˎ	(Lo/Km;)Lo/KF;
      //   274: invokevirtual 197	o/KF:ॱ	()I
      //   277: istore_2
      //   278: iload_1
      //   279: iload_2
      //   280: iconst_1
      //   281: isub
      //   282: if_icmpne +6 -> 288
      //   285: goto -48 -> 237
      //   288: goto -247 -> 41
      //   291: iload_1
      //   292: tableswitch	default:+24->316, 0:+167->459, 1:+174->466
      //   316: goto +150 -> 466
      //   319: iload_1
      //   320: lookupswitch	default:+28->348, 60:+-274->46, 98:+-78->242
      //   348: goto -302 -> 46
      //   351: iload_1
      //   352: lookupswitch	default:+28->380, 1:+36->388, 2:+-279->73
      //   380: goto -307 -> 73
      //   383: iconst_1
      //   384: istore_1
      //   385: goto -94 -> 291
      //   388: aload_0
      //   389: getfield 40	o/Km$ˊ:ॱ	Lo/Km;
      //   392: invokestatic 199	o/Km:ˋ	(Lo/Km;)Landroid/databinding/ViewDataBinding;
      //   395: checkcast 69	o/JF
      //   398: getfield 169	o/JF:ॱ	Landroid/widget/Button;
      //   401: astore 4
      //   403: aload_0
      //   404: getfield 40	o/Km$ˊ:ॱ	Lo/Km;
      //   407: getstatic 202	o/Jy$IF:card_presentment_btn	I
      //   410: invokevirtual 177	o/Km:getString	(I)Ljava/lang/String;
      //   413: astore_3
      //   414: aload_3
      //   415: iconst_4
      //   416: newarray int
      //   418: dup
      //   419: iconst_0
      //   420: iconst_0
      //   421: iastore
      //   422: dup
      //   423: iconst_1
      //   424: iconst_4
      //   425: iastore
      //   426: dup
      //   427: iconst_2
      //   428: sipush 136
      //   431: iastore
      //   432: dup
      //   433: iconst_3
      //   434: iconst_2
      //   435: iastore
      //   436: aconst_null
      //   437: iconst_1
      //   438: invokestatic 122	o/Km$ˊ:ˏ	([I[BZ)Ljava/lang/String;
      //   441: invokevirtual 128	java/lang/String:intern	()Ljava/lang/String;
      //   444: invokevirtual 181	java/lang/String:startsWith	(Ljava/lang/String;)Z
      //   447: ifeq +6 -> 453
      //   450: goto -302 -> 148
      //   453: goto +19 -> 472
      //   456: astore_3
      //   457: aload_3
      //   458: athrow
      //   459: return
      //   460: bipush 98
      //   462: istore_1
      //   463: goto -144 -> 319
      //   466: bipush 26
      //   468: iconst_0
      //   469: idiv
      //   470: istore_1
      //   471: return
      //   472: aload 4
      //   474: aload_3
      //   475: invokevirtual 158	android/widget/Button:setText	(Ljava/lang/CharSequence;)V
      //   478: goto -459 -> 19
      //   481: aload_0
      //   482: aload_3
      //   483: iconst_4
      //   484: invokevirtual 162	java/lang/String:substring	(I)Ljava/lang/String;
      //   487: invokespecial 164	o/Km$ˊ:ˎ	(Ljava/lang/String;)Ljava/lang/String;
      //   490: invokevirtual 128	java/lang/String:intern	()Ljava/lang/String;
      //   493: astore_3
      //   494: goto -385 -> 109
      // Local variable table:
      //   start	length	slot	name	signature
      //   0	497	0	this	ˊ
      //   0	497	1	paramInt	int
      //   277	5	2	i	int
      //   24	1	3	localCharSequence	CharSequence
      //   118	32	3	localException1	Exception
      //   160	255	3	localObject	Object
      //   456	27	3	localException2	Exception
      //   493	1	3	str	String
      //   22	451	4	localButton	Button
      // Exception table:
      //   from	to	target	type
      //   257	262	118	java/lang/Exception
      //   242	247	456	java/lang/Exception
      //   247	252	456	java/lang/Exception
      //   252	257	456	java/lang/Exception
      //   257	262	456	java/lang/Exception
      //   262	267	456	java/lang/Exception
      //   267	278	456	java/lang/Exception
    }
    
    public void ˋ(int paramInt1, float paramFloat, int paramInt2)
    {
      for (;;)
      {
        paramInt1 = ˎ + 23;
        ˋ = paramInt1 % 128;
        if (paramInt1 % 2 == 0) {
          return;
        } else {
          return;
        }
      }
    }
    
    public void ॱ(int paramInt)
    {
      break label74;
      throw new NullPointerException();
      for (;;)
      {
        switch (paramInt)
        {
        }
        return;
        paramInt = 1;
        continue;
        label42:
        paramInt = 0;
      }
      label74:
      for (;;)
      {
        paramInt = ˎ + 55;
        ˋ = paramInt % 128;
        if (paramInt % 2 != 0) {
          break;
        }
        break label42;
      }
    }
  }
}
