package o;

import android.content.Context;
import android.content.Intent;
import android.support.design.widget.AppBarLayout.ˊ;
import android.support.v7.widget.RecyclerView;
import android.support.v7.widget.RecyclerView.aUx;
import android.view.View;
import android.view.animation.Animation;
import android.view.animation.Animation.AnimationListener;
import com.insidesecure.hce.MatrixHCECard;
import java.io.UnsupportedEncodingException;

public class Kn
  extends IB<JG>
  implements AppBarLayout.ˊ
{
  private static long ˊᐝ;
  private static byte ˋˊ;
  private static int ˌ;
  private static int ˎˎ;
  private H ʼॱ;
  private String ʽॱ;
  private int ʾ;
  private HQ ʿ;
  private Gd ˈ;
  private Animation ˉ;
  private Animation ˊˊ;
  private RecyclerView.aUx ˊˋ;
  
  static
  {
    for (;;)
    {
      int i = ˎˎ + 7;
      ˌ = i % 128;
      if (i % 2 == 0)
      {
        i = 1;
        break label36;
        i = null.length;
        return;
      }
      for (;;)
      {
        label36:
        switch (i)
        {
        }
        return;
        i = 0;
      }
      ˌ = 0;
      ˎˎ = 1;
      ʻॱ();
      ˋˊ = -102;
    }
  }
  
  /* Error */
  public Kn()
  {
    // Byte code:
    //   0: goto +6 -> 6
    //   3: astore_1
    //   4: aload_1
    //   5: athrow
    //   6: aload_0
    //   7: invokespecial 55	o/IB:<init>	()V
    //   10: getstatic 60	o/H:ˏ	Lo/H;
    //   13: astore_1
    //   14: aload_0
    //   15: aload_1
    //   16: putfield 62	o/Kn:ʼॱ	Lo/H;
    //   19: new 64	android/view/animation/TranslateAnimation
    //   22: dup
    //   23: fconst_0
    //   24: fconst_0
    //   25: fconst_0
    //   26: fconst_0
    //   27: invokespecial 67	android/view/animation/TranslateAnimation:<init>	(FFFF)V
    //   30: astore_1
    //   31: aload_0
    //   32: aload_1
    //   33: putfield 69	o/Kn:ˉ	Landroid/view/animation/Animation;
    //   36: new 64	android/view/animation/TranslateAnimation
    //   39: dup
    //   40: fconst_0
    //   41: fconst_0
    //   42: fconst_0
    //   43: fconst_0
    //   44: invokespecial 67	android/view/animation/TranslateAnimation:<init>	(FFFF)V
    //   47: astore_1
    //   48: aload_0
    //   49: aload_1
    //   50: putfield 71	o/Kn:ˊˊ	Landroid/view/animation/Animation;
    //   53: new 9	o/Kn$1
    //   56: dup
    //   57: aload_0
    //   58: invokespecial 74	o/Kn$1:<init>	(Lo/Kn;)V
    //   61: astore_1
    //   62: aload_0
    //   63: aload_1
    //   64: putfield 76	o/Kn:ˊˋ	Landroid/support/v7/widget/RecyclerView$aUx;
    //   67: return
    //   68: astore_1
    //   69: aload_1
    //   70: athrow
    // Local variable table:
    //   start	length	slot	name	signature
    //   0	71	0	this	Kn
    //   3	2	1	localException1	Exception
    //   13	51	1	localObject	Object
    //   68	2	1	localException2	Exception
    // Exception table:
    //   from	to	target	type
    //   14	19	3	java/lang/Exception
    //   10	14	68	java/lang/Exception
    //   14	19	68	java/lang/Exception
    //   19	31	68	java/lang/Exception
    //   31	48	68	java/lang/Exception
    //   48	53	68	java/lang/Exception
    //   53	62	68	java/lang/Exception
    //   62	67	68	java/lang/Exception
  }
  
  static void ʻॱ()
  {
    ˊᐝ = 6593694203784424259L;
  }
  
  /* Error */
  private void ʾ()
  {
    // Byte code:
    //   0: goto +181 -> 181
    //   3: aload_3
    //   4: astore_2
    //   5: iload_1
    //   6: lookupswitch	default:+26->32, 8:+632->638, 77:+218->224
    //   32: goto +606 -> 638
    //   35: getstatic 44	o/Kn:ˌ	I
    //   38: bipush 13
    //   40: iadd
    //   41: istore_1
    //   42: iload_1
    //   43: sipush 128
    //   46: irem
    //   47: putstatic 42	o/Kn:ˎˎ	I
    //   50: iload_1
    //   51: iconst_2
    //   52: irem
    //   53: ifne +6 -> 59
    //   56: goto +211 -> 267
    //   59: goto +419 -> 478
    //   62: aload_0
    //   63: getfield 90	o/Kn:ˈ	Lo/Gd;
    //   66: invokevirtual 96	o/Gd:ॱ	()Ljava/math/BigDecimal;
    //   69: ifnull +6 -> 75
    //   72: goto -37 -> 35
    //   75: goto +109 -> 184
    //   78: aload_0
    //   79: getfield 82	o/Kn:ॱˊ	Landroid/databinding/ViewDataBinding;
    //   82: checkcast 98	o/JG
    //   85: astore 5
    //   87: aload_0
    //   88: getfield 90	o/Kn:ˈ	Lo/Gd;
    //   91: invokevirtual 101	o/Gd:ˎ	()Ljava/math/BigDecimal;
    //   94: ifnull +6 -> 100
    //   97: goto +6 -> 103
    //   100: goto +421 -> 521
    //   103: iconst_1
    //   104: istore_1
    //   105: goto +418 -> 523
    //   108: bipush 46
    //   110: istore_1
    //   111: goto +302 -> 413
    //   114: aload 5
    //   116: aload_2
    //   117: invokevirtual 104	o/JG:ॱ	(Ljava/lang/String;)V
    //   120: return
    //   121: aload_3
    //   122: astore_2
    //   123: iload_1
    //   124: tableswitch	default:+24->148, 0:+365->489, 1:+67->191
    //   148: aload_3
    //   149: astore_2
    //   150: goto +41 -> 191
    //   153: aload_0
    //   154: getfield 90	o/Kn:ˈ	Lo/Gd;
    //   157: astore_2
    //   158: aload_2
    //   159: invokevirtual 101	o/Gd:ˎ	()Ljava/math/BigDecimal;
    //   162: astore_2
    //   163: aload_2
    //   164: getstatic 110	java/math/BigDecimal:ZERO	Ljava/math/BigDecimal;
    //   167: invokevirtual 114	java/math/BigDecimal:compareTo	(Ljava/math/BigDecimal;)I
    //   170: istore_1
    //   171: iload_1
    //   172: ifle +6 -> 178
    //   175: goto -67 -> 108
    //   178: goto +100 -> 278
    //   181: goto -119 -> 62
    //   184: getstatic 110	java/math/BigDecimal:ZERO	Ljava/math/BigDecimal;
    //   187: astore_2
    //   188: goto +169 -> 357
    //   191: aload_2
    //   192: iconst_2
    //   193: anewarray 116	java/lang/Object
    //   196: dup
    //   197: iconst_0
    //   198: aload 4
    //   200: aastore
    //   201: dup
    //   202: iconst_1
    //   203: aload_0
    //   204: getfield 118	o/Kn:ʿ	Lo/HQ;
    //   207: invokevirtual 123	o/HQ:ʻ	()Lo/Ep;
    //   210: aastore
    //   211: invokestatic 129	java/lang/String:format	(Ljava/lang/String;[Ljava/lang/Object;)Ljava/lang/String;
    //   214: astore_2
    //   215: goto -101 -> 114
    //   218: bipush 8
    //   220: istore_1
    //   221: goto -218 -> 3
    //   224: aload_2
    //   225: iconst_3
    //   226: anewarray 116	java/lang/Object
    //   229: dup
    //   230: iconst_0
    //   231: aload 4
    //   233: aastore
    //   234: dup
    //   235: iconst_1
    //   236: aload_0
    //   237: getfield 118	o/Kn:ʿ	Lo/HQ;
    //   240: invokevirtual 123	o/HQ:ʻ	()Lo/Ep;
    //   243: invokevirtual 135	o/Ep:ˊ	()Ljava/lang/String;
    //   246: aastore
    //   247: dup
    //   248: iconst_2
    //   249: aload_0
    //   250: getfield 90	o/Kn:ˈ	Lo/Gd;
    //   253: invokevirtual 101	o/Gd:ˎ	()Ljava/math/BigDecimal;
    //   256: invokestatic 141	o/at:ˋ	(Ljava/math/BigDecimal;)Ljava/lang/String;
    //   259: aastore
    //   260: invokestatic 129	java/lang/String:format	(Ljava/lang/String;[Ljava/lang/Object;)Ljava/lang/String;
    //   263: astore_2
    //   264: goto +185 -> 449
    //   267: goto +211 -> 478
    //   270: iconst_1
    //   271: istore_1
    //   272: goto -151 -> 121
    //   275: goto +279 -> 554
    //   278: bipush 9
    //   280: istore_1
    //   281: goto +132 -> 413
    //   284: aload_0
    //   285: getstatic 146	o/Jy$IF:balance_without_bt_points	I
    //   288: invokevirtual 150	o/Kn:getString	(I)Ljava/lang/String;
    //   291: astore_3
    //   292: aload_3
    //   293: bipush 8
    //   295: newarray char
    //   297: dup
    //   298: iconst_0
    //   299: ldc -105
    //   301: castore
    //   302: dup
    //   303: iconst_1
    //   304: ldc -104
    //   306: castore
    //   307: dup
    //   308: iconst_2
    //   309: ldc -103
    //   311: castore
    //   312: dup
    //   313: iconst_3
    //   314: ldc -102
    //   316: castore
    //   317: dup
    //   318: iconst_4
    //   319: ldc -101
    //   321: castore
    //   322: dup
    //   323: iconst_5
    //   324: ldc -100
    //   326: castore
    //   327: dup
    //   328: bipush 6
    //   330: ldc -99
    //   332: castore
    //   333: dup
    //   334: bipush 7
    //   336: ldc -98
    //   338: castore
    //   339: invokestatic 161	o/Kn:ˋ	([C)Ljava/lang/String;
    //   342: invokevirtual 164	java/lang/String:intern	()Ljava/lang/String;
    //   345: invokevirtual 168	java/lang/String:startsWith	(Ljava/lang/String;)Z
    //   348: ifeq +6 -> 354
    //   351: goto +57 -> 408
    //   354: goto -84 -> 270
    //   357: aload_2
    //   358: invokestatic 141	o/at:ˋ	(Ljava/math/BigDecimal;)Ljava/lang/String;
    //   361: astore 4
    //   363: getstatic 171	o/Kn$2:ˊ	[I
    //   366: aload_0
    //   367: getfield 118	o/Kn:ʿ	Lo/HQ;
    //   370: invokevirtual 175	o/HQ:ˍ	()Lo/Ei;
    //   373: invokevirtual 181	o/Ei:ordinal	()I
    //   376: iaload
    //   377: lookupswitch	default:+27->404, 1:+-299->78, 2:+180->557
    //   404: return
    //   405: astore_2
    //   406: aload_2
    //   407: athrow
    //   408: iconst_0
    //   409: istore_1
    //   410: goto -289 -> 121
    //   413: iload_1
    //   414: lookupswitch	default:+26->440, 9:+-130->284, 46:+240->654
    //   440: goto +214 -> 654
    //   443: bipush 77
    //   445: istore_1
    //   446: goto -443 -> 3
    //   449: getstatic 42	o/Kn:ˎˎ	I
    //   452: istore_1
    //   453: iload_1
    //   454: bipush 49
    //   456: iadd
    //   457: istore_1
    //   458: iload_1
    //   459: sipush 128
    //   462: irem
    //   463: putstatic 44	o/Kn:ˌ	I
    //   466: iload_1
    //   467: iconst_2
    //   468: irem
    //   469: ifeq +6 -> 475
    //   472: goto -197 -> 275
    //   475: goto +79 -> 554
    //   478: aload_0
    //   479: getfield 90	o/Kn:ˈ	Lo/Gd;
    //   482: invokevirtual 96	o/Gd:ॱ	()Ljava/math/BigDecimal;
    //   485: astore_2
    //   486: goto -129 -> 357
    //   489: aload_0
    //   490: aload_3
    //   491: iconst_4
    //   492: invokevirtual 184	java/lang/String:substring	(I)Ljava/lang/String;
    //   495: invokespecial 187	o/Kn:ॱ	(Ljava/lang/String;)Ljava/lang/String;
    //   498: invokevirtual 164	java/lang/String:intern	()Ljava/lang/String;
    //   501: astore_2
    //   502: goto -311 -> 191
    //   505: aload_0
    //   506: aload_2
    //   507: iconst_4
    //   508: invokevirtual 184	java/lang/String:substring	(I)Ljava/lang/String;
    //   511: invokespecial 187	o/Kn:ॱ	(Ljava/lang/String;)Ljava/lang/String;
    //   514: invokevirtual 164	java/lang/String:intern	()Ljava/lang/String;
    //   517: astore_2
    //   518: goto +209 -> 727
    //   521: iconst_0
    //   522: istore_1
    //   523: iload_1
    //   524: tableswitch	default:+24->548, 0:+-240->284, 1:+-371->153
    //   548: goto -264 -> 284
    //   551: astore_2
    //   552: aload_2
    //   553: athrow
    //   554: goto -440 -> 114
    //   557: aload_0
    //   558: getfield 82	o/Kn:ॱˊ	Landroid/databinding/ViewDataBinding;
    //   561: checkcast 98	o/JG
    //   564: astore_3
    //   565: aload_0
    //   566: getstatic 146	o/Jy$IF:balance_without_bt_points	I
    //   569: invokevirtual 150	o/Kn:getString	(I)Ljava/lang/String;
    //   572: astore_2
    //   573: aload_2
    //   574: bipush 8
    //   576: newarray char
    //   578: dup
    //   579: iconst_0
    //   580: ldc -105
    //   582: castore
    //   583: dup
    //   584: iconst_1
    //   585: ldc -104
    //   587: castore
    //   588: dup
    //   589: iconst_2
    //   590: ldc -103
    //   592: castore
    //   593: dup
    //   594: iconst_3
    //   595: ldc -102
    //   597: castore
    //   598: dup
    //   599: iconst_4
    //   600: ldc -101
    //   602: castore
    //   603: dup
    //   604: iconst_5
    //   605: ldc -100
    //   607: castore
    //   608: dup
    //   609: bipush 6
    //   611: ldc -99
    //   613: castore
    //   614: dup
    //   615: bipush 7
    //   617: ldc -98
    //   619: castore
    //   620: invokestatic 161	o/Kn:ˋ	([C)Ljava/lang/String;
    //   623: invokevirtual 164	java/lang/String:intern	()Ljava/lang/String;
    //   626: invokevirtual 168	java/lang/String:startsWith	(Ljava/lang/String;)Z
    //   629: ifeq +6 -> 635
    //   632: goto -127 -> 505
    //   635: goto +92 -> 727
    //   638: aload_0
    //   639: aload_3
    //   640: iconst_4
    //   641: invokevirtual 184	java/lang/String:substring	(I)Ljava/lang/String;
    //   644: invokespecial 187	o/Kn:ॱ	(Ljava/lang/String;)Ljava/lang/String;
    //   647: invokevirtual 164	java/lang/String:intern	()Ljava/lang/String;
    //   650: astore_2
    //   651: goto -427 -> 224
    //   654: aload_0
    //   655: getstatic 190	o/Jy$IF:balance_with_bt_points	I
    //   658: invokevirtual 150	o/Kn:getString	(I)Ljava/lang/String;
    //   661: astore_3
    //   662: aload_3
    //   663: bipush 8
    //   665: newarray char
    //   667: dup
    //   668: iconst_0
    //   669: ldc -105
    //   671: castore
    //   672: dup
    //   673: iconst_1
    //   674: ldc -104
    //   676: castore
    //   677: dup
    //   678: iconst_2
    //   679: ldc -103
    //   681: castore
    //   682: dup
    //   683: iconst_3
    //   684: ldc -102
    //   686: castore
    //   687: dup
    //   688: iconst_4
    //   689: ldc -101
    //   691: castore
    //   692: dup
    //   693: iconst_5
    //   694: ldc -100
    //   696: castore
    //   697: dup
    //   698: bipush 6
    //   700: ldc -99
    //   702: castore
    //   703: dup
    //   704: bipush 7
    //   706: ldc -98
    //   708: castore
    //   709: invokestatic 161	o/Kn:ˋ	([C)Ljava/lang/String;
    //   712: invokevirtual 164	java/lang/String:intern	()Ljava/lang/String;
    //   715: invokevirtual 168	java/lang/String:startsWith	(Ljava/lang/String;)Z
    //   718: ifeq +6 -> 724
    //   721: goto -503 -> 218
    //   724: goto -281 -> 443
    //   727: aload_3
    //   728: aload_2
    //   729: iconst_2
    //   730: anewarray 116	java/lang/Object
    //   733: dup
    //   734: iconst_0
    //   735: aload 4
    //   737: aastore
    //   738: dup
    //   739: iconst_1
    //   740: aload_0
    //   741: getfield 118	o/Kn:ʿ	Lo/HQ;
    //   744: invokevirtual 123	o/HQ:ʻ	()Lo/Ep;
    //   747: aastore
    //   748: invokestatic 129	java/lang/String:format	(Ljava/lang/String;[Ljava/lang/Object;)Ljava/lang/String;
    //   751: invokevirtual 104	o/JG:ॱ	(Ljava/lang/String;)V
    //   754: return
    // Local variable table:
    //   start	length	slot	name	signature
    //   0	755	0	this	Kn
    //   5	519	1	i	int
    //   4	354	2	localObject1	Object
    //   405	2	2	localException1	Exception
    //   485	33	2	localObject2	Object
    //   551	2	2	localException2	Exception
    //   572	157	2	str1	String
    //   3	725	3	localObject3	Object
    //   198	538	4	str2	String
    //   85	30	5	localJG	JG
    // Exception table:
    //   from	to	target	type
    //   153	158	405	java/lang/Exception
    //   158	163	405	java/lang/Exception
    //   163	171	405	java/lang/Exception
    //   158	163	551	java/lang/Exception
    //   449	453	551	java/lang/Exception
    //   458	466	551	java/lang/Exception
  }
  
  /* Error */
  private void ˉ()
  {
    // Byte code:
    //   0: goto +36 -> 36
    //   3: astore 7
    //   5: aload 7
    //   7: athrow
    //   8: getstatic 44	o/Kn:ˌ	I
    //   11: bipush 47
    //   13: iadd
    //   14: istore 6
    //   16: iload 6
    //   18: sipush 128
    //   21: irem
    //   22: putstatic 42	o/Kn:ˎˎ	I
    //   25: iload 6
    //   27: iconst_2
    //   28: irem
    //   29: ifne +6 -> 35
    //   32: goto +7 -> 39
    //   35: return
    //   36: goto +4 -> 40
    //   39: return
    //   40: aload_0
    //   41: getfield 82	o/Kn:ॱˊ	Landroid/databinding/ViewDataBinding;
    //   44: checkcast 98	o/JG
    //   47: getfield 194	o/JG:ᐝ	Landroid/widget/Button;
    //   50: invokevirtual 200	android/widget/Button:getY	()F
    //   53: fstore 5
    //   55: aload_0
    //   56: getfield 82	o/Kn:ॱˊ	Landroid/databinding/ViewDataBinding;
    //   59: checkcast 98	o/JG
    //   62: getfield 194	o/JG:ᐝ	Landroid/widget/Button;
    //   65: invokevirtual 203	android/widget/Button:getHeight	()I
    //   68: i2d
    //   69: dstore_1
    //   70: goto +23 -> 93
    //   73: astore 7
    //   75: aload 7
    //   77: invokevirtual 209	java/lang/Throwable:getCause	()Ljava/lang/Throwable;
    //   80: astore 8
    //   82: aload 8
    //   84: ifnull +6 -> 90
    //   87: aload 8
    //   89: athrow
    //   90: aload 7
    //   92: athrow
    //   93: aload_0
    //   94: invokevirtual 215	android/content/Context:getResources	()Landroid/content/res/Resources;
    //   97: ldc -40
    //   99: invokevirtual 219	android/content/res/Resources:getString	(I)Ljava/lang/String;
    //   102: iconst_0
    //   103: iconst_4
    //   104: invokevirtual 222	java/lang/String:substring	(II)Ljava/lang/String;
    //   107: invokevirtual 225	java/lang/String:length	()I
    //   110: iconst_1
    //   111: isub
    //   112: aload_0
    //   113: invokevirtual 229	android/content/Context:getApplicationInfo	()Landroid/content/pm/ApplicationInfo;
    //   116: getfield 234	android/content/pm/ApplicationInfo:targetSdkVersion	I
    //   119: bipush 25
    //   121: isub
    //   122: aload_0
    //   123: invokevirtual 237	android/content/Context:getPackageName	()Ljava/lang/String;
    //   126: invokevirtual 225	java/lang/String:length	()I
    //   129: ldc -18
    //   131: iadd
    //   132: i2c
    //   133: invokestatic 243	o/O:ˋ	(IIC)Ljava/lang/Object;
    //   136: checkcast 245	java/lang/Class
    //   139: ldc -10
    //   141: aconst_null
    //   142: invokevirtual 250	java/lang/Class:getMethod	(Ljava/lang/String;[Ljava/lang/Class;)Ljava/lang/reflect/Method;
    //   145: aconst_null
    //   146: aconst_null
    //   147: invokevirtual 256	java/lang/reflect/Method:invoke	(Ljava/lang/Object;[Ljava/lang/Object;)Ljava/lang/Object;
    //   150: astore 7
    //   152: goto +23 -> 175
    //   155: astore 7
    //   157: aload 7
    //   159: invokevirtual 209	java/lang/Throwable:getCause	()Ljava/lang/Throwable;
    //   162: astore 8
    //   164: aload 8
    //   166: ifnull +6 -> 172
    //   169: aload 8
    //   171: athrow
    //   172: aload 7
    //   174: athrow
    //   175: aload_0
    //   176: invokevirtual 237	android/content/Context:getPackageName	()Ljava/lang/String;
    //   179: invokevirtual 225	java/lang/String:length	()I
    //   182: bipush 8
    //   184: isub
    //   185: aload_0
    //   186: invokevirtual 215	android/content/Context:getResources	()Landroid/content/res/Resources;
    //   189: ldc_w 257
    //   192: invokevirtual 219	android/content/res/Resources:getString	(I)Ljava/lang/String;
    //   195: iconst_0
    //   196: iconst_4
    //   197: invokevirtual 222	java/lang/String:substring	(II)Ljava/lang/String;
    //   200: iconst_0
    //   201: invokevirtual 261	java/lang/String:codePointAt	(I)I
    //   204: iconst_5
    //   205: isub
    //   206: aload_0
    //   207: invokevirtual 237	android/content/Context:getPackageName	()Ljava/lang/String;
    //   210: bipush 7
    //   212: invokevirtual 261	java/lang/String:codePointAt	(I)I
    //   215: ldc_w 262
    //   218: iadd
    //   219: i2c
    //   220: invokestatic 243	o/O:ˋ	(IIC)Ljava/lang/Object;
    //   223: checkcast 245	java/lang/Class
    //   226: ldc_w 263
    //   229: aconst_null
    //   230: invokevirtual 250	java/lang/Class:getMethod	(Ljava/lang/String;[Ljava/lang/Class;)Ljava/lang/reflect/Method;
    //   233: aload 7
    //   235: aconst_null
    //   236: invokevirtual 256	java/lang/reflect/Method:invoke	(Ljava/lang/Object;[Ljava/lang/Object;)Ljava/lang/Object;
    //   239: checkcast 265	java/lang/Double
    //   242: invokevirtual 269	java/lang/Double:doubleValue	()D
    //   245: dstore_3
    //   246: dload_1
    //   247: dload_3
    //   248: dadd
    //   249: d2f
    //   250: fload 5
    //   252: fsub
    //   253: fstore 5
    //   255: aload_0
    //   256: new 64	android/view/animation/TranslateAnimation
    //   259: dup
    //   260: fconst_0
    //   261: fconst_0
    //   262: fconst_0
    //   263: fload 5
    //   265: invokespecial 67	android/view/animation/TranslateAnimation:<init>	(FFFF)V
    //   268: putfield 69	o/Kn:ˉ	Landroid/view/animation/Animation;
    //   271: aload_0
    //   272: getfield 69	o/Kn:ˉ	Landroid/view/animation/Animation;
    //   275: ldc2_w 270
    //   278: invokevirtual 277	android/view/animation/Animation:setDuration	(J)V
    //   281: aload_0
    //   282: getfield 69	o/Kn:ˉ	Landroid/view/animation/Animation;
    //   285: iconst_1
    //   286: invokevirtual 281	android/view/animation/Animation:setFillAfter	(Z)V
    //   289: aload_0
    //   290: new 64	android/view/animation/TranslateAnimation
    //   293: dup
    //   294: fconst_0
    //   295: fconst_0
    //   296: fload 5
    //   298: fconst_0
    //   299: invokespecial 67	android/view/animation/TranslateAnimation:<init>	(FFFF)V
    //   302: putfield 71	o/Kn:ˊˊ	Landroid/view/animation/Animation;
    //   305: aload_0
    //   306: getfield 71	o/Kn:ˊˊ	Landroid/view/animation/Animation;
    //   309: ldc2_w 270
    //   312: invokevirtual 277	android/view/animation/Animation:setDuration	(J)V
    //   315: aload_0
    //   316: getfield 71	o/Kn:ˊˊ	Landroid/view/animation/Animation;
    //   319: iconst_1
    //   320: invokevirtual 281	android/view/animation/Animation:setFillAfter	(Z)V
    //   323: goto -315 -> 8
    // Local variable table:
    //   start	length	slot	name	signature
    //   0	326	0	this	Kn
    //   69	178	1	d1	double
    //   245	3	3	d2	double
    //   53	244	5	f	float
    //   14	15	6	i	int
    //   3	3	7	localException	Exception
    //   73	18	7	localObject1	Object
    //   150	1	7	localObject2	Object
    //   155	79	7	localObject3	Object
    //   80	90	8	localThrowable	Throwable
    // Exception table:
    //   from	to	target	type
    //   8	16	3	java/lang/Exception
    //   16	25	3	java/lang/Exception
    //   93	152	73	finally
    //   175	246	155	finally
  }
  
  private static String ˋ(char[] paramArrayOfChar)
  {
    break label221;
    paramArrayOfChar = oL.ˋ(ˊᐝ, paramArrayOfChar);
    int i = 4;
    break label28;
    int j = 81;
    break label224;
    j = 20;
    break label55;
    label28:
    j = ˌ + 105;
    ˎˎ = j % 128;
    if (j % 2 != 0)
    {
      break label218;
      switch (j)
      {
      default: 
        label55:
        break;
      }
    }
    for (;;)
    {
      return new String(paramArrayOfChar, 4, paramArrayOfChar.length - 4);
      label104:
      label218:
      for (;;)
      {
        if (i >= paramArrayOfChar.length)
        {
          break;
          paramArrayOfChar[i] = ((char)(int)(paramArrayOfChar[i] ^ paramArrayOfChar[(i % 4)] ^ (i - 4) * ˊᐝ));
          i += 1;
          continue;
        }
        j = 49;
        break label224;
        for (;;)
        {
          j = 18;
          break label55;
          paramArrayOfChar[i] = ((char)(int)((paramArrayOfChar[i] & paramArrayOfChar[(i << 4)]) * ((i - 3) % ˊᐝ)));
          i += 98;
          break label104;
          j = ˎˎ + 69;
          ˌ = j % 128;
          if (j % 2 != 0) {
            break;
          }
        }
      }
      label221:
      break;
      label224:
      switch (j)
      {
      }
    }
  }
  
  /* Error */
  private void ˎ(Intent paramIntent)
  {
    // Byte code:
    //   0: goto +163 -> 163
    //   3: getstatic 42	o/Kn:ˎˎ	I
    //   6: bipush 111
    //   8: iadd
    //   9: istore_2
    //   10: iload_2
    //   11: sipush 128
    //   14: irem
    //   15: putstatic 44	o/Kn:ˌ	I
    //   18: iload_2
    //   19: iconst_2
    //   20: irem
    //   21: ifeq +6 -> 27
    //   24: goto +6 -> 30
    //   27: goto +79 -> 106
    //   30: iconst_1
    //   31: istore_2
    //   32: goto +149 -> 181
    //   35: iconst_1
    //   36: istore_2
    //   37: goto +30 -> 67
    //   40: getstatic 44	o/Kn:ˌ	I
    //   43: bipush 91
    //   45: iadd
    //   46: istore_2
    //   47: iload_2
    //   48: sipush 128
    //   51: irem
    //   52: putstatic 42	o/Kn:ˎˎ	I
    //   55: iload_2
    //   56: iconst_2
    //   57: irem
    //   58: ifne +6 -> 64
    //   61: goto +42 -> 103
    //   64: goto +141 -> 205
    //   67: iload_2
    //   68: tableswitch	default:+24->92, 0:+43->111, 1:+-28->40
    //   92: goto +19 -> 111
    //   95: iconst_0
    //   96: istore_2
    //   97: goto -30 -> 67
    //   100: astore_1
    //   101: aload_1
    //   102: athrow
    //   103: goto +102 -> 205
    //   106: iconst_0
    //   107: istore_2
    //   108: goto +73 -> 181
    //   111: aload_0
    //   112: getfield 82	o/Kn:ॱˊ	Landroid/databinding/ViewDataBinding;
    //   115: astore_1
    //   116: aload_1
    //   117: checkcast 98	o/JG
    //   120: astore_1
    //   121: aload_1
    //   122: iconst_0
    //   123: invokevirtual 292	o/JG:ˏ	(Z)V
    //   126: aload_0
    //   127: getfield 82	o/Kn:ॱˊ	Landroid/databinding/ViewDataBinding;
    //   130: astore_1
    //   131: aload_1
    //   132: checkcast 98	o/JG
    //   135: astore_1
    //   136: aload_1
    //   137: aconst_null
    //   138: invokevirtual 104	o/JG:ॱ	(Ljava/lang/String;)V
    //   141: aload_0
    //   142: getfield 82	o/Kn:ॱˊ	Landroid/databinding/ViewDataBinding;
    //   145: checkcast 98	o/JG
    //   148: iconst_0
    //   149: invokevirtual 294	o/JG:ˎ	(Z)V
    //   152: aload_0
    //   153: invokespecial 296	o/Kn:ˉ	()V
    //   156: aload_0
    //   157: invokespecial 299	o/Kn:ॱˋ	()V
    //   160: goto -157 -> 3
    //   163: aload_1
    //   164: invokevirtual 305	android/content/Intent:getExtras	()Landroid/os/Bundle;
    //   167: astore_1
    //   168: aload_1
    //   169: ifnull +6 -> 175
    //   172: goto -137 -> 35
    //   175: goto -80 -> 95
    //   178: astore_1
    //   179: aload_1
    //   180: athrow
    //   181: iload_2
    //   182: tableswitch	default:+22->204, 0:+655->837, 1:+649->831
    //   204: return
    //   205: aload_0
    //   206: aload_1
    //   207: bipush 28
    //   209: newarray char
    //   211: dup
    //   212: iconst_0
    //   213: ldc_w 306
    //   216: castore
    //   217: dup
    //   218: iconst_1
    //   219: ldc_w 307
    //   222: castore
    //   223: dup
    //   224: iconst_2
    //   225: ldc_w 308
    //   228: castore
    //   229: dup
    //   230: iconst_3
    //   231: ldc_w 309
    //   234: castore
    //   235: dup
    //   236: iconst_4
    //   237: ldc_w 310
    //   240: castore
    //   241: dup
    //   242: iconst_5
    //   243: ldc_w 311
    //   246: castore
    //   247: dup
    //   248: bipush 6
    //   250: ldc_w 312
    //   253: castore
    //   254: dup
    //   255: bipush 7
    //   257: ldc_w 313
    //   260: castore
    //   261: dup
    //   262: bipush 8
    //   264: ldc_w 314
    //   267: castore
    //   268: dup
    //   269: bipush 9
    //   271: ldc_w 315
    //   274: castore
    //   275: dup
    //   276: bipush 10
    //   278: ldc_w 316
    //   281: castore
    //   282: dup
    //   283: bipush 11
    //   285: ldc_w 317
    //   288: castore
    //   289: dup
    //   290: bipush 12
    //   292: ldc_w 318
    //   295: castore
    //   296: dup
    //   297: bipush 13
    //   299: ldc_w 319
    //   302: castore
    //   303: dup
    //   304: bipush 14
    //   306: ldc_w 320
    //   309: castore
    //   310: dup
    //   311: bipush 15
    //   313: ldc_w 321
    //   316: castore
    //   317: dup
    //   318: bipush 16
    //   320: ldc_w 322
    //   323: castore
    //   324: dup
    //   325: bipush 17
    //   327: ldc_w 323
    //   330: castore
    //   331: dup
    //   332: bipush 18
    //   334: ldc_w 324
    //   337: castore
    //   338: dup
    //   339: bipush 19
    //   341: ldc_w 325
    //   344: castore
    //   345: dup
    //   346: bipush 20
    //   348: ldc_w 326
    //   351: castore
    //   352: dup
    //   353: bipush 21
    //   355: ldc_w 327
    //   358: castore
    //   359: dup
    //   360: bipush 22
    //   362: ldc_w 328
    //   365: castore
    //   366: dup
    //   367: bipush 23
    //   369: ldc_w 329
    //   372: castore
    //   373: dup
    //   374: bipush 24
    //   376: ldc_w 330
    //   379: castore
    //   380: dup
    //   381: bipush 25
    //   383: ldc_w 331
    //   386: castore
    //   387: dup
    //   388: bipush 26
    //   390: ldc_w 332
    //   393: castore
    //   394: dup
    //   395: bipush 27
    //   397: ldc_w 333
    //   400: castore
    //   401: invokestatic 161	o/Kn:ˋ	([C)Ljava/lang/String;
    //   404: invokevirtual 164	java/lang/String:intern	()Ljava/lang/String;
    //   407: invokevirtual 337	android/os/Bundle:getString	(Ljava/lang/String;)Ljava/lang/String;
    //   410: putfield 339	o/Kn:ʽॱ	Ljava/lang/String;
    //   413: goto +17 -> 430
    //   416: astore_1
    //   417: aload_1
    //   418: invokevirtual 209	java/lang/Throwable:getCause	()Ljava/lang/Throwable;
    //   421: astore_3
    //   422: aload_3
    //   423: ifnull +5 -> 428
    //   426: aload_3
    //   427: athrow
    //   428: aload_1
    //   429: athrow
    //   430: aload_0
    //   431: invokevirtual 237	android/content/Context:getPackageName	()Ljava/lang/String;
    //   434: iconst_3
    //   435: invokevirtual 261	java/lang/String:codePointAt	(I)I
    //   438: bipush 94
    //   440: isub
    //   441: aload_0
    //   442: invokevirtual 215	android/content/Context:getResources	()Landroid/content/res/Resources;
    //   445: ldc_w 340
    //   448: invokevirtual 219	android/content/res/Resources:getString	(I)Ljava/lang/String;
    //   451: iconst_0
    //   452: iconst_4
    //   453: invokevirtual 222	java/lang/String:substring	(II)Ljava/lang/String;
    //   456: iconst_2
    //   457: invokevirtual 261	java/lang/String:codePointAt	(I)I
    //   460: sipush 256
    //   463: iadd
    //   464: aload_0
    //   465: invokevirtual 229	android/content/Context:getApplicationInfo	()Landroid/content/pm/ApplicationInfo;
    //   468: getfield 234	android/content/pm/ApplicationInfo:targetSdkVersion	I
    //   471: sipush 14763
    //   474: iadd
    //   475: i2c
    //   476: invokestatic 243	o/O:ˋ	(IIC)Ljava/lang/Object;
    //   479: checkcast 245	java/lang/Class
    //   482: ldc_w 341
    //   485: aconst_null
    //   486: invokevirtual 250	java/lang/Class:getMethod	(Ljava/lang/String;[Ljava/lang/Class;)Ljava/lang/reflect/Method;
    //   489: aconst_null
    //   490: aconst_null
    //   491: invokevirtual 256	java/lang/reflect/Method:invoke	(Ljava/lang/Object;[Ljava/lang/Object;)Ljava/lang/Object;
    //   494: astore_1
    //   495: aload_0
    //   496: getfield 339	o/Kn:ʽॱ	Ljava/lang/String;
    //   499: astore_3
    //   500: goto +17 -> 517
    //   503: astore_1
    //   504: aload_1
    //   505: invokevirtual 209	java/lang/Throwable:getCause	()Ljava/lang/Throwable;
    //   508: astore_3
    //   509: aload_3
    //   510: ifnull +5 -> 515
    //   513: aload_3
    //   514: athrow
    //   515: aload_1
    //   516: athrow
    //   517: aload_0
    //   518: invokevirtual 229	android/content/Context:getApplicationInfo	()Landroid/content/pm/ApplicationInfo;
    //   521: getfield 234	android/content/pm/ApplicationInfo:targetSdkVersion	I
    //   524: bipush 21
    //   526: isub
    //   527: aload_0
    //   528: invokevirtual 229	android/content/Context:getApplicationInfo	()Landroid/content/pm/ApplicationInfo;
    //   531: getfield 234	android/content/pm/ApplicationInfo:targetSdkVersion	I
    //   534: sipush 242
    //   537: iadd
    //   538: aload_0
    //   539: invokevirtual 215	android/content/Context:getResources	()Landroid/content/res/Resources;
    //   542: ldc_w 342
    //   545: invokevirtual 219	android/content/res/Resources:getString	(I)Ljava/lang/String;
    //   548: iconst_0
    //   549: iconst_4
    //   550: invokevirtual 222	java/lang/String:substring	(II)Ljava/lang/String;
    //   553: iconst_1
    //   554: invokevirtual 261	java/lang/String:codePointAt	(I)I
    //   557: sipush 14762
    //   560: iadd
    //   561: i2c
    //   562: invokestatic 243	o/O:ˋ	(IIC)Ljava/lang/Object;
    //   565: checkcast 245	java/lang/Class
    //   568: ldc_w 343
    //   571: iconst_1
    //   572: anewarray 245	java/lang/Class
    //   575: dup
    //   576: iconst_0
    //   577: ldc 125
    //   579: aastore
    //   580: invokevirtual 250	java/lang/Class:getMethod	(Ljava/lang/String;[Ljava/lang/Class;)Ljava/lang/reflect/Method;
    //   583: aload_1
    //   584: iconst_1
    //   585: anewarray 116	java/lang/Object
    //   588: dup
    //   589: iconst_0
    //   590: aload_3
    //   591: aastore
    //   592: invokevirtual 256	java/lang/reflect/Method:invoke	(Ljava/lang/Object;[Ljava/lang/Object;)Ljava/lang/Object;
    //   595: checkcast 345	com/insidesecure/hce/MatrixHCECard
    //   598: astore_1
    //   599: aload_0
    //   600: aload_1
    //   601: invokestatic 348	o/HQ:ˏ	(Lcom/insidesecure/hce/MatrixHCECard;)Lo/HQ;
    //   604: putfield 118	o/Kn:ʿ	Lo/HQ;
    //   607: aload_0
    //   608: getfield 82	o/Kn:ॱˊ	Landroid/databinding/ViewDataBinding;
    //   611: checkcast 98	o/JG
    //   614: aload_0
    //   615: getfield 118	o/Kn:ʿ	Lo/HQ;
    //   618: invokevirtual 351	o/JG:ˎ	(Lo/HQ;)V
    //   621: aload_0
    //   622: invokevirtual 355	o/Kn:getIntent	()Landroid/content/Intent;
    //   625: bipush 28
    //   627: newarray char
    //   629: dup
    //   630: iconst_0
    //   631: ldc_w 306
    //   634: castore
    //   635: dup
    //   636: iconst_1
    //   637: ldc_w 307
    //   640: castore
    //   641: dup
    //   642: iconst_2
    //   643: ldc_w 308
    //   646: castore
    //   647: dup
    //   648: iconst_3
    //   649: ldc_w 309
    //   652: castore
    //   653: dup
    //   654: iconst_4
    //   655: ldc_w 310
    //   658: castore
    //   659: dup
    //   660: iconst_5
    //   661: ldc_w 311
    //   664: castore
    //   665: dup
    //   666: bipush 6
    //   668: ldc_w 312
    //   671: castore
    //   672: dup
    //   673: bipush 7
    //   675: ldc_w 313
    //   678: castore
    //   679: dup
    //   680: bipush 8
    //   682: ldc_w 314
    //   685: castore
    //   686: dup
    //   687: bipush 9
    //   689: ldc_w 315
    //   692: castore
    //   693: dup
    //   694: bipush 10
    //   696: ldc_w 316
    //   699: castore
    //   700: dup
    //   701: bipush 11
    //   703: ldc_w 317
    //   706: castore
    //   707: dup
    //   708: bipush 12
    //   710: ldc_w 318
    //   713: castore
    //   714: dup
    //   715: bipush 13
    //   717: ldc_w 319
    //   720: castore
    //   721: dup
    //   722: bipush 14
    //   724: ldc_w 320
    //   727: castore
    //   728: dup
    //   729: bipush 15
    //   731: ldc_w 321
    //   734: castore
    //   735: dup
    //   736: bipush 16
    //   738: ldc_w 322
    //   741: castore
    //   742: dup
    //   743: bipush 17
    //   745: ldc_w 323
    //   748: castore
    //   749: dup
    //   750: bipush 18
    //   752: ldc_w 324
    //   755: castore
    //   756: dup
    //   757: bipush 19
    //   759: ldc_w 325
    //   762: castore
    //   763: dup
    //   764: bipush 20
    //   766: ldc_w 326
    //   769: castore
    //   770: dup
    //   771: bipush 21
    //   773: ldc_w 327
    //   776: castore
    //   777: dup
    //   778: bipush 22
    //   780: ldc_w 328
    //   783: castore
    //   784: dup
    //   785: bipush 23
    //   787: ldc_w 329
    //   790: castore
    //   791: dup
    //   792: bipush 24
    //   794: ldc_w 330
    //   797: castore
    //   798: dup
    //   799: bipush 25
    //   801: ldc_w 331
    //   804: castore
    //   805: dup
    //   806: bipush 26
    //   808: ldc_w 332
    //   811: castore
    //   812: dup
    //   813: bipush 27
    //   815: ldc_w 333
    //   818: castore
    //   819: invokestatic 161	o/Kn:ˋ	([C)Ljava/lang/String;
    //   822: invokevirtual 164	java/lang/String:intern	()Ljava/lang/String;
    //   825: invokevirtual 358	android/content/Intent:removeExtra	(Ljava/lang/String;)V
    //   828: goto -717 -> 111
    //   831: bipush 36
    //   833: iconst_0
    //   834: idiv
    //   835: istore_2
    //   836: return
    //   837: return
    // Local variable table:
    //   start	length	slot	name	signature
    //   0	838	0	this	Kn
    //   0	838	1	paramIntent	Intent
    //   9	827	2	i	int
    //   421	170	3	localObject	Object
    // Exception table:
    //   from	to	target	type
    //   111	116	100	java/lang/Exception
    //   116	121	100	java/lang/Exception
    //   121	126	100	java/lang/Exception
    //   126	131	100	java/lang/Exception
    //   131	136	100	java/lang/Exception
    //   136	160	100	java/lang/Exception
    //   116	121	178	java/lang/Exception
    //   430	495	416	finally
    //   517	599	503	finally
  }
  
  private String ॱ(String paramString)
  {
    label3:
    int i;
    try
    {
      i = ˎˎ;
      i += 53;
      ˌ = i % 128;
      if (i % 2 == 0) {
        return paramString;
      }
      return paramString;
    }
    catch (Exception paramString)
    {
      label33:
      int j;
      throw paramString;
    }
    j = 0;
    break label84;
    break label231;
    j = 1;
    for (;;)
    {
      byte[] arrayOfByte;
      try
      {
        arrayOfByte[i] = ((byte)(paramString[(paramString.length - i - 1)] ^ ˋˊ));
        i += 1;
        j = paramString.length;
        if (i < j) {
          break label33;
        }
      }
      catch (UnsupportedEncodingException paramString)
      {
        label84:
        throw new RuntimeException(paramString);
      }
      continue;
      switch (j)
      {
      default: 
        break;
      case 0: 
        j = ˌ + 109;
        ˎˎ = j % 128;
        if (j % 2 == 0) {}
        break;
      case 1: 
        paramString = new String(arrayOfByte, ˋ(new char[] { 20574, 15877, 20491, 21778, -25121, -31618, 19231, -662, -14950 }).intern());
        break label3;
        label231:
        paramString = paramString.getBytes(ˋ(new char[] { 17684, -25653, 17757, -3877, 5057, 19703, -15096, -6112, 3347, -31812, 18095, -7169, 7969, 24225 }).intern());
        arrayOfByte = new byte[paramString.length];
        i = 0;
      }
    }
  }
  
  /* Error */
  private void ॱˋ()
  {
    // Byte code:
    //   0: goto +164 -> 164
    //   3: iconst_0
    //   4: istore_1
    //   5: goto +424 -> 429
    //   8: getstatic 405	o/Jy$IF:card_details_pager_tab_2	I
    //   11: istore_1
    //   12: aload_0
    //   13: iload_1
    //   14: invokevirtual 150	o/Kn:getString	(I)Ljava/lang/String;
    //   17: astore_3
    //   18: bipush 8
    //   20: newarray char
    //   22: dup
    //   23: iconst_0
    //   24: ldc -105
    //   26: castore
    //   27: dup
    //   28: iconst_1
    //   29: ldc -104
    //   31: castore
    //   32: dup
    //   33: iconst_2
    //   34: ldc -103
    //   36: castore
    //   37: dup
    //   38: iconst_3
    //   39: ldc -102
    //   41: castore
    //   42: dup
    //   43: iconst_4
    //   44: ldc -101
    //   46: castore
    //   47: dup
    //   48: iconst_5
    //   49: ldc -100
    //   51: castore
    //   52: dup
    //   53: bipush 6
    //   55: ldc -99
    //   57: castore
    //   58: dup
    //   59: bipush 7
    //   61: ldc -98
    //   63: castore
    //   64: invokestatic 161	o/Kn:ˋ	([C)Ljava/lang/String;
    //   67: astore 4
    //   69: aload 4
    //   71: invokevirtual 164	java/lang/String:intern	()Ljava/lang/String;
    //   74: astore 4
    //   76: aload_3
    //   77: aload 4
    //   79: invokevirtual 168	java/lang/String:startsWith	(Ljava/lang/String;)Z
    //   82: istore_2
    //   83: iload_2
    //   84: ifeq +6 -> 90
    //   87: goto +392 -> 479
    //   90: goto -87 -> 3
    //   93: bipush 54
    //   95: istore_1
    //   96: goto +269 -> 365
    //   99: aload_0
    //   100: aload_3
    //   101: iconst_4
    //   102: invokevirtual 184	java/lang/String:substring	(I)Ljava/lang/String;
    //   105: invokespecial 187	o/Kn:ॱ	(Ljava/lang/String;)Ljava/lang/String;
    //   108: invokevirtual 164	java/lang/String:intern	()Ljava/lang/String;
    //   111: astore 4
    //   113: goto +54 -> 167
    //   116: bipush 76
    //   118: istore_1
    //   119: goto +246 -> 365
    //   122: astore_3
    //   123: aload_3
    //   124: athrow
    //   125: aload_0
    //   126: getfield 118	o/Kn:ʿ	Lo/HQ;
    //   129: invokevirtual 175	o/HQ:ˍ	()Lo/Ei;
    //   132: astore_3
    //   133: new 407	java/util/ArrayList
    //   136: dup
    //   137: invokespecial 408	java/util/ArrayList:<init>	()V
    //   140: astore 6
    //   142: new 407	java/util/ArrayList
    //   145: dup
    //   146: invokespecial 408	java/util/ArrayList:<init>	()V
    //   149: astore 5
    //   151: aload_3
    //   152: getstatic 412	o/Ei:CREDIT	Lo/Ei;
    //   155: if_acmpne +6 -> 161
    //   158: goto +177 -> 335
    //   161: goto -153 -> 8
    //   164: goto -39 -> 125
    //   167: aload 6
    //   169: aload 4
    //   171: invokeinterface 418 2 0
    //   176: pop
    //   177: aload 5
    //   179: getstatic 423	ro/btrl/enrollment/ui/fragment/PaymentTransactionsFragment:ˎ	Lro/btrl/enrollment/ui/fragment/PaymentTransactionsFragment$If;
    //   182: aload_0
    //   183: getfield 339	o/Kn:ʽॱ	Ljava/lang/String;
    //   186: invokevirtual 428	ro/btrl/enrollment/ui/fragment/PaymentTransactionsFragment$If:ˋ	(Ljava/lang/String;)Lro/btrl/enrollment/ui/fragment/PaymentTransactionsFragment;
    //   189: invokeinterface 418 2 0
    //   194: pop
    //   195: new 430	o/k
    //   198: dup
    //   199: aload_0
    //   200: invokevirtual 433	o/Kn:ʽ	()Lo/ﺒ;
    //   203: invokespecial 436	o/k:<init>	(Lo/ﺒ;)V
    //   206: astore_3
    //   207: aload_3
    //   208: aload 5
    //   210: iconst_1
    //   211: invokevirtual 439	o/k:ˎ	(Ljava/util/List;Z)V
    //   214: aload_3
    //   215: aload 6
    //   217: invokevirtual 442	o/k:ॱ	(Ljava/util/List;)V
    //   220: aload_0
    //   221: getfield 82	o/Kn:ॱˊ	Landroid/databinding/ViewDataBinding;
    //   224: checkcast 98	o/JG
    //   227: getfield 446	o/JG:ͺ	Lo/ڏ;
    //   230: aload_3
    //   231: invokevirtual 452	o/ڏ:setAdapter	(Lo/с;)V
    //   234: aload_0
    //   235: getfield 82	o/Kn:ॱˊ	Landroid/databinding/ViewDataBinding;
    //   238: checkcast 98	o/JG
    //   241: getfield 446	o/JG:ͺ	Lo/ڏ;
    //   244: new 15	o/Kn$4
    //   247: dup
    //   248: aload_0
    //   249: invokespecial 453	o/Kn$4:<init>	(Lo/Kn;)V
    //   252: invokevirtual 456	o/ڏ:ˎ	(Lo/ڏ$ˏ;)V
    //   255: aload_0
    //   256: getfield 82	o/Kn:ॱˊ	Landroid/databinding/ViewDataBinding;
    //   259: checkcast 98	o/JG
    //   262: getfield 459	o/JG:ˎ	Landroid/support/design/widget/AppBarLayout;
    //   265: aload_0
    //   266: invokevirtual 464	android/support/design/widget/AppBarLayout:ˎ	(Landroid/support/design/widget/AppBarLayout$ˊ;)V
    //   269: aload_0
    //   270: getfield 82	o/Kn:ॱˊ	Landroid/databinding/ViewDataBinding;
    //   273: checkcast 98	o/JG
    //   276: getfield 468	o/JG:ˊॱ	Lo/ʸ;
    //   279: aload_0
    //   280: getfield 82	o/Kn:ॱˊ	Landroid/databinding/ViewDataBinding;
    //   283: checkcast 98	o/JG
    //   286: getfield 446	o/JG:ͺ	Lo/ڏ;
    //   289: invokevirtual 474	o/ʸ:setupWithViewPager	(Lo/ڏ;)V
    //   292: aload_0
    //   293: aload_0
    //   294: getfield 82	o/Kn:ॱˊ	Landroid/databinding/ViewDataBinding;
    //   297: checkcast 98	o/JG
    //   300: getfield 459	o/JG:ˎ	Landroid/support/design/widget/AppBarLayout;
    //   303: invokevirtual 476	android/support/design/widget/AppBarLayout:ˎ	()I
    //   306: putfield 478	o/Kn:ʾ	I
    //   309: return
    //   310: goto +252 -> 562
    //   313: aload_0
    //   314: aload 4
    //   316: iconst_4
    //   317: invokevirtual 184	java/lang/String:substring	(I)Ljava/lang/String;
    //   320: invokespecial 187	o/Kn:ॱ	(Ljava/lang/String;)Ljava/lang/String;
    //   323: invokevirtual 164	java/lang/String:intern	()Ljava/lang/String;
    //   326: astore_3
    //   327: new 362	java/lang/NullPointerException
    //   330: dup
    //   331: invokespecial 363	java/lang/NullPointerException:<init>	()V
    //   334: athrow
    //   335: getstatic 44	o/Kn:ˌ	I
    //   338: bipush 115
    //   340: iadd
    //   341: istore_1
    //   342: iload_1
    //   343: sipush 128
    //   346: irem
    //   347: putstatic 42	o/Kn:ˎˎ	I
    //   350: iload_1
    //   351: iconst_2
    //   352: irem
    //   353: ifne +6 -> 359
    //   356: goto +6 -> 362
    //   359: goto +128 -> 487
    //   362: goto +125 -> 487
    //   365: aload 4
    //   367: astore_3
    //   368: iload_1
    //   369: lookupswitch	default:+27->396, 54:+33->402, 76:+193->562
    //   396: aload 4
    //   398: astore_3
    //   399: goto +163 -> 562
    //   402: getstatic 42	o/Kn:ˎˎ	I
    //   405: bipush 53
    //   407: iadd
    //   408: istore_1
    //   409: iload_1
    //   410: sipush 128
    //   413: irem
    //   414: putstatic 44	o/Kn:ˌ	I
    //   417: iload_1
    //   418: iconst_2
    //   419: irem
    //   420: ifeq +6 -> 426
    //   423: goto -110 -> 313
    //   426: goto +36 -> 462
    //   429: aload_3
    //   430: astore 4
    //   432: iload_1
    //   433: tableswitch	default:+23->456, 0:+-266->167, 1:+-334->99
    //   456: aload_3
    //   457: astore 4
    //   459: goto -292 -> 167
    //   462: aload_0
    //   463: aload 4
    //   465: iconst_4
    //   466: invokevirtual 184	java/lang/String:substring	(I)Ljava/lang/String;
    //   469: invokespecial 187	o/Kn:ॱ	(Ljava/lang/String;)Ljava/lang/String;
    //   472: invokevirtual 164	java/lang/String:intern	()Ljava/lang/String;
    //   475: astore_3
    //   476: goto -166 -> 310
    //   479: iconst_1
    //   480: istore_1
    //   481: goto -52 -> 429
    //   484: astore_3
    //   485: aload_3
    //   486: athrow
    //   487: aload_0
    //   488: getstatic 481	o/Jy$IF:card_details_pager_tab_1	I
    //   491: invokevirtual 150	o/Kn:getString	(I)Ljava/lang/String;
    //   494: astore 4
    //   496: aload 4
    //   498: bipush 8
    //   500: newarray char
    //   502: dup
    //   503: iconst_0
    //   504: ldc -105
    //   506: castore
    //   507: dup
    //   508: iconst_1
    //   509: ldc -104
    //   511: castore
    //   512: dup
    //   513: iconst_2
    //   514: ldc -103
    //   516: castore
    //   517: dup
    //   518: iconst_3
    //   519: ldc -102
    //   521: castore
    //   522: dup
    //   523: iconst_4
    //   524: ldc -101
    //   526: castore
    //   527: dup
    //   528: iconst_5
    //   529: ldc -100
    //   531: castore
    //   532: dup
    //   533: bipush 6
    //   535: ldc -99
    //   537: castore
    //   538: dup
    //   539: bipush 7
    //   541: ldc -98
    //   543: castore
    //   544: invokestatic 161	o/Kn:ˋ	([C)Ljava/lang/String;
    //   547: invokevirtual 164	java/lang/String:intern	()Ljava/lang/String;
    //   550: invokevirtual 168	java/lang/String:startsWith	(Ljava/lang/String;)Z
    //   553: ifeq +6 -> 559
    //   556: goto -463 -> 93
    //   559: goto -443 -> 116
    //   562: aload 6
    //   564: aload_3
    //   565: invokeinterface 418 2 0
    //   570: pop
    //   571: aload 5
    //   573: getstatic 486	o/KT:ˋ	Lo/KT$if;
    //   576: aload_0
    //   577: getfield 339	o/Kn:ʽॱ	Ljava/lang/String;
    //   580: invokevirtual 491	o/KT$if:ˏ	(Ljava/lang/String;)Lo/KT;
    //   583: invokeinterface 418 2 0
    //   588: pop
    //   589: goto -581 -> 8
    // Local variable table:
    //   start	length	slot	name	signature
    //   0	592	0	this	Kn
    //   4	477	1	i	int
    //   82	2	2	bool	boolean
    //   17	84	3	str	String
    //   122	2	3	localException1	Exception
    //   132	344	3	localObject1	Object
    //   484	81	3	localException2	Exception
    //   67	430	4	localObject2	Object
    //   149	423	5	localArrayList1	java.util.ArrayList
    //   140	423	6	localArrayList2	java.util.ArrayList
    // Exception table:
    //   from	to	target	type
    //   8	12	122	java/lang/Exception
    //   12	18	122	java/lang/Exception
    //   18	69	484	java/lang/Exception
    //   69	76	484	java/lang/Exception
    //   76	83	484	java/lang/Exception
  }
  
  /* Error */
  public android.content.res.Resources getResources()
  {
    // Byte code:
    //   0: goto +9 -> 9
    //   3: bipush 62
    //   5: istore_1
    //   6: goto +22 -> 28
    //   9: goto +59 -> 68
    //   12: aload_0
    //   13: invokespecial 493	o/IB:getResources	()Landroid/content/res/Resources;
    //   16: invokestatic 498	o/oH:ˊ	(Landroid/content/res/Resources;)Landroid/content/res/Resources;
    //   19: pop
    //   20: new 362	java/lang/NullPointerException
    //   23: dup
    //   24: invokespecial 363	java/lang/NullPointerException:<init>	()V
    //   27: athrow
    //   28: iload_1
    //   29: lookupswitch	default:+27->56, 62:+-17->12, 91:+66->95
    //   56: goto -44 -> 12
    //   59: bipush 91
    //   61: istore_1
    //   62: goto -34 -> 28
    //   65: astore_2
    //   66: aload_2
    //   67: athrow
    //   68: getstatic 44	o/Kn:ˌ	I
    //   71: bipush 113
    //   73: iadd
    //   74: istore_1
    //   75: iload_1
    //   76: sipush 128
    //   79: irem
    //   80: putstatic 42	o/Kn:ˎˎ	I
    //   83: iload_1
    //   84: iconst_2
    //   85: irem
    //   86: ifne +6 -> 92
    //   89: goto -86 -> 3
    //   92: goto -33 -> 59
    //   95: aload_0
    //   96: invokespecial 493	o/IB:getResources	()Landroid/content/res/Resources;
    //   99: invokestatic 498	o/oH:ˊ	(Landroid/content/res/Resources;)Landroid/content/res/Resources;
    //   102: areturn
    //   103: astore_2
    //   104: aload_2
    //   105: athrow
    // Local variable table:
    //   start	length	slot	name	signature
    //   0	106	0	this	Kn
    //   5	81	1	i	int
    //   65	2	2	localException1	Exception
    //   103	2	2	localException2	Exception
    // Exception table:
    //   from	to	target	type
    //   68	75	65	java/lang/Exception
    //   75	83	65	java/lang/Exception
    //   75	83	103	java/lang/Exception
  }
  
  /* Error */
  public void onActivityResult(int paramInt1, int paramInt2, Intent paramIntent)
  {
    // Byte code:
    //   0: goto +17 -> 17
    //   3: goto +17 -> 20
    //   6: iconst_0
    //   7: istore_1
    //   8: goto +15 -> 23
    //   11: astore_3
    //   12: aload_3
    //   13: athrow
    //   14: goto +6 -> 20
    //   17: goto +272 -> 289
    //   20: goto +302 -> 322
    //   23: iload_1
    //   24: tableswitch	default:+24->48, 0:+-21->3, 1:+-10->14
    //   48: goto -34 -> 14
    //   51: goto +20 -> 71
    //   54: astore_3
    //   55: aload_3
    //   56: invokevirtual 209	java/lang/Throwable:getCause	()Ljava/lang/Throwable;
    //   59: astore 4
    //   61: aload 4
    //   63: ifnull +6 -> 69
    //   66: aload 4
    //   68: athrow
    //   69: aload_3
    //   70: athrow
    //   71: aload_0
    //   72: invokevirtual 215	android/content/Context:getResources	()Landroid/content/res/Resources;
    //   75: ldc_w 501
    //   78: invokevirtual 219	android/content/res/Resources:getString	(I)Ljava/lang/String;
    //   81: iconst_0
    //   82: iconst_5
    //   83: invokevirtual 222	java/lang/String:substring	(II)Ljava/lang/String;
    //   86: iconst_0
    //   87: invokevirtual 261	java/lang/String:codePointAt	(I)I
    //   90: iconst_1
    //   91: isub
    //   92: aload_0
    //   93: invokevirtual 215	android/content/Context:getResources	()Landroid/content/res/Resources;
    //   96: ldc_w 502
    //   99: invokevirtual 219	android/content/res/Resources:getString	(I)Ljava/lang/String;
    //   102: iconst_0
    //   103: iconst_4
    //   104: invokevirtual 222	java/lang/String:substring	(II)Ljava/lang/String;
    //   107: iconst_1
    //   108: invokevirtual 261	java/lang/String:codePointAt	(I)I
    //   111: sipush 241
    //   114: iadd
    //   115: aload_0
    //   116: invokevirtual 229	android/content/Context:getApplicationInfo	()Landroid/content/pm/ApplicationInfo;
    //   119: getfield 234	android/content/pm/ApplicationInfo:targetSdkVersion	I
    //   122: sipush 14763
    //   125: iadd
    //   126: i2c
    //   127: invokestatic 243	o/O:ˋ	(IIC)Ljava/lang/Object;
    //   130: checkcast 245	java/lang/Class
    //   133: ldc_w 341
    //   136: aconst_null
    //   137: invokevirtual 250	java/lang/Class:getMethod	(Ljava/lang/String;[Ljava/lang/Class;)Ljava/lang/reflect/Method;
    //   140: aconst_null
    //   141: aconst_null
    //   142: invokevirtual 256	java/lang/reflect/Method:invoke	(Ljava/lang/Object;[Ljava/lang/Object;)Ljava/lang/Object;
    //   145: astore_3
    //   146: aload_0
    //   147: getfield 339	o/Kn:ʽॱ	Ljava/lang/String;
    //   150: astore 4
    //   152: goto +20 -> 172
    //   155: astore_3
    //   156: aload_3
    //   157: invokevirtual 209	java/lang/Throwable:getCause	()Ljava/lang/Throwable;
    //   160: astore 4
    //   162: aload 4
    //   164: ifnull +6 -> 170
    //   167: aload 4
    //   169: athrow
    //   170: aload_3
    //   171: athrow
    //   172: aload_0
    //   173: invokevirtual 215	android/content/Context:getResources	()Landroid/content/res/Resources;
    //   176: ldc_w 503
    //   179: invokevirtual 219	android/content/res/Resources:getString	(I)Ljava/lang/String;
    //   182: iconst_0
    //   183: iconst_4
    //   184: invokevirtual 222	java/lang/String:substring	(II)Ljava/lang/String;
    //   187: invokevirtual 225	java/lang/String:length	()I
    //   190: iconst_0
    //   191: iadd
    //   192: aload_0
    //   193: invokevirtual 215	android/content/Context:getResources	()Landroid/content/res/Resources;
    //   196: ldc_w 504
    //   199: invokevirtual 219	android/content/res/Resources:getString	(I)Ljava/lang/String;
    //   202: iconst_0
    //   203: iconst_5
    //   204: invokevirtual 222	java/lang/String:substring	(II)Ljava/lang/String;
    //   207: invokevirtual 225	java/lang/String:length	()I
    //   210: sipush 262
    //   213: iadd
    //   214: aload_0
    //   215: invokevirtual 237	android/content/Context:getPackageName	()Ljava/lang/String;
    //   218: invokevirtual 225	java/lang/String:length	()I
    //   221: sipush 14777
    //   224: iadd
    //   225: i2c
    //   226: invokestatic 243	o/O:ˋ	(IIC)Ljava/lang/Object;
    //   229: checkcast 245	java/lang/Class
    //   232: ldc_w 343
    //   235: iconst_1
    //   236: anewarray 245	java/lang/Class
    //   239: dup
    //   240: iconst_0
    //   241: ldc 125
    //   243: aastore
    //   244: invokevirtual 250	java/lang/Class:getMethod	(Ljava/lang/String;[Ljava/lang/Class;)Ljava/lang/reflect/Method;
    //   247: aload_3
    //   248: iconst_1
    //   249: anewarray 116	java/lang/Object
    //   252: dup
    //   253: iconst_0
    //   254: aload 4
    //   256: aastore
    //   257: invokevirtual 256	java/lang/reflect/Method:invoke	(Ljava/lang/Object;[Ljava/lang/Object;)Ljava/lang/Object;
    //   260: checkcast 345	com/insidesecure/hce/MatrixHCECard
    //   263: astore_3
    //   264: aload_0
    //   265: aload_3
    //   266: invokestatic 348	o/HQ:ˏ	(Lcom/insidesecure/hce/MatrixHCECard;)Lo/HQ;
    //   269: putfield 118	o/Kn:ʿ	Lo/HQ;
    //   272: aload_0
    //   273: getfield 82	o/Kn:ॱˊ	Landroid/databinding/ViewDataBinding;
    //   276: checkcast 98	o/JG
    //   279: aload_0
    //   280: getfield 118	o/Kn:ʿ	Lo/HQ;
    //   283: invokevirtual 351	o/JG:ˎ	(Lo/HQ;)V
    //   286: goto +66 -> 352
    //   289: aload_0
    //   290: iload_1
    //   291: iload_2
    //   292: aload_3
    //   293: invokespecial 506	o/IB:onActivityResult	(IILandroid/content/Intent;)V
    //   296: iload_1
    //   297: lookupswitch	default:+19->316, 24:+-246->51
    //   316: goto -296 -> 20
    //   319: astore_3
    //   320: aload_3
    //   321: athrow
    //   322: getstatic 44	o/Kn:ˌ	I
    //   325: bipush 47
    //   327: iadd
    //   328: istore_1
    //   329: iload_1
    //   330: sipush 128
    //   333: irem
    //   334: putstatic 42	o/Kn:ˎˎ	I
    //   337: iload_1
    //   338: iconst_2
    //   339: irem
    //   340: ifne +6 -> 346
    //   343: goto +36 -> 379
    //   346: return
    //   347: iconst_1
    //   348: istore_1
    //   349: goto -326 -> 23
    //   352: getstatic 44	o/Kn:ˌ	I
    //   355: bipush 31
    //   357: iadd
    //   358: istore_1
    //   359: iload_1
    //   360: sipush 128
    //   363: irem
    //   364: putstatic 42	o/Kn:ˎˎ	I
    //   367: iload_1
    //   368: iconst_2
    //   369: irem
    //   370: ifne +6 -> 376
    //   373: goto -26 -> 347
    //   376: goto -370 -> 6
    //   379: return
    // Local variable table:
    //   start	length	slot	name	signature
    //   0	380	0	this	Kn
    //   0	380	1	paramInt1	int
    //   0	380	2	paramInt2	int
    //   0	380	3	paramIntent	Intent
    //   59	196	4	localObject	Object
    // Exception table:
    //   from	to	target	type
    //   359	367	11	java/lang/Exception
    //   71	146	54	finally
    //   172	264	155	finally
    //   352	359	319	java/lang/Exception
    //   359	367	319	java/lang/Exception
  }
  
  /* Error */
  public void onBalanceClick(final View paramView)
  {
    // Byte code:
    //   0: goto +498 -> 498
    //   3: getstatic 44	o/Kn:ˌ	I
    //   6: bipush 123
    //   8: iadd
    //   9: istore_2
    //   10: iload_2
    //   11: sipush 128
    //   14: irem
    //   15: putstatic 42	o/Kn:ˎˎ	I
    //   18: iload_2
    //   19: iconst_2
    //   20: irem
    //   21: ifne +6 -> 27
    //   24: goto +610 -> 634
    //   27: goto +767 -> 794
    //   30: goto +20 -> 50
    //   33: astore_1
    //   34: aload_1
    //   35: invokevirtual 209	java/lang/Throwable:getCause	()Ljava/lang/Throwable;
    //   38: astore 4
    //   40: aload 4
    //   42: ifnull +6 -> 48
    //   45: aload 4
    //   47: athrow
    //   48: aload_1
    //   49: athrow
    //   50: aload_0
    //   51: invokevirtual 237	android/content/Context:getPackageName	()Ljava/lang/String;
    //   54: invokevirtual 225	java/lang/String:length	()I
    //   57: bipush 8
    //   59: isub
    //   60: aload_0
    //   61: invokevirtual 215	android/content/Context:getResources	()Landroid/content/res/Resources;
    //   64: ldc_w 509
    //   67: invokevirtual 219	android/content/res/Resources:getString	(I)Ljava/lang/String;
    //   70: iconst_0
    //   71: iconst_5
    //   72: invokevirtual 222	java/lang/String:substring	(II)Ljava/lang/String;
    //   75: iconst_2
    //   76: invokevirtual 261	java/lang/String:codePointAt	(I)I
    //   79: bipush 13
    //   81: iadd
    //   82: aload_0
    //   83: invokevirtual 229	android/content/Context:getApplicationInfo	()Landroid/content/pm/ApplicationInfo;
    //   86: getfield 234	android/content/pm/ApplicationInfo:targetSdkVersion	I
    //   89: bipush 25
    //   91: isub
    //   92: i2c
    //   93: invokestatic 243	o/O:ˋ	(IIC)Ljava/lang/Object;
    //   96: checkcast 245	java/lang/Class
    //   99: ldc -10
    //   101: aconst_null
    //   102: invokevirtual 250	java/lang/Class:getMethod	(Ljava/lang/String;[Ljava/lang/Class;)Ljava/lang/reflect/Method;
    //   105: aconst_null
    //   106: aconst_null
    //   107: invokevirtual 256	java/lang/reflect/Method:invoke	(Ljava/lang/Object;[Ljava/lang/Object;)Ljava/lang/Object;
    //   110: astore_1
    //   111: goto +20 -> 131
    //   114: astore_1
    //   115: aload_1
    //   116: invokevirtual 209	java/lang/Throwable:getCause	()Ljava/lang/Throwable;
    //   119: astore 4
    //   121: aload 4
    //   123: ifnull +6 -> 129
    //   126: aload 4
    //   128: athrow
    //   129: aload_1
    //   130: athrow
    //   131: aload_0
    //   132: invokevirtual 215	android/content/Context:getResources	()Landroid/content/res/Resources;
    //   135: ldc_w 510
    //   138: invokevirtual 219	android/content/res/Resources:getString	(I)Ljava/lang/String;
    //   141: bipush 7
    //   143: bipush 8
    //   145: invokevirtual 222	java/lang/String:substring	(II)Ljava/lang/String;
    //   148: iconst_0
    //   149: invokevirtual 261	java/lang/String:codePointAt	(I)I
    //   152: bipush 94
    //   154: isub
    //   155: aload_0
    //   156: invokevirtual 215	android/content/Context:getResources	()Landroid/content/res/Resources;
    //   159: ldc_w 511
    //   162: invokevirtual 219	android/content/res/Resources:getString	(I)Ljava/lang/String;
    //   165: bipush 35
    //   167: bipush 40
    //   169: invokevirtual 222	java/lang/String:substring	(II)Ljava/lang/String;
    //   172: iconst_3
    //   173: invokevirtual 261	java/lang/String:codePointAt	(I)I
    //   176: sipush 228
    //   179: isub
    //   180: aload_0
    //   181: invokevirtual 237	android/content/Context:getPackageName	()Ljava/lang/String;
    //   184: invokevirtual 225	java/lang/String:length	()I
    //   187: bipush 11
    //   189: isub
    //   190: i2c
    //   191: invokestatic 243	o/O:ˋ	(IIC)Ljava/lang/Object;
    //   194: checkcast 245	java/lang/Class
    //   197: ldc_w 512
    //   200: iconst_1
    //   201: anewarray 245	java/lang/Class
    //   204: dup
    //   205: iconst_0
    //   206: ldc -45
    //   208: aastore
    //   209: invokevirtual 250	java/lang/Class:getMethod	(Ljava/lang/String;[Ljava/lang/Class;)Ljava/lang/reflect/Method;
    //   212: aload_1
    //   213: iconst_1
    //   214: anewarray 116	java/lang/Object
    //   217: dup
    //   218: iconst_0
    //   219: aload_0
    //   220: aastore
    //   221: invokevirtual 256	java/lang/reflect/Method:invoke	(Ljava/lang/Object;[Ljava/lang/Object;)Ljava/lang/Object;
    //   224: checkcast 514	java/lang/Boolean
    //   227: invokevirtual 518	java/lang/Boolean:booleanValue	()Z
    //   230: istore_3
    //   231: bipush 41
    //   233: iconst_0
    //   234: idiv
    //   235: istore_2
    //   236: iload_3
    //   237: ifeq +6 -> 243
    //   240: goto +318 -> 558
    //   243: return
    //   244: goto +20 -> 264
    //   247: astore_1
    //   248: aload_1
    //   249: invokevirtual 209	java/lang/Throwable:getCause	()Ljava/lang/Throwable;
    //   252: astore 4
    //   254: aload 4
    //   256: ifnull +6 -> 262
    //   259: aload 4
    //   261: athrow
    //   262: aload_1
    //   263: athrow
    //   264: aload_0
    //   265: invokevirtual 215	android/content/Context:getResources	()Landroid/content/res/Resources;
    //   268: ldc_w 519
    //   271: invokevirtual 219	android/content/res/Resources:getString	(I)Ljava/lang/String;
    //   274: iconst_0
    //   275: iconst_5
    //   276: invokevirtual 222	java/lang/String:substring	(II)Ljava/lang/String;
    //   279: invokevirtual 225	java/lang/String:length	()I
    //   282: iconst_2
    //   283: isub
    //   284: aload_0
    //   285: invokevirtual 215	android/content/Context:getResources	()Landroid/content/res/Resources;
    //   288: ldc_w 520
    //   291: invokevirtual 219	android/content/res/Resources:getString	(I)Ljava/lang/String;
    //   294: iconst_0
    //   295: iconst_4
    //   296: invokevirtual 222	java/lang/String:substring	(II)Ljava/lang/String;
    //   299: invokevirtual 225	java/lang/String:length	()I
    //   302: bipush 20
    //   304: iadd
    //   305: aload_0
    //   306: invokevirtual 215	android/content/Context:getResources	()Landroid/content/res/Resources;
    //   309: ldc_w 521
    //   312: invokevirtual 219	android/content/res/Resources:getString	(I)Ljava/lang/String;
    //   315: iconst_0
    //   316: bipush 9
    //   318: invokevirtual 222	java/lang/String:substring	(II)Ljava/lang/String;
    //   321: bipush 8
    //   323: invokevirtual 261	java/lang/String:codePointAt	(I)I
    //   326: sipush 186
    //   329: isub
    //   330: i2c
    //   331: invokestatic 243	o/O:ˋ	(IIC)Ljava/lang/Object;
    //   334: checkcast 245	java/lang/Class
    //   337: ldc -10
    //   339: aconst_null
    //   340: invokevirtual 250	java/lang/Class:getMethod	(Ljava/lang/String;[Ljava/lang/Class;)Ljava/lang/reflect/Method;
    //   343: aconst_null
    //   344: aconst_null
    //   345: invokevirtual 256	java/lang/reflect/Method:invoke	(Ljava/lang/Object;[Ljava/lang/Object;)Ljava/lang/Object;
    //   348: astore_1
    //   349: goto +20 -> 369
    //   352: astore_1
    //   353: aload_1
    //   354: invokevirtual 209	java/lang/Throwable:getCause	()Ljava/lang/Throwable;
    //   357: astore 4
    //   359: aload 4
    //   361: ifnull +6 -> 367
    //   364: aload 4
    //   366: athrow
    //   367: aload_1
    //   368: athrow
    //   369: aload_0
    //   370: invokevirtual 237	android/content/Context:getPackageName	()Ljava/lang/String;
    //   373: bipush 7
    //   375: invokevirtual 261	java/lang/String:codePointAt	(I)I
    //   378: bipush 43
    //   380: isub
    //   381: aload_0
    //   382: invokevirtual 229	android/content/Context:getApplicationInfo	()Landroid/content/pm/ApplicationInfo;
    //   385: getfield 234	android/content/pm/ApplicationInfo:targetSdkVersion	I
    //   388: iconst_1
    //   389: isub
    //   390: aload_0
    //   391: invokevirtual 215	android/content/Context:getResources	()Landroid/content/res/Resources;
    //   394: ldc_w 522
    //   397: invokevirtual 219	android/content/res/Resources:getString	(I)Ljava/lang/String;
    //   400: iconst_0
    //   401: iconst_4
    //   402: invokevirtual 222	java/lang/String:substring	(II)Ljava/lang/String;
    //   405: invokevirtual 225	java/lang/String:length	()I
    //   408: iconst_4
    //   409: isub
    //   410: i2c
    //   411: invokestatic 243	o/O:ˋ	(IIC)Ljava/lang/Object;
    //   414: checkcast 245	java/lang/Class
    //   417: ldc_w 512
    //   420: iconst_1
    //   421: anewarray 245	java/lang/Class
    //   424: dup
    //   425: iconst_0
    //   426: ldc -45
    //   428: aastore
    //   429: invokevirtual 250	java/lang/Class:getMethod	(Ljava/lang/String;[Ljava/lang/Class;)Ljava/lang/reflect/Method;
    //   432: aload_1
    //   433: iconst_1
    //   434: anewarray 116	java/lang/Object
    //   437: dup
    //   438: iconst_0
    //   439: aload_0
    //   440: aastore
    //   441: invokevirtual 256	java/lang/reflect/Method:invoke	(Ljava/lang/Object;[Ljava/lang/Object;)Ljava/lang/Object;
    //   444: checkcast 514	java/lang/Boolean
    //   447: invokevirtual 518	java/lang/Boolean:booleanValue	()Z
    //   450: istore_3
    //   451: iload_3
    //   452: ifeq +6 -> 458
    //   455: goto +103 -> 558
    //   458: return
    //   459: iload_2
    //   460: lookupswitch	default:+28->488, 22:+-430->30, 93:+-216->244
    //   488: goto -244 -> 244
    //   491: return
    //   492: bipush 22
    //   494: istore_2
    //   495: goto -36 -> 459
    //   498: getstatic 42	o/Kn:ˎˎ	I
    //   501: bipush 109
    //   503: iadd
    //   504: istore_2
    //   505: iload_2
    //   506: sipush 128
    //   509: irem
    //   510: putstatic 44	o/Kn:ˌ	I
    //   513: iload_2
    //   514: iconst_2
    //   515: irem
    //   516: ifeq +6 -> 522
    //   519: goto -27 -> 492
    //   522: goto +115 -> 637
    //   525: iload_2
    //   526: lookupswitch	default:+26->552, 33:+-523->3, 54:+120->646
    //   552: goto +94 -> 646
    //   555: astore_1
    //   556: aload_1
    //   557: athrow
    //   558: aload_0
    //   559: getfield 82	o/Kn:ॱˊ	Landroid/databinding/ViewDataBinding;
    //   562: astore_1
    //   563: aload_1
    //   564: checkcast 98	o/JG
    //   567: astore_1
    //   568: aload_1
    //   569: getfield 525	o/JG:ˊ	Lo/Ꭸ;
    //   572: astore_1
    //   573: aload_1
    //   574: iconst_0
    //   575: invokevirtual 530	o/Ꭸ:setClickable	(Z)V
    //   578: getstatic 535	o/Jy$If:horizontal_stretch	I
    //   581: istore_2
    //   582: aload_0
    //   583: iload_2
    //   584: invokestatic 541	android/view/animation/AnimationUtils:loadAnimation	(Landroid/content/Context;I)Landroid/view/animation/Animation;
    //   587: astore_1
    //   588: aload_1
    //   589: new 17	o/Kn$5
    //   592: dup
    //   593: aload_0
    //   594: aload_0
    //   595: getstatic 544	o/Jy$If:horizontal_expand	I
    //   598: invokestatic 541	android/view/animation/AnimationUtils:loadAnimation	(Landroid/content/Context;I)Landroid/view/animation/Animation;
    //   601: invokespecial 547	o/Kn$5:<init>	(Lo/Kn;Landroid/view/animation/Animation;)V
    //   604: invokevirtual 551	android/view/animation/Animation:setAnimationListener	(Landroid/view/animation/Animation$AnimationListener;)V
    //   607: aload_0
    //   608: getfield 82	o/Kn:ॱˊ	Landroid/databinding/ViewDataBinding;
    //   611: checkcast 98	o/JG
    //   614: invokevirtual 553	o/JG:ॱˊ	()Ljava/lang/String;
    //   617: astore 4
    //   619: aload 4
    //   621: ifnull +6 -> 627
    //   624: goto +164 -> 788
    //   627: bipush 54
    //   629: istore_2
    //   630: goto -105 -> 525
    //   633: return
    //   634: goto +160 -> 794
    //   637: bipush 93
    //   639: istore_2
    //   640: goto -181 -> 459
    //   643: astore_1
    //   644: aload_1
    //   645: athrow
    //   646: aload_0
    //   647: getfield 82	o/Kn:ॱˊ	Landroid/databinding/ViewDataBinding;
    //   650: checkcast 98	o/JG
    //   653: iconst_1
    //   654: invokevirtual 292	o/JG:ˏ	(Z)V
    //   657: goto +20 -> 677
    //   660: astore_1
    //   661: aload_1
    //   662: invokevirtual 209	java/lang/Throwable:getCause	()Ljava/lang/Throwable;
    //   665: astore 4
    //   667: aload 4
    //   669: ifnull +6 -> 675
    //   672: aload 4
    //   674: athrow
    //   675: aload_1
    //   676: athrow
    //   677: aload_0
    //   678: invokevirtual 215	android/content/Context:getResources	()Landroid/content/res/Resources;
    //   681: ldc_w 554
    //   684: invokevirtual 219	android/content/res/Resources:getString	(I)Ljava/lang/String;
    //   687: iconst_0
    //   688: iconst_4
    //   689: invokevirtual 222	java/lang/String:substring	(II)Ljava/lang/String;
    //   692: iconst_3
    //   693: invokevirtual 261	java/lang/String:codePointAt	(I)I
    //   696: bipush 8
    //   698: isub
    //   699: aload_0
    //   700: invokevirtual 215	android/content/Context:getResources	()Landroid/content/res/Resources;
    //   703: ldc_w 555
    //   706: invokevirtual 219	android/content/res/Resources:getString	(I)Ljava/lang/String;
    //   709: iconst_0
    //   710: iconst_4
    //   711: invokevirtual 222	java/lang/String:substring	(II)Ljava/lang/String;
    //   714: iconst_2
    //   715: invokevirtual 261	java/lang/String:codePointAt	(I)I
    //   718: bipush 124
    //   720: iadd
    //   721: aload_0
    //   722: invokevirtual 229	android/content/Context:getApplicationInfo	()Landroid/content/pm/ApplicationInfo;
    //   725: getfield 234	android/content/pm/ApplicationInfo:targetSdkVersion	I
    //   728: ldc_w 556
    //   731: iadd
    //   732: i2c
    //   733: invokestatic 243	o/O:ˋ	(IIC)Ljava/lang/Object;
    //   736: checkcast 245	java/lang/Class
    //   739: ldc_w 341
    //   742: aconst_null
    //   743: invokevirtual 250	java/lang/Class:getMethod	(Ljava/lang/String;[Ljava/lang/Class;)Ljava/lang/reflect/Method;
    //   746: aconst_null
    //   747: aconst_null
    //   748: invokevirtual 256	java/lang/reflect/Method:invoke	(Ljava/lang/Object;[Ljava/lang/Object;)Ljava/lang/Object;
    //   751: checkcast 558	o/It
    //   754: astore 4
    //   756: aload 4
    //   758: aload_0
    //   759: getfield 118	o/Kn:ʿ	Lo/HQ;
    //   762: invokevirtual 560	o/HQ:ॱॱ	()Ljava/lang/String;
    //   765: invokeinterface 563 2 0
    //   770: new 13	o/Kn$3
    //   773: dup
    //   774: aload_0
    //   775: aload_0
    //   776: aload_1
    //   777: invokespecial 566	o/Kn$3:<init>	(Lo/Kn;Landroid/content/Context;Landroid/view/animation/Animation;)V
    //   780: invokeinterface 571 2 0
    //   785: goto -152 -> 633
    //   788: bipush 33
    //   790: istore_2
    //   791: goto -266 -> 525
    //   794: aload_0
    //   795: getfield 82	o/Kn:ॱˊ	Landroid/databinding/ViewDataBinding;
    //   798: checkcast 98	o/JG
    //   801: getfield 525	o/JG:ˊ	Lo/Ꭸ;
    //   804: aload_1
    //   805: invokevirtual 575	o/Ꭸ:startAnimation	(Landroid/view/animation/Animation;)V
    //   808: goto -317 -> 491
    // Local variable table:
    //   start	length	slot	name	signature
    //   0	811	0	this	Kn
    //   0	811	1	paramView	View
    //   9	782	2	i	int
    //   230	222	3	bool	boolean
    //   38	719	4	localObject	Object
    // Exception table:
    //   from	to	target	type
    //   50	111	33	finally
    //   131	231	114	finally
    //   264	349	247	finally
    //   369	451	352	finally
    //   558	563	555	java/lang/Exception
    //   563	568	555	java/lang/Exception
    //   568	573	555	java/lang/Exception
    //   573	578	555	java/lang/Exception
    //   578	582	555	java/lang/Exception
    //   582	619	555	java/lang/Exception
    //   573	578	643	java/lang/Exception
    //   677	756	660	finally
  }
  
  /* Error */
  public void onCreate(android.os.Bundle paramBundle)
  {
    // Byte code:
    //   0: goto +178 -> 178
    //   3: astore_1
    //   4: aload_1
    //   5: athrow
    //   6: aload_0
    //   7: aload_1
    //   8: invokespecial 579	o/IB:onCreate	(Landroid/os/Bundle;)V
    //   11: aload_0
    //   12: aload_0
    //   13: getfield 82	o/Kn:ॱˊ	Landroid/databinding/ViewDataBinding;
    //   16: checkcast 98	o/JG
    //   19: getfield 582	o/JG:ʽ	Lo/у;
    //   22: invokevirtual 585	o/Kn:ˊ	(Lo/у;)V
    //   25: aload_0
    //   26: aload_0
    //   27: invokevirtual 355	o/Kn:getIntent	()Landroid/content/Intent;
    //   30: invokespecial 587	o/Kn:ˎ	(Landroid/content/Intent;)V
    //   33: new 362	java/lang/NullPointerException
    //   36: dup
    //   37: invokespecial 363	java/lang/NullPointerException:<init>	()V
    //   40: athrow
    //   41: iload_2
    //   42: lookupswitch	default:+26->68, 60:+129->171, 70:+121->163
    //   68: return
    //   69: getstatic 44	o/Kn:ˌ	I
    //   72: bipush 53
    //   74: iadd
    //   75: istore_2
    //   76: iload_2
    //   77: sipush 128
    //   80: irem
    //   81: putstatic 42	o/Kn:ˎˎ	I
    //   84: iload_2
    //   85: iconst_2
    //   86: irem
    //   87: ifne +6 -> 93
    //   90: goto +82 -> 172
    //   93: bipush 60
    //   95: istore_2
    //   96: goto -55 -> 41
    //   99: astore_1
    //   100: aload_1
    //   101: athrow
    //   102: getstatic 44	o/Kn:ˌ	I
    //   105: bipush 27
    //   107: iadd
    //   108: istore_2
    //   109: iload_2
    //   110: sipush 128
    //   113: irem
    //   114: putstatic 42	o/Kn:ˎˎ	I
    //   117: iload_2
    //   118: iconst_2
    //   119: irem
    //   120: ifne +6 -> 126
    //   123: goto +6 -> 129
    //   126: goto +93 -> 219
    //   129: bipush 57
    //   131: istore_2
    //   132: iload_2
    //   133: lookupswitch	default:+27->160, 57:+-127->6, 67:+48->181
    //   160: goto -154 -> 6
    //   163: new 362	java/lang/NullPointerException
    //   166: dup
    //   167: invokespecial 363	java/lang/NullPointerException:<init>	()V
    //   170: athrow
    //   171: return
    //   172: bipush 70
    //   174: istore_2
    //   175: goto -134 -> 41
    //   178: goto -76 -> 102
    //   181: aload_0
    //   182: aload_1
    //   183: invokespecial 579	o/IB:onCreate	(Landroid/os/Bundle;)V
    //   186: aload_0
    //   187: getfield 82	o/Kn:ॱˊ	Landroid/databinding/ViewDataBinding;
    //   190: astore_1
    //   191: aload_1
    //   192: checkcast 98	o/JG
    //   195: astore_1
    //   196: aload_1
    //   197: getfield 582	o/JG:ʽ	Lo/у;
    //   200: astore_1
    //   201: aload_0
    //   202: aload_1
    //   203: invokevirtual 585	o/Kn:ˊ	(Lo/у;)V
    //   206: aload_0
    //   207: invokevirtual 355	o/Kn:getIntent	()Landroid/content/Intent;
    //   210: astore_1
    //   211: aload_0
    //   212: aload_1
    //   213: invokespecial 587	o/Kn:ˎ	(Landroid/content/Intent;)V
    //   216: goto -147 -> 69
    //   219: bipush 67
    //   221: istore_2
    //   222: goto -90 -> 132
    // Local variable table:
    //   start	length	slot	name	signature
    //   0	225	0	this	Kn
    //   0	225	1	paramBundle	android.os.Bundle
    //   41	181	2	i	int
    // Exception table:
    //   from	to	target	type
    //   186	191	3	java/lang/Exception
    //   191	196	3	java/lang/Exception
    //   196	201	3	java/lang/Exception
    //   201	206	3	java/lang/Exception
    //   206	211	3	java/lang/Exception
    //   211	216	3	java/lang/Exception
    //   191	196	99	java/lang/Exception
  }
  
  public void onNewIntent(Intent paramIntent)
  {
    break label29;
    int i = 0;
    break label56;
    for (;;)
    {
      i = 1;
      break label56;
      super.onNewIntent(paramIntent);
      ˎ(paramIntent);
      i = 64 / 0;
      return;
      label29:
      i = ˌ + 73;
      ˎˎ = i % 128;
      if (i % 2 == 0) {
        break;
      }
    }
    label56:
    switch (i)
    {
    }
    super.onNewIntent(paramIntent);
    ˎ(paramIntent);
  }
  
  public void onSettingsClick(View paramView)
  {
    break label123;
    try
    {
      i = ˎˎ + 27;
      ˌ = i % 128;
      if (i % 2 == 0)
      {
        break label126;
        Ic.ˏ(this).ॱ(Gm.PAYMENT_CARD_SETTINGS, this.ʿ.ˎ().getCardName()).ˎ(81);
        break label131;
        label60:
        Ic.ˏ(this).ॱ(Gm.PAYMENT_CARD_SETTINGS, this.ʿ.ˎ().getCardName()).ˎ(24);
        break label131;
      }
      else
      {
        i = 1;
      }
    }
    catch (Exception paramView)
    {
      throw paramView;
    }
    for (;;)
    {
      switch (i)
      {
      }
      break label60;
      label123:
      break;
      label126:
      i = 0;
    }
    label131:
    int i = ˌ + 49;
    ˎˎ = i % 128;
    if (i % 2 == 0) {}
  }
  
  public void ˋ(ز paramز)
  {
    for (;;)
    {
      int i = ˌ + 41;
      ˎˎ = i % 128;
      if (i % 2 == 0) {
        break;
      }
      super.ˋ(paramز);
      paramز.ॱ(true);
      paramز.ˏ(true);
      i = ˌ + 111;
      ˎˎ = i % 128;
      if (i % 2 == 0) {
        return;
      }
      return;
    }
  }
  
  /* Error */
  public int ˎ()
  {
    // Byte code:
    //   0: goto +34 -> 34
    //   3: getstatic 42	o/Kn:ˎˎ	I
    //   6: bipush 19
    //   8: iadd
    //   9: istore_1
    //   10: iload_1
    //   11: sipush 128
    //   14: irem
    //   15: putstatic 44	o/Kn:ˌ	I
    //   18: iload_1
    //   19: iconst_2
    //   20: irem
    //   21: ifeq +6 -> 27
    //   24: goto +5 -> 29
    //   27: iload_2
    //   28: ireturn
    //   29: iload_2
    //   30: ireturn
    //   31: astore_3
    //   32: aload_3
    //   33: athrow
    //   34: goto +6 -> 40
    //   37: goto +29 -> 66
    //   40: getstatic 44	o/Kn:ˌ	I
    //   43: istore_1
    //   44: iload_1
    //   45: bipush 87
    //   47: iadd
    //   48: istore_1
    //   49: iload_1
    //   50: sipush 128
    //   53: irem
    //   54: putstatic 42	o/Kn:ˎˎ	I
    //   57: iload_1
    //   58: iconst_2
    //   59: irem
    //   60: ifne +6 -> 66
    //   63: goto -26 -> 37
    //   66: getstatic 629	o/Jy$ˊ:activity_card_details	I
    //   69: istore_2
    //   70: goto -67 -> 3
    //   73: astore_3
    //   74: aload_3
    //   75: athrow
    // Local variable table:
    //   start	length	slot	name	signature
    //   0	76	0	this	Kn
    //   9	51	1	i	int
    //   27	43	2	j	int
    //   31	2	3	localException1	Exception
    //   73	2	3	localException2	Exception
    // Exception table:
    //   from	to	target	type
    //   40	44	31	java/lang/Exception
    //   49	57	73	java/lang/Exception
  }
  
  /* Error */
  public void ˏ(android.support.design.widget.AppBarLayout paramAppBarLayout, int paramInt)
  {
    // Byte code:
    //   0: goto +242 -> 242
    //   3: aload_0
    //   4: getfield 82	o/Kn:ॱˊ	Landroid/databinding/ViewDataBinding;
    //   7: checkcast 98	o/JG
    //   10: getfield 633	o/JG:ॱˊ	Landroid/view/View;
    //   13: iconst_0
    //   14: invokevirtual 638	android/view/View:setVisibility	(I)V
    //   17: goto +33 -> 50
    //   20: getstatic 44	o/Kn:ˌ	I
    //   23: bipush 7
    //   25: iadd
    //   26: istore 4
    //   28: iload 4
    //   30: sipush 128
    //   33: irem
    //   34: putstatic 42	o/Kn:ˎˎ	I
    //   37: iload 4
    //   39: iconst_2
    //   40: irem
    //   41: ifne +6 -> 47
    //   44: goto +55 -> 99
    //   47: goto +114 -> 161
    //   50: getstatic 42	o/Kn:ˎˎ	I
    //   53: iconst_3
    //   54: iadd
    //   55: istore_2
    //   56: iload_2
    //   57: sipush 128
    //   60: irem
    //   61: putstatic 44	o/Kn:ˌ	I
    //   64: iload_2
    //   65: iconst_2
    //   66: irem
    //   67: ifeq +6 -> 73
    //   70: goto +50 -> 120
    //   73: goto +280 -> 353
    //   76: iconst_1
    //   77: istore 4
    //   79: goto +205 -> 284
    //   82: aload_0
    //   83: getfield 82	o/Kn:ॱˊ	Landroid/databinding/ViewDataBinding;
    //   86: checkcast 98	o/JG
    //   89: getfield 633	o/JG:ॱˊ	Landroid/view/View;
    //   92: iconst_4
    //   93: invokevirtual 638	android/view/View:setVisibility	(I)V
    //   96: goto +149 -> 245
    //   99: aload_0
    //   100: getfield 478	o/Kn:ʾ	I
    //   103: istore 4
    //   105: aconst_null
    //   106: arraylength
    //   107: istore 5
    //   109: iload 4
    //   111: ifne +6 -> 117
    //   114: goto +60 -> 174
    //   117: goto +194 -> 311
    //   120: iconst_4
    //   121: istore_2
    //   122: goto +88 -> 210
    //   125: iload_2
    //   126: lookupswitch	default:+26->152, 45:+-123->3, 62:+-44->82
    //   152: goto -70 -> 82
    //   155: goto +204 -> 359
    //   158: astore_1
    //   159: aload_1
    //   160: athrow
    //   161: aload_0
    //   162: getfield 478	o/Kn:ʾ	I
    //   165: ifne +6 -> 171
    //   168: goto +179 -> 347
    //   171: goto -95 -> 76
    //   174: getstatic 42	o/Kn:ˎˎ	I
    //   177: bipush 11
    //   179: iadd
    //   180: istore 4
    //   182: iload 4
    //   184: sipush 128
    //   187: irem
    //   188: putstatic 44	o/Kn:ˌ	I
    //   191: iload 4
    //   193: iconst_2
    //   194: irem
    //   195: ifeq +6 -> 201
    //   198: goto -43 -> 155
    //   201: goto +158 -> 359
    //   204: bipush 45
    //   206: istore_2
    //   207: goto -82 -> 125
    //   210: iload_2
    //   211: lookupswitch	default:+25->236, 4:+28->239, 30:+133->344
    //   236: goto +108 -> 344
    //   239: goto +6 -> 245
    //   242: goto -222 -> 20
    //   245: fload_3
    //   246: ldc_w 639
    //   249: fdiv
    //   250: fstore_3
    //   251: aload_0
    //   252: getfield 82	o/Kn:ॱˊ	Landroid/databinding/ViewDataBinding;
    //   255: checkcast 98	o/JG
    //   258: getfield 643	o/JG:ˋॱ	Lo/KX;
    //   261: fconst_1
    //   262: fload_3
    //   263: fsub
    //   264: invokevirtual 649	o/KX:setScaleX	(F)V
    //   267: aload_0
    //   268: getfield 82	o/Kn:ॱˊ	Landroid/databinding/ViewDataBinding;
    //   271: checkcast 98	o/JG
    //   274: getfield 643	o/JG:ˋॱ	Lo/KX;
    //   277: fconst_1
    //   278: fload_3
    //   279: fsub
    //   280: invokevirtual 652	o/KX:setScaleY	(F)V
    //   283: return
    //   284: iload 4
    //   286: tableswitch	default:+22->308, 0:+-112->174, 1:+25->311
    //   308: goto -134 -> 174
    //   311: iload_2
    //   312: invokestatic 657	java/lang/Math:abs	(I)I
    //   315: istore_2
    //   316: iload_2
    //   317: bipush 100
    //   319: imul
    //   320: aload_0
    //   321: getfield 478	o/Kn:ʾ	I
    //   324: idiv
    //   325: istore_2
    //   326: iload_2
    //   327: i2f
    //   328: fstore_3
    //   329: fload_3
    //   330: fconst_1
    //   331: fcmpl
    //   332: ifle +6 -> 338
    //   335: goto -131 -> 204
    //   338: bipush 62
    //   340: istore_2
    //   341: goto -216 -> 125
    //   344: goto -99 -> 245
    //   347: iconst_0
    //   348: istore 4
    //   350: goto -66 -> 284
    //   353: bipush 30
    //   355: istore_2
    //   356: goto -146 -> 210
    //   359: aload_1
    //   360: invokevirtual 476	android/support/design/widget/AppBarLayout:ˎ	()I
    //   363: istore 4
    //   365: aload_0
    //   366: iload 4
    //   368: putfield 478	o/Kn:ʾ	I
    //   371: goto -60 -> 311
    // Local variable table:
    //   start	length	slot	name	signature
    //   0	374	0	this	Kn
    //   0	374	1	paramAppBarLayout	android.support.design.widget.AppBarLayout
    //   0	374	2	paramInt	int
    //   245	1	3	localObject	Object
    //   250	80	3	f	float
    //   26	341	4	i	int
    //   107	1	5	j	int
    // Exception table:
    //   from	to	target	type
    //   311	316	158	java/lang/Exception
    //   316	326	158	java/lang/Exception
    //   359	365	158	java/lang/Exception
    //   365	371	158	java/lang/Exception
  }
  
  /* Error */
  @zA(ˎ=org.greenrobot.eventbus.ThreadMode.MAIN)
  public void ॱ(HA paramHA)
  {
    // Byte code:
    //   0: getstatic 44	o/Kn:ˌ	I
    //   3: bipush 111
    //   5: iadd
    //   6: istore_2
    //   7: iload_2
    //   8: sipush 128
    //   11: irem
    //   12: putstatic 42	o/Kn:ˎˎ	I
    //   15: iload_2
    //   16: iconst_2
    //   17: irem
    //   18: ifne +6 -> 24
    //   21: goto +278 -> 299
    //   24: goto +30 -> 54
    //   27: getstatic 42	o/Kn:ˎˎ	I
    //   30: istore_2
    //   31: iload_2
    //   32: bipush 83
    //   34: iadd
    //   35: istore_2
    //   36: iload_2
    //   37: sipush 128
    //   40: irem
    //   41: putstatic 44	o/Kn:ˌ	I
    //   44: iload_2
    //   45: iconst_2
    //   46: irem
    //   47: ifeq +6 -> 53
    //   50: goto +248 -> 298
    //   53: return
    //   54: goto +17 -> 71
    //   57: astore_1
    //   58: aload_1
    //   59: invokevirtual 209	java/lang/Throwable:getCause	()Ljava/lang/Throwable;
    //   62: astore_3
    //   63: aload_3
    //   64: ifnull +5 -> 69
    //   67: aload_3
    //   68: athrow
    //   69: aload_1
    //   70: athrow
    //   71: aload_0
    //   72: invokevirtual 215	android/content/Context:getResources	()Landroid/content/res/Resources;
    //   75: ldc_w 662
    //   78: invokevirtual 219	android/content/res/Resources:getString	(I)Ljava/lang/String;
    //   81: iconst_0
    //   82: iconst_1
    //   83: invokevirtual 222	java/lang/String:substring	(II)Ljava/lang/String;
    //   86: invokevirtual 225	java/lang/String:length	()I
    //   89: iconst_3
    //   90: iadd
    //   91: aload_0
    //   92: invokevirtual 215	android/content/Context:getResources	()Landroid/content/res/Resources;
    //   95: ldc_w 663
    //   98: invokevirtual 219	android/content/res/Resources:getString	(I)Ljava/lang/String;
    //   101: iconst_0
    //   102: iconst_4
    //   103: invokevirtual 222	java/lang/String:substring	(II)Ljava/lang/String;
    //   106: invokevirtual 225	java/lang/String:length	()I
    //   109: sipush 263
    //   112: iadd
    //   113: aload_0
    //   114: invokevirtual 215	android/content/Context:getResources	()Landroid/content/res/Resources;
    //   117: ldc_w 664
    //   120: invokevirtual 219	android/content/res/Resources:getString	(I)Ljava/lang/String;
    //   123: iconst_0
    //   124: iconst_4
    //   125: invokevirtual 222	java/lang/String:substring	(II)Ljava/lang/String;
    //   128: iconst_1
    //   129: invokevirtual 261	java/lang/String:codePointAt	(I)I
    //   132: sipush 14762
    //   135: iadd
    //   136: i2c
    //   137: invokestatic 243	o/O:ˋ	(IIC)Ljava/lang/Object;
    //   140: checkcast 245	java/lang/Class
    //   143: ldc_w 341
    //   146: aconst_null
    //   147: invokevirtual 250	java/lang/Class:getMethod	(Ljava/lang/String;[Ljava/lang/Class;)Ljava/lang/reflect/Method;
    //   150: aconst_null
    //   151: aconst_null
    //   152: invokevirtual 256	java/lang/reflect/Method:invoke	(Ljava/lang/Object;[Ljava/lang/Object;)Ljava/lang/Object;
    //   155: astore_1
    //   156: aload_0
    //   157: getfield 339	o/Kn:ʽॱ	Ljava/lang/String;
    //   160: astore_3
    //   161: goto +17 -> 178
    //   164: astore_1
    //   165: aload_1
    //   166: invokevirtual 209	java/lang/Throwable:getCause	()Ljava/lang/Throwable;
    //   169: astore_3
    //   170: aload_3
    //   171: ifnull +5 -> 176
    //   174: aload_3
    //   175: athrow
    //   176: aload_1
    //   177: athrow
    //   178: aload_0
    //   179: invokevirtual 215	android/content/Context:getResources	()Landroid/content/res/Resources;
    //   182: ldc_w 665
    //   185: invokevirtual 219	android/content/res/Resources:getString	(I)Ljava/lang/String;
    //   188: iconst_0
    //   189: iconst_4
    //   190: invokevirtual 222	java/lang/String:substring	(II)Ljava/lang/String;
    //   193: iconst_0
    //   194: invokevirtual 261	java/lang/String:codePointAt	(I)I
    //   197: iconst_1
    //   198: isub
    //   199: aload_0
    //   200: invokevirtual 237	android/content/Context:getPackageName	()Ljava/lang/String;
    //   203: invokevirtual 225	java/lang/String:length	()I
    //   206: sipush 256
    //   209: iadd
    //   210: aload_0
    //   211: invokevirtual 215	android/content/Context:getResources	()Landroid/content/res/Resources;
    //   214: ldc_w 666
    //   217: invokevirtual 219	android/content/res/Resources:getString	(I)Ljava/lang/String;
    //   220: iconst_0
    //   221: iconst_5
    //   222: invokevirtual 222	java/lang/String:substring	(II)Ljava/lang/String;
    //   225: invokevirtual 225	java/lang/String:length	()I
    //   228: sipush 14783
    //   231: iadd
    //   232: i2c
    //   233: invokestatic 243	o/O:ˋ	(IIC)Ljava/lang/Object;
    //   236: checkcast 245	java/lang/Class
    //   239: ldc_w 343
    //   242: iconst_1
    //   243: anewarray 245	java/lang/Class
    //   246: dup
    //   247: iconst_0
    //   248: ldc 125
    //   250: aastore
    //   251: invokevirtual 250	java/lang/Class:getMethod	(Ljava/lang/String;[Ljava/lang/Class;)Ljava/lang/reflect/Method;
    //   254: aload_1
    //   255: iconst_1
    //   256: anewarray 116	java/lang/Object
    //   259: dup
    //   260: iconst_0
    //   261: aload_3
    //   262: aastore
    //   263: invokevirtual 256	java/lang/reflect/Method:invoke	(Ljava/lang/Object;[Ljava/lang/Object;)Ljava/lang/Object;
    //   266: checkcast 345	com/insidesecure/hce/MatrixHCECard
    //   269: astore_1
    //   270: aload_0
    //   271: aload_1
    //   272: invokestatic 348	o/HQ:ˏ	(Lcom/insidesecure/hce/MatrixHCECard;)Lo/HQ;
    //   275: putfield 118	o/Kn:ʿ	Lo/HQ;
    //   278: aload_0
    //   279: getfield 82	o/Kn:ॱˊ	Landroid/databinding/ViewDataBinding;
    //   282: checkcast 98	o/JG
    //   285: aload_0
    //   286: getfield 118	o/Kn:ʿ	Lo/HQ;
    //   289: invokevirtual 351	o/JG:ˎ	(Lo/HQ;)V
    //   292: goto -265 -> 27
    //   295: astore_1
    //   296: aload_1
    //   297: athrow
    //   298: return
    //   299: goto -245 -> 54
    // Local variable table:
    //   start	length	slot	name	signature
    //   0	302	0	this	Kn
    //   0	302	1	paramHA	HA
    //   6	41	2	i	int
    //   62	200	3	localObject	Object
    // Exception table:
    //   from	to	target	type
    //   71	156	57	finally
    //   178	270	164	finally
    //   27	31	295	java/lang/Exception
    //   36	44	295	java/lang/Exception
  }
}
