package o;

public class KP
  extends x
  implements ᐸ.ˏ
{
  private static byte ߺ;
  private static char[] ॱˈ;
  private static char ॱˌ;
  private static int ॱˑ;
  private static int ॱـ;
  
  static
  {
    try
    {
      for (;;)
      {
        int i = ॱˑ;
        i += 81;
        try
        {
          ॱـ = i % 128;
          if (i % 2 == 0) {
            break;
          }
          return;
        }
        catch (Exception localException1)
        {
          throw localException1;
        }
        ॱˑ = 0;
        ॱـ = 1;
        ˎ();
        ߺ = -102;
      }
      return;
    }
    catch (Exception localException2)
    {
      throw localException2;
    }
  }
  
  /* Error */
  public KP(android.content.Context paramContext)
  {
    // Byte code:
    //   0: goto +114 -> 114
    //   3: bipush 57
    //   5: istore_2
    //   6: goto +335 -> 341
    //   9: aload_0
    //   10: aload_1
    //   11: iconst_4
    //   12: invokevirtual 39	java/lang/String:substring	(I)Ljava/lang/String;
    //   15: invokespecial 43	o/KP:ˋ	(Ljava/lang/String;)Ljava/lang/String;
    //   18: invokevirtual 47	java/lang/String:intern	()Ljava/lang/String;
    //   21: astore_1
    //   22: goto +172 -> 194
    //   25: astore_1
    //   26: aload_1
    //   27: athrow
    //   28: getstatic 23	o/KP:ॱˑ	I
    //   31: bipush 89
    //   33: iadd
    //   34: istore_2
    //   35: iload_2
    //   36: sipush 128
    //   39: irem
    //   40: putstatic 25	o/KP:ॱـ	I
    //   43: iload_2
    //   44: iconst_2
    //   45: irem
    //   46: ifne +6 -> 52
    //   49: goto +139 -> 188
    //   52: goto +283 -> 335
    //   55: aload_0
    //   56: aload_3
    //   57: invokevirtual 50	o/KP:ˋ	(Ljava/lang/CharSequence;)Lo/ᐸ$If;
    //   60: pop
    //   61: aload_1
    //   62: getstatic 55	o/Jy$IF:continue_label	I
    //   65: invokevirtual 60	android/content/Context:getString	(I)Ljava/lang/String;
    //   68: astore_1
    //   69: aload_1
    //   70: iconst_4
    //   71: newarray char
    //   73: dup
    //   74: iconst_0
    //   75: ldc 61
    //   77: castore
    //   78: dup
    //   79: iconst_1
    //   80: ldc 62
    //   82: castore
    //   83: dup
    //   84: iconst_2
    //   85: ldc 63
    //   87: castore
    //   88: dup
    //   89: iconst_3
    //   90: ldc 64
    //   92: castore
    //   93: iconst_4
    //   94: bipush 13
    //   96: invokestatic 67	o/KP:ˎ	([CIB)Ljava/lang/String;
    //   99: invokevirtual 47	java/lang/String:intern	()Ljava/lang/String;
    //   102: invokevirtual 71	java/lang/String:startsWith	(Ljava/lang/String;)Z
    //   105: ifeq +6 -> 111
    //   108: goto -99 -> 9
    //   111: goto +260 -> 371
    //   114: aload_0
    //   115: aload_1
    //   116: invokespecial 73	o/x:<init>	(Landroid/content/Context;)V
    //   119: aload_1
    //   120: getstatic 76	o/Jy$IF:failed_user_identification_title	I
    //   123: invokevirtual 60	android/content/Context:getString	(I)Ljava/lang/String;
    //   126: astore_3
    //   127: aload_3
    //   128: iconst_4
    //   129: newarray char
    //   131: dup
    //   132: iconst_0
    //   133: ldc 61
    //   135: castore
    //   136: dup
    //   137: iconst_1
    //   138: ldc 62
    //   140: castore
    //   141: dup
    //   142: iconst_2
    //   143: ldc 63
    //   145: castore
    //   146: dup
    //   147: iconst_3
    //   148: ldc 64
    //   150: castore
    //   151: iconst_4
    //   152: bipush 13
    //   154: invokestatic 67	o/KP:ˎ	([CIB)Ljava/lang/String;
    //   157: invokevirtual 47	java/lang/String:intern	()Ljava/lang/String;
    //   160: invokevirtual 71	java/lang/String:startsWith	(Ljava/lang/String;)Z
    //   163: ifeq +6 -> 169
    //   166: goto +61 -> 227
    //   169: goto +76 -> 245
    //   172: aload_0
    //   173: aload_3
    //   174: iconst_4
    //   175: invokevirtual 39	java/lang/String:substring	(I)Ljava/lang/String;
    //   178: invokespecial 43	o/KP:ˋ	(Ljava/lang/String;)Ljava/lang/String;
    //   181: invokevirtual 47	java/lang/String:intern	()Ljava/lang/String;
    //   184: astore_3
    //   185: goto -130 -> 55
    //   188: bipush 28
    //   190: istore_2
    //   191: goto +113 -> 304
    //   194: getstatic 25	o/KP:ॱـ	I
    //   197: bipush 115
    //   199: iadd
    //   200: istore_2
    //   201: iload_2
    //   202: sipush 128
    //   205: irem
    //   206: putstatic 23	o/KP:ॱˑ	I
    //   209: iload_2
    //   210: iconst_2
    //   211: irem
    //   212: ifeq +6 -> 218
    //   215: goto -212 -> 3
    //   218: goto +181 -> 399
    //   221: goto +150 -> 371
    //   224: goto +21 -> 245
    //   227: aload_0
    //   228: aload_3
    //   229: iconst_4
    //   230: invokevirtual 39	java/lang/String:substring	(I)Ljava/lang/String;
    //   233: invokespecial 43	o/KP:ˋ	(Ljava/lang/String;)Ljava/lang/String;
    //   236: astore_3
    //   237: aload_3
    //   238: invokevirtual 47	java/lang/String:intern	()Ljava/lang/String;
    //   241: astore_3
    //   242: goto -214 -> 28
    //   245: aload_0
    //   246: aload_3
    //   247: invokevirtual 79	o/KP:ˊ	(Ljava/lang/CharSequence;)Lo/ᐸ$If;
    //   250: pop
    //   251: aload_1
    //   252: getstatic 82	o/Jy$IF:failed_user_identification_message	I
    //   255: invokevirtual 60	android/content/Context:getString	(I)Ljava/lang/String;
    //   258: astore_3
    //   259: aload_3
    //   260: iconst_4
    //   261: newarray char
    //   263: dup
    //   264: iconst_0
    //   265: ldc 61
    //   267: castore
    //   268: dup
    //   269: iconst_1
    //   270: ldc 62
    //   272: castore
    //   273: dup
    //   274: iconst_2
    //   275: ldc 63
    //   277: castore
    //   278: dup
    //   279: iconst_3
    //   280: ldc 64
    //   282: castore
    //   283: iconst_4
    //   284: bipush 13
    //   286: invokestatic 67	o/KP:ˎ	([CIB)Ljava/lang/String;
    //   289: invokevirtual 47	java/lang/String:intern	()Ljava/lang/String;
    //   292: invokevirtual 71	java/lang/String:startsWith	(Ljava/lang/String;)Z
    //   295: ifeq +6 -> 301
    //   298: goto -126 -> 172
    //   301: goto -246 -> 55
    //   304: iload_2
    //   305: lookupswitch	default:+27->332, 8:+91->396, 28:+-81->224
    //   332: goto +64 -> 396
    //   335: bipush 8
    //   337: istore_2
    //   338: goto -34 -> 304
    //   341: iload_2
    //   342: lookupswitch	default:+26->368, 45:+-121->221, 57:+63->405
    //   368: goto -147 -> 221
    //   371: aload_0
    //   372: aload_1
    //   373: invokevirtual 84	o/KP:ˎ	(Ljava/lang/CharSequence;)Lo/ᐸ$If;
    //   376: pop
    //   377: aload_0
    //   378: iconst_0
    //   379: invokevirtual 87	o/KP:ˋ	(Z)Lo/ᐸ$If;
    //   382: pop
    //   383: aload_0
    //   384: aload_0
    //   385: invokevirtual 91	o/KP:ॱ	(Lo/ᐸ$ˏ;)Lo/ᐸ$If;
    //   388: pop
    //   389: aload_0
    //   390: iconst_0
    //   391: invokevirtual 93	o/KP:ˎ	(Z)Lo/ᐸ$If;
    //   394: pop
    //   395: return
    //   396: goto -151 -> 245
    //   399: bipush 45
    //   401: istore_2
    //   402: goto -61 -> 341
    //   405: goto -34 -> 371
    // Local variable table:
    //   start	length	slot	name	signature
    //   0	408	0	this	KP
    //   0	408	1	paramContext	android.content.Context
    //   5	397	2	i	int
    //   56	204	3	localObject	Object
    // Exception table:
    //   from	to	target	type
    //   227	237	25	java/lang/Exception
    //   237	242	25	java/lang/Exception
  }
  
  /* Error */
  private String ˋ(String paramString)
  {
    // Byte code:
    //   0: goto +35 -> 35
    //   3: iload_2
    //   4: lookupswitch	default:+28->32, 48:+51->55, 57:+311->315
    //   32: goto +283 -> 315
    //   35: goto +228 -> 263
    //   38: goto +185 -> 223
    //   41: bipush 48
    //   43: istore_2
    //   44: goto -41 -> 3
    //   47: astore_1
    //   48: aload_1
    //   49: athrow
    //   50: iconst_0
    //   51: istore_3
    //   52: goto +186 -> 238
    //   55: aload_1
    //   56: bipush 10
    //   58: newarray char
    //   60: dup
    //   61: iconst_0
    //   62: ldc 96
    //   64: castore
    //   65: dup
    //   66: iconst_1
    //   67: ldc 97
    //   69: castore
    //   70: dup
    //   71: iconst_2
    //   72: ldc 98
    //   74: castore
    //   75: dup
    //   76: iconst_3
    //   77: ldc 99
    //   79: castore
    //   80: dup
    //   81: iconst_4
    //   82: ldc 100
    //   84: castore
    //   85: dup
    //   86: iconst_5
    //   87: ldc 100
    //   89: castore
    //   90: dup
    //   91: bipush 6
    //   93: ldc 101
    //   95: castore
    //   96: dup
    //   97: bipush 7
    //   99: ldc 102
    //   101: castore
    //   102: dup
    //   103: bipush 8
    //   105: ldc 102
    //   107: castore
    //   108: dup
    //   109: bipush 9
    //   111: ldc 103
    //   113: castore
    //   114: bipush 122
    //   116: bipush 44
    //   118: invokestatic 67	o/KP:ˎ	([CIB)Ljava/lang/String;
    //   121: invokevirtual 47	java/lang/String:intern	()Ljava/lang/String;
    //   124: invokevirtual 107	java/lang/String:getBytes	(Ljava/lang/String;)[B
    //   127: astore 4
    //   129: aload 4
    //   131: arraylength
    //   132: newarray byte
    //   134: astore_1
    //   135: iconst_0
    //   136: istore_2
    //   137: goto +86 -> 223
    //   140: new 35	java/lang/String
    //   143: dup
    //   144: aload_1
    //   145: iconst_5
    //   146: newarray char
    //   148: dup
    //   149: iconst_0
    //   150: ldc 108
    //   152: castore
    //   153: dup
    //   154: iconst_1
    //   155: ldc 109
    //   157: castore
    //   158: dup
    //   159: iconst_2
    //   160: ldc 103
    //   162: castore
    //   163: dup
    //   164: iconst_3
    //   165: ldc 97
    //   167: castore
    //   168: dup
    //   169: iconst_4
    //   170: ldc 110
    //   172: castore
    //   173: iconst_5
    //   174: bipush 91
    //   176: invokestatic 67	o/KP:ˎ	([CIB)Ljava/lang/String;
    //   179: invokevirtual 47	java/lang/String:intern	()Ljava/lang/String;
    //   182: invokespecial 113	java/lang/String:<init>	([BLjava/lang/String;)V
    //   185: astore_1
    //   186: aload_1
    //   187: areturn
    //   188: astore_1
    //   189: aload_1
    //   190: athrow
    //   191: goto +99 -> 290
    //   194: getstatic 23	o/KP:ॱˑ	I
    //   197: istore_3
    //   198: iload_3
    //   199: bipush 31
    //   201: iadd
    //   202: istore_3
    //   203: iload_3
    //   204: sipush 128
    //   207: irem
    //   208: putstatic 25	o/KP:ॱـ	I
    //   211: iload_3
    //   212: iconst_2
    //   213: irem
    //   214: ifne +6 -> 220
    //   217: goto -26 -> 191
    //   220: goto +70 -> 290
    //   223: aload 4
    //   225: arraylength
    //   226: istore_3
    //   227: iload_2
    //   228: iload_3
    //   229: if_icmpge +6 -> 235
    //   232: goto -182 -> 50
    //   235: goto +181 -> 416
    //   238: iload_3
    //   239: tableswitch	default:+21->260, 0:+-45->194, 1:+-99->140
    //   260: goto -120 -> 140
    //   263: getstatic 25	o/KP:ॱـ	I
    //   266: bipush 57
    //   268: iadd
    //   269: istore_2
    //   270: iload_2
    //   271: sipush 128
    //   274: irem
    //   275: putstatic 23	o/KP:ॱˑ	I
    //   278: iload_2
    //   279: iconst_2
    //   280: irem
    //   281: ifeq +6 -> 287
    //   284: goto -243 -> 41
    //   287: goto +113 -> 400
    //   290: aload_1
    //   291: iload_2
    //   292: aload 4
    //   294: aload 4
    //   296: arraylength
    //   297: iload_2
    //   298: isub
    //   299: iconst_1
    //   300: isub
    //   301: baload
    //   302: getstatic 30	o/KP:ߺ	B
    //   305: ixor
    //   306: i2b
    //   307: bastore
    //   308: iload_2
    //   309: iconst_1
    //   310: iadd
    //   311: istore_2
    //   312: goto -274 -> 38
    //   315: aload_1
    //   316: bipush 10
    //   318: newarray char
    //   320: dup
    //   321: iconst_0
    //   322: ldc 96
    //   324: castore
    //   325: dup
    //   326: iconst_1
    //   327: ldc 97
    //   329: castore
    //   330: dup
    //   331: iconst_2
    //   332: ldc 98
    //   334: castore
    //   335: dup
    //   336: iconst_3
    //   337: ldc 99
    //   339: castore
    //   340: dup
    //   341: iconst_4
    //   342: ldc 100
    //   344: castore
    //   345: dup
    //   346: iconst_5
    //   347: ldc 100
    //   349: castore
    //   350: dup
    //   351: bipush 6
    //   353: ldc 101
    //   355: castore
    //   356: dup
    //   357: bipush 7
    //   359: ldc 102
    //   361: castore
    //   362: dup
    //   363: bipush 8
    //   365: ldc 102
    //   367: castore
    //   368: dup
    //   369: bipush 9
    //   371: ldc 103
    //   373: castore
    //   374: bipush 10
    //   376: bipush 13
    //   378: invokestatic 67	o/KP:ˎ	([CIB)Ljava/lang/String;
    //   381: invokevirtual 47	java/lang/String:intern	()Ljava/lang/String;
    //   384: invokevirtual 107	java/lang/String:getBytes	(Ljava/lang/String;)[B
    //   387: astore 4
    //   389: aload 4
    //   391: arraylength
    //   392: newarray byte
    //   394: astore_1
    //   395: iconst_0
    //   396: istore_2
    //   397: goto -174 -> 223
    //   400: bipush 57
    //   402: istore_2
    //   403: goto -400 -> 3
    //   406: astore_1
    //   407: new 115	java/lang/RuntimeException
    //   410: dup
    //   411: aload_1
    //   412: invokespecial 118	java/lang/RuntimeException:<init>	(Ljava/lang/Throwable;)V
    //   415: athrow
    //   416: iconst_1
    //   417: istore_3
    //   418: goto -180 -> 238
    // Local variable table:
    //   start	length	slot	name	signature
    //   0	421	0	this	KP
    //   0	421	1	paramString	String
    //   3	400	2	i	int
    //   51	367	3	j	int
    //   127	263	4	arrayOfByte	byte[]
    // Exception table:
    //   from	to	target	type
    //   203	211	47	java/lang/Exception
    //   194	198	188	java/lang/Exception
    //   55	135	406	java/io/UnsupportedEncodingException
    //   140	186	406	java/io/UnsupportedEncodingException
    //   223	227	406	java/io/UnsupportedEncodingException
    //   290	308	406	java/io/UnsupportedEncodingException
    //   315	395	406	java/io/UnsupportedEncodingException
  }
  
  /* Error */
  private static String ˎ(char[] paramArrayOfChar, int paramInt, byte paramByte)
  {
    // Byte code:
    //   0: goto +117 -> 117
    //   3: iconst_0
    //   4: istore_2
    //   5: goto +386 -> 391
    //   8: astore_0
    //   9: aload_0
    //   10: athrow
    //   11: bipush 69
    //   13: istore 7
    //   15: goto +509 -> 524
    //   18: aload 12
    //   20: iload_1
    //   21: iload 6
    //   23: iload 5
    //   25: isub
    //   26: i2c
    //   27: castore
    //   28: aload 12
    //   30: iload_1
    //   31: iconst_1
    //   32: iadd
    //   33: iload_2
    //   34: iload 5
    //   36: isub
    //   37: i2c
    //   38: castore
    //   39: goto +71 -> 110
    //   42: iconst_5
    //   43: istore 7
    //   45: goto +479 -> 524
    //   48: iload_1
    //   49: iconst_1
    //   50: isub
    //   51: istore 4
    //   53: aload 13
    //   55: iload 4
    //   57: aload_0
    //   58: iload 4
    //   60: caload
    //   61: iload_2
    //   62: isub
    //   63: i2c
    //   64: castore
    //   65: goto +110 -> 175
    //   68: getstatic 23	o/KP:ॱˑ	I
    //   71: bipush 59
    //   73: iadd
    //   74: istore_2
    //   75: iload_2
    //   76: sipush 128
    //   79: irem
    //   80: putstatic 25	o/KP:ॱـ	I
    //   83: iload_2
    //   84: iconst_2
    //   85: irem
    //   86: ifne +6 -> 92
    //   89: goto +562 -> 651
    //   92: goto +327 -> 419
    //   95: iload_2
    //   96: istore 5
    //   98: iload 4
    //   100: iconst_1
    //   101: if_icmple +6 -> 107
    //   104: goto +147 -> 251
    //   107: goto +257 -> 364
    //   110: iload_1
    //   111: iconst_2
    //   112: iadd
    //   113: istore_1
    //   114: goto +165 -> 279
    //   117: goto +207 -> 324
    //   120: iload 7
    //   122: iload_3
    //   123: invokestatic 123	o/oO:ˊ	(II)I
    //   126: istore_2
    //   127: iload 6
    //   129: iload_3
    //   130: invokestatic 123	o/oO:ˊ	(II)I
    //   133: istore 6
    //   135: iload_2
    //   136: iload 8
    //   138: iload_3
    //   139: invokestatic 127	o/oO:ˏ	(III)I
    //   142: istore_2
    //   143: iload 6
    //   145: iload 9
    //   147: iload_3
    //   148: invokestatic 127	o/oO:ˏ	(III)I
    //   151: istore 6
    //   153: aload 12
    //   155: iload_1
    //   156: aload 10
    //   158: iload_2
    //   159: caload
    //   160: castore
    //   161: aload 12
    //   163: iload_1
    //   164: iconst_1
    //   165: iadd
    //   166: aload 10
    //   168: iload 6
    //   170: caload
    //   171: castore
    //   172: goto -104 -> 68
    //   175: iload 5
    //   177: istore_3
    //   178: aload 11
    //   180: astore 10
    //   182: aload 13
    //   184: astore 12
    //   186: goto -91 -> 95
    //   189: getstatic 129	o/KP:ॱˈ	[C
    //   192: astore 14
    //   194: iload_1
    //   195: istore 4
    //   197: getstatic 131	o/KP:ॱˌ	C
    //   200: istore 6
    //   202: iload 4
    //   204: newarray char
    //   206: astore 15
    //   208: iload 4
    //   210: iconst_2
    //   211: iushr
    //   212: ifeq +6 -> 218
    //   215: goto -204 -> 11
    //   218: goto -176 -> 42
    //   221: iconst_1
    //   222: istore_3
    //   223: goto +459 -> 682
    //   226: iload_2
    //   227: tableswitch	default:+21->248, 0:+29->256, 1:+137->364
    //   248: goto +116 -> 364
    //   251: iconst_0
    //   252: istore_1
    //   253: goto +121 -> 374
    //   256: aload_0
    //   257: iload_1
    //   258: caload
    //   259: istore 6
    //   261: aload_0
    //   262: iload_1
    //   263: iconst_1
    //   264: iadd
    //   265: caload
    //   266: istore_2
    //   267: iload 6
    //   269: iload_2
    //   270: if_icmpne +6 -> 276
    //   273: goto -255 -> 18
    //   276: goto +146 -> 422
    //   279: goto +95 -> 374
    //   282: getstatic 129	o/KP:ॱˈ	[C
    //   285: astore 10
    //   287: iload_1
    //   288: istore 4
    //   290: getstatic 131	o/KP:ॱˌ	C
    //   293: istore_3
    //   294: iload 4
    //   296: newarray char
    //   298: astore 12
    //   300: iload 4
    //   302: iconst_2
    //   303: irem
    //   304: ifeq +17 -> 321
    //   307: iload_3
    //   308: istore 5
    //   310: aload 10
    //   312: astore 11
    //   314: aload 12
    //   316: astore 13
    //   318: goto -270 -> 48
    //   321: goto -226 -> 95
    //   324: getstatic 25	o/KP:ॱـ	I
    //   327: bipush 55
    //   329: iadd
    //   330: istore_3
    //   331: iload_3
    //   332: sipush 128
    //   335: irem
    //   336: putstatic 23	o/KP:ॱˑ	I
    //   339: iload_3
    //   340: iconst_2
    //   341: irem
    //   342: ifeq +6 -> 348
    //   345: goto +362 -> 707
    //   348: goto -127 -> 221
    //   351: iload 7
    //   353: iload 6
    //   355: if_icmpne +6 -> 361
    //   358: goto +288 -> 646
    //   361: goto -358 -> 3
    //   364: new 35	java/lang/String
    //   367: dup
    //   368: aload 12
    //   370: invokespecial 134	java/lang/String:<init>	([C)V
    //   373: areturn
    //   374: iload_1
    //   375: iload 4
    //   377: if_icmpge +6 -> 383
    //   380: goto +90 -> 470
    //   383: goto +82 -> 465
    //   386: iconst_1
    //   387: istore_2
    //   388: goto +266 -> 654
    //   391: iload_2
    //   392: tableswitch	default:+24->416, 0:+83->475, 1:+199->591
    //   416: goto +59 -> 475
    //   419: goto -309 -> 110
    //   422: iload 6
    //   424: iload_3
    //   425: invokestatic 136	o/oO:ॱ	(II)I
    //   428: istore 7
    //   430: iload 6
    //   432: iload_3
    //   433: invokestatic 138	o/oO:ˋ	(II)I
    //   436: istore 8
    //   438: iload_2
    //   439: iload_3
    //   440: invokestatic 136	o/oO:ॱ	(II)I
    //   443: istore 6
    //   445: iload_2
    //   446: iload_3
    //   447: invokestatic 138	o/oO:ˋ	(II)I
    //   450: istore 9
    //   452: iload 8
    //   454: iload 9
    //   456: if_icmpne +6 -> 462
    //   459: goto +60 -> 519
    //   462: goto -76 -> 386
    //   465: iconst_1
    //   466: istore_2
    //   467: goto -241 -> 226
    //   470: iconst_0
    //   471: istore_2
    //   472: goto -246 -> 226
    //   475: iload 7
    //   477: iload 9
    //   479: iload_3
    //   480: invokestatic 127	o/oO:ˏ	(III)I
    //   483: istore_2
    //   484: iload 6
    //   486: iload 8
    //   488: iload_3
    //   489: invokestatic 127	o/oO:ˏ	(III)I
    //   492: istore 6
    //   494: aload 12
    //   496: iload_1
    //   497: aload 10
    //   499: iload_2
    //   500: caload
    //   501: castore
    //   502: aload 12
    //   504: iload_1
    //   505: iconst_1
    //   506: iadd
    //   507: aload 10
    //   509: iload 6
    //   511: caload
    //   512: castore
    //   513: goto -403 -> 110
    //   516: astore_0
    //   517: aload_0
    //   518: athrow
    //   519: iconst_0
    //   520: istore_2
    //   521: goto +133 -> 654
    //   524: iload 6
    //   526: istore 5
    //   528: aload 14
    //   530: astore 11
    //   532: aload 15
    //   534: astore 13
    //   536: iload 6
    //   538: istore_3
    //   539: aload 14
    //   541: astore 10
    //   543: aload 15
    //   545: astore 12
    //   547: iload 7
    //   549: lookupswitch	default:+27->576, 5:+-454->95, 69:+-501->48
    //   576: iload 6
    //   578: istore 5
    //   580: aload 14
    //   582: astore 11
    //   584: aload 15
    //   586: astore 13
    //   588: goto -540 -> 48
    //   591: iload 8
    //   593: iload_3
    //   594: invokestatic 123	o/oO:ˊ	(II)I
    //   597: istore_2
    //   598: iload 9
    //   600: iload_3
    //   601: invokestatic 123	o/oO:ˊ	(II)I
    //   604: istore 8
    //   606: iload 7
    //   608: iload_2
    //   609: iload_3
    //   610: invokestatic 127	o/oO:ˏ	(III)I
    //   613: istore_2
    //   614: iload 6
    //   616: iload 8
    //   618: iload_3
    //   619: invokestatic 127	o/oO:ˏ	(III)I
    //   622: istore 6
    //   624: aload 12
    //   626: iload_1
    //   627: aload 10
    //   629: iload_2
    //   630: caload
    //   631: castore
    //   632: aload 12
    //   634: iload_1
    //   635: iconst_1
    //   636: iadd
    //   637: aload 10
    //   639: iload 6
    //   641: caload
    //   642: castore
    //   643: goto +36 -> 679
    //   646: iconst_1
    //   647: istore_2
    //   648: goto -257 -> 391
    //   651: goto -232 -> 419
    //   654: iload_2
    //   655: tableswitch	default:+21->676, 0:+-535->120, 1:+-304->351
    //   676: goto -325 -> 351
    //   679: goto -569 -> 110
    //   682: iload_3
    //   683: tableswitch	default:+21->704, 0:+-494->189, 1:+-401->282
    //   704: goto -422 -> 282
    //   707: iconst_0
    //   708: istore_3
    //   709: goto -27 -> 682
    // Local variable table:
    //   start	length	slot	name	signature
    //   0	712	0	paramArrayOfChar	char[]
    //   0	712	1	paramInt	int
    //   0	712	2	paramByte	byte
    //   122	587	3	b1	byte
    //   51	327	4	i	int
    //   23	556	5	b2	byte
    //   21	619	6	b3	byte
    //   13	594	7	b4	byte
    //   136	481	8	j	int
    //   145	454	9	k	int
    //   156	482	10	localObject1	Object
    //   178	405	11	localObject2	Object
    //   18	615	12	localObject3	Object
    //   53	534	13	localObject4	Object
    //   192	389	14	arrayOfChar1	char[]
    //   206	379	15	arrayOfChar2	char[]
    // Exception table:
    //   from	to	target	type
    //   282	287	8	java/lang/Exception
    //   290	294	8	java/lang/Exception
    //   294	300	8	java/lang/Exception
    //   591	598	8	java/lang/Exception
    //   290	294	516	java/lang/Exception
    //   598	606	516	java/lang/Exception
    //   606	614	516	java/lang/Exception
  }
  
  static void ˎ()
  {
    ॱˈ = new char[] { 5, 26, 11, 12, 73, 83, 79, 45, 56, 53, 57, 49, 85, 84, 70, 6 };
    ॱˌ = '\004';
  }
  
  /* Error */
  public void ˋ(ᐸ paramᐸ, ะ paramะ)
  {
    // Byte code:
    //   0: goto +191 -> 191
    //   3: goto +17 -> 20
    //   6: astore_1
    //   7: aload_1
    //   8: invokevirtual 158	java/lang/Throwable:getCause	()Ljava/lang/Throwable;
    //   11: astore_2
    //   12: aload_2
    //   13: ifnull +5 -> 18
    //   16: aload_2
    //   17: athrow
    //   18: aload_1
    //   19: athrow
    //   20: iconst_4
    //   21: sipush 413
    //   24: sipush 30253
    //   27: invokestatic 163	o/O:ˋ	(IIC)Ljava/lang/Object;
    //   30: checkcast 165	java/lang/Class
    //   33: ldc -89
    //   35: aconst_null
    //   36: invokevirtual 171	java/lang/Class:getMethod	(Ljava/lang/String;[Ljava/lang/Class;)Ljava/lang/reflect/Method;
    //   39: aconst_null
    //   40: aconst_null
    //   41: invokevirtual 177	java/lang/reflect/Method:invoke	(Ljava/lang/Object;[Ljava/lang/Object;)Ljava/lang/Object;
    //   44: astore_2
    //   45: getstatic 183	o/ED:USER_NOT_IDENTIFIED	Lo/ED;
    //   48: astore 4
    //   50: goto +17 -> 67
    //   53: astore_1
    //   54: aload_1
    //   55: invokevirtual 158	java/lang/Throwable:getCause	()Ljava/lang/Throwable;
    //   58: astore_2
    //   59: aload_2
    //   60: ifnull +5 -> 65
    //   63: aload_2
    //   64: athrow
    //   65: aload_1
    //   66: athrow
    //   67: iconst_4
    //   68: sipush 413
    //   71: sipush 30253
    //   74: invokestatic 163	o/O:ˋ	(IIC)Ljava/lang/Object;
    //   77: checkcast 165	java/lang/Class
    //   80: ldc -72
    //   82: iconst_1
    //   83: anewarray 165	java/lang/Class
    //   86: dup
    //   87: iconst_0
    //   88: ldc -77
    //   90: aastore
    //   91: invokevirtual 171	java/lang/Class:getMethod	(Ljava/lang/String;[Ljava/lang/Class;)Ljava/lang/reflect/Method;
    //   94: aload_2
    //   95: iconst_1
    //   96: anewarray 186	java/lang/Object
    //   99: dup
    //   100: iconst_0
    //   101: aload 4
    //   103: aastore
    //   104: invokevirtual 177	java/lang/reflect/Method:invoke	(Ljava/lang/Object;[Ljava/lang/Object;)Ljava/lang/Object;
    //   107: pop
    //   108: aload_0
    //   109: invokevirtual 189	o/KP:ˋ	()Landroid/content/Context;
    //   112: invokestatic 194	o/Ic:ˏ	(Landroid/content/Context;)Lo/Ic;
    //   115: invokevirtual 198	o/Ic:ᐝ	()Lo/j;
    //   118: bipush 13
    //   120: invokevirtual 203	o/j:ˎ	(I)V
    //   123: goto +98 -> 221
    //   126: getstatic 25	o/KP:ॱـ	I
    //   129: bipush 35
    //   131: iadd
    //   132: istore_3
    //   133: iload_3
    //   134: sipush 128
    //   137: irem
    //   138: putstatic 23	o/KP:ॱˑ	I
    //   141: iload_3
    //   142: iconst_2
    //   143: irem
    //   144: ifeq +6 -> 150
    //   147: goto +81 -> 228
    //   150: bipush 58
    //   152: istore_3
    //   153: goto +82 -> 235
    //   156: getstatic 206	o/KP$3:ˊ	[I
    //   159: astore 4
    //   161: aload 4
    //   163: aload_2
    //   164: invokevirtual 212	o/ะ:ordinal	()I
    //   167: iaload
    //   168: istore_3
    //   169: iload_3
    //   170: lookupswitch	default:+18->188, 1:+-167->3
    //   188: goto +33 -> 221
    //   191: getstatic 23	o/KP:ॱˑ	I
    //   194: bipush 99
    //   196: iadd
    //   197: istore_3
    //   198: iload_3
    //   199: sipush 128
    //   202: irem
    //   203: putstatic 25	o/KP:ॱـ	I
    //   206: iload_3
    //   207: iconst_2
    //   208: irem
    //   209: ifne +6 -> 215
    //   212: goto +53 -> 265
    //   215: goto -59 -> 156
    //   218: astore_1
    //   219: aload_1
    //   220: athrow
    //   221: aload_1
    //   222: invokevirtual 217	o/ᐸ:dismiss	()V
    //   225: goto -99 -> 126
    //   228: bipush 38
    //   230: istore_3
    //   231: goto +4 -> 235
    //   234: return
    //   235: iload_3
    //   236: lookupswitch	default:+28->264, 38:+32->268, 58:+-2->234
    //   264: return
    //   265: goto -109 -> 156
    //   268: aconst_null
    //   269: arraylength
    //   270: istore_3
    //   271: return
    // Local variable table:
    //   start	length	slot	name	signature
    //   0	272	0	this	KP
    //   0	272	1	paramᐸ	ᐸ
    //   0	272	2	paramะ	ะ
    //   132	139	3	i	int
    //   48	114	4	localObject	Object
    // Exception table:
    //   from	to	target	type
    //   20	45	6	finally
    //   67	108	53	finally
    //   156	161	218	java/lang/Exception
    //   161	169	218	java/lang/Exception
  }
}
