package o;

import java.io.IOException;
import java.net.SocketTimeoutException;
import java.util.ArrayList;
import java.util.Collection;
import java.util.Date;
import java.util.Iterator;
import java.util.List;

public final class KS
  extends Iy<KO.ˋ, Kk>
  implements KO.iF
{
  private static int ʻ;
  private static int ˊ;
  private static byte[] ˋ;
  private static int ˎ = 1197176077;
  private static short[] ˏ;
  private static int ॱ;
  private static int ॱॱ = 0;
  
  static
  {
    ʻ = 1;
    ˊ = 81;
    ˋ = new byte[] { -58, 7, 1, -11, 34, -33, -1, 6, -11, 17, 2, -18, 5, 13, -17, 30, -32, 6, 9, -8, -12, 24, -15, -76, 0, 51, -14, 0, -65, 1, 14, -13, 17, -7, 5, -18, 51, 19, -54, -11, 1, -3, -3, 48, -77, 18, -4, -13, -71, 7, 3, -5, 11, -10, 4, -1, 11, -13 };
    ॱ = -175042488;
  }
  
  @uv
  public KS(KO.ˋ paramˋ, Kk paramKk)
  {
    super((Iu.if)paramˋ, (Ib)paramKk);
  }
  
  private static String ˎ(short paramShort, int paramInt1, byte paramByte, int paramInt2, int paramInt3)
  {
    break label39;
    int k = 28;
    break label272;
    label39:
    label73:
    Object localObject2;
    int j;
    int i;
    switch (paramInt3)
    {
    default: 
      break;
    case 1: 
      paramInt3 = (byte)(ˋ[(ˎ + paramInt1)] + ˊ);
      break label499;
      if (ˋ != null) {
        break label575;
      }
      break label510;
      localObject2 = ˋ;
      j = paramInt1 + 112;
      i = (char)(k << ((byte)(localObject2[paramInt1] + paramShort) & paramByte));
      paramInt1 = j;
      break;
    }
    for (;;)
    {
      try
      {
        paramInt3 = ॱॱ + 125;
        ʻ = paramInt3 % 128;
        if (paramInt3 % 2 != 0)
        {
          continue;
          label135:
          return localObject1.toString();
          paramInt3 = (byte)(ˋ[(paramInt1 >>> ˎ)] % ˊ);
          break label499;
          j = 1;
          continue;
          paramInt3 = 1;
          break;
          label172:
          k = 3;
          continue;
          if (ˋ != null) {
            continue;
          }
          break label360;
          label190:
          paramInt1 = paramInt1 + paramInt3 - 2 + k + j;
        }
      }
      catch (Exception localException1)
      {
        Object localObject1;
        label232:
        label269:
        label272:
        throw localException1;
      }
      try
      {
        j = ॱ;
        i = (char)(j + paramInt2);
        localObject1.append(i);
        paramInt2 = 1;
        k = i;
      }
      catch (Exception localException2)
      {
        throw localException2;
      }
      localObject2 = ˋ;
      j = paramInt1 - 1;
      i = (char)(((byte)(localObject2[paramInt1] + paramShort) ^ paramByte) + k);
      paramInt1 = j;
      break label439;
      paramInt3 = 0;
      break;
      break label458;
      switch (k)
      {
      case 28: 
      default: 
        continue;
        label308:
        break label499;
        label316:
        j = 1;
      }
    }
    label322:
    k = 4 / 4;
    for (;;)
    {
      paramInt1 = ʻ + 51;
      ॱॱ = paramInt1 % 128;
      if (paramInt1 % 2 == 0)
      {
        break label415;
        label357:
        break label660;
        label360:
        paramInt3 = (short)(ˏ[(ˎ + paramInt1)] + ˊ);
        break label308;
      }
      for (;;)
      {
        k = ʻ + 113;
        ॱॱ = k % 128;
        if (k % 2 != 0) {
          break label322;
        }
        break label269;
        label409:
        j = 0;
        break label190;
        label415:
        paramInt1 = j;
        for (;;)
        {
          j = 0;
          break label458;
          while (paramInt2 >= paramInt3)
          {
            break label135;
            label439:
            localException2.append(i);
            paramInt2 += 1;
            k = i;
          }
          label458:
          if (j != 0) {
            break;
          }
          break label172;
          j = ॱॱ + 47;
          ʻ = j % 128;
          if (j % 2 == 0) {
            break label73;
          }
          break label232;
          label499:
          if (paramInt3 <= 0)
          {
            break label135;
            label510:
            j = 1;
          }
          label575:
          do
          {
            j = ॱॱ + 77;
            ʻ = j % 128;
            if (j % 2 == 0) {
              break label357;
            }
            break label660;
            break label415;
            for (;;)
            {
              switch (j)
              {
              case 0: 
              default: 
                break label666;
                j = 0;
              }
            }
            k = ˎ;
            if (j == 0) {
              break label409;
            }
            j = ʻ + 125;
            ॱॱ = j % 128;
            if (j % 2 != 0) {
              break label316;
            }
            break;
            StringBuilder localStringBuilder = new StringBuilder();
            j = ˊ + paramInt3;
            paramInt3 = j;
          } while (j == -1);
        }
        label660:
        j = 1;
      }
      label666:
      localObject2 = ˏ;
      j = paramInt1 - 1;
      paramInt1 = localObject2[paramInt1];
      i = (char)(((short)(paramInt1 + paramShort) ^ paramByte) + k);
    }
  }
  
  private final List<Kl> ˏ(Gf paramGf)
  {
    break label71;
    int i = 0;
    break label99;
    ArrayList localArrayList;
    for (;;)
    {
      label44:
      do
      {
        i = 1;
        break;
        for (;;)
        {
          paramGf = (Collection)localArrayList;
          return (List)localArrayList;
          if (paramGf.hasNext()) {
            break;
          }
        }
        i = ʻ + 103;
        ॱॱ = i % 128;
      } while (i % 2 != 0);
      break;
      label71:
      break label132;
      label74:
      switch (i)
      {
      }
    }
    switch (i)
    {
    case 0: 
    default: 
      label99:
      break;
    }
    for (;;)
    {
      i = 1;
      break label74;
      label132:
      localArrayList = new ArrayList();
      paramGf = ((Iterable)paramGf.ˊ()).iterator();
      break label44;
      break;
      label316:
      do
      {
        i = 0;
        break label74;
        Object localObject = paramGf.next();
        Collection localCollection = (Collection)localArrayList;
        localObject = (Ev)localObject;
        localCollection.add(new Kl(ak.ˏ(new Date(((Ev)localObject).ˎ())), ak.ˎ(new Date(((Ev)localObject).ˎ()), ˎ((short)0, -1197176054, (byte)0, 175042560, -82).intern(), ˎ((short)0, -1197176049, (byte)0, 175042557, -82).intern()), ((Ev)localObject).ˊ(), ((Ev)localObject).ॱ(), ((Ev)localObject).ˏ().ˋ(), ((Ev)localObject).ˏ().ˏ(), ((Ev)localObject).ˋ().ˏ(), Integer.valueOf(Hn.ॱ.ॱ(((Ev)localObject).ˋ()))));
        break label316;
        i = 4 / 5;
        break;
        i = ॱॱ + 123;
        ʻ = i % 128;
      } while (i % 2 == 0);
    }
  }
  
  public void ˏ(String paramString, long paramLong1, long paramLong2)
  {
    for (;;)
    {
      ((Kk)ʼ()).ॱ(paramString, paramLong1, paramLong2).ˋ((sV)new if(this)).ˋ(sB.ˋ()).ˊ((sW)new If(this)).ˊ((sW)new ˋ(this), (sW)new iF(this));
      i = ʻ + 3;
      ॱॱ = i % 128;
      if (i % 2 == 0)
      {
        i = 58;
        break;
      }
      i = 86;
      break;
      return;
    }
    int i = 99 / 0;
    return;
    switch (i)
    {
    }
  }
  
  /* Error */
  public void ॱ(Kl paramKl)
  {
    // Byte code:
    //   0: goto +12 -> 12
    //   3: bipush 70
    //   5: istore_2
    //   6: goto +33 -> 39
    //   9: astore_1
    //   10: aload_1
    //   11: athrow
    //   12: getstatic 31	o/KS:ʻ	I
    //   15: bipush 43
    //   17: iadd
    //   18: istore_2
    //   19: iload_2
    //   20: sipush 128
    //   23: irem
    //   24: putstatic 29	o/KS:ॱॱ	I
    //   27: iload_2
    //   28: iconst_2
    //   29: irem
    //   30: ifeq +6 -> 36
    //   33: goto +41 -> 74
    //   36: goto -33 -> 3
    //   39: iload_2
    //   40: lookupswitch	default:+28->68, 70:+40->80, 94:+74->114
    //   68: goto +12 -> 80
    //   71: astore_1
    //   72: aload_1
    //   73: athrow
    //   74: bipush 94
    //   76: istore_2
    //   77: goto -38 -> 39
    //   80: aload_1
    //   81: iconst_0
    //   82: ldc_w 281
    //   85: iconst_0
    //   86: ldc_w 282
    //   89: bipush -82
    //   91: invokestatic 92	o/KS:ˎ	(SIBII)Ljava/lang/String;
    //   94: invokevirtual 98	java/lang/String:intern	()Ljava/lang/String;
    //   97: invokestatic 103	o/vq:ˎ	(Ljava/lang/Object;Ljava/lang/String;)V
    //   100: aload_0
    //   101: invokevirtual 128	o/KS:ʽ	()Lo/Iu$if;
    //   104: checkcast 130	o/KO$ˋ
    //   107: aload_1
    //   108: invokeinterface 284 2 0
    //   113: return
    //   114: iconst_1
    //   115: ldc_w 281
    //   118: iconst_0
    //   119: ldc_w 282
    //   122: bipush 124
    //   124: invokestatic 92	o/KS:ˎ	(SIBII)Ljava/lang/String;
    //   127: astore_3
    //   128: aload_3
    //   129: invokevirtual 98	java/lang/String:intern	()Ljava/lang/String;
    //   132: astore_3
    //   133: aload_1
    //   134: aload_3
    //   135: invokestatic 103	o/vq:ˎ	(Ljava/lang/Object;Ljava/lang/String;)V
    //   138: aload_0
    //   139: invokevirtual 128	o/KS:ʽ	()Lo/Iu$if;
    //   142: checkcast 130	o/KO$ˋ
    //   145: aload_1
    //   146: invokeinterface 284 2 0
    //   151: return
    // Local variable table:
    //   start	length	slot	name	signature
    //   0	152	0	this	KS
    //   0	152	1	paramKl	Kl
    //   5	72	2	i	int
    //   127	8	3	str	String
    // Exception table:
    //   from	to	target	type
    //   114	128	9	java/lang/Exception
    //   128	133	9	java/lang/Exception
    //   133	138	9	java/lang/Exception
    //   138	151	9	java/lang/Exception
    //   133	138	71	java/lang/Exception
  }
  
  static final class If<T>
    implements sW<Throwable>
  {
    If(KS paramKS) {}
    
    public final void ˏ(Throwable paramThrowable)
    {
      KS.ˋ(this.ˊ).D_();
    }
  }
  
  static final class iF<T>
    implements sW<Throwable>
  {
    iF(KS paramKS) {}
    
    public final void ˊ(Throwable paramThrowable)
    {
      if (((paramThrowable instanceof IOException)) || ((paramThrowable instanceof SocketTimeoutException))) {
        KS.ˎ(this.ˊ);
      }
    }
  }
  
  static final class if<T, R>
    implements sV<T, R>
  {
    private static int ʻ = 0;
    private static int ʼ = 1;
    private static int ˊ = 1;
    private static int ˋ = 1469356588;
    private static byte[] ˎ = { 5, -1, 6, -11, 17, 2, -18, 5, 13, -17, -2, 0 };
    private static int ˏ = -915445113;
    private static short[] ॱॱ;
    
    if(KS paramKS) {}
    
    /* Error */
    private static String ˊ(short paramShort, int paramInt1, byte paramByte, int paramInt2, int paramInt3)
    {
      // Byte code:
      //   0: goto +435 -> 435
      //   3: aload 8
      //   5: invokevirtual 66	java/lang/StringBuilder:toString	()Ljava/lang/String;
      //   8: areturn
      //   9: iload 7
      //   11: istore 4
      //   13: goto +93 -> 106
      //   16: getstatic 50	o/KS$if:ˋ	I
      //   19: istore 7
      //   21: iload 6
      //   23: ifeq +6 -> 29
      //   26: goto +17 -> 43
      //   29: goto +274 -> 303
      //   32: iload 6
      //   34: ifeq +6 -> 40
      //   37: goto +350 -> 387
      //   40: goto +66 -> 106
      //   43: bipush 13
      //   45: istore 6
      //   47: goto +356 -> 403
      //   50: getstatic 44	o/KS$if:ˎ	[B
      //   53: astore 9
      //   55: iload_1
      //   56: iconst_1
      //   57: isub
      //   58: istore 6
      //   60: aload 9
      //   62: iload_1
      //   63: baload
      //   64: iload_0
      //   65: iadd
      //   66: i2b
      //   67: iload_2
      //   68: ixor
      //   69: iload 7
      //   71: iadd
      //   72: i2c
      //   73: istore 5
      //   75: iload 6
      //   77: istore_1
      //   78: goto +252 -> 330
      //   81: goto +403 -> 484
      //   84: iconst_0
      //   85: istore 6
      //   87: goto -55 -> 32
      //   90: getstatic 44	o/KS$if:ˎ	[B
      //   93: getstatic 50	o/KS$if:ˋ	I
      //   96: iload_1
      //   97: iadd
      //   98: baload
      //   99: getstatic 31	o/KS$if:ˊ	I
      //   102: iadd
      //   103: i2b
      //   104: istore 4
      //   106: iload 4
      //   108: ifle +6 -> 114
      //   111: goto +592 -> 703
      //   114: goto +70 -> 184
      //   117: bipush 65
      //   119: istore 4
      //   121: goto +100 -> 221
      //   124: new 62	java/lang/StringBuilder
      //   127: dup
      //   128: invokespecial 67	java/lang/StringBuilder:<init>	()V
      //   131: astore 8
      //   133: getstatic 31	o/KS$if:ˊ	I
      //   136: iload 4
      //   138: iadd
      //   139: istore 6
      //   141: iload 6
      //   143: istore 4
      //   145: iload 6
      //   147: iconst_m1
      //   148: if_icmpne +6 -> 154
      //   151: goto +327 -> 478
      //   154: goto -70 -> 84
      //   157: getstatic 29	o/KS$if:ʼ	I
      //   160: bipush 73
      //   162: iadd
      //   163: istore_1
      //   164: iload_1
      //   165: sipush 128
      //   168: irem
      //   169: putstatic 27	o/KS$if:ʻ	I
      //   172: iload_1
      //   173: iconst_2
      //   174: irem
      //   175: ifeq +6 -> 181
      //   178: goto +144 -> 322
      //   181: goto +394 -> 575
      //   184: bipush 77
      //   186: istore 7
      //   188: goto +168 -> 356
      //   191: getstatic 29	o/KS$if:ʼ	I
      //   194: bipush 83
      //   196: iadd
      //   197: istore 4
      //   199: iload 4
      //   201: sipush 128
      //   204: irem
      //   205: putstatic 27	o/KS$if:ʻ	I
      //   208: iload 4
      //   210: iconst_2
      //   211: irem
      //   212: ifeq +6 -> 218
      //   215: goto -98 -> 117
      //   218: goto +363 -> 581
      //   221: iload 4
      //   223: lookupswitch	default:+25->248, 65:+424->647, 91:+-133->90
      //   248: goto +399 -> 647
      //   251: iconst_1
      //   252: istore 4
      //   254: goto +10 -> 264
      //   257: iload 7
      //   259: istore 4
      //   261: goto -155 -> 106
      //   264: iload 4
      //   266: tableswitch	default:+22->288, 0:+322->588, 1:+-75->191
      //   288: goto -97 -> 191
      //   291: astore 8
      //   293: aload 8
      //   295: athrow
      //   296: bipush 93
      //   298: istore 6
      //   300: goto +244 -> 544
      //   303: bipush 30
      //   305: istore 6
      //   307: goto +96 -> 403
      //   310: iload_3
      //   311: iload 4
      //   313: if_icmpge +6 -> 319
      //   316: goto -20 -> 296
      //   319: goto +347 -> 666
      //   322: goto +253 -> 575
      //   325: astore 8
      //   327: aload 8
      //   329: athrow
      //   330: aload 8
      //   332: iload 5
      //   334: invokevirtual 71	java/lang/StringBuilder:append	(C)Ljava/lang/StringBuilder;
      //   337: pop
      //   338: iload_3
      //   339: iconst_1
      //   340: iadd
      //   341: istore_3
      //   342: iload 5
      //   344: istore 7
      //   346: goto -36 -> 310
      //   349: bipush 84
      //   351: istore 4
      //   353: goto +320 -> 673
      //   356: iload 7
      //   358: lookupswitch	default:+26->384, 13:+-342->16, 77:+-355->3
      //   384: goto -381 -> 3
      //   387: getstatic 44	o/KS$if:ˎ	[B
      //   390: astore 9
      //   392: aload 9
      //   394: ifnull +6 -> 400
      //   397: goto -146 -> 251
      //   400: goto +126 -> 526
      //   403: iload 6
      //   405: lookupswitch	default:+27->432, 13:+67->472, 30:+127->532
      //   432: goto +40 -> 472
      //   435: goto -311 -> 124
      //   438: getstatic 29	o/KS$if:ʼ	I
      //   441: istore 4
      //   443: iload 4
      //   445: bipush 41
      //   447: iadd
      //   448: istore 4
      //   450: iload 4
      //   452: sipush 128
      //   455: irem
      //   456: putstatic 27	o/KS$if:ʻ	I
      //   459: iload 4
      //   461: iconst_2
      //   462: irem
      //   463: ifeq +6 -> 469
      //   466: goto +72 -> 538
      //   469: goto -120 -> 349
      //   472: iconst_1
      //   473: istore 6
      //   475: goto +9 -> 484
      //   478: iconst_1
      //   479: istore 6
      //   481: goto -449 -> 32
      //   484: iload_1
      //   485: iload 4
      //   487: iadd
      //   488: iconst_2
      //   489: isub
      //   490: iload 7
      //   492: iadd
      //   493: iload 6
      //   495: iadd
      //   496: istore_1
      //   497: getstatic 47	o/KS$if:ˏ	I
      //   500: istore 6
      //   502: iload 6
      //   504: iload_3
      //   505: iadd
      //   506: i2c
      //   507: istore 5
      //   509: aload 8
      //   511: iload 5
      //   513: invokevirtual 71	java/lang/StringBuilder:append	(C)Ljava/lang/StringBuilder;
      //   516: pop
      //   517: iconst_1
      //   518: istore_3
      //   519: iload 5
      //   521: istore 7
      //   523: goto -213 -> 310
      //   526: iconst_0
      //   527: istore 4
      //   529: goto -265 -> 264
      //   532: iconst_0
      //   533: istore 6
      //   535: goto -454 -> 81
      //   538: iconst_3
      //   539: istore 4
      //   541: goto +132 -> 673
      //   544: iload 6
      //   546: lookupswitch	default:+26->572, 78:+-543->3, 93:+89->635
      //   572: goto -569 -> 3
      //   575: iload 6
      //   577: istore_1
      //   578: goto -248 -> 330
      //   581: bipush 91
      //   583: istore 4
      //   585: goto -364 -> 221
      //   588: getstatic 73	o/KS$if:ॱॱ	[S
      //   591: getstatic 50	o/KS$if:ˋ	I
      //   594: iload_1
      //   595: iadd
      //   596: saload
      //   597: getstatic 31	o/KS$if:ˊ	I
      //   600: iadd
      //   601: i2s
      //   602: istore 7
      //   604: goto -166 -> 438
      //   607: getstatic 73	o/KS$if:ॱॱ	[S
      //   610: astore 9
      //   612: iload_1
      //   613: iconst_1
      //   614: isub
      //   615: istore 6
      //   617: aload 9
      //   619: iload_1
      //   620: saload
      //   621: iload_0
      //   622: iadd
      //   623: i2s
      //   624: iload_2
      //   625: ixor
      //   626: iload 7
      //   628: iadd
      //   629: i2c
      //   630: istore 5
      //   632: goto -475 -> 157
      //   635: getstatic 44	o/KS$if:ˎ	[B
      //   638: ifnull +6 -> 644
      //   641: goto -591 -> 50
      //   644: goto -37 -> 607
      //   647: getstatic 44	o/KS$if:ˎ	[B
      //   650: getstatic 50	o/KS$if:ˋ	I
      //   653: iload_1
      //   654: iadd
      //   655: baload
      //   656: getstatic 31	o/KS$if:ˊ	I
      //   659: ishr
      //   660: i2b
      //   661: istore 4
      //   663: goto -557 -> 106
      //   666: bipush 78
      //   668: istore 6
      //   670: goto -126 -> 544
      //   673: iload 4
      //   675: lookupswitch	default:+25->700, 3:+-666->9, 84:+-418->257
      //   700: goto -443 -> 257
      //   703: bipush 13
      //   705: istore 7
      //   707: goto -351 -> 356
      // Local variable table:
      //   start	length	slot	name	signature
      //   0	710	0	paramShort	short
      //   0	710	1	paramInt1	int
      //   0	710	2	paramByte	byte
      //   0	710	3	paramInt2	int
      //   0	710	4	paramInt3	int
      //   73	558	5	i	int
      //   21	648	6	j	int
      //   9	697	7	k	int
      //   3	129	8	localStringBuilder	StringBuilder
      //   291	3	8	localException1	Exception
      //   325	185	8	localException2	Exception
      //   53	565	9	localObject	Object
      // Exception table:
      //   from	to	target	type
      //   497	502	291	java/lang/Exception
      //   509	517	291	java/lang/Exception
      //   387	392	325	java/lang/Exception
      //   438	443	325	java/lang/Exception
      //   450	459	325	java/lang/Exception
    }
    
    public final List<Kl> ˊ(Gf paramGf)
    {
      break label5;
      return paramGf;
      label5:
      int i = ʻ + 61;
      ʼ = i % 128;
      if (i % 2 != 0) {
        break label38;
      }
      for (;;)
      {
        i = 86;
        break;
        label38:
        vq.ˎ(paramGf, ˊ((short)0, -1469356588, (byte)0, 915445229, 11).intern());
        paramGf = KS.ˋ(this.ॱ, paramGf);
        try
        {
          i = ʻ + 83;
          ʼ = i % 128;
          if (i % 2 != 0) {
            i = 44;
          }
        }
        catch (Exception paramGf)
        {
          throw paramGf;
        }
      }
      switch (i)
      {
      case 44: 
      default: 
        return paramGf;
      }
      throw new NullPointerException();
    }
  }
  
  static final class ˋ<T>
    implements sW<List<? extends Kl>>
  {
    private static int ˊ = 85;
    private static int ˋ = 0;
    private static int ˏ = 1;
    
    ˋ(KS paramKS) {}
    
    private static String ˏ(int paramInt1, int paramInt2, char[] paramArrayOfChar, int paramInt3, boolean paramBoolean)
    {
      break label221;
      int j = ˏ + 109;
      ˋ = j % 128;
      label39:
      char[] arrayOfChar;
      if (j % 2 == 0)
      {
        break label252;
        paramInt2 = 33;
        break label148;
        paramArrayOfChar = arrayOfChar;
      }
      label71:
      label77:
      int i;
      label107:
      label129:
      int k;
      switch (paramInt1)
      {
      default: 
        break label224;
        paramInt2 = 60;
        break label148;
        i = ˋ + 119;
        ˏ = i % 128;
        if (i % 2 != 0)
        {
          break;
          break label237;
          paramArrayOfChar[paramInt1] = arrayOfChar[(j - paramInt1 - 1)];
          paramInt1 += 1;
          break label288;
        }
        else
        {
          for (;;)
          {
            k = paramInt3;
            j = paramInt2;
            if (i < j) {
              break;
            }
            break label346;
            label148:
            switch (paramInt2)
            {
            }
            break label107;
            arrayOfChar = new char[paramInt2];
            i = 0;
          }
        }
        break;
      }
      for (;;)
      {
        if (!paramBoolean) {
          break label246;
        }
        paramInt1 = 15;
        break label39;
        arrayOfChar = new char[paramInt2];
        i = 0;
        break label129;
        label221:
        break label77;
        label224:
        paramArrayOfChar = new char[j];
        paramInt1 = 0;
        break label288;
        for (;;)
        {
          break label129;
          label237:
          return new String(paramArrayOfChar);
          label246:
          paramInt1 = 75;
          break;
          label252:
          arrayOfChar[i] = ((char)(paramInt1 + paramArrayOfChar[i]));
          arrayOfChar[i] = ((char)(arrayOfChar[i] - ˊ));
          i += 1;
        }
        label288:
        if (paramInt1 < j) {
          break;
        }
        break label71;
        label346:
        do
        {
          paramArrayOfChar = new char[j];
          System.arraycopy(arrayOfChar, 0, paramArrayOfChar, 0, j);
          System.arraycopy(paramArrayOfChar, 0, arrayOfChar, j - k, k);
          System.arraycopy(paramArrayOfChar, k, arrayOfChar, 0, j - k);
          break;
        } while (k > 0);
      }
    }
    
    public final void ˏ(List<Kl> paramList)
    {
      for (;;)
      {
        int i = ˏ + 73;
        ˋ = i % 128;
        if (i % 2 == 0)
        {
          break label40;
          return;
          break label111;
        }
        else
        {
          i = 64;
          break label43;
        }
        label40:
        i = 50;
        switch (i)
        {
        case 50: 
        default: 
          label43:
          return;
        }
        for (;;)
        {
          i = ˋ + 55;
          ˏ = i % 128;
          if (i % 2 == 0) {
            break;
          }
          break;
          throw new NullPointerException();
        }
        label111:
        vq.ˎ(paramList, ˏ(191, 17, new char[] { -1, 10, -7, -9, 9, 4, -9, 8, 10, 2, -5, -6, 5, -29, 9, 4, 5 }, 9, true).intern());
        KS.ˋ(this.ॱ).ˊ(paramList);
      }
    }
  }
}
