package o;

import android.content.Context;
import android.os.Bundle;

public final class KT
  extends K<JO>
{
  private static int ʻ;
  public static final if ˋ;
  private static char[] ˎ;
  private static final String ॱ;
  private static int ᐝ;
  private String ˊ;
  
  static
  {
    break label40;
    int i = null.length;
    return;
    for (;;)
    {
      switch (i)
      {
      case 18: 
      default: 
        break;
      case 95: 
        return;
        label40:
        ᐝ = 0;
        ʻ = 1;
        ﹳ();
        ˋ = new if(null);
        ॱ = ˏ(new int[] { 75, 37, 0, 0 }, new byte[] { 1, 1, 0, 0, 1, 0, 1, 0, 1, 1, 1, 0, 0, 1, 1, 0, 1, 1, 0, 0, 0, 1, 0, 1, 0, 1, 1, 1, 1, 1, 1, 0, 0, 0, 0, 0, 1 }, false).intern();
        i = ᐝ + 97;
        ʻ = i % 128;
        if (i % 2 != 0) {
          break label346;
        }
        i = 18;
        continue;
        label346:
        i = 95;
      }
    }
  }
  
  public KT() {}
  
  /* Error */
  private final void ʻˋ()
  {
    // Byte code:
    //   0: goto +788 -> 788
    //   3: iconst_4
    //   4: newarray int
    //   6: dup
    //   7: iconst_0
    //   8: bipush 58
    //   10: iastore
    //   11: dup
    //   12: iconst_1
    //   13: bipush 17
    //   15: iastore
    //   16: dup
    //   17: iconst_2
    //   18: iconst_0
    //   19: iastore
    //   20: dup
    //   21: iconst_3
    //   22: iconst_0
    //   23: iastore
    //   24: bipush 17
    //   26: newarray byte
    //   28: dup
    //   29: iconst_0
    //   30: ldc 37
    //   32: bastore
    //   33: dup
    //   34: iconst_1
    //   35: ldc 36
    //   37: bastore
    //   38: dup
    //   39: iconst_2
    //   40: ldc 37
    //   42: bastore
    //   43: dup
    //   44: iconst_3
    //   45: ldc 37
    //   47: bastore
    //   48: dup
    //   49: iconst_4
    //   50: ldc 37
    //   52: bastore
    //   53: dup
    //   54: iconst_5
    //   55: ldc 37
    //   57: bastore
    //   58: dup
    //   59: bipush 6
    //   61: ldc 36
    //   63: bastore
    //   64: dup
    //   65: bipush 7
    //   67: ldc 36
    //   69: bastore
    //   70: dup
    //   71: bipush 8
    //   73: ldc 36
    //   75: bastore
    //   76: dup
    //   77: bipush 9
    //   79: ldc 36
    //   81: bastore
    //   82: dup
    //   83: bipush 10
    //   85: ldc 36
    //   87: bastore
    //   88: dup
    //   89: bipush 11
    //   91: ldc 36
    //   93: bastore
    //   94: dup
    //   95: bipush 12
    //   97: ldc 36
    //   99: bastore
    //   100: dup
    //   101: bipush 13
    //   103: ldc 37
    //   105: bastore
    //   106: dup
    //   107: bipush 14
    //   109: ldc 36
    //   111: bastore
    //   112: dup
    //   113: bipush 15
    //   115: ldc 37
    //   117: bastore
    //   118: dup
    //   119: bipush 16
    //   121: ldc 37
    //   123: bastore
    //   124: iconst_1
    //   125: invokestatic 41	o/KT:ˏ	([I[BZ)Ljava/lang/String;
    //   128: invokevirtual 47	java/lang/String:intern	()Ljava/lang/String;
    //   131: invokestatic 60	o/vq:ˊ	(Ljava/lang/String;)V
    //   134: goto +627 -> 761
    //   137: iload_1
    //   138: tableswitch	default:+22->160, 0:+75->213, 1:+272->410
    //   160: goto +53 -> 213
    //   163: astore_2
    //   164: aload_2
    //   165: athrow
    //   166: iconst_0
    //   167: istore_1
    //   168: aload 6
    //   170: astore_2
    //   171: aload 7
    //   173: astore_3
    //   174: aload 6
    //   176: astore 4
    //   178: aload 7
    //   180: astore 5
    //   182: iload_1
    //   183: tableswitch	default:+21->204, 0:+195->378, 1:+543->726
    //   204: aload 6
    //   206: astore_2
    //   207: aload 7
    //   209: astore_3
    //   210: goto +168 -> 378
    //   213: aload_2
    //   214: astore 4
    //   216: aload_3
    //   217: astore 5
    //   219: goto +507 -> 726
    //   222: aload_0
    //   223: getfield 63	o/KT:ˏ	Landroid/databinding/ViewDataBinding;
    //   226: astore_2
    //   227: aload_2
    //   228: iconst_4
    //   229: newarray int
    //   231: dup
    //   232: iconst_0
    //   233: bipush 50
    //   235: iastore
    //   236: dup
    //   237: iconst_1
    //   238: bipush 8
    //   240: iastore
    //   241: dup
    //   242: iconst_2
    //   243: iconst_0
    //   244: iastore
    //   245: dup
    //   246: iconst_3
    //   247: iconst_0
    //   248: iastore
    //   249: bipush 8
    //   251: newarray byte
    //   253: dup
    //   254: iconst_0
    //   255: ldc 36
    //   257: bastore
    //   258: dup
    //   259: iconst_1
    //   260: ldc 36
    //   262: bastore
    //   263: dup
    //   264: iconst_2
    //   265: ldc 36
    //   267: bastore
    //   268: dup
    //   269: iconst_3
    //   270: ldc 36
    //   272: bastore
    //   273: dup
    //   274: iconst_4
    //   275: ldc 37
    //   277: bastore
    //   278: dup
    //   279: iconst_5
    //   280: ldc 36
    //   282: bastore
    //   283: dup
    //   284: bipush 6
    //   286: ldc 36
    //   288: bastore
    //   289: dup
    //   290: bipush 7
    //   292: ldc 36
    //   294: bastore
    //   295: iconst_0
    //   296: invokestatic 41	o/KT:ˏ	([I[BZ)Ljava/lang/String;
    //   299: invokevirtual 47	java/lang/String:intern	()Ljava/lang/String;
    //   302: invokestatic 66	o/vq:ˋ	(Ljava/lang/Object;Ljava/lang/String;)V
    //   305: aload_2
    //   306: checkcast 68	o/JO
    //   309: iconst_0
    //   310: invokevirtual 71	o/JO:ˏ	(Z)V
    //   313: goto +17 -> 330
    //   316: astore_2
    //   317: aload_2
    //   318: invokevirtual 77	java/lang/Throwable:getCause	()Ljava/lang/Throwable;
    //   321: astore_3
    //   322: aload_3
    //   323: ifnull +5 -> 328
    //   326: aload_3
    //   327: athrow
    //   328: aload_2
    //   329: athrow
    //   330: iconst_4
    //   331: sipush 135
    //   334: ldc 78
    //   336: invokestatic 83	o/O:ˋ	(IIC)Ljava/lang/Object;
    //   339: checkcast 85	java/lang/Class
    //   342: ldc 86
    //   344: aconst_null
    //   345: invokevirtual 90	java/lang/Class:getMethod	(Ljava/lang/String;[Ljava/lang/Class;)Ljava/lang/reflect/Method;
    //   348: aconst_null
    //   349: aconst_null
    //   350: invokevirtual 96	java/lang/reflect/Method:invoke	(Ljava/lang/Object;[Ljava/lang/Object;)Ljava/lang/Object;
    //   353: checkcast 98	o/It
    //   356: astore 6
    //   358: aload_0
    //   359: getfield 100	o/KT:ˊ	Ljava/lang/String;
    //   362: astore 7
    //   364: aload 7
    //   366: ifnonnull +6 -> 372
    //   369: goto -203 -> 166
    //   372: goto +384 -> 756
    //   375: astore_2
    //   376: aload_2
    //   377: athrow
    //   378: getstatic 24	o/KT:ᐝ	I
    //   381: bipush 117
    //   383: iadd
    //   384: istore_1
    //   385: iload_1
    //   386: sipush 128
    //   389: irem
    //   390: putstatic 26	o/KT:ʻ	I
    //   393: iload_1
    //   394: iconst_2
    //   395: irem
    //   396: ifne +6 -> 402
    //   399: goto -396 -> 3
    //   402: goto +177 -> 579
    //   405: iconst_1
    //   406: istore_1
    //   407: goto -270 -> 137
    //   410: iconst_4
    //   411: iconst_4
    //   412: idiv
    //   413: istore_1
    //   414: aload_2
    //   415: astore 4
    //   417: aload_3
    //   418: astore 5
    //   420: goto +306 -> 726
    //   423: aload_0
    //   424: getfield 63	o/KT:ˏ	Landroid/databinding/ViewDataBinding;
    //   427: astore_2
    //   428: aload_2
    //   429: iconst_4
    //   430: newarray int
    //   432: dup
    //   433: iconst_0
    //   434: bipush 50
    //   436: iastore
    //   437: dup
    //   438: iconst_1
    //   439: bipush 8
    //   441: iastore
    //   442: dup
    //   443: iconst_2
    //   444: iconst_0
    //   445: iastore
    //   446: dup
    //   447: iconst_3
    //   448: iconst_0
    //   449: iastore
    //   450: bipush 8
    //   452: newarray byte
    //   454: dup
    //   455: iconst_0
    //   456: ldc 36
    //   458: bastore
    //   459: dup
    //   460: iconst_1
    //   461: ldc 36
    //   463: bastore
    //   464: dup
    //   465: iconst_2
    //   466: ldc 36
    //   468: bastore
    //   469: dup
    //   470: iconst_3
    //   471: ldc 36
    //   473: bastore
    //   474: dup
    //   475: iconst_4
    //   476: ldc 37
    //   478: bastore
    //   479: dup
    //   480: iconst_5
    //   481: ldc 36
    //   483: bastore
    //   484: dup
    //   485: bipush 6
    //   487: ldc 36
    //   489: bastore
    //   490: dup
    //   491: bipush 7
    //   493: ldc 36
    //   495: bastore
    //   496: iconst_1
    //   497: invokestatic 41	o/KT:ˏ	([I[BZ)Ljava/lang/String;
    //   500: invokevirtual 47	java/lang/String:intern	()Ljava/lang/String;
    //   503: invokestatic 66	o/vq:ˋ	(Ljava/lang/Object;Ljava/lang/String;)V
    //   506: aload_2
    //   507: checkcast 68	o/JO
    //   510: iconst_1
    //   511: invokevirtual 71	o/JO:ˏ	(Z)V
    //   514: goto +17 -> 531
    //   517: astore_2
    //   518: aload_2
    //   519: invokevirtual 77	java/lang/Throwable:getCause	()Ljava/lang/Throwable;
    //   522: astore_3
    //   523: aload_3
    //   524: ifnull +5 -> 529
    //   527: aload_3
    //   528: athrow
    //   529: aload_2
    //   530: athrow
    //   531: iconst_4
    //   532: sipush 135
    //   535: ldc 78
    //   537: invokestatic 83	o/O:ˋ	(IIC)Ljava/lang/Object;
    //   540: checkcast 85	java/lang/Class
    //   543: ldc 86
    //   545: aconst_null
    //   546: invokevirtual 90	java/lang/Class:getMethod	(Ljava/lang/String;[Ljava/lang/Class;)Ljava/lang/reflect/Method;
    //   549: aconst_null
    //   550: aconst_null
    //   551: invokevirtual 96	java/lang/reflect/Method:invoke	(Ljava/lang/Object;[Ljava/lang/Object;)Ljava/lang/Object;
    //   554: checkcast 98	o/It
    //   557: astore_2
    //   558: aload_0
    //   559: getfield 100	o/KT:ˊ	Ljava/lang/String;
    //   562: astore_3
    //   563: aload_3
    //   564: ifnonnull +6 -> 570
    //   567: goto -189 -> 378
    //   570: aload_2
    //   571: astore 4
    //   573: aload_3
    //   574: astore 5
    //   576: goto +150 -> 726
    //   579: iconst_4
    //   580: newarray int
    //   582: dup
    //   583: iconst_0
    //   584: bipush 58
    //   586: iastore
    //   587: dup
    //   588: iconst_1
    //   589: bipush 17
    //   591: iastore
    //   592: dup
    //   593: iconst_2
    //   594: iconst_0
    //   595: iastore
    //   596: dup
    //   597: iconst_3
    //   598: iconst_0
    //   599: iastore
    //   600: bipush 17
    //   602: newarray byte
    //   604: dup
    //   605: iconst_0
    //   606: ldc 37
    //   608: bastore
    //   609: dup
    //   610: iconst_1
    //   611: ldc 36
    //   613: bastore
    //   614: dup
    //   615: iconst_2
    //   616: ldc 37
    //   618: bastore
    //   619: dup
    //   620: iconst_3
    //   621: ldc 37
    //   623: bastore
    //   624: dup
    //   625: iconst_4
    //   626: ldc 37
    //   628: bastore
    //   629: dup
    //   630: iconst_5
    //   631: ldc 37
    //   633: bastore
    //   634: dup
    //   635: bipush 6
    //   637: ldc 36
    //   639: bastore
    //   640: dup
    //   641: bipush 7
    //   643: ldc 36
    //   645: bastore
    //   646: dup
    //   647: bipush 8
    //   649: ldc 36
    //   651: bastore
    //   652: dup
    //   653: bipush 9
    //   655: ldc 36
    //   657: bastore
    //   658: dup
    //   659: bipush 10
    //   661: ldc 36
    //   663: bastore
    //   664: dup
    //   665: bipush 11
    //   667: ldc 36
    //   669: bastore
    //   670: dup
    //   671: bipush 12
    //   673: ldc 36
    //   675: bastore
    //   676: dup
    //   677: bipush 13
    //   679: ldc 37
    //   681: bastore
    //   682: dup
    //   683: bipush 14
    //   685: ldc 36
    //   687: bastore
    //   688: dup
    //   689: bipush 15
    //   691: ldc 37
    //   693: bastore
    //   694: dup
    //   695: bipush 16
    //   697: ldc 37
    //   699: bastore
    //   700: iconst_1
    //   701: invokestatic 41	o/KT:ˏ	([I[BZ)Ljava/lang/String;
    //   704: astore 4
    //   706: aload 4
    //   708: invokevirtual 47	java/lang/String:intern	()Ljava/lang/String;
    //   711: astore 4
    //   713: aload 4
    //   715: invokestatic 60	o/vq:ˊ	(Ljava/lang/String;)V
    //   718: goto +43 -> 761
    //   721: iconst_0
    //   722: istore_1
    //   723: goto -586 -> 137
    //   726: aload 4
    //   728: aload 5
    //   730: invokeinterface 103 2 0
    //   735: new 7	o/KT$iF
    //   738: dup
    //   739: aload_0
    //   740: aload_0
    //   741: invokevirtual 107	o/KT:ˏॱ	()Landroid/content/Context;
    //   744: invokespecial 110	o/KT$iF:<init>	(Lo/KT;Landroid/content/Context;)V
    //   747: checkcast 112	o/Cx
    //   750: invokeinterface 117 2 0
    //   755: return
    //   756: iconst_1
    //   757: istore_1
    //   758: goto -590 -> 168
    //   761: getstatic 26	o/KT:ʻ	I
    //   764: bipush 95
    //   766: iadd
    //   767: istore_1
    //   768: iload_1
    //   769: sipush 128
    //   772: irem
    //   773: putstatic 24	o/KT:ᐝ	I
    //   776: iload_1
    //   777: iconst_2
    //   778: irem
    //   779: ifeq +6 -> 785
    //   782: goto -377 -> 405
    //   785: goto -64 -> 721
    //   788: getstatic 26	o/KT:ʻ	I
    //   791: bipush 41
    //   793: iadd
    //   794: istore_1
    //   795: iload_1
    //   796: sipush 128
    //   799: irem
    //   800: putstatic 24	o/KT:ᐝ	I
    //   803: iload_1
    //   804: iconst_2
    //   805: irem
    //   806: ifeq +6 -> 812
    //   809: goto -587 -> 222
    //   812: goto -389 -> 423
    // Local variable table:
    //   start	length	slot	name	signature
    //   0	815	0	this	KT
    //   137	669	1	i	int
    //   163	2	2	localException1	Exception
    //   170	136	2	localObject1	Object
    //   316	13	2	localObject2	Object
    //   375	40	2	localException2	Exception
    //   427	80	2	localViewDataBinding	android.databinding.ViewDataBinding
    //   517	13	2	localObject3	Object
    //   557	14	2	localIt1	It
    //   173	401	3	localObject4	Object
    //   176	551	4	localObject5	Object
    //   180	549	5	localObject6	Object
    //   168	189	6	localIt2	It
    //   171	194	7	str	String
    // Exception table:
    //   from	to	target	type
    //   713	718	163	java/lang/Exception
    //   330	358	316	finally
    //   579	706	375	java/lang/Exception
    //   706	713	375	java/lang/Exception
    //   713	718	375	java/lang/Exception
    //   531	558	517	finally
  }
  
  /* Error */
  private static String ˏ(int[] paramArrayOfInt, byte[] paramArrayOfByte, boolean paramBoolean)
  {
    // Byte code:
    //   0: goto +552 -> 552
    //   3: iload_3
    //   4: iload 6
    //   6: if_icmpge +6 -> 12
    //   9: goto +588 -> 597
    //   12: goto +370 -> 382
    //   15: iload 5
    //   17: lookupswitch	default:+27->44, 4:+72->89, 77:+181->198
    //   44: goto +45 -> 89
    //   47: iload 5
    //   49: lookupswitch	default:+27->76, 31:+369->418, 68:+545->594
    //   76: goto +518 -> 594
    //   79: bipush 77
    //   81: istore 5
    //   83: goto -68 -> 15
    //   86: astore_0
    //   87: aload_0
    //   88: athrow
    //   89: aload_1
    //   90: iload 4
    //   92: baload
    //   93: iconst_1
    //   94: if_icmpne +6 -> 100
    //   97: goto +191 -> 288
    //   100: goto +434 -> 534
    //   103: goto +465 -> 568
    //   106: aload_0
    //   107: iconst_0
    //   108: iaload
    //   109: istore_3
    //   110: aload_0
    //   111: iconst_1
    //   112: iaload
    //   113: istore 6
    //   115: aload_0
    //   116: iconst_2
    //   117: iaload
    //   118: istore 7
    //   120: aload_0
    //   121: iconst_3
    //   122: iaload
    //   123: istore 8
    //   125: getstatic 120	o/KT:ˎ	[C
    //   128: astore 9
    //   130: iload 6
    //   132: newarray char
    //   134: astore 10
    //   136: aload 9
    //   138: iload_3
    //   139: aload 10
    //   141: iconst_0
    //   142: iload 6
    //   144: invokestatic 126	java/lang/System:arraycopy	(Ljava/lang/Object;ILjava/lang/Object;II)V
    //   147: aload_1
    //   148: ifnull +6 -> 154
    //   151: goto +128 -> 279
    //   154: goto +374 -> 528
    //   157: iload_2
    //   158: ifeq +6 -> 164
    //   161: goto +155 -> 316
    //   164: aload 9
    //   166: astore_1
    //   167: goto +401 -> 568
    //   170: bipush 68
    //   172: istore 5
    //   174: goto -127 -> 47
    //   177: astore_0
    //   178: aload_0
    //   179: athrow
    //   180: aload_1
    //   181: iload_3
    //   182: aload_1
    //   183: iload_3
    //   184: caload
    //   185: aload_0
    //   186: iconst_2
    //   187: iaload
    //   188: isub
    //   189: i2c
    //   190: castore
    //   191: iload_3
    //   192: iconst_1
    //   193: iadd
    //   194: istore_3
    //   195: goto +264 -> 459
    //   198: aload_1
    //   199: iload 4
    //   201: baload
    //   202: iconst_1
    //   203: if_icmpne +6 -> 209
    //   206: goto +82 -> 288
    //   209: goto +325 -> 534
    //   212: getstatic 24	o/KT:ᐝ	I
    //   215: bipush 119
    //   217: iadd
    //   218: istore 5
    //   220: iload 5
    //   222: sipush 128
    //   225: irem
    //   226: putstatic 26	o/KT:ʻ	I
    //   229: iload 5
    //   231: iconst_2
    //   232: irem
    //   233: ifne +6 -> 239
    //   236: goto +49 -> 285
    //   239: goto +74 -> 313
    //   242: aload 10
    //   244: astore 9
    //   246: iload_3
    //   247: lookupswitch	default:+25->272, 61:+270->517, 96:+79->326
    //   272: aload 10
    //   274: astore 9
    //   276: goto +241 -> 517
    //   279: bipush 96
    //   281: istore_3
    //   282: goto -40 -> 242
    //   285: goto +28 -> 313
    //   288: aload 9
    //   290: iload 4
    //   292: aload 10
    //   294: iload 4
    //   296: caload
    //   297: iconst_1
    //   298: ishl
    //   299: iconst_1
    //   300: iadd
    //   301: iload_3
    //   302: isub
    //   303: i2c
    //   304: castore
    //   305: goto +274 -> 579
    //   308: iconst_0
    //   309: istore_3
    //   310: goto +149 -> 459
    //   313: goto +242 -> 555
    //   316: iload 6
    //   318: newarray char
    //   320: astore_1
    //   321: iconst_0
    //   322: istore_3
    //   323: goto -320 -> 3
    //   326: iload 6
    //   328: newarray char
    //   330: astore 9
    //   332: iconst_0
    //   333: istore_3
    //   334: iconst_0
    //   335: istore 4
    //   337: goto +42 -> 379
    //   340: iconst_4
    //   341: istore 5
    //   343: goto -328 -> 15
    //   346: iload 4
    //   348: lookupswitch	default:+28->376, 35:+51->399, 39:+108->456
    //   376: goto +23 -> 399
    //   379: goto +176 -> 555
    //   382: bipush 39
    //   384: istore 4
    //   386: goto -40 -> 346
    //   389: bipush 31
    //   391: istore 5
    //   393: goto -346 -> 47
    //   396: goto +121 -> 517
    //   399: aload_1
    //   400: iload_3
    //   401: aload 9
    //   403: iload 6
    //   405: iload_3
    //   406: isub
    //   407: iconst_1
    //   408: isub
    //   409: caload
    //   410: castore
    //   411: iload_3
    //   412: iconst_1
    //   413: iadd
    //   414: istore_3
    //   415: goto -412 -> 3
    //   418: getstatic 24	o/KT:ᐝ	I
    //   421: iconst_5
    //   422: iadd
    //   423: istore 5
    //   425: iload 5
    //   427: sipush 128
    //   430: irem
    //   431: putstatic 26	o/KT:ʻ	I
    //   434: iload 5
    //   436: iconst_2
    //   437: irem
    //   438: ifne +6 -> 444
    //   441: goto -101 -> 340
    //   444: goto -365 -> 79
    //   447: new 43	java/lang/String
    //   450: dup
    //   451: aload_1
    //   452: invokespecial 129	java/lang/String:<init>	([C)V
    //   455: areturn
    //   456: goto -353 -> 103
    //   459: iload_3
    //   460: iload 6
    //   462: if_icmpge +6 -> 468
    //   465: goto -285 -> 180
    //   468: goto -21 -> 447
    //   471: iload 6
    //   473: newarray char
    //   475: astore_1
    //   476: aload 9
    //   478: iconst_0
    //   479: aload_1
    //   480: iconst_0
    //   481: iload 6
    //   483: invokestatic 126	java/lang/System:arraycopy	(Ljava/lang/Object;ILjava/lang/Object;II)V
    //   486: aload_1
    //   487: iconst_0
    //   488: aload 9
    //   490: iload 6
    //   492: iload 8
    //   494: isub
    //   495: iload 8
    //   497: invokestatic 126	java/lang/System:arraycopy	(Ljava/lang/Object;ILjava/lang/Object;II)V
    //   500: aload_1
    //   501: iload 8
    //   503: aload 9
    //   505: iconst_0
    //   506: iload 6
    //   508: iload 8
    //   510: isub
    //   511: invokestatic 126	java/lang/System:arraycopy	(Ljava/lang/Object;ILjava/lang/Object;II)V
    //   514: goto -357 -> 157
    //   517: iload 8
    //   519: ifle +6 -> 525
    //   522: goto -51 -> 471
    //   525: goto -368 -> 157
    //   528: bipush 61
    //   530: istore_3
    //   531: goto -289 -> 242
    //   534: aload 9
    //   536: iload 4
    //   538: aload 10
    //   540: iload 4
    //   542: caload
    //   543: iconst_1
    //   544: ishl
    //   545: iload_3
    //   546: isub
    //   547: i2c
    //   548: castore
    //   549: goto +30 -> 579
    //   552: goto -446 -> 106
    //   555: iload 4
    //   557: iload 6
    //   559: if_icmpge +6 -> 565
    //   562: goto -173 -> 389
    //   565: goto -395 -> 170
    //   568: iload 7
    //   570: ifle +6 -> 576
    //   573: goto -265 -> 308
    //   576: goto -129 -> 447
    //   579: aload 9
    //   581: iload 4
    //   583: caload
    //   584: istore_3
    //   585: iload 4
    //   587: iconst_1
    //   588: iadd
    //   589: istore 4
    //   591: goto -379 -> 212
    //   594: goto -198 -> 396
    //   597: bipush 35
    //   599: istore 4
    //   601: goto -255 -> 346
    // Local variable table:
    //   start	length	slot	name	signature
    //   0	604	0	paramArrayOfInt	int[]
    //   0	604	1	paramArrayOfByte	byte[]
    //   0	604	2	paramBoolean	boolean
    //   3	582	3	i	int
    //   90	510	4	j	int
    //   15	423	5	k	int
    //   4	556	6	m	int
    //   118	451	7	n	int
    //   123	395	8	i1	int
    //   128	452	9	localObject	Object
    //   134	405	10	arrayOfChar	char[]
    // Exception table:
    //   from	to	target	type
    //   476	486	86	java/lang/Exception
    //   486	500	86	java/lang/Exception
    //   500	514	86	java/lang/Exception
    //   212	220	177	java/lang/Exception
    //   220	229	177	java/lang/Exception
  }
  
  static void ﹳ()
  {
    ˎ = new char[] { 36, 86, 94, 89, 83, 74, 58, 73, 111, 117, 109, 108, 108, 77, 78, 106, 112, 103, 103, 119, 113, 111, 110, 75, 58, 82, 90, 87, 77, 84, 93, 4161, 4161, 82, 80, 82, 84, 93, 85, 70, 77, 79, 85, 88, 79, 84, 87, 78, 75, 76, 51, 106, 107, 102, 105, 107, 85, 87, 34, 70, 79, 85, 93, 100, 104, 103, 106, 115, 112, 91, 86, 107, 105, 82, 88, 50, 110, 118, 115, 105, 96, 105, 115, 105, 103, 112, 106, 98, 107, 110, 108, 110, 112, 105, 97, 98, 105, 107, 97, 100, 107, 112, 115, 106, 103, 104, 100, 98, 106, 117, 111, 102 };
  }
  
  public int ˎ()
  {
    break label88;
    int j = 0;
    break label108;
    label8:
    throw new NullPointerException();
    int i = Jy.ˊ.fragment_payments_turnover;
    break label135;
    return i;
    label25:
    i = ʻ + 25;
    ᐝ = i % 128;
    if (i % 2 == 0) {
      break label83;
    }
    for (;;)
    {
      j = 1;
      break label108;
      for (;;)
      {
        switch (i)
        {
        case 0: 
        default: 
          break label96;
          label83:
          i = 0;
          continue;
          label88:
          break label25;
          i = 1;
        }
      }
      label96:
      i = Jy.ˊ.fragment_payments_turnover;
      j = 9 / 0;
      break label135;
      label108:
      switch (j)
      {
      }
      break label8;
      label135:
      j = ʻ + 51;
      ᐝ = j % 128;
      if (j % 2 != 0) {
        break;
      }
    }
  }
  
  public void ˎ(Bundle paramBundle)
  {
    break label507;
    int i = 1;
    Object localObject;
    for (;;)
    {
      try
      {
        localObject = ˋ;
      }
      catch (Exception paramBundle)
      {
        throw paramBundle;
      }
      try
      {
        localObject = ((if)localObject).ˊ();
        paramBundle = paramBundle.getString((String)localObject);
        vq.ˋ(paramBundle, ˏ(new int[] { 0, 50, 4, 7 }, new byte[] { 1, 0, 0, 0, 0, 1, 1, 1, 1, 1, 0, 0, 1, 1, 1, 0, 1, 1, 1, 0, 1, 1, 1, 1, 1, 1, 0, 0, 1, 0, 1, 0, 0, 1, 0, 1, 1, 0, 0, 0, 1, 0, 1, 0, 1, 1, 1, 1, 1, 1 }, false).intern());
        this.ˊ = paramBundle;
        i = ᐝ + 63;
        ʻ = i % 128;
        if (i % 2 == 0) {
          break label573;
        }
      }
      catch (Exception paramBundle)
      {
        throw paramBundle;
      }
      i = 88;
      break label513;
      i = 0;
      continue;
      super.ˎ(paramBundle);
      paramBundle = ʽ();
      i = 10 / 0;
      if (paramBundle != null) {
        break;
      }
      continue;
      i = 0;
      break label543;
      switch (i)
      {
      case 1: 
      default: 
        break label576;
        label460:
        do
        {
          i = 22;
          break;
          i = ʻ + 9;
          ᐝ = i % 128;
        } while (i % 2 != 0);
      }
    }
    for (;;)
    {
      super.ˎ(paramBundle);
      localObject = ʽ();
      if (localObject != null) {
        break;
      }
      break label581;
      label507:
      break label460;
      label513:
      switch (i)
      {
      }
    }
    for (;;)
    {
      label543:
      paramBundle = (Bundle)localObject;
      switch (i)
      {
      case 0: 
      default: 
        paramBundle = (Bundle)localObject;
        break;
        break;
      case 1: 
        label573:
        label576:
        ʻˋ();
        return;
        label581:
        i = 1;
      }
    }
  }
  
  public static final class iF
    extends Ik<EN>
  {
    private static int ʻ = 0;
    private static int ʼ = 1;
    private static char ˋ = 58105;
    private static char ˎ = 48158;
    private static char ˏ = 38117;
    private static char ॱ = '䵱';
    
    iF(Context paramContext) {}
    
    /* Error */
    private static String ˊ(char[] paramArrayOfChar)
    {
      // Byte code:
      //   0: goto +96 -> 96
      //   3: goto +37 -> 40
      //   6: iload_2
      //   7: istore_1
      //   8: goto +239 -> 247
      //   11: getstatic 25	o/KT$iF:ʼ	I
      //   14: istore_1
      //   15: iload_1
      //   16: bipush 93
      //   18: iadd
      //   19: istore_1
      //   20: iload_1
      //   21: sipush 128
      //   24: irem
      //   25: putstatic 23	o/KT$iF:ʻ	I
      //   28: iload_1
      //   29: iconst_2
      //   30: irem
      //   31: ifeq +6 -> 37
      //   34: goto +73 -> 107
      //   37: goto +125 -> 162
      //   40: aload 4
      //   42: iconst_0
      //   43: aload_0
      //   44: iload_1
      //   45: caload
      //   46: castore
      //   47: aload 4
      //   49: iconst_1
      //   50: aload_0
      //   51: iload_1
      //   52: iconst_1
      //   53: iadd
      //   54: caload
      //   55: castore
      //   56: aload 4
      //   58: getstatic 36	o/KT$iF:ˏ	C
      //   61: getstatic 30	o/KT$iF:ˋ	C
      //   64: getstatic 33	o/KT$iF:ˎ	C
      //   67: getstatic 27	o/KT$iF:ॱ	C
      //   70: invokestatic 53	o/oP:ˏ	([CCCCC)V
      //   73: aload_3
      //   74: iload_1
      //   75: aload 4
      //   77: iconst_0
      //   78: caload
      //   79: castore
      //   80: aload_3
      //   81: iload_1
      //   82: iconst_1
      //   83: iadd
      //   84: aload 4
      //   86: iconst_1
      //   87: caload
      //   88: castore
      //   89: iload_1
      //   90: iconst_2
      //   91: iadd
      //   92: istore_2
      //   93: goto +24 -> 117
      //   96: goto +123 -> 219
      //   99: astore_0
      //   100: aload_0
      //   101: athrow
      //   102: iconst_1
      //   103: istore_1
      //   104: goto +87 -> 191
      //   107: iconst_1
      //   108: istore_1
      //   109: goto +55 -> 164
      //   112: iload_2
      //   113: istore_1
      //   114: goto +133 -> 247
      //   117: getstatic 25	o/KT$iF:ʼ	I
      //   120: bipush 47
      //   122: iadd
      //   123: istore_1
      //   124: iload_1
      //   125: sipush 128
      //   128: irem
      //   129: putstatic 23	o/KT$iF:ʻ	I
      //   132: iload_1
      //   133: iconst_2
      //   134: irem
      //   135: ifeq +6 -> 141
      //   138: goto -36 -> 102
      //   141: goto +101 -> 242
      //   144: iload_2
      //   145: istore_1
      //   146: goto +101 -> 247
      //   149: new 55	java/lang/String
      //   152: dup
      //   153: aload_3
      //   154: iconst_1
      //   155: aload_3
      //   156: iconst_0
      //   157: caload
      //   158: invokespecial 58	java/lang/String:<init>	([CII)V
      //   161: areturn
      //   162: iconst_0
      //   163: istore_1
      //   164: iload_1
      //   165: tableswitch	default:+23->188, 0:+-21->144, 1:+69->234
      //   188: goto -44 -> 144
      //   191: iload_1
      //   192: tableswitch	default:+24->216, 0:+-80->112, 1:+-186->6
      //   216: goto -104 -> 112
      //   219: aload_0
      //   220: arraylength
      //   221: newarray char
      //   223: astore_3
      //   224: iconst_0
      //   225: istore_2
      //   226: iconst_2
      //   227: newarray char
      //   229: astore 4
      //   231: goto -220 -> 11
      //   234: iload_2
      //   235: istore_1
      //   236: goto +11 -> 247
      //   239: astore_0
      //   240: aload_0
      //   241: athrow
      //   242: iconst_0
      //   243: istore_1
      //   244: goto -53 -> 191
      //   247: iload_1
      //   248: aload_0
      //   249: arraylength
      //   250: if_icmpge +6 -> 256
      //   253: goto +6 -> 259
      //   256: goto -107 -> 149
      //   259: getstatic 23	o/KT$iF:ʻ	I
      //   262: bipush 41
      //   264: iadd
      //   265: istore_2
      //   266: iload_2
      //   267: sipush 128
      //   270: irem
      //   271: putstatic 25	o/KT$iF:ʼ	I
      //   274: iload_2
      //   275: iconst_2
      //   276: irem
      //   277: ifne +6 -> 283
      //   280: goto -277 -> 3
      //   283: goto -243 -> 40
      // Local variable table:
      //   start	length	slot	name	signature
      //   0	286	0	paramArrayOfChar	char[]
      //   7	244	1	i	int
      //   6	271	2	j	int
      //   73	151	3	arrayOfChar1	char[]
      //   40	190	4	arrayOfChar2	char[]
      // Exception table:
      //   from	to	target	type
      //   11	15	99	java/lang/Exception
      //   117	124	99	java/lang/Exception
      //   124	132	99	java/lang/Exception
      //   259	266	239	java/lang/Exception
      //   266	274	239	java/lang/Exception
    }
    
    protected void ˊ(EN paramEN)
    {
      break label318;
      int i = 47;
      break label152;
      vq.ˎ(paramEN, ˊ(new char[] { -20661, 27193, 16304, 31017, 22917, 25765, 8980, -2400 }).intern());
      JO localJO = KT.ˊ(this.ˊ);
      vq.ˋ(localJO, ˊ(new char[] { -1311, 17096, 6024, 31314, 18403, 9734, -18307, 4984, 9993, 14679 }).intern());
      localJO.ˏ(paramEN);
      i = 98 / 0;
      return;
      label152:
      switch (i)
      {
      }
      vq.ˎ(paramEN, ˊ(new char[] { -20661, 27193, 16304, 31017, 22917, 25765, 8980, -2400 }).intern());
      localJO = KT.ˊ(this.ˊ);
      vq.ˋ(localJO, ˊ(new char[] { -1311, 17096, 6024, 31314, 18403, 9734, -18307, 4984, 9993, 14679 }).intern());
      localJO.ˏ(paramEN);
      return;
      for (;;)
      {
        label318:
        i = 2;
        break label152;
        i = ʻ + 31;
        ʼ = i % 128;
        if (i % 2 == 0) {
          break;
        }
      }
    }
    
    /* Error */
    public void ˏ()
    {
      // Byte code:
      //   0: goto +152 -> 152
      //   3: iconst_1
      //   4: istore_1
      //   5: goto +30 -> 35
      //   8: getstatic 23	o/KT$iF:ʻ	I
      //   11: bipush 67
      //   13: iadd
      //   14: istore_1
      //   15: iload_1
      //   16: sipush 128
      //   19: irem
      //   20: putstatic 25	o/KT$iF:ʼ	I
      //   23: iload_1
      //   24: iconst_2
      //   25: irem
      //   26: ifne +6 -> 32
      //   29: goto +119 -> 148
      //   32: return
      //   33: iconst_0
      //   34: istore_1
      //   35: iload_1
      //   36: tableswitch	default:+24->60, 0:+24->60, 1:+143->179
      //   60: aload_0
      //   61: invokespecial 99	o/Ik:ˏ	()V
      //   64: aload_0
      //   65: getfield 43	o/KT$iF:ˊ	Lo/KT;
      //   68: invokestatic 81	o/KT:ˊ	(Lo/KT;)Lo/JO;
      //   71: astore_2
      //   72: aload_2
      //   73: bipush 10
      //   75: newarray char
      //   77: dup
      //   78: iconst_0
      //   79: ldc 82
      //   81: castore
      //   82: dup
      //   83: iconst_1
      //   84: ldc 83
      //   86: castore
      //   87: dup
      //   88: iconst_2
      //   89: ldc 84
      //   91: castore
      //   92: dup
      //   93: iconst_3
      //   94: ldc 85
      //   96: castore
      //   97: dup
      //   98: iconst_4
      //   99: ldc 86
      //   101: castore
      //   102: dup
      //   103: iconst_5
      //   104: ldc 87
      //   106: castore
      //   107: dup
      //   108: bipush 6
      //   110: ldc 88
      //   112: castore
      //   113: dup
      //   114: bipush 7
      //   116: ldc 89
      //   118: castore
      //   119: dup
      //   120: bipush 8
      //   122: ldc 90
      //   124: castore
      //   125: dup
      //   126: bipush 9
      //   128: ldc 91
      //   130: castore
      //   131: invokestatic 69	o/KT$iF:ˊ	([C)Ljava/lang/String;
      //   134: invokevirtual 73	java/lang/String:intern	()Ljava/lang/String;
      //   137: invokestatic 93	o/vq:ˋ	(Ljava/lang/Object;Ljava/lang/String;)V
      //   140: aload_2
      //   141: iconst_0
      //   142: invokevirtual 102	o/JO:ˏ	(Z)V
      //   145: goto -137 -> 8
      //   148: return
      //   149: astore_2
      //   150: aload_2
      //   151: athrow
      //   152: getstatic 23	o/KT$iF:ʻ	I
      //   155: bipush 53
      //   157: iadd
      //   158: istore_1
      //   159: iload_1
      //   160: sipush 128
      //   163: irem
      //   164: putstatic 25	o/KT$iF:ʼ	I
      //   167: iload_1
      //   168: iconst_2
      //   169: irem
      //   170: ifne +6 -> 176
      //   173: goto -170 -> 3
      //   176: goto -143 -> 33
      //   179: aload_0
      //   180: invokespecial 99	o/Ik:ˏ	()V
      //   183: aload_0
      //   184: getfield 43	o/KT$iF:ˊ	Lo/KT;
      //   187: invokestatic 81	o/KT:ˊ	(Lo/KT;)Lo/JO;
      //   190: astore_2
      //   191: aload_2
      //   192: bipush 10
      //   194: newarray char
      //   196: dup
      //   197: iconst_0
      //   198: ldc 82
      //   200: castore
      //   201: dup
      //   202: iconst_1
      //   203: ldc 83
      //   205: castore
      //   206: dup
      //   207: iconst_2
      //   208: ldc 84
      //   210: castore
      //   211: dup
      //   212: iconst_3
      //   213: ldc 85
      //   215: castore
      //   216: dup
      //   217: iconst_4
      //   218: ldc 86
      //   220: castore
      //   221: dup
      //   222: iconst_5
      //   223: ldc 87
      //   225: castore
      //   226: dup
      //   227: bipush 6
      //   229: ldc 88
      //   231: castore
      //   232: dup
      //   233: bipush 7
      //   235: ldc 89
      //   237: castore
      //   238: dup
      //   239: bipush 8
      //   241: ldc 90
      //   243: castore
      //   244: dup
      //   245: bipush 9
      //   247: ldc 91
      //   249: castore
      //   250: invokestatic 69	o/KT$iF:ˊ	([C)Ljava/lang/String;
      //   253: invokevirtual 73	java/lang/String:intern	()Ljava/lang/String;
      //   256: invokestatic 93	o/vq:ˋ	(Ljava/lang/Object;Ljava/lang/String;)V
      //   259: aload_2
      //   260: iconst_1
      //   261: invokevirtual 102	o/JO:ˏ	(Z)V
      //   264: goto -256 -> 8
      //   267: astore_2
      //   268: aload_2
      //   269: athrow
      // Local variable table:
      //   start	length	slot	name	signature
      //   0	270	0	this	iF
      //   4	166	1	i	int
      //   71	70	2	localJO1	JO
      //   149	2	2	localException1	Exception
      //   190	70	2	localJO2	JO
      //   267	2	2	localException2	Exception
      // Exception table:
      //   from	to	target	type
      //   8	15	149	java/lang/Exception
      //   15	23	149	java/lang/Exception
      //   15	23	267	java/lang/Exception
    }
  }
  
  public static final class if
  {
    private static int ʼ = 0;
    private static int ˊ;
    private static byte[] ˋ;
    private static int ˎ = 596751217;
    private static short[] ˏ;
    private static int ॱ;
    private static int ॱॱ = 1;
    
    static
    {
      ˊ = 22;
      ˋ = new byte[] { -6, -8, -15, -3, -19, -1, -14, 10, -22, -2, 2, 34, -30, -17, 14, -5 };
      ॱ = 595936830;
    }
    
    private if() {}
    
    /* Error */
    private static String ˏ(short paramShort, int paramInt1, byte paramByte, int paramInt2, int paramInt3)
    {
      // Byte code:
      //   0: goto +621 -> 621
      //   3: iload 4
      //   5: ifle +6 -> 11
      //   8: goto +35 -> 43
      //   11: goto +115 -> 126
      //   14: iload 6
      //   16: tableswitch	default:+24->40, 0:+527->543, 1:+261->277
      //   40: goto +503 -> 543
      //   43: getstatic 49	o/KT$if:ˎ	I
      //   46: istore 8
      //   48: iload 7
      //   50: ifeq +6 -> 56
      //   53: goto +521 -> 574
      //   56: goto +467 -> 523
      //   59: iload 6
      //   61: istore 4
      //   63: iload 8
      //   65: tableswitch	default:+23->88, 0:+49->114, 1:+-62->3
      //   88: iload 6
      //   90: istore 4
      //   92: goto -89 -> 3
      //   95: getstatic 60	o/KT$if:ˏ	[S
      //   98: getstatic 49	o/KT$if:ˎ	I
      //   101: iload_1
      //   102: iadd
      //   103: saload
      //   104: getstatic 25	o/KT$if:ˊ	I
      //   107: iadd
      //   108: i2s
      //   109: istore 4
      //   111: goto -108 -> 3
      //   114: getstatic 43	o/KT$if:ˋ	[B
      //   117: ifnull +6 -> 123
      //   120: goto +197 -> 317
      //   123: goto -28 -> 95
      //   126: aload 9
      //   128: invokevirtual 66	java/lang/StringBuilder:toString	()Ljava/lang/String;
      //   131: areturn
      //   132: iconst_0
      //   133: istore 6
      //   135: goto -121 -> 14
      //   138: goto +242 -> 380
      //   141: iload 7
      //   143: ifeq +6 -> 149
      //   146: goto +73 -> 219
      //   149: goto +159 -> 308
      //   152: getstatic 21	o/KT$if:ʼ	I
      //   155: bipush 19
      //   157: iadd
      //   158: istore 7
      //   160: iload 7
      //   162: sipush 128
      //   165: irem
      //   166: putstatic 23	o/KT$if:ॱॱ	I
      //   169: iload 7
      //   171: iconst_2
      //   172: irem
      //   173: ifne +6 -> 179
      //   176: goto +364 -> 540
      //   179: goto -41 -> 138
      //   182: getstatic 43	o/KT$if:ˋ	[B
      //   185: getstatic 49	o/KT$if:ˎ	I
      //   188: iload_1
      //   189: iadd
      //   190: baload
      //   191: getstatic 25	o/KT$if:ˊ	I
      //   194: iadd
      //   195: i2b
      //   196: istore 4
      //   198: goto -195 -> 3
      //   201: iload_3
      //   202: iload 4
      //   204: if_icmpge +6 -> 210
      //   207: goto +211 -> 418
      //   210: goto -84 -> 126
      //   213: iconst_1
      //   214: istore 6
      //   216: goto -202 -> 14
      //   219: iconst_0
      //   220: istore 8
      //   222: goto -163 -> 59
      //   225: getstatic 23	o/KT$if:ॱॱ	I
      //   228: istore 4
      //   230: iload 4
      //   232: bipush 17
      //   234: iadd
      //   235: istore 4
      //   237: iload 4
      //   239: sipush 128
      //   242: irem
      //   243: putstatic 21	o/KT$if:ʼ	I
      //   246: iload 4
      //   248: iconst_2
      //   249: irem
      //   250: ifeq +6 -> 256
      //   253: goto +267 -> 520
      //   256: goto +261 -> 517
      //   259: iconst_0
      //   260: istore 6
      //   262: goto +205 -> 467
      //   265: iconst_1
      //   266: istore 6
      //   268: goto +199 -> 467
      //   271: iconst_1
      //   272: istore 6
      //   274: goto -122 -> 152
      //   277: getstatic 60	o/KT$if:ˏ	[S
      //   280: astore 10
      //   282: iload_1
      //   283: iconst_1
      //   284: isub
      //   285: istore 6
      //   287: aload 10
      //   289: iload_1
      //   290: saload
      //   291: iload_0
      //   292: iadd
      //   293: i2s
      //   294: iload_2
      //   295: ixor
      //   296: iload 7
      //   298: iadd
      //   299: i2c
      //   300: istore 5
      //   302: iload 6
      //   304: istore_1
      //   305: goto +143 -> 448
      //   308: iconst_1
      //   309: istore 8
      //   311: goto -252 -> 59
      //   314: goto +66 -> 380
      //   317: getstatic 21	o/KT$if:ʼ	I
      //   320: bipush 37
      //   322: iadd
      //   323: istore 4
      //   325: iload 4
      //   327: sipush 128
      //   330: irem
      //   331: putstatic 23	o/KT$if:ॱॱ	I
      //   334: iload 4
      //   336: iconst_2
      //   337: irem
      //   338: ifne +6 -> 344
      //   341: goto +271 -> 612
      //   344: goto -162 -> 182
      //   347: new 62	java/lang/StringBuilder
      //   350: dup
      //   351: invokespecial 67	java/lang/StringBuilder:<init>	()V
      //   354: astore 9
      //   356: getstatic 25	o/KT$if:ˊ	I
      //   359: iload 4
      //   361: iadd
      //   362: istore 4
      //   364: iload 4
      //   366: istore 6
      //   368: iload 4
      //   370: iconst_m1
      //   371: if_icmpne +6 -> 377
      //   374: goto -149 -> 225
      //   377: goto +152 -> 529
      //   380: iload_1
      //   381: iload 4
      //   383: iadd
      //   384: iconst_2
      //   385: isub
      //   386: iload 8
      //   388: iadd
      //   389: iload 6
      //   391: iadd
      //   392: istore_1
      //   393: getstatic 46	o/KT$if:ॱ	I
      //   396: iload_3
      //   397: iadd
      //   398: i2c
      //   399: istore 5
      //   401: aload 9
      //   403: iload 5
      //   405: invokevirtual 71	java/lang/StringBuilder:append	(C)Ljava/lang/StringBuilder;
      //   408: pop
      //   409: iconst_1
      //   410: istore_3
      //   411: iload 5
      //   413: istore 7
      //   415: goto -214 -> 201
      //   418: getstatic 23	o/KT$if:ॱॱ	I
      //   421: bipush 103
      //   423: iadd
      //   424: istore 6
      //   426: iload 6
      //   428: sipush 128
      //   431: irem
      //   432: putstatic 21	o/KT$if:ʼ	I
      //   435: iload 6
      //   437: iconst_2
      //   438: irem
      //   439: ifeq +6 -> 445
      //   442: goto +53 -> 495
      //   445: goto +179 -> 624
      //   448: aload 9
      //   450: iload 5
      //   452: invokevirtual 71	java/lang/StringBuilder:append	(C)Ljava/lang/StringBuilder;
      //   455: pop
      //   456: iload_3
      //   457: iconst_1
      //   458: iadd
      //   459: istore_3
      //   460: iload 5
      //   462: istore 7
      //   464: goto -263 -> 201
      //   467: iload 6
      //   469: tableswitch	default:+23->492, 0:+-192->277, 1:+74->543
      //   492: goto +51 -> 543
      //   495: getstatic 43	o/KT$if:ˋ	[B
      //   498: astore 10
      //   500: bipush 16
      //   502: iconst_0
      //   503: idiv
      //   504: istore 6
      //   506: aload 10
      //   508: ifnull +6 -> 514
      //   511: goto -379 -> 132
      //   514: goto -301 -> 213
      //   517: goto +98 -> 615
      //   520: goto +95 -> 615
      //   523: iconst_0
      //   524: istore 6
      //   526: goto -212 -> 314
      //   529: iconst_0
      //   530: istore 7
      //   532: goto -391 -> 141
      //   535: astore 9
      //   537: aload 9
      //   539: athrow
      //   540: goto -160 -> 380
      //   543: getstatic 43	o/KT$if:ˋ	[B
      //   546: astore 10
      //   548: iload_1
      //   549: iconst_1
      //   550: isub
      //   551: istore 6
      //   553: aload 10
      //   555: iload_1
      //   556: baload
      //   557: iload_0
      //   558: iadd
      //   559: i2b
      //   560: iload_2
      //   561: ixor
      //   562: iload 7
      //   564: iadd
      //   565: i2c
      //   566: istore 5
      //   568: iload 6
      //   570: istore_1
      //   571: goto -123 -> 448
      //   574: getstatic 21	o/KT$if:ʼ	I
      //   577: bipush 31
      //   579: iadd
      //   580: istore 6
      //   582: iload 6
      //   584: sipush 128
      //   587: irem
      //   588: putstatic 23	o/KT$if:ॱॱ	I
      //   591: iload 6
      //   593: iconst_2
      //   594: irem
      //   595: ifne +6 -> 601
      //   598: goto +6 -> 604
      //   601: goto -330 -> 271
      //   604: goto -333 -> 271
      //   607: astore 9
      //   609: aload 9
      //   611: athrow
      //   612: goto -430 -> 182
      //   615: iconst_1
      //   616: istore 7
      //   618: goto -477 -> 141
      //   621: goto -274 -> 347
      //   624: getstatic 43	o/KT$if:ˋ	[B
      //   627: ifnull +6 -> 633
      //   630: goto -365 -> 265
      //   633: goto -374 -> 259
      // Local variable table:
      //   start	length	slot	name	signature
      //   0	636	0	paramShort	short
      //   0	636	1	paramInt1	int
      //   0	636	2	paramByte	byte
      //   0	636	3	paramInt2	int
      //   0	636	4	paramInt3	int
      //   300	267	5	i	int
      //   14	581	6	j	int
      //   48	569	7	k	int
      //   46	343	8	m	int
      //   126	323	9	localStringBuilder	StringBuilder
      //   535	3	9	localException1	Exception
      //   607	3	9	localException2	Exception
      //   280	274	10	localObject	Object
      // Exception table:
      //   from	to	target	type
      //   43	48	535	java/lang/Exception
      //   237	246	535	java/lang/Exception
      //   225	230	607	java/lang/Exception
    }
    
    /* Error */
    public final String ˊ()
    {
      // Byte code:
      //   0: goto +30 -> 30
      //   3: getstatic 21	o/KT$if:ʼ	I
      //   6: bipush 95
      //   8: iadd
      //   9: istore_1
      //   10: iload_1
      //   11: sipush 128
      //   14: irem
      //   15: putstatic 23	o/KT$if:ॱॱ	I
      //   18: iload_1
      //   19: iconst_2
      //   20: irem
      //   21: ifne +6 -> 27
      //   24: goto +9 -> 33
      //   27: goto +9 -> 36
      //   30: goto -27 -> 3
      //   33: goto +3 -> 36
      //   36: invokestatic 73	o/KT:ˋ	()Ljava/lang/String;
      //   39: astore_2
      //   40: goto +6 -> 46
      //   43: astore_2
      //   44: aload_2
      //   45: athrow
      //   46: getstatic 23	o/KT$if:ॱॱ	I
      //   49: istore_1
      //   50: iload_1
      //   51: bipush 57
      //   53: iadd
      //   54: istore_1
      //   55: iload_1
      //   56: sipush 128
      //   59: irem
      //   60: putstatic 21	o/KT$if:ʼ	I
      //   63: iload_1
      //   64: iconst_2
      //   65: irem
      //   66: ifeq +5 -> 71
      //   69: aload_2
      //   70: areturn
      //   71: aload_2
      //   72: areturn
      //   73: astore_2
      //   74: aload_2
      //   75: athrow
      // Local variable table:
      //   start	length	slot	name	signature
      //   0	76	0	this	if
      //   9	57	1	i	int
      //   39	1	2	str	String
      //   43	29	2	localException1	Exception
      //   73	2	2	localException2	Exception
      // Exception table:
      //   from	to	target	type
      //   46	50	43	java/lang/Exception
      //   36	40	73	java/lang/Exception
      //   55	63	73	java/lang/Exception
    }
    
    /* Error */
    public final KT ˏ(String paramString)
    {
      // Byte code:
      //   0: goto +3 -> 3
      //   3: goto +6 -> 9
      //   6: astore_1
      //   7: aload_1
      //   8: athrow
      //   9: iconst_3
      //   10: ldc 75
      //   12: iconst_0
      //   13: ldc 76
      //   15: bipush -23
      //   17: invokestatic 78	o/KT$if:ˏ	(SIBII)Ljava/lang/String;
      //   20: astore_3
      //   21: aload_1
      //   22: aload_3
      //   23: invokevirtual 83	java/lang/String:intern	()Ljava/lang/String;
      //   26: invokestatic 88	o/vq:ˎ	(Ljava/lang/Object;Ljava/lang/String;)V
      //   29: new 6	o/KT
      //   32: dup
      //   33: invokespecial 89	o/KT:<init>	()V
      //   36: astore_3
      //   37: new 91	android/os/Bundle
      //   40: dup
      //   41: invokespecial 92	android/os/Bundle:<init>	()V
      //   44: astore 4
      //   46: aload 4
      //   48: aload_0
      //   49: checkcast 2	o/KT$if
      //   52: invokevirtual 94	o/KT$if:ˊ	()Ljava/lang/String;
      //   55: aload_1
      //   56: invokevirtual 98	android/os/Bundle:putString	(Ljava/lang/String;Ljava/lang/String;)V
      //   59: aload_3
      //   60: aload 4
      //   62: invokevirtual 102	o/KT:ʽ	(Landroid/os/Bundle;)V
      //   65: goto +6 -> 71
      //   68: astore_1
      //   69: aload_1
      //   70: athrow
      //   71: getstatic 23	o/KT$if:ॱॱ	I
      //   74: istore_2
      //   75: iload_2
      //   76: bipush 33
      //   78: iadd
      //   79: istore_2
      //   80: iload_2
      //   81: sipush 128
      //   84: irem
      //   85: putstatic 21	o/KT$if:ʼ	I
      //   88: iload_2
      //   89: iconst_2
      //   90: irem
      //   91: ifeq +5 -> 96
      //   94: aload_3
      //   95: areturn
      //   96: aload_3
      //   97: areturn
      // Local variable table:
      //   start	length	slot	name	signature
      //   0	98	0	this	if
      //   0	98	1	paramString	String
      //   74	17	2	i	int
      //   20	77	3	localObject	Object
      //   44	17	4	localBundle	Bundle
      // Exception table:
      //   from	to	target	type
      //   9	21	6	java/lang/Exception
      //   71	75	68	java/lang/Exception
      //   80	88	68	java/lang/Exception
    }
  }
}
