package o;

import android.content.Context;
import android.content.Intent;
import android.content.pm.ApplicationInfo;
import android.os.Bundle;
import android.view.ViewTreeObserver;
import android.view.ViewTreeObserver.OnGlobalLayoutListener;

public class Ku
  extends IB<JE>
{
  private static long ʼॱ = 2789108854478204423L;
  private static int ʽॱ;
  private static char[] ʾ = { -30865, 26997, 23408, 19821, 16247, 8566, 4944, 1370, -2229, -9896, -13527, -17111, -20694, -28402, -31989, 29954, 26376, 18713, 101, -4481, -9094, -13721, -18307, -22916, -27575, -32176, 28746, 24155, 19481, 14884, 10298, 5672, 1046, -3576, -8162, -12780, -17381, -21798, -26375, -31002, 29939, 25285 };
  private static int ˈ = 0;
  
  static
  {
    ʽॱ = 1;
  }
  
  public Ku() {}
  
  private void ʻॱ()
  {
    for (;;)
    {
      try
      {
        localObject = this.ॱˊ;
      }
      catch (Exception localException1)
      {
        try
        {
          Object localObject = (JE)localObject;
          localObject = ((JE)localObject).ᐝ;
          ((Jh)localObject).ˏ(new Jd[] { ((JE)this.ॱˊ).ˎ });
          ((JE)this.ॱˊ).ʻ.setPaymentCard((Eu)getIntent().getParcelableExtra(ˏ(getApplicationInfo().targetSdkVersion - 25, (char)(getPackageName().codePointAt(3) + 34472), getPackageName().codePointAt(10) - 103).intern()));
        }
        catch (Exception localException2)
        {
          throw localException2;
        }
        localException1 = localException1;
        throw localException1;
      }
      int i = ʽॱ + 53;
      ˈ = i % 128;
      if (i % 2 == 0)
      {
        continue;
        i = ˈ + 37;
        ʽॱ = i % 128;
        if (i % 2 == 0) {
          break;
        }
        return;
      }
    }
  }
  
  private static String ˏ(int paramInt1, char paramChar, int paramInt2)
  {
    break label199;
    Object localObject;
    int i;
    for (;;)
    {
      localObject[i] = ((char)(int)(ʾ[(paramInt1 + i)] ^ i * ʼॱ ^ paramChar));
      i += 1;
      break;
      paramInt1 = null.length;
      return localObject;
      do
      {
        break;
        j = ʽॱ + 105;
        ˈ = j % 128;
      } while (j % 2 != 0);
    }
    int j = 68;
    for (;;)
    {
      switch (paramInt1)
      {
      }
      return localObject;
      for (;;)
      {
        switch (j)
        {
        }
        localObject = new String((char[])localObject);
        break;
        label154:
        j = 93;
      }
      paramInt1 = ˈ + 123;
      ʽॱ = paramInt1 % 128;
      if (paramInt1 % 2 != 0)
      {
        break label205;
        label188:
        if (i >= paramInt2)
        {
          break;
          label199:
          break label211;
        }
        for (;;)
        {
          break label188;
          break label154;
          label205:
          paramInt1 = 96;
          break;
          label211:
          localObject = new char[paramInt2];
          i = 0;
        }
      }
      paramInt1 = 25;
    }
  }
  
  /* Error */
  private void ॱˋ()
  {
    // Byte code:
    //   0: goto +336 -> 336
    //   3: astore_2
    //   4: aload_2
    //   5: athrow
    //   6: aload_0
    //   7: invokevirtual 105	o/Ku:getIntent	()Landroid/content/Intent;
    //   10: aload_0
    //   11: invokevirtual 120	android/content/Context:getPackageName	()Ljava/lang/String;
    //   14: iconst_5
    //   15: invokevirtual 126	java/lang/String:codePointAt	(I)I
    //   18: bipush 114
    //   20: isub
    //   21: aload_0
    //   22: invokevirtual 120	android/content/Context:getPackageName	()Ljava/lang/String;
    //   25: invokevirtual 158	java/lang/String:length	()I
    //   28: ldc -97
    //   30: iadd
    //   31: i2c
    //   32: aload_0
    //   33: invokevirtual 120	android/content/Context:getPackageName	()Ljava/lang/String;
    //   36: invokevirtual 158	java/lang/String:length	()I
    //   39: bipush 7
    //   41: iadd
    //   42: invokestatic 130	o/Ku:ˏ	(ICI)Ljava/lang/String;
    //   45: invokevirtual 133	java/lang/String:intern	()Ljava/lang/String;
    //   48: invokevirtual 139	android/content/Intent:getParcelableExtra	(Ljava/lang/String;)Landroid/os/Parcelable;
    //   51: checkcast 141	o/Eu
    //   54: astore_2
    //   55: aload_0
    //   56: getfield 79	o/Ku:ॱˊ	Landroid/databinding/ViewDataBinding;
    //   59: checkcast 81	o/JE
    //   62: getfield 91	o/JE:ˎ	Lo/IV;
    //   65: invokevirtual 164	o/IV:ʽ	()Ljava/lang/String;
    //   68: astore_3
    //   69: aload_0
    //   70: invokevirtual 105	o/Ku:getIntent	()Landroid/content/Intent;
    //   73: aload_0
    //   74: invokevirtual 168	android/content/Context:getResources	()Landroid/content/res/Resources;
    //   77: ldc -87
    //   79: invokevirtual 175	android/content/res/Resources:getString	(I)Ljava/lang/String;
    //   82: iconst_0
    //   83: iconst_5
    //   84: invokevirtual 179	java/lang/String:substring	(II)Ljava/lang/String;
    //   87: iconst_3
    //   88: invokevirtual 126	java/lang/String:codePointAt	(I)I
    //   91: bipush 6
    //   93: iadd
    //   94: aload_0
    //   95: invokevirtual 168	android/content/Context:getResources	()Landroid/content/res/Resources;
    //   98: ldc -76
    //   100: invokevirtual 175	android/content/res/Resources:getString	(I)Ljava/lang/String;
    //   103: iconst_0
    //   104: iconst_4
    //   105: invokevirtual 179	java/lang/String:substring	(II)Ljava/lang/String;
    //   108: iconst_2
    //   109: invokevirtual 126	java/lang/String:codePointAt	(I)I
    //   112: bipush 11
    //   114: isub
    //   115: i2c
    //   116: aload_0
    //   117: invokevirtual 168	android/content/Context:getResources	()Landroid/content/res/Resources;
    //   120: ldc -75
    //   122: invokevirtual 175	android/content/res/Resources:getString	(I)Ljava/lang/String;
    //   125: iconst_0
    //   126: iconst_4
    //   127: invokevirtual 179	java/lang/String:substring	(II)Ljava/lang/String;
    //   130: iconst_1
    //   131: invokevirtual 126	java/lang/String:codePointAt	(I)I
    //   134: iconst_2
    //   135: isub
    //   136: invokestatic 130	o/Ku:ˏ	(ICI)Ljava/lang/String;
    //   139: invokevirtual 133	java/lang/String:intern	()Ljava/lang/String;
    //   142: invokevirtual 185	android/content/Intent:getStringExtra	(Ljava/lang/String;)Ljava/lang/String;
    //   145: astore 4
    //   147: aload_0
    //   148: invokestatic 190	o/Ic:ˏ	(Landroid/content/Context;)Lo/Ic;
    //   151: aload_2
    //   152: getstatic 196	o/Er:CARD_REGISTRATION_FROM_PRESENTMENT	Lo/Er;
    //   155: aload_3
    //   156: invokevirtual 199	o/Ic:ˎ	(Lo/Eu;Lo/Er;Ljava/lang/String;)Lo/j;
    //   159: aload_0
    //   160: invokevirtual 168	android/content/Context:getResources	()Landroid/content/res/Resources;
    //   163: ldc -56
    //   165: invokevirtual 175	android/content/res/Resources:getString	(I)Ljava/lang/String;
    //   168: iconst_0
    //   169: iconst_4
    //   170: invokevirtual 179	java/lang/String:substring	(II)Ljava/lang/String;
    //   173: invokevirtual 158	java/lang/String:length	()I
    //   176: iconst_4
    //   177: isub
    //   178: aload_0
    //   179: invokevirtual 168	android/content/Context:getResources	()Landroid/content/res/Resources;
    //   182: ldc -55
    //   184: invokevirtual 175	android/content/res/Resources:getString	(I)Ljava/lang/String;
    //   187: bipush 52
    //   189: bipush 59
    //   191: invokevirtual 179	java/lang/String:substring	(II)Ljava/lang/String;
    //   194: iconst_1
    //   195: invokevirtual 126	java/lang/String:codePointAt	(I)I
    //   198: ldc -54
    //   200: iadd
    //   201: i2c
    //   202: aload_0
    //   203: invokevirtual 120	android/content/Context:getPackageName	()Ljava/lang/String;
    //   206: invokevirtual 158	java/lang/String:length	()I
    //   209: bipush 7
    //   211: iadd
    //   212: invokestatic 130	o/Ku:ˏ	(ICI)Ljava/lang/String;
    //   215: invokevirtual 133	java/lang/String:intern	()Ljava/lang/String;
    //   218: aload_2
    //   219: invokevirtual 207	o/j:ˎ	(Ljava/lang/String;Landroid/os/Parcelable;)Lo/j;
    //   222: aload_0
    //   223: invokevirtual 168	android/content/Context:getResources	()Landroid/content/res/Resources;
    //   226: ldc -48
    //   228: invokevirtual 175	android/content/res/Resources:getString	(I)Ljava/lang/String;
    //   231: bipush 26
    //   233: bipush 34
    //   235: invokevirtual 179	java/lang/String:substring	(II)Ljava/lang/String;
    //   238: invokevirtual 158	java/lang/String:length	()I
    //   241: bipush 10
    //   243: iadd
    //   244: aload_0
    //   245: invokevirtual 111	android/content/Context:getApplicationInfo	()Landroid/content/pm/ApplicationInfo;
    //   248: getfield 116	android/content/pm/ApplicationInfo:targetSdkVersion	I
    //   251: bipush 25
    //   253: isub
    //   254: i2c
    //   255: aload_0
    //   256: invokevirtual 111	android/content/Context:getApplicationInfo	()Landroid/content/pm/ApplicationInfo;
    //   259: getfield 116	android/content/pm/ApplicationInfo:targetSdkVersion	I
    //   262: iconst_1
    //   263: isub
    //   264: invokestatic 130	o/Ku:ˏ	(ICI)Ljava/lang/String;
    //   267: invokevirtual 133	java/lang/String:intern	()Ljava/lang/String;
    //   270: aload 4
    //   272: invokevirtual 211	o/j:ˋ	(Ljava/lang/String;Ljava/lang/String;)Lo/j;
    //   275: invokevirtual 213	o/j:ˎ	()V
    //   278: getstatic 20	o/Ku:ʽॱ	I
    //   281: bipush 69
    //   283: iadd
    //   284: istore_1
    //   285: iload_1
    //   286: sipush 128
    //   289: irem
    //   290: putstatic 18	o/Ku:ˈ	I
    //   293: iload_1
    //   294: iconst_2
    //   295: irem
    //   296: ifeq +6 -> 302
    //   299: goto +4 -> 303
    //   302: return
    //   303: return
    //   304: getstatic 20	o/Ku:ʽॱ	I
    //   307: istore_1
    //   308: iload_1
    //   309: bipush 87
    //   311: iadd
    //   312: istore_1
    //   313: iload_1
    //   314: sipush 128
    //   317: irem
    //   318: putstatic 18	o/Ku:ˈ	I
    //   321: iload_1
    //   322: iconst_2
    //   323: irem
    //   324: ifeq +6 -> 330
    //   327: goto +6 -> 333
    //   330: goto -324 -> 6
    //   333: goto -327 -> 6
    //   336: goto -32 -> 304
    // Local variable table:
    //   start	length	slot	name	signature
    //   0	339	0	this	Ku
    //   284	40	1	i	int
    //   3	2	2	localException	Exception
    //   54	165	2	localEu	Eu
    //   68	88	3	str1	String
    //   145	126	4	str2	String
    // Exception table:
    //   from	to	target	type
    //   304	308	3	java/lang/Exception
    //   313	321	3	java/lang/Exception
  }
  
  /* Error */
  public android.content.res.Resources getResources()
  {
    // Byte code:
    //   0: goto +52 -> 52
    //   3: astore_2
    //   4: aload_2
    //   5: athrow
    //   6: iload_1
    //   7: lookupswitch	default:+25->32, 41:+48->55, 47:+28->35
    //   32: goto +23 -> 55
    //   35: aload_0
    //   36: invokespecial 214	o/IB:getResources	()Landroid/content/res/Resources;
    //   39: invokestatic 219	o/oH:ˊ	(Landroid/content/res/Resources;)Landroid/content/res/Resources;
    //   42: areturn
    //   43: bipush 41
    //   45: istore_1
    //   46: goto -40 -> 6
    //   49: astore_2
    //   50: aload_2
    //   51: athrow
    //   52: goto +22 -> 74
    //   55: aload_0
    //   56: invokespecial 214	o/IB:getResources	()Landroid/content/res/Resources;
    //   59: invokestatic 219	o/oH:ˊ	(Landroid/content/res/Resources;)Landroid/content/res/Resources;
    //   62: astore_2
    //   63: aconst_null
    //   64: arraylength
    //   65: istore_1
    //   66: aload_2
    //   67: areturn
    //   68: bipush 47
    //   70: istore_1
    //   71: goto -65 -> 6
    //   74: getstatic 18	o/Ku:ˈ	I
    //   77: istore_1
    //   78: iload_1
    //   79: bipush 49
    //   81: iadd
    //   82: istore_1
    //   83: iload_1
    //   84: sipush 128
    //   87: irem
    //   88: putstatic 20	o/Ku:ʽॱ	I
    //   91: iload_1
    //   92: iconst_2
    //   93: irem
    //   94: ifne +6 -> 100
    //   97: goto -54 -> 43
    //   100: goto -32 -> 68
    // Local variable table:
    //   start	length	slot	name	signature
    //   0	103	0	this	Ku
    //   6	88	1	i	int
    //   3	2	2	localException1	Exception
    //   49	2	2	localException2	Exception
    //   62	5	2	localResources	android.content.res.Resources
    // Exception table:
    //   from	to	target	type
    //   83	91	3	java/lang/Exception
    //   74	78	49	java/lang/Exception
  }
  
  /* Error */
  public void onBackPressed()
  {
    // Byte code:
    //   0: goto +33 -> 33
    //   3: bipush 38
    //   5: istore_1
    //   6: iload_1
    //   7: lookupswitch	default:+25->32, 38:+29->36, 47:+55->62
    //   32: return
    //   33: goto +49 -> 82
    //   36: aconst_null
    //   37: arraylength
    //   38: istore_1
    //   39: return
    //   40: astore_2
    //   41: aload_2
    //   42: athrow
    //   43: aload_0
    //   44: invokespecial 222	o/IB:onBackPressed	()V
    //   47: aload_0
    //   48: iconst_0
    //   49: iconst_0
    //   50: invokevirtual 226	o/Ku:overridePendingTransition	(II)V
    //   53: goto +62 -> 115
    //   56: bipush 68
    //   58: istore_1
    //   59: goto +85 -> 144
    //   62: return
    //   63: bipush 86
    //   65: istore_1
    //   66: goto +78 -> 144
    //   69: aload_0
    //   70: invokespecial 222	o/IB:onBackPressed	()V
    //   73: aload_0
    //   74: iconst_1
    //   75: iconst_0
    //   76: invokevirtual 226	o/Ku:overridePendingTransition	(II)V
    //   79: goto +36 -> 115
    //   82: getstatic 20	o/Ku:ʽॱ	I
    //   85: bipush 37
    //   87: iadd
    //   88: istore_1
    //   89: iload_1
    //   90: sipush 128
    //   93: irem
    //   94: putstatic 18	o/Ku:ˈ	I
    //   97: iload_1
    //   98: iconst_2
    //   99: irem
    //   100: ifeq +6 -> 106
    //   103: goto -40 -> 63
    //   106: goto -50 -> 56
    //   109: bipush 47
    //   111: istore_1
    //   112: goto -106 -> 6
    //   115: getstatic 20	o/Ku:ʽॱ	I
    //   118: istore_1
    //   119: iload_1
    //   120: bipush 57
    //   122: iadd
    //   123: istore_1
    //   124: iload_1
    //   125: sipush 128
    //   128: irem
    //   129: putstatic 18	o/Ku:ˈ	I
    //   132: iload_1
    //   133: iconst_2
    //   134: irem
    //   135: ifeq +6 -> 141
    //   138: goto -135 -> 3
    //   141: goto -32 -> 109
    //   144: iload_1
    //   145: lookupswitch	default:+27->172, 68:+-102->43, 86:+-76->69
    //   172: goto -129 -> 43
    // Local variable table:
    //   start	length	slot	name	signature
    //   0	175	0	this	Ku
    //   5	140	1	i	int
    //   40	2	2	localException	Exception
    // Exception table:
    //   from	to	target	type
    //   115	119	40	java/lang/Exception
    //   124	132	40	java/lang/Exception
  }
  
  public void onCreate(Bundle paramBundle)
  {
    break label79;
    int i = ˈ + 15;
    ʽॱ = i % 128;
    if (i % 2 != 0) {
      return;
    }
    return;
    label79:
    for (;;)
    {
      super.onCreate(paramBundle);
      ˊ(((JE)this.ॱˊ).ॱॱ);
      ʻॱ();
      ((JE)this.ॱˊ).ʻ.getViewTreeObserver().addOnGlobalLayoutListener(new ViewTreeObserver.OnGlobalLayoutListener()
      {
        public void onGlobalLayout()
        {
          ((JE)Ku.ˊ(Ku.this)).ʻ.getViewTreeObserver().removeOnGlobalLayoutListener(this);
          ((JE)Ku.ˋ(Ku.this)).ʻ.ॱ();
        }
      });
      break;
    }
  }
  
  /* Error */
  public void onValidateClicked(android.view.View paramView)
  {
    // Byte code:
    //   0: goto +118 -> 118
    //   3: getstatic 20	o/Ku:ʽॱ	I
    //   6: bipush 119
    //   8: iadd
    //   9: istore_2
    //   10: iload_2
    //   11: sipush 128
    //   14: irem
    //   15: putstatic 18	o/Ku:ˈ	I
    //   18: iload_2
    //   19: iconst_2
    //   20: irem
    //   21: ifeq +6 -> 27
    //   24: goto +327 -> 351
    //   27: goto +336 -> 363
    //   30: iload_2
    //   31: lookupswitch	default:+25->56, 2:+380->411, 55:+328->359
    //   56: goto +355 -> 411
    //   59: iload_2
    //   60: lookupswitch	default:+28->88, 31:+309->369, 96:+318->378
    //   88: goto +281 -> 369
    //   91: getstatic 18	o/Ku:ˈ	I
    //   94: bipush 43
    //   96: iadd
    //   97: istore_2
    //   98: iload_2
    //   99: sipush 128
    //   102: irem
    //   103: putstatic 20	o/Ku:ʽॱ	I
    //   106: iload_2
    //   107: iconst_2
    //   108: irem
    //   109: ifne +6 -> 115
    //   112: goto +248 -> 360
    //   115: goto +19 -> 134
    //   118: goto -27 -> 91
    //   121: aload_0
    //   122: invokespecial 256	o/Ku:ॱˋ	()V
    //   125: goto +244 -> 369
    //   128: bipush 96
    //   130: istore_2
    //   131: goto -72 -> 59
    //   134: goto +20 -> 154
    //   137: astore_1
    //   138: aload_1
    //   139: invokevirtual 262	java/lang/Throwable:getCause	()Ljava/lang/Throwable;
    //   142: astore 4
    //   144: aload 4
    //   146: ifnull +6 -> 152
    //   149: aload 4
    //   151: athrow
    //   152: aload_1
    //   153: athrow
    //   154: aload_0
    //   155: invokevirtual 120	android/content/Context:getPackageName	()Ljava/lang/String;
    //   158: invokevirtual 158	java/lang/String:length	()I
    //   161: bipush 8
    //   163: isub
    //   164: aload_0
    //   165: invokevirtual 168	android/content/Context:getResources	()Landroid/content/res/Resources;
    //   168: ldc_w 263
    //   171: invokevirtual 175	android/content/res/Resources:getString	(I)Ljava/lang/String;
    //   174: iconst_0
    //   175: iconst_4
    //   176: invokevirtual 179	java/lang/String:substring	(II)Ljava/lang/String;
    //   179: iconst_1
    //   180: invokevirtual 126	java/lang/String:codePointAt	(I)I
    //   183: iconst_2
    //   184: isub
    //   185: aload_0
    //   186: invokevirtual 168	android/content/Context:getResources	()Landroid/content/res/Resources;
    //   189: ldc_w 264
    //   192: invokevirtual 175	android/content/res/Resources:getString	(I)Ljava/lang/String;
    //   195: iconst_0
    //   196: iconst_1
    //   197: invokevirtual 179	java/lang/String:substring	(II)Ljava/lang/String;
    //   200: invokevirtual 158	java/lang/String:length	()I
    //   203: iconst_1
    //   204: isub
    //   205: i2c
    //   206: invokestatic 269	o/O:ˋ	(IIC)Ljava/lang/Object;
    //   209: checkcast 271	java/lang/Class
    //   212: ldc_w 272
    //   215: aconst_null
    //   216: invokevirtual 276	java/lang/Class:getMethod	(Ljava/lang/String;[Ljava/lang/Class;)Ljava/lang/reflect/Method;
    //   219: aconst_null
    //   220: aconst_null
    //   221: invokevirtual 282	java/lang/reflect/Method:invoke	(Ljava/lang/Object;[Ljava/lang/Object;)Ljava/lang/Object;
    //   224: astore_1
    //   225: goto +20 -> 245
    //   228: astore_1
    //   229: aload_1
    //   230: invokevirtual 262	java/lang/Throwable:getCause	()Ljava/lang/Throwable;
    //   233: astore 4
    //   235: aload 4
    //   237: ifnull +6 -> 243
    //   240: aload 4
    //   242: athrow
    //   243: aload_1
    //   244: athrow
    //   245: aload_0
    //   246: invokevirtual 168	android/content/Context:getResources	()Landroid/content/res/Resources;
    //   249: ldc_w 283
    //   252: invokevirtual 175	android/content/res/Resources:getString	(I)Ljava/lang/String;
    //   255: iconst_0
    //   256: bipush 7
    //   258: invokevirtual 179	java/lang/String:substring	(II)Ljava/lang/String;
    //   261: iconst_2
    //   262: invokevirtual 126	java/lang/String:codePointAt	(I)I
    //   265: bipush 8
    //   267: isub
    //   268: aload_0
    //   269: invokevirtual 168	android/content/Context:getResources	()Landroid/content/res/Resources;
    //   272: ldc_w 284
    //   275: invokevirtual 175	android/content/res/Resources:getString	(I)Ljava/lang/String;
    //   278: iconst_0
    //   279: iconst_5
    //   280: invokevirtual 179	java/lang/String:substring	(II)Ljava/lang/String;
    //   283: iconst_2
    //   284: invokevirtual 126	java/lang/String:codePointAt	(I)I
    //   287: bipush 13
    //   289: iadd
    //   290: aload_0
    //   291: invokevirtual 111	android/content/Context:getApplicationInfo	()Landroid/content/pm/ApplicationInfo;
    //   294: getfield 116	android/content/pm/ApplicationInfo:targetSdkVersion	I
    //   297: bipush 25
    //   299: isub
    //   300: i2c
    //   301: invokestatic 269	o/O:ˋ	(IIC)Ljava/lang/Object;
    //   304: checkcast 271	java/lang/Class
    //   307: ldc_w 285
    //   310: iconst_1
    //   311: anewarray 271	java/lang/Class
    //   314: dup
    //   315: iconst_0
    //   316: ldc 107
    //   318: aastore
    //   319: invokevirtual 276	java/lang/Class:getMethod	(Ljava/lang/String;[Ljava/lang/Class;)Ljava/lang/reflect/Method;
    //   322: aload_1
    //   323: iconst_1
    //   324: anewarray 287	java/lang/Object
    //   327: dup
    //   328: iconst_0
    //   329: aload_0
    //   330: aastore
    //   331: invokevirtual 282	java/lang/reflect/Method:invoke	(Ljava/lang/Object;[Ljava/lang/Object;)Ljava/lang/Object;
    //   334: checkcast 289	java/lang/Boolean
    //   337: invokevirtual 293	java/lang/Boolean:booleanValue	()Z
    //   340: istore_3
    //   341: iload_3
    //   342: ifeq +6 -> 348
    //   345: goto -217 -> 128
    //   348: goto +24 -> 372
    //   351: iconst_2
    //   352: istore_2
    //   353: goto -323 -> 30
    //   356: astore_1
    //   357: aload_1
    //   358: athrow
    //   359: return
    //   360: goto -226 -> 134
    //   363: bipush 55
    //   365: istore_2
    //   366: goto -336 -> 30
    //   369: goto -366 -> 3
    //   372: bipush 31
    //   374: istore_2
    //   375: goto -316 -> 59
    //   378: getstatic 18	o/Ku:ˈ	I
    //   381: bipush 123
    //   383: iadd
    //   384: istore_2
    //   385: iload_2
    //   386: sipush 128
    //   389: irem
    //   390: putstatic 20	o/Ku:ʽॱ	I
    //   393: iload_2
    //   394: iconst_2
    //   395: irem
    //   396: ifne +6 -> 402
    //   399: goto +6 -> 405
    //   402: goto -281 -> 121
    //   405: goto -284 -> 121
    //   408: astore_1
    //   409: aload_1
    //   410: athrow
    //   411: aconst_null
    //   412: arraylength
    //   413: istore_2
    //   414: return
    // Local variable table:
    //   start	length	slot	name	signature
    //   0	415	0	this	Ku
    //   0	415	1	paramView	android.view.View
    //   9	405	2	i	int
    //   340	2	3	bool	boolean
    //   142	99	4	localThrowable	Throwable
    // Exception table:
    //   from	to	target	type
    //   154	225	137	finally
    //   245	341	228	finally
    //   378	385	356	java/lang/Exception
    //   385	393	356	java/lang/Exception
    //   385	393	408	java/lang/Exception
  }
  
  /* Error */
  public void ˋ(ز paramز)
  {
    // Byte code:
    //   0: goto +57 -> 57
    //   3: iconst_1
    //   4: istore_2
    //   5: goto +120 -> 125
    //   8: getstatic 20	o/Ku:ʽॱ	I
    //   11: bipush 103
    //   13: iadd
    //   14: istore_2
    //   15: iload_2
    //   16: sipush 128
    //   19: irem
    //   20: putstatic 18	o/Ku:ˈ	I
    //   23: iload_2
    //   24: iconst_2
    //   25: irem
    //   26: ifeq +6 -> 32
    //   29: goto +19 -> 48
    //   32: goto +124 -> 156
    //   35: aload_1
    //   36: iconst_1
    //   37: invokevirtual 300	o/ز:ॱ	(Z)V
    //   40: aload_1
    //   41: iconst_0
    //   42: invokevirtual 302	o/ز:ˏ	(Z)V
    //   45: goto +15 -> 60
    //   48: bipush 54
    //   50: istore_2
    //   51: goto +36 -> 87
    //   54: astore_1
    //   55: aload_1
    //   56: athrow
    //   57: goto -49 -> 8
    //   60: getstatic 18	o/Ku:ˈ	I
    //   63: bipush 95
    //   65: iadd
    //   66: istore_2
    //   67: iload_2
    //   68: sipush 128
    //   71: irem
    //   72: putstatic 20	o/Ku:ʽॱ	I
    //   75: iload_2
    //   76: iconst_2
    //   77: irem
    //   78: ifne +6 -> 84
    //   81: goto -78 -> 3
    //   84: goto +39 -> 123
    //   87: iload_2
    //   88: lookupswitch	default:+28->116, 54:+-53->35, 88:+74->162
    //   116: goto +46 -> 162
    //   119: return
    //   120: astore_1
    //   121: aload_1
    //   122: athrow
    //   123: iconst_0
    //   124: istore_2
    //   125: iload_2
    //   126: tableswitch	default:+22->148, 0:+-7->119, 1:+22->148
    //   148: new 304	java/lang/NullPointerException
    //   151: dup
    //   152: invokespecial 305	java/lang/NullPointerException:<init>	()V
    //   155: athrow
    //   156: bipush 88
    //   158: istore_2
    //   159: goto -72 -> 87
    //   162: aload_1
    //   163: iconst_1
    //   164: invokevirtual 300	o/ز:ॱ	(Z)V
    //   167: aload_1
    //   168: iconst_1
    //   169: invokevirtual 302	o/ز:ˏ	(Z)V
    //   172: goto -112 -> 60
    // Local variable table:
    //   start	length	slot	name	signature
    //   0	175	0	this	Ku
    //   0	175	1	paramز	ز
    //   4	155	2	i	int
    // Exception table:
    //   from	to	target	type
    //   35	40	54	java/lang/Exception
    //   40	45	120	java/lang/Exception
  }
  
  /* Error */
  public int ˎ()
  {
    // Byte code:
    //   0: goto +65 -> 65
    //   3: iload_1
    //   4: lookupswitch	default:+28->32, 22:+64->68, 92:+40->44
    //   32: goto +36 -> 68
    //   35: astore_2
    //   36: aload_2
    //   37: athrow
    //   38: bipush 92
    //   40: istore_1
    //   41: goto -38 -> 3
    //   44: getstatic 310	o/Jy$ˊ:activity_cvv	I
    //   47: istore_1
    //   48: new 304	java/lang/NullPointerException
    //   51: dup
    //   52: invokespecial 305	java/lang/NullPointerException:<init>	()V
    //   55: athrow
    //   56: astore_2
    //   57: aload_2
    //   58: athrow
    //   59: bipush 22
    //   61: istore_1
    //   62: goto -59 -> 3
    //   65: goto +9 -> 74
    //   68: getstatic 310	o/Jy$ˊ:activity_cvv	I
    //   71: istore_1
    //   72: iload_1
    //   73: ireturn
    //   74: getstatic 18	o/Ku:ˈ	I
    //   77: istore_1
    //   78: iload_1
    //   79: bipush 13
    //   81: iadd
    //   82: istore_1
    //   83: iload_1
    //   84: sipush 128
    //   87: irem
    //   88: putstatic 20	o/Ku:ʽॱ	I
    //   91: iload_1
    //   92: iconst_2
    //   93: irem
    //   94: ifne +6 -> 100
    //   97: goto -59 -> 38
    //   100: goto -41 -> 59
    // Local variable table:
    //   start	length	slot	name	signature
    //   0	103	0	this	Ku
    //   3	91	1	i	int
    //   35	2	2	localException1	Exception
    //   56	2	2	localException2	Exception
    // Exception table:
    //   from	to	target	type
    //   74	78	35	java/lang/Exception
    //   83	91	35	java/lang/Exception
    //   68	72	56	java/lang/Exception
  }
}
