package o;

import android.content.Intent;
import android.content.res.Resources;
import android.view.View;
import android.view.View.OnClickListener;

public class Kv
  extends IB<JD>
{
  private static boolean ʼॱ = true;
  private static char[] ʽॱ = { 393, 412, 408, 406, 389, 387, 391, 403, 409, 402, 413, 401, 374, 397, 324, 377, 407, 365, 392, 394, 400, 390, 395, 398, 404, 396, 338, 361 };
  private static int ʿ = 292;
  private static boolean ˈ;
  private static int ˊˊ = 0;
  private static int ˊˋ = 1;
  private View.OnClickListener ʾ;
  
  static
  {
    ˈ = true;
  }
  
  /* Error */
  public Kv()
  {
    // Byte code:
    //   0: goto +6 -> 6
    //   3: astore_1
    //   4: aload_1
    //   5: athrow
    //   6: aload_0
    //   7: invokespecial 68	o/IB:<init>	()V
    //   10: new 7	o/Kv$1
    //   13: dup
    //   14: aload_0
    //   15: invokespecial 71	o/Kv$1:<init>	(Lo/Kv;)V
    //   18: astore_1
    //   19: aload_0
    //   20: aload_1
    //   21: putfield 73	o/Kv:ʾ	Landroid/view/View$OnClickListener;
    //   24: return
    // Local variable table:
    //   start	length	slot	name	signature
    //   0	25	0	this	Kv
    //   3	2	1	localException	Exception
    //   18	3	1	local1	1
    // Exception table:
    //   from	to	target	type
    //   19	24	3	java/lang/Exception
  }
  
  private void ʻॱ()
  {
    for (;;)
    {
      break label75;
      try
      {
        i = ˊˋ;
        i += 125;
      }
      catch (Exception localException1)
      {
        throw localException1;
      }
      try
      {
        ˊˊ = i % 128;
        if (i % 2 != 0) {}
      }
      catch (Exception localException2)
      {
        throw localException2;
      }
    }
    int i = 31 / 0;
    return;
    for (;;)
    {
      switch (i)
      {
      case 1: 
      default: 
        break;
        ((JD)this.ॱˊ).ॱ.ˏ(new Jd[] { ((JD)this.ॱˊ).ʻ.ˏ() });
        ((JD)this.ॱˊ).ॱ.ˏ(new Jd[] { ((JD)this.ॱˊ).ʼ });
        ((JD)this.ॱˊ).ˎ(pQ.ˋ(ˋ(new byte[] { -123, -114, -118, -123, -116, -120, -115 }, null, null, 127).intern()));
        ((JD)this.ॱˊ).ˏ(this.ʾ);
        i = ˊˋ + 81;
        ˊˊ = i % 128;
        if (i % 2 == 0) {
          i = 0;
        }
        break;
      case 0: 
        label75:
        return;
        i = 1;
      }
    }
  }
  
  /* Error */
  private void ʾ()
  {
    // Byte code:
    //   0: goto +1330 -> 1330
    //   3: bipush 18
    //   5: newarray byte
    //   7: dup
    //   8: iconst_0
    //   9: ldc 108
    //   11: bastore
    //   12: dup
    //   13: iconst_1
    //   14: ldc 110
    //   16: bastore
    //   17: dup
    //   18: iconst_2
    //   19: ldc 107
    //   21: bastore
    //   22: dup
    //   23: iconst_3
    //   24: ldc -122
    //   26: bastore
    //   27: dup
    //   28: iconst_4
    //   29: ldc 106
    //   31: bastore
    //   32: dup
    //   33: iconst_5
    //   34: ldc -121
    //   36: bastore
    //   37: dup
    //   38: bipush 6
    //   40: ldc 107
    //   42: bastore
    //   43: dup
    //   44: bipush 7
    //   46: ldc -120
    //   48: bastore
    //   49: dup
    //   50: bipush 8
    //   52: ldc 107
    //   54: bastore
    //   55: dup
    //   56: bipush 9
    //   58: ldc -122
    //   60: bastore
    //   61: dup
    //   62: bipush 10
    //   64: ldc 108
    //   66: bastore
    //   67: dup
    //   68: bipush 11
    //   70: ldc -119
    //   72: bastore
    //   73: dup
    //   74: bipush 12
    //   76: ldc -118
    //   78: bastore
    //   79: dup
    //   80: bipush 13
    //   82: ldc -117
    //   84: bastore
    //   85: dup
    //   86: bipush 14
    //   88: ldc -116
    //   90: bastore
    //   91: dup
    //   92: bipush 15
    //   94: ldc -119
    //   96: bastore
    //   97: dup
    //   98: bipush 16
    //   100: ldc -115
    //   102: bastore
    //   103: dup
    //   104: bipush 17
    //   106: ldc -114
    //   108: bastore
    //   109: aconst_null
    //   110: aconst_null
    //   111: bipush 127
    //   113: invokestatic 115	o/Kv:ˋ	([B[I[CI)Ljava/lang/String;
    //   116: invokevirtual 121	java/lang/String:intern	()Ljava/lang/String;
    //   119: astore_3
    //   120: bipush 78
    //   122: newarray byte
    //   124: dup
    //   125: iconst_0
    //   126: ldc -113
    //   128: bastore
    //   129: dup
    //   130: iconst_1
    //   131: ldc 108
    //   133: bastore
    //   134: dup
    //   135: iconst_2
    //   136: ldc -119
    //   138: bastore
    //   139: dup
    //   140: iconst_3
    //   141: ldc -119
    //   143: bastore
    //   144: dup
    //   145: iconst_4
    //   146: ldc -116
    //   148: bastore
    //   149: dup
    //   150: iconst_5
    //   151: ldc -121
    //   153: bastore
    //   154: dup
    //   155: bipush 6
    //   157: ldc -115
    //   159: bastore
    //   160: dup
    //   161: bipush 7
    //   163: ldc -112
    //   165: bastore
    //   166: dup
    //   167: bipush 8
    //   169: ldc -119
    //   171: bastore
    //   172: dup
    //   173: bipush 9
    //   175: ldc -122
    //   177: bastore
    //   178: dup
    //   179: bipush 10
    //   181: ldc 106
    //   183: bastore
    //   184: dup
    //   185: bipush 11
    //   187: ldc -118
    //   189: bastore
    //   190: dup
    //   191: bipush 12
    //   193: ldc -112
    //   195: bastore
    //   196: dup
    //   197: bipush 13
    //   199: ldc -111
    //   201: bastore
    //   202: dup
    //   203: bipush 14
    //   205: ldc -122
    //   207: bastore
    //   208: dup
    //   209: bipush 15
    //   211: ldc -116
    //   213: bastore
    //   214: dup
    //   215: bipush 16
    //   217: ldc 107
    //   219: bastore
    //   220: dup
    //   221: bipush 17
    //   223: ldc -110
    //   225: bastore
    //   226: dup
    //   227: bipush 18
    //   229: ldc -112
    //   231: bastore
    //   232: dup
    //   233: bipush 19
    //   235: ldc -116
    //   237: bastore
    //   238: dup
    //   239: bipush 20
    //   241: ldc -119
    //   243: bastore
    //   244: dup
    //   245: bipush 21
    //   247: ldc -122
    //   249: bastore
    //   250: dup
    //   251: bipush 22
    //   253: ldc 108
    //   255: bastore
    //   256: dup
    //   257: bipush 23
    //   259: ldc -109
    //   261: bastore
    //   262: dup
    //   263: bipush 24
    //   265: ldc -112
    //   267: bastore
    //   268: dup
    //   269: bipush 25
    //   271: ldc -113
    //   273: bastore
    //   274: dup
    //   275: bipush 26
    //   277: ldc -116
    //   279: bastore
    //   280: dup
    //   281: bipush 27
    //   283: ldc -119
    //   285: bastore
    //   286: dup
    //   287: bipush 28
    //   289: ldc -110
    //   291: bastore
    //   292: dup
    //   293: bipush 29
    //   295: ldc 109
    //   297: bastore
    //   298: dup
    //   299: bipush 30
    //   301: ldc -108
    //   303: bastore
    //   304: dup
    //   305: bipush 31
    //   307: ldc 108
    //   309: bastore
    //   310: dup
    //   311: bipush 32
    //   313: ldc -112
    //   315: bastore
    //   316: dup
    //   317: bipush 33
    //   319: ldc -119
    //   321: bastore
    //   322: dup
    //   323: bipush 34
    //   325: ldc 108
    //   327: bastore
    //   328: dup
    //   329: bipush 35
    //   331: ldc 110
    //   333: bastore
    //   334: dup
    //   335: bipush 36
    //   337: ldc -111
    //   339: bastore
    //   340: dup
    //   341: bipush 37
    //   343: ldc -107
    //   345: bastore
    //   346: dup
    //   347: bipush 38
    //   349: ldc -112
    //   351: bastore
    //   352: dup
    //   353: bipush 39
    //   355: ldc -122
    //   357: bastore
    //   358: dup
    //   359: bipush 40
    //   361: ldc -115
    //   363: bastore
    //   364: dup
    //   365: bipush 41
    //   367: ldc -108
    //   369: bastore
    //   370: dup
    //   371: bipush 42
    //   373: ldc -106
    //   375: bastore
    //   376: dup
    //   377: bipush 43
    //   379: ldc -112
    //   381: bastore
    //   382: dup
    //   383: bipush 44
    //   385: ldc -105
    //   387: bastore
    //   388: dup
    //   389: bipush 45
    //   391: ldc 108
    //   393: bastore
    //   394: dup
    //   395: bipush 46
    //   397: ldc 107
    //   399: bastore
    //   400: dup
    //   401: bipush 47
    //   403: ldc -115
    //   405: bastore
    //   406: dup
    //   407: bipush 48
    //   409: ldc -108
    //   411: bastore
    //   412: dup
    //   413: bipush 49
    //   415: ldc -112
    //   417: bastore
    //   418: dup
    //   419: bipush 50
    //   421: ldc -118
    //   423: bastore
    //   424: dup
    //   425: bipush 51
    //   427: ldc -119
    //   429: bastore
    //   430: dup
    //   431: bipush 52
    //   433: ldc 107
    //   435: bastore
    //   436: dup
    //   437: bipush 53
    //   439: ldc -120
    //   441: bastore
    //   442: dup
    //   443: bipush 54
    //   445: ldc 107
    //   447: bastore
    //   448: dup
    //   449: bipush 55
    //   451: ldc -122
    //   453: bastore
    //   454: dup
    //   455: bipush 56
    //   457: ldc 108
    //   459: bastore
    //   460: dup
    //   461: bipush 57
    //   463: ldc -119
    //   465: bastore
    //   466: dup
    //   467: bipush 58
    //   469: ldc -118
    //   471: bastore
    //   472: dup
    //   473: bipush 59
    //   475: ldc 107
    //   477: bastore
    //   478: dup
    //   479: bipush 60
    //   481: ldc -112
    //   483: bastore
    //   484: dup
    //   485: bipush 61
    //   487: ldc -119
    //   489: bastore
    //   490: dup
    //   491: bipush 62
    //   493: ldc -110
    //   495: bastore
    //   496: dup
    //   497: bipush 63
    //   499: ldc -112
    //   501: bastore
    //   502: dup
    //   503: bipush 64
    //   505: ldc -122
    //   507: bastore
    //   508: dup
    //   509: bipush 65
    //   511: ldc 110
    //   513: bastore
    //   514: dup
    //   515: bipush 66
    //   517: ldc 108
    //   519: bastore
    //   520: dup
    //   521: bipush 67
    //   523: ldc -112
    //   525: bastore
    //   526: dup
    //   527: bipush 68
    //   529: ldc -118
    //   531: bastore
    //   532: dup
    //   533: bipush 69
    //   535: ldc -104
    //   537: bastore
    //   538: dup
    //   539: bipush 70
    //   541: ldc -108
    //   543: bastore
    //   544: dup
    //   545: bipush 71
    //   547: ldc 110
    //   549: bastore
    //   550: dup
    //   551: bipush 72
    //   553: ldc -121
    //   555: bastore
    //   556: dup
    //   557: bipush 73
    //   559: ldc -112
    //   561: bastore
    //   562: dup
    //   563: bipush 74
    //   565: ldc -116
    //   567: bastore
    //   568: dup
    //   569: bipush 75
    //   571: ldc -119
    //   573: bastore
    //   574: dup
    //   575: bipush 76
    //   577: ldc -115
    //   579: bastore
    //   580: dup
    //   581: bipush 77
    //   583: ldc -114
    //   585: bastore
    //   586: aconst_null
    //   587: aconst_null
    //   588: bipush 127
    //   590: invokestatic 115	o/Kv:ˋ	([B[I[CI)Ljava/lang/String;
    //   593: invokevirtual 121	java/lang/String:intern	()Ljava/lang/String;
    //   596: astore 4
    //   598: goto +20 -> 618
    //   601: astore_3
    //   602: aload_3
    //   603: invokevirtual 158	java/lang/Throwable:getCause	()Ljava/lang/Throwable;
    //   606: astore 4
    //   608: aload 4
    //   610: ifnull +6 -> 616
    //   613: aload 4
    //   615: athrow
    //   616: aload_3
    //   617: athrow
    //   618: aload_0
    //   619: invokevirtual 164	android/content/Context:getResources	()Landroid/content/res/Resources;
    //   622: ldc -91
    //   624: invokevirtual 171	android/content/res/Resources:getString	(I)Ljava/lang/String;
    //   627: iconst_0
    //   628: iconst_4
    //   629: invokevirtual 175	java/lang/String:substring	(II)Ljava/lang/String;
    //   632: invokevirtual 179	java/lang/String:length	()I
    //   635: iconst_0
    //   636: iadd
    //   637: aload_0
    //   638: invokevirtual 182	android/content/Context:getPackageName	()Ljava/lang/String;
    //   641: bipush 10
    //   643: invokevirtual 186	java/lang/String:codePointAt	(I)I
    //   646: bipush 79
    //   648: isub
    //   649: aload_0
    //   650: invokevirtual 182	android/content/Context:getPackageName	()Ljava/lang/String;
    //   653: iconst_5
    //   654: invokevirtual 186	java/lang/String:codePointAt	(I)I
    //   657: ldc -69
    //   659: iadd
    //   660: i2c
    //   661: invokestatic 192	o/O:ˋ	(IIC)Ljava/lang/Object;
    //   664: checkcast 194	java/lang/Class
    //   667: ldc -61
    //   669: iconst_2
    //   670: anewarray 194	java/lang/Class
    //   673: dup
    //   674: iconst_0
    //   675: ldc 117
    //   677: aastore
    //   678: dup
    //   679: iconst_1
    //   680: ldc 117
    //   682: aastore
    //   683: invokevirtual 199	java/lang/Class:getMethod	(Ljava/lang/String;[Ljava/lang/Class;)Ljava/lang/reflect/Method;
    //   686: aconst_null
    //   687: iconst_2
    //   688: anewarray 201	java/lang/Object
    //   691: dup
    //   692: iconst_0
    //   693: aload_3
    //   694: aastore
    //   695: dup
    //   696: iconst_1
    //   697: aload 4
    //   699: aastore
    //   700: invokevirtual 207	java/lang/reflect/Method:invoke	(Ljava/lang/Object;[Ljava/lang/Object;)Ljava/lang/Object;
    //   703: pop
    //   704: aload_0
    //   705: invokevirtual 210	o/Kv:finish	()V
    //   708: aload_0
    //   709: invokestatic 215	o/Ic:ˏ	(Landroid/content/Context;)Lo/Ic;
    //   712: invokevirtual 218	o/Ic:ʽॱ	()Lo/j;
    //   715: invokevirtual 222	o/j:ˎ	()V
    //   718: goto +615 -> 1333
    //   721: iconst_1
    //   722: istore_1
    //   723: goto +613 -> 1336
    //   726: astore_3
    //   727: aload_3
    //   728: athrow
    //   729: getstatic 26	o/Kv:ˊˋ	I
    //   732: iconst_5
    //   733: iadd
    //   734: istore_1
    //   735: iload_1
    //   736: sipush 128
    //   739: irem
    //   740: putstatic 24	o/Kv:ˊˊ	I
    //   743: iload_1
    //   744: iconst_2
    //   745: irem
    //   746: ifeq +6 -> 752
    //   749: goto +851 -> 1600
    //   752: goto -31 -> 721
    //   755: goto +20 -> 775
    //   758: astore_3
    //   759: aload_3
    //   760: invokevirtual 158	java/lang/Throwable:getCause	()Ljava/lang/Throwable;
    //   763: astore 4
    //   765: aload 4
    //   767: ifnull +6 -> 773
    //   770: aload 4
    //   772: athrow
    //   773: aload_3
    //   774: athrow
    //   775: aload_0
    //   776: invokevirtual 164	android/content/Context:getResources	()Landroid/content/res/Resources;
    //   779: ldc -33
    //   781: invokevirtual 171	android/content/res/Resources:getString	(I)Ljava/lang/String;
    //   784: iconst_0
    //   785: iconst_4
    //   786: invokevirtual 175	java/lang/String:substring	(II)Ljava/lang/String;
    //   789: iconst_3
    //   790: invokevirtual 186	java/lang/String:codePointAt	(I)I
    //   793: bipush 8
    //   795: isub
    //   796: aload_0
    //   797: invokevirtual 164	android/content/Context:getResources	()Landroid/content/res/Resources;
    //   800: ldc -32
    //   802: invokevirtual 171	android/content/res/Resources:getString	(I)Ljava/lang/String;
    //   805: iconst_0
    //   806: bipush 10
    //   808: invokevirtual 175	java/lang/String:substring	(II)Ljava/lang/String;
    //   811: invokevirtual 179	java/lang/String:length	()I
    //   814: sipush 403
    //   817: iadd
    //   818: aload_0
    //   819: invokevirtual 164	android/content/Context:getResources	()Landroid/content/res/Resources;
    //   822: ldc -31
    //   824: invokevirtual 171	android/content/res/Resources:getString	(I)Ljava/lang/String;
    //   827: iconst_0
    //   828: iconst_4
    //   829: invokevirtual 175	java/lang/String:substring	(II)Ljava/lang/String;
    //   832: iconst_1
    //   833: invokevirtual 186	java/lang/String:codePointAt	(I)I
    //   836: sipush 30227
    //   839: iadd
    //   840: i2c
    //   841: invokestatic 192	o/O:ˋ	(IIC)Ljava/lang/Object;
    //   844: checkcast 194	java/lang/Class
    //   847: ldc -30
    //   849: aconst_null
    //   850: invokevirtual 199	java/lang/Class:getMethod	(Ljava/lang/String;[Ljava/lang/Class;)Ljava/lang/reflect/Method;
    //   853: aconst_null
    //   854: aconst_null
    //   855: invokevirtual 207	java/lang/reflect/Method:invoke	(Ljava/lang/Object;[Ljava/lang/Object;)Ljava/lang/Object;
    //   858: astore_3
    //   859: goto +20 -> 879
    //   862: astore_3
    //   863: aload_3
    //   864: invokevirtual 158	java/lang/Throwable:getCause	()Ljava/lang/Throwable;
    //   867: astore 4
    //   869: aload 4
    //   871: ifnull +6 -> 877
    //   874: aload 4
    //   876: athrow
    //   877: aload_3
    //   878: athrow
    //   879: aload_0
    //   880: invokevirtual 164	android/content/Context:getResources	()Landroid/content/res/Resources;
    //   883: ldc -29
    //   885: invokevirtual 171	android/content/res/Resources:getString	(I)Ljava/lang/String;
    //   888: iconst_0
    //   889: iconst_5
    //   890: invokevirtual 175	java/lang/String:substring	(II)Ljava/lang/String;
    //   893: iconst_1
    //   894: invokevirtual 186	java/lang/String:codePointAt	(I)I
    //   897: bipush 22
    //   899: isub
    //   900: aload_0
    //   901: invokevirtual 231	android/content/Context:getApplicationInfo	()Landroid/content/pm/ApplicationInfo;
    //   904: getfield 236	android/content/pm/ApplicationInfo:targetSdkVersion	I
    //   907: sipush 388
    //   910: iadd
    //   911: aload_0
    //   912: invokevirtual 164	android/content/Context:getResources	()Landroid/content/res/Resources;
    //   915: ldc -19
    //   917: invokevirtual 171	android/content/res/Resources:getString	(I)Ljava/lang/String;
    //   920: iconst_0
    //   921: iconst_1
    //   922: invokevirtual 175	java/lang/String:substring	(II)Ljava/lang/String;
    //   925: iconst_0
    //   926: invokevirtual 186	java/lang/String:codePointAt	(I)I
    //   929: sipush 30196
    //   932: iadd
    //   933: i2c
    //   934: invokestatic 192	o/O:ˋ	(IIC)Ljava/lang/Object;
    //   937: checkcast 194	java/lang/Class
    //   940: ldc -18
    //   942: aconst_null
    //   943: invokevirtual 199	java/lang/Class:getMethod	(Ljava/lang/String;[Ljava/lang/Class;)Ljava/lang/reflect/Method;
    //   946: aload_3
    //   947: aconst_null
    //   948: invokevirtual 207	java/lang/reflect/Method:invoke	(Ljava/lang/Object;[Ljava/lang/Object;)Ljava/lang/Object;
    //   951: checkcast 240	o/ED
    //   954: astore_3
    //   955: getstatic 243	o/Kv$2:ॱ	[I
    //   958: astore 4
    //   960: aload 4
    //   962: aload_3
    //   963: invokevirtual 246	o/ED:ordinal	()I
    //   966: iaload
    //   967: istore_1
    //   968: iload_1
    //   969: lookupswitch	default:+19->988, 1:+-966->3
    //   988: goto +3 -> 991
    //   991: bipush 18
    //   993: newarray byte
    //   995: dup
    //   996: iconst_0
    //   997: ldc 108
    //   999: bastore
    //   1000: dup
    //   1001: iconst_1
    //   1002: ldc 110
    //   1004: bastore
    //   1005: dup
    //   1006: iconst_2
    //   1007: ldc 107
    //   1009: bastore
    //   1010: dup
    //   1011: iconst_3
    //   1012: ldc -122
    //   1014: bastore
    //   1015: dup
    //   1016: iconst_4
    //   1017: ldc 106
    //   1019: bastore
    //   1020: dup
    //   1021: iconst_5
    //   1022: ldc -121
    //   1024: bastore
    //   1025: dup
    //   1026: bipush 6
    //   1028: ldc 107
    //   1030: bastore
    //   1031: dup
    //   1032: bipush 7
    //   1034: ldc -120
    //   1036: bastore
    //   1037: dup
    //   1038: bipush 8
    //   1040: ldc 107
    //   1042: bastore
    //   1043: dup
    //   1044: bipush 9
    //   1046: ldc -122
    //   1048: bastore
    //   1049: dup
    //   1050: bipush 10
    //   1052: ldc 108
    //   1054: bastore
    //   1055: dup
    //   1056: bipush 11
    //   1058: ldc -119
    //   1060: bastore
    //   1061: dup
    //   1062: bipush 12
    //   1064: ldc -118
    //   1066: bastore
    //   1067: dup
    //   1068: bipush 13
    //   1070: ldc -117
    //   1072: bastore
    //   1073: dup
    //   1074: bipush 14
    //   1076: ldc -116
    //   1078: bastore
    //   1079: dup
    //   1080: bipush 15
    //   1082: ldc -119
    //   1084: bastore
    //   1085: dup
    //   1086: bipush 16
    //   1088: ldc -115
    //   1090: bastore
    //   1091: dup
    //   1092: bipush 17
    //   1094: ldc -114
    //   1096: bastore
    //   1097: aconst_null
    //   1098: aconst_null
    //   1099: bipush 127
    //   1101: invokestatic 115	o/Kv:ˋ	([B[I[CI)Ljava/lang/String;
    //   1104: invokevirtual 121	java/lang/String:intern	()Ljava/lang/String;
    //   1107: astore_3
    //   1108: bipush 15
    //   1110: newarray byte
    //   1112: dup
    //   1113: iconst_0
    //   1114: ldc -118
    //   1116: bastore
    //   1117: dup
    //   1118: iconst_1
    //   1119: ldc -119
    //   1121: bastore
    //   1122: dup
    //   1123: iconst_2
    //   1124: ldc 107
    //   1126: bastore
    //   1127: dup
    //   1128: iconst_3
    //   1129: ldc -120
    //   1131: bastore
    //   1132: dup
    //   1133: iconst_4
    //   1134: ldc 107
    //   1136: bastore
    //   1137: dup
    //   1138: iconst_5
    //   1139: ldc -122
    //   1141: bastore
    //   1142: dup
    //   1143: bipush 6
    //   1145: ldc 108
    //   1147: bastore
    //   1148: dup
    //   1149: bipush 7
    //   1151: ldc -119
    //   1153: bastore
    //   1154: dup
    //   1155: bipush 8
    //   1157: ldc -118
    //   1159: bastore
    //   1160: dup
    //   1161: bipush 9
    //   1163: ldc 107
    //   1165: bastore
    //   1166: dup
    //   1167: bipush 10
    //   1169: ldc -112
    //   1171: bastore
    //   1172: dup
    //   1173: bipush 11
    //   1175: ldc -116
    //   1177: bastore
    //   1178: dup
    //   1179: bipush 12
    //   1181: ldc -119
    //   1183: bastore
    //   1184: dup
    //   1185: bipush 13
    //   1187: ldc -115
    //   1189: bastore
    //   1190: dup
    //   1191: bipush 14
    //   1193: ldc -114
    //   1195: bastore
    //   1196: aconst_null
    //   1197: aconst_null
    //   1198: bipush 127
    //   1200: invokestatic 115	o/Kv:ˋ	([B[I[CI)Ljava/lang/String;
    //   1203: invokevirtual 121	java/lang/String:intern	()Ljava/lang/String;
    //   1206: astore 4
    //   1208: goto +20 -> 1228
    //   1211: astore_3
    //   1212: aload_3
    //   1213: invokevirtual 158	java/lang/Throwable:getCause	()Ljava/lang/Throwable;
    //   1216: astore 4
    //   1218: aload 4
    //   1220: ifnull +6 -> 1226
    //   1223: aload 4
    //   1225: athrow
    //   1226: aload_3
    //   1227: athrow
    //   1228: aload_0
    //   1229: invokevirtual 182	android/content/Context:getPackageName	()Ljava/lang/String;
    //   1232: invokevirtual 179	java/lang/String:length	()I
    //   1235: bipush 7
    //   1237: isub
    //   1238: aload_0
    //   1239: invokevirtual 231	android/content/Context:getApplicationInfo	()Landroid/content/pm/ApplicationInfo;
    //   1242: getfield 236	android/content/pm/ApplicationInfo:targetSdkVersion	I
    //   1245: bipush 17
    //   1247: iadd
    //   1248: aload_0
    //   1249: invokevirtual 164	android/content/Context:getResources	()Landroid/content/res/Resources;
    //   1252: ldc -9
    //   1254: invokevirtual 171	android/content/res/Resources:getString	(I)Ljava/lang/String;
    //   1257: iconst_0
    //   1258: bipush 15
    //   1260: invokevirtual 175	java/lang/String:substring	(II)Ljava/lang/String;
    //   1263: bipush 8
    //   1265: invokevirtual 186	java/lang/String:codePointAt	(I)I
    //   1268: ldc -8
    //   1270: iadd
    //   1271: i2c
    //   1272: invokestatic 192	o/O:ˋ	(IIC)Ljava/lang/Object;
    //   1275: checkcast 194	java/lang/Class
    //   1278: ldc -61
    //   1280: iconst_2
    //   1281: anewarray 194	java/lang/Class
    //   1284: dup
    //   1285: iconst_0
    //   1286: ldc 117
    //   1288: aastore
    //   1289: dup
    //   1290: iconst_1
    //   1291: ldc 117
    //   1293: aastore
    //   1294: invokevirtual 199	java/lang/Class:getMethod	(Ljava/lang/String;[Ljava/lang/Class;)Ljava/lang/reflect/Method;
    //   1297: aconst_null
    //   1298: iconst_2
    //   1299: anewarray 201	java/lang/Object
    //   1302: dup
    //   1303: iconst_0
    //   1304: aload_3
    //   1305: aastore
    //   1306: dup
    //   1307: iconst_1
    //   1308: aload 4
    //   1310: aastore
    //   1311: invokevirtual 207	java/lang/reflect/Method:invoke	(Ljava/lang/Object;[Ljava/lang/Object;)Ljava/lang/Object;
    //   1314: pop
    //   1315: aload_0
    //   1316: invokestatic 215	o/Ic:ˏ	(Landroid/content/Context;)Lo/Ic;
    //   1319: invokevirtual 251	o/Ic:ͺ	()Lo/j;
    //   1322: bipush 13
    //   1324: invokevirtual 254	o/j:ˎ	(I)V
    //   1327: goto +6 -> 1333
    //   1330: goto -601 -> 729
    //   1333: goto +242 -> 1575
    //   1336: iload_1
    //   1337: tableswitch	default:+23->1360, 0:+23->1360, 1:+-582->755
    //   1360: goto +20 -> 1380
    //   1363: astore_3
    //   1364: aload_3
    //   1365: invokevirtual 158	java/lang/Throwable:getCause	()Ljava/lang/Throwable;
    //   1368: astore 4
    //   1370: aload 4
    //   1372: ifnull +6 -> 1378
    //   1375: aload 4
    //   1377: athrow
    //   1378: aload_3
    //   1379: athrow
    //   1380: aload_0
    //   1381: invokevirtual 164	android/content/Context:getResources	()Landroid/content/res/Resources;
    //   1384: ldc -1
    //   1386: invokevirtual 171	android/content/res/Resources:getString	(I)Ljava/lang/String;
    //   1389: iconst_0
    //   1390: iconst_5
    //   1391: invokevirtual 175	java/lang/String:substring	(II)Ljava/lang/String;
    //   1394: iconst_3
    //   1395: invokevirtual 186	java/lang/String:codePointAt	(I)I
    //   1398: bipush 8
    //   1400: isub
    //   1401: aload_0
    //   1402: invokevirtual 182	android/content/Context:getPackageName	()Ljava/lang/String;
    //   1405: invokevirtual 179	java/lang/String:length	()I
    //   1408: sipush 402
    //   1411: iadd
    //   1412: aload_0
    //   1413: invokevirtual 182	android/content/Context:getPackageName	()Ljava/lang/String;
    //   1416: invokevirtual 179	java/lang/String:length	()I
    //   1419: sipush 30242
    //   1422: iadd
    //   1423: i2c
    //   1424: invokestatic 192	o/O:ˋ	(IIC)Ljava/lang/Object;
    //   1427: checkcast 194	java/lang/Class
    //   1430: ldc -30
    //   1432: aconst_null
    //   1433: invokevirtual 199	java/lang/Class:getMethod	(Ljava/lang/String;[Ljava/lang/Class;)Ljava/lang/reflect/Method;
    //   1436: aconst_null
    //   1437: aconst_null
    //   1438: invokevirtual 207	java/lang/reflect/Method:invoke	(Ljava/lang/Object;[Ljava/lang/Object;)Ljava/lang/Object;
    //   1441: astore_3
    //   1442: goto +20 -> 1462
    //   1445: astore_3
    //   1446: aload_3
    //   1447: invokevirtual 158	java/lang/Throwable:getCause	()Ljava/lang/Throwable;
    //   1450: astore 4
    //   1452: aload 4
    //   1454: ifnull +6 -> 1460
    //   1457: aload 4
    //   1459: athrow
    //   1460: aload_3
    //   1461: athrow
    //   1462: aload_0
    //   1463: invokevirtual 164	android/content/Context:getResources	()Landroid/content/res/Resources;
    //   1466: ldc_w 256
    //   1469: invokevirtual 171	android/content/res/Resources:getString	(I)Ljava/lang/String;
    //   1472: iconst_0
    //   1473: iconst_5
    //   1474: invokevirtual 175	java/lang/String:substring	(II)Ljava/lang/String;
    //   1477: invokevirtual 179	java/lang/String:length	()I
    //   1480: iconst_1
    //   1481: isub
    //   1482: aload_0
    //   1483: invokevirtual 164	android/content/Context:getResources	()Landroid/content/res/Resources;
    //   1486: ldc_w 257
    //   1489: invokevirtual 171	android/content/res/Resources:getString	(I)Ljava/lang/String;
    //   1492: iconst_0
    //   1493: iconst_5
    //   1494: invokevirtual 175	java/lang/String:substring	(II)Ljava/lang/String;
    //   1497: invokevirtual 179	java/lang/String:length	()I
    //   1500: sipush 408
    //   1503: iadd
    //   1504: aload_0
    //   1505: invokevirtual 231	android/content/Context:getApplicationInfo	()Landroid/content/pm/ApplicationInfo;
    //   1508: getfield 236	android/content/pm/ApplicationInfo:targetSdkVersion	I
    //   1511: sipush 30228
    //   1514: iadd
    //   1515: i2c
    //   1516: invokestatic 192	o/O:ˋ	(IIC)Ljava/lang/Object;
    //   1519: checkcast 194	java/lang/Class
    //   1522: ldc -18
    //   1524: aconst_null
    //   1525: invokevirtual 199	java/lang/Class:getMethod	(Ljava/lang/String;[Ljava/lang/Class;)Ljava/lang/reflect/Method;
    //   1528: aload_3
    //   1529: aconst_null
    //   1530: invokevirtual 207	java/lang/reflect/Method:invoke	(Ljava/lang/Object;[Ljava/lang/Object;)Ljava/lang/Object;
    //   1533: checkcast 240	o/ED
    //   1536: astore_3
    //   1537: getstatic 243	o/Kv$2:ॱ	[I
    //   1540: aload_3
    //   1541: invokevirtual 246	o/ED:ordinal	()I
    //   1544: iaload
    //   1545: istore_1
    //   1546: bipush 59
    //   1548: iconst_0
    //   1549: idiv
    //   1550: istore_2
    //   1551: iload_1
    //   1552: lookupswitch	default:+20->1572, 1:+-1549->3
    //   1572: goto -581 -> 991
    //   1575: getstatic 26	o/Kv:ˊˋ	I
    //   1578: istore_1
    //   1579: iload_1
    //   1580: bipush 113
    //   1582: iadd
    //   1583: istore_1
    //   1584: iload_1
    //   1585: sipush 128
    //   1588: irem
    //   1589: putstatic 24	o/Kv:ˊˊ	I
    //   1592: iload_1
    //   1593: iconst_2
    //   1594: irem
    //   1595: ifeq +4 -> 1599
    //   1598: return
    //   1599: return
    //   1600: iconst_0
    //   1601: istore_1
    //   1602: goto -266 -> 1336
    //   1605: astore_3
    //   1606: aload_3
    //   1607: athrow
    // Local variable table:
    //   start	length	slot	name	signature
    //   0	1608	0	this	Kv
    //   722	880	1	i	int
    //   1550	1	2	j	int
    //   119	1	3	str	String
    //   601	93	3	localObject1	Object
    //   726	2	3	localException1	Exception
    //   758	16	3	localObject2	Object
    //   858	1	3	localObject3	Object
    //   862	85	3	localObject4	Object
    //   954	154	3	localObject5	Object
    //   1211	94	3	localObject6	Object
    //   1363	16	3	localObject7	Object
    //   1441	1	3	localObject8	Object
    //   1445	84	3	localObject9	Object
    //   1536	5	3	localED	ED
    //   1605	2	3	localException2	Exception
    //   596	862	4	localObject10	Object
    // Exception table:
    //   from	to	target	type
    //   618	704	601	finally
    //   759	765	726	java/lang/Exception
    //   770	773	726	java/lang/Exception
    //   773	775	726	java/lang/Exception
    //   863	869	726	java/lang/Exception
    //   874	877	726	java/lang/Exception
    //   877	879	726	java/lang/Exception
    //   955	960	726	java/lang/Exception
    //   960	968	726	java/lang/Exception
    //   775	859	758	finally
    //   879	955	862	finally
    //   1228	1315	1211	finally
    //   1380	1442	1363	finally
    //   1462	1537	1445	finally
    //   863	869	1605	java/lang/Exception
    //   874	877	1605	java/lang/Exception
    //   877	879	1605	java/lang/Exception
    //   1575	1579	1605	java/lang/Exception
  }
  
  /* Error */
  private static String ˋ(byte[] paramArrayOfByte, int[] paramArrayOfInt, char[] paramArrayOfChar, int paramInt)
  {
    // Byte code:
    //   0: goto +71 -> 71
    //   3: new 117	java/lang/String
    //   6: dup
    //   7: aload_1
    //   8: invokespecial 260	java/lang/String:<init>	([C)V
    //   11: areturn
    //   12: getstatic 26	o/Kv:ˊˋ	I
    //   15: bipush 121
    //   17: iadd
    //   18: istore 4
    //   20: iload 4
    //   22: sipush 128
    //   25: irem
    //   26: putstatic 24	o/Kv:ˊˊ	I
    //   29: iload 4
    //   31: iconst_2
    //   32: irem
    //   33: ifeq +6 -> 39
    //   36: goto +417 -> 453
    //   39: goto +158 -> 197
    //   42: iload 5
    //   44: tableswitch	default:+24->68, 0:+94->138, 1:+273->317
    //   68: goto +249 -> 317
    //   71: goto +172 -> 243
    //   74: getstatic 30	o/Kv:ʼॱ	Z
    //   77: ifeq +6 -> 83
    //   80: goto +189 -> 269
    //   83: goto +265 -> 348
    //   86: goto +268 -> 354
    //   89: new 117	java/lang/String
    //   92: dup
    //   93: aload_0
    //   94: invokespecial 260	java/lang/String:<init>	([C)V
    //   97: areturn
    //   98: iload 4
    //   100: lookupswitch	default:+28->128, 2:+282->382, 22:+-88->12
    //   128: goto +254 -> 382
    //   131: bipush 60
    //   133: istore 4
    //   135: goto +77 -> 212
    //   138: new 117	java/lang/String
    //   141: dup
    //   142: aload_0
    //   143: invokespecial 260	java/lang/String:<init>	([C)V
    //   146: areturn
    //   147: iload 4
    //   149: iload 7
    //   151: if_icmpge +6 -> 157
    //   154: goto +262 -> 416
    //   157: goto +253 -> 410
    //   160: astore_0
    //   161: aload_0
    //   162: athrow
    //   163: getstatic 24	o/Kv:ˊˊ	I
    //   166: istore 7
    //   168: iload 7
    //   170: bipush 9
    //   172: iadd
    //   173: istore 7
    //   175: iload 7
    //   177: sipush 128
    //   180: irem
    //   181: putstatic 26	o/Kv:ˊˋ	I
    //   184: iload 7
    //   186: iconst_2
    //   187: irem
    //   188: ifne +6 -> 194
    //   191: goto +123 -> 314
    //   194: goto +89 -> 283
    //   197: aload_2
    //   198: arraylength
    //   199: istore 5
    //   201: iload 5
    //   203: newarray char
    //   205: astore_0
    //   206: iconst_0
    //   207: istore 4
    //   209: goto +188 -> 397
    //   212: iload 4
    //   214: lookupswitch	default:+26->240, 59:+-140->74, 60:+153->367
    //   240: goto -166 -> 74
    //   243: getstatic 60	o/Kv:ʽॱ	[C
    //   246: astore 9
    //   248: getstatic 62	o/Kv:ʿ	I
    //   251: istore 6
    //   253: getstatic 28	o/Kv:ˈ	Z
    //   256: istore 8
    //   258: iload 8
    //   260: ifeq +6 -> 266
    //   263: goto -132 -> 131
    //   266: goto +10 -> 276
    //   269: bipush 22
    //   271: istore 4
    //   273: goto -175 -> 98
    //   276: bipush 59
    //   278: istore 4
    //   280: goto -68 -> 212
    //   283: aload_0
    //   284: iload 4
    //   286: aload 9
    //   288: aload_2
    //   289: iload 5
    //   291: iconst_1
    //   292: isub
    //   293: iload 4
    //   295: isub
    //   296: caload
    //   297: iload_3
    //   298: isub
    //   299: caload
    //   300: iload 6
    //   302: isub
    //   303: i2c
    //   304: castore
    //   305: iload 4
    //   307: iconst_1
    //   308: iadd
    //   309: istore 4
    //   311: goto +86 -> 397
    //   314: goto -31 -> 283
    //   317: aload_0
    //   318: iload 4
    //   320: aload 9
    //   322: aload_1
    //   323: iload 7
    //   325: iconst_1
    //   326: isub
    //   327: iload 4
    //   329: isub
    //   330: iaload
    //   331: iload_3
    //   332: isub
    //   333: caload
    //   334: iload 6
    //   336: isub
    //   337: i2c
    //   338: castore
    //   339: iload 4
    //   341: iconst_1
    //   342: iadd
    //   343: istore 4
    //   345: goto -198 -> 147
    //   348: iconst_2
    //   349: istore 4
    //   351: goto -253 -> 98
    //   354: iload 4
    //   356: iload 5
    //   358: if_icmpge +6 -> 364
    //   361: goto +61 -> 422
    //   364: goto -361 -> 3
    //   367: aload_0
    //   368: arraylength
    //   369: istore 5
    //   371: iload 5
    //   373: newarray char
    //   375: astore_1
    //   376: iconst_0
    //   377: istore 4
    //   379: goto -293 -> 86
    //   382: aload_1
    //   383: arraylength
    //   384: istore 7
    //   386: iload 7
    //   388: newarray char
    //   390: astore_0
    //   391: iconst_0
    //   392: istore 4
    //   394: goto -247 -> 147
    //   397: iload 4
    //   399: iload 5
    //   401: if_icmpge +6 -> 407
    //   404: goto -241 -> 163
    //   407: goto -318 -> 89
    //   410: iconst_0
    //   411: istore 5
    //   413: goto -371 -> 42
    //   416: iconst_1
    //   417: istore 5
    //   419: goto -377 -> 42
    //   422: aload_1
    //   423: iload 4
    //   425: aload 9
    //   427: aload_0
    //   428: iload 5
    //   430: iconst_1
    //   431: isub
    //   432: iload 4
    //   434: isub
    //   435: baload
    //   436: iload_3
    //   437: iadd
    //   438: caload
    //   439: iload 6
    //   441: isub
    //   442: i2c
    //   443: castore
    //   444: iload 4
    //   446: iconst_1
    //   447: iadd
    //   448: istore 4
    //   450: goto -96 -> 354
    //   453: goto -256 -> 197
    //   456: astore_0
    //   457: aload_0
    //   458: athrow
    // Local variable table:
    //   start	length	slot	name	signature
    //   0	459	0	paramArrayOfByte	byte[]
    //   0	459	1	paramArrayOfInt	int[]
    //   0	459	2	paramArrayOfChar	char[]
    //   0	459	3	paramInt	int
    //   18	431	4	i	int
    //   42	390	5	j	int
    //   251	191	6	k	int
    //   149	238	7	m	int
    //   256	3	8	bool	boolean
    //   246	180	9	arrayOfChar	char[]
    // Exception table:
    //   from	to	target	type
    //   175	184	160	java/lang/Exception
    //   243	248	160	java/lang/Exception
    //   163	168	456	java/lang/Exception
    //   248	253	456	java/lang/Exception
    //   253	258	456	java/lang/Exception
  }
  
  /* Error */
  private void ॱˋ()
  {
    // Byte code:
    //   0: goto +148 -> 148
    //   3: iload_1
    //   4: tableswitch	default:+24->28, 0:+362->366, 1:+334->338
    //   28: goto +338 -> 366
    //   31: astore_2
    //   32: aload_2
    //   33: athrow
    //   34: aload_2
    //   35: iconst_1
    //   36: newarray byte
    //   38: dup
    //   39: iconst_0
    //   40: ldc -112
    //   42: bastore
    //   43: aconst_null
    //   44: aconst_null
    //   45: bipush 127
    //   47: invokestatic 115	o/Kv:ˋ	([B[I[CI)Ljava/lang/String;
    //   50: invokevirtual 121	java/lang/String:intern	()Ljava/lang/String;
    //   53: ldc_w 263
    //   56: invokevirtual 267	java/lang/String:replaceAll	(Ljava/lang/String;Ljava/lang/String;)Ljava/lang/String;
    //   59: astore 4
    //   61: new 269	o/KM
    //   64: dup
    //   65: aload_0
    //   66: aload_2
    //   67: aload_3
    //   68: new 271	o/Em
    //   71: dup
    //   72: getstatic 277	o/Er:PHONE_VALIDATION	Lo/Er;
    //   75: getstatic 283	o/Eq:SMS	Lo/Eq;
    //   78: aload 4
    //   80: aconst_null
    //   81: aload_0
    //   82: getfield 78	o/Kv:ॱˊ	Landroid/databinding/ViewDataBinding;
    //   85: checkcast 80	o/JD
    //   88: getfield 105	o/JD:ʼ	Lo/Jl;
    //   91: invokevirtual 288	o/Jl:ʽ	()Ljava/lang/String;
    //   94: invokespecial 291	o/Em:<init>	(Lo/Er;Lo/Eq;Ljava/lang/String;Ljava/lang/String;Ljava/lang/String;)V
    //   97: invokespecial 294	o/KM:<init>	(Landroid/content/Context;Ljava/lang/String;Ljava/lang/String;Lo/Em;)V
    //   100: invokevirtual 297	o/KM:ˏ	()Lo/ᐸ;
    //   103: pop
    //   104: return
    //   105: iconst_1
    //   106: istore_1
    //   107: goto -104 -> 3
    //   110: aload 4
    //   112: iconst_0
    //   113: invokevirtual 301	java/lang/String:charAt	(I)C
    //   116: istore_1
    //   117: iload_1
    //   118: bipush 48
    //   120: if_icmpne +6 -> 126
    //   123: goto +156 -> 279
    //   126: goto +212 -> 338
    //   129: aload 4
    //   131: iconst_0
    //   132: invokevirtual 301	java/lang/String:charAt	(I)C
    //   135: istore_1
    //   136: iload_1
    //   137: bipush 97
    //   139: if_icmpne +6 -> 145
    //   142: goto +137 -> 279
    //   145: goto +193 -> 338
    //   148: goto +6 -> 154
    //   151: astore_2
    //   152: aload_2
    //   153: athrow
    //   154: aload_0
    //   155: getfield 78	o/Kv:ॱˊ	Landroid/databinding/ViewDataBinding;
    //   158: checkcast 80	o/JD
    //   161: invokevirtual 304	o/JD:ॱˊ	()Lo/pQ;
    //   164: invokevirtual 306	o/pQ:ˏ	()Ljava/lang/String;
    //   167: astore_3
    //   168: new 308	java/lang/StringBuilder
    //   171: dup
    //   172: invokespecial 309	java/lang/StringBuilder:<init>	()V
    //   175: aload_3
    //   176: invokevirtual 313	java/lang/StringBuilder:append	(Ljava/lang/String;)Ljava/lang/StringBuilder;
    //   179: iconst_1
    //   180: newarray byte
    //   182: dup
    //   183: iconst_0
    //   184: ldc -112
    //   186: bastore
    //   187: aconst_null
    //   188: aconst_null
    //   189: bipush 127
    //   191: invokestatic 115	o/Kv:ˋ	([B[I[CI)Ljava/lang/String;
    //   194: invokevirtual 121	java/lang/String:intern	()Ljava/lang/String;
    //   197: invokevirtual 313	java/lang/StringBuilder:append	(Ljava/lang/String;)Ljava/lang/StringBuilder;
    //   200: invokevirtual 316	java/lang/StringBuilder:toString	()Ljava/lang/String;
    //   203: astore_2
    //   204: aload_0
    //   205: getfield 78	o/Kv:ॱˊ	Landroid/databinding/ViewDataBinding;
    //   208: checkcast 80	o/JD
    //   211: getfield 90	o/JD:ʻ	Lo/La;
    //   214: invokevirtual 96	o/La:ˏ	()Lo/Jc;
    //   217: invokevirtual 319	o/Jc:ʽ	()Ljava/lang/String;
    //   220: astore 4
    //   222: aload 4
    //   224: invokevirtual 179	java/lang/String:length	()I
    //   227: bipush 12
    //   229: if_icmpne +6 -> 235
    //   232: goto +9 -> 241
    //   235: goto -130 -> 105
    //   238: goto -204 -> 34
    //   241: iconst_0
    //   242: istore_1
    //   243: goto -240 -> 3
    //   246: iload_1
    //   247: tableswitch	default:+21->268, 0:+-137->110, 1:+-118->129
    //   268: goto -139 -> 129
    //   271: goto -33 -> 238
    //   274: iconst_0
    //   275: istore_1
    //   276: goto -30 -> 246
    //   279: new 308	java/lang/StringBuilder
    //   282: dup
    //   283: invokespecial 309	java/lang/StringBuilder:<init>	()V
    //   286: aload_2
    //   287: invokevirtual 313	java/lang/StringBuilder:append	(Ljava/lang/String;)Ljava/lang/StringBuilder;
    //   290: aload 4
    //   292: iconst_1
    //   293: aload 4
    //   295: invokevirtual 179	java/lang/String:length	()I
    //   298: invokevirtual 175	java/lang/String:substring	(II)Ljava/lang/String;
    //   301: invokevirtual 313	java/lang/StringBuilder:append	(Ljava/lang/String;)Ljava/lang/StringBuilder;
    //   304: invokevirtual 316	java/lang/StringBuilder:toString	()Ljava/lang/String;
    //   307: astore_2
    //   308: goto -274 -> 34
    //   311: getstatic 26	o/Kv:ˊˋ	I
    //   314: bipush 11
    //   316: iadd
    //   317: istore_1
    //   318: iload_1
    //   319: sipush 128
    //   322: irem
    //   323: putstatic 24	o/Kv:ˊˊ	I
    //   326: iload_1
    //   327: iconst_2
    //   328: irem
    //   329: ifeq +6 -> 335
    //   332: goto -61 -> 271
    //   335: goto -97 -> 238
    //   338: new 308	java/lang/StringBuilder
    //   341: dup
    //   342: invokespecial 309	java/lang/StringBuilder:<init>	()V
    //   345: aload_2
    //   346: invokevirtual 313	java/lang/StringBuilder:append	(Ljava/lang/String;)Ljava/lang/StringBuilder;
    //   349: aload 4
    //   351: invokevirtual 313	java/lang/StringBuilder:append	(Ljava/lang/String;)Ljava/lang/StringBuilder;
    //   354: invokevirtual 316	java/lang/StringBuilder:toString	()Ljava/lang/String;
    //   357: astore_2
    //   358: goto -47 -> 311
    //   361: iconst_1
    //   362: istore_1
    //   363: goto -117 -> 246
    //   366: getstatic 24	o/Kv:ˊˊ	I
    //   369: bipush 43
    //   371: iadd
    //   372: istore_1
    //   373: iload_1
    //   374: sipush 128
    //   377: irem
    //   378: putstatic 26	o/Kv:ˊˋ	I
    //   381: iload_1
    //   382: iconst_2
    //   383: irem
    //   384: ifne +6 -> 390
    //   387: goto -26 -> 361
    //   390: goto -116 -> 274
    // Local variable table:
    //   start	length	slot	name	signature
    //   0	393	0	this	Kv
    //   3	381	1	i	int
    //   31	36	2	localException1	Exception
    //   151	2	2	localException2	Exception
    //   203	155	2	str1	String
    //   67	109	3	str2	String
    //   59	291	4	str3	String
    // Exception table:
    //   from	to	target	type
    //   129	136	31	java/lang/Exception
    //   110	117	151	java/lang/Exception
  }
  
  public Resources getResources()
  {
    for (;;)
    {
      try
      {
        i = ˊˋ + 7;
        try
        {
          ˊˊ = i % 128;
          if (i % 2 != 0) {
            break;
          }
          return localResources1;
        }
        catch (Exception localException1)
        {
          Resources localResources1;
          throw localException1;
        }
        localResources1 = super.getResources();
        localResources1 = oH.ˊ(localResources1);
        continue;
        i = 0;
      }
      catch (Exception localException2)
      {
        throw localException2;
      }
      i = ˊˋ + 27;
      ˊˊ = i % 128;
      if (i % 2 != 0) {
        break label82;
      }
    }
    return localException2;
    label82:
    int i = 1;
    switch (i)
    {
    }
    Resources localResources2 = oH.ˊ(super.getResources());
    throw new NullPointerException();
  }
  
  public void onActivityResult(int paramInt1, int paramInt2, Intent paramIntent)
  {
    break label256;
    for (;;)
    {
      paramInt2 = 85;
      break label323;
      label219:
      do
      {
        paramInt2 = 60;
        break label323;
        paramIntent = paramIntent.getStringExtra(ˋ(new byte[] { -127, -116, -123, -118, -122, -117, -124, -125, -118, -119, -120, -121, -122, -123, -124, -125, -126, -127 }, null, null, 127).intern());
        ((JD)this.ॱˊ).ˎ(pQ.ˋ(paramIntent));
        break;
        switch (paramInt1)
        {
        case 6: 
        default: 
          break label259;
          switch (paramInt1)
          {
          default: 
            break label237;
            super.onActivityResult(paramInt1, paramInt2, paramIntent);
          }
          break;
        }
      } while (paramInt2 == -1);
    }
    for (;;)
    {
      label237:
      break label300;
      ॱ(0);
      continue;
      ॱ(-1);
      continue;
      label256:
      break label219;
      label259:
      continue;
      label262:
      break;
      ॱ(-1);
    }
    for (;;)
    {
      paramInt2 = ˊˊ + 11;
      ˊˋ = paramInt2 % 128;
      if (paramInt2 % 2 == 0) {
        break label262;
      }
      break;
      label300:
      paramInt1 = ˊˋ + 63;
      ˊˊ = paramInt1 % 128;
      if (paramInt1 % 2 != 0) {
        return;
      }
      return;
      label323:
      switch (paramInt2)
      {
      }
    }
  }
  
  public void onConfirmClicked(View paramView)
  {
    break label60;
    ॱˋ();
    int i = ˊˋ + 81;
    ˊˊ = i % 128;
    if (i % 2 != 0) {
      return;
    }
    return;
    label60:
    for (;;)
    {
      try
      {
        i = ˊˊ + 111;
        ˊˋ = i % 128;
        if (i % 2 == 0) {
          break;
        }
      }
      catch (Exception paramView)
      {
        throw paramView;
      }
    }
  }
  
  /* Error */
  public void onCreate(android.os.Bundle paramBundle)
  {
    // Byte code:
    //   0: goto +547 -> 547
    //   3: iconst_1
    //   4: istore_2
    //   5: goto +61 -> 66
    //   8: iload_2
    //   9: lookupswitch	default:+27->36, 18:+544->553, 84:+315->324
    //   36: goto +517 -> 553
    //   39: getstatic 24	o/Kv:ˊˊ	I
    //   42: bipush 29
    //   44: iadd
    //   45: istore_2
    //   46: iload_2
    //   47: sipush 128
    //   50: irem
    //   51: putstatic 26	o/Kv:ˊˋ	I
    //   54: iload_2
    //   55: iconst_2
    //   56: irem
    //   57: ifne +6 -> 63
    //   60: goto +543 -> 603
    //   63: goto +532 -> 595
    //   66: iload_2
    //   67: lookupswitch	default:+25->92, 1:+486->553, 20:+257->324
    //   92: goto +232 -> 324
    //   95: bipush 84
    //   97: istore_2
    //   98: goto -90 -> 8
    //   101: aload_0
    //   102: aload_1
    //   103: invokespecial 352	o/IB:onCreate	(Landroid/os/Bundle;)V
    //   106: aload_0
    //   107: iconst_0
    //   108: putfield 354	o/IB:ॱˋ	Z
    //   111: aload_0
    //   112: aload_0
    //   113: getfield 78	o/Kv:ॱˊ	Landroid/databinding/ViewDataBinding;
    //   116: checkcast 80	o/JD
    //   119: getfield 357	o/JD:ʽ	Lo/у;
    //   122: invokevirtual 360	o/Kv:ˊ	(Lo/у;)V
    //   125: goto +17 -> 142
    //   128: astore_1
    //   129: aload_1
    //   130: invokevirtual 158	java/lang/Throwable:getCause	()Ljava/lang/Throwable;
    //   133: astore_3
    //   134: aload_3
    //   135: ifnull +5 -> 140
    //   138: aload_3
    //   139: athrow
    //   140: aload_1
    //   141: athrow
    //   142: aload_0
    //   143: invokevirtual 231	android/content/Context:getApplicationInfo	()Landroid/content/pm/ApplicationInfo;
    //   146: getfield 236	android/content/pm/ApplicationInfo:targetSdkVersion	I
    //   149: bipush 21
    //   151: isub
    //   152: aload_0
    //   153: invokevirtual 231	android/content/Context:getApplicationInfo	()Landroid/content/pm/ApplicationInfo;
    //   156: getfield 236	android/content/pm/ApplicationInfo:targetSdkVersion	I
    //   159: sipush 388
    //   162: iadd
    //   163: aload_0
    //   164: invokevirtual 164	android/content/Context:getResources	()Landroid/content/res/Resources;
    //   167: ldc_w 361
    //   170: invokevirtual 171	android/content/res/Resources:getString	(I)Ljava/lang/String;
    //   173: iconst_0
    //   174: bipush 7
    //   176: invokevirtual 175	java/lang/String:substring	(II)Ljava/lang/String;
    //   179: iconst_2
    //   180: invokevirtual 186	java/lang/String:codePointAt	(I)I
    //   183: sipush 30242
    //   186: iadd
    //   187: i2c
    //   188: invokestatic 192	o/O:ˋ	(IIC)Ljava/lang/Object;
    //   191: checkcast 194	java/lang/Class
    //   194: ldc -30
    //   196: aconst_null
    //   197: invokevirtual 199	java/lang/Class:getMethod	(Ljava/lang/String;[Ljava/lang/Class;)Ljava/lang/reflect/Method;
    //   200: aconst_null
    //   201: aconst_null
    //   202: invokevirtual 207	java/lang/reflect/Method:invoke	(Ljava/lang/Object;[Ljava/lang/Object;)Ljava/lang/Object;
    //   205: astore_1
    //   206: goto +17 -> 223
    //   209: astore_1
    //   210: aload_1
    //   211: invokevirtual 158	java/lang/Throwable:getCause	()Ljava/lang/Throwable;
    //   214: astore_3
    //   215: aload_3
    //   216: ifnull +5 -> 221
    //   219: aload_3
    //   220: athrow
    //   221: aload_1
    //   222: athrow
    //   223: aload_0
    //   224: invokevirtual 182	android/content/Context:getPackageName	()Ljava/lang/String;
    //   227: iconst_3
    //   228: invokevirtual 186	java/lang/String:codePointAt	(I)I
    //   231: bipush 94
    //   233: isub
    //   234: aload_0
    //   235: invokevirtual 164	android/content/Context:getResources	()Landroid/content/res/Resources;
    //   238: ldc_w 362
    //   241: invokevirtual 171	android/content/res/Resources:getString	(I)Ljava/lang/String;
    //   244: iconst_0
    //   245: iconst_4
    //   246: invokevirtual 175	java/lang/String:substring	(II)Ljava/lang/String;
    //   249: invokevirtual 179	java/lang/String:length	()I
    //   252: sipush 409
    //   255: iadd
    //   256: aload_0
    //   257: invokevirtual 164	android/content/Context:getResources	()Landroid/content/res/Resources;
    //   260: ldc_w 363
    //   263: invokevirtual 171	android/content/res/Resources:getString	(I)Ljava/lang/String;
    //   266: iconst_0
    //   267: iconst_4
    //   268: invokevirtual 175	java/lang/String:substring	(II)Ljava/lang/String;
    //   271: iconst_1
    //   272: invokevirtual 186	java/lang/String:codePointAt	(I)I
    //   275: sipush 30227
    //   278: iadd
    //   279: i2c
    //   280: invokestatic 192	o/O:ˋ	(IIC)Ljava/lang/Object;
    //   283: checkcast 194	java/lang/Class
    //   286: ldc_w 365
    //   289: aconst_null
    //   290: invokevirtual 199	java/lang/Class:getMethod	(Ljava/lang/String;[Ljava/lang/Class;)Ljava/lang/reflect/Method;
    //   293: aload_1
    //   294: aconst_null
    //   295: invokevirtual 207	java/lang/reflect/Method:invoke	(Ljava/lang/Object;[Ljava/lang/Object;)Ljava/lang/Object;
    //   298: checkcast 367	o/Gw
    //   301: astore_1
    //   302: aload_1
    //   303: getstatic 371	o/Gw:ACTIVE_REGISTERED	Lo/Gw;
    //   306: invokevirtual 375	o/Gw:equals	(Ljava/lang/Object;)Z
    //   309: ifeq +6 -> 315
    //   312: goto -309 -> 3
    //   315: goto +274 -> 589
    //   318: bipush 18
    //   320: istore_2
    //   321: goto -313 -> 8
    //   324: aload_0
    //   325: invokespecial 377	o/Kv:ʻॱ	()V
    //   328: return
    //   329: iload_2
    //   330: tableswitch	default:+22->352, 0:+-229->101, 1:+22->352
    //   352: aload_0
    //   353: aload_1
    //   354: invokespecial 352	o/IB:onCreate	(Landroid/os/Bundle;)V
    //   357: aload_0
    //   358: iconst_0
    //   359: putfield 354	o/IB:ॱˋ	Z
    //   362: aload_0
    //   363: aload_0
    //   364: getfield 78	o/Kv:ॱˊ	Landroid/databinding/ViewDataBinding;
    //   367: checkcast 80	o/JD
    //   370: getfield 357	o/JD:ʽ	Lo/у;
    //   373: invokevirtual 360	o/Kv:ˊ	(Lo/у;)V
    //   376: goto +17 -> 393
    //   379: astore_1
    //   380: aload_1
    //   381: invokevirtual 158	java/lang/Throwable:getCause	()Ljava/lang/Throwable;
    //   384: astore_3
    //   385: aload_3
    //   386: ifnull +5 -> 391
    //   389: aload_3
    //   390: athrow
    //   391: aload_1
    //   392: athrow
    //   393: aload_0
    //   394: invokevirtual 182	android/content/Context:getPackageName	()Ljava/lang/String;
    //   397: invokevirtual 179	java/lang/String:length	()I
    //   400: bipush 7
    //   402: isub
    //   403: aload_0
    //   404: invokevirtual 164	android/content/Context:getResources	()Landroid/content/res/Resources;
    //   407: ldc_w 378
    //   410: invokevirtual 171	android/content/res/Resources:getString	(I)Ljava/lang/String;
    //   413: iconst_0
    //   414: bipush 10
    //   416: invokevirtual 175	java/lang/String:substring	(II)Ljava/lang/String;
    //   419: invokevirtual 179	java/lang/String:length	()I
    //   422: sipush 403
    //   425: iadd
    //   426: aload_0
    //   427: invokevirtual 182	android/content/Context:getPackageName	()Ljava/lang/String;
    //   430: invokevirtual 179	java/lang/String:length	()I
    //   433: sipush 30242
    //   436: iadd
    //   437: i2c
    //   438: invokestatic 192	o/O:ˋ	(IIC)Ljava/lang/Object;
    //   441: checkcast 194	java/lang/Class
    //   444: ldc -30
    //   446: aconst_null
    //   447: invokevirtual 199	java/lang/Class:getMethod	(Ljava/lang/String;[Ljava/lang/Class;)Ljava/lang/reflect/Method;
    //   450: aconst_null
    //   451: aconst_null
    //   452: invokevirtual 207	java/lang/reflect/Method:invoke	(Ljava/lang/Object;[Ljava/lang/Object;)Ljava/lang/Object;
    //   455: astore_1
    //   456: goto +17 -> 473
    //   459: astore_1
    //   460: aload_1
    //   461: invokevirtual 158	java/lang/Throwable:getCause	()Ljava/lang/Throwable;
    //   464: astore_3
    //   465: aload_3
    //   466: ifnull +5 -> 471
    //   469: aload_3
    //   470: athrow
    //   471: aload_1
    //   472: athrow
    //   473: aload_0
    //   474: invokevirtual 182	android/content/Context:getPackageName	()Ljava/lang/String;
    //   477: bipush 9
    //   479: invokevirtual 186	java/lang/String:codePointAt	(I)I
    //   482: bipush 93
    //   484: isub
    //   485: aload_0
    //   486: invokevirtual 231	android/content/Context:getApplicationInfo	()Landroid/content/pm/ApplicationInfo;
    //   489: getfield 236	android/content/pm/ApplicationInfo:targetSdkVersion	I
    //   492: sipush 388
    //   495: iadd
    //   496: aload_0
    //   497: invokevirtual 182	android/content/Context:getPackageName	()Ljava/lang/String;
    //   500: iconst_1
    //   501: invokevirtual 186	java/lang/String:codePointAt	(I)I
    //   504: sipush 30142
    //   507: iadd
    //   508: i2c
    //   509: invokestatic 192	o/O:ˋ	(IIC)Ljava/lang/Object;
    //   512: checkcast 194	java/lang/Class
    //   515: ldc_w 365
    //   518: aconst_null
    //   519: invokevirtual 199	java/lang/Class:getMethod	(Ljava/lang/String;[Ljava/lang/Class;)Ljava/lang/reflect/Method;
    //   522: aload_1
    //   523: aconst_null
    //   524: invokevirtual 207	java/lang/reflect/Method:invoke	(Ljava/lang/Object;[Ljava/lang/Object;)Ljava/lang/Object;
    //   527: checkcast 367	o/Gw
    //   530: astore_1
    //   531: aload_1
    //   532: getstatic 371	o/Gw:ACTIVE_REGISTERED	Lo/Gw;
    //   535: invokevirtual 375	o/Gw:equals	(Ljava/lang/Object;)Z
    //   538: ifeq +6 -> 544
    //   541: goto -223 -> 318
    //   544: goto -449 -> 95
    //   547: goto -508 -> 39
    //   550: goto -226 -> 324
    //   553: aload_0
    //   554: invokespecial 380	o/Kv:ʾ	()V
    //   557: getstatic 24	o/Kv:ˊˊ	I
    //   560: istore_2
    //   561: iload_2
    //   562: bipush 99
    //   564: iadd
    //   565: istore_2
    //   566: iload_2
    //   567: sipush 128
    //   570: irem
    //   571: putstatic 26	o/Kv:ˊˋ	I
    //   574: iload_2
    //   575: iconst_2
    //   576: irem
    //   577: ifne +6 -> 583
    //   580: goto +20 -> 600
    //   583: goto -33 -> 550
    //   586: astore_1
    //   587: aload_1
    //   588: athrow
    //   589: bipush 20
    //   591: istore_2
    //   592: goto -526 -> 66
    //   595: iconst_0
    //   596: istore_2
    //   597: goto -268 -> 329
    //   600: goto -50 -> 550
    //   603: iconst_1
    //   604: istore_2
    //   605: goto -276 -> 329
    // Local variable table:
    //   start	length	slot	name	signature
    //   0	608	0	this	Kv
    //   0	608	1	paramBundle	android.os.Bundle
    //   4	601	2	i	int
    //   133	337	3	localThrowable	Throwable
    // Exception table:
    //   from	to	target	type
    //   142	206	128	finally
    //   223	302	209	finally
    //   393	456	379	finally
    //   473	531	459	finally
    //   557	561	586	java/lang/Exception
    //   566	574	586	java/lang/Exception
  }
  
  /* Error */
  public void ˋ(ز paramز)
  {
    // Byte code:
    //   0: goto +53 -> 53
    //   3: getstatic 24	o/Kv:ˊˊ	I
    //   6: bipush 109
    //   8: iadd
    //   9: istore_2
    //   10: iload_2
    //   11: sipush 128
    //   14: irem
    //   15: putstatic 26	o/Kv:ˊˋ	I
    //   18: iload_2
    //   19: iconst_2
    //   20: irem
    //   21: ifne +4 -> 25
    //   24: return
    //   25: return
    //   26: getstatic 26	o/Kv:ˊˋ	I
    //   29: bipush 119
    //   31: iadd
    //   32: istore_2
    //   33: iload_2
    //   34: sipush 128
    //   37: irem
    //   38: putstatic 24	o/Kv:ˊˊ	I
    //   41: iload_2
    //   42: iconst_2
    //   43: irem
    //   44: ifeq +6 -> 50
    //   47: goto +12 -> 59
    //   50: goto +9 -> 59
    //   53: goto -27 -> 26
    //   56: astore_1
    //   57: aload_1
    //   58: athrow
    //   59: aload_0
    //   60: aload_1
    //   61: invokespecial 383	o/IB:ˋ	(Lo/ز;)V
    //   64: aload_1
    //   65: iconst_1
    //   66: invokevirtual 388	o/ز:ॱ	(Z)V
    //   69: aload_1
    //   70: iconst_1
    //   71: invokevirtual 390	o/ز:ˏ	(Z)V
    //   74: goto -71 -> 3
    // Local variable table:
    //   start	length	slot	name	signature
    //   0	77	0	this	Kv
    //   0	77	1	paramز	ز
    //   9	35	2	i	int
    // Exception table:
    //   from	to	target	type
    //   64	69	56	java/lang/Exception
    //   69	74	56	java/lang/Exception
  }
  
  /* Error */
  public int ˎ()
  {
    // Byte code:
    //   0: getstatic 24	o/Kv:ˊˊ	I
    //   3: bipush 83
    //   5: iadd
    //   6: istore_1
    //   7: iload_1
    //   8: sipush 128
    //   11: irem
    //   12: putstatic 26	o/Kv:ˊˋ	I
    //   15: iload_1
    //   16: iconst_2
    //   17: irem
    //   18: ifne +6 -> 24
    //   21: goto +6 -> 27
    //   24: goto +8 -> 32
    //   27: iconst_1
    //   28: istore_1
    //   29: goto +31 -> 60
    //   32: iconst_0
    //   33: istore_1
    //   34: goto +26 -> 60
    //   37: astore_3
    //   38: aload_3
    //   39: athrow
    //   40: astore_3
    //   41: aload_3
    //   42: athrow
    //   43: getstatic 395	o/Jy$ˊ:activity_client_identification	I
    //   46: istore_1
    //   47: bipush 70
    //   49: iconst_0
    //   50: idiv
    //   51: istore_2
    //   52: iload_1
    //   53: ireturn
    //   54: getstatic 395	o/Jy$ˊ:activity_client_identification	I
    //   57: istore_1
    //   58: iload_1
    //   59: ireturn
    //   60: iload_1
    //   61: tableswitch	default:+23->84, 0:+-7->54, 1:+-18->43
    //   84: goto -30 -> 54
    // Local variable table:
    //   start	length	slot	name	signature
    //   0	87	0	this	Kv
    //   6	55	1	i	int
    //   51	1	2	j	int
    //   37	2	3	localException1	Exception
    //   40	2	3	localException2	Exception
    // Exception table:
    //   from	to	target	type
    //   43	47	37	java/lang/Exception
    //   54	58	40	java/lang/Exception
  }
  
  /* Error */
  @zA(ˎ=org.greenrobot.eventbus.ThreadMode.MAIN)
  public void ˎ(DZ paramDZ)
  {
    // Byte code:
    //   0: goto +58 -> 58
    //   3: aload_0
    //   4: getfield 78	o/Kv:ॱˊ	Landroid/databinding/ViewDataBinding;
    //   7: astore_1
    //   8: aload_1
    //   9: checkcast 80	o/JD
    //   12: getfield 84	o/JD:ॱ	Lo/Jh;
    //   15: invokevirtual 401	o/Jh:ˊ	()V
    //   18: goto +43 -> 61
    //   21: astore_1
    //   22: aload_1
    //   23: athrow
    //   24: getstatic 24	o/Kv:ˊˊ	I
    //   27: bipush 77
    //   29: iadd
    //   30: istore_2
    //   31: iload_2
    //   32: sipush 128
    //   35: irem
    //   36: putstatic 26	o/Kv:ˊˋ	I
    //   39: iload_2
    //   40: iconst_2
    //   41: irem
    //   42: ifne +6 -> 48
    //   45: goto +10 -> 55
    //   48: goto -45 -> 3
    //   51: astore_1
    //   52: aload_1
    //   53: athrow
    //   54: return
    //   55: goto -52 -> 3
    //   58: goto -34 -> 24
    //   61: getstatic 24	o/Kv:ˊˊ	I
    //   64: istore_2
    //   65: iload_2
    //   66: bipush 117
    //   68: iadd
    //   69: istore_2
    //   70: iload_2
    //   71: sipush 128
    //   74: irem
    //   75: putstatic 26	o/Kv:ˊˋ	I
    //   78: iload_2
    //   79: iconst_2
    //   80: irem
    //   81: ifne +6 -> 87
    //   84: goto -30 -> 54
    //   87: return
    // Local variable table:
    //   start	length	slot	name	signature
    //   0	88	0	this	Kv
    //   0	88	1	paramDZ	DZ
    //   30	51	2	i	int
    // Exception table:
    //   from	to	target	type
    //   31	39	21	java/lang/Exception
    //   70	78	21	java/lang/Exception
    //   3	8	51	java/lang/Exception
    //   24	31	51	java/lang/Exception
    //   31	39	51	java/lang/Exception
    //   61	65	51	java/lang/Exception
  }
}
