package o;

import android.content.Context;
import android.util.AttributeSet;
import com.insidesecure.hce.MatrixHCECard;

public class KX
  extends au<JS>
{
  private static long ˊ = -9191144121583462076L;
  private static int ˎ;
  private static int ˏ = 0;
  
  static
  {
    ˎ = 1;
  }
  
  public KX(Context paramContext)
  {
    super(paramContext);
  }
  
  public KX(Context paramContext, AttributeSet paramAttributeSet)
  {
    super(paramContext, paramAttributeSet);
  }
  
  public KX(Context paramContext, AttributeSet paramAttributeSet, int paramInt) {}
  
  /* Error */
  private static String ˋ(char[] paramArrayOfChar)
  {
    // Byte code:
    //   0: goto +77 -> 77
    //   3: iconst_0
    //   4: istore_2
    //   5: goto +149 -> 154
    //   8: iconst_1
    //   9: istore_2
    //   10: goto +144 -> 154
    //   13: getstatic 18	o/KX:ˎ	I
    //   16: bipush 103
    //   18: iadd
    //   19: istore_1
    //   20: iload_1
    //   21: sipush 128
    //   24: irem
    //   25: putstatic 16	o/KX:ˏ	I
    //   28: iload_1
    //   29: iconst_2
    //   30: irem
    //   31: ifeq +6 -> 37
    //   34: goto +101 -> 135
    //   37: goto +104 -> 141
    //   40: aload_0
    //   41: iload_1
    //   42: aload_0
    //   43: iload_1
    //   44: caload
    //   45: aload_0
    //   46: iload_1
    //   47: iconst_4
    //   48: irem
    //   49: caload
    //   50: ixor
    //   51: i2l
    //   52: iload_1
    //   53: iconst_4
    //   54: isub
    //   55: i2l
    //   56: getstatic 22	o/KX:ˊ	J
    //   59: lmul
    //   60: lxor
    //   61: l2i
    //   62: i2c
    //   63: castore
    //   64: iload_1
    //   65: iconst_1
    //   66: iadd
    //   67: istore_1
    //   68: goto +41 -> 109
    //   71: astore_0
    //   72: aload_0
    //   73: athrow
    //   74: goto -34 -> 40
    //   77: goto -64 -> 13
    //   80: getstatic 16	o/KX:ˏ	I
    //   83: istore_2
    //   84: iload_2
    //   85: bipush 93
    //   87: iadd
    //   88: istore_2
    //   89: iload_2
    //   90: sipush 128
    //   93: irem
    //   94: putstatic 18	o/KX:ˎ	I
    //   97: iload_2
    //   98: iconst_2
    //   99: irem
    //   100: ifne +6 -> 106
    //   103: goto -29 -> 74
    //   106: goto -66 -> 40
    //   109: iload_1
    //   110: aload_0
    //   111: arraylength
    //   112: if_icmpge +6 -> 118
    //   115: goto -107 -> 8
    //   118: goto -115 -> 3
    //   121: new 39	java/lang/String
    //   124: dup
    //   125: aload_0
    //   126: iconst_4
    //   127: aload_0
    //   128: arraylength
    //   129: iconst_4
    //   130: isub
    //   131: invokespecial 42	java/lang/String:<init>	([CII)V
    //   134: areturn
    //   135: goto +6 -> 141
    //   138: astore_0
    //   139: aload_0
    //   140: athrow
    //   141: getstatic 22	o/KX:ˊ	J
    //   144: aload_0
    //   145: invokestatic 47	o/oL:ˋ	(J[C)[C
    //   148: astore_0
    //   149: iconst_4
    //   150: istore_1
    //   151: goto -42 -> 109
    //   154: iload_2
    //   155: tableswitch	default:+21->176, 0:+-34->121, 1:+-75->80
    //   176: goto -55 -> 121
    // Local variable table:
    //   start	length	slot	name	signature
    //   0	179	0	paramArrayOfChar	char[]
    //   19	132	1	i	int
    //   4	151	2	j	int
    // Exception table:
    //   from	to	target	type
    //   89	97	71	java/lang/Exception
    //   80	84	138	java/lang/Exception
  }
  
  /* Error */
  private boolean ˏ()
  {
    // Byte code:
    //   0: goto +265 -> 265
    //   3: aload_3
    //   4: astore 4
    //   6: aload_3
    //   7: astore 6
    //   9: iload_1
    //   10: tableswitch	default:+22->32, 0:+150->160, 1:+33->43
    //   32: aload_3
    //   33: astore 4
    //   35: goto +8 -> 43
    //   38: iconst_0
    //   39: istore_1
    //   40: goto -37 -> 3
    //   43: aload 4
    //   45: invokeinterface 53 1 0
    //   50: ireturn
    //   51: getstatic 59	o/Gv:ॱ	Lo/Gv;
    //   54: invokevirtual 63	o/Gv:ˊॱ$3bf17111	()Lo/GD;
    //   57: astore 5
    //   59: aload_0
    //   60: getfield 66	o/KX:ˋ	Landroid/databinding/ViewDataBinding;
    //   63: checkcast 68	o/JS
    //   66: invokevirtual 72	o/JS:ˏॱ	()Lo/HQ;
    //   69: invokevirtual 77	o/HQ:ˎ	()Lcom/insidesecure/hce/MatrixHCECard;
    //   72: astore_3
    //   73: goto +20 -> 93
    //   76: astore_3
    //   77: aload_3
    //   78: invokevirtual 83	java/lang/Throwable:getCause	()Ljava/lang/Throwable;
    //   81: astore 4
    //   83: aload 4
    //   85: ifnull +6 -> 91
    //   88: aload 4
    //   90: athrow
    //   91: aload_3
    //   92: athrow
    //   93: iconst_4
    //   94: sipush 164
    //   97: iconst_0
    //   98: invokestatic 88	o/O:ˋ	(IIC)Ljava/lang/Object;
    //   101: checkcast 90	java/lang/Class
    //   104: ldc 92
    //   106: aconst_null
    //   107: invokevirtual 96	java/lang/Class:getMethod	(Ljava/lang/String;[Ljava/lang/Class;)Ljava/lang/reflect/Method;
    //   110: aload 5
    //   112: aconst_null
    //   113: invokevirtual 102	java/lang/reflect/Method:invoke	(Ljava/lang/Object;[Ljava/lang/Object;)Ljava/lang/Object;
    //   116: astore 4
    //   118: iconst_2
    //   119: iconst_0
    //   120: idiv
    //   121: istore_1
    //   122: aload 4
    //   124: ifnull +6 -> 130
    //   127: goto -89 -> 38
    //   130: goto +138 -> 268
    //   133: getstatic 16	o/KX:ˏ	I
    //   136: bipush 39
    //   138: iadd
    //   139: istore_1
    //   140: iload_1
    //   141: sipush 128
    //   144: irem
    //   145: putstatic 18	o/KX:ˎ	I
    //   148: iload_1
    //   149: iconst_2
    //   150: irem
    //   151: ifne +6 -> 157
    //   154: goto +105 -> 259
    //   157: goto +70 -> 227
    //   160: goto +20 -> 180
    //   163: astore_3
    //   164: aload_3
    //   165: invokevirtual 83	java/lang/Throwable:getCause	()Ljava/lang/Throwable;
    //   168: astore 4
    //   170: aload 4
    //   172: ifnull +6 -> 178
    //   175: aload 4
    //   177: athrow
    //   178: aload_3
    //   179: athrow
    //   180: iconst_4
    //   181: sipush 164
    //   184: iconst_0
    //   185: invokestatic 88	o/O:ˋ	(IIC)Ljava/lang/Object;
    //   188: checkcast 90	java/lang/Class
    //   191: ldc 104
    //   193: aconst_null
    //   194: invokevirtual 96	java/lang/Class:getMethod	(Ljava/lang/String;[Ljava/lang/Class;)Ljava/lang/reflect/Method;
    //   197: aload 5
    //   199: aconst_null
    //   200: invokevirtual 102	java/lang/reflect/Method:invoke	(Ljava/lang/Object;[Ljava/lang/Object;)Ljava/lang/Object;
    //   203: checkcast 50	com/insidesecure/hce/MatrixHCECard
    //   206: astore_3
    //   207: aload 6
    //   209: invokeinterface 108 1 0
    //   214: aload_3
    //   215: invokeinterface 108 1 0
    //   220: invokevirtual 112	java/lang/String:equals	(Ljava/lang/Object;)Z
    //   223: istore_2
    //   224: goto +130 -> 354
    //   227: iconst_0
    //   228: istore_1
    //   229: iload_1
    //   230: lookupswitch	default:+26->256, 0:+43->273, 23:+-179->51
    //   256: goto +17 -> 273
    //   259: bipush 23
    //   261: istore_1
    //   262: goto -33 -> 229
    //   265: goto -132 -> 133
    //   268: iconst_1
    //   269: istore_1
    //   270: goto -267 -> 3
    //   273: getstatic 59	o/Gv:ॱ	Lo/Gv;
    //   276: invokevirtual 63	o/Gv:ˊॱ$3bf17111	()Lo/GD;
    //   279: astore 5
    //   281: aload_0
    //   282: getfield 66	o/KX:ˋ	Landroid/databinding/ViewDataBinding;
    //   285: checkcast 68	o/JS
    //   288: invokevirtual 72	o/JS:ˏॱ	()Lo/HQ;
    //   291: invokevirtual 77	o/HQ:ˎ	()Lcom/insidesecure/hce/MatrixHCECard;
    //   294: astore 4
    //   296: goto +20 -> 316
    //   299: astore_3
    //   300: aload_3
    //   301: invokevirtual 83	java/lang/Throwable:getCause	()Ljava/lang/Throwable;
    //   304: astore 4
    //   306: aload 4
    //   308: ifnull +6 -> 314
    //   311: aload 4
    //   313: athrow
    //   314: aload_3
    //   315: athrow
    //   316: iconst_4
    //   317: sipush 164
    //   320: iconst_0
    //   321: invokestatic 88	o/O:ˋ	(IIC)Ljava/lang/Object;
    //   324: checkcast 90	java/lang/Class
    //   327: ldc 92
    //   329: aconst_null
    //   330: invokevirtual 96	java/lang/Class:getMethod	(Ljava/lang/String;[Ljava/lang/Class;)Ljava/lang/reflect/Method;
    //   333: aload 5
    //   335: aconst_null
    //   336: invokevirtual 102	java/lang/reflect/Method:invoke	(Ljava/lang/Object;[Ljava/lang/Object;)Ljava/lang/Object;
    //   339: astore_3
    //   340: aload_3
    //   341: ifnull +10 -> 351
    //   344: aload 4
    //   346: astore 6
    //   348: goto -188 -> 160
    //   351: goto -308 -> 43
    //   354: getstatic 16	o/KX:ˏ	I
    //   357: bipush 103
    //   359: iadd
    //   360: istore_1
    //   361: iload_1
    //   362: sipush 128
    //   365: irem
    //   366: putstatic 18	o/KX:ˎ	I
    //   369: iload_1
    //   370: iconst_2
    //   371: irem
    //   372: ifne +5 -> 377
    //   375: iload_2
    //   376: ireturn
    //   377: iload_2
    //   378: ireturn
    // Local variable table:
    //   start	length	slot	name	signature
    //   0	379	0	this	KX
    //   9	363	1	i	int
    //   223	155	2	bool	boolean
    //   3	70	3	localMatrixHCECard1	MatrixHCECard
    //   76	16	3	localObject1	Object
    //   163	16	3	localObject2	Object
    //   206	9	3	localMatrixHCECard2	MatrixHCECard
    //   299	16	3	localObject3	Object
    //   339	2	3	localObject4	Object
    //   4	341	4	localObject5	Object
    //   57	277	5	localGD	GD
    //   7	340	6	localObject6	Object
    // Exception table:
    //   from	to	target	type
    //   93	118	76	finally
    //   180	207	163	finally
    //   316	340	299	finally
  }
  
  private void ॱ(boolean paramBoolean)
  {
    for (;;)
    {
      int i = ˏ + 41;
      ˎ = i % 128;
      if (i % 2 != 0)
      {
        return;
        do
        {
          break;
          i = ˏ + 23;
          ˎ = i % 128;
        } while (i % 2 == 0);
      }
      else
      {
        return;
      }
      ((JS)this.ˋ).ˏ(paramBoolean);
    }
  }
  
  public final void setEnrolledCard(MatrixHCECard paramMatrixHCECard)
  {
    break label6;
    break label9;
    label6:
    break label13;
    label9:
    return;
    label13:
    int i;
    for (;;)
    {
      break;
      i = ˏ + 65;
      ˎ = i % 128;
      if (i % 2 != 0) {
        break;
      }
    }
    for (;;)
    {
      i = ˏ + 13;
      ˎ = i % 128;
      if (i % 2 != 0) {
        break;
      }
      break;
      if (paramMatrixHCECard == null) {
        return;
      }
      ((JS)this.ˋ).ॱ(HQ.ˏ(paramMatrixHCECard));
      ((JS)this.ˋ).ˏ(new ˊ());
      ॱ(ˏ());
    }
  }
  
  /* Error */
  public String toString()
  {
    // Byte code:
    //   0: goto +254 -> 254
    //   3: astore_2
    //   4: aload_2
    //   5: athrow
    //   6: new 136	java/lang/StringBuilder
    //   9: dup
    //   10: invokespecial 138	java/lang/StringBuilder:<init>	()V
    //   13: astore_2
    //   14: bipush 22
    //   16: newarray char
    //   18: dup
    //   19: iconst_0
    //   20: ldc -117
    //   22: castore
    //   23: dup
    //   24: iconst_1
    //   25: ldc -116
    //   27: castore
    //   28: dup
    //   29: iconst_2
    //   30: ldc -115
    //   32: castore
    //   33: dup
    //   34: iconst_3
    //   35: ldc -114
    //   37: castore
    //   38: dup
    //   39: iconst_4
    //   40: ldc -113
    //   42: castore
    //   43: dup
    //   44: iconst_5
    //   45: ldc -112
    //   47: castore
    //   48: dup
    //   49: bipush 6
    //   51: ldc -111
    //   53: castore
    //   54: dup
    //   55: bipush 7
    //   57: ldc -110
    //   59: castore
    //   60: dup
    //   61: bipush 8
    //   63: ldc -109
    //   65: castore
    //   66: dup
    //   67: bipush 9
    //   69: ldc -108
    //   71: castore
    //   72: dup
    //   73: bipush 10
    //   75: ldc -107
    //   77: castore
    //   78: dup
    //   79: bipush 11
    //   81: ldc -106
    //   83: castore
    //   84: dup
    //   85: bipush 12
    //   87: ldc -105
    //   89: castore
    //   90: dup
    //   91: bipush 13
    //   93: ldc -104
    //   95: castore
    //   96: dup
    //   97: bipush 14
    //   99: ldc -103
    //   101: castore
    //   102: dup
    //   103: bipush 15
    //   105: ldc -102
    //   107: castore
    //   108: dup
    //   109: bipush 16
    //   111: ldc -101
    //   113: castore
    //   114: dup
    //   115: bipush 17
    //   117: ldc -100
    //   119: castore
    //   120: dup
    //   121: bipush 18
    //   123: ldc -99
    //   125: castore
    //   126: dup
    //   127: bipush 19
    //   129: ldc -98
    //   131: castore
    //   132: dup
    //   133: bipush 20
    //   135: ldc -97
    //   137: castore
    //   138: dup
    //   139: bipush 21
    //   141: ldc -96
    //   143: castore
    //   144: invokestatic 162	o/KX:ˋ	([C)Ljava/lang/String;
    //   147: astore_3
    //   148: aload_3
    //   149: invokevirtual 165	java/lang/String:intern	()Ljava/lang/String;
    //   152: astore_3
    //   153: aload_2
    //   154: aload_3
    //   155: invokevirtual 169	java/lang/StringBuilder:append	(Ljava/lang/String;)Ljava/lang/StringBuilder;
    //   158: astore_2
    //   159: aload_2
    //   160: aload_0
    //   161: getfield 66	o/KX:ˋ	Landroid/databinding/ViewDataBinding;
    //   164: checkcast 68	o/JS
    //   167: getfield 172	o/JS:ˎ	Landroid/widget/TextView;
    //   170: invokevirtual 178	android/widget/TextView:getText	()Ljava/lang/CharSequence;
    //   173: invokevirtual 181	java/lang/StringBuilder:append	(Ljava/lang/Object;)Ljava/lang/StringBuilder;
    //   176: bipush 6
    //   178: newarray char
    //   180: dup
    //   181: iconst_0
    //   182: ldc -74
    //   184: castore
    //   185: dup
    //   186: iconst_1
    //   187: ldc -73
    //   189: castore
    //   190: dup
    //   191: iconst_2
    //   192: ldc -72
    //   194: castore
    //   195: dup
    //   196: iconst_3
    //   197: ldc -71
    //   199: castore
    //   200: dup
    //   201: iconst_4
    //   202: ldc -70
    //   204: castore
    //   205: dup
    //   206: iconst_5
    //   207: ldc -69
    //   209: castore
    //   210: invokestatic 162	o/KX:ˋ	([C)Ljava/lang/String;
    //   213: invokevirtual 165	java/lang/String:intern	()Ljava/lang/String;
    //   216: invokevirtual 169	java/lang/StringBuilder:append	(Ljava/lang/String;)Ljava/lang/StringBuilder;
    //   219: invokevirtual 189	java/lang/StringBuilder:toString	()Ljava/lang/String;
    //   222: astore_2
    //   223: goto +3 -> 226
    //   226: getstatic 16	o/KX:ˏ	I
    //   229: bipush 97
    //   231: iadd
    //   232: istore_1
    //   233: iload_1
    //   234: sipush 128
    //   237: irem
    //   238: putstatic 18	o/KX:ˎ	I
    //   241: iload_1
    //   242: iconst_2
    //   243: irem
    //   244: ifne +5 -> 249
    //   247: aload_2
    //   248: areturn
    //   249: aload_2
    //   250: areturn
    //   251: astore_2
    //   252: aload_2
    //   253: athrow
    //   254: goto -248 -> 6
    // Local variable table:
    //   start	length	slot	name	signature
    //   0	257	0	this	KX
    //   232	12	1	i	int
    //   3	2	2	localException1	Exception
    //   13	237	2	localObject	Object
    //   251	2	2	localException2	Exception
    //   147	8	3	str	String
    // Exception table:
    //   from	to	target	type
    //   14	148	3	java/lang/Exception
    //   14	148	251	java/lang/Exception
    //   148	153	251	java/lang/Exception
    //   153	159	251	java/lang/Exception
    //   159	223	251	java/lang/Exception
  }
  
  public int ˎ()
  {
    break label69;
    int i = 23 / 0;
    int j;
    return j;
    for (;;)
    {
      switch (i)
      {
      case 1: 
      default: 
        break;
        i = 1;
        break;
      case 0: 
        label69:
        for (;;)
        {
          i = ˎ + 55;
          ˏ = i % 128;
          if (i % 2 != 0) {
            break;
          }
          break;
          return j;
        }
        for (;;)
        {
          i = ˎ + 83;
          ˏ = i % 128;
          if (i % 2 != 0) {
            break;
          }
          break label106;
          j = Jy.ˊ.view_enrolled_card;
        }
        label106:
        i = 0;
      }
    }
  }
  
  /* Error */
  public MatrixHCECard ॱ()
  {
    // Byte code:
    //   0: goto +61 -> 61
    //   3: iload_1
    //   4: lookupswitch	default:+28->32, 15:+28->32, 19:+63->67
    //   32: aload_2
    //   33: areturn
    //   34: getstatic 16	o/KX:ˏ	I
    //   37: bipush 101
    //   39: iadd
    //   40: istore_1
    //   41: iload_1
    //   42: sipush 128
    //   45: irem
    //   46: putstatic 18	o/KX:ˎ	I
    //   49: iload_1
    //   50: iconst_2
    //   51: irem
    //   52: ifne +6 -> 58
    //   55: goto +40 -> 95
    //   58: goto +16 -> 74
    //   61: goto -27 -> 34
    //   64: astore_2
    //   65: aload_2
    //   66: athrow
    //   67: bipush 54
    //   69: iconst_0
    //   70: idiv
    //   71: istore_1
    //   72: aload_2
    //   73: areturn
    //   74: aload_0
    //   75: getfield 66	o/KX:ˋ	Landroid/databinding/ViewDataBinding;
    //   78: astore_2
    //   79: aload_2
    //   80: checkcast 68	o/JS
    //   83: astore_2
    //   84: aload_2
    //   85: invokevirtual 72	o/JS:ˏॱ	()Lo/HQ;
    //   88: invokevirtual 77	o/HQ:ˎ	()Lcom/insidesecure/hce/MatrixHCECard;
    //   91: astore_2
    //   92: goto +15 -> 107
    //   95: goto -21 -> 74
    //   98: bipush 15
    //   100: istore_1
    //   101: goto -98 -> 3
    //   104: astore_2
    //   105: aload_2
    //   106: athrow
    //   107: getstatic 16	o/KX:ˏ	I
    //   110: istore_1
    //   111: iload_1
    //   112: iconst_1
    //   113: iadd
    //   114: istore_1
    //   115: iload_1
    //   116: sipush 128
    //   119: irem
    //   120: putstatic 18	o/KX:ˎ	I
    //   123: iload_1
    //   124: iconst_2
    //   125: irem
    //   126: ifne +6 -> 132
    //   129: goto +6 -> 135
    //   132: goto -34 -> 98
    //   135: bipush 19
    //   137: istore_1
    //   138: goto -135 -> 3
    // Local variable table:
    //   start	length	slot	name	signature
    //   0	141	0	this	KX
    //   3	135	1	i	int
    //   32	1	2	localMatrixHCECard	MatrixHCECard
    //   64	9	2	localException1	Exception
    //   78	14	2	localObject	Object
    //   104	2	2	localException2	Exception
    // Exception table:
    //   from	to	target	type
    //   74	79	64	java/lang/Exception
    //   79	84	64	java/lang/Exception
    //   84	92	64	java/lang/Exception
    //   84	92	104	java/lang/Exception
    //   107	111	104	java/lang/Exception
    //   115	123	104	java/lang/Exception
  }
  
  public class ˊ
  {
    private static int ˊ;
    private static char ˋ;
    private static long ˎ;
    private static byte ॱ;
    private static int ॱॱ;
    private static int ᐝ;
    
    static
    {
      try
      {
        int i = ᐝ;
        i += 81;
        ॱॱ = i % 128;
        if (i % 2 != 0) {
          break label59;
        }
        for (;;)
        {
          throw new NullPointerException();
          ᐝ = 0;
          ॱॱ = 1;
          ˋ();
          ॱ = -102;
          break;
          label59:
          i = 8;
          break label68;
          i = 94;
          label68:
          switch (i)
          {
          }
        }
        return;
      }
      catch (Exception localException)
      {
        throw localException;
      }
    }
    
    public ˊ() {}
    
    static void ˋ()
    {
      ˋ = 60855;
      ˎ = 0L;
      ˊ = 0;
    }
    
    /* Error */
    private String ˏ(String paramString)
    {
      // Byte code:
      //   0: goto +212 -> 212
      //   3: aload 4
      //   5: iload_2
      //   6: aload_1
      //   7: aload_1
      //   8: arraylength
      //   9: iload_2
      //   10: ishl
      //   11: iconst_0
      //   12: idiv
      //   13: baload
      //   14: getstatic 35	o/KX$ˊ:ॱ	B
      //   17: ior
      //   18: i2b
      //   19: bastore
      //   20: iload_2
      //   21: bipush 79
      //   23: iadd
      //   24: istore_2
      //   25: goto +318 -> 343
      //   28: goto +187 -> 215
      //   31: iload_3
      //   32: tableswitch	default:+24->56, 0:+359->391, 1:+56->88
      //   56: goto +32 -> 88
      //   59: iload_3
      //   60: istore_2
      //   61: goto +282 -> 343
      //   64: aload 4
      //   66: iload_2
      //   67: aload_1
      //   68: aload_1
      //   69: arraylength
      //   70: iload_2
      //   71: isub
      //   72: iconst_1
      //   73: isub
      //   74: baload
      //   75: getstatic 35	o/KX$ˊ:ॱ	B
      //   78: ixor
      //   79: i2b
      //   80: bastore
      //   81: iload_2
      //   82: iconst_1
      //   83: iadd
      //   84: istore_2
      //   85: goto +258 -> 343
      //   88: new 52	java/lang/String
      //   91: dup
      //   92: aload 4
      //   94: iconst_4
      //   95: newarray char
      //   97: dup
      //   98: iconst_0
      //   99: ldc 53
      //   101: castore
      //   102: dup
      //   103: iconst_1
      //   104: ldc 54
      //   106: castore
      //   107: dup
      //   108: iconst_2
      //   109: ldc 55
      //   111: castore
      //   112: dup
      //   113: iconst_3
      //   114: ldc 56
      //   116: castore
      //   117: sipush 6516
      //   120: iconst_5
      //   121: newarray char
      //   123: dup
      //   124: iconst_0
      //   125: ldc 57
      //   127: castore
      //   128: dup
      //   129: iconst_1
      //   130: ldc 58
      //   132: castore
      //   133: dup
      //   134: iconst_2
      //   135: ldc 59
      //   137: castore
      //   138: dup
      //   139: iconst_3
      //   140: ldc 60
      //   142: castore
      //   143: dup
      //   144: iconst_4
      //   145: ldc 61
      //   147: castore
      //   148: ldc 62
      //   150: iconst_4
      //   151: newarray char
      //   153: dup
      //   154: iconst_0
      //   155: ldc 63
      //   157: castore
      //   158: dup
      //   159: iconst_1
      //   160: ldc 63
      //   162: castore
      //   163: dup
      //   164: iconst_2
      //   165: ldc 63
      //   167: castore
      //   168: dup
      //   169: iconst_3
      //   170: ldc 63
      //   172: castore
      //   173: invokestatic 66	o/KX$ˊ:ॱ	([CC[CI[C)Ljava/lang/String;
      //   176: invokevirtual 70	java/lang/String:intern	()Ljava/lang/String;
      //   179: invokespecial 73	java/lang/String:<init>	([BLjava/lang/String;)V
      //   182: astore_1
      //   183: aload_1
      //   184: areturn
      //   185: getstatic 24	o/KX$ˊ:ᐝ	I
      //   188: bipush 95
      //   190: iadd
      //   191: istore_2
      //   192: iload_2
      //   193: sipush 128
      //   196: irem
      //   197: putstatic 26	o/KX$ˊ:ॱॱ	I
      //   200: iload_2
      //   201: iconst_2
      //   202: irem
      //   203: ifne +6 -> 209
      //   206: goto -178 -> 28
      //   209: goto +6 -> 215
      //   212: goto -27 -> 185
      //   215: aload_1
      //   216: iconst_4
      //   217: newarray char
      //   219: dup
      //   220: iconst_0
      //   221: ldc 74
      //   223: castore
      //   224: dup
      //   225: iconst_1
      //   226: ldc 75
      //   228: castore
      //   229: dup
      //   230: iconst_2
      //   231: ldc 76
      //   233: castore
      //   234: dup
      //   235: iconst_3
      //   236: ldc 77
      //   238: castore
      //   239: iconst_0
      //   240: bipush 10
      //   242: newarray char
      //   244: dup
      //   245: iconst_0
      //   246: ldc 78
      //   248: castore
      //   249: dup
      //   250: iconst_1
      //   251: ldc 79
      //   253: castore
      //   254: dup
      //   255: iconst_2
      //   256: ldc 80
      //   258: castore
      //   259: dup
      //   260: iconst_3
      //   261: ldc 81
      //   263: castore
      //   264: dup
      //   265: iconst_4
      //   266: ldc 82
      //   268: castore
      //   269: dup
      //   270: iconst_5
      //   271: ldc 83
      //   273: castore
      //   274: dup
      //   275: bipush 6
      //   277: ldc 84
      //   279: castore
      //   280: dup
      //   281: bipush 7
      //   283: ldc 85
      //   285: castore
      //   286: dup
      //   287: bipush 8
      //   289: ldc 86
      //   291: castore
      //   292: dup
      //   293: bipush 9
      //   295: ldc 87
      //   297: castore
      //   298: iconst_0
      //   299: iconst_4
      //   300: newarray char
      //   302: dup
      //   303: iconst_0
      //   304: ldc 63
      //   306: castore
      //   307: dup
      //   308: iconst_1
      //   309: ldc 63
      //   311: castore
      //   312: dup
      //   313: iconst_2
      //   314: ldc 63
      //   316: castore
      //   317: dup
      //   318: iconst_3
      //   319: ldc 63
      //   321: castore
      //   322: invokestatic 66	o/KX$ˊ:ॱ	([CC[CI[C)Ljava/lang/String;
      //   325: invokevirtual 70	java/lang/String:intern	()Ljava/lang/String;
      //   328: invokevirtual 91	java/lang/String:getBytes	(Ljava/lang/String;)[B
      //   331: astore_1
      //   332: aload_1
      //   333: arraylength
      //   334: newarray byte
      //   336: astore 4
      //   338: iconst_0
      //   339: istore_3
      //   340: goto +78 -> 418
      //   343: aload_1
      //   344: arraylength
      //   345: istore_3
      //   346: iload_2
      //   347: iload_3
      //   348: if_icmpge +6 -> 354
      //   351: goto +8 -> 359
      //   354: iconst_1
      //   355: istore_3
      //   356: goto -325 -> 31
      //   359: iconst_0
      //   360: istore_3
      //   361: goto -330 -> 31
      //   364: iconst_0
      //   365: istore_2
      //   366: iload_2
      //   367: tableswitch	default:+21->388, 0:+78->445, 1:+-308->59
      //   388: goto -329 -> 59
      //   391: getstatic 24	o/KX$ˊ:ᐝ	I
      //   394: bipush 27
      //   396: iadd
      //   397: istore_3
      //   398: iload_3
      //   399: sipush 128
      //   402: irem
      //   403: putstatic 26	o/KX$ˊ:ॱॱ	I
      //   406: iload_3
      //   407: iconst_2
      //   408: irem
      //   409: ifne +6 -> 415
      //   412: goto -409 -> 3
      //   415: goto -351 -> 64
      //   418: getstatic 26	o/KX$ˊ:ॱॱ	I
      //   421: bipush 31
      //   423: iadd
      //   424: istore_2
      //   425: iload_2
      //   426: sipush 128
      //   429: irem
      //   430: putstatic 24	o/KX$ˊ:ᐝ	I
      //   433: iload_2
      //   434: iconst_2
      //   435: irem
      //   436: ifeq +6 -> 442
      //   439: goto -75 -> 364
      //   442: goto +8 -> 450
      //   445: iload_3
      //   446: istore_2
      //   447: goto -104 -> 343
      //   450: iconst_1
      //   451: istore_2
      //   452: goto -86 -> 366
      //   455: astore_1
      //   456: new 93	java/lang/RuntimeException
      //   459: dup
      //   460: aload_1
      //   461: invokespecial 96	java/lang/RuntimeException:<init>	(Ljava/lang/Throwable;)V
      //   464: athrow
      // Local variable table:
      //   start	length	slot	name	signature
      //   0	465	0	this	ˊ
      //   0	465	1	paramString	String
      //   5	447	2	i	int
      //   31	415	3	j	int
      //   3	334	4	arrayOfByte	byte[]
      // Exception table:
      //   from	to	target	type
      //   3	20	455	java/io/UnsupportedEncodingException
      //   64	81	455	java/io/UnsupportedEncodingException
      //   88	183	455	java/io/UnsupportedEncodingException
      //   215	338	455	java/io/UnsupportedEncodingException
      //   343	346	455	java/io/UnsupportedEncodingException
    }
    
    /* Error */
    private static String ॱ(char[] paramArrayOfChar1, char paramChar, char[] paramArrayOfChar2, int paramInt, char[] paramArrayOfChar3)
    {
      // Byte code:
      //   0: goto +361 -> 361
      //   3: bipush 23
      //   5: istore_3
      //   6: goto +293 -> 299
      //   9: aload_0
      //   10: invokevirtual 102	[C:clone	()Ljava/lang/Object;
      //   13: checkcast 98	[C
      //   16: astore_0
      //   17: aload 4
      //   19: invokevirtual 102	[C:clone	()Ljava/lang/Object;
      //   22: checkcast 98	[C
      //   25: astore 4
      //   27: aload_0
      //   28: iconst_0
      //   29: aload_0
      //   30: iconst_0
      //   31: caload
      //   32: iload_1
      //   33: ixor
      //   34: i2c
      //   35: castore
      //   36: aload 4
      //   38: iconst_2
      //   39: aload 4
      //   41: iconst_2
      //   42: caload
      //   43: iload_3
      //   44: i2c
      //   45: iadd
      //   46: i2c
      //   47: castore
      //   48: aload_2
      //   49: arraylength
      //   50: istore 5
      //   52: iload 5
      //   54: newarray char
      //   56: astore 6
      //   58: iconst_0
      //   59: istore_3
      //   60: goto +115 -> 175
      //   63: astore_0
      //   64: aload_0
      //   65: athrow
      //   66: iload_1
      //   67: lookupswitch	default:+25->92, 3:+195->262, 22:+39->106
      //   92: goto +14 -> 106
      //   95: iconst_3
      //   96: istore_1
      //   97: goto -31 -> 66
      //   100: bipush 92
      //   102: istore_3
      //   103: goto +164 -> 267
      //   106: iload_3
      //   107: istore_1
      //   108: goto +49 -> 157
      //   111: goto -102 -> 9
      //   114: aload_0
      //   115: aload 4
      //   117: iload_1
      //   118: invokestatic 107	o/oJ:ˏ	([C[CI)V
      //   121: aload 6
      //   123: iload_1
      //   124: aload_2
      //   125: iload_1
      //   126: caload
      //   127: aload_0
      //   128: iload_1
      //   129: iconst_3
      //   130: iadd
      //   131: iconst_4
      //   132: irem
      //   133: caload
      //   134: ixor
      //   135: i2l
      //   136: getstatic 45	o/KX$ˊ:ˎ	J
      //   139: lxor
      //   140: getstatic 47	o/KX$ˊ:ˊ	I
      //   143: i2l
      //   144: lxor
      //   145: getstatic 43	o/KX$ˊ:ˋ	C
      //   148: i2l
      //   149: lxor
      //   150: l2i
      //   151: i2c
      //   152: castore
      //   153: iload_1
      //   154: iconst_1
      //   155: iadd
      //   156: istore_1
      //   157: iload_1
      //   158: iload 5
      //   160: if_icmpge +6 -> 166
      //   163: goto -160 -> 3
      //   166: goto +228 -> 394
      //   169: bipush 22
      //   171: istore_1
      //   172: goto -106 -> 66
      //   175: getstatic 26	o/KX$ˊ:ॱॱ	I
      //   178: bipush 83
      //   180: iadd
      //   181: istore_1
      //   182: iload_1
      //   183: sipush 128
      //   186: irem
      //   187: putstatic 24	o/KX$ˊ:ᐝ	I
      //   190: iload_1
      //   191: iconst_2
      //   192: irem
      //   193: ifeq +6 -> 199
      //   196: goto -27 -> 169
      //   199: goto -104 -> 95
      //   202: new 52	java/lang/String
      //   205: dup
      //   206: aload 6
      //   208: invokespecial 110	java/lang/String:<init>	([C)V
      //   211: areturn
      //   212: astore_0
      //   213: aload_0
      //   214: athrow
      //   215: aload_0
      //   216: aload 4
      //   218: iload_1
      //   219: invokestatic 107	o/oJ:ˏ	([C[CI)V
      //   222: aload 6
      //   224: iload_1
      //   225: aload_2
      //   226: iload_1
      //   227: caload
      //   228: aload_0
      //   229: iload_1
      //   230: iconst_3
      //   231: ishr
      //   232: iconst_5
      //   233: irem
      //   234: caload
      //   235: ior
      //   236: i2l
      //   237: getstatic 45	o/KX$ˊ:ˎ	J
      //   240: land
      //   241: getstatic 47	o/KX$ˊ:ˊ	I
      //   244: i2l
      //   245: lrem
      //   246: getstatic 43	o/KX$ˊ:ˋ	C
      //   249: i2l
      //   250: ldiv
      //   251: l2i
      //   252: i2c
      //   253: castore
      //   254: iload_1
      //   255: bipush 7
      //   257: iadd
      //   258: istore_1
      //   259: goto -102 -> 157
      //   262: iload_3
      //   263: istore_1
      //   264: goto -107 -> 157
      //   267: iload_3
      //   268: lookupswitch	default:+28->296, 45:+-154->114, 92:+-53->215
      //   296: goto -81 -> 215
      //   299: iload_3
      //   300: lookupswitch	default:+28->328, 23:+64->364, 59:+-98->202
      //   328: goto -126 -> 202
      //   331: getstatic 26	o/KX$ˊ:ॱॱ	I
      //   334: bipush 97
      //   336: iadd
      //   337: istore 5
      //   339: iload 5
      //   341: sipush 128
      //   344: irem
      //   345: putstatic 24	o/KX$ˊ:ᐝ	I
      //   348: iload 5
      //   350: iconst_2
      //   351: irem
      //   352: ifeq +6 -> 358
      //   355: goto -244 -> 111
      //   358: goto -349 -> 9
      //   361: goto -30 -> 331
      //   364: getstatic 24	o/KX$ˊ:ᐝ	I
      //   367: bipush 107
      //   369: iadd
      //   370: istore_3
      //   371: iload_3
      //   372: sipush 128
      //   375: irem
      //   376: putstatic 26	o/KX$ˊ:ॱॱ	I
      //   379: iload_3
      //   380: iconst_2
      //   381: irem
      //   382: ifne +6 -> 388
      //   385: goto -285 -> 100
      //   388: bipush 45
      //   390: istore_3
      //   391: goto -124 -> 267
      //   394: bipush 59
      //   396: istore_3
      //   397: goto -98 -> 299
      // Local variable table:
      //   start	length	slot	name	signature
      //   0	400	0	paramArrayOfChar1	char[]
      //   0	400	1	paramChar	char
      //   0	400	2	paramArrayOfChar2	char[]
      //   0	400	3	paramInt	int
      //   0	400	4	paramArrayOfChar3	char[]
      //   50	302	5	c	char
      //   56	167	6	arrayOfChar	char[]
      // Exception table:
      //   from	to	target	type
      //   175	182	63	java/lang/Exception
      //   182	190	63	java/lang/Exception
      //   182	190	212	java/lang/Exception
    }
    
    /* Error */
    public void ˊ(android.view.View paramView)
    {
      // Byte code:
      //   0: goto +269 -> 269
      //   3: aload_0
      //   4: getfield 39	o/KX$ˊ:ˏ	Lo/KX;
      //   7: astore_1
      //   8: aload_1
      //   9: invokevirtual 115	o/KX:getContext	()Landroid/content/Context;
      //   12: astore 5
      //   14: aload_0
      //   15: getfield 39	o/KX$ˊ:ˏ	Lo/KX;
      //   18: astore_1
      //   19: aload_1
      //   20: invokevirtual 115	o/KX:getContext	()Landroid/content/Context;
      //   23: astore_1
      //   24: aload_1
      //   25: getstatic 120	o/Jy$IF:default_payment_card	I
      //   28: invokevirtual 126	android/content/Context:getString	(I)Ljava/lang/String;
      //   31: astore 4
      //   33: aload 4
      //   35: iconst_4
      //   36: newarray char
      //   38: dup
      //   39: iconst_0
      //   40: ldc 127
      //   42: castore
      //   43: dup
      //   44: iconst_1
      //   45: ldc -128
      //   47: castore
      //   48: dup
      //   49: iconst_2
      //   50: ldc -127
      //   52: castore
      //   53: dup
      //   54: iconst_3
      //   55: ldc -126
      //   57: castore
      //   58: ldc -125
      //   60: iconst_4
      //   61: newarray char
      //   63: dup
      //   64: iconst_0
      //   65: ldc -124
      //   67: castore
      //   68: dup
      //   69: iconst_1
      //   70: ldc -123
      //   72: castore
      //   73: dup
      //   74: iconst_2
      //   75: ldc -122
      //   77: castore
      //   78: dup
      //   79: iconst_3
      //   80: ldc -121
      //   82: castore
      //   83: iconst_0
      //   84: iconst_4
      //   85: newarray char
      //   87: dup
      //   88: iconst_0
      //   89: ldc 63
      //   91: castore
      //   92: dup
      //   93: iconst_1
      //   94: ldc 63
      //   96: castore
      //   97: dup
      //   98: iconst_2
      //   99: ldc 63
      //   101: castore
      //   102: dup
      //   103: iconst_3
      //   104: ldc 63
      //   106: castore
      //   107: invokestatic 66	o/KX$ˊ:ॱ	([CC[CI[C)Ljava/lang/String;
      //   110: invokevirtual 70	java/lang/String:intern	()Ljava/lang/String;
      //   113: invokevirtual 139	java/lang/String:startsWith	(Ljava/lang/String;)Z
      //   116: istore_3
      //   117: iload_3
      //   118: ifeq +6 -> 124
      //   121: goto +23 -> 144
      //   124: goto +55 -> 179
      //   127: aload_0
      //   128: aload 4
      //   130: iconst_4
      //   131: invokevirtual 142	java/lang/String:substring	(I)Ljava/lang/String;
      //   134: invokespecial 144	o/KX$ˊ:ˏ	(Ljava/lang/String;)Ljava/lang/String;
      //   137: invokevirtual 70	java/lang/String:intern	()Ljava/lang/String;
      //   140: astore_1
      //   141: goto +125 -> 266
      //   144: iconst_0
      //   145: istore_2
      //   146: goto +146 -> 292
      //   149: getstatic 26	o/KX$ˊ:ॱॱ	I
      //   152: bipush 37
      //   154: iadd
      //   155: istore_2
      //   156: iload_2
      //   157: sipush 128
      //   160: irem
      //   161: putstatic 24	o/KX$ˊ:ᐝ	I
      //   164: iload_2
      //   165: iconst_2
      //   166: irem
      //   167: ifeq +6 -> 173
      //   170: goto +74 -> 244
      //   173: goto -170 -> 3
      //   176: astore_1
      //   177: aload_1
      //   178: athrow
      //   179: iconst_1
      //   180: istore_2
      //   181: goto +111 -> 292
      //   184: getstatic 26	o/KX$ˊ:ॱॱ	I
      //   187: bipush 19
      //   189: iadd
      //   190: istore_2
      //   191: iload_2
      //   192: sipush 128
      //   195: irem
      //   196: putstatic 24	o/KX$ˊ:ᐝ	I
      //   199: iload_2
      //   200: iconst_2
      //   201: irem
      //   202: ifeq +6 -> 208
      //   205: goto +42 -> 247
      //   208: goto +31 -> 239
      //   211: iload_2
      //   212: tableswitch	default:+24->236, 0:+60->272, 1:+-85->127
      //   236: goto +36 -> 272
      //   239: iconst_1
      //   240: istore_2
      //   241: goto -30 -> 211
      //   244: goto -241 -> 3
      //   247: iconst_0
      //   248: istore_2
      //   249: goto -38 -> 211
      //   252: aload 5
      //   254: aload_1
      //   255: iconst_0
      //   256: invokestatic 150	android/widget/Toast:makeText	(Landroid/content/Context;Ljava/lang/CharSequence;I)Landroid/widget/Toast;
      //   259: invokevirtual 153	android/widget/Toast:show	()V
      //   262: return
      //   263: astore_1
      //   264: aload_1
      //   265: athrow
      //   266: goto -14 -> 252
      //   269: goto -120 -> 149
      //   272: aload_0
      //   273: aload 4
      //   275: iconst_4
      //   276: invokevirtual 142	java/lang/String:substring	(I)Ljava/lang/String;
      //   279: invokespecial 144	o/KX$ˊ:ˏ	(Ljava/lang/String;)Ljava/lang/String;
      //   282: invokevirtual 70	java/lang/String:intern	()Ljava/lang/String;
      //   285: astore_1
      //   286: aconst_null
      //   287: arraylength
      //   288: istore_2
      //   289: goto -23 -> 266
      //   292: aload 4
      //   294: astore_1
      //   295: iload_2
      //   296: tableswitch	default:+24->320, 0:+-112->184, 1:+-44->252
      //   320: aload 4
      //   322: astore_1
      //   323: goto -71 -> 252
      // Local variable table:
      //   start	length	slot	name	signature
      //   0	326	0	this	ˊ
      //   0	326	1	paramView	android.view.View
      //   145	151	2	i	int
      //   116	2	3	bool	boolean
      //   31	290	4	str	String
      //   12	241	5	localContext	Context
      // Exception table:
      //   from	to	target	type
      //   3	8	176	java/lang/Exception
      //   8	14	176	java/lang/Exception
      //   14	19	176	java/lang/Exception
      //   19	24	176	java/lang/Exception
      //   24	117	176	java/lang/Exception
      //   14	19	263	java/lang/Exception
    }
  }
}
