package o;

import android.content.Context;
import android.databinding.ViewDataBinding;

public abstract class Kx<VDB extends ViewDataBinding>
  extends IB<VDB>
{
  protected static EK ʼॱ;
  private static int ʽॱ = 1;
  private static int[] ʾ = { -166885465, -878361633, -965934599, -1105796860, 612712714, -1261461276, 926434949, -2025266477, -214533200, 851114426, -646685462, 299733596, -768400313, 588115334, -209523929, 2694157, 588410237, 1380467836 };
  private static int ˈ = 0;
  protected coN ʿ;
  
  public Kx() {}
  
  /* Error */
  private static String ˏ(int[] paramArrayOfInt, int paramInt)
  {
    // Byte code:
    //   0: goto +210 -> 210
    //   3: aload 5
    //   5: iconst_0
    //   6: aload 7
    //   8: iload_2
    //   9: iaload
    //   10: bipush 16
    //   12: ishr
    //   13: i2c
    //   14: castore
    //   15: aload 5
    //   17: iconst_1
    //   18: aload 7
    //   20: iload_2
    //   21: iaload
    //   22: i2c
    //   23: castore
    //   24: aload 5
    //   26: iconst_2
    //   27: aload 7
    //   29: iload_2
    //   30: iconst_1
    //   31: iadd
    //   32: iaload
    //   33: bipush 16
    //   35: ishr
    //   36: i2c
    //   37: castore
    //   38: aload 5
    //   40: iconst_3
    //   41: aload 7
    //   43: iload_2
    //   44: iconst_1
    //   45: iadd
    //   46: iaload
    //   47: i2c
    //   48: castore
    //   49: aload 5
    //   51: aload 4
    //   53: iconst_0
    //   54: invokestatic 61	o/oN:ˏ	([C[IZ)[I
    //   57: pop
    //   58: aload 6
    //   60: iload_2
    //   61: iconst_1
    //   62: ishl
    //   63: aload 5
    //   65: iconst_0
    //   66: caload
    //   67: castore
    //   68: aload 6
    //   70: iload_2
    //   71: iconst_1
    //   72: ishl
    //   73: iconst_1
    //   74: iadd
    //   75: aload 5
    //   77: iconst_1
    //   78: caload
    //   79: castore
    //   80: aload 6
    //   82: iload_2
    //   83: iconst_1
    //   84: ishl
    //   85: iconst_2
    //   86: iadd
    //   87: aload 5
    //   89: iconst_2
    //   90: caload
    //   91: castore
    //   92: aload 6
    //   94: iload_2
    //   95: iconst_1
    //   96: ishl
    //   97: iconst_3
    //   98: iadd
    //   99: aload 5
    //   101: iconst_3
    //   102: caload
    //   103: castore
    //   104: iload_2
    //   105: iconst_2
    //   106: iadd
    //   107: istore_2
    //   108: goto +15 -> 123
    //   111: new 63	java/lang/String
    //   114: dup
    //   115: aload 6
    //   117: iconst_0
    //   118: iload_1
    //   119: invokespecial 66	java/lang/String:<init>	([CII)V
    //   122: areturn
    //   123: aload_0
    //   124: astore 7
    //   126: iload_2
    //   127: aload 7
    //   129: arraylength
    //   130: if_icmpge +6 -> 136
    //   133: goto +176 -> 309
    //   136: goto +128 -> 264
    //   139: iconst_1
    //   140: istore_2
    //   141: goto +173 -> 314
    //   144: iconst_0
    //   145: istore_2
    //   146: goto +168 -> 314
    //   149: iload_3
    //   150: tableswitch	default:+22->172, 0:+-39->111, 1:+87->237
    //   172: goto +65 -> 237
    //   175: iconst_4
    //   176: newarray char
    //   178: astore 5
    //   180: aload_0
    //   181: arraylength
    //   182: iconst_1
    //   183: ishl
    //   184: newarray char
    //   186: astore 6
    //   188: getstatic 42	o/Kx:ʾ	[I
    //   191: invokevirtual 71	[I:clone	()Ljava/lang/Object;
    //   194: checkcast 67	[I
    //   197: astore 4
    //   199: iconst_0
    //   200: istore_2
    //   201: goto -78 -> 123
    //   204: astore_0
    //   205: aload_0
    //   206: athrow
    //   207: goto -204 -> 3
    //   210: getstatic 22	o/Kx:ʽॱ	I
    //   213: bipush 7
    //   215: iadd
    //   216: istore_2
    //   217: iload_2
    //   218: sipush 128
    //   221: irem
    //   222: putstatic 20	o/Kx:ˈ	I
    //   225: iload_2
    //   226: iconst_2
    //   227: irem
    //   228: ifeq +6 -> 234
    //   231: goto -92 -> 139
    //   234: goto -90 -> 144
    //   237: getstatic 20	o/Kx:ˈ	I
    //   240: bipush 85
    //   242: iadd
    //   243: istore_3
    //   244: iload_3
    //   245: sipush 128
    //   248: irem
    //   249: putstatic 22	o/Kx:ʽॱ	I
    //   252: iload_3
    //   253: iconst_2
    //   254: irem
    //   255: ifne +6 -> 261
    //   258: goto -51 -> 207
    //   261: goto -258 -> 3
    //   264: iconst_0
    //   265: istore_3
    //   266: goto -117 -> 149
    //   269: astore_0
    //   270: aload_0
    //   271: athrow
    //   272: iconst_5
    //   273: newarray char
    //   275: astore 5
    //   277: aload_0
    //   278: arraylength
    //   279: iconst_0
    //   280: irem
    //   281: newarray char
    //   283: astore 6
    //   285: getstatic 42	o/Kx:ʾ	[I
    //   288: astore 4
    //   290: aload 4
    //   292: invokevirtual 71	[I:clone	()Ljava/lang/Object;
    //   295: astore 4
    //   297: aload 4
    //   299: checkcast 67	[I
    //   302: astore 4
    //   304: iconst_1
    //   305: istore_2
    //   306: goto -183 -> 123
    //   309: iconst_1
    //   310: istore_3
    //   311: goto -162 -> 149
    //   314: iload_2
    //   315: tableswitch	default:+21->336, 0:+-140->175, 1:+-43->272
    //   336: goto -64 -> 272
    // Local variable table:
    //   start	length	slot	name	signature
    //   0	339	0	paramArrayOfInt	int[]
    //   0	339	1	paramInt	int
    //   8	307	2	i	int
    //   149	162	3	j	int
    //   51	252	4	localObject	Object
    //   3	273	5	arrayOfChar1	char[]
    //   58	226	6	arrayOfChar2	char[]
    //   6	122	7	arrayOfInt	int[]
    // Exception table:
    //   from	to	target	type
    //   49	58	204	java/lang/Exception
    //   285	290	269	java/lang/Exception
    //   290	297	269	java/lang/Exception
    //   297	304	269	java/lang/Exception
  }
  
  /* Error */
  public android.content.res.Resources getResources()
  {
    // Byte code:
    //   0: goto +162 -> 162
    //   3: iload_1
    //   4: lookupswitch	default:+28->32, 17:+105->109, 92:+161->165
    //   32: aload_2
    //   33: areturn
    //   34: iload_1
    //   35: tableswitch	default:+21->56, 0:+21->56, 1:+109->144
    //   56: aload_0
    //   57: invokespecial 75	o/IB:getResources	()Landroid/content/res/Resources;
    //   60: invokestatic 81	o/oH:ˊ	(Landroid/content/res/Resources;)Landroid/content/res/Resources;
    //   63: astore_2
    //   64: goto +16 -> 80
    //   67: iconst_1
    //   68: istore_1
    //   69: goto -35 -> 34
    //   72: astore_2
    //   73: aload_2
    //   74: athrow
    //   75: iconst_0
    //   76: istore_1
    //   77: goto -43 -> 34
    //   80: getstatic 20	o/Kx:ˈ	I
    //   83: iconst_5
    //   84: iadd
    //   85: istore_1
    //   86: iload_1
    //   87: sipush 128
    //   90: irem
    //   91: putstatic 22	o/Kx:ʽॱ	I
    //   94: iload_1
    //   95: iconst_2
    //   96: irem
    //   97: ifne +6 -> 103
    //   100: goto +38 -> 138
    //   103: bipush 17
    //   105: istore_1
    //   106: goto -103 -> 3
    //   109: aload_2
    //   110: areturn
    //   111: getstatic 20	o/Kx:ˈ	I
    //   114: bipush 59
    //   116: iadd
    //   117: istore_1
    //   118: iload_1
    //   119: sipush 128
    //   122: irem
    //   123: putstatic 22	o/Kx:ʽॱ	I
    //   126: iload_1
    //   127: iconst_2
    //   128: irem
    //   129: ifne +6 -> 135
    //   132: goto -65 -> 67
    //   135: goto -60 -> 75
    //   138: bipush 92
    //   140: istore_1
    //   141: goto -138 -> 3
    //   144: aload_0
    //   145: invokespecial 75	o/IB:getResources	()Landroid/content/res/Resources;
    //   148: astore_2
    //   149: aload_2
    //   150: invokestatic 81	o/oH:ˊ	(Landroid/content/res/Resources;)Landroid/content/res/Resources;
    //   153: astore_2
    //   154: bipush 58
    //   156: iconst_0
    //   157: idiv
    //   158: istore_1
    //   159: goto -79 -> 80
    //   162: goto -51 -> 111
    //   165: new 83	java/lang/NullPointerException
    //   168: dup
    //   169: invokespecial 84	java/lang/NullPointerException:<init>	()V
    //   172: athrow
    // Local variable table:
    //   start	length	slot	name	signature
    //   0	173	0	this	Kx
    //   3	156	1	i	int
    //   32	32	2	localResources1	android.content.res.Resources
    //   72	38	2	localException	Exception
    //   148	6	2	localResources2	android.content.res.Resources
    // Exception table:
    //   from	to	target	type
    //   149	154	72	java/lang/Exception
  }
  
  /* Error */
  public void onCreate(android.os.Bundle paramBundle)
  {
    // Byte code:
    //   0: goto +33 -> 33
    //   3: astore_1
    //   4: aload_1
    //   5: athrow
    //   6: getstatic 22	o/Kx:ʽॱ	I
    //   9: istore_2
    //   10: iload_2
    //   11: bipush 19
    //   13: iadd
    //   14: istore_2
    //   15: iload_2
    //   16: sipush 128
    //   19: irem
    //   20: putstatic 20	o/Kx:ˈ	I
    //   23: iload_2
    //   24: iconst_2
    //   25: irem
    //   26: ifeq +6 -> 32
    //   29: goto +24 -> 53
    //   32: return
    //   33: aload_0
    //   34: aload_1
    //   35: invokespecial 88	o/IB:onCreate	(Landroid/os/Bundle;)V
    //   38: aload_0
    //   39: new 90	o/coN
    //   42: dup
    //   43: iconst_0
    //   44: invokespecial 93	o/coN:<init>	(Z)V
    //   47: putfield 95	o/Kx:ʿ	Lo/coN;
    //   50: goto -44 -> 6
    //   53: return
    //   54: astore_1
    //   55: aload_1
    //   56: athrow
    // Local variable table:
    //   start	length	slot	name	signature
    //   0	57	0	this	Kx
    //   0	57	1	paramBundle	android.os.Bundle
    //   9	17	2	i	int
    // Exception table:
    //   from	to	target	type
    //   6	10	3	java/lang/Exception
    //   15	23	54	java/lang/Exception
  }
  
  protected abstract void ʻॱ();
  
  /* Error */
  protected void ʾ()
  {
    // Byte code:
    //   0: goto +53 -> 53
    //   3: getstatic 20	o/Kx:ˈ	I
    //   6: bipush 63
    //   8: iadd
    //   9: istore_1
    //   10: iload_1
    //   11: sipush 128
    //   14: irem
    //   15: putstatic 22	o/Kx:ʽॱ	I
    //   18: iload_1
    //   19: iconst_2
    //   20: irem
    //   21: ifne +6 -> 27
    //   24: goto +479 -> 503
    //   27: goto +489 -> 516
    //   30: iload_1
    //   31: tableswitch	default:+21->52, 0:+477->508, 1:+471->502
    //   52: return
    //   53: aload_0
    //   54: invokevirtual 102	android/content/Context:getPackageName	()Ljava/lang/String;
    //   57: bipush 8
    //   59: invokevirtual 106	java/lang/String:codePointAt	(I)I
    //   62: istore_1
    //   63: bipush 10
    //   65: newarray int
    //   67: dup
    //   68: iconst_0
    //   69: ldc 107
    //   71: iastore
    //   72: dup
    //   73: iconst_1
    //   74: ldc 108
    //   76: iastore
    //   77: dup
    //   78: iconst_2
    //   79: ldc 109
    //   81: iastore
    //   82: dup
    //   83: iconst_3
    //   84: ldc 110
    //   86: iastore
    //   87: dup
    //   88: iconst_4
    //   89: ldc 111
    //   91: iastore
    //   92: dup
    //   93: iconst_5
    //   94: ldc 112
    //   96: iastore
    //   97: dup
    //   98: bipush 6
    //   100: ldc 113
    //   102: iastore
    //   103: dup
    //   104: bipush 7
    //   106: ldc 114
    //   108: iastore
    //   109: dup
    //   110: bipush 8
    //   112: ldc 115
    //   114: iastore
    //   115: dup
    //   116: bipush 9
    //   118: ldc 116
    //   120: iastore
    //   121: iload_1
    //   122: bipush 94
    //   124: isub
    //   125: invokestatic 118	o/Kx:ˏ	([II)Ljava/lang/String;
    //   128: invokevirtual 121	java/lang/String:intern	()Ljava/lang/String;
    //   131: astore_2
    //   132: new 123	java/lang/StringBuilder
    //   135: dup
    //   136: invokespecial 124	java/lang/StringBuilder:<init>	()V
    //   139: astore_3
    //   140: aload_0
    //   141: invokevirtual 125	android/content/Context:getResources	()Landroid/content/res/Resources;
    //   144: ldc 126
    //   146: invokevirtual 132	android/content/res/Resources:getString	(I)Ljava/lang/String;
    //   149: iconst_0
    //   150: iconst_4
    //   151: invokevirtual 136	java/lang/String:substring	(II)Ljava/lang/String;
    //   154: iconst_2
    //   155: invokevirtual 106	java/lang/String:codePointAt	(I)I
    //   158: istore_1
    //   159: aload_3
    //   160: bipush 14
    //   162: newarray int
    //   164: dup
    //   165: iconst_0
    //   166: ldc 109
    //   168: iastore
    //   169: dup
    //   170: iconst_1
    //   171: ldc 110
    //   173: iastore
    //   174: dup
    //   175: iconst_2
    //   176: ldc -119
    //   178: iastore
    //   179: dup
    //   180: iconst_3
    //   181: ldc -118
    //   183: iastore
    //   184: dup
    //   185: iconst_4
    //   186: ldc -117
    //   188: iastore
    //   189: dup
    //   190: iconst_5
    //   191: ldc -116
    //   193: iastore
    //   194: dup
    //   195: bipush 6
    //   197: ldc -115
    //   199: iastore
    //   200: dup
    //   201: bipush 7
    //   203: ldc -114
    //   205: iastore
    //   206: dup
    //   207: bipush 8
    //   209: ldc -113
    //   211: iastore
    //   212: dup
    //   213: bipush 9
    //   215: ldc -112
    //   217: iastore
    //   218: dup
    //   219: bipush 10
    //   221: ldc -111
    //   223: iastore
    //   224: dup
    //   225: bipush 11
    //   227: ldc -110
    //   229: iastore
    //   230: dup
    //   231: bipush 12
    //   233: ldc -109
    //   235: iastore
    //   236: dup
    //   237: bipush 13
    //   239: ldc -108
    //   241: iastore
    //   242: iload_1
    //   243: bipush 17
    //   245: iadd
    //   246: invokestatic 118	o/Kx:ˏ	([II)Ljava/lang/String;
    //   249: invokevirtual 121	java/lang/String:intern	()Ljava/lang/String;
    //   252: invokevirtual 152	java/lang/StringBuilder:append	(Ljava/lang/String;)Ljava/lang/StringBuilder;
    //   255: getstatic 154	o/Kx:ʼॱ	Lo/EK;
    //   258: invokevirtual 159	java/lang/Object:toString	()Ljava/lang/String;
    //   261: invokevirtual 152	java/lang/StringBuilder:append	(Ljava/lang/String;)Ljava/lang/StringBuilder;
    //   264: invokevirtual 160	java/lang/StringBuilder:toString	()Ljava/lang/String;
    //   267: astore_3
    //   268: goto +17 -> 285
    //   271: astore_3
    //   272: aload_3
    //   273: invokevirtual 166	java/lang/Throwable:getCause	()Ljava/lang/Throwable;
    //   276: astore_2
    //   277: aload_2
    //   278: ifnull +5 -> 283
    //   281: aload_2
    //   282: athrow
    //   283: aload_3
    //   284: athrow
    //   285: aload_0
    //   286: invokevirtual 125	android/content/Context:getResources	()Landroid/content/res/Resources;
    //   289: ldc -89
    //   291: invokevirtual 132	android/content/res/Resources:getString	(I)Ljava/lang/String;
    //   294: iconst_0
    //   295: iconst_4
    //   296: invokevirtual 136	java/lang/String:substring	(II)Ljava/lang/String;
    //   299: invokevirtual 171	java/lang/String:length	()I
    //   302: iconst_0
    //   303: iadd
    //   304: aload_0
    //   305: invokevirtual 102	android/content/Context:getPackageName	()Ljava/lang/String;
    //   308: invokevirtual 171	java/lang/String:length	()I
    //   311: bipush 31
    //   313: iadd
    //   314: aload_0
    //   315: invokevirtual 125	android/content/Context:getResources	()Landroid/content/res/Resources;
    //   318: ldc -84
    //   320: invokevirtual 132	android/content/res/Resources:getString	(I)Ljava/lang/String;
    //   323: iconst_0
    //   324: iconst_4
    //   325: invokevirtual 136	java/lang/String:substring	(II)Ljava/lang/String;
    //   328: invokevirtual 171	java/lang/String:length	()I
    //   331: ldc -83
    //   333: iadd
    //   334: i2c
    //   335: invokestatic 178	o/O:ˋ	(IIC)Ljava/lang/Object;
    //   338: checkcast 180	java/lang/Class
    //   341: ldc -74
    //   343: iconst_2
    //   344: anewarray 180	java/lang/Class
    //   347: dup
    //   348: iconst_0
    //   349: ldc 63
    //   351: aastore
    //   352: dup
    //   353: iconst_1
    //   354: ldc 63
    //   356: aastore
    //   357: invokevirtual 186	java/lang/Class:getMethod	(Ljava/lang/String;[Ljava/lang/Class;)Ljava/lang/reflect/Method;
    //   360: aconst_null
    //   361: iconst_2
    //   362: anewarray 156	java/lang/Object
    //   365: dup
    //   366: iconst_0
    //   367: aload_2
    //   368: aastore
    //   369: dup
    //   370: iconst_1
    //   371: aload_3
    //   372: aastore
    //   373: invokevirtual 192	java/lang/reflect/Method:invoke	(Ljava/lang/Object;[Ljava/lang/Object;)Ljava/lang/Object;
    //   376: pop
    //   377: aload_0
    //   378: getfield 95	o/Kx:ʿ	Lo/coN;
    //   381: iconst_1
    //   382: invokevirtual 194	o/coN:ˋ	(Z)V
    //   385: goto +17 -> 402
    //   388: astore_2
    //   389: aload_2
    //   390: invokevirtual 166	java/lang/Throwable:getCause	()Ljava/lang/Throwable;
    //   393: astore_3
    //   394: aload_3
    //   395: ifnull +5 -> 400
    //   398: aload_3
    //   399: athrow
    //   400: aload_2
    //   401: athrow
    //   402: aload_0
    //   403: invokevirtual 125	android/content/Context:getResources	()Landroid/content/res/Resources;
    //   406: ldc -61
    //   408: invokevirtual 132	android/content/res/Resources:getString	(I)Ljava/lang/String;
    //   411: iconst_0
    //   412: iconst_4
    //   413: invokevirtual 136	java/lang/String:substring	(II)Ljava/lang/String;
    //   416: iconst_2
    //   417: invokevirtual 106	java/lang/String:codePointAt	(I)I
    //   420: bipush 7
    //   422: isub
    //   423: aload_0
    //   424: invokevirtual 199	android/content/Context:getApplicationInfo	()Landroid/content/pm/ApplicationInfo;
    //   427: getfield 204	android/content/pm/ApplicationInfo:targetSdkVersion	I
    //   430: bipush 110
    //   432: iadd
    //   433: aload_0
    //   434: invokevirtual 125	android/content/Context:getResources	()Landroid/content/res/Resources;
    //   437: ldc -51
    //   439: invokevirtual 132	android/content/res/Resources:getString	(I)Ljava/lang/String;
    //   442: iconst_0
    //   443: iconst_4
    //   444: invokevirtual 136	java/lang/String:substring	(II)Ljava/lang/String;
    //   447: iconst_1
    //   448: invokevirtual 106	java/lang/String:codePointAt	(I)I
    //   451: ldc -50
    //   453: iadd
    //   454: i2c
    //   455: invokestatic 178	o/O:ˋ	(IIC)Ljava/lang/Object;
    //   458: checkcast 180	java/lang/Class
    //   461: ldc -49
    //   463: aconst_null
    //   464: invokevirtual 186	java/lang/Class:getMethod	(Ljava/lang/String;[Ljava/lang/Class;)Ljava/lang/reflect/Method;
    //   467: aconst_null
    //   468: aconst_null
    //   469: invokevirtual 192	java/lang/reflect/Method:invoke	(Ljava/lang/Object;[Ljava/lang/Object;)Ljava/lang/Object;
    //   472: checkcast 209	o/It
    //   475: astore_2
    //   476: aload_2
    //   477: getstatic 154	o/Kx:ʼॱ	Lo/EK;
    //   480: invokeinterface 212 2 0
    //   485: new 7	o/Kx$2
    //   488: dup
    //   489: aload_0
    //   490: aload_0
    //   491: invokespecial 215	o/Kx$2:<init>	(Lo/Kx;Landroid/content/Context;)V
    //   494: invokeinterface 220 2 0
    //   499: goto -496 -> 3
    //   502: return
    //   503: iconst_0
    //   504: istore_1
    //   505: goto -475 -> 30
    //   508: new 83	java/lang/NullPointerException
    //   511: dup
    //   512: invokespecial 84	java/lang/NullPointerException:<init>	()V
    //   515: athrow
    //   516: iconst_1
    //   517: istore_1
    //   518: goto -488 -> 30
    // Local variable table:
    //   start	length	slot	name	signature
    //   0	521	0	this	Kx
    //   9	509	1	i	int
    //   131	237	2	localObject1	Object
    //   388	13	2	localObject2	Object
    //   475	2	2	localIt	It
    //   139	129	3	localObject3	Object
    //   271	101	3	localObject4	Object
    //   393	6	3	localThrowable	Throwable
    // Exception table:
    //   from	to	target	type
    //   285	377	271	finally
    //   402	476	388	finally
  }
  
  /* Error */
  public void ˋ(ز paramز)
  {
    // Byte code:
    //   0: goto +47 -> 47
    //   3: iload_2
    //   4: tableswitch	default:+24->28, 0:+82->86, 1:+49->53
    //   28: return
    //   29: iconst_0
    //   30: istore_2
    //   31: goto -28 -> 3
    //   34: aload_1
    //   35: iconst_1
    //   36: invokevirtual 225	o/ز:ॱ	(Z)V
    //   39: aload_1
    //   40: iconst_1
    //   41: invokevirtual 227	o/ز:ˏ	(Z)V
    //   44: goto +10 -> 54
    //   47: goto +45 -> 92
    //   50: astore_1
    //   51: aload_1
    //   52: athrow
    //   53: return
    //   54: getstatic 20	o/Kx:ˈ	I
    //   57: istore_2
    //   58: iload_2
    //   59: bipush 113
    //   61: iadd
    //   62: istore_2
    //   63: iload_2
    //   64: sipush 128
    //   67: irem
    //   68: putstatic 22	o/Kx:ʽॱ	I
    //   71: iload_2
    //   72: iconst_2
    //   73: irem
    //   74: ifne +6 -> 80
    //   77: goto -48 -> 29
    //   80: goto +39 -> 119
    //   83: astore_1
    //   84: aload_1
    //   85: athrow
    //   86: bipush 14
    //   88: iconst_0
    //   89: idiv
    //   90: istore_2
    //   91: return
    //   92: getstatic 22	o/Kx:ʽॱ	I
    //   95: bipush 91
    //   97: iadd
    //   98: istore_2
    //   99: iload_2
    //   100: sipush 128
    //   103: irem
    //   104: putstatic 20	o/Kx:ˈ	I
    //   107: iload_2
    //   108: iconst_2
    //   109: irem
    //   110: ifeq +6 -> 116
    //   113: goto -79 -> 34
    //   116: goto -82 -> 34
    //   119: iconst_1
    //   120: istore_2
    //   121: goto -118 -> 3
    // Local variable table:
    //   start	length	slot	name	signature
    //   0	124	0	this	Kx
    //   0	124	1	paramز	ز
    //   3	118	2	i	int
    // Exception table:
    //   from	to	target	type
    //   54	58	50	java/lang/Exception
    //   63	71	83	java/lang/Exception
  }
}
