package o;

import android.content.Context;
import android.content.DialogInterface;
import android.content.DialogInterface.OnCancelListener;
import android.content.pm.ApplicationInfo;
import android.content.res.Resources;
import android.databinding.ViewDataBinding;
import android.view.View;
import android.view.View.OnClickListener;
import android.widget.Toast;
import java.io.UnsupportedEncodingException;
import uk.co.chrisjenx.calligraphy.CalligraphyContextWrapper;

public abstract class l<VDB extends ViewDataBinding>
  extends ܖ
  implements View.OnClickListener, v
{
  private static int ʼॱ;
  private static int ʾ;
  private static long ˈ;
  private static byte ॱˋ;
  private static char[] ॱˎ;
  protected boolean ʻॱ;
  protected af ͺ;
  public VDB ॱˊ;
  private boolean ॱᐝ;
  protected boolean ᐝॱ;
  
  static
  {
    for (;;)
    {
      int i = ʼॱ + 83;
      ʾ = i % 128;
      if (i % 2 != 0) {
        break;
      }
      return;
      ʾ = 0;
      ʼॱ = 1;
      ᐝॱ();
      ॱˋ = -102;
    }
  }
  
  public l() {}
  
  /* Error */
  private static String ˋ(char paramChar, int paramInt1, int paramInt2)
  {
    // Byte code:
    //   0: goto +215 -> 215
    //   3: iload_2
    //   4: newarray char
    //   6: astore 5
    //   8: goto +138 -> 146
    //   11: iload_3
    //   12: tableswitch	default:+24->36, 0:+-9->3, 1:+129->141
    //   36: goto -33 -> 3
    //   39: iload_3
    //   40: iload_2
    //   41: if_icmpge +6 -> 47
    //   44: goto +60 -> 104
    //   47: goto +171 -> 218
    //   50: iconst_1
    //   51: istore_3
    //   52: goto -41 -> 11
    //   55: getstatic 39	o/l:ʾ	I
    //   58: iconst_3
    //   59: iadd
    //   60: istore 4
    //   62: iload 4
    //   64: sipush 128
    //   67: irem
    //   68: putstatic 37	o/l:ʼॱ	I
    //   71: iload 4
    //   73: iconst_2
    //   74: irem
    //   75: ifne +6 -> 81
    //   78: goto +134 -> 212
    //   81: goto -42 -> 39
    //   84: astore 5
    //   86: aload 5
    //   88: athrow
    //   89: new 53	java/lang/String
    //   92: dup
    //   93: aload 5
    //   95: invokespecial 56	java/lang/String:<init>	([C)V
    //   98: areturn
    //   99: iconst_0
    //   100: istore_3
    //   101: goto -90 -> 11
    //   104: iconst_1
    //   105: istore 4
    //   107: goto +71 -> 178
    //   110: aload 5
    //   112: iload_3
    //   113: getstatic 58	o/l:ॱˎ	[C
    //   116: iload_1
    //   117: iload_3
    //   118: iadd
    //   119: caload
    //   120: i2l
    //   121: iload_3
    //   122: i2l
    //   123: getstatic 60	o/l:ˈ	J
    //   126: lmul
    //   127: lxor
    //   128: iload_0
    //   129: i2l
    //   130: lxor
    //   131: l2i
    //   132: i2c
    //   133: castore
    //   134: iload_3
    //   135: iconst_1
    //   136: iadd
    //   137: istore_3
    //   138: goto -83 -> 55
    //   141: iload_2
    //   142: newarray char
    //   144: astore 5
    //   146: iconst_0
    //   147: istore_3
    //   148: goto -109 -> 39
    //   151: getstatic 39	o/l:ʾ	I
    //   154: bipush 65
    //   156: iadd
    //   157: istore_3
    //   158: iload_3
    //   159: sipush 128
    //   162: irem
    //   163: putstatic 37	o/l:ʼॱ	I
    //   166: iload_3
    //   167: iconst_2
    //   168: irem
    //   169: ifne +6 -> 175
    //   172: goto -122 -> 50
    //   175: goto -76 -> 99
    //   178: iload 4
    //   180: tableswitch	default:+24->204, 0:+-91->89, 1:+-70->110
    //   204: goto -115 -> 89
    //   207: astore 5
    //   209: aload 5
    //   211: athrow
    //   212: goto -173 -> 39
    //   215: goto -64 -> 151
    //   218: iconst_0
    //   219: istore 4
    //   221: goto -43 -> 178
    // Local variable table:
    //   start	length	slot	name	signature
    //   0	224	0	paramChar	char
    //   0	224	1	paramInt1	int
    //   0	224	2	paramInt2	int
    //   11	158	3	i	int
    //   60	160	4	j	int
    //   6	1	5	arrayOfChar1	char[]
    //   84	27	5	localException1	Exception
    //   144	1	5	arrayOfChar2	char[]
    //   207	3	5	localException2	Exception
    // Exception table:
    //   from	to	target	type
    //   151	158	84	java/lang/Exception
    //   158	166	84	java/lang/Exception
    //   158	166	207	java/lang/Exception
  }
  
  private String ˋ(String paramString)
  {
    break label97;
    int j;
    switch (j)
    {
    default: 
      break;
    }
    int i;
    label97:
    byte[] arrayOfByte;
    for (;;)
    {
      try
      {
        j = paramString.length;
        if (i >= j) {
          continue;
        }
        switch (j)
        {
        default: 
          continue;
          j = ʼॱ + 1;
          ʾ = j % 128;
          if (j % 2 != 0) {
            break label295;
          }
          break label229;
          continue;
          j = ʾ + 37;
          ʼॱ = j % 128;
          if (j % 2 != 0)
          {
            continue;
            j = 0;
            break;
          }
          continue;
          j = 1;
          break;
          i = ʼॱ + 107;
          ʾ = i % 128;
          if (i % 2 != 0) {
            break label377;
          }
          break label300;
          break;
        case 1: 
          arrayOfByte[i] = ((byte)(paramString[(paramString.length >> i >>> 1)] ^ ॱˋ));
          i += 95;
          break;
        case 0: 
          arrayOfByte[i] = ((byte)(paramString[(paramString.length - i - 1)] ^ ॱˋ));
          i += 1;
          continue;
          j = 0;
        }
      }
      catch (UnsupportedEncodingException paramString)
      {
        throw new RuntimeException(paramString);
      }
      label229:
      continue;
      paramString = new String(arrayOfByte, ˋ((char)(getResources().getString(2131755326).substring(0, 10).length() - 10), getPackageName().length() + 396, getApplicationInfo().targetSdkVersion - 20).intern());
      return paramString;
      label295:
      j = 1;
    }
    label300:
    label377:
    for (;;)
    {
      paramString = paramString.getBytes(ˋ((char)(getPackageName().codePointAt(8) - 112), getResources().getString(2131755142).substring(0, 5).codePointAt(2) + 386, getResources().getString(2131755060).substring(0, 4).length() + 6).intern());
      arrayOfByte = new byte[paramString.length];
      i = 0;
      break;
    }
  }
  
  static void ᐝॱ()
  {
    ˈ = 1193227051546499003L;
    ॱˎ = new char[] { -14219, 8147, 26386, 20307, -26979, -280, -14829, 11873, 30116, 24044, -23255, -29370, -11077, 15361, 1141, 27537, -19505, -25845, -7319, -13666, 4842, 31256, 17006, -22094, -3589, -9928, 8369, 2266, 20487, -18355, -28769, -10288, 16158, -26037, 19922, 13576, 7506, -15216, -21308, -27620, 31854, 10142, 4080, -2270, -8346, -31059, 28172, 22099, 14739, -7713, 18748, -24923, -6529, -12763, 6119, 32691, 18283, -20711, -2939, 32, -10292, -20713, -30910, 24268, 14020, 3600, -6536, -16967, -27161, 27947, 17773, 32, -10284, -20712, -30849, 24201, 14032, 3627, -6541, -16980, -27146, 27936, 17789, 7396, -3064, -13221, -23674, 31632, 21256, 11079, 653, -9488, -19918, -30090, 32, -10295, -20717, -30894, 24201, 14030, 3604, -6536, -16964, -27213, 27964, 17772, 7351, -3062, -13226, -23679, 31632, 21276, 11087, 661, -9484, -19849, -30112, 25000, 14843, 4406, -5998, -16179, -26569, 28736, 18318, 8128, -2214, -12485, 32, -10278, -20712, -30891, 24268, 14030, 3596, -6551, -16963, -27139, 27962, 17705, 7328, -3042, -13234, -23660, 31626, 21323, 32, -10296, -20734, -30896, 24222, 14035, 3591, -6535, 32, -10295, -20717, -30910, 24217, 14026, 3591, -6535, -16904, -27150, 27936, 17773, 7396, -3063, -13229, -23674, 31705, 21257, 11082, 644, 32, -10293, -20713, -30908, 24223, 14018, 3590, -6595, -16967, -27139, 27946, 17705, 7341, -3055, -13236, -23652, 31683, 21250, 11076, 653, -9479, 32, -10296, -20734, -30882, 24220, 14039, 3591, -6535, 32, -10273, -20717, -30910, 24216, 14037, 3597, -6556, -16963, -27145, -28551, 18399, 16158, 5983, -12655, -22812, -25076, 30308, 11701, 1530, -713, -10906, -29524, 25660, 23621, 13190, -5176, -15598, 6866, -12981, -19059, -25151, 17419, 11347, 5275, 79, -10283, -20650, -30882, 24220, 14035, 3595, -6542, -16970, -27168, 28014, 17764, 7329, -3055, -13233, -23595, 31705, 21279, 11075, 652, -9540, -19932, -30089, 24993, 14829, 4384, -6006, -16164, -26608, 28687, 4443, -14625, -16866, -27061, 20417, 10205, 7942, -2204, -21315, -31554, 31786, 21600, 3561, -11519, 1261, 31798, 21603, -29203, -6666, -8911, 13657, 28298, 18113, -16886, -27060, 3398, -9530, -24052, -30125, 21392, 15324, 784, -5336, -20291, -26397, 24617, 18545, 4536, -1767, -16036, -20855, 30410, 24080, 9747, 3974, -10264, -16586, -30866, 27831, 13555, 7223, -6777, -12855, -27327, 32078, 19088, 4752, -1535, -15770, -21594, 29604, 23340, 9057, 2226, -12262, 11684, -1536, -32036, -21860, 82, -10274, -20729, -30908, 24201, 14036, 3606, -6540, -16970, -27148, 28014, 17785, 7329, -3059, -13225, -23652, 31683, 21272, 11087, 654, -9486, -19932, -30158, 6714, -12884, -19103, -25307, 17632, 11516, 5240, -1019, -22569, -28799, 30531, 24347, 1739, -4483, -10655, -18842, 24978, 6494, 12631, -5922, -32626, -18348, 20603, 3057, 9139, -9432, -3293, -21779, 16986, 31255, 5523, -12923, -6834, -25326, -19262, 27839, 1151, 73, -10264, -20679, -30948, 24276, 13983, 3671, -6620, -16907, -27230, 85, -10257, -20688, -30948, 24276 };
  }
  
  protected void attachBaseContext(Context paramContext)
  {
    break label54;
    int i = 0;
    break label57;
    label54:
    for (;;)
    {
      i = ʾ + 67;
      ʼॱ = i % 128;
      if (i % 2 != 0) {
        break;
      }
      i = 1;
      break label57;
      super.attachBaseContext(CalligraphyContextWrapper.wrap(paramContext));
      i = 75 / 0;
      return;
    }
    label57:
    switch (i)
    {
    }
    super.attachBaseContext(CalligraphyContextWrapper.wrap(paramContext));
  }
  
  /* Error */
  public Resources getResources()
  {
    // Byte code:
    //   0: goto +71 -> 71
    //   3: getstatic 39	o/l:ʾ	I
    //   6: bipush 39
    //   8: iadd
    //   9: istore_1
    //   10: iload_1
    //   11: sipush 128
    //   14: irem
    //   15: putstatic 37	o/l:ʼॱ	I
    //   18: iload_1
    //   19: iconst_2
    //   20: irem
    //   21: ifne +6 -> 27
    //   24: goto +65 -> 89
    //   27: goto +31 -> 58
    //   30: iload_1
    //   31: tableswitch	default:+21->52, 0:+43->74, 1:+32->63
    //   52: goto +22 -> 74
    //   55: astore_2
    //   56: aload_2
    //   57: athrow
    //   58: iconst_1
    //   59: istore_1
    //   60: goto -30 -> 30
    //   63: aload_0
    //   64: invokespecial 492	o/ܖ:getResources	()Landroid/content/res/Resources;
    //   67: invokestatic 498	o/oH:ˊ	(Landroid/content/res/Resources;)Landroid/content/res/Resources;
    //   70: areturn
    //   71: goto -68 -> 3
    //   74: aload_0
    //   75: invokespecial 492	o/ܖ:getResources	()Landroid/content/res/Resources;
    //   78: astore_2
    //   79: aload_2
    //   80: invokestatic 498	o/oH:ˊ	(Landroid/content/res/Resources;)Landroid/content/res/Resources;
    //   83: astore_2
    //   84: aconst_null
    //   85: arraylength
    //   86: istore_1
    //   87: aload_2
    //   88: areturn
    //   89: iconst_0
    //   90: istore_1
    //   91: goto -61 -> 30
    // Local variable table:
    //   start	length	slot	name	signature
    //   0	94	0	this	l
    //   9	82	1	i	int
    //   55	2	2	localException	Exception
    //   78	10	2	localResources	Resources
    // Exception table:
    //   from	to	target	type
    //   79	84	55	java/lang/Exception
  }
  
  /* Error */
  protected void onActivityResult(int paramInt1, int paramInt2, android.content.Intent paramIntent)
  {
    // Byte code:
    //   0: goto +45 -> 45
    //   3: iconst_0
    //   4: istore_1
    //   5: goto +121 -> 126
    //   8: return
    //   9: aload_3
    //   10: ifnull +6 -> 16
    //   13: goto +138 -> 151
    //   16: return
    //   17: return
    //   18: getstatic 39	o/l:ʾ	I
    //   21: bipush 71
    //   23: iadd
    //   24: istore_1
    //   25: iload_1
    //   26: sipush 128
    //   29: irem
    //   30: putstatic 37	o/l:ʼॱ	I
    //   33: iload_1
    //   34: iconst_2
    //   35: irem
    //   36: ifne +6 -> 42
    //   39: goto +496 -> 535
    //   42: goto +6 -> 48
    //   45: goto +64 -> 109
    //   48: iconst_0
    //   49: istore_1
    //   50: goto +457 -> 507
    //   53: getstatic 37	o/l:ʼॱ	I
    //   56: bipush 113
    //   58: iadd
    //   59: istore_1
    //   60: iload_1
    //   61: sipush 128
    //   64: irem
    //   65: putstatic 39	o/l:ʾ	I
    //   68: iload_1
    //   69: iconst_2
    //   70: irem
    //   71: ifeq +6 -> 77
    //   74: goto +422 -> 496
    //   77: goto +399 -> 476
    //   80: return
    //   81: iload_1
    //   82: lookupswitch	default:+26->108, 52:+-65->17, 91:+-74->8
    //   108: return
    //   109: aload_0
    //   110: iload_1
    //   111: iload_2
    //   112: aload_3
    //   113: invokespecial 502	o/ܖ:onActivityResult	(IILandroid/content/Intent;)V
    //   116: iload_1
    //   117: ifeq +6 -> 123
    //   120: goto -117 -> 3
    //   123: goto +379 -> 502
    //   126: iload_1
    //   127: tableswitch	default:+21->148, 0:+-109->18, 1:+-47->80
    //   148: goto -130 -> 18
    //   151: aload_0
    //   152: invokevirtual 508	java/lang/Object:getClass	()Ljava/lang/Class;
    //   155: astore 5
    //   157: new 510	java/lang/StringBuilder
    //   160: dup
    //   161: invokespecial 511	java/lang/StringBuilder:<init>	()V
    //   164: astore 6
    //   166: aload_0
    //   167: invokevirtual 93	android/content/Context:getPackageName	()Ljava/lang/String;
    //   170: astore 7
    //   172: aload 7
    //   174: invokevirtual 89	java/lang/String:length	()I
    //   177: istore_1
    //   178: iload_1
    //   179: sipush 18802
    //   182: iadd
    //   183: i2c
    //   184: istore 4
    //   186: aload_0
    //   187: invokevirtual 74	android/content/Context:getResources	()Landroid/content/res/Resources;
    //   190: astore 7
    //   192: aload 6
    //   194: iload 4
    //   196: aload 7
    //   198: ldc_w 512
    //   201: invokevirtual 81	android/content/res/Resources:getString	(I)Ljava/lang/String;
    //   204: iconst_0
    //   205: iconst_4
    //   206: invokevirtual 85	java/lang/String:substring	(II)Ljava/lang/String;
    //   209: invokevirtual 89	java/lang/String:length	()I
    //   212: bipush 46
    //   214: iadd
    //   215: aload_0
    //   216: invokevirtual 93	android/content/Context:getPackageName	()Ljava/lang/String;
    //   219: invokevirtual 89	java/lang/String:length	()I
    //   222: iconst_2
    //   223: isub
    //   224: invokestatic 104	o/l:ˋ	(CII)Ljava/lang/String;
    //   227: invokevirtual 107	java/lang/String:intern	()Ljava/lang/String;
    //   230: invokevirtual 516	java/lang/StringBuilder:append	(Ljava/lang/String;)Ljava/lang/StringBuilder;
    //   233: aload_0
    //   234: invokevirtual 508	java/lang/Object:getClass	()Ljava/lang/Class;
    //   237: invokevirtual 521	java/lang/Class:getSimpleName	()Ljava/lang/String;
    //   240: invokevirtual 516	java/lang/StringBuilder:append	(Ljava/lang/String;)Ljava/lang/StringBuilder;
    //   243: aload_0
    //   244: invokevirtual 93	android/content/Context:getPackageName	()Ljava/lang/String;
    //   247: bipush 9
    //   249: invokevirtual 114	java/lang/String:codePointAt	(I)I
    //   252: bipush 97
    //   254: isub
    //   255: i2c
    //   256: aload_0
    //   257: invokevirtual 74	android/content/Context:getResources	()Landroid/content/res/Resources;
    //   260: ldc_w 522
    //   263: invokevirtual 81	android/content/res/Resources:getString	(I)Ljava/lang/String;
    //   266: iconst_0
    //   267: iconst_5
    //   268: invokevirtual 85	java/lang/String:substring	(II)Ljava/lang/String;
    //   271: iconst_3
    //   272: invokevirtual 114	java/lang/String:codePointAt	(I)I
    //   275: bipush 82
    //   277: iadd
    //   278: aload_0
    //   279: invokevirtual 97	android/content/Context:getApplicationInfo	()Landroid/content/pm/ApplicationInfo;
    //   282: getfield 102	android/content/pm/ApplicationInfo:targetSdkVersion	I
    //   285: bipush 9
    //   287: iadd
    //   288: invokestatic 104	o/l:ˋ	(CII)Ljava/lang/String;
    //   291: invokevirtual 107	java/lang/String:intern	()Ljava/lang/String;
    //   294: invokevirtual 516	java/lang/StringBuilder:append	(Ljava/lang/String;)Ljava/lang/StringBuilder;
    //   297: iload_2
    //   298: invokevirtual 525	java/lang/StringBuilder:append	(I)Ljava/lang/StringBuilder;
    //   301: aload_0
    //   302: invokevirtual 74	android/content/Context:getResources	()Landroid/content/res/Resources;
    //   305: ldc_w 526
    //   308: invokevirtual 81	android/content/res/Resources:getString	(I)Ljava/lang/String;
    //   311: iconst_0
    //   312: iconst_4
    //   313: invokevirtual 85	java/lang/String:substring	(II)Ljava/lang/String;
    //   316: iconst_0
    //   317: invokevirtual 114	java/lang/String:codePointAt	(I)I
    //   320: iconst_5
    //   321: isub
    //   322: i2c
    //   323: aload_0
    //   324: invokevirtual 74	android/content/Context:getResources	()Landroid/content/res/Resources;
    //   327: ldc_w 527
    //   330: invokevirtual 81	android/content/res/Resources:getString	(I)Ljava/lang/String;
    //   333: iconst_0
    //   334: bipush 8
    //   336: invokevirtual 85	java/lang/String:substring	(II)Ljava/lang/String;
    //   339: invokevirtual 89	java/lang/String:length	()I
    //   342: bipush 120
    //   344: iadd
    //   345: aload_0
    //   346: invokevirtual 93	android/content/Context:getPackageName	()Ljava/lang/String;
    //   349: invokevirtual 89	java/lang/String:length	()I
    //   352: bipush 7
    //   354: iadd
    //   355: invokestatic 104	o/l:ˋ	(CII)Ljava/lang/String;
    //   358: invokevirtual 107	java/lang/String:intern	()Ljava/lang/String;
    //   361: invokevirtual 516	java/lang/StringBuilder:append	(Ljava/lang/String;)Ljava/lang/StringBuilder;
    //   364: aload_3
    //   365: invokevirtual 532	android/content/Intent:toString	()Ljava/lang/String;
    //   368: invokevirtual 516	java/lang/StringBuilder:append	(Ljava/lang/String;)Ljava/lang/StringBuilder;
    //   371: invokevirtual 533	java/lang/StringBuilder:toString	()Ljava/lang/String;
    //   374: astore_3
    //   375: goto +20 -> 395
    //   378: astore_3
    //   379: aload_3
    //   380: invokevirtual 539	java/lang/Throwable:getCause	()Ljava/lang/Throwable;
    //   383: astore 5
    //   385: aload 5
    //   387: ifnull +6 -> 393
    //   390: aload 5
    //   392: athrow
    //   393: aload_3
    //   394: athrow
    //   395: aload_0
    //   396: invokevirtual 97	android/content/Context:getApplicationInfo	()Landroid/content/pm/ApplicationInfo;
    //   399: getfield 102	android/content/pm/ApplicationInfo:targetSdkVersion	I
    //   402: bipush 21
    //   404: isub
    //   405: aload_0
    //   406: invokevirtual 97	android/content/Context:getApplicationInfo	()Landroid/content/pm/ApplicationInfo;
    //   409: getfield 102	android/content/pm/ApplicationInfo:targetSdkVersion	I
    //   412: bipush 17
    //   414: iadd
    //   415: aload_0
    //   416: invokevirtual 93	android/content/Context:getPackageName	()Ljava/lang/String;
    //   419: iconst_2
    //   420: invokevirtual 114	java/lang/String:codePointAt	(I)I
    //   423: ldc_w 540
    //   426: iadd
    //   427: i2c
    //   428: invokestatic 545	o/O:ˋ	(IIC)Ljava/lang/Object;
    //   431: checkcast 518	java/lang/Class
    //   434: ldc_w 547
    //   437: iconst_2
    //   438: anewarray 518	java/lang/Class
    //   441: dup
    //   442: iconst_0
    //   443: ldc_w 518
    //   446: aastore
    //   447: dup
    //   448: iconst_1
    //   449: ldc 53
    //   451: aastore
    //   452: invokevirtual 551	java/lang/Class:getMethod	(Ljava/lang/String;[Ljava/lang/Class;)Ljava/lang/reflect/Method;
    //   455: aconst_null
    //   456: iconst_2
    //   457: anewarray 504	java/lang/Object
    //   460: dup
    //   461: iconst_0
    //   462: aload 5
    //   464: aastore
    //   465: dup
    //   466: iconst_1
    //   467: aload_3
    //   468: aastore
    //   469: invokevirtual 557	java/lang/reflect/Method:invoke	(Ljava/lang/Object;[Ljava/lang/Object;)Ljava/lang/Object;
    //   472: pop
    //   473: goto -420 -> 53
    //   476: bipush 91
    //   478: istore_1
    //   479: goto -398 -> 81
    //   482: astore_3
    //   483: aload_3
    //   484: athrow
    //   485: aconst_null
    //   486: arraylength
    //   487: istore_1
    //   488: aload_3
    //   489: ifnull +6 -> 495
    //   492: goto -341 -> 151
    //   495: return
    //   496: bipush 52
    //   498: istore_1
    //   499: goto -418 -> 81
    //   502: iconst_1
    //   503: istore_1
    //   504: goto -378 -> 126
    //   507: iload_1
    //   508: tableswitch	default:+24->532, 0:+-499->9, 1:+-23->485
    //   532: goto -523 -> 9
    //   535: iconst_1
    //   536: istore_1
    //   537: goto -30 -> 507
    // Local variable table:
    //   start	length	slot	name	signature
    //   0	540	0	this	l
    //   0	540	1	paramInt1	int
    //   0	540	2	paramInt2	int
    //   0	540	3	paramIntent	android.content.Intent
    //   184	11	4	c	char
    //   155	308	5	localObject1	Object
    //   164	29	6	localStringBuilder	StringBuilder
    //   170	27	7	localObject2	Object
    // Exception table:
    //   from	to	target	type
    //   395	473	378	finally
    //   151	166	482	java/lang/Exception
    //   166	172	482	java/lang/Exception
    //   172	178	482	java/lang/Exception
    //   186	192	482	java/lang/Exception
    //   192	375	482	java/lang/Exception
    //   379	385	482	java/lang/Exception
    //   390	393	482	java/lang/Exception
    //   393	395	482	java/lang/Exception
  }
  
  public void onClick(View paramView)
  {
    break label164;
    int i = ʾ + 41;
    ʼॱ = i % 128;
    if (i % 2 != 0) {
      return;
    }
    label164:
    for (;;)
    {
      Toast.makeText(this, ˋ((char)(getApplicationInfo().targetSdkVersion + 4340), getApplicationInfo().targetSdkVersion + 243, getPackageName().length() + 2).intern() + paramView.getId() + ˋ((char)(getPackageName().length() + 54038), getResources().getString(2131755161).substring(0, 4).codePointAt(0) + 276, getResources().getString(2131755113).substring(0, 8).codePointAt(3) + 0).intern(), 1).show();
      break;
      return;
    }
  }
  
  /* Error */
  protected void onCreate(android.os.Bundle paramBundle)
  {
    // Byte code:
    //   0: goto +544 -> 544
    //   3: getstatic 37	o/l:ʼॱ	I
    //   6: bipush 21
    //   8: iadd
    //   9: istore_2
    //   10: iload_2
    //   11: sipush 128
    //   14: irem
    //   15: putstatic 39	o/l:ʾ	I
    //   18: iload_2
    //   19: iconst_2
    //   20: irem
    //   21: ifeq +6 -> 27
    //   24: goto +363 -> 387
    //   27: goto +602 -> 629
    //   30: bipush 99
    //   32: istore_2
    //   33: goto +601 -> 634
    //   36: aload_0
    //   37: invokevirtual 74	android/content/Context:getResources	()Landroid/content/res/Resources;
    //   40: ldc_w 579
    //   43: invokevirtual 81	android/content/res/Resources:getString	(I)Ljava/lang/String;
    //   46: iconst_0
    //   47: iconst_4
    //   48: invokevirtual 85	java/lang/String:substring	(II)Ljava/lang/String;
    //   51: iconst_1
    //   52: invokevirtual 114	java/lang/String:codePointAt	(I)I
    //   55: ldc_w 580
    //   58: iadd
    //   59: i2c
    //   60: aload_0
    //   61: invokevirtual 74	android/content/Context:getResources	()Landroid/content/res/Resources;
    //   64: ldc_w 581
    //   67: invokevirtual 81	android/content/res/Resources:getString	(I)Ljava/lang/String;
    //   70: bipush 6
    //   72: bipush 18
    //   74: invokevirtual 85	java/lang/String:substring	(II)Ljava/lang/String;
    //   77: bipush 7
    //   79: invokevirtual 114	java/lang/String:codePointAt	(I)I
    //   82: sipush 153
    //   85: isub
    //   86: aload_0
    //   87: invokevirtual 74	android/content/Context:getResources	()Landroid/content/res/Resources;
    //   90: ldc_w 582
    //   93: invokevirtual 81	android/content/res/Resources:getString	(I)Ljava/lang/String;
    //   96: bipush 11
    //   98: bipush 16
    //   100: invokevirtual 85	java/lang/String:substring	(II)Ljava/lang/String;
    //   103: invokevirtual 89	java/lang/String:length	()I
    //   106: bipush 12
    //   108: iadd
    //   109: invokestatic 104	o/l:ˋ	(CII)Ljava/lang/String;
    //   112: invokevirtual 107	java/lang/String:intern	()Ljava/lang/String;
    //   115: astore_1
    //   116: new 510	java/lang/StringBuilder
    //   119: dup
    //   120: invokespecial 511	java/lang/StringBuilder:<init>	()V
    //   123: aload_0
    //   124: invokevirtual 74	android/content/Context:getResources	()Landroid/content/res/Resources;
    //   127: ldc_w 583
    //   130: invokevirtual 81	android/content/res/Resources:getString	(I)Ljava/lang/String;
    //   133: bipush 58
    //   135: bipush 64
    //   137: invokevirtual 85	java/lang/String:substring	(II)Ljava/lang/String;
    //   140: invokevirtual 89	java/lang/String:length	()I
    //   143: sipush 18807
    //   146: iadd
    //   147: i2c
    //   148: aload_0
    //   149: invokevirtual 93	android/content/Context:getPackageName	()Ljava/lang/String;
    //   152: invokevirtual 89	java/lang/String:length	()I
    //   155: bipush 39
    //   157: iadd
    //   158: aload_0
    //   159: invokevirtual 93	android/content/Context:getPackageName	()Ljava/lang/String;
    //   162: iconst_2
    //   163: invokevirtual 114	java/lang/String:codePointAt	(I)I
    //   166: bipush 37
    //   168: isub
    //   169: invokestatic 104	o/l:ˋ	(CII)Ljava/lang/String;
    //   172: invokevirtual 107	java/lang/String:intern	()Ljava/lang/String;
    //   175: invokevirtual 516	java/lang/StringBuilder:append	(Ljava/lang/String;)Ljava/lang/StringBuilder;
    //   178: aload_0
    //   179: invokevirtual 508	java/lang/Object:getClass	()Ljava/lang/Class;
    //   182: invokevirtual 521	java/lang/Class:getSimpleName	()Ljava/lang/String;
    //   185: invokevirtual 516	java/lang/StringBuilder:append	(Ljava/lang/String;)Ljava/lang/StringBuilder;
    //   188: aload_0
    //   189: invokevirtual 74	android/content/Context:getResources	()Landroid/content/res/Resources;
    //   192: ldc_w 584
    //   195: invokevirtual 81	android/content/res/Resources:getString	(I)Ljava/lang/String;
    //   198: iconst_0
    //   199: iconst_4
    //   200: invokevirtual 85	java/lang/String:substring	(II)Ljava/lang/String;
    //   203: invokevirtual 89	java/lang/String:length	()I
    //   206: iconst_4
    //   207: isub
    //   208: i2c
    //   209: aload_0
    //   210: invokevirtual 74	android/content/Context:getResources	()Landroid/content/res/Resources;
    //   213: ldc_w 585
    //   216: invokevirtual 81	android/content/res/Resources:getString	(I)Ljava/lang/String;
    //   219: iconst_0
    //   220: iconst_4
    //   221: invokevirtual 85	java/lang/String:substring	(II)Ljava/lang/String;
    //   224: iconst_1
    //   225: invokevirtual 114	java/lang/String:codePointAt	(I)I
    //   228: bipush 33
    //   230: iadd
    //   231: aload_0
    //   232: invokevirtual 74	android/content/Context:getResources	()Landroid/content/res/Resources;
    //   235: ldc_w 586
    //   238: invokevirtual 81	android/content/res/Resources:getString	(I)Ljava/lang/String;
    //   241: iconst_0
    //   242: iconst_4
    //   243: invokevirtual 85	java/lang/String:substring	(II)Ljava/lang/String;
    //   246: invokevirtual 89	java/lang/String:length	()I
    //   249: bipush 8
    //   251: iadd
    //   252: invokestatic 104	o/l:ˋ	(CII)Ljava/lang/String;
    //   255: invokevirtual 107	java/lang/String:intern	()Ljava/lang/String;
    //   258: invokevirtual 516	java/lang/StringBuilder:append	(Ljava/lang/String;)Ljava/lang/StringBuilder;
    //   261: invokevirtual 533	java/lang/StringBuilder:toString	()Ljava/lang/String;
    //   264: astore 4
    //   266: goto +20 -> 286
    //   269: astore_1
    //   270: aload_1
    //   271: invokevirtual 539	java/lang/Throwable:getCause	()Ljava/lang/Throwable;
    //   274: astore 4
    //   276: aload 4
    //   278: ifnull +6 -> 284
    //   281: aload 4
    //   283: athrow
    //   284: aload_1
    //   285: athrow
    //   286: aload_0
    //   287: invokevirtual 74	android/content/Context:getResources	()Landroid/content/res/Resources;
    //   290: ldc_w 587
    //   293: invokevirtual 81	android/content/res/Resources:getString	(I)Ljava/lang/String;
    //   296: iconst_0
    //   297: iconst_5
    //   298: invokevirtual 85	java/lang/String:substring	(II)Ljava/lang/String;
    //   301: invokevirtual 89	java/lang/String:length	()I
    //   304: iconst_1
    //   305: isub
    //   306: aload_0
    //   307: invokevirtual 97	android/content/Context:getApplicationInfo	()Landroid/content/pm/ApplicationInfo;
    //   310: getfield 102	android/content/pm/ApplicationInfo:targetSdkVersion	I
    //   313: bipush 17
    //   315: iadd
    //   316: aload_0
    //   317: invokevirtual 74	android/content/Context:getResources	()Landroid/content/res/Resources;
    //   320: ldc_w 588
    //   323: invokevirtual 81	android/content/res/Resources:getString	(I)Ljava/lang/String;
    //   326: iconst_0
    //   327: iconst_4
    //   328: invokevirtual 85	java/lang/String:substring	(II)Ljava/lang/String;
    //   331: iconst_3
    //   332: invokevirtual 114	java/lang/String:codePointAt	(I)I
    //   335: ldc_w 589
    //   338: iadd
    //   339: i2c
    //   340: invokestatic 545	o/O:ˋ	(IIC)Ljava/lang/Object;
    //   343: checkcast 518	java/lang/Class
    //   346: ldc_w 591
    //   349: iconst_2
    //   350: anewarray 518	java/lang/Class
    //   353: dup
    //   354: iconst_0
    //   355: ldc 53
    //   357: aastore
    //   358: dup
    //   359: iconst_1
    //   360: ldc 53
    //   362: aastore
    //   363: invokevirtual 551	java/lang/Class:getMethod	(Ljava/lang/String;[Ljava/lang/Class;)Ljava/lang/reflect/Method;
    //   366: aconst_null
    //   367: iconst_2
    //   368: anewarray 504	java/lang/Object
    //   371: dup
    //   372: iconst_0
    //   373: aload_1
    //   374: aastore
    //   375: dup
    //   376: iconst_1
    //   377: aload 4
    //   379: aastore
    //   380: invokevirtual 557	java/lang/reflect/Method:invoke	(Ljava/lang/Object;[Ljava/lang/Object;)Ljava/lang/Object;
    //   383: pop
    //   384: goto -381 -> 3
    //   387: iconst_0
    //   388: istore_2
    //   389: iload_2
    //   390: tableswitch	default:+22->412, 0:+45->435, 1:+25->415
    //   412: goto +23 -> 435
    //   415: return
    //   416: aload_0
    //   417: iload_3
    //   418: invokestatic 596	o/ˌ:ˊ	(Landroid/app/Activity;I)Landroid/databinding/ViewDataBinding;
    //   421: astore_1
    //   422: aload_0
    //   423: aload_1
    //   424: putfield 598	o/l:ॱˊ	Landroid/databinding/ViewDataBinding;
    //   427: goto +14 -> 441
    //   430: iconst_1
    //   431: istore_2
    //   432: goto +139 -> 571
    //   435: bipush 95
    //   437: iconst_0
    //   438: idiv
    //   439: istore_2
    //   440: return
    //   441: aload_0
    //   442: invokevirtual 602	o/l:getIntent	()Landroid/content/Intent;
    //   445: aload_0
    //   446: invokevirtual 74	android/content/Context:getResources	()Landroid/content/res/Resources;
    //   449: ldc_w 603
    //   452: invokevirtual 81	android/content/res/Resources:getString	(I)Ljava/lang/String;
    //   455: iconst_0
    //   456: iconst_4
    //   457: invokevirtual 85	java/lang/String:substring	(II)Ljava/lang/String;
    //   460: iconst_2
    //   461: invokevirtual 114	java/lang/String:codePointAt	(I)I
    //   464: ldc_w 604
    //   467: iadd
    //   468: i2c
    //   469: aload_0
    //   470: invokevirtual 74	android/content/Context:getResources	()Landroid/content/res/Resources;
    //   473: ldc_w 605
    //   476: invokevirtual 81	android/content/res/Resources:getString	(I)Ljava/lang/String;
    //   479: iconst_0
    //   480: iconst_4
    //   481: invokevirtual 85	java/lang/String:substring	(II)Ljava/lang/String;
    //   484: invokevirtual 89	java/lang/String:length	()I
    //   487: iconst_4
    //   488: isub
    //   489: aload_0
    //   490: invokevirtual 74	android/content/Context:getResources	()Landroid/content/res/Resources;
    //   493: ldc_w 606
    //   496: invokevirtual 81	android/content/res/Resources:getString	(I)Ljava/lang/String;
    //   499: iconst_0
    //   500: iconst_5
    //   501: invokevirtual 85	java/lang/String:substring	(II)Ljava/lang/String;
    //   504: iconst_3
    //   505: invokevirtual 114	java/lang/String:codePointAt	(I)I
    //   508: bipush 21
    //   510: iadd
    //   511: invokestatic 104	o/l:ˋ	(CII)Ljava/lang/String;
    //   514: invokevirtual 107	java/lang/String:intern	()Ljava/lang/String;
    //   517: invokevirtual 610	android/content/Intent:hasExtra	(Ljava/lang/String;)Z
    //   520: ifeq +6 -> 526
    //   523: goto -493 -> 30
    //   526: goto +208 -> 734
    //   529: aload_0
    //   530: aload_0
    //   531: iload_3
    //   532: invokestatic 596	o/ˌ:ˊ	(Landroid/app/Activity;I)Landroid/databinding/ViewDataBinding;
    //   535: putfield 598	o/l:ॱˊ	Landroid/databinding/ViewDataBinding;
    //   538: aconst_null
    //   539: arraylength
    //   540: istore_2
    //   541: goto -100 -> 441
    //   544: goto +136 -> 680
    //   547: aload_0
    //   548: aload_1
    //   549: invokespecial 612	o/ܖ:onCreate	(Landroid/os/Bundle;)V
    //   552: iconst_1
    //   553: invokestatic 617	o/ڔ:ˎ	(Z)V
    //   556: aload_0
    //   557: invokevirtual 619	o/l:ˎ	()I
    //   560: istore_3
    //   561: iload_3
    //   562: ifeq +6 -> 568
    //   565: goto +142 -> 707
    //   568: goto -127 -> 441
    //   571: iload_2
    //   572: tableswitch	default:+24->596, 0:+-43->529, 1:+-156->416
    //   596: goto -180 -> 416
    //   599: astore_1
    //   600: aload_1
    //   601: athrow
    //   602: getstatic 39	o/l:ʾ	I
    //   605: bipush 33
    //   607: iadd
    //   608: istore_2
    //   609: iload_2
    //   610: sipush 128
    //   613: irem
    //   614: putstatic 37	o/l:ʼॱ	I
    //   617: iload_2
    //   618: iconst_2
    //   619: irem
    //   620: ifne +6 -> 626
    //   623: goto +122 -> 745
    //   626: goto +43 -> 669
    //   629: iconst_1
    //   630: istore_2
    //   631: goto -242 -> 389
    //   634: iload_2
    //   635: lookupswitch	default:+25->660, 51:+-599->36, 99:+-33->602
    //   660: goto -624 -> 36
    //   663: astore_1
    //   664: aload_1
    //   665: athrow
    //   666: goto -119 -> 547
    //   669: aload_0
    //   670: aload_0
    //   671: invokevirtual 623	o/l:getWindow	()Landroid/view/Window;
    //   674: invokevirtual 627	o/l:ॱ	(Landroid/view/Window;)V
    //   677: goto -641 -> 36
    //   680: getstatic 37	o/l:ʼॱ	I
    //   683: bipush 77
    //   685: iadd
    //   686: istore_2
    //   687: iload_2
    //   688: sipush 128
    //   691: irem
    //   692: putstatic 39	o/l:ʾ	I
    //   695: iload_2
    //   696: iconst_2
    //   697: irem
    //   698: ifeq +6 -> 704
    //   701: goto -35 -> 666
    //   704: goto -157 -> 547
    //   707: getstatic 39	o/l:ʾ	I
    //   710: bipush 83
    //   712: iadd
    //   713: istore_2
    //   714: iload_2
    //   715: sipush 128
    //   718: irem
    //   719: putstatic 37	o/l:ʼॱ	I
    //   722: iload_2
    //   723: iconst_2
    //   724: irem
    //   725: ifne +6 -> 731
    //   728: goto +12 -> 740
    //   731: goto -301 -> 430
    //   734: bipush 51
    //   736: istore_2
    //   737: goto -103 -> 634
    //   740: iconst_0
    //   741: istore_2
    //   742: goto -171 -> 571
    //   745: aload_0
    //   746: invokevirtual 623	o/l:getWindow	()Landroid/view/Window;
    //   749: astore_1
    //   750: aload_0
    //   751: aload_1
    //   752: invokevirtual 627	o/l:ॱ	(Landroid/view/Window;)V
    //   755: aconst_null
    //   756: arraylength
    //   757: istore_2
    //   758: goto -722 -> 36
    // Local variable table:
    //   start	length	slot	name	signature
    //   0	761	0	this	l
    //   0	761	1	paramBundle	android.os.Bundle
    //   9	749	2	i	int
    //   417	145	3	j	int
    //   264	114	4	localObject	Object
    // Exception table:
    //   from	to	target	type
    //   286	384	269	finally
    //   422	427	599	java/lang/Exception
    //   552	556	599	java/lang/Exception
    //   556	561	599	java/lang/Exception
    //   745	750	599	java/lang/Exception
    //   416	422	663	java/lang/Exception
    //   422	427	663	java/lang/Exception
  }
  
  /* Error */
  protected void onDestroy()
  {
    // Byte code:
    //   0: goto +35 -> 35
    //   3: iload_1
    //   4: lookupswitch	default:+28->32, 13:+34->38, 23:+65->69
    //   32: goto +6 -> 38
    //   35: goto +38 -> 73
    //   38: aconst_null
    //   39: arraylength
    //   40: istore_1
    //   41: return
    //   42: getstatic 37	o/l:ʼॱ	I
    //   45: bipush 9
    //   47: iadd
    //   48: istore_1
    //   49: iload_1
    //   50: sipush 128
    //   53: irem
    //   54: putstatic 39	o/l:ʾ	I
    //   57: iload_1
    //   58: iconst_2
    //   59: irem
    //   60: ifeq +6 -> 66
    //   63: goto +347 -> 410
    //   66: goto +350 -> 416
    //   69: return
    //   70: astore_2
    //   71: aload_2
    //   72: athrow
    //   73: aload_0
    //   74: invokespecial 630	o/ܖ:onDestroy	()V
    //   77: aload_0
    //   78: invokevirtual 93	android/content/Context:getPackageName	()Ljava/lang/String;
    //   81: bipush 8
    //   83: invokevirtual 114	java/lang/String:codePointAt	(I)I
    //   86: ldc_w 631
    //   89: iadd
    //   90: i2c
    //   91: aload_0
    //   92: invokevirtual 74	android/content/Context:getResources	()Landroid/content/res/Resources;
    //   95: ldc_w 632
    //   98: invokevirtual 81	android/content/res/Resources:getString	(I)Ljava/lang/String;
    //   101: iconst_0
    //   102: iconst_4
    //   103: invokevirtual 85	java/lang/String:substring	(II)Ljava/lang/String;
    //   106: iconst_1
    //   107: invokevirtual 114	java/lang/String:codePointAt	(I)I
    //   110: bipush 7
    //   112: iadd
    //   113: aload_0
    //   114: invokevirtual 93	android/content/Context:getPackageName	()Ljava/lang/String;
    //   117: invokevirtual 89	java/lang/String:length	()I
    //   120: bipush 6
    //   122: iadd
    //   123: invokestatic 104	o/l:ˋ	(CII)Ljava/lang/String;
    //   126: invokevirtual 107	java/lang/String:intern	()Ljava/lang/String;
    //   129: astore_2
    //   130: new 510	java/lang/StringBuilder
    //   133: dup
    //   134: invokespecial 511	java/lang/StringBuilder:<init>	()V
    //   137: aload_0
    //   138: invokevirtual 74	android/content/Context:getResources	()Landroid/content/res/Resources;
    //   141: ldc_w 633
    //   144: invokevirtual 81	android/content/res/Resources:getString	(I)Ljava/lang/String;
    //   147: bipush 11
    //   149: bipush 16
    //   151: invokevirtual 85	java/lang/String:substring	(II)Ljava/lang/String;
    //   154: iconst_3
    //   155: invokevirtual 114	java/lang/String:codePointAt	(I)I
    //   158: sipush 18575
    //   161: iadd
    //   162: i2c
    //   163: aload_0
    //   164: invokevirtual 74	android/content/Context:getResources	()Landroid/content/res/Resources;
    //   167: ldc_w 634
    //   170: invokevirtual 81	android/content/res/Resources:getString	(I)Ljava/lang/String;
    //   173: iconst_0
    //   174: bipush 9
    //   176: invokevirtual 85	java/lang/String:substring	(II)Ljava/lang/String;
    //   179: iconst_4
    //   180: invokevirtual 114	java/lang/String:codePointAt	(I)I
    //   183: sipush 204
    //   186: isub
    //   187: aload_0
    //   188: invokevirtual 97	android/content/Context:getApplicationInfo	()Landroid/content/pm/ApplicationInfo;
    //   191: getfield 102	android/content/pm/ApplicationInfo:targetSdkVersion	I
    //   194: bipush 16
    //   196: isub
    //   197: invokestatic 104	o/l:ˋ	(CII)Ljava/lang/String;
    //   200: invokevirtual 107	java/lang/String:intern	()Ljava/lang/String;
    //   203: invokevirtual 516	java/lang/StringBuilder:append	(Ljava/lang/String;)Ljava/lang/StringBuilder;
    //   206: aload_0
    //   207: invokevirtual 508	java/lang/Object:getClass	()Ljava/lang/Class;
    //   210: invokevirtual 521	java/lang/Class:getSimpleName	()Ljava/lang/String;
    //   213: invokevirtual 516	java/lang/StringBuilder:append	(Ljava/lang/String;)Ljava/lang/StringBuilder;
    //   216: aload_0
    //   217: invokevirtual 93	android/content/Context:getPackageName	()Ljava/lang/String;
    //   220: iconst_4
    //   221: invokevirtual 114	java/lang/String:codePointAt	(I)I
    //   224: bipush 116
    //   226: isub
    //   227: i2c
    //   228: aload_0
    //   229: invokevirtual 74	android/content/Context:getResources	()Landroid/content/res/Resources;
    //   232: ldc_w 635
    //   235: invokevirtual 81	android/content/res/Resources:getString	(I)Ljava/lang/String;
    //   238: iconst_0
    //   239: iconst_4
    //   240: invokevirtual 85	java/lang/String:substring	(II)Ljava/lang/String;
    //   243: iconst_2
    //   244: invokevirtual 114	java/lang/String:codePointAt	(I)I
    //   247: sipush 192
    //   250: iadd
    //   251: aload_0
    //   252: invokevirtual 74	android/content/Context:getResources	()Landroid/content/res/Resources;
    //   255: ldc_w 636
    //   258: invokevirtual 81	android/content/res/Resources:getString	(I)Ljava/lang/String;
    //   261: iconst_0
    //   262: bipush 11
    //   264: invokevirtual 85	java/lang/String:substring	(II)Ljava/lang/String;
    //   267: invokevirtual 89	java/lang/String:length	()I
    //   270: iconst_1
    //   271: isub
    //   272: invokestatic 104	o/l:ˋ	(CII)Ljava/lang/String;
    //   275: invokevirtual 107	java/lang/String:intern	()Ljava/lang/String;
    //   278: invokevirtual 516	java/lang/StringBuilder:append	(Ljava/lang/String;)Ljava/lang/StringBuilder;
    //   281: invokevirtual 533	java/lang/StringBuilder:toString	()Ljava/lang/String;
    //   284: astore_3
    //   285: goto +17 -> 302
    //   288: astore_2
    //   289: aload_2
    //   290: invokevirtual 539	java/lang/Throwable:getCause	()Ljava/lang/Throwable;
    //   293: astore_3
    //   294: aload_3
    //   295: ifnull +5 -> 300
    //   298: aload_3
    //   299: athrow
    //   300: aload_2
    //   301: athrow
    //   302: aload_0
    //   303: invokevirtual 74	android/content/Context:getResources	()Landroid/content/res/Resources;
    //   306: ldc_w 637
    //   309: invokevirtual 81	android/content/res/Resources:getString	(I)Ljava/lang/String;
    //   312: bipush 9
    //   314: bipush 18
    //   316: invokevirtual 85	java/lang/String:substring	(II)Ljava/lang/String;
    //   319: iconst_5
    //   320: invokevirtual 114	java/lang/String:codePointAt	(I)I
    //   323: sipush 240
    //   326: isub
    //   327: aload_0
    //   328: invokevirtual 93	android/content/Context:getPackageName	()Ljava/lang/String;
    //   331: iconst_4
    //   332: invokevirtual 114	java/lang/String:codePointAt	(I)I
    //   335: bipush 74
    //   337: isub
    //   338: aload_0
    //   339: invokevirtual 74	android/content/Context:getResources	()Landroid/content/res/Resources;
    //   342: ldc_w 638
    //   345: invokevirtual 81	android/content/res/Resources:getString	(I)Ljava/lang/String;
    //   348: iconst_0
    //   349: bipush 12
    //   351: invokevirtual 85	java/lang/String:substring	(II)Ljava/lang/String;
    //   354: bipush 8
    //   356: invokevirtual 114	java/lang/String:codePointAt	(I)I
    //   359: ldc_w 639
    //   362: iadd
    //   363: i2c
    //   364: invokestatic 545	o/O:ˋ	(IIC)Ljava/lang/Object;
    //   367: checkcast 518	java/lang/Class
    //   370: ldc_w 591
    //   373: iconst_2
    //   374: anewarray 518	java/lang/Class
    //   377: dup
    //   378: iconst_0
    //   379: ldc 53
    //   381: aastore
    //   382: dup
    //   383: iconst_1
    //   384: ldc 53
    //   386: aastore
    //   387: invokevirtual 551	java/lang/Class:getMethod	(Ljava/lang/String;[Ljava/lang/Class;)Ljava/lang/reflect/Method;
    //   390: aconst_null
    //   391: iconst_2
    //   392: anewarray 504	java/lang/Object
    //   395: dup
    //   396: iconst_0
    //   397: aload_2
    //   398: aastore
    //   399: dup
    //   400: iconst_1
    //   401: aload_3
    //   402: aastore
    //   403: invokevirtual 557	java/lang/reflect/Method:invoke	(Ljava/lang/Object;[Ljava/lang/Object;)Ljava/lang/Object;
    //   406: pop
    //   407: goto -365 -> 42
    //   410: bipush 13
    //   412: istore_1
    //   413: goto -410 -> 3
    //   416: bipush 23
    //   418: istore_1
    //   419: goto -416 -> 3
    // Local variable table:
    //   start	length	slot	name	signature
    //   0	422	0	this	l
    //   3	416	1	i	int
    //   70	2	2	localException	Exception
    //   129	1	2	str	String
    //   288	110	2	localObject1	Object
    //   284	118	3	localObject2	Object
    // Exception table:
    //   from	to	target	type
    //   42	49	70	java/lang/Exception
    //   49	57	70	java/lang/Exception
    //   302	407	288	finally
  }
  
  public void onFragmentInteraction(View paramView)
  {
    for (;;)
    {
      int i = ʼॱ + 65;
      ʾ = i % 128;
      if (i % 2 == 0) {
        return;
      } else {
        return;
      }
    }
  }
  
  /* Error */
  protected void onNewIntent(android.content.Intent paramIntent)
  {
    // Byte code:
    //   0: goto +87 -> 87
    //   3: aload_0
    //   4: aload_0
    //   5: invokevirtual 623	o/l:getWindow	()Landroid/view/Window;
    //   8: invokevirtual 627	o/l:ॱ	(Landroid/view/Window;)V
    //   11: goto +98 -> 109
    //   14: getstatic 39	o/l:ʾ	I
    //   17: bipush 87
    //   19: iadd
    //   20: istore_2
    //   21: iload_2
    //   22: sipush 128
    //   25: irem
    //   26: putstatic 37	o/l:ʼॱ	I
    //   29: iload_2
    //   30: iconst_2
    //   31: irem
    //   32: ifne +6 -> 38
    //   35: goto +55 -> 90
    //   38: return
    //   39: bipush 50
    //   41: istore_2
    //   42: goto +483 -> 525
    //   45: bipush 20
    //   47: istore_2
    //   48: goto +477 -> 525
    //   51: iconst_1
    //   52: istore_2
    //   53: goto +6 -> 59
    //   56: astore_1
    //   57: aload_1
    //   58: athrow
    //   59: iload_2
    //   60: tableswitch	default:+24->84, 0:+-57->3, 1:+34->94
    //   84: goto +10 -> 94
    //   87: goto +54 -> 141
    //   90: aconst_null
    //   91: arraylength
    //   92: istore_2
    //   93: return
    //   94: aload_0
    //   95: aload_0
    //   96: invokevirtual 623	o/l:getWindow	()Landroid/view/Window;
    //   99: invokevirtual 627	o/l:ॱ	(Landroid/view/Window;)V
    //   102: iconst_5
    //   103: iconst_0
    //   104: idiv
    //   105: istore_2
    //   106: goto +3 -> 109
    //   109: goto -95 -> 14
    //   112: getstatic 39	o/l:ʾ	I
    //   115: istore_2
    //   116: iload_2
    //   117: bipush 99
    //   119: iadd
    //   120: istore_2
    //   121: iload_2
    //   122: sipush 128
    //   125: irem
    //   126: putstatic 37	o/l:ʼॱ	I
    //   129: iload_2
    //   130: iconst_2
    //   131: irem
    //   132: ifne +6 -> 138
    //   135: goto -84 -> 51
    //   138: goto +417 -> 555
    //   141: aload_0
    //   142: aload_1
    //   143: invokespecial 644	o/ܖ:onNewIntent	(Landroid/content/Intent;)V
    //   146: aload_0
    //   147: invokevirtual 74	android/content/Context:getResources	()Landroid/content/res/Resources;
    //   150: ldc_w 645
    //   153: invokevirtual 81	android/content/res/Resources:getString	(I)Ljava/lang/String;
    //   156: iconst_0
    //   157: bipush 8
    //   159: invokevirtual 85	java/lang/String:substring	(II)Ljava/lang/String;
    //   162: invokevirtual 89	java/lang/String:length	()I
    //   165: ldc_w 646
    //   168: iadd
    //   169: i2c
    //   170: aload_0
    //   171: invokevirtual 93	android/content/Context:getPackageName	()Ljava/lang/String;
    //   174: iconst_5
    //   175: invokevirtual 114	java/lang/String:codePointAt	(I)I
    //   178: bipush 81
    //   180: isub
    //   181: aload_0
    //   182: invokevirtual 97	android/content/Context:getApplicationInfo	()Landroid/content/pm/ApplicationInfo;
    //   185: getfield 102	android/content/pm/ApplicationInfo:targetSdkVersion	I
    //   188: bipush 8
    //   190: isub
    //   191: invokestatic 104	o/l:ˋ	(CII)Ljava/lang/String;
    //   194: invokevirtual 107	java/lang/String:intern	()Ljava/lang/String;
    //   197: astore_3
    //   198: new 510	java/lang/StringBuilder
    //   201: dup
    //   202: invokespecial 511	java/lang/StringBuilder:<init>	()V
    //   205: aload_0
    //   206: invokevirtual 74	android/content/Context:getResources	()Landroid/content/res/Resources;
    //   209: ldc_w 647
    //   212: invokevirtual 81	android/content/res/Resources:getString	(I)Ljava/lang/String;
    //   215: iconst_5
    //   216: bipush 7
    //   218: invokevirtual 85	java/lang/String:substring	(II)Ljava/lang/String;
    //   221: invokevirtual 89	java/lang/String:length	()I
    //   224: sipush 18811
    //   227: iadd
    //   228: i2c
    //   229: aload_0
    //   230: invokevirtual 93	android/content/Context:getPackageName	()Ljava/lang/String;
    //   233: bipush 7
    //   235: invokevirtual 114	java/lang/String:codePointAt	(I)I
    //   238: iconst_4
    //   239: iadd
    //   240: aload_0
    //   241: invokevirtual 74	android/content/Context:getResources	()Landroid/content/res/Resources;
    //   244: ldc_w 648
    //   247: invokevirtual 81	android/content/res/Resources:getString	(I)Ljava/lang/String;
    //   250: iconst_0
    //   251: iconst_4
    //   252: invokevirtual 85	java/lang/String:substring	(II)Ljava/lang/String;
    //   255: iconst_3
    //   256: invokevirtual 114	java/lang/String:codePointAt	(I)I
    //   259: iconst_3
    //   260: isub
    //   261: invokestatic 104	o/l:ˋ	(CII)Ljava/lang/String;
    //   264: invokevirtual 107	java/lang/String:intern	()Ljava/lang/String;
    //   267: invokevirtual 516	java/lang/StringBuilder:append	(Ljava/lang/String;)Ljava/lang/StringBuilder;
    //   270: aload_0
    //   271: invokevirtual 508	java/lang/Object:getClass	()Ljava/lang/Class;
    //   274: invokevirtual 521	java/lang/Class:getSimpleName	()Ljava/lang/String;
    //   277: invokevirtual 516	java/lang/StringBuilder:append	(Ljava/lang/String;)Ljava/lang/StringBuilder;
    //   280: aload_0
    //   281: invokevirtual 97	android/content/Context:getApplicationInfo	()Landroid/content/pm/ApplicationInfo;
    //   284: getfield 102	android/content/pm/ApplicationInfo:targetSdkVersion	I
    //   287: bipush 25
    //   289: isub
    //   290: i2c
    //   291: aload_0
    //   292: invokevirtual 74	android/content/Context:getResources	()Landroid/content/res/Resources;
    //   295: ldc_w 649
    //   298: invokevirtual 81	android/content/res/Resources:getString	(I)Ljava/lang/String;
    //   301: bipush 19
    //   303: bipush 30
    //   305: invokevirtual 85	java/lang/String:substring	(II)Ljava/lang/String;
    //   308: invokevirtual 89	java/lang/String:length	()I
    //   311: bipush 60
    //   313: iadd
    //   314: aload_0
    //   315: invokevirtual 97	android/content/Context:getApplicationInfo	()Landroid/content/pm/ApplicationInfo;
    //   318: getfield 102	android/content/pm/ApplicationInfo:targetSdkVersion	I
    //   321: iconst_2
    //   322: isub
    //   323: invokestatic 104	o/l:ˋ	(CII)Ljava/lang/String;
    //   326: invokevirtual 107	java/lang/String:intern	()Ljava/lang/String;
    //   329: invokevirtual 516	java/lang/StringBuilder:append	(Ljava/lang/String;)Ljava/lang/StringBuilder;
    //   332: invokevirtual 533	java/lang/StringBuilder:toString	()Ljava/lang/String;
    //   335: astore 4
    //   337: goto +17 -> 354
    //   340: astore_1
    //   341: aload_1
    //   342: invokevirtual 539	java/lang/Throwable:getCause	()Ljava/lang/Throwable;
    //   345: astore_3
    //   346: aload_3
    //   347: ifnull +5 -> 352
    //   350: aload_3
    //   351: athrow
    //   352: aload_1
    //   353: athrow
    //   354: aload_0
    //   355: invokevirtual 74	android/content/Context:getResources	()Landroid/content/res/Resources;
    //   358: ldc_w 650
    //   361: invokevirtual 81	android/content/res/Resources:getString	(I)Ljava/lang/String;
    //   364: iconst_0
    //   365: iconst_1
    //   366: invokevirtual 85	java/lang/String:substring	(II)Ljava/lang/String;
    //   369: invokevirtual 89	java/lang/String:length	()I
    //   372: iconst_3
    //   373: iadd
    //   374: aload_0
    //   375: invokevirtual 97	android/content/Context:getApplicationInfo	()Landroid/content/pm/ApplicationInfo;
    //   378: getfield 102	android/content/pm/ApplicationInfo:targetSdkVersion	I
    //   381: bipush 17
    //   383: iadd
    //   384: aload_0
    //   385: invokevirtual 74	android/content/Context:getResources	()Landroid/content/res/Resources;
    //   388: ldc_w 651
    //   391: invokevirtual 81	android/content/res/Resources:getString	(I)Ljava/lang/String;
    //   394: iconst_0
    //   395: iconst_5
    //   396: invokevirtual 85	java/lang/String:substring	(II)Ljava/lang/String;
    //   399: iconst_0
    //   400: invokevirtual 114	java/lang/String:codePointAt	(I)I
    //   403: ldc_w 652
    //   406: iadd
    //   407: i2c
    //   408: invokestatic 545	o/O:ˋ	(IIC)Ljava/lang/Object;
    //   411: checkcast 518	java/lang/Class
    //   414: ldc_w 591
    //   417: iconst_2
    //   418: anewarray 518	java/lang/Class
    //   421: dup
    //   422: iconst_0
    //   423: ldc 53
    //   425: aastore
    //   426: dup
    //   427: iconst_1
    //   428: ldc 53
    //   430: aastore
    //   431: invokevirtual 551	java/lang/Class:getMethod	(Ljava/lang/String;[Ljava/lang/Class;)Ljava/lang/reflect/Method;
    //   434: aconst_null
    //   435: iconst_2
    //   436: anewarray 504	java/lang/Object
    //   439: dup
    //   440: iconst_0
    //   441: aload_3
    //   442: aastore
    //   443: dup
    //   444: iconst_1
    //   445: aload 4
    //   447: aastore
    //   448: invokevirtual 557	java/lang/reflect/Method:invoke	(Ljava/lang/Object;[Ljava/lang/Object;)Ljava/lang/Object;
    //   451: pop
    //   452: aload_1
    //   453: aload_0
    //   454: invokevirtual 74	android/content/Context:getResources	()Landroid/content/res/Resources;
    //   457: ldc_w 653
    //   460: invokevirtual 81	android/content/res/Resources:getString	(I)Ljava/lang/String;
    //   463: iconst_0
    //   464: iconst_4
    //   465: invokevirtual 85	java/lang/String:substring	(II)Ljava/lang/String;
    //   468: invokevirtual 89	java/lang/String:length	()I
    //   471: ldc_w 654
    //   474: iadd
    //   475: i2c
    //   476: aload_0
    //   477: invokevirtual 74	android/content/Context:getResources	()Landroid/content/res/Resources;
    //   480: ldc_w 655
    //   483: invokevirtual 81	android/content/res/Resources:getString	(I)Ljava/lang/String;
    //   486: iconst_0
    //   487: iconst_4
    //   488: invokevirtual 85	java/lang/String:substring	(II)Ljava/lang/String;
    //   491: iconst_0
    //   492: invokevirtual 114	java/lang/String:codePointAt	(I)I
    //   495: iconst_5
    //   496: isub
    //   497: aload_0
    //   498: invokevirtual 93	android/content/Context:getPackageName	()Ljava/lang/String;
    //   501: invokevirtual 89	java/lang/String:length	()I
    //   504: bipush 22
    //   506: iadd
    //   507: invokestatic 104	o/l:ˋ	(CII)Ljava/lang/String;
    //   510: invokevirtual 107	java/lang/String:intern	()Ljava/lang/String;
    //   513: invokevirtual 610	android/content/Intent:hasExtra	(Ljava/lang/String;)Z
    //   516: ifeq +6 -> 522
    //   519: goto -480 -> 39
    //   522: goto -477 -> 45
    //   525: iload_2
    //   526: lookupswitch	default:+26->552, 20:+-417->109, 50:+-414->112
    //   552: goto -440 -> 112
    //   555: iconst_0
    //   556: istore_2
    //   557: goto -498 -> 59
    //   560: astore_1
    //   561: aload_1
    //   562: athrow
    // Local variable table:
    //   start	length	slot	name	signature
    //   0	563	0	this	l
    //   0	563	1	paramIntent	android.content.Intent
    //   20	537	2	i	int
    //   197	245	3	localObject	Object
    //   335	111	4	str	String
    // Exception table:
    //   from	to	target	type
    //   121	129	56	java/lang/Exception
    //   354	452	340	finally
    //   112	116	560	java/lang/Exception
  }
  
  /* Error */
  public boolean onOptionsItemSelected(android.view.MenuItem paramMenuItem)
  {
    // Byte code:
    //   0: goto +339 -> 339
    //   3: goto +342 -> 345
    //   6: aload_0
    //   7: invokevirtual 74	android/content/Context:getResources	()Landroid/content/res/Resources;
    //   10: ldc_w 658
    //   13: invokevirtual 81	android/content/res/Resources:getString	(I)Ljava/lang/String;
    //   16: iconst_0
    //   17: iconst_5
    //   18: invokevirtual 85	java/lang/String:substring	(II)Ljava/lang/String;
    //   21: iconst_1
    //   22: invokevirtual 114	java/lang/String:codePointAt	(I)I
    //   25: sipush 6779
    //   28: iadd
    //   29: i2c
    //   30: aload_0
    //   31: invokevirtual 74	android/content/Context:getResources	()Landroid/content/res/Resources;
    //   34: ldc_w 659
    //   37: invokevirtual 81	android/content/res/Resources:getString	(I)Ljava/lang/String;
    //   40: iconst_0
    //   41: iconst_4
    //   42: invokevirtual 85	java/lang/String:substring	(II)Ljava/lang/String;
    //   45: invokevirtual 89	java/lang/String:length	()I
    //   48: sipush 227
    //   51: iadd
    //   52: aload_0
    //   53: invokevirtual 97	android/content/Context:getApplicationInfo	()Landroid/content/pm/ApplicationInfo;
    //   56: getfield 102	android/content/pm/ApplicationInfo:targetSdkVersion	I
    //   59: bipush 18
    //   61: isub
    //   62: invokestatic 104	o/l:ˋ	(CII)Ljava/lang/String;
    //   65: invokevirtual 107	java/lang/String:intern	()Ljava/lang/String;
    //   68: astore 4
    //   70: new 510	java/lang/StringBuilder
    //   73: dup
    //   74: invokespecial 511	java/lang/StringBuilder:<init>	()V
    //   77: aload_0
    //   78: invokevirtual 74	android/content/Context:getResources	()Landroid/content/res/Resources;
    //   81: ldc_w 660
    //   84: invokevirtual 81	android/content/res/Resources:getString	(I)Ljava/lang/String;
    //   87: bipush 33
    //   89: bipush 34
    //   91: invokevirtual 85	java/lang/String:substring	(II)Ljava/lang/String;
    //   94: iconst_0
    //   95: invokevirtual 114	java/lang/String:codePointAt	(I)I
    //   98: bipush 108
    //   100: isub
    //   101: i2c
    //   102: aload_0
    //   103: invokevirtual 97	android/content/Context:getApplicationInfo	()Landroid/content/pm/ApplicationInfo;
    //   106: getfield 102	android/content/pm/ApplicationInfo:targetSdkVersion	I
    //   109: sipush 213
    //   112: iadd
    //   113: aload_0
    //   114: invokevirtual 97	android/content/Context:getApplicationInfo	()Landroid/content/pm/ApplicationInfo;
    //   117: getfield 102	android/content/pm/ApplicationInfo:targetSdkVersion	I
    //   120: iconst_5
    //   121: iadd
    //   122: invokestatic 104	o/l:ˋ	(CII)Ljava/lang/String;
    //   125: invokevirtual 107	java/lang/String:intern	()Ljava/lang/String;
    //   128: invokevirtual 516	java/lang/StringBuilder:append	(Ljava/lang/String;)Ljava/lang/StringBuilder;
    //   131: aload_3
    //   132: invokevirtual 516	java/lang/StringBuilder:append	(Ljava/lang/String;)Ljava/lang/StringBuilder;
    //   135: invokevirtual 533	java/lang/StringBuilder:toString	()Ljava/lang/String;
    //   138: astore_3
    //   139: goto +17 -> 156
    //   142: astore_1
    //   143: aload_1
    //   144: invokevirtual 539	java/lang/Throwable:getCause	()Ljava/lang/Throwable;
    //   147: astore_3
    //   148: aload_3
    //   149: ifnull +5 -> 154
    //   152: aload_3
    //   153: athrow
    //   154: aload_1
    //   155: athrow
    //   156: aload_0
    //   157: invokevirtual 74	android/content/Context:getResources	()Landroid/content/res/Resources;
    //   160: ldc_w 661
    //   163: invokevirtual 81	android/content/res/Resources:getString	(I)Ljava/lang/String;
    //   166: iconst_0
    //   167: bipush 17
    //   169: invokevirtual 85	java/lang/String:substring	(II)Ljava/lang/String;
    //   172: invokevirtual 89	java/lang/String:length	()I
    //   175: bipush 13
    //   177: isub
    //   178: aload_0
    //   179: invokevirtual 74	android/content/Context:getResources	()Landroid/content/res/Resources;
    //   182: ldc_w 662
    //   185: invokevirtual 81	android/content/res/Resources:getString	(I)Ljava/lang/String;
    //   188: iconst_0
    //   189: iconst_4
    //   190: invokevirtual 85	java/lang/String:substring	(II)Ljava/lang/String;
    //   193: iconst_1
    //   194: invokevirtual 114	java/lang/String:codePointAt	(I)I
    //   197: bipush 16
    //   199: iadd
    //   200: aload_0
    //   201: invokevirtual 97	android/content/Context:getApplicationInfo	()Landroid/content/pm/ApplicationInfo;
    //   204: getfield 102	android/content/pm/ApplicationInfo:targetSdkVersion	I
    //   207: ldc_w 663
    //   210: iadd
    //   211: i2c
    //   212: invokestatic 545	o/O:ˋ	(IIC)Ljava/lang/Object;
    //   215: checkcast 518	java/lang/Class
    //   218: ldc_w 591
    //   221: iconst_2
    //   222: anewarray 518	java/lang/Class
    //   225: dup
    //   226: iconst_0
    //   227: ldc 53
    //   229: aastore
    //   230: dup
    //   231: iconst_1
    //   232: ldc 53
    //   234: aastore
    //   235: invokevirtual 551	java/lang/Class:getMethod	(Ljava/lang/String;[Ljava/lang/Class;)Ljava/lang/reflect/Method;
    //   238: aconst_null
    //   239: iconst_2
    //   240: anewarray 504	java/lang/Object
    //   243: dup
    //   244: iconst_0
    //   245: aload 4
    //   247: aastore
    //   248: dup
    //   249: iconst_1
    //   250: aload_3
    //   251: aastore
    //   252: invokevirtual 557	java/lang/reflect/Method:invoke	(Ljava/lang/Object;[Ljava/lang/Object;)Ljava/lang/Object;
    //   255: pop
    //   256: aload_1
    //   257: invokeinterface 668 1 0
    //   262: lookupswitch	default:+18->280, 16908332:+153->415
    //   280: goto +38 -> 318
    //   283: iload_2
    //   284: tableswitch	default:+24->308, 0:+40->324, 1:+27->311
    //   308: goto +16 -> 324
    //   311: ldc_w 670
    //   314: astore_3
    //   315: goto -309 -> 6
    //   318: aload_0
    //   319: aload_1
    //   320: invokespecial 672	o/ܖ:onOptionsItemSelected	(Landroid/view/MenuItem;)Z
    //   323: ireturn
    //   324: aload_1
    //   325: invokeinterface 676 1 0
    //   330: invokeinterface 679 1 0
    //   335: astore_3
    //   336: goto +52 -> 388
    //   339: goto +17 -> 356
    //   342: goto +80 -> 422
    //   345: goto -339 -> 6
    //   348: astore_1
    //   349: aload_1
    //   350: athrow
    //   351: iconst_1
    //   352: istore_2
    //   353: goto -70 -> 283
    //   356: getstatic 37	o/l:ʼॱ	I
    //   359: bipush 55
    //   361: iadd
    //   362: istore_2
    //   363: iload_2
    //   364: sipush 128
    //   367: irem
    //   368: putstatic 39	o/l:ʾ	I
    //   371: iload_2
    //   372: iconst_2
    //   373: irem
    //   374: ifeq +6 -> 380
    //   377: goto -35 -> 342
    //   380: goto +42 -> 422
    //   383: iconst_0
    //   384: istore_2
    //   385: goto -102 -> 283
    //   388: getstatic 39	o/l:ʾ	I
    //   391: bipush 21
    //   393: iadd
    //   394: istore_2
    //   395: iload_2
    //   396: sipush 128
    //   399: irem
    //   400: putstatic 37	o/l:ʼॱ	I
    //   403: iload_2
    //   404: iconst_2
    //   405: irem
    //   406: ifne +6 -> 412
    //   409: goto -406 -> 3
    //   412: goto -67 -> 345
    //   415: aload_0
    //   416: invokevirtual 682	o/l:onBackPressed	()V
    //   419: goto -101 -> 318
    //   422: aload_1
    //   423: invokeinterface 676 1 0
    //   428: invokestatic 688	android/text/TextUtils:isEmpty	(Ljava/lang/CharSequence;)Z
    //   431: ifeq +6 -> 437
    //   434: goto -83 -> 351
    //   437: goto -54 -> 383
    // Local variable table:
    //   start	length	slot	name	signature
    //   0	440	0	this	l
    //   0	440	1	paramMenuItem	android.view.MenuItem
    //   283	123	2	i	int
    //   131	205	3	localObject	Object
    //   68	178	4	str	String
    // Exception table:
    //   from	to	target	type
    //   156	256	142	finally
    //   356	363	348	java/lang/Exception
    //   363	371	348	java/lang/Exception
  }
  
  /* Error */
  protected void onPause()
  {
    // Byte code:
    //   0: goto +628 -> 628
    //   3: iconst_1
    //   4: istore_1
    //   5: goto +330 -> 335
    //   8: iconst_0
    //   9: istore_1
    //   10: goto +325 -> 335
    //   13: aload_0
    //   14: iload_2
    //   15: putfield 691	o/l:ॱᐝ	Z
    //   18: aload_0
    //   19: invokespecial 693	o/ܖ:onPause	()V
    //   22: aload_0
    //   23: invokevirtual 74	android/content/Context:getResources	()Landroid/content/res/Resources;
    //   26: ldc_w 694
    //   29: invokevirtual 81	android/content/res/Resources:getString	(I)Ljava/lang/String;
    //   32: iconst_0
    //   33: iconst_4
    //   34: invokevirtual 85	java/lang/String:substring	(II)Ljava/lang/String;
    //   37: iconst_2
    //   38: invokevirtual 114	java/lang/String:codePointAt	(I)I
    //   41: ldc_w 695
    //   44: iadd
    //   45: i2c
    //   46: aload_0
    //   47: invokevirtual 74	android/content/Context:getResources	()Landroid/content/res/Resources;
    //   50: ldc_w 696
    //   53: invokevirtual 81	android/content/res/Resources:getString	(I)Ljava/lang/String;
    //   56: iconst_0
    //   57: bipush 22
    //   59: invokevirtual 85	java/lang/String:substring	(II)Ljava/lang/String;
    //   62: invokevirtual 89	java/lang/String:length	()I
    //   65: bipush 11
    //   67: iadd
    //   68: aload_0
    //   69: invokevirtual 74	android/content/Context:getResources	()Landroid/content/res/Resources;
    //   72: ldc_w 697
    //   75: invokevirtual 81	android/content/res/Resources:getString	(I)Ljava/lang/String;
    //   78: iconst_0
    //   79: iconst_4
    //   80: invokevirtual 85	java/lang/String:substring	(II)Ljava/lang/String;
    //   83: iconst_1
    //   84: invokevirtual 114	java/lang/String:codePointAt	(I)I
    //   87: bipush 9
    //   89: isub
    //   90: invokestatic 104	o/l:ˋ	(CII)Ljava/lang/String;
    //   93: invokevirtual 107	java/lang/String:intern	()Ljava/lang/String;
    //   96: astore_3
    //   97: new 510	java/lang/StringBuilder
    //   100: dup
    //   101: invokespecial 511	java/lang/StringBuilder:<init>	()V
    //   104: aload_0
    //   105: invokevirtual 93	android/content/Context:getPackageName	()Ljava/lang/String;
    //   108: invokevirtual 89	java/lang/String:length	()I
    //   111: sipush 18802
    //   114: iadd
    //   115: i2c
    //   116: aload_0
    //   117: invokevirtual 97	android/content/Context:getApplicationInfo	()Landroid/content/pm/ApplicationInfo;
    //   120: getfield 102	android/content/pm/ApplicationInfo:targetSdkVersion	I
    //   123: bipush 25
    //   125: iadd
    //   126: aload_0
    //   127: invokevirtual 93	android/content/Context:getPackageName	()Ljava/lang/String;
    //   130: iconst_4
    //   131: invokevirtual 114	java/lang/String:codePointAt	(I)I
    //   134: bipush 107
    //   136: isub
    //   137: invokestatic 104	o/l:ˋ	(CII)Ljava/lang/String;
    //   140: invokevirtual 107	java/lang/String:intern	()Ljava/lang/String;
    //   143: invokevirtual 516	java/lang/StringBuilder:append	(Ljava/lang/String;)Ljava/lang/StringBuilder;
    //   146: aload_0
    //   147: invokevirtual 508	java/lang/Object:getClass	()Ljava/lang/Class;
    //   150: invokevirtual 521	java/lang/Class:getSimpleName	()Ljava/lang/String;
    //   153: invokevirtual 516	java/lang/StringBuilder:append	(Ljava/lang/String;)Ljava/lang/StringBuilder;
    //   156: aload_0
    //   157: invokevirtual 74	android/content/Context:getResources	()Landroid/content/res/Resources;
    //   160: ldc_w 698
    //   163: invokevirtual 81	android/content/res/Resources:getString	(I)Ljava/lang/String;
    //   166: iconst_0
    //   167: iconst_4
    //   168: invokevirtual 85	java/lang/String:substring	(II)Ljava/lang/String;
    //   171: invokevirtual 89	java/lang/String:length	()I
    //   174: iconst_4
    //   175: isub
    //   176: i2c
    //   177: aload_0
    //   178: invokevirtual 93	android/content/Context:getPackageName	()Ljava/lang/String;
    //   181: invokevirtual 89	java/lang/String:length	()I
    //   184: sipush 163
    //   187: iadd
    //   188: aload_0
    //   189: invokevirtual 93	android/content/Context:getPackageName	()Ljava/lang/String;
    //   192: bipush 7
    //   194: invokevirtual 114	java/lang/String:codePointAt	(I)I
    //   197: bipush 25
    //   199: isub
    //   200: invokestatic 104	o/l:ˋ	(CII)Ljava/lang/String;
    //   203: invokevirtual 107	java/lang/String:intern	()Ljava/lang/String;
    //   206: invokevirtual 516	java/lang/StringBuilder:append	(Ljava/lang/String;)Ljava/lang/StringBuilder;
    //   209: invokevirtual 533	java/lang/StringBuilder:toString	()Ljava/lang/String;
    //   212: astore 4
    //   214: goto +20 -> 234
    //   217: astore_3
    //   218: aload_3
    //   219: invokevirtual 539	java/lang/Throwable:getCause	()Ljava/lang/Throwable;
    //   222: astore 4
    //   224: aload 4
    //   226: ifnull +6 -> 232
    //   229: aload 4
    //   231: athrow
    //   232: aload_3
    //   233: athrow
    //   234: aload_0
    //   235: invokevirtual 74	android/content/Context:getResources	()Landroid/content/res/Resources;
    //   238: ldc_w 699
    //   241: invokevirtual 81	android/content/res/Resources:getString	(I)Ljava/lang/String;
    //   244: iconst_0
    //   245: iconst_4
    //   246: invokevirtual 85	java/lang/String:substring	(II)Ljava/lang/String;
    //   249: invokevirtual 89	java/lang/String:length	()I
    //   252: iconst_0
    //   253: iadd
    //   254: aload_0
    //   255: invokevirtual 93	android/content/Context:getPackageName	()Ljava/lang/String;
    //   258: invokevirtual 89	java/lang/String:length	()I
    //   261: bipush 31
    //   263: iadd
    //   264: aload_0
    //   265: invokevirtual 74	android/content/Context:getResources	()Landroid/content/res/Resources;
    //   268: ldc_w 700
    //   271: invokevirtual 81	android/content/res/Resources:getString	(I)Ljava/lang/String;
    //   274: iconst_0
    //   275: iconst_4
    //   276: invokevirtual 85	java/lang/String:substring	(II)Ljava/lang/String;
    //   279: iconst_2
    //   280: invokevirtual 114	java/lang/String:codePointAt	(I)I
    //   283: ldc_w 701
    //   286: iadd
    //   287: i2c
    //   288: invokestatic 545	o/O:ˋ	(IIC)Ljava/lang/Object;
    //   291: checkcast 518	java/lang/Class
    //   294: ldc_w 591
    //   297: iconst_2
    //   298: anewarray 518	java/lang/Class
    //   301: dup
    //   302: iconst_0
    //   303: ldc 53
    //   305: aastore
    //   306: dup
    //   307: iconst_1
    //   308: ldc 53
    //   310: aastore
    //   311: invokevirtual 551	java/lang/Class:getMethod	(Ljava/lang/String;[Ljava/lang/Class;)Ljava/lang/reflect/Method;
    //   314: aconst_null
    //   315: iconst_2
    //   316: anewarray 504	java/lang/Object
    //   319: dup
    //   320: iconst_0
    //   321: aload_3
    //   322: aastore
    //   323: dup
    //   324: iconst_1
    //   325: aload 4
    //   327: aastore
    //   328: invokevirtual 557	java/lang/reflect/Method:invoke	(Ljava/lang/Object;[Ljava/lang/Object;)Ljava/lang/Object;
    //   331: pop
    //   332: goto +66 -> 398
    //   335: iload_1
    //   336: tableswitch	default:+24->360, 0:+286->622, 1:+57->393
    //   360: goto +262 -> 622
    //   363: astore_3
    //   364: aload_3
    //   365: athrow
    //   366: getstatic 37	o/l:ʼॱ	I
    //   369: bipush 37
    //   371: iadd
    //   372: istore_1
    //   373: iload_1
    //   374: sipush 128
    //   377: irem
    //   378: putstatic 39	o/l:ʾ	I
    //   381: iload_1
    //   382: iconst_2
    //   383: irem
    //   384: ifeq +6 -> 390
    //   387: goto +232 -> 619
    //   390: goto +33 -> 423
    //   393: iconst_0
    //   394: istore_2
    //   395: goto -382 -> 13
    //   398: getstatic 39	o/l:ʾ	I
    //   401: bipush 63
    //   403: iadd
    //   404: istore_1
    //   405: iload_1
    //   406: sipush 128
    //   409: irem
    //   410: putstatic 37	o/l:ʼॱ	I
    //   413: iload_1
    //   414: iconst_2
    //   415: irem
    //   416: ifne +6 -> 422
    //   419: goto +208 -> 627
    //   422: return
    //   423: aload_0
    //   424: iconst_0
    //   425: putfield 703	o/l:ᐝॱ	Z
    //   428: goto +20 -> 448
    //   431: astore_3
    //   432: aload_3
    //   433: invokevirtual 539	java/lang/Throwable:getCause	()Ljava/lang/Throwable;
    //   436: astore 4
    //   438: aload 4
    //   440: ifnull +6 -> 446
    //   443: aload 4
    //   445: athrow
    //   446: aload_3
    //   447: athrow
    //   448: aload_0
    //   449: invokevirtual 97	android/content/Context:getApplicationInfo	()Landroid/content/pm/ApplicationInfo;
    //   452: getfield 102	android/content/pm/ApplicationInfo:targetSdkVersion	I
    //   455: bipush 22
    //   457: isub
    //   458: aload_0
    //   459: invokevirtual 74	android/content/Context:getResources	()Landroid/content/res/Resources;
    //   462: ldc_w 704
    //   465: invokevirtual 81	android/content/res/Resources:getString	(I)Ljava/lang/String;
    //   468: iconst_0
    //   469: iconst_5
    //   470: invokevirtual 85	java/lang/String:substring	(II)Ljava/lang/String;
    //   473: invokevirtual 89	java/lang/String:length	()I
    //   476: iconst_5
    //   477: isub
    //   478: aload_0
    //   479: invokevirtual 74	android/content/Context:getResources	()Landroid/content/res/Resources;
    //   482: ldc_w 705
    //   485: invokevirtual 81	android/content/res/Resources:getString	(I)Ljava/lang/String;
    //   488: iconst_0
    //   489: iconst_1
    //   490: invokevirtual 85	java/lang/String:substring	(II)Ljava/lang/String;
    //   493: invokevirtual 89	java/lang/String:length	()I
    //   496: ldc_w 706
    //   499: iadd
    //   500: i2c
    //   501: invokestatic 545	o/O:ˋ	(IIC)Ljava/lang/Object;
    //   504: checkcast 518	java/lang/Class
    //   507: ldc_w 591
    //   510: aconst_null
    //   511: invokevirtual 551	java/lang/Class:getMethod	(Ljava/lang/String;[Ljava/lang/Class;)Ljava/lang/reflect/Method;
    //   514: aconst_null
    //   515: aconst_null
    //   516: invokevirtual 557	java/lang/reflect/Method:invoke	(Ljava/lang/Object;[Ljava/lang/Object;)Ljava/lang/Object;
    //   519: astore_3
    //   520: goto +20 -> 540
    //   523: astore_3
    //   524: aload_3
    //   525: invokevirtual 539	java/lang/Throwable:getCause	()Ljava/lang/Throwable;
    //   528: astore 4
    //   530: aload 4
    //   532: ifnull +6 -> 538
    //   535: aload 4
    //   537: athrow
    //   538: aload_3
    //   539: athrow
    //   540: aload_0
    //   541: invokevirtual 93	android/content/Context:getPackageName	()Ljava/lang/String;
    //   544: invokevirtual 89	java/lang/String:length	()I
    //   547: bipush 8
    //   549: isub
    //   550: aload_0
    //   551: invokevirtual 74	android/content/Context:getResources	()Landroid/content/res/Resources;
    //   554: ldc_w 707
    //   557: invokevirtual 81	android/content/res/Resources:getString	(I)Ljava/lang/String;
    //   560: iconst_0
    //   561: iconst_1
    //   562: invokevirtual 85	java/lang/String:substring	(II)Ljava/lang/String;
    //   565: iconst_0
    //   566: invokevirtual 114	java/lang/String:codePointAt	(I)I
    //   569: bipush 57
    //   571: isub
    //   572: aload_0
    //   573: invokevirtual 97	android/content/Context:getApplicationInfo	()Landroid/content/pm/ApplicationInfo;
    //   576: getfield 102	android/content/pm/ApplicationInfo:targetSdkVersion	I
    //   579: ldc_w 708
    //   582: iadd
    //   583: i2c
    //   584: invokestatic 545	o/O:ˋ	(IIC)Ljava/lang/Object;
    //   587: checkcast 518	java/lang/Class
    //   590: ldc_w 709
    //   593: aconst_null
    //   594: invokevirtual 551	java/lang/Class:getMethod	(Ljava/lang/String;[Ljava/lang/Class;)Ljava/lang/reflect/Method;
    //   597: aload_3
    //   598: aconst_null
    //   599: invokevirtual 557	java/lang/reflect/Method:invoke	(Ljava/lang/Object;[Ljava/lang/Object;)Ljava/lang/Object;
    //   602: checkcast 711	java/lang/Boolean
    //   605: invokevirtual 715	java/lang/Boolean:booleanValue	()Z
    //   608: istore_2
    //   609: iload_2
    //   610: ifne +6 -> 616
    //   613: goto -605 -> 8
    //   616: goto -613 -> 3
    //   619: goto -196 -> 423
    //   622: iconst_1
    //   623: istore_2
    //   624: goto -611 -> 13
    //   627: return
    //   628: goto -262 -> 366
    //   631: astore_3
    //   632: aload_3
    //   633: athrow
    // Local variable table:
    //   start	length	slot	name	signature
    //   0	634	0	this	l
    //   4	412	1	i	int
    //   14	610	2	bool	boolean
    //   96	1	3	str	String
    //   217	105	3	localObject1	Object
    //   363	2	3	localException1	Exception
    //   431	16	3	localObject2	Object
    //   519	1	3	localObject3	Object
    //   523	75	3	localObject4	Object
    //   631	2	3	localException2	Exception
    //   212	324	4	localObject5	Object
    // Exception table:
    //   from	to	target	type
    //   234	332	217	finally
    //   432	438	363	java/lang/Exception
    //   443	446	363	java/lang/Exception
    //   446	448	363	java/lang/Exception
    //   448	520	431	finally
    //   540	609	523	finally
    //   423	428	631	java/lang/Exception
    //   432	438	631	java/lang/Exception
    //   443	446	631	java/lang/Exception
    //   446	448	631	java/lang/Exception
    //   524	530	631	java/lang/Exception
    //   535	538	631	java/lang/Exception
    //   538	540	631	java/lang/Exception
  }
  
  /* Error */
  public void onRequestPermissionsResult(int paramInt, String[] paramArrayOfString, int[] paramArrayOfInt)
  {
    // Byte code:
    //   0: goto +573 -> 573
    //   3: goto +329 -> 332
    //   6: aload_0
    //   7: getfield 719	o/l:ͺ	Lo/af;
    //   10: invokevirtual 723	o/af:ˋ	()Z
    //   13: istore 7
    //   15: aconst_null
    //   16: arraylength
    //   17: istore 5
    //   19: iload 7
    //   21: ifeq +6 -> 27
    //   24: goto +43 -> 67
    //   27: goto +314 -> 341
    //   30: getstatic 39	o/l:ʾ	I
    //   33: bipush 93
    //   35: iadd
    //   36: istore 5
    //   38: iload 5
    //   40: sipush 128
    //   43: irem
    //   44: putstatic 37	o/l:ʼॱ	I
    //   47: iload 5
    //   49: iconst_2
    //   50: irem
    //   51: ifne +6 -> 57
    //   54: goto +455 -> 509
    //   57: goto +623 -> 680
    //   60: iconst_1
    //   61: istore 5
    //   63: goto +384 -> 447
    //   66: return
    //   67: aload_0
    //   68: invokevirtual 74	android/content/Context:getResources	()Landroid/content/res/Resources;
    //   71: ldc_w 724
    //   74: invokevirtual 81	android/content/res/Resources:getString	(I)Ljava/lang/String;
    //   77: bipush 8
    //   79: bipush 13
    //   81: invokevirtual 85	java/lang/String:substring	(II)Ljava/lang/String;
    //   84: iconst_4
    //   85: invokevirtual 114	java/lang/String:codePointAt	(I)I
    //   88: sipush 6571
    //   91: iadd
    //   92: i2c
    //   93: aload_0
    //   94: invokevirtual 74	android/content/Context:getResources	()Landroid/content/res/Resources;
    //   97: ldc_w 725
    //   100: invokevirtual 81	android/content/res/Resources:getString	(I)Ljava/lang/String;
    //   103: iconst_0
    //   104: iconst_5
    //   105: invokevirtual 85	java/lang/String:substring	(II)Ljava/lang/String;
    //   108: invokevirtual 89	java/lang/String:length	()I
    //   111: sipush 226
    //   114: iadd
    //   115: aload_0
    //   116: invokevirtual 74	android/content/Context:getResources	()Landroid/content/res/Resources;
    //   119: ldc_w 726
    //   122: invokevirtual 81	android/content/res/Resources:getString	(I)Ljava/lang/String;
    //   125: iconst_0
    //   126: iconst_4
    //   127: invokevirtual 85	java/lang/String:substring	(II)Ljava/lang/String;
    //   130: iconst_2
    //   131: invokevirtual 114	java/lang/String:codePointAt	(I)I
    //   134: iconst_4
    //   135: isub
    //   136: invokestatic 104	o/l:ˋ	(CII)Ljava/lang/String;
    //   139: invokevirtual 107	java/lang/String:intern	()Ljava/lang/String;
    //   142: astore 8
    //   144: aload_0
    //   145: invokevirtual 97	android/content/Context:getApplicationInfo	()Landroid/content/pm/ApplicationInfo;
    //   148: getfield 102	android/content/pm/ApplicationInfo:targetSdkVersion	I
    //   151: sipush 3324
    //   154: iadd
    //   155: i2c
    //   156: aload_0
    //   157: invokevirtual 74	android/content/Context:getResources	()Landroid/content/res/Resources;
    //   160: ldc_w 727
    //   163: invokevirtual 81	android/content/res/Resources:getString	(I)Ljava/lang/String;
    //   166: iconst_0
    //   167: iconst_4
    //   168: invokevirtual 85	java/lang/String:substring	(II)Ljava/lang/String;
    //   171: invokevirtual 89	java/lang/String:length	()I
    //   174: sipush 289
    //   177: iadd
    //   178: aload_0
    //   179: invokevirtual 93	android/content/Context:getPackageName	()Ljava/lang/String;
    //   182: iconst_0
    //   183: invokevirtual 114	java/lang/String:codePointAt	(I)I
    //   186: bipush 74
    //   188: isub
    //   189: invokestatic 104	o/l:ˋ	(CII)Ljava/lang/String;
    //   192: invokevirtual 107	java/lang/String:intern	()Ljava/lang/String;
    //   195: astore 9
    //   197: goto +17 -> 214
    //   200: astore_2
    //   201: aload_2
    //   202: invokevirtual 539	java/lang/Throwable:getCause	()Ljava/lang/Throwable;
    //   205: astore_3
    //   206: aload_3
    //   207: ifnull +5 -> 212
    //   210: aload_3
    //   211: athrow
    //   212: aload_2
    //   213: athrow
    //   214: aload_0
    //   215: invokevirtual 93	android/content/Context:getPackageName	()Ljava/lang/String;
    //   218: bipush 8
    //   220: invokevirtual 114	java/lang/String:codePointAt	(I)I
    //   223: bipush 108
    //   225: isub
    //   226: aload_0
    //   227: invokevirtual 97	android/content/Context:getApplicationInfo	()Landroid/content/pm/ApplicationInfo;
    //   230: getfield 102	android/content/pm/ApplicationInfo:targetSdkVersion	I
    //   233: bipush 17
    //   235: iadd
    //   236: aload_0
    //   237: invokevirtual 93	android/content/Context:getPackageName	()Ljava/lang/String;
    //   240: invokevirtual 89	java/lang/String:length	()I
    //   243: ldc_w 701
    //   246: iadd
    //   247: i2c
    //   248: invokestatic 545	o/O:ˋ	(IIC)Ljava/lang/Object;
    //   251: checkcast 518	java/lang/Class
    //   254: ldc_w 591
    //   257: iconst_2
    //   258: anewarray 518	java/lang/Class
    //   261: dup
    //   262: iconst_0
    //   263: ldc 53
    //   265: aastore
    //   266: dup
    //   267: iconst_1
    //   268: ldc 53
    //   270: aastore
    //   271: invokevirtual 551	java/lang/Class:getMethod	(Ljava/lang/String;[Ljava/lang/Class;)Ljava/lang/reflect/Method;
    //   274: aconst_null
    //   275: iconst_2
    //   276: anewarray 504	java/lang/Object
    //   279: dup
    //   280: iconst_0
    //   281: aload 8
    //   283: aastore
    //   284: dup
    //   285: iconst_1
    //   286: aload 9
    //   288: aastore
    //   289: invokevirtual 557	java/lang/reflect/Method:invoke	(Ljava/lang/Object;[Ljava/lang/Object;)Ljava/lang/Object;
    //   292: pop
    //   293: aload_0
    //   294: aload_2
    //   295: aload_0
    //   296: getfield 719	o/l:ͺ	Lo/af;
    //   299: invokevirtual 730	o/af:ॱ	()Lo/ai;
    //   302: aload_0
    //   303: getfield 719	o/l:ͺ	Lo/af;
    //   306: invokevirtual 733	o/af:ˎ	()Lo/ah;
    //   309: iload_1
    //   310: invokevirtual 736	o/l:ˊ	([Ljava/lang/String;Lo/ai;Lo/ah;I)V
    //   313: goto +318 -> 631
    //   316: aload_0
    //   317: getfield 719	o/l:ͺ	Lo/af;
    //   320: invokevirtual 723	o/af:ˋ	()Z
    //   323: ifeq +6 -> 329
    //   326: goto +199 -> 525
    //   329: goto +112 -> 441
    //   332: iload 4
    //   334: iconst_1
    //   335: iadd
    //   336: istore 4
    //   338: goto +326 -> 664
    //   341: aload_0
    //   342: getfield 719	o/l:ͺ	Lo/af;
    //   345: astore 8
    //   347: aload 8
    //   349: iload_1
    //   350: iconst_0
    //   351: invokevirtual 739	o/af:ˊ	(IZ)V
    //   354: aload_0
    //   355: getfield 719	o/l:ͺ	Lo/af;
    //   358: astore 8
    //   360: aload 8
    //   362: iload_1
    //   363: iconst_0
    //   364: invokevirtual 741	o/af:ˋ	(IZ)V
    //   367: aload_0
    //   368: getfield 719	o/l:ͺ	Lo/af;
    //   371: iload_1
    //   372: invokevirtual 744	o/af:ॱ	(I)V
    //   375: aload_0
    //   376: aconst_null
    //   377: putfield 719	o/l:ͺ	Lo/af;
    //   380: goto +96 -> 476
    //   383: iload 5
    //   385: tableswitch	default:+23->408, 0:+-318->67, 1:+-44->341
    //   408: goto -67 -> 341
    //   411: getstatic 37	o/l:ʼॱ	I
    //   414: bipush 41
    //   416: iadd
    //   417: istore 5
    //   419: iload 5
    //   421: sipush 128
    //   424: irem
    //   425: putstatic 39	o/l:ʾ	I
    //   428: iload 5
    //   430: iconst_2
    //   431: irem
    //   432: ifeq +6 -> 438
    //   435: goto +226 -> 661
    //   438: goto +173 -> 611
    //   441: iconst_1
    //   442: istore 5
    //   444: goto -61 -> 383
    //   447: iload 5
    //   449: tableswitch	default:+23->472, 0:+-383->66, 1:+-38->411
    //   472: return
    //   473: goto +30 -> 503
    //   476: getstatic 37	o/l:ʼॱ	I
    //   479: bipush 7
    //   481: iadd
    //   482: istore 5
    //   484: iload 5
    //   486: sipush 128
    //   489: irem
    //   490: putstatic 39	o/l:ʾ	I
    //   493: iload 5
    //   495: iconst_2
    //   496: irem
    //   497: ifeq +6 -> 503
    //   500: goto -27 -> 473
    //   503: goto -171 -> 332
    //   506: goto -503 -> 3
    //   509: iconst_0
    //   510: istore 5
    //   512: goto +70 -> 582
    //   515: aload_2
    //   516: arraylength
    //   517: istore 6
    //   519: iconst_0
    //   520: istore 4
    //   522: goto +142 -> 664
    //   525: iconst_0
    //   526: istore 5
    //   528: goto -145 -> 383
    //   531: aload_0
    //   532: aload 8
    //   534: invokestatic 749	o/ז:ॱ	(Landroid/app/Activity;Ljava/lang/String;)Z
    //   537: ifeq +6 -> 543
    //   540: goto -510 -> 30
    //   543: goto -202 -> 341
    //   546: astore_2
    //   547: aload_2
    //   548: athrow
    //   549: aload_0
    //   550: getfield 719	o/l:ͺ	Lo/af;
    //   553: iload_1
    //   554: iconst_1
    //   555: invokevirtual 741	o/af:ˋ	(IZ)V
    //   558: aload_0
    //   559: getfield 719	o/l:ͺ	Lo/af;
    //   562: iload_1
    //   563: iconst_1
    //   564: invokevirtual 739	o/af:ˊ	(IZ)V
    //   567: aload_0
    //   568: aconst_null
    //   569: putfield 719	o/l:ͺ	Lo/af;
    //   572: return
    //   573: goto -58 -> 515
    //   576: iconst_0
    //   577: istore 5
    //   579: goto -132 -> 447
    //   582: iload 5
    //   584: tableswitch	default:+24->608, 0:+-578->6, 1:+-268->316
    //   608: goto -602 -> 6
    //   611: aload_2
    //   612: iload 4
    //   614: aaload
    //   615: astore 8
    //   617: aload_0
    //   618: aload_3
    //   619: invokevirtual 752	o/l:ˋ	([I)Z
    //   622: ifeq +6 -> 628
    //   625: goto -76 -> 549
    //   628: goto -97 -> 531
    //   631: getstatic 37	o/l:ʼॱ	I
    //   634: bipush 27
    //   636: iadd
    //   637: istore 5
    //   639: iload 5
    //   641: sipush 128
    //   644: irem
    //   645: putstatic 39	o/l:ʾ	I
    //   648: iload 5
    //   650: iconst_2
    //   651: irem
    //   652: ifeq +6 -> 658
    //   655: goto -149 -> 506
    //   658: goto -655 -> 3
    //   661: goto -50 -> 611
    //   664: iload 4
    //   666: iload 6
    //   668: if_icmpge +6 -> 674
    //   671: goto -611 -> 60
    //   674: goto -98 -> 576
    //   677: astore_2
    //   678: aload_2
    //   679: athrow
    //   680: iconst_1
    //   681: istore 5
    //   683: goto -101 -> 582
    // Local variable table:
    //   start	length	slot	name	signature
    //   0	686	0	this	l
    //   0	686	1	paramInt	int
    //   0	686	2	paramArrayOfString	String[]
    //   0	686	3	paramArrayOfInt	int[]
    //   332	337	4	i	int
    //   17	665	5	j	int
    //   517	152	6	k	int
    //   13	7	7	bool	boolean
    //   142	474	8	localObject	Object
    //   195	92	9	str	String
    // Exception table:
    //   from	to	target	type
    //   214	293	200	finally
    //   341	347	546	java/lang/Exception
    //   347	354	546	java/lang/Exception
    //   354	360	546	java/lang/Exception
    //   360	367	546	java/lang/Exception
    //   367	380	546	java/lang/Exception
    //   347	354	677	java/lang/Exception
  }
  
  /* Error */
  protected void onResume()
  {
    // Byte code:
    //   0: goto +345 -> 345
    //   3: aload_0
    //   4: iconst_1
    //   5: putfield 703	o/l:ᐝॱ	Z
    //   8: aload_0
    //   9: invokespecial 755	o/ܖ:onResume	()V
    //   12: aload_0
    //   13: invokevirtual 74	android/content/Context:getResources	()Landroid/content/res/Resources;
    //   16: astore_2
    //   17: aload_2
    //   18: ldc_w 756
    //   21: invokevirtual 81	android/content/res/Resources:getString	(I)Ljava/lang/String;
    //   24: astore_2
    //   25: aload_2
    //   26: iconst_0
    //   27: iconst_4
    //   28: invokevirtual 85	java/lang/String:substring	(II)Ljava/lang/String;
    //   31: invokevirtual 89	java/lang/String:length	()I
    //   34: ldc_w 757
    //   37: iadd
    //   38: i2c
    //   39: aload_0
    //   40: invokevirtual 97	android/content/Context:getApplicationInfo	()Landroid/content/pm/ApplicationInfo;
    //   43: getfield 102	android/content/pm/ApplicationInfo:targetSdkVersion	I
    //   46: bipush 8
    //   48: iadd
    //   49: aload_0
    //   50: invokevirtual 97	android/content/Context:getApplicationInfo	()Landroid/content/pm/ApplicationInfo;
    //   53: getfield 102	android/content/pm/ApplicationInfo:targetSdkVersion	I
    //   56: bipush 8
    //   58: isub
    //   59: invokestatic 104	o/l:ˋ	(CII)Ljava/lang/String;
    //   62: invokevirtual 107	java/lang/String:intern	()Ljava/lang/String;
    //   65: astore_3
    //   66: new 510	java/lang/StringBuilder
    //   69: dup
    //   70: invokespecial 511	java/lang/StringBuilder:<init>	()V
    //   73: aload_0
    //   74: invokevirtual 93	android/content/Context:getPackageName	()Ljava/lang/String;
    //   77: invokevirtual 89	java/lang/String:length	()I
    //   80: sipush 18802
    //   83: iadd
    //   84: i2c
    //   85: aload_0
    //   86: invokevirtual 74	android/content/Context:getResources	()Landroid/content/res/Resources;
    //   89: ldc_w 758
    //   92: invokevirtual 81	android/content/res/Resources:getString	(I)Ljava/lang/String;
    //   95: iconst_0
    //   96: iconst_4
    //   97: invokevirtual 85	java/lang/String:substring	(II)Ljava/lang/String;
    //   100: iconst_1
    //   101: invokevirtual 114	java/lang/String:codePointAt	(I)I
    //   104: bipush 24
    //   106: iadd
    //   107: aload_0
    //   108: invokevirtual 74	android/content/Context:getResources	()Landroid/content/res/Resources;
    //   111: ldc_w 634
    //   114: invokevirtual 81	android/content/res/Resources:getString	(I)Ljava/lang/String;
    //   117: iconst_0
    //   118: bipush 9
    //   120: invokevirtual 85	java/lang/String:substring	(II)Ljava/lang/String;
    //   123: invokevirtual 89	java/lang/String:length	()I
    //   126: iconst_0
    //   127: iadd
    //   128: invokestatic 104	o/l:ˋ	(CII)Ljava/lang/String;
    //   131: invokevirtual 107	java/lang/String:intern	()Ljava/lang/String;
    //   134: invokevirtual 516	java/lang/StringBuilder:append	(Ljava/lang/String;)Ljava/lang/StringBuilder;
    //   137: aload_0
    //   138: invokevirtual 508	java/lang/Object:getClass	()Ljava/lang/Class;
    //   141: invokevirtual 521	java/lang/Class:getSimpleName	()Ljava/lang/String;
    //   144: invokevirtual 516	java/lang/StringBuilder:append	(Ljava/lang/String;)Ljava/lang/StringBuilder;
    //   147: aload_0
    //   148: invokevirtual 93	android/content/Context:getPackageName	()Ljava/lang/String;
    //   151: invokevirtual 89	java/lang/String:length	()I
    //   154: bipush 11
    //   156: isub
    //   157: i2c
    //   158: aload_0
    //   159: invokevirtual 97	android/content/Context:getApplicationInfo	()Landroid/content/pm/ApplicationInfo;
    //   162: getfield 102	android/content/pm/ApplicationInfo:targetSdkVersion	I
    //   165: sipush 129
    //   168: iadd
    //   169: aload_0
    //   170: invokevirtual 74	android/content/Context:getResources	()Landroid/content/res/Resources;
    //   173: ldc_w 759
    //   176: invokevirtual 81	android/content/res/Resources:getString	(I)Ljava/lang/String;
    //   179: iconst_0
    //   180: iconst_5
    //   181: invokevirtual 85	java/lang/String:substring	(II)Ljava/lang/String;
    //   184: iconst_3
    //   185: invokevirtual 114	java/lang/String:codePointAt	(I)I
    //   188: bipush 8
    //   190: iadd
    //   191: invokestatic 104	o/l:ˋ	(CII)Ljava/lang/String;
    //   194: invokevirtual 107	java/lang/String:intern	()Ljava/lang/String;
    //   197: invokevirtual 516	java/lang/StringBuilder:append	(Ljava/lang/String;)Ljava/lang/StringBuilder;
    //   200: invokevirtual 533	java/lang/StringBuilder:toString	()Ljava/lang/String;
    //   203: astore_2
    //   204: goto +17 -> 221
    //   207: astore_3
    //   208: aload_3
    //   209: invokevirtual 539	java/lang/Throwable:getCause	()Ljava/lang/Throwable;
    //   212: astore_2
    //   213: aload_2
    //   214: ifnull +5 -> 219
    //   217: aload_2
    //   218: athrow
    //   219: aload_3
    //   220: athrow
    //   221: aload_0
    //   222: invokevirtual 74	android/content/Context:getResources	()Landroid/content/res/Resources;
    //   225: ldc_w 760
    //   228: invokevirtual 81	android/content/res/Resources:getString	(I)Ljava/lang/String;
    //   231: iconst_0
    //   232: iconst_5
    //   233: invokevirtual 85	java/lang/String:substring	(II)Ljava/lang/String;
    //   236: invokevirtual 89	java/lang/String:length	()I
    //   239: iconst_1
    //   240: isub
    //   241: aload_0
    //   242: invokevirtual 97	android/content/Context:getApplicationInfo	()Landroid/content/pm/ApplicationInfo;
    //   245: getfield 102	android/content/pm/ApplicationInfo:targetSdkVersion	I
    //   248: bipush 17
    //   250: iadd
    //   251: aload_0
    //   252: invokevirtual 74	android/content/Context:getResources	()Landroid/content/res/Resources;
    //   255: ldc_w 761
    //   258: invokevirtual 81	android/content/res/Resources:getString	(I)Ljava/lang/String;
    //   261: iconst_0
    //   262: iconst_4
    //   263: invokevirtual 85	java/lang/String:substring	(II)Ljava/lang/String;
    //   266: iconst_1
    //   267: invokevirtual 114	java/lang/String:codePointAt	(I)I
    //   270: ldc_w 762
    //   273: iadd
    //   274: i2c
    //   275: invokestatic 545	o/O:ˋ	(IIC)Ljava/lang/Object;
    //   278: checkcast 518	java/lang/Class
    //   281: ldc_w 591
    //   284: iconst_2
    //   285: anewarray 518	java/lang/Class
    //   288: dup
    //   289: iconst_0
    //   290: ldc 53
    //   292: aastore
    //   293: dup
    //   294: iconst_1
    //   295: ldc 53
    //   297: aastore
    //   298: invokevirtual 551	java/lang/Class:getMethod	(Ljava/lang/String;[Ljava/lang/Class;)Ljava/lang/reflect/Method;
    //   301: aconst_null
    //   302: iconst_2
    //   303: anewarray 504	java/lang/Object
    //   306: dup
    //   307: iconst_0
    //   308: aload_3
    //   309: aastore
    //   310: dup
    //   311: iconst_1
    //   312: aload_2
    //   313: aastore
    //   314: invokevirtual 557	java/lang/reflect/Method:invoke	(Ljava/lang/Object;[Ljava/lang/Object;)Ljava/lang/Object;
    //   317: pop
    //   318: getstatic 39	o/l:ʾ	I
    //   321: bipush 53
    //   323: iadd
    //   324: istore_1
    //   325: iload_1
    //   326: sipush 128
    //   329: irem
    //   330: putstatic 37	o/l:ʼॱ	I
    //   333: iload_1
    //   334: iconst_2
    //   335: irem
    //   336: ifne +6 -> 342
    //   339: goto +44 -> 383
    //   342: goto +6 -> 348
    //   345: goto -342 -> 3
    //   348: bipush 87
    //   350: istore_1
    //   351: iload_1
    //   352: lookupswitch	default:+28->380, 17:+41->393, 87:+37->389
    //   380: goto +13 -> 393
    //   383: bipush 17
    //   385: istore_1
    //   386: goto -35 -> 351
    //   389: return
    //   390: astore_2
    //   391: aload_2
    //   392: athrow
    //   393: new 764	java/lang/NullPointerException
    //   396: dup
    //   397: invokespecial 765	java/lang/NullPointerException:<init>	()V
    //   400: athrow
    //   401: astore_2
    //   402: aload_2
    //   403: athrow
    // Local variable table:
    //   start	length	slot	name	signature
    //   0	404	0	this	l
    //   324	62	1	i	int
    //   16	297	2	localObject1	Object
    //   390	2	2	localException1	Exception
    //   401	2	2	localException2	Exception
    //   65	1	3	str	String
    //   207	102	3	localObject2	Object
    // Exception table:
    //   from	to	target	type
    //   221	318	207	finally
    //   12	17	390	java/lang/Exception
    //   3	12	401	java/lang/Exception
    //   12	17	401	java/lang/Exception
    //   17	25	401	java/lang/Exception
    //   25	204	401	java/lang/Exception
    //   208	213	401	java/lang/Exception
    //   217	219	401	java/lang/Exception
    //   219	221	401	java/lang/Exception
  }
  
  /* Error */
  protected void onStart()
  {
    // Byte code:
    //   0: goto +365 -> 365
    //   3: aconst_null
    //   4: arraylength
    //   5: istore_1
    //   6: return
    //   7: iconst_1
    //   8: istore_1
    //   9: goto +333 -> 342
    //   12: aload_0
    //   13: invokespecial 768	o/ܖ:onStart	()V
    //   16: aload_0
    //   17: invokevirtual 93	android/content/Context:getPackageName	()Ljava/lang/String;
    //   20: iconst_1
    //   21: invokevirtual 114	java/lang/String:codePointAt	(I)I
    //   24: ldc_w 769
    //   27: iadd
    //   28: i2c
    //   29: aload_0
    //   30: invokevirtual 97	android/content/Context:getApplicationInfo	()Landroid/content/pm/ApplicationInfo;
    //   33: getfield 102	android/content/pm/ApplicationInfo:targetSdkVersion	I
    //   36: bipush 8
    //   38: iadd
    //   39: aload_0
    //   40: invokevirtual 93	android/content/Context:getPackageName	()Ljava/lang/String;
    //   43: invokevirtual 89	java/lang/String:length	()I
    //   46: bipush 6
    //   48: iadd
    //   49: invokestatic 104	o/l:ˋ	(CII)Ljava/lang/String;
    //   52: invokevirtual 107	java/lang/String:intern	()Ljava/lang/String;
    //   55: astore_2
    //   56: new 510	java/lang/StringBuilder
    //   59: dup
    //   60: invokespecial 511	java/lang/StringBuilder:<init>	()V
    //   63: aload_0
    //   64: invokevirtual 74	android/content/Context:getResources	()Landroid/content/res/Resources;
    //   67: ldc_w 770
    //   70: invokevirtual 81	android/content/res/Resources:getString	(I)Ljava/lang/String;
    //   73: iconst_0
    //   74: iconst_5
    //   75: invokevirtual 85	java/lang/String:substring	(II)Ljava/lang/String;
    //   78: iconst_2
    //   79: invokevirtual 114	java/lang/String:codePointAt	(I)I
    //   82: sipush 18802
    //   85: iadd
    //   86: i2c
    //   87: aload_0
    //   88: invokevirtual 74	android/content/Context:getResources	()Landroid/content/res/Resources;
    //   91: ldc_w 771
    //   94: invokevirtual 81	android/content/res/Resources:getString	(I)Ljava/lang/String;
    //   97: iconst_0
    //   98: iconst_4
    //   99: invokevirtual 85	java/lang/String:substring	(II)Ljava/lang/String;
    //   102: invokevirtual 89	java/lang/String:length	()I
    //   105: bipush 46
    //   107: iadd
    //   108: aload_0
    //   109: invokevirtual 93	android/content/Context:getPackageName	()Ljava/lang/String;
    //   112: invokevirtual 89	java/lang/String:length	()I
    //   115: iconst_2
    //   116: isub
    //   117: invokestatic 104	o/l:ˋ	(CII)Ljava/lang/String;
    //   120: invokevirtual 107	java/lang/String:intern	()Ljava/lang/String;
    //   123: invokevirtual 516	java/lang/StringBuilder:append	(Ljava/lang/String;)Ljava/lang/StringBuilder;
    //   126: aload_0
    //   127: invokevirtual 508	java/lang/Object:getClass	()Ljava/lang/Class;
    //   130: invokevirtual 521	java/lang/Class:getSimpleName	()Ljava/lang/String;
    //   133: invokevirtual 516	java/lang/StringBuilder:append	(Ljava/lang/String;)Ljava/lang/StringBuilder;
    //   136: aload_0
    //   137: invokevirtual 93	android/content/Context:getPackageName	()Ljava/lang/String;
    //   140: invokevirtual 89	java/lang/String:length	()I
    //   143: bipush 11
    //   145: isub
    //   146: i2c
    //   147: aload_0
    //   148: invokevirtual 97	android/content/Context:getApplicationInfo	()Landroid/content/pm/ApplicationInfo;
    //   151: getfield 102	android/content/pm/ApplicationInfo:targetSdkVersion	I
    //   154: bipush 121
    //   156: iadd
    //   157: aload_0
    //   158: invokevirtual 74	android/content/Context:getResources	()Landroid/content/res/Resources;
    //   161: ldc_w 772
    //   164: invokevirtual 81	android/content/res/Resources:getString	(I)Ljava/lang/String;
    //   167: iconst_0
    //   168: iconst_5
    //   169: invokevirtual 85	java/lang/String:substring	(II)Ljava/lang/String;
    //   172: invokevirtual 89	java/lang/String:length	()I
    //   175: iconst_3
    //   176: iadd
    //   177: invokestatic 104	o/l:ˋ	(CII)Ljava/lang/String;
    //   180: invokevirtual 107	java/lang/String:intern	()Ljava/lang/String;
    //   183: invokevirtual 516	java/lang/StringBuilder:append	(Ljava/lang/String;)Ljava/lang/StringBuilder;
    //   186: invokevirtual 533	java/lang/StringBuilder:toString	()Ljava/lang/String;
    //   189: astore_3
    //   190: goto +17 -> 207
    //   193: astore_2
    //   194: aload_2
    //   195: invokevirtual 539	java/lang/Throwable:getCause	()Ljava/lang/Throwable;
    //   198: astore_3
    //   199: aload_3
    //   200: ifnull +5 -> 205
    //   203: aload_3
    //   204: athrow
    //   205: aload_2
    //   206: athrow
    //   207: aload_0
    //   208: invokevirtual 74	android/content/Context:getResources	()Landroid/content/res/Resources;
    //   211: ldc_w 773
    //   214: invokevirtual 81	android/content/res/Resources:getString	(I)Ljava/lang/String;
    //   217: iconst_0
    //   218: iconst_5
    //   219: invokevirtual 85	java/lang/String:substring	(II)Ljava/lang/String;
    //   222: iconst_1
    //   223: invokevirtual 114	java/lang/String:codePointAt	(I)I
    //   226: bipush 22
    //   228: isub
    //   229: aload_0
    //   230: invokevirtual 93	android/content/Context:getPackageName	()Ljava/lang/String;
    //   233: iconst_2
    //   234: invokevirtual 114	java/lang/String:codePointAt	(I)I
    //   237: iconst_4
    //   238: isub
    //   239: aload_0
    //   240: invokevirtual 74	android/content/Context:getResources	()Landroid/content/res/Resources;
    //   243: ldc_w 774
    //   246: invokevirtual 81	android/content/res/Resources:getString	(I)Ljava/lang/String;
    //   249: iconst_0
    //   250: iconst_5
    //   251: invokevirtual 85	java/lang/String:substring	(II)Ljava/lang/String;
    //   254: iconst_2
    //   255: invokevirtual 114	java/lang/String:codePointAt	(I)I
    //   258: ldc_w 701
    //   261: iadd
    //   262: i2c
    //   263: invokestatic 545	o/O:ˋ	(IIC)Ljava/lang/Object;
    //   266: checkcast 518	java/lang/Class
    //   269: ldc_w 591
    //   272: iconst_2
    //   273: anewarray 518	java/lang/Class
    //   276: dup
    //   277: iconst_0
    //   278: ldc 53
    //   280: aastore
    //   281: dup
    //   282: iconst_1
    //   283: ldc 53
    //   285: aastore
    //   286: invokevirtual 551	java/lang/Class:getMethod	(Ljava/lang/String;[Ljava/lang/Class;)Ljava/lang/reflect/Method;
    //   289: aconst_null
    //   290: iconst_2
    //   291: anewarray 504	java/lang/Object
    //   294: dup
    //   295: iconst_0
    //   296: aload_2
    //   297: aastore
    //   298: dup
    //   299: iconst_1
    //   300: aload_3
    //   301: aastore
    //   302: invokevirtual 557	java/lang/reflect/Method:invoke	(Ljava/lang/Object;[Ljava/lang/Object;)Ljava/lang/Object;
    //   305: pop
    //   306: goto +9 -> 315
    //   309: iconst_0
    //   310: istore_1
    //   311: goto +31 -> 342
    //   314: return
    //   315: getstatic 37	o/l:ʼॱ	I
    //   318: bipush 57
    //   320: iadd
    //   321: istore_1
    //   322: iload_1
    //   323: sipush 128
    //   326: irem
    //   327: putstatic 39	o/l:ʾ	I
    //   330: iload_1
    //   331: iconst_2
    //   332: irem
    //   333: ifeq +6 -> 339
    //   336: goto -329 -> 7
    //   339: goto -30 -> 309
    //   342: iload_1
    //   343: tableswitch	default:+21->364, 0:+-29->314, 1:+-340->3
    //   364: return
    //   365: goto -353 -> 12
    // Local variable table:
    //   start	length	slot	name	signature
    //   0	368	0	this	l
    //   5	338	1	i	int
    //   55	1	2	str	String
    //   193	104	2	localObject1	Object
    //   189	112	3	localObject2	Object
    // Exception table:
    //   from	to	target	type
    //   207	306	193	finally
  }
  
  /* Error */
  protected void onStop()
  {
    // Byte code:
    //   0: goto +70 -> 70
    //   3: iload_1
    //   4: tableswitch	default:+24->28, 0:+52->56, 1:+65->69
    //   28: return
    //   29: getstatic 39	o/l:ʾ	I
    //   32: bipush 83
    //   34: iadd
    //   35: istore_1
    //   36: iload_1
    //   37: sipush 128
    //   40: irem
    //   41: putstatic 37	o/l:ʼॱ	I
    //   44: iload_1
    //   45: iconst_2
    //   46: irem
    //   47: ifne +6 -> 53
    //   50: goto +341 -> 391
    //   53: goto +11 -> 64
    //   56: new 764	java/lang/NullPointerException
    //   59: dup
    //   60: invokespecial 765	java/lang/NullPointerException:<init>	()V
    //   63: athrow
    //   64: iconst_1
    //   65: istore_1
    //   66: goto -63 -> 3
    //   69: return
    //   70: aload_0
    //   71: invokespecial 777	o/ܖ:onStop	()V
    //   74: aload_0
    //   75: invokevirtual 74	android/content/Context:getResources	()Landroid/content/res/Resources;
    //   78: ldc_w 778
    //   81: invokevirtual 81	android/content/res/Resources:getString	(I)Ljava/lang/String;
    //   84: iconst_0
    //   85: iconst_4
    //   86: invokevirtual 85	java/lang/String:substring	(II)Ljava/lang/String;
    //   89: invokevirtual 89	java/lang/String:length	()I
    //   92: ldc_w 757
    //   95: iadd
    //   96: i2c
    //   97: aload_0
    //   98: invokevirtual 93	android/content/Context:getPackageName	()Ljava/lang/String;
    //   101: iconst_5
    //   102: invokevirtual 114	java/lang/String:codePointAt	(I)I
    //   105: bipush 81
    //   107: isub
    //   108: aload_0
    //   109: invokevirtual 93	android/content/Context:getPackageName	()Ljava/lang/String;
    //   112: invokevirtual 89	java/lang/String:length	()I
    //   115: bipush 6
    //   117: iadd
    //   118: invokestatic 104	o/l:ˋ	(CII)Ljava/lang/String;
    //   121: invokevirtual 107	java/lang/String:intern	()Ljava/lang/String;
    //   124: astore_3
    //   125: new 510	java/lang/StringBuilder
    //   128: dup
    //   129: invokespecial 511	java/lang/StringBuilder:<init>	()V
    //   132: aload_0
    //   133: invokevirtual 74	android/content/Context:getResources	()Landroid/content/res/Resources;
    //   136: ldc_w 779
    //   139: invokevirtual 81	android/content/res/Resources:getString	(I)Ljava/lang/String;
    //   142: iconst_0
    //   143: iconst_4
    //   144: invokevirtual 85	java/lang/String:substring	(II)Ljava/lang/String;
    //   147: iconst_2
    //   148: invokevirtual 114	java/lang/String:codePointAt	(I)I
    //   151: sipush 18802
    //   154: iadd
    //   155: i2c
    //   156: aload_0
    //   157: invokevirtual 74	android/content/Context:getResources	()Landroid/content/res/Resources;
    //   160: ldc_w 780
    //   163: invokevirtual 81	android/content/res/Resources:getString	(I)Ljava/lang/String;
    //   166: iconst_0
    //   167: iconst_4
    //   168: invokevirtual 85	java/lang/String:substring	(II)Ljava/lang/String;
    //   171: iconst_2
    //   172: invokevirtual 114	java/lang/String:codePointAt	(I)I
    //   175: bipush 39
    //   177: iadd
    //   178: aload_0
    //   179: invokevirtual 74	android/content/Context:getResources	()Landroid/content/res/Resources;
    //   182: ldc_w 781
    //   185: invokevirtual 81	android/content/res/Resources:getString	(I)Ljava/lang/String;
    //   188: iconst_0
    //   189: iconst_4
    //   190: invokevirtual 85	java/lang/String:substring	(II)Ljava/lang/String;
    //   193: invokevirtual 89	java/lang/String:length	()I
    //   196: iconst_5
    //   197: iadd
    //   198: invokestatic 104	o/l:ˋ	(CII)Ljava/lang/String;
    //   201: invokevirtual 107	java/lang/String:intern	()Ljava/lang/String;
    //   204: invokevirtual 516	java/lang/StringBuilder:append	(Ljava/lang/String;)Ljava/lang/StringBuilder;
    //   207: aload_0
    //   208: invokevirtual 508	java/lang/Object:getClass	()Ljava/lang/Class;
    //   211: invokevirtual 521	java/lang/Class:getSimpleName	()Ljava/lang/String;
    //   214: invokevirtual 516	java/lang/StringBuilder:append	(Ljava/lang/String;)Ljava/lang/StringBuilder;
    //   217: aload_0
    //   218: invokevirtual 93	android/content/Context:getPackageName	()Ljava/lang/String;
    //   221: invokevirtual 89	java/lang/String:length	()I
    //   224: bipush 11
    //   226: isub
    //   227: i2c
    //   228: aload_0
    //   229: invokevirtual 74	android/content/Context:getResources	()Landroid/content/res/Resources;
    //   232: ldc_w 782
    //   235: invokevirtual 81	android/content/res/Resources:getString	(I)Ljava/lang/String;
    //   238: iconst_0
    //   239: iconst_5
    //   240: invokevirtual 85	java/lang/String:substring	(II)Ljava/lang/String;
    //   243: iconst_1
    //   244: invokevirtual 114	java/lang/String:codePointAt	(I)I
    //   247: sipush 169
    //   250: iadd
    //   251: aload_0
    //   252: invokevirtual 93	android/content/Context:getPackageName	()Ljava/lang/String;
    //   255: invokevirtual 89	java/lang/String:length	()I
    //   258: iconst_3
    //   259: isub
    //   260: invokestatic 104	o/l:ˋ	(CII)Ljava/lang/String;
    //   263: invokevirtual 107	java/lang/String:intern	()Ljava/lang/String;
    //   266: invokevirtual 516	java/lang/StringBuilder:append	(Ljava/lang/String;)Ljava/lang/StringBuilder;
    //   269: invokevirtual 533	java/lang/StringBuilder:toString	()Ljava/lang/String;
    //   272: astore_2
    //   273: goto +17 -> 290
    //   276: astore_2
    //   277: aload_2
    //   278: invokevirtual 539	java/lang/Throwable:getCause	()Ljava/lang/Throwable;
    //   281: astore_3
    //   282: aload_3
    //   283: ifnull +5 -> 288
    //   286: aload_3
    //   287: athrow
    //   288: aload_2
    //   289: athrow
    //   290: aload_0
    //   291: invokevirtual 74	android/content/Context:getResources	()Landroid/content/res/Resources;
    //   294: ldc_w 783
    //   297: invokevirtual 81	android/content/res/Resources:getString	(I)Ljava/lang/String;
    //   300: iconst_0
    //   301: iconst_1
    //   302: invokevirtual 85	java/lang/String:substring	(II)Ljava/lang/String;
    //   305: iconst_0
    //   306: invokevirtual 114	java/lang/String:codePointAt	(I)I
    //   309: bipush 46
    //   311: isub
    //   312: aload_0
    //   313: invokevirtual 97	android/content/Context:getApplicationInfo	()Landroid/content/pm/ApplicationInfo;
    //   316: getfield 102	android/content/pm/ApplicationInfo:targetSdkVersion	I
    //   319: bipush 17
    //   321: iadd
    //   322: aload_0
    //   323: invokevirtual 74	android/content/Context:getResources	()Landroid/content/res/Resources;
    //   326: ldc_w 784
    //   329: invokevirtual 81	android/content/res/Resources:getString	(I)Ljava/lang/String;
    //   332: iconst_0
    //   333: iconst_4
    //   334: invokevirtual 85	java/lang/String:substring	(II)Ljava/lang/String;
    //   337: invokevirtual 89	java/lang/String:length	()I
    //   340: ldc_w 785
    //   343: iadd
    //   344: i2c
    //   345: invokestatic 545	o/O:ˋ	(IIC)Ljava/lang/Object;
    //   348: checkcast 518	java/lang/Class
    //   351: ldc_w 591
    //   354: iconst_2
    //   355: anewarray 518	java/lang/Class
    //   358: dup
    //   359: iconst_0
    //   360: ldc 53
    //   362: aastore
    //   363: dup
    //   364: iconst_1
    //   365: ldc 53
    //   367: aastore
    //   368: invokevirtual 551	java/lang/Class:getMethod	(Ljava/lang/String;[Ljava/lang/Class;)Ljava/lang/reflect/Method;
    //   371: aconst_null
    //   372: iconst_2
    //   373: anewarray 504	java/lang/Object
    //   376: dup
    //   377: iconst_0
    //   378: aload_3
    //   379: aastore
    //   380: dup
    //   381: iconst_1
    //   382: aload_2
    //   383: aastore
    //   384: invokevirtual 557	java/lang/reflect/Method:invoke	(Ljava/lang/Object;[Ljava/lang/Object;)Ljava/lang/Object;
    //   387: pop
    //   388: goto -359 -> 29
    //   391: iconst_0
    //   392: istore_1
    //   393: goto -390 -> 3
    // Local variable table:
    //   start	length	slot	name	signature
    //   0	396	0	this	l
    //   3	390	1	i	int
    //   272	1	2	str	String
    //   276	107	2	localObject1	Object
    //   124	255	3	localObject2	Object
    // Exception table:
    //   from	to	target	type
    //   290	388	276	finally
  }
  
  /* Error */
  public void startActivityForResult(android.content.Intent paramIntent, int paramInt)
  {
    // Byte code:
    //   0: goto +6 -> 6
    //   3: astore_1
    //   4: aload_1
    //   5: athrow
    //   6: goto +75 -> 81
    //   9: astore_1
    //   10: aload_1
    //   11: athrow
    //   12: aload_1
    //   13: aload_0
    //   14: invokevirtual 97	android/content/Context:getApplicationInfo	()Landroid/content/pm/ApplicationInfo;
    //   17: getfield 102	android/content/pm/ApplicationInfo:targetSdkVersion	I
    //   20: ldc_w 788
    //   23: iadd
    //   24: i2c
    //   25: aload_0
    //   26: invokevirtual 97	android/content/Context:getApplicationInfo	()Landroid/content/pm/ApplicationInfo;
    //   29: getfield 102	android/content/pm/ApplicationInfo:targetSdkVersion	I
    //   32: sipush 188
    //   35: iadd
    //   36: aload_0
    //   37: invokevirtual 74	android/content/Context:getResources	()Landroid/content/res/Resources;
    //   40: ldc_w 789
    //   43: invokevirtual 81	android/content/res/Resources:getString	(I)Ljava/lang/String;
    //   46: iconst_0
    //   47: iconst_5
    //   48: invokevirtual 85	java/lang/String:substring	(II)Ljava/lang/String;
    //   51: iconst_2
    //   52: invokevirtual 114	java/lang/String:codePointAt	(I)I
    //   55: bipush 7
    //   57: iadd
    //   58: invokestatic 104	o/l:ˋ	(CII)Ljava/lang/String;
    //   61: invokevirtual 107	java/lang/String:intern	()Ljava/lang/String;
    //   64: iload_2
    //   65: invokevirtual 793	android/content/Intent:putExtra	(Ljava/lang/String;I)Landroid/content/Intent;
    //   68: pop
    //   69: aload_0
    //   70: aload_1
    //   71: iload_2
    //   72: invokespecial 795	o/ܖ:startActivityForResult	(Landroid/content/Intent;I)V
    //   75: goto +33 -> 108
    //   78: goto -66 -> 12
    //   81: getstatic 37	o/l:ʼॱ	I
    //   84: bipush 85
    //   86: iadd
    //   87: istore_3
    //   88: iload_3
    //   89: sipush 128
    //   92: irem
    //   93: putstatic 39	o/l:ʾ	I
    //   96: iload_3
    //   97: iconst_2
    //   98: irem
    //   99: ifeq +6 -> 105
    //   102: goto -24 -> 78
    //   105: goto -93 -> 12
    //   108: getstatic 39	o/l:ʾ	I
    //   111: bipush 83
    //   113: iadd
    //   114: istore_2
    //   115: iload_2
    //   116: sipush 128
    //   119: irem
    //   120: putstatic 37	o/l:ʼॱ	I
    //   123: iload_2
    //   124: iconst_2
    //   125: irem
    //   126: ifne +4 -> 130
    //   129: return
    //   130: return
    // Local variable table:
    //   start	length	slot	name	signature
    //   0	131	0	this	l
    //   0	131	1	paramIntent	android.content.Intent
    //   0	131	2	paramInt	int
    //   87	12	3	i	int
    // Exception table:
    //   from	to	target	type
    //   81	88	3	java/lang/Exception
    //   88	96	3	java/lang/Exception
    //   88	96	9	java/lang/Exception
  }
  
  /* Error */
  public void ˊ(у paramУ)
  {
    // Byte code:
    //   0: goto +97 -> 97
    //   3: aload_0
    //   4: aload_1
    //   5: invokespecial 798	o/ܖ:ˊ	(Lo/у;)V
    //   8: aload_0
    //   9: aload_0
    //   10: invokevirtual 802	o/l:ʻ	()Lo/ز;
    //   13: invokevirtual 805	o/l:ˋ	(Lo/ز;)V
    //   16: aload_1
    //   17: iconst_1
    //   18: invokevirtual 810	o/у:setContentInsetStartWithNavigation	(I)V
    //   21: goto +109 -> 130
    //   24: iload_2
    //   25: lookupswitch	default:+27->52, 47:+-22->3, 56:+33->58
    //   52: goto +6 -> 58
    //   55: astore_1
    //   56: aload_1
    //   57: athrow
    //   58: aload_0
    //   59: aload_1
    //   60: invokespecial 798	o/ܖ:ˊ	(Lo/у;)V
    //   63: aload_0
    //   64: invokevirtual 802	o/l:ʻ	()Lo/ز;
    //   67: astore_3
    //   68: aload_0
    //   69: aload_3
    //   70: invokevirtual 805	o/l:ˋ	(Lo/ز;)V
    //   73: aload_1
    //   74: iconst_0
    //   75: invokevirtual 810	o/у:setContentInsetStartWithNavigation	(I)V
    //   78: goto +52 -> 130
    //   81: bipush 56
    //   83: istore_2
    //   84: goto -60 -> 24
    //   87: iconst_0
    //   88: istore_2
    //   89: goto +69 -> 158
    //   92: iconst_1
    //   93: istore_2
    //   94: goto +64 -> 158
    //   97: goto +6 -> 103
    //   100: astore_1
    //   101: aload_1
    //   102: athrow
    //   103: getstatic 39	o/l:ʾ	I
    //   106: bipush 87
    //   108: iadd
    //   109: istore_2
    //   110: iload_2
    //   111: sipush 128
    //   114: irem
    //   115: putstatic 37	o/l:ʼॱ	I
    //   118: iload_2
    //   119: iconst_2
    //   120: irem
    //   121: ifne +6 -> 127
    //   124: goto +61 -> 185
    //   127: goto -46 -> 81
    //   130: getstatic 37	o/l:ʼॱ	I
    //   133: bipush 21
    //   135: iadd
    //   136: istore_2
    //   137: iload_2
    //   138: sipush 128
    //   141: irem
    //   142: putstatic 39	o/l:ʾ	I
    //   145: iload_2
    //   146: iconst_2
    //   147: irem
    //   148: ifeq +6 -> 154
    //   151: goto -64 -> 87
    //   154: goto -62 -> 92
    //   157: return
    //   158: iload_2
    //   159: tableswitch	default:+21->180, 0:+22->181, 1:+-2->157
    //   180: return
    //   181: aconst_null
    //   182: arraylength
    //   183: istore_2
    //   184: return
    //   185: bipush 47
    //   187: istore_2
    //   188: goto -164 -> 24
    // Local variable table:
    //   start	length	slot	name	signature
    //   0	191	0	this	l
    //   0	191	1	paramУ	у
    //   24	164	2	i	int
    //   67	3	3	localز	ز
    // Exception table:
    //   from	to	target	type
    //   68	73	55	java/lang/Exception
    //   63	68	100	java/lang/Exception
    //   73	78	100	java/lang/Exception
    //   130	137	100	java/lang/Exception
    //   137	145	100	java/lang/Exception
  }
  
  /* Error */
  public void ˊ(String[] paramArrayOfString, ai paramAi, int paramInt, ah paramAh)
  {
    // Byte code:
    //   0: goto +385 -> 385
    //   3: getstatic 37	o/l:ʼॱ	I
    //   6: bipush 41
    //   8: iadd
    //   9: istore 5
    //   11: iload 5
    //   13: sipush 128
    //   16: irem
    //   17: putstatic 39	o/l:ʾ	I
    //   20: iload 5
    //   22: iconst_2
    //   23: irem
    //   24: ifeq +6 -> 30
    //   27: goto +6 -> 33
    //   30: goto +9 -> 39
    //   33: iconst_0
    //   34: istore 5
    //   36: goto +394 -> 430
    //   39: iconst_1
    //   40: istore 5
    //   42: goto +388 -> 430
    //   45: return
    //   46: astore_1
    //   47: aload_1
    //   48: athrow
    //   49: aload_0
    //   50: invokevirtual 74	android/content/Context:getResources	()Landroid/content/res/Resources;
    //   53: astore 7
    //   55: aload 7
    //   57: ldc_w 812
    //   60: invokevirtual 81	android/content/res/Resources:getString	(I)Ljava/lang/String;
    //   63: astore 7
    //   65: aload 7
    //   67: iconst_0
    //   68: iconst_5
    //   69: invokevirtual 85	java/lang/String:substring	(II)Ljava/lang/String;
    //   72: astore 7
    //   74: aload 7
    //   76: invokevirtual 89	java/lang/String:length	()I
    //   79: sipush 6800
    //   82: iadd
    //   83: i2c
    //   84: aload_0
    //   85: invokevirtual 93	android/content/Context:getPackageName	()Ljava/lang/String;
    //   88: bipush 8
    //   90: invokevirtual 114	java/lang/String:codePointAt	(I)I
    //   93: bipush 119
    //   95: iadd
    //   96: aload_0
    //   97: invokevirtual 93	android/content/Context:getPackageName	()Ljava/lang/String;
    //   100: bipush 8
    //   102: invokevirtual 114	java/lang/String:codePointAt	(I)I
    //   105: bipush 105
    //   107: isub
    //   108: invokestatic 104	o/l:ˋ	(CII)Ljava/lang/String;
    //   111: invokevirtual 107	java/lang/String:intern	()Ljava/lang/String;
    //   114: astore 7
    //   116: new 510	java/lang/StringBuilder
    //   119: dup
    //   120: invokespecial 511	java/lang/StringBuilder:<init>	()V
    //   123: aload_0
    //   124: invokevirtual 74	android/content/Context:getResources	()Landroid/content/res/Resources;
    //   127: ldc_w 813
    //   130: invokevirtual 81	android/content/res/Resources:getString	(I)Ljava/lang/String;
    //   133: iconst_0
    //   134: iconst_4
    //   135: invokevirtual 85	java/lang/String:substring	(II)Ljava/lang/String;
    //   138: iconst_0
    //   139: invokevirtual 114	java/lang/String:codePointAt	(I)I
    //   142: iconst_5
    //   143: isub
    //   144: i2c
    //   145: aload_0
    //   146: invokevirtual 74	android/content/Context:getResources	()Landroid/content/res/Resources;
    //   149: ldc_w 814
    //   152: invokevirtual 81	android/content/res/Resources:getString	(I)Ljava/lang/String;
    //   155: iconst_0
    //   156: bipush 8
    //   158: invokevirtual 85	java/lang/String:substring	(II)Ljava/lang/String;
    //   161: invokevirtual 89	java/lang/String:length	()I
    //   164: sipush 329
    //   167: iadd
    //   168: aload_0
    //   169: invokevirtual 74	android/content/Context:getResources	()Landroid/content/res/Resources;
    //   172: ldc_w 815
    //   175: invokevirtual 81	android/content/res/Resources:getString	(I)Ljava/lang/String;
    //   178: iconst_0
    //   179: iconst_4
    //   180: invokevirtual 85	java/lang/String:substring	(II)Ljava/lang/String;
    //   183: iconst_1
    //   184: invokevirtual 114	java/lang/String:codePointAt	(I)I
    //   187: iconst_3
    //   188: isub
    //   189: invokestatic 104	o/l:ˋ	(CII)Ljava/lang/String;
    //   192: invokevirtual 107	java/lang/String:intern	()Ljava/lang/String;
    //   195: invokevirtual 516	java/lang/StringBuilder:append	(Ljava/lang/String;)Ljava/lang/StringBuilder;
    //   198: aload_1
    //   199: invokevirtual 818	java/lang/StringBuilder:append	(Ljava/lang/Object;)Ljava/lang/StringBuilder;
    //   202: invokevirtual 533	java/lang/StringBuilder:toString	()Ljava/lang/String;
    //   205: astore 8
    //   207: goto +17 -> 224
    //   210: astore_1
    //   211: aload_1
    //   212: invokevirtual 539	java/lang/Throwable:getCause	()Ljava/lang/Throwable;
    //   215: astore_2
    //   216: aload_2
    //   217: ifnull +5 -> 222
    //   220: aload_2
    //   221: athrow
    //   222: aload_1
    //   223: athrow
    //   224: aload_0
    //   225: invokevirtual 74	android/content/Context:getResources	()Landroid/content/res/Resources;
    //   228: ldc_w 758
    //   231: invokevirtual 81	android/content/res/Resources:getString	(I)Ljava/lang/String;
    //   234: iconst_0
    //   235: iconst_4
    //   236: invokevirtual 85	java/lang/String:substring	(II)Ljava/lang/String;
    //   239: invokevirtual 89	java/lang/String:length	()I
    //   242: iconst_0
    //   243: iadd
    //   244: aload_0
    //   245: invokevirtual 74	android/content/Context:getResources	()Landroid/content/res/Resources;
    //   248: ldc_w 819
    //   251: invokevirtual 81	android/content/res/Resources:getString	(I)Ljava/lang/String;
    //   254: iconst_0
    //   255: iconst_5
    //   256: invokevirtual 85	java/lang/String:substring	(II)Ljava/lang/String;
    //   259: invokevirtual 89	java/lang/String:length	()I
    //   262: bipush 37
    //   264: iadd
    //   265: aload_0
    //   266: invokevirtual 74	android/content/Context:getResources	()Landroid/content/res/Resources;
    //   269: ldc_w 820
    //   272: invokevirtual 81	android/content/res/Resources:getString	(I)Ljava/lang/String;
    //   275: iconst_0
    //   276: bipush 6
    //   278: invokevirtual 85	java/lang/String:substring	(II)Ljava/lang/String;
    //   281: iconst_1
    //   282: invokevirtual 114	java/lang/String:codePointAt	(I)I
    //   285: ldc_w 762
    //   288: iadd
    //   289: i2c
    //   290: invokestatic 545	o/O:ˋ	(IIC)Ljava/lang/Object;
    //   293: checkcast 518	java/lang/Class
    //   296: ldc_w 821
    //   299: iconst_2
    //   300: anewarray 518	java/lang/Class
    //   303: dup
    //   304: iconst_0
    //   305: ldc 53
    //   307: aastore
    //   308: dup
    //   309: iconst_1
    //   310: ldc 53
    //   312: aastore
    //   313: invokevirtual 551	java/lang/Class:getMethod	(Ljava/lang/String;[Ljava/lang/Class;)Ljava/lang/reflect/Method;
    //   316: aconst_null
    //   317: iconst_2
    //   318: anewarray 504	java/lang/Object
    //   321: dup
    //   322: iconst_0
    //   323: aload 7
    //   325: aastore
    //   326: dup
    //   327: iconst_1
    //   328: aload 8
    //   330: aastore
    //   331: invokevirtual 557	java/lang/reflect/Method:invoke	(Ljava/lang/Object;[Ljava/lang/Object;)Ljava/lang/Object;
    //   334: pop
    //   335: aload_0
    //   336: new 721	o/af
    //   339: dup
    //   340: aload_1
    //   341: invokespecial 824	o/af:<init>	([Ljava/lang/String;)V
    //   344: putfield 719	o/l:ͺ	Lo/af;
    //   347: aload_0
    //   348: getfield 719	o/l:ͺ	Lo/af;
    //   351: aload_2
    //   352: invokevirtual 827	o/af:ˏ	(Lo/ai;)V
    //   355: aload_0
    //   356: getfield 719	o/l:ͺ	Lo/af;
    //   359: aload 4
    //   361: invokevirtual 830	o/af:ˋ	(Lo/ah;)V
    //   364: aload_0
    //   365: aload_1
    //   366: invokevirtual 833	o/l:ॱ	([Ljava/lang/String;)Z
    //   369: istore 6
    //   371: iload 6
    //   373: ifeq +6 -> 379
    //   376: goto +12 -> 388
    //   379: goto +140 -> 519
    //   382: astore_1
    //   383: aload_1
    //   384: athrow
    //   385: goto -336 -> 49
    //   388: iconst_0
    //   389: istore 5
    //   391: goto +131 -> 522
    //   394: aload_0
    //   395: getfield 719	o/l:ͺ	Lo/af;
    //   398: iload_3
    //   399: iconst_1
    //   400: invokevirtual 739	o/af:ˊ	(IZ)V
    //   403: getstatic 39	o/l:ʾ	I
    //   406: bipush 43
    //   408: iadd
    //   409: istore_3
    //   410: iload_3
    //   411: sipush 128
    //   414: irem
    //   415: putstatic 37	o/l:ʼॱ	I
    //   418: iload_3
    //   419: iconst_2
    //   420: irem
    //   421: ifne +6 -> 427
    //   424: goto +61 -> 485
    //   427: goto +42 -> 469
    //   430: iload 5
    //   432: tableswitch	default:+24->456, 0:+24->456, 1:+-38->394
    //   456: aload_0
    //   457: getfield 719	o/l:ͺ	Lo/af;
    //   460: iload_3
    //   461: iconst_0
    //   462: invokevirtual 739	o/af:ˊ	(IZ)V
    //   465: goto -62 -> 403
    //   468: return
    //   469: bipush 6
    //   471: istore_3
    //   472: goto +16 -> 488
    //   475: aload_0
    //   476: getfield 719	o/l:ͺ	Lo/af;
    //   479: aload_0
    //   480: iload_3
    //   481: invokevirtual 836	o/af:ˎ	(Landroid/app/Activity;I)V
    //   484: return
    //   485: bipush 61
    //   487: istore_3
    //   488: iload_3
    //   489: lookupswitch	default:+27->516, 6:+-444->45, 61:+-21->468
    //   516: goto -471 -> 45
    //   519: iconst_1
    //   520: istore 5
    //   522: iload 5
    //   524: tableswitch	default:+24->548, 0:+-521->3, 1:+-49->475
    //   548: goto -73 -> 475
    // Local variable table:
    //   start	length	slot	name	signature
    //   0	551	0	this	l
    //   0	551	1	paramArrayOfString	String[]
    //   0	551	2	paramAi	ai
    //   0	551	3	paramInt	int
    //   0	551	4	paramAh	ah
    //   9	514	5	i	int
    //   369	3	6	bool	boolean
    //   53	271	7	localObject	Object
    //   205	124	8	str	String
    // Exception table:
    //   from	to	target	type
    //   49	55	46	java/lang/Exception
    //   55	65	46	java/lang/Exception
    //   65	74	46	java/lang/Exception
    //   74	207	46	java/lang/Exception
    //   211	216	46	java/lang/Exception
    //   220	222	46	java/lang/Exception
    //   222	224	46	java/lang/Exception
    //   335	371	46	java/lang/Exception
    //   224	335	210	finally
    //   55	65	382	java/lang/Exception
  }
  
  /* Error */
  protected void ˊ(final String[] paramArrayOfString, final ai paramAi, final ah paramAh, final int paramInt)
  {
    // Byte code:
    //   0: goto +659 -> 659
    //   3: getstatic 39	o/l:ʾ	I
    //   6: bipush 33
    //   8: iadd
    //   9: istore 6
    //   11: iload 6
    //   13: sipush 128
    //   16: irem
    //   17: putstatic 37	o/l:ʼॱ	I
    //   20: iload 6
    //   22: iconst_2
    //   23: irem
    //   24: ifne +6 -> 30
    //   27: goto +365 -> 392
    //   30: goto +382 -> 412
    //   33: aload 9
    //   35: astore 8
    //   37: iload 6
    //   39: lookupswitch	default:+25->64, 23:+-36->3, 33:+540->579
    //   64: aload 9
    //   66: astore 8
    //   68: goto +511 -> 579
    //   71: aload_0
    //   72: aload 9
    //   74: iconst_4
    //   75: invokevirtual 838	java/lang/String:substring	(I)Ljava/lang/String;
    //   78: invokespecial 840	o/l:ˋ	(Ljava/lang/String;)Ljava/lang/String;
    //   81: invokevirtual 107	java/lang/String:intern	()Ljava/lang/String;
    //   84: astore 8
    //   86: goto +576 -> 662
    //   89: iconst_1
    //   90: istore 6
    //   92: goto +457 -> 549
    //   95: aload_0
    //   96: aload 8
    //   98: iconst_4
    //   99: invokevirtual 838	java/lang/String:substring	(I)Ljava/lang/String;
    //   102: invokespecial 840	o/l:ˋ	(Ljava/lang/String;)Ljava/lang/String;
    //   105: invokevirtual 107	java/lang/String:intern	()Ljava/lang/String;
    //   108: astore 8
    //   110: goto +95 -> 205
    //   113: new 842	o/ᐸ$If
    //   116: dup
    //   117: aload_0
    //   118: invokespecial 844	o/ᐸ$If:<init>	(Landroid/content/Context;)V
    //   121: astore 10
    //   123: aload_0
    //   124: aload_2
    //   125: invokevirtual 847	o/ai:ˎ	()I
    //   128: invokevirtual 848	o/l:getString	(I)Ljava/lang/String;
    //   131: astore 9
    //   133: aload 9
    //   135: aload_0
    //   136: invokevirtual 93	android/content/Context:getPackageName	()Ljava/lang/String;
    //   139: bipush 7
    //   141: invokevirtual 114	java/lang/String:codePointAt	(I)I
    //   144: sipush 11635
    //   147: iadd
    //   148: i2c
    //   149: aload_0
    //   150: invokevirtual 97	android/content/Context:getApplicationInfo	()Landroid/content/pm/ApplicationInfo;
    //   153: getfield 102	android/content/pm/ApplicationInfo:targetSdkVersion	I
    //   156: sipush 308
    //   159: iadd
    //   160: aload_0
    //   161: invokevirtual 74	android/content/Context:getResources	()Landroid/content/res/Resources;
    //   164: ldc_w 815
    //   167: invokevirtual 81	android/content/res/Resources:getString	(I)Ljava/lang/String;
    //   170: iconst_0
    //   171: iconst_4
    //   172: invokevirtual 85	java/lang/String:substring	(II)Ljava/lang/String;
    //   175: invokevirtual 89	java/lang/String:length	()I
    //   178: iconst_0
    //   179: iadd
    //   180: invokestatic 104	o/l:ˋ	(CII)Ljava/lang/String;
    //   183: invokevirtual 107	java/lang/String:intern	()Ljava/lang/String;
    //   186: invokevirtual 851	java/lang/String:startsWith	(Ljava/lang/String;)Z
    //   189: ifeq +6 -> 195
    //   192: goto +213 -> 405
    //   195: goto +200 -> 395
    //   198: bipush 23
    //   200: istore 6
    //   202: goto -169 -> 33
    //   205: goto +42 -> 247
    //   208: aload 9
    //   210: astore 8
    //   212: iload 6
    //   214: lookupswitch	default:+26->240, 52:+216->430, 73:+142->356
    //   240: aload 9
    //   242: astore 8
    //   244: goto +186 -> 430
    //   247: aload 9
    //   249: aload 8
    //   251: invokevirtual 854	o/ᐸ$If:ˋ	(Ljava/lang/CharSequence;)Lo/ᐸ$If;
    //   254: astore 10
    //   256: aload_0
    //   257: aload_2
    //   258: invokevirtual 856	o/ai:ˋ	()I
    //   261: invokevirtual 848	o/l:getString	(I)Ljava/lang/String;
    //   264: astore 9
    //   266: aload 9
    //   268: aload_0
    //   269: invokevirtual 74	android/content/Context:getResources	()Landroid/content/res/Resources;
    //   272: ldc_w 857
    //   275: invokevirtual 81	android/content/res/Resources:getString	(I)Ljava/lang/String;
    //   278: iconst_0
    //   279: iconst_4
    //   280: invokevirtual 85	java/lang/String:substring	(II)Ljava/lang/String;
    //   283: invokevirtual 89	java/lang/String:length	()I
    //   286: sipush 11677
    //   289: iadd
    //   290: i2c
    //   291: aload_0
    //   292: invokevirtual 74	android/content/Context:getResources	()Landroid/content/res/Resources;
    //   295: ldc_w 858
    //   298: invokevirtual 81	android/content/res/Resources:getString	(I)Ljava/lang/String;
    //   301: iconst_0
    //   302: iconst_5
    //   303: invokevirtual 85	java/lang/String:substring	(II)Ljava/lang/String;
    //   306: iconst_1
    //   307: invokevirtual 114	java/lang/String:codePointAt	(I)I
    //   310: sipush 307
    //   313: iadd
    //   314: aload_0
    //   315: invokevirtual 74	android/content/Context:getResources	()Landroid/content/res/Resources;
    //   318: ldc_w 859
    //   321: invokevirtual 81	android/content/res/Resources:getString	(I)Ljava/lang/String;
    //   324: iconst_0
    //   325: bipush 6
    //   327: invokevirtual 85	java/lang/String:substring	(II)Ljava/lang/String;
    //   330: invokevirtual 89	java/lang/String:length	()I
    //   333: iconst_2
    //   334: isub
    //   335: invokestatic 104	o/l:ˋ	(CII)Ljava/lang/String;
    //   338: invokevirtual 107	java/lang/String:intern	()Ljava/lang/String;
    //   341: invokevirtual 851	java/lang/String:startsWith	(Ljava/lang/String;)Z
    //   344: ifeq +6 -> 350
    //   347: goto -258 -> 89
    //   350: goto +36 -> 386
    //   353: astore_1
    //   354: aload_1
    //   355: athrow
    //   356: getstatic 39	o/l:ʾ	I
    //   359: bipush 17
    //   361: iadd
    //   362: istore 6
    //   364: iload 6
    //   366: sipush 128
    //   369: irem
    //   370: putstatic 37	o/l:ʼॱ	I
    //   373: iload 6
    //   375: iconst_2
    //   376: irem
    //   377: ifne +6 -> 383
    //   380: goto +381 -> 761
    //   383: goto +258 -> 641
    //   386: iconst_0
    //   387: istore 6
    //   389: goto +160 -> 549
    //   392: goto +20 -> 412
    //   395: bipush 52
    //   397: istore 6
    //   399: goto -191 -> 208
    //   402: goto +177 -> 579
    //   405: bipush 73
    //   407: istore 6
    //   409: goto -201 -> 208
    //   412: aload_0
    //   413: aload 9
    //   415: iconst_4
    //   416: invokevirtual 838	java/lang/String:substring	(I)Ljava/lang/String;
    //   419: invokespecial 840	o/l:ˋ	(Ljava/lang/String;)Ljava/lang/String;
    //   422: invokevirtual 107	java/lang/String:intern	()Ljava/lang/String;
    //   425: astore 8
    //   427: goto -25 -> 402
    //   430: aload 10
    //   432: aload 8
    //   434: invokevirtual 861	o/ᐸ$If:ˊ	(Ljava/lang/CharSequence;)Lo/ᐸ$If;
    //   437: astore 9
    //   439: aload_2
    //   440: invokevirtual 863	o/ai:ˏ	()I
    //   443: istore 6
    //   445: aload_0
    //   446: iload 6
    //   448: invokevirtual 848	o/l:getString	(I)Ljava/lang/String;
    //   451: astore 8
    //   453: aload_0
    //   454: invokevirtual 97	android/content/Context:getApplicationInfo	()Landroid/content/pm/ApplicationInfo;
    //   457: astore 10
    //   459: aload 10
    //   461: getfield 102	android/content/pm/ApplicationInfo:targetSdkVersion	I
    //   464: istore 6
    //   466: iload 6
    //   468: sipush 11656
    //   471: iadd
    //   472: i2c
    //   473: istore 5
    //   475: aload 8
    //   477: iload 5
    //   479: aload_0
    //   480: invokevirtual 74	android/content/Context:getResources	()Landroid/content/res/Resources;
    //   483: ldc_w 778
    //   486: invokevirtual 81	android/content/res/Resources:getString	(I)Ljava/lang/String;
    //   489: iconst_0
    //   490: iconst_4
    //   491: invokevirtual 85	java/lang/String:substring	(II)Ljava/lang/String;
    //   494: iconst_2
    //   495: invokevirtual 114	java/lang/String:codePointAt	(I)I
    //   498: sipush 322
    //   501: iadd
    //   502: aload_0
    //   503: invokevirtual 74	android/content/Context:getResources	()Landroid/content/res/Resources;
    //   506: ldc_w 864
    //   509: invokevirtual 81	android/content/res/Resources:getString	(I)Ljava/lang/String;
    //   512: iconst_0
    //   513: iconst_4
    //   514: invokevirtual 85	java/lang/String:substring	(II)Ljava/lang/String;
    //   517: iconst_3
    //   518: invokevirtual 114	java/lang/String:codePointAt	(I)I
    //   521: bipush 8
    //   523: isub
    //   524: invokestatic 104	o/l:ˋ	(CII)Ljava/lang/String;
    //   527: invokevirtual 107	java/lang/String:intern	()Ljava/lang/String;
    //   530: invokevirtual 851	java/lang/String:startsWith	(Ljava/lang/String;)Z
    //   533: istore 7
    //   535: iload 7
    //   537: ifeq +6 -> 543
    //   540: goto -445 -> 95
    //   543: goto -296 -> 247
    //   546: astore_1
    //   547: aload_1
    //   548: athrow
    //   549: aload 9
    //   551: astore 8
    //   553: iload 6
    //   555: tableswitch	default:+21->576, 0:+107->662, 1:+-484->71
    //   576: goto -505 -> 71
    //   579: aload 10
    //   581: aload 8
    //   583: invokevirtual 866	o/ᐸ$If:ॱ	(Ljava/lang/CharSequence;)Lo/ᐸ$If;
    //   586: new 13	o/l$4
    //   589: dup
    //   590: aload_0
    //   591: iload 4
    //   593: invokespecial 869	o/l$4:<init>	(Lo/l;I)V
    //   596: invokevirtual 872	o/ᐸ$If:ˊ	(Lo/ᐸ$ˏ;)Lo/ᐸ$If;
    //   599: new 15	o/l$5
    //   602: dup
    //   603: aload_0
    //   604: aload_1
    //   605: aload_2
    //   606: iload 4
    //   608: aload_3
    //   609: invokespecial 875	o/l$5:<init>	(Lo/l;[Ljava/lang/String;Lo/ai;ILo/ah;)V
    //   612: invokevirtual 877	o/ᐸ$If:ॱ	(Lo/ᐸ$ˏ;)Lo/ᐸ$If;
    //   615: iconst_1
    //   616: invokevirtual 880	o/ᐸ$If:ˋ	(Z)Lo/ᐸ$If;
    //   619: iconst_0
    //   620: invokevirtual 882	o/ᐸ$If:ˊ	(Z)Lo/ᐸ$If;
    //   623: new 11	o/l$3
    //   626: dup
    //   627: aload_0
    //   628: iload 4
    //   630: invokespecial 883	o/l$3:<init>	(Lo/l;I)V
    //   633: invokevirtual 886	o/ᐸ$If:ˎ	(Landroid/content/DialogInterface$OnCancelListener;)Lo/ᐸ$If;
    //   636: invokevirtual 889	o/ᐸ$If:ˏ	()Lo/ᐸ;
    //   639: pop
    //   640: return
    //   641: aload_0
    //   642: aload 9
    //   644: iconst_4
    //   645: invokevirtual 838	java/lang/String:substring	(I)Ljava/lang/String;
    //   648: invokespecial 840	o/l:ˋ	(Ljava/lang/String;)Ljava/lang/String;
    //   651: invokevirtual 107	java/lang/String:intern	()Ljava/lang/String;
    //   654: astore 8
    //   656: goto -226 -> 430
    //   659: goto -546 -> 113
    //   662: aload 10
    //   664: aload 8
    //   666: invokevirtual 891	o/ᐸ$If:ˎ	(Ljava/lang/CharSequence;)Lo/ᐸ$If;
    //   669: astore 10
    //   671: aload_0
    //   672: getstatic 896	o/h$if:deny	I
    //   675: invokevirtual 848	o/l:getString	(I)Ljava/lang/String;
    //   678: astore 9
    //   680: aload 9
    //   682: aload_0
    //   683: invokevirtual 74	android/content/Context:getResources	()Landroid/content/res/Resources;
    //   686: ldc_w 897
    //   689: invokevirtual 81	android/content/res/Resources:getString	(I)Ljava/lang/String;
    //   692: iconst_0
    //   693: iconst_4
    //   694: invokevirtual 85	java/lang/String:substring	(II)Ljava/lang/String;
    //   697: iconst_1
    //   698: invokevirtual 114	java/lang/String:codePointAt	(I)I
    //   701: sipush 11655
    //   704: iadd
    //   705: i2c
    //   706: aload_0
    //   707: invokevirtual 74	android/content/Context:getResources	()Landroid/content/res/Resources;
    //   710: ldc_w 898
    //   713: invokevirtual 81	android/content/res/Resources:getString	(I)Ljava/lang/String;
    //   716: iconst_0
    //   717: iconst_5
    //   718: invokevirtual 85	java/lang/String:substring	(II)Ljava/lang/String;
    //   721: iconst_3
    //   722: invokevirtual 114	java/lang/String:codePointAt	(I)I
    //   725: sipush 321
    //   728: iadd
    //   729: aload_0
    //   730: invokevirtual 93	android/content/Context:getPackageName	()Ljava/lang/String;
    //   733: invokevirtual 89	java/lang/String:length	()I
    //   736: bipush 7
    //   738: isub
    //   739: invokestatic 104	o/l:ˋ	(CII)Ljava/lang/String;
    //   742: invokevirtual 107	java/lang/String:intern	()Ljava/lang/String;
    //   745: invokevirtual 851	java/lang/String:startsWith	(Ljava/lang/String;)Z
    //   748: ifeq +6 -> 754
    //   751: goto -553 -> 198
    //   754: bipush 33
    //   756: istore 6
    //   758: goto -725 -> 33
    //   761: goto -120 -> 641
    // Local variable table:
    //   start	length	slot	name	signature
    //   0	764	0	this	l
    //   0	764	1	paramArrayOfString	String[]
    //   0	764	2	paramAi	ai
    //   0	764	3	paramAh	ah
    //   0	764	4	paramInt	int
    //   473	5	5	c	char
    //   9	748	6	i	int
    //   533	3	7	bool	boolean
    //   35	630	8	localObject1	Object
    //   33	648	9	localObject2	Object
    //   121	549	10	localObject3	Object
    // Exception table:
    //   from	to	target	type
    //   430	439	353	java/lang/Exception
    //   439	445	546	java/lang/Exception
    //   445	453	546	java/lang/Exception
    //   453	459	546	java/lang/Exception
    //   459	466	546	java/lang/Exception
    //   475	535	546	java/lang/Exception
  }
  
  public boolean ˊ(String paramString)
  {
    for (;;)
    {
      boolean bool = true;
      break label12;
      break label47;
      label12:
      break label142;
      label15:
      int i = 78;
      switch (i)
      {
      default: 
        break label230;
        i = ʾ + 49;
        ʼॱ = i % 128;
        if (i % 2 != 0)
        {
          break;
          switch (i)
          {
          }
        }
        break;
      case 78: 
        for (;;)
        {
          label18:
          label47:
          label74:
          switch (i)
          {
          default: 
            break label200;
            i = 84;
            break;
          case 84: 
            label142:
            do
            {
              i = 2;
              break label18;
              i = ʾ + 9;
              ʼॱ = i % 128;
              if (i % 2 == 0) {
                return bool;
              }
              return bool;
              bool = false;
              break;
            } while (ז.ॱ(this, paramString) == 0);
            break label15;
            i = 39;
          }
        }
        for (;;)
        {
          i = 0;
          break;
          label200:
          i = ז.ॱ(this, paramString);
          int j = null.length;
          if (i != 0) {
            break label225;
          }
        }
      }
      label225:
      label230:
      do
      {
        bool = false;
        break;
        i = 1;
        break label74;
        i = ʾ + 123;
        ʼॱ = i % 128;
      } while (i % 2 == 0);
    }
  }
  
  protected void ˋ(ز paramز)
  {
    int i;
    switch (i)
    {
    default: 
      break label90;
      break;
      label38:
      i = 1;
      break label139;
      i = 0;
      break;
    }
    for (;;)
    {
      try
      {
        i = ʾ;
        i += 13;
        ʼॱ = i % 128;
        if (i % 2 != 0)
        {
          continue;
          i = 13 / 0;
          return;
          return;
          i = 66;
          break;
          label90:
          paramز.ॱ(false);
          paramز.ˏ(true);
        }
      }
      catch (Exception paramز)
      {
        try
        {
          i = ʾ + 49;
          ʼॱ = i % 128;
          if (i % 2 == 0) {
            break label38;
          }
        }
        catch (Exception paramز)
        {
          throw paramز;
        }
        paramز = paramز;
        throw paramز;
      }
      i = 53;
      break;
      label139:
      switch (i)
      {
      }
      continue;
      paramز.ॱ(false);
      paramز.ˏ(false);
    }
  }
  
  /* Error */
  protected boolean ˋ(int[] paramArrayOfInt)
  {
    // Byte code:
    //   0: goto +311 -> 311
    //   3: iconst_0
    //   4: ireturn
    //   5: aload_1
    //   6: iconst_1
    //   7: iaload
    //   8: ifne +6 -> 14
    //   11: goto +131 -> 142
    //   14: goto +20 -> 34
    //   17: aload_1
    //   18: iconst_0
    //   19: iaload
    //   20: ifne +6 -> 26
    //   23: goto +6 -> 29
    //   26: goto +189 -> 215
    //   29: iconst_0
    //   30: istore_2
    //   31: goto +252 -> 283
    //   34: bipush 68
    //   36: istore_2
    //   37: goto +215 -> 252
    //   40: astore_1
    //   41: aload_1
    //   42: athrow
    //   43: aload_1
    //   44: arraylength
    //   45: istore_2
    //   46: aconst_null
    //   47: arraylength
    //   48: istore_3
    //   49: iload_2
    //   50: ifle +6 -> 56
    //   53: goto +52 -> 105
    //   56: goto +261 -> 317
    //   59: iload_2
    //   60: lookupswitch	default:+28->88, 32:+88->148, 88:+254->314
    //   88: goto +60 -> 148
    //   91: goto +20 -> 111
    //   94: aload_1
    //   95: arraylength
    //   96: ifle +6 -> 102
    //   99: goto +49 -> 148
    //   102: goto +212 -> 314
    //   105: bipush 32
    //   107: istore_2
    //   108: goto -49 -> 59
    //   111: iconst_1
    //   112: ireturn
    //   113: getstatic 39	o/l:ʾ	I
    //   116: istore_2
    //   117: iload_2
    //   118: bipush 27
    //   120: iadd
    //   121: istore_2
    //   122: iload_2
    //   123: sipush 128
    //   126: irem
    //   127: putstatic 37	o/l:ʼॱ	I
    //   130: iload_2
    //   131: iconst_2
    //   132: irem
    //   133: ifne +6 -> 139
    //   136: goto -45 -> 91
    //   139: goto -28 -> 111
    //   142: bipush 23
    //   144: istore_2
    //   145: goto +107 -> 252
    //   148: getstatic 37	o/l:ʼॱ	I
    //   151: istore_2
    //   152: iload_2
    //   153: bipush 61
    //   155: iadd
    //   156: istore_2
    //   157: iload_2
    //   158: sipush 128
    //   161: irem
    //   162: putstatic 39	o/l:ʾ	I
    //   165: iload_2
    //   166: iconst_2
    //   167: irem
    //   168: ifeq +6 -> 174
    //   171: goto +49 -> 220
    //   174: goto +36 -> 210
    //   177: astore_1
    //   178: aload_1
    //   179: athrow
    //   180: iload_2
    //   181: tableswitch	default:+23->204, 0:+-164->17, 1:+-176->5
    //   204: goto -187 -> 17
    //   207: goto -94 -> 113
    //   210: iconst_0
    //   211: istore_2
    //   212: goto -32 -> 180
    //   215: iconst_1
    //   216: istore_2
    //   217: goto +66 -> 283
    //   220: iconst_1
    //   221: istore_2
    //   222: goto -42 -> 180
    //   225: getstatic 37	o/l:ʼॱ	I
    //   228: bipush 109
    //   230: iadd
    //   231: istore_2
    //   232: iload_2
    //   233: sipush 128
    //   236: irem
    //   237: putstatic 39	o/l:ʾ	I
    //   240: iload_2
    //   241: iconst_2
    //   242: irem
    //   243: ifeq +6 -> 249
    //   246: goto -203 -> 43
    //   249: goto -155 -> 94
    //   252: iload_2
    //   253: lookupswitch	default:+27->280, 23:+-46->207, 68:+61->314
    //   280: goto +34 -> 314
    //   283: iload_2
    //   284: tableswitch	default:+24->308, 0:+-77->207, 1:+30->314
    //   308: goto -101 -> 207
    //   311: goto -86 -> 225
    //   314: goto -311 -> 3
    //   317: bipush 88
    //   319: istore_2
    //   320: goto -261 -> 59
    // Local variable table:
    //   start	length	slot	name	signature
    //   0	323	0	this	l
    //   0	323	1	paramArrayOfInt	int[]
    //   30	290	2	i	int
    //   48	1	3	j	int
    // Exception table:
    //   from	to	target	type
    //   122	130	40	java/lang/Exception
    //   148	152	40	java/lang/Exception
    //   113	117	177	java/lang/Exception
    //   157	165	177	java/lang/Exception
  }
  
  public boolean ˋॱ()
  {
    break label71;
    boolean bool = this.ᐝॱ;
    break label98;
    int i = 31;
    break label23;
    label17:
    i = 67;
    break label132;
    switch (i)
    {
    case 22: 
    default: 
      label23:
      return bool;
      bool = this.ᐝॱ;
      i = null.length;
      for (;;)
      {
        i = 22;
        break label23;
        label71:
        i = ʾ + 27;
        ʼॱ = i % 128;
        if (i % 2 == 0) {
          break label163;
        }
        break label17;
        label98:
        i = ʾ + 97;
        ʼॱ = i % 128;
        if (i % 2 == 0) {
          break;
        }
      }
    }
    i = 10 / 0;
    return bool;
    for (;;)
    {
      label132:
      switch (i)
      {
      }
      break;
      label163:
      i = 87;
    }
  }
  
  public l ͺ()
  {
    break label14;
    int i = null.length;
    return this;
    i = 60;
    break label17;
    label14:
    break label55;
    switch (i)
    {
    case 60: 
    default: 
      label17:
      break;
    }
    for (;;)
    {
      i = 82;
      break label17;
      return this;
      label55:
      i = ʼॱ + 59;
      ʾ = i % 128;
      if (i % 2 != 0) {
        break;
      }
    }
  }
  
  /* Error */
  public void ॱ(int paramInt)
  {
    // Byte code:
    //   0: goto +25 -> 25
    //   3: astore_3
    //   4: aload_3
    //   5: athrow
    //   6: aload_0
    //   7: iload_1
    //   8: invokevirtual 912	o/l:setResult	(I)V
    //   11: aload_0
    //   12: invokevirtual 915	o/l:finish	()V
    //   15: goto +37 -> 52
    //   18: return
    //   19: goto -13 -> 6
    //   22: astore_3
    //   23: aload_3
    //   24: athrow
    //   25: getstatic 37	o/l:ʼॱ	I
    //   28: bipush 109
    //   30: iadd
    //   31: istore_2
    //   32: iload_2
    //   33: sipush 128
    //   36: irem
    //   37: putstatic 39	o/l:ʾ	I
    //   40: iload_2
    //   41: iconst_2
    //   42: irem
    //   43: ifeq +6 -> 49
    //   46: goto -27 -> 19
    //   49: goto -43 -> 6
    //   52: getstatic 37	o/l:ʼॱ	I
    //   55: bipush 107
    //   57: iadd
    //   58: istore_1
    //   59: iload_1
    //   60: sipush 128
    //   63: irem
    //   64: putstatic 39	o/l:ʾ	I
    //   67: iload_1
    //   68: iconst_2
    //   69: irem
    //   70: ifeq +6 -> 76
    //   73: goto -55 -> 18
    //   76: return
    // Local variable table:
    //   start	length	slot	name	signature
    //   0	77	0	this	l
    //   0	77	1	paramInt	int
    //   31	12	2	i	int
    //   3	2	3	localException1	Exception
    //   22	2	3	localException2	Exception
    // Exception table:
    //   from	to	target	type
    //   6	11	3	java/lang/Exception
    //   11	15	3	java/lang/Exception
    //   25	32	3	java/lang/Exception
    //   32	40	3	java/lang/Exception
    //   32	40	22	java/lang/Exception
  }
  
  /* Error */
  protected void ॱ(android.view.Window paramWindow)
  {
    // Byte code:
    //   0: goto +463 -> 463
    //   3: aload_0
    //   4: invokevirtual 97	android/content/Context:getApplicationInfo	()Landroid/content/pm/ApplicationInfo;
    //   7: getfield 102	android/content/pm/ApplicationInfo:targetSdkVersion	I
    //   10: sipush 6780
    //   13: iadd
    //   14: i2c
    //   15: aload_0
    //   16: invokevirtual 97	android/content/Context:getApplicationInfo	()Landroid/content/pm/ApplicationInfo;
    //   19: getfield 102	android/content/pm/ApplicationInfo:targetSdkVersion	I
    //   22: sipush 206
    //   25: iadd
    //   26: aload_0
    //   27: invokevirtual 97	android/content/Context:getApplicationInfo	()Landroid/content/pm/ApplicationInfo;
    //   30: getfield 102	android/content/pm/ApplicationInfo:targetSdkVersion	I
    //   33: bipush 18
    //   35: isub
    //   36: invokestatic 104	o/l:ˋ	(CII)Ljava/lang/String;
    //   39: invokevirtual 107	java/lang/String:intern	()Ljava/lang/String;
    //   42: astore 4
    //   44: new 510	java/lang/StringBuilder
    //   47: dup
    //   48: invokespecial 511	java/lang/StringBuilder:<init>	()V
    //   51: aload_0
    //   52: invokevirtual 97	android/content/Context:getApplicationInfo	()Landroid/content/pm/ApplicationInfo;
    //   55: getfield 102	android/content/pm/ApplicationInfo:targetSdkVersion	I
    //   58: sipush 6754
    //   61: iadd
    //   62: i2c
    //   63: aload_0
    //   64: invokevirtual 97	android/content/Context:getApplicationInfo	()Landroid/content/pm/ApplicationInfo;
    //   67: getfield 102	android/content/pm/ApplicationInfo:targetSdkVersion	I
    //   70: sipush 335
    //   73: iadd
    //   74: aload_0
    //   75: invokevirtual 97	android/content/Context:getApplicationInfo	()Landroid/content/pm/ApplicationInfo;
    //   78: getfield 102	android/content/pm/ApplicationInfo:targetSdkVersion	I
    //   81: bipush 10
    //   83: isub
    //   84: invokestatic 104	o/l:ˋ	(CII)Ljava/lang/String;
    //   87: invokevirtual 107	java/lang/String:intern	()Ljava/lang/String;
    //   90: invokevirtual 516	java/lang/StringBuilder:append	(Ljava/lang/String;)Ljava/lang/StringBuilder;
    //   93: aload_0
    //   94: invokevirtual 508	java/lang/Object:getClass	()Ljava/lang/Class;
    //   97: invokevirtual 918	java/lang/Class:getName	()Ljava/lang/String;
    //   100: invokevirtual 516	java/lang/StringBuilder:append	(Ljava/lang/String;)Ljava/lang/StringBuilder;
    //   103: aload_0
    //   104: invokevirtual 93	android/content/Context:getPackageName	()Ljava/lang/String;
    //   107: invokevirtual 89	java/lang/String:length	()I
    //   110: ldc_w 919
    //   113: iadd
    //   114: i2c
    //   115: aload_0
    //   116: invokevirtual 74	android/content/Context:getResources	()Landroid/content/res/Resources;
    //   119: ldc_w 588
    //   122: invokevirtual 81	android/content/res/Resources:getString	(I)Ljava/lang/String;
    //   125: iconst_0
    //   126: iconst_4
    //   127: invokevirtual 85	java/lang/String:substring	(II)Ljava/lang/String;
    //   130: iconst_1
    //   131: invokevirtual 114	java/lang/String:codePointAt	(I)I
    //   134: sipush 349
    //   137: iadd
    //   138: aload_0
    //   139: invokevirtual 93	android/content/Context:getPackageName	()Ljava/lang/String;
    //   142: iconst_1
    //   143: invokevirtual 114	java/lang/String:codePointAt	(I)I
    //   146: bipush 89
    //   148: isub
    //   149: invokestatic 104	o/l:ˋ	(CII)Ljava/lang/String;
    //   152: invokevirtual 107	java/lang/String:intern	()Ljava/lang/String;
    //   155: invokevirtual 516	java/lang/StringBuilder:append	(Ljava/lang/String;)Ljava/lang/StringBuilder;
    //   158: invokevirtual 533	java/lang/StringBuilder:toString	()Ljava/lang/String;
    //   161: astore 5
    //   163: goto +20 -> 183
    //   166: astore_1
    //   167: aload_1
    //   168: invokevirtual 539	java/lang/Throwable:getCause	()Ljava/lang/Throwable;
    //   171: astore 4
    //   173: aload 4
    //   175: ifnull +6 -> 181
    //   178: aload 4
    //   180: athrow
    //   181: aload_1
    //   182: athrow
    //   183: aload_0
    //   184: invokevirtual 97	android/content/Context:getApplicationInfo	()Landroid/content/pm/ApplicationInfo;
    //   187: getfield 102	android/content/pm/ApplicationInfo:targetSdkVersion	I
    //   190: bipush 21
    //   192: isub
    //   193: aload_0
    //   194: invokevirtual 93	android/content/Context:getPackageName	()Ljava/lang/String;
    //   197: invokevirtual 89	java/lang/String:length	()I
    //   200: bipush 31
    //   202: iadd
    //   203: aload_0
    //   204: invokevirtual 74	android/content/Context:getResources	()Landroid/content/res/Resources;
    //   207: ldc_w 920
    //   210: invokevirtual 81	android/content/res/Resources:getString	(I)Ljava/lang/String;
    //   213: iconst_0
    //   214: iconst_5
    //   215: invokevirtual 85	java/lang/String:substring	(II)Ljava/lang/String;
    //   218: iconst_1
    //   219: invokevirtual 114	java/lang/String:codePointAt	(I)I
    //   222: ldc_w 762
    //   225: iadd
    //   226: i2c
    //   227: invokestatic 545	o/O:ˋ	(IIC)Ljava/lang/Object;
    //   230: checkcast 518	java/lang/Class
    //   233: ldc_w 821
    //   236: iconst_2
    //   237: anewarray 518	java/lang/Class
    //   240: dup
    //   241: iconst_0
    //   242: ldc 53
    //   244: aastore
    //   245: dup
    //   246: iconst_1
    //   247: ldc 53
    //   249: aastore
    //   250: invokevirtual 551	java/lang/Class:getMethod	(Ljava/lang/String;[Ljava/lang/Class;)Ljava/lang/reflect/Method;
    //   253: aconst_null
    //   254: iconst_2
    //   255: anewarray 504	java/lang/Object
    //   258: dup
    //   259: iconst_0
    //   260: aload 4
    //   262: aastore
    //   263: dup
    //   264: iconst_1
    //   265: aload 5
    //   267: aastore
    //   268: invokevirtual 557	java/lang/reflect/Method:invoke	(Ljava/lang/Object;[Ljava/lang/Object;)Ljava/lang/Object;
    //   271: pop
    //   272: goto +20 -> 292
    //   275: astore_1
    //   276: aload_1
    //   277: invokevirtual 539	java/lang/Throwable:getCause	()Ljava/lang/Throwable;
    //   280: astore 4
    //   282: aload 4
    //   284: ifnull +6 -> 290
    //   287: aload 4
    //   289: athrow
    //   290: aload_1
    //   291: athrow
    //   292: aload_0
    //   293: invokevirtual 93	android/content/Context:getPackageName	()Ljava/lang/String;
    //   296: iconst_1
    //   297: invokevirtual 114	java/lang/String:codePointAt	(I)I
    //   300: bipush 108
    //   302: isub
    //   303: aload_0
    //   304: invokevirtual 93	android/content/Context:getPackageName	()Ljava/lang/String;
    //   307: bipush 9
    //   309: invokevirtual 114	java/lang/String:codePointAt	(I)I
    //   312: bipush 58
    //   314: isub
    //   315: aload_0
    //   316: invokevirtual 97	android/content/Context:getApplicationInfo	()Landroid/content/pm/ApplicationInfo;
    //   319: getfield 102	android/content/pm/ApplicationInfo:targetSdkVersion	I
    //   322: sipush 29322
    //   325: iadd
    //   326: i2c
    //   327: invokestatic 545	o/O:ˋ	(IIC)Ljava/lang/Object;
    //   330: checkcast 518	java/lang/Class
    //   333: ldc_w 821
    //   336: aconst_null
    //   337: invokevirtual 551	java/lang/Class:getMethod	(Ljava/lang/String;[Ljava/lang/Class;)Ljava/lang/reflect/Method;
    //   340: aconst_null
    //   341: aconst_null
    //   342: invokevirtual 557	java/lang/reflect/Method:invoke	(Ljava/lang/Object;[Ljava/lang/Object;)Ljava/lang/Object;
    //   345: astore 4
    //   347: goto +20 -> 367
    //   350: astore_1
    //   351: aload_1
    //   352: invokevirtual 539	java/lang/Throwable:getCause	()Ljava/lang/Throwable;
    //   355: astore 4
    //   357: aload 4
    //   359: ifnull +6 -> 365
    //   362: aload 4
    //   364: athrow
    //   365: aload_1
    //   366: athrow
    //   367: aload_0
    //   368: invokevirtual 74	android/content/Context:getResources	()Landroid/content/res/Resources;
    //   371: ldc_w 633
    //   374: invokevirtual 81	android/content/res/Resources:getString	(I)Ljava/lang/String;
    //   377: bipush 11
    //   379: bipush 16
    //   381: invokevirtual 85	java/lang/String:substring	(II)Ljava/lang/String;
    //   384: invokevirtual 89	java/lang/String:length	()I
    //   387: iconst_2
    //   388: isub
    //   389: aload_0
    //   390: invokevirtual 97	android/content/Context:getApplicationInfo	()Landroid/content/pm/ApplicationInfo;
    //   393: getfield 102	android/content/pm/ApplicationInfo:targetSdkVersion	I
    //   396: bipush 14
    //   398: iadd
    //   399: aload_0
    //   400: invokevirtual 74	android/content/Context:getResources	()Landroid/content/res/Resources;
    //   403: ldc_w 921
    //   406: invokevirtual 81	android/content/res/Resources:getString	(I)Ljava/lang/String;
    //   409: iconst_0
    //   410: iconst_4
    //   411: invokevirtual 85	java/lang/String:substring	(II)Ljava/lang/String;
    //   414: invokevirtual 89	java/lang/String:length	()I
    //   417: sipush 29343
    //   420: iadd
    //   421: i2c
    //   422: invokestatic 545	o/O:ˋ	(IIC)Ljava/lang/Object;
    //   425: checkcast 518	java/lang/Class
    //   428: ldc_w 922
    //   431: aconst_null
    //   432: invokevirtual 551	java/lang/Class:getMethod	(Ljava/lang/String;[Ljava/lang/Class;)Ljava/lang/reflect/Method;
    //   435: aload 4
    //   437: aconst_null
    //   438: invokevirtual 557	java/lang/reflect/Method:invoke	(Ljava/lang/Object;[Ljava/lang/Object;)Ljava/lang/Object;
    //   441: checkcast 711	java/lang/Boolean
    //   444: invokevirtual 715	java/lang/Boolean:booleanValue	()Z
    //   447: istore_3
    //   448: aload_0
    //   449: iload_3
    //   450: putfield 924	o/l:ʻॱ	Z
    //   453: aload_1
    //   454: ldc_w 925
    //   457: invokevirtual 930	android/view/Window:addFlags	(I)V
    //   460: goto +6 -> 466
    //   463: goto -460 -> 3
    //   466: getstatic 37	o/l:ʼॱ	I
    //   469: bipush 85
    //   471: iadd
    //   472: istore_2
    //   473: iload_2
    //   474: sipush 128
    //   477: irem
    //   478: putstatic 39	o/l:ʾ	I
    //   481: iload_2
    //   482: iconst_2
    //   483: irem
    //   484: ifeq +4 -> 488
    //   487: return
    //   488: return
    // Local variable table:
    //   start	length	slot	name	signature
    //   0	489	0	this	l
    //   0	489	1	paramWindow	android.view.Window
    //   472	12	2	i	int
    //   447	3	3	bool	boolean
    //   42	394	4	localObject	Object
    //   161	105	5	str	String
    // Exception table:
    //   from	to	target	type
    //   183	272	166	finally
    //   292	347	275	finally
    //   367	448	350	finally
  }
  
  /* Error */
  public boolean ॱ(String[] paramArrayOfString)
  {
    // Byte code:
    //   0: goto +199 -> 199
    //   3: aload_0
    //   4: aload_1
    //   5: iload_2
    //   6: aaload
    //   7: invokevirtual 932	o/l:ˊ	(Ljava/lang/String;)Z
    //   10: ifne +6 -> 16
    //   13: goto +138 -> 151
    //   16: goto +110 -> 126
    //   19: goto +41 -> 60
    //   22: iconst_1
    //   23: ireturn
    //   24: iload_3
    //   25: lookupswitch	default:+27->52, 24:+119->144, 35:+177->202
    //   52: goto +92 -> 144
    //   55: iconst_1
    //   56: istore_3
    //   57: goto +147 -> 204
    //   60: iload_2
    //   61: iload 4
    //   63: if_icmpge +6 -> 69
    //   66: goto -11 -> 55
    //   69: goto +66 -> 135
    //   72: getstatic 37	o/l:ʼॱ	I
    //   75: bipush 115
    //   77: iadd
    //   78: istore_2
    //   79: iload_2
    //   80: sipush 128
    //   83: irem
    //   84: putstatic 39	o/l:ʾ	I
    //   87: iload_2
    //   88: iconst_2
    //   89: irem
    //   90: ifeq +6 -> 96
    //   93: goto +48 -> 141
    //   96: goto +67 -> 163
    //   99: getstatic 37	o/l:ʼॱ	I
    //   102: bipush 55
    //   104: iadd
    //   105: istore_3
    //   106: iload_3
    //   107: sipush 128
    //   110: irem
    //   111: putstatic 39	o/l:ʾ	I
    //   114: iload_3
    //   115: iconst_2
    //   116: irem
    //   117: ifeq +6 -> 123
    //   120: goto -117 -> 3
    //   123: goto -120 -> 3
    //   126: bipush 24
    //   128: istore_3
    //   129: goto -105 -> 24
    //   132: astore_1
    //   133: aload_1
    //   134: athrow
    //   135: bipush 41
    //   137: istore_3
    //   138: goto +66 -> 204
    //   141: goto +22 -> 163
    //   144: iload_2
    //   145: iconst_1
    //   146: iadd
    //   147: istore_2
    //   148: goto +24 -> 172
    //   151: bipush 35
    //   153: istore_3
    //   154: goto -130 -> 24
    //   157: goto -135 -> 22
    //   160: goto -141 -> 19
    //   163: aload_1
    //   164: arraylength
    //   165: istore 4
    //   167: iconst_0
    //   168: istore_2
    //   169: goto -109 -> 60
    //   172: getstatic 37	o/l:ʼॱ	I
    //   175: bipush 83
    //   177: iadd
    //   178: istore_3
    //   179: iload_3
    //   180: sipush 128
    //   183: irem
    //   184: putstatic 39	o/l:ʾ	I
    //   187: iload_3
    //   188: iconst_2
    //   189: irem
    //   190: ifeq +6 -> 196
    //   193: goto -33 -> 160
    //   196: goto -177 -> 19
    //   199: goto -127 -> 72
    //   202: iconst_0
    //   203: ireturn
    //   204: iload_3
    //   205: lookupswitch	default:+27->232, 1:+-106->99, 41:+-48->157
    //   232: goto -75 -> 157
    //   235: astore_1
    //   236: aload_1
    //   237: athrow
    // Local variable table:
    //   start	length	slot	name	signature
    //   0	238	0	this	l
    //   0	238	1	paramArrayOfString	String[]
    //   5	164	2	i	int
    //   24	181	3	j	int
    //   61	105	4	k	int
    // Exception table:
    //   from	to	target	type
    //   72	79	132	java/lang/Exception
    //   79	87	132	java/lang/Exception
    //   79	87	235	java/lang/Exception
  }
  
  /* Error */
  public Context ॱˊ()
  {
    // Byte code:
    //   0: goto +118 -> 118
    //   3: astore_2
    //   4: aload_2
    //   5: athrow
    //   6: aload_0
    //   7: astore_2
    //   8: getstatic 39	o/l:ʾ	I
    //   11: bipush 85
    //   13: iadd
    //   14: istore_1
    //   15: iload_1
    //   16: sipush 128
    //   19: irem
    //   20: putstatic 37	o/l:ʼॱ	I
    //   23: iload_1
    //   24: iconst_2
    //   25: irem
    //   26: ifne +6 -> 32
    //   29: goto +78 -> 107
    //   32: aload_2
    //   33: areturn
    //   34: getstatic 39	o/l:ʾ	I
    //   37: bipush 9
    //   39: iadd
    //   40: istore_1
    //   41: iload_1
    //   42: sipush 128
    //   45: irem
    //   46: putstatic 37	o/l:ʼॱ	I
    //   49: iload_1
    //   50: iconst_2
    //   51: irem
    //   52: ifne +6 -> 58
    //   55: goto +46 -> 101
    //   58: goto +37 -> 95
    //   61: astore_2
    //   62: aload_2
    //   63: athrow
    //   64: iload_1
    //   65: lookupswitch	default:+27->92, 32:+44->109, 91:+50->115
    //   92: goto +17 -> 109
    //   95: bipush 91
    //   97: istore_1
    //   98: goto -34 -> 64
    //   101: bipush 32
    //   103: istore_1
    //   104: goto -40 -> 64
    //   107: aload_2
    //   108: areturn
    //   109: aconst_null
    //   110: arraylength
    //   111: istore_1
    //   112: goto -106 -> 6
    //   115: goto -109 -> 6
    //   118: goto -84 -> 34
    // Local variable table:
    //   start	length	slot	name	signature
    //   0	121	0	this	l
    //   14	98	1	i	int
    //   3	2	2	localException1	Exception
    //   7	26	2	localL	l
    //   61	47	2	localException2	Exception
    // Exception table:
    //   from	to	target	type
    //   34	41	3	java/lang/Exception
    //   41	49	3	java/lang/Exception
    //   41	49	61	java/lang/Exception
  }
}
