package o;

import android.app.Activity;
import android.content.Context;
import android.view.View;
import android.view.View.OnClickListener;

public final class LC
  extends o<FF, ˋ>
{
  private static int ˎ = 0;
  private static int[] ˏ = { 85154082, 1949533817, -913969169, 1829493326, -925939260, 1490641360, -2020239897, 23571424, 159748616, 2133648110, -1235212659, -166844339, -1562844574, 1480595196, 1240771441, 154171784, -1052871082, -1667577022 };
  private static int ॱ = 1;
  private Activity ˋ;
  
  public LC() {}
  
  /* Error */
  private static String ˎ(int[] paramArrayOfInt, int paramInt)
  {
    // Byte code:
    //   0: goto +190 -> 190
    //   3: iconst_3
    //   4: newarray char
    //   6: astore 5
    //   8: aload_0
    //   9: arraylength
    //   10: iconst_0
    //   11: ishl
    //   12: newarray char
    //   14: astore 6
    //   16: getstatic 40	o/LC:ˏ	[I
    //   19: astore 4
    //   21: aload 4
    //   23: invokevirtual 52	[I:clone	()Ljava/lang/Object;
    //   26: astore 4
    //   28: aload 4
    //   30: checkcast 48	[I
    //   33: astore 4
    //   35: goto +48 -> 83
    //   38: bipush 57
    //   40: istore_3
    //   41: goto +47 -> 88
    //   44: bipush 49
    //   46: istore_2
    //   47: goto +72 -> 119
    //   50: bipush 68
    //   52: istore_3
    //   53: goto +35 -> 88
    //   56: bipush 39
    //   58: istore_2
    //   59: goto +60 -> 119
    //   62: iload_2
    //   63: aload_0
    //   64: arraylength
    //   65: if_icmpge +6 -> 71
    //   68: goto -18 -> 50
    //   71: goto -33 -> 38
    //   74: goto -12 -> 62
    //   77: goto +167 -> 244
    //   80: astore_0
    //   81: aload_0
    //   82: athrow
    //   83: iconst_0
    //   84: istore_2
    //   85: goto -23 -> 62
    //   88: iload_3
    //   89: lookupswitch	default:+27->116, 57:+62->151, 68:+131->220
    //   116: goto +104 -> 220
    //   119: iload_2
    //   120: lookupswitch	default:+28->148, 39:+73->193, 49:+-117->3
    //   148: goto -145 -> 3
    //   151: new 54	java/lang/String
    //   154: dup
    //   155: aload 6
    //   157: iconst_0
    //   158: iload_1
    //   159: invokespecial 57	java/lang/String:<init>	([CII)V
    //   162: areturn
    //   163: getstatic 20	o/LC:ॱ	I
    //   166: bipush 9
    //   168: iadd
    //   169: istore_2
    //   170: iload_2
    //   171: sipush 128
    //   174: irem
    //   175: putstatic 18	o/LC:ˎ	I
    //   178: iload_2
    //   179: iconst_2
    //   180: irem
    //   181: ifeq +6 -> 187
    //   184: goto -140 -> 44
    //   187: goto -131 -> 56
    //   190: goto -27 -> 163
    //   193: iconst_4
    //   194: newarray char
    //   196: astore 5
    //   198: aload_0
    //   199: arraylength
    //   200: iconst_1
    //   201: ishl
    //   202: newarray char
    //   204: astore 6
    //   206: getstatic 40	o/LC:ˏ	[I
    //   209: invokevirtual 52	[I:clone	()Ljava/lang/Object;
    //   212: checkcast 48	[I
    //   215: astore 4
    //   217: goto -134 -> 83
    //   220: getstatic 20	o/LC:ॱ	I
    //   223: bipush 125
    //   225: iadd
    //   226: istore_3
    //   227: iload_3
    //   228: sipush 128
    //   231: irem
    //   232: putstatic 18	o/LC:ˎ	I
    //   235: iload_3
    //   236: iconst_2
    //   237: irem
    //   238: ifeq +6 -> 244
    //   241: goto -164 -> 77
    //   244: aload 5
    //   246: iconst_0
    //   247: aload_0
    //   248: iload_2
    //   249: iaload
    //   250: bipush 16
    //   252: ishr
    //   253: i2c
    //   254: castore
    //   255: aload 5
    //   257: iconst_1
    //   258: aload_0
    //   259: iload_2
    //   260: iaload
    //   261: i2c
    //   262: castore
    //   263: aload 5
    //   265: iconst_2
    //   266: aload_0
    //   267: iload_2
    //   268: iconst_1
    //   269: iadd
    //   270: iaload
    //   271: bipush 16
    //   273: ishr
    //   274: i2c
    //   275: castore
    //   276: aload 5
    //   278: iconst_3
    //   279: aload_0
    //   280: iload_2
    //   281: iconst_1
    //   282: iadd
    //   283: iaload
    //   284: i2c
    //   285: castore
    //   286: aload 5
    //   288: aload 4
    //   290: iconst_0
    //   291: invokestatic 62	o/oN:ˏ	([C[IZ)[I
    //   294: pop
    //   295: aload 6
    //   297: iload_2
    //   298: iconst_1
    //   299: ishl
    //   300: aload 5
    //   302: iconst_0
    //   303: caload
    //   304: castore
    //   305: aload 6
    //   307: iload_2
    //   308: iconst_1
    //   309: ishl
    //   310: iconst_1
    //   311: iadd
    //   312: aload 5
    //   314: iconst_1
    //   315: caload
    //   316: castore
    //   317: aload 6
    //   319: iload_2
    //   320: iconst_1
    //   321: ishl
    //   322: iconst_2
    //   323: iadd
    //   324: aload 5
    //   326: iconst_2
    //   327: caload
    //   328: castore
    //   329: aload 6
    //   331: iload_2
    //   332: iconst_1
    //   333: ishl
    //   334: iconst_3
    //   335: iadd
    //   336: aload 5
    //   338: iconst_3
    //   339: caload
    //   340: castore
    //   341: iload_2
    //   342: iconst_2
    //   343: iadd
    //   344: istore_2
    //   345: goto -271 -> 74
    //   348: astore_0
    //   349: aload_0
    //   350: athrow
    // Local variable table:
    //   start	length	slot	name	signature
    //   0	351	0	paramArrayOfInt	int[]
    //   0	351	1	paramInt	int
    //   46	299	2	i	int
    //   40	198	3	j	int
    //   19	270	4	localObject	Object
    //   6	331	5	arrayOfChar1	char[]
    //   14	316	6	arrayOfChar2	char[]
    // Exception table:
    //   from	to	target	type
    //   16	21	80	java/lang/Exception
    //   21	28	348	java/lang/Exception
    //   28	35	348	java/lang/Exception
  }
  
  /* Error */
  public ˋ ˊ(android.view.ViewGroup paramViewGroup, int paramInt)
  {
    // Byte code:
    //   0: goto +29 -> 29
    //   3: getstatic 18	o/LC:ˎ	I
    //   6: bipush 33
    //   8: iadd
    //   9: istore_2
    //   10: iload_2
    //   11: sipush 128
    //   14: irem
    //   15: putstatic 20	o/LC:ॱ	I
    //   18: iload_2
    //   19: iconst_2
    //   20: irem
    //   21: ifne +6 -> 27
    //   24: goto +11 -> 35
    //   27: aload_1
    //   28: areturn
    //   29: goto +8 -> 37
    //   32: astore_1
    //   33: aload_1
    //   34: athrow
    //   35: aload_1
    //   36: areturn
    //   37: iconst_4
    //   38: newarray int
    //   40: dup
    //   41: iconst_0
    //   42: ldc 68
    //   44: iastore
    //   45: dup
    //   46: iconst_1
    //   47: ldc 69
    //   49: iastore
    //   50: dup
    //   51: iconst_2
    //   52: ldc 70
    //   54: iastore
    //   55: dup
    //   56: iconst_3
    //   57: ldc 71
    //   59: iastore
    //   60: bipush 6
    //   62: invokestatic 73	o/LC:ˎ	([II)Ljava/lang/String;
    //   65: astore_3
    //   66: aload_3
    //   67: invokevirtual 77	java/lang/String:intern	()Ljava/lang/String;
    //   70: astore_3
    //   71: aload_1
    //   72: aload_3
    //   73: invokestatic 82	o/vq:ˎ	(Ljava/lang/Object;Ljava/lang/String;)V
    //   76: getstatic 87	o/Lt$ˋ:layout_offer_card	I
    //   79: istore_2
    //   80: aload_0
    //   81: aload_1
    //   82: iload_2
    //   83: invokevirtual 90	o/LC:ॱ	(Landroid/view/ViewGroup;I)Landroid/view/View;
    //   86: astore_1
    //   87: aload_1
    //   88: bipush 22
    //   90: newarray int
    //   92: dup
    //   93: iconst_0
    //   94: ldc 91
    //   96: iastore
    //   97: dup
    //   98: iconst_1
    //   99: ldc 92
    //   101: iastore
    //   102: dup
    //   103: iconst_2
    //   104: ldc 93
    //   106: iastore
    //   107: dup
    //   108: iconst_3
    //   109: ldc 94
    //   111: iastore
    //   112: dup
    //   113: iconst_4
    //   114: ldc 68
    //   116: iastore
    //   117: dup
    //   118: iconst_5
    //   119: ldc 69
    //   121: iastore
    //   122: dup
    //   123: bipush 6
    //   125: ldc 95
    //   127: iastore
    //   128: dup
    //   129: bipush 7
    //   131: ldc 96
    //   133: iastore
    //   134: dup
    //   135: bipush 8
    //   137: ldc 97
    //   139: iastore
    //   140: dup
    //   141: bipush 9
    //   143: ldc 98
    //   145: iastore
    //   146: dup
    //   147: bipush 10
    //   149: ldc 99
    //   151: iastore
    //   152: dup
    //   153: bipush 11
    //   155: ldc 100
    //   157: iastore
    //   158: dup
    //   159: bipush 12
    //   161: ldc 101
    //   163: iastore
    //   164: dup
    //   165: bipush 13
    //   167: ldc 102
    //   169: iastore
    //   170: dup
    //   171: bipush 14
    //   173: ldc 103
    //   175: iastore
    //   176: dup
    //   177: bipush 15
    //   179: ldc 104
    //   181: iastore
    //   182: dup
    //   183: bipush 16
    //   185: ldc 105
    //   187: iastore
    //   188: dup
    //   189: bipush 17
    //   191: ldc 106
    //   193: iastore
    //   194: dup
    //   195: bipush 18
    //   197: ldc 107
    //   199: iastore
    //   200: dup
    //   201: bipush 19
    //   203: ldc 108
    //   205: iastore
    //   206: dup
    //   207: bipush 20
    //   209: ldc 109
    //   211: iastore
    //   212: dup
    //   213: bipush 21
    //   215: ldc 110
    //   217: iastore
    //   218: bipush 43
    //   220: invokestatic 73	o/LC:ˎ	([II)Ljava/lang/String;
    //   223: invokevirtual 77	java/lang/String:intern	()Ljava/lang/String;
    //   226: invokestatic 112	o/vq:ˋ	(Ljava/lang/Object;Ljava/lang/String;)V
    //   229: new 7	o/LC$ˋ
    //   232: dup
    //   233: aload_0
    //   234: aload_1
    //   235: invokespecial 115	o/LC$ˋ:<init>	(Lo/LC;Landroid/view/View;)V
    //   238: astore_1
    //   239: goto -236 -> 3
    //   242: astore_1
    //   243: aload_1
    //   244: athrow
    // Local variable table:
    //   start	length	slot	name	signature
    //   0	245	0	this	LC
    //   0	245	1	paramViewGroup	android.view.ViewGroup
    //   0	245	2	paramInt	int
    //   65	8	3	str	String
    // Exception table:
    //   from	to	target	type
    //   37	66	32	java/lang/Exception
    //   37	66	242	java/lang/Exception
    //   66	71	242	java/lang/Exception
    //   71	76	242	java/lang/Exception
    //   76	80	242	java/lang/Exception
    //   80	239	242	java/lang/Exception
  }
  
  public void ˊ(ˋ paramˋ, int paramInt)
  {
    break label248;
    vq.ˎ(paramˋ, ˎ(new int[] { 228800708, -1449593499, -1074078096, -808174890 }, 6).intern());
    FF localFF = (FF)ॱ(paramInt);
    LF localLF = (LF)paramˋ.ˋ();
    vq.ˋ(localLF, ˎ(new int[] { 228800708, -1449593499, -718544856, -151109835, -876442843, 257049788, -582134285, -1572554494 }, 14).intern());
    localLF.ॱ(localFF);
    paramˋ = paramˋ.ॱ;
    vq.ˋ(paramˋ, ˎ(new int[] { 228800708, -1449593499, 2015815159, 1270605254, -1923663800, -1873918886, 867432113, -559854467 }, 15).intern());
    paramˋ.setTag(localFF);
    label248:
    for (;;)
    {
      int i = ˎ + 39;
      ॱ = i % 128;
      if (i % 2 != 0)
      {
        break;
        paramInt = ˎ + 91;
        ॱ = paramInt % 128;
        if (paramInt % 2 == 0) {
          return;
        }
        return;
      }
      break;
    }
  }
  
  public final class ˋ
    extends p<LF>
    implements View.OnClickListener
  {
    private static int ʻॱ = 0;
    private static int[] ˊॱ = { 2039818755, 208163386, 1505168182, -1556198609, -763183132, 454446937, -77831659, -442309858, -422548704, -1695353547, 1206276933, 2033152417, -1883573893, 610288753, 473708365, -2025971882, 480400032, 750972980 };
    private static int ᐝॱ = 1;
    
    public ˋ()
    {
      super();
      Context localContext = ॱ();
      if (localContext != null) {
        for (;;)
        {
          int i = ᐝॱ + 77;
          ʻॱ = i % 128;
          if (i % 2 == 0) {
            break label105;
          }
          label105:
          for (i = 0;; i = 1) {
            switch (i)
            {
            case 1: 
            default: 
              return;
            }
          }
          throw new NullPointerException();
          LC.ˏ(LC.this, (Activity)localContext);
          localObject.setOnClickListener((View.OnClickListener)this);
        }
      }
      throw new uH(ˋ(new int[] { -253742562, -1302487068, 1859705837, 1612544036, 1363356009, 247530575, 789696016, -1005940913, 1754647215, 613354395, -813863396, -1215328789, 681476128, -1790503021, -1458437965, -770409108, -479396013, 1184738684, 1931683519, -1236224771, 1108135335, 630885045, 634624357, -1036425202, 794503156, 243963999, 1392273206, 1790966541, -1456098003, -325910752 }, 57).intern());
    }
    
    /* Error */
    private static String ˋ(int[] paramArrayOfInt, int paramInt)
    {
      // Byte code:
      //   0: goto +8 -> 8
      //   3: iconst_0
      //   4: istore_3
      //   5: goto +38 -> 43
      //   8: goto +244 -> 252
      //   11: iconst_1
      //   12: istore_1
      //   13: goto +270 -> 283
      //   16: getstatic 23	o/LC$ˋ:ᐝॱ	I
      //   19: bipush 123
      //   21: iadd
      //   22: istore_1
      //   23: iload_1
      //   24: sipush 128
      //   27: irem
      //   28: putstatic 21	o/LC$ˋ:ʻॱ	I
      //   31: iload_1
      //   32: iconst_2
      //   33: irem
      //   34: ifeq +6 -> 40
      //   37: goto +106 -> 143
      //   40: goto -29 -> 11
      //   43: iload_3
      //   44: tableswitch	default:+24->68, 0:+66->110, 1:+39->83
      //   68: goto +15 -> 83
      //   71: iload_2
      //   72: aload_0
      //   73: arraylength
      //   74: if_icmpge +6 -> 80
      //   77: goto +48 -> 125
      //   80: goto -77 -> 3
      //   83: getstatic 21	o/LC$ˋ:ʻॱ	I
      //   86: bipush 93
      //   88: iadd
      //   89: istore_3
      //   90: iload_3
      //   91: sipush 128
      //   94: irem
      //   95: putstatic 23	o/LC$ˋ:ᐝॱ	I
      //   98: iload_3
      //   99: iconst_2
      //   100: irem
      //   101: ifne +6 -> 107
      //   104: goto +26 -> 130
      //   107: goto +41 -> 148
      //   110: new 53	java/lang/String
      //   113: dup
      //   114: aload 5
      //   116: iconst_0
      //   117: iload_1
      //   118: invokespecial 129	java/lang/String:<init>	([CII)V
      //   121: astore_0
      //   122: goto -106 -> 16
      //   125: iconst_1
      //   126: istore_3
      //   127: goto -84 -> 43
      //   130: goto +18 -> 148
      //   133: astore_0
      //   134: aload_0
      //   135: athrow
      //   136: bipush 89
      //   138: iconst_0
      //   139: idiv
      //   140: istore_1
      //   141: aload_0
      //   142: areturn
      //   143: iconst_0
      //   144: istore_1
      //   145: goto +138 -> 283
      //   148: aload 4
      //   150: iconst_0
      //   151: aload_0
      //   152: iload_2
      //   153: iaload
      //   154: bipush 16
      //   156: ishr
      //   157: i2c
      //   158: castore
      //   159: aload 4
      //   161: iconst_1
      //   162: aload_0
      //   163: iload_2
      //   164: iaload
      //   165: i2c
      //   166: castore
      //   167: aload 4
      //   169: iconst_2
      //   170: aload_0
      //   171: iload_2
      //   172: iconst_1
      //   173: iadd
      //   174: iaload
      //   175: bipush 16
      //   177: ishr
      //   178: i2c
      //   179: castore
      //   180: aload 4
      //   182: iconst_3
      //   183: aload_0
      //   184: iload_2
      //   185: iconst_1
      //   186: iadd
      //   187: iaload
      //   188: i2c
      //   189: castore
      //   190: aload 4
      //   192: aload 6
      //   194: iconst_0
      //   195: invokestatic 134	o/oN:ˏ	([C[IZ)[I
      //   198: pop
      //   199: aload 5
      //   201: iload_2
      //   202: iconst_1
      //   203: ishl
      //   204: aload 4
      //   206: iconst_0
      //   207: caload
      //   208: castore
      //   209: aload 5
      //   211: iload_2
      //   212: iconst_1
      //   213: ishl
      //   214: iconst_1
      //   215: iadd
      //   216: aload 4
      //   218: iconst_1
      //   219: caload
      //   220: castore
      //   221: aload 5
      //   223: iload_2
      //   224: iconst_1
      //   225: ishl
      //   226: iconst_2
      //   227: iadd
      //   228: aload 4
      //   230: iconst_2
      //   231: caload
      //   232: castore
      //   233: aload 5
      //   235: iload_2
      //   236: iconst_1
      //   237: ishl
      //   238: iconst_3
      //   239: iadd
      //   240: aload 4
      //   242: iconst_3
      //   243: caload
      //   244: castore
      //   245: iload_2
      //   246: iconst_2
      //   247: iadd
      //   248: istore_2
      //   249: goto -178 -> 71
      //   252: iconst_4
      //   253: newarray char
      //   255: astore 4
      //   257: aload_0
      //   258: arraylength
      //   259: iconst_1
      //   260: ishl
      //   261: newarray char
      //   263: astore 5
      //   265: getstatic 43	o/LC$ˋ:ˊॱ	[I
      //   268: invokevirtual 139	[I:clone	()Ljava/lang/Object;
      //   271: checkcast 135	[I
      //   274: astore 6
      //   276: iconst_0
      //   277: istore_2
      //   278: goto -207 -> 71
      //   281: aload_0
      //   282: areturn
      //   283: iload_1
      //   284: tableswitch	default:+24->308, 0:+-148->136, 1:+-3->281
      //   308: aload_0
      //   309: areturn
      // Local variable table:
      //   start	length	slot	name	signature
      //   0	310	0	paramArrayOfInt	int[]
      //   0	310	1	paramInt	int
      //   71	207	2	i	int
      //   4	123	3	j	int
      //   148	108	4	arrayOfChar1	char[]
      //   114	150	5	arrayOfChar2	char[]
      //   192	83	6	arrayOfInt	int[]
      // Exception table:
      //   from	to	target	type
      //   190	199	133	java/lang/Exception
    }
    
    /* Error */
    public void onClick(View paramView)
    {
      // Byte code:
      //   0: goto +57 -> 57
      //   3: getstatic 23	o/LC$ˋ:ᐝॱ	I
      //   6: bipush 97
      //   8: iadd
      //   9: istore_2
      //   10: iload_2
      //   11: sipush 128
      //   14: irem
      //   15: putstatic 21	o/LC$ˋ:ʻॱ	I
      //   18: iload_2
      //   19: iconst_2
      //   20: irem
      //   21: ifeq +6 -> 27
      //   24: goto +184 -> 208
      //   27: goto +448 -> 475
      //   30: getstatic 21	o/LC$ˋ:ʻॱ	I
      //   33: bipush 61
      //   35: iadd
      //   36: istore_2
      //   37: iload_2
      //   38: sipush 128
      //   41: irem
      //   42: putstatic 23	o/LC$ˋ:ᐝॱ	I
      //   45: iload_2
      //   46: iconst_2
      //   47: irem
      //   48: ifne +6 -> 54
      //   51: goto +9 -> 60
      //   54: goto +494 -> 548
      //   57: goto -27 -> 30
      //   60: aload_1
      //   61: iconst_2
      //   62: newarray int
      //   64: dup
      //   65: iconst_0
      //   66: ldc 47
      //   68: iastore
      //   69: dup
      //   70: iconst_1
      //   71: ldc 48
      //   73: iastore
      //   74: iconst_4
      //   75: invokestatic 51	o/LC$ˋ:ˋ	([II)Ljava/lang/String;
      //   78: invokevirtual 57	java/lang/String:intern	()Ljava/lang/String;
      //   81: invokestatic 63	o/vq:ˎ	(Ljava/lang/Object;Ljava/lang/String;)V
      //   84: goto +20 -> 104
      //   87: astore_1
      //   88: aload_1
      //   89: invokevirtual 146	java/lang/Throwable:getCause	()Ljava/lang/Throwable;
      //   92: astore 4
      //   94: aload 4
      //   96: ifnull +6 -> 102
      //   99: aload 4
      //   101: athrow
      //   102: aload_1
      //   103: athrow
      //   104: iconst_3
      //   105: bipush 24
      //   107: iconst_0
      //   108: invokestatic 151	o/O:ˋ	(IIC)Ljava/lang/Object;
      //   111: checkcast 153	java/lang/Class
      //   114: ldc -102
      //   116: aconst_null
      //   117: invokevirtual 158	java/lang/Class:getMethod	(Ljava/lang/String;[Ljava/lang/Class;)Ljava/lang/reflect/Method;
      //   120: aconst_null
      //   121: aconst_null
      //   122: invokevirtual 164	java/lang/reflect/Method:invoke	(Ljava/lang/Object;[Ljava/lang/Object;)Ljava/lang/Object;
      //   125: astore 4
      //   127: aload_0
      //   128: invokevirtual 72	o/LC$ˋ:ॱ	()Landroid/content/Context;
      //   131: astore 5
      //   133: goto +20 -> 153
      //   136: astore_1
      //   137: aload_1
      //   138: invokevirtual 146	java/lang/Throwable:getCause	()Ljava/lang/Throwable;
      //   141: astore 4
      //   143: aload 4
      //   145: ifnull +6 -> 151
      //   148: aload 4
      //   150: athrow
      //   151: aload_1
      //   152: athrow
      //   153: iconst_3
      //   154: bipush 24
      //   156: iconst_0
      //   157: invokestatic 151	o/O:ˋ	(IIC)Ljava/lang/Object;
      //   160: checkcast 153	java/lang/Class
      //   163: ldc -91
      //   165: iconst_1
      //   166: anewarray 153	java/lang/Class
      //   169: dup
      //   170: iconst_0
      //   171: ldc -89
      //   173: aastore
      //   174: invokevirtual 158	java/lang/Class:getMethod	(Ljava/lang/String;[Ljava/lang/Class;)Ljava/lang/reflect/Method;
      //   177: aload 4
      //   179: iconst_1
      //   180: anewarray 169	java/lang/Object
      //   183: dup
      //   184: iconst_0
      //   185: aload 5
      //   187: aastore
      //   188: invokevirtual 164	java/lang/reflect/Method:invoke	(Ljava/lang/Object;[Ljava/lang/Object;)Ljava/lang/Object;
      //   191: checkcast 171	java/lang/Boolean
      //   194: invokevirtual 175	java/lang/Boolean:booleanValue	()Z
      //   197: istore_3
      //   198: iload_3
      //   199: ifeq +6 -> 205
      //   202: goto +312 -> 514
      //   205: goto +265 -> 470
      //   208: goto +267 -> 475
      //   211: iload_2
      //   212: tableswitch	default:+24->236, 0:+299->511, 1:+-209->3
      //   236: goto -233 -> 3
      //   239: new 90	o/uH
      //   242: dup
      //   243: bipush 36
      //   245: newarray int
      //   247: dup
      //   248: iconst_0
      //   249: ldc 91
      //   251: iastore
      //   252: dup
      //   253: iconst_1
      //   254: ldc 92
      //   256: iastore
      //   257: dup
      //   258: iconst_2
      //   259: ldc 93
      //   261: iastore
      //   262: dup
      //   263: iconst_3
      //   264: ldc 94
      //   266: iastore
      //   267: dup
      //   268: iconst_4
      //   269: ldc 95
      //   271: iastore
      //   272: dup
      //   273: iconst_5
      //   274: ldc 96
      //   276: iastore
      //   277: dup
      //   278: bipush 6
      //   280: ldc 97
      //   282: iastore
      //   283: dup
      //   284: bipush 7
      //   286: ldc 98
      //   288: iastore
      //   289: dup
      //   290: bipush 8
      //   292: ldc 99
      //   294: iastore
      //   295: dup
      //   296: bipush 9
      //   298: ldc 100
      //   300: iastore
      //   301: dup
      //   302: bipush 10
      //   304: ldc 101
      //   306: iastore
      //   307: dup
      //   308: bipush 11
      //   310: ldc 102
      //   312: iastore
      //   313: dup
      //   314: bipush 12
      //   316: ldc 103
      //   318: iastore
      //   319: dup
      //   320: bipush 13
      //   322: ldc 104
      //   324: iastore
      //   325: dup
      //   326: bipush 14
      //   328: ldc 105
      //   330: iastore
      //   331: dup
      //   332: bipush 15
      //   334: ldc 106
      //   336: iastore
      //   337: dup
      //   338: bipush 16
      //   340: ldc 107
      //   342: iastore
      //   343: dup
      //   344: bipush 17
      //   346: ldc 108
      //   348: iastore
      //   349: dup
      //   350: bipush 18
      //   352: ldc -80
      //   354: iastore
      //   355: dup
      //   356: bipush 19
      //   358: ldc -79
      //   360: iastore
      //   361: dup
      //   362: bipush 20
      //   364: ldc -78
      //   366: iastore
      //   367: dup
      //   368: bipush 21
      //   370: ldc -77
      //   372: iastore
      //   373: dup
      //   374: bipush 22
      //   376: ldc -76
      //   378: iastore
      //   379: dup
      //   380: bipush 23
      //   382: ldc -75
      //   384: iastore
      //   385: dup
      //   386: bipush 24
      //   388: ldc -74
      //   390: iastore
      //   391: dup
      //   392: bipush 25
      //   394: ldc -73
      //   396: iastore
      //   397: dup
      //   398: bipush 26
      //   400: ldc -72
      //   402: iastore
      //   403: dup
      //   404: bipush 27
      //   406: ldc -71
      //   408: iastore
      //   409: dup
      //   410: bipush 28
      //   412: ldc -70
      //   414: iastore
      //   415: dup
      //   416: bipush 29
      //   418: ldc -69
      //   420: iastore
      //   421: dup
      //   422: bipush 30
      //   424: ldc -68
      //   426: iastore
      //   427: dup
      //   428: bipush 31
      //   430: ldc -67
      //   432: iastore
      //   433: dup
      //   434: bipush 32
      //   436: ldc -66
      //   438: iastore
      //   439: dup
      //   440: bipush 33
      //   442: ldc -65
      //   444: iastore
      //   445: dup
      //   446: bipush 34
      //   448: ldc -64
      //   450: iastore
      //   451: dup
      //   452: bipush 35
      //   454: ldc -63
      //   456: iastore
      //   457: bipush 71
      //   459: invokestatic 51	o/LC$ˋ:ˋ	([II)Ljava/lang/String;
      //   462: invokevirtual 57	java/lang/String:intern	()Ljava/lang/String;
      //   465: invokespecial 123	o/uH:<init>	(Ljava/lang/String;)V
      //   468: athrow
      //   469: return
      //   470: iconst_1
      //   471: istore_2
      //   472: goto +44 -> 516
      //   475: aload_1
      //   476: invokevirtual 196	android/view/View:getTag	()Ljava/lang/Object;
      //   479: astore_1
      //   480: aload_1
      //   481: ifnonnull +6 -> 487
      //   484: goto -245 -> 239
      //   487: aload_1
      //   488: checkcast 198	o/FF
      //   491: astore_1
      //   492: aload_0
      //   493: invokevirtual 72	o/LC$ˋ:ॱ	()Landroid/content/Context;
      //   496: invokestatic 203	o/Ic:ˏ	(Landroid/content/Context;)Lo/Ic;
      //   499: aload_1
      //   500: invokevirtual 205	o/FF:ˎ	()Ljava/lang/String;
      //   503: invokevirtual 209	o/Ic:ʽ	(Ljava/lang/String;)Lo/j;
      //   506: bipush 28
      //   508: invokevirtual 214	o/j:ˎ	(I)V
      //   511: goto +187 -> 698
      //   514: iconst_0
      //   515: istore_2
      //   516: iload_2
      //   517: tableswitch	default:+23->540, 0:+-514->3, 1:+-6->511
      //   540: goto -537 -> 3
      //   543: iconst_1
      //   544: istore_2
      //   545: goto -334 -> 211
      //   548: aload_1
      //   549: iconst_2
      //   550: newarray int
      //   552: dup
      //   553: iconst_0
      //   554: ldc 47
      //   556: iastore
      //   557: dup
      //   558: iconst_1
      //   559: ldc 48
      //   561: iastore
      //   562: iconst_4
      //   563: invokestatic 51	o/LC$ˋ:ˋ	([II)Ljava/lang/String;
      //   566: invokevirtual 57	java/lang/String:intern	()Ljava/lang/String;
      //   569: invokestatic 63	o/vq:ˎ	(Ljava/lang/Object;Ljava/lang/String;)V
      //   572: goto +20 -> 592
      //   575: astore_1
      //   576: aload_1
      //   577: invokevirtual 146	java/lang/Throwable:getCause	()Ljava/lang/Throwable;
      //   580: astore 4
      //   582: aload 4
      //   584: ifnull +6 -> 590
      //   587: aload 4
      //   589: athrow
      //   590: aload_1
      //   591: athrow
      //   592: iconst_3
      //   593: bipush 24
      //   595: iconst_0
      //   596: invokestatic 151	o/O:ˋ	(IIC)Ljava/lang/Object;
      //   599: checkcast 153	java/lang/Class
      //   602: ldc -102
      //   604: aconst_null
      //   605: invokevirtual 158	java/lang/Class:getMethod	(Ljava/lang/String;[Ljava/lang/Class;)Ljava/lang/reflect/Method;
      //   608: aconst_null
      //   609: aconst_null
      //   610: invokevirtual 164	java/lang/reflect/Method:invoke	(Ljava/lang/Object;[Ljava/lang/Object;)Ljava/lang/Object;
      //   613: astore 4
      //   615: aload_0
      //   616: invokevirtual 72	o/LC$ˋ:ॱ	()Landroid/content/Context;
      //   619: astore 5
      //   621: goto +20 -> 641
      //   624: astore_1
      //   625: aload_1
      //   626: invokevirtual 146	java/lang/Throwable:getCause	()Ljava/lang/Throwable;
      //   629: astore 4
      //   631: aload 4
      //   633: ifnull +6 -> 639
      //   636: aload 4
      //   638: athrow
      //   639: aload_1
      //   640: athrow
      //   641: iconst_3
      //   642: bipush 24
      //   644: iconst_0
      //   645: invokestatic 151	o/O:ˋ	(IIC)Ljava/lang/Object;
      //   648: checkcast 153	java/lang/Class
      //   651: ldc -91
      //   653: iconst_1
      //   654: anewarray 153	java/lang/Class
      //   657: dup
      //   658: iconst_0
      //   659: ldc -89
      //   661: aastore
      //   662: invokevirtual 158	java/lang/Class:getMethod	(Ljava/lang/String;[Ljava/lang/Class;)Ljava/lang/reflect/Method;
      //   665: aload 4
      //   667: iconst_1
      //   668: anewarray 169	java/lang/Object
      //   671: dup
      //   672: iconst_0
      //   673: aload 5
      //   675: aastore
      //   676: invokevirtual 164	java/lang/reflect/Method:invoke	(Ljava/lang/Object;[Ljava/lang/Object;)Ljava/lang/Object;
      //   679: checkcast 171	java/lang/Boolean
      //   682: invokevirtual 175	java/lang/Boolean:booleanValue	()Z
      //   685: istore_3
      //   686: iload_3
      //   687: ifeq +6 -> 693
      //   690: goto -147 -> 543
      //   693: iconst_0
      //   694: istore_2
      //   695: goto -484 -> 211
      //   698: getstatic 23	o/LC$ˋ:ᐝॱ	I
      //   701: bipush 7
      //   703: iadd
      //   704: istore_2
      //   705: iload_2
      //   706: sipush 128
      //   709: irem
      //   710: putstatic 21	o/LC$ˋ:ʻॱ	I
      //   713: iload_2
      //   714: iconst_2
      //   715: irem
      //   716: ifeq +6 -> 722
      //   719: goto -250 -> 469
      //   722: return
      //   723: astore_1
      //   724: aload_1
      //   725: athrow
      // Local variable table:
      //   start	length	slot	name	signature
      //   0	726	0	this	ˋ
      //   0	726	1	paramView	View
      //   9	707	2	i	int
      //   197	490	3	bool	boolean
      //   92	574	4	localObject	Object
      //   131	543	5	localContext	Context
      // Exception table:
      //   from	to	target	type
      //   104	127	87	finally
      //   153	198	136	finally
      //   592	615	575	finally
      //   641	686	624	finally
      //   475	480	723	java/lang/Exception
    }
  }
}
