package o;

import android.content.res.Resources;
import android.databinding.ViewDataBinding;
import android.databinding.ViewDataBinding.If;
import android.text.TextUtils;
import android.util.SparseIntArray;
import android.view.View;
import android.widget.Button;
import android.widget.LinearLayout;
import android.widget.ProgressBar;
import android.widget.RelativeLayout;
import android.widget.TextView;

public class LD
  extends ViewDataBinding
{
  private static final SparseIntArray ʿ;
  private static byte ˊᐝ;
  private static int ˋˋ;
  private static int ˋᐝ;
  private static byte[] ˌ;
  private static int ˍ;
  private static short[] ˎˎ;
  private static int ˏˎ;
  private static int ˏˏ;
  private static final ViewDataBinding.If ॱˎ;
  public final TextView ʻ;
  public final LinearLayout ʻॱ;
  public final LX ʼ;
  private final az ʼॱ;
  public final View ʽ;
  private final TextView ʽॱ;
  private final TextView ʾ;
  private final TextView ˈ;
  private long ˉ = -1L;
  public final aw ˊ;
  private String ˊˊ;
  private boolean ˊˋ;
  public final LinearLayout ˊॱ;
  private FF ˋˊ;
  public final View ˋॱ;
  public final ar ˎ;
  public final ProgressBar ˏॱ;
  public final LinearLayout ͺ;
  public final เ ॱ;
  public final RelativeLayout ॱˊ;
  public final aD ॱˋ;
  public final у ॱॱ;
  public final View ॱᐝ;
  public final Button ᐝ;
  public final View ᐝॱ;
  
  /* Error */
  static
  {
    // Byte code:
    //   0: goto +35 -> 35
    //   3: astore_1
    //   4: aload_1
    //   5: athrow
    //   6: getstatic 68	o/LD:ˏˏ	I
    //   9: bipush 123
    //   11: iadd
    //   12: istore_0
    //   13: iload_0
    //   14: sipush 128
    //   17: irem
    //   18: putstatic 70	o/LD:ˏˎ	I
    //   21: iload_0
    //   22: iconst_2
    //   23: irem
    //   24: ifeq +6 -> 30
    //   27: goto +4 -> 31
    //   30: return
    //   31: return
    //   32: astore_1
    //   33: aload_1
    //   34: athrow
    //   35: iconst_0
    //   36: putstatic 70	o/LD:ˏˎ	I
    //   39: iconst_1
    //   40: putstatic 68	o/LD:ˏˏ	I
    //   43: invokestatic 72	o/LD:ॱˊ	()V
    //   46: invokestatic 74	o/LD:ˊॱ	()V
    //   49: aconst_null
    //   50: putstatic 76	o/LD:ॱˎ	Landroid/databinding/ViewDataBinding$If;
    //   53: new 78	android/util/SparseIntArray
    //   56: dup
    //   57: invokespecial 81	android/util/SparseIntArray:<init>	()V
    //   60: putstatic 83	o/LD:ʿ	Landroid/util/SparseIntArray;
    //   63: getstatic 83	o/LD:ʿ	Landroid/util/SparseIntArray;
    //   66: ldc 84
    //   68: bipush 12
    //   70: invokevirtual 88	android/util/SparseIntArray:put	(II)V
    //   73: getstatic 83	o/LD:ʿ	Landroid/util/SparseIntArray;
    //   76: ldc 89
    //   78: bipush 13
    //   80: invokevirtual 88	android/util/SparseIntArray:put	(II)V
    //   83: getstatic 83	o/LD:ʿ	Landroid/util/SparseIntArray;
    //   86: ldc 90
    //   88: bipush 14
    //   90: invokevirtual 88	android/util/SparseIntArray:put	(II)V
    //   93: getstatic 83	o/LD:ʿ	Landroid/util/SparseIntArray;
    //   96: ldc 91
    //   98: bipush 15
    //   100: invokevirtual 88	android/util/SparseIntArray:put	(II)V
    //   103: getstatic 83	o/LD:ʿ	Landroid/util/SparseIntArray;
    //   106: ldc 92
    //   108: bipush 16
    //   110: invokevirtual 88	android/util/SparseIntArray:put	(II)V
    //   113: getstatic 83	o/LD:ʿ	Landroid/util/SparseIntArray;
    //   116: ldc 93
    //   118: bipush 17
    //   120: invokevirtual 88	android/util/SparseIntArray:put	(II)V
    //   123: getstatic 83	o/LD:ʿ	Landroid/util/SparseIntArray;
    //   126: ldc 94
    //   128: bipush 18
    //   130: invokevirtual 88	android/util/SparseIntArray:put	(II)V
    //   133: getstatic 83	o/LD:ʿ	Landroid/util/SparseIntArray;
    //   136: ldc 95
    //   138: bipush 19
    //   140: invokevirtual 88	android/util/SparseIntArray:put	(II)V
    //   143: getstatic 83	o/LD:ʿ	Landroid/util/SparseIntArray;
    //   146: ldc 96
    //   148: bipush 20
    //   150: invokevirtual 88	android/util/SparseIntArray:put	(II)V
    //   153: goto -147 -> 6
    // Local variable table:
    //   start	length	slot	name	signature
    //   12	12	0	i	int
    //   3	2	1	localException1	Exception
    //   32	2	1	localException2	Exception
    // Exception table:
    //   from	to	target	type
    //   39	43	3	java/lang/Exception
    //   43	46	3	java/lang/Exception
    //   46	49	3	java/lang/Exception
    //   49	153	3	java/lang/Exception
    //   35	39	32	java/lang/Exception
  }
  
  public LD(ˉ paramˉ, View paramView)
  {
    super(paramˉ, paramView, 0);
    paramˉ = ॱ(paramˉ, paramView, 21, ॱˎ, ʿ);
    this.ˎ = ((ar)paramˉ[13]);
    this.ॱ = ((เ)paramˉ[14]);
    this.ˊ = ((aw)paramˉ[3]);
    this.ˊ.setTag(null);
    this.ʽ = ((View)paramˉ[17]);
    this.ʽॱ = ((TextView)paramˉ[2]);
    this.ʽॱ.setTag(null);
    this.ʼॱ = ((az)paramˉ[5]);
    this.ʼॱ.setTag(null);
    this.ˈ = ((TextView)paramˉ[7]);
    this.ˈ.setTag(null);
    this.ʾ = ((TextView)paramˉ[9]);
    this.ʾ.setTag(null);
    this.ʻ = ((TextView)paramˉ[6]);
    this.ʻ.setTag(null);
    this.ᐝ = ((Button)paramˉ[11]);
    this.ᐝ.setTag(null);
    this.ॱॱ = ((у)paramˉ[15]);
    this.ʼ = ((LX)paramˉ[4]);
    this.ʼ.setTag(null);
    this.ˏॱ = ((ProgressBar)paramˉ[12]);
    this.ͺ = ((LinearLayout)paramˉ[1]);
    this.ͺ.setTag(null);
    this.ॱˊ = ((RelativeLayout)paramˉ[0]);
    this.ॱˊ.setTag(null);
    this.ˊॱ = ((LinearLayout)paramˉ[8]);
    this.ˊॱ.setTag(null);
    this.ˋॱ = ((View)paramˉ[10]);
    this.ˋॱ.setTag(null);
    this.ॱˋ = ((aD)paramˉ[16]);
    this.ʻॱ = ((LinearLayout)paramˉ[18]);
    this.ॱᐝ = ((View)paramˉ[19]);
    this.ᐝॱ = ((View)paramˉ[20]);
    ˋ(paramView);
    ͺ();
  }
  
  static void ˊॱ()
  {
    break label71;
    label3:
    int i = ˏˎ + 43;
    ˏˏ = i % 128;
    if (i % 2 != 0) {
      break label77;
    }
    i = 22;
    for (;;)
    {
      try
      {
        ˊᐝ = -102;
        return;
      }
      catch (Exception localException)
      {
        label71:
        throw localException;
      }
      switch (i)
      {
      case 56: 
      default: 
        continue;
        break label3;
        label77:
        i = 56;
      }
    }
    ˊᐝ = 2;
  }
  
  private static String ˏ(short paramShort, int paramInt1, byte paramByte, int paramInt2, int paramInt3)
  {
    break label454;
    int j;
    paramInt1 = j;
    int i;
    char c = i;
    break label303;
    paramInt3 = (short)(ˎˎ[(ˋˋ + paramInt1)] + ˋᐝ);
    int k;
    label51:
    label88:
    label123:
    label142:
    label148:
    label199:
    label236:
    label303:
    label315:
    label334:
    label421:
    label454:
    label457:
    label467:
    label487:
    while (paramInt3 > 0)
    {
      k = ˋˋ;
      if (j != 0) {
        break label594;
      }
      break label88;
      break label698;
      Object localObject2;
      try
      {
        localObject2 = ˌ;
        try
        {
          paramInt3 = localObject2[(ˋˋ + paramInt1)];
          k = ˋᐝ;
          paramInt3 = (byte)(paramInt3 + k);
        }
        catch (Exception localException1)
        {
          throw localException1;
        }
        j = 1;
      }
      catch (Exception localException2)
      {
        throw localException2;
      }
      j = 4;
      for (;;)
      {
        switch (paramInt1)
        {
        case 47: 
        default: 
          break;
          Object localObject1;
          localObject1.append(i);
          paramInt2 += 1;
          k = i;
          break label303;
          paramInt1 = 15;
          continue;
          paramInt1 = 47;
          continue;
          if (ˌ != null) {}
        case 15: 
          for (;;)
          {
            localObject2 = ˎˎ;
            j = paramInt1 - 1;
            i = (char)(((short)(localObject2[paramInt1] + paramShort) ^ paramByte) + k);
            paramInt1 = j;
            break label123;
            paramInt3 = ˏˏ + 71;
            ˏˎ = paramInt3 % 128;
            if (paramInt3 % 2 == 0)
            {
              break label607;
              j = 28;
              break label334;
              int m = ˏˏ + 27;
              ˏˎ = m % 128;
              if (m % 2 == 0) {
                break;
              }
            }
            do
            {
              localObject2 = ˌ;
              j = paramInt1 - 1;
              i = (char)(((byte)(localObject2[paramInt1] + paramShort) ^ paramByte) + k);
              paramInt1 = j;
              break label123;
              j = 0;
              break label528;
              if (paramInt2 < paramInt3) {
                break;
              }
              break label601;
              paramInt3 = (byte)(ˌ[(paramInt1 >>> ˋˋ)] >>> ˋᐝ);
              break label487;
              for (;;)
              {
                switch (j)
                {
                case 28: 
                default: 
                  break;
                case 7: 
                  j = 1;
                  break label528;
                  for (;;)
                  {
                    StringBuilder localStringBuilder = new StringBuilder();
                    j = ˋᐝ + paramInt3;
                    paramInt3 = j;
                    if (j == -1) {
                      break label457;
                    }
                    break;
                    paramInt1 = j;
                    k = i;
                    break label303;
                    switch (j)
                    {
                    default: 
                      break label653;
                      break label698;
                    }
                  }
                  j = 7;
                }
              }
              break label607;
              localObject2 = ˌ;
              j = null.length;
            } while (localObject2 != null);
          }
        }
      }
    }
    break label619;
    for (;;)
    {
      j = ˏˎ + 17;
      ˏˏ = j % 128;
      if (j % 2 == 0) {
        break label467;
      }
      break;
      label528:
      if (j != 0) {
        break label199;
      }
      break label487;
      label539:
      switch (j)
      {
      }
    }
    for (;;)
    {
      paramInt1 = ˏˏ + 115;
      ˏˎ = paramInt1 % 128;
      if (paramInt1 % 2 != 0) {
        break label148;
      }
      break label142;
      label594:
      j = 72;
      break label421;
      label601:
      j = 0;
      break label539;
      label607:
      label619:
      String str;
      if (ˌ == null)
      {
        break;
        str = localException2.toString();
        paramShort = ˏˏ + 69;
        ˏˎ = paramShort % 128;
        if (paramShort % 2 != 0) {
          return str;
        }
        return str;
        label653:
        j = 0;
        break label695;
      }
      paramInt3 = ˏˏ + 15;
      ˏˎ = paramInt3 % 128;
      if (paramInt3 % 2 != 0) {
        break label315;
      }
      break label51;
      j = 1;
      break label236;
      label695:
      label698:
      j = paramInt1 + paramInt3 - 2 + k + j;
      i = (char)(ˍ + paramInt2);
      str.append(i);
      paramInt2 = 1;
    }
  }
  
  /* Error */
  private String ॱ(String paramString)
  {
    // Byte code:
    //   0: goto +151 -> 151
    //   3: new 223	java/lang/String
    //   6: dup
    //   7: aload_1
    //   8: iconst_0
    //   9: ldc -32
    //   11: bipush 110
    //   13: ldc -31
    //   15: bipush -63
    //   17: invokestatic 227	o/LD:ˏ	(SIBII)Ljava/lang/String;
    //   20: invokevirtual 230	java/lang/String:intern	()Ljava/lang/String;
    //   23: invokespecial 233	java/lang/String:<init>	([BLjava/lang/String;)V
    //   26: astore_1
    //   27: aload_1
    //   28: areturn
    //   29: iconst_0
    //   30: istore_2
    //   31: getstatic 68	o/LD:ˏˏ	I
    //   34: bipush 87
    //   36: iadd
    //   37: istore_3
    //   38: iload_3
    //   39: sipush 128
    //   42: irem
    //   43: putstatic 70	o/LD:ˏˎ	I
    //   46: iload_3
    //   47: iconst_2
    //   48: irem
    //   49: ifeq +6 -> 55
    //   52: goto +119 -> 171
    //   55: goto +99 -> 154
    //   58: aload_1
    //   59: iconst_0
    //   60: ldc -22
    //   62: bipush 87
    //   64: ldc -21
    //   66: bipush -63
    //   68: invokestatic 227	o/LD:ˏ	(SIBII)Ljava/lang/String;
    //   71: invokevirtual 230	java/lang/String:intern	()Ljava/lang/String;
    //   74: invokevirtual 239	java/lang/String:getBytes	(Ljava/lang/String;)[B
    //   77: astore 4
    //   79: aload 4
    //   81: arraylength
    //   82: newarray byte
    //   84: astore_1
    //   85: goto -56 -> 29
    //   88: iconst_0
    //   89: istore_3
    //   90: goto +33 -> 123
    //   93: iload_2
    //   94: lookupswitch	default:+26->120, 22:+105->199, 87:+113->207
    //   120: goto +87 -> 207
    //   123: iload_3
    //   124: tableswitch	default:+24->148, 0:+105->229, 1:+-121->3
    //   148: goto -145 -> 3
    //   151: goto +144 -> 295
    //   154: goto +55 -> 209
    //   157: astore_1
    //   158: aload_1
    //   159: athrow
    //   160: iconst_1
    //   161: istore_2
    //   162: goto +12 -> 174
    //   165: bipush 22
    //   167: istore_2
    //   168: goto -75 -> 93
    //   171: goto -17 -> 154
    //   174: iload_2
    //   175: tableswitch	default:+21->196, 0:+90->265, 1:+-117->58
    //   196: goto -138 -> 58
    //   199: iload_3
    //   200: istore_2
    //   201: goto +8 -> 209
    //   204: astore_1
    //   205: aload_1
    //   206: athrow
    //   207: iload_3
    //   208: istore_2
    //   209: aload 4
    //   211: arraylength
    //   212: istore_3
    //   213: iload_2
    //   214: iload_3
    //   215: if_icmpge +6 -> 221
    //   218: goto -130 -> 88
    //   221: goto +39 -> 260
    //   224: iconst_0
    //   225: istore_2
    //   226: goto -52 -> 174
    //   229: aload_1
    //   230: iload_2
    //   231: aload 4
    //   233: aload 4
    //   235: arraylength
    //   236: iload_2
    //   237: isub
    //   238: iconst_1
    //   239: isub
    //   240: baload
    //   241: getstatic 195	o/LD:ˊᐝ	B
    //   244: ixor
    //   245: i2b
    //   246: bastore
    //   247: iload_2
    //   248: iconst_1
    //   249: iadd
    //   250: istore_3
    //   251: goto +70 -> 321
    //   254: bipush 87
    //   256: istore_2
    //   257: goto -164 -> 93
    //   260: iconst_1
    //   261: istore_3
    //   262: goto -139 -> 123
    //   265: aload_1
    //   266: iconst_1
    //   267: ldc -22
    //   269: bipush 64
    //   271: ldc -21
    //   273: bipush 95
    //   275: invokestatic 227	o/LD:ˏ	(SIBII)Ljava/lang/String;
    //   278: invokevirtual 230	java/lang/String:intern	()Ljava/lang/String;
    //   281: invokevirtual 239	java/lang/String:getBytes	(Ljava/lang/String;)[B
    //   284: astore 4
    //   286: aload 4
    //   288: arraylength
    //   289: newarray byte
    //   291: astore_1
    //   292: goto -263 -> 29
    //   295: getstatic 70	o/LD:ˏˎ	I
    //   298: iconst_1
    //   299: iadd
    //   300: istore_2
    //   301: iload_2
    //   302: sipush 128
    //   305: irem
    //   306: putstatic 68	o/LD:ˏˏ	I
    //   309: iload_2
    //   310: iconst_2
    //   311: irem
    //   312: ifne +6 -> 318
    //   315: goto -91 -> 224
    //   318: goto -158 -> 160
    //   321: getstatic 68	o/LD:ˏˏ	I
    //   324: bipush 33
    //   326: iadd
    //   327: istore_2
    //   328: iload_2
    //   329: sipush 128
    //   332: irem
    //   333: putstatic 70	o/LD:ˏˎ	I
    //   336: iload_2
    //   337: iconst_2
    //   338: irem
    //   339: ifeq +6 -> 345
    //   342: goto -177 -> 165
    //   345: goto -91 -> 254
    //   348: astore_1
    //   349: new 241	java/lang/RuntimeException
    //   352: dup
    //   353: aload_1
    //   354: invokespecial 244	java/lang/RuntimeException:<init>	(Ljava/lang/Throwable;)V
    //   357: athrow
    // Local variable table:
    //   start	length	slot	name	signature
    //   0	358	0	this	LD
    //   0	358	1	paramString	String
    //   30	309	2	i	int
    //   37	225	3	j	int
    //   77	210	4	arrayOfByte	byte[]
    // Exception table:
    //   from	to	target	type
    //   295	301	157	java/lang/Exception
    //   301	309	157	java/lang/Exception
    //   301	309	204	java/lang/Exception
    //   321	328	204	java/lang/Exception
    //   328	336	204	java/lang/Exception
    //   3	27	348	java/io/UnsupportedEncodingException
    //   58	85	348	java/io/UnsupportedEncodingException
    //   209	213	348	java/io/UnsupportedEncodingException
    //   229	247	348	java/io/UnsupportedEncodingException
    //   265	292	348	java/io/UnsupportedEncodingException
  }
  
  static void ॱˊ()
  {
    ˋᐝ = 62;
    ˌ = new byte[] { -58, -19, 29, -7, -52, 83, -93, 83, -86, 87, 92, -119, -85, 93, -57, 101, -119, -100, -111 };
    ˍ = -1637676555;
    ˋˋ = -289900981;
  }
  
  public void ˋ(String paramString)
  {
    this.ˊˊ = paramString;
    try
    {
      this.ˉ |= 0x10;
    }
    finally
    {
      paramString = finally;
      throw paramString;
    }
    ˊ(12);
    super.ʽ();
  }
  
  /* Error */
  public FF ˋॱ()
  {
    // Byte code:
    //   0: goto +68 -> 68
    //   3: iload_1
    //   4: tableswitch	default:+24->28, 0:+107->111, 1:+62->66
    //   28: goto +83 -> 111
    //   31: astore_2
    //   32: aload_2
    //   33: athrow
    //   34: iconst_0
    //   35: istore_1
    //   36: goto -33 -> 3
    //   39: getstatic 70	o/LD:ˏˎ	I
    //   42: bipush 91
    //   44: iadd
    //   45: istore_1
    //   46: iload_1
    //   47: sipush 128
    //   50: irem
    //   51: putstatic 68	o/LD:ˏˏ	I
    //   54: iload_1
    //   55: iconst_2
    //   56: irem
    //   57: ifne +6 -> 63
    //   60: goto +11 -> 71
    //   63: goto +8 -> 71
    //   66: aload_2
    //   67: areturn
    //   68: goto -29 -> 39
    //   71: aload_0
    //   72: getfield 276	o/LD:ˋˊ	Lo/FF;
    //   75: astore_2
    //   76: goto +8 -> 84
    //   79: iconst_1
    //   80: istore_1
    //   81: goto -78 -> 3
    //   84: getstatic 70	o/LD:ˏˎ	I
    //   87: bipush 63
    //   89: iadd
    //   90: istore_1
    //   91: iload_1
    //   92: sipush 128
    //   95: irem
    //   96: putstatic 68	o/LD:ˏˏ	I
    //   99: iload_1
    //   100: iconst_2
    //   101: irem
    //   102: ifne +6 -> 108
    //   105: goto -71 -> 34
    //   108: goto -29 -> 79
    //   111: new 278	java/lang/NullPointerException
    //   114: dup
    //   115: invokespecial 279	java/lang/NullPointerException:<init>	()V
    //   118: athrow
    // Local variable table:
    //   start	length	slot	name	signature
    //   0	119	0	this	LD
    //   3	99	1	i	int
    //   31	36	2	localException	Exception
    //   75	1	2	localFF	FF
    // Exception table:
    //   from	to	target	type
    //   39	46	31	java/lang/Exception
    //   46	54	31	java/lang/Exception
    //   71	76	31	java/lang/Exception
  }
  
  public void ˎ(FF paramFF)
  {
    this.ˋˊ = paramFF;
    try
    {
      this.ˉ |= 0x4;
    }
    finally
    {
      paramFF = finally;
      throw paramFF;
    }
    ˊ(98);
    super.ʽ();
  }
  
  public void ˏ()
  {
    try
    {
      l2 = this.ˉ;
      this.ˉ = 0L;
    }
    finally
    {
      localObject1 = finally;
      throw localObject1;
    }
    boolean bool3 = false;
    boolean bool1 = false;
    boolean bool6 = this.ˊˋ;
    FF localFF = this.ˋˊ;
    boolean bool2 = false;
    int m = 0;
    int k = 0;
    Object localObject3 = null;
    Object localObject2 = null;
    String str1 = null;
    int n = 0;
    int i = 0;
    boolean bool5 = false;
    String str2 = this.ˊˊ;
    boolean bool4 = false;
    long l1 = l2;
    if ((0x41 & l2) != 0L)
    {
      l1 = l2;
      if ((0x41 & l2) != 0L) {
        if (bool6) {
          l1 = l2 | 0x100 | 0x4000;
        } else {
          l1 = l2 | 0x80 | 0x2000;
        }
      }
      if (bool6) {
        j = 0;
      } else {
        j = 8;
      }
      if (bool6)
      {
        i = 4;
        m = j;
      }
      else
      {
        i = 0;
        m = j;
      }
    }
    long l2 = l1;
    int j = n;
    if ((0x44 & l1) != 0L)
    {
      localObject2 = str1;
      bool2 = bool5;
      if (localFF != null)
      {
        bool1 = localFF.ʽ();
        localObject3 = localFF.ᐝ();
        localObject2 = localFF.ˋ();
        bool2 = localFF.ॱˊ();
      }
      l2 = l1;
      if ((0x44 & l1) != 0L) {
        if (bool1) {
          l2 = l1 | 0x10000;
        } else {
          l2 = l1 | 0x8000;
        }
      }
      bool3 = TextUtils.isEmpty((CharSequence)localObject3);
      if (!bool2) {
        bool2 = true;
      } else {
        bool2 = false;
      }
      l1 = l2;
      if ((0x44 & l2) != 0L) {
        if (bool3) {
          l1 = l2 | 0x1000;
        } else {
          l1 = l2 | 0x800;
        }
      }
      if (bool3)
      {
        j = 8;
        l2 = l1;
        bool3 = bool1;
      }
      else
      {
        j = 0;
        bool3 = bool1;
        l2 = l1;
      }
    }
    bool1 = bool4;
    if ((0x8000 & l2) != 0L)
    {
      bool1 = bool4;
      if (localFF != null) {
        bool1 = localFF.ʻ();
      }
    }
    l1 = l2;
    if ((0x44 & l2) != 0L)
    {
      if (bool3) {
        bool1 = true;
      }
      l1 = l2;
      if ((0x44 & l2) != 0L) {
        if (bool1) {
          l1 = l2 | 0x400;
        } else {
          l1 = l2 | 0x200;
        }
      }
      if (bool1) {
        k = 0;
      } else {
        k = 8;
      }
    }
    if ((0x41 & l1) != 0L)
    {
      this.ˊ.setVisibility(i);
      this.ͺ.setVisibility(m);
    }
    if ((0x40 & l1) != 0L)
    {
      this.ˊ.setShowShadow(true);
      TextView localTextView = this.ʽॱ;
      str1 = this.ʽॱ.getResources().getString(2131755246);
      localObject3 = str1;
      if (str1.startsWith(ˏ((short)0, 289900981, (byte)-20, 1637676560, -63).intern())) {
        localObject3 = ॱ(str1.substring(4)).intern();
      }
      ʹ.ˊ(localTextView, (CharSequence)localObject3);
      this.ʼॱ.setShadowBottom(ॱ(this.ʼॱ, 2131231257));
      localTextView = this.ˈ;
      str1 = this.ˈ.getResources().getString(2131755323);
      localObject3 = str1;
      if (str1.startsWith(ˏ((short)0, 289900981, (byte)-20, 1637676560, -63).intern())) {
        localObject3 = ॱ(str1.substring(4)).intern();
      }
      ʹ.ˊ(localTextView, (CharSequence)localObject3);
      localTextView = this.ʾ;
      str1 = this.ʾ.getResources().getString(2131755324);
      localObject3 = str1;
      if (str1.startsWith(ˏ((short)0, 289900981, (byte)-20, 1637676560, -63).intern())) {
        localObject3 = ॱ(str1.substring(4)).intern();
      }
      ʹ.ˊ(localTextView, (CharSequence)localObject3);
      this.ʼ.setShowFullDate(true);
    }
    if ((0x44 & l1) != 0L)
    {
      ʹ.ˊ(this.ʻ, (CharSequence)localObject2);
      this.ᐝ.setEnabled(bool2);
      this.ᐝ.setVisibility(k);
      this.ʼ.setOffer(localFF);
      this.ˊॱ.setVisibility(j);
      this.ˋॱ.setVisibility(j);
    }
    if ((0x50 & l1) != 0L) {
      ʹ.ˊ(this.ᐝ, str2);
    }
  }
  
  public void ˏ(boolean paramBoolean)
  {
    this.ˊˋ = paramBoolean;
    try
    {
      this.ˉ |= 1L;
    }
    finally
    {
      localObject = finally;
      throw localObject;
    }
    ˊ(70);
    super.ʽ();
  }
  
  /* Error */
  public boolean ˏ(int paramInt1, Object paramObject, int paramInt2)
  {
    // Byte code:
    //   0: goto +116 -> 116
    //   3: goto +38 -> 41
    //   6: astore_2
    //   7: aload_2
    //   8: athrow
    //   9: getstatic 70	o/LD:ˏˎ	I
    //   12: bipush 33
    //   14: iadd
    //   15: istore_1
    //   16: iload_1
    //   17: sipush 128
    //   20: irem
    //   21: putstatic 68	o/LD:ˏˏ	I
    //   24: iload_1
    //   25: iconst_2
    //   26: irem
    //   27: ifne +6 -> 33
    //   30: goto +40 -> 70
    //   33: goto -30 -> 3
    //   36: iconst_1
    //   37: istore_1
    //   38: goto +45 -> 83
    //   41: getstatic 70	o/LD:ˏˎ	I
    //   44: istore_1
    //   45: iload_1
    //   46: bipush 29
    //   48: iadd
    //   49: istore_1
    //   50: iload_1
    //   51: sipush 128
    //   54: irem
    //   55: putstatic 68	o/LD:ˏˏ	I
    //   58: iload_1
    //   59: iconst_2
    //   60: irem
    //   61: ifne +6 -> 67
    //   64: goto +12 -> 76
    //   67: goto -31 -> 36
    //   70: goto -67 -> 3
    //   73: astore_2
    //   74: aload_2
    //   75: athrow
    //   76: iconst_0
    //   77: istore_1
    //   78: goto +5 -> 83
    //   81: iconst_0
    //   82: ireturn
    //   83: iload_1
    //   84: tableswitch	default:+24->108, 0:+27->111, 1:+-3->81
    //   108: goto -27 -> 81
    //   111: aconst_null
    //   112: arraylength
    //   113: istore_1
    //   114: iconst_0
    //   115: ireturn
    //   116: goto -107 -> 9
    // Local variable table:
    //   start	length	slot	name	signature
    //   0	119	0	this	LD
    //   0	119	1	paramInt1	int
    //   0	119	2	paramObject	Object
    //   0	119	3	paramInt2	int
    // Exception table:
    //   from	to	target	type
    //   9	16	6	java/lang/Exception
    //   16	24	6	java/lang/Exception
    //   50	58	6	java/lang/Exception
    //   16	24	73	java/lang/Exception
    //   41	45	73	java/lang/Exception
  }
  
  public void ͺ()
  {
    try
    {
      this.ˉ = 64L;
    }
    finally
    {
      localObject = finally;
      throw localObject;
    }
    ʽ();
  }
  
  public boolean ॱ()
  {
    try
    {
      long l = this.ˉ;
      if (l != 0L) {
        return true;
      }
    }
    finally
    {
      localObject = finally;
      throw localObject;
    }
    return false;
  }
}
