package o;

import android.os.Bundle;

public final class LO
  extends LR
{
  private static int ʻ;
  public static final ˊ ˊ;
  private static long ॱ;
  private static int ᐝ;
  
  static
  {
    for (;;)
    {
      int i = 27;
      break label46;
      return;
      throw new NullPointerException();
      ᐝ = 0;
      ʻ = 1;
      ʼˋ();
      ˊ = new ˊ(null);
      label46:
      do
      {
        i = 33;
        switch (i)
        {
        }
        break;
        i = ᐝ + 83;
        ʻ = i % 128;
      } while (i % 2 == 0);
    }
  }
  
  public LO() {}
  
  static void ʼˋ()
  {
    ॱ = 769700430496896585L;
  }
  
  /* Error */
  private static String ˊ(char[] paramArrayOfChar)
  {
    // Byte code:
    //   0: goto +117 -> 117
    //   3: astore_0
    //   4: aload_0
    //   5: athrow
    //   6: aload_0
    //   7: iload_1
    //   8: aload_0
    //   9: iload_1
    //   10: caload
    //   11: aload_0
    //   12: iload_1
    //   13: iconst_4
    //   14: irem
    //   15: caload
    //   16: ixor
    //   17: i2l
    //   18: iload_1
    //   19: iconst_4
    //   20: isub
    //   21: i2l
    //   22: getstatic 38	o/LO:ॱ	J
    //   25: lmul
    //   26: lxor
    //   27: l2i
    //   28: i2c
    //   29: castore
    //   30: iload_1
    //   31: iconst_1
    //   32: iadd
    //   33: istore_1
    //   34: goto +33 -> 67
    //   37: goto +92 -> 129
    //   40: getstatic 22	o/LO:ᐝ	I
    //   43: bipush 89
    //   45: iadd
    //   46: istore_2
    //   47: iload_2
    //   48: sipush 128
    //   51: irem
    //   52: putstatic 24	o/LO:ʻ	I
    //   55: iload_2
    //   56: iconst_2
    //   57: irem
    //   58: ifne +6 -> 64
    //   61: goto +85 -> 146
    //   64: goto -58 -> 6
    //   67: getstatic 22	o/LO:ᐝ	I
    //   70: istore_2
    //   71: iload_2
    //   72: bipush 17
    //   74: iadd
    //   75: istore_2
    //   76: iload_2
    //   77: sipush 128
    //   80: irem
    //   81: putstatic 24	o/LO:ʻ	I
    //   84: iload_2
    //   85: iconst_2
    //   86: irem
    //   87: ifne +6 -> 93
    //   90: goto -53 -> 37
    //   93: goto +36 -> 129
    //   96: getstatic 38	o/LO:ॱ	J
    //   99: lstore_3
    //   100: lload_3
    //   101: aload_0
    //   102: invokestatic 47	o/oL:ˋ	(J[C)[C
    //   105: astore_0
    //   106: iconst_4
    //   107: istore_1
    //   108: goto +41 -> 149
    //   111: bipush 47
    //   113: istore_2
    //   114: goto +38 -> 152
    //   117: goto -21 -> 96
    //   120: astore_0
    //   121: aload_0
    //   122: athrow
    //   123: bipush 70
    //   125: istore_2
    //   126: goto +26 -> 152
    //   129: goto +54 -> 183
    //   132: new 49	java/lang/String
    //   135: dup
    //   136: aload_0
    //   137: iconst_4
    //   138: aload_0
    //   139: arraylength
    //   140: iconst_4
    //   141: isub
    //   142: invokespecial 52	java/lang/String:<init>	([CII)V
    //   145: areturn
    //   146: goto -140 -> 6
    //   149: goto +34 -> 183
    //   152: iload_2
    //   153: lookupswitch	default:+27->180, 47:+-113->40, 70:+-21->132
    //   180: goto -140 -> 40
    //   183: iload_1
    //   184: aload_0
    //   185: arraylength
    //   186: if_icmpge +6 -> 192
    //   189: goto -78 -> 111
    //   192: goto -69 -> 123
    // Local variable table:
    //   start	length	slot	name	signature
    //   0	195	0	paramArrayOfChar	char[]
    //   7	180	1	i	int
    //   46	107	2	j	int
    //   99	2	3	l	long
    // Exception table:
    //   from	to	target	type
    //   67	71	3	java/lang/Exception
    //   40	47	120	java/lang/Exception
    //   47	55	120	java/lang/Exception
    //   76	84	120	java/lang/Exception
    //   96	100	120	java/lang/Exception
  }
  
  /* Error */
  public int ˎ()
  {
    // Byte code:
    //   0: goto +52 -> 52
    //   3: iconst_0
    //   4: istore_1
    //   5: goto +6 -> 11
    //   8: astore_2
    //   9: aload_2
    //   10: athrow
    //   11: iload_1
    //   12: tableswitch	default:+24->36, 0:+24->36, 1:+28->40
    //   36: getstatic 59	o/Lt$ˋ:fragment_offers_list	I
    //   39: ireturn
    //   40: getstatic 59	o/Lt$ˋ:fragment_offers_list	I
    //   43: istore_1
    //   44: new 17	java/lang/NullPointerException
    //   47: dup
    //   48: invokespecial 20	java/lang/NullPointerException:<init>	()V
    //   51: athrow
    //   52: getstatic 24	o/LO:ʻ	I
    //   55: istore_1
    //   56: iload_1
    //   57: bipush 91
    //   59: iadd
    //   60: istore_1
    //   61: iload_1
    //   62: sipush 128
    //   65: irem
    //   66: putstatic 22	o/LO:ᐝ	I
    //   69: iload_1
    //   70: iconst_2
    //   71: irem
    //   72: ifeq +6 -> 78
    //   75: goto +6 -> 81
    //   78: goto -75 -> 3
    //   81: iconst_1
    //   82: istore_1
    //   83: goto -72 -> 11
    //   86: astore_2
    //   87: aload_2
    //   88: athrow
    // Local variable table:
    //   start	length	slot	name	signature
    //   0	89	0	this	LO
    //   4	79	1	i	int
    //   8	2	2	localException1	Exception
    //   86	2	2	localException2	Exception
    // Exception table:
    //   from	to	target	type
    //   52	56	8	java/lang/Exception
    //   61	69	86	java/lang/Exception
  }
  
  /* Error */
  public void ˏ(java.util.List<FF> paramList)
  {
    // Byte code:
    //   0: goto +121 -> 121
    //   3: bipush 66
    //   5: istore_2
    //   6: goto +11 -> 17
    //   9: astore_1
    //   10: aload_1
    //   11: athrow
    //   12: iconst_0
    //   13: istore_2
    //   14: goto +154 -> 168
    //   17: iload_2
    //   18: lookupswitch	default:+26->44, 33:+85->103, 66:+210->228
    //   44: goto +59 -> 103
    //   47: iload_2
    //   48: lookupswitch	default:+28->76, 44:+28->76, 72:+106->154
    //   76: goto +7 -> 83
    //   79: aconst_null
    //   80: arraylength
    //   81: istore_2
    //   82: return
    //   83: aload_3
    //   84: invokeinterface 67 1 0
    //   89: ifeq +6 -> 95
    //   92: goto -89 -> 3
    //   95: goto +67 -> 162
    //   98: iconst_1
    //   99: istore_2
    //   100: goto +68 -> 168
    //   103: aload_0
    //   104: invokevirtual 70	o/LO:ˋ	()Lo/LC;
    //   107: aload_0
    //   108: invokevirtual 74	o/LO:ﹳ	()Ljava/util/ArrayList;
    //   111: checkcast 76	java/util/List
    //   114: iconst_1
    //   115: invokevirtual 81	o/LC:ˎ	(Ljava/util/List;Z)V
    //   118: goto +80 -> 198
    //   121: goto +142 -> 263
    //   124: getstatic 22	o/LO:ᐝ	I
    //   127: bipush 65
    //   129: iadd
    //   130: istore_2
    //   131: iload_2
    //   132: sipush 128
    //   135: irem
    //   136: putstatic 24	o/LO:ʻ	I
    //   139: iload_2
    //   140: iconst_2
    //   141: irem
    //   142: ifne +6 -> 148
    //   145: goto +200 -> 345
    //   148: bipush 44
    //   150: istore_2
    //   151: goto -104 -> 47
    //   154: iconst_5
    //   155: iconst_2
    //   156: idiv
    //   157: istore_2
    //   158: goto -75 -> 83
    //   161: return
    //   162: bipush 33
    //   164: istore_2
    //   165: goto -148 -> 17
    //   168: iload_2
    //   169: tableswitch	default:+23->192, 0:+-8->161, 1:+-90->79
    //   192: goto -113 -> 79
    //   195: astore_1
    //   196: aload_1
    //   197: athrow
    //   198: getstatic 22	o/LO:ᐝ	I
    //   201: bipush 51
    //   203: iadd
    //   204: istore_2
    //   205: iload_2
    //   206: sipush 128
    //   209: irem
    //   210: putstatic 24	o/LO:ʻ	I
    //   213: iload_2
    //   214: iconst_2
    //   215: irem
    //   216: ifne +6 -> 222
    //   219: goto -121 -> 98
    //   222: goto -210 -> 12
    //   225: goto -142 -> 83
    //   228: aload_3
    //   229: invokeinterface 85 1 0
    //   234: checkcast 87	o/FF
    //   237: astore_1
    //   238: aload_1
    //   239: invokevirtual 90	o/FF:ॱॱ	()Z
    //   242: ifne +6 -> 248
    //   245: goto +134 -> 379
    //   248: goto +103 -> 351
    //   251: aload_0
    //   252: invokevirtual 74	o/LO:ﹳ	()Ljava/util/ArrayList;
    //   255: aload_1
    //   256: invokevirtual 96	java/util/ArrayList:add	(Ljava/lang/Object;)Z
    //   259: pop
    //   260: goto -35 -> 225
    //   263: bipush 10
    //   265: newarray char
    //   267: dup
    //   268: iconst_0
    //   269: ldc 97
    //   271: castore
    //   272: dup
    //   273: iconst_1
    //   274: ldc 98
    //   276: castore
    //   277: dup
    //   278: iconst_2
    //   279: ldc 99
    //   281: castore
    //   282: dup
    //   283: iconst_3
    //   284: ldc 100
    //   286: castore
    //   287: dup
    //   288: iconst_4
    //   289: ldc 101
    //   291: castore
    //   292: dup
    //   293: iconst_5
    //   294: ldc 102
    //   296: castore
    //   297: dup
    //   298: bipush 6
    //   300: ldc 103
    //   302: castore
    //   303: dup
    //   304: bipush 7
    //   306: ldc 104
    //   308: castore
    //   309: dup
    //   310: bipush 8
    //   312: ldc 105
    //   314: castore
    //   315: dup
    //   316: bipush 9
    //   318: ldc 106
    //   320: castore
    //   321: invokestatic 108	o/LO:ˊ	([C)Ljava/lang/String;
    //   324: astore_3
    //   325: aload_3
    //   326: invokevirtual 112	java/lang/String:intern	()Ljava/lang/String;
    //   329: astore_3
    //   330: aload_1
    //   331: aload_3
    //   332: invokestatic 117	o/vq:ˎ	(Ljava/lang/Object;Ljava/lang/String;)V
    //   335: aload_1
    //   336: invokeinterface 121 1 0
    //   341: astore_3
    //   342: goto -218 -> 124
    //   345: bipush 72
    //   347: istore_2
    //   348: goto -301 -> 47
    //   351: iconst_0
    //   352: istore_2
    //   353: iload_2
    //   354: tableswitch	default:+22->376, 0:+-129->225, 1:+-103->251
    //   376: goto -125 -> 251
    //   379: iconst_1
    //   380: istore_2
    //   381: goto -28 -> 353
    // Local variable table:
    //   start	length	slot	name	signature
    //   0	384	0	this	LO
    //   0	384	1	paramList	java.util.List<FF>
    //   5	376	2	i	int
    //   83	259	3	localObject	Object
    // Exception table:
    //   from	to	target	type
    //   263	325	9	java/lang/Exception
    //   325	330	9	java/lang/Exception
    //   330	335	9	java/lang/Exception
    //   335	342	9	java/lang/Exception
    //   263	325	195	java/lang/Exception
  }
  
  public static final class ˊ
  {
    private static int ˋ = 1;
    private static char[] ˏ = { 97, 196, 205, 211, 200, 191, 201, 199, 192, 191, 199, 208, 201, 195, 196, 200, 197, 190, 199, 209, 212, 204 };
    private static int ॱ = 0;
    
    private ˊ() {}
    
    private static String ˊ(int[] paramArrayOfInt, byte[] paramArrayOfByte, boolean paramBoolean)
    {
      break label580;
      int k;
      int n;
      label49:
      int m;
      for (;;)
      {
        try
        {
          i = ॱ;
          i += 67;
          try
          {
            ˋ = i % 128;
            if (i % 2 == 0) {
              break label407;
            }
          }
          catch (Exception paramArrayOfInt)
          {
            throw paramArrayOfInt;
          }
          i = k;
        }
        catch (Exception paramArrayOfInt)
        {
          label61:
          throw paramArrayOfInt;
        }
        if (n > 0) {
          break label538;
        }
        break;
        if (i < m) {
          break label328;
        }
        break label532;
        break label313;
        i = 5 / 2;
      }
      int i = 1;
      break label647;
      i = ˋ + 93;
      ॱ = i % 128;
      label106:
      label133:
      int j;
      label168:
      Object localObject;
      label199:
      char[] arrayOfChar;
      label231:
      label244:
      int i1;
      if (i % 2 == 0)
      {
        break label443;
        i = ॱ + 27;
        ˋ = i % 128;
        if (i % 2 != 0)
        {
          break label696;
          for (;;)
          {
            switch (j)
            {
            default: 
              break;
              k = 0;
              break;
            case 0: 
              for (;;)
              {
                if (j < m) {
                  break label598;
                }
                break label717;
                for (;;)
                {
                  localObject = new char[m];
                  k = 0;
                  j = 0;
                  break label106;
                  break;
                  localObject = arrayOfChar;
                  switch (i)
                  {
                  }
                }
                if (paramArrayOfByte[j] == 0) {
                  break label789;
                }
                break label511;
                paramArrayOfByte = new char[m];
                System.arraycopy(localObject, 0, paramArrayOfByte, 0, m);
                System.arraycopy(paramArrayOfByte, 0, localObject, m - i1, i1);
                System.arraycopy(paramArrayOfByte, i1, localObject, 0, m - i1);
                break label583;
                localObject = paramArrayOfByte;
                break;
                i = 0;
                break label334;
                label301:
                if (i < m) {
                  break label769;
                }
                break label702;
                label313:
                i = localObject[j];
                j += 1;
              }
              label328:
              j = 1;
            }
          }
          switch (i)
          {
          default: 
            label334:
            break;
          }
        }
      }
      label359:
      label379:
      label407:
      label412:
      label443:
      label505:
      label511:
      label529:
      label532:
      label538:
      label580:
      label583:
      label598:
      label647:
      label675:
      label696:
      label702:
      label712:
      label717:
      label726:
      label755:
      label769:
      label789:
      label822:
      label868:
      for (;;)
      {
        localObject[j] = ((char)((arrayOfChar[j] << '\001') + 1 - i));
        break label61;
        for (;;)
        {
          switch (i)
          {
          }
          break;
          i = 0;
        }
        switch (i)
        {
        case 7: 
        default: 
          break;
          i = paramArrayOfInt[0];
          m = paramArrayOfInt[1];
          n = paramArrayOfInt[2];
          i1 = paramArrayOfInt[3];
          localObject = ˏ;
          arrayOfChar = new char[m];
          System.arraycopy(localObject, i, arrayOfChar, 0, m);
          if (paramArrayOfByte == null)
          {
            break label712;
            for (;;)
            {
              if (i1 > 0) {
                break label675;
              }
              break;
              k = 1;
              break label726;
              localObject[j] = ((char)((arrayOfChar[j] << '\001') - i));
              break label313;
            }
            j = 0;
            break label133;
            i = 1;
            break label334;
            i = ॱ + 43;
            ˋ = i % 128;
            if (i % 2 == 0) {
              break label822;
            }
            break label244;
          }
          i = 1;
          break label199;
          i = 0;
          break label301;
          break;
        case 44: 
          for (;;)
          {
            if (!paramBoolean)
            {
              break;
              i = 1;
              break label379;
              k = ˋ + 101;
              ॱ = k % 128;
              if (k % 2 != 0) {
                break label231;
              }
              break label755;
              paramArrayOfByte[i] = localObject[(m - i - 1)];
              i += 1;
              break label49;
              for (;;)
              {
                switch (i)
                {
                }
                break;
                i = 0;
              }
              i = k;
              break label168;
            }
            paramArrayOfByte = new char[m];
            i = 0;
            break label49;
            i = 44;
            break label412;
            return new String((char[])localObject);
            i = 0;
            break label199;
            break label529;
            i = 7;
            break label412;
            switch (k)
            {
            case 1: 
            default: 
              break label511;
              if (paramArrayOfByte[j] == 1) {
                break;
              }
              break label505;
              localObject[i] = ((char)(localObject[i] - paramArrayOfInt[2]));
              i += 1;
              break;
            case 0: 
              k = ॱ + 29;
              ˋ = k % 128;
              if (k % 2 == 0) {
                break label868;
              }
              break label359;
              break label443;
              paramArrayOfByte = new char[m];
              System.arraycopy(localObject, 1, paramArrayOfByte, 0, m);
              System.arraycopy(paramArrayOfByte, 0, localObject, m * i1, i1);
              System.arraycopy(paramArrayOfByte, i1, localObject, 0, m >> i1);
            }
          }
        }
      }
    }
    
    public final LO ˎ(String paramString)
    {
      LO localLO;
      for (;;)
      {
        localLO = new LO();
        Bundle localBundle = new Bundle();
        localBundle.putString(ˊ(new int[] { 0, 22, 94, 0 }, new byte[] { 0, 1, 0, 0, 0, 1, 0, 1, 0, 0, 0, 1, 1, 1, 0, 1, 0, 0, 1, 0, 0, 1 }, true).intern(), paramString);
        localLO.ʽ(localBundle);
        break;
      }
      int i = ˋ + 59;
      ॱ = i % 128;
      if (i % 2 != 0) {
        return localLO;
      }
      return localLO;
    }
  }
}
