package o;

import java.util.List;

public final class LQ
  extends x
{
  private static int ॱˉ;
  private static byte ॱˌ;
  private static char[] ॱˑ;
  private static int ॱᐧ;
  private LL ߺ;
  private LE ॱˈ;
  private final List<FN> ॱˍ;
  private Lz ॱـ;
  
  static
  {
    break label41;
    int i = 0;
    break label61;
    i = 35 / 0;
    return;
    for (;;)
    {
      i = ॱᐧ + 15;
      ॱˉ = i % 128;
      if (i % 2 != 0) {
        break label85;
      }
      break;
      label41:
      ॱˉ = 0;
      ॱᐧ = 1;
      ˎ();
      ॱˌ = -102;
    }
    return;
    for (;;)
    {
      label61:
      switch (i)
      {
      }
      return;
      label85:
      i = 1;
    }
  }
  
  /* Error */
  public LQ(android.content.Context paramContext, List<FN> paramList)
  {
    // Byte code:
    //   0: goto +401 -> 401
    //   3: aload_0
    //   4: aload_1
    //   5: checkcast 36	java/lang/CharSequence
    //   8: putfield 39	o/LQ:ˎ	Ljava/lang/CharSequence;
    //   11: goto +217 -> 228
    //   14: aload_0
    //   15: aload_2
    //   16: checkcast 36	java/lang/CharSequence
    //   19: invokevirtual 43	o/LQ:ॱ	(Ljava/lang/CharSequence;)Lo/ᐸ$If;
    //   22: pop
    //   23: iconst_4
    //   24: sipush 413
    //   27: sipush 30253
    //   30: invokestatic 49	o/O:ˋ	(IIC)Ljava/lang/Object;
    //   33: checkcast 51	java/lang/Class
    //   36: ldc 52
    //   38: invokevirtual 56	java/lang/Class:getField	(Ljava/lang/String;)Ljava/lang/reflect/Field;
    //   41: aconst_null
    //   42: invokevirtual 62	java/lang/reflect/Field:get	(Ljava/lang/Object;)Ljava/lang/Object;
    //   45: astore_2
    //   46: goto +17 -> 63
    //   49: astore_1
    //   50: aload_1
    //   51: invokevirtual 68	java/lang/Throwable:getCause	()Ljava/lang/Throwable;
    //   54: astore_2
    //   55: aload_2
    //   56: ifnull +5 -> 61
    //   59: aload_2
    //   60: athrow
    //   61: aload_1
    //   62: athrow
    //   63: bipush 6
    //   65: sipush 417
    //   68: iconst_0
    //   69: invokestatic 49	o/O:ˋ	(IIC)Ljava/lang/Object;
    //   72: checkcast 51	java/lang/Class
    //   75: ldc 70
    //   77: aconst_null
    //   78: invokevirtual 74	java/lang/Class:getMethod	(Ljava/lang/String;[Ljava/lang/Class;)Ljava/lang/reflect/Method;
    //   81: aload_2
    //   82: aconst_null
    //   83: invokevirtual 80	java/lang/reflect/Method:invoke	(Ljava/lang/Object;[Ljava/lang/Object;)Ljava/lang/Object;
    //   86: astore_2
    //   87: goto +17 -> 104
    //   90: astore_1
    //   91: aload_1
    //   92: invokevirtual 68	java/lang/Throwable:getCause	()Ljava/lang/Throwable;
    //   95: astore_2
    //   96: aload_2
    //   97: ifnull +5 -> 102
    //   100: aload_2
    //   101: athrow
    //   102: aload_1
    //   103: athrow
    //   104: iconst_4
    //   105: sipush 413
    //   108: sipush 30253
    //   111: invokestatic 49	o/O:ˋ	(IIC)Ljava/lang/Object;
    //   114: checkcast 51	java/lang/Class
    //   117: ldc 82
    //   119: aconst_null
    //   120: invokevirtual 74	java/lang/Class:getMethod	(Ljava/lang/String;[Ljava/lang/Class;)Ljava/lang/reflect/Method;
    //   123: aload_2
    //   124: aconst_null
    //   125: invokevirtual 80	java/lang/reflect/Method:invoke	(Ljava/lang/Object;[Ljava/lang/Object;)Ljava/lang/Object;
    //   128: astore_2
    //   129: aload_2
    //   130: checkcast 36	java/lang/CharSequence
    //   133: invokeinterface 86 1 0
    //   138: ifle +6 -> 144
    //   141: goto +222 -> 363
    //   144: goto +49 -> 193
    //   147: aload_0
    //   148: aload_2
    //   149: iconst_4
    //   150: invokevirtual 92	java/lang/String:substring	(I)Ljava/lang/String;
    //   153: invokespecial 95	o/LQ:ˋ	(Ljava/lang/String;)Ljava/lang/String;
    //   156: invokevirtual 99	java/lang/String:intern	()Ljava/lang/String;
    //   159: astore_2
    //   160: goto +235 -> 395
    //   163: iconst_0
    //   164: istore_3
    //   165: goto +33 -> 198
    //   168: aload_0
    //   169: aload_1
    //   170: getstatic 104	o/Lt$If:offers_shop_dialog_filter_title	I
    //   173: iconst_1
    //   174: anewarray 106	java/lang/Object
    //   177: dup
    //   178: iconst_0
    //   179: aload_2
    //   180: aastore
    //   181: invokevirtual 112	android/content/Context:getString	(I[Ljava/lang/Object;)Ljava/lang/String;
    //   184: checkcast 36	java/lang/CharSequence
    //   187: putfield 39	o/LQ:ˎ	Ljava/lang/CharSequence;
    //   190: goto +33 -> 223
    //   193: iconst_0
    //   194: istore_3
    //   195: goto +97 -> 292
    //   198: iload_3
    //   199: tableswitch	default:+21->220, 0:+843->1042, 1:+-31->168
    //   220: goto +822 -> 1042
    //   223: aload_0
    //   224: invokespecial 115	o/LQ:ᐝ	()V
    //   227: return
    //   228: getstatic 26	o/LQ:ॱˉ	I
    //   231: bipush 85
    //   233: iadd
    //   234: istore_3
    //   235: iload_3
    //   236: sipush 128
    //   239: irem
    //   240: putstatic 24	o/LQ:ॱᐧ	I
    //   243: iload_3
    //   244: iconst_2
    //   245: irem
    //   246: ifne +6 -> 252
    //   249: goto +92 -> 341
    //   252: goto +784 -> 1036
    //   255: iload_3
    //   256: lookupswitch	default:+28->284, 52:+104->360, 68:+82->338
    //   284: goto +76 -> 360
    //   287: iconst_1
    //   288: istore_3
    //   289: goto -91 -> 198
    //   292: getstatic 24	o/LQ:ॱᐧ	I
    //   295: bipush 55
    //   297: iadd
    //   298: istore 4
    //   300: iload 4
    //   302: sipush 128
    //   305: irem
    //   306: putstatic 26	o/LQ:ॱˉ	I
    //   309: iload 4
    //   311: iconst_2
    //   312: irem
    //   313: ifeq +6 -> 319
    //   316: goto +31 -> 347
    //   319: goto +79 -> 398
    //   322: aload_0
    //   323: aload_1
    //   324: iconst_4
    //   325: invokevirtual 92	java/lang/String:substring	(I)Ljava/lang/String;
    //   328: invokespecial 95	o/LQ:ˋ	(Ljava/lang/String;)Ljava/lang/String;
    //   331: invokevirtual 99	java/lang/String:intern	()Ljava/lang/String;
    //   334: astore_1
    //   335: goto -332 -> 3
    //   338: goto -115 -> 223
    //   341: bipush 52
    //   343: istore_3
    //   344: goto -89 -> 255
    //   347: goto +51 -> 398
    //   350: iload_3
    //   351: ifeq +6 -> 357
    //   354: goto -67 -> 287
    //   357: goto -194 -> 163
    //   360: goto -137 -> 223
    //   363: iconst_1
    //   364: istore_3
    //   365: goto -15 -> 350
    //   368: getstatic 26	o/LQ:ॱˉ	I
    //   371: bipush 13
    //   373: iadd
    //   374: istore_3
    //   375: iload_3
    //   376: sipush 128
    //   379: irem
    //   380: putstatic 24	o/LQ:ॱᐧ	I
    //   383: iload_3
    //   384: iconst_2
    //   385: irem
    //   386: ifne +6 -> 392
    //   389: goto +725 -> 1114
    //   392: goto -70 -> 322
    //   395: goto -381 -> 14
    //   398: goto -48 -> 350
    //   401: aload_1
    //   402: iconst_4
    //   403: newarray int
    //   405: dup
    //   406: iconst_0
    //   407: bipush 33
    //   409: iastore
    //   410: dup
    //   411: iconst_1
    //   412: bipush 7
    //   414: iastore
    //   415: dup
    //   416: iconst_2
    //   417: bipush 93
    //   419: iastore
    //   420: dup
    //   421: iconst_3
    //   422: iconst_5
    //   423: iastore
    //   424: bipush 7
    //   426: newarray byte
    //   428: dup
    //   429: iconst_0
    //   430: ldc 116
    //   432: bastore
    //   433: dup
    //   434: iconst_1
    //   435: ldc 117
    //   437: bastore
    //   438: dup
    //   439: iconst_2
    //   440: ldc 116
    //   442: bastore
    //   443: dup
    //   444: iconst_3
    //   445: ldc 116
    //   447: bastore
    //   448: dup
    //   449: iconst_4
    //   450: ldc 117
    //   452: bastore
    //   453: dup
    //   454: iconst_5
    //   455: ldc 116
    //   457: bastore
    //   458: dup
    //   459: bipush 6
    //   461: ldc 117
    //   463: bastore
    //   464: iconst_0
    //   465: invokestatic 121	o/LQ:ˊ	([I[BZ)Ljava/lang/String;
    //   468: invokevirtual 99	java/lang/String:intern	()Ljava/lang/String;
    //   471: invokestatic 126	o/vq:ˎ	(Ljava/lang/Object;Ljava/lang/String;)V
    //   474: aload_2
    //   475: iconst_4
    //   476: newarray int
    //   478: dup
    //   479: iconst_0
    //   480: bipush 40
    //   482: iastore
    //   483: dup
    //   484: iconst_1
    //   485: iconst_5
    //   486: iastore
    //   487: dup
    //   488: iconst_2
    //   489: bipush 94
    //   491: iastore
    //   492: dup
    //   493: iconst_3
    //   494: iconst_0
    //   495: iastore
    //   496: iconst_5
    //   497: newarray byte
    //   499: dup
    //   500: iconst_0
    //   501: ldc 116
    //   503: bastore
    //   504: dup
    //   505: iconst_1
    //   506: ldc 116
    //   508: bastore
    //   509: dup
    //   510: iconst_2
    //   511: ldc 116
    //   513: bastore
    //   514: dup
    //   515: iconst_3
    //   516: ldc 116
    //   518: bastore
    //   519: dup
    //   520: iconst_4
    //   521: ldc 116
    //   523: bastore
    //   524: iconst_0
    //   525: invokestatic 121	o/LQ:ˊ	([I[BZ)Ljava/lang/String;
    //   528: invokevirtual 99	java/lang/String:intern	()Ljava/lang/String;
    //   531: invokestatic 126	o/vq:ˎ	(Ljava/lang/Object;Ljava/lang/String;)V
    //   534: aload_0
    //   535: aload_1
    //   536: invokespecial 129	o/x:<init>	(Landroid/content/Context;)V
    //   539: aload_0
    //   540: aload_2
    //   541: putfield 131	o/LQ:ॱˍ	Ljava/util/List;
    //   544: aload_1
    //   545: invokestatic 137	android/view/LayoutInflater:from	(Landroid/content/Context;)Landroid/view/LayoutInflater;
    //   548: getstatic 142	o/Lt$ˋ:dialog_offer_shop_location	I
    //   551: aconst_null
    //   552: iconst_0
    //   553: invokestatic 147	o/ˌ:ˎ	(Landroid/view/LayoutInflater;ILandroid/view/ViewGroup;Z)Landroid/databinding/ViewDataBinding;
    //   556: astore_2
    //   557: aload_2
    //   558: iconst_4
    //   559: newarray int
    //   561: dup
    //   562: iconst_0
    //   563: bipush 45
    //   565: iastore
    //   566: dup
    //   567: iconst_1
    //   568: bipush 50
    //   570: iastore
    //   571: dup
    //   572: iconst_2
    //   573: sipush 190
    //   576: iastore
    //   577: dup
    //   578: iconst_3
    //   579: bipush 6
    //   581: iastore
    //   582: aconst_null
    //   583: iconst_1
    //   584: invokestatic 121	o/LQ:ˊ	([I[BZ)Ljava/lang/String;
    //   587: invokevirtual 99	java/lang/String:intern	()Ljava/lang/String;
    //   590: invokestatic 149	o/vq:ˋ	(Ljava/lang/Object;Ljava/lang/String;)V
    //   593: aload_0
    //   594: aload_2
    //   595: checkcast 151	o/LE
    //   598: putfield 153	o/LQ:ॱˈ	Lo/LE;
    //   601: aload_1
    //   602: invokestatic 137	android/view/LayoutInflater:from	(Landroid/content/Context;)Landroid/view/LayoutInflater;
    //   605: getstatic 156	o/Lt$ˋ:view_shop_title	I
    //   608: aconst_null
    //   609: iconst_0
    //   610: invokestatic 147	o/ˌ:ˎ	(Landroid/view/LayoutInflater;ILandroid/view/ViewGroup;Z)Landroid/databinding/ViewDataBinding;
    //   613: astore_2
    //   614: aload_2
    //   615: iconst_4
    //   616: newarray int
    //   618: dup
    //   619: iconst_0
    //   620: bipush 95
    //   622: iastore
    //   623: dup
    //   624: iconst_1
    //   625: bipush 50
    //   627: iastore
    //   628: dup
    //   629: iconst_2
    //   630: bipush 71
    //   632: iastore
    //   633: dup
    //   634: iconst_3
    //   635: iconst_0
    //   636: iastore
    //   637: bipush 50
    //   639: newarray byte
    //   641: dup
    //   642: iconst_0
    //   643: ldc 117
    //   645: bastore
    //   646: dup
    //   647: iconst_1
    //   648: ldc 117
    //   650: bastore
    //   651: dup
    //   652: iconst_2
    //   653: ldc 117
    //   655: bastore
    //   656: dup
    //   657: iconst_3
    //   658: ldc 116
    //   660: bastore
    //   661: dup
    //   662: iconst_4
    //   663: ldc 116
    //   665: bastore
    //   666: dup
    //   667: iconst_5
    //   668: ldc 116
    //   670: bastore
    //   671: dup
    //   672: bipush 6
    //   674: ldc 117
    //   676: bastore
    //   677: dup
    //   678: bipush 7
    //   680: ldc 117
    //   682: bastore
    //   683: dup
    //   684: bipush 8
    //   686: ldc 117
    //   688: bastore
    //   689: dup
    //   690: bipush 9
    //   692: ldc 117
    //   694: bastore
    //   695: dup
    //   696: bipush 10
    //   698: ldc 116
    //   700: bastore
    //   701: dup
    //   702: bipush 11
    //   704: ldc 116
    //   706: bastore
    //   707: dup
    //   708: bipush 12
    //   710: ldc 117
    //   712: bastore
    //   713: dup
    //   714: bipush 13
    //   716: ldc 117
    //   718: bastore
    //   719: dup
    //   720: bipush 14
    //   722: ldc 116
    //   724: bastore
    //   725: dup
    //   726: bipush 15
    //   728: ldc 116
    //   730: bastore
    //   731: dup
    //   732: bipush 16
    //   734: ldc 117
    //   736: bastore
    //   737: dup
    //   738: bipush 17
    //   740: ldc 116
    //   742: bastore
    //   743: dup
    //   744: bipush 18
    //   746: ldc 116
    //   748: bastore
    //   749: dup
    //   750: bipush 19
    //   752: ldc 116
    //   754: bastore
    //   755: dup
    //   756: bipush 20
    //   758: ldc 116
    //   760: bastore
    //   761: dup
    //   762: bipush 21
    //   764: ldc 116
    //   766: bastore
    //   767: dup
    //   768: bipush 22
    //   770: ldc 116
    //   772: bastore
    //   773: dup
    //   774: bipush 23
    //   776: ldc 116
    //   778: bastore
    //   779: dup
    //   780: bipush 24
    //   782: ldc 117
    //   784: bastore
    //   785: dup
    //   786: bipush 25
    //   788: ldc 116
    //   790: bastore
    //   791: dup
    //   792: bipush 26
    //   794: ldc 117
    //   796: bastore
    //   797: dup
    //   798: bipush 27
    //   800: ldc 117
    //   802: bastore
    //   803: dup
    //   804: bipush 28
    //   806: ldc 117
    //   808: bastore
    //   809: dup
    //   810: bipush 29
    //   812: ldc 116
    //   814: bastore
    //   815: dup
    //   816: bipush 30
    //   818: ldc 116
    //   820: bastore
    //   821: dup
    //   822: bipush 31
    //   824: ldc 116
    //   826: bastore
    //   827: dup
    //   828: bipush 32
    //   830: ldc 116
    //   832: bastore
    //   833: dup
    //   834: bipush 33
    //   836: ldc 117
    //   838: bastore
    //   839: dup
    //   840: bipush 34
    //   842: ldc 117
    //   844: bastore
    //   845: dup
    //   846: bipush 35
    //   848: ldc 116
    //   850: bastore
    //   851: dup
    //   852: bipush 36
    //   854: ldc 116
    //   856: bastore
    //   857: dup
    //   858: bipush 37
    //   860: ldc 116
    //   862: bastore
    //   863: dup
    //   864: bipush 38
    //   866: ldc 117
    //   868: bastore
    //   869: dup
    //   870: bipush 39
    //   872: ldc 117
    //   874: bastore
    //   875: dup
    //   876: bipush 40
    //   878: ldc 117
    //   880: bastore
    //   881: dup
    //   882: bipush 41
    //   884: ldc 116
    //   886: bastore
    //   887: dup
    //   888: bipush 42
    //   890: ldc 117
    //   892: bastore
    //   893: dup
    //   894: bipush 43
    //   896: ldc 116
    //   898: bastore
    //   899: dup
    //   900: bipush 44
    //   902: ldc 116
    //   904: bastore
    //   905: dup
    //   906: bipush 45
    //   908: ldc 116
    //   910: bastore
    //   911: dup
    //   912: bipush 46
    //   914: ldc 116
    //   916: bastore
    //   917: dup
    //   918: bipush 47
    //   920: ldc 117
    //   922: bastore
    //   923: dup
    //   924: bipush 48
    //   926: ldc 117
    //   928: bastore
    //   929: dup
    //   930: bipush 49
    //   932: ldc 116
    //   934: bastore
    //   935: iconst_1
    //   936: invokestatic 121	o/LQ:ˊ	([I[BZ)Ljava/lang/String;
    //   939: invokevirtual 99	java/lang/String:intern	()Ljava/lang/String;
    //   942: invokestatic 149	o/vq:ˋ	(Ljava/lang/Object;Ljava/lang/String;)V
    //   945: aload_0
    //   946: aload_2
    //   947: checkcast 158	o/LL
    //   950: putfield 160	o/LQ:ߺ	Lo/LL;
    //   953: aload_0
    //   954: aload_0
    //   955: getfield 153	o/LQ:ॱˈ	Lo/LE;
    //   958: invokevirtual 163	o/LE:ᐝ	()Landroid/view/View;
    //   961: putfield 167	o/LQ:ॱᐝ	Landroid/view/View;
    //   964: aload_1
    //   965: getstatic 170	o/Lt$If:offers_shop_dialog_close_button	I
    //   968: invokevirtual 172	android/content/Context:getString	(I)Ljava/lang/String;
    //   971: astore_2
    //   972: aload_2
    //   973: iconst_4
    //   974: newarray int
    //   976: dup
    //   977: iconst_0
    //   978: sipush 145
    //   981: iastore
    //   982: dup
    //   983: iconst_1
    //   984: iconst_4
    //   985: iastore
    //   986: dup
    //   987: iconst_2
    //   988: iconst_0
    //   989: iastore
    //   990: dup
    //   991: iconst_3
    //   992: iconst_0
    //   993: iastore
    //   994: iconst_4
    //   995: newarray byte
    //   997: dup
    //   998: iconst_0
    //   999: ldc 116
    //   1001: bastore
    //   1002: dup
    //   1003: iconst_1
    //   1004: ldc 116
    //   1006: bastore
    //   1007: dup
    //   1008: iconst_2
    //   1009: ldc 116
    //   1011: bastore
    //   1012: dup
    //   1013: iconst_3
    //   1014: ldc 116
    //   1016: bastore
    //   1017: iconst_0
    //   1018: invokestatic 121	o/LQ:ˊ	([I[BZ)Ljava/lang/String;
    //   1021: invokevirtual 99	java/lang/String:intern	()Ljava/lang/String;
    //   1024: invokevirtual 176	java/lang/String:startsWith	(Ljava/lang/String;)Z
    //   1027: ifeq +6 -> 1033
    //   1030: goto -883 -> 147
    //   1033: goto -1019 -> 14
    //   1036: bipush 68
    //   1038: istore_3
    //   1039: goto -784 -> 255
    //   1042: aload_1
    //   1043: getstatic 179	o/Lt$If:offers_shop_dialog_title	I
    //   1046: invokevirtual 172	android/content/Context:getString	(I)Ljava/lang/String;
    //   1049: astore_1
    //   1050: aload_1
    //   1051: iconst_4
    //   1052: newarray int
    //   1054: dup
    //   1055: iconst_0
    //   1056: sipush 145
    //   1059: iastore
    //   1060: dup
    //   1061: iconst_1
    //   1062: iconst_4
    //   1063: iastore
    //   1064: dup
    //   1065: iconst_2
    //   1066: iconst_0
    //   1067: iastore
    //   1068: dup
    //   1069: iconst_3
    //   1070: iconst_0
    //   1071: iastore
    //   1072: iconst_4
    //   1073: newarray byte
    //   1075: dup
    //   1076: iconst_0
    //   1077: ldc 116
    //   1079: bastore
    //   1080: dup
    //   1081: iconst_1
    //   1082: ldc 116
    //   1084: bastore
    //   1085: dup
    //   1086: iconst_2
    //   1087: ldc 116
    //   1089: bastore
    //   1090: dup
    //   1091: iconst_3
    //   1092: ldc 116
    //   1094: bastore
    //   1095: iconst_0
    //   1096: invokestatic 121	o/LQ:ˊ	([I[BZ)Ljava/lang/String;
    //   1099: invokevirtual 99	java/lang/String:intern	()Ljava/lang/String;
    //   1102: invokevirtual 176	java/lang/String:startsWith	(Ljava/lang/String;)Z
    //   1105: ifeq +6 -> 1111
    //   1108: goto -740 -> 368
    //   1111: goto -1108 -> 3
    //   1114: goto -792 -> 322
    // Local variable table:
    //   start	length	slot	name	signature
    //   0	1117	0	this	LQ
    //   0	1117	1	paramContext	android.content.Context
    //   0	1117	2	paramList	List<FN>
    //   164	875	3	i	int
    //   298	15	4	j	int
    // Exception table:
    //   from	to	target	type
    //   63	87	49	finally
    //   104	129	90	finally
  }
  
  /* Error */
  private final void ʼ()
  {
    // Byte code:
    //   0: goto +47 -> 47
    //   3: astore_2
    //   4: aload_2
    //   5: athrow
    //   6: getstatic 26	o/LQ:ॱˉ	I
    //   9: iconst_3
    //   10: iadd
    //   11: istore_1
    //   12: iload_1
    //   13: sipush 128
    //   16: irem
    //   17: putstatic 24	o/LQ:ॱᐧ	I
    //   20: iload_1
    //   21: iconst_2
    //   22: irem
    //   23: ifne +6 -> 29
    //   26: goto +333 -> 359
    //   29: goto +273 -> 302
    //   32: iconst_1
    //   33: istore_1
    //   34: goto +300 -> 334
    //   37: aload_2
    //   38: aload_0
    //   39: getfield 131	o/LQ:ॱˍ	Ljava/util/List;
    //   42: iconst_1
    //   43: invokevirtual 189	o/Lz:ˎ	(Ljava/util/List;Z)V
    //   46: return
    //   47: goto +260 -> 307
    //   50: goto +133 -> 183
    //   53: iconst_4
    //   54: newarray int
    //   56: dup
    //   57: iconst_0
    //   58: bipush 21
    //   60: iastore
    //   61: dup
    //   62: iconst_1
    //   63: bipush 12
    //   65: iastore
    //   66: dup
    //   67: iconst_2
    //   68: iconst_0
    //   69: iastore
    //   70: dup
    //   71: iconst_3
    //   72: iconst_3
    //   73: iastore
    //   74: bipush 12
    //   76: newarray byte
    //   78: dup
    //   79: iconst_0
    //   80: ldc 117
    //   82: bastore
    //   83: dup
    //   84: iconst_1
    //   85: ldc 116
    //   87: bastore
    //   88: dup
    //   89: iconst_2
    //   90: ldc 117
    //   92: bastore
    //   93: dup
    //   94: iconst_3
    //   95: ldc 116
    //   97: bastore
    //   98: dup
    //   99: iconst_4
    //   100: ldc 116
    //   102: bastore
    //   103: dup
    //   104: iconst_5
    //   105: ldc 116
    //   107: bastore
    //   108: dup
    //   109: bipush 6
    //   111: ldc 117
    //   113: bastore
    //   114: dup
    //   115: bipush 7
    //   117: ldc 116
    //   119: bastore
    //   120: dup
    //   121: bipush 8
    //   123: ldc 116
    //   125: bastore
    //   126: dup
    //   127: bipush 9
    //   129: ldc 116
    //   131: bastore
    //   132: dup
    //   133: bipush 10
    //   135: ldc 116
    //   137: bastore
    //   138: dup
    //   139: bipush 11
    //   141: ldc 116
    //   143: bastore
    //   144: iconst_0
    //   145: invokestatic 121	o/LQ:ˊ	([I[BZ)Ljava/lang/String;
    //   148: invokevirtual 99	java/lang/String:intern	()Ljava/lang/String;
    //   151: invokestatic 192	o/vq:ˊ	(Ljava/lang/String;)V
    //   154: goto +145 -> 299
    //   157: iload_1
    //   158: tableswitch	default:+22->180, 0:+40->198, 1:+-105->53
    //   180: goto +18 -> 198
    //   183: aload_0
    //   184: getfield 194	o/LQ:ॱـ	Lo/Lz;
    //   187: astore_2
    //   188: aload_2
    //   189: ifnonnull +6 -> 195
    //   192: goto +172 -> 364
    //   195: goto -163 -> 32
    //   198: iconst_4
    //   199: newarray int
    //   201: dup
    //   202: iconst_0
    //   203: bipush 21
    //   205: iastore
    //   206: dup
    //   207: iconst_1
    //   208: bipush 12
    //   210: iastore
    //   211: dup
    //   212: iconst_2
    //   213: iconst_0
    //   214: iastore
    //   215: dup
    //   216: iconst_3
    //   217: iconst_3
    //   218: iastore
    //   219: bipush 12
    //   221: newarray byte
    //   223: dup
    //   224: iconst_0
    //   225: ldc 117
    //   227: bastore
    //   228: dup
    //   229: iconst_1
    //   230: ldc 116
    //   232: bastore
    //   233: dup
    //   234: iconst_2
    //   235: ldc 117
    //   237: bastore
    //   238: dup
    //   239: iconst_3
    //   240: ldc 116
    //   242: bastore
    //   243: dup
    //   244: iconst_4
    //   245: ldc 116
    //   247: bastore
    //   248: dup
    //   249: iconst_5
    //   250: ldc 116
    //   252: bastore
    //   253: dup
    //   254: bipush 6
    //   256: ldc 117
    //   258: bastore
    //   259: dup
    //   260: bipush 7
    //   262: ldc 116
    //   264: bastore
    //   265: dup
    //   266: bipush 8
    //   268: ldc 116
    //   270: bastore
    //   271: dup
    //   272: bipush 9
    //   274: ldc 116
    //   276: bastore
    //   277: dup
    //   278: bipush 10
    //   280: ldc 116
    //   282: bastore
    //   283: dup
    //   284: bipush 11
    //   286: ldc 116
    //   288: bastore
    //   289: iconst_1
    //   290: invokestatic 121	o/LQ:ˊ	([I[BZ)Ljava/lang/String;
    //   293: invokevirtual 99	java/lang/String:intern	()Ljava/lang/String;
    //   296: invokestatic 192	o/vq:ˊ	(Ljava/lang/String;)V
    //   299: goto -262 -> 37
    //   302: iconst_0
    //   303: istore_1
    //   304: goto -147 -> 157
    //   307: getstatic 24	o/LQ:ॱᐧ	I
    //   310: bipush 89
    //   312: iadd
    //   313: istore_1
    //   314: iload_1
    //   315: sipush 128
    //   318: irem
    //   319: putstatic 26	o/LQ:ॱˉ	I
    //   322: iload_1
    //   323: iconst_2
    //   324: irem
    //   325: ifeq +6 -> 331
    //   328: goto -278 -> 50
    //   331: goto -148 -> 183
    //   334: iload_1
    //   335: tableswitch	default:+21->356, 0:+-329->6, 1:+-298->37
    //   356: goto -350 -> 6
    //   359: iconst_1
    //   360: istore_1
    //   361: goto -204 -> 157
    //   364: iconst_0
    //   365: istore_1
    //   366: goto -32 -> 334
    // Local variable table:
    //   start	length	slot	name	signature
    //   0	369	0	this	LQ
    //   11	355	1	i	int
    //   3	35	2	localException	Exception
    //   187	2	2	localLz	Lz
    // Exception table:
    //   from	to	target	type
    //   183	188	3	java/lang/Exception
  }
  
  /* Error */
  private static String ˊ(int[] paramArrayOfInt, byte[] paramArrayOfByte, boolean paramBoolean)
  {
    // Byte code:
    //   0: goto +383 -> 383
    //   3: goto +127 -> 130
    //   6: iload 4
    //   8: iload 5
    //   10: if_icmpge +6 -> 16
    //   13: goto +549 -> 562
    //   16: goto +342 -> 358
    //   19: iconst_0
    //   20: istore_3
    //   21: goto +9 -> 30
    //   24: bipush 49
    //   26: istore_3
    //   27: goto +424 -> 451
    //   30: iload_3
    //   31: iload 5
    //   33: if_icmpge +6 -> 39
    //   36: goto +367 -> 403
    //   39: goto +310 -> 349
    //   42: aload 9
    //   44: iload 4
    //   46: aload 10
    //   48: iload 4
    //   50: caload
    //   51: iconst_1
    //   52: ishl
    //   53: iload_3
    //   54: isub
    //   55: i2c
    //   56: castore
    //   57: goto +575 -> 632
    //   60: goto +332 -> 392
    //   63: bipush 93
    //   65: istore_3
    //   66: goto +226 -> 292
    //   69: iload 5
    //   71: newarray char
    //   73: astore 9
    //   75: aload_1
    //   76: iconst_0
    //   77: aload 9
    //   79: iconst_0
    //   80: iload 5
    //   82: invokestatic 200	java/lang/System:arraycopy	(Ljava/lang/Object;ILjava/lang/Object;II)V
    //   85: aload 9
    //   87: iconst_0
    //   88: aload_1
    //   89: iload 5
    //   91: iload 7
    //   93: isub
    //   94: iload 7
    //   96: invokestatic 200	java/lang/System:arraycopy	(Ljava/lang/Object;ILjava/lang/Object;II)V
    //   99: aload 9
    //   101: iload 7
    //   103: aload_1
    //   104: iconst_0
    //   105: iload 5
    //   107: iload 7
    //   109: isub
    //   110: invokestatic 200	java/lang/System:arraycopy	(Ljava/lang/Object;ILjava/lang/Object;II)V
    //   113: goto +176 -> 289
    //   116: iload 5
    //   118: newarray char
    //   120: astore 9
    //   122: iconst_0
    //   123: istore_3
    //   124: iconst_0
    //   125: istore 4
    //   127: goto -121 -> 6
    //   130: aload_0
    //   131: iconst_0
    //   132: iaload
    //   133: istore_3
    //   134: aload_0
    //   135: iconst_1
    //   136: iaload
    //   137: istore 5
    //   139: aload_0
    //   140: iconst_2
    //   141: iaload
    //   142: istore 6
    //   144: aload_0
    //   145: iconst_3
    //   146: iaload
    //   147: istore 7
    //   149: getstatic 202	o/LQ:ॱˑ	[C
    //   152: astore 9
    //   154: iload 5
    //   156: newarray char
    //   158: astore 10
    //   160: aload 9
    //   162: iload_3
    //   163: aload 10
    //   165: iconst_0
    //   166: iload 5
    //   168: invokestatic 200	java/lang/System:arraycopy	(Ljava/lang/Object;ILjava/lang/Object;II)V
    //   171: aload_1
    //   172: ifnull +6 -> 178
    //   175: goto +81 -> 256
    //   178: aload 10
    //   180: astore_1
    //   181: goto +211 -> 392
    //   184: iload 5
    //   186: newarray char
    //   188: astore 9
    //   190: iconst_0
    //   191: istore_3
    //   192: iconst_0
    //   193: istore 4
    //   195: goto -189 -> 6
    //   198: bipush 82
    //   200: istore 4
    //   202: goto +308 -> 510
    //   205: getstatic 26	o/LQ:ॱˉ	I
    //   208: bipush 107
    //   210: iadd
    //   211: istore_3
    //   212: iload_3
    //   213: sipush 128
    //   216: irem
    //   217: putstatic 24	o/LQ:ॱᐧ	I
    //   220: iload_3
    //   221: iconst_2
    //   222: irem
    //   223: ifne +6 -> 229
    //   226: goto -207 -> 19
    //   229: goto +314 -> 543
    //   232: bipush 43
    //   234: istore 4
    //   236: goto +274 -> 510
    //   239: iload 5
    //   241: newarray char
    //   243: astore 9
    //   245: iconst_0
    //   246: istore_3
    //   247: goto +90 -> 337
    //   250: aload 9
    //   252: astore_1
    //   253: goto +73 -> 326
    //   256: getstatic 26	o/LQ:ॱˉ	I
    //   259: bipush 99
    //   261: iadd
    //   262: istore_3
    //   263: iload_3
    //   264: sipush 128
    //   267: irem
    //   268: putstatic 24	o/LQ:ॱᐧ	I
    //   271: iload_3
    //   272: iconst_2
    //   273: irem
    //   274: ifne +6 -> 280
    //   277: goto +6 -> 283
    //   280: goto -217 -> 63
    //   283: bipush 80
    //   285: istore_3
    //   286: goto +6 -> 292
    //   289: goto +132 -> 421
    //   292: iload_3
    //   293: lookupswitch	default:+27->320, 80:+-109->184, 93:+-177->116
    //   320: goto -204 -> 116
    //   323: goto +108 -> 431
    //   326: iload 6
    //   328: ifle +6 -> 334
    //   331: goto -126 -> 205
    //   334: goto +15 -> 349
    //   337: iload_3
    //   338: iload 5
    //   340: if_icmpge +6 -> 346
    //   343: goto -111 -> 232
    //   346: goto -148 -> 198
    //   349: new 88	java/lang/String
    //   352: dup
    //   353: aload_1
    //   354: invokespecial 205	java/lang/String:<init>	([C)V
    //   357: areturn
    //   358: aload 9
    //   360: astore_1
    //   361: goto -301 -> 60
    //   364: aload 9
    //   366: iload_3
    //   367: aload_1
    //   368: iload 5
    //   370: iload_3
    //   371: isub
    //   372: iconst_1
    //   373: isub
    //   374: caload
    //   375: castore
    //   376: iload_3
    //   377: iconst_1
    //   378: iadd
    //   379: istore_3
    //   380: goto -43 -> 337
    //   383: goto +100 -> 483
    //   386: astore_0
    //   387: aload_0
    //   388: athrow
    //   389: goto +159 -> 548
    //   392: iload 7
    //   394: ifle +6 -> 400
    //   397: goto +195 -> 592
    //   400: goto -376 -> 24
    //   403: aload_1
    //   404: iload_3
    //   405: aload_1
    //   406: iload_3
    //   407: caload
    //   408: aload_0
    //   409: iconst_2
    //   410: iaload
    //   411: isub
    //   412: i2c
    //   413: castore
    //   414: iload_3
    //   415: iconst_1
    //   416: iadd
    //   417: istore_3
    //   418: goto -388 -> 30
    //   421: iload_2
    //   422: ifeq +6 -> 428
    //   425: goto -186 -> 239
    //   428: goto -102 -> 326
    //   431: aload 9
    //   433: iload 4
    //   435: aload 10
    //   437: iload 4
    //   439: caload
    //   440: iconst_1
    //   441: ishl
    //   442: iconst_1
    //   443: iadd
    //   444: iload_3
    //   445: isub
    //   446: i2c
    //   447: castore
    //   448: goto +184 -> 632
    //   451: iload_3
    //   452: lookupswitch	default:+28->480, 49:+-31->421, 99:+-383->69
    //   480: goto -59 -> 421
    //   483: getstatic 24	o/LQ:ॱᐧ	I
    //   486: bipush 117
    //   488: iadd
    //   489: istore_3
    //   490: iload_3
    //   491: sipush 128
    //   494: irem
    //   495: putstatic 26	o/LQ:ॱˉ	I
    //   498: iload_3
    //   499: iconst_2
    //   500: irem
    //   501: ifeq +6 -> 507
    //   504: goto -501 -> 3
    //   507: goto -377 -> 130
    //   510: iload 4
    //   512: lookupswitch	default:+28->540, 43:+-148->364, 82:+-262->250
    //   540: goto -290 -> 250
    //   543: iconst_0
    //   544: istore_3
    //   545: goto -515 -> 30
    //   548: aload_1
    //   549: iload 4
    //   551: baload
    //   552: iconst_1
    //   553: if_icmpne +6 -> 559
    //   556: goto +42 -> 598
    //   559: goto -517 -> 42
    //   562: getstatic 24	o/LQ:ॱᐧ	I
    //   565: bipush 15
    //   567: iadd
    //   568: istore 8
    //   570: iload 8
    //   572: sipush 128
    //   575: irem
    //   576: putstatic 26	o/LQ:ॱˉ	I
    //   579: iload 8
    //   581: iconst_2
    //   582: irem
    //   583: ifeq +6 -> 589
    //   586: goto -197 -> 389
    //   589: goto -41 -> 548
    //   592: bipush 99
    //   594: istore_3
    //   595: goto -144 -> 451
    //   598: getstatic 24	o/LQ:ॱᐧ	I
    //   601: istore 8
    //   603: iload 8
    //   605: bipush 61
    //   607: iadd
    //   608: istore 8
    //   610: iload 8
    //   612: sipush 128
    //   615: irem
    //   616: putstatic 26	o/LQ:ॱˉ	I
    //   619: iload 8
    //   621: iconst_2
    //   622: irem
    //   623: ifeq +6 -> 629
    //   626: goto -303 -> 323
    //   629: goto -198 -> 431
    //   632: aload 9
    //   634: iload 4
    //   636: caload
    //   637: istore_3
    //   638: iload 4
    //   640: iconst_1
    //   641: iadd
    //   642: istore 4
    //   644: goto -638 -> 6
    // Local variable table:
    //   start	length	slot	name	signature
    //   0	647	0	paramArrayOfInt	int[]
    //   0	647	1	paramArrayOfByte	byte[]
    //   0	647	2	paramBoolean	boolean
    //   20	618	3	i	int
    //   6	637	4	j	int
    //   8	364	5	k	int
    //   142	185	6	m	int
    //   91	302	7	n	int
    //   568	55	8	i1	int
    //   42	591	9	arrayOfChar1	char[]
    //   46	390	10	arrayOfChar2	char[]
    // Exception table:
    //   from	to	target	type
    //   598	603	386	java/lang/Exception
    //   610	619	386	java/lang/Exception
  }
  
  /* Error */
  private String ˋ(String paramString)
  {
    // Byte code:
    //   0: goto +289 -> 289
    //   3: aload 4
    //   5: arraylength
    //   6: istore_3
    //   7: iload_2
    //   8: iload_3
    //   9: if_icmpge +6 -> 15
    //   12: goto +430 -> 442
    //   15: goto +234 -> 249
    //   18: aload_1
    //   19: iconst_4
    //   20: newarray int
    //   22: dup
    //   23: iconst_0
    //   24: sipush 149
    //   27: iastore
    //   28: dup
    //   29: iconst_1
    //   30: bipush 10
    //   32: iastore
    //   33: dup
    //   34: iconst_2
    //   35: bipush 114
    //   37: iastore
    //   38: dup
    //   39: iconst_3
    //   40: iconst_0
    //   41: iastore
    //   42: bipush 10
    //   44: newarray byte
    //   46: dup
    //   47: iconst_0
    //   48: ldc 116
    //   50: bastore
    //   51: dup
    //   52: iconst_1
    //   53: ldc 117
    //   55: bastore
    //   56: dup
    //   57: iconst_2
    //   58: ldc 117
    //   60: bastore
    //   61: dup
    //   62: iconst_3
    //   63: ldc 117
    //   65: bastore
    //   66: dup
    //   67: iconst_4
    //   68: ldc 116
    //   70: bastore
    //   71: dup
    //   72: iconst_5
    //   73: ldc 117
    //   75: bastore
    //   76: dup
    //   77: bipush 6
    //   79: ldc 116
    //   81: bastore
    //   82: dup
    //   83: bipush 7
    //   85: ldc 117
    //   87: bastore
    //   88: dup
    //   89: bipush 8
    //   91: ldc 117
    //   93: bastore
    //   94: dup
    //   95: bipush 9
    //   97: ldc 117
    //   99: bastore
    //   100: iconst_1
    //   101: invokestatic 121	o/LQ:ˊ	([I[BZ)Ljava/lang/String;
    //   104: invokevirtual 99	java/lang/String:intern	()Ljava/lang/String;
    //   107: invokevirtual 211	java/lang/String:getBytes	(Ljava/lang/String;)[B
    //   110: astore 4
    //   112: aload 4
    //   114: arraylength
    //   115: newarray byte
    //   117: astore_1
    //   118: goto +287 -> 405
    //   121: new 88	java/lang/String
    //   124: dup
    //   125: aload_1
    //   126: iconst_4
    //   127: newarray int
    //   129: dup
    //   130: iconst_0
    //   131: sipush 159
    //   134: iastore
    //   135: dup
    //   136: iconst_1
    //   137: iconst_5
    //   138: iastore
    //   139: dup
    //   140: iconst_2
    //   141: iconst_0
    //   142: iastore
    //   143: dup
    //   144: iconst_3
    //   145: iconst_4
    //   146: iastore
    //   147: iconst_5
    //   148: newarray byte
    //   150: dup
    //   151: iconst_0
    //   152: ldc 116
    //   154: bastore
    //   155: dup
    //   156: iconst_1
    //   157: ldc 116
    //   159: bastore
    //   160: dup
    //   161: iconst_2
    //   162: ldc 117
    //   164: bastore
    //   165: dup
    //   166: iconst_3
    //   167: ldc 116
    //   169: bastore
    //   170: dup
    //   171: iconst_4
    //   172: ldc 116
    //   174: bastore
    //   175: iconst_1
    //   176: invokestatic 121	o/LQ:ˊ	([I[BZ)Ljava/lang/String;
    //   179: invokevirtual 99	java/lang/String:intern	()Ljava/lang/String;
    //   182: invokespecial 214	java/lang/String:<init>	([BLjava/lang/String;)V
    //   185: astore_1
    //   186: aload_1
    //   187: areturn
    //   188: aload_1
    //   189: iload_2
    //   190: aload 4
    //   192: aload 4
    //   194: arraylength
    //   195: iload_2
    //   196: isub
    //   197: iconst_1
    //   198: isub
    //   199: baload
    //   200: getstatic 31	o/LQ:ॱˌ	B
    //   203: ixor
    //   204: i2b
    //   205: bastore
    //   206: iload_2
    //   207: iconst_1
    //   208: iadd
    //   209: istore_2
    //   210: goto +45 -> 255
    //   213: iload_3
    //   214: lookupswitch	default:+26->240, 33:+261->475, 70:+-93->121
    //   240: goto +235 -> 475
    //   243: astore_1
    //   244: aload_1
    //   245: athrow
    //   246: astore_1
    //   247: aload_1
    //   248: athrow
    //   249: bipush 70
    //   251: istore_3
    //   252: goto -39 -> 213
    //   255: getstatic 24	o/LQ:ॱᐧ	I
    //   258: istore_3
    //   259: iload_3
    //   260: bipush 81
    //   262: iadd
    //   263: istore_3
    //   264: iload_3
    //   265: sipush 128
    //   268: irem
    //   269: putstatic 26	o/LQ:ॱˉ	I
    //   272: iload_3
    //   273: iconst_2
    //   274: irem
    //   275: ifeq +6 -> 281
    //   278: goto +161 -> 439
    //   281: goto +129 -> 410
    //   284: iconst_0
    //   285: istore_2
    //   286: goto +127 -> 413
    //   289: goto +159 -> 448
    //   292: goto -104 -> 188
    //   295: astore_1
    //   296: new 216	java/lang/RuntimeException
    //   299: dup
    //   300: aload_1
    //   301: invokespecial 219	java/lang/RuntimeException:<init>	(Ljava/lang/Throwable;)V
    //   304: athrow
    //   305: aload_1
    //   306: iconst_4
    //   307: newarray int
    //   309: dup
    //   310: iconst_0
    //   311: sipush 149
    //   314: iastore
    //   315: dup
    //   316: iconst_1
    //   317: bipush 10
    //   319: iastore
    //   320: dup
    //   321: iconst_2
    //   322: bipush 114
    //   324: iastore
    //   325: dup
    //   326: iconst_3
    //   327: iconst_0
    //   328: iastore
    //   329: bipush 10
    //   331: newarray byte
    //   333: dup
    //   334: iconst_0
    //   335: ldc 116
    //   337: bastore
    //   338: dup
    //   339: iconst_1
    //   340: ldc 117
    //   342: bastore
    //   343: dup
    //   344: iconst_2
    //   345: ldc 117
    //   347: bastore
    //   348: dup
    //   349: iconst_3
    //   350: ldc 117
    //   352: bastore
    //   353: dup
    //   354: iconst_4
    //   355: ldc 116
    //   357: bastore
    //   358: dup
    //   359: iconst_5
    //   360: ldc 117
    //   362: bastore
    //   363: dup
    //   364: bipush 6
    //   366: ldc 116
    //   368: bastore
    //   369: dup
    //   370: bipush 7
    //   372: ldc 117
    //   374: bastore
    //   375: dup
    //   376: bipush 8
    //   378: ldc 117
    //   380: bastore
    //   381: dup
    //   382: bipush 9
    //   384: ldc 117
    //   386: bastore
    //   387: iconst_1
    //   388: invokestatic 121	o/LQ:ˊ	([I[BZ)Ljava/lang/String;
    //   391: invokevirtual 99	java/lang/String:intern	()Ljava/lang/String;
    //   394: invokevirtual 211	java/lang/String:getBytes	(Ljava/lang/String;)[B
    //   397: astore 4
    //   399: aload 4
    //   401: arraylength
    //   402: newarray byte
    //   404: astore_1
    //   405: iconst_0
    //   406: istore_2
    //   407: goto -404 -> 3
    //   410: goto -407 -> 3
    //   413: iload_2
    //   414: tableswitch	default:+22->436, 0:+-396->18, 1:+-109->305
    //   436: goto -418 -> 18
    //   439: goto -29 -> 410
    //   442: bipush 33
    //   444: istore_3
    //   445: goto -232 -> 213
    //   448: getstatic 24	o/LQ:ॱᐧ	I
    //   451: bipush 63
    //   453: iadd
    //   454: istore_2
    //   455: iload_2
    //   456: sipush 128
    //   459: irem
    //   460: putstatic 26	o/LQ:ॱˉ	I
    //   463: iload_2
    //   464: iconst_2
    //   465: irem
    //   466: ifeq +6 -> 472
    //   469: goto +33 -> 502
    //   472: goto -188 -> 284
    //   475: getstatic 26	o/LQ:ॱˉ	I
    //   478: bipush 103
    //   480: iadd
    //   481: istore_3
    //   482: iload_3
    //   483: sipush 128
    //   486: irem
    //   487: putstatic 24	o/LQ:ॱᐧ	I
    //   490: iload_3
    //   491: iconst_2
    //   492: irem
    //   493: ifne +6 -> 499
    //   496: goto -204 -> 292
    //   499: goto -311 -> 188
    //   502: iconst_1
    //   503: istore_2
    //   504: goto -91 -> 413
    // Local variable table:
    //   start	length	slot	name	signature
    //   0	507	0	this	LQ
    //   0	507	1	paramString	String
    //   7	497	2	i	int
    //   6	487	3	j	int
    //   3	397	4	arrayOfByte	byte[]
    // Exception table:
    //   from	to	target	type
    //   264	272	243	java/lang/Exception
    //   255	259	246	java/lang/Exception
    //   3	7	295	java/io/UnsupportedEncodingException
    //   18	118	295	java/io/UnsupportedEncodingException
    //   121	186	295	java/io/UnsupportedEncodingException
    //   188	206	295	java/io/UnsupportedEncodingException
    //   305	405	295	java/io/UnsupportedEncodingException
  }
  
  static void ˎ()
  {
    ॱˑ = new char[] { 87, 152, 150, 172, 170, 167, 172, 171, 139, 143, 171, 167, 166, 172, 179, 164, 158, 172, 176, 162, 149, 52, 93, 96, 111, 107, 108, 114, 104, 98, 82, 88, 111, 101, 206, 201, 203, 211, 200, 198, 104, 203, 201, 205, 207, 306, 287, 298, 292, 300, 295, 231, 291, 305, 298, 287, 292, 222, 234, 298, 298, 307, 300, 222, 234, 300, 301, 295, 306, 287, 289, 301, 298, 285, 302, 301, 8420, 292, 236, 304, 291, 306, 287, 298, 292, 300, 263, 306, 307, 301, 311, 287, 266, 230, 291, 56, 142, 179, 182, 173, 170, 138, 109, 147, 179, 183, 184, 142, 109, 143, 175, 183, 181, 181, 176, 174, 182, 178, 180, 176, 4233, 4237, 145, 151, 178, 179, 177, 173, 176, 177, 162, 165, 187, 185, 187, 180, 157, 129, 141, 179, 177, 173, 176, 177, 178, 2, 15, 18, 11, 81, 161, 165, 169, 168, 170, 164, 176, 195, 192, 22, 57, 77, 84, 70 };
  }
  
  /* Error */
  private final void ᐝ()
  {
    // Byte code:
    //   0: goto +449 -> 449
    //   3: iload_1
    //   4: lookupswitch	default:+28->32, 20:+333->337, 41:+42->46
    //   32: goto +305 -> 337
    //   35: iconst_0
    //   36: istore_1
    //   37: goto +113 -> 150
    //   40: bipush 41
    //   42: istore_1
    //   43: goto -40 -> 3
    //   46: iconst_4
    //   47: newarray int
    //   49: dup
    //   50: iconst_0
    //   51: bipush 21
    //   53: iastore
    //   54: dup
    //   55: iconst_1
    //   56: bipush 12
    //   58: iastore
    //   59: dup
    //   60: iconst_2
    //   61: iconst_0
    //   62: iastore
    //   63: dup
    //   64: iconst_3
    //   65: iconst_3
    //   66: iastore
    //   67: bipush 12
    //   69: newarray byte
    //   71: dup
    //   72: iconst_0
    //   73: ldc 117
    //   75: bastore
    //   76: dup
    //   77: iconst_1
    //   78: ldc 116
    //   80: bastore
    //   81: dup
    //   82: iconst_2
    //   83: ldc 117
    //   85: bastore
    //   86: dup
    //   87: iconst_3
    //   88: ldc 116
    //   90: bastore
    //   91: dup
    //   92: iconst_4
    //   93: ldc 116
    //   95: bastore
    //   96: dup
    //   97: iconst_5
    //   98: ldc 116
    //   100: bastore
    //   101: dup
    //   102: bipush 6
    //   104: ldc 117
    //   106: bastore
    //   107: dup
    //   108: bipush 7
    //   110: ldc 116
    //   112: bastore
    //   113: dup
    //   114: bipush 8
    //   116: ldc 116
    //   118: bastore
    //   119: dup
    //   120: bipush 9
    //   122: ldc 116
    //   124: bastore
    //   125: dup
    //   126: bipush 10
    //   128: ldc 116
    //   130: bastore
    //   131: dup
    //   132: bipush 11
    //   134: ldc 116
    //   136: bastore
    //   137: iconst_1
    //   138: invokestatic 121	o/LQ:ˊ	([I[BZ)Ljava/lang/String;
    //   141: invokevirtual 99	java/lang/String:intern	()Ljava/lang/String;
    //   144: invokestatic 192	o/vq:ˊ	(Ljava/lang/String;)V
    //   147: goto +94 -> 241
    //   150: iload_1
    //   151: tableswitch	default:+21->172, 0:+90->241, 1:+36->187
    //   172: goto +15 -> 187
    //   175: astore_2
    //   176: aload_2
    //   177: athrow
    //   178: goto +44 -> 222
    //   181: bipush 37
    //   183: istore_1
    //   184: goto +276 -> 460
    //   187: getstatic 26	o/LQ:ॱˉ	I
    //   190: bipush 77
    //   192: iadd
    //   193: istore_1
    //   194: iload_1
    //   195: sipush 128
    //   198: irem
    //   199: putstatic 24	o/LQ:ॱᐧ	I
    //   202: iload_1
    //   203: iconst_2
    //   204: irem
    //   205: ifne +6 -> 211
    //   208: goto +683 -> 891
    //   211: goto -171 -> 40
    //   214: iconst_1
    //   215: istore_1
    //   216: goto +275 -> 491
    //   219: astore_2
    //   220: aload_2
    //   221: athrow
    //   222: aload_0
    //   223: getfield 153	o/LQ:ॱˈ	Lo/LE;
    //   226: getfield 321	o/LE:ˊ	Lo/aH;
    //   229: aload_2
    //   230: checkcast 323	android/support/v7/widget/RecyclerView$ˎ
    //   233: invokevirtual 328	o/aH:ˏ	(Landroid/support/v7/widget/RecyclerView$ˎ;)V
    //   236: aload_0
    //   237: invokespecial 330	o/LQ:ʼ	()V
    //   240: return
    //   241: aload_2
    //   242: aload_3
    //   243: checkcast 332	android/support/v7/widget/RecyclerView$ˊ
    //   246: invokevirtual 336	o/aH:setAdapter	(Landroid/support/v7/widget/RecyclerView$ˊ;)V
    //   249: aload_0
    //   250: getfield 153	o/LQ:ॱˈ	Lo/LE;
    //   253: getfield 321	o/LE:ˊ	Lo/aH;
    //   256: aload_0
    //   257: getfield 153	o/LQ:ॱˈ	Lo/LE;
    //   260: getfield 339	o/LE:ॱ	Landroid/widget/TextView;
    //   263: checkcast 341	android/view/View
    //   266: invokevirtual 345	o/aH:setEmptyView	(Landroid/view/View;)V
    //   269: new 347	o/ᔄ
    //   272: dup
    //   273: aload_0
    //   274: getfield 350	o/LQ:ˏ	Landroid/content/Context;
    //   277: iconst_1
    //   278: invokespecial 353	o/ᔄ:<init>	(Landroid/content/Context;I)V
    //   281: astore_2
    //   282: aload_0
    //   283: getfield 350	o/LQ:ˏ	Landroid/content/Context;
    //   286: getstatic 358	o/Lt$iF:preference_list_divider_material	I
    //   289: invokestatic 363	o/ᔆ:ˎ	(Landroid/content/Context;I)Landroid/graphics/drawable/Drawable;
    //   292: astore_3
    //   293: aload_3
    //   294: ifnull +6 -> 300
    //   297: goto +600 -> 897
    //   300: goto -119 -> 181
    //   303: goto -81 -> 222
    //   306: iconst_0
    //   307: istore_1
    //   308: goto +183 -> 491
    //   311: getstatic 26	o/LQ:ॱˉ	I
    //   314: iconst_5
    //   315: iadd
    //   316: istore_1
    //   317: iload_1
    //   318: sipush 128
    //   321: irem
    //   322: putstatic 24	o/LQ:ॱᐧ	I
    //   325: iload_1
    //   326: iconst_2
    //   327: irem
    //   328: ifne +6 -> 334
    //   331: goto -117 -> 214
    //   334: goto -28 -> 306
    //   337: iconst_4
    //   338: newarray int
    //   340: dup
    //   341: iconst_0
    //   342: bipush 21
    //   344: iastore
    //   345: dup
    //   346: iconst_1
    //   347: bipush 12
    //   349: iastore
    //   350: dup
    //   351: iconst_2
    //   352: iconst_0
    //   353: iastore
    //   354: dup
    //   355: iconst_3
    //   356: iconst_3
    //   357: iastore
    //   358: bipush 12
    //   360: newarray byte
    //   362: dup
    //   363: iconst_0
    //   364: ldc 117
    //   366: bastore
    //   367: dup
    //   368: iconst_1
    //   369: ldc 116
    //   371: bastore
    //   372: dup
    //   373: iconst_2
    //   374: ldc 117
    //   376: bastore
    //   377: dup
    //   378: iconst_3
    //   379: ldc 116
    //   381: bastore
    //   382: dup
    //   383: iconst_4
    //   384: ldc 116
    //   386: bastore
    //   387: dup
    //   388: iconst_5
    //   389: ldc 116
    //   391: bastore
    //   392: dup
    //   393: bipush 6
    //   395: ldc 117
    //   397: bastore
    //   398: dup
    //   399: bipush 7
    //   401: ldc 116
    //   403: bastore
    //   404: dup
    //   405: bipush 8
    //   407: ldc 116
    //   409: bastore
    //   410: dup
    //   411: bipush 9
    //   413: ldc 116
    //   415: bastore
    //   416: dup
    //   417: bipush 10
    //   419: ldc 116
    //   421: bastore
    //   422: dup
    //   423: bipush 11
    //   425: ldc 116
    //   427: bastore
    //   428: iconst_1
    //   429: invokestatic 121	o/LQ:ˊ	([I[BZ)Ljava/lang/String;
    //   432: astore 4
    //   434: aload 4
    //   436: invokevirtual 99	java/lang/String:intern	()Ljava/lang/String;
    //   439: astore 4
    //   441: aload 4
    //   443: invokestatic 192	o/vq:ˊ	(Ljava/lang/String;)V
    //   446: goto -205 -> 241
    //   449: goto +70 -> 519
    //   452: aload_2
    //   453: aload_3
    //   454: invokevirtual 366	o/ᔄ:ॱ	(Landroid/graphics/drawable/Drawable;)V
    //   457: goto -146 -> 311
    //   460: iload_1
    //   461: lookupswitch	default:+27->488, 37:+-239->222, 47:+-9->452
    //   488: goto -266 -> 222
    //   491: iload_1
    //   492: tableswitch	default:+24->516, 0:+-314->178, 1:+-189->303
    //   516: goto -338 -> 178
    //   519: aload_0
    //   520: new 186	o/Lz
    //   523: dup
    //   524: invokespecial 368	o/Lz:<init>	()V
    //   527: putfield 194	o/LQ:ॱـ	Lo/Lz;
    //   530: aload_0
    //   531: getfield 153	o/LQ:ॱˈ	Lo/LE;
    //   534: getfield 321	o/LE:ˊ	Lo/aH;
    //   537: astore_2
    //   538: aload_2
    //   539: iconst_4
    //   540: newarray int
    //   542: dup
    //   543: iconst_0
    //   544: iconst_0
    //   545: iastore
    //   546: dup
    //   547: iconst_1
    //   548: bipush 21
    //   550: iastore
    //   551: dup
    //   552: iconst_2
    //   553: bipush 65
    //   555: iastore
    //   556: dup
    //   557: iconst_3
    //   558: iconst_0
    //   559: iastore
    //   560: bipush 21
    //   562: newarray byte
    //   564: dup
    //   565: iconst_0
    //   566: ldc 117
    //   568: bastore
    //   569: dup
    //   570: iconst_1
    //   571: ldc 116
    //   573: bastore
    //   574: dup
    //   575: iconst_2
    //   576: ldc 116
    //   578: bastore
    //   579: dup
    //   580: iconst_3
    //   581: ldc 116
    //   583: bastore
    //   584: dup
    //   585: iconst_4
    //   586: ldc 117
    //   588: bastore
    //   589: dup
    //   590: iconst_5
    //   591: ldc 116
    //   593: bastore
    //   594: dup
    //   595: bipush 6
    //   597: ldc 116
    //   599: bastore
    //   600: dup
    //   601: bipush 7
    //   603: ldc 116
    //   605: bastore
    //   606: dup
    //   607: bipush 8
    //   609: ldc 116
    //   611: bastore
    //   612: dup
    //   613: bipush 9
    //   615: ldc 116
    //   617: bastore
    //   618: dup
    //   619: bipush 10
    //   621: ldc 116
    //   623: bastore
    //   624: dup
    //   625: bipush 11
    //   627: ldc 117
    //   629: bastore
    //   630: dup
    //   631: bipush 12
    //   633: ldc 116
    //   635: bastore
    //   636: dup
    //   637: bipush 13
    //   639: ldc 116
    //   641: bastore
    //   642: dup
    //   643: bipush 14
    //   645: ldc 116
    //   647: bastore
    //   648: dup
    //   649: bipush 15
    //   651: ldc 117
    //   653: bastore
    //   654: dup
    //   655: bipush 16
    //   657: ldc 116
    //   659: bastore
    //   660: dup
    //   661: bipush 17
    //   663: ldc 116
    //   665: bastore
    //   666: dup
    //   667: bipush 18
    //   669: ldc 116
    //   671: bastore
    //   672: dup
    //   673: bipush 19
    //   675: ldc 117
    //   677: bastore
    //   678: dup
    //   679: bipush 20
    //   681: ldc 117
    //   683: bastore
    //   684: iconst_0
    //   685: invokestatic 121	o/LQ:ˊ	([I[BZ)Ljava/lang/String;
    //   688: invokevirtual 99	java/lang/String:intern	()Ljava/lang/String;
    //   691: invokestatic 149	o/vq:ˋ	(Ljava/lang/Object;Ljava/lang/String;)V
    //   694: aload_2
    //   695: new 370	android/support/v7/widget/LinearLayoutManager
    //   698: dup
    //   699: aload_0
    //   700: getfield 350	o/LQ:ˏ	Landroid/content/Context;
    //   703: invokespecial 371	android/support/v7/widget/LinearLayoutManager:<init>	(Landroid/content/Context;)V
    //   706: checkcast 373	android/support/v7/widget/RecyclerView$LayoutManager
    //   709: invokevirtual 377	o/aH:setLayoutManager	(Landroid/support/v7/widget/RecyclerView$LayoutManager;)V
    //   712: aload_0
    //   713: getfield 153	o/LQ:ॱˈ	Lo/LE;
    //   716: getfield 321	o/LE:ˊ	Lo/aH;
    //   719: astore_2
    //   720: aload_2
    //   721: iconst_4
    //   722: newarray int
    //   724: dup
    //   725: iconst_0
    //   726: iconst_0
    //   727: iastore
    //   728: dup
    //   729: iconst_1
    //   730: bipush 21
    //   732: iastore
    //   733: dup
    //   734: iconst_2
    //   735: bipush 65
    //   737: iastore
    //   738: dup
    //   739: iconst_3
    //   740: iconst_0
    //   741: iastore
    //   742: bipush 21
    //   744: newarray byte
    //   746: dup
    //   747: iconst_0
    //   748: ldc 117
    //   750: bastore
    //   751: dup
    //   752: iconst_1
    //   753: ldc 116
    //   755: bastore
    //   756: dup
    //   757: iconst_2
    //   758: ldc 116
    //   760: bastore
    //   761: dup
    //   762: iconst_3
    //   763: ldc 116
    //   765: bastore
    //   766: dup
    //   767: iconst_4
    //   768: ldc 117
    //   770: bastore
    //   771: dup
    //   772: iconst_5
    //   773: ldc 116
    //   775: bastore
    //   776: dup
    //   777: bipush 6
    //   779: ldc 116
    //   781: bastore
    //   782: dup
    //   783: bipush 7
    //   785: ldc 116
    //   787: bastore
    //   788: dup
    //   789: bipush 8
    //   791: ldc 116
    //   793: bastore
    //   794: dup
    //   795: bipush 9
    //   797: ldc 116
    //   799: bastore
    //   800: dup
    //   801: bipush 10
    //   803: ldc 116
    //   805: bastore
    //   806: dup
    //   807: bipush 11
    //   809: ldc 117
    //   811: bastore
    //   812: dup
    //   813: bipush 12
    //   815: ldc 116
    //   817: bastore
    //   818: dup
    //   819: bipush 13
    //   821: ldc 116
    //   823: bastore
    //   824: dup
    //   825: bipush 14
    //   827: ldc 116
    //   829: bastore
    //   830: dup
    //   831: bipush 15
    //   833: ldc 117
    //   835: bastore
    //   836: dup
    //   837: bipush 16
    //   839: ldc 116
    //   841: bastore
    //   842: dup
    //   843: bipush 17
    //   845: ldc 116
    //   847: bastore
    //   848: dup
    //   849: bipush 18
    //   851: ldc 116
    //   853: bastore
    //   854: dup
    //   855: bipush 19
    //   857: ldc 117
    //   859: bastore
    //   860: dup
    //   861: bipush 20
    //   863: ldc 117
    //   865: bastore
    //   866: iconst_0
    //   867: invokestatic 121	o/LQ:ˊ	([I[BZ)Ljava/lang/String;
    //   870: invokevirtual 99	java/lang/String:intern	()Ljava/lang/String;
    //   873: invokestatic 149	o/vq:ˋ	(Ljava/lang/Object;Ljava/lang/String;)V
    //   876: aload_0
    //   877: getfield 194	o/LQ:ॱـ	Lo/Lz;
    //   880: astore_3
    //   881: aload_3
    //   882: ifnonnull +6 -> 888
    //   885: goto +18 -> 903
    //   888: goto -853 -> 35
    //   891: bipush 20
    //   893: istore_1
    //   894: goto -891 -> 3
    //   897: bipush 47
    //   899: istore_1
    //   900: goto -440 -> 460
    //   903: iconst_1
    //   904: istore_1
    //   905: goto -755 -> 150
    // Local variable table:
    //   start	length	slot	name	signature
    //   0	908	0	this	LQ
    //   3	902	1	i	int
    //   175	2	2	localException1	Exception
    //   219	23	2	localException2	Exception
    //   281	440	2	localObject1	Object
    //   242	640	3	localObject2	Object
    //   432	10	4	str	String
    // Exception table:
    //   from	to	target	type
    //   441	446	175	java/lang/Exception
    //   337	434	219	java/lang/Exception
    //   434	441	219	java/lang/Exception
    //   441	446	219	java/lang/Exception
  }
}
