package o;

import android.content.Context;
import android.graphics.drawable.Drawable;
import android.os.Bundle;
import android.support.v7.widget.LinearLayoutManager;
import android.support.v7.widget.RecyclerView.LayoutManager;
import android.support.v7.widget.RecyclerView.aUx;
import android.support.v7.widget.RecyclerView.ˊ;
import android.support.v7.widget.RecyclerView.ˎ;
import android.view.View;
import android.widget.TextView;
import java.util.ArrayList;
import java.util.List;

public abstract class LR
  extends K<LG>
{
  private static int ʹ;
  private static int ʻ = 0;
  private static long ʼ;
  private static char[] ʽ;
  public static final If ˋ;
  private RecyclerView.aUx ˊ;
  protected LC ˎ;
  private String ॱ;
  private ArrayList<FF> ᐝ;
  
  static
  {
    ʹ = 1;
    ʼˊ();
    ˋ = new If(null);
    int i = ʻ + 17;
    ʹ = i % 128;
    if (i % 2 == 0) {}
  }
  
  public LR()
  {
    ArrayList localArrayList = new ArrayList();
    try
    {
      this.ᐝ = localArrayList;
      return;
    }
    catch (Exception localException)
    {
      throw localException;
    }
  }
  
  /* Error */
  private final void ʻˊ()
  {
    // Byte code:
    //   0: goto +431 -> 431
    //   3: getstatic 36	o/LR:ʹ	I
    //   6: bipush 77
    //   8: iadd
    //   9: istore_2
    //   10: iload_2
    //   11: sipush 128
    //   14: irem
    //   15: putstatic 34	o/LR:ʻ	I
    //   18: iload_2
    //   19: iconst_2
    //   20: irem
    //   21: ifeq +6 -> 27
    //   24: goto +226 -> 250
    //   27: goto +369 -> 396
    //   30: iconst_4
    //   31: sipush 413
    //   34: sipush 30253
    //   37: invokestatic 61	o/O:ˋ	(IIC)Ljava/lang/Object;
    //   40: checkcast 63	java/lang/Class
    //   43: ldc 64
    //   45: invokevirtual 68	java/lang/Class:getField	(Ljava/lang/String;)Ljava/lang/reflect/Field;
    //   48: aconst_null
    //   49: invokevirtual 74	java/lang/reflect/Field:get	(Ljava/lang/Object;)Ljava/lang/Object;
    //   52: astore_3
    //   53: goto +20 -> 73
    //   56: astore_3
    //   57: aload_3
    //   58: invokevirtual 80	java/lang/Throwable:getCause	()Ljava/lang/Throwable;
    //   61: astore 4
    //   63: aload 4
    //   65: ifnull +6 -> 71
    //   68: aload 4
    //   70: athrow
    //   71: aload_3
    //   72: athrow
    //   73: bipush 6
    //   75: sipush 417
    //   78: iconst_0
    //   79: invokestatic 61	o/O:ˋ	(IIC)Ljava/lang/Object;
    //   82: checkcast 63	java/lang/Class
    //   85: ldc 82
    //   87: aconst_null
    //   88: invokevirtual 86	java/lang/Class:getMethod	(Ljava/lang/String;[Ljava/lang/Class;)Ljava/lang/reflect/Method;
    //   91: aload_3
    //   92: aconst_null
    //   93: invokevirtual 92	java/lang/reflect/Method:invoke	(Ljava/lang/Object;[Ljava/lang/Object;)Ljava/lang/Object;
    //   96: astore_3
    //   97: goto +20 -> 117
    //   100: astore_3
    //   101: aload_3
    //   102: invokevirtual 80	java/lang/Throwable:getCause	()Ljava/lang/Throwable;
    //   105: astore 4
    //   107: aload 4
    //   109: ifnull +6 -> 115
    //   112: aload 4
    //   114: athrow
    //   115: aload_3
    //   116: athrow
    //   117: iconst_4
    //   118: sipush 413
    //   121: sipush 30253
    //   124: invokestatic 61	o/O:ˋ	(IIC)Ljava/lang/Object;
    //   127: checkcast 63	java/lang/Class
    //   130: ldc 94
    //   132: aconst_null
    //   133: invokevirtual 86	java/lang/Class:getMethod	(Ljava/lang/String;[Ljava/lang/Class;)Ljava/lang/reflect/Method;
    //   136: aload_3
    //   137: aconst_null
    //   138: invokevirtual 92	java/lang/reflect/Method:invoke	(Ljava/lang/Object;[Ljava/lang/Object;)Ljava/lang/Object;
    //   141: checkcast 96	java/lang/String
    //   144: astore_3
    //   145: aload_3
    //   146: checkcast 98	java/lang/CharSequence
    //   149: invokeinterface 102 1 0
    //   154: ifle +6 -> 160
    //   157: goto +285 -> 442
    //   160: goto +239 -> 399
    //   163: return
    //   164: bipush 8
    //   166: istore_1
    //   167: goto +86 -> 253
    //   170: goto +20 -> 190
    //   173: astore_3
    //   174: aload_3
    //   175: invokevirtual 80	java/lang/Throwable:getCause	()Ljava/lang/Throwable;
    //   178: astore 4
    //   180: aload 4
    //   182: ifnull +6 -> 188
    //   185: aload 4
    //   187: athrow
    //   188: aload_3
    //   189: athrow
    //   190: iconst_4
    //   191: sipush 135
    //   194: ldc 103
    //   196: invokestatic 61	o/O:ˋ	(IIC)Ljava/lang/Object;
    //   199: checkcast 63	java/lang/Class
    //   202: ldc 104
    //   204: aconst_null
    //   205: invokevirtual 86	java/lang/Class:getMethod	(Ljava/lang/String;[Ljava/lang/Class;)Ljava/lang/reflect/Method;
    //   208: aconst_null
    //   209: aconst_null
    //   210: invokevirtual 92	java/lang/reflect/Method:invoke	(Ljava/lang/Object;[Ljava/lang/Object;)Ljava/lang/Object;
    //   213: checkcast 106	o/It
    //   216: astore 4
    //   218: aload 4
    //   220: aload_3
    //   221: invokeinterface 109 2 0
    //   226: new 10	o/LR$if
    //   229: dup
    //   230: aload_0
    //   231: aload_0
    //   232: invokevirtual 113	o/LR:ˏॱ	()Landroid/content/Context;
    //   235: invokespecial 116	o/LR$if:<init>	(Lo/LR;Landroid/content/Context;)V
    //   238: checkcast 118	o/Cx
    //   241: invokeinterface 123 2 0
    //   246: return
    //   247: goto +201 -> 448
    //   250: goto +146 -> 396
    //   253: iload_1
    //   254: lookupswitch	default:+26->280, 6:+41->295, 8:+185->439
    //   280: goto +15 -> 295
    //   283: iconst_1
    //   284: istore_1
    //   285: iload_1
    //   286: ifeq +6 -> 292
    //   289: goto -119 -> 170
    //   292: goto +203 -> 495
    //   295: goto -265 -> 30
    //   298: aload_0
    //   299: getfield 126	o/LR:ˏ	Landroid/databinding/ViewDataBinding;
    //   302: astore_3
    //   303: aload_3
    //   304: bipush 123
    //   306: sipush 18897
    //   309: bipush 8
    //   311: invokestatic 129	o/LR:ˎ	(ICI)Ljava/lang/String;
    //   314: invokevirtual 133	java/lang/String:intern	()Ljava/lang/String;
    //   317: invokestatic 138	o/vq:ˋ	(Ljava/lang/Object;Ljava/lang/String;)V
    //   320: aload_3
    //   321: checkcast 140	o/LG
    //   324: iconst_1
    //   325: invokevirtual 143	o/LG:ˊ	(Z)V
    //   328: aload_0
    //   329: getfield 126	o/LR:ˏ	Landroid/databinding/ViewDataBinding;
    //   332: checkcast 140	o/LG
    //   335: getfield 146	o/LG:ˊ	Landroid/widget/TextView;
    //   338: astore_3
    //   339: aload_3
    //   340: sipush 131
    //   343: iconst_0
    //   344: bipush 24
    //   346: invokestatic 129	o/LR:ˎ	(ICI)Ljava/lang/String;
    //   349: invokevirtual 133	java/lang/String:intern	()Ljava/lang/String;
    //   352: invokestatic 138	o/vq:ˋ	(Ljava/lang/Object;Ljava/lang/String;)V
    //   355: aload_3
    //   356: iconst_4
    //   357: invokevirtual 152	android/widget/TextView:setVisibility	(I)V
    //   360: goto +9 -> 369
    //   363: bipush 6
    //   365: istore_1
    //   366: goto -113 -> 253
    //   369: getstatic 36	o/LR:ʹ	I
    //   372: bipush 61
    //   374: iadd
    //   375: istore_1
    //   376: iload_1
    //   377: sipush 128
    //   380: irem
    //   381: putstatic 34	o/LR:ʻ	I
    //   384: iload_1
    //   385: iconst_2
    //   386: irem
    //   387: ifeq +6 -> 393
    //   390: goto -226 -> 164
    //   393: goto -30 -> 363
    //   396: goto -111 -> 285
    //   399: iconst_5
    //   400: istore_1
    //   401: goto +63 -> 464
    //   404: getstatic 36	o/LR:ʹ	I
    //   407: bipush 7
    //   409: iadd
    //   410: istore_1
    //   411: iload_1
    //   412: sipush 128
    //   415: irem
    //   416: putstatic 34	o/LR:ʻ	I
    //   419: iload_1
    //   420: iconst_2
    //   421: irem
    //   422: ifeq +6 -> 428
    //   425: goto -178 -> 247
    //   428: goto +20 -> 448
    //   431: goto -27 -> 404
    //   434: iconst_0
    //   435: istore_1
    //   436: goto -433 -> 3
    //   439: goto -409 -> 30
    //   442: bipush 67
    //   444: istore_1
    //   445: goto +19 -> 464
    //   448: aload_0
    //   449: getfield 55	o/LR:ᐝ	Ljava/util/ArrayList;
    //   452: invokevirtual 156	java/util/ArrayList:isEmpty	()Z
    //   455: ifeq +6 -> 461
    //   458: goto -160 -> 298
    //   461: goto -431 -> 30
    //   464: iload_1
    //   465: lookupswitch	default:+27->492, 5:+-31->434, 67:+-182->283
    //   492: goto -58 -> 434
    //   495: goto +20 -> 515
    //   498: astore_3
    //   499: aload_3
    //   500: invokevirtual 80	java/lang/Throwable:getCause	()Ljava/lang/Throwable;
    //   503: astore 4
    //   505: aload 4
    //   507: ifnull +6 -> 513
    //   510: aload 4
    //   512: athrow
    //   513: aload_3
    //   514: athrow
    //   515: iconst_4
    //   516: sipush 135
    //   519: ldc 103
    //   521: invokestatic 61	o/O:ˋ	(IIC)Ljava/lang/Object;
    //   524: checkcast 63	java/lang/Class
    //   527: ldc 104
    //   529: aconst_null
    //   530: invokevirtual 86	java/lang/Class:getMethod	(Ljava/lang/String;[Ljava/lang/Class;)Ljava/lang/reflect/Method;
    //   533: aconst_null
    //   534: aconst_null
    //   535: invokevirtual 92	java/lang/reflect/Method:invoke	(Ljava/lang/Object;[Ljava/lang/Object;)Ljava/lang/Object;
    //   538: checkcast 106	o/It
    //   541: astore_3
    //   542: iconst_4
    //   543: sipush 413
    //   546: sipush 30253
    //   549: invokestatic 61	o/O:ˋ	(IIC)Ljava/lang/Object;
    //   552: checkcast 63	java/lang/Class
    //   555: ldc 64
    //   557: invokevirtual 68	java/lang/Class:getField	(Ljava/lang/String;)Ljava/lang/reflect/Field;
    //   560: aconst_null
    //   561: invokevirtual 74	java/lang/reflect/Field:get	(Ljava/lang/Object;)Ljava/lang/Object;
    //   564: astore 4
    //   566: goto +20 -> 586
    //   569: astore_3
    //   570: aload_3
    //   571: invokevirtual 80	java/lang/Throwable:getCause	()Ljava/lang/Throwable;
    //   574: astore 4
    //   576: aload 4
    //   578: ifnull +6 -> 584
    //   581: aload 4
    //   583: athrow
    //   584: aload_3
    //   585: athrow
    //   586: bipush 6
    //   588: sipush 417
    //   591: iconst_0
    //   592: invokestatic 61	o/O:ˋ	(IIC)Ljava/lang/Object;
    //   595: checkcast 63	java/lang/Class
    //   598: ldc 82
    //   600: aconst_null
    //   601: invokevirtual 86	java/lang/Class:getMethod	(Ljava/lang/String;[Ljava/lang/Class;)Ljava/lang/reflect/Method;
    //   604: aload 4
    //   606: aconst_null
    //   607: invokevirtual 92	java/lang/reflect/Method:invoke	(Ljava/lang/Object;[Ljava/lang/Object;)Ljava/lang/Object;
    //   610: astore 4
    //   612: goto +20 -> 632
    //   615: astore_3
    //   616: aload_3
    //   617: invokevirtual 80	java/lang/Throwable:getCause	()Ljava/lang/Throwable;
    //   620: astore 4
    //   622: aload 4
    //   624: ifnull +6 -> 630
    //   627: aload 4
    //   629: athrow
    //   630: aload_3
    //   631: athrow
    //   632: iconst_4
    //   633: sipush 413
    //   636: sipush 30253
    //   639: invokestatic 61	o/O:ˋ	(IIC)Ljava/lang/Object;
    //   642: checkcast 63	java/lang/Class
    //   645: ldc -98
    //   647: aconst_null
    //   648: invokevirtual 86	java/lang/Class:getMethod	(Ljava/lang/String;[Ljava/lang/Class;)Ljava/lang/reflect/Method;
    //   651: aload 4
    //   653: aconst_null
    //   654: invokevirtual 92	java/lang/reflect/Method:invoke	(Ljava/lang/Object;[Ljava/lang/Object;)Ljava/lang/Object;
    //   657: checkcast 96	java/lang/String
    //   660: astore 4
    //   662: aload_3
    //   663: aload 4
    //   665: invokeinterface 161 2 0
    //   670: new 12	o/LR$ˊ
    //   673: dup
    //   674: aload_0
    //   675: aload_0
    //   676: invokevirtual 113	o/LR:ˏॱ	()Landroid/content/Context;
    //   679: invokespecial 162	o/LR$ˊ:<init>	(Lo/LR;Landroid/content/Context;)V
    //   682: checkcast 118	o/Cx
    //   685: invokeinterface 123 2 0
    //   690: goto -527 -> 163
    // Local variable table:
    //   start	length	slot	name	signature
    //   0	693	0	this	LR
    //   166	299	1	i	int
    //   9	12	2	j	int
    //   52	1	3	localObject1	Object
    //   56	36	3	localObject2	Object
    //   96	1	3	localObject3	Object
    //   100	37	3	localObject4	Object
    //   144	2	3	str1	String
    //   173	48	3	str2	String
    //   302	54	3	localObject5	Object
    //   498	16	3	localObject6	Object
    //   541	1	3	localIt	It
    //   569	16	3	localObject7	Object
    //   615	48	3	localObject8	Object
    //   61	603	4	localObject9	Object
    // Exception table:
    //   from	to	target	type
    //   73	97	56	finally
    //   117	145	100	finally
    //   190	218	173	finally
    //   515	542	498	finally
    //   586	612	569	finally
    //   632	662	615	finally
  }
  
  private final void ʻˋ()
  {
    break label94;
    ((aH)localObject1).setAdapter((RecyclerView.ˊ)localObject2);
    ((LG)this.ˏ).ˎ.setEmptyView((View)((LG)this.ˏ).ˊ);
    Object localObject1 = new ᔄ(ˏॱ(), 1);
    Object localObject2 = ˏॱ();
    label65:
    int i;
    if (localObject2 == null)
    {
      break label71;
      i = 52;
      break label240;
      label71:
      i = 58;
      break label97;
      vq.ˊ(ˎ(0, 49633, 13).intern());
      break label140;
      label94:
      break label271;
      switch (i)
      {
      default: 
        break;
        i = 1;
        break;
      case 58: 
        label97:
        break;
        for (;;)
        {
          i = 0;
          break label371;
          label140:
          i = ʹ + 37;
          ʻ = i % 128;
          if (i % 2 != 0) {
            break;
          }
        }
      }
    }
    else
    {
      for (;;)
      {
        break label458;
        label170:
        ((ᔄ)localObject1).ॱ((Drawable)localObject2);
        break label217;
        i = 69;
        break;
        label184:
        continue;
        label187:
        break label449;
        i = ʹ + 25;
        ʻ = i % 128;
        if (i % 2 == 0)
        {
          break label220;
          label217:
          break label542;
        }
      }
    }
    for (;;)
    {
      try
      {
        label220:
        i = Lt.iF.recycler_item_divider;
      }
      catch (Exception localException1)
      {
        label240:
        label271:
        label371:
        throw localException1;
      }
      try
      {
        localObject2 = ᔆ.ˎ((Context)localObject2, i);
        if (localObject2 != null) {
          break label170;
        }
      }
      catch (Exception localException2)
      {
        throw localException2;
      }
      switch (i)
      {
      }
      break;
      this.ˎ = new LC();
      localObject1 = ((LG)this.ˏ).ˎ;
      vq.ˋ(localObject1, ˎ(81, '侬', 21).intern());
      ((aH)localObject1).setLayoutManager((RecyclerView.LayoutManager)new LinearLayoutManager(ˏॱ()));
      localObject1 = ((LG)this.ˏ).ˎ;
      vq.ˋ(localObject1, ˎ(81, '侬', 21).intern());
      localObject2 = this.ˎ;
      if (localObject2 == null) {
        break label65;
      }
      break label507;
      switch (i)
      {
      default: 
        break label504;
        vq.ˊ(ˎ(102, '\000', 16).intern());
        break label498;
        i = ʹ + 93;
        ʻ = i % 128;
        if (i % 2 != 0) {
          break label187;
        }
        break;
      case 1: 
        break;
        break label542;
        ((LG)this.ˏ).ˎ.ˏ((RecyclerView.ˎ)localException2);
        aH localAH = ((LG)this.ˏ).ˎ;
        localObject2 = this.ˊ;
        if (localObject2 == null) {
          continue;
        }
        localAH.ॱ((RecyclerView.aUx)localObject2);
        return;
      case 0: 
        label449:
        label458:
        label498:
        label504:
        break;
      }
      label507:
      i = 13;
    }
    label542:
    for (;;)
    {
      i = ʹ;
      i += 31;
      ʻ = i % 128;
      if (i % 2 != 0) {
        break label184;
      }
      break;
    }
  }
  
  static void ʼˊ()
  {
    ʼ = -1354366837934841365L;
    ʽ = new char[] { -15988, -8123, -32175, -23482, 17960, 26628, 2594, 11496, -12584, -3886, -27973, -19299, 22167, -4106, -12800, -21455, -30176, 26718, 18011, 9342, 664, -8019, -8523, -17201, -25863, 30920, 22303, 13608, 4900, -3769, -20649, -29344, 27543, 18854, 10160, 97, 8601, 17329, 26034, -30846, -22032, -13337, -4839, 3851, 12599, 21340, 30064, -26774, -18296, -9486, -896, 7912, 16591, 25300, -31696, -23037, -14328, -5516, 3163, 11853, 20385, 29069, -27754, -18953, -10274, -1576, 6961, 15679, 24350, -32413, -23704, -15032, -6434, 25424, 17084, 8329, 1684, -6924, -13606, -22306, -29146, 20417, 28165, 3091, 10755, -14236, -6574, -31680, -23898, 16602, 32384, 7396, 15059, -10035, -2255, -27387, -19675, 20853, 3908, 11614, -13425, -5722, 109, 8612, 17315, 26037, -30753, -22018, -13338, -4856, 3860, 12586, 21341, 30061, -26783, -18303, -9537, -841, 101, 8605, 17331, 26031, -30760, 18876, 26744, 2670, 11390, -12775, -8145, -32195, -23333, 109, 8617, 17343, 26031, -30776, -22018, -13332, -4854, 3958, 12588, 21320, 30079, -26783, -18275, -9559, -887, 7897, 16616, 25330, -31692, -22991, -14281, -5562, 3172, 110, 8606, 17338, 26029, -30836, -22028, -13341, -4861, 3894, 12588, 21338, 30009, -26778, -18294, -9478, -858, 7889, 16616, 25330, -31663, -23000, -14296, -5614, 3187, 11879, 20381, 29171, -27737, -19007, -10253, -1562, 6997, 15636, 24370, -32442, -23740, -15060, -6523, 2189, 10979, 19674, 28375, -28420, -19947, -11190, -2528, 6236, 14915, 23669, 32137, -24683, -15873, -7203, 1476, 10214, 18708, 27422, -29382, -20662, -11952, -3270, 5296, 13964, 22707, 31397, -25383, -16678, -7960, 543, 9251, 17923, 26702, -30100, -21398, -12904, -4176, 4528, 13270, 115, 8584, 17316, 26030, -30784, -22021, -13362, -4860, 3883, 12599, 21323, 30071, -26783, -18275 };
  }
  
  /* Error */
  private final void ʼˋ()
  {
    // Byte code:
    //   0: goto +127 -> 127
    //   3: aload_0
    //   4: getfield 207	o/LR:ˎ	Lo/LC;
    //   7: astore_2
    //   8: aload_2
    //   9: ifnonnull +6 -> 15
    //   12: goto +183 -> 195
    //   15: aload_2
    //   16: astore_3
    //   17: goto +195 -> 212
    //   20: iconst_1
    //   21: istore_1
    //   22: goto +31 -> 53
    //   25: astore_2
    //   26: aload_2
    //   27: athrow
    //   28: aload_0
    //   29: getfield 207	o/LR:ˎ	Lo/LC;
    //   32: astore 4
    //   34: aconst_null
    //   35: arraylength
    //   36: istore_1
    //   37: aload 4
    //   39: ifnonnull +6 -> 45
    //   42: goto +80 -> 122
    //   45: goto -25 -> 20
    //   48: aload_2
    //   49: astore_3
    //   50: goto +162 -> 212
    //   53: aload 4
    //   55: astore_2
    //   56: aload 4
    //   58: astore_3
    //   59: iload_1
    //   60: tableswitch	default:+24->84, 0:+135->195, 1:+152->212
    //   84: aload 4
    //   86: astore_2
    //   87: goto +108 -> 195
    //   90: getstatic 34	o/LR:ʻ	I
    //   93: bipush 103
    //   95: iadd
    //   96: istore_1
    //   97: iload_1
    //   98: sipush 128
    //   101: irem
    //   102: putstatic 36	o/LR:ʹ	I
    //   105: iload_1
    //   106: iconst_2
    //   107: irem
    //   108: ifne +6 -> 114
    //   111: goto -83 -> 28
    //   114: goto -111 -> 3
    //   117: aload_2
    //   118: astore_3
    //   119: goto +93 -> 212
    //   122: iconst_0
    //   123: istore_1
    //   124: goto -71 -> 53
    //   127: goto -37 -> 90
    //   130: bipush 12
    //   132: istore_1
    //   133: goto +30 -> 163
    //   136: getstatic 34	o/LR:ʻ	I
    //   139: bipush 43
    //   141: iadd
    //   142: istore_1
    //   143: iload_1
    //   144: sipush 128
    //   147: irem
    //   148: putstatic 36	o/LR:ʹ	I
    //   151: iload_1
    //   152: iconst_2
    //   153: irem
    //   154: ifne +6 -> 160
    //   157: goto -27 -> 130
    //   160: bipush 61
    //   162: istore_1
    //   163: iload_1
    //   164: lookupswitch	default:+28->192, 12:+-116->48, 61:+-47->117
    //   192: goto -144 -> 48
    //   195: iconst_0
    //   196: ldc -70
    //   198: bipush 13
    //   200: invokestatic 129	o/LR:ˎ	(ICI)Ljava/lang/String;
    //   203: invokevirtual 133	java/lang/String:intern	()Ljava/lang/String;
    //   206: invokestatic 189	o/vq:ˊ	(Ljava/lang/String;)V
    //   209: goto -73 -> 136
    //   212: aload_3
    //   213: invokevirtual 474	o/LC:ʼ	()V
    //   216: return
    // Local variable table:
    //   start	length	slot	name	signature
    //   0	217	0	this	LR
    //   21	143	1	i	int
    //   7	9	2	localLC1	LC
    //   25	24	2	localException	Exception
    //   55	63	2	localObject1	Object
    //   16	197	3	localObject2	Object
    //   32	53	4	localLC2	LC
    // Exception table:
    //   from	to	target	type
    //   212	216	25	java/lang/Exception
  }
  
  /* Error */
  private static String ˎ(int paramInt1, char paramChar, int paramInt2)
  {
    // Byte code:
    //   0: goto +87 -> 87
    //   3: astore 5
    //   5: aload 5
    //   7: athrow
    //   8: iconst_0
    //   9: istore 4
    //   11: goto +93 -> 104
    //   14: iload 4
    //   16: tableswitch	default:+24->40, 0:+147->163, 1:+227->243
    //   40: goto +123 -> 163
    //   43: iconst_1
    //   44: istore 4
    //   46: goto -32 -> 14
    //   49: aload 5
    //   51: iload_3
    //   52: getstatic 471	o/LR:ʽ	[C
    //   55: iload_0
    //   56: iload_3
    //   57: isub
    //   58: caload
    //   59: i2l
    //   60: iload_3
    //   61: i2l
    //   62: getstatic 232	o/LR:ʼ	J
    //   65: lrem
    //   66: ladd
    //   67: iload_1
    //   68: i2l
    //   69: land
    //   70: l2i
    //   71: i2c
    //   72: castore
    //   73: iload_3
    //   74: bipush 55
    //   76: iadd
    //   77: istore_3
    //   78: goto +115 -> 193
    //   81: iconst_0
    //   82: istore 4
    //   84: goto -70 -> 14
    //   87: goto +176 -> 263
    //   90: aload 5
    //   92: areturn
    //   93: iload_3
    //   94: iload_2
    //   95: if_icmpge +6 -> 101
    //   98: goto -17 -> 81
    //   101: goto -58 -> 43
    //   104: iload 4
    //   106: tableswitch	default:+22->128, 0:+-57->49, 1:+100->206
    //   128: goto +78 -> 206
    //   131: astore 5
    //   133: aload 5
    //   135: athrow
    //   136: iload_0
    //   137: tableswitch	default:+23->160, 0:+-47->90, 1:+100->237
    //   160: aload 5
    //   162: areturn
    //   163: getstatic 36	o/LR:ʹ	I
    //   166: bipush 103
    //   168: iadd
    //   169: istore 4
    //   171: iload 4
    //   173: sipush 128
    //   176: irem
    //   177: putstatic 34	o/LR:ʻ	I
    //   180: iload 4
    //   182: iconst_2
    //   183: irem
    //   184: ifeq +6 -> 190
    //   187: goto -179 -> 8
    //   190: goto +67 -> 257
    //   193: goto -100 -> 93
    //   196: iconst_0
    //   197: istore_0
    //   198: goto -62 -> 136
    //   201: iconst_1
    //   202: istore_0
    //   203: goto -67 -> 136
    //   206: aload 5
    //   208: iload_3
    //   209: getstatic 471	o/LR:ʽ	[C
    //   212: iload_0
    //   213: iload_3
    //   214: iadd
    //   215: caload
    //   216: i2l
    //   217: iload_3
    //   218: i2l
    //   219: getstatic 232	o/LR:ʼ	J
    //   222: lmul
    //   223: lxor
    //   224: iload_1
    //   225: i2l
    //   226: lxor
    //   227: l2i
    //   228: i2c
    //   229: castore
    //   230: iload_3
    //   231: iconst_1
    //   232: iadd
    //   233: istore_3
    //   234: goto -41 -> 193
    //   237: aconst_null
    //   238: arraylength
    //   239: istore_0
    //   240: aload 5
    //   242: areturn
    //   243: new 96	java/lang/String
    //   246: dup
    //   247: aload 5
    //   249: invokespecial 481	java/lang/String:<init>	([C)V
    //   252: astore 5
    //   254: goto +19 -> 273
    //   257: iconst_1
    //   258: istore 4
    //   260: goto -156 -> 104
    //   263: iload_2
    //   264: newarray char
    //   266: astore 5
    //   268: iconst_0
    //   269: istore_3
    //   270: goto -177 -> 93
    //   273: getstatic 36	o/LR:ʹ	I
    //   276: bipush 103
    //   278: iadd
    //   279: istore_0
    //   280: iload_0
    //   281: sipush 128
    //   284: irem
    //   285: putstatic 34	o/LR:ʻ	I
    //   288: iload_0
    //   289: iconst_2
    //   290: irem
    //   291: ifeq +6 -> 297
    //   294: goto -93 -> 201
    //   297: goto -101 -> 196
    // Local variable table:
    //   start	length	slot	name	signature
    //   0	300	0	paramInt1	int
    //   0	300	1	paramChar	char
    //   0	300	2	paramInt2	int
    //   51	219	3	i	int
    //   9	250	4	j	int
    //   3	88	5	localException1	Exception
    //   131	117	5	localException2	Exception
    //   252	15	5	localObject	Object
    // Exception table:
    //   from	to	target	type
    //   171	180	3	java/lang/Exception
    //   163	171	131	java/lang/Exception
    //   171	180	131	java/lang/Exception
  }
  
  /* Error */
  private final void ˏ(EV paramEV)
  {
    // Byte code:
    //   0: goto +88 -> 88
    //   3: astore_1
    //   4: aload_1
    //   5: athrow
    //   6: goto +381 -> 387
    //   9: iconst_1
    //   10: istore_2
    //   11: goto +7 -> 18
    //   14: aconst_null
    //   15: arraylength
    //   16: istore_2
    //   17: return
    //   18: goto +125 -> 143
    //   21: getstatic 34	o/LR:ʻ	I
    //   24: bipush 117
    //   26: iadd
    //   27: istore_2
    //   28: iload_2
    //   29: sipush 128
    //   32: irem
    //   33: putstatic 36	o/LR:ʹ	I
    //   36: iload_2
    //   37: iconst_2
    //   38: irem
    //   39: ifne +6 -> 45
    //   42: goto -28 -> 14
    //   45: return
    //   46: aload 8
    //   48: aload_1
    //   49: invokevirtual 487	o/EV:ˊ	()Ljava/util/List;
    //   52: checkcast 489	java/util/Collection
    //   55: invokevirtual 495	java/util/HashSet:addAll	(Ljava/util/Collection;)Z
    //   58: pop
    //   59: aload 8
    //   61: aload_1
    //   62: invokevirtual 497	o/EV:ॱ	()Ljava/util/List;
    //   65: checkcast 489	java/util/Collection
    //   68: invokevirtual 495	java/util/HashSet:addAll	(Ljava/util/Collection;)Z
    //   71: pop
    //   72: aload 8
    //   74: aload_1
    //   75: invokevirtual 499	o/EV:ˋ	()Ljava/util/List;
    //   78: checkcast 489	java/util/Collection
    //   81: invokevirtual 495	java/util/HashSet:addAll	(Ljava/util/Collection;)Z
    //   84: pop
    //   85: goto +106 -> 191
    //   88: new 491	java/util/HashSet
    //   91: dup
    //   92: invokespecial 500	java/util/HashSet:<init>	()V
    //   95: astore 8
    //   97: invokestatic 506	java/lang/System:currentTimeMillis	()J
    //   100: lstore_3
    //   101: aload_1
    //   102: ifnull +6 -> 108
    //   105: goto -59 -> 46
    //   108: goto +45 -> 153
    //   111: aload 8
    //   113: invokeinterface 512 1 0
    //   118: astore 9
    //   120: aload 9
    //   122: checkcast 514	o/FF
    //   125: invokevirtual 516	o/FF:ʼ	()J
    //   128: lstore 5
    //   130: lload 5
    //   132: lload_3
    //   133: lcmp
    //   134: ifle +6 -> 140
    //   137: goto +200 -> 337
    //   140: goto +270 -> 410
    //   143: iload_2
    //   144: ifeq +6 -> 150
    //   147: goto +39 -> 186
    //   150: goto +182 -> 332
    //   153: aload 8
    //   155: checkcast 518	java/lang/Iterable
    //   158: astore 8
    //   160: new 52	java/util/ArrayList
    //   163: dup
    //   164: invokespecial 53	java/util/ArrayList:<init>	()V
    //   167: checkcast 489	java/util/Collection
    //   170: astore_1
    //   171: aload 8
    //   173: invokeinterface 522 1 0
    //   178: astore 8
    //   180: goto +210 -> 390
    //   183: goto +207 -> 390
    //   186: iconst_1
    //   187: istore_2
    //   188: goto +111 -> 299
    //   191: getstatic 36	o/LR:ʹ	I
    //   194: bipush 113
    //   196: iadd
    //   197: istore_2
    //   198: iload_2
    //   199: sipush 128
    //   202: irem
    //   203: putstatic 34	o/LR:ʻ	I
    //   206: iload_2
    //   207: iconst_2
    //   208: irem
    //   209: ifeq +6 -> 215
    //   212: goto -206 -> 6
    //   215: goto +172 -> 387
    //   218: iload_2
    //   219: tableswitch	default:+21->240, 0:+68->287, 1:+24->243
    //   240: goto +3 -> 243
    //   243: aload_1
    //   244: aload 9
    //   246: invokeinterface 526 2 0
    //   251: pop
    //   252: new 528	java/lang/NullPointerException
    //   255: dup
    //   256: invokespecial 529	java/lang/NullPointerException:<init>	()V
    //   259: athrow
    //   260: getstatic 34	o/LR:ʻ	I
    //   263: bipush 111
    //   265: iadd
    //   266: istore_2
    //   267: iload_2
    //   268: sipush 128
    //   271: irem
    //   272: putstatic 36	o/LR:ʹ	I
    //   275: iload_2
    //   276: iconst_2
    //   277: irem
    //   278: ifne +6 -> 284
    //   281: goto +134 -> 415
    //   284: goto +43 -> 327
    //   287: aload_1
    //   288: aload 9
    //   290: invokeinterface 526 2 0
    //   295: pop
    //   296: goto -113 -> 183
    //   299: iload_2
    //   300: tableswitch	default:+24->324, 0:+-117->183, 1:+-40->260
    //   324: goto -64 -> 260
    //   327: iconst_0
    //   328: istore_2
    //   329: goto -111 -> 218
    //   332: iconst_0
    //   333: istore_2
    //   334: goto -35 -> 299
    //   337: iconst_0
    //   338: istore_2
    //   339: goto +84 -> 423
    //   342: iconst_0
    //   343: istore_2
    //   344: goto -201 -> 143
    //   347: aload_1
    //   348: checkcast 531	java/util/List
    //   351: checkcast 518	java/lang/Iterable
    //   354: invokestatic 536	o/uQ:ˋ	(Ljava/lang/Iterable;)Ljava/util/HashSet;
    //   357: astore_1
    //   358: aload_0
    //   359: aload_1
    //   360: checkcast 489	java/util/Collection
    //   363: invokespecial 539	o/LR:ॱ	(Ljava/util/Collection;)V
    //   366: aload_0
    //   367: getfield 55	o/LR:ᐝ	Ljava/util/ArrayList;
    //   370: invokevirtual 542	java/util/ArrayList:clear	()V
    //   373: aload_0
    //   374: aload_1
    //   375: checkcast 518	java/lang/Iterable
    //   378: invokestatic 545	o/uQ:ॱ	(Ljava/lang/Iterable;)Ljava/util/List;
    //   381: invokevirtual 548	o/LR:ˏ	(Ljava/util/List;)V
    //   384: goto -363 -> 21
    //   387: goto -234 -> 153
    //   390: aload 8
    //   392: invokeinterface 551 1 0
    //   397: istore 7
    //   399: iload 7
    //   401: ifeq +6 -> 407
    //   404: goto -293 -> 111
    //   407: goto -60 -> 347
    //   410: iconst_1
    //   411: istore_2
    //   412: goto +11 -> 423
    //   415: iconst_1
    //   416: istore_2
    //   417: goto -199 -> 218
    //   420: astore_1
    //   421: aload_1
    //   422: athrow
    //   423: iload_2
    //   424: tableswitch	default:+24->448, 0:+-415->9, 1:+-82->342
    //   448: goto -106 -> 342
    // Local variable table:
    //   start	length	slot	name	signature
    //   0	451	0	this	LR
    //   0	451	1	paramEV	EV
    //   10	414	2	i	int
    //   100	33	3	l1	long
    //   128	3	5	l2	long
    //   397	3	7	bool	boolean
    //   46	345	8	localObject1	Object
    //   118	171	9	localObject2	Object
    // Exception table:
    //   from	to	target	type
    //   97	101	3	java/lang/Exception
    //   243	252	3	java/lang/Exception
    //   111	120	420	java/lang/Exception
    //   120	130	420	java/lang/Exception
    //   390	399	420	java/lang/Exception
  }
  
  /* Error */
  private final void ॱ(java.util.Collection<FF> paramCollection)
  {
    // Byte code:
    //   0: goto +398 -> 398
    //   3: aload 4
    //   5: astore_1
    //   6: iload_2
    //   7: tableswitch	default:+21->28, 0:+383->390, 1:+120->127
    //   28: aload 4
    //   30: astore_1
    //   31: goto +96 -> 127
    //   34: aload 5
    //   36: checkcast 531	java/util/List
    //   39: invokeinterface 554 1 0
    //   44: istore_2
    //   45: aload_0
    //   46: invokevirtual 558	o/LR:ͺ	()Lo/ᴊ;
    //   49: astore_1
    //   50: aload_1
    //   51: ifnonnull +6 -> 57
    //   54: goto +283 -> 337
    //   57: goto +217 -> 274
    //   60: aload 4
    //   62: astore_1
    //   63: iload_2
    //   64: lookupswitch	default:+28->92, 54:+326->390, 84:+63->127
    //   92: aload 4
    //   94: astore_1
    //   95: goto +32 -> 127
    //   98: iload_2
    //   99: lookupswitch	default:+25->124, 35:+-65->34, 94:+205->304
    //   124: goto +180 -> 304
    //   127: getstatic 34	o/LR:ʻ	I
    //   130: bipush 87
    //   132: iadd
    //   133: istore_2
    //   134: iload_2
    //   135: sipush 128
    //   138: irem
    //   139: putstatic 36	o/LR:ʹ	I
    //   142: iload_2
    //   143: iconst_2
    //   144: irem
    //   145: ifne +6 -> 151
    //   148: goto +209 -> 357
    //   151: goto +40 -> 191
    //   154: astore_1
    //   155: aload_1
    //   156: athrow
    //   157: goto +215 -> 372
    //   160: aload_1
    //   161: checkcast 518	java/lang/Iterable
    //   164: astore_1
    //   165: new 52	java/util/ArrayList
    //   168: dup
    //   169: invokespecial 53	java/util/ArrayList:<init>	()V
    //   172: checkcast 489	java/util/Collection
    //   175: astore 5
    //   177: aload_1
    //   178: invokeinterface 522 1 0
    //   183: astore 6
    //   185: goto +98 -> 283
    //   188: astore_1
    //   189: aload_1
    //   190: athrow
    //   191: aload 5
    //   193: aload_1
    //   194: invokeinterface 526 2 0
    //   199: pop
    //   200: goto +190 -> 390
    //   203: aload 6
    //   205: invokeinterface 512 1 0
    //   210: astore 4
    //   212: aload 4
    //   214: checkcast 514	o/FF
    //   217: astore_1
    //   218: aload_1
    //   219: invokevirtual 560	o/FF:ॱˊ	()Z
    //   222: aload_1
    //   223: invokevirtual 563	o/FF:ˊॱ	()Z
    //   226: ixor
    //   227: ifeq +6 -> 233
    //   230: goto +101 -> 331
    //   233: goto +53 -> 286
    //   236: iconst_0
    //   237: istore_2
    //   238: goto -235 -> 3
    //   241: aload 6
    //   243: invokeinterface 512 1 0
    //   248: astore 4
    //   250: aload 4
    //   252: checkcast 514	o/FF
    //   255: astore_1
    //   256: aload_1
    //   257: invokevirtual 560	o/FF:ॱˊ	()Z
    //   260: aload_1
    //   261: invokevirtual 563	o/FF:ˊॱ	()Z
    //   264: ior
    //   265: ifeq +6 -> 271
    //   268: goto +125 -> 393
    //   271: goto -35 -> 236
    //   274: aload_1
    //   275: checkcast 565	o/Lu
    //   278: iload_2
    //   279: invokevirtual 567	o/Lu:ˋ	(I)V
    //   282: return
    //   283: goto +89 -> 372
    //   286: bipush 54
    //   288: istore_2
    //   289: goto -229 -> 60
    //   292: bipush 35
    //   294: istore_2
    //   295: goto -197 -> 98
    //   298: bipush 94
    //   300: istore_2
    //   301: goto -203 -> 98
    //   304: getstatic 36	o/LR:ʹ	I
    //   307: bipush 7
    //   309: iadd
    //   310: istore_2
    //   311: iload_2
    //   312: sipush 128
    //   315: irem
    //   316: putstatic 34	o/LR:ʻ	I
    //   319: iload_2
    //   320: iconst_2
    //   321: irem
    //   322: ifeq +6 -> 328
    //   325: goto -122 -> 203
    //   328: goto -87 -> 241
    //   331: bipush 84
    //   333: istore_2
    //   334: goto -274 -> 60
    //   337: new 569	o/uH
    //   340: dup
    //   341: sipush 155
    //   344: iconst_0
    //   345: bipush 78
    //   347: invokestatic 129	o/LR:ˎ	(ICI)Ljava/lang/String;
    //   350: invokevirtual 133	java/lang/String:intern	()Ljava/lang/String;
    //   353: invokespecial 571	o/uH:<init>	(Ljava/lang/String;)V
    //   356: athrow
    //   357: aload 5
    //   359: aload_1
    //   360: invokeinterface 526 2 0
    //   365: pop
    //   366: aconst_null
    //   367: arraylength
    //   368: istore_2
    //   369: goto +21 -> 390
    //   372: aload 6
    //   374: invokeinterface 551 1 0
    //   379: istore_3
    //   380: iload_3
    //   381: ifeq +6 -> 387
    //   384: goto -86 -> 298
    //   387: goto -95 -> 292
    //   390: goto -233 -> 157
    //   393: iconst_1
    //   394: istore_2
    //   395: goto -392 -> 3
    //   398: goto -238 -> 160
    // Local variable table:
    //   start	length	slot	name	signature
    //   0	401	0	this	LR
    //   0	401	1	paramCollection	java.util.Collection<FF>
    //   6	389	2	i	int
    //   379	2	3	bool	boolean
    //   3	248	4	localObject	Object
    //   34	324	5	localCollection	java.util.Collection
    //   183	190	6	localIterator	java.util.Iterator
    // Exception table:
    //   from	to	target	type
    //   191	200	154	java/lang/Exception
    //   372	380	188	java/lang/Exception
  }
  
  public void ʼ()
  {
    break label99;
    int i = 1;
    break label72;
    label8:
    i = 0;
    break label72;
    try
    {
      zp localZp = zp.ॱ();
      localZp.ॱ(this);
      super.ʼ();
      return;
    }
    catch (Exception localException)
    {
      label27:
      throw localException;
    }
    zp.ॱ().ॱ(this);
    super.ʼ();
    i = null.length;
    return;
    label72:
    label99:
    for (;;)
    {
      i = ʻ + 111;
      ʹ = i % 128;
      if (i % 2 == 0) {
        break label8;
      }
      break;
      switch (i)
      {
      }
      break label27;
    }
  }
  
  /* Error */
  public void ˈ()
  {
    // Byte code:
    //   0: goto +67 -> 67
    //   3: iload_1
    //   4: tableswitch	default:+24->28, 0:+98->102, 1:+138->142
    //   28: return
    //   29: astore_2
    //   30: aload_2
    //   31: athrow
    //   32: iconst_0
    //   33: istore_1
    //   34: goto -31 -> 3
    //   37: aload_0
    //   38: invokespecial 584	o/K:ˈ	()V
    //   41: aload_0
    //   42: invokespecial 586	o/LR:ʻˊ	()V
    //   45: goto +30 -> 75
    //   48: aload_0
    //   49: invokespecial 584	o/K:ˈ	()V
    //   52: aload_0
    //   53: invokespecial 586	o/LR:ʻˊ	()V
    //   56: bipush 40
    //   58: iconst_0
    //   59: idiv
    //   60: istore_1
    //   61: goto +14 -> 75
    //   64: astore_2
    //   65: aload_2
    //   66: athrow
    //   67: goto +45 -> 112
    //   70: iconst_1
    //   71: istore_1
    //   72: goto -69 -> 3
    //   75: getstatic 36	o/LR:ʹ	I
    //   78: bipush 57
    //   80: iadd
    //   81: istore_1
    //   82: iload_1
    //   83: sipush 128
    //   86: irem
    //   87: putstatic 34	o/LR:ʻ	I
    //   90: iload_1
    //   91: iconst_2
    //   92: irem
    //   93: ifeq +6 -> 99
    //   96: goto -64 -> 32
    //   99: goto -29 -> 70
    //   102: aconst_null
    //   103: arraylength
    //   104: istore_1
    //   105: return
    //   106: bipush 86
    //   108: istore_1
    //   109: goto +34 -> 143
    //   112: getstatic 36	o/LR:ʹ	I
    //   115: bipush 11
    //   117: iadd
    //   118: istore_1
    //   119: iload_1
    //   120: sipush 128
    //   123: irem
    //   124: putstatic 34	o/LR:ʻ	I
    //   127: iload_1
    //   128: iconst_2
    //   129: irem
    //   130: ifeq +6 -> 136
    //   133: goto -27 -> 106
    //   136: bipush 63
    //   138: istore_1
    //   139: goto +4 -> 143
    //   142: return
    //   143: iload_1
    //   144: lookupswitch	default:+28->172, 63:+-107->37, 86:+-96->48
    //   172: goto -135 -> 37
    // Local variable table:
    //   start	length	slot	name	signature
    //   0	175	0	this	LR
    //   3	141	1	i	int
    //   29	2	2	localException1	Exception
    //   64	2	2	localException2	Exception
    // Exception table:
    //   from	to	target	type
    //   75	82	29	java/lang/Exception
    //   82	90	29	java/lang/Exception
    //   82	90	64	java/lang/Exception
  }
  
  /* Error */
  protected final LC ˋ()
  {
    // Byte code:
    //   0: goto +209 -> 209
    //   3: bipush 63
    //   5: iconst_0
    //   6: idiv
    //   7: istore_1
    //   8: aload_2
    //   9: areturn
    //   10: iload_1
    //   11: lookupswitch	default:+25->36, 40:+244->255, 41:+115->126
    //   36: goto +90 -> 126
    //   39: bipush 62
    //   41: istore_1
    //   42: goto +18 -> 60
    //   45: aload_0
    //   46: getfield 207	o/LR:ˎ	Lo/LC;
    //   49: astore_2
    //   50: aload_2
    //   51: ifnonnull +6 -> 57
    //   54: goto +195 -> 249
    //   57: goto +34 -> 91
    //   60: iload_1
    //   61: lookupswitch	default:+27->88, 62:+48->109, 67:+127->188
    //   88: goto +21 -> 109
    //   91: bipush 40
    //   93: istore_1
    //   94: goto -84 -> 10
    //   97: bipush 42
    //   99: istore_1
    //   100: goto +53 -> 153
    //   103: bipush 21
    //   105: istore_1
    //   106: goto +47 -> 153
    //   109: iconst_0
    //   110: ldc -70
    //   112: bipush 13
    //   114: invokestatic 129	o/LR:ˎ	(ICI)Ljava/lang/String;
    //   117: invokevirtual 133	java/lang/String:intern	()Ljava/lang/String;
    //   120: invokestatic 189	o/vq:ˊ	(Ljava/lang/String;)V
    //   123: goto +123 -> 246
    //   126: getstatic 34	o/LR:ʻ	I
    //   129: bipush 61
    //   131: iadd
    //   132: istore_1
    //   133: iload_1
    //   134: sipush 128
    //   137: irem
    //   138: putstatic 36	o/LR:ʹ	I
    //   141: iload_1
    //   142: iconst_2
    //   143: irem
    //   144: ifne +6 -> 150
    //   147: goto +93 -> 240
    //   150: goto -111 -> 39
    //   153: iload_1
    //   154: lookupswitch	default:+26->180, 21:+-151->3, 42:+84->238
    //   180: aload_2
    //   181: areturn
    //   182: astore_2
    //   183: aload_2
    //   184: athrow
    //   185: astore_2
    //   186: aload_2
    //   187: athrow
    //   188: iconst_1
    //   189: ldc -70
    //   191: bipush 115
    //   193: invokestatic 129	o/LR:ˎ	(ICI)Ljava/lang/String;
    //   196: astore_3
    //   197: aload_3
    //   198: invokevirtual 133	java/lang/String:intern	()Ljava/lang/String;
    //   201: astore_3
    //   202: aload_3
    //   203: invokestatic 189	o/vq:ˊ	(Ljava/lang/String;)V
    //   206: goto +40 -> 246
    //   209: goto -164 -> 45
    //   212: getstatic 36	o/LR:ʹ	I
    //   215: iconst_1
    //   216: iadd
    //   217: istore_1
    //   218: iload_1
    //   219: sipush 128
    //   222: irem
    //   223: putstatic 34	o/LR:ʻ	I
    //   226: iload_1
    //   227: iconst_2
    //   228: irem
    //   229: ifeq +6 -> 235
    //   232: goto -129 -> 103
    //   235: goto -138 -> 97
    //   238: aload_2
    //   239: areturn
    //   240: bipush 67
    //   242: istore_1
    //   243: goto -183 -> 60
    //   246: goto +9 -> 255
    //   249: bipush 41
    //   251: istore_1
    //   252: goto -242 -> 10
    //   255: goto -43 -> 212
    // Local variable table:
    //   start	length	slot	name	signature
    //   0	258	0	this	LR
    //   7	245	1	i	int
    //   8	173	2	localLC	LC
    //   182	2	2	localException1	Exception
    //   185	54	2	localException2	Exception
    //   196	7	3	str	String
    // Exception table:
    //   from	to	target	type
    //   188	197	182	java/lang/Exception
    //   197	202	182	java/lang/Exception
    //   202	206	182	java/lang/Exception
    //   126	133	185	java/lang/Exception
    //   133	141	185	java/lang/Exception
  }
  
  /* Error */
  @zA
  public final void ˋ(LP paramLP)
  {
    // Byte code:
    //   0: goto +74 -> 74
    //   3: getstatic 36	o/LR:ʹ	I
    //   6: bipush 123
    //   8: iadd
    //   9: istore_2
    //   10: iload_2
    //   11: sipush 128
    //   14: irem
    //   15: putstatic 34	o/LR:ʻ	I
    //   18: iload_2
    //   19: iconst_2
    //   20: irem
    //   21: ifeq +6 -> 27
    //   24: goto +53 -> 77
    //   27: aload_1
    //   28: bipush 118
    //   30: iconst_0
    //   31: iconst_5
    //   32: invokestatic 129	o/LR:ˎ	(ICI)Ljava/lang/String;
    //   35: invokevirtual 133	java/lang/String:intern	()Ljava/lang/String;
    //   38: invokestatic 591	o/vq:ˎ	(Ljava/lang/Object;Ljava/lang/String;)V
    //   41: aload_0
    //   42: invokespecial 593	o/LR:ʼˋ	()V
    //   45: goto +6 -> 51
    //   48: astore_1
    //   49: aload_1
    //   50: athrow
    //   51: getstatic 36	o/LR:ʹ	I
    //   54: bipush 113
    //   56: iadd
    //   57: istore_2
    //   58: iload_2
    //   59: sipush 128
    //   62: irem
    //   63: putstatic 34	o/LR:ʻ	I
    //   66: iload_2
    //   67: iconst_2
    //   68: irem
    //   69: ifeq +4 -> 73
    //   72: return
    //   73: return
    //   74: goto -71 -> 3
    //   77: goto -50 -> 27
    //   80: astore_1
    //   81: aload_1
    //   82: athrow
    // Local variable table:
    //   start	length	slot	name	signature
    //   0	83	0	this	LR
    //   0	83	1	paramLP	LP
    //   9	60	2	i	int
    // Exception table:
    //   from	to	target	type
    //   51	58	48	java/lang/Exception
    //   58	66	48	java/lang/Exception
    //   58	66	80	java/lang/Exception
  }
  
  /* Error */
  public void ˎ(Bundle paramBundle)
  {
    // Byte code:
    //   0: goto +64 -> 64
    //   3: aload_0
    //   4: aload_1
    //   5: invokespecial 597	o/K:ˎ	(Landroid/os/Bundle;)V
    //   8: aload_0
    //   9: invokespecial 599	o/LR:ʻˋ	()V
    //   12: bipush 75
    //   14: iconst_0
    //   15: idiv
    //   16: istore_2
    //   17: goto +87 -> 104
    //   20: iload_2
    //   21: tableswitch	default:+23->44, 0:+-18->3, 1:+26->47
    //   44: goto -41 -> 3
    //   47: aload_0
    //   48: aload_1
    //   49: invokespecial 597	o/K:ˎ	(Landroid/os/Bundle;)V
    //   52: aload_0
    //   53: invokespecial 599	o/LR:ʻˋ	()V
    //   56: goto +48 -> 104
    //   59: iconst_1
    //   60: istore_2
    //   61: goto -41 -> 20
    //   64: goto +6 -> 70
    //   67: astore_1
    //   68: aload_1
    //   69: athrow
    //   70: getstatic 34	o/LR:ʻ	I
    //   73: iconst_5
    //   74: iadd
    //   75: istore_2
    //   76: iload_2
    //   77: sipush 128
    //   80: irem
    //   81: putstatic 36	o/LR:ʹ	I
    //   84: iload_2
    //   85: iconst_2
    //   86: irem
    //   87: ifne +6 -> 93
    //   90: goto +6 -> 96
    //   93: goto -34 -> 59
    //   96: iconst_0
    //   97: istore_2
    //   98: goto -78 -> 20
    //   101: astore_1
    //   102: aload_1
    //   103: athrow
    //   104: getstatic 34	o/LR:ʻ	I
    //   107: bipush 81
    //   109: iadd
    //   110: istore_2
    //   111: iload_2
    //   112: sipush 128
    //   115: irem
    //   116: putstatic 36	o/LR:ʹ	I
    //   119: iload_2
    //   120: iconst_2
    //   121: irem
    //   122: ifne +4 -> 126
    //   125: return
    //   126: return
    // Local variable table:
    //   start	length	slot	name	signature
    //   0	127	0	this	LR
    //   0	127	1	paramBundle	Bundle
    //   16	106	2	i	int
    // Exception table:
    //   from	to	target	type
    //   76	84	67	java/lang/Exception
    //   70	76	101	java/lang/Exception
    //   76	84	101	java/lang/Exception
  }
  
  /* Error */
  public View ˏ(android.view.LayoutInflater paramLayoutInflater, android.view.ViewGroup paramViewGroup, Bundle paramBundle)
  {
    // Byte code:
    //   0: goto +86 -> 86
    //   3: bipush 73
    //   5: sipush 25401
    //   8: bipush 8
    //   10: invokestatic 129	o/LR:ˎ	(ICI)Ljava/lang/String;
    //   13: astore 5
    //   15: aload 5
    //   17: invokevirtual 133	java/lang/String:intern	()Ljava/lang/String;
    //   20: astore 5
    //   22: aload_1
    //   23: aload 5
    //   25: invokestatic 591	o/vq:ˎ	(Ljava/lang/Object;Ljava/lang/String;)V
    //   28: invokestatic 578	o/zp:ॱ	()Lo/zp;
    //   31: aload_0
    //   32: invokevirtual 602	o/zp:ˋ	(Ljava/lang/Object;)V
    //   35: aload_0
    //   36: aload_1
    //   37: aload_2
    //   38: aload_3
    //   39: invokespecial 604	o/K:ˏ	(Landroid/view/LayoutInflater;Landroid/view/ViewGroup;Landroid/os/Bundle;)Landroid/view/View;
    //   42: astore_1
    //   43: goto +52 -> 95
    //   46: aload_1
    //   47: areturn
    //   48: iconst_0
    //   49: istore 4
    //   51: goto +6 -> 57
    //   54: goto -51 -> 3
    //   57: iload 4
    //   59: tableswitch	default:+21->80, 0:+96->155, 1:+-13->46
    //   80: goto +75 -> 155
    //   83: astore_1
    //   84: aload_1
    //   85: athrow
    //   86: goto +39 -> 125
    //   89: iconst_1
    //   90: istore 4
    //   92: goto -35 -> 57
    //   95: getstatic 34	o/LR:ʻ	I
    //   98: bipush 109
    //   100: iadd
    //   101: istore 4
    //   103: iload 4
    //   105: sipush 128
    //   108: irem
    //   109: putstatic 36	o/LR:ʹ	I
    //   112: iload 4
    //   114: iconst_2
    //   115: irem
    //   116: ifne +6 -> 122
    //   119: goto -71 -> 48
    //   122: goto -33 -> 89
    //   125: getstatic 34	o/LR:ʻ	I
    //   128: bipush 19
    //   130: iadd
    //   131: istore 4
    //   133: iload 4
    //   135: sipush 128
    //   138: irem
    //   139: putstatic 36	o/LR:ʹ	I
    //   142: iload 4
    //   144: iconst_2
    //   145: irem
    //   146: ifne +6 -> 152
    //   149: goto -95 -> 54
    //   152: goto -149 -> 3
    //   155: new 528	java/lang/NullPointerException
    //   158: dup
    //   159: invokespecial 529	java/lang/NullPointerException:<init>	()V
    //   162: athrow
    //   163: astore_1
    //   164: aload_1
    //   165: athrow
    // Local variable table:
    //   start	length	slot	name	signature
    //   0	166	0	this	LR
    //   0	166	1	paramLayoutInflater	android.view.LayoutInflater
    //   0	166	2	paramViewGroup	android.view.ViewGroup
    //   0	166	3	paramBundle	Bundle
    //   49	97	4	i	int
    //   13	11	5	str	String
    // Exception table:
    //   from	to	target	type
    //   3	15	83	java/lang/Exception
    //   15	22	83	java/lang/Exception
    //   22	43	83	java/lang/Exception
    //   15	22	163	java/lang/Exception
    //   95	103	163	java/lang/Exception
    //   103	112	163	java/lang/Exception
  }
  
  public final void ˏ(RecyclerView.aUx paramAUx)
  {
    int i = ʹ + 5;
    ʻ = i % 128;
    if (i % 2 == 0) {
      break label55;
    }
    for (;;)
    {
      i = ʹ + 13;
      ʻ = i % 128;
      if (i % 2 != 0) {
        return;
      }
      return;
      label55:
      vq.ˎ(paramAUx, ˎ(233, '\000', 14).intern());
      this.ˊ = paramAUx;
    }
  }
  
  public abstract void ˏ(List<FF> paramList);
  
  public void ॱ(Bundle paramBundle)
  {
    break label194;
    int i = 1;
    break label75;
    label8:
    i = 0;
    break label75;
    for (;;)
    {
      switch (i)
      {
      default: 
        break;
        break label153;
        for (;;)
        {
          i = 0;
          break;
          super.ॱ(paramBundle);
          paramBundle = ʽ();
          if (paramBundle != null) {
            break label70;
          }
        }
      case 0: 
        label39:
        label47:
        break;
        label70:
        i = 1;
      }
    }
    switch (i)
    {
    default: 
      label75:
      return;
    }
    label153:
    label194:
    label201:
    for (;;)
    {
      i = ʻ + 105;
      ʹ = i % 128;
      if (i % 2 == 0) {
        break label8;
      }
      break;
      return;
      i = ʹ + 97;
      ʻ = i % 128;
      if (i % 2 != 0) {
        break label39;
      }
      paramBundle = paramBundle.getString(ˎ(13, 61331, 22).intern());
      vq.ˋ(paramBundle, ˎ(35, '\000', 38).intern());
      this.ॱ = paramBundle;
      break label201;
      break label47;
      i = null.length;
      return;
    }
  }
  
  protected final ArrayList<FF> ﹳ()
  {
    label51:
    do
    {
      i = 31;
      break label134;
      i = ʹ + 7;
      ʻ = i % 128;
      if (i % 2 != 0) {
        break label115;
      }
      break;
      localArrayList = this.ᐝ;
      break label51;
      i = null.length;
      return localArrayList;
      return localArrayList;
      i = ʻ + 41;
      ʹ = i % 128;
    } while (i % 2 == 0);
    int i = 0;
    break label134;
    label115:
    for (i = 76;; i = 60) {
      switch (i)
      {
      case 76: 
      default: 
        break label121;
      }
    }
    label121:
    ArrayList localArrayList = this.ᐝ;
    throw new NullPointerException();
    label134:
    switch (i)
    {
    }
    return localArrayList;
  }
  
  public static final class If
  {
    private If() {}
  }
  
  public static final class if
    extends Ik<EV>
  {
    private static int ˊ = 0;
    private static int ˎ = 1;
    private static char[] ˏ = { 114, -14706, -29275, 21684, 7104, -7453, -24106, 26386, 11268, -2796, -17805, 17221, 2135, -11855, -17490, 32106, 13948, -4244, -24565, 22845, 4655, -13367, -29515, 17903, 32395, 14268, -5982, -23970, 23402, 7242, -10982, -29141, 18225, 30967, 12786, -5388, -23675, 25767 };
    private static long ॱ = -7138396053081372949L;
    
    if(Context paramContext)
    {
      super();
    }
    
    private static String ˊ(int paramInt1, char paramChar, int paramInt2)
    {
      break label164;
      break label69;
      label6:
      int i;
      try
      {
        i = ˎ + 85;
        ˊ = i % 128;
        if (i % 2 != 0) {
          break label202;
        }
      }
      catch (Exception localException)
      {
        label33:
        Object localObject;
        throw localException;
      }
      localObject[i] = ((char)(int)(ˏ[(paramInt1 + i)] ^ i * ॱ ^ paramChar));
      i += 1;
      label69:
      if (i >= paramInt2) {
        break label157;
      }
      char[] arrayOfChar;
      label157:
      label164:
      label167:
      label199:
      label202:
      for (;;)
      {
        arrayOfChar = new char[paramInt2];
        i = 0;
        int j = ˊ + 83;
        ˎ = j % 128;
        if (j % 2 != 0)
        {
          break;
          j = ˊ + 91;
          ˎ = j % 128;
          if (j % 2 == 0) {
            break label199;
          }
          break label33;
          j = 38;
          break label167;
        }
        break;
        j = 50;
        break label167;
        break label6;
        switch (j)
        {
        case 38: 
        default: 
          break label205;
          break label33;
        }
      }
      label205:
      return new String(arrayOfChar);
    }
    
    public void ˊ(Fg paramFg)
    {
      break label44;
      int i = 58;
      for (;;)
      {
        super.ˊ(paramFg);
        LR.ˋ(this.ˋ, null);
        throw new NullPointerException();
        super.ˊ(paramFg);
        LR.ˋ(this.ˋ, null);
        return;
        for (;;)
        {
          label44:
          i = 60;
          break label80;
          i = ˊ + 59;
          ˎ = i % 128;
          if (i % 2 == 0) {
            break;
          }
        }
        label80:
        switch (i)
        {
        }
      }
    }
    
    public void ˏ()
    {
      break label156;
      Object localObject;
      for (;;)
      {
        i = 65;
        break label162;
        return;
        localObject = LR.ˎ(this.ˋ).ˊ;
        vq.ˋ(localObject, ˊ(14, 48067, 24).intern());
        ((TextView)localObject).setVisibility(0);
        i = ˎ + 93;
        ˊ = i % 128;
        if (i % 2 != 0) {
          break;
        }
      }
      return;
      label148:
      label156:
      for (;;)
      {
        super.ˏ();
        localObject = LR.ˎ(this.ˋ);
        vq.ˋ(localObject, ˊ(6, 41403, 8).intern());
        ((LG)localObject).ˊ(false);
        if (this.ˋ.ﹳ().isEmpty()) {
          break label213;
        }
        break label148;
        i = ˊ + 1;
        ˎ = i % 128;
        if (i % 2 != 0)
        {
          break;
          i = 0;
          break label189;
        }
        break;
      }
      int i = 54;
      label162:
      switch (i)
      {
      }
      return;
      for (;;)
      {
        label189:
        switch (i)
        {
        }
        return;
        label213:
        i = 1;
      }
    }
    
    protected void ॱ(EV paramEV)
    {
      for (;;)
      {
        int i = ˎ + 13;
        ˊ = i % 128;
        if (i % 2 != 0) {
          break;
        }
        for (;;)
        {
          i = ˊ + 25;
          ˎ = i % 128;
          if (i % 2 == 0) {
            break;
          }
          return;
          vq.ˎ(paramEV, ˊ(0, '\000', 6).intern());
          LR.ˋ(this.ˋ, paramEV);
        }
      }
    }
  }
  
  public static final class ˊ
    extends Ik<EV>
  {
    private static int ʼ = 0;
    private static char ˋ = '⊤';
    private static char ˎ = '༿';
    private static char ˏ = 'Ⲭ';
    private static char ॱ = 35898;
    private static int ॱॱ = 1;
    
    ˊ(Context paramContext)
    {
      super();
    }
    
    private static String ˎ(char[] paramArrayOfChar)
    {
      break label68;
      int i = 1;
      break label114;
      int j;
      label35:
      label38:
      char[] arrayOfChar1;
      char[] arrayOfChar2;
      for (;;)
      {
        j = ॱॱ + 123;
        ʼ = j % 128;
        if (j % 2 != 0) {
          break;
        }
        break;
        break label224;
        arrayOfChar1 = new char[paramArrayOfChar.length];
        i = 0;
        arrayOfChar2 = new char[2];
        break label224;
        arrayOfChar1 = new char[paramArrayOfChar.length];
        i = 0;
        arrayOfChar2 = new char[2];
        break label224;
        label68:
        break label139;
        label71:
        switch (j)
        {
        }
      }
      for (;;)
      {
        j = 1;
        break label71;
        label114:
        label139:
        char[] arrayOfChar3;
        label224:
        do
        {
          j = 0;
          break label71;
          for (;;)
          {
            i = 0;
            switch (i)
            {
            }
            break label38;
            i = ॱॱ + 23;
            ʼ = i % 128;
            if (i % 2 != 0) {
              break;
            }
          }
          arrayOfChar2[0] = arrayOfChar3[i];
          arrayOfChar2[1] = arrayOfChar3[(i + 1)];
          oP.ˏ(arrayOfChar2, ॱ, ˎ, ˏ, ˋ);
          arrayOfChar1[i] = arrayOfChar2[0];
          arrayOfChar1[(i + 1)] = arrayOfChar2[1];
          i += 2;
          break label35;
          arrayOfChar3 = paramArrayOfChar;
        } while (i < arrayOfChar3.length);
      }
      return new String(arrayOfChar1, 1, arrayOfChar1[0]);
    }
    
    public void ˊ(Fg paramFg)
    {
      break label15;
      label3:
      int i = 48;
      for (;;)
      {
        i = 0;
        break label77;
        return;
        label15:
        break label154;
        super.ˊ(paramFg);
        LR.ˋ(this.ˊ, null);
        i = 31 / 0;
        switch (i)
        {
        case 99: 
        default: 
          label39:
          break;
          for (;;)
          {
            i = 99;
            break label39;
            switch (i)
            {
            case 1: 
            default: 
              break;
            case 0: 
              label77:
              super.ˊ(paramFg);
              LR.ˋ(this.ˊ, null);
              i = ॱॱ + 17;
              ʼ = i % 128;
              if (i % 2 != 0) {
                break label3;
              }
            }
          }
        }
        i = 72 / 0;
        return;
        label154:
        do
        {
          i = 1;
          break;
          i = ʼ + 43;
          ॱॱ = i % 128;
        } while (i % 2 == 0);
      }
    }
    
    protected void ˋ(EV paramEV)
    {
      break label123;
      label70:
      for (;;)
      {
        vq.ˎ(paramEV, ˎ(new char[] { 4837, -27599, 784, -10081, 10942, -29587, 8819, -20636 }).intern());
        LR.ˋ(this.ˊ, paramEV);
        break;
      }
      label123:
      for (;;)
      {
        int i = ʼ + 99;
        ॱॱ = i % 128;
        if (i % 2 == 0) {
          break label70;
        }
        break;
        i = ॱॱ + 25;
        ʼ = i % 128;
        if (i % 2 != 0) {
          return;
        }
        return;
      }
    }
    
    /* Error */
    public void ˏ()
    {
      // Byte code:
      //   0: goto +370 -> 370
      //   3: bipush 72
      //   5: istore_1
      //   6: goto +329 -> 335
      //   9: aload_0
      //   10: getfield 39	o/LR$ˊ:ˊ	Lo/LR;
      //   13: invokestatic 85	o/LR:ˎ	(Lo/LR;)Lo/LG;
      //   16: getfield 90	o/LG:ˊ	Landroid/widget/TextView;
      //   19: astore_3
      //   20: aload_3
      //   21: bipush 26
      //   23: newarray char
      //   25: dup
      //   26: iconst_0
      //   27: ldc 91
      //   29: castore
      //   30: dup
      //   31: iconst_1
      //   32: ldc 92
      //   34: castore
      //   35: dup
      //   36: iconst_2
      //   37: ldc 93
      //   39: castore
      //   40: dup
      //   41: iconst_3
      //   42: ldc 94
      //   44: castore
      //   45: dup
      //   46: iconst_4
      //   47: ldc 95
      //   49: castore
      //   50: dup
      //   51: iconst_5
      //   52: ldc 96
      //   54: castore
      //   55: dup
      //   56: bipush 6
      //   58: ldc 97
      //   60: castore
      //   61: dup
      //   62: bipush 7
      //   64: ldc 98
      //   66: castore
      //   67: dup
      //   68: bipush 8
      //   70: ldc 99
      //   72: castore
      //   73: dup
      //   74: bipush 9
      //   76: ldc 100
      //   78: castore
      //   79: dup
      //   80: bipush 10
      //   82: ldc 101
      //   84: castore
      //   85: dup
      //   86: bipush 11
      //   88: ldc 102
      //   90: castore
      //   91: dup
      //   92: bipush 12
      //   94: ldc 103
      //   96: castore
      //   97: dup
      //   98: bipush 13
      //   100: ldc 104
      //   102: castore
      //   103: dup
      //   104: bipush 14
      //   106: ldc 105
      //   108: castore
      //   109: dup
      //   110: bipush 15
      //   112: ldc 106
      //   114: castore
      //   115: dup
      //   116: bipush 16
      //   118: ldc 107
      //   120: castore
      //   121: dup
      //   122: bipush 17
      //   124: ldc 108
      //   126: castore
      //   127: dup
      //   128: bipush 18
      //   130: ldc 109
      //   132: castore
      //   133: dup
      //   134: bipush 19
      //   136: ldc 110
      //   138: castore
      //   139: dup
      //   140: bipush 20
      //   142: ldc 111
      //   144: castore
      //   145: dup
      //   146: bipush 21
      //   148: ldc 112
      //   150: castore
      //   151: dup
      //   152: bipush 22
      //   154: ldc 113
      //   156: castore
      //   157: dup
      //   158: bipush 23
      //   160: ldc 114
      //   162: castore
      //   163: dup
      //   164: bipush 24
      //   166: ldc 115
      //   168: castore
      //   169: dup
      //   170: bipush 25
      //   172: ldc 116
      //   174: castore
      //   175: invokestatic 71	o/LR$ˊ:ˎ	([C)Ljava/lang/String;
      //   178: invokevirtual 75	java/lang/String:intern	()Ljava/lang/String;
      //   181: invokestatic 118	o/vq:ˋ	(Ljava/lang/Object;Ljava/lang/String;)V
      //   184: aload_3
      //   185: iconst_0
      //   186: invokevirtual 124	android/widget/TextView:setVisibility	(I)V
      //   189: goto +368 -> 557
      //   192: astore_3
      //   193: aload_3
      //   194: athrow
      //   195: aload_0
      //   196: invokespecial 126	o/Ik:ˏ	()V
      //   199: aload_0
      //   200: getfield 39	o/LR$ˊ:ˊ	Lo/LR;
      //   203: astore_3
      //   204: aload_3
      //   205: invokestatic 85	o/LR:ˎ	(Lo/LR;)Lo/LG;
      //   208: astore_3
      //   209: aload_3
      //   210: bipush 10
      //   212: newarray char
      //   214: dup
      //   215: iconst_0
      //   216: ldc 127
      //   218: castore
      //   219: dup
      //   220: iconst_1
      //   221: ldc -128
      //   223: castore
      //   224: dup
      //   225: iconst_2
      //   226: ldc 93
      //   228: castore
      //   229: dup
      //   230: iconst_3
      //   231: ldc 94
      //   233: castore
      //   234: dup
      //   235: iconst_4
      //   236: ldc 95
      //   238: castore
      //   239: dup
      //   240: iconst_5
      //   241: ldc 96
      //   243: castore
      //   244: dup
      //   245: bipush 6
      //   247: ldc 97
      //   249: castore
      //   250: dup
      //   251: bipush 7
      //   253: ldc 98
      //   255: castore
      //   256: dup
      //   257: bipush 8
      //   259: ldc -127
      //   261: castore
      //   262: dup
      //   263: bipush 9
      //   265: ldc -126
      //   267: castore
      //   268: invokestatic 71	o/LR$ˊ:ˎ	([C)Ljava/lang/String;
      //   271: invokevirtual 75	java/lang/String:intern	()Ljava/lang/String;
      //   274: invokestatic 118	o/vq:ˋ	(Ljava/lang/Object;Ljava/lang/String;)V
      //   277: aload_3
      //   278: iconst_0
      //   279: invokevirtual 133	o/LG:ˊ	(Z)V
      //   282: aload_0
      //   283: getfield 39	o/LR$ˊ:ˊ	Lo/LR;
      //   286: invokevirtual 137	o/LR:ﹳ	()Ljava/util/ArrayList;
      //   289: invokevirtual 143	java/util/ArrayList:isEmpty	()Z
      //   292: istore_2
      //   293: iload_2
      //   294: ifeq +6 -> 300
      //   297: goto +263 -> 560
      //   300: iconst_0
      //   301: istore_1
      //   302: goto +269 -> 571
      //   305: getstatic 23	o/LR$ˊ:ʼ	I
      //   308: bipush 65
      //   310: iadd
      //   311: istore_1
      //   312: iload_1
      //   313: sipush 128
      //   316: irem
      //   317: putstatic 25	o/LR$ˊ:ॱॱ	I
      //   320: iload_1
      //   321: iconst_2
      //   322: irem
      //   323: ifne +6 -> 329
      //   326: goto -323 -> 3
      //   329: goto +236 -> 565
      //   332: astore_3
      //   333: aload_3
      //   334: athrow
      //   335: iload_1
      //   336: lookupswitch	default:+28->364, 72:+41->377, 93:+-327->9
      //   364: goto +13 -> 377
      //   367: goto +232 -> 599
      //   370: goto -175 -> 195
      //   373: aconst_null
      //   374: arraylength
      //   375: istore_1
      //   376: return
      //   377: aload_0
      //   378: getfield 39	o/LR$ˊ:ˊ	Lo/LR;
      //   381: invokestatic 85	o/LR:ˎ	(Lo/LR;)Lo/LG;
      //   384: getfield 90	o/LG:ˊ	Landroid/widget/TextView;
      //   387: astore_3
      //   388: aload_3
      //   389: bipush 26
      //   391: newarray char
      //   393: dup
      //   394: iconst_0
      //   395: ldc 91
      //   397: castore
      //   398: dup
      //   399: iconst_1
      //   400: ldc 92
      //   402: castore
      //   403: dup
      //   404: iconst_2
      //   405: ldc 93
      //   407: castore
      //   408: dup
      //   409: iconst_3
      //   410: ldc 94
      //   412: castore
      //   413: dup
      //   414: iconst_4
      //   415: ldc 95
      //   417: castore
      //   418: dup
      //   419: iconst_5
      //   420: ldc 96
      //   422: castore
      //   423: dup
      //   424: bipush 6
      //   426: ldc 97
      //   428: castore
      //   429: dup
      //   430: bipush 7
      //   432: ldc 98
      //   434: castore
      //   435: dup
      //   436: bipush 8
      //   438: ldc 99
      //   440: castore
      //   441: dup
      //   442: bipush 9
      //   444: ldc 100
      //   446: castore
      //   447: dup
      //   448: bipush 10
      //   450: ldc 101
      //   452: castore
      //   453: dup
      //   454: bipush 11
      //   456: ldc 102
      //   458: castore
      //   459: dup
      //   460: bipush 12
      //   462: ldc 103
      //   464: castore
      //   465: dup
      //   466: bipush 13
      //   468: ldc 104
      //   470: castore
      //   471: dup
      //   472: bipush 14
      //   474: ldc 105
      //   476: castore
      //   477: dup
      //   478: bipush 15
      //   480: ldc 106
      //   482: castore
      //   483: dup
      //   484: bipush 16
      //   486: ldc 107
      //   488: castore
      //   489: dup
      //   490: bipush 17
      //   492: ldc 108
      //   494: castore
      //   495: dup
      //   496: bipush 18
      //   498: ldc 109
      //   500: castore
      //   501: dup
      //   502: bipush 19
      //   504: ldc 110
      //   506: castore
      //   507: dup
      //   508: bipush 20
      //   510: ldc 111
      //   512: castore
      //   513: dup
      //   514: bipush 21
      //   516: ldc 112
      //   518: castore
      //   519: dup
      //   520: bipush 22
      //   522: ldc 113
      //   524: castore
      //   525: dup
      //   526: bipush 23
      //   528: ldc 114
      //   530: castore
      //   531: dup
      //   532: bipush 24
      //   534: ldc 115
      //   536: castore
      //   537: dup
      //   538: bipush 25
      //   540: ldc 116
      //   542: castore
      //   543: invokestatic 71	o/LR$ˊ:ˎ	([C)Ljava/lang/String;
      //   546: invokevirtual 75	java/lang/String:intern	()Ljava/lang/String;
      //   549: invokestatic 118	o/vq:ˋ	(Ljava/lang/Object;Ljava/lang/String;)V
      //   552: aload_3
      //   553: iconst_1
      //   554: invokevirtual 124	android/widget/TextView:setVisibility	(I)V
      //   557: goto -190 -> 367
      //   560: iconst_1
      //   561: istore_1
      //   562: goto +9 -> 571
      //   565: bipush 93
      //   567: istore_1
      //   568: goto -233 -> 335
      //   571: iload_1
      //   572: tableswitch	default:+24->596, 0:+-205->367, 1:+-267->305
      //   596: goto -229 -> 367
      //   599: getstatic 23	o/LR$ˊ:ʼ	I
      //   602: bipush 9
      //   604: iadd
      //   605: istore_1
      //   606: iload_1
      //   607: sipush 128
      //   610: irem
      //   611: putstatic 25	o/LR$ˊ:ॱॱ	I
      //   614: iload_1
      //   615: iconst_2
      //   616: irem
      //   617: ifne +6 -> 623
      //   620: goto -247 -> 373
      //   623: return
      // Local variable table:
      //   start	length	slot	name	signature
      //   0	624	0	this	ˊ
      //   5	612	1	i	int
      //   292	2	2	bool	boolean
      //   19	166	3	localTextView1	TextView
      //   192	2	3	localException1	Exception
      //   203	75	3	localObject	Object
      //   332	2	3	localException2	Exception
      //   387	166	3	localTextView2	TextView
      // Exception table:
      //   from	to	target	type
      //   199	204	192	java/lang/Exception
      //   204	209	192	java/lang/Exception
      //   209	293	192	java/lang/Exception
      //   204	209	332	java/lang/Exception
      //   305	312	332	java/lang/Exception
      //   312	320	332	java/lang/Exception
    }
  }
}
