package o;

import java.util.ArrayList;
import java.util.Iterator;
import java.util.List;

public final class LS
  extends LR
{
  private static int ʻ;
  private static int ʽ;
  public static final ˊ ˊ;
  private static long ॱ;
  
  static
  {
    for (;;)
    {
      int i = ʽ + 111;
      ʻ = i % 128;
      if (i % 2 == 0) {
        return;
      }
      return;
      ʻ = 0;
      ʽ = 1;
      ʻᐝ();
      ˊ = new ˊ(null);
    }
  }
  
  public LS() {}
  
  static void ʻᐝ()
  {
    ॱ = -4273094842019461579L;
  }
  
  /* Error */
  private static String ˋ(char[] paramArrayOfChar)
  {
    // Byte code:
    //   0: goto +77 -> 77
    //   3: iload_2
    //   4: istore_1
    //   5: goto +196 -> 201
    //   8: bipush 86
    //   10: istore_1
    //   11: goto +28 -> 39
    //   14: aload_0
    //   15: iconst_0
    //   16: caload
    //   17: istore_3
    //   18: aload_0
    //   19: arraylength
    //   20: iconst_1
    //   21: isub
    //   22: newarray char
    //   24: astore 4
    //   26: iconst_1
    //   27: istore_1
    //   28: goto +52 -> 80
    //   31: iconst_0
    //   32: istore_2
    //   33: goto +141 -> 174
    //   36: astore_0
    //   37: aload_0
    //   38: athrow
    //   39: iload_1
    //   40: lookupswitch	default:+28->68, 19:+159->199, 86:+-37->3
    //   68: goto +131 -> 199
    //   71: bipush 19
    //   73: istore_1
    //   74: goto -35 -> 39
    //   77: goto -63 -> 14
    //   80: getstatic 17	o/LS:ʽ	I
    //   83: bipush 111
    //   85: iadd
    //   86: istore_2
    //   87: iload_2
    //   88: sipush 128
    //   91: irem
    //   92: putstatic 19	o/LS:ʻ	I
    //   95: iload_2
    //   96: iconst_2
    //   97: irem
    //   98: ifeq +6 -> 104
    //   101: goto +6 -> 107
    //   104: goto +35 -> 139
    //   107: goto +32 -> 139
    //   110: getstatic 19	o/LS:ʻ	I
    //   113: istore_1
    //   114: iload_1
    //   115: bipush 29
    //   117: iadd
    //   118: istore_1
    //   119: iload_1
    //   120: sipush 128
    //   123: irem
    //   124: putstatic 17	o/LS:ʽ	I
    //   127: iload_1
    //   128: iconst_2
    //   129: irem
    //   130: ifne +6 -> 136
    //   133: goto -62 -> 71
    //   136: goto -128 -> 8
    //   139: goto +62 -> 201
    //   142: iconst_1
    //   143: istore_2
    //   144: goto +30 -> 174
    //   147: aload 4
    //   149: iload_1
    //   150: iconst_1
    //   151: isub
    //   152: aload_0
    //   153: iload_1
    //   154: caload
    //   155: iload_1
    //   156: iload_3
    //   157: imul
    //   158: ixor
    //   159: i2l
    //   160: getstatic 35	o/LS:ॱ	J
    //   163: lxor
    //   164: l2i
    //   165: i2c
    //   166: castore
    //   167: iload_1
    //   168: iconst_1
    //   169: iadd
    //   170: istore_2
    //   171: goto -61 -> 110
    //   174: iload_2
    //   175: tableswitch	default:+21->196, 0:+-28->147, 1:+38->213
    //   196: goto -49 -> 147
    //   199: iload_2
    //   200: istore_1
    //   201: iload_1
    //   202: aload_0
    //   203: arraylength
    //   204: if_icmpge +6 -> 210
    //   207: goto -176 -> 31
    //   210: goto -68 -> 142
    //   213: new 41	java/lang/String
    //   216: dup
    //   217: aload 4
    //   219: invokespecial 44	java/lang/String:<init>	([C)V
    //   222: areturn
    //   223: astore_0
    //   224: aload_0
    //   225: athrow
    // Local variable table:
    //   start	length	slot	name	signature
    //   0	226	0	paramArrayOfChar	char[]
    //   4	201	1	i	int
    //   3	197	2	j	int
    //   17	141	3	k	int
    //   24	194	4	arrayOfChar	char[]
    // Exception table:
    //   from	to	target	type
    //   87	95	36	java/lang/Exception
    //   80	87	223	java/lang/Exception
    //   87	95	223	java/lang/Exception
    //   110	114	223	java/lang/Exception
    //   119	127	223	java/lang/Exception
  }
  
  public int ˎ()
  {
    try
    {
      i = Lt.ˋ.fragment_offers_list;
      return i;
    }
    catch (Exception localException)
    {
      int j;
      throw localException;
    }
    int i = Lt.ˋ.fragment_offers_list;
    j = 74 / 0;
    return i;
    for (;;)
    {
      i = 0;
      switch (i)
      {
      }
      break;
      do
      {
        i = 1;
        break;
        i = ʽ + 85;
        ʻ = i % 128;
      } while (i % 2 != 0);
    }
  }
  
  public void ˏ(List<FF> paramList)
  {
    break label199;
    int i = 0;
    break label31;
    label8:
    FF localFF = (FF)paramList.next();
    if (!localFF.ॱॱ())
    {
      break label357;
      switch (i)
      {
      default: 
        label31:
        break;
        label59:
        break label202;
        i = ʻ + 1;
        ʽ = i % 128;
        if (i % 2 == 0) {}
        break;
      }
    }
    label158:
    label173:
    label179:
    label199:
    label202:
    label289:
    label357:
    for (i = 1;; i = 0) {
      switch (i)
      {
      case 0: 
      default: 
        break label179;
        i = ʻ + 109;
        ʽ = i % 128;
        if (i % 2 != 0)
        {
          break label8;
          ˋ().ˎ((List)ﹳ(), true);
          return;
          if (paramList.hasNext()) {
            break;
          }
        }
        break;
      case 1: 
        for (;;)
        {
          break label158;
          break;
          ﹳ().add(localFF);
          break label59;
          i = 1;
          break label31;
          for (;;)
          {
            break label289;
            break;
            i = ʻ + 51;
            ʽ = i % 128;
            if (i % 2 != 0)
            {
              break label289;
              vq.ˎ(paramList, ˋ(new char[] { 28151, 11181, -25155, 4022, -3700, 25492, -10868 }).intern());
              paramList = paramList.iterator();
              break label173;
            }
          }
          break label158;
          vq.ˎ(paramList, ˋ(new char[] { 28151, 11181, -25155, 4022, -3700, 25492, -10868 }).intern());
          paramList = paramList.iterator();
          i = 37 / 0;
        }
      }
    }
  }
  
  public static final class ˊ
  {
    private static long ˋ = 5569025535639683164L;
    private static int ˎ = 0;
    private static int ˏ = 1;
    
    private ˊ() {}
    
    private static String ˋ(char[] paramArrayOfChar)
    {
      break label126;
      int i = ˏ + 117;
      ˎ = i % 128;
      if (i % 2 == 0) {}
      for (;;)
      {
        paramArrayOfChar = oL.ˋ(ˋ, paramArrayOfChar);
        i = 4;
        for (;;)
        {
          switch (j)
          {
          default: 
            label40:
            break label129;
            label67:
            if (i < paramArrayOfChar.length) {
              break label89;
            }
            j = 1;
          }
        }
        label81:
        int j = 0;
        for (;;)
        {
          label86:
          break label67;
          label89:
          j = 0;
          break label40;
          for (;;)
          {
            paramArrayOfChar[i] = ((char)(int)((paramArrayOfChar[i] | paramArrayOfChar[(i * 4)]) / ((i >>> 5) - ˋ)));
            i += 48;
            break label86;
            label126:
            break;
            label129:
            j = ˏ + 5;
            ˎ = j % 128;
            if (j % 2 == 0) {
              break label81;
            }
            j = 1;
            switch (j)
            {
            }
          }
          paramArrayOfChar[i] = ((char)(int)(paramArrayOfChar[i] ^ paramArrayOfChar[(i % 4)] ^ (i - 4) * ˋ));
          i += 1;
        }
      }
      return new String(paramArrayOfChar, 4, paramArrayOfChar.length - 4);
    }
    
    /* Error */
    public final LS ॱ(String arg1)
    {
      // Byte code:
      //   0: goto +206 -> 206
      //   3: new 6	o/LS
      //   6: dup
      //   7: invokespecial 44	o/LS:<init>	()V
      //   10: astore_3
      //   11: new 46	android/os/Bundle
      //   14: dup
      //   15: invokespecial 47	android/os/Bundle:<init>	()V
      //   18: astore 4
      //   20: bipush 26
      //   22: newarray char
      //   24: dup
      //   25: iconst_0
      //   26: ldc 48
      //   28: castore
      //   29: dup
      //   30: iconst_1
      //   31: ldc 49
      //   33: castore
      //   34: dup
      //   35: iconst_2
      //   36: ldc 50
      //   38: castore
      //   39: dup
      //   40: iconst_3
      //   41: ldc 51
      //   43: castore
      //   44: dup
      //   45: iconst_4
      //   46: ldc 52
      //   48: castore
      //   49: dup
      //   50: iconst_5
      //   51: ldc 53
      //   53: castore
      //   54: dup
      //   55: bipush 6
      //   57: ldc 54
      //   59: castore
      //   60: dup
      //   61: bipush 7
      //   63: ldc 55
      //   65: castore
      //   66: dup
      //   67: bipush 8
      //   69: ldc 56
      //   71: castore
      //   72: dup
      //   73: bipush 9
      //   75: ldc 57
      //   77: castore
      //   78: dup
      //   79: bipush 10
      //   81: ldc 58
      //   83: castore
      //   84: dup
      //   85: bipush 11
      //   87: ldc 59
      //   89: castore
      //   90: dup
      //   91: bipush 12
      //   93: ldc 60
      //   95: castore
      //   96: dup
      //   97: bipush 13
      //   99: ldc 61
      //   101: castore
      //   102: dup
      //   103: bipush 14
      //   105: ldc 62
      //   107: castore
      //   108: dup
      //   109: bipush 15
      //   111: ldc 63
      //   113: castore
      //   114: dup
      //   115: bipush 16
      //   117: ldc 64
      //   119: castore
      //   120: dup
      //   121: bipush 17
      //   123: ldc 65
      //   125: castore
      //   126: dup
      //   127: bipush 18
      //   129: ldc 66
      //   131: castore
      //   132: dup
      //   133: bipush 19
      //   135: ldc 67
      //   137: castore
      //   138: dup
      //   139: bipush 20
      //   141: ldc 68
      //   143: castore
      //   144: dup
      //   145: bipush 21
      //   147: ldc 69
      //   149: castore
      //   150: dup
      //   151: bipush 22
      //   153: ldc 70
      //   155: castore
      //   156: dup
      //   157: bipush 23
      //   159: ldc 71
      //   161: castore
      //   162: dup
      //   163: bipush 24
      //   165: ldc 72
      //   167: castore
      //   168: dup
      //   169: bipush 25
      //   171: ldc 73
      //   173: castore
      //   174: invokestatic 75	o/LS$ˊ:ˋ	([C)Ljava/lang/String;
      //   177: astore 5
      //   179: aload 5
      //   181: invokevirtual 79	java/lang/String:intern	()Ljava/lang/String;
      //   184: astore 5
      //   186: aload 4
      //   188: aload 5
      //   190: aload_1
      //   191: invokevirtual 83	android/os/Bundle:putString	(Ljava/lang/String;Ljava/lang/String;)V
      //   194: aload_3
      //   195: aload 4
      //   197: invokevirtual 87	o/LS:ʽ	(Landroid/os/Bundle;)V
      //   200: goto +9 -> 209
      //   203: astore_1
      //   204: aload_1
      //   205: athrow
      //   206: goto -203 -> 3
      //   209: getstatic 16	o/LS$ˊ:ˎ	I
      //   212: bipush 103
      //   214: iadd
      //   215: istore_2
      //   216: iload_2
      //   217: sipush 128
      //   220: irem
      //   221: putstatic 18	o/LS$ˊ:ˏ	I
      //   224: iload_2
      //   225: iconst_2
      //   226: irem
      //   227: ifne +5 -> 232
      //   230: aload_3
      //   231: areturn
      //   232: aload_3
      //   233: areturn
      //   234: astore_1
      //   235: aload_1
      //   236: athrow
      // Exception table:
      //   from	to	target	type
      //   20	179	234	java/lang/Exception
      //   179	186	234	java/lang/Exception
      //   186	194	234	java/lang/Exception
      //   194	200	234	java/lang/Exception
    }
  }
}
