package o;

import android.content.Context;
import android.content.Intent;
import android.graphics.PorterDuff.Mode;
import android.graphics.drawable.Drawable;
import android.view.View;
import android.widget.ProgressBar;
import android.widget.TextView;
import java.io.UnsupportedEncodingException;
import java.math.BigDecimal;
import java.util.Collections;
import org.greenrobot.eventbus.ThreadMode;

public class LU
  extends Mg<Mo>
{
  private static int ʽॱ;
  private static byte ʾ;
  private static long ˈ;
  private static int ˉ;
  private String ʼॱ;
  
  /* Error */
  static
  {
    // Byte code:
    //   0: goto +43 -> 43
    //   3: astore_1
    //   4: aload_1
    //   5: athrow
    //   6: new 28	java/lang/NullPointerException
    //   9: dup
    //   10: invokespecial 31	java/lang/NullPointerException:<init>	()V
    //   13: athrow
    //   14: getstatic 33	o/LU:ʽॱ	I
    //   17: istore_0
    //   18: iload_0
    //   19: bipush 93
    //   21: iadd
    //   22: istore_0
    //   23: iload_0
    //   24: sipush 128
    //   27: irem
    //   28: putstatic 35	o/LU:ˉ	I
    //   31: iload_0
    //   32: iconst_2
    //   33: irem
    //   34: ifne +6 -> 40
    //   37: goto +26 -> 63
    //   40: goto +29 -> 69
    //   43: iconst_0
    //   44: putstatic 33	o/LU:ʽॱ	I
    //   47: iconst_1
    //   48: putstatic 35	o/LU:ˉ	I
    //   51: invokestatic 37	o/LU:ʾ	()V
    //   54: bipush -102
    //   56: putstatic 39	o/LU:ʾ	B
    //   59: goto -45 -> 14
    //   62: return
    //   63: bipush 26
    //   65: istore_0
    //   66: goto +6 -> 72
    //   69: bipush 45
    //   71: istore_0
    //   72: iload_0
    //   73: lookupswitch	default:+27->100, 26:+-67->6, 45:+-11->62
    //   100: return
    // Local variable table:
    //   start	length	slot	name	signature
    //   17	56	0	i	int
    //   3	2	1	localException	Exception
    // Exception table:
    //   from	to	target	type
    //   14	18	3	java/lang/Exception
    //   23	31	3	java/lang/Exception
  }
  
  public LU() {}
  
  static void ʾ()
  {
    ˈ = 6695152758351924864L;
  }
  
  private void ˉ()
  {
    break label56;
    int i = 1;
    switch (i)
    {
    default: 
      label5:
      return;
    }
    for (;;)
    {
      i = ˉ + 5;
      ʽॱ = i % 128;
      if (i % 2 != 0) {
        break;
      }
      break label67;
      return;
      label56:
      break label72;
      throw new NullPointerException();
      label67:
      i = 0;
      break label5;
      label72:
      ((Mo)this.ॱˊ).ʻ.ᐝ().ˎ(new ڏ.ˏ()
      {
        public void ˊ(int paramAnonymousInt) {}
        
        public void ˋ(int paramAnonymousInt1, float paramAnonymousFloat, int paramAnonymousInt2) {}
        
        public void ॱ(int paramAnonymousInt)
        {
          HQ localHQ = ((Mo)LU.ॱ(LU.this)).ʻ.ʻ();
          ((Mo)LU.ˋ(LU.this)).ˊ(localHQ.ˊᐝ());
          ((Mo)LU.ˏ(LU.this)).ॱ(true);
          LU.this.ˎ(localHQ, new BigDecimal(((Mo)LU.ˊ(LU.this)).ͺ().ॱ()));
        }
      });
    }
  }
  
  /* Error */
  private static String ˊ(char[] paramArrayOfChar)
  {
    // Byte code:
    //   0: goto +54 -> 54
    //   3: bipush 73
    //   5: istore_2
    //   6: goto +120 -> 126
    //   9: astore_0
    //   10: aload_0
    //   11: athrow
    //   12: bipush 51
    //   14: istore_1
    //   15: goto +69 -> 84
    //   18: bipush 18
    //   20: istore_1
    //   21: goto +63 -> 84
    //   24: iconst_5
    //   25: istore_2
    //   26: goto +100 -> 126
    //   29: getstatic 45	o/LU:ˈ	J
    //   32: lstore_3
    //   33: lload_3
    //   34: aload_0
    //   35: invokestatic 79	o/oL:ˋ	(J[C)[C
    //   38: astore_0
    //   39: goto +116 -> 155
    //   42: iload_1
    //   43: aload_0
    //   44: arraylength
    //   45: if_icmpge +6 -> 51
    //   48: goto -24 -> 24
    //   51: goto -48 -> 3
    //   54: getstatic 33	o/LU:ʽॱ	I
    //   57: bipush 81
    //   59: iadd
    //   60: istore_1
    //   61: iload_1
    //   62: sipush 128
    //   65: irem
    //   66: putstatic 35	o/LU:ˉ	I
    //   69: iload_1
    //   70: iconst_2
    //   71: irem
    //   72: ifne +6 -> 78
    //   75: goto -63 -> 12
    //   78: goto -60 -> 18
    //   81: goto +157 -> 238
    //   84: iload_1
    //   85: lookupswitch	default:+27->112, 18:+-56->29, 51:+30->115
    //   112: goto -83 -> 29
    //   115: getstatic 45	o/LU:ˈ	J
    //   118: aload_0
    //   119: invokestatic 79	o/oL:ˋ	(J[C)[C
    //   122: astore_0
    //   123: goto +32 -> 155
    //   126: iload_2
    //   127: lookupswitch	default:+25->152, 5:+57->184, 73:+97->224
    //   152: goto +32 -> 184
    //   155: iconst_4
    //   156: istore_1
    //   157: getstatic 35	o/LU:ˉ	I
    //   160: bipush 45
    //   162: iadd
    //   163: istore_2
    //   164: iload_2
    //   165: sipush 128
    //   168: irem
    //   169: putstatic 33	o/LU:ʽॱ	I
    //   172: iload_2
    //   173: iconst_2
    //   174: irem
    //   175: ifeq +6 -> 181
    //   178: goto -97 -> 81
    //   181: goto +57 -> 238
    //   184: aload_0
    //   185: iload_1
    //   186: caload
    //   187: aload_0
    //   188: iload_1
    //   189: iconst_4
    //   190: irem
    //   191: caload
    //   192: ixor
    //   193: i2l
    //   194: lstore_3
    //   195: iload_1
    //   196: iconst_4
    //   197: isub
    //   198: i2l
    //   199: lstore 5
    //   201: aload_0
    //   202: iload_1
    //   203: lload_3
    //   204: lload 5
    //   206: getstatic 45	o/LU:ˈ	J
    //   209: lmul
    //   210: lxor
    //   211: l2i
    //   212: i2c
    //   213: castore
    //   214: iload_1
    //   215: iconst_1
    //   216: iadd
    //   217: istore_1
    //   218: goto -176 -> 42
    //   221: astore_0
    //   222: aload_0
    //   223: athrow
    //   224: new 81	java/lang/String
    //   227: dup
    //   228: aload_0
    //   229: iconst_4
    //   230: aload_0
    //   231: arraylength
    //   232: iconst_4
    //   233: isub
    //   234: invokespecial 84	java/lang/String:<init>	([CII)V
    //   237: areturn
    //   238: goto -196 -> 42
    // Local variable table:
    //   start	length	slot	name	signature
    //   0	241	0	paramArrayOfChar	char[]
    //   14	204	1	i	int
    //   5	170	2	j	int
    //   32	172	3	l1	long
    //   199	6	5	l2	long
    // Exception table:
    //   from	to	target	type
    //   201	214	9	java/lang/Exception
    //   29	33	221	java/lang/Exception
    //   33	39	221	java/lang/Exception
    //   54	61	221	java/lang/Exception
    //   61	69	221	java/lang/Exception
  }
  
  private void ˊ(FW paramFW, FS paramFS)
  {
    break label148;
    label6:
    int i;
    label31:
    label48:
    Object localObject1;
    for (;;)
    {
      break label260;
      switch (i)
      {
      default: 
        break label255;
        paramFS.setValueStyle(i);
        ((Mo)this.ॱˊ).ॱ(true);
        return;
        localObject1 = ˎ(((String)localObject1).substring(4)).intern();
      }
    }
    Object localObject2;
    ((Mo)localObject2).ॱ((String)localObject1);
    ((Mo)this.ॱˊ).ˊ(paramFW);
    ((Mo)this.ॱˊ).ˎ(paramFS);
    paramFS = ((Mo)this.ॱˊ).ॱᐝ;
    if (!paramFW.ʽॱ())
    {
      break label220;
      for (;;)
      {
        label119:
        localObject1 = paramFW.status;
        if (localObject1 == FV.ACCEPTED) {
          break label441;
        }
        break label255;
        label142:
        label145:
        label148:
        do
        {
          break label119;
          break;
          break;
          i = ˉ + 79;
          ʽॱ = i % 128;
        } while (i % 2 != 0);
      }
    }
    for (;;)
    {
      i = 1;
      break label6;
      label180:
      ((Mo)this.ॱˊ).ˏ(ॱ((FV)localObject1));
      localObject2 = (Mo)this.ॱˊ;
      if (i == 0) {
        break label289;
      }
      label220:
      label255:
      label260:
      label289:
      label425:
      label434:
      label441:
      do
      {
        i = 0;
        break label6;
        i = 33;
        for (;;)
        {
          try
          {
            i = ˉ;
            i += 45;
          }
          catch (Exception paramFW)
          {
            throw paramFW;
          }
          try
          {
            ʽॱ = i % 128;
            if (i % 2 != 0) {
              break label425;
            }
          }
          catch (Exception paramFW)
          {
            throw paramFW;
          }
        }
        i = 0;
        break label180;
        i = ʽॱ;
        i += 43;
        ˉ = i % 128;
        if (i % 2 != 0)
        {
          break label142;
          localObject1 = ˋ((FV)localObject1);
          break label145;
          localObject1 = getString(LV.If.transaction_details_card_deleted);
          if (((String)localObject1).startsWith(ˊ(new char[] { 4298, 13257, -2409, -15979, 4303, 15699, -5220, -5607 }).intern())) {
            break label48;
          }
          break;
          i = 1;
          break label180;
        }
        break label142;
        for (;;)
        {
          switch (i)
          {
          case 39: 
          default: 
            break label434;
            for (;;)
            {
              i = LV.if.F15B_Black;
              break;
            }
            i = 39;
          }
        }
        i = LV.if.F15R_Black;
        break label31;
        localObject2 = ˏ(paramFW);
      } while (localObject2 == null);
    }
  }
  
  private void ˊˋ()
  {
    break label391;
    int i = 1;
    break label49;
    label8:
    Object localObject1;
    ((Mo)this.ॱˊ).ʻ.setCards(Collections.singletonList(ˏ((FW)localObject1)));
    ((Mo)this.ॱˊ).ˏ(true);
    break label75;
    i = 42;
    for (;;)
    {
      switch (i)
      {
      default: 
        label49:
        break;
      }
      for (;;)
      {
        label75:
        ((Mo)this.ॱˊ).ˎ(an.ˏ(((Mo)this.ॱˊ).ʻ.ॱ()));
        label118:
        label156:
        label220:
        Object localObject2;
        label254:
        Object localObject3;
        if (((Mo)this.ॱˊ).ˋॱ())
        {
          return;
          ˎ(((Mo)this.ॱˊ).ʻ.ʻ(), new BigDecimal(((Mo)this.ॱˊ).ͺ().amount));
          return;
          i = 20;
          break label326;
          localObject1 = ((Mo)this.ॱˊ).ͺ();
          localObject1 = ((FW)localObject1).status;
          localObject1 = FV.INITIATED;
          throw new NullPointerException();
          i = 55;
          break label359;
        }
        else
        {
          for (;;)
          {
            ((Mo)this.ॱˊ).ˎ(new BigDecimal(((FW)localObject1).commission));
            break label285;
            ˋᐝ();
            ((Mo)this.ॱˊ).ʻ.ˏ();
            ((Mo)this.ॱˊ).ˏ(true);
            localObject1 = localObject2;
            break label75;
            if (localObject3 == FV.ACKNOWLEDGED) {
              break;
            }
            break label156;
            ˎˎ();
            if (((FW)localObject1).ʽॱ()) {
              break label118;
            }
          }
          label285:
          i = ʽॱ + 101;
          ˉ = i % 128;
          if (i % 2 == 0) {
            break;
          }
          break label474;
        }
        for (;;)
        {
          if (localObject3 == FV.ACCEPTED) {
            break label460;
          }
          break;
          label326:
          localObject2 = localObject1;
          switch (i)
          {
          }
        }
        for (;;)
        {
          switch (i)
          {
          case 55: 
          default: 
            label359:
            label391:
            break;
          }
          localObject1 = ((Mo)this.ॱˊ).ͺ();
          localObject2 = ((FW)localObject1).status;
          if (localObject2 != FV.INITIATED)
          {
            localObject3 = localObject2;
            break label254;
          }
          localObject2 = localObject1;
          break label220;
          i = ʽॱ + 107;
          ˉ = i % 128;
          if (i % 2 == 0) {
            break;
          }
          i = 81;
        }
        return;
        return;
        label460:
        if (ˏ((FW)localObject1) != null) {
          break label8;
        }
      }
      label474:
      i = 0;
    }
  }
  
  private void ˊᐝ()
  {
    int i;
    for (;;)
    {
      break;
      i = ʽॱ + 61;
      ˉ = i % 128;
      if (i % 2 != 0) {
        break;
      }
    }
    for (;;)
    {
      i = ʽॱ + 33;
      ˉ = i % 128;
      if (i % 2 == 0) {
        return;
      }
      return;
      ((Mo)this.ॱˊ).ॱ(this.ˊˊ);
      ((Mo)this.ॱˊ).ʽ.getIndeterminateDrawable().setColorFilter(ᔆ.ˊ(this, LV.ˊ.romanian_yellow), PorterDuff.Mode.SRC_IN);
    }
  }
  
  /* Error */
  private String ˋ(FV paramFV)
  {
    // Byte code:
    //   0: goto +424 -> 424
    //   3: bipush 41
    //   5: istore_2
    //   6: goto +497 -> 503
    //   9: aload_0
    //   10: aload_1
    //   11: iconst_4
    //   12: invokevirtual 99	java/lang/String:substring	(I)Ljava/lang/String;
    //   15: invokespecial 102	o/LU:ˎ	(Ljava/lang/String;)Ljava/lang/String;
    //   18: invokevirtual 106	java/lang/String:intern	()Ljava/lang/String;
    //   21: areturn
    //   22: getstatic 33	o/LU:ʽॱ	I
    //   25: bipush 83
    //   27: iadd
    //   28: istore_2
    //   29: iload_2
    //   30: sipush 128
    //   33: irem
    //   34: putstatic 35	o/LU:ˉ	I
    //   37: iload_2
    //   38: iconst_2
    //   39: irem
    //   40: ifne +6 -> 46
    //   43: goto +224 -> 267
    //   46: goto +179 -> 225
    //   49: astore_1
    //   50: aload_1
    //   51: athrow
    //   52: getstatic 35	o/LU:ˉ	I
    //   55: bipush 9
    //   57: iadd
    //   58: istore_2
    //   59: iload_2
    //   60: sipush 128
    //   63: irem
    //   64: putstatic 33	o/LU:ʽॱ	I
    //   67: iload_2
    //   68: iconst_2
    //   69: irem
    //   70: ifeq +6 -> 76
    //   73: goto +506 -> 579
    //   76: aload_1
    //   77: areturn
    //   78: aload_0
    //   79: getstatic 282	o/LV$If:transaction_is_failed	I
    //   82: invokevirtual 149	o/LU:getString	(I)Ljava/lang/String;
    //   85: astore_1
    //   86: aload_1
    //   87: bipush 8
    //   89: newarray char
    //   91: dup
    //   92: iconst_0
    //   93: ldc -106
    //   95: castore
    //   96: dup
    //   97: iconst_1
    //   98: ldc -105
    //   100: castore
    //   101: dup
    //   102: iconst_2
    //   103: ldc -104
    //   105: castore
    //   106: dup
    //   107: iconst_3
    //   108: ldc -103
    //   110: castore
    //   111: dup
    //   112: iconst_4
    //   113: ldc -102
    //   115: castore
    //   116: dup
    //   117: iconst_5
    //   118: ldc -101
    //   120: castore
    //   121: dup
    //   122: bipush 6
    //   124: ldc -100
    //   126: castore
    //   127: dup
    //   128: bipush 7
    //   130: ldc -99
    //   132: castore
    //   133: invokestatic 159	o/LU:ˊ	([C)Ljava/lang/String;
    //   136: invokevirtual 106	java/lang/String:intern	()Ljava/lang/String;
    //   139: invokevirtual 163	java/lang/String:startsWith	(Ljava/lang/String;)Z
    //   142: ifeq +6 -> 148
    //   145: goto +257 -> 402
    //   148: goto +469 -> 617
    //   151: aload_0
    //   152: aload_1
    //   153: iconst_4
    //   154: invokevirtual 99	java/lang/String:substring	(I)Ljava/lang/String;
    //   157: invokespecial 102	o/LU:ˎ	(Ljava/lang/String;)Ljava/lang/String;
    //   160: invokevirtual 106	java/lang/String:intern	()Ljava/lang/String;
    //   163: astore_1
    //   164: bipush 52
    //   166: iconst_0
    //   167: idiv
    //   168: istore_2
    //   169: aload_1
    //   170: areturn
    //   171: aload_1
    //   172: areturn
    //   173: getstatic 33	o/LU:ʽॱ	I
    //   176: bipush 65
    //   178: iadd
    //   179: istore_2
    //   180: iload_2
    //   181: sipush 128
    //   184: irem
    //   185: putstatic 35	o/LU:ˉ	I
    //   188: iload_2
    //   189: iconst_2
    //   190: irem
    //   191: ifne +6 -> 197
    //   194: goto +224 -> 418
    //   197: goto +9 -> 206
    //   200: bipush 13
    //   202: istore_2
    //   203: goto +67 -> 270
    //   206: bipush 28
    //   208: istore_2
    //   209: goto +325 -> 534
    //   212: aload_0
    //   213: aload_1
    //   214: iconst_4
    //   215: invokevirtual 99	java/lang/String:substring	(I)Ljava/lang/String;
    //   218: invokespecial 102	o/LU:ˎ	(Ljava/lang/String;)Ljava/lang/String;
    //   221: invokevirtual 106	java/lang/String:intern	()Ljava/lang/String;
    //   224: areturn
    //   225: getstatic 285	o/LU$1:ॱ	[I
    //   228: aload_1
    //   229: invokevirtual 289	o/FV:ordinal	()I
    //   232: iaload
    //   233: tableswitch	default:+31->264, 2:+66->299, 3:+-155->78, 4:+194->427, 5:+390->623
    //   264: goto +311 -> 575
    //   267: goto -42 -> 225
    //   270: iload_2
    //   271: lookupswitch	default:+25->296, 13:+313->584, 49:+-120->151
    //   296: goto +288 -> 584
    //   299: getstatic 292	o/LV$If:transaction_is_expired	I
    //   302: istore_2
    //   303: aload_0
    //   304: iload_2
    //   305: invokevirtual 149	o/LU:getString	(I)Ljava/lang/String;
    //   308: astore_1
    //   309: aload_1
    //   310: bipush 8
    //   312: newarray char
    //   314: dup
    //   315: iconst_0
    //   316: ldc -106
    //   318: castore
    //   319: dup
    //   320: iconst_1
    //   321: ldc -105
    //   323: castore
    //   324: dup
    //   325: iconst_2
    //   326: ldc -104
    //   328: castore
    //   329: dup
    //   330: iconst_3
    //   331: ldc -103
    //   333: castore
    //   334: dup
    //   335: iconst_4
    //   336: ldc -102
    //   338: castore
    //   339: dup
    //   340: iconst_5
    //   341: ldc -101
    //   343: castore
    //   344: dup
    //   345: bipush 6
    //   347: ldc -100
    //   349: castore
    //   350: dup
    //   351: bipush 7
    //   353: ldc -99
    //   355: castore
    //   356: invokestatic 159	o/LU:ˊ	([C)Ljava/lang/String;
    //   359: invokevirtual 106	java/lang/String:intern	()Ljava/lang/String;
    //   362: invokevirtual 163	java/lang/String:startsWith	(Ljava/lang/String;)Z
    //   365: istore_3
    //   366: iload_3
    //   367: ifeq +6 -> 373
    //   370: goto +5 -> 375
    //   373: aload_1
    //   374: areturn
    //   375: getstatic 33	o/LU:ʽॱ	I
    //   378: bipush 91
    //   380: iadd
    //   381: istore_2
    //   382: iload_2
    //   383: sipush 128
    //   386: irem
    //   387: putstatic 35	o/LU:ˉ	I
    //   390: iload_2
    //   391: iconst_2
    //   392: irem
    //   393: ifne +6 -> 399
    //   396: goto +173 -> 569
    //   399: goto -199 -> 200
    //   402: aload_0
    //   403: aload_1
    //   404: iconst_4
    //   405: invokevirtual 99	java/lang/String:substring	(I)Ljava/lang/String;
    //   408: invokespecial 102	o/LU:ˎ	(Ljava/lang/String;)Ljava/lang/String;
    //   411: invokevirtual 106	java/lang/String:intern	()Ljava/lang/String;
    //   414: astore_1
    //   415: goto +85 -> 500
    //   418: bipush 95
    //   420: istore_2
    //   421: goto +113 -> 534
    //   424: goto -402 -> 22
    //   427: aload_0
    //   428: getstatic 295	o/LV$If:transaction_is_canceled	I
    //   431: invokevirtual 149	o/LU:getString	(I)Ljava/lang/String;
    //   434: astore_1
    //   435: aload_1
    //   436: bipush 8
    //   438: newarray char
    //   440: dup
    //   441: iconst_0
    //   442: ldc -106
    //   444: castore
    //   445: dup
    //   446: iconst_1
    //   447: ldc -105
    //   449: castore
    //   450: dup
    //   451: iconst_2
    //   452: ldc -104
    //   454: castore
    //   455: dup
    //   456: iconst_3
    //   457: ldc -103
    //   459: castore
    //   460: dup
    //   461: iconst_4
    //   462: ldc -102
    //   464: castore
    //   465: dup
    //   466: iconst_5
    //   467: ldc -101
    //   469: castore
    //   470: dup
    //   471: bipush 6
    //   473: ldc -100
    //   475: castore
    //   476: dup
    //   477: bipush 7
    //   479: ldc -99
    //   481: castore
    //   482: invokestatic 159	o/LU:ˊ	([C)Ljava/lang/String;
    //   485: invokevirtual 106	java/lang/String:intern	()Ljava/lang/String;
    //   488: invokevirtual 163	java/lang/String:startsWith	(Ljava/lang/String;)Z
    //   491: ifeq +6 -> 497
    //   494: goto +69 -> 563
    //   497: goto -494 -> 3
    //   500: goto +117 -> 617
    //   503: iload_2
    //   504: lookupswitch	default:+28->532, 22:+-495->9, 41:+-333->171
    //   532: aload_1
    //   533: areturn
    //   534: iload_2
    //   535: lookupswitch	default:+25->560, 28:+-323->212, 95:+62->597
    //   560: goto -348 -> 212
    //   563: bipush 22
    //   565: istore_2
    //   566: goto -63 -> 503
    //   569: bipush 49
    //   571: istore_2
    //   572: goto -302 -> 270
    //   575: ldc_w 297
    //   578: areturn
    //   579: aconst_null
    //   580: arraylength
    //   581: istore_2
    //   582: aload_1
    //   583: areturn
    //   584: aload_0
    //   585: aload_1
    //   586: iconst_4
    //   587: invokevirtual 99	java/lang/String:substring	(I)Ljava/lang/String;
    //   590: invokespecial 102	o/LU:ˎ	(Ljava/lang/String;)Ljava/lang/String;
    //   593: invokevirtual 106	java/lang/String:intern	()Ljava/lang/String;
    //   596: areturn
    //   597: aload_0
    //   598: aload_1
    //   599: iconst_4
    //   600: invokevirtual 99	java/lang/String:substring	(I)Ljava/lang/String;
    //   603: invokespecial 102	o/LU:ˎ	(Ljava/lang/String;)Ljava/lang/String;
    //   606: invokevirtual 106	java/lang/String:intern	()Ljava/lang/String;
    //   609: astore_1
    //   610: bipush 15
    //   612: iconst_0
    //   613: idiv
    //   614: istore_2
    //   615: aload_1
    //   616: areturn
    //   617: goto -565 -> 52
    //   620: astore_1
    //   621: aload_1
    //   622: athrow
    //   623: aload_0
    //   624: getstatic 300	o/LV$If:transaction_was_rejected	I
    //   627: invokevirtual 149	o/LU:getString	(I)Ljava/lang/String;
    //   630: astore_1
    //   631: aload_1
    //   632: bipush 8
    //   634: newarray char
    //   636: dup
    //   637: iconst_0
    //   638: ldc -106
    //   640: castore
    //   641: dup
    //   642: iconst_1
    //   643: ldc -105
    //   645: castore
    //   646: dup
    //   647: iconst_2
    //   648: ldc -104
    //   650: castore
    //   651: dup
    //   652: iconst_3
    //   653: ldc -103
    //   655: castore
    //   656: dup
    //   657: iconst_4
    //   658: ldc -102
    //   660: castore
    //   661: dup
    //   662: iconst_5
    //   663: ldc -101
    //   665: castore
    //   666: dup
    //   667: bipush 6
    //   669: ldc -100
    //   671: castore
    //   672: dup
    //   673: bipush 7
    //   675: ldc -99
    //   677: castore
    //   678: invokestatic 159	o/LU:ˊ	([C)Ljava/lang/String;
    //   681: invokevirtual 106	java/lang/String:intern	()Ljava/lang/String;
    //   684: invokevirtual 163	java/lang/String:startsWith	(Ljava/lang/String;)Z
    //   687: ifeq +6 -> 693
    //   690: goto -517 -> 173
    //   693: aload_1
    //   694: areturn
    // Local variable table:
    //   start	length	slot	name	signature
    //   0	695	0	this	LU
    //   0	695	1	paramFV	FV
    //   5	610	2	i	int
    //   365	2	3	bool	boolean
    // Exception table:
    //   from	to	target	type
    //   299	303	49	java/lang/Exception
    //   303	309	49	java/lang/Exception
    //   309	366	49	java/lang/Exception
    //   22	29	620	java/lang/Exception
    //   29	37	620	java/lang/Exception
  }
  
  private void ˋ(BigDecimal paramBigDecimal)
  {
    break label178;
    for (;;)
    {
      try
      {
        localObject = this.ॱˊ;
      }
      catch (Exception paramBigDecimal)
      {
        Object localObject;
        double d1;
        double d2;
        int i;
        label142:
        throw paramBigDecimal;
      }
      try
      {
        localObject = (Mo)localObject;
        localObject = ((Mo)localObject).ͺ();
        d1 = ((FW)localObject).amount;
        d2 = paramBigDecimal.doubleValue();
        ((Mo)this.ॱˊ).ˎ(paramBigDecimal);
        ((Mo)this.ॱˊ).ͺ().totalAmount = (d1 + d2);
        return;
      }
      catch (Exception paramBigDecimal)
      {
        throw paramBigDecimal;
      }
      switch (i)
      {
      case 1: 
      default: 
        continue;
        i = 1;
        break;
      case 0: 
        d1 = ((Mo)this.ॱˊ).ͺ().amount / paramBigDecimal.doubleValue();
        ((Mo)this.ॱˊ).ˎ(paramBigDecimal);
        ((Mo)this.ॱˊ).ͺ().totalAmount = d1;
        return;
        i = 0;
      }
    }
    label178:
    for (;;)
    {
      i = ˉ + 61;
      ʽॱ = i % 128;
      if (i % 2 != 0) {
        break label142;
      }
      break;
    }
  }
  
  /* Error */
  private boolean ˋˋ()
  {
    // Byte code:
    //   0: goto +90 -> 90
    //   3: aload_0
    //   4: getfield 49	o/LU:ॱˊ	Landroid/databinding/ViewDataBinding;
    //   7: astore_2
    //   8: aload_2
    //   9: checkcast 51	o/Mo
    //   12: getfield 55	o/Mo:ʻ	Lo/KZ;
    //   15: invokevirtual 312	o/KZ:ॱॱ	()Lcom/insidesecure/hce/MatrixHCECard;
    //   18: astore_2
    //   19: aload_2
    //   20: ifnonnull +6 -> 26
    //   23: goto +47 -> 70
    //   26: goto +39 -> 65
    //   29: goto -26 -> 3
    //   32: getstatic 35	o/LU:ˉ	I
    //   35: bipush 71
    //   37: iadd
    //   38: istore_1
    //   39: iload_1
    //   40: sipush 128
    //   43: irem
    //   44: putstatic 33	o/LU:ʽॱ	I
    //   47: iload_1
    //   48: iconst_2
    //   49: irem
    //   50: ifeq +6 -> 56
    //   53: goto -24 -> 29
    //   56: goto -53 -> 3
    //   59: astore_2
    //   60: aload_2
    //   61: athrow
    //   62: astore_2
    //   63: aload_2
    //   64: athrow
    //   65: iconst_0
    //   66: istore_1
    //   67: goto +56 -> 123
    //   70: iconst_1
    //   71: istore_1
    //   72: goto +51 -> 123
    //   75: iconst_0
    //   76: istore_1
    //   77: goto +18 -> 95
    //   80: iconst_1
    //   81: ireturn
    //   82: aload_2
    //   83: invokestatic 317	o/HQ:ˏ	(Lcom/insidesecure/hce/MatrixHCECard;)Lo/HQ;
    //   86: invokevirtual 319	o/HQ:ˏ	()Z
    //   89: ireturn
    //   90: goto -58 -> 32
    //   93: iconst_1
    //   94: istore_1
    //   95: iload_1
    //   96: tableswitch	default:+24->120, 0:+84->180, 1:+-16->80
    //   120: goto -40 -> 80
    //   123: iload_1
    //   124: tableswitch	default:+24->148, 0:+-42->82, 1:+27->151
    //   148: goto -66 -> 82
    //   151: getstatic 35	o/LU:ˉ	I
    //   154: istore_1
    //   155: iload_1
    //   156: bipush 69
    //   158: iadd
    //   159: istore_1
    //   160: iload_1
    //   161: sipush 128
    //   164: irem
    //   165: putstatic 33	o/LU:ʽॱ	I
    //   168: iload_1
    //   169: iconst_2
    //   170: irem
    //   171: ifeq +6 -> 177
    //   174: goto -81 -> 93
    //   177: goto -102 -> 75
    //   180: iconst_0
    //   181: ireturn
    // Local variable table:
    //   start	length	slot	name	signature
    //   0	182	0	this	LU
    //   38	133	1	i	int
    //   7	13	2	localObject	Object
    //   59	2	2	localException1	Exception
    //   62	21	2	localException2	Exception
    // Exception table:
    //   from	to	target	type
    //   3	8	59	java/lang/Exception
    //   160	168	59	java/lang/Exception
    //   32	39	62	java/lang/Exception
    //   39	47	62	java/lang/Exception
    //   151	155	62	java/lang/Exception
  }
  
  /* Error */
  private void ˋᐝ()
  {
    // Byte code:
    //   0: goto +213 -> 213
    //   3: return
    //   4: iconst_1
    //   5: istore_1
    //   6: goto +53 -> 59
    //   9: aload_0
    //   10: getfield 49	o/LU:ॱˊ	Landroid/databinding/ViewDataBinding;
    //   13: checkcast 51	o/Mo
    //   16: getfield 55	o/Mo:ʻ	Lo/KZ;
    //   19: aload_0
    //   20: aload_0
    //   21: getfield 49	o/LU:ॱˊ	Landroid/databinding/ViewDataBinding;
    //   24: checkcast 51	o/Mo
    //   27: invokevirtual 209	o/Mo:ͺ	()Lo/FW;
    //   30: getfield 323	o/FW:currency	Lo/Ep;
    //   33: getstatic 329	o/FY:RECEIVED	Lo/FY;
    //   36: getstatic 335	o/FT:REQUEST_MONEY	Lo/FT;
    //   39: invokevirtual 338	o/LU:ॱ	(Lo/Ep;Lo/FY;Lo/FT;)Ljava/util/List;
    //   42: checkcast 340	java/util/ArrayList
    //   45: invokevirtual 344	o/KZ:setFilters	(Ljava/util/ArrayList;)V
    //   48: goto +138 -> 186
    //   51: iconst_0
    //   52: istore_1
    //   53: goto +105 -> 158
    //   56: astore_2
    //   57: aload_2
    //   58: athrow
    //   59: iload_1
    //   60: tableswitch	default:+24->84, 0:+92->152, 1:+-57->3
    //   84: return
    //   85: iconst_1
    //   86: istore_1
    //   87: goto +71 -> 158
    //   90: iconst_0
    //   91: istore_1
    //   92: goto -33 -> 59
    //   95: aload_0
    //   96: getfield 49	o/LU:ॱˊ	Landroid/databinding/ViewDataBinding;
    //   99: astore_2
    //   100: aload_2
    //   101: checkcast 51	o/Mo
    //   104: astore_2
    //   105: aload_2
    //   106: getfield 55	o/Mo:ʻ	Lo/KZ;
    //   109: astore_2
    //   110: aload_0
    //   111: getfield 49	o/LU:ॱˊ	Landroid/databinding/ViewDataBinding;
    //   114: astore_3
    //   115: aload_3
    //   116: checkcast 51	o/Mo
    //   119: astore_3
    //   120: aload_2
    //   121: aload_0
    //   122: aload_3
    //   123: invokevirtual 209	o/Mo:ͺ	()Lo/FW;
    //   126: getfield 323	o/FW:currency	Lo/Ep;
    //   129: getstatic 329	o/FY:RECEIVED	Lo/FY;
    //   132: getstatic 335	o/FT:REQUEST_MONEY	Lo/FT;
    //   135: invokevirtual 338	o/LU:ॱ	(Lo/Ep;Lo/FY;Lo/FT;)Ljava/util/List;
    //   138: checkcast 340	java/util/ArrayList
    //   141: invokevirtual 344	o/KZ:setFilters	(Ljava/util/ArrayList;)V
    //   144: new 28	java/lang/NullPointerException
    //   147: dup
    //   148: invokespecial 31	java/lang/NullPointerException:<init>	()V
    //   151: athrow
    //   152: bipush 39
    //   154: iconst_0
    //   155: idiv
    //   156: istore_1
    //   157: return
    //   158: iload_1
    //   159: tableswitch	default:+21->180, 0:+-64->95, 1:+-150->9
    //   180: goto -171 -> 9
    //   183: astore_2
    //   184: aload_2
    //   185: athrow
    //   186: getstatic 35	o/LU:ˉ	I
    //   189: bipush 59
    //   191: iadd
    //   192: istore_1
    //   193: iload_1
    //   194: sipush 128
    //   197: irem
    //   198: putstatic 33	o/LU:ʽॱ	I
    //   201: iload_1
    //   202: iconst_2
    //   203: irem
    //   204: ifeq +6 -> 210
    //   207: goto -117 -> 90
    //   210: goto -206 -> 4
    //   213: getstatic 35	o/LU:ˉ	I
    //   216: bipush 69
    //   218: iadd
    //   219: istore_1
    //   220: iload_1
    //   221: sipush 128
    //   224: irem
    //   225: putstatic 33	o/LU:ʽॱ	I
    //   228: iload_1
    //   229: iconst_2
    //   230: irem
    //   231: ifeq +6 -> 237
    //   234: goto -183 -> 51
    //   237: goto -152 -> 85
    // Local variable table:
    //   start	length	slot	name	signature
    //   0	240	0	this	LU
    //   5	226	1	i	int
    //   56	2	2	localException1	Exception
    //   99	22	2	localObject1	Object
    //   183	2	2	localException2	Exception
    //   114	9	3	localObject2	Object
    // Exception table:
    //   from	to	target	type
    //   100	105	56	java/lang/Exception
    //   95	100	183	java/lang/Exception
    //   100	105	183	java/lang/Exception
    //   105	110	183	java/lang/Exception
    //   110	115	183	java/lang/Exception
    //   115	120	183	java/lang/Exception
    //   120	152	183	java/lang/Exception
  }
  
  private void ˌ()
  {
    for (;;)
    {
      int i;
      try
      {
        String str2;
        String str1 = str2.substring(4);
        str1 = ˎ(str1);
        str1 = str1.intern();
        continue;
        str1 = str2;
        double d;
        String str3;
        switch (i)
        {
        default: 
          str1 = str2;
          continue;
          d = ((Mo)this.ॱˊ).ͺ().totalAmount;
          str3 = ((Mo)this.ॱˊ).ͺ().currency.ˊ();
          str2 = ॱˊ().getString(LV.If.p2p_device_unlock_required_desc);
          if (str2.startsWith(ˊ(new char[] { 4298, 13257, -2409, -15979, 4303, 15699, -5220, -5607 }).intern())) {}
          break;
        case 34: 
          i = ˉ + 73;
          ʽॱ = i % 128;
          if (i % 2 == 0)
          {
            continue;
            i = 1;
            break label309;
          }
          continue;
          i = 34;
          continue;
          i = 2;
          break;
        }
        str1 = String.format(str1, new Object[] { String.valueOf(d), str3 });
        Ic.ˏ(ॱˊ()).ˊ(str1).ˎ(23);
        i = ʽॱ + 105;
        ˉ = i % 128;
        if (i % 2 != 0) {
          continue;
        }
        i = 0;
      }
      catch (Exception localException)
      {
        throw localException;
      }
      throw new NullPointerException();
      return;
      label309:
      switch (i)
      {
      }
    }
  }
  
  /* Error */
  private void ˍ()
  {
    // Byte code:
    //   0: goto +3 -> 3
    //   3: goto +3 -> 6
    //   6: aload_0
    //   7: getfield 244	o/LU:ˊˊ	Lo/coN;
    //   10: iconst_1
    //   11: invokevirtual 385	o/coN:ˋ	(Z)V
    //   14: aload_0
    //   15: getfield 49	o/LU:ॱˊ	Landroid/databinding/ViewDataBinding;
    //   18: checkcast 51	o/Mo
    //   21: getfield 55	o/Mo:ʻ	Lo/KZ;
    //   24: invokevirtual 312	o/KZ:ॱॱ	()Lcom/insidesecure/hce/MatrixHCECard;
    //   27: invokestatic 317	o/HQ:ˏ	(Lcom/insidesecure/hce/MatrixHCECard;)Lo/HQ;
    //   30: invokevirtual 387	o/HQ:ॱॱ	()Ljava/lang/String;
    //   33: astore_2
    //   34: goto +17 -> 51
    //   37: astore_2
    //   38: aload_2
    //   39: invokevirtual 393	java/lang/Throwable:getCause	()Ljava/lang/Throwable;
    //   42: astore_3
    //   43: aload_3
    //   44: ifnull +5 -> 49
    //   47: aload_3
    //   48: athrow
    //   49: aload_2
    //   50: athrow
    //   51: aload_0
    //   52: invokevirtual 397	android/content/Context:getResources	()Landroid/content/res/Resources;
    //   55: ldc_w 398
    //   58: invokevirtual 401	android/content/res/Resources:getString	(I)Ljava/lang/String;
    //   61: iconst_0
    //   62: iconst_4
    //   63: invokevirtual 404	java/lang/String:substring	(II)Ljava/lang/String;
    //   66: invokevirtual 407	java/lang/String:length	()I
    //   69: iconst_0
    //   70: iadd
    //   71: aload_0
    //   72: invokevirtual 397	android/content/Context:getResources	()Landroid/content/res/Resources;
    //   75: ldc_w 408
    //   78: invokevirtual 401	android/content/res/Resources:getString	(I)Ljava/lang/String;
    //   81: iconst_0
    //   82: iconst_4
    //   83: invokevirtual 404	java/lang/String:substring	(II)Ljava/lang/String;
    //   86: iconst_2
    //   87: invokevirtual 412	java/lang/String:codePointAt	(I)I
    //   90: bipush 124
    //   92: iadd
    //   93: aload_0
    //   94: invokevirtual 415	android/content/Context:getPackageName	()Ljava/lang/String;
    //   97: iconst_2
    //   98: invokevirtual 412	java/lang/String:codePointAt	(I)I
    //   101: ldc_w 416
    //   104: iadd
    //   105: i2c
    //   106: invokestatic 421	o/O:ˋ	(IIC)Ljava/lang/Object;
    //   109: checkcast 423	java/lang/Class
    //   112: ldc_w 424
    //   115: aconst_null
    //   116: invokevirtual 428	java/lang/Class:getMethod	(Ljava/lang/String;[Ljava/lang/Class;)Ljava/lang/reflect/Method;
    //   119: aconst_null
    //   120: aconst_null
    //   121: invokevirtual 434	java/lang/reflect/Method:invoke	(Ljava/lang/Object;[Ljava/lang/Object;)Ljava/lang/Object;
    //   124: checkcast 436	o/It
    //   127: astore_3
    //   128: aload_3
    //   129: aload_0
    //   130: getfield 439	o/LU:ʿ	Ljava/lang/String;
    //   133: new 441	o/Gb
    //   136: dup
    //   137: aload_2
    //   138: aload_0
    //   139: getfield 49	o/LU:ॱˊ	Landroid/databinding/ViewDataBinding;
    //   142: checkcast 51	o/Mo
    //   145: invokevirtual 445	o/Mo:ˏॱ	()Ljava/math/BigDecimal;
    //   148: invokespecial 448	o/Gb:<init>	(Ljava/lang/String;Ljava/math/BigDecimal;)V
    //   151: invokeinterface 451 3 0
    //   156: new 13	o/LU$5
    //   159: dup
    //   160: aload_0
    //   161: aload_0
    //   162: invokespecial 454	o/LU$5:<init>	(Lo/LU;Landroid/content/Context;)V
    //   165: invokeinterface 459 2 0
    //   170: getstatic 35	o/LU:ˉ	I
    //   173: bipush 35
    //   175: iadd
    //   176: istore_1
    //   177: iload_1
    //   178: sipush 128
    //   181: irem
    //   182: putstatic 33	o/LU:ʽॱ	I
    //   185: iload_1
    //   186: iconst_2
    //   187: irem
    //   188: ifeq +4 -> 192
    //   191: return
    //   192: return
    // Local variable table:
    //   start	length	slot	name	signature
    //   0	193	0	this	LU
    //   176	12	1	i	int
    //   33	1	2	str1	String
    //   37	101	2	str2	String
    //   42	87	3	localObject	Object
    // Exception table:
    //   from	to	target	type
    //   51	128	37	finally
  }
  
  /* Error */
  private String ˎ(String paramString)
  {
    // Byte code:
    //   0: goto +35 -> 35
    //   3: iload_3
    //   4: lookupswitch	default:+28->32, 21:+323->327, 87:+290->294
    //   32: goto +262 -> 294
    //   35: goto +71 -> 106
    //   38: astore_1
    //   39: new 463	java/lang/RuntimeException
    //   42: dup
    //   43: aload_1
    //   44: invokespecial 466	java/lang/RuntimeException:<init>	(Ljava/lang/Throwable;)V
    //   47: athrow
    //   48: goto +214 -> 262
    //   51: aload_1
    //   52: arraylength
    //   53: istore_3
    //   54: iload_2
    //   55: iload_3
    //   56: if_icmpge +6 -> 62
    //   59: goto +227 -> 286
    //   62: goto +259 -> 321
    //   65: goto -14 -> 51
    //   68: bipush 23
    //   70: istore_2
    //   71: goto +161 -> 232
    //   74: iconst_0
    //   75: istore_2
    //   76: goto +156 -> 232
    //   79: getstatic 35	o/LU:ˉ	I
    //   82: bipush 119
    //   84: iadd
    //   85: istore_2
    //   86: iload_2
    //   87: sipush 128
    //   90: irem
    //   91: putstatic 33	o/LU:ʽॱ	I
    //   94: iload_2
    //   95: iconst_2
    //   96: irem
    //   97: ifeq +6 -> 103
    //   100: goto -26 -> 74
    //   103: goto -35 -> 68
    //   106: aload_1
    //   107: bipush 14
    //   109: newarray char
    //   111: dup
    //   112: iconst_0
    //   113: ldc_w 467
    //   116: castore
    //   117: dup
    //   118: iconst_1
    //   119: ldc_w 468
    //   122: castore
    //   123: dup
    //   124: iconst_2
    //   125: ldc_w 469
    //   128: castore
    //   129: dup
    //   130: iconst_3
    //   131: ldc_w 470
    //   134: castore
    //   135: dup
    //   136: iconst_4
    //   137: ldc_w 471
    //   140: castore
    //   141: dup
    //   142: iconst_5
    //   143: ldc_w 472
    //   146: castore
    //   147: dup
    //   148: bipush 6
    //   150: ldc_w 473
    //   153: castore
    //   154: dup
    //   155: bipush 7
    //   157: ldc_w 474
    //   160: castore
    //   161: dup
    //   162: bipush 8
    //   164: ldc_w 475
    //   167: castore
    //   168: dup
    //   169: bipush 9
    //   171: ldc_w 476
    //   174: castore
    //   175: dup
    //   176: bipush 10
    //   178: ldc_w 477
    //   181: castore
    //   182: dup
    //   183: bipush 11
    //   185: ldc_w 478
    //   188: castore
    //   189: dup
    //   190: bipush 12
    //   192: ldc_w 479
    //   195: castore
    //   196: dup
    //   197: bipush 13
    //   199: ldc_w 480
    //   202: castore
    //   203: invokestatic 159	o/LU:ˊ	([C)Ljava/lang/String;
    //   206: invokevirtual 106	java/lang/String:intern	()Ljava/lang/String;
    //   209: invokevirtual 484	java/lang/String:getBytes	(Ljava/lang/String;)[B
    //   212: astore_1
    //   213: aload_1
    //   214: arraylength
    //   215: newarray byte
    //   217: astore 4
    //   219: iconst_0
    //   220: istore_2
    //   221: goto -156 -> 65
    //   224: aconst_null
    //   225: arraylength
    //   226: istore_2
    //   227: aload_1
    //   228: areturn
    //   229: goto -178 -> 51
    //   232: iload_2
    //   233: lookupswitch	default:+27->260, 0:+-9->224, 23:+59->292
    //   260: aload_1
    //   261: areturn
    //   262: aload 4
    //   264: iload_2
    //   265: aload_1
    //   266: aload_1
    //   267: arraylength
    //   268: iload_2
    //   269: isub
    //   270: iconst_1
    //   271: isub
    //   272: baload
    //   273: getstatic 39	o/LU:ʾ	B
    //   276: ixor
    //   277: i2b
    //   278: bastore
    //   279: iload_2
    //   280: iconst_1
    //   281: iadd
    //   282: istore_2
    //   283: goto -54 -> 229
    //   286: bipush 87
    //   288: istore_3
    //   289: goto -286 -> 3
    //   292: aload_1
    //   293: areturn
    //   294: getstatic 35	o/LU:ˉ	I
    //   297: bipush 69
    //   299: iadd
    //   300: istore_3
    //   301: iload_3
    //   302: sipush 128
    //   305: irem
    //   306: putstatic 33	o/LU:ʽॱ	I
    //   309: iload_3
    //   310: iconst_2
    //   311: irem
    //   312: ifeq +6 -> 318
    //   315: goto -267 -> 48
    //   318: goto -56 -> 262
    //   321: bipush 21
    //   323: istore_3
    //   324: goto -321 -> 3
    //   327: new 81	java/lang/String
    //   330: dup
    //   331: aload 4
    //   333: bipush 9
    //   335: newarray char
    //   337: dup
    //   338: iconst_0
    //   339: ldc_w 485
    //   342: castore
    //   343: dup
    //   344: iconst_1
    //   345: ldc_w 486
    //   348: castore
    //   349: dup
    //   350: iconst_2
    //   351: ldc_w 487
    //   354: castore
    //   355: dup
    //   356: iconst_3
    //   357: ldc_w 488
    //   360: castore
    //   361: dup
    //   362: iconst_4
    //   363: ldc_w 489
    //   366: castore
    //   367: dup
    //   368: iconst_5
    //   369: ldc_w 490
    //   372: castore
    //   373: dup
    //   374: bipush 6
    //   376: ldc_w 491
    //   379: castore
    //   380: dup
    //   381: bipush 7
    //   383: ldc_w 492
    //   386: castore
    //   387: dup
    //   388: bipush 8
    //   390: ldc_w 493
    //   393: castore
    //   394: invokestatic 159	o/LU:ˊ	([C)Ljava/lang/String;
    //   397: invokevirtual 106	java/lang/String:intern	()Ljava/lang/String;
    //   400: invokespecial 496	java/lang/String:<init>	([BLjava/lang/String;)V
    //   403: astore_1
    //   404: goto -325 -> 79
    // Local variable table:
    //   start	length	slot	name	signature
    //   0	407	0	this	LU
    //   0	407	1	paramString	String
    //   54	229	2	i	int
    //   3	321	3	j	int
    //   217	115	4	arrayOfByte	byte[]
    // Exception table:
    //   from	to	target	type
    //   51	54	38	java/io/UnsupportedEncodingException
    //   106	219	38	java/io/UnsupportedEncodingException
    //   262	279	38	java/io/UnsupportedEncodingException
    //   327	404	38	java/io/UnsupportedEncodingException
  }
  
  /* Error */
  private void ˎˎ()
  {
    // Byte code:
    //   0: goto +134 -> 134
    //   3: new 28	java/lang/NullPointerException
    //   6: dup
    //   7: invokespecial 31	java/lang/NullPointerException:<init>	()V
    //   10: athrow
    //   11: getstatic 33	o/LU:ʽॱ	I
    //   14: istore_1
    //   15: iload_1
    //   16: bipush 73
    //   18: iadd
    //   19: istore_1
    //   20: iload_1
    //   21: sipush 128
    //   24: irem
    //   25: putstatic 35	o/LU:ˉ	I
    //   28: iload_1
    //   29: iconst_2
    //   30: irem
    //   31: ifne +6 -> 37
    //   34: goto +61 -> 95
    //   37: goto +92 -> 129
    //   40: getstatic 35	o/LU:ˉ	I
    //   43: bipush 83
    //   45: iadd
    //   46: istore_1
    //   47: iload_1
    //   48: sipush 128
    //   51: irem
    //   52: putstatic 33	o/LU:ʽॱ	I
    //   55: iload_1
    //   56: iconst_2
    //   57: irem
    //   58: ifeq +6 -> 64
    //   61: goto +39 -> 100
    //   64: aload_0
    //   65: getfield 49	o/LU:ॱˊ	Landroid/databinding/ViewDataBinding;
    //   68: checkcast 51	o/Mo
    //   71: getfield 55	o/Mo:ʻ	Lo/KZ;
    //   74: invokevirtual 203	o/KZ:ʻ	()Lo/HQ;
    //   77: astore_2
    //   78: aload_0
    //   79: getfield 49	o/LU:ॱˊ	Landroid/databinding/ViewDataBinding;
    //   82: checkcast 51	o/Mo
    //   85: aload_2
    //   86: invokevirtual 498	o/HQ:ˊᐝ	()Z
    //   89: invokevirtual 500	o/Mo:ˊ	(Z)V
    //   92: goto -81 -> 11
    //   95: iconst_0
    //   96: istore_1
    //   97: goto +6 -> 103
    //   100: goto -36 -> 64
    //   103: iload_1
    //   104: tableswitch	default:+24->128, 0:+-101->3, 1:+36->140
    //   128: return
    //   129: iconst_1
    //   130: istore_1
    //   131: goto -28 -> 103
    //   134: goto -94 -> 40
    //   137: astore_2
    //   138: aload_2
    //   139: athrow
    //   140: return
    //   141: astore_2
    //   142: aload_2
    //   143: athrow
    // Local variable table:
    //   start	length	slot	name	signature
    //   0	144	0	this	LU
    //   14	117	1	i	int
    //   77	9	2	localHQ	HQ
    //   137	2	2	localException1	Exception
    //   141	2	2	localException2	Exception
    // Exception table:
    //   from	to	target	type
    //   11	15	137	java/lang/Exception
    //   40	47	137	java/lang/Exception
    //   47	55	137	java/lang/Exception
    //   20	28	141	java/lang/Exception
  }
  
  /* Error */
  private String ॱ(FV paramFV)
  {
    // Byte code:
    //   0: goto +747 -> 747
    //   3: bipush 8
    //   5: newarray char
    //   7: dup
    //   8: iconst_0
    //   9: ldc -106
    //   11: castore
    //   12: dup
    //   13: iconst_1
    //   14: ldc -105
    //   16: castore
    //   17: dup
    //   18: iconst_2
    //   19: ldc -104
    //   21: castore
    //   22: dup
    //   23: iconst_3
    //   24: ldc -103
    //   26: castore
    //   27: dup
    //   28: iconst_4
    //   29: ldc -102
    //   31: castore
    //   32: dup
    //   33: iconst_5
    //   34: ldc -101
    //   36: castore
    //   37: dup
    //   38: bipush 6
    //   40: ldc -100
    //   42: castore
    //   43: dup
    //   44: bipush 7
    //   46: ldc -99
    //   48: castore
    //   49: invokestatic 159	o/LU:ˊ	([C)Ljava/lang/String;
    //   52: invokevirtual 106	java/lang/String:intern	()Ljava/lang/String;
    //   55: astore 4
    //   57: aload 4
    //   59: astore 5
    //   61: aload 4
    //   63: astore 6
    //   65: aload 4
    //   67: astore 7
    //   69: aload 4
    //   71: astore 8
    //   73: aload 4
    //   75: astore 9
    //   77: getstatic 285	o/LU$1:ॱ	[I
    //   80: aload_1
    //   81: invokevirtual 289	o/FV:ordinal	()I
    //   84: iaload
    //   85: tableswitch	default:+43->128, 1:+97->182, 2:+148->233, 3:+72->157, 4:+300->385, 5:+123->208, 6:+528->613, 7:+528->613
    //   128: goto +207 -> 335
    //   131: getstatic 33	o/LU:ʽॱ	I
    //   134: iconst_1
    //   135: iadd
    //   136: istore_2
    //   137: iload_2
    //   138: sipush 128
    //   141: irem
    //   142: putstatic 35	o/LU:ˉ	I
    //   145: iload_2
    //   146: iconst_2
    //   147: irem
    //   148: ifne +6 -> 154
    //   151: goto +216 -> 367
    //   154: goto +190 -> 344
    //   157: aload_0
    //   158: getstatic 503	o/LV$If:failed_transaction	I
    //   161: invokevirtual 149	o/LU:getString	(I)Ljava/lang/String;
    //   164: astore 4
    //   166: aload 4
    //   168: aload 5
    //   170: invokevirtual 163	java/lang/String:startsWith	(Ljava/lang/String;)Z
    //   173: ifeq +6 -> 179
    //   176: goto +399 -> 575
    //   179: goto +579 -> 758
    //   182: aload_0
    //   183: getstatic 506	o/LV$If:transaction_details_sent	I
    //   186: invokevirtual 149	o/LU:getString	(I)Ljava/lang/String;
    //   189: astore_1
    //   190: aload_1
    //   191: aload 6
    //   193: invokevirtual 163	java/lang/String:startsWith	(Ljava/lang/String;)Z
    //   196: ifeq +6 -> 202
    //   199: goto -68 -> 131
    //   202: goto +181 -> 383
    //   205: astore_1
    //   206: aload_1
    //   207: athrow
    //   208: aload_0
    //   209: getstatic 509	o/LV$If:rejected_transaction	I
    //   212: invokevirtual 149	o/LU:getString	(I)Ljava/lang/String;
    //   215: astore 4
    //   217: aload 4
    //   219: aload 7
    //   221: invokevirtual 163	java/lang/String:startsWith	(Ljava/lang/String;)Z
    //   224: ifeq +6 -> 230
    //   227: goto +353 -> 580
    //   230: goto +522 -> 752
    //   233: aload_0
    //   234: getstatic 512	o/LV$If:expired_transaction	I
    //   237: invokevirtual 149	o/LU:getString	(I)Ljava/lang/String;
    //   240: astore_1
    //   241: aload_1
    //   242: aload 8
    //   244: invokevirtual 163	java/lang/String:startsWith	(Ljava/lang/String;)Z
    //   247: ifeq +6 -> 253
    //   250: goto +37 -> 287
    //   253: aload_1
    //   254: areturn
    //   255: aload 4
    //   257: astore_1
    //   258: iload_2
    //   259: lookupswitch	default:+25->284, 46:+491->750, 47:+327->586
    //   284: goto +302 -> 586
    //   287: aload_0
    //   288: aload_1
    //   289: iconst_4
    //   290: invokevirtual 99	java/lang/String:substring	(I)Ljava/lang/String;
    //   293: invokespecial 102	o/LU:ˎ	(Ljava/lang/String;)Ljava/lang/String;
    //   296: invokevirtual 106	java/lang/String:intern	()Ljava/lang/String;
    //   299: areturn
    //   300: getstatic 35	o/LU:ˉ	I
    //   303: istore_2
    //   304: iload_2
    //   305: bipush 77
    //   307: iadd
    //   308: istore_2
    //   309: iload_2
    //   310: sipush 128
    //   313: irem
    //   314: putstatic 33	o/LU:ʽॱ	I
    //   317: iload_2
    //   318: iconst_2
    //   319: irem
    //   320: ifeq +6 -> 326
    //   323: goto +394 -> 717
    //   326: aload_1
    //   327: areturn
    //   328: iconst_1
    //   329: istore_2
    //   330: goto +392 -> 722
    //   333: aload_1
    //   334: areturn
    //   335: ldc_w 297
    //   338: areturn
    //   339: iconst_0
    //   340: istore_2
    //   341: goto +381 -> 722
    //   344: aload_1
    //   345: iconst_4
    //   346: invokevirtual 99	java/lang/String:substring	(I)Ljava/lang/String;
    //   349: astore_1
    //   350: aload_0
    //   351: aload_1
    //   352: invokespecial 102	o/LU:ˎ	(Ljava/lang/String;)Ljava/lang/String;
    //   355: astore_1
    //   356: aload_1
    //   357: invokevirtual 106	java/lang/String:intern	()Ljava/lang/String;
    //   360: astore_1
    //   361: goto +22 -> 383
    //   364: goto +62 -> 426
    //   367: goto -23 -> 344
    //   370: aload_0
    //   371: aload_1
    //   372: iconst_4
    //   373: invokevirtual 99	java/lang/String:substring	(I)Ljava/lang/String;
    //   376: invokespecial 102	o/LU:ˎ	(Ljava/lang/String;)Ljava/lang/String;
    //   379: invokevirtual 106	java/lang/String:intern	()Ljava/lang/String;
    //   382: areturn
    //   383: aload_1
    //   384: areturn
    //   385: aload_0
    //   386: getstatic 515	o/LV$If:cancelled_transaction	I
    //   389: invokevirtual 149	o/LU:getString	(I)Ljava/lang/String;
    //   392: astore_1
    //   393: aload_1
    //   394: aload 9
    //   396: invokevirtual 163	java/lang/String:startsWith	(Ljava/lang/String;)Z
    //   399: ifeq +6 -> 405
    //   402: goto +299 -> 701
    //   405: aload_1
    //   406: areturn
    //   407: aload_0
    //   408: aload 4
    //   410: iconst_4
    //   411: invokevirtual 99	java/lang/String:substring	(I)Ljava/lang/String;
    //   414: invokespecial 102	o/LU:ˎ	(Ljava/lang/String;)Ljava/lang/String;
    //   417: invokevirtual 106	java/lang/String:intern	()Ljava/lang/String;
    //   420: astore_1
    //   421: goto +215 -> 636
    //   424: aload_1
    //   425: areturn
    //   426: aload_0
    //   427: aload 4
    //   429: iconst_4
    //   430: invokevirtual 99	java/lang/String:substring	(I)Ljava/lang/String;
    //   433: invokespecial 102	o/LU:ˎ	(Ljava/lang/String;)Ljava/lang/String;
    //   436: invokevirtual 106	java/lang/String:intern	()Ljava/lang/String;
    //   439: astore_1
    //   440: goto +310 -> 750
    //   443: bipush 8
    //   445: newarray char
    //   447: dup
    //   448: iconst_0
    //   449: ldc -106
    //   451: castore
    //   452: dup
    //   453: iconst_1
    //   454: ldc -105
    //   456: castore
    //   457: dup
    //   458: iconst_2
    //   459: ldc -104
    //   461: castore
    //   462: dup
    //   463: iconst_3
    //   464: ldc -103
    //   466: castore
    //   467: dup
    //   468: iconst_4
    //   469: ldc -102
    //   471: castore
    //   472: dup
    //   473: iconst_5
    //   474: ldc -101
    //   476: castore
    //   477: dup
    //   478: bipush 6
    //   480: ldc -100
    //   482: castore
    //   483: dup
    //   484: bipush 7
    //   486: ldc -99
    //   488: castore
    //   489: invokestatic 159	o/LU:ˊ	([C)Ljava/lang/String;
    //   492: invokevirtual 106	java/lang/String:intern	()Ljava/lang/String;
    //   495: astore 4
    //   497: getstatic 285	o/LU$1:ॱ	[I
    //   500: aload_1
    //   501: invokevirtual 289	o/FV:ordinal	()I
    //   504: iaload
    //   505: istore_2
    //   506: aconst_null
    //   507: arraylength
    //   508: istore_3
    //   509: aload 4
    //   511: astore 5
    //   513: aload 4
    //   515: astore 6
    //   517: aload 4
    //   519: astore 7
    //   521: aload 4
    //   523: astore 8
    //   525: aload 4
    //   527: astore 9
    //   529: iload_2
    //   530: tableswitch	default:+42->572, 1:+-348->182, 2:+-297->233, 3:+-373->157, 4:+-145->385, 5:+-322->208, 6:+83->613, 7:+83->613
    //   572: goto -237 -> 335
    //   575: iconst_4
    //   576: istore_2
    //   577: goto +62 -> 639
    //   580: bipush 47
    //   582: istore_2
    //   583: goto -328 -> 255
    //   586: getstatic 33	o/LU:ʽॱ	I
    //   589: bipush 117
    //   591: iadd
    //   592: istore_2
    //   593: iload_2
    //   594: sipush 128
    //   597: irem
    //   598: putstatic 35	o/LU:ˉ	I
    //   601: iload_2
    //   602: iconst_2
    //   603: irem
    //   604: ifne +6 -> 610
    //   607: goto -243 -> 364
    //   610: goto -184 -> 426
    //   613: aload_0
    //   614: getstatic 518	o/LV$If:request_money_confirmation_toolbar	I
    //   617: invokevirtual 149	o/LU:getString	(I)Ljava/lang/String;
    //   620: astore_1
    //   621: aload_1
    //   622: aload 4
    //   624: invokevirtual 163	java/lang/String:startsWith	(Ljava/lang/String;)Z
    //   627: ifeq +6 -> 633
    //   630: goto -302 -> 328
    //   633: goto -294 -> 339
    //   636: goto -336 -> 300
    //   639: aload 4
    //   641: astore_1
    //   642: iload_2
    //   643: lookupswitch	default:+25->668, 4:+-236->407, 13:+-7->636
    //   668: goto -261 -> 407
    //   671: getstatic 33	o/LU:ʽॱ	I
    //   674: bipush 43
    //   676: iadd
    //   677: istore_2
    //   678: iload_2
    //   679: sipush 128
    //   682: irem
    //   683: putstatic 35	o/LU:ˉ	I
    //   686: iload_2
    //   687: iconst_2
    //   688: irem
    //   689: ifne +6 -> 695
    //   692: goto -249 -> 443
    //   695: goto -692 -> 3
    //   698: astore_1
    //   699: aload_1
    //   700: athrow
    //   701: aload_0
    //   702: aload_1
    //   703: iconst_4
    //   704: invokevirtual 99	java/lang/String:substring	(I)Ljava/lang/String;
    //   707: invokespecial 102	o/LU:ˎ	(Ljava/lang/String;)Ljava/lang/String;
    //   710: invokevirtual 106	java/lang/String:intern	()Ljava/lang/String;
    //   713: astore_1
    //   714: goto -290 -> 424
    //   717: aconst_null
    //   718: arraylength
    //   719: istore_2
    //   720: aload_1
    //   721: areturn
    //   722: iload_2
    //   723: tableswitch	default:+21->744, 0:+-390->333, 1:+-353->370
    //   744: goto -374 -> 370
    //   747: goto -76 -> 671
    //   750: aload_1
    //   751: areturn
    //   752: bipush 46
    //   754: istore_2
    //   755: goto -500 -> 255
    //   758: bipush 13
    //   760: istore_2
    //   761: goto -122 -> 639
    // Local variable table:
    //   start	length	slot	name	signature
    //   0	764	0	this	LU
    //   0	764	1	paramFV	FV
    //   136	625	2	i	int
    //   508	1	3	j	int
    //   55	585	4	str1	String
    //   59	453	5	str2	String
    //   63	453	6	str3	String
    //   67	453	7	str4	String
    //   71	453	8	str5	String
    //   75	453	9	str6	String
    // Exception table:
    //   from	to	target	type
    //   356	361	205	java/lang/Exception
    //   300	304	698	java/lang/Exception
    //   344	350	698	java/lang/Exception
    //   350	356	698	java/lang/Exception
    //   356	361	698	java/lang/Exception
  }
  
  /* Error */
  private void ॱ(String paramString)
  {
    // Byte code:
    //   0: goto +143 -> 143
    //   3: aload_0
    //   4: getfield 244	o/LU:ˊˊ	Lo/coN;
    //   7: iconst_1
    //   8: invokevirtual 385	o/coN:ˋ	(Z)V
    //   11: goto +17 -> 28
    //   14: astore_1
    //   15: aload_1
    //   16: invokevirtual 393	java/lang/Throwable:getCause	()Ljava/lang/Throwable;
    //   19: astore_3
    //   20: aload_3
    //   21: ifnull +5 -> 26
    //   24: aload_3
    //   25: athrow
    //   26: aload_1
    //   27: athrow
    //   28: aload_0
    //   29: invokevirtual 522	android/content/Context:getApplicationInfo	()Landroid/content/pm/ApplicationInfo;
    //   32: getfield 527	android/content/pm/ApplicationInfo:targetSdkVersion	I
    //   35: bipush 21
    //   37: isub
    //   38: aload_0
    //   39: invokevirtual 397	android/content/Context:getResources	()Landroid/content/res/Resources;
    //   42: ldc_w 528
    //   45: invokevirtual 401	android/content/res/Resources:getString	(I)Ljava/lang/String;
    //   48: iconst_0
    //   49: bipush 15
    //   51: invokevirtual 404	java/lang/String:substring	(II)Ljava/lang/String;
    //   54: iconst_0
    //   55: invokevirtual 412	java/lang/String:codePointAt	(I)I
    //   58: sipush 130
    //   61: iadd
    //   62: aload_0
    //   63: invokevirtual 397	android/content/Context:getResources	()Landroid/content/res/Resources;
    //   66: ldc_w 529
    //   69: invokevirtual 401	android/content/res/Resources:getString	(I)Ljava/lang/String;
    //   72: iconst_0
    //   73: iconst_4
    //   74: invokevirtual 404	java/lang/String:substring	(II)Ljava/lang/String;
    //   77: iconst_2
    //   78: invokevirtual 412	java/lang/String:codePointAt	(I)I
    //   81: ldc_w 530
    //   84: iadd
    //   85: i2c
    //   86: invokestatic 421	o/O:ˋ	(IIC)Ljava/lang/Object;
    //   89: checkcast 423	java/lang/Class
    //   92: ldc_w 424
    //   95: aconst_null
    //   96: invokevirtual 428	java/lang/Class:getMethod	(Ljava/lang/String;[Ljava/lang/Class;)Ljava/lang/reflect/Method;
    //   99: aconst_null
    //   100: aconst_null
    //   101: invokevirtual 434	java/lang/reflect/Method:invoke	(Ljava/lang/Object;[Ljava/lang/Object;)Ljava/lang/Object;
    //   104: checkcast 436	o/It
    //   107: astore_3
    //   108: aload_3
    //   109: aload_0
    //   110: getfield 439	o/LU:ʿ	Ljava/lang/String;
    //   113: new 532	o/Gc
    //   116: dup
    //   117: aload_1
    //   118: invokespecial 534	o/Gc:<init>	(Ljava/lang/String;)V
    //   121: invokeinterface 537 3 0
    //   126: new 11	o/LU$3
    //   129: dup
    //   130: aload_0
    //   131: aload_0
    //   132: invokespecial 538	o/LU$3:<init>	(Lo/LU;Landroid/content/Context;)V
    //   135: invokeinterface 459 2 0
    //   140: goto +7 -> 147
    //   143: goto -140 -> 3
    //   146: return
    //   147: getstatic 35	o/LU:ˉ	I
    //   150: bipush 89
    //   152: iadd
    //   153: istore_2
    //   154: iload_2
    //   155: sipush 128
    //   158: irem
    //   159: putstatic 33	o/LU:ʽॱ	I
    //   162: iload_2
    //   163: iconst_2
    //   164: irem
    //   165: ifeq +6 -> 171
    //   168: goto -22 -> 146
    //   171: return
    // Local variable table:
    //   start	length	slot	name	signature
    //   0	172	0	this	LU
    //   0	172	1	paramString	String
    //   153	12	2	i	int
    //   19	90	3	localObject	Object
    // Exception table:
    //   from	to	target	type
    //   28	108	14	finally
  }
  
  /* Error */
  public android.content.res.Resources getResources()
  {
    // Byte code:
    //   0: goto +30 -> 30
    //   3: getstatic 35	o/LU:ˉ	I
    //   6: bipush 21
    //   8: iadd
    //   9: istore_1
    //   10: iload_1
    //   11: sipush 128
    //   14: irem
    //   15: putstatic 33	o/LU:ʽॱ	I
    //   18: iload_1
    //   19: iconst_2
    //   20: irem
    //   21: ifeq +6 -> 27
    //   24: goto +43 -> 67
    //   27: goto +56 -> 83
    //   30: getstatic 33	o/LU:ʽॱ	I
    //   33: iconst_1
    //   34: iadd
    //   35: istore_1
    //   36: iload_1
    //   37: sipush 128
    //   40: irem
    //   41: putstatic 35	o/LU:ˉ	I
    //   44: iload_1
    //   45: iconst_2
    //   46: irem
    //   47: ifne +6 -> 53
    //   50: goto +23 -> 73
    //   53: goto +61 -> 114
    //   56: aload_0
    //   57: invokespecial 539	o/Mg:getResources	()Landroid/content/res/Resources;
    //   60: invokestatic 544	o/oH:ˊ	(Landroid/content/res/Resources;)Landroid/content/res/Resources;
    //   63: astore_2
    //   64: goto -61 -> 3
    //   67: bipush 29
    //   69: istore_1
    //   70: goto +16 -> 86
    //   73: iconst_1
    //   74: istore_1
    //   75: goto +41 -> 116
    //   78: aload_2
    //   79: areturn
    //   80: astore_2
    //   81: aload_2
    //   82: athrow
    //   83: bipush 16
    //   85: istore_1
    //   86: iload_1
    //   87: lookupswitch	default:+25->112, 16:+-9->78, 29:+74->161
    //   112: aload_2
    //   113: areturn
    //   114: iconst_0
    //   115: istore_1
    //   116: iload_1
    //   117: tableswitch	default:+23->140, 0:+-61->56, 1:+26->143
    //   140: goto -84 -> 56
    //   143: aload_0
    //   144: invokespecial 539	o/Mg:getResources	()Landroid/content/res/Resources;
    //   147: astore_2
    //   148: aload_2
    //   149: invokestatic 544	o/oH:ˊ	(Landroid/content/res/Resources;)Landroid/content/res/Resources;
    //   152: astore_2
    //   153: new 28	java/lang/NullPointerException
    //   156: dup
    //   157: invokespecial 31	java/lang/NullPointerException:<init>	()V
    //   160: athrow
    //   161: bipush 93
    //   163: iconst_0
    //   164: idiv
    //   165: istore_1
    //   166: aload_2
    //   167: areturn
    // Local variable table:
    //   start	length	slot	name	signature
    //   0	168	0	this	LU
    //   9	157	1	i	int
    //   63	16	2	localResources1	android.content.res.Resources
    //   80	33	2	localException	Exception
    //   147	20	2	localResources2	android.content.res.Resources
    // Exception table:
    //   from	to	target	type
    //   148	161	80	java/lang/Exception
  }
  
  /* Error */
  public void onActivityResult(int paramInt1, int paramInt2, Intent paramIntent)
  {
    // Byte code:
    //   0: goto +231 -> 231
    //   3: iload_2
    //   4: tableswitch	default:+24->28, 0:+114->118, 1:+230->234
    //   28: goto +90 -> 118
    //   31: aload_0
    //   32: iload_1
    //   33: iload_2
    //   34: aload_3
    //   35: invokespecial 548	o/Mg:onActivityResult	(IILandroid/content/Intent;)V
    //   38: new 28	java/lang/NullPointerException
    //   41: dup
    //   42: invokespecial 31	java/lang/NullPointerException:<init>	()V
    //   45: athrow
    //   46: aload_0
    //   47: iload_1
    //   48: iload_2
    //   49: aload_3
    //   50: invokespecial 548	o/Mg:onActivityResult	(IILandroid/content/Intent;)V
    //   53: iload_2
    //   54: iconst_m1
    //   55: if_icmpne +6 -> 61
    //   58: goto +140 -> 198
    //   61: goto +9 -> 70
    //   64: iconst_0
    //   65: istore 4
    //   67: goto +136 -> 203
    //   70: iconst_1
    //   71: istore_2
    //   72: goto -69 -> 3
    //   75: astore_3
    //   76: aload_3
    //   77: athrow
    //   78: aload_0
    //   79: getfield 49	o/LU:ॱˊ	Landroid/databinding/ViewDataBinding;
    //   82: astore_3
    //   83: aload_3
    //   84: checkcast 51	o/Mo
    //   87: astore_3
    //   88: aload_0
    //   89: aload_3
    //   90: getfield 55	o/Mo:ʻ	Lo/KZ;
    //   93: invokevirtual 312	o/KZ:ॱॱ	()Lcom/insidesecure/hce/MatrixHCECard;
    //   96: invokestatic 317	o/HQ:ˏ	(Lcom/insidesecure/hce/MatrixHCECard;)Lo/HQ;
    //   99: aload_0
    //   100: getfield 49	o/LU:ॱˊ	Landroid/databinding/ViewDataBinding;
    //   103: checkcast 51	o/Mo
    //   106: invokevirtual 209	o/Mo:ͺ	()Lo/FW;
    //   109: getfield 307	o/FW:totalAmount	D
    //   112: iconst_1
    //   113: iconst_0
    //   114: invokevirtual 551	o/LU:ˊ	(Lo/HQ;DZZ)V
    //   117: return
    //   118: iload_1
    //   119: lookupswitch	default:+25->144, 22:+-41->78, 23:+65->184
    //   144: return
    //   145: iconst_1
    //   146: istore 4
    //   148: goto +55 -> 203
    //   151: getstatic 33	o/LU:ʽॱ	I
    //   154: bipush 37
    //   156: iadd
    //   157: istore 4
    //   159: iload 4
    //   161: sipush 128
    //   164: irem
    //   165: putstatic 35	o/LU:ˉ	I
    //   168: iload 4
    //   170: iconst_2
    //   171: irem
    //   172: ifne +6 -> 178
    //   175: goto -111 -> 64
    //   178: goto -33 -> 145
    //   181: goto +78 -> 259
    //   184: aload_0
    //   185: aload_0
    //   186: getfield 553	o/LU:ʼॱ	Ljava/lang/String;
    //   189: invokespecial 554	o/LU:ॱ	(Ljava/lang/String;)V
    //   192: goto +43 -> 235
    //   195: astore_3
    //   196: aload_3
    //   197: athrow
    //   198: iconst_0
    //   199: istore_2
    //   200: goto -197 -> 3
    //   203: iload 4
    //   205: tableswitch	default:+23->228, 0:+-174->31, 1:+-159->46
    //   228: goto -197 -> 31
    //   231: goto -80 -> 151
    //   234: return
    //   235: getstatic 33	o/LU:ʽॱ	I
    //   238: bipush 33
    //   240: iadd
    //   241: istore_1
    //   242: iload_1
    //   243: sipush 128
    //   246: irem
    //   247: putstatic 35	o/LU:ˉ	I
    //   250: iload_1
    //   251: iconst_2
    //   252: irem
    //   253: ifne +6 -> 259
    //   256: goto -75 -> 181
    //   259: return
    // Local variable table:
    //   start	length	slot	name	signature
    //   0	260	0	this	LU
    //   0	260	1	paramInt1	int
    //   0	260	2	paramInt2	int
    //   0	260	3	paramIntent	Intent
    //   65	139	4	i	int
    // Exception table:
    //   from	to	target	type
    //   151	159	75	java/lang/Exception
    //   159	168	75	java/lang/Exception
    //   184	192	75	java/lang/Exception
    //   78	83	195	java/lang/Exception
    //   83	88	195	java/lang/Exception
    //   88	117	195	java/lang/Exception
  }
  
  /* Error */
  public void onBackPressed()
  {
    // Byte code:
    //   0: goto +124 -> 124
    //   3: bipush 42
    //   5: istore_1
    //   6: goto +9 -> 15
    //   9: astore_2
    //   10: aload_2
    //   11: athrow
    //   12: astore_2
    //   13: aload_2
    //   14: athrow
    //   15: iload_1
    //   16: lookupswitch	default:+28->44, 26:+100->116, 42:+93->109
    //   44: goto +72 -> 116
    //   47: getstatic 35	o/LU:ˉ	I
    //   50: bipush 59
    //   52: iadd
    //   53: istore_1
    //   54: iload_1
    //   55: sipush 128
    //   58: irem
    //   59: putstatic 33	o/LU:ʽॱ	I
    //   62: iload_1
    //   63: iconst_2
    //   64: irem
    //   65: ifeq +6 -> 71
    //   68: goto +42 -> 110
    //   71: goto -68 -> 3
    //   74: aload_0
    //   75: invokespecial 557	o/Mg:onBackPressed	()V
    //   78: aload_0
    //   79: invokestatic 373	o/Ic:ˏ	(Landroid/content/Context;)Lo/Ic;
    //   82: astore_2
    //   83: aload_2
    //   84: iconst_0
    //   85: iconst_0
    //   86: invokevirtual 560	o/Ic:ˏ	(ZZ)Lo/j;
    //   89: astore_2
    //   90: aload_2
    //   91: ldc_w 561
    //   94: invokevirtual 564	o/j:ॱ	(I)Lo/j;
    //   97: astore_2
    //   98: aload_2
    //   99: invokevirtual 566	o/j:ˎ	()V
    //   102: aload_0
    //   103: invokevirtual 569	o/LU:finish	()V
    //   106: goto -59 -> 47
    //   109: return
    //   110: bipush 26
    //   112: istore_1
    //   113: goto -98 -> 15
    //   116: new 28	java/lang/NullPointerException
    //   119: dup
    //   120: invokespecial 31	java/lang/NullPointerException:<init>	()V
    //   123: athrow
    //   124: getstatic 35	o/LU:ˉ	I
    //   127: bipush 73
    //   129: iadd
    //   130: istore_1
    //   131: iload_1
    //   132: sipush 128
    //   135: irem
    //   136: putstatic 33	o/LU:ʽॱ	I
    //   139: iload_1
    //   140: iconst_2
    //   141: irem
    //   142: ifeq +6 -> 148
    //   145: goto +6 -> 151
    //   148: goto -74 -> 74
    //   151: goto -77 -> 74
    // Local variable table:
    //   start	length	slot	name	signature
    //   0	154	0	this	LU
    //   5	137	1	i	int
    //   9	2	2	localException1	Exception
    //   12	2	2	localException2	Exception
    //   82	17	2	localObject	Object
    // Exception table:
    //   from	to	target	type
    //   78	83	9	java/lang/Exception
    //   83	90	9	java/lang/Exception
    //   90	98	9	java/lang/Exception
    //   98	102	9	java/lang/Exception
    //   102	106	9	java/lang/Exception
    //   98	102	12	java/lang/Exception
  }
  
  /* Error */
  public void onConfirmClick(View paramView)
  {
    // Byte code:
    //   0: goto +477 -> 477
    //   3: aload_0
    //   4: aload_1
    //   5: iconst_1
    //   6: invokestatic 577	android/widget/Toast:makeText	(Landroid/content/Context;Ljava/lang/CharSequence;I)Landroid/widget/Toast;
    //   9: invokevirtual 580	android/widget/Toast:show	()V
    //   12: return
    //   13: aload_0
    //   14: aload 4
    //   16: iconst_4
    //   17: invokevirtual 99	java/lang/String:substring	(I)Ljava/lang/String;
    //   20: invokespecial 102	o/LU:ˎ	(Ljava/lang/String;)Ljava/lang/String;
    //   23: invokevirtual 106	java/lang/String:intern	()Ljava/lang/String;
    //   26: astore_1
    //   27: goto -24 -> 3
    //   30: aload_0
    //   31: getstatic 583	o/LV$If:receive_money_at_lest_one_card_digitized	I
    //   34: invokevirtual 149	o/LU:getString	(I)Ljava/lang/String;
    //   37: astore 5
    //   39: aload 5
    //   41: bipush 8
    //   43: newarray char
    //   45: dup
    //   46: iconst_0
    //   47: ldc -106
    //   49: castore
    //   50: dup
    //   51: iconst_1
    //   52: ldc -105
    //   54: castore
    //   55: dup
    //   56: iconst_2
    //   57: ldc -104
    //   59: castore
    //   60: dup
    //   61: iconst_3
    //   62: ldc -103
    //   64: castore
    //   65: dup
    //   66: iconst_4
    //   67: ldc -102
    //   69: castore
    //   70: dup
    //   71: iconst_5
    //   72: ldc -101
    //   74: castore
    //   75: dup
    //   76: bipush 6
    //   78: ldc -100
    //   80: castore
    //   81: dup
    //   82: bipush 7
    //   84: ldc -99
    //   86: castore
    //   87: invokestatic 159	o/LU:ˊ	([C)Ljava/lang/String;
    //   90: invokevirtual 106	java/lang/String:intern	()Ljava/lang/String;
    //   93: invokevirtual 163	java/lang/String:startsWith	(Ljava/lang/String;)Z
    //   96: ifeq +6 -> 102
    //   99: goto +200 -> 299
    //   102: goto +138 -> 240
    //   105: iload_2
    //   106: lookupswitch	default:+26->132, 4:+413->519, 41:+417->523
    //   132: goto +387 -> 519
    //   135: aload_0
    //   136: aload_1
    //   137: iconst_4
    //   138: invokevirtual 99	java/lang/String:substring	(I)Ljava/lang/String;
    //   141: invokespecial 102	o/LU:ˎ	(Ljava/lang/String;)Ljava/lang/String;
    //   144: invokevirtual 106	java/lang/String:intern	()Ljava/lang/String;
    //   147: astore_1
    //   148: goto +443 -> 591
    //   151: aload_0
    //   152: getstatic 583	o/LV$If:receive_money_at_lest_one_card_digitized	I
    //   155: invokevirtual 149	o/LU:getString	(I)Ljava/lang/String;
    //   158: astore_1
    //   159: aload_1
    //   160: bipush 8
    //   162: newarray char
    //   164: dup
    //   165: iconst_0
    //   166: ldc -106
    //   168: castore
    //   169: dup
    //   170: iconst_1
    //   171: ldc -105
    //   173: castore
    //   174: dup
    //   175: iconst_2
    //   176: ldc -104
    //   178: castore
    //   179: dup
    //   180: iconst_3
    //   181: ldc -103
    //   183: castore
    //   184: dup
    //   185: iconst_4
    //   186: ldc -102
    //   188: castore
    //   189: dup
    //   190: iconst_5
    //   191: ldc -101
    //   193: castore
    //   194: dup
    //   195: bipush 6
    //   197: ldc -100
    //   199: castore
    //   200: dup
    //   201: bipush 7
    //   203: ldc -99
    //   205: castore
    //   206: invokestatic 159	o/LU:ˊ	([C)Ljava/lang/String;
    //   209: invokevirtual 106	java/lang/String:intern	()Ljava/lang/String;
    //   212: invokevirtual 163	java/lang/String:startsWith	(Ljava/lang/String;)Z
    //   215: istore_3
    //   216: bipush 82
    //   218: iconst_0
    //   219: idiv
    //   220: istore_2
    //   221: iload_3
    //   222: ifeq +9 -> 231
    //   225: aload_1
    //   226: astore 4
    //   228: goto -215 -> 13
    //   231: goto -228 -> 3
    //   234: bipush 22
    //   236: istore_2
    //   237: goto +323 -> 560
    //   240: iconst_1
    //   241: istore_2
    //   242: goto +68 -> 310
    //   245: astore_1
    //   246: aload_1
    //   247: athrow
    //   248: iconst_4
    //   249: istore_2
    //   250: goto -145 -> 105
    //   253: getstatic 33	o/LU:ʽॱ	I
    //   256: bipush 97
    //   258: iadd
    //   259: istore_2
    //   260: iload_2
    //   261: sipush 128
    //   264: irem
    //   265: putstatic 35	o/LU:ˉ	I
    //   268: iload_2
    //   269: iconst_2
    //   270: irem
    //   271: ifne +6 -> 277
    //   274: goto -139 -> 135
    //   277: goto -142 -> 135
    //   280: aload_0
    //   281: getfield 49	o/LU:ॱˊ	Landroid/databinding/ViewDataBinding;
    //   284: checkcast 51	o/Mo
    //   287: invokevirtual 200	o/Mo:ˋॱ	()Z
    //   290: ifeq +6 -> 296
    //   293: goto +80 -> 373
    //   296: goto +184 -> 480
    //   299: iconst_0
    //   300: istore_2
    //   301: goto +9 -> 310
    //   304: bipush 41
    //   306: istore_2
    //   307: goto -202 -> 105
    //   310: aload 5
    //   312: astore_1
    //   313: aload 5
    //   315: astore 4
    //   317: iload_2
    //   318: tableswitch	default:+22->340, 0:+-305->13, 1:+-315->3
    //   340: aload 5
    //   342: astore_1
    //   343: goto -340 -> 3
    //   346: getstatic 33	o/LU:ʽॱ	I
    //   349: bipush 9
    //   351: iadd
    //   352: istore_2
    //   353: iload_2
    //   354: sipush 128
    //   357: irem
    //   358: putstatic 35	o/LU:ˉ	I
    //   361: iload_2
    //   362: iconst_2
    //   363: irem
    //   364: ifne +6 -> 370
    //   367: goto +104 -> 471
    //   370: goto -136 -> 234
    //   373: getstatic 586	o/LV$If:send_money_at_lest_one_card_added	I
    //   376: istore_2
    //   377: aload_0
    //   378: iload_2
    //   379: invokevirtual 149	o/LU:getString	(I)Ljava/lang/String;
    //   382: astore_1
    //   383: bipush 8
    //   385: newarray char
    //   387: dup
    //   388: iconst_0
    //   389: ldc -106
    //   391: castore
    //   392: dup
    //   393: iconst_1
    //   394: ldc -105
    //   396: castore
    //   397: dup
    //   398: iconst_2
    //   399: ldc -104
    //   401: castore
    //   402: dup
    //   403: iconst_3
    //   404: ldc -103
    //   406: castore
    //   407: dup
    //   408: iconst_4
    //   409: ldc -102
    //   411: castore
    //   412: dup
    //   413: iconst_5
    //   414: ldc -101
    //   416: castore
    //   417: dup
    //   418: bipush 6
    //   420: ldc -100
    //   422: castore
    //   423: dup
    //   424: bipush 7
    //   426: ldc -99
    //   428: castore
    //   429: invokestatic 159	o/LU:ˊ	([C)Ljava/lang/String;
    //   432: astore 4
    //   434: aload 4
    //   436: invokevirtual 106	java/lang/String:intern	()Ljava/lang/String;
    //   439: astore 4
    //   441: aload_1
    //   442: aload 4
    //   444: invokevirtual 163	java/lang/String:startsWith	(Ljava/lang/String;)Z
    //   447: istore_3
    //   448: iload_3
    //   449: ifeq +6 -> 455
    //   452: goto -199 -> 253
    //   455: goto +136 -> 591
    //   458: aload_1
    //   459: invokevirtual 591	android/view/View:isEnabled	()Z
    //   462: ifeq +6 -> 468
    //   465: goto -161 -> 304
    //   468: goto -220 -> 248
    //   471: bipush 8
    //   473: istore_2
    //   474: goto +86 -> 560
    //   477: goto +16 -> 493
    //   480: aload_0
    //   481: invokespecial 593	o/LU:ˋˋ	()Z
    //   484: ifne +6 -> 490
    //   487: goto -141 -> 346
    //   490: goto -32 -> 458
    //   493: getstatic 35	o/LU:ˉ	I
    //   496: iconst_1
    //   497: iadd
    //   498: istore_2
    //   499: iload_2
    //   500: sipush 128
    //   503: irem
    //   504: putstatic 33	o/LU:ʽॱ	I
    //   507: iload_2
    //   508: iconst_2
    //   509: irem
    //   510: ifeq +6 -> 516
    //   513: goto +7 -> 520
    //   516: goto -236 -> 280
    //   519: return
    //   520: goto -240 -> 280
    //   523: aload_0
    //   524: aload_0
    //   525: getfield 49	o/LU:ॱˊ	Landroid/databinding/ViewDataBinding;
    //   528: checkcast 51	o/Mo
    //   531: invokevirtual 209	o/Mo:ͺ	()Lo/FW;
    //   534: getfield 307	o/FW:totalAmount	D
    //   537: invokestatic 364	java/lang/String:valueOf	(D)Ljava/lang/String;
    //   540: aload_0
    //   541: getfield 49	o/LU:ॱˊ	Landroid/databinding/ViewDataBinding;
    //   544: checkcast 51	o/Mo
    //   547: invokevirtual 209	o/Mo:ͺ	()Lo/FW;
    //   550: getfield 323	o/FW:currency	Lo/Ep;
    //   553: invokevirtual 349	o/Ep:ˊ	()Ljava/lang/String;
    //   556: invokevirtual 596	o/LU:ˎ	(Ljava/lang/String;Ljava/lang/String;)V
    //   559: return
    //   560: iload_2
    //   561: lookupswitch	default:+27->588, 8:+-410->151, 22:+-531->30
    //   588: goto -558 -> 30
    //   591: aload_0
    //   592: aload_1
    //   593: iconst_1
    //   594: invokestatic 577	android/widget/Toast:makeText	(Landroid/content/Context;Ljava/lang/CharSequence;I)Landroid/widget/Toast;
    //   597: invokevirtual 580	android/widget/Toast:show	()V
    //   600: return
    // Local variable table:
    //   start	length	slot	name	signature
    //   0	601	0	this	LU
    //   0	601	1	paramView	View
    //   105	456	2	i	int
    //   215	234	3	bool	boolean
    //   14	429	4	localObject	Object
    //   37	304	5	str	String
    // Exception table:
    //   from	to	target	type
    //   373	377	245	java/lang/Exception
    //   377	383	245	java/lang/Exception
    //   383	434	245	java/lang/Exception
    //   434	441	245	java/lang/Exception
    //   441	448	245	java/lang/Exception
  }
  
  /* Error */
  public void onCreate(android.os.Bundle paramBundle)
  {
    // Byte code:
    //   0: goto +151 -> 151
    //   3: iconst_0
    //   4: istore_2
    //   5: goto +62 -> 67
    //   8: getstatic 33	o/LU:ʽॱ	I
    //   11: bipush 83
    //   13: iadd
    //   14: istore_2
    //   15: iload_2
    //   16: sipush 128
    //   19: irem
    //   20: putstatic 35	o/LU:ˉ	I
    //   23: iload_2
    //   24: iconst_2
    //   25: irem
    //   26: ifne +6 -> 32
    //   29: goto +33 -> 62
    //   32: goto +129 -> 161
    //   35: getstatic 35	o/LU:ˉ	I
    //   38: bipush 65
    //   40: iadd
    //   41: istore_2
    //   42: iload_2
    //   43: sipush 128
    //   46: irem
    //   47: putstatic 33	o/LU:ʽॱ	I
    //   50: iload_2
    //   51: iconst_2
    //   52: irem
    //   53: ifeq +6 -> 59
    //   56: goto -53 -> 3
    //   59: goto +133 -> 192
    //   62: iconst_0
    //   63: istore_2
    //   64: goto +60 -> 124
    //   67: iload_2
    //   68: tableswitch	default:+24->92, 0:+27->95, 1:+98->166
    //   92: goto +74 -> 166
    //   95: aload_0
    //   96: aload_1
    //   97: invokespecial 600	o/Mg:onCreate	(Landroid/os/Bundle;)V
    //   100: aload_0
    //   101: aload_0
    //   102: getfield 49	o/LU:ॱˊ	Landroid/databinding/ViewDataBinding;
    //   105: checkcast 51	o/Mo
    //   108: getfield 603	o/Mo:ͺ	Lo/у;
    //   111: invokevirtual 606	o/LU:ˊ	(Lo/у;)V
    //   114: aload_0
    //   115: invokespecial 608	o/LU:ˊᐝ	()V
    //   118: aconst_null
    //   119: arraylength
    //   120: istore_2
    //   121: goto -113 -> 8
    //   124: iload_2
    //   125: tableswitch	default:+23->148, 0:+29->154, 1:+35->160
    //   148: goto +6 -> 154
    //   151: goto -116 -> 35
    //   154: bipush 94
    //   156: iconst_0
    //   157: idiv
    //   158: istore_2
    //   159: return
    //   160: return
    //   161: iconst_1
    //   162: istore_2
    //   163: goto -39 -> 124
    //   166: aload_0
    //   167: aload_1
    //   168: invokespecial 600	o/Mg:onCreate	(Landroid/os/Bundle;)V
    //   171: aload_0
    //   172: aload_0
    //   173: getfield 49	o/LU:ॱˊ	Landroid/databinding/ViewDataBinding;
    //   176: checkcast 51	o/Mo
    //   179: getfield 603	o/Mo:ͺ	Lo/у;
    //   182: invokevirtual 606	o/LU:ˊ	(Lo/у;)V
    //   185: aload_0
    //   186: invokespecial 608	o/LU:ˊᐝ	()V
    //   189: goto -181 -> 8
    //   192: iconst_1
    //   193: istore_2
    //   194: goto -127 -> 67
    //   197: astore_1
    //   198: aload_1
    //   199: athrow
    // Local variable table:
    //   start	length	slot	name	signature
    //   0	200	0	this	LU
    //   0	200	1	paramBundle	android.os.Bundle
    //   4	190	2	i	int
    // Exception table:
    //   from	to	target	type
    //   35	42	197	java/lang/Exception
    //   42	50	197	java/lang/Exception
  }
  
  public void onEmptyPaymentCardClicked(View paramView)
  {
    break label405;
    for (;;)
    {
      i = 46 / 0;
      return;
      i = ʽॱ + 19;
      ˉ = i % 128;
      if (i % 2 == 0) {
        break label418;
      }
      break;
      label36:
      switch (i)
      {
      }
    }
    return;
    label64:
    int i = ʽॱ + 27;
    ˉ = i % 128;
    if (i % 2 != 0) {
      break label413;
    }
    label405:
    label413:
    label418:
    for (;;)
    {
      Ic.ˏ(this).ॱᐝ().ˏ(ˊ(new char[] { 26326, -359, 31006, 10185, 23768, -18303, 13068, 26292, 27100, -3987, 25705, 3112, 4762, 29356, -2774, -27669, -14095, 19645, -20675, -10761, -28954, 1704, 24888, 8189, 17649, -16194, 23357, 16887, 15097, -25950, 7463, -29715, -3859, 21682, -10456, -12821, -18720, 11940, -30401, -2079, 27872, -5964 }).intern()).ˎ();
      break label64;
      break;
      i = 1;
      break label36;
      i = 0;
      break label36;
    }
  }
  
  public void onNewIntent(Intent paramIntent)
  {
    break label116;
    int i = 49;
    switch (i)
    {
    default: 
      label9:
      break;
      label35:
      i = ˉ + 1;
      ʽॱ = i % 128;
      if (i % 2 == 0)
      {
        return;
        label59:
        i = 38;
        switch (i)
        {
        }
      }
      break;
    }
    for (;;)
    {
      label91:
      break label35;
      for (;;)
      {
        i = 1;
        break;
        ॱ(((Mo)this.ॱˊ).ͺ());
        break label91;
        label116:
        break label151;
        i = ʽॱ + 113;
        ˉ = i % 128;
        if (i % 2 == 0) {
          break label146;
        }
      }
      label146:
      i = 0;
      break label9;
      label151:
      super.onNewIntent(paramIntent);
      ˊˋ();
      if (((Mo)this.ॱˊ).ͺ().status == FV.INITIATED) {
        break;
      }
      break label59;
      i = null.length;
      return;
      ॱ(((Mo)this.ॱˊ).ͺ());
      i = null.length;
    }
  }
  
  /* Error */
  public boolean onOptionsItemSelected(android.view.MenuItem paramMenuItem)
  {
    // Byte code:
    //   0: goto +35 -> 35
    //   3: astore_1
    //   4: aload_1
    //   5: athrow
    //   6: aload_1
    //   7: invokeinterface 671 1 0
    //   12: istore_2
    //   13: aconst_null
    //   14: arraylength
    //   15: istore_3
    //   16: ldc_w 672
    //   19: iload_2
    //   20: if_icmpne +6 -> 26
    //   23: goto +108 -> 131
    //   26: goto +111 -> 137
    //   29: bipush 24
    //   31: istore_2
    //   32: goto +55 -> 87
    //   35: goto +108 -> 143
    //   38: aload_1
    //   39: invokeinterface 671 1 0
    //   44: istore_2
    //   45: ldc_w 672
    //   48: iload_2
    //   49: if_icmpne +6 -> 55
    //   52: goto +67 -> 119
    //   55: goto -26 -> 29
    //   58: iload_2
    //   59: lookupswitch	default:+25->84, 16:+111->170, 66:+66->125
    //   84: goto +86 -> 170
    //   87: iload_2
    //   88: lookupswitch	default:+28->116, 24:+82->170, 78:+37->125
    //   116: goto +9 -> 125
    //   119: bipush 78
    //   121: istore_2
    //   122: goto -35 -> 87
    //   125: aload_0
    //   126: invokevirtual 673	o/LU:onBackPressed	()V
    //   129: iconst_1
    //   130: ireturn
    //   131: bipush 66
    //   133: istore_2
    //   134: goto -76 -> 58
    //   137: bipush 16
    //   139: istore_2
    //   140: goto -82 -> 58
    //   143: getstatic 33	o/LU:ʽॱ	I
    //   146: bipush 85
    //   148: iadd
    //   149: istore_2
    //   150: iload_2
    //   151: sipush 128
    //   154: irem
    //   155: putstatic 35	o/LU:ˉ	I
    //   158: iload_2
    //   159: iconst_2
    //   160: irem
    //   161: ifne +6 -> 167
    //   164: goto -158 -> 6
    //   167: goto -129 -> 38
    //   170: aload_0
    //   171: aload_1
    //   172: invokespecial 675	o/Mg:onOptionsItemSelected	(Landroid/view/MenuItem;)Z
    //   175: istore 4
    //   177: getstatic 35	o/LU:ˉ	I
    //   180: bipush 13
    //   182: iadd
    //   183: istore_2
    //   184: iload_2
    //   185: sipush 128
    //   188: irem
    //   189: putstatic 33	o/LU:ʽॱ	I
    //   192: iload_2
    //   193: iconst_2
    //   194: irem
    //   195: ifeq +6 -> 201
    //   198: iload 4
    //   200: ireturn
    //   201: iload 4
    //   203: ireturn
    // Local variable table:
    //   start	length	slot	name	signature
    //   0	204	0	this	LU
    //   0	204	1	paramMenuItem	android.view.MenuItem
    //   12	183	2	i	int
    //   15	1	3	j	int
    //   175	27	4	bool	boolean
    // Exception table:
    //   from	to	target	type
    //   38	45	3	java/lang/Exception
    //   125	129	3	java/lang/Exception
  }
  
  public void onRejectClick(View paramView)
  {
    for (;;)
    {
      paramView = ˎ(paramView.substring(4)).intern();
      try
      {
        label19:
        int i = LV.If.reject_reason;
        String str1;
        String str2;
        try
        {
          str1 = getString(i);
          str2 = ˊ(new char[] { 4298, 13257, -2409, -15979, 4303, 15699, -5220, -5607 });
          boolean bool = str1.startsWith(str2.intern());
          if (bool) {
            break label256;
          }
        }
        catch (Exception paramView)
        {
          throw paramView;
        }
        i = 42;
        label140:
        label206:
        label246:
        label256:
        Context localContext;
        for (;;)
        {
          i = 1;
          for (;;)
          {
            i = ˉ + 11;
            ʽॱ = i % 128;
            if (i % 2 != 0) {
              break label246;
            }
            break;
            for (;;)
            {
              str2 = str1;
              switch (i)
              {
              default: 
                break label376;
                i = 62;
              }
            }
            paramView = ˎ(str1.substring(4)).intern();
            throw new NullPointerException();
            switch (i)
            {
            }
            str2 = ˎ(str1.substring(4)).intern();
          }
          i = 5;
          label376:
          do
          {
            i = 0;
            break label206;
            i = 37;
            break label140;
            switch (i)
            {
            case 5: 
            default: 
              break;
            }
            for (;;)
            {
              localContext = ॱˊ();
              paramView = getString(LV.If.reject_transaction);
              if (paramView.startsWith(ˊ(new char[] { 4298, 13257, -2409, -15979, 4303, 15699, -5220, -5607 }).intern())) {
                break;
              }
              break label19;
              break label403;
            }
            i = ˉ + 103;
            ʽॱ = i % 128;
          } while (i % 2 != 0);
        }
        label403:
        paramView = new KK(localContext, paramView, str2);
        paramView.ˏ();
        return;
      }
      catch (Exception paramView)
      {
        throw paramView;
      }
    }
  }
  
  /* Error */
  protected void ʻॱ()
  {
    // Byte code:
    //   0: goto +375 -> 375
    //   3: aload_2
    //   4: invokeinterface 696 1 0
    //   9: astore_2
    //   10: goto +17 -> 27
    //   13: astore_2
    //   14: aload_2
    //   15: invokevirtual 393	java/lang/Throwable:getCause	()Ljava/lang/Throwable;
    //   18: astore_3
    //   19: aload_3
    //   20: ifnull +5 -> 25
    //   23: aload_3
    //   24: athrow
    //   25: aload_2
    //   26: athrow
    //   27: aload_0
    //   28: invokevirtual 522	android/content/Context:getApplicationInfo	()Landroid/content/pm/ApplicationInfo;
    //   31: getfield 527	android/content/pm/ApplicationInfo:targetSdkVersion	I
    //   34: bipush 21
    //   36: isub
    //   37: aload_0
    //   38: invokevirtual 397	android/content/Context:getResources	()Landroid/content/res/Resources;
    //   41: ldc_w 697
    //   44: invokevirtual 401	android/content/res/Resources:getString	(I)Ljava/lang/String;
    //   47: iconst_0
    //   48: iconst_4
    //   49: invokevirtual 404	java/lang/String:substring	(II)Ljava/lang/String;
    //   52: invokevirtual 407	java/lang/String:length	()I
    //   55: sipush 263
    //   58: iadd
    //   59: aload_0
    //   60: invokevirtual 415	android/content/Context:getPackageName	()Ljava/lang/String;
    //   63: iconst_4
    //   64: invokevirtual 412	java/lang/String:codePointAt	(I)I
    //   67: sipush 14672
    //   70: iadd
    //   71: i2c
    //   72: invokestatic 421	o/O:ˋ	(IIC)Ljava/lang/Object;
    //   75: checkcast 423	java/lang/Class
    //   78: ldc_w 424
    //   81: aconst_null
    //   82: invokevirtual 428	java/lang/Class:getMethod	(Ljava/lang/String;[Ljava/lang/Class;)Ljava/lang/reflect/Method;
    //   85: aconst_null
    //   86: aconst_null
    //   87: invokevirtual 434	java/lang/reflect/Method:invoke	(Ljava/lang/Object;[Ljava/lang/Object;)Ljava/lang/Object;
    //   90: astore_3
    //   91: goto +17 -> 108
    //   94: astore_2
    //   95: aload_2
    //   96: invokevirtual 393	java/lang/Throwable:getCause	()Ljava/lang/Throwable;
    //   99: astore_3
    //   100: aload_3
    //   101: ifnull +5 -> 106
    //   104: aload_3
    //   105: athrow
    //   106: aload_2
    //   107: athrow
    //   108: aload_0
    //   109: invokevirtual 522	android/content/Context:getApplicationInfo	()Landroid/content/pm/ApplicationInfo;
    //   112: getfield 527	android/content/pm/ApplicationInfo:targetSdkVersion	I
    //   115: bipush 21
    //   117: isub
    //   118: aload_0
    //   119: invokevirtual 415	android/content/Context:getPackageName	()Ljava/lang/String;
    //   122: invokevirtual 407	java/lang/String:length	()I
    //   125: sipush 256
    //   128: iadd
    //   129: aload_0
    //   130: invokevirtual 397	android/content/Context:getResources	()Landroid/content/res/Resources;
    //   133: ldc_w 698
    //   136: invokevirtual 401	android/content/res/Resources:getString	(I)Ljava/lang/String;
    //   139: iconst_0
    //   140: iconst_5
    //   141: invokevirtual 404	java/lang/String:substring	(II)Ljava/lang/String;
    //   144: iconst_1
    //   145: invokevirtual 412	java/lang/String:codePointAt	(I)I
    //   148: sipush 14762
    //   151: iadd
    //   152: i2c
    //   153: invokestatic 421	o/O:ˋ	(IIC)Ljava/lang/Object;
    //   156: checkcast 423	java/lang/Class
    //   159: ldc_w 699
    //   162: iconst_1
    //   163: anewarray 423	java/lang/Class
    //   166: dup
    //   167: iconst_0
    //   168: ldc 81
    //   170: aastore
    //   171: invokevirtual 428	java/lang/Class:getMethod	(Ljava/lang/String;[Ljava/lang/Class;)Ljava/lang/reflect/Method;
    //   174: aload_3
    //   175: iconst_1
    //   176: anewarray 360	java/lang/Object
    //   179: dup
    //   180: iconst_0
    //   181: aload_2
    //   182: aastore
    //   183: invokevirtual 434	java/lang/reflect/Method:invoke	(Ljava/lang/Object;[Ljava/lang/Object;)Ljava/lang/Object;
    //   186: checkcast 693	com/insidesecure/hce/MatrixHCECard
    //   189: astore_2
    //   190: aload_2
    //   191: ifnull +6 -> 197
    //   194: goto +151 -> 345
    //   197: goto +86 -> 283
    //   200: aload_0
    //   201: invokespecial 664	o/LU:ˊˋ	()V
    //   204: return
    //   205: astore_2
    //   206: aload_2
    //   207: athrow
    //   208: aload_0
    //   209: getfield 49	o/LU:ॱˊ	Landroid/databinding/ViewDataBinding;
    //   212: astore_2
    //   213: aload_2
    //   214: checkcast 51	o/Mo
    //   217: astore_2
    //   218: aload_2
    //   219: invokevirtual 209	o/Mo:ͺ	()Lo/FW;
    //   222: astore_2
    //   223: aload_0
    //   224: aload_2
    //   225: invokevirtual 174	o/LU:ˏ	(Lo/FW;)Lcom/insidesecure/hce/MatrixHCECard;
    //   228: astore_2
    //   229: aload_2
    //   230: ifnull +6 -> 236
    //   233: goto +145 -> 378
    //   236: goto +38 -> 274
    //   239: iload_1
    //   240: lookupswitch	default:+28->268, 8:+-237->3, 43:+-40->200
    //   268: goto -265 -> 3
    //   271: goto -71 -> 200
    //   274: bipush 43
    //   276: istore_1
    //   277: goto -38 -> 239
    //   280: goto -80 -> 200
    //   283: iconst_0
    //   284: istore_1
    //   285: goto +99 -> 384
    //   288: getstatic 35	o/LU:ˉ	I
    //   291: bipush 47
    //   293: iadd
    //   294: istore_1
    //   295: iload_1
    //   296: sipush 128
    //   299: irem
    //   300: putstatic 33	o/LU:ʽॱ	I
    //   303: iload_1
    //   304: iconst_2
    //   305: irem
    //   306: ifeq +6 -> 312
    //   309: goto +33 -> 342
    //   312: goto +41 -> 353
    //   315: getstatic 33	o/LU:ʽॱ	I
    //   318: bipush 57
    //   320: iadd
    //   321: istore_1
    //   322: iload_1
    //   323: sipush 128
    //   326: irem
    //   327: putstatic 35	o/LU:ˉ	I
    //   330: iload_1
    //   331: iconst_2
    //   332: irem
    //   333: ifne +6 -> 339
    //   336: goto -65 -> 271
    //   339: goto -59 -> 280
    //   342: goto +11 -> 353
    //   345: iconst_1
    //   346: istore_1
    //   347: goto +37 -> 384
    //   350: astore_2
    //   351: aload_2
    //   352: athrow
    //   353: aload_0
    //   354: getfield 49	o/LU:ॱˊ	Landroid/databinding/ViewDataBinding;
    //   357: checkcast 51	o/Mo
    //   360: invokevirtual 209	o/Mo:ͺ	()Lo/FW;
    //   363: aload_2
    //   364: invokeinterface 696 1 0
    //   369: invokevirtual 701	o/FW:ˋ	(Ljava/lang/String;)V
    //   372: goto -57 -> 315
    //   375: goto -167 -> 208
    //   378: bipush 8
    //   380: istore_1
    //   381: goto -142 -> 239
    //   384: iload_1
    //   385: tableswitch	default:+23->408, 0:+-185->200, 1:+-97->288
    //   408: goto -120 -> 288
    // Local variable table:
    //   start	length	slot	name	signature
    //   0	411	0	this	LU
    //   239	146	1	i	int
    //   3	7	2	str	String
    //   13	13	2	localObject1	Object
    //   94	88	2	localObject2	Object
    //   189	2	2	localMatrixHCECard	com.insidesecure.hce.MatrixHCECard
    //   205	2	2	localException1	Exception
    //   212	18	2	localObject3	Object
    //   350	14	2	localException2	Exception
    //   18	157	3	localObject4	Object
    // Exception table:
    //   from	to	target	type
    //   27	91	13	finally
    //   108	190	94	finally
    //   208	213	205	java/lang/Exception
    //   213	218	205	java/lang/Exception
    //   218	223	205	java/lang/Exception
    //   223	229	205	java/lang/Exception
    //   315	330	205	java/lang/Exception
    //   213	218	350	java/lang/Exception
  }
  
  @zA(ˎ=ThreadMode.MAIN)
  public void ˊ(Ef paramEf)
  {
    for (;;)
    {
      switch (i)
      {
      default: 
        break;
      case 0: 
        for (;;)
        {
          i = ʽॱ + 105;
          ˉ = i % 128;
          if (i % 2 == 0) {
            break label99;
          }
          break label78;
          this.ʼॱ = paramEf.ˊ();
          ˌ();
          throw new NullPointerException();
          label78:
          i = 1;
          break;
        }
      }
      this.ʼॱ = paramEf.ˊ();
      ˌ();
      return;
      label99:
      int i = 0;
    }
  }
  
  /* Error */
  public void ˋ(ز paramز)
  {
    // Byte code:
    //   0: goto +47 -> 47
    //   3: bipush 85
    //   5: istore_2
    //   6: goto +168 -> 174
    //   9: goto +41 -> 50
    //   12: astore_1
    //   13: aload_1
    //   14: athrow
    //   15: bipush 52
    //   17: istore_2
    //   18: goto +156 -> 174
    //   21: aload_1
    //   22: iconst_1
    //   23: invokevirtual 715	o/ز:ॱ	(Z)V
    //   26: aload_1
    //   27: iconst_1
    //   28: invokevirtual 716	o/ز:ˏ	(Z)V
    //   31: aload_0
    //   32: invokevirtual 719	o/LU:ʻ	()Lo/ز;
    //   35: ifnull +6 -> 41
    //   38: goto +63 -> 101
    //   41: goto +55 -> 96
    //   44: goto -23 -> 21
    //   47: goto +100 -> 147
    //   50: getstatic 35	o/LU:ˉ	I
    //   53: bipush 87
    //   55: iadd
    //   56: istore_2
    //   57: iload_2
    //   58: sipush 128
    //   61: irem
    //   62: putstatic 33	o/LU:ʽॱ	I
    //   65: iload_2
    //   66: iconst_2
    //   67: irem
    //   68: ifeq +6 -> 74
    //   71: goto +24 -> 95
    //   74: return
    //   75: aload_0
    //   76: invokevirtual 719	o/LU:ʻ	()Lo/ز;
    //   79: astore_1
    //   80: aload_0
    //   81: invokevirtual 721	o/LU:ˊˊ	()Z
    //   84: istore_3
    //   85: iload_3
    //   86: ifeq +6 -> 92
    //   89: goto -74 -> 15
    //   92: goto -89 -> 3
    //   95: return
    //   96: iconst_1
    //   97: istore_2
    //   98: goto +15 -> 113
    //   101: iconst_0
    //   102: istore_2
    //   103: goto +10 -> 113
    //   106: getstatic 726	o/LV$ˋ:ic_white_close	I
    //   109: istore_2
    //   110: goto +29 -> 139
    //   113: iload_2
    //   114: tableswitch	default:+22->136, 0:+-39->75, 1:+-105->9
    //   136: goto -61 -> 75
    //   139: aload_1
    //   140: iload_2
    //   141: invokevirtual 728	o/ز:ˏ	(I)V
    //   144: goto -135 -> 9
    //   147: getstatic 33	o/LU:ʽॱ	I
    //   150: bipush 89
    //   152: iadd
    //   153: istore_2
    //   154: iload_2
    //   155: sipush 128
    //   158: irem
    //   159: putstatic 35	o/LU:ˉ	I
    //   162: iload_2
    //   163: iconst_2
    //   164: irem
    //   165: ifne +6 -> 171
    //   168: goto -124 -> 44
    //   171: goto -150 -> 21
    //   174: iload_2
    //   175: lookupswitch	default:+25->200, 52:+25->200, 85:+-69->106
    //   200: getstatic 731	o/LV$ˋ:ic_back_white	I
    //   203: istore_2
    //   204: goto -65 -> 139
    // Local variable table:
    //   start	length	slot	name	signature
    //   0	207	0	this	LU
    //   0	207	1	paramز	ز
    //   5	199	2	i	int
    //   84	2	3	bool	boolean
    // Exception table:
    //   from	to	target	type
    //   75	80	12	java/lang/Exception
    //   80	85	12	java/lang/Exception
    //   200	204	12	java/lang/Exception
  }
  
  public int ˎ()
  {
    break label51;
    return LV.iF.activity_accept_request_money;
    int i = 1;
    break label23;
    label12:
    i = LV.iF.activity_accept_request_money;
    int j = 62 / 0;
    return i;
    for (;;)
    {
      label23:
      switch (i)
      {
      }
      break label12;
      label51:
      i = ʽॱ + 55;
      ˉ = i % 128;
      if (i % 2 == 0) {
        break;
      }
      i = 0;
    }
  }
  
  protected void ˎ(BigDecimal paramBigDecimal)
  {
    int i;
    label62:
    Double localDouble;
    for (;;)
    {
      i = ˉ + 69;
      ʽॱ = i % 128;
      if (i % 2 == 0)
      {
        break label123;
        i = ʽॱ + 85;
        ˉ = i % 128;
        if (i % 2 == 0) {
          break label201;
        }
        break label62;
        i = 1;
        break label177;
        i = 1;
        break;
      }
      break label123;
      ˊ(paramBigDecimal, localDouble.doubleValue(), false, false);
      return;
    }
    label85:
    ˊ(paramBigDecimal, localDouble.doubleValue(), false, true);
    return;
    for (;;)
    {
      switch (i)
      {
      }
      break label85;
      label123:
      ˋ(paramBigDecimal);
      paramBigDecimal = HQ.ˏ(((Mo)this.ॱˊ).ʻ.ॱॱ());
      localDouble = Double.valueOf(((Mo)this.ॱˊ).ͺ().totalAmount);
      if (paramBigDecimal.ˊᐝ()) {
        break;
      }
      i = 0;
      label177:
      switch (i)
      {
      }
      return;
      label201:
      i = 0;
    }
  }
  
  protected void ˎ(FW paramFW, FS paramFS)
  {
    for (;;)
    {
      try
      {
        paramFW = this.ॱˊ;
        try
        {
          paramFW = (Mo)paramFW;
          paramFW = paramFW.ͺ();
          ॱ(paramFW);
          continue;
          switch (i)
          {
          case 53: 
          default: 
            break;
          }
          continue;
          continue;
          throw new NullPointerException();
          i = ˉ + 29;
          ʽॱ = i % 128;
          if (i % 2 != 0) {
            break label187;
          }
          break label138;
          i = 0;
          break label237;
          i = 35;
          continue;
          i = ʽॱ + 59;
          ˉ = i % 128;
          if (i % 2 == 0) {
            continue;
          }
          return;
        }
        catch (Exception paramFW)
        {
          throw paramFW;
        }
        ˊ(paramFW, paramFS);
      }
      catch (Exception paramFW)
      {
        throw paramFW;
      }
      label138:
      ˊˋ();
      ˉ();
      paramFW = ((Mo)this.ॱˊ).ͺ().status;
      paramFS = FV.INITIATED;
      if (paramFW != paramFS) {}
      int i = 53;
      continue;
      label187:
      ˊ(paramFW, paramFS);
      ˊˋ();
      ˉ();
      paramFW = ((Mo)this.ॱˊ).ͺ().status;
      paramFS = FV.INITIATED;
      i = 89 / 0;
      if (paramFW != paramFS) {}
      i = 1;
      label237:
      switch (i)
      {
      }
    }
  }
  
  protected void ˎ(boolean paramBoolean)
  {
    break label47;
    KZ localKZ;
    try
    {
      String str1;
      localKZ.setPaymentHint(str1);
    }
    catch (Exception localException1)
    {
      try
      {
        ((Mo)this.ॱˊ).ʻ.ʽ().setCompoundDrawablesWithIntrinsicBounds(ᔆ.ˎ(ॱˊ(), LV.ˋ.ic_error), null, null, null);
      }
      catch (Exception localException2)
      {
        throw localException2;
      }
      localException1 = localException1;
      throw localException1;
    }
    for (;;)
    {
      label47:
      i = ˉ + 13;
      ʽॱ = i % 128;
      if (i % 2 != 0) {
        break;
      }
      break;
      label74:
      i = 1;
      break label169;
      label79:
      new MC(this).ˏ();
    }
    label94:
    int i = 1;
    for (;;)
    {
      i = 0;
      break label217;
      for (;;)
      {
        break;
        String str2 = str3.substring(4);
        str2 = ˎ(str2);
        str2 = str2.intern();
        for (;;)
        {
          i = 0;
          break label169;
          break;
          break label196;
          i = ʽॱ + 125;
          ˉ = i % 128;
          if (i % 2 == 0) {
            break label74;
          }
        }
        label169:
        switch (i)
        {
        }
      }
      return;
      label196:
      ((Mo)this.ॱˊ).ॱ(false);
      if (paramBoolean) {
        break label79;
      }
      break label250;
      label217:
      Object localObject = str3;
      switch (i)
      {
      }
      localObject = str3;
      break;
      label250:
      localKZ = ((Mo)this.ॱˊ).ʻ;
      String str3 = getString(LV.If.insufficient_funds_for_this_card);
      if (str3.startsWith(ˊ(new char[] { 4298, 13257, -2409, -15979, 4303, 15699, -5220, -5607 }).intern())) {
        break label94;
      }
    }
  }
  
  /* Error */
  protected void ॱ(boolean paramBoolean)
  {
    // Byte code:
    //   0: goto +342 -> 342
    //   3: iconst_1
    //   4: istore_2
    //   5: goto +226 -> 231
    //   8: aload_0
    //   9: getfield 49	o/LU:ॱˊ	Landroid/databinding/ViewDataBinding;
    //   12: checkcast 51	o/Mo
    //   15: getfield 55	o/Mo:ʻ	Lo/KZ;
    //   18: astore 5
    //   20: aload_0
    //   21: getstatic 778	o/LV$If:select_the_card_and_transfer	I
    //   24: invokevirtual 149	o/LU:getString	(I)Ljava/lang/String;
    //   27: astore 4
    //   29: aload 4
    //   31: bipush 8
    //   33: newarray char
    //   35: dup
    //   36: iconst_0
    //   37: ldc -106
    //   39: castore
    //   40: dup
    //   41: iconst_1
    //   42: ldc -105
    //   44: castore
    //   45: dup
    //   46: iconst_2
    //   47: ldc -104
    //   49: castore
    //   50: dup
    //   51: iconst_3
    //   52: ldc -103
    //   54: castore
    //   55: dup
    //   56: iconst_4
    //   57: ldc -102
    //   59: castore
    //   60: dup
    //   61: iconst_5
    //   62: ldc -101
    //   64: castore
    //   65: dup
    //   66: bipush 6
    //   68: ldc -100
    //   70: castore
    //   71: dup
    //   72: bipush 7
    //   74: ldc -99
    //   76: castore
    //   77: invokestatic 159	o/LU:ˊ	([C)Ljava/lang/String;
    //   80: invokevirtual 106	java/lang/String:intern	()Ljava/lang/String;
    //   83: invokevirtual 163	java/lang/String:startsWith	(Ljava/lang/String;)Z
    //   86: ifeq +6 -> 92
    //   89: goto +108 -> 197
    //   92: goto +69 -> 161
    //   95: getstatic 33	o/LU:ʽॱ	I
    //   98: bipush 45
    //   100: iadd
    //   101: istore_2
    //   102: iload_2
    //   103: sipush 128
    //   106: irem
    //   107: putstatic 35	o/LU:ˉ	I
    //   110: iload_2
    //   111: iconst_2
    //   112: irem
    //   113: ifne +6 -> 119
    //   116: goto +78 -> 194
    //   119: goto +105 -> 224
    //   122: return
    //   123: iconst_0
    //   124: istore_2
    //   125: goto +106 -> 231
    //   128: astore_3
    //   129: aload_3
    //   130: athrow
    //   131: getstatic 33	o/LU:ʽॱ	I
    //   134: bipush 9
    //   136: iadd
    //   137: istore_2
    //   138: iload_2
    //   139: sipush 128
    //   142: irem
    //   143: putstatic 35	o/LU:ˉ	I
    //   146: iload_2
    //   147: iconst_2
    //   148: irem
    //   149: ifne +6 -> 155
    //   152: goto +107 -> 259
    //   155: goto +48 -> 203
    //   158: astore_3
    //   159: aload_3
    //   160: athrow
    //   161: bipush 36
    //   163: istore_2
    //   164: goto +143 -> 307
    //   167: getstatic 35	o/LU:ˉ	I
    //   170: bipush 51
    //   172: iadd
    //   173: istore_2
    //   174: iload_2
    //   175: sipush 128
    //   178: irem
    //   179: putstatic 33	o/LU:ʽॱ	I
    //   182: iload_2
    //   183: iconst_2
    //   184: irem
    //   185: ifeq +6 -> 191
    //   188: goto +116 -> 304
    //   191: goto +29 -> 220
    //   194: goto +30 -> 224
    //   197: bipush 41
    //   199: istore_2
    //   200: goto +107 -> 307
    //   203: aload_0
    //   204: aload 4
    //   206: iconst_4
    //   207: invokevirtual 99	java/lang/String:substring	(I)Ljava/lang/String;
    //   210: invokespecial 102	o/LU:ˎ	(Ljava/lang/String;)Ljava/lang/String;
    //   213: invokevirtual 106	java/lang/String:intern	()Ljava/lang/String;
    //   216: astore_3
    //   217: goto +45 -> 262
    //   220: return
    //   221: goto -213 -> 8
    //   224: aload_0
    //   225: invokespecial 780	o/LU:ˍ	()V
    //   228: goto -61 -> 167
    //   231: iload_2
    //   232: tableswitch	default:+24->256, 0:+-110->122, 1:+-137->95
    //   256: goto -161 -> 95
    //   259: goto -56 -> 203
    //   262: aload 5
    //   264: aload_3
    //   265: invokevirtual 751	o/KZ:setPaymentHint	(Ljava/lang/String;)V
    //   268: aload_0
    //   269: getfield 49	o/LU:ॱˊ	Landroid/databinding/ViewDataBinding;
    //   272: astore_3
    //   273: aload_3
    //   274: checkcast 51	o/Mo
    //   277: astore_3
    //   278: aload_3
    //   279: getfield 55	o/Mo:ʻ	Lo/KZ;
    //   282: astore_3
    //   283: aload_3
    //   284: invokevirtual 754	o/KZ:ʽ	()Landroid/widget/TextView;
    //   287: aconst_null
    //   288: aconst_null
    //   289: aconst_null
    //   290: aconst_null
    //   291: invokevirtual 766	android/widget/TextView:setCompoundDrawablesWithIntrinsicBounds	(Landroid/graphics/drawable/Drawable;Landroid/graphics/drawable/Drawable;Landroid/graphics/drawable/Drawable;Landroid/graphics/drawable/Drawable;)V
    //   294: iload_1
    //   295: ifeq +6 -> 301
    //   298: goto -295 -> 3
    //   301: goto -178 -> 123
    //   304: goto -84 -> 220
    //   307: aload 4
    //   309: astore_3
    //   310: iload_2
    //   311: lookupswitch	default:+25->336, 36:+-49->262, 41:+-180->131
    //   336: aload 4
    //   338: astore_3
    //   339: goto -77 -> 262
    //   342: getstatic 33	o/LU:ʽॱ	I
    //   345: bipush 125
    //   347: iadd
    //   348: istore_2
    //   349: iload_2
    //   350: sipush 128
    //   353: irem
    //   354: putstatic 35	o/LU:ˉ	I
    //   357: iload_2
    //   358: iconst_2
    //   359: irem
    //   360: ifne +6 -> 366
    //   363: goto -142 -> 221
    //   366: goto -358 -> 8
    // Local variable table:
    //   start	length	slot	name	signature
    //   0	369	0	this	LU
    //   0	369	1	paramBoolean	boolean
    //   4	356	2	i	int
    //   128	2	3	localException1	Exception
    //   158	2	3	localException2	Exception
    //   216	123	3	localObject	Object
    //   27	310	4	str	String
    //   18	245	5	localKZ	KZ
    // Exception table:
    //   from	to	target	type
    //   278	283	128	java/lang/Exception
    //   262	268	158	java/lang/Exception
    //   268	273	158	java/lang/Exception
    //   273	278	158	java/lang/Exception
    //   278	283	158	java/lang/Exception
    //   283	294	158	java/lang/Exception
  }
  
  /* Error */
  protected void ॱˋ()
  {
    // Byte code:
    //   0: goto +206 -> 206
    //   3: aload_0
    //   4: aload_2
    //   5: iconst_1
    //   6: invokestatic 577	android/widget/Toast:makeText	(Landroid/content/Context;Ljava/lang/CharSequence;I)Landroid/widget/Toast;
    //   9: astore_2
    //   10: aload_2
    //   11: invokevirtual 580	android/widget/Toast:show	()V
    //   14: goto +37 -> 51
    //   17: astore_2
    //   18: aload_2
    //   19: athrow
    //   20: goto +59 -> 79
    //   23: aload_3
    //   24: astore_2
    //   25: iload_1
    //   26: tableswitch	default:+22->48, 0:+183->209, 1:+-23->3
    //   48: goto +161 -> 209
    //   51: getstatic 33	o/LU:ʽॱ	I
    //   54: bipush 81
    //   56: iadd
    //   57: istore_1
    //   58: iload_1
    //   59: sipush 128
    //   62: irem
    //   63: putstatic 35	o/LU:ˉ	I
    //   66: iload_1
    //   67: iconst_2
    //   68: irem
    //   69: ifne +4 -> 73
    //   72: return
    //   73: return
    //   74: iconst_0
    //   75: istore_1
    //   76: goto -53 -> 23
    //   79: aload_0
    //   80: getfield 49	o/LU:ॱˊ	Landroid/databinding/ViewDataBinding;
    //   83: checkcast 51	o/Mo
    //   86: getstatic 785	java/math/BigDecimal:ZERO	Ljava/math/BigDecimal;
    //   89: invokevirtual 228	o/Mo:ˎ	(Ljava/math/BigDecimal;)V
    //   92: aload_0
    //   93: getfield 49	o/LU:ॱˊ	Landroid/databinding/ViewDataBinding;
    //   96: checkcast 51	o/Mo
    //   99: iconst_0
    //   100: invokevirtual 95	o/Mo:ॱ	(Z)V
    //   103: aload_0
    //   104: getstatic 788	o/LV$If:invalid_p2p_operation	I
    //   107: invokevirtual 149	o/LU:getString	(I)Ljava/lang/String;
    //   110: astore_3
    //   111: aload_3
    //   112: bipush 8
    //   114: newarray char
    //   116: dup
    //   117: iconst_0
    //   118: ldc -106
    //   120: castore
    //   121: dup
    //   122: iconst_1
    //   123: ldc -105
    //   125: castore
    //   126: dup
    //   127: iconst_2
    //   128: ldc -104
    //   130: castore
    //   131: dup
    //   132: iconst_3
    //   133: ldc -103
    //   135: castore
    //   136: dup
    //   137: iconst_4
    //   138: ldc -102
    //   140: castore
    //   141: dup
    //   142: iconst_5
    //   143: ldc -101
    //   145: castore
    //   146: dup
    //   147: bipush 6
    //   149: ldc -100
    //   151: castore
    //   152: dup
    //   153: bipush 7
    //   155: ldc -99
    //   157: castore
    //   158: invokestatic 159	o/LU:ˊ	([C)Ljava/lang/String;
    //   161: invokevirtual 106	java/lang/String:intern	()Ljava/lang/String;
    //   164: invokevirtual 163	java/lang/String:startsWith	(Ljava/lang/String;)Z
    //   167: ifeq +6 -> 173
    //   170: goto -96 -> 74
    //   173: goto +54 -> 227
    //   176: getstatic 35	o/LU:ˉ	I
    //   179: bipush 81
    //   181: iadd
    //   182: istore_1
    //   183: iload_1
    //   184: sipush 128
    //   187: irem
    //   188: putstatic 33	o/LU:ʽॱ	I
    //   191: iload_1
    //   192: iconst_2
    //   193: irem
    //   194: ifeq +6 -> 200
    //   197: goto -177 -> 20
    //   200: goto -121 -> 79
    //   203: astore_2
    //   204: aload_2
    //   205: athrow
    //   206: goto -30 -> 176
    //   209: aload_0
    //   210: aload_3
    //   211: iconst_4
    //   212: invokevirtual 99	java/lang/String:substring	(I)Ljava/lang/String;
    //   215: invokespecial 102	o/LU:ˎ	(Ljava/lang/String;)Ljava/lang/String;
    //   218: astore_2
    //   219: aload_2
    //   220: invokevirtual 106	java/lang/String:intern	()Ljava/lang/String;
    //   223: astore_2
    //   224: goto -221 -> 3
    //   227: iconst_1
    //   228: istore_1
    //   229: goto -206 -> 23
    // Local variable table:
    //   start	length	slot	name	signature
    //   0	232	0	this	LU
    //   25	204	1	i	int
    //   4	7	2	localObject1	Object
    //   17	2	2	localException1	Exception
    //   24	1	2	localObject2	Object
    //   203	2	2	localException2	Exception
    //   218	6	2	str1	String
    //   23	188	3	str2	String
    // Exception table:
    //   from	to	target	type
    //   209	219	17	java/lang/Exception
    //   219	224	17	java/lang/Exception
    //   3	10	203	java/lang/Exception
    //   10	14	203	java/lang/Exception
  }
}
