package o;

import android.content.Context;
import android.content.Intent;
import android.content.pm.ApplicationInfo;
import android.content.res.Resources;
import android.databinding.ViewDataBinding;
import android.os.Bundle;
import java.util.ArrayList;
import java.util.Collection;
import java.util.Iterator;
import java.util.List;

public final class Lv
  extends IB<LA>
{
  public static final ˋ ʿ;
  private static byte ˈ;
  private static char[] ˉ;
  private static int ˊˊ;
  private static long ˊˋ;
  private static int ˋˊ;
  private ArrayList<FM> ʼॱ;
  private FM ʽॱ;
  private Lx ʾ;
  
  static
  {
    for (;;)
    {
      int i = ˋˊ + 59;
      ˊˊ = i % 128;
      if (i % 2 != 0) {
        return;
      }
      return;
      ˋˊ = 0;
      ˊˊ = 1;
      ॱˋ();
      ʻॱ();
      ʿ = new ˋ(null);
    }
  }
  
  public Lv() {}
  
  static void ʻॱ()
  {
    break label109;
    for (;;)
    {
      switch (i)
      {
      default: 
        break;
      case 4: 
        return;
        for (;;)
        {
          i = ˊˊ + 99;
          ˋˊ = i % 128;
          if (i % 2 != 0) {
            break label76;
          }
          i = 4;
          break;
          ˈ = -102;
        }
        label76:
        i = 74;
      }
    }
    label109:
    for (;;)
    {
      i = ˊˊ + 87;
      ˋˊ = i % 128;
      if (i % 2 != 0) {
        break;
      }
      break;
    }
    int i = null.length;
  }
  
  /* Error */
  private final void ʾ()
  {
    // Byte code:
    //   0: goto +537 -> 537
    //   3: iconst_1
    //   4: istore_1
    //   5: goto +145 -> 150
    //   8: goto +79 -> 87
    //   11: goto +76 -> 87
    //   14: iconst_0
    //   15: istore_1
    //   16: goto +483 -> 499
    //   19: aload_2
    //   20: aload_3
    //   21: checkcast 59	android/support/v7/widget/RecyclerView$ˊ
    //   24: invokevirtual 65	o/aH:setAdapter	(Landroid/support/v7/widget/RecyclerView$ˊ;)V
    //   27: aload_0
    //   28: getfield 69	o/Lv:ॱˊ	Landroid/databinding/ViewDataBinding;
    //   31: checkcast 71	o/LA
    //   34: getfield 75	o/LA:ˊ	Lo/aH;
    //   37: aload_0
    //   38: getfield 69	o/Lv:ॱˊ	Landroid/databinding/ViewDataBinding;
    //   41: checkcast 71	o/LA
    //   44: getfield 79	o/LA:ॱ	Landroid/widget/TextView;
    //   47: checkcast 81	android/view/View
    //   50: invokevirtual 85	o/aH:setEmptyView	(Landroid/view/View;)V
    //   53: new 87	o/ᔄ
    //   56: dup
    //   57: aload_0
    //   58: invokevirtual 90	o/Lv:ॱˊ	()Landroid/content/Context;
    //   61: iconst_1
    //   62: invokespecial 93	o/ᔄ:<init>	(Landroid/content/Context;I)V
    //   65: astore_2
    //   66: aload_0
    //   67: checkcast 95	android/content/Context
    //   70: getstatic 100	o/Lt$iF:recycler_item_divider	I
    //   73: invokestatic 106	o/ᔆ:ˎ	(Landroid/content/Context;I)Landroid/graphics/drawable/Drawable;
    //   76: astore_3
    //   77: aload_3
    //   78: ifnull +6 -> 84
    //   81: goto -78 -> 3
    //   84: goto +448 -> 532
    //   87: aload_0
    //   88: getfield 69	o/Lv:ॱˊ	Landroid/databinding/ViewDataBinding;
    //   91: checkcast 71	o/LA
    //   94: getfield 75	o/LA:ˊ	Lo/aH;
    //   97: aload_2
    //   98: checkcast 108	android/support/v7/widget/RecyclerView$ˎ
    //   101: invokevirtual 112	o/aH:ˏ	(Landroid/support/v7/widget/RecyclerView$ˎ;)V
    //   104: aload_0
    //   105: invokespecial 114	o/Lv:ˋˊ	()V
    //   108: goto +17 -> 125
    //   111: astore_2
    //   112: aload_2
    //   113: athrow
    //   114: goto +303 -> 417
    //   117: aload_2
    //   118: aload_3
    //   119: invokevirtual 117	o/ᔄ:ॱ	(Landroid/graphics/drawable/Drawable;)V
    //   122: goto -114 -> 8
    //   125: getstatic 38	o/Lv:ˊˊ	I
    //   128: bipush 77
    //   130: iadd
    //   131: istore_1
    //   132: iload_1
    //   133: sipush 128
    //   136: irem
    //   137: putstatic 36	o/Lv:ˋˊ	I
    //   140: iload_1
    //   141: iconst_2
    //   142: irem
    //   143: ifeq +6 -> 149
    //   146: goto +56 -> 202
    //   149: return
    //   150: iload_1
    //   151: tableswitch	default:+21->172, 0:+-140->11, 1:+-34->117
    //   172: goto -55 -> 117
    //   175: getstatic 38	o/Lv:ˊˊ	I
    //   178: bipush 121
    //   180: iadd
    //   181: istore_1
    //   182: iload_1
    //   183: sipush 128
    //   186: irem
    //   187: putstatic 36	o/Lv:ˋˊ	I
    //   190: iload_1
    //   191: iconst_2
    //   192: irem
    //   193: ifeq +6 -> 199
    //   196: goto -82 -> 114
    //   199: goto +218 -> 417
    //   202: return
    //   203: astore_2
    //   204: aload_2
    //   205: athrow
    //   206: new 119	o/Lx
    //   209: dup
    //   210: invokespecial 120	o/Lx:<init>	()V
    //   213: astore_2
    //   214: aload_0
    //   215: aload_2
    //   216: putfield 122	o/Lv:ʾ	Lo/Lx;
    //   219: aload_0
    //   220: getfield 69	o/Lv:ॱˊ	Landroid/databinding/ViewDataBinding;
    //   223: astore_2
    //   224: aload_2
    //   225: checkcast 71	o/LA
    //   228: astore_2
    //   229: aload_2
    //   230: getfield 75	o/LA:ˊ	Lo/aH;
    //   233: astore_2
    //   234: aload_2
    //   235: aload_0
    //   236: invokevirtual 126	android/content/Context:getResources	()Landroid/content/res/Resources;
    //   239: ldc 127
    //   241: invokevirtual 133	android/content/res/Resources:getString	(I)Ljava/lang/String;
    //   244: iconst_0
    //   245: iconst_4
    //   246: invokevirtual 139	java/lang/String:substring	(II)Ljava/lang/String;
    //   249: iconst_0
    //   250: invokevirtual 143	java/lang/String:codePointAt	(I)I
    //   253: bipush 47
    //   255: iadd
    //   256: aload_0
    //   257: invokevirtual 147	android/content/Context:getPackageName	()Ljava/lang/String;
    //   260: bipush 8
    //   262: invokevirtual 143	java/lang/String:codePointAt	(I)I
    //   265: sipush 30604
    //   268: iadd
    //   269: i2c
    //   270: aload_0
    //   271: invokevirtual 126	android/content/Context:getResources	()Landroid/content/res/Resources;
    //   274: ldc -108
    //   276: invokevirtual 133	android/content/res/Resources:getString	(I)Ljava/lang/String;
    //   279: iconst_0
    //   280: iconst_5
    //   281: invokevirtual 139	java/lang/String:substring	(II)Ljava/lang/String;
    //   284: iconst_2
    //   285: invokevirtual 143	java/lang/String:codePointAt	(I)I
    //   288: bipush 16
    //   290: iadd
    //   291: invokestatic 151	o/Lv:ˋ	(ICI)Ljava/lang/String;
    //   294: invokevirtual 154	java/lang/String:intern	()Ljava/lang/String;
    //   297: invokestatic 159	o/vq:ˋ	(Ljava/lang/Object;Ljava/lang/String;)V
    //   300: aload_2
    //   301: new 161	android/support/v7/widget/LinearLayoutManager
    //   304: dup
    //   305: aload_0
    //   306: checkcast 95	android/content/Context
    //   309: invokespecial 164	android/support/v7/widget/LinearLayoutManager:<init>	(Landroid/content/Context;)V
    //   312: checkcast 166	android/support/v7/widget/RecyclerView$LayoutManager
    //   315: invokevirtual 170	o/aH:setLayoutManager	(Landroid/support/v7/widget/RecyclerView$LayoutManager;)V
    //   318: aload_0
    //   319: getfield 69	o/Lv:ॱˊ	Landroid/databinding/ViewDataBinding;
    //   322: checkcast 71	o/LA
    //   325: getfield 75	o/LA:ˊ	Lo/aH;
    //   328: astore_2
    //   329: aload_2
    //   330: aload_0
    //   331: invokevirtual 126	android/content/Context:getResources	()Landroid/content/res/Resources;
    //   334: ldc -85
    //   336: invokevirtual 133	android/content/res/Resources:getString	(I)Ljava/lang/String;
    //   339: iconst_0
    //   340: iconst_1
    //   341: invokevirtual 139	java/lang/String:substring	(II)Ljava/lang/String;
    //   344: invokevirtual 175	java/lang/String:length	()I
    //   347: bipush 51
    //   349: iadd
    //   350: aload_0
    //   351: invokevirtual 126	android/content/Context:getResources	()Landroid/content/res/Resources;
    //   354: ldc -80
    //   356: invokevirtual 133	android/content/res/Resources:getString	(I)Ljava/lang/String;
    //   359: iconst_0
    //   360: iconst_4
    //   361: invokevirtual 139	java/lang/String:substring	(II)Ljava/lang/String;
    //   364: iconst_2
    //   365: invokevirtual 143	java/lang/String:codePointAt	(I)I
    //   368: sipush 30705
    //   371: iadd
    //   372: i2c
    //   373: aload_0
    //   374: invokevirtual 126	android/content/Context:getResources	()Landroid/content/res/Resources;
    //   377: ldc -79
    //   379: invokevirtual 133	android/content/res/Resources:getString	(I)Ljava/lang/String;
    //   382: iconst_0
    //   383: iconst_4
    //   384: invokevirtual 139	java/lang/String:substring	(II)Ljava/lang/String;
    //   387: iconst_1
    //   388: invokevirtual 143	java/lang/String:codePointAt	(I)I
    //   391: iconst_1
    //   392: iadd
    //   393: invokestatic 151	o/Lv:ˋ	(ICI)Ljava/lang/String;
    //   396: invokevirtual 154	java/lang/String:intern	()Ljava/lang/String;
    //   399: invokestatic 159	o/vq:ˋ	(Ljava/lang/Object;Ljava/lang/String;)V
    //   402: aload_0
    //   403: getfield 122	o/Lv:ʾ	Lo/Lx;
    //   406: astore_3
    //   407: aload_3
    //   408: ifnonnull +6 -> 414
    //   411: goto +116 -> 527
    //   414: goto -400 -> 14
    //   417: aload_0
    //   418: invokevirtual 126	android/content/Context:getResources	()Landroid/content/res/Resources;
    //   421: ldc -78
    //   423: invokevirtual 133	android/content/res/Resources:getString	(I)Ljava/lang/String;
    //   426: bipush 7
    //   428: bipush 13
    //   430: invokevirtual 139	java/lang/String:substring	(II)Ljava/lang/String;
    //   433: iconst_1
    //   434: invokevirtual 143	java/lang/String:codePointAt	(I)I
    //   437: sipush 164
    //   440: isub
    //   441: aload_0
    //   442: invokevirtual 126	android/content/Context:getResources	()Landroid/content/res/Resources;
    //   445: ldc -77
    //   447: invokevirtual 133	android/content/res/Resources:getString	(I)Ljava/lang/String;
    //   450: bipush 19
    //   452: bipush 30
    //   454: invokevirtual 139	java/lang/String:substring	(II)Ljava/lang/String;
    //   457: iconst_1
    //   458: invokevirtual 143	java/lang/String:codePointAt	(I)I
    //   461: sipush 233
    //   464: isub
    //   465: i2c
    //   466: aload_0
    //   467: invokevirtual 126	android/content/Context:getResources	()Landroid/content/res/Resources;
    //   470: ldc -76
    //   472: invokevirtual 133	android/content/res/Resources:getString	(I)Ljava/lang/String;
    //   475: iconst_0
    //   476: iconst_4
    //   477: invokevirtual 139	java/lang/String:substring	(II)Ljava/lang/String;
    //   480: iconst_1
    //   481: invokevirtual 143	java/lang/String:codePointAt	(I)I
    //   484: bipush 12
    //   486: isub
    //   487: invokestatic 151	o/Lv:ˋ	(ICI)Ljava/lang/String;
    //   490: invokevirtual 154	java/lang/String:intern	()Ljava/lang/String;
    //   493: invokestatic 183	o/vq:ˊ	(Ljava/lang/String;)V
    //   496: goto -477 -> 19
    //   499: iload_1
    //   500: tableswitch	default:+24->524, 0:+-481->19, 1:+-325->175
    //   524: goto -505 -> 19
    //   527: iconst_1
    //   528: istore_1
    //   529: goto -30 -> 499
    //   532: iconst_0
    //   533: istore_1
    //   534: goto -384 -> 150
    //   537: goto -331 -> 206
    // Local variable table:
    //   start	length	slot	name	signature
    //   0	540	0	this	Lv
    //   4	530	1	i	int
    //   19	79	2	localᔄ	ᔄ
    //   111	7	2	localException1	Exception
    //   203	2	2	localException2	Exception
    //   213	117	2	localObject1	Object
    //   20	388	3	localObject2	Object
    // Exception table:
    //   from	to	target	type
    //   224	229	111	java/lang/Exception
    //   214	219	203	java/lang/Exception
    //   219	224	203	java/lang/Exception
    //   224	229	203	java/lang/Exception
    //   229	234	203	java/lang/Exception
    //   234	407	203	java/lang/Exception
  }
  
  /* Error */
  private final void ˉ()
  {
    // Byte code:
    //   0: goto +249 -> 249
    //   3: astore_2
    //   4: aload_2
    //   5: athrow
    //   6: new 185	o/vv$if
    //   9: dup
    //   10: invokespecial 186	o/vv$if:<init>	()V
    //   13: astore_2
    //   14: aload_2
    //   15: iconst_0
    //   16: putfield 189	o/vv$if:ˎ	Z
    //   19: goto +17 -> 36
    //   22: astore_2
    //   23: aload_2
    //   24: invokevirtual 195	java/lang/Throwable:getCause	()Ljava/lang/Throwable;
    //   27: astore_3
    //   28: aload_3
    //   29: ifnull +5 -> 34
    //   32: aload_3
    //   33: athrow
    //   34: aload_2
    //   35: athrow
    //   36: aload_0
    //   37: invokevirtual 126	android/content/Context:getResources	()Landroid/content/res/Resources;
    //   40: ldc -60
    //   42: invokevirtual 133	android/content/res/Resources:getString	(I)Ljava/lang/String;
    //   45: iconst_0
    //   46: iconst_4
    //   47: invokevirtual 139	java/lang/String:substring	(II)Ljava/lang/String;
    //   50: invokevirtual 175	java/lang/String:length	()I
    //   53: iconst_0
    //   54: iadd
    //   55: aload_0
    //   56: invokevirtual 126	android/content/Context:getResources	()Landroid/content/res/Resources;
    //   59: ldc -59
    //   61: invokevirtual 133	android/content/res/Resources:getString	(I)Ljava/lang/String;
    //   64: iconst_0
    //   65: iconst_4
    //   66: invokevirtual 139	java/lang/String:substring	(II)Ljava/lang/String;
    //   69: iconst_1
    //   70: invokevirtual 143	java/lang/String:codePointAt	(I)I
    //   73: bipush 109
    //   75: iadd
    //   76: aload_0
    //   77: invokevirtual 126	android/content/Context:getResources	()Landroid/content/res/Resources;
    //   80: ldc -58
    //   82: invokevirtual 133	android/content/res/Resources:getString	(I)Ljava/lang/String;
    //   85: iconst_0
    //   86: iconst_5
    //   87: invokevirtual 139	java/lang/String:substring	(II)Ljava/lang/String;
    //   90: iconst_1
    //   91: invokevirtual 143	java/lang/String:codePointAt	(I)I
    //   94: ldc -57
    //   96: iadd
    //   97: i2c
    //   98: invokestatic 204	o/O:ˋ	(IIC)Ljava/lang/Object;
    //   101: checkcast 206	java/lang/Class
    //   104: ldc -49
    //   106: aconst_null
    //   107: invokevirtual 211	java/lang/Class:getMethod	(Ljava/lang/String;[Ljava/lang/Class;)Ljava/lang/reflect/Method;
    //   110: aconst_null
    //   111: aconst_null
    //   112: invokevirtual 217	java/lang/reflect/Method:invoke	(Ljava/lang/Object;[Ljava/lang/Object;)Ljava/lang/Object;
    //   115: checkcast 219	o/It
    //   118: astore_3
    //   119: aload_0
    //   120: invokevirtual 126	android/content/Context:getResources	()Landroid/content/res/Resources;
    //   123: astore 4
    //   125: aload_3
    //   126: aload 4
    //   128: ldc -36
    //   130: invokevirtual 133	android/content/res/Resources:getString	(I)Ljava/lang/String;
    //   133: iconst_0
    //   134: bipush 8
    //   136: invokevirtual 139	java/lang/String:substring	(II)Ljava/lang/String;
    //   139: invokevirtual 175	java/lang/String:length	()I
    //   142: sipush 197
    //   145: iadd
    //   146: aload_0
    //   147: invokevirtual 147	android/content/Context:getPackageName	()Ljava/lang/String;
    //   150: invokevirtual 175	java/lang/String:length	()I
    //   153: sipush 31262
    //   156: iadd
    //   157: i2c
    //   158: aload_0
    //   159: invokevirtual 126	android/content/Context:getResources	()Landroid/content/res/Resources;
    //   162: ldc -35
    //   164: invokevirtual 133	android/content/res/Resources:getString	(I)Ljava/lang/String;
    //   167: iconst_0
    //   168: bipush 17
    //   170: invokevirtual 139	java/lang/String:substring	(II)Ljava/lang/String;
    //   173: bipush 10
    //   175: invokevirtual 143	java/lang/String:codePointAt	(I)I
    //   178: sipush 174
    //   181: isub
    //   182: invokestatic 151	o/Lv:ˋ	(ICI)Ljava/lang/String;
    //   185: invokevirtual 154	java/lang/String:intern	()Ljava/lang/String;
    //   188: invokestatic 159	o/vq:ˋ	(Ljava/lang/Object;Ljava/lang/String;)V
    //   191: aload_3
    //   192: invokeinterface 225 1 0
    //   197: new 7	o/Lv$If
    //   200: dup
    //   201: aload_0
    //   202: aload_2
    //   203: aload_0
    //   204: checkcast 95	android/content/Context
    //   207: invokespecial 228	o/Lv$If:<init>	(Lo/Lv;Lo/vv$if;Landroid/content/Context;)V
    //   210: checkcast 230	o/Cx
    //   213: invokeinterface 235 2 0
    //   218: goto +6 -> 224
    //   221: astore_2
    //   222: aload_2
    //   223: athrow
    //   224: getstatic 36	o/Lv:ˋˊ	I
    //   227: bipush 85
    //   229: iadd
    //   230: istore_1
    //   231: iload_1
    //   232: sipush 128
    //   235: irem
    //   236: putstatic 38	o/Lv:ˊˊ	I
    //   239: iload_1
    //   240: iconst_2
    //   241: irem
    //   242: ifne +6 -> 248
    //   245: goto +7 -> 252
    //   248: return
    //   249: goto -243 -> 6
    //   252: return
    // Local variable table:
    //   start	length	slot	name	signature
    //   0	253	0	this	Lv
    //   230	12	1	i	int
    //   3	2	2	localException1	Exception
    //   13	2	2	localIf1	vv.if
    //   22	181	2	localIf2	vv.if
    //   221	2	2	localException2	Exception
    //   27	165	3	localObject	Object
    //   123	4	4	localResources	Resources
    // Exception table:
    //   from	to	target	type
    //   119	125	3	java/lang/Exception
    //   36	119	22	finally
    //   14	19	221	java/lang/Exception
    //   23	28	221	java/lang/Exception
    //   32	34	221	java/lang/Exception
    //   34	36	221	java/lang/Exception
    //   119	125	221	java/lang/Exception
    //   125	218	221	java/lang/Exception
  }
  
  /* Error */
  private final void ˊˊ()
  {
    // Byte code:
    //   0: goto +9 -> 9
    //   3: astore_2
    //   4: aload_2
    //   5: athrow
    //   6: astore_2
    //   7: aload_2
    //   8: athrow
    //   9: goto +26 -> 35
    //   12: getstatic 38	o/Lv:ˊˊ	I
    //   15: bipush 93
    //   17: iadd
    //   18: istore_1
    //   19: iload_1
    //   20: sipush 128
    //   23: irem
    //   24: putstatic 36	o/Lv:ˋˊ	I
    //   27: iload_1
    //   28: iconst_2
    //   29: irem
    //   30: ifeq +4 -> 34
    //   33: return
    //   34: return
    //   35: aload_0
    //   36: getfield 69	o/Lv:ॱˊ	Landroid/databinding/ViewDataBinding;
    //   39: astore_2
    //   40: aload_2
    //   41: checkcast 71	o/LA
    //   44: astore_2
    //   45: aload_2
    //   46: getfield 240	o/LA:ॱॱ	Lo/Jn;
    //   49: astore_2
    //   50: new 9	o/Lv$iF
    //   53: dup
    //   54: aload_0
    //   55: invokespecial 243	o/Lv$iF:<init>	(Lo/Lv;)V
    //   58: astore_3
    //   59: aload_3
    //   60: checkcast 245	o/Hp
    //   63: astore_3
    //   64: aload_2
    //   65: aload_3
    //   66: invokevirtual 250	o/Jn:ˊ	(Lo/Hp;)V
    //   69: goto -57 -> 12
    // Local variable table:
    //   start	length	slot	name	signature
    //   0	72	0	this	Lv
    //   18	12	1	i	int
    //   3	2	2	localException1	Exception
    //   6	2	2	localException2	Exception
    //   39	26	2	localObject1	Object
    //   58	8	3	localObject2	Object
    // Exception table:
    //   from	to	target	type
    //   35	40	3	java/lang/Exception
    //   40	45	3	java/lang/Exception
    //   45	50	3	java/lang/Exception
    //   50	59	3	java/lang/Exception
    //   59	64	3	java/lang/Exception
    //   64	69	3	java/lang/Exception
    //   45	50	6	java/lang/Exception
  }
  
  private static String ˋ(int paramInt1, char paramChar, int paramInt2)
  {
    break label203;
    break label206;
    int i;
    if (i >= paramInt2) {
      break label188;
    }
    for (;;)
    {
      label17:
      int j;
      label47:
      char[] arrayOfChar;
      switch (j)
      {
      default: 
        break label115;
        arrayOfChar[i] = ((char)(int)(ˉ[(paramInt1 + i)] ^ i * ˊˋ ^ paramChar));
        i += 1;
        break;
      case 51: 
      case 82: 
        label115:
        label145:
        label188:
        label195:
        label203:
        for (;;)
        {
          i = ˊˊ + 33;
          ˋˊ = i % 128;
          if (i % 2 == 0)
          {
            break label145;
            return new String(arrayOfChar);
            j = ˊˊ + 93;
            ˋˊ = j % 128;
            if (j % 2 != 0) {
              break label195;
            }
            break label47;
          }
          for (;;)
          {
            arrayOfChar = new char[paramInt2];
            i = 0;
            break;
          }
          try
          {
            j = ˋˊ + 55;
            ˊˊ = j % 128;
            if (j % 2 == 0) {
              break;
            }
          }
          catch (Exception localException)
          {
            throw localException;
          }
          j = 51;
          break label17;
          break label47;
        }
        label206:
        break;
        j = 82;
      }
    }
  }
  
  private final void ˋˊ()
  {
    do
    {
      break;
      i = ˊˊ + 123;
      ˋˊ = i % 128;
    } while (i % 2 != 0);
    ViewDataBinding localViewDataBinding = this.ॱˊ;
    vq.ˋ(localViewDataBinding, ˋ(getResources().getString(2131755125).substring(0, 4).codePointAt(0) + 88, (char)(getResources().getString(2131755640).substring(0, 4).length() - 4), getPackageName().codePointAt(3) - 90).intern());
    ((LA)localViewDataBinding).ˏ(true);
    localViewDataBinding = this.ॱˊ;
    vq.ˋ(localViewDataBinding, ˋ(getPackageName().length() + 82, (char)(getPackageName().codePointAt(3) - 98), getResources().getString(2131755293).substring(0, 5).codePointAt(4) - 179).intern());
    ((LA)localViewDataBinding).ˋ(false);
    ˉ();
    int i = ˊˊ + 1;
    ˋˊ = i % 128;
    if (i % 2 != 0) {}
  }
  
  private final void ˎ(String paramString)
  {
    break label578;
    label15:
    Object localObject2;
    ArrayList localArrayList;
    do
    {
      i = 1;
      break;
      i = 39;
      break label581;
      return;
      ((Lx)localObject2).ˊ((List)localArrayList);
      localObject2 = this.ʾ;
    } while (localObject2 == null);
    break label573;
    int i = ˊˊ + 93;
    ˋˊ = i % 128;
    if (i % 2 == 0)
    {
      break label492;
      label68:
      ((Lx)localObject2).ʼ();
    }
    label319:
    label336:
    label422:
    label426:
    label428:
    label434:
    label492:
    label546:
    label573:
    label578:
    for (;;)
    {
      localArrayList = new ArrayList();
      Object localObject1 = this.ʼॱ;
      if (localObject1 != null) {
        break label336;
      }
      for (;;)
      {
        switch (i)
        {
        }
        break label68;
        localObject2 = (FM)((Iterator)localObject1).next();
        Object localObject3 = aq.ˋ(((FM)localObject2).ˊ());
        vq.ˋ(localObject3, ˋ(getPackageName().length() + 97, (char)(getResources().getString(2131755551).substring(0, 6).length() - 6), getResources().getString(2131755196).substring(0, 10).length() + 24).intern());
        localObject3 = (CharSequence)localObject3;
        String str = aq.ˋ(paramString);
        vq.ˋ(str, ˋ(getApplicationInfo().targetSdkVersion + 117, (char)(getResources().getString(2131755093).substring(0, 4).length() + 8231), getResources().getString(2131755498).substring(5, 7).codePointAt(1) - 3).intern());
        if (!vT.ˊ((CharSequence)localObject3, (CharSequence)str, false, 2, null))
        {
          break label319;
          break label492;
          localObject2 = this.ʾ;
          if (localObject2 == null) {
            break label546;
          }
          break label15;
          localObject1 = ((ArrayList)localObject1).iterator();
        }
        for (;;)
        {
          if (((Iterator)localObject1).hasNext()) {
            break label426;
          }
          break label428;
          vq.ˊ(ˋ(getResources().getString(2131755583).substring(0, 4).length() + 97, (char)(getApplicationInfo().targetSdkVersion - 25), getPackageName().length() - 4).intern());
          break label336;
          localArrayList.add(localObject2);
          break;
          break label434;
        }
        break;
        i = 66;
        break label581;
        for (;;)
        {
          vq.ˊ(ˋ(getPackageName().length() + 68, (char)(getPackageName().length() - 11), getResources().getString(2131755559).substring(0, 16).codePointAt(14) - 203).intern());
          break;
          vq.ˊ(ˋ(getPackageName().length() + 68, (char)(getPackageName().length() - 11), getResources().getString(2131755214).substring(0, 4).codePointAt(3) + 2).intern());
          break label68;
          i = ˋˊ + 65;
          ˊˊ = i % 128;
          if (i % 2 == 0) {
            break label422;
          }
        }
        i = 0;
      }
    }
    label581:
    switch (i)
    {
    }
  }
  
  /* Error */
  private final void ˏ(String paramString)
  {
    // Byte code:
    //   0: goto +164 -> 164
    //   3: iload_2
    //   4: tableswitch	default:+24->28, 0:+24->28, 1:+195->199
    //   28: return
    //   29: goto +17 -> 46
    //   32: astore_1
    //   33: aload_1
    //   34: invokevirtual 195	java/lang/Throwable:getCause	()Ljava/lang/Throwable;
    //   37: astore_3
    //   38: aload_3
    //   39: ifnull +5 -> 44
    //   42: aload_3
    //   43: athrow
    //   44: aload_1
    //   45: athrow
    //   46: aload_0
    //   47: invokevirtual 126	android/content/Context:getResources	()Landroid/content/res/Resources;
    //   50: ldc_w 341
    //   53: invokevirtual 133	android/content/res/Resources:getString	(I)Ljava/lang/String;
    //   56: bipush 52
    //   58: bipush 59
    //   60: invokevirtual 139	java/lang/String:substring	(II)Ljava/lang/String;
    //   63: invokevirtual 175	java/lang/String:length	()I
    //   66: iconst_3
    //   67: isub
    //   68: aload_0
    //   69: invokevirtual 126	android/content/Context:getResources	()Landroid/content/res/Resources;
    //   72: ldc_w 342
    //   75: invokevirtual 133	android/content/res/Resources:getString	(I)Ljava/lang/String;
    //   78: iconst_0
    //   79: iconst_4
    //   80: invokevirtual 139	java/lang/String:substring	(II)Ljava/lang/String;
    //   83: invokevirtual 175	java/lang/String:length	()I
    //   86: sipush 131
    //   89: iadd
    //   90: aload_0
    //   91: invokevirtual 126	android/content/Context:getResources	()Landroid/content/res/Resources;
    //   94: ldc_w 343
    //   97: invokevirtual 133	android/content/res/Resources:getString	(I)Ljava/lang/String;
    //   100: iconst_0
    //   101: iconst_4
    //   102: invokevirtual 139	java/lang/String:substring	(II)Ljava/lang/String;
    //   105: invokevirtual 175	java/lang/String:length	()I
    //   108: ldc_w 344
    //   111: iadd
    //   112: i2c
    //   113: invokestatic 204	o/O:ˋ	(IIC)Ljava/lang/Object;
    //   116: checkcast 206	java/lang/Class
    //   119: ldc -49
    //   121: aconst_null
    //   122: invokevirtual 211	java/lang/Class:getMethod	(Ljava/lang/String;[Ljava/lang/Class;)Ljava/lang/reflect/Method;
    //   125: aconst_null
    //   126: aconst_null
    //   127: invokevirtual 217	java/lang/reflect/Method:invoke	(Ljava/lang/Object;[Ljava/lang/Object;)Ljava/lang/Object;
    //   130: checkcast 219	o/It
    //   133: astore_3
    //   134: aload_3
    //   135: aload_1
    //   136: invokeinterface 347 2 0
    //   141: new 11	o/Lv$ˊ
    //   144: dup
    //   145: aload_0
    //   146: aload_0
    //   147: checkcast 95	android/content/Context
    //   150: invokespecial 350	o/Lv$ˊ:<init>	(Lo/Lv;Landroid/content/Context;)V
    //   153: checkcast 230	o/Cx
    //   156: invokeinterface 235 2 0
    //   161: goto +11 -> 172
    //   164: goto -135 -> 29
    //   167: iconst_1
    //   168: istore_2
    //   169: goto -166 -> 3
    //   172: getstatic 38	o/Lv:ˊˊ	I
    //   175: bipush 123
    //   177: iadd
    //   178: istore_2
    //   179: iload_2
    //   180: sipush 128
    //   183: irem
    //   184: putstatic 36	o/Lv:ˋˊ	I
    //   187: iload_2
    //   188: iconst_2
    //   189: irem
    //   190: ifeq +6 -> 196
    //   193: goto -26 -> 167
    //   196: goto +7 -> 203
    //   199: aconst_null
    //   200: arraylength
    //   201: istore_2
    //   202: return
    //   203: iconst_0
    //   204: istore_2
    //   205: goto -202 -> 3
    // Local variable table:
    //   start	length	slot	name	signature
    //   0	208	0	this	Lv
    //   0	208	1	paramString	String
    //   3	202	2	i	int
    //   37	98	3	localObject	Object
    // Exception table:
    //   from	to	target	type
    //   46	134	32	finally
  }
  
  /* Error */
  private String ॱ(String paramString)
  {
    // Byte code:
    //   0: goto +136 -> 136
    //   3: astore_1
    //   4: aload_1
    //   5: athrow
    //   6: new 135	java/lang/String
    //   9: dup
    //   10: aload 4
    //   12: aload_0
    //   13: invokevirtual 147	android/content/Context:getPackageName	()Ljava/lang/String;
    //   16: invokevirtual 175	java/lang/String:length	()I
    //   19: sipush 235
    //   22: iadd
    //   23: aload_0
    //   24: invokevirtual 126	android/content/Context:getResources	()Landroid/content/res/Resources;
    //   27: ldc_w 355
    //   30: invokevirtual 133	android/content/res/Resources:getString	(I)Ljava/lang/String;
    //   33: iconst_0
    //   34: iconst_5
    //   35: invokevirtual 139	java/lang/String:substring	(II)Ljava/lang/String;
    //   38: iconst_4
    //   39: invokevirtual 143	java/lang/String:codePointAt	(I)I
    //   42: sipush 160
    //   45: isub
    //   46: i2c
    //   47: aload_0
    //   48: invokevirtual 306	android/content/Context:getApplicationInfo	()Landroid/content/pm/ApplicationInfo;
    //   51: getfield 311	android/content/pm/ApplicationInfo:targetSdkVersion	I
    //   54: bipush 20
    //   56: isub
    //   57: invokestatic 151	o/Lv:ˋ	(ICI)Ljava/lang/String;
    //   60: invokevirtual 154	java/lang/String:intern	()Ljava/lang/String;
    //   63: invokespecial 358	java/lang/String:<init>	([BLjava/lang/String;)V
    //   66: astore_1
    //   67: aload_1
    //   68: areturn
    //   69: iconst_0
    //   70: istore_3
    //   71: goto +33 -> 104
    //   74: aload_1
    //   75: arraylength
    //   76: istore_3
    //   77: iload_2
    //   78: iload_3
    //   79: if_icmpge +6 -> 85
    //   82: goto -13 -> 69
    //   85: goto +46 -> 131
    //   88: goto -14 -> 74
    //   91: astore_1
    //   92: new 360	java/lang/RuntimeException
    //   95: dup
    //   96: aload_1
    //   97: invokespecial 363	java/lang/RuntimeException:<init>	(Ljava/lang/Throwable;)V
    //   100: athrow
    //   101: goto -13 -> 88
    //   104: iload_3
    //   105: tableswitch	default:+23->128, 0:+34->139, 1:+-99->6
    //   128: goto +11 -> 139
    //   131: iconst_1
    //   132: istore_3
    //   133: goto -29 -> 104
    //   136: goto +145 -> 281
    //   139: aload 4
    //   141: iload_2
    //   142: aload_1
    //   143: aload_1
    //   144: arraylength
    //   145: iload_2
    //   146: isub
    //   147: iconst_1
    //   148: isub
    //   149: baload
    //   150: getstatic 55	o/Lv:ˈ	B
    //   153: ixor
    //   154: i2b
    //   155: bastore
    //   156: iload_2
    //   157: iconst_1
    //   158: iadd
    //   159: istore_2
    //   160: goto +6 -> 166
    //   163: goto +30 -> 193
    //   166: getstatic 36	o/Lv:ˋˊ	I
    //   169: bipush 121
    //   171: iadd
    //   172: istore_3
    //   173: iload_3
    //   174: sipush 128
    //   177: irem
    //   178: putstatic 38	o/Lv:ˊˊ	I
    //   181: iload_3
    //   182: iconst_2
    //   183: irem
    //   184: ifne +6 -> 190
    //   187: goto -86 -> 101
    //   190: goto -102 -> 88
    //   193: aload_1
    //   194: aload_0
    //   195: invokevirtual 126	android/content/Context:getResources	()Landroid/content/res/Resources;
    //   198: ldc_w 364
    //   201: invokevirtual 133	android/content/res/Resources:getString	(I)Ljava/lang/String;
    //   204: iconst_0
    //   205: iconst_4
    //   206: invokevirtual 139	java/lang/String:substring	(II)Ljava/lang/String;
    //   209: iconst_1
    //   210: invokevirtual 143	java/lang/String:codePointAt	(I)I
    //   213: sipush 210
    //   216: iadd
    //   217: aload_0
    //   218: invokevirtual 126	android/content/Context:getResources	()Landroid/content/res/Resources;
    //   221: ldc_w 365
    //   224: invokevirtual 133	android/content/res/Resources:getString	(I)Ljava/lang/String;
    //   227: iconst_0
    //   228: bipush 9
    //   230: invokevirtual 139	java/lang/String:substring	(II)Ljava/lang/String;
    //   233: invokevirtual 175	java/lang/String:length	()I
    //   236: bipush 9
    //   238: isub
    //   239: i2c
    //   240: aload_0
    //   241: invokevirtual 126	android/content/Context:getResources	()Landroid/content/res/Resources;
    //   244: ldc -59
    //   246: invokevirtual 133	android/content/res/Resources:getString	(I)Ljava/lang/String;
    //   249: iconst_0
    //   250: iconst_4
    //   251: invokevirtual 139	java/lang/String:substring	(II)Ljava/lang/String;
    //   254: invokevirtual 175	java/lang/String:length	()I
    //   257: bipush 6
    //   259: iadd
    //   260: invokestatic 151	o/Lv:ˋ	(ICI)Ljava/lang/String;
    //   263: invokevirtual 154	java/lang/String:intern	()Ljava/lang/String;
    //   266: invokevirtual 369	java/lang/String:getBytes	(Ljava/lang/String;)[B
    //   269: astore_1
    //   270: aload_1
    //   271: arraylength
    //   272: newarray byte
    //   274: astore 4
    //   276: iconst_0
    //   277: istore_2
    //   278: goto -204 -> 74
    //   281: getstatic 36	o/Lv:ˋˊ	I
    //   284: bipush 7
    //   286: iadd
    //   287: istore_2
    //   288: iload_2
    //   289: sipush 128
    //   292: irem
    //   293: putstatic 38	o/Lv:ˊˊ	I
    //   296: iload_2
    //   297: iconst_2
    //   298: irem
    //   299: ifne +6 -> 305
    //   302: goto -139 -> 163
    //   305: goto -112 -> 193
    // Local variable table:
    //   start	length	slot	name	signature
    //   0	308	0	this	Lv
    //   0	308	1	paramString	String
    //   77	222	2	i	int
    //   70	114	3	j	int
    //   10	265	4	arrayOfByte	byte[]
    // Exception table:
    //   from	to	target	type
    //   281	288	3	java/lang/Exception
    //   288	296	3	java/lang/Exception
    //   6	67	91	java/io/UnsupportedEncodingException
    //   74	77	91	java/io/UnsupportedEncodingException
    //   139	156	91	java/io/UnsupportedEncodingException
    //   193	276	91	java/io/UnsupportedEncodingException
  }
  
  static void ॱˋ()
  {
    ˊˋ = 3268048070208534134L;
    ˉ = new char[] { 31955, 19130, 4145, -8264, 14453, 3585, 21642, -25821, -7746, 10286, 32447, 17734, -29755, -11748, 6364, 28462, -18967, -1128, -15852, 2193, 24348, -23133, -5008, 12991, 31052, 20442, -27053, -8966, 9073, 27083, -16504, -31223, -13162, 4920, 22947, -24534, -2419, 15687, 978, 19029, -28437, -6290, 11711, 97, 13845, 27800, -23797, -9801, 4128, 18054, 32091, -19518, 30609, 16840, 7033, -11024, -20928, 26587, 12630, 2721, -15262, -25156, 22281, 8322, -1536, -19353, -29190, 18244, 4345, -5559, -23607, 32093, 13992, 55, -9814, -27856, 27781, 9759, -3977, 109, 13872, 27781, -23794, -9812, 4139, 18102, 32123, -19500, -5561, 8428, 22374, -29203, -15476, 109, 13876, 27781, -23796, -9796, 4135, 18090, 32093, 109, 13877, 27781, -23786, -9807, 4139, 18103, 83, 13826, 27806, -23797, -9802, 4137, 18065, 32078, -19495, -5558, 8431, 22332, -29188, -15471, -1480, 12421, 26391, -25165, -11202, 2689, 16729, 30685, -20927, -6990, 7027, 20975, -30840, -16885, -2874, 11056, 25013, -26585, -12635, 1311, 8312, 5673, 19637, -31968, -1635, 12290, 26298, 23909, -27662, -13727, 196, 30487, -21033, -7238, -9709, 4270, 18236, -17000, -3051, 10922, 24946, 22518, -29078, -15207, 15183, 29128, -22609, -25043, -11030, 9215, 5507, 20228, -32633, -15569, -2748, -20526, 24666, 6899, -11429, -31251, -16871, 28814, 10517, -7287, -27594, 20131, 217, 14683, 31167, 20436, 5442, -9526, -24477, 27083, 16253, 1161, -13794, -27771, 22809, 11947, -3011, -17856, -31797, 31336, 19503, 5804, -9978, -23664, 27145, 15500, 1908, -13828, -28547, 23195, 11612, -2108, -18013, -32651, 19178, 16183, 2382, 21469, -25513, -6402, 12124, 31225, 16898, -29552, -10985, 8122, 26629, -19787, -802, -15015, 73, 13861, 27811, -23729, -9760, 4214, 18161, 32003, -19555, -5609, 85, 13858, 27818, -23729, -9760 };
  }
  
  public Resources getResources()
  {
    for (;;)
    {
      i = ˊˊ + 57;
      ˋˊ = i % 128;
      if (i % 2 != 0) {
        break;
      }
      break label115;
      localResources = oH.ˊ(super.getResources());
      i = null.length;
      break label60;
    }
    int i = 0;
    break label88;
    Resources localResources = oH.ˊ(super.getResources());
    label60:
    i = ˊˊ + 81;
    ˋˊ = i % 128;
    if (i % 2 == 0) {
      return localResources;
    }
    return localResources;
    for (;;)
    {
      label88:
      switch (i)
      {
      }
      break;
      label115:
      i = 1;
    }
  }
  
  public void onCreate(Bundle paramBundle)
  {
    break label9;
    int i = 43;
    break label243;
    for (;;)
    {
      label9:
      i = ˊˊ + 57;
      ˋˊ = i % 128;
      if (i % 2 != 0) {
        break;
      }
      break label240;
      super.onCreate(paramBundle);
      ˊ(((LA)this.ॱˊ).ᐝ);
      paramBundle = getString(Lt.If.offers_filter_clear);
      if (!paramBundle.startsWith(ˋ(getResources().getString(2131755535).substring(0, 7).codePointAt(2) - 116, (char)(getResources().getString(2131755437).substring(0, 4).codePointAt(1) + 31932), getPackageName().length() - 7).intern())) {
        break label158;
      }
      paramBundle = ॱ(paramBundle.substring(4)).intern();
    }
    for (;;)
    {
      label158:
      vq.ˋ(paramBundle, ˋ(getResources().getString(2131755538).substring(0, 5).length() - 1, (char)(getPackageName().codePointAt(3) + 14256), getApplicationInfo().targetSdkVersion + 14).intern());
      this.ʽॱ = new FM("", "", paramBundle, "", "");
      ʾ();
      return;
      label240:
      i = 83;
      switch (i)
      {
      default: 
        label243:
        break;
      case 43: 
        
      }
    }
  }
  
  public void ˋ(ز paramز)
  {
    int i;
    try
    {
      i = ˋˊ;
      i += 49;
      ˊˊ = i % 128;
      if (i % 2 == 0) {
        break label161;
      }
    }
    catch (Exception paramز)
    {
      throw paramز;
    }
    for (;;)
    {
      i = 68;
      break label164;
      i = ˋˊ + 123;
      ˊˊ = i % 128;
      if (i % 2 != 0) {
        break;
      }
    }
    for (;;)
    {
      i = 25 / 0;
      return;
      label161:
      for (;;)
      {
        Resources localResources = getResources();
        vq.ˎ(paramز, ˋ(localResources.getString(2131755114).substring(0, 4).length() + 39, (char)(getResources().getString(2131755282).substring(0, 5).codePointAt(0) - 5), getApplicationInfo().targetSdkVersion - 16).intern());
        super.ˋ(paramز);
        paramز.ॱ(true);
        paramز.ˏ(true);
        break;
        return;
        i = 79;
        break label164;
      }
      label164:
      switch (i)
      {
      }
    }
  }
  
  /* Error */
  public int ˎ()
  {
    // Byte code:
    //   0: goto +18 -> 18
    //   3: bipush 73
    //   5: istore_1
    //   6: goto +47 -> 53
    //   9: astore_3
    //   10: aload_3
    //   11: athrow
    //   12: bipush 47
    //   14: istore_1
    //   15: goto +38 -> 53
    //   18: goto +74 -> 92
    //   21: getstatic 38	o/Lv:ˊˊ	I
    //   24: bipush 119
    //   26: iadd
    //   27: istore_2
    //   28: iload_2
    //   29: sipush 128
    //   32: irem
    //   33: putstatic 36	o/Lv:ˋˊ	I
    //   36: iload_2
    //   37: iconst_2
    //   38: irem
    //   39: ifeq +5 -> 44
    //   42: iload_1
    //   43: ireturn
    //   44: iload_1
    //   45: ireturn
    //   46: getstatic 672	o/Lt$ˋ:activity_offer_filter	I
    //   49: istore_1
    //   50: goto -29 -> 21
    //   53: iload_1
    //   54: lookupswitch	default:+26->80, 47:+26->80, 73:+-8->46
    //   80: getstatic 672	o/Lt$ˋ:activity_offer_filter	I
    //   83: istore_1
    //   84: bipush 58
    //   86: iconst_0
    //   87: idiv
    //   88: istore_2
    //   89: goto -68 -> 21
    //   92: getstatic 38	o/Lv:ˊˊ	I
    //   95: bipush 45
    //   97: iadd
    //   98: istore_1
    //   99: iload_1
    //   100: sipush 128
    //   103: irem
    //   104: putstatic 36	o/Lv:ˋˊ	I
    //   107: iload_1
    //   108: iconst_2
    //   109: irem
    //   110: ifeq +6 -> 116
    //   113: goto -101 -> 12
    //   116: goto -113 -> 3
    // Local variable table:
    //   start	length	slot	name	signature
    //   0	119	0	this	Lv
    //   5	105	1	i	int
    //   27	62	2	j	int
    //   9	2	3	localException	Exception
    // Exception table:
    //   from	to	target	type
    //   46	50	9	java/lang/Exception
    //   80	89	9	java/lang/Exception
  }
  
  public final void ˏ(FM paramFM)
  {
    for (;;)
    {
      vq.ˎ(paramFM, ˋ(getApplicationInfo().targetSdkVersion + 146, (char)(getPackageName().codePointAt(7) + 9070), getPackageName().length() - 7).intern());
      Intent localIntent = new Intent();
      localIntent.putExtra(ˋ(getPackageName().length() + 164, (char)(getResources().getString(2131755476).substring(0, 5).codePointAt(2) + 49983), getResources().getString(2131755139).substring(0, 4).length() + 11).intern(), paramFM.ˊ());
      localIntent.putExtra(ˋ(getApplicationInfo().targetSdkVersion + 165, (char)(getApplicationInfo().targetSdkVersion + 31169), getResources().getString(2131755325).substring(0, 5).codePointAt(3) + 3).intern(), paramFM.ˏ());
      setResult(-1, localIntent);
      finish();
      break;
    }
    int i = ˋˊ + 51;
    ˊˊ = i % 128;
    if (i % 2 == 0) {}
  }
  
  public static final class If
    extends Ik<EW>
  {
    private static int ˋ = 0;
    private static int ˏ = 1;
    private static char[] ॱ = { 221, 223, 215, 224, 222, 208, 85, 148, 146, 168, 166, 163, 168, 167 };
    
    If(vv.if paramIf, Context paramContext)
    {
      super();
    }
    
    private static String ˎ(int[] paramArrayOfInt, byte[] paramArrayOfByte, boolean paramBoolean)
    {
      break label265;
      int i = ˋ + 49;
      ˏ = i % 128;
      label29:
      label66:
      int m;
      int n;
      int i1;
      char[] arrayOfChar2;
      char[] arrayOfChar1;
      label132:
      label135:
      label138:
      int k;
      if (i % 2 != 0)
      {
        return paramArrayOfInt;
        if (paramBoolean) {
          break label571;
        }
        break label451;
        for (;;)
        {
          i = ˏ + 123;
          ˋ = i % 128;
          if (i % 2 != 0) {
            break label144;
          }
          break label333;
          i = paramArrayOfInt[0];
          m = paramArrayOfInt[1];
          n = paramArrayOfInt[2];
          i1 = paramArrayOfInt[3];
          try
          {
            arrayOfChar2 = ॱ;
            arrayOfChar1 = new char[m];
            System.arraycopy(arrayOfChar2, i, arrayOfChar1, 0, m);
            if (paramArrayOfByte == null) {
              paramArrayOfByte = arrayOfChar1;
            }
          }
          catch (Exception paramArrayOfInt)
          {
            label144:
            throw paramArrayOfInt;
          }
        }
        if (i >= m)
        {
          break label480;
          break label492;
          break label492;
          k = 1;
          break label224;
          break label333;
        }
        for (;;)
        {
          switch (i)
          {
          default: 
            break label480;
            paramArrayOfByte[i] = ((char)(paramArrayOfByte[i] - paramArrayOfInt[2]));
            i += 1;
            break;
            k = 0;
            break;
          case 0: 
            label193:
            i = 0;
            break;
            label207:
            paramArrayOfByte = arrayOfChar1;
            break label451;
            label213:
            i = 1;
            continue;
            label218:
            k = 0;
            break label542;
            switch (k)
            {
            default: 
              label224:
              break label421;
              label251:
              if (i1 > 0) {
                break label374;
              }
              break label29;
              label262:
              break label519;
              label265:
              break label66;
              label268:
              i = 0;
            }
            break;
          }
        }
      }
      int j;
      for (;;)
      {
        if (j < m) {
          break label138;
        }
        break label193;
        return paramArrayOfInt;
        label288:
        arrayOfChar1[i] = paramArrayOfByte[(m - i - 1)];
        i += 1;
        break label507;
        label307:
        k = 1;
        break label542;
        arrayOfChar2[j] = ((char)((arrayOfChar1[j] << '\001') + 1 - i));
        break label347;
        label333:
        arrayOfChar2 = new char[m];
        i = 0;
        j = 0;
        continue;
        label347:
        i = ˏ + 115;
        ˋ = i % 128;
        if (i % 2 != 0) {
          break label533;
        }
        break label132;
        label374:
        arrayOfChar1 = new char[m];
        System.arraycopy(paramArrayOfByte, 0, arrayOfChar1, 0, m);
        System.arraycopy(arrayOfChar1, 0, paramArrayOfByte, m - i1, i1);
        System.arraycopy(arrayOfChar1, i1, paramArrayOfByte, 0, m - i1);
        break label29;
        label421:
        k = ˋ + 93;
        ˏ = k % 128;
        if (k % 2 == 0) {
          break label262;
        }
        break label519;
        label451:
        if (n > 0) {
          break label268;
        }
        break label213;
        label462:
        arrayOfChar2[j] = ((char)((arrayOfChar1[j] << '\001') - i));
        break label135;
        label480:
        paramArrayOfInt = new String(paramArrayOfByte);
        break;
        label492:
        i = arrayOfChar2[j];
        j += 1;
      }
      for (;;)
      {
        label507:
        if (i < m) {
          break label288;
        }
        break label207;
        label519:
        if (paramArrayOfByte[j] == 1) {
          break label218;
        }
        break label307;
        label533:
        break;
        paramArrayOfByte = arrayOfChar2;
        break label251;
        label542:
        switch (k)
        {
        }
        break label462;
        label571:
        arrayOfChar1 = new char[m];
        i = 0;
      }
    }
    
    /* Error */
    public void ˏ()
    {
      // Byte code:
      //   0: goto +359 -> 359
      //   3: iload_1
      //   4: tableswitch	default:+24->28, 0:+195->199, 1:+300->304
      //   28: goto +171 -> 199
      //   31: astore_2
      //   32: aload_2
      //   33: athrow
      //   34: bipush 20
      //   36: istore_1
      //   37: goto +330 -> 367
      //   40: aload_0
      //   41: invokespecial 67	o/Ik:ˏ	()V
      //   44: aload_0
      //   45: getfield 44	o/Lv$If:ˎ	Lo/Lv;
      //   48: invokestatic 70	o/Lv:ˊ	(Lo/Lv;)Lo/LA;
      //   51: astore_2
      //   52: aload_2
      //   53: iconst_4
      //   54: newarray int
      //   56: dup
      //   57: iconst_0
      //   58: bipush 6
      //   60: iastore
      //   61: dup
      //   62: iconst_1
      //   63: bipush 8
      //   65: iastore
      //   66: dup
      //   67: iconst_2
      //   68: bipush 61
      //   70: iastore
      //   71: dup
      //   72: iconst_3
      //   73: bipush 8
      //   75: iastore
      //   76: bipush 8
      //   78: newarray byte
      //   80: dup
      //   81: iconst_0
      //   82: ldc 71
      //   84: bastore
      //   85: dup
      //   86: iconst_1
      //   87: ldc 72
      //   89: bastore
      //   90: dup
      //   91: iconst_2
      //   92: ldc 72
      //   94: bastore
      //   95: dup
      //   96: iconst_3
      //   97: ldc 72
      //   99: bastore
      //   100: dup
      //   101: iconst_4
      //   102: ldc 71
      //   104: bastore
      //   105: dup
      //   106: iconst_5
      //   107: ldc 72
      //   109: bastore
      //   110: dup
      //   111: bipush 6
      //   113: ldc 72
      //   115: bastore
      //   116: dup
      //   117: bipush 7
      //   119: ldc 72
      //   121: bastore
      //   122: iconst_0
      //   123: invokestatic 74	o/Lv$If:ˎ	([I[BZ)Ljava/lang/String;
      //   126: invokevirtual 78	java/lang/String:intern	()Ljava/lang/String;
      //   129: invokestatic 83	o/vq:ˋ	(Ljava/lang/Object;Ljava/lang/String;)V
      //   132: aload_2
      //   133: iconst_0
      //   134: invokevirtual 88	o/LA:ˏ	(Z)V
      //   137: aload_0
      //   138: getfield 46	o/Lv$If:ˊ	Lo/vv$if;
      //   141: getfield 93	o/vv$if:ˎ	Z
      //   144: ifne +6 -> 150
      //   147: goto +17 -> 164
      //   150: goto +149 -> 299
      //   153: bipush 11
      //   155: istore_1
      //   156: goto +211 -> 367
      //   159: iconst_1
      //   160: istore_1
      //   161: goto +144 -> 305
      //   164: iconst_0
      //   165: istore_1
      //   166: goto -163 -> 3
      //   169: goto +129 -> 298
      //   172: getstatic 22	o/Lv$If:ˋ	I
      //   175: bipush 115
      //   177: iadd
      //   178: istore_1
      //   179: iload_1
      //   180: sipush 128
      //   183: irem
      //   184: putstatic 24	o/Lv$If:ˏ	I
      //   187: iload_1
      //   188: iconst_2
      //   189: irem
      //   190: ifne +6 -> 196
      //   193: goto -34 -> 159
      //   196: goto +166 -> 362
      //   199: aload_0
      //   200: getfield 44	o/Lv$If:ˎ	Lo/Lv;
      //   203: invokestatic 70	o/Lv:ˊ	(Lo/Lv;)Lo/LA;
      //   206: astore_2
      //   207: aload_2
      //   208: iconst_4
      //   209: newarray int
      //   211: dup
      //   212: iconst_0
      //   213: bipush 6
      //   215: iastore
      //   216: dup
      //   217: iconst_1
      //   218: bipush 8
      //   220: iastore
      //   221: dup
      //   222: iconst_2
      //   223: bipush 61
      //   225: iastore
      //   226: dup
      //   227: iconst_3
      //   228: bipush 8
      //   230: iastore
      //   231: bipush 8
      //   233: newarray byte
      //   235: dup
      //   236: iconst_0
      //   237: ldc 71
      //   239: bastore
      //   240: dup
      //   241: iconst_1
      //   242: ldc 72
      //   244: bastore
      //   245: dup
      //   246: iconst_2
      //   247: ldc 72
      //   249: bastore
      //   250: dup
      //   251: iconst_3
      //   252: ldc 72
      //   254: bastore
      //   255: dup
      //   256: iconst_4
      //   257: ldc 71
      //   259: bastore
      //   260: dup
      //   261: iconst_5
      //   262: ldc 72
      //   264: bastore
      //   265: dup
      //   266: bipush 6
      //   268: ldc 72
      //   270: bastore
      //   271: dup
      //   272: bipush 7
      //   274: ldc 72
      //   276: bastore
      //   277: iconst_0
      //   278: invokestatic 74	o/Lv$If:ˎ	([I[BZ)Ljava/lang/String;
      //   281: invokevirtual 78	java/lang/String:intern	()Ljava/lang/String;
      //   284: invokestatic 83	o/vq:ˋ	(Ljava/lang/Object;Ljava/lang/String;)V
      //   287: aload_2
      //   288: iconst_1
      //   289: invokevirtual 95	o/LA:ˋ	(Z)V
      //   292: goto +39 -> 331
      //   295: astore_2
      //   296: aload_2
      //   297: athrow
      //   298: return
      //   299: iconst_1
      //   300: istore_1
      //   301: goto -298 -> 3
      //   304: return
      //   305: iload_1
      //   306: tableswitch	default:+22->328, 0:+-266->40, 1:+91->397
      //   328: goto -288 -> 40
      //   331: getstatic 24	o/Lv$If:ˏ	I
      //   334: istore_1
      //   335: iload_1
      //   336: iconst_1
      //   337: iadd
      //   338: istore_1
      //   339: iload_1
      //   340: sipush 128
      //   343: irem
      //   344: putstatic 22	o/Lv$If:ˋ	I
      //   347: iload_1
      //   348: iconst_2
      //   349: irem
      //   350: ifeq +6 -> 356
      //   353: goto -184 -> 169
      //   356: goto -58 -> 298
      //   359: goto -187 -> 172
      //   362: iconst_0
      //   363: istore_1
      //   364: goto -59 -> 305
      //   367: iload_1
      //   368: lookupswitch	default:+28->396, 11:+-169->199, 20:+-64->304
      //   396: return
      //   397: aload_0
      //   398: invokespecial 67	o/Ik:ˏ	()V
      //   401: aload_0
      //   402: getfield 44	o/Lv$If:ˎ	Lo/Lv;
      //   405: invokestatic 70	o/Lv:ˊ	(Lo/Lv;)Lo/LA;
      //   408: astore_2
      //   409: aload_2
      //   410: iconst_4
      //   411: newarray int
      //   413: dup
      //   414: iconst_0
      //   415: bipush 6
      //   417: iastore
      //   418: dup
      //   419: iconst_1
      //   420: bipush 8
      //   422: iastore
      //   423: dup
      //   424: iconst_2
      //   425: bipush 61
      //   427: iastore
      //   428: dup
      //   429: iconst_3
      //   430: bipush 8
      //   432: iastore
      //   433: bipush 8
      //   435: newarray byte
      //   437: dup
      //   438: iconst_0
      //   439: ldc 71
      //   441: bastore
      //   442: dup
      //   443: iconst_1
      //   444: ldc 72
      //   446: bastore
      //   447: dup
      //   448: iconst_2
      //   449: ldc 72
      //   451: bastore
      //   452: dup
      //   453: iconst_3
      //   454: ldc 72
      //   456: bastore
      //   457: dup
      //   458: iconst_4
      //   459: ldc 71
      //   461: bastore
      //   462: dup
      //   463: iconst_5
      //   464: ldc 72
      //   466: bastore
      //   467: dup
      //   468: bipush 6
      //   470: ldc 72
      //   472: bastore
      //   473: dup
      //   474: bipush 7
      //   476: ldc 72
      //   478: bastore
      //   479: iconst_0
      //   480: invokestatic 74	o/Lv$If:ˎ	([I[BZ)Ljava/lang/String;
      //   483: invokevirtual 78	java/lang/String:intern	()Ljava/lang/String;
      //   486: invokestatic 83	o/vq:ˋ	(Ljava/lang/Object;Ljava/lang/String;)V
      //   489: aload_2
      //   490: iconst_1
      //   491: invokevirtual 88	o/LA:ˏ	(Z)V
      //   494: aload_0
      //   495: getfield 46	o/Lv$If:ˊ	Lo/vv$if;
      //   498: getfield 93	o/vv$if:ˎ	Z
      //   501: ifne +6 -> 507
      //   504: goto -351 -> 153
      //   507: goto -473 -> 34
      // Local variable table:
      //   start	length	slot	name	signature
      //   0	510	0	this	If
      //   3	365	1	i	int
      //   31	2	2	localException1	Exception
      //   51	237	2	localLA1	LA
      //   295	2	2	localException2	Exception
      //   408	82	2	localLA2	LA
      // Exception table:
      //   from	to	target	type
      //   331	335	31	java/lang/Exception
      //   339	347	295	java/lang/Exception
    }
    
    /* Error */
    protected void ˏ(EW paramEW)
    {
      // Byte code:
      //   0: goto +74 -> 74
      //   3: getstatic 24	o/Lv$If:ˏ	I
      //   6: bipush 89
      //   8: iadd
      //   9: istore_2
      //   10: iload_2
      //   11: sipush 128
      //   14: irem
      //   15: putstatic 22	o/Lv$If:ˋ	I
      //   18: iload_2
      //   19: iconst_2
      //   20: irem
      //   21: ifeq +6 -> 27
      //   24: goto +357 -> 381
      //   27: goto +139 -> 166
      //   30: iconst_1
      //   31: istore_2
      //   32: goto +304 -> 336
      //   35: iload_2
      //   36: tableswitch	default:+24->60, 0:+41->77, 1:+-6->30
      //   60: goto -30 -> 30
      //   63: iconst_1
      //   64: istore_2
      //   65: goto -30 -> 35
      //   68: bipush 60
      //   70: istore_2
      //   71: goto +282 -> 353
      //   74: goto +14 -> 88
      //   77: iconst_0
      //   78: istore_2
      //   79: goto +270 -> 349
      //   82: bipush 11
      //   84: istore_2
      //   85: goto +268 -> 353
      //   88: getstatic 24	o/Lv$If:ˏ	I
      //   91: bipush 77
      //   93: iadd
      //   94: istore_2
      //   95: iload_2
      //   96: sipush 128
      //   99: irem
      //   100: putstatic 22	o/Lv$If:ˋ	I
      //   103: iload_2
      //   104: iconst_2
      //   105: irem
      //   106: ifeq +6 -> 112
      //   109: goto +237 -> 346
      //   112: aload_1
      //   113: iconst_4
      //   114: newarray int
      //   116: dup
      //   117: iconst_0
      //   118: iconst_0
      //   119: iastore
      //   120: dup
      //   121: iconst_1
      //   122: bipush 6
      //   124: iastore
      //   125: dup
      //   126: iconst_2
      //   127: bipush 107
      //   129: iastore
      //   130: dup
      //   131: iconst_3
      //   132: iconst_1
      //   133: iastore
      //   134: aconst_null
      //   135: iconst_1
      //   136: invokestatic 74	o/Lv$If:ˎ	([I[BZ)Ljava/lang/String;
      //   139: invokevirtual 78	java/lang/String:intern	()Ljava/lang/String;
      //   142: invokestatic 103	o/vq:ˎ	(Ljava/lang/Object;Ljava/lang/String;)V
      //   145: aload_1
      //   146: invokevirtual 106	o/EW:ˎ	()Ljava/util/List;
      //   149: checkcast 108	java/util/Collection
      //   152: invokeinterface 112 1 0
      //   157: ifne +6 -> 163
      //   160: goto -97 -> 63
      //   163: goto +221 -> 384
      //   166: aload_0
      //   167: getfield 46	o/Lv$If:ˊ	Lo/vv$if;
      //   170: iconst_1
      //   171: putfield 93	o/vv$if:ˎ	Z
      //   174: aload_0
      //   175: getfield 44	o/Lv$If:ˎ	Lo/Lv;
      //   178: aload_1
      //   179: invokevirtual 106	o/EW:ˎ	()Ljava/util/List;
      //   182: iconst_0
      //   183: invokeinterface 118 2 0
      //   188: checkcast 120	o/FL
      //   191: invokevirtual 122	o/FL:ˊ	()Ljava/lang/String;
      //   194: invokestatic 125	o/Lv:ˏ	(Lo/Lv;Ljava/lang/String;)V
      //   197: iconst_4
      //   198: sipush 413
      //   201: sipush 30253
      //   204: invokestatic 130	o/O:ˋ	(IIC)Ljava/lang/Object;
      //   207: checkcast 132	java/lang/Class
      //   210: ldc -123
      //   212: invokevirtual 137	java/lang/Class:getField	(Ljava/lang/String;)Ljava/lang/reflect/Field;
      //   215: aconst_null
      //   216: invokevirtual 142	java/lang/reflect/Field:get	(Ljava/lang/Object;)Ljava/lang/Object;
      //   219: astore_3
      //   220: goto +17 -> 237
      //   223: astore_1
      //   224: aload_1
      //   225: invokevirtual 148	java/lang/Throwable:getCause	()Ljava/lang/Throwable;
      //   228: astore_3
      //   229: aload_3
      //   230: ifnull +5 -> 235
      //   233: aload_3
      //   234: athrow
      //   235: aload_1
      //   236: athrow
      //   237: bipush 6
      //   239: sipush 417
      //   242: iconst_0
      //   243: invokestatic 130	o/O:ˋ	(IIC)Ljava/lang/Object;
      //   246: checkcast 132	java/lang/Class
      //   249: ldc -107
      //   251: aconst_null
      //   252: invokevirtual 153	java/lang/Class:getMethod	(Ljava/lang/String;[Ljava/lang/Class;)Ljava/lang/reflect/Method;
      //   255: aload_3
      //   256: aconst_null
      //   257: invokevirtual 159	java/lang/reflect/Method:invoke	(Ljava/lang/Object;[Ljava/lang/Object;)Ljava/lang/Object;
      //   260: astore_3
      //   261: aload_1
      //   262: invokevirtual 106	o/EW:ˎ	()Ljava/util/List;
      //   265: iconst_0
      //   266: invokeinterface 118 2 0
      //   271: checkcast 120	o/FL
      //   274: invokevirtual 122	o/FL:ˊ	()Ljava/lang/String;
      //   277: astore_1
      //   278: goto +17 -> 295
      //   281: astore_1
      //   282: aload_1
      //   283: invokevirtual 148	java/lang/Throwable:getCause	()Ljava/lang/Throwable;
      //   286: astore_3
      //   287: aload_3
      //   288: ifnull +5 -> 293
      //   291: aload_3
      //   292: athrow
      //   293: aload_1
      //   294: athrow
      //   295: iconst_4
      //   296: sipush 413
      //   299: sipush 30253
      //   302: invokestatic 130	o/O:ˋ	(IIC)Ljava/lang/Object;
      //   305: checkcast 132	java/lang/Class
      //   308: ldc -95
      //   310: iconst_1
      //   311: anewarray 132	java/lang/Class
      //   314: dup
      //   315: iconst_0
      //   316: ldc 62
      //   318: aastore
      //   319: invokevirtual 153	java/lang/Class:getMethod	(Ljava/lang/String;[Ljava/lang/Class;)Ljava/lang/reflect/Method;
      //   322: aload_3
      //   323: iconst_1
      //   324: anewarray 163	java/lang/Object
      //   327: dup
      //   328: iconst_0
      //   329: aload_1
      //   330: aastore
      //   331: invokevirtual 159	java/lang/reflect/Method:invoke	(Ljava/lang/Object;[Ljava/lang/Object;)Ljava/lang/Object;
      //   334: pop
      //   335: return
      //   336: iload_2
      //   337: ifeq +6 -> 343
      //   340: goto -272 -> 68
      //   343: goto -261 -> 82
      //   346: goto -234 -> 112
      //   349: goto -13 -> 336
      //   352: return
      //   353: iload_2
      //   354: lookupswitch	default:+26->380, 11:+-2->352, 60:+-351->3
      //   380: return
      //   381: goto -215 -> 166
      //   384: iconst_0
      //   385: istore_2
      //   386: goto -351 -> 35
      // Local variable table:
      //   start	length	slot	name	signature
      //   0	389	0	this	If
      //   0	389	1	paramEW	EW
      //   9	377	2	i	int
      //   219	104	3	localObject	Object
      // Exception table:
      //   from	to	target	type
      //   237	261	223	finally
      //   295	335	281	finally
    }
  }
  
  public static final class iF
    extends Hp
  {
    private static int ˊ = 1;
    private static char[] ˎ = { 187, 187, 191, 172 };
    private static int ॱ = 0;
    
    iF() {}
    
    private static String ˋ(int[] paramArrayOfInt, byte[] paramArrayOfByte, boolean paramBoolean)
    {
      break label304;
      int n;
      int i;
      int k;
      label79:
      label114:
      int m;
      label132:
      label137:
      int j;
      label144:
      char[] arrayOfChar2;
      char[] arrayOfChar1;
      if (n <= 0)
      {
        break label132;
        for (;;)
        {
          try
          {
            i = ॱ;
            i += 123;
            try
            {
              ˊ = i % 128;
              if (i % 2 == 0) {
                break;
              }
            }
            catch (Exception paramArrayOfInt)
            {
              throw paramArrayOfInt;
            }
            continue;
            i = 0;
          }
          catch (Exception paramArrayOfInt)
          {
            throw paramArrayOfInt;
          }
          switch (k)
          {
          }
        }
        break label549;
        for (;;)
        {
          break label431;
          for (;;)
          {
            switch (i)
            {
            case 0: 
            default: 
              break label682;
              i = 1;
              break label144;
              paramArrayOfByte = new char[m];
              i = 0;
              break label262;
              break label532;
              i = 1;
            }
          }
          j = 31;
          break label646;
          arrayOfChar1 = arrayOfChar2;
          switch (i)
          {
          default: 
            break label307;
            label175:
            j = ˊ + 21;
            ॱ = j % 128;
            if (j % 2 == 0) {
              break label431;
            }
            break;
          }
        }
      }
      label205:
      label262:
      label277:
      label304:
      label307:
      label343:
      label353:
      label383:
      label418:
      label431:
      label450:
      label532:
      label543:
      label549:
      label552:
      label577:
      label616:
      label646:
      label682:
      label691:
      label694:
      label697:
      label717:
      label747:
      for (;;)
      {
        i = paramArrayOfInt[0];
        m = paramArrayOfInt[1];
        n = paramArrayOfInt[2];
        int i1 = paramArrayOfInt[3];
        arrayOfChar1 = ˎ;
        arrayOfChar2 = new char[m];
        System.arraycopy(arrayOfChar1, i, arrayOfChar2, 0, m);
        if (paramArrayOfByte == null)
        {
          break label114;
          for (;;)
          {
            i = 51;
            break label383;
            if (i < m) {
              break label137;
            }
            break label552;
            i = arrayOfChar1[j];
            j += 1;
            break label418;
            do
            {
              i = 90;
              break label383;
              do
              {
                k = 2;
                break label353;
                break label450;
                arrayOfChar1 = new char[m];
                i = 0;
                j = 0;
                break label616;
                i = 0;
                break;
                break label532;
              } while (paramArrayOfByte[j] == 1);
              break label717;
            } while (paramBoolean);
          }
          switch (k)
          {
          default: 
            break label697;
            paramArrayOfByte = arrayOfChar1;
            switch (i)
            {
            }
            paramArrayOfByte = arrayOfChar1;
            break;
            for (;;)
            {
              if (j >= m)
              {
                break label543;
                paramArrayOfByte[i] = arrayOfChar1[(m - i - 1)];
                i += 1;
                break label262;
                i = ˊ + 29;
                ॱ = i % 128;
                if (i % 2 != 0) {
                  break label747;
                }
                break label205;
              }
              do
              {
                paramArrayOfByte = new char[m];
                System.arraycopy(arrayOfChar1, 0, paramArrayOfByte, 0, m);
                System.arraycopy(paramArrayOfByte, 0, arrayOfChar1, m - i1, i1);
                System.arraycopy(paramArrayOfByte, i1, arrayOfChar1, 0, m - i1);
                break label343;
                break label577;
                k = 0;
                break;
              } while (i1 > 0);
              break label343;
              k = 1;
              break;
            }
            j = 95;
            break;
          case 96: 
            arrayOfChar1[j] = ((char)((arrayOfChar2[j] << '\001') - i));
            break label694;
            i = ˊ + 65;
            ॱ = i % 128;
            if (i % 2 != 0) {}
            break;
          }
        }
        for (;;)
        {
          if (i >= m)
          {
            break label682;
            k = ॱ + 45;
            ˊ = k % 128;
            if (k % 2 == 0) {
              break label79;
            }
            break label549;
            switch (j)
            {
            }
            break label175;
            break label691;
            return new String(paramArrayOfByte);
            break;
            break label277;
            arrayOfChar1[j] = ((char)((arrayOfChar2[j] << '\001') + 1 - i));
            break label277;
            k = 96;
            break label353;
            i = 0;
            break label144;
          }
          paramArrayOfByte[i] = ((char)(paramArrayOfByte[i] - paramArrayOfInt[2]));
          i += 1;
        }
      }
    }
    
    /* Error */
    public void ˏ(String paramString)
    {
      // Byte code:
      //   0: goto +103 -> 103
      //   3: astore_1
      //   4: aload_1
      //   5: athrow
      //   6: getstatic 21	o/Lv$iF:ˊ	I
      //   9: bipush 125
      //   11: iadd
      //   12: istore_2
      //   13: iload_2
      //   14: sipush 128
      //   17: irem
      //   18: putstatic 19	o/Lv$iF:ॱ	I
      //   21: iload_2
      //   22: iconst_2
      //   23: irem
      //   24: ifeq +6 -> 30
      //   27: goto +129 -> 156
      //   30: goto +121 -> 151
      //   33: astore_1
      //   34: aload_1
      //   35: athrow
      //   36: aload_1
      //   37: iconst_4
      //   38: newarray int
      //   40: dup
      //   41: iconst_0
      //   42: iconst_0
      //   43: iastore
      //   44: dup
      //   45: iconst_1
      //   46: iconst_4
      //   47: iastore
      //   48: dup
      //   49: iconst_2
      //   50: bipush 71
      //   52: iastore
      //   53: dup
      //   54: iconst_3
      //   55: iconst_1
      //   56: iastore
      //   57: aconst_null
      //   58: iconst_1
      //   59: invokestatic 52	o/Lv$iF:ˋ	([I[BZ)Ljava/lang/String;
      //   62: invokevirtual 56	java/lang/String:intern	()Ljava/lang/String;
      //   65: invokestatic 61	o/vq:ˎ	(Ljava/lang/Object;Ljava/lang/String;)V
      //   68: aload_0
      //   69: getfield 31	o/Lv$iF:ˏ	Lo/Lv;
      //   72: aload_1
      //   73: invokestatic 64	o/Lv:ˋ	(Lo/Lv;Ljava/lang/String;)V
      //   76: return
      //   77: iload_2
      //   78: tableswitch	default:+22->100, 0:+28->106, 1:+-42->36
      //   100: goto -64 -> 36
      //   103: goto -97 -> 6
      //   106: iconst_4
      //   107: newarray int
      //   109: dup
      //   110: iconst_0
      //   111: iconst_0
      //   112: iastore
      //   113: dup
      //   114: iconst_1
      //   115: iconst_4
      //   116: iastore
      //   117: dup
      //   118: iconst_2
      //   119: bipush 71
      //   121: iastore
      //   122: dup
      //   123: iconst_3
      //   124: iconst_1
      //   125: iastore
      //   126: aconst_null
      //   127: iconst_1
      //   128: invokestatic 52	o/Lv$iF:ˋ	([I[BZ)Ljava/lang/String;
      //   131: astore_3
      //   132: aload_3
      //   133: invokevirtual 56	java/lang/String:intern	()Ljava/lang/String;
      //   136: astore_3
      //   137: aload_1
      //   138: aload_3
      //   139: invokestatic 61	o/vq:ˎ	(Ljava/lang/Object;Ljava/lang/String;)V
      //   142: aload_0
      //   143: getfield 31	o/Lv$iF:ˏ	Lo/Lv;
      //   146: aload_1
      //   147: invokestatic 64	o/Lv:ˋ	(Lo/Lv;Ljava/lang/String;)V
      //   150: return
      //   151: iconst_1
      //   152: istore_2
      //   153: goto -76 -> 77
      //   156: iconst_0
      //   157: istore_2
      //   158: goto -81 -> 77
      // Local variable table:
      //   start	length	slot	name	signature
      //   0	161	0	this	iF
      //   0	161	1	paramString	String
      //   12	146	2	i	int
      //   131	8	3	str	String
      // Exception table:
      //   from	to	target	type
      //   106	132	3	java/lang/Exception
      //   132	137	3	java/lang/Exception
      //   137	142	33	java/lang/Exception
      //   142	150	33	java/lang/Exception
    }
  }
  
  public static final class ˊ
    extends Ik<EZ>
  {
    private static int ʻ;
    private static int ʽ = 0;
    private static int ˊ = -1899737237;
    private static byte[] ˋ;
    private static int ˏ = 1043483293;
    private static int ॱ;
    private static short[] ॱॱ;
    
    static
    {
      ʻ = 1;
      ॱ = 72;
      ˋ = new byte[] { -66, 8, -9, 2, 14, -13, -64, -7, 5, 5, -10, 5, 39, -43 };
    }
    
    /* Error */
    ˊ(Context paramContext)
    {
      // Byte code:
      //   0: goto +6 -> 6
      //   3: astore_1
      //   4: aload_1
      //   5: athrow
      //   6: aload_0
      //   7: aload_1
      //   8: putfield 56	o/Lv$ˊ:ˎ	Lo/Lv;
      //   11: aload_0
      //   12: aload_2
      //   13: invokespecial 59	o/Ik:<init>	(Landroid/content/Context;)V
      //   16: return
      // Local variable table:
      //   start	length	slot	name	signature
      //   0	17	0	this	ˊ
      //   0	17	1	paramContext	Context
      //   12	1	2	localContext	Context
      // Exception table:
      //   from	to	target	type
      //   6	16	3	java/lang/Exception
    }
    
    private static String ॱ(short paramShort, int paramInt1, byte paramByte, int paramInt2, int paramInt3)
    {
      break label363;
      label3:
      Object localObject2 = ॱॱ;
      int j = paramInt1 - 1;
      int k;
      int i = (char)(((short)(localObject2[paramInt1] + paramShort) ^ paramByte) + k);
      break label255;
      paramInt3 = ʽ + 19;
      ʻ = paramInt3 % 128;
      if (paramInt3 % 2 != 0)
      {
        break label943;
        label61:
        k = paramInt1 / paramInt3 - 4 << ˏ;
        if (j != 0) {
          break label372;
        }
        break label553;
      }
      label84:
      label117:
      label150:
      label162:
      label192:
      label223:
      label255:
      Object localObject1;
      label295:
      label325:
      label363:
      label372:
      int m;
      switch (j)
      {
      default: 
        break;
        paramInt3 = 1;
        break label793;
        switch (paramInt1)
        {
        default: 
          break label691;
          do
          {
            break label1046;
            if (paramInt2 < paramInt3) {
              break label819;
            }
            break;
            paramInt3 = ʻ + 19;
            ʽ = paramInt3 % 128;
          } while (paramInt3 % 2 != 0);
        }
        break;
      case 0: 
        for (;;)
        {
          switch (k)
          {
          case 30: 
          default: 
            break label61;
            for (;;)
            {
              switch (j)
              {
              case 64: 
              default: 
                break label3;
                paramInt1 = ʽ + 31;
                ʻ = paramInt1 % 128;
                if (paramInt1 % 2 == 0) {
                  break label619;
                }
                break label1004;
                localObject1 = ˋ;
                throw new NullPointerException();
                k = ʻ + 71;
                ʽ = k % 128;
                if (k % 2 != 0) {
                  break label763;
                }
                break label543;
                j = 64;
              }
            }
            localObject2 = ˋ;
            j = paramInt1 - 1;
            i = (char)(((byte)(localObject2[paramInt1] + paramShort) ^ paramByte) + k);
            paramInt1 = j;
            break label497;
            break label385;
            paramInt1 = j;
            break label497;
            m = 1;
            break label887;
            label378:
            k = 30;
          }
        }
        label385:
        localObject1 = new StringBuilder();
        j = ॱ + paramInt3;
        paramInt3 = j;
        if (j == -1) {
          break label751;
        }
        break label663;
        label418:
        j = ʻ + 33;
        ʽ = j % 128;
        if (j % 2 != 0) {}
        break;
      }
      for (;;)
      {
        label448:
        paramInt1 += j;
        i = (char)(ˊ + paramInt2);
        ((StringBuilder)localObject1).append(i);
        paramInt2 = 1;
        k = i;
        break label150;
        for (;;)
        {
          m = 1;
          break label1010;
          k = 13;
          break label192;
          label491:
          paramShort = 47;
          break label855;
          label497:
          ((StringBuilder)localObject1).append(i);
          paramInt2 += 1;
          break label418;
          switch (j)
          {
          default: 
            break;
          case 73: 
            for (;;)
            {
              label512:
              label543:
              k = i;
              break label150;
              label553:
              m = 50;
              break label887;
              for (;;)
              {
                try
                {
                  paramShort = ʽ;
                  paramShort += 85;
                  ʻ = paramShort % 128;
                  if (paramShort % 2 == 0) {
                    break label491;
                  }
                }
                catch (Exception localException1)
                {
                  label589:
                  label619:
                  label663:
                  throw localException1;
                }
                k = ʻ + 47;
                try
                {
                  ʽ = k % 128;
                  if (k % 2 != 0) {
                    break label378;
                  }
                }
                catch (Exception localException2)
                {
                  String str;
                  throw localException2;
                }
                paramInt1 = 42;
                break label117;
                localObject2 = ˋ;
                j = paramInt1 + 32;
                i = (char)(k - ((byte)(localObject2[paramInt1] + paramShort) | paramByte));
                paramInt1 = j;
                break label497;
                j = 1;
                break label295;
                j = 18;
                break label512;
                label675:
                j = 1;
                break;
                label681:
                str = localException1.toString();
              }
              label691:
              paramInt1 = 5 / 4;
              paramInt1 = j;
              break label497;
            }
            k = paramInt1 + paramInt3 - 2 + ˏ;
            if (j != 0) {
              break label937;
            }
          }
        }
        k = 1;
        paramInt1 = j;
        j = k;
      }
      for (;;)
      {
        label740:
        if (paramInt3 > 0) {
          break label589;
        }
        break label681;
        label751:
        j = 73;
        break label512;
        label763:
        break label543;
        label793:
        label819:
        do
        {
          j = 25;
          break label223;
          return localException2;
          while (j == 0)
          {
            break label740;
            j = 0;
          }
          switch (paramInt3)
          {
          case 1: 
          default: 
            break label843;
          }
        } while (ˋ != null);
        break label325;
        paramShort = 53;
        break label855;
        label837:
        j = 0;
        break label84;
        label843:
        if (ˋ != null) {
          break label162;
        }
        break label985;
        switch (paramShort)
        {
        case 53: 
        default: 
          label855:
          break label949;
          label887:
          j = k;
          paramInt1 = k;
          switch (m)
          {
          case 1: 
          default: 
            j = k;
          }
          break;
        }
        for (;;)
        {
          j = 0;
          break label448;
          label937:
          m = 0;
          break label1010;
          label943:
          paramInt3 = 0;
          break label793;
          label949:
          paramShort = null.length;
          return localException2;
          j = ʻ + 9;
          ʽ = j % 128;
          if (j % 2 != 0) {
            break label675;
          }
          break label837;
          label985:
          paramInt3 = (short)(ॱॱ[(ˏ + paramInt1)] + ॱ);
          break label740;
          label1004:
          paramInt1 = 92;
          break;
          label1010:
          j = k;
          paramInt1 = k;
          switch (m)
          {
          }
          paramInt1 = k;
        }
        label1046:
        paramInt3 = (byte)(ˋ[(ˏ + paramInt1)] + ॱ);
      }
    }
    
    /* Error */
    public void ˏ()
    {
      // Byte code:
      //   0: goto +235 -> 235
      //   3: aload_0
      //   4: getfield 56	o/Lv$ˊ:ˎ	Lo/Lv;
      //   7: invokestatic 81	o/Lv:ˊ	(Lo/Lv;)Lo/LA;
      //   10: astore_2
      //   11: aload_2
      //   12: iconst_0
      //   13: ldc 82
      //   15: iconst_0
      //   16: ldc 83
      //   18: bipush -73
      //   20: invokestatic 85	o/Lv$ˊ:ॱ	(SIBII)Ljava/lang/String;
      //   23: invokevirtual 90	java/lang/String:intern	()Ljava/lang/String;
      //   26: invokestatic 95	o/vq:ˋ	(Ljava/lang/Object;Ljava/lang/String;)V
      //   29: aload_2
      //   30: iconst_1
      //   31: invokevirtual 100	o/LA:ˋ	(Z)V
      //   34: goto +194 -> 228
      //   37: bipush 83
      //   39: istore_1
      //   40: goto +148 -> 188
      //   43: getstatic 27	o/Lv$ˊ:ʻ	I
      //   46: istore_1
      //   47: iload_1
      //   48: bipush 19
      //   50: iadd
      //   51: istore_1
      //   52: iload_1
      //   53: sipush 128
      //   56: irem
      //   57: putstatic 25	o/Lv$ˊ:ʽ	I
      //   60: iload_1
      //   61: iconst_2
      //   62: irem
      //   63: ifeq +6 -> 69
      //   66: goto +153 -> 219
      //   69: goto +6 -> 75
      //   72: astore_2
      //   73: aload_2
      //   74: athrow
      //   75: aload_0
      //   76: invokespecial 102	o/Ik:ˏ	()V
      //   79: aload_0
      //   80: getfield 56	o/Lv$ˊ:ˎ	Lo/Lv;
      //   83: invokestatic 81	o/Lv:ˊ	(Lo/Lv;)Lo/LA;
      //   86: astore_2
      //   87: aload_2
      //   88: iconst_0
      //   89: ldc 82
      //   91: iconst_0
      //   92: ldc 83
      //   94: bipush -73
      //   96: invokestatic 85	o/Lv$ˊ:ॱ	(SIBII)Ljava/lang/String;
      //   99: invokevirtual 90	java/lang/String:intern	()Ljava/lang/String;
      //   102: invokestatic 95	o/vq:ˋ	(Ljava/lang/Object;Ljava/lang/String;)V
      //   105: aload_2
      //   106: iconst_0
      //   107: invokevirtual 104	o/LA:ˏ	(Z)V
      //   110: aload_0
      //   111: getfield 56	o/Lv$ˊ:ˎ	Lo/Lv;
      //   114: invokestatic 107	o/Lv:ˋ	(Lo/Lv;)Ljava/util/ArrayList;
      //   117: invokevirtual 113	java/util/ArrayList:isEmpty	()Z
      //   120: ifeq +6 -> 126
      //   123: goto +99 -> 222
      //   126: goto -89 -> 37
      //   129: getstatic 27	o/Lv$ˊ:ʻ	I
      //   132: istore_1
      //   133: iload_1
      //   134: bipush 75
      //   136: iadd
      //   137: istore_1
      //   138: iload_1
      //   139: sipush 128
      //   142: irem
      //   143: putstatic 25	o/Lv$ˊ:ʽ	I
      //   146: iload_1
      //   147: iconst_2
      //   148: irem
      //   149: ifeq +6 -> 155
      //   152: goto +82 -> 234
      //   155: return
      //   156: getstatic 27	o/Lv$ˊ:ʻ	I
      //   159: istore_1
      //   160: iload_1
      //   161: bipush 97
      //   163: iadd
      //   164: istore_1
      //   165: iload_1
      //   166: sipush 128
      //   169: irem
      //   170: putstatic 25	o/Lv$ˊ:ʽ	I
      //   173: iload_1
      //   174: iconst_2
      //   175: irem
      //   176: ifeq +6 -> 182
      //   179: goto +52 -> 231
      //   182: goto -179 -> 3
      //   185: astore_2
      //   186: aload_2
      //   187: athrow
      //   188: iload_1
      //   189: lookupswitch	default:+27->216, 41:+-33->156, 83:+39->228
      //   216: goto +12 -> 228
      //   219: goto -144 -> 75
      //   222: bipush 41
      //   224: istore_1
      //   225: goto -37 -> 188
      //   228: goto -99 -> 129
      //   231: goto -228 -> 3
      //   234: return
      //   235: goto -192 -> 43
      // Local variable table:
      //   start	length	slot	name	signature
      //   0	238	0	this	ˊ
      //   39	186	1	i	int
      //   10	20	2	localLA1	LA
      //   72	2	2	localException1	Exception
      //   86	20	2	localLA2	LA
      //   185	2	2	localException2	Exception
      // Exception table:
      //   from	to	target	type
      //   43	47	72	java/lang/Exception
      //   138	146	72	java/lang/Exception
      //   52	60	185	java/lang/Exception
      //   129	133	185	java/lang/Exception
      //   156	160	185	java/lang/Exception
    }
    
    protected void ॱ(EZ paramEZ)
    {
      break label132;
      int i = ʽ + 55;
      ʻ = i % 128;
      if (i % 2 != 0) {
        return;
      }
      return;
      for (;;)
      {
        try
        {
          str = ॱ((short)0, -1043483293, (byte)0, 1899737351, -73);
        }
        catch (Exception paramEZ)
        {
          String str;
          label132:
          throw paramEZ;
        }
        try
        {
          str = str.intern();
          vq.ˎ(paramEZ, str);
          Lv.ˎ(this.ˎ, new ArrayList());
          Lv.ˋ(this.ˎ).add(Lv.ॱ(this.ˎ));
          Lv.ˋ(this.ˎ).addAll((Collection)paramEZ.ˏ());
          Lv.ˏ(this.ˎ).ˎ((List)Lv.ˋ(this.ˎ), true);
          Lv.ˎ(this.ˎ);
        }
        catch (Exception paramEZ)
        {
          throw paramEZ;
        }
      }
    }
  }
  
  public static final class ˋ
  {
    private ˋ() {}
  }
}
