package o;

import android.content.Context;
import android.content.Intent;
import android.content.res.Resources;
import android.graphics.drawable.Drawable;
import android.support.v7.widget.LinearLayoutManager;
import android.support.v7.widget.RecyclerView.LayoutManager;
import android.support.v7.widget.RecyclerView.ˊ;
import android.support.v7.widget.RecyclerView.ˎ;
import android.view.View;
import android.widget.TextView;
import java.util.ArrayList;
import java.util.Collection;
import java.util.HashSet;
import java.util.Iterator;
import java.util.List;

public final class Lw
  extends IB<LB>
{
  private static int ʽॱ = 0;
  private static char ʿ;
  private static long ˈ;
  private static int ˊᐝ = 0;
  private static int ˋˊ = 1;
  private HashSet<FF> ʼॱ = new HashSet();
  private LC ʾ;
  
  static
  {
    ʿ = '汛';
    ˈ = 0L;
  }
  
  public Lw() {}
  
  /* Error */
  private final void ʻॱ()
  {
    // Byte code:
    //   0: goto +896 -> 896
    //   3: getstatic 24	o/Lw:ˊᐝ	I
    //   6: bipush 89
    //   8: iadd
    //   9: istore_2
    //   10: iload_2
    //   11: sipush 128
    //   14: irem
    //   15: putstatic 26	o/Lw:ˋˊ	I
    //   18: iload_2
    //   19: iconst_2
    //   20: irem
    //   21: ifne +6 -> 27
    //   24: goto +935 -> 959
    //   27: goto +69 -> 96
    //   30: iconst_0
    //   31: istore_2
    //   32: goto +902 -> 934
    //   35: iload_2
    //   36: lookupswitch	default:+28->64, 20:+37->73, 52:+493->529
    //   64: goto +9 -> 73
    //   67: bipush 52
    //   69: istore_2
    //   70: goto -35 -> 35
    //   73: aload_0
    //   74: getfield 41	o/Lw:ʼॱ	Ljava/util/HashSet;
    //   77: invokevirtual 48	java/util/HashSet:isEmpty	()Z
    //   80: istore_3
    //   81: aconst_null
    //   82: arraylength
    //   83: istore_2
    //   84: iload_3
    //   85: ifeq +6 -> 91
    //   88: goto -58 -> 30
    //   91: iconst_1
    //   92: istore_2
    //   93: goto +841 -> 934
    //   96: goto +446 -> 542
    //   99: aload_0
    //   100: getfield 52	o/Lw:ॱˊ	Landroid/databinding/ViewDataBinding;
    //   103: astore 6
    //   105: aload_0
    //   106: invokevirtual 58	android/content/Context:getResources	()Landroid/content/res/Resources;
    //   109: ldc 59
    //   111: invokevirtual 65	android/content/res/Resources:getString	(I)Ljava/lang/String;
    //   114: bipush 11
    //   116: bipush 16
    //   118: invokevirtual 71	java/lang/String:substring	(II)Ljava/lang/String;
    //   121: iconst_2
    //   122: invokevirtual 75	java/lang/String:codePointAt	(I)I
    //   125: sipush 232
    //   128: isub
    //   129: i2c
    //   130: istore_1
    //   131: aload_0
    //   132: invokevirtual 79	android/content/Context:getPackageName	()Ljava/lang/String;
    //   135: invokevirtual 83	java/lang/String:length	()I
    //   138: istore_2
    //   139: aload 6
    //   141: iconst_4
    //   142: newarray char
    //   144: dup
    //   145: iconst_0
    //   146: ldc 84
    //   148: castore
    //   149: dup
    //   150: iconst_1
    //   151: ldc 85
    //   153: castore
    //   154: dup
    //   155: iconst_2
    //   156: ldc 86
    //   158: castore
    //   159: dup
    //   160: iconst_3
    //   161: ldc 87
    //   163: castore
    //   164: iload_1
    //   165: bipush 8
    //   167: newarray char
    //   169: dup
    //   170: iconst_0
    //   171: ldc 88
    //   173: castore
    //   174: dup
    //   175: iconst_1
    //   176: ldc 89
    //   178: castore
    //   179: dup
    //   180: iconst_2
    //   181: ldc 90
    //   183: castore
    //   184: dup
    //   185: iconst_3
    //   186: ldc 91
    //   188: castore
    //   189: dup
    //   190: iconst_4
    //   191: ldc 92
    //   193: castore
    //   194: dup
    //   195: iconst_5
    //   196: ldc 93
    //   198: castore
    //   199: dup
    //   200: bipush 6
    //   202: ldc 94
    //   204: castore
    //   205: dup
    //   206: bipush 7
    //   208: ldc 95
    //   210: castore
    //   211: iload_2
    //   212: bipush 11
    //   214: isub
    //   215: iconst_4
    //   216: newarray char
    //   218: dup
    //   219: iconst_0
    //   220: ldc 96
    //   222: castore
    //   223: dup
    //   224: iconst_1
    //   225: ldc 96
    //   227: castore
    //   228: dup
    //   229: iconst_2
    //   230: ldc 96
    //   232: castore
    //   233: dup
    //   234: iconst_3
    //   235: ldc 96
    //   237: castore
    //   238: invokestatic 100	o/Lw:ॱ	([CC[CI[C)Ljava/lang/String;
    //   241: invokevirtual 103	java/lang/String:intern	()Ljava/lang/String;
    //   244: invokestatic 109	o/vq:ˋ	(Ljava/lang/Object;Ljava/lang/String;)V
    //   247: aload 6
    //   249: checkcast 111	o/LB
    //   252: iconst_1
    //   253: invokevirtual 115	o/LB:ˏ	(Z)V
    //   256: aload_0
    //   257: getfield 52	o/Lw:ॱˊ	Landroid/databinding/ViewDataBinding;
    //   260: checkcast 111	o/LB
    //   263: getfield 119	o/LB:ʼ	Landroid/widget/TextView;
    //   266: astore 6
    //   268: aload_0
    //   269: invokevirtual 58	android/content/Context:getResources	()Landroid/content/res/Resources;
    //   272: ldc 120
    //   274: invokevirtual 65	android/content/res/Resources:getString	(I)Ljava/lang/String;
    //   277: iconst_0
    //   278: bipush 9
    //   280: invokevirtual 71	java/lang/String:substring	(II)Ljava/lang/String;
    //   283: bipush 8
    //   285: invokevirtual 75	java/lang/String:codePointAt	(I)I
    //   288: sipush 186
    //   291: isub
    //   292: i2c
    //   293: istore_1
    //   294: aload_0
    //   295: invokevirtual 58	android/content/Context:getResources	()Landroid/content/res/Resources;
    //   298: ldc 121
    //   300: invokevirtual 65	android/content/res/Resources:getString	(I)Ljava/lang/String;
    //   303: iconst_0
    //   304: iconst_4
    //   305: invokevirtual 71	java/lang/String:substring	(II)Ljava/lang/String;
    //   308: invokevirtual 83	java/lang/String:length	()I
    //   311: istore_2
    //   312: aload 6
    //   314: iconst_4
    //   315: newarray char
    //   317: dup
    //   318: iconst_0
    //   319: ldc 122
    //   321: castore
    //   322: dup
    //   323: iconst_1
    //   324: ldc 123
    //   326: castore
    //   327: dup
    //   328: iconst_2
    //   329: ldc 124
    //   331: castore
    //   332: dup
    //   333: iconst_3
    //   334: ldc 125
    //   336: castore
    //   337: iload_1
    //   338: bipush 24
    //   340: newarray char
    //   342: dup
    //   343: iconst_0
    //   344: ldc 126
    //   346: castore
    //   347: dup
    //   348: iconst_1
    //   349: ldc 127
    //   351: castore
    //   352: dup
    //   353: iconst_2
    //   354: ldc -128
    //   356: castore
    //   357: dup
    //   358: iconst_3
    //   359: ldc -127
    //   361: castore
    //   362: dup
    //   363: iconst_4
    //   364: ldc -126
    //   366: castore
    //   367: dup
    //   368: iconst_5
    //   369: ldc -125
    //   371: castore
    //   372: dup
    //   373: bipush 6
    //   375: ldc -124
    //   377: castore
    //   378: dup
    //   379: bipush 7
    //   381: ldc -123
    //   383: castore
    //   384: dup
    //   385: bipush 8
    //   387: ldc -122
    //   389: castore
    //   390: dup
    //   391: bipush 9
    //   393: ldc -121
    //   395: castore
    //   396: dup
    //   397: bipush 10
    //   399: ldc -120
    //   401: castore
    //   402: dup
    //   403: bipush 11
    //   405: ldc -119
    //   407: castore
    //   408: dup
    //   409: bipush 12
    //   411: ldc -118
    //   413: castore
    //   414: dup
    //   415: bipush 13
    //   417: ldc -117
    //   419: castore
    //   420: dup
    //   421: bipush 14
    //   423: ldc -116
    //   425: castore
    //   426: dup
    //   427: bipush 15
    //   429: ldc -115
    //   431: castore
    //   432: dup
    //   433: bipush 16
    //   435: ldc -114
    //   437: castore
    //   438: dup
    //   439: bipush 17
    //   441: ldc -113
    //   443: castore
    //   444: dup
    //   445: bipush 18
    //   447: ldc -112
    //   449: castore
    //   450: dup
    //   451: bipush 19
    //   453: ldc -111
    //   455: castore
    //   456: dup
    //   457: bipush 20
    //   459: ldc -110
    //   461: castore
    //   462: dup
    //   463: bipush 21
    //   465: ldc -109
    //   467: castore
    //   468: dup
    //   469: bipush 22
    //   471: ldc -108
    //   473: castore
    //   474: dup
    //   475: bipush 23
    //   477: ldc -107
    //   479: castore
    //   480: iload_2
    //   481: iconst_4
    //   482: isub
    //   483: iconst_4
    //   484: newarray char
    //   486: dup
    //   487: iconst_0
    //   488: ldc 96
    //   490: castore
    //   491: dup
    //   492: iconst_1
    //   493: ldc 96
    //   495: castore
    //   496: dup
    //   497: iconst_2
    //   498: ldc 96
    //   500: castore
    //   501: dup
    //   502: iconst_3
    //   503: ldc 96
    //   505: castore
    //   506: invokestatic 100	o/Lw:ॱ	([CC[CI[C)Ljava/lang/String;
    //   509: invokevirtual 103	java/lang/String:intern	()Ljava/lang/String;
    //   512: invokestatic 109	o/vq:ˋ	(Ljava/lang/Object;Ljava/lang/String;)V
    //   515: aload 6
    //   517: iconst_4
    //   518: invokevirtual 155	android/widget/TextView:setVisibility	(I)V
    //   521: goto -518 -> 3
    //   524: astore 6
    //   526: aload 6
    //   528: athrow
    //   529: aload_0
    //   530: getfield 41	o/Lw:ʼॱ	Ljava/util/HashSet;
    //   533: invokevirtual 48	java/util/HashSet:isEmpty	()Z
    //   536: ifeq +6 -> 542
    //   539: goto -440 -> 99
    //   542: invokestatic 161	java/lang/System:currentTimeMillis	()J
    //   545: lstore 4
    //   547: goto +23 -> 570
    //   550: astore 6
    //   552: aload 6
    //   554: invokevirtual 167	java/lang/Throwable:getCause	()Ljava/lang/Throwable;
    //   557: astore 7
    //   559: aload 7
    //   561: ifnull +6 -> 567
    //   564: aload 7
    //   566: athrow
    //   567: aload 6
    //   569: athrow
    //   570: aload_0
    //   571: invokevirtual 58	android/content/Context:getResources	()Landroid/content/res/Resources;
    //   574: ldc -88
    //   576: invokevirtual 65	android/content/res/Resources:getString	(I)Ljava/lang/String;
    //   579: iconst_0
    //   580: iconst_5
    //   581: invokevirtual 71	java/lang/String:substring	(II)Ljava/lang/String;
    //   584: iconst_3
    //   585: invokevirtual 75	java/lang/String:codePointAt	(I)I
    //   588: bipush 8
    //   590: isub
    //   591: aload_0
    //   592: invokevirtual 79	android/content/Context:getPackageName	()Ljava/lang/String;
    //   595: invokevirtual 83	java/lang/String:length	()I
    //   598: bipush 124
    //   600: iadd
    //   601: aload_0
    //   602: invokevirtual 172	android/content/Context:getApplicationInfo	()Landroid/content/pm/ApplicationInfo;
    //   605: getfield 177	android/content/pm/ApplicationInfo:targetSdkVersion	I
    //   608: ldc -78
    //   610: iadd
    //   611: i2c
    //   612: invokestatic 183	o/O:ˋ	(IIC)Ljava/lang/Object;
    //   615: checkcast 185	java/lang/Class
    //   618: ldc -70
    //   620: aconst_null
    //   621: invokevirtual 190	java/lang/Class:getMethod	(Ljava/lang/String;[Ljava/lang/Class;)Ljava/lang/reflect/Method;
    //   624: aconst_null
    //   625: aconst_null
    //   626: invokevirtual 196	java/lang/reflect/Method:invoke	(Ljava/lang/Object;[Ljava/lang/Object;)Ljava/lang/Object;
    //   629: checkcast 198	o/It
    //   632: astore 6
    //   634: aload_0
    //   635: invokevirtual 58	android/content/Context:getResources	()Landroid/content/res/Resources;
    //   638: ldc -57
    //   640: invokevirtual 65	android/content/res/Resources:getString	(I)Ljava/lang/String;
    //   643: iconst_0
    //   644: iconst_4
    //   645: invokevirtual 71	java/lang/String:substring	(II)Ljava/lang/String;
    //   648: iconst_2
    //   649: invokevirtual 75	java/lang/String:codePointAt	(I)I
    //   652: bipush 7
    //   654: isub
    //   655: aload_0
    //   656: invokevirtual 79	android/content/Context:getPackageName	()Ljava/lang/String;
    //   659: iconst_4
    //   660: invokevirtual 75	java/lang/String:codePointAt	(I)I
    //   663: sipush 297
    //   666: iadd
    //   667: aload_0
    //   668: invokevirtual 79	android/content/Context:getPackageName	()Ljava/lang/String;
    //   671: iconst_2
    //   672: invokevirtual 75	java/lang/String:codePointAt	(I)I
    //   675: sipush 30207
    //   678: iadd
    //   679: i2c
    //   680: invokestatic 183	o/O:ˋ	(IIC)Ljava/lang/Object;
    //   683: checkcast 185	java/lang/Class
    //   686: ldc -56
    //   688: invokevirtual 204	java/lang/Class:getField	(Ljava/lang/String;)Ljava/lang/reflect/Field;
    //   691: aconst_null
    //   692: invokevirtual 210	java/lang/reflect/Field:get	(Ljava/lang/Object;)Ljava/lang/Object;
    //   695: astore 7
    //   697: goto +23 -> 720
    //   700: astore 6
    //   702: aload 6
    //   704: invokevirtual 167	java/lang/Throwable:getCause	()Ljava/lang/Throwable;
    //   707: astore 7
    //   709: aload 7
    //   711: ifnull +6 -> 717
    //   714: aload 7
    //   716: athrow
    //   717: aload 6
    //   719: athrow
    //   720: aload_0
    //   721: invokevirtual 172	android/content/Context:getApplicationInfo	()Landroid/content/pm/ApplicationInfo;
    //   724: getfield 177	android/content/pm/ApplicationInfo:targetSdkVersion	I
    //   727: bipush 19
    //   729: isub
    //   730: aload_0
    //   731: invokevirtual 172	android/content/Context:getApplicationInfo	()Landroid/content/pm/ApplicationInfo;
    //   734: getfield 177	android/content/pm/ApplicationInfo:targetSdkVersion	I
    //   737: sipush 392
    //   740: iadd
    //   741: aload_0
    //   742: invokevirtual 79	android/content/Context:getPackageName	()Ljava/lang/String;
    //   745: invokevirtual 83	java/lang/String:length	()I
    //   748: bipush 11
    //   750: isub
    //   751: i2c
    //   752: invokestatic 183	o/O:ˋ	(IIC)Ljava/lang/Object;
    //   755: checkcast 185	java/lang/Class
    //   758: ldc -45
    //   760: aconst_null
    //   761: invokevirtual 190	java/lang/Class:getMethod	(Ljava/lang/String;[Ljava/lang/Class;)Ljava/lang/reflect/Method;
    //   764: aload 7
    //   766: aconst_null
    //   767: invokevirtual 196	java/lang/reflect/Method:invoke	(Ljava/lang/Object;[Ljava/lang/Object;)Ljava/lang/Object;
    //   770: astore 7
    //   772: goto +23 -> 795
    //   775: astore 6
    //   777: aload 6
    //   779: invokevirtual 167	java/lang/Throwable:getCause	()Ljava/lang/Throwable;
    //   782: astore 7
    //   784: aload 7
    //   786: ifnull +6 -> 792
    //   789: aload 7
    //   791: athrow
    //   792: aload 6
    //   794: athrow
    //   795: aload_0
    //   796: invokevirtual 172	android/content/Context:getApplicationInfo	()Landroid/content/pm/ApplicationInfo;
    //   799: getfield 177	android/content/pm/ApplicationInfo:targetSdkVersion	I
    //   802: bipush 21
    //   804: isub
    //   805: aload_0
    //   806: invokevirtual 58	android/content/Context:getResources	()Landroid/content/res/Resources;
    //   809: ldc -44
    //   811: invokevirtual 65	android/content/res/Resources:getString	(I)Ljava/lang/String;
    //   814: bipush 20
    //   816: bipush 21
    //   818: invokevirtual 71	java/lang/String:substring	(II)Ljava/lang/String;
    //   821: iconst_0
    //   822: invokevirtual 75	java/lang/String:codePointAt	(I)I
    //   825: sipush 381
    //   828: iadd
    //   829: aload_0
    //   830: invokevirtual 172	android/content/Context:getApplicationInfo	()Landroid/content/pm/ApplicationInfo;
    //   833: getfield 177	android/content/pm/ApplicationInfo:targetSdkVersion	I
    //   836: sipush 30228
    //   839: iadd
    //   840: i2c
    //   841: invokestatic 183	o/O:ˋ	(IIC)Ljava/lang/Object;
    //   844: checkcast 185	java/lang/Class
    //   847: ldc -43
    //   849: aconst_null
    //   850: invokevirtual 190	java/lang/Class:getMethod	(Ljava/lang/String;[Ljava/lang/Class;)Ljava/lang/reflect/Method;
    //   853: aload 7
    //   855: aconst_null
    //   856: invokevirtual 196	java/lang/reflect/Method:invoke	(Ljava/lang/Object;[Ljava/lang/Object;)Ljava/lang/Object;
    //   859: checkcast 67	java/lang/String
    //   862: astore 7
    //   864: aload 6
    //   866: aload 7
    //   868: invokeinterface 216 2 0
    //   873: new 7	o/Lw$ˊ
    //   876: dup
    //   877: aload_0
    //   878: lload 4
    //   880: aload_0
    //   881: invokevirtual 219	o/Lw:ॱˊ	()Landroid/content/Context;
    //   884: invokespecial 222	o/Lw$ˊ:<init>	(Lo/Lw;JLandroid/content/Context;)V
    //   887: checkcast 224	o/Cx
    //   890: invokeinterface 229 2 0
    //   895: return
    //   896: goto +9 -> 905
    //   899: bipush 20
    //   901: istore_2
    //   902: goto -867 -> 35
    //   905: getstatic 24	o/Lw:ˊᐝ	I
    //   908: istore_2
    //   909: iload_2
    //   910: bipush 31
    //   912: iadd
    //   913: istore_2
    //   914: iload_2
    //   915: sipush 128
    //   918: irem
    //   919: putstatic 26	o/Lw:ˋˊ	I
    //   922: iload_2
    //   923: iconst_2
    //   924: irem
    //   925: ifne +6 -> 931
    //   928: goto -29 -> 899
    //   931: goto -864 -> 67
    //   934: iload_2
    //   935: tableswitch	default:+21->956, 0:+-836->99, 1:+-393->542
    //   956: goto -857 -> 99
    //   959: goto -863 -> 96
    // Local variable table:
    //   start	length	slot	name	signature
    //   0	962	0	this	Lw
    //   130	208	1	c	char
    //   9	926	2	i	int
    //   80	5	3	bool	boolean
    //   545	334	4	l	long
    //   103	413	6	localObject1	Object
    //   524	3	6	localException	Exception
    //   550	18	6	localObject2	Object
    //   632	1	6	localIt	It
    //   700	18	6	localObject3	Object
    //   775	90	6	localObject4	Object
    //   557	310	7	localObject5	Object
    // Exception table:
    //   from	to	target	type
    //   905	909	524	java/lang/Exception
    //   914	922	524	java/lang/Exception
    //   570	634	550	finally
    //   720	772	700	finally
    //   795	864	775	finally
  }
  
  private final void ˏ(FF paramFF)
  {
    break label266;
    int i = 97;
    for (;;)
    {
      try
      {
        i = ˋˊ + 69;
      }
      catch (Exception paramFF)
      {
        try
        {
          ˊᐝ = i % 128;
          if (i % 2 != 0) {
            break;
          }
          continue;
          break label275;
          switch (i)
          {
          default: 
            break;
          case 40: 
            label39:
            char c = (char)(getResources().getString(2131755084).substring(11, 16).length() + 32259);
            i = getResources().getString(2131755150).substring(0, 4).codePointAt(3);
            vq.ˊ(ॱ(new char[] { 7336, 3326, 2070, 22910 }, c, new char[] { -32721, -14950, -13113, -19643, 22221, 14657, 29405, 1641, -30754, -14906, -2366, 7847, -19064 }, i + 369950224, new char[] { 0, 0, 0, 0 }).intern());
            continue;
            i = 66;
          }
        }
        catch (Exception paramFF)
        {
          throw paramFF;
        }
        paramFF = paramFF;
        throw paramFF;
      }
      label266:
      label275:
      do
      {
        i = 40;
        break label39;
        paramFF.ˎ(uQ.ॱ((Iterable)this.ʼॱ), true);
        break label350;
        switch (i)
        {
        }
        break;
        this.ʼॱ.remove(paramFF);
        paramFF = this.ʾ;
      } while (paramFF == null);
      i = 99;
    }
    label350:
    i = ˋˊ + 87;
    ˊᐝ = i % 128;
    if (i % 2 != 0) {}
  }
  
  private static String ॱ(char[] paramArrayOfChar1, char paramChar, char[] paramArrayOfChar2, int paramInt, char[] paramArrayOfChar3)
  {
    break label219;
    label31:
    label37:
    char c;
    char[] arrayOfChar;
    switch (paramInt)
    {
    default: 
      break label282;
      paramInt = 60;
      break;
      paramArrayOfChar1 = (char[])paramArrayOfChar1.clone();
      paramArrayOfChar3 = (char[])paramArrayOfChar3.clone();
      paramArrayOfChar1[0] = ((char)(paramArrayOfChar1[0] ^ paramChar));
      paramArrayOfChar3[2] = ((char)(paramArrayOfChar3[2] + (char)paramInt));
      c = paramArrayOfChar2.length;
      arrayOfChar = new char[c];
      paramChar = '\000';
      break;
    }
    label105:
    label135:
    label219:
    label222:
    label282:
    label326:
    label328:
    do
    {
      throw new NullPointerException();
      for (;;)
      {
        paramInt = 64;
        break label135;
        c = ˊᐝ + 87;
        ˋˊ = c % '';
        if (c % '\002' != 0)
        {
          break label37;
          switch (paramInt)
          {
          default: 
            break;
          case 64: 
            paramInt = ˋˊ + 101;
            ˊᐝ = paramInt % 128;
            if (paramInt % 2 != 0) {
              break label222;
            }
            break;
          }
          paramArrayOfChar1 = new String(arrayOfChar);
          break label328;
        }
        for (;;)
        {
          if (paramChar < c) {
            break label326;
          }
          break label31;
          break label105;
          paramInt = 0;
          break;
          paramInt = 1;
          break;
          break label37;
          oJ.ˏ(paramArrayOfChar1, paramArrayOfChar3, paramChar);
          arrayOfChar[paramChar] = ((char)(int)(((paramArrayOfChar2[paramChar] | paramArrayOfChar1[(paramChar - '\003' >> 4)]) + ˈ) % ʽॱ | ʿ));
          paramChar += 'k';
          continue;
          oJ.ˏ(paramArrayOfChar1, paramArrayOfChar3, paramChar);
          arrayOfChar[paramChar] = ((char)(int)(paramArrayOfChar2[paramChar] ^ paramArrayOfChar1[((paramChar + '\003') % 4)] ^ ˈ ^ ʽॱ ^ ʿ));
          paramChar += '\001';
        }
      }
      paramChar = ˊᐝ + 123;
      ˋˊ = paramChar % '';
    } while (paramChar % '\002' == 0);
    return paramArrayOfChar1;
  }
  
  private final void ॱˋ()
  {
    break label150;
    int i = ˋˊ + 27;
    ˊᐝ = i % 128;
    Object localObject1;
    Object localObject2;
    if (i % 2 == 0)
    {
      break label779;
      ((ᔄ)localObject1).ॱ((Drawable)localObject2);
    }
    for (;;)
    {
      try
      {
        localObject2 = (RecyclerView.ˊ)localObject2;
        try
        {
          ((aH)localObject1).setAdapter((RecyclerView.ˊ)localObject2);
          localObject1 = this.ॱˊ;
          localObject1 = (LB)localObject1;
          localObject1 = ((LB)localObject1).ॱ;
          ((aH)localObject1).setEmptyView((View)((LB)this.ॱˊ).ʼ);
          localObject1 = new ᔄ(ॱˊ(), 1);
          localObject2 = ᔆ.ˎ(ॱˊ(), Lt.iF.recycler_item_divider);
          if (localObject2 != null) {
            break label963;
          }
        }
        catch (Exception localException1)
        {
          throw localException1;
        }
        label150:
        aH localAH;
        char c;
        switch (i)
        {
        default: 
          continue;
          this.ʾ = new LC();
          localAH = ((LB)this.ॱˊ).ॱ;
          c = (char)(getPackageName().length() + 8805);
          i = getResources().getString(2131755641).substring(0, 5).codePointAt(3);
          vq.ˋ(localAH, ॱ(new char[] { -18855, 24315, 28865, 18466 }, c, new char[] { -18022, 10864, -28483, -19894, 30416, 30951, -3752, -23322, -29803, 28916, 22565, 5286, -18146, 3388, 20578, -30672, -25951, -20956, -274 }, i - 1050739798, new char[] { 0, 0, 0, 0 }).intern());
          localAH.setLayoutManager((RecyclerView.LayoutManager)new LinearLayoutManager(getApplicationContext()));
          localAH = ((LB)this.ॱˊ).ॱ;
          c = (char)(getPackageName().codePointAt(4) + 8700);
          i = getResources().getString(2131755195).substring(0, 4).length();
          vq.ˋ(localAH, ॱ(new char[] { -18855, 24315, 28865, 18466 }, c, new char[] { -18022, 10864, -28483, -19894, 30416, 30951, -3752, -23322, -29803, 28916, 22565, 5286, -18146, 3388, 20578, -30672, -25951, -20956, -274 }, i - 1050739790, new char[] { 0, 0, 0, 0 }).intern());
          localObject2 = this.ʾ;
          if (localObject2 == null) {
            break;
          }
          continue;
          i = 0;
          continue;
          i = 1;
          break;
        case 1: 
          i = ˋˊ + 5;
          ˊᐝ = i % 128;
          if (i % 2 == 0)
          {
            continue;
            continue;
          }
          i = 0;
          continue;
          ((LB)this.ॱˊ).ॱ.ˏ((RecyclerView.ˎ)localAH);
          return;
          switch (i)
          {
          case 1: 
          default: 
            break;
          case 0: 
            localAH.ॱ((Drawable)localObject2);
            i = null.length;
            continue;
            c = (char)(getResources().getString(2131755248).substring(0, 9).length() + 32255);
            i = getPackageName().codePointAt(8);
            vq.ˊ(ॱ(new char[] { 7336, 3326, 2070, 22910 }, c, new char[] { -32721, -14950, -13113, -19643, 22221, 14657, 29405, 1641, -30754, -14906, -2366, 7847, -19064 }, i + 369950124, new char[] { 0, 0, 0, 0 }).intern());
            continue;
          }
          break;
        case 0: 
          label779:
          continue;
        }
      }
      catch (Exception localException2)
      {
        throw localException2;
      }
      label963:
      i = 1;
    }
  }
  
  public Resources getResources()
  {
    break label35;
    int i = 1;
    label35:
    label95:
    Resources localResources;
    for (;;)
    {
      i = ˋˊ + 77;
      ˊᐝ = i % 128;
      if (i % 2 == 0)
      {
        break;
        do
        {
          break;
          i = ˊᐝ + 73;
          ˋˊ = i % 128;
        } while (i % 2 == 0);
        break label95;
      }
      i = 0;
      switch (i)
      {
      default: 
        break label108;
        localResources = oH.ˊ(super.getResources());
      }
    }
    return localResources;
    label108:
    i = 44 / 0;
    return localResources;
  }
  
  public void onActivityResult(int paramInt1, int paramInt2, Intent paramIntent)
  {
    break label103;
    paramInt2 = 32;
    break label18;
    label9:
    paramInt2 = 11;
    for (;;)
    {
      break label151;
      switch (paramInt2)
      {
      default: 
        return;
      case 32: 
        label18:
        switch (paramInt1)
        {
        }
        break;
      }
      return;
      setResult(-1);
      break label106;
      label103:
      for (;;)
      {
        int i = ˊᐝ + 17;
        ˋˊ = i % 128;
        if (i % 2 == 0) {
          break label152;
        }
        break;
      }
      label106:
      paramInt1 = ˋˊ + 97;
      ˊᐝ = paramInt1 % 128;
      if (paramInt1 % 2 == 0) {
        break label151;
      }
    }
    label151:
    label152:
    for (;;)
    {
      super.onActivityResult(paramInt1, paramInt2, paramIntent);
      if (paramInt2 == -1) {
        break;
      }
      break label9;
      return;
    }
  }
  
  /* Error */
  public void onCreate(android.os.Bundle paramBundle)
  {
    // Byte code:
    //   0: goto +6 -> 6
    //   3: astore_1
    //   4: aload_1
    //   5: athrow
    //   6: getstatic 24	o/Lw:ˊᐝ	I
    //   9: bipush 31
    //   11: iadd
    //   12: istore_2
    //   13: iload_2
    //   14: sipush 128
    //   17: irem
    //   18: putstatic 26	o/Lw:ˋˊ	I
    //   21: iload_2
    //   22: iconst_2
    //   23: irem
    //   24: ifne +6 -> 30
    //   27: goto +95 -> 122
    //   30: goto +97 -> 127
    //   33: aload_0
    //   34: aload_1
    //   35: invokespecial 397	o/IB:onCreate	(Landroid/os/Bundle;)V
    //   38: aload_0
    //   39: aload_0
    //   40: getfield 52	o/Lw:ॱˊ	Landroid/databinding/ViewDataBinding;
    //   43: checkcast 111	o/LB
    //   46: getfield 400	o/LB:ˊ	Lo/у;
    //   49: invokevirtual 403	o/Lw:ˊ	(Lo/у;)V
    //   52: aload_0
    //   53: invokespecial 405	o/Lw:ॱˋ	()V
    //   56: new 284	java/lang/NullPointerException
    //   59: dup
    //   60: invokespecial 285	java/lang/NullPointerException:<init>	()V
    //   63: athrow
    //   64: aload_0
    //   65: aload_1
    //   66: invokespecial 397	o/IB:onCreate	(Landroid/os/Bundle;)V
    //   69: aload_0
    //   70: getfield 52	o/Lw:ॱˊ	Landroid/databinding/ViewDataBinding;
    //   73: astore_1
    //   74: aload_1
    //   75: checkcast 111	o/LB
    //   78: astore_1
    //   79: aload_1
    //   80: getfield 400	o/LB:ˊ	Lo/у;
    //   83: astore_1
    //   84: aload_0
    //   85: aload_1
    //   86: invokevirtual 403	o/Lw:ˊ	(Lo/у;)V
    //   89: aload_0
    //   90: invokespecial 405	o/Lw:ॱˋ	()V
    //   93: return
    //   94: iload_2
    //   95: tableswitch	default:+21->116, 0:+-62->33, 1:+-31->64
    //   116: goto -52 -> 64
    //   119: astore_1
    //   120: aload_1
    //   121: athrow
    //   122: iconst_0
    //   123: istore_2
    //   124: goto -30 -> 94
    //   127: iconst_1
    //   128: istore_2
    //   129: goto -35 -> 94
    // Local variable table:
    //   start	length	slot	name	signature
    //   0	132	0	this	Lw
    //   0	132	1	paramBundle	android.os.Bundle
    //   12	117	2	i	int
    // Exception table:
    //   from	to	target	type
    //   84	93	3	java/lang/Exception
    //   69	74	119	java/lang/Exception
    //   74	79	119	java/lang/Exception
    //   79	84	119	java/lang/Exception
    //   84	93	119	java/lang/Exception
  }
  
  public void onResume()
  {
    break label107;
    int i = 1;
    label101:
    label107:
    for (;;)
    {
      i = ˊᐝ + 25;
      ˋˊ = i % 128;
      if (i % 2 == 0) {
        break label147;
      }
      break;
      return;
      for (;;)
      {
        switch (i)
        {
        case 53: 
        default: 
          break label171;
          switch (i)
          {
          default: 
            break label110;
            i = 53;
            continue;
            i = 82;
          }
          break;
        }
      }
    }
    label110:
    super.onResume();
    ʻॱ();
    for (;;)
    {
      try
      {
        i = ˋˊ;
        i += 77;
        ˊᐝ = i % 128;
        if (i % 2 != 0) {
          break label101;
        }
      }
      catch (Exception localException)
      {
        label147:
        throw localException;
      }
      i = 0;
      break;
      super.onResume();
      ʻॱ();
      i = 96 / 0;
    }
    label171:
    i = null.length;
  }
  
  /* Error */
  public void ˋ(ز paramز)
  {
    // Byte code:
    //   0: goto +280 -> 280
    //   3: getstatic 24	o/Lw:ˊᐝ	I
    //   6: bipush 97
    //   8: iadd
    //   9: istore_3
    //   10: iload_3
    //   11: sipush 128
    //   14: irem
    //   15: putstatic 26	o/Lw:ˋˊ	I
    //   18: iload_3
    //   19: iconst_2
    //   20: irem
    //   21: ifne +6 -> 27
    //   24: goto +259 -> 283
    //   27: goto +218 -> 245
    //   30: bipush 27
    //   32: iconst_0
    //   33: idiv
    //   34: istore_3
    //   35: return
    //   36: goto +6 -> 42
    //   39: astore_1
    //   40: aload_1
    //   41: athrow
    //   42: aload_0
    //   43: invokevirtual 58	android/content/Context:getResources	()Landroid/content/res/Resources;
    //   46: ldc_w 412
    //   49: invokevirtual 65	android/content/res/Resources:getString	(I)Ljava/lang/String;
    //   52: iconst_0
    //   53: bipush 8
    //   55: invokevirtual 71	java/lang/String:substring	(II)Ljava/lang/String;
    //   58: iconst_1
    //   59: invokevirtual 75	java/lang/String:codePointAt	(I)I
    //   62: bipush 26
    //   64: isub
    //   65: i2c
    //   66: istore_2
    //   67: aload_0
    //   68: invokevirtual 79	android/content/Context:getPackageName	()Ljava/lang/String;
    //   71: bipush 6
    //   73: invokevirtual 75	java/lang/String:codePointAt	(I)I
    //   76: istore_3
    //   77: aload_1
    //   78: iconst_4
    //   79: newarray char
    //   81: dup
    //   82: iconst_0
    //   83: ldc_w 413
    //   86: castore
    //   87: dup
    //   88: iconst_1
    //   89: ldc_w 414
    //   92: castore
    //   93: dup
    //   94: iconst_2
    //   95: ldc_w 415
    //   98: castore
    //   99: dup
    //   100: iconst_3
    //   101: ldc_w 416
    //   104: castore
    //   105: iload_2
    //   106: bipush 9
    //   108: newarray char
    //   110: dup
    //   111: iconst_0
    //   112: ldc_w 417
    //   115: castore
    //   116: dup
    //   117: iconst_1
    //   118: ldc_w 418
    //   121: castore
    //   122: dup
    //   123: iconst_2
    //   124: ldc_w 419
    //   127: castore
    //   128: dup
    //   129: iconst_3
    //   130: ldc_w 420
    //   133: castore
    //   134: dup
    //   135: iconst_4
    //   136: ldc_w 421
    //   139: castore
    //   140: dup
    //   141: iconst_5
    //   142: ldc_w 422
    //   145: castore
    //   146: dup
    //   147: bipush 6
    //   149: ldc_w 423
    //   152: castore
    //   153: dup
    //   154: bipush 7
    //   156: ldc_w 424
    //   159: castore
    //   160: dup
    //   161: bipush 8
    //   163: ldc_w 425
    //   166: castore
    //   167: iload_3
    //   168: ldc_w 426
    //   171: isub
    //   172: iconst_4
    //   173: newarray char
    //   175: dup
    //   176: iconst_0
    //   177: ldc 96
    //   179: castore
    //   180: dup
    //   181: iconst_1
    //   182: ldc 96
    //   184: castore
    //   185: dup
    //   186: iconst_2
    //   187: ldc 96
    //   189: castore
    //   190: dup
    //   191: iconst_3
    //   192: ldc 96
    //   194: castore
    //   195: invokestatic 100	o/Lw:ॱ	([CC[CI[C)Ljava/lang/String;
    //   198: invokevirtual 103	java/lang/String:intern	()Ljava/lang/String;
    //   201: invokestatic 428	o/vq:ˎ	(Ljava/lang/Object;Ljava/lang/String;)V
    //   204: aload_0
    //   205: aload_1
    //   206: invokespecial 430	o/IB:ˋ	(Lo/ز;)V
    //   209: aload_1
    //   210: iconst_1
    //   211: invokevirtual 434	o/ز:ॱ	(Z)V
    //   214: aload_1
    //   215: iconst_1
    //   216: invokevirtual 435	o/ز:ˏ	(Z)V
    //   219: goto -216 -> 3
    //   222: iload_3
    //   223: tableswitch	default:+21->244, 0:+56->279, 1:+-193->30
    //   244: return
    //   245: iconst_0
    //   246: istore_3
    //   247: goto -25 -> 222
    //   250: getstatic 24	o/Lw:ˊᐝ	I
    //   253: istore_3
    //   254: iload_3
    //   255: bipush 97
    //   257: iadd
    //   258: istore_3
    //   259: iload_3
    //   260: sipush 128
    //   263: irem
    //   264: putstatic 26	o/Lw:ˋˊ	I
    //   267: iload_3
    //   268: iconst_2
    //   269: irem
    //   270: ifne +6 -> 276
    //   273: goto -237 -> 36
    //   276: goto -234 -> 42
    //   279: return
    //   280: goto -30 -> 250
    //   283: iconst_1
    //   284: istore_3
    //   285: goto -63 -> 222
    // Local variable table:
    //   start	length	slot	name	signature
    //   0	288	0	this	Lw
    //   0	288	1	paramز	ز
    //   66	40	2	c	char
    //   9	276	3	i	int
    // Exception table:
    //   from	to	target	type
    //   250	254	39	java/lang/Exception
    //   259	267	39	java/lang/Exception
  }
  
  /* Error */
  public int ˎ()
  {
    // Byte code:
    //   0: goto +102 -> 102
    //   3: goto +105 -> 108
    //   6: bipush 20
    //   8: istore_1
    //   9: goto +33 -> 42
    //   12: getstatic 26	o/Lw:ˋˊ	I
    //   15: bipush 9
    //   17: iadd
    //   18: istore_1
    //   19: iload_1
    //   20: sipush 128
    //   23: irem
    //   24: putstatic 24	o/Lw:ˊᐝ	I
    //   27: iload_1
    //   28: iconst_2
    //   29: irem
    //   30: ifeq +6 -> 36
    //   33: goto +6 -> 39
    //   36: goto -30 -> 6
    //   39: bipush 36
    //   41: istore_1
    //   42: iload_1
    //   43: lookupswitch	default:+25->68, 20:+57->100, 36:+25->68
    //   68: aconst_null
    //   69: arraylength
    //   70: istore_1
    //   71: iload_2
    //   72: ireturn
    //   73: getstatic 24	o/Lw:ˊᐝ	I
    //   76: bipush 15
    //   78: iadd
    //   79: istore_1
    //   80: iload_1
    //   81: sipush 128
    //   84: irem
    //   85: putstatic 26	o/Lw:ˋˊ	I
    //   88: iload_1
    //   89: iconst_2
    //   90: irem
    //   91: ifne +6 -> 97
    //   94: goto -91 -> 3
    //   97: goto +11 -> 108
    //   100: iload_2
    //   101: ireturn
    //   102: goto -29 -> 73
    //   105: astore_3
    //   106: aload_3
    //   107: athrow
    //   108: getstatic 440	o/Lt$ˋ:activity_offers_favorites	I
    //   111: istore_2
    //   112: goto -100 -> 12
    // Local variable table:
    //   start	length	slot	name	signature
    //   0	115	0	this	Lw
    //   8	83	1	i	int
    //   71	41	2	j	int
    //   105	2	3	localException	Exception
    // Exception table:
    //   from	to	target	type
    //   108	112	105	java/lang/Exception
  }
  
  /* Error */
  @zA
  public final void ॱ(LP paramLP)
  {
    // Byte code:
    //   0: goto +173 -> 173
    //   3: astore_1
    //   4: aload_1
    //   5: athrow
    //   6: getstatic 26	o/Lw:ˋˊ	I
    //   9: bipush 103
    //   11: iadd
    //   12: istore_3
    //   13: iload_3
    //   14: sipush 128
    //   17: irem
    //   18: putstatic 24	o/Lw:ˊᐝ	I
    //   21: iload_3
    //   22: iconst_2
    //   23: irem
    //   24: ifeq +6 -> 30
    //   27: goto +181 -> 208
    //   30: return
    //   31: aload_0
    //   32: invokevirtual 172	android/content/Context:getApplicationInfo	()Landroid/content/pm/ApplicationInfo;
    //   35: getfield 177	android/content/pm/ApplicationInfo:targetSdkVersion	I
    //   38: ldc_w 443
    //   41: iadd
    //   42: i2c
    //   43: istore_2
    //   44: aload_0
    //   45: invokevirtual 58	android/content/Context:getResources	()Landroid/content/res/Resources;
    //   48: ldc_w 444
    //   51: invokevirtual 65	android/content/res/Resources:getString	(I)Ljava/lang/String;
    //   54: iconst_0
    //   55: iconst_1
    //   56: invokevirtual 71	java/lang/String:substring	(II)Ljava/lang/String;
    //   59: invokevirtual 83	java/lang/String:length	()I
    //   62: istore_3
    //   63: aload_1
    //   64: iconst_4
    //   65: newarray char
    //   67: dup
    //   68: iconst_0
    //   69: ldc_w 445
    //   72: castore
    //   73: dup
    //   74: iconst_1
    //   75: ldc_w 446
    //   78: castore
    //   79: dup
    //   80: iconst_2
    //   81: ldc_w 447
    //   84: castore
    //   85: dup
    //   86: iconst_3
    //   87: ldc_w 448
    //   90: castore
    //   91: iload_2
    //   92: iconst_5
    //   93: newarray char
    //   95: dup
    //   96: iconst_0
    //   97: ldc_w 449
    //   100: castore
    //   101: dup
    //   102: iconst_1
    //   103: ldc_w 450
    //   106: castore
    //   107: dup
    //   108: iconst_2
    //   109: ldc_w 451
    //   112: castore
    //   113: dup
    //   114: iconst_3
    //   115: ldc_w 452
    //   118: castore
    //   119: dup
    //   120: iconst_4
    //   121: ldc_w 453
    //   124: castore
    //   125: iload_3
    //   126: ldc_w 454
    //   129: isub
    //   130: iconst_4
    //   131: newarray char
    //   133: dup
    //   134: iconst_0
    //   135: ldc 96
    //   137: castore
    //   138: dup
    //   139: iconst_1
    //   140: ldc 96
    //   142: castore
    //   143: dup
    //   144: iconst_2
    //   145: ldc 96
    //   147: castore
    //   148: dup
    //   149: iconst_3
    //   150: ldc 96
    //   152: castore
    //   153: invokestatic 100	o/Lw:ॱ	([CC[CI[C)Ljava/lang/String;
    //   156: invokevirtual 103	java/lang/String:intern	()Ljava/lang/String;
    //   159: invokestatic 428	o/vq:ˎ	(Ljava/lang/Object;Ljava/lang/String;)V
    //   162: aload_0
    //   163: aload_1
    //   164: invokevirtual 459	o/LP:ˏ	()Lo/FF;
    //   167: invokespecial 461	o/Lw:ˏ	(Lo/FF;)V
    //   170: goto -164 -> 6
    //   173: goto +6 -> 179
    //   176: goto -145 -> 31
    //   179: getstatic 24	o/Lw:ˊᐝ	I
    //   182: istore_3
    //   183: iload_3
    //   184: bipush 103
    //   186: iadd
    //   187: istore_3
    //   188: iload_3
    //   189: sipush 128
    //   192: irem
    //   193: putstatic 26	o/Lw:ˋˊ	I
    //   196: iload_3
    //   197: iconst_2
    //   198: irem
    //   199: ifne +6 -> 205
    //   202: goto -26 -> 176
    //   205: goto -174 -> 31
    //   208: return
    //   209: astore_1
    //   210: aload_1
    //   211: athrow
    // Local variable table:
    //   start	length	slot	name	signature
    //   0	212	0	this	Lw
    //   0	212	1	paramLP	LP
    //   43	49	2	c	char
    //   12	187	3	i	int
    // Exception table:
    //   from	to	target	type
    //   188	196	3	java/lang/Exception
    //   179	183	209	java/lang/Exception
  }
  
  public static final class ˊ
    extends Ik<EV>
  {
    private static int ʻ = 0;
    private static int ʽ = 1;
    private static char[] ˋ = { 306, 293, 307, 309, 300, 308, 301, 258, 297, 302, 292, 295, 238, 303, 294, 268, 261, 304, 313 };
    private static boolean ˎ;
    private static int ॱ = 192;
    private static boolean ᐝ = true;
    
    static
    {
      ˎ = true;
    }
    
    /* Error */
    ˊ(long paramLong, Context paramContext)
    {
      // Byte code:
      //   0: goto +9 -> 9
      //   3: astore_1
      //   4: aload_1
      //   5: athrow
      //   6: astore_1
      //   7: aload_1
      //   8: athrow
      //   9: aload_0
      //   10: aload_1
      //   11: putfield 62	o/Lw$ˊ:ˏ	Lo/Lw;
      //   14: aload_0
      //   15: lload_2
      //   16: putfield 64	o/Lw$ˊ:ˊ	J
      //   19: aload_0
      //   20: aload 4
      //   22: invokespecial 67	o/Ik:<init>	(Landroid/content/Context;)V
      //   25: return
      // Local variable table:
      //   start	length	slot	name	signature
      //   0	26	0	this	ˊ
      //   0	26	1	paramLong	long
      //   15	1	2	???	Object
      //   0	26	3	paramContext	Context
      //   20	1	4	localContext1	Context
      // Exception table:
      //   from	to	target	type
      //   14	25	3	java/lang/Exception
      //   9	14	6	java/lang/Exception
      //   14	25	6	java/lang/Exception
    }
    
    private static String ˎ(byte[] paramArrayOfByte, int[] paramArrayOfInt, char[] paramArrayOfChar, int paramInt)
    {
      break label379;
      break label357;
      int i = ʻ + 91;
      ʽ = i % 128;
      if (i % 2 != 0) {
        break label549;
      }
      label36:
      int j;
      char[] arrayOfChar;
      int k;
      label116:
      label164:
      int m;
      switch (j)
      {
      default: 
        break label481;
        for (;;)
        {
          if (!ˎ) {
            break label335;
          }
          j = paramArrayOfChar.length;
          paramArrayOfByte = new char[j];
          i = 0;
          break label226;
          arrayOfChar = ˋ;
          k = ॱ;
          if (ᐝ) {
            break;
          }
        }
        j = 35;
        break label415;
        paramArrayOfByte[i] = ((char)(arrayOfChar[(paramArrayOfChar[((j >> 1) * i)] >>> paramInt)] >>> k));
        i += 118;
        break;
      case 30: 
        return new String(paramArrayOfInt);
        paramArrayOfInt[i] = ((char)(arrayOfChar[(paramArrayOfByte[(m * 0 >> i)] >> paramInt)] * k));
        i += 107;
        label226:
        while (i < j)
        {
          m = ʽ + 121;
          ʻ = m % 128;
          if (m % 2 != 0) {
            break;
          }
          break label518;
        }
        break label370;
        break label549;
        for (;;)
        {
          break label357;
          label245:
          j = 63;
          break;
          label252:
          return new String(paramArrayOfByte);
          label261:
          paramArrayOfInt[i] = ((char)(arrayOfChar[(paramArrayOfByte[(m - 1 - i)] + paramInt)] - k));
          i += 1;
          break label322;
          label292:
          j = ʽ + 15;
          ʻ = j % 128;
          if (j % 2 == 0) {
            break label447;
          }
        }
      }
      for (;;)
      {
        label322:
        if (i < m) {
          break label245;
        }
        break label511;
        label335:
        m = paramArrayOfInt.length;
        paramArrayOfByte = new char[m];
        i = 0;
        break;
        label350:
        j = 10;
        label357:
        label370:
        label379:
        label415:
        label447:
        for (;;)
        {
          if (i < m) {
            break label116;
          }
          break label350;
          return new String(paramArrayOfByte);
          break;
          do
          {
            break;
            j = ʽ + 51;
            ʻ = j % 128;
          } while (j % 2 != 0);
          break label450;
          switch (j)
          {
          }
          break label252;
        }
        label450:
        paramArrayOfByte[i] = ((char)(arrayOfChar[(paramArrayOfInt[(m - 1 - i)] - paramInt)] - k));
        i += 1;
        break label292;
        label481:
        j = ʽ + 13;
        ʻ = j % 128;
        if (j % 2 != 0) {
          break label164;
        }
        break label261;
        label511:
        j = 30;
        break label36;
        label518:
        paramArrayOfByte[i] = ((char)(arrayOfChar[(paramArrayOfChar[(j - 1 - i)] - paramInt)] - k));
        i += 1;
        break label226;
        label549:
        m = paramArrayOfByte.length;
        paramArrayOfInt = new char[m];
        i = 0;
      }
    }
    
    protected void ˊ(EV paramEV)
    {
      break label272;
      break label256;
      label6:
      vq.ˎ(paramEV, ˎ(new byte[] { -122, -123, -124, -125, -126, -127 }, null, null, 127).intern());
      Lw.ˏ(this.ˏ, new HashSet());
      Lw.ˋ(this.ˏ).addAll((Collection)paramEV.ˊ());
      Lw.ˋ(this.ˏ).addAll((Collection)paramEV.ॱ());
      paramEV = Lw.ॱ(this.ˏ);
      Object localObject2 = (Iterable)Lw.ˋ(this.ˏ);
      Object localObject1 = (Collection)new ArrayList();
      localObject2 = ((Iterable)localObject2).iterator();
      break label256;
      int i = 12;
      break label361;
      label153:
      label165:
      Object localObject3;
      try
      {
        localObject1 = (List)localObject1;
      }
      catch (Exception paramEV)
      {
        label234:
        throw paramEV;
      }
      try
      {
        paramEV.ˎ((List)localObject1, true);
        return;
      }
      catch (Exception paramEV)
      {
        label245:
        label251:
        label256:
        label272:
        label275:
        throw paramEV;
      }
      ((Collection)localObject1).add(localObject3);
      for (;;)
      {
        switch (i)
        {
        default: 
          break;
        case 0: 
          do
          {
            localObject3 = ((Iterator)localObject2).next();
            if (((FF)localObject3).ʼ() > this.ˊ) {
              break label332;
            }
            break label418;
            i = 0;
            break label426;
            break label275;
            i = 60;
            break label361;
            i = 0;
            break;
          } while (((Iterator)localObject2).hasNext());
          break label153;
          break label6;
          i = ʽ + 23;
          ʻ = i % 128;
          if (i % 2 != 0) {
            break;
          }
          break label423;
          ((Collection)localObject1).add(localObject3);
          throw new NullPointerException();
        case 1: 
          label332:
          label361:
          label418:
          label423:
          label426:
          for (;;)
          {
            if (i != 0) {
              break label429;
            }
            break label251;
            i = ʻ + 13;
            ʽ = i % 128;
            if (i % 2 == 0) {
              break label234;
            }
            i = 1;
            break label426;
            switch (i)
            {
            }
            break label165;
            i = ʻ + 53;
            ʽ = i % 128;
            if (i % 2 == 0) {
              break;
            }
            break label245;
            i = 0;
            continue;
            break label256;
          }
          label429:
          i = 1;
        }
      }
    }
    
    public void ˏ()
    {
      for (;;)
      {
        label6:
        break label315;
        for (;;)
        {
          Object localObject = Lw.ˏ(this.ˏ).ʼ;
          vq.ˋ(localObject, ˎ(new byte[] { -109, -122, -110, -121, -111, -122, -125, -119, -112, -125, -127, -126, -113, -113, -114, -115, -116, -118, -119, -117, -118, -119, -120, -121 }, null, null, 127).intern());
          ((TextView)localObject).setVisibility(0);
          break label6;
          do
          {
            i = 1;
            break;
            super.ˏ();
            localObject = Lw.ˏ(this.ˏ);
            vq.ˋ(localObject, ˎ(new byte[] { -116, -118, -119, -117, -118, -119, -120, -121 }, null, null, 127).intern());
            ((LB)localObject).ˏ(false);
          } while (Lw.ˋ(this.ˏ).isEmpty());
          break label338;
          i = ʻ + 119;
          ʽ = i % 128;
          if (i % 2 == 0) {
            break;
          }
        }
        label315:
        int i = ʽ + 9;
        ʻ = i % 128;
        if (i % 2 != 0) {
          return;
        }
        return;
        label338:
        i = 0;
        switch (i)
        {
        }
      }
    }
  }
}
