package o;

import android.app.Activity;
import android.content.Context;
import android.view.View;
import android.view.View.OnClickListener;

public final class Lx
  extends o<FM, If>
{
  private static int ˊ = 0;
  private static int ˋ = 0;
  private static char ˎ;
  private static long ˏ;
  private static int ॱॱ = 1;
  private Activity ॱ;
  
  static
  {
    ˎ = '\000';
    ˏ = -5037491779750117929L;
  }
  
  public Lx() {}
  
  private static String ˊ(char[] paramArrayOfChar1, char paramChar, char[] paramArrayOfChar2, int paramInt, char[] paramArrayOfChar3)
  {
    break label174;
    char c;
    if (paramChar >= c) {
      break label210;
    }
    label45:
    char[] arrayOfChar;
    label174:
    for (;;)
    {
      c = ॱॱ + 7;
      ˋ = c % '';
      if (c % '\002' != 0) {
        break label177;
      }
      break label227;
      switch (paramInt)
      {
      default: 
        break;
      case 33: 
        oJ.ˏ(paramArrayOfChar1, paramArrayOfChar3, paramChar);
        arrayOfChar[paramChar] = ((char)(int)(((paramArrayOfChar2[paramChar] | paramArrayOfChar1[(paramChar % '\005' % 3)]) & ˏ | ˊ) * ˎ));
        paramChar += '5';
        break;
      case 0: 
        oJ.ˏ(paramArrayOfChar1, paramArrayOfChar3, paramChar);
        arrayOfChar[paramChar] = ((char)(int)(paramArrayOfChar2[paramChar] ^ paramArrayOfChar1[((paramChar + '\003') % 4)] ^ ˏ ^ ˊ ^ ˎ));
        paramChar += '\001';
        break;
        paramInt = 85;
        break label291;
      }
    }
    for (;;)
    {
      label177:
      break;
      paramInt = ˋ + 19;
      ॱॱ = paramInt % 128;
      if (paramInt % 2 != 0)
      {
        break label222;
        label210:
        paramInt = 35;
        break label291;
      }
      else
      {
        paramInt = 33;
        break label45;
      }
      label222:
      paramInt = 0;
      break label45;
      label227:
      paramArrayOfChar1 = (char[])paramArrayOfChar1.clone();
      paramArrayOfChar3 = (char[])paramArrayOfChar3.clone();
      paramArrayOfChar1[0] = ((char)(paramArrayOfChar1[0] ^ paramChar));
      paramArrayOfChar3[2] = ((char)(paramArrayOfChar3[2] + (char)paramInt));
      c = paramArrayOfChar2.length;
      arrayOfChar = new char[c];
      paramChar = '\000';
    }
    for (;;)
    {
      return new String(arrayOfChar);
      label291:
      switch (paramInt)
      {
      }
    }
  }
  
  /* Error */
  public If ˎ(android.view.ViewGroup arg1, int arg2)
  {
    // Byte code:
    //   0: goto +39 -> 39
    //   3: aload_1
    //   4: areturn
    //   5: iconst_0
    //   6: istore_2
    //   7: iload_2
    //   8: tableswitch	default:+24->32, 0:+-5->3, 1:+505->513
    //   32: aload_1
    //   33: areturn
    //   34: iconst_1
    //   35: istore_2
    //   36: goto -29 -> 7
    //   39: iconst_4
    //   40: newarray char
    //   42: dup
    //   43: iconst_0
    //   44: ldc 96
    //   46: castore
    //   47: dup
    //   48: iconst_1
    //   49: ldc 97
    //   51: castore
    //   52: dup
    //   53: iconst_2
    //   54: ldc 98
    //   56: castore
    //   57: dup
    //   58: iconst_3
    //   59: ldc 99
    //   61: castore
    //   62: sipush 14920
    //   65: bipush 6
    //   67: newarray char
    //   69: dup
    //   70: iconst_0
    //   71: ldc 100
    //   73: castore
    //   74: dup
    //   75: iconst_1
    //   76: ldc 101
    //   78: castore
    //   79: dup
    //   80: iconst_2
    //   81: ldc 102
    //   83: castore
    //   84: dup
    //   85: iconst_3
    //   86: ldc 103
    //   88: castore
    //   89: dup
    //   90: iconst_4
    //   91: ldc 104
    //   93: castore
    //   94: dup
    //   95: iconst_5
    //   96: ldc 105
    //   98: castore
    //   99: iconst_0
    //   100: iconst_4
    //   101: newarray char
    //   103: dup
    //   104: iconst_0
    //   105: ldc 72
    //   107: castore
    //   108: dup
    //   109: iconst_1
    //   110: ldc 73
    //   112: castore
    //   113: dup
    //   114: iconst_2
    //   115: ldc 74
    //   117: castore
    //   118: dup
    //   119: iconst_3
    //   120: ldc 75
    //   122: castore
    //   123: invokestatic 77	o/Lx:ˊ	([CC[CI[C)Ljava/lang/String;
    //   126: astore_3
    //   127: aload_1
    //   128: aload_3
    //   129: invokevirtual 81	java/lang/String:intern	()Ljava/lang/String;
    //   132: invokestatic 108	o/vq:ˎ	(Ljava/lang/Object;Ljava/lang/String;)V
    //   135: aload_0
    //   136: aload_1
    //   137: getstatic 113	o/Lt$ˋ:layout_offer_filter_city_card	I
    //   140: invokevirtual 116	o/Lx:ॱ	(Landroid/view/ViewGroup;I)Landroid/view/View;
    //   143: astore_1
    //   144: aload_1
    //   145: iconst_4
    //   146: newarray char
    //   148: dup
    //   149: iconst_0
    //   150: ldc 117
    //   152: castore
    //   153: dup
    //   154: iconst_1
    //   155: ldc 118
    //   157: castore
    //   158: dup
    //   159: iconst_2
    //   160: ldc 119
    //   162: castore
    //   163: dup
    //   164: iconst_3
    //   165: ldc 120
    //   167: castore
    //   168: iconst_0
    //   169: bipush 50
    //   171: newarray char
    //   173: dup
    //   174: iconst_0
    //   175: ldc 121
    //   177: castore
    //   178: dup
    //   179: iconst_1
    //   180: ldc 122
    //   182: castore
    //   183: dup
    //   184: iconst_2
    //   185: ldc 123
    //   187: castore
    //   188: dup
    //   189: iconst_3
    //   190: ldc 124
    //   192: castore
    //   193: dup
    //   194: iconst_4
    //   195: ldc 125
    //   197: castore
    //   198: dup
    //   199: iconst_5
    //   200: ldc 126
    //   202: castore
    //   203: dup
    //   204: bipush 6
    //   206: ldc 127
    //   208: castore
    //   209: dup
    //   210: bipush 7
    //   212: ldc -128
    //   214: castore
    //   215: dup
    //   216: bipush 8
    //   218: ldc -127
    //   220: castore
    //   221: dup
    //   222: bipush 9
    //   224: ldc -126
    //   226: castore
    //   227: dup
    //   228: bipush 10
    //   230: ldc -125
    //   232: castore
    //   233: dup
    //   234: bipush 11
    //   236: ldc -124
    //   238: castore
    //   239: dup
    //   240: bipush 12
    //   242: ldc -123
    //   244: castore
    //   245: dup
    //   246: bipush 13
    //   248: ldc -122
    //   250: castore
    //   251: dup
    //   252: bipush 14
    //   254: ldc -121
    //   256: castore
    //   257: dup
    //   258: bipush 15
    //   260: ldc -120
    //   262: castore
    //   263: dup
    //   264: bipush 16
    //   266: ldc -119
    //   268: castore
    //   269: dup
    //   270: bipush 17
    //   272: ldc -118
    //   274: castore
    //   275: dup
    //   276: bipush 18
    //   278: ldc -117
    //   280: castore
    //   281: dup
    //   282: bipush 19
    //   284: ldc -116
    //   286: castore
    //   287: dup
    //   288: bipush 20
    //   290: ldc -115
    //   292: castore
    //   293: dup
    //   294: bipush 21
    //   296: ldc -114
    //   298: castore
    //   299: dup
    //   300: bipush 22
    //   302: ldc -113
    //   304: castore
    //   305: dup
    //   306: bipush 23
    //   308: ldc -112
    //   310: castore
    //   311: dup
    //   312: bipush 24
    //   314: ldc -111
    //   316: castore
    //   317: dup
    //   318: bipush 25
    //   320: ldc -110
    //   322: castore
    //   323: dup
    //   324: bipush 26
    //   326: ldc -109
    //   328: castore
    //   329: dup
    //   330: bipush 27
    //   332: ldc -108
    //   334: castore
    //   335: dup
    //   336: bipush 28
    //   338: ldc -107
    //   340: castore
    //   341: dup
    //   342: bipush 29
    //   344: ldc -106
    //   346: castore
    //   347: dup
    //   348: bipush 30
    //   350: ldc -105
    //   352: castore
    //   353: dup
    //   354: bipush 31
    //   356: ldc -104
    //   358: castore
    //   359: dup
    //   360: bipush 32
    //   362: ldc -103
    //   364: castore
    //   365: dup
    //   366: bipush 33
    //   368: ldc -102
    //   370: castore
    //   371: dup
    //   372: bipush 34
    //   374: ldc -101
    //   376: castore
    //   377: dup
    //   378: bipush 35
    //   380: ldc -100
    //   382: castore
    //   383: dup
    //   384: bipush 36
    //   386: ldc -99
    //   388: castore
    //   389: dup
    //   390: bipush 37
    //   392: ldc -98
    //   394: castore
    //   395: dup
    //   396: bipush 38
    //   398: ldc -97
    //   400: castore
    //   401: dup
    //   402: bipush 39
    //   404: ldc -96
    //   406: castore
    //   407: dup
    //   408: bipush 40
    //   410: ldc -95
    //   412: castore
    //   413: dup
    //   414: bipush 41
    //   416: ldc -94
    //   418: castore
    //   419: dup
    //   420: bipush 42
    //   422: ldc -93
    //   424: castore
    //   425: dup
    //   426: bipush 43
    //   428: ldc -92
    //   430: castore
    //   431: dup
    //   432: bipush 44
    //   434: ldc -91
    //   436: castore
    //   437: dup
    //   438: bipush 45
    //   440: ldc -90
    //   442: castore
    //   443: dup
    //   444: bipush 46
    //   446: ldc -89
    //   448: castore
    //   449: dup
    //   450: bipush 47
    //   452: ldc -88
    //   454: castore
    //   455: dup
    //   456: bipush 48
    //   458: ldc -87
    //   460: castore
    //   461: dup
    //   462: bipush 49
    //   464: ldc -86
    //   466: castore
    //   467: iconst_0
    //   468: iconst_4
    //   469: newarray char
    //   471: dup
    //   472: iconst_0
    //   473: ldc 72
    //   475: castore
    //   476: dup
    //   477: iconst_1
    //   478: ldc 73
    //   480: castore
    //   481: dup
    //   482: iconst_2
    //   483: ldc 74
    //   485: castore
    //   486: dup
    //   487: iconst_3
    //   488: ldc 75
    //   490: castore
    //   491: invokestatic 77	o/Lx:ˊ	([CC[CI[C)Ljava/lang/String;
    //   494: invokevirtual 81	java/lang/String:intern	()Ljava/lang/String;
    //   497: invokestatic 172	o/vq:ˋ	(Ljava/lang/Object;Ljava/lang/String;)V
    //   500: new 7	o/Lx$If
    //   503: dup
    //   504: aload_0
    //   505: aload_1
    //   506: invokespecial 175	o/Lx$If:<init>	(Lo/Lx;Landroid/view/View;)V
    //   509: astore_1
    //   510: goto +11 -> 521
    //   513: aconst_null
    //   514: arraylength
    //   515: istore_2
    //   516: aload_1
    //   517: areturn
    //   518: astore_1
    //   519: aload_1
    //   520: athrow
    //   521: getstatic 24	o/Lx:ॱॱ	I
    //   524: bipush 107
    //   526: iadd
    //   527: istore_2
    //   528: iload_2
    //   529: sipush 128
    //   532: irem
    //   533: putstatic 22	o/Lx:ˋ	I
    //   536: iload_2
    //   537: iconst_2
    //   538: irem
    //   539: ifeq +6 -> 545
    //   542: goto -508 -> 34
    //   545: goto -540 -> 5
    //   548: astore_1
    //   549: aload_1
    //   550: athrow
    // Exception table:
    //   from	to	target	type
    //   39	127	548	java/lang/Exception
    //   127	510	548	java/lang/Exception
  }
  
  public void ॱ(If paramIf, int paramInt)
  {
    for (;;)
    {
      int i = ॱॱ + 115;
      ˋ = i % 128;
      if (i % 2 != 0) {
        break;
      }
      break;
    }
    vq.ˎ(paramIf, ˊ(new char[] { 26958, 28432, -26726, -10613 }, 35735, new char[] { -7305, -13098, 7526, 7720, -24311, -22062 }, 0, new char[] { 15831, -31477, 15338, -17897 }).intern());
    FM localFM = (FM)ॱ(paramInt);
    LH localLH = (LH)paramIf.ˋ();
    vq.ˋ(localLH, ˊ(new char[] { -2232, -28513, 26981, -19080 }, '硩', new char[] { 13138, -8698, 23522, -10001, 5767, -32628, 9669, 26084, 25425, 22602, -2298, 3438, -14273, 16526 }, 0, new char[] { 15831, -31477, 15338, -17897 }).intern());
    localLH.ˋ(localFM);
    paramIf = paramIf.ॱ;
    vq.ˋ(paramIf, ˊ(new char[] { 24097, -11551, -30609, -10020 }, 56456, new char[] { 25662, 6178, 25105, -22665, -15492, -28520, 6200, -10491, 28788, -28689, 20125, -18378, 17836, 24329, -15441 }, 1876091230, new char[] { 15831, -31477, 15338, -17897 }).intern());
    paramIf.setTag(localFM);
    paramInt = ॱॱ + 107;
    ˋ = paramInt % 128;
    if (paramInt % 2 != 0) {}
  }
  
  public final class If
    extends p<LH>
    implements View.OnClickListener
  {
    private static int ʻॱ = 1;
    private static char[] ˊॱ = { 118, 105, 101, 119, 110, 117, 108, 32, 99, 97, 111, 116, 98, 115, 45, 121, 112, 114, 46, 102, 109, 100, 79, 67, 65 };
    private static char ॱˋ = '\005';
    private static int ॱˎ = 0;
    
    public If() {}
    
    private static String ˊ(char[] paramArrayOfChar, int paramInt, byte paramByte)
    {
      break label566;
      label3:
      break label293;
      label6:
      byte b3;
      byte b2;
      label19:
      byte b1;
      int i;
      label60:
      label63:
      int k;
      byte b4;
      char[] arrayOfChar2;
      char[] arrayOfChar1;
      label126:
      label143:
      byte b5;
      byte b6;
      int j;
      if (b3 != b2)
      {
        break label248;
        b1 = ॱˎ + 85;
        ʻॱ = b1 % 128;
        if (b1 % 2 == 0) {
          break label523;
        }
        break label572;
        while (i >= paramInt) {
          break label603;
        }
        b3 = oO.ˊ(b3, k);
        b2 = oO.ˊ(b2, k);
        b3 = oO.ˏ(b3, b4, k);
        b1 = oO.ˏ(b2, b1, k);
        arrayOfChar2[i] = arrayOfChar1[b3];
        arrayOfChar2[(i + 1)] = arrayOfChar1[b1];
        break label356;
        paramInt -= 1;
        arrayOfChar2[paramInt] = ((char)(paramArrayOfChar[paramInt] - paramByte));
        break label609;
        b2 = b3;
        b1 = b4;
        b5 = b3;
        b6 = b4;
        switch (j)
        {
        default: 
          b5 = b3;
          b6 = b4;
          break;
        }
      }
      label248:
      label293:
      label356:
      label363:
      label391:
      label398:
      label425:
      label433:
      label516:
      label523:
      label553:
      for (;;)
      {
        b3 = oO.ॱ(b2, k);
        b4 = oO.ˋ(b2, k);
        b2 = oO.ॱ(b1, k);
        b1 = oO.ˋ(b1, k);
        if (b4 == b1) {
          break label63;
        }
        break label6;
        b1 = oO.ˏ(b3, b1, k);
        b2 = oO.ˏ(b2, b4, k);
        arrayOfChar2[i] = arrayOfChar1[b1];
        arrayOfChar2[(i + 1)] = arrayOfChar1[b2];
        for (;;)
        {
          b4 = oO.ˊ(b4, k);
          b1 = oO.ˊ(b1, k);
          b3 = oO.ˏ(b3, b4, k);
          b1 = oO.ˏ(b2, b1, k);
          arrayOfChar2[i] = arrayOfChar1[b3];
          arrayOfChar2[(i + 1)] = arrayOfChar1[b1];
          break label433;
          i += 2;
          break label569;
          switch (b1)
          {
          case 0: 
          default: 
            break label19;
            j = 18;
            break label143;
            arrayOfChar1 = ˊॱ;
            k = ॱˋ;
            arrayOfChar2 = new char[paramInt];
            if (paramInt % 2 != 0) {
              break label126;
            }
            break label609;
            i = 0;
            break label60;
            for (;;)
            {
              break;
              b1 = ॱˎ + 45;
              ʻॱ = b1 % 128;
              if (b1 % 2 == 0) {
                break;
              }
            }
            b5 = ʻॱ + 11;
            ॱˎ = b5 % 128;
            if (b5 % 2 != 0) {
              break label3;
            }
          }
        }
        for (;;)
        {
          arrayOfChar2[i] = ((char)(b5 - paramByte));
          arrayOfChar2[(i + 1)] = ((char)(b6 - paramByte));
          break label356;
          j = 63;
          break;
          b2 = paramArrayOfChar[i];
          b1 = paramArrayOfChar[(i >> 0)];
          if (b2 != b1) {
            break label553;
          }
          b5 = b2;
          b6 = b1;
        }
      }
      for (;;)
      {
        return new String(arrayOfChar2);
        label566:
        break label398;
        label569:
        break;
        label572:
        b3 = paramArrayOfChar[i];
        b4 = paramArrayOfChar[(i + 1)];
        if (b3 == b4) {
          break label391;
        }
        break label516;
        b1 = 0;
        break label363;
        label603:
        b1 = 1;
        break label363;
        label609:
        if (paramInt > 1) {
          break label425;
        }
      }
    }
    
    /* Error */
    public void onClick(View paramView)
    {
      // Byte code:
      //   0: goto +555 -> 555
      //   3: astore_1
      //   4: aload_1
      //   5: athrow
      //   6: iconst_4
      //   7: newarray char
      //   9: dup
      //   10: iconst_0
      //   11: ldc 73
      //   13: castore
      //   14: dup
      //   15: iconst_1
      //   16: ldc 69
      //   18: castore
      //   19: dup
      //   20: iconst_2
      //   21: ldc 82
      //   23: castore
      //   24: dup
      //   25: iconst_3
      //   26: ldc 98
      //   28: castore
      //   29: iconst_4
      //   30: bipush 29
      //   32: invokestatic 86	o/Lx$If:ˊ	([CIB)Ljava/lang/String;
      //   35: astore_3
      //   36: aload_3
      //   37: invokevirtual 92	java/lang/String:intern	()Ljava/lang/String;
      //   40: astore_3
      //   41: aload_1
      //   42: aload_3
      //   43: invokestatic 104	o/vq:ˎ	(Ljava/lang/Object;Ljava/lang/String;)V
      //   46: aload_1
      //   47: invokevirtual 149	android/view/View:getTag	()Ljava/lang/Object;
      //   50: astore_1
      //   51: aload_1
      //   52: ifnonnull +6 -> 58
      //   55: goto +29 -> 84
      //   58: aload_1
      //   59: checkcast 151	o/FM
      //   62: astore_3
      //   63: aload_0
      //   64: getfield 106	o/Lx$If:ˋॱ	Lo/Lx;
      //   67: invokestatic 154	o/Lx:ˋ	(Lo/Lx;)Landroid/app/Activity;
      //   70: astore_1
      //   71: aload_1
      //   72: ifnonnull +6 -> 78
      //   75: goto +511 -> 586
      //   78: goto +992 -> 1070
      //   81: goto -75 -> 6
      //   84: new 94	o/uH
      //   87: dup
      //   88: bipush 75
      //   90: newarray char
      //   92: dup
      //   93: iconst_0
      //   94: ldc 60
      //   96: castore
      //   97: dup
      //   98: iconst_1
      //   99: ldc 61
      //   101: castore
      //   102: dup
      //   103: iconst_2
      //   104: ldc -101
      //   106: castore
      //   107: dup
      //   108: iconst_3
      //   109: ldc -101
      //   111: castore
      //   112: dup
      //   113: iconst_4
      //   114: ldc 62
      //   116: castore
      //   117: dup
      //   118: iconst_5
      //   119: ldc 61
      //   121: castore
      //   122: dup
      //   123: bipush 6
      //   125: ldc 63
      //   127: castore
      //   128: dup
      //   129: bipush 7
      //   131: ldc 61
      //   133: castore
      //   134: dup
      //   135: bipush 8
      //   137: ldc 60
      //   139: castore
      //   140: dup
      //   141: bipush 9
      //   143: ldc 63
      //   145: castore
      //   146: dup
      //   147: bipush 10
      //   149: ldc 64
      //   151: castore
      //   152: dup
      //   153: bipush 11
      //   155: ldc 65
      //   157: castore
      //   158: dup
      //   159: bipush 12
      //   161: ldc 66
      //   163: castore
      //   164: dup
      //   165: bipush 13
      //   167: ldc 67
      //   169: castore
      //   170: dup
      //   171: bipush 14
      //   173: ldc 62
      //   175: castore
      //   176: dup
      //   177: bipush 15
      //   179: ldc 61
      //   181: castore
      //   182: dup
      //   183: bipush 16
      //   185: ldc 62
      //   187: castore
      //   188: dup
      //   189: bipush 17
      //   191: ldc 63
      //   193: castore
      //   194: dup
      //   195: bipush 18
      //   197: ldc 64
      //   199: castore
      //   200: dup
      //   201: bipush 19
      //   203: ldc 65
      //   205: castore
      //   206: dup
      //   207: bipush 20
      //   209: ldc 64
      //   211: castore
      //   212: dup
      //   213: bipush 21
      //   215: ldc 68
      //   217: castore
      //   218: dup
      //   219: bipush 22
      //   221: ldc 61
      //   223: castore
      //   224: dup
      //   225: bipush 23
      //   227: ldc 69
      //   229: castore
      //   230: dup
      //   231: bipush 24
      //   233: ldc 63
      //   235: castore
      //   236: dup
      //   237: bipush 25
      //   239: ldc 60
      //   241: castore
      //   242: dup
      //   243: bipush 26
      //   245: ldc 70
      //   247: castore
      //   248: dup
      //   249: bipush 27
      //   251: ldc 61
      //   253: castore
      //   254: dup
      //   255: bipush 28
      //   257: ldc 65
      //   259: castore
      //   260: dup
      //   261: bipush 29
      //   263: ldc 67
      //   265: castore
      //   266: dup
      //   267: bipush 30
      //   269: ldc 67
      //   271: castore
      //   272: dup
      //   273: bipush 31
      //   275: ldc 62
      //   277: castore
      //   278: dup
      //   279: bipush 32
      //   281: ldc 71
      //   283: castore
      //   284: dup
      //   285: bipush 33
      //   287: ldc 72
      //   289: castore
      //   290: dup
      //   291: bipush 34
      //   293: ldc 66
      //   295: castore
      //   296: dup
      //   297: bipush 35
      //   299: ldc 73
      //   301: castore
      //   302: dup
      //   303: bipush 36
      //   305: ldc 64
      //   307: castore
      //   308: dup
      //   309: bipush 37
      //   311: ldc 74
      //   313: castore
      //   314: dup
      //   315: bipush 38
      //   317: ldc 75
      //   319: castore
      //   320: dup
      //   321: bipush 39
      //   323: ldc 76
      //   325: castore
      //   326: dup
      //   327: bipush 40
      //   329: ldc 75
      //   331: castore
      //   332: dup
      //   333: bipush 41
      //   335: ldc 64
      //   337: castore
      //   338: dup
      //   339: bipush 42
      //   341: ldc 72
      //   343: castore
      //   344: dup
      //   345: bipush 43
      //   347: ldc 67
      //   349: castore
      //   350: dup
      //   351: bipush 44
      //   353: ldc 66
      //   355: castore
      //   356: dup
      //   357: bipush 45
      //   359: ldc 75
      //   361: castore
      //   362: dup
      //   363: bipush 46
      //   365: ldc 62
      //   367: castore
      //   368: dup
      //   369: bipush 47
      //   371: ldc 71
      //   373: castore
      //   374: dup
      //   375: bipush 48
      //   377: ldc 69
      //   379: castore
      //   380: dup
      //   381: bipush 49
      //   383: ldc 60
      //   385: castore
      //   386: dup
      //   387: bipush 50
      //   389: ldc 82
      //   391: castore
      //   392: dup
      //   393: bipush 51
      //   395: ldc 64
      //   397: castore
      //   398: dup
      //   399: bipush 52
      //   401: ldc 78
      //   403: castore
      //   404: dup
      //   405: bipush 53
      //   407: ldc 79
      //   409: castore
      //   410: dup
      //   411: bipush 54
      //   413: ldc 63
      //   415: castore
      //   416: dup
      //   417: bipush 55
      //   419: ldc 76
      //   421: castore
      //   422: dup
      //   423: bipush 56
      //   425: ldc 66
      //   427: castore
      //   428: dup
      //   429: bipush 57
      //   431: ldc 98
      //   433: castore
      //   434: dup
      //   435: bipush 58
      //   437: ldc 78
      //   439: castore
      //   440: dup
      //   441: bipush 59
      //   443: ldc 70
      //   445: castore
      //   446: dup
      //   447: bipush 60
      //   449: ldc 60
      //   451: castore
      //   452: dup
      //   453: bipush 61
      //   455: ldc 76
      //   457: castore
      //   458: dup
      //   459: bipush 62
      //   461: ldc 74
      //   463: castore
      //   464: dup
      //   465: bipush 63
      //   467: ldc 73
      //   469: castore
      //   470: dup
      //   471: bipush 64
      //   473: ldc 62
      //   475: castore
      //   476: dup
      //   477: bipush 65
      //   479: ldc 72
      //   481: castore
      //   482: dup
      //   483: bipush 66
      //   485: ldc -100
      //   487: castore
      //   488: dup
      //   489: bipush 67
      //   491: ldc 66
      //   493: castore
      //   494: dup
      //   495: bipush 68
      //   497: ldc 66
      //   499: castore
      //   500: dup
      //   501: bipush 69
      //   503: ldc 98
      //   505: castore
      //   506: dup
      //   507: bipush 70
      //   509: ldc 78
      //   511: castore
      //   512: dup
      //   513: bipush 71
      //   515: ldc 74
      //   517: castore
      //   518: dup
      //   519: bipush 72
      //   521: ldc 65
      //   523: castore
      //   524: dup
      //   525: bipush 73
      //   527: ldc 72
      //   529: castore
      //   530: dup
      //   531: bipush 74
      //   533: ldc -99
      //   535: castore
      //   536: bipush 75
      //   538: bipush 70
      //   540: invokestatic 86	o/Lx$If:ˊ	([CIB)Ljava/lang/String;
      //   543: invokevirtual 92	java/lang/String:intern	()Ljava/lang/String;
      //   546: invokespecial 97	o/uH:<init>	(Ljava/lang/String;)V
      //   549: athrow
      //   550: iconst_1
      //   551: istore_2
      //   552: goto +529 -> 1081
      //   555: goto +558 -> 1113
      //   558: return
      //   559: getstatic 23	o/Lx$If:ॱˎ	I
      //   562: bipush 123
      //   564: iadd
      //   565: istore_2
      //   566: iload_2
      //   567: sipush 128
      //   570: irem
      //   571: putstatic 25	o/Lx$If:ʻॱ	I
      //   574: iload_2
      //   575: iconst_2
      //   576: irem
      //   577: ifne +6 -> 583
      //   580: goto +528 -> 1108
      //   583: goto -33 -> 550
      //   586: new 94	o/uH
      //   589: dup
      //   590: bipush 78
      //   592: newarray char
      //   594: dup
      //   595: iconst_0
      //   596: ldc 60
      //   598: castore
      //   599: dup
      //   600: iconst_1
      //   601: ldc 61
      //   603: castore
      //   604: dup
      //   605: iconst_2
      //   606: ldc 29
      //   608: castore
      //   609: dup
      //   610: iconst_3
      //   611: ldc 29
      //   613: castore
      //   614: dup
      //   615: iconst_4
      //   616: ldc 62
      //   618: castore
      //   619: dup
      //   620: iconst_5
      //   621: ldc 61
      //   623: castore
      //   624: dup
      //   625: bipush 6
      //   627: ldc 63
      //   629: castore
      //   630: dup
      //   631: bipush 7
      //   633: ldc 61
      //   635: castore
      //   636: dup
      //   637: bipush 8
      //   639: ldc 60
      //   641: castore
      //   642: dup
      //   643: bipush 9
      //   645: ldc 63
      //   647: castore
      //   648: dup
      //   649: bipush 10
      //   651: ldc 64
      //   653: castore
      //   654: dup
      //   655: bipush 11
      //   657: ldc 65
      //   659: castore
      //   660: dup
      //   661: bipush 12
      //   663: ldc 66
      //   665: castore
      //   666: dup
      //   667: bipush 13
      //   669: ldc 67
      //   671: castore
      //   672: dup
      //   673: bipush 14
      //   675: ldc 62
      //   677: castore
      //   678: dup
      //   679: bipush 15
      //   681: ldc 61
      //   683: castore
      //   684: dup
      //   685: bipush 16
      //   687: ldc 62
      //   689: castore
      //   690: dup
      //   691: bipush 17
      //   693: ldc 63
      //   695: castore
      //   696: dup
      //   697: bipush 18
      //   699: ldc 64
      //   701: castore
      //   702: dup
      //   703: bipush 19
      //   705: ldc 65
      //   707: castore
      //   708: dup
      //   709: bipush 20
      //   711: ldc 64
      //   713: castore
      //   714: dup
      //   715: bipush 21
      //   717: ldc 68
      //   719: castore
      //   720: dup
      //   721: bipush 22
      //   723: ldc 61
      //   725: castore
      //   726: dup
      //   727: bipush 23
      //   729: ldc 69
      //   731: castore
      //   732: dup
      //   733: bipush 24
      //   735: ldc 63
      //   737: castore
      //   738: dup
      //   739: bipush 25
      //   741: ldc 60
      //   743: castore
      //   744: dup
      //   745: bipush 26
      //   747: ldc 70
      //   749: castore
      //   750: dup
      //   751: bipush 27
      //   753: ldc 61
      //   755: castore
      //   756: dup
      //   757: bipush 28
      //   759: ldc 65
      //   761: castore
      //   762: dup
      //   763: bipush 29
      //   765: ldc 67
      //   767: castore
      //   768: dup
      //   769: bipush 30
      //   771: ldc 67
      //   773: castore
      //   774: dup
      //   775: bipush 31
      //   777: ldc 62
      //   779: castore
      //   780: dup
      //   781: bipush 32
      //   783: ldc 71
      //   785: castore
      //   786: dup
      //   787: bipush 33
      //   789: ldc 72
      //   791: castore
      //   792: dup
      //   793: bipush 34
      //   795: ldc 66
      //   797: castore
      //   798: dup
      //   799: bipush 35
      //   801: ldc 73
      //   803: castore
      //   804: dup
      //   805: bipush 36
      //   807: ldc 64
      //   809: castore
      //   810: dup
      //   811: bipush 37
      //   813: ldc 74
      //   815: castore
      //   816: dup
      //   817: bipush 38
      //   819: ldc 75
      //   821: castore
      //   822: dup
      //   823: bipush 39
      //   825: ldc 76
      //   827: castore
      //   828: dup
      //   829: bipush 40
      //   831: ldc 75
      //   833: castore
      //   834: dup
      //   835: bipush 41
      //   837: ldc 64
      //   839: castore
      //   840: dup
      //   841: bipush 42
      //   843: ldc 72
      //   845: castore
      //   846: dup
      //   847: bipush 43
      //   849: ldc 67
      //   851: castore
      //   852: dup
      //   853: bipush 44
      //   855: ldc 76
      //   857: castore
      //   858: dup
      //   859: bipush 45
      //   861: ldc 75
      //   863: castore
      //   864: dup
      //   865: bipush 46
      //   867: ldc 77
      //   869: castore
      //   870: dup
      //   871: bipush 47
      //   873: ldc 77
      //   875: castore
      //   876: dup
      //   877: bipush 48
      //   879: ldc 67
      //   881: castore
      //   882: dup
      //   883: bipush 49
      //   885: ldc 74
      //   887: castore
      //   888: dup
      //   889: bipush 50
      //   891: ldc 78
      //   893: castore
      //   894: dup
      //   895: bipush 51
      //   897: ldc 79
      //   899: castore
      //   900: dup
      //   901: bipush 52
      //   903: ldc 80
      //   905: castore
      //   906: dup
      //   907: bipush 53
      //   909: ldc 61
      //   911: castore
      //   912: dup
      //   913: bipush 54
      //   915: ldc 72
      //   917: castore
      //   918: dup
      //   919: bipush 55
      //   921: ldc 65
      //   923: castore
      //   924: dup
      //   925: bipush 56
      //   927: ldc 73
      //   929: castore
      //   930: dup
      //   931: bipush 57
      //   933: ldc 69
      //   935: castore
      //   936: dup
      //   937: bipush 58
      //   939: ldc 71
      //   941: castore
      //   942: dup
      //   943: bipush 59
      //   945: ldc 72
      //   947: castore
      //   948: dup
      //   949: bipush 60
      //   951: ldc 66
      //   953: castore
      //   954: dup
      //   955: bipush 61
      //   957: ldc 79
      //   959: castore
      //   960: dup
      //   961: bipush 62
      //   963: ldc 77
      //   965: castore
      //   966: dup
      //   967: bipush 63
      //   969: ldc 77
      //   971: castore
      //   972: dup
      //   973: bipush 64
      //   975: ldc 67
      //   977: castore
      //   978: dup
      //   979: bipush 65
      //   981: ldc 74
      //   983: castore
      //   984: dup
      //   985: bipush 66
      //   987: ldc 81
      //   989: castore
      //   990: dup
      //   991: bipush 67
      //   993: ldc 82
      //   995: castore
      //   996: dup
      //   997: bipush 68
      //   999: ldc 71
      //   1001: castore
      //   1002: dup
      //   1003: bipush 69
      //   1005: ldc 72
      //   1007: castore
      //   1008: dup
      //   1009: bipush 70
      //   1011: ldc 79
      //   1013: castore
      //   1014: dup
      //   1015: bipush 71
      //   1017: ldc 61
      //   1019: castore
      //   1020: dup
      //   1021: bipush 72
      //   1023: ldc 72
      //   1025: castore
      //   1026: dup
      //   1027: bipush 73
      //   1029: ldc 65
      //   1031: castore
      //   1032: dup
      //   1033: bipush 74
      //   1035: ldc 73
      //   1037: castore
      //   1038: dup
      //   1039: bipush 75
      //   1041: ldc 69
      //   1043: castore
      //   1044: dup
      //   1045: bipush 76
      //   1047: ldc 71
      //   1049: castore
      //   1050: dup
      //   1051: bipush 77
      //   1053: ldc 72
      //   1055: castore
      //   1056: bipush 78
      //   1058: bipush 11
      //   1060: invokestatic 86	o/Lx$If:ˊ	([CIB)Ljava/lang/String;
      //   1063: invokevirtual 92	java/lang/String:intern	()Ljava/lang/String;
      //   1066: invokespecial 97	o/uH:<init>	(Ljava/lang/String;)V
      //   1069: athrow
      //   1070: aload_1
      //   1071: checkcast 115	o/Lv
      //   1074: aload_3
      //   1075: invokevirtual 160	o/Lv:ˏ	(Lo/FM;)V
      //   1078: goto -519 -> 559
      //   1081: iload_2
      //   1082: tableswitch	default:+22->1104, 0:+58->1140, 1:+-524->558
      //   1104: return
      //   1105: astore_1
      //   1106: aload_1
      //   1107: athrow
      //   1108: iconst_0
      //   1109: istore_2
      //   1110: goto -29 -> 1081
      //   1113: getstatic 25	o/Lx$If:ʻॱ	I
      //   1116: bipush 123
      //   1118: iadd
      //   1119: istore_2
      //   1120: iload_2
      //   1121: sipush 128
      //   1124: irem
      //   1125: putstatic 23	o/Lx$If:ॱˎ	I
      //   1128: iload_2
      //   1129: iconst_2
      //   1130: irem
      //   1131: ifeq +6 -> 1137
      //   1134: goto -1053 -> 81
      //   1137: goto -1131 -> 6
      //   1140: new 162	java/lang/NullPointerException
      //   1143: dup
      //   1144: invokespecial 164	java/lang/NullPointerException:<init>	()V
      //   1147: athrow
      // Local variable table:
      //   start	length	slot	name	signature
      //   0	1148	0	this	If
      //   0	1148	1	paramView	View
      //   551	580	2	i	int
      //   35	1040	3	localObject	Object
      // Exception table:
      //   from	to	target	type
      //   41	46	3	java/lang/Exception
      //   6	36	1105	java/lang/Exception
      //   36	41	1105	java/lang/Exception
      //   41	46	1105	java/lang/Exception
      //   46	51	1105	java/lang/Exception
    }
  }
}
