package o;

import android.content.Context;
import android.content.res.Resources;
import android.util.AttributeSet;
import android.view.View.OnClickListener;
import java.io.UnsupportedEncodingException;
import java.util.Arrays;

public final class LX
  extends au<LK>
  implements View.OnClickListener
{
  private static int ʻ;
  private static boolean ʼ;
  private static int ʽ;
  private static byte ˊ;
  private static char[] ˏ;
  private static int ॱ;
  private static boolean ॱॱ;
  private boolean ˎ;
  
  static
  {
    break label69;
    throw new NullPointerException();
    label37:
    for (int i = 0;; i = 1) {
      switch (i)
      {
      case 0: 
      default: 
        return;
      }
    }
    for (;;)
    {
      i = ʽ + 113;
      ʻ = i % 128;
      if (i % 2 != 0) {
        break;
      }
      break label37;
      label69:
      ʻ = 0;
      ʽ = 1;
      ॱ();
      ˊ = -102;
    }
  }
  
  public LX(Context paramContext)
  {
    this(paramContext, null);
  }
  
  public LX(Context paramContext, AttributeSet paramAttributeSet)
  {
    this(paramContext, paramAttributeSet, 0);
  }
  
  public LX(Context paramContext, AttributeSet paramAttributeSet, int paramInt)
  {
    super(paramContext, paramAttributeSet, paramInt);
  }
  
  private String ˋ(String paramString)
  {
    break label320;
    byte[] arrayOfByte;
    int j;
    int i;
    try
    {
      for (;;)
      {
        j = arrayOfByte.length;
        if (i < j) {
          break label314;
        }
        break;
        i = 0;
      }
      label23:
      label103:
      for (;;)
      {
        paramString[i] = ((byte)(arrayOfByte[(arrayOfByte.length - i - 1)] ^ ˊ));
        i += 1;
        break;
        j = 69;
        break label106;
        paramString = new String(paramString, ˎ(new byte[] { -83, -84, -88, -78, -79 }, null, null, 127).intern());
        return paramString;
      }
      label106:
      switch (j)
      {
      }
    }
    catch (UnsupportedEncodingException paramString)
    {
      throw new RuntimeException(paramString);
    }
    for (;;)
    {
      switch (i)
      {
      default: 
        break;
      case 3: 
        label145:
        label314:
        label320:
        for (;;)
        {
          i = ʻ + 15;
          ʽ = i % 128;
          if (i % 2 == 0) {
            break label406;
          }
          i = 3;
          break label145;
          j = ʻ + 57;
          ʽ = j % 128;
          if (j % 2 == 0) {
            break label103;
          }
          break label23;
          arrayOfByte = paramString.getBytes(ˎ(new byte[] { -80, -84, -81, -82, -83, -83, -84, -85, -111, -86 }, null, null, 127).intern());
          paramString = new byte[arrayOfByte.length];
          break;
          j = 90;
          break label106;
        }
      }
      arrayOfByte = paramString.getBytes(ˎ(new byte[] { -80, -84, -81, -82, -83, -83, -84, -85, -111, -86 }, null, null, 95).intern());
      paramString = new byte[arrayOfByte.length];
      break;
      label406:
      i = 33;
    }
  }
  
  private final void ˋ(FF paramFF)
  {
    break label1621;
    int i = 56;
    break label1104;
    label9:
    i = ʽ + 35;
    ʻ = i % 128;
    if (i % 2 == 0)
    {
      break label1184;
      break label44;
      label39:
      i = 5;
      break label1104;
    }
    label44:
    int j;
    label369:
    label372:
    label430:
    String str1;
    String str2;
    for (;;)
    {
      vq.ˋ(paramFF, ˎ(new byte[] { -87, -98, -98, -98, -98, -98, -98, -98, -98, -98, -98, -98, -98, -90, -115, -102, -127, -110, -116, -88, -107, -114, -115, -89, -124, -106, -123, -98, -98, -98, -98, -98, -98, -98, -98, -98, -98, -98, -98, -98, -98, -98, -98, -90, -91, -98, -124, -114, -92, -93 }, null, null, 127).intern());
      break label1491;
      if (j > 0) {
        break label1624;
      }
      break label1141;
      break label430;
      paramFF = vw.ˊ;
      paramFF = getContext().getString(Lt.If.offer_expire_days_prefix);
      if (paramFF.startsWith(ˎ(new byte[] { -118, -119, -120, -121 }, null, null, 127).intern())) {
        break label1605;
      }
      vq.ˋ(paramFF, ˎ(new byte[] { -100, -113, -125, -105, -114, -110, -103, -104, -107, -101, -102, -123, -104, -114, -110, -125, -103, -113, -114, -104, -110, -114, -105, -105, -116, -106, -125, -110, -115, -107, -112, -108, -109, -122, -124, -125, -110, -115, -111, -115, -114, -122, -112, -115, -113, -114, -115, -124, -116, -117 }, null, null, 127).intern());
      Object[] arrayOfObject = new Object[1];
      arrayOfObject[0] = ("" + (String)localObject + ˎ(new byte[] { -98, -99 }, null, null, 127).intern() + str1 + ˎ(new byte[] { -98, -99 }, null, null, 127).intern() + str2);
      i = arrayOfObject.length;
      paramFF = String.format(paramFF, Arrays.copyOf(arrayOfObject, 1));
      vq.ˋ(paramFF, ˎ(new byte[] { -100, -107, -122, -110, -102, -94, -98, -99, -115, -102, -127, -110, -116, -105, -109, -115, -102, -127, -110, -116, -105, -112, -122, -124, -125, -110, -115, -111, -112, -122, -124, -102, -95, -112, -102, -96, -102, -97 }, null, null, 127).intern());
      break label1491;
      break label1184;
      label1095:
      label1101:
      for (;;)
      {
        paramFF = (FF)localObject;
        break;
      }
      switch (i)
      {
      case 56: 
      default: 
        label1104:
        break label1157;
        paramFF = str2;
      }
    }
    label1141:
    i = 15;
    break label1568;
    for (;;)
    {
      if (i > 0) {
        break label39;
      }
      break;
      label1157:
      i = ʽ + 27;
      ʻ = i % 128;
      if (i % 2 != 0) {
        break label1101;
      }
      break label1095;
      label1184:
      long l = paramFF.ʼ() - System.currentTimeMillis();
      i = (int)(l / 86400000L);
      paramFF = getContext();
      vq.ˋ(paramFF, ˎ(new byte[] { -115, -113, -114, -115, -124, -116, -117 }, null, null, 127).intern());
      localObject = paramFF.getResources().getQuantityString(Lt.if.calendar_days, i, new Object[] { Integer.valueOf(i) });
      j = (int)(l % 86400000L / 3600000L);
      paramFF = getContext();
      vq.ˋ(paramFF, ˎ(new byte[] { -115, -113, -114, -115, -124, -116, -117 }, null, null, 127).intern());
      str1 = paramFF.getResources().getQuantityString(Lt.if.calendar_hours, j, new Object[] { Integer.valueOf(j) });
      int k = (int)(l % 3600000L / 60000L);
      paramFF = getContext();
      vq.ˋ(paramFF, ˎ(new byte[] { -115, -113, -114, -115, -124, -116, -117 }, null, null, 127).intern());
      str2 = paramFF.getResources().getQuantityString(Lt.if.calendar_minutes, k, new Object[] { Integer.valueOf(k) });
      if (this.ˎ) {
        break label372;
      }
    }
    label1491:
    Object localObject = this.ˋ;
    vq.ˋ(localObject, ˎ(new byte[] { -122, -124, -125, -123, -124, -125, -126, -127 }, null, null, 127).intern());
    ((LK)localObject).ˎ(paramFF);
    return;
    for (;;)
    {
      switch (i)
      {
      case 15: 
      default: 
        break;
      case 13: 
        label1568:
        paramFF = str1;
        break label44;
        label1605:
        paramFF = ˋ(paramFF.substring(4)).intern();
        break label369;
        label1621:
        break label9;
        label1624:
        i = 13;
      }
    }
  }
  
  private static String ˎ(byte[] paramArrayOfByte, int[] paramArrayOfInt, char[] paramArrayOfChar, int paramInt)
  {
    break label18;
    int j = paramArrayOfInt.length;
    paramArrayOfByte = new char[j];
    int i = 0;
    break label71;
    label18:
    break label350;
    i = 0;
    break label380;
    char[] arrayOfChar;
    int m;
    int k;
    if (i >= j) {
      for (;;)
      {
        paramArrayOfByte[i] = ((char)(arrayOfChar[(paramArrayOfChar[(m - 1 - i)] - paramInt)] - k));
        i += 1;
        break;
        label71:
        break label461;
        j = 44;
        break label425;
        for (;;)
        {
          switch (i)
          {
          default: 
            break label281;
            label107:
            return new String(paramArrayOfByte);
            m = ʻ + 39;
            ʽ = m % 128;
            if (m % 2 == 0) {
              break label229;
            }
            break label422;
            label146:
            i = 0;
          }
        }
        j = 20;
        break label425;
        try
        {
          j = ʻ + 125;
          try
          {
            ʽ = j % 128;
            if (j % 2 == 0) {
              break label256;
            }
          }
          catch (Exception paramArrayOfByte)
          {
            label192:
            throw paramArrayOfByte;
          }
        }
        catch (Exception paramArrayOfByte)
        {
          label229:
          label232:
          label256:
          throw paramArrayOfByte;
        }
      }
    }
    label275:
    label281:
    label350:
    label380:
    label422:
    label425:
    label455:
    label461:
    while (i < j)
    {
      for (;;)
      {
        paramArrayOfByte[i] = ((char)(arrayOfChar[(paramArrayOfInt[(j - 1 - i)] - paramInt)] - k));
        i += 1;
        continue;
        break label422;
        m = paramArrayOfChar.length;
        paramArrayOfByte = new char[m];
        i = 0;
        continue;
        return new String(paramArrayOfInt);
        break;
        if (i >= m)
        {
          continue;
          i = 1;
        }
      }
      if (ॱॱ) {
        break;
      }
      break label455;
      for (;;)
      {
        arrayOfChar = ˏ;
        k = ॱ;
        boolean bool = ʼ;
        if (bool) {
          break label275;
        }
        break label146;
        paramArrayOfInt[i] = ((char)(arrayOfChar[(paramArrayOfByte[(j - 1 - i)] + paramInt)] - k));
        i += 1;
        break;
        i = ʻ + 109;
        ʽ = i % 128;
        if (i % 2 == 0) {
          break label192;
        }
      }
      for (;;)
      {
        switch (i)
        {
        }
        break label232;
        j = paramArrayOfByte.length;
        paramArrayOfInt = new char[j];
        i = 0;
        break;
        break label461;
        switch (j)
        {
        }
        break label107;
        i = 1;
      }
    }
    return new String(paramArrayOfByte);
  }
  
  static void ॱ()
  {
    ʼ = true;
    ॱॱ = true;
    ˏ = new char[] { 166, 123, 162, 167, 157, 160, 62, 83, 68, 69, 156, 168, 173, 158, 177, 103, 140, 171, 97, 139, 172, 8287, 159, 152, 169, 154, 178, 98, 101, 89, 163, 175, 165, 99, 176, 161, 180, 67, 174, 127, 182, 130, 136, 102, 113, 110, 114, 106, 142, 141 };
    ॱ = 57;
  }
  
  /* Error */
  public void onClick(final android.view.View paramView)
  {
    // Byte code:
    //   0: goto +84 -> 84
    //   3: goto +56 -> 59
    //   6: goto +252 -> 258
    //   9: iconst_1
    //   10: istore_2
    //   11: goto +21 -> 32
    //   14: iconst_0
    //   15: istore_2
    //   16: goto +208 -> 224
    //   19: iconst_1
    //   20: istore_2
    //   21: goto +203 -> 224
    //   24: iconst_0
    //   25: istore_2
    //   26: goto +6 -> 32
    //   29: goto +226 -> 255
    //   32: iload_2
    //   33: tableswitch	default:+23->56, 0:+-30->3, 1:+164->197
    //   56: goto +141 -> 197
    //   59: getstatic 30	o/LX:ʽ	I
    //   62: bipush 85
    //   64: iadd
    //   65: istore_2
    //   66: iload_2
    //   67: sipush 128
    //   70: irem
    //   71: putstatic 32	o/LX:ʻ	I
    //   74: iload_2
    //   75: iconst_2
    //   76: irem
    //   77: ifeq +6 -> 83
    //   80: goto +171 -> 251
    //   83: return
    //   84: goto +345 -> 429
    //   87: aload 4
    //   89: iload_3
    //   90: invokevirtual 303	o/LK:ˏ	(Z)V
    //   93: goto +20 -> 113
    //   96: astore_1
    //   97: aload_1
    //   98: invokevirtual 309	java/lang/Throwable:getCause	()Ljava/lang/Throwable;
    //   101: astore 4
    //   103: aload 4
    //   105: ifnull +6 -> 111
    //   108: aload 4
    //   110: athrow
    //   111: aload_1
    //   112: athrow
    //   113: iconst_4
    //   114: sipush 135
    //   117: ldc_w 310
    //   120: invokestatic 315	o/O:ˋ	(IIC)Ljava/lang/Object;
    //   123: checkcast 317	java/lang/Class
    //   126: ldc_w 318
    //   129: aconst_null
    //   130: invokevirtual 322	java/lang/Class:getMethod	(Ljava/lang/String;[Ljava/lang/Class;)Ljava/lang/reflect/Method;
    //   133: aconst_null
    //   134: aconst_null
    //   135: invokevirtual 328	java/lang/reflect/Method:invoke	(Ljava/lang/Object;[Ljava/lang/Object;)Ljava/lang/Object;
    //   138: checkcast 330	o/It
    //   141: astore 4
    //   143: aload 4
    //   145: aload_1
    //   146: invokevirtual 332	o/FF:ˎ	()Ljava/lang/String;
    //   149: new 334	o/FJ
    //   152: dup
    //   153: aconst_null
    //   154: getstatic 339	o/Gv:ˊ	Lo/Gv$If;
    //   157: invokevirtual 344	o/Gv$If:ˎ	()Lo/Gv;
    //   160: invokevirtual 347	o/Gv:ˏॱ	()Ljava/lang/String;
    //   163: iconst_1
    //   164: aconst_null
    //   165: invokespecial 350	o/FJ:<init>	(Ljava/lang/String;Ljava/lang/String;ILo/vn;)V
    //   168: invokeinterface 353 3 0
    //   173: new 9	o/LX$ˊ
    //   176: dup
    //   177: aload_0
    //   178: aload_1
    //   179: aload_0
    //   180: invokevirtual 125	o/LX:getContext	()Landroid/content/Context;
    //   183: invokespecial 356	o/LX$ˊ:<init>	(Lo/LX;Lo/FF;Landroid/content/Context;)V
    //   186: checkcast 358	o/Cx
    //   189: invokeinterface 363 2 0
    //   194: goto +338 -> 532
    //   197: getstatic 32	o/LX:ʻ	I
    //   200: bipush 31
    //   202: iadd
    //   203: istore_2
    //   204: iload_2
    //   205: sipush 128
    //   208: irem
    //   209: putstatic 30	o/LX:ʽ	I
    //   212: iload_2
    //   213: iconst_2
    //   214: irem
    //   215: ifne +6 -> 221
    //   218: goto -212 -> 6
    //   221: goto +37 -> 258
    //   224: iload_2
    //   225: tableswitch	default:+23->248, 0:+194->419, 1:+199->424
    //   248: goto +171 -> 419
    //   251: return
    //   252: astore_1
    //   253: aload_1
    //   254: athrow
    //   255: goto -252 -> 3
    //   258: aload_0
    //   259: getfield 98	o/LX:ˋ	Landroid/databinding/ViewDataBinding;
    //   262: astore 4
    //   264: aload 4
    //   266: bipush 8
    //   268: newarray byte
    //   270: dup
    //   271: iconst_0
    //   272: ldc -102
    //   274: bastore
    //   275: dup
    //   276: iconst_1
    //   277: ldc 42
    //   279: bastore
    //   280: dup
    //   281: iconst_2
    //   282: ldc -110
    //   284: bastore
    //   285: dup
    //   286: iconst_3
    //   287: ldc 111
    //   289: bastore
    //   290: dup
    //   291: iconst_4
    //   292: ldc 42
    //   294: bastore
    //   295: dup
    //   296: iconst_5
    //   297: ldc -110
    //   299: bastore
    //   300: dup
    //   301: bipush 6
    //   303: ldc -27
    //   305: bastore
    //   306: dup
    //   307: bipush 7
    //   309: ldc 106
    //   311: bastore
    //   312: aconst_null
    //   313: aconst_null
    //   314: bipush 127
    //   316: invokestatic 47	o/LX:ˎ	([B[I[CI)Ljava/lang/String;
    //   319: invokevirtual 53	java/lang/String:intern	()Ljava/lang/String;
    //   322: invokestatic 116	o/vq:ˋ	(Ljava/lang/Object;Ljava/lang/String;)V
    //   325: aload 4
    //   327: checkcast 100	o/LK
    //   330: astore 4
    //   332: aload_0
    //   333: getfield 98	o/LX:ˋ	Landroid/databinding/ViewDataBinding;
    //   336: astore 5
    //   338: aload 5
    //   340: bipush 8
    //   342: newarray byte
    //   344: dup
    //   345: iconst_0
    //   346: ldc -102
    //   348: bastore
    //   349: dup
    //   350: iconst_1
    //   351: ldc 42
    //   353: bastore
    //   354: dup
    //   355: iconst_2
    //   356: ldc -110
    //   358: bastore
    //   359: dup
    //   360: iconst_3
    //   361: ldc 111
    //   363: bastore
    //   364: dup
    //   365: iconst_4
    //   366: ldc 42
    //   368: bastore
    //   369: dup
    //   370: iconst_5
    //   371: ldc -110
    //   373: bastore
    //   374: dup
    //   375: bipush 6
    //   377: ldc -27
    //   379: bastore
    //   380: dup
    //   381: bipush 7
    //   383: ldc 106
    //   385: bastore
    //   386: aconst_null
    //   387: aconst_null
    //   388: bipush 127
    //   390: invokestatic 47	o/LX:ˎ	([B[I[CI)Ljava/lang/String;
    //   393: invokevirtual 53	java/lang/String:intern	()Ljava/lang/String;
    //   396: invokestatic 116	o/vq:ˋ	(Ljava/lang/Object;Ljava/lang/String;)V
    //   399: aload 5
    //   401: checkcast 100	o/LK
    //   404: invokevirtual 366	o/LK:ˏॱ	()Z
    //   407: ifne +6 -> 413
    //   410: goto -396 -> 14
    //   413: goto -394 -> 19
    //   416: astore_1
    //   417: aload_1
    //   418: athrow
    //   419: iconst_1
    //   420: istore_3
    //   421: goto -334 -> 87
    //   424: iconst_0
    //   425: istore_3
    //   426: goto -339 -> 87
    //   429: aload_0
    //   430: getfield 98	o/LX:ˋ	Landroid/databinding/ViewDataBinding;
    //   433: astore_1
    //   434: aload_1
    //   435: checkcast 100	o/LK
    //   438: astore_1
    //   439: aload_1
    //   440: getfield 369	o/LK:ॱ	Landroid/widget/ImageView;
    //   443: astore_1
    //   444: aload_1
    //   445: aconst_null
    //   446: invokevirtual 375	android/widget/ImageView:setOnClickListener	(Landroid/view/View$OnClickListener;)V
    //   449: aload_0
    //   450: getfield 98	o/LX:ˋ	Landroid/databinding/ViewDataBinding;
    //   453: astore_1
    //   454: aload_1
    //   455: bipush 8
    //   457: newarray byte
    //   459: dup
    //   460: iconst_0
    //   461: ldc -102
    //   463: bastore
    //   464: dup
    //   465: iconst_1
    //   466: ldc 42
    //   468: bastore
    //   469: dup
    //   470: iconst_2
    //   471: ldc -110
    //   473: bastore
    //   474: dup
    //   475: iconst_3
    //   476: ldc 111
    //   478: bastore
    //   479: dup
    //   480: iconst_4
    //   481: ldc 42
    //   483: bastore
    //   484: dup
    //   485: iconst_5
    //   486: ldc -110
    //   488: bastore
    //   489: dup
    //   490: bipush 6
    //   492: ldc -27
    //   494: bastore
    //   495: dup
    //   496: bipush 7
    //   498: ldc 106
    //   500: bastore
    //   501: aconst_null
    //   502: aconst_null
    //   503: bipush 127
    //   505: invokestatic 47	o/LX:ˎ	([B[I[CI)Ljava/lang/String;
    //   508: invokevirtual 53	java/lang/String:intern	()Ljava/lang/String;
    //   511: invokestatic 116	o/vq:ˋ	(Ljava/lang/Object;Ljava/lang/String;)V
    //   514: aload_1
    //   515: checkcast 100	o/LK
    //   518: invokevirtual 379	o/LK:ॱˊ	()Lo/FF;
    //   521: astore_1
    //   522: aload_1
    //   523: ifnull +6 -> 529
    //   526: goto -517 -> 9
    //   529: goto -505 -> 24
    //   532: getstatic 32	o/LX:ʻ	I
    //   535: bipush 59
    //   537: iadd
    //   538: istore_2
    //   539: iload_2
    //   540: sipush 128
    //   543: irem
    //   544: putstatic 30	o/LX:ʽ	I
    //   547: iload_2
    //   548: iconst_2
    //   549: irem
    //   550: ifne +6 -> 556
    //   553: goto -524 -> 29
    //   556: goto -301 -> 255
    // Local variable table:
    //   start	length	slot	name	signature
    //   0	559	0	this	LX
    //   0	559	1	paramView	android.view.View
    //   10	540	2	i	int
    //   89	337	3	bool	boolean
    //   87	244	4	localObject	Object
    //   336	64	5	localViewDataBinding	android.databinding.ViewDataBinding
    // Exception table:
    //   from	to	target	type
    //   113	143	96	finally
    //   434	439	252	java/lang/Exception
    //   439	444	252	java/lang/Exception
    //   444	449	252	java/lang/Exception
    //   449	522	252	java/lang/Exception
    //   429	434	416	java/lang/Exception
  }
  
  /* Error */
  public final void setOffer(FF paramFF)
  {
    // Byte code:
    //   0: goto +177 -> 177
    //   3: iload_2
    //   4: tableswitch	default:+24->28, 0:+59->63, 1:+461->465
    //   28: goto +35 -> 63
    //   31: goto +221 -> 252
    //   34: goto +328 -> 362
    //   37: iload_2
    //   38: tableswitch	default:+22->60, 0:+490->528, 1:+397->435
    //   60: goto +468 -> 528
    //   63: return
    //   64: aload_0
    //   65: getfield 98	o/LX:ˋ	Landroid/databinding/ViewDataBinding;
    //   68: astore 4
    //   70: aload 4
    //   72: aload_3
    //   73: invokestatic 116	o/vq:ˋ	(Ljava/lang/Object;Ljava/lang/String;)V
    //   76: aload 4
    //   78: checkcast 100	o/LK
    //   81: aload_1
    //   82: invokevirtual 382	o/LK:ˋ	(Lo/FF;)V
    //   85: aload_0
    //   86: getfield 98	o/LX:ˋ	Landroid/databinding/ViewDataBinding;
    //   89: astore 4
    //   91: aload 4
    //   93: aload_3
    //   94: invokestatic 116	o/vq:ˋ	(Ljava/lang/Object;Ljava/lang/String;)V
    //   97: aload 4
    //   99: checkcast 100	o/LK
    //   102: aload_1
    //   103: invokevirtual 384	o/FF:ʽ	()Z
    //   106: invokevirtual 386	o/LK:ˊ	(Z)V
    //   109: aload_0
    //   110: getfield 98	o/LX:ˋ	Landroid/databinding/ViewDataBinding;
    //   113: astore 4
    //   115: aload 4
    //   117: aload_3
    //   118: invokestatic 116	o/vq:ˋ	(Ljava/lang/Object;Ljava/lang/String;)V
    //   121: aload 4
    //   123: checkcast 100	o/LK
    //   126: aload_1
    //   127: invokevirtual 388	o/FF:ॱˊ	()Z
    //   130: invokevirtual 390	o/LK:ˎ	(Z)V
    //   133: aload_1
    //   134: invokevirtual 388	o/FF:ॱˊ	()Z
    //   137: ifeq +6 -> 143
    //   140: goto +326 -> 466
    //   143: goto +6 -> 149
    //   146: goto +106 -> 252
    //   149: aload_0
    //   150: getfield 98	o/LX:ˋ	Landroid/databinding/ViewDataBinding;
    //   153: checkcast 100	o/LK
    //   156: getfield 369	o/LK:ॱ	Landroid/widget/ImageView;
    //   159: aload_0
    //   160: checkcast 7	android/view/View$OnClickListener
    //   163: invokevirtual 375	android/widget/ImageView:setOnClickListener	(Landroid/view/View$OnClickListener;)V
    //   166: goto -20 -> 146
    //   169: astore_1
    //   170: aload_1
    //   171: athrow
    //   172: iconst_0
    //   173: istore_2
    //   174: goto -137 -> 37
    //   177: goto +193 -> 370
    //   180: aload_0
    //   181: getfield 98	o/LX:ˋ	Landroid/databinding/ViewDataBinding;
    //   184: astore_1
    //   185: aload_1
    //   186: aload_3
    //   187: invokestatic 116	o/vq:ˋ	(Ljava/lang/Object;Ljava/lang/String;)V
    //   190: aload_1
    //   191: checkcast 100	o/LK
    //   194: astore_1
    //   195: aload_0
    //   196: invokevirtual 125	o/LX:getContext	()Landroid/content/Context;
    //   199: getstatic 393	o/Lt$If:offer_expired	I
    //   202: invokevirtual 136	android/content/Context:getString	(I)Ljava/lang/String;
    //   205: astore_3
    //   206: aload_3
    //   207: iconst_4
    //   208: newarray byte
    //   210: dup
    //   211: iconst_0
    //   212: ldc -119
    //   214: bastore
    //   215: dup
    //   216: iconst_1
    //   217: ldc -118
    //   219: bastore
    //   220: dup
    //   221: iconst_2
    //   222: ldc -117
    //   224: bastore
    //   225: dup
    //   226: iconst_3
    //   227: ldc -116
    //   229: bastore
    //   230: aconst_null
    //   231: aconst_null
    //   232: bipush 127
    //   234: invokestatic 47	o/LX:ˎ	([B[I[CI)Ljava/lang/String;
    //   237: invokevirtual 53	java/lang/String:intern	()Ljava/lang/String;
    //   240: invokevirtual 144	java/lang/String:startsWith	(Ljava/lang/String;)Z
    //   243: ifeq +6 -> 249
    //   246: goto +195 -> 441
    //   249: goto +113 -> 362
    //   252: aload_0
    //   253: getfield 98	o/LX:ˋ	Landroid/databinding/ViewDataBinding;
    //   256: astore 4
    //   258: aload 4
    //   260: aload_3
    //   261: invokestatic 116	o/vq:ˋ	(Ljava/lang/Object;Ljava/lang/String;)V
    //   264: aload 4
    //   266: checkcast 100	o/LK
    //   269: aload_1
    //   270: invokevirtual 396	o/FF:ˊॱ	()Z
    //   273: invokevirtual 303	o/LK:ˏ	(Z)V
    //   276: invokestatic 193	java/lang/System:currentTimeMillis	()J
    //   279: aload_1
    //   280: invokevirtual 188	o/FF:ʼ	()J
    //   283: lcmp
    //   284: ifle +6 -> 290
    //   287: goto -115 -> 172
    //   290: goto +201 -> 491
    //   293: aload_0
    //   294: getfield 98	o/LX:ˋ	Landroid/databinding/ViewDataBinding;
    //   297: astore_1
    //   298: aload_1
    //   299: aload_3
    //   300: invokestatic 116	o/vq:ˋ	(Ljava/lang/Object;Ljava/lang/String;)V
    //   303: aload_1
    //   304: checkcast 100	o/LK
    //   307: astore_1
    //   308: aload_0
    //   309: invokevirtual 125	o/LX:getContext	()Landroid/content/Context;
    //   312: getstatic 393	o/Lt$If:offer_expired	I
    //   315: invokevirtual 136	android/content/Context:getString	(I)Ljava/lang/String;
    //   318: astore_3
    //   319: aload_3
    //   320: iconst_4
    //   321: newarray byte
    //   323: dup
    //   324: iconst_0
    //   325: ldc -119
    //   327: bastore
    //   328: dup
    //   329: iconst_1
    //   330: ldc -118
    //   332: bastore
    //   333: dup
    //   334: iconst_2
    //   335: ldc -117
    //   337: bastore
    //   338: dup
    //   339: iconst_3
    //   340: ldc -116
    //   342: bastore
    //   343: aconst_null
    //   344: aconst_null
    //   345: bipush 37
    //   347: invokestatic 47	o/LX:ˎ	([B[I[CI)Ljava/lang/String;
    //   350: invokevirtual 53	java/lang/String:intern	()Ljava/lang/String;
    //   353: invokevirtual 144	java/lang/String:startsWith	(Ljava/lang/String;)Z
    //   356: ifeq +6 -> 362
    //   359: goto +82 -> 441
    //   362: aload_1
    //   363: aload_3
    //   364: invokevirtual 232	o/LK:ˎ	(Ljava/lang/String;)V
    //   367: goto +134 -> 501
    //   370: bipush 8
    //   372: newarray byte
    //   374: dup
    //   375: iconst_0
    //   376: ldc -102
    //   378: bastore
    //   379: dup
    //   380: iconst_1
    //   381: ldc 42
    //   383: bastore
    //   384: dup
    //   385: iconst_2
    //   386: ldc -110
    //   388: bastore
    //   389: dup
    //   390: iconst_3
    //   391: ldc 111
    //   393: bastore
    //   394: dup
    //   395: iconst_4
    //   396: ldc 42
    //   398: bastore
    //   399: dup
    //   400: iconst_5
    //   401: ldc -110
    //   403: bastore
    //   404: dup
    //   405: bipush 6
    //   407: ldc -27
    //   409: bastore
    //   410: dup
    //   411: bipush 7
    //   413: ldc 106
    //   415: bastore
    //   416: aconst_null
    //   417: aconst_null
    //   418: bipush 127
    //   420: invokestatic 47	o/LX:ˎ	([B[I[CI)Ljava/lang/String;
    //   423: invokevirtual 53	java/lang/String:intern	()Ljava/lang/String;
    //   426: astore_3
    //   427: aload_1
    //   428: ifnull +6 -> 434
    //   431: goto -367 -> 64
    //   434: return
    //   435: aload_0
    //   436: aload_1
    //   437: invokespecial 397	o/LX:ˋ	(Lo/FF;)V
    //   440: return
    //   441: aload_0
    //   442: aload_3
    //   443: iconst_4
    //   444: invokevirtual 235	java/lang/String:substring	(I)Ljava/lang/String;
    //   447: invokespecial 237	o/LX:ˋ	(Ljava/lang/String;)Ljava/lang/String;
    //   450: invokevirtual 53	java/lang/String:intern	()Ljava/lang/String;
    //   453: astore_3
    //   454: goto -420 -> 34
    //   457: iconst_0
    //   458: istore_2
    //   459: goto -456 -> 3
    //   462: astore_1
    //   463: aload_1
    //   464: athrow
    //   465: return
    //   466: aload_0
    //   467: getfield 98	o/LX:ˋ	Landroid/databinding/ViewDataBinding;
    //   470: astore 4
    //   472: aload 4
    //   474: checkcast 100	o/LK
    //   477: astore 4
    //   479: aload 4
    //   481: getfield 369	o/LK:ॱ	Landroid/widget/ImageView;
    //   484: aconst_null
    //   485: invokevirtual 375	android/widget/ImageView:setOnClickListener	(Landroid/view/View$OnClickListener;)V
    //   488: goto -457 -> 31
    //   491: iconst_1
    //   492: istore_2
    //   493: goto -456 -> 37
    //   496: iconst_1
    //   497: istore_2
    //   498: goto -495 -> 3
    //   501: getstatic 30	o/LX:ʽ	I
    //   504: bipush 47
    //   506: iadd
    //   507: istore_2
    //   508: iload_2
    //   509: sipush 128
    //   512: irem
    //   513: putstatic 32	o/LX:ʻ	I
    //   516: iload_2
    //   517: iconst_2
    //   518: irem
    //   519: ifeq +6 -> 525
    //   522: goto -65 -> 457
    //   525: goto -29 -> 496
    //   528: getstatic 30	o/LX:ʽ	I
    //   531: istore_2
    //   532: iload_2
    //   533: bipush 69
    //   535: iadd
    //   536: istore_2
    //   537: iload_2
    //   538: sipush 128
    //   541: irem
    //   542: putstatic 32	o/LX:ʻ	I
    //   545: iload_2
    //   546: iconst_2
    //   547: irem
    //   548: ifeq +6 -> 554
    //   551: goto -258 -> 293
    //   554: goto -374 -> 180
    // Local variable table:
    //   start	length	slot	name	signature
    //   0	557	0	this	LX
    //   0	557	1	paramFF	FF
    //   3	545	2	i	int
    //   72	382	3	str	String
    //   68	412	4	localObject	Object
    // Exception table:
    //   from	to	target	type
    //   528	532	169	java/lang/Exception
    //   537	545	169	java/lang/Exception
    //   466	472	462	java/lang/Exception
    //   472	479	462	java/lang/Exception
    //   479	488	462	java/lang/Exception
  }
  
  public final void setShowFullDate(boolean paramBoolean)
  {
    for (;;)
    {
      int i;
      try
      {
        i = ʻ;
        i += 49;
        try
        {
          ʽ = i % 128;
          if (i % 2 == 0) {
            break label71;
          }
          return;
        }
        catch (Exception localException1)
        {
          throw localException1;
        }
        this.ˎ = paramBoolean;
        continue;
        i = ʽ + 111;
      }
      catch (Exception localException2)
      {
        throw localException2;
      }
      ʻ = i % 128;
      if (i % 2 == 0)
      {
        continue;
        label71:
        return;
      }
    }
  }
  
  /* Error */
  public void ˊ()
  {
    // Byte code:
    //   0: goto +30 -> 30
    //   3: aload_0
    //   4: invokespecial 400	o/au:ˊ	()V
    //   7: goto +57 -> 64
    //   10: astore_2
    //   11: aload_2
    //   12: athrow
    //   13: iconst_1
    //   14: istore_1
    //   15: goto +18 -> 33
    //   18: aload_0
    //   19: invokespecial 400	o/au:ˊ	()V
    //   22: bipush 86
    //   24: iconst_0
    //   25: idiv
    //   26: istore_1
    //   27: goto +37 -> 64
    //   30: goto +57 -> 87
    //   33: iload_1
    //   34: tableswitch	default:+22->56, 0:+-31->3, 1:+-16->18
    //   56: goto -53 -> 3
    //   59: iconst_0
    //   60: istore_1
    //   61: goto -28 -> 33
    //   64: getstatic 30	o/LX:ʽ	I
    //   67: bipush 81
    //   69: iadd
    //   70: istore_1
    //   71: iload_1
    //   72: sipush 128
    //   75: irem
    //   76: putstatic 32	o/LX:ʻ	I
    //   79: iload_1
    //   80: iconst_2
    //   81: irem
    //   82: ifeq +4 -> 86
    //   85: return
    //   86: return
    //   87: getstatic 32	o/LX:ʻ	I
    //   90: istore_1
    //   91: iload_1
    //   92: bipush 77
    //   94: iadd
    //   95: istore_1
    //   96: iload_1
    //   97: sipush 128
    //   100: irem
    //   101: putstatic 30	o/LX:ʽ	I
    //   104: iload_1
    //   105: iconst_2
    //   106: irem
    //   107: ifne +6 -> 113
    //   110: goto -97 -> 13
    //   113: goto -54 -> 59
    // Local variable table:
    //   start	length	slot	name	signature
    //   0	116	0	this	LX
    //   14	93	1	i	int
    //   10	2	2	localException	Exception
    // Exception table:
    //   from	to	target	type
    //   87	91	10	java/lang/Exception
    //   96	104	10	java/lang/Exception
  }
  
  public int ˎ()
  {
    switch (i)
    {
    default: 
      break;
    case 91: 
      for (;;)
      {
        i = ʽ + 31;
        ʻ = i % 128;
        if (i % 2 == 0)
        {
          break label72;
          return Lt.ˋ.view_offer_item;
        }
        else
        {
          i = 17;
          break;
        }
        label72:
        i = 91;
        break;
      }
    }
    int i = Lt.ˋ.view_offer_item;
    throw new NullPointerException();
  }
  
  public static final class ˊ
    extends Ik<Void>
  {
    private static int ʻ = 1;
    private static long ˋ = 6672550157919235983L;
    private static int ˏ = 0;
    private static char[] ॱ = { -10346, 30774, -30580, -9928, 27043, -17831, -13617, 7029 };
    
    ˊ(FF paramFF, Context paramContext)
    {
      super();
    }
    
    /* Error */
    private static String ˋ(int paramInt1, char paramChar, int paramInt2)
    {
      // Byte code:
      //   0: goto +55 -> 55
      //   3: getstatic 41	o/LX$ˊ:ॱ	[C
      //   6: iload 5
      //   8: iload_0
      //   9: iadd
      //   10: caload
      //   11: istore_1
      //   12: iload_1
      //   13: i2l
      //   14: lstore 6
      //   16: iload_0
      //   17: i2l
      //   18: lstore 8
      //   20: getstatic 31	o/LX$ˊ:ˋ	J
      //   23: lstore 10
      //   25: aload 12
      //   27: iload_0
      //   28: lload 6
      //   30: lload 8
      //   32: lload 10
      //   34: lmul
      //   35: lxor
      //   36: iload 4
      //   38: i2l
      //   39: lxor
      //   40: l2i
      //   41: i2c
      //   42: castore
      //   43: iload_0
      //   44: iconst_1
      //   45: iadd
      //   46: istore_0
      //   47: goto +69 -> 116
      //   50: astore 12
      //   52: aload 12
      //   54: athrow
      //   55: goto +164 -> 219
      //   58: getstatic 25	o/LX$ˊ:ˏ	I
      //   61: bipush 35
      //   63: iadd
      //   64: istore_1
      //   65: iload_1
      //   66: sipush 128
      //   69: irem
      //   70: putstatic 27	o/LX$ˊ:ʻ	I
      //   73: iload_1
      //   74: iconst_2
      //   75: irem
      //   76: ifne +6 -> 82
      //   79: goto +48 -> 127
      //   82: goto +81 -> 163
      //   85: aload 12
      //   87: iload_0
      //   88: getstatic 41	o/LX$ˊ:ॱ	[C
      //   91: iload 5
      //   93: iload_0
      //   94: imul
      //   95: caload
      //   96: i2l
      //   97: iload_0
      //   98: i2l
      //   99: getstatic 31	o/LX$ˊ:ˋ	J
      //   102: ldiv
      //   103: lrem
      //   104: iload 4
      //   106: i2l
      //   107: lor
      //   108: l2i
      //   109: i2c
      //   110: castore
      //   111: iload_0
      //   112: bipush 47
      //   114: iadd
      //   115: istore_0
      //   116: iload_0
      //   117: iload_2
      //   118: if_icmpge +6 -> 124
      //   121: goto +11 -> 132
      //   124: goto +132 -> 256
      //   127: iconst_1
      //   128: istore_1
      //   129: goto +8 -> 137
      //   132: iconst_0
      //   133: istore_1
      //   134: goto +57 -> 191
      //   137: iload_1
      //   138: tableswitch	default:+22->160, 0:+-135->3, 1:+-53->85
      //   160: goto -157 -> 3
      //   163: iconst_0
      //   164: istore_1
      //   165: goto -28 -> 137
      //   168: astore 12
      //   170: aload 12
      //   172: athrow
      //   173: iload_2
      //   174: newarray char
      //   176: astore 12
      //   178: iconst_1
      //   179: istore_3
      //   180: iload_1
      //   181: istore 4
      //   183: iload_0
      //   184: istore 5
      //   186: iload_3
      //   187: istore_0
      //   188: goto -72 -> 116
      //   191: iload_1
      //   192: tableswitch	default:+24->216, 0:+-134->58, 1:+54->246
      //   216: goto +30 -> 246
      //   219: getstatic 27	o/LX$ˊ:ʻ	I
      //   222: bipush 43
      //   224: iadd
      //   225: istore_3
      //   226: iload_3
      //   227: sipush 128
      //   230: irem
      //   231: putstatic 25	o/LX$ˊ:ˏ	I
      //   234: iload_3
      //   235: iconst_2
      //   236: irem
      //   237: ifeq +6 -> 243
      //   240: goto -67 -> 173
      //   243: goto +18 -> 261
      //   246: new 58	java/lang/String
      //   249: dup
      //   250: aload 12
      //   252: invokespecial 61	java/lang/String:<init>	([C)V
      //   255: areturn
      //   256: iconst_1
      //   257: istore_1
      //   258: goto -67 -> 191
      //   261: iload_2
      //   262: newarray char
      //   264: astore 12
      //   266: iconst_0
      //   267: istore_3
      //   268: goto -88 -> 180
      // Local variable table:
      //   start	length	slot	name	signature
      //   0	271	0	paramInt1	int
      //   0	271	1	paramChar	char
      //   0	271	2	paramInt2	int
      //   179	89	3	i	int
      //   36	146	4	j	int
      //   6	179	5	k	int
      //   14	15	6	l1	long
      //   18	13	8	l2	long
      //   23	10	10	l3	long
      //   25	1	12	localObject	Object
      //   50	36	12	localException1	Exception
      //   168	3	12	localException2	Exception
      //   176	89	12	arrayOfChar	char[]
      // Exception table:
      //   from	to	target	type
      //   3	12	50	java/lang/Exception
      //   20	25	50	java/lang/Exception
      //   20	25	168	java/lang/Exception
    }
    
    /* Error */
    public void ˏ()
    {
      // Byte code:
      //   0: goto +113 -> 113
      //   3: new 63	java/lang/NullPointerException
      //   6: dup
      //   7: invokespecial 65	java/lang/NullPointerException:<init>	()V
      //   10: athrow
      //   11: astore_2
      //   12: aload_2
      //   13: athrow
      //   14: aload_0
      //   15: invokespecial 67	o/Ik:ˏ	()V
      //   18: aload_0
      //   19: getfield 46	o/LX$ˊ:ˊ	Lo/LX;
      //   22: astore_2
      //   23: aload_2
      //   24: invokestatic 70	o/LX:ˋ	(Lo/LX;)Lo/LK;
      //   27: astore_2
      //   28: aload_2
      //   29: iconst_0
      //   30: ldc 71
      //   32: bipush 8
      //   34: invokestatic 73	o/LX$ˊ:ˋ	(ICI)Ljava/lang/String;
      //   37: invokevirtual 77	java/lang/String:intern	()Ljava/lang/String;
      //   40: invokestatic 82	o/vq:ˋ	(Ljava/lang/Object;Ljava/lang/String;)V
      //   43: aload_2
      //   44: aload_0
      //   45: getfield 48	o/LX$ˊ:ˎ	Lo/FF;
      //   48: invokevirtual 88	o/FF:ˊॱ	()Z
      //   51: invokevirtual 93	o/LK:ˏ	(Z)V
      //   54: aload_0
      //   55: getfield 46	o/LX$ˊ:ˊ	Lo/LX;
      //   58: invokestatic 70	o/LX:ˋ	(Lo/LX;)Lo/LK;
      //   61: getfield 96	o/LK:ॱ	Landroid/widget/ImageView;
      //   64: aload_0
      //   65: getfield 46	o/LX$ˊ:ˊ	Lo/LX;
      //   68: checkcast 98	android/view/View$OnClickListener
      //   71: invokevirtual 104	android/widget/ImageView:setOnClickListener	(Landroid/view/View$OnClickListener;)V
      //   74: goto +42 -> 116
      //   77: iconst_1
      //   78: istore_1
      //   79: iload_1
      //   80: tableswitch	default:+24->104, 0:+-77->3, 1:+24->104
      //   104: return
      //   105: iconst_0
      //   106: istore_1
      //   107: goto -28 -> 79
      //   110: astore_2
      //   111: aload_2
      //   112: athrow
      //   113: goto +32 -> 145
      //   116: getstatic 27	o/LX$ˊ:ʻ	I
      //   119: istore_1
      //   120: iload_1
      //   121: bipush 99
      //   123: iadd
      //   124: istore_1
      //   125: iload_1
      //   126: sipush 128
      //   129: irem
      //   130: putstatic 25	o/LX$ˊ:ˏ	I
      //   133: iload_1
      //   134: iconst_2
      //   135: irem
      //   136: ifeq +6 -> 142
      //   139: goto -34 -> 105
      //   142: goto -65 -> 77
      //   145: getstatic 25	o/LX$ˊ:ˏ	I
      //   148: bipush 109
      //   150: iadd
      //   151: istore_1
      //   152: iload_1
      //   153: sipush 128
      //   156: irem
      //   157: putstatic 27	o/LX$ˊ:ʻ	I
      //   160: iload_1
      //   161: iconst_2
      //   162: irem
      //   163: ifne +6 -> 169
      //   166: goto -152 -> 14
      //   169: goto -155 -> 14
      // Local variable table:
      //   start	length	slot	name	signature
      //   0	172	0	this	ˊ
      //   78	85	1	i	int
      //   11	2	2	localException1	Exception
      //   22	22	2	localObject	Object
      //   110	2	2	localException2	Exception
      // Exception table:
      //   from	to	target	type
      //   18	23	11	java/lang/Exception
      //   23	28	11	java/lang/Exception
      //   28	74	11	java/lang/Exception
      //   116	120	11	java/lang/Exception
      //   125	133	11	java/lang/Exception
      //   23	28	110	java/lang/Exception
    }
    
    /* Error */
    protected void ॱ(Void paramVoid)
    {
      // Byte code:
      //   0: goto +119 -> 119
      //   3: aload_1
      //   4: iload_3
      //   5: invokevirtual 111	o/FF:ˏ	(Z)V
      //   8: aload_0
      //   9: getfield 46	o/LX$ˊ:ˊ	Lo/LX;
      //   12: invokestatic 70	o/LX:ˋ	(Lo/LX;)Lo/LK;
      //   15: astore_1
      //   16: aload_1
      //   17: iconst_0
      //   18: ldc 71
      //   20: bipush 8
      //   22: invokestatic 73	o/LX$ˊ:ˋ	(ICI)Ljava/lang/String;
      //   25: invokevirtual 77	java/lang/String:intern	()Ljava/lang/String;
      //   28: invokestatic 82	o/vq:ˋ	(Ljava/lang/Object;Ljava/lang/String;)V
      //   31: aload_1
      //   32: aload_0
      //   33: getfield 48	o/LX$ˊ:ˎ	Lo/FF;
      //   36: invokevirtual 114	o/LK:ˋ	(Lo/FF;)V
      //   39: invokestatic 119	o/zp:ॱ	()Lo/zp;
      //   42: new 121	o/LP
      //   45: dup
      //   46: aload_0
      //   47: getfield 48	o/LX$ˊ:ˎ	Lo/FF;
      //   50: invokespecial 123	o/LP:<init>	(Lo/FF;)V
      //   53: invokevirtual 125	o/zp:ˎ	(Ljava/lang/Object;)V
      //   56: goto +136 -> 192
      //   59: aload_0
      //   60: getfield 48	o/LX$ˊ:ˎ	Lo/FF;
      //   63: astore_1
      //   64: aload_0
      //   65: getfield 48	o/LX$ˊ:ˎ	Lo/FF;
      //   68: invokevirtual 88	o/FF:ˊॱ	()Z
      //   71: pop
      //   72: new 63	java/lang/NullPointerException
      //   75: dup
      //   76: invokespecial 65	java/lang/NullPointerException:<init>	()V
      //   79: athrow
      //   80: aload 4
      //   82: astore 5
      //   84: aload 4
      //   86: astore_1
      //   87: iload_2
      //   88: tableswitch	default:+24->112, 0:+132->220, 1:+192->280
      //   112: aload 4
      //   114: astore 5
      //   116: goto +104 -> 220
      //   119: getstatic 25	o/LX$ˊ:ˏ	I
      //   122: istore_2
      //   123: iload_2
      //   124: bipush 105
      //   126: iadd
      //   127: istore_2
      //   128: iload_2
      //   129: sipush 128
      //   132: irem
      //   133: putstatic 27	o/LX$ˊ:ʻ	I
      //   136: iload_2
      //   137: iconst_2
      //   138: irem
      //   139: ifne +6 -> 145
      //   142: goto +105 -> 247
      //   145: goto +171 -> 316
      //   148: astore_1
      //   149: aload_1
      //   150: athrow
      //   151: goto -148 -> 3
      //   154: getstatic 25	o/LX$ˊ:ˏ	I
      //   157: bipush 119
      //   159: iadd
      //   160: istore_2
      //   161: iload_2
      //   162: sipush 128
      //   165: irem
      //   166: putstatic 27	o/LX$ˊ:ʻ	I
      //   169: iload_2
      //   170: iconst_2
      //   171: irem
      //   172: ifne +6 -> 178
      //   175: goto +14 -> 189
      //   178: goto +74 -> 252
      //   181: iconst_1
      //   182: istore_2
      //   183: goto -103 -> 80
      //   186: astore_1
      //   187: aload_1
      //   188: athrow
      //   189: goto +63 -> 252
      //   192: getstatic 27	o/LX$ˊ:ʻ	I
      //   195: bipush 23
      //   197: iadd
      //   198: istore_2
      //   199: iload_2
      //   200: sipush 128
      //   203: irem
      //   204: putstatic 25	o/LX$ˊ:ˏ	I
      //   207: iload_2
      //   208: iconst_2
      //   209: irem
      //   210: ifeq +4 -> 214
      //   213: return
      //   214: return
      //   215: iconst_0
      //   216: istore_3
      //   217: goto -63 -> 154
      //   220: getstatic 27	o/LX$ˊ:ʻ	I
      //   223: bipush 67
      //   225: iadd
      //   226: istore_2
      //   227: iload_2
      //   228: sipush 128
      //   231: irem
      //   232: putstatic 25	o/LX$ˊ:ˏ	I
      //   235: iload_2
      //   236: iconst_2
      //   237: irem
      //   238: ifeq +6 -> 244
      //   241: goto -26 -> 215
      //   244: goto +67 -> 311
      //   247: iconst_0
      //   248: istore_2
      //   249: goto +36 -> 285
      //   252: aload 5
      //   254: astore_1
      //   255: goto -252 -> 3
      //   258: aload_0
      //   259: getfield 48	o/LX$ˊ:ˎ	Lo/FF;
      //   262: astore 4
      //   264: aload_0
      //   265: getfield 48	o/LX$ˊ:ˎ	Lo/FF;
      //   268: invokevirtual 88	o/FF:ˊॱ	()Z
      //   271: ifne +6 -> 277
      //   274: goto +47 -> 321
      //   277: goto -96 -> 181
      //   280: iconst_0
      //   281: istore_3
      //   282: goto -131 -> 151
      //   285: iload_2
      //   286: tableswitch	default:+22->308, 0:+-227->59, 1:+-28->258
      //   308: goto -249 -> 59
      //   311: iconst_1
      //   312: istore_3
      //   313: goto -159 -> 154
      //   316: iconst_1
      //   317: istore_2
      //   318: goto -33 -> 285
      //   321: iconst_0
      //   322: istore_2
      //   323: goto -243 -> 80
      // Local variable table:
      //   start	length	slot	name	signature
      //   0	326	0	this	ˊ
      //   0	326	1	paramVoid	Void
      //   87	236	2	i	int
      //   4	309	3	bool	boolean
      //   80	183	4	localFF1	FF
      //   82	171	5	localFF2	FF
      // Exception table:
      //   from	to	target	type
      //   154	161	148	java/lang/Exception
      //   161	169	148	java/lang/Exception
      //   119	123	186	java/lang/Exception
      //   192	199	186	java/lang/Exception
      //   199	207	186	java/lang/Exception
    }
  }
}
