package o;

import android.content.Context;
import android.content.Intent;
import android.content.pm.ApplicationInfo;
import android.content.res.Resources;
import android.view.View;
import android.widget.Button;
import java.io.UnsupportedEncodingException;

public final class Ly
  extends IB<LD>
{
  private static int ʼॱ = 0;
  private static char[] ʽॱ;
  private static byte ʾ;
  private static long ʿ;
  private static int ˉ = 1;
  private FF ˈ;
  
  static
  {
    ʻॱ();
    ʾ = -102;
    int i = ˉ + 15;
    ʼॱ = i % 128;
    if (i % 2 == 0) {}
  }
  
  public Ly() {}
  
  static void ʻॱ()
  {
    ʿ = 6009758420931389315L;
    ʽॱ = new char[] { 109, 10177, 20335, 30439, -24984, -14874, -4740, 5362, 105, 10221, 20338, 30444, -24990, -14853, 97, 10208, 20338, 30432, -24989, -14879, -4784, 5364, 15466, 118, 10218, 20323, 30462, -7179, -15276, -21256, -27273, 32241, 9829, 5, 10137, 20237, 30341, 109, 10177, 20335, 30439, -24984, -14874, -4740, 5362, 15414, 25588, -29832, -19769, -9663, 469, 10603, 20701, 30784, -24609, -14513, -4357, 5705, 15819, 25910, -29526, -19418, -26128, -16783, -10523, -4275, 2031, 23658, 29932, -29332, -23064, -1500, 4827, 11032, 17344, -26556, -20273, -13997, -7735, 1603, 24207, 30529, -28723, -23474, -848, 5408, 11648, 16957, -25943, -19658, -13393, -8151, 14504, 20782, 27048, -29184, -22892, -250, 6031, 11345, 103, 10214, 20338, 30426, -24968, -14851, -4741, 5371, 15487, 25523, -29876, -19825, -9641, 467, 10584, 20676, 30814, -24620, -14568, -4394, 5722, 15833, 25895, -29513, -19433, -9302, 813, 10917, 21053, 31137, -24261, -14167, -4091, 6023, 16185, 26269, -29175, -19049, -8954, 1244, 1973, 8244, 18592, 28936, -26198, -15825, -5463, 4905, 15277, 25697, -29538, -19107, -8827, 1537, 11914, 22294, 32652, -26618, -16182, -5884, 4488, 14859, 25333, -29851, -19515, -9096, 1260, 11635, 21994, 32380, -22825, -12421, -2089, 4169, 14528, 24850, 103, 10214, 20338, 30426, -24968, -14851, -4741, 5371, 15487, 25523, -29876, -19825, -9641, 467, 10584, 20676, 30814, -24620, -14568, -4394, 5722, 15833, 25895, -29513, -19433, -9302, 813, 10917, 21053, 31137, -24261, -14167, -4091, 6076, 16146, 26252, -29164, -19045, -8869, 73, 10192, 20297, 30372, -25036, -14921, -4825, 5292, 15413, 25514, -6412, -16010, -22047, -28667, 30869 };
  }
  
  private static String ˋ(int paramInt1, char paramChar, int paramInt2)
  {
    for (;;)
    {
      int j = 34;
      break label106;
      Object localObject = new char[paramInt2];
      int i = 0;
      break label209;
      break label139;
      label23:
      paramInt1 = ʼॱ + 39;
      ˉ = paramInt1 % 128;
      if (paramInt1 % 2 != 0) {
        return localObject;
      }
      label106:
      label139:
      do
      {
        i = 1;
        switch (i)
        {
        case 1: 
        default: 
          break;
          return localObject;
        case 0: 
          localObject = new char[paramInt2];
          i = 0;
          break label209;
          localObject = new String((char[])localObject);
          break label23;
          switch (j)
          {
          case 34: 
          default: 
            break label166;
            i = ʼॱ + 19;
            ˉ = i % 128;
          }
          break;
        }
      } while (i % 2 == 0);
      break label204;
      label166:
      localObject[i] = ((char)(int)(ʽॱ[(paramInt1 + i)] ^ i * ʿ ^ paramChar));
      i += 1;
      label204:
      label209:
      while (i < paramInt2)
      {
        j = 70;
        break label106;
        i = 0;
        break;
      }
    }
  }
  
  private String ˏ(String paramString)
  {
    for (;;)
    {
      int j = 81;
      break label275;
      byte[] arrayOfByte;
      int i;
      try
      {
        paramString = paramString.getBytes(ˋ(getResources().getString(2131755118).substring(0, 5).length() + 210, (char)(getResources().getString(2131755549).substring(3, 4).codePointAt(0) - 111), getResources().getString(2131755309).substring(0, 5).length() + 5).intern());
        arrayOfByte = new byte[paramString.length];
        i = 0;
      }
      catch (UnsupportedEncodingException paramString)
      {
        label120:
        throw new RuntimeException(paramString);
      }
      arrayOfByte[i] = ((byte)(paramString[(paramString.length - i - 1)] ^ ʾ));
      i += 1;
      break label307;
      return paramString;
      label275:
      label307:
      do
      {
        j = 10;
        break label275;
        do
        {
          break;
          i = ˉ + 87;
          ʼॱ = i % 128;
        } while (i % 2 != 0);
        break;
        i = ˉ + 65;
        ʼॱ = i % 128;
        if (i % 2 != 0) {
          break label120;
        }
        return paramString;
        for (;;)
        {
          paramString = new String(arrayOfByte, ˋ(getResources().getString(2131755442).substring(0, 4).codePointAt(2) + 214, (char)(getApplicationInfo().targetSdkVersion + 59016), getResources().getString(2131755468).substring(0, 10).codePointAt(5) - 238).intern());
          break;
          switch (j)
          {
          }
        }
        j = paramString.length;
      } while (i < j);
    }
  }
  
  /* Error */
  public Resources getResources()
  {
    // Byte code:
    //   0: getstatic 28	o/Ly:ˉ	I
    //   3: bipush 61
    //   5: iadd
    //   6: istore_1
    //   7: iload_1
    //   8: sipush 128
    //   11: irem
    //   12: putstatic 26	o/Ly:ʼॱ	I
    //   15: iload_1
    //   16: iconst_2
    //   17: irem
    //   18: ifeq +6 -> 24
    //   21: goto +53 -> 74
    //   24: goto +55 -> 79
    //   27: aload_2
    //   28: areturn
    //   29: iload_1
    //   30: lookupswitch	default:+26->56, 45:+-3->27, 98:+28->58
    //   56: aload_2
    //   57: areturn
    //   58: aconst_null
    //   59: arraylength
    //   60: istore_1
    //   61: aload_2
    //   62: areturn
    //   63: aload_0
    //   64: invokespecial 323	o/IB:getResources	()Landroid/content/res/Resources;
    //   67: invokestatic 328	o/oH:ˊ	(Landroid/content/res/Resources;)Landroid/content/res/Resources;
    //   70: astore_2
    //   71: goto +16 -> 87
    //   74: iconst_1
    //   75: istore_1
    //   76: goto +41 -> 117
    //   79: iconst_0
    //   80: istore_1
    //   81: goto +36 -> 117
    //   84: astore_2
    //   85: aload_2
    //   86: athrow
    //   87: getstatic 28	o/Ly:ˉ	I
    //   90: bipush 81
    //   92: iadd
    //   93: istore_1
    //   94: iload_1
    //   95: sipush 128
    //   98: irem
    //   99: putstatic 26	o/Ly:ʼॱ	I
    //   102: iload_1
    //   103: iconst_2
    //   104: irem
    //   105: ifeq +6 -> 111
    //   108: goto +35 -> 143
    //   111: bipush 45
    //   113: istore_1
    //   114: goto -85 -> 29
    //   117: iload_1
    //   118: tableswitch	default:+22->140, 0:+-55->63, 1:+31->149
    //   140: goto +9 -> 149
    //   143: bipush 98
    //   145: istore_1
    //   146: goto -117 -> 29
    //   149: aload_0
    //   150: invokespecial 323	o/IB:getResources	()Landroid/content/res/Resources;
    //   153: astore_2
    //   154: aload_2
    //   155: invokestatic 328	o/oH:ˊ	(Landroid/content/res/Resources;)Landroid/content/res/Resources;
    //   158: astore_2
    //   159: new 236	java/lang/NullPointerException
    //   162: dup
    //   163: invokespecial 237	java/lang/NullPointerException:<init>	()V
    //   166: athrow
    // Local variable table:
    //   start	length	slot	name	signature
    //   0	167	0	this	Ly
    //   6	140	1	i	int
    //   27	44	2	localResources1	Resources
    //   84	2	2	localException	Exception
    //   153	6	2	localResources2	Resources
    // Exception table:
    //   from	to	target	type
    //   154	167	84	java/lang/Exception
  }
  
  public void onActivityResult(int paramInt1, int paramInt2, Intent paramIntent)
  {
    break label143;
    for (;;)
    {
      try
      {
        paramInt2 = ʼॱ + 65;
        try
        {
          ˉ = paramInt2 % 128;
          if (paramInt2 % 2 == 0) {
            break;
          }
        }
        catch (Exception paramIntent)
        {
          throw paramIntent;
        }
      }
      catch (Exception paramIntent)
      {
        throw paramIntent;
      }
      setResult(-1);
      continue;
      paramInt2 = null.length;
      switch (paramInt1)
      {
      }
    }
    for (;;)
    {
      label70:
      switch (paramInt2)
      {
      }
      break;
      label102:
      super.onActivityResult(paramInt1, paramInt2, paramIntent);
      if (paramInt2 != -1) {
        break label223;
      }
      for (;;)
      {
        switch (paramInt1)
        {
        }
        break;
        label143:
        break label102;
        paramInt2 = 1;
        break label195;
        do
        {
          throw new NullPointerException();
          paramInt1 = ʼॱ + 71;
          ˉ = paramInt1 % 128;
        } while (paramInt1 % 2 == 0);
        return;
        paramInt2 = 0;
        break label195;
        paramInt2 = 13;
        break label70;
        label195:
        switch (paramInt2)
        {
        }
      }
      label223:
      paramInt2 = 72;
    }
  }
  
  /* Error */
  public final void onApplyClick(View paramView)
  {
    // Byte code:
    //   0: goto +258 -> 258
    //   3: astore_1
    //   4: aload_1
    //   5: athrow
    //   6: bipush 56
    //   8: istore_2
    //   9: goto +276 -> 285
    //   12: aload_1
    //   13: aload_0
    //   14: invokevirtual 277	android/content/Context:getResources	()Landroid/content/res/Resources;
    //   17: ldc_w 339
    //   20: invokevirtual 284	android/content/res/Resources:getString	(I)Ljava/lang/String;
    //   23: iconst_0
    //   24: iconst_4
    //   25: invokevirtual 288	java/lang/String:substring	(II)Ljava/lang/String;
    //   28: invokevirtual 292	java/lang/String:length	()I
    //   31: bipush 19
    //   33: iadd
    //   34: aload_0
    //   35: invokevirtual 277	android/content/Context:getResources	()Landroid/content/res/Resources;
    //   38: ldc_w 340
    //   41: invokevirtual 284	android/content/res/Resources:getString	(I)Ljava/lang/String;
    //   44: iconst_0
    //   45: bipush 6
    //   47: invokevirtual 288	java/lang/String:substring	(II)Ljava/lang/String;
    //   50: invokevirtual 292	java/lang/String:length	()I
    //   53: bipush 6
    //   55: isub
    //   56: i2c
    //   57: aload_0
    //   58: invokevirtual 343	android/content/Context:getPackageName	()Ljava/lang/String;
    //   61: invokevirtual 292	java/lang/String:length	()I
    //   64: bipush 7
    //   66: isub
    //   67: invokestatic 256	o/Ly:ˋ	(ICI)Ljava/lang/String;
    //   70: invokevirtual 260	java/lang/String:intern	()Ljava/lang/String;
    //   73: invokestatic 346	o/vq:ˎ	(Ljava/lang/Object;Ljava/lang/String;)V
    //   76: aload_0
    //   77: getfield 241	o/Ly:ॱˊ	Landroid/databinding/ViewDataBinding;
    //   80: checkcast 243	o/LD
    //   83: getfield 350	o/LD:ᐝ	Landroid/widget/Button;
    //   86: astore_1
    //   87: aload_1
    //   88: aload_0
    //   89: invokevirtual 277	android/content/Context:getResources	()Landroid/content/res/Resources;
    //   92: ldc_w 351
    //   95: invokevirtual 284	android/content/res/Resources:getString	(I)Ljava/lang/String;
    //   98: iconst_0
    //   99: bipush 15
    //   101: invokevirtual 288	java/lang/String:substring	(II)Ljava/lang/String;
    //   104: invokevirtual 292	java/lang/String:length	()I
    //   107: bipush 22
    //   109: iadd
    //   110: aload_0
    //   111: invokevirtual 312	android/content/Context:getApplicationInfo	()Landroid/content/pm/ApplicationInfo;
    //   114: getfield 317	android/content/pm/ApplicationInfo:targetSdkVersion	I
    //   117: bipush 25
    //   119: isub
    //   120: i2c
    //   121: aload_0
    //   122: invokevirtual 277	android/content/Context:getResources	()Landroid/content/res/Resources;
    //   125: ldc_w 352
    //   128: invokevirtual 284	android/content/res/Resources:getString	(I)Ljava/lang/String;
    //   131: iconst_0
    //   132: bipush 8
    //   134: invokevirtual 288	java/lang/String:substring	(II)Ljava/lang/String;
    //   137: bipush 7
    //   139: invokevirtual 297	java/lang/String:codePointAt	(I)I
    //   142: sipush 207
    //   145: isub
    //   146: invokestatic 256	o/Ly:ˋ	(ICI)Ljava/lang/String;
    //   149: invokevirtual 260	java/lang/String:intern	()Ljava/lang/String;
    //   152: invokestatic 354	o/vq:ˋ	(Ljava/lang/Object;Ljava/lang/String;)V
    //   155: aload_1
    //   156: iconst_0
    //   157: invokevirtual 360	android/widget/Button:setEnabled	(Z)V
    //   160: goto +17 -> 177
    //   163: astore_1
    //   164: aload_1
    //   165: invokevirtual 366	java/lang/Throwable:getCause	()Ljava/lang/Throwable;
    //   168: astore_3
    //   169: aload_3
    //   170: ifnull +5 -> 175
    //   173: aload_3
    //   174: athrow
    //   175: aload_1
    //   176: athrow
    //   177: aload_0
    //   178: invokevirtual 343	android/content/Context:getPackageName	()Ljava/lang/String;
    //   181: invokevirtual 292	java/lang/String:length	()I
    //   184: bipush 7
    //   186: isub
    //   187: aload_0
    //   188: invokevirtual 312	android/content/Context:getApplicationInfo	()Landroid/content/pm/ApplicationInfo;
    //   191: getfield 317	android/content/pm/ApplicationInfo:targetSdkVersion	I
    //   194: bipush 110
    //   196: iadd
    //   197: aload_0
    //   198: invokevirtual 277	android/content/Context:getResources	()Landroid/content/res/Resources;
    //   201: ldc_w 367
    //   204: invokevirtual 284	android/content/res/Resources:getString	(I)Ljava/lang/String;
    //   207: iconst_0
    //   208: bipush 17
    //   210: invokevirtual 288	java/lang/String:substring	(II)Ljava/lang/String;
    //   213: invokevirtual 292	java/lang/String:length	()I
    //   216: ldc_w 368
    //   219: iadd
    //   220: i2c
    //   221: invokestatic 373	o/O:ˋ	(IIC)Ljava/lang/Object;
    //   224: checkcast 375	java/lang/Class
    //   227: ldc_w 376
    //   230: aconst_null
    //   231: invokevirtual 380	java/lang/Class:getMethod	(Ljava/lang/String;[Ljava/lang/Class;)Ljava/lang/reflect/Method;
    //   234: aconst_null
    //   235: aconst_null
    //   236: invokevirtual 386	java/lang/reflect/Method:invoke	(Ljava/lang/Object;[Ljava/lang/Object;)Ljava/lang/Object;
    //   239: checkcast 388	o/It
    //   242: astore_1
    //   243: aload_0
    //   244: getfield 253	o/Ly:ˈ	Lo/FF;
    //   247: astore_3
    //   248: aload_3
    //   249: ifnonnull +6 -> 255
    //   252: goto +195 -> 447
    //   255: goto -249 -> 6
    //   258: getstatic 26	o/Ly:ʼॱ	I
    //   261: bipush 89
    //   263: iadd
    //   264: istore_2
    //   265: iload_2
    //   266: sipush 128
    //   269: irem
    //   270: putstatic 28	o/Ly:ˉ	I
    //   273: iload_2
    //   274: iconst_2
    //   275: irem
    //   276: ifne +6 -> 282
    //   279: goto +207 -> 486
    //   282: goto -270 -> 12
    //   285: iload_2
    //   286: lookupswitch	default:+26->312, 18:+167->453, 56:+26->312
    //   312: aload_3
    //   313: invokevirtual 392	o/FF:ˎ	()Ljava/lang/String;
    //   316: astore_3
    //   317: getstatic 397	o/Gv:ˊ	Lo/Gv$If;
    //   320: astore 4
    //   322: aload 4
    //   324: invokevirtual 402	o/Gv$If:ˎ	()Lo/Gv;
    //   327: astore 4
    //   329: aload 4
    //   331: invokevirtual 405	o/Gv:ˏॱ	()Ljava/lang/String;
    //   334: astore 4
    //   336: new 407	o/FJ
    //   339: dup
    //   340: aconst_null
    //   341: aload 4
    //   343: iconst_1
    //   344: aconst_null
    //   345: invokespecial 410	o/FJ:<init>	(Ljava/lang/String;Ljava/lang/String;ILo/vn;)V
    //   348: astore 4
    //   350: aload_1
    //   351: aload_3
    //   352: aload 4
    //   354: invokeinterface 414 3 0
    //   359: new 7	o/Ly$If
    //   362: dup
    //   363: aload_0
    //   364: aload_0
    //   365: checkcast 273	android/content/Context
    //   368: invokespecial 417	o/Ly$If:<init>	(Lo/Ly;Landroid/content/Context;)V
    //   371: checkcast 419	o/Cx
    //   374: invokeinterface 424 2 0
    //   379: return
    //   380: aload_0
    //   381: invokevirtual 312	android/content/Context:getApplicationInfo	()Landroid/content/pm/ApplicationInfo;
    //   384: getfield 317	android/content/pm/ApplicationInfo:targetSdkVersion	I
    //   387: iconst_2
    //   388: iadd
    //   389: aload_0
    //   390: invokevirtual 277	android/content/Context:getResources	()Landroid/content/res/Resources;
    //   393: ldc_w 425
    //   396: invokevirtual 284	android/content/res/Resources:getString	(I)Ljava/lang/String;
    //   399: iconst_0
    //   400: bipush 10
    //   402: invokevirtual 288	java/lang/String:substring	(II)Ljava/lang/String;
    //   405: iconst_1
    //   406: invokevirtual 297	java/lang/String:codePointAt	(I)I
    //   409: ldc_w 426
    //   412: iadd
    //   413: i2c
    //   414: aload_0
    //   415: invokevirtual 277	android/content/Context:getResources	()Landroid/content/res/Resources;
    //   418: ldc_w 427
    //   421: invokevirtual 284	android/content/res/Resources:getString	(I)Ljava/lang/String;
    //   424: iconst_0
    //   425: iconst_4
    //   426: invokevirtual 288	java/lang/String:substring	(II)Ljava/lang/String;
    //   429: iconst_2
    //   430: invokevirtual 297	java/lang/String:codePointAt	(I)I
    //   433: iconst_5
    //   434: isub
    //   435: invokestatic 256	o/Ly:ˋ	(ICI)Ljava/lang/String;
    //   438: invokevirtual 260	java/lang/String:intern	()Ljava/lang/String;
    //   441: invokestatic 265	o/vq:ˊ	(Ljava/lang/String;)V
    //   444: goto -132 -> 312
    //   447: bipush 18
    //   449: istore_2
    //   450: goto -165 -> 285
    //   453: getstatic 26	o/Ly:ʼॱ	I
    //   456: bipush 111
    //   458: iadd
    //   459: istore_2
    //   460: iload_2
    //   461: sipush 128
    //   464: irem
    //   465: putstatic 28	o/Ly:ˉ	I
    //   468: iload_2
    //   469: iconst_2
    //   470: irem
    //   471: ifne +6 -> 477
    //   474: goto +6 -> 480
    //   477: goto -97 -> 380
    //   480: goto -100 -> 380
    //   483: astore_1
    //   484: aload_1
    //   485: athrow
    //   486: goto -474 -> 12
    // Local variable table:
    //   start	length	slot	name	signature
    //   0	489	0	this	Ly
    //   0	489	1	paramView	View
    //   8	463	2	i	int
    //   168	184	3	localObject1	Object
    //   320	33	4	localObject2	Object
    // Exception table:
    //   from	to	target	type
    //   322	329	3	java/lang/Exception
    //   329	336	3	java/lang/Exception
    //   336	350	3	java/lang/Exception
    //   350	379	3	java/lang/Exception
    //   177	243	163	finally
    //   312	317	483	java/lang/Exception
    //   317	322	483	java/lang/Exception
  }
  
  public final void onBackClick(View paramView)
  {
    break label126;
    int i = ʼॱ + 29;
    ˉ = i % 128;
    if (i % 2 != 0) {
      return;
    }
    return;
    label29:
    i = ʼॱ + 55;
    ˉ = i % 128;
    if (i % 2 != 0) {}
    for (;;)
    {
      vq.ˎ(paramView, ˋ(getResources().getString(2131755248).substring(0, 9).length() + 14, (char)(getPackageName().codePointAt(2) - 46), getResources().getString(2131755431).substring(0, 4).codePointAt(3) - 8).intern());
      onBackPressed();
      break;
      label126:
      break label29;
    }
  }
  
  /* Error */
  public void onCreate(android.os.Bundle paramBundle)
  {
    // Byte code:
    //   0: goto +349 -> 349
    //   3: goto +26 -> 29
    //   6: getstatic 26	o/Ly:ʼॱ	I
    //   9: bipush 25
    //   11: iadd
    //   12: istore_2
    //   13: iload_2
    //   14: sipush 128
    //   17: irem
    //   18: putstatic 28	o/Ly:ˉ	I
    //   21: iload_2
    //   22: iconst_2
    //   23: irem
    //   24: ifne +4 -> 28
    //   27: return
    //   28: return
    //   29: aload_0
    //   30: aload_1
    //   31: invokespecial 437	o/IB:onCreate	(Landroid/os/Bundle;)V
    //   34: aload_0
    //   35: aload_0
    //   36: getfield 241	o/Ly:ॱˊ	Landroid/databinding/ViewDataBinding;
    //   39: checkcast 243	o/LD
    //   42: getfield 441	o/LD:ॱॱ	Lo/у;
    //   45: invokevirtual 444	o/Ly:ˊ	(Lo/у;)V
    //   48: aload_0
    //   49: getfield 241	o/Ly:ॱˊ	Landroid/databinding/ViewDataBinding;
    //   52: astore_1
    //   53: aload_1
    //   54: aload_0
    //   55: invokevirtual 277	android/content/Context:getResources	()Landroid/content/res/Resources;
    //   58: ldc_w 445
    //   61: invokevirtual 284	android/content/res/Resources:getString	(I)Ljava/lang/String;
    //   64: iconst_0
    //   65: bipush 7
    //   67: invokevirtual 288	java/lang/String:substring	(II)Ljava/lang/String;
    //   70: iconst_1
    //   71: invokevirtual 297	java/lang/String:codePointAt	(I)I
    //   74: bipush 101
    //   76: isub
    //   77: aload_0
    //   78: invokevirtual 312	android/content/Context:getApplicationInfo	()Landroid/content/pm/ApplicationInfo;
    //   81: getfield 317	android/content/pm/ApplicationInfo:targetSdkVersion	I
    //   84: bipush 25
    //   86: isub
    //   87: i2c
    //   88: aload_0
    //   89: invokevirtual 277	android/content/Context:getResources	()Landroid/content/res/Resources;
    //   92: ldc_w 446
    //   95: invokevirtual 284	android/content/res/Resources:getString	(I)Ljava/lang/String;
    //   98: iconst_0
    //   99: iconst_4
    //   100: invokevirtual 288	java/lang/String:substring	(II)Ljava/lang/String;
    //   103: invokevirtual 292	java/lang/String:length	()I
    //   106: iconst_4
    //   107: iadd
    //   108: invokestatic 256	o/Ly:ˋ	(ICI)Ljava/lang/String;
    //   111: invokevirtual 260	java/lang/String:intern	()Ljava/lang/String;
    //   114: invokestatic 354	o/vq:ˋ	(Ljava/lang/Object;Ljava/lang/String;)V
    //   117: aload_1
    //   118: checkcast 243	o/LD
    //   121: iconst_1
    //   122: invokevirtual 448	o/LD:ˏ	(Z)V
    //   125: aload_0
    //   126: invokevirtual 452	o/Ly:getIntent	()Landroid/content/Intent;
    //   129: astore_1
    //   130: aload_1
    //   131: aload_0
    //   132: invokevirtual 277	android/content/Context:getResources	()Landroid/content/res/Resources;
    //   135: ldc_w 453
    //   138: invokevirtual 284	android/content/res/Resources:getString	(I)Ljava/lang/String;
    //   141: iconst_0
    //   142: bipush 9
    //   144: invokevirtual 288	java/lang/String:substring	(II)Ljava/lang/String;
    //   147: iconst_3
    //   148: invokevirtual 297	java/lang/String:codePointAt	(I)I
    //   151: iconst_4
    //   152: isub
    //   153: aload_0
    //   154: invokevirtual 343	android/content/Context:getPackageName	()Ljava/lang/String;
    //   157: invokevirtual 292	java/lang/String:length	()I
    //   160: bipush 11
    //   162: isub
    //   163: i2c
    //   164: aload_0
    //   165: invokevirtual 343	android/content/Context:getPackageName	()Ljava/lang/String;
    //   168: invokevirtual 292	java/lang/String:length	()I
    //   171: iconst_5
    //   172: isub
    //   173: invokestatic 256	o/Ly:ˋ	(ICI)Ljava/lang/String;
    //   176: invokevirtual 260	java/lang/String:intern	()Ljava/lang/String;
    //   179: invokestatic 354	o/vq:ˋ	(Ljava/lang/Object;Ljava/lang/String;)V
    //   182: aload_1
    //   183: invokevirtual 459	android/content/Intent:getExtras	()Landroid/os/Bundle;
    //   186: ifnull +6 -> 192
    //   189: goto +36 -> 225
    //   192: goto +160 -> 352
    //   195: goto +157 -> 352
    //   198: getstatic 26	o/Ly:ʼॱ	I
    //   201: bipush 49
    //   203: iadd
    //   204: istore_2
    //   205: iload_2
    //   206: sipush 128
    //   209: irem
    //   210: putstatic 28	o/Ly:ˉ	I
    //   213: iload_2
    //   214: iconst_2
    //   215: irem
    //   216: ifne +6 -> 222
    //   219: goto -216 -> 3
    //   222: goto -193 -> 29
    //   225: aload_0
    //   226: invokevirtual 452	o/Ly:getIntent	()Landroid/content/Intent;
    //   229: getstatic 464	o/HW:ॱˊ	Ljava/lang/String;
    //   232: invokevirtual 467	android/content/Intent:getStringExtra	(Ljava/lang/String;)Ljava/lang/String;
    //   235: astore_1
    //   236: goto +17 -> 253
    //   239: astore_1
    //   240: aload_1
    //   241: invokevirtual 366	java/lang/Throwable:getCause	()Ljava/lang/Throwable;
    //   244: astore_3
    //   245: aload_3
    //   246: ifnull +5 -> 251
    //   249: aload_3
    //   250: athrow
    //   251: aload_1
    //   252: athrow
    //   253: aload_0
    //   254: invokevirtual 343	android/content/Context:getPackageName	()Ljava/lang/String;
    //   257: invokevirtual 292	java/lang/String:length	()I
    //   260: bipush 7
    //   262: isub
    //   263: aload_0
    //   264: invokevirtual 312	android/content/Context:getApplicationInfo	()Landroid/content/pm/ApplicationInfo;
    //   267: getfield 317	android/content/pm/ApplicationInfo:targetSdkVersion	I
    //   270: bipush 110
    //   272: iadd
    //   273: aload_0
    //   274: invokevirtual 277	android/content/Context:getResources	()Landroid/content/res/Resources;
    //   277: ldc_w 468
    //   280: invokevirtual 284	android/content/res/Resources:getString	(I)Ljava/lang/String;
    //   283: iconst_0
    //   284: bipush 6
    //   286: invokevirtual 288	java/lang/String:substring	(II)Ljava/lang/String;
    //   289: invokevirtual 292	java/lang/String:length	()I
    //   292: ldc_w 469
    //   295: iadd
    //   296: i2c
    //   297: invokestatic 373	o/O:ˋ	(IIC)Ljava/lang/Object;
    //   300: checkcast 375	java/lang/Class
    //   303: ldc_w 376
    //   306: aconst_null
    //   307: invokevirtual 380	java/lang/Class:getMethod	(Ljava/lang/String;[Ljava/lang/Class;)Ljava/lang/reflect/Method;
    //   310: aconst_null
    //   311: aconst_null
    //   312: invokevirtual 386	java/lang/reflect/Method:invoke	(Ljava/lang/Object;[Ljava/lang/Object;)Ljava/lang/Object;
    //   315: checkcast 388	o/It
    //   318: astore_3
    //   319: aload_3
    //   320: aload_1
    //   321: invokeinterface 473 2 0
    //   326: new 9	o/Ly$ˊ
    //   329: dup
    //   330: aload_0
    //   331: aload_0
    //   332: checkcast 273	android/content/Context
    //   335: invokespecial 474	o/Ly$ˊ:<init>	(Lo/Ly;Landroid/content/Context;)V
    //   338: checkcast 419	o/Cx
    //   341: invokeinterface 424 2 0
    //   346: goto -151 -> 195
    //   349: goto -151 -> 198
    //   352: goto -346 -> 6
    // Local variable table:
    //   start	length	slot	name	signature
    //   0	355	0	this	Ly
    //   0	355	1	paramBundle	android.os.Bundle
    //   12	204	2	i	int
    //   244	76	3	localObject	Object
    // Exception table:
    //   from	to	target	type
    //   253	319	239	finally
  }
  
  /* Error */
  public final void onRulesClick(View paramView)
  {
    // Byte code:
    //   0: goto +366 -> 366
    //   3: aload_0
    //   4: getfield 253	o/Ly:ˈ	Lo/FF;
    //   7: astore 4
    //   9: aload 4
    //   11: ifnonnull +6 -> 17
    //   14: goto +230 -> 244
    //   17: goto +265 -> 282
    //   20: iconst_1
    //   21: istore_2
    //   22: goto +227 -> 249
    //   25: goto +254 -> 279
    //   28: iload_2
    //   29: tableswitch	default:+23->52, 0:+340->369, 1:+23->52
    //   52: aload 5
    //   54: aload_1
    //   55: aload 4
    //   57: invokevirtual 477	o/FF:ᐝ	()Ljava/lang/String;
    //   60: invokevirtual 482	o/Ic:ˋ	(Ljava/lang/String;Ljava/lang/String;)Lo/j;
    //   63: invokevirtual 486	o/j:ˎ	()V
    //   66: return
    //   67: aload_0
    //   68: invokevirtual 277	android/content/Context:getResources	()Landroid/content/res/Resources;
    //   71: astore 4
    //   73: aload 4
    //   75: ldc_w 487
    //   78: invokevirtual 284	android/content/res/Resources:getString	(I)Ljava/lang/String;
    //   81: astore 4
    //   83: aload_1
    //   84: aload 4
    //   86: iconst_0
    //   87: bipush 17
    //   89: invokevirtual 288	java/lang/String:substring	(II)Ljava/lang/String;
    //   92: bipush 7
    //   94: invokevirtual 297	java/lang/String:codePointAt	(I)I
    //   97: sipush 152
    //   100: isub
    //   101: aload_0
    //   102: invokevirtual 277	android/content/Context:getResources	()Landroid/content/res/Resources;
    //   105: ldc_w 488
    //   108: invokevirtual 284	android/content/res/Resources:getString	(I)Ljava/lang/String;
    //   111: iconst_0
    //   112: iconst_5
    //   113: invokevirtual 288	java/lang/String:substring	(II)Ljava/lang/String;
    //   116: iconst_1
    //   117: invokevirtual 297	java/lang/String:codePointAt	(I)I
    //   120: bipush 26
    //   122: isub
    //   123: i2c
    //   124: aload_0
    //   125: invokevirtual 343	android/content/Context:getPackageName	()Ljava/lang/String;
    //   128: bipush 6
    //   130: invokevirtual 297	java/lang/String:codePointAt	(I)I
    //   133: bipush 104
    //   135: isub
    //   136: invokestatic 256	o/Ly:ˋ	(ICI)Ljava/lang/String;
    //   139: invokevirtual 260	java/lang/String:intern	()Ljava/lang/String;
    //   142: invokestatic 346	o/vq:ˎ	(Ljava/lang/Object;Ljava/lang/String;)V
    //   145: aload_0
    //   146: invokevirtual 491	o/Ly:ॱˊ	()Landroid/content/Context;
    //   149: invokestatic 494	o/Ic:ˏ	(Landroid/content/Context;)Lo/Ic;
    //   152: astore 5
    //   154: aload_0
    //   155: getstatic 499	o/Lt$If:offers_rules_title	I
    //   158: invokevirtual 500	o/Ly:getString	(I)Ljava/lang/String;
    //   161: astore 4
    //   163: aload 4
    //   165: aload_0
    //   166: invokevirtual 277	android/content/Context:getResources	()Landroid/content/res/Resources;
    //   169: ldc_w 501
    //   172: invokevirtual 284	android/content/res/Resources:getString	(I)Ljava/lang/String;
    //   175: iconst_0
    //   176: iconst_5
    //   177: invokevirtual 288	java/lang/String:substring	(II)Ljava/lang/String;
    //   180: invokevirtual 292	java/lang/String:length	()I
    //   183: bipush 28
    //   185: iadd
    //   186: aload_0
    //   187: invokevirtual 277	android/content/Context:getResources	()Landroid/content/res/Resources;
    //   190: ldc_w 502
    //   193: invokevirtual 284	android/content/res/Resources:getString	(I)Ljava/lang/String;
    //   196: iconst_0
    //   197: iconst_1
    //   198: invokevirtual 288	java/lang/String:substring	(II)Ljava/lang/String;
    //   201: iconst_0
    //   202: invokevirtual 297	java/lang/String:codePointAt	(I)I
    //   205: bipush 50
    //   207: isub
    //   208: i2c
    //   209: aload_0
    //   210: invokevirtual 343	android/content/Context:getPackageName	()Ljava/lang/String;
    //   213: invokevirtual 292	java/lang/String:length	()I
    //   216: bipush 7
    //   218: isub
    //   219: invokestatic 256	o/Ly:ˋ	(ICI)Ljava/lang/String;
    //   222: invokevirtual 260	java/lang/String:intern	()Ljava/lang/String;
    //   225: invokevirtual 506	java/lang/String:startsWith	(Ljava/lang/String;)Z
    //   228: istore_3
    //   229: iload_3
    //   230: ifeq +6 -> 236
    //   233: goto +6 -> 239
    //   236: goto -216 -> 20
    //   239: iconst_0
    //   240: istore_2
    //   241: goto +8 -> 249
    //   244: iconst_0
    //   245: istore_2
    //   246: goto -218 -> 28
    //   249: aload 4
    //   251: astore_1
    //   252: iload_2
    //   253: tableswitch	default:+23->276, 0:+54->307, 1:+-250->3
    //   276: goto +31 -> 307
    //   279: goto -227 -> 52
    //   282: iconst_1
    //   283: istore_2
    //   284: goto -256 -> 28
    //   287: astore_1
    //   288: aload_1
    //   289: athrow
    //   290: aload_0
    //   291: aload 4
    //   293: iconst_4
    //   294: invokevirtual 508	java/lang/String:substring	(I)Ljava/lang/String;
    //   297: invokespecial 510	o/Ly:ˏ	(Ljava/lang/String;)Ljava/lang/String;
    //   300: invokevirtual 260	java/lang/String:intern	()Ljava/lang/String;
    //   303: astore_1
    //   304: goto -301 -> 3
    //   307: getstatic 26	o/Ly:ʼॱ	I
    //   310: bipush 61
    //   312: iadd
    //   313: istore_2
    //   314: iload_2
    //   315: sipush 128
    //   318: irem
    //   319: putstatic 28	o/Ly:ˉ	I
    //   322: iload_2
    //   323: iconst_2
    //   324: irem
    //   325: ifne +6 -> 331
    //   328: goto -38 -> 290
    //   331: goto -41 -> 290
    //   334: astore_1
    //   335: aload_1
    //   336: athrow
    //   337: getstatic 28	o/Ly:ˉ	I
    //   340: istore_2
    //   341: iload_2
    //   342: bipush 115
    //   344: iadd
    //   345: istore_2
    //   346: iload_2
    //   347: sipush 128
    //   350: irem
    //   351: putstatic 26	o/Ly:ʼॱ	I
    //   354: iload_2
    //   355: iconst_2
    //   356: irem
    //   357: ifeq +6 -> 363
    //   360: goto -335 -> 25
    //   363: goto -84 -> 279
    //   366: goto -299 -> 67
    //   369: aload_0
    //   370: invokevirtual 277	android/content/Context:getResources	()Landroid/content/res/Resources;
    //   373: ldc_w 511
    //   376: invokevirtual 284	android/content/res/Resources:getString	(I)Ljava/lang/String;
    //   379: iconst_0
    //   380: iconst_5
    //   381: invokevirtual 288	java/lang/String:substring	(II)Ljava/lang/String;
    //   384: invokevirtual 292	java/lang/String:length	()I
    //   387: bipush 22
    //   389: iadd
    //   390: aload_0
    //   391: invokevirtual 343	android/content/Context:getPackageName	()Ljava/lang/String;
    //   394: iconst_5
    //   395: invokevirtual 297	java/lang/String:codePointAt	(I)I
    //   398: ldc_w 512
    //   401: iadd
    //   402: i2c
    //   403: aload_0
    //   404: invokevirtual 343	android/content/Context:getPackageName	()Ljava/lang/String;
    //   407: iconst_3
    //   408: invokevirtual 297	java/lang/String:codePointAt	(I)I
    //   411: bipush 92
    //   413: isub
    //   414: invokestatic 256	o/Ly:ˋ	(ICI)Ljava/lang/String;
    //   417: invokevirtual 260	java/lang/String:intern	()Ljava/lang/String;
    //   420: invokestatic 265	o/vq:ˊ	(Ljava/lang/String;)V
    //   423: goto -86 -> 337
    // Local variable table:
    //   start	length	slot	name	signature
    //   0	426	0	this	Ly
    //   0	426	1	paramView	View
    //   21	336	2	i	int
    //   228	2	3	bool	boolean
    //   7	285	4	localObject	Object
    //   52	101	5	localIc	Ic
    // Exception table:
    //   from	to	target	type
    //   67	73	287	java/lang/Exception
    //   73	83	287	java/lang/Exception
    //   83	229	287	java/lang/Exception
    //   73	83	334	java/lang/Exception
    //   337	341	334	java/lang/Exception
    //   346	354	334	java/lang/Exception
  }
  
  /* Error */
  public final void onShopClick(View paramView)
  {
    // Byte code:
    //   0: goto +1352 -> 1352
    //   3: invokestatic 514	o/vq:ˎ	()V
    //   6: goto +1243 -> 1249
    //   9: aload 5
    //   11: checkcast 516	java/lang/CharSequence
    //   14: invokeinterface 517 1 0
    //   19: ifne +6 -> 25
    //   22: goto +217 -> 239
    //   25: goto +203 -> 228
    //   28: aload 7
    //   30: invokevirtual 521	o/FN:ˊ	()Ljava/lang/String;
    //   33: astore 7
    //   35: aload 7
    //   37: checkcast 516	java/lang/CharSequence
    //   40: invokestatic 527	android/text/TextUtils:isEmpty	(Ljava/lang/CharSequence;)Z
    //   43: istore 4
    //   45: iload 4
    //   47: ifne +6 -> 53
    //   50: goto +1291 -> 1341
    //   53: goto +47 -> 100
    //   56: goto +96 -> 152
    //   59: aload 5
    //   61: astore_1
    //   62: iload_2
    //   63: lookupswitch	default:+25->88, 57:+1408->1471, 81:+1323->1386
    //   88: aload 5
    //   90: astore_1
    //   91: goto +1295 -> 1386
    //   94: bipush 57
    //   96: istore_2
    //   97: goto -38 -> 59
    //   100: iconst_0
    //   101: istore_2
    //   102: goto +1398 -> 1500
    //   105: getstatic 26	o/Ly:ʼॱ	I
    //   108: bipush 109
    //   110: iadd
    //   111: istore_2
    //   112: iload_2
    //   113: sipush 128
    //   116: irem
    //   117: putstatic 28	o/Ly:ˉ	I
    //   120: iload_2
    //   121: iconst_2
    //   122: irem
    //   123: ifne +6 -> 129
    //   126: goto +1330 -> 1456
    //   129: goto +341 -> 470
    //   132: goto +1451 -> 1583
    //   135: aload_0
    //   136: getfield 253	o/Ly:ˈ	Lo/FF;
    //   139: astore 5
    //   141: aload 5
    //   143: ifnonnull +6 -> 149
    //   146: goto +1200 -> 1346
    //   149: goto +1339 -> 1488
    //   152: aload_1
    //   153: invokevirtual 532	java/util/ArrayList:isEmpty	()Z
    //   156: ifne +6 -> 162
    //   159: goto +688 -> 847
    //   162: goto +82 -> 244
    //   165: aload 6
    //   167: invokeinterface 538 1 0
    //   172: astore 5
    //   174: aload 5
    //   176: checkcast 519	o/FN
    //   179: astore 7
    //   181: aload 7
    //   183: invokevirtual 541	o/FN:ˏ	()Lo/FM;
    //   186: ifnull +6 -> 192
    //   189: goto +1093 -> 1282
    //   192: goto +199 -> 391
    //   195: iconst_1
    //   196: istore_2
    //   197: goto +129 -> 326
    //   200: aload 5
    //   202: invokevirtual 544	o/FF:ॱ	()Ljava/util/ArrayList;
    //   205: checkcast 546	java/lang/Iterable
    //   208: invokeinterface 550 1 0
    //   213: astore 6
    //   215: goto +212 -> 427
    //   218: iload_2
    //   219: ifeq +6 -> 225
    //   222: goto +1133 -> 1355
    //   225: goto +311 -> 536
    //   228: iconst_0
    //   229: istore_2
    //   230: goto +1326 -> 1556
    //   233: bipush 75
    //   235: istore_2
    //   236: goto +303 -> 539
    //   239: iconst_1
    //   240: istore_2
    //   241: goto +1342 -> 1583
    //   244: aload_0
    //   245: invokevirtual 491	o/Ly:ॱˊ	()Landroid/content/Context;
    //   248: invokestatic 494	o/Ic:ˏ	(Landroid/content/Context;)Lo/Ic;
    //   251: astore 6
    //   253: aload_0
    //   254: getstatic 553	o/Lt$If:offers_shop_dialog_title	I
    //   257: invokevirtual 500	o/Ly:getString	(I)Ljava/lang/String;
    //   260: astore 5
    //   262: aload 5
    //   264: aload_0
    //   265: invokevirtual 312	android/content/Context:getApplicationInfo	()Landroid/content/pm/ApplicationInfo;
    //   268: getfield 317	android/content/pm/ApplicationInfo:targetSdkVersion	I
    //   271: bipush 8
    //   273: iadd
    //   274: aload_0
    //   275: invokevirtual 277	android/content/Context:getResources	()Landroid/content/res/Resources;
    //   278: ldc_w 554
    //   281: invokevirtual 284	android/content/res/Resources:getString	(I)Ljava/lang/String;
    //   284: iconst_0
    //   285: iconst_4
    //   286: invokevirtual 288	java/lang/String:substring	(II)Ljava/lang/String;
    //   289: invokevirtual 292	java/lang/String:length	()I
    //   292: iconst_4
    //   293: isub
    //   294: i2c
    //   295: aload_0
    //   296: invokevirtual 343	android/content/Context:getPackageName	()Ljava/lang/String;
    //   299: invokevirtual 292	java/lang/String:length	()I
    //   302: bipush 7
    //   304: isub
    //   305: invokestatic 256	o/Ly:ˋ	(ICI)Ljava/lang/String;
    //   308: invokevirtual 260	java/lang/String:intern	()Ljava/lang/String;
    //   311: invokevirtual 506	java/lang/String:startsWith	(Ljava/lang/String;)Z
    //   314: ifeq +6 -> 320
    //   317: goto -223 -> 94
    //   320: goto +31 -> 351
    //   323: goto -105 -> 218
    //   326: iload_2
    //   327: tableswitch	default:+21->348, 0:+64->391, 1:+1014->1341
    //   348: goto +993 -> 1341
    //   351: bipush 81
    //   353: istore_2
    //   354: goto -295 -> 59
    //   357: goto +214 -> 571
    //   360: iload_2
    //   361: lookupswitch	default:+27->388, 37:+833->1194, 78:+-161->200
    //   388: goto +806 -> 1194
    //   391: aload 7
    //   393: invokevirtual 556	o/FN:ˎ	()Z
    //   396: istore 4
    //   398: iload 4
    //   400: ifeq +6 -> 406
    //   403: goto -375 -> 28
    //   406: goto -306 -> 100
    //   409: aload_0
    //   410: aload 5
    //   412: iconst_4
    //   413: invokevirtual 508	java/lang/String:substring	(I)Ljava/lang/String;
    //   416: invokespecial 510	o/Ly:ˏ	(Ljava/lang/String;)Ljava/lang/String;
    //   419: invokevirtual 260	java/lang/String:intern	()Ljava/lang/String;
    //   422: astore 5
    //   424: goto +1035 -> 1459
    //   427: aload 6
    //   429: invokeinterface 559 1 0
    //   434: ifeq +6 -> 440
    //   437: goto +6 -> 443
    //   440: goto +889 -> 1329
    //   443: getstatic 28	o/Ly:ˉ	I
    //   446: bipush 89
    //   448: iadd
    //   449: istore_2
    //   450: iload_2
    //   451: sipush 128
    //   454: irem
    //   455: putstatic 26	o/Ly:ʼॱ	I
    //   458: iload_2
    //   459: iconst_2
    //   460: irem
    //   461: ifeq +6 -> 467
    //   464: goto +380 -> 844
    //   467: goto -302 -> 165
    //   470: aload_0
    //   471: invokevirtual 312	android/content/Context:getApplicationInfo	()Landroid/content/pm/ApplicationInfo;
    //   474: getfield 317	android/content/pm/ApplicationInfo:targetSdkVersion	I
    //   477: iconst_2
    //   478: iadd
    //   479: aload_0
    //   480: invokevirtual 277	android/content/Context:getResources	()Landroid/content/res/Resources;
    //   483: ldc_w 560
    //   486: invokevirtual 284	android/content/res/Resources:getString	(I)Ljava/lang/String;
    //   489: iconst_0
    //   490: iconst_4
    //   491: invokevirtual 288	java/lang/String:substring	(II)Ljava/lang/String;
    //   494: iconst_2
    //   495: invokevirtual 297	java/lang/String:codePointAt	(I)I
    //   498: ldc_w 561
    //   501: iadd
    //   502: i2c
    //   503: aload_0
    //   504: invokevirtual 277	android/content/Context:getResources	()Landroid/content/res/Resources;
    //   507: ldc_w 562
    //   510: invokevirtual 284	android/content/res/Resources:getString	(I)Ljava/lang/String;
    //   513: iconst_0
    //   514: iconst_4
    //   515: invokevirtual 288	java/lang/String:substring	(II)Ljava/lang/String;
    //   518: iconst_2
    //   519: invokevirtual 297	java/lang/String:codePointAt	(I)I
    //   522: iconst_5
    //   523: isub
    //   524: invokestatic 256	o/Ly:ˋ	(ICI)Ljava/lang/String;
    //   527: invokevirtual 260	java/lang/String:intern	()Ljava/lang/String;
    //   530: invokestatic 265	o/vq:ˊ	(Ljava/lang/String;)V
    //   533: goto +837 -> 1370
    //   536: goto -109 -> 427
    //   539: iload_2
    //   540: lookupswitch	default:+28->568, 57:+-435->105, 75:+830->1370
    //   568: goto -463 -> 105
    //   571: aload 7
    //   573: invokevirtual 541	o/FN:ˏ	()Lo/FM;
    //   576: invokevirtual 566	o/FM:ˏ	()Ljava/lang/String;
    //   579: astore 8
    //   581: aload_0
    //   582: invokevirtual 277	android/content/Context:getResources	()Landroid/content/res/Resources;
    //   585: ldc_w 567
    //   588: invokevirtual 284	android/content/res/Resources:getString	(I)Ljava/lang/String;
    //   591: iconst_0
    //   592: iconst_4
    //   593: invokevirtual 288	java/lang/String:substring	(II)Ljava/lang/String;
    //   596: invokevirtual 292	java/lang/String:length	()I
    //   599: iconst_0
    //   600: iadd
    //   601: aload_0
    //   602: invokevirtual 277	android/content/Context:getResources	()Landroid/content/res/Resources;
    //   605: ldc_w 568
    //   608: invokevirtual 284	android/content/res/Resources:getString	(I)Ljava/lang/String;
    //   611: iconst_0
    //   612: iconst_4
    //   613: invokevirtual 288	java/lang/String:substring	(II)Ljava/lang/String;
    //   616: iconst_2
    //   617: invokevirtual 297	java/lang/String:codePointAt	(I)I
    //   620: sipush 402
    //   623: iadd
    //   624: aload_0
    //   625: invokevirtual 277	android/content/Context:getResources	()Landroid/content/res/Resources;
    //   628: ldc_w 569
    //   631: invokevirtual 284	android/content/res/Resources:getString	(I)Ljava/lang/String;
    //   634: bipush 22
    //   636: bipush 23
    //   638: invokevirtual 288	java/lang/String:substring	(II)Ljava/lang/String;
    //   641: iconst_0
    //   642: invokevirtual 297	java/lang/String:codePointAt	(I)I
    //   645: sipush 30221
    //   648: iadd
    //   649: i2c
    //   650: invokestatic 373	o/O:ˋ	(IIC)Ljava/lang/Object;
    //   653: checkcast 375	java/lang/Class
    //   656: ldc_w 570
    //   659: invokevirtual 574	java/lang/Class:getField	(Ljava/lang/String;)Ljava/lang/reflect/Field;
    //   662: aconst_null
    //   663: invokevirtual 580	java/lang/reflect/Field:get	(Ljava/lang/Object;)Ljava/lang/Object;
    //   666: astore 9
    //   668: goto +20 -> 688
    //   671: astore_1
    //   672: aload_1
    //   673: invokevirtual 366	java/lang/Throwable:getCause	()Ljava/lang/Throwable;
    //   676: astore 5
    //   678: aload 5
    //   680: ifnull +6 -> 686
    //   683: aload 5
    //   685: athrow
    //   686: aload_1
    //   687: athrow
    //   688: aload_0
    //   689: invokevirtual 343	android/content/Context:getPackageName	()Ljava/lang/String;
    //   692: invokevirtual 292	java/lang/String:length	()I
    //   695: iconst_5
    //   696: isub
    //   697: aload_0
    //   698: invokevirtual 312	android/content/Context:getApplicationInfo	()Landroid/content/pm/ApplicationInfo;
    //   701: getfield 317	android/content/pm/ApplicationInfo:targetSdkVersion	I
    //   704: sipush 392
    //   707: iadd
    //   708: aload_0
    //   709: invokevirtual 312	android/content/Context:getApplicationInfo	()Landroid/content/pm/ApplicationInfo;
    //   712: getfield 317	android/content/pm/ApplicationInfo:targetSdkVersion	I
    //   715: bipush 25
    //   717: isub
    //   718: i2c
    //   719: invokestatic 373	o/O:ˋ	(IIC)Ljava/lang/Object;
    //   722: checkcast 375	java/lang/Class
    //   725: ldc_w 581
    //   728: aconst_null
    //   729: invokevirtual 380	java/lang/Class:getMethod	(Ljava/lang/String;[Ljava/lang/Class;)Ljava/lang/reflect/Method;
    //   732: aload 9
    //   734: aconst_null
    //   735: invokevirtual 386	java/lang/reflect/Method:invoke	(Ljava/lang/Object;[Ljava/lang/Object;)Ljava/lang/Object;
    //   738: astore 9
    //   740: goto +20 -> 760
    //   743: astore_1
    //   744: aload_1
    //   745: invokevirtual 366	java/lang/Throwable:getCause	()Ljava/lang/Throwable;
    //   748: astore 5
    //   750: aload 5
    //   752: ifnull +6 -> 758
    //   755: aload 5
    //   757: athrow
    //   758: aload_1
    //   759: athrow
    //   760: aload_0
    //   761: invokevirtual 343	android/content/Context:getPackageName	()Ljava/lang/String;
    //   764: invokevirtual 292	java/lang/String:length	()I
    //   767: bipush 7
    //   769: isub
    //   770: aload_0
    //   771: invokevirtual 312	android/content/Context:getApplicationInfo	()Landroid/content/pm/ApplicationInfo;
    //   774: getfield 317	android/content/pm/ApplicationInfo:targetSdkVersion	I
    //   777: sipush 388
    //   780: iadd
    //   781: aload_0
    //   782: invokevirtual 277	android/content/Context:getResources	()Landroid/content/res/Resources;
    //   785: ldc_w 582
    //   788: invokevirtual 284	android/content/res/Resources:getString	(I)Ljava/lang/String;
    //   791: iconst_0
    //   792: iconst_4
    //   793: invokevirtual 288	java/lang/String:substring	(II)Ljava/lang/String;
    //   796: invokevirtual 292	java/lang/String:length	()I
    //   799: sipush 30249
    //   802: iadd
    //   803: i2c
    //   804: invokestatic 373	o/O:ˋ	(IIC)Ljava/lang/Object;
    //   807: checkcast 375	java/lang/Class
    //   810: ldc_w 583
    //   813: aconst_null
    //   814: invokevirtual 380	java/lang/Class:getMethod	(Ljava/lang/String;[Ljava/lang/Class;)Ljava/lang/reflect/Method;
    //   817: aload 9
    //   819: aconst_null
    //   820: invokevirtual 386	java/lang/reflect/Method:invoke	(Ljava/lang/Object;[Ljava/lang/Object;)Ljava/lang/Object;
    //   823: astore 9
    //   825: aload 8
    //   827: aload 9
    //   829: invokevirtual 587	java/lang/String:equals	(Ljava/lang/Object;)Z
    //   832: ifne +6 -> 838
    //   835: goto +354 -> 1189
    //   838: goto -643 -> 195
    //   841: goto -623 -> 218
    //   844: goto -679 -> 165
    //   847: new 589	o/LQ
    //   850: dup
    //   851: aload_0
    //   852: checkcast 273	android/content/Context
    //   855: aload_1
    //   856: checkcast 591	java/util/List
    //   859: invokespecial 594	o/LQ:<init>	(Landroid/content/Context;Ljava/util/List;)V
    //   862: invokevirtual 597	o/LQ:ˏ	()Lo/ᐸ;
    //   865: pop
    //   866: return
    //   867: aload_1
    //   868: aload_0
    //   869: invokevirtual 277	android/content/Context:getResources	()Landroid/content/res/Resources;
    //   872: ldc_w 598
    //   875: invokevirtual 284	android/content/res/Resources:getString	(I)Ljava/lang/String;
    //   878: iconst_0
    //   879: iconst_4
    //   880: invokevirtual 288	java/lang/String:substring	(II)Ljava/lang/String;
    //   883: iconst_1
    //   884: invokevirtual 297	java/lang/String:codePointAt	(I)I
    //   887: iconst_3
    //   888: isub
    //   889: aload_0
    //   890: invokevirtual 343	android/content/Context:getPackageName	()Ljava/lang/String;
    //   893: invokevirtual 292	java/lang/String:length	()I
    //   896: bipush 11
    //   898: isub
    //   899: i2c
    //   900: aload_0
    //   901: invokevirtual 312	android/content/Context:getApplicationInfo	()Landroid/content/pm/ApplicationInfo;
    //   904: getfield 317	android/content/pm/ApplicationInfo:targetSdkVersion	I
    //   907: bipush 21
    //   909: isub
    //   910: invokestatic 256	o/Ly:ˋ	(ICI)Ljava/lang/String;
    //   913: invokevirtual 260	java/lang/String:intern	()Ljava/lang/String;
    //   916: invokestatic 346	o/vq:ˎ	(Ljava/lang/Object;Ljava/lang/String;)V
    //   919: new 529	java/util/ArrayList
    //   922: dup
    //   923: invokespecial 599	java/util/ArrayList:<init>	()V
    //   926: astore_1
    //   927: aload_0
    //   928: invokevirtual 277	android/content/Context:getResources	()Landroid/content/res/Resources;
    //   931: ldc_w 600
    //   934: invokevirtual 284	android/content/res/Resources:getString	(I)Ljava/lang/String;
    //   937: iconst_0
    //   938: iconst_4
    //   939: invokevirtual 288	java/lang/String:substring	(II)Ljava/lang/String;
    //   942: invokevirtual 292	java/lang/String:length	()I
    //   945: iconst_0
    //   946: iadd
    //   947: aload_0
    //   948: invokevirtual 343	android/content/Context:getPackageName	()Ljava/lang/String;
    //   951: invokevirtual 292	java/lang/String:length	()I
    //   954: sipush 402
    //   957: iadd
    //   958: aload_0
    //   959: invokevirtual 312	android/content/Context:getApplicationInfo	()Landroid/content/pm/ApplicationInfo;
    //   962: getfield 317	android/content/pm/ApplicationInfo:targetSdkVersion	I
    //   965: sipush 30228
    //   968: iadd
    //   969: i2c
    //   970: invokestatic 373	o/O:ˋ	(IIC)Ljava/lang/Object;
    //   973: checkcast 375	java/lang/Class
    //   976: ldc_w 570
    //   979: invokevirtual 574	java/lang/Class:getField	(Ljava/lang/String;)Ljava/lang/reflect/Field;
    //   982: aconst_null
    //   983: invokevirtual 580	java/lang/reflect/Field:get	(Ljava/lang/Object;)Ljava/lang/Object;
    //   986: astore 5
    //   988: goto +20 -> 1008
    //   991: astore_1
    //   992: aload_1
    //   993: invokevirtual 366	java/lang/Throwable:getCause	()Ljava/lang/Throwable;
    //   996: astore 5
    //   998: aload 5
    //   1000: ifnull +6 -> 1006
    //   1003: aload 5
    //   1005: athrow
    //   1006: aload_1
    //   1007: athrow
    //   1008: aload_0
    //   1009: invokevirtual 277	android/content/Context:getResources	()Landroid/content/res/Resources;
    //   1012: ldc_w 601
    //   1015: invokevirtual 284	android/content/res/Resources:getString	(I)Ljava/lang/String;
    //   1018: iconst_0
    //   1019: iconst_4
    //   1020: invokevirtual 288	java/lang/String:substring	(II)Ljava/lang/String;
    //   1023: invokevirtual 292	java/lang/String:length	()I
    //   1026: iconst_2
    //   1027: iadd
    //   1028: aload_0
    //   1029: invokevirtual 343	android/content/Context:getPackageName	()Ljava/lang/String;
    //   1032: iconst_1
    //   1033: invokevirtual 297	java/lang/String:codePointAt	(I)I
    //   1036: sipush 306
    //   1039: iadd
    //   1040: aload_0
    //   1041: invokevirtual 277	android/content/Context:getResources	()Landroid/content/res/Resources;
    //   1044: ldc_w 501
    //   1047: invokevirtual 284	android/content/res/Resources:getString	(I)Ljava/lang/String;
    //   1050: iconst_0
    //   1051: iconst_5
    //   1052: invokevirtual 288	java/lang/String:substring	(II)Ljava/lang/String;
    //   1055: invokevirtual 292	java/lang/String:length	()I
    //   1058: iconst_5
    //   1059: isub
    //   1060: i2c
    //   1061: invokestatic 373	o/O:ˋ	(IIC)Ljava/lang/Object;
    //   1064: checkcast 375	java/lang/Class
    //   1067: ldc_w 581
    //   1070: aconst_null
    //   1071: invokevirtual 380	java/lang/Class:getMethod	(Ljava/lang/String;[Ljava/lang/Class;)Ljava/lang/reflect/Method;
    //   1074: aload 5
    //   1076: aconst_null
    //   1077: invokevirtual 386	java/lang/reflect/Method:invoke	(Ljava/lang/Object;[Ljava/lang/Object;)Ljava/lang/Object;
    //   1080: astore 5
    //   1082: goto +20 -> 1102
    //   1085: astore_1
    //   1086: aload_1
    //   1087: invokevirtual 366	java/lang/Throwable:getCause	()Ljava/lang/Throwable;
    //   1090: astore 5
    //   1092: aload 5
    //   1094: ifnull +6 -> 1100
    //   1097: aload 5
    //   1099: athrow
    //   1100: aload_1
    //   1101: athrow
    //   1102: aload_0
    //   1103: invokevirtual 277	android/content/Context:getResources	()Landroid/content/res/Resources;
    //   1106: ldc_w 602
    //   1109: invokevirtual 284	android/content/res/Resources:getString	(I)Ljava/lang/String;
    //   1112: iconst_0
    //   1113: iconst_4
    //   1114: invokevirtual 288	java/lang/String:substring	(II)Ljava/lang/String;
    //   1117: invokevirtual 292	java/lang/String:length	()I
    //   1120: iconst_0
    //   1121: iadd
    //   1122: aload_0
    //   1123: invokevirtual 277	android/content/Context:getResources	()Landroid/content/res/Resources;
    //   1126: ldc_w 603
    //   1129: invokevirtual 284	android/content/res/Resources:getString	(I)Ljava/lang/String;
    //   1132: iconst_0
    //   1133: iconst_5
    //   1134: invokevirtual 288	java/lang/String:substring	(II)Ljava/lang/String;
    //   1137: iconst_3
    //   1138: invokevirtual 297	java/lang/String:codePointAt	(I)I
    //   1141: sipush 401
    //   1144: iadd
    //   1145: aload_0
    //   1146: invokevirtual 312	android/content/Context:getApplicationInfo	()Landroid/content/pm/ApplicationInfo;
    //   1149: getfield 317	android/content/pm/ApplicationInfo:targetSdkVersion	I
    //   1152: sipush 30228
    //   1155: iadd
    //   1156: i2c
    //   1157: invokestatic 373	o/O:ˋ	(IIC)Ljava/lang/Object;
    //   1160: checkcast 375	java/lang/Class
    //   1163: ldc_w 583
    //   1166: aconst_null
    //   1167: invokevirtual 380	java/lang/Class:getMethod	(Ljava/lang/String;[Ljava/lang/Class;)Ljava/lang/reflect/Method;
    //   1170: aload 5
    //   1172: aconst_null
    //   1173: invokevirtual 386	java/lang/reflect/Method:invoke	(Ljava/lang/Object;[Ljava/lang/Object;)Ljava/lang/Object;
    //   1176: astore 5
    //   1178: aload 5
    //   1180: ifnonnull +6 -> 1186
    //   1183: goto -1180 -> 3
    //   1186: goto -1177 -> 9
    //   1189: iconst_0
    //   1190: istore_2
    //   1191: goto -865 -> 326
    //   1194: aload_0
    //   1195: invokevirtual 277	android/content/Context:getResources	()Landroid/content/res/Resources;
    //   1198: ldc_w 604
    //   1201: invokevirtual 284	android/content/res/Resources:getString	(I)Ljava/lang/String;
    //   1204: iconst_0
    //   1205: iconst_4
    //   1206: invokevirtual 288	java/lang/String:substring	(II)Ljava/lang/String;
    //   1209: invokevirtual 292	java/lang/String:length	()I
    //   1212: bipush 23
    //   1214: iadd
    //   1215: aload_0
    //   1216: invokevirtual 312	android/content/Context:getApplicationInfo	()Landroid/content/pm/ApplicationInfo;
    //   1219: getfield 317	android/content/pm/ApplicationInfo:targetSdkVersion	I
    //   1222: ldc_w 605
    //   1225: iadd
    //   1226: i2c
    //   1227: aload_0
    //   1228: invokevirtual 312	android/content/Context:getApplicationInfo	()Landroid/content/pm/ApplicationInfo;
    //   1231: getfield 317	android/content/pm/ApplicationInfo:targetSdkVersion	I
    //   1234: bipush 19
    //   1236: isub
    //   1237: invokestatic 256	o/Ly:ˋ	(ICI)Ljava/lang/String;
    //   1240: invokevirtual 260	java/lang/String:intern	()Ljava/lang/String;
    //   1243: invokestatic 265	o/vq:ˊ	(Ljava/lang/String;)V
    //   1246: goto -1046 -> 200
    //   1249: getstatic 26	o/Ly:ʼॱ	I
    //   1252: bipush 79
    //   1254: iadd
    //   1255: istore_2
    //   1256: iload_2
    //   1257: sipush 128
    //   1260: irem
    //   1261: putstatic 28	o/Ly:ˉ	I
    //   1264: iload_2
    //   1265: iconst_2
    //   1266: irem
    //   1267: ifne +6 -> 1273
    //   1270: goto +224 -> 1494
    //   1273: goto +53 -> 1326
    //   1276: bipush 57
    //   1278: istore_2
    //   1279: goto -740 -> 539
    //   1282: getstatic 28	o/Ly:ˉ	I
    //   1285: bipush 13
    //   1287: iadd
    //   1288: istore_2
    //   1289: iload_2
    //   1290: sipush 128
    //   1293: irem
    //   1294: putstatic 26	o/Ly:ʼॱ	I
    //   1297: iload_2
    //   1298: iconst_2
    //   1299: irem
    //   1300: ifeq +6 -> 1306
    //   1303: goto -946 -> 357
    //   1306: goto -735 -> 571
    //   1309: aload_0
    //   1310: getfield 253	o/Ly:ˈ	Lo/FF;
    //   1313: astore 5
    //   1315: aload 5
    //   1317: ifnonnull +6 -> 1323
    //   1320: goto -44 -> 1276
    //   1323: goto -1090 -> 233
    //   1326: goto -1317 -> 9
    //   1329: aload_1
    //   1330: checkcast 607	java/util/Collection
    //   1333: astore 5
    //   1335: goto -1279 -> 56
    //   1338: astore_1
    //   1339: aload_1
    //   1340: athrow
    //   1341: iconst_1
    //   1342: istore_2
    //   1343: goto -1125 -> 218
    //   1346: bipush 37
    //   1348: istore_2
    //   1349: goto -989 -> 360
    //   1352: goto -485 -> 867
    //   1355: aload_1
    //   1356: checkcast 607	java/util/Collection
    //   1359: aload 5
    //   1361: invokeinterface 610 2 0
    //   1366: pop
    //   1367: goto -831 -> 536
    //   1370: aload_1
    //   1371: aload 5
    //   1373: invokevirtual 544	o/FF:ॱ	()Ljava/util/ArrayList;
    //   1376: checkcast 607	java/util/Collection
    //   1379: invokevirtual 614	java/util/ArrayList:addAll	(Ljava/util/Collection;)Z
    //   1382: pop
    //   1383: goto -1231 -> 152
    //   1386: aload_0
    //   1387: getstatic 617	o/Lt$If:shop_locations_url	I
    //   1390: invokevirtual 500	o/Ly:getString	(I)Ljava/lang/String;
    //   1393: astore 5
    //   1395: aload 5
    //   1397: aload_0
    //   1398: invokevirtual 312	android/content/Context:getApplicationInfo	()Landroid/content/pm/ApplicationInfo;
    //   1401: getfield 317	android/content/pm/ApplicationInfo:targetSdkVersion	I
    //   1404: bipush 8
    //   1406: iadd
    //   1407: aload_0
    //   1408: invokevirtual 312	android/content/Context:getApplicationInfo	()Landroid/content/pm/ApplicationInfo;
    //   1411: getfield 317	android/content/pm/ApplicationInfo:targetSdkVersion	I
    //   1414: bipush 25
    //   1416: isub
    //   1417: i2c
    //   1418: aload_0
    //   1419: invokevirtual 277	android/content/Context:getResources	()Landroid/content/res/Resources;
    //   1422: ldc_w 618
    //   1425: invokevirtual 284	android/content/res/Resources:getString	(I)Ljava/lang/String;
    //   1428: iconst_0
    //   1429: iconst_5
    //   1430: invokevirtual 288	java/lang/String:substring	(II)Ljava/lang/String;
    //   1433: invokevirtual 292	java/lang/String:length	()I
    //   1436: iconst_1
    //   1437: isub
    //   1438: invokestatic 256	o/Ly:ˋ	(ICI)Ljava/lang/String;
    //   1441: invokevirtual 260	java/lang/String:intern	()Ljava/lang/String;
    //   1444: invokevirtual 506	java/lang/String:startsWith	(Ljava/lang/String;)Z
    //   1447: ifeq +6 -> 1453
    //   1450: goto +79 -> 1529
    //   1453: goto +6 -> 1459
    //   1456: goto -986 -> 470
    //   1459: aload 6
    //   1461: aload_1
    //   1462: aload 5
    //   1464: invokevirtual 482	o/Ic:ˋ	(Ljava/lang/String;Ljava/lang/String;)Lo/j;
    //   1467: invokevirtual 486	o/j:ˎ	()V
    //   1470: return
    //   1471: aload_0
    //   1472: aload 5
    //   1474: iconst_4
    //   1475: invokevirtual 508	java/lang/String:substring	(I)Ljava/lang/String;
    //   1478: invokespecial 510	o/Ly:ˏ	(Ljava/lang/String;)Ljava/lang/String;
    //   1481: invokevirtual 260	java/lang/String:intern	()Ljava/lang/String;
    //   1484: astore_1
    //   1485: goto -99 -> 1386
    //   1488: bipush 78
    //   1490: istore_2
    //   1491: goto -1131 -> 360
    //   1494: goto -168 -> 1326
    //   1497: goto -1365 -> 132
    //   1500: getstatic 26	o/Ly:ʼॱ	I
    //   1503: istore_3
    //   1504: iload_3
    //   1505: bipush 111
    //   1507: iadd
    //   1508: istore_3
    //   1509: iload_3
    //   1510: sipush 128
    //   1513: irem
    //   1514: putstatic 28	o/Ly:ˉ	I
    //   1517: iload_3
    //   1518: iconst_2
    //   1519: irem
    //   1520: ifne +6 -> 1526
    //   1523: goto -1200 -> 323
    //   1526: goto -685 -> 841
    //   1529: getstatic 28	o/Ly:ˉ	I
    //   1532: bipush 59
    //   1534: iadd
    //   1535: istore_2
    //   1536: iload_2
    //   1537: sipush 128
    //   1540: irem
    //   1541: putstatic 26	o/Ly:ʼॱ	I
    //   1544: iload_2
    //   1545: iconst_2
    //   1546: irem
    //   1547: ifeq +6 -> 1553
    //   1550: goto -1141 -> 409
    //   1553: goto -1144 -> 409
    //   1556: getstatic 28	o/Ly:ˉ	I
    //   1559: bipush 21
    //   1561: iadd
    //   1562: istore_3
    //   1563: iload_3
    //   1564: sipush 128
    //   1567: irem
    //   1568: putstatic 26	o/Ly:ʼॱ	I
    //   1571: iload_3
    //   1572: iconst_2
    //   1573: irem
    //   1574: ifeq +6 -> 1580
    //   1577: goto -80 -> 1497
    //   1580: goto -1448 -> 132
    //   1583: iload_2
    //   1584: ifeq +6 -> 1590
    //   1587: goto -278 -> 1309
    //   1590: goto -1455 -> 135
    // Local variable table:
    //   start	length	slot	name	signature
    //   0	1593	0	this	Ly
    //   0	1593	1	paramView	View
    //   62	1522	2	i	int
    //   1503	71	3	j	int
    //   43	356	4	bool	boolean
    //   9	1464	5	localObject1	Object
    //   165	1295	6	localObject2	Object
    //   28	544	7	localObject3	Object
    //   579	247	8	str	String
    //   666	162	9	localObject4	Object
    // Exception table:
    //   from	to	target	type
    //   688	740	671	finally
    //   760	825	743	finally
    //   1008	1082	991	finally
    //   1102	1178	1085	finally
    //   28	35	1338	java/lang/Exception
    //   35	45	1338	java/lang/Exception
    //   391	398	1338	java/lang/Exception
    //   1500	1504	1338	java/lang/Exception
    //   1509	1517	1338	java/lang/Exception
  }
  
  public void ˋ(ز paramز)
  {
    for (;;)
    {
      int i;
      switch (i)
      {
      default: 
        return;
        i = 67;
        break;
      case 31: 
      case 67: 
        try
        {
          for (;;)
          {
            i = ˉ + 119;
            ʼॱ = i % 128;
            if (i % 2 != 0) {
              break label171;
            }
            break;
            i = ˉ;
            i += 23;
            ʼॱ = i % 128;
            if (i % 2 == 0) {
              break label104;
            }
            break label104;
            i = 4 / 0;
            return;
            return;
            label104:
            vq.ˎ(paramز, ˋ(getPackageName().codePointAt(5) - 100, (char)(getResources().getString(2131755586).substring(0, 4).codePointAt(2) - 11), getApplicationInfo().targetSdkVersion - 16).intern());
            super.ˋ(paramز);
            paramز.ॱ(false);
          }
          label171:
          i = 31;
        }
        catch (Exception paramز)
        {
          throw paramز;
        }
      }
    }
  }
  
  /* Error */
  public int ˎ()
  {
    // Byte code:
    //   0: goto +79 -> 79
    //   3: astore_3
    //   4: aload_3
    //   5: athrow
    //   6: getstatic 631	o/Lt$ˋ:activity_offer_details	I
    //   9: istore_1
    //   10: bipush 41
    //   12: iconst_0
    //   13: idiv
    //   14: istore_2
    //   15: iload_1
    //   16: ireturn
    //   17: iconst_0
    //   18: istore_1
    //   19: goto +34 -> 53
    //   22: getstatic 26	o/Ly:ʼॱ	I
    //   25: istore_1
    //   26: iload_1
    //   27: iconst_1
    //   28: iadd
    //   29: istore_1
    //   30: iload_1
    //   31: sipush 128
    //   34: irem
    //   35: putstatic 28	o/Ly:ˉ	I
    //   38: iload_1
    //   39: iconst_2
    //   40: irem
    //   41: ifne +6 -> 47
    //   44: goto +42 -> 86
    //   47: goto -30 -> 17
    //   50: astore_3
    //   51: aload_3
    //   52: athrow
    //   53: iload_1
    //   54: tableswitch	default:+22->76, 0:+28->82, 1:+-48->6
    //   76: goto -70 -> 6
    //   79: goto -57 -> 22
    //   82: getstatic 631	o/Lt$ˋ:activity_offer_details	I
    //   85: ireturn
    //   86: iconst_1
    //   87: istore_1
    //   88: goto -35 -> 53
    // Local variable table:
    //   start	length	slot	name	signature
    //   0	91	0	this	Ly
    //   9	79	1	i	int
    //   14	1	2	j	int
    //   3	2	3	localException1	Exception
    //   50	2	3	localException2	Exception
    // Exception table:
    //   from	to	target	type
    //   6	10	3	java/lang/Exception
    //   22	26	3	java/lang/Exception
    //   30	38	50	java/lang/Exception
  }
  
  /* Error */
  public final void ॱˋ()
  {
    // Byte code:
    //   0: goto +297 -> 297
    //   3: bipush 72
    //   5: istore_1
    //   6: goto +313 -> 319
    //   9: aload 4
    //   11: invokevirtual 635	o/FF:ʻ	()Z
    //   14: ifeq +6 -> 20
    //   17: goto +125 -> 142
    //   20: goto -17 -> 3
    //   23: aload_0
    //   24: getstatic 638	o/Lt$If:offer_apply_text	I
    //   27: invokevirtual 500	o/Ly:getString	(I)Ljava/lang/String;
    //   30: astore_3
    //   31: aload_3
    //   32: aload_0
    //   33: invokevirtual 277	android/content/Context:getResources	()Landroid/content/res/Resources;
    //   36: ldc_w 639
    //   39: invokevirtual 284	android/content/res/Resources:getString	(I)Ljava/lang/String;
    //   42: iconst_0
    //   43: iconst_4
    //   44: invokevirtual 288	java/lang/String:substring	(II)Ljava/lang/String;
    //   47: iconst_1
    //   48: invokevirtual 297	java/lang/String:codePointAt	(I)I
    //   51: bipush 7
    //   53: iadd
    //   54: aload_0
    //   55: invokevirtual 277	android/content/Context:getResources	()Landroid/content/res/Resources;
    //   58: ldc_w 640
    //   61: invokevirtual 284	android/content/res/Resources:getString	(I)Ljava/lang/String;
    //   64: iconst_0
    //   65: bipush 23
    //   67: invokevirtual 288	java/lang/String:substring	(II)Ljava/lang/String;
    //   70: bipush 10
    //   72: invokevirtual 297	java/lang/String:codePointAt	(I)I
    //   75: sipush 186
    //   78: isub
    //   79: i2c
    //   80: aload_0
    //   81: invokevirtual 343	android/content/Context:getPackageName	()Ljava/lang/String;
    //   84: iconst_5
    //   85: invokevirtual 297	java/lang/String:codePointAt	(I)I
    //   88: bipush 110
    //   90: isub
    //   91: invokestatic 256	o/Ly:ˋ	(ICI)Ljava/lang/String;
    //   94: invokevirtual 260	java/lang/String:intern	()Ljava/lang/String;
    //   97: invokevirtual 506	java/lang/String:startsWith	(Ljava/lang/String;)Z
    //   100: ifeq +6 -> 106
    //   103: goto +1262 -> 1365
    //   106: goto +127 -> 233
    //   109: getstatic 28	o/Ly:ˉ	I
    //   112: bipush 19
    //   114: iadd
    //   115: istore_1
    //   116: iload_1
    //   117: sipush 128
    //   120: irem
    //   121: putstatic 26	o/Ly:ʼॱ	I
    //   124: iload_1
    //   125: iconst_2
    //   126: irem
    //   127: ifeq +6 -> 133
    //   130: goto +981 -> 1111
    //   133: goto +281 -> 414
    //   136: goto +1038 -> 1174
    //   139: goto +26 -> 165
    //   142: bipush 35
    //   144: istore_1
    //   145: goto +174 -> 319
    //   148: aload_0
    //   149: getfield 253	o/Ly:ˈ	Lo/FF;
    //   152: astore 4
    //   154: aload 4
    //   156: ifnonnull +6 -> 162
    //   159: goto +1236 -> 1395
    //   162: goto +118 -> 280
    //   165: aload_3
    //   166: aload_0
    //   167: invokevirtual 277	android/content/Context:getResources	()Landroid/content/res/Resources;
    //   170: ldc_w 641
    //   173: invokevirtual 284	android/content/res/Resources:getString	(I)Ljava/lang/String;
    //   176: iconst_0
    //   177: iconst_5
    //   178: invokevirtual 288	java/lang/String:substring	(II)Ljava/lang/String;
    //   181: invokevirtual 292	java/lang/String:length	()I
    //   184: sipush 171
    //   187: iadd
    //   188: aload_0
    //   189: invokevirtual 312	android/content/Context:getApplicationInfo	()Landroid/content/pm/ApplicationInfo;
    //   192: getfield 317	android/content/pm/ApplicationInfo:targetSdkVersion	I
    //   195: bipush 25
    //   197: isub
    //   198: i2c
    //   199: aload_0
    //   200: invokevirtual 277	android/content/Context:getResources	()Landroid/content/res/Resources;
    //   203: ldc_w 642
    //   206: invokevirtual 284	android/content/res/Resources:getString	(I)Ljava/lang/String;
    //   209: iconst_0
    //   210: iconst_4
    //   211: invokevirtual 288	java/lang/String:substring	(II)Ljava/lang/String;
    //   214: iconst_1
    //   215: invokevirtual 297	java/lang/String:codePointAt	(I)I
    //   218: bipush 13
    //   220: iadd
    //   221: invokestatic 256	o/Ly:ˋ	(ICI)Ljava/lang/String;
    //   224: invokevirtual 260	java/lang/String:intern	()Ljava/lang/String;
    //   227: invokestatic 354	o/vq:ˋ	(Ljava/lang/Object;Ljava/lang/String;)V
    //   230: goto +993 -> 1223
    //   233: aload_3
    //   234: aload_0
    //   235: invokevirtual 343	android/content/Context:getPackageName	()Ljava/lang/String;
    //   238: iconst_1
    //   239: invokevirtual 297	java/lang/String:codePointAt	(I)I
    //   242: bipush 29
    //   244: iadd
    //   245: aload_0
    //   246: invokevirtual 343	android/content/Context:getPackageName	()Ljava/lang/String;
    //   249: iconst_0
    //   250: invokevirtual 297	java/lang/String:codePointAt	(I)I
    //   253: sipush 1888
    //   256: iadd
    //   257: i2c
    //   258: aload_0
    //   259: invokevirtual 312	android/content/Context:getApplicationInfo	()Landroid/content/pm/ApplicationInfo;
    //   262: getfield 317	android/content/pm/ApplicationInfo:targetSdkVersion	I
    //   265: bipush 11
    //   267: iadd
    //   268: invokestatic 256	o/Ly:ˋ	(ICI)Ljava/lang/String;
    //   271: invokevirtual 260	java/lang/String:intern	()Ljava/lang/String;
    //   274: invokestatic 354	o/vq:ˋ	(Ljava/lang/Object;Ljava/lang/String;)V
    //   277: goto +510 -> 787
    //   280: aload 4
    //   282: invokevirtual 635	o/FF:ʻ	()Z
    //   285: ifeq +6 -> 291
    //   288: goto +1002 -> 1290
    //   291: aload 5
    //   293: astore_3
    //   294: goto +487 -> 781
    //   297: goto -188 -> 109
    //   300: ldc_w 644
    //   303: astore 5
    //   305: aload 4
    //   307: invokevirtual 646	o/FF:ॱˊ	()Z
    //   310: ifeq +6 -> 316
    //   313: goto +663 -> 976
    //   316: goto +665 -> 981
    //   319: aload 5
    //   321: astore_3
    //   322: iload_1
    //   323: lookupswitch	default:+25->348, 35:+260->583, 72:+464->787
    //   348: aload 5
    //   350: astore_3
    //   351: goto +436 -> 787
    //   354: aload_0
    //   355: getfield 253	o/Ly:ˈ	Lo/FF;
    //   358: astore 4
    //   360: aload 4
    //   362: ifnonnull +6 -> 368
    //   365: goto +261 -> 626
    //   368: goto -359 -> 9
    //   371: aload_0
    //   372: getfield 253	o/Ly:ˈ	Lo/FF;
    //   375: astore 4
    //   377: aload 4
    //   379: ifnonnull +6 -> 385
    //   382: goto +1020 -> 1402
    //   385: goto +168 -> 553
    //   388: goto +554 -> 942
    //   391: iconst_0
    //   392: istore_1
    //   393: goto +836 -> 1229
    //   396: aload 6
    //   398: invokestatic 265	o/vq:ˊ	(Ljava/lang/String;)V
    //   401: aload 5
    //   403: astore 4
    //   405: aload 6
    //   407: astore_3
    //   408: goto -108 -> 300
    //   411: goto +356 -> 767
    //   414: aload_0
    //   415: invokevirtual 343	android/content/Context:getPackageName	()Ljava/lang/String;
    //   418: invokevirtual 292	java/lang/String:length	()I
    //   421: bipush 16
    //   423: iadd
    //   424: aload_0
    //   425: invokevirtual 312	android/content/Context:getApplicationInfo	()Landroid/content/pm/ApplicationInfo;
    //   428: getfield 317	android/content/pm/ApplicationInfo:targetSdkVersion	I
    //   431: ldc_w 605
    //   434: iadd
    //   435: i2c
    //   436: aload_0
    //   437: invokevirtual 343	android/content/Context:getPackageName	()Ljava/lang/String;
    //   440: invokevirtual 292	java/lang/String:length	()I
    //   443: iconst_5
    //   444: isub
    //   445: invokestatic 256	o/Ly:ˋ	(ICI)Ljava/lang/String;
    //   448: invokevirtual 260	java/lang/String:intern	()Ljava/lang/String;
    //   451: astore 7
    //   453: aload_0
    //   454: getfield 253	o/Ly:ˈ	Lo/FF;
    //   457: astore 8
    //   459: aload 8
    //   461: ifnonnull +6 -> 467
    //   464: goto +726 -> 1190
    //   467: goto -76 -> 391
    //   470: aload_0
    //   471: getstatic 649	o/Lt$If:offer_applied_text	I
    //   474: invokevirtual 500	o/Ly:getString	(I)Ljava/lang/String;
    //   477: astore_3
    //   478: aload_3
    //   479: aload_0
    //   480: invokevirtual 277	android/content/Context:getResources	()Landroid/content/res/Resources;
    //   483: ldc_w 650
    //   486: invokevirtual 284	android/content/res/Resources:getString	(I)Ljava/lang/String;
    //   489: iconst_0
    //   490: iconst_4
    //   491: invokevirtual 288	java/lang/String:substring	(II)Ljava/lang/String;
    //   494: invokevirtual 292	java/lang/String:length	()I
    //   497: bipush 29
    //   499: iadd
    //   500: aload_0
    //   501: invokevirtual 312	android/content/Context:getApplicationInfo	()Landroid/content/pm/ApplicationInfo;
    //   504: getfield 317	android/content/pm/ApplicationInfo:targetSdkVersion	I
    //   507: bipush 25
    //   509: isub
    //   510: i2c
    //   511: aload_0
    //   512: invokevirtual 343	android/content/Context:getPackageName	()Ljava/lang/String;
    //   515: iconst_2
    //   516: invokevirtual 297	java/lang/String:codePointAt	(I)I
    //   519: bipush 42
    //   521: isub
    //   522: invokestatic 256	o/Ly:ˋ	(ICI)Ljava/lang/String;
    //   525: invokevirtual 260	java/lang/String:intern	()Ljava/lang/String;
    //   528: invokevirtual 506	java/lang/String:startsWith	(Ljava/lang/String;)Z
    //   531: ifeq +6 -> 537
    //   534: goto +76 -> 610
    //   537: goto +160 -> 697
    //   540: aload_3
    //   541: invokestatic 265	o/vq:ˊ	(Ljava/lang/String;)V
    //   544: aconst_null
    //   545: arraylength
    //   546: istore_1
    //   547: goto -136 -> 411
    //   550: goto +436 -> 986
    //   553: aload 4
    //   555: invokevirtual 653	o/FF:ʽ	()Z
    //   558: ifeq +6 -> 564
    //   561: goto +723 -> 1284
    //   564: goto +714 -> 1278
    //   567: aload_0
    //   568: aload_3
    //   569: iconst_4
    //   570: invokevirtual 508	java/lang/String:substring	(I)Ljava/lang/String;
    //   573: invokespecial 510	o/Ly:ˏ	(Ljava/lang/String;)Ljava/lang/String;
    //   576: invokevirtual 260	java/lang/String:intern	()Ljava/lang/String;
    //   579: astore_3
    //   580: goto +267 -> 847
    //   583: getstatic 28	o/Ly:ˉ	I
    //   586: bipush 105
    //   588: iadd
    //   589: istore_1
    //   590: iload_1
    //   591: sipush 128
    //   594: irem
    //   595: putstatic 26	o/Ly:ʼॱ	I
    //   598: iload_1
    //   599: iconst_2
    //   600: irem
    //   601: ifeq +6 -> 607
    //   604: goto -54 -> 550
    //   607: goto +379 -> 986
    //   610: aload_0
    //   611: aload_3
    //   612: iconst_4
    //   613: invokevirtual 508	java/lang/String:substring	(I)Ljava/lang/String;
    //   616: invokespecial 510	o/Ly:ˏ	(Ljava/lang/String;)Ljava/lang/String;
    //   619: invokevirtual 260	java/lang/String:intern	()Ljava/lang/String;
    //   622: astore_3
    //   623: goto +74 -> 697
    //   626: getstatic 28	o/Ly:ˉ	I
    //   629: bipush 53
    //   631: iadd
    //   632: istore_1
    //   633: iload_1
    //   634: sipush 128
    //   637: irem
    //   638: putstatic 26	o/Ly:ʼॱ	I
    //   641: iload_1
    //   642: iconst_2
    //   643: irem
    //   644: ifeq +6 -> 650
    //   647: goto -259 -> 388
    //   650: goto +292 -> 942
    //   653: aload_0
    //   654: getfield 253	o/Ly:ˈ	Lo/FF;
    //   657: astore 4
    //   659: aload 4
    //   661: ifnonnull +6 -> 667
    //   664: goto +6 -> 670
    //   667: goto +100 -> 767
    //   670: getstatic 28	o/Ly:ˉ	I
    //   673: bipush 87
    //   675: iadd
    //   676: istore_1
    //   677: iload_1
    //   678: sipush 128
    //   681: irem
    //   682: putstatic 26	o/Ly:ʼॱ	I
    //   685: iload_1
    //   686: iconst_2
    //   687: irem
    //   688: ifeq +6 -> 694
    //   691: goto -151 -> 540
    //   694: goto +664 -> 1358
    //   697: aload_3
    //   698: aload_0
    //   699: invokevirtual 277	android/content/Context:getResources	()Landroid/content/res/Resources;
    //   702: ldc_w 654
    //   705: invokevirtual 284	android/content/res/Resources:getString	(I)Ljava/lang/String;
    //   708: iconst_0
    //   709: iconst_4
    //   710: invokevirtual 288	java/lang/String:substring	(II)Ljava/lang/String;
    //   713: invokevirtual 292	java/lang/String:length	()I
    //   716: bipush 58
    //   718: iadd
    //   719: aload_0
    //   720: invokevirtual 343	android/content/Context:getPackageName	()Ljava/lang/String;
    //   723: invokevirtual 292	java/lang/String:length	()I
    //   726: ldc_w 655
    //   729: iadd
    //   730: i2c
    //   731: aload_0
    //   732: invokevirtual 277	android/content/Context:getResources	()Landroid/content/res/Resources;
    //   735: ldc_w 656
    //   738: invokevirtual 284	android/content/res/Resources:getString	(I)Ljava/lang/String;
    //   741: bipush 16
    //   743: bipush 17
    //   745: invokevirtual 288	java/lang/String:substring	(II)Ljava/lang/String;
    //   748: iconst_0
    //   749: invokevirtual 297	java/lang/String:codePointAt	(I)I
    //   752: bipush 62
    //   754: isub
    //   755: invokestatic 256	o/Ly:ˋ	(ICI)Ljava/lang/String;
    //   758: invokevirtual 260	java/lang/String:intern	()Ljava/lang/String;
    //   761: invokestatic 354	o/vq:ˋ	(Ljava/lang/Object;Ljava/lang/String;)V
    //   764: goto +17 -> 781
    //   767: aload 4
    //   769: invokevirtual 653	o/FF:ʽ	()Z
    //   772: ifeq +6 -> 778
    //   775: goto -305 -> 470
    //   778: goto -630 -> 148
    //   781: goto +6 -> 787
    //   784: astore_3
    //   785: aload_3
    //   786: athrow
    //   787: aload_0
    //   788: getfield 241	o/Ly:ॱˊ	Landroid/databinding/ViewDataBinding;
    //   791: astore 4
    //   793: aload 4
    //   795: aload_0
    //   796: invokevirtual 312	android/content/Context:getApplicationInfo	()Landroid/content/pm/ApplicationInfo;
    //   799: getfield 317	android/content/pm/ApplicationInfo:targetSdkVersion	I
    //   802: bipush 25
    //   804: isub
    //   805: aload_0
    //   806: invokevirtual 312	android/content/Context:getApplicationInfo	()Landroid/content/pm/ApplicationInfo;
    //   809: getfield 317	android/content/pm/ApplicationInfo:targetSdkVersion	I
    //   812: bipush 25
    //   814: isub
    //   815: i2c
    //   816: aload_0
    //   817: invokevirtual 343	android/content/Context:getPackageName	()Ljava/lang/String;
    //   820: invokevirtual 292	java/lang/String:length	()I
    //   823: iconst_3
    //   824: isub
    //   825: invokestatic 256	o/Ly:ˋ	(ICI)Ljava/lang/String;
    //   828: invokevirtual 260	java/lang/String:intern	()Ljava/lang/String;
    //   831: invokestatic 354	o/vq:ˋ	(Ljava/lang/Object;Ljava/lang/String;)V
    //   834: aload 4
    //   836: checkcast 243	o/LD
    //   839: aload_3
    //   840: invokevirtual 658	o/LD:ˋ	(Ljava/lang/String;)V
    //   843: return
    //   844: goto +80 -> 924
    //   847: aload_3
    //   848: aload_0
    //   849: invokevirtual 277	android/content/Context:getResources	()Landroid/content/res/Resources;
    //   852: ldc_w 659
    //   855: invokevirtual 284	android/content/res/Resources:getString	(I)Ljava/lang/String;
    //   858: iconst_0
    //   859: iconst_4
    //   860: invokevirtual 288	java/lang/String:substring	(II)Ljava/lang/String;
    //   863: invokevirtual 292	java/lang/String:length	()I
    //   866: bipush 96
    //   868: iadd
    //   869: aload_0
    //   870: invokevirtual 277	android/content/Context:getResources	()Landroid/content/res/Resources;
    //   873: ldc_w 660
    //   876: invokevirtual 284	android/content/res/Resources:getString	(I)Ljava/lang/String;
    //   879: iconst_0
    //   880: iconst_4
    //   881: invokevirtual 288	java/lang/String:substring	(II)Ljava/lang/String;
    //   884: iconst_0
    //   885: invokevirtual 297	java/lang/String:codePointAt	(I)I
    //   888: iconst_5
    //   889: isub
    //   890: i2c
    //   891: aload_0
    //   892: invokevirtual 277	android/content/Context:getResources	()Landroid/content/res/Resources;
    //   895: ldc_w 661
    //   898: invokevirtual 284	android/content/res/Resources:getString	(I)Ljava/lang/String;
    //   901: iconst_0
    //   902: iconst_4
    //   903: invokevirtual 288	java/lang/String:substring	(II)Ljava/lang/String;
    //   906: invokevirtual 292	java/lang/String:length	()I
    //   909: bipush 36
    //   911: iadd
    //   912: invokestatic 256	o/Ly:ˋ	(ICI)Ljava/lang/String;
    //   915: invokevirtual 260	java/lang/String:intern	()Ljava/lang/String;
    //   918: invokestatic 354	o/vq:ˋ	(Ljava/lang/Object;Ljava/lang/String;)V
    //   921: goto -140 -> 781
    //   924: aload_0
    //   925: aload_3
    //   926: iconst_4
    //   927: invokevirtual 508	java/lang/String:substring	(I)Ljava/lang/String;
    //   930: invokespecial 510	o/Ly:ˏ	(Ljava/lang/String;)Ljava/lang/String;
    //   933: astore_3
    //   934: aload_3
    //   935: invokevirtual 260	java/lang/String:intern	()Ljava/lang/String;
    //   938: astore_3
    //   939: goto -706 -> 233
    //   942: aload_3
    //   943: invokestatic 265	o/vq:ˊ	(Ljava/lang/String;)V
    //   946: goto -937 -> 9
    //   949: getstatic 26	o/Ly:ʼॱ	I
    //   952: bipush 37
    //   954: iadd
    //   955: istore_1
    //   956: iload_1
    //   957: sipush 128
    //   960: irem
    //   961: putstatic 28	o/Ly:ˉ	I
    //   964: iload_1
    //   965: iconst_2
    //   966: irem
    //   967: ifne +6 -> 973
    //   970: goto -834 -> 136
    //   973: goto +201 -> 1174
    //   976: iconst_0
    //   977: istore_1
    //   978: goto +217 -> 1195
    //   981: iconst_1
    //   982: istore_1
    //   983: goto +212 -> 1195
    //   986: getstatic 664	o/Lt$If:offer_activate_text	I
    //   989: istore_1
    //   990: aload_0
    //   991: iload_1
    //   992: invokevirtual 500	o/Ly:getString	(I)Ljava/lang/String;
    //   995: astore_3
    //   996: aload_3
    //   997: aload_0
    //   998: invokevirtual 277	android/content/Context:getResources	()Landroid/content/res/Resources;
    //   1001: ldc_w 665
    //   1004: invokevirtual 284	android/content/res/Resources:getString	(I)Ljava/lang/String;
    //   1007: iconst_0
    //   1008: iconst_4
    //   1009: invokevirtual 288	java/lang/String:substring	(II)Ljava/lang/String;
    //   1012: invokevirtual 292	java/lang/String:length	()I
    //   1015: bipush 29
    //   1017: iadd
    //   1018: aload_0
    //   1019: invokevirtual 277	android/content/Context:getResources	()Landroid/content/res/Resources;
    //   1022: ldc_w 501
    //   1025: invokevirtual 284	android/content/res/Resources:getString	(I)Ljava/lang/String;
    //   1028: iconst_0
    //   1029: iconst_5
    //   1030: invokevirtual 288	java/lang/String:substring	(II)Ljava/lang/String;
    //   1033: invokevirtual 292	java/lang/String:length	()I
    //   1036: iconst_5
    //   1037: isub
    //   1038: i2c
    //   1039: aload_0
    //   1040: invokevirtual 277	android/content/Context:getResources	()Landroid/content/res/Resources;
    //   1043: ldc_w 666
    //   1046: invokevirtual 284	android/content/res/Resources:getString	(I)Ljava/lang/String;
    //   1049: iconst_0
    //   1050: iconst_4
    //   1051: invokevirtual 288	java/lang/String:substring	(II)Ljava/lang/String;
    //   1054: iconst_0
    //   1055: invokevirtual 297	java/lang/String:codePointAt	(I)I
    //   1058: iconst_1
    //   1059: isub
    //   1060: invokestatic 256	o/Ly:ˋ	(ICI)Ljava/lang/String;
    //   1063: invokevirtual 260	java/lang/String:intern	()Ljava/lang/String;
    //   1066: invokevirtual 506	java/lang/String:startsWith	(Ljava/lang/String;)Z
    //   1069: istore_2
    //   1070: iload_2
    //   1071: ifeq +6 -> 1077
    //   1074: goto -125 -> 949
    //   1077: goto -912 -> 165
    //   1080: iload_1
    //   1081: lookupswitch	default:+27->1108, 24:+-727->354, 38:+-1058->23
    //   1108: goto -1085 -> 23
    //   1111: aload_0
    //   1112: invokevirtual 343	android/content/Context:getPackageName	()Ljava/lang/String;
    //   1115: invokevirtual 292	java/lang/String:length	()I
    //   1118: bipush 51
    //   1120: ishr
    //   1121: ldc_w 605
    //   1124: aload_0
    //   1125: invokevirtual 312	android/content/Context:getApplicationInfo	()Landroid/content/pm/ApplicationInfo;
    //   1128: getfield 317	android/content/pm/ApplicationInfo:targetSdkVersion	I
    //   1131: ishr
    //   1132: i2c
    //   1133: bipush 35
    //   1135: aload_0
    //   1136: invokevirtual 343	android/content/Context:getPackageName	()Ljava/lang/String;
    //   1139: invokevirtual 292	java/lang/String:length	()I
    //   1142: isub
    //   1143: invokestatic 256	o/Ly:ˋ	(ICI)Ljava/lang/String;
    //   1146: invokevirtual 260	java/lang/String:intern	()Ljava/lang/String;
    //   1149: astore_3
    //   1150: aload_0
    //   1151: getfield 253	o/Ly:ˈ	Lo/FF;
    //   1154: astore 4
    //   1156: aload 4
    //   1158: ifnonnull +13 -> 1171
    //   1161: aload 4
    //   1163: astore 5
    //   1165: aload_3
    //   1166: astore 6
    //   1168: goto -772 -> 396
    //   1171: goto -871 -> 300
    //   1174: aload_0
    //   1175: aload_3
    //   1176: iconst_4
    //   1177: invokevirtual 508	java/lang/String:substring	(I)Ljava/lang/String;
    //   1180: invokespecial 510	o/Ly:ˏ	(Ljava/lang/String;)Ljava/lang/String;
    //   1183: invokevirtual 260	java/lang/String:intern	()Ljava/lang/String;
    //   1186: astore_3
    //   1187: goto -1048 -> 139
    //   1190: iconst_1
    //   1191: istore_1
    //   1192: goto +37 -> 1229
    //   1195: iload_1
    //   1196: tableswitch	default:+24->1220, 0:+-543->653, 1:+-825->371
    //   1220: goto -849 -> 371
    //   1223: goto -436 -> 787
    //   1226: astore_3
    //   1227: aload_3
    //   1228: athrow
    //   1229: aload 8
    //   1231: astore 4
    //   1233: aload 7
    //   1235: astore_3
    //   1236: aload 8
    //   1238: astore 5
    //   1240: aload 7
    //   1242: astore 6
    //   1244: iload_1
    //   1245: tableswitch	default:+23->1268, 0:+-945->300, 1:+-849->396
    //   1268: aload 8
    //   1270: astore 4
    //   1272: aload 7
    //   1274: astore_3
    //   1275: goto -975 -> 300
    //   1278: bipush 24
    //   1280: istore_1
    //   1281: goto -201 -> 1080
    //   1284: bipush 38
    //   1286: istore_1
    //   1287: goto -207 -> 1080
    //   1290: aload_0
    //   1291: getstatic 669	o/Lt$If:offer_activated_text	I
    //   1294: invokevirtual 500	o/Ly:getString	(I)Ljava/lang/String;
    //   1297: astore_3
    //   1298: aload_3
    //   1299: aload_0
    //   1300: invokevirtual 312	android/content/Context:getApplicationInfo	()Landroid/content/pm/ApplicationInfo;
    //   1303: getfield 317	android/content/pm/ApplicationInfo:targetSdkVersion	I
    //   1306: bipush 8
    //   1308: iadd
    //   1309: aload_0
    //   1310: invokevirtual 277	android/content/Context:getResources	()Landroid/content/res/Resources;
    //   1313: ldc_w 670
    //   1316: invokevirtual 284	android/content/res/Resources:getString	(I)Ljava/lang/String;
    //   1319: iconst_0
    //   1320: iconst_4
    //   1321: invokevirtual 288	java/lang/String:substring	(II)Ljava/lang/String;
    //   1324: invokevirtual 292	java/lang/String:length	()I
    //   1327: iconst_4
    //   1328: isub
    //   1329: i2c
    //   1330: aload_0
    //   1331: invokevirtual 312	android/content/Context:getApplicationInfo	()Landroid/content/pm/ApplicationInfo;
    //   1334: getfield 317	android/content/pm/ApplicationInfo:targetSdkVersion	I
    //   1337: bipush 21
    //   1339: isub
    //   1340: invokestatic 256	o/Ly:ˋ	(ICI)Ljava/lang/String;
    //   1343: invokevirtual 260	java/lang/String:intern	()Ljava/lang/String;
    //   1346: invokevirtual 506	java/lang/String:startsWith	(Ljava/lang/String;)Z
    //   1349: ifeq +6 -> 1355
    //   1352: goto -785 -> 567
    //   1355: goto -508 -> 847
    //   1358: aload_3
    //   1359: invokestatic 265	o/vq:ˊ	(Ljava/lang/String;)V
    //   1362: goto -951 -> 411
    //   1365: getstatic 26	o/Ly:ʼॱ	I
    //   1368: bipush 17
    //   1370: iadd
    //   1371: istore_1
    //   1372: iload_1
    //   1373: sipush 128
    //   1376: irem
    //   1377: putstatic 28	o/Ly:ˉ	I
    //   1380: iload_1
    //   1381: iconst_2
    //   1382: irem
    //   1383: ifne +6 -> 1389
    //   1386: goto -542 -> 844
    //   1389: goto -465 -> 924
    //   1392: goto -839 -> 553
    //   1395: aload_3
    //   1396: invokestatic 265	o/vq:ˊ	(Ljava/lang/String;)V
    //   1399: goto -1119 -> 280
    //   1402: aload_3
    //   1403: invokestatic 265	o/vq:ˊ	(Ljava/lang/String;)V
    //   1406: goto -14 -> 1392
    // Local variable table:
    //   start	length	slot	name	signature
    //   0	1409	0	this	Ly
    //   5	1378	1	i	int
    //   1069	2	2	bool	boolean
    //   30	668	3	localObject1	Object
    //   784	142	3	localException1	Exception
    //   933	254	3	str1	String
    //   1226	2	3	localException2	Exception
    //   1235	168	3	localObject2	Object
    //   9	1262	4	localObject3	Object
    //   291	948	5	localObject4	Object
    //   396	847	6	localObject5	Object
    //   451	822	7	str2	String
    //   457	812	8	localFF	FF
    // Exception table:
    //   from	to	target	type
    //   924	934	784	java/lang/Exception
    //   934	939	784	java/lang/Exception
    //   986	990	784	java/lang/Exception
    //   990	1070	784	java/lang/Exception
    //   934	939	1226	java/lang/Exception
  }
  
  public static final class If
    extends Ik<Void>
  {
    private static long ˋ;
    private static int ˎ;
    private static byte ˏ;
    private static int ॱ;
    
    static
    {
      for (;;)
      {
        int i = 1;
        label37:
        label61:
        do
        {
          i = 0;
          break label37;
          ॱ = 0;
          ˎ = 1;
          ˊ();
          ˏ = -102;
          break label61;
          return;
          i = null.length;
          return;
          switch (i)
          {
          }
          return;
          i = ॱ + 41;
          ˎ = i % 128;
        } while (i % 2 == 0);
      }
    }
    
    If(Context paramContext)
    {
      super();
    }
    
    static void ˊ()
    {
      ˋ = -2227932523860859517L;
    }
    
    /* Error */
    private String ॱ(String paramString)
    {
      // Byte code:
      //   0: goto +228 -> 228
      //   3: astore_1
      //   4: new 49	java/lang/RuntimeException
      //   7: dup
      //   8: aload_1
      //   9: invokespecial 52	java/lang/RuntimeException:<init>	(Ljava/lang/Throwable;)V
      //   12: athrow
      //   13: aload_1
      //   14: bipush 14
      //   16: newarray char
      //   18: dup
      //   19: iconst_0
      //   20: ldc 53
      //   22: castore
      //   23: dup
      //   24: iconst_1
      //   25: ldc 54
      //   27: castore
      //   28: dup
      //   29: iconst_2
      //   30: ldc 55
      //   32: castore
      //   33: dup
      //   34: iconst_3
      //   35: ldc 56
      //   37: castore
      //   38: dup
      //   39: iconst_4
      //   40: ldc 57
      //   42: castore
      //   43: dup
      //   44: iconst_5
      //   45: ldc 58
      //   47: castore
      //   48: dup
      //   49: bipush 6
      //   51: ldc 59
      //   53: castore
      //   54: dup
      //   55: bipush 7
      //   57: ldc 60
      //   59: castore
      //   60: dup
      //   61: bipush 8
      //   63: ldc 61
      //   65: castore
      //   66: dup
      //   67: bipush 9
      //   69: ldc 62
      //   71: castore
      //   72: dup
      //   73: bipush 10
      //   75: ldc 63
      //   77: castore
      //   78: dup
      //   79: bipush 11
      //   81: ldc 64
      //   83: castore
      //   84: dup
      //   85: bipush 12
      //   87: ldc 65
      //   89: castore
      //   90: dup
      //   91: bipush 13
      //   93: ldc 66
      //   95: castore
      //   96: invokestatic 69	o/Ly$If:ॱ	([C)Ljava/lang/String;
      //   99: invokevirtual 75	java/lang/String:intern	()Ljava/lang/String;
      //   102: invokevirtual 79	java/lang/String:getBytes	(Ljava/lang/String;)[B
      //   105: astore 4
      //   107: aload 4
      //   109: arraylength
      //   110: newarray byte
      //   112: astore_1
      //   113: iconst_0
      //   114: istore_2
      //   115: aload 4
      //   117: arraylength
      //   118: istore_3
      //   119: iload_2
      //   120: iload_3
      //   121: if_icmpge +6 -> 127
      //   124: goto +184 -> 308
      //   127: goto +32 -> 159
      //   130: iload_2
      //   131: lookupswitch	default:+25->156, 9:+261->392, 71:+-118->13
      //   156: goto +236 -> 392
      //   159: new 71	java/lang/String
      //   162: dup
      //   163: aload_1
      //   164: bipush 9
      //   166: newarray char
      //   168: dup
      //   169: iconst_0
      //   170: ldc 80
      //   172: castore
      //   173: dup
      //   174: iconst_1
      //   175: ldc 81
      //   177: castore
      //   178: dup
      //   179: iconst_2
      //   180: ldc 82
      //   182: castore
      //   183: dup
      //   184: iconst_3
      //   185: ldc 83
      //   187: castore
      //   188: dup
      //   189: iconst_4
      //   190: ldc 84
      //   192: castore
      //   193: dup
      //   194: iconst_5
      //   195: ldc 85
      //   197: castore
      //   198: dup
      //   199: bipush 6
      //   201: ldc 86
      //   203: castore
      //   204: dup
      //   205: bipush 7
      //   207: ldc 87
      //   209: castore
      //   210: dup
      //   211: bipush 8
      //   213: ldc 88
      //   215: castore
      //   216: invokestatic 69	o/Ly$If:ॱ	([C)Ljava/lang/String;
      //   219: invokevirtual 75	java/lang/String:intern	()Ljava/lang/String;
      //   222: invokespecial 91	java/lang/String:<init>	([BLjava/lang/String;)V
      //   225: astore_1
      //   226: aload_1
      //   227: areturn
      //   228: goto +112 -> 340
      //   231: iconst_0
      //   232: istore_3
      //   233: iload_3
      //   234: tableswitch	default:+22->256, 0:+36->270, 1:+133->367
      //   256: goto +14 -> 270
      //   259: bipush 9
      //   261: istore_2
      //   262: goto -132 -> 130
      //   265: iconst_1
      //   266: istore_3
      //   267: goto -34 -> 233
      //   270: aload_1
      //   271: iload_2
      //   272: aload 4
      //   274: aload 4
      //   276: arraylength
      //   277: iload_2
      //   278: iushr
      //   279: iconst_1
      //   280: isub
      //   281: baload
      //   282: getstatic 29	o/Ly$If:ˏ	B
      //   285: ior
      //   286: i2b
      //   287: bastore
      //   288: iload_2
      //   289: bipush 124
      //   291: iadd
      //   292: istore_2
      //   293: goto +6 -> 299
      //   296: astore_1
      //   297: aload_1
      //   298: athrow
      //   299: goto -184 -> 115
      //   302: bipush 71
      //   304: istore_2
      //   305: goto -175 -> 130
      //   308: getstatic 25	o/Ly$If:ˎ	I
      //   311: istore_3
      //   312: iload_3
      //   313: bipush 49
      //   315: iadd
      //   316: istore_3
      //   317: iload_3
      //   318: sipush 128
      //   321: irem
      //   322: putstatic 23	o/Ly$If:ॱ	I
      //   325: iload_3
      //   326: iconst_2
      //   327: irem
      //   328: ifeq +6 -> 334
      //   331: goto -100 -> 231
      //   334: goto -69 -> 265
      //   337: astore_1
      //   338: aload_1
      //   339: athrow
      //   340: getstatic 23	o/Ly$If:ॱ	I
      //   343: bipush 27
      //   345: iadd
      //   346: istore_2
      //   347: iload_2
      //   348: sipush 128
      //   351: irem
      //   352: putstatic 25	o/Ly$If:ˎ	I
      //   355: iload_2
      //   356: iconst_2
      //   357: irem
      //   358: ifne +6 -> 364
      //   361: goto -102 -> 259
      //   364: goto -62 -> 302
      //   367: aload_1
      //   368: iload_2
      //   369: aload 4
      //   371: aload 4
      //   373: arraylength
      //   374: iload_2
      //   375: isub
      //   376: iconst_1
      //   377: isub
      //   378: baload
      //   379: getstatic 29	o/Ly$If:ˏ	B
      //   382: ixor
      //   383: i2b
      //   384: bastore
      //   385: iload_2
      //   386: iconst_1
      //   387: iadd
      //   388: istore_2
      //   389: goto -90 -> 299
      //   392: aload_1
      //   393: bipush 14
      //   395: newarray char
      //   397: dup
      //   398: iconst_0
      //   399: ldc 53
      //   401: castore
      //   402: dup
      //   403: iconst_1
      //   404: ldc 54
      //   406: castore
      //   407: dup
      //   408: iconst_2
      //   409: ldc 55
      //   411: castore
      //   412: dup
      //   413: iconst_3
      //   414: ldc 56
      //   416: castore
      //   417: dup
      //   418: iconst_4
      //   419: ldc 57
      //   421: castore
      //   422: dup
      //   423: iconst_5
      //   424: ldc 58
      //   426: castore
      //   427: dup
      //   428: bipush 6
      //   430: ldc 59
      //   432: castore
      //   433: dup
      //   434: bipush 7
      //   436: ldc 60
      //   438: castore
      //   439: dup
      //   440: bipush 8
      //   442: ldc 61
      //   444: castore
      //   445: dup
      //   446: bipush 9
      //   448: ldc 62
      //   450: castore
      //   451: dup
      //   452: bipush 10
      //   454: ldc 63
      //   456: castore
      //   457: dup
      //   458: bipush 11
      //   460: ldc 64
      //   462: castore
      //   463: dup
      //   464: bipush 12
      //   466: ldc 65
      //   468: castore
      //   469: dup
      //   470: bipush 13
      //   472: ldc 66
      //   474: castore
      //   475: invokestatic 69	o/Ly$If:ॱ	([C)Ljava/lang/String;
      //   478: invokevirtual 75	java/lang/String:intern	()Ljava/lang/String;
      //   481: invokevirtual 79	java/lang/String:getBytes	(Ljava/lang/String;)[B
      //   484: astore 4
      //   486: aload 4
      //   488: arraylength
      //   489: newarray byte
      //   491: astore_1
      //   492: iconst_1
      //   493: istore_2
      //   494: goto -379 -> 115
      // Local variable table:
      //   start	length	slot	name	signature
      //   0	497	0	this	If
      //   0	497	1	paramString	String
      //   114	380	2	i	int
      //   118	210	3	j	int
      //   105	382	4	arrayOfByte	byte[]
      // Exception table:
      //   from	to	target	type
      //   13	113	3	java/io/UnsupportedEncodingException
      //   115	119	3	java/io/UnsupportedEncodingException
      //   159	226	3	java/io/UnsupportedEncodingException
      //   270	288	3	java/io/UnsupportedEncodingException
      //   367	385	3	java/io/UnsupportedEncodingException
      //   392	492	3	java/io/UnsupportedEncodingException
      //   308	312	296	java/lang/Exception
      //   317	325	337	java/lang/Exception
    }
    
    /* Error */
    private static String ॱ(char[] paramArrayOfChar)
    {
      // Byte code:
      //   0: goto +168 -> 168
      //   3: aload_0
      //   4: iload_1
      //   5: caload
      //   6: aload_0
      //   7: iload_1
      //   8: iconst_4
      //   9: irem
      //   10: caload
      //   11: ixor
      //   12: i2l
      //   13: lstore_3
      //   14: iload_1
      //   15: iconst_4
      //   16: isub
      //   17: i2l
      //   18: lstore 5
      //   20: getstatic 42	o/Ly$If:ˋ	J
      //   23: lstore 7
      //   25: aload_0
      //   26: iload_1
      //   27: lload_3
      //   28: lload 5
      //   30: lload 7
      //   32: lmul
      //   33: lxor
      //   34: l2i
      //   35: i2c
      //   36: castore
      //   37: iload_1
      //   38: iconst_1
      //   39: iadd
      //   40: istore_1
      //   41: goto +56 -> 97
      //   44: bipush 91
      //   46: istore_2
      //   47: iload_2
      //   48: lookupswitch	default:+28->76, 75:+-45->3, 91:+126->174
      //   76: goto -73 -> 3
      //   79: iload_1
      //   80: aload_0
      //   81: arraylength
      //   82: if_icmpge +6 -> 88
      //   85: goto +77 -> 162
      //   88: goto -44 -> 44
      //   91: goto -12 -> 79
      //   94: astore_0
      //   95: aload_0
      //   96: athrow
      //   97: getstatic 23	o/Ly$If:ॱ	I
      //   100: istore_2
      //   101: iload_2
      //   102: bipush 51
      //   104: iadd
      //   105: istore_2
      //   106: iload_2
      //   107: sipush 128
      //   110: irem
      //   111: putstatic 25	o/Ly$If:ˎ	I
      //   114: iload_2
      //   115: iconst_2
      //   116: irem
      //   117: ifne +6 -> 123
      //   120: goto +51 -> 171
      //   123: goto -32 -> 91
      //   126: getstatic 23	o/Ly$If:ॱ	I
      //   129: bipush 37
      //   131: iadd
      //   132: istore_1
      //   133: iload_1
      //   134: sipush 128
      //   137: irem
      //   138: putstatic 25	o/Ly$If:ˎ	I
      //   141: iload_1
      //   142: iconst_2
      //   143: irem
      //   144: ifne +6 -> 150
      //   147: goto +101 -> 248
      //   150: goto +6 -> 156
      //   153: goto -74 -> 79
      //   156: bipush 54
      //   158: istore_1
      //   159: goto +45 -> 204
      //   162: bipush 75
      //   164: istore_2
      //   165: goto -118 -> 47
      //   168: goto -42 -> 126
      //   171: goto -80 -> 91
      //   174: new 71	java/lang/String
      //   177: dup
      //   178: aload_0
      //   179: iconst_4
      //   180: aload_0
      //   181: arraylength
      //   182: iconst_4
      //   183: isub
      //   184: invokespecial 94	java/lang/String:<init>	([CII)V
      //   187: areturn
      //   188: astore_0
      //   189: aload_0
      //   190: athrow
      //   191: getstatic 42	o/Ly$If:ˋ	J
      //   194: aload_0
      //   195: invokestatic 99	o/oL:ˋ	(J[C)[C
      //   198: astore_0
      //   199: iconst_3
      //   200: istore_1
      //   201: goto -48 -> 153
      //   204: iload_1
      //   205: lookupswitch	default:+27->232, 46:+-14->191, 54:+30->235
      //   232: goto -41 -> 191
      //   235: getstatic 42	o/Ly$If:ˋ	J
      //   238: aload_0
      //   239: invokestatic 99	o/oL:ˋ	(J[C)[C
      //   242: astore_0
      //   243: iconst_4
      //   244: istore_1
      //   245: goto -92 -> 153
      //   248: bipush 46
      //   250: istore_1
      //   251: goto -47 -> 204
      // Local variable table:
      //   start	length	slot	name	signature
      //   0	254	0	paramArrayOfChar	char[]
      //   4	247	1	i	int
      //   46	119	2	j	int
      //   13	15	3	l1	long
      //   18	11	5	l2	long
      //   23	8	7	l3	long
      // Exception table:
      //   from	to	target	type
      //   106	114	94	java/lang/Exception
      //   20	25	188	java/lang/Exception
      //   97	101	188	java/lang/Exception
    }
    
    public void ˊ(Fg paramFg)
    {
      break label268;
      int i = 82;
      label268:
      for (;;)
      {
        i = ˎ + 93;
        ॱ = i % 128;
        if (i % 2 != 0) {
          break;
        }
        i = 63;
        switch (i)
        {
        case 63: 
        default: 
          super.ˊ(paramFg);
          paramFg = Ly.ˊ(this.ˊ).ᐝ;
          vq.ˋ(paramFg, ॱ(new char[] { 2850, 5815, 2895, -3210, -8655, 2047, -25270, 5470, -18664, 27985, 29730, -3606, 10004, 1859, -7642, 27615, -13981, -20126, -26571, -14907, 21346, 11112, 13841, -16413, -6805, -14980, -21400, 10674, -28924 }).intern());
          paramFg.setEnabled(true);
          return;
        }
      }
      super.ˊ(paramFg);
      paramFg = Ly.ˊ(this.ˊ).ᐝ;
      vq.ˋ(paramFg, ॱ(new char[] { 2850, 5815, 2895, -3210, -8655, 2047, -25270, 5470, -18664, 27985, 29730, -3606, 10004, 1859, -7642, 27615, -13981, -20126, -26571, -14907, 21346, 11112, 13841, -16413, -6805, -14980, -21400, 10674, -28924 }).intern());
      paramFg.setEnabled(true);
    }
    
    /* Error */
    protected void ˏ(Void paramVoid)
    {
      // Byte code:
      //   0: goto +559 -> 559
      //   3: astore_1
      //   4: aload_1
      //   5: athrow
      //   6: aload_0
      //   7: getfield 34	o/Ly$If:ˊ	Lo/Ly;
      //   10: invokestatic 164	o/Ly:ˋ	(Lo/Ly;)Lo/FF;
      //   13: invokevirtual 170	o/FF:ʽ	()Z
      //   16: ifeq +6 -> 22
      //   19: goto +133 -> 152
      //   22: goto +185 -> 207
      //   25: aload_0
      //   26: getfield 34	o/Ly$If:ˊ	Lo/Ly;
      //   29: invokevirtual 173	o/Ly:ॱˋ	()V
      //   32: aload_0
      //   33: getfield 34	o/Ly$If:ˊ	Lo/Ly;
      //   36: invokestatic 105	o/Ly:ˊ	(Lo/Ly;)Lo/LD;
      //   39: astore_3
      //   40: aload_3
      //   41: bipush 12
      //   43: newarray char
      //   45: dup
      //   46: iconst_0
      //   47: ldc -82
      //   49: castore
      //   50: dup
      //   51: iconst_1
      //   52: ldc -81
      //   54: castore
      //   55: dup
      //   56: iconst_2
      //   57: ldc -80
      //   59: castore
      //   60: dup
      //   61: iconst_3
      //   62: ldc -79
      //   64: castore
      //   65: dup
      //   66: iconst_4
      //   67: ldc -78
      //   69: castore
      //   70: dup
      //   71: iconst_5
      //   72: ldc -77
      //   74: castore
      //   75: dup
      //   76: bipush 6
      //   78: ldc -76
      //   80: castore
      //   81: dup
      //   82: bipush 7
      //   84: ldc -75
      //   86: castore
      //   87: dup
      //   88: bipush 8
      //   90: ldc -74
      //   92: castore
      //   93: dup
      //   94: bipush 9
      //   96: ldc -73
      //   98: castore
      //   99: dup
      //   100: bipush 10
      //   102: ldc -72
      //   104: castore
      //   105: dup
      //   106: bipush 11
      //   108: ldc -71
      //   110: castore
      //   111: invokestatic 69	o/Ly$If:ॱ	([C)Ljava/lang/String;
      //   114: invokevirtual 75	java/lang/String:intern	()Ljava/lang/String;
      //   117: invokestatic 145	o/vq:ˋ	(Ljava/lang/Object;Ljava/lang/String;)V
      //   120: aload_3
      //   121: aload_0
      //   122: getfield 34	o/Ly$If:ˊ	Lo/Ly;
      //   125: invokestatic 164	o/Ly:ˋ	(Lo/Ly;)Lo/FF;
      //   128: invokevirtual 188	o/LD:ˎ	(Lo/FF;)V
      //   131: aload_0
      //   132: getfield 34	o/Ly$If:ˊ	Lo/Ly;
      //   135: checkcast 190	android/content/Context
      //   138: invokestatic 195	o/Ic:ˏ	(Landroid/content/Context;)Lo/Ic;
      //   141: aload_1
      //   142: iconst_0
      //   143: invokevirtual 198	o/Ic:ॱ	(Ljava/lang/String;Z)Lo/j;
      //   146: invokevirtual 202	o/j:ˎ	()V
      //   149: goto +344 -> 493
      //   152: iconst_1
      //   153: istore_2
      //   154: goto +55 -> 209
      //   157: getstatic 25	o/Ly$If:ˎ	I
      //   160: bipush 115
      //   162: iadd
      //   163: istore_2
      //   164: iload_2
      //   165: sipush 128
      //   168: irem
      //   169: putstatic 23	o/Ly$If:ॱ	I
      //   172: iload_2
      //   173: iconst_2
      //   174: irem
      //   175: ifeq +6 -> 181
      //   178: goto +384 -> 562
      //   181: goto +386 -> 567
      //   184: aload_0
      //   185: getfield 34	o/Ly$If:ˊ	Lo/Ly;
      //   188: invokestatic 164	o/Ly:ˋ	(Lo/Ly;)Lo/FF;
      //   191: invokevirtual 205	o/FF:ॱˊ	()Z
      //   194: ifne +6 -> 200
      //   197: goto +237 -> 434
      //   200: goto +239 -> 439
      //   203: return
      //   204: astore_1
      //   205: aload_1
      //   206: athrow
      //   207: iconst_0
      //   208: istore_2
      //   209: iload_2
      //   210: tableswitch	default:+22->232, 0:+53->263, 1:+-53->157
      //   232: goto +31 -> 263
      //   235: iload_2
      //   236: tableswitch	default:+24->260, 0:+416->652, 1:+-211->25
      //   260: goto -235 -> 25
      //   263: aload_0
      //   264: getfield 34	o/Ly$If:ˊ	Lo/Ly;
      //   267: getstatic 210	o/Lt$If:offer_activate_confirmation	I
      //   270: invokevirtual 214	o/Ly:getString	(I)Ljava/lang/String;
      //   273: astore_1
      //   274: aload_1
      //   275: bipush 8
      //   277: newarray char
      //   279: dup
      //   280: iconst_0
      //   281: ldc -41
      //   283: castore
      //   284: dup
      //   285: iconst_1
      //   286: ldc -40
      //   288: castore
      //   289: dup
      //   290: iconst_2
      //   291: ldc -39
      //   293: castore
      //   294: dup
      //   295: iconst_3
      //   296: ldc -38
      //   298: castore
      //   299: dup
      //   300: iconst_4
      //   301: ldc -37
      //   303: castore
      //   304: dup
      //   305: iconst_5
      //   306: ldc -36
      //   308: castore
      //   309: dup
      //   310: bipush 6
      //   312: ldc -35
      //   314: castore
      //   315: dup
      //   316: bipush 7
      //   318: ldc -34
      //   320: castore
      //   321: invokestatic 69	o/Ly$If:ॱ	([C)Ljava/lang/String;
      //   324: invokevirtual 75	java/lang/String:intern	()Ljava/lang/String;
      //   327: invokevirtual 226	java/lang/String:startsWith	(Ljava/lang/String;)Z
      //   330: ifeq +6 -> 336
      //   333: goto +85 -> 418
      //   336: goto -152 -> 184
      //   339: goto -155 -> 184
      //   342: aload_0
      //   343: getfield 34	o/Ly$If:ˊ	Lo/Ly;
      //   346: getstatic 229	o/Lt$If:offer_apply_confirmation	I
      //   349: invokevirtual 214	o/Ly:getString	(I)Ljava/lang/String;
      //   352: astore_1
      //   353: aload_1
      //   354: bipush 8
      //   356: newarray char
      //   358: dup
      //   359: iconst_0
      //   360: ldc -41
      //   362: castore
      //   363: dup
      //   364: iconst_1
      //   365: ldc -40
      //   367: castore
      //   368: dup
      //   369: iconst_2
      //   370: ldc -39
      //   372: castore
      //   373: dup
      //   374: iconst_3
      //   375: ldc -38
      //   377: castore
      //   378: dup
      //   379: iconst_4
      //   380: ldc -37
      //   382: castore
      //   383: dup
      //   384: iconst_5
      //   385: ldc -36
      //   387: castore
      //   388: dup
      //   389: bipush 6
      //   391: ldc -35
      //   393: castore
      //   394: dup
      //   395: bipush 7
      //   397: ldc -34
      //   399: castore
      //   400: invokestatic 69	o/Ly$If:ॱ	([C)Ljava/lang/String;
      //   403: invokevirtual 75	java/lang/String:intern	()Ljava/lang/String;
      //   406: invokevirtual 226	java/lang/String:startsWith	(Ljava/lang/String;)Z
      //   409: ifeq +6 -> 415
      //   412: goto +32 -> 444
      //   415: goto -76 -> 339
      //   418: aload_0
      //   419: aload_1
      //   420: iconst_4
      //   421: invokevirtual 232	java/lang/String:substring	(I)Ljava/lang/String;
      //   424: invokespecial 234	o/Ly$If:ॱ	(Ljava/lang/String;)Ljava/lang/String;
      //   427: invokevirtual 75	java/lang/String:intern	()Ljava/lang/String;
      //   430: astore_1
      //   431: goto -247 -> 184
      //   434: iconst_0
      //   435: istore_2
      //   436: goto -201 -> 235
      //   439: iconst_1
      //   440: istore_2
      //   441: goto -206 -> 235
      //   444: aload_0
      //   445: aload_1
      //   446: iconst_4
      //   447: invokevirtual 232	java/lang/String:substring	(I)Ljava/lang/String;
      //   450: invokespecial 234	o/Ly$If:ॱ	(Ljava/lang/String;)Ljava/lang/String;
      //   453: invokevirtual 75	java/lang/String:intern	()Ljava/lang/String;
      //   456: astore_1
      //   457: goto -118 -> 339
      //   460: bipush 22
      //   462: istore_2
      //   463: iload_2
      //   464: lookupswitch	default:+28->492, 22:+-261->203, 57:+220->684
      //   492: return
      //   493: getstatic 23	o/Ly$If:ॱ	I
      //   496: bipush 77
      //   498: iadd
      //   499: istore_2
      //   500: iload_2
      //   501: sipush 128
      //   504: irem
      //   505: putstatic 25	o/Ly$If:ˎ	I
      //   508: iload_2
      //   509: iconst_2
      //   510: irem
      //   511: ifne +6 -> 517
      //   514: goto +164 -> 678
      //   517: goto -57 -> 460
      //   520: aload_0
      //   521: getfield 34	o/Ly$If:ˊ	Lo/Ly;
      //   524: invokestatic 164	o/Ly:ˋ	(Lo/Ly;)Lo/FF;
      //   527: iconst_1
      //   528: invokevirtual 236	o/FF:ˊ	(Z)V
      //   531: goto -506 -> 25
      //   534: iload_2
      //   535: tableswitch	default:+21->556, 0:+-193->342, 1:+37->572
      //   556: goto +16 -> 572
      //   559: goto -553 -> 6
      //   562: iconst_1
      //   563: istore_2
      //   564: goto -30 -> 534
      //   567: iconst_0
      //   568: istore_2
      //   569: goto -35 -> 534
      //   572: aload_0
      //   573: getfield 34	o/Ly$If:ˊ	Lo/Ly;
      //   576: astore_1
      //   577: getstatic 229	o/Lt$If:offer_apply_confirmation	I
      //   580: istore_2
      //   581: aload_1
      //   582: iload_2
      //   583: invokevirtual 214	o/Ly:getString	(I)Ljava/lang/String;
      //   586: astore_1
      //   587: aload_1
      //   588: bipush 8
      //   590: newarray char
      //   592: dup
      //   593: iconst_0
      //   594: ldc -41
      //   596: castore
      //   597: dup
      //   598: iconst_1
      //   599: ldc -40
      //   601: castore
      //   602: dup
      //   603: iconst_2
      //   604: ldc -39
      //   606: castore
      //   607: dup
      //   608: iconst_3
      //   609: ldc -38
      //   611: castore
      //   612: dup
      //   613: iconst_4
      //   614: ldc -37
      //   616: castore
      //   617: dup
      //   618: iconst_5
      //   619: ldc -36
      //   621: castore
      //   622: dup
      //   623: bipush 6
      //   625: ldc -35
      //   627: castore
      //   628: dup
      //   629: bipush 7
      //   631: ldc -34
      //   633: castore
      //   634: invokestatic 69	o/Ly$If:ॱ	([C)Ljava/lang/String;
      //   637: invokevirtual 75	java/lang/String:intern	()Ljava/lang/String;
      //   640: invokevirtual 226	java/lang/String:startsWith	(Ljava/lang/String;)Z
      //   643: pop
      //   644: new 159	java/lang/NullPointerException
      //   647: dup
      //   648: invokespecial 161	java/lang/NullPointerException:<init>	()V
      //   651: athrow
      //   652: getstatic 23	o/Ly$If:ॱ	I
      //   655: iconst_3
      //   656: iadd
      //   657: istore_2
      //   658: iload_2
      //   659: sipush 128
      //   662: irem
      //   663: putstatic 25	o/Ly$If:ˎ	I
      //   666: iload_2
      //   667: iconst_2
      //   668: irem
      //   669: ifne +6 -> 675
      //   672: goto -152 -> 520
      //   675: goto -155 -> 520
      //   678: bipush 57
      //   680: istore_2
      //   681: goto -218 -> 463
      //   684: aconst_null
      //   685: arraylength
      //   686: istore_2
      //   687: return
      // Local variable table:
      //   start	length	slot	name	signature
      //   0	688	0	this	If
      //   0	688	1	paramVoid	Void
      //   153	534	2	i	int
      //   39	82	3	localLD	LD
      // Exception table:
      //   from	to	target	type
      //   577	581	3	java/lang/Exception
      //   581	587	3	java/lang/Exception
      //   587	652	3	java/lang/Exception
      //   572	577	204	java/lang/Exception
    }
  }
  
  public static final class ˊ
    extends Ik<FF>
  {
    private static short[] ʻ;
    private static int ʼ;
    private static byte[] ʽ;
    private static int ˊ;
    private static byte ˋ;
    private static int ˏ;
    private static int ॱ;
    private static int ᐝ;
    
    static
    {
      for (;;)
      {
        int i = ʼ + 1;
        ᐝ = i % 128;
        if (i % 2 == 0) {
          return;
        }
        return;
        ʼ = 0;
        ᐝ = 1;
        ˊ();
        ˋ = -102;
      }
    }
    
    ˊ(Context paramContext) {}
    
    static void ˊ()
    {
      ˏ = 8;
      ʽ = new byte[] { -2, -55, 16, -61, -57, 20, 0, 10, 6, 6, 21, 6, -28, 54, -4, -5, 43, 7, 16, 53, -24, -26, -25, 38, -92, 126, -30, 116, 125, -26, 34, -101, -47, -90, 126, -30, 116, 125, -58, -100, -20, 125, 40, -128, 53, 78, 61, 65, 33, 68, 75, 59, 77, 49, 89, 31, 50, 91, 54, 77, 60, 52, 89, 51, 47, 61, 73, 72, 69, 54, 60, 3, 117, 71, 51, 69, 78, 47, -13, 108, 26, 111, 71, 51, 69, 78, 15, 109, 61, 78, 14, 31, -35, 64, -58, -40, -124, -42, -33, -128, 68, -67, -85, -64, -40, -124, -42, -33, -96, -66, -114, -33, 2, 122, 42, 122, 35, 126, 117, 64, 34, 116, -3, 76, 96, 85, 88 };
      ˊ = -254793251;
      ॱ = 1064496243;
    }
    
    /* Error */
    private static String ˋ(short paramShort, int paramInt1, byte paramByte, int paramInt2, int paramInt3)
    {
      // Byte code:
      //   0: goto +314 -> 314
      //   3: iconst_1
      //   4: istore 6
      //   6: goto +266 -> 272
      //   9: iconst_1
      //   10: istore 6
      //   12: goto +238 -> 250
      //   15: aload 8
      //   17: invokevirtual 150	java/lang/StringBuilder:toString	()Ljava/lang/String;
      //   20: areturn
      //   21: iconst_0
      //   22: istore 4
      //   24: goto +187 -> 211
      //   27: goto +8 -> 35
      //   30: astore 8
      //   32: aload 8
      //   34: athrow
      //   35: getstatic 137	o/Ly$ˊ:ʽ	[B
      //   38: astore 9
      //   40: aload 9
      //   42: ifnull +6 -> 48
      //   45: goto +421 -> 466
      //   48: goto +452 -> 500
      //   51: iload_3
      //   52: iload 4
      //   54: if_icmpge +6 -> 60
      //   57: goto +286 -> 343
      //   60: goto +459 -> 519
      //   63: iconst_0
      //   64: istore 6
      //   66: goto +251 -> 317
      //   69: getstatic 137	o/Ly$ˊ:ʽ	[B
      //   72: astore 9
      //   74: iload_1
      //   75: iconst_1
      //   76: isub
      //   77: istore 6
      //   79: aload 9
      //   81: iload_1
      //   82: baload
      //   83: iload_0
      //   84: iadd
      //   85: i2b
      //   86: iload_2
      //   87: ixor
      //   88: iload 7
      //   90: iadd
      //   91: i2c
      //   92: istore 5
      //   94: iload 6
      //   96: istore_1
      //   97: goto +252 -> 349
      //   100: iload 6
      //   102: istore_1
      //   103: goto +246 -> 349
      //   106: getstatic 137	o/Ly$ˊ:ʽ	[B
      //   109: ifnull +6 -> 115
      //   112: goto -43 -> 69
      //   115: goto +317 -> 432
      //   118: iconst_1
      //   119: istore 4
      //   121: goto +90 -> 211
      //   124: getstatic 30	o/Ly$ˊ:ʼ	I
      //   127: bipush 123
      //   129: iadd
      //   130: istore 4
      //   132: iload 4
      //   134: sipush 128
      //   137: irem
      //   138: putstatic 32	o/Ly$ˊ:ᐝ	I
      //   141: iload 4
      //   143: iconst_2
      //   144: irem
      //   145: ifne +6 -> 151
      //   148: goto -121 -> 27
      //   151: goto -116 -> 35
      //   154: goto +19 -> 173
      //   157: getstatic 143	o/Ly$ˊ:ॱ	I
      //   160: istore 7
      //   162: iload 6
      //   164: ifeq +6 -> 170
      //   167: goto -164 -> 3
      //   170: goto +256 -> 426
      //   173: iload 6
      //   175: ifeq +6 -> 181
      //   178: goto -54 -> 124
      //   181: goto +58 -> 239
      //   184: iload 6
      //   186: tableswitch	default:+22->208, 0:+-80->106, 1:+-171->15
      //   208: goto -193 -> 15
      //   211: iload 4
      //   213: tableswitch	default:+23->236, 0:+40->253, 1:+194->407
      //   236: goto +17 -> 253
      //   239: iload 4
      //   241: ifle +6 -> 247
      //   244: goto -87 -> 157
      //   247: goto -232 -> 15
      //   250: goto -77 -> 173
      //   253: getstatic 137	o/Ly$ˊ:ʽ	[B
      //   256: iload_1
      //   257: getstatic 143	o/Ly$ˊ:ॱ	I
      //   260: isub
      //   261: baload
      //   262: getstatic 49	o/Ly$ˊ:ˏ	I
      //   265: iadd
      //   266: i2b
      //   267: istore 4
      //   269: goto -30 -> 239
      //   272: iload_1
      //   273: iload 4
      //   275: iadd
      //   276: iconst_2
      //   277: isub
      //   278: iload 7
      //   280: iadd
      //   281: iload 6
      //   283: iadd
      //   284: istore_1
      //   285: getstatic 140	o/Ly$ˊ:ˊ	I
      //   288: istore 6
      //   290: iload 6
      //   292: iload_3
      //   293: iadd
      //   294: i2c
      //   295: istore 5
      //   297: aload 8
      //   299: iload 5
      //   301: invokevirtual 154	java/lang/StringBuilder:append	(C)Ljava/lang/StringBuilder;
      //   304: pop
      //   305: iconst_1
      //   306: istore_3
      //   307: iload 5
      //   309: istore 7
      //   311: goto -260 -> 51
      //   314: goto +60 -> 374
      //   317: iload 6
      //   319: tableswitch	default:+21->340, 0:+49->368, 1:+-310->9
      //   340: goto +28 -> 368
      //   343: iconst_0
      //   344: istore 6
      //   346: goto -162 -> 184
      //   349: aload 8
      //   351: iload 5
      //   353: invokevirtual 154	java/lang/StringBuilder:append	(C)Ljava/lang/StringBuilder;
      //   356: pop
      //   357: iload_3
      //   358: iconst_1
      //   359: iadd
      //   360: istore_3
      //   361: iload 5
      //   363: istore 7
      //   365: goto -314 -> 51
      //   368: iconst_0
      //   369: istore 6
      //   371: goto -217 -> 154
      //   374: new 146	java/lang/StringBuilder
      //   377: dup
      //   378: invokespecial 156	java/lang/StringBuilder:<init>	()V
      //   381: astore 8
      //   383: getstatic 49	o/Ly$ˊ:ˏ	I
      //   386: iload 4
      //   388: iadd
      //   389: istore 6
      //   391: iload 6
      //   393: istore 4
      //   395: iload 6
      //   397: iconst_m1
      //   398: if_icmpne +6 -> 404
      //   401: goto +59 -> 460
      //   404: goto -341 -> 63
      //   407: getstatic 137	o/Ly$ˊ:ʽ	[B
      //   410: getstatic 143	o/Ly$ˊ:ॱ	I
      //   413: iload_1
      //   414: iadd
      //   415: baload
      //   416: getstatic 49	o/Ly$ˊ:ˏ	I
      //   419: iadd
      //   420: i2b
      //   421: istore 4
      //   423: goto -184 -> 239
      //   426: iconst_0
      //   427: istore 6
      //   429: goto -157 -> 272
      //   432: getstatic 158	o/Ly$ˊ:ʻ	[S
      //   435: astore 9
      //   437: iload_1
      //   438: iconst_1
      //   439: isub
      //   440: istore 6
      //   442: aload 9
      //   444: iload_1
      //   445: saload
      //   446: iload_0
      //   447: iadd
      //   448: i2s
      //   449: iload_2
      //   450: ixor
      //   451: iload 7
      //   453: iadd
      //   454: i2c
      //   455: istore 5
      //   457: goto -357 -> 100
      //   460: iconst_1
      //   461: istore 6
      //   463: goto -146 -> 317
      //   466: getstatic 30	o/Ly$ˊ:ʼ	I
      //   469: istore 4
      //   471: iload 4
      //   473: bipush 13
      //   475: iadd
      //   476: istore 4
      //   478: iload 4
      //   480: sipush 128
      //   483: irem
      //   484: putstatic 32	o/Ly$ˊ:ᐝ	I
      //   487: iload 4
      //   489: iconst_2
      //   490: irem
      //   491: ifne +6 -> 497
      //   494: goto -473 -> 21
      //   497: goto -379 -> 118
      //   500: getstatic 158	o/Ly$ˊ:ʻ	[S
      //   503: getstatic 143	o/Ly$ˊ:ॱ	I
      //   506: iload_1
      //   507: iadd
      //   508: saload
      //   509: getstatic 49	o/Ly$ˊ:ˏ	I
      //   512: iadd
      //   513: i2s
      //   514: istore 4
      //   516: goto -277 -> 239
      //   519: iconst_1
      //   520: istore 6
      //   522: goto -338 -> 184
      //   525: astore 8
      //   527: aload 8
      //   529: athrow
      // Local variable table:
      //   start	length	slot	name	signature
      //   0	530	0	paramShort	short
      //   0	530	1	paramInt1	int
      //   0	530	2	paramByte	byte
      //   0	530	3	paramInt2	int
      //   0	530	4	paramInt3	int
      //   92	364	5	i	int
      //   4	517	6	j	int
      //   88	366	7	k	int
      //   15	1	8	localObject1	Object
      //   30	320	8	localException1	Exception
      //   381	1	8	localStringBuilder	StringBuilder
      //   525	3	8	localException2	Exception
      //   38	405	9	localObject2	Object
      // Exception table:
      //   from	to	target	type
      //   35	40	30	java/lang/Exception
      //   285	290	525	java/lang/Exception
      //   297	305	525	java/lang/Exception
      //   466	471	525	java/lang/Exception
      //   478	487	525	java/lang/Exception
    }
    
    private String ˏ(String paramString)
    {
      break label40;
      int j;
      int i = j;
      break label222;
      byte[] arrayOfByte;
      for (;;)
      {
        try
        {
          paramString = paramString.getBytes(ˋ((short)48, -1064496131, (byte)-82, 254793324, -9).intern());
          arrayOfByte = new byte[paramString.length];
          j = 0;
        }
        catch (UnsupportedEncodingException paramString)
        {
          label40:
          label43:
          label49:
          throw new RuntimeException(paramString);
        }
        continue;
        i = 66;
        break;
        paramString = new String(arrayOfByte, ˋ((short)50, -1064496121, (byte)117, 254793336, -9).intern());
        return paramString;
      }
      for (;;)
      {
        arrayOfByte[i] = ((byte)(paramString[((paramString.length << i) + 0)] | ˋ));
        i += 45;
        label222:
        label275:
        label280:
        label286:
        for (;;)
        {
          try
          {
            j = ʼ + 83;
            ᐝ = j % 128;
            if (j % 2 != 0)
            {
              break label286;
              arrayOfByte[i] = ((byte)(paramString[(paramString.length - i - 1)] ^ ˋ));
              i += 1;
              continue;
            }
            switch (i)
            {
            case 16: 
            default: 
              break label275;
              i = ʼ + 81;
              ᐝ = i % 128;
              if (i % 2 == 0) {
                break label280;
              }
              break label43;
              j = paramString.length;
              if (i >= j)
              {
                break label49;
                break label286;
              }
              j = ʼ + 97;
              ᐝ = j % 128;
              if (j % 2 == 0) {
                break label289;
              }
              break;
            }
          }
          catch (Exception paramString)
          {
            throw paramString;
          }
          j = 21;
          break label292;
          i = j;
          continue;
          i = 16;
        }
        label289:
        j = 18;
        label292:
        switch (j)
        {
        }
      }
    }
    
    /* Error */
    public void ˎ(Cv<FF> paramCv, Throwable paramThrowable)
    {
      // Byte code:
      //   0: goto +115 -> 115
      //   3: astore_1
      //   4: aload_1
      //   5: athrow
      //   6: bipush 26
      //   8: istore_3
      //   9: goto +47 -> 56
      //   12: aload 5
      //   14: astore_1
      //   15: iload_3
      //   16: lookupswitch	default:+28->44, 18:+209->225, 68:+111->127
      //   44: aload 5
      //   46: astore_1
      //   47: goto +178 -> 225
      //   50: bipush 18
      //   52: istore_3
      //   53: goto -41 -> 12
      //   56: aload 6
      //   58: astore 5
      //   60: iload_3
      //   61: lookupswitch	default:+27->88, 26:+332->393, 56:+305->366
      //   88: aload 6
      //   90: astore 5
      //   92: goto +301 -> 393
      //   95: aload_0
      //   96: aload 5
      //   98: iconst_4
      //   99: invokevirtual 189	java/lang/String:substring	(I)Ljava/lang/String;
      //   102: invokespecial 191	o/Ly$ˊ:ˏ	(Ljava/lang/String;)Ljava/lang/String;
      //   105: invokevirtual 170	java/lang/String:intern	()Ljava/lang/String;
      //   108: astore_1
      //   109: aconst_null
      //   110: arraylength
      //   111: istore_3
      //   112: goto +48 -> 160
      //   115: goto +202 -> 317
      //   118: bipush 68
      //   120: istore_3
      //   121: goto -109 -> 12
      //   124: astore_1
      //   125: aload_1
      //   126: athrow
      //   127: getstatic 30	o/Ly$ˊ:ʼ	I
      //   130: bipush 33
      //   132: iadd
      //   133: istore_3
      //   134: iload_3
      //   135: sipush 128
      //   138: irem
      //   139: putstatic 32	o/Ly$ˊ:ᐝ	I
      //   142: iload_3
      //   143: iconst_2
      //   144: irem
      //   145: ifne +6 -> 151
      //   148: goto -53 -> 95
      //   151: goto +295 -> 446
      //   154: bipush 56
      //   156: istore_3
      //   157: goto -101 -> 56
      //   160: goto +65 -> 225
      //   163: aload_2
      //   164: bipush -50
      //   166: ldc -64
      //   168: bipush -75
      //   170: ldc -63
      //   172: bipush -9
      //   174: invokestatic 165	o/Ly$ˊ:ˋ	(SIBII)Ljava/lang/String;
      //   177: invokevirtual 170	java/lang/String:intern	()Ljava/lang/String;
      //   180: invokestatic 198	o/vq:ˋ	(Ljava/lang/Object;Ljava/lang/String;)V
      //   183: aload_0
      //   184: getfield 43	o/Ly$ˊ:ˎ	Lo/Ly;
      //   187: getstatic 203	o/Lt$If:could_not_contact_bank_retry	I
      //   190: invokevirtual 206	o/Ly:getString	(I)Ljava/lang/String;
      //   193: astore 5
      //   195: aload 5
      //   197: bipush -15
      //   199: ldc -49
      //   201: bipush -19
      //   203: ldc -48
      //   205: bipush -9
      //   207: invokestatic 165	o/Ly$ˊ:ˋ	(SIBII)Ljava/lang/String;
      //   210: invokevirtual 170	java/lang/String:intern	()Ljava/lang/String;
      //   213: invokevirtual 212	java/lang/String:startsWith	(Ljava/lang/String;)Z
      //   216: ifeq +6 -> 222
      //   219: goto -101 -> 118
      //   222: goto -172 -> 50
      //   225: bipush 65
      //   227: ldc -43
      //   229: bipush 113
      //   231: ldc -63
      //   233: bipush -9
      //   235: invokestatic 165	o/Ly$ˊ:ˋ	(SIBII)Ljava/lang/String;
      //   238: astore 5
      //   240: aload 5
      //   242: invokevirtual 170	java/lang/String:intern	()Ljava/lang/String;
      //   245: astore 5
      //   247: aload_1
      //   248: aload 5
      //   250: invokestatic 198	o/vq:ˋ	(Ljava/lang/Object;Ljava/lang/String;)V
      //   253: aload_0
      //   254: getfield 43	o/Ly$ˊ:ˎ	Lo/Ly;
      //   257: getstatic 216	o/Lt$If:ok	I
      //   260: invokevirtual 206	o/Ly:getString	(I)Ljava/lang/String;
      //   263: astore 6
      //   265: aload 6
      //   267: bipush -15
      //   269: ldc -49
      //   271: bipush -19
      //   273: ldc -48
      //   275: bipush -9
      //   277: invokestatic 165	o/Ly$ˊ:ˋ	(SIBII)Ljava/lang/String;
      //   280: invokevirtual 170	java/lang/String:intern	()Ljava/lang/String;
      //   283: invokevirtual 212	java/lang/String:startsWith	(Ljava/lang/String;)Z
      //   286: istore 4
      //   288: iload 4
      //   290: ifeq +6 -> 296
      //   293: goto -139 -> 154
      //   296: goto -290 -> 6
      //   299: aload_0
      //   300: aload 6
      //   302: iconst_4
      //   303: invokevirtual 189	java/lang/String:substring	(I)Ljava/lang/String;
      //   306: invokespecial 191	o/Ly$ˊ:ˏ	(Ljava/lang/String;)Ljava/lang/String;
      //   309: invokevirtual 170	java/lang/String:intern	()Ljava/lang/String;
      //   312: astore 5
      //   314: goto +79 -> 393
      //   317: aload_0
      //   318: getfield 43	o/Ly$ˊ:ˎ	Lo/Ly;
      //   321: checkcast 218	android/content/Context
      //   324: astore 7
      //   326: aload_0
      //   327: getfield 43	o/Ly$ˊ:ˎ	Lo/Ly;
      //   330: getstatic 221	o/Lt$If:oops	I
      //   333: invokevirtual 206	o/Ly:getString	(I)Ljava/lang/String;
      //   336: astore_2
      //   337: aload_2
      //   338: bipush -15
      //   340: ldc -49
      //   342: bipush -19
      //   344: ldc -48
      //   346: bipush -9
      //   348: invokestatic 165	o/Ly$ˊ:ˋ	(SIBII)Ljava/lang/String;
      //   351: invokevirtual 170	java/lang/String:intern	()Ljava/lang/String;
      //   354: invokevirtual 212	java/lang/String:startsWith	(Ljava/lang/String;)Z
      //   357: ifeq +6 -> 363
      //   360: goto +103 -> 463
      //   363: goto -200 -> 163
      //   366: getstatic 32	o/Ly$ˊ:ᐝ	I
      //   369: bipush 85
      //   371: iadd
      //   372: istore_3
      //   373: iload_3
      //   374: sipush 128
      //   377: irem
      //   378: putstatic 30	o/Ly$ˊ:ʼ	I
      //   381: iload_3
      //   382: iconst_2
      //   383: irem
      //   384: ifeq +6 -> 390
      //   387: goto +92 -> 479
      //   390: goto -91 -> 299
      //   393: aload 5
      //   395: bipush 80
      //   397: ldc -34
      //   399: bipush -47
      //   401: ldc -63
      //   403: bipush -9
      //   405: invokestatic 165	o/Ly$ˊ:ˋ	(SIBII)Ljava/lang/String;
      //   408: invokevirtual 170	java/lang/String:intern	()Ljava/lang/String;
      //   411: invokestatic 198	o/vq:ˋ	(Ljava/lang/Object;Ljava/lang/String;)V
      //   414: new 224	o/B
      //   417: dup
      //   418: aload 7
      //   420: aload_2
      //   421: aload_1
      //   422: aload 5
      //   424: invokespecial 227	o/B:<init>	(Landroid/content/Context;Ljava/lang/String;Ljava/lang/String;Ljava/lang/String;)V
      //   427: new 12	o/Ly$ˊ$If
      //   430: dup
      //   431: aload_0
      //   432: invokespecial 230	o/Ly$ˊ$If:<init>	(Lo/Ly$ˊ;)V
      //   435: checkcast 232	o/ᐸ$ˏ
      //   438: invokevirtual 235	o/B:ॱ	(Lo/ᐸ$ˏ;)Lo/ᐸ$If;
      //   441: invokevirtual 240	o/ᐸ$If:ˏ	()Lo/ᐸ;
      //   444: pop
      //   445: return
      //   446: aload_0
      //   447: aload 5
      //   449: iconst_4
      //   450: invokevirtual 189	java/lang/String:substring	(I)Ljava/lang/String;
      //   453: invokespecial 191	o/Ly$ˊ:ˏ	(Ljava/lang/String;)Ljava/lang/String;
      //   456: invokevirtual 170	java/lang/String:intern	()Ljava/lang/String;
      //   459: astore_1
      //   460: goto -300 -> 160
      //   463: aload_0
      //   464: aload_2
      //   465: iconst_4
      //   466: invokevirtual 189	java/lang/String:substring	(I)Ljava/lang/String;
      //   469: invokespecial 191	o/Ly$ˊ:ˏ	(Ljava/lang/String;)Ljava/lang/String;
      //   472: invokevirtual 170	java/lang/String:intern	()Ljava/lang/String;
      //   475: astore_2
      //   476: goto -313 -> 163
      //   479: goto -180 -> 299
      // Local variable table:
      //   start	length	slot	name	signature
      //   0	482	0	this	ˊ
      //   0	482	1	paramCv	Cv<FF>
      //   0	482	2	paramThrowable	Throwable
      //   8	376	3	i	int
      //   286	3	4	bool	boolean
      //   12	436	5	localObject	Object
      //   56	245	6	str	String
      //   324	95	7	localContext	Context
      // Exception table:
      //   from	to	target	type
      //   247	253	3	java/lang/Exception
      //   225	240	124	java/lang/Exception
      //   240	247	124	java/lang/Exception
      //   247	253	124	java/lang/Exception
      //   253	288	124	java/lang/Exception
    }
    
    /* Error */
    protected void ˎ(FF paramFF)
    {
      // Byte code:
      //   0: goto +178 -> 178
      //   3: iload_2
      //   4: tableswitch	default:+24->28, 0:+177->181, 1:+24->28
      //   28: bipush 35
      //   30: iconst_0
      //   31: idiv
      //   32: istore_2
      //   33: return
      //   34: getstatic 32	o/Ly$ˊ:ᐝ	I
      //   37: istore_2
      //   38: iload_2
      //   39: bipush 103
      //   41: iadd
      //   42: istore_2
      //   43: iload_2
      //   44: sipush 128
      //   47: irem
      //   48: putstatic 30	o/Ly$ˊ:ʼ	I
      //   51: iload_2
      //   52: iconst_2
      //   53: irem
      //   54: ifeq +6 -> 60
      //   57: goto +128 -> 185
      //   60: goto +83 -> 143
      //   63: astore_1
      //   64: aload_1
      //   65: athrow
      //   66: aload_1
      //   67: bipush -109
      //   69: ldc -13
      //   71: bipush 84
      //   73: ldc -12
      //   75: bipush -9
      //   77: invokestatic 165	o/Ly$ˊ:ˋ	(SIBII)Ljava/lang/String;
      //   80: invokevirtual 170	java/lang/String:intern	()Ljava/lang/String;
      //   83: invokestatic 246	o/vq:ˎ	(Ljava/lang/Object;Ljava/lang/String;)V
      //   86: aload_0
      //   87: getfield 43	o/Ly$ˊ:ˎ	Lo/Ly;
      //   90: aload_1
      //   91: invokestatic 249	o/Ly:ˎ	(Lo/Ly;Lo/FF;)V
      //   94: aload_0
      //   95: getfield 43	o/Ly$ˊ:ˎ	Lo/Ly;
      //   98: invokestatic 252	o/Ly:ˊ	(Lo/Ly;)Lo/LD;
      //   101: astore_1
      //   102: aload_1
      //   103: bipush 120
      //   105: ldc -3
      //   107: bipush 123
      //   109: ldc -2
      //   111: bipush -9
      //   113: invokestatic 165	o/Ly$ˊ:ˋ	(SIBII)Ljava/lang/String;
      //   116: invokevirtual 170	java/lang/String:intern	()Ljava/lang/String;
      //   119: invokestatic 198	o/vq:ˋ	(Ljava/lang/Object;Ljava/lang/String;)V
      //   122: aload_1
      //   123: aload_0
      //   124: getfield 43	o/Ly$ˊ:ˎ	Lo/Ly;
      //   127: invokestatic 257	o/Ly:ˋ	(Lo/Ly;)Lo/FF;
      //   130: invokevirtual 261	o/LD:ˎ	(Lo/FF;)V
      //   133: aload_0
      //   134: getfield 43	o/Ly$ˊ:ˎ	Lo/Ly;
      //   137: invokevirtual 264	o/Ly:ॱˋ	()V
      //   140: goto -106 -> 34
      //   143: iconst_0
      //   144: istore_2
      //   145: goto -142 -> 3
      //   148: getstatic 30	o/Ly$ˊ:ʼ	I
      //   151: bipush 67
      //   153: iadd
      //   154: istore_2
      //   155: iload_2
      //   156: sipush 128
      //   159: irem
      //   160: putstatic 32	o/Ly$ˊ:ᐝ	I
      //   163: iload_2
      //   164: iconst_2
      //   165: irem
      //   166: ifne +6 -> 172
      //   169: goto +13 -> 182
      //   172: goto -106 -> 66
      //   175: astore_1
      //   176: aload_1
      //   177: athrow
      //   178: goto -30 -> 148
      //   181: return
      //   182: goto -116 -> 66
      //   185: iconst_1
      //   186: istore_2
      //   187: goto -184 -> 3
      // Local variable table:
      //   start	length	slot	name	signature
      //   0	190	0	this	ˊ
      //   0	190	1	paramFF	FF
      //   3	184	2	i	int
      // Exception table:
      //   from	to	target	type
      //   34	38	63	java/lang/Exception
      //   43	51	175	java/lang/Exception
    }
    
    /* Error */
    public void ˏ()
    {
      // Byte code:
      //   0: goto +259 -> 259
      //   3: iconst_1
      //   4: istore_1
      //   5: goto +102 -> 107
      //   8: astore_2
      //   9: aload_2
      //   10: athrow
      //   11: iconst_0
      //   12: istore_1
      //   13: goto +221 -> 234
      //   16: aload_0
      //   17: getfield 43	o/Ly$ˊ:ˎ	Lo/Ly;
      //   20: invokestatic 252	o/Ly:ˊ	(Lo/Ly;)Lo/LD;
      //   23: astore_2
      //   24: aload_2
      //   25: bipush 120
      //   27: ldc -3
      //   29: bipush 123
      //   31: ldc -2
      //   33: bipush -9
      //   35: invokestatic 165	o/Ly$ˊ:ˋ	(SIBII)Ljava/lang/String;
      //   38: invokevirtual 170	java/lang/String:intern	()Ljava/lang/String;
      //   41: invokestatic 198	o/vq:ˋ	(Ljava/lang/Object;Ljava/lang/String;)V
      //   44: aload_2
      //   45: iconst_0
      //   46: invokevirtual 267	o/LD:ˏ	(Z)V
      //   49: goto +91 -> 140
      //   52: getstatic 30	o/Ly$ˊ:ʼ	I
      //   55: istore_1
      //   56: iload_1
      //   57: bipush 49
      //   59: iadd
      //   60: istore_1
      //   61: iload_1
      //   62: sipush 128
      //   65: irem
      //   66: putstatic 32	o/Ly$ˊ:ᐝ	I
      //   69: iload_1
      //   70: iconst_2
      //   71: irem
      //   72: ifne +6 -> 78
      //   75: goto +187 -> 262
      //   78: goto -75 -> 3
      //   81: getstatic 32	o/Ly$ˊ:ᐝ	I
      //   84: iconst_5
      //   85: iadd
      //   86: istore_1
      //   87: iload_1
      //   88: sipush 128
      //   91: irem
      //   92: putstatic 30	o/Ly$ˊ:ʼ	I
      //   95: iload_1
      //   96: iconst_2
      //   97: irem
      //   98: ifeq +6 -> 104
      //   101: goto +42 -> 143
      //   104: goto -88 -> 16
      //   107: iload_1
      //   108: tableswitch	default:+24->132, 0:+73->181, 1:+72->180
      //   132: goto +49 -> 181
      //   135: iconst_1
      //   136: istore_1
      //   137: goto +97 -> 234
      //   140: goto -88 -> 52
      //   143: aload_0
      //   144: getfield 43	o/Ly$ˊ:ˎ	Lo/Ly;
      //   147: astore_2
      //   148: aload_2
      //   149: invokestatic 252	o/Ly:ˊ	(Lo/Ly;)Lo/LD;
      //   152: astore_2
      //   153: aload_2
      //   154: iconst_5
      //   155: ldc -3
      //   157: bipush 127
      //   159: ldc -2
      //   161: bipush 77
      //   163: invokestatic 165	o/Ly$ˊ:ˋ	(SIBII)Ljava/lang/String;
      //   166: invokevirtual 170	java/lang/String:intern	()Ljava/lang/String;
      //   169: invokestatic 198	o/vq:ˋ	(Ljava/lang/Object;Ljava/lang/String;)V
      //   172: aload_2
      //   173: iconst_0
      //   174: invokevirtual 267	o/LD:ˏ	(Z)V
      //   177: goto -37 -> 140
      //   180: return
      //   181: new 269	java/lang/NullPointerException
      //   184: dup
      //   185: invokespecial 270	java/lang/NullPointerException:<init>	()V
      //   188: athrow
      //   189: aload_0
      //   190: invokespecial 272	o/Ik:ˏ	()V
      //   193: aload_0
      //   194: getfield 43	o/Ly$ˊ:ˎ	Lo/Ly;
      //   197: invokestatic 252	o/Ly:ˊ	(Lo/Ly;)Lo/LD;
      //   200: astore_2
      //   201: aload_2
      //   202: bipush 120
      //   204: ldc -3
      //   206: bipush 123
      //   208: ldc -2
      //   210: bipush -9
      //   212: invokestatic 165	o/Ly$ˊ:ˋ	(SIBII)Ljava/lang/String;
      //   215: invokevirtual 170	java/lang/String:intern	()Ljava/lang/String;
      //   218: invokestatic 198	o/vq:ˋ	(Ljava/lang/Object;Ljava/lang/String;)V
      //   221: aload_2
      //   222: invokevirtual 276	o/LD:ˋॱ	()Lo/FF;
      //   225: ifnull +6 -> 231
      //   228: goto -93 -> 135
      //   231: goto -220 -> 11
      //   234: iload_1
      //   235: tableswitch	default:+21->256, 0:+-95->140, 1:+-154->81
      //   256: goto -175 -> 81
      //   259: goto -70 -> 189
      //   262: iconst_0
      //   263: istore_1
      //   264: goto -157 -> 107
      //   267: astore_2
      //   268: aload_2
      //   269: athrow
      // Local variable table:
      //   start	length	slot	name	signature
      //   0	270	0	this	ˊ
      //   4	260	1	i	int
      //   8	2	2	localException1	Exception
      //   23	199	2	localObject	Object
      //   267	2	2	localException2	Exception
      // Exception table:
      //   from	to	target	type
      //   61	69	8	java/lang/Exception
      //   143	148	8	java/lang/Exception
      //   148	153	8	java/lang/Exception
      //   52	56	267	java/lang/Exception
    }
    
    static final class If
      implements ᐸ.ˏ
    {
      private static int ʻ;
      private static char ˊ;
      private static int ˋ = 0;
      private static int ˎ = 0;
      private static long ॱ;
      
      static
      {
        ʻ = 1;
        ˊ = '櫶';
        ॱ = 0L;
      }
      
      If(Ly.ˊ paramˊ) {}
      
      private static String ˎ(char[] paramArrayOfChar1, char paramChar, char[] paramArrayOfChar2, int paramInt, char[] paramArrayOfChar3)
      {
        break label254;
        for (;;)
        {
          switch (paramInt)
          {
          default: 
            break label79;
            paramInt = 99;
          }
        }
        label41:
        label79:
        label251:
        label252:
        label254:
        for (;;)
        {
          char c = ˋ + 39;
          ʻ = c % '';
          if (c % '\002' == 0) {
            break label41;
          }
          for (;;)
          {
            paramInt = 1;
            break;
            char[] arrayOfChar;
            try
            {
              oJ.ˏ(paramArrayOfChar1, paramArrayOfChar3, paramChar);
              paramInt = paramArrayOfChar2[paramChar];
              int i = paramArrayOfChar1[((paramChar + '\003') % 4)];
              l1 = paramInt ^ i;
              l2 = ॱ;
            }
            catch (Exception paramArrayOfChar1)
            {
              long l1;
              long l2;
              throw paramArrayOfChar1;
            }
            try
            {
              arrayOfChar[paramChar] = ((char)(int)(l1 ^ l2 ^ ˎ ^ ˊ));
              paramChar += '\001';
            }
            catch (Exception paramArrayOfChar1)
            {
              throw paramArrayOfChar1;
            }
            return new String(arrayOfChar);
            for (;;)
            {
              break label251;
              paramArrayOfChar1 = (char[])paramArrayOfChar1.clone();
              paramArrayOfChar3 = (char[])paramArrayOfChar3.clone();
              paramArrayOfChar1[0] = ((char)(paramArrayOfChar1[0] ^ paramChar));
              paramArrayOfChar3[2] = ((char)(paramArrayOfChar3[2] + (char)paramInt));
              c = paramArrayOfChar2.length;
              arrayOfChar = new char[c];
              paramChar = '\000';
              break;
              paramInt = ˋ + 61;
              ʻ = paramInt % 128;
              if (paramInt % 2 != 0) {
                break label251;
              }
            }
            for (;;)
            {
              if (paramChar < c) {
                break label252;
              }
              break;
            }
          }
        }
      }
      
      public final void ˋ(ᐸ paramᐸ, ะ paramะ)
      {
        break label445;
        return;
        int i;
        switch (i)
        {
        case 46: 
        default: 
          return;
          for (;;)
          {
            label33:
            vq.ˎ(paramᐸ, ˎ(new char[] { -29114, 9887, -2472, 23646 }, '\000', new char[] { 30240, 23744, -12725, 5786, 4999, -15091, -13585, 3114, 9383, 24430, -28360, 24208, 11485, 6857, 25143, -29454, -30316, 4775, 16389, -2877, -8930, 24457, 19434 }, 1478926222, new char[] { 0, 0, 0, 0 }).intern());
            vq.ˎ(paramะ, ˎ(new char[] { -12080, -13629, -31887, 31922 }, '\000', new char[] { 2490, -7182, 5972, 16486, 23269, -19435, 7898, 13313, 24582, 30472, 20090, -9258, -27912, -30862, -20686, -7620, 16341, -20741, -7941, -28906, -21381, 3484, -27418 }, 1909113808, new char[] { 0, 0, 0, 0 }).intern());
            this.ˏ.ˎ.finish();
            break label454;
            label436:
            i = 46;
            break;
            label445:
            label454:
            label481:
            do
            {
              break label33;
              break label481;
              do
              {
                i = 42;
                break;
                i = ʻ + 79;
                ˋ = i % 128;
              } while (i % 2 != 0);
              break label436;
              i = ˋ + 119;
              ʻ = i % 128;
            } while (i % 2 == 0);
          }
        }
        throw new NullPointerException();
      }
    }
  }
}
