package o;

import android.content.Context;
import android.content.Intent;
import android.content.pm.ApplicationInfo;
import android.content.res.Resources;
import android.graphics.PorterDuff.Mode;
import android.graphics.drawable.Drawable;
import android.os.Parcelable;
import android.view.MenuItem;
import android.widget.ProgressBar;
import com.insidesecure.hce.MatrixHCECard;
import java.io.UnsupportedEncodingException;
import java.util.ArrayList;

public class LY
  extends Mg<Mq>
{
  private static int ʼॱ;
  private static int ʽॱ;
  private static byte ʾ;
  private static int ˈ;
  
  /* Error */
  static
  {
    // Byte code:
    //   0: goto +31 -> 31
    //   3: astore_1
    //   4: aload_1
    //   5: athrow
    //   6: getstatic 23	o/LY:ˈ	I
    //   9: bipush 47
    //   11: iadd
    //   12: istore_0
    //   13: iload_0
    //   14: sipush 128
    //   17: irem
    //   18: putstatic 25	o/LY:ʽॱ	I
    //   21: iload_0
    //   22: iconst_2
    //   23: irem
    //   24: ifne +6 -> 30
    //   27: goto +26 -> 53
    //   30: return
    //   31: iconst_0
    //   32: putstatic 23	o/LY:ˈ	I
    //   35: iconst_1
    //   36: putstatic 25	o/LY:ʽॱ	I
    //   39: invokestatic 27	o/LY:ʾ	()V
    //   42: bipush -102
    //   44: putstatic 29	o/LY:ʾ	B
    //   47: goto -41 -> 6
    //   50: astore_1
    //   51: aload_1
    //   52: athrow
    //   53: return
    // Local variable table:
    //   start	length	slot	name	signature
    //   12	12	0	i	int
    //   3	2	1	localException1	Exception
    //   50	2	1	localException2	Exception
    // Exception table:
    //   from	to	target	type
    //   13	21	3	java/lang/Exception
    //   6	13	50	java/lang/Exception
    //   13	21	50	java/lang/Exception
  }
  
  public LY() {}
  
  static void ʾ()
  {
    ʼॱ = 183;
  }
  
  private void ˉ()
  {
    int i;
    for (;;)
    {
      ((Mq)this.ॱˊ).ʼ.ᐝ().ˎ(new ڏ.ˏ()
      {
        public void ˊ(int paramAnonymousInt) {}
        
        public void ˋ(int paramAnonymousInt1, float paramAnonymousFloat, int paramAnonymousInt2) {}
        
        public void ॱ(int paramAnonymousInt)
        {
          LY.ˋ(LY.this);
        }
      });
      break;
      switch (i)
      {
      default: 
        return;
      }
    }
    for (;;)
    {
      i = 28;
      break;
      i = 54 / 0;
      return;
      do
      {
        i = 4;
        break;
        i = ʽॱ + 83;
        ˈ = i % 128;
      } while (i % 2 != 0);
    }
  }
  
  private static String ˊ(int paramInt1, int paramInt2, char[] paramArrayOfChar, int paramInt3, boolean paramBoolean)
  {
    break label331;
    label35:
    label38:
    char[] arrayOfChar;
    int i;
    for (;;)
    {
      switch (paramInt3)
      {
      default: 
        break;
        break label140;
        arrayOfChar[i] = ((char)(paramInt1 + paramArrayOfChar[i]));
        j = arrayOfChar[i];
        try
        {
          k = ʼॱ;
          arrayOfChar[i] = ((char)(j - k));
          i += 1;
        }
        catch (Exception paramArrayOfChar)
        {
          throw paramArrayOfChar;
        }
        paramInt3 = ʽॱ + 99;
        ˈ = paramInt3 % 128;
        if (paramInt3 % 2 != 0) {
          break label215;
        }
      case 58: 
        label137:
        label140:
        while (paramInt1 < paramInt2)
        {
          int j;
          int k;
          paramInt3 = 20;
          break label300;
          paramArrayOfChar[paramInt1] = arrayOfChar[(paramInt2 + paramInt1 - 1)];
          paramInt1 += 9;
          break;
          break label250;
        }
        break label348;
        break label179;
        paramInt3 = 9;
      }
    }
    for (;;)
    {
      if (paramInt3 <= 0)
      {
        break label334;
        label170:
        paramArrayOfChar = new char[paramInt2];
        paramInt1 = 0;
        break label140;
        label179:
        return new String(paramArrayOfChar);
      }
      paramInt1 = ˈ + 85;
      ʽॱ = paramInt1 % 128;
      if (paramInt1 % 2 == 0) {
        break label137;
      }
      break label250;
      label215:
      paramInt3 = 58;
      break;
      label221:
      arrayOfChar = new char[paramInt2];
      i = 0;
      break label288;
      paramArrayOfChar[paramInt1] = arrayOfChar[(paramInt2 - paramInt1 - 1)];
      paramInt1 += 1;
      break label35;
      label250:
      paramArrayOfChar = new char[paramInt2];
      System.arraycopy(arrayOfChar, 0, paramArrayOfChar, 0, paramInt2);
      System.arraycopy(paramArrayOfChar, 0, arrayOfChar, paramInt2 - paramInt3, paramInt3);
      System.arraycopy(paramArrayOfChar, paramInt3, arrayOfChar, 0, paramInt2 - paramInt3);
      break label334;
      label288:
      if (i < paramInt2) {
        break label38;
      }
    }
    for (;;)
    {
      label300:
      switch (paramInt3)
      {
      }
      break;
      label331:
      break label221;
      label334:
      if (paramBoolean) {
        break label170;
      }
      paramArrayOfChar = arrayOfChar;
      break;
      label348:
      paramInt3 = 77;
    }
  }
  
  /* Error */
  private void ˊˋ()
  {
    // Byte code:
    //   0: goto +307 -> 307
    //   3: bipush 59
    //   5: istore_1
    //   6: goto +272 -> 278
    //   9: iload_1
    //   10: lookupswitch	default:+26->36, 47:+29->39, 60:+134->144
    //   36: goto +108 -> 144
    //   39: aload_0
    //   40: getfield 40	o/LY:ॱˊ	Landroid/databinding/ViewDataBinding;
    //   43: checkcast 42	o/Mq
    //   46: aload_0
    //   47: getfield 40	o/LY:ॱˊ	Landroid/databinding/ViewDataBinding;
    //   50: checkcast 42	o/Mq
    //   53: getfield 46	o/Mq:ʼ	Lo/KZ;
    //   56: invokevirtual 79	o/KZ:ॱ	()Ljava/util/List;
    //   59: invokestatic 85	o/an:ˏ	(Ljava/util/Collection;)Z
    //   62: invokevirtual 88	o/Mq:ˎ	(Z)V
    //   65: aload_0
    //   66: getfield 40	o/LY:ॱˊ	Landroid/databinding/ViewDataBinding;
    //   69: checkcast 42	o/Mq
    //   72: invokevirtual 92	o/Mq:ͺ	()Z
    //   75: ifne +6 -> 81
    //   78: goto +142 -> 220
    //   81: goto +41 -> 122
    //   84: bipush 47
    //   86: istore_1
    //   87: goto -78 -> 9
    //   90: aload_0
    //   91: getfield 40	o/LY:ॱˊ	Landroid/databinding/ViewDataBinding;
    //   94: checkcast 42	o/Mq
    //   97: getfield 46	o/Mq:ʼ	Lo/KZ;
    //   100: aload 4
    //   102: invokestatic 98	java/util/Collections:singletonList	(Ljava/lang/Object;)Ljava/util/List;
    //   105: invokevirtual 102	o/KZ:setCards	(Ljava/util/List;)V
    //   108: aload_0
    //   109: getfield 40	o/LY:ॱˊ	Landroid/databinding/ViewDataBinding;
    //   112: checkcast 42	o/Mq
    //   115: iconst_1
    //   116: invokevirtual 104	o/Mq:ˊ	(Z)V
    //   119: goto +230 -> 349
    //   122: iconst_0
    //   123: istore_1
    //   124: goto +104 -> 228
    //   127: aload_0
    //   128: invokespecial 107	o/LY:ˍ	()V
    //   131: return
    //   132: bipush 37
    //   134: istore_1
    //   135: goto +143 -> 278
    //   138: astore_2
    //   139: aload_2
    //   140: athrow
    //   141: goto -102 -> 39
    //   144: aload 4
    //   146: ifnull +6 -> 152
    //   149: goto -59 -> 90
    //   152: goto -113 -> 39
    //   155: getstatic 25	o/LY:ʽॱ	I
    //   158: bipush 25
    //   160: iadd
    //   161: istore_1
    //   162: iload_1
    //   163: sipush 128
    //   166: irem
    //   167: putstatic 23	o/LY:ˈ	I
    //   170: iload_1
    //   171: iconst_2
    //   172: irem
    //   173: ifeq +6 -> 179
    //   176: goto +134 -> 310
    //   179: goto -52 -> 127
    //   182: aload_0
    //   183: invokespecial 110	o/LY:ˋˋ	()V
    //   186: aload_0
    //   187: getfield 40	o/LY:ॱˊ	Landroid/databinding/ViewDataBinding;
    //   190: astore_2
    //   191: aload_2
    //   192: checkcast 42	o/Mq
    //   195: astore_2
    //   196: aload_2
    //   197: getfield 46	o/Mq:ʼ	Lo/KZ;
    //   200: astore_2
    //   201: aload_2
    //   202: invokevirtual 112	o/KZ:ˏ	()Ljava/util/List;
    //   205: pop
    //   206: aload_0
    //   207: getfield 40	o/LY:ॱˊ	Landroid/databinding/ViewDataBinding;
    //   210: checkcast 42	o/Mq
    //   213: iconst_1
    //   214: invokevirtual 104	o/Mq:ˊ	(Z)V
    //   217: goto -76 -> 141
    //   220: iconst_1
    //   221: istore_1
    //   222: goto +6 -> 228
    //   225: astore_2
    //   226: aload_2
    //   227: athrow
    //   228: iload_1
    //   229: tableswitch	default:+23->252, 0:+-98->131, 1:+-74->155
    //   252: return
    //   253: goto +9 -> 262
    //   256: bipush 60
    //   258: istore_1
    //   259: goto -250 -> 9
    //   262: goto -223 -> 39
    //   265: aload_3
    //   266: getstatic 118	o/FV:ACCEPTED	Lo/FV;
    //   269: if_acmpne +6 -> 275
    //   272: goto -16 -> 256
    //   275: goto -191 -> 84
    //   278: iload_1
    //   279: lookupswitch	default:+25->304, 37:+-97->182, 59:+-14->265
    //   304: goto -122 -> 182
    //   307: goto +6 -> 313
    //   310: goto -183 -> 127
    //   313: aload_0
    //   314: getfield 40	o/LY:ॱˊ	Landroid/databinding/ViewDataBinding;
    //   317: checkcast 42	o/Mq
    //   320: invokevirtual 122	o/Mq:ˏॱ	()Lo/FW;
    //   323: astore_2
    //   324: aload_2
    //   325: getfield 127	o/FW:status	Lo/FV;
    //   328: astore_3
    //   329: aload_0
    //   330: aload_2
    //   331: invokevirtual 130	o/LY:ˏ	(Lo/FW;)Lcom/insidesecure/hce/MatrixHCECard;
    //   334: astore 4
    //   336: aload_2
    //   337: invokevirtual 132	o/FW:ʽॱ	()Z
    //   340: ifeq +6 -> 346
    //   343: goto -211 -> 132
    //   346: goto -343 -> 3
    //   349: getstatic 23	o/LY:ˈ	I
    //   352: bipush 91
    //   354: iadd
    //   355: istore_1
    //   356: iload_1
    //   357: sipush 128
    //   360: irem
    //   361: putstatic 25	o/LY:ʽॱ	I
    //   364: iload_1
    //   365: iconst_2
    //   366: irem
    //   367: ifne +6 -> 373
    //   370: goto -117 -> 253
    //   373: goto -111 -> 262
    // Local variable table:
    //   start	length	slot	name	signature
    //   0	376	0	this	LY
    //   5	362	1	i	int
    //   138	2	2	localException1	Exception
    //   190	12	2	localObject1	Object
    //   225	2	2	localException2	Exception
    //   323	14	2	localFW	FW
    //   265	64	3	localFV	FV
    //   100	235	4	localObject2	Object
    // Exception table:
    //   from	to	target	type
    //   186	191	138	java/lang/Exception
    //   191	196	138	java/lang/Exception
    //   196	201	138	java/lang/Exception
    //   201	206	138	java/lang/Exception
    //   206	217	138	java/lang/Exception
    //   191	196	225	java/lang/Exception
  }
  
  private void ˊᐝ()
  {
    break label94;
    for (;;)
    {
      try
      {
        localObject = this.ॱˊ;
        localObject = (Mq)localObject;
        localCoN = this.ˊˊ;
      }
      catch (Exception localException1)
      {
        Object localObject;
        coN localCoN;
        throw localException1;
      }
      try
      {
        ((Mq)localObject).ˎ(localCoN);
        ((Mq)this.ॱˊ).ʻ.getIndeterminateDrawable().setColorFilter(ᔆ.ˊ(this, LV.ˊ.romanian_yellow), PorterDuff.Mode.SRC_IN);
        return;
      }
      catch (Exception localException2)
      {
        throw localException2;
      }
      switch (i)
      {
      }
    }
    for (;;)
    {
      i = 26;
      break;
      label94:
      do
      {
        i = 61;
        break;
        i = ʽॱ + 95;
        ˈ = i % 128;
      } while (i % 2 != 0);
    }
    ((Mq)this.ॱˊ).ˎ(this.ˊˊ);
    ((Mq)this.ॱˊ).ʻ.getIndeterminateDrawable().setColorFilter(ᔆ.ˊ(this, LV.ˊ.romanian_yellow), PorterDuff.Mode.SRC_IN);
    int i = null.length;
  }
  
  /* Error */
  private String ˋ(FV paramFV)
  {
    // Byte code:
    //   0: goto +204 -> 204
    //   3: goto +259 -> 262
    //   6: iload_2
    //   7: lookupswitch	default:+25->32, 19:+27->34, 47:+190->197
    //   32: aload_1
    //   33: areturn
    //   34: aload_0
    //   35: aload_1
    //   36: iconst_4
    //   37: invokevirtual 178	java/lang/String:substring	(I)Ljava/lang/String;
    //   40: invokespecial 181	o/LY:ˎ	(Ljava/lang/String;)Ljava/lang/String;
    //   43: invokevirtual 185	java/lang/String:intern	()Ljava/lang/String;
    //   46: areturn
    //   47: getstatic 23	o/LY:ˈ	I
    //   50: bipush 123
    //   52: iadd
    //   53: istore_2
    //   54: iload_2
    //   55: sipush 128
    //   58: irem
    //   59: putstatic 25	o/LY:ʽॱ	I
    //   62: iload_2
    //   63: iconst_2
    //   64: irem
    //   65: ifne +6 -> 71
    //   68: goto -65 -> 3
    //   71: goto +191 -> 262
    //   74: astore_1
    //   75: aload_1
    //   76: athrow
    //   77: aload_0
    //   78: getstatic 190	o/LV$If:transaction_is_canceled	I
    //   81: invokevirtual 193	o/LY:getString	(I)Ljava/lang/String;
    //   84: astore_1
    //   85: aload_0
    //   86: invokevirtual 199	android/content/Context:getApplicationInfo	()Landroid/content/pm/ApplicationInfo;
    //   89: getfield 204	android/content/pm/ApplicationInfo:targetSdkVersion	I
    //   92: istore_2
    //   93: aload_0
    //   94: invokevirtual 199	android/content/Context:getApplicationInfo	()Landroid/content/pm/ApplicationInfo;
    //   97: getfield 204	android/content/pm/ApplicationInfo:targetSdkVersion	I
    //   100: istore_3
    //   101: aload_0
    //   102: invokevirtual 199	android/content/Context:getApplicationInfo	()Landroid/content/pm/ApplicationInfo;
    //   105: getfield 204	android/content/pm/ApplicationInfo:targetSdkVersion	I
    //   108: istore 4
    //   110: aload_1
    //   111: iload_2
    //   112: sipush 171
    //   115: iadd
    //   116: iload_3
    //   117: bipush 21
    //   119: isub
    //   120: iconst_4
    //   121: newarray char
    //   123: dup
    //   124: iconst_0
    //   125: ldc -51
    //   127: castore
    //   128: dup
    //   129: iconst_1
    //   130: ldc -50
    //   132: castore
    //   133: dup
    //   134: iconst_2
    //   135: ldc -49
    //   137: castore
    //   138: dup
    //   139: iconst_3
    //   140: ldc -48
    //   142: castore
    //   143: iload 4
    //   145: bipush 22
    //   147: isub
    //   148: iconst_1
    //   149: invokestatic 210	o/LY:ˊ	(II[CIZ)Ljava/lang/String;
    //   152: invokevirtual 185	java/lang/String:intern	()Ljava/lang/String;
    //   155: invokevirtual 214	java/lang/String:startsWith	(Ljava/lang/String;)Z
    //   158: ifeq +6 -> 164
    //   161: goto +254 -> 415
    //   164: goto +249 -> 413
    //   167: getstatic 25	o/LY:ʽॱ	I
    //   170: bipush 51
    //   172: iadd
    //   173: istore_2
    //   174: iload_2
    //   175: sipush 128
    //   178: irem
    //   179: putstatic 23	o/LY:ˈ	I
    //   182: iload_2
    //   183: iconst_2
    //   184: irem
    //   185: ifeq +6 -> 191
    //   188: goto +66 -> 254
    //   191: goto +8 -> 199
    //   194: goto +219 -> 413
    //   197: aload_1
    //   198: areturn
    //   199: iconst_0
    //   200: istore_2
    //   201: goto +6 -> 207
    //   204: goto -157 -> 47
    //   207: iload_2
    //   208: tableswitch	default:+24->232, 0:+253->461, 1:+-14->194
    //   232: goto -38 -> 194
    //   235: aload_0
    //   236: aload_1
    //   237: iconst_4
    //   238: invokevirtual 178	java/lang/String:substring	(I)Ljava/lang/String;
    //   241: invokespecial 181	o/LY:ˎ	(Ljava/lang/String;)Ljava/lang/String;
    //   244: invokevirtual 185	java/lang/String:intern	()Ljava/lang/String;
    //   247: astore_1
    //   248: goto +183 -> 431
    //   251: astore_1
    //   252: aload_1
    //   253: athrow
    //   254: iconst_1
    //   255: istore_2
    //   256: goto -49 -> 207
    //   259: goto -24 -> 235
    //   262: getstatic 217	o/LY$2:ॱ	[I
    //   265: aload_1
    //   266: invokevirtual 221	o/FV:ordinal	()I
    //   269: iaload
    //   270: tableswitch	default:+30->300, 2:+33->303, 3:+-193->77, 4:+-193->77, 5:+208->478
    //   300: goto +169 -> 469
    //   303: aload_0
    //   304: getstatic 224	o/LV$If:transaction_is_expired	I
    //   307: invokevirtual 193	o/LY:getString	(I)Ljava/lang/String;
    //   310: astore_1
    //   311: aload_0
    //   312: invokevirtual 228	android/content/Context:getResources	()Landroid/content/res/Resources;
    //   315: ldc -27
    //   317: invokevirtual 232	android/content/res/Resources:getString	(I)Ljava/lang/String;
    //   320: iconst_0
    //   321: iconst_4
    //   322: invokevirtual 235	java/lang/String:substring	(II)Ljava/lang/String;
    //   325: iconst_0
    //   326: invokevirtual 239	java/lang/String:codePointAt	(I)I
    //   329: istore_2
    //   330: aload_0
    //   331: invokevirtual 199	android/content/Context:getApplicationInfo	()Landroid/content/pm/ApplicationInfo;
    //   334: getfield 204	android/content/pm/ApplicationInfo:targetSdkVersion	I
    //   337: istore_3
    //   338: aload_0
    //   339: invokevirtual 228	android/content/Context:getResources	()Landroid/content/res/Resources;
    //   342: ldc -16
    //   344: invokevirtual 232	android/content/res/Resources:getString	(I)Ljava/lang/String;
    //   347: iconst_0
    //   348: iconst_4
    //   349: invokevirtual 235	java/lang/String:substring	(II)Ljava/lang/String;
    //   352: invokevirtual 243	java/lang/String:length	()I
    //   355: istore 4
    //   357: aload_1
    //   358: iload_2
    //   359: sipush 191
    //   362: iadd
    //   363: iload_3
    //   364: bipush 21
    //   366: isub
    //   367: iconst_4
    //   368: newarray char
    //   370: dup
    //   371: iconst_0
    //   372: ldc -51
    //   374: castore
    //   375: dup
    //   376: iconst_1
    //   377: ldc -50
    //   379: castore
    //   380: dup
    //   381: iconst_2
    //   382: ldc -49
    //   384: castore
    //   385: dup
    //   386: iconst_3
    //   387: ldc -48
    //   389: castore
    //   390: iload 4
    //   392: iconst_1
    //   393: isub
    //   394: iconst_1
    //   395: invokestatic 210	o/LY:ˊ	(II[CIZ)Ljava/lang/String;
    //   398: invokevirtual 185	java/lang/String:intern	()Ljava/lang/String;
    //   401: invokevirtual 214	java/lang/String:startsWith	(Ljava/lang/String;)Z
    //   404: ifeq +6 -> 410
    //   407: goto +27 -> 434
    //   410: goto +21 -> 431
    //   413: aload_1
    //   414: areturn
    //   415: aload_0
    //   416: aload_1
    //   417: iconst_4
    //   418: invokevirtual 178	java/lang/String:substring	(I)Ljava/lang/String;
    //   421: invokespecial 181	o/LY:ˎ	(Ljava/lang/String;)Ljava/lang/String;
    //   424: invokevirtual 185	java/lang/String:intern	()Ljava/lang/String;
    //   427: astore_1
    //   428: goto -261 -> 167
    //   431: goto +169 -> 600
    //   434: getstatic 25	o/LY:ʽॱ	I
    //   437: bipush 9
    //   439: iadd
    //   440: istore_2
    //   441: iload_2
    //   442: sipush 128
    //   445: irem
    //   446: putstatic 23	o/LY:ˈ	I
    //   449: iload_2
    //   450: iconst_2
    //   451: irem
    //   452: ifeq +6 -> 458
    //   455: goto -196 -> 259
    //   458: goto -223 -> 235
    //   461: aload_1
    //   462: areturn
    //   463: bipush 19
    //   465: istore_2
    //   466: goto -460 -> 6
    //   469: ldc -11
    //   471: areturn
    //   472: bipush 47
    //   474: istore_2
    //   475: goto -469 -> 6
    //   478: aload_0
    //   479: getstatic 248	o/LV$If:transaction_is_failed	I
    //   482: invokevirtual 193	o/LY:getString	(I)Ljava/lang/String;
    //   485: astore_1
    //   486: aload_0
    //   487: invokevirtual 228	android/content/Context:getResources	()Landroid/content/res/Resources;
    //   490: ldc -7
    //   492: invokevirtual 232	android/content/res/Resources:getString	(I)Ljava/lang/String;
    //   495: iconst_0
    //   496: iconst_4
    //   497: invokevirtual 235	java/lang/String:substring	(II)Ljava/lang/String;
    //   500: invokevirtual 243	java/lang/String:length	()I
    //   503: istore_2
    //   504: aload_0
    //   505: invokevirtual 228	android/content/Context:getResources	()Landroid/content/res/Resources;
    //   508: ldc -6
    //   510: invokevirtual 232	android/content/res/Resources:getString	(I)Ljava/lang/String;
    //   513: iconst_0
    //   514: iconst_4
    //   515: invokevirtual 235	java/lang/String:substring	(II)Ljava/lang/String;
    //   518: iconst_2
    //   519: invokevirtual 239	java/lang/String:codePointAt	(I)I
    //   522: istore_3
    //   523: aload_0
    //   524: invokevirtual 228	android/content/Context:getResources	()Landroid/content/res/Resources;
    //   527: ldc -5
    //   529: invokevirtual 232	android/content/res/Resources:getString	(I)Ljava/lang/String;
    //   532: iconst_0
    //   533: iconst_4
    //   534: invokevirtual 235	java/lang/String:substring	(II)Ljava/lang/String;
    //   537: iconst_2
    //   538: invokevirtual 239	java/lang/String:codePointAt	(I)I
    //   541: istore 4
    //   543: aload_1
    //   544: iload_2
    //   545: sipush 192
    //   548: iadd
    //   549: iload_3
    //   550: bipush 7
    //   552: isub
    //   553: iconst_4
    //   554: newarray char
    //   556: dup
    //   557: iconst_0
    //   558: ldc -51
    //   560: castore
    //   561: dup
    //   562: iconst_1
    //   563: ldc -50
    //   565: castore
    //   566: dup
    //   567: iconst_2
    //   568: ldc -49
    //   570: castore
    //   571: dup
    //   572: iconst_3
    //   573: ldc -48
    //   575: castore
    //   576: iload 4
    //   578: bipush 8
    //   580: isub
    //   581: iconst_1
    //   582: invokestatic 210	o/LY:ˊ	(II[CIZ)Ljava/lang/String;
    //   585: invokevirtual 185	java/lang/String:intern	()Ljava/lang/String;
    //   588: invokevirtual 214	java/lang/String:startsWith	(Ljava/lang/String;)Z
    //   591: ifeq +6 -> 597
    //   594: goto -131 -> 463
    //   597: goto -125 -> 472
    //   600: getstatic 25	o/LY:ʽॱ	I
    //   603: bipush 67
    //   605: iadd
    //   606: istore_2
    //   607: iload_2
    //   608: sipush 128
    //   611: irem
    //   612: putstatic 23	o/LY:ˈ	I
    //   615: iload_2
    //   616: iconst_2
    //   617: irem
    //   618: ifeq +5 -> 623
    //   621: aload_1
    //   622: areturn
    //   623: aload_1
    //   624: areturn
    // Local variable table:
    //   start	length	slot	name	signature
    //   0	625	0	this	LY
    //   0	625	1	paramFV	FV
    //   6	612	2	i	int
    //   100	453	3	j	int
    //   108	473	4	k	int
    // Exception table:
    //   from	to	target	type
    //   167	174	74	java/lang/Exception
    //   174	182	74	java/lang/Exception
    //   174	182	251	java/lang/Exception
  }
  
  private void ˋˋ()
  {
    break label160;
    int i;
    switch (i)
    {
    default: 
      break;
    }
    label150:
    label160:
    for (;;)
    {
      try
      {
        i = ˈ;
        i += 61;
        ʽॱ = i % 128;
        if (i % 2 == 0) {
          break label150;
        }
      }
      catch (Exception localException)
      {
        throw localException;
      }
      ((Mq)this.ॱˊ).ʼ.setFilters((ArrayList)ॱ(((Mq)this.ॱˊ).ˏॱ().currency, FY.RECEIVED, FT.SEND_MONEY));
      return;
      ((Mq)this.ॱˊ).ʼ.setFilters((ArrayList)ॱ(((Mq)this.ॱˊ).ˏॱ().currency, FY.RECEIVED, FT.SEND_MONEY));
      throw new NullPointerException();
      i = 0;
      break;
      i = 1;
      break;
    }
  }
  
  /* Error */
  private void ˋᐝ()
  {
    // Byte code:
    //   0: goto +156 -> 156
    //   3: iconst_1
    //   4: istore_3
    //   5: goto +96 -> 101
    //   8: return
    //   9: getstatic 25	o/LY:ʽॱ	I
    //   12: bipush 125
    //   14: iadd
    //   15: istore_3
    //   16: iload_3
    //   17: sipush 128
    //   20: irem
    //   21: putstatic 23	o/LY:ˈ	I
    //   24: iload_3
    //   25: iconst_2
    //   26: irem
    //   27: ifeq +6 -> 33
    //   30: goto +134 -> 164
    //   33: goto -30 -> 3
    //   36: astore 4
    //   38: aload 4
    //   40: athrow
    //   41: aload_0
    //   42: getfield 40	o/LY:ॱˊ	Landroid/databinding/ViewDataBinding;
    //   45: astore 4
    //   47: aload 4
    //   49: checkcast 42	o/Mq
    //   52: astore 4
    //   54: aload 4
    //   56: invokevirtual 122	o/Mq:ˏॱ	()Lo/FW;
    //   59: astore 4
    //   61: aload 4
    //   63: getfield 284	o/FW:amount	D
    //   66: dstore_1
    //   67: aload_0
    //   68: dload_1
    //   69: invokestatic 288	java/lang/String:valueOf	(D)Ljava/lang/String;
    //   72: aload_0
    //   73: getfield 40	o/LY:ॱˊ	Landroid/databinding/ViewDataBinding;
    //   76: checkcast 42	o/Mq
    //   79: invokevirtual 122	o/Mq:ˏॱ	()Lo/FW;
    //   82: getfield 258	o/FW:currency	Lo/Ep;
    //   85: invokevirtual 292	o/Ep:ˊ	()Ljava/lang/String;
    //   88: invokevirtual 295	o/LY:ˎ	(Ljava/lang/String;Ljava/lang/String;)V
    //   91: goto -82 -> 9
    //   94: aconst_null
    //   95: arraylength
    //   96: istore_3
    //   97: return
    //   98: goto -57 -> 41
    //   101: iload_3
    //   102: lookupswitch	default:+26->128, 1:+-94->8, 81:+-8->94
    //   128: return
    //   129: getstatic 23	o/LY:ˈ	I
    //   132: bipush 55
    //   134: iadd
    //   135: istore_3
    //   136: iload_3
    //   137: sipush 128
    //   140: irem
    //   141: putstatic 25	o/LY:ʽॱ	I
    //   144: iload_3
    //   145: iconst_2
    //   146: irem
    //   147: ifne +6 -> 153
    //   150: goto -52 -> 98
    //   153: goto -112 -> 41
    //   156: goto -27 -> 129
    //   159: astore 4
    //   161: aload 4
    //   163: athrow
    //   164: bipush 81
    //   166: istore_3
    //   167: goto -66 -> 101
    // Local variable table:
    //   start	length	slot	name	signature
    //   0	170	0	this	LY
    //   66	3	1	d	double
    //   4	163	3	i	int
    //   36	3	4	localException1	Exception
    //   45	17	4	localObject	Object
    //   159	3	4	localException2	Exception
    // Exception table:
    //   from	to	target	type
    //   47	54	36	java/lang/Exception
    //   41	47	159	java/lang/Exception
    //   47	54	159	java/lang/Exception
    //   54	61	159	java/lang/Exception
    //   61	67	159	java/lang/Exception
    //   67	91	159	java/lang/Exception
  }
  
  /* Error */
  private void ˌ()
  {
    // Byte code:
    //   0: goto +134 -> 134
    //   3: iload_1
    //   4: tableswitch	default:+24->28, 0:+179->183, 1:+125->129
    //   28: goto +101 -> 129
    //   31: getstatic 25	o/LY:ʽॱ	I
    //   34: bipush 45
    //   36: iadd
    //   37: istore_1
    //   38: iload_1
    //   39: sipush 128
    //   42: irem
    //   43: putstatic 23	o/LY:ˈ	I
    //   46: iload_1
    //   47: iconst_2
    //   48: irem
    //   49: ifeq +6 -> 55
    //   52: goto +120 -> 172
    //   55: goto +41 -> 96
    //   58: iload_1
    //   59: lookupswitch	default:+25->84, 62:+78->137, 70:+137->196
    //   84: goto +112 -> 196
    //   87: return
    //   88: iconst_1
    //   89: istore_1
    //   90: goto -87 -> 3
    //   93: astore_2
    //   94: aload_2
    //   95: athrow
    //   96: bipush 62
    //   98: istore_1
    //   99: goto -41 -> 58
    //   102: getstatic 23	o/LY:ˈ	I
    //   105: bipush 35
    //   107: iadd
    //   108: istore_1
    //   109: iload_1
    //   110: sipush 128
    //   113: irem
    //   114: putstatic 25	o/LY:ʽॱ	I
    //   117: iload_1
    //   118: iconst_2
    //   119: irem
    //   120: ifne +6 -> 126
    //   123: goto +67 -> 190
    //   126: goto -39 -> 87
    //   129: aload_0
    //   130: invokespecial 298	o/LY:ˋᐝ	()V
    //   133: return
    //   134: goto -103 -> 31
    //   137: aload_0
    //   138: getfield 40	o/LY:ॱˊ	Landroid/databinding/ViewDataBinding;
    //   141: astore_2
    //   142: aload_2
    //   143: checkcast 42	o/Mq
    //   146: astore_2
    //   147: aload_2
    //   148: invokevirtual 122	o/Mq:ˏॱ	()Lo/FW;
    //   151: astore_2
    //   152: aload_2
    //   153: getfield 127	o/FW:status	Lo/FV;
    //   156: astore_2
    //   157: getstatic 118	o/FV:ACCEPTED	Lo/FV;
    //   160: astore_3
    //   161: aload_2
    //   162: aload_3
    //   163: if_acmpne +6 -> 169
    //   166: goto +12 -> 178
    //   169: goto -81 -> 88
    //   172: bipush 70
    //   174: istore_1
    //   175: goto -117 -> 58
    //   178: iconst_0
    //   179: istore_1
    //   180: goto -177 -> 3
    //   183: aload_0
    //   184: invokespecial 301	o/LY:ˎˎ	()V
    //   187: goto -85 -> 102
    //   190: goto -103 -> 87
    //   193: astore_2
    //   194: aload_2
    //   195: athrow
    //   196: aload_0
    //   197: getfield 40	o/LY:ॱˊ	Landroid/databinding/ViewDataBinding;
    //   200: checkcast 42	o/Mq
    //   203: invokevirtual 122	o/Mq:ˏॱ	()Lo/FW;
    //   206: getfield 127	o/FW:status	Lo/FV;
    //   209: astore_2
    //   210: getstatic 118	o/FV:ACCEPTED	Lo/FV;
    //   213: astore_3
    //   214: aconst_null
    //   215: arraylength
    //   216: istore_1
    //   217: aload_2
    //   218: aload_3
    //   219: if_acmpne +6 -> 225
    //   222: goto -39 -> 183
    //   225: goto -96 -> 129
    // Local variable table:
    //   start	length	slot	name	signature
    //   0	228	0	this	LY
    //   3	214	1	i	int
    //   93	2	2	localException1	Exception
    //   141	21	2	localObject	Object
    //   193	2	2	localException2	Exception
    //   209	9	2	localFV1	FV
    //   160	59	3	localFV2	FV
    // Exception table:
    //   from	to	target	type
    //   157	161	93	java/lang/Exception
    //   137	142	193	java/lang/Exception
    //   142	147	193	java/lang/Exception
    //   147	152	193	java/lang/Exception
    //   152	157	193	java/lang/Exception
    //   157	161	193	java/lang/Exception
  }
  
  private void ˍ()
  {
    break label106;
    break label35;
    label6:
    int i;
    switch (i)
    {
    default: 
      break;
    }
    for (;;)
    {
      label35:
      HQ localHQ = ((Mq)this.ॱˊ).ʼ.ʻ();
      ((Mq)this.ॱˊ).ˋ(localHQ.ˊᐝ());
      break label72;
      i = 66 / 0;
      return;
      label72:
      i = ˈ + 91;
      ʽॱ = i % 128;
      if (i % 2 != 0) {}else
      {
        i = 98;
        break label6;
        label106:
        break label115;
      }
      i = 93;
      break label6;
      label115:
      i = ˈ + 23;
      ʽॱ = i % 128;
      if (i % 2 == 0) {
        break;
      }
    }
  }
  
  /* Error */
  private String ˎ(String paramString)
  {
    // Byte code:
    //   0: goto +71 -> 71
    //   3: goto +168 -> 171
    //   6: astore_1
    //   7: aload_1
    //   8: athrow
    //   9: goto +469 -> 478
    //   12: iconst_1
    //   13: istore_3
    //   14: goto +516 -> 530
    //   17: getstatic 23	o/LY:ˈ	I
    //   20: bipush 55
    //   22: iadd
    //   23: istore_3
    //   24: iload_3
    //   25: sipush 128
    //   28: irem
    //   29: putstatic 25	o/LY:ʽॱ	I
    //   32: iload_3
    //   33: iconst_2
    //   34: irem
    //   35: ifne +6 -> 41
    //   38: goto -26 -> 12
    //   41: goto +432 -> 473
    //   44: aload 5
    //   46: iload_2
    //   47: aload_1
    //   48: aload_1
    //   49: arraylength
    //   50: iload_2
    //   51: isub
    //   52: iconst_1
    //   53: isub
    //   54: baload
    //   55: getstatic 29	o/LY:ʾ	B
    //   58: ixor
    //   59: i2b
    //   60: bastore
    //   61: iload_2
    //   62: iconst_1
    //   63: iadd
    //   64: istore_2
    //   65: goto -48 -> 17
    //   68: astore_1
    //   69: aload_1
    //   70: athrow
    //   71: goto +257 -> 328
    //   74: iconst_1
    //   75: istore_3
    //   76: goto +36 -> 112
    //   79: bipush 53
    //   81: istore_3
    //   82: goto +57 -> 139
    //   85: getstatic 25	o/LY:ʽॱ	I
    //   88: bipush 39
    //   90: iadd
    //   91: istore_3
    //   92: iload_3
    //   93: sipush 128
    //   96: irem
    //   97: putstatic 23	o/LY:ˈ	I
    //   100: iload_3
    //   101: iconst_2
    //   102: irem
    //   103: ifeq +6 -> 109
    //   106: goto +449 -> 555
    //   109: goto -35 -> 74
    //   112: iload_3
    //   113: tableswitch	default:+23->136, 0:+392->505, 1:+-69->44
    //   136: goto +369 -> 505
    //   139: iload_3
    //   140: lookupswitch	default:+28->168, 51:+-55->85, 53:+217->357
    //   168: goto +189 -> 357
    //   171: aload_0
    //   172: invokevirtual 228	android/content/Context:getResources	()Landroid/content/res/Resources;
    //   175: ldc_w 313
    //   178: invokevirtual 232	android/content/res/Resources:getString	(I)Ljava/lang/String;
    //   181: iconst_0
    //   182: iconst_4
    //   183: invokevirtual 235	java/lang/String:substring	(II)Ljava/lang/String;
    //   186: invokevirtual 243	java/lang/String:length	()I
    //   189: istore_2
    //   190: aload_0
    //   191: invokevirtual 228	android/content/Context:getResources	()Landroid/content/res/Resources;
    //   194: ldc_w 314
    //   197: invokevirtual 232	android/content/res/Resources:getString	(I)Ljava/lang/String;
    //   200: iconst_0
    //   201: bipush 15
    //   203: invokevirtual 235	java/lang/String:substring	(II)Ljava/lang/String;
    //   206: invokevirtual 243	java/lang/String:length	()I
    //   209: istore_3
    //   210: aload_0
    //   211: invokevirtual 199	android/content/Context:getApplicationInfo	()Landroid/content/pm/ApplicationInfo;
    //   214: getfield 204	android/content/pm/ApplicationInfo:targetSdkVersion	I
    //   217: istore 4
    //   219: aload_1
    //   220: iload_2
    //   221: sipush 238
    //   224: iadd
    //   225: iload_3
    //   226: iconst_5
    //   227: isub
    //   228: bipush 10
    //   230: newarray char
    //   232: dup
    //   233: iconst_0
    //   234: ldc_w 315
    //   237: castore
    //   238: dup
    //   239: iconst_1
    //   240: ldc -51
    //   242: castore
    //   243: dup
    //   244: iconst_2
    //   245: ldc_w 316
    //   248: castore
    //   249: dup
    //   250: iconst_3
    //   251: ldc_w 317
    //   254: castore
    //   255: dup
    //   256: iconst_4
    //   257: ldc_w 317
    //   260: castore
    //   261: dup
    //   262: iconst_5
    //   263: ldc_w 315
    //   266: castore
    //   267: dup
    //   268: bipush 6
    //   270: ldc_w 318
    //   273: castore
    //   274: dup
    //   275: bipush 7
    //   277: ldc_w 319
    //   280: castore
    //   281: dup
    //   282: bipush 8
    //   284: ldc_w 320
    //   287: castore
    //   288: dup
    //   289: bipush 9
    //   291: ldc_w 321
    //   294: castore
    //   295: iload 4
    //   297: bipush 16
    //   299: isub
    //   300: iconst_1
    //   301: invokestatic 210	o/LY:ˊ	(II[CIZ)Ljava/lang/String;
    //   304: invokevirtual 185	java/lang/String:intern	()Ljava/lang/String;
    //   307: invokevirtual 325	java/lang/String:getBytes	(Ljava/lang/String;)[B
    //   310: astore_1
    //   311: aload_1
    //   312: arraylength
    //   313: newarray byte
    //   315: astore 5
    //   317: iconst_0
    //   318: istore_2
    //   319: goto +173 -> 492
    //   322: bipush 51
    //   324: istore_3
    //   325: goto -186 -> 139
    //   328: getstatic 25	o/LY:ʽॱ	I
    //   331: istore_2
    //   332: iload_2
    //   333: bipush 57
    //   335: iadd
    //   336: istore_2
    //   337: iload_2
    //   338: sipush 128
    //   341: irem
    //   342: putstatic 23	o/LY:ˈ	I
    //   345: iload_2
    //   346: iconst_2
    //   347: irem
    //   348: ifeq +6 -> 354
    //   351: goto -348 -> 3
    //   354: goto -183 -> 171
    //   357: aload_0
    //   358: invokevirtual 228	android/content/Context:getResources	()Landroid/content/res/Resources;
    //   361: ldc_w 326
    //   364: invokevirtual 232	android/content/res/Resources:getString	(I)Ljava/lang/String;
    //   367: iconst_0
    //   368: bipush 9
    //   370: invokevirtual 235	java/lang/String:substring	(II)Ljava/lang/String;
    //   373: iconst_1
    //   374: invokevirtual 239	java/lang/String:codePointAt	(I)I
    //   377: istore_2
    //   378: aload_0
    //   379: invokevirtual 228	android/content/Context:getResources	()Landroid/content/res/Resources;
    //   382: ldc_w 327
    //   385: invokevirtual 232	android/content/res/Resources:getString	(I)Ljava/lang/String;
    //   388: iconst_0
    //   389: iconst_4
    //   390: invokevirtual 235	java/lang/String:substring	(II)Ljava/lang/String;
    //   393: invokevirtual 243	java/lang/String:length	()I
    //   396: istore_3
    //   397: aload_0
    //   398: invokevirtual 330	android/content/Context:getPackageName	()Ljava/lang/String;
    //   401: bipush 9
    //   403: invokevirtual 239	java/lang/String:codePointAt	(I)I
    //   406: istore 4
    //   408: new 65	java/lang/String
    //   411: dup
    //   412: aload 5
    //   414: iload_2
    //   415: sipush 225
    //   418: iadd
    //   419: iload_3
    //   420: iconst_1
    //   421: iadd
    //   422: iconst_5
    //   423: newarray char
    //   425: dup
    //   426: iconst_0
    //   427: ldc_w 331
    //   430: castore
    //   431: dup
    //   432: iconst_1
    //   433: ldc_w 332
    //   436: castore
    //   437: dup
    //   438: iconst_2
    //   439: ldc_w 333
    //   442: castore
    //   443: dup
    //   444: iconst_3
    //   445: ldc_w 334
    //   448: castore
    //   449: dup
    //   450: iconst_4
    //   451: ldc_w 335
    //   454: castore
    //   455: iload 4
    //   457: bipush 94
    //   459: isub
    //   460: iconst_0
    //   461: invokestatic 210	o/LY:ˊ	(II[CIZ)Ljava/lang/String;
    //   464: invokevirtual 185	java/lang/String:intern	()Ljava/lang/String;
    //   467: invokespecial 338	java/lang/String:<init>	([BLjava/lang/String;)V
    //   470: astore_1
    //   471: aload_1
    //   472: areturn
    //   473: iconst_0
    //   474: istore_3
    //   475: goto +55 -> 530
    //   478: aload_1
    //   479: arraylength
    //   480: istore_3
    //   481: iload_2
    //   482: iload_3
    //   483: if_icmpge +6 -> 489
    //   486: goto -164 -> 322
    //   489: goto -410 -> 79
    //   492: goto -14 -> 478
    //   495: astore_1
    //   496: new 340	java/lang/RuntimeException
    //   499: dup
    //   500: aload_1
    //   501: invokespecial 343	java/lang/RuntimeException:<init>	(Ljava/lang/Throwable;)V
    //   504: athrow
    //   505: aload 5
    //   507: iload_2
    //   508: aload_1
    //   509: aload_1
    //   510: arraylength
    //   511: iload_2
    //   512: ishl
    //   513: iconst_0
    //   514: ishr
    //   515: baload
    //   516: getstatic 29	o/LY:ʾ	B
    //   519: iand
    //   520: i2b
    //   521: bastore
    //   522: iload_2
    //   523: bipush 119
    //   525: iadd
    //   526: istore_2
    //   527: goto -510 -> 17
    //   530: iload_3
    //   531: tableswitch	default:+21->552, 0:+-522->9, 1:+29->560
    //   552: goto +8 -> 560
    //   555: iconst_0
    //   556: istore_3
    //   557: goto -445 -> 112
    //   560: iconst_4
    //   561: iconst_2
    //   562: idiv
    //   563: istore_3
    //   564: goto -86 -> 478
    // Local variable table:
    //   start	length	slot	name	signature
    //   0	567	0	this	LY
    //   0	567	1	paramString	String
    //   46	481	2	i	int
    //   13	551	3	j	int
    //   217	243	4	k	int
    //   44	462	5	arrayOfByte	byte[]
    // Exception table:
    //   from	to	target	type
    //   337	345	6	java/lang/Exception
    //   328	332	68	java/lang/Exception
    //   44	61	495	java/io/UnsupportedEncodingException
    //   171	317	495	java/io/UnsupportedEncodingException
    //   357	471	495	java/io/UnsupportedEncodingException
    //   478	481	495	java/io/UnsupportedEncodingException
    //   505	522	495	java/io/UnsupportedEncodingException
  }
  
  private void ˎˎ()
  {
    for (;;)
    {
      int i = ʽॱ + 123;
      ˈ = i % 128;
      if (i % 2 != 0) {
        return;
      }
      return;
      Object localObject = ((Mq)this.ॱˊ).ˏॱ();
      localObject = new Is((FW)localObject, ((Mq)this.ॱˊ).ˊॱ(), ˏ((FW)localObject));
      j localJ = Ic.ˏ(this).ˋ(FT.SEND_MONEY);
      i = getPackageName().codePointAt(4);
      int j = getResources().getString(2131755030).substring(0, 4).length();
      int k = getApplicationInfo().targetSdkVersion;
      localJ.ˎ(ˊ(i + 173, j + 29, new char[] { -5, 9, 2, -1, -9, 10, -5, -6, -11, 3, 8, 5, -4, -11, 8, -5, -4, 9, 4, -9, 8, 10, -11, 15, -5, 4, 5, 3, -11, -9, 8, 10, 14 }, k - 24, true).intern(), (Parcelable)localObject).ˎ();
    }
  }
  
  private boolean ˎˏ()
  {
    break label29;
    int i = ʽॱ + 67;
    ˈ = i % 128;
    boolean bool;
    if (i % 2 == 0)
    {
      return bool;
      label29:
      MatrixHCECard localMatrixHCECard = ((Mq)this.ॱˊ).ʼ.ॱॱ();
      if (localMatrixHCECard != null)
      {
        break label171;
        return HQ.ˏ(localMatrixHCECard).ˏ();
      }
    }
    for (;;)
    {
      bool = false;
      break;
      i = 1;
      break label145;
      i = 72 / 0;
      return bool;
      label78:
      switch (i)
      {
      }
    }
    for (;;)
    {
      i = 0;
      break label78;
      bool = true;
      break;
      do
      {
        i = 1;
        break;
        i = ʽॱ + 121;
        ˈ = i % 128;
      } while (i % 2 != 0);
    }
    for (;;)
    {
      label145:
      switch (i)
      {
      }
      break;
      label171:
      i = 0;
    }
  }
  
  /* Error */
  private String ˏ(FV paramFV)
  {
    // Byte code:
    //   0: goto +268 -> 268
    //   3: iload_2
    //   4: lookupswitch	default:+28->32, 0:+467->471, 4:+539->543
    //   32: goto +439 -> 471
    //   35: iconst_1
    //   36: istore_2
    //   37: goto +546 -> 583
    //   40: iconst_4
    //   41: istore_2
    //   42: goto -39 -> 3
    //   45: iload_2
    //   46: lookupswitch	default:+26->72, 17:+84->130, 39:+195->241
    //   72: goto +169 -> 241
    //   75: aload_0
    //   76: getstatic 392	o/LV$If:receive_money	I
    //   79: invokevirtual 193	o/LY:getString	(I)Ljava/lang/String;
    //   82: astore_1
    //   83: aload_1
    //   84: aload 6
    //   86: invokevirtual 214	java/lang/String:startsWith	(Ljava/lang/String;)Z
    //   89: ifeq +6 -> 95
    //   92: goto +363 -> 455
    //   95: aload_1
    //   96: areturn
    //   97: iconst_0
    //   98: istore_2
    //   99: goto -96 -> 3
    //   102: astore_1
    //   103: aload_1
    //   104: athrow
    //   105: aload_0
    //   106: getstatic 395	o/LV$If:transaction_details_received	I
    //   109: invokevirtual 193	o/LY:getString	(I)Ljava/lang/String;
    //   112: astore_1
    //   113: aload_1
    //   114: aload 6
    //   116: invokevirtual 214	java/lang/String:startsWith	(Ljava/lang/String;)Z
    //   119: ifeq +6 -> 125
    //   122: goto +378 -> 500
    //   125: aload_1
    //   126: areturn
    //   127: astore_1
    //   128: aload_1
    //   129: athrow
    //   130: aload_1
    //   131: areturn
    //   132: aload_0
    //   133: aload_1
    //   134: iconst_4
    //   135: invokevirtual 178	java/lang/String:substring	(I)Ljava/lang/String;
    //   138: invokespecial 181	o/LY:ˎ	(Ljava/lang/String;)Ljava/lang/String;
    //   141: astore_1
    //   142: aload_1
    //   143: invokevirtual 185	java/lang/String:intern	()Ljava/lang/String;
    //   146: astore_1
    //   147: aload_1
    //   148: areturn
    //   149: iconst_0
    //   150: istore_2
    //   151: goto +432 -> 583
    //   154: aload_0
    //   155: aload 5
    //   157: iconst_4
    //   158: invokevirtual 178	java/lang/String:substring	(I)Ljava/lang/String;
    //   161: invokespecial 181	o/LY:ˎ	(Ljava/lang/String;)Ljava/lang/String;
    //   164: invokevirtual 185	java/lang/String:intern	()Ljava/lang/String;
    //   167: astore_1
    //   168: goto +305 -> 473
    //   171: bipush 39
    //   173: istore_2
    //   174: goto -129 -> 45
    //   177: getstatic 23	o/LY:ˈ	I
    //   180: bipush 69
    //   182: iadd
    //   183: istore_2
    //   184: iload_2
    //   185: sipush 128
    //   188: irem
    //   189: putstatic 25	o/LY:ʽॱ	I
    //   192: iload_2
    //   193: iconst_2
    //   194: irem
    //   195: ifne +6 -> 201
    //   198: goto +413 -> 611
    //   201: goto -69 -> 132
    //   204: aload_1
    //   205: areturn
    //   206: aload_0
    //   207: getstatic 398	o/LV$If:failed_transaction	I
    //   210: invokevirtual 193	o/LY:getString	(I)Ljava/lang/String;
    //   213: astore_1
    //   214: aload_1
    //   215: aload 6
    //   217: invokevirtual 214	java/lang/String:startsWith	(Ljava/lang/String;)Z
    //   220: ifeq +6 -> 226
    //   223: goto +5 -> 228
    //   226: aload_1
    //   227: areturn
    //   228: aload_0
    //   229: aload_1
    //   230: iconst_4
    //   231: invokevirtual 178	java/lang/String:substring	(I)Ljava/lang/String;
    //   234: invokespecial 181	o/LY:ˎ	(Ljava/lang/String;)Ljava/lang/String;
    //   237: invokevirtual 185	java/lang/String:intern	()Ljava/lang/String;
    //   240: areturn
    //   241: getstatic 25	o/LY:ʽॱ	I
    //   244: bipush 43
    //   246: iadd
    //   247: istore_2
    //   248: iload_2
    //   249: sipush 128
    //   252: irem
    //   253: putstatic 23	o/LY:ˈ	I
    //   256: iload_2
    //   257: iconst_2
    //   258: irem
    //   259: ifeq +6 -> 265
    //   262: goto +278 -> 540
    //   265: goto +305 -> 570
    //   268: goto +25 -> 293
    //   271: aload_0
    //   272: getstatic 401	o/LV$If:expired_transaction	I
    //   275: invokevirtual 193	o/LY:getString	(I)Ljava/lang/String;
    //   278: astore_1
    //   279: aload_1
    //   280: aload 6
    //   282: invokevirtual 214	java/lang/String:startsWith	(Ljava/lang/String;)Z
    //   285: ifeq +6 -> 291
    //   288: goto -111 -> 177
    //   291: aload_1
    //   292: areturn
    //   293: aload_0
    //   294: invokevirtual 228	android/content/Context:getResources	()Landroid/content/res/Resources;
    //   297: ldc_w 402
    //   300: invokevirtual 232	android/content/res/Resources:getString	(I)Ljava/lang/String;
    //   303: bipush 7
    //   305: bipush 84
    //   307: invokevirtual 235	java/lang/String:substring	(II)Ljava/lang/String;
    //   310: bipush 69
    //   312: invokevirtual 239	java/lang/String:codePointAt	(I)I
    //   315: istore_2
    //   316: aload_0
    //   317: invokevirtual 228	android/content/Context:getResources	()Landroid/content/res/Resources;
    //   320: ldc_w 403
    //   323: invokevirtual 232	android/content/res/Resources:getString	(I)Ljava/lang/String;
    //   326: iconst_0
    //   327: iconst_4
    //   328: invokevirtual 235	java/lang/String:substring	(II)Ljava/lang/String;
    //   331: invokevirtual 243	java/lang/String:length	()I
    //   334: istore_3
    //   335: aload_0
    //   336: invokevirtual 228	android/content/Context:getResources	()Landroid/content/res/Resources;
    //   339: ldc_w 404
    //   342: invokevirtual 232	android/content/res/Resources:getString	(I)Ljava/lang/String;
    //   345: iconst_0
    //   346: iconst_4
    //   347: invokevirtual 235	java/lang/String:substring	(II)Ljava/lang/String;
    //   350: iconst_1
    //   351: invokevirtual 239	java/lang/String:codePointAt	(I)I
    //   354: istore 4
    //   356: iload_2
    //   357: bipush 15
    //   359: iadd
    //   360: iload_3
    //   361: iconst_0
    //   362: iadd
    //   363: iconst_4
    //   364: newarray char
    //   366: dup
    //   367: iconst_0
    //   368: ldc -51
    //   370: castore
    //   371: dup
    //   372: iconst_1
    //   373: ldc -50
    //   375: castore
    //   376: dup
    //   377: iconst_2
    //   378: ldc -49
    //   380: castore
    //   381: dup
    //   382: iconst_3
    //   383: ldc -48
    //   385: castore
    //   386: iload 4
    //   388: bipush 23
    //   390: isub
    //   391: iconst_1
    //   392: invokestatic 210	o/LY:ˊ	(II[CIZ)Ljava/lang/String;
    //   395: invokevirtual 185	java/lang/String:intern	()Ljava/lang/String;
    //   398: astore 6
    //   400: getstatic 217	o/LY$2:ॱ	[I
    //   403: aload_1
    //   404: invokevirtual 221	o/FV:ordinal	()I
    //   407: iaload
    //   408: tableswitch	default:+44->452, 1:+-303->105, 2:+-137->271, 3:+67->475, 4:+137->545, 5:+-202->206, 6:+-333->75, 7:+-333->75
    //   452: goto +185 -> 637
    //   455: aload_0
    //   456: aload_1
    //   457: iconst_4
    //   458: invokevirtual 178	java/lang/String:substring	(I)Ljava/lang/String;
    //   461: invokespecial 181	o/LY:ˎ	(Ljava/lang/String;)Ljava/lang/String;
    //   464: invokevirtual 185	java/lang/String:intern	()Ljava/lang/String;
    //   467: astore_1
    //   468: goto -264 -> 204
    //   471: aload_1
    //   472: areturn
    //   473: aload_1
    //   474: areturn
    //   475: getstatic 407	o/LV$If:cancelled_transaction	I
    //   478: istore_2
    //   479: aload_0
    //   480: iload_2
    //   481: invokevirtual 193	o/LY:getString	(I)Ljava/lang/String;
    //   484: astore_1
    //   485: aload_1
    //   486: aload 6
    //   488: invokevirtual 214	java/lang/String:startsWith	(Ljava/lang/String;)Z
    //   491: ifeq +6 -> 497
    //   494: goto -323 -> 171
    //   497: goto +134 -> 631
    //   500: aload_0
    //   501: aload_1
    //   502: iconst_4
    //   503: invokevirtual 178	java/lang/String:substring	(I)Ljava/lang/String;
    //   506: invokespecial 181	o/LY:ˎ	(Ljava/lang/String;)Ljava/lang/String;
    //   509: invokevirtual 185	java/lang/String:intern	()Ljava/lang/String;
    //   512: astore_1
    //   513: getstatic 25	o/LY:ʽॱ	I
    //   516: bipush 81
    //   518: iadd
    //   519: istore_2
    //   520: iload_2
    //   521: sipush 128
    //   524: irem
    //   525: putstatic 23	o/LY:ˈ	I
    //   528: iload_2
    //   529: iconst_2
    //   530: irem
    //   531: ifeq +6 -> 537
    //   534: goto -437 -> 97
    //   537: goto -497 -> 40
    //   540: goto +30 -> 570
    //   543: aload_1
    //   544: areturn
    //   545: aload_0
    //   546: getstatic 410	o/LV$If:rejected_transaction	I
    //   549: invokevirtual 193	o/LY:getString	(I)Ljava/lang/String;
    //   552: astore 5
    //   554: aload 5
    //   556: aload 6
    //   558: invokevirtual 214	java/lang/String:startsWith	(Ljava/lang/String;)Z
    //   561: ifeq +6 -> 567
    //   564: goto -529 -> 35
    //   567: goto -418 -> 149
    //   570: aload_0
    //   571: aload_1
    //   572: iconst_4
    //   573: invokevirtual 178	java/lang/String:substring	(I)Ljava/lang/String;
    //   576: invokespecial 181	o/LY:ˎ	(Ljava/lang/String;)Ljava/lang/String;
    //   579: invokevirtual 185	java/lang/String:intern	()Ljava/lang/String;
    //   582: areturn
    //   583: aload 5
    //   585: astore_1
    //   586: iload_2
    //   587: tableswitch	default:+21->608, 0:+-114->473, 1:+-433->154
    //   608: aload 5
    //   610: areturn
    //   611: aload_0
    //   612: aload_1
    //   613: iconst_4
    //   614: invokevirtual 178	java/lang/String:substring	(I)Ljava/lang/String;
    //   617: invokespecial 181	o/LY:ˎ	(Ljava/lang/String;)Ljava/lang/String;
    //   620: invokevirtual 185	java/lang/String:intern	()Ljava/lang/String;
    //   623: astore_1
    //   624: bipush 43
    //   626: iconst_0
    //   627: idiv
    //   628: istore_2
    //   629: aload_1
    //   630: areturn
    //   631: bipush 17
    //   633: istore_2
    //   634: goto -589 -> 45
    //   637: ldc -11
    //   639: areturn
    // Local variable table:
    //   start	length	slot	name	signature
    //   0	640	0	this	LY
    //   0	640	1	paramFV	FV
    //   3	631	2	i	int
    //   334	29	3	j	int
    //   354	37	4	k	int
    //   155	454	5	str1	String
    //   84	473	6	str2	String
    // Exception table:
    //   from	to	target	type
    //   132	142	102	java/lang/Exception
    //   142	147	102	java/lang/Exception
    //   479	485	102	java/lang/Exception
    //   475	479	127	java/lang/Exception
  }
  
  /* Error */
  private void ͺॱ()
  {
    // Byte code:
    //   0: goto +58 -> 58
    //   3: goto +93 -> 96
    //   6: aload_0
    //   7: getfield 137	o/LY:ˊˊ	Lo/coN;
    //   10: iconst_1
    //   11: invokevirtual 414	o/coN:ˋ	(Z)V
    //   14: aload_0
    //   15: invokespecial 416	o/LY:ˎˏ	()Z
    //   18: ifeq +6 -> 24
    //   21: goto +242 -> 263
    //   24: goto +114 -> 138
    //   27: goto +28 -> 55
    //   30: getstatic 25	o/LY:ʽॱ	I
    //   33: bipush 109
    //   35: iadd
    //   36: istore_1
    //   37: iload_1
    //   38: sipush 128
    //   41: irem
    //   42: putstatic 23	o/LY:ˈ	I
    //   45: iload_1
    //   46: iconst_2
    //   47: irem
    //   48: ifeq +6 -> 54
    //   51: goto +10 -> 61
    //   54: return
    //   55: goto +7 -> 62
    //   58: goto -52 -> 6
    //   61: return
    //   62: goto -32 -> 30
    //   65: iconst_1
    //   66: istore_1
    //   67: goto +378 -> 445
    //   70: aload 5
    //   72: iconst_4
    //   73: invokevirtual 178	java/lang/String:substring	(I)Ljava/lang/String;
    //   76: astore 4
    //   78: aload_0
    //   79: aload 4
    //   81: invokespecial 181	o/LY:ˎ	(Ljava/lang/String;)Ljava/lang/String;
    //   84: astore 4
    //   86: aload 4
    //   88: invokevirtual 185	java/lang/String:intern	()Ljava/lang/String;
    //   91: astore 4
    //   93: goto -90 -> 3
    //   96: aload_0
    //   97: aload 4
    //   99: iconst_1
    //   100: invokestatic 422	android/widget/Toast:makeText	(Landroid/content/Context;Ljava/lang/CharSequence;I)Landroid/widget/Toast;
    //   103: invokevirtual 425	android/widget/Toast:show	()V
    //   106: getstatic 25	o/LY:ʽॱ	I
    //   109: bipush 93
    //   111: iadd
    //   112: istore_1
    //   113: iload_1
    //   114: sipush 128
    //   117: irem
    //   118: putstatic 23	o/LY:ˈ	I
    //   121: iload_1
    //   122: iconst_2
    //   123: irem
    //   124: ifeq +6 -> 130
    //   127: goto -100 -> 27
    //   130: goto -75 -> 55
    //   133: iconst_0
    //   134: istore_1
    //   135: goto +310 -> 445
    //   138: aload_0
    //   139: getfield 137	o/LY:ˊˊ	Lo/coN;
    //   142: iconst_0
    //   143: invokevirtual 414	o/coN:ˋ	(Z)V
    //   146: aload_0
    //   147: getstatic 428	o/LV$If:receive_money_at_lest_one_card_digitized	I
    //   150: invokevirtual 193	o/LY:getString	(I)Ljava/lang/String;
    //   153: astore 5
    //   155: aload_0
    //   156: invokevirtual 228	android/content/Context:getResources	()Landroid/content/res/Resources;
    //   159: ldc_w 429
    //   162: invokevirtual 232	android/content/res/Resources:getString	(I)Ljava/lang/String;
    //   165: iconst_0
    //   166: iconst_5
    //   167: invokevirtual 235	java/lang/String:substring	(II)Ljava/lang/String;
    //   170: iconst_2
    //   171: invokevirtual 239	java/lang/String:codePointAt	(I)I
    //   174: istore_1
    //   175: aload_0
    //   176: invokevirtual 228	android/content/Context:getResources	()Landroid/content/res/Resources;
    //   179: ldc_w 430
    //   182: invokevirtual 232	android/content/res/Resources:getString	(I)Ljava/lang/String;
    //   185: iconst_0
    //   186: bipush 9
    //   188: invokevirtual 235	java/lang/String:substring	(II)Ljava/lang/String;
    //   191: bipush 7
    //   193: invokevirtual 239	java/lang/String:codePointAt	(I)I
    //   196: istore_2
    //   197: aload_0
    //   198: invokevirtual 199	android/content/Context:getApplicationInfo	()Landroid/content/pm/ApplicationInfo;
    //   201: getfield 204	android/content/pm/ApplicationInfo:targetSdkVersion	I
    //   204: istore_3
    //   205: aload 5
    //   207: iload_1
    //   208: sipush 185
    //   211: iadd
    //   212: iload_2
    //   213: sipush 245
    //   216: isub
    //   217: iconst_4
    //   218: newarray char
    //   220: dup
    //   221: iconst_0
    //   222: ldc -51
    //   224: castore
    //   225: dup
    //   226: iconst_1
    //   227: ldc -50
    //   229: castore
    //   230: dup
    //   231: iconst_2
    //   232: ldc -49
    //   234: castore
    //   235: dup
    //   236: iconst_3
    //   237: ldc -48
    //   239: castore
    //   240: iload_3
    //   241: bipush 22
    //   243: isub
    //   244: iconst_1
    //   245: invokestatic 210	o/LY:ˊ	(II[CIZ)Ljava/lang/String;
    //   248: invokevirtual 185	java/lang/String:intern	()Ljava/lang/String;
    //   251: invokevirtual 214	java/lang/String:startsWith	(Ljava/lang/String;)Z
    //   254: ifeq +6 -> 260
    //   257: goto -192 -> 65
    //   260: goto -127 -> 133
    //   263: aload_0
    //   264: getfield 40	o/LY:ॱˊ	Landroid/databinding/ViewDataBinding;
    //   267: astore 4
    //   269: aload 4
    //   271: checkcast 42	o/Mq
    //   274: astore 4
    //   276: aload 4
    //   278: getfield 46	o/Mq:ʼ	Lo/KZ;
    //   281: invokevirtual 384	o/KZ:ॱॱ	()Lcom/insidesecure/hce/MatrixHCECard;
    //   284: invokestatic 387	o/HQ:ˏ	(Lcom/insidesecure/hce/MatrixHCECard;)Lo/HQ;
    //   287: invokevirtual 432	o/HQ:ॱॱ	()Ljava/lang/String;
    //   290: astore 4
    //   292: goto +23 -> 315
    //   295: astore 4
    //   297: aload 4
    //   299: invokevirtual 438	java/lang/Throwable:getCause	()Ljava/lang/Throwable;
    //   302: astore 5
    //   304: aload 5
    //   306: ifnull +6 -> 312
    //   309: aload 5
    //   311: athrow
    //   312: aload 4
    //   314: athrow
    //   315: aload_0
    //   316: invokevirtual 228	android/content/Context:getResources	()Landroid/content/res/Resources;
    //   319: ldc_w 439
    //   322: invokevirtual 232	android/content/res/Resources:getString	(I)Ljava/lang/String;
    //   325: bipush 19
    //   327: bipush 30
    //   329: invokevirtual 235	java/lang/String:substring	(II)Ljava/lang/String;
    //   332: invokevirtual 243	java/lang/String:length	()I
    //   335: bipush 7
    //   337: isub
    //   338: aload_0
    //   339: invokevirtual 199	android/content/Context:getApplicationInfo	()Landroid/content/pm/ApplicationInfo;
    //   342: getfield 204	android/content/pm/ApplicationInfo:targetSdkVersion	I
    //   345: bipush 110
    //   347: iadd
    //   348: aload_0
    //   349: invokevirtual 199	android/content/Context:getApplicationInfo	()Landroid/content/pm/ApplicationInfo;
    //   352: getfield 204	android/content/pm/ApplicationInfo:targetSdkVersion	I
    //   355: ldc_w 440
    //   358: iadd
    //   359: i2c
    //   360: invokestatic 445	o/O:ˋ	(IIC)Ljava/lang/Object;
    //   363: checkcast 447	java/lang/Class
    //   366: ldc_w 448
    //   369: aconst_null
    //   370: invokevirtual 452	java/lang/Class:getMethod	(Ljava/lang/String;[Ljava/lang/Class;)Ljava/lang/reflect/Method;
    //   373: aconst_null
    //   374: aconst_null
    //   375: invokevirtual 458	java/lang/reflect/Method:invoke	(Ljava/lang/Object;[Ljava/lang/Object;)Ljava/lang/Object;
    //   378: checkcast 460	o/It
    //   381: astore 5
    //   383: aload 5
    //   385: aload_0
    //   386: getfield 464	o/LY:ʿ	Ljava/lang/String;
    //   389: new 466	o/Gb
    //   392: dup
    //   393: aload 4
    //   395: new 468	java/math/BigDecimal
    //   398: dup
    //   399: aload_0
    //   400: getfield 40	o/LY:ॱˊ	Landroid/databinding/ViewDataBinding;
    //   403: checkcast 42	o/Mq
    //   406: invokevirtual 122	o/Mq:ˏॱ	()Lo/FW;
    //   409: invokevirtual 471	o/FW:ˎ	()D
    //   412: invokespecial 474	java/math/BigDecimal:<init>	(D)V
    //   415: invokespecial 477	o/Gb:<init>	(Ljava/lang/String;Ljava/math/BigDecimal;)V
    //   418: invokeinterface 480 3 0
    //   423: new 9	o/LY$3
    //   426: dup
    //   427: aload_0
    //   428: aload_0
    //   429: invokespecial 483	o/LY$3:<init>	(Lo/LY;Landroid/content/Context;)V
    //   432: invokeinterface 488 2 0
    //   437: goto -375 -> 62
    //   440: astore 4
    //   442: aload 4
    //   444: athrow
    //   445: aload 5
    //   447: astore 4
    //   449: iload_1
    //   450: tableswitch	default:+22->472, 0:+-354->96, 1:+-380->70
    //   472: goto -402 -> 70
    // Local variable table:
    //   start	length	slot	name	signature
    //   0	475	0	this	LY
    //   36	414	1	i	int
    //   196	21	2	j	int
    //   204	40	3	k	int
    //   76	215	4	localObject1	Object
    //   295	99	4	str	String
    //   440	3	4	localException	Exception
    //   447	1	4	localObject2	Object
    //   70	376	5	localObject3	Object
    // Exception table:
    //   from	to	target	type
    //   315	383	295	finally
    //   70	78	440	java/lang/Exception
    //   86	93	440	java/lang/Exception
    //   263	269	440	java/lang/Exception
    //   269	276	440	java/lang/Exception
  }
  
  /* Error */
  private void ॱ(FW paramFW, FS paramFS)
  {
    // Byte code:
    //   0: goto +215 -> 215
    //   3: iconst_0
    //   4: istore_3
    //   5: goto +552 -> 557
    //   8: aload 6
    //   10: iconst_4
    //   11: invokevirtual 178	java/lang/String:substring	(I)Ljava/lang/String;
    //   14: astore 6
    //   16: aload_0
    //   17: aload 6
    //   19: invokespecial 181	o/LY:ˎ	(Ljava/lang/String;)Ljava/lang/String;
    //   22: astore 6
    //   24: aload 6
    //   26: invokevirtual 185	java/lang/String:intern	()Ljava/lang/String;
    //   29: astore 6
    //   31: aconst_null
    //   32: arraylength
    //   33: istore_3
    //   34: goto +125 -> 159
    //   37: aload_0
    //   38: aload_1
    //   39: invokevirtual 130	o/LY:ˏ	(Lo/FW;)Lcom/insidesecure/hce/MatrixHCECard;
    //   42: ifnonnull +6 -> 48
    //   45: goto +604 -> 649
    //   48: goto +388 -> 436
    //   51: iconst_0
    //   52: istore_3
    //   53: goto +109 -> 162
    //   56: getstatic 494	o/LV$if:F15B_Black	I
    //   59: istore_3
    //   60: goto +149 -> 209
    //   63: bipush 14
    //   65: istore_3
    //   66: goto +384 -> 450
    //   69: getstatic 23	o/LY:ˈ	I
    //   72: bipush 29
    //   74: iadd
    //   75: istore_3
    //   76: iload_3
    //   77: sipush 128
    //   80: irem
    //   81: putstatic 25	o/LY:ʽॱ	I
    //   84: iload_3
    //   85: iconst_2
    //   86: irem
    //   87: ifne +6 -> 93
    //   90: goto +357 -> 447
    //   93: goto -30 -> 63
    //   96: iload_3
    //   97: lookupswitch	default:+27->124, 68:+-46->51, 78:+547->644
    //   124: goto -73 -> 51
    //   127: astore_1
    //   128: aload_1
    //   129: athrow
    //   130: goto +79 -> 209
    //   133: iload_3
    //   134: tableswitch	default:+22->156, 0:+256->390, 1:+-126->8
    //   156: goto -148 -> 8
    //   159: goto +429 -> 588
    //   162: aload_0
    //   163: getfield 40	o/LY:ॱˊ	Landroid/databinding/ViewDataBinding;
    //   166: astore 7
    //   168: aload 7
    //   170: checkcast 42	o/Mq
    //   173: aload_0
    //   174: aload 6
    //   176: invokespecial 496	o/LY:ˏ	(Lo/FV;)Ljava/lang/String;
    //   179: invokevirtual 499	o/Mq:ˎ	(Ljava/lang/String;)V
    //   182: aload_0
    //   183: getfield 40	o/LY:ॱˊ	Landroid/databinding/ViewDataBinding;
    //   186: checkcast 42	o/Mq
    //   189: astore 7
    //   191: iload_3
    //   192: ifeq +6 -> 198
    //   195: goto +388 -> 583
    //   198: goto +210 -> 408
    //   201: goto +73 -> 274
    //   204: iconst_1
    //   205: istore_3
    //   206: goto +351 -> 557
    //   209: aload_2
    //   210: iload_3
    //   211: invokevirtual 505	o/Je:setValueStyle	(I)V
    //   214: return
    //   215: goto +317 -> 532
    //   218: goto +261 -> 479
    //   221: iload_3
    //   222: tableswitch	default:+22->244, 0:+393->615, 1:+433->655
    //   244: goto +411 -> 655
    //   247: getstatic 25	o/LY:ʽॱ	I
    //   250: bipush 109
    //   252: iadd
    //   253: istore_3
    //   254: iload_3
    //   255: sipush 128
    //   258: irem
    //   259: putstatic 23	o/LY:ˈ	I
    //   262: iload_3
    //   263: iconst_2
    //   264: irem
    //   265: ifeq +6 -> 271
    //   268: goto +368 -> 636
    //   271: goto +171 -> 442
    //   274: aload_0
    //   275: getstatic 508	o/LV$If:transaction_details_card_deleted	I
    //   278: invokevirtual 193	o/LY:getString	(I)Ljava/lang/String;
    //   281: astore 6
    //   283: aload_0
    //   284: invokevirtual 228	android/content/Context:getResources	()Landroid/content/res/Resources;
    //   287: ldc_w 509
    //   290: invokevirtual 232	android/content/res/Resources:getString	(I)Ljava/lang/String;
    //   293: iconst_0
    //   294: iconst_4
    //   295: invokevirtual 235	java/lang/String:substring	(II)Ljava/lang/String;
    //   298: iconst_1
    //   299: invokevirtual 239	java/lang/String:codePointAt	(I)I
    //   302: istore_3
    //   303: aload_0
    //   304: invokevirtual 228	android/content/Context:getResources	()Landroid/content/res/Resources;
    //   307: ldc_w 510
    //   310: invokevirtual 232	android/content/res/Resources:getString	(I)Ljava/lang/String;
    //   313: iconst_0
    //   314: iconst_4
    //   315: invokevirtual 235	java/lang/String:substring	(II)Ljava/lang/String;
    //   318: invokevirtual 243	java/lang/String:length	()I
    //   321: istore 4
    //   323: aload_0
    //   324: invokevirtual 199	android/content/Context:getApplicationInfo	()Landroid/content/pm/ApplicationInfo;
    //   327: getfield 204	android/content/pm/ApplicationInfo:targetSdkVersion	I
    //   330: istore 5
    //   332: aload 6
    //   334: iload_3
    //   335: sipush 170
    //   338: iadd
    //   339: iload 4
    //   341: iconst_0
    //   342: iadd
    //   343: iconst_4
    //   344: newarray char
    //   346: dup
    //   347: iconst_0
    //   348: ldc -51
    //   350: castore
    //   351: dup
    //   352: iconst_1
    //   353: ldc -50
    //   355: castore
    //   356: dup
    //   357: iconst_2
    //   358: ldc -49
    //   360: castore
    //   361: dup
    //   362: iconst_3
    //   363: ldc -48
    //   365: castore
    //   366: iload 5
    //   368: bipush 22
    //   370: isub
    //   371: iconst_1
    //   372: invokestatic 210	o/LY:ˊ	(II[CIZ)Ljava/lang/String;
    //   375: invokevirtual 185	java/lang/String:intern	()Ljava/lang/String;
    //   378: invokevirtual 214	java/lang/String:startsWith	(Ljava/lang/String;)Z
    //   381: ifeq +6 -> 387
    //   384: goto -137 -> 247
    //   387: goto -228 -> 159
    //   390: aload_0
    //   391: aload 6
    //   393: iconst_4
    //   394: invokevirtual 178	java/lang/String:substring	(I)Ljava/lang/String;
    //   397: invokespecial 181	o/LY:ˎ	(Ljava/lang/String;)Ljava/lang/String;
    //   400: invokevirtual 185	java/lang/String:intern	()Ljava/lang/String;
    //   403: astore 6
    //   405: goto -246 -> 159
    //   408: iconst_0
    //   409: istore_3
    //   410: goto -189 -> 221
    //   413: aload_0
    //   414: aload_1
    //   415: invokevirtual 130	o/LY:ˏ	(Lo/FW;)Lcom/insidesecure/hce/MatrixHCECard;
    //   418: astore 7
    //   420: bipush 73
    //   422: iconst_0
    //   423: idiv
    //   424: istore_3
    //   425: aload 7
    //   427: ifnonnull +6 -> 433
    //   430: goto +214 -> 644
    //   433: goto -382 -> 51
    //   436: bipush 68
    //   438: istore_3
    //   439: goto -343 -> 96
    //   442: iconst_0
    //   443: istore_3
    //   444: goto -311 -> 133
    //   447: bipush 95
    //   449: istore_3
    //   450: iload_3
    //   451: lookupswitch	default:+25->476, 14:+-414->37, 95:+-38->413
    //   476: goto -63 -> 413
    //   479: aload 7
    //   481: aload 6
    //   483: invokevirtual 512	o/Mq:ˊ	(Ljava/lang/String;)V
    //   486: aload_0
    //   487: getfield 40	o/LY:ॱˊ	Landroid/databinding/ViewDataBinding;
    //   490: checkcast 42	o/Mq
    //   493: aload_1
    //   494: invokevirtual 515	o/Mq:ˊ	(Lo/FW;)V
    //   497: aload_0
    //   498: getfield 40	o/LY:ॱˊ	Landroid/databinding/ViewDataBinding;
    //   501: checkcast 42	o/Mq
    //   504: aload_2
    //   505: invokevirtual 518	o/Mq:ˊ	(Lo/FS;)V
    //   508: aload_0
    //   509: getfield 40	o/LY:ॱˊ	Landroid/databinding/ViewDataBinding;
    //   512: checkcast 42	o/Mq
    //   515: getfield 522	o/Mq:ᐝॱ	Lo/Je;
    //   518: astore_2
    //   519: aload_1
    //   520: invokevirtual 132	o/FW:ʽॱ	()Z
    //   523: ifeq +6 -> 529
    //   526: goto -523 -> 3
    //   529: goto -325 -> 204
    //   532: aload_1
    //   533: getfield 127	o/FW:status	Lo/FV;
    //   536: astore 6
    //   538: aload_1
    //   539: getfield 127	o/FW:status	Lo/FV;
    //   542: getstatic 118	o/FV:ACCEPTED	Lo/FV;
    //   545: invokevirtual 526	o/FV:equals	(Ljava/lang/Object;)Z
    //   548: ifeq +6 -> 554
    //   551: goto -482 -> 69
    //   554: goto -503 -> 51
    //   557: iload_3
    //   558: tableswitch	default:+22->580, 0:+-502->56, 1:+68->626
    //   580: goto -524 -> 56
    //   583: iconst_1
    //   584: istore_3
    //   585: goto -364 -> 221
    //   588: getstatic 25	o/LY:ʽॱ	I
    //   591: bipush 11
    //   593: iadd
    //   594: istore_3
    //   595: iload_3
    //   596: sipush 128
    //   599: irem
    //   600: putstatic 23	o/LY:ˈ	I
    //   603: iload_3
    //   604: iconst_2
    //   605: irem
    //   606: ifeq +6 -> 612
    //   609: goto +24 -> 633
    //   612: goto -394 -> 218
    //   615: aload_0
    //   616: aload 6
    //   618: invokespecial 528	o/LY:ˋ	(Lo/FV;)Ljava/lang/String;
    //   621: astore 6
    //   623: goto -144 -> 479
    //   626: getstatic 531	o/LV$if:F15R_Black	I
    //   629: istore_3
    //   630: goto -500 -> 130
    //   633: goto -154 -> 479
    //   636: iconst_1
    //   637: istore_3
    //   638: goto -505 -> 133
    //   641: astore_1
    //   642: aload_1
    //   643: athrow
    //   644: iconst_1
    //   645: istore_3
    //   646: goto -484 -> 162
    //   649: bipush 78
    //   651: istore_3
    //   652: goto -556 -> 96
    //   655: getstatic 25	o/LY:ʽॱ	I
    //   658: bipush 123
    //   660: iadd
    //   661: istore_3
    //   662: iload_3
    //   663: sipush 128
    //   666: irem
    //   667: putstatic 23	o/LY:ˈ	I
    //   670: iload_3
    //   671: iconst_2
    //   672: irem
    //   673: ifeq +6 -> 679
    //   676: goto -475 -> 201
    //   679: goto -405 -> 274
    // Local variable table:
    //   start	length	slot	name	signature
    //   0	682	0	this	LY
    //   0	682	1	paramFW	FW
    //   0	682	2	paramFS	FS
    //   4	669	3	i	int
    //   321	22	4	j	int
    //   330	41	5	k	int
    //   8	614	6	localObject1	Object
    //   166	314	7	localObject2	Object
    // Exception table:
    //   from	to	target	type
    //   8	16	127	java/lang/Exception
    //   16	24	127	java/lang/Exception
    //   24	34	127	java/lang/Exception
    //   24	34	641	java/lang/Exception
    //   162	168	641	java/lang/Exception
    //   168	191	641	java/lang/Exception
  }
  
  public Resources getResources()
  {
    break label134;
    int i = 35;
    break label23;
    Resources localResources = oH.ˊ(super.getResources());
    i = null.length;
    switch (i)
    {
    case 35: 
    default: 
      label23:
      break;
      return localResources;
      i = 93 / 0;
      return localResources;
      for (;;)
      {
        i = 15;
        break label103;
        label70:
        i = 63;
        break;
        label76:
        i = ˈ + 23;
        ʽॱ = i % 128;
        if (i % 2 == 0) {
          break label172;
        }
      }
    }
    for (;;)
    {
      label103:
      switch (i)
      {
      }
      return localResources;
      label134:
      i = ʽॱ + 45;
      ˈ = i % 128;
      if (i % 2 != 0) {
        break;
      }
      break label70;
      localResources = oH.ˊ(super.getResources());
      break label76;
      label172:
      i = 74;
    }
  }
  
  /* Error */
  public void onAcceptMoneyClick(android.view.View paramView)
  {
    // Byte code:
    //   0: goto +21 -> 21
    //   3: iconst_1
    //   4: istore_2
    //   5: goto +49 -> 54
    //   8: iconst_1
    //   9: istore_2
    //   10: goto +288 -> 298
    //   13: iconst_0
    //   14: istore_2
    //   15: goto +238 -> 253
    //   18: astore_1
    //   19: aload_1
    //   20: athrow
    //   21: goto +449 -> 470
    //   24: goto +430 -> 454
    //   27: getstatic 25	o/LY:ʽॱ	I
    //   30: bipush 29
    //   32: iadd
    //   33: istore_2
    //   34: iload_2
    //   35: sipush 128
    //   38: irem
    //   39: putstatic 23	o/LY:ˈ	I
    //   42: iload_2
    //   43: iconst_2
    //   44: irem
    //   45: ifeq +6 -> 51
    //   48: goto +32 -> 80
    //   51: goto +76 -> 127
    //   54: iload_2
    //   55: tableswitch	default:+21->76, 0:+499->554, 1:+381->436
    //   76: goto +478 -> 554
    //   79: return
    //   80: aload_0
    //   81: aload 6
    //   83: iconst_4
    //   84: invokevirtual 178	java/lang/String:substring	(I)Ljava/lang/String;
    //   87: invokespecial 181	o/LY:ˎ	(Ljava/lang/String;)Ljava/lang/String;
    //   90: invokevirtual 185	java/lang/String:intern	()Ljava/lang/String;
    //   93: astore_1
    //   94: new 253	java/lang/NullPointerException
    //   97: dup
    //   98: invokespecial 254	java/lang/NullPointerException:<init>	()V
    //   101: athrow
    //   102: bipush 44
    //   104: istore_2
    //   105: goto +66 -> 171
    //   108: aload_0
    //   109: getfield 40	o/LY:ॱˊ	Landroid/databinding/ViewDataBinding;
    //   112: checkcast 42	o/Mq
    //   115: invokevirtual 92	o/Mq:ͺ	()Z
    //   118: pop
    //   119: new 253	java/lang/NullPointerException
    //   122: dup
    //   123: invokespecial 254	java/lang/NullPointerException:<init>	()V
    //   126: athrow
    //   127: aload_0
    //   128: aload 6
    //   130: iconst_4
    //   131: invokevirtual 178	java/lang/String:substring	(I)Ljava/lang/String;
    //   134: invokespecial 181	o/LY:ˎ	(Ljava/lang/String;)Ljava/lang/String;
    //   137: invokevirtual 185	java/lang/String:intern	()Ljava/lang/String;
    //   140: astore_1
    //   141: goto +397 -> 538
    //   144: getstatic 23	o/LY:ˈ	I
    //   147: bipush 41
    //   149: iadd
    //   150: istore_2
    //   151: iload_2
    //   152: sipush 128
    //   155: irem
    //   156: putstatic 25	o/LY:ʽॱ	I
    //   159: iload_2
    //   160: iconst_2
    //   161: irem
    //   162: ifne +6 -> 168
    //   165: goto +383 -> 548
    //   168: goto +51 -> 219
    //   171: iload_2
    //   172: lookupswitch	default:+28->200, 44:+156->328, 54:+34->206
    //   200: goto +6 -> 206
    //   203: goto +375 -> 578
    //   206: aload_0
    //   207: invokespecial 416	o/LY:ˎˏ	()Z
    //   210: ifne +6 -> 216
    //   213: goto +110 -> 323
    //   216: goto -213 -> 3
    //   219: aload_0
    //   220: invokespecial 541	o/LY:ˌ	()V
    //   223: goto -144 -> 79
    //   226: getstatic 23	o/LY:ˈ	I
    //   229: bipush 83
    //   231: iadd
    //   232: istore_2
    //   233: iload_2
    //   234: sipush 128
    //   237: irem
    //   238: putstatic 25	o/LY:ʽॱ	I
    //   241: iload_2
    //   242: iconst_2
    //   243: irem
    //   244: ifne +6 -> 250
    //   247: goto -223 -> 24
    //   250: goto +204 -> 454
    //   253: aload 6
    //   255: astore_1
    //   256: iload_2
    //   257: tableswitch	default:+23->280, 0:+281->538, 1:+-230->27
    //   280: aload 6
    //   282: astore_1
    //   283: goto +255 -> 538
    //   286: aload_0
    //   287: aload_1
    //   288: iconst_1
    //   289: invokestatic 422	android/widget/Toast:makeText	(Landroid/content/Context;Ljava/lang/CharSequence;I)Landroid/widget/Toast;
    //   292: astore_1
    //   293: aload_1
    //   294: invokevirtual 425	android/widget/Toast:show	()V
    //   297: return
    //   298: iload_2
    //   299: tableswitch	default:+21->320, 0:+-155->144, 1:+198->497
    //   320: goto -176 -> 144
    //   323: iconst_0
    //   324: istore_2
    //   325: goto -271 -> 54
    //   328: aload_0
    //   329: getstatic 544	o/LV$If:receive_money_at_lest_one_card_added	I
    //   332: invokevirtual 193	o/LY:getString	(I)Ljava/lang/String;
    //   335: astore 6
    //   337: aload_0
    //   338: invokevirtual 228	android/content/Context:getResources	()Landroid/content/res/Resources;
    //   341: ldc_w 545
    //   344: invokevirtual 232	android/content/res/Resources:getString	(I)Ljava/lang/String;
    //   347: iconst_0
    //   348: iconst_5
    //   349: invokevirtual 235	java/lang/String:substring	(II)Ljava/lang/String;
    //   352: invokevirtual 243	java/lang/String:length	()I
    //   355: istore_2
    //   356: aload_0
    //   357: invokevirtual 199	android/content/Context:getApplicationInfo	()Landroid/content/pm/ApplicationInfo;
    //   360: getfield 204	android/content/pm/ApplicationInfo:targetSdkVersion	I
    //   363: istore_3
    //   364: aload_0
    //   365: invokevirtual 199	android/content/Context:getApplicationInfo	()Landroid/content/pm/ApplicationInfo;
    //   368: getfield 204	android/content/pm/ApplicationInfo:targetSdkVersion	I
    //   371: istore 4
    //   373: aload 6
    //   375: iload_2
    //   376: sipush 191
    //   379: iadd
    //   380: iload_3
    //   381: bipush 21
    //   383: isub
    //   384: iconst_4
    //   385: newarray char
    //   387: dup
    //   388: iconst_0
    //   389: ldc -51
    //   391: castore
    //   392: dup
    //   393: iconst_1
    //   394: ldc -50
    //   396: castore
    //   397: dup
    //   398: iconst_2
    //   399: ldc -49
    //   401: castore
    //   402: dup
    //   403: iconst_3
    //   404: ldc -48
    //   406: castore
    //   407: iload 4
    //   409: bipush 22
    //   411: isub
    //   412: iconst_1
    //   413: invokestatic 210	o/LY:ˊ	(II[CIZ)Ljava/lang/String;
    //   416: invokevirtual 185	java/lang/String:intern	()Ljava/lang/String;
    //   419: invokevirtual 214	java/lang/String:startsWith	(Ljava/lang/String;)Z
    //   422: ifeq +6 -> 428
    //   425: goto +6 -> 431
    //   428: goto -415 -> 13
    //   431: iconst_1
    //   432: istore_2
    //   433: goto -180 -> 253
    //   436: aload_1
    //   437: invokevirtual 550	android/view/View:isEnabled	()Z
    //   440: ifeq +6 -> 446
    //   443: goto +6 -> 449
    //   446: goto -438 -> 8
    //   449: iconst_0
    //   450: istore_2
    //   451: goto -153 -> 298
    //   454: aload_0
    //   455: aload_1
    //   456: iconst_4
    //   457: invokevirtual 178	java/lang/String:substring	(I)Ljava/lang/String;
    //   460: invokespecial 181	o/LY:ˎ	(Ljava/lang/String;)Ljava/lang/String;
    //   463: invokevirtual 185	java/lang/String:intern	()Ljava/lang/String;
    //   466: astore_1
    //   467: goto +62 -> 529
    //   470: getstatic 25	o/LY:ʽॱ	I
    //   473: bipush 27
    //   475: iadd
    //   476: istore_2
    //   477: iload_2
    //   478: sipush 128
    //   481: irem
    //   482: putstatic 23	o/LY:ˈ	I
    //   485: iload_2
    //   486: iconst_2
    //   487: irem
    //   488: ifeq +6 -> 494
    //   491: goto -383 -> 108
    //   494: goto +4 -> 498
    //   497: return
    //   498: aload_0
    //   499: getfield 40	o/LY:ॱˊ	Landroid/databinding/ViewDataBinding;
    //   502: astore 6
    //   504: aload 6
    //   506: checkcast 42	o/Mq
    //   509: astore 6
    //   511: aload 6
    //   513: invokevirtual 92	o/Mq:ͺ	()Z
    //   516: istore 5
    //   518: iload 5
    //   520: ifeq +6 -> 526
    //   523: goto -421 -> 102
    //   526: goto +6 -> 532
    //   529: goto -243 -> 286
    //   532: bipush 54
    //   534: istore_2
    //   535: goto -364 -> 171
    //   538: aload_0
    //   539: aload_1
    //   540: iconst_1
    //   541: invokestatic 422	android/widget/Toast:makeText	(Landroid/content/Context;Ljava/lang/CharSequence;I)Landroid/widget/Toast;
    //   544: invokevirtual 425	android/widget/Toast:show	()V
    //   547: return
    //   548: goto -329 -> 219
    //   551: astore_1
    //   552: aload_1
    //   553: athrow
    //   554: getstatic 23	o/LY:ˈ	I
    //   557: bipush 69
    //   559: iadd
    //   560: istore_2
    //   561: iload_2
    //   562: sipush 128
    //   565: irem
    //   566: putstatic 25	o/LY:ʽॱ	I
    //   569: iload_2
    //   570: iconst_2
    //   571: irem
    //   572: ifne +6 -> 578
    //   575: goto -372 -> 203
    //   578: aload_0
    //   579: getstatic 428	o/LV$If:receive_money_at_lest_one_card_digitized	I
    //   582: invokevirtual 193	o/LY:getString	(I)Ljava/lang/String;
    //   585: astore_1
    //   586: aload_0
    //   587: invokevirtual 228	android/content/Context:getResources	()Landroid/content/res/Resources;
    //   590: ldc_w 551
    //   593: invokevirtual 232	android/content/res/Resources:getString	(I)Ljava/lang/String;
    //   596: iconst_0
    //   597: bipush 16
    //   599: invokevirtual 235	java/lang/String:substring	(II)Ljava/lang/String;
    //   602: iconst_0
    //   603: invokevirtual 239	java/lang/String:codePointAt	(I)I
    //   606: istore_3
    //   607: aload_0
    //   608: invokevirtual 199	android/content/Context:getApplicationInfo	()Landroid/content/pm/ApplicationInfo;
    //   611: getfield 204	android/content/pm/ApplicationInfo:targetSdkVersion	I
    //   614: istore_2
    //   615: aload_0
    //   616: invokevirtual 228	android/content/Context:getResources	()Landroid/content/res/Resources;
    //   619: ldc_w 552
    //   622: invokevirtual 232	android/content/res/Resources:getString	(I)Ljava/lang/String;
    //   625: iconst_0
    //   626: iconst_5
    //   627: invokevirtual 235	java/lang/String:substring	(II)Ljava/lang/String;
    //   630: invokevirtual 243	java/lang/String:length	()I
    //   633: istore 4
    //   635: aload_1
    //   636: iload_3
    //   637: sipush 191
    //   640: iadd
    //   641: iload_2
    //   642: bipush 21
    //   644: isub
    //   645: iconst_4
    //   646: newarray char
    //   648: dup
    //   649: iconst_0
    //   650: ldc -51
    //   652: castore
    //   653: dup
    //   654: iconst_1
    //   655: ldc -50
    //   657: castore
    //   658: dup
    //   659: iconst_2
    //   660: ldc -49
    //   662: castore
    //   663: dup
    //   664: iconst_3
    //   665: ldc -48
    //   667: castore
    //   668: iload 4
    //   670: iconst_2
    //   671: isub
    //   672: iconst_1
    //   673: invokestatic 210	o/LY:ˊ	(II[CIZ)Ljava/lang/String;
    //   676: invokevirtual 185	java/lang/String:intern	()Ljava/lang/String;
    //   679: invokevirtual 214	java/lang/String:startsWith	(Ljava/lang/String;)Z
    //   682: ifeq +6 -> 688
    //   685: goto -459 -> 226
    //   688: goto -402 -> 286
    // Local variable table:
    //   start	length	slot	name	signature
    //   0	691	0	this	LY
    //   0	691	1	paramView	android.view.View
    //   4	641	2	i	int
    //   363	278	3	j	int
    //   371	301	4	k	int
    //   516	3	5	bool	boolean
    //   81	431	6	localObject	Object
    // Exception table:
    //   from	to	target	type
    //   504	511	18	java/lang/Exception
    //   511	518	18	java/lang/Exception
    //   286	293	551	java/lang/Exception
    //   293	297	551	java/lang/Exception
    //   498	504	551	java/lang/Exception
  }
  
  public void onActivityResult(int paramInt1, int paramInt2, Intent paramIntent)
  {
    for (;;)
    {
      switch (paramInt2)
      {
      default: 
        break label141;
        label31:
        paramInt1 = ʽॱ + 83;
        ˈ = paramInt1 % 128;
        if (paramInt1 % 2 != 0) {
          break label205;
        }
        break label191;
        break label161;
        paramInt2 = 1;
      }
    }
    for (;;)
    {
      switch (paramInt2)
      {
      default: 
        return;
      case 91: 
        for (;;)
        {
          super.onActivityResult(paramInt1, paramInt2, paramIntent);
          if (paramInt2 == -1) {
            break label192;
          }
          break;
          int i;
          label141:
          label161:
          do
          {
            super.onActivityResult(paramInt1, paramInt2, paramIntent);
            i = 90 / 0;
            if (paramInt2 != -1) {
              break label208;
            }
            paramInt2 = 91;
            break;
            switch (paramInt1)
            {
            default: 
              return;
              i = ˈ + 7;
              ʽॱ = i % 128;
            }
          } while (i % 2 == 0);
        }
      }
      label191:
      label192:
      label205:
      for (;;)
      {
        return;
        paramInt2 = 0;
        break;
        return;
        ͺॱ();
        break label31;
      }
      label208:
      paramInt2 = 76;
    }
  }
  
  /* Error */
  public void onBackPressed()
  {
    // Byte code:
    //   0: goto +3 -> 3
    //   3: goto +32 -> 35
    //   6: astore_2
    //   7: aload_2
    //   8: athrow
    //   9: goto +50 -> 59
    //   12: getstatic 23	o/LY:ˈ	I
    //   15: bipush 83
    //   17: iadd
    //   18: istore_1
    //   19: iload_1
    //   20: sipush 128
    //   23: irem
    //   24: putstatic 25	o/LY:ʽॱ	I
    //   27: iload_1
    //   28: iconst_2
    //   29: irem
    //   30: ifne +4 -> 34
    //   33: return
    //   34: return
    //   35: getstatic 23	o/LY:ˈ	I
    //   38: bipush 117
    //   40: iadd
    //   41: istore_1
    //   42: iload_1
    //   43: sipush 128
    //   46: irem
    //   47: putstatic 25	o/LY:ʽॱ	I
    //   50: iload_1
    //   51: iconst_2
    //   52: irem
    //   53: ifne +6 -> 59
    //   56: goto -47 -> 9
    //   59: aload_0
    //   60: invokespecial 561	o/Mg:onBackPressed	()V
    //   63: aload_0
    //   64: invokestatic 357	o/Ic:ˏ	(Landroid/content/Context;)Lo/Ic;
    //   67: astore_2
    //   68: aload_2
    //   69: iconst_0
    //   70: iconst_0
    //   71: invokevirtual 564	o/Ic:ˏ	(ZZ)Lo/j;
    //   74: astore_2
    //   75: aload_2
    //   76: ldc_w 565
    //   79: invokevirtual 568	o/j:ॱ	(I)Lo/j;
    //   82: invokevirtual 379	o/j:ˎ	()V
    //   85: aload_0
    //   86: invokevirtual 571	o/LY:finish	()V
    //   89: goto -77 -> 12
    //   92: astore_2
    //   93: aload_2
    //   94: athrow
    // Local variable table:
    //   start	length	slot	name	signature
    //   0	95	0	this	LY
    //   18	35	1	i	int
    //   6	2	2	localException1	Exception
    //   67	9	2	localObject	Object
    //   92	2	2	localException2	Exception
    // Exception table:
    //   from	to	target	type
    //   63	68	6	java/lang/Exception
    //   68	75	6	java/lang/Exception
    //   75	89	6	java/lang/Exception
    //   35	42	92	java/lang/Exception
    //   42	50	92	java/lang/Exception
  }
  
  /* Error */
  public void onCreate(android.os.Bundle paramBundle)
  {
    // Byte code:
    //   0: goto +82 -> 82
    //   3: bipush 15
    //   5: iconst_0
    //   6: idiv
    //   7: istore_2
    //   8: return
    //   9: bipush 8
    //   11: istore_2
    //   12: goto +103 -> 115
    //   15: iload_2
    //   16: tableswitch	default:+24->40, 0:+-13->3, 1:+185->201
    //   40: goto -37 -> 3
    //   43: aload_0
    //   44: aload_1
    //   45: invokespecial 575	o/Mg:onCreate	(Landroid/os/Bundle;)V
    //   48: aload_0
    //   49: aload_0
    //   50: getfield 40	o/LY:ॱˊ	Landroid/databinding/ViewDataBinding;
    //   53: checkcast 42	o/Mq
    //   56: getfield 579	o/Mq:ʽ	Lo/у;
    //   59: invokevirtual 582	o/LY:ˊ	(Lo/у;)V
    //   62: aload_0
    //   63: invokespecial 584	o/LY:ˊᐝ	()V
    //   66: aload_0
    //   67: getfield 464	o/LY:ʿ	Ljava/lang/String;
    //   70: invokestatic 590	android/text/TextUtils:isEmpty	(Ljava/lang/CharSequence;)Z
    //   73: ifeq +6 -> 79
    //   76: goto +36 -> 112
    //   79: goto -70 -> 9
    //   82: getstatic 25	o/LY:ʽॱ	I
    //   85: bipush 75
    //   87: iadd
    //   88: istore_2
    //   89: iload_2
    //   90: sipush 128
    //   93: irem
    //   94: putstatic 23	o/LY:ˈ	I
    //   97: iload_2
    //   98: iconst_2
    //   99: irem
    //   100: ifeq +6 -> 106
    //   103: goto +54 -> 157
    //   106: goto -63 -> 43
    //   109: astore_1
    //   110: aload_1
    //   111: athrow
    //   112: bipush 10
    //   114: istore_2
    //   115: iload_2
    //   116: lookupswitch	default:+28->144, 8:+120->236, 10:+86->202
    //   144: goto +92 -> 236
    //   147: iconst_0
    //   148: istore_2
    //   149: goto -134 -> 15
    //   152: iconst_1
    //   153: istore_2
    //   154: goto -139 -> 15
    //   157: aload_0
    //   158: aload_1
    //   159: invokespecial 575	o/Mg:onCreate	(Landroid/os/Bundle;)V
    //   162: aload_0
    //   163: aload_0
    //   164: getfield 40	o/LY:ॱˊ	Landroid/databinding/ViewDataBinding;
    //   167: checkcast 42	o/Mq
    //   170: getfield 579	o/Mq:ʽ	Lo/у;
    //   173: invokevirtual 582	o/LY:ˊ	(Lo/у;)V
    //   176: aload_0
    //   177: invokespecial 584	o/LY:ˊᐝ	()V
    //   180: aload_0
    //   181: getfield 464	o/LY:ʿ	Ljava/lang/String;
    //   184: invokestatic 590	android/text/TextUtils:isEmpty	(Ljava/lang/CharSequence;)Z
    //   187: istore_3
    //   188: aconst_null
    //   189: arraylength
    //   190: istore_2
    //   191: iload_3
    //   192: ifeq +6 -> 198
    //   195: goto +7 -> 202
    //   198: goto +38 -> 236
    //   201: return
    //   202: aload_0
    //   203: invokevirtual 571	o/LY:finish	()V
    //   206: goto +30 -> 236
    //   209: getstatic 25	o/LY:ʽॱ	I
    //   212: bipush 115
    //   214: iadd
    //   215: istore_2
    //   216: iload_2
    //   217: sipush 128
    //   220: irem
    //   221: putstatic 23	o/LY:ˈ	I
    //   224: iload_2
    //   225: iconst_2
    //   226: irem
    //   227: ifeq +6 -> 233
    //   230: goto -83 -> 147
    //   233: goto -81 -> 152
    //   236: goto -27 -> 209
    // Local variable table:
    //   start	length	slot	name	signature
    //   0	239	0	this	LY
    //   0	239	1	paramBundle	android.os.Bundle
    //   7	220	2	i	int
    //   187	5	3	bool	boolean
    // Exception table:
    //   from	to	target	type
    //   202	206	109	java/lang/Exception
    //   209	216	109	java/lang/Exception
    //   216	224	109	java/lang/Exception
  }
  
  /* Error */
  public void onEmptyPaymentCardClicked(android.view.View paramView)
  {
    // Byte code:
    //   0: goto +389 -> 389
    //   3: aload_0
    //   4: invokestatic 357	o/Ic:ˏ	(Landroid/content/Context;)Lo/Ic;
    //   7: invokevirtual 595	o/Ic:ॱᐝ	()Lo/j;
    //   10: astore_1
    //   11: aload_0
    //   12: invokevirtual 228	android/content/Context:getResources	()Landroid/content/res/Resources;
    //   15: ldc_w 596
    //   18: invokevirtual 232	android/content/res/Resources:getString	(I)Ljava/lang/String;
    //   21: iconst_0
    //   22: iconst_5
    //   23: invokevirtual 235	java/lang/String:substring	(II)Ljava/lang/String;
    //   26: invokevirtual 243	java/lang/String:length	()I
    //   29: istore_2
    //   30: aload_0
    //   31: invokevirtual 228	android/content/Context:getResources	()Landroid/content/res/Resources;
    //   34: ldc_w 597
    //   37: invokevirtual 232	android/content/res/Resources:getString	(I)Ljava/lang/String;
    //   40: iconst_0
    //   41: iconst_5
    //   42: invokevirtual 235	java/lang/String:substring	(II)Ljava/lang/String;
    //   45: invokevirtual 243	java/lang/String:length	()I
    //   48: istore_3
    //   49: aload_0
    //   50: invokevirtual 330	android/content/Context:getPackageName	()Ljava/lang/String;
    //   53: invokevirtual 243	java/lang/String:length	()I
    //   56: istore 4
    //   58: aload_1
    //   59: iload_2
    //   60: sipush 261
    //   63: iadd
    //   64: iload_3
    //   65: bipush 30
    //   67: iadd
    //   68: bipush 35
    //   70: newarray char
    //   72: dup
    //   73: iconst_0
    //   74: ldc_w 598
    //   77: castore
    //   78: dup
    //   79: iconst_1
    //   80: ldc_w 599
    //   83: castore
    //   84: dup
    //   85: iconst_2
    //   86: ldc_w 600
    //   89: castore
    //   90: dup
    //   91: iconst_3
    //   92: ldc_w 601
    //   95: castore
    //   96: dup
    //   97: iconst_4
    //   98: ldc_w 602
    //   101: castore
    //   102: dup
    //   103: iconst_5
    //   104: ldc_w 602
    //   107: castore
    //   108: dup
    //   109: bipush 6
    //   111: ldc_w 315
    //   114: castore
    //   115: dup
    //   116: bipush 7
    //   118: ldc_w 317
    //   121: castore
    //   122: dup
    //   123: bipush 8
    //   125: ldc_w 603
    //   128: castore
    //   129: dup
    //   130: bipush 9
    //   132: ldc_w 604
    //   135: castore
    //   136: dup
    //   137: bipush 10
    //   139: ldc_w 605
    //   142: castore
    //   143: dup
    //   144: bipush 11
    //   146: ldc_w 315
    //   149: castore
    //   150: dup
    //   151: bipush 12
    //   153: ldc_w 362
    //   156: castore
    //   157: dup
    //   158: bipush 13
    //   160: ldc_w 606
    //   163: castore
    //   164: dup
    //   165: bipush 14
    //   167: ldc_w 604
    //   170: castore
    //   171: dup
    //   172: bipush 15
    //   174: ldc_w 316
    //   177: castore
    //   178: dup
    //   179: bipush 16
    //   181: ldc_w 370
    //   184: castore
    //   185: dup
    //   186: bipush 17
    //   188: ldc_w 362
    //   191: castore
    //   192: dup
    //   193: bipush 18
    //   195: ldc_w 315
    //   198: castore
    //   199: dup
    //   200: bipush 19
    //   202: ldc_w 607
    //   205: castore
    //   206: dup
    //   207: bipush 20
    //   209: ldc_w 604
    //   212: castore
    //   213: dup
    //   214: bipush 21
    //   216: ldc_w 601
    //   219: castore
    //   220: dup
    //   221: bipush 22
    //   223: ldc_w 602
    //   226: castore
    //   227: dup
    //   228: bipush 23
    //   230: ldc_w 603
    //   233: castore
    //   234: dup
    //   235: bipush 24
    //   237: ldc_w 321
    //   240: castore
    //   241: dup
    //   242: bipush 25
    //   244: ldc_w 367
    //   247: castore
    //   248: dup
    //   249: bipush 26
    //   251: ldc_w 321
    //   254: castore
    //   255: dup
    //   256: bipush 27
    //   258: ldc_w 603
    //   261: castore
    //   262: dup
    //   263: bipush 28
    //   265: ldc_w 607
    //   268: castore
    //   269: dup
    //   270: bipush 29
    //   272: ldc_w 372
    //   275: castore
    //   276: dup
    //   277: bipush 30
    //   279: ldc_w 599
    //   282: castore
    //   283: dup
    //   284: bipush 31
    //   286: ldc_w 608
    //   289: castore
    //   290: dup
    //   291: bipush 32
    //   293: ldc_w 320
    //   296: castore
    //   297: dup
    //   298: bipush 33
    //   300: ldc_w 609
    //   303: castore
    //   304: dup
    //   305: bipush 34
    //   307: ldc_w 609
    //   310: castore
    //   311: iload 4
    //   313: bipush 18
    //   315: iadd
    //   316: iconst_0
    //   317: invokestatic 210	o/LY:ˊ	(II[CIZ)Ljava/lang/String;
    //   320: invokevirtual 185	java/lang/String:intern	()Ljava/lang/String;
    //   323: invokevirtual 612	o/j:ˏ	(Ljava/lang/String;)Lo/j;
    //   326: invokevirtual 379	o/j:ˎ	()V
    //   329: goto +3 -> 332
    //   332: getstatic 25	o/LY:ʽॱ	I
    //   335: iconst_3
    //   336: iadd
    //   337: istore_2
    //   338: iload_2
    //   339: sipush 128
    //   342: irem
    //   343: putstatic 23	o/LY:ˈ	I
    //   346: iload_2
    //   347: iconst_2
    //   348: irem
    //   349: ifeq +4 -> 353
    //   352: return
    //   353: return
    //   354: astore_1
    //   355: aload_1
    //   356: athrow
    //   357: getstatic 25	o/LY:ʽॱ	I
    //   360: istore_2
    //   361: iload_2
    //   362: bipush 57
    //   364: iadd
    //   365: istore_2
    //   366: iload_2
    //   367: sipush 128
    //   370: irem
    //   371: putstatic 23	o/LY:ˈ	I
    //   374: iload_2
    //   375: iconst_2
    //   376: irem
    //   377: ifeq +6 -> 383
    //   380: goto -377 -> 3
    //   383: goto -380 -> 3
    //   386: astore_1
    //   387: aload_1
    //   388: athrow
    //   389: goto -32 -> 357
    // Local variable table:
    //   start	length	slot	name	signature
    //   0	392	0	this	LY
    //   0	392	1	paramView	android.view.View
    //   29	348	2	i	int
    //   48	20	3	j	int
    //   56	260	4	k	int
    // Exception table:
    //   from	to	target	type
    //   357	361	354	java/lang/Exception
    //   366	374	354	java/lang/Exception
    //   332	338	386	java/lang/Exception
    //   338	346	386	java/lang/Exception
  }
  
  public void onNewIntent(Intent paramIntent)
  {
    break label235;
    int i;
    for (;;)
    {
      switch (i)
      {
      case 49: 
      default: 
        for (;;)
        {
          ॱ(((Mq)this.ॱˊ).ˏॱ());
          break label238;
          super.onNewIntent(paramIntent);
          ˊˋ();
          paramIntent = ((Mq)this.ॱˊ).ˏॱ().status;
          FV localFV = FV.INITIATED;
          i = 60 / 0;
          if (paramIntent == localFV) {
            break label171;
          }
          i = 10;
          break;
          for (;;)
          {
            i = 87;
            break;
            label101:
            i = null.length;
            return;
            label105:
            super.onNewIntent(paramIntent);
            ˊˋ();
            if (((Mq)this.ॱˊ).ˏॱ().status == FV.INITIATED) {
              break label229;
            }
          }
          label139:
          switch (i)
          {
          }
        }
        label171:
        i = 49;
      }
    }
    label229:
    label235:
    label238:
    for (;;)
    {
      i = ʽॱ + 91;
      ˈ = i % 128;
      if (i % 2 != 0) {
        break label101;
      }
      return;
      for (;;)
      {
        i = ʽॱ + 25;
        ˈ = i % 128;
        if (i % 2 != 0) {
          break;
        }
        break label105;
        i = 96;
        break label139;
      }
    }
  }
  
  public boolean onOptionsItemSelected(MenuItem paramMenuItem)
  {
    break label16;
    int i = 89;
    label16:
    label56:
    label141:
    label197:
    label228:
    for (;;)
    {
      try
      {
        onBackPressed();
      }
      catch (Exception paramMenuItem)
      {
        throw paramMenuItem;
      }
      continue;
      return true;
      i = 1;
      break label197;
      i = ˈ + 39;
      ʽॱ = i % 128;
      if (i % 2 != 0)
      {
        break;
        i = ʽॱ + 71;
        ˈ = i % 128;
        if (i % 2 != 0) {
          break label228;
        }
        continue;
      }
      i = 86;
      for (;;)
      {
        i = paramMenuItem.getItemId();
        int j = 38 / 0;
        if (16908332 == i) {
          break label56;
        }
        break label141;
        i = ʽॱ + 77;
        ˈ = i % 128;
        if (i % 2 == 0)
        {
          break;
          return super.onOptionsItemSelected(paramMenuItem);
        }
        break;
        switch (i)
        {
        }
      }
      if (16908332 != paramMenuItem.getItemId()) {
        for (;;)
        {
          switch (i)
          {
          }
          break;
          i = 0;
        }
      }
    }
  }
  
  /* Error */
  protected void ʻॱ()
  {
    // Byte code:
    //   0: goto +367 -> 367
    //   3: iload_1
    //   4: lookupswitch	default:+28->32, 14:+61->65, 67:+64->68
    //   32: goto +33 -> 65
    //   35: getstatic 25	o/LY:ʽॱ	I
    //   38: bipush 105
    //   40: iadd
    //   41: istore_1
    //   42: iload_1
    //   43: sipush 128
    //   46: irem
    //   47: putstatic 23	o/LY:ˈ	I
    //   50: iload_1
    //   51: iconst_2
    //   52: irem
    //   53: ifeq +6 -> 59
    //   56: goto +6 -> 62
    //   59: goto +46 -> 105
    //   62: goto +43 -> 105
    //   65: goto +297 -> 362
    //   68: iconst_5
    //   69: iconst_5
    //   70: idiv
    //   71: istore_1
    //   72: goto +290 -> 362
    //   75: astore_2
    //   76: aload_2
    //   77: athrow
    //   78: aload_0
    //   79: getfield 40	o/LY:ॱˊ	Landroid/databinding/ViewDataBinding;
    //   82: checkcast 42	o/Mq
    //   85: invokevirtual 122	o/Mq:ˏॱ	()Lo/FW;
    //   88: aload_2
    //   89: invokeinterface 640 1 0
    //   94: invokevirtual 642	o/FW:ˋ	(Ljava/lang/String;)V
    //   97: goto +227 -> 324
    //   100: iconst_0
    //   101: istore_1
    //   102: goto +293 -> 395
    //   105: aload_2
    //   106: invokeinterface 640 1 0
    //   111: astore_2
    //   112: goto +17 -> 129
    //   115: astore_2
    //   116: aload_2
    //   117: invokevirtual 438	java/lang/Throwable:getCause	()Ljava/lang/Throwable;
    //   120: astore_3
    //   121: aload_3
    //   122: ifnull +5 -> 127
    //   125: aload_3
    //   126: athrow
    //   127: aload_2
    //   128: athrow
    //   129: aload_0
    //   130: invokevirtual 228	android/content/Context:getResources	()Landroid/content/res/Resources;
    //   133: ldc_w 643
    //   136: invokevirtual 232	android/content/res/Resources:getString	(I)Ljava/lang/String;
    //   139: iconst_0
    //   140: iconst_1
    //   141: invokevirtual 235	java/lang/String:substring	(II)Ljava/lang/String;
    //   144: iconst_0
    //   145: invokevirtual 239	java/lang/String:codePointAt	(I)I
    //   148: bipush 50
    //   150: isub
    //   151: aload_0
    //   152: invokevirtual 199	android/content/Context:getApplicationInfo	()Landroid/content/pm/ApplicationInfo;
    //   155: getfield 204	android/content/pm/ApplicationInfo:targetSdkVersion	I
    //   158: sipush 242
    //   161: iadd
    //   162: aload_0
    //   163: invokevirtual 330	android/content/Context:getPackageName	()Ljava/lang/String;
    //   166: bipush 6
    //   168: invokevirtual 239	java/lang/String:codePointAt	(I)I
    //   171: sipush 14680
    //   174: iadd
    //   175: i2c
    //   176: invokestatic 445	o/O:ˋ	(IIC)Ljava/lang/Object;
    //   179: checkcast 447	java/lang/Class
    //   182: ldc_w 448
    //   185: aconst_null
    //   186: invokevirtual 452	java/lang/Class:getMethod	(Ljava/lang/String;[Ljava/lang/Class;)Ljava/lang/reflect/Method;
    //   189: aconst_null
    //   190: aconst_null
    //   191: invokevirtual 458	java/lang/reflect/Method:invoke	(Ljava/lang/Object;[Ljava/lang/Object;)Ljava/lang/Object;
    //   194: astore_3
    //   195: goto +17 -> 212
    //   198: astore_2
    //   199: aload_2
    //   200: invokevirtual 438	java/lang/Throwable:getCause	()Ljava/lang/Throwable;
    //   203: astore_3
    //   204: aload_3
    //   205: ifnull +5 -> 210
    //   208: aload_3
    //   209: athrow
    //   210: aload_2
    //   211: athrow
    //   212: aload_0
    //   213: invokevirtual 330	android/content/Context:getPackageName	()Ljava/lang/String;
    //   216: bipush 9
    //   218: invokevirtual 239	java/lang/String:codePointAt	(I)I
    //   221: bipush 93
    //   223: isub
    //   224: aload_0
    //   225: invokevirtual 228	android/content/Context:getResources	()Landroid/content/res/Resources;
    //   228: ldc_w 644
    //   231: invokevirtual 232	android/content/res/Resources:getString	(I)Ljava/lang/String;
    //   234: iconst_0
    //   235: iconst_4
    //   236: invokevirtual 235	java/lang/String:substring	(II)Ljava/lang/String;
    //   239: iconst_2
    //   240: invokevirtual 239	java/lang/String:codePointAt	(I)I
    //   243: sipush 256
    //   246: iadd
    //   247: aload_0
    //   248: invokevirtual 228	android/content/Context:getResources	()Landroid/content/res/Resources;
    //   251: ldc_w 645
    //   254: invokevirtual 232	android/content/res/Resources:getString	(I)Ljava/lang/String;
    //   257: iconst_0
    //   258: iconst_5
    //   259: invokevirtual 235	java/lang/String:substring	(II)Ljava/lang/String;
    //   262: iconst_4
    //   263: invokevirtual 239	java/lang/String:codePointAt	(I)I
    //   266: sipush 14608
    //   269: iadd
    //   270: i2c
    //   271: invokestatic 445	o/O:ˋ	(IIC)Ljava/lang/Object;
    //   274: checkcast 447	java/lang/Class
    //   277: ldc_w 646
    //   280: iconst_1
    //   281: anewarray 447	java/lang/Class
    //   284: dup
    //   285: iconst_0
    //   286: ldc 65
    //   288: aastore
    //   289: invokevirtual 452	java/lang/Class:getMethod	(Ljava/lang/String;[Ljava/lang/Class;)Ljava/lang/reflect/Method;
    //   292: aload_3
    //   293: iconst_1
    //   294: anewarray 648	java/lang/Object
    //   297: dup
    //   298: iconst_0
    //   299: aload_2
    //   300: aastore
    //   301: invokevirtual 458	java/lang/reflect/Method:invoke	(Ljava/lang/Object;[Ljava/lang/Object;)Ljava/lang/Object;
    //   304: checkcast 637	com/insidesecure/hce/MatrixHCECard
    //   307: astore_2
    //   308: aload_2
    //   309: ifnull +6 -> 315
    //   312: goto -234 -> 78
    //   315: goto +47 -> 362
    //   318: bipush 67
    //   320: istore_1
    //   321: goto -318 -> 3
    //   324: getstatic 23	o/LY:ˈ	I
    //   327: bipush 117
    //   329: iadd
    //   330: istore_1
    //   331: iload_1
    //   332: sipush 128
    //   335: irem
    //   336: putstatic 25	o/LY:ʽॱ	I
    //   339: iload_1
    //   340: iconst_2
    //   341: irem
    //   342: ifne +6 -> 348
    //   345: goto -27 -> 318
    //   348: goto +8 -> 356
    //   351: iconst_1
    //   352: istore_1
    //   353: goto +42 -> 395
    //   356: bipush 14
    //   358: istore_1
    //   359: goto -356 -> 3
    //   362: aload_0
    //   363: invokespecial 620	o/LY:ˊˋ	()V
    //   366: return
    //   367: aload_0
    //   368: aload_0
    //   369: getfield 40	o/LY:ॱˊ	Landroid/databinding/ViewDataBinding;
    //   372: checkcast 42	o/Mq
    //   375: invokevirtual 122	o/Mq:ˏॱ	()Lo/FW;
    //   378: invokevirtual 130	o/LY:ˏ	(Lo/FW;)Lcom/insidesecure/hce/MatrixHCECard;
    //   381: astore_2
    //   382: aload_2
    //   383: ifnull +6 -> 389
    //   386: goto -286 -> 100
    //   389: goto -38 -> 351
    //   392: astore_2
    //   393: aload_2
    //   394: athrow
    //   395: iload_1
    //   396: tableswitch	default:+24->420, 0:+-361->35, 1:+-34->362
    //   420: goto -385 -> 35
    // Local variable table:
    //   start	length	slot	name	signature
    //   0	423	0	this	LY
    //   3	393	1	i	int
    //   75	31	2	localException1	Exception
    //   111	1	2	str	String
    //   115	13	2	localObject1	Object
    //   198	102	2	localObject2	Object
    //   307	76	2	localMatrixHCECard	MatrixHCECard
    //   392	2	2	localException2	Exception
    //   120	173	3	localObject3	Object
    // Exception table:
    //   from	to	target	type
    //   105	112	75	java/lang/Exception
    //   116	121	75	java/lang/Exception
    //   125	127	75	java/lang/Exception
    //   127	129	75	java/lang/Exception
    //   199	204	75	java/lang/Exception
    //   208	210	75	java/lang/Exception
    //   210	212	75	java/lang/Exception
    //   129	195	115	finally
    //   212	308	198	finally
    //   116	121	392	java/lang/Exception
    //   125	127	392	java/lang/Exception
    //   127	129	392	java/lang/Exception
  }
  
  /* Error */
  public void ˋ(ز paramز)
  {
    // Byte code:
    //   0: goto +193 -> 193
    //   3: goto +119 -> 122
    //   6: getstatic 23	o/LY:ˈ	I
    //   9: istore_2
    //   10: iload_2
    //   11: bipush 95
    //   13: iadd
    //   14: istore_2
    //   15: iload_2
    //   16: sipush 128
    //   19: irem
    //   20: putstatic 25	o/LY:ʽॱ	I
    //   23: iload_2
    //   24: iconst_2
    //   25: irem
    //   26: ifne +6 -> 32
    //   29: goto +49 -> 78
    //   32: goto +164 -> 196
    //   35: astore_1
    //   36: aload_1
    //   37: athrow
    //   38: iload_2
    //   39: tableswitch	default:+21->60, 0:+38->77, 1:+104->143
    //   60: goto +17 -> 77
    //   63: getstatic 654	o/LV$ˋ:ic_white_close	I
    //   66: istore_2
    //   67: goto -64 -> 3
    //   70: getstatic 657	o/LV$ˋ:ic_back_white	I
    //   73: istore_2
    //   74: goto +48 -> 122
    //   77: return
    //   78: aload_1
    //   79: iconst_1
    //   80: invokevirtual 661	o/ز:ॱ	(Z)V
    //   83: aload_1
    //   84: iconst_0
    //   85: invokevirtual 663	o/ز:ˏ	(Z)V
    //   88: aload_0
    //   89: invokevirtual 666	o/LY:ʻ	()Lo/ز;
    //   92: ifnull +6 -> 98
    //   95: goto +38 -> 133
    //   98: goto +30 -> 128
    //   101: astore_1
    //   102: aload_1
    //   103: athrow
    //   104: aload_0
    //   105: invokevirtual 666	o/LY:ʻ	()Lo/ز;
    //   108: astore_1
    //   109: aload_0
    //   110: invokevirtual 668	o/LY:ˊˊ	()Z
    //   113: ifeq +6 -> 119
    //   116: goto -46 -> 70
    //   119: goto -56 -> 63
    //   122: aload_1
    //   123: iload_2
    //   124: invokevirtual 670	o/ز:ˏ	(I)V
    //   127: return
    //   128: iconst_0
    //   129: istore_2
    //   130: goto -92 -> 38
    //   133: iconst_1
    //   134: istore_2
    //   135: goto -97 -> 38
    //   138: iconst_1
    //   139: istore_2
    //   140: goto +81 -> 221
    //   143: getstatic 25	o/LY:ʽॱ	I
    //   146: bipush 69
    //   148: iadd
    //   149: istore_2
    //   150: iload_2
    //   151: sipush 128
    //   154: irem
    //   155: putstatic 23	o/LY:ˈ	I
    //   158: iload_2
    //   159: iconst_2
    //   160: irem
    //   161: ifeq +6 -> 167
    //   164: goto +6 -> 170
    //   167: goto -63 -> 104
    //   170: aload_0
    //   171: invokevirtual 666	o/LY:ʻ	()Lo/ز;
    //   174: astore_1
    //   175: aload_0
    //   176: invokevirtual 668	o/LY:ˊˊ	()Z
    //   179: istore_3
    //   180: aconst_null
    //   181: arraylength
    //   182: istore_2
    //   183: iload_3
    //   184: ifeq +6 -> 190
    //   187: goto -117 -> 70
    //   190: goto -127 -> 63
    //   193: goto -187 -> 6
    //   196: aload_1
    //   197: iconst_1
    //   198: invokevirtual 661	o/ز:ॱ	(Z)V
    //   201: aload_1
    //   202: iconst_1
    //   203: invokevirtual 663	o/ز:ˏ	(Z)V
    //   206: aload_0
    //   207: invokevirtual 666	o/LY:ʻ	()Lo/ز;
    //   210: astore_1
    //   211: aload_1
    //   212: ifnull +6 -> 218
    //   215: goto -77 -> 138
    //   218: goto +29 -> 247
    //   221: iload_2
    //   222: tableswitch	default:+22->244, 0:+-145->77, 1:+-79->143
    //   244: goto -101 -> 143
    //   247: iconst_0
    //   248: istore_2
    //   249: goto -28 -> 221
    // Local variable table:
    //   start	length	slot	name	signature
    //   0	252	0	this	LY
    //   0	252	1	paramز	ز
    //   9	240	2	i	int
    //   179	5	3	bool	boolean
    // Exception table:
    //   from	to	target	type
    //   6	10	35	java/lang/Exception
    //   15	23	35	java/lang/Exception
    //   201	206	35	java/lang/Exception
    //   206	211	35	java/lang/Exception
    //   196	201	101	java/lang/Exception
  }
  
  public int ˎ()
  {
    for (;;)
    {
      int i = 78;
      break label16;
      return LV.iF.activity_accept_send_money;
      label16:
      do
      {
        i = 64;
        switch (i)
        {
        case 78: 
        default: 
          break;
        case 64: 
          i = LV.iF.activity_accept_send_money;
          int j = 16 / 0;
          return i;
          i = ˈ + 57;
          ʽॱ = i % 128;
        }
      } while (i % 2 == 0);
    }
  }
  
  protected void ˎ(FW paramFW, FS paramFS)
  {
    break label56;
    return;
    int i = 3;
    break label59;
    return;
    for (;;)
    {
      i = 0;
      break label236;
      label56:
      label59:
      label89:
      label128:
      label157:
      do
      {
        ॱ(((Mq)this.ॱˊ).ˏॱ());
        i = ʽॱ + 29;
        ˈ = i % 128;
        if (i % 2 != 0) {
          break label263;
        }
        break label157;
        break label210;
        switch (i)
        {
        }
        return;
        ॱ(paramFW, paramFS);
        ˊˋ();
        ˉ();
        if (((Mq)this.ॱˊ).ˏॱ().status == FV.INITIATED) {
          break;
        }
        break label269;
        for (;;)
        {
          switch (i)
          {
          case 40: 
          default: 
            return;
            i = 36;
          }
        }
        return;
        ॱ(paramFW, paramFS);
        ˊˋ();
        ˉ();
        paramFW = ((Mq)this.ॱˊ).ˏॱ().status;
        paramFS = FV.INITIATED;
        i = 33 / 0;
      } while (paramFW == paramFS);
      return;
      label210:
      i = ʽॱ + 5;
      ˈ = i % 128;
      if (i % 2 == 0) {
        break label275;
      }
    }
    for (;;)
    {
      label236:
      switch (i)
      {
      }
      break label89;
      label263:
      i = 40;
      break label128;
      label269:
      i = 57;
      break;
      label275:
      i = 1;
    }
  }
}
