package o;

import android.content.Intent;
import android.databinding.ViewDataBinding;
import android.os.Bundle;
import android.view.View;

public abstract class LZ<VDB extends ViewDataBinding>
  extends Mg<VDB>
{
  private static boolean ˉ;
  private static byte ˊˋ;
  private static int ˊᐝ;
  private static char[] ˋˊ;
  private static int ˋˋ;
  private static int ˋᐝ;
  private static boolean ˍ;
  protected HQ ʼॱ;
  protected Gh ʽॱ;
  protected HQ ʾ;
  protected String ˈ;
  
  static
  {
    for (;;)
    {
      int i = ˋˋ + 37;
      ˋᐝ = i % 128;
      if (i % 2 == 0) {
        return;
      }
      return;
      ˋˋ = 0;
      ˋᐝ = 1;
      ˊˋ();
      ˊˋ = -102;
    }
  }
  
  public LZ() {}
  
  /* Error */
  private void ˉ()
  {
    // Byte code:
    //   0: goto +130 -> 130
    //   3: aload_0
    //   4: aload_2
    //   5: invokestatic 45	o/HQ:ˏ	(Lcom/insidesecure/hce/MatrixHCECard;)Lo/HQ;
    //   8: putfield 47	o/LZ:ʾ	Lo/HQ;
    //   11: goto +330 -> 341
    //   14: bipush 46
    //   16: istore_1
    //   17: goto +54 -> 71
    //   20: bipush 48
    //   22: istore_1
    //   23: goto +48 -> 71
    //   26: astore_2
    //   27: aload_2
    //   28: athrow
    //   29: aload_3
    //   30: astore_2
    //   31: iload_1
    //   32: lookupswitch	default:+28->60, 77:+334->366, 84:+-29->3
    //   60: aload_3
    //   61: astore_2
    //   62: goto -59 -> 3
    //   65: bipush 84
    //   67: istore_1
    //   68: goto -39 -> 29
    //   71: iload_1
    //   72: lookupswitch	default:+28->100, 46:+300->372, 48:+62->134
    //   100: goto +34 -> 134
    //   103: getstatic 29	o/LZ:ˋᐝ	I
    //   106: bipush 51
    //   108: iadd
    //   109: istore_1
    //   110: iload_1
    //   111: sipush 128
    //   114: irem
    //   115: putstatic 27	o/LZ:ˋˋ	I
    //   118: iload_1
    //   119: iconst_2
    //   120: irem
    //   121: ifeq +6 -> 127
    //   124: goto -104 -> 20
    //   127: goto -113 -> 14
    //   130: goto -27 -> 103
    //   133: return
    //   134: goto +17 -> 151
    //   137: astore_2
    //   138: aload_2
    //   139: invokevirtual 53	java/lang/Throwable:getCause	()Ljava/lang/Throwable;
    //   142: astore_3
    //   143: aload_3
    //   144: ifnull +5 -> 149
    //   147: aload_3
    //   148: athrow
    //   149: aload_2
    //   150: athrow
    //   151: aload_0
    //   152: invokevirtual 59	android/content/Context:getResources	()Landroid/content/res/Resources;
    //   155: ldc 60
    //   157: invokevirtual 66	android/content/res/Resources:getString	(I)Ljava/lang/String;
    //   160: iconst_0
    //   161: iconst_4
    //   162: invokevirtual 72	java/lang/String:substring	(II)Ljava/lang/String;
    //   165: iconst_1
    //   166: invokevirtual 76	java/lang/String:codePointAt	(I)I
    //   169: bipush 22
    //   171: isub
    //   172: aload_0
    //   173: invokevirtual 80	android/content/Context:getPackageName	()Ljava/lang/String;
    //   176: invokevirtual 84	java/lang/String:length	()I
    //   179: sipush 256
    //   182: iadd
    //   183: aload_0
    //   184: invokevirtual 88	android/content/Context:getApplicationInfo	()Landroid/content/pm/ApplicationInfo;
    //   187: getfield 93	android/content/pm/ApplicationInfo:targetSdkVersion	I
    //   190: sipush 14763
    //   193: iadd
    //   194: i2c
    //   195: invokestatic 99	o/O:ˋ	(IIC)Ljava/lang/Object;
    //   198: checkcast 101	java/lang/Class
    //   201: ldc 102
    //   203: aconst_null
    //   204: invokevirtual 106	java/lang/Class:getMethod	(Ljava/lang/String;[Ljava/lang/Class;)Ljava/lang/reflect/Method;
    //   207: aconst_null
    //   208: aconst_null
    //   209: invokevirtual 112	java/lang/reflect/Method:invoke	(Ljava/lang/Object;[Ljava/lang/Object;)Ljava/lang/Object;
    //   212: astore_2
    //   213: aload_0
    //   214: getfield 114	o/LZ:ʽॱ	Lo/Gh;
    //   217: getfield 119	o/Gh:fromCardUuid	Ljava/lang/String;
    //   220: astore_3
    //   221: goto +17 -> 238
    //   224: astore_2
    //   225: aload_2
    //   226: invokevirtual 53	java/lang/Throwable:getCause	()Ljava/lang/Throwable;
    //   229: astore_3
    //   230: aload_3
    //   231: ifnull +5 -> 236
    //   234: aload_3
    //   235: athrow
    //   236: aload_2
    //   237: athrow
    //   238: aload_0
    //   239: invokevirtual 88	android/content/Context:getApplicationInfo	()Landroid/content/pm/ApplicationInfo;
    //   242: getfield 93	android/content/pm/ApplicationInfo:targetSdkVersion	I
    //   245: bipush 21
    //   247: isub
    //   248: aload_0
    //   249: invokevirtual 59	android/content/Context:getResources	()Landroid/content/res/Resources;
    //   252: ldc 120
    //   254: invokevirtual 66	android/content/res/Resources:getString	(I)Ljava/lang/String;
    //   257: iconst_0
    //   258: iconst_5
    //   259: invokevirtual 72	java/lang/String:substring	(II)Ljava/lang/String;
    //   262: iconst_0
    //   263: invokevirtual 76	java/lang/String:codePointAt	(I)I
    //   266: sipush 262
    //   269: iadd
    //   270: aload_0
    //   271: invokevirtual 59	android/content/Context:getResources	()Landroid/content/res/Resources;
    //   274: ldc 121
    //   276: invokevirtual 66	android/content/res/Resources:getString	(I)Ljava/lang/String;
    //   279: iconst_0
    //   280: iconst_4
    //   281: invokevirtual 72	java/lang/String:substring	(II)Ljava/lang/String;
    //   284: invokevirtual 84	java/lang/String:length	()I
    //   287: sipush 14784
    //   290: iadd
    //   291: i2c
    //   292: invokestatic 99	o/O:ˋ	(IIC)Ljava/lang/Object;
    //   295: checkcast 101	java/lang/Class
    //   298: ldc 123
    //   300: iconst_1
    //   301: anewarray 101	java/lang/Class
    //   304: dup
    //   305: iconst_0
    //   306: ldc 68
    //   308: aastore
    //   309: invokevirtual 106	java/lang/Class:getMethod	(Ljava/lang/String;[Ljava/lang/Class;)Ljava/lang/reflect/Method;
    //   312: aload_2
    //   313: iconst_1
    //   314: anewarray 125	java/lang/Object
    //   317: dup
    //   318: iconst_0
    //   319: aload_3
    //   320: aastore
    //   321: invokevirtual 112	java/lang/reflect/Method:invoke	(Ljava/lang/Object;[Ljava/lang/Object;)Ljava/lang/Object;
    //   324: checkcast 127	com/insidesecure/hce/MatrixHCECard
    //   327: astore_2
    //   328: aconst_null
    //   329: arraylength
    //   330: istore_1
    //   331: aload_2
    //   332: ifnull +6 -> 338
    //   335: goto -332 -> 3
    //   338: goto +28 -> 366
    //   341: getstatic 27	o/LZ:ˋˋ	I
    //   344: bipush 13
    //   346: iadd
    //   347: istore_1
    //   348: iload_1
    //   349: sipush 128
    //   352: irem
    //   353: putstatic 29	o/LZ:ˋᐝ	I
    //   356: iload_1
    //   357: iconst_2
    //   358: irem
    //   359: ifne +4 -> 363
    //   362: return
    //   363: goto -230 -> 133
    //   366: aload_0
    //   367: aconst_null
    //   368: putfield 47	o/LZ:ʾ	Lo/HQ;
    //   371: return
    //   372: goto +17 -> 389
    //   375: astore_2
    //   376: aload_2
    //   377: invokevirtual 53	java/lang/Throwable:getCause	()Ljava/lang/Throwable;
    //   380: astore_3
    //   381: aload_3
    //   382: ifnull +5 -> 387
    //   385: aload_3
    //   386: athrow
    //   387: aload_2
    //   388: athrow
    //   389: aload_0
    //   390: invokevirtual 59	android/content/Context:getResources	()Landroid/content/res/Resources;
    //   393: ldc -128
    //   395: invokevirtual 66	android/content/res/Resources:getString	(I)Ljava/lang/String;
    //   398: iconst_0
    //   399: iconst_4
    //   400: invokevirtual 72	java/lang/String:substring	(II)Ljava/lang/String;
    //   403: iconst_2
    //   404: invokevirtual 76	java/lang/String:codePointAt	(I)I
    //   407: bipush 7
    //   409: isub
    //   410: aload_0
    //   411: invokevirtual 80	android/content/Context:getPackageName	()Ljava/lang/String;
    //   414: invokevirtual 84	java/lang/String:length	()I
    //   417: sipush 256
    //   420: iadd
    //   421: aload_0
    //   422: invokevirtual 59	android/content/Context:getResources	()Landroid/content/res/Resources;
    //   425: ldc -127
    //   427: invokevirtual 66	android/content/res/Resources:getString	(I)Ljava/lang/String;
    //   430: iconst_0
    //   431: bipush 11
    //   433: invokevirtual 72	java/lang/String:substring	(II)Ljava/lang/String;
    //   436: invokevirtual 84	java/lang/String:length	()I
    //   439: sipush 14777
    //   442: iadd
    //   443: i2c
    //   444: invokestatic 99	o/O:ˋ	(IIC)Ljava/lang/Object;
    //   447: checkcast 101	java/lang/Class
    //   450: ldc 102
    //   452: aconst_null
    //   453: invokevirtual 106	java/lang/Class:getMethod	(Ljava/lang/String;[Ljava/lang/Class;)Ljava/lang/reflect/Method;
    //   456: aconst_null
    //   457: aconst_null
    //   458: invokevirtual 112	java/lang/reflect/Method:invoke	(Ljava/lang/Object;[Ljava/lang/Object;)Ljava/lang/Object;
    //   461: astore_2
    //   462: aload_0
    //   463: getfield 114	o/LZ:ʽॱ	Lo/Gh;
    //   466: getfield 119	o/Gh:fromCardUuid	Ljava/lang/String;
    //   469: astore_3
    //   470: goto +17 -> 487
    //   473: astore_2
    //   474: aload_2
    //   475: invokevirtual 53	java/lang/Throwable:getCause	()Ljava/lang/Throwable;
    //   478: astore_3
    //   479: aload_3
    //   480: ifnull +5 -> 485
    //   483: aload_3
    //   484: athrow
    //   485: aload_2
    //   486: athrow
    //   487: aload_0
    //   488: invokevirtual 88	android/content/Context:getApplicationInfo	()Landroid/content/pm/ApplicationInfo;
    //   491: getfield 93	android/content/pm/ApplicationInfo:targetSdkVersion	I
    //   494: bipush 21
    //   496: isub
    //   497: aload_0
    //   498: invokevirtual 88	android/content/Context:getApplicationInfo	()Landroid/content/pm/ApplicationInfo;
    //   501: getfield 93	android/content/pm/ApplicationInfo:targetSdkVersion	I
    //   504: sipush 242
    //   507: iadd
    //   508: aload_0
    //   509: invokevirtual 59	android/content/Context:getResources	()Landroid/content/res/Resources;
    //   512: ldc -126
    //   514: invokevirtual 66	android/content/res/Resources:getString	(I)Ljava/lang/String;
    //   517: iconst_0
    //   518: iconst_4
    //   519: invokevirtual 72	java/lang/String:substring	(II)Ljava/lang/String;
    //   522: invokevirtual 84	java/lang/String:length	()I
    //   525: sipush 14784
    //   528: iadd
    //   529: i2c
    //   530: invokestatic 99	o/O:ˋ	(IIC)Ljava/lang/Object;
    //   533: checkcast 101	java/lang/Class
    //   536: ldc 123
    //   538: iconst_1
    //   539: anewarray 101	java/lang/Class
    //   542: dup
    //   543: iconst_0
    //   544: ldc 68
    //   546: aastore
    //   547: invokevirtual 106	java/lang/Class:getMethod	(Ljava/lang/String;[Ljava/lang/Class;)Ljava/lang/reflect/Method;
    //   550: aload_2
    //   551: iconst_1
    //   552: anewarray 125	java/lang/Object
    //   555: dup
    //   556: iconst_0
    //   557: aload_3
    //   558: aastore
    //   559: invokevirtual 112	java/lang/reflect/Method:invoke	(Ljava/lang/Object;[Ljava/lang/Object;)Ljava/lang/Object;
    //   562: checkcast 127	com/insidesecure/hce/MatrixHCECard
    //   565: astore_3
    //   566: aload_3
    //   567: ifnull +6 -> 573
    //   570: goto -505 -> 65
    //   573: goto +3 -> 576
    //   576: bipush 77
    //   578: istore_1
    //   579: goto -550 -> 29
    // Local variable table:
    //   start	length	slot	name	signature
    //   0	582	0	this	LZ
    //   16	563	1	i	int
    //   4	1	2	localMatrixHCECard1	com.insidesecure.hce.MatrixHCECard
    //   26	2	2	localException	Exception
    //   30	32	2	localObject1	Object
    //   137	13	2	localObject2	Object
    //   212	1	2	localObject3	Object
    //   224	89	2	localObject4	Object
    //   327	5	2	localMatrixHCECard2	com.insidesecure.hce.MatrixHCECard
    //   375	13	2	localObject5	Object
    //   461	1	2	localObject6	Object
    //   473	78	2	localObject7	Object
    //   29	538	3	localObject8	Object
    // Exception table:
    //   from	to	target	type
    //   341	348	26	java/lang/Exception
    //   348	356	26	java/lang/Exception
    //   151	213	137	finally
    //   238	328	224	finally
    //   389	462	375	finally
    //   487	566	473	finally
  }
  
  static void ˊˋ()
  {
    ˍ = true;
    ˉ = true;
    ˋˊ = new char[] { 126, 145, 141, 139, 122, 120, 135, 140, 124, 130, 136, 127, 134, 137, 133, 125, 142, 98, 57, 146, 58, 128, 30, 51, 36, 37, 108, 104, 70, 81, 78, 82, 74, 110, 109, 95 };
    ˊᐝ = 25;
  }
  
  /* Error */
  private static String ˋ(byte[] paramArrayOfByte, int[] paramArrayOfInt, char[] paramArrayOfChar, int paramInt)
  {
    // Byte code:
    //   0: goto +369 -> 369
    //   3: getstatic 134	o/LZ:ˉ	Z
    //   6: ifeq +6 -> 12
    //   9: goto +233 -> 242
    //   12: goto +431 -> 443
    //   15: iload 4
    //   17: iload 7
    //   19: if_icmpge +6 -> 25
    //   22: goto +86 -> 108
    //   25: goto +176 -> 201
    //   28: iconst_1
    //   29: istore 5
    //   31: iload 5
    //   33: tableswitch	default:+23->56, 0:+57->90, 1:+345->378
    //   56: goto +34 -> 90
    //   59: aload_1
    //   60: iload 4
    //   62: aload 8
    //   64: aload_0
    //   65: iload 7
    //   67: iconst_1
    //   68: isub
    //   69: iload 4
    //   71: isub
    //   72: baload
    //   73: iload_3
    //   74: iadd
    //   75: caload
    //   76: iload 6
    //   78: isub
    //   79: i2c
    //   80: castore
    //   81: iload 4
    //   83: iconst_1
    //   84: iadd
    //   85: istore 4
    //   87: goto +363 -> 450
    //   90: new 68	java/lang/String
    //   93: dup
    //   94: aload_0
    //   95: invokespecial 178	java/lang/String:<init>	([C)V
    //   98: areturn
    //   99: iconst_0
    //   100: istore 5
    //   102: goto +394 -> 496
    //   105: goto +242 -> 347
    //   108: iconst_0
    //   109: istore 5
    //   111: goto +12 -> 123
    //   114: new 68	java/lang/String
    //   117: dup
    //   118: aload_1
    //   119: invokespecial 178	java/lang/String:<init>	([C)V
    //   122: areturn
    //   123: iload 5
    //   125: tableswitch	default:+23->148, 0:+124->249, 1:+471->596
    //   148: goto +101 -> 249
    //   151: getstatic 27	o/LZ:ˋˋ	I
    //   154: bipush 27
    //   156: iadd
    //   157: istore 4
    //   159: iload 4
    //   161: sipush 128
    //   164: irem
    //   165: putstatic 29	o/LZ:ˋᐝ	I
    //   168: iload 4
    //   170: iconst_2
    //   171: irem
    //   172: ifne +6 -> 178
    //   175: goto -70 -> 105
    //   178: goto +169 -> 347
    //   181: iload 4
    //   183: iload 7
    //   185: if_icmpge +6 -> 191
    //   188: goto -160 -> 28
    //   191: goto +181 -> 372
    //   194: iload 5
    //   196: istore 4
    //   198: goto +361 -> 559
    //   201: iconst_1
    //   202: istore 5
    //   204: goto -81 -> 123
    //   207: iconst_1
    //   208: istore 4
    //   210: iload 4
    //   212: tableswitch	default:+24->236, 0:+-18->194, 1:+83->295
    //   236: goto -42 -> 194
    //   239: goto +333 -> 572
    //   242: bipush 67
    //   244: istore 4
    //   246: goto +166 -> 412
    //   249: aload_0
    //   250: iload 4
    //   252: aload 8
    //   254: aload_2
    //   255: iload 7
    //   257: iconst_1
    //   258: isub
    //   259: iload 4
    //   261: isub
    //   262: caload
    //   263: iload_3
    //   264: isub
    //   265: caload
    //   266: iload 6
    //   268: isub
    //   269: i2c
    //   270: castore
    //   271: iload 4
    //   273: iconst_1
    //   274: iadd
    //   275: istore 4
    //   277: goto -262 -> 15
    //   280: aload_1
    //   281: arraylength
    //   282: istore 7
    //   284: iload 7
    //   286: newarray char
    //   288: astore_0
    //   289: iconst_0
    //   290: istore 4
    //   292: goto -111 -> 181
    //   295: iload 5
    //   297: istore 4
    //   299: goto +260 -> 559
    //   302: goto -287 -> 15
    //   305: aload_0
    //   306: arraylength
    //   307: istore 7
    //   309: iload 7
    //   311: newarray char
    //   313: astore_1
    //   314: iconst_0
    //   315: istore 5
    //   317: getstatic 27	o/LZ:ˋˋ	I
    //   320: bipush 15
    //   322: iadd
    //   323: istore 4
    //   325: iload 4
    //   327: sipush 128
    //   330: irem
    //   331: putstatic 29	o/LZ:ˋᐝ	I
    //   334: iload 4
    //   336: iconst_2
    //   337: irem
    //   338: ifne +6 -> 344
    //   341: goto +112 -> 453
    //   344: goto -137 -> 207
    //   347: getstatic 172	o/LZ:ˋˊ	[C
    //   350: astore 8
    //   352: getstatic 174	o/LZ:ˊᐝ	I
    //   355: istore 6
    //   357: getstatic 132	o/LZ:ˍ	Z
    //   360: ifeq +6 -> 366
    //   363: goto -58 -> 305
    //   366: goto -363 -> 3
    //   369: goto -218 -> 151
    //   372: iconst_0
    //   373: istore 5
    //   375: goto -344 -> 31
    //   378: getstatic 27	o/LZ:ˋˋ	I
    //   381: istore 5
    //   383: iload 5
    //   385: bipush 41
    //   387: iadd
    //   388: istore 5
    //   390: iload 5
    //   392: sipush 128
    //   395: irem
    //   396: putstatic 29	o/LZ:ˋᐝ	I
    //   399: iload 5
    //   401: iconst_2
    //   402: irem
    //   403: ifne +6 -> 409
    //   406: goto +184 -> 590
    //   409: goto +53 -> 462
    //   412: iload 4
    //   414: lookupswitch	default:+26->440, 62:+-134->280, 67:+109->523
    //   440: goto -160 -> 280
    //   443: bipush 62
    //   445: istore 4
    //   447: goto -35 -> 412
    //   450: goto +109 -> 559
    //   453: iconst_0
    //   454: istore 4
    //   456: goto -246 -> 210
    //   459: astore_0
    //   460: aload_0
    //   461: athrow
    //   462: aload_0
    //   463: iload 4
    //   465: aload 8
    //   467: aload_1
    //   468: iload 7
    //   470: iconst_1
    //   471: isub
    //   472: iload 4
    //   474: isub
    //   475: iaload
    //   476: iload_3
    //   477: isub
    //   478: caload
    //   479: iload 6
    //   481: isub
    //   482: i2c
    //   483: castore
    //   484: iload 4
    //   486: iconst_1
    //   487: iadd
    //   488: istore 4
    //   490: goto +103 -> 593
    //   493: astore_0
    //   494: aload_0
    //   495: athrow
    //   496: iload 5
    //   498: tableswitch	default:+22->520, 0:+-439->59, 1:+-384->114
    //   520: goto -461 -> 59
    //   523: getstatic 29	o/LZ:ˋᐝ	I
    //   526: bipush 93
    //   528: iadd
    //   529: istore 4
    //   531: iload 4
    //   533: sipush 128
    //   536: irem
    //   537: putstatic 27	o/LZ:ˋˋ	I
    //   540: iload 4
    //   542: iconst_2
    //   543: irem
    //   544: ifeq +6 -> 550
    //   547: goto -308 -> 239
    //   550: goto +22 -> 572
    //   553: iconst_1
    //   554: istore 5
    //   556: goto -60 -> 496
    //   559: iload 4
    //   561: iload 7
    //   563: if_icmpge +6 -> 569
    //   566: goto -467 -> 99
    //   569: goto -16 -> 553
    //   572: aload_2
    //   573: arraylength
    //   574: istore 7
    //   576: iload 7
    //   578: newarray char
    //   580: astore_0
    //   581: iconst_0
    //   582: istore 4
    //   584: goto +21 -> 605
    //   587: goto -572 -> 15
    //   590: goto -128 -> 462
    //   593: goto -412 -> 181
    //   596: new 68	java/lang/String
    //   599: dup
    //   600: aload_0
    //   601: invokespecial 178	java/lang/String:<init>	([C)V
    //   604: areturn
    //   605: getstatic 29	o/LZ:ˋᐝ	I
    //   608: istore 5
    //   610: iload 5
    //   612: bipush 47
    //   614: iadd
    //   615: istore 5
    //   617: iload 5
    //   619: sipush 128
    //   622: irem
    //   623: putstatic 27	o/LZ:ˋˋ	I
    //   626: iload 5
    //   628: iconst_2
    //   629: irem
    //   630: ifeq +6 -> 636
    //   633: goto -331 -> 302
    //   636: goto -49 -> 587
    // Local variable table:
    //   start	length	slot	name	signature
    //   0	639	0	paramArrayOfByte	byte[]
    //   0	639	1	paramArrayOfInt	int[]
    //   0	639	2	paramArrayOfChar	char[]
    //   0	639	3	paramInt	int
    //   15	568	4	i	int
    //   29	601	5	j	int
    //   76	406	6	k	int
    //   17	560	7	m	int
    //   62	404	8	arrayOfChar	char[]
    // Exception table:
    //   from	to	target	type
    //   378	383	459	java/lang/Exception
    //   605	610	459	java/lang/Exception
    //   390	399	493	java/lang/Exception
    //   617	626	493	java/lang/Exception
  }
  
  /* Error */
  private String ˎ(String paramString)
  {
    // Byte code:
    //   0: goto +31 -> 31
    //   3: iload_2
    //   4: tableswitch	default:+24->28, 0:+296->300, 1:+38->42
    //   28: goto +272 -> 300
    //   31: goto +240 -> 271
    //   34: goto +212 -> 246
    //   37: iconst_0
    //   38: istore_3
    //   39: goto +88 -> 127
    //   42: aload_1
    //   43: bipush 10
    //   45: newarray byte
    //   47: dup
    //   48: iconst_0
    //   49: ldc -73
    //   51: bastore
    //   52: dup
    //   53: iconst_1
    //   54: ldc -72
    //   56: bastore
    //   57: dup
    //   58: iconst_2
    //   59: ldc -71
    //   61: bastore
    //   62: dup
    //   63: iconst_3
    //   64: ldc -70
    //   66: bastore
    //   67: dup
    //   68: iconst_4
    //   69: ldc -69
    //   71: bastore
    //   72: dup
    //   73: iconst_5
    //   74: ldc -69
    //   76: bastore
    //   77: dup
    //   78: bipush 6
    //   80: ldc -72
    //   82: bastore
    //   83: dup
    //   84: bipush 7
    //   86: ldc -68
    //   88: bastore
    //   89: dup
    //   90: bipush 8
    //   92: ldc -67
    //   94: bastore
    //   95: dup
    //   96: bipush 9
    //   98: ldc -66
    //   100: bastore
    //   101: aconst_null
    //   102: aconst_null
    //   103: bipush 127
    //   105: invokestatic 192	o/LZ:ˋ	([B[I[CI)Ljava/lang/String;
    //   108: invokevirtual 195	java/lang/String:intern	()Ljava/lang/String;
    //   111: invokevirtual 199	java/lang/String:getBytes	(Ljava/lang/String;)[B
    //   114: astore 4
    //   116: aload 4
    //   118: arraylength
    //   119: newarray byte
    //   121: astore_1
    //   122: iconst_0
    //   123: istore_2
    //   124: goto +286 -> 410
    //   127: iload_3
    //   128: tableswitch	default:+24->152, 0:+94->222, 1:+32->160
    //   152: goto +8 -> 160
    //   155: iconst_1
    //   156: istore_2
    //   157: goto -154 -> 3
    //   160: new 68	java/lang/String
    //   163: dup
    //   164: aload_1
    //   165: iconst_5
    //   166: newarray byte
    //   168: dup
    //   169: iconst_0
    //   170: ldc -69
    //   172: bastore
    //   173: dup
    //   174: iconst_1
    //   175: ldc -72
    //   177: bastore
    //   178: dup
    //   179: iconst_2
    //   180: ldc -56
    //   182: bastore
    //   183: dup
    //   184: iconst_3
    //   185: ldc -55
    //   187: bastore
    //   188: dup
    //   189: iconst_4
    //   190: ldc -54
    //   192: bastore
    //   193: aconst_null
    //   194: aconst_null
    //   195: bipush 127
    //   197: invokestatic 192	o/LZ:ˋ	([B[I[CI)Ljava/lang/String;
    //   200: invokevirtual 195	java/lang/String:intern	()Ljava/lang/String;
    //   203: invokespecial 205	java/lang/String:<init>	([BLjava/lang/String;)V
    //   206: astore_1
    //   207: aload_1
    //   208: areturn
    //   209: astore_1
    //   210: aload_1
    //   211: athrow
    //   212: iconst_1
    //   213: istore_3
    //   214: goto -87 -> 127
    //   217: iconst_0
    //   218: istore_2
    //   219: goto -216 -> 3
    //   222: getstatic 27	o/LZ:ˋˋ	I
    //   225: bipush 117
    //   227: iadd
    //   228: istore_3
    //   229: iload_3
    //   230: sipush 128
    //   233: irem
    //   234: putstatic 29	o/LZ:ˋᐝ	I
    //   237: iload_3
    //   238: iconst_2
    //   239: irem
    //   240: ifne +6 -> 246
    //   243: goto -209 -> 34
    //   246: aload_1
    //   247: iload_2
    //   248: aload 4
    //   250: aload 4
    //   252: arraylength
    //   253: iload_2
    //   254: isub
    //   255: iconst_1
    //   256: isub
    //   257: baload
    //   258: getstatic 33	o/LZ:ˊˋ	B
    //   261: ixor
    //   262: i2b
    //   263: bastore
    //   264: iload_2
    //   265: iconst_1
    //   266: iadd
    //   267: istore_2
    //   268: goto +127 -> 395
    //   271: getstatic 29	o/LZ:ˋᐝ	I
    //   274: istore_2
    //   275: iload_2
    //   276: bipush 29
    //   278: iadd
    //   279: istore_2
    //   280: iload_2
    //   281: sipush 128
    //   284: irem
    //   285: putstatic 27	o/LZ:ˋˋ	I
    //   288: iload_2
    //   289: iconst_2
    //   290: irem
    //   291: ifeq +6 -> 297
    //   294: goto -77 -> 217
    //   297: goto -142 -> 155
    //   300: aload_1
    //   301: bipush 10
    //   303: newarray byte
    //   305: dup
    //   306: iconst_0
    //   307: ldc -73
    //   309: bastore
    //   310: dup
    //   311: iconst_1
    //   312: ldc -72
    //   314: bastore
    //   315: dup
    //   316: iconst_2
    //   317: ldc -71
    //   319: bastore
    //   320: dup
    //   321: iconst_3
    //   322: ldc -70
    //   324: bastore
    //   325: dup
    //   326: iconst_4
    //   327: ldc -69
    //   329: bastore
    //   330: dup
    //   331: iconst_5
    //   332: ldc -69
    //   334: bastore
    //   335: dup
    //   336: bipush 6
    //   338: ldc -72
    //   340: bastore
    //   341: dup
    //   342: bipush 7
    //   344: ldc -68
    //   346: bastore
    //   347: dup
    //   348: bipush 8
    //   350: ldc -67
    //   352: bastore
    //   353: dup
    //   354: bipush 9
    //   356: ldc -66
    //   358: bastore
    //   359: aconst_null
    //   360: aconst_null
    //   361: bipush 54
    //   363: invokestatic 192	o/LZ:ˋ	([B[I[CI)Ljava/lang/String;
    //   366: invokevirtual 195	java/lang/String:intern	()Ljava/lang/String;
    //   369: invokevirtual 199	java/lang/String:getBytes	(Ljava/lang/String;)[B
    //   372: astore 4
    //   374: aload 4
    //   376: arraylength
    //   377: newarray byte
    //   379: astore_1
    //   380: iconst_1
    //   381: istore_2
    //   382: goto +28 -> 410
    //   385: astore_1
    //   386: new 207	java/lang/RuntimeException
    //   389: dup
    //   390: aload_1
    //   391: invokespecial 210	java/lang/RuntimeException:<init>	(Ljava/lang/Throwable;)V
    //   394: athrow
    //   395: aload 4
    //   397: arraylength
    //   398: istore_3
    //   399: iload_2
    //   400: iload_3
    //   401: if_icmpge +6 -> 407
    //   404: goto -367 -> 37
    //   407: goto -195 -> 212
    //   410: goto -15 -> 395
    // Local variable table:
    //   start	length	slot	name	signature
    //   0	413	0	this	LZ
    //   0	413	1	paramString	String
    //   3	399	2	i	int
    //   38	364	3	j	int
    //   114	282	4	arrayOfByte	byte[]
    // Exception table:
    //   from	to	target	type
    //   271	275	209	java/lang/Exception
    //   280	288	209	java/lang/Exception
    //   42	122	385	java/io/UnsupportedEncodingException
    //   160	207	385	java/io/UnsupportedEncodingException
    //   246	264	385	java/io/UnsupportedEncodingException
    //   300	380	385	java/io/UnsupportedEncodingException
    //   395	399	385	java/io/UnsupportedEncodingException
  }
  
  private void ˎ(Bundle paramBundle)
  {
    break label275;
    int i = 35 / 0;
    if (paramBundle == null)
    {
      break label753;
      throw new IllegalArgumentException(ˋ(new byte[] { -107, -108, -125, -114, -115, -127, -109, -120, -118, -109, -123, -124, -125, -126, -127, -109, -124, -127, -116, -120, -121, -123, -124, -125, -109, -112, -124, -123, -119, -109, -124, -127, -125, -121, -110 }, null, null, 127).intern());
      switch (i)
      {
      case 84: 
      default: 
        label244:
        label275:
        break;
      }
    }
    for (;;)
    {
      label278:
      return;
      i = 42;
      break label375;
      if (paramBundle == null)
      {
        break label333;
        for (;;)
        {
          label295:
          switch (i)
          {
          }
          break;
          label327:
          i = 24;
        }
        label333:
        i = 84;
        break label244;
      }
      label375:
      label753:
      label759:
      do
      {
        break label278;
        i = 50;
        break label244;
        i = ˋˋ + 47;
        ˋᐝ = i % 128;
        if (i % 2 == 0) {
          break label327;
        }
        for (;;)
        {
          switch (i)
          {
          case 99: 
          default: 
            break;
          case 42: 
            this.ˈ = paramBundle.getString(ˋ(new byte[] { -112, -118, -111, -111, -122, -112, -124, -123, -119, -122, -112, -127, -125, -119, -127, -113, -127, -120, -127, -124, -114, -122, -123, -124, -125, -126, -127 }, null, null, 127).intern());
            this.ʽॱ = ((Gh)paramBundle.getParcelable(ˋ(new byte[] { -115, -124, -117, -116, -122, -121, -117, -118, -125, -119, -123, -120, -121, -123, -124, -125, -122, -123, -124, -125, -126, -127 }, null, null, 127).intern()));
            ˉ();
            ˎˎ();
            break label759;
            i = 41;
            break label295;
            i = 99;
          }
        }
        i = ˋᐝ + 43;
        ˋˋ = i % 128;
      } while (i % 2 != 0);
    }
  }
  
  /* Error */
  private void ˎˎ()
  {
    // Byte code:
    //   0: goto +146 -> 146
    //   3: astore_2
    //   4: aload_2
    //   5: athrow
    //   6: getstatic 29	o/LZ:ˋᐝ	I
    //   9: bipush 33
    //   11: iadd
    //   12: istore_1
    //   13: iload_1
    //   14: sipush 128
    //   17: irem
    //   18: putstatic 27	o/LZ:ˋˋ	I
    //   21: iload_1
    //   22: iconst_2
    //   23: irem
    //   24: ifeq +6 -> 30
    //   27: goto +50 -> 77
    //   30: return
    //   31: aload_0
    //   32: aload_3
    //   33: invokestatic 45	o/HQ:ˏ	(Lcom/insidesecure/hce/MatrixHCECard;)Lo/HQ;
    //   36: putfield 253	o/LZ:ʼॱ	Lo/HQ;
    //   39: new 255	java/lang/NullPointerException
    //   42: dup
    //   43: invokespecial 256	java/lang/NullPointerException:<init>	()V
    //   46: athrow
    //   47: aload_2
    //   48: astore_3
    //   49: iload_1
    //   50: tableswitch	default:+22->72, 0:+317->367, 1:+66->116
    //   72: aload_2
    //   73: astore_3
    //   74: goto +42 -> 116
    //   77: return
    //   78: iconst_1
    //   79: istore_1
    //   80: goto -33 -> 47
    //   83: astore_2
    //   84: aload_2
    //   85: athrow
    //   86: goto +57 -> 143
    //   89: getstatic 27	o/LZ:ˋˋ	I
    //   92: bipush 17
    //   94: iadd
    //   95: istore_1
    //   96: iload_1
    //   97: sipush 128
    //   100: irem
    //   101: putstatic 29	o/LZ:ˋᐝ	I
    //   104: iload_1
    //   105: iconst_2
    //   106: irem
    //   107: ifne +6 -> 113
    //   110: goto +251 -> 361
    //   113: goto +510 -> 623
    //   116: getstatic 27	o/LZ:ˋˋ	I
    //   119: bipush 119
    //   121: iadd
    //   122: istore_1
    //   123: iload_1
    //   124: sipush 128
    //   127: irem
    //   128: putstatic 29	o/LZ:ˋᐝ	I
    //   131: iload_1
    //   132: iconst_2
    //   133: irem
    //   134: ifne +6 -> 140
    //   137: goto -106 -> 31
    //   140: goto +210 -> 350
    //   143: goto -137 -> 6
    //   146: goto -57 -> 89
    //   149: goto +17 -> 166
    //   152: astore_2
    //   153: aload_2
    //   154: invokevirtual 53	java/lang/Throwable:getCause	()Ljava/lang/Throwable;
    //   157: astore_3
    //   158: aload_3
    //   159: ifnull +5 -> 164
    //   162: aload_3
    //   163: athrow
    //   164: aload_2
    //   165: athrow
    //   166: aload_0
    //   167: invokevirtual 80	android/content/Context:getPackageName	()Ljava/lang/String;
    //   170: invokevirtual 84	java/lang/String:length	()I
    //   173: bipush 7
    //   175: isub
    //   176: aload_0
    //   177: invokevirtual 88	android/content/Context:getApplicationInfo	()Landroid/content/pm/ApplicationInfo;
    //   180: getfield 93	android/content/pm/ApplicationInfo:targetSdkVersion	I
    //   183: sipush 242
    //   186: iadd
    //   187: aload_0
    //   188: invokevirtual 59	android/content/Context:getResources	()Landroid/content/res/Resources;
    //   191: ldc_w 257
    //   194: invokevirtual 66	android/content/res/Resources:getString	(I)Ljava/lang/String;
    //   197: iconst_0
    //   198: bipush 9
    //   200: invokevirtual 72	java/lang/String:substring	(II)Ljava/lang/String;
    //   203: iconst_4
    //   204: invokevirtual 76	java/lang/String:codePointAt	(I)I
    //   207: sipush 14534
    //   210: iadd
    //   211: i2c
    //   212: invokestatic 99	o/O:ˋ	(IIC)Ljava/lang/Object;
    //   215: checkcast 101	java/lang/Class
    //   218: ldc 102
    //   220: aconst_null
    //   221: invokevirtual 106	java/lang/Class:getMethod	(Ljava/lang/String;[Ljava/lang/Class;)Ljava/lang/reflect/Method;
    //   224: aconst_null
    //   225: aconst_null
    //   226: invokevirtual 112	java/lang/reflect/Method:invoke	(Ljava/lang/Object;[Ljava/lang/Object;)Ljava/lang/Object;
    //   229: astore_3
    //   230: aload_0
    //   231: getfield 114	o/LZ:ʽॱ	Lo/Gh;
    //   234: getfield 260	o/Gh:toCardUuid	Ljava/lang/String;
    //   237: astore_2
    //   238: goto +17 -> 255
    //   241: astore_2
    //   242: aload_2
    //   243: invokevirtual 53	java/lang/Throwable:getCause	()Ljava/lang/Throwable;
    //   246: astore_3
    //   247: aload_3
    //   248: ifnull +5 -> 253
    //   251: aload_3
    //   252: athrow
    //   253: aload_2
    //   254: athrow
    //   255: aload_0
    //   256: invokevirtual 88	android/content/Context:getApplicationInfo	()Landroid/content/pm/ApplicationInfo;
    //   259: getfield 93	android/content/pm/ApplicationInfo:targetSdkVersion	I
    //   262: bipush 21
    //   264: isub
    //   265: aload_0
    //   266: invokevirtual 80	android/content/Context:getPackageName	()Ljava/lang/String;
    //   269: bipush 10
    //   271: invokevirtual 76	java/lang/String:codePointAt	(I)I
    //   274: sipush 146
    //   277: iadd
    //   278: aload_0
    //   279: invokevirtual 59	android/content/Context:getResources	()Landroid/content/res/Resources;
    //   282: ldc_w 261
    //   285: invokevirtual 66	android/content/res/Resources:getString	(I)Ljava/lang/String;
    //   288: iconst_0
    //   289: iconst_5
    //   290: invokevirtual 72	java/lang/String:substring	(II)Ljava/lang/String;
    //   293: iconst_1
    //   294: invokevirtual 76	java/lang/String:codePointAt	(I)I
    //   297: sipush 14762
    //   300: iadd
    //   301: i2c
    //   302: invokestatic 99	o/O:ˋ	(IIC)Ljava/lang/Object;
    //   305: checkcast 101	java/lang/Class
    //   308: ldc 123
    //   310: iconst_1
    //   311: anewarray 101	java/lang/Class
    //   314: dup
    //   315: iconst_0
    //   316: ldc 68
    //   318: aastore
    //   319: invokevirtual 106	java/lang/Class:getMethod	(Ljava/lang/String;[Ljava/lang/Class;)Ljava/lang/reflect/Method;
    //   322: aload_3
    //   323: iconst_1
    //   324: anewarray 125	java/lang/Object
    //   327: dup
    //   328: iconst_0
    //   329: aload_2
    //   330: aastore
    //   331: invokevirtual 112	java/lang/reflect/Method:invoke	(Ljava/lang/Object;[Ljava/lang/Object;)Ljava/lang/Object;
    //   334: checkcast 127	com/insidesecure/hce/MatrixHCECard
    //   337: astore_2
    //   338: aload_2
    //   339: ifnull +6 -> 345
    //   342: goto -264 -> 78
    //   345: iconst_0
    //   346: istore_1
    //   347: goto -300 -> 47
    //   350: aload_0
    //   351: aload_3
    //   352: invokestatic 45	o/HQ:ˏ	(Lcom/insidesecure/hce/MatrixHCECard;)Lo/HQ;
    //   355: putfield 253	o/LZ:ʼॱ	Lo/HQ;
    //   358: goto -215 -> 143
    //   361: bipush 20
    //   363: istore_1
    //   364: goto +229 -> 593
    //   367: aload_0
    //   368: aconst_null
    //   369: putfield 253	o/LZ:ʼॱ	Lo/HQ;
    //   372: goto -286 -> 86
    //   375: goto +17 -> 392
    //   378: astore_3
    //   379: aload_3
    //   380: invokevirtual 53	java/lang/Throwable:getCause	()Ljava/lang/Throwable;
    //   383: astore_2
    //   384: aload_2
    //   385: ifnull +5 -> 390
    //   388: aload_2
    //   389: athrow
    //   390: aload_3
    //   391: athrow
    //   392: aload_0
    //   393: invokevirtual 59	android/content/Context:getResources	()Landroid/content/res/Resources;
    //   396: ldc_w 262
    //   399: invokevirtual 66	android/content/res/Resources:getString	(I)Ljava/lang/String;
    //   402: iconst_0
    //   403: iconst_4
    //   404: invokevirtual 72	java/lang/String:substring	(II)Ljava/lang/String;
    //   407: iconst_3
    //   408: invokevirtual 76	java/lang/String:codePointAt	(I)I
    //   411: bipush 8
    //   413: isub
    //   414: aload_0
    //   415: invokevirtual 59	android/content/Context:getResources	()Landroid/content/res/Resources;
    //   418: ldc_w 263
    //   421: invokevirtual 66	android/content/res/Resources:getString	(I)Ljava/lang/String;
    //   424: iconst_0
    //   425: iconst_4
    //   426: invokevirtual 72	java/lang/String:substring	(II)Ljava/lang/String;
    //   429: iconst_1
    //   430: invokevirtual 76	java/lang/String:codePointAt	(I)I
    //   433: sipush 241
    //   436: iadd
    //   437: aload_0
    //   438: invokevirtual 80	android/content/Context:getPackageName	()Ljava/lang/String;
    //   441: invokevirtual 84	java/lang/String:length	()I
    //   444: sipush 14777
    //   447: iadd
    //   448: i2c
    //   449: invokestatic 99	o/O:ˋ	(IIC)Ljava/lang/Object;
    //   452: checkcast 101	java/lang/Class
    //   455: ldc 102
    //   457: aconst_null
    //   458: invokevirtual 106	java/lang/Class:getMethod	(Ljava/lang/String;[Ljava/lang/Class;)Ljava/lang/reflect/Method;
    //   461: aconst_null
    //   462: aconst_null
    //   463: invokevirtual 112	java/lang/reflect/Method:invoke	(Ljava/lang/Object;[Ljava/lang/Object;)Ljava/lang/Object;
    //   466: astore_2
    //   467: aload_0
    //   468: getfield 114	o/LZ:ʽॱ	Lo/Gh;
    //   471: astore_3
    //   472: aload_3
    //   473: getfield 260	o/Gh:toCardUuid	Ljava/lang/String;
    //   476: astore_3
    //   477: goto +17 -> 494
    //   480: astore_2
    //   481: aload_2
    //   482: invokevirtual 53	java/lang/Throwable:getCause	()Ljava/lang/Throwable;
    //   485: astore_3
    //   486: aload_3
    //   487: ifnull +5 -> 492
    //   490: aload_3
    //   491: athrow
    //   492: aload_2
    //   493: athrow
    //   494: aload_0
    //   495: invokevirtual 59	android/content/Context:getResources	()Landroid/content/res/Resources;
    //   498: ldc_w 264
    //   501: invokevirtual 66	android/content/res/Resources:getString	(I)Ljava/lang/String;
    //   504: iconst_0
    //   505: iconst_4
    //   506: invokevirtual 72	java/lang/String:substring	(II)Ljava/lang/String;
    //   509: invokevirtual 84	java/lang/String:length	()I
    //   512: iconst_0
    //   513: iadd
    //   514: aload_0
    //   515: invokevirtual 59	android/content/Context:getResources	()Landroid/content/res/Resources;
    //   518: ldc_w 265
    //   521: invokevirtual 66	android/content/res/Resources:getString	(I)Ljava/lang/String;
    //   524: iconst_0
    //   525: iconst_4
    //   526: invokevirtual 72	java/lang/String:substring	(II)Ljava/lang/String;
    //   529: iconst_2
    //   530: invokevirtual 76	java/lang/String:codePointAt	(I)I
    //   533: sipush 256
    //   536: iadd
    //   537: aload_0
    //   538: invokevirtual 88	android/content/Context:getApplicationInfo	()Landroid/content/pm/ApplicationInfo;
    //   541: getfield 93	android/content/pm/ApplicationInfo:targetSdkVersion	I
    //   544: sipush 14763
    //   547: iadd
    //   548: i2c
    //   549: invokestatic 99	o/O:ˋ	(IIC)Ljava/lang/Object;
    //   552: checkcast 101	java/lang/Class
    //   555: ldc 123
    //   557: iconst_1
    //   558: anewarray 101	java/lang/Class
    //   561: dup
    //   562: iconst_0
    //   563: ldc 68
    //   565: aastore
    //   566: invokevirtual 106	java/lang/Class:getMethod	(Ljava/lang/String;[Ljava/lang/Class;)Ljava/lang/reflect/Method;
    //   569: aload_2
    //   570: iconst_1
    //   571: anewarray 125	java/lang/Object
    //   574: dup
    //   575: iconst_0
    //   576: aload_3
    //   577: aastore
    //   578: invokevirtual 112	java/lang/reflect/Method:invoke	(Ljava/lang/Object;[Ljava/lang/Object;)Ljava/lang/Object;
    //   581: checkcast 127	com/insidesecure/hce/MatrixHCECard
    //   584: astore_2
    //   585: new 255	java/lang/NullPointerException
    //   588: dup
    //   589: invokespecial 256	java/lang/NullPointerException:<init>	()V
    //   592: athrow
    //   593: iload_1
    //   594: lookupswitch	default:+26->620, 20:+-219->375, 47:+-445->149
    //   620: goto -471 -> 149
    //   623: bipush 47
    //   625: istore_1
    //   626: goto -33 -> 593
    // Local variable table:
    //   start	length	slot	name	signature
    //   0	629	0	this	LZ
    //   12	614	1	i	int
    //   3	70	2	localException1	Exception
    //   83	2	2	localException2	Exception
    //   152	13	2	localObject1	Object
    //   237	1	2	str	String
    //   241	89	2	localObject2	Object
    //   337	130	2	localObject3	Object
    //   480	90	2	localObject4	Object
    //   584	1	2	localMatrixHCECard	com.insidesecure.hce.MatrixHCECard
    //   32	320	3	localObject5	Object
    //   378	13	3	localObject6	Object
    //   471	106	3	localObject7	Object
    // Exception table:
    //   from	to	target	type
    //   379	384	3	java/lang/Exception
    //   388	390	3	java/lang/Exception
    //   390	392	3	java/lang/Exception
    //   472	477	3	java/lang/Exception
    //   481	486	3	java/lang/Exception
    //   490	492	3	java/lang/Exception
    //   492	494	3	java/lang/Exception
    //   585	593	3	java/lang/Exception
    //   116	123	83	java/lang/Exception
    //   123	131	83	java/lang/Exception
    //   467	472	83	java/lang/Exception
    //   166	230	152	finally
    //   255	338	241	finally
    //   392	467	378	finally
    //   494	585	480	finally
  }
  
  /* Error */
  public android.content.res.Resources getResources()
  {
    // Byte code:
    //   0: goto +38 -> 38
    //   3: iload_1
    //   4: lookupswitch	default:+28->32, 47:+60->64, 52:+90->94
    //   32: goto +32 -> 64
    //   35: astore_2
    //   36: aload_2
    //   37: athrow
    //   38: getstatic 29	o/LZ:ˋᐝ	I
    //   41: iconst_1
    //   42: iadd
    //   43: istore_1
    //   44: iload_1
    //   45: sipush 128
    //   48: irem
    //   49: putstatic 27	o/LZ:ˋˋ	I
    //   52: iload_1
    //   53: iconst_2
    //   54: irem
    //   55: ifeq +6 -> 61
    //   58: goto +30 -> 88
    //   61: goto +21 -> 82
    //   64: aload_0
    //   65: invokespecial 266	o/Mg:getResources	()Landroid/content/res/Resources;
    //   68: astore_2
    //   69: aload_2
    //   70: invokestatic 271	o/oH:ˊ	(Landroid/content/res/Resources;)Landroid/content/res/Resources;
    //   73: pop
    //   74: new 255	java/lang/NullPointerException
    //   77: dup
    //   78: invokespecial 256	java/lang/NullPointerException:<init>	()V
    //   81: athrow
    //   82: bipush 52
    //   84: istore_1
    //   85: goto -82 -> 3
    //   88: bipush 47
    //   90: istore_1
    //   91: goto -88 -> 3
    //   94: aload_0
    //   95: invokespecial 266	o/Mg:getResources	()Landroid/content/res/Resources;
    //   98: invokestatic 271	o/oH:ˊ	(Landroid/content/res/Resources;)Landroid/content/res/Resources;
    //   101: areturn
    // Local variable table:
    //   start	length	slot	name	signature
    //   0	102	0	this	LZ
    //   3	88	1	i	int
    //   35	2	2	localException	Exception
    //   68	2	2	localResources	android.content.res.Resources
    // Exception table:
    //   from	to	target	type
    //   69	74	35	java/lang/Exception
  }
  
  public void onActivityResult(int paramInt1, int paramInt2, Intent paramIntent)
  {
    label817:
    for (;;)
    {
      try
      {
        Object localObject = ˋ(new byte[] { -115, -124, -117, -116, -122, -121, -117, -118, -125, -119, -123, -120, -121, -123, -124, -125, -122, -123, -124, -125, -126, -127 }, null, null, 127);
        localObject = ((String)localObject).intern();
        localObject = paramIntent.getParcelableExtra((String)localObject);
        this.ʽॱ = ((Gh)localObject);
        this.ˈ = paramIntent.getStringExtra(ˋ(new byte[] { -112, -118, -111, -111, -122, -112, -124, -123, -119, -122, -112, -127, -125, -119, -127, -113, -127, -120, -127, -124, -114, -122, -123, -124, -125, -126, -127 }, null, null, 127).intern());
        ˎˎ();
        ˊᐝ();
        continue;
        paramInt1 = ˋᐝ + 1;
        ˋˋ = paramInt1 % 128;
        if (paramInt1 % 2 == 0)
        {
          return;
          paramInt2 = 14;
          break label817;
          continue;
          paramInt2 = 23;
          break label817;
          continue;
        }
        else
        {
          return;
          switch (paramInt1)
          {
          case 17: 
          default: 
            continue;
            super.onActivityResult(paramInt1, paramInt2, paramIntent);
            if (paramInt2 == -1) {
              continue;
            }
            break;
          case 16: 
            this.ʽॱ = ((Gh)paramIntent.getParcelableExtra(ˋ(new byte[] { -115, -124, -117, -116, -122, -121, -117, -118, -125, -119, -123, -120, -121, -123, -124, -125, -122, -123, -124, -125, -126, -127 }, null, null, 127).intern()));
            this.ˈ = paramIntent.getStringExtra(ˋ(new byte[] { -112, -118, -111, -111, -122, -112, -124, -123, -119, -122, -112, -127, -125, -119, -127, -113, -127, -120, -127, -124, -114, -122, -123, -124, -125, -126, -127 }, null, null, 127).intern());
            ˉ();
            ʾ();
            break;
          }
          paramInt1 = ˋˋ + 1;
          ˋᐝ = paramInt1 % 128;
          if (paramInt1 % 2 == 0) {
            continue;
          }
          continue;
        }
        switch (paramInt2)
        {
        }
      }
      catch (Exception paramIntent)
      {
        throw paramIntent;
      }
      catch (Exception paramIntent)
      {
        throw paramIntent;
      }
    }
  }
  
  public void onCreate(Bundle paramBundle)
  {
    break label135;
    ˎ(getIntent().getExtras());
    break label35;
    label17:
    super.onCreate(paramBundle);
    label35:
    int i;
    if (ˊˊ())
    {
      break label95;
      i = ˋᐝ + 41;
      ˋˋ = i % 128;
      if (i % 2 == 0) {
        break label161;
      }
    }
    for (;;)
    {
      label62:
      break label138;
      i = 1;
      break label100;
      for (;;)
      {
        switch (i)
        {
        }
        break;
        label95:
        i = 0;
      }
      for (;;)
      {
        switch (i)
        {
        default: 
          break label132;
          i = 1;
          break;
        case 0: 
          label100:
          label132:
          break label62;
          label135:
          break label17;
          label138:
          i = ˋˋ + 53;
          ˋᐝ = i % 128;
          if (i % 2 == 0) {
            return;
          }
          return;
          label161:
          i = 0;
        }
      }
    }
  }
  
  public void onPickFromCardClick(View paramView)
  {
    int i;
    for (;;)
    {
      switch (i)
      {
      default: 
        return;
        break;
      case 1: 
      case 0: 
        for (;;)
        {
          try
          {
            i = ˋˋ;
            i += 37;
            ˋᐝ = i % 128;
            if (i % 2 == 0) {
              break;
            }
          }
          catch (Exception paramView)
          {
            throw paramView;
          }
          return;
          i = null.length;
          return;
        }
        i = 1;
        continue;
        label77:
        i = 0;
      }
    }
    for (;;)
    {
      i = ˋᐝ + 99;
      ˋˋ = i % 128;
      if (i % 2 != 0) {
        break label77;
      }
      break;
      ˊ(3);
    }
  }
  
  public void onPickToCardClick(View paramView)
  {
    for (;;)
    {
      int i;
      switch (i)
      {
      case 68: 
      default: 
        ˊ(4);
        return;
        for (;;)
        {
          i = ˋᐝ + 27;
          ˋˋ = i % 128;
          if (i % 2 == 0) {
            break label74;
          }
          i = 88;
          break;
        }
        label74:
        i = 68;
      }
    }
    ˊ(2);
  }
  
  /* Error */
  protected void ʻॱ()
  {
    // Byte code:
    //   0: goto +34 -> 34
    //   3: getstatic 27	o/LZ:ˋˋ	I
    //   6: bipush 53
    //   8: iadd
    //   9: istore_1
    //   10: iload_1
    //   11: sipush 128
    //   14: irem
    //   15: putstatic 29	o/LZ:ˋᐝ	I
    //   18: iload_1
    //   19: iconst_2
    //   20: irem
    //   21: ifne +6 -> 27
    //   24: goto +91 -> 115
    //   27: return
    //   28: bipush 97
    //   30: istore_1
    //   31: goto +38 -> 69
    //   34: goto +6 -> 40
    //   37: astore_2
    //   38: aload_2
    //   39: athrow
    //   40: getstatic 29	o/LZ:ˋᐝ	I
    //   43: istore_1
    //   44: iload_1
    //   45: bipush 63
    //   47: iadd
    //   48: istore_1
    //   49: iload_1
    //   50: sipush 128
    //   53: irem
    //   54: putstatic 27	o/LZ:ˋˋ	I
    //   57: iload_1
    //   58: iconst_2
    //   59: irem
    //   60: ifeq +6 -> 66
    //   63: goto -35 -> 28
    //   66: goto +77 -> 143
    //   69: iload_1
    //   70: lookupswitch	default:+26->96, 25:+26->96, 97:+46->116
    //   96: aload_0
    //   97: invokespecial 248	o/LZ:ˉ	()V
    //   100: aload_0
    //   101: invokespecial 251	o/LZ:ˎˎ	()V
    //   104: aload_0
    //   105: invokevirtual 287	o/LZ:ʾ	()V
    //   108: aload_0
    //   109: invokevirtual 283	o/LZ:ˊᐝ	()V
    //   112: goto -109 -> 3
    //   115: return
    //   116: aload_0
    //   117: invokespecial 248	o/LZ:ˉ	()V
    //   120: aload_0
    //   121: invokespecial 251	o/LZ:ˎˎ	()V
    //   124: aload_0
    //   125: invokevirtual 287	o/LZ:ʾ	()V
    //   128: aload_0
    //   129: invokevirtual 283	o/LZ:ˊᐝ	()V
    //   132: new 255	java/lang/NullPointerException
    //   135: dup
    //   136: invokespecial 256	java/lang/NullPointerException:<init>	()V
    //   139: athrow
    //   140: astore_2
    //   141: aload_2
    //   142: athrow
    //   143: bipush 25
    //   145: istore_1
    //   146: goto -77 -> 69
    // Local variable table:
    //   start	length	slot	name	signature
    //   0	149	0	this	LZ
    //   9	137	1	i	int
    //   37	2	2	localException1	Exception
    //   140	2	2	localException2	Exception
    // Exception table:
    //   from	to	target	type
    //   40	44	37	java/lang/Exception
    //   49	57	37	java/lang/Exception
    //   108	112	37	java/lang/Exception
    //   104	108	140	java/lang/Exception
  }
  
  protected abstract void ʾ();
  
  /* Error */
  void ˊ(int paramInt)
  {
    // Byte code:
    //   0: goto +681 -> 681
    //   3: astore_3
    //   4: aload_3
    //   5: athrow
    //   6: goto +689 -> 695
    //   9: bipush 72
    //   11: istore_1
    //   12: goto +528 -> 540
    //   15: bipush 27
    //   17: newarray byte
    //   19: dup
    //   20: iconst_0
    //   21: ldc -28
    //   23: bastore
    //   24: dup
    //   25: iconst_1
    //   26: ldc -34
    //   28: bastore
    //   29: dup
    //   30: iconst_2
    //   31: ldc -23
    //   33: bastore
    //   34: dup
    //   35: iconst_3
    //   36: ldc -23
    //   38: bastore
    //   39: dup
    //   40: iconst_4
    //   41: ldc -22
    //   43: bastore
    //   44: dup
    //   45: iconst_5
    //   46: ldc -28
    //   48: bastore
    //   49: dup
    //   50: bipush 6
    //   52: ldc -32
    //   54: bastore
    //   55: dup
    //   56: bipush 7
    //   58: ldc -33
    //   60: bastore
    //   61: dup
    //   62: bipush 8
    //   64: ldc -27
    //   66: bastore
    //   67: dup
    //   68: bipush 9
    //   70: ldc -22
    //   72: bastore
    //   73: dup
    //   74: bipush 10
    //   76: ldc -28
    //   78: bastore
    //   79: dup
    //   80: bipush 11
    //   82: ldc -37
    //   84: bastore
    //   85: dup
    //   86: bipush 12
    //   88: ldc -40
    //   90: bastore
    //   91: dup
    //   92: bipush 13
    //   94: ldc -27
    //   96: bastore
    //   97: dup
    //   98: bipush 14
    //   100: ldc -37
    //   102: bastore
    //   103: dup
    //   104: bipush 15
    //   106: ldc -21
    //   108: bastore
    //   109: dup
    //   110: bipush 16
    //   112: ldc -37
    //   114: bastore
    //   115: dup
    //   116: bipush 17
    //   118: ldc -35
    //   120: bastore
    //   121: dup
    //   122: bipush 18
    //   124: ldc -37
    //   126: bastore
    //   127: dup
    //   128: bipush 19
    //   130: ldc -32
    //   132: bastore
    //   133: dup
    //   134: bipush 20
    //   136: ldc -39
    //   138: bastore
    //   139: dup
    //   140: bipush 21
    //   142: ldc -22
    //   144: bastore
    //   145: dup
    //   146: bipush 22
    //   148: ldc -33
    //   150: bastore
    //   151: dup
    //   152: bipush 23
    //   154: ldc -32
    //   156: bastore
    //   157: dup
    //   158: bipush 24
    //   160: ldc -40
    //   162: bastore
    //   163: dup
    //   164: bipush 25
    //   166: ldc -31
    //   168: bastore
    //   169: dup
    //   170: bipush 26
    //   172: ldc -37
    //   174: bastore
    //   175: aconst_null
    //   176: aconst_null
    //   177: bipush 127
    //   179: invokestatic 192	o/LZ:ˋ	([B[I[CI)Ljava/lang/String;
    //   182: astore_3
    //   183: aload_3
    //   184: invokevirtual 195	java/lang/String:intern	()Ljava/lang/String;
    //   187: astore_3
    //   188: aload_0
    //   189: getfield 241	o/LZ:ˈ	Ljava/lang/String;
    //   192: astore 5
    //   194: aload 4
    //   196: aload_3
    //   197: aload 5
    //   199: invokevirtual 315	android/os/Bundle:putString	(Ljava/lang/String;Ljava/lang/String;)V
    //   202: goto +717 -> 919
    //   205: new 237	android/os/Bundle
    //   208: dup
    //   209: invokespecial 316	android/os/Bundle:<init>	()V
    //   212: astore 4
    //   214: aload 4
    //   216: bipush 22
    //   218: newarray byte
    //   220: dup
    //   221: iconst_0
    //   222: ldc -38
    //   224: bastore
    //   225: dup
    //   226: iconst_1
    //   227: ldc -32
    //   229: bastore
    //   230: dup
    //   231: iconst_2
    //   232: ldc -14
    //   234: bastore
    //   235: dup
    //   236: iconst_3
    //   237: ldc -30
    //   239: bastore
    //   240: dup
    //   241: iconst_4
    //   242: ldc -22
    //   244: bastore
    //   245: dup
    //   246: iconst_5
    //   247: ldc -29
    //   249: bastore
    //   250: dup
    //   251: bipush 6
    //   253: ldc -14
    //   255: bastore
    //   256: dup
    //   257: bipush 7
    //   259: ldc -34
    //   261: bastore
    //   262: dup
    //   263: bipush 8
    //   265: ldc -40
    //   267: bastore
    //   268: dup
    //   269: bipush 9
    //   271: ldc -27
    //   273: bastore
    //   274: dup
    //   275: bipush 10
    //   277: ldc -33
    //   279: bastore
    //   280: dup
    //   281: bipush 11
    //   283: ldc -35
    //   285: bastore
    //   286: dup
    //   287: bipush 12
    //   289: ldc -29
    //   291: bastore
    //   292: dup
    //   293: bipush 13
    //   295: ldc -33
    //   297: bastore
    //   298: dup
    //   299: bipush 14
    //   301: ldc -32
    //   303: bastore
    //   304: dup
    //   305: bipush 15
    //   307: ldc -40
    //   309: bastore
    //   310: dup
    //   311: bipush 16
    //   313: ldc -22
    //   315: bastore
    //   316: dup
    //   317: bipush 17
    //   319: ldc -33
    //   321: bastore
    //   322: dup
    //   323: bipush 18
    //   325: ldc -32
    //   327: bastore
    //   328: dup
    //   329: bipush 19
    //   331: ldc -40
    //   333: bastore
    //   334: dup
    //   335: bipush 20
    //   337: ldc -31
    //   339: bastore
    //   340: dup
    //   341: bipush 21
    //   343: ldc -37
    //   345: bastore
    //   346: aconst_null
    //   347: aconst_null
    //   348: bipush 127
    //   350: invokestatic 192	o/LZ:ˋ	([B[I[CI)Ljava/lang/String;
    //   353: invokevirtual 195	java/lang/String:intern	()Ljava/lang/String;
    //   356: aload_0
    //   357: getfield 114	o/LZ:ʽॱ	Lo/Gh;
    //   360: invokevirtual 320	android/os/Bundle:putParcelable	(Ljava/lang/String;Landroid/os/Parcelable;)V
    //   363: aload 4
    //   365: bipush 22
    //   367: newarray byte
    //   369: dup
    //   370: iconst_0
    //   371: ldc_w 321
    //   374: bastore
    //   375: dup
    //   376: iconst_1
    //   377: ldc -29
    //   379: bastore
    //   380: dup
    //   381: iconst_2
    //   382: ldc -34
    //   384: bastore
    //   385: dup
    //   386: iconst_3
    //   387: ldc -21
    //   389: bastore
    //   390: dup
    //   391: iconst_4
    //   392: ldc -21
    //   394: bastore
    //   395: dup
    //   396: iconst_5
    //   397: ldc -33
    //   399: bastore
    //   400: dup
    //   401: bipush 6
    //   403: ldc -27
    //   405: bastore
    //   406: dup
    //   407: bipush 7
    //   409: ldc -22
    //   411: bastore
    //   412: dup
    //   413: bipush 8
    //   415: ldc -32
    //   417: bastore
    //   418: dup
    //   419: bipush 9
    //   421: ldc -14
    //   423: bastore
    //   424: dup
    //   425: bipush 10
    //   427: ldc -30
    //   429: bastore
    //   430: dup
    //   431: bipush 11
    //   433: ldc -22
    //   435: bastore
    //   436: dup
    //   437: bipush 12
    //   439: ldc -37
    //   441: bastore
    //   442: dup
    //   443: bipush 13
    //   445: ldc -35
    //   447: bastore
    //   448: dup
    //   449: bipush 14
    //   451: ldc -33
    //   453: bastore
    //   454: dup
    //   455: bipush 15
    //   457: ldc -27
    //   459: bastore
    //   460: dup
    //   461: bipush 16
    //   463: ldc -22
    //   465: bastore
    //   466: dup
    //   467: bipush 17
    //   469: ldc -33
    //   471: bastore
    //   472: dup
    //   473: bipush 18
    //   475: ldc -32
    //   477: bastore
    //   478: dup
    //   479: bipush 19
    //   481: ldc -40
    //   483: bastore
    //   484: dup
    //   485: bipush 20
    //   487: ldc -31
    //   489: bastore
    //   490: dup
    //   491: bipush 21
    //   493: ldc -37
    //   495: bastore
    //   496: aconst_null
    //   497: aconst_null
    //   498: bipush 127
    //   500: invokestatic 192	o/LZ:ˋ	([B[I[CI)Ljava/lang/String;
    //   503: invokevirtual 195	java/lang/String:intern	()Ljava/lang/String;
    //   506: iload_1
    //   507: invokevirtual 325	android/os/Bundle:putInt	(Ljava/lang/String;I)V
    //   510: aload_0
    //   511: invokevirtual 304	o/LZ:ˊˊ	()Z
    //   514: ifeq +6 -> 520
    //   517: goto +370 -> 887
    //   520: goto -505 -> 15
    //   523: aload_0
    //   524: invokestatic 330	o/Ic:ˏ	(Landroid/content/Context;)Lo/Ic;
    //   527: invokevirtual 333	o/Ic:ʾ	()Lo/j;
    //   530: aload 4
    //   532: invokevirtual 338	o/j:ˊ	(Landroid/os/Bundle;)Lo/j;
    //   535: iload_1
    //   536: invokevirtual 340	o/j:ˎ	(I)V
    //   539: return
    //   540: iload_1
    //   541: lookupswitch	default:+27->568, 49:+340->881, 72:+100->641
    //   568: goto +313 -> 881
    //   571: iconst_1
    //   572: istore_2
    //   573: goto +74 -> 647
    //   576: goto +343 -> 919
    //   579: goto -3 -> 576
    //   582: getstatic 29	o/LZ:ˋᐝ	I
    //   585: iconst_5
    //   586: iadd
    //   587: istore_2
    //   588: iload_2
    //   589: sipush 128
    //   592: irem
    //   593: putstatic 27	o/LZ:ˋˋ	I
    //   596: iload_2
    //   597: iconst_2
    //   598: irem
    //   599: ifeq +6 -> 605
    //   602: goto -23 -> 579
    //   605: goto -29 -> 576
    //   608: iload_1
    //   609: iconst_3
    //   610: if_icmpne +6 -> 616
    //   613: goto -604 -> 9
    //   616: goto +59 -> 675
    //   619: aload 4
    //   621: aload 5
    //   623: aload_3
    //   624: invokevirtual 315	android/os/Bundle:putString	(Ljava/lang/String;Ljava/lang/String;)V
    //   627: goto -45 -> 582
    //   630: aload_0
    //   631: getfield 114	o/LZ:ʽॱ	Lo/Gh;
    //   634: getfield 119	o/Gh:fromCardUuid	Ljava/lang/String;
    //   637: astore_3
    //   638: goto -19 -> 619
    //   641: bipush 16
    //   643: istore_1
    //   644: goto -121 -> 523
    //   647: iload_2
    //   648: tableswitch	default:+24->672, 0:+36->684, 1:+-18->630
    //   672: goto +12 -> 684
    //   675: bipush 49
    //   677: istore_1
    //   678: goto -138 -> 540
    //   681: goto -476 -> 205
    //   684: aload_0
    //   685: getfield 114	o/LZ:ʽॱ	Lo/Gh;
    //   688: getfield 260	o/Gh:toCardUuid	Ljava/lang/String;
    //   691: astore_3
    //   692: goto -73 -> 619
    //   695: bipush 27
    //   697: newarray byte
    //   699: dup
    //   700: iconst_0
    //   701: ldc -28
    //   703: bastore
    //   704: dup
    //   705: iconst_1
    //   706: ldc -34
    //   708: bastore
    //   709: dup
    //   710: iconst_2
    //   711: ldc -23
    //   713: bastore
    //   714: dup
    //   715: iconst_3
    //   716: ldc -23
    //   718: bastore
    //   719: dup
    //   720: iconst_4
    //   721: ldc -22
    //   723: bastore
    //   724: dup
    //   725: iconst_5
    //   726: ldc -28
    //   728: bastore
    //   729: dup
    //   730: bipush 6
    //   732: ldc -32
    //   734: bastore
    //   735: dup
    //   736: bipush 7
    //   738: ldc -33
    //   740: bastore
    //   741: dup
    //   742: bipush 8
    //   744: ldc -27
    //   746: bastore
    //   747: dup
    //   748: bipush 9
    //   750: ldc -22
    //   752: bastore
    //   753: dup
    //   754: bipush 10
    //   756: ldc -28
    //   758: bastore
    //   759: dup
    //   760: bipush 11
    //   762: ldc -37
    //   764: bastore
    //   765: dup
    //   766: bipush 12
    //   768: ldc -40
    //   770: bastore
    //   771: dup
    //   772: bipush 13
    //   774: ldc -27
    //   776: bastore
    //   777: dup
    //   778: bipush 14
    //   780: ldc -37
    //   782: bastore
    //   783: dup
    //   784: bipush 15
    //   786: ldc -21
    //   788: bastore
    //   789: dup
    //   790: bipush 16
    //   792: ldc -37
    //   794: bastore
    //   795: dup
    //   796: bipush 17
    //   798: ldc -35
    //   800: bastore
    //   801: dup
    //   802: bipush 18
    //   804: ldc -37
    //   806: bastore
    //   807: dup
    //   808: bipush 19
    //   810: ldc -32
    //   812: bastore
    //   813: dup
    //   814: bipush 20
    //   816: ldc -39
    //   818: bastore
    //   819: dup
    //   820: bipush 21
    //   822: ldc -22
    //   824: bastore
    //   825: dup
    //   826: bipush 22
    //   828: ldc -33
    //   830: bastore
    //   831: dup
    //   832: bipush 23
    //   834: ldc -32
    //   836: bastore
    //   837: dup
    //   838: bipush 24
    //   840: ldc -40
    //   842: bastore
    //   843: dup
    //   844: bipush 25
    //   846: ldc -31
    //   848: bastore
    //   849: dup
    //   850: bipush 26
    //   852: ldc -37
    //   854: bastore
    //   855: aconst_null
    //   856: aconst_null
    //   857: bipush 127
    //   859: invokestatic 192	o/LZ:ˋ	([B[I[CI)Ljava/lang/String;
    //   862: invokevirtual 195	java/lang/String:intern	()Ljava/lang/String;
    //   865: astore 5
    //   867: iload_1
    //   868: iconst_3
    //   869: if_icmpne +6 -> 875
    //   872: goto -301 -> 571
    //   875: goto +39 -> 914
    //   878: astore_3
    //   879: aload_3
    //   880: athrow
    //   881: bipush 17
    //   883: istore_1
    //   884: goto -361 -> 523
    //   887: getstatic 27	o/LZ:ˋˋ	I
    //   890: bipush 125
    //   892: iadd
    //   893: istore_2
    //   894: iload_2
    //   895: sipush 128
    //   898: irem
    //   899: putstatic 29	o/LZ:ˋᐝ	I
    //   902: iload_2
    //   903: iconst_2
    //   904: irem
    //   905: ifne +6 -> 911
    //   908: goto -902 -> 6
    //   911: goto -216 -> 695
    //   914: iconst_0
    //   915: istore_2
    //   916: goto -269 -> 647
    //   919: iload_1
    //   920: ifeq +6 -> 926
    //   923: goto -315 -> 608
    //   926: goto -285 -> 641
    // Local variable table:
    //   start	length	slot	name	signature
    //   0	929	0	this	LZ
    //   0	929	1	paramInt	int
    //   572	344	2	i	int
    //   3	2	3	localException1	Exception
    //   182	510	3	str1	String
    //   878	2	3	localException2	Exception
    //   194	426	4	localBundle	Bundle
    //   192	674	5	str2	String
    // Exception table:
    //   from	to	target	type
    //   15	183	3	java/lang/Exception
    //   188	194	3	java/lang/Exception
    //   194	202	3	java/lang/Exception
    //   183	188	878	java/lang/Exception
  }
  
  protected abstract void ˊᐝ();
  
  /* Error */
  protected android.util.Pair<String, android.graphics.drawable.Drawable> ˎ(HQ paramHQ)
  {
    // Byte code:
    //   0: goto +95 -> 95
    //   3: new 343	android/util/Pair
    //   6: dup
    //   7: aload_1
    //   8: aconst_null
    //   9: invokespecial 346	android/util/Pair:<init>	(Ljava/lang/Object;Ljava/lang/Object;)V
    //   12: areturn
    //   13: goto +327 -> 340
    //   16: aload_0
    //   17: getstatic 351	o/LV$If:transfer_between_cards_destination_card	I
    //   20: invokevirtual 352	o/LZ:getString	(I)Ljava/lang/String;
    //   23: astore_1
    //   24: aload_1
    //   25: iconst_4
    //   26: newarray byte
    //   28: dup
    //   29: iconst_0
    //   30: ldc_w 353
    //   33: bastore
    //   34: dup
    //   35: iconst_1
    //   36: ldc_w 354
    //   39: bastore
    //   40: dup
    //   41: iconst_2
    //   42: ldc_w 355
    //   45: bastore
    //   46: dup
    //   47: iconst_3
    //   48: ldc_w 356
    //   51: bastore
    //   52: aconst_null
    //   53: aconst_null
    //   54: bipush 127
    //   56: invokestatic 192	o/LZ:ˋ	([B[I[CI)Ljava/lang/String;
    //   59: invokevirtual 195	java/lang/String:intern	()Ljava/lang/String;
    //   62: invokevirtual 360	java/lang/String:startsWith	(Ljava/lang/String;)Z
    //   65: ifeq +6 -> 71
    //   68: goto +9 -> 77
    //   71: goto -68 -> 3
    //   74: astore_1
    //   75: aload_1
    //   76: athrow
    //   77: aload_1
    //   78: iconst_4
    //   79: invokevirtual 362	java/lang/String:substring	(I)Ljava/lang/String;
    //   82: astore_1
    //   83: aload_0
    //   84: aload_1
    //   85: invokespecial 364	o/LZ:ˎ	(Ljava/lang/String;)Ljava/lang/String;
    //   88: invokevirtual 195	java/lang/String:intern	()Ljava/lang/String;
    //   91: astore_1
    //   92: goto -89 -> 3
    //   95: goto +47 -> 142
    //   98: goto -85 -> 13
    //   101: aload_0
    //   102: aload_1
    //   103: iconst_4
    //   104: invokevirtual 362	java/lang/String:substring	(I)Ljava/lang/String;
    //   107: invokespecial 364	o/LZ:ˎ	(Ljava/lang/String;)Ljava/lang/String;
    //   110: astore_1
    //   111: aload_1
    //   112: invokevirtual 195	java/lang/String:intern	()Ljava/lang/String;
    //   115: astore_1
    //   116: getstatic 29	o/LZ:ˋᐝ	I
    //   119: iconst_3
    //   120: iadd
    //   121: istore_2
    //   122: iload_2
    //   123: sipush 128
    //   126: irem
    //   127: putstatic 27	o/LZ:ˋˋ	I
    //   130: iload_2
    //   131: iconst_2
    //   132: irem
    //   133: ifeq +6 -> 139
    //   136: goto -38 -> 98
    //   139: goto -126 -> 13
    //   142: getstatic 29	o/LZ:ˋᐝ	I
    //   145: bipush 101
    //   147: iadd
    //   148: istore_2
    //   149: iload_2
    //   150: sipush 128
    //   153: irem
    //   154: putstatic 27	o/LZ:ˋˋ	I
    //   157: iload_2
    //   158: iconst_2
    //   159: irem
    //   160: ifeq +6 -> 166
    //   163: goto +64 -> 227
    //   166: goto +77 -> 243
    //   169: aload_0
    //   170: getstatic 367	o/LV$If:transfer_between_cards_source_card	I
    //   173: invokevirtual 352	o/LZ:getString	(I)Ljava/lang/String;
    //   176: astore_1
    //   177: aload_1
    //   178: iconst_4
    //   179: newarray byte
    //   181: dup
    //   182: iconst_0
    //   183: ldc_w 353
    //   186: bastore
    //   187: dup
    //   188: iconst_1
    //   189: ldc_w 354
    //   192: bastore
    //   193: dup
    //   194: iconst_2
    //   195: ldc_w 355
    //   198: bastore
    //   199: dup
    //   200: iconst_3
    //   201: ldc_w 356
    //   204: bastore
    //   205: aconst_null
    //   206: aconst_null
    //   207: bipush 127
    //   209: invokestatic 192	o/LZ:ˋ	([B[I[CI)Ljava/lang/String;
    //   212: invokevirtual 195	java/lang/String:intern	()Ljava/lang/String;
    //   215: invokevirtual 360	java/lang/String:startsWith	(Ljava/lang/String;)Z
    //   218: ifeq +6 -> 224
    //   221: goto -120 -> 101
    //   224: goto +116 -> 340
    //   227: goto +16 -> 243
    //   230: aload_1
    //   231: invokevirtual 369	o/HQ:ˊᐝ	()Z
    //   234: ifeq +6 -> 240
    //   237: goto +33 -> 270
    //   240: goto +56 -> 296
    //   243: aload_1
    //   244: ifnonnull +6 -> 250
    //   247: goto +69 -> 316
    //   250: goto -20 -> 230
    //   253: aload_1
    //   254: aload_0
    //   255: getfield 253	o/LZ:ʼॱ	Lo/HQ;
    //   258: invokevirtual 373	java/lang/Object:equals	(Ljava/lang/Object;)Z
    //   261: ifeq +6 -> 267
    //   264: goto -248 -> 16
    //   267: goto +61 -> 328
    //   270: new 343	android/util/Pair
    //   273: dup
    //   274: aload_1
    //   275: aload_0
    //   276: invokevirtual 377	o/LZ:ॱˊ	()Landroid/content/Context;
    //   279: invokevirtual 380	o/HQ:ˊ	(Landroid/content/Context;)Ljava/lang/String;
    //   282: aload_0
    //   283: invokevirtual 377	o/LZ:ॱˊ	()Landroid/content/Context;
    //   286: getstatic 385	o/LV$ˋ:ic_disabled_card_lock	I
    //   289: invokestatic 390	o/ᔆ:ˎ	(Landroid/content/Context;I)Landroid/graphics/drawable/Drawable;
    //   292: invokespecial 346	android/util/Pair:<init>	(Ljava/lang/Object;Ljava/lang/Object;)V
    //   295: areturn
    //   296: aload_1
    //   297: aload_0
    //   298: getfield 47	o/LZ:ʾ	Lo/HQ;
    //   301: invokevirtual 373	java/lang/Object:equals	(Ljava/lang/Object;)Z
    //   304: ifeq +6 -> 310
    //   307: goto -138 -> 169
    //   310: goto -57 -> 253
    //   313: astore_1
    //   314: aload_1
    //   315: athrow
    //   316: new 343	android/util/Pair
    //   319: dup
    //   320: ldc_w 392
    //   323: aconst_null
    //   324: invokespecial 346	android/util/Pair:<init>	(Ljava/lang/Object;Ljava/lang/Object;)V
    //   327: areturn
    //   328: new 343	android/util/Pair
    //   331: dup
    //   332: ldc_w 392
    //   335: aconst_null
    //   336: invokespecial 346	android/util/Pair:<init>	(Ljava/lang/Object;Ljava/lang/Object;)V
    //   339: areturn
    //   340: new 343	android/util/Pair
    //   343: dup
    //   344: aload_1
    //   345: aconst_null
    //   346: invokespecial 346	android/util/Pair:<init>	(Ljava/lang/Object;Ljava/lang/Object;)V
    //   349: areturn
    // Local variable table:
    //   start	length	slot	name	signature
    //   0	350	0	this	LZ
    //   0	350	1	paramHQ	HQ
    //   121	39	2	i	int
    // Exception table:
    //   from	to	target	type
    //   77	83	74	java/lang/Exception
    //   101	111	74	java/lang/Exception
    //   111	116	74	java/lang/Exception
    //   111	116	313	java/lang/Exception
  }
  
  protected void ˎ(FW paramFW, FS paramFS)
  {
    for (;;)
    {
      int i = ˋˋ + 121;
      ˋᐝ = i % 128;
      if (i % 2 == 0) {
        return;
      }
      return;
      this.ʽॱ = new Gh(paramFW);
      ˉ();
      ˎˎ();
    }
  }
}
