package o;

import android.content.Intent;
import android.content.res.Resources;
import android.graphics.PorterDuff.Mode;
import android.graphics.drawable.Drawable;
import android.os.Bundle;
import android.view.View;
import android.widget.ProgressBar;
import java.util.Collections;
import org.greenrobot.eventbus.ThreadMode;

public class Ma
  extends Mg<Mn>
{
  private static byte ʼॱ;
  private static long ʽॱ;
  private static int ʾ;
  private static int ˈ;
  
  /* Error */
  static
  {
    // Byte code:
    //   0: goto +33 -> 33
    //   3: iload_0
    //   4: tableswitch	default:+24->28, 0:+25->29, 1:+59->63
    //   28: return
    //   29: aconst_null
    //   30: arraylength
    //   31: istore_0
    //   32: return
    //   33: iconst_0
    //   34: putstatic 24	o/Ma:ʾ	I
    //   37: iconst_1
    //   38: putstatic 26	o/Ma:ˈ	I
    //   41: invokestatic 28	o/Ma:ʾ	()V
    //   44: bipush -102
    //   46: putstatic 30	o/Ma:ʼॱ	B
    //   49: goto +15 -> 64
    //   52: astore_1
    //   53: aload_1
    //   54: athrow
    //   55: astore_1
    //   56: aload_1
    //   57: athrow
    //   58: iconst_1
    //   59: istore_0
    //   60: goto -57 -> 3
    //   63: return
    //   64: getstatic 24	o/Ma:ʾ	I
    //   67: istore_0
    //   68: iload_0
    //   69: bipush 75
    //   71: iadd
    //   72: istore_0
    //   73: iload_0
    //   74: sipush 128
    //   77: irem
    //   78: putstatic 26	o/Ma:ˈ	I
    //   81: iload_0
    //   82: iconst_2
    //   83: irem
    //   84: ifne +6 -> 90
    //   87: goto +6 -> 93
    //   90: goto -32 -> 58
    //   93: iconst_0
    //   94: istore_0
    //   95: goto -92 -> 3
    // Local variable table:
    //   start	length	slot	name	signature
    //   3	92	0	i	int
    //   52	2	1	localException1	Exception
    //   55	2	1	localException2	Exception
    // Exception table:
    //   from	to	target	type
    //   73	81	52	java/lang/Exception
    //   64	68	55	java/lang/Exception
  }
  
  public Ma() {}
  
  static void ʾ()
  {
    ʽॱ = -7644805248192399634L;
  }
  
  private void ˉ()
  {
    for (;;)
    {
      HQ localHQ = ((Mn)this.ॱˊ).ʻ.ʻ();
      ((Mn)this.ॱˊ).ˊ(localHQ.ˊᐝ());
      int i;
      do
      {
        break;
        switch (i)
        {
        default: 
          break;
          for (;;)
          {
            i = 0;
            break;
            do
            {
              i = 1;
              break;
              i = ʾ + 31;
              ˈ = i % 128;
            } while (i % 2 == 0);
          }
        case 0: 
          return;
        }
        i = 73 / 0;
        return;
        i = ʾ + 107;
        ˈ = i % 128;
      } while (i % 2 == 0);
    }
  }
  
  /* Error */
  private String ˊ(FV arg1)
  {
    // Byte code:
    //   0: goto +90 -> 90
    //   3: aload_1
    //   4: areturn
    //   5: getstatic 68	o/Ma$3:ˊ	[I
    //   8: aload_1
    //   9: invokevirtual 74	o/FV:ordinal	()I
    //   12: iaload
    //   13: tableswitch	default:+39->52, 1:+198->211, 2:+198->211, 3:+110->123, 4:+253->266, 5:+253->266, 6:+253->266
    //   52: goto +68 -> 120
    //   55: aload_1
    //   56: areturn
    //   57: bipush 93
    //   59: istore_2
    //   60: goto +386 -> 446
    //   63: getstatic 26	o/Ma:ˈ	I
    //   66: bipush 53
    //   68: iadd
    //   69: istore_2
    //   70: iload_2
    //   71: sipush 128
    //   74: irem
    //   75: putstatic 24	o/Ma:ʾ	I
    //   78: iload_2
    //   79: iconst_2
    //   80: irem
    //   81: ifeq +6 -> 87
    //   84: goto +31 -> 115
    //   87: goto +90 -> 177
    //   90: goto -27 -> 63
    //   93: astore_1
    //   94: aload_1
    //   95: athrow
    //   96: aload_0
    //   97: aload_1
    //   98: iconst_4
    //   99: invokevirtual 80	java/lang/String:substring	(I)Ljava/lang/String;
    //   102: invokespecial 84	o/Ma:ˎ	(Ljava/lang/String;)Ljava/lang/String;
    //   105: invokevirtual 88	java/lang/String:intern	()Ljava/lang/String;
    //   108: areturn
    //   109: goto +260 -> 369
    //   112: goto +363 -> 475
    //   115: iconst_1
    //   116: istore_2
    //   117: goto +68 -> 185
    //   120: ldc 90
    //   122: areturn
    //   123: aload_0
    //   124: getstatic 95	o/LV$If:receive_money_card	I
    //   127: invokevirtual 98	o/Ma:getString	(I)Ljava/lang/String;
    //   130: astore_1
    //   131: aload_1
    //   132: iconst_5
    //   133: newarray char
    //   135: dup
    //   136: iconst_0
    //   137: ldc 99
    //   139: castore
    //   140: dup
    //   141: iconst_1
    //   142: ldc 100
    //   144: castore
    //   145: dup
    //   146: iconst_2
    //   147: ldc 101
    //   149: castore
    //   150: dup
    //   151: iconst_3
    //   152: ldc 102
    //   154: castore
    //   155: dup
    //   156: iconst_4
    //   157: ldc 103
    //   159: castore
    //   160: invokestatic 107	o/Ma:ˋ	([C)Ljava/lang/String;
    //   163: invokevirtual 88	java/lang/String:intern	()Ljava/lang/String;
    //   166: invokevirtual 111	java/lang/String:startsWith	(Ljava/lang/String;)Z
    //   169: ifeq +6 -> 175
    //   172: goto +243 -> 415
    //   175: aload_1
    //   176: areturn
    //   177: iconst_0
    //   178: istore_2
    //   179: goto +6 -> 185
    //   182: astore_1
    //   183: aload_1
    //   184: athrow
    //   185: iload_2
    //   186: tableswitch	default:+22->208, 0:+149->335, 1:+245->431
    //   208: goto +223 -> 431
    //   211: aload_0
    //   212: getstatic 114	o/LV$If:you_will_receive_money_on_this_card	I
    //   215: invokevirtual 98	o/Ma:getString	(I)Ljava/lang/String;
    //   218: astore_1
    //   219: aload_1
    //   220: iconst_5
    //   221: newarray char
    //   223: dup
    //   224: iconst_0
    //   225: ldc 99
    //   227: castore
    //   228: dup
    //   229: iconst_1
    //   230: ldc 100
    //   232: castore
    //   233: dup
    //   234: iconst_2
    //   235: ldc 101
    //   237: castore
    //   238: dup
    //   239: iconst_3
    //   240: ldc 102
    //   242: castore
    //   243: dup
    //   244: iconst_4
    //   245: ldc 103
    //   247: castore
    //   248: invokestatic 107	o/Ma:ˋ	([C)Ljava/lang/String;
    //   251: invokevirtual 88	java/lang/String:intern	()Ljava/lang/String;
    //   254: invokevirtual 111	java/lang/String:startsWith	(Ljava/lang/String;)Z
    //   257: ifeq +6 -> 263
    //   260: goto +149 -> 409
    //   263: goto -206 -> 57
    //   266: getstatic 117	o/LV$If:you_requested_money_on_this_card	I
    //   269: istore_2
    //   270: aload_0
    //   271: iload_2
    //   272: invokevirtual 98	o/Ma:getString	(I)Ljava/lang/String;
    //   275: astore_1
    //   276: aload_1
    //   277: iconst_5
    //   278: newarray char
    //   280: dup
    //   281: iconst_0
    //   282: ldc 99
    //   284: castore
    //   285: dup
    //   286: iconst_1
    //   287: ldc 100
    //   289: castore
    //   290: dup
    //   291: iconst_2
    //   292: ldc 101
    //   294: castore
    //   295: dup
    //   296: iconst_3
    //   297: ldc 102
    //   299: castore
    //   300: dup
    //   301: iconst_4
    //   302: ldc 103
    //   304: castore
    //   305: invokestatic 107	o/Ma:ˋ	([C)Ljava/lang/String;
    //   308: invokevirtual 88	java/lang/String:intern	()Ljava/lang/String;
    //   311: invokevirtual 111	java/lang/String:startsWith	(Ljava/lang/String;)Z
    //   314: ifeq +6 -> 320
    //   317: goto -221 -> 96
    //   320: aload_1
    //   321: areturn
    //   322: aload_0
    //   323: aload_1
    //   324: iconst_4
    //   325: invokevirtual 80	java/lang/String:substring	(I)Ljava/lang/String;
    //   328: invokespecial 84	o/Ma:ˎ	(Ljava/lang/String;)Ljava/lang/String;
    //   331: invokevirtual 88	java/lang/String:intern	()Ljava/lang/String;
    //   334: areturn
    //   335: aload_1
    //   336: ifnonnull +6 -> 342
    //   339: goto +43 -> 382
    //   342: goto -337 -> 5
    //   345: getstatic 24	o/Ma:ʾ	I
    //   348: bipush 119
    //   350: iadd
    //   351: istore_2
    //   352: iload_2
    //   353: sipush 128
    //   356: irem
    //   357: putstatic 26	o/Ma:ˈ	I
    //   360: iload_2
    //   361: iconst_2
    //   362: irem
    //   363: ifne +6 -> 369
    //   366: goto -257 -> 109
    //   369: aload_0
    //   370: aload_1
    //   371: iconst_4
    //   372: invokevirtual 80	java/lang/String:substring	(I)Ljava/lang/String;
    //   375: invokespecial 84	o/Ma:ˎ	(Ljava/lang/String;)Ljava/lang/String;
    //   378: invokevirtual 88	java/lang/String:intern	()Ljava/lang/String;
    //   381: areturn
    //   382: getstatic 24	o/Ma:ʾ	I
    //   385: bipush 21
    //   387: iadd
    //   388: istore_2
    //   389: iload_2
    //   390: sipush 128
    //   393: irem
    //   394: putstatic 26	o/Ma:ˈ	I
    //   397: iload_2
    //   398: iconst_2
    //   399: irem
    //   400: ifne +6 -> 406
    //   403: goto -291 -> 112
    //   406: goto +69 -> 475
    //   409: bipush 99
    //   411: istore_2
    //   412: goto +34 -> 446
    //   415: aload_0
    //   416: aload_1
    //   417: iconst_4
    //   418: invokevirtual 80	java/lang/String:substring	(I)Ljava/lang/String;
    //   421: invokespecial 84	o/Ma:ˎ	(Ljava/lang/String;)Ljava/lang/String;
    //   424: invokevirtual 88	java/lang/String:intern	()Ljava/lang/String;
    //   427: astore_1
    //   428: goto -425 -> 3
    //   431: bipush 31
    //   433: iconst_0
    //   434: idiv
    //   435: istore_2
    //   436: aload_1
    //   437: ifnonnull +6 -> 443
    //   440: goto -58 -> 382
    //   443: goto -438 -> 5
    //   446: iload_2
    //   447: lookupswitch	default:+25->472, 93:+-392->55, 99:+-102->345
    //   472: goto -127 -> 345
    //   475: aload_0
    //   476: getstatic 120	o/LV$If:select_the_card_receive_money	I
    //   479: invokevirtual 98	o/Ma:getString	(I)Ljava/lang/String;
    //   482: astore_1
    //   483: aload_1
    //   484: iconst_5
    //   485: newarray char
    //   487: dup
    //   488: iconst_0
    //   489: ldc 99
    //   491: castore
    //   492: dup
    //   493: iconst_1
    //   494: ldc 100
    //   496: castore
    //   497: dup
    //   498: iconst_2
    //   499: ldc 101
    //   501: castore
    //   502: dup
    //   503: iconst_3
    //   504: ldc 102
    //   506: castore
    //   507: dup
    //   508: iconst_4
    //   509: ldc 103
    //   511: castore
    //   512: invokestatic 107	o/Ma:ˋ	([C)Ljava/lang/String;
    //   515: invokevirtual 88	java/lang/String:intern	()Ljava/lang/String;
    //   518: invokevirtual 111	java/lang/String:startsWith	(Ljava/lang/String;)Z
    //   521: ifeq +6 -> 527
    //   524: goto -202 -> 322
    //   527: aload_1
    //   528: areturn
    // Exception table:
    //   from	to	target	type
    //   266	270	93	java/lang/Exception
    //   270	276	93	java/lang/Exception
    //   345	352	93	java/lang/Exception
    //   352	360	93	java/lang/Exception
  }
  
  /* Error */
  private void ˊˋ()
  {
    // Byte code:
    //   0: goto +383 -> 383
    //   3: goto +342 -> 345
    //   6: getstatic 134	o/Ep:UNKNOWN	Lo/Ep;
    //   9: astore_2
    //   10: goto +335 -> 345
    //   13: bipush 70
    //   15: istore_1
    //   16: goto +115 -> 131
    //   19: goto +144 -> 163
    //   22: goto +323 -> 345
    //   25: getstatic 26	o/Ma:ˈ	I
    //   28: bipush 107
    //   30: iadd
    //   31: istore_1
    //   32: iload_1
    //   33: sipush 128
    //   36: irem
    //   37: putstatic 24	o/Ma:ʾ	I
    //   40: iload_1
    //   41: iconst_2
    //   42: irem
    //   43: ifeq +6 -> 49
    //   46: goto -27 -> 19
    //   49: goto +114 -> 163
    //   52: getstatic 134	o/Ep:UNKNOWN	Lo/Ep;
    //   55: astore_2
    //   56: aconst_null
    //   57: arraylength
    //   58: istore_1
    //   59: goto +286 -> 345
    //   62: bipush 8
    //   64: istore_1
    //   65: goto +66 -> 131
    //   68: iconst_1
    //   69: istore_1
    //   70: goto +35 -> 105
    //   73: getstatic 24	o/Ma:ʾ	I
    //   76: bipush 99
    //   78: iadd
    //   79: istore_1
    //   80: iload_1
    //   81: sipush 128
    //   84: irem
    //   85: putstatic 26	o/Ma:ˈ	I
    //   88: iload_1
    //   89: iconst_2
    //   90: irem
    //   91: ifne +6 -> 97
    //   94: goto -72 -> 22
    //   97: goto -94 -> 3
    //   100: astore_2
    //   101: aload_2
    //   102: athrow
    //   103: iconst_0
    //   104: istore_1
    //   105: iload_1
    //   106: tableswitch	default:+22->128, 0:+-100->6, 1:+-54->52
    //   128: goto -76 -> 52
    //   131: iload_1
    //   132: lookupswitch	default:+28->160, 8:+254->386, 70:+262->394
    //   160: goto +234 -> 394
    //   163: goto +17 -> 180
    //   166: astore_2
    //   167: aload_2
    //   168: invokevirtual 140	java/lang/Throwable:getCause	()Ljava/lang/Throwable;
    //   171: astore_3
    //   172: aload_3
    //   173: ifnull +5 -> 178
    //   176: aload_3
    //   177: athrow
    //   178: aload_2
    //   179: athrow
    //   180: aload_0
    //   181: invokevirtual 146	android/content/Context:getResources	()Landroid/content/res/Resources;
    //   184: ldc -109
    //   186: invokevirtual 150	android/content/res/Resources:getString	(I)Ljava/lang/String;
    //   189: iconst_0
    //   190: iconst_4
    //   191: invokevirtual 153	java/lang/String:substring	(II)Ljava/lang/String;
    //   194: iconst_0
    //   195: invokevirtual 157	java/lang/String:codePointAt	(I)I
    //   198: iconst_1
    //   199: isub
    //   200: aload_0
    //   201: invokevirtual 160	android/content/Context:getPackageName	()Ljava/lang/String;
    //   204: iconst_1
    //   205: invokevirtual 157	java/lang/String:codePointAt	(I)I
    //   208: sipush 156
    //   211: iadd
    //   212: aload_0
    //   213: invokevirtual 164	android/content/Context:getApplicationInfo	()Landroid/content/pm/ApplicationInfo;
    //   216: getfield 169	android/content/pm/ApplicationInfo:targetSdkVersion	I
    //   219: sipush 14763
    //   222: iadd
    //   223: i2c
    //   224: invokestatic 174	o/O:ˋ	(IIC)Ljava/lang/Object;
    //   227: checkcast 176	java/lang/Class
    //   230: ldc -79
    //   232: aconst_null
    //   233: invokevirtual 181	java/lang/Class:getMethod	(Ljava/lang/String;[Ljava/lang/Class;)Ljava/lang/reflect/Method;
    //   236: aconst_null
    //   237: aconst_null
    //   238: invokevirtual 187	java/lang/reflect/Method:invoke	(Ljava/lang/Object;[Ljava/lang/Object;)Ljava/lang/Object;
    //   241: astore_2
    //   242: goto +17 -> 259
    //   245: astore_2
    //   246: aload_2
    //   247: invokevirtual 140	java/lang/Throwable:getCause	()Ljava/lang/Throwable;
    //   250: astore_3
    //   251: aload_3
    //   252: ifnull +5 -> 257
    //   255: aload_3
    //   256: athrow
    //   257: aload_2
    //   258: athrow
    //   259: aload_0
    //   260: invokevirtual 146	android/content/Context:getResources	()Landroid/content/res/Resources;
    //   263: ldc -68
    //   265: invokevirtual 150	android/content/res/Resources:getString	(I)Ljava/lang/String;
    //   268: iconst_0
    //   269: iconst_4
    //   270: invokevirtual 153	java/lang/String:substring	(II)Ljava/lang/String;
    //   273: iconst_1
    //   274: invokevirtual 157	java/lang/String:codePointAt	(I)I
    //   277: bipush 22
    //   279: isub
    //   280: aload_0
    //   281: invokevirtual 164	android/content/Context:getApplicationInfo	()Landroid/content/pm/ApplicationInfo;
    //   284: getfield 169	android/content/pm/ApplicationInfo:targetSdkVersion	I
    //   287: sipush 242
    //   290: iadd
    //   291: aload_0
    //   292: invokevirtual 146	android/content/Context:getResources	()Landroid/content/res/Resources;
    //   295: ldc -67
    //   297: invokevirtual 150	android/content/res/Resources:getString	(I)Ljava/lang/String;
    //   300: iconst_0
    //   301: iconst_4
    //   302: invokevirtual 153	java/lang/String:substring	(II)Ljava/lang/String;
    //   305: iconst_2
    //   306: invokevirtual 157	java/lang/String:codePointAt	(I)I
    //   309: sipush 14777
    //   312: iadd
    //   313: i2c
    //   314: invokestatic 174	o/O:ˋ	(IIC)Ljava/lang/Object;
    //   317: checkcast 176	java/lang/Class
    //   320: ldc -66
    //   322: aconst_null
    //   323: invokevirtual 181	java/lang/Class:getMethod	(Ljava/lang/String;[Ljava/lang/Class;)Ljava/lang/reflect/Method;
    //   326: aload_2
    //   327: aconst_null
    //   328: invokevirtual 187	java/lang/reflect/Method:invoke	(Ljava/lang/Object;[Ljava/lang/Object;)Ljava/lang/Object;
    //   331: checkcast 56	o/HQ
    //   334: astore_2
    //   335: aload_2
    //   336: ifnonnull +6 -> 342
    //   339: goto -326 -> 13
    //   342: goto -280 -> 62
    //   345: getstatic 196	o/FY:SENT	Lo/FY;
    //   348: astore_3
    //   349: getstatic 202	o/FT:REQUEST_MONEY	Lo/FT;
    //   352: astore 4
    //   354: aload_0
    //   355: aload_2
    //   356: aload_3
    //   357: aload 4
    //   359: invokevirtual 206	o/Ma:ॱ	(Lo/Ep;Lo/FY;Lo/FT;)Ljava/util/List;
    //   362: astore_2
    //   363: aload_2
    //   364: checkcast 208	java/util/ArrayList
    //   367: astore_2
    //   368: aload_0
    //   369: getfield 43	o/Ma:ॱˊ	Landroid/databinding/ViewDataBinding;
    //   372: checkcast 45	o/Mn
    //   375: getfield 49	o/Mn:ʻ	Lo/KZ;
    //   378: aload_2
    //   379: invokevirtual 212	o/KZ:setFilters	(Ljava/util/ArrayList;)V
    //   382: return
    //   383: goto -358 -> 25
    //   386: aload_2
    //   387: invokevirtual 215	o/HQ:ʻ	()Lo/Ep;
    //   390: astore_2
    //   391: goto -318 -> 73
    //   394: getstatic 26	o/Ma:ˈ	I
    //   397: bipush 81
    //   399: iadd
    //   400: istore_1
    //   401: iload_1
    //   402: sipush 128
    //   405: irem
    //   406: putstatic 24	o/Ma:ʾ	I
    //   409: iload_1
    //   410: iconst_2
    //   411: irem
    //   412: ifeq +6 -> 418
    //   415: goto -347 -> 68
    //   418: goto -315 -> 103
    // Local variable table:
    //   start	length	slot	name	signature
    //   0	421	0	this	Ma
    //   15	397	1	i	int
    //   9	47	2	localEp	Ep
    //   100	2	2	localException	Exception
    //   166	13	2	localObject1	Object
    //   241	1	2	localObject2	Object
    //   245	82	2	localObject3	Object
    //   334	57	2	localObject4	Object
    //   171	186	3	localObject5	Object
    //   352	6	4	localFT	FT
    // Exception table:
    //   from	to	target	type
    //   345	349	100	java/lang/Exception
    //   349	354	100	java/lang/Exception
    //   354	363	100	java/lang/Exception
    //   363	368	100	java/lang/Exception
    //   368	382	100	java/lang/Exception
    //   180	242	166	finally
    //   259	335	245	finally
  }
  
  private void ˊᐝ()
  {
    break label116;
    boolean bool;
    label8:
    label13:
    for (;;)
    {
      bool = true;
      break label284;
      bool = false;
      break;
    }
    for (;;)
    {
      Object localObject = ((Mn)this.ॱˊ).ˊॱ();
      if (ˊˊ())
      {
        if (((Is)localObject).selectedCard != null) {
          break label175;
        }
        break label106;
        for (;;)
        {
          switch (i)
          {
          case 20: 
          default: 
            label50:
            break label8;
            i = 20;
          }
        }
      }
      else
      {
        ˊˋ();
        ((Mn)this.ॱˊ).ʻ.ˏ();
        break label222;
      }
      label106:
      int i = 0;
      break label119;
      label111:
      ˉ();
      return;
      label116:
      break label287;
      switch (i)
      {
      default: 
        label119:
        break;
      }
      label169:
      label175:
      label222:
      label284:
      for (;;)
      {
        ((Mn)localObject).ˎ(bool);
        if (((Mn)this.ॱˊ).ˋॱ()) {
          break label111;
        }
        return;
        i = 12;
        break label50;
        i = 1;
        break label119;
        ((Mn)this.ॱˊ).ʻ.setCards(Collections.emptyList());
        break label222;
        ((Mn)this.ॱˊ).ʻ.setCards(Collections.singletonList(((Is)localObject).selectedCard));
        for (;;)
        {
          localObject = (Mn)this.ॱˊ;
          if (!an.ˏ(((Mn)this.ॱˊ).ʻ.ॱ())) {
            break label169;
          }
          break;
        }
        i = ʾ + 5;
        ˈ = i % 128;
        if (i % 2 == 0) {
          break label13;
        }
        break;
      }
      label287:
      i = ʾ + 107;
      ˈ = i % 128;
      if (i % 2 != 0) {}
    }
  }
  
  private static String ˋ(char[] paramArrayOfChar)
  {
    label78:
    label130:
    label174:
    label188:
    label246:
    for (;;)
    {
      int i;
      int j;
      int k;
      char[] arrayOfChar;
      if (i >= paramArrayOfChar.length)
      {
        break label174;
        j = 0;
      }
      else
      {
        j = 65;
        break label188;
        long l1 = paramArrayOfChar[i] ^ i / k;
        try
        {
          long l2 = ʽॱ;
          arrayOfChar[(i >> 1)] = ((char)(int)(l1 + l2));
          i += 60;
        }
        catch (Exception paramArrayOfChar)
        {
          throw paramArrayOfChar;
        }
        break label130;
        return new String(arrayOfChar);
      }
      switch (j)
      {
      case 1: 
      default: 
        break;
        for (;;)
        {
          j = ˈ + 95;
          ʾ = j % 128;
          if (j % 2 != 0) {
            break;
          }
          break;
          k = paramArrayOfChar[0];
          arrayOfChar = new char[paramArrayOfChar.length - 1];
          i = 1;
        }
        for (;;)
        {
          j = ˈ + 19;
          ʾ = j % 128;
          if (j % 2 == 0)
          {
            break;
            j = 73;
            break label188;
            break label246;
          }
          j = 1;
          break label78;
          switch (j)
          {
          }
        }
      }
      arrayOfChar[(i - 1)] = ((char)(int)(paramArrayOfChar[i] ^ i * k ^ ʽॱ));
      i += 1;
    }
  }
  
  private void ˋˋ()
  {
    int i = ʾ + 107;
    ˈ = i % 128;
    if (i % 2 != 0) {
      break label67;
    }
    i = 33;
    for (;;)
    {
      ˎ(((Mn)this.ॱˊ).ˊॱ().amount, ((Mn)this.ॱˊ).ˊॱ().currency.ˊ());
      return;
      label67:
      i = 55;
      switch (i)
      {
      }
    }
    ˎ(((Mn)this.ॱˊ).ˊॱ().amount, ((Mn)this.ॱˊ).ˊॱ().currency.ˊ());
    i = null.length;
  }
  
  /* Error */
  private void ˋᐝ()
  {
    // Byte code:
    //   0: goto +32 -> 32
    //   3: getstatic 24	o/Ma:ʾ	I
    //   6: bipush 121
    //   8: iadd
    //   9: istore_1
    //   10: iload_1
    //   11: sipush 128
    //   14: irem
    //   15: putstatic 26	o/Ma:ˈ	I
    //   18: iload_1
    //   19: iconst_2
    //   20: irem
    //   21: ifne +6 -> 27
    //   24: goto +4 -> 28
    //   27: return
    //   28: return
    //   29: astore_2
    //   30: aload_2
    //   31: athrow
    //   32: aload_0
    //   33: getfield 43	o/Ma:ॱˊ	Landroid/databinding/ViewDataBinding;
    //   36: astore_2
    //   37: aload_2
    //   38: checkcast 45	o/Mn
    //   41: astore_2
    //   42: aload_2
    //   43: getfield 49	o/Mn:ʻ	Lo/KZ;
    //   46: astore_2
    //   47: aload_2
    //   48: invokevirtual 282	o/KZ:ᐝ	()Lo/aG;
    //   51: astore_2
    //   52: new 7	o/Ma$2
    //   55: dup
    //   56: aload_0
    //   57: invokespecial 285	o/Ma$2:<init>	(Lo/Ma;)V
    //   60: astore_3
    //   61: aload_2
    //   62: aload_3
    //   63: invokevirtual 290	o/aG:ˎ	(Lo/ڏ$ˏ;)V
    //   66: goto -63 -> 3
    //   69: astore_2
    //   70: aload_2
    //   71: athrow
    // Local variable table:
    //   start	length	slot	name	signature
    //   0	72	0	this	Ma
    //   9	12	1	i	int
    //   29	2	2	localException1	Exception
    //   36	26	2	localObject	Object
    //   69	2	2	localException2	Exception
    //   60	3	3	local2	2
    // Exception table:
    //   from	to	target	type
    //   32	37	29	java/lang/Exception
    //   37	42	29	java/lang/Exception
    //   42	47	29	java/lang/Exception
    //   47	61	29	java/lang/Exception
    //   61	66	29	java/lang/Exception
    //   37	42	69	java/lang/Exception
  }
  
  private void ˌ()
  {
    for (;;)
    {
      ((Mn)this.ॱˊ).ˋ(this.ˊˊ);
      ((Mn)this.ॱˊ).ˋॱ.getIndeterminateDrawable().setColorFilter(ᔆ.ˊ(this, LV.ˊ.romanian_yellow), PorterDuff.Mode.SRC_IN);
      int i = ˈ + 97;
      ʾ = i % 128;
      if (i % 2 == 0) {
        return;
      } else {
        return;
      }
      i = ʾ + 61;
      ˈ = i % 128;
      if (i % 2 == 0) {}
    }
  }
  
  private void ˍ()
  {
    break label39;
    int i = 1;
    break label13;
    label8:
    i = 0;
    switch (i)
    {
    default: 
      break;
    case 1: 
      label13:
      label39:
      Ic.ˏ(this).ˋ(FT.REQUEST_MONEY).ˎ(ˋ(new char[] { -20697, -26196, 26840, 15343, -30208, 23884, 11355, -878, 20409, 7903, -7923, -20422, 869, -11679, -23874, 30150, -15120, -26870, 26166, -13970, -26224, 26754, 15314, -30208, 23860, 11340, -185, 20375, 7887, -7695, -20451, 830, -11678, -23910 }).intern(), ((Mn)this.ॱˊ).ˊॱ()).ˎ();
    }
    for (;;)
    {
      i = ʾ + 51;
      ˈ = i % 128;
      if (i % 2 == 0) {
        return;
      }
      return;
      i = ˈ + 17;
      ʾ = i % 128;
      if (i % 2 != 0) {
        break label8;
      }
      break;
      Ic.ˏ(this).ˋ(FT.REQUEST_MONEY).ˎ(ˋ(new char[] { -20697, -26196, 26840, 15343, -30208, 23884, 11355, -878, 20409, 7903, -7923, -20422, 869, -11679, -23874, 30150, -15120, -26870, 26166, -13970, -26224, 26754, 15314, -30208, 23860, 11340, -185, 20375, 7887, -7695, -20451, 830, -11678, -23910 }).intern(), ((Mn)this.ॱˊ).ˊॱ()).ˎ();
      i = 94 / 0;
    }
  }
  
  /* Error */
  private String ˎ(String paramString)
  {
    // Byte code:
    //   0: goto +49 -> 49
    //   3: getstatic 24	o/Ma:ʾ	I
    //   6: bipush 13
    //   8: iadd
    //   9: istore_3
    //   10: iload_3
    //   11: sipush 128
    //   14: irem
    //   15: putstatic 26	o/Ma:ˈ	I
    //   18: iload_3
    //   19: iconst_2
    //   20: irem
    //   21: ifne +6 -> 27
    //   24: goto +40 -> 64
    //   27: goto +50 -> 77
    //   30: bipush 57
    //   32: istore_2
    //   33: goto +47 -> 80
    //   36: bipush 21
    //   38: iconst_0
    //   39: idiv
    //   40: istore_2
    //   41: aload_1
    //   42: areturn
    //   43: bipush 82
    //   45: istore_2
    //   46: goto +34 -> 80
    //   49: goto +210 -> 259
    //   52: aload_1
    //   53: areturn
    //   54: iconst_1
    //   55: istore_3
    //   56: goto +120 -> 176
    //   59: iconst_0
    //   60: istore_3
    //   61: goto +115 -> 176
    //   64: goto +13 -> 77
    //   67: astore_1
    //   68: new 381	java/lang/RuntimeException
    //   71: dup
    //   72: aload_1
    //   73: invokespecial 384	java/lang/RuntimeException:<init>	(Ljava/lang/Throwable;)V
    //   76: athrow
    //   77: goto +34 -> 111
    //   80: iload_2
    //   81: lookupswitch	default:+27->108, 57:+-45->36, 82:+-29->52
    //   108: goto -72 -> 36
    //   111: aload_1
    //   112: arraylength
    //   113: istore_3
    //   114: iload_2
    //   115: iload_3
    //   116: if_icmpge +6 -> 122
    //   119: goto -60 -> 59
    //   122: goto -68 -> 54
    //   125: aload 4
    //   127: iload_2
    //   128: aload_1
    //   129: aload_1
    //   130: arraylength
    //   131: iload_2
    //   132: isub
    //   133: iconst_1
    //   134: isub
    //   135: baload
    //   136: getstatic 30	o/Ma:ʼॱ	B
    //   139: ixor
    //   140: i2b
    //   141: bastore
    //   142: iload_2
    //   143: iconst_1
    //   144: iadd
    //   145: istore_2
    //   146: goto -143 -> 3
    //   149: getstatic 24	o/Ma:ʾ	I
    //   152: bipush 17
    //   154: iadd
    //   155: istore_2
    //   156: iload_2
    //   157: sipush 128
    //   160: irem
    //   161: putstatic 26	o/Ma:ˈ	I
    //   164: iload_2
    //   165: iconst_2
    //   166: irem
    //   167: ifne +6 -> 173
    //   170: goto -140 -> 30
    //   173: goto -130 -> 43
    //   176: iload_3
    //   177: tableswitch	default:+23->200, 0:+-52->125, 1:+23->200
    //   200: new 76	java/lang/String
    //   203: dup
    //   204: aload 4
    //   206: bipush 6
    //   208: newarray char
    //   210: dup
    //   211: iconst_0
    //   212: ldc_w 385
    //   215: castore
    //   216: dup
    //   217: iconst_1
    //   218: ldc_w 386
    //   221: castore
    //   222: dup
    //   223: iconst_2
    //   224: ldc_w 387
    //   227: castore
    //   228: dup
    //   229: iconst_3
    //   230: ldc_w 388
    //   233: castore
    //   234: dup
    //   235: iconst_4
    //   236: ldc_w 389
    //   239: castore
    //   240: dup
    //   241: iconst_5
    //   242: ldc_w 390
    //   245: castore
    //   246: invokestatic 107	o/Ma:ˋ	([C)Ljava/lang/String;
    //   249: invokevirtual 88	java/lang/String:intern	()Ljava/lang/String;
    //   252: invokespecial 393	java/lang/String:<init>	([BLjava/lang/String;)V
    //   255: astore_1
    //   256: goto -107 -> 149
    //   259: aload_1
    //   260: bipush 11
    //   262: newarray char
    //   264: dup
    //   265: iconst_0
    //   266: ldc_w 394
    //   269: castore
    //   270: dup
    //   271: iconst_1
    //   272: ldc_w 395
    //   275: castore
    //   276: dup
    //   277: iconst_2
    //   278: ldc_w 396
    //   281: castore
    //   282: dup
    //   283: iconst_3
    //   284: ldc_w 397
    //   287: castore
    //   288: dup
    //   289: iconst_4
    //   290: ldc_w 398
    //   293: castore
    //   294: dup
    //   295: iconst_5
    //   296: ldc_w 399
    //   299: castore
    //   300: dup
    //   301: bipush 6
    //   303: ldc_w 400
    //   306: castore
    //   307: dup
    //   308: bipush 7
    //   310: ldc_w 401
    //   313: castore
    //   314: dup
    //   315: bipush 8
    //   317: ldc_w 402
    //   320: castore
    //   321: dup
    //   322: bipush 9
    //   324: ldc_w 403
    //   327: castore
    //   328: dup
    //   329: bipush 10
    //   331: ldc_w 404
    //   334: castore
    //   335: invokestatic 107	o/Ma:ˋ	([C)Ljava/lang/String;
    //   338: invokevirtual 88	java/lang/String:intern	()Ljava/lang/String;
    //   341: invokevirtual 408	java/lang/String:getBytes	(Ljava/lang/String;)[B
    //   344: astore_1
    //   345: aload_1
    //   346: arraylength
    //   347: newarray byte
    //   349: astore 4
    //   351: iconst_0
    //   352: istore_2
    //   353: goto -242 -> 111
    // Local variable table:
    //   start	length	slot	name	signature
    //   0	356	0	this	Ma
    //   0	356	1	paramString	String
    //   32	321	2	i	int
    //   9	168	3	j	int
    //   125	225	4	arrayOfByte	byte[]
    // Exception table:
    //   from	to	target	type
    //   111	114	67	java/io/UnsupportedEncodingException
    //   125	142	67	java/io/UnsupportedEncodingException
    //   200	256	67	java/io/UnsupportedEncodingException
    //   259	351	67	java/io/UnsupportedEncodingException
  }
  
  /* Error */
  private void ˎ(Is paramIs)
  {
    // Byte code:
    //   0: goto +387 -> 387
    //   3: goto +6 -> 9
    //   6: goto +231 -> 237
    //   9: aload_1
    //   10: getfield 413	o/Is:status	Lo/FV;
    //   13: astore 6
    //   15: aload_0
    //   16: getfield 43	o/Ma:ॱˊ	Landroid/databinding/ViewDataBinding;
    //   19: checkcast 45	o/Mn
    //   22: aload_1
    //   23: invokevirtual 415	o/Mn:ˋ	(Lo/Is;)V
    //   26: aload_0
    //   27: invokespecial 417	o/Ma:ˊᐝ	()V
    //   30: aload_0
    //   31: invokespecial 419	o/Ma:ˋᐝ	()V
    //   34: aload_0
    //   35: getfield 43	o/Ma:ॱˊ	Landroid/databinding/ViewDataBinding;
    //   38: checkcast 45	o/Mn
    //   41: getfield 49	o/Mn:ʻ	Lo/KZ;
    //   44: invokevirtual 423	o/KZ:ॱॱ	()Lcom/insidesecure/hce/MatrixHCECard;
    //   47: ifnonnull +6 -> 53
    //   50: goto +73 -> 123
    //   53: goto +65 -> 118
    //   56: aload_0
    //   57: getstatic 426	o/LV$If:transaction_details_card_deleted	I
    //   60: invokevirtual 98	o/Ma:getString	(I)Ljava/lang/String;
    //   63: astore 5
    //   65: aload 5
    //   67: iconst_5
    //   68: newarray char
    //   70: dup
    //   71: iconst_0
    //   72: ldc 99
    //   74: castore
    //   75: dup
    //   76: iconst_1
    //   77: ldc 100
    //   79: castore
    //   80: dup
    //   81: iconst_2
    //   82: ldc 101
    //   84: castore
    //   85: dup
    //   86: iconst_3
    //   87: ldc 102
    //   89: castore
    //   90: dup
    //   91: iconst_4
    //   92: ldc 103
    //   94: castore
    //   95: invokestatic 107	o/Ma:ˋ	([C)Ljava/lang/String;
    //   98: invokevirtual 88	java/lang/String:intern	()Ljava/lang/String;
    //   101: invokevirtual 111	java/lang/String:startsWith	(Ljava/lang/String;)Z
    //   104: ifeq +6 -> 110
    //   107: goto +52 -> 159
    //   110: goto -104 -> 6
    //   113: iconst_2
    //   114: istore_2
    //   115: goto +62 -> 177
    //   118: iconst_0
    //   119: istore_2
    //   120: goto +270 -> 390
    //   123: iconst_1
    //   124: istore_2
    //   125: goto +330 -> 455
    //   128: iconst_0
    //   129: istore_2
    //   130: goto +155 -> 285
    //   133: goto +284 -> 417
    //   136: aload 5
    //   138: iload_2
    //   139: invokevirtual 432	o/Je:setValueStyle	(I)V
    //   142: aload_0
    //   143: getfield 43	o/Ma:ॱˊ	Landroid/databinding/ViewDataBinding;
    //   146: checkcast 45	o/Mn
    //   149: aload_0
    //   150: invokespecial 127	o/Ma:ˎˏ	()Z
    //   153: invokevirtual 434	o/Mn:ˋ	(Z)V
    //   156: goto +205 -> 361
    //   159: aload_0
    //   160: aload 5
    //   162: iconst_4
    //   163: invokevirtual 80	java/lang/String:substring	(I)Ljava/lang/String;
    //   166: invokespecial 84	o/Ma:ˎ	(Ljava/lang/String;)Ljava/lang/String;
    //   169: invokevirtual 88	java/lang/String:intern	()Ljava/lang/String;
    //   172: astore 5
    //   174: goto -168 -> 6
    //   177: iload_2
    //   178: lookupswitch	default:+26->204, 2:+138->316, 82:+-122->56
    //   204: goto -148 -> 56
    //   207: astore_1
    //   208: aload_1
    //   209: athrow
    //   210: getstatic 26	o/Ma:ˈ	I
    //   213: bipush 75
    //   215: iadd
    //   216: istore_2
    //   217: iload_2
    //   218: sipush 128
    //   221: irem
    //   222: putstatic 24	o/Ma:ʾ	I
    //   225: iload_2
    //   226: iconst_2
    //   227: irem
    //   228: ifeq +6 -> 234
    //   231: goto -228 -> 3
    //   234: goto -225 -> 9
    //   237: aload 7
    //   239: aload 5
    //   241: invokevirtual 437	o/Mn:ˊ	(Ljava/lang/String;)V
    //   244: aload_0
    //   245: getfield 43	o/Ma:ॱˊ	Landroid/databinding/ViewDataBinding;
    //   248: checkcast 45	o/Mn
    //   251: astore 5
    //   253: aload 6
    //   255: ifnull +6 -> 261
    //   258: goto +53 -> 311
    //   261: goto -133 -> 128
    //   264: goto +18 -> 282
    //   267: astore_1
    //   268: aload_1
    //   269: athrow
    //   270: iconst_1
    //   271: istore 4
    //   273: goto +144 -> 417
    //   276: bipush 82
    //   278: istore_2
    //   279: goto -102 -> 177
    //   282: goto +173 -> 455
    //   285: iload_2
    //   286: tableswitch	default:+22->308, 0:+163->449, 1:+-16->270
    //   308: goto +141 -> 449
    //   311: iconst_1
    //   312: istore_2
    //   313: goto -28 -> 285
    //   316: aload_0
    //   317: aload 6
    //   319: invokespecial 439	o/Ma:ˊ	(Lo/FV;)Ljava/lang/String;
    //   322: astore 5
    //   324: goto -87 -> 237
    //   327: getstatic 26	o/Ma:ˈ	I
    //   330: bipush 71
    //   332: iadd
    //   333: istore_2
    //   334: iload_2
    //   335: sipush 128
    //   338: irem
    //   339: putstatic 24	o/Ma:ʾ	I
    //   342: iload_2
    //   343: iconst_2
    //   344: irem
    //   345: ifeq +6 -> 351
    //   348: goto +36 -> 384
    //   351: goto -218 -> 133
    //   354: getstatic 444	o/LV$if:F15R_Black	I
    //   357: istore_2
    //   358: goto -222 -> 136
    //   361: getstatic 26	o/Ma:ˈ	I
    //   364: bipush 79
    //   366: iadd
    //   367: istore_2
    //   368: iload_2
    //   369: sipush 128
    //   372: irem
    //   373: putstatic 24	o/Ma:ʾ	I
    //   376: iload_2
    //   377: iconst_2
    //   378: irem
    //   379: ifeq +4 -> 383
    //   382: return
    //   383: return
    //   384: goto -251 -> 133
    //   387: goto -177 -> 210
    //   390: getstatic 26	o/Ma:ˈ	I
    //   393: bipush 17
    //   395: iadd
    //   396: istore_3
    //   397: iload_3
    //   398: sipush 128
    //   401: irem
    //   402: putstatic 24	o/Ma:ʾ	I
    //   405: iload_3
    //   406: iconst_2
    //   407: irem
    //   408: ifeq +6 -> 414
    //   411: goto -147 -> 264
    //   414: goto -132 -> 282
    //   417: aload 5
    //   419: iload 4
    //   421: invokevirtual 446	o/Mn:ॱ	(Z)V
    //   424: aload_0
    //   425: getfield 43	o/Ma:ॱˊ	Landroid/databinding/ViewDataBinding;
    //   428: checkcast 45	o/Mn
    //   431: getfield 450	o/Mn:ʿ	Lo/Je;
    //   434: astore 5
    //   436: aload_1
    //   437: invokevirtual 452	o/Is:ˊ	()Z
    //   440: ifeq +6 -> 446
    //   443: goto +86 -> 529
    //   446: goto -92 -> 354
    //   449: iconst_0
    //   450: istore 4
    //   452: goto -125 -> 327
    //   455: aload_0
    //   456: getfield 43	o/Ma:ॱˊ	Landroid/databinding/ViewDataBinding;
    //   459: astore 5
    //   461: aload 5
    //   463: checkcast 45	o/Mn
    //   466: astore 5
    //   468: invokestatic 458	java/util/Calendar:getInstance	()Ljava/util/Calendar;
    //   471: astore 7
    //   473: aload 7
    //   475: invokevirtual 462	java/util/Calendar:getTime	()Ljava/util/Date;
    //   478: astore 7
    //   480: aload 7
    //   482: invokestatic 467	o/ak:ˏ	(Ljava/util/Date;)Ljava/lang/String;
    //   485: astore 7
    //   487: aload 5
    //   489: aload 7
    //   491: invokevirtual 469	o/Mn:ˋ	(Ljava/lang/String;)V
    //   494: aload_0
    //   495: getfield 43	o/Ma:ॱˊ	Landroid/databinding/ViewDataBinding;
    //   498: checkcast 45	o/Mn
    //   501: aload_0
    //   502: aload 6
    //   504: invokespecial 471	o/Ma:ˏ	(Lo/FV;)Ljava/lang/String;
    //   507: invokevirtual 473	o/Mn:ॱ	(Ljava/lang/String;)V
    //   510: aload_0
    //   511: getfield 43	o/Ma:ॱˊ	Landroid/databinding/ViewDataBinding;
    //   514: checkcast 45	o/Mn
    //   517: astore 7
    //   519: iload_2
    //   520: ifeq +6 -> 526
    //   523: goto -247 -> 276
    //   526: goto -413 -> 113
    //   529: getstatic 476	o/LV$if:F15B_Black	I
    //   532: istore_2
    //   533: goto -397 -> 136
    // Local variable table:
    //   start	length	slot	name	signature
    //   0	536	0	this	Ma
    //   0	536	1	paramIs	Is
    //   114	419	2	i	int
    //   396	12	3	j	int
    //   271	180	4	bool	boolean
    //   63	425	5	localObject1	Object
    //   13	490	6	localFV	FV
    //   237	281	7	localObject2	Object
    // Exception table:
    //   from	to	target	type
    //   461	468	207	java/lang/Exception
    //   468	473	207	java/lang/Exception
    //   473	480	207	java/lang/Exception
    //   480	487	207	java/lang/Exception
    //   487	519	207	java/lang/Exception
    //   455	461	267	java/lang/Exception
  }
  
  /* Error */
  private void ˎˎ()
  {
    // Byte code:
    //   0: goto +36 -> 36
    //   3: bipush 8
    //   5: iconst_0
    //   6: idiv
    //   7: istore_1
    //   8: return
    //   9: getstatic 24	o/Ma:ʾ	I
    //   12: bipush 57
    //   14: iadd
    //   15: istore_1
    //   16: iload_1
    //   17: sipush 128
    //   20: irem
    //   21: putstatic 26	o/Ma:ˈ	I
    //   24: iload_1
    //   25: iconst_2
    //   26: irem
    //   27: ifne +6 -> 33
    //   30: goto +15 -> 45
    //   33: goto +6 -> 39
    //   36: goto +15 -> 51
    //   39: bipush 86
    //   41: istore_1
    //   42: goto +465 -> 507
    //   45: bipush 35
    //   47: istore_1
    //   48: goto +459 -> 507
    //   51: aload_0
    //   52: getfield 294	o/Ma:ˊˊ	Lo/coN;
    //   55: iconst_1
    //   56: invokevirtual 480	o/coN:ˋ	(Z)V
    //   59: aload_0
    //   60: getfield 43	o/Ma:ॱˊ	Landroid/databinding/ViewDataBinding;
    //   63: checkcast 45	o/Mn
    //   66: invokevirtual 219	o/Mn:ˊॱ	()Lo/Is;
    //   69: astore_3
    //   70: new 482	o/FZ
    //   73: dup
    //   74: invokespecial 483	o/FZ:<init>	()V
    //   77: astore_2
    //   78: aload_2
    //   79: aload_0
    //   80: getfield 43	o/Ma:ॱˊ	Landroid/databinding/ViewDataBinding;
    //   83: checkcast 45	o/Mn
    //   86: getfield 49	o/Mn:ʻ	Lo/KZ;
    //   89: invokevirtual 423	o/KZ:ॱॱ	()Lcom/insidesecure/hce/MatrixHCECard;
    //   92: invokestatic 486	o/HQ:ˏ	(Lcom/insidesecure/hce/MatrixHCECard;)Lo/HQ;
    //   95: invokevirtual 488	o/HQ:ॱॱ	()Ljava/lang/String;
    //   98: putfield 491	o/FZ:initiatorCardInstanceUuid	Ljava/lang/String;
    //   101: aload_2
    //   102: getstatic 496	o/Gv:ॱ	Lo/Gv;
    //   105: invokevirtual 499	o/Gv:ˏॱ	()Ljava/lang/String;
    //   108: putfield 502	o/FZ:initiatorWalletAppInstanceId	Ljava/lang/String;
    //   111: aload_2
    //   112: aconst_null
    //   113: putfield 505	o/FZ:accepterCardInstanceUuid	Ljava/lang/String;
    //   116: aload_2
    //   117: aconst_null
    //   118: putfield 508	o/FZ:accepterWalletAppInstanceId	Ljava/lang/String;
    //   121: aload_2
    //   122: aload_3
    //   123: getfield 272	o/Is:currency	Lo/Ep;
    //   126: putfield 509	o/FZ:currency	Lo/Ep;
    //   129: aload_2
    //   130: new 511	java/math/BigDecimal
    //   133: dup
    //   134: aload_3
    //   135: getfield 269	o/Is:amount	Ljava/lang/String;
    //   138: invokespecial 513	java/math/BigDecimal:<init>	(Ljava/lang/String;)V
    //   141: putfield 516	o/FZ:amount	Ljava/math/BigDecimal;
    //   144: aload_2
    //   145: getstatic 519	java/math/BigDecimal:ZERO	Ljava/math/BigDecimal;
    //   148: putfield 522	o/FZ:fee	Ljava/math/BigDecimal;
    //   151: aload_2
    //   152: getstatic 528	o/FU:OUTBOUND	Lo/FU;
    //   155: putfield 531	o/FZ:type	Lo/FU;
    //   158: aload_2
    //   159: getstatic 537	o/Eq:SMS	Lo/Eq;
    //   162: putfield 540	o/FZ:channel	Lo/Eq;
    //   165: aload_3
    //   166: getfield 544	o/Is:phoneNumber	Lo/ـ;
    //   169: invokevirtual 549	o/ـ:ˏ	()Ljava/lang/Object;
    //   172: checkcast 551	o/FQ
    //   175: astore 4
    //   177: goto +17 -> 194
    //   180: astore_2
    //   181: aload_2
    //   182: invokevirtual 140	java/lang/Throwable:getCause	()Ljava/lang/Throwable;
    //   185: astore_3
    //   186: aload_3
    //   187: ifnull +5 -> 192
    //   190: aload_3
    //   191: athrow
    //   192: aload_2
    //   193: athrow
    //   194: aload_0
    //   195: invokevirtual 146	android/content/Context:getResources	()Landroid/content/res/Resources;
    //   198: ldc_w 552
    //   201: invokevirtual 150	android/content/res/Resources:getString	(I)Ljava/lang/String;
    //   204: iconst_0
    //   205: iconst_4
    //   206: invokevirtual 153	java/lang/String:substring	(II)Ljava/lang/String;
    //   209: invokevirtual 555	java/lang/String:length	()I
    //   212: iconst_0
    //   213: iadd
    //   214: aload_0
    //   215: invokevirtual 146	android/content/Context:getResources	()Landroid/content/res/Resources;
    //   218: ldc_w 556
    //   221: invokevirtual 150	android/content/res/Resources:getString	(I)Ljava/lang/String;
    //   224: iconst_0
    //   225: iconst_4
    //   226: invokevirtual 153	java/lang/String:substring	(II)Ljava/lang/String;
    //   229: invokevirtual 555	java/lang/String:length	()I
    //   232: sipush 409
    //   235: iadd
    //   236: aload_0
    //   237: invokevirtual 160	android/content/Context:getPackageName	()Ljava/lang/String;
    //   240: bipush 9
    //   242: invokevirtual 157	java/lang/String:codePointAt	(I)I
    //   245: sipush 30156
    //   248: iadd
    //   249: i2c
    //   250: invokestatic 174	o/O:ˋ	(IIC)Ljava/lang/Object;
    //   253: checkcast 176	java/lang/Class
    //   256: ldc_w 557
    //   259: aconst_null
    //   260: invokevirtual 181	java/lang/Class:getMethod	(Ljava/lang/String;[Ljava/lang/Class;)Ljava/lang/reflect/Method;
    //   263: aconst_null
    //   264: aconst_null
    //   265: invokevirtual 187	java/lang/reflect/Method:invoke	(Ljava/lang/Object;[Ljava/lang/Object;)Ljava/lang/Object;
    //   268: astore 5
    //   270: goto +17 -> 287
    //   273: astore_2
    //   274: aload_2
    //   275: invokevirtual 140	java/lang/Throwable:getCause	()Ljava/lang/Throwable;
    //   278: astore_3
    //   279: aload_3
    //   280: ifnull +5 -> 285
    //   283: aload_3
    //   284: athrow
    //   285: aload_2
    //   286: athrow
    //   287: aload_0
    //   288: invokevirtual 146	android/content/Context:getResources	()Landroid/content/res/Resources;
    //   291: ldc_w 558
    //   294: invokevirtual 150	android/content/res/Resources:getString	(I)Ljava/lang/String;
    //   297: iconst_0
    //   298: iconst_5
    //   299: invokevirtual 153	java/lang/String:substring	(II)Ljava/lang/String;
    //   302: iconst_4
    //   303: invokevirtual 157	java/lang/String:codePointAt	(I)I
    //   306: sipush 251
    //   309: isub
    //   310: aload_0
    //   311: invokevirtual 146	android/content/Context:getResources	()Landroid/content/res/Resources;
    //   314: ldc_w 559
    //   317: invokevirtual 150	android/content/res/Resources:getString	(I)Ljava/lang/String;
    //   320: iconst_0
    //   321: bipush 8
    //   323: invokevirtual 153	java/lang/String:substring	(II)Ljava/lang/String;
    //   326: invokevirtual 555	java/lang/String:length	()I
    //   329: sipush 405
    //   332: iadd
    //   333: aload_0
    //   334: invokevirtual 164	android/content/Context:getApplicationInfo	()Landroid/content/pm/ApplicationInfo;
    //   337: getfield 169	android/content/pm/ApplicationInfo:targetSdkVersion	I
    //   340: sipush 30228
    //   343: iadd
    //   344: i2c
    //   345: invokestatic 174	o/O:ˋ	(IIC)Ljava/lang/Object;
    //   348: checkcast 176	java/lang/Class
    //   351: ldc_w 561
    //   354: aconst_null
    //   355: invokevirtual 181	java/lang/Class:getMethod	(Ljava/lang/String;[Ljava/lang/Class;)Ljava/lang/reflect/Method;
    //   358: aload 5
    //   360: aconst_null
    //   361: invokevirtual 187	java/lang/reflect/Method:invoke	(Ljava/lang/Object;[Ljava/lang/Object;)Ljava/lang/Object;
    //   364: checkcast 76	java/lang/String
    //   367: astore 5
    //   369: aload_2
    //   370: aload 4
    //   372: aload 5
    //   374: invokevirtual 563	o/FQ:ˊ	(Ljava/lang/String;)Ljava/lang/String;
    //   377: putfield 566	o/FZ:destination	Ljava/lang/String;
    //   380: aload_2
    //   381: aload_3
    //   382: getfield 569	o/Is:transferDetail	Lo/ـ;
    //   385: invokevirtual 549	o/ـ:ˏ	()Ljava/lang/Object;
    //   388: checkcast 76	java/lang/String
    //   391: putfield 572	o/FZ:initiatorMessage	Ljava/lang/String;
    //   394: aload_2
    //   395: getstatic 202	o/FT:REQUEST_MONEY	Lo/FT;
    //   398: putfield 575	o/FZ:scope	Lo/FT;
    //   401: goto +17 -> 418
    //   404: astore_2
    //   405: aload_2
    //   406: invokevirtual 140	java/lang/Throwable:getCause	()Ljava/lang/Throwable;
    //   409: astore_3
    //   410: aload_3
    //   411: ifnull +5 -> 416
    //   414: aload_3
    //   415: athrow
    //   416: aload_2
    //   417: athrow
    //   418: aload_0
    //   419: invokevirtual 164	android/content/Context:getApplicationInfo	()Landroid/content/pm/ApplicationInfo;
    //   422: getfield 169	android/content/pm/ApplicationInfo:targetSdkVersion	I
    //   425: bipush 21
    //   427: isub
    //   428: aload_0
    //   429: invokevirtual 164	android/content/Context:getApplicationInfo	()Landroid/content/pm/ApplicationInfo;
    //   432: getfield 169	android/content/pm/ApplicationInfo:targetSdkVersion	I
    //   435: bipush 110
    //   437: iadd
    //   438: aload_0
    //   439: invokevirtual 146	android/content/Context:getResources	()Landroid/content/res/Resources;
    //   442: ldc_w 576
    //   445: invokevirtual 150	android/content/res/Resources:getString	(I)Ljava/lang/String;
    //   448: iconst_0
    //   449: iconst_4
    //   450: invokevirtual 153	java/lang/String:substring	(II)Ljava/lang/String;
    //   453: iconst_1
    //   454: invokevirtual 157	java/lang/String:codePointAt	(I)I
    //   457: ldc_w 577
    //   460: iadd
    //   461: i2c
    //   462: invokestatic 174	o/O:ˋ	(IIC)Ljava/lang/Object;
    //   465: checkcast 176	java/lang/Class
    //   468: ldc -79
    //   470: aconst_null
    //   471: invokevirtual 181	java/lang/Class:getMethod	(Ljava/lang/String;[Ljava/lang/Class;)Ljava/lang/reflect/Method;
    //   474: aconst_null
    //   475: aconst_null
    //   476: invokevirtual 187	java/lang/reflect/Method:invoke	(Ljava/lang/Object;[Ljava/lang/Object;)Ljava/lang/Object;
    //   479: checkcast 579	o/It
    //   482: astore_3
    //   483: aload_3
    //   484: aload_2
    //   485: invokeinterface 582 2 0
    //   490: new 11	o/Ma$4
    //   493: dup
    //   494: aload_0
    //   495: aload_0
    //   496: invokespecial 585	o/Ma$4:<init>	(Lo/Ma;Landroid/content/Context;)V
    //   499: invokeinterface 590 2 0
    //   504: goto -495 -> 9
    //   507: iload_1
    //   508: lookupswitch	default:+28->536, 35:+-505->3, 86:+31->539
    //   536: goto -533 -> 3
    //   539: return
    // Local variable table:
    //   start	length	slot	name	signature
    //   0	540	0	this	Ma
    //   7	501	1	i	int
    //   77	82	2	localFZ1	FZ
    //   180	13	2	localObject1	Object
    //   273	122	2	localObject2	Object
    //   404	81	2	localFZ2	FZ
    //   69	415	3	localObject3	Object
    //   175	196	4	localFQ	FQ
    //   268	105	5	localObject4	Object
    // Exception table:
    //   from	to	target	type
    //   194	270	180	finally
    //   287	369	273	finally
    //   418	483	404	finally
  }
  
  /* Error */
  private boolean ˎˏ()
  {
    // Byte code:
    //   0: goto +481 -> 481
    //   3: getstatic 26	o/Ma:ˈ	I
    //   6: bipush 79
    //   8: iadd
    //   9: istore_1
    //   10: iload_1
    //   11: sipush 128
    //   14: irem
    //   15: putstatic 24	o/Ma:ʾ	I
    //   18: iload_1
    //   19: iconst_2
    //   20: irem
    //   21: ifeq +6 -> 27
    //   24: goto +115 -> 139
    //   27: goto +142 -> 169
    //   30: bipush 15
    //   32: istore_1
    //   33: goto +194 -> 227
    //   36: iconst_1
    //   37: istore_1
    //   38: goto +76 -> 114
    //   41: aload_0
    //   42: getfield 43	o/Ma:ॱˊ	Landroid/databinding/ViewDataBinding;
    //   45: checkcast 45	o/Mn
    //   48: invokevirtual 219	o/Mn:ˊॱ	()Lo/Is;
    //   51: astore_3
    //   52: aload_0
    //   53: getfield 43	o/Ma:ॱˊ	Landroid/databinding/ViewDataBinding;
    //   56: checkcast 45	o/Mn
    //   59: invokevirtual 241	o/Mn:ˋॱ	()Z
    //   62: ifeq +6 -> 68
    //   65: goto +263 -> 328
    //   68: goto +231 -> 299
    //   71: astore_3
    //   72: aload_3
    //   73: athrow
    //   74: aload_3
    //   75: invokevirtual 452	o/Is:ˊ	()Z
    //   78: ifne +6 -> 84
    //   81: goto +6 -> 87
    //   84: goto +215 -> 299
    //   87: getstatic 24	o/Ma:ʾ	I
    //   90: bipush 91
    //   92: iadd
    //   93: istore_1
    //   94: iload_1
    //   95: sipush 128
    //   98: irem
    //   99: putstatic 26	o/Ma:ˈ	I
    //   102: iload_1
    //   103: iconst_2
    //   104: irem
    //   105: ifne +6 -> 111
    //   108: goto +265 -> 373
    //   111: goto +148 -> 259
    //   114: iload_1
    //   115: tableswitch	default:+21->136, 0:+207->322, 1:+-112->3
    //   136: goto +186 -> 322
    //   139: aload_0
    //   140: getfield 43	o/Ma:ॱˊ	Landroid/databinding/ViewDataBinding;
    //   143: astore_3
    //   144: aload_3
    //   145: checkcast 45	o/Mn
    //   148: astore_3
    //   149: aload_3
    //   150: invokevirtual 593	o/Mn:ͺ	()Z
    //   153: istore_2
    //   154: bipush 17
    //   156: iconst_0
    //   157: idiv
    //   158: istore_1
    //   159: iload_2
    //   160: ifne +6 -> 166
    //   163: goto +204 -> 367
    //   166: goto -136 -> 30
    //   169: aload_0
    //   170: getfield 43	o/Ma:ॱˊ	Landroid/databinding/ViewDataBinding;
    //   173: checkcast 45	o/Mn
    //   176: invokevirtual 593	o/Mn:ͺ	()Z
    //   179: ifne +6 -> 185
    //   182: goto +179 -> 361
    //   185: goto +225 -> 410
    //   188: iconst_0
    //   189: istore_1
    //   190: goto -76 -> 114
    //   193: iconst_1
    //   194: ireturn
    //   195: iload_1
    //   196: lookupswitch	default:+28->224, 13:+-3->193, 18:+126->322
    //   224: goto +98 -> 322
    //   227: iload_1
    //   228: lookupswitch	default:+28->256, 15:+94->322, 84:+-35->193
    //   256: goto -63 -> 193
    //   259: iconst_1
    //   260: istore_2
    //   261: goto +147 -> 408
    //   264: iconst_0
    //   265: istore_1
    //   266: goto +5 -> 271
    //   269: iconst_0
    //   270: ireturn
    //   271: iload_1
    //   272: tableswitch	default:+24->296, 0:+27->299, 1:+104->376
    //   296: goto +80 -> 376
    //   299: iconst_0
    //   300: istore_2
    //   301: goto +107 -> 408
    //   304: aload_0
    //   305: invokevirtual 222	o/Ma:ˊˊ	()Z
    //   308: ifeq +6 -> 314
    //   311: goto -270 -> 41
    //   314: goto +102 -> 416
    //   317: iconst_1
    //   318: istore_1
    //   319: goto -48 -> 271
    //   322: goto -53 -> 269
    //   325: goto -21 -> 304
    //   328: getstatic 26	o/Ma:ˈ	I
    //   331: bipush 117
    //   333: iadd
    //   334: istore_1
    //   335: iload_1
    //   336: sipush 128
    //   339: irem
    //   340: putstatic 24	o/Ma:ʾ	I
    //   343: iload_1
    //   344: iconst_2
    //   345: irem
    //   346: ifeq +6 -> 352
    //   349: goto +56 -> 405
    //   352: goto +83 -> 435
    //   355: astore_3
    //   356: aload_3
    //   357: athrow
    //   358: goto -284 -> 74
    //   361: bipush 13
    //   363: istore_1
    //   364: goto -169 -> 195
    //   367: bipush 84
    //   369: istore_1
    //   370: goto -143 -> 227
    //   373: goto -114 -> 259
    //   376: getstatic 24	o/Ma:ʾ	I
    //   379: istore_1
    //   380: iload_1
    //   381: bipush 21
    //   383: iadd
    //   384: istore_1
    //   385: iload_1
    //   386: sipush 128
    //   389: irem
    //   390: putstatic 26	o/Ma:ˈ	I
    //   393: iload_1
    //   394: iconst_2
    //   395: irem
    //   396: ifne +6 -> 402
    //   399: goto -41 -> 358
    //   402: goto -328 -> 74
    //   405: goto +30 -> 435
    //   408: iload_2
    //   409: ireturn
    //   410: bipush 18
    //   412: istore_1
    //   413: goto -218 -> 195
    //   416: aload_0
    //   417: getfield 43	o/Ma:ॱˊ	Landroid/databinding/ViewDataBinding;
    //   420: checkcast 45	o/Mn
    //   423: invokevirtual 241	o/Mn:ˋॱ	()Z
    //   426: ifeq +6 -> 432
    //   429: goto -393 -> 36
    //   432: goto -244 -> 188
    //   435: aload_0
    //   436: getfield 43	o/Ma:ॱˊ	Landroid/databinding/ViewDataBinding;
    //   439: checkcast 45	o/Mn
    //   442: invokevirtual 593	o/Mn:ͺ	()Z
    //   445: ifne +6 -> 451
    //   448: goto -131 -> 317
    //   451: goto -187 -> 264
    //   454: getstatic 24	o/Ma:ʾ	I
    //   457: bipush 21
    //   459: iadd
    //   460: istore_1
    //   461: iload_1
    //   462: sipush 128
    //   465: irem
    //   466: putstatic 26	o/Ma:ˈ	I
    //   469: iload_1
    //   470: iconst_2
    //   471: irem
    //   472: ifne +6 -> 478
    //   475: goto -150 -> 325
    //   478: goto -174 -> 304
    //   481: goto -27 -> 454
    // Local variable table:
    //   start	length	slot	name	signature
    //   0	484	0	this	Ma
    //   9	463	1	i	int
    //   153	256	2	bool	boolean
    //   51	1	3	localIs	Is
    //   71	4	3	localException1	Exception
    //   143	7	3	localObject	Object
    //   355	2	3	localException2	Exception
    // Exception table:
    //   from	to	target	type
    //   139	144	71	java/lang/Exception
    //   144	149	71	java/lang/Exception
    //   149	159	71	java/lang/Exception
    //   376	380	71	java/lang/Exception
    //   144	149	355	java/lang/Exception
    //   385	393	355	java/lang/Exception
  }
  
  /* Error */
  private String ˏ(FV paramFV)
  {
    // Byte code:
    //   0: goto +138 -> 138
    //   3: goto +168 -> 171
    //   6: iconst_0
    //   7: istore_2
    //   8: goto +582 -> 590
    //   11: iconst_1
    //   12: istore_2
    //   13: goto +577 -> 590
    //   16: getstatic 24	o/Ma:ʾ	I
    //   19: bipush 125
    //   21: iadd
    //   22: istore_2
    //   23: iload_2
    //   24: sipush 128
    //   27: irem
    //   28: putstatic 26	o/Ma:ˈ	I
    //   31: iload_2
    //   32: iconst_2
    //   33: irem
    //   34: ifne +6 -> 40
    //   37: goto +316 -> 353
    //   40: goto +432 -> 472
    //   43: iload_2
    //   44: tableswitch	default:+24->68, 0:+69->113, 1:+274->318
    //   68: goto +45 -> 113
    //   71: goto +506 -> 577
    //   74: aload_0
    //   75: aload_1
    //   76: iconst_4
    //   77: invokevirtual 80	java/lang/String:substring	(I)Ljava/lang/String;
    //   80: invokespecial 84	o/Ma:ˎ	(Ljava/lang/String;)Ljava/lang/String;
    //   83: invokevirtual 88	java/lang/String:intern	()Ljava/lang/String;
    //   86: astore_1
    //   87: aconst_null
    //   88: arraylength
    //   89: istore_2
    //   90: aload_1
    //   91: areturn
    //   92: aload_0
    //   93: aload_1
    //   94: iconst_4
    //   95: invokevirtual 80	java/lang/String:substring	(I)Ljava/lang/String;
    //   98: invokespecial 84	o/Ma:ˎ	(Ljava/lang/String;)Ljava/lang/String;
    //   101: invokevirtual 88	java/lang/String:intern	()Ljava/lang/String;
    //   104: astore_1
    //   105: goto +402 -> 507
    //   108: iconst_1
    //   109: istore_2
    //   110: goto -67 -> 43
    //   113: aload_0
    //   114: getstatic 596	o/LV$If:request_money_confirmation_toolbar	I
    //   117: invokevirtual 98	o/Ma:getString	(I)Ljava/lang/String;
    //   120: astore 4
    //   122: aload 4
    //   124: aload 5
    //   126: invokevirtual 111	java/lang/String:startsWith	(Ljava/lang/String;)Z
    //   129: ifeq +6 -> 135
    //   132: goto +431 -> 563
    //   135: aload 4
    //   137: areturn
    //   138: goto +3 -> 141
    //   141: getstatic 24	o/Ma:ʾ	I
    //   144: bipush 125
    //   146: iadd
    //   147: istore_2
    //   148: iload_2
    //   149: sipush 128
    //   152: irem
    //   153: putstatic 26	o/Ma:ˈ	I
    //   156: iload_2
    //   157: iconst_2
    //   158: irem
    //   159: ifne +6 -> 165
    //   162: goto -159 -> 3
    //   165: goto +6 -> 171
    //   168: ldc 90
    //   170: areturn
    //   171: iconst_5
    //   172: newarray char
    //   174: dup
    //   175: iconst_0
    //   176: ldc 99
    //   178: castore
    //   179: dup
    //   180: iconst_1
    //   181: ldc 100
    //   183: castore
    //   184: dup
    //   185: iconst_2
    //   186: ldc 101
    //   188: castore
    //   189: dup
    //   190: iconst_3
    //   191: ldc 102
    //   193: castore
    //   194: dup
    //   195: iconst_4
    //   196: ldc 103
    //   198: castore
    //   199: invokestatic 107	o/Ma:ˋ	([C)Ljava/lang/String;
    //   202: invokevirtual 88	java/lang/String:intern	()Ljava/lang/String;
    //   205: astore 5
    //   207: aload_1
    //   208: ifnonnull +6 -> 214
    //   211: goto +325 -> 536
    //   214: goto +159 -> 373
    //   217: getstatic 24	o/Ma:ʾ	I
    //   220: iconst_3
    //   221: iadd
    //   222: istore_2
    //   223: iload_2
    //   224: sipush 128
    //   227: irem
    //   228: putstatic 26	o/Ma:ˈ	I
    //   231: iload_2
    //   232: iconst_2
    //   233: irem
    //   234: ifne +6 -> 240
    //   237: goto -163 -> 74
    //   240: goto +5 -> 245
    //   243: aload_1
    //   244: areturn
    //   245: aload_0
    //   246: aload_1
    //   247: iconst_4
    //   248: invokevirtual 80	java/lang/String:substring	(I)Ljava/lang/String;
    //   251: invokespecial 84	o/Ma:ˎ	(Ljava/lang/String;)Ljava/lang/String;
    //   254: invokevirtual 88	java/lang/String:intern	()Ljava/lang/String;
    //   257: areturn
    //   258: aload_0
    //   259: aload_1
    //   260: iconst_4
    //   261: invokevirtual 80	java/lang/String:substring	(I)Ljava/lang/String;
    //   264: invokespecial 84	o/Ma:ˎ	(Ljava/lang/String;)Ljava/lang/String;
    //   267: invokevirtual 88	java/lang/String:intern	()Ljava/lang/String;
    //   270: areturn
    //   271: aload_0
    //   272: getstatic 599	o/LV$If:transaction_requested_rejected	I
    //   275: invokevirtual 98	o/Ma:getString	(I)Ljava/lang/String;
    //   278: astore_1
    //   279: aload_1
    //   280: aload 5
    //   282: invokevirtual 111	java/lang/String:startsWith	(Ljava/lang/String;)Z
    //   285: ifeq +6 -> 291
    //   288: goto -272 -> 16
    //   291: aload_1
    //   292: areturn
    //   293: astore_1
    //   294: aload_1
    //   295: athrow
    //   296: aload_0
    //   297: getstatic 602	o/LV$If:transaction_details_requested	I
    //   300: invokevirtual 98	o/Ma:getString	(I)Ljava/lang/String;
    //   303: astore_1
    //   304: aload_1
    //   305: aload 5
    //   307: invokevirtual 111	java/lang/String:startsWith	(Ljava/lang/String;)Z
    //   310: ifeq +6 -> 316
    //   313: goto +196 -> 509
    //   316: aload_1
    //   317: areturn
    //   318: getstatic 596	o/LV$If:request_money_confirmation_toolbar	I
    //   321: istore_2
    //   322: aload_0
    //   323: iload_2
    //   324: invokevirtual 98	o/Ma:getString	(I)Ljava/lang/String;
    //   327: astore_1
    //   328: aload_1
    //   329: aload 5
    //   331: invokevirtual 111	java/lang/String:startsWith	(Ljava/lang/String;)Z
    //   334: istore_3
    //   335: bipush 86
    //   337: iconst_0
    //   338: idiv
    //   339: istore_2
    //   340: iload_3
    //   341: ifeq +6 -> 347
    //   344: goto -338 -> 6
    //   347: goto -336 -> 11
    //   350: astore_1
    //   351: aload_1
    //   352: athrow
    //   353: aload_0
    //   354: aload_1
    //   355: iconst_4
    //   356: invokevirtual 80	java/lang/String:substring	(I)Ljava/lang/String;
    //   359: invokespecial 84	o/Ma:ˎ	(Ljava/lang/String;)Ljava/lang/String;
    //   362: invokevirtual 88	java/lang/String:intern	()Ljava/lang/String;
    //   365: astore_1
    //   366: bipush 56
    //   368: iconst_0
    //   369: idiv
    //   370: istore_2
    //   371: aload_1
    //   372: areturn
    //   373: getstatic 68	o/Ma$3:ˊ	[I
    //   376: aload_1
    //   377: invokevirtual 74	o/FV:ordinal	()I
    //   380: iaload
    //   381: tableswitch	default:+39->420, 1:+-85->296, 2:+-85->296, 3:+104->485, 4:+47->428, 5:+69->450, 6:+-110->271
    //   420: goto -252 -> 168
    //   423: iconst_0
    //   424: istore_2
    //   425: goto -382 -> 43
    //   428: aload_0
    //   429: getstatic 605	o/LV$If:transaction_requested_expired	I
    //   432: invokevirtual 98	o/Ma:getString	(I)Ljava/lang/String;
    //   435: astore_1
    //   436: aload_1
    //   437: aload 5
    //   439: invokevirtual 111	java/lang/String:startsWith	(Ljava/lang/String;)Z
    //   442: ifeq +6 -> 448
    //   445: goto -228 -> 217
    //   448: aload_1
    //   449: areturn
    //   450: aload_0
    //   451: getstatic 608	o/LV$If:transaction_requested_canceled	I
    //   454: invokevirtual 98	o/Ma:getString	(I)Ljava/lang/String;
    //   457: astore_1
    //   458: aload_1
    //   459: aload 5
    //   461: invokevirtual 111	java/lang/String:startsWith	(Ljava/lang/String;)Z
    //   464: ifeq +6 -> 470
    //   467: goto -209 -> 258
    //   470: aload_1
    //   471: areturn
    //   472: aload_0
    //   473: aload_1
    //   474: iconst_4
    //   475: invokevirtual 80	java/lang/String:substring	(I)Ljava/lang/String;
    //   478: invokespecial 84	o/Ma:ˎ	(Ljava/lang/String;)Ljava/lang/String;
    //   481: invokevirtual 88	java/lang/String:intern	()Ljava/lang/String;
    //   484: areturn
    //   485: aload_0
    //   486: getstatic 611	o/LV$If:transaction_requested_accepted	I
    //   489: invokevirtual 98	o/Ma:getString	(I)Ljava/lang/String;
    //   492: astore_1
    //   493: aload_1
    //   494: aload 5
    //   496: invokevirtual 111	java/lang/String:startsWith	(Ljava/lang/String;)Z
    //   499: ifeq +6 -> 505
    //   502: goto -410 -> 92
    //   505: aload_1
    //   506: areturn
    //   507: aload_1
    //   508: areturn
    //   509: getstatic 26	o/Ma:ˈ	I
    //   512: bipush 9
    //   514: iadd
    //   515: istore_2
    //   516: iload_2
    //   517: sipush 128
    //   520: irem
    //   521: putstatic 24	o/Ma:ʾ	I
    //   524: iload_2
    //   525: iconst_2
    //   526: irem
    //   527: ifeq +6 -> 533
    //   530: goto -459 -> 71
    //   533: goto +44 -> 577
    //   536: getstatic 26	o/Ma:ˈ	I
    //   539: bipush 9
    //   541: iadd
    //   542: istore_2
    //   543: iload_2
    //   544: sipush 128
    //   547: irem
    //   548: putstatic 24	o/Ma:ʾ	I
    //   551: iload_2
    //   552: iconst_2
    //   553: irem
    //   554: ifeq +6 -> 560
    //   557: goto -449 -> 108
    //   560: goto -137 -> 423
    //   563: aload_0
    //   564: aload 4
    //   566: iconst_4
    //   567: invokevirtual 80	java/lang/String:substring	(I)Ljava/lang/String;
    //   570: invokespecial 84	o/Ma:ˎ	(Ljava/lang/String;)Ljava/lang/String;
    //   573: invokevirtual 88	java/lang/String:intern	()Ljava/lang/String;
    //   576: areturn
    //   577: aload_0
    //   578: aload_1
    //   579: iconst_4
    //   580: invokevirtual 80	java/lang/String:substring	(I)Ljava/lang/String;
    //   583: invokespecial 84	o/Ma:ˎ	(Ljava/lang/String;)Ljava/lang/String;
    //   586: invokevirtual 88	java/lang/String:intern	()Ljava/lang/String;
    //   589: areturn
    //   590: aload_1
    //   591: astore 4
    //   593: iload_2
    //   594: tableswitch	default:+22->616, 0:+-31->563, 1:+-351->243
    //   616: aload_1
    //   617: areturn
    // Local variable table:
    //   start	length	slot	name	signature
    //   0	618	0	this	Ma
    //   0	618	1	paramFV	FV
    //   7	587	2	i	int
    //   334	7	3	bool	boolean
    //   120	472	4	localObject	Object
    //   124	371	5	str	String
    // Exception table:
    //   from	to	target	type
    //   318	322	293	java/lang/Exception
    //   322	328	293	java/lang/Exception
    //   328	340	293	java/lang/Exception
    //   353	371	293	java/lang/Exception
    //   328	340	350	java/lang/Exception
  }
  
  public Resources getResources()
  {
    break label64;
    return oH.ˊ(super.getResources());
    int i;
    switch (i)
    {
    }
    Resources localResources = super.getResources();
    for (;;)
    {
      try
      {
        localResources = oH.ˊ(localResources);
        i = null.length;
        return localResources;
      }
      catch (Exception localException)
      {
        throw localException;
      }
      i = 0;
      break;
      label64:
      do
      {
        i = 1;
        break;
        i = ˈ + 97;
        ʾ = i % 128;
      } while (i % 2 != 0);
    }
  }
  
  public void onActivityResult(int paramInt1, int paramInt2, Intent paramIntent)
  {
    break label95;
    label3:
    paramInt1 = 1;
    break label68;
    break label164;
    for (;;)
    {
      paramInt1 = 0;
      switch (paramInt1)
      {
      default: 
        label13:
        break label130;
        for (;;)
        {
          try
          {
            paramInt1 = ˈ;
            paramInt1 += 97;
          }
          catch (Exception paramIntent)
          {
            label68:
            throw paramIntent;
          }
          try
          {
            ʾ = paramInt1 % 128;
            if (paramInt1 % 2 != 0) {
              break;
            }
          }
          catch (Exception paramIntent)
          {
            throw paramIntent;
          }
          switch (paramInt1)
          {
          }
        }
        label95:
        break label141;
        paramInt1 = ʾ + 89;
        ˈ = paramInt1 % 128;
        if (paramInt1 % 2 == 0) {
          break label131;
        }
      }
    }
    for (;;)
    {
      paramInt1 = 0;
      break label68;
      label130:
      return;
      label131:
      paramInt1 = 1;
      break label13;
      return;
      return;
      switch (paramInt1)
      {
      default: 
        return;
        ˎˎ();
        break;
      case 22: 
        label141:
        label164:
        if (paramInt2 == -1) {
          break label3;
        }
      }
    }
  }
  
  public void onCancelClick(View paramView)
  {
    break label315;
    int i = 0;
    for (;;)
    {
      label8:
      String str2;
      try
      {
        i = ˈ + 53;
        ʾ = i % 128;
        if (i % 2 != 0) {
          break label8;
        }
        String str1;
        switch (i)
        {
        default: 
          break label318;
          str2 = getString(LV.If.cancel_reason);
          if (!str2.startsWith(ˋ(new char[] { 2833, 15866, 8406, 6102, 6822 }).intern()))
          {
            continue;
            paramView = str2;
            switch (i)
            {
            default: 
              paramView = str2;
              continue;
              str1 = getString(LV.If.cancel_transaction);
              if (!str1.startsWith(ˋ(new char[] { 2833, 15866, 8406, 6102, 6822 }).intern())) {
                continue;
              }
              str1 = ˎ(str1.substring(4)).intern();
              continue;
              i = 1;
              continue;
            }
          }
          break;
        case 1: 
          paramView = ˎ(str2.substring(4)).intern();
          i = 47 / 0;
          continue;
          i = 0;
          continue;
          i = 1;
          continue;
          new KK(this, str1, paramView).ˏ();
          return;
        }
      }
      catch (Exception paramView)
      {
        try
        {
          i = ʾ;
          i += 111;
          ˈ = i % 128;
          if (i % 2 == 0) {
            continue;
          }
        }
        catch (Exception paramView)
        {
          throw paramView;
        }
        paramView = paramView;
        throw paramView;
      }
      label315:
      continue;
      label318:
      paramView = ˎ(str2.substring(4)).intern();
    }
  }
  
  /* Error */
  public void onConfirmationClick(View paramView)
  {
    // Byte code:
    //   0: goto +136 -> 136
    //   3: iload_2
    //   4: tableswitch	default:+24->28, 0:+172->176, 1:+167->171
    //   28: goto +148 -> 176
    //   31: astore_1
    //   32: aload_1
    //   33: athrow
    //   34: getstatic 26	o/Ma:ˈ	I
    //   37: bipush 77
    //   39: iadd
    //   40: istore_2
    //   41: iload_2
    //   42: sipush 128
    //   45: irem
    //   46: putstatic 24	o/Ma:ʾ	I
    //   49: iload_2
    //   50: iconst_2
    //   51: irem
    //   52: ifeq +6 -> 58
    //   55: goto +122 -> 177
    //   58: aload_0
    //   59: invokevirtual 222	o/Ma:ˊˊ	()Z
    //   62: istore_3
    //   63: iload_3
    //   64: ifeq +6 -> 70
    //   67: goto +98 -> 165
    //   70: goto +86 -> 156
    //   73: iconst_0
    //   74: istore_2
    //   75: goto -72 -> 3
    //   78: iload_2
    //   79: lookupswitch	default:+25->104, 30:+60->139, 76:+67->146
    //   104: goto +42 -> 146
    //   107: getstatic 24	o/Ma:ʾ	I
    //   110: istore_2
    //   111: iload_2
    //   112: bipush 115
    //   114: iadd
    //   115: istore_2
    //   116: iload_2
    //   117: sipush 128
    //   120: irem
    //   121: putstatic 26	o/Ma:ˈ	I
    //   124: iload_2
    //   125: iconst_2
    //   126: irem
    //   127: ifne +6 -> 133
    //   130: goto +21 -> 151
    //   133: goto -60 -> 73
    //   136: goto -102 -> 34
    //   139: aload_0
    //   140: invokespecial 641	o/Ma:ˍ	()V
    //   143: goto -36 -> 107
    //   146: aload_0
    //   147: invokespecial 643	o/Ma:ˋˋ	()V
    //   150: return
    //   151: iconst_1
    //   152: istore_2
    //   153: goto -150 -> 3
    //   156: bipush 76
    //   158: istore_2
    //   159: goto -81 -> 78
    //   162: astore_1
    //   163: aload_1
    //   164: athrow
    //   165: bipush 30
    //   167: istore_2
    //   168: goto -90 -> 78
    //   171: iconst_5
    //   172: iconst_2
    //   173: idiv
    //   174: istore_2
    //   175: return
    //   176: return
    //   177: goto -119 -> 58
    // Local variable table:
    //   start	length	slot	name	signature
    //   0	180	0	this	Ma
    //   0	180	1	paramView	View
    //   3	172	2	i	int
    //   62	2	3	bool	boolean
    // Exception table:
    //   from	to	target	type
    //   107	111	31	java/lang/Exception
    //   116	124	31	java/lang/Exception
    //   58	63	162	java/lang/Exception
  }
  
  public void onCreate(Bundle paramBundle)
  {
    break label424;
    int i = 0;
    break label11;
    label8:
    break label386;
    switch (i)
    {
    default: 
      label11:
      return;
    }
    try
    {
      i = ˈ + 113;
      ʾ = i % 128;
      if (i % 2 != 0) {
        break label690;
      }
    }
    catch (Exception paramBundle)
    {
      throw paramBundle;
    }
    return;
    for (;;)
    {
      switch (i)
      {
      default: 
        break;
      case 1: 
        label68:
        label386:
        label424:
        for (;;)
        {
          i = ˈ + 59;
          ʾ = i % 128;
          if (i % 2 != 0) {
            break label8;
          }
          break label386;
          i = 1;
          break label68;
          ˎ((Is)getIntent().getParcelableExtra(ˋ(new char[] { -20697, -26196, 26840, 15343, -30208, 23884, 11355, -878, 20409, 7903, -7923, -20422, 869, -11679, -23874, 30150, -15120, -26870, 26166, -13970, -26224, 26754, 15314, -30208, 23860, 11340, -185, 20375, 7887, -7695, -20451, 830, -11678, -23910 }).intern()));
          break label427;
          super.onCreate(paramBundle);
          ˊ(((Mn)this.ॱˊ).ʼ);
          ˌ();
          if (!ˊˊ()) {
            break;
          }
          i = 1;
          break label11;
        }
      }
      for (;;)
      {
        label427:
        return;
        ˎ((Is)getIntent().getParcelableExtra(ˋ(new char[] { -20697, -26196, 26840, 15343, -30208, 23884, 11355, -878, 20409, 7903, -7923, -20422, 869, -11679, -23874, 30150, -15120, -26870, 26166, -13970, -26224, 26754, 15314, -30208, 23860, 11340, -185, 20375, 7887, -7695, -20451, 830, -11678, -23910 }).intern()));
        i = null.length;
      }
      label690:
      i = 0;
    }
  }
  
  /* Error */
  protected void ʻॱ()
  {
    // Byte code:
    //   0: goto +407 -> 407
    //   3: getstatic 26	o/Ma:ˈ	I
    //   6: bipush 31
    //   8: iadd
    //   9: istore_1
    //   10: iload_1
    //   11: sipush 128
    //   14: irem
    //   15: putstatic 24	o/Ma:ʾ	I
    //   18: iload_1
    //   19: iconst_2
    //   20: irem
    //   21: ifeq +6 -> 27
    //   24: goto +348 -> 372
    //   27: goto +12 -> 39
    //   30: bipush 22
    //   32: istore_1
    //   33: goto +57 -> 90
    //   36: astore_2
    //   37: aload_2
    //   38: athrow
    //   39: aload_0
    //   40: getfield 43	o/Ma:ॱˊ	Landroid/databinding/ViewDataBinding;
    //   43: checkcast 45	o/Mn
    //   46: invokevirtual 219	o/Mn:ˊॱ	()Lo/Is;
    //   49: astore_2
    //   50: aload_2
    //   51: getfield 228	o/Is:selectedCard	Lcom/insidesecure/hce/MatrixHCECard;
    //   54: ifnull +6 -> 60
    //   57: goto +344 -> 401
    //   60: goto -30 -> 30
    //   63: getstatic 26	o/Ma:ˈ	I
    //   66: istore_1
    //   67: iload_1
    //   68: bipush 27
    //   70: iadd
    //   71: istore_1
    //   72: iload_1
    //   73: sipush 128
    //   76: irem
    //   77: putstatic 24	o/Ma:ʾ	I
    //   80: iload_1
    //   81: iconst_2
    //   82: irem
    //   83: ifeq +6 -> 89
    //   86: goto +285 -> 371
    //   89: return
    //   90: iload_1
    //   91: lookupswitch	default:+25->116, 22:+34->125, 25:+75->166
    //   116: goto +9 -> 125
    //   119: bipush 15
    //   121: istore_1
    //   122: goto +13 -> 135
    //   125: aload_0
    //   126: invokespecial 417	o/Ma:ˊᐝ	()V
    //   129: goto -66 -> 63
    //   132: bipush 6
    //   134: istore_1
    //   135: aload_3
    //   136: astore_2
    //   137: iload_1
    //   138: lookupswitch	default:+26->164, 6:+-13->125, 15:+28->166
    //   164: aload_3
    //   165: astore_2
    //   166: aload_2
    //   167: getfield 228	o/Is:selectedCard	Lcom/insidesecure/hce/MatrixHCECard;
    //   170: astore_2
    //   171: aload_2
    //   172: invokeinterface 673 1 0
    //   177: astore_3
    //   178: aload_0
    //   179: getfield 43	o/Ma:ॱˊ	Landroid/databinding/ViewDataBinding;
    //   182: checkcast 45	o/Mn
    //   185: invokevirtual 219	o/Mn:ˊॱ	()Lo/Is;
    //   188: astore_2
    //   189: goto +17 -> 206
    //   192: astore_2
    //   193: aload_2
    //   194: invokevirtual 140	java/lang/Throwable:getCause	()Ljava/lang/Throwable;
    //   197: astore_3
    //   198: aload_3
    //   199: ifnull +5 -> 204
    //   202: aload_3
    //   203: athrow
    //   204: aload_2
    //   205: athrow
    //   206: aload_0
    //   207: invokevirtual 160	android/content/Context:getPackageName	()Ljava/lang/String;
    //   210: invokevirtual 555	java/lang/String:length	()I
    //   213: bipush 7
    //   215: isub
    //   216: aload_0
    //   217: invokevirtual 160	android/content/Context:getPackageName	()Ljava/lang/String;
    //   220: invokevirtual 555	java/lang/String:length	()I
    //   223: sipush 256
    //   226: iadd
    //   227: aload_0
    //   228: invokevirtual 164	android/content/Context:getApplicationInfo	()Landroid/content/pm/ApplicationInfo;
    //   231: getfield 169	android/content/pm/ApplicationInfo:targetSdkVersion	I
    //   234: sipush 14763
    //   237: iadd
    //   238: i2c
    //   239: invokestatic 174	o/O:ˋ	(IIC)Ljava/lang/Object;
    //   242: checkcast 176	java/lang/Class
    //   245: ldc -79
    //   247: aconst_null
    //   248: invokevirtual 181	java/lang/Class:getMethod	(Ljava/lang/String;[Ljava/lang/Class;)Ljava/lang/reflect/Method;
    //   251: aconst_null
    //   252: aconst_null
    //   253: invokevirtual 187	java/lang/reflect/Method:invoke	(Ljava/lang/Object;[Ljava/lang/Object;)Ljava/lang/Object;
    //   256: astore 4
    //   258: goto +17 -> 275
    //   261: astore_2
    //   262: aload_2
    //   263: invokevirtual 140	java/lang/Throwable:getCause	()Ljava/lang/Throwable;
    //   266: astore_3
    //   267: aload_3
    //   268: ifnull +5 -> 273
    //   271: aload_3
    //   272: athrow
    //   273: aload_2
    //   274: athrow
    //   275: aload_0
    //   276: invokevirtual 146	android/content/Context:getResources	()Landroid/content/res/Resources;
    //   279: ldc_w 674
    //   282: invokevirtual 150	android/content/res/Resources:getString	(I)Ljava/lang/String;
    //   285: iconst_0
    //   286: iconst_4
    //   287: invokevirtual 153	java/lang/String:substring	(II)Ljava/lang/String;
    //   290: iconst_3
    //   291: invokevirtual 157	java/lang/String:codePointAt	(I)I
    //   294: bipush 8
    //   296: isub
    //   297: aload_0
    //   298: invokevirtual 160	android/content/Context:getPackageName	()Ljava/lang/String;
    //   301: bipush 6
    //   303: invokevirtual 157	java/lang/String:codePointAt	(I)I
    //   306: sipush 159
    //   309: iadd
    //   310: aload_0
    //   311: invokevirtual 164	android/content/Context:getApplicationInfo	()Landroid/content/pm/ApplicationInfo;
    //   314: getfield 169	android/content/pm/ApplicationInfo:targetSdkVersion	I
    //   317: sipush 14763
    //   320: iadd
    //   321: i2c
    //   322: invokestatic 174	o/O:ˋ	(IIC)Ljava/lang/Object;
    //   325: checkcast 176	java/lang/Class
    //   328: ldc_w 675
    //   331: iconst_1
    //   332: anewarray 176	java/lang/Class
    //   335: dup
    //   336: iconst_0
    //   337: ldc 76
    //   339: aastore
    //   340: invokevirtual 181	java/lang/Class:getMethod	(Ljava/lang/String;[Ljava/lang/Class;)Ljava/lang/reflect/Method;
    //   343: aload 4
    //   345: iconst_1
    //   346: anewarray 677	java/lang/Object
    //   349: dup
    //   350: iconst_0
    //   351: aload_3
    //   352: aastore
    //   353: invokevirtual 187	java/lang/reflect/Method:invoke	(Ljava/lang/Object;[Ljava/lang/Object;)Ljava/lang/Object;
    //   356: checkcast 670	com/insidesecure/hce/MatrixHCECard
    //   359: astore_3
    //   360: aload_2
    //   361: aload_3
    //   362: putfield 228	o/Is:selectedCard	Lcom/insidesecure/hce/MatrixHCECard;
    //   365: goto -240 -> 125
    //   368: astore_2
    //   369: aload_2
    //   370: athrow
    //   371: return
    //   372: aload_0
    //   373: getfield 43	o/Ma:ॱˊ	Landroid/databinding/ViewDataBinding;
    //   376: checkcast 45	o/Mn
    //   379: invokevirtual 219	o/Mn:ˊॱ	()Lo/Is;
    //   382: astore_3
    //   383: aload_3
    //   384: getfield 228	o/Is:selectedCard	Lcom/insidesecure/hce/MatrixHCECard;
    //   387: astore_2
    //   388: aconst_null
    //   389: arraylength
    //   390: istore_1
    //   391: aload_2
    //   392: ifnull +6 -> 398
    //   395: goto -276 -> 119
    //   398: goto -266 -> 132
    //   401: bipush 25
    //   403: istore_1
    //   404: goto -314 -> 90
    //   407: goto -404 -> 3
    // Local variable table:
    //   start	length	slot	name	signature
    //   0	410	0	this	Ma
    //   9	395	1	i	int
    //   36	2	2	localException1	Exception
    //   49	140	2	localObject1	Object
    //   192	13	2	localObject2	Object
    //   261	100	2	localObject3	Object
    //   368	2	2	localException2	Exception
    //   387	5	2	localMatrixHCECard	com.insidesecure.hce.MatrixHCECard
    //   135	249	3	localObject4	Object
    //   256	88	4	localObject5	Object
    // Exception table:
    //   from	to	target	type
    //   166	171	36	java/lang/Exception
    //   171	178	36	java/lang/Exception
    //   178	189	36	java/lang/Exception
    //   193	198	36	java/lang/Exception
    //   202	204	36	java/lang/Exception
    //   204	206	36	java/lang/Exception
    //   262	267	36	java/lang/Exception
    //   271	273	36	java/lang/Exception
    //   273	275	36	java/lang/Exception
    //   360	365	36	java/lang/Exception
    //   206	258	192	finally
    //   275	360	261	finally
    //   63	67	368	java/lang/Exception
    //   72	80	368	java/lang/Exception
  }
  
  /* Error */
  public void ˋ(ز paramز)
  {
    // Byte code:
    //   0: goto +78 -> 78
    //   3: iconst_0
    //   4: istore_2
    //   5: goto +80 -> 85
    //   8: astore_1
    //   9: aload_1
    //   10: athrow
    //   11: iconst_1
    //   12: istore_2
    //   13: goto +72 -> 85
    //   16: new 123	java/lang/NullPointerException
    //   19: dup
    //   20: invokespecial 124	java/lang/NullPointerException:<init>	()V
    //   23: athrow
    //   24: getstatic 26	o/Ma:ˈ	I
    //   27: bipush 99
    //   29: iadd
    //   30: istore_2
    //   31: iload_2
    //   32: sipush 128
    //   35: irem
    //   36: putstatic 24	o/Ma:ʾ	I
    //   39: iload_2
    //   40: iconst_2
    //   41: irem
    //   42: ifeq +6 -> 48
    //   45: goto +37 -> 82
    //   48: goto +63 -> 111
    //   51: getstatic 24	o/Ma:ʾ	I
    //   54: bipush 67
    //   56: iadd
    //   57: istore_2
    //   58: iload_2
    //   59: sipush 128
    //   62: irem
    //   63: putstatic 26	o/Ma:ˈ	I
    //   66: iload_2
    //   67: iconst_2
    //   68: irem
    //   69: ifne +6 -> 75
    //   72: goto -61 -> 11
    //   75: goto -72 -> 3
    //   78: goto -54 -> 24
    //   81: return
    //   82: goto +29 -> 111
    //   85: iload_2
    //   86: tableswitch	default:+22->108, 0:+-5->81, 1:+-70->16
    //   108: goto -92 -> 16
    //   111: aload_0
    //   112: aload_1
    //   113: invokespecial 680	o/Mg:ˋ	(Lo/ز;)V
    //   116: aload_1
    //   117: iconst_1
    //   118: invokevirtual 683	o/ز:ॱ	(Z)V
    //   121: aload_1
    //   122: iconst_1
    //   123: invokevirtual 685	o/ز:ˏ	(Z)V
    //   126: goto -75 -> 51
    //   129: astore_1
    //   130: aload_1
    //   131: athrow
    // Local variable table:
    //   start	length	slot	name	signature
    //   0	132	0	this	Ma
    //   0	132	1	paramز	ز
    //   4	82	2	i	int
    // Exception table:
    //   from	to	target	type
    //   116	121	8	java/lang/Exception
    //   121	126	129	java/lang/Exception
  }
  
  public int ˎ()
  {
    break label65;
    int i = ʾ + 97;
    ˈ = i % 128;
    int j;
    label29:
    if (i % 2 != 0) {
      return j;
    }
    label65:
    for (;;)
    {
      i = ˈ + 103;
      ʾ = i % 128;
      if (i % 2 != 0) {
        break label29;
      }
      j = LV.iF.activity_confirm_request_money;
      break;
      return j;
    }
  }
  
  @zA(ˎ=ThreadMode.MAIN)
  public void ˎ(Ef paramEf)
  {
    for (;;)
    {
      ˏ(paramEf.ˊ());
      int i = ˈ + 53;
      ʾ = i % 128;
      if (i % 2 == 0) {
        return;
      }
      do
      {
        break;
        return;
        i = ʾ + 63;
        ˈ = i % 128;
      } while (i % 2 == 0);
    }
  }
  
  protected void ˎ(FW paramFW, FS paramFS)
  {
    break label47;
    int i = ʾ + 41;
    ˈ = i % 128;
    if (i % 2 == 0) {
      return;
    }
    return;
    label47:
    for (;;)
    {
      ˎ(new Is(paramFW, paramFS, ˏ(paramFW)));
      break;
    }
  }
}
