package o;

import android.content.Context;
import android.content.Intent;
import android.content.res.Resources;
import android.graphics.drawable.Drawable;
import android.os.Bundle;
import android.text.TextUtils;
import android.util.Pair;
import android.view.View;
import android.widget.TextView;
import java.io.UnsupportedEncodingException;
import java.math.BigDecimal;

public class Mb
  extends LZ<Mu>
{
  private static int ˉ;
  private static int ˊˋ;
  private static byte ˊᐝ = -102;
  private static int[] ˋˊ;
  
  /* Error */
  static
  {
    // Byte code:
    //   0: goto +78 -> 78
    //   3: iconst_1
    //   4: istore_0
    //   5: goto +6 -> 11
    //   8: astore_1
    //   9: aload_1
    //   10: athrow
    //   11: iload_0
    //   12: tableswitch	default:+24->36, 0:+55->67, 1:+24->36
    //   36: return
    //   37: astore_1
    //   38: aload_1
    //   39: athrow
    //   40: getstatic 20	o/Mb:ˉ	I
    //   43: bipush 63
    //   45: iadd
    //   46: istore_0
    //   47: iload_0
    //   48: sipush 128
    //   51: irem
    //   52: putstatic 22	o/Mb:ˊˋ	I
    //   55: iload_0
    //   56: iconst_2
    //   57: irem
    //   58: ifeq +6 -> 64
    //   61: goto +12 -> 73
    //   64: goto -61 -> 3
    //   67: bipush 77
    //   69: iconst_0
    //   70: idiv
    //   71: istore_0
    //   72: return
    //   73: iconst_0
    //   74: istore_0
    //   75: goto -64 -> 11
    //   78: iconst_0
    //   79: putstatic 22	o/Mb:ˊˋ	I
    //   82: iconst_1
    //   83: putstatic 20	o/Mb:ˉ	I
    //   86: invokestatic 24	o/Mb:ˉ	()V
    //   89: bipush -102
    //   91: putstatic 26	o/Mb:ˊᐝ	B
    //   94: goto -54 -> 40
    // Local variable table:
    //   start	length	slot	name	signature
    //   4	71	0	i	int
    //   8	2	1	localException1	Exception
    //   37	2	1	localException2	Exception
    // Exception table:
    //   from	to	target	type
    //   82	86	8	java/lang/Exception
    //   78	82	37	java/lang/Exception
    //   82	86	37	java/lang/Exception
    //   86	89	37	java/lang/Exception
    //   89	94	37	java/lang/Exception
  }
  
  public Mb() {}
  
  static void ˉ()
  {
    ˋˊ = new int[] { -2059592219, -1524226678, 537228124, -1174244381, -1904118092, -1961308499, -1723030417, -1803589825, -1514188193, -1180411569, -241978891, -498994538, -1600143392, 112576845, -496236785, -2104511711, -1738190174, -2035698292 };
  }
  
  private void ˋˋ()
  {
    break label80;
    for (;;)
    {
      i = 1;
      break label94;
      try
      {
        i = ˊˋ;
        i += 109;
        ˉ = i % 128;
        if (i % 2 == 0) {
          break label159;
        }
      }
      catch (Exception localException)
      {
        throw localException;
      }
      if (ˊˊ()) {
        break;
      }
    }
    label50:
    int i = ˉ + 89;
    ˊˋ = i % 128;
    if (i % 2 == 0)
    {
      return;
      i = 0;
      break label94;
      label80:
      break label132;
    }
    else
    {
      return;
    }
    for (;;)
    {
      ˑ();
      break;
      label94:
      switch (i)
      {
      }
    }
    label132:
    label159:
    for (;;)
    {
      ˎˎ();
      do
      {
        break;
        break label50;
        i = ˉ + 95;
        ˊˋ = i % 128;
      } while (i % 2 != 0);
      break;
    }
  }
  
  /* Error */
  private void ˋᐝ()
  {
    // Byte code:
    //   0: goto +58 -> 58
    //   3: astore_2
    //   4: aload_2
    //   5: athrow
    //   6: astore_2
    //   7: aload_2
    //   8: athrow
    //   9: aload_0
    //   10: getfield 66	o/Mb:ॱˊ	Landroid/databinding/ViewDataBinding;
    //   13: astore_2
    //   14: aload_2
    //   15: checkcast 68	o/Mu
    //   18: astore_2
    //   19: aload_0
    //   20: getfield 71	o/Mb:ˊˊ	Lo/coN;
    //   23: astore_3
    //   24: aload_2
    //   25: aload_3
    //   26: invokevirtual 75	o/Mu:ˋ	(Lo/coN;)V
    //   29: aload_0
    //   30: getfield 66	o/Mb:ॱˊ	Landroid/databinding/ViewDataBinding;
    //   33: checkcast 68	o/Mu
    //   36: getfield 78	o/Mu:ॱˊ	Landroid/widget/ProgressBar;
    //   39: invokevirtual 84	android/widget/ProgressBar:getIndeterminateDrawable	()Landroid/graphics/drawable/Drawable;
    //   42: aload_0
    //   43: getstatic 89	o/LV$ˊ:romanian_yellow	I
    //   46: invokestatic 95	o/ᔆ:ˊ	(Landroid/content/Context;I)I
    //   49: getstatic 101	android/graphics/PorterDuff$Mode:SRC_IN	Landroid/graphics/PorterDuff$Mode;
    //   52: invokevirtual 107	android/graphics/drawable/Drawable:setColorFilter	(ILandroid/graphics/PorterDuff$Mode;)V
    //   55: goto +29 -> 84
    //   58: getstatic 20	o/Mb:ˉ	I
    //   61: iconst_3
    //   62: iadd
    //   63: istore_1
    //   64: iload_1
    //   65: sipush 128
    //   68: irem
    //   69: putstatic 22	o/Mb:ˊˋ	I
    //   72: iload_1
    //   73: iconst_2
    //   74: irem
    //   75: ifeq +6 -> 81
    //   78: goto +32 -> 110
    //   81: goto -72 -> 9
    //   84: getstatic 20	o/Mb:ˉ	I
    //   87: bipush 49
    //   89: iadd
    //   90: istore_1
    //   91: iload_1
    //   92: sipush 128
    //   95: irem
    //   96: putstatic 22	o/Mb:ˊˋ	I
    //   99: iload_1
    //   100: iconst_2
    //   101: irem
    //   102: ifeq +6 -> 108
    //   105: goto +4 -> 109
    //   108: return
    //   109: return
    //   110: goto -101 -> 9
    // Local variable table:
    //   start	length	slot	name	signature
    //   0	113	0	this	Mb
    //   63	39	1	i	int
    //   3	2	2	localException1	Exception
    //   6	2	2	localException2	Exception
    //   13	12	2	localObject	Object
    //   23	3	3	localCoN	coN
    // Exception table:
    //   from	to	target	type
    //   14	19	3	java/lang/Exception
    //   9	14	6	java/lang/Exception
    //   14	19	6	java/lang/Exception
    //   19	24	6	java/lang/Exception
    //   24	29	6	java/lang/Exception
    //   29	55	6	java/lang/Exception
  }
  
  /* Error */
  private void ˌ()
  {
    // Byte code:
    //   0: goto +36 -> 36
    //   3: iconst_2
    //   4: iconst_0
    //   5: idiv
    //   6: istore_1
    //   7: return
    //   8: getstatic 22	o/Mb:ˊˋ	I
    //   11: bipush 27
    //   13: iadd
    //   14: istore_1
    //   15: iload_1
    //   16: sipush 128
    //   19: irem
    //   20: putstatic 20	o/Mb:ˉ	I
    //   23: iload_1
    //   24: iconst_2
    //   25: irem
    //   26: ifne +6 -> 32
    //   29: goto +301 -> 330
    //   32: goto +325 -> 357
    //   35: return
    //   36: new 110	o/FZ
    //   39: dup
    //   40: invokespecial 111	o/FZ:<init>	()V
    //   43: astore_2
    //   44: getstatic 117	o/Gv:ॱ	Lo/Gv;
    //   47: invokevirtual 121	o/Gv:ˏॱ	()Ljava/lang/String;
    //   50: astore_3
    //   51: aload_0
    //   52: getfield 66	o/Mb:ॱˊ	Landroid/databinding/ViewDataBinding;
    //   55: checkcast 68	o/Mu
    //   58: getfield 125	o/Mu:ᐝ	Lo/ME;
    //   61: invokevirtual 131	o/ME:ˏ	()Lo/HQ;
    //   64: invokevirtual 136	o/HQ:ॱॱ	()Ljava/lang/String;
    //   67: astore 4
    //   69: aload_0
    //   70: getfield 66	o/Mb:ॱˊ	Landroid/databinding/ViewDataBinding;
    //   73: checkcast 68	o/Mu
    //   76: getfield 139	o/Mu:ˋॱ	Lo/ME;
    //   79: invokevirtual 131	o/ME:ˏ	()Lo/HQ;
    //   82: invokevirtual 136	o/HQ:ॱॱ	()Ljava/lang/String;
    //   85: astore 5
    //   87: aload_2
    //   88: aload 4
    //   90: putfield 143	o/FZ:initiatorCardInstanceUuid	Ljava/lang/String;
    //   93: aload_2
    //   94: aload_3
    //   95: putfield 146	o/FZ:initiatorWalletAppInstanceId	Ljava/lang/String;
    //   98: aload_2
    //   99: aload 5
    //   101: putfield 149	o/FZ:accepterCardInstanceUuid	Ljava/lang/String;
    //   104: aload_2
    //   105: aload_3
    //   106: putfield 152	o/FZ:accepterWalletAppInstanceId	Ljava/lang/String;
    //   109: aload_2
    //   110: aload_0
    //   111: getfield 156	o/Mb:ʽॱ	Lo/Gh;
    //   114: getfield 162	o/Gh:currency	Lo/Ep;
    //   117: putfield 163	o/FZ:currency	Lo/Ep;
    //   120: aload_2
    //   121: new 165	java/math/BigDecimal
    //   124: dup
    //   125: aload_0
    //   126: getfield 156	o/Mb:ʽॱ	Lo/Gh;
    //   129: getfield 169	o/Gh:amount	Lo/ـ;
    //   132: invokevirtual 174	o/ـ:ˏ	()Ljava/lang/Object;
    //   135: checkcast 176	java/lang/String
    //   138: invokespecial 179	java/math/BigDecimal:<init>	(Ljava/lang/String;)V
    //   141: putfield 182	o/FZ:amount	Ljava/math/BigDecimal;
    //   144: aload_2
    //   145: new 165	java/math/BigDecimal
    //   148: dup
    //   149: aload_0
    //   150: getfield 156	o/Mb:ʽॱ	Lo/Gh;
    //   153: getfield 186	o/Gh:commission	Lo/cON;
    //   156: invokevirtual 191	o/cON:ˏ	()D
    //   159: invokespecial 194	java/math/BigDecimal:<init>	(D)V
    //   162: putfield 197	o/FZ:fee	Ljava/math/BigDecimal;
    //   165: aload_2
    //   166: getstatic 203	o/FU:INBOUND	Lo/FU;
    //   169: putfield 206	o/FZ:type	Lo/FU;
    //   172: aload_2
    //   173: getstatic 212	o/Eq:SMS	Lo/Eq;
    //   176: putfield 215	o/FZ:channel	Lo/Eq;
    //   179: aload_2
    //   180: getstatic 221	o/FT:SEND_MONEY	Lo/FT;
    //   183: putfield 224	o/FZ:scope	Lo/FT;
    //   186: aload_2
    //   187: aload_0
    //   188: getfield 156	o/Mb:ʽॱ	Lo/Gh;
    //   191: getfield 227	o/Gh:transferDetail	Lo/ـ;
    //   194: invokevirtual 174	o/ـ:ˏ	()Ljava/lang/Object;
    //   197: checkcast 176	java/lang/String
    //   200: putfield 230	o/FZ:initiatorMessage	Ljava/lang/String;
    //   203: aload_0
    //   204: getfield 71	o/Mb:ˊˊ	Lo/coN;
    //   207: iconst_1
    //   208: invokevirtual 235	o/coN:ˋ	(Z)V
    //   211: goto +17 -> 228
    //   214: astore_2
    //   215: aload_2
    //   216: invokevirtual 241	java/lang/Throwable:getCause	()Ljava/lang/Throwable;
    //   219: astore_3
    //   220: aload_3
    //   221: ifnull +5 -> 226
    //   224: aload_3
    //   225: athrow
    //   226: aload_2
    //   227: athrow
    //   228: aload_0
    //   229: invokevirtual 247	android/content/Context:getResources	()Landroid/content/res/Resources;
    //   232: ldc -8
    //   234: invokevirtual 254	android/content/res/Resources:getString	(I)Ljava/lang/String;
    //   237: iconst_0
    //   238: iconst_5
    //   239: invokevirtual 258	java/lang/String:substring	(II)Ljava/lang/String;
    //   242: iconst_0
    //   243: invokevirtual 262	java/lang/String:codePointAt	(I)I
    //   246: iconst_1
    //   247: isub
    //   248: aload_0
    //   249: invokevirtual 265	android/content/Context:getPackageName	()Ljava/lang/String;
    //   252: bipush 6
    //   254: invokevirtual 262	java/lang/String:codePointAt	(I)I
    //   257: bipush 27
    //   259: iadd
    //   260: aload_0
    //   261: invokevirtual 247	android/content/Context:getResources	()Landroid/content/res/Resources;
    //   264: ldc_w 266
    //   267: invokevirtual 254	android/content/res/Resources:getString	(I)Ljava/lang/String;
    //   270: iconst_0
    //   271: iconst_5
    //   272: invokevirtual 258	java/lang/String:substring	(II)Ljava/lang/String;
    //   275: iconst_3
    //   276: invokevirtual 262	java/lang/String:codePointAt	(I)I
    //   279: ldc_w 267
    //   282: iadd
    //   283: i2c
    //   284: invokestatic 272	o/O:ˋ	(IIC)Ljava/lang/Object;
    //   287: checkcast 274	java/lang/Class
    //   290: ldc_w 275
    //   293: aconst_null
    //   294: invokevirtual 279	java/lang/Class:getMethod	(Ljava/lang/String;[Ljava/lang/Class;)Ljava/lang/reflect/Method;
    //   297: aconst_null
    //   298: aconst_null
    //   299: invokevirtual 285	java/lang/reflect/Method:invoke	(Ljava/lang/Object;[Ljava/lang/Object;)Ljava/lang/Object;
    //   302: checkcast 287	o/It
    //   305: astore_3
    //   306: aload_3
    //   307: aload_2
    //   308: invokeinterface 291 2 0
    //   313: new 7	o/Mb$2
    //   316: dup
    //   317: aload_0
    //   318: aload_0
    //   319: invokespecial 294	o/Mb$2:<init>	(Lo/Mb;Landroid/content/Context;)V
    //   322: invokeinterface 299 2 0
    //   327: goto -319 -> 8
    //   330: iconst_1
    //   331: istore_1
    //   332: iload_1
    //   333: tableswitch	default:+23->356, 0:+-298->35, 1:+-330->3
    //   356: return
    //   357: iconst_0
    //   358: istore_1
    //   359: goto -27 -> 332
    // Local variable table:
    //   start	length	slot	name	signature
    //   0	362	0	this	Mb
    //   6	353	1	i	int
    //   43	144	2	localFZ1	FZ
    //   214	94	2	localFZ2	FZ
    //   50	257	3	localObject	Object
    //   67	22	4	str1	String
    //   85	15	5	str2	String
    // Exception table:
    //   from	to	target	type
    //   228	306	214	finally
  }
  
  private void ˍ()
  {
    break label131;
    int i = ˉ + 27;
    ˊˋ = i % 128;
    if (i % 2 == 0) {}
    for (;;)
    {
      ((Mu)this.ॱˊ).ˊ(this.ʾ);
      ((Mu)this.ॱˊ).ˏ(this.ʼॱ);
      ˏˏ();
      ˎˏ();
      ((Mu)this.ॱˊ).ˊ(this.ʽॱ);
      ((Mu)this.ॱˊ).ˊ(true);
      ((Mu)this.ॱˊ).ॱ(TextUtils.isEmpty(this.ʿ));
      i = ˉ + 45;
      ˊˋ = i % 128;
      if (i % 2 != 0) {
        return;
      }
      return;
      label131:
      break;
    }
  }
  
  /* Error */
  private void ˎˎ()
  {
    // Byte code:
    //   0: goto +88 -> 88
    //   3: getstatic 20	o/Mb:ˉ	I
    //   6: bipush 111
    //   8: iadd
    //   9: istore_1
    //   10: iload_1
    //   11: sipush 128
    //   14: irem
    //   15: putstatic 22	o/Mb:ˊˋ	I
    //   18: iload_1
    //   19: iconst_2
    //   20: irem
    //   21: ifeq +6 -> 27
    //   24: goto +15 -> 39
    //   27: goto +6 -> 33
    //   30: astore_2
    //   31: aload_2
    //   32: athrow
    //   33: bipush 96
    //   35: istore_1
    //   36: goto +20 -> 56
    //   39: bipush 57
    //   41: istore_1
    //   42: goto +14 -> 56
    //   45: astore_2
    //   46: aload_2
    //   47: athrow
    //   48: new 337	java/lang/NullPointerException
    //   51: dup
    //   52: invokespecial 338	java/lang/NullPointerException:<init>	()V
    //   55: athrow
    //   56: iload_1
    //   57: lookupswitch	default:+27->84, 57:+-9->48, 96:+30->87
    //   84: goto -36 -> 48
    //   87: return
    //   88: new 340	android/os/Bundle
    //   91: dup
    //   92: invokespecial 341	android/os/Bundle:<init>	()V
    //   95: astore_2
    //   96: aload_0
    //   97: invokevirtual 247	android/content/Context:getResources	()Landroid/content/res/Resources;
    //   100: astore_3
    //   101: aload_3
    //   102: ldc_w 342
    //   105: invokevirtual 254	android/content/res/Resources:getString	(I)Ljava/lang/String;
    //   108: astore_3
    //   109: aload_3
    //   110: iconst_0
    //   111: iconst_4
    //   112: invokevirtual 258	java/lang/String:substring	(II)Ljava/lang/String;
    //   115: astore_3
    //   116: aload_3
    //   117: invokevirtual 346	java/lang/String:length	()I
    //   120: istore_1
    //   121: aload_2
    //   122: bipush 12
    //   124: newarray int
    //   126: dup
    //   127: iconst_0
    //   128: ldc_w 347
    //   131: iastore
    //   132: dup
    //   133: iconst_1
    //   134: ldc_w 348
    //   137: iastore
    //   138: dup
    //   139: iconst_2
    //   140: ldc_w 349
    //   143: iastore
    //   144: dup
    //   145: iconst_3
    //   146: ldc_w 350
    //   149: iastore
    //   150: dup
    //   151: iconst_4
    //   152: ldc_w 351
    //   155: iastore
    //   156: dup
    //   157: iconst_5
    //   158: ldc_w 352
    //   161: iastore
    //   162: dup
    //   163: bipush 6
    //   165: ldc_w 353
    //   168: iastore
    //   169: dup
    //   170: bipush 7
    //   172: ldc_w 354
    //   175: iastore
    //   176: dup
    //   177: bipush 8
    //   179: ldc_w 355
    //   182: iastore
    //   183: dup
    //   184: bipush 9
    //   186: ldc_w 356
    //   189: iastore
    //   190: dup
    //   191: bipush 10
    //   193: ldc_w 357
    //   196: iastore
    //   197: dup
    //   198: bipush 11
    //   200: ldc_w 358
    //   203: iastore
    //   204: iload_1
    //   205: bipush 18
    //   207: iadd
    //   208: invokestatic 361	o/Mb:ॱ	([II)Ljava/lang/String;
    //   211: invokevirtual 364	java/lang/String:intern	()Ljava/lang/String;
    //   214: aload_0
    //   215: getfield 156	o/Mb:ʽॱ	Lo/Gh;
    //   218: invokevirtual 368	android/os/Bundle:putParcelable	(Ljava/lang/String;Landroid/os/Parcelable;)V
    //   221: aload_0
    //   222: invokevirtual 265	android/content/Context:getPackageName	()Ljava/lang/String;
    //   225: invokevirtual 346	java/lang/String:length	()I
    //   228: istore_1
    //   229: aload_2
    //   230: bipush 14
    //   232: newarray int
    //   234: dup
    //   235: iconst_0
    //   236: ldc_w 347
    //   239: iastore
    //   240: dup
    //   241: iconst_1
    //   242: ldc_w 348
    //   245: iastore
    //   246: dup
    //   247: iconst_2
    //   248: ldc_w 369
    //   251: iastore
    //   252: dup
    //   253: iconst_3
    //   254: ldc_w 370
    //   257: iastore
    //   258: dup
    //   259: iconst_4
    //   260: ldc_w 371
    //   263: iastore
    //   264: dup
    //   265: iconst_5
    //   266: ldc_w 372
    //   269: iastore
    //   270: dup
    //   271: bipush 6
    //   273: ldc_w 373
    //   276: iastore
    //   277: dup
    //   278: bipush 7
    //   280: ldc_w 374
    //   283: iastore
    //   284: dup
    //   285: bipush 8
    //   287: ldc_w 375
    //   290: iastore
    //   291: dup
    //   292: bipush 9
    //   294: ldc_w 376
    //   297: iastore
    //   298: dup
    //   299: bipush 10
    //   301: ldc_w 377
    //   304: iastore
    //   305: dup
    //   306: bipush 11
    //   308: ldc_w 378
    //   311: iastore
    //   312: dup
    //   313: bipush 12
    //   315: ldc_w 379
    //   318: iastore
    //   319: dup
    //   320: bipush 13
    //   322: ldc_w 380
    //   325: iastore
    //   326: iload_1
    //   327: bipush 16
    //   329: iadd
    //   330: invokestatic 361	o/Mb:ॱ	([II)Ljava/lang/String;
    //   333: invokevirtual 364	java/lang/String:intern	()Ljava/lang/String;
    //   336: aload_0
    //   337: getfield 156	o/Mb:ʽॱ	Lo/Gh;
    //   340: getfield 383	o/Gh:fromCardUuid	Ljava/lang/String;
    //   343: invokevirtual 387	android/os/Bundle:putString	(Ljava/lang/String;Ljava/lang/String;)V
    //   346: aload_0
    //   347: invokestatic 392	o/Ic:ˏ	(Landroid/content/Context;)Lo/Ic;
    //   350: invokevirtual 395	o/Ic:ʼॱ	()Lo/j;
    //   353: aload_2
    //   354: invokevirtual 400	o/j:ˊ	(Landroid/os/Bundle;)Lo/j;
    //   357: invokevirtual 402	o/j:ˎ	()V
    //   360: goto -357 -> 3
    // Local variable table:
    //   start	length	slot	name	signature
    //   0	363	0	this	Mb
    //   9	321	1	i	int
    //   30	2	2	localException1	Exception
    //   45	2	2	localException2	Exception
    //   95	259	2	localBundle	Bundle
    //   100	17	3	localObject	Object
    // Exception table:
    //   from	to	target	type
    //   96	101	30	java/lang/Exception
    //   101	109	30	java/lang/Exception
    //   109	116	30	java/lang/Exception
    //   116	360	30	java/lang/Exception
    //   101	109	45	java/lang/Exception
  }
  
  private void ˎˏ()
  {
    for (;;)
    {
      int i = 69;
      break label125;
      label9:
      Pair localPair = ˎ(this.ʾ);
      ((Mu)this.ॱˊ).ʽ.setText((CharSequence)localPair.first);
      ((Mu)this.ॱˊ).ʽ.setCompoundDrawablesWithIntrinsicBounds((Drawable)localPair.second, null, null, null);
      try
      {
        i = ˊˋ + 39;
        try
        {
          ˉ = i % 128;
          if (i % 2 == 0) {
            break label122;
          }
        }
        catch (Exception localException1)
        {
          throw localException1;
        }
        i = ˊˋ + 57;
        ˉ = i % 128;
        if (i % 2 != 0)
        {
          break label9;
          return;
        }
      }
      catch (Exception localException2)
      {
        label122:
        label125:
        throw localException2;
      }
    }
    i = 64;
    switch (i)
    {
    }
    throw new NullPointerException();
  }
  
  /* Error */
  private void ˏˏ()
  {
    // Byte code:
    //   0: goto +95 -> 95
    //   3: goto +31 -> 34
    //   6: astore_2
    //   7: aload_2
    //   8: athrow
    //   9: getstatic 22	o/Mb:ˊˋ	I
    //   12: bipush 55
    //   14: iadd
    //   15: istore_1
    //   16: iload_1
    //   17: sipush 128
    //   20: irem
    //   21: putstatic 20	o/Mb:ˉ	I
    //   24: iload_1
    //   25: iconst_2
    //   26: irem
    //   27: ifne +6 -> 33
    //   30: goto +68 -> 98
    //   33: return
    //   34: aload_0
    //   35: getfield 310	o/Mb:ʼॱ	Lo/HQ;
    //   38: astore_2
    //   39: aload_0
    //   40: aload_2
    //   41: invokevirtual 405	o/Mb:ˎ	(Lo/HQ;)Landroid/util/Pair;
    //   44: astore_2
    //   45: aload_0
    //   46: getfield 66	o/Mb:ॱˊ	Landroid/databinding/ViewDataBinding;
    //   49: astore_3
    //   50: aload_3
    //   51: checkcast 68	o/Mu
    //   54: astore_3
    //   55: aload_3
    //   56: getfield 432	o/Mu:ˏॱ	Landroid/widget/TextView;
    //   59: aload_2
    //   60: getfield 415	android/util/Pair:first	Ljava/lang/Object;
    //   63: checkcast 417	java/lang/CharSequence
    //   66: invokevirtual 423	android/widget/TextView:setText	(Ljava/lang/CharSequence;)V
    //   69: aload_0
    //   70: getfield 66	o/Mb:ॱˊ	Landroid/databinding/ViewDataBinding;
    //   73: checkcast 68	o/Mu
    //   76: getfield 432	o/Mu:ˏॱ	Landroid/widget/TextView;
    //   79: aload_2
    //   80: getfield 426	android/util/Pair:second	Ljava/lang/Object;
    //   83: checkcast 103	android/graphics/drawable/Drawable
    //   86: aconst_null
    //   87: aconst_null
    //   88: aconst_null
    //   89: invokevirtual 430	android/widget/TextView:setCompoundDrawablesWithIntrinsicBounds	(Landroid/graphics/drawable/Drawable;Landroid/graphics/drawable/Drawable;Landroid/graphics/drawable/Drawable;Landroid/graphics/drawable/Drawable;)V
    //   92: goto -83 -> 9
    //   95: goto +7 -> 102
    //   98: return
    //   99: astore_2
    //   100: aload_2
    //   101: athrow
    //   102: getstatic 20	o/Mb:ˉ	I
    //   105: bipush 117
    //   107: iadd
    //   108: istore_1
    //   109: iload_1
    //   110: sipush 128
    //   113: irem
    //   114: putstatic 22	o/Mb:ˊˋ	I
    //   117: iload_1
    //   118: iconst_2
    //   119: irem
    //   120: ifeq +6 -> 126
    //   123: goto -120 -> 3
    //   126: goto -92 -> 34
    // Local variable table:
    //   start	length	slot	name	signature
    //   0	129	0	this	Mb
    //   15	105	1	i	int
    //   6	2	2	localException1	Exception
    //   38	42	2	localObject1	Object
    //   99	2	2	localException2	Exception
    //   49	7	3	localObject2	Object
    // Exception table:
    //   from	to	target	type
    //   34	39	6	java/lang/Exception
    //   39	45	6	java/lang/Exception
    //   45	50	6	java/lang/Exception
    //   50	55	6	java/lang/Exception
    //   55	92	6	java/lang/Exception
    //   45	50	99	java/lang/Exception
  }
  
  private void ˑ()
  {
    for (;;)
    {
      int i = ˉ + 23;
      ˊˋ = i % 128;
      if (i % 2 == 0) {
        break label36;
      }
      for (;;)
      {
        i = 1;
        break label50;
        return;
        label36:
        i = 57;
        break;
        label50:
        do
        {
          i = 0;
          switch (i)
          {
          default: 
            break;
            i = 46;
            break;
          case 0: 
            ˎ(String.valueOf(((Mu)this.ॱˊ).ॱˊ().totalAmount.ˏ()), ((Mu)this.ॱˊ).ॱˊ().currency.ˊ());
            throw new NullPointerException();
            i = ˉ + 95;
            ˊˋ = i % 128;
          }
        } while (i % 2 != 0);
      }
      throw new NullPointerException();
      switch (i)
      {
      }
      return;
      ˎ(String.valueOf(((Mu)this.ॱˊ).ॱˊ().totalAmount.ˏ()), ((Mu)this.ॱˊ).ॱˊ().currency.ˊ());
    }
  }
  
  /* Error */
  private String ॱ(String paramString)
  {
    // Byte code:
    //   0: goto +85 -> 85
    //   3: aload_1
    //   4: arraylength
    //   5: istore_3
    //   6: iload_2
    //   7: iload_3
    //   8: if_icmpge +6 -> 14
    //   11: goto +282 -> 293
    //   14: goto +188 -> 202
    //   17: bipush 88
    //   19: istore_2
    //   20: goto +151 -> 171
    //   23: getstatic 22	o/Mb:ˊˋ	I
    //   26: bipush 37
    //   28: iadd
    //   29: istore_2
    //   30: iload_2
    //   31: sipush 128
    //   34: irem
    //   35: putstatic 20	o/Mb:ˉ	I
    //   38: iload_2
    //   39: iconst_2
    //   40: irem
    //   41: ifne +6 -> 47
    //   44: goto -27 -> 17
    //   47: bipush 69
    //   49: istore_2
    //   50: goto +121 -> 171
    //   53: getstatic 20	o/Mb:ˉ	I
    //   56: istore_2
    //   57: iload_2
    //   58: bipush 87
    //   60: iadd
    //   61: istore_2
    //   62: iload_2
    //   63: sipush 128
    //   66: irem
    //   67: putstatic 22	o/Mb:ˊˋ	I
    //   70: iload_2
    //   71: iconst_2
    //   72: irem
    //   73: ifeq +6 -> 79
    //   76: goto +49 -> 125
    //   79: goto +205 -> 284
    //   82: astore_1
    //   83: aload_1
    //   84: athrow
    //   85: goto +13 -> 98
    //   88: astore_1
    //   89: new 453	java/lang/RuntimeException
    //   92: dup
    //   93: aload_1
    //   94: invokespecial 456	java/lang/RuntimeException:<init>	(Ljava/lang/Throwable;)V
    //   97: athrow
    //   98: getstatic 20	o/Mb:ˉ	I
    //   101: bipush 11
    //   103: iadd
    //   104: istore_2
    //   105: iload_2
    //   106: sipush 128
    //   109: irem
    //   110: putstatic 22	o/Mb:ˊˋ	I
    //   113: iload_2
    //   114: iconst_2
    //   115: irem
    //   116: ifeq +6 -> 122
    //   119: goto +12 -> 131
    //   122: goto +197 -> 319
    //   125: bipush 13
    //   127: istore_2
    //   128: goto +11 -> 139
    //   131: goto +188 -> 319
    //   134: aconst_null
    //   135: arraylength
    //   136: istore_2
    //   137: aload_1
    //   138: areturn
    //   139: iload_2
    //   140: lookupswitch	default:+28->168, 13:+134->274, 79:+139->279
    //   168: goto +106 -> 274
    //   171: iload_2
    //   172: lookupswitch	default:+28->200, 69:+145->317, 88:+-38->134
    //   200: aload_1
    //   201: areturn
    //   202: aload_0
    //   203: invokevirtual 247	android/content/Context:getResources	()Landroid/content/res/Resources;
    //   206: ldc_w 457
    //   209: invokevirtual 254	android/content/res/Resources:getString	(I)Ljava/lang/String;
    //   212: bipush 7
    //   214: bipush 8
    //   216: invokevirtual 258	java/lang/String:substring	(II)Ljava/lang/String;
    //   219: iconst_0
    //   220: invokevirtual 262	java/lang/String:codePointAt	(I)I
    //   223: istore_2
    //   224: new 176	java/lang/String
    //   227: dup
    //   228: aload 4
    //   230: iconst_4
    //   231: newarray int
    //   233: dup
    //   234: iconst_0
    //   235: ldc_w 458
    //   238: iastore
    //   239: dup
    //   240: iconst_1
    //   241: ldc_w 459
    //   244: iastore
    //   245: dup
    //   246: iconst_2
    //   247: ldc_w 460
    //   250: iastore
    //   251: dup
    //   252: iconst_3
    //   253: ldc_w 461
    //   256: iastore
    //   257: iload_2
    //   258: bipush 92
    //   260: isub
    //   261: invokestatic 361	o/Mb:ॱ	([II)Ljava/lang/String;
    //   264: invokevirtual 364	java/lang/String:intern	()Ljava/lang/String;
    //   267: invokespecial 464	java/lang/String:<init>	([BLjava/lang/String;)V
    //   270: astore_1
    //   271: goto -248 -> 23
    //   274: iload_3
    //   275: istore_2
    //   276: goto -273 -> 3
    //   279: iload_3
    //   280: istore_2
    //   281: goto -278 -> 3
    //   284: bipush 79
    //   286: istore_2
    //   287: goto -148 -> 139
    //   290: astore_1
    //   291: aload_1
    //   292: athrow
    //   293: aload 4
    //   295: iload_2
    //   296: aload_1
    //   297: aload_1
    //   298: arraylength
    //   299: iload_2
    //   300: isub
    //   301: iconst_1
    //   302: isub
    //   303: baload
    //   304: getstatic 26	o/Mb:ˊᐝ	B
    //   307: ixor
    //   308: i2b
    //   309: bastore
    //   310: iload_2
    //   311: iconst_1
    //   312: iadd
    //   313: istore_3
    //   314: goto -261 -> 53
    //   317: aload_1
    //   318: areturn
    //   319: aload_0
    //   320: invokevirtual 247	android/content/Context:getResources	()Landroid/content/res/Resources;
    //   323: ldc_w 465
    //   326: invokevirtual 254	android/content/res/Resources:getString	(I)Ljava/lang/String;
    //   329: bipush 11
    //   331: bipush 16
    //   333: invokevirtual 258	java/lang/String:substring	(II)Ljava/lang/String;
    //   336: invokevirtual 346	java/lang/String:length	()I
    //   339: istore_2
    //   340: aload_1
    //   341: bipush 6
    //   343: newarray int
    //   345: dup
    //   346: iconst_0
    //   347: ldc_w 466
    //   350: iastore
    //   351: dup
    //   352: iconst_1
    //   353: ldc_w 467
    //   356: iastore
    //   357: dup
    //   358: iconst_2
    //   359: ldc_w 468
    //   362: iastore
    //   363: dup
    //   364: iconst_3
    //   365: ldc_w 469
    //   368: iastore
    //   369: dup
    //   370: iconst_4
    //   371: ldc_w 470
    //   374: iastore
    //   375: dup
    //   376: iconst_5
    //   377: ldc_w 471
    //   380: iastore
    //   381: iload_2
    //   382: iconst_5
    //   383: iadd
    //   384: invokestatic 361	o/Mb:ॱ	([II)Ljava/lang/String;
    //   387: invokevirtual 364	java/lang/String:intern	()Ljava/lang/String;
    //   390: invokevirtual 475	java/lang/String:getBytes	(Ljava/lang/String;)[B
    //   393: astore_1
    //   394: aload_1
    //   395: arraylength
    //   396: newarray byte
    //   398: astore 4
    //   400: iconst_0
    //   401: istore_2
    //   402: goto -399 -> 3
    // Local variable table:
    //   start	length	slot	name	signature
    //   0	405	0	this	Mb
    //   0	405	1	paramString	String
    //   6	396	2	i	int
    //   5	309	3	j	int
    //   228	171	4	arrayOfByte	byte[]
    // Exception table:
    //   from	to	target	type
    //   98	105	82	java/lang/Exception
    //   105	113	82	java/lang/Exception
    //   3	6	88	java/io/UnsupportedEncodingException
    //   202	271	88	java/io/UnsupportedEncodingException
    //   293	310	88	java/io/UnsupportedEncodingException
    //   319	400	88	java/io/UnsupportedEncodingException
    //   53	57	290	java/lang/Exception
    //   62	70	290	java/lang/Exception
  }
  
  /* Error */
  private static String ॱ(int[] paramArrayOfInt, int paramInt)
  {
    // Byte code:
    //   0: goto +320 -> 320
    //   3: goto +144 -> 147
    //   6: getstatic 22	o/Mb:ˊˋ	I
    //   9: iconst_3
    //   10: iadd
    //   11: istore_2
    //   12: iload_2
    //   13: sipush 128
    //   16: irem
    //   17: putstatic 20	o/Mb:ˉ	I
    //   20: iload_2
    //   21: iconst_2
    //   22: irem
    //   23: ifne +6 -> 29
    //   26: goto +33 -> 59
    //   29: goto +247 -> 276
    //   32: iconst_1
    //   33: istore_3
    //   34: iload_3
    //   35: tableswitch	default:+21->56, 0:+270->305, 1:+137->172
    //   56: goto +249 -> 305
    //   59: iconst_2
    //   60: newarray char
    //   62: astore 5
    //   64: aload_0
    //   65: arraylength
    //   66: iconst_1
    //   67: iadd
    //   68: newarray char
    //   70: astore 6
    //   72: getstatic 50	o/Mb:ˋˊ	[I
    //   75: invokevirtual 479	[I:clone	()Ljava/lang/Object;
    //   78: checkcast 476	[I
    //   81: astore 4
    //   83: iconst_1
    //   84: istore_2
    //   85: goto +33 -> 118
    //   88: iconst_0
    //   89: istore_3
    //   90: iload_3
    //   91: tableswitch	default:+21->112, 0:+226->317, 1:+-88->3
    //   112: goto -109 -> 3
    //   115: astore_0
    //   116: aload_0
    //   117: athrow
    //   118: getstatic 22	o/Mb:ˊˋ	I
    //   121: istore_3
    //   122: iload_3
    //   123: bipush 29
    //   125: iadd
    //   126: istore_3
    //   127: iload_3
    //   128: sipush 128
    //   131: irem
    //   132: putstatic 20	o/Mb:ˉ	I
    //   135: iload_3
    //   136: iconst_2
    //   137: irem
    //   138: ifne +6 -> 144
    //   141: goto -53 -> 88
    //   144: goto +15 -> 159
    //   147: iload_2
    //   148: aload_0
    //   149: arraylength
    //   150: if_icmpge +6 -> 156
    //   153: goto -121 -> 32
    //   156: goto +8 -> 164
    //   159: iconst_1
    //   160: istore_3
    //   161: goto -71 -> 90
    //   164: iconst_0
    //   165: istore_3
    //   166: goto -132 -> 34
    //   169: astore_0
    //   170: aload_0
    //   171: athrow
    //   172: aload 5
    //   174: iconst_0
    //   175: aload_0
    //   176: iload_2
    //   177: iaload
    //   178: bipush 16
    //   180: ishr
    //   181: i2c
    //   182: castore
    //   183: aload 5
    //   185: iconst_1
    //   186: aload_0
    //   187: iload_2
    //   188: iaload
    //   189: i2c
    //   190: castore
    //   191: aload 5
    //   193: iconst_2
    //   194: aload_0
    //   195: iload_2
    //   196: iconst_1
    //   197: iadd
    //   198: iaload
    //   199: bipush 16
    //   201: ishr
    //   202: i2c
    //   203: castore
    //   204: aload 5
    //   206: iconst_3
    //   207: aload_0
    //   208: iload_2
    //   209: iconst_1
    //   210: iadd
    //   211: iaload
    //   212: i2c
    //   213: castore
    //   214: aload 5
    //   216: aload 4
    //   218: iconst_0
    //   219: invokestatic 484	o/oN:ˏ	([C[IZ)[I
    //   222: pop
    //   223: aload 6
    //   225: iload_2
    //   226: iconst_1
    //   227: ishl
    //   228: aload 5
    //   230: iconst_0
    //   231: caload
    //   232: castore
    //   233: aload 6
    //   235: iload_2
    //   236: iconst_1
    //   237: ishl
    //   238: iconst_1
    //   239: iadd
    //   240: aload 5
    //   242: iconst_1
    //   243: caload
    //   244: castore
    //   245: aload 6
    //   247: iload_2
    //   248: iconst_1
    //   249: ishl
    //   250: iconst_2
    //   251: iadd
    //   252: aload 5
    //   254: iconst_2
    //   255: caload
    //   256: castore
    //   257: aload 6
    //   259: iload_2
    //   260: iconst_1
    //   261: ishl
    //   262: iconst_3
    //   263: iadd
    //   264: aload 5
    //   266: iconst_3
    //   267: caload
    //   268: castore
    //   269: iload_2
    //   270: iconst_2
    //   271: iadd
    //   272: istore_2
    //   273: goto -126 -> 147
    //   276: iconst_4
    //   277: newarray char
    //   279: astore 5
    //   281: aload_0
    //   282: arraylength
    //   283: iconst_1
    //   284: ishl
    //   285: newarray char
    //   287: astore 6
    //   289: getstatic 50	o/Mb:ˋˊ	[I
    //   292: invokevirtual 479	[I:clone	()Ljava/lang/Object;
    //   295: checkcast 476	[I
    //   298: astore 4
    //   300: iconst_0
    //   301: istore_2
    //   302: goto -184 -> 118
    //   305: new 176	java/lang/String
    //   308: dup
    //   309: aload 6
    //   311: iconst_0
    //   312: iload_1
    //   313: invokespecial 487	java/lang/String:<init>	([CII)V
    //   316: areturn
    //   317: goto -170 -> 147
    //   320: goto -314 -> 6
    // Local variable table:
    //   start	length	slot	name	signature
    //   0	323	0	paramArrayOfInt	int[]
    //   0	323	1	paramInt	int
    //   11	291	2	i	int
    //   33	133	3	j	int
    //   81	218	4	arrayOfInt	int[]
    //   62	218	5	arrayOfChar1	char[]
    //   70	240	6	arrayOfChar2	char[]
    // Exception table:
    //   from	to	target	type
    //   118	122	115	java/lang/Exception
    //   127	135	169	java/lang/Exception
  }
  
  public Resources getResources()
  {
    break label28;
    throw new NullPointerException();
    int i = 25;
    break label31;
    label17:
    Resources localResources = oH.ˊ(super.getResources());
    for (;;)
    {
      label28:
      switch (i)
      {
      case 55: 
      default: 
        break;
      case 25: 
        label31:
        do
        {
          break label17;
          i = ˊˋ + 23;
          ˉ = i % 128;
          if (i % 2 == 0) {
            break label122;
          }
          break;
          return localResources;
          i = ˉ + 101;
          ˊˋ = i % 128;
        } while (i % 2 != 0);
        break label17;
        label122:
        i = 55;
      }
    }
  }
  
  public void onActivityResult(int paramInt1, int paramInt2, Intent paramIntent)
  {
    break label167;
    switch (paramInt2)
    {
    default: 
      label3:
      break;
    }
    for (;;)
    {
      paramInt1 = 2;
      break label176;
      paramInt1 = null.length;
      return;
      label113:
      label167:
      label170:
      label176:
      label205:
      do
      {
        paramInt1 = 58;
        break label176;
        paramInt2 = 75;
        break;
        switch (paramInt1)
        {
        default: 
          break;
          return;
        case 22: 
          double d = ((Mu)this.ॱˊ).ॱˊ().totalAmount.ˏ();
          ˊ(this.ʾ, d, true, false);
          break;
          paramInt2 = 15;
          break label3;
          for (;;)
          {
            super.onActivityResult(paramInt1, paramInt2, paramIntent);
            if (paramInt2 == -1) {
              break;
            }
            break label113;
            for (;;)
            {
              int i = ˉ + 25;
              ˊˋ = i % 128;
              if (i % 2 != 0) {
                break label170;
              }
              break;
            }
          }
        }
        break label205;
        switch (paramInt1)
        {
        }
        return;
        paramInt1 = ˉ + 121;
        ˊˋ = paramInt1 % 128;
      } while (paramInt1 % 2 != 0);
    }
  }
  
  public void onBackPressed()
  {
    for (;;)
    {
      Intent localIntent = new Intent();
      Bundle localBundle = new Bundle();
      i = getPackageName().codePointAt(3);
      localBundle.putParcelable(ॱ(new int[] { 1605731414, 604439238, -187561032, 1536610025, -189317974, 284843475, 2113906768, -652428786, 319106619, 805961822, 1803059986, 569530903 }, i - 76).intern(), this.ʽॱ);
      localIntent.putExtras(localBundle);
      setResult(0, localIntent);
      finish();
      break;
    }
    for (;;)
    {
      i = 0;
      break;
      i = ˊˋ + 9;
      ˉ = i % 128;
      if (i % 2 == 0) {
        break label215;
      }
    }
    return;
    int i = null.length;
    return;
    for (;;)
    {
      switch (i)
      {
      }
      break;
      label215:
      i = 1;
    }
  }
  
  public void onConfirmationClick(View paramView)
  {
    switch (i)
    {
    default: 
      break;
    case 0: 
      for (;;)
      {
        i = 0;
        break;
        do
        {
          i = 1;
          break;
          ˋˋ();
          return;
          i = ˉ + 77;
          ˊˋ = i % 128;
        } while (i % 2 != 0);
      }
    }
    ˋˋ();
    int i = null.length;
  }
  
  /* Error */
  public void onCreate(Bundle paramBundle)
  {
    // Byte code:
    //   0: goto +160 -> 160
    //   3: bipush 92
    //   5: istore_2
    //   6: goto +197 -> 203
    //   9: getstatic 22	o/Mb:ˊˋ	I
    //   12: bipush 21
    //   14: iadd
    //   15: istore_2
    //   16: iload_2
    //   17: sipush 128
    //   20: irem
    //   21: putstatic 20	o/Mb:ˉ	I
    //   24: iload_2
    //   25: iconst_2
    //   26: irem
    //   27: ifne +6 -> 33
    //   30: goto +45 -> 75
    //   33: return
    //   34: getstatic 20	o/Mb:ˉ	I
    //   37: istore_2
    //   38: iload_2
    //   39: bipush 69
    //   41: iadd
    //   42: istore_2
    //   43: iload_2
    //   44: sipush 128
    //   47: irem
    //   48: putstatic 22	o/Mb:ˊˋ	I
    //   51: iload_2
    //   52: iconst_2
    //   53: irem
    //   54: ifeq +6 -> 60
    //   57: goto +12 -> 69
    //   60: goto -57 -> 3
    //   63: astore_1
    //   64: aload_1
    //   65: athrow
    //   66: astore_1
    //   67: aload_1
    //   68: athrow
    //   69: bipush 72
    //   71: istore_2
    //   72: goto +131 -> 203
    //   75: goto -42 -> 33
    //   78: aload_0
    //   79: invokespecial 523	o/Mb:ˍ	()V
    //   82: aload_0
    //   83: aload_0
    //   84: getfield 304	o/Mb:ʾ	Lo/HQ;
    //   87: new 165	java/math/BigDecimal
    //   90: dup
    //   91: aload_0
    //   92: getfield 66	o/Mb:ॱˊ	Landroid/databinding/ViewDataBinding;
    //   95: checkcast 68	o/Mu
    //   98: invokevirtual 435	o/Mu:ॱˊ	()Lo/Gh;
    //   101: getfield 169	o/Gh:amount	Lo/ـ;
    //   104: invokevirtual 174	o/ـ:ˏ	()Ljava/lang/Object;
    //   107: checkcast 176	java/lang/String
    //   110: invokespecial 179	java/math/BigDecimal:<init>	(Ljava/lang/String;)V
    //   113: invokevirtual 526	o/Mb:ˎ	(Lo/HQ;Ljava/math/BigDecimal;)V
    //   116: goto -107 -> 9
    //   119: aload_0
    //   120: aload_1
    //   121: invokespecial 528	o/LZ:onCreate	(Landroid/os/Bundle;)V
    //   124: aload_0
    //   125: aload_0
    //   126: getfield 66	o/Mb:ॱˊ	Landroid/databinding/ViewDataBinding;
    //   129: checkcast 68	o/Mu
    //   132: getfield 532	o/Mu:ʻॱ	Lo/у;
    //   135: invokevirtual 535	o/Mb:ˊ	(Lo/у;)V
    //   138: aload_0
    //   139: invokespecial 537	o/Mb:ˋᐝ	()V
    //   142: aload_0
    //   143: invokevirtual 55	o/Mb:ˊˊ	()Z
    //   146: istore_3
    //   147: bipush 28
    //   149: iconst_0
    //   150: idiv
    //   151: istore_2
    //   152: iload_3
    //   153: ifne +6 -> 159
    //   156: goto -78 -> 78
    //   159: return
    //   160: goto -126 -> 34
    //   163: aload_0
    //   164: aload_1
    //   165: invokespecial 528	o/LZ:onCreate	(Landroid/os/Bundle;)V
    //   168: aload_0
    //   169: getfield 66	o/Mb:ॱˊ	Landroid/databinding/ViewDataBinding;
    //   172: astore_1
    //   173: aload_1
    //   174: checkcast 68	o/Mu
    //   177: astore_1
    //   178: aload_0
    //   179: aload_1
    //   180: getfield 532	o/Mu:ʻॱ	Lo/у;
    //   183: invokevirtual 535	o/Mb:ˊ	(Lo/у;)V
    //   186: aload_0
    //   187: invokespecial 537	o/Mb:ˋᐝ	()V
    //   190: aload_0
    //   191: invokevirtual 55	o/Mb:ˊˊ	()Z
    //   194: istore_3
    //   195: iload_3
    //   196: ifne +6 -> 202
    //   199: goto -121 -> 78
    //   202: return
    //   203: iload_2
    //   204: lookupswitch	default:+28->232, 72:+-85->119, 92:+-41->163
    //   232: goto -69 -> 163
    // Local variable table:
    //   start	length	slot	name	signature
    //   0	235	0	this	Mb
    //   0	235	1	paramBundle	Bundle
    //   5	199	2	i	int
    //   146	50	3	bool	boolean
    // Exception table:
    //   from	to	target	type
    //   34	38	63	java/lang/Exception
    //   43	51	63	java/lang/Exception
    //   168	173	63	java/lang/Exception
    //   173	178	63	java/lang/Exception
    //   178	195	66	java/lang/Exception
  }
  
  public void onPickFromCardClick(View paramView)
  {
    break label61;
    int i = ˉ + 109;
    ˊˋ = i % 128;
    if (i % 2 != 0) {
      return;
    }
    return;
    label53:
    label61:
    for (;;)
    {
      i = ˊˋ + 7;
      ˉ = i % 128;
      if (i % 2 != 0) {
        break label53;
      }
      ˊ(3);
      break;
    }
  }
  
  /* Error */
  public void onPickToCardClick(View paramView)
  {
    // Byte code:
    //   0: goto +123 -> 123
    //   3: new 337	java/lang/NullPointerException
    //   6: dup
    //   7: invokespecial 338	java/lang/NullPointerException:<init>	()V
    //   10: athrow
    //   11: aload_0
    //   12: iconst_4
    //   13: invokevirtual 541	o/Mb:ˊ	(I)V
    //   16: goto +43 -> 59
    //   19: astore_1
    //   20: aload_1
    //   21: athrow
    //   22: astore_1
    //   23: aload_1
    //   24: athrow
    //   25: return
    //   26: bipush 23
    //   28: istore_2
    //   29: goto +62 -> 91
    //   32: getstatic 22	o/Mb:ˊˋ	I
    //   35: bipush 9
    //   37: iadd
    //   38: istore_2
    //   39: iload_2
    //   40: sipush 128
    //   43: irem
    //   44: putstatic 20	o/Mb:ˉ	I
    //   47: iload_2
    //   48: iconst_2
    //   49: irem
    //   50: ifne +6 -> 56
    //   53: goto +35 -> 88
    //   56: goto -45 -> 11
    //   59: getstatic 22	o/Mb:ˊˋ	I
    //   62: istore_2
    //   63: iload_2
    //   64: bipush 33
    //   66: iadd
    //   67: istore_2
    //   68: iload_2
    //   69: sipush 128
    //   72: irem
    //   73: putstatic 20	o/Mb:ˉ	I
    //   76: iload_2
    //   77: iconst_2
    //   78: irem
    //   79: ifne +6 -> 85
    //   82: goto -56 -> 26
    //   85: goto +41 -> 126
    //   88: goto -77 -> 11
    //   91: iload_2
    //   92: lookupswitch	default:+28->120, 23:+-89->3, 68:+-67->25
    //   120: goto -117 -> 3
    //   123: goto -91 -> 32
    //   126: bipush 68
    //   128: istore_2
    //   129: goto -38 -> 91
    // Local variable table:
    //   start	length	slot	name	signature
    //   0	132	0	this	Mb
    //   0	132	1	paramView	View
    //   28	101	2	i	int
    // Exception table:
    //   from	to	target	type
    //   68	76	19	java/lang/Exception
    //   59	63	22	java/lang/Exception
  }
  
  protected void ʾ()
  {
    break label135;
    int i;
    switch (i)
    {
    case 68: 
    default: 
      return;
      label33:
      i = ˉ + 123;
      ˊˋ = i % 128;
      if (i % 2 != 0) {
        break;
      }
      break;
    }
    label135:
    for (;;)
    {
      ((Mu)this.ॱˊ).ˊ(this.ʾ);
      ˎˏ();
      ˎ(this.ʾ, new BigDecimal((String)((Mu)this.ॱˊ).ॱˊ().amount.ˏ()));
      break label33;
      i = 96;
      break;
      i = 68;
      break;
      throw new NullPointerException();
    }
  }
  
  protected void ˊᐝ()
  {
    for (;;)
    {
      int i = 3 / 0;
      return;
      for (;;)
      {
        try
        {
          Object localObject = this.ॱˊ;
          localObject = (Mu)localObject;
          HQ localHQ = this.ʼॱ;
          ((Mu)localObject).ˏ(localHQ);
          ˏˏ();
        }
        catch (Exception localException)
        {
          throw localException;
        }
        do
        {
          break;
          i = ˊˋ + 123;
          ˉ = i % 128;
          if (i % 2 == 0) {
            break label96;
          }
          break label102;
          return;
          i = ˉ + 61;
          ˊˋ = i % 128;
        } while (i % 2 != 0);
      }
      label96:
      i = 43;
      break label105;
      label102:
      i = 19;
      label105:
      switch (i)
      {
      }
    }
  }
  
  /* Error */
  public void ˋ(ز paramز)
  {
    // Byte code:
    //   0: goto +9 -> 9
    //   3: astore_1
    //   4: aload_1
    //   5: athrow
    //   6: astore_1
    //   7: aload_1
    //   8: athrow
    //   9: goto +26 -> 35
    //   12: getstatic 22	o/Mb:ˊˋ	I
    //   15: bipush 97
    //   17: iadd
    //   18: istore_2
    //   19: iload_2
    //   20: sipush 128
    //   23: irem
    //   24: putstatic 20	o/Mb:ˉ	I
    //   27: iload_2
    //   28: iconst_2
    //   29: irem
    //   30: ifne +4 -> 34
    //   33: return
    //   34: return
    //   35: getstatic 22	o/Mb:ˊˋ	I
    //   38: istore_2
    //   39: iload_2
    //   40: bipush 25
    //   42: iadd
    //   43: istore_2
    //   44: iload_2
    //   45: sipush 128
    //   48: irem
    //   49: putstatic 20	o/Mb:ˉ	I
    //   52: iload_2
    //   53: iconst_2
    //   54: irem
    //   55: ifne +6 -> 61
    //   58: goto +6 -> 64
    //   61: goto +3 -> 64
    //   64: aload_1
    //   65: iconst_1
    //   66: invokevirtual 546	o/ز:ॱ	(Z)V
    //   69: aload_1
    //   70: iconst_1
    //   71: invokevirtual 548	o/ز:ˏ	(Z)V
    //   74: goto -62 -> 12
    // Local variable table:
    //   start	length	slot	name	signature
    //   0	77	0	this	Mb
    //   0	77	1	paramز	ز
    //   18	37	2	i	int
    // Exception table:
    //   from	to	target	type
    //   44	52	3	java/lang/Exception
    //   35	39	6	java/lang/Exception
  }
  
  public int ˎ()
  {
    for (;;)
    {
      i = 93;
      do
      {
        i = 99;
        switch (i)
        {
        case 93: 
        default: 
          try
          {
            i = LV.iF.activity_inter_cards_transfer_details;
            return i;
          }
          catch (Exception localException)
          {
            throw localException;
          }
          i = ˉ + 25;
          ˊˋ = i % 128;
        }
      } while (i % 2 != 0);
    }
    int i = LV.iF.activity_inter_cards_transfer_details;
    int j = null.length;
    return i;
  }
  
  protected void ˎ(BigDecimal paramBigDecimal)
  {
    break label167;
    int i = ˉ + 5;
    ˊˋ = i % 128;
    if (i % 2 == 0) {
      return;
    }
    for (;;)
    {
      try
      {
        localObject = this.ʽॱ;
      }
      catch (Exception paramBigDecimal)
      {
        Object localObject;
        double d;
        throw paramBigDecimal;
      }
      try
      {
        localObject = ((Gh)localObject).amount;
        localObject = ((ـ)localObject).ˏ();
        localObject = (String)localObject;
        d = Double.parseDouble((String)localObject) + paramBigDecimal.doubleValue();
        ((Mu)this.ॱˊ).ॱˊ().commission.ˏ(paramBigDecimal.doubleValue());
        ((Mu)this.ॱˊ).ॱˊ().totalAmount.ˏ(d);
        ((Mu)this.ॱˊ).ˊ(true);
        ˊ(this.ʾ, d, false, false);
      }
      catch (Exception paramBigDecimal)
      {
        throw paramBigDecimal;
      }
      i = ˉ + 63;
      ˊˋ = i % 128;
      label167:
      if (i % 2 == 0)
      {
        continue;
        return;
      }
    }
  }
  
  protected void ˎ(FW paramFW, FS paramFS)
  {
    break label233;
    int i = ˊˋ + 117;
    ˉ = i % 128;
    if (i % 2 != 0) {
      break label36;
    }
    for (;;)
    {
      i = 8;
      break;
      label36:
      super.ˎ(paramFW, paramFS);
      ˍ();
      try
      {
        paramFW = this.ʾ;
        if (paramFW == null)
        {
          break label63;
          return;
          return;
          label63:
          i = 0;
          break label109;
          i = ˊˋ + 55;
          ˉ = i % 128;
          if (i % 2 == 0) {
            continue;
          }
          break label236;
          label95:
          if (this.ʾ.ˊᐝ()) {
            return;
          }
        }
        for (;;)
        {
          label109:
          switch (i)
          {
          }
          break label95;
          ˎ(this.ʾ, new BigDecimal((String)((Mu)this.ॱˊ).ॱˊ().amount.ˏ()));
          break;
          i = 1;
        }
        super.ˎ(paramFW, paramFS);
        ˍ();
        paramFW = this.ʾ;
        throw new NullPointerException();
      }
      catch (Exception paramFW)
      {
        throw paramFW;
      }
    }
    for (;;)
    {
      switch (i)
      {
      }
      return;
      label233:
      break;
      label236:
      i = 99;
    }
  }
  
  /* Error */
  protected void ˎ(boolean paramBoolean)
  {
    // Byte code:
    //   0: goto +8 -> 8
    //   3: iconst_1
    //   4: istore_2
    //   5: goto +192 -> 197
    //   8: goto +28 -> 36
    //   11: bipush 69
    //   13: istore_2
    //   14: goto +106 -> 120
    //   17: astore_3
    //   18: aload_3
    //   19: athrow
    //   20: aload_0
    //   21: aload_3
    //   22: iconst_4
    //   23: invokevirtual 572	java/lang/String:substring	(I)Ljava/lang/String;
    //   26: invokespecial 574	o/Mb:ॱ	(Ljava/lang/String;)Ljava/lang/String;
    //   29: invokevirtual 364	java/lang/String:intern	()Ljava/lang/String;
    //   32: astore_3
    //   33: goto +54 -> 87
    //   36: getstatic 20	o/Mb:ˉ	I
    //   39: bipush 63
    //   41: iadd
    //   42: istore_2
    //   43: iload_2
    //   44: sipush 128
    //   47: irem
    //   48: putstatic 22	o/Mb:ˊˋ	I
    //   51: iload_2
    //   52: iconst_2
    //   53: irem
    //   54: ifeq +6 -> 60
    //   57: goto -46 -> 11
    //   60: goto +118 -> 178
    //   63: aload_0
    //   64: getfield 66	o/Mb:ॱˊ	Landroid/databinding/ViewDataBinding;
    //   67: checkcast 68	o/Mu
    //   70: iconst_0
    //   71: invokevirtual 323	o/Mu:ˊ	(Z)V
    //   74: iload_1
    //   75: ifeq +6 -> 81
    //   78: goto +106 -> 184
    //   81: goto +142 -> 223
    //   84: astore_3
    //   85: aload_3
    //   86: athrow
    //   87: aload 4
    //   89: aload_3
    //   90: invokevirtual 423	android/widget/TextView:setText	(Ljava/lang/CharSequence;)V
    //   93: aload_0
    //   94: getfield 66	o/Mb:ॱˊ	Landroid/databinding/ViewDataBinding;
    //   97: checkcast 68	o/Mu
    //   100: getfield 409	o/Mu:ʽ	Landroid/widget/TextView;
    //   103: aload_0
    //   104: invokevirtual 577	o/Mb:ॱˊ	()Landroid/content/Context;
    //   107: getstatic 582	o/LV$ˋ:ic_error	I
    //   110: invokestatic 585	o/ᔆ:ˎ	(Landroid/content/Context;I)Landroid/graphics/drawable/Drawable;
    //   113: aconst_null
    //   114: aconst_null
    //   115: aconst_null
    //   116: invokevirtual 430	android/widget/TextView:setCompoundDrawablesWithIntrinsicBounds	(Landroid/graphics/drawable/Drawable;Landroid/graphics/drawable/Drawable;Landroid/graphics/drawable/Drawable;Landroid/graphics/drawable/Drawable;)V
    //   119: return
    //   120: iload_2
    //   121: lookupswitch	default:+27->148, 20:+-58->63, 69:+27->148
    //   148: aload_0
    //   149: getfield 66	o/Mb:ॱˊ	Landroid/databinding/ViewDataBinding;
    //   152: astore_3
    //   153: aload_3
    //   154: checkcast 68	o/Mu
    //   157: astore_3
    //   158: aload_3
    //   159: iconst_1
    //   160: invokevirtual 323	o/Mu:ˊ	(Z)V
    //   163: iload_1
    //   164: ifeq +6 -> 170
    //   167: goto +17 -> 184
    //   170: goto +53 -> 223
    //   173: iconst_0
    //   174: istore_2
    //   175: goto +22 -> 197
    //   178: bipush 20
    //   180: istore_2
    //   181: goto -61 -> 120
    //   184: new 587	o/MC
    //   187: dup
    //   188: aload_0
    //   189: invokespecial 590	o/MC:<init>	(Landroid/content/Context;)V
    //   192: invokevirtual 593	o/MC:ˏ	()Lo/ᐸ;
    //   195: pop
    //   196: return
    //   197: iload_2
    //   198: tableswitch	default:+22->220, 0:+129->327, 1:+-178->20
    //   220: goto -200 -> 20
    //   223: aload_0
    //   224: getfield 66	o/Mb:ॱˊ	Landroid/databinding/ViewDataBinding;
    //   227: checkcast 68	o/Mu
    //   230: getfield 409	o/Mu:ʽ	Landroid/widget/TextView;
    //   233: astore 4
    //   235: aload_0
    //   236: getstatic 598	o/LV$If:insufficient_funds_title	I
    //   239: invokevirtual 599	o/Mb:getString	(I)Ljava/lang/String;
    //   242: astore_3
    //   243: aload_0
    //   244: invokevirtual 247	android/content/Context:getResources	()Landroid/content/res/Resources;
    //   247: ldc_w 600
    //   250: invokevirtual 254	android/content/res/Resources:getString	(I)Ljava/lang/String;
    //   253: iconst_0
    //   254: bipush 9
    //   256: invokevirtual 258	java/lang/String:substring	(II)Ljava/lang/String;
    //   259: invokevirtual 346	java/lang/String:length	()I
    //   262: istore_2
    //   263: aload_3
    //   264: iconst_2
    //   265: newarray int
    //   267: dup
    //   268: iconst_0
    //   269: ldc_w 601
    //   272: iastore
    //   273: dup
    //   274: iconst_1
    //   275: ldc_w 602
    //   278: iastore
    //   279: iload_2
    //   280: iconst_5
    //   281: isub
    //   282: invokestatic 361	o/Mb:ॱ	([II)Ljava/lang/String;
    //   285: invokevirtual 364	java/lang/String:intern	()Ljava/lang/String;
    //   288: invokevirtual 606	java/lang/String:startsWith	(Ljava/lang/String;)Z
    //   291: ifeq +6 -> 297
    //   294: goto +6 -> 300
    //   297: goto -210 -> 87
    //   300: getstatic 22	o/Mb:ˊˋ	I
    //   303: bipush 15
    //   305: iadd
    //   306: istore_2
    //   307: iload_2
    //   308: sipush 128
    //   311: irem
    //   312: putstatic 20	o/Mb:ˉ	I
    //   315: iload_2
    //   316: iconst_2
    //   317: irem
    //   318: ifne +6 -> 324
    //   321: goto -148 -> 173
    //   324: goto -321 -> 3
    //   327: aload_0
    //   328: aload_3
    //   329: iconst_4
    //   330: invokevirtual 572	java/lang/String:substring	(I)Ljava/lang/String;
    //   333: invokespecial 574	o/Mb:ॱ	(Ljava/lang/String;)Ljava/lang/String;
    //   336: invokevirtual 364	java/lang/String:intern	()Ljava/lang/String;
    //   339: astore_3
    //   340: aconst_null
    //   341: arraylength
    //   342: istore_2
    //   343: goto -256 -> 87
    // Local variable table:
    //   start	length	slot	name	signature
    //   0	346	0	this	Mb
    //   0	346	1	paramBoolean	boolean
    //   4	339	2	i	int
    //   17	5	3	localException1	Exception
    //   32	1	3	str	String
    //   84	6	3	localException2	Exception
    //   152	188	3	localObject	Object
    //   87	147	4	localTextView	TextView
    // Exception table:
    //   from	to	target	type
    //   36	43	17	java/lang/Exception
    //   43	51	17	java/lang/Exception
    //   148	153	17	java/lang/Exception
    //   158	163	17	java/lang/Exception
    //   153	158	84	java/lang/Exception
  }
  
  /* Error */
  protected void ॱ(boolean paramBoolean)
  {
    // Byte code:
    //   0: goto +239 -> 239
    //   3: getstatic 22	o/Mb:ˊˋ	I
    //   6: bipush 87
    //   8: iadd
    //   9: istore_2
    //   10: iload_2
    //   11: sipush 128
    //   14: irem
    //   15: putstatic 20	o/Mb:ˉ	I
    //   18: iload_2
    //   19: iconst_2
    //   20: irem
    //   21: ifne +6 -> 27
    //   24: goto +218 -> 242
    //   27: return
    //   28: bipush 25
    //   30: istore_2
    //   31: goto +6 -> 37
    //   34: goto -31 -> 3
    //   37: iload_2
    //   38: lookupswitch	default:+26->64, 25:+-4->34, 97:+194->232
    //   64: goto -30 -> 34
    //   67: aload 4
    //   69: aload_3
    //   70: invokevirtual 423	android/widget/TextView:setText	(Ljava/lang/CharSequence;)V
    //   73: aload_0
    //   74: getfield 66	o/Mb:ॱˊ	Landroid/databinding/ViewDataBinding;
    //   77: checkcast 68	o/Mu
    //   80: getfield 409	o/Mu:ʽ	Landroid/widget/TextView;
    //   83: aconst_null
    //   84: aconst_null
    //   85: aconst_null
    //   86: aconst_null
    //   87: invokevirtual 430	android/widget/TextView:setCompoundDrawablesWithIntrinsicBounds	(Landroid/graphics/drawable/Drawable;Landroid/graphics/drawable/Drawable;Landroid/graphics/drawable/Drawable;Landroid/graphics/drawable/Drawable;)V
    //   90: iload_1
    //   91: ifeq +6 -> 97
    //   94: goto +105 -> 199
    //   97: goto -69 -> 28
    //   100: astore_3
    //   101: aload_3
    //   102: athrow
    //   103: iconst_0
    //   104: istore_2
    //   105: goto +67 -> 172
    //   108: aload_0
    //   109: aload_3
    //   110: iconst_4
    //   111: invokevirtual 572	java/lang/String:substring	(I)Ljava/lang/String;
    //   114: invokespecial 574	o/Mb:ॱ	(Ljava/lang/String;)Ljava/lang/String;
    //   117: invokevirtual 364	java/lang/String:intern	()Ljava/lang/String;
    //   120: astore_3
    //   121: goto -54 -> 67
    //   124: getstatic 22	o/Mb:ˊˋ	I
    //   127: bipush 65
    //   129: iadd
    //   130: istore_2
    //   131: iload_2
    //   132: sipush 128
    //   135: irem
    //   136: putstatic 20	o/Mb:ˉ	I
    //   139: iload_2
    //   140: iconst_2
    //   141: irem
    //   142: ifne +6 -> 148
    //   145: goto -42 -> 103
    //   148: goto +95 -> 243
    //   151: aload_0
    //   152: aload_3
    //   153: iconst_4
    //   154: invokevirtual 572	java/lang/String:substring	(I)Ljava/lang/String;
    //   157: invokespecial 574	o/Mb:ॱ	(Ljava/lang/String;)Ljava/lang/String;
    //   160: invokevirtual 364	java/lang/String:intern	()Ljava/lang/String;
    //   163: astore_3
    //   164: bipush 10
    //   166: iconst_0
    //   167: idiv
    //   168: istore_2
    //   169: goto -102 -> 67
    //   172: iload_2
    //   173: tableswitch	default:+23->196, 0:+-22->151, 1:+-65->108
    //   196: goto -88 -> 108
    //   199: bipush 97
    //   201: istore_2
    //   202: goto -165 -> 37
    //   205: getstatic 22	o/Mb:ˊˋ	I
    //   208: bipush 15
    //   210: iadd
    //   211: istore_2
    //   212: iload_2
    //   213: sipush 128
    //   216: irem
    //   217: putstatic 20	o/Mb:ˉ	I
    //   220: iload_2
    //   221: iconst_2
    //   222: irem
    //   223: ifne +6 -> 229
    //   226: goto +99 -> 325
    //   229: goto +19 -> 248
    //   232: aload_0
    //   233: invokespecial 608	o/Mb:ˌ	()V
    //   236: goto -202 -> 34
    //   239: goto -34 -> 205
    //   242: return
    //   243: iconst_1
    //   244: istore_2
    //   245: goto -73 -> 172
    //   248: aload_0
    //   249: getfield 66	o/Mb:ॱˊ	Landroid/databinding/ViewDataBinding;
    //   252: checkcast 68	o/Mu
    //   255: getfield 409	o/Mu:ʽ	Landroid/widget/TextView;
    //   258: astore 4
    //   260: aload_0
    //   261: getstatic 611	o/LV$If:transfer_between_cards_source_card	I
    //   264: invokevirtual 599	o/Mb:getString	(I)Ljava/lang/String;
    //   267: astore_3
    //   268: aload_0
    //   269: invokevirtual 247	android/content/Context:getResources	()Landroid/content/res/Resources;
    //   272: ldc_w 612
    //   275: invokevirtual 254	android/content/res/Resources:getString	(I)Ljava/lang/String;
    //   278: iconst_0
    //   279: bipush 9
    //   281: invokevirtual 258	java/lang/String:substring	(II)Ljava/lang/String;
    //   284: invokevirtual 346	java/lang/String:length	()I
    //   287: istore_2
    //   288: aload_3
    //   289: iconst_2
    //   290: newarray int
    //   292: dup
    //   293: iconst_0
    //   294: ldc_w 601
    //   297: iastore
    //   298: dup
    //   299: iconst_1
    //   300: ldc_w 602
    //   303: iastore
    //   304: iload_2
    //   305: iconst_5
    //   306: isub
    //   307: invokestatic 361	o/Mb:ॱ	([II)Ljava/lang/String;
    //   310: invokevirtual 364	java/lang/String:intern	()Ljava/lang/String;
    //   313: invokevirtual 606	java/lang/String:startsWith	(Ljava/lang/String;)Z
    //   316: ifeq +6 -> 322
    //   319: goto -195 -> 124
    //   322: goto -255 -> 67
    //   325: goto -77 -> 248
    // Local variable table:
    //   start	length	slot	name	signature
    //   0	328	0	this	Mb
    //   0	328	1	paramBoolean	boolean
    //   9	298	2	i	int
    //   69	1	3	localCharSequence	CharSequence
    //   100	10	3	localException	Exception
    //   120	169	3	str	String
    //   67	192	4	localTextView	TextView
    // Exception table:
    //   from	to	target	type
    //   124	131	100	java/lang/Exception
    //   131	139	100	java/lang/Exception
  }
  
  /* Error */
  protected void ॱˋ()
  {
    // Byte code:
    //   0: goto +301 -> 301
    //   3: bipush 84
    //   5: istore_1
    //   6: goto +189 -> 195
    //   9: bipush 68
    //   11: istore_1
    //   12: goto +123 -> 135
    //   15: iconst_0
    //   16: istore_1
    //   17: goto +13 -> 30
    //   20: new 337	java/lang/NullPointerException
    //   23: dup
    //   24: invokespecial 338	java/lang/NullPointerException:<init>	()V
    //   27: athrow
    //   28: iconst_1
    //   29: istore_1
    //   30: iload_1
    //   31: tableswitch	default:+21->52, 0:+242->273, 1:+221->252
    //   52: goto +200 -> 252
    //   55: aload_0
    //   56: getfield 66	o/Mb:ॱˊ	Landroid/databinding/ViewDataBinding;
    //   59: checkcast 68	o/Mu
    //   62: iconst_0
    //   63: invokevirtual 323	o/Mu:ˊ	(Z)V
    //   66: aload_0
    //   67: getstatic 616	o/LV$If:invalid_p2p_operation	I
    //   70: invokevirtual 599	o/Mb:getString	(I)Ljava/lang/String;
    //   73: astore_3
    //   74: aload_0
    //   75: invokevirtual 247	android/content/Context:getResources	()Landroid/content/res/Resources;
    //   78: ldc_w 617
    //   81: invokevirtual 254	android/content/res/Resources:getString	(I)Ljava/lang/String;
    //   84: bipush 6
    //   86: bipush 12
    //   88: invokevirtual 258	java/lang/String:substring	(II)Ljava/lang/String;
    //   91: invokevirtual 346	java/lang/String:length	()I
    //   94: istore_1
    //   95: aload_3
    //   96: iconst_2
    //   97: newarray int
    //   99: dup
    //   100: iconst_0
    //   101: ldc_w 601
    //   104: iastore
    //   105: dup
    //   106: iconst_1
    //   107: ldc_w 602
    //   110: iastore
    //   111: iload_1
    //   112: iconst_2
    //   113: isub
    //   114: invokestatic 361	o/Mb:ॱ	([II)Ljava/lang/String;
    //   117: invokevirtual 364	java/lang/String:intern	()Ljava/lang/String;
    //   120: invokevirtual 606	java/lang/String:startsWith	(Ljava/lang/String;)Z
    //   123: ifeq +6 -> 129
    //   126: goto +192 -> 318
    //   129: goto -120 -> 9
    //   132: goto +172 -> 304
    //   135: aload_3
    //   136: astore_2
    //   137: iload_1
    //   138: lookupswitch	default:+26->164, 68:+166->304, 69:+87->225
    //   164: goto +61 -> 225
    //   167: getstatic 20	o/Mb:ˉ	I
    //   170: bipush 91
    //   172: iadd
    //   173: istore_1
    //   174: iload_1
    //   175: sipush 128
    //   178: irem
    //   179: putstatic 22	o/Mb:ˊˋ	I
    //   182: iload_1
    //   183: iconst_2
    //   184: irem
    //   185: ifeq +6 -> 191
    //   188: goto -185 -> 3
    //   191: goto +98 -> 289
    //   194: return
    //   195: iload_1
    //   196: lookupswitch	default:+28->224, 17:+-2->194, 84:+-176->20
    //   224: return
    //   225: getstatic 22	o/Mb:ˊˋ	I
    //   228: bipush 79
    //   230: iadd
    //   231: istore_1
    //   232: iload_1
    //   233: sipush 128
    //   236: irem
    //   237: putstatic 20	o/Mb:ˉ	I
    //   240: iload_1
    //   241: iconst_2
    //   242: irem
    //   243: ifne +6 -> 249
    //   246: goto -218 -> 28
    //   249: goto -234 -> 15
    //   252: aload_0
    //   253: aload_3
    //   254: iconst_4
    //   255: invokevirtual 572	java/lang/String:substring	(I)Ljava/lang/String;
    //   258: invokespecial 574	o/Mb:ॱ	(Ljava/lang/String;)Ljava/lang/String;
    //   261: invokevirtual 364	java/lang/String:intern	()Ljava/lang/String;
    //   264: astore_2
    //   265: new 337	java/lang/NullPointerException
    //   268: dup
    //   269: invokespecial 338	java/lang/NullPointerException:<init>	()V
    //   272: athrow
    //   273: aload_0
    //   274: aload_3
    //   275: iconst_4
    //   276: invokevirtual 572	java/lang/String:substring	(I)Ljava/lang/String;
    //   279: invokespecial 574	o/Mb:ॱ	(Ljava/lang/String;)Ljava/lang/String;
    //   282: invokevirtual 364	java/lang/String:intern	()Ljava/lang/String;
    //   285: astore_2
    //   286: goto -154 -> 132
    //   289: bipush 17
    //   291: istore_1
    //   292: goto -97 -> 195
    //   295: astore_2
    //   296: aload_2
    //   297: athrow
    //   298: astore_2
    //   299: aload_2
    //   300: athrow
    //   301: goto -246 -> 55
    //   304: aload_0
    //   305: aload_2
    //   306: iconst_1
    //   307: invokestatic 623	android/widget/Toast:makeText	(Landroid/content/Context;Ljava/lang/CharSequence;I)Landroid/widget/Toast;
    //   310: astore_2
    //   311: aload_2
    //   312: invokevirtual 626	android/widget/Toast:show	()V
    //   315: goto -148 -> 167
    //   318: bipush 69
    //   320: istore_1
    //   321: goto -186 -> 135
    // Local variable table:
    //   start	length	slot	name	signature
    //   0	324	0	this	Mb
    //   5	316	1	i	int
    //   136	150	2	str1	String
    //   295	2	2	localException1	Exception
    //   298	8	2	localException2	Exception
    //   310	2	2	localToast	android.widget.Toast
    //   73	202	3	str2	String
    // Exception table:
    //   from	to	target	type
    //   311	315	295	java/lang/Exception
    //   304	311	298	java/lang/Exception
  }
}
