package o;

import android.content.Intent;
import android.os.Bundle;
import android.view.View;
import com.insidesecure.hce.MatrixHCECard;
import java.util.ArrayList;
import java.util.Iterator;
import java.util.List;
import org.greenrobot.eventbus.ThreadMode;

public class Md
  extends IB<Mw>
{
  private static int ʼॱ = 75972022;
  private static int ʾ;
  private static byte[] ˉ;
  private static int ˊˊ;
  private static int ˊˋ;
  private static short[] ˊᐝ;
  private static int ˋˊ = 0;
  private String ʽॱ;
  private Gh ʿ;
  private int ˈ = -1;
  
  static
  {
    ˊˊ = 1;
    ʾ = 103;
    ˉ = new byte[] { -128, 124, -124, 121, 114, -121, 125, -108, 122, 112, 126, -125, -117, 107, -121, 125, -121, -106, -121, -123, 106, -24, 16, 26, 20, -30, -20, 21, -26, 2, 17, -3, 22, 30, -4, -19, 6, -19, -4, -19, -17, 0, 69, 74, -66, -88, 69, 76, -81, 64, -70, 69, 65, 79, -81, 64, 71, -71, 76, -80, 77, -68, -81, 64, 81, 64, 66, -83, 0, 0, 0 };
    ˊˋ = -782888013;
  }
  
  public Md() {}
  
  private void ʻॱ()
  {
    int i;
    for (;;)
    {
      i = ˋˊ + 123;
      ˊˊ = i % 128;
      if (i % 2 != 0) {
        break;
      }
      break;
    }
    for (;;)
    {
      i = ˋˊ + 67;
      ˊˊ = i % 128;
      if (i % 2 == 0) {
        return;
      }
      return;
      HQ localHQ = ((Mw)this.ॱˊ).ॱ.ʻ();
      ((Mw)this.ॱˊ).ॱ(localHQ.ˊᐝ());
    }
  }
  
  private void ʾ()
  {
    break label127;
    return;
    int i;
    for (;;)
    {
      switch (i)
      {
      case 1: 
      default: 
        return;
        i = ˊˊ + 7;
        ˋˊ = i % 128;
        if (i % 2 != 0) {
          break;
        }
        break;
      case 0: 
        i = null.length;
        return;
        label60:
        i = ˊˊ + 5;
        ˋˊ = i % 128;
        if (i % 2 != 0) {
          break label138;
        }
        break;
      }
      i = 0;
    }
    label127:
    label138:
    for (;;)
    {
      try
      {
        Object localObject = this.ॱˊ;
        localObject = (Mw)localObject;
        localObject = ((Mw)localObject).ॱ;
        localObject = ((KZ)localObject).ॱॱ();
        localObject = HQ.ˏ((MatrixHCECard)localObject);
        ॱ(((HQ)localObject).ॱॱ());
      }
      catch (Exception localException)
      {
        throw localException;
      }
      break label60;
      i = 1;
      break;
    }
  }
  
  /* Error */
  private ArrayList<HG> ˊ(FT paramFT)
  {
    // Byte code:
    //   0: goto +167 -> 167
    //   3: getstatic 146	o/Ep:UNKNOWN	Lo/Ep;
    //   6: astore_3
    //   7: goto +71 -> 78
    //   10: iconst_0
    //   11: istore_2
    //   12: goto +130 -> 142
    //   15: astore_1
    //   16: aload_1
    //   17: athrow
    //   18: getstatic 146	o/Ep:UNKNOWN	Lo/Ep;
    //   21: astore_3
    //   22: aconst_null
    //   23: arraylength
    //   24: istore_2
    //   25: goto +53 -> 78
    //   28: getstatic 28	o/Md:ˊˊ	I
    //   31: istore_2
    //   32: iload_2
    //   33: bipush 59
    //   35: iadd
    //   36: istore_2
    //   37: iload_2
    //   38: sipush 128
    //   41: irem
    //   42: putstatic 26	o/Md:ˋˊ	I
    //   45: iload_2
    //   46: iconst_2
    //   47: irem
    //   48: ifeq +6 -> 54
    //   51: goto -41 -> 10
    //   54: goto +141 -> 195
    //   57: iconst_1
    //   58: istore_2
    //   59: goto +111 -> 170
    //   62: aload_3
    //   63: invokevirtual 149	o/HQ:ʻ	()Lo/Ep;
    //   66: astore_3
    //   67: goto +48 -> 115
    //   70: iconst_0
    //   71: istore_2
    //   72: goto +98 -> 170
    //   75: goto +325 -> 400
    //   78: aload 4
    //   80: aload 5
    //   82: aload_3
    //   83: invokevirtual 155	o/HF:ˋ	(Lo/Ep;)Lo/HG;
    //   86: invokevirtual 161	java/util/ArrayList:add	(Ljava/lang/Object;)Z
    //   89: pop
    //   90: aload 4
    //   92: getstatic 164	o/HF:ˊ	Lo/HF$If;
    //   95: invokevirtual 169	o/HF$If:ˊ	()Lo/HF;
    //   98: getstatic 175	o/FY:BETWEEN_CARDS	Lo/FY;
    //   101: aload_1
    //   102: invokevirtual 178	o/HF:ॱ	(Lo/FY;Lo/FT;)Lo/HG;
    //   105: invokevirtual 161	java/util/ArrayList:add	(Ljava/lang/Object;)Z
    //   108: pop
    //   109: aload 4
    //   111: areturn
    //   112: astore_1
    //   113: aload_1
    //   114: athrow
    //   115: getstatic 28	o/Md:ˊˊ	I
    //   118: bipush 79
    //   120: iadd
    //   121: istore_2
    //   122: iload_2
    //   123: sipush 128
    //   126: irem
    //   127: putstatic 26	o/Md:ˋˊ	I
    //   130: iload_2
    //   131: iconst_2
    //   132: irem
    //   133: ifeq +6 -> 139
    //   136: goto -61 -> 75
    //   139: goto +261 -> 400
    //   142: iload_2
    //   143: tableswitch	default:+21->164, 0:+-125->18, 1:+-140->3
    //   164: goto -161 -> 3
    //   167: goto +33 -> 200
    //   170: iload_2
    //   171: tableswitch	default:+21->192, 0:+-109->62, 1:+-143->28
    //   192: goto -164 -> 28
    //   195: iconst_1
    //   196: istore_2
    //   197: goto -55 -> 142
    //   200: goto +17 -> 217
    //   203: astore_1
    //   204: aload_1
    //   205: invokevirtual 184	java/lang/Throwable:getCause	()Ljava/lang/Throwable;
    //   208: astore_3
    //   209: aload_3
    //   210: ifnull +5 -> 215
    //   213: aload_3
    //   214: athrow
    //   215: aload_1
    //   216: athrow
    //   217: aload_0
    //   218: invokevirtual 190	android/content/Context:getApplicationInfo	()Landroid/content/pm/ApplicationInfo;
    //   221: getfield 195	android/content/pm/ApplicationInfo:targetSdkVersion	I
    //   224: bipush 21
    //   226: isub
    //   227: aload_0
    //   228: invokevirtual 190	android/content/Context:getApplicationInfo	()Landroid/content/pm/ApplicationInfo;
    //   231: getfield 195	android/content/pm/ApplicationInfo:targetSdkVersion	I
    //   234: sipush 242
    //   237: iadd
    //   238: aload_0
    //   239: invokevirtual 198	android/content/Context:getPackageName	()Ljava/lang/String;
    //   242: invokevirtual 204	java/lang/String:length	()I
    //   245: sipush 14777
    //   248: iadd
    //   249: i2c
    //   250: invokestatic 209	o/O:ˋ	(IIC)Ljava/lang/Object;
    //   253: checkcast 211	java/lang/Class
    //   256: ldc -44
    //   258: aconst_null
    //   259: invokevirtual 216	java/lang/Class:getMethod	(Ljava/lang/String;[Ljava/lang/Class;)Ljava/lang/reflect/Method;
    //   262: aconst_null
    //   263: aconst_null
    //   264: invokevirtual 222	java/lang/reflect/Method:invoke	(Ljava/lang/Object;[Ljava/lang/Object;)Ljava/lang/Object;
    //   267: astore_3
    //   268: goto +17 -> 285
    //   271: astore_1
    //   272: aload_1
    //   273: invokevirtual 184	java/lang/Throwable:getCause	()Ljava/lang/Throwable;
    //   276: astore_3
    //   277: aload_3
    //   278: ifnull +5 -> 283
    //   281: aload_3
    //   282: athrow
    //   283: aload_1
    //   284: athrow
    //   285: aload_0
    //   286: invokevirtual 226	android/content/Context:getResources	()Landroid/content/res/Resources;
    //   289: ldc -29
    //   291: invokevirtual 233	android/content/res/Resources:getString	(I)Ljava/lang/String;
    //   294: iconst_0
    //   295: iconst_4
    //   296: invokevirtual 237	java/lang/String:substring	(II)Ljava/lang/String;
    //   299: invokevirtual 204	java/lang/String:length	()I
    //   302: iconst_0
    //   303: iadd
    //   304: aload_0
    //   305: invokevirtual 226	android/content/Context:getResources	()Landroid/content/res/Resources;
    //   308: ldc -18
    //   310: invokevirtual 233	android/content/res/Resources:getString	(I)Ljava/lang/String;
    //   313: iconst_0
    //   314: iconst_4
    //   315: invokevirtual 237	java/lang/String:substring	(II)Ljava/lang/String;
    //   318: invokevirtual 204	java/lang/String:length	()I
    //   321: sipush 263
    //   324: iadd
    //   325: aload_0
    //   326: invokevirtual 226	android/content/Context:getResources	()Landroid/content/res/Resources;
    //   329: ldc -17
    //   331: invokevirtual 233	android/content/res/Resources:getString	(I)Ljava/lang/String;
    //   334: iconst_0
    //   335: iconst_5
    //   336: invokevirtual 237	java/lang/String:substring	(II)Ljava/lang/String;
    //   339: iconst_3
    //   340: invokevirtual 243	java/lang/String:codePointAt	(I)I
    //   343: sipush 14776
    //   346: iadd
    //   347: i2c
    //   348: invokestatic 209	o/O:ˋ	(IIC)Ljava/lang/Object;
    //   351: checkcast 211	java/lang/Class
    //   354: ldc -12
    //   356: aconst_null
    //   357: invokevirtual 216	java/lang/Class:getMethod	(Ljava/lang/String;[Ljava/lang/Class;)Ljava/lang/reflect/Method;
    //   360: aload_3
    //   361: aconst_null
    //   362: invokevirtual 222	java/lang/reflect/Method:invoke	(Ljava/lang/Object;[Ljava/lang/Object;)Ljava/lang/Object;
    //   365: checkcast 116	o/HQ
    //   368: astore_3
    //   369: new 157	java/util/ArrayList
    //   372: dup
    //   373: invokespecial 245	java/util/ArrayList:<init>	()V
    //   376: astore 4
    //   378: getstatic 164	o/HF:ˊ	Lo/HF$If;
    //   381: astore 5
    //   383: aload 5
    //   385: invokevirtual 169	o/HF$If:ˊ	()Lo/HF;
    //   388: astore 5
    //   390: aload_3
    //   391: ifnonnull +6 -> 397
    //   394: goto -337 -> 57
    //   397: goto -327 -> 70
    //   400: goto -322 -> 78
    // Local variable table:
    //   start	length	slot	name	signature
    //   0	403	0	this	Md
    //   0	403	1	paramFT	FT
    //   11	186	2	i	int
    //   6	385	3	localObject1	Object
    //   78	299	4	localObject2	Object
    //   80	309	5	localObject3	Object
    // Exception table:
    //   from	to	target	type
    //   28	32	15	java/lang/Exception
    //   204	209	112	java/lang/Exception
    //   213	215	112	java/lang/Exception
    //   215	217	112	java/lang/Exception
    //   272	277	112	java/lang/Exception
    //   281	283	112	java/lang/Exception
    //   283	285	112	java/lang/Exception
    //   369	378	112	java/lang/Exception
    //   378	383	112	java/lang/Exception
    //   383	390	112	java/lang/Exception
    //   217	268	203	finally
    //   285	369	271	finally
  }
  
  private static String ˎ(short paramShort, int paramInt1, byte paramByte, int paramInt2, int paramInt3)
  {
    break label243;
    int k = ˊˊ + 111;
    ˋˊ = k % 128;
    label39:
    Object localObject2;
    int j;
    int i;
    label70:
    int m;
    if (k % 2 == 0)
    {
      break label70;
      paramInt3 = 1;
      break label215;
      localObject2 = ˉ;
      j = paramInt1 - 1;
      i = (char)(((byte)(localObject2[paramInt1] + paramShort) ^ paramByte) + k);
      paramInt1 = j;
      break label302;
      m = ʼॱ;
      if (j == 0) {
        break label406;
      }
      j = 1;
      break label452;
    }
    for (;;)
    {
      try
      {
        paramInt3 = ˊˊ;
        paramInt3 += 25;
        ˋˊ = paramInt3 % 128;
        if (paramInt3 % 2 != 0) {
          break;
        }
        continue;
        k = ˊˊ + 83;
        ˋˊ = k % 128;
        if (k % 2 != 0) {
          break label628;
        }
        try
        {
          localObject2 = ˉ;
          if (localObject2 != null) {
            break label39;
          }
        }
        catch (Exception localException1)
        {
          Object localObject1;
          throw localException1;
        }
        return localObject1.toString();
        label178:
        if (paramInt3 > 0) {
          break label412;
        }
        continue;
        label189:
        switch (j)
        {
        }
        continue;
        switch (paramInt3)
        {
        default: 
          continue;
          break label559;
          paramInt3 = 0;
          continue;
          continue;
          j = k;
          break label452;
          k = 30;
          break label490;
          j = 0;
          break;
        case 0: 
          label215:
          label243:
          label269:
          if (ˉ != null) {
            break label387;
          }
          break;
        }
      }
      catch (Exception localException2)
      {
        label287:
        label293:
        label302:
        label317:
        label347:
        throw localException2;
      }
      j = 0;
      continue;
      j = 1;
      break label376;
      break label70;
      localObject1.append(i);
      paramInt2 += 1;
      break label631;
      switch (j)
      {
      case 10: 
      default: 
        break label621;
        j = 10;
        break;
      }
      for (;;)
      {
        label364:
        if (paramInt2 < paramInt3) {
          break label287;
        }
        break label553;
        label376:
        if (j != 0) {
          break;
        }
        break label178;
        label387:
        paramInt3 = (byte)(ˉ[(ʼॱ + paramInt1)] + ʾ);
        break label178;
        label406:
        k = 0;
        break label523;
        label412:
        k = 85;
        break label490;
        localObject2 = ˊᐝ;
        j = paramInt1 - 1;
        paramInt1 = localObject2[paramInt1];
        i = (char)(((short)(paramInt1 + paramShort) ^ paramByte) + k);
        paramInt1 = j;
        break label302;
        for (;;)
        {
          label452:
          paramInt1 = paramInt1 + paramInt3 - 2 + m + j;
          i = (char)(ˊˋ + paramInt2);
          localException2.append(i);
          paramInt2 = 1;
          k = i;
          break label364;
          label490:
          switch (k)
          {
          }
          break;
          label523:
          j = ˋˊ + 117;
          ˊˊ = j % 128;
          if (j % 2 != 0)
          {
            break label347;
            label553:
            j = 1;
            break label189;
            label559:
            StringBuilder localStringBuilder = new StringBuilder();
            j = ʾ + paramInt3;
            paramInt3 = j;
            if (j == -1) {
              break label293;
            }
            break label269;
          }
          j = 16;
          break label317;
          localObject2 = ˉ;
          paramInt3 = 17 / 0;
          if (localObject2 != null) {
            break label387;
          }
          break label638;
          label621:
          j = k;
        }
        label628:
        break label178;
        label631:
        k = i;
      }
      label638:
      paramInt3 = (short)(ˊᐝ[(ʼॱ + paramInt1)] + ʾ);
    }
  }
  
  private List<MatrixHCECard> ॱ(List<MatrixHCECard> paramList, String paramString)
  {
    break label144;
    label3:
    break label40;
    int i;
    Object localObject1;
    label35:
    label40:
    Object localObject2;
    switch (i)
    {
    default: 
      return localObject1;
      i = 1;
      break;
      break label227;
      ((ArrayList)localObject1).add(localObject2);
      break label95;
      if (paramList.hasNext()) {}
      break;
    case 0: 
      for (;;)
      {
        label54:
        switch (i)
        {
        case 0: 
        default: 
          break label227;
          label95:
          i = ˋˊ + 73;
          ˊˊ = i % 128;
          if (i % 2 == 0) {
            break label3;
          }
          break label40;
          label141:
          label144:
          for (;;)
          {
            localObject1 = new ArrayList();
            paramList = paramList.iterator();
            break;
            break;
          }
          return localObject1;
          label150:
          i = 0;
        }
      }
    }
    label219:
    label227:
    for (;;)
    {
      i = ˋˊ + 43;
      ˊˊ = i % 128;
      if (i % 2 == 0) {
        break label141;
      }
      break label219;
      i = 0;
      break;
      localObject2 = (MatrixHCECard)paramList.next();
      if (!HQ.ˏ((MatrixHCECard)localObject2).ॱॱ().equalsIgnoreCase(paramString)) {
        break label150;
      }
      break label35;
      break label54;
      i = 1;
      break;
    }
  }
  
  /* Error */
  private void ॱ(String paramString)
  {
    // Byte code:
    //   0: goto +190 -> 190
    //   3: aload_0
    //   4: getfield 289	o/Md:ʿ	Lo/Gh;
    //   7: aload_1
    //   8: putfield 294	o/Gh:toCardUuid	Ljava/lang/String;
    //   11: aload_3
    //   12: iconst_0
    //   13: aload_0
    //   14: invokevirtual 226	android/content/Context:getResources	()Landroid/content/res/Resources;
    //   17: ldc_w 295
    //   20: invokevirtual 233	android/content/res/Resources:getString	(I)Ljava/lang/String;
    //   23: iconst_0
    //   24: iconst_5
    //   25: invokevirtual 237	java/lang/String:substring	(II)Ljava/lang/String;
    //   28: iconst_2
    //   29: invokevirtual 243	java/lang/String:codePointAt	(I)I
    //   32: ldc_w 296
    //   35: isub
    //   36: aload_0
    //   37: invokevirtual 226	android/content/Context:getResources	()Landroid/content/res/Resources;
    //   40: ldc_w 297
    //   43: invokevirtual 233	android/content/res/Resources:getString	(I)Ljava/lang/String;
    //   46: iconst_0
    //   47: iconst_4
    //   48: invokevirtual 237	java/lang/String:substring	(II)Ljava/lang/String;
    //   51: iconst_2
    //   52: invokevirtual 243	java/lang/String:codePointAt	(I)I
    //   55: bipush 8
    //   57: iadd
    //   58: i2b
    //   59: ldc_w 298
    //   62: aload_0
    //   63: invokevirtual 198	android/content/Context:getPackageName	()Ljava/lang/String;
    //   66: bipush 6
    //   68: invokevirtual 243	java/lang/String:codePointAt	(I)I
    //   71: sipush 189
    //   74: isub
    //   75: invokestatic 300	o/Md:ˎ	(SIBII)Ljava/lang/String;
    //   78: invokevirtual 303	java/lang/String:intern	()Ljava/lang/String;
    //   81: aload_0
    //   82: getfield 289	o/Md:ʿ	Lo/Gh;
    //   85: invokevirtual 309	android/os/Bundle:putParcelable	(Ljava/lang/String;Landroid/os/Parcelable;)V
    //   88: aload_3
    //   89: iconst_0
    //   90: aload_0
    //   91: invokevirtual 190	android/content/Context:getApplicationInfo	()Landroid/content/pm/ApplicationInfo;
    //   94: getfield 195	android/content/pm/ApplicationInfo:targetSdkVersion	I
    //   97: ldc_w 310
    //   100: isub
    //   101: aload_0
    //   102: invokevirtual 226	android/content/Context:getResources	()Landroid/content/res/Resources;
    //   105: ldc_w 311
    //   108: invokevirtual 233	android/content/res/Resources:getString	(I)Ljava/lang/String;
    //   111: iconst_0
    //   112: bipush 8
    //   114: invokevirtual 237	java/lang/String:substring	(II)Ljava/lang/String;
    //   117: invokevirtual 204	java/lang/String:length	()I
    //   120: bipush 74
    //   122: isub
    //   123: i2b
    //   124: ldc_w 298
    //   127: aload_0
    //   128: invokevirtual 226	android/content/Context:getResources	()Landroid/content/res/Resources;
    //   131: ldc_w 312
    //   134: invokevirtual 233	android/content/res/Resources:getString	(I)Ljava/lang/String;
    //   137: iconst_0
    //   138: iconst_4
    //   139: invokevirtual 237	java/lang/String:substring	(II)Ljava/lang/String;
    //   142: iconst_0
    //   143: invokevirtual 243	java/lang/String:codePointAt	(I)I
    //   146: bipush 81
    //   148: isub
    //   149: invokestatic 300	o/Md:ˎ	(SIBII)Ljava/lang/String;
    //   152: invokevirtual 303	java/lang/String:intern	()Ljava/lang/String;
    //   155: aload_0
    //   156: getfield 314	o/Md:ʽॱ	Ljava/lang/String;
    //   159: invokevirtual 318	android/os/Bundle:putString	(Ljava/lang/String;Ljava/lang/String;)V
    //   162: aload 4
    //   164: aload_3
    //   165: invokevirtual 324	android/content/Intent:putExtras	(Landroid/os/Bundle;)Landroid/content/Intent;
    //   168: pop
    //   169: aload_0
    //   170: iconst_m1
    //   171: aload 4
    //   173: invokevirtual 328	o/Md:setResult	(ILandroid/content/Intent;)V
    //   176: aload_0
    //   177: invokevirtual 331	o/Md:finish	()V
    //   180: goto +472 -> 652
    //   183: goto +982 -> 1165
    //   186: return
    //   187: goto +496 -> 683
    //   190: goto +885 -> 1075
    //   193: astore_1
    //   194: aload_1
    //   195: athrow
    //   196: bipush 90
    //   198: iconst_0
    //   199: idiv
    //   200: istore_2
    //   201: return
    //   202: aload_0
    //   203: getfield 289	o/Md:ʿ	Lo/Gh;
    //   206: aload_1
    //   207: putfield 334	o/Gh:fromCardUuid	Ljava/lang/String;
    //   210: goto +17 -> 227
    //   213: astore_1
    //   214: aload_1
    //   215: invokevirtual 184	java/lang/Throwable:getCause	()Ljava/lang/Throwable;
    //   218: astore_3
    //   219: aload_3
    //   220: ifnull +5 -> 225
    //   223: aload_3
    //   224: athrow
    //   225: aload_1
    //   226: athrow
    //   227: aload_0
    //   228: invokevirtual 198	android/content/Context:getPackageName	()Ljava/lang/String;
    //   231: iconst_4
    //   232: invokevirtual 243	java/lang/String:codePointAt	(I)I
    //   235: bipush 112
    //   237: isub
    //   238: aload_0
    //   239: invokevirtual 226	android/content/Context:getResources	()Landroid/content/res/Resources;
    //   242: ldc_w 335
    //   245: invokevirtual 233	android/content/res/Resources:getString	(I)Ljava/lang/String;
    //   248: iconst_0
    //   249: iconst_5
    //   250: invokevirtual 237	java/lang/String:substring	(II)Ljava/lang/String;
    //   253: invokevirtual 204	java/lang/String:length	()I
    //   256: sipush 262
    //   259: iadd
    //   260: aload_0
    //   261: invokevirtual 198	android/content/Context:getPackageName	()Ljava/lang/String;
    //   264: bipush 8
    //   266: invokevirtual 243	java/lang/String:codePointAt	(I)I
    //   269: sipush 14676
    //   272: iadd
    //   273: i2c
    //   274: invokestatic 209	o/O:ˋ	(IIC)Ljava/lang/Object;
    //   277: checkcast 211	java/lang/Class
    //   280: ldc -44
    //   282: aconst_null
    //   283: invokevirtual 216	java/lang/Class:getMethod	(Ljava/lang/String;[Ljava/lang/Class;)Ljava/lang/reflect/Method;
    //   286: aconst_null
    //   287: aconst_null
    //   288: invokevirtual 222	java/lang/reflect/Method:invoke	(Ljava/lang/Object;[Ljava/lang/Object;)Ljava/lang/Object;
    //   291: astore 4
    //   293: goto +17 -> 310
    //   296: astore_1
    //   297: aload_1
    //   298: invokevirtual 184	java/lang/Throwable:getCause	()Ljava/lang/Throwable;
    //   301: astore_3
    //   302: aload_3
    //   303: ifnull +5 -> 308
    //   306: aload_3
    //   307: athrow
    //   308: aload_1
    //   309: athrow
    //   310: aload_0
    //   311: invokevirtual 226	android/content/Context:getResources	()Landroid/content/res/Resources;
    //   314: ldc_w 336
    //   317: invokevirtual 233	android/content/res/Resources:getString	(I)Ljava/lang/String;
    //   320: iconst_0
    //   321: iconst_4
    //   322: invokevirtual 237	java/lang/String:substring	(II)Ljava/lang/String;
    //   325: iconst_1
    //   326: invokevirtual 243	java/lang/String:codePointAt	(I)I
    //   329: bipush 22
    //   331: isub
    //   332: aload_0
    //   333: invokevirtual 226	android/content/Context:getResources	()Landroid/content/res/Resources;
    //   336: ldc_w 337
    //   339: invokevirtual 233	android/content/res/Resources:getString	(I)Ljava/lang/String;
    //   342: iconst_0
    //   343: iconst_5
    //   344: invokevirtual 237	java/lang/String:substring	(II)Ljava/lang/String;
    //   347: iconst_1
    //   348: invokevirtual 243	java/lang/String:codePointAt	(I)I
    //   351: sipush 241
    //   354: iadd
    //   355: aload_0
    //   356: invokevirtual 226	android/content/Context:getResources	()Landroid/content/res/Resources;
    //   359: ldc_w 338
    //   362: invokevirtual 233	android/content/res/Resources:getString	(I)Ljava/lang/String;
    //   365: iconst_0
    //   366: iconst_4
    //   367: invokevirtual 237	java/lang/String:substring	(II)Ljava/lang/String;
    //   370: invokevirtual 204	java/lang/String:length	()I
    //   373: sipush 14784
    //   376: iadd
    //   377: i2c
    //   378: invokestatic 209	o/O:ˋ	(IIC)Ljava/lang/Object;
    //   381: checkcast 211	java/lang/Class
    //   384: ldc_w 339
    //   387: iconst_1
    //   388: anewarray 211	java/lang/Class
    //   391: dup
    //   392: iconst_0
    //   393: ldc -56
    //   395: aastore
    //   396: invokevirtual 216	java/lang/Class:getMethod	(Ljava/lang/String;[Ljava/lang/Class;)Ljava/lang/reflect/Method;
    //   399: aload 4
    //   401: iconst_1
    //   402: anewarray 341	java/lang/Object
    //   405: dup
    //   406: iconst_0
    //   407: aload_1
    //   408: aastore
    //   409: invokevirtual 222	java/lang/reflect/Method:invoke	(Ljava/lang/Object;[Ljava/lang/Object;)Ljava/lang/Object;
    //   412: checkcast 282	com/insidesecure/hce/MatrixHCECard
    //   415: astore_1
    //   416: aload_1
    //   417: invokestatic 132	o/HQ:ˏ	(Lcom/insidesecure/hce/MatrixHCECard;)Lo/HQ;
    //   420: astore_1
    //   421: aload_0
    //   422: getfield 289	o/Md:ʿ	Lo/Gh;
    //   425: aload_1
    //   426: invokevirtual 149	o/HQ:ʻ	()Lo/Ep;
    //   429: putfield 344	o/Gh:currency	Lo/Ep;
    //   432: aload_3
    //   433: iconst_0
    //   434: aload_0
    //   435: invokevirtual 226	android/content/Context:getResources	()Landroid/content/res/Resources;
    //   438: ldc_w 345
    //   441: invokevirtual 233	android/content/res/Resources:getString	(I)Ljava/lang/String;
    //   444: iconst_0
    //   445: iconst_4
    //   446: invokevirtual 237	java/lang/String:substring	(II)Ljava/lang/String;
    //   449: invokevirtual 204	java/lang/String:length	()I
    //   452: ldc_w 310
    //   455: isub
    //   456: aload_0
    //   457: invokevirtual 226	android/content/Context:getResources	()Landroid/content/res/Resources;
    //   460: ldc_w 346
    //   463: invokevirtual 233	android/content/res/Resources:getString	(I)Ljava/lang/String;
    //   466: iconst_0
    //   467: iconst_5
    //   468: invokevirtual 237	java/lang/String:substring	(II)Ljava/lang/String;
    //   471: invokevirtual 204	java/lang/String:length	()I
    //   474: bipush 14
    //   476: iadd
    //   477: i2b
    //   478: ldc_w 298
    //   481: aload_0
    //   482: invokevirtual 226	android/content/Context:getResources	()Landroid/content/res/Resources;
    //   485: ldc_w 347
    //   488: invokevirtual 233	android/content/res/Resources:getString	(I)Ljava/lang/String;
    //   491: iconst_0
    //   492: iconst_4
    //   493: invokevirtual 237	java/lang/String:substring	(II)Ljava/lang/String;
    //   496: iconst_1
    //   497: invokevirtual 243	java/lang/String:codePointAt	(I)I
    //   500: bipush 107
    //   502: isub
    //   503: invokestatic 300	o/Md:ˎ	(SIBII)Ljava/lang/String;
    //   506: invokevirtual 303	java/lang/String:intern	()Ljava/lang/String;
    //   509: aload_0
    //   510: getfield 289	o/Md:ʿ	Lo/Gh;
    //   513: invokevirtual 309	android/os/Bundle:putParcelable	(Ljava/lang/String;Landroid/os/Parcelable;)V
    //   516: aload_3
    //   517: iconst_0
    //   518: aload_0
    //   519: invokevirtual 198	android/content/Context:getPackageName	()Ljava/lang/String;
    //   522: invokevirtual 204	java/lang/String:length	()I
    //   525: ldc_w 348
    //   528: isub
    //   529: aload_0
    //   530: invokevirtual 190	android/content/Context:getApplicationInfo	()Landroid/content/pm/ApplicationInfo;
    //   533: getfield 195	android/content/pm/ApplicationInfo:targetSdkVersion	I
    //   536: bipush 91
    //   538: isub
    //   539: i2b
    //   540: ldc_w 298
    //   543: aload_0
    //   544: invokevirtual 226	android/content/Context:getResources	()Landroid/content/res/Resources;
    //   547: ldc_w 349
    //   550: invokevirtual 233	android/content/res/Resources:getString	(I)Ljava/lang/String;
    //   553: iconst_0
    //   554: iconst_4
    //   555: invokevirtual 237	java/lang/String:substring	(II)Ljava/lang/String;
    //   558: invokevirtual 204	java/lang/String:length	()I
    //   561: bipush 80
    //   563: isub
    //   564: invokestatic 300	o/Md:ˎ	(SIBII)Ljava/lang/String;
    //   567: invokevirtual 303	java/lang/String:intern	()Ljava/lang/String;
    //   570: aload_0
    //   571: getfield 314	o/Md:ʽॱ	Ljava/lang/String;
    //   574: invokevirtual 318	android/os/Bundle:putString	(Ljava/lang/String;Ljava/lang/String;)V
    //   577: aload_3
    //   578: iconst_0
    //   579: aload_0
    //   580: invokevirtual 226	android/content/Context:getResources	()Landroid/content/res/Resources;
    //   583: ldc_w 350
    //   586: invokevirtual 233	android/content/res/Resources:getString	(I)Ljava/lang/String;
    //   589: iconst_0
    //   590: iconst_4
    //   591: invokevirtual 237	java/lang/String:substring	(II)Ljava/lang/String;
    //   594: invokevirtual 204	java/lang/String:length	()I
    //   597: ldc_w 351
    //   600: isub
    //   601: aload_0
    //   602: invokevirtual 190	android/content/Context:getApplicationInfo	()Landroid/content/pm/ApplicationInfo;
    //   605: getfield 195	android/content/pm/ApplicationInfo:targetSdkVersion	I
    //   608: bipush 96
    //   610: iadd
    //   611: i2b
    //   612: ldc_w 298
    //   615: aload_0
    //   616: invokevirtual 190	android/content/Context:getApplicationInfo	()Landroid/content/pm/ApplicationInfo;
    //   619: getfield 195	android/content/pm/ApplicationInfo:targetSdkVersion	I
    //   622: bipush 106
    //   624: isub
    //   625: invokestatic 300	o/Md:ˎ	(SIBII)Ljava/lang/String;
    //   628: invokevirtual 303	java/lang/String:intern	()Ljava/lang/String;
    //   631: iconst_1
    //   632: invokevirtual 355	android/os/Bundle:putInt	(Ljava/lang/String;I)V
    //   635: aload_0
    //   636: invokestatic 360	o/Ic:ˏ	(Landroid/content/Context;)Lo/Ic;
    //   639: invokevirtual 363	o/Ic:ʾ	()Lo/j;
    //   642: aload_3
    //   643: invokevirtual 368	o/j:ˊ	(Landroid/os/Bundle;)Lo/j;
    //   646: invokevirtual 370	o/j:ˎ	()V
    //   649: goto +34 -> 683
    //   652: getstatic 26	o/Md:ˋˊ	I
    //   655: bipush 37
    //   657: iadd
    //   658: istore_2
    //   659: iload_2
    //   660: sipush 128
    //   663: irem
    //   664: putstatic 28	o/Md:ˊˊ	I
    //   667: iload_2
    //   668: iconst_2
    //   669: irem
    //   670: ifne +6 -> 676
    //   673: goto -490 -> 183
    //   676: goto +489 -> 1165
    //   679: aload_0
    //   680: invokevirtual 331	o/Md:finish	()V
    //   683: goto +184 -> 867
    //   686: astore_1
    //   687: aload_1
    //   688: athrow
    //   689: aload_0
    //   690: getfield 289	o/Md:ʿ	Lo/Gh;
    //   693: astore 4
    //   695: aload 4
    //   697: aload_1
    //   698: putfield 294	o/Gh:toCardUuid	Ljava/lang/String;
    //   701: aload_0
    //   702: invokevirtual 190	android/content/Context:getApplicationInfo	()Landroid/content/pm/ApplicationInfo;
    //   705: astore_1
    //   706: aload_1
    //   707: getfield 195	android/content/pm/ApplicationInfo:targetSdkVersion	I
    //   710: istore_2
    //   711: aload_3
    //   712: iconst_0
    //   713: iload_2
    //   714: ldc_w 351
    //   717: isub
    //   718: aload_0
    //   719: invokevirtual 226	android/content/Context:getResources	()Landroid/content/res/Resources;
    //   722: ldc_w 371
    //   725: invokevirtual 233	android/content/res/Resources:getString	(I)Ljava/lang/String;
    //   728: iconst_0
    //   729: iconst_5
    //   730: invokevirtual 237	java/lang/String:substring	(II)Ljava/lang/String;
    //   733: invokevirtual 204	java/lang/String:length	()I
    //   736: bipush 14
    //   738: iadd
    //   739: i2b
    //   740: ldc_w 298
    //   743: aload_0
    //   744: invokevirtual 226	android/content/Context:getResources	()Landroid/content/res/Resources;
    //   747: ldc_w 372
    //   750: invokevirtual 233	android/content/res/Resources:getString	(I)Ljava/lang/String;
    //   753: iconst_0
    //   754: iconst_4
    //   755: invokevirtual 237	java/lang/String:substring	(II)Ljava/lang/String;
    //   758: invokevirtual 204	java/lang/String:length	()I
    //   761: bipush 85
    //   763: isub
    //   764: invokestatic 300	o/Md:ˎ	(SIBII)Ljava/lang/String;
    //   767: invokevirtual 303	java/lang/String:intern	()Ljava/lang/String;
    //   770: aload_0
    //   771: getfield 289	o/Md:ʿ	Lo/Gh;
    //   774: invokevirtual 309	android/os/Bundle:putParcelable	(Ljava/lang/String;Landroid/os/Parcelable;)V
    //   777: aload_3
    //   778: iconst_0
    //   779: aload_0
    //   780: invokevirtual 226	android/content/Context:getResources	()Landroid/content/res/Resources;
    //   783: ldc_w 373
    //   786: invokevirtual 233	android/content/res/Resources:getString	(I)Ljava/lang/String;
    //   789: iconst_0
    //   790: iconst_4
    //   791: invokevirtual 237	java/lang/String:substring	(II)Ljava/lang/String;
    //   794: invokevirtual 204	java/lang/String:length	()I
    //   797: ldc_w 374
    //   800: isub
    //   801: aload_0
    //   802: invokevirtual 190	android/content/Context:getApplicationInfo	()Landroid/content/pm/ApplicationInfo;
    //   805: getfield 195	android/content/pm/ApplicationInfo:targetSdkVersion	I
    //   808: bipush 91
    //   810: isub
    //   811: i2b
    //   812: ldc_w 298
    //   815: aload_0
    //   816: invokevirtual 226	android/content/Context:getResources	()Landroid/content/res/Resources;
    //   819: ldc_w 375
    //   822: invokevirtual 233	android/content/res/Resources:getString	(I)Ljava/lang/String;
    //   825: iconst_0
    //   826: bipush 17
    //   828: invokevirtual 237	java/lang/String:substring	(II)Ljava/lang/String;
    //   831: invokevirtual 204	java/lang/String:length	()I
    //   834: bipush 93
    //   836: isub
    //   837: invokestatic 300	o/Md:ˎ	(SIBII)Ljava/lang/String;
    //   840: invokevirtual 303	java/lang/String:intern	()Ljava/lang/String;
    //   843: aload_0
    //   844: getfield 314	o/Md:ʽॱ	Ljava/lang/String;
    //   847: invokevirtual 318	android/os/Bundle:putString	(Ljava/lang/String;Ljava/lang/String;)V
    //   850: aload_0
    //   851: invokestatic 360	o/Ic:ˏ	(Landroid/content/Context;)Lo/Ic;
    //   854: invokevirtual 377	o/Ic:ʼॱ	()Lo/j;
    //   857: aload_3
    //   858: invokevirtual 368	o/j:ˊ	(Landroid/os/Bundle;)Lo/j;
    //   861: invokevirtual 370	o/j:ˎ	()V
    //   864: goto -181 -> 683
    //   867: getstatic 26	o/Md:ˋˊ	I
    //   870: bipush 39
    //   872: iadd
    //   873: istore_2
    //   874: iload_2
    //   875: sipush 128
    //   878: irem
    //   879: putstatic 28	o/Md:ˊˊ	I
    //   882: iload_2
    //   883: iconst_2
    //   884: irem
    //   885: ifne +6 -> 891
    //   888: goto +247 -> 1135
    //   891: goto +178 -> 1069
    //   894: aload_0
    //   895: getfield 289	o/Md:ʿ	Lo/Gh;
    //   898: aload_1
    //   899: putfield 334	o/Gh:fromCardUuid	Ljava/lang/String;
    //   902: aload_3
    //   903: iconst_0
    //   904: aload_0
    //   905: invokevirtual 190	android/content/Context:getApplicationInfo	()Landroid/content/pm/ApplicationInfo;
    //   908: getfield 195	android/content/pm/ApplicationInfo:targetSdkVersion	I
    //   911: ldc_w 351
    //   914: isub
    //   915: aload_0
    //   916: invokevirtual 198	android/content/Context:getPackageName	()Ljava/lang/String;
    //   919: invokevirtual 204	java/lang/String:length	()I
    //   922: bipush 8
    //   924: iadd
    //   925: i2b
    //   926: ldc_w 298
    //   929: aload_0
    //   930: invokevirtual 226	android/content/Context:getResources	()Landroid/content/res/Resources;
    //   933: ldc_w 378
    //   936: invokevirtual 233	android/content/res/Resources:getString	(I)Ljava/lang/String;
    //   939: iconst_0
    //   940: iconst_4
    //   941: invokevirtual 237	java/lang/String:substring	(II)Ljava/lang/String;
    //   944: iconst_2
    //   945: invokevirtual 243	java/lang/String:codePointAt	(I)I
    //   948: bipush 92
    //   950: isub
    //   951: invokestatic 300	o/Md:ˎ	(SIBII)Ljava/lang/String;
    //   954: invokevirtual 303	java/lang/String:intern	()Ljava/lang/String;
    //   957: aload_0
    //   958: getfield 289	o/Md:ʿ	Lo/Gh;
    //   961: invokevirtual 309	android/os/Bundle:putParcelable	(Ljava/lang/String;Landroid/os/Parcelable;)V
    //   964: aload_3
    //   965: iconst_0
    //   966: aload_0
    //   967: invokevirtual 226	android/content/Context:getResources	()Landroid/content/res/Resources;
    //   970: ldc_w 379
    //   973: invokevirtual 233	android/content/res/Resources:getString	(I)Ljava/lang/String;
    //   976: iconst_3
    //   977: iconst_4
    //   978: invokevirtual 237	java/lang/String:substring	(II)Ljava/lang/String;
    //   981: iconst_0
    //   982: invokevirtual 243	java/lang/String:codePointAt	(I)I
    //   985: ldc_w 380
    //   988: isub
    //   989: aload_0
    //   990: invokevirtual 226	android/content/Context:getResources	()Landroid/content/res/Resources;
    //   993: ldc_w 381
    //   996: invokevirtual 233	android/content/res/Resources:getString	(I)Ljava/lang/String;
    //   999: iconst_0
    //   1000: iconst_4
    //   1001: invokevirtual 237	java/lang/String:substring	(II)Ljava/lang/String;
    //   1004: invokevirtual 204	java/lang/String:length	()I
    //   1007: bipush 70
    //   1009: isub
    //   1010: i2b
    //   1011: ldc_w 298
    //   1014: aload_0
    //   1015: invokevirtual 226	android/content/Context:getResources	()Landroid/content/res/Resources;
    //   1018: ldc_w 382
    //   1021: invokevirtual 233	android/content/res/Resources:getString	(I)Ljava/lang/String;
    //   1024: iconst_0
    //   1025: iconst_4
    //   1026: invokevirtual 237	java/lang/String:substring	(II)Ljava/lang/String;
    //   1029: invokevirtual 204	java/lang/String:length	()I
    //   1032: bipush 80
    //   1034: isub
    //   1035: invokestatic 300	o/Md:ˎ	(SIBII)Ljava/lang/String;
    //   1038: invokevirtual 303	java/lang/String:intern	()Ljava/lang/String;
    //   1041: aload_0
    //   1042: getfield 314	o/Md:ʽॱ	Ljava/lang/String;
    //   1045: invokevirtual 318	android/os/Bundle:putString	(Ljava/lang/String;Ljava/lang/String;)V
    //   1048: aload 4
    //   1050: aload_3
    //   1051: invokevirtual 324	android/content/Intent:putExtras	(Landroid/os/Bundle;)Landroid/content/Intent;
    //   1054: pop
    //   1055: aload_0
    //   1056: iconst_m1
    //   1057: aload 4
    //   1059: invokevirtual 328	o/Md:setResult	(ILandroid/content/Intent;)V
    //   1062: aload_0
    //   1063: invokevirtual 331	o/Md:finish	()V
    //   1066: goto -879 -> 187
    //   1069: bipush 7
    //   1071: istore_2
    //   1072: goto +66 -> 1138
    //   1075: new 320	android/content/Intent
    //   1078: dup
    //   1079: invokespecial 383	android/content/Intent:<init>	()V
    //   1082: astore 4
    //   1084: new 305	android/os/Bundle
    //   1087: dup
    //   1088: invokespecial 384	android/os/Bundle:<init>	()V
    //   1091: astore_3
    //   1092: aload_0
    //   1093: getfield 97	o/Md:ˈ	I
    //   1096: tableswitch	default:+36->1132, 0:+-894->202, 1:+-407->689, 2:+-417->679, 3:+-202->894, 4:+-1093->3
    //   1132: goto -453 -> 679
    //   1135: bipush 49
    //   1137: istore_2
    //   1138: iload_2
    //   1139: lookupswitch	default:+25->1164, 7:+-953->186, 49:+-943->196
    //   1164: return
    //   1165: goto -482 -> 683
    // Local variable table:
    //   start	length	slot	name	signature
    //   0	1168	0	this	Md
    //   0	1168	1	paramString	String
    //   200	939	2	i	int
    //   11	1081	3	localObject1	Object
    //   162	921	4	localObject2	Object
    // Exception table:
    //   from	to	target	type
    //   689	695	193	java/lang/Exception
    //   695	701	193	java/lang/Exception
    //   701	706	193	java/lang/Exception
    //   706	711	193	java/lang/Exception
    //   711	864	193	java/lang/Exception
    //   227	293	213	finally
    //   310	416	296	finally
    //   701	706	686	java/lang/Exception
  }
  
  /* Error */
  private void ॱˋ()
  {
    // Byte code:
    //   0: goto +9 -> 9
    //   3: astore_2
    //   4: aload_2
    //   5: athrow
    //   6: astore_2
    //   7: aload_2
    //   8: athrow
    //   9: aload_0
    //   10: getfield 102	o/Md:ॱˊ	Landroid/databinding/ViewDataBinding;
    //   13: astore_2
    //   14: aload_2
    //   15: checkcast 104	o/Mw
    //   18: astore_2
    //   19: aload_2
    //   20: getfield 108	o/Mw:ॱ	Lo/KZ;
    //   23: astore_2
    //   24: aload_2
    //   25: invokevirtual 389	o/KZ:ᐝ	()Lo/aG;
    //   28: astore_2
    //   29: new 7	o/Md$4
    //   32: dup
    //   33: aload_0
    //   34: invokespecial 391	o/Md$4:<init>	(Lo/Md;)V
    //   37: astore_3
    //   38: aload_2
    //   39: aload_3
    //   40: invokevirtual 396	o/aG:ˎ	(Lo/ڏ$ˏ;)V
    //   43: getstatic 26	o/Md:ˋˊ	I
    //   46: bipush 39
    //   48: iadd
    //   49: istore_1
    //   50: iload_1
    //   51: sipush 128
    //   54: irem
    //   55: putstatic 28	o/Md:ˊˊ	I
    //   58: iload_1
    //   59: iconst_2
    //   60: irem
    //   61: ifne +4 -> 65
    //   64: return
    //   65: return
    // Local variable table:
    //   start	length	slot	name	signature
    //   0	66	0	this	Md
    //   49	12	1	i	int
    //   3	2	2	localException1	Exception
    //   6	2	2	localException2	Exception
    //   13	26	2	localObject	Object
    //   37	3	3	local4	4
    // Exception table:
    //   from	to	target	type
    //   14	19	3	java/lang/Exception
    //   9	14	6	java/lang/Exception
    //   14	19	6	java/lang/Exception
    //   19	24	6	java/lang/Exception
    //   24	38	6	java/lang/Exception
    //   38	43	6	java/lang/Exception
  }
  
  /* Error */
  public android.content.res.Resources getResources()
  {
    // Byte code:
    //   0: goto +6 -> 6
    //   3: astore_2
    //   4: aload_2
    //   5: athrow
    //   6: goto +83 -> 89
    //   9: getstatic 28	o/Md:ˊˊ	I
    //   12: bipush 57
    //   14: iadd
    //   15: istore_1
    //   16: iload_1
    //   17: sipush 128
    //   20: irem
    //   21: putstatic 26	o/Md:ˋˊ	I
    //   24: iload_1
    //   25: iconst_2
    //   26: irem
    //   27: ifeq +6 -> 33
    //   30: goto +87 -> 117
    //   33: aload_2
    //   34: areturn
    //   35: iload_1
    //   36: lookupswitch	default:+28->64, 34:+37->73, 58:+92->128
    //   64: goto +64 -> 128
    //   67: bipush 58
    //   69: istore_1
    //   70: goto -35 -> 35
    //   73: aload_0
    //   74: invokespecial 397	o/IB:getResources	()Landroid/content/res/Resources;
    //   77: invokestatic 402	o/oH:ˊ	(Landroid/content/res/Resources;)Landroid/content/res/Resources;
    //   80: astore_2
    //   81: new 404	java/lang/NullPointerException
    //   84: dup
    //   85: invokespecial 405	java/lang/NullPointerException:<init>	()V
    //   88: athrow
    //   89: getstatic 28	o/Md:ˊˊ	I
    //   92: istore_1
    //   93: iload_1
    //   94: iconst_1
    //   95: iadd
    //   96: istore_1
    //   97: iload_1
    //   98: sipush 128
    //   101: irem
    //   102: putstatic 26	o/Md:ˋˊ	I
    //   105: iload_1
    //   106: iconst_2
    //   107: irem
    //   108: ifeq +6 -> 114
    //   111: goto +11 -> 122
    //   114: goto -47 -> 67
    //   117: aload_2
    //   118: areturn
    //   119: astore_2
    //   120: aload_2
    //   121: athrow
    //   122: bipush 34
    //   124: istore_1
    //   125: goto -90 -> 35
    //   128: aload_0
    //   129: invokespecial 397	o/IB:getResources	()Landroid/content/res/Resources;
    //   132: invokestatic 402	o/oH:ˊ	(Landroid/content/res/Resources;)Landroid/content/res/Resources;
    //   135: astore_2
    //   136: goto -127 -> 9
    // Local variable table:
    //   start	length	slot	name	signature
    //   0	139	0	this	Md
    //   15	110	1	i	int
    //   3	31	2	localException1	Exception
    //   80	38	2	localResources1	android.content.res.Resources
    //   119	2	2	localException2	Exception
    //   135	1	2	localResources2	android.content.res.Resources
    // Exception table:
    //   from	to	target	type
    //   97	105	3	java/lang/Exception
    //   89	93	119	java/lang/Exception
  }
  
  public void onCardSelected(View paramView)
  {
    int i;
    for (;;)
    {
      i = ˋˊ + 75;
      ˊˊ = i % 128;
      if (i % 2 != 0) {
        break label65;
      }
      break label65;
      i = 0;
      break;
      for (;;)
      {
        i = ˋˊ + 103;
        ˊˊ = i % 128;
        if (i % 2 == 0) {
          break;
        }
        break label72;
        label65:
        ʾ();
      }
      label72:
      i = 1;
      break;
    }
    return;
    switch (i)
    {
    case 1: 
    default: 
      return;
    }
    throw new NullPointerException();
  }
  
  public void onCreate(Bundle paramBundle)
  {
    break label60;
    super.onCreate(paramBundle);
    ˊ(((Mw)this.ॱˊ).ʽ);
    return;
    for (;;)
    {
      super.onCreate(paramBundle);
      ˊ(((Mw)this.ॱˊ).ʽ);
      throw new NullPointerException();
      int i = 0;
      break label87;
      for (;;)
      {
        i = 1;
        break label87;
        label60:
        i = ˊˊ + 97;
        ˋˊ = i % 128;
        if (i % 2 != 0) {
          break;
        }
      }
      label87:
      switch (i)
      {
      }
    }
  }
  
  /* Error */
  public void onStart()
  {
    // Byte code:
    //   0: goto +162 -> 162
    //   3: goto +187 -> 190
    //   6: bipush 33
    //   8: istore_1
    //   9: goto +68 -> 77
    //   12: getstatic 26	o/Md:ˋˊ	I
    //   15: bipush 17
    //   17: iadd
    //   18: istore_1
    //   19: iload_1
    //   20: sipush 128
    //   23: irem
    //   24: putstatic 28	o/Md:ˊˊ	I
    //   27: iload_1
    //   28: iconst_2
    //   29: irem
    //   30: ifne +6 -> 36
    //   33: goto +135 -> 168
    //   36: goto -30 -> 6
    //   39: iload_1
    //   40: lookupswitch	default:+28->68, 38:+95->135, 92:+140->180
    //   68: goto +112 -> 180
    //   71: bipush 92
    //   73: istore_1
    //   74: goto -35 -> 39
    //   77: iload_1
    //   78: lookupswitch	default:+26->104, 33:+87->165, 68:+102->180
    //   104: goto +76 -> 180
    //   107: aload_0
    //   108: invokespecial 423	o/IB:onStart	()V
    //   111: aload_0
    //   112: invokevirtual 427	o/Md:getIntent	()Landroid/content/Intent;
    //   115: invokevirtual 431	android/content/Intent:getExtras	()Landroid/os/Bundle;
    //   118: astore_2
    //   119: aload_2
    //   120: ifnull +6 -> 126
    //   123: goto +6 -> 129
    //   126: goto -55 -> 71
    //   129: bipush 38
    //   131: istore_1
    //   132: goto -93 -> 39
    //   135: getstatic 26	o/Md:ˋˊ	I
    //   138: bipush 77
    //   140: iadd
    //   141: istore_1
    //   142: iload_1
    //   143: sipush 128
    //   146: irem
    //   147: putstatic 28	o/Md:ˊˊ	I
    //   150: iload_1
    //   151: iconst_2
    //   152: irem
    //   153: ifne +6 -> 159
    //   156: goto -153 -> 3
    //   159: goto +31 -> 190
    //   162: goto -55 -> 107
    //   165: goto +15 -> 180
    //   168: bipush 68
    //   170: istore_1
    //   171: goto -94 -> 77
    //   174: astore_2
    //   175: aload_2
    //   176: athrow
    //   177: astore_2
    //   178: aload_2
    //   179: athrow
    //   180: aload_0
    //   181: aload_2
    //   182: invokevirtual 433	o/Md:ˊ	(Landroid/os/Bundle;)V
    //   185: aload_0
    //   186: invokespecial 435	o/Md:ॱˋ	()V
    //   189: return
    //   190: aload_0
    //   191: invokevirtual 226	android/content/Context:getResources	()Landroid/content/res/Resources;
    //   194: astore_3
    //   195: aload_3
    //   196: ldc_w 436
    //   199: invokevirtual 233	android/content/res/Resources:getString	(I)Ljava/lang/String;
    //   202: astore_3
    //   203: aload_3
    //   204: iconst_0
    //   205: iconst_4
    //   206: invokevirtual 237	java/lang/String:substring	(II)Ljava/lang/String;
    //   209: astore_3
    //   210: aload_0
    //   211: aload_2
    //   212: iconst_0
    //   213: aload_3
    //   214: invokevirtual 204	java/lang/String:length	()I
    //   217: ldc_w 351
    //   220: isub
    //   221: aload_0
    //   222: invokevirtual 190	android/content/Context:getApplicationInfo	()Landroid/content/pm/ApplicationInfo;
    //   225: getfield 195	android/content/pm/ApplicationInfo:targetSdkVersion	I
    //   228: bipush 96
    //   230: iadd
    //   231: i2b
    //   232: ldc_w 298
    //   235: aload_0
    //   236: invokevirtual 190	android/content/Context:getApplicationInfo	()Landroid/content/pm/ApplicationInfo;
    //   239: getfield 195	android/content/pm/ApplicationInfo:targetSdkVersion	I
    //   242: bipush 106
    //   244: isub
    //   245: invokestatic 300	o/Md:ˎ	(SIBII)Ljava/lang/String;
    //   248: invokevirtual 303	java/lang/String:intern	()Ljava/lang/String;
    //   251: invokevirtual 440	android/os/Bundle:getInt	(Ljava/lang/String;)I
    //   254: putfield 97	o/Md:ˈ	I
    //   257: goto -245 -> 12
    // Local variable table:
    //   start	length	slot	name	signature
    //   0	260	0	this	Md
    //   8	163	1	i	int
    //   118	2	2	localBundle	Bundle
    //   174	2	2	localException1	Exception
    //   177	35	2	localException2	Exception
    //   194	20	3	localObject	Object
    // Exception table:
    //   from	to	target	type
    //   190	195	174	java/lang/Exception
    //   195	203	174	java/lang/Exception
    //   203	210	174	java/lang/Exception
    //   210	257	174	java/lang/Exception
    //   195	203	177	java/lang/Exception
  }
  
  /* Error */
  public void ˊ(Bundle paramBundle)
  {
    // Byte code:
    //   0: goto +176 -> 176
    //   3: goto +148 -> 151
    //   6: aload_0
    //   7: getfield 97	o/Md:ˈ	I
    //   10: tableswitch	default:+34->44, 0:+193->203, 1:+347->357, 2:+134->144, 3:+254->264, 4:+40->50
    //   44: goto +100 -> 144
    //   47: goto -44 -> 3
    //   50: aload_0
    //   51: getfield 102	o/Md:ॱˊ	Landroid/databinding/ViewDataBinding;
    //   54: checkcast 104	o/Mw
    //   57: iconst_1
    //   58: invokevirtual 442	o/Mw:ˊ	(Z)V
    //   61: aload_0
    //   62: aload_1
    //   63: iconst_0
    //   64: aload_0
    //   65: invokevirtual 190	android/content/Context:getApplicationInfo	()Landroid/content/pm/ApplicationInfo;
    //   68: getfield 195	android/content/pm/ApplicationInfo:targetSdkVersion	I
    //   71: ldc_w 351
    //   74: isub
    //   75: aload_0
    //   76: invokevirtual 226	android/content/Context:getResources	()Landroid/content/res/Resources;
    //   79: ldc_w 443
    //   82: invokevirtual 233	android/content/res/Resources:getString	(I)Ljava/lang/String;
    //   85: iconst_0
    //   86: iconst_4
    //   87: invokevirtual 237	java/lang/String:substring	(II)Ljava/lang/String;
    //   90: invokevirtual 204	java/lang/String:length	()I
    //   93: bipush 15
    //   95: iadd
    //   96: i2b
    //   97: ldc_w 298
    //   100: aload_0
    //   101: invokevirtual 198	android/content/Context:getPackageName	()Ljava/lang/String;
    //   104: iconst_3
    //   105: invokevirtual 243	java/lang/String:codePointAt	(I)I
    //   108: sipush 179
    //   111: isub
    //   112: invokestatic 300	o/Md:ˎ	(SIBII)Ljava/lang/String;
    //   115: invokevirtual 303	java/lang/String:intern	()Ljava/lang/String;
    //   118: invokevirtual 447	android/os/Bundle:getParcelable	(Ljava/lang/String;)Landroid/os/Parcelable;
    //   121: checkcast 291	o/Gh
    //   124: putfield 289	o/Md:ʿ	Lo/Gh;
    //   127: aload_0
    //   128: aload_0
    //   129: getfield 289	o/Md:ʿ	Lo/Gh;
    //   132: getfield 334	o/Gh:fromCardUuid	Ljava/lang/String;
    //   135: getstatic 453	o/FT:REQUEST_MONEY	Lo/FT;
    //   138: invokevirtual 456	o/Md:ˊ	(Ljava/lang/String;Lo/FT;)V
    //   141: goto -138 -> 3
    //   144: aload_0
    //   145: invokevirtual 331	o/Md:finish	()V
    //   148: goto -145 -> 3
    //   151: getstatic 26	o/Md:ˋˊ	I
    //   154: bipush 111
    //   156: iadd
    //   157: istore_2
    //   158: iload_2
    //   159: sipush 128
    //   162: irem
    //   163: putstatic 28	o/Md:ˊˊ	I
    //   166: iload_2
    //   167: iconst_2
    //   168: irem
    //   169: ifne +6 -> 175
    //   172: goto +294 -> 466
    //   175: return
    //   176: getstatic 26	o/Md:ˋˊ	I
    //   179: bipush 75
    //   181: iadd
    //   182: istore_2
    //   183: iload_2
    //   184: sipush 128
    //   187: irem
    //   188: putstatic 28	o/Md:ˊˊ	I
    //   191: iload_2
    //   192: iconst_2
    //   193: irem
    //   194: ifne +6 -> 200
    //   197: goto +266 -> 463
    //   200: goto -194 -> 6
    //   203: aload_0
    //   204: getfield 102	o/Md:ॱˊ	Landroid/databinding/ViewDataBinding;
    //   207: checkcast 104	o/Mw
    //   210: iconst_1
    //   211: invokevirtual 442	o/Mw:ˊ	(Z)V
    //   214: aload_0
    //   215: new 291	o/Gh
    //   218: dup
    //   219: invokespecial 457	o/Gh:<init>	()V
    //   222: putfield 289	o/Md:ʿ	Lo/Gh;
    //   225: aload_0
    //   226: aconst_null
    //   227: getstatic 460	o/FT:SEND_MONEY	Lo/FT;
    //   230: invokevirtual 456	o/Md:ˊ	(Ljava/lang/String;Lo/FT;)V
    //   233: aload_0
    //   234: invokespecial 250	o/Md:ʻॱ	()V
    //   237: getstatic 26	o/Md:ˋˊ	I
    //   240: bipush 19
    //   242: iadd
    //   243: istore_2
    //   244: iload_2
    //   245: sipush 128
    //   248: irem
    //   249: putstatic 28	o/Md:ˊˊ	I
    //   252: iload_2
    //   253: iconst_2
    //   254: irem
    //   255: ifne +6 -> 261
    //   258: goto +196 -> 454
    //   261: goto +190 -> 451
    //   264: aload_0
    //   265: getfield 102	o/Md:ॱˊ	Landroid/databinding/ViewDataBinding;
    //   268: checkcast 104	o/Mw
    //   271: iconst_1
    //   272: invokevirtual 442	o/Mw:ˊ	(Z)V
    //   275: aload_0
    //   276: aload_1
    //   277: iconst_0
    //   278: aload_0
    //   279: invokevirtual 226	android/content/Context:getResources	()Landroid/content/res/Resources;
    //   282: ldc_w 461
    //   285: invokevirtual 233	android/content/res/Resources:getString	(I)Ljava/lang/String;
    //   288: iconst_0
    //   289: iconst_4
    //   290: invokevirtual 237	java/lang/String:substring	(II)Ljava/lang/String;
    //   293: iconst_3
    //   294: invokevirtual 243	java/lang/String:codePointAt	(I)I
    //   297: ldc_w 462
    //   300: isub
    //   301: aload_0
    //   302: invokevirtual 190	android/content/Context:getApplicationInfo	()Landroid/content/pm/ApplicationInfo;
    //   305: getfield 195	android/content/pm/ApplicationInfo:targetSdkVersion	I
    //   308: bipush 6
    //   310: isub
    //   311: i2b
    //   312: ldc_w 298
    //   315: aload_0
    //   316: invokevirtual 190	android/content/Context:getApplicationInfo	()Landroid/content/pm/ApplicationInfo;
    //   319: getfield 195	android/content/pm/ApplicationInfo:targetSdkVersion	I
    //   322: bipush 106
    //   324: isub
    //   325: invokestatic 300	o/Md:ˎ	(SIBII)Ljava/lang/String;
    //   328: invokevirtual 303	java/lang/String:intern	()Ljava/lang/String;
    //   331: invokevirtual 447	android/os/Bundle:getParcelable	(Ljava/lang/String;)Landroid/os/Parcelable;
    //   334: checkcast 291	o/Gh
    //   337: putfield 289	o/Md:ʿ	Lo/Gh;
    //   340: aload_0
    //   341: aload_0
    //   342: getfield 289	o/Md:ʿ	Lo/Gh;
    //   345: getfield 294	o/Gh:toCardUuid	Ljava/lang/String;
    //   348: getstatic 460	o/FT:SEND_MONEY	Lo/FT;
    //   351: invokevirtual 456	o/Md:ˊ	(Ljava/lang/String;Lo/FT;)V
    //   354: goto -351 -> 3
    //   357: aload_0
    //   358: getfield 102	o/Md:ॱˊ	Landroid/databinding/ViewDataBinding;
    //   361: checkcast 104	o/Mw
    //   364: iconst_0
    //   365: invokevirtual 442	o/Mw:ˊ	(Z)V
    //   368: aload_0
    //   369: aload_1
    //   370: iconst_0
    //   371: aload_0
    //   372: invokevirtual 226	android/content/Context:getResources	()Landroid/content/res/Resources;
    //   375: ldc_w 463
    //   378: invokevirtual 233	android/content/res/Resources:getString	(I)Ljava/lang/String;
    //   381: iconst_0
    //   382: iconst_5
    //   383: invokevirtual 237	java/lang/String:substring	(II)Ljava/lang/String;
    //   386: invokevirtual 204	java/lang/String:length	()I
    //   389: ldc_w 464
    //   392: isub
    //   393: aload_0
    //   394: invokevirtual 198	android/content/Context:getPackageName	()Ljava/lang/String;
    //   397: bipush 9
    //   399: invokevirtual 243	java/lang/String:codePointAt	(I)I
    //   402: bipush 78
    //   404: isub
    //   405: i2b
    //   406: ldc_w 298
    //   409: aload_0
    //   410: invokevirtual 190	android/content/Context:getApplicationInfo	()Landroid/content/pm/ApplicationInfo;
    //   413: getfield 195	android/content/pm/ApplicationInfo:targetSdkVersion	I
    //   416: bipush 106
    //   418: isub
    //   419: invokestatic 300	o/Md:ˎ	(SIBII)Ljava/lang/String;
    //   422: invokevirtual 303	java/lang/String:intern	()Ljava/lang/String;
    //   425: invokevirtual 447	android/os/Bundle:getParcelable	(Ljava/lang/String;)Landroid/os/Parcelable;
    //   428: checkcast 291	o/Gh
    //   431: putfield 289	o/Md:ʿ	Lo/Gh;
    //   434: aload_0
    //   435: aload_0
    //   436: getfield 289	o/Md:ʿ	Lo/Gh;
    //   439: getfield 334	o/Gh:fromCardUuid	Ljava/lang/String;
    //   442: getstatic 453	o/FT:REQUEST_MONEY	Lo/FT;
    //   445: invokevirtual 456	o/Md:ˊ	(Ljava/lang/String;Lo/FT;)V
    //   448: goto -401 -> 47
    //   451: goto -448 -> 3
    //   454: goto -3 -> 451
    //   457: astore_1
    //   458: aload_1
    //   459: athrow
    //   460: astore_1
    //   461: aload_1
    //   462: athrow
    //   463: goto -457 -> 6
    //   466: return
    // Local variable table:
    //   start	length	slot	name	signature
    //   0	467	0	this	Md
    //   0	467	1	paramBundle	Bundle
    //   157	98	2	i	int
    // Exception table:
    //   from	to	target	type
    //   237	244	457	java/lang/Exception
    //   244	252	457	java/lang/Exception
    //   244	252	460	java/lang/Exception
  }
  
  /* Error */
  public void ˊ(String paramString, FT paramFT)
  {
    // Byte code:
    //   0: goto +657 -> 657
    //   3: goto +17 -> 20
    //   6: astore_1
    //   7: aload_1
    //   8: invokevirtual 184	java/lang/Throwable:getCause	()Ljava/lang/Throwable;
    //   11: astore_2
    //   12: aload_2
    //   13: ifnull +5 -> 18
    //   16: aload_2
    //   17: athrow
    //   18: aload_1
    //   19: athrow
    //   20: aload_0
    //   21: invokevirtual 198	android/content/Context:getPackageName	()Ljava/lang/String;
    //   24: invokevirtual 204	java/lang/String:length	()I
    //   27: bipush 7
    //   29: isub
    //   30: aload_0
    //   31: invokevirtual 226	android/content/Context:getResources	()Landroid/content/res/Resources;
    //   34: ldc_w 465
    //   37: invokevirtual 233	android/content/res/Resources:getString	(I)Ljava/lang/String;
    //   40: bipush 33
    //   42: bipush 34
    //   44: invokevirtual 237	java/lang/String:substring	(II)Ljava/lang/String;
    //   47: invokevirtual 204	java/lang/String:length	()I
    //   50: sipush 266
    //   53: iadd
    //   54: aload_0
    //   55: invokevirtual 198	android/content/Context:getPackageName	()Ljava/lang/String;
    //   58: invokevirtual 204	java/lang/String:length	()I
    //   61: sipush 14777
    //   64: iadd
    //   65: i2c
    //   66: invokestatic 209	o/O:ˋ	(IIC)Ljava/lang/Object;
    //   69: checkcast 211	java/lang/Class
    //   72: ldc -44
    //   74: aconst_null
    //   75: invokevirtual 216	java/lang/Class:getMethod	(Ljava/lang/String;[Ljava/lang/Class;)Ljava/lang/reflect/Method;
    //   78: aconst_null
    //   79: aconst_null
    //   80: invokevirtual 222	java/lang/reflect/Method:invoke	(Ljava/lang/Object;[Ljava/lang/Object;)Ljava/lang/Object;
    //   83: astore 4
    //   85: aload_0
    //   86: aload_2
    //   87: invokespecial 467	o/Md:ˊ	(Lo/FT;)Ljava/util/ArrayList;
    //   90: astore 5
    //   92: goto +17 -> 109
    //   95: astore_1
    //   96: aload_1
    //   97: invokevirtual 184	java/lang/Throwable:getCause	()Ljava/lang/Throwable;
    //   100: astore_2
    //   101: aload_2
    //   102: ifnull +5 -> 107
    //   105: aload_2
    //   106: athrow
    //   107: aload_1
    //   108: athrow
    //   109: aload_0
    //   110: invokevirtual 190	android/content/Context:getApplicationInfo	()Landroid/content/pm/ApplicationInfo;
    //   113: getfield 195	android/content/pm/ApplicationInfo:targetSdkVersion	I
    //   116: bipush 21
    //   118: isub
    //   119: aload_0
    //   120: invokevirtual 198	android/content/Context:getPackageName	()Ljava/lang/String;
    //   123: bipush 10
    //   125: invokevirtual 243	java/lang/String:codePointAt	(I)I
    //   128: sipush 146
    //   131: iadd
    //   132: aload_0
    //   133: invokevirtual 190	android/content/Context:getApplicationInfo	()Landroid/content/pm/ApplicationInfo;
    //   136: getfield 195	android/content/pm/ApplicationInfo:targetSdkVersion	I
    //   139: sipush 14763
    //   142: iadd
    //   143: i2c
    //   144: invokestatic 209	o/O:ˋ	(IIC)Ljava/lang/Object;
    //   147: checkcast 211	java/lang/Class
    //   150: ldc_w 468
    //   153: iconst_1
    //   154: anewarray 211	java/lang/Class
    //   157: dup
    //   158: iconst_0
    //   159: ldc -99
    //   161: aastore
    //   162: invokevirtual 216	java/lang/Class:getMethod	(Ljava/lang/String;[Ljava/lang/Class;)Ljava/lang/reflect/Method;
    //   165: aload 4
    //   167: iconst_1
    //   168: anewarray 341	java/lang/Object
    //   171: dup
    //   172: iconst_0
    //   173: aload 5
    //   175: aastore
    //   176: invokevirtual 222	java/lang/reflect/Method:invoke	(Ljava/lang/Object;[Ljava/lang/Object;)Ljava/lang/Object;
    //   179: checkcast 272	java/util/List
    //   182: astore 5
    //   184: aload_2
    //   185: getstatic 460	o/FT:SEND_MONEY	Lo/FT;
    //   188: if_acmpne +6 -> 194
    //   191: goto +739 -> 930
    //   194: aload 5
    //   196: astore_2
    //   197: goto +37 -> 234
    //   200: iconst_1
    //   201: istore_3
    //   202: goto +458 -> 660
    //   205: iconst_0
    //   206: istore_3
    //   207: goto +691 -> 898
    //   210: aload_0
    //   211: getfield 102	o/Md:ॱˊ	Landroid/databinding/ViewDataBinding;
    //   214: checkcast 104	o/Mw
    //   217: getfield 108	o/Mw:ॱ	Lo/KZ;
    //   220: aload_2
    //   221: invokevirtual 472	o/KZ:setCards	(Ljava/util/List;)V
    //   224: aload_0
    //   225: invokespecial 250	o/Md:ʻॱ	()V
    //   228: return
    //   229: iconst_1
    //   230: istore_3
    //   231: goto +732 -> 963
    //   234: aload_1
    //   235: invokestatic 478	android/text/TextUtils:isEmpty	(Ljava/lang/CharSequence;)Z
    //   238: ifne +6 -> 244
    //   241: goto +401 -> 642
    //   244: goto -34 -> 210
    //   247: iconst_0
    //   248: istore_3
    //   249: goto +714 -> 963
    //   252: aload 4
    //   254: iconst_0
    //   255: invokeinterface 482 2 0
    //   260: astore_2
    //   261: aload_2
    //   262: checkcast 282	com/insidesecure/hce/MatrixHCECard
    //   265: astore_2
    //   266: aload_2
    //   267: invokestatic 132	o/HQ:ˏ	(Lcom/insidesecure/hce/MatrixHCECard;)Lo/HQ;
    //   270: astore_2
    //   271: aload_2
    //   272: invokevirtual 486	o/HQ:ˎˎ	()Lo/Ej;
    //   275: astore_2
    //   276: getstatic 492	o/Ej:ALL	Lo/Ej;
    //   279: astore 6
    //   281: aload_2
    //   282: aload 6
    //   284: if_acmpne +6 -> 290
    //   287: goto -87 -> 200
    //   290: goto +347 -> 637
    //   293: goto +17 -> 310
    //   296: astore_1
    //   297: aload_1
    //   298: invokevirtual 184	java/lang/Throwable:getCause	()Ljava/lang/Throwable;
    //   301: astore_2
    //   302: aload_2
    //   303: ifnull +5 -> 308
    //   306: aload_2
    //   307: athrow
    //   308: aload_1
    //   309: athrow
    //   310: aload_0
    //   311: invokevirtual 190	android/content/Context:getApplicationInfo	()Landroid/content/pm/ApplicationInfo;
    //   314: getfield 195	android/content/pm/ApplicationInfo:targetSdkVersion	I
    //   317: bipush 21
    //   319: isub
    //   320: aload_0
    //   321: invokevirtual 226	android/content/Context:getResources	()Landroid/content/res/Resources;
    //   324: ldc_w 493
    //   327: invokevirtual 233	android/content/res/Resources:getString	(I)Ljava/lang/String;
    //   330: iconst_0
    //   331: iconst_4
    //   332: invokevirtual 237	java/lang/String:substring	(II)Ljava/lang/String;
    //   335: iconst_1
    //   336: invokevirtual 243	java/lang/String:codePointAt	(I)I
    //   339: sipush 241
    //   342: iadd
    //   343: aload_0
    //   344: invokevirtual 226	android/content/Context:getResources	()Landroid/content/res/Resources;
    //   347: ldc_w 494
    //   350: invokevirtual 233	android/content/res/Resources:getString	(I)Ljava/lang/String;
    //   353: iconst_0
    //   354: iconst_4
    //   355: invokevirtual 237	java/lang/String:substring	(II)Ljava/lang/String;
    //   358: iconst_2
    //   359: invokevirtual 243	java/lang/String:codePointAt	(I)I
    //   362: sipush 14777
    //   365: iadd
    //   366: i2c
    //   367: invokestatic 209	o/O:ˋ	(IIC)Ljava/lang/Object;
    //   370: checkcast 211	java/lang/Class
    //   373: ldc -44
    //   375: aconst_null
    //   376: invokevirtual 216	java/lang/Class:getMethod	(Ljava/lang/String;[Ljava/lang/Class;)Ljava/lang/reflect/Method;
    //   379: aconst_null
    //   380: aconst_null
    //   381: invokevirtual 222	java/lang/reflect/Method:invoke	(Ljava/lang/Object;[Ljava/lang/Object;)Ljava/lang/Object;
    //   384: astore_2
    //   385: aload_0
    //   386: getstatic 453	o/FT:REQUEST_MONEY	Lo/FT;
    //   389: invokespecial 467	o/Md:ˊ	(Lo/FT;)Ljava/util/ArrayList;
    //   392: astore 4
    //   394: goto +17 -> 411
    //   397: astore_1
    //   398: aload_1
    //   399: invokevirtual 184	java/lang/Throwable:getCause	()Ljava/lang/Throwable;
    //   402: astore_2
    //   403: aload_2
    //   404: ifnull +5 -> 409
    //   407: aload_2
    //   408: athrow
    //   409: aload_1
    //   410: athrow
    //   411: aload_0
    //   412: invokevirtual 198	android/content/Context:getPackageName	()Ljava/lang/String;
    //   415: invokevirtual 204	java/lang/String:length	()I
    //   418: bipush 7
    //   420: isub
    //   421: aload_0
    //   422: invokevirtual 226	android/content/Context:getResources	()Landroid/content/res/Resources;
    //   425: ldc_w 495
    //   428: invokevirtual 233	android/content/res/Resources:getString	(I)Ljava/lang/String;
    //   431: iconst_0
    //   432: iconst_4
    //   433: invokevirtual 237	java/lang/String:substring	(II)Ljava/lang/String;
    //   436: iconst_2
    //   437: invokevirtual 243	java/lang/String:codePointAt	(I)I
    //   440: sipush 256
    //   443: iadd
    //   444: aload_0
    //   445: invokevirtual 226	android/content/Context:getResources	()Landroid/content/res/Resources;
    //   448: ldc_w 496
    //   451: invokevirtual 233	android/content/res/Resources:getString	(I)Ljava/lang/String;
    //   454: iconst_0
    //   455: bipush 6
    //   457: invokevirtual 237	java/lang/String:substring	(II)Ljava/lang/String;
    //   460: iconst_3
    //   461: invokevirtual 243	java/lang/String:codePointAt	(I)I
    //   464: sipush 14776
    //   467: iadd
    //   468: i2c
    //   469: invokestatic 209	o/O:ˋ	(IIC)Ljava/lang/Object;
    //   472: checkcast 211	java/lang/Class
    //   475: ldc_w 468
    //   478: iconst_1
    //   479: anewarray 211	java/lang/Class
    //   482: dup
    //   483: iconst_0
    //   484: ldc -99
    //   486: aastore
    //   487: invokevirtual 216	java/lang/Class:getMethod	(Ljava/lang/String;[Ljava/lang/Class;)Ljava/lang/reflect/Method;
    //   490: aload_2
    //   491: iconst_1
    //   492: anewarray 341	java/lang/Object
    //   495: dup
    //   496: iconst_0
    //   497: aload 4
    //   499: aastore
    //   500: invokevirtual 222	java/lang/reflect/Method:invoke	(Ljava/lang/Object;[Ljava/lang/Object;)Ljava/lang/Object;
    //   503: checkcast 272	java/util/List
    //   506: astore 4
    //   508: aload 4
    //   510: invokeinterface 499 1 0
    //   515: iconst_1
    //   516: if_icmpne +6 -> 522
    //   519: goto +9 -> 528
    //   522: aload 5
    //   524: astore_2
    //   525: goto -291 -> 234
    //   528: getstatic 26	o/Md:ˋˊ	I
    //   531: bipush 97
    //   533: iadd
    //   534: istore_3
    //   535: iload_3
    //   536: sipush 128
    //   539: irem
    //   540: putstatic 28	o/Md:ˊˊ	I
    //   543: iload_3
    //   544: iconst_2
    //   545: irem
    //   546: ifne +6 -> 552
    //   549: goto -297 -> 252
    //   552: aload 4
    //   554: iconst_0
    //   555: invokeinterface 482 2 0
    //   560: checkcast 282	com/insidesecure/hce/MatrixHCECard
    //   563: invokestatic 132	o/HQ:ˏ	(Lcom/insidesecure/hce/MatrixHCECard;)Lo/HQ;
    //   566: invokevirtual 486	o/HQ:ˎˎ	()Lo/Ej;
    //   569: getstatic 492	o/Ej:ALL	Lo/Ej;
    //   572: if_acmpne +6 -> 578
    //   575: goto -346 -> 229
    //   578: goto -331 -> 247
    //   581: aload_0
    //   582: aload 5
    //   584: aload 4
    //   586: iconst_0
    //   587: invokeinterface 482 2 0
    //   592: checkcast 282	com/insidesecure/hce/MatrixHCECard
    //   595: invokeinterface 502 1 0
    //   600: invokespecial 504	o/Md:ॱ	(Ljava/util/List;Ljava/lang/String;)Ljava/util/List;
    //   603: astore_2
    //   604: goto +87 -> 691
    //   607: getstatic 28	o/Md:ˊˊ	I
    //   610: bipush 103
    //   612: iadd
    //   613: istore_3
    //   614: iload_3
    //   615: sipush 128
    //   618: irem
    //   619: putstatic 26	o/Md:ˋˊ	I
    //   622: iload_3
    //   623: iconst_2
    //   624: irem
    //   625: ifeq +6 -> 631
    //   628: goto +6 -> 634
    //   631: goto -628 -> 3
    //   634: goto -631 -> 3
    //   637: iconst_0
    //   638: istore_3
    //   639: goto +21 -> 660
    //   642: aload_0
    //   643: aload_2
    //   644: aload_1
    //   645: invokespecial 504	o/Md:ॱ	(Ljava/util/List;Ljava/lang/String;)Ljava/util/List;
    //   648: astore_2
    //   649: goto -439 -> 210
    //   652: iconst_1
    //   653: istore_3
    //   654: goto +244 -> 898
    //   657: goto -50 -> 607
    //   660: aload 5
    //   662: astore_2
    //   663: iload_3
    //   664: tableswitch	default:+24->688, 0:+-430->234, 1:+-83->581
    //   688: goto -107 -> 581
    //   691: goto -457 -> 234
    //   694: goto +17 -> 711
    //   697: astore_1
    //   698: aload_1
    //   699: invokevirtual 184	java/lang/Throwable:getCause	()Ljava/lang/Throwable;
    //   702: astore_2
    //   703: aload_2
    //   704: ifnull +5 -> 709
    //   707: aload_2
    //   708: athrow
    //   709: aload_1
    //   710: athrow
    //   711: aload_0
    //   712: invokevirtual 226	android/content/Context:getResources	()Landroid/content/res/Resources;
    //   715: ldc -29
    //   717: invokevirtual 233	android/content/res/Resources:getString	(I)Ljava/lang/String;
    //   720: iconst_0
    //   721: iconst_4
    //   722: invokevirtual 237	java/lang/String:substring	(II)Ljava/lang/String;
    //   725: invokevirtual 204	java/lang/String:length	()I
    //   728: iconst_0
    //   729: iadd
    //   730: aload_0
    //   731: invokevirtual 190	android/content/Context:getApplicationInfo	()Landroid/content/pm/ApplicationInfo;
    //   734: getfield 195	android/content/pm/ApplicationInfo:targetSdkVersion	I
    //   737: sipush 242
    //   740: iadd
    //   741: aload_0
    //   742: invokevirtual 198	android/content/Context:getPackageName	()Ljava/lang/String;
    //   745: invokevirtual 204	java/lang/String:length	()I
    //   748: sipush 14777
    //   751: iadd
    //   752: i2c
    //   753: invokestatic 209	o/O:ˋ	(IIC)Ljava/lang/Object;
    //   756: checkcast 211	java/lang/Class
    //   759: ldc -44
    //   761: aconst_null
    //   762: invokevirtual 216	java/lang/Class:getMethod	(Ljava/lang/String;[Ljava/lang/Class;)Ljava/lang/reflect/Method;
    //   765: aconst_null
    //   766: aconst_null
    //   767: invokevirtual 222	java/lang/reflect/Method:invoke	(Ljava/lang/Object;[Ljava/lang/Object;)Ljava/lang/Object;
    //   770: astore_2
    //   771: aload_0
    //   772: getstatic 453	o/FT:REQUEST_MONEY	Lo/FT;
    //   775: invokespecial 467	o/Md:ˊ	(Lo/FT;)Ljava/util/ArrayList;
    //   778: astore 4
    //   780: goto +17 -> 797
    //   783: astore_1
    //   784: aload_1
    //   785: invokevirtual 184	java/lang/Throwable:getCause	()Ljava/lang/Throwable;
    //   788: astore_2
    //   789: aload_2
    //   790: ifnull +5 -> 795
    //   793: aload_2
    //   794: athrow
    //   795: aload_1
    //   796: athrow
    //   797: aload_0
    //   798: invokevirtual 190	android/content/Context:getApplicationInfo	()Landroid/content/pm/ApplicationInfo;
    //   801: getfield 195	android/content/pm/ApplicationInfo:targetSdkVersion	I
    //   804: bipush 21
    //   806: isub
    //   807: aload_0
    //   808: invokevirtual 198	android/content/Context:getPackageName	()Ljava/lang/String;
    //   811: iconst_5
    //   812: invokevirtual 243	java/lang/String:codePointAt	(I)I
    //   815: sipush 153
    //   818: iadd
    //   819: aload_0
    //   820: invokevirtual 226	android/content/Context:getResources	()Landroid/content/res/Resources;
    //   823: ldc_w 505
    //   826: invokevirtual 233	android/content/res/Resources:getString	(I)Ljava/lang/String;
    //   829: iconst_0
    //   830: iconst_4
    //   831: invokevirtual 237	java/lang/String:substring	(II)Ljava/lang/String;
    //   834: invokevirtual 204	java/lang/String:length	()I
    //   837: sipush 14784
    //   840: iadd
    //   841: i2c
    //   842: invokestatic 209	o/O:ˋ	(IIC)Ljava/lang/Object;
    //   845: checkcast 211	java/lang/Class
    //   848: ldc_w 468
    //   851: iconst_1
    //   852: anewarray 211	java/lang/Class
    //   855: dup
    //   856: iconst_0
    //   857: ldc -99
    //   859: aastore
    //   860: invokevirtual 216	java/lang/Class:getMethod	(Ljava/lang/String;[Ljava/lang/Class;)Ljava/lang/reflect/Method;
    //   863: aload_2
    //   864: iconst_1
    //   865: anewarray 341	java/lang/Object
    //   868: dup
    //   869: iconst_0
    //   870: aload 4
    //   872: aastore
    //   873: invokevirtual 222	java/lang/reflect/Method:invoke	(Ljava/lang/Object;[Ljava/lang/Object;)Ljava/lang/Object;
    //   876: checkcast 272	java/util/List
    //   879: astore 4
    //   881: aload 4
    //   883: invokeinterface 499 1 0
    //   888: iconst_1
    //   889: if_icmpne +6 -> 895
    //   892: goto -240 -> 652
    //   895: goto -690 -> 205
    //   898: aload 5
    //   900: astore_2
    //   901: iload_3
    //   902: tableswitch	default:+22->924, 0:+-668->234, 1:+-374->528
    //   924: aload 5
    //   926: astore_2
    //   927: goto -693 -> 234
    //   930: getstatic 28	o/Md:ˊˊ	I
    //   933: bipush 29
    //   935: iadd
    //   936: istore_3
    //   937: iload_3
    //   938: sipush 128
    //   941: irem
    //   942: putstatic 26	o/Md:ˋˊ	I
    //   945: iload_3
    //   946: iconst_2
    //   947: irem
    //   948: ifeq +6 -> 954
    //   951: goto -658 -> 293
    //   954: goto -260 -> 694
    //   957: astore_1
    //   958: aload_1
    //   959: athrow
    //   960: astore_1
    //   961: aload_1
    //   962: athrow
    //   963: aload 5
    //   965: astore_2
    //   966: iload_3
    //   967: tableswitch	default:+21->988, 0:+-733->234, 1:+-386->581
    //   988: goto -407 -> 581
    // Local variable table:
    //   start	length	slot	name	signature
    //   0	991	0	this	Md
    //   0	991	1	paramString	String
    //   0	991	2	paramFT	FT
    //   201	766	3	i	int
    //   83	799	4	localObject1	Object
    //   90	874	5	localObject2	Object
    //   279	4	6	localEj	Ej
    // Exception table:
    //   from	to	target	type
    //   20	85	6	finally
    //   109	184	95	finally
    //   310	385	296	finally
    //   411	508	397	finally
    //   711	771	697	finally
    //   797	881	783	finally
    //   261	266	957	java/lang/Exception
    //   252	261	960	java/lang/Exception
    //   261	266	960	java/lang/Exception
    //   266	271	960	java/lang/Exception
    //   271	276	960	java/lang/Exception
    //   276	281	960	java/lang/Exception
  }
  
  @zA(ˎ=ThreadMode.MAIN)
  public void ˊ(HA paramHA)
  {
    break label10;
    int i = 61;
    break label132;
    return;
    label10:
    break label18;
    i = 0;
    for (;;)
    {
      try
      {
        label18:
        i = ˊˊ + 29;
        ˋˊ = i % 128;
        if (i % 2 != 0) {
          break;
        }
        continue;
        i = null.length;
        return;
        i = 26;
      }
      catch (Exception paramHA)
      {
        throw paramHA;
      }
      ˊ(getIntent().getExtras());
      i = 66 / 0;
      break label103;
      label77:
      switch (i)
      {
      }
    }
    for (;;)
    {
      label103:
      i = ˊˊ + 53;
      ˋˊ = i % 128;
      if (i % 2 != 0) {
        break;
      }
      i = 1;
      break label77;
      switch (i)
      {
      case 61: 
      default: 
        break;
      case 26: 
        label132:
        ˊ(getIntent().getExtras());
      }
    }
  }
  
  @zA(ˎ=ThreadMode.MAIN)
  public void ˋ(Kj paramKj)
  {
    break label56;
    label6:
    int i = 0;
    break label23;
    ʾ();
    throw new NullPointerException();
    for (;;)
    {
      switch (i)
      {
      case 0: 
      default: 
        break;
      case 1: 
        label23:
        ʾ();
        return;
        label56:
        i = ˋˊ + 117;
        ˊˊ = i % 128;
        if (i % 2 == 0) {
          break label6;
        }
        i = 1;
      }
    }
  }
  
  /* Error */
  public void ˋ(ز paramز)
  {
    // Byte code:
    //   0: goto +47 -> 47
    //   3: getstatic 28	o/Md:ˊˊ	I
    //   6: bipush 57
    //   8: iadd
    //   9: istore_2
    //   10: iload_2
    //   11: sipush 128
    //   14: irem
    //   15: putstatic 26	o/Md:ˋˊ	I
    //   18: iload_2
    //   19: iconst_2
    //   20: irem
    //   21: ifeq +4 -> 25
    //   24: return
    //   25: return
    //   26: astore_1
    //   27: aload_1
    //   28: athrow
    //   29: iconst_1
    //   30: istore_2
    //   31: goto +61 -> 92
    //   34: aload_1
    //   35: iconst_0
    //   36: invokevirtual 515	o/ز:ॱ	(Z)V
    //   39: aload_1
    //   40: iconst_1
    //   41: invokevirtual 517	o/ز:ˏ	(Z)V
    //   44: goto -41 -> 3
    //   47: getstatic 28	o/Md:ˊˊ	I
    //   50: bipush 19
    //   52: iadd
    //   53: istore_2
    //   54: iload_2
    //   55: sipush 128
    //   58: irem
    //   59: putstatic 26	o/Md:ˋˊ	I
    //   62: iload_2
    //   63: iconst_2
    //   64: irem
    //   65: ifeq +6 -> 71
    //   68: goto +22 -> 90
    //   71: goto -42 -> 29
    //   74: astore_1
    //   75: aload_1
    //   76: athrow
    //   77: aload_1
    //   78: iconst_1
    //   79: invokevirtual 515	o/ز:ॱ	(Z)V
    //   82: aload_1
    //   83: iconst_1
    //   84: invokevirtual 517	o/ز:ˏ	(Z)V
    //   87: goto -84 -> 3
    //   90: iconst_0
    //   91: istore_2
    //   92: iload_2
    //   93: tableswitch	default:+23->116, 0:+-59->34, 1:+-16->77
    //   116: goto -39 -> 77
    // Local variable table:
    //   start	length	slot	name	signature
    //   0	119	0	this	Md
    //   0	119	1	paramز	ز
    //   9	84	2	i	int
    // Exception table:
    //   from	to	target	type
    //   82	87	26	java/lang/Exception
    //   3	10	74	java/lang/Exception
    //   10	18	74	java/lang/Exception
    //   77	82	74	java/lang/Exception
    //   82	87	74	java/lang/Exception
  }
  
  public int ˎ()
  {
    int j;
    for (;;)
    {
      j = LV.iF.activity_pick_card;
      break label67;
      label10:
      int i = ˋˊ + 3;
      ˊˊ = i % 128;
      if (i % 2 != 0)
      {
        continue;
        for (;;)
        {
          switch (i)
          {
          case 0: 
          default: 
            i = 72 / 0;
            return j;
            label67:
            i = ˊˊ + 121;
            ˋˊ = i % 128;
            if (i % 2 == 0) {
              break label102;
            }
            i = 0;
            continue;
            break label10;
            label102:
            i = 1;
          }
        }
      }
    }
    return j;
  }
}
