package o;

import android.content.Context;
import android.text.TextUtils;
import java.util.Arrays;

public final class mF
{
  private static int ʻ = 1;
  private static int[] ʼ = { -1601721399, 242373856, -1786600525, 1083811337, 1435284367, -1801120710, 125070124, 948719524, -355369349, -417735218, -646158448, -553887240, 588109102, -1458358070, 1143732941, -126839095, -1922097869, -1954665035 };
  private static int ॱॱ = 0;
  private final String ʽ;
  private final String ˊ;
  private final String ˋ;
  private final String ˎ;
  private final String ˏ;
  private final String ॱ;
  private final String ᐝ;
  
  /* Error */
  private mF(String paramString1, String paramString2, String paramString3, String paramString4, String paramString5, String paramString6, String paramString7)
  {
    // Byte code:
    //   0: goto +214 -> 214
    //   3: getstatic 21	o/mF:ॱॱ	I
    //   6: bipush 113
    //   8: iadd
    //   9: istore 8
    //   11: iload 8
    //   13: sipush 128
    //   16: irem
    //   17: putstatic 23	o/mF:ʻ	I
    //   20: iload 8
    //   22: iconst_2
    //   23: irem
    //   24: ifne +6 -> 30
    //   27: goto +184 -> 211
    //   30: goto +178 -> 208
    //   33: astore_1
    //   34: aload_1
    //   35: athrow
    //   36: new 50	java/lang/NullPointerException
    //   39: dup
    //   40: invokespecial 52	java/lang/NullPointerException:<init>	()V
    //   43: athrow
    //   44: iload 9
    //   46: ldc 54
    //   48: invokestatic 59	o/fg:ˏ	(ZLjava/lang/Object;)V
    //   51: aload_0
    //   52: aload_1
    //   53: putfield 61	o/mF:ˋ	Ljava/lang/String;
    //   56: aload_0
    //   57: aload_2
    //   58: putfield 63	o/mF:ॱ	Ljava/lang/String;
    //   61: aload_0
    //   62: aload_3
    //   63: putfield 65	o/mF:ˊ	Ljava/lang/String;
    //   66: aload_0
    //   67: aload 4
    //   69: putfield 67	o/mF:ˏ	Ljava/lang/String;
    //   72: aload_0
    //   73: aload 5
    //   75: putfield 69	o/mF:ˎ	Ljava/lang/String;
    //   78: aload_0
    //   79: aload 6
    //   81: putfield 71	o/mF:ᐝ	Ljava/lang/String;
    //   84: aload_0
    //   85: aload 7
    //   87: putfield 73	o/mF:ʽ	Ljava/lang/String;
    //   90: goto +72 -> 162
    //   93: getstatic 21	o/mF:ॱॱ	I
    //   96: bipush 13
    //   98: iadd
    //   99: istore 8
    //   101: iload 8
    //   103: sipush 128
    //   106: irem
    //   107: putstatic 23	o/mF:ʻ	I
    //   110: iload 8
    //   112: iconst_2
    //   113: irem
    //   114: ifne +6 -> 120
    //   117: goto +38 -> 155
    //   120: goto +111 -> 231
    //   123: iload 8
    //   125: lookupswitch	default:+27->152, 14:+74->199, 98:+160->285
    //   152: goto +47 -> 199
    //   155: bipush 98
    //   157: istore 8
    //   159: goto -36 -> 123
    //   162: getstatic 23	o/mF:ʻ	I
    //   165: istore 8
    //   167: iload 8
    //   169: bipush 83
    //   171: iadd
    //   172: istore 8
    //   174: iload 8
    //   176: sipush 128
    //   179: irem
    //   180: putstatic 21	o/mF:ॱॱ	I
    //   183: iload 8
    //   185: iconst_2
    //   186: irem
    //   187: ifeq +6 -> 193
    //   190: goto +82 -> 272
    //   193: goto +95 -> 288
    //   196: astore_1
    //   197: aload_1
    //   198: athrow
    //   199: goto -155 -> 44
    //   202: iconst_0
    //   203: istore 9
    //   205: goto -112 -> 93
    //   208: goto -164 -> 44
    //   211: goto -167 -> 44
    //   214: aload_0
    //   215: invokespecial 74	java/lang/Object:<init>	()V
    //   218: aload_1
    //   219: invokestatic 79	o/fT:ˎ	(Ljava/lang/String;)Z
    //   222: ifne +6 -> 228
    //   225: goto +54 -> 279
    //   228: goto -26 -> 202
    //   231: bipush 14
    //   233: istore 8
    //   235: goto -112 -> 123
    //   238: iload 8
    //   240: lookupswitch	default:+28->268, 24:+-204->36, 30:+31->271
    //   268: goto -232 -> 36
    //   271: return
    //   272: bipush 24
    //   274: istore 8
    //   276: goto -38 -> 238
    //   279: iconst_1
    //   280: istore 9
    //   282: goto -279 -> 3
    //   285: goto -241 -> 44
    //   288: bipush 30
    //   290: istore 8
    //   292: goto -54 -> 238
    // Local variable table:
    //   start	length	slot	name	signature
    //   0	295	0	this	mF
    //   0	295	1	paramString1	String
    //   0	295	2	paramString2	String
    //   0	295	3	paramString3	String
    //   0	295	4	paramString4	String
    //   0	295	5	paramString5	String
    //   0	295	6	paramString6	String
    //   0	295	7	paramString7	String
    //   9	282	8	i	int
    //   44	237	9	bool	boolean
    // Exception table:
    //   from	to	target	type
    //   174	183	33	java/lang/Exception
    //   162	167	196	java/lang/Exception
  }
  
  /* Error */
  private static String ˎ(int[] paramArrayOfInt, int paramInt)
  {
    // Byte code:
    //   0: goto +37 -> 37
    //   3: iconst_4
    //   4: newarray char
    //   6: astore 4
    //   8: aload_0
    //   9: arraylength
    //   10: iconst_1
    //   11: ishl
    //   12: newarray char
    //   14: astore 5
    //   16: getstatic 43	o/mF:ʼ	[I
    //   19: invokevirtual 85	[I:clone	()Ljava/lang/Object;
    //   22: checkcast 81	[I
    //   25: astore 6
    //   27: iconst_0
    //   28: istore_2
    //   29: goto +94 -> 123
    //   32: iconst_1
    //   33: istore_3
    //   34: goto +62 -> 96
    //   37: goto -34 -> 3
    //   40: new 87	java/lang/String
    //   43: dup
    //   44: aload 5
    //   46: iconst_0
    //   47: iload_1
    //   48: invokespecial 90	java/lang/String:<init>	([CII)V
    //   51: astore_0
    //   52: goto +83 -> 135
    //   55: iconst_0
    //   56: istore_3
    //   57: goto +39 -> 96
    //   60: goto +100 -> 160
    //   63: getstatic 21	o/mF:ॱॱ	I
    //   66: bipush 49
    //   68: iadd
    //   69: istore_3
    //   70: iload_3
    //   71: sipush 128
    //   74: irem
    //   75: putstatic 23	o/mF:ʻ	I
    //   78: iload_3
    //   79: iconst_2
    //   80: irem
    //   81: ifne +6 -> 87
    //   84: goto -24 -> 60
    //   87: goto +73 -> 160
    //   90: astore_0
    //   91: aload_0
    //   92: athrow
    //   93: goto +30 -> 123
    //   96: iload_3
    //   97: tableswitch	default:+23->120, 0:+-34->63, 1:+-57->40
    //   120: goto -80 -> 40
    //   123: iload_2
    //   124: aload_0
    //   125: arraylength
    //   126: if_icmpge +6 -> 132
    //   129: goto -74 -> 55
    //   132: goto -100 -> 32
    //   135: getstatic 23	o/mF:ʻ	I
    //   138: bipush 87
    //   140: iadd
    //   141: istore_1
    //   142: iload_1
    //   143: sipush 128
    //   146: irem
    //   147: putstatic 21	o/mF:ॱॱ	I
    //   150: iload_1
    //   151: iconst_2
    //   152: irem
    //   153: ifeq +5 -> 158
    //   156: aload_0
    //   157: areturn
    //   158: aload_0
    //   159: areturn
    //   160: aload 4
    //   162: iconst_0
    //   163: aload_0
    //   164: iload_2
    //   165: iaload
    //   166: bipush 16
    //   168: ishr
    //   169: i2c
    //   170: castore
    //   171: aload 4
    //   173: iconst_1
    //   174: aload_0
    //   175: iload_2
    //   176: iaload
    //   177: i2c
    //   178: castore
    //   179: aload 4
    //   181: iconst_2
    //   182: aload_0
    //   183: iload_2
    //   184: iconst_1
    //   185: iadd
    //   186: iaload
    //   187: bipush 16
    //   189: ishr
    //   190: i2c
    //   191: castore
    //   192: aload 4
    //   194: iconst_3
    //   195: aload_0
    //   196: iload_2
    //   197: iconst_1
    //   198: iadd
    //   199: iaload
    //   200: i2c
    //   201: castore
    //   202: aload 4
    //   204: aload 6
    //   206: iconst_0
    //   207: invokestatic 95	o/oN:ˏ	([C[IZ)[I
    //   210: pop
    //   211: aload 5
    //   213: iload_2
    //   214: iconst_1
    //   215: ishl
    //   216: aload 4
    //   218: iconst_0
    //   219: caload
    //   220: castore
    //   221: aload 5
    //   223: iload_2
    //   224: iconst_1
    //   225: ishl
    //   226: iconst_1
    //   227: iadd
    //   228: aload 4
    //   230: iconst_1
    //   231: caload
    //   232: castore
    //   233: aload 5
    //   235: iload_2
    //   236: iconst_1
    //   237: ishl
    //   238: iconst_2
    //   239: iadd
    //   240: aload 4
    //   242: iconst_2
    //   243: caload
    //   244: castore
    //   245: aload 5
    //   247: iload_2
    //   248: iconst_1
    //   249: ishl
    //   250: iconst_3
    //   251: iadd
    //   252: aload 4
    //   254: iconst_3
    //   255: caload
    //   256: castore
    //   257: iload_2
    //   258: iconst_2
    //   259: iadd
    //   260: istore_2
    //   261: goto -168 -> 93
    // Local variable table:
    //   start	length	slot	name	signature
    //   0	264	0	paramArrayOfInt	int[]
    //   0	264	1	paramInt	int
    //   28	233	2	i	int
    //   33	64	3	j	int
    //   6	247	4	arrayOfChar1	char[]
    //   14	232	5	arrayOfChar2	char[]
    //   25	180	6	arrayOfInt	int[]
    // Exception table:
    //   from	to	target	type
    //   135	142	90	java/lang/Exception
    //   142	150	90	java/lang/Exception
    //   202	211	90	java/lang/Exception
  }
  
  public static mF ˎ(Context paramContext)
  {
    int i;
    label70:
    fo localFo;
    switch (i)
    {
    default: 
      break;
    case 23: 
      i = ॱॱ + 57;
      ʻ = i % 128;
      if (i % 2 != 0)
      {
        break label180;
        throw new NullPointerException();
        localFo = new fo(paramContext);
        paramContext = localFo.ॱ("google_app_id");
        if (TextUtils.isEmpty(paramContext)) {
          break label171;
        }
      }
      for (;;)
      {
        switch (i)
        {
        case 50: 
        default: 
          label99:
          break;
        }
        do
        {
          break label169;
          i = 4;
          break;
          i = 50;
          break label99;
          i = ʻ + 61;
          ॱॱ = i % 128;
        } while (i % 2 != 0);
        label169:
        return null;
        label171:
        i = 23;
        break;
        break label70;
        label180:
        i = 94;
      }
    }
    return new mF(paramContext, localFo.ॱ(ˎ(new int[] { 1691794010, -1398549881, 273600782, 300583246, 1675245058, -2089931747, 1728766250, -1057334030 }, 14).intern()), localFo.ॱ("firebase_database_url"), localFo.ॱ("ga_trackingId"), localFo.ॱ("gcm_defaultSenderId"), localFo.ॱ("google_storage_bucket"), localFo.ॱ("project_id"));
  }
  
  /* Error */
  public final boolean equals(Object paramObject)
  {
    // Byte code:
    //   0: goto +341 -> 341
    //   3: getstatic 21	o/mF:ॱॱ	I
    //   6: bipush 93
    //   8: iadd
    //   9: istore_2
    //   10: iload_2
    //   11: sipush 128
    //   14: irem
    //   15: putstatic 23	o/mF:ʻ	I
    //   18: iload_2
    //   19: iconst_2
    //   20: irem
    //   21: ifne +6 -> 27
    //   24: goto +312 -> 336
    //   27: goto +304 -> 331
    //   30: getstatic 21	o/mF:ॱॱ	I
    //   33: bipush 35
    //   35: iadd
    //   36: istore_2
    //   37: iload_2
    //   38: sipush 128
    //   41: irem
    //   42: putstatic 23	o/mF:ʻ	I
    //   45: iload_2
    //   46: iconst_2
    //   47: irem
    //   48: ifne +6 -> 54
    //   51: goto +124 -> 175
    //   54: goto +175 -> 229
    //   57: bipush 52
    //   59: istore_2
    //   60: goto +291 -> 351
    //   63: aload_0
    //   64: getfield 63	o/mF:ॱ	Ljava/lang/String;
    //   67: aload_1
    //   68: getfield 63	o/mF:ॱ	Ljava/lang/String;
    //   71: invokestatic 145	o/fa:ˊ	(Ljava/lang/Object;Ljava/lang/Object;)Z
    //   74: ifeq +6 -> 80
    //   77: goto +243 -> 320
    //   80: goto +175 -> 255
    //   83: getstatic 21	o/mF:ॱॱ	I
    //   86: bipush 61
    //   88: iadd
    //   89: istore_2
    //   90: iload_2
    //   91: sipush 128
    //   94: irem
    //   95: putstatic 23	o/mF:ʻ	I
    //   98: iload_2
    //   99: iconst_2
    //   100: irem
    //   101: ifne +6 -> 107
    //   104: goto +156 -> 260
    //   107: iconst_0
    //   108: ireturn
    //   109: aload_0
    //   110: getfield 71	o/mF:ᐝ	Ljava/lang/String;
    //   113: aload_1
    //   114: getfield 71	o/mF:ᐝ	Ljava/lang/String;
    //   117: invokestatic 145	o/fa:ˊ	(Ljava/lang/Object;Ljava/lang/Object;)Z
    //   120: ifeq +6 -> 126
    //   123: goto -66 -> 57
    //   126: goto +337 -> 463
    //   129: aload_0
    //   130: getfield 67	o/mF:ˏ	Ljava/lang/String;
    //   133: aload_1
    //   134: getfield 67	o/mF:ˏ	Ljava/lang/String;
    //   137: invokestatic 145	o/fa:ˊ	(Ljava/lang/Object;Ljava/lang/Object;)Z
    //   140: ifeq +6 -> 146
    //   143: goto -113 -> 30
    //   146: goto +171 -> 317
    //   149: iload_2
    //   150: tableswitch	default:+22->172, 0:+197->347, 1:+199->349
    //   172: goto +175 -> 347
    //   175: aload_0
    //   176: getfield 69	o/mF:ˎ	Ljava/lang/String;
    //   179: aload_1
    //   180: getfield 69	o/mF:ˎ	Ljava/lang/String;
    //   183: invokestatic 145	o/fa:ˊ	(Ljava/lang/Object;Ljava/lang/Object;)Z
    //   186: istore_3
    //   187: bipush 59
    //   189: iconst_0
    //   190: idiv
    //   191: istore_2
    //   192: iload_3
    //   193: ifeq +6 -> 199
    //   196: goto -87 -> 109
    //   199: goto +118 -> 317
    //   202: getstatic 23	o/mF:ʻ	I
    //   205: bipush 121
    //   207: iadd
    //   208: istore_2
    //   209: iload_2
    //   210: sipush 128
    //   213: irem
    //   214: putstatic 21	o/mF:ॱॱ	I
    //   217: iload_2
    //   218: iconst_2
    //   219: irem
    //   220: ifeq +6 -> 226
    //   223: goto +91 -> 314
    //   226: goto +243 -> 469
    //   229: aload_0
    //   230: getfield 69	o/mF:ˎ	Ljava/lang/String;
    //   233: aload_1
    //   234: getfield 69	o/mF:ˎ	Ljava/lang/String;
    //   237: invokestatic 145	o/fa:ˊ	(Ljava/lang/Object;Ljava/lang/Object;)Z
    //   240: ifeq +6 -> 246
    //   243: goto -134 -> 109
    //   246: goto +71 -> 317
    //   249: bipush 20
    //   251: istore_2
    //   252: goto +179 -> 431
    //   255: iconst_1
    //   256: istore_2
    //   257: goto +148 -> 405
    //   260: goto -153 -> 107
    //   263: aload_1
    //   264: checkcast 2	o/mF
    //   267: astore_1
    //   268: aload_0
    //   269: getfield 61	o/mF:ˋ	Ljava/lang/String;
    //   272: astore 4
    //   274: aload_1
    //   275: getfield 61	o/mF:ˋ	Ljava/lang/String;
    //   278: astore 5
    //   280: aload 4
    //   282: aload 5
    //   284: invokestatic 145	o/fa:ˊ	(Ljava/lang/Object;Ljava/lang/Object;)Z
    //   287: istore_3
    //   288: iload_3
    //   289: ifeq +6 -> 295
    //   292: goto -229 -> 63
    //   295: goto +22 -> 317
    //   298: astore_1
    //   299: aload_1
    //   300: athrow
    //   301: aload_1
    //   302: instanceof 2
    //   305: ifne +6 -> 311
    //   308: goto -59 -> 249
    //   311: goto +14 -> 325
    //   314: goto +155 -> 469
    //   317: goto -234 -> 83
    //   320: iconst_0
    //   321: istore_2
    //   322: goto +83 -> 405
    //   325: bipush 39
    //   327: istore_2
    //   328: goto +103 -> 431
    //   331: iconst_1
    //   332: istore_2
    //   333: goto -184 -> 149
    //   336: iconst_0
    //   337: istore_2
    //   338: goto -189 -> 149
    //   341: goto -40 -> 301
    //   344: astore_1
    //   345: aload_1
    //   346: athrow
    //   347: iconst_1
    //   348: ireturn
    //   349: iconst_1
    //   350: ireturn
    //   351: iload_2
    //   352: lookupswitch	default:+28->380, 52:+-150->202, 53:+-35->317
    //   380: goto -63 -> 317
    //   383: aload_0
    //   384: getfield 65	o/mF:ˊ	Ljava/lang/String;
    //   387: aload_1
    //   388: getfield 65	o/mF:ˊ	Ljava/lang/String;
    //   391: invokestatic 145	o/fa:ˊ	(Ljava/lang/Object;Ljava/lang/Object;)Z
    //   394: ifeq +6 -> 400
    //   397: goto -268 -> 129
    //   400: goto -83 -> 317
    //   403: iconst_0
    //   404: ireturn
    //   405: iload_2
    //   406: tableswitch	default:+22->428, 0:+-23->383, 1:+-89->317
    //   428: goto -45 -> 383
    //   431: iload_2
    //   432: lookupswitch	default:+28->460, 20:+-29->403, 39:+-169->263
    //   460: goto -197 -> 263
    //   463: bipush 53
    //   465: istore_2
    //   466: goto -115 -> 351
    //   469: aload_0
    //   470: getfield 73	o/mF:ʽ	Ljava/lang/String;
    //   473: aload_1
    //   474: getfield 73	o/mF:ʽ	Ljava/lang/String;
    //   477: invokestatic 145	o/fa:ˊ	(Ljava/lang/Object;Ljava/lang/Object;)Z
    //   480: ifeq +6 -> 486
    //   483: goto -480 -> 3
    //   486: goto -169 -> 317
    // Local variable table:
    //   start	length	slot	name	signature
    //   0	489	0	this	mF
    //   0	489	1	paramObject	Object
    //   9	457	2	i	int
    //   186	103	3	bool	boolean
    //   272	9	4	str1	String
    //   278	5	5	str2	String
    // Exception table:
    //   from	to	target	type
    //   202	209	298	java/lang/Exception
    //   209	217	298	java/lang/Exception
    //   209	217	344	java/lang/Exception
    //   263	268	344	java/lang/Exception
    //   268	274	344	java/lang/Exception
    //   274	280	344	java/lang/Exception
    //   280	288	344	java/lang/Exception
  }
  
  public final int hashCode()
  {
    break label118;
    int i = ʻ + 91;
    ॱॱ = i % 128;
    label30:
    int j;
    if (i % 2 == 0)
    {
      break label56;
      i = ʻ + 13;
      ॱॱ = i % 128;
      if (i % 2 == 0) {
        return j;
      }
    }
    for (;;)
    {
      label56:
      j = Arrays.hashCode(new Object[] { this.ˋ, this.ॱ, this.ˊ, this.ˏ, this.ˎ, this.ᐝ, this.ʽ });
      break label30;
      label118:
      break;
      return j;
    }
  }
  
  public final String toString()
  {
    break label142;
    int i = ʻ + 17;
    ॱॱ = i % 128;
    if (i % 2 == 0)
    {
      break label77;
      for (;;)
      {
        i = 1;
        break label145;
        label35:
        i = ॱॱ + 15;
        ʻ = i % 128;
        if (i % 2 == 0) {
          break;
        }
      }
    }
    String str;
    for (;;)
    {
      i = 12 / 0;
      return str;
      break label77;
      i = 0;
      break label145;
      label77:
      str = fa.ॱ(this).ˏ("applicationId", this.ˋ).ˏ("apiKey", this.ॱ).ˏ("databaseUrl", this.ˊ).ˏ("gcmSenderId", this.ˎ).ˏ("storageBucket", this.ᐝ).ˏ("projectId", this.ʽ).toString();
      break label35;
      label142:
      break;
      label145:
      switch (i)
      {
      }
    }
    return str;
  }
  
  /* Error */
  public final String ˊ()
  {
    // Byte code:
    //   0: goto +33 -> 33
    //   3: getstatic 21	o/mF:ॱॱ	I
    //   6: bipush 35
    //   8: iadd
    //   9: istore_1
    //   10: iload_1
    //   11: sipush 128
    //   14: irem
    //   15: putstatic 23	o/mF:ʻ	I
    //   18: iload_1
    //   19: iconst_2
    //   20: irem
    //   21: ifne +6 -> 27
    //   24: goto +20 -> 44
    //   27: goto +9 -> 36
    //   30: astore_2
    //   31: aload_2
    //   32: athrow
    //   33: goto -30 -> 3
    //   36: aload_0
    //   37: getfield 61	o/mF:ˋ	Ljava/lang/String;
    //   40: astore_2
    //   41: goto +6 -> 47
    //   44: goto -8 -> 36
    //   47: getstatic 23	o/mF:ʻ	I
    //   50: bipush 111
    //   52: iadd
    //   53: istore_1
    //   54: iload_1
    //   55: sipush 128
    //   58: irem
    //   59: putstatic 21	o/mF:ॱॱ	I
    //   62: iload_1
    //   63: iconst_2
    //   64: irem
    //   65: ifeq +5 -> 70
    //   68: aload_2
    //   69: areturn
    //   70: aload_2
    //   71: areturn
    // Local variable table:
    //   start	length	slot	name	signature
    //   0	72	0	this	mF
    //   9	56	1	i	int
    //   30	2	2	localException	Exception
    //   40	31	2	str	String
    // Exception table:
    //   from	to	target	type
    //   36	41	30	java/lang/Exception
  }
  
  /* Error */
  public final String ˎ()
  {
    // Byte code:
    //   0: goto +93 -> 93
    //   3: bipush 14
    //   5: istore_1
    //   6: goto +3 -> 9
    //   9: iload_1
    //   10: lookupswitch	default:+26->36, 14:+29->39, 73:+75->85
    //   36: goto +49 -> 85
    //   39: aload_0
    //   40: getfield 69	o/mF:ˎ	Ljava/lang/String;
    //   43: astore_2
    //   44: bipush 15
    //   46: iconst_0
    //   47: idiv
    //   48: istore_1
    //   49: goto +50 -> 99
    //   52: bipush 73
    //   54: istore_1
    //   55: goto -46 -> 9
    //   58: getstatic 21	o/mF:ॱॱ	I
    //   61: bipush 17
    //   63: iadd
    //   64: istore_1
    //   65: iload_1
    //   66: sipush 128
    //   69: irem
    //   70: putstatic 23	o/mF:ʻ	I
    //   73: iload_1
    //   74: iconst_2
    //   75: irem
    //   76: ifne +6 -> 82
    //   79: goto -76 -> 3
    //   82: goto -30 -> 52
    //   85: aload_0
    //   86: getfield 69	o/mF:ˎ	Ljava/lang/String;
    //   89: astore_2
    //   90: goto +9 -> 99
    //   93: goto -35 -> 58
    //   96: astore_2
    //   97: aload_2
    //   98: athrow
    //   99: getstatic 21	o/mF:ॱॱ	I
    //   102: bipush 71
    //   104: iadd
    //   105: istore_1
    //   106: iload_1
    //   107: sipush 128
    //   110: irem
    //   111: putstatic 23	o/mF:ʻ	I
    //   114: iload_1
    //   115: iconst_2
    //   116: irem
    //   117: ifne +5 -> 122
    //   120: aload_2
    //   121: areturn
    //   122: aload_2
    //   123: areturn
    // Local variable table:
    //   start	length	slot	name	signature
    //   0	124	0	this	mF
    //   5	112	1	i	int
    //   43	47	2	str	String
    //   96	27	2	localException	Exception
    // Exception table:
    //   from	to	target	type
    //   99	106	96	java/lang/Exception
    //   106	114	96	java/lang/Exception
  }
}
