package o;

import android.graphics.drawable.Drawable;
import android.os.Bundle;
import android.util.Pair;
import android.view.View;
import android.widget.ScrollView;
import android.widget.TextView;
import java.math.BigDecimal;

public class Mf
  extends LZ<Mt>
{
  private static int ˉ = -197653850;
  private static int ˊᐝ;
  private static int ˋˊ;
  private static byte[] ˋˋ;
  private static short[] ˌ;
  private static int ˍ;
  private static int ˎˎ = 0;
  private FP ˊˋ;
  
  static
  {
    ˍ = 1;
    ˋˊ = 59;
    ˋˋ = new byte[] { -27, -46, -34, -50, -39, -24, -53, -51, -24, -9, -69, -54, -14, -38, -38, -31, -23, -17, -19, -41, -27, -20, -37, -9, -24, -44, -21, -13, -43, -28, -5, -28, -43, -28, -30, -7, 108, 101, 113, -121, 108, 99, -126, 111, 117, 108, 112, 98, -126, 111, 106, 120, 99, 127, 100, 115, -126, 111, 96, 111, 109, -124, 0, 0, 0 };
    ˊᐝ = -661510029;
  }
  
  public Mf() {}
  
  private void ˉ()
  {
    ((Mt)this.ॱˊ).ˏ(this.ʽॱ);
    ((Mt)this.ॱˊ).ˊ(this.ʾ);
    ((Mt)this.ॱˊ).ˏ(this.ʼॱ);
    ˋᐝ();
    ˎˎ();
    ((Mt)this.ॱˊ).ᐝ.requestFocus();
    BigDecimal localBigDecimal1 = this.ˊˋ.ʼ();
    BigDecimal localBigDecimal2 = this.ˊˋ.ᐝ();
    ((Mt)this.ॱˊ).ᐝ.setValidationRule(new Fq(localBigDecimal1.floatValue()));
    ((Mt)this.ॱˊ).ᐝ.setValidationRule(new Ft(localBigDecimal2.floatValue()));
    ((Mt)this.ॱˊ).ॱॱ.ˏ(new Fs(30));
    try
    {
      int i = ˎˎ;
      i += 31;
      ˍ = i % 128;
      if (i % 2 == 0) {
        return;
      }
      return;
    }
    catch (Exception localException)
    {
      throw localException;
    }
  }
  
  /* Error */
  private static String ˋ(short paramShort, int paramInt1, byte paramByte, int paramInt2, int paramInt3)
  {
    // Byte code:
    //   0: goto +668 -> 668
    //   3: goto +488 -> 491
    //   6: iload 4
    //   8: lookupswitch	default:+28->36, 12:+518->526, 59:+235->243
    //   36: goto +207 -> 243
    //   39: bipush 40
    //   41: istore 4
    //   43: goto +418 -> 461
    //   46: getstatic 25	o/Mf:ˎˎ	I
    //   49: bipush 91
    //   51: iadd
    //   52: istore 6
    //   54: iload 6
    //   56: sipush 128
    //   59: irem
    //   60: putstatic 27	o/Mf:ˍ	I
    //   63: iload 6
    //   65: iconst_2
    //   66: irem
    //   67: ifne +6 -> 73
    //   70: goto +589 -> 659
    //   73: goto +543 -> 616
    //   76: aload 9
    //   78: invokevirtual 182	java/lang/StringBuilder:toString	()Ljava/lang/String;
    //   81: areturn
    //   82: getstatic 27	o/Mf:ˍ	I
    //   85: istore 4
    //   87: iload 4
    //   89: bipush 125
    //   91: iadd
    //   92: istore 4
    //   94: iload 4
    //   96: sipush 128
    //   99: irem
    //   100: putstatic 25	o/Mf:ˎˎ	I
    //   103: iload 4
    //   105: iconst_2
    //   106: irem
    //   107: ifeq +6 -> 113
    //   110: goto +313 -> 423
    //   113: goto +118 -> 231
    //   116: astore 9
    //   118: aload 9
    //   120: athrow
    //   121: getstatic 25	o/Mf:ˎˎ	I
    //   124: bipush 29
    //   126: iadd
    //   127: istore 4
    //   129: iload 4
    //   131: sipush 128
    //   134: irem
    //   135: putstatic 27	o/Mf:ˍ	I
    //   138: iload 4
    //   140: iconst_2
    //   141: irem
    //   142: ifne +6 -> 148
    //   145: goto -106 -> 39
    //   148: goto +303 -> 451
    //   151: iload 6
    //   153: tableswitch	default:+23->176, 0:+428->581, 1:+159->312
    //   176: goto +136 -> 312
    //   179: new 178	java/lang/StringBuilder
    //   182: dup
    //   183: invokespecial 183	java/lang/StringBuilder:<init>	()V
    //   186: astore 9
    //   188: getstatic 29	o/Mf:ˋˊ	I
    //   191: iload 4
    //   193: iadd
    //   194: istore 4
    //   196: iload 4
    //   198: istore 7
    //   200: iload 4
    //   202: iconst_m1
    //   203: if_icmpne +6 -> 209
    //   206: goto +239 -> 445
    //   209: goto +453 -> 662
    //   212: aload 9
    //   214: iload 5
    //   216: invokevirtual 187	java/lang/StringBuilder:append	(C)Ljava/lang/StringBuilder;
    //   219: pop
    //   220: iload_3
    //   221: iconst_1
    //   222: iadd
    //   223: istore_3
    //   224: iload 5
    //   226: istore 7
    //   228: goto +409 -> 637
    //   231: getstatic 78	o/Mf:ˋˋ	[B
    //   234: ifnull +6 -> 240
    //   237: goto +6 -> 243
    //   240: goto +286 -> 526
    //   243: getstatic 78	o/Mf:ˋˋ	[B
    //   246: astore 10
    //   248: aload 10
    //   250: getstatic 84	o/Mf:ˉ	I
    //   253: iload_1
    //   254: iadd
    //   255: baload
    //   256: istore 4
    //   258: getstatic 29	o/Mf:ˋˊ	I
    //   261: istore 7
    //   263: iload 4
    //   265: iload 7
    //   267: iadd
    //   268: i2b
    //   269: istore 4
    //   271: goto +400 -> 671
    //   274: iload_1
    //   275: iload 4
    //   277: iadd
    //   278: iconst_2
    //   279: isub
    //   280: iload 7
    //   282: iadd
    //   283: iload 6
    //   285: iadd
    //   286: istore_1
    //   287: getstatic 81	o/Mf:ˊᐝ	I
    //   290: iload_3
    //   291: iadd
    //   292: i2c
    //   293: istore 5
    //   295: aload 9
    //   297: iload 5
    //   299: invokevirtual 187	java/lang/StringBuilder:append	(C)Ljava/lang/StringBuilder;
    //   302: pop
    //   303: iconst_1
    //   304: istore_3
    //   305: iload 5
    //   307: istore 7
    //   309: goto +328 -> 637
    //   312: getstatic 189	o/Mf:ˌ	[S
    //   315: astore 10
    //   317: iload_1
    //   318: iconst_1
    //   319: isub
    //   320: istore 6
    //   322: aload 10
    //   324: iload_1
    //   325: saload
    //   326: iload_0
    //   327: iadd
    //   328: i2s
    //   329: iload_2
    //   330: ixor
    //   331: iload 7
    //   333: iadd
    //   334: i2c
    //   335: istore 5
    //   337: iload 6
    //   339: istore_1
    //   340: goto -128 -> 212
    //   343: iconst_1
    //   344: istore 6
    //   346: goto -195 -> 151
    //   349: iload 7
    //   351: istore 4
    //   353: iload 8
    //   355: tableswitch	default:+21->376, 0:+-273->82, 1:+136->491
    //   376: iload 7
    //   378: istore 4
    //   380: goto +111 -> 491
    //   383: iconst_0
    //   384: istore 8
    //   386: goto -37 -> 349
    //   389: bipush 43
    //   391: istore 7
    //   393: goto +152 -> 545
    //   396: getstatic 84	o/Mf:ˉ	I
    //   399: istore 7
    //   401: iload 6
    //   403: ifeq +6 -> 409
    //   406: goto -360 -> 46
    //   409: goto +292 -> 701
    //   412: iload 6
    //   414: ifeq +6 -> 420
    //   417: goto -34 -> 383
    //   420: goto +202 -> 622
    //   423: getstatic 78	o/Mf:ˋˋ	[B
    //   426: astore 10
    //   428: bipush 85
    //   430: iconst_0
    //   431: idiv
    //   432: istore 4
    //   434: aload 10
    //   436: ifnull +6 -> 442
    //   439: goto +63 -> 502
    //   442: goto +210 -> 652
    //   445: iconst_1
    //   446: istore 6
    //   448: goto -327 -> 121
    //   451: bipush 19
    //   453: istore 4
    //   455: goto +6 -> 461
    //   458: goto -455 -> 3
    //   461: iload 4
    //   463: lookupswitch	default:+25->488, 19:+165->628, 40:+186->649
    //   488: goto +161 -> 649
    //   491: iload 4
    //   493: ifle +6 -> 499
    //   496: goto +113 -> 609
    //   499: goto -110 -> 389
    //   502: bipush 59
    //   504: istore 4
    //   506: goto -500 -> 6
    //   509: getstatic 78	o/Mf:ˋˋ	[B
    //   512: ifnull +6 -> 518
    //   515: goto +116 -> 631
    //   518: goto -175 -> 343
    //   521: astore 9
    //   523: aload 9
    //   525: athrow
    //   526: getstatic 189	o/Mf:ˌ	[S
    //   529: getstatic 84	o/Mf:ˉ	I
    //   532: iload_1
    //   533: iadd
    //   534: saload
    //   535: getstatic 29	o/Mf:ˋˊ	I
    //   538: iadd
    //   539: i2s
    //   540: istore 4
    //   542: goto -51 -> 491
    //   545: iload 7
    //   547: lookupswitch	default:+25->572, 43:+-471->76, 67:+-151->396
    //   572: goto -496 -> 76
    //   575: iload 6
    //   577: istore_1
    //   578: goto -366 -> 212
    //   581: getstatic 78	o/Mf:ˋˋ	[B
    //   584: astore 10
    //   586: iload_1
    //   587: iconst_1
    //   588: isub
    //   589: istore 6
    //   591: aload 10
    //   593: iload_1
    //   594: baload
    //   595: iload_0
    //   596: iadd
    //   597: i2b
    //   598: iload_2
    //   599: ixor
    //   600: iload 7
    //   602: iadd
    //   603: i2c
    //   604: istore 5
    //   606: goto -31 -> 575
    //   609: bipush 67
    //   611: istore 7
    //   613: goto -68 -> 545
    //   616: iconst_1
    //   617: istore 6
    //   619: goto -345 -> 274
    //   622: iconst_1
    //   623: istore 8
    //   625: goto -276 -> 349
    //   628: goto -216 -> 412
    //   631: iconst_0
    //   632: istore 6
    //   634: goto -483 -> 151
    //   637: iload_3
    //   638: iload 4
    //   640: if_icmpge +6 -> 646
    //   643: goto -134 -> 509
    //   646: goto -570 -> 76
    //   649: goto -237 -> 412
    //   652: bipush 12
    //   654: istore 4
    //   656: goto -650 -> 6
    //   659: goto -43 -> 616
    //   662: iconst_0
    //   663: istore 6
    //   665: goto -253 -> 412
    //   668: goto -489 -> 179
    //   671: getstatic 27	o/Mf:ˍ	I
    //   674: bipush 77
    //   676: iadd
    //   677: istore 7
    //   679: iload 7
    //   681: sipush 128
    //   684: irem
    //   685: putstatic 25	o/Mf:ˎˎ	I
    //   688: iload 7
    //   690: iconst_2
    //   691: irem
    //   692: ifeq +6 -> 698
    //   695: goto -237 -> 458
    //   698: goto -695 -> 3
    //   701: iconst_0
    //   702: istore 6
    //   704: goto -430 -> 274
    // Local variable table:
    //   start	length	slot	name	signature
    //   0	707	0	paramShort	short
    //   0	707	1	paramInt1	int
    //   0	707	2	paramByte	byte
    //   0	707	3	paramInt2	int
    //   0	707	4	paramInt3	int
    //   214	391	5	i	int
    //   52	651	6	j	int
    //   198	494	7	k	int
    //   353	271	8	m	int
    //   76	1	9	localObject1	Object
    //   116	3	9	localException1	Exception
    //   186	110	9	localStringBuilder	StringBuilder
    //   521	3	9	localException2	Exception
    //   246	346	10	localObject2	Object
    // Exception table:
    //   from	to	target	type
    //   243	248	116	java/lang/Exception
    //   248	258	116	java/lang/Exception
    //   258	263	116	java/lang/Exception
    //   82	87	521	java/lang/Exception
    //   94	103	521	java/lang/Exception
  }
  
  /* Error */
  private void ˋˋ()
  {
    // Byte code:
    //   0: goto +667 -> 667
    //   3: new 191	android/os/Bundle
    //   6: dup
    //   7: invokespecial 192	android/os/Bundle:<init>	()V
    //   10: astore_3
    //   11: aload_3
    //   12: aload_0
    //   13: invokevirtual 197	android/content/Context:getPackageName	()Ljava/lang/String;
    //   16: iconst_2
    //   17: invokevirtual 203	java/lang/String:codePointAt	(I)I
    //   20: bipush 20
    //   22: isub
    //   23: i2s
    //   24: aload_0
    //   25: invokevirtual 207	android/content/Context:getApplicationInfo	()Landroid/content/pm/ApplicationInfo;
    //   28: getfield 212	android/content/pm/ApplicationInfo:targetSdkVersion	I
    //   31: ldc -43
    //   33: iadd
    //   34: iconst_0
    //   35: aload_0
    //   36: invokevirtual 217	android/content/Context:getResources	()Landroid/content/res/Resources;
    //   39: ldc -38
    //   41: invokevirtual 224	android/content/res/Resources:getString	(I)Ljava/lang/String;
    //   44: bipush 33
    //   46: bipush 34
    //   48: invokevirtual 228	java/lang/String:substring	(II)Ljava/lang/String;
    //   51: iconst_0
    //   52: invokevirtual 203	java/lang/String:codePointAt	(I)I
    //   55: ldc -27
    //   57: iadd
    //   58: aload_0
    //   59: invokevirtual 217	android/content/Context:getResources	()Landroid/content/res/Resources;
    //   62: ldc -26
    //   64: invokevirtual 224	android/content/res/Resources:getString	(I)Ljava/lang/String;
    //   67: iconst_3
    //   68: iconst_4
    //   69: invokevirtual 228	java/lang/String:substring	(II)Ljava/lang/String;
    //   72: iconst_0
    //   73: invokevirtual 203	java/lang/String:codePointAt	(I)I
    //   76: bipush 69
    //   78: isub
    //   79: invokestatic 232	o/Mf:ˋ	(SIBII)Ljava/lang/String;
    //   82: invokevirtual 235	java/lang/String:intern	()Ljava/lang/String;
    //   85: aload_0
    //   86: getfield 100	o/Mf:ʽॱ	Lo/Gh;
    //   89: invokevirtual 239	android/os/Bundle:putParcelable	(Ljava/lang/String;Landroid/os/Parcelable;)V
    //   92: aload_0
    //   93: invokestatic 244	o/Ic:ˏ	(Landroid/content/Context;)Lo/Ic;
    //   96: invokevirtual 248	o/Ic:ˈ	()Lo/j;
    //   99: aload_3
    //   100: invokevirtual 253	o/j:ˊ	(Landroid/os/Bundle;)Lo/j;
    //   103: aload_0
    //   104: invokevirtual 207	android/content/Context:getApplicationInfo	()Landroid/content/pm/ApplicationInfo;
    //   107: getfield 212	android/content/pm/ApplicationInfo:targetSdkVersion	I
    //   110: sipush 138
    //   113: isub
    //   114: i2s
    //   115: aload_0
    //   116: invokevirtual 207	android/content/Context:getApplicationInfo	()Landroid/content/pm/ApplicationInfo;
    //   119: getfield 212	android/content/pm/ApplicationInfo:targetSdkVersion	I
    //   122: ldc -2
    //   124: iadd
    //   125: iconst_0
    //   126: aload_0
    //   127: invokevirtual 217	android/content/Context:getResources	()Landroid/content/res/Resources;
    //   130: ldc -1
    //   132: invokevirtual 224	android/content/res/Resources:getString	(I)Ljava/lang/String;
    //   135: iconst_0
    //   136: iconst_5
    //   137: invokevirtual 228	java/lang/String:substring	(II)Ljava/lang/String;
    //   140: invokevirtual 259	java/lang/String:length	()I
    //   143: ldc_w 260
    //   146: iadd
    //   147: aload_0
    //   148: invokevirtual 207	android/content/Context:getApplicationInfo	()Landroid/content/pm/ApplicationInfo;
    //   151: getfield 212	android/content/pm/ApplicationInfo:targetSdkVersion	I
    //   154: bipush 57
    //   156: isub
    //   157: invokestatic 232	o/Mf:ˋ	(SIBII)Ljava/lang/String;
    //   160: invokevirtual 235	java/lang/String:intern	()Ljava/lang/String;
    //   163: aload_0
    //   164: getfield 263	o/Mf:ˈ	Ljava/lang/String;
    //   167: invokevirtual 266	o/j:ˋ	(Ljava/lang/String;Ljava/lang/String;)Lo/j;
    //   170: invokevirtual 269	o/j:ˎ	()V
    //   173: goto +442 -> 615
    //   176: goto +20 -> 196
    //   179: astore_3
    //   180: aload_3
    //   181: invokevirtual 275	java/lang/Throwable:getCause	()Ljava/lang/Throwable;
    //   184: astore 4
    //   186: aload 4
    //   188: ifnull +6 -> 194
    //   191: aload 4
    //   193: athrow
    //   194: aload_3
    //   195: athrow
    //   196: aload_0
    //   197: invokevirtual 207	android/content/Context:getApplicationInfo	()Landroid/content/pm/ApplicationInfo;
    //   200: getfield 212	android/content/pm/ApplicationInfo:targetSdkVersion	I
    //   203: bipush 22
    //   205: isub
    //   206: aload_0
    //   207: invokevirtual 197	android/content/Context:getPackageName	()Ljava/lang/String;
    //   210: bipush 6
    //   212: invokevirtual 203	java/lang/String:codePointAt	(I)I
    //   215: bipush 84
    //   217: isub
    //   218: aload_0
    //   219: invokevirtual 197	android/content/Context:getPackageName	()Ljava/lang/String;
    //   222: bipush 7
    //   224: invokevirtual 203	java/lang/String:codePointAt	(I)I
    //   227: bipush 46
    //   229: isub
    //   230: i2c
    //   231: invokestatic 280	o/O:ˋ	(IIC)Ljava/lang/Object;
    //   234: checkcast 282	java/lang/Class
    //   237: ldc_w 283
    //   240: aconst_null
    //   241: invokevirtual 287	java/lang/Class:getMethod	(Ljava/lang/String;[Ljava/lang/Class;)Ljava/lang/reflect/Method;
    //   244: aconst_null
    //   245: aconst_null
    //   246: invokevirtual 293	java/lang/reflect/Method:invoke	(Ljava/lang/Object;[Ljava/lang/Object;)Ljava/lang/Object;
    //   249: astore_3
    //   250: goto +20 -> 270
    //   253: astore_3
    //   254: aload_3
    //   255: invokevirtual 275	java/lang/Throwable:getCause	()Ljava/lang/Throwable;
    //   258: astore 4
    //   260: aload 4
    //   262: ifnull +6 -> 268
    //   265: aload 4
    //   267: athrow
    //   268: aload_3
    //   269: athrow
    //   270: aload_0
    //   271: invokevirtual 217	android/content/Context:getResources	()Landroid/content/res/Resources;
    //   274: ldc_w 294
    //   277: invokevirtual 224	android/content/res/Resources:getString	(I)Ljava/lang/String;
    //   280: iconst_0
    //   281: bipush 15
    //   283: invokevirtual 228	java/lang/String:substring	(II)Ljava/lang/String;
    //   286: invokevirtual 259	java/lang/String:length	()I
    //   289: bipush 12
    //   291: isub
    //   292: aload_0
    //   293: invokevirtual 217	android/content/Context:getResources	()Landroid/content/res/Resources;
    //   296: ldc_w 295
    //   299: invokevirtual 224	android/content/res/Resources:getString	(I)Ljava/lang/String;
    //   302: iconst_0
    //   303: iconst_4
    //   304: invokevirtual 228	java/lang/String:substring	(II)Ljava/lang/String;
    //   307: iconst_3
    //   308: invokevirtual 203	java/lang/String:codePointAt	(I)I
    //   311: bipush 12
    //   313: iadd
    //   314: aload_0
    //   315: invokevirtual 197	android/content/Context:getPackageName	()Ljava/lang/String;
    //   318: iconst_3
    //   319: invokevirtual 203	java/lang/String:codePointAt	(I)I
    //   322: bipush 98
    //   324: isub
    //   325: i2c
    //   326: invokestatic 280	o/O:ˋ	(IIC)Ljava/lang/Object;
    //   329: checkcast 282	java/lang/Class
    //   332: ldc_w 296
    //   335: iconst_1
    //   336: anewarray 282	java/lang/Class
    //   339: dup
    //   340: iconst_0
    //   341: ldc -62
    //   343: aastore
    //   344: invokevirtual 287	java/lang/Class:getMethod	(Ljava/lang/String;[Ljava/lang/Class;)Ljava/lang/reflect/Method;
    //   347: aload_3
    //   348: iconst_1
    //   349: anewarray 298	java/lang/Object
    //   352: dup
    //   353: iconst_0
    //   354: aload_0
    //   355: aastore
    //   356: invokevirtual 293	java/lang/reflect/Method:invoke	(Ljava/lang/Object;[Ljava/lang/Object;)Ljava/lang/Object;
    //   359: checkcast 300	java/lang/Boolean
    //   362: invokevirtual 303	java/lang/Boolean:booleanValue	()Z
    //   365: istore_2
    //   366: bipush 80
    //   368: iconst_0
    //   369: idiv
    //   370: istore_1
    //   371: iload_2
    //   372: ifeq +6 -> 378
    //   375: goto -372 -> 3
    //   378: goto +237 -> 615
    //   381: astore_3
    //   382: aload_3
    //   383: athrow
    //   384: getstatic 25	o/Mf:ˎˎ	I
    //   387: bipush 19
    //   389: iadd
    //   390: istore_1
    //   391: iload_1
    //   392: sipush 128
    //   395: irem
    //   396: putstatic 27	o/Mf:ˍ	I
    //   399: iload_1
    //   400: iconst_2
    //   401: irem
    //   402: ifne +6 -> 408
    //   405: goto +265 -> 670
    //   408: goto +201 -> 609
    //   411: goto +20 -> 431
    //   414: astore_3
    //   415: aload_3
    //   416: invokevirtual 275	java/lang/Throwable:getCause	()Ljava/lang/Throwable;
    //   419: astore 4
    //   421: aload 4
    //   423: ifnull +6 -> 429
    //   426: aload 4
    //   428: athrow
    //   429: aload_3
    //   430: athrow
    //   431: aload_0
    //   432: invokevirtual 197	android/content/Context:getPackageName	()Ljava/lang/String;
    //   435: invokevirtual 259	java/lang/String:length	()I
    //   438: bipush 8
    //   440: isub
    //   441: aload_0
    //   442: invokevirtual 207	android/content/Context:getApplicationInfo	()Landroid/content/pm/ApplicationInfo;
    //   445: getfield 212	android/content/pm/ApplicationInfo:targetSdkVersion	I
    //   448: iconst_1
    //   449: isub
    //   450: aload_0
    //   451: invokevirtual 217	android/content/Context:getResources	()Landroid/content/res/Resources;
    //   454: ldc_w 304
    //   457: invokevirtual 224	android/content/res/Resources:getString	(I)Ljava/lang/String;
    //   460: iconst_0
    //   461: iconst_4
    //   462: invokevirtual 228	java/lang/String:substring	(II)Ljava/lang/String;
    //   465: iconst_1
    //   466: invokevirtual 203	java/lang/String:codePointAt	(I)I
    //   469: bipush 26
    //   471: isub
    //   472: i2c
    //   473: invokestatic 280	o/O:ˋ	(IIC)Ljava/lang/Object;
    //   476: checkcast 282	java/lang/Class
    //   479: ldc_w 283
    //   482: aconst_null
    //   483: invokevirtual 287	java/lang/Class:getMethod	(Ljava/lang/String;[Ljava/lang/Class;)Ljava/lang/reflect/Method;
    //   486: aconst_null
    //   487: aconst_null
    //   488: invokevirtual 293	java/lang/reflect/Method:invoke	(Ljava/lang/Object;[Ljava/lang/Object;)Ljava/lang/Object;
    //   491: astore_3
    //   492: goto +20 -> 512
    //   495: astore_3
    //   496: aload_3
    //   497: invokevirtual 275	java/lang/Throwable:getCause	()Ljava/lang/Throwable;
    //   500: astore 4
    //   502: aload 4
    //   504: ifnull +6 -> 510
    //   507: aload 4
    //   509: athrow
    //   510: aload_3
    //   511: athrow
    //   512: aload_0
    //   513: invokevirtual 217	android/content/Context:getResources	()Landroid/content/res/Resources;
    //   516: ldc_w 305
    //   519: invokevirtual 224	android/content/res/Resources:getString	(I)Ljava/lang/String;
    //   522: bipush 10
    //   524: bipush 18
    //   526: invokevirtual 228	java/lang/String:substring	(II)Ljava/lang/String;
    //   529: iconst_3
    //   530: invokevirtual 203	java/lang/String:codePointAt	(I)I
    //   533: sipush 241
    //   536: isub
    //   537: aload_0
    //   538: invokevirtual 197	android/content/Context:getPackageName	()Ljava/lang/String;
    //   541: iconst_2
    //   542: invokevirtual 203	java/lang/String:codePointAt	(I)I
    //   545: bipush 22
    //   547: isub
    //   548: aload_0
    //   549: invokevirtual 197	android/content/Context:getPackageName	()Ljava/lang/String;
    //   552: invokevirtual 259	java/lang/String:length	()I
    //   555: bipush 11
    //   557: isub
    //   558: i2c
    //   559: invokestatic 280	o/O:ˋ	(IIC)Ljava/lang/Object;
    //   562: checkcast 282	java/lang/Class
    //   565: ldc_w 296
    //   568: iconst_1
    //   569: anewarray 282	java/lang/Class
    //   572: dup
    //   573: iconst_0
    //   574: ldc -62
    //   576: aastore
    //   577: invokevirtual 287	java/lang/Class:getMethod	(Ljava/lang/String;[Ljava/lang/Class;)Ljava/lang/reflect/Method;
    //   580: aload_3
    //   581: iconst_1
    //   582: anewarray 298	java/lang/Object
    //   585: dup
    //   586: iconst_0
    //   587: aload_0
    //   588: aastore
    //   589: invokevirtual 293	java/lang/reflect/Method:invoke	(Ljava/lang/Object;[Ljava/lang/Object;)Ljava/lang/Object;
    //   592: checkcast 300	java/lang/Boolean
    //   595: invokevirtual 303	java/lang/Boolean:booleanValue	()Z
    //   598: istore_2
    //   599: iload_2
    //   600: ifeq +6 -> 606
    //   603: goto -600 -> 3
    //   606: goto +9 -> 615
    //   609: bipush 25
    //   611: istore_1
    //   612: goto +26 -> 638
    //   615: getstatic 25	o/Mf:ˎˎ	I
    //   618: bipush 89
    //   620: iadd
    //   621: istore_1
    //   622: iload_1
    //   623: sipush 128
    //   626: irem
    //   627: putstatic 27	o/Mf:ˍ	I
    //   630: iload_1
    //   631: iconst_2
    //   632: irem
    //   633: ifne +4 -> 637
    //   636: return
    //   637: return
    //   638: iload_1
    //   639: lookupswitch	default:+25->664, 25:+-228->411, 35:+-463->176
    //   664: goto -253 -> 411
    //   667: goto -283 -> 384
    //   670: bipush 35
    //   672: istore_1
    //   673: goto -35 -> 638
    //   676: astore_3
    //   677: aload_3
    //   678: athrow
    // Local variable table:
    //   start	length	slot	name	signature
    //   0	679	0	this	Mf
    //   370	303	1	i	int
    //   365	235	2	bool	boolean
    //   10	90	3	localBundle	Bundle
    //   179	16	3	localObject1	Object
    //   249	1	3	localObject2	Object
    //   253	95	3	localObject3	Object
    //   381	2	3	localException1	Exception
    //   414	16	3	localObject4	Object
    //   491	1	3	localObject5	Object
    //   495	86	3	localObject6	Object
    //   676	2	3	localException2	Exception
    //   184	324	4	localThrowable	Throwable
    // Exception table:
    //   from	to	target	type
    //   196	250	179	finally
    //   270	366	253	finally
    //   622	630	381	java/lang/Exception
    //   431	492	414	finally
    //   512	599	495	finally
    //   615	622	676	java/lang/Exception
    //   622	630	676	java/lang/Exception
  }
  
  private void ˋᐝ()
  {
    break label155;
    int i;
    switch (i)
    {
    default: 
      break;
      label31:
      label115:
      for (;;)
      {
        Pair localPair = ˎ(this.ʼॱ);
        ((Mt)this.ॱˊ).ˊॱ.setText((CharSequence)localPair.first);
        ((Mt)this.ॱˊ).ˊॱ.setCompoundDrawablesWithIntrinsicBounds((Drawable)localPair.second, null, null, null);
        i = ˎˎ + 67;
        ˍ = i % 128;
        if (i % 2 != 0) {
          break label145;
        }
        i = 0;
        break;
      }
    }
    label145:
    label155:
    for (;;)
    {
      i = ˍ + 51;
      ˎˎ = i % 128;
      if (i % 2 != 0) {
        break label115;
      }
      break label31;
      i = 1;
      break;
      i = null.length;
      return;
      return;
    }
  }
  
  /* Error */
  private void ˌ()
  {
    // Byte code:
    //   0: goto +511 -> 511
    //   3: goto +418 -> 421
    //   6: iconst_0
    //   7: istore_1
    //   8: goto +478 -> 486
    //   11: iconst_1
    //   12: istore_1
    //   13: goto +473 -> 486
    //   16: new 337	java/lang/NullPointerException
    //   19: dup
    //   20: invokespecial 338	java/lang/NullPointerException:<init>	()V
    //   23: athrow
    //   24: goto +17 -> 41
    //   27: astore_2
    //   28: aload_2
    //   29: invokevirtual 275	java/lang/Throwable:getCause	()Ljava/lang/Throwable;
    //   32: astore_3
    //   33: aload_3
    //   34: ifnull +5 -> 39
    //   37: aload_3
    //   38: athrow
    //   39: aload_2
    //   40: athrow
    //   41: aload_0
    //   42: invokevirtual 207	android/content/Context:getApplicationInfo	()Landroid/content/pm/ApplicationInfo;
    //   45: getfield 212	android/content/pm/ApplicationInfo:targetSdkVersion	I
    //   48: bipush 21
    //   50: isub
    //   51: aload_0
    //   52: invokevirtual 207	android/content/Context:getApplicationInfo	()Landroid/content/pm/ApplicationInfo;
    //   55: getfield 212	android/content/pm/ApplicationInfo:targetSdkVersion	I
    //   58: sipush 135
    //   61: iadd
    //   62: aload_0
    //   63: invokevirtual 217	android/content/Context:getResources	()Landroid/content/res/Resources;
    //   66: ldc_w 339
    //   69: invokevirtual 224	android/content/res/Resources:getString	(I)Ljava/lang/String;
    //   72: iconst_0
    //   73: iconst_4
    //   74: invokevirtual 228	java/lang/String:substring	(II)Ljava/lang/String;
    //   77: iconst_2
    //   78: invokevirtual 203	java/lang/String:codePointAt	(I)I
    //   81: bipush 11
    //   83: isub
    //   84: i2c
    //   85: invokestatic 280	o/O:ˋ	(IIC)Ljava/lang/Object;
    //   88: checkcast 282	java/lang/Class
    //   91: ldc_w 283
    //   94: aconst_null
    //   95: invokevirtual 287	java/lang/Class:getMethod	(Ljava/lang/String;[Ljava/lang/Class;)Ljava/lang/reflect/Method;
    //   98: aconst_null
    //   99: aconst_null
    //   100: invokevirtual 293	java/lang/reflect/Method:invoke	(Ljava/lang/Object;[Ljava/lang/Object;)Ljava/lang/Object;
    //   103: checkcast 341	o/Fb
    //   106: astore_2
    //   107: aload_0
    //   108: aload_2
    //   109: invokevirtual 344	o/Fb:ˎ	()Lro/btrl/business/general/dao/P2PSettingsDao;
    //   112: invokevirtual 349	ro/btrl/business/general/dao/P2PSettingsDao:ᐝ	()Lo/Ah;
    //   115: getstatic 355	ro/btrl/business/general/dao/P2PSettingsDao$Properties:Scheme	Lo/zJ;
    //   118: aload_0
    //   119: getfield 108	o/Mf:ʾ	Lo/HQ;
    //   122: invokevirtual 361	o/HQ:ˏॱ	()Lo/Eh;
    //   125: invokevirtual 365	o/Eh:ˏ	()Ljava/lang/String;
    //   128: invokevirtual 370	o/zJ:ˊ	(Ljava/lang/Object;)Lo/Af;
    //   131: iconst_1
    //   132: anewarray 372	o/Af
    //   135: dup
    //   136: iconst_0
    //   137: getstatic 375	ro/btrl/business/general/dao/P2PSettingsDao$Properties:Currency	Lo/zJ;
    //   140: aload_0
    //   141: getfield 108	o/Mf:ʾ	Lo/HQ;
    //   144: invokevirtual 379	o/HQ:ʻ	()Lo/Ep;
    //   147: invokevirtual 383	o/Ep:ˊ	()Ljava/lang/String;
    //   150: invokevirtual 370	o/zJ:ˊ	(Ljava/lang/Object;)Lo/Af;
    //   153: aastore
    //   154: invokevirtual 388	o/Ah:ˏ	(Lo/Af;[Lo/Af;)Lo/Ah;
    //   157: invokevirtual 391	o/Ah:ˋ	()Ljava/lang/Object;
    //   160: checkcast 136	o/FP
    //   163: putfield 134	o/Mf:ˊˋ	Lo/FP;
    //   166: aload_0
    //   167: getfield 134	o/Mf:ˊˋ	Lo/FP;
    //   170: ifnonnull +6 -> 176
    //   173: goto -162 -> 11
    //   176: goto -170 -> 6
    //   179: goto -155 -> 24
    //   182: goto +17 -> 199
    //   185: astore_3
    //   186: aload_3
    //   187: invokevirtual 275	java/lang/Throwable:getCause	()Ljava/lang/Throwable;
    //   190: astore_2
    //   191: aload_2
    //   192: ifnull +5 -> 197
    //   195: aload_2
    //   196: athrow
    //   197: aload_3
    //   198: athrow
    //   199: aload_0
    //   200: invokevirtual 217	android/content/Context:getResources	()Landroid/content/res/Resources;
    //   203: ldc_w 392
    //   206: invokevirtual 224	android/content/res/Resources:getString	(I)Ljava/lang/String;
    //   209: bipush 56
    //   211: bipush 61
    //   213: invokevirtual 228	java/lang/String:substring	(II)Ljava/lang/String;
    //   216: iconst_1
    //   217: invokevirtual 203	java/lang/String:codePointAt	(I)I
    //   220: bipush 62
    //   222: isub
    //   223: aload_0
    //   224: invokevirtual 217	android/content/Context:getResources	()Landroid/content/res/Resources;
    //   227: ldc_w 393
    //   230: invokevirtual 224	android/content/res/Resources:getString	(I)Ljava/lang/String;
    //   233: iconst_0
    //   234: iconst_4
    //   235: invokevirtual 228	java/lang/String:substring	(II)Ljava/lang/String;
    //   238: invokevirtual 259	java/lang/String:length	()I
    //   241: sipush 156
    //   244: iadd
    //   245: aload_0
    //   246: invokevirtual 207	android/content/Context:getApplicationInfo	()Landroid/content/pm/ApplicationInfo;
    //   249: getfield 212	android/content/pm/ApplicationInfo:targetSdkVersion	I
    //   252: bipush 25
    //   254: isub
    //   255: i2c
    //   256: invokestatic 280	o/O:ˋ	(IIC)Ljava/lang/Object;
    //   259: checkcast 282	java/lang/Class
    //   262: ldc_w 283
    //   265: aconst_null
    //   266: invokevirtual 287	java/lang/Class:getMethod	(Ljava/lang/String;[Ljava/lang/Class;)Ljava/lang/reflect/Method;
    //   269: aconst_null
    //   270: aconst_null
    //   271: invokevirtual 293	java/lang/reflect/Method:invoke	(Ljava/lang/Object;[Ljava/lang/Object;)Ljava/lang/Object;
    //   274: checkcast 341	o/Fb
    //   277: astore_2
    //   278: aload_0
    //   279: aload_2
    //   280: invokevirtual 344	o/Fb:ˎ	()Lro/btrl/business/general/dao/P2PSettingsDao;
    //   283: invokevirtual 349	ro/btrl/business/general/dao/P2PSettingsDao:ᐝ	()Lo/Ah;
    //   286: getstatic 396	ro/btrl/business/general/dao/P2PSettingsDao$Properties:Identifier	Lo/zJ;
    //   289: aload_0
    //   290: invokevirtual 217	android/content/Context:getResources	()Landroid/content/res/Resources;
    //   293: ldc_w 397
    //   296: invokevirtual 224	android/content/res/Resources:getString	(I)Ljava/lang/String;
    //   299: iconst_0
    //   300: iconst_4
    //   301: invokevirtual 228	java/lang/String:substring	(II)Ljava/lang/String;
    //   304: invokevirtual 259	java/lang/String:length	()I
    //   307: bipush 35
    //   309: iadd
    //   310: i2s
    //   311: aload_0
    //   312: invokevirtual 217	android/content/Context:getResources	()Landroid/content/res/Resources;
    //   315: ldc_w 398
    //   318: invokevirtual 224	android/content/res/Resources:getString	(I)Ljava/lang/String;
    //   321: iconst_0
    //   322: iconst_4
    //   323: invokevirtual 228	java/lang/String:substring	(II)Ljava/lang/String;
    //   326: iconst_2
    //   327: invokevirtual 203	java/lang/String:codePointAt	(I)I
    //   330: ldc_w 399
    //   333: iadd
    //   334: iconst_0
    //   335: aload_0
    //   336: invokevirtual 217	android/content/Context:getResources	()Landroid/content/res/Resources;
    //   339: ldc_w 400
    //   342: invokevirtual 224	android/content/res/Resources:getString	(I)Ljava/lang/String;
    //   345: iconst_0
    //   346: iconst_5
    //   347: invokevirtual 228	java/lang/String:substring	(II)Ljava/lang/String;
    //   350: iconst_2
    //   351: invokevirtual 203	java/lang/String:codePointAt	(I)I
    //   354: ldc_w 401
    //   357: iadd
    //   358: aload_0
    //   359: invokevirtual 197	android/content/Context:getPackageName	()Ljava/lang/String;
    //   362: invokevirtual 259	java/lang/String:length	()I
    //   365: bipush 54
    //   367: isub
    //   368: invokestatic 232	o/Mf:ˋ	(SIBII)Ljava/lang/String;
    //   371: invokevirtual 235	java/lang/String:intern	()Ljava/lang/String;
    //   374: invokevirtual 370	o/zJ:ˊ	(Ljava/lang/Object;)Lo/Af;
    //   377: iconst_0
    //   378: anewarray 372	o/Af
    //   381: invokevirtual 388	o/Ah:ˏ	(Lo/Af;[Lo/Af;)Lo/Ah;
    //   384: invokevirtual 391	o/Ah:ˋ	()Ljava/lang/Object;
    //   387: checkcast 136	o/FP
    //   390: putfield 134	o/Mf:ˊˋ	Lo/FP;
    //   393: goto -390 -> 3
    //   396: iload_1
    //   397: tableswitch	default:+23->420, 0:+-381->16, 1:+59->456
    //   420: return
    //   421: getstatic 27	o/Mf:ˍ	I
    //   424: bipush 17
    //   426: iadd
    //   427: istore_1
    //   428: iload_1
    //   429: sipush 128
    //   432: irem
    //   433: putstatic 25	o/Mf:ˎˎ	I
    //   436: iload_1
    //   437: iconst_2
    //   438: irem
    //   439: ifeq +6 -> 445
    //   442: goto +72 -> 514
    //   445: goto +6 -> 451
    //   448: astore_2
    //   449: aload_2
    //   450: athrow
    //   451: iconst_1
    //   452: istore_1
    //   453: goto -57 -> 396
    //   456: return
    //   457: getstatic 27	o/Mf:ˍ	I
    //   460: istore_1
    //   461: iload_1
    //   462: bipush 85
    //   464: iadd
    //   465: istore_1
    //   466: iload_1
    //   467: sipush 128
    //   470: irem
    //   471: putstatic 25	o/Mf:ˎˎ	I
    //   474: iload_1
    //   475: iconst_2
    //   476: irem
    //   477: ifeq +6 -> 483
    //   480: goto -301 -> 179
    //   483: goto -459 -> 24
    //   486: iload_1
    //   487: tableswitch	default:+21->508, 0:+-484->3, 1:+-305->182
    //   508: goto -326 -> 182
    //   511: goto -54 -> 457
    //   514: iconst_0
    //   515: istore_1
    //   516: goto -120 -> 396
    // Local variable table:
    //   start	length	slot	name	signature
    //   0	519	0	this	Mf
    //   7	509	1	i	int
    //   27	13	2	localObject1	Object
    //   106	174	2	localObject2	Object
    //   448	2	2	localException	Exception
    //   32	6	3	localThrowable	Throwable
    //   185	13	3	localObject3	Object
    // Exception table:
    //   from	to	target	type
    //   41	107	27	finally
    //   199	278	185	finally
    //   457	461	448	java/lang/Exception
    //   466	474	448	java/lang/Exception
  }
  
  private void ˎˎ()
  {
    for (;;)
    {
      Pair localPair = ˎ(this.ʾ);
      ((Mt)this.ॱˊ).ʽ.setText((CharSequence)localPair.first);
      ((Mt)this.ॱˊ).ʽ.setCompoundDrawablesWithIntrinsicBounds((Drawable)localPair.second, null, null, null);
      break;
      i = ˎˎ + 67;
      ˍ = i % 128;
      if (i % 2 != 0) {}
    }
    int i = ˎˎ + 19;
    ˍ = i % 128;
    if (i % 2 == 0) {}
  }
  
  /* Error */
  public android.content.res.Resources getResources()
  {
    // Byte code:
    //   0: goto +74 -> 74
    //   3: getstatic 25	o/Mf:ˎˎ	I
    //   6: bipush 83
    //   8: iadd
    //   9: istore_1
    //   10: iload_1
    //   11: sipush 128
    //   14: irem
    //   15: putstatic 27	o/Mf:ˍ	I
    //   18: iload_1
    //   19: iconst_2
    //   20: irem
    //   21: ifne +6 -> 27
    //   24: goto +8 -> 32
    //   27: aload_2
    //   28: areturn
    //   29: astore_2
    //   30: aload_2
    //   31: athrow
    //   32: aload_2
    //   33: areturn
    //   34: getstatic 25	o/Mf:ˎˎ	I
    //   37: istore_1
    //   38: iload_1
    //   39: bipush 31
    //   41: iadd
    //   42: istore_1
    //   43: iload_1
    //   44: sipush 128
    //   47: irem
    //   48: putstatic 27	o/Mf:ˍ	I
    //   51: iload_1
    //   52: iconst_2
    //   53: irem
    //   54: ifne +6 -> 60
    //   57: goto +20 -> 77
    //   60: goto +3 -> 63
    //   63: aload_0
    //   64: invokespecial 405	o/LZ:getResources	()Landroid/content/res/Resources;
    //   67: invokestatic 410	o/oH:ˊ	(Landroid/content/res/Resources;)Landroid/content/res/Resources;
    //   70: astore_2
    //   71: goto -68 -> 3
    //   74: goto -40 -> 34
    //   77: goto -14 -> 63
    // Local variable table:
    //   start	length	slot	name	signature
    //   0	80	0	this	Mf
    //   9	45	1	i	int
    //   27	1	2	localResources1	android.content.res.Resources
    //   29	4	2	localException	Exception
    //   70	1	2	localResources2	android.content.res.Resources
    // Exception table:
    //   from	to	target	type
    //   34	38	29	java/lang/Exception
    //   43	51	29	java/lang/Exception
  }
  
  public void onContinue(View paramView)
  {
    break label337;
    int j = ˎˎ + 123;
    ˍ = j % 128;
    if (j % 2 != 0) {
      break label350;
    }
    j = 4;
    break label389;
    int i;
    switch (i)
    {
    default: 
      break label305;
      label63:
      label68:
      label71:
      label103:
      do
      {
        ˋˋ();
        return;
        break label356;
        if (((Mt)this.ॱˊ).ᐝ.ˋ(new Fr()).isValid) {
          break;
        }
        break label300;
        j = null.length;
      } while (i != 0);
      return;
      i = ˎˎ + 25;
      ˍ = i % 128;
      if (i % 2 == 0) {}
      break;
    }
    label141:
    label189:
    label194:
    label259:
    label294:
    label300:
    label305:
    label310:
    label337:
    label345:
    label350:
    label356:
    label359:
    label361:
    label389:
    label419:
    for (;;)
    {
      if (j == 0)
      {
        break label294;
        for (;;)
        {
          if (((Mt)this.ॱˊ).ᐝ.ॱॱ().isValid) {
            break label310;
          }
          break label345;
          i = 1;
          break label259;
          if (i != 0) {
            break label63;
          }
          return;
          i = 0;
          break label419;
          i = 0;
          break;
        }
      }
      for (;;)
      {
        if (!((Mt)this.ॱˊ).ॱॱ.ॱॱ().isValid) {
          break label194;
        }
        for (;;)
        {
          if (((Mt)this.ॱˊ).ॱॱ.ˋ(new Fr()).isValid) {
            break label359;
          }
          break label189;
          for (;;)
          {
            switch (i)
            {
            case 1: 
            default: 
              break label345;
              j = 99;
              break label361;
              return;
              j = 30;
              break label361;
              i = 0;
            }
          }
          i = 1;
          break label141;
          i = ˍ + 97;
          ˎˎ = i % 128;
          if (i % 2 != 0) {
            break label68;
          }
          break label356;
          break label71;
          i = 1;
          break;
          j = 0;
          continue;
          j = 70;
          break label389;
          j = 1;
        }
      }
      switch (j)
      {
      }
      return;
      switch (j)
      {
      }
      break label103;
    }
  }
  
  public void onCreate(Bundle paramBundle)
  {
    break label37;
    int i = 32 / 0;
    return;
    return;
    switch (i)
    {
    }
    return;
    for (;;)
    {
      label37:
      i = 48;
      break;
      super.onCreate(paramBundle);
      ˊ(((Mt)this.ॱˊ).ˋॱ);
      ˌ();
      ˉ();
      xe.ˎ(this, new xd()
      {
        public void ˋ(boolean paramAnonymousBoolean)
        {
          ((Mt)Mf.ˊ(Mf.this)).ˎ(paramAnonymousBoolean);
          if (paramAnonymousBoolean) {
            ((Mt)Mf.ˋ(Mf.this)).ͺ.postDelayed(new Runnable()
            {
              public void run()
              {
                ((Mt)Mf.ˎ(Mf.this)).ͺ.smoothScrollBy(0, 100);
              }
            }, 100L);
          }
        }
      });
      do
      {
        i = 29;
        break;
        i = ˎˎ + 25;
        ˍ = i % 128;
      } while (i % 2 == 0);
    }
  }
  
  /* Error */
  protected void ʾ()
  {
    // Byte code:
    //   0: goto +77 -> 77
    //   3: iconst_1
    //   4: istore_1
    //   5: goto +75 -> 80
    //   8: iload_1
    //   9: tableswitch	default:+23->32, 0:+34->43, 1:+96->105
    //   32: goto +73 -> 105
    //   35: astore_2
    //   36: aload_2
    //   37: athrow
    //   38: iconst_1
    //   39: istore_1
    //   40: goto -32 -> 8
    //   43: aload_0
    //   44: getfield 94	o/Mf:ॱˊ	Landroid/databinding/ViewDataBinding;
    //   47: checkcast 96	o/Mt
    //   50: aload_0
    //   51: getfield 108	o/Mf:ʾ	Lo/HQ;
    //   54: invokevirtual 112	o/Mt:ˊ	(Lo/HQ;)V
    //   57: aload_0
    //   58: invokespecial 444	o/Mf:ˌ	()V
    //   61: aload_0
    //   62: invokespecial 122	o/Mf:ˎˎ	()V
    //   65: goto +107 -> 172
    //   68: astore_2
    //   69: aload_2
    //   70: athrow
    //   71: iconst_0
    //   72: istore_1
    //   73: goto -65 -> 8
    //   76: return
    //   77: goto +64 -> 141
    //   80: iload_1
    //   81: tableswitch	default:+23->104, 0:+-5->76, 1:+87->168
    //   104: return
    //   105: aload_0
    //   106: getfield 94	o/Mf:ॱˊ	Landroid/databinding/ViewDataBinding;
    //   109: astore_2
    //   110: aload_2
    //   111: checkcast 96	o/Mt
    //   114: astore_2
    //   115: aload_0
    //   116: getfield 108	o/Mf:ʾ	Lo/HQ;
    //   119: astore_3
    //   120: aload_2
    //   121: aload_3
    //   122: invokevirtual 112	o/Mt:ˊ	(Lo/HQ;)V
    //   125: aload_0
    //   126: invokespecial 444	o/Mf:ˌ	()V
    //   129: aload_0
    //   130: invokespecial 122	o/Mf:ˎˎ	()V
    //   133: bipush 40
    //   135: iconst_0
    //   136: idiv
    //   137: istore_1
    //   138: goto +34 -> 172
    //   141: getstatic 27	o/Mf:ˍ	I
    //   144: bipush 119
    //   146: iadd
    //   147: istore_1
    //   148: iload_1
    //   149: sipush 128
    //   152: irem
    //   153: putstatic 25	o/Mf:ˎˎ	I
    //   156: iload_1
    //   157: iconst_2
    //   158: irem
    //   159: ifeq +6 -> 165
    //   162: goto -124 -> 38
    //   165: goto -94 -> 71
    //   168: aconst_null
    //   169: arraylength
    //   170: istore_1
    //   171: return
    //   172: getstatic 27	o/Mf:ˍ	I
    //   175: bipush 41
    //   177: iadd
    //   178: istore_1
    //   179: iload_1
    //   180: sipush 128
    //   183: irem
    //   184: putstatic 25	o/Mf:ˎˎ	I
    //   187: iload_1
    //   188: iconst_2
    //   189: irem
    //   190: ifeq +6 -> 196
    //   193: goto -190 -> 3
    //   196: iconst_0
    //   197: istore_1
    //   198: goto -118 -> 80
    // Local variable table:
    //   start	length	slot	name	signature
    //   0	201	0	this	Mf
    //   4	194	1	i	int
    //   35	2	2	localException1	Exception
    //   68	2	2	localException2	Exception
    //   109	12	2	localObject	Object
    //   119	3	3	localHQ	HQ
    // Exception table:
    //   from	to	target	type
    //   110	115	35	java/lang/Exception
    //   105	110	68	java/lang/Exception
    //   110	115	68	java/lang/Exception
    //   115	120	68	java/lang/Exception
    //   120	138	68	java/lang/Exception
  }
  
  protected void ˊᐝ()
  {
    break label8;
    int i = 1;
    for (;;)
    {
      label8:
      ((Mt)this.ॱˊ).ˏ(this.ʼॱ);
      ˋᐝ();
      return;
      do
      {
        i = 0;
        break;
        i = ˍ + 47;
        ˎˎ = i % 128;
      } while (i % 2 != 0);
      break;
      ((Mt)this.ॱˊ).ˏ(this.ʼॱ);
      ˋᐝ();
      i = null.length;
      return;
      switch (i)
      {
      }
    }
  }
  
  public void ˋ(ز paramز)
  {
    break label63;
    int i = ˎˎ + 97;
    ˍ = i % 128;
    if (i % 2 != 0) {}
    for (;;)
    {
      paramز.ॱ(true);
      paramز.ˏ(true);
      i = ˎˎ + 21;
      ˍ = i % 128;
      if (i % 2 != 0) {
        return;
      }
      return;
      label63:
      break;
    }
  }
  
  public int ˎ()
  {
    for (;;)
    {
      break;
      i = ˎˎ + 9;
      ˍ = i % 128;
      if (i % 2 != 0) {
        break;
      }
    }
    int i = LV.iF.activity_inter_cards_transfer_inputs;
    int j = ˎˎ + 41;
    ˍ = j % 128;
    if (j % 2 == 0) {
      return i;
    }
    return i;
  }
}
