package o;

import android.app.Activity;
import android.app.Application;
import java.util.Map;
import ro.btrl.boot.di.builder.BootActivityBuilder_BindTacActivity.ˊ;
import ro.btrl.boot.di.builder.BootActivityBuilder_BindTacActivity.ˊ.ˋ;
import ro.btrl.boot.di.builder.BootActivityBuilder_BindTourActivity.ˊ;
import ro.btrl.boot.di.builder.BootActivityBuilder_BindTourActivity.ˊ.if;
import ro.btrl.boot.di.module.BootModule;
import ro.btrl.boot.ui.activity.TncActivity;
import ro.btrl.boot.ui.activity.TourActivity;
import ro.btrl.commons.di.module.CommonsModule;
import ro.btrl.commons.di.module.RepositoryModule;
import ro.btrl.devoptions.di.builder.DevOptionsBuilder_BindDevOptionsFragment.If;
import ro.btrl.devoptions.di.builder.DevOptionsBuilder_BindDevOptionsFragment.If.ˋ;
import ro.btrl.devoptions.di.module.DevOptionsModule;
import ro.btrl.devoptions.ui.fragment.DevOptionsFragment;
import ro.btrl.enrollment.di.builder.EnrollmentActivityBuilder_BindPaymentTransactionsFragment.if;
import ro.btrl.enrollment.di.builder.EnrollmentActivityBuilder_BindPaymentTransactionsFragment.if.ˊ;
import ro.btrl.enrollment.di.module.EnrollmentModule;
import ro.btrl.enrollment.ui.fragment.PaymentTransactionsFragment;
import ro.btrl.pay.App;

public final class ML
  implements MD
{
  private uu<Io> ʻ;
  private uu<DevOptionsBuilder_BindDevOptionsFragment.If.ˋ> ʼ;
  private uu<Ig> ʽ;
  private CommonsModule ˊ;
  private uu<In> ˊॱ;
  private BootModule ˋ;
  private uu<Id> ˋॱ;
  private uu<BootActivityBuilder_BindTacActivity.ˊ.ˋ> ˎ;
  private DevOptionsModule ˏ;
  private uu<Ij> ˏॱ;
  private uu<Kq> ͺ;
  private EnrollmentModule ॱ;
  private uu<DH> ॱˊ;
  private uu<Jw> ॱˎ;
  private uu<EnrollmentActivityBuilder_BindPaymentTransactionsFragment.if.ˊ> ॱॱ;
  private uu<BootActivityBuilder_BindTourActivity.ˊ.if> ᐝ;
  
  private ML(ˋ paramˋ)
  {
    ॱ(paramˋ);
  }
  
  private Map<Class<? extends Activity>, uu<qb.ˋ<? extends Activity>>> ˊ()
  {
    return qk.ˊ(2).ˏ(TncActivity.class, this.ˎ).ˏ(TourActivity.class, this.ᐝ).ˋ();
  }
  
  private Map<Class<? extends ᴷ>, uu<qb.ˋ<? extends ᴷ>>> ˋ()
  {
    return qk.ˊ(2).ˏ(PaymentTransactionsFragment.class, this.ॱॱ).ˏ(DevOptionsFragment.class, this.ʼ).ˋ();
  }
  
  public static MD.if ˎ()
  {
    return new ˋ(null);
  }
  
  private qc<Activity> ˏ()
  {
    return qd.ˊ(ˊ());
  }
  
  private qc<ᴷ> ॱ()
  {
    return qd.ˊ(ˋ());
  }
  
  private App ॱ(App paramApp)
  {
    MJ.ˎ(paramApp, ˏ());
    MJ.ˏ(paramApp, ॱ());
    return paramApp;
  }
  
  private void ॱ(ˋ paramˋ)
  {
    this.ˎ = new uu()
    {
      public BootActivityBuilder_BindTacActivity.ˊ.ˋ ˏ()
      {
        return new ML.IF(ML.this, null);
      }
    };
    this.ᐝ = new uu()
    {
      public BootActivityBuilder_BindTourActivity.ˊ.if ˊ()
      {
        return new ML.ˎ(ML.this, null);
      }
    };
    this.ॱॱ = new uu()
    {
      public EnrollmentActivityBuilder_BindPaymentTransactionsFragment.if.ˊ ॱ()
      {
        return new ML.if(ML.this, null);
      }
    };
    this.ʼ = new uu()
    {
      public DevOptionsBuilder_BindDevOptionsFragment.If.ˋ ˏ()
      {
        return new ML.iF(ML.this, null);
      }
    };
    this.ˋ = ˋ.ˏ(paramˋ);
    this.ʻ = qi.ˋ(Hk.ˎ(ˋ.ˊ(paramˋ)));
    this.ʽ = qi.ˋ(Hg.ॱ(ˋ.ˊ(paramˋ)));
    this.ˋॱ = qi.ˋ(Hd.ˊ(ˋ.ˊ(paramˋ)));
    this.ˏॱ = qi.ˋ(Hb.ˏ(ˋ.ˊ(paramˋ)));
    this.ˊॱ = qi.ˋ(Hj.ˎ(ˋ.ˊ(paramˋ)));
    this.ॱˊ = qi.ˋ(DI.ˎ(this.ʻ, this.ʽ, this.ˋॱ, this.ˏॱ, this.ˊॱ));
    this.ॱ = ˋ.ˋ(paramˋ);
    this.ͺ = qi.ˋ(Ko.ˎ(this.ʻ, this.ʽ, this.ˋॱ, this.ˏॱ, this.ˊॱ));
    this.ˏ = ˋ.ˎ(paramˋ);
    this.ॱˎ = qi.ˋ(Ju.ˎ(this.ʻ, this.ʽ, this.ˋॱ, this.ˏॱ, this.ˊॱ));
    this.ˊ = ˋ.ॱ(paramˋ);
  }
  
  public void ˏ(App paramApp)
  {
    ॱ(paramApp);
  }
  
  final class IF
    extends BootActivityBuilder_BindTacActivity.ˊ.ˋ
  {
    private static boolean ʼ;
    private static int ʽ;
    private static int ˊ = 275;
    private static boolean ˎ;
    private static char[] ॱ;
    private static int ॱॱ = 0;
    private TncActivity ˋ;
    
    static
    {
      ʽ = 1;
      ʼ = true;
      ˎ = true;
      ॱ = new char[] { 307, 384, 392, 390, 391, 373, 376 };
    }
    
    private IF() {}
    
    private static String ॱ(byte[] paramArrayOfByte, int[] paramArrayOfInt, char[] paramArrayOfChar, int paramInt)
    {
      break label145;
      label3:
      int j;
      int i = j;
      break label409;
      char[] arrayOfChar;
      int m;
      int k;
      label145:
      do
      {
        break label516;
        switch (i)
        {
        case 1: 
        default: 
          break label3;
          i = ʽ + 121;
          ॱॱ = i % 128;
          if (i % 2 != 0) {
            break label356;
          }
          break label291;
          for (;;)
          {
            i = ʽ + 125;
            ॱॱ = i % 128;
            if (i % 2 != 0) {
              break label288;
            }
            break label209;
            paramArrayOfInt[i] = ((char)(arrayOfChar[(paramArrayOfByte[(m - 1 - i)] + paramInt)] - k));
            i += 1;
            break label339;
            m = paramArrayOfChar.length;
            paramArrayOfByte = new char[m];
            j = 0;
            break;
          }
          j = ʽ + 91;
          ॱॱ = j % 128;
        }
      } while (j % 2 != 0);
      break label516;
      for (;;)
      {
        j = 0;
        break label312;
        label184:
        break label467;
        label187:
        if (i < j) {
          break label470;
        }
        break label231;
        label200:
        return new String(paramArrayOfByte);
        label209:
        label231:
        label240:
        label270:
        label276:
        label288:
        for (;;)
        {
          arrayOfChar = ॱ;
          k = ˊ;
          if (ʼ) {
            break label379;
          }
          break label276;
          return new String(paramArrayOfByte);
          m = ʽ + 119;
          ॱॱ = m % 128;
          if (m % 2 != 0) {
            break label184;
          }
          break label467;
          j = 1;
          break label312;
          if (ˎ) {
            break;
          }
          break label501;
        }
        label291:
        i = 0;
        break;
        for (;;)
        {
          m = paramArrayOfByte.length;
          paramArrayOfInt = new char[m];
          i = 0;
          break label339;
          label312:
          switch (j)
          {
          }
          break label200;
          label339:
          if (i >= m)
          {
            j = 42;
            break label437;
            label356:
            i = 1;
            break;
            i = j;
            break label409;
          }
          label379:
          do
          {
            break;
            j = 82;
            break label437;
            i = ॱॱ + 117;
            ʽ = i % 128;
          } while (i % 2 == 0);
        }
        label409:
        if (i < m) {
          break label423;
        }
      }
      for (;;)
      {
        break label409;
        label423:
        break label270;
        for (;;)
        {
          break label187;
          return new String(paramArrayOfInt);
          label437:
          switch (j)
          {
          }
          break;
          label467:
          break label187;
          label470:
          paramArrayOfByte[i] = ((char)(arrayOfChar[(paramArrayOfInt[(j - 1 - i)] - paramInt)] - k));
          i += 1;
          break label240;
          label501:
          j = paramArrayOfInt.length;
          paramArrayOfByte = new char[j];
          i = 0;
        }
        label516:
        paramArrayOfByte[i] = ((char)(arrayOfChar[(paramArrayOfChar[(m - 1 - i)] - paramInt)] - k));
        i += 1;
      }
    }
    
    /* Error */
    public void ˊ(TncActivity paramTncActivity)
    {
      // Byte code:
      //   0: goto +34 -> 34
      //   3: iconst_0
      //   4: istore_2
      //   5: goto +105 -> 110
      //   8: getstatic 24	o/ML$IF:ॱॱ	I
      //   11: bipush 83
      //   13: iadd
      //   14: istore_2
      //   15: iload_2
      //   16: sipush 128
      //   19: irem
      //   20: putstatic 26	o/ML$IF:ʽ	I
      //   23: iload_2
      //   24: iconst_2
      //   25: irem
      //   26: ifne +6 -> 32
      //   29: goto +4 -> 33
      //   32: return
      //   33: return
      //   34: goto +11 -> 45
      //   37: astore_1
      //   38: aload_1
      //   39: athrow
      //   40: iconst_1
      //   41: istore_2
      //   42: goto +68 -> 110
      //   45: getstatic 26	o/ML$IF:ʽ	I
      //   48: bipush 15
      //   50: iadd
      //   51: istore_2
      //   52: iload_2
      //   53: sipush 128
      //   56: irem
      //   57: putstatic 24	o/ML$IF:ॱॱ	I
      //   60: iload_2
      //   61: iconst_2
      //   62: irem
      //   63: ifeq +6 -> 69
      //   66: goto -63 -> 3
      //   69: goto -29 -> 40
      //   72: aload_0
      //   73: aload_1
      //   74: invokestatic 68	o/qn:ˊ	(Ljava/lang/Object;)Ljava/lang/Object;
      //   77: checkcast 70	ro/btrl/boot/ui/activity/TncActivity
      //   80: putfield 60	o/ML$IF:ˋ	Lro/btrl/boot/ui/activity/TncActivity;
      //   83: aconst_null
      //   84: arraylength
      //   85: istore_2
      //   86: goto -78 -> 8
      //   89: aload_1
      //   90: invokestatic 68	o/qn:ˊ	(Ljava/lang/Object;)Ljava/lang/Object;
      //   93: astore_1
      //   94: aload_1
      //   95: checkcast 70	ro/btrl/boot/ui/activity/TncActivity
      //   98: astore_1
      //   99: aload_0
      //   100: aload_1
      //   101: putfield 60	o/ML$IF:ˋ	Lro/btrl/boot/ui/activity/TncActivity;
      //   104: goto -96 -> 8
      //   107: astore_1
      //   108: aload_1
      //   109: athrow
      //   110: iload_2
      //   111: tableswitch	default:+21->132, 0:+-39->72, 1:+-22->89
      //   132: goto -60 -> 72
      // Local variable table:
      //   start	length	slot	name	signature
      //   0	135	0	this	IF
      //   0	135	1	paramTncActivity	TncActivity
      //   4	107	2	i	int
      // Exception table:
      //   from	to	target	type
      //   89	94	37	java/lang/Exception
      //   94	99	37	java/lang/Exception
      //   99	104	37	java/lang/Exception
      //   99	104	107	java/lang/Exception
    }
    
    public BootActivityBuilder_BindTacActivity.ˊ ˎ()
    {
      break label251;
      throw new NullPointerException();
      int i = 68;
      break label221;
      Object localObject;
      return localObject;
      label19:
      label185:
      label191:
      for (;;)
      {
        if (this.ˋ != null) {
          for (;;)
          {
            i = ʽ + 121;
            ॱॱ = i % 128;
            if (i % 2 != 0) {
              break;
            }
            break label185;
            localObject = new ML.aux(ML.this, this, null);
          }
        }
        throw new IllegalStateException(TncActivity.class.getCanonicalName() + ॱ(new byte[] { -123, -121, -124, -127, -121, -122, -127, -123, -124, -125, -126, -127 }, null, null, 127).intern());
        i = 54;
        break label221;
      }
      label221:
      label251:
      for (;;)
      {
        i = ॱॱ + 81;
        ʽ = i % 128;
        if (i % 2 == 0) {
          break label191;
        }
        break label19;
        switch (i)
        {
        }
        break;
      }
    }
  }
  
  final class If
    implements EnrollmentActivityBuilder_BindPaymentTransactionsFragment.if
  {
    private PaymentTransactionsFragment ॱ;
    
    private If(ML.if paramIf)
    {
      ˋ(paramIf);
    }
    
    private PaymentTransactionsFragment ˋ(PaymentTransactionsFragment paramPaymentTransactionsFragment)
    {
      KU.ˏ(paramPaymentTransactionsFragment, ˏ());
      return paramPaymentTransactionsFragment;
    }
    
    private void ˋ(ML.if paramIf)
    {
      this.ॱ = ML.if.ˋ(paramIf);
    }
    
    private KO.iF ˏ()
    {
      return Kh.ˊ(ML.ˏ(ML.this), this.ॱ, (Kk)ML.ˊ(ML.this).ˋ());
    }
    
    public void ˎ(PaymentTransactionsFragment paramPaymentTransactionsFragment)
    {
      ˋ(paramPaymentTransactionsFragment);
    }
  }
  
  final class aux
    implements BootActivityBuilder_BindTacActivity.ˊ
  {
    private TncActivity ˊ;
    
    private aux(ML.IF paramIF)
    {
      ˋ(paramIF);
    }
    
    private void ˋ(ML.IF paramIF)
    {
      this.ˊ = ML.IF.ॱ(paramIF);
    }
    
    private DK.iF ˎ()
    {
      return DC.ˏ(ML.ˋ(ML.this), this.ˊ, (DF)ML.ॱ(ML.this).ˋ());
    }
    
    private TncActivity ˏ(TncActivity paramTncActivity)
    {
      DM.ˎ(paramTncActivity, ˎ());
      return paramTncActivity;
    }
    
    public void ˊ(TncActivity paramTncActivity)
    {
      ˏ(paramTncActivity);
    }
  }
  
  final class iF
    extends DevOptionsBuilder_BindDevOptionsFragment.If.ˋ
  {
    private static int ʻ;
    private static char ˊ;
    private static int ˏ = 3272546;
    private static long ॱ;
    private static int ॱॱ = 0;
    private DevOptionsFragment ˎ;
    
    static
    {
      ʻ = 1;
      ˊ = '\000';
      ॱ = 0L;
    }
    
    private iF() {}
    
    /* Error */
    private static String ˊ(char[] paramArrayOfChar1, char paramChar, char[] paramArrayOfChar2, int paramInt, char[] paramArrayOfChar3)
    {
      // Byte code:
      //   0: goto +285 -> 285
      //   3: goto +152 -> 155
      //   6: aload_0
      //   7: invokevirtual 51	[C:clone	()Ljava/lang/Object;
      //   10: checkcast 47	[C
      //   13: astore_0
      //   14: aload 4
      //   16: invokevirtual 51	[C:clone	()Ljava/lang/Object;
      //   19: checkcast 47	[C
      //   22: astore 4
      //   24: aload_0
      //   25: iconst_0
      //   26: aload_0
      //   27: iconst_0
      //   28: caload
      //   29: iload_1
      //   30: ixor
      //   31: i2c
      //   32: castore
      //   33: aload 4
      //   35: iconst_2
      //   36: aload 4
      //   38: iconst_2
      //   39: caload
      //   40: iload_3
      //   41: i2c
      //   42: iadd
      //   43: i2c
      //   44: castore
      //   45: aload_2
      //   46: arraylength
      //   47: istore 5
      //   49: iload 5
      //   51: newarray char
      //   53: astore 10
      //   55: iconst_0
      //   56: istore_3
      //   57: goto +231 -> 288
      //   60: getstatic 23	o/ML$iF:ॱॱ	I
      //   63: bipush 23
      //   65: iadd
      //   66: istore 5
      //   68: iload 5
      //   70: sipush 128
      //   73: irem
      //   74: putstatic 25	o/ML$iF:ʻ	I
      //   77: iload 5
      //   79: iconst_2
      //   80: irem
      //   81: ifne +6 -> 87
      //   84: goto +304 -> 388
      //   87: goto -81 -> 6
      //   90: iconst_1
      //   91: istore_3
      //   92: goto +238 -> 330
      //   95: getstatic 23	o/ML$iF:ॱॱ	I
      //   98: bipush 49
      //   100: iadd
      //   101: istore_3
      //   102: iload_3
      //   103: sipush 128
      //   106: irem
      //   107: putstatic 25	o/ML$iF:ʻ	I
      //   110: iload_3
      //   111: iconst_2
      //   112: irem
      //   113: ifne +6 -> 119
      //   116: goto -26 -> 90
      //   119: iconst_0
      //   120: istore_3
      //   121: goto +209 -> 330
      //   124: astore_0
      //   125: aload_0
      //   126: athrow
      //   127: iload_1
      //   128: tableswitch	default:+24->152, 0:+255->383, 1:+95->223
      //   152: goto +71 -> 223
      //   155: iload_1
      //   156: iload 5
      //   158: if_icmpge +6 -> 164
      //   161: goto -66 -> 95
      //   164: goto +153 -> 317
      //   167: aload_0
      //   168: aload 4
      //   170: iload_1
      //   171: invokestatic 56	o/oJ:ˏ	([C[CI)V
      //   174: aload_2
      //   175: iload_1
      //   176: caload
      //   177: aload_0
      //   178: iload_1
      //   179: iconst_3
      //   180: iadd
      //   181: iconst_4
      //   182: irem
      //   183: caload
      //   184: ixor
      //   185: i2l
      //   186: lstore 6
      //   188: getstatic 29	o/ML$iF:ॱ	J
      //   191: lstore 8
      //   193: getstatic 32	o/ML$iF:ˏ	I
      //   196: istore_3
      //   197: aload 10
      //   199: iload_1
      //   200: lload 6
      //   202: lload 8
      //   204: lxor
      //   205: iload_3
      //   206: i2l
      //   207: lxor
      //   208: getstatic 27	o/ML$iF:ˊ	C
      //   211: i2l
      //   212: lxor
      //   213: l2i
      //   214: i2c
      //   215: castore
      //   216: iload_1
      //   217: iconst_1
      //   218: iadd
      //   219: istore_1
      //   220: goto -217 -> 3
      //   223: iload_3
      //   224: istore_1
      //   225: goto -70 -> 155
      //   228: iconst_1
      //   229: istore_1
      //   230: goto -103 -> 127
      //   233: iconst_0
      //   234: istore_1
      //   235: goto -108 -> 127
      //   238: aload_0
      //   239: aload 4
      //   241: iload_1
      //   242: invokestatic 56	o/oJ:ˏ	([C[CI)V
      //   245: aload 10
      //   247: iload_1
      //   248: aload_2
      //   249: iload_1
      //   250: caload
      //   251: aload_0
      //   252: iload_1
      //   253: iconst_4
      //   254: irem
      //   255: iconst_4
      //   256: imul
      //   257: caload
      //   258: ior
      //   259: i2l
      //   260: getstatic 29	o/ML$iF:ॱ	J
      //   263: ladd
      //   264: getstatic 32	o/ML$iF:ˏ	I
      //   267: i2l
      //   268: lrem
      //   269: getstatic 27	o/ML$iF:ˊ	C
      //   272: i2l
      //   273: ldiv
      //   274: l2i
      //   275: i2c
      //   276: castore
      //   277: iload_1
      //   278: bipush 24
      //   280: iadd
      //   281: istore_1
      //   282: goto -279 -> 3
      //   285: goto -225 -> 60
      //   288: getstatic 23	o/ML$iF:ॱॱ	I
      //   291: istore_1
      //   292: iload_1
      //   293: bipush 45
      //   295: iadd
      //   296: istore_1
      //   297: iload_1
      //   298: sipush 128
      //   301: irem
      //   302: putstatic 25	o/ML$iF:ʻ	I
      //   305: iload_1
      //   306: iconst_2
      //   307: irem
      //   308: ifne +6 -> 314
      //   311: goto -83 -> 228
      //   314: goto -81 -> 233
      //   317: new 58	java/lang/String
      //   320: dup
      //   321: aload 10
      //   323: invokespecial 61	java/lang/String:<init>	([C)V
      //   326: astore_0
      //   327: goto +28 -> 355
      //   330: iload_3
      //   331: tableswitch	default:+21->352, 0:+-164->167, 1:+-93->238
      //   352: goto -185 -> 167
      //   355: getstatic 23	o/ML$iF:ॱॱ	I
      //   358: bipush 117
      //   360: iadd
      //   361: istore_1
      //   362: iload_1
      //   363: sipush 128
      //   366: irem
      //   367: putstatic 25	o/ML$iF:ʻ	I
      //   370: iload_1
      //   371: iconst_2
      //   372: irem
      //   373: ifne +5 -> 378
      //   376: aload_0
      //   377: areturn
      //   378: aload_0
      //   379: areturn
      //   380: astore_0
      //   381: aload_0
      //   382: athrow
      //   383: iload_3
      //   384: istore_1
      //   385: goto -230 -> 155
      //   388: goto -382 -> 6
      // Local variable table:
      //   start	length	slot	name	signature
      //   0	391	0	paramArrayOfChar1	char[]
      //   0	391	1	paramChar	char
      //   0	391	2	paramArrayOfChar2	char[]
      //   0	391	3	paramInt	int
      //   0	391	4	paramArrayOfChar3	char[]
      //   47	112	5	c	char
      //   186	15	6	l1	long
      //   191	12	8	l2	long
      //   53	269	10	arrayOfChar	char[]
      // Exception table:
      //   from	to	target	type
      //   288	292	124	java/lang/Exception
      //   297	305	124	java/lang/Exception
      //   167	174	380	java/lang/Exception
      //   188	193	380	java/lang/Exception
      //   193	197	380	java/lang/Exception
    }
    
    public DevOptionsBuilder_BindDevOptionsFragment.If ˋ()
    {
      try
      {
        Object localObject;
        for (;;)
        {
          i = ʻ + 99;
          ॱॱ = i % 128;
          if (i % 2 != 0) {
            break label90;
          }
          break label75;
          localObject = new ML.ˊ(ML.this, this, null);
          break;
        }
        int i = ʻ + 111;
        ॱॱ = i % 128;
        if (i % 2 != 0) {
          return localObject;
        }
        return localObject;
        label75:
        label90:
        for (;;)
        {
          localObject = this.ˎ;
          if (localObject == null) {
            break label96;
          }
          break;
        }
      }
      catch (Exception localException)
      {
        throw localException;
      }
      label96:
      tmp118_116[0] = 14562;
      char[] tmp123_118 = tmp118_116;
      tmp123_118[1] = -1924;
      char[] tmp128_123 = tmp123_118;
      tmp128_123[2] = 9788;
      char[] tmp133_128 = tmp128_123;
      tmp133_128[3] = -14193;
      throw new IllegalStateException(DevOptionsFragment.class.getCanonicalName() + ˊ(tmp133_128, '\000', new char[] { -4352, -18183, 22739, -32678, -29, -26411, -13869, 31580, 30852, -5710, -6920, 21869 }, 0, new char[] { 0, 0, 0, 0 }).intern());
    }
    
    public void ॱ(DevOptionsFragment paramDevOptionsFragment)
    {
      break label59;
      int i = ॱॱ + 71;
      ʻ = i % 128;
      if (i % 2 != 0) {
        break label77;
      }
      for (;;)
      {
        switch (i)
        {
        default: 
          break;
        case 86: 
          this.ˎ = ((DevOptionsFragment)qn.ˊ(paramDevOptionsFragment));
          i = null.length;
          return;
          i = 8;
          break;
        case 8: 
          label59:
          label77:
          this.ˎ = ((DevOptionsFragment)qn.ˊ(paramDevOptionsFragment));
          return;
          i = 86;
        }
      }
    }
  }
  
  final class if
    extends EnrollmentActivityBuilder_BindPaymentTransactionsFragment.if.ˊ
  {
    private static long ˊ = 3710796825553904406L;
    private static int ˎ = 0;
    private static int ॱ = 1;
    private PaymentTransactionsFragment ˏ;
    
    private if() {}
    
    /* Error */
    private static String ˊ(char[] paramArrayOfChar)
    {
      // Byte code:
      //   0: goto +209 -> 209
      //   3: bipush 69
      //   5: istore_2
      //   6: goto +134 -> 140
      //   9: bipush 17
      //   11: istore_2
      //   12: goto +128 -> 140
      //   15: iconst_2
      //   16: istore_2
      //   17: goto +154 -> 171
      //   20: getstatic 22	o/ML$if:ॱ	I
      //   23: bipush 73
      //   25: iadd
      //   26: istore_1
      //   27: iload_1
      //   28: sipush 128
      //   31: irem
      //   32: putstatic 20	o/ML$if:ˎ	I
      //   35: iload_1
      //   36: iconst_2
      //   37: irem
      //   38: ifeq +6 -> 44
      //   41: goto +162 -> 203
      //   44: goto +198 -> 242
      //   47: astore_0
      //   48: aload_0
      //   49: athrow
      //   50: bipush 15
      //   52: istore_2
      //   53: goto +118 -> 171
      //   56: new 41	java/lang/String
      //   59: dup
      //   60: aload 8
      //   62: invokespecial 44	java/lang/String:<init>	([C)V
      //   65: areturn
      //   66: aload_0
      //   67: iload_1
      //   68: caload
      //   69: iload_1
      //   70: iload_3
      //   71: isub
      //   72: ixor
      //   73: i2l
      //   74: lstore 4
      //   76: getstatic 26	o/ML$if:ˊ	J
      //   79: lstore 6
      //   81: aload 8
      //   83: iload_1
      //   84: iconst_0
      //   85: iadd
      //   86: lload 4
      //   88: lload 6
      //   90: ldiv
      //   91: l2i
      //   92: i2c
      //   93: castore
      //   94: iload_1
      //   95: bipush 15
      //   97: iadd
      //   98: istore_1
      //   99: iload_1
      //   100: aload_0
      //   101: arraylength
      //   102: if_icmpge +6 -> 108
      //   105: goto -102 -> 3
      //   108: goto -99 -> 9
      //   111: getstatic 20	o/ML$if:ˎ	I
      //   114: istore_2
      //   115: iload_2
      //   116: bipush 109
      //   118: iadd
      //   119: istore_2
      //   120: iload_2
      //   121: sipush 128
      //   124: irem
      //   125: putstatic 22	o/ML$if:ॱ	I
      //   128: iload_2
      //   129: iconst_2
      //   130: irem
      //   131: ifne +6 -> 137
      //   134: goto -119 -> 15
      //   137: goto -87 -> 50
      //   140: iload_2
      //   141: lookupswitch	default:+27->168, 17:+-85->56, 69:+-30->111
      //   168: goto -112 -> 56
      //   171: iload_2
      //   172: lookupswitch	default:+28->200, 2:+-106->66, 15:+40->212
      //   200: goto +12 -> 212
      //   203: goto +39 -> 242
      //   206: astore_0
      //   207: aload_0
      //   208: athrow
      //   209: goto -189 -> 20
      //   212: aload 8
      //   214: iload_1
      //   215: iconst_1
      //   216: isub
      //   217: aload_0
      //   218: iload_1
      //   219: caload
      //   220: iload_1
      //   221: iload_3
      //   222: imul
      //   223: ixor
      //   224: i2l
      //   225: getstatic 26	o/ML$if:ˊ	J
      //   228: lxor
      //   229: l2i
      //   230: i2c
      //   231: castore
      //   232: iload_1
      //   233: iconst_1
      //   234: iadd
      //   235: istore_1
      //   236: goto -137 -> 99
      //   239: goto -140 -> 99
      //   242: aload_0
      //   243: iconst_0
      //   244: caload
      //   245: istore_3
      //   246: aload_0
      //   247: arraylength
      //   248: iconst_1
      //   249: isub
      //   250: newarray char
      //   252: astore 8
      //   254: iconst_1
      //   255: istore_1
      //   256: goto -17 -> 239
      // Local variable table:
      //   start	length	slot	name	signature
      //   0	259	0	paramArrayOfChar	char[]
      //   26	230	1	i	int
      //   5	167	2	j	int
      //   70	176	3	k	int
      //   74	13	4	l1	long
      //   79	10	6	l2	long
      //   60	193	8	arrayOfChar	char[]
      // Exception table:
      //   from	to	target	type
      //   76	81	47	java/lang/Exception
      //   111	115	47	java/lang/Exception
      //   120	128	206	java/lang/Exception
    }
    
    /* Error */
    public EnrollmentActivityBuilder_BindPaymentTransactionsFragment.if ˋ()
    {
      // Byte code:
      //   0: goto +46 -> 46
      //   3: aload_0
      //   4: getfield 47	o/ML$if:ˏ	Lro/btrl/enrollment/ui/fragment/PaymentTransactionsFragment;
      //   7: ifnonnull +6 -> 13
      //   10: goto +64 -> 74
      //   13: goto +36 -> 49
      //   16: astore_2
      //   17: aload_2
      //   18: athrow
      //   19: getstatic 22	o/ML$if:ॱ	I
      //   22: bipush 91
      //   24: iadd
      //   25: istore_1
      //   26: iload_1
      //   27: sipush 128
      //   30: irem
      //   31: putstatic 20	o/ML$if:ˎ	I
      //   34: iload_1
      //   35: iconst_2
      //   36: irem
      //   37: ifeq +6 -> 43
      //   40: goto +153 -> 193
      //   43: goto -40 -> 3
      //   46: goto -27 -> 19
      //   49: aload_0
      //   50: getfield 31	o/ML$if:ˋ	Lo/ML;
      //   53: astore_2
      //   54: new 50	o/ML$If
      //   57: dup
      //   58: aload_2
      //   59: aload_0
      //   60: aconst_null
      //   61: invokespecial 53	o/ML$If:<init>	(Lo/ML;Lo/ML$if;Lo/ML$4;)V
      //   64: astore_2
      //   65: goto +140 -> 205
      //   68: bipush 9
      //   70: istore_1
      //   71: goto +161 -> 232
      //   74: new 55	java/lang/StringBuilder
      //   77: dup
      //   78: invokespecial 56	java/lang/StringBuilder:<init>	()V
      //   81: astore_2
      //   82: ldc 58
      //   84: invokevirtual 64	java/lang/Class:getCanonicalName	()Ljava/lang/String;
      //   87: astore_3
      //   88: aload_2
      //   89: aload_3
      //   90: invokevirtual 68	java/lang/StringBuilder:append	(Ljava/lang/String;)Ljava/lang/StringBuilder;
      //   93: astore_2
      //   94: new 70	java/lang/IllegalStateException
      //   97: dup
      //   98: aload_2
      //   99: bipush 13
      //   101: newarray char
      //   103: dup
      //   104: iconst_0
      //   105: ldc 71
      //   107: castore
      //   108: dup
      //   109: iconst_1
      //   110: ldc 72
      //   112: castore
      //   113: dup
      //   114: iconst_2
      //   115: ldc 73
      //   117: castore
      //   118: dup
      //   119: iconst_3
      //   120: ldc 74
      //   122: castore
      //   123: dup
      //   124: iconst_4
      //   125: ldc 75
      //   127: castore
      //   128: dup
      //   129: iconst_5
      //   130: ldc 76
      //   132: castore
      //   133: dup
      //   134: bipush 6
      //   136: ldc 77
      //   138: castore
      //   139: dup
      //   140: bipush 7
      //   142: ldc 78
      //   144: castore
      //   145: dup
      //   146: bipush 8
      //   148: ldc 79
      //   150: castore
      //   151: dup
      //   152: bipush 9
      //   154: ldc 80
      //   156: castore
      //   157: dup
      //   158: bipush 10
      //   160: ldc 81
      //   162: castore
      //   163: dup
      //   164: bipush 11
      //   166: ldc 82
      //   168: castore
      //   169: dup
      //   170: bipush 12
      //   172: ldc 83
      //   174: castore
      //   175: invokestatic 85	o/ML$if:ˊ	([C)Ljava/lang/String;
      //   178: invokevirtual 88	java/lang/String:intern	()Ljava/lang/String;
      //   181: invokevirtual 68	java/lang/StringBuilder:append	(Ljava/lang/String;)Ljava/lang/StringBuilder;
      //   184: invokevirtual 91	java/lang/StringBuilder:toString	()Ljava/lang/String;
      //   187: invokespecial 94	java/lang/IllegalStateException:<init>	(Ljava/lang/String;)V
      //   190: athrow
      //   191: aload_2
      //   192: areturn
      //   193: goto -190 -> 3
      //   196: bipush 32
      //   198: istore_1
      //   199: goto +33 -> 232
      //   202: astore_2
      //   203: aload_2
      //   204: athrow
      //   205: getstatic 20	o/ML$if:ˎ	I
      //   208: bipush 31
      //   210: iadd
      //   211: istore_1
      //   212: iload_1
      //   213: sipush 128
      //   216: irem
      //   217: putstatic 22	o/ML$if:ॱ	I
      //   220: iload_1
      //   221: iconst_2
      //   222: irem
      //   223: ifne +6 -> 229
      //   226: goto -158 -> 68
      //   229: goto -33 -> 196
      //   232: iload_1
      //   233: lookupswitch	default:+27->260, 9:+29->262, 32:+-42->191
      //   260: aload_2
      //   261: areturn
      //   262: bipush 28
      //   264: iconst_0
      //   265: idiv
      //   266: istore_1
      //   267: aload_2
      //   268: areturn
      // Local variable table:
      //   start	length	slot	name	signature
      //   0	269	0	this	if
      //   25	242	1	i	int
      //   16	2	2	localException1	Exception
      //   53	139	2	localObject	Object
      //   202	66	2	localException2	Exception
      //   87	3	3	str	String
      // Exception table:
      //   from	to	target	type
      //   49	54	16	java/lang/Exception
      //   82	88	202	java/lang/Exception
      //   88	94	202	java/lang/Exception
      //   94	191	202	java/lang/Exception
    }
    
    public void ॱ(PaymentTransactionsFragment paramPaymentTransactionsFragment)
    {
      int i;
      switch (i)
      {
      case 10: 
      default: 
        return;
        i = ˎ + 81;
        ॱ = i % 128;
        if (i % 2 != 0) {
          break;
        }
        i = 1;
        break;
      }
      for (;;)
      {
        i = ˎ + 63;
        ॱ = i % 128;
        if (i % 2 != 0)
        {
          break label105;
          throw new NullPointerException();
          i = 0;
          break label150;
          label105:
          i = 10;
          break;
        }
        i = 92;
        break;
        this.ˏ = ((PaymentTransactionsFragment)qn.ˊ(paramPaymentTransactionsFragment));
        i = 85 / 0;
      }
      for (;;)
      {
        this.ˏ = ((PaymentTransactionsFragment)qn.ˊ(paramPaymentTransactionsFragment));
        break;
        label150:
        switch (i)
        {
        }
      }
    }
  }
  
  final class ˊ
    implements DevOptionsBuilder_BindDevOptionsFragment.If
  {
    private DevOptionsFragment ˋ;
    
    private ˊ(ML.iF paramIF)
    {
      ॱ(paramIF);
    }
    
    private JB.ˊ ˊ()
    {
      return Jv.ˊ(ML.ˎ(ML.this), this.ˋ, (Jt)ML.ॱॱ(ML.this).ˋ(), ˎ());
    }
    
    private wk ˎ()
    {
      return Jx.ˋ(ML.ˎ(ML.this), He.ˊ(ML.ʻ(ML.this)));
    }
    
    private DevOptionsFragment ॱ(DevOptionsFragment paramDevOptionsFragment)
    {
      Jz.ˎ(paramDevOptionsFragment, ˊ());
      return paramDevOptionsFragment;
    }
    
    private void ॱ(ML.iF paramIF)
    {
      this.ˋ = ML.iF.ˏ(paramIF);
    }
    
    public void ˊ(DevOptionsFragment paramDevOptionsFragment)
    {
      ॱ(paramDevOptionsFragment);
    }
  }
  
  static final class ˋ
    implements MD.if
  {
    private static boolean ʻ;
    private static int ʼ = 4;
    private static boolean ʽ;
    private static int ˊॱ = 0;
    private static int ˋॱ = 1;
    private static char[] ॱॱ;
    private DevOptionsModule ˊ;
    private CommonsModule ˋ;
    private RepositoryModule ˎ;
    private BootModule ˏ;
    private EnrollmentModule ॱ;
    private Application ᐝ;
    
    static
    {
      ʻ = true;
      ʽ = true;
      ॱॱ = new char[] { 36, 113, 121, 119, 120, 102, 105 };
    }
    
    private ˋ() {}
    
    private static String ˋ(byte[] paramArrayOfByte, int[] paramArrayOfInt, char[] paramArrayOfChar, int paramInt)
    {
      break label364;
      int k;
      label22:
      label52:
      int j;
      int i;
      for (;;)
      {
        break label181;
        return new String(paramArrayOfInt);
        k = 42;
        break label276;
        k = ˋॱ + 109;
        ˊॱ = k % 128;
        if (k % 2 == 0)
        {
          break label181;
          paramArrayOfInt[j] = ((char)(paramArrayOfByte[(paramArrayOfChar[(paramInt - 1 - j)] - k)] - i));
          j += 1;
          break label169;
          return new String(paramArrayOfChar);
          label91:
          k = paramInt;
          if (ʽ) {
            break label337;
          }
          break label412;
          paramInt = 0;
          break label234;
          j = paramArrayOfChar.length;
          paramInt = j;
          paramArrayOfInt = new char[j];
        }
      }
      label169:
      label181:
      label194:
      label231:
      label234:
      label271:
      label276:
      label337:
      label364:
      label394:
      label400:
      label412:
      label426:
      label456:
      label483:
      label489:
      label517:
      label561:
      for (;;)
      {
        k = 55;
        break label276;
        char[] arrayOfChar;
        try
        {
          arrayOfChar = ॱॱ;
          i = ʼ;
          boolean bool = ʻ;
          j = null.length;
          if (bool) {
            break label517;
          }
          paramArrayOfByte = arrayOfChar;
        }
        catch (Exception paramArrayOfByte)
        {
          throw paramArrayOfByte;
        }
        j = 0;
        if (j < paramInt) {
          break label52;
        }
        break;
        for (;;)
        {
          if (j < m) {
            break label561;
          }
          break;
          return new String(paramArrayOfInt);
          arrayOfChar = ॱॱ;
          i = ʼ;
          if (!ʻ)
          {
            paramArrayOfByte = arrayOfChar;
            break label91;
            for (;;)
            {
              break label400;
              for (;;)
              {
                switch (paramInt)
                {
                }
                j = paramArrayOfChar.length;
                paramInt = j;
                paramArrayOfInt = new char[j];
                break;
                paramInt = 1;
              }
              switch (k)
              {
              case 42: 
              default: 
                break label194;
                for (;;)
                {
                  i = ˋॱ + 57;
                  ˊॱ = i % 128;
                  if (i % 2 != 0) {
                    break label394;
                  }
                  break label483;
                  paramInt = ˋॱ + 9;
                  ˊॱ = paramInt % 128;
                  if (paramInt % 2 != 0) {
                    break;
                  }
                  break label271;
                }
                for (;;)
                {
                  paramArrayOfChar[paramInt] = ((char)(paramArrayOfByte[(paramArrayOfInt[(j - 1 - paramInt)] - k)] - i));
                  paramInt += 1;
                  break label231;
                  i = 1;
                  break label456;
                  for (;;)
                  {
                    if (paramInt < j) {
                      break label426;
                    }
                    break;
                    j = paramArrayOfInt.length;
                    paramArrayOfChar = new char[j];
                    paramInt = 0;
                  }
                  m = ˊॱ + 111;
                  ˋॱ = m % 128;
                  if (m % 2 == 0) {
                    break label489;
                  }
                }
                for (;;)
                {
                  switch (i)
                  {
                  }
                  break;
                  i = 0;
                }
                paramArrayOfChar[paramInt] = ((char)(paramArrayOfByte[(paramArrayOfInt[((j >> 1) + paramInt)] * k)] - i));
                paramInt += 55;
              }
            }
          }
          int m = paramArrayOfByte.length;
          paramArrayOfInt = new char[m];
          j = 0;
          break label22;
          paramArrayOfInt[j] = ((char)(arrayOfChar[(paramArrayOfByte[(m - 1 - j)] + paramInt)] - i));
          j += 1;
        }
      }
    }
    
    /* Error */
    public MD ˊ()
    {
      // Byte code:
      //   0: goto +358 -> 358
      //   3: aload_0
      //   4: getfield 85	o/ML$ˋ:ᐝ	Landroid/app/Application;
      //   7: ifnonnull +6 -> 13
      //   10: goto +218 -> 228
      //   13: goto +22 -> 35
      //   16: aload_0
      //   17: getfield 79	o/ML$ˋ:ˏ	Lro/btrl/boot/di/module/BootModule;
      //   20: ifnonnull +6 -> 26
      //   23: goto +158 -> 181
      //   26: goto +317 -> 343
      //   29: bipush 71
      //   31: istore_1
      //   32: goto +95 -> 127
      //   35: new 8	o/ML
      //   38: dup
      //   39: aload_0
      //   40: aconst_null
      //   41: invokespecial 88	o/ML:<init>	(Lo/ML$ˋ;Lo/ML$4;)V
      //   44: areturn
      //   45: aload_0
      //   46: getfield 76	o/ML$ˋ:ˊ	Lro/btrl/devoptions/di/module/DevOptionsModule;
      //   49: ifnonnull +6 -> 55
      //   52: goto +315 -> 367
      //   55: goto -52 -> 3
      //   58: goto +285 -> 343
      //   61: goto -16 -> 45
      //   64: aload_0
      //   65: new 90	ro/btrl/commons/di/module/RepositoryModule
      //   68: dup
      //   69: invokespecial 91	ro/btrl/commons/di/module/RepositoryModule:<init>	()V
      //   72: putfield 61	o/ML$ˋ:ˎ	Lro/btrl/commons/di/module/RepositoryModule;
      //   75: goto -59 -> 16
      //   78: astore_2
      //   79: aload_2
      //   80: athrow
      //   81: aload_0
      //   82: getfield 61	o/ML$ˋ:ˎ	Lro/btrl/commons/di/module/RepositoryModule;
      //   85: ifnonnull +6 -> 91
      //   88: goto -24 -> 64
      //   91: goto -75 -> 16
      //   94: goto +249 -> 343
      //   97: iload_1
      //   98: lookupswitch	default:+26->124, 13:+-4->94, 54:+-40->58
      //   124: goto -66 -> 58
      //   127: iload_1
      //   128: lookupswitch	default:+28->156, 71:+50->178, 98:+-67->61
      //   156: goto +22 -> 178
      //   159: new 93	ro/btrl/enrollment/di/module/EnrollmentModule
      //   162: dup
      //   163: invokespecial 94	ro/btrl/enrollment/di/module/EnrollmentModule:<init>	()V
      //   166: astore_2
      //   167: aload_0
      //   168: aload_2
      //   169: putfield 73	o/ML$ˋ:ॱ	Lro/btrl/enrollment/di/module/EnrollmentModule;
      //   172: goto +252 -> 424
      //   175: astore_2
      //   176: aload_2
      //   177: athrow
      //   178: goto -133 -> 45
      //   181: aload_0
      //   182: new 96	ro/btrl/boot/di/module/BootModule
      //   185: dup
      //   186: invokespecial 97	ro/btrl/boot/di/module/BootModule:<init>	()V
      //   189: putfield 79	o/ML$ˋ:ˏ	Lro/btrl/boot/di/module/BootModule;
      //   192: goto +205 -> 397
      //   195: getstatic 33	o/ML$ˋ:ˊॱ	I
      //   198: bipush 87
      //   200: iadd
      //   201: istore_1
      //   202: iload_1
      //   203: sipush 128
      //   206: irem
      //   207: putstatic 35	o/ML$ˋ:ˋॱ	I
      //   210: iload_1
      //   211: iconst_2
      //   212: irem
      //   213: ifne +6 -> 219
      //   216: goto +121 -> 337
      //   219: goto -190 -> 29
      //   222: bipush 13
      //   224: istore_1
      //   225: goto -128 -> 97
      //   228: new 99	java/lang/IllegalStateException
      //   231: dup
      //   232: new 101	java/lang/StringBuilder
      //   235: dup
      //   236: invokespecial 102	java/lang/StringBuilder:<init>	()V
      //   239: ldc 104
      //   241: invokevirtual 110	java/lang/Class:getCanonicalName	()Ljava/lang/String;
      //   244: invokevirtual 114	java/lang/StringBuilder:append	(Ljava/lang/String;)Ljava/lang/StringBuilder;
      //   247: bipush 12
      //   249: newarray byte
      //   251: dup
      //   252: iconst_0
      //   253: ldc 115
      //   255: bastore
      //   256: dup
      //   257: iconst_1
      //   258: ldc 116
      //   260: bastore
      //   261: dup
      //   262: iconst_2
      //   263: ldc 117
      //   265: bastore
      //   266: dup
      //   267: iconst_3
      //   268: ldc 118
      //   270: bastore
      //   271: dup
      //   272: iconst_4
      //   273: ldc 116
      //   275: bastore
      //   276: dup
      //   277: iconst_5
      //   278: ldc 119
      //   280: bastore
      //   281: dup
      //   282: bipush 6
      //   284: ldc 118
      //   286: bastore
      //   287: dup
      //   288: bipush 7
      //   290: ldc 115
      //   292: bastore
      //   293: dup
      //   294: bipush 8
      //   296: ldc 117
      //   298: bastore
      //   299: dup
      //   300: bipush 9
      //   302: ldc 120
      //   304: bastore
      //   305: dup
      //   306: bipush 10
      //   308: ldc 121
      //   310: bastore
      //   311: dup
      //   312: bipush 11
      //   314: ldc 118
      //   316: bastore
      //   317: aconst_null
      //   318: aconst_null
      //   319: bipush 127
      //   321: invokestatic 123	o/ML$ˋ:ˋ	([B[I[CI)Ljava/lang/String;
      //   324: invokevirtual 126	java/lang/String:intern	()Ljava/lang/String;
      //   327: invokevirtual 114	java/lang/StringBuilder:append	(Ljava/lang/String;)Ljava/lang/StringBuilder;
      //   330: invokevirtual 129	java/lang/StringBuilder:toString	()Ljava/lang/String;
      //   333: invokespecial 132	java/lang/IllegalStateException:<init>	(Ljava/lang/String;)V
      //   336: athrow
      //   337: bipush 98
      //   339: istore_1
      //   340: goto -213 -> 127
      //   343: aload_0
      //   344: getfield 73	o/ML$ˋ:ॱ	Lro/btrl/enrollment/di/module/EnrollmentModule;
      //   347: astore_2
      //   348: aload_2
      //   349: ifnonnull +6 -> 355
      //   352: goto -193 -> 159
      //   355: goto +69 -> 424
      //   358: goto -277 -> 81
      //   361: bipush 54
      //   363: istore_1
      //   364: goto -267 -> 97
      //   367: new 134	ro/btrl/devoptions/di/module/DevOptionsModule
      //   370: dup
      //   371: invokespecial 135	ro/btrl/devoptions/di/module/DevOptionsModule:<init>	()V
      //   374: astore_2
      //   375: aload_0
      //   376: aload_2
      //   377: putfield 76	o/ML$ˋ:ˊ	Lro/btrl/devoptions/di/module/DevOptionsModule;
      //   380: goto -377 -> 3
      //   383: aload_0
      //   384: new 137	ro/btrl/commons/di/module/CommonsModule
      //   387: dup
      //   388: invokespecial 138	ro/btrl/commons/di/module/CommonsModule:<init>	()V
      //   391: putfield 82	o/ML$ˋ:ˋ	Lro/btrl/commons/di/module/CommonsModule;
      //   394: goto -199 -> 195
      //   397: getstatic 33	o/ML$ˋ:ˊॱ	I
      //   400: bipush 35
      //   402: iadd
      //   403: istore_1
      //   404: iload_1
      //   405: sipush 128
      //   408: irem
      //   409: putstatic 35	o/ML$ˋ:ˋॱ	I
      //   412: iload_1
      //   413: iconst_2
      //   414: irem
      //   415: ifne +6 -> 421
      //   418: goto -57 -> 361
      //   421: goto -199 -> 222
      //   424: aload_0
      //   425: getfield 82	o/ML$ˋ:ˋ	Lro/btrl/commons/di/module/CommonsModule;
      //   428: ifnonnull +6 -> 434
      //   431: goto -48 -> 383
      //   434: goto -389 -> 45
      // Local variable table:
      //   start	length	slot	name	signature
      //   0	437	0	this	ˋ
      //   31	384	1	i	int
      //   78	2	2	localException1	Exception
      //   166	3	2	localEnrollmentModule	EnrollmentModule
      //   175	2	2	localException2	Exception
      //   347	30	2	localObject	Object
      // Exception table:
      //   from	to	target	type
      //   167	172	78	java/lang/Exception
      //   375	380	78	java/lang/Exception
      //   343	348	175	java/lang/Exception
      //   397	404	175	java/lang/Exception
      //   404	412	175	java/lang/Exception
    }
    
    public ˋ ˊ(Application paramApplication)
    {
      for (;;)
      {
        this.ᐝ = ((Application)qn.ˊ(paramApplication));
        break label20;
        break label45;
        label20:
        int i = ˋॱ + 35;
        ˊॱ = i % 128;
        if (i % 2 != 0) {
          return this;
        }
        return this;
        label45:
        i = ˊॱ + 97;
        ˋॱ = i % 128;
        if (i % 2 == 0) {}
      }
    }
  }
  
  final class ˎ
    extends BootActivityBuilder_BindTourActivity.ˊ.if
  {
    private static char[] ˊ = { 32, 109, 117, 115, 116, 98, 101, 33, 34 };
    private static char ˎ = '\003';
    private static int ॱ = 0;
    private static int ॱॱ = 1;
    private TourActivity ˏ;
    
    private ˎ() {}
    
    /* Error */
    private static String ˎ(char[] paramArrayOfChar, int paramInt, byte paramByte)
    {
      // Byte code:
      //   0: goto +106 -> 106
      //   3: getstatic 23	o/ML$ˎ:ॱॱ	I
      //   6: bipush 39
      //   8: iadd
      //   9: istore 4
      //   11: iload 4
      //   13: sipush 128
      //   16: irem
      //   17: putstatic 21	o/ML$ˎ:ॱ	I
      //   20: iload 4
      //   22: iconst_2
      //   23: irem
      //   24: ifeq +6 -> 30
      //   27: goto +76 -> 103
      //   30: iload 7
      //   32: iload 5
      //   34: invokestatic 54	o/oO:ˊ	(II)I
      //   37: istore 4
      //   39: iload 6
      //   41: iload 5
      //   43: invokestatic 54	o/oO:ˊ	(II)I
      //   46: istore 6
      //   48: iload 4
      //   50: iload 8
      //   52: iload 5
      //   54: invokestatic 57	o/oO:ˏ	(III)I
      //   57: istore 4
      //   59: iload 6
      //   61: iload 9
      //   63: iload 5
      //   65: invokestatic 57	o/oO:ˏ	(III)I
      //   68: istore 6
      //   70: aload 11
      //   72: iload_3
      //   73: aload 10
      //   75: iload 4
      //   77: caload
      //   78: castore
      //   79: aload 11
      //   81: iload_3
      //   82: iconst_1
      //   83: iadd
      //   84: aload 10
      //   86: iload 6
      //   88: caload
      //   89: castore
      //   90: goto +150 -> 240
      //   93: new 59	java/lang/String
      //   96: dup
      //   97: aload 11
      //   99: invokespecial 62	java/lang/String:<init>	([C)V
      //   102: areturn
      //   103: goto -73 -> 30
      //   106: goto +190 -> 296
      //   109: iload 4
      //   111: tableswitch	default:+21->132, 0:+300->411, 1:+366->477
      //   132: goto +345 -> 477
      //   135: bipush 98
      //   137: istore_3
      //   138: goto +244 -> 382
      //   141: bipush 76
      //   143: istore_3
      //   144: goto +238 -> 382
      //   147: aload 11
      //   149: iload_3
      //   150: iload 6
      //   152: iload_2
      //   153: isub
      //   154: i2c
      //   155: castore
      //   156: aload 11
      //   158: iload_3
      //   159: iconst_1
      //   160: iadd
      //   161: iload 4
      //   163: iload_2
      //   164: isub
      //   165: i2c
      //   166: castore
      //   167: goto +73 -> 240
      //   170: iload_3
      //   171: iload_1
      //   172: if_icmpge +6 -> 178
      //   175: goto +365 -> 540
      //   178: goto -85 -> 93
      //   181: astore_0
      //   182: aload_0
      //   183: athrow
      //   184: goto -14 -> 170
      //   187: iconst_1
      //   188: istore 4
      //   190: goto +386 -> 576
      //   193: iconst_0
      //   194: istore_3
      //   195: goto -11 -> 184
      //   198: iload_1
      //   199: iconst_1
      //   200: if_icmple +6 -> 206
      //   203: goto -62 -> 141
      //   206: goto -71 -> 135
      //   209: iconst_0
      //   210: istore 4
      //   212: goto +364 -> 576
      //   215: aload_0
      //   216: iload_3
      //   217: caload
      //   218: istore 6
      //   220: aload_0
      //   221: iload_3
      //   222: iconst_1
      //   223: iadd
      //   224: caload
      //   225: istore 4
      //   227: iload 6
      //   229: iload 4
      //   231: if_icmpne +6 -> 237
      //   234: goto -87 -> 147
      //   237: goto +10 -> 247
      //   240: iload_3
      //   241: iconst_2
      //   242: iadd
      //   243: istore_3
      //   244: goto -74 -> 170
      //   247: iload 6
      //   249: iload 5
      //   251: invokestatic 64	o/oO:ॱ	(II)I
      //   254: istore 7
      //   256: iload 6
      //   258: iload 5
      //   260: invokestatic 66	o/oO:ˋ	(II)I
      //   263: istore 8
      //   265: iload 4
      //   267: iload 5
      //   269: invokestatic 64	o/oO:ॱ	(II)I
      //   272: istore 6
      //   274: iload 4
      //   276: iload 5
      //   278: invokestatic 66	o/oO:ˋ	(II)I
      //   281: istore 9
      //   283: iload 8
      //   285: iload 9
      //   287: if_icmpne +6 -> 293
      //   290: goto -287 -> 3
      //   293: goto +49 -> 342
      //   296: getstatic 34	o/ML$ˎ:ˊ	[C
      //   299: astore 10
      //   301: iload_1
      //   302: istore_3
      //   303: getstatic 36	o/ML$ˎ:ˎ	C
      //   306: istore 5
      //   308: iload_3
      //   309: newarray char
      //   311: astore 11
      //   313: iload_3
      //   314: iconst_2
      //   315: irem
      //   316: ifeq +6 -> 322
      //   319: goto -132 -> 187
      //   322: goto -113 -> 209
      //   325: iload_3
      //   326: iconst_1
      //   327: isub
      //   328: istore_1
      //   329: aload 11
      //   331: iload_1
      //   332: aload_0
      //   333: iload_1
      //   334: caload
      //   335: iload_2
      //   336: isub
      //   337: i2c
      //   338: castore
      //   339: goto -141 -> 198
      //   342: iload 7
      //   344: iload 6
      //   346: if_icmpne +6 -> 352
      //   349: goto +260 -> 609
      //   352: goto +218 -> 570
      //   355: getstatic 23	o/ML$ˎ:ॱॱ	I
      //   358: bipush 39
      //   360: iadd
      //   361: istore_1
      //   362: iload_1
      //   363: sipush 128
      //   366: irem
      //   367: putstatic 21	o/ML$ˎ:ॱ	I
      //   370: iload_1
      //   371: iconst_2
      //   372: irem
      //   373: ifeq +6 -> 379
      //   376: goto +80 -> 456
      //   379: goto -54 -> 325
      //   382: iload_3
      //   383: lookupswitch	default:+25->408, 76:+-190->193, 98:+-290->93
      //   408: goto -315 -> 93
      //   411: iload 7
      //   413: iload 9
      //   415: iload 5
      //   417: invokestatic 57	o/oO:ˏ	(III)I
      //   420: istore 4
      //   422: iload 6
      //   424: iload 8
      //   426: iload 5
      //   428: invokestatic 57	o/oO:ˏ	(III)I
      //   431: istore 6
      //   433: aload 11
      //   435: iload_3
      //   436: aload 10
      //   438: iload 4
      //   440: caload
      //   441: castore
      //   442: aload 11
      //   444: iload_3
      //   445: iconst_1
      //   446: iadd
      //   447: aload 10
      //   449: iload 6
      //   451: caload
      //   452: castore
      //   453: goto -213 -> 240
      //   456: iload_3
      //   457: bipush 127
      //   459: iadd
      //   460: istore_1
      //   461: aload 11
      //   463: iload_1
      //   464: aload_0
      //   465: iload_1
      //   466: caload
      //   467: iload_2
      //   468: iadd
      //   469: i2c
      //   470: castore
      //   471: goto -273 -> 198
      //   474: astore_0
      //   475: aload_0
      //   476: athrow
      //   477: iload 8
      //   479: iload 5
      //   481: invokestatic 54	o/oO:ˊ	(II)I
      //   484: istore 4
      //   486: iload 9
      //   488: iload 5
      //   490: invokestatic 54	o/oO:ˊ	(II)I
      //   493: istore 8
      //   495: iload 7
      //   497: iload 4
      //   499: iload 5
      //   501: invokestatic 57	o/oO:ˏ	(III)I
      //   504: istore 4
      //   506: iload 6
      //   508: iload 8
      //   510: iload 5
      //   512: invokestatic 57	o/oO:ˏ	(III)I
      //   515: istore 6
      //   517: aload 11
      //   519: iload_3
      //   520: aload 10
      //   522: iload 4
      //   524: caload
      //   525: castore
      //   526: aload 11
      //   528: iload_3
      //   529: iconst_1
      //   530: iadd
      //   531: aload 10
      //   533: iload 6
      //   535: caload
      //   536: castore
      //   537: goto -297 -> 240
      //   540: getstatic 21	o/ML$ˎ:ॱ	I
      //   543: bipush 47
      //   545: iadd
      //   546: istore 4
      //   548: iload 4
      //   550: sipush 128
      //   553: irem
      //   554: putstatic 23	o/ML$ˎ:ॱॱ	I
      //   557: iload 4
      //   559: iconst_2
      //   560: irem
      //   561: ifne +6 -> 567
      //   564: goto +51 -> 615
      //   567: goto -352 -> 215
      //   570: iconst_0
      //   571: istore 4
      //   573: goto -464 -> 109
      //   576: iload_3
      //   577: istore_1
      //   578: iload 4
      //   580: tableswitch	default:+24->604, 0:+-382->198, 1:+-225->355
      //   604: iload_3
      //   605: istore_1
      //   606: goto -408 -> 198
      //   609: iconst_1
      //   610: istore 4
      //   612: goto -503 -> 109
      //   615: goto -400 -> 215
      // Local variable table:
      //   start	length	slot	name	signature
      //   0	618	0	paramArrayOfChar	char[]
      //   0	618	1	paramInt	int
      //   0	618	2	paramByte	byte
      //   72	533	3	i	int
      //   9	602	4	b1	byte
      //   32	479	5	j	int
      //   39	495	6	b2	byte
      //   30	466	7	b3	byte
      //   50	459	8	k	int
      //   61	426	9	m	int
      //   73	459	10	arrayOfChar1	char[]
      //   70	457	11	arrayOfChar2	char[]
      // Exception table:
      //   from	to	target	type
      //   247	256	181	java/lang/Exception
      //   256	265	181	java/lang/Exception
      //   265	274	181	java/lang/Exception
      //   274	283	181	java/lang/Exception
      //   256	265	474	java/lang/Exception
    }
    
    /* Error */
    public BootActivityBuilder_BindTourActivity.ˊ ˋ()
    {
      // Byte code:
      //   0: goto +161 -> 161
      //   3: aconst_null
      //   4: arraylength
      //   5: istore_1
      //   6: aload_2
      //   7: areturn
      //   8: getstatic 21	o/ML$ˎ:ॱ	I
      //   11: bipush 43
      //   13: iadd
      //   14: istore_1
      //   15: iload_1
      //   16: sipush 128
      //   19: irem
      //   20: putstatic 23	o/ML$ˎ:ॱॱ	I
      //   23: iload_1
      //   24: iconst_2
      //   25: irem
      //   26: ifne +6 -> 32
      //   29: goto +135 -> 164
      //   32: goto +138 -> 170
      //   35: aload_0
      //   36: getfield 69	o/ML$ˎ:ˏ	Lro/btrl/boot/ui/activity/TourActivity;
      //   39: ifnonnull +6 -> 45
      //   42: goto +6 -> 48
      //   45: goto +198 -> 243
      //   48: new 75	java/lang/StringBuilder
      //   51: dup
      //   52: invokespecial 76	java/lang/StringBuilder:<init>	()V
      //   55: astore_2
      //   56: ldc 78
      //   58: invokevirtual 84	java/lang/Class:getCanonicalName	()Ljava/lang/String;
      //   61: astore_3
      //   62: new 86	java/lang/IllegalStateException
      //   65: dup
      //   66: aload_2
      //   67: aload_3
      //   68: invokevirtual 90	java/lang/StringBuilder:append	(Ljava/lang/String;)Ljava/lang/StringBuilder;
      //   71: bipush 12
      //   73: newarray char
      //   75: dup
      //   76: iconst_0
      //   77: ldc 91
      //   79: castore
      //   80: dup
      //   81: iconst_1
      //   82: ldc 92
      //   84: castore
      //   85: dup
      //   86: iconst_2
      //   87: ldc 93
      //   89: castore
      //   90: dup
      //   91: iconst_3
      //   92: ldc 94
      //   94: castore
      //   95: dup
      //   96: iconst_4
      //   97: ldc 95
      //   99: castore
      //   100: dup
      //   101: iconst_5
      //   102: ldc 91
      //   104: castore
      //   105: dup
      //   106: bipush 6
      //   108: ldc 95
      //   110: castore
      //   111: dup
      //   112: bipush 7
      //   114: ldc 96
      //   116: castore
      //   117: dup
      //   118: bipush 8
      //   120: ldc 95
      //   122: castore
      //   123: dup
      //   124: bipush 9
      //   126: ldc 97
      //   128: castore
      //   129: dup
      //   130: bipush 10
      //   132: ldc 98
      //   134: castore
      //   135: dup
      //   136: bipush 11
      //   138: ldc 95
      //   140: castore
      //   141: bipush 12
      //   143: bipush 17
      //   145: invokestatic 100	o/ML$ˎ:ˎ	([CIB)Ljava/lang/String;
      //   148: invokevirtual 103	java/lang/String:intern	()Ljava/lang/String;
      //   151: invokevirtual 90	java/lang/StringBuilder:append	(Ljava/lang/String;)Ljava/lang/StringBuilder;
      //   154: invokevirtual 106	java/lang/StringBuilder:toString	()Ljava/lang/String;
      //   157: invokespecial 109	java/lang/IllegalStateException:<init>	(Ljava/lang/String;)V
      //   160: athrow
      //   161: goto +26 -> 187
      //   164: bipush 32
      //   166: istore_1
      //   167: goto +47 -> 214
      //   170: bipush 33
      //   172: istore_1
      //   173: goto +41 -> 214
      //   176: aload_2
      //   177: areturn
      //   178: astore_2
      //   179: aload_2
      //   180: athrow
      //   181: goto -146 -> 35
      //   184: astore_2
      //   185: aload_2
      //   186: athrow
      //   187: getstatic 23	o/ML$ˎ:ॱॱ	I
      //   190: bipush 53
      //   192: iadd
      //   193: istore_1
      //   194: iload_1
      //   195: sipush 128
      //   198: irem
      //   199: putstatic 21	o/ML$ˎ:ॱ	I
      //   202: iload_1
      //   203: iconst_2
      //   204: irem
      //   205: ifeq +6 -> 211
      //   208: goto -27 -> 181
      //   211: goto -176 -> 35
      //   214: iload_1
      //   215: lookupswitch	default:+25->240, 32:+-212->3, 33:+-39->176
      //   240: goto -237 -> 3
      //   243: new 111	o/ML$ˏ
      //   246: dup
      //   247: aload_0
      //   248: getfield 41	o/ML$ˎ:ˋ	Lo/ML;
      //   251: aload_0
      //   252: aconst_null
      //   253: invokespecial 114	o/ML$ˏ:<init>	(Lo/ML;Lo/ML$ˎ;Lo/ML$4;)V
      //   256: astore_2
      //   257: goto -249 -> 8
      // Local variable table:
      //   start	length	slot	name	signature
      //   0	260	0	this	ˎ
      //   5	210	1	i	int
      //   6	171	2	localObject	Object
      //   178	2	2	localException1	Exception
      //   184	2	2	localException2	Exception
      //   256	1	2	localˏ	ML.ˏ
      //   61	7	3	str	String
      // Exception table:
      //   from	to	target	type
      //   56	62	178	java/lang/Exception
      //   62	161	178	java/lang/Exception
      //   187	194	178	java/lang/Exception
      //   194	202	178	java/lang/Exception
      //   194	202	184	java/lang/Exception
    }
    
    /* Error */
    public void ॱ(TourActivity paramTourActivity)
    {
      // Byte code:
      //   0: goto +6 -> 6
      //   3: astore_1
      //   4: aload_1
      //   5: athrow
      //   6: goto +29 -> 35
      //   9: iload_2
      //   10: tableswitch	default:+22->32, 0:+82->92, 1:+54->64
      //   32: goto +60 -> 92
      //   35: getstatic 23	o/ML$ˎ:ॱॱ	I
      //   38: bipush 59
      //   40: iadd
      //   41: istore_2
      //   42: iload_2
      //   43: sipush 128
      //   46: irem
      //   47: putstatic 21	o/ML$ˎ:ॱ	I
      //   50: iload_2
      //   51: iconst_2
      //   52: irem
      //   53: ifeq +6 -> 59
      //   56: goto +31 -> 87
      //   59: iconst_0
      //   60: istore_2
      //   61: goto -52 -> 9
      //   64: aload_1
      //   65: invokestatic 126	o/qn:ˊ	(Ljava/lang/Object;)Ljava/lang/Object;
      //   68: astore_1
      //   69: aload_1
      //   70: checkcast 78	ro/btrl/boot/ui/activity/TourActivity
      //   73: astore_1
      //   74: aload_0
      //   75: aload_1
      //   76: putfield 69	o/ML$ˎ:ˏ	Lro/btrl/boot/ui/activity/TourActivity;
      //   79: new 71	java/lang/NullPointerException
      //   82: dup
      //   83: invokespecial 72	java/lang/NullPointerException:<init>	()V
      //   86: athrow
      //   87: iconst_1
      //   88: istore_2
      //   89: goto -80 -> 9
      //   92: aload_1
      //   93: invokestatic 126	o/qn:ˊ	(Ljava/lang/Object;)Ljava/lang/Object;
      //   96: astore_1
      //   97: aload_1
      //   98: checkcast 78	ro/btrl/boot/ui/activity/TourActivity
      //   101: astore_1
      //   102: aload_0
      //   103: aload_1
      //   104: putfield 69	o/ML$ˎ:ˏ	Lro/btrl/boot/ui/activity/TourActivity;
      //   107: getstatic 23	o/ML$ˎ:ॱॱ	I
      //   110: bipush 113
      //   112: iadd
      //   113: istore_2
      //   114: iload_2
      //   115: sipush 128
      //   118: irem
      //   119: putstatic 21	o/ML$ˎ:ॱ	I
      //   122: iload_2
      //   123: iconst_2
      //   124: irem
      //   125: ifeq +4 -> 129
      //   128: return
      //   129: return
      // Local variable table:
      //   start	length	slot	name	signature
      //   0	130	0	this	ˎ
      //   0	130	1	paramTourActivity	TourActivity
      //   9	116	2	i	int
      // Exception table:
      //   from	to	target	type
      //   64	69	3	java/lang/Exception
      //   69	74	3	java/lang/Exception
      //   74	79	3	java/lang/Exception
      //   79	87	3	java/lang/Exception
      //   92	97	3	java/lang/Exception
      //   97	102	3	java/lang/Exception
      //   102	107	3	java/lang/Exception
    }
  }
  
  final class ˏ
    implements BootActivityBuilder_BindTourActivity.ˊ
  {
    private TourActivity ˊ;
    
    private ˏ(ML.ˎ paramˎ)
    {
      ˋ(paramˎ);
    }
    
    private DO.iF ˊ()
    {
      return Dz.ॱ(ML.ˋ(ML.this), this.ˊ, (DF)ML.ॱ(ML.this).ˋ());
    }
    
    private void ˋ(ML.ˎ paramˎ)
    {
      this.ˊ = ML.ˎ.ˎ(paramˎ);
    }
    
    private TourActivity ॱ(TourActivity paramTourActivity)
    {
      DQ.ˎ(paramTourActivity, ˊ());
      return paramTourActivity;
    }
    
    public void ˊ(TourActivity paramTourActivity)
    {
      ॱ(paramTourActivity);
    }
  }
}
