package o;

import android.content.res.Resources;
import android.view.View;
import android.widget.ScrollView;
import java.math.BigDecimal;

public class Ml
  extends IB<Mz>
{
  private static char[] ʽॱ = { 101, 120, 116, 114, 97, 95, 99, 111, 110, 112, 115, 104, 68, 69, 70, 80, 50, 83, 84, 73, 78, 71, 105, 109, 121, 102, 100, 108, 103, 106, 107, 113, 117, 118, 119, 122 };
  private static int ˉ = 0;
  private static int ˊˊ = 1;
  private static char ˊᐝ = '\006';
  private FT ʼॱ;
  private Is ʾ;
  private FP ʿ;
  private HQ ˈ;
  
  public Ml() {}
  
  /* Error */
  private void ʻॱ()
  {
    // Byte code:
    //   0: goto +72 -> 72
    //   3: bipush 83
    //   5: istore_2
    //   6: goto +144 -> 150
    //   9: getstatic 28	o/Ml:ˉ	I
    //   12: bipush 15
    //   14: iadd
    //   15: istore_2
    //   16: iload_2
    //   17: sipush 128
    //   20: irem
    //   21: putstatic 30	o/Ml:ˊˊ	I
    //   24: iload_2
    //   25: iconst_2
    //   26: irem
    //   27: ifne +6 -> 33
    //   30: goto +45 -> 75
    //   33: goto +588 -> 621
    //   36: getstatic 28	o/Ml:ˉ	I
    //   39: bipush 113
    //   41: iadd
    //   42: istore_2
    //   43: iload_2
    //   44: sipush 128
    //   47: irem
    //   48: putstatic 30	o/Ml:ˊˊ	I
    //   51: iload_2
    //   52: iconst_2
    //   53: irem
    //   54: ifne +6 -> 60
    //   57: goto +74 -> 131
    //   60: goto +119 -> 179
    //   63: bipush 27
    //   65: istore_2
    //   66: goto +33 -> 99
    //   69: goto +68 -> 137
    //   72: goto -63 -> 9
    //   75: aload_0
    //   76: getfield 79	o/Ml:ˈ	Lo/HQ;
    //   79: astore_3
    //   80: aconst_null
    //   81: arraylength
    //   82: istore_2
    //   83: aload_3
    //   84: ifnull +6 -> 90
    //   87: goto -24 -> 63
    //   90: goto +547 -> 637
    //   93: bipush 58
    //   95: istore_2
    //   96: goto +54 -> 150
    //   99: iload_2
    //   100: lookupswitch	default:+28->128, 10:+37->137, 27:+339->439
    //   128: goto +311 -> 439
    //   131: goto +48 -> 179
    //   134: astore_3
    //   135: aload_3
    //   136: athrow
    //   137: aload_0
    //   138: getfield 81	o/Ml:ʿ	Lo/FP;
    //   141: astore_3
    //   142: aload_3
    //   143: ifnonnull +6 -> 149
    //   146: goto -110 -> 36
    //   149: return
    //   150: iload_2
    //   151: lookupswitch	default:+25->176, 58:+-14->137, 83:+288->439
    //   176: goto -39 -> 137
    //   179: goto +20 -> 199
    //   182: astore_3
    //   183: aload_3
    //   184: invokevirtual 87	java/lang/Throwable:getCause	()Ljava/lang/Throwable;
    //   187: astore 4
    //   189: aload 4
    //   191: ifnull +6 -> 197
    //   194: aload 4
    //   196: athrow
    //   197: aload_3
    //   198: athrow
    //   199: aload_0
    //   200: invokevirtual 93	android/content/Context:getPackageName	()Ljava/lang/String;
    //   203: bipush 7
    //   205: invokevirtual 99	java/lang/String:codePointAt	(I)I
    //   208: bipush 42
    //   210: isub
    //   211: aload_0
    //   212: invokevirtual 93	android/content/Context:getPackageName	()Ljava/lang/String;
    //   215: iconst_5
    //   216: invokevirtual 99	java/lang/String:codePointAt	(I)I
    //   219: bipush 46
    //   221: iadd
    //   222: aload_0
    //   223: invokevirtual 103	android/content/Context:getApplicationInfo	()Landroid/content/pm/ApplicationInfo;
    //   226: getfield 108	android/content/pm/ApplicationInfo:targetSdkVersion	I
    //   229: bipush 25
    //   231: isub
    //   232: i2c
    //   233: invokestatic 114	o/O:ˋ	(IIC)Ljava/lang/Object;
    //   236: checkcast 116	java/lang/Class
    //   239: ldc 118
    //   241: aconst_null
    //   242: invokevirtual 122	java/lang/Class:getMethod	(Ljava/lang/String;[Ljava/lang/Class;)Ljava/lang/reflect/Method;
    //   245: aconst_null
    //   246: aconst_null
    //   247: invokevirtual 128	java/lang/reflect/Method:invoke	(Ljava/lang/Object;[Ljava/lang/Object;)Ljava/lang/Object;
    //   250: checkcast 130	o/Fb
    //   253: astore_3
    //   254: aload_3
    //   255: invokevirtual 133	o/Fb:ˎ	()Lro/btrl/business/general/dao/P2PSettingsDao;
    //   258: invokevirtual 139	ro/btrl/business/general/dao/P2PSettingsDao:ᐝ	()Lo/Ah;
    //   261: astore_3
    //   262: getstatic 145	ro/btrl/business/general/dao/P2PSettingsDao$Properties:Identifier	Lo/zJ;
    //   265: astore 4
    //   267: aload_0
    //   268: invokevirtual 149	android/content/Context:getResources	()Landroid/content/res/Resources;
    //   271: ldc -106
    //   273: invokevirtual 156	android/content/res/Resources:getString	(I)Ljava/lang/String;
    //   276: iconst_0
    //   277: bipush 7
    //   279: invokevirtual 160	java/lang/String:substring	(II)Ljava/lang/String;
    //   282: iconst_5
    //   283: invokevirtual 99	java/lang/String:codePointAt	(I)I
    //   286: istore_2
    //   287: aload_0
    //   288: invokevirtual 149	android/content/Context:getResources	()Landroid/content/res/Resources;
    //   291: ldc -95
    //   293: invokevirtual 156	android/content/res/Resources:getString	(I)Ljava/lang/String;
    //   296: iconst_0
    //   297: iconst_5
    //   298: invokevirtual 160	java/lang/String:substring	(II)Ljava/lang/String;
    //   301: invokevirtual 165	java/lang/String:length	()I
    //   304: bipush 13
    //   306: iadd
    //   307: i2b
    //   308: istore_1
    //   309: aload_0
    //   310: aload_3
    //   311: aload 4
    //   313: bipush 16
    //   315: newarray char
    //   317: dup
    //   318: iconst_0
    //   319: ldc -90
    //   321: castore
    //   322: dup
    //   323: iconst_1
    //   324: ldc -89
    //   326: castore
    //   327: dup
    //   328: iconst_2
    //   329: ldc -88
    //   331: castore
    //   332: dup
    //   333: iconst_3
    //   334: ldc -87
    //   336: castore
    //   337: dup
    //   338: iconst_4
    //   339: ldc -86
    //   341: castore
    //   342: dup
    //   343: iconst_5
    //   344: ldc -88
    //   346: castore
    //   347: dup
    //   348: bipush 6
    //   350: ldc -88
    //   352: castore
    //   353: dup
    //   354: bipush 7
    //   356: ldc -85
    //   358: castore
    //   359: dup
    //   360: bipush 8
    //   362: ldc -84
    //   364: castore
    //   365: dup
    //   366: bipush 9
    //   368: ldc -89
    //   370: castore
    //   371: dup
    //   372: bipush 10
    //   374: ldc 56
    //   376: castore
    //   377: dup
    //   378: bipush 11
    //   380: ldc 56
    //   382: castore
    //   383: dup
    //   384: bipush 12
    //   386: ldc -83
    //   388: castore
    //   389: dup
    //   390: bipush 13
    //   392: ldc -82
    //   394: castore
    //   395: dup
    //   396: bipush 14
    //   398: ldc -81
    //   400: castore
    //   401: dup
    //   402: bipush 15
    //   404: ldc -80
    //   406: castore
    //   407: iload_2
    //   408: sipush 147
    //   411: isub
    //   412: iload_1
    //   413: invokestatic 180	o/Ml:ˊ	([CIB)Ljava/lang/String;
    //   416: invokevirtual 183	java/lang/String:intern	()Ljava/lang/String;
    //   419: invokevirtual 188	o/zJ:ˊ	(Ljava/lang/Object;)Lo/Af;
    //   422: iconst_0
    //   423: anewarray 190	o/Af
    //   426: invokevirtual 196	o/Ah:ˏ	(Lo/Af;[Lo/Af;)Lo/Ah;
    //   429: invokevirtual 199	o/Ah:ˋ	()Ljava/lang/Object;
    //   432: checkcast 201	o/FP
    //   435: putfield 81	o/Ml:ʿ	Lo/FP;
    //   438: return
    //   439: getstatic 30	o/Ml:ˊˊ	I
    //   442: bipush 23
    //   444: iadd
    //   445: istore_2
    //   446: iload_2
    //   447: sipush 128
    //   450: irem
    //   451: putstatic 28	o/Ml:ˉ	I
    //   454: iload_2
    //   455: iconst_2
    //   456: irem
    //   457: ifeq +6 -> 463
    //   460: goto +174 -> 634
    //   463: goto +20 -> 483
    //   466: astore_3
    //   467: aload_3
    //   468: invokevirtual 87	java/lang/Throwable:getCause	()Ljava/lang/Throwable;
    //   471: astore 4
    //   473: aload 4
    //   475: ifnull +6 -> 481
    //   478: aload 4
    //   480: athrow
    //   481: aload_3
    //   482: athrow
    //   483: aload_0
    //   484: invokevirtual 93	android/content/Context:getPackageName	()Ljava/lang/String;
    //   487: invokevirtual 165	java/lang/String:length	()I
    //   490: bipush 7
    //   492: isub
    //   493: aload_0
    //   494: invokevirtual 149	android/content/Context:getResources	()Landroid/content/res/Resources;
    //   497: ldc -54
    //   499: invokevirtual 156	android/content/res/Resources:getString	(I)Ljava/lang/String;
    //   502: bipush 58
    //   504: bipush 64
    //   506: invokevirtual 160	java/lang/String:substring	(II)Ljava/lang/String;
    //   509: invokevirtual 165	java/lang/String:length	()I
    //   512: sipush 154
    //   515: iadd
    //   516: aload_0
    //   517: invokevirtual 149	android/content/Context:getResources	()Landroid/content/res/Resources;
    //   520: ldc -53
    //   522: invokevirtual 156	android/content/res/Resources:getString	(I)Ljava/lang/String;
    //   525: iconst_0
    //   526: iconst_5
    //   527: invokevirtual 160	java/lang/String:substring	(II)Ljava/lang/String;
    //   530: iconst_1
    //   531: invokevirtual 99	java/lang/String:codePointAt	(I)I
    //   534: bipush 26
    //   536: isub
    //   537: i2c
    //   538: invokestatic 114	o/O:ˋ	(IIC)Ljava/lang/Object;
    //   541: checkcast 116	java/lang/Class
    //   544: ldc 118
    //   546: aconst_null
    //   547: invokevirtual 122	java/lang/Class:getMethod	(Ljava/lang/String;[Ljava/lang/Class;)Ljava/lang/reflect/Method;
    //   550: aconst_null
    //   551: aconst_null
    //   552: invokevirtual 128	java/lang/reflect/Method:invoke	(Ljava/lang/Object;[Ljava/lang/Object;)Ljava/lang/Object;
    //   555: checkcast 130	o/Fb
    //   558: astore_3
    //   559: aload_0
    //   560: aload_3
    //   561: invokevirtual 133	o/Fb:ˎ	()Lro/btrl/business/general/dao/P2PSettingsDao;
    //   564: invokevirtual 139	ro/btrl/business/general/dao/P2PSettingsDao:ᐝ	()Lo/Ah;
    //   567: getstatic 206	ro/btrl/business/general/dao/P2PSettingsDao$Properties:Scheme	Lo/zJ;
    //   570: aload_0
    //   571: getfield 79	o/Ml:ˈ	Lo/HQ;
    //   574: invokevirtual 212	o/HQ:ˏॱ	()Lo/Eh;
    //   577: invokevirtual 216	o/Eh:ˏ	()Ljava/lang/String;
    //   580: invokevirtual 188	o/zJ:ˊ	(Ljava/lang/Object;)Lo/Af;
    //   583: iconst_1
    //   584: anewarray 190	o/Af
    //   587: dup
    //   588: iconst_0
    //   589: getstatic 219	ro/btrl/business/general/dao/P2PSettingsDao$Properties:Currency	Lo/zJ;
    //   592: aload_0
    //   593: getfield 79	o/Ml:ˈ	Lo/HQ;
    //   596: invokevirtual 223	o/HQ:ʻ	()Lo/Ep;
    //   599: invokevirtual 227	o/Ep:ˊ	()Ljava/lang/String;
    //   602: invokevirtual 188	o/zJ:ˊ	(Ljava/lang/Object;)Lo/Af;
    //   605: aastore
    //   606: invokevirtual 196	o/Ah:ˏ	(Lo/Af;[Lo/Af;)Lo/Ah;
    //   609: invokevirtual 199	o/Ah:ˋ	()Ljava/lang/Object;
    //   612: checkcast 201	o/FP
    //   615: putfield 81	o/Ml:ʿ	Lo/FP;
    //   618: goto -549 -> 69
    //   621: aload_0
    //   622: getfield 79	o/Ml:ˈ	Lo/HQ;
    //   625: ifnull +6 -> 631
    //   628: goto -625 -> 3
    //   631: goto -538 -> 93
    //   634: goto -171 -> 463
    //   637: bipush 10
    //   639: istore_2
    //   640: goto -541 -> 99
    // Local variable table:
    //   start	length	slot	name	signature
    //   0	643	0	this	Ml
    //   308	105	1	b	byte
    //   5	635	2	i	int
    //   79	5	3	localHQ	HQ
    //   134	2	3	localException	Exception
    //   141	2	3	localFP	FP
    //   182	16	3	localObject1	Object
    //   253	58	3	localObject2	Object
    //   466	16	3	localObject3	Object
    //   558	3	3	localFb	Fb
    //   187	292	4	localObject4	Object
    // Exception table:
    //   from	to	target	type
    //   137	142	134	java/lang/Exception
    //   199	254	182	finally
    //   483	559	466	finally
  }
  
  private void ʾ()
  {
    break label50;
    try
    {
      int i = ˉ + 121;
      try
      {
        ˊˊ = i % 128;
        if (i % 2 != 0) {
          return;
        }
        return;
      }
      catch (Exception localException1)
      {
        throw localException1;
      }
      xe.ˎ(this, new xd()
      {
        public void ˋ(boolean paramAnonymousBoolean)
        {
          ((Mz)Ml.ˊ(Ml.this)).ˎ(paramAnonymousBoolean);
          if (paramAnonymousBoolean) {
            ((Mz)Ml.ˎ(Ml.this)).ᐝ.postDelayed(new Runnable()
            {
              public void run()
              {
                ((Mz)Ml.ˋ(Ml.this)).ᐝ.smoothScrollBy(0, 100);
              }
            }, 100L);
          }
        }
      });
    }
    catch (Exception localException2)
    {
      throw localException2;
    }
    label50:
    for (;;)
    {
      break;
    }
  }
  
  private static String ˊ(char[] paramArrayOfChar, int paramInt, byte paramByte)
  {
    break label545;
    int k;
    int j = oO.ˊ(m, k);
    byte b3;
    int m = oO.ˊ(b3, k);
    byte b2;
    j = oO.ˏ(b2, j, k);
    byte b1 = oO.ˏ(b1, m, k);
    char[] arrayOfChar2;
    int i;
    char[] arrayOfChar1;
    arrayOfChar2[i] = arrayOfChar1[j];
    arrayOfChar2[(i + 1)] = arrayOfChar1[b1];
    break label346;
    label66:
    return new String(arrayOfChar2);
    try
    {
      label76:
      j = oO.ˊ(b2, k);
      b1 = oO.ˊ(b1, k);
      j = oO.ˏ(j, m, k);
      b1 = oO.ˏ(b1, b3, k);
      arrayOfChar2[i] = arrayOfChar1[j];
      arrayOfChar2[(i + 1)] = arrayOfChar1[b1];
    }
    catch (Exception paramArrayOfChar)
    {
      throw paramArrayOfChar;
    }
    break label346;
    for (;;)
    {
      j = 83;
      break label160;
      label149:
      j = 73;
      break label313;
      label160:
      label288:
      do
      {
        j = 23;
        switch (j)
        {
        default: 
          break;
          j = ˊˊ;
          j += 121;
        case 83: 
          try
          {
            ˉ = j % 128;
            if (j % 2 == 0) {
              break label76;
            }
          }
          catch (Exception paramArrayOfChar)
          {
            throw paramArrayOfChar;
          }
          if (paramInt > 1) {
            break label540;
          }
          break label66;
          b2 = oO.ॱ(b1, k);
          m = oO.ˋ(b1, k);
          b1 = oO.ॱ(b3, k);
          b3 = oO.ˋ(b3, k);
          if (m == b3) {
            break label548;
          }
          break label353;
          b1 = paramArrayOfChar[i];
          b3 = paramArrayOfChar[(i + 1)];
        }
      } while (b1 == b3);
    }
    switch (j)
    {
    case 76: 
    default: 
      label313:
      break;
    }
    for (;;)
    {
      label346:
      i += 2;
      break label529;
      label353:
      j = 0;
      break label437;
      continue;
      j = oO.ˏ(b2, b3, k);
      b1 = oO.ˏ(b1, m, k);
      arrayOfChar2[i] = arrayOfChar1[j];
      arrayOfChar2[(i + 1)] = arrayOfChar1[b1];
      break;
      label407:
      j = 76;
      break label313;
      label414:
      arrayOfChar2[i] = ((char)(b1 >> paramByte));
      arrayOfChar2[(i + 0)] = ((char)(b3 + paramByte));
    }
    for (;;)
    {
      switch (j)
      {
      case 1: 
      default: 
        label437:
        break;
      }
      if (b2 == b1) {
        break label407;
      }
      break label149;
      for (;;)
      {
        break;
        j = ˊˊ + 23;
        ˉ = j % 128;
        if (j % 2 != 0) {
          break label414;
        }
        break label584;
        label512:
        paramInt -= 1;
        arrayOfChar2[paramInt] = ((char)(paramArrayOfChar[paramInt] - paramByte));
      }
      for (;;)
      {
        label529:
        if (i < paramInt) {
          break label543;
        }
        break;
        label540:
        i = 0;
      }
      label543:
      break label288;
      label545:
      break label607;
      label548:
      j = 1;
    }
    for (;;)
    {
      label554:
      arrayOfChar1 = ʽॱ;
      k = ˊᐝ;
      arrayOfChar2 = new char[paramInt];
      if (paramInt % 2 != 0) {
        break label512;
      }
      break;
      label584:
      label607:
      do
      {
        break label554;
        arrayOfChar2[i] = ((char)(b1 - paramByte));
        arrayOfChar2[(i + 1)] = ((char)(b3 - paramByte));
        break;
        i = ˊˊ + 119;
        ˉ = i % 128;
      } while (i % 2 != 0);
    }
  }
  
  /* Error */
  private void ˋˊ()
  {
    // Byte code:
    //   0: goto +748 -> 748
    //   3: aload_0
    //   4: getfield 262	o/Ml:ʾ	Lo/Is;
    //   7: aload_0
    //   8: getfield 240	o/Ml:ॱˊ	Landroid/databinding/ViewDataBinding;
    //   11: checkcast 264	o/Mz
    //   14: getfield 267	o/Mz:ॱ	Lo/Ja;
    //   17: invokevirtual 270	o/Ja:ˏ	()Ljava/lang/String;
    //   20: putfield 276	o/Is:amount	Ljava/lang/String;
    //   23: goto +20 -> 43
    //   26: astore 4
    //   28: aload 4
    //   30: invokevirtual 87	java/lang/Throwable:getCause	()Ljava/lang/Throwable;
    //   33: astore_3
    //   34: aload_3
    //   35: ifnull +5 -> 40
    //   38: aload_3
    //   39: athrow
    //   40: aload 4
    //   42: athrow
    //   43: aload_0
    //   44: invokevirtual 149	android/content/Context:getResources	()Landroid/content/res/Resources;
    //   47: ldc_w 277
    //   50: invokevirtual 156	android/content/res/Resources:getString	(I)Ljava/lang/String;
    //   53: iconst_0
    //   54: bipush 20
    //   56: invokevirtual 160	java/lang/String:substring	(II)Ljava/lang/String;
    //   59: bipush 11
    //   61: invokevirtual 99	java/lang/String:codePointAt	(I)I
    //   64: sipush 178
    //   67: isub
    //   68: aload_0
    //   69: invokevirtual 103	android/content/Context:getApplicationInfo	()Landroid/content/pm/ApplicationInfo;
    //   72: getfield 108	android/content/pm/ApplicationInfo:targetSdkVersion	I
    //   75: iconst_1
    //   76: isub
    //   77: aload_0
    //   78: invokevirtual 149	android/content/Context:getResources	()Landroid/content/res/Resources;
    //   81: ldc_w 278
    //   84: invokevirtual 156	android/content/res/Resources:getString	(I)Ljava/lang/String;
    //   87: iconst_0
    //   88: iconst_4
    //   89: invokevirtual 160	java/lang/String:substring	(II)Ljava/lang/String;
    //   92: invokevirtual 165	java/lang/String:length	()I
    //   95: iconst_4
    //   96: isub
    //   97: i2c
    //   98: invokestatic 114	o/O:ˋ	(IIC)Ljava/lang/Object;
    //   101: checkcast 116	java/lang/Class
    //   104: ldc 118
    //   106: aconst_null
    //   107: invokevirtual 122	java/lang/Class:getMethod	(Ljava/lang/String;[Ljava/lang/Class;)Ljava/lang/reflect/Method;
    //   110: aconst_null
    //   111: aconst_null
    //   112: invokevirtual 128	java/lang/reflect/Method:invoke	(Ljava/lang/Object;[Ljava/lang/Object;)Ljava/lang/Object;
    //   115: astore_3
    //   116: goto +20 -> 136
    //   119: astore_3
    //   120: aload_3
    //   121: invokevirtual 87	java/lang/Throwable:getCause	()Ljava/lang/Throwable;
    //   124: astore 4
    //   126: aload 4
    //   128: ifnull +6 -> 134
    //   131: aload 4
    //   133: athrow
    //   134: aload_3
    //   135: athrow
    //   136: aload_0
    //   137: invokevirtual 149	android/content/Context:getResources	()Landroid/content/res/Resources;
    //   140: ldc_w 279
    //   143: invokevirtual 156	android/content/res/Resources:getString	(I)Ljava/lang/String;
    //   146: iconst_0
    //   147: bipush 9
    //   149: invokevirtual 160	java/lang/String:substring	(II)Ljava/lang/String;
    //   152: bipush 7
    //   154: invokevirtual 99	java/lang/String:codePointAt	(I)I
    //   157: sipush 246
    //   160: isub
    //   161: aload_0
    //   162: invokevirtual 149	android/content/Context:getResources	()Landroid/content/res/Resources;
    //   165: ldc_w 280
    //   168: invokevirtual 156	android/content/res/Resources:getString	(I)Ljava/lang/String;
    //   171: iconst_0
    //   172: bipush 15
    //   174: invokevirtual 160	java/lang/String:substring	(II)Ljava/lang/String;
    //   177: invokevirtual 165	java/lang/String:length	()I
    //   180: bipush 9
    //   182: iadd
    //   183: aload_0
    //   184: invokevirtual 103	android/content/Context:getApplicationInfo	()Landroid/content/pm/ApplicationInfo;
    //   187: getfield 108	android/content/pm/ApplicationInfo:targetSdkVersion	I
    //   190: bipush 25
    //   192: isub
    //   193: i2c
    //   194: invokestatic 114	o/O:ˋ	(IIC)Ljava/lang/Object;
    //   197: checkcast 116	java/lang/Class
    //   200: ldc_w 281
    //   203: iconst_1
    //   204: anewarray 116	java/lang/Class
    //   207: dup
    //   208: iconst_0
    //   209: ldc 89
    //   211: aastore
    //   212: invokevirtual 122	java/lang/Class:getMethod	(Ljava/lang/String;[Ljava/lang/Class;)Ljava/lang/reflect/Method;
    //   215: aload_3
    //   216: iconst_1
    //   217: anewarray 283	java/lang/Object
    //   220: dup
    //   221: iconst_0
    //   222: aload_0
    //   223: aastore
    //   224: invokevirtual 128	java/lang/reflect/Method:invoke	(Ljava/lang/Object;[Ljava/lang/Object;)Ljava/lang/Object;
    //   227: checkcast 285	java/lang/Boolean
    //   230: invokevirtual 289	java/lang/Boolean:booleanValue	()Z
    //   233: pop
    //   234: new 258	java/lang/NullPointerException
    //   237: dup
    //   238: invokespecial 259	java/lang/NullPointerException:<init>	()V
    //   241: athrow
    //   242: return
    //   243: astore_3
    //   244: aload_3
    //   245: athrow
    //   246: goto +499 -> 745
    //   249: getstatic 28	o/Ml:ˉ	I
    //   252: bipush 85
    //   254: iadd
    //   255: istore_1
    //   256: iload_1
    //   257: sipush 128
    //   260: irem
    //   261: putstatic 30	o/Ml:ˊˊ	I
    //   264: iload_1
    //   265: iconst_2
    //   266: irem
    //   267: ifne +6 -> 273
    //   270: goto -24 -> 246
    //   273: goto +472 -> 745
    //   276: iconst_1
    //   277: istore_1
    //   278: goto +123 -> 401
    //   281: iload_1
    //   282: tableswitch	default:+22->304, 0:+80->362, 1:+102->384
    //   304: goto +58 -> 362
    //   307: getstatic 30	o/Ml:ˊˊ	I
    //   310: bipush 21
    //   312: iadd
    //   313: istore_1
    //   314: iload_1
    //   315: sipush 128
    //   318: irem
    //   319: putstatic 28	o/Ml:ˉ	I
    //   322: iload_1
    //   323: iconst_2
    //   324: irem
    //   325: ifeq +6 -> 331
    //   328: goto +352 -> 680
    //   331: goto +26 -> 357
    //   334: aload_0
    //   335: invokestatic 294	o/Ic:ˏ	(Landroid/content/Context;)Lo/Ic;
    //   338: astore_3
    //   339: aload_0
    //   340: getfield 262	o/Ml:ʾ	Lo/Is;
    //   343: astore 4
    //   345: aload_3
    //   346: aload 4
    //   348: invokevirtual 297	o/Ic:ˊ	(Lo/Is;)Lo/j;
    //   351: invokevirtual 301	o/j:ˎ	()V
    //   354: goto -105 -> 249
    //   357: iconst_1
    //   358: istore_1
    //   359: goto -78 -> 281
    //   362: aload_0
    //   363: invokestatic 294	o/Ic:ˏ	(Landroid/content/Context;)Lo/Ic;
    //   366: aload_0
    //   367: getfield 262	o/Ml:ʾ	Lo/Is;
    //   370: invokevirtual 303	o/Ic:ˎ	(Lo/Is;)Lo/j;
    //   373: invokevirtual 301	o/j:ˎ	()V
    //   376: bipush 94
    //   378: iconst_0
    //   379: idiv
    //   380: istore_1
    //   381: goto +17 -> 398
    //   384: aload_0
    //   385: invokestatic 294	o/Ic:ˏ	(Landroid/content/Context;)Lo/Ic;
    //   388: aload_0
    //   389: getfield 262	o/Ml:ʾ	Lo/Is;
    //   392: invokevirtual 303	o/Ic:ˎ	(Lo/Is;)Lo/j;
    //   395: invokevirtual 301	o/j:ˎ	()V
    //   398: goto +287 -> 685
    //   401: iload_1
    //   402: tableswitch	default:+22->424, 0:+-160->242, 1:+310->712
    //   424: goto +288 -> 712
    //   427: iconst_0
    //   428: istore_1
    //   429: goto -28 -> 401
    //   432: getstatic 30	o/Ml:ˊˊ	I
    //   435: bipush 85
    //   437: iadd
    //   438: istore_1
    //   439: iload_1
    //   440: sipush 128
    //   443: irem
    //   444: putstatic 28	o/Ml:ˉ	I
    //   447: iload_1
    //   448: iconst_2
    //   449: irem
    //   450: ifeq +6 -> 456
    //   453: goto -450 -> 3
    //   456: aload_0
    //   457: getfield 262	o/Ml:ʾ	Lo/Is;
    //   460: aload_0
    //   461: getfield 240	o/Ml:ॱˊ	Landroid/databinding/ViewDataBinding;
    //   464: checkcast 264	o/Mz
    //   467: getfield 267	o/Mz:ॱ	Lo/Ja;
    //   470: invokevirtual 270	o/Ja:ˏ	()Ljava/lang/String;
    //   473: putfield 276	o/Is:amount	Ljava/lang/String;
    //   476: goto +20 -> 496
    //   479: astore_3
    //   480: aload_3
    //   481: invokevirtual 87	java/lang/Throwable:getCause	()Ljava/lang/Throwable;
    //   484: astore 4
    //   486: aload 4
    //   488: ifnull +6 -> 494
    //   491: aload 4
    //   493: athrow
    //   494: aload_3
    //   495: athrow
    //   496: aload_0
    //   497: invokevirtual 93	android/content/Context:getPackageName	()Ljava/lang/String;
    //   500: invokevirtual 165	java/lang/String:length	()I
    //   503: bipush 8
    //   505: isub
    //   506: aload_0
    //   507: invokevirtual 93	android/content/Context:getPackageName	()Ljava/lang/String;
    //   510: invokevirtual 165	java/lang/String:length	()I
    //   513: bipush 13
    //   515: iadd
    //   516: aload_0
    //   517: invokevirtual 93	android/content/Context:getPackageName	()Ljava/lang/String;
    //   520: invokevirtual 165	java/lang/String:length	()I
    //   523: bipush 11
    //   525: isub
    //   526: i2c
    //   527: invokestatic 114	o/O:ˋ	(IIC)Ljava/lang/Object;
    //   530: checkcast 116	java/lang/Class
    //   533: ldc 118
    //   535: aconst_null
    //   536: invokevirtual 122	java/lang/Class:getMethod	(Ljava/lang/String;[Ljava/lang/Class;)Ljava/lang/reflect/Method;
    //   539: aconst_null
    //   540: aconst_null
    //   541: invokevirtual 128	java/lang/reflect/Method:invoke	(Ljava/lang/Object;[Ljava/lang/Object;)Ljava/lang/Object;
    //   544: astore_3
    //   545: goto +20 -> 565
    //   548: astore 4
    //   550: aload 4
    //   552: invokevirtual 87	java/lang/Throwable:getCause	()Ljava/lang/Throwable;
    //   555: astore_3
    //   556: aload_3
    //   557: ifnull +5 -> 562
    //   560: aload_3
    //   561: athrow
    //   562: aload 4
    //   564: athrow
    //   565: aload_0
    //   566: invokevirtual 149	android/content/Context:getResources	()Landroid/content/res/Resources;
    //   569: ldc_w 304
    //   572: invokevirtual 156	android/content/res/Resources:getString	(I)Ljava/lang/String;
    //   575: iconst_0
    //   576: iconst_4
    //   577: invokevirtual 160	java/lang/String:substring	(II)Ljava/lang/String;
    //   580: iconst_1
    //   581: invokevirtual 99	java/lang/String:codePointAt	(I)I
    //   584: bipush 23
    //   586: isub
    //   587: aload_0
    //   588: invokevirtual 149	android/content/Context:getResources	()Landroid/content/res/Resources;
    //   591: ldc_w 305
    //   594: invokevirtual 156	android/content/res/Resources:getString	(I)Ljava/lang/String;
    //   597: iconst_0
    //   598: iconst_4
    //   599: invokevirtual 160	java/lang/String:substring	(II)Ljava/lang/String;
    //   602: iconst_3
    //   603: invokevirtual 99	java/lang/String:codePointAt	(I)I
    //   606: bipush 12
    //   608: iadd
    //   609: aload_0
    //   610: invokevirtual 149	android/content/Context:getResources	()Landroid/content/res/Resources;
    //   613: ldc_w 306
    //   616: invokevirtual 156	android/content/res/Resources:getString	(I)Ljava/lang/String;
    //   619: iconst_0
    //   620: iconst_4
    //   621: invokevirtual 160	java/lang/String:substring	(II)Ljava/lang/String;
    //   624: invokevirtual 165	java/lang/String:length	()I
    //   627: iconst_4
    //   628: isub
    //   629: i2c
    //   630: invokestatic 114	o/O:ˋ	(IIC)Ljava/lang/Object;
    //   633: checkcast 116	java/lang/Class
    //   636: ldc_w 281
    //   639: iconst_1
    //   640: anewarray 116	java/lang/Class
    //   643: dup
    //   644: iconst_0
    //   645: ldc 89
    //   647: aastore
    //   648: invokevirtual 122	java/lang/Class:getMethod	(Ljava/lang/String;[Ljava/lang/Class;)Ljava/lang/reflect/Method;
    //   651: aload_3
    //   652: iconst_1
    //   653: anewarray 283	java/lang/Object
    //   656: dup
    //   657: iconst_0
    //   658: aload_0
    //   659: aastore
    //   660: invokevirtual 128	java/lang/reflect/Method:invoke	(Ljava/lang/Object;[Ljava/lang/Object;)Ljava/lang/Object;
    //   663: checkcast 285	java/lang/Boolean
    //   666: invokevirtual 289	java/lang/Boolean:booleanValue	()Z
    //   669: istore_2
    //   670: iload_2
    //   671: ifeq +6 -> 677
    //   674: goto +46 -> 720
    //   677: goto -279 -> 398
    //   680: iconst_0
    //   681: istore_1
    //   682: goto -401 -> 281
    //   685: getstatic 28	o/Ml:ˉ	I
    //   688: bipush 81
    //   690: iadd
    //   691: istore_1
    //   692: iload_1
    //   693: sipush 128
    //   696: irem
    //   697: putstatic 30	o/Ml:ˊˊ	I
    //   700: iload_1
    //   701: iconst_2
    //   702: irem
    //   703: ifne +6 -> 709
    //   706: goto -430 -> 276
    //   709: goto -282 -> 427
    //   712: new 258	java/lang/NullPointerException
    //   715: dup
    //   716: invokespecial 259	java/lang/NullPointerException:<init>	()V
    //   719: athrow
    //   720: aload_0
    //   721: getfield 308	o/Ml:ʼॱ	Lo/FT;
    //   724: astore_3
    //   725: getstatic 313	o/FT:SEND_MONEY	Lo/FT;
    //   728: astore 4
    //   730: aload_3
    //   731: aload 4
    //   733: if_acmpne +6 -> 739
    //   736: goto -429 -> 307
    //   739: goto -405 -> 334
    //   742: astore_3
    //   743: aload_3
    //   744: athrow
    //   745: goto -347 -> 398
    //   748: goto -316 -> 432
    // Local variable table:
    //   start	length	slot	name	signature
    //   0	751	0	this	Ml
    //   255	448	1	i	int
    //   669	2	2	bool	boolean
    //   33	83	3	localObject1	Object
    //   119	97	3	localObject2	Object
    //   243	2	3	localException1	Exception
    //   338	8	3	localIc	Ic
    //   479	16	3	localObject3	Object
    //   544	187	3	localObject4	Object
    //   742	2	3	localException2	Exception
    //   26	15	4	localObject5	Object
    //   124	368	4	localObject6	Object
    //   548	15	4	localObject7	Object
    //   728	4	4	localFT	FT
    // Exception table:
    //   from	to	target	type
    //   43	116	26	finally
    //   136	234	119	finally
    //   339	345	243	java/lang/Exception
    //   345	354	243	java/lang/Exception
    //   496	545	479	finally
    //   565	670	548	finally
    //   334	339	742	java/lang/Exception
    //   720	725	742	java/lang/Exception
    //   725	730	742	java/lang/Exception
  }
  
  /* Error */
  private void ˎ(android.content.Intent paramIntent)
  {
    // Byte code:
    //   0: goto +351 -> 351
    //   3: getstatic 30	o/Ml:ˊˊ	I
    //   6: bipush 39
    //   8: iadd
    //   9: istore_3
    //   10: iload_3
    //   11: sipush 128
    //   14: irem
    //   15: putstatic 28	o/Ml:ˉ	I
    //   18: iload_3
    //   19: iconst_2
    //   20: irem
    //   21: ifeq +6 -> 27
    //   24: goto +282 -> 306
    //   27: return
    //   28: aload_0
    //   29: invokevirtual 149	android/content/Context:getResources	()Landroid/content/res/Resources;
    //   32: ldc_w 315
    //   35: invokevirtual 156	android/content/res/Resources:getString	(I)Ljava/lang/String;
    //   38: iconst_0
    //   39: iconst_4
    //   40: invokevirtual 160	java/lang/String:substring	(II)Ljava/lang/String;
    //   43: iconst_2
    //   44: invokevirtual 99	java/lang/String:codePointAt	(I)I
    //   47: istore_3
    //   48: aload_0
    //   49: invokevirtual 93	android/content/Context:getPackageName	()Ljava/lang/String;
    //   52: invokevirtual 165	java/lang/String:length	()I
    //   55: bipush 16
    //   57: iadd
    //   58: i2b
    //   59: istore_2
    //   60: aload_0
    //   61: aload_1
    //   62: bipush 33
    //   64: newarray char
    //   66: dup
    //   67: iconst_0
    //   68: ldc_w 316
    //   71: castore
    //   72: dup
    //   73: iconst_1
    //   74: ldc -87
    //   76: castore
    //   77: dup
    //   78: iconst_2
    //   79: ldc -85
    //   81: castore
    //   82: dup
    //   83: iconst_3
    //   84: ldc_w 317
    //   87: castore
    //   88: dup
    //   89: iconst_4
    //   90: ldc_w 318
    //   93: castore
    //   94: dup
    //   95: iconst_5
    //   96: ldc_w 319
    //   99: castore
    //   100: dup
    //   101: bipush 6
    //   103: ldc_w 320
    //   106: castore
    //   107: dup
    //   108: bipush 7
    //   110: ldc_w 321
    //   113: castore
    //   114: dup
    //   115: bipush 8
    //   117: ldc_w 322
    //   120: castore
    //   121: dup
    //   122: bipush 9
    //   124: ldc -87
    //   126: castore
    //   127: dup
    //   128: bipush 10
    //   130: ldc_w 323
    //   133: castore
    //   134: dup
    //   135: bipush 11
    //   137: ldc_w 319
    //   140: castore
    //   141: dup
    //   142: bipush 12
    //   144: ldc -85
    //   146: castore
    //   147: dup
    //   148: bipush 13
    //   150: ldc_w 317
    //   153: castore
    //   154: dup
    //   155: bipush 14
    //   157: ldc -87
    //   159: castore
    //   160: dup
    //   161: bipush 15
    //   163: ldc_w 324
    //   166: castore
    //   167: dup
    //   168: bipush 16
    //   170: ldc_w 325
    //   173: castore
    //   174: dup
    //   175: bipush 17
    //   177: ldc_w 326
    //   180: castore
    //   181: dup
    //   182: bipush 18
    //   184: ldc_w 316
    //   187: castore
    //   188: dup
    //   189: bipush 19
    //   191: ldc_w 317
    //   194: castore
    //   195: dup
    //   196: bipush 20
    //   198: ldc_w 316
    //   201: castore
    //   202: dup
    //   203: bipush 21
    //   205: ldc_w 323
    //   208: castore
    //   209: dup
    //   210: bipush 22
    //   212: ldc_w 327
    //   215: castore
    //   216: dup
    //   217: bipush 23
    //   219: ldc_w 316
    //   222: castore
    //   223: dup
    //   224: bipush 24
    //   226: ldc_w 323
    //   229: castore
    //   230: dup
    //   231: bipush 25
    //   233: ldc_w 321
    //   236: castore
    //   237: dup
    //   238: bipush 26
    //   240: ldc_w 328
    //   243: castore
    //   244: dup
    //   245: bipush 27
    //   247: ldc -87
    //   249: castore
    //   250: dup
    //   251: bipush 28
    //   253: ldc -85
    //   255: castore
    //   256: dup
    //   257: bipush 29
    //   259: ldc_w 318
    //   262: castore
    //   263: dup
    //   264: bipush 30
    //   266: ldc -82
    //   268: castore
    //   269: dup
    //   270: bipush 31
    //   272: ldc_w 326
    //   275: castore
    //   276: dup
    //   277: bipush 32
    //   279: ldc_w 329
    //   282: castore
    //   283: iload_3
    //   284: bipush 22
    //   286: iadd
    //   287: iload_2
    //   288: invokestatic 180	o/Ml:ˊ	([CIB)Ljava/lang/String;
    //   291: invokevirtual 183	java/lang/String:intern	()Ljava/lang/String;
    //   294: invokevirtual 335	android/content/Intent:getParcelableExtra	(Ljava/lang/String;)Landroid/os/Parcelable;
    //   297: checkcast 272	o/Is
    //   300: putfield 262	o/Ml:ʾ	Lo/Is;
    //   303: goto +4 -> 307
    //   306: return
    //   307: goto -304 -> 3
    //   310: goto -282 -> 28
    //   313: goto +44 -> 357
    //   316: astore_1
    //   317: aload_1
    //   318: athrow
    //   319: iload_3
    //   320: lookupswitch	default:+28->348, 29:+563->883, 58:+-13->307
    //   348: goto -41 -> 307
    //   351: goto +505 -> 856
    //   354: astore_1
    //   355: aload_1
    //   356: athrow
    //   357: aload_0
    //   358: invokevirtual 149	android/content/Context:getResources	()Landroid/content/res/Resources;
    //   361: astore 5
    //   363: aload 5
    //   365: ldc_w 336
    //   368: invokevirtual 156	android/content/res/Resources:getString	(I)Ljava/lang/String;
    //   371: astore 5
    //   373: aload 5
    //   375: iconst_0
    //   376: iconst_2
    //   377: invokevirtual 160	java/lang/String:substring	(II)Ljava/lang/String;
    //   380: astore 5
    //   382: aload 5
    //   384: invokevirtual 165	java/lang/String:length	()I
    //   387: istore_3
    //   388: aload_0
    //   389: invokevirtual 103	android/content/Context:getApplicationInfo	()Landroid/content/pm/ApplicationInfo;
    //   392: getfield 108	android/content/pm/ApplicationInfo:targetSdkVersion	I
    //   395: bipush 88
    //   397: iadd
    //   398: i2b
    //   399: istore_2
    //   400: aload_0
    //   401: aload_1
    //   402: bipush 23
    //   404: newarray char
    //   406: dup
    //   407: iconst_0
    //   408: ldc_w 316
    //   411: castore
    //   412: dup
    //   413: iconst_1
    //   414: ldc -87
    //   416: castore
    //   417: dup
    //   418: iconst_2
    //   419: ldc -85
    //   421: castore
    //   422: dup
    //   423: iconst_3
    //   424: ldc_w 317
    //   427: castore
    //   428: dup
    //   429: iconst_4
    //   430: ldc_w 318
    //   433: castore
    //   434: dup
    //   435: iconst_5
    //   436: ldc_w 319
    //   439: castore
    //   440: dup
    //   441: bipush 6
    //   443: ldc -85
    //   445: castore
    //   446: dup
    //   447: bipush 7
    //   449: ldc_w 317
    //   452: castore
    //   453: dup
    //   454: bipush 8
    //   456: ldc -87
    //   458: castore
    //   459: dup
    //   460: bipush 9
    //   462: ldc_w 324
    //   465: castore
    //   466: dup
    //   467: bipush 10
    //   469: ldc -86
    //   471: castore
    //   472: dup
    //   473: bipush 11
    //   475: ldc_w 324
    //   478: castore
    //   479: dup
    //   480: bipush 12
    //   482: ldc_w 337
    //   485: castore
    //   486: dup
    //   487: bipush 13
    //   489: ldc_w 319
    //   492: castore
    //   493: dup
    //   494: bipush 14
    //   496: ldc_w 320
    //   499: castore
    //   500: dup
    //   501: bipush 15
    //   503: ldc_w 324
    //   506: castore
    //   507: dup
    //   508: bipush 16
    //   510: ldc_w 321
    //   513: castore
    //   514: dup
    //   515: bipush 17
    //   517: ldc -87
    //   519: castore
    //   520: dup
    //   521: bipush 18
    //   523: ldc_w 321
    //   526: castore
    //   527: dup
    //   528: bipush 19
    //   530: ldc_w 325
    //   533: castore
    //   534: dup
    //   535: bipush 20
    //   537: ldc_w 337
    //   540: castore
    //   541: dup
    //   542: bipush 21
    //   544: ldc_w 324
    //   547: castore
    //   548: dup
    //   549: bipush 22
    //   551: ldc_w 338
    //   554: castore
    //   555: iload_3
    //   556: bipush 21
    //   558: iadd
    //   559: iload_2
    //   560: invokestatic 180	o/Ml:ˊ	([CIB)Ljava/lang/String;
    //   563: invokevirtual 183	java/lang/String:intern	()Ljava/lang/String;
    //   566: invokevirtual 342	android/content/Intent:getSerializableExtra	(Ljava/lang/String;)Ljava/io/Serializable;
    //   569: checkcast 310	o/FT
    //   572: putfield 308	o/Ml:ʼॱ	Lo/FT;
    //   575: aload_0
    //   576: invokevirtual 93	android/content/Context:getPackageName	()Ljava/lang/String;
    //   579: invokevirtual 165	java/lang/String:length	()I
    //   582: istore_3
    //   583: aload_0
    //   584: invokevirtual 149	android/content/Context:getResources	()Landroid/content/res/Resources;
    //   587: ldc_w 343
    //   590: invokevirtual 156	android/content/res/Resources:getString	(I)Ljava/lang/String;
    //   593: iconst_0
    //   594: iconst_4
    //   595: invokevirtual 160	java/lang/String:substring	(II)Ljava/lang/String;
    //   598: iconst_2
    //   599: invokevirtual 99	java/lang/String:codePointAt	(I)I
    //   602: bipush 16
    //   604: iadd
    //   605: i2b
    //   606: istore_2
    //   607: aload_1
    //   608: bipush 33
    //   610: newarray char
    //   612: dup
    //   613: iconst_0
    //   614: ldc_w 316
    //   617: castore
    //   618: dup
    //   619: iconst_1
    //   620: ldc -87
    //   622: castore
    //   623: dup
    //   624: iconst_2
    //   625: ldc -85
    //   627: castore
    //   628: dup
    //   629: iconst_3
    //   630: ldc_w 317
    //   633: castore
    //   634: dup
    //   635: iconst_4
    //   636: ldc_w 318
    //   639: castore
    //   640: dup
    //   641: iconst_5
    //   642: ldc_w 319
    //   645: castore
    //   646: dup
    //   647: bipush 6
    //   649: ldc_w 320
    //   652: castore
    //   653: dup
    //   654: bipush 7
    //   656: ldc_w 321
    //   659: castore
    //   660: dup
    //   661: bipush 8
    //   663: ldc_w 322
    //   666: castore
    //   667: dup
    //   668: bipush 9
    //   670: ldc -87
    //   672: castore
    //   673: dup
    //   674: bipush 10
    //   676: ldc_w 323
    //   679: castore
    //   680: dup
    //   681: bipush 11
    //   683: ldc_w 319
    //   686: castore
    //   687: dup
    //   688: bipush 12
    //   690: ldc -85
    //   692: castore
    //   693: dup
    //   694: bipush 13
    //   696: ldc_w 317
    //   699: castore
    //   700: dup
    //   701: bipush 14
    //   703: ldc -87
    //   705: castore
    //   706: dup
    //   707: bipush 15
    //   709: ldc_w 324
    //   712: castore
    //   713: dup
    //   714: bipush 16
    //   716: ldc_w 325
    //   719: castore
    //   720: dup
    //   721: bipush 17
    //   723: ldc_w 326
    //   726: castore
    //   727: dup
    //   728: bipush 18
    //   730: ldc_w 316
    //   733: castore
    //   734: dup
    //   735: bipush 19
    //   737: ldc_w 317
    //   740: castore
    //   741: dup
    //   742: bipush 20
    //   744: ldc_w 316
    //   747: castore
    //   748: dup
    //   749: bipush 21
    //   751: ldc_w 323
    //   754: castore
    //   755: dup
    //   756: bipush 22
    //   758: ldc_w 327
    //   761: castore
    //   762: dup
    //   763: bipush 23
    //   765: ldc_w 316
    //   768: castore
    //   769: dup
    //   770: bipush 24
    //   772: ldc_w 323
    //   775: castore
    //   776: dup
    //   777: bipush 25
    //   779: ldc_w 321
    //   782: castore
    //   783: dup
    //   784: bipush 26
    //   786: ldc_w 328
    //   789: castore
    //   790: dup
    //   791: bipush 27
    //   793: ldc -87
    //   795: castore
    //   796: dup
    //   797: bipush 28
    //   799: ldc -85
    //   801: castore
    //   802: dup
    //   803: bipush 29
    //   805: ldc_w 318
    //   808: castore
    //   809: dup
    //   810: bipush 30
    //   812: ldc -82
    //   814: castore
    //   815: dup
    //   816: bipush 31
    //   818: ldc_w 326
    //   821: castore
    //   822: dup
    //   823: bipush 32
    //   825: ldc_w 329
    //   828: castore
    //   829: iload_3
    //   830: bipush 22
    //   832: iadd
    //   833: iload_2
    //   834: invokestatic 180	o/Ml:ˊ	([CIB)Ljava/lang/String;
    //   837: invokevirtual 183	java/lang/String:intern	()Ljava/lang/String;
    //   840: invokevirtual 347	android/content/Intent:hasExtra	(Ljava/lang/String;)Z
    //   843: istore 4
    //   845: iload 4
    //   847: ifeq +6 -> 853
    //   850: goto +66 -> 916
    //   853: goto +57 -> 910
    //   856: getstatic 28	o/Ml:ˉ	I
    //   859: bipush 103
    //   861: iadd
    //   862: istore_3
    //   863: iload_3
    //   864: sipush 128
    //   867: irem
    //   868: putstatic 30	o/Ml:ˊˊ	I
    //   871: iload_3
    //   872: iconst_2
    //   873: irem
    //   874: ifne +6 -> 880
    //   877: goto -564 -> 313
    //   880: goto -523 -> 357
    //   883: getstatic 30	o/Ml:ˊˊ	I
    //   886: bipush 125
    //   888: iadd
    //   889: istore_3
    //   890: iload_3
    //   891: sipush 128
    //   894: irem
    //   895: putstatic 28	o/Ml:ˉ	I
    //   898: iload_3
    //   899: iconst_2
    //   900: irem
    //   901: ifeq +6 -> 907
    //   904: goto -594 -> 310
    //   907: goto -879 -> 28
    //   910: bipush 58
    //   912: istore_3
    //   913: goto -594 -> 319
    //   916: bipush 29
    //   918: istore_3
    //   919: goto -600 -> 319
    // Local variable table:
    //   start	length	slot	name	signature
    //   0	922	0	this	Ml
    //   0	922	1	paramIntent	android.content.Intent
    //   59	775	2	b	byte
    //   9	910	3	i	int
    //   843	3	4	bool	boolean
    //   361	22	5	localObject	Object
    // Exception table:
    //   from	to	target	type
    //   363	373	316	java/lang/Exception
    //   357	363	354	java/lang/Exception
    //   363	373	354	java/lang/Exception
    //   373	382	354	java/lang/Exception
    //   382	845	354	java/lang/Exception
  }
  
  private void ॱˋ()
  {
    for (;;)
    {
      Object localObject2;
      try
      {
        localFP = this.ʿ;
        localObject2 = localFP.ʻ();
      }
      catch (Exception localException1)
      {
        FP localFP;
        throw localException1;
      }
      ((Mz)this.ॱˊ).ॱ.setValidationRule(new Fq(((BigDecimal)localObject2).floatValue()));
      ((Mz)this.ॱˊ).ॱ.setValidationRule(new Ft(localFP.floatValue()));
      ((Mz)this.ॱˊ).ʼ.ˏ(new Fs(30));
      return;
      label90:
      int i = 57;
      for (;;)
      {
        label96:
        Object localObject1 = this.ʼॱ;
        FT localFT = FT.SEND_MONEY;
        if (localObject1 != localFT)
        {
          break label182;
          label124:
          i = ˉ + 99;
          ˊˊ = i % 128;
          if (i % 2 != 0)
          {
            break label525;
            label151:
            localObject2 = this.ʿ.ʽ();
            break label322;
            localObject1 = this.ʾ;
            i = 82 / 0;
            if (localObject1 == null) {
              break label438;
            }
            break label236;
            label182:
            i = 5;
          }
        }
        for (;;)
        {
          switch (i)
          {
          case 96: 
          default: 
            break label512;
            localObject1 = this.ʿ.ॱॱ();
            break;
            i = 81;
            break;
          case 99: 
            for (;;)
            {
              label187:
              label230:
              label236:
              ((Mz)this.ॱˊ).ॱ(this.ʾ);
              ((Mz)this.ॱˊ).ॱ.requestFocus();
              if (this.ʼॱ == FT.SEND_MONEY) {
                break label230;
              }
              break label90;
              for (;;)
              {
                switch (i)
                {
                case 5: 
                default: 
                  break;
                }
                for (;;)
                {
                  localObject1 = this.ʿ.ॱ();
                  break;
                  label322:
                  i = ˉ + 69;
                  ˊˊ = i % 128;
                  if (i % 2 == 0) {
                    break label96;
                  }
                  try
                  {
                    i = ˊˊ;
                    i += 89;
                    ˉ = i % 128;
                    if (i % 2 != 0) {
                      break label537;
                    }
                  }
                  catch (Exception localException2)
                  {
                    throw localException2;
                  }
                }
                switch (i)
                {
                }
                break label151;
                i = 96;
                break label187;
                label413:
                ((Is)localObject2).currency = ((Ep)localObject1);
                ((Mz)this.ॱˊ).ॱ(true);
                break label236;
                i = 81;
              }
              label438:
              label512:
              do
              {
                this.ʾ = new Is();
                localObject2 = this.ʾ;
                if (this.ˈ != null)
                {
                  localObject1 = this.ˈ.ʻ();
                  break label413;
                  break label124;
                }
                for (;;)
                {
                  break label413;
                  i = ˊˊ + 55;
                  ˉ = i % 128;
                  if (i % 2 != 0) {
                    break;
                  }
                  localObject1 = Ep.UNKNOWN;
                }
              } while (this.ʾ == null);
            }
            label525:
            i = 99;
          }
        }
      }
      label537:
      BigDecimal localBigDecimal = this.ʿ.ॱ();
      i = null.length;
    }
  }
  
  public Resources getResources()
  {
    for (;;)
    {
      int i = ˉ + 69;
      ˊˊ = i % 128;
      if (i % 2 != 0) {
        return localResources;
      }
      return localResources;
      do
      {
        break;
        i = ˊˊ + 35;
        ˉ = i % 128;
      } while (i % 2 != 0);
      Resources localResources = oH.ˊ(super.getResources());
    }
  }
  
  /* Error */
  public void onActivityResult(int paramInt1, int paramInt2, android.content.Intent paramIntent)
  {
    // Byte code:
    //   0: goto +120 -> 120
    //   3: aload_0
    //   4: getfield 262	o/Ml:ʾ	Lo/Is;
    //   7: getfield 419	o/Is:contactPerson	Lo/ـ;
    //   10: invokevirtual 423	o/ـ:ˏ	()Ljava/lang/Object;
    //   13: ifnonnull +6 -> 19
    //   16: goto +60 -> 76
    //   19: goto +52 -> 71
    //   22: getstatic 30	o/Ml:ˊˊ	I
    //   25: bipush 29
    //   27: iadd
    //   28: istore_2
    //   29: iload_2
    //   30: sipush 128
    //   33: irem
    //   34: putstatic 28	o/Ml:ˉ	I
    //   37: iload_2
    //   38: iconst_2
    //   39: irem
    //   40: ifeq +6 -> 46
    //   43: goto +184 -> 227
    //   46: goto +187 -> 233
    //   49: iload_1
    //   50: lookupswitch	default:+18->68, 3:+225->275
    //   68: goto +55 -> 123
    //   71: iconst_0
    //   72: istore_1
    //   73: goto +129 -> 202
    //   76: iconst_1
    //   77: istore_1
    //   78: goto +124 -> 202
    //   81: astore_3
    //   82: aload_3
    //   83: athrow
    //   84: aload_0
    //   85: invokevirtual 426	o/Ml:finish	()V
    //   88: goto +31 -> 119
    //   91: goto +88 -> 179
    //   94: aconst_null
    //   95: arraylength
    //   96: istore_2
    //   97: iload_1
    //   98: lookupswitch	default:+18->116, 3:+177->275
    //   116: goto +7 -> 123
    //   119: return
    //   120: goto +4 -> 124
    //   123: return
    //   124: getstatic 28	o/Ml:ˉ	I
    //   127: bipush 75
    //   129: iadd
    //   130: istore 5
    //   132: iload 5
    //   134: sipush 128
    //   137: irem
    //   138: putstatic 30	o/Ml:ˊˊ	I
    //   141: iload 5
    //   143: iconst_2
    //   144: irem
    //   145: ifne +6 -> 151
    //   148: goto -57 -> 91
    //   151: goto +28 -> 179
    //   154: iload_2
    //   155: tableswitch	default:+21->176, 0:+-133->22, 1:+-152->3
    //   176: goto -173 -> 3
    //   179: aload_0
    //   180: iload_1
    //   181: iload_2
    //   182: aload_3
    //   183: invokespecial 428	o/IB:onActivityResult	(IILandroid/content/Intent;)V
    //   186: iload_2
    //   187: iconst_m1
    //   188: if_icmpne +6 -> 194
    //   191: goto +48 -> 239
    //   194: iconst_1
    //   195: istore_2
    //   196: goto -42 -> 154
    //   199: astore_3
    //   200: aload_3
    //   201: athrow
    //   202: iload_1
    //   203: tableswitch	default:+21->224, 0:+-84->119, 1:+-119->84
    //   224: goto -140 -> 84
    //   227: bipush 16
    //   229: istore_2
    //   230: goto +14 -> 244
    //   233: bipush 62
    //   235: istore_2
    //   236: goto +8 -> 244
    //   239: iconst_0
    //   240: istore_2
    //   241: goto -87 -> 154
    //   244: iload_2
    //   245: lookupswitch	default:+27->272, 16:+-151->94, 62:+-196->49
    //   272: goto -223 -> 49
    //   275: aload_0
    //   276: invokevirtual 103	android/content/Context:getApplicationInfo	()Landroid/content/pm/ApplicationInfo;
    //   279: astore 6
    //   281: aload 6
    //   283: getfield 108	android/content/pm/ApplicationInfo:targetSdkVersion	I
    //   286: istore_1
    //   287: aload_0
    //   288: invokevirtual 93	android/content/Context:getPackageName	()Ljava/lang/String;
    //   291: iconst_1
    //   292: invokevirtual 99	java/lang/String:codePointAt	(I)I
    //   295: bipush 52
    //   297: isub
    //   298: i2b
    //   299: istore 4
    //   301: aload_3
    //   302: bipush 20
    //   304: newarray char
    //   306: dup
    //   307: iconst_0
    //   308: ldc_w 316
    //   311: castore
    //   312: dup
    //   313: iconst_1
    //   314: ldc -87
    //   316: castore
    //   317: dup
    //   318: iconst_2
    //   319: ldc -85
    //   321: castore
    //   322: dup
    //   323: iconst_3
    //   324: ldc_w 317
    //   327: castore
    //   328: dup
    //   329: iconst_4
    //   330: ldc_w 318
    //   333: castore
    //   334: dup
    //   335: iconst_5
    //   336: ldc_w 319
    //   339: castore
    //   340: dup
    //   341: bipush 6
    //   343: ldc_w 325
    //   346: castore
    //   347: dup
    //   348: bipush 7
    //   350: ldc_w 337
    //   353: castore
    //   354: dup
    //   355: bipush 8
    //   357: ldc -89
    //   359: castore
    //   360: dup
    //   361: bipush 9
    //   363: ldc_w 337
    //   366: castore
    //   367: dup
    //   368: bipush 10
    //   370: ldc_w 319
    //   373: castore
    //   374: dup
    //   375: bipush 11
    //   377: ldc_w 324
    //   380: castore
    //   381: dup
    //   382: bipush 12
    //   384: ldc -85
    //   386: castore
    //   387: dup
    //   388: bipush 13
    //   390: ldc_w 319
    //   393: castore
    //   394: dup
    //   395: bipush 14
    //   397: ldc_w 322
    //   400: castore
    //   401: dup
    //   402: bipush 15
    //   404: ldc -85
    //   406: castore
    //   407: dup
    //   408: bipush 16
    //   410: ldc_w 317
    //   413: castore
    //   414: dup
    //   415: bipush 17
    //   417: ldc_w 327
    //   420: castore
    //   421: dup
    //   422: bipush 18
    //   424: ldc_w 337
    //   427: castore
    //   428: dup
    //   429: bipush 19
    //   431: ldc_w 327
    //   434: castore
    //   435: iload_1
    //   436: iconst_5
    //   437: isub
    //   438: iload 4
    //   440: invokestatic 180	o/Ml:ˊ	([CIB)Ljava/lang/String;
    //   443: invokevirtual 183	java/lang/String:intern	()Ljava/lang/String;
    //   446: invokevirtual 335	android/content/Intent:getParcelableExtra	(Ljava/lang/String;)Landroid/os/Parcelable;
    //   449: checkcast 430	o/FS
    //   452: astore 6
    //   454: aload_0
    //   455: invokevirtual 149	android/content/Context:getResources	()Landroid/content/res/Resources;
    //   458: ldc_w 431
    //   461: invokevirtual 156	android/content/res/Resources:getString	(I)Ljava/lang/String;
    //   464: iconst_0
    //   465: iconst_4
    //   466: invokevirtual 160	java/lang/String:substring	(II)Ljava/lang/String;
    //   469: invokevirtual 165	java/lang/String:length	()I
    //   472: istore_1
    //   473: aload_0
    //   474: invokevirtual 149	android/content/Context:getResources	()Landroid/content/res/Resources;
    //   477: ldc_w 432
    //   480: invokevirtual 156	android/content/res/Resources:getString	(I)Ljava/lang/String;
    //   483: iconst_0
    //   484: iconst_4
    //   485: invokevirtual 160	java/lang/String:substring	(II)Ljava/lang/String;
    //   488: invokevirtual 165	java/lang/String:length	()I
    //   491: bipush 78
    //   493: iadd
    //   494: i2b
    //   495: istore 4
    //   497: aload_3
    //   498: bipush 26
    //   500: newarray char
    //   502: dup
    //   503: iconst_0
    //   504: ldc_w 316
    //   507: castore
    //   508: dup
    //   509: iconst_1
    //   510: ldc -87
    //   512: castore
    //   513: dup
    //   514: iconst_2
    //   515: ldc -85
    //   517: castore
    //   518: dup
    //   519: iconst_3
    //   520: ldc_w 317
    //   523: castore
    //   524: dup
    //   525: iconst_4
    //   526: ldc_w 318
    //   529: castore
    //   530: dup
    //   531: iconst_5
    //   532: ldc_w 319
    //   535: castore
    //   536: dup
    //   537: bipush 6
    //   539: ldc_w 325
    //   542: castore
    //   543: dup
    //   544: bipush 7
    //   546: ldc_w 337
    //   549: castore
    //   550: dup
    //   551: bipush 8
    //   553: ldc -89
    //   555: castore
    //   556: dup
    //   557: bipush 9
    //   559: ldc_w 337
    //   562: castore
    //   563: dup
    //   564: bipush 10
    //   566: ldc_w 319
    //   569: castore
    //   570: dup
    //   571: bipush 11
    //   573: ldc_w 324
    //   576: castore
    //   577: dup
    //   578: bipush 12
    //   580: ldc -85
    //   582: castore
    //   583: dup
    //   584: bipush 13
    //   586: ldc_w 319
    //   589: castore
    //   590: dup
    //   591: bipush 14
    //   593: ldc_w 322
    //   596: castore
    //   597: dup
    //   598: bipush 15
    //   600: ldc -85
    //   602: castore
    //   603: dup
    //   604: bipush 16
    //   606: ldc_w 317
    //   609: castore
    //   610: dup
    //   611: bipush 17
    //   613: ldc_w 327
    //   616: castore
    //   617: dup
    //   618: bipush 18
    //   620: ldc_w 337
    //   623: castore
    //   624: dup
    //   625: bipush 19
    //   627: ldc_w 327
    //   630: castore
    //   631: dup
    //   632: bipush 20
    //   634: ldc -85
    //   636: castore
    //   637: dup
    //   638: bipush 21
    //   640: ldc_w 321
    //   643: castore
    //   644: dup
    //   645: bipush 22
    //   647: ldc_w 322
    //   650: castore
    //   651: dup
    //   652: bipush 23
    //   654: ldc_w 337
    //   657: castore
    //   658: dup
    //   659: bipush 24
    //   661: ldc_w 322
    //   664: castore
    //   665: dup
    //   666: bipush 25
    //   668: ldc -87
    //   670: castore
    //   671: iload_1
    //   672: bipush 22
    //   674: iadd
    //   675: iload 4
    //   677: invokestatic 180	o/Ml:ˊ	([CIB)Ljava/lang/String;
    //   680: invokevirtual 183	java/lang/String:intern	()Ljava/lang/String;
    //   683: invokevirtual 335	android/content/Intent:getParcelableExtra	(Ljava/lang/String;)Landroid/os/Parcelable;
    //   686: checkcast 434	o/FQ
    //   689: astore_3
    //   690: aload_0
    //   691: getfield 262	o/Ml:ʾ	Lo/Is;
    //   694: getfield 419	o/Is:contactPerson	Lo/ـ;
    //   697: aload 6
    //   699: invokevirtual 437	o/ـ:ˎ	(Ljava/lang/Object;)V
    //   702: aload_0
    //   703: getfield 262	o/Ml:ʾ	Lo/Is;
    //   706: getfield 440	o/Is:phoneNumber	Lo/ـ;
    //   709: aload_3
    //   710: invokevirtual 437	o/ـ:ˎ	(Ljava/lang/Object;)V
    //   713: return
    // Local variable table:
    //   start	length	slot	name	signature
    //   0	714	0	this	Ml
    //   0	714	1	paramInt1	int
    //   0	714	2	paramInt2	int
    //   0	714	3	paramIntent	android.content.Intent
    //   299	377	4	b	byte
    //   130	15	5	i	int
    //   279	419	6	localObject	Object
    // Exception table:
    //   from	to	target	type
    //   275	281	81	java/lang/Exception
    //   281	287	81	java/lang/Exception
    //   287	713	81	java/lang/Exception
    //   84	88	199	java/lang/Exception
  }
  
  public void onChangeContact(View paramView)
  {
    break label88;
    label21:
    for (;;)
    {
      Ic.ˏ(this).ˏ(this.ʼॱ).ˎ(3);
      break;
    }
    for (;;)
    {
      int i = 1;
      switch (i)
      {
      default: 
        return;
        i = ˊˊ + 55;
        ˉ = i % 128;
        if (i % 2 != 0) {
          break label21;
        }
        break;
      case 1: 
      case 0: 
        label49:
        label88:
        do
        {
          i = 0;
          break;
          return;
          i = 22 / 0;
          return;
          break label49;
          i = ˊˊ + 81;
          ˉ = i % 128;
        } while (i % 2 != 0);
      }
    }
  }
  
  /* Error */
  public void onContinue(View paramView)
  {
    // Byte code:
    //   0: goto +413 -> 413
    //   3: iconst_1
    //   4: istore_3
    //   5: goto +72 -> 77
    //   8: getstatic 30	o/Ml:ˊˊ	I
    //   11: bipush 31
    //   13: iadd
    //   14: istore_3
    //   15: iload_3
    //   16: sipush 128
    //   19: irem
    //   20: putstatic 28	o/Ml:ˉ	I
    //   23: iload_3
    //   24: iconst_2
    //   25: irem
    //   26: ifeq +6 -> 32
    //   29: goto +314 -> 343
    //   32: goto +195 -> 227
    //   35: iload_2
    //   36: lookupswitch	default:+28->64, 23:+339->375, 77:+28->64
    //   64: iconst_1
    //   65: istore_2
    //   66: goto +320 -> 386
    //   69: iload_3
    //   70: ifeq +6 -> 76
    //   73: goto +54 -> 127
    //   76: return
    //   77: iload_2
    //   78: ifeq +6 -> 84
    //   81: goto -12 -> 69
    //   84: return
    //   85: goto -82 -> 3
    //   88: aload_0
    //   89: getfield 240	o/Ml:ॱˊ	Landroid/databinding/ViewDataBinding;
    //   92: checkcast 264	o/Mz
    //   95: getfield 267	o/Mz:ॱ	Lo/Ja;
    //   98: invokevirtual 451	o/Ja:ॱॱ	()Lo/FC;
    //   101: getfield 457	o/FC:isValid	Z
    //   104: ifeq +6 -> 110
    //   107: goto +273 -> 380
    //   110: goto +259 -> 369
    //   113: aload_0
    //   114: invokespecial 459	o/Ml:ˋˊ	()V
    //   117: aconst_null
    //   118: arraylength
    //   119: istore_2
    //   120: return
    //   121: bipush 24
    //   123: istore_3
    //   124: goto +65 -> 189
    //   127: getstatic 30	o/Ml:ˊˊ	I
    //   130: bipush 71
    //   132: iadd
    //   133: istore_2
    //   134: iload_2
    //   135: sipush 128
    //   138: irem
    //   139: putstatic 28	o/Ml:ˉ	I
    //   142: iload_2
    //   143: iconst_2
    //   144: irem
    //   145: ifeq +6 -> 151
    //   148: goto -35 -> 113
    //   151: goto +106 -> 257
    //   154: aload_0
    //   155: getfield 240	o/Ml:ॱˊ	Landroid/databinding/ViewDataBinding;
    //   158: checkcast 264	o/Mz
    //   161: getfield 373	o/Mz:ʼ	Lo/Jc;
    //   164: new 461	o/Fr
    //   167: dup
    //   168: invokespecial 462	o/Fr:<init>	()V
    //   171: invokevirtual 465	o/Jc:ˋ	(Lo/FA;)Lo/FC;
    //   174: getfield 457	o/FC:isValid	Z
    //   177: ifeq +6 -> 183
    //   180: goto -172 -> 8
    //   183: goto +36 -> 219
    //   186: astore_1
    //   187: aload_1
    //   188: athrow
    //   189: iload_3
    //   190: lookupswitch	default:+26->216, 1:+120->310, 24:+29->219
    //   216: goto +94 -> 310
    //   219: iconst_0
    //   220: istore_3
    //   221: goto -144 -> 77
    //   224: goto +192 -> 416
    //   227: aload_0
    //   228: getfield 240	o/Ml:ॱˊ	Landroid/databinding/ViewDataBinding;
    //   231: checkcast 264	o/Mz
    //   234: getfield 373	o/Mz:ʼ	Lo/Jc;
    //   237: invokevirtual 466	o/Jc:ॱॱ	()Lo/FC;
    //   240: getfield 457	o/FC:isValid	Z
    //   243: ifeq +6 -> 249
    //   246: goto +6 -> 252
    //   249: goto -128 -> 121
    //   252: iconst_1
    //   253: istore_3
    //   254: goto -65 -> 189
    //   257: aload_0
    //   258: invokespecial 459	o/Ml:ˋˊ	()V
    //   261: return
    //   262: aload_0
    //   263: getfield 240	o/Ml:ॱˊ	Landroid/databinding/ViewDataBinding;
    //   266: astore_1
    //   267: aload_1
    //   268: checkcast 264	o/Mz
    //   271: astore_1
    //   272: aload_1
    //   273: getfield 267	o/Mz:ॱ	Lo/Ja;
    //   276: astore_1
    //   277: new 461	o/Fr
    //   280: dup
    //   281: invokespecial 462	o/Fr:<init>	()V
    //   284: astore 5
    //   286: aload_1
    //   287: aload 5
    //   289: invokevirtual 467	o/Ja:ˋ	(Lo/FA;)Lo/FC;
    //   292: astore_1
    //   293: aload_1
    //   294: getfield 457	o/FC:isValid	Z
    //   297: istore 4
    //   299: iload 4
    //   301: ifeq +6 -> 307
    //   304: goto -216 -> 88
    //   307: goto +68 -> 375
    //   310: getstatic 28	o/Ml:ˉ	I
    //   313: bipush 91
    //   315: iadd
    //   316: istore_3
    //   317: iload_3
    //   318: sipush 128
    //   321: irem
    //   322: putstatic 30	o/Ml:ˊˊ	I
    //   325: iload_3
    //   326: iconst_2
    //   327: irem
    //   328: ifne +6 -> 334
    //   331: goto -246 -> 85
    //   334: goto -331 -> 3
    //   337: goto -183 -> 154
    //   340: astore_1
    //   341: aload_1
    //   342: athrow
    //   343: aload_0
    //   344: getfield 240	o/Ml:ॱˊ	Landroid/databinding/ViewDataBinding;
    //   347: checkcast 264	o/Mz
    //   350: getfield 373	o/Mz:ʼ	Lo/Jc;
    //   353: invokevirtual 466	o/Jc:ॱॱ	()Lo/FC;
    //   356: getfield 457	o/FC:isValid	Z
    //   359: istore 4
    //   361: new 258	java/lang/NullPointerException
    //   364: dup
    //   365: invokespecial 259	java/lang/NullPointerException:<init>	()V
    //   368: athrow
    //   369: bipush 23
    //   371: istore_2
    //   372: goto -337 -> 35
    //   375: iconst_0
    //   376: istore_2
    //   377: goto -40 -> 337
    //   380: bipush 77
    //   382: istore_2
    //   383: goto -348 -> 35
    //   386: getstatic 30	o/Ml:ˊˊ	I
    //   389: bipush 35
    //   391: iadd
    //   392: istore_3
    //   393: iload_3
    //   394: sipush 128
    //   397: irem
    //   398: putstatic 28	o/Ml:ˉ	I
    //   401: iload_3
    //   402: iconst_2
    //   403: irem
    //   404: ifeq +6 -> 410
    //   407: goto -183 -> 224
    //   410: goto +6 -> 416
    //   413: goto -151 -> 262
    //   416: goto -262 -> 154
    // Local variable table:
    //   start	length	slot	name	signature
    //   0	419	0	this	Ml
    //   0	419	1	paramView	View
    //   35	348	2	i	int
    //   4	400	3	j	int
    //   297	63	4	bool	boolean
    //   284	4	5	localFr	Fr
    // Exception table:
    //   from	to	target	type
    //   286	293	186	java/lang/Exception
    //   293	299	186	java/lang/Exception
    //   262	267	340	java/lang/Exception
    //   267	272	340	java/lang/Exception
    //   272	277	340	java/lang/Exception
  }
  
  /* Error */
  public void onCreate(android.os.Bundle paramBundle)
  {
    // Byte code:
    //   0: goto +311 -> 311
    //   3: getstatic 30	o/Ml:ˊˊ	I
    //   6: bipush 69
    //   8: iadd
    //   9: istore_2
    //   10: iload_2
    //   11: sipush 128
    //   14: irem
    //   15: putstatic 28	o/Ml:ˉ	I
    //   18: iload_2
    //   19: iconst_2
    //   20: irem
    //   21: ifeq +6 -> 27
    //   24: goto +290 -> 314
    //   27: return
    //   28: astore_1
    //   29: aload_1
    //   30: athrow
    //   31: aload_0
    //   32: aload_1
    //   33: invokespecial 471	o/IB:onCreate	(Landroid/os/Bundle;)V
    //   36: aload_0
    //   37: aload_0
    //   38: getfield 240	o/Ml:ॱˊ	Landroid/databinding/ViewDataBinding;
    //   41: checkcast 264	o/Mz
    //   44: getfield 474	o/Mz:ॱॱ	Lo/у;
    //   47: invokevirtual 477	o/Ml:ˊ	(Lo/у;)V
    //   50: aload_0
    //   51: invokespecial 479	o/Ml:ʾ	()V
    //   54: aload_0
    //   55: aload_0
    //   56: invokevirtual 483	o/Ml:getIntent	()Landroid/content/Intent;
    //   59: invokespecial 485	o/Ml:ˎ	(Landroid/content/Intent;)V
    //   62: goto +20 -> 82
    //   65: astore_1
    //   66: aload_1
    //   67: invokevirtual 87	java/lang/Throwable:getCause	()Ljava/lang/Throwable;
    //   70: astore 4
    //   72: aload 4
    //   74: ifnull +6 -> 80
    //   77: aload 4
    //   79: athrow
    //   80: aload_1
    //   81: athrow
    //   82: aload_0
    //   83: invokevirtual 93	android/content/Context:getPackageName	()Ljava/lang/String;
    //   86: iconst_4
    //   87: invokevirtual 99	java/lang/String:codePointAt	(I)I
    //   90: bipush 112
    //   92: isub
    //   93: aload_0
    //   94: invokevirtual 149	android/content/Context:getResources	()Landroid/content/res/Resources;
    //   97: ldc_w 486
    //   100: invokevirtual 156	android/content/res/Resources:getString	(I)Ljava/lang/String;
    //   103: bipush 22
    //   105: bipush 23
    //   107: invokevirtual 160	java/lang/String:substring	(II)Ljava/lang/String;
    //   110: invokevirtual 165	java/lang/String:length	()I
    //   113: sipush 266
    //   116: iadd
    //   117: aload_0
    //   118: invokevirtual 149	android/content/Context:getResources	()Landroid/content/res/Resources;
    //   121: ldc_w 487
    //   124: invokevirtual 156	android/content/res/Resources:getString	(I)Ljava/lang/String;
    //   127: iconst_0
    //   128: iconst_4
    //   129: invokevirtual 160	java/lang/String:substring	(II)Ljava/lang/String;
    //   132: iconst_3
    //   133: invokevirtual 99	java/lang/String:codePointAt	(I)I
    //   136: sipush 14776
    //   139: iadd
    //   140: i2c
    //   141: invokestatic 114	o/O:ˋ	(IIC)Ljava/lang/Object;
    //   144: checkcast 116	java/lang/Class
    //   147: ldc_w 488
    //   150: aconst_null
    //   151: invokevirtual 122	java/lang/Class:getMethod	(Ljava/lang/String;[Ljava/lang/Class;)Ljava/lang/reflect/Method;
    //   154: aconst_null
    //   155: aconst_null
    //   156: invokevirtual 128	java/lang/reflect/Method:invoke	(Ljava/lang/Object;[Ljava/lang/Object;)Ljava/lang/Object;
    //   159: astore 4
    //   161: goto +20 -> 181
    //   164: astore_1
    //   165: aload_1
    //   166: invokevirtual 87	java/lang/Throwable:getCause	()Ljava/lang/Throwable;
    //   169: astore 4
    //   171: aload 4
    //   173: ifnull +6 -> 179
    //   176: aload 4
    //   178: athrow
    //   179: aload_1
    //   180: athrow
    //   181: aload_0
    //   182: invokevirtual 149	android/content/Context:getResources	()Landroid/content/res/Resources;
    //   185: ldc_w 489
    //   188: invokevirtual 156	android/content/res/Resources:getString	(I)Ljava/lang/String;
    //   191: iconst_0
    //   192: iconst_4
    //   193: invokevirtual 160	java/lang/String:substring	(II)Ljava/lang/String;
    //   196: iconst_2
    //   197: invokevirtual 99	java/lang/String:codePointAt	(I)I
    //   200: bipush 7
    //   202: isub
    //   203: aload_0
    //   204: invokevirtual 149	android/content/Context:getResources	()Landroid/content/res/Resources;
    //   207: ldc_w 490
    //   210: invokevirtual 156	android/content/res/Resources:getString	(I)Ljava/lang/String;
    //   213: iconst_0
    //   214: iconst_4
    //   215: invokevirtual 160	java/lang/String:substring	(II)Ljava/lang/String;
    //   218: invokevirtual 165	java/lang/String:length	()I
    //   221: sipush 263
    //   224: iadd
    //   225: aload_0
    //   226: invokevirtual 103	android/content/Context:getApplicationInfo	()Landroid/content/pm/ApplicationInfo;
    //   229: getfield 108	android/content/pm/ApplicationInfo:targetSdkVersion	I
    //   232: sipush 14763
    //   235: iadd
    //   236: i2c
    //   237: invokestatic 114	o/O:ˋ	(IIC)Ljava/lang/Object;
    //   240: checkcast 116	java/lang/Class
    //   243: ldc_w 491
    //   246: aconst_null
    //   247: invokevirtual 122	java/lang/Class:getMethod	(Ljava/lang/String;[Ljava/lang/Class;)Ljava/lang/reflect/Method;
    //   250: aload 4
    //   252: aconst_null
    //   253: invokevirtual 128	java/lang/reflect/Method:invoke	(Ljava/lang/Object;[Ljava/lang/Object;)Ljava/lang/Object;
    //   256: checkcast 208	o/HQ
    //   259: astore 4
    //   261: aload_0
    //   262: aload 4
    //   264: putfield 79	o/Ml:ˈ	Lo/HQ;
    //   267: aload_0
    //   268: invokespecial 493	o/Ml:ʻॱ	()V
    //   271: aload_0
    //   272: invokespecial 495	o/Ml:ॱˋ	()V
    //   275: aload_1
    //   276: ifnonnull +6 -> 282
    //   279: goto +15 -> 294
    //   282: goto +23 -> 305
    //   285: goto +121 -> 406
    //   288: bipush 99
    //   290: istore_2
    //   291: goto +24 -> 315
    //   294: iconst_0
    //   295: istore_2
    //   296: goto +51 -> 347
    //   299: bipush 47
    //   301: istore_2
    //   302: goto +13 -> 315
    //   305: bipush 51
    //   307: istore_2
    //   308: goto +39 -> 347
    //   311: goto +141 -> 452
    //   314: return
    //   315: iload_2
    //   316: lookupswitch	default:+28->344, 47:+60->376, 99:+118->434
    //   344: goto +32 -> 376
    //   347: iload_2
    //   348: lookupswitch	default:+28->376, 0:+34->382, 51:+28->376
    //   376: goto -373 -> 3
    //   379: astore_1
    //   380: aload_1
    //   381: athrow
    //   382: getstatic 30	o/Ml:ˊˊ	I
    //   385: bipush 15
    //   387: iadd
    //   388: istore_2
    //   389: iload_2
    //   390: sipush 128
    //   393: irem
    //   394: putstatic 28	o/Ml:ˉ	I
    //   397: iload_2
    //   398: iconst_2
    //   399: irem
    //   400: ifeq +6 -> 406
    //   403: goto -118 -> 285
    //   406: aload_0
    //   407: getfield 240	o/Ml:ॱˊ	Landroid/databinding/ViewDataBinding;
    //   410: astore_1
    //   411: aload_1
    //   412: checkcast 264	o/Mz
    //   415: astore_1
    //   416: aload_1
    //   417: invokevirtual 497	o/Mz:ˏॱ	()Z
    //   420: istore_3
    //   421: iload_3
    //   422: ifeq +6 -> 428
    //   425: goto -137 -> 288
    //   428: goto -129 -> 299
    //   431: goto -400 -> 31
    //   434: aload_0
    //   435: invokestatic 294	o/Ic:ˏ	(Landroid/content/Context;)Lo/Ic;
    //   438: aload_0
    //   439: getfield 308	o/Ml:ʼॱ	Lo/FT;
    //   442: invokevirtual 445	o/Ic:ˏ	(Lo/FT;)Lo/j;
    //   445: iconst_3
    //   446: invokevirtual 447	o/j:ˎ	(I)V
    //   449: goto -73 -> 376
    //   452: getstatic 30	o/Ml:ˊˊ	I
    //   455: bipush 41
    //   457: iadd
    //   458: istore_2
    //   459: iload_2
    //   460: sipush 128
    //   463: irem
    //   464: putstatic 28	o/Ml:ˉ	I
    //   467: iload_2
    //   468: iconst_2
    //   469: irem
    //   470: ifeq +6 -> 476
    //   473: goto -42 -> 431
    //   476: goto -445 -> 31
    // Local variable table:
    //   start	length	slot	name	signature
    //   0	479	0	this	Ml
    //   0	479	1	paramBundle	android.os.Bundle
    //   9	461	2	i	int
    //   420	2	3	bool	boolean
    //   70	193	4	localObject	Object
    // Exception table:
    //   from	to	target	type
    //   406	411	28	java/lang/Exception
    //   82	161	65	finally
    //   181	261	164	finally
    //   411	416	379	java/lang/Exception
    //   416	421	379	java/lang/Exception
  }
  
  public void ˋ(ز paramز)
  {
    break label164;
    int i = 0;
    break label14;
    i = 40;
    for (;;)
    {
      switch (i)
      {
      case 1: 
      default: 
        label14:
        paramز.ॱ(false);
        paramز.ˏ(false);
        break;
        switch (i)
        {
        default: 
          return;
        case 52: 
          label49:
          throw new NullPointerException();
        }
        break;
      }
      for (;;)
      {
        i = ˊˊ + 19;
        ˉ = i % 128;
        if (i % 2 == 0) {
          break;
        }
        i = 52;
        break label49;
        paramز.ॱ(true);
        paramز.ˏ(true);
      }
      label131:
      i = 1;
    }
    return;
    label164:
    for (;;)
    {
      i = ˉ + 71;
      ˊˊ = i % 128;
      if (i % 2 == 0) {
        break label131;
      }
      break;
    }
  }
  
  public int ˎ()
  {
    for (;;)
    {
      i = ˊˊ + 107;
      ˉ = i % 128;
      if (i % 2 == 0) {
        break label39;
      }
      i = 0;
      break label41;
      return LV.iF.activity_transfer_money_details;
      label39:
      i = 1;
      switch (i)
      {
      case 1: 
      default: 
        label41:
        break label70;
      }
    }
    label70:
    int i = LV.iF.activity_transfer_money_details;
    int j = null.length;
    return i;
  }
}
