package o;

import android.content.res.Resources;
import android.databinding.ViewDataBinding;
import android.databinding.ViewDataBinding.If;
import android.util.SparseIntArray;
import android.view.View;
import android.widget.LinearLayout;
import android.widget.TextView;

public class MM
  extends ViewDataBinding
{
  private static long ʻॱ;
  private static int ʽॱ;
  private static int ʿ;
  private static final ViewDataBinding.If ˎ;
  private static int ॱˋ;
  private static final SparseIntArray ॱॱ;
  private static byte ॱᐝ;
  private static char ᐝॱ;
  private final Js ʻ;
  private final Js ʼ;
  private final LinearLayout ʽ;
  public final TextView ˊ;
  private final Js ˊॱ;
  private String ˋॱ;
  private String ˏॱ;
  private final Js ͺ;
  public final у ॱ;
  private Gk ॱˊ;
  private long ॱˎ = -1L;
  private final Js ᐝ;
  
  /* Error */
  static
  {
    // Byte code:
    //   0: goto +49 -> 49
    //   3: astore_1
    //   4: aload_1
    //   5: athrow
    //   6: bipush 32
    //   8: iconst_0
    //   9: idiv
    //   10: istore_0
    //   11: return
    //   12: iconst_0
    //   13: istore_0
    //   14: goto +61 -> 75
    //   17: iconst_1
    //   18: istore_0
    //   19: goto +56 -> 75
    //   22: getstatic 42	o/MM:ʿ	I
    //   25: bipush 17
    //   27: iadd
    //   28: istore_0
    //   29: iload_0
    //   30: sipush 128
    //   33: irem
    //   34: putstatic 44	o/MM:ʽॱ	I
    //   37: iload_0
    //   38: iconst_2
    //   39: irem
    //   40: ifeq +6 -> 46
    //   43: goto -31 -> 12
    //   46: goto -29 -> 17
    //   49: iconst_0
    //   50: putstatic 44	o/MM:ʽॱ	I
    //   53: iconst_1
    //   54: putstatic 42	o/MM:ʿ	I
    //   57: invokestatic 46	o/MM:ॱˊ	()V
    //   60: invokestatic 48	o/MM:ˋॱ	()V
    //   63: aconst_null
    //   64: putstatic 50	o/MM:ˎ	Landroid/databinding/ViewDataBinding$If;
    //   67: aconst_null
    //   68: putstatic 52	o/MM:ॱॱ	Landroid/util/SparseIntArray;
    //   71: goto -49 -> 22
    //   74: return
    //   75: iload_0
    //   76: tableswitch	default:+24->100, 0:+-70->6, 1:+-2->74
    //   100: return
    // Local variable table:
    //   start	length	slot	name	signature
    //   10	66	0	i	int
    //   3	2	1	localException	Exception
    // Exception table:
    //   from	to	target	type
    //   49	53	3	java/lang/Exception
    //   53	57	3	java/lang/Exception
    //   57	60	3	java/lang/Exception
    //   60	63	3	java/lang/Exception
    //   63	67	3	java/lang/Exception
    //   67	71	3	java/lang/Exception
  }
  
  public MM(ˉ paramˉ, View paramView)
  {
    super(paramˉ, paramView, 0);
    paramˉ = ॱ(paramˉ, paramView, 8, ˎ, ॱॱ);
    this.ʽ = ((LinearLayout)paramˉ[0]);
    this.ʽ.setTag(null);
    this.ᐝ = ((Js)paramˉ[3]);
    this.ᐝ.setTag(null);
    this.ʻ = ((Js)paramˉ[4]);
    this.ʻ.setTag(null);
    this.ʼ = ((Js)paramˉ[5]);
    this.ʼ.setTag(null);
    this.ˊॱ = ((Js)paramˉ[6]);
    this.ˊॱ.setTag(null);
    this.ͺ = ((Js)paramˉ[7]);
    this.ͺ.setTag(null);
    this.ॱ = ((у)paramˉ[1]);
    this.ॱ.setTag(null);
    this.ˊ = ((TextView)paramˉ[2]);
    this.ˊ.setTag(null);
    ˋ(paramView);
    ˊॱ();
  }
  
  /* Error */
  private static String ˋ(char[] paramArrayOfChar1, char paramChar, char[] paramArrayOfChar2, int paramInt, char[] paramArrayOfChar3)
  {
    // Byte code:
    //   0: goto +358 -> 358
    //   3: bipush 75
    //   5: istore_3
    //   6: goto +193 -> 199
    //   9: iconst_0
    //   10: istore_1
    //   11: goto +283 -> 294
    //   14: bipush 45
    //   16: istore_3
    //   17: goto +182 -> 199
    //   20: iload_3
    //   21: istore_1
    //   22: goto +324 -> 346
    //   25: iload_3
    //   26: istore_1
    //   27: goto +319 -> 346
    //   30: iconst_1
    //   31: istore_1
    //   32: goto +262 -> 294
    //   35: aload_0
    //   36: aload 4
    //   38: iload_1
    //   39: invokestatic 109	o/oJ:ˏ	([C[CI)V
    //   42: aload 6
    //   44: iload_1
    //   45: aload_2
    //   46: iload_1
    //   47: caload
    //   48: aload_0
    //   49: iload_1
    //   50: iconst_3
    //   51: iadd
    //   52: iconst_4
    //   53: irem
    //   54: caload
    //   55: ixor
    //   56: i2l
    //   57: getstatic 111	o/MM:ʻॱ	J
    //   60: lxor
    //   61: getstatic 113	o/MM:ॱˋ	I
    //   64: i2l
    //   65: lxor
    //   66: getstatic 115	o/MM:ᐝॱ	C
    //   69: i2l
    //   70: lxor
    //   71: l2i
    //   72: i2c
    //   73: castore
    //   74: iload_1
    //   75: iconst_1
    //   76: iadd
    //   77: istore_1
    //   78: goto +153 -> 231
    //   81: getstatic 44	o/MM:ʽॱ	I
    //   84: bipush 85
    //   86: iadd
    //   87: istore_3
    //   88: iload_3
    //   89: sipush 128
    //   92: irem
    //   93: putstatic 42	o/MM:ʿ	I
    //   96: iload_3
    //   97: iconst_2
    //   98: irem
    //   99: ifne +6 -> 105
    //   102: goto -99 -> 3
    //   105: goto -91 -> 14
    //   108: aload_0
    //   109: aload 4
    //   111: iload_1
    //   112: invokestatic 109	o/oJ:ˏ	([C[CI)V
    //   115: aload 6
    //   117: iload_1
    //   118: aload_2
    //   119: iload_1
    //   120: caload
    //   121: aload_0
    //   122: iload_1
    //   123: iconst_4
    //   124: ishl
    //   125: iconst_4
    //   126: iushr
    //   127: caload
    //   128: ixor
    //   129: i2l
    //   130: getstatic 111	o/MM:ʻॱ	J
    //   133: lor
    //   134: getstatic 113	o/MM:ॱˋ	I
    //   137: i2l
    //   138: land
    //   139: getstatic 115	o/MM:ᐝॱ	C
    //   142: i2l
    //   143: ldiv
    //   144: l2i
    //   145: i2c
    //   146: castore
    //   147: iload_1
    //   148: bipush 80
    //   150: iadd
    //   151: istore_1
    //   152: goto +79 -> 231
    //   155: getstatic 44	o/MM:ʽॱ	I
    //   158: bipush 67
    //   160: iadd
    //   161: istore_1
    //   162: iload_1
    //   163: sipush 128
    //   166: irem
    //   167: putstatic 42	o/MM:ʿ	I
    //   170: iload_1
    //   171: iconst_2
    //   172: irem
    //   173: ifne +5 -> 178
    //   176: aload_0
    //   177: areturn
    //   178: aload_0
    //   179: areturn
    //   180: astore_0
    //   181: aload_0
    //   182: athrow
    //   183: new 117	java/lang/String
    //   186: dup
    //   187: aload 6
    //   189: invokespecial 120	java/lang/String:<init>	([C)V
    //   192: astore_0
    //   193: goto -38 -> 155
    //   196: astore_0
    //   197: aload_0
    //   198: athrow
    //   199: iload_3
    //   200: lookupswitch	default:+28->228, 45:+-165->35, 75:+-92->108
    //   228: goto -120 -> 108
    //   231: goto +115 -> 346
    //   234: aload_0
    //   235: invokevirtual 126	[C:clone	()Ljava/lang/Object;
    //   238: astore_0
    //   239: aload_0
    //   240: checkcast 122	[C
    //   243: astore_0
    //   244: aload 4
    //   246: invokevirtual 126	[C:clone	()Ljava/lang/Object;
    //   249: astore 4
    //   251: aload 4
    //   253: checkcast 122	[C
    //   256: astore 4
    //   258: aload_0
    //   259: iconst_0
    //   260: aload_0
    //   261: iconst_0
    //   262: caload
    //   263: iload_1
    //   264: ixor
    //   265: i2c
    //   266: castore
    //   267: aload 4
    //   269: iconst_2
    //   270: aload 4
    //   272: iconst_2
    //   273: caload
    //   274: iload_3
    //   275: i2c
    //   276: iadd
    //   277: i2c
    //   278: castore
    //   279: aload_2
    //   280: arraylength
    //   281: istore 5
    //   283: iload 5
    //   285: newarray char
    //   287: astore 6
    //   289: iconst_0
    //   290: istore_3
    //   291: goto +28 -> 319
    //   294: iload_1
    //   295: tableswitch	default:+21->316, 0:+-275->20, 1:+-270->25
    //   316: goto -291 -> 25
    //   319: getstatic 42	o/MM:ʿ	I
    //   322: bipush 91
    //   324: iadd
    //   325: istore_1
    //   326: iload_1
    //   327: sipush 128
    //   330: irem
    //   331: putstatic 44	o/MM:ʽॱ	I
    //   334: iload_1
    //   335: iconst_2
    //   336: irem
    //   337: ifeq +6 -> 343
    //   340: goto -331 -> 9
    //   343: goto -313 -> 30
    //   346: iload_1
    //   347: iload 5
    //   349: if_icmpge +6 -> 355
    //   352: goto -271 -> 81
    //   355: goto -172 -> 183
    //   358: goto -124 -> 234
    // Local variable table:
    //   start	length	slot	name	signature
    //   0	361	0	paramArrayOfChar1	char[]
    //   0	361	1	paramChar	char
    //   0	361	2	paramArrayOfChar2	char[]
    //   0	361	3	paramInt	int
    //   0	361	4	paramArrayOfChar3	char[]
    //   281	69	5	c	char
    //   42	246	6	arrayOfChar	char[]
    // Exception table:
    //   from	to	target	type
    //   239	244	180	java/lang/Exception
    //   234	239	196	java/lang/Exception
    //   239	244	196	java/lang/Exception
    //   244	251	196	java/lang/Exception
    //   251	258	196	java/lang/Exception
    //   279	289	196	java/lang/Exception
  }
  
  static void ˋॱ()
  {
    break label9;
    label3:
    int i = 39;
    for (;;)
    {
      label9:
      i = 46;
      switch (i)
      {
      default: 
        break label74;
        i = ʽॱ + 53;
        ʿ = i % 128;
        if (i % 2 == 0) {
          break label3;
        }
      }
    }
    label74:
    ॱᐝ = 105;
    return;
    ॱᐝ = -102;
  }
  
  /* Error */
  private String ॱ(String paramString)
  {
    // Byte code:
    //   0: goto +284 -> 284
    //   3: iconst_5
    //   4: iconst_2
    //   5: idiv
    //   6: istore_2
    //   7: iload_3
    //   8: istore_2
    //   9: goto +258 -> 267
    //   12: iload_2
    //   13: tableswitch	default:+23->36, 0:+-10->3, 1:+94->107
    //   36: goto +71 -> 107
    //   39: astore_1
    //   40: new 133	java/lang/RuntimeException
    //   43: dup
    //   44: aload_1
    //   45: invokespecial 136	java/lang/RuntimeException:<init>	(Ljava/lang/Throwable;)V
    //   48: athrow
    //   49: getstatic 42	o/MM:ʿ	I
    //   52: bipush 111
    //   54: iadd
    //   55: istore_2
    //   56: iload_2
    //   57: sipush 128
    //   60: irem
    //   61: putstatic 44	o/MM:ʽॱ	I
    //   64: iload_2
    //   65: iconst_2
    //   66: irem
    //   67: ifeq +6 -> 73
    //   70: goto +211 -> 281
    //   73: goto +226 -> 299
    //   76: iload_3
    //   77: lookupswitch	default:+27->104, 10:+66->143, 12:+92->169
    //   104: goto +65 -> 169
    //   107: iload_3
    //   108: istore_2
    //   109: goto +158 -> 267
    //   112: iconst_0
    //   113: istore_2
    //   114: goto -102 -> 12
    //   117: getstatic 42	o/MM:ʿ	I
    //   120: bipush 65
    //   122: iadd
    //   123: istore_2
    //   124: iload_2
    //   125: sipush 128
    //   128: irem
    //   129: putstatic 44	o/MM:ʽॱ	I
    //   132: iload_2
    //   133: iconst_2
    //   134: irem
    //   135: ifeq +6 -> 141
    //   138: goto +29 -> 167
    //   141: aload_1
    //   142: areturn
    //   143: aload 4
    //   145: iload_2
    //   146: aload_1
    //   147: aload_1
    //   148: arraylength
    //   149: iload_2
    //   150: isub
    //   151: iconst_1
    //   152: isub
    //   153: baload
    //   154: getstatic 128	o/MM:ॱᐝ	B
    //   157: ixor
    //   158: i2b
    //   159: bastore
    //   160: iload_2
    //   161: iconst_1
    //   162: iadd
    //   163: istore_2
    //   164: goto +103 -> 267
    //   167: aload_1
    //   168: areturn
    //   169: new 117	java/lang/String
    //   172: dup
    //   173: aload 4
    //   175: iconst_4
    //   176: newarray char
    //   178: dup
    //   179: iconst_0
    //   180: ldc -119
    //   182: castore
    //   183: dup
    //   184: iconst_1
    //   185: ldc -118
    //   187: castore
    //   188: dup
    //   189: iconst_2
    //   190: ldc -117
    //   192: castore
    //   193: dup
    //   194: iconst_3
    //   195: ldc -116
    //   197: castore
    //   198: sipush 28339
    //   201: iconst_5
    //   202: newarray char
    //   204: dup
    //   205: iconst_0
    //   206: ldc -115
    //   208: castore
    //   209: dup
    //   210: iconst_1
    //   211: ldc -114
    //   213: castore
    //   214: dup
    //   215: iconst_2
    //   216: ldc -113
    //   218: castore
    //   219: dup
    //   220: iconst_3
    //   221: ldc -112
    //   223: castore
    //   224: dup
    //   225: iconst_4
    //   226: ldc -111
    //   228: castore
    //   229: ldc -110
    //   231: iconst_4
    //   232: newarray char
    //   234: dup
    //   235: iconst_0
    //   236: ldc -109
    //   238: castore
    //   239: dup
    //   240: iconst_1
    //   241: ldc -109
    //   243: castore
    //   244: dup
    //   245: iconst_2
    //   246: ldc -109
    //   248: castore
    //   249: dup
    //   250: iconst_3
    //   251: ldc -109
    //   253: castore
    //   254: invokestatic 149	o/MM:ˋ	([CC[CI[C)Ljava/lang/String;
    //   257: invokevirtual 153	java/lang/String:intern	()Ljava/lang/String;
    //   260: invokespecial 156	java/lang/String:<init>	([BLjava/lang/String;)V
    //   263: astore_1
    //   264: goto -147 -> 117
    //   267: aload_1
    //   268: arraylength
    //   269: istore_3
    //   270: iload_2
    //   271: iload_3
    //   272: if_icmpge +6 -> 278
    //   275: goto +18 -> 293
    //   278: goto +9 -> 287
    //   281: goto +18 -> 299
    //   284: goto -235 -> 49
    //   287: bipush 12
    //   289: istore_3
    //   290: goto -214 -> 76
    //   293: bipush 10
    //   295: istore_3
    //   296: goto -220 -> 76
    //   299: aload_1
    //   300: iconst_4
    //   301: newarray char
    //   303: dup
    //   304: iconst_0
    //   305: ldc -99
    //   307: castore
    //   308: dup
    //   309: iconst_1
    //   310: ldc -98
    //   312: castore
    //   313: dup
    //   314: iconst_2
    //   315: ldc -97
    //   317: castore
    //   318: dup
    //   319: iconst_3
    //   320: ldc -96
    //   322: castore
    //   323: iconst_0
    //   324: bipush 10
    //   326: newarray char
    //   328: dup
    //   329: iconst_0
    //   330: ldc -95
    //   332: castore
    //   333: dup
    //   334: iconst_1
    //   335: ldc -94
    //   337: castore
    //   338: dup
    //   339: iconst_2
    //   340: ldc -93
    //   342: castore
    //   343: dup
    //   344: iconst_3
    //   345: ldc -92
    //   347: castore
    //   348: dup
    //   349: iconst_4
    //   350: ldc -91
    //   352: castore
    //   353: dup
    //   354: iconst_5
    //   355: ldc -90
    //   357: castore
    //   358: dup
    //   359: bipush 6
    //   361: ldc -89
    //   363: castore
    //   364: dup
    //   365: bipush 7
    //   367: ldc -88
    //   369: castore
    //   370: dup
    //   371: bipush 8
    //   373: ldc -87
    //   375: castore
    //   376: dup
    //   377: bipush 9
    //   379: ldc -86
    //   381: castore
    //   382: iconst_0
    //   383: iconst_4
    //   384: newarray char
    //   386: dup
    //   387: iconst_0
    //   388: ldc -109
    //   390: castore
    //   391: dup
    //   392: iconst_1
    //   393: ldc -109
    //   395: castore
    //   396: dup
    //   397: iconst_2
    //   398: ldc -109
    //   400: castore
    //   401: dup
    //   402: iconst_3
    //   403: ldc -109
    //   405: castore
    //   406: invokestatic 149	o/MM:ˋ	([CC[CI[C)Ljava/lang/String;
    //   409: invokevirtual 153	java/lang/String:intern	()Ljava/lang/String;
    //   412: invokevirtual 174	java/lang/String:getBytes	(Ljava/lang/String;)[B
    //   415: astore_1
    //   416: aload_1
    //   417: arraylength
    //   418: newarray byte
    //   420: astore 4
    //   422: iconst_0
    //   423: istore_3
    //   424: getstatic 42	o/MM:ʿ	I
    //   427: bipush 45
    //   429: iadd
    //   430: istore_2
    //   431: iload_2
    //   432: sipush 128
    //   435: irem
    //   436: putstatic 44	o/MM:ʽॱ	I
    //   439: iload_2
    //   440: iconst_2
    //   441: irem
    //   442: ifeq +6 -> 448
    //   445: goto -333 -> 112
    //   448: iconst_1
    //   449: istore_2
    //   450: goto -438 -> 12
    // Local variable table:
    //   start	length	slot	name	signature
    //   0	453	0	this	MM
    //   0	453	1	paramString	String
    //   6	444	2	i	int
    //   7	417	3	j	int
    //   143	278	4	arrayOfByte	byte[]
    // Exception table:
    //   from	to	target	type
    //   143	160	39	java/io/UnsupportedEncodingException
    //   169	264	39	java/io/UnsupportedEncodingException
    //   267	270	39	java/io/UnsupportedEncodingException
    //   299	422	39	java/io/UnsupportedEncodingException
  }
  
  static void ॱˊ()
  {
    ᐝॱ = 53027;
    ʻॱ = 0L;
    ॱˋ = 0;
  }
  
  public void ˊॱ()
  {
    try
    {
      this.ॱˎ = 8L;
    }
    finally
    {
      localObject = finally;
      throw localObject;
    }
    ʽ();
  }
  
  public void ˎ(String paramString)
  {
    this.ˏॱ = paramString;
    try
    {
      this.ॱˎ |= 0x4;
    }
    finally
    {
      paramString = finally;
      throw paramString;
    }
    ˊ(102);
    super.ʽ();
  }
  
  public void ˏ()
  {
    String str5 = ˋ(new char[] { 13381, 5210, -16315, -5607 }, 'ᧀ', new char[] { 32153, 19021, -23019, 13624 }, 0, new char[] { 0, 0, 0, 0 }).intern();
    long l;
    try
    {
      l = this.ॱˎ;
      this.ॱˎ = 0L;
    }
    finally
    {
      localObject1 = finally;
      throw localObject1;
    }
    Object localObject6 = null;
    String str2 = null;
    Gk localGk = this.ॱˊ;
    Js localJs = null;
    Object localObject7 = null;
    String str3 = this.ˋॱ;
    Object localObject8 = null;
    String str4 = this.ˏॱ;
    Object localObject5 = localObject6;
    String str1 = str2;
    Object localObject4 = localJs;
    Object localObject3 = localObject7;
    Object localObject2 = localObject8;
    if ((0x9 & l) != 0L)
    {
      localObject5 = localObject6;
      str1 = str2;
      localObject4 = localJs;
      localObject3 = localObject7;
      localObject2 = localObject8;
      if (localGk != null)
      {
        localObject5 = localGk.ˎ();
        str1 = localGk.ˏ();
        localObject4 = localGk.ˋ();
        localObject3 = localGk.ˊ();
        localObject2 = localGk.ॱ();
      }
    }
    if ((0x8 & l) != 0L)
    {
      localJs = this.ᐝ;
      str2 = this.ᐝ.getResources().getString(2131755511);
      localObject6 = str2;
      if (str2.startsWith(str5)) {
        localObject6 = ॱ(str2.substring(4)).intern();
      }
      localJs.setLabel((String)localObject6);
      localJs = this.ʻ;
      str2 = this.ʻ.getResources().getString(2131755508);
      localObject6 = str2;
      if (str2.startsWith(str5)) {
        localObject6 = ॱ(str2.substring(4)).intern();
      }
      localJs.setLabel((String)localObject6);
      localJs = this.ʼ;
      str2 = this.ʼ.getResources().getString(2131755509);
      localObject6 = str2;
      if (str2.startsWith(str5)) {
        localObject6 = ॱ(str2.substring(4)).intern();
      }
      localJs.setLabel((String)localObject6);
      localJs = this.ˊॱ;
      str2 = this.ˊॱ.getResources().getString(2131755512);
      localObject6 = str2;
      if (str2.startsWith(str5)) {
        localObject6 = ॱ(str2.substring(4)).intern();
      }
      localJs.setLabel((String)localObject6);
      localJs = this.ͺ;
      str2 = this.ͺ.getResources().getString(2131755510);
      localObject6 = str2;
      if (str2.startsWith(str5)) {
        localObject6 = ॱ(str2.substring(4)).intern();
      }
      localJs.setLabel((String)localObject6);
    }
    if ((0x9 & l) != 0L)
    {
      this.ᐝ.setValue(str1);
      this.ʻ.setValue((String)localObject4);
      this.ʼ.setValue((String)localObject3);
      this.ˊॱ.setValue((String)localObject5);
      this.ͺ.setValue((String)localObject2);
    }
    if ((0xA & l) != 0L) {
      this.ॱ.setTitle(str3);
    }
    if ((0xC & l) != 0L) {
      ʹ.ˊ(this.ˊ, str4);
    }
  }
  
  public void ˏ(String paramString)
  {
    this.ˋॱ = paramString;
    try
    {
      this.ॱˎ |= 0x2;
    }
    finally
    {
      paramString = finally;
      throw paramString;
    }
    ˊ(123);
    super.ʽ();
  }
  
  public boolean ˏ(int paramInt1, Object paramObject, int paramInt2)
  {
    for (;;)
    {
      switch (paramInt1)
      {
      default: 
        break;
      case 0: 
        return false;
        for (;;)
        {
          paramInt1 = ʽॱ + 31;
          ʿ = paramInt1 % 128;
          if (paramInt1 % 2 == 0) {
            break label103;
          }
          break;
        }
        paramInt1 = 0;
        continue;
        for (;;)
        {
          paramInt1 = ʽॱ + 101;
          ʿ = paramInt1 % 128;
          if (paramInt1 % 2 == 0) {
            break;
          }
          break;
        }
      case 1: 
        paramInt1 = null.length;
        return false;
        label103:
        paramInt1 = 1;
      }
    }
  }
  
  public void ॱ(Gk paramGk)
  {
    this.ॱˊ = paramGk;
    try
    {
      this.ॱˎ |= 1L;
    }
    finally
    {
      paramGk = finally;
      throw paramGk;
    }
    ˊ(15);
    super.ʽ();
  }
  
  public boolean ॱ()
  {
    try
    {
      long l = this.ॱˎ;
      if (l != 0L) {
        return true;
      }
    }
    finally
    {
      localObject = finally;
      throw localObject;
    }
    return false;
  }
}
