package o;

import android.content.res.Resources;
import android.databinding.ViewDataBinding;
import android.databinding.ViewDataBinding.If;
import android.util.SparseIntArray;
import android.view.View;
import android.widget.Button;
import android.widget.FrameLayout;
import android.widget.ImageView;
import android.widget.LinearLayout;
import android.widget.ProgressBar;
import android.widget.RelativeLayout;
import android.widget.TextView;

public class Mn
  extends ViewDataBinding
{
  private static final SparseIntArray ʼॱ;
  private static final ViewDataBinding.If ˈ;
  private static int ॱʼ;
  private static byte ॱͺ;
  private static int ᐝᐝ;
  private static int ᐧ;
  public final KZ ʻ;
  public final Ꭸ ʻॱ;
  public final у ʼ;
  public final FrameLayout ʽ;
  public final Je ʽॱ;
  private final RelativeLayout ʾ;
  public final Je ʿ;
  private final View ˉ;
  public final ImageView ˊ;
  private final ImageView ˊˊ;
  private final View ˊˋ;
  public final LinearLayout ˊॱ;
  private final TextView ˊᐝ;
  private final aA ˋˊ;
  private boolean ˋˋ;
  public final ProgressBar ˋॱ;
  private final TextView ˋᐝ;
  private String ˌ;
  private final LinearLayout ˍ;
  public final RelativeLayout ˎ;
  private final KQ ˎˎ;
  private boolean ˎˏ;
  private String ˏˎ;
  private Is ˏˏ;
  public final Je ˏॱ;
  private String ˑ;
  public final TextView ͺ;
  private boolean ͺॱ;
  private coN ـ;
  public final Button ॱ;
  private long ॱʻ = -1L;
  private boolean ॱʽ;
  public final TextView ॱˊ;
  public final Je ॱˋ;
  public final LinearLayout ॱˎ;
  public final aD ॱॱ;
  public final Je ॱᐝ;
  public final RelativeLayout ᐝ;
  public final Ꭸ ᐝॱ;
  
  /* Error */
  static
  {
    // Byte code:
    //   0: goto +30 -> 30
    //   3: getstatic 79	o/Mn:ᐧ	I
    //   6: iconst_1
    //   7: iadd
    //   8: istore_0
    //   9: iload_0
    //   10: sipush 128
    //   13: irem
    //   14: putstatic 81	o/Mn:ᐝᐝ	I
    //   17: iload_0
    //   18: iconst_2
    //   19: irem
    //   20: ifne +6 -> 26
    //   23: goto +88 -> 111
    //   26: return
    //   27: astore_1
    //   28: aload_1
    //   29: athrow
    //   30: iconst_0
    //   31: putstatic 79	o/Mn:ᐧ	I
    //   34: iconst_1
    //   35: putstatic 81	o/Mn:ᐝᐝ	I
    //   38: invokestatic 83	o/Mn:ʻॱ	()V
    //   41: invokestatic 85	o/Mn:ˏॱ	()V
    //   44: aconst_null
    //   45: putstatic 87	o/Mn:ˈ	Landroid/databinding/ViewDataBinding$If;
    //   48: new 89	android/util/SparseIntArray
    //   51: dup
    //   52: invokespecial 92	android/util/SparseIntArray:<init>	()V
    //   55: putstatic 94	o/Mn:ʼॱ	Landroid/util/SparseIntArray;
    //   58: getstatic 94	o/Mn:ʼॱ	Landroid/util/SparseIntArray;
    //   61: ldc 95
    //   63: bipush 24
    //   65: invokevirtual 99	android/util/SparseIntArray:put	(II)V
    //   68: getstatic 94	o/Mn:ʼॱ	Landroid/util/SparseIntArray;
    //   71: ldc 100
    //   73: bipush 25
    //   75: invokevirtual 99	android/util/SparseIntArray:put	(II)V
    //   78: getstatic 94	o/Mn:ʼॱ	Landroid/util/SparseIntArray;
    //   81: ldc 101
    //   83: bipush 26
    //   85: invokevirtual 99	android/util/SparseIntArray:put	(II)V
    //   88: getstatic 94	o/Mn:ʼॱ	Landroid/util/SparseIntArray;
    //   91: ldc 102
    //   93: bipush 27
    //   95: invokevirtual 99	android/util/SparseIntArray:put	(II)V
    //   98: getstatic 94	o/Mn:ʼॱ	Landroid/util/SparseIntArray;
    //   101: ldc 103
    //   103: bipush 28
    //   105: invokevirtual 99	android/util/SparseIntArray:put	(II)V
    //   108: goto -105 -> 3
    //   111: return
    //   112: astore_1
    //   113: aload_1
    //   114: athrow
    // Local variable table:
    //   start	length	slot	name	signature
    //   8	12	0	i	int
    //   27	2	1	localException1	Exception
    //   112	2	1	localException2	Exception
    // Exception table:
    //   from	to	target	type
    //   30	34	27	java/lang/Exception
    //   34	38	112	java/lang/Exception
    //   38	41	112	java/lang/Exception
    //   41	44	112	java/lang/Exception
    //   44	108	112	java/lang/Exception
  }
  
  public Mn(ˉ paramˉ, View paramView)
  {
    super(paramˉ, paramView, 4);
    paramˉ = ॱ(paramˉ, paramView, 29, ˈ, ʼॱ);
    this.ॱ = ((Button)paramˉ[23]);
    this.ॱ.setTag(null);
    this.ˎ = ((RelativeLayout)paramˉ[25]);
    this.ˊ = ((ImageView)paramˉ[1]);
    this.ˊ.setTag(null);
    this.ʽ = ((FrameLayout)paramˉ[28]);
    this.ॱॱ = ((aD)paramˉ[24]);
    this.ʼ = ((у)paramˉ[2]);
    this.ʼ.setTag(null);
    this.ʻ = ((KZ)paramˉ[5]);
    this.ʻ.setTag(null);
    this.ʾ = ((RelativeLayout)paramˉ[0]);
    this.ʾ.setTag(null);
    this.ˊᐝ = ((TextView)paramˉ[14]);
    this.ˊᐝ.setTag(null);
    this.ˊˋ = ((View)paramˉ[18]);
    this.ˊˋ.setTag(null);
    this.ˉ = ((View)paramˉ[20]);
    this.ˉ.setTag(null);
    this.ˊˊ = ((ImageView)paramˉ[3]);
    this.ˊˊ.setTag(null);
    this.ˋˊ = ((aA)paramˉ[4]);
    this.ˋˊ.setTag(null);
    this.ˋᐝ = ((TextView)paramˉ[6]);
    this.ˋᐝ.setTag(null);
    this.ˍ = ((LinearLayout)paramˉ[7]);
    this.ˍ.setTag(null);
    this.ˎˎ = ((KQ)paramˉ[9]);
    this.ˎˎ.setTag(null);
    this.ᐝ = ((RelativeLayout)paramˉ[26]);
    this.ˊॱ = ((LinearLayout)paramˉ[13]);
    this.ˊॱ.setTag(null);
    this.ͺ = ((TextView)paramˉ[22]);
    this.ͺ.setTag(null);
    this.ˏॱ = ((Je)paramˉ[21]);
    this.ˏॱ.setTag(null);
    this.ॱˊ = ((TextView)paramˉ[10]);
    this.ॱˊ.setTag(null);
    this.ˋॱ = ((ProgressBar)paramˉ[27]);
    this.ॱˎ = ((LinearLayout)paramˉ[15]);
    this.ॱˎ.setTag(null);
    this.ᐝॱ = ((Ꭸ)paramˉ[8]);
    this.ᐝॱ.setTag(null);
    this.ॱᐝ = ((Je)paramˉ[11]);
    this.ॱᐝ.setTag(null);
    this.ʻॱ = ((Ꭸ)paramˉ[12]);
    this.ʻॱ.setTag(null);
    this.ॱˋ = ((Je)paramˉ[16]);
    this.ॱˋ.setTag(null);
    this.ʿ = ((Je)paramˉ[19]);
    this.ʿ.setTag(null);
    this.ʽॱ = ((Je)paramˉ[17]);
    this.ʽॱ.setTag(null);
    ˋ(paramView);
    ॱˊ();
  }
  
  static void ʻॱ()
  {
    ॱʼ = 163;
  }
  
  private static String ˊ(int paramInt1, int paramInt2, char[] paramArrayOfChar, int paramInt3, boolean paramBoolean)
  {
    break label190;
    label17:
    char[] arrayOfChar;
    for (;;)
    {
      if (!paramBoolean)
      {
        break label101;
        paramInt1 = ᐧ + 17;
        ᐝᐝ = paramInt1 % 128;
        if (paramInt1 % 2 == 0) {
          break label259;
        }
        break;
      }
      else
      {
        paramInt1 = 72;
        break label291;
      }
      label101:
      label113:
      label190:
      for (;;)
      {
        arrayOfChar = new char[paramInt2];
        int i = 0;
        while (i < paramInt2)
        {
          arrayOfChar[i] = ((char)(paramInt1 + paramArrayOfChar[i]));
          int j = arrayOfChar[i];
          try
          {
            arrayOfChar[i] = ((char)(j - ॱʼ));
            i += 1;
          }
          catch (Exception paramArrayOfChar)
          {
            throw paramArrayOfChar;
          }
          paramInt1 = 99;
          break label291;
          break;
          for (;;)
          {
            if (paramInt1 >= paramInt2)
            {
              break label323;
              for (;;)
              {
                break;
                paramInt1 = ᐝᐝ + 125;
                ᐧ = paramInt1 % 128;
                if (paramInt1 % 2 != 0) {
                  break;
                }
              }
            }
            paramInt3 = 14;
            break label262;
            paramArrayOfChar[paramInt1] = arrayOfChar[(paramInt2 - paramInt1 - 1)];
            paramInt1 += 1;
          }
        }
        break label202;
      }
      return new String(paramArrayOfChar);
      label202:
      if (paramInt3 > 0) {
        break label221;
      }
    }
    label221:
    label259:
    for (;;)
    {
      paramArrayOfChar = new char[paramInt2];
      paramInt1 = 0;
      break label113;
      paramArrayOfChar = new char[paramInt2];
      System.arraycopy(arrayOfChar, 0, paramArrayOfChar, 0, paramInt2);
      System.arraycopy(paramArrayOfChar, 0, arrayOfChar, paramInt2 - paramInt3, paramInt3);
      System.arraycopy(paramArrayOfChar, paramInt3, arrayOfChar, 0, paramInt2 - paramInt3);
      break;
    }
    for (;;)
    {
      label262:
      switch (paramInt3)
      {
      }
      break;
      label291:
      paramArrayOfChar = arrayOfChar;
      switch (paramInt1)
      {
      }
      break label17;
      label323:
      paramInt3 = 49;
    }
  }
  
  private boolean ˊ(coN paramCoN, int paramInt)
  {
    if (paramInt == 0)
    {
      try
      {
        this.ॱʻ |= 0x4;
      }
      finally
      {
        paramCoN = finally;
        throw paramCoN;
      }
      return true;
    }
    return false;
  }
  
  private boolean ˊ(ـ<FQ> paramـ, int paramInt)
  {
    if (paramInt == 0)
    {
      try
      {
        this.ॱʻ |= 0x2;
      }
      finally
      {
        paramـ = finally;
        throw paramـ;
      }
      return true;
    }
    return false;
  }
  
  private boolean ˋ(ـ<String> paramـ, int paramInt)
  {
    if (paramInt == 0)
    {
      try
      {
        this.ॱʻ |= 0x8;
      }
      finally
      {
        paramـ = finally;
        throw paramـ;
      }
      return true;
    }
    return false;
  }
  
  /* Error */
  private String ˎ(String paramString)
  {
    // Byte code:
    //   0: goto +264 -> 264
    //   3: aload_1
    //   4: sipush 222
    //   7: bipush 10
    //   9: bipush 10
    //   11: newarray char
    //   13: dup
    //   14: iconst_0
    //   15: ldc -3
    //   17: castore
    //   18: dup
    //   19: iconst_1
    //   20: ldc -2
    //   22: castore
    //   23: dup
    //   24: iconst_2
    //   25: ldc -1
    //   27: castore
    //   28: dup
    //   29: iconst_3
    //   30: ldc_w 256
    //   33: castore
    //   34: dup
    //   35: iconst_4
    //   36: ldc_w 257
    //   39: castore
    //   40: dup
    //   41: iconst_5
    //   42: ldc -3
    //   44: castore
    //   45: dup
    //   46: bipush 6
    //   48: ldc_w 258
    //   51: castore
    //   52: dup
    //   53: bipush 7
    //   55: ldc_w 259
    //   58: castore
    //   59: dup
    //   60: bipush 8
    //   62: ldc_w 260
    //   65: castore
    //   66: dup
    //   67: bipush 9
    //   69: ldc_w 260
    //   72: castore
    //   73: iconst_4
    //   74: iconst_1
    //   75: invokestatic 262	o/Mn:ˊ	(II[CIZ)Ljava/lang/String;
    //   78: invokevirtual 266	java/lang/String:intern	()Ljava/lang/String;
    //   81: invokevirtual 270	java/lang/String:getBytes	(Ljava/lang/String;)[B
    //   84: astore_1
    //   85: aload_1
    //   86: arraylength
    //   87: newarray byte
    //   89: astore 4
    //   91: iconst_0
    //   92: istore_3
    //   93: goto +94 -> 187
    //   96: new 229	java/lang/String
    //   99: dup
    //   100: aload 4
    //   102: sipush 231
    //   105: iconst_5
    //   106: iconst_5
    //   107: newarray char
    //   109: dup
    //   110: iconst_0
    //   111: ldc_w 271
    //   114: castore
    //   115: dup
    //   116: iconst_1
    //   117: ldc_w 272
    //   120: castore
    //   121: dup
    //   122: iconst_2
    //   123: ldc_w 273
    //   126: castore
    //   127: dup
    //   128: iconst_3
    //   129: ldc_w 274
    //   132: castore
    //   133: dup
    //   134: iconst_4
    //   135: ldc_w 275
    //   138: castore
    //   139: iconst_4
    //   140: iconst_1
    //   141: invokestatic 262	o/Mn:ˊ	(II[CIZ)Ljava/lang/String;
    //   144: invokevirtual 266	java/lang/String:intern	()Ljava/lang/String;
    //   147: invokespecial 278	java/lang/String:<init>	([BLjava/lang/String;)V
    //   150: astore_1
    //   151: aload_1
    //   152: areturn
    //   153: iload_3
    //   154: istore_2
    //   155: goto +139 -> 294
    //   158: iconst_0
    //   159: istore_3
    //   160: iload_3
    //   161: tableswitch	default:+23->184, 0:+155->316, 1:+-65->96
    //   184: goto -88 -> 96
    //   187: getstatic 79	o/Mn:ᐧ	I
    //   190: istore_2
    //   191: iload_2
    //   192: bipush 95
    //   194: iadd
    //   195: istore_2
    //   196: iload_2
    //   197: sipush 128
    //   200: irem
    //   201: putstatic 81	o/Mn:ᐝᐝ	I
    //   204: iload_2
    //   205: iconst_2
    //   206: irem
    //   207: ifne +6 -> 213
    //   210: goto +48 -> 258
    //   213: goto +97 -> 310
    //   216: iconst_3
    //   217: iconst_2
    //   218: idiv
    //   219: istore_2
    //   220: iload_3
    //   221: istore_2
    //   222: goto +72 -> 294
    //   225: iload_2
    //   226: lookupswitch	default:+26->252, 38:+-73->153, 99:+-10->216
    //   252: goto -36 -> 216
    //   255: astore_1
    //   256: aload_1
    //   257: athrow
    //   258: bipush 99
    //   260: istore_2
    //   261: goto -36 -> 225
    //   264: goto -261 -> 3
    //   267: aload 4
    //   269: iload_2
    //   270: aload_1
    //   271: aload_1
    //   272: arraylength
    //   273: iload_2
    //   274: isub
    //   275: iconst_1
    //   276: isub
    //   277: baload
    //   278: getstatic 280	o/Mn:ॱͺ	B
    //   281: ixor
    //   282: i2b
    //   283: bastore
    //   284: iload_2
    //   285: iconst_1
    //   286: iadd
    //   287: istore_2
    //   288: goto +6 -> 294
    //   291: goto -24 -> 267
    //   294: aload_1
    //   295: arraylength
    //   296: istore_3
    //   297: iload_2
    //   298: iload_3
    //   299: if_icmpge +6 -> 305
    //   302: goto -144 -> 158
    //   305: iconst_1
    //   306: istore_3
    //   307: goto -147 -> 160
    //   310: bipush 38
    //   312: istore_2
    //   313: goto -88 -> 225
    //   316: getstatic 79	o/Mn:ᐧ	I
    //   319: bipush 53
    //   321: iadd
    //   322: istore_3
    //   323: iload_3
    //   324: sipush 128
    //   327: irem
    //   328: putstatic 81	o/Mn:ᐝᐝ	I
    //   331: iload_3
    //   332: iconst_2
    //   333: irem
    //   334: ifne +6 -> 340
    //   337: goto -46 -> 291
    //   340: goto -73 -> 267
    //   343: astore_1
    //   344: new 282	java/lang/RuntimeException
    //   347: dup
    //   348: aload_1
    //   349: invokespecial 285	java/lang/RuntimeException:<init>	(Ljava/lang/Throwable;)V
    //   352: athrow
    // Local variable table:
    //   start	length	slot	name	signature
    //   0	353	0	this	Mn
    //   0	353	1	paramString	String
    //   154	159	2	i	int
    //   92	242	3	j	int
    //   89	179	4	arrayOfByte	byte[]
    // Exception table:
    //   from	to	target	type
    //   187	191	255	java/lang/Exception
    //   196	204	255	java/lang/Exception
    //   3	91	343	java/io/UnsupportedEncodingException
    //   96	151	343	java/io/UnsupportedEncodingException
    //   267	284	343	java/io/UnsupportedEncodingException
    //   294	297	343	java/io/UnsupportedEncodingException
  }
  
  private boolean ˏ(ـ<FS> paramـ, int paramInt)
  {
    if (paramInt == 0)
    {
      try
      {
        this.ॱʻ |= 1L;
      }
      finally
      {
        paramـ = finally;
        throw paramـ;
      }
      return true;
    }
    return false;
  }
  
  /* Error */
  static void ˏॱ()
  {
    // Byte code:
    //   0: goto +79 -> 79
    //   3: return
    //   4: iconst_0
    //   5: istore_0
    //   6: goto +48 -> 54
    //   9: bipush 87
    //   11: putstatic 280	o/Mn:ॱͺ	B
    //   14: goto +73 -> 87
    //   17: getstatic 79	o/Mn:ᐧ	I
    //   20: iconst_1
    //   21: iadd
    //   22: istore_0
    //   23: iload_0
    //   24: sipush 128
    //   27: irem
    //   28: putstatic 81	o/Mn:ᐝᐝ	I
    //   31: iload_0
    //   32: iconst_2
    //   33: irem
    //   34: ifne +6 -> 40
    //   37: goto -33 -> 4
    //   40: goto +42 -> 82
    //   43: astore_1
    //   44: aload_1
    //   45: athrow
    //   46: bipush -102
    //   48: putstatic 280	o/Mn:ॱͺ	B
    //   51: goto +36 -> 87
    //   54: iload_0
    //   55: tableswitch	default:+21->76, 0:+-46->9, 1:+-9->46
    //   76: goto -30 -> 46
    //   79: goto -62 -> 17
    //   82: iconst_1
    //   83: istore_0
    //   84: goto -30 -> 54
    //   87: getstatic 79	o/Mn:ᐧ	I
    //   90: istore_0
    //   91: iload_0
    //   92: bipush 21
    //   94: iadd
    //   95: istore_0
    //   96: iload_0
    //   97: sipush 128
    //   100: irem
    //   101: putstatic 81	o/Mn:ᐝᐝ	I
    //   104: iload_0
    //   105: iconst_2
    //   106: irem
    //   107: ifne +6 -> 113
    //   110: goto -107 -> 3
    //   113: return
    // Local variable table:
    //   start	length	slot	name	signature
    //   5	102	0	i	int
    //   43	2	1	localException	Exception
    // Exception table:
    //   from	to	target	type
    //   87	91	43	java/lang/Exception
    //   96	104	43	java/lang/Exception
  }
  
  public void ˊ(String paramString)
  {
    this.ˑ = paramString;
    try
    {
      this.ॱʻ |= 0x40;
    }
    finally
    {
      paramString = finally;
      throw paramString;
    }
    ˊ(118);
    super.ʽ();
  }
  
  public void ˊ(boolean paramBoolean)
  {
    for (;;)
    {
      try
      {
        i = ᐝᐝ;
        i += 49;
        ᐧ = i % 128;
        if (i % 2 != 0) {
          break label71;
        }
        return;
      }
      catch (Exception localException)
      {
        int i;
        throw localException;
      }
      this.ॱʽ = paramBoolean;
      continue;
      i = ᐧ + 101;
      ᐝᐝ = i % 128;
      if (i % 2 != 0)
      {
        continue;
        label71:
        return;
      }
    }
  }
  
  public Is ˊॱ()
  {
    for (;;)
    {
      int i = ᐝᐝ + 115;
      ᐧ = i % 128;
      if (i % 2 == 0)
      {
        break label67;
        return this.ˏˏ;
      }
      for (;;)
      {
        switch (i)
        {
        case 49: 
        default: 
          break;
          i = 49;
          break;
        case 10: 
          label67:
          Is localIs = this.ˏˏ;
          i = 23 / 0;
          return localIs;
          i = 10;
        }
      }
    }
  }
  
  public void ˋ(String paramString)
  {
    this.ˏˎ = paramString;
    try
    {
      this.ॱʻ |= 0x1000;
    }
    finally
    {
      paramString = finally;
      throw paramString;
    }
    ˊ(112);
    super.ʽ();
  }
  
  public void ˋ(Is paramIs)
  {
    this.ˏˏ = paramIs;
    try
    {
      this.ॱʻ |= 0x80;
    }
    finally
    {
      paramIs = finally;
      throw paramIs;
    }
    ˊ(100);
    super.ʽ();
  }
  
  public void ˋ(coN paramCoN)
  {
    ˎ(2, paramCoN);
    this.ـ = paramCoN;
    try
    {
      this.ॱʻ |= 0x4;
    }
    finally
    {
      paramCoN = finally;
      throw paramCoN;
    }
    ˊ(86);
    super.ʽ();
  }
  
  public void ˋ(boolean paramBoolean)
  {
    this.ˋˋ = paramBoolean;
    try
    {
      this.ॱʻ |= 0x10;
    }
    finally
    {
      localObject = finally;
      throw localObject;
    }
    ˊ(73);
    super.ʽ();
  }
  
  public boolean ˋॱ()
  {
    break label72;
    int i = ᐧ + 115;
    ᐝᐝ = i % 128;
    boolean bool;
    if (i % 2 != 0) {
      return bool;
    }
    return bool;
    label31:
    i = ᐝᐝ + 35;
    ᐧ = i % 128;
    if (i % 2 == 0) {
      break label66;
    }
    for (;;)
    {
      bool = this.ͺॱ;
      break;
      label66:
      i = 15;
      break label89;
      label72:
      break label31;
      bool = this.ͺॱ;
      i = null.length;
      break;
      i = 71;
      label89:
      switch (i)
      {
      }
    }
  }
  
  public void ˎ(boolean paramBoolean)
  {
    this.ͺॱ = paramBoolean;
    try
    {
      this.ॱʻ |= 0x400;
    }
    finally
    {
      localObject = finally;
      throw localObject;
    }
    ˊ(59);
    super.ʽ();
  }
  
  public void ˏ()
  {
    String str4 = ˊ(176, 4, new char[] { -1, -2, 13, -8 }, 4, true).intern();
    try
    {
      l2 = this.ॱʻ;
      this.ॱʻ = 0L;
    }
    finally
    {
      localObject1 = finally;
      throw localObject1;
    }
    int i12 = 0;
    float f3 = 0.0F;
    boolean bool4 = this.ˋˋ;
    Object localObject37 = null;
    Object localObject3 = null;
    Object localObject15 = null;
    Object localObject10 = null;
    int i2 = 0;
    int k = 0;
    int i15 = 0;
    int i10 = 0;
    boolean bool2 = false;
    boolean bool1 = false;
    boolean bool7 = false;
    String str2 = this.ˌ;
    int i3 = 0;
    int i19 = 0;
    int i8 = 0;
    int i13 = 0;
    Object localObject24 = null;
    String str1 = this.ˑ;
    int i16 = 0;
    Object localObject31 = null;
    boolean bool5 = false;
    Object localObject12 = null;
    Object localObject30 = null;
    Is localIs = this.ˏˏ;
    Object localObject23 = null;
    Object localObject25 = null;
    Object localObject4 = null;
    Object localObject16 = null;
    Object localObject11 = null;
    Object localObject13 = null;
    Object localObject28 = null;
    Object localObject17 = null;
    Object localObject2 = null;
    Object localObject5 = null;
    Object localObject22 = null;
    Object localObject36 = null;
    boolean bool8 = this.ˎˏ;
    Object localObject26 = null;
    Object localObject6 = null;
    Object localObject18 = null;
    Object localObject35 = null;
    boolean bool3 = this.ͺॱ;
    int i7 = 0;
    int n = 0;
    int i9 = 0;
    Object localObject29 = null;
    boolean bool6 = false;
    int i11 = 0;
    int i4 = 0;
    int i20 = 0;
    int i18 = 0;
    int i6 = 0;
    int j = 0;
    Object localObject7 = null;
    Object localObject19 = null;
    Object localObject34 = null;
    int i5 = 0;
    Object localObject8 = null;
    Object localObject20 = null;
    Object localObject33 = null;
    int i14 = 0;
    float f2 = 0.0F;
    float f4 = 0.0F;
    Object localObject9 = null;
    Object localObject21 = null;
    Object localObject32 = null;
    String str3 = this.ˏˎ;
    coN localCoN = this.ـ;
    int i17 = 0;
    Object localObject27 = null;
    long l1 = l2;
    if ((0x4040 & l2) != 0L)
    {
      if (str1 == null) {
        i = 1;
      } else {
        i = 0;
      }
      l1 = l2;
      i5 = i;
      if ((0x4040 & l2) != 0L) {
        if (i != 0)
        {
          l1 = l2 | 0x100000000;
          i5 = i;
        }
        else
        {
          l1 = l2 | 0x80000000;
          i5 = i;
        }
      }
    }
    long l2 = l1;
    Object localObject14 = localObject26;
    if ((0x448B & l1) != 0L)
    {
      l2 = l1;
      i = k;
      if ((0x4080 & l1) != 0L)
      {
        localObject2 = localObject37;
        bool1 = bool7;
        localObject12 = localObject36;
        localObject13 = localObject35;
        localObject14 = localObject34;
        if (localIs != null)
        {
          localObject2 = localIs.currency;
          localObject10 = localIs.reason;
          bool1 = localIs.ˊ();
          localObject11 = localIs.ˋ();
          localObject12 = localIs.status;
          localObject13 = localIs.statusDate;
          localObject14 = localIs.statusLabel;
        }
        l2 = l1;
        if ((0x4080 & l1) != 0L) {
          if (bool1) {
            l2 = l1 | 0x100000;
          } else {
            l2 = l1 | 0x80000;
          }
        }
        localObject15 = localObject33;
        localObject16 = localObject32;
        if (localObject2 != null)
        {
          localObject15 = ((Ep)localObject2).ˊ();
          localObject16 = ((Ep)localObject2).ˊ();
        }
        if (bool1) {
          k = 0;
        } else {
          k = 8;
        }
        if (localObject12 == FV.ACCEPTED) {
          i = 1;
        } else {
          i = 0;
        }
        if (localObject12 == FV.DECLINED) {
          m = 1;
        } else {
          m = 0;
        }
        l1 = l2;
        if ((0x4080 & l2) != 0L) {
          if (i != 0) {
            l1 = l2 | 0x400000000;
          } else {
            l1 = l2 | 0x200000000;
          }
        }
        long l3 = l1;
        if ((0x4080 & l1) != 0L) {
          if (m != 0) {
            l3 = l1 | 0x100000000000;
          } else {
            l3 = l1 | 0x80000000000;
          }
        }
        if (i != 0)
        {
          localObject3 = this.ʽॱ.getResources().getString(2131755478);
          localObject2 = localObject3;
          if (((String)localObject3).startsWith(str4)) {
            localObject2 = ˎ(((String)localObject3).substring(4)).intern();
          }
          l2 = l3;
          localObject3 = localObject10;
          i = k;
          bool2 = bool1;
          localObject4 = localObject11;
          localObject5 = localObject12;
          localObject6 = localObject13;
          j = m;
          localObject7 = localObject14;
          localObject8 = localObject15;
          localObject9 = localObject16;
        }
        else
        {
          localObject17 = this.ʽॱ.getResources().getString(2131755480);
          l2 = l3;
          localObject3 = localObject10;
          i = k;
          bool2 = bool1;
          localObject4 = localObject11;
          localObject2 = localObject17;
          localObject5 = localObject12;
          localObject6 = localObject13;
          j = m;
          localObject7 = localObject14;
          localObject8 = localObject15;
          localObject9 = localObject16;
          if (((String)localObject17).startsWith(str4))
          {
            localObject2 = ˎ(((String)localObject17).substring(4)).intern();
            localObject9 = localObject16;
            localObject8 = localObject15;
            localObject7 = localObject14;
            j = m;
            localObject6 = localObject13;
            localObject5 = localObject12;
            localObject4 = localObject11;
            bool2 = bool1;
            i = k;
            localObject3 = localObject10;
            l2 = l3;
          }
        }
      }
      localObject10 = localObject30;
      if ((0x4081 & l2) != 0L)
      {
        localObject11 = localObject31;
        if (localIs != null) {
          localObject11 = localIs.contactPerson;
        }
        ˎ(0, (ˑ)localObject11);
        localObject10 = localObject30;
        if (localObject11 != null) {
          localObject10 = (FS)((ـ)localObject11).ˏ();
        }
      }
      l1 = l2;
      k = i19;
      m = n;
      i1 = i20;
      f1 = f4;
      if ((0x4480 & l2) != 0L)
      {
        if (localIs == null) {
          n = 1;
        } else {
          n = 0;
        }
        l1 = l2;
        if ((0x4080 & l2) != 0L) {
          if (n != 0) {
            l1 = l2 | 0x1000000 | 0x40000000000 | 0x4000000000000;
          } else {
            l1 = l2 | 0x800000 | 0x20000000000 | 0x2000000000000;
          }
        }
        l2 = l1;
        if ((0x4480 & l1) != 0L) {
          if (n != 0) {
            l2 = l1 | 0x1000000000 | 0x10000000000000;
          } else {
            l2 = l1 | 0x800000000 | 0x8000000000000;
          }
        }
        l1 = l2;
        k = i19;
        m = n;
        i1 = i20;
        f1 = f4;
        if ((0x4080 & l2) != 0L)
        {
          if (n != 0) {
            k = ˋ(this.ʻॱ, 17170445);
          } else {
            k = ˋ(this.ʻॱ, 2131099797);
          }
          if (n != 0) {
            i1 = 4;
          } else {
            i1 = 0;
          }
          if (n != 0)
          {
            f1 = this.ʻॱ.getResources().getDimension(2131165260);
            l1 = l2;
            m = n;
          }
          else
          {
            f1 = this.ʻॱ.getResources().getDimension(2131165259);
            m = n;
            l1 = l2;
          }
        }
      }
      localObject11 = localObject28;
      if ((0x4082 & l1) != 0L)
      {
        localObject12 = localObject29;
        if (localIs != null) {
          localObject12 = localIs.phoneNumber;
        }
        ˎ(1, (ˑ)localObject12);
        localObject11 = localObject28;
        if (localObject12 != null) {
          localObject11 = (FQ)((ـ)localObject12).ˏ();
        }
      }
      l2 = l1;
      localObject15 = localObject3;
      i2 = i;
      bool1 = bool2;
      i3 = k;
      localObject12 = localObject10;
      localObject16 = localObject4;
      localObject13 = localObject11;
      localObject17 = localObject2;
      localObject22 = localObject5;
      localObject14 = localObject26;
      localObject18 = localObject6;
      i7 = m;
      i4 = i1;
      i6 = j;
      localObject19 = localObject7;
      localObject20 = localObject8;
      f2 = f1;
      localObject21 = localObject9;
      if ((0x4088 & l1) != 0L)
      {
        localObject12 = localObject27;
        if (localIs != null) {
          localObject12 = localIs.transferDetail;
        }
        ˎ(3, (ˑ)localObject12);
        localObject13 = localObject25;
        if (localObject12 != null) {
          localObject13 = (String)((ـ)localObject12).ˏ();
        }
        localObject14 = aq.ॱ((String)localObject13);
        localObject21 = localObject9;
        f2 = f1;
        localObject20 = localObject8;
        localObject19 = localObject7;
        i6 = j;
        i4 = i1;
        i7 = m;
        localObject18 = localObject6;
        localObject22 = localObject5;
        localObject17 = localObject2;
        localObject13 = localObject11;
        localObject16 = localObject4;
        localObject12 = localObject10;
        i3 = k;
        bool1 = bool2;
        i2 = i;
        localObject15 = localObject3;
        l2 = l1;
      }
    }
    l1 = l2;
    localObject3 = localObject24;
    int m = i18;
    if ((0x4280 & l2) != 0L)
    {
      l1 = l2;
      if ((0x4200 & l2) != 0L) {
        if (bool8) {
          l1 = l2 | 0x4000000 | 0x1000000000000;
        } else {
          l1 = l2 | 0x2000000 | 0x800000000000;
        }
      }
      l2 = l1;
      if ((0x4280 & l1) != 0L) {
        if (bool8) {
          l2 = l1 | 0x400000000000;
        } else {
          l2 = l1 | 0x200000000000;
        }
      }
      l1 = l2;
      localObject3 = localObject24;
      m = i18;
      if ((0x4200 & l2) != 0L)
      {
        if (bool8)
        {
          localObject3 = this.ॱ.getResources().getString(2131755444);
          localObject2 = localObject3;
          if (((String)localObject3).startsWith(str4)) {
            localObject2 = ˎ(((String)localObject3).substring(4)).intern();
          }
        }
        else
        {
          localObject3 = this.ॱ.getResources().getString(2131755475);
          localObject2 = localObject3;
          if (((String)localObject3).startsWith(str4)) {
            localObject2 = ˎ(((String)localObject3).substring(4)).intern();
          }
        }
        if (bool8)
        {
          m = 0;
          l1 = l2;
          localObject3 = localObject2;
        }
        else
        {
          m = 8;
          localObject3 = localObject2;
          l1 = l2;
        }
      }
    }
    l2 = l1;
    int i1 = i8;
    i8 = i16;
    n = i17;
    if ((0x4014 & l1) != 0L)
    {
      bool2 = bool6;
      if (localCoN != null) {
        bool2 = localCoN.ˊ();
      }
      l2 = l1;
      if ((0x4004 & l1) != 0L) {
        if (bool2) {
          l2 = l1 | 0x10000000 | 0x40000000000000;
        } else {
          l2 = l1 | 0x8000000 | 0x20000000000000;
        }
      }
      if (!bool2) {
        i = 1;
      } else {
        i = 0;
      }
      l1 = l2;
      if ((0x4014 & l2) != 0L) {
        if (i != 0) {
          l1 = l2 | 0x40000000;
        } else {
          l1 = l2 | 0x20000000;
        }
      }
      l2 = l1;
      i1 = i;
      i8 = i16;
      n = i17;
      if ((0x4004 & l1) != 0L)
      {
        if (bool2) {
          j = 0;
        } else {
          j = 8;
        }
        if (bool2)
        {
          n = 4;
          l2 = l1;
          i1 = i;
          i8 = j;
        }
        else
        {
          n = 0;
          i8 = j;
          i1 = i;
          l2 = l1;
        }
      }
    }
    j = i15;
    if ((0x80000000000 & l2) != 0L) {
      if (localObject22 == FV.CANCELED) {
        j = 1;
      } else {
        j = 0;
      }
    }
    l1 = l2;
    int i = i14;
    if ((0x400000000000 & l2) != 0L)
    {
      if (localIs != null) {
        bool1 = localIs.ˊ();
      }
      l1 = l2;
      if ((0x4080 & l2) != 0L) {
        if (bool1) {
          l1 = l2 | 0x100000;
        } else {
          l1 = l2 | 0x80000;
        }
      }
      if (!bool1) {
        i = 1;
      } else {
        i = 0;
      }
    }
    localObject2 = localObject23;
    if ((0x4040 & l1) != 0L) {
      if (i5 != 0)
      {
        localObject4 = this.ʻ.getResources().getString(2131755466);
        localObject2 = localObject4;
        if (((String)localObject4).startsWith(str4)) {
          localObject2 = ˎ(((String)localObject4).substring(4)).intern();
        }
      }
      else
      {
        localObject2 = str1;
      }
    }
    k = i13;
    if ((0x8000800000000 & l1) != 0L)
    {
      k = i13;
      if ((0x800000000 & l1) != 0L) {
        if (!bool3) {
          k = 1;
        } else {
          k = 0;
        }
      }
    }
    bool1 = bool5;
    if ((0x4014 & l1) != 0L) {
      if (i1 != 0) {
        bool1 = bool4;
      } else {
        bool1 = false;
      }
    }
    l2 = l1;
    i5 = i12;
    float f1 = f3;
    i1 = i11;
    if ((0x4480 & l1) != 0L)
    {
      if (i7 != 0) {
        k = 1;
      }
      if (i7 != 0) {
        bool2 = true;
      } else {
        bool2 = bool3;
      }
      l2 = l1;
      if ((0x4480 & l1) != 0L) {
        if (k != 0) {
          l2 = l1 | 0x10000;
        } else {
          l2 = l1 | 0x8000;
        }
      }
      l1 = l2;
      if ((0x4480 & l2) != 0L) {
        if (bool2) {
          l1 = l2 | 0x40000 | 0x10000000000;
        } else {
          l1 = l2 | 0x20000 | 0x8000000000;
        }
      }
      if (k != 0) {
        k = 4;
      } else {
        k = 0;
      }
      if (bool2) {
        f1 = this.ˍ.getResources().getDimension(2131165398);
      } else {
        f1 = this.ˍ.getResources().getDimension(2131165399);
      }
      if (bool2)
      {
        i1 = 4;
        l2 = l1;
        i5 = k;
      }
      else
      {
        i1 = 0;
        i5 = k;
        l2 = l1;
      }
    }
    l1 = l2;
    k = i10;
    if ((0x4080 & l2) != 0L)
    {
      if (i6 != 0) {
        j = 1;
      }
      l1 = l2;
      if ((0x4080 & l2) != 0L) {
        if (j != 0) {
          l1 = l2 | 0x400000;
        } else {
          l1 = l2 | 0x200000;
        }
      }
      if (j != 0) {
        k = 0;
      } else {
        k = 8;
      }
    }
    l2 = l1;
    j = i9;
    if ((0x4280 & l1) != 0L)
    {
      if (!bool8) {
        i = 0;
      }
      l2 = l1;
      if ((0x4280 & l1) != 0L) {
        if (i != 0) {
          l2 = l1 | 0x4000000000;
        } else {
          l2 = l1 | 0x2000000000;
        }
      }
      if (i != 0) {
        j = 0;
      } else {
        j = 8;
      }
    }
    if ((0x4014 & l2) != 0L) {
      this.ॱ.setEnabled(bool1);
    }
    if ((0x4200 & l2) != 0L)
    {
      ʹ.ˊ(this.ॱ, (CharSequence)localObject3);
      this.ˊˋ.setVisibility(m);
      this.ʿ.setVisibility(m);
    }
    if ((0x4080 & l2) != 0L)
    {
      this.ॱ.setVisibility(i4);
      this.ˉ.setVisibility(k);
      this.ͺ.setVisibility(i2);
      this.ˏॱ.setVisibility(k);
      this.ˏॱ.setValue((String)localObject15);
      this.ᐝॱ.setVisibility(i4);
      this.ॱᐝ.setValue((String)localObject16);
      this.ॱᐝ.setValueInfo(localObject21);
      this.ʻॱ.setCardBackgroundColor(i3);
      this.ʻॱ.setCardElevation(f2);
      this.ʿ.setLabel(localObject19);
      this.ʿ.setValue(localObject18);
      this.ʽॱ.setLabel((String)localObject17);
      this.ʽॱ.setValue((String)localObject16);
      this.ʽॱ.setValueInfo(localObject20);
    }
    if ((0x4000 & l2) != 0L)
    {
      r.ˊ(this.ˊ, ˊ(253, 77, new char[] { 8, 26, 22, 7, 31, -45, 11, 20, -44, 8, 26, 24, 18, -44, 24, 21, -43, 8, 26, 29, 7, 18, 18, 11, 26, -43, 7, 22, 15, -43, 28, -41, -43, 25, 11, 26, 26, 15, 20, 13, 25, -43, 26, 14, 11, 19, 11, -17, 19, 7, 13, 11, -43, -24, -25, -23, -15, -19, -8, -11, -5, -12, -22, 5, -17, -13, -25, -19, -21, 14, 26, 26, 22, 25, -32, -43, -43 }, 69, false).intern(), ॱ(this.ˊ, 2131230823), true);
      this.ʻ.setViewPagerHeight(this.ʻ.getResources().getDimension(2131165400));
      localObject5 = this.ˊᐝ;
      localObject4 = this.ˊᐝ.getResources().getString(2131755246);
      localObject3 = localObject4;
      if (((String)localObject4).startsWith(str4)) {
        localObject3 = ˎ(((String)localObject4).substring(4)).intern();
      }
      ʹ.ˊ((TextView)localObject5, (CharSequence)localObject3);
      this.ˋˊ.setShadowBottom(ॱ(this.ˋˊ, 2131231257));
      this.ˋˊ.setShadowTop(ॱ(this.ˋˊ, 2131231258));
      this.ˎˎ.setShowPhoneType(false);
      localObject5 = this.ͺ;
      localObject4 = this.ͺ.getResources().getString(2131755084);
      localObject3 = localObject4;
      if (((String)localObject4).startsWith(str4)) {
        localObject3 = ˎ(((String)localObject4).substring(4)).intern();
      }
      ʹ.ˊ((TextView)localObject5, (CharSequence)localObject3);
      localObject5 = this.ˏॱ;
      localObject4 = this.ˏॱ.getResources().getString(2131755421);
      localObject3 = localObject4;
      if (((String)localObject4).startsWith(str4)) {
        localObject3 = ˎ(((String)localObject4).substring(4)).intern();
      }
      ((Je)localObject5).setLabel((String)localObject3);
      localObject5 = this.ॱˋ;
      localObject4 = this.ॱˋ.getResources().getString(2131755477);
      localObject3 = localObject4;
      if (((String)localObject4).startsWith(str4)) {
        localObject3 = ˎ(((String)localObject4).substring(4)).intern();
      }
      ((Je)localObject5).setLabel((String)localObject3);
    }
    if ((0x4020 & l2) != 0L) {
      this.ʼ.setTitle(str2);
    }
    if ((0x4480 & l2) != 0L)
    {
      this.ʻ.setVisibility(i5);
      this.ˋᐝ.setVisibility(i1);
      A.ˋ(this.ˍ, f1, 0.0F, 0.0F, 0.0F);
    }
    if ((0x4040 & l2) != 0L)
    {
      this.ʻ.setPaymentHint((String)localObject2);
      ʹ.ˊ(this.ˋᐝ, str1);
    }
    if ((0x4280 & l2) != 0L) {
      this.ˊˊ.setVisibility(j);
    }
    if ((0x4081 & l2) != 0L) {
      this.ˎˎ.setContactPerson((FS)localObject12);
    }
    if ((0x4082 & l2) != 0L) {
      this.ˎˎ.setPhoneNumber((FQ)localObject13);
    }
    if ((0x4004 & l2) != 0L)
    {
      this.ˊॱ.setVisibility(i8);
      this.ॱˎ.setVisibility(n);
    }
    if ((0x5000 & l2) != 0L) {
      ʹ.ˊ(this.ॱˊ, str3);
    }
    if ((0x4088 & l2) != 0L) {
      this.ॱˋ.setValue((String)localObject14);
    }
  }
  
  /* Error */
  public boolean ˏ(int paramInt1, Object paramObject, int paramInt2)
  {
    // Byte code:
    //   0: goto +75 -> 75
    //   3: aload_0
    //   4: aload_2
    //   5: checkcast 418	o/ـ
    //   8: iload_3
    //   9: invokespecial 663	o/Mn:ˏ	(Lo/ـ;I)Z
    //   12: istore 5
    //   14: goto +67 -> 81
    //   17: iconst_0
    //   18: ireturn
    //   19: aload_0
    //   20: aload_2
    //   21: checkcast 418	o/ـ
    //   24: iload_3
    //   25: invokespecial 665	o/Mn:ˊ	(Lo/ـ;I)Z
    //   28: ireturn
    //   29: aload_0
    //   30: aload_2
    //   31: checkcast 418	o/ـ
    //   34: iload_3
    //   35: invokespecial 667	o/Mn:ˋ	(Lo/ـ;I)Z
    //   38: ireturn
    //   39: iload_1
    //   40: tableswitch	default:+32->72, 0:+-37->3, 1:+-21->19, 2:+128->168, 3:+-11->29
    //   72: goto -55 -> 17
    //   75: goto +63 -> 138
    //   78: goto -39 -> 39
    //   81: getstatic 79	o/Mn:ᐧ	I
    //   84: bipush 111
    //   86: iadd
    //   87: istore_1
    //   88: iload_1
    //   89: sipush 128
    //   92: irem
    //   93: putstatic 81	o/Mn:ᐝᐝ	I
    //   96: iload_1
    //   97: iconst_2
    //   98: irem
    //   99: ifne +6 -> 105
    //   102: iload 5
    //   104: ireturn
    //   105: iload 5
    //   107: ireturn
    //   108: astore_2
    //   109: aload_2
    //   110: athrow
    //   111: getstatic 79	o/Mn:ᐧ	I
    //   114: bipush 113
    //   116: iadd
    //   117: istore_1
    //   118: iload_1
    //   119: sipush 128
    //   122: irem
    //   123: putstatic 81	o/Mn:ᐝᐝ	I
    //   126: iload_1
    //   127: iconst_2
    //   128: irem
    //   129: ifne +6 -> 135
    //   132: iload 5
    //   134: ireturn
    //   135: iload 5
    //   137: ireturn
    //   138: getstatic 81	o/Mn:ᐝᐝ	I
    //   141: bipush 89
    //   143: iadd
    //   144: istore 4
    //   146: iload 4
    //   148: sipush 128
    //   151: irem
    //   152: putstatic 79	o/Mn:ᐧ	I
    //   155: iload 4
    //   157: iconst_2
    //   158: irem
    //   159: ifeq +6 -> 165
    //   162: goto -84 -> 78
    //   165: goto -126 -> 39
    //   168: aload_0
    //   169: aload_2
    //   170: checkcast 496	o/coN
    //   173: iload_3
    //   174: invokespecial 669	o/Mn:ˊ	(Lo/coN;I)Z
    //   177: istore 5
    //   179: goto -68 -> 111
    // Local variable table:
    //   start	length	slot	name	signature
    //   0	182	0	this	Mn
    //   0	182	1	paramInt1	int
    //   0	182	2	paramObject	Object
    //   0	182	3	paramInt2	int
    //   144	15	4	i	int
    //   12	166	5	bool	boolean
    // Exception table:
    //   from	to	target	type
    //   138	146	108	java/lang/Exception
    //   146	155	108	java/lang/Exception
  }
  
  /* Error */
  public boolean ͺ()
  {
    // Byte code:
    //   0: goto +76 -> 76
    //   3: iload_1
    //   4: tableswitch	default:+24->28, 0:+143->147, 1:+62->66
    //   28: goto +38 -> 66
    //   31: astore_3
    //   32: aload_3
    //   33: athrow
    //   34: iconst_0
    //   35: istore_1
    //   36: goto +82 -> 118
    //   39: getstatic 81	o/Mn:ᐝᐝ	I
    //   42: bipush 109
    //   44: iadd
    //   45: istore_1
    //   46: iload_1
    //   47: sipush 128
    //   50: irem
    //   51: putstatic 79	o/Mn:ᐧ	I
    //   54: iload_1
    //   55: iconst_2
    //   56: irem
    //   57: ifeq +6 -> 63
    //   60: goto +53 -> 113
    //   63: goto +45 -> 108
    //   66: aload_0
    //   67: getfield 300	o/Mn:ॱʽ	Z
    //   70: istore_2
    //   71: goto +8 -> 79
    //   74: iload_2
    //   75: ireturn
    //   76: goto -37 -> 39
    //   79: getstatic 81	o/Mn:ᐝᐝ	I
    //   82: istore_1
    //   83: iload_1
    //   84: bipush 21
    //   86: iadd
    //   87: istore_1
    //   88: iload_1
    //   89: sipush 128
    //   92: irem
    //   93: putstatic 79	o/Mn:ᐧ	I
    //   96: iload_1
    //   97: iconst_2
    //   98: irem
    //   99: ifeq +6 -> 105
    //   102: goto -68 -> 34
    //   105: goto +37 -> 142
    //   108: iconst_1
    //   109: istore_1
    //   110: goto -107 -> 3
    //   113: iconst_0
    //   114: istore_1
    //   115: goto -112 -> 3
    //   118: iload_1
    //   119: tableswitch	default:+21->140, 0:+41->160, 1:+-45->74
    //   140: iload_2
    //   141: ireturn
    //   142: iconst_1
    //   143: istore_1
    //   144: goto -26 -> 118
    //   147: aload_0
    //   148: getfield 300	o/Mn:ॱʽ	Z
    //   151: istore_2
    //   152: new 671	java/lang/NullPointerException
    //   155: dup
    //   156: invokespecial 672	java/lang/NullPointerException:<init>	()V
    //   159: athrow
    //   160: aconst_null
    //   161: arraylength
    //   162: istore_1
    //   163: iload_2
    //   164: ireturn
    // Local variable table:
    //   start	length	slot	name	signature
    //   0	165	0	this	Mn
    //   3	160	1	i	int
    //   70	94	2	bool	boolean
    //   31	2	3	localException	Exception
    // Exception table:
    //   from	to	target	type
    //   79	83	31	java/lang/Exception
    //   88	96	31	java/lang/Exception
  }
  
  public void ॱ(String paramString)
  {
    this.ˌ = paramString;
    try
    {
      this.ॱʻ |= 0x20;
    }
    finally
    {
      paramString = finally;
      throw paramString;
    }
    ˊ(123);
    super.ʽ();
  }
  
  public void ॱ(boolean paramBoolean)
  {
    this.ˎˏ = paramBoolean;
    try
    {
      this.ॱʻ |= 0x200;
    }
    finally
    {
      localObject = finally;
      throw localObject;
    }
    ˊ(87);
    super.ʽ();
  }
  
  public boolean ॱ()
  {
    try
    {
      long l = this.ॱʻ;
      if (l != 0L) {
        return true;
      }
    }
    finally
    {
      localObject = finally;
      throw localObject;
    }
    return false;
  }
  
  public void ॱˊ()
  {
    try
    {
      this.ॱʻ = 16384L;
    }
    finally
    {
      localObject = finally;
      throw localObject;
    }
    ʽ();
  }
}
