package o;

import android.content.res.Resources;
import android.databinding.ViewDataBinding;
import android.databinding.ViewDataBinding.If;
import android.util.SparseIntArray;
import android.view.View;
import android.widget.FrameLayout;
import android.widget.ImageView;
import android.widget.LinearLayout;
import android.widget.ProgressBar;
import android.widget.RelativeLayout;
import android.widget.TextView;
import java.io.UnsupportedEncodingException;
import java.math.BigDecimal;

public class Mo
  extends ViewDataBinding
{
  private static final SparseIntArray ʽॱ;
  private static final ViewDataBinding.If ʿ;
  private static byte ॱʼ;
  private static char[] ᐝˊ;
  private static int ᐝᐝ = 0;
  private static char ᐧ;
  private static int ᐨ = 1;
  public final KZ ʻ;
  public final Je ʻॱ;
  public final TextView ʼ;
  private final RelativeLayout ʼॱ;
  public final ProgressBar ʽ;
  public final Je ʾ;
  private final TextView ˈ;
  private final aA ˉ;
  public final FrameLayout ˊ;
  private final View ˊˊ;
  private final View ˊˋ;
  public final LinearLayout ˊॱ;
  private final ImageView ˊᐝ;
  private final View ˋˊ;
  private final TextView ˋˋ;
  public final TextView ˋॱ;
  private boolean ˋᐝ;
  private coN ˌ;
  private final KQ ˍ;
  public final ImageView ˎ;
  private final LinearLayout ˎˎ;
  private String ˎˏ;
  private FW ˏˎ;
  private String ˏˏ;
  public final Ꭸ ˏॱ;
  private boolean ˑ;
  public final у ͺ;
  private FS ͺॱ;
  private boolean ـ;
  public final KY ॱ;
  private long ॱʻ = -1L;
  private boolean ॱʽ;
  public final Je ॱˊ;
  public final Ꭸ ॱˋ;
  public final Je ॱˎ;
  private BigDecimal ॱͺ;
  public final LinearLayout ॱॱ;
  public final Je ॱᐝ;
  public final RelativeLayout ᐝ;
  public final Je ᐝॱ;
  
  static
  {
    ॱˋ();
    ˊॱ();
    ʿ = null;
    ʽॱ = new SparseIntArray();
    ʽॱ.put(2131296586, 27);
    ʽॱ.put(2131296654, 28);
    break label52;
    return;
    label52:
    int i = ᐝᐝ + 57;
    ᐨ = i % 128;
    if (i % 2 != 0) {}
    for (i = 93;; i = 19)
    {
      switch (i)
      {
      }
      throw new NullPointerException();
    }
  }
  
  public Mo(ˉ paramˉ, View paramView)
  {
    super(paramˉ, paramView, 1);
    paramˉ = ॱ(paramˉ, paramView, 29, ʿ, ʽॱ);
    this.ˎ = ((ImageView)paramˉ[1]);
    this.ˎ.setTag(null);
    this.ˊ = ((FrameLayout)paramˉ[25]);
    this.ˊ.setTag(null);
    this.ॱ = ((KY)paramˉ[26]);
    this.ॱ.setTag(null);
    this.ʻ = ((KZ)paramˉ[5]);
    this.ʻ.setTag(null);
    this.ʼॱ = ((RelativeLayout)paramˉ[0]);
    this.ʼॱ.setTag(null);
    this.ˈ = ((TextView)paramˉ[14]);
    this.ˈ.setTag(null);
    this.ˊˋ = ((View)paramˉ[17]);
    this.ˊˋ.setTag(null);
    this.ˊˊ = ((View)paramˉ[19]);
    this.ˊˊ.setTag(null);
    this.ˋˊ = ((View)paramˉ[22]);
    this.ˋˊ.setTag(null);
    this.ˊᐝ = ((ImageView)paramˉ[3]);
    this.ˊᐝ.setTag(null);
    this.ˉ = ((aA)paramˉ[4]);
    this.ˉ.setTag(null);
    this.ˋˋ = ((TextView)paramˉ[6]);
    this.ˋˋ.setTag(null);
    this.ˎˎ = ((LinearLayout)paramˉ[7]);
    this.ˎˎ.setTag(null);
    this.ˍ = ((KQ)paramˉ[9]);
    this.ˍ.setTag(null);
    this.ᐝ = ((RelativeLayout)paramˉ[27]);
    this.ॱॱ = ((LinearLayout)paramˉ[13]);
    this.ॱॱ.setTag(null);
    this.ʼ = ((TextView)paramˉ[24]);
    this.ʼ.setTag(null);
    this.ʽ = ((ProgressBar)paramˉ[28]);
    this.ͺ = ((у)paramˉ[2]);
    this.ͺ.setTag(null);
    this.ˊॱ = ((LinearLayout)paramˉ[15]);
    this.ˊॱ.setTag(null);
    this.ॱˊ = ((Je)paramˉ[18]);
    this.ॱˊ.setTag(null);
    this.ˏॱ = ((Ꭸ)paramˉ[8]);
    this.ˏॱ.setTag(null);
    this.ˋॱ = ((TextView)paramˉ[10]);
    this.ˋॱ.setTag(null);
    this.ॱˎ = ((Je)paramˉ[11]);
    this.ॱˎ.setTag(null);
    this.ॱˋ = ((Ꭸ)paramˉ[12]);
    this.ॱˋ.setTag(null);
    this.ᐝॱ = ((Je)paramˉ[16]);
    this.ᐝॱ.setTag(null);
    this.ʻॱ = ((Je)paramˉ[23]);
    this.ʻॱ.setTag(null);
    this.ॱᐝ = ((Je)paramˉ[21]);
    this.ॱᐝ.setTag(null);
    this.ʾ = ((Je)paramˉ[20]);
    this.ʾ.setTag(null);
    ˋ(paramView);
    ॱˊ();
  }
  
  private String ˊ(String paramString)
  {
    break label306;
    label3:
    int i = 12 / 0;
    return paramString;
    label16:
    do
    {
      i = 59;
      break;
      i = ᐨ + 43;
      ᐝᐝ = i % 128;
    } while (i % 2 != 0);
    break label279;
    break label309;
    byte[] arrayOfByte;
    label220:
    int j;
    for (;;)
    {
      try
      {
        paramString = paramString.getBytes(ˊ(new char[] { 33, 47, 32, 5, 67, 67, 43, 44, 2, 25 }, 10, (byte)11).intern());
        arrayOfByte = new byte[paramString.length];
        i = 0;
      }
      catch (UnsupportedEncodingException paramString)
      {
        throw new RuntimeException(paramString);
      }
      switch (i)
      {
      case 59: 
      default: 
        break label3;
        paramString = new String(arrayOfByte, ˊ(new char[] { 30, 48, 46, 3, 160 }, 5, (byte)104).intern());
        break label16;
        j = 0;
        for (;;)
        {
          j = ᐝᐝ + 93;
          ᐨ = j % 128;
          if (j % 2 == 0) {
            break;
          }
          break;
          label252:
          switch (j)
          {
          }
        }
        label279:
        i = 20;
      }
    }
    for (;;)
    {
      j = paramString.length;
      if (i < j) {
        break label220;
      }
      break label301;
      return paramString;
      label301:
      j = 1;
      break label252;
      label306:
      break;
      label309:
      arrayOfByte[i] = ((byte)(paramString[(paramString.length - i - 1)] ^ ॱʼ));
      i += 1;
    }
  }
  
  /* Error */
  private static String ˊ(char[] paramArrayOfChar, int paramInt, byte paramByte)
  {
    // Byte code:
    //   0: goto +378 -> 378
    //   3: getstatic 84	o/Mo:ᐨ	I
    //   6: bipush 55
    //   8: iadd
    //   9: istore_1
    //   10: iload_1
    //   11: sipush 128
    //   14: irem
    //   15: putstatic 82	o/Mo:ᐝᐝ	I
    //   18: iload_1
    //   19: iconst_2
    //   20: irem
    //   21: ifeq +6 -> 27
    //   24: goto +443 -> 467
    //   27: aload_0
    //   28: areturn
    //   29: goto +41 -> 70
    //   32: iload 4
    //   34: tableswitch	default:+22->56, 0:+114->148, 1:+438->472
    //   56: goto +92 -> 148
    //   59: iconst_0
    //   60: istore 4
    //   62: goto -30 -> 32
    //   65: iconst_1
    //   66: istore_3
    //   67: goto +346 -> 413
    //   70: iload_1
    //   71: iconst_1
    //   72: if_icmple +6 -> 78
    //   75: goto +236 -> 311
    //   78: goto -13 -> 65
    //   81: iconst_0
    //   82: istore_3
    //   83: goto +78 -> 161
    //   86: iconst_1
    //   87: istore 4
    //   89: goto +350 -> 439
    //   92: aload 10
    //   94: iload_3
    //   95: iload 4
    //   97: iload_2
    //   98: isub
    //   99: i2c
    //   100: castore
    //   101: aload 10
    //   103: iload_3
    //   104: iconst_1
    //   105: iadd
    //   106: iload 8
    //   108: iload_2
    //   109: isub
    //   110: i2c
    //   111: castore
    //   112: goto +357 -> 469
    //   115: goto +46 -> 161
    //   118: getstatic 84	o/Mo:ᐨ	I
    //   121: bipush 67
    //   123: iadd
    //   124: istore 6
    //   126: iload 6
    //   128: sipush 128
    //   131: irem
    //   132: putstatic 82	o/Mo:ᐝᐝ	I
    //   135: iload 6
    //   137: iconst_2
    //   138: irem
    //   139: ifeq +6 -> 145
    //   142: goto +197 -> 339
    //   145: goto -53 -> 92
    //   148: new 243	java/lang/String
    //   151: dup
    //   152: aload 10
    //   154: invokespecial 271	java/lang/String:<init>	([C)V
    //   157: astore_0
    //   158: goto -155 -> 3
    //   161: iload_3
    //   162: iload_1
    //   163: if_icmpge +6 -> 169
    //   166: goto +150 -> 316
    //   169: goto -110 -> 59
    //   172: iload 6
    //   174: iload 5
    //   176: invokestatic 276	o/oO:ˊ	(II)I
    //   179: istore 6
    //   181: iload 4
    //   183: iload 5
    //   185: invokestatic 276	o/oO:ˊ	(II)I
    //   188: istore 4
    //   190: iload 6
    //   192: iload 7
    //   194: iload 5
    //   196: invokestatic 280	o/oO:ˏ	(III)I
    //   199: istore 6
    //   201: iload 4
    //   203: iload 8
    //   205: iload 5
    //   207: invokestatic 280	o/oO:ˏ	(III)I
    //   210: istore 4
    //   212: aload 10
    //   214: iload_3
    //   215: aload 9
    //   217: iload 6
    //   219: caload
    //   220: castore
    //   221: aload 10
    //   223: iload_3
    //   224: iconst_1
    //   225: iadd
    //   226: aload 9
    //   228: iload 4
    //   230: caload
    //   231: castore
    //   232: goto +136 -> 368
    //   235: iload 7
    //   237: iload 5
    //   239: invokestatic 276	o/oO:ˊ	(II)I
    //   242: istore 7
    //   244: iload 8
    //   246: iload 5
    //   248: invokestatic 276	o/oO:ˊ	(II)I
    //   251: istore 8
    //   253: iload 6
    //   255: iload 7
    //   257: iload 5
    //   259: invokestatic 280	o/oO:ˏ	(III)I
    //   262: istore 6
    //   264: iload 4
    //   266: iload 8
    //   268: iload 5
    //   270: invokestatic 280	o/oO:ˏ	(III)I
    //   273: istore 4
    //   275: aload 10
    //   277: iload_3
    //   278: aload 9
    //   280: iload 6
    //   282: caload
    //   283: castore
    //   284: aload 10
    //   286: iload_3
    //   287: iconst_1
    //   288: iadd
    //   289: aload 9
    //   291: iload 4
    //   293: caload
    //   294: castore
    //   295: goto +73 -> 368
    //   298: iload 6
    //   300: iload 4
    //   302: if_icmpne +6 -> 308
    //   305: goto -70 -> 235
    //   308: goto +189 -> 497
    //   311: iconst_0
    //   312: istore_3
    //   313: goto +100 -> 413
    //   316: iconst_1
    //   317: istore 4
    //   319: goto -287 -> 32
    //   322: iload_3
    //   323: iconst_1
    //   324: isub
    //   325: istore_1
    //   326: aload 10
    //   328: iload_1
    //   329: aload_0
    //   330: iload_1
    //   331: caload
    //   332: iload_2
    //   333: isub
    //   334: i2c
    //   335: castore
    //   336: goto +206 -> 542
    //   339: aload 10
    //   341: iload_3
    //   342: iload 4
    //   344: iload_2
    //   345: iadd
    //   346: i2c
    //   347: castore
    //   348: aload 10
    //   350: iload_3
    //   351: iconst_1
    //   352: imul
    //   353: iload 8
    //   355: iload_2
    //   356: iadd
    //   357: i2c
    //   358: castore
    //   359: goto +110 -> 469
    //   362: iconst_0
    //   363: istore 4
    //   365: goto +74 -> 439
    //   368: iload_3
    //   369: iconst_2
    //   370: iadd
    //   371: istore_3
    //   372: goto -257 -> 115
    //   375: astore_0
    //   376: aload_0
    //   377: athrow
    //   378: getstatic 282	o/Mo:ᐝˊ	[C
    //   381: astore 9
    //   383: iload_1
    //   384: istore_3
    //   385: getstatic 284	o/Mo:ᐧ	C
    //   388: istore 5
    //   390: iload_3
    //   391: newarray char
    //   393: astore 10
    //   395: iload_3
    //   396: iconst_2
    //   397: irem
    //   398: ifeq +6 -> 404
    //   401: goto -39 -> 362
    //   404: goto -318 -> 86
    //   407: goto -337 -> 70
    //   410: astore_0
    //   411: aload_0
    //   412: athrow
    //   413: iload_3
    //   414: tableswitch	default:+22->436, 0:+-333->81, 1:+-266->148
    //   436: goto -288 -> 148
    //   439: iload_3
    //   440: istore_1
    //   441: iload 4
    //   443: tableswitch	default:+21->464, 0:+-121->322, 1:+-373->70
    //   464: goto -142 -> 322
    //   467: aload_0
    //   468: areturn
    //   469: goto -101 -> 368
    //   472: aload_0
    //   473: iload_3
    //   474: caload
    //   475: istore 4
    //   477: aload_0
    //   478: iload_3
    //   479: iconst_1
    //   480: iadd
    //   481: caload
    //   482: istore 8
    //   484: iload 4
    //   486: iload 8
    //   488: if_icmpne +6 -> 494
    //   491: goto -373 -> 118
    //   494: goto +75 -> 569
    //   497: iload 6
    //   499: iload 8
    //   501: iload 5
    //   503: invokestatic 280	o/oO:ˏ	(III)I
    //   506: istore 6
    //   508: iload 4
    //   510: iload 7
    //   512: iload 5
    //   514: invokestatic 280	o/oO:ˏ	(III)I
    //   517: istore 4
    //   519: aload 10
    //   521: iload_3
    //   522: aload 9
    //   524: iload 6
    //   526: caload
    //   527: castore
    //   528: aload 10
    //   530: iload_3
    //   531: iconst_1
    //   532: iadd
    //   533: aload 9
    //   535: iload 4
    //   537: caload
    //   538: castore
    //   539: goto -171 -> 368
    //   542: getstatic 82	o/Mo:ᐝᐝ	I
    //   545: bipush 117
    //   547: iadd
    //   548: istore_3
    //   549: iload_3
    //   550: sipush 128
    //   553: irem
    //   554: putstatic 84	o/Mo:ᐨ	I
    //   557: iload_3
    //   558: iconst_2
    //   559: irem
    //   560: ifne +6 -> 566
    //   563: goto -534 -> 29
    //   566: goto -159 -> 407
    //   569: iload 4
    //   571: iload 5
    //   573: invokestatic 286	o/oO:ॱ	(II)I
    //   576: istore 6
    //   578: iload 4
    //   580: iload 5
    //   582: invokestatic 288	o/oO:ˋ	(II)I
    //   585: istore 7
    //   587: iload 8
    //   589: iload 5
    //   591: invokestatic 286	o/oO:ॱ	(II)I
    //   594: istore 4
    //   596: iload 8
    //   598: iload 5
    //   600: invokestatic 288	o/oO:ˋ	(II)I
    //   603: istore 8
    //   605: iload 7
    //   607: iload 8
    //   609: if_icmpne +6 -> 615
    //   612: goto -440 -> 172
    //   615: goto -317 -> 298
    // Local variable table:
    //   start	length	slot	name	signature
    //   0	618	0	paramArrayOfChar	char[]
    //   0	618	1	paramInt	int
    //   0	618	2	paramByte	byte
    //   66	494	3	i	int
    //   32	563	4	b1	byte
    //   174	425	5	j	int
    //   124	453	6	b2	byte
    //   192	418	7	b3	byte
    //   106	504	8	b4	byte
    //   215	319	9	arrayOfChar1	char[]
    //   92	437	10	arrayOfChar2	char[]
    // Exception table:
    //   from	to	target	type
    //   497	508	375	java/lang/Exception
    //   508	519	410	java/lang/Exception
  }
  
  static void ˊॱ()
  {
    for (;;)
    {
      i = ᐝᐝ + 117;
      ᐨ = i % 128;
      if (i % 2 != 0)
      {
        break label97;
        return;
      }
      break label97;
      i = ᐨ + 101;
      ᐝᐝ = i % 128;
      if (i % 2 != 0) {
        break label105;
      }
      break;
      i = 79 / 0;
      return;
    }
    label97:
    label105:
    for (int i = 0;; i = 1)
    {
      switch (i)
      {
      }
      return;
      ॱʼ = -102;
      break;
    }
  }
  
  private boolean ˋ(coN paramCoN, int paramInt)
  {
    if (paramInt == 0)
    {
      try
      {
        this.ॱʻ |= 1L;
      }
      finally
      {
        paramCoN = finally;
        throw paramCoN;
      }
      return true;
    }
    return false;
  }
  
  static void ॱˋ()
  {
    ᐝˊ = new char[] { 5, 26, 11, 12, 45, 104, 116, 112, 115, 58, 47, 98, 97, 121, 101, 110, 46, 114, 108, 111, 119, 105, 118, 49, 103, 109, 73, 66, 65, 67, 75, 71, 82, 79, 85, 78, 68, 95, 77, 69, 83, 56, 53, 57, 84, 70, 6, 7, 8 };
    ᐧ = '\007';
  }
  
  public void ˊ(FW paramFW)
  {
    this.ˏˎ = paramFW;
    try
    {
      this.ॱʻ |= 0x8;
    }
    finally
    {
      paramFW = finally;
      throw paramFW;
    }
    ˊ(127);
    super.ʽ();
  }
  
  public void ˊ(boolean paramBoolean)
  {
    this.ـ = paramBoolean;
    try
    {
      this.ॱʻ |= 0x200;
    }
    finally
    {
      localObject = finally;
      throw localObject;
    }
    ˊ(60);
    super.ʽ();
  }
  
  public boolean ˋॱ()
  {
    break label109;
    int i = ᐨ + 5;
    ᐝᐝ = i % 128;
    boolean bool;
    if (i % 2 == 0)
    {
      break label104;
      for (;;)
      {
        bool = this.ˑ;
        break;
        label37:
        i = ᐝᐝ + 113;
        ᐨ = i % 128;
        if (i % 2 == 0) {
          break label91;
        }
      }
    }
    for (;;)
    {
      switch (i)
      {
      default: 
        break;
      case 1: 
        return bool;
      case 0: 
        label91:
        throw new NullPointerException();
        label104:
        i = 1;
        continue;
        label109:
        break label37;
        i = 0;
      }
    }
  }
  
  public void ˎ(BigDecimal paramBigDecimal)
  {
    this.ॱͺ = paramBigDecimal;
    try
    {
      this.ॱʻ |= 0x100;
    }
    finally
    {
      paramBigDecimal = finally;
      throw paramBigDecimal;
    }
    ˊ(23);
    super.ʽ();
  }
  
  public void ˎ(FS paramFS)
  {
    this.ͺॱ = paramFS;
    try
    {
      this.ॱʻ |= 0x40;
    }
    finally
    {
      paramFS = finally;
      throw paramFS;
    }
    ˊ(24);
    super.ʽ();
  }
  
  public void ˎ(boolean paramBoolean)
  {
    this.ˑ = paramBoolean;
    try
    {
      this.ॱʻ |= 0x20;
    }
    finally
    {
      localObject = finally;
      throw localObject;
    }
    ˊ(58);
    super.ʽ();
  }
  
  public void ˏ()
  {
    String str3 = ˊ(new char[] { 1, 2, 3, 4 }, 4, (byte)76).intern();
    try
    {
      l2 = this.ॱʻ;
      this.ॱʻ = 0L;
    }
    finally
    {
      localObject1 = finally;
      throw localObject1;
    }
    Object localObject28 = null;
    Object localObject27 = null;
    coN localCoN = this.ˌ;
    boolean bool4 = this.ˋᐝ;
    Object localObject25 = null;
    int i15 = 0;
    Object localObject3 = null;
    Object localObject15 = null;
    Object localObject40 = null;
    Object localObject16 = null;
    Object localObject6 = null;
    int i5 = 0;
    Object localObject39 = null;
    int i18 = 0;
    boolean bool1 = false;
    boolean bool8 = false;
    Object localObject23 = null;
    boolean bool5 = false;
    int i17 = 0;
    int i16 = 0;
    String str1 = this.ˎˏ;
    int i20 = 0;
    FW localFW = this.ˏˎ;
    Object localObject7 = null;
    Object localObject17 = null;
    Object localObject38 = null;
    String str2 = this.ˏˏ;
    Object localObject8 = null;
    Object localObject5 = null;
    Object localObject37 = null;
    Object localObject24 = null;
    int i14 = 0;
    int i23 = 0;
    int i13 = 0;
    boolean bool9 = this.ˑ;
    int k = 0;
    Object localObject30 = null;
    Object localObject31 = null;
    Object localObject29 = null;
    int i12 = 0;
    boolean bool3 = false;
    boolean bool2 = false;
    boolean bool7 = false;
    int i11 = 0;
    float f1 = 0.0F;
    Object localObject18 = null;
    Object localObject9 = null;
    FS localFS = this.ͺॱ;
    int i26 = 0;
    boolean bool6 = this.ॱʽ;
    int i24 = 0;
    Object localObject10 = null;
    Object localObject4 = null;
    Object localObject36 = null;
    Object localObject22 = null;
    int i10 = 0;
    int i2 = 0;
    int i8 = 0;
    int j = 0;
    int i9 = 0;
    double d4 = 0.0D;
    int i19 = 0;
    Object localObject11 = null;
    Object localObject19 = null;
    Object localObject35 = null;
    Object localObject12 = null;
    Object localObject20 = null;
    Object localObject34 = null;
    float f3 = 0.0F;
    int i6 = 0;
    int n = 0;
    int i22 = 0;
    int i21 = 0;
    Object localObject13 = null;
    Object localObject21 = null;
    Object localObject33 = null;
    int i7 = 0;
    int i1 = 0;
    BigDecimal localBigDecimal = this.ॱͺ;
    int i25 = 0;
    Object localObject2 = null;
    Object localObject32 = null;
    boolean bool10 = this.ـ;
    Object localObject26 = null;
    double d3 = 0.0D;
    long l1 = l2;
    if ((0x401 & l2) != 0L)
    {
      bool1 = bool8;
      if (localCoN != null) {
        bool1 = localCoN.ˊ();
      }
      l1 = l2;
      if ((0x401 & l2) != 0L) {
        if (bool1) {
          l1 = l2 | 0x40000 | 0x1000000000;
        } else {
          l1 = l2 | 0x20000 | 0x800000000;
        }
      }
      if (bool1) {
        i = 0;
      } else {
        i = 8;
      }
      if (bool1)
      {
        k = 4;
        i5 = i;
      }
      else
      {
        k = 0;
        i5 = i;
      }
    }
    long l2 = l1;
    int i4 = i12;
    float f2 = f1;
    int m = i26;
    double d2 = d3;
    if ((0x488 & l1) != 0L)
    {
      l3 = l1;
      i = i2;
      Object localObject14 = localObject32;
      d1 = d3;
      if ((0x408 & l1) != 0L)
      {
        localObject2 = localObject40;
        localObject3 = localObject39;
        localObject4 = localObject38;
        localObject5 = localObject37;
        bool2 = bool7;
        localObject15 = localObject36;
        localObject16 = localObject35;
        localObject17 = localObject34;
        localObject18 = localObject33;
        if (localFW != null)
        {
          localObject2 = localFW.ॱᐝ();
          localObject3 = localFW.ʼ();
          localObject4 = localFW.ॱˋ();
          localObject5 = localFW.ˏ();
          bool2 = localFW.ʽॱ();
          localObject15 = localFW.ॱॱ();
          localObject16 = localFW.ˏ(ᐝ().getContext());
          localObject17 = localFW.ʻ();
          localObject18 = localFW.ʽ();
          d3 = localFW.ॱ();
        }
        l2 = l1;
        if ((0x408 & l1) != 0L) {
          if (bool2) {
            l2 = l1 | 0x400000000000000 | 0x1000000000000000;
          } else {
            l2 = l1 | 0x200000000000000 | 0x800000000000000;
          }
        }
        if (localFW != null) {
          m = 1;
        } else {
          m = 0;
        }
        l1 = l2;
        if ((0x408 & l2) != 0L) {
          if (m != 0) {
            l1 = l2 | 0x1000000000000;
          } else {
            l1 = l2 | 0x800000000000;
          }
        }
        localObject19 = aq.ॱ((String)localObject3);
        if (bool2) {
          i2 = 8;
        } else {
          i2 = 0;
        }
        if (bool2) {
          i3 = 0;
        } else {
          i3 = 8;
        }
        if (localObject15 == FV.DECLINED) {
          i4 = 1;
        } else {
          i4 = 0;
        }
        localObject20 = at.ˎ(d3);
        l2 = l1;
        if ((0x408 & l1) != 0L) {
          if (i4 != 0) {
            l2 = l1 | 0x40000000;
          } else {
            l2 = l1 | 0x20000000;
          }
        }
        l3 = l2;
        localObject3 = localObject2;
        localObject6 = localObject19;
        localObject7 = localObject4;
        localObject8 = localObject5;
        bool3 = bool2;
        localObject9 = localObject20;
        localObject10 = localObject15;
        i = m;
        j = i4;
        localObject11 = localObject16;
        localObject12 = localObject17;
        n = i2;
        localObject13 = localObject18;
        i1 = i3;
        localObject14 = localObject32;
        d1 = d3;
        if (localObject5 != null)
        {
          localObject14 = ((Ep)localObject5).ˊ();
          d1 = d3;
          i1 = i3;
          localObject13 = localObject18;
          n = i2;
          localObject12 = localObject17;
          localObject11 = localObject16;
          j = i4;
          i = m;
          localObject10 = localObject15;
          localObject9 = localObject20;
          bool3 = bool2;
          localObject8 = localObject5;
          localObject7 = localObject4;
          localObject6 = localObject19;
          localObject3 = localObject2;
          l3 = l2;
        }
      }
      if (localFW == null) {
        i2 = 1;
      } else {
        i2 = 0;
      }
      l1 = l3;
      if ((0x488 & l3) != 0L) {
        if (i2 != 0) {
          l1 = l3 | 0x10000 | 0x40000000000000;
        } else {
          l1 = l3 | 0x8000 | 0x20000000000000;
        }
      }
      l3 = l1;
      if ((0x408 & l1) != 0L) {
        if (i2 != 0) {
          l3 = l1 | 0x10000000000 | 0x40000000000 | 0x100000000000;
        } else {
          l3 = l1 | 0x8000000000 | 0x20000000000 | 0x80000000000;
        }
      }
      l2 = l3;
      localObject15 = localObject3;
      localObject16 = localObject6;
      localObject17 = localObject7;
      localObject5 = localObject8;
      i4 = i12;
      bool2 = bool3;
      f2 = f1;
      localObject18 = localObject9;
      m = i26;
      localObject4 = localObject10;
      i10 = i;
      i8 = j;
      i9 = i2;
      localObject19 = localObject11;
      localObject20 = localObject12;
      i6 = n;
      localObject21 = localObject13;
      i7 = i1;
      localObject2 = localObject14;
      d2 = d1;
      if ((0x408 & l3) != 0L)
      {
        if (i2 != 0) {
          i3 = ˋ(this.ॱˋ, 17170445);
        } else {
          i3 = ˋ(this.ॱˋ, 2131099797);
        }
        if (i2 != 0) {
          f1 = this.ॱˋ.getResources().getDimension(2131165260);
        } else {
          f1 = this.ॱˋ.getResources().getDimension(2131165259);
        }
        if (i2 != 0)
        {
          m = 4;
          l2 = l3;
          localObject15 = localObject3;
          localObject16 = localObject6;
          localObject17 = localObject7;
          localObject5 = localObject8;
          i4 = i3;
          bool2 = bool3;
          f2 = f1;
          localObject18 = localObject9;
          localObject4 = localObject10;
          i10 = i;
          i8 = j;
          i9 = i2;
          localObject19 = localObject11;
          localObject20 = localObject12;
          i6 = n;
          localObject21 = localObject13;
          i7 = i1;
          localObject2 = localObject14;
          d2 = d1;
        }
        else
        {
          m = 0;
          d2 = d1;
          localObject2 = localObject14;
          i7 = i1;
          localObject21 = localObject13;
          i6 = n;
          localObject20 = localObject12;
          localObject19 = localObject11;
          i9 = i2;
          i8 = j;
          i10 = i;
          localObject4 = localObject10;
          localObject18 = localObject9;
          f2 = f1;
          bool2 = bool3;
          i4 = i3;
          localObject5 = localObject8;
          localObject17 = localObject7;
          localObject16 = localObject6;
          localObject15 = localObject3;
          l2 = l3;
        }
      }
    }
    l1 = l2;
    i12 = i25;
    if ((0x62B & l2) != 0L)
    {
      l3 = l2;
      if ((0x428 & l2) != 0L) {
        if (bool9) {
          l3 = l2 | 0x400000;
        } else {
          l3 = l2 | 0x200000;
        }
      }
      l1 = l3;
      i12 = i25;
      if ((0x623 & l3) != 0L)
      {
        if (!bool9) {
          i = 1;
        } else {
          i = 0;
        }
        l1 = l3;
        i12 = i;
        if ((0x623 & l3) != 0L) {
          if (i != 0)
          {
            l1 = l3 | 0x10000000;
            i12 = i;
          }
          else
          {
            l1 = l3 | 0x8000000;
            i12 = i;
          }
        }
      }
    }
    long l3 = l1;
    n = i24;
    if ((0x480 & l1) != 0L)
    {
      l3 = l1;
      if ((0x480 & l1) != 0L) {
        if (bool6) {
          l3 = l1 | 0x400000000000;
        } else {
          l3 = l1 | 0x200000000000;
        }
      }
      if (bool6) {
        n = 0;
      } else {
        n = 8;
      }
    }
    l2 = l3;
    if ((0x508 & l3) != 0L)
    {
      if (localBigDecimal == null) {
        i = 1;
      } else {
        i = 0;
      }
      l1 = l3;
      if ((0x508 & l3) != 0L) {
        if (i != 0) {
          l1 = l3 | 0x1000 | 0x100000000;
        } else {
          l1 = l3 | 0x800 | 0x80000000;
        }
      }
      l2 = l1;
      i11 = i;
      if ((0x500 & l1) != 0L) {
        if (i != 0)
        {
          l2 = l1 | 0x4000000000000;
          i11 = i;
        }
        else
        {
          l2 = l1 | 0x2000000000000;
          i11 = i;
        }
      }
    }
    l1 = l2;
    int i = i23;
    if ((0x10000000 & l2) != 0L)
    {
      if (localCoN != null) {
        bool1 = localCoN.ˊ();
      }
      l1 = l2;
      if ((0x401 & l2) != 0L) {
        if (bool1) {
          l1 = l2 | 0x40000 | 0x1000000000;
        } else {
          l1 = l2 | 0x20000 | 0x800000000;
        }
      }
      if (!bool1) {
        i = 1;
      } else {
        i = 0;
      }
    }
    l2 = l1;
    localObject6 = localObject31;
    i2 = i22;
    localObject3 = localObject2;
    double d1 = d2;
    if ((0xA0200800 & l1) != 0L)
    {
      localObject7 = localObject2;
      if ((0x80000000 & l1) != 0L)
      {
        if (localFW != null) {
          localObject5 = localFW.ˏ();
        }
        localObject7 = localObject2;
        if (localObject5 != null) {
          localObject7 = ((Ep)localObject5).ˊ();
        }
      }
      long l4 = l1;
      localObject5 = localObject30;
      j = i21;
      if ((0x20200000 & l1) != 0L)
      {
        if (localFW != null) {
          localObject4 = localFW.ॱॱ();
        }
        l3 = l1;
        localObject2 = localObject29;
        if ((0x200000 & l1) != 0L)
        {
          if (localObject4 == FV.ACCEPTED) {
            j = 1;
          } else {
            j = 0;
          }
          l2 = l1;
          if ((0x200000 & l1) != 0L) {
            if (j != 0) {
              l2 = l1 | 0x4000000000;
            } else {
              l2 = l1 | 0x2000000000;
            }
          }
          if (j != 0)
          {
            localObject3 = this.ʻ.getResources().getString(2131755473);
            localObject2 = localObject3;
            if (((String)localObject3).startsWith(str3)) {
              localObject2 = ˊ(((String)localObject3).substring(4)).intern();
            }
            l3 = l2;
          }
          else
          {
            localObject3 = this.ʻ.getResources().getString(2131755465);
            l3 = l2;
            localObject2 = localObject3;
            if (((String)localObject3).startsWith(str3))
            {
              localObject2 = ˊ(((String)localObject3).substring(4)).intern();
              l3 = l2;
            }
          }
        }
        l4 = l3;
        localObject5 = localObject2;
        j = i21;
        if ((0x20000000 & l3) != 0L) {
          if (localObject4 == FV.CANCELED)
          {
            j = 1;
            l4 = l3;
            localObject5 = localObject2;
          }
          else
          {
            j = 0;
            localObject5 = localObject2;
            l4 = l3;
          }
        }
      }
      l2 = l4;
      localObject6 = localObject5;
      i2 = j;
      localObject3 = localObject7;
      d1 = d2;
      if ((0x800 & l4) != 0L)
      {
        l2 = l4;
        localObject6 = localObject5;
        i2 = j;
        localObject3 = localObject7;
        d1 = d2;
        if (localFW != null)
        {
          d1 = localFW.ॱ();
          localObject3 = localObject7;
          i2 = j;
          localObject6 = localObject5;
          l2 = l4;
        }
      }
    }
    l1 = l2;
    j = i20;
    if ((0x20000000008000 & l2) != 0L)
    {
      l3 = l2;
      if ((0x480 & l2) != 0L) {
        if (bool6) {
          l3 = l2 | 0x400000000000;
        } else {
          l3 = l2 | 0x200000000000;
        }
      }
      l1 = l3;
      j = i20;
      if ((0x8000 & l3) != 0L) {
        if (!bool6)
        {
          j = 1;
          l1 = l3;
        }
        else
        {
          j = 0;
          l1 = l3;
        }
      }
    }
    l2 = l1;
    i1 = i19;
    if ((0x408 & l1) != 0L)
    {
      if (i10 == 0) {
        bool2 = false;
      }
      l2 = l1;
      if ((0x408 & l1) != 0L) {
        if (bool2) {
          l2 = l1 | 0x10000000000000;
        } else {
          l2 = l1 | 0x8000000000000;
        }
      }
      if (bool2) {
        i1 = 0;
      } else {
        i1 = 8;
      }
    }
    localObject7 = localObject28;
    localObject4 = localObject26;
    if ((0x2000000000800 & l2) != 0L)
    {
      d2 = d4;
      if (localBigDecimal != null) {
        d2 = localBigDecimal.doubleValue();
      }
      localObject2 = localObject27;
      if ((0x2000000000000 & l2) != 0L) {
        localObject2 = at.ˎ(d2);
      }
      localObject7 = localObject2;
      localObject4 = localObject26;
      if ((0x800 & l2) != 0L)
      {
        localObject4 = at.ˎ(d1 + d2);
        localObject7 = localObject2;
      }
    }
    localObject8 = localObject25;
    localObject2 = localObject24;
    if ((0x508 & l2) != 0L)
    {
      if (i11 != 0) {
        localObject4 = "";
      }
      if (i11 != 0)
      {
        localObject2 = ˊ(new char[] { 156 }, 1, (byte)111).intern();
        localObject8 = localObject4;
      }
      else
      {
        localObject2 = localObject3;
        localObject8 = localObject4;
      }
    }
    l3 = l2;
    i10 = i18;
    int i3 = i17;
    f1 = f3;
    if ((0x488 & l2) != 0L)
    {
      if (i9 != 0) {
        j = 1;
      }
      if (i9 != 0) {
        bool1 = true;
      } else {
        bool1 = bool6;
      }
      l1 = l2;
      if ((0x488 & l2) != 0L) {
        if (j != 0) {
          l1 = l2 | 0x100000;
        } else {
          l1 = l2 | 0x80000;
        }
      }
      l2 = l1;
      if ((0x488 & l1) != 0L) {
        if (bool1) {
          l2 = l1 | 0x4000000 | 0x100000000000000;
        } else {
          l2 = l1 | 0x2000000 | 0x80000000000000;
        }
      }
      if (j != 0) {
        j = 4;
      } else {
        j = 0;
      }
      if (bool1) {
        i3 = 4;
      } else {
        i3 = 0;
      }
      if (bool1)
      {
        f1 = this.ˎˎ.getResources().getDimension(2131165398);
        l3 = l2;
        i10 = j;
      }
      else
      {
        f1 = this.ˎˎ.getResources().getDimension(2131165399);
        i10 = j;
        l3 = l2;
      }
    }
    localObject4 = localObject23;
    if ((0x428 & l3) != 0L) {
      if (bool9)
      {
        localObject5 = this.ʻ.getResources().getString(2131755471);
        localObject4 = localObject5;
        if (((String)localObject5).startsWith(str3)) {
          localObject4 = ˊ(((String)localObject5).substring(4)).intern();
        }
      }
      else
      {
        localObject4 = localObject6;
      }
    }
    l1 = l3;
    i9 = i16;
    if ((0x623 & l3) != 0L)
    {
      if (i12 == 0) {
        i = 0;
      }
      l1 = l3;
      i9 = i;
      if ((0x623 & l3) != 0L) {
        if (i != 0)
        {
          l1 = l3 | 0x400000000;
          i9 = i;
        }
        else
        {
          l1 = l3 | 0x200000000;
          i9 = i;
        }
      }
    }
    l2 = l1;
    j = i15;
    if ((0x408 & l1) != 0L)
    {
      if (i8 != 0) {
        i2 = 1;
      }
      l2 = l1;
      if ((0x408 & l1) != 0L) {
        if (i2 != 0) {
          l2 = l1 | 0x4000;
        } else {
          l2 = l1 | 0x2000;
        }
      }
      if (i2 != 0) {
        j = 0;
      } else {
        j = 8;
      }
    }
    localObject5 = localObject22;
    if ((0x500 & l2) != 0L) {
      if (i11 != 0) {
        localObject5 = "";
      } else {
        localObject5 = localObject7;
      }
    }
    i = i14;
    if ((0x400000000 & l2) != 0L) {
      if (!bool10) {
        i = 1;
      } else {
        i = 0;
      }
    }
    l1 = l2;
    i2 = i13;
    if ((0x623 & l2) != 0L)
    {
      if (i9 == 0) {
        i = 0;
      }
      l1 = l2;
      i2 = i;
      if ((0x623 & l2) != 0L) {
        if (i != 0)
        {
          l1 = l2 | 0x1000000;
          i2 = i;
        }
        else
        {
          l1 = l2 | 0x800000;
          i2 = i;
        }
      }
    }
    bool1 = bool5;
    if ((0x623 & l1) != 0L) {
      if (i2 != 0) {
        bool1 = bool4;
      } else {
        bool1 = false;
      }
    }
    if ((0x400 & l1) != 0L)
    {
      r.ˊ(this.ˎ, ˊ(new char[] { 6, 0, 0, 13, 9, 10, 169, 169, 13, 4, 8, 13, 11, 6, 15, 16, 18, 9, 3, 20, 19, 17, 18, 20, 11, 12, 13, 27, 11, 19, 19, 15, 3, 13, 13, 8, 24, 7, 23, 24, 11, 9, 20, 0, 0, 27, 17, 22, 9, 11, 0, 6, 18, 21, 19, 21, 26, 11, 21, 17, 13, 24, 29, 30, 31, 32, 33, 34, 28, 41, 37, 38, 24, 40, 29, 32, 191 }, 77, (byte)122).intern(), ॱ(this.ˎ, 2131230823), true);
      localObject9 = this.ॱ;
      localObject7 = this.ॱ.getResources().getString(2131755475);
      localObject6 = localObject7;
      if (((String)localObject7).startsWith(str3)) {
        localObject6 = ˊ(((String)localObject7).substring(4)).intern();
      }
      ʹ.ˊ((TextView)localObject9, (CharSequence)localObject6);
      this.ʻ.setViewPagerHeight(this.ʻ.getResources().getDimension(2131165400));
      localObject9 = this.ˈ;
      localObject7 = this.ˈ.getResources().getString(2131755246);
      localObject6 = localObject7;
      if (((String)localObject7).startsWith(str3)) {
        localObject6 = ˊ(((String)localObject7).substring(4)).intern();
      }
      ʹ.ˊ((TextView)localObject9, (CharSequence)localObject6);
      this.ˉ.setShadowBottom(ॱ(this.ˉ, 2131231257));
      this.ˉ.setShadowTop(ॱ(this.ˉ, 2131231258));
      this.ˍ.setShowPhoneType(false);
      localObject9 = this.ʼ;
      localObject7 = this.ʼ.getResources().getString(2131755432);
      localObject6 = localObject7;
      if (((String)localObject7).startsWith(str3)) {
        localObject6 = ˊ(((String)localObject7).substring(4)).intern();
      }
      ʹ.ˊ((TextView)localObject9, (CharSequence)localObject6);
      localObject9 = this.ॱˊ;
      localObject7 = this.ॱˊ.getResources().getString(2131755476);
      localObject6 = localObject7;
      if (((String)localObject7).startsWith(str3)) {
        localObject6 = ˊ(((String)localObject7).substring(4)).intern();
      }
      ((Je)localObject9).setLabel((String)localObject6);
      localObject9 = this.ᐝॱ;
      localObject7 = this.ᐝॱ.getResources().getString(2131755477);
      localObject6 = localObject7;
      if (((String)localObject7).startsWith(str3)) {
        localObject6 = ˊ(((String)localObject7).substring(4)).intern();
      }
      ((Je)localObject9).setLabel((String)localObject6);
      localObject9 = this.ʻॱ;
      localObject7 = this.ʻॱ.getResources().getString(2131755421);
      localObject6 = localObject7;
      if (((String)localObject7).startsWith(str3)) {
        localObject6 = ˊ(((String)localObject7).substring(4)).intern();
      }
      ((Je)localObject9).setLabel((String)localObject6);
      localObject9 = this.ʾ;
      localObject7 = this.ʾ.getResources().getString(2131755480);
      localObject6 = localObject7;
      if (((String)localObject7).startsWith(str3)) {
        localObject6 = ˊ(((String)localObject7).substring(4)).intern();
      }
      ((Je)localObject9).setLabel((String)localObject6);
    }
    if ((0x408 & l1) != 0L)
    {
      this.ˊ.setVisibility(i1);
      this.ˋˊ.setVisibility(j);
      this.ˊᐝ.setVisibility(i6);
      this.ˍ.setPhoneNumber((FQ)localObject20);
      this.ʼ.setVisibility(i7);
      this.ˏॱ.setVisibility(m);
      ʹ.ˊ(this.ˋॱ, localObject21);
      this.ॱˎ.setValue((String)localObject18);
      this.ॱˎ.setValueInfo((String)localObject3);
      this.ॱˋ.setCardBackgroundColor(i4);
      this.ॱˋ.setCardElevation(f2);
      this.ᐝॱ.setValue((String)localObject16);
      this.ʻॱ.setVisibility(j);
      this.ʻॱ.setValue((String)localObject15);
      this.ॱᐝ.setLabel((String)localObject19);
      this.ॱᐝ.setValue((String)localObject17);
    }
    if ((0x623 & l1) != 0L) {
      this.ॱ.setEnabled(bool1);
    }
    if ((0x488 & l1) != 0L)
    {
      this.ʻ.setVisibility(i10);
      this.ˋˋ.setVisibility(i3);
      A.ˋ(this.ˎˎ, f1, 0.0F, 0.0F, 0.0F);
    }
    if ((0x428 & l1) != 0L) {
      this.ʻ.setPaymentHint((String)localObject4);
    }
    if ((0x480 & l1) != 0L)
    {
      this.ˊˋ.setVisibility(n);
      this.ˊˊ.setVisibility(n);
      this.ॱˊ.setVisibility(n);
      this.ʾ.setVisibility(n);
    }
    if ((0x410 & l1) != 0L) {
      ʹ.ˊ(this.ˋˋ, str2);
    }
    if ((0x440 & l1) != 0L) {
      this.ˍ.setContactPerson(localFS);
    }
    if ((0x401 & l1) != 0L)
    {
      this.ॱॱ.setVisibility(i5);
      this.ˊॱ.setVisibility(k);
    }
    if ((0x404 & l1) != 0L) {
      this.ͺ.setTitle(str1);
    }
    if ((0x500 & l1) != 0L) {
      this.ॱˊ.setValue((String)localObject5);
    }
    if ((0x508 & l1) != 0L)
    {
      this.ॱˊ.setValueInfo((String)localObject2);
      this.ʾ.setValue(localObject8);
      this.ʾ.setValueInfo((String)localObject2);
    }
  }
  
  public void ˏ(String paramString)
  {
    this.ˎˏ = paramString;
    try
    {
      this.ॱʻ |= 0x4;
    }
    finally
    {
      paramString = finally;
      throw paramString;
    }
    ˊ(123);
    super.ʽ();
  }
  
  public void ˏ(boolean paramBoolean)
  {
    this.ॱʽ = paramBoolean;
    try
    {
      this.ॱʻ |= 0x80;
    }
    finally
    {
      localObject = finally;
      throw localObject;
    }
    ˊ(59);
    super.ʽ();
  }
  
  /* Error */
  public boolean ˏ(int paramInt1, Object paramObject, int paramInt2)
  {
    // Byte code:
    //   0: goto +6 -> 6
    //   3: astore_2
    //   4: aload_2
    //   5: athrow
    //   6: goto +55 -> 61
    //   9: iconst_0
    //   10: ireturn
    //   11: goto -2 -> 9
    //   14: goto +74 -> 88
    //   17: aload_0
    //   18: aload_2
    //   19: checkcast 380	o/coN
    //   22: iload_3
    //   23: invokespecial 739	o/Mo:ˋ	(Lo/coN;I)Z
    //   26: istore 5
    //   28: iload 5
    //   30: ireturn
    //   31: getstatic 82	o/Mo:ᐝᐝ	I
    //   34: bipush 57
    //   36: iadd
    //   37: istore_1
    //   38: iload_1
    //   39: sipush 128
    //   42: irem
    //   43: putstatic 84	o/Mo:ᐨ	I
    //   46: iload_1
    //   47: iconst_2
    //   48: irem
    //   49: ifne +6 -> 55
    //   52: goto -41 -> 11
    //   55: goto -46 -> 9
    //   58: astore_2
    //   59: aload_2
    //   60: athrow
    //   61: getstatic 84	o/Mo:ᐨ	I
    //   64: bipush 115
    //   66: iadd
    //   67: istore 4
    //   69: iload 4
    //   71: sipush 128
    //   74: irem
    //   75: putstatic 82	o/Mo:ᐝᐝ	I
    //   78: iload 4
    //   80: iconst_2
    //   81: irem
    //   82: ifeq +6 -> 88
    //   85: goto -71 -> 14
    //   88: iload_1
    //   89: lookupswitch	default:+19->108, 0:+-72->17
    //   108: goto -77 -> 31
    // Local variable table:
    //   start	length	slot	name	signature
    //   0	111	0	this	Mo
    //   0	111	1	paramInt1	int
    //   0	111	2	paramObject	Object
    //   0	111	3	paramInt2	int
    //   67	15	4	i	int
    //   26	3	5	bool	boolean
    // Exception table:
    //   from	to	target	type
    //   17	28	3	java/lang/Exception
    //   61	69	3	java/lang/Exception
    //   69	78	3	java/lang/Exception
    //   69	78	58	java/lang/Exception
  }
  
  public BigDecimal ˏॱ()
  {
    try
    {
      localBigDecimal = this.ॱͺ;
    }
    catch (Exception localException)
    {
      BigDecimal localBigDecimal;
      label16:
      label18:
      throw localException;
    }
    int i = 1;
    break label18;
    i = 0;
    switch (i)
    {
    case 0: 
    default: 
      break;
    }
    for (;;)
    {
      i = ᐨ + 107;
      ᐝᐝ = i % 128;
      if (i % 2 != 0) {
        break;
      }
      break label16;
      localBigDecimal = this.ॱͺ;
      throw new NullPointerException();
      i = 0;
      break label104;
    }
    for (;;)
    {
      i = 1;
      for (;;)
      {
        i = null.length;
        return localException;
        label104:
        switch (i)
        {
        }
      }
      return localException;
      i = ᐝᐝ + 101;
      ᐨ = i % 128;
      if (i % 2 == 0) {
        break;
      }
    }
  }
  
  /* Error */
  public FW ͺ()
  {
    // Byte code:
    //   0: goto +74 -> 74
    //   3: astore_2
    //   4: aload_2
    //   5: athrow
    //   6: goto +58 -> 64
    //   9: getstatic 84	o/Mo:ᐨ	I
    //   12: bipush 69
    //   14: iadd
    //   15: istore_1
    //   16: iload_1
    //   17: sipush 128
    //   20: irem
    //   21: putstatic 82	o/Mo:ᐝᐝ	I
    //   24: iload_1
    //   25: iconst_2
    //   26: irem
    //   27: ifeq +6 -> 33
    //   30: goto -24 -> 6
    //   33: goto +31 -> 64
    //   36: getstatic 84	o/Mo:ᐨ	I
    //   39: istore_1
    //   40: iload_1
    //   41: bipush 121
    //   43: iadd
    //   44: istore_1
    //   45: iload_1
    //   46: sipush 128
    //   49: irem
    //   50: putstatic 82	o/Mo:ᐝᐝ	I
    //   53: iload_1
    //   54: iconst_2
    //   55: irem
    //   56: ifeq +6 -> 62
    //   59: goto +13 -> 72
    //   62: aload_2
    //   63: areturn
    //   64: aload_0
    //   65: getfield 337	o/Mo:ˏˎ	Lo/FW;
    //   68: astore_2
    //   69: goto -33 -> 36
    //   72: aload_2
    //   73: areturn
    //   74: goto -65 -> 9
    // Local variable table:
    //   start	length	slot	name	signature
    //   0	77	0	this	Mo
    //   15	41	1	i	int
    //   3	60	2	localException	Exception
    //   68	5	2	localFW	FW
    // Exception table:
    //   from	to	target	type
    //   36	40	3	java/lang/Exception
    //   45	53	3	java/lang/Exception
    //   64	69	3	java/lang/Exception
  }
  
  public void ॱ(String paramString)
  {
    this.ˏˏ = paramString;
    try
    {
      this.ॱʻ |= 0x10;
    }
    finally
    {
      paramString = finally;
      throw paramString;
    }
    ˊ(118);
    super.ʽ();
  }
  
  public void ॱ(coN paramCoN)
  {
    ˎ(0, paramCoN);
    this.ˌ = paramCoN;
    try
    {
      this.ॱʻ |= 1L;
    }
    finally
    {
      paramCoN = finally;
      throw paramCoN;
    }
    ˊ(70);
    super.ʽ();
  }
  
  public void ॱ(boolean paramBoolean)
  {
    this.ˋᐝ = paramBoolean;
    try
    {
      this.ॱʻ |= 0x2;
    }
    finally
    {
      localObject = finally;
      throw localObject;
    }
    ˊ(73);
    super.ʽ();
  }
  
  public boolean ॱ()
  {
    try
    {
      long l = this.ॱʻ;
      if (l != 0L) {
        return true;
      }
    }
    finally
    {
      localObject = finally;
      throw localObject;
    }
    return false;
  }
  
  public void ॱˊ()
  {
    try
    {
      this.ॱʻ = 1024L;
    }
    finally
    {
      localObject = finally;
      throw localObject;
    }
    ʽ();
  }
}
