package o;

import android.content.res.Resources;
import android.databinding.ViewDataBinding;
import android.databinding.ViewDataBinding.If;
import android.util.SparseIntArray;
import android.view.View;
import android.widget.FrameLayout;
import android.widget.ImageView;
import android.widget.LinearLayout;
import android.widget.ProgressBar;
import android.widget.RelativeLayout;
import android.widget.TextView;
import java.io.UnsupportedEncodingException;

public class Mq
  extends ViewDataBinding
{
  private static final SparseIntArray ʻॱ;
  private static int ˎˏ;
  private static int ˏˏ = 0;
  private static byte ͺॱ;
  private static int ـ = 1;
  private static final ViewDataBinding.If ॱˋ;
  public final ProgressBar ʻ;
  public final KZ ʼ;
  private final ImageView ʼॱ;
  public final у ʽ;
  private final TextView ʽॱ;
  private final RelativeLayout ʾ;
  private final View ʿ;
  private final aA ˈ;
  private String ˉ;
  public final KY ˊ;
  private coN ˊˊ;
  private final KQ ˊˋ;
  public final Je ˊॱ;
  private final TextView ˊᐝ;
  private final LinearLayout ˋˊ;
  private boolean ˋˋ;
  public final LinearLayout ˋॱ;
  private FW ˋᐝ;
  private String ˌ;
  private boolean ˍ;
  public final ImageView ˎ;
  private FS ˎˎ;
  private boolean ˏˎ;
  public final Ꭸ ˏॱ;
  private long ˑ = -1L;
  public final Ꭸ ͺ;
  public final FrameLayout ॱ;
  public final TextView ॱˊ;
  public final Je ॱˎ;
  public final LinearLayout ॱॱ;
  public final Je ॱᐝ;
  public final RelativeLayout ᐝ;
  public final Je ᐝॱ;
  
  static
  {
    ॱˋ();
    ˋॱ();
    ॱˋ = null;
    ʻॱ = new SparseIntArray();
    ʻॱ.put(2131296586, 21);
    ʻॱ.put(2131296654, 22);
    ʻॱ.put(2131296270, 23);
    int i = ˏˏ + 63;
    ـ = i % 128;
    if (i % 2 != 0) {}
  }
  
  public Mq(ˉ paramˉ, View paramView)
  {
    super(paramˉ, paramView, 1);
    paramˉ = ॱ(paramˉ, paramView, 24, ॱˋ, ʻॱ);
    this.ˎ = ((ImageView)paramˉ[1]);
    this.ˎ.setTag(null);
    this.ॱ = ((FrameLayout)paramˉ[23]);
    this.ˊ = ((KY)paramˉ[20]);
    this.ˊ.setTag(null);
    this.ʼ = ((KZ)paramˉ[5]);
    this.ʼ.setTag(null);
    this.ʾ = ((RelativeLayout)paramˉ[0]);
    this.ʾ.setTag(null);
    this.ʽॱ = ((TextView)paramˉ[14]);
    this.ʽॱ.setTag(null);
    this.ʿ = ((View)paramˉ[18]);
    this.ʿ.setTag(null);
    this.ʼॱ = ((ImageView)paramˉ[3]);
    this.ʼॱ.setTag(null);
    this.ˈ = ((aA)paramˉ[4]);
    this.ˈ.setTag(null);
    this.ˊᐝ = ((TextView)paramˉ[6]);
    this.ˊᐝ.setTag(null);
    this.ˋˊ = ((LinearLayout)paramˉ[7]);
    this.ˋˊ.setTag(null);
    this.ˊˋ = ((KQ)paramˉ[9]);
    this.ˊˋ.setTag(null);
    this.ᐝ = ((RelativeLayout)paramˉ[21]);
    this.ॱॱ = ((LinearLayout)paramˉ[13]);
    this.ॱॱ.setTag(null);
    this.ʻ = ((ProgressBar)paramˉ[22]);
    this.ʽ = ((у)paramˉ[2]);
    this.ʽ.setTag(null);
    this.ˋॱ = ((LinearLayout)paramˉ[15]);
    this.ˋॱ.setTag(null);
    this.ͺ = ((Ꭸ)paramˉ[8]);
    this.ͺ.setTag(null);
    this.ॱˊ = ((TextView)paramˉ[10]);
    this.ॱˊ.setTag(null);
    this.ˊॱ = ((Je)paramˉ[11]);
    this.ˊॱ.setTag(null);
    this.ˏॱ = ((Ꭸ)paramˉ[12]);
    this.ˏॱ.setTag(null);
    this.ॱᐝ = ((Je)paramˉ[16]);
    this.ॱᐝ.setTag(null);
    this.ॱˎ = ((Je)paramˉ[19]);
    this.ॱˎ.setTag(null);
    this.ᐝॱ = ((Je)paramˉ[17]);
    this.ᐝॱ.setTag(null);
    ˋ(paramView);
    ॱˊ();
  }
  
  private boolean ˊ(coN paramCoN, int paramInt)
  {
    if (paramInt == 0)
    {
      try
      {
        this.ˑ |= 1L;
      }
      finally
      {
        paramCoN = finally;
        throw paramCoN;
      }
      return true;
    }
    return false;
  }
  
  /* Error */
  private static String ˋ(int paramInt1, int paramInt2, char[] paramArrayOfChar, int paramInt3, boolean paramBoolean)
  {
    // Byte code:
    //   0: goto +239 -> 239
    //   3: iconst_1
    //   4: istore 5
    //   6: goto +9 -> 15
    //   9: iconst_1
    //   10: istore 6
    //   12: goto +109 -> 121
    //   15: iload 5
    //   17: tableswitch	default:+23->40, 0:+254->271, 1:+265->282
    //   40: goto +242 -> 282
    //   43: aload 9
    //   45: astore_2
    //   46: iload_0
    //   47: lookupswitch	default:+25->72, 13:+437->484, 59:+332->379
    //   72: aload 9
    //   74: astore_2
    //   75: goto +409 -> 484
    //   78: astore_2
    //   79: aload_2
    //   80: athrow
    //   81: aload 9
    //   83: iload 5
    //   85: iload_0
    //   86: aload_2
    //   87: iload 5
    //   89: caload
    //   90: iadd
    //   91: i2c
    //   92: castore
    //   93: aload 9
    //   95: iload 5
    //   97: caload
    //   98: istore 6
    //   100: aload 9
    //   102: iload 5
    //   104: iload 6
    //   106: getstatic 208	o/Mq:ˎˏ	I
    //   109: isub
    //   110: i2c
    //   111: castore
    //   112: iload 5
    //   114: iconst_1
    //   115: iadd
    //   116: istore 5
    //   118: goto +29 -> 147
    //   121: iload 6
    //   123: tableswitch	default:+21->144, 0:+-42->81, 1:+43->166
    //   144: goto -63 -> 81
    //   147: iload_3
    //   148: istore 8
    //   150: iload_1
    //   151: istore 7
    //   153: iload 5
    //   155: iload 7
    //   157: if_icmpge +6 -> 163
    //   160: goto +357 -> 517
    //   163: goto -154 -> 9
    //   166: iload 8
    //   168: ifle +6 -> 174
    //   171: goto +322 -> 493
    //   174: goto +249 -> 423
    //   177: iload 7
    //   179: newarray char
    //   181: astore_2
    //   182: aload 9
    //   184: iconst_0
    //   185: aload_2
    //   186: iconst_0
    //   187: iload 7
    //   189: invokestatic 214	java/lang/System:arraycopy	(Ljava/lang/Object;ILjava/lang/Object;II)V
    //   192: aload_2
    //   193: iconst_0
    //   194: aload 9
    //   196: iload 7
    //   198: iload 8
    //   200: isub
    //   201: iload 8
    //   203: invokestatic 214	java/lang/System:arraycopy	(Ljava/lang/Object;ILjava/lang/Object;II)V
    //   206: aload_2
    //   207: iload 8
    //   209: aload 9
    //   211: iconst_0
    //   212: iload 7
    //   214: iload 8
    //   216: isub
    //   217: invokestatic 214	java/lang/System:arraycopy	(Ljava/lang/Object;ILjava/lang/Object;II)V
    //   220: goto +285 -> 505
    //   223: iload 7
    //   225: newarray char
    //   227: astore_2
    //   228: iconst_0
    //   229: istore_0
    //   230: goto +181 -> 411
    //   233: bipush 13
    //   235: istore_0
    //   236: goto -193 -> 43
    //   239: goto +215 -> 454
    //   242: iload_1
    //   243: lookupswitch	default:+25->268, 65:+256->499, 66:+192->435
    //   268: goto +167 -> 435
    //   271: iload_1
    //   272: newarray char
    //   274: astore 9
    //   276: iconst_0
    //   277: istore 5
    //   279: goto -132 -> 147
    //   282: iload_1
    //   283: newarray char
    //   285: astore 9
    //   287: iconst_0
    //   288: istore 5
    //   290: goto -143 -> 147
    //   293: iload 4
    //   295: ifeq +6 -> 301
    //   298: goto +45 -> 343
    //   301: goto -68 -> 233
    //   304: bipush 65
    //   306: istore_1
    //   307: goto -65 -> 242
    //   310: bipush 66
    //   312: istore_1
    //   313: goto -71 -> 242
    //   316: getstatic 73	o/Mq:ـ	I
    //   319: bipush 105
    //   321: iadd
    //   322: istore_0
    //   323: iload_0
    //   324: sipush 128
    //   327: irem
    //   328: putstatic 71	o/Mq:ˏˏ	I
    //   331: iload_0
    //   332: iconst_2
    //   333: irem
    //   334: ifeq +6 -> 340
    //   337: goto +71 -> 408
    //   340: goto -163 -> 177
    //   343: bipush 59
    //   345: istore_0
    //   346: goto -303 -> 43
    //   349: iload_0
    //   350: lookupswitch	default:+26->376, 25:+-34->316, 93:+-57->293
    //   376: goto -60 -> 316
    //   379: getstatic 71	o/Mq:ˏˏ	I
    //   382: istore_0
    //   383: iload_0
    //   384: bipush 107
    //   386: iadd
    //   387: istore_0
    //   388: iload_0
    //   389: sipush 128
    //   392: irem
    //   393: putstatic 73	o/Mq:ـ	I
    //   396: iload_0
    //   397: iconst_2
    //   398: irem
    //   399: ifne +6 -> 405
    //   402: goto +100 -> 502
    //   405: goto -182 -> 223
    //   408: goto -231 -> 177
    //   411: iload_0
    //   412: iload 7
    //   414: if_icmpge +6 -> 420
    //   417: goto -107 -> 310
    //   420: goto -116 -> 304
    //   423: bipush 93
    //   425: istore_0
    //   426: goto -77 -> 349
    //   429: goto -18 -> 411
    //   432: astore_2
    //   433: aload_2
    //   434: athrow
    //   435: aload_2
    //   436: iload_0
    //   437: aload 9
    //   439: iload 7
    //   441: iload_0
    //   442: isub
    //   443: iconst_1
    //   444: isub
    //   445: caload
    //   446: castore
    //   447: iload_0
    //   448: iconst_1
    //   449: iadd
    //   450: istore_0
    //   451: goto -22 -> 429
    //   454: getstatic 71	o/Mq:ˏˏ	I
    //   457: bipush 21
    //   459: iadd
    //   460: istore 5
    //   462: iload 5
    //   464: sipush 128
    //   467: irem
    //   468: putstatic 73	o/Mq:ـ	I
    //   471: iload 5
    //   473: iconst_2
    //   474: irem
    //   475: ifne +6 -> 481
    //   478: goto +30 -> 508
    //   481: goto -478 -> 3
    //   484: new 216	java/lang/String
    //   487: dup
    //   488: aload_2
    //   489: invokespecial 219	java/lang/String:<init>	([C)V
    //   492: areturn
    //   493: bipush 25
    //   495: istore_0
    //   496: goto -147 -> 349
    //   499: goto +15 -> 514
    //   502: goto -279 -> 223
    //   505: goto -212 -> 293
    //   508: iconst_0
    //   509: istore 5
    //   511: goto -496 -> 15
    //   514: goto -30 -> 484
    //   517: iconst_0
    //   518: istore 6
    //   520: goto -399 -> 121
    // Local variable table:
    //   start	length	slot	name	signature
    //   0	523	0	paramInt1	int
    //   0	523	1	paramInt2	int
    //   0	523	2	paramArrayOfChar	char[]
    //   0	523	3	paramInt3	int
    //   0	523	4	paramBoolean	boolean
    //   4	506	5	i	int
    //   10	509	6	j	int
    //   151	292	7	k	int
    //   148	69	8	m	int
    //   43	395	9	localObject	Object
    // Exception table:
    //   from	to	target	type
    //   388	396	78	java/lang/Exception
    //   100	112	432	java/lang/Exception
    //   379	383	432	java/lang/Exception
  }
  
  private String ˋ(String paramString)
  {
    break label60;
    int j = 80;
    break label202;
    byte[] arrayOfByte;
    label60:
    int i;
    try
    {
      paramString = new String(arrayOfByte, ˋ(87, 5, new char[] { -23, 2, 16, 17, -12 }, 4, true).intern());
      return paramString;
    }
    catch (UnsupportedEncodingException paramString)
    {
      label180:
      label183:
      throw new RuntimeException(paramString);
    }
    for (;;)
    {
      j = ـ + 17;
      ˏˏ = j % 128;
      if (j % 2 == 0)
      {
        break;
        paramString = paramString.getBytes(ˋ(78, 10, new char[] { -14, -3, -3, -6, -2, -14, -10, 14, 24, 20 }, 7, false).intern());
        arrayOfByte = new byte[paramString.length];
        i = 0;
      }
      else
      {
        break;
      }
    }
    for (;;)
    {
      break label255;
      j = 71;
      label202:
      label255:
      label272:
      do
      {
        break label180;
        switch (j)
        {
        case 80: 
        default: 
          break;
        case 71: 
          arrayOfByte[i] = ((byte)(paramString[(paramString.length - i - 1)] ^ ͺॱ));
          i += 1;
          break label272;
          for (;;)
          {
            j = paramString.length;
            if (i < j) {
              break label183;
            }
            break;
          }
          j = ـ + 13;
          ˏˏ = j % 128;
        }
      } while (j % 2 != 0);
    }
  }
  
  static void ˋॱ()
  {
    for (;;)
    {
      try
      {
        ͺॱ = -102;
      }
      catch (Exception localException)
      {
        throw localException;
      }
      i = ˏˏ + 99;
      ـ = i % 128;
      if (i % 2 == 0) {
        break;
      }
    }
    int i = ˏˏ + 125;
    ـ = i % 128;
    if (i % 2 == 0) {}
  }
  
  static void ॱˋ()
  {
    ˎˏ = 19;
  }
  
  public void ˊ(String paramString)
  {
    this.ˌ = paramString;
    try
    {
      this.ˑ |= 0x8;
    }
    finally
    {
      paramString = finally;
      throw paramString;
    }
    ˊ(118);
    super.ʽ();
  }
  
  public void ˊ(FS paramFS)
  {
    this.ˎˎ = paramFS;
    try
    {
      this.ˑ |= 0x20;
    }
    finally
    {
      paramFS = finally;
      throw paramFS;
    }
    ˊ(24);
    super.ʽ();
  }
  
  public void ˊ(FW paramFW)
  {
    this.ˋᐝ = paramFW;
    try
    {
      this.ˑ |= 0x4;
    }
    finally
    {
      paramFW = finally;
      throw paramFW;
    }
    ˊ(127);
    super.ʽ();
  }
  
  public void ˊ(boolean paramBoolean)
  {
    this.ˍ = paramBoolean;
    try
    {
      this.ˑ |= 0x40;
    }
    finally
    {
      localObject = finally;
      throw localObject;
    }
    ˊ(59);
    super.ʽ();
  }
  
  public FS ˊॱ()
  {
    for (;;)
    {
      int i = ـ + 7;
      ˏˏ = i % 128;
      if (i % 2 == 0) {}
      FS localFS;
      for (;;)
      {
        localFS = this.ˎˎ;
        break;
      }
      i = ˏˏ + 13;
      ـ = i % 128;
      if (i % 2 == 0) {
        return localFS;
      }
      return localFS;
    }
  }
  
  public void ˋ(boolean paramBoolean)
  {
    this.ˏˎ = paramBoolean;
    try
    {
      this.ˑ |= 0x80;
    }
    finally
    {
      localObject = finally;
      throw localObject;
    }
    ˊ(60);
    super.ʽ();
  }
  
  public void ˎ(String paramString)
  {
    this.ˉ = paramString;
    try
    {
      this.ˑ |= 0x2;
    }
    finally
    {
      paramString = finally;
      throw paramString;
    }
    ˊ(123);
    super.ʽ();
  }
  
  public void ˎ(coN paramCoN)
  {
    ˎ(0, paramCoN);
    this.ˊˊ = paramCoN;
    try
    {
      this.ˑ |= 1L;
    }
    finally
    {
      paramCoN = finally;
      throw paramCoN;
    }
    ˊ(70);
    super.ʽ();
  }
  
  public void ˎ(boolean paramBoolean)
  {
    this.ˋˋ = paramBoolean;
    try
    {
      this.ˑ |= 0x10;
    }
    finally
    {
      localObject = finally;
      throw localObject;
    }
    ˊ(58);
    super.ʽ();
  }
  
  public void ˏ()
  {
    String str4 = ˋ(32, 4, new char[] { -1, -8, 13, -2 }, 1, false).intern();
    try
    {
      l2 = this.ˑ;
      this.ˑ = 0L;
    }
    finally
    {
      localObject1 = finally;
      throw localObject1;
    }
    int n = 0;
    int i1 = 0;
    coN localCoN = this.ˊˊ;
    Object localObject3 = null;
    Object localObject12 = null;
    Object localObject31 = null;
    Object localObject13 = null;
    Object localObject4 = null;
    int k = 0;
    Object localObject30 = null;
    int i10 = 0;
    boolean bool1 = false;
    boolean bool2 = false;
    int i6 = 0;
    int i = 0;
    int i9 = 0;
    String str2 = this.ˉ;
    int i11 = 0;
    FW localFW = this.ˋᐝ;
    Object localObject5 = null;
    Object localObject14 = null;
    Object localObject29 = null;
    String str3 = this.ˌ;
    Object localObject28 = null;
    Object localObject22 = null;
    int i16 = 0;
    int i15 = 0;
    boolean bool5 = false;
    Object localObject15 = null;
    Object localObject2 = null;
    boolean bool8 = this.ˋˋ;
    int i18 = 0;
    boolean bool7 = false;
    int i20 = 0;
    boolean bool6 = false;
    int i14 = 0;
    float f1 = 0.0F;
    Object localObject16 = null;
    String str1 = null;
    FS localFS = this.ˎˎ;
    int i19 = 0;
    boolean bool3 = this.ˍ;
    int i13 = 0;
    Object localObject7 = null;
    Object localObject6 = null;
    Object localObject27 = null;
    int i8 = 0;
    int i2 = 0;
    int m = 0;
    Object localObject8 = null;
    Object localObject17 = null;
    Object localObject26 = null;
    Object localObject9 = null;
    Object localObject18 = null;
    Object localObject25 = null;
    float f3 = 0.0F;
    int i7 = 0;
    int i3 = 0;
    Object localObject10 = null;
    Object localObject19 = null;
    Object localObject24 = null;
    int i17 = 0;
    int i12 = 0;
    boolean bool4 = false;
    Object localObject11 = null;
    Object localObject20 = null;
    Object localObject23 = null;
    boolean bool9 = this.ˏˎ;
    Object localObject21 = null;
    double d = 0.0D;
    long l1 = l2;
    int j = k;
    if ((0x105 & l2) != 0L)
    {
      if (localCoN != null) {
        bool2 = localCoN.ˊ();
      }
      l1 = l2;
      if ((0x101 & l2) != 0L) {
        if (bool2) {
          l1 = l2 | 0x4000;
        } else {
          l1 = l2 | 0x2000;
        }
      }
      l2 = l1;
      if ((0x105 & l1) != 0L) {
        if (bool2) {
          l2 = l1 | 0x100000000000;
        } else {
          l2 = l1 | 0x80000000000;
        }
      }
      l1 = l2;
      j = k;
      bool1 = bool2;
      if ((0x101 & l2) != 0L) {
        if (bool2)
        {
          j = 0;
          l1 = l2;
          bool1 = bool2;
        }
        else
        {
          j = 8;
          bool1 = bool2;
          l1 = l2;
        }
      }
    }
    long l2 = l1;
    int i5 = i18;
    float f2 = f1;
    k = i19;
    if ((0x144 & l1) != 0L)
    {
      l2 = l1;
      bool2 = bool7;
      if ((0x104 & l1) != 0L)
      {
        localObject3 = localObject31;
        localObject4 = localObject30;
        localObject5 = localObject29;
        localObject2 = localObject28;
        bool2 = bool6;
        localObject7 = localObject27;
        localObject8 = localObject26;
        localObject9 = localObject25;
        localObject10 = localObject24;
        if (localFW != null)
        {
          localObject3 = localFW.ॱᐝ();
          localObject4 = localFW.ʼ();
          localObject5 = localFW.ॱˋ();
          localObject2 = localFW.ˏ();
          bool2 = localFW.ʽॱ();
          localObject7 = localFW.ॱॱ();
          localObject8 = localFW.ˏ(ᐝ().getContext());
          localObject9 = localFW.ʻ();
          localObject10 = localFW.ʽ();
          d = localFW.ॱ();
        }
        l2 = l1;
        if ((0x400 & l1) != 0L) {
          if (bool2) {
            l2 = l1 | 0x40000000;
          } else {
            l2 = l1 | 0x20000000;
          }
        }
        l1 = l2;
        if ((0x104 & l2) != 0L) {
          if (bool2) {
            l1 = l2 | 0x40000000000;
          } else {
            l1 = l2 | 0x20000000000;
          }
        }
        if (localFW != null) {
          i2 = 1;
        } else {
          i2 = 0;
        }
        l2 = l1;
        if ((0x104 & l1) != 0L) {
          if (i2 != 0) {
            l2 = l1 | 0x400;
          } else {
            l2 = l1 | 0x200;
          }
        }
        localObject4 = aq.ॱ((String)localObject4);
        if (bool2) {
          i3 = 8;
        } else {
          i3 = 0;
        }
        if (localObject7 == FV.ACCEPTED) {
          i1 = 1;
        } else {
          i1 = 0;
        }
        if (localObject7 == FV.CANCELED) {
          i = 1;
        } else {
          i = 0;
        }
        str1 = at.ˎ(d);
        l1 = l2;
        if ((0x2000000000000 & l2) != 0L) {
          if (i1 != 0) {
            l1 = l2 | 0x400000;
          } else {
            l1 = l2 | 0x200000;
          }
        }
        l2 = l1;
        if ((0x104 & l1) != 0L) {
          if (i1 != 0) {
            l2 = l1 | 0x4000000;
          } else {
            l2 = l1 | 0x2000000;
          }
        }
        l1 = l2;
        if ((0x104 & l2) != 0L) {
          if (i != 0) {
            l1 = l2 | 0x40000;
          } else {
            l1 = l2 | 0x20000;
          }
        }
        localObject11 = localObject23;
        if (localObject2 != null) {
          localObject11 = ((Ep)localObject2).ˊ();
        }
        if (i1 != 0)
        {
          localObject6 = this.ˊ.getResources().getString(2131755430);
          localObject2 = localObject6;
          if (((String)localObject6).startsWith(str4)) {
            localObject2 = ˋ(((String)localObject6).substring(4)).intern();
          }
        }
        else
        {
          localObject6 = this.ˊ.getResources().getString(2131755044);
          localObject2 = localObject6;
          if (((String)localObject6).startsWith(str4)) {
            localObject2 = ˋ(((String)localObject6).substring(4)).intern();
          }
        }
        if (i != 0)
        {
          i = 0;
          l2 = l1;
        }
        else
        {
          i = 8;
          l2 = l1;
        }
      }
      int i4;
      if (localFW == null) {
        i4 = 1;
      } else {
        i4 = 0;
      }
      l1 = l2;
      if ((0x144 & l2) != 0L) {
        if (i4 != 0) {
          l1 = l2 | 0x1000 | 0x4000000000;
        } else {
          l1 = l2 | 0x800 | 0x2000000000;
        }
      }
      l3 = l1;
      if ((0x104 & l1) != 0L) {
        if (i4 != 0) {
          l3 = l1 | 0x10000000 | 0x100000000 | 0x400000000;
        } else {
          l3 = l1 | 0x8000000 | 0x80000000 | 0x200000000;
        }
      }
      l2 = l3;
      n = i1;
      localObject12 = localObject3;
      localObject13 = localObject4;
      i6 = i;
      localObject14 = localObject5;
      localObject15 = localObject2;
      i5 = i18;
      i20 = bool2;
      f2 = f1;
      localObject16 = str1;
      k = i19;
      localObject6 = localObject7;
      i8 = i2;
      m = i4;
      localObject17 = localObject8;
      localObject18 = localObject9;
      i7 = i3;
      localObject19 = localObject10;
      localObject20 = localObject11;
      if ((0x104 & l3) != 0L)
      {
        if (i4 != 0) {
          i5 = ˋ(this.ˏॱ, 17170445);
        } else {
          i5 = ˋ(this.ˏॱ, 2131099797);
        }
        if (i4 != 0) {
          f1 = this.ˏॱ.getResources().getDimension(2131165260);
        } else {
          f1 = this.ˏॱ.getResources().getDimension(2131165259);
        }
        if (i4 != 0)
        {
          k = 4;
          l2 = l3;
          n = i1;
          localObject12 = localObject3;
          localObject13 = localObject4;
          i6 = i;
          localObject14 = localObject5;
          localObject15 = localObject2;
          i20 = bool2;
          f2 = f1;
          localObject16 = str1;
          localObject6 = localObject7;
          i8 = i2;
          m = i4;
          localObject17 = localObject8;
          localObject18 = localObject9;
          i7 = i3;
          localObject19 = localObject10;
          localObject20 = localObject11;
        }
        else
        {
          k = 0;
          localObject20 = localObject11;
          localObject19 = localObject10;
          i7 = i3;
          localObject18 = localObject9;
          localObject17 = localObject8;
          m = i4;
          i8 = i2;
          localObject6 = localObject7;
          localObject16 = str1;
          f2 = f1;
          i20 = bool2;
          localObject15 = localObject2;
          localObject14 = localObject5;
          i6 = i;
          localObject13 = localObject4;
          localObject12 = localObject3;
          n = i1;
          l2 = l3;
        }
      }
    }
    l1 = l2;
    i1 = i17;
    if ((0x195 & l2) != 0L)
    {
      l3 = l2;
      if ((0x114 & l2) != 0L) {
        if (bool8) {
          l3 = l2 | 0x4000000000000;
        } else {
          l3 = l2 | 0x2000000000000;
        }
      }
      l1 = l3;
      i1 = i17;
      if ((0x191 & l3) != 0L)
      {
        if (!bool8) {
          i = 1;
        } else {
          i = 0;
        }
        l1 = l3;
        i1 = i;
        if ((0x191 & l3) != 0L) {
          if (i != 0)
          {
            l1 = l3 | 0x1000000;
            i1 = i;
          }
          else
          {
            l1 = l3 | 0x800000;
            i1 = i;
          }
        }
      }
    }
    l2 = l1;
    localObject2 = localObject22;
    if ((0x2000020000000 & l1) != 0L)
    {
      if (localFW != null) {
        localObject6 = localFW.ॱॱ();
      }
      if (localObject6 == FV.ACCEPTED) {
        i = 1;
      } else {
        i = 0;
      }
      l2 = l1;
      if ((0x2000000000000 & l1) != 0L) {
        if (i != 0) {
          l2 = l1 | 0x400000;
        } else {
          l2 = l1 | 0x200000;
        }
      }
      l1 = l2;
      if ((0x104 & l2) != 0L) {
        if (i != 0) {
          l1 = l2 | 0x4000000;
        } else {
          l1 = l2 | 0x2000000;
        }
      }
      l2 = l1;
      n = i;
      localObject2 = localObject22;
      if ((0x2000000000000 & l1) != 0L) {
        if (i != 0)
        {
          localObject3 = this.ʼ.getResources().getString(2131755427);
          localObject2 = localObject3;
          if (((String)localObject3).startsWith(str4)) {
            localObject2 = ˋ(((String)localObject3).substring(4)).intern();
          }
          l2 = l1;
          n = i;
        }
        else
        {
          localObject3 = this.ʼ.getResources().getString(2131755428);
          l2 = l1;
          n = i;
          localObject2 = localObject3;
          if (((String)localObject3).startsWith(str4))
          {
            localObject2 = ˋ(((String)localObject3).substring(4)).intern();
            n = i;
            l2 = l1;
          }
        }
      }
    }
    i = i16;
    if ((0x1000000 & l2) != 0L) {
      if (!bool9) {
        i = 1;
      } else {
        i = 0;
      }
    }
    l1 = l2;
    i2 = i15;
    if ((0x191 & l2) != 0L)
    {
      if (i1 == 0) {
        i = 0;
      }
      l1 = l2;
      i2 = i;
      if ((0x191 & l2) != 0L) {
        if (i != 0)
        {
          l1 = l2 | 0x1000000000000;
          i2 = i;
        }
        else
        {
          l1 = l2 | 0x800000000000;
          i2 = i;
        }
      }
    }
    i = i14;
    if ((0x400 & l1) != 0L) {
      if (i20 != 0) {
        i = 1;
      } else {
        i = n;
      }
    }
    localObject3 = localObject21;
    if ((0x114 & l1) != 0L) {
      if (bool8)
      {
        localObject2 = this.ʼ.getResources().getString(2131755423);
        localObject3 = localObject2;
        if (((String)localObject2).startsWith(str4)) {
          localObject3 = ˋ(((String)localObject2).substring(4)).intern();
        }
      }
      else
      {
        localObject3 = localObject2;
      }
    }
    l2 = l1;
    n = i13;
    if ((0x104 & l1) != 0L)
    {
      if (i8 == 0) {
        i = 0;
      }
      l2 = l1;
      if ((0x104 & l1) != 0L) {
        if (i != 0) {
          l2 = l1 | 0x1000000000;
        } else {
          l2 = l1 | 0x800000000;
        }
      }
      if (i != 0) {
        n = 0;
      } else {
        n = 8;
      }
    }
    long l3 = l2;
    i20 = bool1;
    bool2 = bool5;
    if ((0x1000000000000 & l2) != 0L)
    {
      if (localCoN != null) {
        bool1 = localCoN.ˊ();
      }
      l1 = l2;
      if ((0x101 & l2) != 0L) {
        if (bool1) {
          l1 = l2 | 0x4000;
        } else {
          l1 = l2 | 0x2000;
        }
      }
      l3 = l1;
      if ((0x105 & l1) != 0L) {
        if (bool1) {
          l3 = l1 | 0x100000000000;
        } else {
          l3 = l1 | 0x80000000000;
        }
      }
      if (!bool1)
      {
        bool2 = true;
        i20 = bool1;
      }
      else
      {
        bool2 = false;
        i20 = bool1;
      }
    }
    bool1 = bool4;
    if ((0x191 & l3) != 0L) {
      if (i2 != 0) {
        bool1 = bool2;
      } else {
        bool1 = false;
      }
    }
    l1 = l3;
    if ((0x80000000000 & l3) != 0L)
    {
      if (localFW == null) {
        i = 1;
      } else {
        i = 0;
      }
      l2 = l3;
      if ((0x144 & l3) != 0L) {
        if (i != 0) {
          l2 = l3 | 0x1000 | 0x4000000000;
        } else {
          l2 = l3 | 0x800 | 0x2000000000;
        }
      }
      l1 = l2;
      m = i;
      if ((0x104 & l2) != 0L) {
        if (i != 0)
        {
          l1 = l2 | 0x10000000 | 0x100000000 | 0x400000000;
          m = i;
        }
        else
        {
          l1 = l2 | 0x8000000 | 0x80000000 | 0x200000000;
          m = i;
        }
      }
    }
    l2 = l1;
    i1 = i12;
    if ((0x105 & l1) != 0L)
    {
      if (i20 != 0) {
        i = 1;
      } else {
        i = m;
      }
      l2 = l1;
      if ((0x105 & l1) != 0L) {
        if (i != 0) {
          l2 = l1 | 0x400000000000;
        } else {
          l2 = l1 | 0x200000000000;
        }
      }
      if (i != 0) {
        i1 = 4;
      } else {
        i1 = 0;
      }
    }
    i = i11;
    if ((0x2000000800 & l2) != 0L)
    {
      i = i11;
      if ((0x800 & l2) != 0L) {
        if (!bool3) {
          i = 1;
        } else {
          i = 0;
        }
      }
    }
    l1 = l2;
    i2 = i10;
    i3 = i9;
    f1 = f3;
    if ((0x144 & l2) != 0L)
    {
      if (m != 0) {
        i = 1;
      }
      if (m != 0) {
        bool2 = true;
      } else {
        bool2 = bool3;
      }
      l1 = l2;
      if ((0x144 & l2) != 0L) {
        if (i != 0) {
          l1 = l2 | 0x10000;
        } else {
          l1 = l2 | 0x8000;
        }
      }
      l2 = l1;
      if ((0x144 & l1) != 0L) {
        if (bool2) {
          l2 = l1 | 0x100000 | 0x10000000000;
        } else {
          l2 = l1 | 0x80000 | 0x8000000000;
        }
      }
      if (i != 0) {
        i = 4;
      } else {
        i = 0;
      }
      if (bool2) {
        m = 4;
      } else {
        m = 0;
      }
      if (bool2)
      {
        f1 = this.ˋˊ.getResources().getDimension(2131165398);
        l1 = l2;
        i2 = i;
        i3 = m;
      }
      else
      {
        f1 = this.ˋˊ.getResources().getDimension(2131165399);
        i3 = m;
        i2 = i;
        l1 = l2;
      }
    }
    if ((0x100 & l1) != 0L)
    {
      r.ˊ(this.ˎ, ˋ(109, 77, new char[] { 14, 26, -43, 25, 13, 20, 15, 26, 26, 11, 25, -43, -41, 28, -43, 15, 22, 7, -43, 26, 11, 18, 18, 7, 29, 26, 8, -43, 21, 24, -44, 18, 24, 26, 8, -44, 20, 11, -45, 31, 7, 22, 26, 8, -43, -43, -32, 25, 22, 26, 26, 14, -21, -19, -25, -13, -17, 5, -22, -12, -5, -11, -8, -19, -15, -23, -25, -24, -43, 11, 13, 7, 19, -17, 11, 19, 11 }, 52, true).intern(), ॱ(this.ˎ, 2131230823), true);
      this.ʼ.setViewPagerHeight(this.ʼ.getResources().getDimension(2131165400));
      localObject5 = this.ʽॱ;
      localObject4 = this.ʽॱ.getResources().getString(2131755246);
      localObject2 = localObject4;
      if (((String)localObject4).startsWith(str4)) {
        localObject2 = ˋ(((String)localObject4).substring(4)).intern();
      }
      ʹ.ˊ((TextView)localObject5, (CharSequence)localObject2);
      this.ˈ.setShadowBottom(ॱ(this.ˈ, 2131231257));
      this.ˈ.setShadowTop(ॱ(this.ˈ, 2131231258));
      this.ˊˋ.setShowPhoneType(false);
      localObject5 = this.ॱᐝ;
      localObject4 = this.ॱᐝ.getResources().getString(2131755477);
      localObject2 = localObject4;
      if (((String)localObject4).startsWith(str4)) {
        localObject2 = ˋ(((String)localObject4).substring(4)).intern();
      }
      ((Je)localObject5).setLabel((String)localObject2);
      localObject5 = this.ॱˎ;
      localObject4 = this.ॱˎ.getResources().getString(2131755421);
      localObject2 = localObject4;
      if (((String)localObject4).startsWith(str4)) {
        localObject2 = ˋ(((String)localObject4).substring(4)).intern();
      }
      ((Je)localObject5).setLabel((String)localObject2);
    }
    if ((0x191 & l1) != 0L) {
      this.ˊ.setEnabled(bool1);
    }
    if ((0x104 & l1) != 0L)
    {
      ʹ.ˊ(this.ˊ, localObject15);
      this.ˊ.setVisibility(n);
      this.ʿ.setVisibility(i6);
      this.ʼॱ.setVisibility(i7);
      this.ˊˋ.setPhoneNumber(localObject18);
      this.ͺ.setVisibility(k);
      ʹ.ˊ(this.ॱˊ, localObject19);
      this.ˊॱ.setValue(localObject16);
      this.ˊॱ.setValueInfo(localObject20);
      this.ˏॱ.setCardBackgroundColor(i5);
      this.ˏॱ.setCardElevation(f2);
      this.ॱᐝ.setValue(localObject13);
      this.ॱˎ.setVisibility(i6);
      this.ॱˎ.setValue(localObject12);
      this.ᐝॱ.setLabel(localObject17);
      this.ᐝॱ.setValue(localObject14);
    }
    if ((0x144 & l1) != 0L)
    {
      this.ʼ.setVisibility(i2);
      this.ˊᐝ.setVisibility(i3);
      A.ˋ(this.ˋˊ, f1, 0.0F, 0.0F, 0.0F);
    }
    if ((0x114 & l1) != 0L) {
      this.ʼ.setPaymentHint((String)localObject3);
    }
    if ((0x108 & l1) != 0L) {
      ʹ.ˊ(this.ˊᐝ, str3);
    }
    if ((0x120 & l1) != 0L) {
      this.ˊˋ.setContactPerson(localFS);
    }
    if ((0x101 & l1) != 0L) {
      this.ॱॱ.setVisibility(j);
    }
    if ((0x102 & l1) != 0L) {
      this.ʽ.setTitle(str2);
    }
    if ((0x105 & l1) != 0L) {
      this.ˋॱ.setVisibility(i1);
    }
  }
  
  public boolean ˏ(int paramInt1, Object paramObject, int paramInt2)
  {
    break label60;
    boolean bool;
    return bool;
    int i = 55 / 0;
    switch (paramInt1)
    {
    default: 
      break;
    case 0: 
      try
      {
        paramObject = (coN)paramObject;
        bool = ˊ(paramObject, paramInt2);
      }
      catch (Exception paramObject)
      {
        throw paramObject;
      }
      paramInt1 = 41;
      break;
    }
    label60:
    break label163;
    label72:
    label128:
    for (;;)
    {
      return false;
      i = 97;
      break label131;
      switch (paramInt1)
      {
      }
      break label128;
      for (;;)
      {
        paramInt1 = 47;
        break label203;
        paramInt1 = ـ + 115;
        ˏˏ = paramInt1 % 128;
        if (paramInt1 % 2 != 0) {
          break;
        }
      }
    }
    for (;;)
    {
      label131:
      switch (i)
      {
      }
      break label72;
      label163:
      i = ـ + 101;
      ˏˏ = i % 128;
      if (i % 2 != 0) {
        break;
      }
      i = 25;
    }
    paramInt1 = null.length;
    return bool;
    label203:
    switch (paramInt1)
    {
    }
    return bool;
  }
  
  public FW ˏॱ()
  {
    break label66;
    break label69;
    label6:
    int i = ˏˏ + 19;
    ـ = i % 128;
    FW localFW;
    if (i % 2 != 0)
    {
      break label40;
      return localFW;
    }
    else
    {
      i = 0;
      break label42;
    }
    label40:
    i = 1;
    switch (i)
    {
    case 1: 
    default: 
      label42:
      return localFW;
      for (;;)
      {
        label66:
        label69:
        localFW = this.ˋᐝ;
        break label6;
        i = ـ + 3;
        ˏˏ = i % 128;
        if (i % 2 != 0) {
          break;
        }
      }
    }
    i = null.length;
    return localFW;
  }
  
  public boolean ͺ()
  {
    for (;;)
    {
      label35:
      boolean bool;
      switch (i)
      {
      default: 
        break;
      case 57: 
        for (;;)
        {
          i = ˏˏ + 79;
          ـ = i % 128;
          if (i % 2 != 0)
          {
            return bool;
            try
            {
              bool = this.ˋˋ;
              i = 79 / 0;
            }
            catch (Exception localException)
            {
              throw localException;
            }
          }
        }
        return bool;
      }
      do
      {
        i = 57;
        break;
        bool = this.ˋˋ;
        break label35;
        i = ˏˏ + 39;
        ـ = i % 128;
      } while (i % 2 == 0);
      int i = 54;
    }
  }
  
  public boolean ॱ()
  {
    try
    {
      long l = this.ˑ;
      if (l != 0L) {
        return true;
      }
    }
    finally
    {
      localObject = finally;
      throw localObject;
    }
    return false;
  }
  
  public void ॱˊ()
  {
    try
    {
      this.ˑ = 256L;
    }
    finally
    {
      localObject = finally;
      throw localObject;
    }
    ʽ();
  }
}
