package o;

import android.content.res.Resources;
import android.databinding.ViewDataBinding;
import android.databinding.ViewDataBinding.If;
import android.util.SparseIntArray;
import android.view.View;
import android.widget.Button;
import android.widget.FrameLayout;
import android.widget.ImageView;
import android.widget.LinearLayout;
import android.widget.ProgressBar;
import android.widget.RelativeLayout;
import android.widget.TextView;
import java.io.UnsupportedEncodingException;

public class Mr
  extends ViewDataBinding
{
  private static final ViewDataBinding.If ˊˊ;
  private static final SparseIntArray ˋˊ;
  private static byte ᐝˊ;
  private static int ᐝˋ;
  private static int ᐧ = 0;
  private static long ᐨ;
  public final RelativeLayout ʻ;
  public final Ꭸ ʻॱ;
  public final у ʼ;
  public final Je ʼॱ;
  public final ImageView ʽ;
  public final Ꭸ ʽॱ;
  public final Je ʾ;
  public final Je ʿ;
  public final Je ˈ;
  private final TextView ˉ;
  public final View ˊ;
  private final RelativeLayout ˊˋ;
  public final KZ ˊॱ;
  private final View ˊᐝ;
  private final ImageView ˋˋ;
  public final TextView ˋॱ;
  private final View ˋᐝ;
  private final LinearLayout ˌ;
  private final TextView ˍ;
  public final Button ˎ;
  private final aA ˎˎ;
  private final KQ ˎˏ;
  private Is ˏˎ;
  private boolean ˏˏ;
  public final RelativeLayout ˏॱ;
  private String ˑ;
  public final LinearLayout ͺ;
  private String ͺॱ;
  private boolean ـ;
  public final View ॱ;
  private boolean ॱʻ;
  private boolean ॱʼ;
  private coN ॱʽ;
  public final Je ॱˊ;
  public final LinearLayout ॱˋ;
  public final Je ॱˎ;
  private long ॱͺ = -1L;
  public final FrameLayout ॱॱ;
  public final ProgressBar ॱᐝ;
  public final aD ᐝ;
  public final TextView ᐝॱ;
  
  static
  {
    ᐝˋ = 1;
    ॱᐝ();
    ॱˋ();
    ˊˊ = null;
    ˋˊ = new SparseIntArray();
    ˋˊ.put(2131296367, 25);
    ˋˊ.put(2131296364, 26);
    ˋˊ.put(2131296586, 27);
    ˋˊ.put(2131296654, 28);
    ˋˊ.put(2131296319, 29);
    ˋˊ.put(2131296320, 30);
    ˋˊ.put(2131296366, 31);
    int i = ᐧ + 19;
    ᐝˋ = i % 128;
    if (i % 2 == 0) {}
  }
  
  public Mr(ˉ paramˉ, View paramView)
  {
    super(paramˉ, paramView, 6);
    paramˉ = ॱ(paramˉ, paramView, 32, ˊˊ, ˋˊ);
    this.ॱ = ((View)paramˉ[29]);
    this.ˊ = ((View)paramˉ[30]);
    this.ˎ = ((Button)paramˉ[24]);
    this.ˎ.setTag(null);
    this.ʻ = ((RelativeLayout)paramˉ[26]);
    this.ʽ = ((ImageView)paramˉ[1]);
    this.ʽ.setTag(null);
    this.ॱॱ = ((FrameLayout)paramˉ[31]);
    this.ᐝ = ((aD)paramˉ[25]);
    this.ʼ = ((у)paramˉ[2]);
    this.ʼ.setTag(null);
    this.ˊॱ = ((KZ)paramˉ[5]);
    this.ˊॱ.setTag(null);
    this.ˊˋ = ((RelativeLayout)paramˉ[0]);
    this.ˊˋ.setTag(null);
    this.ˉ = ((TextView)paramˉ[14]);
    this.ˉ.setTag(null);
    this.ˊᐝ = ((View)paramˉ[19]);
    this.ˊᐝ.setTag(null);
    this.ˋᐝ = ((View)paramˉ[21]);
    this.ˋᐝ.setTag(null);
    this.ˋˋ = ((ImageView)paramˉ[3]);
    this.ˋˋ.setTag(null);
    this.ˎˎ = ((aA)paramˉ[4]);
    this.ˎˎ.setTag(null);
    this.ˍ = ((TextView)paramˉ[6]);
    this.ˍ.setTag(null);
    this.ˌ = ((LinearLayout)paramˉ[7]);
    this.ˌ.setTag(null);
    this.ˎˏ = ((KQ)paramˉ[9]);
    this.ˎˏ.setTag(null);
    this.ˏॱ = ((RelativeLayout)paramˉ[27]);
    this.ͺ = ((LinearLayout)paramˉ[13]);
    this.ͺ.setTag(null);
    this.ˋॱ = ((TextView)paramˉ[23]);
    this.ˋॱ.setTag(null);
    this.ॱˊ = ((Je)paramˉ[22]);
    this.ॱˊ.setTag(null);
    this.ᐝॱ = ((TextView)paramˉ[10]);
    this.ᐝॱ.setTag(null);
    this.ॱᐝ = ((ProgressBar)paramˉ[28]);
    this.ॱˋ = ((LinearLayout)paramˉ[15]);
    this.ॱˋ.setTag(null);
    this.ॱˎ = ((Je)paramˉ[17]);
    this.ॱˎ.setTag(null);
    this.ʻॱ = ((Ꭸ)paramˉ[8]);
    this.ʻॱ.setTag(null);
    this.ˈ = ((Je)paramˉ[11]);
    this.ˈ.setTag(null);
    this.ʽॱ = ((Ꭸ)paramˉ[12]);
    this.ʽॱ.setTag(null);
    this.ʾ = ((Je)paramˉ[16]);
    this.ʾ.setTag(null);
    this.ʼॱ = ((Je)paramˉ[20]);
    this.ʼॱ.setTag(null);
    this.ʿ = ((Je)paramˉ[18]);
    this.ʿ.setTag(null);
    ˋ(paramView);
    ͺ();
  }
  
  private boolean ˊ(cON paramCON, int paramInt)
  {
    if (paramInt == 0)
    {
      try
      {
        this.ॱͺ |= 0x10;
      }
      finally
      {
        paramCON = finally;
        throw paramCON;
      }
      return true;
    }
    return false;
  }
  
  private boolean ˎ(cON paramCON, int paramInt)
  {
    if (paramInt == 0)
    {
      try
      {
        this.ॱͺ |= 0x4;
      }
      finally
      {
        paramCON = finally;
        throw paramCON;
      }
      return true;
    }
    return false;
  }
  
  private boolean ˎ(coN paramCoN, int paramInt)
  {
    if (paramInt == 0)
    {
      try
      {
        this.ॱͺ |= 0x8;
      }
      finally
      {
        paramCoN = finally;
        throw paramCoN;
      }
      return true;
    }
    return false;
  }
  
  private boolean ˎ(ـ<FS> paramـ, int paramInt)
  {
    if (paramInt == 0)
    {
      try
      {
        this.ॱͺ |= 1L;
      }
      finally
      {
        paramـ = finally;
        throw paramـ;
      }
      return true;
    }
    return false;
  }
  
  private boolean ˏ(ـ<FQ> paramـ, int paramInt)
  {
    if (paramInt == 0)
    {
      try
      {
        this.ॱͺ |= 0x2;
      }
      finally
      {
        paramـ = finally;
        throw paramـ;
      }
      return true;
    }
    return false;
  }
  
  private String ॱ(String paramString)
  {
    break label333;
    int i = ᐧ + 107;
    ᐝˋ = i % 128;
    int j;
    if (i % 2 != 0)
    {
      break label73;
      j = 25;
      break label170;
    }
    for (;;)
    {
      try
      {
        j = paramString.length;
        if (i < j) {
          break label327;
        }
      }
      catch (UnsupportedEncodingException paramString)
      {
        label50:
        label55:
        throw new RuntimeException(paramString);
      }
      j = 0;
      break label254;
      j = 1;
      break label254;
      label73:
      paramString = paramString.getBytes(ॱ(new char[] { 30649, 18480, -12063, 22692, -7927, 26981, -3666, 31226, -32207, 2668, -27957 }).intern());
      byte[] arrayOfByte = new byte[paramString.length];
      i = 0;
      continue;
      for (;;)
      {
        switch (j)
        {
        case 25: 
        default: 
          paramString = new String(arrayOfByte, ॱ(new char[] { 2281, 14204, 11846, 9533, 7241, 4981 }).intern());
          return paramString;
          switch (j)
          {
          case 0: 
          default: 
            arrayOfByte[i] = ((byte)(paramString[(paramString.length - i - 1)] ^ ᐝˊ));
            i += 1;
          }
          break;
        case 36: 
          label170:
          label254:
          j = ᐧ + 31;
          ᐝˋ = j % 128;
          if (j % 2 == 0) {
            break label55;
          }
          break label50;
          label327:
          j = 36;
        }
      }
      label333:
      break;
      arrayOfByte[i] = ((byte)(paramString[(paramString.length >>> i << 0)] & ᐝˊ));
      i += 78;
    }
  }
  
  /* Error */
  private static String ॱ(char[] paramArrayOfChar)
  {
    // Byte code:
    //   0: goto +192 -> 192
    //   3: iload_3
    //   4: istore_2
    //   5: goto +274 -> 279
    //   8: iconst_1
    //   9: istore_2
    //   10: goto +209 -> 219
    //   13: iload_3
    //   14: istore_2
    //   15: goto +264 -> 279
    //   18: aload 4
    //   20: iload_2
    //   21: iconst_1
    //   22: isub
    //   23: aload_0
    //   24: iload_2
    //   25: caload
    //   26: iload_2
    //   27: iload_1
    //   28: imul
    //   29: ixor
    //   30: i2l
    //   31: getstatic 294	o/Mr:ᐨ	J
    //   34: lxor
    //   35: l2i
    //   36: i2c
    //   37: castore
    //   38: iload_2
    //   39: iconst_1
    //   40: iadd
    //   41: istore_2
    //   42: goto +17 -> 59
    //   45: iconst_1
    //   46: istore_1
    //   47: goto +103 -> 150
    //   50: astore_0
    //   51: aload_0
    //   52: athrow
    //   53: bipush 16
    //   55: istore_3
    //   56: goto +191 -> 247
    //   59: goto +220 -> 279
    //   62: new 271	java/lang/String
    //   65: dup
    //   66: aload 4
    //   68: invokespecial 297	java/lang/String:<init>	([C)V
    //   71: astore_0
    //   72: getstatic 81	o/Mr:ᐝˋ	I
    //   75: bipush 105
    //   77: iadd
    //   78: istore_1
    //   79: iload_1
    //   80: sipush 128
    //   83: irem
    //   84: putstatic 79	o/Mr:ᐧ	I
    //   87: iload_1
    //   88: iconst_2
    //   89: irem
    //   90: ifeq +5 -> 95
    //   93: aload_0
    //   94: areturn
    //   95: aload_0
    //   96: areturn
    //   97: aload_0
    //   98: astore 4
    //   100: aload 4
    //   102: iconst_0
    //   103: caload
    //   104: istore_1
    //   105: aload 4
    //   107: arraylength
    //   108: iconst_1
    //   109: isub
    //   110: newarray char
    //   112: astore 4
    //   114: iconst_1
    //   115: istore_3
    //   116: getstatic 79	o/Mr:ᐧ	I
    //   119: bipush 123
    //   121: iadd
    //   122: istore_2
    //   123: iload_2
    //   124: sipush 128
    //   127: irem
    //   128: putstatic 81	o/Mr:ᐝˋ	I
    //   131: iload_2
    //   132: iconst_2
    //   133: irem
    //   134: ifne +6 -> 140
    //   137: goto +6 -> 143
    //   140: goto -132 -> 8
    //   143: iconst_0
    //   144: istore_2
    //   145: goto +74 -> 219
    //   148: iconst_0
    //   149: istore_1
    //   150: iload_1
    //   151: tableswitch	default:+21->172, 0:+21->172, 1:+-54->97
    //   172: aload_0
    //   173: astore 4
    //   175: aload 4
    //   177: iconst_0
    //   178: caload
    //   179: istore_1
    //   180: aload 4
    //   182: arraylength
    //   183: iconst_1
    //   184: isub
    //   185: newarray char
    //   187: astore 4
    //   189: goto -75 -> 114
    //   192: getstatic 81	o/Mr:ᐝˋ	I
    //   195: bipush 75
    //   197: iadd
    //   198: istore_1
    //   199: iload_1
    //   200: sipush 128
    //   203: irem
    //   204: putstatic 79	o/Mr:ᐧ	I
    //   207: iload_1
    //   208: iconst_2
    //   209: irem
    //   210: ifeq +6 -> 216
    //   213: goto -168 -> 45
    //   216: goto -68 -> 148
    //   219: iload_2
    //   220: tableswitch	default:+24->244, 0:+-217->3, 1:+-207->13
    //   244: goto -231 -> 13
    //   247: iload_3
    //   248: lookupswitch	default:+28->276, 16:+-186->62, 99:+-230->18
    //   276: goto -214 -> 62
    //   279: iload_2
    //   280: aload_0
    //   281: arraylength
    //   282: if_icmpge +6 -> 288
    //   285: goto +6 -> 291
    //   288: goto -235 -> 53
    //   291: bipush 99
    //   293: istore_3
    //   294: goto -47 -> 247
    // Local variable table:
    //   start	length	slot	name	signature
    //   0	297	0	paramArrayOfChar	char[]
    //   27	183	1	i	int
    //   4	279	2	j	int
    //   3	291	3	k	int
    //   18	170	4	arrayOfChar	char[]
    // Exception table:
    //   from	to	target	type
    //   116	123	50	java/lang/Exception
    //   123	131	50	java/lang/Exception
  }
  
  private boolean ॱ(ـ<String> paramـ, int paramInt)
  {
    if (paramInt == 0)
    {
      try
      {
        this.ॱͺ |= 0x20;
      }
      finally
      {
        paramـ = finally;
        throw paramـ;
      }
      return true;
    }
    return false;
  }
  
  static void ॱˋ()
  {
    break label55;
    for (;;)
    {
      try
      {
        ᐝˊ = -102;
        return;
      }
      catch (Exception localException)
      {
        int i;
        throw localException;
      }
      switch (i)
      {
      }
    }
    for (;;)
    {
      i = 0;
      break;
      label55:
      do
      {
        i = 1;
        break;
        ᐝˊ = 72;
        return;
        i = ᐧ + 117;
        ᐝˋ = i % 128;
      } while (i % 2 == 0);
    }
  }
  
  static void ॱᐝ()
  {
    ᐨ = -4631539320271454272L;
  }
  
  public void ˊ(String paramString)
  {
    this.ͺॱ = paramString;
    try
    {
      this.ॱͺ |= 0x100;
    }
    finally
    {
      paramString = finally;
      throw paramString;
    }
    ˊ(118);
    super.ʽ();
  }
  
  public void ˊ(boolean paramBoolean)
  {
    this.ॱʻ = paramBoolean;
    try
    {
      this.ॱͺ |= 0x800;
    }
    finally
    {
      localObject = finally;
      throw localObject;
    }
    ˊ(87);
    super.ʽ();
  }
  
  public boolean ˊॱ()
  {
    break label90;
    boolean bool;
    return bool;
    for (;;)
    {
      bool = this.ॱʼ;
      for (;;)
      {
        i = 37;
        break;
        throw new NullPointerException();
        do
        {
          i = 93;
          break;
          i = ᐧ + 45;
          ᐝˋ = i % 128;
        } while (i % 2 == 0);
      }
      switch (i)
      {
      }
      return bool;
      label90:
      int i = ᐧ + 3;
      ᐝˋ = i % 128;
      if (i % 2 == 0) {}
    }
  }
  
  public void ˋ(coN paramCoN)
  {
    ˎ(3, paramCoN);
    this.ॱʽ = paramCoN;
    try
    {
      this.ॱͺ |= 0x8;
    }
    finally
    {
      paramCoN = finally;
      throw paramCoN;
    }
    ˊ(86);
    super.ʽ();
  }
  
  public void ˋ(boolean paramBoolean)
  {
    break label163;
    int i = null.length;
    return;
    for (;;)
    {
      try
      {
        i = ᐝˋ + 25;
        try
        {
          ᐧ = i % 128;
          if (i % 2 != 0) {
            break label166;
          }
        }
        catch (Exception localException1)
        {
          throw localException1;
        }
        i = 50;
      }
      catch (Exception localException2)
      {
        label44:
        throw localException2;
      }
      return;
      i = ᐝˋ + 107;
      ᐧ = i % 128;
      if (i % 2 == 0)
      {
        continue;
        i = 1;
        break;
        this.ـ = paramBoolean;
      }
      else
      {
        for (;;)
        {
          switch (i)
          {
          case 50: 
          default: 
            break label125;
            i = 25;
          }
        }
        label125:
        this.ـ = paramBoolean;
        i = 18 / 0;
      }
    }
    for (;;)
    {
      switch (i)
      {
      }
      break;
      label163:
      break label44;
      label166:
      i = 0;
    }
  }
  
  /* Error */
  public boolean ˋॱ()
  {
    // Byte code:
    //   0: goto +67 -> 67
    //   3: bipush 22
    //   5: istore_1
    //   6: goto +13 -> 19
    //   9: aload_0
    //   10: getfield 331	o/Mr:ـ	Z
    //   13: istore_2
    //   14: iload_2
    //   15: ireturn
    //   16: astore_3
    //   17: aload_3
    //   18: athrow
    //   19: iload_1
    //   20: lookupswitch	default:+28->48, 22:+-11->9, 39:+37->57
    //   48: goto +9 -> 57
    //   51: bipush 39
    //   53: istore_1
    //   54: goto -35 -> 19
    //   57: aload_0
    //   58: getfield 331	o/Mr:ـ	Z
    //   61: istore_2
    //   62: aconst_null
    //   63: arraylength
    //   64: istore_1
    //   65: iload_2
    //   66: ireturn
    //   67: goto +6 -> 73
    //   70: astore_3
    //   71: aload_3
    //   72: athrow
    //   73: getstatic 79	o/Mr:ᐧ	I
    //   76: bipush 59
    //   78: iadd
    //   79: istore_1
    //   80: iload_1
    //   81: sipush 128
    //   84: irem
    //   85: putstatic 81	o/Mr:ᐝˋ	I
    //   88: iload_1
    //   89: iconst_2
    //   90: irem
    //   91: ifne +6 -> 97
    //   94: goto -43 -> 51
    //   97: goto -94 -> 3
    // Local variable table:
    //   start	length	slot	name	signature
    //   0	100	0	this	Mr
    //   5	86	1	i	int
    //   13	53	2	bool	boolean
    //   16	2	3	localException1	Exception
    //   70	2	3	localException2	Exception
    // Exception table:
    //   from	to	target	type
    //   57	65	16	java/lang/Exception
    //   9	14	70	java/lang/Exception
  }
  
  public void ˎ(boolean paramBoolean)
  {
    this.ॱʼ = paramBoolean;
    try
    {
      this.ॱͺ |= 0x1000;
    }
    finally
    {
      localObject = finally;
      throw localObject;
    }
    ˊ(59);
    super.ʽ();
  }
  
  public void ˏ()
  {
    String str3 = ॱ(new char[] { 13901, 2440, 21312, -25300, -6408 }).intern();
    try
    {
      l2 = this.ॱͺ;
      this.ॱͺ = 0L;
    }
    finally
    {
      localObject1 = finally;
      throw localObject1;
    }
    double d1 = 0.0D;
    Object localObject12 = null;
    Object localObject30 = null;
    int i7 = 0;
    float f3 = 0.0F;
    boolean bool4 = this.ˏˏ;
    Object localObject13 = null;
    Object localObject11 = null;
    Object localObject9 = null;
    Object localObject2 = null;
    Object localObject17 = null;
    Object localObject39 = null;
    int n = 0;
    int j = 0;
    boolean bool2 = false;
    boolean bool1 = false;
    boolean bool7 = false;
    String str1 = this.ˑ;
    int i2 = 0;
    int i15 = 0;
    int i6 = 0;
    int i10 = 0;
    Object localObject23 = null;
    String str2 = this.ͺॱ;
    int i12 = 0;
    Object localObject33 = null;
    boolean bool5 = false;
    Object localObject14 = null;
    Object localObject32 = null;
    int i3 = 0;
    int i = 0;
    Is localIs = this.ˏˎ;
    Object localObject25 = null;
    Object localObject3 = null;
    Object localObject18 = null;
    Object localObject38 = null;
    Object localObject15 = null;
    Object localObject31 = null;
    Object localObject8 = null;
    boolean bool8 = this.ॱʻ;
    Object localObject26 = null;
    Object localObject4 = null;
    Object localObject19 = null;
    Object localObject37 = null;
    boolean bool3 = this.ॱʼ;
    int i5 = 0;
    int m = 0;
    int i8 = 0;
    Object localObject10 = null;
    Object localObject29 = null;
    double d2 = 0.0D;
    boolean bool6 = false;
    int i9 = 0;
    int i4 = 0;
    int i16 = 0;
    int i14 = 0;
    Object localObject5 = null;
    Object localObject20 = null;
    Object localObject36 = null;
    Object localObject6 = null;
    Object localObject21 = null;
    Object localObject35 = null;
    int i11 = 0;
    float f2 = 0.0F;
    float f4 = 0.0F;
    Object localObject7 = null;
    Object localObject22 = null;
    Object localObject34 = null;
    coN localCoN = this.ॱʽ;
    Object localObject28 = null;
    int i13 = 0;
    Object localObject24 = null;
    Object localObject27 = null;
    long l1 = l2;
    Object localObject16 = localObject26;
    if ((0x9237 & l2) != 0L)
    {
      l1 = l2;
      if ((0x8200 & l2) != 0L)
      {
        localObject2 = localObject39;
        bool2 = bool7;
        localObject3 = localObject38;
        localObject4 = localObject37;
        localObject5 = localObject36;
        if (localIs != null)
        {
          localObject9 = localIs.currency;
          localObject2 = localIs.reason;
          bool2 = localIs.ˊ();
          localObject3 = localIs.ˋ();
          localObject8 = localIs.status;
          localObject4 = localIs.statusDate;
          localObject5 = localIs.statusLabel;
        }
        l1 = l2;
        if ((0x8200 & l2) != 0L) {
          if (bool2) {
            l1 = l2 | 0x200000;
          } else {
            l1 = l2 | 0x100000;
          }
        }
        localObject6 = localObject35;
        localObject7 = localObject34;
        if (localObject9 != null)
        {
          localObject6 = ((Ep)localObject9).ˊ();
          localObject7 = ((Ep)localObject9).ˊ();
        }
        if (bool2) {
          j = 0;
        } else {
          j = 8;
        }
        if (localObject8 == FV.CANCELED) {
          i = 1;
        } else {
          i = 0;
        }
        l2 = l1;
        if ((0x8200 & l1) != 0L) {
          if (i != 0) {
            l2 = l1 | 0x80000000;
          } else {
            l2 = l1 | 0x40000000;
          }
        }
        if (i != 0)
        {
          i = 0;
          l1 = l2;
        }
        else
        {
          i = 8;
          l1 = l2;
        }
      }
      localObject8 = localObject32;
      if ((0x8201 & l1) != 0L)
      {
        localObject9 = localObject33;
        if (localIs != null) {
          localObject9 = localIs.contactPerson;
        }
        ˎ(0, (ˑ)localObject9);
        localObject8 = localObject32;
        if (localObject9 != null) {
          localObject8 = (FS)((ـ)localObject9).ˏ();
        }
      }
      l2 = l1;
      k = i15;
      i1 = i16;
      f1 = f4;
      if ((0x9200 & l1) != 0L)
      {
        if (localIs == null) {
          n = 1;
        } else {
          n = 0;
        }
        l2 = l1;
        if ((0x8200 & l1) != 0L) {
          if (n != 0) {
            l2 = l1 | 0x800000 | 0x8000000000 | 0x200000000000;
          } else {
            l2 = l1 | 0x400000 | 0x4000000000 | 0x100000000000;
          }
        }
        l1 = l2;
        if ((0x9200 & l2) != 0L) {
          if (n != 0) {
            l1 = l2 | 0x200000000 | 0x800000000000;
          } else {
            l1 = l2 | 0x100000000 | 0x400000000000;
          }
        }
        l2 = l1;
        k = i15;
        m = n;
        i1 = i16;
        f1 = f4;
        if ((0x8200 & l1) != 0L)
        {
          if (n != 0) {
            k = ˋ(this.ʽॱ, 17170445);
          } else {
            k = ˋ(this.ʽॱ, 2131099797);
          }
          if (n != 0) {
            i1 = 4;
          } else {
            i1 = 0;
          }
          if (n != 0)
          {
            f1 = this.ʽॱ.getResources().getDimension(2131165260);
            l2 = l1;
            m = n;
          }
          else
          {
            f1 = this.ʽॱ.getResources().getDimension(2131165259);
            m = n;
            l2 = l1;
          }
        }
      }
      localObject9 = localObject31;
      if ((0x8202 & l2) != 0L)
      {
        if (localIs != null) {
          localObject10 = localIs.phoneNumber;
        }
        ˎ(1, (ˑ)localObject10);
        localObject9 = localObject31;
        if (localObject10 != null) {
          localObject9 = (FQ)((ـ)localObject10).ˏ();
        }
      }
      localObject10 = localObject30;
      if ((0x8204 & l2) != 0L)
      {
        localObject10 = localObject29;
        if (localIs != null) {
          localObject10 = localIs.totalAmount;
        }
        ˎ(2, (ˑ)localObject10);
        if (localObject10 != null) {
          d1 = ((cON)localObject10).ˏ();
        }
        localObject10 = at.ˎ(d1);
      }
      if ((0x8210 & l2) != 0L)
      {
        localObject11 = localObject28;
        if (localIs != null) {
          localObject11 = localIs.commission;
        }
        ˎ(4, (ˑ)localObject11);
        d1 = d2;
        if (localObject11 != null) {
          d1 = ((cON)localObject11).ˏ();
        }
        localObject11 = at.ˎ(d1);
      }
      l1 = l2;
      localObject12 = localObject10;
      localObject13 = localObject11;
      localObject17 = localObject2;
      n = j;
      bool1 = bool2;
      i2 = k;
      localObject14 = localObject8;
      i3 = i;
      localObject18 = localObject3;
      localObject15 = localObject9;
      localObject16 = localObject26;
      localObject19 = localObject4;
      i5 = m;
      i4 = i1;
      localObject20 = localObject5;
      localObject21 = localObject6;
      f2 = f1;
      localObject22 = localObject7;
      if ((0x8220 & l2) != 0L)
      {
        localObject12 = localObject27;
        if (localIs != null) {
          localObject12 = localIs.transferDetail;
        }
        ˎ(5, (ˑ)localObject12);
        localObject13 = localObject25;
        if (localObject12 != null) {
          localObject13 = (String)((ـ)localObject12).ˏ();
        }
        localObject16 = aq.ॱ((String)localObject13);
        localObject22 = localObject7;
        f2 = f1;
        localObject21 = localObject6;
        localObject20 = localObject5;
        i4 = i1;
        i5 = m;
        localObject19 = localObject4;
        localObject15 = localObject9;
        localObject18 = localObject3;
        i3 = i;
        localObject14 = localObject8;
        i2 = k;
        bool1 = bool2;
        n = j;
        localObject17 = localObject2;
        localObject13 = localObject11;
        localObject12 = localObject10;
        l1 = l2;
      }
    }
    long l2 = l1;
    localObject4 = localObject23;
    int i1 = i14;
    localObject3 = localObject24;
    if ((0x8A00 & l1) != 0L)
    {
      l2 = l1;
      if ((0x8800 & l1) != 0L) {
        if (bool8) {
          l2 = l1 | 0x2000000 | 0x80000000000 | 0x8000000000000;
        } else {
          l2 = l1 | 0x1000000 | 0x40000000000 | 0x4000000000000;
        }
      }
      l1 = l2;
      if ((0x8A00 & l2) != 0L) {
        if (bool8) {
          l1 = l2 | 0x20000000000;
        } else {
          l1 = l2 | 0x10000000000;
        }
      }
      l2 = l1;
      localObject4 = localObject23;
      i1 = i14;
      localObject3 = localObject24;
      if ((0x8800 & l1) != 0L)
      {
        if (bool8)
        {
          localObject3 = this.ˎ.getResources().getString(2131755444);
          localObject2 = localObject3;
          if (((String)localObject3).startsWith(str3)) {
            localObject2 = ॱ(((String)localObject3).substring(4)).intern();
          }
        }
        else
        {
          localObject3 = this.ˎ.getResources().getString(2131755475);
          localObject2 = localObject3;
          if (((String)localObject3).startsWith(str3)) {
            localObject2 = ॱ(((String)localObject3).substring(4)).intern();
          }
        }
        if (bool8) {
          i = 0;
        } else {
          i = 8;
        }
        if (bool8)
        {
          localObject4 = this.ˊॱ.getResources().getString(2131755473);
          localObject3 = localObject4;
          if (((String)localObject4).startsWith(str3)) {
            localObject3 = ॱ(((String)localObject4).substring(4)).intern();
          }
          l2 = l1;
          localObject4 = localObject2;
          i1 = i;
        }
        else
        {
          localObject5 = this.ˊॱ.getResources().getString(2131755465);
          l2 = l1;
          localObject4 = localObject2;
          i1 = i;
          localObject3 = localObject5;
          if (((String)localObject5).startsWith(str3))
          {
            localObject3 = ॱ(((String)localObject5).substring(4)).intern();
            i1 = i;
            localObject4 = localObject2;
            l2 = l1;
          }
        }
      }
    }
    l1 = l2;
    m = i6;
    i6 = i12;
    int k = i13;
    if ((0x8048 & l2) != 0L)
    {
      bool2 = bool6;
      if (localCoN != null) {
        bool2 = localCoN.ˊ();
      }
      l1 = l2;
      if ((0x8008 & l2) != 0L) {
        if (bool2) {
          l1 = l2 | 0x8000000 | 0x2000000000000;
        } else {
          l1 = l2 | 0x4000000 | 0x1000000000000;
        }
      }
      if (!bool2) {
        i = 1;
      } else {
        i = 0;
      }
      l2 = l1;
      if ((0x8048 & l1) != 0L) {
        if (i != 0) {
          l2 = l1 | 0x20000000;
        } else {
          l2 = l1 | 0x10000000;
        }
      }
      l1 = l2;
      m = i;
      i6 = i12;
      k = i13;
      if ((0x8008 & l2) != 0L)
      {
        if (bool2) {
          j = 0;
        } else {
          j = 8;
        }
        if (bool2)
        {
          k = 4;
          l1 = l2;
          m = i;
          i6 = j;
        }
        else
        {
          k = 0;
          i6 = j;
          m = i;
          l1 = l2;
        }
      }
    }
    l2 = l1;
    i = i11;
    if ((0x20000000000 & l1) != 0L)
    {
      if (localIs != null) {
        bool1 = localIs.ˊ();
      }
      l2 = l1;
      if ((0x8200 & l1) != 0L) {
        if (bool1) {
          l2 = l1 | 0x200000;
        } else {
          l2 = l1 | 0x100000;
        }
      }
      if (!bool1) {
        i = 1;
      } else {
        i = 0;
      }
    }
    j = i10;
    if ((0x400100000000 & l2) != 0L)
    {
      j = i10;
      if ((0x100000000 & l2) != 0L) {
        if (!bool3) {
          j = 1;
        } else {
          j = 0;
        }
      }
    }
    bool1 = bool5;
    if ((0x8048 & l2) != 0L) {
      if (m != 0) {
        bool1 = bool4;
      } else {
        bool1 = false;
      }
    }
    l1 = l2;
    float f1 = f3;
    m = i9;
    if ((0x9200 & l2) != 0L)
    {
      if (i5 != 0) {
        j = 1;
      }
      if (i5 != 0) {
        bool2 = true;
      } else {
        bool2 = bool3;
      }
      l1 = l2;
      if ((0x9200 & l2) != 0L) {
        if (j != 0) {
          l1 = l2 | 0x20000;
        } else {
          l1 = l2 | 0x10000;
        }
      }
      l2 = l1;
      if ((0x9200 & l1) != 0L) {
        if (bool2) {
          l2 = l1 | 0x80000 | 0x2000000000;
        } else {
          l2 = l1 | 0x40000 | 0x1000000000;
        }
      }
      if (j != 0) {
        j = 4;
      } else {
        j = 0;
      }
      if (bool2) {
        f1 = this.ˌ.getResources().getDimension(2131165398);
      } else {
        f1 = this.ˌ.getResources().getDimension(2131165399);
      }
      if (bool2)
      {
        m = 4;
        l1 = l2;
        i7 = j;
      }
      else
      {
        m = 0;
        i7 = j;
        l1 = l2;
      }
    }
    l2 = l1;
    j = i8;
    if ((0x8A00 & l1) != 0L)
    {
      if (!bool8) {
        i = 0;
      }
      l2 = l1;
      if ((0x8A00 & l1) != 0L) {
        if (i != 0) {
          l2 = l1 | 0x800000000;
        } else {
          l2 = l1 | 0x400000000;
        }
      }
      if (i != 0) {
        j = 0;
      } else {
        j = 8;
      }
    }
    if ((0x8048 & l2) != 0L) {
      this.ˎ.setEnabled(bool1);
    }
    if ((0x8800 & l2) != 0L)
    {
      ʹ.ˊ(this.ˎ, (CharSequence)localObject4);
      this.ˊॱ.setPaymentHint((String)localObject3);
      this.ˊᐝ.setVisibility(i1);
      this.ʼॱ.setVisibility(i1);
    }
    if ((0x8200 & l2) != 0L)
    {
      this.ˎ.setVisibility(i4);
      this.ˋᐝ.setVisibility(i3);
      this.ˋॱ.setVisibility(n);
      this.ॱˊ.setVisibility(i3);
      this.ॱˊ.setValue(localObject17);
      this.ॱˎ.setValueInfo(localObject21);
      this.ʻॱ.setVisibility(i4);
      this.ˈ.setValue(localObject18);
      this.ˈ.setValueInfo(localObject22);
      this.ʽॱ.setCardBackgroundColor(i2);
      this.ʽॱ.setCardElevation(f2);
      this.ʼॱ.setLabel(localObject20);
      this.ʼॱ.setValue(localObject19);
      this.ʿ.setValueInfo(localObject21);
    }
    if ((0x8000 & l2) != 0L)
    {
      r.ˊ(this.ʽ, ॱ(new char[] { -10685, -5653, -27854, -17027, 26300, 4348, 14952, -7110, -29193, -18439, 24874, 2897, 13445, -8482, -30649, -19896, 23454, 1437, 12052, -9907, -32114, -21293, 22060, 32695, 10727, -11420, -660, -22875, 20707, 31286, 9334, -12879, -2107, -24297, 19209, 29832, 7900, -14330, -3555, -25725, 17801, 28500, 6477, -15644, -5072, -27021, -16477, 27107, 4919, 15712, -6407, -28435, -17868, 25722, 3471, 14272, -7903, -29882, -19313, 24278, 2065, 12824, -9288, -31236, -20669, 22664, 705, 11291, -10685, -102, -22052, 21265, 32071, 9874, -12077, -1504, -23453, 19874 }).intern(), ॱ(this.ʽ, 2131230823), true);
      this.ˊॱ.setViewPagerHeight(this.ˊॱ.getResources().getDimension(2131165400));
      localObject4 = this.ˉ;
      localObject3 = this.ˉ.getResources().getString(2131755246);
      localObject2 = localObject3;
      if (((String)localObject3).startsWith(str3)) {
        localObject2 = ॱ(((String)localObject3).substring(4)).intern();
      }
      ʹ.ˊ((TextView)localObject4, (CharSequence)localObject2);
      this.ˎˎ.setShadowBottom(ॱ(this.ˎˎ, 2131231257));
      this.ˎˎ.setShadowTop(ॱ(this.ˎˎ, 2131231258));
      this.ˎˏ.setShowPhoneType(false);
      localObject4 = this.ˋॱ;
      localObject3 = this.ˋॱ.getResources().getString(2131755084);
      localObject2 = localObject3;
      if (((String)localObject3).startsWith(str3)) {
        localObject2 = ॱ(((String)localObject3).substring(4)).intern();
      }
      ʹ.ˊ((TextView)localObject4, (CharSequence)localObject2);
      localObject4 = this.ॱˊ;
      localObject3 = this.ॱˊ.getResources().getString(2131755421);
      localObject2 = localObject3;
      if (((String)localObject3).startsWith(str3)) {
        localObject2 = ॱ(((String)localObject3).substring(4)).intern();
      }
      ((Je)localObject4).setLabel((String)localObject2);
      localObject4 = this.ᐝॱ;
      localObject3 = this.ᐝॱ.getResources().getString(2131755474);
      localObject2 = localObject3;
      if (((String)localObject3).startsWith(str3)) {
        localObject2 = ॱ(((String)localObject3).substring(4)).intern();
      }
      ʹ.ˊ((TextView)localObject4, (CharSequence)localObject2);
      localObject4 = this.ॱˎ;
      localObject3 = this.ॱˎ.getResources().getString(2131755476);
      localObject2 = localObject3;
      if (((String)localObject3).startsWith(str3)) {
        localObject2 = ॱ(((String)localObject3).substring(4)).intern();
      }
      ((Je)localObject4).setLabel((String)localObject2);
      localObject4 = this.ʾ;
      localObject3 = this.ʾ.getResources().getString(2131755477);
      localObject2 = localObject3;
      if (((String)localObject3).startsWith(str3)) {
        localObject2 = ॱ(((String)localObject3).substring(4)).intern();
      }
      ((Je)localObject4).setLabel((String)localObject2);
      localObject4 = this.ʿ;
      localObject3 = this.ʿ.getResources().getString(2131755480);
      localObject2 = localObject3;
      if (((String)localObject3).startsWith(str3)) {
        localObject2 = ॱ(((String)localObject3).substring(4)).intern();
      }
      ((Je)localObject4).setLabel((String)localObject2);
    }
    if ((0x8080 & l2) != 0L) {
      this.ʼ.setTitle(str1);
    }
    if ((0x9200 & l2) != 0L)
    {
      this.ˊॱ.setVisibility(i7);
      this.ˍ.setVisibility(m);
      A.ˋ(this.ˌ, f1, 0.0F, 0.0F, 0.0F);
    }
    if ((0x8A00 & l2) != 0L) {
      this.ˋˋ.setVisibility(j);
    }
    if ((0x8100 & l2) != 0L) {
      ʹ.ˊ(this.ˍ, str2);
    }
    if ((0x8201 & l2) != 0L) {
      this.ˎˏ.setContactPerson(localObject14);
    }
    if ((0x8202 & l2) != 0L) {
      this.ˎˏ.setPhoneNumber(localObject15);
    }
    if ((0x8008 & l2) != 0L)
    {
      this.ͺ.setVisibility(i6);
      this.ॱˋ.setVisibility(k);
    }
    if ((0x8210 & l2) != 0L) {
      this.ॱˎ.setValue((String)localObject13);
    }
    if ((0x8220 & l2) != 0L) {
      this.ʾ.setValue((String)localObject16);
    }
    if ((0x8204 & l2) != 0L) {
      this.ʿ.setValue((String)localObject12);
    }
  }
  
  public void ˏ(String paramString)
  {
    this.ˑ = paramString;
    try
    {
      this.ॱͺ |= 0x80;
    }
    finally
    {
      paramString = finally;
      throw paramString;
    }
    ˊ(123);
    super.ʽ();
  }
  
  public void ˏ(Is paramIs)
  {
    this.ˏˎ = paramIs;
    try
    {
      this.ॱͺ |= 0x200;
    }
    finally
    {
      paramIs = finally;
      throw paramIs;
    }
    ˊ(100);
    super.ʽ();
  }
  
  public boolean ˏ(int paramInt1, Object paramObject, int paramInt2)
  {
    break label311;
    boolean bool;
    int i;
    for (;;)
    {
      switch (paramInt1)
      {
      default: 
        return bool;
      case 0: 
        try
        {
          bool = ॱ((ـ)paramObject, paramInt2);
          return bool;
        }
        catch (Exception paramObject)
        {
          label48:
          throw paramObject;
        }
        i = 0;
        switch (i)
        {
        default: 
          break;
          paramInt1 = 46 / 0;
          return bool;
        case 1: 
          switch (paramInt1)
          {
          case 5: 
          default: 
            break;
          case 1: 
            bool = ˏ((ـ)paramObject, paramInt2);
          }
          break;
        }
        for (;;)
        {
          return false;
          paramInt1 = ᐝˋ + 77;
          ᐧ = paramInt1 % 128;
          if (paramInt1 % 2 == 0)
          {
            break label231;
            label173:
            i = 1;
            break label48;
          }
          paramInt1 = 0;
          break;
          i = null.length;
          switch (paramInt1)
          {
          }
        }
        label231:
        paramInt1 = 1;
      }
    }
    label311:
    for (;;)
    {
      i = ᐧ + 123;
      ᐝˋ = i % 128;
      if (i % 2 == 0) {
        break;
      }
      break label173;
      return ˎ((ـ)paramObject, paramInt2);
      return ˊ((cON)paramObject, paramInt2);
      return bool;
      paramObject = (cON)paramObject;
      return ˎ(paramObject, paramInt2);
      return ˎ((coN)paramObject, paramInt2);
    }
  }
  
  public boolean ˏॱ()
  {
    int i = ᐝˋ + 67;
    ᐧ = i % 128;
    if (i % 2 == 0)
    {
      i = 0;
      break label34;
      return this.ॱʻ;
    }
    for (;;)
    {
      switch (i)
      {
      case 0: 
      default: 
        label34:
        break label64;
        i = 1;
      }
    }
    label64:
    boolean bool = this.ॱʻ;
    i = 71 / 0;
    return bool;
  }
  
  public void ͺ()
  {
    try
    {
      this.ॱͺ = 32768L;
    }
    finally
    {
      localObject = finally;
      throw localObject;
    }
    ʽ();
  }
  
  public void ॱ(boolean paramBoolean)
  {
    this.ˏˏ = paramBoolean;
    try
    {
      this.ॱͺ |= 0x40;
    }
    finally
    {
      localObject = finally;
      throw localObject;
    }
    ˊ(73);
    super.ʽ();
  }
  
  public boolean ॱ()
  {
    try
    {
      long l = this.ॱͺ;
      if (l != 0L) {
        return true;
      }
    }
    finally
    {
      localObject = finally;
      throw localObject;
    }
    return false;
  }
  
  public Is ॱˊ()
  {
    for (;;)
    {
      Is localIs = this.ˏˎ;
      break label59;
      for (;;)
      {
        int i = ᐝˋ + 71;
        ᐧ = i % 128;
        if (i % 2 == 0) {
          break;
        }
        i = 2;
        try
        {
          localIs = this.ˏˎ;
          throw new NullPointerException();
        }
        catch (Exception localException)
        {
          throw localException;
        }
      }
      label59:
      i = ᐧ + 83;
      ᐝˋ = i % 128;
      if (i % 2 == 0) {
        return localIs;
      }
      return localIs;
      i = 7;
      switch (i)
      {
      }
    }
  }
}
