package o;

import android.content.res.Resources;
import android.databinding.ViewDataBinding;
import android.databinding.ViewDataBinding.If;
import android.util.SparseIntArray;
import android.view.View;
import android.widget.LinearLayout;
import java.io.UnsupportedEncodingException;

public class MS
  extends ViewDataBinding
{
  private static final ViewDataBinding.If ʻ;
  private static int ʻॱ;
  private static byte ॱˋ;
  private static int ॱˎ;
  private static final SparseIntArray ॱॱ;
  private static char[] ᐝॱ;
  public final Ji ʼ;
  private final LinearLayout ʽ;
  public final Ji ˊ;
  private String ˊॱ;
  private final IS ˋॱ;
  public final Ji ˎ;
  private String ˏॱ;
  private String ͺ;
  public final Ji ॱ;
  private String ॱˊ;
  private long ॱᐝ = -1L;
  public final у ᐝ;
  
  static
  {
    for (;;)
    {
      int i = null.length;
      return;
      for (;;)
      {
        i = ʻॱ + 119;
        ॱˎ = i % 128;
        if (i % 2 == 0) {
          break label39;
        }
        i = 0;
        break;
        label39:
        i = 1;
        break;
        ॱˎ = 0;
        ʻॱ = 1;
        ॱˎ();
        ˊॱ();
        ʻ = null;
        ॱॱ = null;
      }
      switch (i)
      {
      }
    }
  }
  
  public MS(ˉ paramˉ, View paramView)
  {
    super(paramˉ, paramView, 0);
    paramˉ = ॱ(paramˉ, paramView, 7, ʻ, ॱॱ);
    this.ˎ = ((Ji)paramˉ[3]);
    this.ˎ.setTag(null);
    this.ˊ = ((Ji)paramˉ[4]);
    this.ˊ.setTag(null);
    this.ॱ = ((Ji)paramˉ[6]);
    this.ॱ.setTag(null);
    this.ʽ = ((LinearLayout)paramˉ[0]);
    this.ʽ.setTag(null);
    this.ˋॱ = ((IS)paramˉ[2]);
    this.ˋॱ.setTag(null);
    this.ᐝ = ((у)paramˉ[1]);
    this.ᐝ.setTag(null);
    this.ʼ = ((Ji)paramˉ[5]);
    this.ʼ.setTag(null);
    ˋ(paramView);
    ˋॱ();
  }
  
  /* Error */
  static void ˊॱ()
  {
    // Byte code:
    //   0: goto +146 -> 146
    //   3: bipush 38
    //   5: putstatic 99	o/MS:ॱˋ	B
    //   8: goto +43 -> 51
    //   11: return
    //   12: bipush 9
    //   14: istore_0
    //   15: goto +68 -> 83
    //   18: bipush 32
    //   20: istore_0
    //   21: goto +62 -> 83
    //   24: getstatic 37	o/MS:ʻॱ	I
    //   27: bipush 15
    //   29: iadd
    //   30: istore_0
    //   31: iload_0
    //   32: sipush 128
    //   35: irem
    //   36: putstatic 39	o/MS:ॱˎ	I
    //   39: iload_0
    //   40: iconst_2
    //   41: irem
    //   42: ifeq +6 -> 48
    //   45: goto +32 -> 77
    //   48: goto +107 -> 155
    //   51: getstatic 39	o/MS:ॱˎ	I
    //   54: iconst_3
    //   55: iadd
    //   56: istore_0
    //   57: iload_0
    //   58: sipush 128
    //   61: irem
    //   62: putstatic 37	o/MS:ʻॱ	I
    //   65: iload_0
    //   66: iconst_2
    //   67: irem
    //   68: ifne +6 -> 74
    //   71: goto -59 -> 12
    //   74: goto -56 -> 18
    //   77: bipush 14
    //   79: istore_0
    //   80: goto +33 -> 113
    //   83: iload_0
    //   84: lookupswitch	default:+28->112, 9:+65->149, 32:+-73->11
    //   112: return
    //   113: iload_0
    //   114: lookupswitch	default:+26->140, 14:+-111->3, 27:+47->161
    //   140: goto +21 -> 161
    //   143: astore_1
    //   144: aload_1
    //   145: athrow
    //   146: goto -122 -> 24
    //   149: bipush 37
    //   151: iconst_0
    //   152: idiv
    //   153: istore_0
    //   154: return
    //   155: bipush 27
    //   157: istore_0
    //   158: goto -45 -> 113
    //   161: bipush -102
    //   163: putstatic 99	o/MS:ॱˋ	B
    //   166: goto -115 -> 51
    //   169: astore_1
    //   170: aload_1
    //   171: athrow
    // Local variable table:
    //   start	length	slot	name	signature
    //   14	144	0	i	int
    //   143	2	1	localException1	Exception
    //   169	2	1	localException2	Exception
    // Exception table:
    //   from	to	target	type
    //   24	31	143	java/lang/Exception
    //   31	39	143	java/lang/Exception
    //   31	39	169	java/lang/Exception
  }
  
  /* Error */
  private static String ˋ(int[] paramArrayOfInt, byte[] paramArrayOfByte, boolean paramBoolean)
  {
    // Byte code:
    //   0: goto +170 -> 170
    //   3: astore_0
    //   4: aload_0
    //   5: athrow
    //   6: iload 6
    //   8: newarray char
    //   10: astore_1
    //   11: iconst_0
    //   12: istore_3
    //   13: goto +178 -> 191
    //   16: aload 10
    //   18: astore 9
    //   20: iload_3
    //   21: lookupswitch	default:+27->48, 22:+754->775, 58:+135->156
    //   48: aload 10
    //   50: astore 9
    //   52: goto +104 -> 156
    //   55: aload 9
    //   57: iload 4
    //   59: aload 10
    //   61: iload 4
    //   63: caload
    //   64: iconst_0
    //   65: idiv
    //   66: iconst_1
    //   67: ishl
    //   68: iload_3
    //   69: irem
    //   70: i2c
    //   71: castore
    //   72: goto +381 -> 453
    //   75: goto +116 -> 191
    //   78: new 102	java/lang/String
    //   81: dup
    //   82: aload 9
    //   84: invokespecial 105	java/lang/String:<init>	([C)V
    //   87: areturn
    //   88: bipush 78
    //   90: istore 4
    //   92: goto +608 -> 700
    //   95: iload_2
    //   96: ifeq +6 -> 102
    //   99: goto -93 -> 6
    //   102: goto +71 -> 173
    //   105: iconst_0
    //   106: istore_3
    //   107: goto +158 -> 265
    //   110: aload_1
    //   111: iload_3
    //   112: aload 9
    //   114: iload 6
    //   116: iload_3
    //   117: isub
    //   118: iconst_1
    //   119: isub
    //   120: caload
    //   121: castore
    //   122: iload_3
    //   123: iconst_1
    //   124: iadd
    //   125: istore_3
    //   126: goto -51 -> 75
    //   129: goto -34 -> 95
    //   132: bipush 22
    //   134: istore_3
    //   135: goto -119 -> 16
    //   138: aload 9
    //   140: iload 4
    //   142: aload 10
    //   144: iload 4
    //   146: caload
    //   147: iconst_1
    //   148: ishl
    //   149: iload_3
    //   150: isub
    //   151: i2c
    //   152: castore
    //   153: goto +300 -> 453
    //   156: iload 8
    //   158: ifle +6 -> 164
    //   161: goto +90 -> 251
    //   164: goto +257 -> 421
    //   167: goto +98 -> 265
    //   170: goto +256 -> 426
    //   173: iload 7
    //   175: ifle +6 -> 181
    //   178: goto -73 -> 105
    //   181: goto -103 -> 78
    //   184: bipush 31
    //   186: istore 5
    //   188: goto +557 -> 745
    //   191: iload_3
    //   192: iload 6
    //   194: if_icmpge +6 -> 200
    //   197: goto +80 -> 277
    //   200: goto +480 -> 680
    //   203: goto +296 -> 499
    //   206: iload_3
    //   207: tableswitch	default:+21->228, 0:+394->601, 1:+-112->95
    //   228: goto -133 -> 95
    //   231: bipush 44
    //   233: istore 5
    //   235: goto +510 -> 745
    //   238: iload 4
    //   240: iload 6
    //   242: if_icmpge +6 -> 248
    //   245: goto +89 -> 334
    //   248: goto +100 -> 348
    //   251: iconst_0
    //   252: istore_3
    //   253: goto -47 -> 206
    //   256: goto -161 -> 95
    //   259: bipush 58
    //   261: istore_3
    //   262: goto -246 -> 16
    //   265: iload_3
    //   266: iload 6
    //   268: if_icmpge +6 -> 274
    //   271: goto +100 -> 371
    //   274: goto -196 -> 78
    //   277: getstatic 39	o/MS:ॱˎ	I
    //   280: bipush 123
    //   282: iadd
    //   283: istore 4
    //   285: iload 4
    //   287: sipush 128
    //   290: irem
    //   291: putstatic 37	o/MS:ʻॱ	I
    //   294: iload 4
    //   296: iconst_2
    //   297: irem
    //   298: ifne +6 -> 304
    //   301: goto +6 -> 307
    //   304: goto -194 -> 110
    //   307: aload_1
    //   308: iload_3
    //   309: aload 9
    //   311: iload 6
    //   313: iload_3
    //   314: idiv
    //   315: iconst_0
    //   316: iushr
    //   317: caload
    //   318: castore
    //   319: iload_3
    //   320: bipush 114
    //   322: iadd
    //   323: istore_3
    //   324: goto -249 -> 75
    //   327: bipush 6
    //   329: istore 5
    //   331: goto +137 -> 468
    //   334: aload_1
    //   335: iload 4
    //   337: baload
    //   338: iconst_1
    //   339: if_icmpne +6 -> 345
    //   342: goto -158 -> 184
    //   345: goto -114 -> 231
    //   348: goto -192 -> 156
    //   351: aload 9
    //   353: iload 4
    //   355: aload 10
    //   357: iload 4
    //   359: caload
    //   360: iconst_1
    //   361: ishl
    //   362: iconst_1
    //   363: iadd
    //   364: iload_3
    //   365: isub
    //   366: i2c
    //   367: castore
    //   368: goto +85 -> 453
    //   371: getstatic 37	o/MS:ʻॱ	I
    //   374: bipush 75
    //   376: iadd
    //   377: istore 4
    //   379: iload 4
    //   381: sipush 128
    //   384: irem
    //   385: putstatic 39	o/MS:ॱˎ	I
    //   388: iload 4
    //   390: iconst_2
    //   391: irem
    //   392: ifeq +6 -> 398
    //   395: goto +343 -> 738
    //   398: goto -310 -> 88
    //   401: aload 9
    //   403: iload_3
    //   404: aload 9
    //   406: iload_3
    //   407: caload
    //   408: aload_0
    //   409: iconst_2
    //   410: iaload
    //   411: isub
    //   412: i2c
    //   413: castore
    //   414: iload_3
    //   415: iconst_1
    //   416: iadd
    //   417: istore_3
    //   418: goto -251 -> 167
    //   421: iconst_1
    //   422: istore_3
    //   423: goto -217 -> 206
    //   426: getstatic 39	o/MS:ॱˎ	I
    //   429: bipush 25
    //   431: iadd
    //   432: istore_3
    //   433: iload_3
    //   434: sipush 128
    //   437: irem
    //   438: putstatic 37	o/MS:ʻॱ	I
    //   441: iload_3
    //   442: iconst_2
    //   443: irem
    //   444: ifne +6 -> 450
    //   447: goto -244 -> 203
    //   450: goto +49 -> 499
    //   453: aload 9
    //   455: iload 4
    //   457: caload
    //   458: istore_3
    //   459: iload 4
    //   461: iconst_1
    //   462: iadd
    //   463: istore 4
    //   465: goto -227 -> 238
    //   468: iload 5
    //   470: lookupswitch	default:+26->496, 6:+-415->55, 59:+-119->351
    //   496: goto -441 -> 55
    //   499: aload_0
    //   500: iconst_0
    //   501: iaload
    //   502: istore_3
    //   503: aload_0
    //   504: iconst_1
    //   505: iaload
    //   506: istore 6
    //   508: aload_0
    //   509: iconst_2
    //   510: iaload
    //   511: istore 7
    //   513: aload_0
    //   514: iconst_3
    //   515: iaload
    //   516: istore 8
    //   518: getstatic 107	o/MS:ᐝॱ	[C
    //   521: astore 9
    //   523: iload 6
    //   525: newarray char
    //   527: astore 10
    //   529: aload 9
    //   531: iload_3
    //   532: aload 10
    //   534: iconst_0
    //   535: iload 6
    //   537: invokestatic 113	java/lang/System:arraycopy	(Ljava/lang/Object;ILjava/lang/Object;II)V
    //   540: aload_1
    //   541: ifnull +6 -> 547
    //   544: goto -412 -> 132
    //   547: goto -288 -> 259
    //   550: aload 9
    //   552: iload_3
    //   553: aload 9
    //   555: iload_3
    //   556: caload
    //   557: aload_0
    //   558: iconst_5
    //   559: iaload
    //   560: iushr
    //   561: i2c
    //   562: castore
    //   563: iload_3
    //   564: bipush 83
    //   566: iadd
    //   567: istore_3
    //   568: goto -401 -> 167
    //   571: getstatic 37	o/MS:ʻॱ	I
    //   574: bipush 93
    //   576: iadd
    //   577: istore_3
    //   578: iload_3
    //   579: sipush 128
    //   582: irem
    //   583: putstatic 39	o/MS:ॱˎ	I
    //   586: iload_3
    //   587: iconst_2
    //   588: irem
    //   589: ifeq +6 -> 595
    //   592: goto -336 -> 256
    //   595: goto -466 -> 129
    //   598: goto +88 -> 686
    //   601: iload 6
    //   603: newarray char
    //   605: astore_1
    //   606: aload 9
    //   608: iconst_0
    //   609: aload_1
    //   610: iconst_0
    //   611: iload 6
    //   613: invokestatic 113	java/lang/System:arraycopy	(Ljava/lang/Object;ILjava/lang/Object;II)V
    //   616: aload_1
    //   617: iconst_0
    //   618: aload 9
    //   620: iload 6
    //   622: iload 8
    //   624: isub
    //   625: iload 8
    //   627: invokestatic 113	java/lang/System:arraycopy	(Ljava/lang/Object;ILjava/lang/Object;II)V
    //   630: aload_1
    //   631: iload 8
    //   633: aload 9
    //   635: iconst_0
    //   636: iload 6
    //   638: iload 8
    //   640: isub
    //   641: invokestatic 113	java/lang/System:arraycopy	(Ljava/lang/Object;ILjava/lang/Object;II)V
    //   644: goto -73 -> 571
    //   647: getstatic 37	o/MS:ʻॱ	I
    //   650: bipush 61
    //   652: iadd
    //   653: istore 5
    //   655: iload 5
    //   657: sipush 128
    //   660: irem
    //   661: putstatic 39	o/MS:ॱˎ	I
    //   664: iload 5
    //   666: iconst_2
    //   667: irem
    //   668: ifeq +6 -> 674
    //   671: goto -344 -> 327
    //   674: goto +57 -> 731
    //   677: astore_0
    //   678: aload_0
    //   679: athrow
    //   680: aload_1
    //   681: astore 9
    //   683: goto -510 -> 173
    //   686: iload 6
    //   688: newarray char
    //   690: astore 9
    //   692: iconst_0
    //   693: istore_3
    //   694: iconst_0
    //   695: istore 4
    //   697: goto -459 -> 238
    //   700: iload 4
    //   702: lookupswitch	default:+26->728, 37:+-152->550, 78:+-301->401
    //   728: goto -178 -> 550
    //   731: bipush 59
    //   733: istore 5
    //   735: goto -267 -> 468
    //   738: bipush 37
    //   740: istore 4
    //   742: goto -42 -> 700
    //   745: iload 5
    //   747: lookupswitch	default:+25->772, 31:+-100->647, 44:+-609->138
    //   772: goto -125 -> 647
    //   775: getstatic 39	o/MS:ॱˎ	I
    //   778: bipush 109
    //   780: iadd
    //   781: istore_3
    //   782: iload_3
    //   783: sipush 128
    //   786: irem
    //   787: putstatic 37	o/MS:ʻॱ	I
    //   790: iload_3
    //   791: iconst_2
    //   792: irem
    //   793: ifne +6 -> 799
    //   796: goto -198 -> 598
    //   799: goto -113 -> 686
    // Local variable table:
    //   start	length	slot	name	signature
    //   0	802	0	paramArrayOfInt	int[]
    //   0	802	1	paramArrayOfByte	byte[]
    //   0	802	2	paramBoolean	boolean
    //   12	781	3	i	int
    //   57	684	4	j	int
    //   186	560	5	k	int
    //   6	681	6	m	int
    //   173	339	7	n	int
    //   156	485	8	i1	int
    //   18	673	9	localObject	Object
    //   16	517	10	arrayOfChar	char[]
    // Exception table:
    //   from	to	target	type
    //   518	523	3	java/lang/Exception
    //   529	540	3	java/lang/Exception
    //   606	616	3	java/lang/Exception
    //   616	630	3	java/lang/Exception
    //   630	644	3	java/lang/Exception
    //   616	630	677	java/lang/Exception
  }
  
  private String ॱ(String paramString)
  {
    break label241;
    byte[] arrayOfByte;
    try
    {
      paramString = new String(arrayOfByte, ˋ(new int[] { 14, 5, 54, 0 }, new byte[] { 0, 1, 1, 0, 1 }, true).intern());
      return paramString;
    }
    catch (UnsupportedEncodingException paramString)
    {
      throw new RuntimeException(paramString);
    }
    int j = 1;
    for (;;)
    {
      paramString = paramString.getBytes(ˋ(new int[] { 4, 10, 0, 0 }, new byte[] { 1, 0, 0, 0, 1, 0, 1, 0, 0, 0 }, false).intern());
      arrayOfByte = new byte[paramString.length];
      int i = 0;
      label206:
      label235:
      for (;;)
      {
        j = paramString.length;
        if (i >= j) {
          break;
        }
        j = 0;
        break label298;
        j = 92;
        switch (j)
        {
        default: 
          break label323;
        }
      }
      label241:
      label298:
      label323:
      label348:
      do
      {
        break;
        break label348;
        for (;;)
        {
          j = ॱˎ + 7;
          ʻॱ = j % 128;
          if (j % 2 == 0) {
            break;
          }
          j = 70;
          break label206;
          arrayOfByte[i] = ((byte)(paramString[(paramString.length - i - 1)] ^ ॱˋ));
          i += 1;
          break label235;
          switch (j)
          {
          }
        }
        arrayOfByte[i] = ((byte)(paramString[(paramString.length % i + 1)] | ॱˋ));
        i += 26;
        break label235;
        i = ॱˎ + 107;
        ʻॱ = i % 128;
      } while (i % 2 == 0);
    }
  }
  
  static void ॱˎ()
  {
    ᐝॱ = new char[] { 6, 11, 18, 15, 36, 78, 81, 62, 50, 56, 54, 55, 51, 47, 55, 104, 111, 131, 138 };
  }
  
  public void ˊ(String paramString)
  {
    this.ॱˊ = paramString;
    try
    {
      this.ॱᐝ |= 0x2;
    }
    finally
    {
      paramString = finally;
      throw paramString;
    }
    ˊ(32);
    super.ʽ();
  }
  
  public void ˋ(String paramString)
  {
    this.ˊॱ = paramString;
    try
    {
      this.ॱᐝ |= 0x8;
    }
    finally
    {
      paramString = finally;
      throw paramString;
    }
    ˊ(106);
    super.ʽ();
  }
  
  public void ˋॱ()
  {
    try
    {
      this.ॱᐝ = 16L;
    }
    finally
    {
      localObject = finally;
      throw localObject;
    }
    ʽ();
  }
  
  public void ˎ(String paramString)
  {
    this.ˏॱ = paramString;
    try
    {
      this.ॱᐝ |= 1L;
    }
    finally
    {
      paramString = finally;
      throw paramString;
    }
    ˊ(37);
    super.ʽ();
  }
  
  public void ˏ()
  {
    String str5 = ˋ(new int[] { 0, 4, 0, 4 }, new byte[] { 0, 1, 1, 1 }, true).intern();
    long l;
    try
    {
      l = this.ॱᐝ;
      this.ॱᐝ = 0L;
    }
    finally
    {
      localObject1 = finally;
      throw localObject1;
    }
    String str2 = this.ˏॱ;
    String str3 = this.ॱˊ;
    String str4 = this.ͺ;
    Object localObject2 = this.ˊॱ;
    if ((0x18 & l) != 0L) {
      this.ˎ.setSummary((String)localObject2);
    }
    if ((0x10 & l) != 0L)
    {
      Object localObject3 = this.ˎ;
      String str1 = this.ˎ.getResources().getString(2131755559);
      localObject2 = str1;
      if (str1.startsWith(str5)) {
        localObject2 = ॱ(str1.substring(4)).intern();
      }
      ((Ji)localObject3).setTitle((String)localObject2);
      localObject3 = this.ˊ;
      str1 = this.ˊ.getResources().getString(2131755560);
      localObject2 = str1;
      if (str1.startsWith(str5)) {
        localObject2 = ॱ(str1.substring(4)).intern();
      }
      ((Ji)localObject3).setTitle((String)localObject2);
      localObject3 = this.ॱ;
      str1 = this.ॱ.getResources().getString(2131755561);
      localObject2 = str1;
      if (str1.startsWith(str5)) {
        localObject2 = ॱ(str1.substring(4)).intern();
      }
      ((Ji)localObject3).setTitle((String)localObject2);
      localObject3 = this.ˋॱ;
      str1 = this.ˋॱ.getResources().getString(2131755562);
      localObject2 = str1;
      if (str1.startsWith(str5)) {
        localObject2 = ॱ(str1.substring(4)).intern();
      }
      ((IS)localObject3).setSubTitle((String)localObject2);
      localObject3 = this.ˋॱ;
      str1 = this.ˋॱ.getResources().getString(2131755563);
      localObject2 = str1;
      if (str1.startsWith(str5)) {
        localObject2 = ॱ(str1.substring(4)).intern();
      }
      ((IS)localObject3).setTitle((String)localObject2);
      localObject3 = this.ᐝ;
      str1 = this.ᐝ.getResources().getString(2131755041);
      localObject2 = str1;
      if (str1.startsWith(str5)) {
        localObject2 = ॱ(str1.substring(4)).intern();
      }
      ((у)localObject3).setTitle((CharSequence)localObject2);
      localObject3 = this.ʼ;
      str1 = this.ʼ.getResources().getString(2131755564);
      localObject2 = str1;
      if (str1.startsWith(str5)) {
        localObject2 = ॱ(str1.substring(4)).intern();
      }
      ((Ji)localObject3).setTitle((String)localObject2);
    }
    if ((0x12 & l) != 0L) {
      this.ˊ.setSummary(str3);
    }
    if ((0x11 & l) != 0L) {
      this.ॱ.setSummary(str2);
    }
    if ((0x14 & l) != 0L) {
      this.ʼ.setSummary(str4);
    }
  }
  
  public void ˏ(String paramString)
  {
    this.ͺ = paramString;
    try
    {
      this.ॱᐝ |= 0x4;
    }
    finally
    {
      paramString = finally;
      throw paramString;
    }
    ˊ(137);
    super.ʽ();
  }
  
  /* Error */
  public boolean ˏ(int paramInt1, Object paramObject, int paramInt2)
  {
    // Byte code:
    //   0: goto +30 -> 30
    //   3: getstatic 39	o/MS:ॱˎ	I
    //   6: bipush 25
    //   8: iadd
    //   9: istore_1
    //   10: iload_1
    //   11: sipush 128
    //   14: irem
    //   15: putstatic 37	o/MS:ʻॱ	I
    //   18: iload_1
    //   19: iconst_2
    //   20: irem
    //   21: ifne +6 -> 27
    //   24: goto +88 -> 112
    //   27: goto +80 -> 107
    //   30: goto +44 -> 74
    //   33: iconst_0
    //   34: ireturn
    //   35: astore_2
    //   36: aload_2
    //   37: athrow
    //   38: iconst_1
    //   39: istore_1
    //   40: goto +77 -> 117
    //   43: goto -40 -> 3
    //   46: iload_1
    //   47: tableswitch	default:+21->68, 0:+-14->33, 1:+96->143
    //   68: goto -35 -> 33
    //   71: astore_2
    //   72: aload_2
    //   73: athrow
    //   74: getstatic 39	o/MS:ॱˎ	I
    //   77: istore_1
    //   78: iload_1
    //   79: iconst_5
    //   80: iadd
    //   81: istore_1
    //   82: iload_1
    //   83: sipush 128
    //   86: irem
    //   87: putstatic 37	o/MS:ʻॱ	I
    //   90: iload_1
    //   91: iconst_2
    //   92: irem
    //   93: ifne +6 -> 99
    //   96: goto +6 -> 102
    //   99: goto -61 -> 38
    //   102: iconst_0
    //   103: istore_1
    //   104: goto +13 -> 117
    //   107: iconst_0
    //   108: istore_1
    //   109: goto -63 -> 46
    //   112: iconst_1
    //   113: istore_1
    //   114: goto -68 -> 46
    //   117: iload_1
    //   118: tableswitch	default:+22->140, 0:+30->148, 1:+-75->43
    //   140: goto +8 -> 148
    //   143: aconst_null
    //   144: arraylength
    //   145: istore_1
    //   146: iconst_0
    //   147: ireturn
    //   148: goto -145 -> 3
    // Local variable table:
    //   start	length	slot	name	signature
    //   0	151	0	this	MS
    //   0	151	1	paramInt1	int
    //   0	151	2	paramObject	Object
    //   0	151	3	paramInt2	int
    // Exception table:
    //   from	to	target	type
    //   74	78	35	java/lang/Exception
    //   3	10	71	java/lang/Exception
    //   10	18	71	java/lang/Exception
    //   82	90	71	java/lang/Exception
  }
  
  /* Error */
  public String ˏॱ()
  {
    // Byte code:
    //   0: goto +8 -> 8
    //   3: iconst_1
    //   4: istore_1
    //   5: goto +30 -> 35
    //   8: getstatic 39	o/MS:ॱˎ	I
    //   11: bipush 77
    //   13: iadd
    //   14: istore_1
    //   15: iload_1
    //   16: sipush 128
    //   19: irem
    //   20: putstatic 37	o/MS:ʻॱ	I
    //   23: iload_1
    //   24: iconst_2
    //   25: irem
    //   26: ifne +6 -> 32
    //   29: goto +54 -> 83
    //   32: goto -29 -> 3
    //   35: iload_1
    //   36: tableswitch	default:+24->60, 0:+37->73, 1:+30->66
    //   60: goto +6 -> 66
    //   63: astore_2
    //   64: aload_2
    //   65: athrow
    //   66: aload_0
    //   67: getfield 173	o/MS:ˏॱ	Ljava/lang/String;
    //   70: astore_2
    //   71: aload_2
    //   72: areturn
    //   73: aload_0
    //   74: getfield 173	o/MS:ˏॱ	Ljava/lang/String;
    //   77: astore_2
    //   78: aconst_null
    //   79: arraylength
    //   80: istore_1
    //   81: aload_2
    //   82: areturn
    //   83: iconst_0
    //   84: istore_1
    //   85: goto -50 -> 35
    // Local variable table:
    //   start	length	slot	name	signature
    //   0	88	0	this	MS
    //   4	81	1	i	int
    //   63	2	2	localException	Exception
    //   70	12	2	str	String
    // Exception table:
    //   from	to	target	type
    //   66	71	63	java/lang/Exception
    //   73	81	63	java/lang/Exception
  }
  
  public String ͺ()
  {
    for (;;)
    {
      i = ʻॱ + 9;
      ॱˎ = i % 128;
      if (i % 2 == 0) {
        break;
      }
      break;
    }
    String str = this.ͺ;
    int i = ॱˎ + 57;
    ʻॱ = i % 128;
    if (i % 2 == 0) {
      return str;
    }
    return str;
  }
  
  public boolean ॱ()
  {
    try
    {
      long l = this.ॱᐝ;
      if (l != 0L) {
        return true;
      }
    }
    finally
    {
      localObject = finally;
      throw localObject;
    }
    return false;
  }
  
  /* Error */
  public String ॱˊ()
  {
    // Byte code:
    //   0: goto +66 -> 66
    //   3: getstatic 37	o/MS:ʻॱ	I
    //   6: bipush 37
    //   8: iadd
    //   9: istore_1
    //   10: iload_1
    //   11: sipush 128
    //   14: irem
    //   15: putstatic 39	o/MS:ॱˎ	I
    //   18: iload_1
    //   19: iconst_2
    //   20: irem
    //   21: ifeq +6 -> 27
    //   24: goto +45 -> 69
    //   27: goto +6 -> 33
    //   30: astore_2
    //   31: aload_2
    //   32: athrow
    //   33: aload_0
    //   34: getfield 157	o/MS:ॱˊ	Ljava/lang/String;
    //   37: astore_2
    //   38: getstatic 39	o/MS:ॱˎ	I
    //   41: bipush 67
    //   43: iadd
    //   44: istore_1
    //   45: iload_1
    //   46: sipush 128
    //   49: irem
    //   50: putstatic 37	o/MS:ʻॱ	I
    //   53: iload_1
    //   54: iconst_2
    //   55: irem
    //   56: ifne +6 -> 62
    //   59: goto +5 -> 64
    //   62: aload_2
    //   63: areturn
    //   64: aload_2
    //   65: areturn
    //   66: goto -63 -> 3
    //   69: goto -36 -> 33
    // Local variable table:
    //   start	length	slot	name	signature
    //   0	72	0	this	MS
    //   9	47	1	i	int
    //   30	2	2	localException	Exception
    //   37	28	2	str	String
    // Exception table:
    //   from	to	target	type
    //   33	38	30	java/lang/Exception
  }
}
