package o;

import android.content.res.Resources;
import android.databinding.ViewDataBinding;
import android.databinding.ViewDataBinding.If;
import android.util.SparseIntArray;
import android.view.View;
import android.widget.ImageView;
import android.widget.LinearLayout;
import android.widget.RelativeLayout;
import android.widget.TextView;

public class Ms
  extends ViewDataBinding
{
  private static int ʼॱ;
  private static final ViewDataBinding.If ʽ;
  private static int ʽॱ;
  private static char[] ʾ;
  private static byte ʿ;
  private static long ˈ;
  private static final SparseIntArray ˏॱ;
  public final LinearLayout ʻ;
  private long ʻॱ = -1L;
  public final у ʼ;
  public final LinearLayout ˊ;
  private final TextView ˊॱ;
  private final TextView ˋॱ;
  public final aH ˎ;
  private String ͺ;
  public final TextView ॱ;
  private final RelativeLayout ॱˊ;
  private boolean ॱˋ;
  private boolean ॱˎ;
  public final Jn ॱॱ;
  private boolean ॱᐝ;
  public final ImageView ᐝ;
  private boolean ᐝॱ;
  
  /* Error */
  static
  {
    // Byte code:
    //   0: goto +72 -> 72
    //   3: astore_1
    //   4: aload_1
    //   5: athrow
    //   6: iload_0
    //   7: lookupswitch	default:+25->32, 29:+59->66, 52:+58->65
    //   32: goto +34 -> 66
    //   35: astore_1
    //   36: aload_1
    //   37: athrow
    //   38: getstatic 48	o/Ms:ʼॱ	I
    //   41: bipush 39
    //   43: iadd
    //   44: istore_0
    //   45: iload_0
    //   46: sipush 128
    //   49: irem
    //   50: putstatic 50	o/Ms:ʽॱ	I
    //   53: iload_0
    //   54: iconst_2
    //   55: irem
    //   56: ifne +6 -> 62
    //   59: goto +60 -> 119
    //   62: goto +51 -> 113
    //   65: return
    //   66: bipush 91
    //   68: iconst_0
    //   69: idiv
    //   70: istore_0
    //   71: return
    //   72: iconst_0
    //   73: putstatic 48	o/Ms:ʼॱ	I
    //   76: iconst_1
    //   77: putstatic 50	o/Ms:ʽॱ	I
    //   80: invokestatic 52	o/Ms:ॱˊ	()V
    //   83: invokestatic 54	o/Ms:ˏॱ	()V
    //   86: aconst_null
    //   87: putstatic 56	o/Ms:ʽ	Landroid/databinding/ViewDataBinding$If;
    //   90: new 58	android/util/SparseIntArray
    //   93: dup
    //   94: invokespecial 61	android/util/SparseIntArray:<init>	()V
    //   97: putstatic 63	o/Ms:ˏॱ	Landroid/util/SparseIntArray;
    //   100: getstatic 63	o/Ms:ˏॱ	Landroid/util/SparseIntArray;
    //   103: ldc 64
    //   105: bipush 9
    //   107: invokevirtual 68	android/util/SparseIntArray:put	(II)V
    //   110: goto -72 -> 38
    //   113: bipush 52
    //   115: istore_0
    //   116: goto -110 -> 6
    //   119: bipush 29
    //   121: istore_0
    //   122: goto -116 -> 6
    // Local variable table:
    //   start	length	slot	name	signature
    //   6	116	0	i	int
    //   3	2	1	localException1	Exception
    //   35	2	1	localException2	Exception
    // Exception table:
    //   from	to	target	type
    //   72	76	3	java/lang/Exception
    //   76	80	35	java/lang/Exception
    //   80	83	35	java/lang/Exception
    //   83	86	35	java/lang/Exception
    //   86	90	35	java/lang/Exception
    //   90	110	35	java/lang/Exception
  }
  
  public Ms(ˉ paramˉ, View paramView)
  {
    super(paramˉ, paramView, 0);
    paramˉ = ॱ(paramˉ, paramView, 10, ʽ, ˏॱ);
    this.ॱ = ((TextView)paramˉ[8]);
    this.ॱ.setTag(null);
    this.ˎ = ((aH)paramˉ[4]);
    this.ˎ.setTag(null);
    this.ˊ = ((LinearLayout)paramˉ[9]);
    this.ᐝ = ((ImageView)paramˉ[1]);
    this.ᐝ.setTag(null);
    this.ॱˊ = ((RelativeLayout)paramˉ[0]);
    this.ॱˊ.setTag(null);
    this.ˊॱ = ((TextView)paramˉ[5]);
    this.ˊॱ.setTag(null);
    this.ˋॱ = ((TextView)paramˉ[7]);
    this.ˋॱ.setTag(null);
    this.ʻ = ((LinearLayout)paramˉ[6]);
    this.ʻ.setTag(null);
    this.ॱॱ = ((Jn)paramˉ[3]);
    this.ॱॱ.setTag(null);
    this.ʼ = ((у)paramˉ[2]);
    this.ʼ.setTag(null);
    ˋ(paramView);
    ˋॱ();
  }
  
  private static String ˊ(int paramInt1, char paramChar, int paramInt2)
  {
    for (;;)
    {
      int j;
      int i;
      try
      {
        j = ʼॱ;
        j += 81;
        try
        {
          ʽॱ = j % 128;
          if (j % 2 != 0) {
            break label266;
          }
          switch (j)
          {
          case 1: 
          default: 
            continue;
            j = 67;
            continue;
            j = 1;
            break;
          case 0: 
            Object localObject = new String((char[])localObject);
            continue;
            j = 0;
            continue;
            localObject = new char[paramInt2];
            i = 0;
            continue;
            switch (j)
            {
            case 67: 
            default: 
              char[] arrayOfChar = ʾ;
              long l1 = arrayOfChar[(paramInt1 >>> i)];
              long l2 = i;
              long l3 = ˈ;
              localObject[i] = ((char)(int)(l1 % (l2 + l3) / paramChar));
              i += 113;
            }
            break;
          }
        }
        catch (Exception localException1)
        {
          throw localException1;
        }
        paramInt1 = ʼॱ + 79;
        ʽॱ = paramInt1 % 128;
        if (paramInt1 % 2 != 0) {
          return localException1;
        }
        return localException1;
      }
      catch (Exception localException2)
      {
        throw localException2;
      }
      if (i >= paramInt2)
      {
        continue;
        localException2[i] = ((char)(int)(ʾ[(paramInt1 + i)] ^ i * ˈ ^ paramChar));
        i += 1;
        continue;
        label266:
        j = 34;
      }
    }
  }
  
  /* Error */
  private String ˋ(String paramString)
  {
    // Byte code:
    //   0: goto +11 -> 11
    //   3: goto +74 -> 77
    //   6: iconst_1
    //   7: istore_3
    //   8: goto +6 -> 14
    //   11: goto +162 -> 173
    //   14: iload_3
    //   15: tableswitch	default:+21->36, 0:+24->39, 1:+129->144
    //   36: goto +108 -> 144
    //   39: aload 4
    //   41: iload_2
    //   42: aload_1
    //   43: aload_1
    //   44: arraylength
    //   45: iload_2
    //   46: isub
    //   47: iconst_1
    //   48: isub
    //   49: baload
    //   50: getstatic 145	o/Ms:ʿ	B
    //   53: ixor
    //   54: i2b
    //   55: bastore
    //   56: iload_2
    //   57: iconst_1
    //   58: iadd
    //   59: istore_2
    //   60: goto +55 -> 115
    //   63: aload_1
    //   64: arraylength
    //   65: istore_3
    //   66: iload_2
    //   67: iload_3
    //   68: if_icmpge +6 -> 74
    //   71: goto +97 -> 168
    //   74: goto -68 -> 6
    //   77: aload_1
    //   78: bipush 81
    //   80: ldc -110
    //   82: bipush 10
    //   84: invokestatic 148	o/Ms:ˊ	(ICI)Ljava/lang/String;
    //   87: invokevirtual 152	java/lang/String:intern	()Ljava/lang/String;
    //   90: invokevirtual 156	java/lang/String:getBytes	(Ljava/lang/String;)[B
    //   93: astore_1
    //   94: aload_1
    //   95: arraylength
    //   96: newarray byte
    //   98: astore 4
    //   100: iconst_0
    //   101: istore_2
    //   102: goto -39 -> 63
    //   105: astore_1
    //   106: new 158	java/lang/RuntimeException
    //   109: dup
    //   110: aload_1
    //   111: invokespecial 161	java/lang/RuntimeException:<init>	(Ljava/lang/Throwable;)V
    //   114: athrow
    //   115: goto -52 -> 63
    //   118: getstatic 48	o/Ms:ʼॱ	I
    //   121: bipush 9
    //   123: iadd
    //   124: istore_2
    //   125: iload_2
    //   126: sipush 128
    //   129: irem
    //   130: putstatic 50	o/Ms:ʽॱ	I
    //   133: iload_2
    //   134: iconst_2
    //   135: irem
    //   136: ifne +6 -> 142
    //   139: goto +66 -> 205
    //   142: aload_1
    //   143: areturn
    //   144: new 133	java/lang/String
    //   147: dup
    //   148: aload 4
    //   150: bipush 91
    //   152: ldc -94
    //   154: iconst_5
    //   155: invokestatic 148	o/Ms:ˊ	(ICI)Ljava/lang/String;
    //   158: invokevirtual 152	java/lang/String:intern	()Ljava/lang/String;
    //   161: invokespecial 165	java/lang/String:<init>	([BLjava/lang/String;)V
    //   164: astore_1
    //   165: goto -47 -> 118
    //   168: iconst_0
    //   169: istore_3
    //   170: goto -156 -> 14
    //   173: getstatic 48	o/Ms:ʼॱ	I
    //   176: istore_2
    //   177: iload_2
    //   178: bipush 83
    //   180: iadd
    //   181: istore_2
    //   182: iload_2
    //   183: sipush 128
    //   186: irem
    //   187: putstatic 50	o/Ms:ʽॱ	I
    //   190: iload_2
    //   191: iconst_2
    //   192: irem
    //   193: ifne +6 -> 199
    //   196: goto -193 -> 3
    //   199: goto -122 -> 77
    //   202: astore_1
    //   203: aload_1
    //   204: athrow
    //   205: aload_1
    //   206: areturn
    //   207: astore_1
    //   208: aload_1
    //   209: athrow
    // Local variable table:
    //   start	length	slot	name	signature
    //   0	210	0	this	Ms
    //   0	210	1	paramString	String
    //   41	152	2	i	int
    //   7	163	3	j	int
    //   39	110	4	arrayOfByte	byte[]
    // Exception table:
    //   from	to	target	type
    //   39	56	105	java/io/UnsupportedEncodingException
    //   63	66	105	java/io/UnsupportedEncodingException
    //   77	100	105	java/io/UnsupportedEncodingException
    //   144	165	105	java/io/UnsupportedEncodingException
    //   118	125	202	java/lang/Exception
    //   125	133	202	java/lang/Exception
    //   173	177	202	java/lang/Exception
    //   182	190	202	java/lang/Exception
    //   125	133	207	java/lang/Exception
  }
  
  static void ˏॱ()
  {
    int i;
    for (;;)
    {
      i = 36;
      break;
      i = ʽॱ + 77;
      ʼॱ = i % 128;
      if (i % 2 == 0) {
        break label80;
      }
    }
    for (;;)
    {
      try
      {
        ʿ = -102;
        return;
      }
      catch (Exception localException)
      {
        throw localException;
      }
      switch (i)
      {
      case 9: 
      default: 
        break;
      case 36: 
        ʿ = 122;
        return;
        label80:
        i = 9;
      }
    }
  }
  
  static void ॱˊ()
  {
    ˈ = -4093436948860050193L;
    ʾ = new char[] { -29731, 28461, 16909, 9497, 104, -7013, -13910, -20803, -27697, 30865, 23989, 17062, 10010, 3091, -3802, -10716, -17587, -24562, -31369, 27247, 20190, 13245, 6330, -561, -7488, -14411, -21256, -28394, 30279, 23349, 16434, 9538, 2629, -4225, -11154, -18284, -25196, -32032, 26591, 19677, 12789, 5796, -1268, -8104, -14985, -21964, -28845, 29777, 22880, 15978, 8860, 1926, -4957, -11888, -18726, -25611, -32535, 25878, 18959, 12048, 5157, -1706, -8639, -15504, -22485, -29519, 29091, 22162, 15243, 8424, 1484, -5438, -12503, -19419, -26338, 32278, 25457, 18538, 11607, 4674, -2383, -31143, 25260, 20353, 10480, 5524, -381, -9281, -15200, -24251, -30138, -19441, 20705, 32194, 6842, 10206 };
  }
  
  /* Error */
  public void ˋ(boolean paramBoolean)
  {
    // Byte code:
    //   0: goto +35 -> 35
    //   3: iconst_1
    //   4: istore_2
    //   5: goto +57 -> 62
    //   8: iconst_0
    //   9: istore_2
    //   10: goto +52 -> 62
    //   13: aload_0
    //   14: iload_1
    //   15: putfield 266	o/Ms:ॱᐝ	Z
    //   18: new 268	java/lang/NullPointerException
    //   21: dup
    //   22: invokespecial 269	java/lang/NullPointerException:<init>	()V
    //   25: athrow
    //   26: astore_3
    //   27: aload_3
    //   28: athrow
    //   29: aload_0
    //   30: iload_1
    //   31: putfield 266	o/Ms:ॱᐝ	Z
    //   34: return
    //   35: getstatic 50	o/Ms:ʽॱ	I
    //   38: bipush 117
    //   40: iadd
    //   41: istore_2
    //   42: iload_2
    //   43: sipush 128
    //   46: irem
    //   47: putstatic 48	o/Ms:ʼॱ	I
    //   50: iload_2
    //   51: iconst_2
    //   52: irem
    //   53: ifeq +6 -> 59
    //   56: goto -53 -> 3
    //   59: goto -51 -> 8
    //   62: iload_2
    //   63: tableswitch	default:+21->84, 0:+-34->29, 1:+-50->13
    //   84: goto -55 -> 29
    // Local variable table:
    //   start	length	slot	name	signature
    //   0	87	0	this	Ms
    //   0	87	1	paramBoolean	boolean
    //   4	59	2	i	int
    //   26	2	3	localException	Exception
    // Exception table:
    //   from	to	target	type
    //   29	34	26	java/lang/Exception
  }
  
  public void ˋॱ()
  {
    try
    {
      this.ʻॱ = 128L;
    }
    finally
    {
      localObject = finally;
      throw localObject;
    }
    ʽ();
  }
  
  public void ˎ(boolean paramBoolean)
  {
    this.ᐝॱ = paramBoolean;
    try
    {
      this.ʻॱ |= 0x40;
    }
    finally
    {
      localObject = finally;
      throw localObject;
    }
    ˊ(74);
    super.ʽ();
  }
  
  public void ˏ()
  {
    String str3 = ˊ(0, 35800, 4).intern();
    long l3;
    try
    {
      l3 = this.ʻॱ;
      this.ʻॱ = 0L;
    }
    finally
    {
      localObject1 = finally;
      throw localObject1;
    }
    int j = 0;
    Object localObject2 = null;
    String str2 = this.ͺ;
    int i = 0;
    boolean bool1 = this.ॱˎ;
    int k = 0;
    boolean bool2 = this.ॱˋ;
    boolean bool3 = this.ᐝॱ;
    int m = 0;
    long l1 = l3;
    Object localObject3;
    if ((0x84 & l3) != 0L)
    {
      l2 = l3;
      if ((0x84 & l3) != 0L) {
        if (bool1) {
          l2 = l3 | 0x800;
        } else {
          l2 = l3 | 0x400;
        }
      }
      if (bool1)
      {
        localObject3 = this.ˊॱ.getResources().getString(2131755270);
        localObject2 = localObject3;
        if (((String)localObject3).startsWith(str3)) {
          localObject2 = ˋ(((String)localObject3).substring(4)).intern();
        }
        l1 = l2;
      }
      else
      {
        localObject3 = this.ˊॱ.getResources().getString(2131755272);
        l1 = l2;
        localObject2 = localObject3;
        if (((String)localObject3).startsWith(str3))
        {
          localObject2 = ˋ(((String)localObject3).substring(4)).intern();
          l1 = l2;
        }
      }
    }
    long l2 = l1;
    if ((0x90 & l1) != 0L)
    {
      l2 = l1;
      if ((0x90 & l1) != 0L) {
        if (bool2) {
          l2 = l1 | 0x2000;
        } else {
          l2 = l1 | 0x1000;
        }
      }
      if (bool2) {
        i = 0;
      } else {
        i = 8;
      }
    }
    l1 = l2;
    if ((0xC0 & l2) != 0L)
    {
      l1 = l2;
      if ((0xC0 & l2) != 0L) {
        if (bool3) {
          l1 = l2 | 0x200 | 0x8000 | 0x20000;
        } else {
          l1 = l2 | 0x100 | 0x4000 | 0x10000;
        }
      }
      if (bool3) {
        j = 8;
      } else {
        j = 0;
      }
      if (bool3) {
        k = 4;
      } else {
        k = 0;
      }
      if (bool3) {
        m = 0;
      } else {
        m = 8;
      }
    }
    if ((0x80 & l1) != 0L)
    {
      Object localObject4 = this.ॱ;
      String str1 = this.ॱ.getResources().getString(2131755143);
      localObject3 = str1;
      if (str1.startsWith(str3)) {
        localObject3 = ˋ(str1.substring(4)).intern();
      }
      ʹ.ˊ((TextView)localObject4, (CharSequence)localObject3);
      r.ˊ(this.ᐝ, ˊ(4, '\000', 77).intern(), ॱ(this.ᐝ, 2131230823), true);
      localObject4 = this.ˋॱ;
      str1 = this.ˋॱ.getResources().getString(2131755144);
      localObject3 = str1;
      if (str1.startsWith(str3)) {
        localObject3 = ˋ(str1.substring(4)).intern();
      }
      ʹ.ˊ((TextView)localObject4, (CharSequence)localObject3);
      localObject4 = this.ॱॱ;
      str1 = this.ॱॱ.getResources().getString(2131755452);
      localObject3 = str1;
      if (str1.startsWith(str3)) {
        localObject3 = ˋ(str1.substring(4)).intern();
      }
      ((Jn)localObject4).setHint((String)localObject3);
    }
    if ((0xC0 & l1) != 0L)
    {
      this.ˎ.setVisibility(j);
      this.ʻ.setVisibility(m);
      this.ॱॱ.setVisibility(k);
    }
    if ((0x84 & l1) != 0L) {
      ʹ.ˊ(this.ˊॱ, (CharSequence)localObject2);
    }
    if ((0x90 & l1) != 0L) {
      this.ˊॱ.setVisibility(i);
    }
    if ((0x81 & l1) != 0L) {
      this.ʼ.setTitle(str2);
    }
  }
  
  public void ˏ(String paramString)
  {
    this.ͺ = paramString;
    try
    {
      this.ʻॱ |= 1L;
    }
    finally
    {
      paramString = finally;
      throw paramString;
    }
    ˊ(123);
    super.ʽ();
  }
  
  public void ˏ(boolean paramBoolean)
  {
    this.ॱˋ = paramBoolean;
    try
    {
      this.ʻॱ |= 0x10;
    }
    finally
    {
      localObject = finally;
      throw localObject;
    }
    ˊ(63);
    super.ʽ();
  }
  
  public boolean ˏ(int paramInt1, Object paramObject, int paramInt2)
  {
    break label69;
    paramInt1 = 0;
    break label42;
    label8:
    paramInt1 = 1;
    break label42;
    return true;
    label42:
    label69:
    for (;;)
    {
      paramInt1 = ʽॱ + 61;
      ʼॱ = paramInt1 % 128;
      if (paramInt1 % 2 != 0) {
        break label8;
      }
      break;
      switch (paramInt1)
      {
      case 1: 
      default: 
        break;
      case 0: 
        return false;
      }
    }
  }
  
  public void ॱ(boolean paramBoolean)
  {
    this.ॱˎ = paramBoolean;
    try
    {
      this.ʻॱ |= 0x4;
    }
    finally
    {
      localObject = finally;
      throw localObject;
    }
    ˊ(72);
    super.ʽ();
  }
  
  public boolean ॱ()
  {
    try
    {
      long l = this.ʻॱ;
      if (l != 0L) {
        return true;
      }
    }
    finally
    {
      localObject = finally;
      throw localObject;
    }
    return false;
  }
}
