package o;

import android.content.res.Resources;
import android.databinding.ViewDataBinding;
import android.databinding.ViewDataBinding.If;
import android.util.SparseIntArray;
import android.widget.Button;
import android.widget.ImageView;
import android.widget.LinearLayout;
import android.widget.RelativeLayout;
import android.widget.ScrollView;
import android.widget.TextView;
import java.io.UnsupportedEncodingException;

public class Mt
  extends ViewDataBinding
{
  private static final SparseIntArray ʻॱ;
  private static byte ˊˊ;
  private static int ˊˋ;
  private static int ˊᐝ;
  private static int[] ˋˊ;
  private static final ViewDataBinding.If ॱᐝ;
  public final ME ʻ;
  public final ImageView ʼ;
  private HQ ʼॱ;
  public final TextView ʽ;
  private ˍ ʽॱ;
  private ˍ ʾ;
  private long ʿ;
  private HQ ˈ;
  public final Button ˊ;
  public final TextView ˊॱ;
  public final у ˋॱ;
  public final LinearLayout ˎ;
  public final ImageView ˏॱ;
  public final ScrollView ͺ;
  public final LinearLayout ॱ;
  public final ME ॱˊ;
  private Gh ॱˋ;
  private boolean ॱˎ;
  public final Jc ॱॱ;
  public final Ja ᐝ;
  private final RelativeLayout ᐝॱ;
  
  static
  {
    for (;;)
    {
      try
      {
        ˊᐝ = 0;
        ˊˋ = 1;
        ˊॱ();
        ॱˊ();
        ॱᐝ = null;
        ʻॱ = new SparseIntArray();
        ʻॱ.put(2131296628, 10);
        ʻॱ.put(2131296774, 11);
        ʻॱ.put(2131296345, 12);
        ʻॱ.put(2131296400, 13);
      }
      catch (Exception localException)
      {
        throw localException;
      }
      switch (i)
      {
      default: 
        break label140;
        do
        {
          i = 0;
          break;
          i = ˊᐝ + 29;
          ˊˋ = i % 128;
        } while (i % 2 == 0);
        break;
      case 1: 
        return;
        i = 1;
      }
    }
    label140:
    int i = 68 / 0;
  }
  
  /* Error */
  public Mt(ˉ paramˉ, android.view.View paramView)
  {
    // Byte code:
    //   0: aload_0
    //   1: aload_1
    //   2: aload_2
    //   3: iconst_2
    //   4: invokespecial 89	android/databinding/ViewDataBinding:<init>	(Lo/ˉ;Landroid/view/View;I)V
    //   7: new 6	o/Mt$1
    //   10: dup
    //   11: aload_0
    //   12: invokespecial 92	o/Mt$1:<init>	(Lo/Mt;)V
    //   15: astore_3
    //   16: aload_0
    //   17: aload_3
    //   18: putfield 94	o/Mt:ʽॱ	Lo/ˍ;
    //   21: new 8	o/Mt$4
    //   24: dup
    //   25: aload_0
    //   26: invokespecial 95	o/Mt$4:<init>	(Lo/Mt;)V
    //   29: astore_3
    //   30: aload_0
    //   31: aload_3
    //   32: putfield 97	o/Mt:ʾ	Lo/ˍ;
    //   35: aload_0
    //   36: ldc2_w 98
    //   39: putfield 101	o/Mt:ʿ	J
    //   42: getstatic 69	o/Mt:ॱᐝ	Landroid/databinding/ViewDataBinding$If;
    //   45: astore_3
    //   46: aload_1
    //   47: aload_2
    //   48: bipush 14
    //   50: aload_3
    //   51: getstatic 76	o/Mt:ʻॱ	Landroid/util/SparseIntArray;
    //   54: invokestatic 104	o/Mt:ॱ	(Lo/ˉ;Landroid/view/View;ILandroid/databinding/ViewDataBinding$If;Landroid/util/SparseIntArray;)[Ljava/lang/Object;
    //   57: astore_1
    //   58: aload_0
    //   59: aload_1
    //   60: bipush 9
    //   62: aaload
    //   63: checkcast 106	android/widget/Button
    //   66: putfield 108	o/Mt:ˊ	Landroid/widget/Button;
    //   69: aload_0
    //   70: getfield 108	o/Mt:ˊ	Landroid/widget/Button;
    //   73: aconst_null
    //   74: invokevirtual 112	android/widget/Button:setTag	(Ljava/lang/Object;)V
    //   77: aload_0
    //   78: aload_1
    //   79: bipush 12
    //   81: aaload
    //   82: checkcast 114	android/widget/LinearLayout
    //   85: putfield 116	o/Mt:ˎ	Landroid/widget/LinearLayout;
    //   88: aload_0
    //   89: aload_1
    //   90: bipush 13
    //   92: aaload
    //   93: checkcast 114	android/widget/LinearLayout
    //   96: putfield 118	o/Mt:ॱ	Landroid/widget/LinearLayout;
    //   99: aload_0
    //   100: aload_1
    //   101: bipush 7
    //   103: aaload
    //   104: checkcast 120	o/Ja
    //   107: putfield 122	o/Mt:ᐝ	Lo/Ja;
    //   110: aload_0
    //   111: getfield 122	o/Mt:ᐝ	Lo/Ja;
    //   114: aconst_null
    //   115: invokevirtual 123	o/Ja:setTag	(Ljava/lang/Object;)V
    //   118: aload_0
    //   119: aload_1
    //   120: bipush 8
    //   122: aaload
    //   123: checkcast 125	o/Jc
    //   126: putfield 127	o/Mt:ॱॱ	Lo/Jc;
    //   129: aload_0
    //   130: getfield 127	o/Mt:ॱॱ	Lo/Jc;
    //   133: aconst_null
    //   134: invokevirtual 128	o/Jc:setTag	(Ljava/lang/Object;)V
    //   137: aload_0
    //   138: aload_1
    //   139: iconst_3
    //   140: aaload
    //   141: checkcast 130	android/widget/TextView
    //   144: putfield 132	o/Mt:ʽ	Landroid/widget/TextView;
    //   147: aload_0
    //   148: getfield 132	o/Mt:ʽ	Landroid/widget/TextView;
    //   151: aconst_null
    //   152: invokevirtual 133	android/widget/TextView:setTag	(Ljava/lang/Object;)V
    //   155: aload_0
    //   156: aload_1
    //   157: iconst_5
    //   158: aaload
    //   159: checkcast 135	o/ME
    //   162: putfield 137	o/Mt:ʻ	Lo/ME;
    //   165: aload_0
    //   166: getfield 137	o/Mt:ʻ	Lo/ME;
    //   169: aconst_null
    //   170: invokevirtual 138	o/ME:setTag	(Ljava/lang/Object;)V
    //   173: aload_0
    //   174: aload_1
    //   175: iconst_1
    //   176: aaload
    //   177: checkcast 140	android/widget/ImageView
    //   180: putfield 142	o/Mt:ʼ	Landroid/widget/ImageView;
    //   183: aload_0
    //   184: getfield 142	o/Mt:ʼ	Landroid/widget/ImageView;
    //   187: aconst_null
    //   188: invokevirtual 143	android/widget/ImageView:setTag	(Ljava/lang/Object;)V
    //   191: aload_0
    //   192: aload_1
    //   193: iconst_0
    //   194: aaload
    //   195: checkcast 145	android/widget/RelativeLayout
    //   198: putfield 147	o/Mt:ᐝॱ	Landroid/widget/RelativeLayout;
    //   201: aload_0
    //   202: getfield 147	o/Mt:ᐝॱ	Landroid/widget/RelativeLayout;
    //   205: aconst_null
    //   206: invokevirtual 148	android/widget/RelativeLayout:setTag	(Ljava/lang/Object;)V
    //   209: aload_0
    //   210: aload_1
    //   211: bipush 10
    //   213: aaload
    //   214: checkcast 150	android/widget/ScrollView
    //   217: putfield 152	o/Mt:ͺ	Landroid/widget/ScrollView;
    //   220: aload_0
    //   221: aload_1
    //   222: iconst_4
    //   223: aaload
    //   224: checkcast 130	android/widget/TextView
    //   227: putfield 154	o/Mt:ˊॱ	Landroid/widget/TextView;
    //   230: aload_0
    //   231: getfield 154	o/Mt:ˊॱ	Landroid/widget/TextView;
    //   234: aconst_null
    //   235: invokevirtual 133	android/widget/TextView:setTag	(Ljava/lang/Object;)V
    //   238: aload_0
    //   239: aload_1
    //   240: bipush 6
    //   242: aaload
    //   243: checkcast 135	o/ME
    //   246: putfield 156	o/Mt:ॱˊ	Lo/ME;
    //   249: aload_0
    //   250: getfield 156	o/Mt:ॱˊ	Lo/ME;
    //   253: aconst_null
    //   254: invokevirtual 138	o/ME:setTag	(Ljava/lang/Object;)V
    //   257: aload_0
    //   258: aload_1
    //   259: iconst_2
    //   260: aaload
    //   261: checkcast 158	o/у
    //   264: putfield 160	o/Mt:ˋॱ	Lo/у;
    //   267: aload_0
    //   268: getfield 160	o/Mt:ˋॱ	Lo/у;
    //   271: aconst_null
    //   272: invokevirtual 161	o/у:setTag	(Ljava/lang/Object;)V
    //   275: aload_0
    //   276: aload_1
    //   277: bipush 11
    //   279: aaload
    //   280: checkcast 140	android/widget/ImageView
    //   283: putfield 163	o/Mt:ˏॱ	Landroid/widget/ImageView;
    //   286: aload_0
    //   287: aload_2
    //   288: invokevirtual 167	o/Mt:ˋ	(Landroid/view/View;)V
    //   291: aload_0
    //   292: invokevirtual 169	o/Mt:ͺ	()V
    //   295: return
    //   296: astore_1
    //   297: aload_1
    //   298: athrow
    //   299: astore_1
    //   300: aload_1
    //   301: athrow
    // Local variable table:
    //   start	length	slot	name	signature
    //   0	302	0	this	Mt
    //   0	302	1	paramˉ	ˉ
    //   0	302	2	paramView	android.view.View
    //   15	36	3	localObject	Object
    // Exception table:
    //   from	to	target	type
    //   30	35	296	java/lang/Exception
    //   35	42	296	java/lang/Exception
    //   42	46	296	java/lang/Exception
    //   46	295	296	java/lang/Exception
    //   16	21	299	java/lang/Exception
  }
  
  private boolean ˊ(ـ<String> paramـ, int paramInt)
  {
    if (paramInt == 0)
    {
      try
      {
        this.ʿ |= 0x2;
      }
      finally
      {
        paramـ = finally;
        throw paramـ;
      }
      return true;
    }
    return false;
  }
  
  static void ˊॱ()
  {
    ˋˊ = new int[] { 30419148, 865737693, 1370793822, -995389047, -1410407186, -1991551193, -859856155, -770478170, 1774218340, -1039666255, -1311958405, -558338708, -1994141842, 1950730487, -1161319069, 956785894, 2144369188, 1931086048 };
  }
  
  private String ˎ(String paramString)
  {
    break label315;
    for (;;)
    {
      try
      {
        paramString = new String(paramString, ˎ(new int[] { 360623365, -893863228, -1647555448, -297613887 }, 5).intern());
        return paramString;
      }
      catch (UnsupportedEncodingException paramString)
      {
        int j;
        byte[] arrayOfByte;
        label161:
        label176:
        throw new RuntimeException(paramString);
      }
      j = 0;
      continue;
      j = ˊˋ + 119;
      ˊᐝ = j % 128;
      if (j % 2 == 0)
      {
        continue;
        i = 0;
        continue;
        arrayOfByte = paramString.getBytes(ˎ(new int[] { -108166826, 1509033913, 1911750676, -1482719746, -1021164534, 1798789858 }, 10).intern());
        paramString = new byte[arrayOfByte.length];
        continue;
      }
      else
      {
        paramString[i] = ((byte)(arrayOfByte[((arrayOfByte.length << i) * 1)] & ˊˊ));
        i += 93;
      }
      j = arrayOfByte.length;
      if (i >= j)
      {
        continue;
        switch (j)
        {
        }
      }
    }
    label203:
    for (int i = 1;; i = 0)
    {
      switch (i)
      {
      }
      arrayOfByte = paramString.getBytes(ˎ(new int[] { -108166826, 1509033913, 1911750676, -1482719746, -1021164534, 1798789858 }, 16).intern());
      paramString = new byte[arrayOfByte.length];
      break;
      paramString[i] = ((byte)(arrayOfByte[(arrayOfByte.length - i - 1)] ^ ˊˊ));
      i += 1;
      break label161;
      j = 1;
      break label176;
      label315:
      i = ˊˋ + 17;
      ˊᐝ = i % 128;
      if (i % 2 != 0) {
        break label203;
      }
    }
  }
  
  /* Error */
  private static String ˎ(int[] paramArrayOfInt, int paramInt)
  {
    // Byte code:
    //   0: goto +78 -> 78
    //   3: getstatic 61	o/Mt:ˊᐝ	I
    //   6: bipush 83
    //   8: iadd
    //   9: istore_3
    //   10: iload_3
    //   11: sipush 128
    //   14: irem
    //   15: putstatic 63	o/Mt:ˊˋ	I
    //   18: iload_3
    //   19: iconst_2
    //   20: irem
    //   21: ifne +6 -> 27
    //   24: goto +189 -> 213
    //   27: goto +218 -> 245
    //   30: bipush 96
    //   32: istore_2
    //   33: iload_2
    //   34: lookupswitch	default:+26->60, 66:+117->151, 96:+182->216
    //   60: goto +91 -> 151
    //   63: new 199	java/lang/String
    //   66: dup
    //   67: aload 6
    //   69: iconst_0
    //   70: iload_1
    //   71: invokespecial 233	java/lang/String:<init>	([CII)V
    //   74: areturn
    //   75: astore_0
    //   76: aload_0
    //   77: athrow
    //   78: goto +9 -> 87
    //   81: bipush 78
    //   83: istore_3
    //   84: goto +36 -> 120
    //   87: getstatic 61	o/Mt:ˊᐝ	I
    //   90: bipush 25
    //   92: iadd
    //   93: istore_2
    //   94: iload_2
    //   95: sipush 128
    //   98: irem
    //   99: putstatic 63	o/Mt:ˊˋ	I
    //   102: iload_2
    //   103: iconst_2
    //   104: irem
    //   105: ifne +6 -> 111
    //   108: goto +6 -> 114
    //   111: goto -81 -> 30
    //   114: bipush 66
    //   116: istore_2
    //   117: goto -84 -> 33
    //   120: iload_3
    //   121: lookupswitch	default:+27->148, 74:+-118->3, 78:+-58->63
    //   148: goto -85 -> 63
    //   151: iconst_4
    //   152: newarray char
    //   154: astore 5
    //   156: aload_0
    //   157: arraylength
    //   158: iconst_0
    //   159: imul
    //   160: newarray char
    //   162: astore 6
    //   164: getstatic 194	o/Mt:ˋˊ	[I
    //   167: astore 4
    //   169: aload 4
    //   171: invokevirtual 238	[I:clone	()Ljava/lang/Object;
    //   174: astore 4
    //   176: aload 4
    //   178: checkcast 234	[I
    //   181: astore 4
    //   183: iconst_0
    //   184: istore_2
    //   185: goto +9 -> 194
    //   188: bipush 74
    //   190: istore_3
    //   191: goto -71 -> 120
    //   194: aload_0
    //   195: astore 7
    //   197: iload_2
    //   198: aload 7
    //   200: arraylength
    //   201: if_icmpge +6 -> 207
    //   204: goto -16 -> 188
    //   207: goto -126 -> 81
    //   210: astore_0
    //   211: aload_0
    //   212: athrow
    //   213: goto +32 -> 245
    //   216: iconst_4
    //   217: newarray char
    //   219: astore 5
    //   221: aload_0
    //   222: arraylength
    //   223: iconst_1
    //   224: ishl
    //   225: newarray char
    //   227: astore 6
    //   229: getstatic 194	o/Mt:ˋˊ	[I
    //   232: invokevirtual 238	[I:clone	()Ljava/lang/Object;
    //   235: checkcast 234	[I
    //   238: astore 4
    //   240: iconst_0
    //   241: istore_2
    //   242: goto -48 -> 194
    //   245: aload 5
    //   247: iconst_0
    //   248: aload 7
    //   250: iload_2
    //   251: iaload
    //   252: bipush 16
    //   254: ishr
    //   255: i2c
    //   256: castore
    //   257: aload 5
    //   259: iconst_1
    //   260: aload 7
    //   262: iload_2
    //   263: iaload
    //   264: i2c
    //   265: castore
    //   266: aload 5
    //   268: iconst_2
    //   269: aload 7
    //   271: iload_2
    //   272: iconst_1
    //   273: iadd
    //   274: iaload
    //   275: bipush 16
    //   277: ishr
    //   278: i2c
    //   279: castore
    //   280: aload 5
    //   282: iconst_3
    //   283: aload 7
    //   285: iload_2
    //   286: iconst_1
    //   287: iadd
    //   288: iaload
    //   289: i2c
    //   290: castore
    //   291: aload 5
    //   293: aload 4
    //   295: iconst_0
    //   296: invokestatic 244	o/oN:ˏ	([C[IZ)[I
    //   299: pop
    //   300: aload 6
    //   302: iload_2
    //   303: iconst_1
    //   304: ishl
    //   305: aload 5
    //   307: iconst_0
    //   308: caload
    //   309: castore
    //   310: aload 6
    //   312: iload_2
    //   313: iconst_1
    //   314: ishl
    //   315: iconst_1
    //   316: iadd
    //   317: aload 5
    //   319: iconst_1
    //   320: caload
    //   321: castore
    //   322: aload 6
    //   324: iload_2
    //   325: iconst_1
    //   326: ishl
    //   327: iconst_2
    //   328: iadd
    //   329: aload 5
    //   331: iconst_2
    //   332: caload
    //   333: castore
    //   334: aload 6
    //   336: iload_2
    //   337: iconst_1
    //   338: ishl
    //   339: iconst_3
    //   340: iadd
    //   341: aload 5
    //   343: iconst_3
    //   344: caload
    //   345: castore
    //   346: iload_2
    //   347: iconst_2
    //   348: iadd
    //   349: istore_2
    //   350: goto -156 -> 194
    // Local variable table:
    //   start	length	slot	name	signature
    //   0	353	0	paramArrayOfInt	int[]
    //   0	353	1	paramInt	int
    //   32	318	2	i	int
    //   9	182	3	j	int
    //   167	127	4	localObject	Object
    //   154	188	5	arrayOfChar1	char[]
    //   67	268	6	arrayOfChar2	char[]
    //   195	89	7	arrayOfInt	int[]
    // Exception table:
    //   from	to	target	type
    //   164	169	75	java/lang/Exception
    //   169	176	210	java/lang/Exception
    //   176	183	210	java/lang/Exception
    //   291	300	210	java/lang/Exception
  }
  
  private boolean ॱ(ـ<String> paramـ, int paramInt)
  {
    if (paramInt == 0)
    {
      try
      {
        this.ʿ |= 1L;
      }
      finally
      {
        paramـ = finally;
        throw paramـ;
      }
      return true;
    }
    return false;
  }
  
  static void ॱˊ()
  {
    for (;;)
    {
      i = ˊˋ + 55;
      ˊᐝ = i % 128;
      if (i % 2 != 0) {
        break label44;
      }
      break;
    }
    int i = 0;
    for (;;)
    {
      ˊˊ = -102;
      return;
      label44:
      i = 1;
      break label55;
      ˊˊ = 109;
      return;
      label55:
      switch (i)
      {
      }
    }
  }
  
  public void ˊ(HQ paramHQ)
  {
    this.ˈ = paramHQ;
    try
    {
      this.ʿ |= 0x10;
    }
    finally
    {
      paramHQ = finally;
      throw paramHQ;
    }
    ˊ(43);
    super.ʽ();
  }
  
  public void ˎ(boolean paramBoolean)
  {
    this.ॱˎ = paramBoolean;
    try
    {
      this.ʿ |= 0x4;
    }
    finally
    {
      localObject = finally;
      throw localObject;
    }
    ˊ(68);
    super.ʽ();
  }
  
  public void ˏ()
  {
    String str = ˎ(new int[] { 696944728, -826398958 }, 4).intern();
    try
    {
      l2 = this.ʿ;
      this.ʿ = 0L;
    }
    finally
    {
      localObject1 = finally;
      throw localObject1;
    }
    boolean bool1 = false;
    boolean bool2 = false;
    Object localObject6 = null;
    Object localObject8 = null;
    boolean bool3 = false;
    boolean bool5 = this.ॱˎ;
    int i = 0;
    Gh localGh = this.ॱˋ;
    Object localObject4 = null;
    Object localObject7 = null;
    int k = 0;
    Object localObject5 = null;
    HQ localHQ1 = this.ˈ;
    boolean bool4 = false;
    HQ localHQ2 = this.ʼॱ;
    long l1 = l2;
    if ((0x44 & l2) != 0L)
    {
      l1 = l2;
      if ((0x44 & l2) != 0L) {
        if (bool5) {
          l1 = l2 | 0x400;
        } else {
          l1 = l2 | 0x200;
        }
      }
      if (bool5) {
        i = 4;
      } else {
        i = 0;
      }
    }
    Object localObject3 = localObject6;
    Object localObject2;
    if ((0x4B & l1) != 0L)
    {
      localObject2 = localObject7;
      if ((0x49 & l1) != 0L)
      {
        localObject3 = localObject8;
        if (localGh != null) {
          localObject3 = localGh.amount;
        }
        ˎ(0, (ˑ)localObject3);
        localObject2 = localObject7;
        if (localObject3 != null) {
          localObject2 = (String)((ـ)localObject3).ˏ();
        }
      }
      localObject3 = localObject6;
      localObject4 = localObject2;
      if ((0x4A & l1) != 0L)
      {
        if (localGh != null) {
          localObject5 = localGh.transferDetail;
        }
        ˎ(1, (ˑ)localObject5);
        localObject3 = localObject6;
        localObject4 = localObject2;
        if (localObject5 != null)
        {
          localObject3 = (String)((ـ)localObject5).ˏ();
          localObject4 = localObject2;
        }
      }
    }
    long l2 = l1;
    if ((0x70 & l1) != 0L)
    {
      if (localHQ1 != null) {
        bool1 = localHQ1.ˊᐝ();
      }
      int j;
      if (!bool1) {
        j = 1;
      } else {
        j = 0;
      }
      l2 = l1;
      k = j;
      if ((0x70 & l1) != 0L) {
        if (j != 0)
        {
          l2 = l1 | 0x100;
          k = j;
        }
        else
        {
          l2 = l1 | 0x80;
          k = j;
        }
      }
    }
    bool1 = bool4;
    if ((0x100 & l2) != 0L)
    {
      bool1 = bool3;
      if (localHQ2 != null) {
        bool1 = localHQ2.ˊᐝ();
      }
      if (!bool1) {
        bool1 = true;
      } else {
        bool1 = false;
      }
    }
    if ((0x70 & l2) != 0L) {
      if (k != 0) {
        bool2 = bool1;
      } else {
        bool2 = false;
      }
    }
    if ((0x70 & l2) != 0L) {
      this.ˊ.setEnabled(bool2);
    }
    if ((0x40 & l2) != 0L)
    {
      localObject6 = this.ˊ;
      localObject5 = this.ˊ.getResources().getString(2131755147);
      localObject2 = localObject5;
      if (((String)localObject5).startsWith(str)) {
        localObject2 = ˎ(((String)localObject5).substring(4)).intern();
      }
      ʹ.ˊ((TextView)localObject6, (CharSequence)localObject2);
      Jr.ॱ(this.ᐝ, this.ʽॱ);
      localObject6 = this.ᐝ;
      localObject5 = this.ᐝ.getResources().getString(2131755605);
      localObject2 = localObject5;
      if (((String)localObject5).startsWith(str)) {
        localObject2 = ˎ(((String)localObject5).substring(4)).intern();
      }
      ((Ja)localObject6).setHintText((String)localObject2);
      localObject6 = this.ॱॱ;
      localObject5 = this.ॱॱ.getResources().getString(2131755606);
      localObject2 = localObject5;
      if (((String)localObject5).startsWith(str)) {
        localObject2 = ˎ(((String)localObject5).substring(4)).intern();
      }
      ((Jc)localObject6).setHintText((String)localObject2);
      Jq.ˋ(this.ॱॱ, this.ʾ);
      this.ॱॱ.setInputType(16385);
      this.ॱॱ.setMaxInputLength(30);
      localObject6 = this.ʽ;
      localObject5 = this.ʽ.getResources().getString(2131755608);
      localObject2 = localObject5;
      if (((String)localObject5).startsWith(str)) {
        localObject2 = ˎ(((String)localObject5).substring(4)).intern();
      }
      ʹ.ˊ((TextView)localObject6, (CharSequence)localObject2);
      r.ˊ(this.ʼ, ˎ(new int[] { -197854181, 1464415074, -1003685818, 1376917551, -1475615194, 622757323, -1378490424, -918863424, -171306907, 77890569, -2131030648, -206590315, 904788964, -511910437, 1421005475, 2062609932, -1218857628, 1451223460, 1862607982, -177346584, 1365952696, -2143627679, -1244153925, -1942692427, 235844387, -1051626533, -1762178677, -1918769977, -1759567601, -834886752, 1417065381, 644809968, -1545681543, 1674295800, 1125877354, 1726125962, 1754722093, 2129491674, 248975181, 827944452 }, 77).intern(), ॱ(this.ʼ, 2131230823), true);
      localObject6 = this.ˊॱ;
      localObject5 = this.ˊॱ.getResources().getString(2131755600);
      localObject2 = localObject5;
      if (((String)localObject5).startsWith(str)) {
        localObject2 = ˎ(((String)localObject5).substring(4)).intern();
      }
      ʹ.ˊ((TextView)localObject6, (CharSequence)localObject2);
      A.ॱ(this.ˋॱ, true);
      localObject6 = this.ˋॱ;
      localObject5 = this.ˋॱ.getResources().getString(2131755604);
      localObject2 = localObject5;
      if (((String)localObject5).startsWith(str)) {
        localObject2 = ˎ(((String)localObject5).substring(4)).intern();
      }
      ((у)localObject6).setTitle((CharSequence)localObject2);
    }
    if ((0x44 & l2) != 0L) {
      this.ˊ.setVisibility(i);
    }
    if ((0x49 & l2) != 0L) {
      this.ᐝ.setAmount(localObject4);
    }
    if ((0x4A & l2) != 0L) {
      this.ॱॱ.setInputText((String)localObject3);
    }
    if ((0x50 & l2) != 0L) {
      this.ʻ.setCard(localHQ1);
    }
    if ((0x60 & l2) != 0L) {
      this.ॱˊ.setCard(localHQ2);
    }
  }
  
  public void ˏ(Gh paramGh)
  {
    this.ॱˋ = paramGh;
    try
    {
      this.ʿ |= 0x8;
    }
    finally
    {
      paramGh = finally;
      throw paramGh;
    }
    ˊ(129);
    super.ʽ();
  }
  
  public void ˏ(HQ paramHQ)
  {
    this.ʼॱ = paramHQ;
    try
    {
      this.ʿ |= 0x20;
    }
    finally
    {
      paramHQ = finally;
      throw paramHQ;
    }
    ˊ(125);
    super.ʽ();
  }
  
  public boolean ˏ(int paramInt1, Object paramObject, int paramInt2)
  {
    for (;;)
    {
      int i = 0;
      break label59;
      boolean bool;
      switch (paramInt1)
      {
      default: 
        break;
      case 0: 
        bool = ॱ((ـ)paramObject, paramInt2);
        break;
      }
      label59:
      do
      {
        i = 1;
        switch (i)
        {
        }
        i = null.length;
        switch (paramInt1)
        {
        case 0: 
        default: 
          return false;
        }
        return ˊ((ـ)paramObject, paramInt2);
        paramInt1 = ˊᐝ + 115;
        ˊˋ = paramInt1 % 128;
        if (paramInt1 % 2 == 0) {
          return bool;
        }
        return bool;
        i = ˊˋ + 5;
        ˊᐝ = i % 128;
      } while (i % 2 != 0);
    }
  }
  
  public void ͺ()
  {
    try
    {
      this.ʿ = 64L;
    }
    finally
    {
      localObject = finally;
      throw localObject;
    }
    ʽ();
  }
  
  public boolean ॱ()
  {
    try
    {
      long l = this.ʿ;
      if (l != 0L) {
        return true;
      }
    }
    finally
    {
      localObject = finally;
      throw localObject;
    }
    return false;
  }
}
