package o;

import android.content.res.Resources;
import android.databinding.ViewDataBinding;
import android.databinding.ViewDataBinding.If;
import android.util.SparseIntArray;
import android.view.View;
import android.widget.Button;
import android.widget.FrameLayout;
import android.widget.ImageView;
import android.widget.LinearLayout;
import android.widget.ProgressBar;
import android.widget.RelativeLayout;
import android.widget.ScrollView;
import android.widget.TextView;
import java.io.UnsupportedEncodingException;

public class Mu
  extends ViewDataBinding
{
  private static final SparseIntArray ʼॱ;
  private static final ViewDataBinding.If ˈ;
  private static int ˎˏ;
  private static long ˏˏ;
  private static byte ͺॱ;
  private static int ـ;
  private static int ॱʻ;
  private static char ॱʽ;
  public final FrameLayout ʻ;
  public final у ʻॱ;
  public final ImageView ʼ;
  public final TextView ʽ;
  public final ImageView ʽॱ;
  private final RelativeLayout ʾ;
  public final Je ʿ;
  private final TextView ˉ;
  public final View ˊ;
  private final ImageView ˊˊ;
  private final LinearLayout ˊˋ;
  public final LinearLayout ˊॱ;
  private final TextView ˊᐝ;
  private final TextView ˋˊ;
  private HQ ˋˋ;
  public final ME ˋॱ;
  private HQ ˋᐝ;
  private Gh ˌ;
  private boolean ˍ;
  public final LinearLayout ˎ;
  private boolean ˎˎ;
  private long ˏˎ;
  public final TextView ˏॱ;
  private coN ˑ;
  public final ScrollView ͺ;
  public final View ॱ;
  public final ProgressBar ॱˊ;
  public final Ꭸ ॱˋ;
  public final LinearLayout ॱˎ;
  public final Button ॱॱ;
  public final Je ॱᐝ;
  public final ME ᐝ;
  public final Je ᐝॱ;
  
  static
  {
    for (;;)
    {
      int i = ॱʻ + 99;
      ـ = i % 128;
      if (i % 2 != 0) {
        return;
      }
      return;
      ॱʻ = 0;
      ـ = 1;
      ˋॱ();
      ˏॱ();
      ˈ = null;
      ʼॱ = new SparseIntArray();
      ʼॱ.put(2131296628, 20);
      ʼॱ.put(2131296774, 21);
      ʼॱ.put(2131296654, 22);
      ʼॱ.put(2131296319, 23);
      ʼॱ.put(2131296320, 24);
      ʼॱ.put(2131296366, 25);
    }
  }
  
  /* Error */
  public Mu(ˉ paramˉ, View paramView)
  {
    // Byte code:
    //   0: goto +9 -> 9
    //   3: astore_1
    //   4: aload_1
    //   5: athrow
    //   6: astore_1
    //   7: aload_1
    //   8: athrow
    //   9: aload_0
    //   10: aload_1
    //   11: aload_2
    //   12: iconst_4
    //   13: invokespecial 104	android/databinding/ViewDataBinding:<init>	(Lo/ˉ;Landroid/view/View;I)V
    //   16: aload_0
    //   17: ldc2_w 105
    //   20: putfield 108	o/Mu:ˏˎ	J
    //   23: getstatic 80	o/Mu:ˈ	Landroid/databinding/ViewDataBinding$If;
    //   26: astore_3
    //   27: getstatic 87	o/Mu:ʼॱ	Landroid/util/SparseIntArray;
    //   30: astore 4
    //   32: aload_1
    //   33: aload_2
    //   34: bipush 26
    //   36: aload_3
    //   37: aload 4
    //   39: invokestatic 111	o/Mu:ॱ	(Lo/ˉ;Landroid/view/View;ILandroid/databinding/ViewDataBinding$If;Landroid/util/SparseIntArray;)[Ljava/lang/Object;
    //   42: astore_1
    //   43: aload_0
    //   44: aload_1
    //   45: bipush 23
    //   47: aaload
    //   48: checkcast 113	android/view/View
    //   51: putfield 115	o/Mu:ˊ	Landroid/view/View;
    //   54: aload_0
    //   55: aload_1
    //   56: bipush 24
    //   58: aaload
    //   59: checkcast 113	android/view/View
    //   62: putfield 117	o/Mu:ॱ	Landroid/view/View;
    //   65: aload_0
    //   66: aload_1
    //   67: iconst_4
    //   68: aaload
    //   69: checkcast 119	android/widget/LinearLayout
    //   72: putfield 121	o/Mu:ˎ	Landroid/widget/LinearLayout;
    //   75: aload_0
    //   76: getfield 121	o/Mu:ˎ	Landroid/widget/LinearLayout;
    //   79: aconst_null
    //   80: invokevirtual 125	android/widget/LinearLayout:setTag	(Ljava/lang/Object;)V
    //   83: aload_0
    //   84: aload_1
    //   85: bipush 19
    //   87: aaload
    //   88: checkcast 127	android/widget/Button
    //   91: putfield 129	o/Mu:ॱॱ	Landroid/widget/Button;
    //   94: aload_0
    //   95: getfield 129	o/Mu:ॱॱ	Landroid/widget/Button;
    //   98: aconst_null
    //   99: invokevirtual 130	android/widget/Button:setTag	(Ljava/lang/Object;)V
    //   102: aload_0
    //   103: aload_1
    //   104: bipush 25
    //   106: aaload
    //   107: checkcast 132	android/widget/FrameLayout
    //   110: putfield 134	o/Mu:ʻ	Landroid/widget/FrameLayout;
    //   113: aload_0
    //   114: aload_1
    //   115: iconst_5
    //   116: aaload
    //   117: checkcast 136	android/widget/TextView
    //   120: putfield 138	o/Mu:ʽ	Landroid/widget/TextView;
    //   123: aload_0
    //   124: getfield 138	o/Mu:ʽ	Landroid/widget/TextView;
    //   127: aconst_null
    //   128: invokevirtual 139	android/widget/TextView:setTag	(Ljava/lang/Object;)V
    //   131: aload_0
    //   132: aload_1
    //   133: bipush 8
    //   135: aaload
    //   136: checkcast 141	o/ME
    //   139: putfield 143	o/Mu:ᐝ	Lo/ME;
    //   142: aload_0
    //   143: getfield 143	o/Mu:ᐝ	Lo/ME;
    //   146: aconst_null
    //   147: invokevirtual 144	o/ME:setTag	(Ljava/lang/Object;)V
    //   150: aload_0
    //   151: aload_1
    //   152: iconst_3
    //   153: aaload
    //   154: checkcast 146	android/widget/ImageView
    //   157: putfield 148	o/Mu:ʼ	Landroid/widget/ImageView;
    //   160: aload_0
    //   161: getfield 148	o/Mu:ʼ	Landroid/widget/ImageView;
    //   164: aconst_null
    //   165: invokevirtual 149	android/widget/ImageView:setTag	(Ljava/lang/Object;)V
    //   168: aload_0
    //   169: aload_1
    //   170: iconst_0
    //   171: aaload
    //   172: checkcast 151	android/widget/RelativeLayout
    //   175: putfield 153	o/Mu:ʾ	Landroid/widget/RelativeLayout;
    //   178: aload_0
    //   179: getfield 153	o/Mu:ʾ	Landroid/widget/RelativeLayout;
    //   182: aconst_null
    //   183: invokevirtual 154	android/widget/RelativeLayout:setTag	(Ljava/lang/Object;)V
    //   186: aload_0
    //   187: aload_1
    //   188: bipush 11
    //   190: aaload
    //   191: checkcast 136	android/widget/TextView
    //   194: putfield 156	o/Mu:ˋˊ	Landroid/widget/TextView;
    //   197: aload_0
    //   198: getfield 156	o/Mu:ˋˊ	Landroid/widget/TextView;
    //   201: aconst_null
    //   202: invokevirtual 139	android/widget/TextView:setTag	(Ljava/lang/Object;)V
    //   205: aload_0
    //   206: aload_1
    //   207: bipush 14
    //   209: aaload
    //   210: checkcast 136	android/widget/TextView
    //   213: putfield 158	o/Mu:ˊᐝ	Landroid/widget/TextView;
    //   216: aload_0
    //   217: getfield 158	o/Mu:ˊᐝ	Landroid/widget/TextView;
    //   220: aconst_null
    //   221: invokevirtual 139	android/widget/TextView:setTag	(Ljava/lang/Object;)V
    //   224: aload_0
    //   225: aload_1
    //   226: iconst_2
    //   227: aaload
    //   228: checkcast 146	android/widget/ImageView
    //   231: putfield 160	o/Mu:ˊˊ	Landroid/widget/ImageView;
    //   234: aload_0
    //   235: getfield 160	o/Mu:ˊˊ	Landroid/widget/ImageView;
    //   238: aconst_null
    //   239: invokevirtual 149	android/widget/ImageView:setTag	(Ljava/lang/Object;)V
    //   242: aload_0
    //   243: aload_1
    //   244: bipush 7
    //   246: aaload
    //   247: checkcast 119	android/widget/LinearLayout
    //   250: putfield 162	o/Mu:ˊˋ	Landroid/widget/LinearLayout;
    //   253: aload_0
    //   254: getfield 162	o/Mu:ˊˋ	Landroid/widget/LinearLayout;
    //   257: aconst_null
    //   258: invokevirtual 125	android/widget/LinearLayout:setTag	(Ljava/lang/Object;)V
    //   261: aload_0
    //   262: aload_1
    //   263: bipush 9
    //   265: aaload
    //   266: checkcast 136	android/widget/TextView
    //   269: putfield 164	o/Mu:ˉ	Landroid/widget/TextView;
    //   272: aload_0
    //   273: getfield 164	o/Mu:ˉ	Landroid/widget/TextView;
    //   276: aconst_null
    //   277: invokevirtual 139	android/widget/TextView:setTag	(Ljava/lang/Object;)V
    //   280: aload_0
    //   281: aload_1
    //   282: bipush 13
    //   284: aaload
    //   285: checkcast 119	android/widget/LinearLayout
    //   288: putfield 166	o/Mu:ˊॱ	Landroid/widget/LinearLayout;
    //   291: aload_0
    //   292: getfield 166	o/Mu:ˊॱ	Landroid/widget/LinearLayout;
    //   295: aconst_null
    //   296: invokevirtual 125	android/widget/LinearLayout:setTag	(Ljava/lang/Object;)V
    //   299: aload_0
    //   300: aload_1
    //   301: bipush 20
    //   303: aaload
    //   304: checkcast 168	android/widget/ScrollView
    //   307: putfield 170	o/Mu:ͺ	Landroid/widget/ScrollView;
    //   310: aload_0
    //   311: aload_1
    //   312: bipush 22
    //   314: aaload
    //   315: checkcast 172	android/widget/ProgressBar
    //   318: putfield 174	o/Mu:ॱˊ	Landroid/widget/ProgressBar;
    //   321: aload_0
    //   322: aload_1
    //   323: bipush 6
    //   325: aaload
    //   326: checkcast 136	android/widget/TextView
    //   329: putfield 176	o/Mu:ˏॱ	Landroid/widget/TextView;
    //   332: aload_0
    //   333: getfield 176	o/Mu:ˏॱ	Landroid/widget/TextView;
    //   336: aconst_null
    //   337: invokevirtual 139	android/widget/TextView:setTag	(Ljava/lang/Object;)V
    //   340: aload_0
    //   341: aload_1
    //   342: bipush 10
    //   344: aaload
    //   345: checkcast 141	o/ME
    //   348: putfield 178	o/Mu:ˋॱ	Lo/ME;
    //   351: aload_0
    //   352: getfield 178	o/Mu:ˋॱ	Lo/ME;
    //   355: aconst_null
    //   356: invokevirtual 144	o/ME:setTag	(Ljava/lang/Object;)V
    //   359: aload_0
    //   360: aload_1
    //   361: iconst_1
    //   362: aaload
    //   363: checkcast 180	o/у
    //   366: putfield 182	o/Mu:ʻॱ	Lo/у;
    //   369: aload_0
    //   370: getfield 182	o/Mu:ʻॱ	Lo/у;
    //   373: aconst_null
    //   374: invokevirtual 183	o/у:setTag	(Ljava/lang/Object;)V
    //   377: aload_0
    //   378: aload_1
    //   379: bipush 15
    //   381: aaload
    //   382: checkcast 119	android/widget/LinearLayout
    //   385: putfield 185	o/Mu:ॱˎ	Landroid/widget/LinearLayout;
    //   388: aload_0
    //   389: getfield 185	o/Mu:ॱˎ	Landroid/widget/LinearLayout;
    //   392: aconst_null
    //   393: invokevirtual 125	android/widget/LinearLayout:setTag	(Ljava/lang/Object;)V
    //   396: aload_0
    //   397: aload_1
    //   398: bipush 17
    //   400: aaload
    //   401: checkcast 187	o/Je
    //   404: putfield 189	o/Mu:ॱᐝ	Lo/Je;
    //   407: aload_0
    //   408: getfield 189	o/Mu:ॱᐝ	Lo/Je;
    //   411: aconst_null
    //   412: invokevirtual 190	o/Je:setTag	(Ljava/lang/Object;)V
    //   415: aload_0
    //   416: aload_1
    //   417: bipush 12
    //   419: aaload
    //   420: checkcast 192	o/Ꭸ
    //   423: putfield 194	o/Mu:ॱˋ	Lo/Ꭸ;
    //   426: aload_0
    //   427: getfield 194	o/Mu:ॱˋ	Lo/Ꭸ;
    //   430: aconst_null
    //   431: invokevirtual 195	o/Ꭸ:setTag	(Ljava/lang/Object;)V
    //   434: aload_0
    //   435: aload_1
    //   436: bipush 16
    //   438: aaload
    //   439: checkcast 187	o/Je
    //   442: putfield 197	o/Mu:ᐝॱ	Lo/Je;
    //   445: aload_0
    //   446: getfield 197	o/Mu:ᐝॱ	Lo/Je;
    //   449: aconst_null
    //   450: invokevirtual 190	o/Je:setTag	(Ljava/lang/Object;)V
    //   453: aload_0
    //   454: aload_1
    //   455: bipush 18
    //   457: aaload
    //   458: checkcast 187	o/Je
    //   461: putfield 199	o/Mu:ʿ	Lo/Je;
    //   464: aload_0
    //   465: getfield 199	o/Mu:ʿ	Lo/Je;
    //   468: aconst_null
    //   469: invokevirtual 190	o/Je:setTag	(Ljava/lang/Object;)V
    //   472: aload_0
    //   473: aload_1
    //   474: bipush 21
    //   476: aaload
    //   477: checkcast 146	android/widget/ImageView
    //   480: putfield 201	o/Mu:ʽॱ	Landroid/widget/ImageView;
    //   483: aload_0
    //   484: aload_2
    //   485: invokevirtual 205	o/Mu:ˋ	(Landroid/view/View;)V
    //   488: aload_0
    //   489: invokevirtual 207	o/Mu:ˊॱ	()V
    //   492: return
    // Local variable table:
    //   start	length	slot	name	signature
    //   0	493	0	this	Mu
    //   0	493	1	paramˉ	ˉ
    //   0	493	2	paramView	View
    //   26	11	3	localIf	ViewDataBinding.If
    //   30	8	4	localSparseIntArray	SparseIntArray
    // Exception table:
    //   from	to	target	type
    //   16	23	3	java/lang/Exception
    //   16	23	6	java/lang/Exception
    //   23	27	6	java/lang/Exception
    //   27	32	6	java/lang/Exception
    //   32	43	6	java/lang/Exception
    //   43	492	6	java/lang/Exception
  }
  
  private boolean ˋ(coN paramCoN, int paramInt)
  {
    if (paramInt == 0)
    {
      try
      {
        this.ˏˎ |= 0x8;
      }
      finally
      {
        paramCoN = finally;
        throw paramCoN;
      }
      return true;
    }
    return false;
  }
  
  static void ˋॱ()
  {
    ॱʽ = '\000';
    ˏˏ = 3920415434461654566L;
    ˎˏ = 0;
  }
  
  private static String ˎ(char[] paramArrayOfChar1, char paramChar, char[] paramArrayOfChar2, int paramInt, char[] paramArrayOfChar3)
  {
    break label250;
    oJ.ˏ(paramArrayOfChar1, paramArrayOfChar3, paramChar);
    char[] arrayOfChar;
    arrayOfChar[paramChar] = ((char)(int)(paramArrayOfChar2[paramChar] ^ paramArrayOfChar1[((paramChar + '\003') % 4)] ^ ˏˏ ^ ˎˏ ^ ॱʽ));
    paramChar += '\001';
    break label143;
    paramInt = 57;
    break label174;
    label55:
    char c;
    if (paramChar >= c) {
      break label169;
    }
    for (;;)
    {
      break label55;
      for (;;)
      {
        switch (paramInt)
        {
        case 0: 
        default: 
          paramInt = ـ + 59;
          ॱʻ = paramInt % 128;
          if (paramInt % 2 != 0) {
            break label137;
          }
          break;
          break;
        case 1: 
          label119:
          return new String(arrayOfChar);
          paramInt = 0;
        }
      }
      label137:
      paramInt = 79;
      for (;;)
      {
        label143:
        paramInt = ـ + 1;
        ॱʻ = paramInt % 128;
        if (paramInt % 2 != 0) {
          break label119;
        }
        break label247;
        label169:
        paramInt = 1;
        break;
        label174:
        switch (paramInt)
        {
        }
        oJ.ˏ(paramArrayOfChar1, paramArrayOfChar3, paramChar);
        arrayOfChar[paramChar] = ((char)(int)((paramArrayOfChar2[paramChar] & paramArrayOfChar1[((paramChar + '\003') % 3)]) + ˏˏ + ˎˏ & ॱʽ));
        paramChar += 'u';
      }
      label247:
      break label55;
      label250:
      paramArrayOfChar1 = (char[])paramArrayOfChar1.clone();
      paramArrayOfChar3 = (char[])paramArrayOfChar3.clone();
      paramArrayOfChar1[0] = ((char)(paramArrayOfChar1[0] ^ paramChar));
      paramArrayOfChar3[2] = ((char)(paramArrayOfChar3[2] + (char)paramInt));
      c = paramArrayOfChar2.length;
      arrayOfChar = new char[c];
      paramChar = '\000';
    }
  }
  
  private boolean ˎ(cON paramCON, int paramInt)
  {
    if (paramInt == 0)
    {
      try
      {
        this.ˏˎ |= 0x2;
      }
      finally
      {
        paramCON = finally;
        throw paramCON;
      }
      return true;
    }
    return false;
  }
  
  static void ˏॱ()
  {
    for (;;)
    {
      i = 66;
      break label40;
      break;
      try
      {
        i = ॱʻ + 11;
        try
        {
          ـ = i % 128;
          if (i % 2 == 0) {
            break label115;
          }
        }
        catch (Exception localException1)
        {
          throw localException1;
        }
        return;
      }
      catch (Exception localException2)
      {
        label40:
        throw localException2;
      }
    }
    switch (i)
    {
    case 66: 
    default: 
      break;
    }
    int i = 87 / 0;
    return;
    i = ॱʻ + 39;
    ـ = i % 128;
    if (i % 2 != 0) {}
    for (;;)
    {
      ͺॱ = -102;
      break;
      label115:
      i = 27;
      break label40;
    }
  }
  
  private String ॱ(String paramString)
  {
    for (;;)
    {
      byte[] arrayOfByte;
      int i;
      int j;
      try
      {
        arrayOfByte[i] = ((byte)(paramString[(paramString.length - i - 1)] ^ ͺॱ));
        i += 1;
        continue;
        j = 61;
        continue;
        j = 87;
        continue;
        j = ॱʻ + 13;
        ـ = j % 128;
        if (j % 2 == 0) {
          continue;
        }
        continue;
        j = ॱʻ + 89;
        ـ = j % 128;
        if (j % 2 == 0) {
          break label195;
        }
        break label309;
        j = 68;
        break label166;
        switch (j)
        {
        case 87: 
        default: 
          break;
        case 61: 
          arrayOfByte[i] = ((byte)(paramString[(paramString.length >> i << 1)] ^ ͺॱ));
        }
      }
      catch (UnsupportedEncodingException paramString)
      {
        throw new RuntimeException(paramString);
      }
      i += 6;
      continue;
      switch (j)
      {
      case 7: 
      default: 
        label166:
        label195:
        break;
      }
      label309:
      label461:
      do
      {
        j = 7;
        break;
        paramString = new String(arrayOfByte, ˎ(new char[] { -3047, 23491, -4092, 14935 }, '埰', new char[] { 292, 28840, 18111, 26704, -12641 }, 73122804, new char[] { -20954, -245, 7440, 13928 }).intern());
        return paramString;
        break label461;
        for (;;)
        {
          paramString = paramString.getBytes(ˎ(new char[] { 31365, -2968, 32570, -1499 }, '\000', new char[] { 16943, -27422, 3378, 25981, -15016, -3676, 27604, 15727, 19714, -9862 }, 0, new char[] { -20954, -245, 7440, 13928 }).intern());
          arrayOfByte = new byte[paramString.length];
          i = 0;
          break;
        }
        j = paramString.length;
      } while (i < j);
    }
  }
  
  private boolean ॱ(cON paramCON, int paramInt)
  {
    if (paramInt == 0)
    {
      try
      {
        this.ˏˎ |= 1L;
      }
      finally
      {
        paramCON = finally;
        throw paramCON;
      }
      return true;
    }
    return false;
  }
  
  private boolean ॱ(ـ<String> paramـ, int paramInt)
  {
    if (paramInt == 0)
    {
      try
      {
        this.ˏˎ |= 0x4;
      }
      finally
      {
        paramـ = finally;
        throw paramـ;
      }
      return true;
    }
    return false;
  }
  
  public void ˊ(Gh paramGh)
  {
    this.ˌ = paramGh;
    try
    {
      this.ˏˎ |= 0x10;
    }
    finally
    {
      paramGh = finally;
      throw paramGh;
    }
    ˊ(129);
    super.ʽ();
  }
  
  public void ˊ(HQ paramHQ)
  {
    this.ˋᐝ = paramHQ;
    try
    {
      this.ˏˎ |= 0x40;
    }
    finally
    {
      paramHQ = finally;
      throw paramHQ;
    }
    ˊ(43);
    super.ʽ();
  }
  
  public void ˊ(boolean paramBoolean)
  {
    this.ˎˎ = paramBoolean;
    try
    {
      this.ˏˎ |= 0x20;
    }
    finally
    {
      localObject = finally;
      throw localObject;
    }
    ˊ(61);
    super.ʽ();
  }
  
  public void ˊॱ()
  {
    try
    {
      this.ˏˎ = 512L;
    }
    finally
    {
      localObject = finally;
      throw localObject;
    }
    ʽ();
  }
  
  public void ˋ(coN paramCoN)
  {
    ˎ(3, paramCoN);
    this.ˑ = paramCoN;
    try
    {
      this.ˏˎ |= 0x8;
    }
    finally
    {
      paramCoN = finally;
      throw paramCoN;
    }
    ˊ(86);
    super.ʽ();
  }
  
  public void ˏ()
  {
    String str2 = ˎ(new char[] { -8972, -14824, -10914, -2047 }, 'Ǖ', new char[] { 29984, -32710, -32067, 10125 }, 0, new char[] { -20954, -245, 7440, 13928 }).intern();
    try
    {
      l2 = this.ˏˎ;
      this.ˏˎ = 0L;
    }
    finally
    {
      localObject1 = finally;
      throw localObject1;
    }
    float f2 = 0.0F;
    float f1 = 0.0F;
    boolean bool6 = false;
    Object localObject8 = null;
    Object localObject16 = null;
    int i5 = 0;
    int i7 = 0;
    Object localObject10 = null;
    boolean bool4 = false;
    double d1 = 0.0D;
    int i6 = 0;
    Object localObject14 = null;
    int i1 = 0;
    int i10 = 0;
    boolean bool3 = false;
    Gh localGh = this.ˌ;
    int i15 = 0;
    Object localObject13 = null;
    int i12 = 0;
    int i3 = 0;
    int j = 0;
    int i9 = 0;
    Object localObject11 = null;
    boolean bool7 = this.ˎˎ;
    int i11 = 0;
    HQ localHQ1 = this.ˋᐝ;
    Object localObject9 = null;
    HQ localHQ2 = this.ˋˋ;
    int i17 = 0;
    Object localObject12 = null;
    Object localObject6 = null;
    Object localObject4 = null;
    Object localObject3 = null;
    boolean bool1 = false;
    int n = 0;
    int i2 = 0;
    String str1 = null;
    double d2 = 0.0D;
    int i13 = 0;
    Object localObject7 = null;
    Object localObject15 = null;
    int i4 = 0;
    int k = 0;
    boolean bool2 = false;
    boolean bool8 = this.ˍ;
    coN localCoN = this.ˑ;
    int i14 = 0;
    boolean bool5 = false;
    int i8 = 0;
    int i16 = 0;
    long l1 = l2;
    Object localObject5 = localObject12;
    Object localObject2;
    if ((0x217 & l2) != 0L)
    {
      l3 = l2;
      localObject2 = localObject16;
      if ((0x210 & l2) != 0L)
      {
        if (localGh == null) {
          j = 1;
        } else {
          j = 0;
        }
        l1 = l2;
        if ((0x210 & l2) != 0L) {
          if (j != 0) {
            l1 = l2 | 0x800 | 0x800000 | 0x8000000000;
          } else {
            l1 = l2 | 0x400 | 0x400000 | 0x4000000000;
          }
        }
        if (localGh != null) {
          localObject3 = localGh.currency;
        }
        if (j != 0) {
          f2 = this.ॱˋ.getResources().getDimension(2131165260);
        } else {
          f2 = this.ॱˋ.getResources().getDimension(2131165259);
        }
        if (j != 0) {
          i = ˋ(this.ॱˋ, 17170445);
        } else {
          i = ˋ(this.ॱˋ, 2131099797);
        }
        if (j != 0) {
          m = 4;
        } else {
          m = 0;
        }
        l3 = l1;
        f1 = f2;
        localObject2 = localObject16;
        j = i;
        k = m;
        if (localObject3 != null)
        {
          localObject2 = ((Ep)localObject3).ˊ();
          k = m;
          j = i;
          f1 = f2;
          l3 = l1;
        }
      }
      localObject3 = localObject15;
      if ((0x211 & l3) != 0L)
      {
        localObject3 = localObject14;
        if (localGh != null) {
          localObject3 = localGh.commission;
        }
        ˎ(0, (ˑ)localObject3);
        if (localObject3 != null) {
          d1 = ((cON)localObject3).ˏ();
        }
        localObject3 = at.ˎ(d1);
      }
      if ((0x212 & l3) != 0L)
      {
        localObject4 = localObject13;
        if (localGh != null) {
          localObject4 = localGh.totalAmount;
        }
        ˎ(1, (ˑ)localObject4);
        d1 = d2;
        if (localObject4 != null) {
          d1 = ((cON)localObject4).ˏ();
        }
        localObject4 = at.ˎ(d1);
      }
      l1 = l3;
      f2 = f1;
      localObject8 = localObject2;
      i3 = j;
      localObject5 = localObject12;
      localObject6 = localObject4;
      localObject7 = localObject3;
      i4 = k;
      if ((0x214 & l3) != 0L)
      {
        localObject5 = localObject11;
        if (localGh != null) {
          localObject5 = localGh.transferDetail;
        }
        ˎ(2, (ˑ)localObject5);
        localObject6 = localObject10;
        if (localObject5 != null) {
          localObject6 = (String)((ـ)localObject5).ˏ();
        }
        localObject5 = aq.ॱ((String)localObject6);
        i4 = k;
        localObject7 = localObject3;
        localObject6 = localObject4;
        i3 = j;
        localObject8 = localObject2;
        f2 = f1;
        l1 = l3;
      }
    }
    long l2 = l1;
    j = i17;
    int i = i2;
    if ((0x240 & l1) != 0L)
    {
      if (localHQ1 == null) {
        j = 1;
      } else {
        j = 0;
      }
      if (localHQ1 != null) {
        i = 1;
      } else {
        i = 0;
      }
      l2 = l1;
      if ((0x240 & l1) != 0L) {
        if (j != 0) {
          l2 = l1 | 0x20000;
        } else {
          l2 = l1 | 0x10000;
        }
      }
      l1 = l2;
      if ((0x240 & l2) != 0L) {
        if (i != 0) {
          l1 = l2 | 0x2000 | 0x80000000;
        } else {
          l1 = l2 | 0x1000 | 0x40000000;
        }
      }
      if (j != 0) {
        k = 0;
      } else {
        k = 8;
      }
      if (i != 0) {
        m = 0;
      } else {
        m = 4;
      }
      if (i != 0)
      {
        j = 0;
        l2 = l1;
        i5 = m;
        i6 = k;
      }
      else
      {
        j = 8;
        i6 = k;
        i5 = m;
        l2 = l1;
      }
    }
    long l3 = l2;
    int m = i1;
    k = n;
    if ((0x280 & l2) != 0L)
    {
      if (localHQ2 != null) {
        m = 1;
      } else {
        m = 0;
      }
      if (localHQ2 == null) {
        k = 1;
      } else {
        k = 0;
      }
      l1 = l2;
      if ((0x280 & l2) != 0L) {
        if (m != 0) {
          l1 = l2 | 0x8000 | 0x200000000000;
        } else {
          l1 = l2 | 0x4000 | 0x100000000000;
        }
      }
      l3 = l1;
      if ((0x280 & l1) != 0L) {
        if (k != 0) {
          l3 = l1 | 0x200000000;
        } else {
          l3 = l1 | 0x100000000;
        }
      }
      if (m != 0) {
        n = 0;
      } else {
        n = 4;
      }
      if (m != 0) {
        i1 = 0;
      } else {
        i1 = 8;
      }
      if (k != 0)
      {
        k = 0;
        i7 = n;
        i8 = i1;
      }
      else
      {
        k = 8;
        i8 = i1;
        i7 = n;
      }
    }
    l1 = l3;
    localObject4 = localObject9;
    localObject3 = str1;
    if ((0x300 & l3) != 0L)
    {
      l2 = l3;
      if ((0x300 & l3) != 0L) {
        if (bool8) {
          l2 = l3 | 0x2000000 | 0x20000000 | 0x800000000;
        } else {
          l2 = l3 | 0x1000000 | 0x10000000 | 0x400000000;
        }
      }
      if (bool8) {
        n = 8;
      } else {
        n = 0;
      }
      if (bool8)
      {
        localObject3 = this.ʻॱ.getResources().getString(2131755604);
        localObject2 = localObject3;
        if (((String)localObject3).startsWith(str2)) {
          localObject2 = ॱ(((String)localObject3).substring(4)).intern();
        }
      }
      else
      {
        localObject3 = this.ʻॱ.getResources().getString(2131755577);
        localObject2 = localObject3;
        if (((String)localObject3).startsWith(str2)) {
          localObject2 = ॱ(((String)localObject3).substring(4)).intern();
        }
      }
      if (bool8)
      {
        localObject4 = this.ॱॱ.getResources().getString(2131755475);
        localObject3 = localObject4;
        if (((String)localObject4).startsWith(str2)) {
          localObject3 = ॱ(((String)localObject4).substring(4)).intern();
        }
        l1 = l2;
        i9 = n;
        localObject4 = localObject2;
      }
      else
      {
        str1 = this.ॱॱ.getResources().getString(2131755444);
        l1 = l2;
        i9 = n;
        localObject4 = localObject2;
        localObject3 = str1;
        if (str1.startsWith(str2))
        {
          localObject3 = ॱ(str1.substring(4)).intern();
          localObject4 = localObject2;
          i9 = n;
          l1 = l2;
        }
      }
    }
    l2 = l1;
    i2 = i15;
    n = i16;
    if ((0x2E8 & l1) != 0L)
    {
      if (localCoN != null) {
        bool1 = localCoN.ˊ();
      }
      l2 = l1;
      if ((0x208 & l1) != 0L) {
        if (bool1) {
          l2 = l1 | 0x200000 | 0x800000000000;
        } else {
          l2 = l1 | 0x100000 | 0x400000000000;
        }
      }
      if (!bool1) {
        i1 = 1;
      } else {
        i1 = 0;
      }
      l1 = l2;
      if ((0x2E8 & l2) != 0L) {
        if (i1 != 0) {
          l1 = l2 | 0x20000000000;
        } else {
          l1 = l2 | 0x10000000000;
        }
      }
      l2 = l1;
      i10 = i1;
      i2 = i15;
      n = i16;
      if ((0x208 & l1) != 0L)
      {
        if (bool1) {
          i2 = 0;
        } else {
          i2 = 8;
        }
        if (bool1)
        {
          n = 4;
          l2 = l1;
          i10 = i1;
        }
        else
        {
          n = 0;
          i10 = i1;
          l2 = l1;
        }
      }
    }
    l1 = l2;
    if ((0x2E8 & l2) != 0L)
    {
      if (i10 != 0) {
        bool1 = bool7;
      } else {
        bool1 = false;
      }
      l1 = l2;
      bool2 = bool1;
      if ((0x2E8 & l2) != 0L) {
        if (bool1)
        {
          l1 = l2 | 0x80000000000;
          bool2 = bool1;
        }
        else
        {
          l1 = l2 | 0x40000000000;
          bool2 = bool1;
        }
      }
    }
    l2 = l1;
    if ((0x80000000000 & l1) != 0L)
    {
      if (localHQ1 != null) {
        i1 = 1;
      } else {
        i1 = 0;
      }
      l2 = l1;
      i = i1;
      if ((0x240 & l1) != 0L) {
        if (i1 != 0)
        {
          l2 = l1 | 0x2000 | 0x80000000;
          i = i1;
        }
        else
        {
          l2 = l1 | 0x1000 | 0x40000000;
          i = i1;
        }
      }
    }
    l1 = l2;
    i1 = i14;
    if ((0x2E8 & l2) != 0L)
    {
      if (!bool2) {
        i = 0;
      }
      l1 = l2;
      i1 = i;
      if ((0x2E8 & l2) != 0L) {
        if (i != 0)
        {
          l1 = l2 | 0x2000000000;
          i1 = i;
        }
        else
        {
          l1 = l2 | 0x1000000000;
          i1 = i;
        }
      }
    }
    l2 = l1;
    if ((0x2000000000 & l1) != 0L)
    {
      if (localHQ2 != null) {
        i = 1;
      } else {
        i = 0;
      }
      l2 = l1;
      m = i;
      if ((0x280 & l1) != 0L) {
        if (i != 0)
        {
          l2 = l1 | 0x8000 | 0x200000000000;
          m = i;
        }
        else
        {
          l2 = l1 | 0x4000 | 0x100000000000;
          m = i;
        }
      }
    }
    l1 = l2;
    i10 = i13;
    if ((0x2E8 & l2) != 0L)
    {
      if (i1 != 0) {
        i = m;
      } else {
        i = 0;
      }
      l1 = l2;
      i10 = i;
      if ((0x2E8 & l2) != 0L) {
        if (i != 0)
        {
          l1 = l2 | 0x8000000;
          i10 = i;
        }
        else
        {
          l1 = l2 | 0x4000000;
          i10 = i;
        }
      }
    }
    i = i12;
    if ((0x8000000 & l1) != 0L)
    {
      bool1 = bool6;
      if (localHQ1 != null) {
        bool1 = localHQ1.ˊᐝ();
      }
      if (!bool1) {
        i = 1;
      } else {
        i = 0;
      }
    }
    l2 = l1;
    m = i11;
    if ((0x2E8 & l1) != 0L)
    {
      if (i10 == 0) {
        i = 0;
      }
      l2 = l1;
      m = i;
      if ((0x2E8 & l1) != 0L) {
        if (i != 0)
        {
          l2 = l1 | 0x80000;
          m = i;
        }
        else
        {
          l2 = l1 | 0x40000;
          m = i;
        }
      }
    }
    bool1 = bool5;
    if ((0x80000 & l2) != 0L)
    {
      bool1 = bool4;
      if (localHQ2 != null) {
        bool1 = localHQ2.ˊᐝ();
      }
      if (!bool1) {
        bool1 = true;
      } else {
        bool1 = false;
      }
    }
    bool2 = bool3;
    if ((0x2E8 & l2) != 0L) {
      if (m != 0) {
        bool2 = bool1;
      } else {
        bool2 = false;
      }
    }
    if ((0x210 & l2) != 0L)
    {
      this.ˎ.setVisibility(i4);
      this.ॱॱ.setVisibility(i4);
      this.ˊˋ.setVisibility(i4);
      this.ॱᐝ.setValueInfo(localObject8);
      this.ॱˋ.setCardBackgroundColor(i3);
      this.ॱˋ.setCardElevation(f2);
      this.ʿ.setValueInfo(localObject8);
    }
    if ((0x2E8 & l2) != 0L) {
      this.ॱॱ.setEnabled(bool2);
    }
    if ((0x300 & l2) != 0L)
    {
      ʹ.ˊ(this.ॱॱ, (CharSequence)localObject3);
      this.ˊˊ.setVisibility(i9);
      this.ʻॱ.setTitle((CharSequence)localObject4);
    }
    if ((0x200 & l2) != 0L)
    {
      localObject4 = this.ʽ;
      localObject3 = this.ʽ.getResources().getString(2131755608);
      localObject2 = localObject3;
      if (((String)localObject3).startsWith(str2)) {
        localObject2 = ॱ(((String)localObject3).substring(4)).intern();
      }
      ʹ.ˊ((TextView)localObject4, (CharSequence)localObject2);
      r.ˊ(this.ʼ, ˎ(new char[] { 7286, -10129, -31803, -27520 }, '\000', new char[] { -23272, 24272, -16938, -27460, 28194, -28285, -16959, -865, -422, 8884, -30236, 8772, 17657, -11001, 7652, 6850, -11020, -27012, -1330, 16267, -10999, 20259, -14078, 31481, -28450, -5104, -405, 8873, 14499, -19968, 28999, 21658, 24665, 1071, -23874, -18875, 14477, -13633, -31983, 29134, 15542, -23172, -14363, -26402, 26883, 30170, -10435, -31697, -29804, -14014, -26879, -15996, 12889, -11510, 15279, 17175, -11794, -265, -537, -19942, 29311, -17035, -31894, 9891, 28724, -27035, 14677, 13941, -16124, 6250, 7181, -27742, -19451, -26266, 19102, -27664, 22449 }, -975671524, new char[] { -20954, -245, 7440, 13928 }).intern(), ॱ(this.ʼ, 2131230823), true);
      localObject4 = this.ˋˊ;
      localObject3 = this.ˋˊ.getResources().getString(2131755578);
      localObject2 = localObject3;
      if (((String)localObject3).startsWith(str2)) {
        localObject2 = ॱ(((String)localObject3).substring(4)).intern();
      }
      ʹ.ˊ((TextView)localObject4, (CharSequence)localObject2);
      localObject4 = this.ˊᐝ;
      localObject3 = this.ˊᐝ.getResources().getString(2131755246);
      localObject2 = localObject3;
      if (((String)localObject3).startsWith(str2)) {
        localObject2 = ॱ(((String)localObject3).substring(4)).intern();
      }
      ʹ.ˊ((TextView)localObject4, (CharSequence)localObject2);
      localObject4 = this.ˉ;
      localObject3 = this.ˉ.getResources().getString(2131755578);
      localObject2 = localObject3;
      if (((String)localObject3).startsWith(str2)) {
        localObject2 = ॱ(((String)localObject3).substring(4)).intern();
      }
      ʹ.ˊ((TextView)localObject4, (CharSequence)localObject2);
      localObject4 = this.ˏॱ;
      localObject3 = this.ˏॱ.getResources().getString(2131755600);
      localObject2 = localObject3;
      if (((String)localObject3).startsWith(str2)) {
        localObject2 = ॱ(((String)localObject3).substring(4)).intern();
      }
      ʹ.ˊ((TextView)localObject4, (CharSequence)localObject2);
      A.ॱ(this.ʻॱ, true);
      localObject4 = this.ॱᐝ;
      localObject3 = this.ॱᐝ.getResources().getString(2131755602);
      localObject2 = localObject3;
      if (((String)localObject3).startsWith(str2)) {
        localObject2 = ॱ(((String)localObject3).substring(4)).intern();
      }
      ((Je)localObject4).setLabel((String)localObject2);
      localObject4 = this.ᐝॱ;
      localObject3 = this.ᐝॱ.getResources().getString(2131755603);
      localObject2 = localObject3;
      if (((String)localObject3).startsWith(str2)) {
        localObject2 = ॱ(((String)localObject3).substring(4)).intern();
      }
      ((Je)localObject4).setLabel((String)localObject2);
      localObject4 = this.ʿ;
      localObject3 = this.ʿ.getResources().getString(2131755601);
      localObject2 = localObject3;
      if (((String)localObject3).startsWith(str2)) {
        localObject2 = ॱ(((String)localObject3).substring(4)).intern();
      }
      ((Je)localObject4).setLabel((String)localObject2);
    }
    if ((0x240 & l2) != 0L)
    {
      this.ʽ.setVisibility(i5);
      this.ᐝ.setVisibility(j);
      this.ᐝ.setCard(localHQ1);
      this.ˉ.setVisibility(i6);
    }
    if ((0x280 & l2) != 0L)
    {
      this.ˋˊ.setVisibility(k);
      this.ˏॱ.setVisibility(i7);
      this.ˋॱ.setVisibility(i8);
      this.ˋॱ.setCard(localHQ2);
    }
    if ((0x208 & l2) != 0L)
    {
      this.ˊॱ.setVisibility(i2);
      this.ॱˎ.setVisibility(n);
    }
    if ((0x211 & l2) != 0L) {
      this.ॱᐝ.setValue(localObject7);
    }
    if ((0x214 & l2) != 0L) {
      this.ᐝॱ.setValue((String)localObject5);
    }
    if ((0x212 & l2) != 0L) {
      this.ʿ.setValue((String)localObject6);
    }
  }
  
  public void ˏ(HQ paramHQ)
  {
    this.ˋˋ = paramHQ;
    try
    {
      this.ˏˎ |= 0x80;
    }
    finally
    {
      paramHQ = finally;
      throw paramHQ;
    }
    ˊ(125);
    super.ʽ();
  }
  
  /* Error */
  public boolean ˏ(int paramInt1, Object paramObject, int paramInt2)
  {
    // Byte code:
    //   0: goto +237 -> 237
    //   3: astore_2
    //   4: aload_2
    //   5: athrow
    //   6: aload_0
    //   7: aload_2
    //   8: checkcast 408	o/ـ
    //   11: iload_3
    //   12: invokespecial 664	o/Mu:ॱ	(Lo/ـ;I)Z
    //   15: istore 5
    //   17: iload 5
    //   19: ireturn
    //   20: iload 5
    //   22: ireturn
    //   23: bipush 45
    //   25: istore 4
    //   27: goto +116 -> 143
    //   30: getstatic 74	o/Mu:ـ	I
    //   33: bipush 39
    //   35: iadd
    //   36: istore_1
    //   37: iload_1
    //   38: sipush 128
    //   41: irem
    //   42: putstatic 72	o/Mu:ॱʻ	I
    //   45: iload_1
    //   46: iconst_2
    //   47: irem
    //   48: ifeq +6 -> 54
    //   51: goto +195 -> 246
    //   54: iload 5
    //   56: ireturn
    //   57: aconst_null
    //   58: arraylength
    //   59: istore 4
    //   61: iload_1
    //   62: tableswitch	default:+30->92, 0:+187->249, 1:+33->95, 2:+-56->6, 3:+201->263
    //   92: goto +13 -> 105
    //   95: aload_0
    //   96: aload_2
    //   97: checkcast 387	o/cON
    //   100: iload_3
    //   101: invokespecial 666	o/Mu:ˎ	(Lo/cON;I)Z
    //   104: ireturn
    //   105: iconst_0
    //   106: ireturn
    //   107: iload_1
    //   108: tableswitch	default:+32->140, 0:+141->249, 1:+-13->95, 2:+-102->6, 3:+155->263
    //   140: goto -35 -> 105
    //   143: iload 4
    //   145: lookupswitch	default:+27->172, 45:+-38->107, 93:+-88->57
    //   172: goto -65 -> 107
    //   175: getstatic 72	o/Mu:ॱʻ	I
    //   178: bipush 43
    //   180: iadd
    //   181: istore_1
    //   182: iload_1
    //   183: sipush 128
    //   186: irem
    //   187: putstatic 74	o/Mu:ـ	I
    //   190: iload_1
    //   191: iconst_2
    //   192: irem
    //   193: ifne +6 -> 199
    //   196: goto +36 -> 232
    //   199: goto +41 -> 240
    //   202: getstatic 74	o/Mu:ـ	I
    //   205: bipush 121
    //   207: iadd
    //   208: istore 4
    //   210: iload 4
    //   212: sipush 128
    //   215: irem
    //   216: putstatic 72	o/Mu:ॱʻ	I
    //   219: iload 4
    //   221: iconst_2
    //   222: irem
    //   223: ifeq +6 -> 229
    //   226: goto +92 -> 318
    //   229: goto -206 -> 23
    //   232: iconst_3
    //   233: istore_1
    //   234: goto +51 -> 285
    //   237: goto -35 -> 202
    //   240: bipush 43
    //   242: istore_1
    //   243: goto +42 -> 285
    //   246: iload 5
    //   248: ireturn
    //   249: aload_0
    //   250: aload_2
    //   251: checkcast 387	o/cON
    //   254: iload_3
    //   255: invokespecial 668	o/Mu:ॱ	(Lo/cON;I)Z
    //   258: istore 5
    //   260: goto -85 -> 175
    //   263: aload_0
    //   264: aload_2
    //   265: checkcast 478	o/coN
    //   268: iload_3
    //   269: invokespecial 670	o/Mu:ˋ	(Lo/coN;I)Z
    //   272: istore 5
    //   274: goto -244 -> 30
    //   277: bipush 42
    //   279: iconst_0
    //   280: idiv
    //   281: istore_1
    //   282: iload 5
    //   284: ireturn
    //   285: iload_1
    //   286: lookupswitch	default:+26->312, 3:+-9->277, 43:+-266->20
    //   312: goto -35 -> 277
    //   315: astore_2
    //   316: aload_2
    //   317: athrow
    //   318: bipush 93
    //   320: istore 4
    //   322: goto -179 -> 143
    // Local variable table:
    //   start	length	slot	name	signature
    //   0	325	0	this	Mu
    //   0	325	1	paramInt1	int
    //   0	325	2	paramObject	Object
    //   0	325	3	paramInt2	int
    //   25	296	4	i	int
    //   15	268	5	bool	boolean
    // Exception table:
    //   from	to	target	type
    //   30	37	3	java/lang/Exception
    //   37	45	3	java/lang/Exception
    //   6	17	315	java/lang/Exception
  }
  
  public void ॱ(boolean paramBoolean)
  {
    this.ˍ = paramBoolean;
    try
    {
      this.ˏˎ |= 0x100;
    }
    finally
    {
      localObject = finally;
      throw localObject;
    }
    ˊ(85);
    super.ʽ();
  }
  
  public boolean ॱ()
  {
    try
    {
      long l = this.ˏˎ;
      if (l != 0L) {
        return true;
      }
    }
    finally
    {
      localObject = finally;
      throw localObject;
    }
    return false;
  }
  
  /* Error */
  public Gh ॱˊ()
  {
    // Byte code:
    //   0: goto +124 -> 124
    //   3: aload_2
    //   4: areturn
    //   5: bipush 74
    //   7: iconst_0
    //   8: idiv
    //   9: istore_1
    //   10: aload_2
    //   11: areturn
    //   12: aload_0
    //   13: getfield 298	o/Mu:ˌ	Lo/Gh;
    //   16: astore_2
    //   17: goto +78 -> 95
    //   20: bipush 98
    //   22: istore_1
    //   23: goto +42 -> 65
    //   26: bipush 25
    //   28: istore_1
    //   29: goto +36 -> 65
    //   32: astore_2
    //   33: aload_2
    //   34: athrow
    //   35: goto -23 -> 12
    //   38: getstatic 74	o/Mu:ـ	I
    //   41: bipush 95
    //   43: iadd
    //   44: istore_1
    //   45: iload_1
    //   46: sipush 128
    //   49: irem
    //   50: putstatic 72	o/Mu:ॱʻ	I
    //   53: iload_1
    //   54: iconst_2
    //   55: irem
    //   56: ifeq +6 -> 62
    //   59: goto -24 -> 35
    //   62: goto -50 -> 12
    //   65: iload_1
    //   66: lookupswitch	default:+26->92, 25:+-63->3, 98:+-61->5
    //   92: goto -87 -> 5
    //   95: getstatic 74	o/Mu:ـ	I
    //   98: istore_1
    //   99: iload_1
    //   100: bipush 27
    //   102: iadd
    //   103: istore_1
    //   104: iload_1
    //   105: sipush 128
    //   108: irem
    //   109: putstatic 72	o/Mu:ॱʻ	I
    //   112: iload_1
    //   113: iconst_2
    //   114: irem
    //   115: ifeq +6 -> 121
    //   118: goto -98 -> 20
    //   121: goto -95 -> 26
    //   124: goto -86 -> 38
    //   127: astore_2
    //   128: aload_2
    //   129: athrow
    // Local variable table:
    //   start	length	slot	name	signature
    //   0	130	0	this	Mu
    //   9	106	1	i	int
    //   3	14	2	localGh	Gh
    //   32	2	2	localException1	Exception
    //   127	2	2	localException2	Exception
    // Exception table:
    //   from	to	target	type
    //   95	99	32	java/lang/Exception
    //   104	112	127	java/lang/Exception
  }
}
