package o;

import android.content.res.Resources;
import android.databinding.ViewDataBinding;
import android.databinding.ViewDataBinding.If;
import android.util.SparseIntArray;
import android.widget.FrameLayout;
import android.widget.ImageView;
import android.widget.LinearLayout;
import android.widget.ProgressBar;
import android.widget.RelativeLayout;
import android.widget.TextView;
import java.io.UnsupportedEncodingException;

public class Mv
  extends ViewDataBinding
{
  private static long ʼॱ;
  private static byte ʽॱ;
  private static int ʿ;
  private static int ˈ;
  private static final ViewDataBinding.If ˊॱ;
  private static final SparseIntArray ͺ;
  public final TextView ʻ;
  private final TextView ʻॱ;
  public final Ꭸ ʼ;
  public final aH ʽ;
  public final ProgressBar ˊ;
  private final KV ˋॱ;
  public final FrameLayout ˎ;
  private final KV ˏॱ;
  public final ImageView ॱ;
  private final RelativeLayout ॱˊ;
  private final TextView ॱˋ;
  private boolean ॱˎ;
  public final KV ॱॱ;
  private final LinearLayout ॱᐝ;
  public final у ᐝ;
  private long ᐝॱ;
  
  static
  {
    for (;;)
    {
      int i = ʿ + 89;
      ˈ = i % 128;
      if (i % 2 != 0) {
        return;
      }
      return;
      ʿ = 0;
      ˈ = 1;
      ॱˊ();
      ˋॱ();
      ˊॱ = null;
      ͺ = new SparseIntArray();
      ͺ.put(2131296653, 10);
      ͺ.put(2131296581, 11);
      ͺ.put(2131296720, 12);
      ͺ.put(2131296600, 13);
    }
  }
  
  /* Error */
  public Mv(ˉ paramˉ, android.view.View paramView)
  {
    // Byte code:
    //   0: goto +6 -> 6
    //   3: astore_1
    //   4: aload_1
    //   5: athrow
    //   6: aload_0
    //   7: aload_1
    //   8: aload_2
    //   9: iconst_0
    //   10: invokespecial 76	android/databinding/ViewDataBinding:<init>	(Lo/ˉ;Landroid/view/View;I)V
    //   13: aload_0
    //   14: ldc2_w 77
    //   17: putfield 80	o/Mv:ᐝॱ	J
    //   20: getstatic 54	o/Mv:ˊॱ	Landroid/databinding/ViewDataBinding$If;
    //   23: astore_3
    //   24: getstatic 61	o/Mv:ͺ	Landroid/util/SparseIntArray;
    //   27: astore 4
    //   29: aload_1
    //   30: aload_2
    //   31: bipush 14
    //   33: aload_3
    //   34: aload 4
    //   36: invokestatic 83	o/Mv:ॱ	(Lo/ˉ;Landroid/view/View;ILandroid/databinding/ViewDataBinding$If;Landroid/util/SparseIntArray;)[Ljava/lang/Object;
    //   39: astore_1
    //   40: aload_0
    //   41: aload_1
    //   42: iconst_1
    //   43: aaload
    //   44: checkcast 85	android/widget/ImageView
    //   47: putfield 87	o/Mv:ॱ	Landroid/widget/ImageView;
    //   50: aload_0
    //   51: getfield 87	o/Mv:ॱ	Landroid/widget/ImageView;
    //   54: aconst_null
    //   55: invokevirtual 91	android/widget/ImageView:setTag	(Ljava/lang/Object;)V
    //   58: aload_0
    //   59: aload_1
    //   60: iconst_0
    //   61: aaload
    //   62: checkcast 93	android/widget/RelativeLayout
    //   65: putfield 95	o/Mv:ॱˊ	Landroid/widget/RelativeLayout;
    //   68: aload_0
    //   69: getfield 95	o/Mv:ॱˊ	Landroid/widget/RelativeLayout;
    //   72: aconst_null
    //   73: invokevirtual 96	android/widget/RelativeLayout:setTag	(Ljava/lang/Object;)V
    //   76: aload_0
    //   77: aload_1
    //   78: iconst_4
    //   79: aaload
    //   80: checkcast 98	o/KV
    //   83: putfield 100	o/Mv:ˏॱ	Lo/KV;
    //   86: aload_0
    //   87: getfield 100	o/Mv:ˏॱ	Lo/KV;
    //   90: aconst_null
    //   91: invokevirtual 101	o/KV:setTag	(Ljava/lang/Object;)V
    //   94: aload_0
    //   95: aload_1
    //   96: iconst_5
    //   97: aaload
    //   98: checkcast 98	o/KV
    //   101: putfield 103	o/Mv:ˋॱ	Lo/KV;
    //   104: aload_0
    //   105: getfield 103	o/Mv:ˋॱ	Lo/KV;
    //   108: aconst_null
    //   109: invokevirtual 101	o/KV:setTag	(Ljava/lang/Object;)V
    //   112: aload_0
    //   113: aload_1
    //   114: bipush 6
    //   116: aaload
    //   117: checkcast 105	android/widget/TextView
    //   120: putfield 107	o/Mv:ʻॱ	Landroid/widget/TextView;
    //   123: aload_0
    //   124: getfield 107	o/Mv:ʻॱ	Landroid/widget/TextView;
    //   127: aconst_null
    //   128: invokevirtual 108	android/widget/TextView:setTag	(Ljava/lang/Object;)V
    //   131: aload_0
    //   132: aload_1
    //   133: bipush 8
    //   135: aaload
    //   136: checkcast 110	android/widget/LinearLayout
    //   139: putfield 112	o/Mv:ॱᐝ	Landroid/widget/LinearLayout;
    //   142: aload_0
    //   143: getfield 112	o/Mv:ॱᐝ	Landroid/widget/LinearLayout;
    //   146: aconst_null
    //   147: invokevirtual 113	android/widget/LinearLayout:setTag	(Ljava/lang/Object;)V
    //   150: aload_0
    //   151: aload_1
    //   152: bipush 9
    //   154: aaload
    //   155: checkcast 105	android/widget/TextView
    //   158: putfield 115	o/Mv:ॱˋ	Landroid/widget/TextView;
    //   161: aload_0
    //   162: getfield 115	o/Mv:ॱˋ	Landroid/widget/TextView;
    //   165: aconst_null
    //   166: invokevirtual 108	android/widget/TextView:setTag	(Ljava/lang/Object;)V
    //   169: aload_0
    //   170: aload_1
    //   171: bipush 11
    //   173: aaload
    //   174: checkcast 117	android/widget/FrameLayout
    //   177: putfield 119	o/Mv:ˎ	Landroid/widget/FrameLayout;
    //   180: aload_0
    //   181: aload_1
    //   182: bipush 13
    //   184: aaload
    //   185: checkcast 121	android/widget/ProgressBar
    //   188: putfield 123	o/Mv:ˊ	Landroid/widget/ProgressBar;
    //   191: aload_0
    //   192: aload_1
    //   193: iconst_3
    //   194: aaload
    //   195: checkcast 98	o/KV
    //   198: putfield 125	o/Mv:ॱॱ	Lo/KV;
    //   201: aload_0
    //   202: getfield 125	o/Mv:ॱॱ	Lo/KV;
    //   205: aconst_null
    //   206: invokevirtual 101	o/KV:setTag	(Ljava/lang/Object;)V
    //   209: aload_0
    //   210: aload_1
    //   211: bipush 10
    //   213: aaload
    //   214: checkcast 127	o/Ꭸ
    //   217: putfield 129	o/Mv:ʼ	Lo/Ꭸ;
    //   220: aload_0
    //   221: aload_1
    //   222: iconst_2
    //   223: aaload
    //   224: checkcast 131	o/у
    //   227: putfield 133	o/Mv:ᐝ	Lo/у;
    //   230: aload_0
    //   231: getfield 133	o/Mv:ᐝ	Lo/у;
    //   234: aconst_null
    //   235: invokevirtual 134	o/у:setTag	(Ljava/lang/Object;)V
    //   238: aload_0
    //   239: aload_1
    //   240: bipush 12
    //   242: aaload
    //   243: checkcast 136	o/aH
    //   246: putfield 138	o/Mv:ʽ	Lo/aH;
    //   249: aload_0
    //   250: aload_1
    //   251: bipush 7
    //   253: aaload
    //   254: checkcast 105	android/widget/TextView
    //   257: putfield 140	o/Mv:ʻ	Landroid/widget/TextView;
    //   260: aload_0
    //   261: getfield 140	o/Mv:ʻ	Landroid/widget/TextView;
    //   264: aconst_null
    //   265: invokevirtual 108	android/widget/TextView:setTag	(Ljava/lang/Object;)V
    //   268: aload_0
    //   269: aload_2
    //   270: invokevirtual 144	o/Mv:ˋ	(Landroid/view/View;)V
    //   273: aload_0
    //   274: invokevirtual 146	o/Mv:ˏॱ	()V
    //   277: return
    //   278: astore_1
    //   279: aload_1
    //   280: athrow
    // Local variable table:
    //   start	length	slot	name	signature
    //   0	281	0	this	Mv
    //   0	281	1	paramˉ	ˉ
    //   0	281	2	paramView	android.view.View
    //   23	11	3	localIf	ViewDataBinding.If
    //   27	8	4	localSparseIntArray	SparseIntArray
    // Exception table:
    //   from	to	target	type
    //   29	277	3	java/lang/Exception
    //   13	20	278	java/lang/Exception
    //   20	24	278	java/lang/Exception
    //   24	29	278	java/lang/Exception
    //   29	277	278	java/lang/Exception
  }
  
  /* Error */
  static void ˋॱ()
  {
    // Byte code:
    //   0: goto +15 -> 15
    //   3: bipush 84
    //   5: putstatic 148	o/Mv:ʽॱ	B
    //   8: goto +97 -> 105
    //   11: astore_1
    //   12: aload_1
    //   13: athrow
    //   14: return
    //   15: getstatic 46	o/Mv:ʿ	I
    //   18: bipush 125
    //   20: iadd
    //   21: istore_0
    //   22: iload_0
    //   23: sipush 128
    //   26: irem
    //   27: putstatic 48	o/Mv:ˈ	I
    //   30: iload_0
    //   31: iconst_2
    //   32: irem
    //   33: ifne +6 -> 39
    //   36: goto +47 -> 83
    //   39: goto +95 -> 134
    //   42: bipush -102
    //   44: putstatic 148	o/Mv:ʽॱ	B
    //   47: goto +58 -> 105
    //   50: astore_1
    //   51: aload_1
    //   52: athrow
    //   53: iload_0
    //   54: lookupswitch	default:+26->80, 16:+-12->42, 18:+-51->3
    //   80: goto -77 -> 3
    //   83: bipush 18
    //   85: istore_0
    //   86: goto -33 -> 53
    //   89: bipush 6
    //   91: iconst_0
    //   92: idiv
    //   93: istore_0
    //   94: return
    //   95: iconst_1
    //   96: istore_0
    //   97: goto +43 -> 140
    //   100: iconst_0
    //   101: istore_0
    //   102: goto +38 -> 140
    //   105: getstatic 48	o/Mv:ˈ	I
    //   108: istore_0
    //   109: iload_0
    //   110: bipush 15
    //   112: iadd
    //   113: istore_0
    //   114: iload_0
    //   115: sipush 128
    //   118: irem
    //   119: putstatic 46	o/Mv:ʿ	I
    //   122: iload_0
    //   123: iconst_2
    //   124: irem
    //   125: ifeq +6 -> 131
    //   128: goto -33 -> 95
    //   131: goto -31 -> 100
    //   134: bipush 16
    //   136: istore_0
    //   137: goto -84 -> 53
    //   140: iload_0
    //   141: tableswitch	default:+23->164, 0:+-127->14, 1:+-52->89
    //   164: return
    // Local variable table:
    //   start	length	slot	name	signature
    //   21	120	0	i	int
    //   11	2	1	localException1	Exception
    //   50	2	1	localException2	Exception
    // Exception table:
    //   from	to	target	type
    //   105	109	11	java/lang/Exception
    //   114	122	11	java/lang/Exception
    //   3	8	50	java/lang/Exception
  }
  
  private String ˏ(String paramString)
  {
    break label251;
    label3:
    int j = ˈ + 51;
    ʿ = j % 128;
    if (j % 2 == 0) {
      break label437;
    }
    for (;;)
    {
      try
      {
        j = arrayOfByte.length;
        if (i >= j)
        {
          break label462;
          arrayOfByte = paramString.getBytes(ॱ(new char[] { 5679, 5734, 13766, -17853, 8198, 16357, -20290, 7953, 10502, -1328, 32567, 24157, 26875, 15217 }).intern());
          paramString = new byte[arrayOfByte.length];
          i = 0;
        }
        switch (j)
        {
        case 86: 
        default: 
          break label3;
          paramString[i] = ((byte)(arrayOfByte[(arrayOfByte.length - i + 1)] ^ ʽॱ));
          i += 54;
          break label434;
          j = 86;
          continue;
          i = ˈ + 41;
          ʿ = i % 128;
          if (i % 2 != 0) {
            break label359;
          }
          break label468;
          continue;
          continue;
        }
      }
      catch (UnsupportedEncodingException paramString)
      {
        throw new RuntimeException(paramString);
      }
      label251:
      byte[] arrayOfByte = paramString.getBytes(ॱ(new char[] { 5679, 5734, 13766, -17853, 8198, 16357, -20290, 7953, 10502, -1328, 32567, 24157, 26875, 15217 }).intern());
      paramString = new byte[arrayOfByte.length];
      int i = 1;
      continue;
      label359:
      i = 55;
      break label471;
      paramString = new String(paramString, ॱ(new char[] { 29751, 29794, 1456, -30158, 3763, 4441, 6798, -19167, 19202 }).intern());
      return paramString;
      for (;;)
      {
        label434:
        break;
        label437:
        paramString[i] = ((byte)(arrayOfByte[(arrayOfByte.length - i - 1)] ^ ʽॱ));
        i += 1;
      }
      label462:
      j = 81;
      continue;
      label468:
      i = 27;
      label471:
      switch (i)
      {
      }
    }
  }
  
  private static String ॱ(char[] paramArrayOfChar)
  {
    break label44;
    int i = j;
    break label61;
    int j = 55;
    break label211;
    label14:
    i = 65;
    break label173;
    paramArrayOfChar = new String(paramArrayOfChar, 4, paramArrayOfChar.length - 4);
    break label248;
    for (;;)
    {
      i = 62 / 0;
      return paramArrayOfChar;
      label44:
      break label49;
      return paramArrayOfChar;
      try
      {
        label49:
        long l = ʼॱ;
        paramArrayOfChar = oL.ˋ(l, paramArrayOfChar);
        i = 4;
        label61:
        if (i < paramArrayOfChar.length) {
          break;
        }
        j = 94;
      }
      catch (Exception paramArrayOfChar)
      {
        label76:
        label107:
        throw paramArrayOfChar;
      }
      paramArrayOfChar[i] = ((char)(int)(paramArrayOfChar[i] ^ paramArrayOfChar[(i % 4)] ^ (i - 4) * ʼॱ));
      j = i + 1;
      break label146;
      switch (i)
      {
      }
    }
    label135:
    i = 81;
    for (;;)
    {
      i = 1;
      break label107;
      label146:
      i = ˈ + 41;
      ʿ = i % 128;
      if (i % 2 != 0) {
        break label14;
      }
      break label135;
      switch (i)
      {
      case 81: 
      default: 
        break;
      case 65: 
        label173:
        i = j;
        break label61;
        label211:
        switch (j)
        {
        }
        break label76;
        label248:
        do
        {
          i = 0;
          break;
          i = ʿ + 7;
          ˈ = i % 128;
        } while (i % 2 == 0);
      }
    }
  }
  
  static void ॱˊ()
  {
    ʼॱ = -7559389585096011818L;
  }
  
  public void ˋ(boolean paramBoolean)
  {
    this.ॱˎ = paramBoolean;
    try
    {
      this.ᐝॱ |= 1L;
    }
    finally
    {
      localObject = finally;
      throw localObject;
    }
    ˊ(70);
    super.ʽ();
  }
  
  public void ˏ()
  {
    String str2 = ॱ(new char[] { 28198, 28195, 12089, -24331, 3141, 5090, -1217, 21681 }).intern();
    long l2;
    try
    {
      l2 = this.ᐝॱ;
      this.ᐝॱ = 0L;
    }
    finally
    {
      localObject1 = finally;
      throw localObject1;
    }
    int i = 0;
    boolean bool = this.ॱˎ;
    long l1 = l2;
    if ((0x3 & l2) != 0L)
    {
      l1 = l2;
      if ((0x3 & l2) != 0L) {
        if (bool) {
          l1 = l2 | 0x8;
        } else {
          l1 = l2 | 0x4;
        }
      }
      if (bool) {
        i = 0;
      } else {
        i = 4;
      }
    }
    if ((0x2 & l1) != 0L)
    {
      r.ˊ(this.ॱ, ॱ(new char[] { 4770, 4810, -16350, 20352, 8921, 15617, -2349, 22817, 11745, 3894, 32242, 6182, 27672, -12592, -17163, -10112, -21317, -29231, -248, -25801, -4220, 19830, 16289, 23107, 11806, 3202, 32463, 6790, 28405, -13402, -18159, -8906, -22077, -29840, -1631, -25508, -6018, 19099, 14548, 23777, 10427, 2531, 31595, 8056, 27541, -14057, -17504, -8619, -21898, -30507, -1341, -24834, -5479, 18427, 13665, 20761, 9687, 1793, 30104, 4192, 25719, -14619, -19262, -12060, -23347, -31330, -2228, -27846, -6399, 17715, 14247, 21406, 9799, 1218, 30233, 4822, 26291, -15255, -20156, -10970, -24313 }).intern(), ॱ(this.ॱ, 2131230823), true);
      this.ˏॱ.setIcon(ॱ(this.ˏॱ, 2131231183));
      Object localObject3 = this.ˏॱ;
      String str1 = this.ˏॱ.getResources().getString(2131755438);
      Object localObject2 = str1;
      if (str1.startsWith(str2)) {
        localObject2 = ˏ(str1.substring(4)).intern();
      }
      ((KV)localObject3).setTitle((String)localObject2);
      this.ˋॱ.setIcon(ॱ(this.ˋॱ, 2131231170));
      localObject3 = this.ˋॱ;
      str1 = this.ˋॱ.getResources().getString(2131755072);
      localObject2 = str1;
      if (str1.startsWith(str2)) {
        localObject2 = ˏ(str1.substring(4)).intern();
      }
      ((KV)localObject3).setTitle((String)localObject2);
      localObject3 = this.ʻॱ;
      str1 = this.ʻॱ.getResources().getString(2131755599);
      localObject2 = str1;
      if (str1.startsWith(str2)) {
        localObject2 = ˏ(str1.substring(4)).intern();
      }
      ʹ.ˊ((TextView)localObject3, (CharSequence)localObject2);
      localObject3 = this.ॱˋ;
      str1 = this.ॱˋ.getResources().getString(2131755246);
      localObject2 = str1;
      if (str1.startsWith(str2)) {
        localObject2 = ˏ(str1.substring(4)).intern();
      }
      ʹ.ˊ((TextView)localObject3, (CharSequence)localObject2);
      this.ॱॱ.setIcon(ॱ(this.ॱॱ, 2131231188));
      localObject3 = this.ॱॱ;
      str1 = this.ॱॱ.getResources().getString(2131755470);
      localObject2 = str1;
      if (str1.startsWith(str2)) {
        localObject2 = ˏ(str1.substring(4)).intern();
      }
      ((KV)localObject3).setTitle((String)localObject2);
      localObject3 = this.ᐝ;
      str1 = this.ᐝ.getResources().getString(2131755610);
      localObject2 = str1;
      if (str1.startsWith(str2)) {
        localObject2 = ˏ(str1.substring(4)).intern();
      }
      ((у)localObject3).setTitle((CharSequence)localObject2);
      localObject3 = this.ʻ;
      str1 = this.ʻ.getResources().getString(2131755274);
      localObject2 = str1;
      if (str1.startsWith(str2)) {
        localObject2 = ˏ(str1.substring(4)).intern();
      }
      ʹ.ˊ((TextView)localObject3, (CharSequence)localObject2);
    }
    if ((0x3 & l1) != 0L) {
      this.ॱᐝ.setVisibility(i);
    }
  }
  
  public boolean ˏ(int paramInt1, Object paramObject, int paramInt2)
  {
    break label103;
    paramInt1 = ʿ + 59;
    ˈ = paramInt1 % 128;
    if (paramInt1 % 2 != 0)
    {
      paramInt1 = 1;
      break label77;
      label32:
      paramInt1 = ˈ + 19;
      ʿ = paramInt1 % 128;
      if (paramInt1 % 2 != 0) {
        break label106;
      }
    }
    else
    {
      paramInt1 = 0;
      break label77;
    }
    label77:
    label103:
    label106:
    for (;;)
    {
      break;
      for (;;)
      {
        return false;
        throw new NullPointerException();
        switch (paramInt1)
        {
        }
      }
      break label32;
    }
  }
  
  public void ˏॱ()
  {
    try
    {
      this.ᐝॱ = 2L;
    }
    finally
    {
      localObject = finally;
      throw localObject;
    }
    ʽ();
  }
  
  public boolean ॱ()
  {
    try
    {
      long l = this.ᐝॱ;
      if (l != 0L) {
        return true;
      }
    }
    finally
    {
      localObject = finally;
      throw localObject;
    }
    return false;
  }
}
