package o;

import android.content.Context;
import android.widget.Toast;
import java.util.ArrayList;
import java.util.Locale;

public class MZ
  extends F<MT>
  implements ᐸ.ˏ
{
  private static byte ॱˍ;
  private static long ॱˑ;
  private static int ॱـ;
  private static int ॱᐧ;
  private static char ॱᐨ;
  private static int ॱꓸ;
  private ArrayList<Locale> ߺ;
  private final String ॱˉ;
  private IM ॱˌ;
  
  /* Error */
  static
  {
    // Byte code:
    //   0: goto +77 -> 77
    //   3: return
    //   4: astore_1
    //   5: aload_1
    //   6: athrow
    //   7: getstatic 34	o/MZ:ॱᐧ	I
    //   10: istore_0
    //   11: iload_0
    //   12: bipush 99
    //   14: iadd
    //   15: istore_0
    //   16: iload_0
    //   17: sipush 128
    //   20: irem
    //   21: putstatic 36	o/MZ:ॱꓸ	I
    //   24: iload_0
    //   25: iconst_2
    //   26: irem
    //   27: ifeq +6 -> 33
    //   30: goto +42 -> 72
    //   33: goto +63 -> 96
    //   36: iload_0
    //   37: tableswitch	default:+23->60, 0:+-34->3, 1:+27->64
    //   60: return
    //   61: astore_1
    //   62: aload_1
    //   63: athrow
    //   64: new 38	java/lang/NullPointerException
    //   67: dup
    //   68: invokespecial 41	java/lang/NullPointerException:<init>	()V
    //   71: athrow
    //   72: iconst_1
    //   73: istore_0
    //   74: goto -38 -> 36
    //   77: iconst_0
    //   78: putstatic 36	o/MZ:ॱꓸ	I
    //   81: iconst_1
    //   82: putstatic 34	o/MZ:ॱᐧ	I
    //   85: invokestatic 44	o/MZ:ᐝ	()V
    //   88: bipush -102
    //   90: putstatic 46	o/MZ:ॱˍ	B
    //   93: goto -86 -> 7
    //   96: iconst_0
    //   97: istore_0
    //   98: goto -62 -> 36
    // Local variable table:
    //   start	length	slot	name	signature
    //   10	88	0	i	int
    //   4	2	1	localException1	Exception
    //   61	2	1	localException2	Exception
    // Exception table:
    //   from	to	target	type
    //   16	24	4	java/lang/Exception
    //   7	11	61	java/lang/Exception
  }
  
  public MZ(Context paramContext, String paramString) {}
  
  /* Error */
  private void ʼ()
  {
    // Byte code:
    //   0: goto +161 -> 161
    //   3: iload_1
    //   4: lookupswitch	default:+28->32, 18:+31->35, 68:+206->210
    //   32: goto +178 -> 210
    //   35: getstatic 36	o/MZ:ॱꓸ	I
    //   38: bipush 53
    //   40: iadd
    //   41: istore_1
    //   42: iload_1
    //   43: sipush 128
    //   46: irem
    //   47: putstatic 34	o/MZ:ॱᐧ	I
    //   50: iload_1
    //   51: iconst_2
    //   52: irem
    //   53: ifne +6 -> 59
    //   56: goto +145 -> 201
    //   59: goto +96 -> 155
    //   62: bipush 68
    //   64: istore_1
    //   65: goto -62 -> 3
    //   68: aload_0
    //   69: invokevirtual 124	o/MZ:ˋ	()Landroid/content/Context;
    //   72: invokevirtual 128	android/content/Context:getPackageManager	()Landroid/content/pm/PackageManager;
    //   75: aload_0
    //   76: invokevirtual 124	o/MZ:ˋ	()Landroid/content/Context;
    //   79: invokevirtual 131	android/content/Context:getPackageName	()Ljava/lang/String;
    //   82: invokevirtual 137	android/content/pm/PackageManager:getLaunchIntentForPackage	(Ljava/lang/String;)Landroid/content/Intent;
    //   85: astore_3
    //   86: aload_3
    //   87: ifnull +6 -> 93
    //   90: goto +102 -> 192
    //   93: goto -31 -> 62
    //   96: getstatic 36	o/MZ:ॱꓸ	I
    //   99: bipush 95
    //   101: iadd
    //   102: istore_1
    //   103: iload_1
    //   104: sipush 128
    //   107: irem
    //   108: putstatic 34	o/MZ:ॱᐧ	I
    //   111: iload_1
    //   112: iconst_2
    //   113: irem
    //   114: ifne +6 -> 120
    //   117: goto +81 -> 198
    //   120: goto -52 -> 68
    //   123: iload_1
    //   124: lookupswitch	default:+28->152, 90:+43->167, 91:+53->177
    //   152: goto +15 -> 167
    //   155: bipush 90
    //   157: istore_1
    //   158: goto -35 -> 123
    //   161: goto -65 -> 96
    //   164: astore_2
    //   165: aload_2
    //   166: athrow
    //   167: aload_3
    //   168: ldc -118
    //   170: invokevirtual 144	android/content/Intent:setFlags	(I)Landroid/content/Intent;
    //   173: pop
    //   174: goto +36 -> 210
    //   177: aload_3
    //   178: ldc -118
    //   180: invokevirtual 144	android/content/Intent:setFlags	(I)Landroid/content/Intent;
    //   183: pop
    //   184: new 38	java/lang/NullPointerException
    //   187: dup
    //   188: invokespecial 41	java/lang/NullPointerException:<init>	()V
    //   191: athrow
    //   192: bipush 18
    //   194: istore_1
    //   195: goto -192 -> 3
    //   198: goto -130 -> 68
    //   201: bipush 91
    //   203: istore_1
    //   204: goto -81 -> 123
    //   207: astore_2
    //   208: aload_2
    //   209: athrow
    //   210: aload_0
    //   211: invokevirtual 124	o/MZ:ˋ	()Landroid/content/Context;
    //   214: astore_2
    //   215: aload_2
    //   216: aload_3
    //   217: invokevirtual 148	android/content/Context:startActivity	(Landroid/content/Intent;)V
    //   220: return
    // Local variable table:
    //   start	length	slot	name	signature
    //   0	221	0	this	MZ
    //   3	201	1	i	int
    //   164	2	2	localException1	Exception
    //   207	2	2	localException2	Exception
    //   214	2	2	localContext	Context
    //   85	132	3	localIntent	android.content.Intent
    // Exception table:
    //   from	to	target	type
    //   215	220	164	java/lang/Exception
    //   35	42	207	java/lang/Exception
    //   42	50	207	java/lang/Exception
    //   210	215	207	java/lang/Exception
  }
  
  /* Error */
  private void ʽ()
  {
    // Byte code:
    //   0: goto +368 -> 368
    //   3: getstatic 34	o/MZ:ॱᐧ	I
    //   6: istore_1
    //   7: iload_1
    //   8: bipush 73
    //   10: iadd
    //   11: istore_1
    //   12: iload_1
    //   13: sipush 128
    //   16: irem
    //   17: putstatic 36	o/MZ:ॱꓸ	I
    //   20: iload_1
    //   21: iconst_2
    //   22: irem
    //   23: ifeq +6 -> 29
    //   26: goto +6 -> 32
    //   29: goto +254 -> 283
    //   32: goto +251 -> 283
    //   35: bipush 9
    //   37: istore_2
    //   38: goto +19 -> 57
    //   41: goto +192 -> 233
    //   44: bipush 62
    //   46: istore_2
    //   47: goto +148 -> 195
    //   50: iload_1
    //   51: iconst_1
    //   52: iadd
    //   53: istore_1
    //   54: goto +114 -> 168
    //   57: iload_2
    //   58: lookupswitch	default:+26->84, 9:+201->259, 64:+29->87
    //   84: goto +175 -> 259
    //   87: aload_0
    //   88: getfield 152	o/MZ:ॱˈ	Landroid/databinding/ViewDataBinding;
    //   91: checkcast 154	o/MT
    //   94: getfield 157	o/MT:ˊ	Lo/IW;
    //   97: iload_1
    //   98: invokevirtual 163	o/IW:getChildAt	(I)Landroid/view/View;
    //   101: checkcast 165	o/IU
    //   104: iconst_1
    //   105: invokevirtual 169	o/IU:setChecked	(Z)V
    //   108: goto -58 -> 50
    //   111: bipush 36
    //   113: istore_2
    //   114: goto +81 -> 195
    //   117: getstatic 36	o/MZ:ॱꓸ	I
    //   120: bipush 63
    //   122: iadd
    //   123: istore_2
    //   124: iload_2
    //   125: sipush 128
    //   128: irem
    //   129: putstatic 34	o/MZ:ॱᐧ	I
    //   132: iload_2
    //   133: iconst_2
    //   134: irem
    //   135: ifne +6 -> 141
    //   138: goto -103 -> 35
    //   141: goto +86 -> 227
    //   144: aload_0
    //   145: getfield 171	o/MZ:ߺ	Ljava/util/ArrayList;
    //   148: astore_3
    //   149: aload_3
    //   150: invokevirtual 177	java/util/ArrayList:size	()I
    //   153: istore_2
    //   154: iload_1
    //   155: iload_2
    //   156: if_icmpge +6 -> 162
    //   159: goto +133 -> 292
    //   162: goto -121 -> 41
    //   165: goto -21 -> 144
    //   168: getstatic 36	o/MZ:ॱꓸ	I
    //   171: bipush 121
    //   173: iadd
    //   174: istore_2
    //   175: iload_2
    //   176: sipush 128
    //   179: irem
    //   180: putstatic 34	o/MZ:ॱᐧ	I
    //   183: iload_2
    //   184: iconst_2
    //   185: irem
    //   186: ifne +6 -> 192
    //   189: goto -24 -> 165
    //   192: goto -48 -> 144
    //   195: iload_2
    //   196: lookupswitch	default:+28->224, 36:+-146->50, 62:+-79->117
    //   224: goto -107 -> 117
    //   227: bipush 64
    //   229: istore_2
    //   230: goto -173 -> 57
    //   233: getstatic 36	o/MZ:ॱꓸ	I
    //   236: bipush 91
    //   238: iadd
    //   239: istore_1
    //   240: iload_1
    //   241: sipush 128
    //   244: irem
    //   245: putstatic 34	o/MZ:ॱᐧ	I
    //   248: iload_1
    //   249: iconst_2
    //   250: irem
    //   251: ifne +6 -> 257
    //   254: goto +4 -> 258
    //   257: return
    //   258: return
    //   259: aload_0
    //   260: getfield 152	o/MZ:ॱˈ	Landroid/databinding/ViewDataBinding;
    //   263: checkcast 154	o/MT
    //   266: getfield 157	o/MT:ˊ	Lo/IW;
    //   269: iload_1
    //   270: invokevirtual 163	o/IW:getChildAt	(I)Landroid/view/View;
    //   273: checkcast 165	o/IU
    //   276: iconst_1
    //   277: invokevirtual 169	o/IU:setChecked	(Z)V
    //   280: goto -230 -> 50
    //   283: aload_0
    //   284: invokespecial 180	o/MZ:ॱॱ	()V
    //   287: iconst_0
    //   288: istore_1
    //   289: goto -145 -> 144
    //   292: aload_0
    //   293: getfield 171	o/MZ:ߺ	Ljava/util/ArrayList;
    //   296: iload_1
    //   297: invokevirtual 184	java/util/ArrayList:get	(I)Ljava/lang/Object;
    //   300: checkcast 186	java/util/Locale
    //   303: invokevirtual 189	java/util/Locale:getDisplayLanguage	()Ljava/lang/String;
    //   306: invokestatic 193	o/aq:ˎ	(Ljava/lang/String;)Ljava/lang/String;
    //   309: astore_3
    //   310: aload_0
    //   311: getfield 152	o/MZ:ॱˈ	Landroid/databinding/ViewDataBinding;
    //   314: checkcast 154	o/MT
    //   317: getfield 157	o/MT:ˊ	Lo/IW;
    //   320: new 165	o/IU
    //   323: dup
    //   324: aload_0
    //   325: getfield 197	o/MZ:ˏ	Landroid/content/Context;
    //   328: aload_3
    //   329: invokespecial 199	o/IU:<init>	(Landroid/content/Context;Ljava/lang/String;)V
    //   332: invokevirtual 203	o/IW:addView	(Landroid/view/View;)V
    //   335: aload_0
    //   336: getfield 171	o/MZ:ߺ	Ljava/util/ArrayList;
    //   339: iload_1
    //   340: invokevirtual 184	java/util/ArrayList:get	(I)Ljava/lang/Object;
    //   343: checkcast 186	java/util/Locale
    //   346: invokevirtual 206	java/util/Locale:getLanguage	()Ljava/lang/String;
    //   349: invokestatic 209	o/aq:ˋॱ	(Ljava/lang/String;)Ljava/lang/String;
    //   352: aload_0
    //   353: getfield 111	o/MZ:ॱˉ	Ljava/lang/String;
    //   356: invokevirtual 213	java/lang/String:equals	(Ljava/lang/Object;)Z
    //   359: ifeq +6 -> 365
    //   362: goto -318 -> 44
    //   365: goto -254 -> 111
    //   368: goto -365 -> 3
    //   371: astore_3
    //   372: aload_3
    //   373: athrow
    // Local variable table:
    //   start	length	slot	name	signature
    //   0	374	0	this	MZ
    //   6	334	1	i	int
    //   37	193	2	j	int
    //   148	181	3	localObject	Object
    //   371	2	3	localException	Exception
    // Exception table:
    //   from	to	target	type
    //   3	7	371	java/lang/Exception
    //   12	20	371	java/lang/Exception
    //   144	149	371	java/lang/Exception
    //   149	154	371	java/lang/Exception
  }
  
  /* Error */
  private void ˏ(final String paramString)
  {
    // Byte code:
    //   0: goto +586 -> 586
    //   3: iconst_1
    //   4: istore_2
    //   5: goto +526 -> 531
    //   8: aconst_null
    //   9: arraylength
    //   10: istore_2
    //   11: return
    //   12: return
    //   13: iconst_0
    //   14: istore_2
    //   15: goto +516 -> 531
    //   18: aload_0
    //   19: invokevirtual 124	o/MZ:ˋ	()Landroid/content/Context;
    //   22: astore 7
    //   24: new 217	o/IM
    //   27: dup
    //   28: aload 7
    //   30: getstatic 220	o/MH$ᐝ:restarting_the_app	I
    //   33: invokespecial 223	o/IM:<init>	(Landroid/content/Context;I)V
    //   36: astore 7
    //   38: aload_0
    //   39: aload 7
    //   41: putfield 225	o/MZ:ॱˌ	Lo/IM;
    //   44: aload_0
    //   45: getfield 225	o/MZ:ॱˌ	Lo/IM;
    //   48: astore 7
    //   50: aload 7
    //   52: invokevirtual 228	o/IM:ˏ	()Lo/ᐸ;
    //   55: pop
    //   56: goto +20 -> 76
    //   59: astore_1
    //   60: aload_1
    //   61: invokevirtual 234	java/lang/Throwable:getCause	()Ljava/lang/Throwable;
    //   64: astore 7
    //   66: aload 7
    //   68: ifnull +6 -> 74
    //   71: aload 7
    //   73: athrow
    //   74: aload_1
    //   75: athrow
    //   76: iconst_4
    //   77: sipush 402
    //   80: iconst_0
    //   81: invokestatic 239	o/O:ˋ	(IIC)Ljava/lang/Object;
    //   84: checkcast 241	java/lang/Class
    //   87: ldc -13
    //   89: aconst_null
    //   90: invokevirtual 247	java/lang/Class:getMethod	(Ljava/lang/String;[Ljava/lang/Class;)Ljava/lang/reflect/Method;
    //   93: aconst_null
    //   94: aconst_null
    //   95: invokevirtual 253	java/lang/reflect/Method:invoke	(Ljava/lang/Object;[Ljava/lang/Object;)Ljava/lang/Object;
    //   98: astore 7
    //   100: goto +20 -> 120
    //   103: astore_1
    //   104: aload_1
    //   105: invokevirtual 234	java/lang/Throwable:getCause	()Ljava/lang/Throwable;
    //   108: astore 7
    //   110: aload 7
    //   112: ifnull +6 -> 118
    //   115: aload 7
    //   117: athrow
    //   118: aload_1
    //   119: athrow
    //   120: iconst_4
    //   121: sipush 402
    //   124: iconst_0
    //   125: invokestatic 239	o/O:ˋ	(IIC)Ljava/lang/Object;
    //   128: checkcast 241	java/lang/Class
    //   131: ldc -1
    //   133: aconst_null
    //   134: invokevirtual 247	java/lang/Class:getMethod	(Ljava/lang/String;[Ljava/lang/Class;)Ljava/lang/reflect/Method;
    //   137: aload 7
    //   139: aconst_null
    //   140: invokevirtual 253	java/lang/reflect/Method:invoke	(Ljava/lang/Object;[Ljava/lang/Object;)Ljava/lang/Object;
    //   143: checkcast 257	java/lang/Boolean
    //   146: invokevirtual 261	java/lang/Boolean:booleanValue	()Z
    //   149: istore_3
    //   150: goto +20 -> 170
    //   153: astore_1
    //   154: aload_1
    //   155: invokevirtual 234	java/lang/Throwable:getCause	()Ljava/lang/Throwable;
    //   158: astore 7
    //   160: aload 7
    //   162: ifnull +6 -> 168
    //   165: aload 7
    //   167: athrow
    //   168: aload_1
    //   169: athrow
    //   170: iconst_4
    //   171: sipush 402
    //   174: iconst_0
    //   175: invokestatic 239	o/O:ˋ	(IIC)Ljava/lang/Object;
    //   178: checkcast 241	java/lang/Class
    //   181: ldc -13
    //   183: aconst_null
    //   184: invokevirtual 247	java/lang/Class:getMethod	(Ljava/lang/String;[Ljava/lang/Class;)Ljava/lang/reflect/Method;
    //   187: aconst_null
    //   188: aconst_null
    //   189: invokevirtual 253	java/lang/reflect/Method:invoke	(Ljava/lang/Object;[Ljava/lang/Object;)Ljava/lang/Object;
    //   192: astore 7
    //   194: goto +20 -> 214
    //   197: astore_1
    //   198: aload_1
    //   199: invokevirtual 234	java/lang/Throwable:getCause	()Ljava/lang/Throwable;
    //   202: astore 7
    //   204: aload 7
    //   206: ifnull +6 -> 212
    //   209: aload 7
    //   211: athrow
    //   212: aload_1
    //   213: athrow
    //   214: iconst_4
    //   215: sipush 402
    //   218: iconst_0
    //   219: invokestatic 239	o/O:ˋ	(IIC)Ljava/lang/Object;
    //   222: checkcast 241	java/lang/Class
    //   225: ldc_w 263
    //   228: aconst_null
    //   229: invokevirtual 247	java/lang/Class:getMethod	(Ljava/lang/String;[Ljava/lang/Class;)Ljava/lang/reflect/Method;
    //   232: aload 7
    //   234: aconst_null
    //   235: invokevirtual 253	java/lang/reflect/Method:invoke	(Ljava/lang/Object;[Ljava/lang/Object;)Ljava/lang/Object;
    //   238: checkcast 257	java/lang/Boolean
    //   241: invokevirtual 261	java/lang/Boolean:booleanValue	()Z
    //   244: istore 4
    //   246: goto +20 -> 266
    //   249: astore_1
    //   250: aload_1
    //   251: invokevirtual 234	java/lang/Throwable:getCause	()Ljava/lang/Throwable;
    //   254: astore 7
    //   256: aload 7
    //   258: ifnull +6 -> 264
    //   261: aload 7
    //   263: athrow
    //   264: aload_1
    //   265: athrow
    //   266: iconst_4
    //   267: sipush 402
    //   270: iconst_0
    //   271: invokestatic 239	o/O:ˋ	(IIC)Ljava/lang/Object;
    //   274: checkcast 241	java/lang/Class
    //   277: ldc -13
    //   279: aconst_null
    //   280: invokevirtual 247	java/lang/Class:getMethod	(Ljava/lang/String;[Ljava/lang/Class;)Ljava/lang/reflect/Method;
    //   283: aconst_null
    //   284: aconst_null
    //   285: invokevirtual 253	java/lang/reflect/Method:invoke	(Ljava/lang/Object;[Ljava/lang/Object;)Ljava/lang/Object;
    //   288: astore 7
    //   290: goto +20 -> 310
    //   293: astore_1
    //   294: aload_1
    //   295: invokevirtual 234	java/lang/Throwable:getCause	()Ljava/lang/Throwable;
    //   298: astore 7
    //   300: aload 7
    //   302: ifnull +6 -> 308
    //   305: aload 7
    //   307: athrow
    //   308: aload_1
    //   309: athrow
    //   310: iconst_4
    //   311: sipush 402
    //   314: iconst_0
    //   315: invokestatic 239	o/O:ˋ	(IIC)Ljava/lang/Object;
    //   318: checkcast 241	java/lang/Class
    //   321: ldc_w 265
    //   324: aconst_null
    //   325: invokevirtual 247	java/lang/Class:getMethod	(Ljava/lang/String;[Ljava/lang/Class;)Ljava/lang/reflect/Method;
    //   328: aload 7
    //   330: aconst_null
    //   331: invokevirtual 253	java/lang/reflect/Method:invoke	(Ljava/lang/Object;[Ljava/lang/Object;)Ljava/lang/Object;
    //   334: checkcast 257	java/lang/Boolean
    //   337: invokevirtual 261	java/lang/Boolean:booleanValue	()Z
    //   340: istore 5
    //   342: goto +20 -> 362
    //   345: astore_1
    //   346: aload_1
    //   347: invokevirtual 234	java/lang/Throwable:getCause	()Ljava/lang/Throwable;
    //   350: astore 7
    //   352: aload 7
    //   354: ifnull +6 -> 360
    //   357: aload 7
    //   359: athrow
    //   360: aload_1
    //   361: athrow
    //   362: iconst_4
    //   363: sipush 402
    //   366: iconst_0
    //   367: invokestatic 239	o/O:ˋ	(IIC)Ljava/lang/Object;
    //   370: checkcast 241	java/lang/Class
    //   373: ldc -13
    //   375: aconst_null
    //   376: invokevirtual 247	java/lang/Class:getMethod	(Ljava/lang/String;[Ljava/lang/Class;)Ljava/lang/reflect/Method;
    //   379: aconst_null
    //   380: aconst_null
    //   381: invokevirtual 253	java/lang/reflect/Method:invoke	(Ljava/lang/Object;[Ljava/lang/Object;)Ljava/lang/Object;
    //   384: astore 7
    //   386: goto +20 -> 406
    //   389: astore_1
    //   390: aload_1
    //   391: invokevirtual 234	java/lang/Throwable:getCause	()Ljava/lang/Throwable;
    //   394: astore 7
    //   396: aload 7
    //   398: ifnull +6 -> 404
    //   401: aload 7
    //   403: athrow
    //   404: aload_1
    //   405: athrow
    //   406: iconst_4
    //   407: sipush 402
    //   410: iconst_0
    //   411: invokestatic 239	o/O:ˋ	(IIC)Ljava/lang/Object;
    //   414: checkcast 241	java/lang/Class
    //   417: ldc_w 267
    //   420: aconst_null
    //   421: invokevirtual 247	java/lang/Class:getMethod	(Ljava/lang/String;[Ljava/lang/Class;)Ljava/lang/reflect/Method;
    //   424: aload 7
    //   426: aconst_null
    //   427: invokevirtual 253	java/lang/reflect/Method:invoke	(Ljava/lang/Object;[Ljava/lang/Object;)Ljava/lang/Object;
    //   430: checkcast 257	java/lang/Boolean
    //   433: invokevirtual 261	java/lang/Boolean:booleanValue	()Z
    //   436: istore 6
    //   438: goto +20 -> 458
    //   441: astore_1
    //   442: aload_1
    //   443: invokevirtual 234	java/lang/Throwable:getCause	()Ljava/lang/Throwable;
    //   446: astore 7
    //   448: aload 7
    //   450: ifnull +6 -> 456
    //   453: aload 7
    //   455: athrow
    //   456: aload_1
    //   457: athrow
    //   458: iconst_4
    //   459: sipush 135
    //   462: ldc_w 268
    //   465: invokestatic 239	o/O:ˋ	(IIC)Ljava/lang/Object;
    //   468: checkcast 241	java/lang/Class
    //   471: ldc_w 269
    //   474: aconst_null
    //   475: invokevirtual 247	java/lang/Class:getMethod	(Ljava/lang/String;[Ljava/lang/Class;)Ljava/lang/reflect/Method;
    //   478: aconst_null
    //   479: aconst_null
    //   480: invokevirtual 253	java/lang/reflect/Method:invoke	(Ljava/lang/Object;[Ljava/lang/Object;)Ljava/lang/Object;
    //   483: checkcast 271	o/It
    //   486: astore 7
    //   488: aload 7
    //   490: new 273	o/EC
    //   493: dup
    //   494: aload_1
    //   495: iload_3
    //   496: iload 4
    //   498: iload 5
    //   500: iload 6
    //   502: invokespecial 276	o/EC:<init>	(Ljava/lang/String;ZZZZ)V
    //   505: invokeinterface 279 2 0
    //   510: new 9	o/MZ$2
    //   513: dup
    //   514: aload_0
    //   515: aload_0
    //   516: invokevirtual 124	o/MZ:ˋ	()Landroid/content/Context;
    //   519: aload_1
    //   520: invokespecial 282	o/MZ$2:<init>	(Lo/MZ;Landroid/content/Context;Ljava/lang/String;)V
    //   523: invokeinterface 287 2 0
    //   528: goto +31 -> 559
    //   531: iload_2
    //   532: tableswitch	default:+24->556, 0:+-524->8, 1:+-520->12
    //   556: goto -548 -> 8
    //   559: getstatic 34	o/MZ:ॱᐧ	I
    //   562: bipush 73
    //   564: iadd
    //   565: istore_2
    //   566: iload_2
    //   567: sipush 128
    //   570: irem
    //   571: putstatic 36	o/MZ:ॱꓸ	I
    //   574: iload_2
    //   575: iconst_2
    //   576: irem
    //   577: ifeq +6 -> 583
    //   580: goto -567 -> 13
    //   583: goto -580 -> 3
    //   586: goto -568 -> 18
    //   589: astore_1
    //   590: aload_1
    //   591: athrow
    // Local variable table:
    //   start	length	slot	name	signature
    //   0	592	0	this	MZ
    //   0	592	1	paramString	String
    //   4	573	2	i	int
    //   149	347	3	bool1	boolean
    //   244	253	4	bool2	boolean
    //   340	159	5	bool3	boolean
    //   436	65	6	bool4	boolean
    //   22	467	7	localObject	Object
    // Exception table:
    //   from	to	target	type
    //   76	100	59	finally
    //   120	150	103	finally
    //   170	194	153	finally
    //   214	246	197	finally
    //   266	290	249	finally
    //   310	342	293	finally
    //   362	386	345	finally
    //   406	438	389	finally
    //   458	488	441	finally
    //   18	24	589	java/lang/Exception
    //   24	38	589	java/lang/Exception
    //   38	44	589	java/lang/Exception
    //   44	50	589	java/lang/Exception
    //   50	56	589	java/lang/Exception
    //   60	66	589	java/lang/Exception
    //   71	74	589	java/lang/Exception
    //   74	76	589	java/lang/Exception
    //   104	110	589	java/lang/Exception
    //   115	118	589	java/lang/Exception
    //   118	120	589	java/lang/Exception
    //   154	160	589	java/lang/Exception
    //   165	168	589	java/lang/Exception
    //   168	170	589	java/lang/Exception
    //   198	204	589	java/lang/Exception
    //   209	212	589	java/lang/Exception
    //   212	214	589	java/lang/Exception
    //   250	256	589	java/lang/Exception
    //   261	264	589	java/lang/Exception
    //   264	266	589	java/lang/Exception
    //   294	300	589	java/lang/Exception
    //   305	308	589	java/lang/Exception
    //   308	310	589	java/lang/Exception
    //   346	352	589	java/lang/Exception
    //   357	360	589	java/lang/Exception
    //   360	362	589	java/lang/Exception
    //   390	396	589	java/lang/Exception
    //   401	404	589	java/lang/Exception
    //   404	406	589	java/lang/Exception
    //   442	448	589	java/lang/Exception
    //   453	456	589	java/lang/Exception
    //   456	458	589	java/lang/Exception
    //   488	528	589	java/lang/Exception
  }
  
  /* Error */
  private String ॱ(String paramString)
  {
    // Byte code:
    //   0: goto +306 -> 306
    //   3: iconst_0
    //   4: istore_3
    //   5: goto +470 -> 475
    //   8: aload 4
    //   10: arraylength
    //   11: istore_3
    //   12: iload_2
    //   13: iload_3
    //   14: if_icmpge +6 -> 20
    //   17: goto +292 -> 309
    //   20: goto +281 -> 301
    //   23: goto -15 -> 8
    //   26: aload_1
    //   27: iconst_4
    //   28: newarray char
    //   30: dup
    //   31: iconst_0
    //   32: ldc_w 293
    //   35: castore
    //   36: dup
    //   37: iconst_1
    //   38: ldc_w 294
    //   41: castore
    //   42: dup
    //   43: iconst_2
    //   44: ldc_w 295
    //   47: castore
    //   48: dup
    //   49: iconst_3
    //   50: ldc_w 296
    //   53: castore
    //   54: iconst_0
    //   55: bipush 10
    //   57: newarray char
    //   59: dup
    //   60: iconst_0
    //   61: ldc_w 297
    //   64: castore
    //   65: dup
    //   66: iconst_1
    //   67: ldc_w 298
    //   70: castore
    //   71: dup
    //   72: iconst_2
    //   73: ldc_w 299
    //   76: castore
    //   77: dup
    //   78: iconst_3
    //   79: ldc_w 300
    //   82: castore
    //   83: dup
    //   84: iconst_4
    //   85: ldc_w 301
    //   88: castore
    //   89: dup
    //   90: iconst_5
    //   91: ldc_w 302
    //   94: castore
    //   95: dup
    //   96: bipush 6
    //   98: ldc_w 303
    //   101: castore
    //   102: dup
    //   103: bipush 7
    //   105: ldc_w 304
    //   108: castore
    //   109: dup
    //   110: bipush 8
    //   112: ldc_w 305
    //   115: castore
    //   116: dup
    //   117: bipush 9
    //   119: ldc_w 306
    //   122: castore
    //   123: iconst_0
    //   124: iconst_4
    //   125: newarray char
    //   127: dup
    //   128: iconst_0
    //   129: ldc 71
    //   131: castore
    //   132: dup
    //   133: iconst_1
    //   134: ldc 71
    //   136: castore
    //   137: dup
    //   138: iconst_2
    //   139: ldc 71
    //   141: castore
    //   142: dup
    //   143: iconst_3
    //   144: ldc 71
    //   146: castore
    //   147: invokestatic 75	o/MZ:ॱ	([CC[CI[C)Ljava/lang/String;
    //   150: invokevirtual 81	java/lang/String:intern	()Ljava/lang/String;
    //   153: invokevirtual 310	java/lang/String:getBytes	(Ljava/lang/String;)[B
    //   156: astore 4
    //   158: aload 4
    //   160: arraylength
    //   161: newarray byte
    //   163: astore_1
    //   164: iconst_0
    //   165: istore_2
    //   166: goto -158 -> 8
    //   169: iload_3
    //   170: tableswitch	default:+22->192, 0:+22->192, 1:+216->386
    //   192: new 77	java/lang/String
    //   195: dup
    //   196: aload_1
    //   197: iconst_4
    //   198: newarray char
    //   200: dup
    //   201: iconst_0
    //   202: ldc_w 311
    //   205: castore
    //   206: dup
    //   207: iconst_1
    //   208: ldc_w 312
    //   211: castore
    //   212: dup
    //   213: iconst_2
    //   214: ldc_w 313
    //   217: castore
    //   218: dup
    //   219: iconst_3
    //   220: ldc_w 314
    //   223: castore
    //   224: sipush 19911
    //   227: iconst_5
    //   228: newarray char
    //   230: dup
    //   231: iconst_0
    //   232: ldc_w 315
    //   235: castore
    //   236: dup
    //   237: iconst_1
    //   238: ldc_w 316
    //   241: castore
    //   242: dup
    //   243: iconst_2
    //   244: ldc_w 317
    //   247: castore
    //   248: dup
    //   249: iconst_3
    //   250: ldc_w 318
    //   253: castore
    //   254: dup
    //   255: iconst_4
    //   256: ldc_w 319
    //   259: castore
    //   260: ldc_w 320
    //   263: iconst_4
    //   264: newarray char
    //   266: dup
    //   267: iconst_0
    //   268: ldc 71
    //   270: castore
    //   271: dup
    //   272: iconst_1
    //   273: ldc 71
    //   275: castore
    //   276: dup
    //   277: iconst_2
    //   278: ldc 71
    //   280: castore
    //   281: dup
    //   282: iconst_3
    //   283: ldc 71
    //   285: castore
    //   286: invokestatic 75	o/MZ:ॱ	([CC[CI[C)Ljava/lang/String;
    //   289: invokevirtual 81	java/lang/String:intern	()Ljava/lang/String;
    //   292: invokespecial 323	java/lang/String:<init>	([BLjava/lang/String;)V
    //   295: astore_1
    //   296: aload_1
    //   297: areturn
    //   298: astore_1
    //   299: aload_1
    //   300: athrow
    //   301: iconst_0
    //   302: istore_3
    //   303: goto -134 -> 169
    //   306: goto +197 -> 503
    //   309: iconst_1
    //   310: istore_3
    //   311: goto -142 -> 169
    //   314: iconst_0
    //   315: istore_3
    //   316: goto +131 -> 447
    //   319: iconst_1
    //   320: istore_3
    //   321: goto +154 -> 475
    //   324: getstatic 36	o/MZ:ॱꓸ	I
    //   327: bipush 125
    //   329: iadd
    //   330: istore_3
    //   331: iload_3
    //   332: sipush 128
    //   335: irem
    //   336: putstatic 34	o/MZ:ॱᐧ	I
    //   339: iload_3
    //   340: iconst_2
    //   341: irem
    //   342: ifne +6 -> 348
    //   345: goto +100 -> 445
    //   348: goto -34 -> 314
    //   351: astore_1
    //   352: new 325	java/lang/RuntimeException
    //   355: dup
    //   356: aload_1
    //   357: invokespecial 328	java/lang/RuntimeException:<init>	(Ljava/lang/Throwable;)V
    //   360: athrow
    //   361: aload_1
    //   362: iload_2
    //   363: aload 4
    //   365: aload 4
    //   367: arraylength
    //   368: iload_2
    //   369: isub
    //   370: iconst_1
    //   371: isub
    //   372: baload
    //   373: getstatic 46	o/MZ:ॱˍ	B
    //   376: ixor
    //   377: i2b
    //   378: bastore
    //   379: iload_2
    //   380: iconst_1
    //   381: iadd
    //   382: istore_2
    //   383: goto -59 -> 324
    //   386: getstatic 34	o/MZ:ॱᐧ	I
    //   389: bipush 113
    //   391: iadd
    //   392: istore_3
    //   393: iload_3
    //   394: sipush 128
    //   397: irem
    //   398: putstatic 36	o/MZ:ॱꓸ	I
    //   401: iload_3
    //   402: iconst_2
    //   403: irem
    //   404: ifeq +6 -> 410
    //   407: goto -88 -> 319
    //   410: goto -407 -> 3
    //   413: aload_1
    //   414: iload_2
    //   415: aload 4
    //   417: aload 4
    //   419: arraylength
    //   420: iload_2
    //   421: iadd
    //   422: iconst_1
    //   423: imul
    //   424: baload
    //   425: getstatic 46	o/MZ:ॱˍ	B
    //   428: iand
    //   429: i2b
    //   430: bastore
    //   431: iload_2
    //   432: bipush 7
    //   434: iadd
    //   435: istore_2
    //   436: goto -112 -> 324
    //   439: goto -431 -> 8
    //   442: astore_1
    //   443: aload_1
    //   444: athrow
    //   445: iconst_1
    //   446: istore_3
    //   447: iload_3
    //   448: tableswitch	default:+24->472, 0:+-9->439, 1:+-425->23
    //   472: goto -33 -> 439
    //   475: iload_3
    //   476: tableswitch	default:+24->500, 0:+-115->361, 1:+-63->413
    //   500: goto -87 -> 413
    //   503: getstatic 34	o/MZ:ॱᐧ	I
    //   506: bipush 43
    //   508: iadd
    //   509: istore_2
    //   510: iload_2
    //   511: sipush 128
    //   514: irem
    //   515: putstatic 36	o/MZ:ॱꓸ	I
    //   518: iload_2
    //   519: iconst_2
    //   520: irem
    //   521: ifeq +6 -> 527
    //   524: goto +6 -> 530
    //   527: goto -501 -> 26
    //   530: aload_1
    //   531: iconst_4
    //   532: newarray char
    //   534: dup
    //   535: iconst_0
    //   536: ldc_w 293
    //   539: castore
    //   540: dup
    //   541: iconst_1
    //   542: ldc_w 294
    //   545: castore
    //   546: dup
    //   547: iconst_2
    //   548: ldc_w 295
    //   551: castore
    //   552: dup
    //   553: iconst_3
    //   554: ldc_w 296
    //   557: castore
    //   558: iconst_0
    //   559: bipush 10
    //   561: newarray char
    //   563: dup
    //   564: iconst_0
    //   565: ldc_w 297
    //   568: castore
    //   569: dup
    //   570: iconst_1
    //   571: ldc_w 298
    //   574: castore
    //   575: dup
    //   576: iconst_2
    //   577: ldc_w 299
    //   580: castore
    //   581: dup
    //   582: iconst_3
    //   583: ldc_w 300
    //   586: castore
    //   587: dup
    //   588: iconst_4
    //   589: ldc_w 301
    //   592: castore
    //   593: dup
    //   594: iconst_5
    //   595: ldc_w 302
    //   598: castore
    //   599: dup
    //   600: bipush 6
    //   602: ldc_w 303
    //   605: castore
    //   606: dup
    //   607: bipush 7
    //   609: ldc_w 304
    //   612: castore
    //   613: dup
    //   614: bipush 8
    //   616: ldc_w 305
    //   619: castore
    //   620: dup
    //   621: bipush 9
    //   623: ldc_w 306
    //   626: castore
    //   627: iconst_0
    //   628: iconst_4
    //   629: newarray char
    //   631: dup
    //   632: iconst_0
    //   633: ldc 71
    //   635: castore
    //   636: dup
    //   637: iconst_1
    //   638: ldc 71
    //   640: castore
    //   641: dup
    //   642: iconst_2
    //   643: ldc 71
    //   645: castore
    //   646: dup
    //   647: iconst_3
    //   648: ldc 71
    //   650: castore
    //   651: invokestatic 75	o/MZ:ॱ	([CC[CI[C)Ljava/lang/String;
    //   654: invokevirtual 81	java/lang/String:intern	()Ljava/lang/String;
    //   657: invokevirtual 310	java/lang/String:getBytes	(Ljava/lang/String;)[B
    //   660: astore 4
    //   662: aload 4
    //   664: arraylength
    //   665: newarray byte
    //   667: astore_1
    //   668: iconst_1
    //   669: istore_2
    //   670: goto -662 -> 8
    // Local variable table:
    //   start	length	slot	name	signature
    //   0	673	0	this	MZ
    //   0	673	1	paramString	String
    //   12	658	2	i	int
    //   4	472	3	j	int
    //   8	655	4	arrayOfByte	byte[]
    // Exception table:
    //   from	to	target	type
    //   324	331	298	java/lang/Exception
    //   331	339	298	java/lang/Exception
    //   8	12	351	java/io/UnsupportedEncodingException
    //   26	164	351	java/io/UnsupportedEncodingException
    //   192	296	351	java/io/UnsupportedEncodingException
    //   361	379	351	java/io/UnsupportedEncodingException
    //   413	431	351	java/io/UnsupportedEncodingException
    //   530	668	351	java/io/UnsupportedEncodingException
    //   331	339	442	java/lang/Exception
  }
  
  private static String ॱ(char[] paramArrayOfChar1, char paramChar, char[] paramArrayOfChar2, int paramInt, char[] paramArrayOfChar3)
  {
    break label213;
    char c;
    if (paramChar >= c) {
      break label204;
    }
    for (;;)
    {
      try
      {
        paramInt = ॱꓸ;
        paramInt += 33;
        ॱᐧ = paramInt % 128;
        if (paramInt % 2 == 0) {
          break label210;
        }
        char[] arrayOfChar;
        switch (paramInt)
        {
        case 34: 
        default: 
          continue;
          continue;
          break;
          oJ.ˏ(paramArrayOfChar1, paramArrayOfChar3, paramChar);
          long l1 = paramArrayOfChar2[paramChar] ^ paramArrayOfChar1[((paramChar + '\003') % 4)];
          long l2 = ॱˑ;
          paramInt = ॱـ;
          arrayOfChar[paramChar] = ((char)(int)(l1 ^ l2 ^ paramInt ^ ॱᐨ));
          paramChar += '\001';
          break;
        case 27: 
          return new String(arrayOfChar);
          paramArrayOfChar1 = (char[])paramArrayOfChar1.clone();
          paramArrayOfChar3 = (char[])paramArrayOfChar3.clone();
          paramArrayOfChar1[0] = ((char)(paramArrayOfChar1[0] ^ paramChar));
          paramArrayOfChar3[2] = ((char)(paramArrayOfChar3[2] + (char)paramInt));
          c = paramArrayOfChar2.length;
          arrayOfChar = new char[c];
          paramChar = '\000';
        }
      }
      catch (Exception paramArrayOfChar1)
      {
        throw paramArrayOfChar1;
      }
      label204:
      paramInt = 27;
      continue;
      label210:
      continue;
      label213:
      break label222;
      paramInt = 34;
      continue;
      label222:
      c = ॱꓸ + 113;
      ॱᐧ = c % '';
      if (c % '\002' == 0) {}
    }
  }
  
  private void ॱॱ()
  {
    break label136;
    int j = 75;
    break label78;
    label9:
    j = 0;
    break label203;
    label14:
    int i;
    Object localObject2 = localObject1[i];
    this.ߺ.add(aq.ᐝ(localObject2.ˋ()));
    i += 1;
    break label192;
    Object localObject1 = new ArrayList();
    for (;;)
    {
      int k;
      try
      {
        this.ߺ = ((ArrayList)localObject1);
        localObject1 = Go.values();
        k = localObject1.length;
        i = 0;
        continue;
        j = 79;
        break label203;
        switch (j)
        {
        default: 
          label78:
          break label235;
          try
          {
            j = ॱꓸ;
            j += 83;
            ॱᐧ = j % 128;
            if (j % 2 == 0) {
              continue;
            }
          }
          catch (Exception localException1)
          {
            label136:
            throw localException1;
          }
        }
      }
      catch (Exception localException2)
      {
        throw localException2;
      }
      localObject2 = localObject1[i];
      this.ߺ.add(aq.ᐝ(localObject2.ˋ()));
      i += 101;
      label192:
      while (i < k)
      {
        j = 18;
        break;
        return;
      }
      break;
      label203:
      switch (j)
      {
      }
      break label14;
      label235:
      j = ॱꓸ;
      j += 87;
      ॱᐧ = j % 128;
      if (j % 2 == 0) {
        break label9;
      }
    }
  }
  
  static void ᐝ()
  {
    ॱᐨ = 56475;
    ॱˑ = 0L;
    ॱـ = 0;
  }
  
  /* Error */
  public void ˋ(ᐸ paramᐸ, ะ paramะ)
  {
    // Byte code:
    //   0: goto +234 -> 234
    //   3: bipush 61
    //   5: istore_3
    //   6: goto +165 -> 171
    //   9: goto +222 -> 231
    //   12: aload_0
    //   13: aload_0
    //   14: getfield 171	o/MZ:ߺ	Ljava/util/ArrayList;
    //   17: iload 4
    //   19: invokevirtual 184	java/util/ArrayList:get	(I)Ljava/lang/Object;
    //   22: checkcast 186	java/util/Locale
    //   25: invokevirtual 206	java/util/Locale:getLanguage	()Ljava/lang/String;
    //   28: invokestatic 209	o/aq:ˋॱ	(Ljava/lang/String;)Ljava/lang/String;
    //   31: invokespecial 368	o/MZ:ˏ	(Ljava/lang/String;)V
    //   34: goto +42 -> 76
    //   37: getstatic 34	o/MZ:ॱᐧ	I
    //   40: bipush 101
    //   42: iadd
    //   43: istore_3
    //   44: iload_3
    //   45: sipush 128
    //   48: irem
    //   49: putstatic 36	o/MZ:ॱꓸ	I
    //   52: iload_3
    //   53: iconst_2
    //   54: irem
    //   55: ifeq +6 -> 61
    //   58: goto +110 -> 168
    //   61: goto +142 -> 203
    //   64: astore_1
    //   65: aload_1
    //   66: athrow
    //   67: bipush 58
    //   69: istore_3
    //   70: goto +177 -> 247
    //   73: astore_1
    //   74: aload_1
    //   75: athrow
    //   76: getstatic 36	o/MZ:ॱꓸ	I
    //   79: bipush 73
    //   81: iadd
    //   82: istore_3
    //   83: iload_3
    //   84: sipush 128
    //   87: irem
    //   88: putstatic 34	o/MZ:ॱᐧ	I
    //   91: iload_3
    //   92: iconst_2
    //   93: irem
    //   94: ifne +6 -> 100
    //   97: goto -88 -> 9
    //   100: goto +131 -> 231
    //   103: aload_0
    //   104: getfield 171	o/MZ:ߺ	Ljava/util/ArrayList;
    //   107: astore_2
    //   108: aload_2
    //   109: iload 4
    //   111: invokevirtual 184	java/util/ArrayList:get	(I)Ljava/lang/Object;
    //   114: astore_2
    //   115: aload_2
    //   116: checkcast 186	java/util/Locale
    //   119: astore_2
    //   120: aload_0
    //   121: aload_2
    //   122: invokevirtual 206	java/util/Locale:getLanguage	()Ljava/lang/String;
    //   125: invokestatic 209	o/aq:ˋॱ	(Ljava/lang/String;)Ljava/lang/String;
    //   128: invokespecial 368	o/MZ:ˏ	(Ljava/lang/String;)V
    //   131: bipush 42
    //   133: iconst_0
    //   134: idiv
    //   135: istore_3
    //   136: goto -60 -> 76
    //   139: getstatic 36	o/MZ:ॱꓸ	I
    //   142: bipush 123
    //   144: iadd
    //   145: istore_3
    //   146: iload_3
    //   147: sipush 128
    //   150: irem
    //   151: putstatic 34	o/MZ:ॱᐧ	I
    //   154: iload_3
    //   155: iconst_2
    //   156: irem
    //   157: ifne +4 -> 161
    //   160: return
    //   161: return
    //   162: bipush 10
    //   164: istore_3
    //   165: goto +6 -> 171
    //   168: goto +35 -> 203
    //   171: iload_3
    //   172: lookupswitch	default:+28->200, 10:+107->279, 61:+65->237
    //   200: goto +37 -> 237
    //   203: getstatic 371	o/MZ$4:ˊ	[I
    //   206: aload_2
    //   207: invokevirtual 376	o/ะ:ordinal	()I
    //   210: iaload
    //   211: lookupswitch	default:+17->228, 1:+79->290
    //   228: goto +9 -> 237
    //   231: goto +6 -> 237
    //   234: goto -197 -> 37
    //   237: aload_1
    //   238: invokevirtual 381	o/ᐸ:dismiss	()V
    //   241: goto -102 -> 139
    //   244: bipush 14
    //   246: istore_3
    //   247: iload_3
    //   248: lookupswitch	default:+28->276, 14:+204->452, 58:+-11->237
    //   276: goto -39 -> 237
    //   279: iload 5
    //   281: ifne +6 -> 287
    //   284: goto -40 -> 244
    //   287: goto -220 -> 67
    //   290: aload_0
    //   291: getfield 152	o/MZ:ॱˈ	Landroid/databinding/ViewDataBinding;
    //   294: checkcast 154	o/MT
    //   297: getfield 157	o/MT:ˊ	Lo/IW;
    //   300: invokevirtual 383	o/IW:ˋ	()I
    //   303: istore 4
    //   305: aload_0
    //   306: getfield 171	o/MZ:ߺ	Ljava/util/ArrayList;
    //   309: iload 4
    //   311: invokevirtual 184	java/util/ArrayList:get	(I)Ljava/lang/Object;
    //   314: checkcast 186	java/util/Locale
    //   317: invokevirtual 206	java/util/Locale:getLanguage	()Ljava/lang/String;
    //   320: aload_0
    //   321: getfield 111	o/MZ:ॱˉ	Ljava/lang/String;
    //   324: invokestatic 385	o/aq:ʽ	(Ljava/lang/String;)Ljava/lang/String;
    //   327: invokevirtual 213	java/lang/String:equals	(Ljava/lang/Object;)Z
    //   330: istore 5
    //   332: goto +17 -> 349
    //   335: astore_1
    //   336: aload_1
    //   337: invokevirtual 234	java/lang/Throwable:getCause	()Ljava/lang/Throwable;
    //   340: astore_2
    //   341: aload_2
    //   342: ifnull +5 -> 347
    //   345: aload_2
    //   346: athrow
    //   347: aload_1
    //   348: athrow
    //   349: iconst_3
    //   350: bipush 24
    //   352: iconst_0
    //   353: invokestatic 239	o/O:ˋ	(IIC)Ljava/lang/Object;
    //   356: checkcast 241	java/lang/Class
    //   359: ldc_w 386
    //   362: aconst_null
    //   363: invokevirtual 247	java/lang/Class:getMethod	(Ljava/lang/String;[Ljava/lang/Class;)Ljava/lang/reflect/Method;
    //   366: aconst_null
    //   367: aconst_null
    //   368: invokevirtual 253	java/lang/reflect/Method:invoke	(Ljava/lang/Object;[Ljava/lang/Object;)Ljava/lang/Object;
    //   371: astore_2
    //   372: aload_0
    //   373: invokevirtual 124	o/MZ:ˋ	()Landroid/content/Context;
    //   376: astore 7
    //   378: goto +17 -> 395
    //   381: astore_1
    //   382: aload_1
    //   383: invokevirtual 234	java/lang/Throwable:getCause	()Ljava/lang/Throwable;
    //   386: astore_2
    //   387: aload_2
    //   388: ifnull +5 -> 393
    //   391: aload_2
    //   392: athrow
    //   393: aload_1
    //   394: athrow
    //   395: iconst_3
    //   396: bipush 24
    //   398: iconst_0
    //   399: invokestatic 239	o/O:ˋ	(IIC)Ljava/lang/Object;
    //   402: checkcast 241	java/lang/Class
    //   405: ldc_w 387
    //   408: iconst_1
    //   409: anewarray 241	java/lang/Class
    //   412: dup
    //   413: iconst_0
    //   414: ldc 58
    //   416: aastore
    //   417: invokevirtual 247	java/lang/Class:getMethod	(Ljava/lang/String;[Ljava/lang/Class;)Ljava/lang/reflect/Method;
    //   420: aload_2
    //   421: iconst_1
    //   422: anewarray 389	java/lang/Object
    //   425: dup
    //   426: iconst_0
    //   427: aload 7
    //   429: aastore
    //   430: invokevirtual 253	java/lang/reflect/Method:invoke	(Ljava/lang/Object;[Ljava/lang/Object;)Ljava/lang/Object;
    //   433: checkcast 257	java/lang/Boolean
    //   436: invokevirtual 261	java/lang/Boolean:booleanValue	()Z
    //   439: istore 6
    //   441: iload 6
    //   443: ifeq +6 -> 449
    //   446: goto -284 -> 162
    //   449: goto -446 -> 3
    //   452: getstatic 34	o/MZ:ॱᐧ	I
    //   455: bipush 17
    //   457: iadd
    //   458: istore_3
    //   459: iload_3
    //   460: sipush 128
    //   463: irem
    //   464: putstatic 36	o/MZ:ॱꓸ	I
    //   467: iload_3
    //   468: iconst_2
    //   469: irem
    //   470: ifeq +6 -> 476
    //   473: goto -370 -> 103
    //   476: goto -464 -> 12
    // Local variable table:
    //   start	length	slot	name	signature
    //   0	479	0	this	MZ
    //   0	479	1	paramᐸ	ᐸ
    //   0	479	2	paramะ	ะ
    //   5	465	3	i	int
    //   17	293	4	j	int
    //   279	52	5	bool1	boolean
    //   439	3	6	bool2	boolean
    //   376	52	7	localContext	Context
    // Exception table:
    //   from	to	target	type
    //   115	120	64	java/lang/Exception
    //   139	146	64	java/lang/Exception
    //   146	154	64	java/lang/Exception
    //   103	108	73	java/lang/Exception
    //   108	115	73	java/lang/Exception
    //   349	372	335	finally
    //   395	441	381	finally
  }
  
  /* Error */
  public int ˎ()
  {
    // Byte code:
    //   0: goto +39 -> 39
    //   3: iload_2
    //   4: ireturn
    //   5: bipush 18
    //   7: istore_1
    //   8: iload_1
    //   9: lookupswitch	default:+27->36, 18:+33->42, 48:+-6->3
    //   36: goto +6 -> 42
    //   39: goto +17 -> 56
    //   42: new 38	java/lang/NullPointerException
    //   45: dup
    //   46: invokespecial 41	java/lang/NullPointerException:<init>	()V
    //   49: athrow
    //   50: bipush 48
    //   52: istore_1
    //   53: goto -45 -> 8
    //   56: getstatic 36	o/MZ:ॱꓸ	I
    //   59: bipush 101
    //   61: iadd
    //   62: istore_1
    //   63: iload_1
    //   64: sipush 128
    //   67: irem
    //   68: putstatic 34	o/MZ:ॱᐧ	I
    //   71: iload_1
    //   72: iconst_2
    //   73: irem
    //   74: ifne +6 -> 80
    //   77: goto +6 -> 83
    //   80: goto +41 -> 121
    //   83: goto +38 -> 121
    //   86: astore_3
    //   87: aload_3
    //   88: athrow
    //   89: astore_3
    //   90: aload_3
    //   91: athrow
    //   92: getstatic 36	o/MZ:ॱꓸ	I
    //   95: istore_1
    //   96: iload_1
    //   97: bipush 31
    //   99: iadd
    //   100: istore_1
    //   101: iload_1
    //   102: sipush 128
    //   105: irem
    //   106: putstatic 34	o/MZ:ॱᐧ	I
    //   109: iload_1
    //   110: iconst_2
    //   111: irem
    //   112: ifne +6 -> 118
    //   115: goto -110 -> 5
    //   118: goto -68 -> 50
    //   121: getstatic 394	o/MH$if:dialog_select_language	I
    //   124: istore_2
    //   125: goto -33 -> 92
    // Local variable table:
    //   start	length	slot	name	signature
    //   0	128	0	this	MZ
    //   7	105	1	i	int
    //   3	122	2	j	int
    //   86	2	3	localException1	Exception
    //   89	2	3	localException2	Exception
    // Exception table:
    //   from	to	target	type
    //   101	109	86	java/lang/Exception
    //   92	96	89	java/lang/Exception
  }
}
