package o;

import android.content.res.Resources;
import android.databinding.ViewDataBinding;
import android.databinding.ViewDataBinding.If;
import android.util.SparseIntArray;
import android.view.View;
import android.widget.Button;
import android.widget.ImageView;
import android.widget.RelativeLayout;
import android.widget.ScrollView;
import android.widget.TextView;

public class Mz
  extends ViewDataBinding
{
  private static long ʼॱ;
  private static int ʽॱ;
  private static char ʾ;
  private static int ʿ;
  private static int ˈ;
  private static final SparseIntArray ˋॱ;
  private static final ViewDataBinding.If ॱˊ;
  private static byte ॱˋ;
  public final ImageView ʻ;
  private ˍ ʻॱ = new ˍ()
  {
    public void ˊ()
    {
      String str = Mz.this.ʼ.ʼ();
      Object localObject = Mz.ˊ(Mz.this);
      int i;
      if (localObject != null) {
        i = 1;
      } else {
        i = 0;
      }
      if (i != 0)
      {
        localObject = ((Is)localObject).transferDetail;
        if (localObject != null) {
          i = 1;
        } else {
          i = 0;
        }
        if (i != 0) {
          ((ـ)localObject).ˎ(str);
        }
      }
    }
  };
  public final Jc ʼ;
  public final ImageView ʽ;
  public final KQ ˊ;
  private final Button ˊॱ;
  public final ImageView ˎ;
  private boolean ˏॱ;
  private final RelativeLayout ͺ;
  public final Ja ॱ;
  private boolean ॱˎ;
  public final у ॱॱ;
  private Is ॱᐝ;
  public final ScrollView ᐝ;
  private long ᐝॱ = -1L;
  
  static
  {
    for (;;)
    {
      try
      {
        ˈ = 0;
        ʿ = 1;
        ͺ();
        ˋॱ();
        try
        {
          ॱˊ = null;
          ˋॱ = new SparseIntArray();
          ˋॱ.put(2131296628, 8);
          ˋॱ.put(2131296314, 9);
        }
        catch (Exception localException1)
        {
          throw localException1;
        }
        i = 47;
        continue;
        i = 46;
        switch (i)
        {
        default: 
          break;
        case 46: 
          return;
        }
        i = 77 / 0;
        return;
      }
      catch (Exception localException2)
      {
        int i;
        throw localException2;
      }
      i = ʿ + 99;
      ˈ = i % 128;
      if (i % 2 != 0) {}
    }
  }
  
  public Mz(ˉ paramˉ, View paramView)
  {
    super(paramˉ, paramView, 3);
    paramˉ = ॱ(paramˉ, paramView, 10, ॱˊ, ˋॱ);
    this.ˎ = ((ImageView)paramˉ[9]);
    this.ˊ = ((KQ)paramˉ[3]);
    this.ˊ.setTag(null);
    this.ॱ = ((Ja)paramˉ[5]);
    this.ॱ.setTag(null);
    this.ʻ = ((ImageView)paramˉ[4]);
    this.ʻ.setTag(null);
    this.ʼ = ((Jc)paramˉ[6]);
    this.ʼ.setTag(null);
    this.ʽ = ((ImageView)paramˉ[1]);
    this.ʽ.setTag(null);
    this.ͺ = ((RelativeLayout)paramˉ[0]);
    this.ͺ.setTag(null);
    this.ˊॱ = ((Button)paramˉ[7]);
    this.ˊॱ.setTag(null);
    this.ᐝ = ((ScrollView)paramˉ[8]);
    this.ॱॱ = ((у)paramˉ[2]);
    this.ॱॱ.setTag(null);
    ˋ(paramView);
    ˊॱ();
  }
  
  /* Error */
  private String ˋ(String paramString)
  {
    // Byte code:
    //   0: goto +246 -> 246
    //   3: iload_3
    //   4: istore_2
    //   5: goto +216 -> 221
    //   8: getstatic 54	o/Mz:ʿ	I
    //   11: bipush 67
    //   13: iadd
    //   14: istore_2
    //   15: iload_2
    //   16: sipush 128
    //   19: irem
    //   20: putstatic 52	o/Mz:ˈ	I
    //   23: iload_2
    //   24: iconst_2
    //   25: irem
    //   26: ifeq +6 -> 32
    //   29: goto +6 -> 35
    //   32: goto +43 -> 75
    //   35: bipush 11
    //   37: istore_2
    //   38: goto +8 -> 46
    //   41: iconst_0
    //   42: istore_2
    //   43: goto +236 -> 279
    //   46: iload_2
    //   47: lookupswitch	default:+25->72, 11:+-44->3, 98:+227->274
    //   72: goto -69 -> 3
    //   75: bipush 98
    //   77: istore_2
    //   78: goto -32 -> 46
    //   81: astore_1
    //   82: new 150	java/lang/RuntimeException
    //   85: dup
    //   86: aload_1
    //   87: invokespecial 153	java/lang/RuntimeException:<init>	(Ljava/lang/Throwable;)V
    //   90: athrow
    //   91: aload_1
    //   92: iconst_4
    //   93: newarray char
    //   95: dup
    //   96: iconst_0
    //   97: ldc -102
    //   99: castore
    //   100: dup
    //   101: iconst_1
    //   102: ldc -101
    //   104: castore
    //   105: dup
    //   106: iconst_2
    //   107: ldc -100
    //   109: castore
    //   110: dup
    //   111: iconst_3
    //   112: ldc -99
    //   114: castore
    //   115: iconst_0
    //   116: bipush 10
    //   118: newarray char
    //   120: dup
    //   121: iconst_0
    //   122: ldc -98
    //   124: castore
    //   125: dup
    //   126: iconst_1
    //   127: ldc -97
    //   129: castore
    //   130: dup
    //   131: iconst_2
    //   132: ldc -96
    //   134: castore
    //   135: dup
    //   136: iconst_3
    //   137: ldc -95
    //   139: castore
    //   140: dup
    //   141: iconst_4
    //   142: ldc -94
    //   144: castore
    //   145: dup
    //   146: iconst_5
    //   147: ldc -93
    //   149: castore
    //   150: dup
    //   151: bipush 6
    //   153: ldc -92
    //   155: castore
    //   156: dup
    //   157: bipush 7
    //   159: ldc -91
    //   161: castore
    //   162: dup
    //   163: bipush 8
    //   165: ldc -90
    //   167: castore
    //   168: dup
    //   169: bipush 9
    //   171: ldc -89
    //   173: castore
    //   174: iconst_0
    //   175: iconst_4
    //   176: newarray char
    //   178: dup
    //   179: iconst_0
    //   180: ldc -88
    //   182: castore
    //   183: dup
    //   184: iconst_1
    //   185: ldc -87
    //   187: castore
    //   188: dup
    //   189: iconst_2
    //   190: ldc -86
    //   192: castore
    //   193: dup
    //   194: iconst_3
    //   195: ldc -85
    //   197: castore
    //   198: invokestatic 174	o/Mz:ˋ	([CC[CI[C)Ljava/lang/String;
    //   201: invokevirtual 180	java/lang/String:intern	()Ljava/lang/String;
    //   204: invokevirtual 184	java/lang/String:getBytes	(Ljava/lang/String;)[B
    //   207: astore 4
    //   209: aload 4
    //   211: arraylength
    //   212: newarray byte
    //   214: astore_1
    //   215: goto +26 -> 241
    //   218: astore_1
    //   219: aload_1
    //   220: athrow
    //   221: aload 4
    //   223: arraylength
    //   224: istore_3
    //   225: iload_2
    //   226: iload_3
    //   227: if_icmpge +6 -> 233
    //   230: goto +19 -> 249
    //   233: goto +227 -> 460
    //   236: iconst_1
    //   237: istore_2
    //   238: goto +41 -> 279
    //   241: iconst_0
    //   242: istore_2
    //   243: goto -22 -> 221
    //   246: goto +185 -> 431
    //   249: aload_1
    //   250: iload_2
    //   251: aload 4
    //   253: aload 4
    //   255: arraylength
    //   256: iload_2
    //   257: isub
    //   258: iconst_1
    //   259: isub
    //   260: baload
    //   261: getstatic 186	o/Mz:ॱˋ	B
    //   264: ixor
    //   265: i2b
    //   266: bastore
    //   267: iload_2
    //   268: iconst_1
    //   269: iadd
    //   270: istore_3
    //   271: goto -263 -> 8
    //   274: iload_3
    //   275: istore_2
    //   276: goto -55 -> 221
    //   279: iload_2
    //   280: tableswitch	default:+24->304, 0:+-189->91, 1:+24->304
    //   304: aload_1
    //   305: iconst_4
    //   306: newarray char
    //   308: dup
    //   309: iconst_0
    //   310: ldc -102
    //   312: castore
    //   313: dup
    //   314: iconst_1
    //   315: ldc -101
    //   317: castore
    //   318: dup
    //   319: iconst_2
    //   320: ldc -100
    //   322: castore
    //   323: dup
    //   324: iconst_3
    //   325: ldc -99
    //   327: castore
    //   328: iconst_0
    //   329: bipush 10
    //   331: newarray char
    //   333: dup
    //   334: iconst_0
    //   335: ldc -98
    //   337: castore
    //   338: dup
    //   339: iconst_1
    //   340: ldc -97
    //   342: castore
    //   343: dup
    //   344: iconst_2
    //   345: ldc -96
    //   347: castore
    //   348: dup
    //   349: iconst_3
    //   350: ldc -95
    //   352: castore
    //   353: dup
    //   354: iconst_4
    //   355: ldc -94
    //   357: castore
    //   358: dup
    //   359: iconst_5
    //   360: ldc -93
    //   362: castore
    //   363: dup
    //   364: bipush 6
    //   366: ldc -92
    //   368: castore
    //   369: dup
    //   370: bipush 7
    //   372: ldc -91
    //   374: castore
    //   375: dup
    //   376: bipush 8
    //   378: ldc -90
    //   380: castore
    //   381: dup
    //   382: bipush 9
    //   384: ldc -89
    //   386: castore
    //   387: iconst_1
    //   388: iconst_4
    //   389: newarray char
    //   391: dup
    //   392: iconst_0
    //   393: ldc -88
    //   395: castore
    //   396: dup
    //   397: iconst_1
    //   398: ldc -87
    //   400: castore
    //   401: dup
    //   402: iconst_2
    //   403: ldc -86
    //   405: castore
    //   406: dup
    //   407: iconst_3
    //   408: ldc -85
    //   410: castore
    //   411: invokestatic 174	o/Mz:ˋ	([CC[CI[C)Ljava/lang/String;
    //   414: invokevirtual 180	java/lang/String:intern	()Ljava/lang/String;
    //   417: invokevirtual 184	java/lang/String:getBytes	(Ljava/lang/String;)[B
    //   420: astore 4
    //   422: aload 4
    //   424: arraylength
    //   425: newarray byte
    //   427: astore_1
    //   428: goto -187 -> 241
    //   431: getstatic 52	o/Mz:ˈ	I
    //   434: istore_2
    //   435: iload_2
    //   436: bipush 65
    //   438: iadd
    //   439: istore_2
    //   440: iload_2
    //   441: sipush 128
    //   444: irem
    //   445: putstatic 54	o/Mz:ʿ	I
    //   448: iload_2
    //   449: iconst_2
    //   450: irem
    //   451: ifne +6 -> 457
    //   454: goto -218 -> 236
    //   457: goto -416 -> 41
    //   460: new 176	java/lang/String
    //   463: dup
    //   464: aload_1
    //   465: iconst_4
    //   466: newarray char
    //   468: dup
    //   469: iconst_0
    //   470: ldc -69
    //   472: castore
    //   473: dup
    //   474: iconst_1
    //   475: ldc -68
    //   477: castore
    //   478: dup
    //   479: iconst_2
    //   480: ldc -67
    //   482: castore
    //   483: dup
    //   484: iconst_3
    //   485: ldc -66
    //   487: castore
    //   488: ldc -65
    //   490: iconst_5
    //   491: newarray char
    //   493: dup
    //   494: iconst_0
    //   495: ldc -64
    //   497: castore
    //   498: dup
    //   499: iconst_1
    //   500: ldc -63
    //   502: castore
    //   503: dup
    //   504: iconst_2
    //   505: ldc -62
    //   507: castore
    //   508: dup
    //   509: iconst_3
    //   510: ldc -61
    //   512: castore
    //   513: dup
    //   514: iconst_4
    //   515: ldc -60
    //   517: castore
    //   518: ldc -59
    //   520: iconst_4
    //   521: newarray char
    //   523: dup
    //   524: iconst_0
    //   525: ldc -88
    //   527: castore
    //   528: dup
    //   529: iconst_1
    //   530: ldc -87
    //   532: castore
    //   533: dup
    //   534: iconst_2
    //   535: ldc -86
    //   537: castore
    //   538: dup
    //   539: iconst_3
    //   540: ldc -85
    //   542: castore
    //   543: invokestatic 174	o/Mz:ˋ	([CC[CI[C)Ljava/lang/String;
    //   546: invokevirtual 180	java/lang/String:intern	()Ljava/lang/String;
    //   549: invokespecial 200	java/lang/String:<init>	([BLjava/lang/String;)V
    //   552: astore_1
    //   553: aload_1
    //   554: areturn
    // Local variable table:
    //   start	length	slot	name	signature
    //   0	555	0	this	Mz
    //   0	555	1	paramString	String
    //   4	447	2	i	int
    //   3	272	3	j	int
    //   207	216	4	arrayOfByte	byte[]
    // Exception table:
    //   from	to	target	type
    //   91	215	81	java/io/UnsupportedEncodingException
    //   221	225	81	java/io/UnsupportedEncodingException
    //   249	267	81	java/io/UnsupportedEncodingException
    //   304	428	81	java/io/UnsupportedEncodingException
    //   460	553	81	java/io/UnsupportedEncodingException
    //   431	435	218	java/lang/Exception
    //   440	448	218	java/lang/Exception
  }
  
  /* Error */
  private static String ˋ(char[] paramArrayOfChar1, char paramChar, char[] paramArrayOfChar2, int paramInt, char[] paramArrayOfChar3)
  {
    // Byte code:
    //   0: goto +206 -> 206
    //   3: goto +137 -> 140
    //   6: getstatic 52	o/Mz:ˈ	I
    //   9: bipush 117
    //   11: iadd
    //   12: istore 5
    //   14: iload 5
    //   16: sipush 128
    //   19: irem
    //   20: putstatic 54	o/Mz:ʿ	I
    //   23: iload 5
    //   25: iconst_2
    //   26: irem
    //   27: ifne +6 -> 33
    //   30: goto -27 -> 3
    //   33: goto +107 -> 140
    //   36: new 176	java/lang/String
    //   39: dup
    //   40: aload 6
    //   42: invokespecial 203	java/lang/String:<init>	([C)V
    //   45: areturn
    //   46: goto +45 -> 91
    //   49: iload_1
    //   50: iload 5
    //   52: if_icmpge +6 -> 58
    //   55: goto +145 -> 200
    //   58: goto +136 -> 194
    //   61: iload_3
    //   62: lookupswitch	default:+26->88, 35:+-26->36, 76:+153->215
    //   88: goto -52 -> 36
    //   91: aload_0
    //   92: aload 4
    //   94: iload_1
    //   95: invokestatic 209	o/oJ:ˏ	([C[CI)V
    //   98: aload 6
    //   100: iload_1
    //   101: aload_2
    //   102: iload_1
    //   103: caload
    //   104: aload_0
    //   105: iload_1
    //   106: iconst_3
    //   107: iadd
    //   108: iconst_4
    //   109: irem
    //   110: caload
    //   111: ixor
    //   112: i2l
    //   113: getstatic 211	o/Mz:ʼॱ	J
    //   116: lxor
    //   117: getstatic 213	o/Mz:ʽॱ	I
    //   120: i2l
    //   121: lxor
    //   122: getstatic 215	o/Mz:ʾ	C
    //   125: i2l
    //   126: lxor
    //   127: l2i
    //   128: i2c
    //   129: castore
    //   130: iload_1
    //   131: iconst_1
    //   132: iadd
    //   133: istore_1
    //   134: goto -85 -> 49
    //   137: astore_0
    //   138: aload_0
    //   139: athrow
    //   140: aload_0
    //   141: invokevirtual 221	[C:clone	()Ljava/lang/Object;
    //   144: checkcast 217	[C
    //   147: astore_0
    //   148: aload 4
    //   150: invokevirtual 221	[C:clone	()Ljava/lang/Object;
    //   153: checkcast 217	[C
    //   156: astore 4
    //   158: aload_0
    //   159: iconst_0
    //   160: aload_0
    //   161: iconst_0
    //   162: caload
    //   163: iload_1
    //   164: ixor
    //   165: i2c
    //   166: castore
    //   167: aload 4
    //   169: iconst_2
    //   170: aload 4
    //   172: iconst_2
    //   173: caload
    //   174: iload_3
    //   175: i2c
    //   176: iadd
    //   177: i2c
    //   178: castore
    //   179: aload_2
    //   180: arraylength
    //   181: istore 5
    //   183: iload 5
    //   185: newarray char
    //   187: astore 6
    //   189: iconst_0
    //   190: istore_1
    //   191: goto +18 -> 209
    //   194: bipush 35
    //   196: istore_3
    //   197: goto -136 -> 61
    //   200: bipush 76
    //   202: istore_3
    //   203: goto -142 -> 61
    //   206: goto -200 -> 6
    //   209: goto -160 -> 49
    //   212: astore_0
    //   213: aload_0
    //   214: athrow
    //   215: getstatic 54	o/Mz:ʿ	I
    //   218: istore_3
    //   219: iload_3
    //   220: bipush 39
    //   222: iadd
    //   223: istore_3
    //   224: iload_3
    //   225: sipush 128
    //   228: irem
    //   229: putstatic 52	o/Mz:ˈ	I
    //   232: iload_3
    //   233: iconst_2
    //   234: irem
    //   235: ifeq +6 -> 241
    //   238: goto -192 -> 46
    //   241: goto -150 -> 91
    // Local variable table:
    //   start	length	slot	name	signature
    //   0	244	0	paramArrayOfChar1	char[]
    //   0	244	1	paramChar	char
    //   0	244	2	paramArrayOfChar2	char[]
    //   0	244	3	paramInt	int
    //   0	244	4	paramArrayOfChar3	char[]
    //   12	172	5	c	char
    //   40	148	6	arrayOfChar	char[]
    // Exception table:
    //   from	to	target	type
    //   224	232	137	java/lang/Exception
    //   215	219	212	java/lang/Exception
  }
  
  private boolean ˋ(ـ<String> paramـ, int paramInt)
  {
    if (paramInt == 0)
    {
      try
      {
        this.ᐝॱ |= 0x4;
      }
      finally
      {
        paramـ = finally;
        throw paramـ;
      }
      return true;
    }
    return false;
  }
  
  static void ˋॱ()
  {
    break label38;
    ॱˋ = -102;
    break label41;
    label38:
    for (;;)
    {
      i = ʿ + 81;
      ˈ = i % 128;
      if (i % 2 != 0) {
        break;
      }
      break;
    }
    label41:
    int i = ʿ + 47;
    ˈ = i % 128;
    if (i % 2 != 0) {}
  }
  
  private boolean ˏ(ـ<FQ> paramـ, int paramInt)
  {
    if (paramInt == 0)
    {
      try
      {
        this.ᐝॱ |= 1L;
      }
      finally
      {
        paramـ = finally;
        throw paramـ;
      }
      return true;
    }
    return false;
  }
  
  static void ͺ()
  {
    ʾ = '\000';
    ʼॱ = 4856866881160445592L;
    ʽॱ = 0;
  }
  
  private boolean ॱ(ـ<FS> paramـ, int paramInt)
  {
    if (paramInt == 0)
    {
      try
      {
        this.ᐝॱ |= 0x2;
      }
      finally
      {
        paramـ = finally;
        throw paramـ;
      }
      return true;
    }
    return false;
  }
  
  public void ˊॱ()
  {
    try
    {
      this.ᐝॱ = 64L;
    }
    finally
    {
      localObject = finally;
      throw localObject;
    }
    ʽ();
  }
  
  public void ˎ(boolean paramBoolean)
  {
    this.ॱˎ = paramBoolean;
    try
    {
      this.ᐝॱ |= 0x10;
    }
    finally
    {
      localObject = finally;
      throw localObject;
    }
    ˊ(68);
    super.ʽ();
  }
  
  public void ˏ()
  {
    try
    {
      l2 = this.ᐝॱ;
      this.ᐝॱ = 0L;
    }
    finally
    {
      localObject1 = finally;
      throw localObject1;
    }
    boolean bool1 = this.ˏॱ;
    Object localObject2 = null;
    Object localObject6 = null;
    Object localObject4 = null;
    Object localObject7 = null;
    Object localObject16 = null;
    Object localObject15 = null;
    Object localObject5 = null;
    boolean bool2 = this.ॱˎ;
    int i = 0;
    int j = 0;
    Object localObject13 = null;
    Object localObject9 = null;
    Object localObject12 = null;
    Is localIs = this.ॱᐝ;
    Object localObject11 = null;
    Object localObject10 = null;
    Object localObject14 = null;
    ـ localـ = null;
    long l1 = l2;
    if ((0x48 & l2) != 0L)
    {
      l1 = l2;
      if ((0x48 & l2) != 0L) {
        if (bool1) {
          l1 = l2 | 0x100;
        } else {
          l1 = l2 | 0x80;
        }
      }
      if (bool1) {
        i = 0;
      } else {
        i = 8;
      }
    }
    long l2 = l1;
    if ((0x50 & l1) != 0L)
    {
      l2 = l1;
      if ((0x50 & l1) != 0L) {
        if (bool2) {
          l2 = l1 | 0x400;
        } else {
          l2 = l1 | 0x200;
        }
      }
      if (bool2) {
        j = 4;
      } else {
        j = 0;
      }
    }
    Object localObject8 = localObject11;
    Object localObject3;
    if ((0x67 & l2) != 0L)
    {
      localObject3 = localObject16;
      if ((0x60 & l2) != 0L)
      {
        if (localIs != null)
        {
          localObject4 = localIs.amount;
          localObject5 = localIs.currency;
        }
        localObject2 = localObject4;
        localObject3 = localObject16;
        if (localObject5 != null)
        {
          localObject3 = ((Ep)localObject5).name();
          localObject2 = localObject4;
        }
      }
      localObject4 = localObject14;
      if ((0x61 & l2) != 0L)
      {
        localObject5 = localObject15;
        if (localIs != null) {
          localObject5 = localIs.phoneNumber;
        }
        ˎ(0, (ˑ)localObject5);
        localObject4 = localObject14;
        if (localObject5 != null) {
          localObject4 = (FQ)((ـ)localObject5).ˏ();
        }
      }
      localObject5 = localObject12;
      if ((0x62 & l2) != 0L)
      {
        localObject6 = localObject13;
        if (localIs != null) {
          localObject6 = localIs.contactPerson;
        }
        ˎ(1, (ˑ)localObject6);
        localObject5 = localObject12;
        if (localObject6 != null) {
          localObject5 = (FS)((ـ)localObject6).ˏ();
        }
      }
      localObject6 = localObject2;
      localObject7 = localObject3;
      localObject9 = localObject5;
      localObject8 = localObject11;
      localObject10 = localObject4;
      if ((0x64 & l2) != 0L)
      {
        if (localIs != null) {
          localـ = localIs.transferDetail;
        }
        ˎ(2, localـ);
        localObject6 = localObject2;
        localObject7 = localObject3;
        localObject9 = localObject5;
        localObject8 = localObject11;
        localObject10 = localObject4;
        if (localـ != null)
        {
          localObject8 = (String)localـ.ˏ();
          localObject10 = localObject4;
          localObject9 = localObject5;
          localObject7 = localObject3;
          localObject6 = localObject2;
        }
      }
    }
    if ((0x62 & l2) != 0L) {
      this.ˊ.setContactPerson(localObject9);
    }
    if ((0x61 & l2) != 0L) {
      this.ˊ.setPhoneNumber(localObject10);
    }
    if ((0x40 & l2) != 0L)
    {
      this.ˊ.setShowPhoneType(true);
      localObject4 = this.ॱ;
      localObject3 = this.ॱ.getResources().getString(2131755481);
      localObject2 = localObject3;
      if (((String)localObject3).startsWith(ˋ(new char[] { -4221, -2293, -4698, -3489 }, '忭', new char[] { -28713, 19122, 6877, -21044 }, 0, new char[] { 32408, 5357, 3762, 17255 }).intern())) {
        localObject2 = ˋ(((String)localObject3).substring(4)).intern();
      }
      ((Ja)localObject4).setHintText((String)localObject2);
      localObject4 = this.ʼ;
      localObject3 = this.ʼ.getResources().getString(2131755482);
      localObject2 = localObject3;
      if (((String)localObject3).startsWith(ˋ(new char[] { -4221, -2293, -4698, -3489 }, '忭', new char[] { -28713, 19122, 6877, -21044 }, 0, new char[] { 32408, 5357, 3762, 17255 }).intern())) {
        localObject2 = ˋ(((String)localObject3).substring(4)).intern();
      }
      ((Jc)localObject4).setHintText((String)localObject2);
      Jq.ˋ(this.ʼ, this.ʻॱ);
      this.ʼ.setInputType(16385);
      this.ʼ.setMaxInputLength(30);
      r.ˊ(this.ʽ, ˋ(new char[] { 3628, 24201, -5108, -8868 }, '\000', new char[] { -23349, -10209, 7295, 631, -11440, -23599, -15307, 26587, -27979, 14489, -1344, 21840, -27678, -26986, 20234, -27839, -13204, 13309, -32200, -702, 28464, 2221, -12364, 28711, -27172, -15372, 9047, 11713, 2034, -21703, 13849, 14830, 11478, -9157, 21114, 16585, -13384, 29447, -19626, -2351, 1998, -4690, -8837, 5979, 13506, -7955, 9849, -30896, -9003, -1049, -1660, -19479, -13464, 23743, 25836, -9738, -17414, -20831, 16396, 3211, 29936, -14206, 14532, -9109, -30673, -30552, -25814, 8128, 22475, 30340, 19419, -1324, -5555, 11587, -31559, 8429, 26242 }, 207522062, new char[] { 32408, 5357, 3762, 17255 }).intern(), ॱ(this.ʽ, 2131230823), true);
      localObject4 = this.ˊॱ;
      localObject3 = this.ˊॱ.getResources().getString(2131755147);
      localObject2 = localObject3;
      if (((String)localObject3).startsWith(ˋ(new char[] { -4221, -2293, -4698, -3489 }, '忭', new char[] { -28713, 19122, 6877, -21044 }, 0, new char[] { 32408, 5357, 3762, 17255 }).intern())) {
        localObject2 = ˋ(((String)localObject3).substring(4)).intern();
      }
      ʹ.ˊ((TextView)localObject4, (CharSequence)localObject2);
      localObject4 = this.ॱॱ;
      localObject3 = this.ॱॱ.getResources().getString(2131755485);
      localObject2 = localObject3;
      if (((String)localObject3).startsWith(ˋ(new char[] { -4221, -2293, -4698, -3489 }, '忭', new char[] { -28713, 19122, 6877, -21044 }, 0, new char[] { 32408, 5357, 3762, 17255 }).intern())) {
        localObject2 = ˋ(((String)localObject3).substring(4)).intern();
      }
      ((у)localObject4).setTitle((CharSequence)localObject2);
    }
    if ((0x60 & l2) != 0L)
    {
      this.ॱ.setAmount((String)localObject6);
      this.ॱ.setCurrency(localObject7);
    }
    if ((0x48 & l2) != 0L) {
      this.ʻ.setVisibility(i);
    }
    if ((0x64 & l2) != 0L) {
      this.ʼ.setInputText((String)localObject8);
    }
    if ((0x50 & l2) != 0L) {
      this.ˊॱ.setVisibility(j);
    }
  }
  
  /* Error */
  public boolean ˏ(int paramInt1, Object paramObject, int paramInt2)
  {
    // Byte code:
    //   0: goto +13 -> 13
    //   3: aload_0
    //   4: aload_2
    //   5: checkcast 289	o/ـ
    //   8: iload_3
    //   9: invokespecial 482	o/Mz:ॱ	(Lo/ـ;I)Z
    //   12: ireturn
    //   13: getstatic 54	o/Mz:ʿ	I
    //   16: bipush 53
    //   18: iadd
    //   19: istore 4
    //   21: iload 4
    //   23: sipush 128
    //   26: irem
    //   27: putstatic 52	o/Mz:ˈ	I
    //   30: iload 4
    //   32: iconst_2
    //   33: irem
    //   34: ifeq +6 -> 40
    //   37: goto +95 -> 132
    //   40: goto +118 -> 158
    //   43: iconst_0
    //   44: ireturn
    //   45: astore_2
    //   46: aload_2
    //   47: athrow
    //   48: bipush 51
    //   50: istore_1
    //   51: goto +47 -> 98
    //   54: astore_2
    //   55: aload_2
    //   56: athrow
    //   57: aload_2
    //   58: checkcast 289	o/ـ
    //   61: astore_2
    //   62: aload_0
    //   63: aload_2
    //   64: iload_3
    //   65: invokespecial 484	o/Mz:ˋ	(Lo/ـ;I)Z
    //   68: ireturn
    //   69: getstatic 54	o/Mz:ʿ	I
    //   72: istore_1
    //   73: iload_1
    //   74: bipush 45
    //   76: iadd
    //   77: istore_1
    //   78: iload_1
    //   79: sipush 128
    //   82: irem
    //   83: putstatic 52	o/Mz:ˈ	I
    //   86: iload_1
    //   87: iconst_2
    //   88: irem
    //   89: ifeq +6 -> 95
    //   92: goto +60 -> 152
    //   95: goto -47 -> 48
    //   98: iload_1
    //   99: lookupswitch	default:+25->124, 12:+25->124, 51:+-56->43
    //   124: new 486	java/lang/NullPointerException
    //   127: dup
    //   128: invokespecial 487	java/lang/NullPointerException:<init>	()V
    //   131: athrow
    //   132: goto +26 -> 158
    //   135: goto -66 -> 69
    //   138: aload_0
    //   139: aload_2
    //   140: checkcast 289	o/ـ
    //   143: iload_3
    //   144: invokespecial 489	o/Mz:ˏ	(Lo/ـ;I)Z
    //   147: istore 5
    //   149: iload 5
    //   151: ireturn
    //   152: bipush 12
    //   154: istore_1
    //   155: goto -57 -> 98
    //   158: iload_1
    //   159: tableswitch	default:+25->184, 0:+-21->138, 1:+-156->3, 2:+-102->57
    //   184: goto -49 -> 135
    // Local variable table:
    //   start	length	slot	name	signature
    //   0	187	0	this	Mz
    //   0	187	1	paramInt1	int
    //   0	187	2	paramObject	Object
    //   0	187	3	paramInt2	int
    //   19	15	4	i	int
    //   147	3	5	bool	boolean
    // Exception table:
    //   from	to	target	type
    //   138	149	45	java/lang/Exception
    //   57	62	54	java/lang/Exception
    //   69	73	54	java/lang/Exception
    //   78	86	54	java/lang/Exception
  }
  
  /* Error */
  public boolean ˏॱ()
  {
    // Byte code:
    //   0: goto +85 -> 85
    //   3: astore_3
    //   4: aload_3
    //   5: athrow
    //   6: iload_2
    //   7: ireturn
    //   8: new 486	java/lang/NullPointerException
    //   11: dup
    //   12: invokespecial 487	java/lang/NullPointerException:<init>	()V
    //   15: athrow
    //   16: getstatic 52	o/Mz:ˈ	I
    //   19: bipush 87
    //   21: iadd
    //   22: istore_1
    //   23: iload_1
    //   24: sipush 128
    //   27: irem
    //   28: putstatic 54	o/Mz:ʿ	I
    //   31: iload_1
    //   32: iconst_2
    //   33: irem
    //   34: ifne +6 -> 40
    //   37: goto +42 -> 79
    //   40: bipush 25
    //   42: istore_1
    //   43: goto +45 -> 88
    //   46: astore_3
    //   47: aload_3
    //   48: athrow
    //   49: getstatic 52	o/Mz:ˈ	I
    //   52: bipush 43
    //   54: iadd
    //   55: istore_1
    //   56: iload_1
    //   57: sipush 128
    //   60: irem
    //   61: putstatic 54	o/Mz:ʿ	I
    //   64: iload_1
    //   65: iconst_2
    //   66: irem
    //   67: ifne +6 -> 73
    //   70: goto +6 -> 76
    //   73: goto +45 -> 118
    //   76: goto +42 -> 118
    //   79: bipush 32
    //   81: istore_1
    //   82: goto +6 -> 88
    //   85: goto -36 -> 49
    //   88: iload_1
    //   89: lookupswitch	default:+27->116, 25:+-83->6, 32:+-81->8
    //   116: iload_2
    //   117: ireturn
    //   118: aload_0
    //   119: getfield 247	o/Mz:ˏॱ	Z
    //   122: istore_2
    //   123: goto -107 -> 16
    // Local variable table:
    //   start	length	slot	name	signature
    //   0	126	0	this	Mz
    //   22	67	1	i	int
    //   6	117	2	bool	boolean
    //   3	2	3	localException1	Exception
    //   46	2	3	localException2	Exception
    // Exception table:
    //   from	to	target	type
    //   56	64	3	java/lang/Exception
    //   49	56	46	java/lang/Exception
    //   56	64	46	java/lang/Exception
  }
  
  public void ॱ(Is paramIs)
  {
    this.ॱᐝ = paramIs;
    try
    {
      this.ᐝॱ |= 0x20;
    }
    finally
    {
      paramIs = finally;
      throw paramIs;
    }
    ˊ(100);
    super.ʽ();
  }
  
  public void ॱ(boolean paramBoolean)
  {
    this.ˏॱ = paramBoolean;
    try
    {
      this.ᐝॱ |= 0x8;
    }
    finally
    {
      localObject = finally;
      throw localObject;
    }
    ˊ(76);
    super.ʽ();
  }
  
  public boolean ॱ()
  {
    try
    {
      long l = this.ᐝॱ;
      if (l != 0L) {
        return true;
      }
    }
    finally
    {
      localObject = finally;
      throw localObject;
    }
    return false;
  }
}
