package o;

import android.support.v7.preference.Preference;

public final class Nd
{
  private static int ʻ = 0;
  private static byte[] ʼ;
  private static int ʽ = 1;
  private static int ˊ;
  private static int ˋ;
  public static final If ˎ;
  private static int ॱ;
  private static short[] ॱॱ;
  private final String ˏ;
  
  static
  {
    ˊ();
    ˎ = new If(null);
    int i = ʽ + 75;
    ʻ = i % 128;
    if (i % 2 == 0) {}
  }
  
  /* Error */
  private Nd(Preference paramPreference)
  {
    // Byte code:
    //   0: aload_0
    //   1: invokespecial 41	java/lang/Object:<init>	()V
    //   4: aload_1
    //   5: invokevirtual 47	android/support/v7/preference/Preference:ˊˊ	()Ljava/lang/String;
    //   8: astore_2
    //   9: bipush 54
    //   11: ldc 48
    //   13: bipush -19
    //   15: ldc 49
    //   17: bipush -12
    //   19: invokestatic 52	o/Nd:ˎ	(SIBII)Ljava/lang/String;
    //   22: astore_3
    //   23: aload_2
    //   24: aload_3
    //   25: invokevirtual 57	java/lang/String:intern	()Ljava/lang/String;
    //   28: invokestatic 62	o/vq:ˋ	(Ljava/lang/Object;Ljava/lang/String;)V
    //   31: aload_0
    //   32: aload_2
    //   33: putfield 64	o/Nd:ˏ	Ljava/lang/String;
    //   36: iconst_3
    //   37: iconst_3
    //   38: iconst_0
    //   39: invokestatic 69	o/O:ˋ	(IIC)Ljava/lang/Object;
    //   42: checkcast 71	java/lang/Class
    //   45: ldc 72
    //   47: invokevirtual 76	java/lang/Class:getField	(Ljava/lang/String;)Ljava/lang/reflect/Field;
    //   50: aconst_null
    //   51: invokevirtual 82	java/lang/reflect/Field:get	(Ljava/lang/Object;)Ljava/lang/Object;
    //   54: astore_2
    //   55: goto +17 -> 72
    //   58: astore_1
    //   59: aload_1
    //   60: invokevirtual 88	java/lang/Throwable:getCause	()Ljava/lang/Throwable;
    //   63: astore_2
    //   64: aload_2
    //   65: ifnull +5 -> 70
    //   68: aload_2
    //   69: athrow
    //   70: aload_1
    //   71: athrow
    //   72: bipush 6
    //   74: bipush 6
    //   76: sipush 10540
    //   79: invokestatic 69	o/O:ˋ	(IIC)Ljava/lang/Object;
    //   82: checkcast 71	java/lang/Class
    //   85: ldc 89
    //   87: aconst_null
    //   88: invokevirtual 93	java/lang/Class:getMethod	(Ljava/lang/String;[Ljava/lang/Class;)Ljava/lang/reflect/Method;
    //   91: aload_2
    //   92: aconst_null
    //   93: invokevirtual 99	java/lang/reflect/Method:invoke	(Ljava/lang/Object;[Ljava/lang/Object;)Ljava/lang/Object;
    //   96: astore_2
    //   97: aload_0
    //   98: getfield 64	o/Nd:ˏ	Ljava/lang/String;
    //   101: astore_3
    //   102: goto +17 -> 119
    //   105: astore_1
    //   106: aload_1
    //   107: invokevirtual 88	java/lang/Throwable:getCause	()Ljava/lang/Throwable;
    //   110: astore_2
    //   111: aload_2
    //   112: ifnull +5 -> 117
    //   115: aload_2
    //   116: athrow
    //   117: aload_1
    //   118: athrow
    //   119: iconst_3
    //   120: iconst_3
    //   121: iconst_0
    //   122: invokestatic 69	o/O:ˋ	(IIC)Ljava/lang/Object;
    //   125: checkcast 71	java/lang/Class
    //   128: ldc 100
    //   130: iconst_1
    //   131: anewarray 71	java/lang/Class
    //   134: dup
    //   135: iconst_0
    //   136: ldc 54
    //   138: aastore
    //   139: invokevirtual 93	java/lang/Class:getMethod	(Ljava/lang/String;[Ljava/lang/Class;)Ljava/lang/reflect/Method;
    //   142: aload_2
    //   143: iconst_1
    //   144: anewarray 4	java/lang/Object
    //   147: dup
    //   148: iconst_0
    //   149: aload_3
    //   150: aastore
    //   151: invokevirtual 99	java/lang/reflect/Method:invoke	(Ljava/lang/Object;[Ljava/lang/Object;)Ljava/lang/Object;
    //   154: checkcast 54	java/lang/String
    //   157: astore_2
    //   158: aload_1
    //   159: aload_2
    //   160: invokevirtual 103	android/support/v7/preference/Preference:ˊ	(Ljava/lang/String;)V
    //   163: return
    //   164: astore_1
    //   165: aload_1
    //   166: athrow
    //   167: astore_1
    //   168: aload_1
    //   169: athrow
    // Local variable table:
    //   start	length	slot	name	signature
    //   0	170	0	this	Nd
    //   0	170	1	paramPreference	Preference
    //   8	152	2	localObject	Object
    //   22	128	3	str	String
    // Exception table:
    //   from	to	target	type
    //   72	97	58	finally
    //   119	158	105	finally
    //   9	23	164	java/lang/Exception
    //   4	9	167	java/lang/Exception
    //   9	23	167	java/lang/Exception
    //   23	55	167	java/lang/Exception
    //   59	64	167	java/lang/Exception
    //   68	70	167	java/lang/Exception
    //   70	72	167	java/lang/Exception
    //   97	102	167	java/lang/Exception
    //   106	111	167	java/lang/Exception
    //   115	117	167	java/lang/Exception
    //   117	119	167	java/lang/Exception
    //   158	163	167	java/lang/Exception
  }
  
  static void ˊ()
  {
    ˋ = 26;
    ʼ = new byte[] { 12, 37, 39, 7, -81, -90, -88, -88, -57, -77, -78, -98, -92, -112, -43, -89, -84, -117, -72, -98, -98, -61, -31, -102, -18, -71, -30, -82, -24, -86, -36, -74, -24, -71, 0, 0, 0 };
    ˊ = 2034320450;
    ॱ = -240772450;
  }
  
  private static String ˎ(short paramShort, int paramInt1, byte paramByte, int paramInt2, int paramInt3)
  {
    break label667;
    int m = 88;
    break label490;
    label10:
    label22:
    int j;
    if (ʼ == null)
    {
      break label700;
      j = 0;
    }
    label31:
    int k;
    for (;;)
    {
      break label479;
      for (;;)
      {
        switch (paramInt3)
        {
        default: 
          break label610;
          Object localObject = ʼ;
          j = paramInt1 - 1;
          int i = (char)(((byte)(localObject[paramInt1] + paramShort) ^ paramByte) + k);
          break label256;
          j = 1;
          break label453;
          label93:
          j = 1;
          for (;;)
          {
            label99:
            localStringBuilder.append(i);
            paramInt2 += 1;
            k = i;
            break label190;
            label118:
            j = 1;
            break label656;
            StringBuilder localStringBuilder = new StringBuilder();
            for (;;)
            {
              try
              {
                j = ˋ;
                paramInt3 = j + paramInt3;
                k = paramInt3;
                if (paramInt3 == -1) {
                  break label118;
                }
                try
                {
                  label164:
                  k = ॱ;
                  paramInt1 = paramInt1 + paramInt3 - 2 + k;
                  if (j != 0) {
                    break label93;
                  }
                }
                catch (Exception localException1)
                {
                  label190:
                  label202:
                  label205:
                  label213:
                  label256:
                  throw localException1;
                }
                if (paramInt2 >= paramInt3)
                {
                  break label604;
                  break label656;
                  break label637;
                  paramInt1 = 0;
                  break label534;
                  localObject = ॱॱ;
                  j = paramInt1 - 1;
                  i = (char)(((short)(localObject[paramInt1] + paramShort) ^ paramByte) + k);
                  paramInt1 = j;
                  break label99;
                  paramInt1 = j;
                  break label99;
                  j = 0;
                  break label569;
                  paramInt1 = ʽ + 77;
                  ʻ = paramInt1 % 128;
                  if (paramInt1 % 2 == 0) {
                    continue;
                  }
                  paramInt1 = 1;
                  break label534;
                  paramInt3 = ʻ + 25;
                  ʽ = paramInt3 % 128;
                  if (paramInt3 % 2 == 0) {
                    continue;
                  }
                  continue;
                }
                j = ʽ + 43;
                ʻ = j % 128;
                if (j % 2 != 0) {
                  break label566;
                }
                break;
                if (ʼ != null) {
                  break label428;
                }
              }
              catch (Exception localException2)
              {
                label365:
                throw localException2;
              }
              paramInt1 = (paramInt1 >>> paramInt3) % 5 + ॱ;
              if (j != 0) {
                break label93;
              }
              break label22;
              paramInt1 += j;
              i = (char)(ˊ + paramInt2);
              localException2.append(i);
              paramInt2 = 1;
              k = i;
            }
            label422:
            paramInt1 = j;
          }
          label428:
          paramInt3 = 1;
        }
      }
      paramInt3 = (short)(ॱॱ[(ॱ + paramInt1)] + ˋ);
    }
    for (;;)
    {
      label453:
      switch (j)
      {
      }
      break label213;
      for (;;)
      {
        label479:
        if (paramInt3 <= 0)
        {
          break label604;
          label490:
          paramInt3 = k;
          switch (m)
          {
          }
          paramInt3 = k;
          continue;
          label531:
          break label656;
          label534:
          switch (paramInt1)
          {
          }
          break label422;
          for (;;)
          {
            m = 16;
            break label490;
            label566:
            break label10;
            label569:
            paramInt3 = ʽ + 1;
            ʻ = paramInt3 % 128;
            if (paramInt3 % 2 != 0) {
              break label202;
            }
            break label531;
            paramInt3 = 0;
            break label31;
            label604:
            return localException2.toString();
            label610:
            paramInt3 = ʻ + 87;
            ʽ = paramInt3 % 128;
            if (paramInt3 % 2 == 0) {
              break label205;
            }
            label637:
            paramInt3 = (byte)(ʼ[(ॱ + paramInt1)] + ˋ);
            break label479;
            label656:
            if (j != 0) {
              break;
            }
          }
          label667:
          break;
        }
      }
      k = ʻ + 103;
      ʽ = k % 128;
      if (k % 2 == 0) {
        break label365;
      }
      break label164;
      label700:
      j = 0;
    }
  }
  
  /* Error */
  public final void ˊ(boolean paramBoolean)
  {
    // Byte code:
    //   0: goto +300 -> 300
    //   3: iload_2
    //   4: lookupswitch	default:+28->32, 0:+340->344, 15:+74->78
    //   32: goto +46 -> 78
    //   35: iconst_0
    //   36: istore_2
    //   37: goto -34 -> 3
    //   40: goto +21 -> 61
    //   43: iconst_1
    //   44: istore_2
    //   45: goto +195 -> 240
    //   48: new 161	java/lang/NullPointerException
    //   51: dup
    //   52: invokespecial 162	java/lang/NullPointerException:<init>	()V
    //   55: athrow
    //   56: iconst_0
    //   57: istore_2
    //   58: goto +182 -> 240
    //   61: aload_0
    //   62: iload_3
    //   63: invokevirtual 165	o/Nd:ˏ	(Z)Z
    //   66: istore_3
    //   67: iload_1
    //   68: iload_3
    //   69: if_icmpeq +6 -> 75
    //   72: goto +11 -> 83
    //   75: goto +228 -> 303
    //   78: iconst_0
    //   79: istore_3
    //   80: goto -40 -> 40
    //   83: iconst_4
    //   84: sipush 402
    //   87: iconst_0
    //   88: invokestatic 69	o/O:ˋ	(IIC)Ljava/lang/Object;
    //   91: checkcast 71	java/lang/Class
    //   94: ldc -90
    //   96: invokevirtual 76	java/lang/Class:getField	(Ljava/lang/String;)Ljava/lang/reflect/Field;
    //   99: aconst_null
    //   100: invokevirtual 82	java/lang/reflect/Field:get	(Ljava/lang/Object;)Ljava/lang/Object;
    //   103: astore 4
    //   105: goto +23 -> 128
    //   108: astore 4
    //   110: aload 4
    //   112: invokevirtual 88	java/lang/Throwable:getCause	()Ljava/lang/Throwable;
    //   115: astore 5
    //   117: aload 5
    //   119: ifnull +6 -> 125
    //   122: aload 5
    //   124: athrow
    //   125: aload 4
    //   127: athrow
    //   128: bipush 7
    //   130: sipush 406
    //   133: ldc -89
    //   135: invokestatic 69	o/O:ˋ	(IIC)Ljava/lang/Object;
    //   138: checkcast 71	java/lang/Class
    //   141: ldc 100
    //   143: aconst_null
    //   144: invokevirtual 93	java/lang/Class:getMethod	(Ljava/lang/String;[Ljava/lang/Class;)Ljava/lang/reflect/Method;
    //   147: aload 4
    //   149: aconst_null
    //   150: invokevirtual 99	java/lang/reflect/Method:invoke	(Ljava/lang/Object;[Ljava/lang/Object;)Ljava/lang/Object;
    //   153: astore 4
    //   155: aload_0
    //   156: getfield 64	o/Nd:ˏ	Ljava/lang/String;
    //   159: astore 5
    //   161: goto +23 -> 184
    //   164: astore 5
    //   166: aload 5
    //   168: invokevirtual 88	java/lang/Throwable:getCause	()Ljava/lang/Throwable;
    //   171: astore 4
    //   173: aload 4
    //   175: ifnull +6 -> 181
    //   178: aload 4
    //   180: athrow
    //   181: aload 5
    //   183: athrow
    //   184: iconst_4
    //   185: sipush 402
    //   188: iconst_0
    //   189: invokestatic 69	o/O:ˋ	(IIC)Ljava/lang/Object;
    //   192: checkcast 71	java/lang/Class
    //   195: ldc 100
    //   197: iconst_2
    //   198: anewarray 71	java/lang/Class
    //   201: dup
    //   202: iconst_0
    //   203: ldc 54
    //   205: aastore
    //   206: dup
    //   207: iconst_1
    //   208: getstatic 173	java/lang/Boolean:TYPE	Ljava/lang/Class;
    //   211: aastore
    //   212: invokevirtual 93	java/lang/Class:getMethod	(Ljava/lang/String;[Ljava/lang/Class;)Ljava/lang/reflect/Method;
    //   215: aload 4
    //   217: iconst_2
    //   218: anewarray 4	java/lang/Object
    //   221: dup
    //   222: iconst_0
    //   223: aload 5
    //   225: aastore
    //   226: dup
    //   227: iconst_1
    //   228: iload_1
    //   229: invokestatic 177	java/lang/Boolean:valueOf	(Z)Ljava/lang/Boolean;
    //   232: aastore
    //   233: invokevirtual 99	java/lang/reflect/Method:invoke	(Ljava/lang/Object;[Ljava/lang/Object;)Ljava/lang/Object;
    //   236: pop
    //   237: goto +66 -> 303
    //   240: iload_2
    //   241: tableswitch	default:+23->264, 0:+26->267, 1:+-193->48
    //   264: goto -216 -> 48
    //   267: iload_1
    //   268: ifne +6 -> 274
    //   271: goto -236 -> 35
    //   274: goto +32 -> 306
    //   277: getstatic 27	o/Nd:ʽ	I
    //   280: bipush 17
    //   282: iadd
    //   283: istore_2
    //   284: iload_2
    //   285: sipush 128
    //   288: irem
    //   289: putstatic 25	o/Nd:ʻ	I
    //   292: iload_2
    //   293: iconst_2
    //   294: irem
    //   295: ifeq +4 -> 299
    //   298: return
    //   299: return
    //   300: goto +17 -> 317
    //   303: goto -26 -> 277
    //   306: bipush 15
    //   308: istore_2
    //   309: goto -306 -> 3
    //   312: astore 4
    //   314: aload 4
    //   316: athrow
    //   317: getstatic 27	o/Nd:ʽ	I
    //   320: bipush 67
    //   322: iadd
    //   323: istore_2
    //   324: iload_2
    //   325: sipush 128
    //   328: irem
    //   329: putstatic 25	o/Nd:ʻ	I
    //   332: iload_2
    //   333: iconst_2
    //   334: irem
    //   335: ifeq +6 -> 341
    //   338: goto -295 -> 43
    //   341: goto -285 -> 56
    //   344: iconst_1
    //   345: istore_3
    //   346: goto -285 -> 61
    // Local variable table:
    //   start	length	slot	name	signature
    //   0	349	0	this	Nd
    //   0	349	1	paramBoolean	boolean
    //   3	332	2	i	int
    //   62	284	3	bool	boolean
    //   103	1	4	localObject1	Object
    //   108	40	4	localObject2	Object
    //   153	63	4	localObject3	Object
    //   312	3	4	localException	Exception
    //   115	45	5	localObject4	Object
    //   164	60	5	localObject5	Object
    // Exception table:
    //   from	to	target	type
    //   128	155	108	finally
    //   184	237	164	finally
    //   61	67	312	java/lang/Exception
  }
  
  /* Error */
  public final String ˎ(String paramString)
  {
    // Byte code:
    //   0: goto +261 -> 261
    //   3: astore_1
    //   4: aload_1
    //   5: athrow
    //   6: getstatic 25	o/Nd:ʻ	I
    //   9: iconst_1
    //   10: iadd
    //   11: istore_2
    //   12: iload_2
    //   13: sipush 128
    //   16: irem
    //   17: putstatic 27	o/Nd:ʽ	I
    //   20: iload_2
    //   21: iconst_2
    //   22: irem
    //   23: ifne +6 -> 29
    //   26: goto +45 -> 71
    //   29: bipush 79
    //   31: istore_2
    //   32: goto +8 -> 40
    //   35: iconst_0
    //   36: istore_2
    //   37: goto +401 -> 438
    //   40: iload_2
    //   41: lookupswitch	default:+27->68, 79:+36->77, 94:+228->269
    //   68: goto +9 -> 77
    //   71: bipush 94
    //   73: istore_2
    //   74: goto -34 -> 40
    //   77: aload_1
    //   78: bipush 86
    //   80: ldc -77
    //   82: bipush -11
    //   84: ldc -76
    //   86: bipush -8
    //   88: invokestatic 52	o/Nd:ˎ	(SIBII)Ljava/lang/String;
    //   91: invokevirtual 57	java/lang/String:intern	()Ljava/lang/String;
    //   94: invokestatic 182	o/vq:ˎ	(Ljava/lang/Object;Ljava/lang/String;)V
    //   97: iconst_4
    //   98: sipush 402
    //   101: iconst_0
    //   102: invokestatic 69	o/O:ˋ	(IIC)Ljava/lang/Object;
    //   105: checkcast 71	java/lang/Class
    //   108: ldc -90
    //   110: invokevirtual 76	java/lang/Class:getField	(Ljava/lang/String;)Ljava/lang/reflect/Field;
    //   113: aconst_null
    //   114: invokevirtual 82	java/lang/reflect/Field:get	(Ljava/lang/Object;)Ljava/lang/Object;
    //   117: astore_3
    //   118: goto +17 -> 135
    //   121: astore_1
    //   122: aload_1
    //   123: invokevirtual 88	java/lang/Throwable:getCause	()Ljava/lang/Throwable;
    //   126: astore_3
    //   127: aload_3
    //   128: ifnull +5 -> 133
    //   131: aload_3
    //   132: athrow
    //   133: aload_1
    //   134: athrow
    //   135: bipush 7
    //   137: sipush 406
    //   140: ldc -89
    //   142: invokestatic 69	o/O:ˋ	(IIC)Ljava/lang/Object;
    //   145: checkcast 71	java/lang/Class
    //   148: ldc 100
    //   150: aconst_null
    //   151: invokevirtual 93	java/lang/Class:getMethod	(Ljava/lang/String;[Ljava/lang/Class;)Ljava/lang/reflect/Method;
    //   154: aload_3
    //   155: aconst_null
    //   156: invokevirtual 99	java/lang/reflect/Method:invoke	(Ljava/lang/Object;[Ljava/lang/Object;)Ljava/lang/Object;
    //   159: astore_3
    //   160: aload_0
    //   161: getfield 64	o/Nd:ˏ	Ljava/lang/String;
    //   164: astore 4
    //   166: goto +17 -> 183
    //   169: astore_1
    //   170: aload_1
    //   171: invokevirtual 88	java/lang/Throwable:getCause	()Ljava/lang/Throwable;
    //   174: astore_3
    //   175: aload_3
    //   176: ifnull +5 -> 181
    //   179: aload_3
    //   180: athrow
    //   181: aload_1
    //   182: athrow
    //   183: iconst_4
    //   184: sipush 402
    //   187: iconst_0
    //   188: invokestatic 69	o/O:ˋ	(IIC)Ljava/lang/Object;
    //   191: checkcast 71	java/lang/Class
    //   194: ldc 89
    //   196: iconst_2
    //   197: anewarray 71	java/lang/Class
    //   200: dup
    //   201: iconst_0
    //   202: ldc 54
    //   204: aastore
    //   205: dup
    //   206: iconst_1
    //   207: ldc 54
    //   209: aastore
    //   210: invokevirtual 93	java/lang/Class:getMethod	(Ljava/lang/String;[Ljava/lang/Class;)Ljava/lang/reflect/Method;
    //   213: aload_3
    //   214: iconst_2
    //   215: anewarray 4	java/lang/Object
    //   218: dup
    //   219: iconst_0
    //   220: aload 4
    //   222: aastore
    //   223: dup
    //   224: iconst_1
    //   225: aload_1
    //   226: aastore
    //   227: invokevirtual 99	java/lang/reflect/Method:invoke	(Ljava/lang/Object;[Ljava/lang/Object;)Ljava/lang/Object;
    //   230: checkcast 54	java/lang/String
    //   233: astore_1
    //   234: getstatic 27	o/Nd:ʽ	I
    //   237: bipush 95
    //   239: iadd
    //   240: istore_2
    //   241: iload_2
    //   242: sipush 128
    //   245: irem
    //   246: putstatic 25	o/Nd:ʻ	I
    //   249: iload_2
    //   250: iconst_2
    //   251: irem
    //   252: ifeq +6 -> 258
    //   255: goto -220 -> 35
    //   258: goto +6 -> 264
    //   261: goto -255 -> 6
    //   264: iconst_1
    //   265: istore_2
    //   266: goto +172 -> 438
    //   269: aload_1
    //   270: bipush 94
    //   272: ldc -77
    //   274: bipush 95
    //   276: ldc -76
    //   278: bipush 87
    //   280: invokestatic 52	o/Nd:ˎ	(SIBII)Ljava/lang/String;
    //   283: invokevirtual 57	java/lang/String:intern	()Ljava/lang/String;
    //   286: invokestatic 182	o/vq:ˎ	(Ljava/lang/Object;Ljava/lang/String;)V
    //   289: iconst_4
    //   290: sipush 402
    //   293: iconst_0
    //   294: invokestatic 69	o/O:ˋ	(IIC)Ljava/lang/Object;
    //   297: checkcast 71	java/lang/Class
    //   300: ldc -90
    //   302: invokevirtual 76	java/lang/Class:getField	(Ljava/lang/String;)Ljava/lang/reflect/Field;
    //   305: aconst_null
    //   306: invokevirtual 82	java/lang/reflect/Field:get	(Ljava/lang/Object;)Ljava/lang/Object;
    //   309: astore_3
    //   310: goto +17 -> 327
    //   313: astore_1
    //   314: aload_1
    //   315: invokevirtual 88	java/lang/Throwable:getCause	()Ljava/lang/Throwable;
    //   318: astore_3
    //   319: aload_3
    //   320: ifnull +5 -> 325
    //   323: aload_3
    //   324: athrow
    //   325: aload_1
    //   326: athrow
    //   327: bipush 7
    //   329: sipush 406
    //   332: ldc -89
    //   334: invokestatic 69	o/O:ˋ	(IIC)Ljava/lang/Object;
    //   337: checkcast 71	java/lang/Class
    //   340: ldc 100
    //   342: aconst_null
    //   343: invokevirtual 93	java/lang/Class:getMethod	(Ljava/lang/String;[Ljava/lang/Class;)Ljava/lang/reflect/Method;
    //   346: aload_3
    //   347: aconst_null
    //   348: invokevirtual 99	java/lang/reflect/Method:invoke	(Ljava/lang/Object;[Ljava/lang/Object;)Ljava/lang/Object;
    //   351: astore_3
    //   352: aload_0
    //   353: getfield 64	o/Nd:ˏ	Ljava/lang/String;
    //   356: astore 4
    //   358: goto +17 -> 375
    //   361: astore_1
    //   362: aload_1
    //   363: invokevirtual 88	java/lang/Throwable:getCause	()Ljava/lang/Throwable;
    //   366: astore_3
    //   367: aload_3
    //   368: ifnull +5 -> 373
    //   371: aload_3
    //   372: athrow
    //   373: aload_1
    //   374: athrow
    //   375: iconst_4
    //   376: sipush 402
    //   379: iconst_0
    //   380: invokestatic 69	o/O:ˋ	(IIC)Ljava/lang/Object;
    //   383: checkcast 71	java/lang/Class
    //   386: ldc 89
    //   388: iconst_2
    //   389: anewarray 71	java/lang/Class
    //   392: dup
    //   393: iconst_0
    //   394: ldc 54
    //   396: aastore
    //   397: dup
    //   398: iconst_1
    //   399: ldc 54
    //   401: aastore
    //   402: invokevirtual 93	java/lang/Class:getMethod	(Ljava/lang/String;[Ljava/lang/Class;)Ljava/lang/reflect/Method;
    //   405: aload_3
    //   406: iconst_2
    //   407: anewarray 4	java/lang/Object
    //   410: dup
    //   411: iconst_0
    //   412: aload 4
    //   414: aastore
    //   415: dup
    //   416: iconst_1
    //   417: aload_1
    //   418: aastore
    //   419: invokevirtual 99	java/lang/reflect/Method:invoke	(Ljava/lang/Object;[Ljava/lang/Object;)Ljava/lang/Object;
    //   422: checkcast 54	java/lang/String
    //   425: astore_1
    //   426: goto -192 -> 234
    //   429: aload_1
    //   430: areturn
    //   431: bipush 49
    //   433: iconst_0
    //   434: idiv
    //   435: istore_2
    //   436: aload_1
    //   437: areturn
    //   438: iload_2
    //   439: tableswitch	default:+21->460, 0:+-8->431, 1:+-10->429
    //   460: goto -29 -> 431
    // Local variable table:
    //   start	length	slot	name	signature
    //   0	463	0	this	Nd
    //   0	463	1	paramString	String
    //   11	428	2	i	int
    //   117	289	3	localObject	Object
    //   164	249	4	str	String
    // Exception table:
    //   from	to	target	type
    //   6	12	3	java/lang/Exception
    //   12	20	3	java/lang/Exception
    //   135	160	121	finally
    //   183	234	169	finally
    //   327	352	313	finally
    //   375	426	361	finally
  }
  
  /* Error */
  public final void ˏ(String paramString)
  {
    // Byte code:
    //   0: goto +198 -> 198
    //   3: getstatic 25	o/Nd:ʻ	I
    //   6: bipush 55
    //   8: iadd
    //   9: istore_2
    //   10: iload_2
    //   11: sipush 128
    //   14: irem
    //   15: putstatic 27	o/Nd:ʽ	I
    //   18: iload_2
    //   19: iconst_2
    //   20: irem
    //   21: ifne +6 -> 27
    //   24: goto +408 -> 432
    //   27: goto +204 -> 231
    //   30: bipush 61
    //   32: istore_2
    //   33: goto +168 -> 201
    //   36: bipush 74
    //   38: istore_2
    //   39: goto +162 -> 201
    //   42: return
    //   43: iconst_4
    //   44: sipush 402
    //   47: iconst_0
    //   48: invokestatic 69	o/O:ˋ	(IIC)Ljava/lang/Object;
    //   51: checkcast 71	java/lang/Class
    //   54: ldc -90
    //   56: invokevirtual 76	java/lang/Class:getField	(Ljava/lang/String;)Ljava/lang/reflect/Field;
    //   59: aconst_null
    //   60: invokevirtual 82	java/lang/reflect/Field:get	(Ljava/lang/Object;)Ljava/lang/Object;
    //   63: astore 4
    //   65: goto +20 -> 85
    //   68: astore_1
    //   69: aload_1
    //   70: invokevirtual 88	java/lang/Throwable:getCause	()Ljava/lang/Throwable;
    //   73: astore 4
    //   75: aload 4
    //   77: ifnull +6 -> 83
    //   80: aload 4
    //   82: athrow
    //   83: aload_1
    //   84: athrow
    //   85: bipush 7
    //   87: sipush 406
    //   90: ldc -89
    //   92: invokestatic 69	o/O:ˋ	(IIC)Ljava/lang/Object;
    //   95: checkcast 71	java/lang/Class
    //   98: ldc 100
    //   100: aconst_null
    //   101: invokevirtual 93	java/lang/Class:getMethod	(Ljava/lang/String;[Ljava/lang/Class;)Ljava/lang/reflect/Method;
    //   104: aload 4
    //   106: aconst_null
    //   107: invokevirtual 99	java/lang/reflect/Method:invoke	(Ljava/lang/Object;[Ljava/lang/Object;)Ljava/lang/Object;
    //   110: astore 4
    //   112: aload_0
    //   113: getfield 64	o/Nd:ˏ	Ljava/lang/String;
    //   116: astore 5
    //   118: goto +20 -> 138
    //   121: astore_1
    //   122: aload_1
    //   123: invokevirtual 88	java/lang/Throwable:getCause	()Ljava/lang/Throwable;
    //   126: astore 4
    //   128: aload 4
    //   130: ifnull +6 -> 136
    //   133: aload 4
    //   135: athrow
    //   136: aload_1
    //   137: athrow
    //   138: iconst_4
    //   139: sipush 402
    //   142: iconst_0
    //   143: invokestatic 69	o/O:ˋ	(IIC)Ljava/lang/Object;
    //   146: checkcast 71	java/lang/Class
    //   149: ldc 72
    //   151: iconst_2
    //   152: anewarray 71	java/lang/Class
    //   155: dup
    //   156: iconst_0
    //   157: ldc 54
    //   159: aastore
    //   160: dup
    //   161: iconst_1
    //   162: ldc 54
    //   164: aastore
    //   165: invokevirtual 93	java/lang/Class:getMethod	(Ljava/lang/String;[Ljava/lang/Class;)Ljava/lang/reflect/Method;
    //   168: aload 4
    //   170: iconst_2
    //   171: anewarray 4	java/lang/Object
    //   174: dup
    //   175: iconst_0
    //   176: aload 5
    //   178: aastore
    //   179: dup
    //   180: iconst_1
    //   181: aload_1
    //   182: aastore
    //   183: invokevirtual 99	java/lang/reflect/Method:invoke	(Ljava/lang/Object;[Ljava/lang/Object;)Ljava/lang/Object;
    //   186: pop
    //   187: goto -184 -> 3
    //   190: iconst_1
    //   191: istore_2
    //   192: goto +69 -> 261
    //   195: astore_1
    //   196: aload_1
    //   197: athrow
    //   198: goto +150 -> 348
    //   201: iload_2
    //   202: lookupswitch	default:+26->228, 61:+185->387, 74:+91->293
    //   228: goto +159 -> 387
    //   231: return
    //   232: iload_2
    //   233: lookupswitch	default:+27->260, 12:+-190->43, 42:+-191->42
    //   260: return
    //   261: iload_2
    //   262: tableswitch	default:+22->284, 0:+-219->43, 1:+-220->42
    //   284: return
    //   285: iconst_0
    //   286: istore_2
    //   287: goto -26 -> 261
    //   290: astore_1
    //   291: aload_1
    //   292: athrow
    //   293: bipush 106
    //   295: ldc -73
    //   297: bipush 72
    //   299: ldc -72
    //   301: bipush 36
    //   303: invokestatic 52	o/Nd:ˎ	(SIBII)Ljava/lang/String;
    //   306: astore 4
    //   308: aload 4
    //   310: invokevirtual 57	java/lang/String:intern	()Ljava/lang/String;
    //   313: astore 4
    //   315: aload_1
    //   316: aload 4
    //   318: invokestatic 182	o/vq:ˎ	(Ljava/lang/Object;Ljava/lang/String;)V
    //   321: aload_1
    //   322: checkcast 186	java/lang/CharSequence
    //   325: aload_0
    //   326: ldc -68
    //   328: invokevirtual 190	o/Nd:ˎ	(Ljava/lang/String;)Ljava/lang/String;
    //   331: checkcast 186	java/lang/CharSequence
    //   334: invokestatic 196	android/text/TextUtils:equals	(Ljava/lang/CharSequence;Ljava/lang/CharSequence;)Z
    //   337: istore_3
    //   338: iload_3
    //   339: ifne +6 -> 345
    //   342: goto +33 -> 375
    //   345: goto +36 -> 381
    //   348: getstatic 25	o/Nd:ʻ	I
    //   351: bipush 27
    //   353: iadd
    //   354: istore_2
    //   355: iload_2
    //   356: sipush 128
    //   359: irem
    //   360: putstatic 27	o/Nd:ʽ	I
    //   363: iload_2
    //   364: iconst_2
    //   365: irem
    //   366: ifne +6 -> 372
    //   369: goto -333 -> 36
    //   372: goto -342 -> 30
    //   375: bipush 12
    //   377: istore_2
    //   378: goto -146 -> 232
    //   381: bipush 42
    //   383: istore_2
    //   384: goto -152 -> 232
    //   387: aload_1
    //   388: bipush 100
    //   390: ldc -73
    //   392: bipush -128
    //   394: ldc -72
    //   396: bipush -21
    //   398: invokestatic 52	o/Nd:ˎ	(SIBII)Ljava/lang/String;
    //   401: invokevirtual 57	java/lang/String:intern	()Ljava/lang/String;
    //   404: invokestatic 182	o/vq:ˎ	(Ljava/lang/Object;Ljava/lang/String;)V
    //   407: aload_1
    //   408: checkcast 186	java/lang/CharSequence
    //   411: aload_0
    //   412: ldc -68
    //   414: invokevirtual 190	o/Nd:ˎ	(Ljava/lang/String;)Ljava/lang/String;
    //   417: checkcast 186	java/lang/CharSequence
    //   420: invokestatic 196	android/text/TextUtils:equals	(Ljava/lang/CharSequence;Ljava/lang/CharSequence;)Z
    //   423: ifne +6 -> 429
    //   426: goto -141 -> 285
    //   429: goto -239 -> 190
    //   432: goto -201 -> 231
    // Local variable table:
    //   start	length	slot	name	signature
    //   0	435	0	this	Nd
    //   0	435	1	paramString	String
    //   9	375	2	i	int
    //   337	2	3	bool	boolean
    //   63	254	4	localObject	Object
    //   116	61	5	str	String
    // Exception table:
    //   from	to	target	type
    //   85	112	68	finally
    //   138	187	121	finally
    //   293	308	195	java/lang/Exception
    //   308	315	195	java/lang/Exception
    //   315	321	195	java/lang/Exception
    //   321	338	195	java/lang/Exception
    //   293	308	290	java/lang/Exception
  }
  
  /* Error */
  public final boolean ˏ(boolean paramBoolean)
  {
    // Byte code:
    //   0: goto +228 -> 228
    //   3: astore_3
    //   4: aload_3
    //   5: athrow
    //   6: getstatic 27	o/Nd:ʽ	I
    //   9: bipush 7
    //   11: iadd
    //   12: istore_2
    //   13: iload_2
    //   14: sipush 128
    //   17: irem
    //   18: putstatic 25	o/Nd:ʻ	I
    //   21: iload_2
    //   22: iconst_2
    //   23: irem
    //   24: ifeq +6 -> 30
    //   27: goto +196 -> 223
    //   30: goto +3 -> 33
    //   33: iconst_0
    //   34: istore_2
    //   35: goto +161 -> 196
    //   38: astore_3
    //   39: aload_3
    //   40: athrow
    //   41: iconst_4
    //   42: sipush 402
    //   45: iconst_0
    //   46: invokestatic 69	o/O:ˋ	(IIC)Ljava/lang/Object;
    //   49: checkcast 71	java/lang/Class
    //   52: ldc -90
    //   54: invokevirtual 76	java/lang/Class:getField	(Ljava/lang/String;)Ljava/lang/reflect/Field;
    //   57: aconst_null
    //   58: invokevirtual 82	java/lang/reflect/Field:get	(Ljava/lang/Object;)Ljava/lang/Object;
    //   61: astore_3
    //   62: goto +20 -> 82
    //   65: astore_3
    //   66: aload_3
    //   67: invokevirtual 88	java/lang/Throwable:getCause	()Ljava/lang/Throwable;
    //   70: astore 4
    //   72: aload 4
    //   74: ifnull +6 -> 80
    //   77: aload 4
    //   79: athrow
    //   80: aload_3
    //   81: athrow
    //   82: bipush 7
    //   84: sipush 406
    //   87: ldc -89
    //   89: invokestatic 69	o/O:ˋ	(IIC)Ljava/lang/Object;
    //   92: checkcast 71	java/lang/Class
    //   95: ldc 100
    //   97: aconst_null
    //   98: invokevirtual 93	java/lang/Class:getMethod	(Ljava/lang/String;[Ljava/lang/Class;)Ljava/lang/reflect/Method;
    //   101: aload_3
    //   102: aconst_null
    //   103: invokevirtual 99	java/lang/reflect/Method:invoke	(Ljava/lang/Object;[Ljava/lang/Object;)Ljava/lang/Object;
    //   106: astore_3
    //   107: aload_0
    //   108: getfield 64	o/Nd:ˏ	Ljava/lang/String;
    //   111: astore 4
    //   113: goto +20 -> 133
    //   116: astore_3
    //   117: aload_3
    //   118: invokevirtual 88	java/lang/Throwable:getCause	()Ljava/lang/Throwable;
    //   121: astore 4
    //   123: aload 4
    //   125: ifnull +6 -> 131
    //   128: aload 4
    //   130: athrow
    //   131: aload_3
    //   132: athrow
    //   133: iconst_4
    //   134: sipush 402
    //   137: iconst_0
    //   138: invokestatic 69	o/O:ˋ	(IIC)Ljava/lang/Object;
    //   141: checkcast 71	java/lang/Class
    //   144: ldc -59
    //   146: iconst_2
    //   147: anewarray 71	java/lang/Class
    //   150: dup
    //   151: iconst_0
    //   152: ldc 54
    //   154: aastore
    //   155: dup
    //   156: iconst_1
    //   157: getstatic 173	java/lang/Boolean:TYPE	Ljava/lang/Class;
    //   160: aastore
    //   161: invokevirtual 93	java/lang/Class:getMethod	(Ljava/lang/String;[Ljava/lang/Class;)Ljava/lang/reflect/Method;
    //   164: aload_3
    //   165: iconst_2
    //   166: anewarray 4	java/lang/Object
    //   169: dup
    //   170: iconst_0
    //   171: aload 4
    //   173: aastore
    //   174: dup
    //   175: iconst_1
    //   176: iload_1
    //   177: invokestatic 177	java/lang/Boolean:valueOf	(Z)Ljava/lang/Boolean;
    //   180: aastore
    //   181: invokevirtual 99	java/lang/reflect/Method:invoke	(Ljava/lang/Object;[Ljava/lang/Object;)Ljava/lang/Object;
    //   184: checkcast 169	java/lang/Boolean
    //   187: invokevirtual 201	java/lang/Boolean:booleanValue	()Z
    //   190: istore_1
    //   191: aconst_null
    //   192: arraylength
    //   193: istore_2
    //   194: iload_1
    //   195: ireturn
    //   196: iload_2
    //   197: tableswitch	default:+23->220, 0:+34->231, 1:+-156->41
    //   220: goto +11 -> 231
    //   223: iconst_1
    //   224: istore_2
    //   225: goto -29 -> 196
    //   228: goto -222 -> 6
    //   231: iconst_4
    //   232: sipush 402
    //   235: iconst_0
    //   236: invokestatic 69	o/O:ˋ	(IIC)Ljava/lang/Object;
    //   239: checkcast 71	java/lang/Class
    //   242: ldc -90
    //   244: invokevirtual 76	java/lang/Class:getField	(Ljava/lang/String;)Ljava/lang/reflect/Field;
    //   247: aconst_null
    //   248: invokevirtual 82	java/lang/reflect/Field:get	(Ljava/lang/Object;)Ljava/lang/Object;
    //   251: astore_3
    //   252: goto +20 -> 272
    //   255: astore_3
    //   256: aload_3
    //   257: invokevirtual 88	java/lang/Throwable:getCause	()Ljava/lang/Throwable;
    //   260: astore 4
    //   262: aload 4
    //   264: ifnull +6 -> 270
    //   267: aload 4
    //   269: athrow
    //   270: aload_3
    //   271: athrow
    //   272: bipush 7
    //   274: sipush 406
    //   277: ldc -89
    //   279: invokestatic 69	o/O:ˋ	(IIC)Ljava/lang/Object;
    //   282: checkcast 71	java/lang/Class
    //   285: ldc 100
    //   287: aconst_null
    //   288: invokevirtual 93	java/lang/Class:getMethod	(Ljava/lang/String;[Ljava/lang/Class;)Ljava/lang/reflect/Method;
    //   291: aload_3
    //   292: aconst_null
    //   293: invokevirtual 99	java/lang/reflect/Method:invoke	(Ljava/lang/Object;[Ljava/lang/Object;)Ljava/lang/Object;
    //   296: astore_3
    //   297: aload_0
    //   298: getfield 64	o/Nd:ˏ	Ljava/lang/String;
    //   301: astore 4
    //   303: goto +20 -> 323
    //   306: astore_3
    //   307: aload_3
    //   308: invokevirtual 88	java/lang/Throwable:getCause	()Ljava/lang/Throwable;
    //   311: astore 4
    //   313: aload 4
    //   315: ifnull +6 -> 321
    //   318: aload 4
    //   320: athrow
    //   321: aload_3
    //   322: athrow
    //   323: iconst_4
    //   324: sipush 402
    //   327: iconst_0
    //   328: invokestatic 69	o/O:ˋ	(IIC)Ljava/lang/Object;
    //   331: checkcast 71	java/lang/Class
    //   334: ldc -59
    //   336: iconst_2
    //   337: anewarray 71	java/lang/Class
    //   340: dup
    //   341: iconst_0
    //   342: ldc 54
    //   344: aastore
    //   345: dup
    //   346: iconst_1
    //   347: getstatic 173	java/lang/Boolean:TYPE	Ljava/lang/Class;
    //   350: aastore
    //   351: invokevirtual 93	java/lang/Class:getMethod	(Ljava/lang/String;[Ljava/lang/Class;)Ljava/lang/reflect/Method;
    //   354: aload_3
    //   355: iconst_2
    //   356: anewarray 4	java/lang/Object
    //   359: dup
    //   360: iconst_0
    //   361: aload 4
    //   363: aastore
    //   364: dup
    //   365: iconst_1
    //   366: iload_1
    //   367: invokestatic 177	java/lang/Boolean:valueOf	(Z)Ljava/lang/Boolean;
    //   370: aastore
    //   371: invokevirtual 99	java/lang/reflect/Method:invoke	(Ljava/lang/Object;[Ljava/lang/Object;)Ljava/lang/Object;
    //   374: checkcast 169	java/lang/Boolean
    //   377: invokevirtual 201	java/lang/Boolean:booleanValue	()Z
    //   380: istore_1
    //   381: iload_1
    //   382: ireturn
    // Local variable table:
    //   start	length	slot	name	signature
    //   0	383	0	this	Nd
    //   0	383	1	paramBoolean	boolean
    //   12	213	2	i	int
    //   3	2	3	localException1	Exception
    //   38	2	3	localException2	Exception
    //   61	1	3	localObject1	Object
    //   65	37	3	localObject2	Object
    //   106	1	3	localObject3	Object
    //   116	49	3	localObject4	Object
    //   251	1	3	localObject5	Object
    //   255	37	3	localObject6	Object
    //   296	1	3	localObject7	Object
    //   306	49	3	localObject8	Object
    //   70	292	4	localObject9	Object
    // Exception table:
    //   from	to	target	type
    //   231	252	3	java/lang/Exception
    //   256	262	3	java/lang/Exception
    //   267	270	3	java/lang/Exception
    //   270	272	3	java/lang/Exception
    //   297	303	3	java/lang/Exception
    //   307	313	3	java/lang/Exception
    //   318	321	3	java/lang/Exception
    //   321	323	3	java/lang/Exception
    //   297	303	38	java/lang/Exception
    //   82	107	65	finally
    //   133	191	116	finally
    //   272	297	255	finally
    //   323	381	306	finally
  }
  
  public static final class If
  {
    private static long ˊ = -3214004800137367062L;
    private static int ˎ;
    private static int ॱ = 0;
    
    static
    {
      ˎ = 1;
    }
    
    private If() {}
    
    private static String ˏ(char[] paramArrayOfChar)
    {
      break label247;
      int k = paramArrayOfChar[0];
      char[] arrayOfChar = new char[paramArrayOfChar.length - 1];
      int i = 1;
      break label182;
      int j;
      for (;;)
      {
        long l = paramArrayOfChar[i] ^ i * k;
        try
        {
          arrayOfChar[(i - 1)] = ((char)(int)(l ^ ˊ));
          i += 1;
        }
        catch (Exception paramArrayOfChar)
        {
          throw paramArrayOfChar;
        }
        i = 73 / 0;
        return paramArrayOfChar;
        do
        {
          break;
          j = ˎ + 5;
          ॱ = j % 128;
        } while (j % 2 != 0);
      }
      switch (j)
      {
      case 1: 
      default: 
        label87:
        break;
      }
      label182:
      label185:
      label215:
      label217:
      label242:
      label247:
      for (;;)
      {
        i = ॱ + 41;
        ˎ = i % 128;
        if (i % 2 != 0) {
          break;
        }
        break;
        for (;;)
        {
          j = 0;
          break;
          return paramArrayOfChar;
          for (;;)
          {
            i = ॱ + 25;
            ˎ = i % 128;
            if (i % 2 == 0) {
              break label215;
            }
            break label185;
            break;
            i = 0;
            break label217;
            paramArrayOfChar = new String(arrayOfChar);
          }
          if (i < paramArrayOfChar.length) {
            break label242;
          }
        }
        i = 1;
        switch (i)
        {
        }
        return paramArrayOfChar;
        j = 1;
        break label87;
      }
    }
    
    public final Nd ˋ(Preference paramPreference)
    {
      break label35;
      int i = 0;
      break label122;
      for (;;)
      {
        i = ˎ + 69;
        ॱ = i % 128;
        if (i % 2 != 0) {
          break label149;
        }
        break;
        label35:
        vq.ˎ(paramPreference, ˏ(new char[] { 16319, 20005, 3814, -12622, -28816, 20276, 4066, -12362, -29572, 19518, 3321 }).intern());
        paramPreference = new Nd(paramPreference, null);
      }
      for (;;)
      {
        switch (i)
        {
        default: 
          break;
        case 0: 
          label122:
          return paramPreference;
          label149:
          i = 1;
        }
      }
      throw new NullPointerException();
    }
  }
}
