package o;

import android.content.Context;
import android.os.Bundle;
import android.support.v14.preference.SwitchPreference;
import android.support.v7.preference.Preference;
import android.view.LayoutInflater;
import com.insidesecure.hce.MatrixHCECard;
import java.io.UnsupportedEncodingException;

public class Ne
  extends J
{
  private static long ʼ;
  private static char[] ʽ;
  private static byte ᐝ;
  private static int ꞌ = 0;
  private static int ﾞ = 1;
  private IM ʻ;
  private Preference ˊ;
  private MatrixHCECard ˋ;
  private Preference ˎ;
  private SwitchPreference ˏ;
  private Preference ॱ;
  
  /* Error */
  static
  {
    // Byte code:
    //   0: iconst_0
    //   1: putstatic 41	o/Ne:ꞌ	I
    //   4: iconst_1
    //   5: putstatic 43	o/Ne:ﾞ	I
    //   8: invokestatic 46	o/Ne:ʻᐝ	()V
    //   11: bipush -102
    //   13: putstatic 48	o/Ne:ᐝ	B
    //   16: goto +9 -> 25
    //   19: astore_1
    //   20: aload_1
    //   21: athrow
    //   22: astore_1
    //   23: aload_1
    //   24: athrow
    //   25: getstatic 43	o/Ne:ﾞ	I
    //   28: istore_0
    //   29: iload_0
    //   30: bipush 89
    //   32: iadd
    //   33: istore_0
    //   34: iload_0
    //   35: sipush 128
    //   38: irem
    //   39: putstatic 41	o/Ne:ꞌ	I
    //   42: iload_0
    //   43: iconst_2
    //   44: irem
    //   45: ifeq +4 -> 49
    //   48: return
    //   49: return
    // Local variable table:
    //   start	length	slot	name	signature
    //   28	17	0	i	int
    //   19	2	1	localException1	Exception
    //   22	2	1	localException2	Exception
    // Exception table:
    //   from	to	target	type
    //   34	42	19	java/lang/Exception
    //   25	29	22	java/lang/Exception
  }
  
  public Ne() {}
  
  static void ʻᐝ()
  {
    ʼ = 7811403958367341124L;
    ʽ = new char[] { 101, -13764, -27396, 24254, 10609, -3317, -16901, -30787, 21074, 7168, -6409, -20348, 31583, 17688, 4060, -9831, -23502, 28379, 14502, 877, -12995, -26639, 5, -13730, -27517, 24256, 68, -13779, -27409, 24229, 10596, -3267, -16926, -30787, 21076, 7181, -6457, -20350, 68, -13791, -27420, 24233, 10596, -3267, -16906, -30789, 20992, 7175, -6455, -20322, 31572, 17748, 4047, -9835, -23500, 28396, 14568, 879, -13007, -26650, 25020, 11349, -2546, -16169, -30052, 21837, 7966, -5673, -19555, 32361, 18665, 4768, -8920, -19743, 30852, 9734, -5119, -25633, 16776, 3922, 13650, -7958, -20817, 21610, 551, -13846, -2113, -17098, 27425, 5787, -9143, -30203, -20025, 32653, 9545, -11434, -24873, 17592, 29295, 14376, -6154, -20994, 23400, 307, -13071, -1461, -24573, 28624, 5511, -15526, 5560, -8227, -32417, 19288, 15494, -6447, -22517, -28149, 18355, 2550, -3277, -23170, 28339, 20710, 6767, -13203, -20010, 31514, 11603, 5851, -10046, -32235, 29770, 14725, -7197, -10893, -24723, 16574, 2788, -986, -22938, 27581, 23826, 1879, -14127, -19813, -22723, 28003, 13235, -1643, -29092, 21528, 6873, 8337, -2695, -17631, 32725, -19056, -5298, 8545, 22184 };
  }
  
  /* Error */
  private void ʼˋ()
  {
    // Byte code:
    //   0: goto +335 -> 335
    //   3: aload_0
    //   4: getfield 218	o/Ne:ˏ	Landroid/support/v14/preference/SwitchPreference;
    //   7: iconst_0
    //   8: invokevirtual 223	android/support/v14/preference/SwitchPreference:ॱ	(Z)V
    //   11: aload_0
    //   12: invokevirtual 227	o/Ne:ˏॱ	()Landroid/content/Context;
    //   15: astore 4
    //   17: aload_0
    //   18: getstatic 232	o/MH$ᐝ:settings_card_suspended_activation_error	I
    //   21: invokevirtual 235	o/Ne:ˋ	(I)Ljava/lang/String;
    //   24: astore_3
    //   25: aload_3
    //   26: bipush 22
    //   28: iconst_0
    //   29: iconst_4
    //   30: invokestatic 238	o/Ne:ˎ	(ICI)Ljava/lang/String;
    //   33: invokevirtual 244	java/lang/String:intern	()Ljava/lang/String;
    //   36: invokevirtual 248	java/lang/String:startsWith	(Ljava/lang/String;)Z
    //   39: ifeq +6 -> 45
    //   42: goto +69 -> 111
    //   45: goto +293 -> 338
    //   48: goto -45 -> 3
    //   51: getstatic 43	o/Ne:ﾞ	I
    //   54: bipush 87
    //   56: iadd
    //   57: istore_1
    //   58: iload_1
    //   59: sipush 128
    //   62: irem
    //   63: putstatic 41	o/Ne:ꞌ	I
    //   66: iload_1
    //   67: iconst_2
    //   68: irem
    //   69: ifeq +6 -> 75
    //   72: goto +6 -> 78
    //   75: goto +241 -> 316
    //   78: bipush 51
    //   80: istore_1
    //   81: goto +46 -> 127
    //   84: aload_0
    //   85: aload_3
    //   86: iconst_4
    //   87: invokevirtual 251	java/lang/String:substring	(I)Ljava/lang/String;
    //   90: invokespecial 254	o/Ne:ˏ	(Ljava/lang/String;)Ljava/lang/String;
    //   93: invokevirtual 244	java/lang/String:intern	()Ljava/lang/String;
    //   96: astore_3
    //   97: bipush 6
    //   99: iconst_0
    //   100: idiv
    //   101: istore_1
    //   102: goto +220 -> 322
    //   105: goto +334 -> 439
    //   108: astore_3
    //   109: aload_3
    //   110: athrow
    //   111: aload_0
    //   112: aload_3
    //   113: iconst_4
    //   114: invokevirtual 251	java/lang/String:substring	(I)Ljava/lang/String;
    //   117: invokespecial 254	o/Ne:ˏ	(Ljava/lang/String;)Ljava/lang/String;
    //   120: invokevirtual 244	java/lang/String:intern	()Ljava/lang/String;
    //   123: astore_3
    //   124: goto +214 -> 338
    //   127: iload_1
    //   128: lookupswitch	default:+28->156, 49:+101->229, 51:+-44->84
    //   156: goto +73 -> 229
    //   159: aload_0
    //   160: getfield 218	o/Ne:ˏ	Landroid/support/v14/preference/SwitchPreference;
    //   163: astore_3
    //   164: aload_3
    //   165: iconst_1
    //   166: invokevirtual 223	android/support/v14/preference/SwitchPreference:ॱ	(Z)V
    //   169: aload_0
    //   170: invokevirtual 227	o/Ne:ˏॱ	()Landroid/content/Context;
    //   173: astore 4
    //   175: getstatic 257	o/MH$ᐝ:settings_card_activation_error	I
    //   178: istore_1
    //   179: aload_0
    //   180: iload_1
    //   181: invokevirtual 235	o/Ne:ˋ	(I)Ljava/lang/String;
    //   184: astore_3
    //   185: aload_3
    //   186: bipush 22
    //   188: iconst_0
    //   189: iconst_4
    //   190: invokestatic 238	o/Ne:ˎ	(ICI)Ljava/lang/String;
    //   193: invokevirtual 244	java/lang/String:intern	()Ljava/lang/String;
    //   196: invokevirtual 248	java/lang/String:startsWith	(Ljava/lang/String;)Z
    //   199: istore_2
    //   200: iload_2
    //   201: ifeq +6 -> 207
    //   204: goto -153 -> 51
    //   207: goto +115 -> 322
    //   210: aload_0
    //   211: getfield 259	o/Ne:ˋ	Lcom/insidesecure/hce/MatrixHCECard;
    //   214: invokestatic 264	o/HQ:ˏ	(Lcom/insidesecure/hce/MatrixHCECard;)Lo/HQ;
    //   217: invokevirtual 268	o/HQ:ˊᐝ	()Z
    //   220: ifeq +6 -> 226
    //   223: goto +132 -> 355
    //   226: goto +192 -> 418
    //   229: aload_0
    //   230: aload_3
    //   231: iconst_4
    //   232: invokevirtual 251	java/lang/String:substring	(I)Ljava/lang/String;
    //   235: invokespecial 254	o/Ne:ˏ	(Ljava/lang/String;)Ljava/lang/String;
    //   238: invokevirtual 244	java/lang/String:intern	()Ljava/lang/String;
    //   241: astore_3
    //   242: goto +80 -> 322
    //   245: goto +40 -> 285
    //   248: iload_1
    //   249: lookupswitch	default:+27->276, 13:+-90->159, 38:+-39->210
    //   276: goto -117 -> 159
    //   279: bipush 13
    //   281: istore_1
    //   282: goto -34 -> 248
    //   285: getstatic 41	o/Ne:ꞌ	I
    //   288: bipush 13
    //   290: iadd
    //   291: istore_1
    //   292: iload_1
    //   293: sipush 128
    //   296: irem
    //   297: putstatic 43	o/Ne:ﾞ	I
    //   300: iload_1
    //   301: iconst_2
    //   302: irem
    //   303: ifne +6 -> 309
    //   306: goto +45 -> 351
    //   309: return
    //   310: goto -65 -> 245
    //   313: astore_3
    //   314: aload_3
    //   315: athrow
    //   316: bipush 49
    //   318: istore_1
    //   319: goto -192 -> 127
    //   322: aload 4
    //   324: aload_3
    //   325: iconst_0
    //   326: invokestatic 274	android/widget/Toast:makeText	(Landroid/content/Context;Ljava/lang/CharSequence;I)Landroid/widget/Toast;
    //   329: invokevirtual 277	android/widget/Toast:show	()V
    //   332: goto -87 -> 245
    //   335: goto +107 -> 442
    //   338: aload 4
    //   340: aload_3
    //   341: iconst_0
    //   342: invokestatic 274	android/widget/Toast:makeText	(Landroid/content/Context;Ljava/lang/CharSequence;I)Landroid/widget/Toast;
    //   345: invokevirtual 277	android/widget/Toast:show	()V
    //   348: goto +43 -> 391
    //   351: aconst_null
    //   352: arraylength
    //   353: istore_1
    //   354: return
    //   355: getstatic 41	o/Ne:ꞌ	I
    //   358: bipush 59
    //   360: iadd
    //   361: istore_1
    //   362: iload_1
    //   363: sipush 128
    //   366: irem
    //   367: putstatic 43	o/Ne:ﾞ	I
    //   370: iload_1
    //   371: iconst_2
    //   372: irem
    //   373: ifne +6 -> 379
    //   376: goto -328 -> 48
    //   379: goto -376 -> 3
    //   382: bipush 38
    //   384: istore_1
    //   385: goto -137 -> 248
    //   388: goto -78 -> 310
    //   391: getstatic 43	o/Ne:ﾞ	I
    //   394: bipush 25
    //   396: iadd
    //   397: istore_1
    //   398: iload_1
    //   399: sipush 128
    //   402: irem
    //   403: putstatic 41	o/Ne:ꞌ	I
    //   406: iload_1
    //   407: iconst_2
    //   408: irem
    //   409: ifeq +6 -> 415
    //   412: goto -307 -> 105
    //   415: goto +24 -> 439
    //   418: aload_0
    //   419: getfield 218	o/Ne:ˏ	Landroid/support/v14/preference/SwitchPreference;
    //   422: iconst_1
    //   423: invokevirtual 223	android/support/v14/preference/SwitchPreference:ॱ	(Z)V
    //   426: aload_0
    //   427: getfield 259	o/Ne:ˋ	Lcom/insidesecure/hce/MatrixHCECard;
    //   430: invokeinterface 282 1 0
    //   435: pop
    //   436: goto -48 -> 388
    //   439: goto -51 -> 388
    //   442: aload_0
    //   443: getfield 218	o/Ne:ˏ	Landroid/support/v14/preference/SwitchPreference;
    //   446: invokevirtual 284	android/support/v14/preference/SwitchPreference:ॱ	()Z
    //   449: ifeq +6 -> 455
    //   452: goto -70 -> 382
    //   455: goto -176 -> 279
    // Local variable table:
    //   start	length	slot	name	signature
    //   0	458	0	this	Ne
    //   57	352	1	i	int
    //   199	2	2	bool	boolean
    //   24	73	3	str	String
    //   108	5	3	localException1	Exception
    //   123	119	3	localObject	Object
    //   313	28	3	localException2	Exception
    //   15	324	4	localContext	Context
    // Exception table:
    //   from	to	target	type
    //   169	175	108	java/lang/Exception
    //   159	164	313	java/lang/Exception
    //   164	169	313	java/lang/Exception
    //   169	175	313	java/lang/Exception
    //   175	179	313	java/lang/Exception
    //   179	200	313	java/lang/Exception
  }
  
  /* Error */
  private void ʼᐝ()
  {
    // Byte code:
    //   0: goto +179 -> 179
    //   3: getstatic 43	o/Ne:ﾞ	I
    //   6: bipush 49
    //   8: iadd
    //   9: istore_1
    //   10: iload_1
    //   11: sipush 128
    //   14: irem
    //   15: putstatic 41	o/Ne:ꞌ	I
    //   18: iload_1
    //   19: iconst_2
    //   20: irem
    //   21: ifeq +4 -> 25
    //   24: return
    //   25: return
    //   26: astore_2
    //   27: aload_2
    //   28: athrow
    //   29: new 287	o/IM
    //   32: dup
    //   33: aload_0
    //   34: invokevirtual 227	o/Ne:ˏॱ	()Landroid/content/Context;
    //   37: getstatic 290	o/MH$ᐝ:loading	I
    //   40: invokespecial 293	o/IM:<init>	(Landroid/content/Context;I)V
    //   43: astore_2
    //   44: aload_2
    //   45: invokevirtual 296	o/IM:ˏ	()Lo/ᐸ;
    //   48: pop
    //   49: aload_0
    //   50: getfield 259	o/Ne:ˋ	Lcom/insidesecure/hce/MatrixHCECard;
    //   53: invokestatic 264	o/HQ:ˏ	(Lcom/insidesecure/hce/MatrixHCECard;)Lo/HQ;
    //   56: invokevirtual 299	o/HQ:ॱॱ	()Ljava/lang/String;
    //   59: astore_3
    //   60: new 301	java/util/ArrayList
    //   63: dup
    //   64: invokespecial 302	java/util/ArrayList:<init>	()V
    //   67: astore 4
    //   69: aload 4
    //   71: getstatic 308	o/FV:INITIATED	Lo/FV;
    //   74: invokeinterface 314 2 0
    //   79: pop
    //   80: aload 4
    //   82: getstatic 317	o/FV:ACKNOWLEDGED	Lo/FV;
    //   85: invokeinterface 314 2 0
    //   90: pop
    //   91: goto +17 -> 108
    //   94: astore_2
    //   95: aload_2
    //   96: invokevirtual 323	java/lang/Throwable:getCause	()Ljava/lang/Throwable;
    //   99: astore_3
    //   100: aload_3
    //   101: ifnull +5 -> 106
    //   104: aload_3
    //   105: athrow
    //   106: aload_2
    //   107: athrow
    //   108: iconst_4
    //   109: sipush 135
    //   112: ldc_w 324
    //   115: invokestatic 329	o/O:ˋ	(IIC)Ljava/lang/Object;
    //   118: checkcast 331	java/lang/Class
    //   121: ldc_w 332
    //   124: aconst_null
    //   125: invokevirtual 336	java/lang/Class:getMethod	(Ljava/lang/String;[Ljava/lang/Class;)Ljava/lang/reflect/Method;
    //   128: aconst_null
    //   129: aconst_null
    //   130: invokevirtual 342	java/lang/reflect/Method:invoke	(Ljava/lang/Object;[Ljava/lang/Object;)Ljava/lang/Object;
    //   133: checkcast 344	o/It
    //   136: astore 5
    //   138: aload 5
    //   140: new 346	o/Ge
    //   143: dup
    //   144: aload_3
    //   145: aload 4
    //   147: invokespecial 349	o/Ge:<init>	(Ljava/lang/String;Ljava/util/List;)V
    //   150: invokeinterface 352 2 0
    //   155: new 6	o/Ne$1
    //   158: dup
    //   159: aload_0
    //   160: aload_0
    //   161: invokevirtual 227	o/Ne:ˏॱ	()Landroid/content/Context;
    //   164: aload_2
    //   165: invokespecial 355	o/Ne$1:<init>	(Lo/Ne;Landroid/content/Context;Lo/IM;)V
    //   168: invokeinterface 360 2 0
    //   173: goto -170 -> 3
    //   176: astore_2
    //   177: aload_2
    //   178: athrow
    //   179: goto -150 -> 29
    // Local variable table:
    //   start	length	slot	name	signature
    //   0	182	0	this	Ne
    //   9	12	1	i	int
    //   26	2	2	localException1	Exception
    //   43	2	2	localIM1	IM
    //   94	71	2	localIM2	IM
    //   176	2	2	localException2	Exception
    //   59	86	3	localObject	Object
    //   67	79	4	localArrayList	java.util.ArrayList
    //   136	3	5	localIt	It
    // Exception table:
    //   from	to	target	type
    //   10	18	26	java/lang/Exception
    //   108	138	94	finally
    //   3	10	176	java/lang/Exception
    //   10	18	176	java/lang/Exception
  }
  
  /* Error */
  private void ʽ(int paramInt)
  {
    // Byte code:
    //   0: goto +35 -> 35
    //   3: goto +38 -> 41
    //   6: aload_0
    //   7: aload 7
    //   9: iconst_4
    //   10: invokevirtual 251	java/lang/String:substring	(I)Ljava/lang/String;
    //   13: invokespecial 254	o/Ne:ˏ	(Ljava/lang/String;)Ljava/lang/String;
    //   16: invokevirtual 244	java/lang/String:intern	()Ljava/lang/String;
    //   19: astore 4
    //   21: goto +17 -> 38
    //   24: astore 4
    //   26: aload 4
    //   28: athrow
    //   29: bipush 60
    //   31: istore_1
    //   32: goto +90 -> 122
    //   35: goto +317 -> 352
    //   38: goto +388 -> 426
    //   41: aload_0
    //   42: aload 7
    //   44: iconst_4
    //   45: invokevirtual 251	java/lang/String:substring	(I)Ljava/lang/String;
    //   48: invokespecial 254	o/Ne:ˏ	(Ljava/lang/String;)Ljava/lang/String;
    //   51: invokevirtual 244	java/lang/String:intern	()Ljava/lang/String;
    //   54: astore 7
    //   56: new 363	o/E
    //   59: dup
    //   60: aload 8
    //   62: aload 5
    //   64: aload 4
    //   66: aload 6
    //   68: aload 7
    //   70: invokespecial 366	o/E:<init>	(Landroid/content/Context;Ljava/lang/String;Ljava/lang/String;Ljava/lang/String;Ljava/lang/String;)V
    //   73: new 12	o/Ne$4
    //   76: dup
    //   77: aload_0
    //   78: invokespecial 369	o/Ne$4:<init>	(Lo/Ne;)V
    //   81: invokevirtual 372	o/E:ॱ	(Lo/ᐸ$ˏ;)Lo/ᐸ$If;
    //   84: invokevirtual 375	o/ᐸ$If:ˏ	()Lo/ᐸ;
    //   87: pop
    //   88: return
    //   89: aload_0
    //   90: invokevirtual 379	o/Ne:ॱᐝ	()Landroid/content/res/Resources;
    //   93: getstatic 384	o/MH$ˎ:settings_card_check_p2p_operations_description	I
    //   96: iload_1
    //   97: iconst_1
    //   98: anewarray 386	java/lang/Object
    //   101: dup
    //   102: iconst_0
    //   103: iload_1
    //   104: invokestatic 392	java/lang/Integer:valueOf	(I)Ljava/lang/Integer;
    //   107: aastore
    //   108: invokevirtual 398	android/content/res/Resources:getQuantityString	(II[Ljava/lang/Object;)Ljava/lang/String;
    //   111: astore 4
    //   113: goto +313 -> 426
    //   116: bipush 89
    //   118: istore_2
    //   119: goto +140 -> 259
    //   122: aload 6
    //   124: astore 4
    //   126: aload 6
    //   128: astore 7
    //   130: iload_1
    //   131: lookupswitch	default:+25->156, 60:+-110->21, 71:+262->393
    //   156: aload 6
    //   158: astore 4
    //   160: goto -139 -> 21
    //   163: getstatic 41	o/Ne:ꞌ	I
    //   166: bipush 9
    //   168: iadd
    //   169: istore_1
    //   170: iload_1
    //   171: sipush 128
    //   174: irem
    //   175: putstatic 43	o/Ne:ﾞ	I
    //   178: iload_1
    //   179: iconst_2
    //   180: irem
    //   181: ifne +6 -> 187
    //   184: goto -181 -> 3
    //   187: goto -146 -> 41
    //   190: goto -184 -> 6
    //   193: iload_1
    //   194: ifne +6 -> 200
    //   197: goto -81 -> 116
    //   200: goto +265 -> 465
    //   203: aload_0
    //   204: aload 5
    //   206: iconst_4
    //   207: invokevirtual 251	java/lang/String:substring	(I)Ljava/lang/String;
    //   210: invokespecial 254	o/Ne:ˏ	(Ljava/lang/String;)Ljava/lang/String;
    //   213: invokevirtual 244	java/lang/String:intern	()Ljava/lang/String;
    //   216: astore 5
    //   218: goto -25 -> 193
    //   221: aload_0
    //   222: getstatic 401	o/MH$ᐝ:settings_card_delete_card_dialog_description	I
    //   225: invokevirtual 235	o/Ne:ˋ	(I)Ljava/lang/String;
    //   228: astore 6
    //   230: aload 6
    //   232: bipush 22
    //   234: iconst_0
    //   235: iconst_4
    //   236: invokestatic 238	o/Ne:ˎ	(ICI)Ljava/lang/String;
    //   239: invokevirtual 244	java/lang/String:intern	()Ljava/lang/String;
    //   242: invokevirtual 248	java/lang/String:startsWith	(Ljava/lang/String;)Z
    //   245: ifeq +6 -> 251
    //   248: goto +172 -> 420
    //   251: goto -222 -> 29
    //   254: astore 4
    //   256: aload 4
    //   258: athrow
    //   259: iload_2
    //   260: lookupswitch	default:+28->288, 64:+-171->89, 89:+28->288
    //   288: getstatic 43	o/Ne:ﾞ	I
    //   291: bipush 123
    //   293: iadd
    //   294: istore_1
    //   295: iload_1
    //   296: sipush 128
    //   299: irem
    //   300: putstatic 41	o/Ne:ꞌ	I
    //   303: iload_1
    //   304: iconst_2
    //   305: irem
    //   306: ifeq +6 -> 312
    //   309: goto +6 -> 315
    //   312: goto -91 -> 221
    //   315: aload_0
    //   316: getstatic 401	o/MH$ᐝ:settings_card_delete_card_dialog_description	I
    //   319: invokevirtual 235	o/Ne:ˋ	(I)Ljava/lang/String;
    //   322: astore 4
    //   324: aload 4
    //   326: bipush 33
    //   328: iconst_0
    //   329: iconst_2
    //   330: invokestatic 238	o/Ne:ˎ	(ICI)Ljava/lang/String;
    //   333: invokevirtual 244	java/lang/String:intern	()Ljava/lang/String;
    //   336: invokevirtual 248	java/lang/String:startsWith	(Ljava/lang/String;)Z
    //   339: ifeq +10 -> 349
    //   342: aload 4
    //   344: astore 7
    //   346: goto +47 -> 393
    //   349: goto -328 -> 21
    //   352: getstatic 404	o/MH$ᐝ:settings_card_delete_card_dialog_title	I
    //   355: istore_2
    //   356: aload_0
    //   357: iload_2
    //   358: invokevirtual 235	o/Ne:ˋ	(I)Ljava/lang/String;
    //   361: astore 5
    //   363: bipush 22
    //   365: iconst_0
    //   366: iconst_4
    //   367: invokestatic 238	o/Ne:ˎ	(ICI)Ljava/lang/String;
    //   370: astore 4
    //   372: aload 5
    //   374: aload 4
    //   376: invokevirtual 244	java/lang/String:intern	()Ljava/lang/String;
    //   379: invokevirtual 248	java/lang/String:startsWith	(Ljava/lang/String;)Z
    //   382: istore_3
    //   383: iload_3
    //   384: ifeq +6 -> 390
    //   387: goto -184 -> 203
    //   390: goto -197 -> 193
    //   393: getstatic 41	o/Ne:ꞌ	I
    //   396: bipush 83
    //   398: iadd
    //   399: istore_1
    //   400: iload_1
    //   401: sipush 128
    //   404: irem
    //   405: putstatic 43	o/Ne:ﾞ	I
    //   408: iload_1
    //   409: iconst_2
    //   410: irem
    //   411: ifne +6 -> 417
    //   414: goto -224 -> 190
    //   417: goto -411 -> 6
    //   420: bipush 71
    //   422: istore_1
    //   423: goto -301 -> 122
    //   426: aload_0
    //   427: invokevirtual 227	o/Ne:ˏॱ	()Landroid/content/Context;
    //   430: astore 8
    //   432: aload_0
    //   433: getstatic 407	o/MH$ᐝ:delete	I
    //   436: invokevirtual 235	o/Ne:ˋ	(I)Ljava/lang/String;
    //   439: astore 6
    //   441: aload 6
    //   443: bipush 22
    //   445: iconst_0
    //   446: iconst_4
    //   447: invokestatic 238	o/Ne:ˎ	(ICI)Ljava/lang/String;
    //   450: invokevirtual 244	java/lang/String:intern	()Ljava/lang/String;
    //   453: invokevirtual 248	java/lang/String:startsWith	(Ljava/lang/String;)Z
    //   456: ifeq +6 -> 462
    //   459: goto +12 -> 471
    //   462: goto +24 -> 486
    //   465: bipush 64
    //   467: istore_2
    //   468: goto -209 -> 259
    //   471: aload_0
    //   472: aload 6
    //   474: iconst_4
    //   475: invokevirtual 251	java/lang/String:substring	(I)Ljava/lang/String;
    //   478: invokespecial 254	o/Ne:ˏ	(Ljava/lang/String;)Ljava/lang/String;
    //   481: invokevirtual 244	java/lang/String:intern	()Ljava/lang/String;
    //   484: astore 6
    //   486: aload_0
    //   487: getstatic 410	o/MH$ᐝ:cancel	I
    //   490: invokevirtual 235	o/Ne:ˋ	(I)Ljava/lang/String;
    //   493: astore 7
    //   495: aload 7
    //   497: bipush 22
    //   499: iconst_0
    //   500: iconst_4
    //   501: invokestatic 238	o/Ne:ˎ	(ICI)Ljava/lang/String;
    //   504: invokevirtual 244	java/lang/String:intern	()Ljava/lang/String;
    //   507: invokevirtual 248	java/lang/String:startsWith	(Ljava/lang/String;)Z
    //   510: ifeq +6 -> 516
    //   513: goto -350 -> 163
    //   516: goto -460 -> 56
    // Local variable table:
    //   start	length	slot	name	signature
    //   0	519	0	this	Ne
    //   0	519	1	paramInt	int
    //   118	350	2	i	int
    //   382	2	3	bool	boolean
    //   19	1	4	str1	String
    //   24	41	4	localException1	Exception
    //   111	48	4	localObject1	Object
    //   254	3	4	localException2	Exception
    //   322	53	4	str2	String
    //   62	311	5	str3	String
    //   66	419	6	str4	String
    //   7	489	7	localObject2	Object
    //   60	371	8	localContext	Context
    // Exception table:
    //   from	to	target	type
    //   356	363	24	java/lang/Exception
    //   352	356	254	java/lang/Exception
    //   356	363	254	java/lang/Exception
    //   363	372	254	java/lang/Exception
    //   372	383	254	java/lang/Exception
  }
  
  private void ʽˊ()
  {
    break label369;
    Object localObject4;
    Object localObject1 = ˏ(((String)localObject4).substring(4)).intern();
    break label177;
    label19:
    int i = 53;
    break label216;
    label25:
    localObject1 = ˏ(((String)localObject1).substring(4)).intern();
    break label52;
    label41:
    i = 0;
    break label491;
    label46:
    i = 30;
    for (;;)
    {
      label52:
      final GQ localGQ;
      final HQ localHQ;
      try
      {
        ᐸ.If localIf;
        localObject1 = localIf.ॱ((CharSequence)localObject1);
        localObject4 = ˏॱ();
        i = MH.iF.black;
        try
        {
          i = ᔆ.ˊ((Context)localObject4, i);
          ((ᐸ.If)localObject1).ˏ(i).ˋ(ᔆ.ˊ(ˏॱ(), MH.iF.black)).ˋ(localGQ.ᐝ(), true).ˋ(false).ॱ(new ᐸ.ˏ()
          {
            public void ˋ(ᐸ paramAnonymousᐸ, ะ paramAnonymousะ)
            {
              if (localGQ.ˎ.ʻ())
              {
                paramAnonymousะ = localGQ.ˎ.ʽ();
                if (localHQ.ˊˋ().equals(paramAnonymousะ))
                {
                  paramAnonymousᐸ.dismiss();
                }
                else
                {
                  localHQ.ʽ(paramAnonymousะ);
                  paramAnonymousᐸ.dismiss();
                }
                return;
              }
              localGQ.ˎ.clearFocus();
            }
          }).ˊ(new ᐸ.ˏ()
          {
            public void ˋ(ᐸ paramAnonymousᐸ, ะ paramAnonymousะ)
            {
              paramAnonymousᐸ.dismiss();
            }
          }).ˏ();
          return;
        }
        catch (Exception localException1)
        {
          throw localException1;
        }
        continue;
        i = ﾞ + 65;
        ꞌ = i % 128;
        label177:
        label216:
        Object localObject2;
        if (i % 2 == 0)
        {
          continue;
          i = 2;
          break label459;
          localIf = localIf.ˎ(localException1);
          localObject4 = ˋ(MH.ᐝ.cancel);
          if (((String)localObject4).startsWith(ˎ(22, '\000', 4).intern())) {
            continue;
          }
          continue;
          localObject2 = localObject4;
        }
        switch (i)
        {
        default: 
          localObject2 = localObject4;
          break;
        case 30: 
          i = ꞌ + 117;
          ﾞ = i % 128;
          if (i % 2 == 0) {
            continue;
          }
          continue;
          i = ꞌ + 111;
          ﾞ = i % 128;
          if (i % 2 != 0)
          {
            break label25;
            continue;
            localObject2 = ˏ(((String)localObject4).substring(4)).intern();
            continue;
            i = 80;
            break label459;
            localIf = ((ᐸ.If)localObject4).ˊ((CharSequence)localObject2);
            localObject4 = ˋ(MH.ᐝ.confirm);
            if (((String)localObject4).startsWith(ˎ(22, '\000', 4).intern())) {
              break label41;
            }
            continue;
          }
          break label25;
          label369:
          continue;
          localHQ = HQ.ˏ(this.ˋ);
          localGQ = (GQ)ˌ.ˎ(LayoutInflater.from(ˏॱ()), MH.if.dialog_input_text, null, false);
          localObject4 = ˋ(MH.ᐝ.settings_card_change_card_name_hint);
          if (((String)localObject4).startsWith(ˎ(22, '\000', 4).intern())) {
            break label46;
          }
          break label19;
          localObject2 = ˏ(((String)localObject4).substring(4)).intern();
          continue;
          break;
          i = 1;
        }
      }
      catch (Exception localException2)
      {
        throw localException2;
      }
      label459:
      Object localObject3 = localObject4;
      switch (i)
      {
      }
      continue;
      label491:
      localObject3 = localObject4;
      switch (i)
      {
      }
      break;
      localGQ.ˊ((String)localObject3);
      localGQ.ˎ.ˏ(new Fx());
      localGQ.ˎ.setMaxInputLength(24);
      localGQ.ˎ.requestFocus();
      localGQ.ˎ.setText(localHQ.ˊˋ());
      localObject4 = new ᐸ.If(ˏॱ());
      localObject3 = ˋ(MH.ᐝ.settings_card_change_card_name);
      if (((String)localObject3).startsWith(ˎ(22, '\000', 4).intern())) {}
    }
  }
  
  /* Error */
  private boolean ʽˋ()
  {
    // Byte code:
    //   0: goto +58 -> 58
    //   3: getstatic 43	o/Ne:ﾞ	I
    //   6: istore_1
    //   7: iload_1
    //   8: iconst_3
    //   9: iadd
    //   10: istore_1
    //   11: iload_1
    //   12: sipush 128
    //   15: irem
    //   16: putstatic 41	o/Ne:ꞌ	I
    //   19: iload_1
    //   20: iconst_2
    //   21: irem
    //   22: ifeq +6 -> 28
    //   25: goto +218 -> 243
    //   28: goto +49 -> 77
    //   31: getstatic 41	o/Ne:ꞌ	I
    //   34: bipush 97
    //   36: iadd
    //   37: istore_1
    //   38: iload_1
    //   39: sipush 128
    //   42: irem
    //   43: putstatic 43	o/Ne:ﾞ	I
    //   46: iload_1
    //   47: iconst_2
    //   48: irem
    //   49: ifne +6 -> 55
    //   52: goto +199 -> 251
    //   55: goto +30 -> 85
    //   58: goto +167 -> 225
    //   61: goto -58 -> 3
    //   64: aload_0
    //   65: invokespecial 509	o/Ne:ʾॱ	()Z
    //   68: ifne +6 -> 74
    //   71: goto -40 -> 31
    //   74: goto -13 -> 61
    //   77: iconst_1
    //   78: ireturn
    //   79: bipush 39
    //   81: istore_1
    //   82: goto +111 -> 193
    //   85: goto +20 -> 105
    //   88: astore 4
    //   90: aload 4
    //   92: invokevirtual 323	java/lang/Throwable:getCause	()Ljava/lang/Throwable;
    //   95: astore_3
    //   96: aload_3
    //   97: ifnull +5 -> 102
    //   100: aload_3
    //   101: athrow
    //   102: aload 4
    //   104: athrow
    //   105: iconst_4
    //   106: sipush 267
    //   109: sipush 14788
    //   112: invokestatic 329	o/O:ˋ	(IIC)Ljava/lang/Object;
    //   115: checkcast 331	java/lang/Class
    //   118: ldc_w 332
    //   121: aconst_null
    //   122: invokevirtual 336	java/lang/Class:getMethod	(Ljava/lang/String;[Ljava/lang/Class;)Ljava/lang/reflect/Method;
    //   125: aconst_null
    //   126: aconst_null
    //   127: invokevirtual 342	java/lang/reflect/Method:invoke	(Ljava/lang/Object;[Ljava/lang/Object;)Ljava/lang/Object;
    //   130: astore_3
    //   131: goto +20 -> 151
    //   134: astore_3
    //   135: aload_3
    //   136: invokevirtual 323	java/lang/Throwable:getCause	()Ljava/lang/Throwable;
    //   139: astore 4
    //   141: aload 4
    //   143: ifnull +6 -> 149
    //   146: aload 4
    //   148: athrow
    //   149: aload_3
    //   150: athrow
    //   151: iconst_4
    //   152: sipush 267
    //   155: sipush 14788
    //   158: invokestatic 329	o/O:ˋ	(IIC)Ljava/lang/Object;
    //   161: checkcast 331	java/lang/Class
    //   164: ldc_w 511
    //   167: aconst_null
    //   168: invokevirtual 336	java/lang/Class:getMethod	(Ljava/lang/String;[Ljava/lang/Class;)Ljava/lang/reflect/Method;
    //   171: aload_3
    //   172: aconst_null
    //   173: invokevirtual 342	java/lang/reflect/Method:invoke	(Ljava/lang/Object;[Ljava/lang/Object;)Ljava/lang/Object;
    //   176: checkcast 513	java/lang/Boolean
    //   179: invokevirtual 516	java/lang/Boolean:booleanValue	()Z
    //   182: istore_2
    //   183: iload_2
    //   184: ifeq +6 -> 190
    //   187: goto -126 -> 61
    //   190: goto +33 -> 223
    //   193: iload_1
    //   194: lookupswitch	default:+26->220, 11:+-130->64, 39:+-133->61
    //   220: goto -156 -> 64
    //   223: iconst_0
    //   224: ireturn
    //   225: aload_0
    //   226: getfield 259	o/Ne:ˋ	Lcom/insidesecure/hce/MatrixHCECard;
    //   229: invokeinterface 519 1 0
    //   234: ifeq +6 -> 240
    //   237: goto +120 -> 357
    //   240: goto -179 -> 61
    //   243: iconst_1
    //   244: ireturn
    //   245: bipush 11
    //   247: istore_1
    //   248: goto -55 -> 193
    //   251: goto +20 -> 271
    //   254: astore_3
    //   255: aload_3
    //   256: invokevirtual 323	java/lang/Throwable:getCause	()Ljava/lang/Throwable;
    //   259: astore 4
    //   261: aload 4
    //   263: ifnull +6 -> 269
    //   266: aload 4
    //   268: athrow
    //   269: aload_3
    //   270: athrow
    //   271: iconst_4
    //   272: sipush 267
    //   275: sipush 14788
    //   278: invokestatic 329	o/O:ˋ	(IIC)Ljava/lang/Object;
    //   281: checkcast 331	java/lang/Class
    //   284: ldc_w 332
    //   287: aconst_null
    //   288: invokevirtual 336	java/lang/Class:getMethod	(Ljava/lang/String;[Ljava/lang/Class;)Ljava/lang/reflect/Method;
    //   291: aconst_null
    //   292: aconst_null
    //   293: invokevirtual 342	java/lang/reflect/Method:invoke	(Ljava/lang/Object;[Ljava/lang/Object;)Ljava/lang/Object;
    //   296: astore_3
    //   297: goto +20 -> 317
    //   300: astore 4
    //   302: aload 4
    //   304: invokevirtual 323	java/lang/Throwable:getCause	()Ljava/lang/Throwable;
    //   307: astore_3
    //   308: aload_3
    //   309: ifnull +5 -> 314
    //   312: aload_3
    //   313: athrow
    //   314: aload 4
    //   316: athrow
    //   317: iconst_4
    //   318: sipush 267
    //   321: sipush 14788
    //   324: invokestatic 329	o/O:ˋ	(IIC)Ljava/lang/Object;
    //   327: checkcast 331	java/lang/Class
    //   330: ldc_w 511
    //   333: aconst_null
    //   334: invokevirtual 336	java/lang/Class:getMethod	(Ljava/lang/String;[Ljava/lang/Class;)Ljava/lang/reflect/Method;
    //   337: aload_3
    //   338: aconst_null
    //   339: invokevirtual 342	java/lang/reflect/Method:invoke	(Ljava/lang/Object;[Ljava/lang/Object;)Ljava/lang/Object;
    //   342: checkcast 513	java/lang/Boolean
    //   345: invokevirtual 516	java/lang/Boolean:booleanValue	()Z
    //   348: pop
    //   349: new 521	java/lang/NullPointerException
    //   352: dup
    //   353: invokespecial 522	java/lang/NullPointerException:<init>	()V
    //   356: athrow
    //   357: goto +20 -> 377
    //   360: astore 4
    //   362: aload 4
    //   364: invokevirtual 323	java/lang/Throwable:getCause	()Ljava/lang/Throwable;
    //   367: astore_3
    //   368: aload_3
    //   369: ifnull +5 -> 374
    //   372: aload_3
    //   373: athrow
    //   374: aload 4
    //   376: athrow
    //   377: iconst_4
    //   378: sipush 267
    //   381: sipush 14788
    //   384: invokestatic 329	o/O:ˋ	(IIC)Ljava/lang/Object;
    //   387: checkcast 331	java/lang/Class
    //   390: ldc_w 332
    //   393: aconst_null
    //   394: invokevirtual 336	java/lang/Class:getMethod	(Ljava/lang/String;[Ljava/lang/Class;)Ljava/lang/reflect/Method;
    //   397: aconst_null
    //   398: aconst_null
    //   399: invokevirtual 342	java/lang/reflect/Method:invoke	(Ljava/lang/Object;[Ljava/lang/Object;)Ljava/lang/Object;
    //   402: astore_3
    //   403: goto +20 -> 423
    //   406: astore 4
    //   408: aload 4
    //   410: invokevirtual 323	java/lang/Throwable:getCause	()Ljava/lang/Throwable;
    //   413: astore_3
    //   414: aload_3
    //   415: ifnull +5 -> 420
    //   418: aload_3
    //   419: athrow
    //   420: aload 4
    //   422: athrow
    //   423: iconst_4
    //   424: sipush 267
    //   427: sipush 14788
    //   430: invokestatic 329	o/O:ˋ	(IIC)Ljava/lang/Object;
    //   433: checkcast 331	java/lang/Class
    //   436: ldc_w 524
    //   439: aconst_null
    //   440: invokevirtual 336	java/lang/Class:getMethod	(Ljava/lang/String;[Ljava/lang/Class;)Ljava/lang/reflect/Method;
    //   443: aload_3
    //   444: aconst_null
    //   445: invokevirtual 342	java/lang/reflect/Method:invoke	(Ljava/lang/Object;[Ljava/lang/Object;)Ljava/lang/Object;
    //   448: checkcast 310	java/util/List
    //   451: astore_3
    //   452: aload_3
    //   453: invokeinterface 528 1 0
    //   458: iconst_1
    //   459: if_icmpeq +6 -> 465
    //   462: goto -217 -> 245
    //   465: goto -386 -> 79
    //   468: astore_3
    //   469: aload_3
    //   470: athrow
    //   471: astore_3
    //   472: aload_3
    //   473: athrow
    // Local variable table:
    //   start	length	slot	name	signature
    //   0	474	0	this	Ne
    //   6	242	1	i	int
    //   182	2	2	bool	boolean
    //   95	36	3	localObject1	Object
    //   134	38	3	localObject2	Object
    //   254	16	3	localObject3	Object
    //   296	157	3	localObject4	Object
    //   468	2	3	localException1	Exception
    //   471	2	3	localException2	Exception
    //   88	15	4	localObject5	Object
    //   139	128	4	localThrowable	Throwable
    //   300	15	4	localObject6	Object
    //   360	15	4	localObject7	Object
    //   406	15	4	localObject8	Object
    // Exception table:
    //   from	to	target	type
    //   105	131	88	finally
    //   151	183	134	finally
    //   271	297	254	finally
    //   317	349	300	finally
    //   377	403	360	finally
    //   423	452	406	finally
    //   255	261	468	java/lang/Exception
    //   266	269	468	java/lang/Exception
    //   269	271	468	java/lang/Exception
    //   302	308	468	java/lang/Exception
    //   312	314	468	java/lang/Exception
    //   314	317	468	java/lang/Exception
    //   349	357	468	java/lang/Exception
    //   3	7	471	java/lang/Exception
    //   11	19	471	java/lang/Exception
  }
  
  /* Error */
  private boolean ʾॱ()
  {
    // Byte code:
    //   0: goto +72 -> 72
    //   3: iconst_0
    //   4: istore_1
    //   5: goto +36 -> 41
    //   8: iload_1
    //   9: lookupswitch	default:+27->36, 53:+69->78, 69:+206->215
    //   36: goto +42 -> 78
    //   39: iconst_1
    //   40: istore_1
    //   41: iload_1
    //   42: tableswitch	default:+22->64, 0:+36->78, 1:+62->104
    //   64: goto +40 -> 104
    //   67: iconst_1
    //   68: istore_2
    //   69: goto +6 -> 75
    //   72: goto +11 -> 83
    //   75: goto +176 -> 251
    //   78: iconst_0
    //   79: istore_2
    //   80: goto -5 -> 75
    //   83: aload_0
    //   84: getfield 259	o/Ne:ˋ	Lcom/insidesecure/hce/MatrixHCECard;
    //   87: invokeinterface 519 1 0
    //   92: ifeq +6 -> 98
    //   95: goto +150 -> 245
    //   98: bipush 53
    //   100: istore_1
    //   101: goto -93 -> 8
    //   104: goto +20 -> 124
    //   107: astore_3
    //   108: aload_3
    //   109: invokevirtual 323	java/lang/Throwable:getCause	()Ljava/lang/Throwable;
    //   112: astore 4
    //   114: aload 4
    //   116: ifnull +6 -> 122
    //   119: aload 4
    //   121: athrow
    //   122: aload_3
    //   123: athrow
    //   124: iconst_4
    //   125: sipush 267
    //   128: sipush 14788
    //   131: invokestatic 329	o/O:ˋ	(IIC)Ljava/lang/Object;
    //   134: checkcast 331	java/lang/Class
    //   137: ldc_w 332
    //   140: aconst_null
    //   141: invokevirtual 336	java/lang/Class:getMethod	(Ljava/lang/String;[Ljava/lang/Class;)Ljava/lang/reflect/Method;
    //   144: aconst_null
    //   145: aconst_null
    //   146: invokevirtual 342	java/lang/reflect/Method:invoke	(Ljava/lang/Object;[Ljava/lang/Object;)Ljava/lang/Object;
    //   149: astore_3
    //   150: goto +20 -> 170
    //   153: astore_3
    //   154: aload_3
    //   155: invokevirtual 323	java/lang/Throwable:getCause	()Ljava/lang/Throwable;
    //   158: astore 4
    //   160: aload 4
    //   162: ifnull +6 -> 168
    //   165: aload 4
    //   167: athrow
    //   168: aload_3
    //   169: athrow
    //   170: iconst_4
    //   171: sipush 267
    //   174: sipush 14788
    //   177: invokestatic 329	o/O:ˋ	(IIC)Ljava/lang/Object;
    //   180: checkcast 331	java/lang/Class
    //   183: ldc_w 530
    //   186: aconst_null
    //   187: invokevirtual 336	java/lang/Class:getMethod	(Ljava/lang/String;[Ljava/lang/Class;)Ljava/lang/reflect/Method;
    //   190: aload_3
    //   191: aconst_null
    //   192: invokevirtual 342	java/lang/reflect/Method:invoke	(Ljava/lang/Object;[Ljava/lang/Object;)Ljava/lang/Object;
    //   195: checkcast 310	java/util/List
    //   198: astore_3
    //   199: aload_3
    //   200: invokeinterface 528 1 0
    //   205: iconst_1
    //   206: if_icmpne +6 -> 212
    //   209: goto -142 -> 67
    //   212: goto -134 -> 78
    //   215: getstatic 41	o/Ne:ꞌ	I
    //   218: bipush 57
    //   220: iadd
    //   221: istore_1
    //   222: iload_1
    //   223: sipush 128
    //   226: irem
    //   227: putstatic 43	o/Ne:ﾞ	I
    //   230: iload_1
    //   231: iconst_2
    //   232: irem
    //   233: ifne +6 -> 239
    //   236: goto +6 -> 242
    //   239: goto +48 -> 287
    //   242: goto +45 -> 287
    //   245: bipush 69
    //   247: istore_1
    //   248: goto -240 -> 8
    //   251: getstatic 41	o/Ne:ꞌ	I
    //   254: bipush 45
    //   256: iadd
    //   257: istore_1
    //   258: iload_1
    //   259: sipush 128
    //   262: irem
    //   263: putstatic 43	o/Ne:ﾞ	I
    //   266: iload_1
    //   267: iconst_2
    //   268: irem
    //   269: ifne +6 -> 275
    //   272: goto +5 -> 277
    //   275: iload_2
    //   276: ireturn
    //   277: bipush 78
    //   279: iconst_0
    //   280: idiv
    //   281: istore_1
    //   282: iload_2
    //   283: ireturn
    //   284: astore_3
    //   285: aload_3
    //   286: athrow
    //   287: aload_0
    //   288: getfield 259	o/Ne:ˋ	Lcom/insidesecure/hce/MatrixHCECard;
    //   291: invokestatic 264	o/HQ:ˏ	(Lcom/insidesecure/hce/MatrixHCECard;)Lo/HQ;
    //   294: invokevirtual 268	o/HQ:ˊᐝ	()Z
    //   297: ifne +6 -> 303
    //   300: goto -261 -> 39
    //   303: goto -300 -> 3
    // Local variable table:
    //   start	length	slot	name	signature
    //   0	306	0	this	Ne
    //   4	278	1	i	int
    //   68	215	2	bool	boolean
    //   107	16	3	localObject1	Object
    //   149	1	3	localObject2	Object
    //   153	38	3	localObject3	Object
    //   198	2	3	localList	java.util.List
    //   284	2	3	localException	Exception
    //   112	54	4	localThrowable	Throwable
    // Exception table:
    //   from	to	target	type
    //   124	150	107	finally
    //   170	199	153	finally
    //   215	222	284	java/lang/Exception
    //   222	230	284	java/lang/Exception
  }
  
  /* Error */
  private void ˊ(String paramString)
  {
    // Byte code:
    //   0: goto +268 -> 268
    //   3: aload_0
    //   4: new 287	o/IM
    //   7: dup
    //   8: aload_0
    //   9: invokevirtual 227	o/Ne:ˏॱ	()Landroid/content/Context;
    //   12: getstatic 533	o/MH$ᐝ:deleting_card	I
    //   15: invokespecial 293	o/IM:<init>	(Landroid/content/Context;I)V
    //   18: putfield 535	o/Ne:ʻ	Lo/IM;
    //   21: aload_0
    //   22: getfield 535	o/Ne:ʻ	Lo/IM;
    //   25: invokevirtual 296	o/IM:ˏ	()Lo/ᐸ;
    //   28: pop
    //   29: bipush 26
    //   31: iconst_0
    //   32: bipush 12
    //   34: invokestatic 238	o/Ne:ˎ	(ICI)Ljava/lang/String;
    //   37: invokevirtual 244	java/lang/String:intern	()Ljava/lang/String;
    //   40: astore_3
    //   41: new 537	java/lang/StringBuilder
    //   44: dup
    //   45: invokespecial 538	java/lang/StringBuilder:<init>	()V
    //   48: bipush 38
    //   50: iconst_0
    //   51: bipush 35
    //   53: invokestatic 238	o/Ne:ˎ	(ICI)Ljava/lang/String;
    //   56: invokevirtual 244	java/lang/String:intern	()Ljava/lang/String;
    //   59: invokevirtual 542	java/lang/StringBuilder:append	(Ljava/lang/String;)Ljava/lang/StringBuilder;
    //   62: aload_1
    //   63: invokevirtual 542	java/lang/StringBuilder:append	(Ljava/lang/String;)Ljava/lang/StringBuilder;
    //   66: invokevirtual 545	java/lang/StringBuilder:toString	()Ljava/lang/String;
    //   69: astore 4
    //   71: goto +17 -> 88
    //   74: astore_1
    //   75: aload_1
    //   76: invokevirtual 323	java/lang/Throwable:getCause	()Ljava/lang/Throwable;
    //   79: astore_3
    //   80: aload_3
    //   81: ifnull +5 -> 86
    //   84: aload_3
    //   85: athrow
    //   86: aload_1
    //   87: athrow
    //   88: iconst_4
    //   89: bipush 42
    //   91: ldc_w 546
    //   94: invokestatic 329	o/O:ˋ	(IIC)Ljava/lang/Object;
    //   97: checkcast 331	java/lang/Class
    //   100: ldc_w 547
    //   103: iconst_2
    //   104: anewarray 331	java/lang/Class
    //   107: dup
    //   108: iconst_0
    //   109: ldc -16
    //   111: aastore
    //   112: dup
    //   113: iconst_1
    //   114: ldc -16
    //   116: aastore
    //   117: invokevirtual 336	java/lang/Class:getMethod	(Ljava/lang/String;[Ljava/lang/Class;)Ljava/lang/reflect/Method;
    //   120: aconst_null
    //   121: iconst_2
    //   122: anewarray 386	java/lang/Object
    //   125: dup
    //   126: iconst_0
    //   127: aload_3
    //   128: aastore
    //   129: dup
    //   130: iconst_1
    //   131: aload 4
    //   133: aastore
    //   134: invokevirtual 342	java/lang/reflect/Method:invoke	(Ljava/lang/Object;[Ljava/lang/Object;)Ljava/lang/Object;
    //   137: pop
    //   138: goto +17 -> 155
    //   141: astore_1
    //   142: aload_1
    //   143: invokevirtual 323	java/lang/Throwable:getCause	()Ljava/lang/Throwable;
    //   146: astore_3
    //   147: aload_3
    //   148: ifnull +5 -> 153
    //   151: aload_3
    //   152: athrow
    //   153: aload_1
    //   154: athrow
    //   155: iconst_4
    //   156: sipush 267
    //   159: sipush 14788
    //   162: invokestatic 329	o/O:ˋ	(IIC)Ljava/lang/Object;
    //   165: checkcast 331	java/lang/Class
    //   168: ldc_w 332
    //   171: aconst_null
    //   172: invokevirtual 336	java/lang/Class:getMethod	(Ljava/lang/String;[Ljava/lang/Class;)Ljava/lang/reflect/Method;
    //   175: aconst_null
    //   176: aconst_null
    //   177: invokevirtual 342	java/lang/reflect/Method:invoke	(Ljava/lang/Object;[Ljava/lang/Object;)Ljava/lang/Object;
    //   180: astore_3
    //   181: goto +17 -> 198
    //   184: astore_1
    //   185: aload_1
    //   186: invokevirtual 323	java/lang/Throwable:getCause	()Ljava/lang/Throwable;
    //   189: astore_3
    //   190: aload_3
    //   191: ifnull +5 -> 196
    //   194: aload_3
    //   195: athrow
    //   196: aload_1
    //   197: athrow
    //   198: iconst_4
    //   199: sipush 267
    //   202: sipush 14788
    //   205: invokestatic 329	o/O:ˋ	(IIC)Ljava/lang/Object;
    //   208: checkcast 331	java/lang/Class
    //   211: ldc_w 332
    //   214: iconst_3
    //   215: anewarray 331	java/lang/Class
    //   218: dup
    //   219: iconst_0
    //   220: ldc -16
    //   222: aastore
    //   223: dup
    //   224: iconst_1
    //   225: getstatic 551	java/lang/Boolean:TYPE	Ljava/lang/Class;
    //   228: aastore
    //   229: dup
    //   230: iconst_2
    //   231: getstatic 551	java/lang/Boolean:TYPE	Ljava/lang/Class;
    //   234: aastore
    //   235: invokevirtual 336	java/lang/Class:getMethod	(Ljava/lang/String;[Ljava/lang/Class;)Ljava/lang/reflect/Method;
    //   238: aload_3
    //   239: iconst_3
    //   240: anewarray 386	java/lang/Object
    //   243: dup
    //   244: iconst_0
    //   245: aload_1
    //   246: aastore
    //   247: dup
    //   248: iconst_1
    //   249: iconst_1
    //   250: invokestatic 554	java/lang/Boolean:valueOf	(Z)Ljava/lang/Boolean;
    //   253: aastore
    //   254: dup
    //   255: iconst_2
    //   256: iconst_1
    //   257: invokestatic 554	java/lang/Boolean:valueOf	(Z)Ljava/lang/Boolean;
    //   260: aastore
    //   261: invokevirtual 342	java/lang/reflect/Method:invoke	(Ljava/lang/Object;[Ljava/lang/Object;)Ljava/lang/Object;
    //   264: pop
    //   265: goto +6 -> 271
    //   268: goto -265 -> 3
    //   271: getstatic 43	o/Ne:ﾞ	I
    //   274: bipush 51
    //   276: iadd
    //   277: istore_2
    //   278: iload_2
    //   279: sipush 128
    //   282: irem
    //   283: putstatic 41	o/Ne:ꞌ	I
    //   286: iload_2
    //   287: iconst_2
    //   288: irem
    //   289: ifeq +6 -> 295
    //   292: goto +4 -> 296
    //   295: return
    //   296: return
    // Local variable table:
    //   start	length	slot	name	signature
    //   0	297	0	this	Ne
    //   0	297	1	paramString	String
    //   277	12	2	i	int
    //   40	199	3	localObject	Object
    //   69	63	4	str	String
    // Exception table:
    //   from	to	target	type
    //   88	138	74	finally
    //   155	181	141	finally
    //   198	265	184	finally
  }
  
  /* Error */
  private static String ˎ(int paramInt1, char paramChar, int paramInt2)
  {
    // Byte code:
    //   0: goto +98 -> 98
    //   3: iload 4
    //   5: lookupswitch	default:+27->32, 38:+96->101, 66:+53->58
    //   32: goto +69 -> 101
    //   35: iconst_0
    //   36: istore_3
    //   37: goto +121 -> 158
    //   40: goto +118 -> 158
    //   43: bipush 66
    //   45: istore 4
    //   47: goto -44 -> 3
    //   50: iload_2
    //   51: newarray char
    //   53: astore 11
    //   55: goto -20 -> 35
    //   58: getstatic 43	o/Ne:ﾞ	I
    //   61: bipush 29
    //   63: iadd
    //   64: istore 4
    //   66: iload 4
    //   68: sipush 128
    //   71: irem
    //   72: putstatic 41	o/Ne:ꞌ	I
    //   75: iload 4
    //   77: iconst_2
    //   78: irem
    //   79: ifeq +6 -> 85
    //   82: goto +164 -> 246
    //   85: goto +26 -> 111
    //   88: astore 11
    //   90: aload 11
    //   92: athrow
    //   93: iconst_1
    //   94: istore_3
    //   95: goto +116 -> 211
    //   98: goto +84 -> 182
    //   101: new 240	java/lang/String
    //   104: dup
    //   105: aload 11
    //   107: invokespecial 560	java/lang/String:<init>	([C)V
    //   110: areturn
    //   111: getstatic 215	o/Ne:ʽ	[C
    //   114: iload_0
    //   115: iload_3
    //   116: iadd
    //   117: caload
    //   118: istore 4
    //   120: iload 4
    //   122: i2l
    //   123: lstore 5
    //   125: iload_3
    //   126: i2l
    //   127: lstore 7
    //   129: getstatic 56	o/Ne:ʼ	J
    //   132: lstore 9
    //   134: aload 11
    //   136: iload_3
    //   137: lload 5
    //   139: lload 7
    //   141: lload 9
    //   143: lmul
    //   144: lxor
    //   145: iload_1
    //   146: i2l
    //   147: lxor
    //   148: l2i
    //   149: i2c
    //   150: castore
    //   151: iload_3
    //   152: iconst_1
    //   153: iadd
    //   154: istore_3
    //   155: goto -115 -> 40
    //   158: iload_3
    //   159: iload_2
    //   160: if_icmpge +6 -> 166
    //   163: goto -120 -> 43
    //   166: goto +73 -> 239
    //   169: iload_2
    //   170: newarray char
    //   172: astore 11
    //   174: goto -139 -> 35
    //   177: astore 11
    //   179: aload 11
    //   181: athrow
    //   182: getstatic 43	o/Ne:ﾞ	I
    //   185: bipush 81
    //   187: iadd
    //   188: istore_3
    //   189: iload_3
    //   190: sipush 128
    //   193: irem
    //   194: putstatic 41	o/Ne:ꞌ	I
    //   197: iload_3
    //   198: iconst_2
    //   199: irem
    //   200: ifeq +6 -> 206
    //   203: goto +6 -> 209
    //   206: goto -113 -> 93
    //   209: iconst_0
    //   210: istore_3
    //   211: iload_3
    //   212: tableswitch	default:+24->236, 0:+-43->169, 1:+-162->50
    //   236: goto -67 -> 169
    //   239: bipush 38
    //   241: istore 4
    //   243: goto -240 -> 3
    //   246: goto -135 -> 111
    // Local variable table:
    //   start	length	slot	name	signature
    //   0	249	0	paramInt1	int
    //   0	249	1	paramChar	char
    //   0	249	2	paramInt2	int
    //   36	176	3	i	int
    //   3	239	4	j	int
    //   123	15	5	l1	long
    //   127	13	7	l2	long
    //   132	10	9	l3	long
    //   53	1	11	arrayOfChar1	char[]
    //   88	47	11	localException1	Exception
    //   172	1	11	arrayOfChar2	char[]
    //   177	3	11	localException2	Exception
    // Exception table:
    //   from	to	target	type
    //   111	120	88	java/lang/Exception
    //   129	134	88	java/lang/Exception
    //   129	134	177	java/lang/Exception
  }
  
  private void ˎ(String paramString)
  {
    break label36;
    return;
    throw new NullPointerException();
    label12:
    int i = 0;
    break label41;
    label36:
    for (;;)
    {
      ͺ().runOnUiThread(new Runnable()
      {
        private static byte ˊ;
        private static int ˋ;
        private static int[] ˏ;
        private static int ᐝ;
        
        /* Error */
        static
        {
          // Byte code:
          //   0: goto +3 -> 3
          //   3: iconst_0
          //   4: putstatic 29	o/Ne$5:ˋ	I
          //   7: iconst_1
          //   8: putstatic 31	o/Ne$5:ᐝ	I
          //   11: invokestatic 33	o/Ne$5:ˏ	()V
          //   14: bipush -102
          //   16: putstatic 35	o/Ne$5:ˊ	B
          //   19: goto +6 -> 25
          //   22: astore_1
          //   23: aload_1
          //   24: athrow
          //   25: getstatic 29	o/Ne$5:ˋ	I
          //   28: istore_0
          //   29: iload_0
          //   30: bipush 31
          //   32: iadd
          //   33: istore_0
          //   34: iload_0
          //   35: sipush 128
          //   38: irem
          //   39: putstatic 31	o/Ne$5:ᐝ	I
          //   42: iload_0
          //   43: iconst_2
          //   44: irem
          //   45: ifne +4 -> 49
          //   48: return
          //   49: return
          // Local variable table:
          //   start	length	slot	name	signature
          //   28	17	0	i	int
          //   22	2	1	localException	Exception
          // Exception table:
          //   from	to	target	type
          //   25	29	22	java/lang/Exception
          //   34	42	22	java/lang/Exception
        }
        
        private String ˋ(String paramAnonymousString)
        {
          break label36;
          int j = 98;
          break label194;
          label9:
          j = ᐝ + 81;
          ˋ = j % 128;
          if (j % 2 == 0)
          {
            break label104;
            label36:
            break label332;
          }
          for (;;)
          {
            byte[] arrayOfByte;
            try
            {
              arrayOfByte = paramAnonymousString.getBytes(ˋ(new int[] { -771912215, -1631255547, -910323731, 1405703589, 65349878, 900493772 }, 39).intern());
              paramAnonymousString = new byte[arrayOfByte.length];
              i = 1;
              continue;
              i = 89;
              continue;
              label104:
              continue;
              paramAnonymousString = new String(paramAnonymousString, ˋ(new int[] { 644702493, -715726058, -352924832, 139424600 }, 5).intern());
              return paramAnonymousString;
              switch (i)
              {
              case 89: 
              default: 
                continue;
                j = arrayOfByte.length;
                if (i < j) {
                  break;
                }
                continue;
                switch (j)
                {
                }
                break;
              case 72: 
                label194:
                arrayOfByte = paramAnonymousString.getBytes(ˋ(new int[] { -771912215, -1631255547, -910323731, 1405703589, 65349878, 900493772 }, 10).intern());
                paramAnonymousString = new byte[arrayOfByte.length];
                i = 0;
                continue;
                i = 72;
                continue;
                j = 78;
                continue;
                continue;
              }
            }
            catch (UnsupportedEncodingException paramAnonymousString)
            {
              throw new RuntimeException(paramAnonymousString);
            }
            paramAnonymousString[i] = ((byte)(arrayOfByte[(arrayOfByte.length - i - 1)] ^ ˊ));
            i += 1;
            break label9;
            label332:
            int i = ˋ + 35;
            ᐝ = i % 128;
            if (i % 2 == 0) {}
          }
        }
        
        private static String ˋ(int[] paramAnonymousArrayOfInt, int paramAnonymousInt)
        {
          for (;;)
          {
            switch (j)
            {
            default: 
              label6:
              break;
            }
            for (;;)
            {
              if (i < paramAnonymousArrayOfInt.length) {
                break label250;
              }
              break label189;
              int i = ᐝ + 55;
              ˋ = i % 128;
              if (i % 2 == 0) {
                break label221;
              }
              for (;;)
              {
                arrayOfChar1[0] = ((char)(paramAnonymousArrayOfInt[i] >> 16));
                arrayOfChar1[1] = ((char)paramAnonymousArrayOfInt[i]);
                arrayOfChar1[2] = ((char)(paramAnonymousArrayOfInt[(i + 1)] >> 16));
                arrayOfChar1[3] = ((char)paramAnonymousArrayOfInt[(i + 1)]);
                oN.ˏ(arrayOfChar1, arrayOfInt, false);
                arrayOfChar2[(i << 1)] = arrayOfChar1[0];
                arrayOfChar2[((i << 1) + 1)] = arrayOfChar1[1];
                arrayOfChar2[((i << 1) + 2)] = arrayOfChar1[2];
                arrayOfChar2[((i << 1) + 3)] = arrayOfChar1[3];
                i += 2;
                break;
                break label221;
                return new String(arrayOfChar2, 0, paramAnonymousInt);
                label189:
                j = 1;
                break label6;
                j = ˋ + 29;
                ᐝ = j % 128;
                if (j % 2 == 0) {}
              }
              label221:
              char[] arrayOfChar1 = new char[4];
              char[] arrayOfChar2 = new char[paramAnonymousArrayOfInt.length << 1];
              int[] arrayOfInt = (int[])ˏ.clone();
              i = 0;
            }
            label250:
            int j = 0;
          }
        }
        
        static void ˏ()
        {
          ˏ = new int[] { 605195026, -962142501, -690026841, -26618286, 411723806, -443992505, 1875561913, -1764364757, -2119602418, -1028863580, 2072188476, -668979555, -2036291341, 1765962654, 1274788589, 2046758069, -200866840, 1499672717 };
        }
        
        /* Error */
        public void run()
        {
          // Byte code:
          //   0: goto +134 -> 134
          //   3: iconst_1
          //   4: istore_1
          //   5: goto +285 -> 290
          //   8: astore_3
          //   9: aload_3
          //   10: athrow
          //   11: return
          //   12: aload 4
          //   14: aload_3
          //   15: invokevirtual 117	o/ᐸ$If:ॱ	(Ljava/lang/CharSequence;)Lo/ᐸ$If;
          //   18: astore_3
          //   19: aload_3
          //   20: iconst_1
          //   21: invokevirtual 120	o/ᐸ$If:ˋ	(Z)Lo/ᐸ$If;
          //   24: astore_3
          //   25: new 13	o/Ne$5$5
          //   28: dup
          //   29: aload_0
          //   30: invokespecial 123	o/Ne$5$5:<init>	(Lo/Ne$5;)V
          //   33: astore 4
          //   35: aload_3
          //   36: aload 4
          //   38: invokevirtual 126	o/ᐸ$If:ˊ	(Lo/ᐸ$ˏ;)Lo/ᐸ$If;
          //   41: astore_3
          //   42: aload_3
          //   43: invokevirtual 129	o/ᐸ$If:ˏ	()Lo/ᐸ;
          //   46: pop
          //   47: goto +90 -> 137
          //   50: astore_3
          //   51: aload_3
          //   52: athrow
          //   53: aload_0
          //   54: aload_3
          //   55: iconst_4
          //   56: invokevirtual 133	java/lang/String:substring	(I)Ljava/lang/String;
          //   59: invokespecial 135	o/Ne$5:ˋ	(Ljava/lang/String;)Ljava/lang/String;
          //   62: invokevirtual 62	java/lang/String:intern	()Ljava/lang/String;
          //   65: astore_3
          //   66: new 137	java/lang/NullPointerException
          //   69: dup
          //   70: invokespecial 138	java/lang/NullPointerException:<init>	()V
          //   73: athrow
          //   74: new 114	o/ᐸ$If
          //   77: dup
          //   78: aload_0
          //   79: getfield 40	o/Ne$5:ॱ	Lo/Ne;
          //   82: invokevirtual 142	o/Ne:ˏॱ	()Landroid/content/Context;
          //   85: invokespecial 145	o/ᐸ$If:<init>	(Landroid/content/Context;)V
          //   88: astore 4
          //   90: aload_0
          //   91: getfield 40	o/Ne$5:ॱ	Lo/Ne;
          //   94: getstatic 150	o/MH$ᐝ:oops	I
          //   97: invokevirtual 152	o/Ne:ˋ	(I)Ljava/lang/String;
          //   100: astore_3
          //   101: aload_3
          //   102: iconst_2
          //   103: newarray int
          //   105: dup
          //   106: iconst_0
          //   107: ldc -103
          //   109: iastore
          //   110: dup
          //   111: iconst_1
          //   112: ldc -102
          //   114: iastore
          //   115: iconst_4
          //   116: invokestatic 56	o/Ne$5:ˋ	([II)Ljava/lang/String;
          //   119: invokevirtual 62	java/lang/String:intern	()Ljava/lang/String;
          //   122: invokevirtual 158	java/lang/String:startsWith	(Ljava/lang/String;)Z
          //   125: ifeq +6 -> 131
          //   128: goto +203 -> 331
          //   131: goto +64 -> 195
          //   134: goto -60 -> 74
          //   137: getstatic 31	o/Ne$5:ᐝ	I
          //   140: bipush 91
          //   142: iadd
          //   143: istore_1
          //   144: iload_1
          //   145: sipush 128
          //   148: irem
          //   149: putstatic 29	o/Ne$5:ˋ	I
          //   152: iload_1
          //   153: iconst_2
          //   154: irem
          //   155: ifeq +6 -> 161
          //   158: goto -155 -> 3
          //   161: iconst_0
          //   162: istore_1
          //   163: goto +127 -> 290
          //   166: iload_1
          //   167: lookupswitch	default:+25->192, 59:+107->274, 66:+-114->53
          //   192: goto -139 -> 53
          //   195: aload 4
          //   197: aload_3
          //   198: invokevirtual 160	o/ᐸ$If:ˊ	(Ljava/lang/CharSequence;)Lo/ᐸ$If;
          //   201: aload_0
          //   202: getfield 42	o/Ne$5:ˎ	Ljava/lang/String;
          //   205: invokevirtual 162	o/ᐸ$If:ˋ	(Ljava/lang/CharSequence;)Lo/ᐸ$If;
          //   208: astore 4
          //   210: aload_0
          //   211: getfield 40	o/Ne$5:ॱ	Lo/Ne;
          //   214: getstatic 165	o/MH$ᐝ:ok	I
          //   217: invokevirtual 152	o/Ne:ˋ	(I)Ljava/lang/String;
          //   220: astore_3
          //   221: aload_3
          //   222: iconst_2
          //   223: newarray int
          //   225: dup
          //   226: iconst_0
          //   227: ldc -103
          //   229: iastore
          //   230: dup
          //   231: iconst_1
          //   232: ldc -102
          //   234: iastore
          //   235: iconst_4
          //   236: invokestatic 56	o/Ne$5:ˋ	([II)Ljava/lang/String;
          //   239: invokevirtual 62	java/lang/String:intern	()Ljava/lang/String;
          //   242: invokevirtual 158	java/lang/String:startsWith	(Ljava/lang/String;)Z
          //   245: istore_2
          //   246: iload_2
          //   247: ifeq +6 -> 253
          //   250: goto +65 -> 315
          //   253: goto -241 -> 12
          //   256: bipush 66
          //   258: istore_1
          //   259: goto -93 -> 166
          //   262: bipush 59
          //   264: istore_1
          //   265: goto -99 -> 166
          //   268: bipush 61
          //   270: iconst_0
          //   271: idiv
          //   272: istore_1
          //   273: return
          //   274: aload_0
          //   275: aload_3
          //   276: iconst_4
          //   277: invokevirtual 133	java/lang/String:substring	(I)Ljava/lang/String;
          //   280: invokespecial 135	o/Ne$5:ˋ	(Ljava/lang/String;)Ljava/lang/String;
          //   283: invokevirtual 62	java/lang/String:intern	()Ljava/lang/String;
          //   286: astore_3
          //   287: goto -92 -> 195
          //   290: iload_1
          //   291: tableswitch	default:+21->312, 0:+-280->11, 1:+-23->268
          //   312: goto -44 -> 268
          //   315: aload_0
          //   316: aload_3
          //   317: iconst_4
          //   318: invokevirtual 133	java/lang/String:substring	(I)Ljava/lang/String;
          //   321: invokespecial 135	o/Ne$5:ˋ	(Ljava/lang/String;)Ljava/lang/String;
          //   324: invokevirtual 62	java/lang/String:intern	()Ljava/lang/String;
          //   327: astore_3
          //   328: goto -316 -> 12
          //   331: getstatic 31	o/Ne$5:ᐝ	I
          //   334: bipush 45
          //   336: iadd
          //   337: istore_1
          //   338: iload_1
          //   339: sipush 128
          //   342: irem
          //   343: putstatic 29	o/Ne$5:ˋ	I
          //   346: iload_1
          //   347: iconst_2
          //   348: irem
          //   349: ifeq +6 -> 355
          //   352: goto -96 -> 256
          //   355: goto -93 -> 262
          // Local variable table:
          //   start	length	slot	name	signature
          //   0	358	0	this	5
          //   4	345	1	i	int
          //   245	2	2	bool	boolean
          //   8	7	3	localException1	Exception
          //   18	25	3	localIf	ᐸ.If
          //   50	5	3	localException2	Exception
          //   65	263	3	str	String
          //   12	197	4	localObject	Object
          // Exception table:
          //   from	to	target	type
          //   19	25	8	java/lang/Exception
          //   35	42	8	java/lang/Exception
          //   42	47	8	java/lang/Exception
          //   12	19	50	java/lang/Exception
          //   195	246	50	java/lang/Exception
        }
      });
      break;
    }
    for (;;)
    {
      i = 1;
      label41:
      switch (i)
      {
      }
      break;
      i = ꞌ + 103;
      ﾞ = i % 128;
      if (i % 2 == 0) {
        break label12;
      }
    }
  }
  
  private String ˏ(String paramString)
  {
    break label179;
    int i = ꞌ + 7;
    ﾞ = i % 128;
    label30:
    int j;
    if (i % 2 != 0)
    {
      break label182;
      j = 13;
    }
    for (;;)
    {
      try
      {
        j = paramString.length;
        if (i < j) {
          break label30;
        }
        continue;
        break label182;
        j = 2;
      }
      catch (UnsupportedEncodingException paramString)
      {
        throw new RuntimeException(paramString);
      }
      continue;
      arrayOfByte[i] = ((byte)(paramString[(paramString.length - i - 1)] ^ ᐝ));
      i += 1;
      continue;
      paramString = new String(arrayOfByte, ˎ(156, '羀', 5).intern());
      return paramString;
      j = ﾞ + 97;
      ꞌ = j % 128;
      if (j % 2 == 0) {}
      continue;
      switch (j)
      {
      }
      continue;
      label179:
      break;
      label182:
      paramString = paramString.getBytes(ˎ(146, 42868, 10).intern());
      byte[] arrayOfByte = new byte[paramString.length];
      i = 0;
    }
  }
  
  public static Ne ॱ(String paramString)
  {
    for (;;)
    {
      Ne localNe = new Ne();
      Bundle localBundle = new Bundle();
      localBundle.putString(ˎ(0, '\000', 22).intern(), paramString);
      localNe.ʽ(localBundle);
      int i = ﾞ + 113;
      ꞌ = i % 128;
      if (i % 2 == 0) {
        return localNe;
      }
      return localNe;
    }
  }
  
  /* Error */
  public void ʼॱ()
  {
    // Byte code:
    //   0: goto +39 -> 39
    //   3: bipush 77
    //   5: istore_1
    //   6: goto +36 -> 42
    //   9: astore_2
    //   10: aload_2
    //   11: athrow
    //   12: getstatic 41	o/Ne:ꞌ	I
    //   15: bipush 73
    //   17: iadd
    //   18: istore_1
    //   19: iload_1
    //   20: sipush 128
    //   23: irem
    //   24: putstatic 43	o/Ne:ﾞ	I
    //   27: iload_1
    //   28: iconst_2
    //   29: irem
    //   30: ifne +6 -> 36
    //   33: goto +70 -> 103
    //   36: goto -33 -> 3
    //   39: goto -27 -> 12
    //   42: iload_1
    //   43: lookupswitch	default:+25->68, 60:+28->71, 77:+48->91
    //   68: goto +23 -> 91
    //   71: aload_0
    //   72: invokespecial 605	o/J:ʼॱ	()V
    //   75: invokestatic 610	o/zp:ॱ	()Lo/zp;
    //   78: astore_2
    //   79: aload_2
    //   80: aload_0
    //   81: invokevirtual 613	o/zp:ॱ	(Ljava/lang/Object;)V
    //   84: aconst_null
    //   85: arraylength
    //   86: istore_1
    //   87: return
    //   88: astore_2
    //   89: aload_2
    //   90: athrow
    //   91: aload_0
    //   92: invokespecial 605	o/J:ʼॱ	()V
    //   95: invokestatic 610	o/zp:ॱ	()Lo/zp;
    //   98: aload_0
    //   99: invokevirtual 613	o/zp:ॱ	(Ljava/lang/Object;)V
    //   102: return
    //   103: bipush 60
    //   105: istore_1
    //   106: goto -64 -> 42
    // Local variable table:
    //   start	length	slot	name	signature
    //   0	109	0	this	Ne
    //   5	101	1	i	int
    //   9	2	2	localException1	Exception
    //   78	2	2	localZp	zp
    //   88	2	2	localException2	Exception
    // Exception table:
    //   from	to	target	type
    //   75	79	9	java/lang/Exception
    //   79	84	9	java/lang/Exception
    //   84	87	9	java/lang/Exception
    //   79	84	88	java/lang/Exception
  }
  
  /* Error */
  public void ˈ()
  {
    // Byte code:
    //   0: goto +14 -> 14
    //   3: astore_2
    //   4: aload_2
    //   5: athrow
    //   6: iconst_0
    //   7: istore_1
    //   8: goto +30 -> 38
    //   11: astore_2
    //   12: aload_2
    //   13: athrow
    //   14: goto +70 -> 84
    //   17: aload_0
    //   18: invokespecial 616	o/J:ˈ	()V
    //   21: invokestatic 610	o/zp:ॱ	()Lo/zp;
    //   24: astore_2
    //   25: aload_2
    //   26: aload_0
    //   27: invokevirtual 618	o/zp:ˋ	(Ljava/lang/Object;)V
    //   30: new 521	java/lang/NullPointerException
    //   33: dup
    //   34: invokespecial 522	java/lang/NullPointerException:<init>	()V
    //   37: athrow
    //   38: iload_1
    //   39: tableswitch	default:+21->60, 0:+-22->17, 1:+29->68
    //   60: goto -43 -> 17
    //   63: iconst_1
    //   64: istore_1
    //   65: goto -27 -> 38
    //   68: aload_0
    //   69: invokespecial 616	o/J:ˈ	()V
    //   72: invokestatic 610	o/zp:ॱ	()Lo/zp;
    //   75: astore_2
    //   76: aload_2
    //   77: aload_0
    //   78: invokevirtual 618	o/zp:ˋ	(Ljava/lang/Object;)V
    //   81: goto +32 -> 113
    //   84: getstatic 41	o/Ne:ꞌ	I
    //   87: istore_1
    //   88: iload_1
    //   89: bipush 37
    //   91: iadd
    //   92: istore_1
    //   93: iload_1
    //   94: sipush 128
    //   97: irem
    //   98: putstatic 43	o/Ne:ﾞ	I
    //   101: iload_1
    //   102: iconst_2
    //   103: irem
    //   104: ifne +6 -> 110
    //   107: goto -101 -> 6
    //   110: goto -47 -> 63
    //   113: getstatic 41	o/Ne:ꞌ	I
    //   116: bipush 87
    //   118: iadd
    //   119: istore_1
    //   120: iload_1
    //   121: sipush 128
    //   124: irem
    //   125: putstatic 43	o/Ne:ﾞ	I
    //   128: iload_1
    //   129: iconst_2
    //   130: irem
    //   131: ifne +4 -> 135
    //   134: return
    //   135: return
    // Local variable table:
    //   start	length	slot	name	signature
    //   0	136	0	this	Ne
    //   7	124	1	i	int
    //   3	2	2	localException1	Exception
    //   11	2	2	localException2	Exception
    //   24	53	2	localZp	zp
    // Exception table:
    //   from	to	target	type
    //   84	88	3	java/lang/Exception
    //   21	25	11	java/lang/Exception
    //   25	30	11	java/lang/Exception
    //   30	38	11	java/lang/Exception
    //   72	76	11	java/lang/Exception
    //   76	81	11	java/lang/Exception
  }
  
  /* Error */
  @zA(ˋ=true, ˎ=org.greenrobot.eventbus.ThreadMode.MAIN)
  public void ˋ(Hv paramHv)
  {
    // Byte code:
    //   0: goto +36 -> 36
    //   3: bipush 88
    //   5: istore_2
    //   6: goto +235 -> 241
    //   9: goto +211 -> 220
    //   12: aload_0
    //   13: aload_1
    //   14: invokevirtual 627	o/Hv:ˊ	()Ljava/lang/String;
    //   17: invokespecial 629	o/Ne:ˎ	(Ljava/lang/String;)V
    //   20: goto +9 -> 29
    //   23: bipush 30
    //   25: istore_2
    //   26: goto +270 -> 296
    //   29: return
    //   30: astore_1
    //   31: aload_1
    //   32: athrow
    //   33: goto +242 -> 275
    //   36: bipush 26
    //   38: iconst_0
    //   39: bipush 12
    //   41: invokestatic 238	o/Ne:ˎ	(ICI)Ljava/lang/String;
    //   44: invokevirtual 244	java/lang/String:intern	()Ljava/lang/String;
    //   47: astore_3
    //   48: new 537	java/lang/StringBuilder
    //   51: dup
    //   52: invokespecial 538	java/lang/StringBuilder:<init>	()V
    //   55: bipush 110
    //   57: sipush 5623
    //   60: bipush 36
    //   62: invokestatic 238	o/Ne:ˎ	(ICI)Ljava/lang/String;
    //   65: invokevirtual 244	java/lang/String:intern	()Ljava/lang/String;
    //   68: invokevirtual 542	java/lang/StringBuilder:append	(Ljava/lang/String;)Ljava/lang/StringBuilder;
    //   71: aload_1
    //   72: invokevirtual 627	o/Hv:ˊ	()Ljava/lang/String;
    //   75: invokevirtual 542	java/lang/StringBuilder:append	(Ljava/lang/String;)Ljava/lang/StringBuilder;
    //   78: invokevirtual 545	java/lang/StringBuilder:toString	()Ljava/lang/String;
    //   81: astore 4
    //   83: goto +17 -> 100
    //   86: astore_1
    //   87: aload_1
    //   88: invokevirtual 323	java/lang/Throwable:getCause	()Ljava/lang/Throwable;
    //   91: astore_3
    //   92: aload_3
    //   93: ifnull +5 -> 98
    //   96: aload_3
    //   97: athrow
    //   98: aload_1
    //   99: athrow
    //   100: iconst_4
    //   101: bipush 42
    //   103: ldc_w 546
    //   106: invokestatic 329	o/O:ˋ	(IIC)Ljava/lang/Object;
    //   109: checkcast 331	java/lang/Class
    //   112: ldc_w 547
    //   115: iconst_2
    //   116: anewarray 331	java/lang/Class
    //   119: dup
    //   120: iconst_0
    //   121: ldc -16
    //   123: aastore
    //   124: dup
    //   125: iconst_1
    //   126: ldc -16
    //   128: aastore
    //   129: invokevirtual 336	java/lang/Class:getMethod	(Ljava/lang/String;[Ljava/lang/Class;)Ljava/lang/reflect/Method;
    //   132: aconst_null
    //   133: iconst_2
    //   134: anewarray 386	java/lang/Object
    //   137: dup
    //   138: iconst_0
    //   139: aload_3
    //   140: aastore
    //   141: dup
    //   142: iconst_1
    //   143: aload 4
    //   145: aastore
    //   146: invokevirtual 342	java/lang/reflect/Method:invoke	(Ljava/lang/Object;[Ljava/lang/Object;)Ljava/lang/Object;
    //   149: pop
    //   150: aload_1
    //   151: invokevirtual 627	o/Hv:ˊ	()Ljava/lang/String;
    //   154: invokestatic 635	android/text/TextUtils:isEmpty	(Ljava/lang/CharSequence;)Z
    //   157: ifne +6 -> 163
    //   160: goto +109 -> 269
    //   163: goto -160 -> 3
    //   166: getstatic 41	o/Ne:ꞌ	I
    //   169: bipush 121
    //   171: iadd
    //   172: istore_2
    //   173: iload_2
    //   174: sipush 128
    //   177: irem
    //   178: putstatic 43	o/Ne:ﾞ	I
    //   181: iload_2
    //   182: iconst_2
    //   183: irem
    //   184: ifne +6 -> 190
    //   187: goto -178 -> 9
    //   190: goto +30 -> 220
    //   193: getstatic 43	o/Ne:ﾞ	I
    //   196: bipush 119
    //   198: iadd
    //   199: istore_2
    //   200: iload_2
    //   201: sipush 128
    //   204: irem
    //   205: putstatic 41	o/Ne:ꞌ	I
    //   208: iload_2
    //   209: iconst_2
    //   210: irem
    //   211: ifeq +6 -> 217
    //   214: goto -181 -> 33
    //   217: goto +58 -> 275
    //   220: aload_0
    //   221: getfield 535	o/Ne:ʻ	Lo/IM;
    //   224: astore_3
    //   225: aload_3
    //   226: invokevirtual 637	o/IM:ʻ	()V
    //   229: goto -217 -> 12
    //   232: bipush 64
    //   234: istore_2
    //   235: goto +61 -> 296
    //   238: astore_1
    //   239: aload_1
    //   240: athrow
    //   241: iload_2
    //   242: lookupswitch	default:+26->268, 88:+-213->29, 89:+-49->193
    //   268: return
    //   269: bipush 89
    //   271: istore_2
    //   272: goto -31 -> 241
    //   275: invokestatic 610	o/zp:ॱ	()Lo/zp;
    //   278: aload_1
    //   279: invokevirtual 639	o/zp:ˏ	(Ljava/lang/Object;)Z
    //   282: pop
    //   283: aload_0
    //   284: getfield 535	o/Ne:ʻ	Lo/IM;
    //   287: ifnull +6 -> 293
    //   290: goto -58 -> 232
    //   293: goto -270 -> 23
    //   296: iload_2
    //   297: lookupswitch	default:+27->324, 30:+-285->12, 64:+-131->166
    //   324: goto -158 -> 166
    // Local variable table:
    //   start	length	slot	name	signature
    //   0	327	0	this	Ne
    //   0	327	1	paramHv	Hv
    //   5	292	2	i	int
    //   47	179	3	localObject	Object
    //   81	63	4	str	String
    // Exception table:
    //   from	to	target	type
    //   193	200	30	java/lang/Exception
    //   200	208	30	java/lang/Exception
    //   220	225	30	java/lang/Exception
    //   225	229	30	java/lang/Exception
    //   100	150	86	finally
    //   200	208	238	java/lang/Exception
  }
  
  /* Error */
  @zA(ˋ=true, ˎ=org.greenrobot.eventbus.ThreadMode.MAIN)
  public void ˋ(Hw paramHw)
  {
    // Byte code:
    //   0: goto +226 -> 226
    //   3: goto +75 -> 78
    //   6: iconst_1
    //   7: istore_2
    //   8: goto +535 -> 543
    //   11: aload_1
    //   12: invokevirtual 646	o/Hw:ॱ	()Lcom/insidesecure/hce/MatrixHCECard;
    //   15: invokeinterface 649 1 0
    //   20: aload_0
    //   21: invokevirtual 227	o/Ne:ˏॱ	()Landroid/content/Context;
    //   24: astore 4
    //   26: aload_0
    //   27: getstatic 652	o/MH$ᐝ:settings_card_delete_card_success	I
    //   30: invokevirtual 235	o/Ne:ˋ	(I)Ljava/lang/String;
    //   33: astore_3
    //   34: aload_3
    //   35: bipush 22
    //   37: iconst_0
    //   38: iconst_4
    //   39: invokestatic 238	o/Ne:ˎ	(ICI)Ljava/lang/String;
    //   42: invokevirtual 244	java/lang/String:intern	()Ljava/lang/String;
    //   45: invokevirtual 248	java/lang/String:startsWith	(Ljava/lang/String;)Z
    //   48: ifeq +6 -> 54
    //   51: goto +477 -> 528
    //   54: goto +517 -> 571
    //   57: aload_0
    //   58: aload_3
    //   59: iconst_4
    //   60: invokevirtual 251	java/lang/String:substring	(I)Ljava/lang/String;
    //   63: invokespecial 254	o/Ne:ˏ	(Ljava/lang/String;)Ljava/lang/String;
    //   66: invokevirtual 244	java/lang/String:intern	()Ljava/lang/String;
    //   69: astore_1
    //   70: new 521	java/lang/NullPointerException
    //   73: dup
    //   74: invokespecial 522	java/lang/NullPointerException:<init>	()V
    //   77: athrow
    //   78: aload 4
    //   80: aload_1
    //   81: iconst_1
    //   82: invokestatic 274	android/widget/Toast:makeText	(Landroid/content/Context;Ljava/lang/CharSequence;I)Landroid/widget/Toast;
    //   85: astore_1
    //   86: aload_1
    //   87: invokevirtual 277	android/widget/Toast:show	()V
    //   90: aload_0
    //   91: invokevirtual 227	o/Ne:ˏॱ	()Landroid/content/Context;
    //   94: astore_1
    //   95: aload_1
    //   96: invokestatic 657	o/Ic:ˏ	(Landroid/content/Context;)Lo/Ic;
    //   99: astore_1
    //   100: aload_1
    //   101: iconst_0
    //   102: iconst_0
    //   103: invokevirtual 660	o/Ic:ˏ	(ZZ)Lo/j;
    //   106: astore_1
    //   107: aload_1
    //   108: invokevirtual 664	o/j:ˎ	()V
    //   111: return
    //   112: iconst_0
    //   113: istore_2
    //   114: goto +429 -> 543
    //   117: iload_2
    //   118: tableswitch	default:+22->140, 0:+-61->57, 1:+92->210
    //   140: goto +70 -> 210
    //   143: iconst_1
    //   144: istore_2
    //   145: goto -28 -> 117
    //   148: getstatic 41	o/Ne:ꞌ	I
    //   151: bipush 29
    //   153: iadd
    //   154: istore_2
    //   155: iload_2
    //   156: sipush 128
    //   159: irem
    //   160: putstatic 43	o/Ne:ﾞ	I
    //   163: iload_2
    //   164: iconst_2
    //   165: irem
    //   166: ifne +6 -> 172
    //   169: goto -163 -> 6
    //   172: goto -60 -> 112
    //   175: astore_1
    //   176: aload_1
    //   177: athrow
    //   178: iconst_0
    //   179: istore_2
    //   180: goto -63 -> 117
    //   183: getstatic 41	o/Ne:ꞌ	I
    //   186: bipush 89
    //   188: iadd
    //   189: istore_2
    //   190: iload_2
    //   191: sipush 128
    //   194: irem
    //   195: putstatic 43	o/Ne:ﾞ	I
    //   198: iload_2
    //   199: iconst_2
    //   200: irem
    //   201: ifne +6 -> 207
    //   204: goto -26 -> 178
    //   207: goto -64 -> 143
    //   210: aload_0
    //   211: aload_3
    //   212: iconst_4
    //   213: invokevirtual 251	java/lang/String:substring	(I)Ljava/lang/String;
    //   216: invokespecial 254	o/Ne:ˏ	(Ljava/lang/String;)Ljava/lang/String;
    //   219: invokevirtual 244	java/lang/String:intern	()Ljava/lang/String;
    //   222: astore_1
    //   223: goto -220 -> 3
    //   226: getstatic 41	o/Ne:ꞌ	I
    //   229: bipush 119
    //   231: iadd
    //   232: istore_2
    //   233: iload_2
    //   234: sipush 128
    //   237: irem
    //   238: putstatic 43	o/Ne:ﾞ	I
    //   241: iload_2
    //   242: iconst_2
    //   243: irem
    //   244: ifne +6 -> 250
    //   247: goto +48 -> 295
    //   250: goto +160 -> 410
    //   253: aload_0
    //   254: getfield 535	o/Ne:ʻ	Lo/IM;
    //   257: invokevirtual 637	o/IM:ʻ	()V
    //   260: aconst_null
    //   261: arraylength
    //   262: istore_2
    //   263: goto -252 -> 11
    //   266: aload_3
    //   267: astore_1
    //   268: iload_2
    //   269: tableswitch	default:+23->292, 0:+-191->78, 1:+-86->183
    //   292: goto -109 -> 183
    //   295: bipush 15
    //   297: iconst_0
    //   298: bipush 76
    //   300: invokestatic 238	o/Ne:ˎ	(ICI)Ljava/lang/String;
    //   303: invokevirtual 244	java/lang/String:intern	()Ljava/lang/String;
    //   306: astore 4
    //   308: bipush 38
    //   310: ldc_w 665
    //   313: bipush 95
    //   315: invokestatic 238	o/Ne:ˎ	(ICI)Ljava/lang/String;
    //   318: invokevirtual 244	java/lang/String:intern	()Ljava/lang/String;
    //   321: astore_3
    //   322: goto +17 -> 339
    //   325: astore_3
    //   326: aload_3
    //   327: invokevirtual 323	java/lang/Throwable:getCause	()Ljava/lang/Throwable;
    //   330: astore_1
    //   331: aload_1
    //   332: ifnull +5 -> 337
    //   335: aload_1
    //   336: athrow
    //   337: aload_3
    //   338: athrow
    //   339: iconst_4
    //   340: bipush 42
    //   342: ldc_w 546
    //   345: invokestatic 329	o/O:ˋ	(IIC)Ljava/lang/Object;
    //   348: checkcast 331	java/lang/Class
    //   351: ldc_w 547
    //   354: iconst_2
    //   355: anewarray 331	java/lang/Class
    //   358: dup
    //   359: iconst_0
    //   360: ldc -16
    //   362: aastore
    //   363: dup
    //   364: iconst_1
    //   365: ldc -16
    //   367: aastore
    //   368: invokevirtual 336	java/lang/Class:getMethod	(Ljava/lang/String;[Ljava/lang/Class;)Ljava/lang/reflect/Method;
    //   371: aconst_null
    //   372: iconst_2
    //   373: anewarray 386	java/lang/Object
    //   376: dup
    //   377: iconst_0
    //   378: aload 4
    //   380: aastore
    //   381: dup
    //   382: iconst_1
    //   383: aload_3
    //   384: aastore
    //   385: invokevirtual 342	java/lang/reflect/Method:invoke	(Ljava/lang/Object;[Ljava/lang/Object;)Ljava/lang/Object;
    //   388: pop
    //   389: invokestatic 610	o/zp:ॱ	()Lo/zp;
    //   392: aload_1
    //   393: invokevirtual 639	o/zp:ˏ	(Ljava/lang/Object;)Z
    //   396: pop
    //   397: aload_0
    //   398: getfield 535	o/Ne:ʻ	Lo/IM;
    //   401: ifnull +6 -> 407
    //   404: goto -256 -> 148
    //   407: goto -396 -> 11
    //   410: bipush 26
    //   412: iconst_0
    //   413: bipush 12
    //   415: invokestatic 238	o/Ne:ˎ	(ICI)Ljava/lang/String;
    //   418: invokevirtual 244	java/lang/String:intern	()Ljava/lang/String;
    //   421: astore 4
    //   423: bipush 73
    //   425: ldc_w 665
    //   428: bipush 37
    //   430: invokestatic 238	o/Ne:ˎ	(ICI)Ljava/lang/String;
    //   433: invokevirtual 244	java/lang/String:intern	()Ljava/lang/String;
    //   436: astore_3
    //   437: goto +17 -> 454
    //   440: astore_1
    //   441: aload_1
    //   442: invokevirtual 323	java/lang/Throwable:getCause	()Ljava/lang/Throwable;
    //   445: astore_3
    //   446: aload_3
    //   447: ifnull +5 -> 452
    //   450: aload_3
    //   451: athrow
    //   452: aload_1
    //   453: athrow
    //   454: iconst_4
    //   455: bipush 42
    //   457: ldc_w 546
    //   460: invokestatic 329	o/O:ˋ	(IIC)Ljava/lang/Object;
    //   463: checkcast 331	java/lang/Class
    //   466: ldc_w 547
    //   469: iconst_2
    //   470: anewarray 331	java/lang/Class
    //   473: dup
    //   474: iconst_0
    //   475: ldc -16
    //   477: aastore
    //   478: dup
    //   479: iconst_1
    //   480: ldc -16
    //   482: aastore
    //   483: invokevirtual 336	java/lang/Class:getMethod	(Ljava/lang/String;[Ljava/lang/Class;)Ljava/lang/reflect/Method;
    //   486: aconst_null
    //   487: iconst_2
    //   488: anewarray 386	java/lang/Object
    //   491: dup
    //   492: iconst_0
    //   493: aload 4
    //   495: aastore
    //   496: dup
    //   497: iconst_1
    //   498: aload_3
    //   499: aastore
    //   500: invokevirtual 342	java/lang/reflect/Method:invoke	(Ljava/lang/Object;[Ljava/lang/Object;)Ljava/lang/Object;
    //   503: pop
    //   504: invokestatic 610	o/zp:ॱ	()Lo/zp;
    //   507: aload_1
    //   508: invokevirtual 639	o/zp:ˏ	(Ljava/lang/Object;)Z
    //   511: pop
    //   512: aload_0
    //   513: getfield 535	o/Ne:ʻ	Lo/IM;
    //   516: ifnull +6 -> 522
    //   519: goto -371 -> 148
    //   522: goto -511 -> 11
    //   525: astore_1
    //   526: aload_1
    //   527: athrow
    //   528: iconst_1
    //   529: istore_2
    //   530: goto -264 -> 266
    //   533: aload_0
    //   534: getfield 535	o/Ne:ʻ	Lo/IM;
    //   537: invokevirtual 637	o/IM:ʻ	()V
    //   540: goto -529 -> 11
    //   543: iload_2
    //   544: tableswitch	default:+24->568, 0:+-11->533, 1:+-291->253
    //   568: goto -315 -> 253
    //   571: iconst_0
    //   572: istore_2
    //   573: goto -307 -> 266
    // Local variable table:
    //   start	length	slot	name	signature
    //   0	576	0	this	Ne
    //   0	576	1	paramHw	Hw
    //   7	566	2	i	int
    //   33	289	3	str	String
    //   325	59	3	localObject1	Object
    //   436	63	3	localObject2	Object
    //   24	470	4	localObject3	Object
    // Exception table:
    //   from	to	target	type
    //   90	95	175	java/lang/Exception
    //   339	389	325	finally
    //   454	504	440	finally
    //   78	86	525	java/lang/Exception
    //   86	90	525	java/lang/Exception
    //   90	95	525	java/lang/Exception
    //   95	100	525	java/lang/Exception
    //   100	107	525	java/lang/Exception
    //   107	111	525	java/lang/Exception
  }
  
  public int ˎ()
  {
    break label12;
    int i = 0;
    break label52;
    return MH.aux.settings_payment_card_preference;
    for (;;)
    {
      label12:
      i = MH.aux.settings_payment_card_preference;
      int j = null.length;
      return i;
      i = ꞌ + 1;
      ﾞ = i % 128;
      if (i % 2 != 0) {
        break;
      }
      i = 1;
      label52:
      switch (i)
      {
      }
    }
  }
  
  /* Error */
  public void ˎ(Bundle paramBundle, String paramString)
  {
    // Byte code:
    //   0: goto +239 -> 239
    //   3: aload_0
    //   4: aload_1
    //   5: aload_2
    //   6: invokespecial 673	o/J:ˎ	(Landroid/os/Bundle;Ljava/lang/String;)V
    //   9: aload_0
    //   10: invokevirtual 676	o/Ne:ʽ	()Landroid/os/Bundle;
    //   13: iconst_0
    //   14: iconst_0
    //   15: bipush 22
    //   17: invokestatic 238	o/Ne:ˎ	(ICI)Ljava/lang/String;
    //   20: invokevirtual 244	java/lang/String:intern	()Ljava/lang/String;
    //   23: invokevirtual 679	android/os/Bundle:getString	(Ljava/lang/String;)Ljava/lang/String;
    //   26: astore_2
    //   27: goto +17 -> 44
    //   30: astore_2
    //   31: aload_2
    //   32: invokevirtual 323	java/lang/Throwable:getCause	()Ljava/lang/Throwable;
    //   35: astore_1
    //   36: aload_1
    //   37: ifnull +5 -> 42
    //   40: aload_1
    //   41: athrow
    //   42: aload_2
    //   43: athrow
    //   44: iconst_4
    //   45: sipush 267
    //   48: sipush 14788
    //   51: invokestatic 329	o/O:ˋ	(IIC)Ljava/lang/Object;
    //   54: checkcast 331	java/lang/Class
    //   57: ldc_w 332
    //   60: aconst_null
    //   61: invokevirtual 336	java/lang/Class:getMethod	(Ljava/lang/String;[Ljava/lang/Class;)Ljava/lang/reflect/Method;
    //   64: aconst_null
    //   65: aconst_null
    //   66: invokevirtual 342	java/lang/reflect/Method:invoke	(Ljava/lang/Object;[Ljava/lang/Object;)Ljava/lang/Object;
    //   69: astore_1
    //   70: goto +17 -> 87
    //   73: astore_2
    //   74: aload_2
    //   75: invokevirtual 323	java/lang/Throwable:getCause	()Ljava/lang/Throwable;
    //   78: astore_1
    //   79: aload_1
    //   80: ifnull +5 -> 85
    //   83: aload_1
    //   84: athrow
    //   85: aload_2
    //   86: athrow
    //   87: iconst_4
    //   88: sipush 267
    //   91: sipush 14788
    //   94: invokestatic 329	o/O:ˋ	(IIC)Ljava/lang/Object;
    //   97: checkcast 331	java/lang/Class
    //   100: ldc_w 680
    //   103: iconst_1
    //   104: anewarray 331	java/lang/Class
    //   107: dup
    //   108: iconst_0
    //   109: ldc -16
    //   111: aastore
    //   112: invokevirtual 336	java/lang/Class:getMethod	(Ljava/lang/String;[Ljava/lang/Class;)Ljava/lang/reflect/Method;
    //   115: aload_1
    //   116: iconst_1
    //   117: anewarray 386	java/lang/Object
    //   120: dup
    //   121: iconst_0
    //   122: aload_2
    //   123: aastore
    //   124: invokevirtual 342	java/lang/reflect/Method:invoke	(Ljava/lang/Object;[Ljava/lang/Object;)Ljava/lang/Object;
    //   127: checkcast 279	com/insidesecure/hce/MatrixHCECard
    //   130: astore_1
    //   131: aload_0
    //   132: aload_1
    //   133: putfield 259	o/Ne:ˋ	Lcom/insidesecure/hce/MatrixHCECard;
    //   136: aload_0
    //   137: aload_0
    //   138: aload_0
    //   139: getstatic 683	o/MH$ᐝ:pref_card_is_active_card	I
    //   142: invokevirtual 685	o/Ne:ʼ	(I)Ljava/lang/String;
    //   145: invokevirtual 688	o/Ne:ˏ	(Ljava/lang/CharSequence;)Landroid/support/v7/preference/Preference;
    //   148: checkcast 220	android/support/v14/preference/SwitchPreference
    //   151: putfield 218	o/Ne:ˏ	Landroid/support/v14/preference/SwitchPreference;
    //   154: aload_0
    //   155: aload_0
    //   156: aload_0
    //   157: getstatic 691	o/MH$ᐝ:pref_card_delete_from_wallet	I
    //   160: invokevirtual 685	o/Ne:ʼ	(I)Ljava/lang/String;
    //   163: invokevirtual 688	o/Ne:ˏ	(Ljava/lang/CharSequence;)Landroid/support/v7/preference/Preference;
    //   166: putfield 693	o/Ne:ˎ	Landroid/support/v7/preference/Preference;
    //   169: aload_0
    //   170: aload_0
    //   171: aload_0
    //   172: getstatic 696	o/MH$ᐝ:pref_card_change_card_name	I
    //   175: invokevirtual 685	o/Ne:ʼ	(I)Ljava/lang/String;
    //   178: invokevirtual 688	o/Ne:ˏ	(Ljava/lang/CharSequence;)Landroid/support/v7/preference/Preference;
    //   181: putfield 698	o/Ne:ॱ	Landroid/support/v7/preference/Preference;
    //   184: aload_0
    //   185: aload_0
    //   186: aload_0
    //   187: getstatic 701	o/MH$ᐝ:pref_card_more_info	I
    //   190: invokevirtual 685	o/Ne:ʼ	(I)Ljava/lang/String;
    //   193: invokevirtual 688	o/Ne:ˏ	(Ljava/lang/CharSequence;)Landroid/support/v7/preference/Preference;
    //   196: putfield 703	o/Ne:ˊ	Landroid/support/v7/preference/Preference;
    //   199: getstatic 43	o/Ne:ﾞ	I
    //   202: bipush 7
    //   204: iadd
    //   205: istore_3
    //   206: iload_3
    //   207: sipush 128
    //   210: irem
    //   211: putstatic 41	o/Ne:ꞌ	I
    //   214: iload_3
    //   215: iconst_2
    //   216: irem
    //   217: ifeq +6 -> 223
    //   220: goto +14 -> 234
    //   223: goto +72 -> 295
    //   226: new 521	java/lang/NullPointerException
    //   229: dup
    //   230: invokespecial 522	java/lang/NullPointerException:<init>	()V
    //   233: athrow
    //   234: iconst_0
    //   235: istore_3
    //   236: goto +6 -> 242
    //   239: goto +28 -> 267
    //   242: iload_3
    //   243: tableswitch	default:+21->264, 0:+-17->226, 1:+51->294
    //   264: goto -38 -> 226
    //   267: getstatic 41	o/Ne:ꞌ	I
    //   270: bipush 55
    //   272: iadd
    //   273: istore_3
    //   274: iload_3
    //   275: sipush 128
    //   278: irem
    //   279: putstatic 43	o/Ne:ﾞ	I
    //   282: iload_3
    //   283: iconst_2
    //   284: irem
    //   285: ifne +6 -> 291
    //   288: goto +12 -> 300
    //   291: goto -288 -> 3
    //   294: return
    //   295: iconst_1
    //   296: istore_3
    //   297: goto -55 -> 242
    //   300: goto -297 -> 3
    // Local variable table:
    //   start	length	slot	name	signature
    //   0	303	0	this	Ne
    //   0	303	1	paramBundle	Bundle
    //   0	303	2	paramString	String
    //   205	92	3	i	int
    // Exception table:
    //   from	to	target	type
    //   44	70	30	finally
    //   87	131	73	finally
  }
  
  protected void ˏ()
  {
    int i;
    label80:
    for (;;)
    {
      this.ˏ.ॱ(this.ˋ.isActive());
      for (;;)
      {
        i = ﾞ + 113;
        ꞌ = i % 128;
        if (i % 2 != 0) {
          break label80;
        }
        break;
        i = ﾞ + 91;
        ꞌ = i % 128;
        if (i % 2 != 0) {
          break label116;
        }
        break label121;
      }
      return;
    }
    for (;;)
    {
      switch (i)
      {
      }
      i = null.length;
      return;
      label116:
      i = 0;
      continue;
      label121:
      i = 4;
    }
  }
  
  /* Error */
  public boolean ॱ(Preference paramPreference)
  {
    // Byte code:
    //   0: goto +319 -> 319
    //   3: aload 4
    //   5: aload_0
    //   6: getfield 693	o/Ne:ˎ	Landroid/support/v7/preference/Preference;
    //   9: invokevirtual 709	android/support/v7/preference/Preference:ˊˊ	()Ljava/lang/String;
    //   12: invokevirtual 712	java/lang/String:equals	(Ljava/lang/Object;)Z
    //   15: ifeq +6 -> 21
    //   18: goto +475 -> 493
    //   21: goto +157 -> 178
    //   24: aload_0
    //   25: invokespecial 714	o/Ne:ʽˋ	()Z
    //   28: ifeq +6 -> 34
    //   31: goto +452 -> 483
    //   34: goto +224 -> 258
    //   37: aload_0
    //   38: invokevirtual 227	o/Ne:ˏॱ	()Landroid/content/Context;
    //   41: invokestatic 657	o/Ic:ˏ	(Landroid/content/Context;)Lo/Ic;
    //   44: aload_0
    //   45: getfield 259	o/Ne:ˋ	Lcom/insidesecure/hce/MatrixHCECard;
    //   48: invokeinterface 717 1 0
    //   53: invokevirtual 720	o/Ic:ʻ	(Ljava/lang/String;)Lo/j;
    //   56: invokevirtual 664	o/j:ˎ	()V
    //   59: iconst_1
    //   60: ireturn
    //   61: getstatic 43	o/Ne:ﾞ	I
    //   64: bipush 21
    //   66: iadd
    //   67: istore_2
    //   68: iload_2
    //   69: sipush 128
    //   72: irem
    //   73: putstatic 41	o/Ne:ꞌ	I
    //   76: iload_2
    //   77: iconst_2
    //   78: irem
    //   79: ifeq +6 -> 85
    //   82: goto +309 -> 391
    //   85: goto -48 -> 37
    //   88: aload 4
    //   90: aload_0
    //   91: getfield 218	o/Ne:ˏ	Landroid/support/v14/preference/SwitchPreference;
    //   94: invokevirtual 721	android/support/v14/preference/SwitchPreference:ˊˊ	()Ljava/lang/String;
    //   97: invokevirtual 712	java/lang/String:equals	(Ljava/lang/Object;)Z
    //   100: ifeq +6 -> 106
    //   103: goto +243 -> 346
    //   106: goto +113 -> 219
    //   109: iconst_1
    //   110: ireturn
    //   111: iload_2
    //   112: lookupswitch	default:+28->140, 16:+506->618, 41:+-109->3
    //   140: goto -137 -> 3
    //   143: iconst_1
    //   144: ireturn
    //   145: bipush 22
    //   147: istore_2
    //   148: goto +306 -> 454
    //   151: getstatic 41	o/Ne:ꞌ	I
    //   154: bipush 45
    //   156: iadd
    //   157: istore_2
    //   158: iload_2
    //   159: sipush 128
    //   162: irem
    //   163: putstatic 43	o/Ne:ﾞ	I
    //   166: iload_2
    //   167: iconst_2
    //   168: irem
    //   169: ifne +6 -> 175
    //   172: goto -27 -> 145
    //   175: goto +77 -> 252
    //   178: aload 4
    //   180: aload_0
    //   181: getfield 698	o/Ne:ॱ	Landroid/support/v7/preference/Preference;
    //   184: invokevirtual 709	android/support/v7/preference/Preference:ˊˊ	()Ljava/lang/String;
    //   187: invokevirtual 712	java/lang/String:equals	(Ljava/lang/Object;)Z
    //   190: ifeq +6 -> 196
    //   193: goto +225 -> 418
    //   196: goto +129 -> 325
    //   199: aload_1
    //   200: invokevirtual 709	android/support/v7/preference/Preference:ˊˊ	()Ljava/lang/String;
    //   203: astore_1
    //   204: aload_1
    //   205: ifnonnull +6 -> 211
    //   208: goto +6 -> 214
    //   211: goto +175 -> 386
    //   214: iconst_0
    //   215: istore_2
    //   216: goto +136 -> 352
    //   219: bipush 41
    //   221: istore_2
    //   222: goto -111 -> 111
    //   225: getstatic 43	o/Ne:ﾞ	I
    //   228: bipush 123
    //   230: iadd
    //   231: istore_2
    //   232: iload_2
    //   233: sipush 128
    //   236: irem
    //   237: putstatic 41	o/Ne:ꞌ	I
    //   240: iload_2
    //   241: iconst_2
    //   242: irem
    //   243: ifeq +6 -> 249
    //   246: goto +387 -> 633
    //   249: goto -50 -> 199
    //   252: bipush 63
    //   254: istore_2
    //   255: goto +199 -> 454
    //   258: aload_0
    //   259: invokevirtual 227	o/Ne:ˏॱ	()Landroid/content/Context;
    //   262: astore 4
    //   264: aload_0
    //   265: getstatic 724	o/MH$ᐝ:settings_card_delete_error	I
    //   268: invokevirtual 235	o/Ne:ˋ	(I)Ljava/lang/String;
    //   271: astore_1
    //   272: aload_1
    //   273: bipush 22
    //   275: iconst_0
    //   276: iconst_4
    //   277: invokestatic 238	o/Ne:ˎ	(ICI)Ljava/lang/String;
    //   280: invokevirtual 244	java/lang/String:intern	()Ljava/lang/String;
    //   283: invokevirtual 248	java/lang/String:startsWith	(Ljava/lang/String;)Z
    //   286: ifeq +6 -> 292
    //   289: goto -138 -> 151
    //   292: goto +354 -> 646
    //   295: goto -186 -> 109
    //   298: aload_0
    //   299: aload_1
    //   300: iconst_4
    //   301: invokevirtual 251	java/lang/String:substring	(I)Ljava/lang/String;
    //   304: invokespecial 254	o/Ne:ˏ	(Ljava/lang/String;)Ljava/lang/String;
    //   307: invokevirtual 244	java/lang/String:intern	()Ljava/lang/String;
    //   310: astore_1
    //   311: bipush 77
    //   313: iconst_0
    //   314: idiv
    //   315: istore_2
    //   316: goto +174 -> 490
    //   319: goto -94 -> 225
    //   322: astore_1
    //   323: aload_1
    //   324: athrow
    //   325: aload 4
    //   327: aload_0
    //   328: getfield 703	o/Ne:ˊ	Landroid/support/v7/preference/Preference;
    //   331: invokevirtual 709	android/support/v7/preference/Preference:ˊˊ	()Ljava/lang/String;
    //   334: invokevirtual 712	java/lang/String:equals	(Ljava/lang/Object;)Z
    //   337: ifeq +6 -> 343
    //   340: goto -279 -> 61
    //   343: goto +102 -> 445
    //   346: bipush 16
    //   348: istore_2
    //   349: goto -238 -> 111
    //   352: aload_1
    //   353: astore 4
    //   355: iload_2
    //   356: tableswitch	default:+24->380, 0:+268->624, 1:+-268->88
    //   380: aload_1
    //   381: astore 4
    //   383: goto -295 -> 88
    //   386: iconst_1
    //   387: istore_2
    //   388: goto -36 -> 352
    //   391: aload_0
    //   392: invokevirtual 227	o/Ne:ˏॱ	()Landroid/content/Context;
    //   395: invokestatic 657	o/Ic:ˏ	(Landroid/content/Context;)Lo/Ic;
    //   398: aload_0
    //   399: getfield 259	o/Ne:ˋ	Lcom/insidesecure/hce/MatrixHCECard;
    //   402: invokeinterface 717 1 0
    //   407: invokevirtual 720	o/Ic:ʻ	(Ljava/lang/String;)Lo/j;
    //   410: invokevirtual 664	o/j:ˎ	()V
    //   413: iconst_1
    //   414: ireturn
    //   415: astore_1
    //   416: aload_1
    //   417: athrow
    //   418: getstatic 41	o/Ne:ꞌ	I
    //   421: bipush 17
    //   423: iadd
    //   424: istore_2
    //   425: iload_2
    //   426: sipush 128
    //   429: irem
    //   430: putstatic 43	o/Ne:ﾞ	I
    //   433: iload_2
    //   434: iconst_2
    //   435: irem
    //   436: ifne +6 -> 442
    //   439: goto +187 -> 626
    //   442: goto +5 -> 447
    //   445: iconst_1
    //   446: ireturn
    //   447: aload_0
    //   448: invokespecial 726	o/Ne:ʽˊ	()V
    //   451: goto -308 -> 143
    //   454: iload_2
    //   455: lookupswitch	default:+25->480, 22:+-157->298, 63:+206->661
    //   480: goto -182 -> 298
    //   483: aload_0
    //   484: invokespecial 728	o/Ne:ʼᐝ	()V
    //   487: goto -192 -> 295
    //   490: goto +156 -> 646
    //   493: goto +20 -> 513
    //   496: astore 4
    //   498: aload 4
    //   500: invokevirtual 323	java/lang/Throwable:getCause	()Ljava/lang/Throwable;
    //   503: astore_1
    //   504: aload_1
    //   505: ifnull +5 -> 510
    //   508: aload_1
    //   509: athrow
    //   510: aload 4
    //   512: athrow
    //   513: iconst_3
    //   514: bipush 24
    //   516: iconst_0
    //   517: invokestatic 329	o/O:ˋ	(IIC)Ljava/lang/Object;
    //   520: checkcast 331	java/lang/Class
    //   523: ldc_w 547
    //   526: aconst_null
    //   527: invokevirtual 336	java/lang/Class:getMethod	(Ljava/lang/String;[Ljava/lang/Class;)Ljava/lang/reflect/Method;
    //   530: aconst_null
    //   531: aconst_null
    //   532: invokevirtual 342	java/lang/reflect/Method:invoke	(Ljava/lang/Object;[Ljava/lang/Object;)Ljava/lang/Object;
    //   535: astore_1
    //   536: aload_0
    //   537: invokevirtual 564	o/Ne:ͺ	()Lo/ᴊ;
    //   540: astore 4
    //   542: goto +20 -> 562
    //   545: astore 4
    //   547: aload 4
    //   549: invokevirtual 323	java/lang/Throwable:getCause	()Ljava/lang/Throwable;
    //   552: astore_1
    //   553: aload_1
    //   554: ifnull +5 -> 559
    //   557: aload_1
    //   558: athrow
    //   559: aload 4
    //   561: athrow
    //   562: iconst_3
    //   563: bipush 24
    //   565: iconst_0
    //   566: invokestatic 329	o/O:ˋ	(IIC)Ljava/lang/Object;
    //   569: checkcast 331	java/lang/Class
    //   572: ldc_w 680
    //   575: iconst_1
    //   576: anewarray 331	java/lang/Class
    //   579: dup
    //   580: iconst_0
    //   581: ldc_w 730
    //   584: aastore
    //   585: invokevirtual 336	java/lang/Class:getMethod	(Ljava/lang/String;[Ljava/lang/Class;)Ljava/lang/reflect/Method;
    //   588: aload_1
    //   589: iconst_1
    //   590: anewarray 386	java/lang/Object
    //   593: dup
    //   594: iconst_0
    //   595: aload 4
    //   597: aastore
    //   598: invokevirtual 342	java/lang/reflect/Method:invoke	(Ljava/lang/Object;[Ljava/lang/Object;)Ljava/lang/Object;
    //   601: checkcast 513	java/lang/Boolean
    //   604: invokevirtual 516	java/lang/Boolean:booleanValue	()Z
    //   607: istore_3
    //   608: iload_3
    //   609: ifeq +6 -> 615
    //   612: goto -588 -> 24
    //   615: goto -506 -> 109
    //   618: aload_0
    //   619: invokespecial 732	o/Ne:ʼˋ	()V
    //   622: iconst_1
    //   623: ireturn
    //   624: iconst_1
    //   625: ireturn
    //   626: aload_0
    //   627: invokespecial 726	o/Ne:ʽˊ	()V
    //   630: goto -487 -> 143
    //   633: aload_1
    //   634: invokevirtual 709	android/support/v7/preference/Preference:ˊˊ	()Ljava/lang/String;
    //   637: astore_1
    //   638: new 521	java/lang/NullPointerException
    //   641: dup
    //   642: invokespecial 522	java/lang/NullPointerException:<init>	()V
    //   645: athrow
    //   646: aload 4
    //   648: aload_1
    //   649: iconst_0
    //   650: invokestatic 274	android/widget/Toast:makeText	(Landroid/content/Context;Ljava/lang/CharSequence;I)Landroid/widget/Toast;
    //   653: astore_1
    //   654: aload_1
    //   655: invokevirtual 277	android/widget/Toast:show	()V
    //   658: goto -549 -> 109
    //   661: aload_0
    //   662: aload_1
    //   663: iconst_4
    //   664: invokevirtual 251	java/lang/String:substring	(I)Ljava/lang/String;
    //   667: invokespecial 254	o/Ne:ˏ	(Ljava/lang/String;)Ljava/lang/String;
    //   670: invokevirtual 244	java/lang/String:intern	()Ljava/lang/String;
    //   673: astore_1
    //   674: goto -184 -> 490
    // Local variable table:
    //   start	length	slot	name	signature
    //   0	677	0	this	Ne
    //   0	677	1	paramPreference	Preference
    //   67	388	2	i	int
    //   607	2	3	bool	boolean
    //   3	379	4	localObject1	Object
    //   496	15	4	localObject2	Object
    //   540	1	4	localᴊ	ᴊ
    //   545	102	4	localContext	Context
    // Exception table:
    //   from	to	target	type
    //   199	204	322	java/lang/Exception
    //   646	654	322	java/lang/Exception
    //   418	425	415	java/lang/Exception
    //   425	433	415	java/lang/Exception
    //   654	658	415	java/lang/Exception
    //   513	536	496	finally
    //   562	608	545	finally
  }
}
