package o;

import android.net.Uri;
import android.os.Bundle;
import android.os.Parcel;
import android.os.Parcelable.Creator;
import java.util.Map;

public final class ng
  extends hS
{
  public static final Parcelable.Creator<ng> CREATOR;
  private static int ʼ;
  private static char[] ˋ;
  private static int ˏ;
  private Map<String, String> ˊ;
  private iF ˎ;
  Bundle ॱ;
  
  static
  {
    for (;;)
    {
      try
      {
        int i = ˏ;
        i += 51;
        ʼ = i % 128;
        if (i % 2 == 0) {
          return;
        }
        return;
      }
      catch (Exception localException)
      {
        throw localException;
      }
      ˏ = 0;
      ʼ = 1;
      ˋ();
      CREATOR = new nr();
    }
  }
  
  public ng(Bundle paramBundle)
  {
    this.ॱ = paramBundle;
  }
  
  static void ˋ()
  {
    ˋ = new char[] { 68, 133, 140, 139, 134, 138, 137, 131, 133, 142, 137, 127 };
  }
  
  private static String ˏ(int[] paramArrayOfInt, byte[] paramArrayOfByte, boolean paramBoolean)
  {
    for (;;)
    {
      try
      {
        int k = ˏ;
        k += 59;
        int j;
        try
        {
          ʼ = k % 128;
          if (k % 2 != 0)
          {
            continue;
            localObject[i] = paramArrayOfByte[(m - i - 1)];
            i += 1;
            continue;
            localObject[i] = ((char)(localObject[i] - paramArrayOfInt[2]));
            i += 1;
            continue;
            localObject = new char[m];
            System.arraycopy(paramArrayOfByte, 0, localObject, 0, m);
            System.arraycopy(localObject, 0, paramArrayOfByte, m - i1, i1);
            System.arraycopy(localObject, i1, paramArrayOfByte, 0, m - i1);
            continue;
            j = ʼ;
            j += 61;
            ˏ = j % 128;
            if (j % 2 != 0) {
              continue;
            }
            continue;
            i = 26;
            continue;
            i = 0;
            continue;
            i = 73;
            continue;
            localObject = new char[m];
            i = 0;
            continue;
            arrayOfChar[j] = ((char)((localObject[j] << '\001') - i));
            continue;
            arrayOfChar[j] = ((char)((localObject[j] << '\001') + 1 - i));
            continue;
          }
          switch (j)
          {
          case 54: 
          default: 
            continue;
            i = ˏ;
            i += 47;
            ʼ = i % 128;
            if (i % 2 != 0)
            {
              break label711;
              localObject = new char[m];
              i = 1;
              continue;
              if (paramBoolean) {
                continue;
              }
              continue;
            }
            switch (k)
            {
            default: 
              continue;
              k = 0;
              continue;
              j = 54;
              continue;
              if (i < m) {
                continue;
              }
              break;
              i = 16;
              continue;
              if (i < m) {
                continue;
              }
              continue;
              k = 1;
              continue;
              if (n > 0) {}
              break;
            case 1: 
              if (paramArrayOfByte[j] == 1) {
                continue;
              }
              continue;
              continue;
              arrayOfChar = new char[m];
              i = 0;
              j = 0;
              break;
            case 0: 
              if (paramArrayOfByte[j] == 1) {
                continue;
              }
              continue;
              j = 43;
              continue;
              i = 53;
              continue;
              paramArrayOfByte = arrayOfChar;
            }
            break;
          case 43: 
            return new String((char[])localObject);
          }
          continue;
          i = arrayOfChar[j];
          j += 1;
        }
        catch (Exception paramArrayOfInt)
        {
          throw paramArrayOfInt;
        }
        continue;
        continue;
        i = paramArrayOfInt[0];
        int m = paramArrayOfInt[1];
        int n = paramArrayOfInt[2];
        int i1 = paramArrayOfInt[3];
        char[] arrayOfChar = ˋ;
        Object localObject = new char[m];
        System.arraycopy(arrayOfChar, i, localObject, 0, m);
        if (paramArrayOfByte == null)
        {
          paramArrayOfByte = (byte[])localObject;
          continue;
          if (j < m) {
            continue;
          }
          continue;
          switch (i)
          {
          }
          continue;
          continue;
          localObject = paramArrayOfByte;
          switch (i)
          {
          }
          localObject = paramArrayOfByte;
          continue;
        }
        else
        {
          i = ʼ + 3;
          ˏ = i % 128;
          if (i % 2 != 0) {
            continue;
          }
          continue;
        }
        if (i1 > 0) {
          continue;
        }
        continue;
        switch (i)
        {
        case 0: 
        default: 
          break;
        case 53: 
          i = 0;
        }
      }
      catch (Exception paramArrayOfInt)
      {
        throw paramArrayOfInt;
      }
      continue;
      label711:
      int i = 95;
    }
  }
  
  public final void writeToParcel(Parcel paramParcel, int paramInt)
  {
    break label58;
    try
    {
      paramInt = ʼ + 71;
      ˏ = paramInt % 128;
      if (paramInt % 2 == 0) {
        return;
      } else {
        label28:
        return;
      }
    }
    catch (Exception paramParcel)
    {
      throw paramParcel;
    }
    for (;;)
    {
      paramInt = hT.ˏ(paramParcel);
      hT.ˊ(paramParcel, 2, this.ॱ, false);
      hT.ˊ(paramParcel, paramInt);
      break;
      label58:
      paramInt = ʼ + 81;
      ˏ = paramInt % 128;
      if (paramInt % 2 != 0) {
        break label28;
      }
    }
  }
  
  public final String ˎ()
  {
    for (;;)
    {
      int i = 1;
      break label16;
      break label43;
      label11:
      i = 0;
      switch (i)
      {
      default: 
        label16:
        break;
      }
      try
      {
        label43:
        i = ˏ;
        i += 75;
        ʼ = i % 128;
        if (i % 2 == 0) {
          break label11;
        }
      }
      catch (Exception localException1)
      {
        try
        {
          Object localObject = this.ॱ;
          localObject = ((Bundle)localObject).getString("from");
          i = ʼ + 49;
          ˏ = i % 128;
          if (i % 2 != 0) {
            return localObject;
          }
          return localObject;
        }
        catch (Exception localException2)
        {
          throw localException2;
        }
        localException1 = localException1;
        throw localException1;
      }
    }
    localObject = this.ॱ.getString("from");
    throw new NullPointerException();
  }
  
  /* Error */
  public final Map<String, String> ˏ()
  {
    // Byte code:
    //   0: goto +129 -> 129
    //   3: iconst_0
    //   4: istore_1
    //   5: goto +452 -> 457
    //   8: aload_0
    //   9: new 95	o/ᔥ
    //   12: dup
    //   13: invokespecial 96	o/ᔥ:<init>	()V
    //   16: putfield 98	o/ng:ˊ	Ljava/util/Map;
    //   19: aload_0
    //   20: getfield 44	o/ng:ॱ	Landroid/os/Bundle;
    //   23: invokevirtual 102	android/os/Bundle:keySet	()Ljava/util/Set;
    //   26: invokeinterface 108 1 0
    //   31: astore_3
    //   32: goto +411 -> 443
    //   35: astore_3
    //   36: aload_3
    //   37: athrow
    //   38: getstatic 30	o/ng:ʼ	I
    //   41: bipush 123
    //   43: iadd
    //   44: istore_1
    //   45: iload_1
    //   46: sipush 128
    //   49: irem
    //   50: putstatic 28	o/ng:ˏ	I
    //   53: iload_1
    //   54: iconst_2
    //   55: irem
    //   56: ifeq +6 -> 62
    //   59: goto +487 -> 546
    //   62: goto +290 -> 352
    //   65: aload 5
    //   67: checkcast 65	java/lang/String
    //   70: astore 5
    //   72: aload 4
    //   74: ldc 110
    //   76: invokevirtual 114	java/lang/String:startsWith	(Ljava/lang/String;)Z
    //   79: ifne +6 -> 85
    //   82: goto +6 -> 88
    //   85: goto +398 -> 483
    //   88: iconst_1
    //   89: istore_1
    //   90: goto +86 -> 176
    //   93: aload_3
    //   94: invokeinterface 120 1 0
    //   99: checkcast 65	java/lang/String
    //   102: astore 4
    //   104: aload_0
    //   105: getfield 44	o/ng:ॱ	Landroid/os/Bundle;
    //   108: aload 4
    //   110: invokevirtual 124	android/os/Bundle:get	(Ljava/lang/String;)Ljava/lang/Object;
    //   113: astore 5
    //   115: aload 5
    //   117: instanceof 65
    //   120: ifeq +6 -> 126
    //   123: goto +192 -> 315
    //   126: goto +74 -> 200
    //   129: goto -91 -> 38
    //   132: aload 4
    //   134: ldc 126
    //   136: invokevirtual 114	java/lang/String:startsWith	(Ljava/lang/String;)Z
    //   139: istore_2
    //   140: iload_2
    //   141: ifne +6 -> 147
    //   144: goto +229 -> 373
    //   147: goto +53 -> 200
    //   150: iconst_1
    //   151: istore_1
    //   152: goto +305 -> 457
    //   155: aload_0
    //   156: getfield 98	o/ng:ˊ	Ljava/util/Map;
    //   159: areturn
    //   160: aload 4
    //   162: ldc -128
    //   164: invokevirtual 132	java/lang/String:equals	(Ljava/lang/Object;)Z
    //   167: ifne +6 -> 173
    //   170: goto -167 -> 3
    //   173: goto -23 -> 150
    //   176: iload_1
    //   177: tableswitch	default:+23->200, 0:+23->200, 1:+214->391
    //   200: goto +331 -> 531
    //   203: aload 4
    //   205: iconst_4
    //   206: newarray int
    //   208: dup
    //   209: iconst_0
    //   210: iconst_0
    //   211: iastore
    //   212: dup
    //   213: iconst_1
    //   214: bipush 12
    //   216: iastore
    //   217: dup
    //   218: iconst_2
    //   219: bipush 29
    //   221: iastore
    //   222: dup
    //   223: iconst_3
    //   224: iconst_3
    //   225: iastore
    //   226: bipush 12
    //   228: newarray byte
    //   230: dup
    //   231: iconst_0
    //   232: ldc -123
    //   234: bastore
    //   235: dup
    //   236: iconst_1
    //   237: ldc -123
    //   239: bastore
    //   240: dup
    //   241: iconst_2
    //   242: ldc -123
    //   244: bastore
    //   245: dup
    //   246: iconst_3
    //   247: ldc -123
    //   249: bastore
    //   250: dup
    //   251: iconst_4
    //   252: ldc -123
    //   254: bastore
    //   255: dup
    //   256: iconst_5
    //   257: ldc -122
    //   259: bastore
    //   260: dup
    //   261: bipush 6
    //   263: ldc -123
    //   265: bastore
    //   266: dup
    //   267: bipush 7
    //   269: ldc -122
    //   271: bastore
    //   272: dup
    //   273: bipush 8
    //   275: ldc -122
    //   277: bastore
    //   278: dup
    //   279: bipush 9
    //   281: ldc -122
    //   283: bastore
    //   284: dup
    //   285: bipush 10
    //   287: ldc -123
    //   289: bastore
    //   290: dup
    //   291: bipush 11
    //   293: ldc -123
    //   295: bastore
    //   296: iconst_0
    //   297: invokestatic 136	o/ng:ˏ	([I[BZ)Ljava/lang/String;
    //   300: invokevirtual 139	java/lang/String:intern	()Ljava/lang/String;
    //   303: invokevirtual 132	java/lang/String:equals	(Ljava/lang/Object;)Z
    //   306: ifne +6 -> 312
    //   309: goto +140 -> 449
    //   312: goto +35 -> 347
    //   315: getstatic 28	o/ng:ˏ	I
    //   318: bipush 83
    //   320: iadd
    //   321: istore_1
    //   322: iload_1
    //   323: sipush 128
    //   326: irem
    //   327: putstatic 30	o/ng:ʼ	I
    //   330: iload_1
    //   331: iconst_2
    //   332: irem
    //   333: ifne +6 -> 339
    //   336: goto +34 -> 370
    //   339: goto -274 -> 65
    //   342: iconst_0
    //   343: istore_1
    //   344: goto +161 -> 505
    //   347: iconst_1
    //   348: istore_1
    //   349: goto +68 -> 417
    //   352: aload_0
    //   353: getfield 98	o/ng:ˊ	Ljava/util/Map;
    //   356: ifnonnull +6 -> 362
    //   359: goto -351 -> 8
    //   362: goto -207 -> 155
    //   365: iconst_1
    //   366: istore_1
    //   367: goto +138 -> 505
    //   370: goto -305 -> 65
    //   373: aload 4
    //   375: ldc 83
    //   377: invokevirtual 132	java/lang/String:equals	(Ljava/lang/Object;)Z
    //   380: istore_2
    //   381: iload_2
    //   382: ifne +6 -> 388
    //   385: goto -225 -> 160
    //   388: goto -188 -> 200
    //   391: getstatic 30	o/ng:ʼ	I
    //   394: iconst_1
    //   395: iadd
    //   396: istore_1
    //   397: iload_1
    //   398: sipush 128
    //   401: irem
    //   402: putstatic 28	o/ng:ˏ	I
    //   405: iload_1
    //   406: iconst_2
    //   407: irem
    //   408: ifeq +6 -> 414
    //   411: goto +35 -> 446
    //   414: goto -282 -> 132
    //   417: iload_1
    //   418: tableswitch	default:+22->440, 0:+70->488, 1:+-218->200
    //   440: goto -240 -> 200
    //   443: goto +88 -> 531
    //   446: goto -314 -> 132
    //   449: iconst_0
    //   450: istore_1
    //   451: goto -34 -> 417
    //   454: astore_3
    //   455: aload_3
    //   456: athrow
    //   457: iload_1
    //   458: tableswitch	default:+22->480, 0:+-255->203, 1:+-258->200
    //   480: goto -280 -> 200
    //   483: iconst_0
    //   484: istore_1
    //   485: goto -309 -> 176
    //   488: aload_0
    //   489: getfield 98	o/ng:ˊ	Ljava/util/Map;
    //   492: aload 4
    //   494: aload 5
    //   496: invokeinterface 145 3 0
    //   501: pop
    //   502: goto -302 -> 200
    //   505: iload_1
    //   506: tableswitch	default:+22->528, 0:+-413->93, 1:+-351->155
    //   528: goto -435 -> 93
    //   531: aload_3
    //   532: invokeinterface 149 1 0
    //   537: ifeq +6 -> 543
    //   540: goto -198 -> 342
    //   543: goto -178 -> 365
    //   546: goto -194 -> 352
    // Local variable table:
    //   start	length	slot	name	signature
    //   0	549	0	this	ng
    //   4	502	1	i	int
    //   139	243	2	bool	boolean
    //   31	1	3	localIterator	java.util.Iterator
    //   35	59	3	localException1	Exception
    //   454	78	3	localException2	Exception
    //   72	421	4	str	String
    //   65	430	5	localObject	Object
    // Exception table:
    //   from	to	target	type
    //   132	140	35	java/lang/Exception
    //   373	381	35	java/lang/Exception
    //   93	115	454	java/lang/Exception
    //   132	140	454	java/lang/Exception
  }
  
  /* Error */
  public final iF ॱ()
  {
    // Byte code:
    //   0: goto +43 -> 43
    //   3: goto +158 -> 161
    //   6: astore_2
    //   7: aload_2
    //   8: athrow
    //   9: iconst_1
    //   10: istore_1
    //   11: goto +112 -> 123
    //   14: iload_1
    //   15: lookupswitch	default:+25->40, 31:+37->52, 59:+182->197
    //   40: goto +12 -> 52
    //   43: goto +125 -> 168
    //   46: bipush 59
    //   48: istore_1
    //   49: goto -35 -> 14
    //   52: aload_0
    //   53: getfield 154	o/ng:ˎ	Lo/ng$iF;
    //   56: ifnonnull +6 -> 62
    //   59: goto +186 -> 245
    //   62: goto -53 -> 9
    //   65: iload_1
    //   66: tableswitch	default:+22->88, 0:+184->250, 1:+-63->3
    //   88: goto -85 -> 3
    //   91: iconst_1
    //   92: istore_1
    //   93: goto -28 -> 65
    //   96: getstatic 28	o/ng:ˏ	I
    //   99: bipush 67
    //   101: iadd
    //   102: istore_1
    //   103: iload_1
    //   104: sipush 128
    //   107: irem
    //   108: putstatic 30	o/ng:ʼ	I
    //   111: iload_1
    //   112: iconst_2
    //   113: irem
    //   114: ifne +6 -> 120
    //   117: goto -26 -> 91
    //   120: goto +133 -> 253
    //   123: iload_1
    //   124: tableswitch	default:+24->148, 0:+24->148, 1:+37->161
    //   148: aload_0
    //   149: getfield 44	o/ng:ॱ	Landroid/os/Bundle;
    //   152: invokestatic 159	o/no:ˋ	(Landroid/os/Bundle;)Z
    //   155: ifeq +6 -> 161
    //   158: goto +59 -> 217
    //   161: aload_0
    //   162: getfield 154	o/ng:ˎ	Lo/ng$iF;
    //   165: astore_2
    //   166: aload_2
    //   167: areturn
    //   168: getstatic 28	o/ng:ˏ	I
    //   171: istore_1
    //   172: iload_1
    //   173: bipush 41
    //   175: iadd
    //   176: istore_1
    //   177: iload_1
    //   178: sipush 128
    //   181: irem
    //   182: putstatic 30	o/ng:ʼ	I
    //   185: iload_1
    //   186: iconst_2
    //   187: irem
    //   188: ifne +6 -> 194
    //   191: goto -145 -> 46
    //   194: goto +42 -> 236
    //   197: aload_0
    //   198: getfield 154	o/ng:ˎ	Lo/ng$iF;
    //   201: astore_2
    //   202: bipush 41
    //   204: iconst_0
    //   205: idiv
    //   206: istore_1
    //   207: aload_2
    //   208: ifnonnull +6 -> 214
    //   211: goto -63 -> 148
    //   214: goto -53 -> 161
    //   217: aload_0
    //   218: new 6	o/ng$iF
    //   221: dup
    //   222: aload_0
    //   223: getfield 44	o/ng:ॱ	Landroid/os/Bundle;
    //   226: aconst_null
    //   227: invokespecial 162	o/ng$iF:<init>	(Landroid/os/Bundle;Lo/ns;)V
    //   230: putfield 154	o/ng:ˎ	Lo/ng$iF;
    //   233: goto -137 -> 96
    //   236: bipush 31
    //   238: istore_1
    //   239: goto -225 -> 14
    //   242: astore_2
    //   243: aload_2
    //   244: athrow
    //   245: iconst_0
    //   246: istore_1
    //   247: goto -124 -> 123
    //   250: goto -89 -> 161
    //   253: iconst_0
    //   254: istore_1
    //   255: goto -190 -> 65
    // Local variable table:
    //   start	length	slot	name	signature
    //   0	258	0	this	ng
    //   10	245	1	i	int
    //   6	2	2	localException1	Exception
    //   165	43	2	localIF	iF
    //   242	2	2	localException2	Exception
    // Exception table:
    //   from	to	target	type
    //   177	185	6	java/lang/Exception
    //   161	166	242	java/lang/Exception
    //   168	172	242	java/lang/Exception
  }
  
  public static class iF
  {
    private final String ʻ;
    private final String ʼ;
    private final String ʽ;
    private final String ˊ;
    private final String ˋ;
    private final String ˎ;
    private final String[] ˏ;
    private final Uri ˏॱ;
    private final String ͺ;
    private final String ॱ;
    private final String ॱॱ;
    private final String[] ᐝ;
    
    private iF(Bundle paramBundle)
    {
      this.ˋ = no.ˎ(paramBundle, "gcm.n.title");
      this.ˎ = no.ˏ(paramBundle, "gcm.n.title");
      this.ˏ = ˋ(paramBundle, "gcm.n.title");
      this.ˊ = no.ˎ(paramBundle, "gcm.n.body");
      this.ॱ = no.ˏ(paramBundle, "gcm.n.body");
      this.ᐝ = ˋ(paramBundle, "gcm.n.body");
      this.ʻ = no.ˎ(paramBundle, "gcm.n.icon");
      this.ॱॱ = no.ˎ(paramBundle);
      this.ʽ = no.ˎ(paramBundle, "gcm.n.tag");
      this.ʼ = no.ˎ(paramBundle, "gcm.n.color");
      this.ͺ = no.ˎ(paramBundle, "gcm.n.click_action");
      this.ˏॱ = no.ˏ(paramBundle);
    }
    
    private static String[] ˋ(Bundle paramBundle, String paramString)
    {
      paramBundle = no.ˊ(paramBundle, paramString);
      if (paramBundle == null) {
        return null;
      }
      paramString = new String[paramBundle.length];
      int i = 0;
      while (i < paramBundle.length)
      {
        paramString[i] = String.valueOf(paramBundle[i]);
        i += 1;
      }
      return paramString;
    }
    
    public String ॱ()
    {
      return this.ˊ;
    }
  }
}
