package o;

import android.app.ActivityManager;
import android.app.ActivityManager.RunningAppProcessInfo;
import android.app.KeyguardManager;
import android.app.Notification;
import android.app.NotificationManager;
import android.app.PendingIntent;
import android.content.Context;
import android.content.Intent;
import android.content.pm.ApplicationInfo;
import android.content.res.Resources;
import android.content.res.Resources.NotFoundException;
import android.graphics.Color;
import android.media.RingtoneManager;
import android.net.Uri;
import android.os.Build.VERSION;
import android.os.Bundle;
import android.os.Parcelable;
import android.os.Process;
import android.os.SystemClock;
import android.text.TextUtils;
import android.util.Log;
import com.google.firebase.messaging.FirebaseMessagingService;
import java.lang.reflect.Method;
import java.util.Iterator;
import java.util.List;
import java.util.concurrent.atomic.AtomicInteger;

public final class no
{
  private static byte ʻ;
  private static int ʼ;
  private static int ˋॱ;
  private static no ˏ;
  private static int ˏॱ = 0;
  private static char ॱॱ;
  private static long ᐝ;
  private final AtomicInteger ʽ;
  private Method ˊ;
  private final Context ˋ;
  private Bundle ˎ;
  private Method ॱ;
  
  static
  {
    ˋॱ = 1;
    ॱ();
    ʻ = -102;
    int i = ˏॱ + 3;
    ˋॱ = i % 128;
    if (i % 2 != 0) {}
  }
  
  /* Error */
  private no(Context paramContext)
  {
    // Byte code:
    //   0: goto +6 -> 6
    //   3: astore_1
    //   4: aload_1
    //   5: athrow
    //   6: aload_0
    //   7: invokespecial 42	java/lang/Object:<init>	()V
    //   10: new 44	java/util/concurrent/atomic/AtomicInteger
    //   13: dup
    //   14: invokestatic 50	android/os/SystemClock:elapsedRealtime	()J
    //   17: l2i
    //   18: invokespecial 53	java/util/concurrent/atomic/AtomicInteger:<init>	(I)V
    //   21: astore_2
    //   22: aload_0
    //   23: aload_2
    //   24: putfield 55	o/no:ʽ	Ljava/util/concurrent/atomic/AtomicInteger;
    //   27: aload_1
    //   28: invokevirtual 61	android/content/Context:getApplicationContext	()Landroid/content/Context;
    //   31: astore_1
    //   32: aload_0
    //   33: aload_1
    //   34: putfield 63	o/no:ˋ	Landroid/content/Context;
    //   37: return
    //   38: astore_1
    //   39: aload_1
    //   40: athrow
    // Local variable table:
    //   start	length	slot	name	signature
    //   0	41	0	this	no
    //   0	41	1	paramContext	Context
    //   21	3	2	localAtomicInteger	AtomicInteger
    // Exception table:
    //   from	to	target	type
    //   27	32	3	java/lang/Exception
    //   10	22	38	java/lang/Exception
    //   22	27	38	java/lang/Exception
    //   27	32	38	java/lang/Exception
    //   32	37	38	java/lang/Exception
  }
  
  /* Error */
  private final PendingIntent ˊ(Bundle paramBundle)
  {
    // Byte code:
    //   0: goto +484 -> 484
    //   3: getstatic 31	o/no:ˋॱ	I
    //   6: bipush 121
    //   8: iadd
    //   9: istore_2
    //   10: iload_2
    //   11: sipush 128
    //   14: irem
    //   15: putstatic 29	o/no:ˏॱ	I
    //   18: iload_2
    //   19: iconst_2
    //   20: irem
    //   21: ifeq +6 -> 27
    //   24: goto +39 -> 63
    //   27: goto +68 -> 95
    //   30: getstatic 31	o/no:ˋॱ	I
    //   33: bipush 83
    //   35: iadd
    //   36: istore_2
    //   37: iload_2
    //   38: sipush 128
    //   41: irem
    //   42: putstatic 29	o/no:ˏॱ	I
    //   45: iload_2
    //   46: iconst_2
    //   47: irem
    //   48: ifeq +6 -> 54
    //   51: goto +265 -> 316
    //   54: goto +271 -> 325
    //   57: aconst_null
    //   58: arraylength
    //   59: istore_2
    //   60: goto +462 -> 522
    //   63: goto +289 -> 352
    //   66: aload 5
    //   68: ldc 66
    //   70: invokevirtual 72	java/lang/String:startsWith	(Ljava/lang/String;)Z
    //   73: ifeq +6 -> 79
    //   76: goto +229 -> 305
    //   79: goto +240 -> 319
    //   82: goto +440 -> 522
    //   85: aload 4
    //   87: aload 5
    //   89: invokevirtual 78	android/content/Intent:removeExtra	(Ljava/lang/String;)V
    //   92: goto +274 -> 366
    //   95: goto +257 -> 352
    //   98: ldc 80
    //   100: ldc 82
    //   102: invokestatic 88	android/util/Log:w	(Ljava/lang/String;Ljava/lang/String;)I
    //   105: pop
    //   106: goto +340 -> 446
    //   109: iload_2
    //   110: tableswitch	default:+22->132, 0:+218->328, 1:+201->311
    //   132: goto +179 -> 311
    //   135: getstatic 31	o/no:ˋॱ	I
    //   138: bipush 69
    //   140: iadd
    //   141: istore_2
    //   142: iload_2
    //   143: sipush 128
    //   146: irem
    //   147: putstatic 29	o/no:ˏॱ	I
    //   150: iload_2
    //   151: iconst_2
    //   152: irem
    //   153: ifeq +6 -> 159
    //   156: goto -99 -> 57
    //   159: goto -77 -> 82
    //   162: iconst_0
    //   163: istore_2
    //   164: goto -55 -> 109
    //   167: aload 4
    //   169: ldc 89
    //   171: invokevirtual 93	android/content/Intent:addFlags	(I)Landroid/content/Intent;
    //   174: pop
    //   175: new 95	android/os/Bundle
    //   178: dup
    //   179: aload_1
    //   180: invokespecial 98	android/os/Bundle:<init>	(Landroid/os/Bundle;)V
    //   183: astore_1
    //   184: aload_1
    //   185: invokestatic 102	com/google/firebase/messaging/FirebaseMessagingService:ˎ	(Landroid/os/Bundle;)V
    //   188: aload 4
    //   190: aload_1
    //   191: invokevirtual 106	android/content/Intent:putExtras	(Landroid/os/Bundle;)Landroid/content/Intent;
    //   194: pop
    //   195: aload_1
    //   196: invokevirtual 110	android/os/Bundle:keySet	()Ljava/util/Set;
    //   199: invokeinterface 116 1 0
    //   204: astore_1
    //   205: goto +190 -> 395
    //   208: iconst_0
    //   209: istore_2
    //   210: goto +159 -> 369
    //   213: aload_1
    //   214: ldc 118
    //   216: invokestatic 121	o/no:ˎ	(Landroid/os/Bundle;Ljava/lang/String;)Ljava/lang/String;
    //   219: astore 4
    //   221: aload 4
    //   223: invokestatic 127	android/text/TextUtils:isEmpty	(Ljava/lang/CharSequence;)Z
    //   226: istore_3
    //   227: iload_3
    //   228: ifne +6 -> 234
    //   231: goto +256 -> 487
    //   234: goto +101 -> 335
    //   237: aload_1
    //   238: invokeinterface 133 1 0
    //   243: astore 5
    //   245: aload 5
    //   247: checkcast 68	java/lang/String
    //   250: astore 5
    //   252: aload 5
    //   254: ldc -121
    //   256: invokevirtual 72	java/lang/String:startsWith	(Ljava/lang/String;)Z
    //   259: istore_3
    //   260: iload_3
    //   261: ifne +6 -> 267
    //   264: goto +334 -> 598
    //   267: goto +63 -> 330
    //   270: new 74	android/content/Intent
    //   273: dup
    //   274: ldc -119
    //   276: invokespecial 139	android/content/Intent:<init>	(Ljava/lang/String;)V
    //   279: astore 4
    //   281: aload 4
    //   283: aload_0
    //   284: getfield 63	o/no:ˋ	Landroid/content/Context;
    //   287: invokevirtual 143	android/content/Context:getPackageName	()Ljava/lang/String;
    //   290: invokevirtual 147	android/content/Intent:setPackage	(Ljava/lang/String;)Landroid/content/Intent;
    //   293: pop
    //   294: aload 4
    //   296: aload 5
    //   298: invokevirtual 151	android/content/Intent:setData	(Landroid/net/Uri;)Landroid/content/Intent;
    //   301: pop
    //   302: goto -299 -> 3
    //   305: bipush 80
    //   307: istore_2
    //   308: goto +241 -> 549
    //   311: aconst_null
    //   312: arraylength
    //   313: istore_2
    //   314: aconst_null
    //   315: areturn
    //   316: goto +9 -> 325
    //   319: bipush 47
    //   321: istore_2
    //   322: goto +227 -> 549
    //   325: goto +27 -> 352
    //   328: aconst_null
    //   329: areturn
    //   330: iconst_0
    //   331: istore_2
    //   332: goto +83 -> 415
    //   335: aload_1
    //   336: invokestatic 154	o/no:ˏ	(Landroid/os/Bundle;)Landroid/net/Uri;
    //   339: astore 5
    //   341: aload 5
    //   343: ifnull +6 -> 349
    //   346: goto -76 -> 270
    //   349: goto +100 -> 449
    //   352: aload 4
    //   354: ifnonnull +6 -> 360
    //   357: goto -222 -> 135
    //   360: goto -193 -> 167
    //   363: astore_1
    //   364: aload_1
    //   365: athrow
    //   366: goto +29 -> 395
    //   369: iload_2
    //   370: tableswitch	default:+22->392, 0:+209->579, 1:+-133->237
    //   392: goto -155 -> 237
    //   395: aload_1
    //   396: invokeinterface 158 1 0
    //   401: ifeq +6 -> 407
    //   404: goto +75 -> 479
    //   407: goto -199 -> 208
    //   410: iconst_1
    //   411: istore_2
    //   412: goto -303 -> 109
    //   415: iload_2
    //   416: tableswitch	default:+24->440, 0:+-331->85, 1:+-350->66
    //   440: goto -355 -> 85
    //   443: astore_1
    //   444: aload_1
    //   445: athrow
    //   446: goto -94 -> 352
    //   449: aload_0
    //   450: getfield 63	o/no:ˋ	Landroid/content/Context;
    //   453: invokevirtual 162	android/content/Context:getPackageManager	()Landroid/content/pm/PackageManager;
    //   456: aload_0
    //   457: getfield 63	o/no:ˋ	Landroid/content/Context;
    //   460: invokevirtual 143	android/content/Context:getPackageName	()Ljava/lang/String;
    //   463: invokevirtual 167	android/content/pm/PackageManager:getLaunchIntentForPackage	(Ljava/lang/String;)Landroid/content/Intent;
    //   466: astore 4
    //   468: aload 4
    //   470: ifnonnull +6 -> 476
    //   473: goto -375 -> 98
    //   476: goto -30 -> 446
    //   479: iconst_1
    //   480: istore_2
    //   481: goto -112 -> 369
    //   484: goto -271 -> 213
    //   487: new 74	android/content/Intent
    //   490: dup
    //   491: aload 4
    //   493: invokespecial 139	android/content/Intent:<init>	(Ljava/lang/String;)V
    //   496: astore 4
    //   498: aload 4
    //   500: aload_0
    //   501: getfield 63	o/no:ˋ	Landroid/content/Context;
    //   504: invokevirtual 143	android/content/Context:getPackageName	()Ljava/lang/String;
    //   507: invokevirtual 147	android/content/Intent:setPackage	(Ljava/lang/String;)Landroid/content/Intent;
    //   510: pop
    //   511: aload 4
    //   513: ldc -88
    //   515: invokevirtual 171	android/content/Intent:setFlags	(I)Landroid/content/Intent;
    //   518: pop
    //   519: goto -489 -> 30
    //   522: getstatic 31	o/no:ˋॱ	I
    //   525: bipush 51
    //   527: iadd
    //   528: istore_2
    //   529: iload_2
    //   530: sipush 128
    //   533: irem
    //   534: putstatic 29	o/no:ˏॱ	I
    //   537: iload_2
    //   538: iconst_2
    //   539: irem
    //   540: ifeq +6 -> 546
    //   543: goto -133 -> 410
    //   546: goto -384 -> 162
    //   549: iload_2
    //   550: lookupswitch	default:+26->576, 47:+-184->366, 80:+-465->85
    //   576: goto -210 -> 366
    //   579: aload_0
    //   580: getfield 63	o/no:ˋ	Landroid/content/Context;
    //   583: aload_0
    //   584: getfield 55	o/no:ʽ	Ljava/util/concurrent/atomic/AtomicInteger;
    //   587: invokevirtual 175	java/util/concurrent/atomic/AtomicInteger:incrementAndGet	()I
    //   590: aload 4
    //   592: ldc -80
    //   594: invokestatic 182	android/app/PendingIntent:getActivity	(Landroid/content/Context;ILandroid/content/Intent;I)Landroid/app/PendingIntent;
    //   597: areturn
    //   598: iconst_1
    //   599: istore_2
    //   600: goto -185 -> 415
    // Local variable table:
    //   start	length	slot	name	signature
    //   0	603	0	this	no
    //   0	603	1	paramBundle	Bundle
    //   9	591	2	i	int
    //   226	35	3	bool	boolean
    //   85	506	4	localObject1	Object
    //   66	276	5	localObject2	Object
    // Exception table:
    //   from	to	target	type
    //   213	221	363	java/lang/Exception
    //   221	227	363	java/lang/Exception
    //   237	245	363	java/lang/Exception
    //   245	260	363	java/lang/Exception
    //   221	227	443	java/lang/Exception
  }
  
  /* Error */
  private final Bundle ˊ()
  {
    // Byte code:
    //   0: goto +161 -> 161
    //   3: aload_0
    //   4: aload_2
    //   5: getfield 190	android/content/pm/ApplicationInfo:metaData	Landroid/os/Bundle;
    //   8: putfield 192	o/no:ˎ	Landroid/os/Bundle;
    //   11: aload_0
    //   12: getfield 192	o/no:ˎ	Landroid/os/Bundle;
    //   15: astore_2
    //   16: new 194	java/lang/NullPointerException
    //   19: dup
    //   20: invokespecial 195	java/lang/NullPointerException:<init>	()V
    //   23: athrow
    //   24: bipush 50
    //   26: istore_1
    //   27: goto +192 -> 219
    //   30: iconst_1
    //   31: istore_1
    //   32: goto +37 -> 69
    //   35: goto +60 -> 95
    //   38: astore_2
    //   39: aload_2
    //   40: athrow
    //   41: aconst_null
    //   42: astore_2
    //   43: aload_0
    //   44: getfield 63	o/no:ˋ	Landroid/content/Context;
    //   47: invokevirtual 162	android/content/Context:getPackageManager	()Landroid/content/pm/PackageManager;
    //   50: aload_0
    //   51: getfield 63	o/no:ˋ	Landroid/content/Context;
    //   54: invokevirtual 143	android/content/Context:getPackageName	()Ljava/lang/String;
    //   57: sipush 128
    //   60: invokevirtual 199	android/content/pm/PackageManager:getApplicationInfo	(Ljava/lang/String;I)Landroid/content/pm/ApplicationInfo;
    //   63: astore_3
    //   64: aload_3
    //   65: astore_2
    //   66: goto -31 -> 35
    //   69: iload_1
    //   70: tableswitch	default:+22->92, 0:+38->108, 1:+64->134
    //   92: goto +16 -> 108
    //   95: aload_2
    //   96: ifnull +6 -> 102
    //   99: goto +16 -> 115
    //   102: goto -78 -> 24
    //   105: goto -10 -> 95
    //   108: getstatic 202	android/os/Bundle:EMPTY	Landroid/os/Bundle;
    //   111: astore_2
    //   112: goto +67 -> 179
    //   115: bipush 73
    //   117: istore_1
    //   118: goto +101 -> 219
    //   121: aload_0
    //   122: getfield 192	o/no:ˎ	Landroid/os/Bundle;
    //   125: areturn
    //   126: iconst_0
    //   127: istore_1
    //   128: goto -59 -> 69
    //   131: astore_2
    //   132: aload_2
    //   133: athrow
    //   134: getstatic 31	o/no:ˋॱ	I
    //   137: bipush 9
    //   139: iadd
    //   140: istore_1
    //   141: iload_1
    //   142: sipush 128
    //   145: irem
    //   146: putstatic 29	o/no:ˏॱ	I
    //   149: iload_1
    //   150: iconst_2
    //   151: irem
    //   152: ifeq +6 -> 158
    //   155: goto -152 -> 3
    //   158: goto +93 -> 251
    //   161: goto +43 -> 204
    //   164: aload_2
    //   165: getfield 190	android/content/pm/ApplicationInfo:metaData	Landroid/os/Bundle;
    //   168: astore_3
    //   169: aload_3
    //   170: ifnull +6 -> 176
    //   173: goto -143 -> 30
    //   176: goto -50 -> 126
    //   179: getstatic 31	o/no:ˋॱ	I
    //   182: bipush 51
    //   184: iadd
    //   185: istore_1
    //   186: iload_1
    //   187: sipush 128
    //   190: irem
    //   191: putstatic 29	o/no:ˏॱ	I
    //   194: iload_1
    //   195: iconst_2
    //   196: irem
    //   197: ifeq +5 -> 202
    //   200: aload_2
    //   201: areturn
    //   202: aload_2
    //   203: areturn
    //   204: aload_0
    //   205: getfield 192	o/no:ˎ	Landroid/os/Bundle;
    //   208: astore_2
    //   209: aload_2
    //   210: ifnull +6 -> 216
    //   213: goto -92 -> 121
    //   216: goto -175 -> 41
    //   219: iload_1
    //   220: lookupswitch	default:+28->248, 50:+-112->108, 73:+-56->164
    //   248: goto -140 -> 108
    //   251: aload_0
    //   252: aload_2
    //   253: getfield 190	android/content/pm/ApplicationInfo:metaData	Landroid/os/Bundle;
    //   256: putfield 192	o/no:ˎ	Landroid/os/Bundle;
    //   259: aload_0
    //   260: getfield 192	o/no:ˎ	Landroid/os/Bundle;
    //   263: areturn
    //   264: astore_3
    //   265: goto -160 -> 105
    // Local variable table:
    //   start	length	slot	name	signature
    //   0	268	0	this	no
    //   26	194	1	i	int
    //   4	12	2	localBundle1	Bundle
    //   38	2	2	localException1	Exception
    //   42	70	2	localObject1	Object
    //   131	72	2	localException2	Exception
    //   208	45	2	localBundle2	Bundle
    //   63	107	3	localObject2	Object
    //   264	1	3	localNameNotFoundException	android.content.pm.PackageManager.NameNotFoundException
    // Exception table:
    //   from	to	target	type
    //   204	209	38	java/lang/Exception
    //   164	169	131	java/lang/Exception
    //   43	64	264	android/content/pm/PackageManager$NameNotFoundException
  }
  
  /* Error */
  @android.annotation.TargetApi(26)
  private static Method ˊ(String paramString)
  {
    // Byte code:
    //   0: goto +44 -> 44
    //   3: ldc -44
    //   5: aload_0
    //   6: iconst_1
    //   7: anewarray 214	java/lang/Class
    //   10: dup
    //   11: iconst_0
    //   12: ldc 68
    //   14: aastore
    //   15: invokevirtual 218	java/lang/Class:getMethod	(Ljava/lang/String;[Ljava/lang/Class;)Ljava/lang/reflect/Method;
    //   18: astore_0
    //   19: goto +57 -> 76
    //   22: goto +83 -> 105
    //   25: iconst_0
    //   26: istore_1
    //   27: goto +80 -> 107
    //   30: aconst_null
    //   31: arraylength
    //   32: istore_1
    //   33: aload_0
    //   34: areturn
    //   35: astore_0
    //   36: aload_0
    //   37: athrow
    //   38: astore_0
    //   39: aload_0
    //   40: athrow
    //   41: goto -38 -> 3
    //   44: getstatic 31	o/no:ˋॱ	I
    //   47: bipush 113
    //   49: iadd
    //   50: istore_1
    //   51: iload_1
    //   52: sipush 128
    //   55: irem
    //   56: putstatic 29	o/no:ˏॱ	I
    //   59: iload_1
    //   60: iconst_2
    //   61: irem
    //   62: ifeq +6 -> 68
    //   65: goto -24 -> 41
    //   68: goto -65 -> 3
    //   71: iconst_1
    //   72: istore_1
    //   73: goto +34 -> 107
    //   76: getstatic 29	o/no:ˏॱ	I
    //   79: istore_1
    //   80: iload_1
    //   81: bipush 65
    //   83: iadd
    //   84: istore_1
    //   85: iload_1
    //   86: sipush 128
    //   89: irem
    //   90: putstatic 31	o/no:ˋॱ	I
    //   93: iload_1
    //   94: iconst_2
    //   95: irem
    //   96: ifne +6 -> 102
    //   99: goto -28 -> 71
    //   102: goto -77 -> 25
    //   105: aconst_null
    //   106: areturn
    //   107: iload_1
    //   108: tableswitch	default:+24->132, 0:+29->137, 1:+-78->30
    //   132: aload_0
    //   133: areturn
    //   134: goto -29 -> 105
    //   137: aload_0
    //   138: areturn
    //   139: astore_0
    //   140: goto -118 -> 22
    //   143: astore_0
    //   144: goto -10 -> 134
    // Local variable table:
    //   start	length	slot	name	signature
    //   0	147	0	paramString	String
    //   26	82	1	i	int
    // Exception table:
    //   from	to	target	type
    //   76	80	35	java/lang/Exception
    //   85	93	38	java/lang/Exception
    //   3	19	139	java/lang/NoSuchMethodException
    //   3	19	143	java/lang/SecurityException
  }
  
  /* Error */
  static Object[] ˊ(Bundle paramBundle, String paramString)
  {
    // Byte code:
    //   0: goto +199 -> 199
    //   3: goto +495 -> 498
    //   6: bipush 54
    //   8: istore_3
    //   9: goto +108 -> 117
    //   12: getstatic 29	o/no:ˏॱ	I
    //   15: bipush 75
    //   17: iadd
    //   18: istore_3
    //   19: iload_3
    //   20: sipush 128
    //   23: irem
    //   24: putstatic 31	o/no:ˋॱ	I
    //   27: iload_3
    //   28: iconst_2
    //   29: irem
    //   30: ifne +6 -> 36
    //   33: goto +174 -> 207
    //   36: goto +441 -> 477
    //   39: iconst_0
    //   40: istore_2
    //   41: goto +133 -> 174
    //   44: aload 5
    //   46: aload 6
    //   48: invokevirtual 226	java/lang/String:concat	(Ljava/lang/String;)Ljava/lang/String;
    //   51: astore 5
    //   53: goto +273 -> 326
    //   56: getstatic 29	o/no:ˏॱ	I
    //   59: iconst_3
    //   60: iadd
    //   61: istore_2
    //   62: iload_2
    //   63: sipush 128
    //   66: irem
    //   67: putstatic 31	o/no:ˋॱ	I
    //   70: iload_2
    //   71: iconst_2
    //   72: irem
    //   73: ifne +6 -> 79
    //   76: goto -37 -> 39
    //   79: goto +414 -> 493
    //   82: iload_2
    //   83: lookupswitch	default:+25->108, 10:+-39->44, 74:+193->276
    //   108: goto +168 -> 276
    //   111: bipush 10
    //   113: istore_2
    //   114: goto -32 -> 82
    //   117: iload_3
    //   118: lookupswitch	default:+26->144, 54:+-106->12, 68:+383->501
    //   144: aload 6
    //   146: areturn
    //   147: getstatic 29	o/no:ˏॱ	I
    //   150: bipush 71
    //   152: iadd
    //   153: istore_2
    //   154: iload_2
    //   155: sipush 128
    //   158: irem
    //   159: putstatic 31	o/no:ˋॱ	I
    //   162: iload_2
    //   163: iconst_2
    //   164: irem
    //   165: ifne +6 -> 171
    //   168: goto +96 -> 264
    //   171: goto +34 -> 205
    //   174: iload_2
    //   175: tableswitch	default:+21->196, 0:+263->438, 1:+92->267
    //   196: goto +71 -> 267
    //   199: goto +35 -> 234
    //   202: astore_0
    //   203: aload_0
    //   204: athrow
    //   205: aconst_null
    //   206: areturn
    //   207: goto +270 -> 477
    //   210: aload_1
    //   211: invokestatic 230	java/lang/String:valueOf	(Ljava/lang/Object;)Ljava/lang/String;
    //   214: astore_0
    //   215: ldc -24
    //   217: invokestatic 230	java/lang/String:valueOf	(Ljava/lang/Object;)Ljava/lang/String;
    //   220: astore_1
    //   221: aload_1
    //   222: invokevirtual 235	java/lang/String:length	()I
    //   225: ifeq +6 -> 231
    //   228: goto +62 -> 290
    //   231: goto +234 -> 465
    //   234: aload_1
    //   235: invokestatic 230	java/lang/String:valueOf	(Ljava/lang/Object;)Ljava/lang/String;
    //   238: astore 5
    //   240: ldc -24
    //   242: invokestatic 230	java/lang/String:valueOf	(Ljava/lang/Object;)Ljava/lang/String;
    //   245: astore 6
    //   247: aload 6
    //   249: invokevirtual 235	java/lang/String:length	()I
    //   252: ifeq +6 -> 258
    //   255: goto -144 -> 111
    //   258: bipush 74
    //   260: istore_2
    //   261: goto -179 -> 82
    //   264: goto -59 -> 205
    //   267: goto +85 -> 352
    //   270: astore_0
    //   271: aload_0
    //   272: athrow
    //   273: goto +53 -> 326
    //   276: new 68	java/lang/String
    //   279: dup
    //   280: aload 5
    //   282: invokespecial 236	java/lang/String:<init>	(Ljava/lang/String;)V
    //   285: astore 5
    //   287: goto -14 -> 273
    //   290: aload_0
    //   291: aload_1
    //   292: invokevirtual 226	java/lang/String:concat	(Ljava/lang/String;)Ljava/lang/String;
    //   295: astore_0
    //   296: goto -240 -> 56
    //   299: getstatic 31	o/no:ˋॱ	I
    //   302: bipush 103
    //   304: iadd
    //   305: istore_3
    //   306: iload_3
    //   307: sipush 128
    //   310: irem
    //   311: putstatic 29	o/no:ˏॱ	I
    //   314: iload_3
    //   315: iconst_2
    //   316: irem
    //   317: ifeq +6 -> 323
    //   320: goto -317 -> 3
    //   323: goto +175 -> 498
    //   326: aload_0
    //   327: aload 5
    //   329: invokestatic 121	o/no:ˎ	(Landroid/os/Bundle;Ljava/lang/String;)Ljava/lang/String;
    //   332: astore 5
    //   334: aload 5
    //   336: invokestatic 127	android/text/TextUtils:isEmpty	(Ljava/lang/CharSequence;)Z
    //   339: istore 4
    //   341: iload 4
    //   343: ifeq +6 -> 349
    //   346: goto +164 -> 510
    //   349: goto +92 -> 441
    //   352: aload_0
    //   353: bipush 6
    //   355: invokevirtual 240	java/lang/String:substring	(I)Ljava/lang/String;
    //   358: astore_0
    //   359: aload_0
    //   360: invokestatic 230	java/lang/String:valueOf	(Ljava/lang/Object;)Ljava/lang/String;
    //   363: invokevirtual 235	java/lang/String:length	()I
    //   366: istore_2
    //   367: ldc 80
    //   369: new 242	java/lang/StringBuilder
    //   372: dup
    //   373: aload 5
    //   375: invokestatic 230	java/lang/String:valueOf	(Ljava/lang/Object;)Ljava/lang/String;
    //   378: invokevirtual 235	java/lang/String:length	()I
    //   381: iload_2
    //   382: bipush 41
    //   384: iadd
    //   385: iadd
    //   386: invokespecial 243	java/lang/StringBuilder:<init>	(I)V
    //   389: ldc -11
    //   391: invokevirtual 249	java/lang/StringBuilder:append	(Ljava/lang/String;)Ljava/lang/StringBuilder;
    //   394: aload_0
    //   395: invokevirtual 249	java/lang/StringBuilder:append	(Ljava/lang/String;)Ljava/lang/StringBuilder;
    //   398: ldc -5
    //   400: invokevirtual 249	java/lang/StringBuilder:append	(Ljava/lang/String;)Ljava/lang/StringBuilder;
    //   403: aload 5
    //   405: invokevirtual 249	java/lang/StringBuilder:append	(Ljava/lang/String;)Ljava/lang/StringBuilder;
    //   408: ldc -3
    //   410: invokevirtual 249	java/lang/StringBuilder:append	(Ljava/lang/String;)Ljava/lang/StringBuilder;
    //   413: invokevirtual 256	java/lang/StringBuilder:toString	()Ljava/lang/String;
    //   416: invokestatic 88	android/util/Log:w	(Ljava/lang/String;Ljava/lang/String;)I
    //   419: pop
    //   420: goto -273 -> 147
    //   423: aload 6
    //   425: arraylength
    //   426: istore_3
    //   427: iload_2
    //   428: iload_3
    //   429: if_icmpge +6 -> 435
    //   432: goto -426 -> 6
    //   435: goto +69 -> 504
    //   438: goto -86 -> 352
    //   441: new 258	org/json/JSONArray
    //   444: dup
    //   445: aload 5
    //   447: invokespecial 259	org/json/JSONArray:<init>	(Ljava/lang/String;)V
    //   450: astore_0
    //   451: aload_0
    //   452: invokevirtual 260	org/json/JSONArray:length	()I
    //   455: anewarray 68	java/lang/String
    //   458: astore 6
    //   460: iconst_0
    //   461: istore_2
    //   462: goto -163 -> 299
    //   465: new 68	java/lang/String
    //   468: dup
    //   469: aload_0
    //   470: invokespecial 236	java/lang/String:<init>	(Ljava/lang/String;)V
    //   473: astore_0
    //   474: goto -122 -> 352
    //   477: aload 6
    //   479: iload_2
    //   480: aload_0
    //   481: iload_2
    //   482: invokevirtual 264	org/json/JSONArray:opt	(I)Ljava/lang/Object;
    //   485: aastore
    //   486: iload_2
    //   487: iconst_1
    //   488: iadd
    //   489: istore_2
    //   490: goto -67 -> 423
    //   493: iconst_1
    //   494: istore_2
    //   495: goto -321 -> 174
    //   498: goto -75 -> 423
    //   501: aload 6
    //   503: areturn
    //   504: bipush 68
    //   506: istore_3
    //   507: goto -390 -> 117
    //   510: aconst_null
    //   511: areturn
    //   512: astore_0
    //   513: goto -303 -> 210
    // Local variable table:
    //   start	length	slot	name	signature
    //   0	516	0	paramBundle	Bundle
    //   0	516	1	paramString	String
    //   40	455	2	i	int
    //   8	499	3	j	int
    //   339	3	4	bool	boolean
    //   44	402	5	str	String
    //   46	456	6	localObject	Object
    // Exception table:
    //   from	to	target	type
    //   234	240	202	java/lang/Exception
    //   334	341	202	java/lang/Exception
    //   44	53	270	java/lang/Exception
    //   326	334	270	java/lang/Exception
    //   423	427	512	org/json/JSONException
    //   441	460	512	org/json/JSONException
    //   477	486	512	org/json/JSONException
  }
  
  /* Error */
  private String ˋ(String paramString)
  {
    // Byte code:
    //   0: goto +95 -> 95
    //   3: astore_1
    //   4: aload_1
    //   5: athrow
    //   6: getstatic 31	o/no:ˋॱ	I
    //   9: bipush 25
    //   11: iadd
    //   12: istore_3
    //   13: iload_3
    //   14: sipush 128
    //   17: irem
    //   18: putstatic 29	o/no:ˏॱ	I
    //   21: iload_3
    //   22: iconst_2
    //   23: irem
    //   24: ifeq +6 -> 30
    //   27: goto +188 -> 215
    //   30: goto +41 -> 71
    //   33: iload_3
    //   34: istore_2
    //   35: goto +72 -> 107
    //   38: getstatic 31	o/no:ˋॱ	I
    //   41: bipush 25
    //   43: iadd
    //   44: istore_2
    //   45: iload_2
    //   46: sipush 128
    //   49: irem
    //   50: putstatic 29	o/no:ˏॱ	I
    //   53: iload_2
    //   54: iconst_2
    //   55: irem
    //   56: ifeq +6 -> 62
    //   59: goto +120 -> 179
    //   62: goto +145 -> 207
    //   65: bipush 60
    //   67: istore_3
    //   68: goto +169 -> 237
    //   71: aload 4
    //   73: iload_2
    //   74: aload_1
    //   75: aload_1
    //   76: arraylength
    //   77: iload_2
    //   78: isub
    //   79: iconst_1
    //   80: isub
    //   81: baload
    //   82: getstatic 35	o/no:ʻ	B
    //   85: ixor
    //   86: i2b
    //   87: bastore
    //   88: iload_2
    //   89: iconst_1
    //   90: iadd
    //   91: istore_3
    //   92: goto -54 -> 38
    //   95: goto +51 -> 146
    //   98: goto +9 -> 107
    //   101: iconst_5
    //   102: iconst_5
    //   103: idiv
    //   104: istore_2
    //   105: iload_3
    //   106: istore_2
    //   107: aload_1
    //   108: arraylength
    //   109: istore_3
    //   110: iload_2
    //   111: iload_3
    //   112: if_icmpge +6 -> 118
    //   115: goto -50 -> 65
    //   118: goto +55 -> 173
    //   121: new 68	java/lang/String
    //   124: dup
    //   125: aload 4
    //   127: ldc_w 268
    //   130: invokespecial 271	java/lang/String:<init>	([BLjava/lang/String;)V
    //   133: astore_1
    //   134: aload_1
    //   135: areturn
    //   136: astore_1
    //   137: new 273	java/lang/RuntimeException
    //   140: dup
    //   141: aload_1
    //   142: invokespecial 276	java/lang/RuntimeException:<init>	(Ljava/lang/Throwable;)V
    //   145: athrow
    //   146: getstatic 29	o/no:ˏॱ	I
    //   149: bipush 69
    //   151: iadd
    //   152: istore_2
    //   153: iload_2
    //   154: sipush 128
    //   157: irem
    //   158: putstatic 31	o/no:ˋॱ	I
    //   161: iload_2
    //   162: iconst_2
    //   163: irem
    //   164: ifne +6 -> 170
    //   167: goto +45 -> 212
    //   170: goto +48 -> 218
    //   173: bipush 47
    //   175: istore_3
    //   176: goto +61 -> 237
    //   179: iconst_1
    //   180: istore_2
    //   181: iload_2
    //   182: tableswitch	default:+22->204, 0:+-149->33, 1:+-81->101
    //   204: goto -171 -> 33
    //   207: iconst_0
    //   208: istore_2
    //   209: goto -28 -> 181
    //   212: goto +6 -> 218
    //   215: goto -144 -> 71
    //   218: aload_1
    //   219: ldc_w 278
    //   222: invokevirtual 282	java/lang/String:getBytes	(Ljava/lang/String;)[B
    //   225: astore_1
    //   226: aload_1
    //   227: arraylength
    //   228: newarray byte
    //   230: astore 4
    //   232: iconst_0
    //   233: istore_2
    //   234: goto -136 -> 98
    //   237: iload_3
    //   238: lookupswitch	default:+26->264, 47:+-117->121, 60:+-232->6
    //   264: goto -143 -> 121
    // Local variable table:
    //   start	length	slot	name	signature
    //   0	267	0	this	no
    //   0	267	1	paramString	String
    //   34	200	2	i	int
    //   12	226	3	j	int
    //   71	160	4	arrayOfByte	byte[]
    // Exception table:
    //   from	to	target	type
    //   146	153	3	java/lang/Exception
    //   153	161	3	java/lang/Exception
    //   71	88	136	java/io/UnsupportedEncodingException
    //   107	110	136	java/io/UnsupportedEncodingException
    //   121	134	136	java/io/UnsupportedEncodingException
    //   218	232	136	java/io/UnsupportedEncodingException
  }
  
  /* Error */
  private static String ˋ(char[] paramArrayOfChar1, char paramChar, char[] paramArrayOfChar2, int paramInt, char[] paramArrayOfChar3)
  {
    // Byte code:
    //   0: goto +160 -> 160
    //   3: bipush 56
    //   5: istore_3
    //   6: goto +200 -> 206
    //   9: iload_1
    //   10: lookupswitch	default:+26->36, 23:+258->268, 59:+145->155
    //   36: goto +119 -> 155
    //   39: goto +240 -> 279
    //   42: aload_0
    //   43: invokevirtual 288	[C:clone	()Ljava/lang/Object;
    //   46: checkcast 285	[C
    //   49: astore_0
    //   50: aload 4
    //   52: invokevirtual 288	[C:clone	()Ljava/lang/Object;
    //   55: checkcast 285	[C
    //   58: astore 4
    //   60: aload_0
    //   61: iconst_0
    //   62: aload_0
    //   63: iconst_0
    //   64: caload
    //   65: iload_1
    //   66: ixor
    //   67: i2c
    //   68: castore
    //   69: aload 4
    //   71: iconst_2
    //   72: aload 4
    //   74: iconst_2
    //   75: caload
    //   76: iload_3
    //   77: i2c
    //   78: iadd
    //   79: i2c
    //   80: castore
    //   81: aload_2
    //   82: arraylength
    //   83: istore 5
    //   85: iload 5
    //   87: newarray char
    //   89: astore 10
    //   91: iconst_0
    //   92: istore_3
    //   93: goto +142 -> 235
    //   96: astore_0
    //   97: aload_0
    //   98: athrow
    //   99: aload_0
    //   100: aload 4
    //   102: iload_1
    //   103: invokestatic 293	o/oJ:ˏ	([C[CI)V
    //   106: aload_2
    //   107: iload_1
    //   108: caload
    //   109: aload_0
    //   110: iload_1
    //   111: iconst_3
    //   112: iadd
    //   113: iconst_4
    //   114: irem
    //   115: caload
    //   116: ixor
    //   117: i2l
    //   118: lstore 6
    //   120: getstatic 295	o/no:ᐝ	J
    //   123: lstore 8
    //   125: getstatic 297	o/no:ʼ	I
    //   128: istore_3
    //   129: aload 10
    //   131: iload_1
    //   132: lload 6
    //   134: lload 8
    //   136: lxor
    //   137: iload_3
    //   138: i2l
    //   139: lxor
    //   140: getstatic 299	o/no:ॱॱ	C
    //   143: i2l
    //   144: lxor
    //   145: l2i
    //   146: i2c
    //   147: castore
    //   148: iload_1
    //   149: iconst_1
    //   150: iadd
    //   151: istore_1
    //   152: goto -113 -> 39
    //   155: iload_3
    //   156: istore_1
    //   157: goto +122 -> 279
    //   160: goto -118 -> 42
    //   163: getstatic 29	o/no:ˏॱ	I
    //   166: bipush 15
    //   168: iadd
    //   169: istore_3
    //   170: iload_3
    //   171: sipush 128
    //   174: irem
    //   175: putstatic 31	o/no:ˋॱ	I
    //   178: iload_3
    //   179: iconst_2
    //   180: irem
    //   181: ifne +6 -> 187
    //   184: goto +19 -> 203
    //   187: goto -88 -> 99
    //   190: new 68	java/lang/String
    //   193: dup
    //   194: aload 10
    //   196: invokespecial 302	java/lang/String:<init>	([C)V
    //   199: areturn
    //   200: astore_0
    //   201: aload_0
    //   202: athrow
    //   203: goto -104 -> 99
    //   206: iload_3
    //   207: lookupswitch	default:+25->232, 21:+-44->163, 56:+-17->190
    //   232: goto -42 -> 190
    //   235: getstatic 31	o/no:ˋॱ	I
    //   238: bipush 63
    //   240: iadd
    //   241: istore_1
    //   242: iload_1
    //   243: sipush 128
    //   246: irem
    //   247: putstatic 29	o/no:ˏॱ	I
    //   250: iload_1
    //   251: iconst_2
    //   252: irem
    //   253: ifeq +6 -> 259
    //   256: goto +35 -> 291
    //   259: goto +14 -> 273
    //   262: bipush 21
    //   264: istore_3
    //   265: goto -59 -> 206
    //   268: iload_3
    //   269: istore_1
    //   270: goto +9 -> 279
    //   273: bipush 23
    //   275: istore_1
    //   276: goto -267 -> 9
    //   279: iload_1
    //   280: iload 5
    //   282: if_icmpge +6 -> 288
    //   285: goto -23 -> 262
    //   288: goto -285 -> 3
    //   291: bipush 59
    //   293: istore_1
    //   294: goto -285 -> 9
    // Local variable table:
    //   start	length	slot	name	signature
    //   0	297	0	paramArrayOfChar1	char[]
    //   0	297	1	paramChar	char
    //   0	297	2	paramArrayOfChar2	char[]
    //   0	297	3	paramInt	int
    //   0	297	4	paramArrayOfChar3	char[]
    //   83	200	5	c	char
    //   118	15	6	l1	long
    //   123	12	8	l2	long
    //   89	106	10	arrayOfChar	char[]
    // Exception table:
    //   from	to	target	type
    //   99	106	96	java/lang/Exception
    //   120	125	96	java/lang/Exception
    //   125	129	200	java/lang/Exception
    //   235	242	200	java/lang/Exception
    //   242	250	200	java/lang/Exception
  }
  
  /* Error */
  public static boolean ˋ(Bundle paramBundle)
  {
    // Byte code:
    //   0: goto +272 -> 272
    //   3: goto +206 -> 209
    //   6: astore_0
    //   7: aload_0
    //   8: athrow
    //   9: bipush 49
    //   11: istore_1
    //   12: goto +224 -> 236
    //   15: bipush 74
    //   17: istore_1
    //   18: goto +218 -> 236
    //   21: iload_1
    //   22: lookupswitch	default:+26->48, 49:+130->152, 89:+185->207
    //   48: goto +104 -> 152
    //   51: bipush 94
    //   53: istore_1
    //   54: goto +123 -> 177
    //   57: aload_0
    //   58: ldc_w 305
    //   61: invokestatic 121	o/no:ˎ	(Landroid/os/Bundle;Ljava/lang/String;)Ljava/lang/String;
    //   64: astore_0
    //   65: bipush 71
    //   67: iconst_0
    //   68: idiv
    //   69: istore_1
    //   70: aload_0
    //   71: ifnull +6 -> 77
    //   74: goto +157 -> 231
    //   77: goto -26 -> 51
    //   80: getstatic 31	o/no:ˋॱ	I
    //   83: bipush 107
    //   85: iadd
    //   86: istore_1
    //   87: iload_1
    //   88: sipush 128
    //   91: irem
    //   92: putstatic 29	o/no:ˏॱ	I
    //   95: iload_1
    //   96: iconst_2
    //   97: irem
    //   98: ifeq +6 -> 104
    //   101: goto +166 -> 267
    //   104: goto +51 -> 155
    //   107: aload_0
    //   108: ldc_w 305
    //   111: invokestatic 121	o/no:ˎ	(Landroid/os/Bundle;Ljava/lang/String;)Ljava/lang/String;
    //   114: astore_0
    //   115: aload_0
    //   116: ifnull +6 -> 122
    //   119: goto +41 -> 160
    //   122: goto +44 -> 166
    //   125: getstatic 29	o/no:ˏॱ	I
    //   128: bipush 73
    //   130: iadd
    //   131: istore_1
    //   132: iload_1
    //   133: sipush 128
    //   136: irem
    //   137: putstatic 31	o/no:ˋॱ	I
    //   140: iload_1
    //   141: iconst_2
    //   142: irem
    //   143: ifne +6 -> 149
    //   146: goto -143 -> 3
    //   149: goto +60 -> 209
    //   152: goto +20 -> 172
    //   155: iconst_0
    //   156: istore_1
    //   157: goto +118 -> 275
    //   160: bipush 89
    //   162: istore_1
    //   163: goto -142 -> 21
    //   166: bipush 49
    //   168: istore_1
    //   169: goto -148 -> 21
    //   172: iconst_0
    //   173: ireturn
    //   174: astore_0
    //   175: aload_0
    //   176: athrow
    //   177: iload_1
    //   178: lookupswitch	default:+26->204, 0:+29->207, 94:+-26->152
    //   204: goto -52 -> 152
    //   207: iconst_1
    //   208: ireturn
    //   209: ldc_w 307
    //   212: aload_0
    //   213: ldc_w 309
    //   216: invokestatic 121	o/no:ˎ	(Landroid/os/Bundle;Ljava/lang/String;)Ljava/lang/String;
    //   219: invokevirtual 313	java/lang/String:equals	(Ljava/lang/Object;)Z
    //   222: ifne +6 -> 228
    //   225: goto -216 -> 9
    //   228: goto -213 -> 15
    //   231: iconst_0
    //   232: istore_1
    //   233: goto -56 -> 177
    //   236: iload_1
    //   237: lookupswitch	default:+27->264, 49:+-157->80, 74:+-30->207
    //   264: goto -57 -> 207
    //   267: iconst_1
    //   268: istore_1
    //   269: goto +6 -> 275
    //   272: goto -147 -> 125
    //   275: iload_1
    //   276: tableswitch	default:+24->300, 0:+-169->107, 1:+-219->57
    //   300: goto -243 -> 57
    // Local variable table:
    //   start	length	slot	name	signature
    //   0	303	0	paramBundle	Bundle
    //   11	265	1	i	int
    // Exception table:
    //   from	to	target	type
    //   107	115	6	java/lang/Exception
    //   80	87	174	java/lang/Exception
    //   87	95	174	java/lang/Exception
  }
  
  private final Integer ˎ(String paramString)
  {
    break label310;
    label3:
    return null;
    for (;;)
    {
      try
      {
        i = Color.parseColor(paramString);
        return Integer.valueOf(i);
      }
      catch (IllegalArgumentException localIllegalArgumentException)
      {
        int i;
        label34:
        int j;
        continue;
        continue;
      }
      i = 61;
      continue;
      if (!TextUtils.isEmpty(paramString)) {
        continue;
      }
      continue;
      i = Color.parseColor(paramString);
      j = 69 / 0;
      return Integer.valueOf(i);
      j = ˊ().getInt("com.google.firebase.messaging.default_notification_color", 0);
      if (j != 0) {
        continue;
      }
    }
    label71:
    if (Build.VERSION.SDK_INT >= 21) {
      break label211;
    }
    i = 1;
    break label270;
    i = 96;
    break label313;
    switch (i)
    {
    case 61: 
    default: 
      label96:
      break;
    }
    for (;;)
    {
      switch (i)
      {
      default: 
        break label200;
        Log.w("FirebaseMessaging", String.valueOf(paramString).length() + 54 + "Color " + paramString + " not valid. Notification will use default color.");
        break;
      case 1: 
        break;
      case 0: 
        label200:
        i = 49 / 0;
        break label369;
        label211:
        i = 0;
        for (;;)
        {
          try
          {
            i = ˏॱ + 59;
            ˋॱ = i % 128;
            if (i % 2 == 0) {
              break label34;
            }
          }
          catch (Exception paramString)
          {
            label270:
            throw paramString;
          }
          i = ˏॱ + 83;
          ˋॱ = i % 128;
          if (i % 2 == 0) {
            break label376;
          }
          break label371;
          switch (i)
          {
          }
        }
        Log.w("FirebaseMessaging", "Cannot find the color resource referenced in AndroidManifest.");
        break label3;
        label310:
        break label71;
        for (;;)
        {
          label313:
          switch (i)
          {
          }
          break;
          try
          {
            i = ᔆ.ˊ(this.ˋ, j);
            return Integer.valueOf(i);
          }
          catch (Resources.NotFoundException paramString) {}
          i = 48;
        }
        i = 45;
        break label96;
        label369:
        return null;
        label371:
        i = 1;
        continue;
        label376:
        i = 0;
      }
    }
  }
  
  static String ˎ(Bundle paramBundle)
  {
    break label249;
    int i = ˋॱ + 97;
    ˏॱ = i % 128;
    label30:
    label33:
    String str;
    if (i % 2 == 0)
    {
      break label94;
      break label67;
      i = 0;
      break label216;
      return str;
      i = ˏॱ + 99;
      ˋॱ = i % 128;
      if (i % 2 == 0) {
        break label181;
      }
      break label102;
      label67:
      i = ˋॱ + 57;
      ˏॱ = i % 128;
      if (i % 2 != 0) {
        break label243;
      }
      break label184;
    }
    for (;;)
    {
      label94:
      break label30;
      label102:
      label113:
      do
      {
        i = 1;
        break label216;
        try
        {
          str = ˎ(paramBundle, "gcm.n.sound");
        }
        catch (Exception paramBundle)
        {
          throw paramBundle;
        }
        str = ˎ(paramBundle, "gcm.n.sound2");
      } while (TextUtils.isEmpty(str));
      break label33;
    }
    for (;;)
    {
      switch (i)
      {
      case 81: 
      default: 
        label137:
        break;
      }
      throw new NullPointerException();
      label178:
      break label113;
      label181:
      break;
      label184:
      i = 81;
    }
    label216:
    label243:
    label249:
    for (;;)
    {
      i = ˋॱ + 1;
      ˏॱ = i % 128;
      if (i % 2 != 0) {
        break label178;
      }
      break label113;
      switch (i)
      {
      }
      break;
      i = 35;
      break label137;
    }
  }
  
  /* Error */
  static String ˎ(Bundle paramBundle, String paramString)
  {
    // Byte code:
    //   0: goto +172 -> 172
    //   3: aload_3
    //   4: areturn
    //   5: bipush 40
    //   7: iconst_0
    //   8: idiv
    //   9: istore_2
    //   10: aload_3
    //   11: areturn
    //   12: iconst_1
    //   13: istore_2
    //   14: goto +116 -> 130
    //   17: goto +158 -> 175
    //   20: astore_0
    //   21: aload_0
    //   22: athrow
    //   23: astore_0
    //   24: aload_0
    //   25: athrow
    //   26: goto +24 -> 50
    //   29: aload_0
    //   30: aload_1
    //   31: ldc -121
    //   33: ldc 66
    //   35: invokevirtual 362	java/lang/String:replace	(Ljava/lang/CharSequence;Ljava/lang/CharSequence;)Ljava/lang/String;
    //   38: invokevirtual 365	android/os/Bundle:getString	(Ljava/lang/String;)Ljava/lang/String;
    //   41: astore_3
    //   42: goto -16 -> 26
    //   45: iconst_1
    //   46: istore_2
    //   47: goto +56 -> 103
    //   50: getstatic 29	o/no:ˏॱ	I
    //   53: bipush 115
    //   55: iadd
    //   56: istore_2
    //   57: iload_2
    //   58: sipush 128
    //   61: irem
    //   62: putstatic 31	o/no:ˋॱ	I
    //   65: iload_2
    //   66: iconst_2
    //   67: irem
    //   68: ifne +6 -> 74
    //   71: goto +96 -> 167
    //   74: goto -29 -> 45
    //   77: getstatic 31	o/no:ˋॱ	I
    //   80: iconst_3
    //   81: iadd
    //   82: istore_2
    //   83: iload_2
    //   84: sipush 128
    //   87: irem
    //   88: putstatic 29	o/no:ˏॱ	I
    //   91: iload_2
    //   92: iconst_2
    //   93: irem
    //   94: ifeq +6 -> 100
    //   97: goto -80 -> 17
    //   100: goto +75 -> 175
    //   103: iload_2
    //   104: tableswitch	default:+24->128, 0:+-99->5, 1:+-101->3
    //   128: aload_3
    //   129: areturn
    //   130: aload 4
    //   132: astore_3
    //   133: iload_2
    //   134: tableswitch	default:+22->156, 0:+-105->29, 1:+-108->26
    //   156: aload 4
    //   158: astore_3
    //   159: goto -133 -> 26
    //   162: iconst_0
    //   163: istore_2
    //   164: goto -34 -> 130
    //   167: iconst_0
    //   168: istore_2
    //   169: goto -66 -> 103
    //   172: goto -95 -> 77
    //   175: aload_0
    //   176: aload_1
    //   177: invokevirtual 365	android/os/Bundle:getString	(Ljava/lang/String;)Ljava/lang/String;
    //   180: astore 4
    //   182: aload 4
    //   184: ifnonnull +6 -> 190
    //   187: goto -25 -> 162
    //   190: goto -178 -> 12
    // Local variable table:
    //   start	length	slot	name	signature
    //   0	193	0	paramBundle	Bundle
    //   0	193	1	paramString	String
    //   9	160	2	i	int
    //   3	156	3	localObject	Object
    //   130	53	4	str	String
    // Exception table:
    //   from	to	target	type
    //   83	91	20	java/lang/Exception
    //   77	83	23	java/lang/Exception
    //   83	91	23	java/lang/Exception
  }
  
  public static no ˎ(Context paramContext)
  {
    break label179;
    label70:
    try
    {
      paramContext = new no(paramContext);
      try
      {
        ˏ = paramContext;
        i = ˏॱ + 67;
        ˋॱ = i % 128;
        if (i % 2 != 0) {
          break label121;
        }
      }
      catch (Exception paramContext)
      {
        throw paramContext;
      }
      i = ˋॱ + 123;
      ˏॱ = i % 128;
      if (i % 2 == 0) {
        break label185;
      }
    }
    finally {}
    int i = 3 / 3;
    break label98;
    paramContext = ˏ;
    throw new NullPointerException();
    for (;;)
    {
      if (ˏ != null) {
        break label188;
      }
      break;
      label98:
      paramContext = ˏ;
      break label110;
      label105:
      i = 1;
      break label124;
      label110:
      return paramContext;
      label121:
      break label201;
      label124:
      switch (i)
      {
      }
    }
    for (;;)
    {
      switch (i)
      {
      case 0: 
      default: 
        break label70;
        break;
      case 1: 
        label179:
        break label98;
        label185:
        break label105;
        label188:
        break label98;
        i = 0;
        break label124;
        i = 0;
        continue;
        label201:
        i = 1;
      }
    }
  }
  
  /* Error */
  private static void ˎ(Intent paramIntent, Bundle paramBundle)
  {
    // Byte code:
    //   0: goto +260 -> 260
    //   3: aload 6
    //   5: astore 5
    //   7: aload 6
    //   9: astore 4
    //   11: iload_2
    //   12: lookupswitch	default:+28->40, 78:+352->364, 93:+287->299
    //   40: aload 6
    //   42: astore 4
    //   44: goto +320 -> 364
    //   47: aload 7
    //   49: invokeinterface 158 1 0
    //   54: ifeq +6 -> 60
    //   57: goto +68 -> 125
    //   60: goto +325 -> 385
    //   63: iconst_0
    //   64: istore_2
    //   65: goto +207 -> 272
    //   68: astore_0
    //   69: aload_0
    //   70: athrow
    //   71: aload 7
    //   73: invokeinterface 133 1 0
    //   78: checkcast 68	java/lang/String
    //   81: astore 6
    //   83: aload 6
    //   85: ldc_w 373
    //   88: invokevirtual 72	java/lang/String:startsWith	(Ljava/lang/String;)Z
    //   91: istore_3
    //   92: bipush 8
    //   94: iconst_0
    //   95: idiv
    //   96: istore_2
    //   97: iload_3
    //   98: ifne +6 -> 104
    //   101: goto +165 -> 266
    //   104: goto +243 -> 347
    //   107: aload_1
    //   108: invokevirtual 110	android/os/Bundle:keySet	()Ljava/util/Set;
    //   111: astore 4
    //   113: aload 4
    //   115: invokeinterface 116 1 0
    //   120: astore 7
    //   122: goto -75 -> 47
    //   125: bipush 81
    //   127: istore_2
    //   128: goto +71 -> 199
    //   131: getstatic 29	o/no:ˏॱ	I
    //   134: istore_2
    //   135: iload_2
    //   136: bipush 25
    //   138: iadd
    //   139: istore_2
    //   140: iload_2
    //   141: sipush 128
    //   144: irem
    //   145: putstatic 31	o/no:ˋॱ	I
    //   148: iload_2
    //   149: iconst_2
    //   150: irem
    //   151: ifne +6 -> 157
    //   154: goto -91 -> 63
    //   157: goto +242 -> 399
    //   160: aload 6
    //   162: astore 5
    //   164: aload 6
    //   166: astore 4
    //   168: iload_2
    //   169: tableswitch	default:+23->192, 0:+195->364, 1:+130->299
    //   192: aload 6
    //   194: astore 5
    //   196: goto +103 -> 299
    //   199: iload_2
    //   200: lookupswitch	default:+28->228, 66:+184->384, 81:+-69->131
    //   228: goto -97 -> 131
    //   231: aload 7
    //   233: invokeinterface 133 1 0
    //   238: checkcast 68	java/lang/String
    //   241: astore 6
    //   243: aload 6
    //   245: ldc_w 373
    //   248: invokevirtual 72	java/lang/String:startsWith	(Ljava/lang/String;)Z
    //   251: ifne +6 -> 257
    //   254: goto +140 -> 394
    //   257: goto +99 -> 356
    //   260: goto -153 -> 107
    //   263: goto +90 -> 353
    //   266: bipush 93
    //   268: istore_2
    //   269: goto -266 -> 3
    //   272: iload_2
    //   273: tableswitch	default:+23->296, 0:+-202->71, 1:+-42->231
    //   296: goto -225 -> 71
    //   299: aload 5
    //   301: ldc_w 375
    //   304: invokevirtual 313	java/lang/String:equals	(Ljava/lang/Object;)Z
    //   307: ifeq +10 -> 317
    //   310: aload 5
    //   312: astore 4
    //   314: goto +50 -> 364
    //   317: goto +36 -> 353
    //   320: getstatic 29	o/no:ˏॱ	I
    //   323: bipush 55
    //   325: iadd
    //   326: istore_2
    //   327: iload_2
    //   328: sipush 128
    //   331: irem
    //   332: putstatic 31	o/no:ˋॱ	I
    //   335: iload_2
    //   336: iconst_2
    //   337: irem
    //   338: ifne +6 -> 344
    //   341: goto +20 -> 361
    //   344: goto -81 -> 263
    //   347: bipush 78
    //   349: istore_2
    //   350: goto -347 -> 3
    //   353: goto -306 -> 47
    //   356: iconst_0
    //   357: istore_2
    //   358: goto -198 -> 160
    //   361: goto -8 -> 353
    //   364: aload_1
    //   365: aload 4
    //   367: invokevirtual 365	android/os/Bundle:getString	(Ljava/lang/String;)Ljava/lang/String;
    //   370: astore 5
    //   372: aload_0
    //   373: aload 4
    //   375: aload 5
    //   377: invokevirtual 379	android/content/Intent:putExtra	(Ljava/lang/String;Ljava/lang/String;)Landroid/content/Intent;
    //   380: pop
    //   381: goto -61 -> 320
    //   384: return
    //   385: bipush 66
    //   387: istore_2
    //   388: goto -189 -> 199
    //   391: astore_0
    //   392: aload_0
    //   393: athrow
    //   394: iconst_1
    //   395: istore_2
    //   396: goto -236 -> 160
    //   399: iconst_1
    //   400: istore_2
    //   401: goto -129 -> 272
    // Local variable table:
    //   start	length	slot	name	signature
    //   0	404	0	paramIntent	Intent
    //   0	404	1	paramBundle	Bundle
    //   11	390	2	i	int
    //   91	7	3	bool	boolean
    //   9	365	4	localObject	Object
    //   5	371	5	str1	String
    //   3	241	6	str2	String
    //   47	185	7	localIterator	Iterator
    // Exception table:
    //   from	to	target	type
    //   107	113	68	java/lang/Exception
    //   140	148	68	java/lang/Exception
    //   131	135	391	java/lang/Exception
    //   364	372	391	java/lang/Exception
    //   372	381	391	java/lang/Exception
  }
  
  /* Error */
  @android.annotation.TargetApi(26)
  private final Notification ˏ(CharSequence paramCharSequence, String paramString1, int paramInt, Integer paramInteger, Uri paramUri, PendingIntent paramPendingIntent1, PendingIntent paramPendingIntent2, String paramString2)
  {
    // Byte code:
    //   0: goto +662 -> 662
    //   3: astore_1
    //   4: ldc 80
    //   6: ldc_w 386
    //   9: aload_1
    //   10: invokestatic 390	android/util/Log:e	(Ljava/lang/String;Ljava/lang/String;Ljava/lang/Throwable;)I
    //   13: pop
    //   14: goto +16 -> 30
    //   17: aload_0
    //   18: getfield 392	o/no:ˊ	Ljava/lang/reflect/Method;
    //   21: ifnonnull +6 -> 27
    //   24: goto +619 -> 643
    //   27: goto +610 -> 637
    //   30: aload 10
    //   32: invokevirtual 396	android/app/Notification$Builder:build	()Landroid/app/Notification;
    //   35: areturn
    //   36: aload 10
    //   38: aload 5
    //   40: invokevirtual 400	android/app/Notification$Builder:setSound	(Landroid/net/Uri;)Landroid/app/Notification$Builder;
    //   43: pop
    //   44: goto +256 -> 300
    //   47: aload 10
    //   49: aload 4
    //   51: invokevirtual 403	java/lang/Integer:intValue	()I
    //   54: invokevirtual 407	android/app/Notification$Builder:setColor	(I)Landroid/app/Notification$Builder;
    //   57: pop
    //   58: goto +190 -> 248
    //   61: aload 10
    //   63: aload 6
    //   65: invokevirtual 411	android/app/Notification$Builder:setContentIntent	(Landroid/app/PendingIntent;)Landroid/app/Notification$Builder;
    //   68: pop
    //   69: goto +607 -> 676
    //   72: astore_1
    //   73: aload_1
    //   74: athrow
    //   75: bipush 36
    //   77: istore_3
    //   78: iload_3
    //   79: lookupswitch	default:+25->104, 36:+101->180, 75:+392->471
    //   104: goto +367 -> 471
    //   107: aload_0
    //   108: getfield 392	o/no:ˊ	Ljava/lang/reflect/Method;
    //   111: ifnonnull +6 -> 117
    //   114: goto +453 -> 567
    //   117: goto +570 -> 687
    //   120: aload_2
    //   121: invokestatic 127	android/text/TextUtils:isEmpty	(Ljava/lang/CharSequence;)Z
    //   124: ifne +6 -> 130
    //   127: goto +483 -> 610
    //   130: goto +282 -> 412
    //   133: iload_3
    //   134: lookupswitch	default:+26->160, 85:+515->649, 98:+-117->17
    //   160: goto +489 -> 649
    //   163: astore_1
    //   164: ldc 80
    //   166: ldc_w 386
    //   169: aload_1
    //   170: invokestatic 390	android/util/Log:e	(Ljava/lang/String;Ljava/lang/String;Ljava/lang/Throwable;)I
    //   173: pop
    //   174: goto -144 -> 30
    //   177: goto -147 -> 30
    //   180: aload 10
    //   182: aload 7
    //   184: invokevirtual 414	android/app/Notification$Builder:setDeleteIntent	(Landroid/app/PendingIntent;)Landroid/app/Notification$Builder;
    //   187: pop
    //   188: goto +283 -> 471
    //   191: iload_3
    //   192: tableswitch	default:+24->216, 0:+135->327, 1:+-131->61
    //   216: goto -155 -> 61
    //   219: ldc 80
    //   221: ldc_w 386
    //   224: invokestatic 416	android/util/Log:e	(Ljava/lang/String;Ljava/lang/String;)I
    //   227: pop
    //   228: goto -198 -> 30
    //   231: iconst_1
    //   232: istore_3
    //   233: goto -42 -> 191
    //   236: bipush 75
    //   238: istore_3
    //   239: goto -161 -> 78
    //   242: bipush 98
    //   244: istore_3
    //   245: goto -112 -> 133
    //   248: getstatic 31	o/no:ˋॱ	I
    //   251: bipush 125
    //   253: iadd
    //   254: istore_3
    //   255: iload_3
    //   256: sipush 128
    //   259: irem
    //   260: putstatic 29	o/no:ˏॱ	I
    //   263: iload_3
    //   264: iconst_2
    //   265: irem
    //   266: ifeq +6 -> 272
    //   269: goto +311 -> 580
    //   272: goto +265 -> 537
    //   275: astore_1
    //   276: aload_1
    //   277: athrow
    //   278: aload_0
    //   279: getfield 392	o/no:ˊ	Ljava/lang/reflect/Method;
    //   282: aload 10
    //   284: iconst_1
    //   285: anewarray 4	java/lang/Object
    //   288: dup
    //   289: iconst_0
    //   290: aload 8
    //   292: aastore
    //   293: invokevirtual 422	java/lang/reflect/Method:invoke	(Ljava/lang/Object;[Ljava/lang/Object;)Ljava/lang/Object;
    //   296: pop
    //   297: goto -120 -> 177
    //   300: aload 6
    //   302: ifnull +6 -> 308
    //   305: goto +278 -> 583
    //   308: goto +368 -> 676
    //   311: aload 10
    //   313: aload_1
    //   314: invokevirtual 426	android/app/Notification$Builder:setContentTitle	(Ljava/lang/CharSequence;)Landroid/app/Notification$Builder;
    //   317: pop
    //   318: goto -198 -> 120
    //   321: bipush 85
    //   323: istore_3
    //   324: goto -191 -> 133
    //   327: aload 10
    //   329: aload 6
    //   331: invokevirtual 411	android/app/Notification$Builder:setContentIntent	(Landroid/app/PendingIntent;)Landroid/app/Notification$Builder;
    //   334: pop
    //   335: aconst_null
    //   336: arraylength
    //   337: istore_3
    //   338: goto +338 -> 676
    //   341: iload_3
    //   342: lookupswitch	default:+26->368, 9:+-123->219, 90:+-64->278
    //   368: goto -149 -> 219
    //   371: astore_1
    //   372: ldc 80
    //   374: ldc_w 386
    //   377: aload_1
    //   378: invokestatic 390	android/util/Log:e	(Ljava/lang/String;Ljava/lang/String;Ljava/lang/Throwable;)I
    //   381: pop
    //   382: goto -352 -> 30
    //   385: getstatic 31	o/no:ˋॱ	I
    //   388: bipush 53
    //   390: iadd
    //   391: istore_3
    //   392: iload_3
    //   393: sipush 128
    //   396: irem
    //   397: putstatic 29	o/no:ˏॱ	I
    //   400: iload_3
    //   401: iconst_2
    //   402: irem
    //   403: ifeq +6 -> 409
    //   406: goto +33 -> 439
    //   409: goto -302 -> 107
    //   412: aload 4
    //   414: ifnull +6 -> 420
    //   417: goto -370 -> 47
    //   420: goto +245 -> 665
    //   423: aload 10
    //   425: aload 5
    //   427: invokevirtual 400	android/app/Notification$Builder:setSound	(Landroid/net/Uri;)Landroid/app/Notification$Builder;
    //   430: pop
    //   431: bipush 95
    //   433: iconst_0
    //   434: idiv
    //   435: istore_3
    //   436: goto -136 -> 300
    //   439: aload_0
    //   440: getfield 392	o/no:ˊ	Ljava/lang/reflect/Method;
    //   443: astore_1
    //   444: aconst_null
    //   445: arraylength
    //   446: istore_3
    //   447: aload_1
    //   448: ifnonnull +6 -> 454
    //   451: goto +116 -> 567
    //   454: goto +233 -> 687
    //   457: astore_1
    //   458: ldc 80
    //   460: ldc_w 386
    //   463: aload_1
    //   464: invokestatic 390	android/util/Log:e	(Ljava/lang/String;Ljava/lang/String;Ljava/lang/Throwable;)I
    //   467: pop
    //   468: goto -438 -> 30
    //   471: aload 8
    //   473: ifnull +6 -> 479
    //   476: goto -91 -> 385
    //   479: goto -449 -> 30
    //   482: aload_0
    //   483: getfield 63	o/no:ˋ	Landroid/content/Context;
    //   486: astore 10
    //   488: new 212	android/app/Notification$Builder
    //   491: dup
    //   492: aload 10
    //   494: invokespecial 427	android/app/Notification$Builder:<init>	(Landroid/content/Context;)V
    //   497: astore 10
    //   499: aload 10
    //   501: iconst_1
    //   502: invokevirtual 431	android/app/Notification$Builder:setAutoCancel	(Z)Landroid/app/Notification$Builder;
    //   505: astore 10
    //   507: aload 10
    //   509: iload_3
    //   510: invokevirtual 434	android/app/Notification$Builder:setSmallIcon	(I)Landroid/app/Notification$Builder;
    //   513: astore 10
    //   515: aload_1
    //   516: invokestatic 127	android/text/TextUtils:isEmpty	(Ljava/lang/CharSequence;)Z
    //   519: istore 9
    //   521: iload 9
    //   523: ifne +6 -> 529
    //   526: goto -215 -> 311
    //   529: goto -409 -> 120
    //   532: iconst_0
    //   533: istore_3
    //   534: goto -343 -> 191
    //   537: goto +128 -> 665
    //   540: getstatic 29	o/no:ˏॱ	I
    //   543: bipush 33
    //   545: iadd
    //   546: istore_3
    //   547: iload_3
    //   548: sipush 128
    //   551: irem
    //   552: putstatic 31	o/no:ˋॱ	I
    //   555: iload_3
    //   556: iconst_2
    //   557: irem
    //   558: ifne +6 -> 564
    //   561: goto -138 -> 423
    //   564: goto -528 -> 36
    //   567: aload_0
    //   568: ldc_w 436
    //   571: invokestatic 438	o/no:ˊ	(Ljava/lang/String;)Ljava/lang/reflect/Method;
    //   574: putfield 392	o/no:ˊ	Ljava/lang/reflect/Method;
    //   577: goto +110 -> 687
    //   580: goto -43 -> 537
    //   583: getstatic 29	o/no:ˏॱ	I
    //   586: bipush 121
    //   588: iadd
    //   589: istore_3
    //   590: iload_3
    //   591: sipush 128
    //   594: irem
    //   595: putstatic 31	o/no:ˋॱ	I
    //   598: iload_3
    //   599: iconst_2
    //   600: irem
    //   601: ifne +6 -> 607
    //   604: goto -72 -> 532
    //   607: goto -376 -> 231
    //   610: aload 10
    //   612: aload_2
    //   613: invokevirtual 441	android/app/Notification$Builder:setContentText	(Ljava/lang/CharSequence;)Landroid/app/Notification$Builder;
    //   616: pop
    //   617: aload 10
    //   619: new 443	android/app/Notification$BigTextStyle
    //   622: dup
    //   623: invokespecial 444	android/app/Notification$BigTextStyle:<init>	()V
    //   626: aload_2
    //   627: invokevirtual 448	android/app/Notification$BigTextStyle:bigText	(Ljava/lang/CharSequence;)Landroid/app/Notification$BigTextStyle;
    //   630: invokevirtual 452	android/app/Notification$Builder:setStyle	(Landroid/app/Notification$Style;)Landroid/app/Notification$Builder;
    //   633: pop
    //   634: goto -222 -> 412
    //   637: bipush 90
    //   639: istore_3
    //   640: goto -299 -> 341
    //   643: bipush 9
    //   645: istore_3
    //   646: goto -305 -> 341
    //   649: aload_0
    //   650: ldc_w 454
    //   653: invokestatic 438	o/no:ˊ	(Ljava/lang/String;)Ljava/lang/reflect/Method;
    //   656: putfield 392	o/no:ˊ	Ljava/lang/reflect/Method;
    //   659: goto -642 -> 17
    //   662: goto -180 -> 482
    //   665: aload 5
    //   667: ifnull +6 -> 673
    //   670: goto -130 -> 540
    //   673: goto -373 -> 300
    //   676: aload 7
    //   678: ifnull +6 -> 684
    //   681: goto -606 -> 75
    //   684: goto -448 -> 236
    //   687: aload_0
    //   688: getfield 392	o/no:ˊ	Ljava/lang/reflect/Method;
    //   691: ifnonnull +6 -> 697
    //   694: goto -373 -> 321
    //   697: goto -455 -> 242
    // Local variable table:
    //   start	length	slot	name	signature
    //   0	700	0	this	no
    //   0	700	1	paramCharSequence	CharSequence
    //   0	700	2	paramString1	String
    //   0	700	3	paramInt	int
    //   0	700	4	paramInteger	Integer
    //   0	700	5	paramUri	Uri
    //   0	700	6	paramPendingIntent1	PendingIntent
    //   0	700	7	paramPendingIntent2	PendingIntent
    //   0	700	8	paramString2	String
    //   519	3	9	bool	boolean
    //   30	588	10	localObject	Object
    // Exception table:
    //   from	to	target	type
    //   278	297	3	java/lang/SecurityException
    //   47	58	72	java/lang/Exception
    //   482	488	72	java/lang/Exception
    //   499	507	72	java/lang/Exception
    //   278	297	163	java/lang/IllegalAccessException
    //   507	515	275	java/lang/Exception
    //   515	521	275	java/lang/Exception
    //   278	297	371	java/lang/IllegalArgumentException
    //   278	297	457	java/lang/reflect/InvocationTargetException
  }
  
  /* Error */
  static Uri ˏ(Bundle paramBundle)
  {
    // Byte code:
    //   0: goto +98 -> 98
    //   3: aconst_null
    //   4: areturn
    //   5: iconst_0
    //   6: istore_1
    //   7: goto +37 -> 44
    //   10: iload_1
    //   11: lookupswitch	default:+25->36, 29:+-8->3, 38:+66->77
    //   36: goto -33 -> 3
    //   39: aload_0
    //   40: invokestatic 460	android/net/Uri:parse	(Ljava/lang/String;)Landroid/net/Uri;
    //   43: areturn
    //   44: iload_1
    //   45: tableswitch	default:+23->68, 0:+139->184, 1:+114->159
    //   68: goto +91 -> 159
    //   71: bipush 38
    //   73: istore_1
    //   74: goto -64 -> 10
    //   77: aconst_null
    //   78: arraylength
    //   79: istore_1
    //   80: aconst_null
    //   81: areturn
    //   82: iconst_1
    //   83: istore_1
    //   84: goto -40 -> 44
    //   87: aload_0
    //   88: ldc_w 462
    //   91: invokestatic 121	o/no:ˎ	(Landroid/os/Bundle;Ljava/lang/String;)Ljava/lang/String;
    //   94: astore_0
    //   95: goto +76 -> 171
    //   98: goto +35 -> 133
    //   101: astore_0
    //   102: aload_0
    //   103: athrow
    //   104: getstatic 31	o/no:ˋॱ	I
    //   107: istore_1
    //   108: iload_1
    //   109: bipush 87
    //   111: iadd
    //   112: istore_1
    //   113: iload_1
    //   114: sipush 128
    //   117: irem
    //   118: putstatic 29	o/no:ˏॱ	I
    //   121: iload_1
    //   122: iconst_2
    //   123: irem
    //   124: ifeq +6 -> 130
    //   127: goto -56 -> 71
    //   130: goto +35 -> 165
    //   133: aload_0
    //   134: ldc_w 464
    //   137: invokestatic 121	o/no:ˎ	(Landroid/os/Bundle;Ljava/lang/String;)Ljava/lang/String;
    //   140: astore_2
    //   141: aload_2
    //   142: invokestatic 127	android/text/TextUtils:isEmpty	(Ljava/lang/CharSequence;)Z
    //   145: ifeq +6 -> 151
    //   148: goto +68 -> 216
    //   151: aload_2
    //   152: astore_0
    //   153: goto +18 -> 171
    //   156: goto -69 -> 87
    //   159: goto -55 -> 104
    //   162: goto -123 -> 39
    //   165: bipush 29
    //   167: istore_1
    //   168: goto -158 -> 10
    //   171: aload_0
    //   172: invokestatic 127	android/text/TextUtils:isEmpty	(Ljava/lang/CharSequence;)Z
    //   175: ifne +6 -> 181
    //   178: goto -173 -> 5
    //   181: goto -99 -> 82
    //   184: getstatic 29	o/no:ˏॱ	I
    //   187: istore_1
    //   188: iload_1
    //   189: bipush 99
    //   191: iadd
    //   192: istore_1
    //   193: iload_1
    //   194: sipush 128
    //   197: irem
    //   198: putstatic 31	o/no:ˋॱ	I
    //   201: iload_1
    //   202: iconst_2
    //   203: irem
    //   204: ifne +6 -> 210
    //   207: goto -45 -> 162
    //   210: goto -171 -> 39
    //   213: astore_0
    //   214: aload_0
    //   215: athrow
    //   216: getstatic 31	o/no:ˋॱ	I
    //   219: bipush 41
    //   221: iadd
    //   222: istore_1
    //   223: iload_1
    //   224: sipush 128
    //   227: irem
    //   228: putstatic 29	o/no:ˏॱ	I
    //   231: iload_1
    //   232: iconst_2
    //   233: irem
    //   234: ifeq +6 -> 240
    //   237: goto -81 -> 156
    //   240: goto -153 -> 87
    // Local variable table:
    //   start	length	slot	name	signature
    //   0	243	0	paramBundle	Bundle
    //   6	228	1	i	int
    //   140	12	2	str	String
    // Exception table:
    //   from	to	target	type
    //   184	188	101	java/lang/Exception
    //   104	108	213	java/lang/Exception
    //   113	121	213	java/lang/Exception
    //   193	201	213	java/lang/Exception
  }
  
  static String ˏ(Bundle paramBundle, String paramString)
  {
    break label52;
    int i;
    switch (i)
    {
    default: 
      break;
    }
    for (;;)
    {
      break label314;
      label34:
      i = 70;
      break label75;
      i = 5 / 4;
      break label314;
      label47:
      i = 1;
      break;
      label52:
      break label170;
      label55:
      i = 0;
      break;
      try
      {
        paramString = paramString.concat(str);
        label75:
        do
        {
          break;
          do
          {
            i = 52;
            switch (i)
            {
            case 52: 
            default: 
              break label308;
              i = ˏॱ + 57;
              ˋॱ = i % 128;
            }
          } while (i % 2 == 0);
          break label34;
          paramString = new String(paramString);
          i = ˋॱ + 31;
          ˏॱ = i % 128;
        } while (i % 2 != 0);
        continue;
        label170:
        paramString = String.valueOf(paramString);
        String str = String.valueOf(ˋ(new char[] { -29683, -11616, -2243, 10545 }, '\000', new char[] { 30281, 18284, -5513, 14533, 24691, -16279, 16427, -23720 }, 0, new char[] { 0, 0, 0, 0 }).intern());
        if (str.length() != 0) {
          break label55;
        }
        break label47;
      }
      catch (Exception paramBundle)
      {
        label308:
        throw paramBundle;
      }
    }
    label314:
    paramBundle = ˎ(paramBundle, paramString);
    return paramBundle;
  }
  
  /* Error */
  @android.annotation.TargetApi(26)
  private final boolean ˏ(int paramInt)
  {
    // Byte code:
    //   0: goto +182 -> 182
    //   3: astore_3
    //   4: aload_3
    //   5: athrow
    //   6: iconst_1
    //   7: ireturn
    //   8: iconst_1
    //   9: istore_2
    //   10: goto +138 -> 148
    //   13: goto +177 -> 190
    //   16: iconst_0
    //   17: ireturn
    //   18: aload_0
    //   19: getfield 63	o/no:ˋ	Landroid/content/Context;
    //   22: invokevirtual 487	android/content/Context:getResources	()Landroid/content/res/Resources;
    //   25: iload_1
    //   26: aconst_null
    //   27: invokevirtual 493	android/content/res/Resources:getDrawable	(ILandroid/content/res/Resources$Theme;)Landroid/graphics/drawable/Drawable;
    //   30: astore_3
    //   31: aload_3
    //   32: instanceof 495
    //   35: ifeq +6 -> 41
    //   38: goto +38 -> 76
    //   41: goto -28 -> 13
    //   44: iload_2
    //   45: tableswitch	default:+23->68, 0:+133->178, 1:+-27->18
    //   68: goto +110 -> 178
    //   71: iconst_0
    //   72: istore_2
    //   73: goto -29 -> 44
    //   76: ldc 80
    //   78: new 242	java/lang/StringBuilder
    //   81: dup
    //   82: bipush 77
    //   84: invokespecial 243	java/lang/StringBuilder:<init>	(I)V
    //   87: ldc_w 497
    //   90: invokevirtual 249	java/lang/StringBuilder:append	(Ljava/lang/String;)Ljava/lang/StringBuilder;
    //   93: iload_1
    //   94: invokevirtual 500	java/lang/StringBuilder:append	(I)Ljava/lang/StringBuilder;
    //   97: invokevirtual 256	java/lang/StringBuilder:toString	()Ljava/lang/String;
    //   100: invokestatic 416	android/util/Log:e	(Ljava/lang/String;Ljava/lang/String;)I
    //   103: pop
    //   104: goto -88 -> 16
    //   107: getstatic 342	android/os/Build$VERSION:SDK_INT	I
    //   110: bipush 77
    //   112: if_icmpeq +6 -> 118
    //   115: goto -44 -> 71
    //   118: goto +67 -> 185
    //   121: getstatic 29	o/no:ˏॱ	I
    //   124: bipush 89
    //   126: iadd
    //   127: istore_2
    //   128: iload_2
    //   129: sipush 128
    //   132: irem
    //   133: putstatic 31	o/no:ˋॱ	I
    //   136: iload_2
    //   137: iconst_2
    //   138: irem
    //   139: ifne +6 -> 145
    //   142: goto -35 -> 107
    //   145: goto +77 -> 222
    //   148: iload_2
    //   149: tableswitch	default:+23->172, 0:+29->178, 1:+-131->18
    //   172: goto -154 -> 18
    //   175: goto -169 -> 6
    //   178: iconst_1
    //   179: ireturn
    //   180: iconst_0
    //   181: ireturn
    //   182: goto -61 -> 121
    //   185: iconst_1
    //   186: istore_2
    //   187: goto -143 -> 44
    //   190: getstatic 29	o/no:ˏॱ	I
    //   193: bipush 87
    //   195: iadd
    //   196: istore_1
    //   197: iload_1
    //   198: sipush 128
    //   201: irem
    //   202: putstatic 31	o/no:ˋॱ	I
    //   205: iload_1
    //   206: iconst_2
    //   207: irem
    //   208: ifne +6 -> 214
    //   211: goto -36 -> 175
    //   214: goto -208 -> 6
    //   217: iconst_0
    //   218: istore_2
    //   219: goto -71 -> 148
    //   222: getstatic 342	android/os/Build$VERSION:SDK_INT	I
    //   225: bipush 26
    //   227: if_icmpeq +6 -> 233
    //   230: goto -13 -> 217
    //   233: goto -225 -> 8
    //   236: astore_3
    //   237: goto -57 -> 180
    // Local variable table:
    //   start	length	slot	name	signature
    //   0	240	0	this	no
    //   0	240	1	paramInt	int
    //   9	210	2	i	int
    //   3	2	3	localException	Exception
    //   30	2	3	localDrawable	android.graphics.drawable.Drawable
    //   236	1	3	localNotFoundException	Resources.NotFoundException
    // Exception table:
    //   from	to	target	type
    //   190	197	3	java/lang/Exception
    //   197	205	3	java/lang/Exception
    //   18	31	236	android/content/res/Resources$NotFoundException
    //   76	104	236	android/content/res/Resources$NotFoundException
  }
  
  /* Error */
  private final String ॱ(Bundle paramBundle, String paramString)
  {
    // Byte code:
    //   0: goto +152 -> 152
    //   3: bipush 19
    //   5: istore_3
    //   6: goto +575 -> 581
    //   9: iconst_0
    //   10: istore_3
    //   11: goto +261 -> 272
    //   14: aload_2
    //   15: invokestatic 230	java/lang/String:valueOf	(Ljava/lang/Object;)Ljava/lang/String;
    //   18: astore_1
    //   19: iconst_4
    //   20: newarray char
    //   22: dup
    //   23: iconst_0
    //   24: ldc_w 465
    //   27: castore
    //   28: dup
    //   29: iconst_1
    //   30: ldc_w 466
    //   33: castore
    //   34: dup
    //   35: iconst_2
    //   36: ldc_w 467
    //   39: castore
    //   40: dup
    //   41: iconst_3
    //   42: ldc_w 468
    //   45: castore
    //   46: iconst_0
    //   47: bipush 8
    //   49: newarray char
    //   51: dup
    //   52: iconst_0
    //   53: ldc_w 469
    //   56: castore
    //   57: dup
    //   58: iconst_1
    //   59: ldc_w 470
    //   62: castore
    //   63: dup
    //   64: iconst_2
    //   65: ldc_w 471
    //   68: castore
    //   69: dup
    //   70: iconst_3
    //   71: ldc_w 472
    //   74: castore
    //   75: dup
    //   76: iconst_4
    //   77: ldc_w 473
    //   80: castore
    //   81: dup
    //   82: iconst_5
    //   83: ldc_w 474
    //   86: castore
    //   87: dup
    //   88: bipush 6
    //   90: ldc_w 475
    //   93: castore
    //   94: dup
    //   95: bipush 7
    //   97: ldc_w 476
    //   100: castore
    //   101: iconst_0
    //   102: iconst_4
    //   103: newarray char
    //   105: dup
    //   106: iconst_0
    //   107: ldc_w 477
    //   110: castore
    //   111: dup
    //   112: iconst_1
    //   113: ldc_w 477
    //   116: castore
    //   117: dup
    //   118: iconst_2
    //   119: ldc_w 477
    //   122: castore
    //   123: dup
    //   124: iconst_3
    //   125: ldc_w 477
    //   128: castore
    //   129: invokestatic 479	o/no:ˋ	([CC[CI[C)Ljava/lang/String;
    //   132: invokevirtual 482	java/lang/String:intern	()Ljava/lang/String;
    //   135: invokestatic 230	java/lang/String:valueOf	(Ljava/lang/Object;)Ljava/lang/String;
    //   138: astore_2
    //   139: aload_2
    //   140: invokevirtual 235	java/lang/String:length	()I
    //   143: ifeq +6 -> 149
    //   146: goto +502 -> 648
    //   149: goto +508 -> 657
    //   152: goto +182 -> 334
    //   155: getstatic 29	o/no:ˏॱ	I
    //   158: bipush 25
    //   160: iadd
    //   161: istore_3
    //   162: iload_3
    //   163: sipush 128
    //   166: irem
    //   167: putstatic 31	o/no:ˋॱ	I
    //   170: iload_3
    //   171: iconst_2
    //   172: irem
    //   173: ifne +6 -> 179
    //   176: goto +440 -> 616
    //   179: goto +266 -> 445
    //   182: aload_0
    //   183: aload_1
    //   184: iconst_4
    //   185: invokevirtual 240	java/lang/String:substring	(I)Ljava/lang/String;
    //   188: invokespecial 504	o/no:ˋ	(Ljava/lang/String;)Ljava/lang/String;
    //   191: invokevirtual 482	java/lang/String:intern	()Ljava/lang/String;
    //   194: astore_1
    //   195: aload_1
    //   196: areturn
    //   197: astore_2
    //   198: aload_1
    //   199: invokestatic 509	java/util/Arrays:toString	([Ljava/lang/Object;)Ljava/lang/String;
    //   202: astore_1
    //   203: aload 6
    //   205: invokestatic 230	java/lang/String:valueOf	(Ljava/lang/Object;)Ljava/lang/String;
    //   208: invokevirtual 235	java/lang/String:length	()I
    //   211: istore_3
    //   212: ldc 80
    //   214: new 242	java/lang/StringBuilder
    //   217: dup
    //   218: aload_1
    //   219: invokestatic 230	java/lang/String:valueOf	(Ljava/lang/Object;)Ljava/lang/String;
    //   222: invokevirtual 235	java/lang/String:length	()I
    //   225: iload_3
    //   226: bipush 58
    //   228: iadd
    //   229: iadd
    //   230: invokespecial 243	java/lang/StringBuilder:<init>	(I)V
    //   233: ldc_w 511
    //   236: invokevirtual 249	java/lang/StringBuilder:append	(Ljava/lang/String;)Ljava/lang/StringBuilder;
    //   239: aload 6
    //   241: invokevirtual 249	java/lang/StringBuilder:append	(Ljava/lang/String;)Ljava/lang/StringBuilder;
    //   244: ldc -5
    //   246: invokevirtual 249	java/lang/StringBuilder:append	(Ljava/lang/String;)Ljava/lang/StringBuilder;
    //   249: aload_1
    //   250: invokevirtual 249	java/lang/StringBuilder:append	(Ljava/lang/String;)Ljava/lang/StringBuilder;
    //   253: ldc_w 513
    //   256: invokevirtual 249	java/lang/StringBuilder:append	(Ljava/lang/String;)Ljava/lang/StringBuilder;
    //   259: invokevirtual 256	java/lang/StringBuilder:toString	()Ljava/lang/String;
    //   262: aload_2
    //   263: invokestatic 515	android/util/Log:w	(Ljava/lang/String;Ljava/lang/String;Ljava/lang/Throwable;)I
    //   266: pop
    //   267: aconst_null
    //   268: areturn
    //   269: goto +285 -> 554
    //   272: iload_3
    //   273: tableswitch	default:+23->296, 0:+87->360, 1:+54->327
    //   296: goto +31 -> 327
    //   299: astore_1
    //   300: aload_1
    //   301: athrow
    //   302: aload_1
    //   303: aload_2
    //   304: invokestatic 517	o/no:ˏ	(Landroid/os/Bundle;Ljava/lang/String;)Ljava/lang/String;
    //   307: astore 6
    //   309: aload 6
    //   311: invokestatic 127	android/text/TextUtils:isEmpty	(Ljava/lang/CharSequence;)Z
    //   314: istore 5
    //   316: iload 5
    //   318: ifeq +6 -> 324
    //   321: goto -52 -> 269
    //   324: goto +82 -> 406
    //   327: bipush 56
    //   329: iconst_0
    //   330: idiv
    //   331: istore_3
    //   332: aconst_null
    //   333: areturn
    //   334: aload_1
    //   335: aload_2
    //   336: invokestatic 121	o/no:ˎ	(Landroid/os/Bundle;Ljava/lang/String;)Ljava/lang/String;
    //   339: astore 6
    //   341: aload 6
    //   343: invokestatic 127	android/text/TextUtils:isEmpty	(Ljava/lang/CharSequence;)Z
    //   346: ifne +6 -> 352
    //   349: goto +43 -> 392
    //   352: goto -50 -> 302
    //   355: iconst_0
    //   356: istore_3
    //   357: goto +5 -> 362
    //   360: aconst_null
    //   361: areturn
    //   362: iload_3
    //   363: tableswitch	default:+21->384, 0:+32->395, 1:+-208->155
    //   384: goto -229 -> 155
    //   387: iconst_0
    //   388: istore_3
    //   389: goto +192 -> 581
    //   392: aload 6
    //   394: areturn
    //   395: aload 7
    //   397: iload 4
    //   399: aload_1
    //   400: invokevirtual 520	android/content/res/Resources:getString	(I[Ljava/lang/Object;)Ljava/lang/String;
    //   403: astore_2
    //   404: aload_2
    //   405: areturn
    //   406: aload_0
    //   407: getfield 63	o/no:ˋ	Landroid/content/Context;
    //   410: invokevirtual 487	android/content/Context:getResources	()Landroid/content/res/Resources;
    //   413: astore 7
    //   415: aload 7
    //   417: aload 6
    //   419: ldc_w 522
    //   422: aload_0
    //   423: getfield 63	o/no:ˋ	Landroid/content/Context;
    //   426: invokevirtual 143	android/content/Context:getPackageName	()Ljava/lang/String;
    //   429: invokevirtual 526	android/content/res/Resources:getIdentifier	(Ljava/lang/String;Ljava/lang/String;Ljava/lang/String;)I
    //   432: istore 4
    //   434: iload 4
    //   436: ifne +6 -> 442
    //   439: goto -436 -> 3
    //   442: goto -55 -> 387
    //   445: aload 7
    //   447: iload 4
    //   449: invokevirtual 528	android/content/res/Resources:getString	(I)Ljava/lang/String;
    //   452: astore_1
    //   453: aload_1
    //   454: ldc_w 530
    //   457: invokevirtual 72	java/lang/String:startsWith	(Ljava/lang/String;)Z
    //   460: ifeq +6 -> 466
    //   463: goto -281 -> 182
    //   466: aload_1
    //   467: areturn
    //   468: aload_1
    //   469: bipush 6
    //   471: invokevirtual 240	java/lang/String:substring	(I)Ljava/lang/String;
    //   474: astore_1
    //   475: aload_1
    //   476: invokestatic 230	java/lang/String:valueOf	(Ljava/lang/Object;)Ljava/lang/String;
    //   479: invokevirtual 235	java/lang/String:length	()I
    //   482: istore_3
    //   483: ldc 80
    //   485: new 242	java/lang/StringBuilder
    //   488: dup
    //   489: aload 6
    //   491: invokestatic 230	java/lang/String:valueOf	(Ljava/lang/Object;)Ljava/lang/String;
    //   494: invokevirtual 235	java/lang/String:length	()I
    //   497: iload_3
    //   498: bipush 49
    //   500: iadd
    //   501: iadd
    //   502: invokespecial 243	java/lang/StringBuilder:<init>	(I)V
    //   505: aload_1
    //   506: invokevirtual 249	java/lang/StringBuilder:append	(Ljava/lang/String;)Ljava/lang/StringBuilder;
    //   509: ldc_w 532
    //   512: invokevirtual 249	java/lang/StringBuilder:append	(Ljava/lang/String;)Ljava/lang/StringBuilder;
    //   515: aload 6
    //   517: invokevirtual 249	java/lang/StringBuilder:append	(Ljava/lang/String;)Ljava/lang/StringBuilder;
    //   520: ldc_w 513
    //   523: invokevirtual 249	java/lang/StringBuilder:append	(Ljava/lang/String;)Ljava/lang/StringBuilder;
    //   526: invokevirtual 256	java/lang/StringBuilder:toString	()Ljava/lang/String;
    //   529: invokestatic 88	android/util/Log:w	(Ljava/lang/String;Ljava/lang/String;)I
    //   532: pop
    //   533: aconst_null
    //   534: areturn
    //   535: astore_1
    //   536: aload_1
    //   537: athrow
    //   538: aload_1
    //   539: aload_2
    //   540: invokestatic 534	o/no:ˊ	(Landroid/os/Bundle;Ljava/lang/String;)[Ljava/lang/Object;
    //   543: astore_1
    //   544: aload_1
    //   545: ifnonnull +6 -> 551
    //   548: goto +63 -> 611
    //   551: goto -196 -> 355
    //   554: getstatic 29	o/no:ˏॱ	I
    //   557: bipush 45
    //   559: iadd
    //   560: istore_3
    //   561: iload_3
    //   562: sipush 128
    //   565: irem
    //   566: putstatic 31	o/no:ˋॱ	I
    //   569: iload_3
    //   570: iconst_2
    //   571: irem
    //   572: ifne +6 -> 578
    //   575: goto +94 -> 669
    //   578: goto -569 -> 9
    //   581: iload_3
    //   582: lookupswitch	default:+26->608, 0:+-44->538, 19:+-568->14
    //   608: goto -594 -> 14
    //   611: iconst_1
    //   612: istore_3
    //   613: goto -251 -> 362
    //   616: aload 7
    //   618: iload 4
    //   620: invokevirtual 528	android/content/res/Resources:getString	(I)Ljava/lang/String;
    //   623: astore_1
    //   624: aload_1
    //   625: ldc_w 530
    //   628: invokevirtual 72	java/lang/String:startsWith	(Ljava/lang/String;)Z
    //   631: istore 5
    //   633: bipush 45
    //   635: iconst_0
    //   636: idiv
    //   637: istore_3
    //   638: iload 5
    //   640: ifeq +6 -> 646
    //   643: goto -461 -> 182
    //   646: aload_1
    //   647: areturn
    //   648: aload_1
    //   649: aload_2
    //   650: invokevirtual 226	java/lang/String:concat	(Ljava/lang/String;)Ljava/lang/String;
    //   653: astore_1
    //   654: goto -186 -> 468
    //   657: new 68	java/lang/String
    //   660: dup
    //   661: aload_1
    //   662: invokespecial 236	java/lang/String:<init>	(Ljava/lang/String;)V
    //   665: astore_1
    //   666: goto -198 -> 468
    //   669: iconst_1
    //   670: istore_3
    //   671: goto -399 -> 272
    // Local variable table:
    //   start	length	slot	name	signature
    //   0	674	0	this	no
    //   0	674	1	paramBundle	Bundle
    //   0	674	2	paramString	String
    //   5	666	3	i	int
    //   397	222	4	j	int
    //   314	325	5	bool	boolean
    //   203	313	6	localObject	Object
    //   395	222	7	localResources	Resources
    // Exception table:
    //   from	to	target	type
    //   395	404	197	java/util/MissingFormatArgumentException
    //   309	316	299	java/lang/Exception
    //   538	544	299	java/lang/Exception
    //   182	195	535	java/lang/Exception
    //   302	309	535	java/lang/Exception
  }
  
  /* Error */
  @android.annotation.TargetApi(26)
  private final String ॱ(String paramString)
  {
    // Byte code:
    //   0: goto +451 -> 451
    //   3: astore_1
    //   4: ldc 80
    //   6: ldc_w 386
    //   9: aload_1
    //   10: invokestatic 390	android/util/Log:e	(Ljava/lang/String;Ljava/lang/String;Ljava/lang/Throwable;)I
    //   13: pop
    //   14: goto +313 -> 327
    //   17: bipush 25
    //   19: istore_2
    //   20: goto +794 -> 814
    //   23: getstatic 29	o/no:ˏॱ	I
    //   26: bipush 67
    //   28: iadd
    //   29: istore_2
    //   30: iload_2
    //   31: sipush 128
    //   34: irem
    //   35: putstatic 31	o/no:ˋॱ	I
    //   38: iload_2
    //   39: iconst_2
    //   40: irem
    //   41: ifne +6 -> 47
    //   44: goto +438 -> 482
    //   47: goto +168 -> 215
    //   50: aload_0
    //   51: getfield 542	o/no:ॱ	Ljava/lang/reflect/Method;
    //   54: aload 4
    //   56: iconst_1
    //   57: anewarray 4	java/lang/Object
    //   60: dup
    //   61: iconst_0
    //   62: aload 5
    //   64: aastore
    //   65: invokevirtual 422	java/lang/reflect/Method:invoke	(Ljava/lang/Object;[Ljava/lang/Object;)Ljava/lang/Object;
    //   68: astore_1
    //   69: aload_1
    //   70: ifnull +6 -> 76
    //   73: goto +308 -> 381
    //   76: goto +732 -> 808
    //   79: getstatic 29	o/no:ˏॱ	I
    //   82: bipush 93
    //   84: iadd
    //   85: istore_2
    //   86: iload_2
    //   87: sipush 128
    //   90: irem
    //   91: putstatic 31	o/no:ˋॱ	I
    //   94: iload_2
    //   95: iconst_2
    //   96: irem
    //   97: ifne +6 -> 103
    //   100: goto +379 -> 479
    //   103: aload 5
    //   105: areturn
    //   106: getstatic 31	o/no:ˋॱ	I
    //   109: iconst_1
    //   110: iadd
    //   111: istore_2
    //   112: iload_2
    //   113: sipush 128
    //   116: irem
    //   117: putstatic 29	o/no:ˏॱ	I
    //   120: iload_2
    //   121: iconst_2
    //   122: irem
    //   123: ifeq +6 -> 129
    //   126: goto +217 -> 343
    //   129: goto +146 -> 275
    //   132: bipush 22
    //   134: istore_2
    //   135: goto +17 -> 152
    //   138: astore_1
    //   139: ldc 80
    //   141: ldc_w 386
    //   144: aload_1
    //   145: invokestatic 390	android/util/Log:e	(Ljava/lang/String;Ljava/lang/String;Ljava/lang/Throwable;)I
    //   148: pop
    //   149: goto +178 -> 327
    //   152: iload_2
    //   153: lookupswitch	default:+27->180, 12:+-103->50, 22:+425->578
    //   180: goto +398 -> 578
    //   183: aconst_null
    //   184: areturn
    //   185: aload_0
    //   186: getfield 542	o/no:ॱ	Ljava/lang/reflect/Method;
    //   189: aload 4
    //   191: iconst_1
    //   192: anewarray 4	java/lang/Object
    //   195: dup
    //   196: iconst_0
    //   197: ldc_w 544
    //   200: aastore
    //   201: invokevirtual 422	java/lang/reflect/Method:invoke	(Ljava/lang/Object;[Ljava/lang/Object;)Ljava/lang/Object;
    //   204: astore_1
    //   205: aload_1
    //   206: ifnonnull +6 -> 212
    //   209: goto +534 -> 743
    //   212: goto +75 -> 287
    //   215: aload_0
    //   216: aload_1
    //   217: iconst_4
    //   218: invokevirtual 240	java/lang/String:substring	(I)Ljava/lang/String;
    //   221: invokespecial 504	o/no:ˋ	(Ljava/lang/String;)Ljava/lang/String;
    //   224: invokevirtual 482	java/lang/String:intern	()Ljava/lang/String;
    //   227: astore_1
    //   228: goto +159 -> 387
    //   231: aload_1
    //   232: invokestatic 127	android/text/TextUtils:isEmpty	(Ljava/lang/CharSequence;)Z
    //   235: istore_3
    //   236: iload_3
    //   237: ifne +6 -> 243
    //   240: goto +135 -> 375
    //   243: goto +347 -> 590
    //   246: iload_2
    //   247: lookupswitch	default:+25->272, 17:+50->297, 18:+243->490
    //   272: goto +218 -> 490
    //   275: invokestatic 548	o/fP:ʻ	()Z
    //   278: ifne +6 -> 284
    //   281: goto +204 -> 485
    //   284: goto +440 -> 724
    //   287: ldc_w 544
    //   290: areturn
    //   291: bipush 12
    //   293: istore_2
    //   294: goto -142 -> 152
    //   297: aload_0
    //   298: getfield 542	o/no:ॱ	Ljava/lang/reflect/Method;
    //   301: aload 4
    //   303: iconst_1
    //   304: anewarray 4	java/lang/Object
    //   307: dup
    //   308: iconst_0
    //   309: aload_1
    //   310: aastore
    //   311: invokevirtual 422	java/lang/reflect/Method:invoke	(Ljava/lang/Object;[Ljava/lang/Object;)Ljava/lang/Object;
    //   314: astore 5
    //   316: aload 5
    //   318: ifnull +6 -> 324
    //   321: goto +133 -> 454
    //   324: goto +194 -> 518
    //   327: aconst_null
    //   328: areturn
    //   329: astore_1
    //   330: ldc 80
    //   332: ldc_w 386
    //   335: aload_1
    //   336: invokestatic 390	android/util/Log:e	(Ljava/lang/String;Ljava/lang/String;Ljava/lang/Throwable;)I
    //   339: pop
    //   340: goto -13 -> 327
    //   343: goto -68 -> 275
    //   346: iload_2
    //   347: lookupswitch	default:+25->372, 73:+-268->79, 80:+216->563
    //   372: goto +191 -> 563
    //   375: bipush 17
    //   377: istore_2
    //   378: goto -132 -> 246
    //   381: bipush 73
    //   383: istore_2
    //   384: goto -38 -> 346
    //   387: aload 6
    //   389: iconst_3
    //   390: anewarray 4	java/lang/Object
    //   393: dup
    //   394: iconst_0
    //   395: ldc_w 544
    //   398: aastore
    //   399: dup
    //   400: iconst_1
    //   401: aload_1
    //   402: aastore
    //   403: dup
    //   404: iconst_2
    //   405: iconst_3
    //   406: invokestatic 329	java/lang/Integer:valueOf	(I)Ljava/lang/Integer;
    //   409: aastore
    //   410: invokevirtual 554	java/lang/reflect/Constructor:newInstance	([Ljava/lang/Object;)Ljava/lang/Object;
    //   413: astore_1
    //   414: aload 4
    //   416: invokevirtual 558	java/lang/Object:getClass	()Ljava/lang/Class;
    //   419: ldc_w 560
    //   422: iconst_1
    //   423: anewarray 214	java/lang/Class
    //   426: dup
    //   427: iconst_0
    //   428: aload 5
    //   430: aastore
    //   431: invokevirtual 218	java/lang/Class:getMethod	(Ljava/lang/String;[Ljava/lang/Class;)Ljava/lang/reflect/Method;
    //   434: aload 4
    //   436: iconst_1
    //   437: anewarray 4	java/lang/Object
    //   440: dup
    //   441: iconst_0
    //   442: aload_1
    //   443: aastore
    //   444: invokevirtual 422	java/lang/reflect/Method:invoke	(Ljava/lang/Object;[Ljava/lang/Object;)Ljava/lang/Object;
    //   447: pop
    //   448: goto -161 -> 287
    //   451: goto -345 -> 106
    //   454: getstatic 29	o/no:ˏॱ	I
    //   457: bipush 19
    //   459: iadd
    //   460: istore_2
    //   461: iload_2
    //   462: sipush 128
    //   465: irem
    //   466: putstatic 31	o/no:ˋॱ	I
    //   469: iload_2
    //   470: iconst_2
    //   471: irem
    //   472: ifne +5 -> 477
    //   475: aload_1
    //   476: areturn
    //   477: aload_1
    //   478: areturn
    //   479: aload 5
    //   481: areturn
    //   482: goto -267 -> 215
    //   485: iconst_1
    //   486: istore_2
    //   487: goto +137 -> 624
    //   490: aload_0
    //   491: invokespecial 331	o/no:ˊ	()Landroid/os/Bundle;
    //   494: ldc_w 562
    //   497: invokevirtual 365	android/os/Bundle:getString	(Ljava/lang/String;)Ljava/lang/String;
    //   500: astore 5
    //   502: aload 5
    //   504: invokestatic 127	android/text/TextUtils:isEmpty	(Ljava/lang/CharSequence;)Z
    //   507: istore_3
    //   508: iload_3
    //   509: ifne +6 -> 515
    //   512: goto -221 -> 291
    //   515: goto -383 -> 132
    //   518: ldc 80
    //   520: new 242	java/lang/StringBuilder
    //   523: dup
    //   524: aload_1
    //   525: invokestatic 230	java/lang/String:valueOf	(Ljava/lang/Object;)Ljava/lang/String;
    //   528: invokevirtual 235	java/lang/String:length	()I
    //   531: bipush 122
    //   533: iadd
    //   534: invokespecial 243	java/lang/StringBuilder:<init>	(I)V
    //   537: ldc_w 564
    //   540: invokevirtual 249	java/lang/StringBuilder:append	(Ljava/lang/String;)Ljava/lang/StringBuilder;
    //   543: aload_1
    //   544: invokevirtual 249	java/lang/StringBuilder:append	(Ljava/lang/String;)Ljava/lang/StringBuilder;
    //   547: ldc_w 566
    //   550: invokevirtual 249	java/lang/StringBuilder:append	(Ljava/lang/String;)Ljava/lang/StringBuilder;
    //   553: invokevirtual 256	java/lang/StringBuilder:toString	()Ljava/lang/String;
    //   556: invokestatic 88	android/util/Log:w	(Ljava/lang/String;Ljava/lang/String;)I
    //   559: pop
    //   560: goto -70 -> 490
    //   563: ldc 80
    //   565: ldc_w 568
    //   568: invokestatic 88	android/util/Log:w	(Ljava/lang/String;Ljava/lang/String;)I
    //   571: pop
    //   572: goto -387 -> 185
    //   575: goto -392 -> 183
    //   578: ldc 80
    //   580: ldc_w 570
    //   583: invokestatic 88	android/util/Log:w	(Ljava/lang/String;Ljava/lang/String;)I
    //   586: pop
    //   587: goto -402 -> 185
    //   590: bipush 18
    //   592: istore_2
    //   593: goto -347 -> 246
    //   596: astore_1
    //   597: ldc 80
    //   599: ldc_w 386
    //   602: aload_1
    //   603: invokestatic 390	android/util/Log:e	(Ljava/lang/String;Ljava/lang/String;Ljava/lang/Throwable;)I
    //   606: pop
    //   607: goto -280 -> 327
    //   610: astore_1
    //   611: ldc 80
    //   613: ldc_w 386
    //   616: aload_1
    //   617: invokestatic 390	android/util/Log:e	(Ljava/lang/String;Ljava/lang/String;Ljava/lang/Throwable;)I
    //   620: pop
    //   621: goto -294 -> 327
    //   624: iload_2
    //   625: tableswitch	default:+23->648, 0:+67->692, 1:+-50->575
    //   648: goto +44 -> 692
    //   651: aload_0
    //   652: aload 4
    //   654: invokevirtual 558	java/lang/Object:getClass	()Ljava/lang/Class;
    //   657: ldc_w 572
    //   660: iconst_1
    //   661: anewarray 214	java/lang/Class
    //   664: dup
    //   665: iconst_0
    //   666: ldc 68
    //   668: aastore
    //   669: invokevirtual 218	java/lang/Class:getMethod	(Ljava/lang/String;[Ljava/lang/Class;)Ljava/lang/reflect/Method;
    //   672: putfield 542	o/no:ॱ	Ljava/lang/reflect/Method;
    //   675: goto -444 -> 231
    //   678: astore_1
    //   679: ldc 80
    //   681: ldc_w 386
    //   684: aload_1
    //   685: invokestatic 390	android/util/Log:e	(Ljava/lang/String;Ljava/lang/String;Ljava/lang/Throwable;)I
    //   688: pop
    //   689: goto -362 -> 327
    //   692: aload_0
    //   693: getfield 63	o/no:ˋ	Landroid/content/Context;
    //   696: ldc_w 574
    //   699: invokevirtual 578	android/content/Context:getSystemService	(Ljava/lang/Class;)Ljava/lang/Object;
    //   702: checkcast 574	android/app/NotificationManager
    //   705: astore 4
    //   707: aload_0
    //   708: getfield 542	o/no:ॱ	Ljava/lang/reflect/Method;
    //   711: astore 5
    //   713: aload 5
    //   715: ifnonnull +6 -> 721
    //   718: goto +139 -> 857
    //   721: goto -704 -> 17
    //   724: iconst_0
    //   725: istore_2
    //   726: goto -102 -> 624
    //   729: astore_1
    //   730: ldc 80
    //   732: ldc_w 386
    //   735: aload_1
    //   736: invokestatic 390	android/util/Log:e	(Ljava/lang/String;Ljava/lang/String;Ljava/lang/Throwable;)I
    //   739: pop
    //   740: goto -413 -> 327
    //   743: ldc_w 580
    //   746: invokestatic 584	java/lang/Class:forName	(Ljava/lang/String;)Ljava/lang/Class;
    //   749: astore 5
    //   751: aload 5
    //   753: iconst_3
    //   754: anewarray 214	java/lang/Class
    //   757: dup
    //   758: iconst_0
    //   759: ldc 68
    //   761: aastore
    //   762: dup
    //   763: iconst_1
    //   764: ldc_w 586
    //   767: aastore
    //   768: dup
    //   769: iconst_2
    //   770: getstatic 590	java/lang/Integer:TYPE	Ljava/lang/Class;
    //   773: aastore
    //   774: invokevirtual 594	java/lang/Class:getConstructor	([Ljava/lang/Class;)Ljava/lang/reflect/Constructor;
    //   777: astore 6
    //   779: aload_0
    //   780: getfield 63	o/no:ˋ	Landroid/content/Context;
    //   783: getstatic 599	o/bf$iF:fcm_fallback_notification_channel_label	I
    //   786: invokevirtual 600	android/content/Context:getString	(I)Ljava/lang/String;
    //   789: astore_1
    //   790: aload_1
    //   791: ldc_w 530
    //   794: invokevirtual 72	java/lang/String:startsWith	(Ljava/lang/String;)Z
    //   797: istore_3
    //   798: iload_3
    //   799: ifeq +6 -> 805
    //   802: goto -779 -> 23
    //   805: goto -418 -> 387
    //   808: bipush 80
    //   810: istore_2
    //   811: goto -465 -> 346
    //   814: iload_2
    //   815: lookupswitch	default:+25->840, 25:+-584->231, 60:+-164->651
    //   840: goto -609 -> 231
    //   843: astore_1
    //   844: ldc 80
    //   846: ldc_w 386
    //   849: aload_1
    //   850: invokestatic 390	android/util/Log:e	(Ljava/lang/String;Ljava/lang/String;Ljava/lang/Throwable;)I
    //   853: pop
    //   854: goto -527 -> 327
    //   857: bipush 60
    //   859: istore_2
    //   860: goto -46 -> 814
    // Local variable table:
    //   start	length	slot	name	signature
    //   0	863	0	this	no
    //   0	863	1	paramString	String
    //   19	841	2	i	int
    //   235	564	3	bool	boolean
    //   54	652	4	localObject1	Object
    //   62	690	5	localObject2	Object
    //   387	391	6	localConstructor	java.lang.reflect.Constructor
    // Exception table:
    //   from	to	target	type
    //   50	69	3	java/lang/IllegalAccessException
    //   185	205	3	java/lang/IllegalAccessException
    //   215	228	3	java/lang/IllegalAccessException
    //   231	236	3	java/lang/IllegalAccessException
    //   297	316	3	java/lang/IllegalAccessException
    //   387	448	3	java/lang/IllegalAccessException
    //   490	508	3	java/lang/IllegalAccessException
    //   518	560	3	java/lang/IllegalAccessException
    //   563	572	3	java/lang/IllegalAccessException
    //   578	587	3	java/lang/IllegalAccessException
    //   651	675	3	java/lang/IllegalAccessException
    //   707	713	3	java/lang/IllegalAccessException
    //   743	798	3	java/lang/IllegalAccessException
    //   50	69	138	java/lang/reflect/InvocationTargetException
    //   185	205	138	java/lang/reflect/InvocationTargetException
    //   215	228	138	java/lang/reflect/InvocationTargetException
    //   231	236	138	java/lang/reflect/InvocationTargetException
    //   297	316	138	java/lang/reflect/InvocationTargetException
    //   387	448	138	java/lang/reflect/InvocationTargetException
    //   490	508	138	java/lang/reflect/InvocationTargetException
    //   518	560	138	java/lang/reflect/InvocationTargetException
    //   563	572	138	java/lang/reflect/InvocationTargetException
    //   578	587	138	java/lang/reflect/InvocationTargetException
    //   651	675	138	java/lang/reflect/InvocationTargetException
    //   707	713	138	java/lang/reflect/InvocationTargetException
    //   743	798	138	java/lang/reflect/InvocationTargetException
    //   50	69	329	java/lang/SecurityException
    //   185	205	329	java/lang/SecurityException
    //   215	228	329	java/lang/SecurityException
    //   231	236	329	java/lang/SecurityException
    //   297	316	329	java/lang/SecurityException
    //   387	448	329	java/lang/SecurityException
    //   490	508	329	java/lang/SecurityException
    //   518	560	329	java/lang/SecurityException
    //   563	572	329	java/lang/SecurityException
    //   578	587	329	java/lang/SecurityException
    //   651	675	329	java/lang/SecurityException
    //   707	713	329	java/lang/SecurityException
    //   743	798	329	java/lang/SecurityException
    //   50	69	596	java/lang/LinkageError
    //   185	205	596	java/lang/LinkageError
    //   215	228	596	java/lang/LinkageError
    //   231	236	596	java/lang/LinkageError
    //   297	316	596	java/lang/LinkageError
    //   387	448	596	java/lang/LinkageError
    //   490	508	596	java/lang/LinkageError
    //   518	560	596	java/lang/LinkageError
    //   563	572	596	java/lang/LinkageError
    //   578	587	596	java/lang/LinkageError
    //   651	675	596	java/lang/LinkageError
    //   707	713	596	java/lang/LinkageError
    //   743	798	596	java/lang/LinkageError
    //   50	69	610	java/lang/ClassNotFoundException
    //   185	205	610	java/lang/ClassNotFoundException
    //   215	228	610	java/lang/ClassNotFoundException
    //   231	236	610	java/lang/ClassNotFoundException
    //   297	316	610	java/lang/ClassNotFoundException
    //   387	448	610	java/lang/ClassNotFoundException
    //   490	508	610	java/lang/ClassNotFoundException
    //   518	560	610	java/lang/ClassNotFoundException
    //   563	572	610	java/lang/ClassNotFoundException
    //   578	587	610	java/lang/ClassNotFoundException
    //   651	675	610	java/lang/ClassNotFoundException
    //   707	713	610	java/lang/ClassNotFoundException
    //   743	798	610	java/lang/ClassNotFoundException
    //   50	69	678	java/lang/NoSuchMethodException
    //   185	205	678	java/lang/NoSuchMethodException
    //   215	228	678	java/lang/NoSuchMethodException
    //   231	236	678	java/lang/NoSuchMethodException
    //   297	316	678	java/lang/NoSuchMethodException
    //   387	448	678	java/lang/NoSuchMethodException
    //   490	508	678	java/lang/NoSuchMethodException
    //   518	560	678	java/lang/NoSuchMethodException
    //   563	572	678	java/lang/NoSuchMethodException
    //   578	587	678	java/lang/NoSuchMethodException
    //   651	675	678	java/lang/NoSuchMethodException
    //   707	713	678	java/lang/NoSuchMethodException
    //   743	798	678	java/lang/NoSuchMethodException
    //   50	69	729	java/lang/InstantiationException
    //   185	205	729	java/lang/InstantiationException
    //   215	228	729	java/lang/InstantiationException
    //   231	236	729	java/lang/InstantiationException
    //   297	316	729	java/lang/InstantiationException
    //   387	448	729	java/lang/InstantiationException
    //   490	508	729	java/lang/InstantiationException
    //   518	560	729	java/lang/InstantiationException
    //   563	572	729	java/lang/InstantiationException
    //   578	587	729	java/lang/InstantiationException
    //   651	675	729	java/lang/InstantiationException
    //   707	713	729	java/lang/InstantiationException
    //   743	798	729	java/lang/InstantiationException
    //   50	69	843	java/lang/IllegalArgumentException
    //   185	205	843	java/lang/IllegalArgumentException
    //   215	228	843	java/lang/IllegalArgumentException
    //   231	236	843	java/lang/IllegalArgumentException
    //   297	316	843	java/lang/IllegalArgumentException
    //   387	448	843	java/lang/IllegalArgumentException
    //   490	508	843	java/lang/IllegalArgumentException
    //   518	560	843	java/lang/IllegalArgumentException
    //   563	572	843	java/lang/IllegalArgumentException
    //   578	587	843	java/lang/IllegalArgumentException
    //   651	675	843	java/lang/IllegalArgumentException
    //   707	713	843	java/lang/IllegalArgumentException
    //   743	798	843	java/lang/IllegalArgumentException
  }
  
  static void ॱ()
  {
    ॱॱ = '\000';
    ᐝ = 0L;
    ʼ = 553721207;
  }
  
  public final boolean ॱ(Bundle paramBundle)
  {
    break label1620;
    int i;
    label31:
    label41:
    label47:
    label50:
    label60:
    label63:
    String str;
    Object localObject3;
    label96:
    Object localObject4;
    label190:
    label197:
    Object localObject1;
    label222:
    label241:
    label253:
    label258:
    int j;
    label264:
    label267:
    Object localObject2;
    label289:
    label298:
    label347:
    label371:
    label388:
    label455:
    label487:
    label493:
    label530:
    label546:
    label549:
    label576:
    label599:
    ʰ.ˋ localˋ;
    label648:
    label663:
    label695:
    label719:
    label730:
    label736:
    label741:
    label890:
    label905:
    Integer localInteger;
    switch (i)
    {
    default: 
      break label1894;
      i = 0;
      break label1650;
      i = 1;
      break;
      i = null.length;
      break label736;
      break label1606;
      for (;;)
      {
        if (i != 0) {
          break label1545;
        }
        break label190;
        break label1134;
        for (;;)
        {
          str = ॱ(paramBundle, "gcm.n.body");
          localObject3 = ˎ(paramBundle, "gcm.n.icon");
          if (!TextUtils.isEmpty((CharSequence)localObject3)) {
            break label298;
          }
          try
          {
            localObject4 = new Intent("com.google.firebase.messaging.NOTIFICATION_OPEN");
            ˎ((Intent)localObject4, paramBundle);
            try
            {
              ((Intent)localObject4).putExtra("pending_intent", (Parcelable)localObject3);
              localObject3 = this.ˋ;
              localObject3 = nk.ˊ((Context)localObject3, this.ʽ.incrementAndGet(), (Intent)localObject4, 1073741824);
              localObject4 = new Intent("com.google.firebase.messaging.NOTIFICATION_DISMISS");
              ˎ((Intent)localObject4, paramBundle);
              localObject4 = nk.ˊ(this.ˋ, this.ʽ.incrementAndGet(), (Intent)localObject4, 1073741824);
            }
            catch (Exception paramBundle)
            {
              throw paramBundle;
            }
            i = 17301651;
          }
          catch (Exception paramBundle)
          {
            throw paramBundle;
          }
          if (!ˏ(i)) {
            break label599;
          }
          break label50;
          if (localObject1 != null) {
            break label1017;
          }
          break label1855;
          ˏ(i);
          throw new NullPointerException();
          i = 1;
          break label1406;
          if (!fP.ʼ()) {
            break label289;
          }
          break label936;
          i = 0;
          break;
          j = 12;
          break label1825;
          break label1134;
          localObject2 = this.ˋ.getApplicationInfo().loadLabel(this.ˋ.getPackageManager());
        }
        SystemClock.sleep(10L);
        break label936;
        localObject1 = this.ˋ.getResources();
        j = ((Resources)localObject1).getIdentifier((String)localObject3, "drawable", this.ˋ.getPackageName());
        if (j == 0) {
          break label1866;
        }
        do
        {
          Log.d("FirebaseMessaging", "Showing notification");
          break label1416;
          paramBundle = (ActivityManager.RunningAppProcessInfo)((Iterator)localObject1).next();
          i = paramBundle.pid;
          throw new NullPointerException();
          if ("default".equals(localObject1))
          {
            break label1681;
            for (;;)
            {
              switch (i)
              {
              default: 
                break label648;
                localObject2 = localObject1;
                switch (i)
                {
                case 0: 
                default: 
                  localObject2 = localObject1;
                  break label63;
                  j = 1;
                  break label1225;
                  i = ˏॱ + 43;
                  ˋॱ = i % 128;
                  if (i % 2 == 0) {
                    break label47;
                  }
                  break label1606;
                  i = 69;
                }
                break;
              }
            }
            i = 51;
            break label663;
          }
          if (this.ˋ.getResources().getIdentifier((String)localObject1, "raw", this.ˋ.getPackageName()) != 0) {
            break label1921;
          }
          break label1681;
          if (((Iterator)localObject1).hasNext()) {
            break;
          }
          break label1501;
          break label267;
          j = ˋॱ + 31;
          ˏॱ = j % 128;
          if (j % 2 != 0) {
            break label222;
          }
          break label1338;
          paramBundle = ˎ(paramBundle, "gcm.n.tag");
        } while (Log.isLoggable("FirebaseMessaging", 3));
        break label1416;
        i = this.ˋ.getApplicationInfo().icon;
      }
      for (;;)
      {
        localˋ = new ʰ.ˋ(this.ˋ).ॱ(true).ˊ(i);
        if (!TextUtils.isEmpty((CharSequence)localObject2)) {
          break label1675;
        }
        break label1731;
        localObject1 = ((List)localObject1).iterator();
        i = null.length;
        break label1603;
        switch (i)
        {
        default: 
          break label1444;
          j = ˊ().getInt("com.google.firebase.messaging.default_notification_icon", 0);
          i = j;
          if (j != 0) {
            break label197;
          }
          break label599;
          localˋ.ˏ((PendingIntent)localObject4);
          break label1097;
          i = 84;
          break label1189;
          i = j;
          break label1134;
          if (!((KeyguardManager)this.ˋ.getSystemService(ˋ(new char[] { -31291, -11861, 10014, -23499 }, '\000', new char[] { -16558, 23123, -20611, 7017, -11931, 21182, 32297, 19990 }, 0, new char[] { 0, 0, 0, 0 }).intern())).inKeyguardRestrictedInputMode()) {
            break label1303;
          }
          break label1695;
          for (;;)
          {
            localˋ.ॱ((PendingIntent)localObject3);
            break label1089;
            break label1187;
            localObject1 = ((List)localObject1).iterator();
            break label1603;
            localˋ.ˏ(localInteger.intValue());
            break;
            label919:
            fP.ʼ();
            throw new NullPointerException();
            label931:
            i = 1;
            break label1650;
            label936:
            j = Process.myPid();
            localObject1 = ((ActivityManager)this.ˋ.getSystemService("activity")).getRunningAppProcesses();
            if (localObject1 != null) {
              break label493;
            }
            break label1509;
            label969:
            i = ˏॱ + 111;
            ˋॱ = i % 128;
            if (i % 2 == 0) {
              break label347;
            }
            break label1774;
            label996:
            if (this.ˋ.getApplicationInfo().targetSdkVersion > 25) {
              break label455;
            }
            break label1330;
            label1017:
            localˋ.ˋ((Uri)localObject1);
            break label1855;
            label1028:
            Log.w("FirebaseMessaging", String.valueOf(localObject3).length() + 61 + "Icon resource " + (String)localObject3 + " not found. Notification will use default icon.");
            break label695;
            label1075:
            if (!TextUtils.isEmpty(str)) {
              break label1251;
            }
            break label1592;
            label1089:
            if (localObject4 == null)
            {
              label1097:
              localObject1 = localˋ.ˏ();
              break label576;
            }
            i = ˋॱ + 65;
            ˏॱ = i % 128;
            if (i % 2 != 0) {
              break label1542;
            }
            break label719;
            label1134:
            localInteger = ˎ(ˎ(paramBundle, "gcm.n.color"));
            localObject1 = ˎ(paramBundle);
            if (TextUtils.isEmpty((CharSequence)localObject1)) {
              break label1219;
            }
            break label371;
            label1167:
            if (fP.ʻ()) {
              break label258;
            }
            break label1471;
            label1179:
            i = 5;
            break label1189;
            label1187:
            return true;
            label1189:
            switch (i)
            {
            }
          }
          label1219:
          localObject1 = null;
          break label1280;
          label1225:
          switch (j)
          {
          }
          break;
        }
      }
      label1251:
      localˋ.ॱ(str);
      localˋ.ॱ(new ʰ.If().ˎ(str));
      break;
    }
    for (;;)
    {
      label1280:
      localObject3 = ˊ(paramBundle);
      localObject4 = null;
      if (FirebaseMessagingService.ˊ(paramBundle)) {
        break label96;
      }
      break label1167;
      label1303:
      i = ˋॱ + 47;
      ˏॱ = i % 128;
      if (i % 2 != 0) {
        break label919;
      }
      break label241;
      label1330:
      j = 0;
      break label1225;
      label1335:
      break label530;
      label1338:
      if (ˏ(i)) {
        break label264;
      }
      break label1028;
      for (;;)
      {
        switch (i)
        {
        case 1: 
        default: 
          break label969;
          for (;;)
          {
            i = 0;
            break label1406;
            localˋ.ˋ((CharSequence)localObject2);
            break label1075;
            for (;;)
            {
              label1395:
              ((NotificationManager)localObject2).notify(paramBundle, 0, (Notification)localObject1);
              return true;
              label1406:
              if (i != 0) {
                break;
              }
              break label1801;
              label1416:
              localObject2 = (NotificationManager)this.ˋ.getSystemService("notification");
              if (TextUtils.isEmpty(paramBundle)) {
                break label1742;
              }
            }
            label1444:
            i = ˋॱ + 71;
            ˏॱ = i % 128;
            if (i % 2 == 0)
            {
              break label487;
              label1471:
              j = 90;
              break label1825;
              return false;
            }
            i = 52;
            break label388;
            label1485:
            if (((ActivityManager.RunningAppProcessInfo)localObject2).importance == 100) {
              break;
            }
          }
          label1501:
          i = 0;
        }
      }
      for (;;)
      {
        break label736;
        label1509:
        i = 30;
        break label663;
        label1542:
        label1545:
        label1592:
        label1603:
        label1606:
        label1620:
        for (;;)
        {
          if ("1".equals(ˎ(paramBundle, "gcm.n.noui"))) {
            break label890;
          }
          break label741;
          for (;;)
          {
            i = 1;
            break;
            break label719;
            if (!ˏ(i)) {
              break label190;
            }
            break label60;
            localObject1 = ˏ((CharSequence)localObject2, str, i, localInteger, (Uri)localObject1, (PendingIntent)localObject3, (PendingIntent)localObject4, ॱ(ˎ(paramBundle, "gcm.n.android_channel_id")));
            break label576;
            if (localInteger != null) {
              break label31;
            }
            break label931;
            break label530;
            if (ˏ(j)) {
              break label253;
            }
          }
        }
        i = ˏॱ + 7;
        ˋॱ = i % 128;
        if (i % 2 == 0) {
          break label546;
        }
        break label267;
        label1650:
        switch (i)
        {
        }
        break label905;
        label1675:
        i = 8;
        break label1700;
        label1681:
        localObject1 = RingtoneManager.getDefaultUri(2);
        break label1280;
        for (;;)
        {
          i = 0;
          break;
          label1695:
          i = 0;
          break label1406;
          for (;;)
          {
            label1700:
            switch (i)
            {
            }
            break;
            label1731:
            i = 13;
          }
          label1742:
          label1774:
          label1801:
          do
          {
            i = 1;
            break;
            long l = SystemClock.uptimeMillis();
            paramBundle = 37 + "FCM-Notification:" + l;
            break label1395;
            localObject2 = (ActivityManager.RunningAppProcessInfo)((Iterator)localObject1).next();
            if (((ActivityManager.RunningAppProcessInfo)localObject2).pid == j) {
              break label1485;
            }
            break label1335;
            localObject1 = ॱ(paramBundle, "gcm.n.title");
          } while (TextUtils.isEmpty((CharSequence)localObject1));
        }
        label1825:
        switch (j)
        {
        }
        break label996;
        label1855:
        if (localObject3 != null) {
          break label730;
        }
        break label1179;
        label1866:
        i = ((Resources)localObject1).getIdentifier((String)localObject3, "mipmap", this.ˋ.getPackageName());
        if (i != 0) {
          break label549;
        }
        break label1028;
        label1894:
        i = ˋॱ + 119;
        ˏॱ = i % 128;
        if (i % 2 != 0) {
          break label41;
        }
      }
      label1921:
      localObject3 = this.ˋ.getPackageName();
      j = String.valueOf(localObject3).length();
      localObject1 = Uri.parse(String.valueOf(localObject1).length() + (j + 24) + "android.resource://" + (String)localObject3 + "/raw/" + (String)localObject1);
    }
  }
}
