package o;

public class O
{
  private static long ʻॱ;
  private static int ʼॱ;
  private static int ʽॱ = 0;
  private static final short[] ʿ;
  private static int ˈ;
  public static byte[] ˏॱ;
  public static byte[] ॱˊ;
  private static Object ॱˋ;
  private static int ॱˎ;
  private static int ॱᐝ;
  private static byte[] ᐝॱ;
  
  /* Error */
  private static String $$d(int paramInt1, int paramInt2, short paramShort)
  {
    // Byte code:
    //   0: goto +237 -> 237
    //   3: aload 9
    //   5: astore 7
    //   7: iload_0
    //   8: istore_2
    //   9: aload 9
    //   11: astore 8
    //   13: iload_3
    //   14: lookupswitch	default:+26->40, 42:+186->200, 58:+340->354
    //   40: aload 9
    //   42: astore 8
    //   44: goto +310 -> 354
    //   47: iload_2
    //   48: istore_0
    //   49: goto +283 -> 332
    //   52: astore 7
    //   54: aload 7
    //   56: athrow
    //   57: iload_0
    //   58: istore_1
    //   59: iload 5
    //   61: istore_3
    //   62: bipush 12
    //   64: iconst_0
    //   65: idiv
    //   66: istore_2
    //   67: aload 8
    //   69: astore 7
    //   71: iload 6
    //   73: istore 4
    //   75: goto +257 -> 332
    //   78: iload_2
    //   79: sipush 17940
    //   82: imul
    //   83: istore_1
    //   84: iload 5
    //   86: newarray char
    //   88: astore 9
    //   90: aload 10
    //   92: ifnonnull +6 -> 98
    //   95: goto +254 -> 349
    //   98: goto +229 -> 327
    //   101: iload_1
    //   102: lookupswitch	default:+26->128, 10:+37->139, 67:+-45->57
    //   128: goto +11 -> 139
    //   131: aload 10
    //   133: iload_2
    //   134: saload
    //   135: istore_3
    //   136: goto +378 -> 514
    //   139: iload_0
    //   140: istore_1
    //   141: iload 5
    //   143: istore_3
    //   144: aload 8
    //   146: astore 7
    //   148: iload 6
    //   150: istore 4
    //   152: goto +180 -> 332
    //   155: iconst_0
    //   156: istore 6
    //   158: iconst_0
    //   159: istore 4
    //   161: iload_0
    //   162: bipush -53
    //   164: ior
    //   165: iload_0
    //   166: bipush -53
    //   168: iand
    //   169: iadd
    //   170: istore_0
    //   171: iload_0
    //   172: bipush 57
    //   174: iand
    //   175: iload_0
    //   176: bipush 57
    //   178: ior
    //   179: iadd
    //   180: istore_0
    //   181: getstatic 310	o/O:ʿ	[S
    //   184: astore 10
    //   186: bipush 28
    //   188: iload_1
    //   189: ineg
    //   190: iconst_m1
    //   191: ixor
    //   192: isub
    //   193: iconst_1
    //   194: isub
    //   195: istore 5
    //   197: goto +286 -> 483
    //   200: aload 7
    //   202: iload 4
    //   204: iload_1
    //   205: i2c
    //   206: castore
    //   207: iload 4
    //   209: iconst_1
    //   210: iadd
    //   211: istore 4
    //   213: iload 4
    //   215: iload 5
    //   217: if_icmpne +6 -> 223
    //   220: goto +249 -> 469
    //   223: goto -92 -> 131
    //   226: iconst_0
    //   227: istore_0
    //   228: goto +71 -> 299
    //   231: bipush 67
    //   233: istore_1
    //   234: goto -133 -> 101
    //   237: goto +347 -> 584
    //   240: iload_1
    //   241: lookupswitch	default:+27->268, 18:+188->429, 78:+-163->78
    //   268: goto +161 -> 429
    //   271: bipush 42
    //   273: istore_3
    //   274: goto -271 -> 3
    //   277: astore 7
    //   279: aload 7
    //   281: athrow
    //   282: iconst_1
    //   283: istore_0
    //   284: goto +15 -> 299
    //   287: bipush 18
    //   289: istore_1
    //   290: goto -50 -> 240
    //   293: bipush 10
    //   295: istore_1
    //   296: goto -195 -> 101
    //   299: iload_0
    //   300: tableswitch	default:+24->324, 0:+-253->47, 1:+243->543
    //   324: goto +219 -> 543
    //   327: iconst_1
    //   328: istore_3
    //   329: goto +54 -> 383
    //   332: iload_0
    //   333: iconst_1
    //   334: iadd
    //   335: istore_2
    //   336: iload_1
    //   337: iload_3
    //   338: ineg
    //   339: iadd
    //   340: iconst_2
    //   341: iadd
    //   342: istore_1
    //   343: goto -143 -> 200
    //   346: goto -191 -> 155
    //   349: iconst_0
    //   350: istore_3
    //   351: goto +32 -> 383
    //   354: getstatic 28	o/O:ʽॱ	I
    //   357: bipush 122
    //   359: iadd
    //   360: iconst_1
    //   361: isub
    //   362: istore_1
    //   363: iload_1
    //   364: sipush 128
    //   367: irem
    //   368: putstatic 30	o/O:ʼॱ	I
    //   371: iload_1
    //   372: iconst_2
    //   373: irem
    //   374: ifne +6 -> 380
    //   377: goto -146 -> 231
    //   380: goto -87 -> 293
    //   383: aload 9
    //   385: astore 7
    //   387: iload_0
    //   388: istore_2
    //   389: aload 9
    //   391: astore 8
    //   393: iload_3
    //   394: tableswitch	default:+22->416, 0:+-40->354, 1:+-194->200
    //   416: aload 9
    //   418: astore 8
    //   420: goto -66 -> 354
    //   423: bipush 58
    //   425: istore_3
    //   426: goto -423 -> 3
    //   429: iload_2
    //   430: ineg
    //   431: istore_1
    //   432: iload_1
    //   433: sipush 718
    //   436: ior
    //   437: iconst_1
    //   438: ishl
    //   439: iload_1
    //   440: sipush 718
    //   443: ixor
    //   444: isub
    //   445: istore_1
    //   446: iload 5
    //   448: newarray char
    //   450: astore 9
    //   452: aload 10
    //   454: ifnonnull +6 -> 460
    //   457: goto -34 -> 423
    //   460: goto -189 -> 271
    //   463: bipush 78
    //   465: istore_1
    //   466: goto -226 -> 240
    //   469: new 312	java/lang/String
    //   472: dup
    //   473: aload 7
    //   475: invokespecial 315	java/lang/String:<init>	([C)V
    //   478: astore 7
    //   480: goto +68 -> 548
    //   483: getstatic 30	o/O:ʼॱ	I
    //   486: istore_1
    //   487: iload_1
    //   488: bipush 14
    //   490: iadd
    //   491: iconst_1
    //   492: isub
    //   493: istore_1
    //   494: iload_1
    //   495: sipush 128
    //   498: irem
    //   499: putstatic 28	o/O:ʽॱ	I
    //   502: iload_1
    //   503: iconst_2
    //   504: irem
    //   505: ifeq +6 -> 511
    //   508: goto -45 -> 463
    //   511: goto -224 -> 287
    //   514: getstatic 30	o/O:ʼॱ	I
    //   517: istore_0
    //   518: iload_0
    //   519: bipush 39
    //   521: iadd
    //   522: istore_0
    //   523: iload_0
    //   524: sipush 128
    //   527: irem
    //   528: putstatic 28	o/O:ʽॱ	I
    //   531: iload_0
    //   532: iconst_2
    //   533: irem
    //   534: ifeq +6 -> 540
    //   537: goto -311 -> 226
    //   540: goto -258 -> 282
    //   543: iload_2
    //   544: istore_0
    //   545: goto -213 -> 332
    //   548: getstatic 28	o/O:ʽॱ	I
    //   551: istore_0
    //   552: iload_0
    //   553: bipush 73
    //   555: ixor
    //   556: iload_0
    //   557: bipush 73
    //   559: iand
    //   560: iconst_1
    //   561: ishl
    //   562: iadd
    //   563: istore_0
    //   564: iload_0
    //   565: sipush 128
    //   568: irem
    //   569: putstatic 30	o/O:ʼॱ	I
    //   572: iload_0
    //   573: iconst_2
    //   574: irem
    //   575: ifne +6 -> 581
    //   578: aload 7
    //   580: areturn
    //   581: aload 7
    //   583: areturn
    //   584: getstatic 28	o/O:ʽॱ	I
    //   587: istore_3
    //   588: iload_3
    //   589: bipush 27
    //   591: ior
    //   592: iconst_1
    //   593: ishl
    //   594: iload_3
    //   595: bipush 27
    //   597: ixor
    //   598: isub
    //   599: istore_3
    //   600: iload_3
    //   601: sipush 128
    //   604: irem
    //   605: putstatic 30	o/O:ʼॱ	I
    //   608: iload_3
    //   609: iconst_2
    //   610: irem
    //   611: ifne +6 -> 617
    //   614: goto -268 -> 346
    //   617: goto -462 -> 155
    // Local variable table:
    //   start	length	slot	name	signature
    //   0	620	0	paramInt1	int
    //   0	620	1	paramInt2	int
    //   0	620	2	paramShort	short
    //   13	598	3	i	int
    //   73	145	4	j	int
    //   59	388	5	k	int
    //   71	86	6	m	int
    //   5	1	7	arrayOfChar1	char[]
    //   52	3	7	localNumberFormatException	NumberFormatException
    //   69	132	7	localObject1	Object
    //   277	3	7	localException	Exception
    //   385	197	7	localObject2	Object
    //   11	408	8	arrayOfChar2	char[]
    //   3	448	9	arrayOfChar3	char[]
    //   90	363	10	arrayOfShort	short[]
    // Exception table:
    //   from	to	target	type
    //   483	487	52	java/lang/NumberFormatException
    //   514	518	52	java/lang/NumberFormatException
    //   523	531	52	java/lang/NullPointerException
    //   548	552	52	java/lang/Exception
    //   564	572	52	java/lang/Exception
    //   564	572	52	java/lang/ArrayStoreException
    //   494	502	277	java/lang/Exception
  }
  
  /* Error */
  static
  {
    // Byte code:
    //   0: iconst_0
    //   1: putstatic 28	o/O:ʽॱ	I
    //   4: iconst_1
    //   5: putstatic 30	o/O:ʼॱ	I
    //   8: goto +5227 -> 5235
    //   11: aload 10
    //   13: athrow
    //   14: goto +11150 -> 11164
    //   17: aload 13
    //   19: checkcast 323	java/lang/Integer
    //   22: invokevirtual 327	java/lang/Integer:intValue	()I
    //   25: istore 4
    //   27: iload 4
    //   29: iconst_m1
    //   30: if_icmpeq +6 -> 36
    //   33: goto +9979 -> 10012
    //   36: goto +258 -> 294
    //   39: getstatic 310	o/O:ʿ	[S
    //   42: bipush 45
    //   44: saload
    //   45: istore_1
    //   46: iload_1
    //   47: i2b
    //   48: istore_1
    //   49: goto +848 -> 897
    //   52: goto +2539 -> 2591
    //   55: aload 13
    //   57: astore 10
    //   59: aload 22
    //   61: astore 11
    //   63: aload 21
    //   65: astore 12
    //   67: iload_1
    //   68: lookupswitch	default:+28->96, 21:+9525->9593, 95:+912->980
    //   96: aload 13
    //   98: astore 10
    //   100: aload 22
    //   102: astore 11
    //   104: aload 21
    //   106: astore 12
    //   108: goto +872 -> 980
    //   111: aload 13
    //   113: iconst_1
    //   114: anewarray 329	java/lang/Class
    //   117: dup
    //   118: iconst_0
    //   119: sipush 393
    //   122: aload 12
    //   124: sipush 142
    //   127: saload
    //   128: i2b
    //   129: sipush 612
    //   132: invokestatic 331	o/O:$$d	(IIS)Ljava/lang/String;
    //   135: invokestatic 335	java/lang/Class:forName	(Ljava/lang/String;)Ljava/lang/Class;
    //   138: aastore
    //   139: invokevirtual 339	java/lang/Class:getDeclaredConstructor	([Ljava/lang/Class;)Ljava/lang/reflect/Constructor;
    //   142: astore 12
    //   144: goto +9172 -> 9316
    //   147: aload 10
    //   149: athrow
    //   150: goto +10620 -> 10770
    //   153: aload 11
    //   155: athrow
    //   156: sipush 393
    //   159: getstatic 310	o/O:ʿ	[S
    //   162: sipush 142
    //   165: saload
    //   166: i2b
    //   167: sipush 612
    //   170: invokestatic 331	o/O:$$d	(IIS)Ljava/lang/String;
    //   173: astore 12
    //   175: goto +8794 -> 8969
    //   178: aload 11
    //   180: athrow
    //   181: aload 13
    //   183: astore 11
    //   185: aload 20
    //   187: astore 10
    //   189: getstatic 310	o/O:ʿ	[S
    //   192: sipush 193
    //   195: saload
    //   196: istore_1
    //   197: goto +8516 -> 8713
    //   200: iconst_0
    //   201: istore_1
    //   202: goto +595 -> 797
    //   205: goto +10094 -> 10299
    //   208: iload_1
    //   209: sipush 648
    //   212: ior
    //   213: i2s
    //   214: istore_0
    //   215: ldc 2
    //   217: sipush 148
    //   220: iload_1
    //   221: iload_0
    //   222: invokestatic 331	o/O:$$d	(IIS)Ljava/lang/String;
    //   225: invokevirtual 343	java/lang/Class:getResourceAsStream	(Ljava/lang/String;)Ljava/io/InputStream;
    //   228: astore 10
    //   230: goto +4447 -> 4677
    //   233: aload 15
    //   235: astore 11
    //   237: goto +6 -> 243
    //   240: aload 10
    //   242: athrow
    //   243: iconst_3
    //   244: istore_1
    //   245: aload 11
    //   247: astore 15
    //   249: goto +10611 -> 10860
    //   252: aload 12
    //   254: astore 11
    //   256: iload_1
    //   257: lookupswitch	default:+27->284, 1:+4659->4916, 8:+9325->9582
    //   284: aload 12
    //   286: astore 11
    //   288: goto +9294 -> 9582
    //   291: aload 10
    //   293: athrow
    //   294: goto +4660 -> 4954
    //   297: aload 11
    //   299: athrow
    //   300: aload 10
    //   302: athrow
    //   303: getstatic 310	o/O:ʿ	[S
    //   306: sipush 142
    //   309: saload
    //   310: istore_1
    //   311: iload_1
    //   312: i2b
    //   313: istore_1
    //   314: goto +9652 -> 9966
    //   317: astore 10
    //   319: aload 10
    //   321: invokevirtual 349	java/lang/Throwable:getCause	()Ljava/lang/Throwable;
    //   324: astore 11
    //   326: aload 11
    //   328: ifnull +6 -> 334
    //   331: goto +10999 -> 11330
    //   334: goto +2005 -> 2339
    //   337: getstatic 28	o/O:ʽॱ	I
    //   340: istore_1
    //   341: iload_1
    //   342: iconst_1
    //   343: iand
    //   344: iload_1
    //   345: iconst_1
    //   346: ior
    //   347: iadd
    //   348: istore_1
    //   349: iload_1
    //   350: sipush 128
    //   353: irem
    //   354: putstatic 30	o/O:ʼॱ	I
    //   357: iload_1
    //   358: iconst_2
    //   359: irem
    //   360: ifne +6 -> 366
    //   363: goto -311 -> 52
    //   366: goto +2225 -> 2591
    //   369: new 312	java/lang/String
    //   372: dup
    //   373: aload 11
    //   375: invokespecial 315	java/lang/String:<init>	([C)V
    //   378: astore 11
    //   380: goto +946 -> 1326
    //   383: sipush 457
    //   386: getstatic 310	o/O:ʿ	[S
    //   389: bipush 11
    //   391: saload
    //   392: i2b
    //   393: sipush 612
    //   396: invokestatic 331	o/O:$$d	(IIS)Ljava/lang/String;
    //   399: astore 13
    //   401: goto +432 -> 833
    //   404: sipush 412
    //   407: i2s
    //   408: istore_1
    //   409: getstatic 310	o/O:ʿ	[S
    //   412: iconst_4
    //   413: saload
    //   414: istore_1
    //   415: iload_1
    //   416: i2b
    //   417: istore_1
    //   418: iload_1
    //   419: sipush 608
    //   422: ixor
    //   423: iload_1
    //   424: sipush 608
    //   427: iand
    //   428: ior
    //   429: i2s
    //   430: istore_0
    //   431: goto +4404 -> 4835
    //   434: getstatic 351	o/O:ʻॱ	J
    //   437: bipush 32
    //   439: lushr
    //   440: l2i
    //   441: istore_3
    //   442: getstatic 351	o/O:ʻॱ	J
    //   445: l2i
    //   446: istore 4
    //   448: getstatic 353	o/O:ॱᐝ	I
    //   451: istore 5
    //   453: getstatic 355	o/O:ᐝॱ	[B
    //   456: astore 11
    //   458: getstatic 357	o/O:ॱˎ	I
    //   461: istore 6
    //   463: new 359	o/oM
    //   466: dup
    //   467: aload 10
    //   469: iconst_2
    //   470: newarray int
    //   472: dup
    //   473: iconst_0
    //   474: ldc_w 360
    //   477: iload_3
    //   478: iand
    //   479: iload_3
    //   480: iconst_m1
    //   481: ixor
    //   482: ldc_w 361
    //   485: iand
    //   486: ior
    //   487: iastore
    //   488: dup
    //   489: iconst_1
    //   490: iload 4
    //   492: ldc_w 361
    //   495: ixor
    //   496: iastore
    //   497: iload 5
    //   499: aload 11
    //   501: bipush 14
    //   503: iload 6
    //   505: invokespecial 364	o/oM:<init>	(Ljava/io/InputStream;[II[BII)V
    //   508: astore 10
    //   510: goto +601 -> 1111
    //   513: sipush 449
    //   516: aload 13
    //   518: bipush 50
    //   520: saload
    //   521: i2b
    //   522: sipush 610
    //   525: invokestatic 331	o/O:$$d	(IIS)Ljava/lang/String;
    //   528: astore 13
    //   530: goto +9461 -> 9991
    //   533: aload 10
    //   535: athrow
    //   536: iconst_0
    //   537: istore_1
    //   538: goto +3736 -> 4274
    //   541: aload 10
    //   543: athrow
    //   544: getstatic 310	o/O:ʿ	[S
    //   547: iconst_5
    //   548: saload
    //   549: istore_1
    //   550: iload_1
    //   551: i2b
    //   552: istore_1
    //   553: iload_1
    //   554: sipush 23928
    //   557: iand
    //   558: iconst_m1
    //   559: ixor
    //   560: iload_1
    //   561: sipush 23928
    //   564: ior
    //   565: iand
    //   566: i2s
    //   567: istore_0
    //   568: goto +4267 -> 4835
    //   571: iload_1
    //   572: lookupswitch	default:+28->600, 60:+10943->11515, 84:+-422->150
    //   600: goto +10915 -> 11515
    //   603: ldc_w 365
    //   606: istore_3
    //   607: goto +2751 -> 3358
    //   610: aload 19
    //   612: athrow
    //   613: aload 12
    //   615: aload 11
    //   617: iconst_4
    //   618: anewarray 4	java/lang/Object
    //   621: dup
    //   622: iconst_0
    //   623: aload 10
    //   625: aastore
    //   626: dup
    //   627: iconst_1
    //   628: iconst_4
    //   629: invokestatic 369	java/lang/Integer:valueOf	(I)Ljava/lang/Integer;
    //   632: aastore
    //   633: dup
    //   634: iconst_2
    //   635: bipush 16
    //   637: newarray byte
    //   639: dup
    //   640: iconst_0
    //   641: ldc -109
    //   643: bastore
    //   644: dup
    //   645: iconst_1
    //   646: ldc -111
    //   648: bastore
    //   649: dup
    //   650: iconst_2
    //   651: ldc 55
    //   653: bastore
    //   654: dup
    //   655: iconst_3
    //   656: ldc 70
    //   658: bastore
    //   659: dup
    //   660: iconst_4
    //   661: ldc 111
    //   663: bastore
    //   664: dup
    //   665: iconst_5
    //   666: ldc 114
    //   668: bastore
    //   669: dup
    //   670: bipush 6
    //   672: ldc -55
    //   674: bastore
    //   675: dup
    //   676: bipush 7
    //   678: ldc_w 279
    //   681: bastore
    //   682: dup
    //   683: bipush 8
    //   685: ldc 53
    //   687: bastore
    //   688: dup
    //   689: bipush 9
    //   691: ldc_w 267
    //   694: bastore
    //   695: dup
    //   696: bipush 10
    //   698: ldc 89
    //   700: bastore
    //   701: dup
    //   702: bipush 11
    //   704: ldc 113
    //   706: bastore
    //   707: dup
    //   708: bipush 12
    //   710: ldc -1
    //   712: bastore
    //   713: dup
    //   714: bipush 13
    //   716: ldc -123
    //   718: bastore
    //   719: dup
    //   720: bipush 14
    //   722: ldc -63
    //   724: bastore
    //   725: dup
    //   726: bipush 15
    //   728: ldc -84
    //   730: bastore
    //   731: aastore
    //   732: dup
    //   733: iconst_3
    //   734: ldc_w 370
    //   737: invokestatic 369	java/lang/Integer:valueOf	(I)Ljava/lang/Integer;
    //   740: aastore
    //   741: invokevirtual 376	java/lang/reflect/Method:invoke	(Ljava/lang/Object;[Ljava/lang/Object;)Ljava/lang/Object;
    //   744: astore 10
    //   746: goto +365 -> 1111
    //   749: aload 11
    //   751: athrow
    //   752: iconst_0
    //   753: istore_1
    //   754: goto +3872 -> 4626
    //   757: goto +9911 -> 10668
    //   760: aload 11
    //   762: athrow
    //   763: getstatic 288	o/O:ॱˊ	[B
    //   766: astore 10
    //   768: goto +9424 -> 10192
    //   771: aload 11
    //   773: athrow
    //   774: iconst_3
    //   775: putstatic 357	o/O:ॱˎ	I
    //   778: aconst_null
    //   779: astore 12
    //   781: getstatic 378	o/O:ॱˋ	Ljava/lang/Object;
    //   784: astore 10
    //   786: aload 10
    //   788: ifnonnull +6 -> 794
    //   791: goto +9511 -> 10302
    //   794: goto +1913 -> 2707
    //   797: aload 19
    //   799: astore 12
    //   801: iload_1
    //   802: tableswitch	default:+22->824, 0:+9719->10521, 1:+10329->11131
    //   824: goto +9697 -> 10521
    //   827: aload 10
    //   829: athrow
    //   830: goto +8536 -> 9366
    //   833: aload 13
    //   835: invokestatic 335	java/lang/Class:forName	(Ljava/lang/String;)Ljava/lang/Class;
    //   838: astore 13
    //   840: getstatic 310	o/O:ʿ	[S
    //   843: sipush 229
    //   846: saload
    //   847: i2s
    //   848: istore_3
    //   849: getstatic 310	o/O:ʿ	[S
    //   852: astore 18
    //   854: goto +8985 -> 9839
    //   857: iload_1
    //   858: iload_2
    //   859: sipush 612
    //   862: invokestatic 331	o/O:$$d	(IIS)Ljava/lang/String;
    //   865: invokestatic 335	java/lang/Class:forName	(Ljava/lang/String;)Ljava/lang/Class;
    //   868: aconst_null
    //   869: invokevirtual 339	java/lang/Class:getDeclaredConstructor	([Ljava/lang/Class;)Ljava/lang/reflect/Constructor;
    //   872: astore 11
    //   874: goto +2689 -> 3563
    //   877: astore 10
    //   879: aload 10
    //   881: invokevirtual 349	java/lang/Throwable:getCause	()Ljava/lang/Throwable;
    //   884: astore 11
    //   886: aload 11
    //   888: ifnull +6 -> 894
    //   891: goto +1257 -> 2148
    //   894: goto +2947 -> 3841
    //   897: bipush 76
    //   899: iload_1
    //   900: sipush 618
    //   903: invokestatic 331	o/O:$$d	(IIS)Ljava/lang/String;
    //   906: invokestatic 335	java/lang/Class:forName	(Ljava/lang/String;)Ljava/lang/Class;
    //   909: astore 10
    //   911: getstatic 310	o/O:ʿ	[S
    //   914: astore 21
    //   916: goto +3036 -> 3952
    //   919: aload 12
    //   921: aload 13
    //   923: iconst_4
    //   924: anewarray 329	java/lang/Class
    //   927: dup
    //   928: iconst_0
    //   929: aload 18
    //   931: aastore
    //   932: dup
    //   933: iconst_1
    //   934: aload 19
    //   936: aastore
    //   937: dup
    //   938: iconst_2
    //   939: ldc_w 379
    //   942: aastore
    //   943: dup
    //   944: iconst_3
    //   945: getstatic 383	java/lang/Integer:TYPE	Ljava/lang/Class;
    //   948: aastore
    //   949: invokevirtual 387	java/lang/Class:getDeclaredMethod	(Ljava/lang/String;[Ljava/lang/Class;)Ljava/lang/reflect/Method;
    //   952: astore 12
    //   954: goto -341 -> 613
    //   957: astore 12
    //   959: aload 11
    //   961: astore 13
    //   963: aload 10
    //   965: astore 11
    //   967: aload 18
    //   969: astore 10
    //   971: goto +9047 -> 10018
    //   974: goto +2870 -> 3844
    //   977: aload 11
    //   979: athrow
    //   980: aload 10
    //   982: astore 13
    //   984: aload 12
    //   986: astore 10
    //   988: goto +9030 -> 10018
    //   991: iload_1
    //   992: ifeq +6 -> 998
    //   995: goto +9313 -> 10308
    //   998: goto +1652 -> 2650
    //   1001: astore 10
    //   1003: aload 10
    //   1005: invokevirtual 349	java/lang/Throwable:getCause	()Ljava/lang/Throwable;
    //   1008: astore 11
    //   1010: aload 11
    //   1012: ifnull +6 -> 1018
    //   1015: goto +205 -> 1220
    //   1018: goto +508 -> 1526
    //   1021: astore 10
    //   1023: aload 10
    //   1025: invokevirtual 349	java/lang/Throwable:getCause	()Ljava/lang/Throwable;
    //   1028: astore 11
    //   1030: aload 11
    //   1032: ifnull +6 -> 1038
    //   1035: goto +4197 -> 5232
    //   1038: goto +4073 -> 5111
    //   1041: goto +2850 -> 3891
    //   1044: aload 19
    //   1046: athrow
    //   1047: iload_3
    //   1048: sipush 513
    //   1051: iand
    //   1052: iconst_m1
    //   1053: ixor
    //   1054: iload_3
    //   1055: sipush 513
    //   1058: ior
    //   1059: iand
    //   1060: i2s
    //   1061: istore_0
    //   1062: sipush 142
    //   1065: iload_2
    //   1066: iload_0
    //   1067: invokestatic 331	o/O:$$d	(IIS)Ljava/lang/String;
    //   1070: astore 11
    //   1072: iconst_1
    //   1073: anewarray 329	java/lang/Class
    //   1076: astore 12
    //   1078: iconst_1
    //   1079: istore_1
    //   1080: getstatic 390	java/lang/Long:TYPE	Ljava/lang/Class;
    //   1083: astore 13
    //   1085: goto +138 -> 1223
    //   1088: aload 12
    //   1090: iconst_0
    //   1091: aload 10
    //   1093: aastore
    //   1094: sipush 27530
    //   1097: i2s
    //   1098: istore_1
    //   1099: getstatic 310	o/O:ʿ	[S
    //   1102: astore 11
    //   1104: sipush 20999
    //   1107: istore_2
    //   1108: goto +1297 -> 2405
    //   1111: goto +9746 -> 10857
    //   1114: getstatic 30	o/O:ʼॱ	I
    //   1117: bipush 122
    //   1119: iadd
    //   1120: iconst_1
    //   1121: isub
    //   1122: istore_1
    //   1123: iload_1
    //   1124: sipush 128
    //   1127: irem
    //   1128: putstatic 28	o/O:ʽॱ	I
    //   1131: iload_1
    //   1132: iconst_2
    //   1133: irem
    //   1134: ifeq +6 -> 1140
    //   1137: goto +9098 -> 10235
    //   1140: goto -604 -> 536
    //   1143: aload 11
    //   1145: athrow
    //   1146: astore 10
    //   1148: aload 10
    //   1150: invokevirtual 349	java/lang/Throwable:getCause	()Ljava/lang/Throwable;
    //   1153: astore 11
    //   1155: aload 11
    //   1157: ifnull +6 -> 1163
    //   1160: goto +2201 -> 3361
    //   1163: goto +260 -> 1423
    //   1166: goto +9780 -> 10946
    //   1169: sipush 393
    //   1172: getstatic 310	o/O:ʿ	[S
    //   1175: sipush 142
    //   1178: saload
    //   1179: i2b
    //   1180: sipush 612
    //   1183: invokestatic 331	o/O:$$d	(IIS)Ljava/lang/String;
    //   1186: astore 11
    //   1188: goto +2919 -> 4107
    //   1191: iconst_0
    //   1192: istore_1
    //   1193: goto +1488 -> 2681
    //   1196: getstatic 310	o/O:ʿ	[S
    //   1199: bipush 34
    //   1201: saload
    //   1202: i2s
    //   1203: istore_3
    //   1204: getstatic 310	o/O:ʿ	[S
    //   1207: bipush 6
    //   1209: saload
    //   1210: istore 5
    //   1212: iload 5
    //   1214: i2b
    //   1215: istore 5
    //   1217: goto +1868 -> 3085
    //   1220: aload 11
    //   1222: athrow
    //   1223: aload 12
    //   1225: iload_1
    //   1226: aload 13
    //   1228: aastore
    //   1229: aload 14
    //   1231: aload 11
    //   1233: aload 12
    //   1235: invokevirtual 393	java/lang/Class:getMethod	(Ljava/lang/String;[Ljava/lang/Class;)Ljava/lang/reflect/Method;
    //   1238: aload 16
    //   1240: iconst_1
    //   1241: anewarray 4	java/lang/Object
    //   1244: dup
    //   1245: iconst_0
    //   1246: lload 8
    //   1248: ldc2_w 394
    //   1251: lxor
    //   1252: invokestatic 398	java/lang/Long:valueOf	(J)Ljava/lang/Long;
    //   1255: aastore
    //   1256: invokevirtual 376	java/lang/reflect/Method:invoke	(Ljava/lang/Object;[Ljava/lang/Object;)Ljava/lang/Object;
    //   1259: pop
    //   1260: aconst_null
    //   1261: astore 14
    //   1263: aconst_null
    //   1264: astore 15
    //   1266: goto +10067 -> 11333
    //   1269: astore 10
    //   1271: aload 10
    //   1273: invokevirtual 349	java/lang/Throwable:getCause	()Ljava/lang/Throwable;
    //   1276: astore 11
    //   1278: aload 11
    //   1280: ifnull +6 -> 1286
    //   1283: goto +3529 -> 4812
    //   1286: goto +7791 -> 9077
    //   1289: getstatic 28	o/O:ʽॱ	I
    //   1292: istore_1
    //   1293: iload_1
    //   1294: bipush 78
    //   1296: iadd
    //   1297: iconst_1
    //   1298: isub
    //   1299: istore_1
    //   1300: iload_1
    //   1301: sipush 128
    //   1304: irem
    //   1305: putstatic 30	o/O:ʼॱ	I
    //   1308: iload_1
    //   1309: iconst_2
    //   1310: irem
    //   1311: ifne +6 -> 1317
    //   1314: goto +1494 -> 2808
    //   1317: goto -714 -> 603
    //   1320: aload 11
    //   1322: athrow
    //   1323: aload 10
    //   1325: athrow
    //   1326: iconst_2
    //   1327: anewarray 4	java/lang/Object
    //   1330: astore 12
    //   1332: aload 12
    //   1334: iconst_1
    //   1335: aload 11
    //   1337: aastore
    //   1338: goto +191 -> 1529
    //   1341: aload 10
    //   1343: athrow
    //   1344: astore 10
    //   1346: aload 10
    //   1348: invokevirtual 349	java/lang/Throwable:getCause	()Ljava/lang/Throwable;
    //   1351: astore 11
    //   1353: aload 11
    //   1355: ifnull +6 -> 1361
    //   1358: goto +9803 -> 11161
    //   1361: goto +1185 -> 2546
    //   1364: goto +2787 -> 4151
    //   1367: iload_1
    //   1368: iconst_1
    //   1369: iand
    //   1370: iload_1
    //   1371: iconst_1
    //   1372: ior
    //   1373: iadd
    //   1374: newarray char
    //   1376: astore 11
    //   1378: aload 11
    //   1380: iconst_0
    //   1381: bipush 46
    //   1383: castore
    //   1384: goto -393 -> 991
    //   1387: getstatic 28	o/O:ʽॱ	I
    //   1390: istore_1
    //   1391: iload_1
    //   1392: bipush 115
    //   1394: ior
    //   1395: iconst_1
    //   1396: ishl
    //   1397: iload_1
    //   1398: bipush 115
    //   1400: ixor
    //   1401: isub
    //   1402: istore_1
    //   1403: iload_1
    //   1404: sipush 128
    //   1407: irem
    //   1408: putstatic 30	o/O:ʼॱ	I
    //   1411: iload_1
    //   1412: iconst_2
    //   1413: irem
    //   1414: ifne +6 -> 1420
    //   1417: goto +8823 -> 10240
    //   1420: goto +3700 -> 5120
    //   1423: aload 10
    //   1425: athrow
    //   1426: iload_1
    //   1427: lookupswitch	default:+25->1452, 22:+8775->10202, 48:+9710->11137
    //   1452: goto +8750 -> 10202
    //   1455: iload_2
    //   1456: i2b
    //   1457: istore_2
    //   1458: iload_1
    //   1459: iload_2
    //   1460: sipush 612
    //   1463: invokestatic 331	o/O:$$d	(IIS)Ljava/lang/String;
    //   1466: invokestatic 335	java/lang/Class:forName	(Ljava/lang/String;)Ljava/lang/Class;
    //   1469: astore 14
    //   1471: goto +2351 -> 3822
    //   1474: astore 10
    //   1476: aload 10
    //   1478: invokevirtual 349	java/lang/Throwable:getCause	()Ljava/lang/Throwable;
    //   1481: astore 11
    //   1483: aload 11
    //   1485: ifnull +6 -> 1491
    //   1488: goto +884 -> 2372
    //   1491: goto +9472 -> 10963
    //   1494: aload 10
    //   1496: athrow
    //   1497: getstatic 28	o/O:ʽॱ	I
    //   1500: bipush 94
    //   1502: iadd
    //   1503: iconst_1
    //   1504: isub
    //   1505: istore_1
    //   1506: iload_1
    //   1507: sipush 128
    //   1510: irem
    //   1511: putstatic 30	o/O:ʼॱ	I
    //   1514: iload_1
    //   1515: iconst_2
    //   1516: irem
    //   1517: ifne +6 -> 1523
    //   1520: goto -1315 -> 205
    //   1523: goto +8776 -> 10299
    //   1526: aload 10
    //   1528: athrow
    //   1529: getstatic 28	o/O:ʽॱ	I
    //   1532: bipush 122
    //   1534: iadd
    //   1535: iconst_1
    //   1536: isub
    //   1537: istore_1
    //   1538: iload_1
    //   1539: sipush 128
    //   1542: irem
    //   1543: putstatic 30	o/O:ʼॱ	I
    //   1546: iload_1
    //   1547: iconst_2
    //   1548: irem
    //   1549: ifne +6 -> 1555
    //   1552: goto -464 -> 1088
    //   1555: goto +1376 -> 2931
    //   1558: sipush 393
    //   1561: iload_1
    //   1562: sipush 612
    //   1565: invokestatic 331	o/O:$$d	(IIS)Ljava/lang/String;
    //   1568: invokestatic 335	java/lang/Class:forName	(Ljava/lang/String;)Ljava/lang/Class;
    //   1571: astore 10
    //   1573: goto +8144 -> 9717
    //   1576: getstatic 310	o/O:ʿ	[S
    //   1579: bipush 60
    //   1581: saload
    //   1582: i2s
    //   1583: getstatic 310	o/O:ʿ	[S
    //   1586: bipush 31
    //   1588: saload
    //   1589: i2b
    //   1590: sipush 612
    //   1593: invokestatic 331	o/O:$$d	(IIS)Ljava/lang/String;
    //   1596: invokestatic 335	java/lang/Class:forName	(Ljava/lang/String;)Ljava/lang/Class;
    //   1599: sipush 387
    //   1602: getstatic 310	o/O:ʿ	[S
    //   1605: sipush 192
    //   1608: saload
    //   1609: i2b
    //   1610: sipush 608
    //   1613: invokestatic 331	o/O:$$d	(IIS)Ljava/lang/String;
    //   1616: iconst_1
    //   1617: anewarray 329	java/lang/Class
    //   1620: dup
    //   1621: iconst_0
    //   1622: getstatic 383	java/lang/Integer:TYPE	Ljava/lang/Class;
    //   1625: aastore
    //   1626: invokevirtual 393	java/lang/Class:getMethod	(Ljava/lang/String;[Ljava/lang/Class;)Ljava/lang/reflect/Method;
    //   1629: aload 16
    //   1631: iconst_1
    //   1632: anewarray 4	java/lang/Object
    //   1635: dup
    //   1636: iconst_0
    //   1637: bipush 12
    //   1639: invokestatic 369	java/lang/Integer:valueOf	(I)Ljava/lang/Integer;
    //   1642: aastore
    //   1643: invokevirtual 376	java/lang/reflect/Method:invoke	(Ljava/lang/Object;[Ljava/lang/Object;)Ljava/lang/Object;
    //   1646: checkcast 323	java/lang/Integer
    //   1649: invokevirtual 327	java/lang/Integer:intValue	()I
    //   1652: istore_2
    //   1653: iload_2
    //   1654: ineg
    //   1655: ineg
    //   1656: istore_3
    //   1657: iload_1
    //   1658: iconst_1
    //   1659: isub
    //   1660: istore_2
    //   1661: aload 11
    //   1663: iload_1
    //   1664: sipush 8192
    //   1667: iload_3
    //   1668: iconst_m1
    //   1669: ixor
    //   1670: isub
    //   1671: iconst_1
    //   1672: isub
    //   1673: i2c
    //   1674: castore
    //   1675: iload_2
    //   1676: istore_1
    //   1677: goto -686 -> 991
    //   1680: aload 11
    //   1682: iconst_1
    //   1683: anewarray 4	java/lang/Object
    //   1686: dup
    //   1687: iconst_0
    //   1688: aload 10
    //   1690: aastore
    //   1691: invokevirtual 404	java/lang/reflect/Constructor:newInstance	([Ljava/lang/Object;)Ljava/lang/Object;
    //   1694: astore 10
    //   1696: sipush 393
    //   1699: getstatic 310	o/O:ʿ	[S
    //   1702: sipush 142
    //   1705: saload
    //   1706: i2b
    //   1707: sipush 612
    //   1710: invokestatic 331	o/O:$$d	(IIS)Ljava/lang/String;
    //   1713: invokestatic 335	java/lang/Class:forName	(Ljava/lang/String;)Ljava/lang/Class;
    //   1716: sipush 362
    //   1719: getstatic 310	o/O:ʿ	[S
    //   1722: iconst_3
    //   1723: saload
    //   1724: ineg
    //   1725: i2b
    //   1726: sipush 619
    //   1729: invokestatic 331	o/O:$$d	(IIS)Ljava/lang/String;
    //   1732: aconst_null
    //   1733: invokevirtual 393	java/lang/Class:getMethod	(Ljava/lang/String;[Ljava/lang/Class;)Ljava/lang/reflect/Method;
    //   1736: aload 10
    //   1738: aconst_null
    //   1739: invokevirtual 376	java/lang/reflect/Method:invoke	(Ljava/lang/Object;[Ljava/lang/Object;)Ljava/lang/Object;
    //   1742: checkcast 406	java/lang/Boolean
    //   1745: invokevirtual 410	java/lang/Boolean:booleanValue	()Z
    //   1748: istore 7
    //   1750: iload 7
    //   1752: ifeq +6 -> 1758
    //   1755: goto +8274 -> 10029
    //   1758: goto +2510 -> 4268
    //   1761: getstatic 28	o/O:ʽॱ	I
    //   1764: istore_3
    //   1765: iload_3
    //   1766: bipush 73
    //   1768: ixor
    //   1769: iload_3
    //   1770: bipush 73
    //   1772: iand
    //   1773: iconst_1
    //   1774: ishl
    //   1775: iadd
    //   1776: istore_3
    //   1777: iload_3
    //   1778: sipush 128
    //   1781: irem
    //   1782: putstatic 30	o/O:ʼॱ	I
    //   1785: iload_3
    //   1786: iconst_2
    //   1787: irem
    //   1788: ifne +6 -> 1794
    //   1791: goto +2389 -> 4180
    //   1794: goto -937 -> 857
    //   1797: astore 10
    //   1799: aload 10
    //   1801: invokevirtual 349	java/lang/Throwable:getCause	()Ljava/lang/Throwable;
    //   1804: astore 11
    //   1806: aload 11
    //   1808: ifnull +6 -> 1814
    //   1811: goto +7447 -> 9258
    //   1814: goto -1514 -> 300
    //   1817: sipush 206
    //   1820: getstatic 310	o/O:ʿ	[S
    //   1823: bipush 17
    //   1825: saload
    //   1826: i2b
    //   1827: sipush 604
    //   1830: invokestatic 331	o/O:$$d	(IIS)Ljava/lang/String;
    //   1833: astore 10
    //   1835: goto +8652 -> 10487
    //   1838: goto -669 -> 1169
    //   1841: bipush 21
    //   1843: istore_1
    //   1844: goto -1789 -> 55
    //   1847: getstatic 28	o/O:ʽॱ	I
    //   1850: istore_3
    //   1851: iload_3
    //   1852: iconst_3
    //   1853: iadd
    //   1854: istore_3
    //   1855: iload_3
    //   1856: sipush 128
    //   1859: irem
    //   1860: putstatic 30	o/O:ʼॱ	I
    //   1863: iload_3
    //   1864: iconst_2
    //   1865: irem
    //   1866: ifne +6 -> 1872
    //   1869: goto +6927 -> 8796
    //   1872: goto +7311 -> 9183
    //   1875: aload 12
    //   1877: sipush 413
    //   1880: saload
    //   1881: ineg
    //   1882: i2s
    //   1883: istore_3
    //   1884: getstatic 310	o/O:ʿ	[S
    //   1887: sipush 368
    //   1890: saload
    //   1891: i2b
    //   1892: istore 4
    //   1894: iload_3
    //   1895: iload 4
    //   1897: iload 4
    //   1899: sipush 582
    //   1902: ixor
    //   1903: iload 4
    //   1905: sipush 582
    //   1908: iand
    //   1909: ior
    //   1910: i2s
    //   1911: invokestatic 331	o/O:$$d	(IIS)Ljava/lang/String;
    //   1914: astore 12
    //   1916: goto +8195 -> 10111
    //   1919: getstatic 310	o/O:ʿ	[S
    //   1922: bipush 60
    //   1924: saload
    //   1925: i2s
    //   1926: istore_1
    //   1927: getstatic 310	o/O:ʿ	[S
    //   1930: bipush 31
    //   1932: saload
    //   1933: istore_2
    //   1934: iload_2
    //   1935: i2b
    //   1936: istore_2
    //   1937: goto -176 -> 1761
    //   1940: getstatic 30	o/O:ʼॱ	I
    //   1943: istore_1
    //   1944: iload_1
    //   1945: bipush 29
    //   1947: ior
    //   1948: iconst_1
    //   1949: ishl
    //   1950: iload_1
    //   1951: bipush 29
    //   1953: ixor
    //   1954: isub
    //   1955: istore_1
    //   1956: iload_1
    //   1957: sipush 128
    //   1960: irem
    //   1961: putstatic 28	o/O:ʽॱ	I
    //   1964: iload_1
    //   1965: iconst_2
    //   1966: irem
    //   1967: ifeq +6 -> 1973
    //   1970: goto +6918 -> 8888
    //   1973: goto +253 -> 2226
    //   1976: iconst_1
    //   1977: istore_1
    //   1978: goto -1181 -> 797
    //   1981: sipush 393
    //   1984: aload 13
    //   1986: sipush 142
    //   1989: saload
    //   1990: i2b
    //   1991: sipush 612
    //   1994: invokestatic 331	o/O:$$d	(IIS)Ljava/lang/String;
    //   1997: invokestatic 335	java/lang/Class:forName	(Ljava/lang/String;)Ljava/lang/Class;
    //   2000: astore 13
    //   2002: goto +547 -> 2549
    //   2005: goto -1858 -> 147
    //   2008: iconst_1
    //   2009: istore_1
    //   2010: goto +2616 -> 4626
    //   2013: iconst_1
    //   2014: istore_1
    //   2015: goto +6969 -> 8984
    //   2018: aload 11
    //   2020: sipush 268
    //   2023: aload 13
    //   2025: bipush 107
    //   2027: saload
    //   2028: i2b
    //   2029: sipush 13800
    //   2032: invokestatic 331	o/O:$$d	(IIS)Ljava/lang/String;
    //   2035: aconst_null
    //   2036: invokevirtual 393	java/lang/Class:getMethod	(Ljava/lang/String;[Ljava/lang/Class;)Ljava/lang/reflect/Method;
    //   2039: astore 11
    //   2041: goto +2266 -> 4307
    //   2044: iload_1
    //   2045: ifle +6 -> 2051
    //   2048: goto +6488 -> 8536
    //   2051: goto -1757 -> 294
    //   2054: getstatic 30	o/O:ʼॱ	I
    //   2057: istore_1
    //   2058: iload_1
    //   2059: bipush 97
    //   2061: ior
    //   2062: iconst_1
    //   2063: ishl
    //   2064: iload_1
    //   2065: bipush 97
    //   2067: ixor
    //   2068: isub
    //   2069: istore_1
    //   2070: iload_1
    //   2071: sipush 128
    //   2074: irem
    //   2075: putstatic 28	o/O:ʽॱ	I
    //   2078: iload_1
    //   2079: iconst_2
    //   2080: irem
    //   2081: ifeq +6 -> 2087
    //   2084: goto +8056 -> 10140
    //   2087: goto +8986 -> 11073
    //   2090: goto +7659 -> 9749
    //   2093: getstatic 310	o/O:ʿ	[S
    //   2096: bipush 31
    //   2098: saload
    //   2099: istore_1
    //   2100: iload_1
    //   2101: i2b
    //   2102: istore_1
    //   2103: goto +8288 -> 10391
    //   2106: aload 13
    //   2108: iconst_1
    //   2109: iconst_0
    //   2110: invokestatic 369	java/lang/Integer:valueOf	(I)Ljava/lang/Integer;
    //   2113: aastore
    //   2114: aload 13
    //   2116: iconst_0
    //   2117: aload 12
    //   2119: aastore
    //   2120: getstatic 310	o/O:ʿ	[S
    //   2123: astore 18
    //   2125: goto +300 -> 2425
    //   2128: astore 10
    //   2130: aload 10
    //   2132: invokevirtual 349	java/lang/Throwable:getCause	()Ljava/lang/Throwable;
    //   2135: astore 12
    //   2137: aload 12
    //   2139: ifnull +6 -> 2145
    //   2142: goto +2532 -> 4674
    //   2145: goto -1905 -> 240
    //   2148: aload 11
    //   2150: athrow
    //   2151: aload 11
    //   2153: athrow
    //   2154: astore 10
    //   2156: aload 10
    //   2158: invokevirtual 349	java/lang/Throwable:getCause	()Ljava/lang/Throwable;
    //   2161: astore 11
    //   2163: aload 11
    //   2165: ifnull +6 -> 2171
    //   2168: goto +8337 -> 10505
    //   2171: goto +2003 -> 4174
    //   2174: aload 12
    //   2176: ifnull +6 -> 2182
    //   2179: goto +8927 -> 11106
    //   2182: goto +7720 -> 9902
    //   2185: bipush 60
    //   2187: istore_1
    //   2188: goto -1617 -> 571
    //   2191: sipush 393
    //   2194: iload_1
    //   2195: sipush 612
    //   2198: invokestatic 331	o/O:$$d	(IIS)Ljava/lang/String;
    //   2201: invokestatic 335	java/lang/Class:forName	(Ljava/lang/String;)Ljava/lang/Class;
    //   2204: astore 10
    //   2206: getstatic 310	o/O:ʿ	[S
    //   2209: astore 19
    //   2211: goto +7302 -> 9513
    //   2214: aload 11
    //   2216: aload 12
    //   2218: invokevirtual 404	java/lang/reflect/Constructor:newInstance	([Ljava/lang/Object;)Ljava/lang/Object;
    //   2221: astore 11
    //   2223: goto +8392 -> 10615
    //   2226: goto +2572 -> 4798
    //   2229: aload 12
    //   2231: ifnull +6 -> 2237
    //   2234: goto +1765 -> 3999
    //   2237: aload 23
    //   2239: astore 10
    //   2241: aload 22
    //   2243: astore 11
    //   2245: aload 21
    //   2247: astore 12
    //   2249: goto -1269 -> 980
    //   2252: astore 10
    //   2254: aload 10
    //   2256: invokevirtual 349	java/lang/Throwable:getCause	()Ljava/lang/Throwable;
    //   2259: astore 11
    //   2261: aload 11
    //   2263: ifnull +6 -> 2269
    //   2266: goto -946 -> 1320
    //   2269: goto -946 -> 1323
    //   2272: iconst_0
    //   2273: istore_1
    //   2274: goto +2873 -> 5147
    //   2277: sipush 369
    //   2280: getstatic 310	o/O:ʿ	[S
    //   2283: bipush 11
    //   2285: saload
    //   2286: i2b
    //   2287: sipush 612
    //   2290: invokestatic 331	o/O:$$d	(IIS)Ljava/lang/String;
    //   2293: invokestatic 335	java/lang/Class:forName	(Ljava/lang/String;)Ljava/lang/Class;
    //   2296: iconst_2
    //   2297: anewarray 329	java/lang/Class
    //   2300: dup
    //   2301: iconst_0
    //   2302: ldc_w 312
    //   2305: aastore
    //   2306: dup
    //   2307: iconst_1
    //   2308: ldc_w 345
    //   2311: aastore
    //   2312: invokevirtual 339	java/lang/Class:getDeclaredConstructor	([Ljava/lang/Class;)Ljava/lang/reflect/Constructor;
    //   2315: iconst_2
    //   2316: anewarray 4	java/lang/Object
    //   2319: dup
    //   2320: iconst_0
    //   2321: aload 11
    //   2323: aastore
    //   2324: dup
    //   2325: iconst_1
    //   2326: aload 10
    //   2328: aastore
    //   2329: invokevirtual 404	java/lang/reflect/Constructor:newInstance	([Ljava/lang/Object;)Ljava/lang/Object;
    //   2332: checkcast 345	java/lang/Throwable
    //   2335: athrow
    //   2336: goto +2479 -> 4815
    //   2339: aload 10
    //   2341: athrow
    //   2342: goto +55 -> 2397
    //   2345: iload_2
    //   2346: i2b
    //   2347: istore_2
    //   2348: iload_1
    //   2349: iload_2
    //   2350: sipush 612
    //   2353: invokestatic 331	o/O:$$d	(IIS)Ljava/lang/String;
    //   2356: invokestatic 335	java/lang/Class:forName	(Ljava/lang/String;)Ljava/lang/Class;
    //   2359: astore 11
    //   2361: goto +6498 -> 8859
    //   2364: goto +1935 -> 4299
    //   2367: astore 10
    //   2369: aload 10
    //   2371: athrow
    //   2372: aload 11
    //   2374: athrow
    //   2375: aload 13
    //   2377: astore 11
    //   2379: aload 20
    //   2381: astore 10
    //   2383: getstatic 310	o/O:ʿ	[S
    //   2386: sipush 238
    //   2389: saload
    //   2390: istore_1
    //   2391: iload_1
    //   2392: i2b
    //   2393: istore_1
    //   2394: goto +7872 -> 10266
    //   2397: getstatic 383	java/lang/Integer:TYPE	Ljava/lang/Class;
    //   2400: astore 21
    //   2402: goto +8143 -> 10545
    //   2405: iload_1
    //   2406: aload 11
    //   2408: iload_2
    //   2409: saload
    //   2410: i2b
    //   2411: sipush 612
    //   2414: invokestatic 331	o/O:$$d	(IIS)Ljava/lang/String;
    //   2417: invokestatic 335	java/lang/Class:forName	(Ljava/lang/String;)Ljava/lang/Class;
    //   2420: astore 11
    //   2422: goto +1926 -> 4348
    //   2425: aload 18
    //   2427: iconst_0
    //   2428: saload
    //   2429: i2b
    //   2430: istore_3
    //   2431: sipush 339
    //   2434: iload_3
    //   2435: iload_3
    //   2436: sipush 608
    //   2439: ixor
    //   2440: iload_3
    //   2441: sipush 608
    //   2444: iand
    //   2445: ior
    //   2446: i2s
    //   2447: invokestatic 331	o/O:$$d	(IIS)Ljava/lang/String;
    //   2450: invokestatic 335	java/lang/Class:forName	(Ljava/lang/String;)Ljava/lang/Class;
    //   2453: astore 18
    //   2455: goto -1259 -> 1196
    //   2458: getstatic 28	o/O:ʽॱ	I
    //   2461: iconst_5
    //   2462: iadd
    //   2463: istore_1
    //   2464: iload_1
    //   2465: sipush 128
    //   2468: irem
    //   2469: putstatic 30	o/O:ʼॱ	I
    //   2472: iload_1
    //   2473: iconst_2
    //   2474: irem
    //   2475: ifne +6 -> 2481
    //   2478: goto -1648 -> 830
    //   2481: goto +6885 -> 9366
    //   2484: getstatic 30	o/O:ʼॱ	I
    //   2487: istore_1
    //   2488: iload_1
    //   2489: bipush 85
    //   2491: iand
    //   2492: iload_1
    //   2493: bipush 85
    //   2495: ior
    //   2496: iadd
    //   2497: istore_1
    //   2498: iload_1
    //   2499: sipush 128
    //   2502: irem
    //   2503: putstatic 28	o/O:ʽॱ	I
    //   2506: iload_1
    //   2507: iconst_2
    //   2508: irem
    //   2509: ifeq +6 -> 2515
    //   2512: goto -170 -> 2342
    //   2515: goto -118 -> 2397
    //   2518: aload 13
    //   2520: iconst_0
    //   2521: aload 15
    //   2523: invokestatic 335	java/lang/Class:forName	(Ljava/lang/String;)Ljava/lang/Class;
    //   2526: aastore
    //   2527: aload 13
    //   2529: iconst_0
    //   2530: ldc_w 312
    //   2533: aastore
    //   2534: aload 11
    //   2536: aload 13
    //   2538: invokevirtual 339	java/lang/Class:getDeclaredConstructor	([Ljava/lang/Class;)Ljava/lang/reflect/Constructor;
    //   2541: astore 11
    //   2543: goto -329 -> 2214
    //   2546: aload 10
    //   2548: athrow
    //   2549: aload 12
    //   2551: iconst_2
    //   2552: anewarray 329	java/lang/Class
    //   2555: dup
    //   2556: iconst_0
    //   2557: aload 13
    //   2559: aastore
    //   2560: dup
    //   2561: iconst_1
    //   2562: ldc_w 312
    //   2565: aastore
    //   2566: invokevirtual 339	java/lang/Class:getDeclaredConstructor	([Ljava/lang/Class;)Ljava/lang/reflect/Constructor;
    //   2569: iconst_2
    //   2570: anewarray 4	java/lang/Object
    //   2573: dup
    //   2574: iconst_0
    //   2575: aload 10
    //   2577: aastore
    //   2578: dup
    //   2579: iconst_1
    //   2580: aload 11
    //   2582: aastore
    //   2583: invokevirtual 404	java/lang/reflect/Constructor:newInstance	([Ljava/lang/Object;)Ljava/lang/Object;
    //   2586: astore 14
    //   2588: goto -2355 -> 233
    //   2591: getstatic 310	o/O:ʿ	[S
    //   2594: bipush 16
    //   2596: saload
    //   2597: istore_1
    //   2598: iload_1
    //   2599: i2b
    //   2600: istore_1
    //   2601: goto +8847 -> 11448
    //   2604: astore 10
    //   2606: aload 10
    //   2608: invokevirtual 349	java/lang/Throwable:getCause	()Ljava/lang/Throwable;
    //   2611: astore 11
    //   2613: aload 11
    //   2615: ifnull +6 -> 2621
    //   2618: goto +6683 -> 9301
    //   2621: goto +8085 -> 10706
    //   2624: goto -2585 -> 39
    //   2627: sipush 258
    //   2630: iload_3
    //   2631: aload 13
    //   2633: bipush 24
    //   2635: saload
    //   2636: i2s
    //   2637: invokestatic 331	o/O:$$d	(IIS)Ljava/lang/String;
    //   2640: astore 13
    //   2642: getstatic 310	o/O:ʿ	[S
    //   2645: astore 18
    //   2647: goto +1578 -> 4225
    //   2650: aload 14
    //   2652: ifnonnull +6 -> 2658
    //   2655: goto +6236 -> 8891
    //   2658: goto -2289 -> 369
    //   2661: astore 10
    //   2663: aload 10
    //   2665: invokevirtual 349	java/lang/Throwable:getCause	()Ljava/lang/Throwable;
    //   2668: astore 11
    //   2670: aload 11
    //   2672: ifnull +6 -> 2678
    //   2675: goto +7648 -> 10323
    //   2678: goto +7430 -> 10108
    //   2681: iload_1
    //   2682: tableswitch	default:+22->2704, 0:+-1635->1047, 1:+8192->10874
    //   2704: goto -1657 -> 1047
    //   2707: bipush 99
    //   2709: istore_1
    //   2710: goto +2369 -> 5079
    //   2713: getstatic 310	o/O:ʿ	[S
    //   2716: bipush 66
    //   2718: saload
    //   2719: i2s
    //   2720: istore_3
    //   2721: getstatic 310	o/O:ʿ	[S
    //   2724: astore 11
    //   2726: goto +7417 -> 10143
    //   2729: astore 10
    //   2731: aload 10
    //   2733: invokevirtual 349	java/lang/Throwable:getCause	()Ljava/lang/Throwable;
    //   2736: astore 11
    //   2738: aload 11
    //   2740: ifnull +6 -> 2746
    //   2743: goto +6767 -> 9510
    //   2746: goto +1579 -> 4325
    //   2749: sipush 393
    //   2752: iload_1
    //   2753: sipush 612
    //   2756: invokestatic 331	o/O:$$d	(IIS)Ljava/lang/String;
    //   2759: invokestatic 335	java/lang/Class:forName	(Ljava/lang/String;)Ljava/lang/Class;
    //   2762: astore 11
    //   2764: getstatic 310	o/O:ʿ	[S
    //   2767: iconst_3
    //   2768: saload
    //   2769: istore_1
    //   2770: iload_1
    //   2771: ineg
    //   2772: istore_1
    //   2773: goto +8143 -> 10916
    //   2776: aload 11
    //   2778: aload 13
    //   2780: iconst_3
    //   2781: anewarray 4	java/lang/Object
    //   2784: dup
    //   2785: iconst_0
    //   2786: aload 14
    //   2788: aastore
    //   2789: dup
    //   2790: iconst_1
    //   2791: aload 12
    //   2793: aastore
    //   2794: dup
    //   2795: iconst_2
    //   2796: iconst_1
    //   2797: invokestatic 413	java/lang/Boolean:valueOf	(Z)Ljava/lang/Boolean;
    //   2800: aastore
    //   2801: invokevirtual 376	java/lang/reflect/Method:invoke	(Ljava/lang/Object;[Ljava/lang/Object;)Ljava/lang/Object;
    //   2804: pop
    //   2805: goto -800 -> 2005
    //   2808: goto -2205 -> 603
    //   2811: ldc_w 414
    //   2814: newarray byte
    //   2816: astore 11
    //   2818: goto +7690 -> 10508
    //   2821: aload 11
    //   2823: sipush 268
    //   2826: aload 13
    //   2828: bipush 107
    //   2830: saload
    //   2831: i2b
    //   2832: sipush 618
    //   2835: invokestatic 331	o/O:$$d	(IIS)Ljava/lang/String;
    //   2838: aconst_null
    //   2839: invokevirtual 393	java/lang/Class:getMethod	(Ljava/lang/String;[Ljava/lang/Class;)Ljava/lang/reflect/Method;
    //   2842: astore 11
    //   2844: goto +1463 -> 4307
    //   2847: iconst_0
    //   2848: istore_1
    //   2849: goto +2168 -> 5017
    //   2852: aload 11
    //   2854: invokevirtual 418	java/lang/Long:longValue	()J
    //   2857: lstore 8
    //   2859: goto +7509 -> 10368
    //   2862: astore 10
    //   2864: aload 10
    //   2866: athrow
    //   2867: getstatic 383	java/lang/Integer:TYPE	Ljava/lang/Class;
    //   2870: astore 18
    //   2872: goto +722 -> 3594
    //   2875: iconst_0
    //   2876: istore_1
    //   2877: goto +906 -> 3783
    //   2880: iload_3
    //   2881: lookupswitch	default:+27->2908, 2:+2045->4926, 4:+123->3004
    //   2908: goto +2018 -> 4926
    //   2911: astore 10
    //   2913: aload 10
    //   2915: invokevirtual 349	java/lang/Throwable:getCause	()Ljava/lang/Throwable;
    //   2918: astore 11
    //   2920: aload 11
    //   2922: ifnull +6 -> 2928
    //   2925: goto +6279 -> 9204
    //   2928: goto -2101 -> 827
    //   2931: aload 12
    //   2933: iconst_0
    //   2934: aload 10
    //   2936: aastore
    //   2937: sipush 393
    //   2940: i2s
    //   2941: istore_1
    //   2942: getstatic 310	o/O:ʿ	[S
    //   2945: astore 11
    //   2947: sipush 142
    //   2950: istore_2
    //   2951: goto -546 -> 2405
    //   2954: iconst_0
    //   2955: istore_1
    //   2956: goto +6028 -> 8984
    //   2959: goto +5887 -> 8846
    //   2962: astore 10
    //   2964: aload 10
    //   2966: invokevirtual 349	java/lang/Throwable:getCause	()Ljava/lang/Throwable;
    //   2969: astore 11
    //   2971: aload 11
    //   2973: ifnull +6 -> 2979
    //   2976: goto -1833 -> 1143
    //   2979: goto +7030 -> 10009
    //   2982: getstatic 310	o/O:ʿ	[S
    //   2985: sipush 142
    //   2988: saload
    //   2989: istore_1
    //   2990: iload_1
    //   2991: i2b
    //   2992: istore_1
    //   2993: goto -802 -> 2191
    //   2996: getstatic 310	o/O:ʿ	[S
    //   2999: astore 11
    //   3001: goto +1741 -> 4742
    //   3004: aload 18
    //   3006: aload 11
    //   3008: aload 13
    //   3010: invokevirtual 376	java/lang/reflect/Method:invoke	(Ljava/lang/Object;[Ljava/lang/Object;)Ljava/lang/Object;
    //   3013: pop
    //   3014: iload_1
    //   3015: iload 4
    //   3017: ishr
    //   3018: istore_1
    //   3019: goto -975 -> 2044
    //   3022: aload 11
    //   3024: bipush 6
    //   3026: saload
    //   3027: i2b
    //   3028: istore_1
    //   3029: sipush 408
    //   3032: iload_1
    //   3033: iload_1
    //   3034: sipush 584
    //   3037: ixor
    //   3038: iload_1
    //   3039: sipush 584
    //   3042: iand
    //   3043: ior
    //   3044: i2s
    //   3045: invokestatic 331	o/O:$$d	(IIS)Ljava/lang/String;
    //   3048: astore 17
    //   3050: goto +5752 -> 8802
    //   3053: astore 10
    //   3055: aload 10
    //   3057: invokevirtual 349	java/lang/Throwable:getCause	()Ljava/lang/Throwable;
    //   3060: astore 11
    //   3062: aload 11
    //   3064: ifnull +6 -> 3070
    //   3067: goto -2090 -> 977
    //   3070: goto -2779 -> 291
    //   3073: astore 10
    //   3075: new 295	java/lang/RuntimeException
    //   3078: dup
    //   3079: aload 10
    //   3081: invokespecial 421	java/lang/RuntimeException:<init>	(Ljava/lang/Throwable;)V
    //   3084: athrow
    //   3085: iload 5
    //   3087: sipush 576
    //   3090: ixor
    //   3091: iload 5
    //   3093: sipush 576
    //   3096: iand
    //   3097: ior
    //   3098: i2s
    //   3099: istore_0
    //   3100: iload_3
    //   3101: iload 5
    //   3103: iload_0
    //   3104: invokestatic 331	o/O:$$d	(IIS)Ljava/lang/String;
    //   3107: astore 19
    //   3109: goto +7344 -> 10453
    //   3112: getstatic 378	o/O:ॱˋ	Ljava/lang/Object;
    //   3115: astore 11
    //   3117: goto +283 -> 3400
    //   3120: iconst_1
    //   3121: istore_1
    //   3122: goto -441 -> 2681
    //   3125: iload_2
    //   3126: invokestatic 427	java/lang/Math:abs	(I)I
    //   3129: istore_2
    //   3130: goto +8393 -> 11523
    //   3133: goto -2830 -> 303
    //   3136: getstatic 310	o/O:ʿ	[S
    //   3139: bipush 31
    //   3141: saload
    //   3142: i2b
    //   3143: istore_1
    //   3144: aload 10
    //   3146: aload 13
    //   3148: iconst_1
    //   3149: anewarray 4	java/lang/Object
    //   3152: dup
    //   3153: iconst_0
    //   3154: sipush 286
    //   3157: iload_1
    //   3158: iload_1
    //   3159: sipush 641
    //   3162: ixor
    //   3163: iload_1
    //   3164: sipush 641
    //   3167: iand
    //   3168: ior
    //   3169: i2s
    //   3170: invokestatic 331	o/O:$$d	(IIS)Ljava/lang/String;
    //   3173: aastore
    //   3174: invokevirtual 376	java/lang/reflect/Method:invoke	(Ljava/lang/Object;[Ljava/lang/Object;)Ljava/lang/Object;
    //   3177: checkcast 312	java/lang/String
    //   3180: astore 12
    //   3182: getstatic 310	o/O:ʿ	[S
    //   3185: bipush 31
    //   3187: saload
    //   3188: i2b
    //   3189: istore_1
    //   3190: aload 11
    //   3192: aload 13
    //   3194: iconst_3
    //   3195: anewarray 4	java/lang/Object
    //   3198: dup
    //   3199: iconst_0
    //   3200: sipush 286
    //   3203: iload_1
    //   3204: iload_1
    //   3205: sipush 641
    //   3208: ior
    //   3209: i2s
    //   3210: invokestatic 331	o/O:$$d	(IIS)Ljava/lang/String;
    //   3213: aastore
    //   3214: dup
    //   3215: iconst_1
    //   3216: getstatic 429	o/O:ˈ	I
    //   3219: sipush 495
    //   3222: iand
    //   3223: i2s
    //   3224: getstatic 310	o/O:ʿ	[S
    //   3227: sipush 368
    //   3230: saload
    //   3231: i2b
    //   3232: sipush 676
    //   3235: invokestatic 331	o/O:$$d	(IIS)Ljava/lang/String;
    //   3238: aastore
    //   3239: dup
    //   3240: iconst_2
    //   3241: iconst_1
    //   3242: invokestatic 413	java/lang/Boolean:valueOf	(Z)Ljava/lang/Boolean;
    //   3245: aastore
    //   3246: invokevirtual 376	java/lang/reflect/Method:invoke	(Ljava/lang/Object;[Ljava/lang/Object;)Ljava/lang/Object;
    //   3249: pop
    //   3250: goto +7881 -> 11131
    //   3253: getstatic 310	o/O:ʿ	[S
    //   3256: iconst_0
    //   3257: saload
    //   3258: i2b
    //   3259: istore_1
    //   3260: sipush 339
    //   3263: iload_1
    //   3264: iload_1
    //   3265: sipush 608
    //   3268: ixor
    //   3269: iload_1
    //   3270: sipush 608
    //   3273: iand
    //   3274: ior
    //   3275: i2s
    //   3276: invokestatic 331	o/O:$$d	(IIS)Ljava/lang/String;
    //   3279: invokestatic 335	java/lang/Class:forName	(Ljava/lang/String;)Ljava/lang/Class;
    //   3282: sipush 277
    //   3285: getstatic 310	o/O:ʿ	[S
    //   3288: bipush 6
    //   3290: saload
    //   3291: i2b
    //   3292: sipush 619
    //   3295: invokestatic 331	o/O:$$d	(IIS)Ljava/lang/String;
    //   3298: aconst_null
    //   3299: invokevirtual 393	java/lang/Class:getMethod	(Ljava/lang/String;[Ljava/lang/Class;)Ljava/lang/reflect/Method;
    //   3302: aload 12
    //   3304: aconst_null
    //   3305: invokevirtual 376	java/lang/reflect/Method:invoke	(Ljava/lang/Object;[Ljava/lang/Object;)Ljava/lang/Object;
    //   3308: pop
    //   3309: goto -3066 -> 243
    //   3312: astore 10
    //   3314: aload 10
    //   3316: invokevirtual 349	java/lang/Throwable:getCause	()Ljava/lang/Throwable;
    //   3319: astore 12
    //   3321: aload 12
    //   3323: ifnull +6 -> 3329
    //   3326: goto +5384 -> 8710
    //   3329: goto +7631 -> 10960
    //   3332: astore 10
    //   3334: aload 10
    //   3336: invokevirtual 349	java/lang/Throwable:getCause	()Ljava/lang/Throwable;
    //   3339: astore 11
    //   3341: aload 11
    //   3343: ifnull +6 -> 3349
    //   3346: goto -2575 -> 771
    //   3349: goto +211 -> 3560
    //   3352: goto +6987 -> 10339
    //   3355: aload 11
    //   3357: athrow
    //   3358: goto +5903 -> 9261
    //   3361: aload 11
    //   3363: athrow
    //   3364: getstatic 28	o/O:ʽॱ	I
    //   3367: istore_1
    //   3368: iload_1
    //   3369: bipush 57
    //   3371: ior
    //   3372: iconst_1
    //   3373: ishl
    //   3374: iload_1
    //   3375: bipush 57
    //   3377: ixor
    //   3378: isub
    //   3379: istore_1
    //   3380: iload_1
    //   3381: sipush 128
    //   3384: irem
    //   3385: putstatic 30	o/O:ʼॱ	I
    //   3388: iload_1
    //   3389: iconst_2
    //   3390: irem
    //   3391: ifne +6 -> 3397
    //   3394: goto +691 -> 4085
    //   3397: goto +7303 -> 10700
    //   3400: goto -1036 -> 2364
    //   3403: aload 11
    //   3405: astore 10
    //   3407: iload_1
    //   3408: tableswitch	default:+24->3432, 0:+743->4151, 1:+8018->11426
    //   3432: aload 11
    //   3434: astore 10
    //   3436: goto +715 -> 4151
    //   3439: sipush 393
    //   3442: getstatic 310	o/O:ʿ	[S
    //   3445: sipush 142
    //   3448: saload
    //   3449: i2b
    //   3450: sipush 612
    //   3453: invokestatic 331	o/O:$$d	(IIS)Ljava/lang/String;
    //   3456: invokestatic 335	java/lang/Class:forName	(Ljava/lang/String;)Ljava/lang/Class;
    //   3459: sipush 325
    //   3462: getstatic 310	o/O:ʿ	[S
    //   3465: bipush 9
    //   3467: saload
    //   3468: i2b
    //   3469: sipush 615
    //   3472: invokestatic 331	o/O:$$d	(IIS)Ljava/lang/String;
    //   3475: aconst_null
    //   3476: invokevirtual 393	java/lang/Class:getMethod	(Ljava/lang/String;[Ljava/lang/Class;)Ljava/lang/reflect/Method;
    //   3479: aload 15
    //   3481: aconst_null
    //   3482: invokevirtual 376	java/lang/reflect/Method:invoke	(Ljava/lang/Object;[Ljava/lang/Object;)Ljava/lang/Object;
    //   3485: astore 10
    //   3487: goto -1397 -> 2090
    //   3490: aload 11
    //   3492: athrow
    //   3493: sipush 428
    //   3496: getstatic 310	o/O:ʿ	[S
    //   3499: bipush 61
    //   3501: saload
    //   3502: i2b
    //   3503: sipush 612
    //   3506: invokestatic 331	o/O:$$d	(IIS)Ljava/lang/String;
    //   3509: invokestatic 335	java/lang/Class:forName	(Ljava/lang/String;)Ljava/lang/Class;
    //   3512: astore 10
    //   3514: getstatic 310	o/O:ʿ	[S
    //   3517: sipush 354
    //   3520: saload
    //   3521: i2b
    //   3522: istore_1
    //   3523: aload 10
    //   3525: bipush 96
    //   3527: iload_1
    //   3528: iload_1
    //   3529: sipush 579
    //   3532: ixor
    //   3533: iload_1
    //   3534: sipush 579
    //   3537: iand
    //   3538: ior
    //   3539: i2s
    //   3540: invokestatic 331	o/O:$$d	(IIS)Ljava/lang/String;
    //   3543: aconst_null
    //   3544: invokevirtual 393	java/lang/Class:getMethod	(Ljava/lang/String;[Ljava/lang/Class;)Ljava/lang/reflect/Method;
    //   3547: aload 12
    //   3549: aconst_null
    //   3550: invokevirtual 376	java/lang/reflect/Method:invoke	(Ljava/lang/Object;[Ljava/lang/Object;)Ljava/lang/Object;
    //   3553: pop
    //   3554: goto +132 -> 3686
    //   3557: aload 10
    //   3559: athrow
    //   3560: aload 10
    //   3562: athrow
    //   3563: aload 11
    //   3565: aconst_null
    //   3566: invokevirtual 404	java/lang/reflect/Constructor:newInstance	([Ljava/lang/Object;)Ljava/lang/Object;
    //   3569: astore 16
    //   3571: goto +6342 -> 9913
    //   3574: astore 10
    //   3576: aload 10
    //   3578: invokevirtual 349	java/lang/Throwable:getCause	()Ljava/lang/Throwable;
    //   3581: astore 19
    //   3583: aload 19
    //   3585: ifnull +6 -> 3591
    //   3588: goto +6954 -> 10542
    //   3591: goto -2250 -> 1341
    //   3594: aload 13
    //   3596: aload 19
    //   3598: iconst_3
    //   3599: anewarray 329	java/lang/Class
    //   3602: dup
    //   3603: iconst_0
    //   3604: ldc_w 379
    //   3607: aastore
    //   3608: dup
    //   3609: iconst_1
    //   3610: aload 18
    //   3612: aastore
    //   3613: dup
    //   3614: iconst_2
    //   3615: getstatic 383	java/lang/Integer:TYPE	Ljava/lang/Class;
    //   3618: aastore
    //   3619: invokevirtual 393	java/lang/Class:getMethod	(Ljava/lang/String;[Ljava/lang/Class;)Ljava/lang/reflect/Method;
    //   3622: aload 10
    //   3624: iconst_3
    //   3625: anewarray 4	java/lang/Object
    //   3628: dup
    //   3629: iconst_0
    //   3630: aload 12
    //   3632: aastore
    //   3633: dup
    //   3634: iconst_1
    //   3635: iconst_0
    //   3636: invokestatic 369	java/lang/Integer:valueOf	(I)Ljava/lang/Integer;
    //   3639: aastore
    //   3640: dup
    //   3641: iconst_2
    //   3642: iload 4
    //   3644: invokestatic 369	java/lang/Integer:valueOf	(I)Ljava/lang/Integer;
    //   3647: aastore
    //   3648: invokevirtual 376	java/lang/reflect/Method:invoke	(Ljava/lang/Object;[Ljava/lang/Object;)Ljava/lang/Object;
    //   3651: astore 13
    //   3653: goto -3636 -> 17
    //   3656: goto +7310 -> 10966
    //   3659: getstatic 30	o/O:ʼॱ	I
    //   3662: bipush 79
    //   3664: iadd
    //   3665: istore_1
    //   3666: iload_1
    //   3667: sipush 128
    //   3670: irem
    //   3671: putstatic 28	o/O:ʽॱ	I
    //   3674: iload_1
    //   3675: iconst_2
    //   3676: irem
    //   3677: ifeq +6 -> 3683
    //   3680: goto -1344 -> 2336
    //   3683: goto +1132 -> 4815
    //   3686: getstatic 310	o/O:ʿ	[S
    //   3689: iconst_0
    //   3690: saload
    //   3691: i2b
    //   3692: istore_1
    //   3693: sipush 339
    //   3696: iload_1
    //   3697: iload_1
    //   3698: sipush 608
    //   3701: ixor
    //   3702: iload_1
    //   3703: sipush 608
    //   3706: iand
    //   3707: ior
    //   3708: i2s
    //   3709: invokestatic 331	o/O:$$d	(IIS)Ljava/lang/String;
    //   3712: invokestatic 335	java/lang/Class:forName	(Ljava/lang/String;)Ljava/lang/Class;
    //   3715: sipush 277
    //   3718: getstatic 310	o/O:ʿ	[S
    //   3721: bipush 6
    //   3723: saload
    //   3724: i2b
    //   3725: sipush 619
    //   3728: invokestatic 331	o/O:$$d	(IIS)Ljava/lang/String;
    //   3731: aconst_null
    //   3732: invokevirtual 393	java/lang/Class:getMethod	(Ljava/lang/String;[Ljava/lang/Class;)Ljava/lang/reflect/Method;
    //   3735: aload 11
    //   3737: aconst_null
    //   3738: invokevirtual 376	java/lang/reflect/Method:invoke	(Ljava/lang/Object;[Ljava/lang/Object;)Ljava/lang/Object;
    //   3741: pop
    //   3742: aconst_null
    //   3743: astore 23
    //   3745: aconst_null
    //   3746: astore 13
    //   3748: aconst_null
    //   3749: astore 22
    //   3751: aconst_null
    //   3752: astore 20
    //   3754: aconst_null
    //   3755: astore 18
    //   3757: aconst_null
    //   3758: astore 21
    //   3760: aconst_null
    //   3761: astore 19
    //   3763: goto -1388 -> 2375
    //   3766: getstatic 310	o/O:ʿ	[S
    //   3769: sipush 142
    //   3772: saload
    //   3773: istore_1
    //   3774: iload_1
    //   3775: i2b
    //   3776: istore_1
    //   3777: goto -1028 -> 2749
    //   3780: goto -1156 -> 2624
    //   3783: aload 18
    //   3785: astore 10
    //   3787: iload_1
    //   3788: tableswitch	default:+24->3812, 0:+6548->10336, 1:+1260->5048
    //   3812: aload 18
    //   3814: astore 10
    //   3816: goto +1232 -> 5048
    //   3819: aload 10
    //   3821: athrow
    //   3822: getstatic 310	o/O:ʿ	[S
    //   3825: sipush 192
    //   3828: saload
    //   3829: i2b
    //   3830: istore_2
    //   3831: getstatic 429	o/O:ˈ	I
    //   3834: istore_3
    //   3835: goto +6970 -> 10805
    //   3838: aload 10
    //   3840: athrow
    //   3841: aload 10
    //   3843: athrow
    //   3844: aload 10
    //   3846: iload_2
    //   3847: sipush 13912
    //   3850: iadd
    //   3851: iconst_1
    //   3852: isub
    //   3853: baload
    //   3854: istore_3
    //   3855: aload 10
    //   3857: iload_2
    //   3858: sipush 726
    //   3861: ixor
    //   3862: iload_2
    //   3863: sipush 726
    //   3866: iand
    //   3867: iconst_1
    //   3868: ishl
    //   3869: iadd
    //   3870: iload_3
    //   3871: bipush 22
    //   3873: ior
    //   3874: iconst_1
    //   3875: ishl
    //   3876: iload_3
    //   3877: bipush 22
    //   3879: ixor
    //   3880: isub
    //   3881: i2b
    //   3882: bastore
    //   3883: aload 10
    //   3885: arraylength
    //   3886: istore 4
    //   3888: goto +6438 -> 10326
    //   3891: getstatic 310	o/O:ʿ	[S
    //   3894: bipush 60
    //   3896: saload
    //   3897: i2s
    //   3898: istore_1
    //   3899: getstatic 310	o/O:ʿ	[S
    //   3902: bipush 31
    //   3904: saload
    //   3905: istore_2
    //   3906: goto -2451 -> 1455
    //   3909: aload 12
    //   3911: iconst_1
    //   3912: anewarray 329	java/lang/Class
    //   3915: dup
    //   3916: iconst_0
    //   3917: aload 11
    //   3919: invokestatic 335	java/lang/Class:forName	(Ljava/lang/String;)Ljava/lang/Class;
    //   3922: aastore
    //   3923: invokevirtual 339	java/lang/Class:getDeclaredConstructor	([Ljava/lang/Class;)Ljava/lang/reflect/Constructor;
    //   3926: iconst_1
    //   3927: anewarray 4	java/lang/Object
    //   3930: dup
    //   3931: iconst_0
    //   3932: aload 14
    //   3934: aastore
    //   3935: invokevirtual 404	java/lang/reflect/Constructor:newInstance	([Ljava/lang/Object;)Ljava/lang/Object;
    //   3938: astore 11
    //   3940: goto -3926 -> 14
    //   3943: aload 11
    //   3945: iconst_1
    //   3946: invokevirtual 433	java/lang/reflect/Constructor:setAccessible	(Z)V
    //   3949: goto +7162 -> 11111
    //   3952: sipush 200
    //   3955: aload 21
    //   3957: sipush 192
    //   3960: saload
    //   3961: i2b
    //   3962: sipush 610
    //   3965: invokestatic 331	o/O:$$d	(IIS)Ljava/lang/String;
    //   3968: astore 22
    //   3970: goto -1486 -> 2484
    //   3973: getstatic 310	o/O:ʿ	[S
    //   3976: sipush 368
    //   3979: saload
    //   3980: i2b
    //   3981: istore_1
    //   3982: bipush 99
    //   3984: iload_1
    //   3985: iload_1
    //   3986: sipush 582
    //   3989: ior
    //   3990: i2s
    //   3991: invokestatic 331	o/O:$$d	(IIS)Ljava/lang/String;
    //   3994: astore 17
    //   3996: goto -3233 -> 763
    //   3999: aload 13
    //   4001: astore 11
    //   4003: aload 20
    //   4005: astore 10
    //   4007: aload 12
    //   4009: aconst_null
    //   4010: invokevirtual 439	java/lang/reflect/Field:get	(Ljava/lang/Object;)Ljava/lang/Object;
    //   4013: astore 13
    //   4015: aload 13
    //   4017: ifnull +6 -> 4023
    //   4020: goto -2179 -> 1841
    //   4023: goto +515 -> 4538
    //   4026: astore 10
    //   4028: new 441	java/lang/StringBuilder
    //   4031: dup
    //   4032: invokespecial 442	java/lang/StringBuilder:<init>	()V
    //   4035: bipush 101
    //   4037: getstatic 310	o/O:ʿ	[S
    //   4040: bipush 6
    //   4042: saload
    //   4043: i2b
    //   4044: sipush 649
    //   4047: invokestatic 331	o/O:$$d	(IIS)Ljava/lang/String;
    //   4050: invokevirtual 446	java/lang/StringBuilder:append	(Ljava/lang/String;)Ljava/lang/StringBuilder;
    //   4053: aload 14
    //   4055: invokevirtual 449	java/lang/StringBuilder:append	(Ljava/lang/Object;)Ljava/lang/StringBuilder;
    //   4058: bipush 76
    //   4060: getstatic 310	o/O:ʿ	[S
    //   4063: sipush 166
    //   4066: saload
    //   4067: i2b
    //   4068: sipush 677
    //   4071: invokestatic 331	o/O:$$d	(IIS)Ljava/lang/String;
    //   4074: invokevirtual 446	java/lang/StringBuilder:append	(Ljava/lang/String;)Ljava/lang/StringBuilder;
    //   4077: invokevirtual 453	java/lang/StringBuilder:toString	()Ljava/lang/String;
    //   4080: astore 11
    //   4082: goto -1805 -> 2277
    //   4085: bipush 22
    //   4087: istore_1
    //   4088: goto -2662 -> 1426
    //   4091: aload 10
    //   4093: athrow
    //   4094: aload 10
    //   4096: aload 14
    //   4098: aconst_null
    //   4099: invokevirtual 376	java/lang/reflect/Method:invoke	(Ljava/lang/Object;[Ljava/lang/Object;)Ljava/lang/Object;
    //   4102: astore 19
    //   4104: goto +5103 -> 9207
    //   4107: aload 11
    //   4109: invokestatic 335	java/lang/Class:forName	(Ljava/lang/String;)Ljava/lang/Class;
    //   4112: iconst_1
    //   4113: anewarray 329	java/lang/Class
    //   4116: dup
    //   4117: iconst_0
    //   4118: ldc_w 312
    //   4121: aastore
    //   4122: invokevirtual 339	java/lang/Class:getDeclaredConstructor	([Ljava/lang/Class;)Ljava/lang/reflect/Constructor;
    //   4125: astore 11
    //   4127: goto +348 -> 4475
    //   4130: sipush 393
    //   4133: aload 15
    //   4135: sipush 142
    //   4138: saload
    //   4139: i2b
    //   4140: sipush 612
    //   4143: invokestatic 331	o/O:$$d	(IIS)Ljava/lang/String;
    //   4146: astore 15
    //   4148: goto -3034 -> 1114
    //   4151: goto -2232 -> 1919
    //   4154: astore 10
    //   4156: aload 10
    //   4158: invokevirtual 349	java/lang/Throwable:getCause	()Ljava/lang/Throwable;
    //   4161: astore 11
    //   4163: aload 11
    //   4165: ifnull +6 -> 4171
    //   4168: goto -3990 -> 178
    //   4171: goto +7128 -> 11299
    //   4174: aload 10
    //   4176: athrow
    //   4177: aload 11
    //   4179: athrow
    //   4180: goto -3323 -> 857
    //   4183: iconst_3
    //   4184: anewarray 4	java/lang/Object
    //   4187: astore 13
    //   4189: aload 13
    //   4191: iconst_2
    //   4192: iload 4
    //   4194: invokestatic 369	java/lang/Integer:valueOf	(I)Ljava/lang/Integer;
    //   4197: aastore
    //   4198: goto -2092 -> 2106
    //   4201: goto -3818 -> 383
    //   4204: aload 11
    //   4206: checkcast 406	java/lang/Boolean
    //   4209: invokevirtual 410	java/lang/Boolean:booleanValue	()Z
    //   4212: istore 7
    //   4214: iload 7
    //   4216: ifeq +6 -> 4222
    //   4219: goto -2211 -> 2008
    //   4222: goto -3470 -> 752
    //   4225: sipush 457
    //   4228: aload 18
    //   4230: bipush 11
    //   4232: saload
    //   4233: i2b
    //   4234: sipush 612
    //   4237: invokestatic 331	o/O:$$d	(IIS)Ljava/lang/String;
    //   4240: invokestatic 335	java/lang/Class:forName	(Ljava/lang/String;)Ljava/lang/Class;
    //   4243: astore 18
    //   4245: getstatic 383	java/lang/Integer:TYPE	Ljava/lang/Class;
    //   4248: astore 19
    //   4250: goto -3331 -> 919
    //   4253: aload 10
    //   4255: ifnull +6 -> 4261
    //   4258: goto -1122 -> 3136
    //   4261: aload 19
    //   4263: astore 12
    //   4265: goto +6866 -> 11131
    //   4268: bipush 8
    //   4270: istore_1
    //   4271: goto -4019 -> 252
    //   4274: iload_1
    //   4275: tableswitch	default:+21->4296, 0:+7027->11302, 1:+-1757->2518
    //   4296: goto +7006 -> 11302
    //   4299: getstatic 310	o/O:ʿ	[S
    //   4302: astore 12
    //   4304: goto -2429 -> 1875
    //   4307: aload 11
    //   4309: aload 14
    //   4311: aconst_null
    //   4312: invokevirtual 376	java/lang/reflect/Method:invoke	(Ljava/lang/Object;[Ljava/lang/Object;)Ljava/lang/Object;
    //   4315: checkcast 406	java/lang/Boolean
    //   4318: invokevirtual 410	java/lang/Boolean:booleanValue	()Z
    //   4321: pop
    //   4322: goto +4689 -> 9011
    //   4325: aload 10
    //   4327: athrow
    //   4328: astore 10
    //   4330: aload 10
    //   4332: invokevirtual 349	java/lang/Throwable:getCause	()Ljava/lang/Throwable;
    //   4335: astore 11
    //   4337: aload 11
    //   4339: ifnull +6 -> 4345
    //   4342: goto -2191 -> 2151
    //   4345: goto -254 -> 4091
    //   4348: iconst_2
    //   4349: anewarray 329	java/lang/Class
    //   4352: astore 13
    //   4354: getstatic 310	o/O:ʿ	[S
    //   4357: astore 15
    //   4359: goto -229 -> 4130
    //   4362: aload 10
    //   4364: athrow
    //   4365: aload 11
    //   4367: athrow
    //   4368: aload 13
    //   4370: aload 10
    //   4372: iconst_1
    //   4373: anewarray 329	java/lang/Class
    //   4376: dup
    //   4377: iconst_0
    //   4378: ldc_w 379
    //   4381: aastore
    //   4382: invokevirtual 393	java/lang/Class:getMethod	(Ljava/lang/String;[Ljava/lang/Class;)Ljava/lang/reflect/Method;
    //   4385: aload 12
    //   4387: iconst_1
    //   4388: anewarray 4	java/lang/Object
    //   4391: dup
    //   4392: iconst_0
    //   4393: aload 11
    //   4395: aastore
    //   4396: invokevirtual 376	java/lang/reflect/Method:invoke	(Ljava/lang/Object;[Ljava/lang/Object;)Ljava/lang/Object;
    //   4399: pop
    //   4400: goto -3013 -> 1387
    //   4403: astore 10
    //   4405: aload 12
    //   4407: ifnull +6 -> 4413
    //   4410: goto -1058 -> 3352
    //   4413: goto -4266 -> 147
    //   4416: aload 11
    //   4418: iconst_3
    //   4419: anewarray 4	java/lang/Object
    //   4422: dup
    //   4423: iconst_0
    //   4424: aload 10
    //   4426: aastore
    //   4427: dup
    //   4428: iconst_1
    //   4429: iload_2
    //   4430: invokestatic 369	java/lang/Integer:valueOf	(I)Ljava/lang/Integer;
    //   4433: aastore
    //   4434: dup
    //   4435: iconst_2
    //   4436: iload 4
    //   4438: iload 6
    //   4440: ior
    //   4441: iload 4
    //   4443: iload 6
    //   4445: iand
    //   4446: iadd
    //   4447: invokestatic 369	java/lang/Integer:valueOf	(I)Ljava/lang/Integer;
    //   4450: aastore
    //   4451: invokevirtual 404	java/lang/reflect/Constructor:newInstance	([Ljava/lang/Object;)Ljava/lang/Object;
    //   4454: checkcast 455	java/io/InputStream
    //   4457: astore 10
    //   4459: getstatic 378	o/O:ॱˋ	Ljava/lang/Object;
    //   4462: astore 11
    //   4464: aload 11
    //   4466: ifnonnull +6 -> 4472
    //   4469: goto -4035 -> 434
    //   4472: goto -1360 -> 3112
    //   4475: getstatic 30	o/O:ʼॱ	I
    //   4478: istore_1
    //   4479: iload_1
    //   4480: bipush 31
    //   4482: iand
    //   4483: iload_1
    //   4484: bipush 31
    //   4486: ior
    //   4487: iadd
    //   4488: istore_1
    //   4489: iload_1
    //   4490: sipush 128
    //   4493: irem
    //   4494: putstatic 28	o/O:ʽॱ	I
    //   4497: iload_1
    //   4498: iconst_2
    //   4499: irem
    //   4500: ifeq +6 -> 4506
    //   4503: goto +5862 -> 10365
    //   4506: goto -2826 -> 1680
    //   4509: aload 11
    //   4511: iconst_1
    //   4512: invokevirtual 433	java/lang/reflect/Constructor:setAccessible	(Z)V
    //   4515: goto +265 -> 4780
    //   4518: astore 10
    //   4520: aload 10
    //   4522: invokevirtual 349	java/lang/Throwable:getCause	()Ljava/lang/Throwable;
    //   4525: astore 11
    //   4527: aload 11
    //   4529: ifnull +6 -> 4535
    //   4532: goto -355 -> 4177
    //   4535: goto +5691 -> 10226
    //   4538: bipush 95
    //   4540: istore_1
    //   4541: goto -4486 -> 55
    //   4544: goto -1831 -> 2713
    //   4547: aload 12
    //   4549: iconst_2
    //   4550: anewarray 329	java/lang/Class
    //   4553: dup
    //   4554: iconst_0
    //   4555: ldc_w 312
    //   4558: aastore
    //   4559: dup
    //   4560: iconst_1
    //   4561: ldc_w 345
    //   4564: aastore
    //   4565: invokevirtual 339	java/lang/Class:getDeclaredConstructor	([Ljava/lang/Class;)Ljava/lang/reflect/Constructor;
    //   4568: astore 12
    //   4570: goto +6264 -> 10834
    //   4573: sipush 393
    //   4576: getstatic 310	o/O:ʿ	[S
    //   4579: sipush 142
    //   4582: saload
    //   4583: i2b
    //   4584: sipush 612
    //   4587: invokestatic 331	o/O:$$d	(IIS)Ljava/lang/String;
    //   4590: astore 11
    //   4592: goto -683 -> 3909
    //   4595: getstatic 310	o/O:ʿ	[S
    //   4598: iconst_0
    //   4599: saload
    //   4600: i2b
    //   4601: istore_3
    //   4602: sipush 339
    //   4605: iload_3
    //   4606: iload_3
    //   4607: sipush 608
    //   4610: ixor
    //   4611: iload_3
    //   4612: sipush 608
    //   4615: iand
    //   4616: ior
    //   4617: i2s
    //   4618: invokestatic 331	o/O:$$d	(IIS)Ljava/lang/String;
    //   4621: astore 11
    //   4623: goto +5909 -> 10532
    //   4626: iload_1
    //   4627: tableswitch	default:+21->4648, 0:+-971->3656, 1:+-3263->1364
    //   4648: goto -992 -> 3656
    //   4651: goto -500 -> 4151
    //   4654: astore 10
    //   4656: aload 10
    //   4658: invokevirtual 349	java/lang/Throwable:getCause	()Ljava/lang/Throwable;
    //   4661: astore 11
    //   4663: aload 11
    //   4665: ifnull +6 -> 4671
    //   4668: goto -1178 -> 3490
    //   4671: goto +5344 -> 10015
    //   4674: aload 12
    //   4676: athrow
    //   4677: sipush 178
    //   4680: getstatic 310	o/O:ʿ	[S
    //   4683: bipush 80
    //   4685: saload
    //   4686: i2b
    //   4687: sipush 612
    //   4690: invokestatic 331	o/O:$$d	(IIS)Ljava/lang/String;
    //   4693: invokestatic 335	java/lang/Class:forName	(Ljava/lang/String;)Ljava/lang/Class;
    //   4696: iconst_1
    //   4697: anewarray 329	java/lang/Class
    //   4700: dup
    //   4701: iconst_0
    //   4702: sipush 457
    //   4705: getstatic 310	o/O:ʿ	[S
    //   4708: bipush 11
    //   4710: saload
    //   4711: i2b
    //   4712: sipush 612
    //   4715: invokestatic 331	o/O:$$d	(IIS)Ljava/lang/String;
    //   4718: invokestatic 335	java/lang/Class:forName	(Ljava/lang/String;)Ljava/lang/Class;
    //   4721: aastore
    //   4722: invokevirtual 339	java/lang/Class:getDeclaredConstructor	([Ljava/lang/Class;)Ljava/lang/reflect/Constructor;
    //   4725: iconst_1
    //   4726: anewarray 4	java/lang/Object
    //   4729: dup
    //   4730: iconst_0
    //   4731: aload 10
    //   4733: aastore
    //   4734: invokevirtual 404	java/lang/reflect/Constructor:newInstance	([Ljava/lang/Object;)Ljava/lang/Object;
    //   4737: astore 12
    //   4739: goto +4166 -> 8905
    //   4742: aload 11
    //   4744: bipush 54
    //   4746: saload
    //   4747: i2s
    //   4748: istore_1
    //   4749: getstatic 310	o/O:ʿ	[S
    //   4752: bipush 31
    //   4754: saload
    //   4755: istore_2
    //   4756: iload_2
    //   4757: i2b
    //   4758: istore_2
    //   4759: goto -2912 -> 1847
    //   4762: sipush 216
    //   4765: iload_1
    //   4766: sipush 621
    //   4769: invokestatic 331	o/O:$$d	(IIS)Ljava/lang/String;
    //   4772: invokestatic 335	java/lang/Class:forName	(Ljava/lang/String;)Ljava/lang/Class;
    //   4775: astore 10
    //   4777: goto -4440 -> 337
    //   4780: aload 11
    //   4782: iconst_1
    //   4783: anewarray 4	java/lang/Object
    //   4786: dup
    //   4787: iconst_0
    //   4788: aload 10
    //   4790: aastore
    //   4791: invokevirtual 404	java/lang/reflect/Constructor:newInstance	([Ljava/lang/Object;)Ljava/lang/Object;
    //   4794: putstatic 378	o/O:ॱˋ	Ljava/lang/Object;
    //   4797: return
    //   4798: getstatic 310	o/O:ʿ	[S
    //   4801: sipush 142
    //   4804: saload
    //   4805: istore_1
    //   4806: iload_1
    //   4807: i2b
    //   4808: istore_1
    //   4809: goto -3251 -> 1558
    //   4812: aload 11
    //   4814: athrow
    //   4815: sipush 314
    //   4818: aload 12
    //   4820: bipush 17
    //   4822: saload
    //   4823: i2b
    //   4824: sipush 615
    //   4827: invokestatic 331	o/O:$$d	(IIS)Ljava/lang/String;
    //   4830: astore 12
    //   4832: goto +6648 -> 11480
    //   4835: aload 11
    //   4837: sipush 412
    //   4840: iload_1
    //   4841: iload_0
    //   4842: invokestatic 331	o/O:$$d	(IIS)Ljava/lang/String;
    //   4845: aconst_null
    //   4846: invokevirtual 393	java/lang/Class:getMethod	(Ljava/lang/String;[Ljava/lang/Class;)Ljava/lang/reflect/Method;
    //   4849: aconst_null
    //   4850: aconst_null
    //   4851: invokevirtual 376	java/lang/reflect/Method:invoke	(Ljava/lang/Object;[Ljava/lang/Object;)Ljava/lang/Object;
    //   4854: checkcast 389	java/lang/Long
    //   4857: astore 11
    //   4859: goto -2007 -> 2852
    //   4862: new 441	java/lang/StringBuilder
    //   4865: dup
    //   4866: invokespecial 442	java/lang/StringBuilder:<init>	()V
    //   4869: astore 11
    //   4871: getstatic 310	o/O:ʿ	[S
    //   4874: bipush 17
    //   4876: saload
    //   4877: i2b
    //   4878: istore_1
    //   4879: aload 11
    //   4881: sipush 258
    //   4884: iload_1
    //   4885: iload_1
    //   4886: sipush 654
    //   4889: ixor
    //   4890: iload_1
    //   4891: sipush 654
    //   4894: iand
    //   4895: ior
    //   4896: i2s
    //   4897: invokestatic 331	o/O:$$d	(IIS)Ljava/lang/String;
    //   4900: invokevirtual 446	java/lang/StringBuilder:append	(Ljava/lang/String;)Ljava/lang/StringBuilder;
    //   4903: aload 10
    //   4905: invokevirtual 446	java/lang/StringBuilder:append	(Ljava/lang/String;)Ljava/lang/StringBuilder;
    //   4908: invokevirtual 453	java/lang/StringBuilder:toString	()Ljava/lang/String;
    //   4911: astore 10
    //   4913: goto -3075 -> 1838
    //   4916: aload 10
    //   4918: astore 11
    //   4920: goto +31 -> 4951
    //   4923: goto -4812 -> 111
    //   4926: aload 18
    //   4928: aload 11
    //   4930: aload 13
    //   4932: invokevirtual 376	java/lang/reflect/Method:invoke	(Ljava/lang/Object;[Ljava/lang/Object;)Ljava/lang/Object;
    //   4935: pop
    //   4936: iload 4
    //   4938: ineg
    //   4939: istore_3
    //   4940: iload_1
    //   4941: iload_3
    //   4942: iand
    //   4943: iload_3
    //   4944: iload_1
    //   4945: ior
    //   4946: iadd
    //   4947: istore_1
    //   4948: goto -2904 -> 2044
    //   4951: goto +4631 -> 9582
    //   4954: getstatic 310	o/O:ʿ	[S
    //   4957: iconst_0
    //   4958: saload
    //   4959: i2b
    //   4960: istore_1
    //   4961: sipush 339
    //   4964: iload_1
    //   4965: iload_1
    //   4966: sipush 608
    //   4969: ixor
    //   4970: iload_1
    //   4971: sipush 608
    //   4974: iand
    //   4975: ior
    //   4976: i2s
    //   4977: invokestatic 331	o/O:$$d	(IIS)Ljava/lang/String;
    //   4980: invokestatic 335	java/lang/Class:forName	(Ljava/lang/String;)Ljava/lang/Class;
    //   4983: sipush 273
    //   4986: getstatic 310	o/O:ʿ	[S
    //   4989: bipush 6
    //   4991: saload
    //   4992: i2b
    //   4993: sipush 615
    //   4996: invokestatic 331	o/O:$$d	(IIS)Ljava/lang/String;
    //   4999: aconst_null
    //   5000: invokevirtual 393	java/lang/Class:getMethod	(Ljava/lang/String;[Ljava/lang/Class;)Ljava/lang/reflect/Method;
    //   5003: aload 11
    //   5005: aconst_null
    //   5006: invokevirtual 376	java/lang/reflect/Method:invoke	(Ljava/lang/Object;[Ljava/lang/Object;)Ljava/lang/Object;
    //   5009: astore 12
    //   5011: goto -1518 -> 3493
    //   5014: aload 10
    //   5016: athrow
    //   5017: aload 18
    //   5019: astore 10
    //   5021: iload_1
    //   5022: tableswitch	default:+22->5044, 0:+26->5048, 1:+5687->10709
    //   5044: aload 18
    //   5046: astore 10
    //   5048: aload 10
    //   5050: ifnonnull +6 -> 5056
    //   5053: goto -2868 -> 2185
    //   5056: goto +4851 -> 9907
    //   5059: astore 10
    //   5061: aload 10
    //   5063: invokevirtual 349	java/lang/Throwable:getCause	()Ljava/lang/Throwable;
    //   5066: astore 11
    //   5068: aload 11
    //   5070: ifnull +6 -> 5076
    //   5073: goto -4313 -> 760
    //   5076: goto -5065 -> 11
    //   5079: iload_1
    //   5080: lookupswitch	default:+28->5108, 63:+-3263->1817, 99:+5149->10229
    //   5108: goto +5121 -> 10229
    //   5111: aload 10
    //   5113: athrow
    //   5114: aload 10
    //   5116: athrow
    //   5117: aload 10
    //   5119: athrow
    //   5120: goto +3989 -> 9109
    //   5123: aload 16
    //   5125: iconst_1
    //   5126: anewarray 329	java/lang/Class
    //   5129: dup
    //   5130: iconst_0
    //   5131: ldc 4
    //   5133: aastore
    //   5134: invokevirtual 339	java/lang/Class:getDeclaredConstructor	([Ljava/lang/Class;)Ljava/lang/reflect/Constructor;
    //   5137: astore 11
    //   5139: goto -630 -> 4509
    //   5142: iconst_4
    //   5143: istore_3
    //   5144: goto -2264 -> 2880
    //   5147: aload 23
    //   5149: astore 10
    //   5151: aload 22
    //   5153: astore 11
    //   5155: aload 21
    //   5157: astore 12
    //   5159: iload_1
    //   5160: tableswitch	default:+24->5184, 0:+-4180->980, 1:+-4979->181
    //   5184: aload 23
    //   5186: astore 10
    //   5188: aload 22
    //   5190: astore 11
    //   5192: aload 21
    //   5194: astore 12
    //   5196: goto -4216 -> 980
    //   5199: aload 11
    //   5201: athrow
    //   5202: iload_1
    //   5203: i2b
    //   5204: istore_1
    //   5205: aload 10
    //   5207: sipush 325
    //   5210: iload_1
    //   5211: sipush 615
    //   5214: invokestatic 331	o/O:$$d	(IIS)Ljava/lang/String;
    //   5217: aconst_null
    //   5218: invokevirtual 393	java/lang/Class:getMethod	(Ljava/lang/String;[Ljava/lang/Class;)Ljava/lang/reflect/Method;
    //   5221: aload 14
    //   5223: aconst_null
    //   5224: invokevirtual 376	java/lang/reflect/Method:invoke	(Ljava/lang/Object;[Ljava/lang/Object;)Ljava/lang/Object;
    //   5227: astore 11
    //   5229: goto +5778 -> 11007
    //   5232: aload 11
    //   5234: athrow
    //   5235: sipush 479
    //   5238: newarray short
    //   5240: dup
    //   5241: iconst_0
    //   5242: ldc 112
    //   5244: sastore
    //   5245: dup
    //   5246: iconst_1
    //   5247: ldc 89
    //   5249: sastore
    //   5250: dup
    //   5251: iconst_2
    //   5252: ldc -93
    //   5254: sastore
    //   5255: dup
    //   5256: iconst_3
    //   5257: ldc -82
    //   5259: sastore
    //   5260: dup
    //   5261: iconst_4
    //   5262: ldc 105
    //   5264: sastore
    //   5265: dup
    //   5266: iconst_5
    //   5267: ldc -17
    //   5269: sastore
    //   5270: dup
    //   5271: bipush 6
    //   5273: ldc -65
    //   5275: sastore
    //   5276: dup
    //   5277: bipush 7
    //   5279: ldc_w 277
    //   5282: sastore
    //   5283: dup
    //   5284: bipush 8
    //   5286: ldc 121
    //   5288: sastore
    //   5289: dup
    //   5290: bipush 9
    //   5292: ldc 115
    //   5294: sastore
    //   5295: dup
    //   5296: bipush 10
    //   5298: ldc_w 274
    //   5301: sastore
    //   5302: dup
    //   5303: bipush 11
    //   5305: ldc -56
    //   5307: sastore
    //   5308: dup
    //   5309: bipush 12
    //   5311: ldc -8
    //   5313: sastore
    //   5314: dup
    //   5315: bipush 13
    //   5317: ldc -1
    //   5319: sastore
    //   5320: dup
    //   5321: bipush 14
    //   5323: ldc -16
    //   5325: sastore
    //   5326: dup
    //   5327: bipush 15
    //   5329: ldc 120
    //   5331: sastore
    //   5332: dup
    //   5333: bipush 16
    //   5335: ldc -79
    //   5337: sastore
    //   5338: dup
    //   5339: bipush 17
    //   5341: ldc -77
    //   5343: sastore
    //   5344: dup
    //   5345: bipush 18
    //   5347: ldc 104
    //   5349: sastore
    //   5350: dup
    //   5351: bipush 19
    //   5353: ldc 105
    //   5355: sastore
    //   5356: dup
    //   5357: bipush 20
    //   5359: ldc -17
    //   5361: sastore
    //   5362: dup
    //   5363: bipush 21
    //   5365: ldc -65
    //   5367: sastore
    //   5368: dup
    //   5369: bipush 22
    //   5371: ldc_w 277
    //   5374: sastore
    //   5375: dup
    //   5376: bipush 23
    //   5378: ldc 99
    //   5380: sastore
    //   5381: dup
    //   5382: bipush 24
    //   5384: ldc 107
    //   5386: sastore
    //   5387: dup
    //   5388: bipush 25
    //   5390: ldc 115
    //   5392: sastore
    //   5393: dup
    //   5394: bipush 26
    //   5396: ldc 122
    //   5398: sastore
    //   5399: dup
    //   5400: bipush 27
    //   5402: ldc -116
    //   5404: sastore
    //   5405: dup
    //   5406: bipush 28
    //   5408: ldc_w 262
    //   5411: sastore
    //   5412: dup
    //   5413: bipush 29
    //   5415: ldc 114
    //   5417: sastore
    //   5418: dup
    //   5419: bipush 30
    //   5421: ldc_w 274
    //   5424: sastore
    //   5425: dup
    //   5426: bipush 31
    //   5428: ldc_w 280
    //   5431: sastore
    //   5432: dup
    //   5433: bipush 32
    //   5435: ldc -94
    //   5437: sastore
    //   5438: dup
    //   5439: bipush 33
    //   5441: ldc 112
    //   5443: sastore
    //   5444: dup
    //   5445: bipush 34
    //   5447: ldc 125
    //   5449: sastore
    //   5450: dup
    //   5451: bipush 35
    //   5453: ldc 110
    //   5455: sastore
    //   5456: dup
    //   5457: bipush 36
    //   5459: ldc 105
    //   5461: sastore
    //   5462: dup
    //   5463: bipush 37
    //   5465: ldc -17
    //   5467: sastore
    //   5468: dup
    //   5469: bipush 38
    //   5471: ldc -65
    //   5473: sastore
    //   5474: dup
    //   5475: bipush 39
    //   5477: ldc_w 277
    //   5480: sastore
    //   5481: dup
    //   5482: bipush 40
    //   5484: ldc 91
    //   5486: sastore
    //   5487: dup
    //   5488: bipush 41
    //   5490: ldc 48
    //   5492: sastore
    //   5493: dup
    //   5494: bipush 42
    //   5496: ldc 125
    //   5498: sastore
    //   5499: dup
    //   5500: bipush 43
    //   5502: ldc -19
    //   5504: sastore
    //   5505: dup
    //   5506: bipush 44
    //   5508: ldc -51
    //   5510: sastore
    //   5511: dup
    //   5512: bipush 45
    //   5514: ldc 80
    //   5516: sastore
    //   5517: dup
    //   5518: bipush 46
    //   5520: ldc -77
    //   5522: sastore
    //   5523: dup
    //   5524: bipush 47
    //   5526: ldc -83
    //   5528: sastore
    //   5529: dup
    //   5530: bipush 48
    //   5532: ldc 52
    //   5534: sastore
    //   5535: dup
    //   5536: bipush 49
    //   5538: ldc_w 266
    //   5541: sastore
    //   5542: dup
    //   5543: bipush 50
    //   5545: ldc_w 257
    //   5548: sastore
    //   5549: dup
    //   5550: bipush 51
    //   5552: ldc 74
    //   5554: sastore
    //   5555: dup
    //   5556: bipush 52
    //   5558: ldc_w 270
    //   5561: sastore
    //   5562: dup
    //   5563: bipush 53
    //   5565: ldc -1
    //   5567: sastore
    //   5568: dup
    //   5569: bipush 54
    //   5571: ldc -54
    //   5573: sastore
    //   5574: dup
    //   5575: bipush 55
    //   5577: ldc 83
    //   5579: sastore
    //   5580: dup
    //   5581: bipush 56
    //   5583: ldc 107
    //   5585: sastore
    //   5586: dup
    //   5587: bipush 57
    //   5589: ldc 82
    //   5591: sastore
    //   5592: dup
    //   5593: bipush 58
    //   5595: ldc -97
    //   5597: sastore
    //   5598: dup
    //   5599: bipush 59
    //   5601: ldc 112
    //   5603: sastore
    //   5604: dup
    //   5605: bipush 60
    //   5607: ldc 57
    //   5609: sastore
    //   5610: dup
    //   5611: bipush 61
    //   5613: ldc 127
    //   5615: sastore
    //   5616: dup
    //   5617: bipush 62
    //   5619: ldc -88
    //   5621: sastore
    //   5622: dup
    //   5623: bipush 63
    //   5625: ldc 57
    //   5627: sastore
    //   5628: dup
    //   5629: bipush 64
    //   5631: ldc 127
    //   5633: sastore
    //   5634: dup
    //   5635: bipush 65
    //   5637: ldc 122
    //   5639: sastore
    //   5640: dup
    //   5641: bipush 66
    //   5643: ldc_w 263
    //   5646: sastore
    //   5647: dup
    //   5648: bipush 67
    //   5650: ldc -99
    //   5652: sastore
    //   5653: dup
    //   5654: bipush 68
    //   5656: ldc 105
    //   5658: sastore
    //   5659: dup
    //   5660: bipush 69
    //   5662: ldc_w 266
    //   5665: sastore
    //   5666: dup
    //   5667: bipush 70
    //   5669: ldc_w 274
    //   5672: sastore
    //   5673: dup
    //   5674: bipush 71
    //   5676: ldc 80
    //   5678: sastore
    //   5679: dup
    //   5680: bipush 72
    //   5682: ldc 105
    //   5684: sastore
    //   5685: dup
    //   5686: bipush 73
    //   5688: ldc -94
    //   5690: sastore
    //   5691: dup
    //   5692: bipush 74
    //   5694: ldc -77
    //   5696: sastore
    //   5697: dup
    //   5698: bipush 75
    //   5700: ldc 57
    //   5702: sastore
    //   5703: dup
    //   5704: bipush 76
    //   5706: ldc 127
    //   5708: sastore
    //   5709: dup
    //   5710: bipush 77
    //   5712: ldc 122
    //   5714: sastore
    //   5715: dup
    //   5716: bipush 78
    //   5718: ldc -53
    //   5720: sastore
    //   5721: dup
    //   5722: bipush 79
    //   5724: ldc -107
    //   5726: sastore
    //   5727: dup
    //   5728: bipush 80
    //   5730: ldc -85
    //   5732: sastore
    //   5733: dup
    //   5734: bipush 81
    //   5736: ldc -94
    //   5738: sastore
    //   5739: dup
    //   5740: bipush 82
    //   5742: ldc 119
    //   5744: sastore
    //   5745: dup
    //   5746: bipush 83
    //   5748: ldc 57
    //   5750: sastore
    //   5751: dup
    //   5752: bipush 84
    //   5754: ldc -54
    //   5756: sastore
    //   5757: dup
    //   5758: bipush 85
    //   5760: ldc 79
    //   5762: sastore
    //   5763: dup
    //   5764: bipush 86
    //   5766: ldc -35
    //   5768: sastore
    //   5769: dup
    //   5770: bipush 87
    //   5772: ldc 48
    //   5774: sastore
    //   5775: dup
    //   5776: bipush 88
    //   5778: ldc 120
    //   5780: sastore
    //   5781: dup
    //   5782: bipush 89
    //   5784: ldc -79
    //   5786: sastore
    //   5787: dup
    //   5788: bipush 90
    //   5790: ldc -77
    //   5792: sastore
    //   5793: dup
    //   5794: bipush 91
    //   5796: ldc 104
    //   5798: sastore
    //   5799: dup
    //   5800: bipush 92
    //   5802: ldc 101
    //   5804: sastore
    //   5805: dup
    //   5806: bipush 93
    //   5808: ldc -82
    //   5810: sastore
    //   5811: dup
    //   5812: bipush 94
    //   5814: ldc -97
    //   5816: sastore
    //   5817: dup
    //   5818: bipush 95
    //   5820: ldc -128
    //   5822: sastore
    //   5823: dup
    //   5824: bipush 96
    //   5826: ldc -5
    //   5828: sastore
    //   5829: dup
    //   5830: bipush 97
    //   5832: ldc 111
    //   5834: sastore
    //   5835: dup
    //   5836: bipush 98
    //   5838: ldc 122
    //   5840: sastore
    //   5841: dup
    //   5842: bipush 99
    //   5844: ldc -56
    //   5846: sastore
    //   5847: dup
    //   5848: bipush 100
    //   5850: ldc 48
    //   5852: sastore
    //   5853: dup
    //   5854: bipush 101
    //   5856: ldc 115
    //   5858: sastore
    //   5859: dup
    //   5860: bipush 102
    //   5862: ldc 115
    //   5864: sastore
    //   5865: dup
    //   5866: bipush 103
    //   5868: ldc_w 281
    //   5871: sastore
    //   5872: dup
    //   5873: bipush 104
    //   5875: ldc -97
    //   5877: sastore
    //   5878: dup
    //   5879: bipush 105
    //   5881: ldc -65
    //   5883: sastore
    //   5884: dup
    //   5885: bipush 106
    //   5887: ldc -50
    //   5889: sastore
    //   5890: dup
    //   5891: bipush 107
    //   5893: ldc -76
    //   5895: sastore
    //   5896: dup
    //   5897: bipush 108
    //   5899: ldc 104
    //   5901: sastore
    //   5902: dup
    //   5903: bipush 109
    //   5905: ldc -85
    //   5907: sastore
    //   5908: dup
    //   5909: bipush 110
    //   5911: ldc -56
    //   5913: sastore
    //   5914: dup
    //   5915: bipush 111
    //   5917: ldc -79
    //   5919: sastore
    //   5920: dup
    //   5921: bipush 112
    //   5923: ldc -88
    //   5925: sastore
    //   5926: dup
    //   5927: bipush 113
    //   5929: ldc 122
    //   5931: sastore
    //   5932: dup
    //   5933: bipush 114
    //   5935: ldc 57
    //   5937: sastore
    //   5938: dup
    //   5939: bipush 115
    //   5941: ldc -105
    //   5943: sastore
    //   5944: dup
    //   5945: bipush 116
    //   5947: ldc 91
    //   5949: sastore
    //   5950: dup
    //   5951: bipush 117
    //   5953: ldc 48
    //   5955: sastore
    //   5956: dup
    //   5957: bipush 118
    //   5959: ldc 125
    //   5961: sastore
    //   5962: dup
    //   5963: bipush 119
    //   5965: ldc -80
    //   5967: sastore
    //   5968: dup
    //   5969: bipush 120
    //   5971: ldc -12
    //   5973: sastore
    //   5974: dup
    //   5975: bipush 121
    //   5977: ldc -56
    //   5979: sastore
    //   5980: dup
    //   5981: bipush 122
    //   5983: ldc -79
    //   5985: sastore
    //   5986: dup
    //   5987: bipush 123
    //   5989: ldc -88
    //   5991: sastore
    //   5992: dup
    //   5993: bipush 124
    //   5995: ldc 122
    //   5997: sastore
    //   5998: dup
    //   5999: bipush 125
    //   6001: ldc 57
    //   6003: sastore
    //   6004: dup
    //   6005: bipush 126
    //   6007: ldc 105
    //   6009: sastore
    //   6010: dup
    //   6011: bipush 127
    //   6013: ldc -17
    //   6015: sastore
    //   6016: dup
    //   6017: sipush 128
    //   6020: ldc -65
    //   6022: sastore
    //   6023: dup
    //   6024: sipush 129
    //   6027: ldc_w 277
    //   6030: sastore
    //   6031: dup
    //   6032: sipush 130
    //   6035: ldc 121
    //   6037: sastore
    //   6038: dup
    //   6039: sipush 131
    //   6042: ldc 115
    //   6044: sastore
    //   6045: dup
    //   6046: sipush 132
    //   6049: ldc_w 274
    //   6052: sastore
    //   6053: dup
    //   6054: sipush 133
    //   6057: ldc -56
    //   6059: sastore
    //   6060: dup
    //   6061: sipush 134
    //   6064: ldc -8
    //   6066: sastore
    //   6067: dup
    //   6068: sipush 135
    //   6071: ldc -17
    //   6073: sastore
    //   6074: dup
    //   6075: sipush 136
    //   6078: ldc_w 265
    //   6081: sastore
    //   6082: dup
    //   6083: sipush 137
    //   6086: ldc 115
    //   6088: sastore
    //   6089: dup
    //   6090: sipush 138
    //   6093: ldc 63
    //   6095: sastore
    //   6096: dup
    //   6097: sipush 139
    //   6100: ldc_w 266
    //   6103: sastore
    //   6104: dup
    //   6105: sipush 140
    //   6108: ldc -9
    //   6110: sastore
    //   6111: dup
    //   6112: sipush 141
    //   6115: ldc 111
    //   6117: sastore
    //   6118: dup
    //   6119: sipush 142
    //   6122: ldc 113
    //   6124: sastore
    //   6125: dup
    //   6126: sipush 143
    //   6129: ldc 122
    //   6131: sastore
    //   6132: dup
    //   6133: sipush 144
    //   6136: ldc -79
    //   6138: sastore
    //   6139: dup
    //   6140: sipush 145
    //   6143: ldc_w 274
    //   6146: sastore
    //   6147: dup
    //   6148: sipush 146
    //   6151: ldc 113
    //   6153: sastore
    //   6154: dup
    //   6155: sipush 147
    //   6158: ldc 114
    //   6160: sastore
    //   6161: dup
    //   6162: sipush 148
    //   6165: ldc 82
    //   6167: sastore
    //   6168: dup
    //   6169: sipush 149
    //   6172: ldc 63
    //   6174: sastore
    //   6175: dup
    //   6176: sipush 150
    //   6179: ldc_w 266
    //   6182: sastore
    //   6183: dup
    //   6184: sipush 151
    //   6187: ldc 107
    //   6189: sastore
    //   6190: dup
    //   6191: sipush 152
    //   6194: ldc_w 456
    //   6197: sastore
    //   6198: dup
    //   6199: sipush 153
    //   6202: ldc_w 457
    //   6205: sastore
    //   6206: dup
    //   6207: sipush 154
    //   6210: ldc_w 458
    //   6213: sastore
    //   6214: dup
    //   6215: sipush 155
    //   6218: ldc_w 459
    //   6221: sastore
    //   6222: dup
    //   6223: sipush 156
    //   6226: ldc 112
    //   6228: sastore
    //   6229: dup
    //   6230: sipush 157
    //   6233: ldc 114
    //   6235: sastore
    //   6236: dup
    //   6237: sipush 158
    //   6240: ldc 118
    //   6242: sastore
    //   6243: dup
    //   6244: sipush 159
    //   6247: ldc_w 261
    //   6250: sastore
    //   6251: dup
    //   6252: sipush 160
    //   6255: ldc 127
    //   6257: sastore
    //   6258: dup
    //   6259: sipush 161
    //   6262: ldc -77
    //   6264: sastore
    //   6265: dup
    //   6266: sipush 162
    //   6269: ldc_w 274
    //   6272: sastore
    //   6273: dup
    //   6274: sipush 163
    //   6277: ldc 127
    //   6279: sastore
    //   6280: dup
    //   6281: sipush 164
    //   6284: ldc 57
    //   6286: sastore
    //   6287: dup
    //   6288: sipush 165
    //   6291: ldc -94
    //   6293: sastore
    //   6294: dup
    //   6295: sipush 166
    //   6298: ldc 58
    //   6300: sastore
    //   6301: dup
    //   6302: sipush 167
    //   6305: ldc -97
    //   6307: sastore
    //   6308: dup
    //   6309: sipush 168
    //   6312: ldc 80
    //   6314: sastore
    //   6315: dup
    //   6316: sipush 169
    //   6319: ldc 122
    //   6321: sastore
    //   6322: dup
    //   6323: sipush 170
    //   6326: ldc_w 257
    //   6329: sastore
    //   6330: dup
    //   6331: sipush 171
    //   6334: ldc 48
    //   6336: sastore
    //   6337: dup
    //   6338: sipush 172
    //   6341: ldc 112
    //   6343: sastore
    //   6344: dup
    //   6345: sipush 173
    //   6348: ldc 82
    //   6350: sastore
    //   6351: dup
    //   6352: sipush 174
    //   6355: ldc -1
    //   6357: sastore
    //   6358: dup
    //   6359: sipush 175
    //   6362: ldc_w 278
    //   6365: sastore
    //   6366: dup
    //   6367: sipush 176
    //   6370: ldc 57
    //   6372: sastore
    //   6373: dup
    //   6374: sipush 177
    //   6377: ldc 112
    //   6379: sastore
    //   6380: dup
    //   6381: sipush 178
    //   6384: ldc -45
    //   6386: sastore
    //   6387: dup
    //   6388: sipush 179
    //   6391: ldc 80
    //   6393: sastore
    //   6394: dup
    //   6395: sipush 180
    //   6398: ldc 122
    //   6400: sastore
    //   6401: dup
    //   6402: sipush 181
    //   6405: ldc -74
    //   6407: sastore
    //   6408: dup
    //   6409: sipush 182
    //   6412: ldc 105
    //   6414: sastore
    //   6415: dup
    //   6416: sipush 183
    //   6419: ldc -17
    //   6421: sastore
    //   6422: dup
    //   6423: sipush 184
    //   6426: ldc -65
    //   6428: sastore
    //   6429: dup
    //   6430: sipush 185
    //   6433: ldc_w 277
    //   6436: sastore
    //   6437: dup
    //   6438: sipush 186
    //   6441: ldc 91
    //   6443: sastore
    //   6444: dup
    //   6445: sipush 187
    //   6448: ldc 48
    //   6450: sastore
    //   6451: dup
    //   6452: sipush 188
    //   6455: ldc 125
    //   6457: sastore
    //   6458: dup
    //   6459: sipush 189
    //   6462: ldc -82
    //   6464: sastore
    //   6465: dup
    //   6466: sipush 190
    //   6469: ldc -12
    //   6471: sastore
    //   6472: dup
    //   6473: sipush 191
    //   6476: ldc -128
    //   6478: sastore
    //   6479: dup
    //   6480: sipush 192
    //   6483: ldc 65
    //   6485: sastore
    //   6486: dup
    //   6487: sipush 193
    //   6490: ldc 123
    //   6492: sastore
    //   6493: dup
    //   6494: sipush 194
    //   6497: ldc -1
    //   6499: sastore
    //   6500: dup
    //   6501: sipush 195
    //   6504: ldc -54
    //   6506: sastore
    //   6507: dup
    //   6508: sipush 196
    //   6511: ldc 83
    //   6513: sastore
    //   6514: dup
    //   6515: sipush 197
    //   6518: ldc 107
    //   6520: sastore
    //   6521: dup
    //   6522: sipush 198
    //   6525: ldc 82
    //   6527: sastore
    //   6528: dup
    //   6529: sipush 199
    //   6532: ldc -97
    //   6534: sastore
    //   6535: dup
    //   6536: sipush 200
    //   6539: ldc 112
    //   6541: sastore
    //   6542: dup
    //   6543: sipush 201
    //   6546: ldc 57
    //   6548: sastore
    //   6549: dup
    //   6550: sipush 202
    //   6553: ldc 127
    //   6555: sastore
    //   6556: dup
    //   6557: sipush 203
    //   6560: ldc -88
    //   6562: sastore
    //   6563: dup
    //   6564: sipush 204
    //   6567: ldc 122
    //   6569: sastore
    //   6570: dup
    //   6571: sipush 205
    //   6574: ldc 113
    //   6576: sastore
    //   6577: dup
    //   6578: sipush 206
    //   6581: ldc 122
    //   6583: sastore
    //   6584: dup
    //   6585: sipush 207
    //   6588: ldc -58
    //   6590: sastore
    //   6591: dup
    //   6592: sipush 208
    //   6595: ldc -97
    //   6597: sastore
    //   6598: dup
    //   6599: sipush 209
    //   6602: ldc -128
    //   6604: sastore
    //   6605: dup
    //   6606: sipush 210
    //   6609: ldc -85
    //   6611: sastore
    //   6612: dup
    //   6613: sipush 211
    //   6616: ldc 125
    //   6618: sastore
    //   6619: dup
    //   6620: sipush 212
    //   6623: ldc 62
    //   6625: sastore
    //   6626: dup
    //   6627: sipush 213
    //   6630: ldc 63
    //   6632: sastore
    //   6633: dup
    //   6634: sipush 214
    //   6637: ldc 112
    //   6639: sastore
    //   6640: dup
    //   6641: sipush 215
    //   6644: ldc 120
    //   6646: sastore
    //   6647: dup
    //   6648: sipush 216
    //   6651: ldc -116
    //   6653: sastore
    //   6654: dup
    //   6655: sipush 217
    //   6658: ldc -73
    //   6660: sastore
    //   6661: dup
    //   6662: sipush 218
    //   6665: ldc -77
    //   6667: sastore
    //   6668: dup
    //   6669: sipush 219
    //   6672: ldc 74
    //   6674: sastore
    //   6675: dup
    //   6676: sipush 220
    //   6679: ldc_w 274
    //   6682: sastore
    //   6683: dup
    //   6684: sipush 221
    //   6687: ldc_w 280
    //   6690: sastore
    //   6691: dup
    //   6692: sipush 222
    //   6695: ldc -113
    //   6697: sastore
    //   6698: dup
    //   6699: sipush 223
    //   6702: ldc -85
    //   6704: sastore
    //   6705: dup
    //   6706: sipush 224
    //   6709: ldc 120
    //   6711: sastore
    //   6712: dup
    //   6713: sipush 225
    //   6716: ldc 80
    //   6718: sastore
    //   6719: dup
    //   6720: sipush 226
    //   6723: ldc 81
    //   6725: sastore
    //   6726: dup
    //   6727: sipush 227
    //   6730: ldc -61
    //   6732: sastore
    //   6733: dup
    //   6734: sipush 228
    //   6737: ldc -50
    //   6739: sastore
    //   6740: dup
    //   6741: sipush 229
    //   6744: ldc_w 283
    //   6747: sastore
    //   6748: dup
    //   6749: sipush 230
    //   6752: ldc 59
    //   6754: sastore
    //   6755: dup
    //   6756: sipush 231
    //   6759: ldc_w 265
    //   6762: sastore
    //   6763: dup
    //   6764: sipush 232
    //   6767: ldc 104
    //   6769: sastore
    //   6770: dup
    //   6771: sipush 233
    //   6774: ldc 57
    //   6776: sastore
    //   6777: dup
    //   6778: sipush 234
    //   6781: ldc_w 278
    //   6784: sastore
    //   6785: dup
    //   6786: sipush 235
    //   6789: ldc -85
    //   6791: sastore
    //   6792: dup
    //   6793: sipush 236
    //   6796: ldc 107
    //   6798: sastore
    //   6799: dup
    //   6800: sipush 237
    //   6803: ldc 107
    //   6805: sastore
    //   6806: dup
    //   6807: sipush 238
    //   6810: ldc 126
    //   6812: sastore
    //   6813: dup
    //   6814: sipush 239
    //   6817: ldc_w 278
    //   6820: sastore
    //   6821: dup
    //   6822: sipush 240
    //   6825: ldc 48
    //   6827: sastore
    //   6828: dup
    //   6829: sipush 241
    //   6832: ldc 113
    //   6834: sastore
    //   6835: dup
    //   6836: sipush 242
    //   6839: ldc 114
    //   6841: sastore
    //   6842: dup
    //   6843: sipush 243
    //   6846: ldc -77
    //   6848: sastore
    //   6849: dup
    //   6850: sipush 244
    //   6853: ldc_w 278
    //   6856: sastore
    //   6857: dup
    //   6858: sipush 245
    //   6861: ldc 104
    //   6863: sastore
    //   6864: dup
    //   6865: sipush 246
    //   6868: ldc 126
    //   6870: sastore
    //   6871: dup
    //   6872: sipush 247
    //   6875: ldc 112
    //   6877: sastore
    //   6878: dup
    //   6879: sipush 248
    //   6882: ldc -74
    //   6884: sastore
    //   6885: dup
    //   6886: sipush 249
    //   6889: ldc 112
    //   6891: sastore
    //   6892: dup
    //   6893: sipush 250
    //   6896: ldc 114
    //   6898: sastore
    //   6899: dup
    //   6900: sipush 251
    //   6903: ldc -14
    //   6905: sastore
    //   6906: dup
    //   6907: sipush 252
    //   6910: ldc_w 265
    //   6913: sastore
    //   6914: dup
    //   6915: sipush 253
    //   6918: ldc 115
    //   6920: sastore
    //   6921: dup
    //   6922: sipush 254
    //   6925: ldc 63
    //   6927: sastore
    //   6928: dup
    //   6929: sipush 255
    //   6932: ldc_w 266
    //   6935: sastore
    //   6936: dup
    //   6937: sipush 256
    //   6940: ldc -9
    //   6942: sastore
    //   6943: dup
    //   6944: sipush 257
    //   6947: ldc 111
    //   6949: sastore
    //   6950: dup
    //   6951: sipush 258
    //   6954: ldc 113
    //   6956: sastore
    //   6957: dup
    //   6958: sipush 259
    //   6961: ldc 122
    //   6963: sastore
    //   6964: dup
    //   6965: sipush 260
    //   6968: ldc -79
    //   6970: sastore
    //   6971: dup
    //   6972: sipush 261
    //   6975: ldc_w 274
    //   6978: sastore
    //   6979: dup
    //   6980: sipush 262
    //   6983: ldc 85
    //   6985: sastore
    //   6986: dup
    //   6987: sipush 263
    //   6990: ldc -85
    //   6992: sastore
    //   6993: dup
    //   6994: sipush 264
    //   6997: ldc -128
    //   6999: sastore
    //   7000: dup
    //   7001: sipush 265
    //   7004: ldc 65
    //   7006: sastore
    //   7007: dup
    //   7008: sipush 266
    //   7011: ldc -5
    //   7013: sastore
    //   7014: dup
    //   7015: sipush 267
    //   7018: ldc 85
    //   7020: sastore
    //   7021: dup
    //   7022: sipush 268
    //   7025: ldc -85
    //   7027: sastore
    //   7028: dup
    //   7029: sipush 269
    //   7032: ldc -128
    //   7034: sastore
    //   7035: dup
    //   7036: sipush 270
    //   7039: ldc 65
    //   7041: sastore
    //   7042: dup
    //   7043: sipush 271
    //   7046: ldc -5
    //   7048: sastore
    //   7049: dup
    //   7050: sipush 272
    //   7053: ldc -79
    //   7055: sastore
    //   7056: dup
    //   7057: sipush 273
    //   7060: ldc -74
    //   7062: sastore
    //   7063: dup
    //   7064: sipush 274
    //   7067: ldc -56
    //   7069: sastore
    //   7070: dup
    //   7071: sipush 275
    //   7074: ldc 114
    //   7076: sastore
    //   7077: dup
    //   7078: sipush 276
    //   7081: ldc -77
    //   7083: sastore
    //   7084: dup
    //   7085: sipush 277
    //   7088: ldc 112
    //   7090: sastore
    //   7091: dup
    //   7092: sipush 278
    //   7095: ldc 114
    //   7097: sastore
    //   7098: dup
    //   7099: sipush 279
    //   7102: ldc -24
    //   7104: sastore
    //   7105: dup
    //   7106: sipush 280
    //   7109: ldc 112
    //   7111: sastore
    //   7112: dup
    //   7113: sipush 281
    //   7116: ldc_w 278
    //   7119: sastore
    //   7120: dup
    //   7121: sipush 282
    //   7124: ldc 122
    //   7126: sastore
    //   7127: dup
    //   7128: sipush 283
    //   7131: ldc -50
    //   7133: sastore
    //   7134: dup
    //   7135: sipush 284
    //   7138: ldc 113
    //   7140: sastore
    //   7141: dup
    //   7142: sipush 285
    //   7145: ldc 112
    //   7147: sastore
    //   7148: dup
    //   7149: sipush 286
    //   7152: ldc 114
    //   7154: sastore
    //   7155: dup
    //   7156: sipush 287
    //   7159: ldc -77
    //   7161: sastore
    //   7162: dup
    //   7163: sipush 288
    //   7166: ldc_w 278
    //   7169: sastore
    //   7170: dup
    //   7171: sipush 289
    //   7174: ldc 104
    //   7176: sastore
    //   7177: dup
    //   7178: sipush 290
    //   7181: ldc_w 274
    //   7184: sastore
    //   7185: dup
    //   7186: sipush 291
    //   7189: ldc_w 280
    //   7192: sastore
    //   7193: dup
    //   7194: sipush 292
    //   7197: ldc -113
    //   7199: sastore
    //   7200: dup
    //   7201: sipush 293
    //   7204: ldc -85
    //   7206: sastore
    //   7207: dup
    //   7208: sipush 294
    //   7211: ldc 120
    //   7213: sastore
    //   7214: dup
    //   7215: sipush 295
    //   7218: ldc 80
    //   7220: sastore
    //   7221: dup
    //   7222: sipush 296
    //   7225: ldc -36
    //   7227: sastore
    //   7228: dup
    //   7229: sipush 297
    //   7232: ldc 65
    //   7234: sastore
    //   7235: dup
    //   7236: sipush 298
    //   7239: ldc 122
    //   7241: sastore
    //   7242: dup
    //   7243: sipush 299
    //   7246: ldc 126
    //   7248: sastore
    //   7249: dup
    //   7250: sipush 300
    //   7253: ldc 74
    //   7255: sastore
    //   7256: dup
    //   7257: sipush 301
    //   7260: ldc 115
    //   7262: sastore
    //   7263: dup
    //   7264: sipush 302
    //   7267: ldc 65
    //   7269: sastore
    //   7270: dup
    //   7271: sipush 303
    //   7274: ldc 48
    //   7276: sastore
    //   7277: dup
    //   7278: sipush 304
    //   7281: ldc -88
    //   7283: sastore
    //   7284: dup
    //   7285: sipush 305
    //   7288: ldc 105
    //   7290: sastore
    //   7291: dup
    //   7292: sipush 306
    //   7295: ldc -17
    //   7297: sastore
    //   7298: dup
    //   7299: sipush 307
    //   7302: ldc -65
    //   7304: sastore
    //   7305: dup
    //   7306: sipush 308
    //   7309: ldc_w 277
    //   7312: sastore
    //   7313: dup
    //   7314: sipush 309
    //   7317: ldc 91
    //   7319: sastore
    //   7320: dup
    //   7321: sipush 310
    //   7324: ldc 48
    //   7326: sastore
    //   7327: dup
    //   7328: sipush 311
    //   7331: ldc 125
    //   7333: sastore
    //   7334: dup
    //   7335: sipush 312
    //   7338: ldc -103
    //   7340: sastore
    //   7341: dup
    //   7342: sipush 313
    //   7345: ldc -56
    //   7347: sastore
    //   7348: dup
    //   7349: sipush 314
    //   7352: ldc 122
    //   7354: sastore
    //   7355: dup
    //   7356: sipush 315
    //   7359: ldc 69
    //   7361: sastore
    //   7362: dup
    //   7363: sipush 316
    //   7366: ldc 83
    //   7368: sastore
    //   7369: dup
    //   7370: sipush 317
    //   7373: ldc_w 278
    //   7376: sastore
    //   7377: dup
    //   7378: sipush 318
    //   7381: ldc 112
    //   7383: sastore
    //   7384: dup
    //   7385: sipush 319
    //   7388: ldc 114
    //   7390: sastore
    //   7391: dup
    //   7392: sipush 320
    //   7395: ldc -83
    //   7397: sastore
    //   7398: dup
    //   7399: sipush 321
    //   7402: ldc 110
    //   7404: sastore
    //   7405: dup
    //   7406: sipush 322
    //   7409: ldc -85
    //   7411: sastore
    //   7412: dup
    //   7413: sipush 323
    //   7416: ldc -79
    //   7418: sastore
    //   7419: dup
    //   7420: sipush 324
    //   7423: ldc 115
    //   7425: sastore
    //   7426: dup
    //   7427: sipush 325
    //   7430: ldc_w 274
    //   7433: sastore
    //   7434: dup
    //   7435: sipush 326
    //   7438: ldc -54
    //   7440: sastore
    //   7441: dup
    //   7442: sipush 327
    //   7445: ldc 83
    //   7447: sastore
    //   7448: dup
    //   7449: sipush 328
    //   7452: ldc -50
    //   7454: sastore
    //   7455: dup
    //   7456: sipush 329
    //   7459: ldc 112
    //   7461: sastore
    //   7462: dup
    //   7463: sipush 330
    //   7466: ldc 114
    //   7468: sastore
    //   7469: dup
    //   7470: sipush 331
    //   7473: ldc_w 277
    //   7476: sastore
    //   7477: dup
    //   7478: sipush 332
    //   7481: ldc -97
    //   7483: sastore
    //   7484: dup
    //   7485: sipush 333
    //   7488: ldc -45
    //   7490: sastore
    //   7491: dup
    //   7492: sipush 334
    //   7495: ldc 127
    //   7497: sastore
    //   7498: dup
    //   7499: sipush 335
    //   7502: ldc -85
    //   7504: sastore
    //   7505: dup
    //   7506: sipush 336
    //   7509: ldc_w 278
    //   7512: sastore
    //   7513: dup
    //   7514: sipush 337
    //   7517: ldc 107
    //   7519: sastore
    //   7520: dup
    //   7521: sipush 338
    //   7524: ldc -77
    //   7526: sastore
    //   7527: dup
    //   7528: sipush 339
    //   7531: ldc -65
    //   7533: sastore
    //   7534: dup
    //   7535: sipush 340
    //   7538: ldc -45
    //   7540: sastore
    //   7541: dup
    //   7542: sipush 341
    //   7545: ldc -128
    //   7547: sastore
    //   7548: dup
    //   7549: sipush 342
    //   7552: ldc 69
    //   7554: sastore
    //   7555: dup
    //   7556: sipush 343
    //   7559: ldc 105
    //   7561: sastore
    //   7562: dup
    //   7563: sipush 344
    //   7566: ldc -17
    //   7568: sastore
    //   7569: dup
    //   7570: sipush 345
    //   7573: ldc -65
    //   7575: sastore
    //   7576: dup
    //   7577: sipush 346
    //   7580: ldc_w 277
    //   7583: sastore
    //   7584: dup
    //   7585: sipush 347
    //   7588: ldc 91
    //   7590: sastore
    //   7591: dup
    //   7592: sipush 348
    //   7595: ldc 48
    //   7597: sastore
    //   7598: dup
    //   7599: sipush 349
    //   7602: ldc 125
    //   7604: sastore
    //   7605: dup
    //   7606: sipush 350
    //   7609: ldc 74
    //   7611: sastore
    //   7612: dup
    //   7613: sipush 351
    //   7616: ldc 111
    //   7618: sastore
    //   7619: dup
    //   7620: sipush 352
    //   7623: ldc 122
    //   7625: sastore
    //   7626: dup
    //   7627: sipush 353
    //   7630: ldc -56
    //   7632: sastore
    //   7633: dup
    //   7634: sipush 354
    //   7637: ldc_w 269
    //   7640: sastore
    //   7641: dup
    //   7642: sipush 355
    //   7645: ldc -16
    //   7647: sastore
    //   7648: dup
    //   7649: sipush 356
    //   7652: ldc 107
    //   7654: sastore
    //   7655: dup
    //   7656: sipush 357
    //   7659: ldc 127
    //   7661: sastore
    //   7662: dup
    //   7663: sipush 358
    //   7666: ldc 83
    //   7668: sastore
    //   7669: dup
    //   7670: sipush 359
    //   7673: ldc 107
    //   7675: sastore
    //   7676: dup
    //   7677: sipush 360
    //   7680: ldc 82
    //   7682: sastore
    //   7683: dup
    //   7684: sipush 361
    //   7687: ldc -97
    //   7689: sastore
    //   7690: dup
    //   7691: sipush 362
    //   7694: ldc 112
    //   7696: sastore
    //   7697: dup
    //   7698: sipush 363
    //   7701: ldc 57
    //   7703: sastore
    //   7704: dup
    //   7705: sipush 364
    //   7708: ldc 127
    //   7710: sastore
    //   7711: dup
    //   7712: sipush 365
    //   7715: ldc -88
    //   7717: sastore
    //   7718: dup
    //   7719: sipush 366
    //   7722: ldc 112
    //   7724: sastore
    //   7725: dup
    //   7726: sipush 367
    //   7729: ldc_w 274
    //   7732: sastore
    //   7733: dup
    //   7734: sipush 368
    //   7737: ldc 86
    //   7739: sastore
    //   7740: dup
    //   7741: sipush 369
    //   7744: ldc -36
    //   7746: sastore
    //   7747: dup
    //   7748: sipush 370
    //   7751: ldc 105
    //   7753: sastore
    //   7754: dup
    //   7755: sipush 371
    //   7758: ldc -94
    //   7760: sastore
    //   7761: dup
    //   7762: sipush 372
    //   7765: ldc -77
    //   7767: sastore
    //   7768: dup
    //   7769: sipush 373
    //   7772: ldc 105
    //   7774: sastore
    //   7775: dup
    //   7776: sipush 374
    //   7779: ldc -17
    //   7781: sastore
    //   7782: dup
    //   7783: sipush 375
    //   7786: ldc -65
    //   7788: sastore
    //   7789: dup
    //   7790: sipush 376
    //   7793: ldc_w 277
    //   7796: sastore
    //   7797: dup
    //   7798: sipush 377
    //   7801: ldc 91
    //   7803: sastore
    //   7804: dup
    //   7805: sipush 378
    //   7808: ldc 48
    //   7810: sastore
    //   7811: dup
    //   7812: sipush 379
    //   7815: ldc 125
    //   7817: sastore
    //   7818: dup
    //   7819: sipush 380
    //   7822: ldc -36
    //   7824: sastore
    //   7825: dup
    //   7826: sipush 381
    //   7829: ldc 48
    //   7831: sastore
    //   7832: dup
    //   7833: sipush 382
    //   7836: ldc_w 280
    //   7839: sastore
    //   7840: dup
    //   7841: sipush 383
    //   7844: ldc_w 261
    //   7847: sastore
    //   7848: dup
    //   7849: sipush 384
    //   7852: ldc -65
    //   7854: sastore
    //   7855: dup
    //   7856: sipush 385
    //   7859: ldc -54
    //   7861: sastore
    //   7862: dup
    //   7863: sipush 386
    //   7866: ldc -94
    //   7868: sastore
    //   7869: dup
    //   7870: sipush 387
    //   7873: ldc -50
    //   7875: sastore
    //   7876: dup
    //   7877: sipush 388
    //   7880: ldc 115
    //   7882: sastore
    //   7883: dup
    //   7884: sipush 389
    //   7887: ldc 48
    //   7889: sastore
    //   7890: dup
    //   7891: sipush 390
    //   7894: ldc 107
    //   7896: sastore
    //   7897: dup
    //   7898: sipush 391
    //   7901: ldc 105
    //   7903: sastore
    //   7904: dup
    //   7905: sipush 392
    //   7908: ldc -128
    //   7910: sastore
    //   7911: dup
    //   7912: sipush 393
    //   7915: ldc 127
    //   7917: sastore
    //   7918: dup
    //   7919: sipush 394
    //   7922: ldc -64
    //   7924: sastore
    //   7925: dup
    //   7926: sipush 395
    //   7929: ldc -1
    //   7931: sastore
    //   7932: dup
    //   7933: sipush 396
    //   7936: ldc 48
    //   7938: sastore
    //   7939: dup
    //   7940: sipush 397
    //   7943: ldc 105
    //   7945: sastore
    //   7946: dup
    //   7947: sipush 398
    //   7950: ldc -17
    //   7952: sastore
    //   7953: dup
    //   7954: sipush 399
    //   7957: ldc -65
    //   7959: sastore
    //   7960: dup
    //   7961: sipush 400
    //   7964: ldc_w 277
    //   7967: sastore
    //   7968: dup
    //   7969: sipush 401
    //   7972: ldc 91
    //   7974: sastore
    //   7975: dup
    //   7976: sipush 402
    //   7979: ldc 48
    //   7981: sastore
    //   7982: dup
    //   7983: sipush 403
    //   7986: ldc 125
    //   7988: sastore
    //   7989: dup
    //   7990: sipush 404
    //   7993: ldc 74
    //   7995: sastore
    //   7996: dup
    //   7997: sipush 405
    //   8000: ldc 111
    //   8002: sastore
    //   8003: dup
    //   8004: sipush 406
    //   8007: ldc 122
    //   8009: sastore
    //   8010: dup
    //   8011: sipush 407
    //   8014: ldc -56
    //   8016: sastore
    //   8017: dup
    //   8018: sipush 408
    //   8021: ldc -65
    //   8023: sastore
    //   8024: dup
    //   8025: sipush 409
    //   8028: ldc 122
    //   8030: sastore
    //   8031: dup
    //   8032: sipush 410
    //   8035: ldc 65
    //   8037: sastore
    //   8038: dup
    //   8039: sipush 411
    //   8042: ldc 104
    //   8044: sastore
    //   8045: dup
    //   8046: sipush 412
    //   8049: ldc_w 281
    //   8052: sastore
    //   8053: dup
    //   8054: sipush 413
    //   8057: ldc -111
    //   8059: sastore
    //   8060: dup
    //   8061: sipush 414
    //   8064: ldc -64
    //   8066: sastore
    //   8067: dup
    //   8068: sipush 415
    //   8071: ldc 42
    //   8073: sastore
    //   8074: dup
    //   8075: sipush 416
    //   8078: ldc 63
    //   8080: sastore
    //   8081: dup
    //   8082: sipush 417
    //   8085: ldc -85
    //   8087: sastore
    //   8088: dup
    //   8089: sipush 418
    //   8092: ldc_w 266
    //   8095: sastore
    //   8096: dup
    //   8097: sipush 419
    //   8100: ldc 57
    //   8102: sastore
    //   8103: dup
    //   8104: sipush 420
    //   8107: ldc_w 278
    //   8110: sastore
    //   8111: dup
    //   8112: sipush 421
    //   8115: ldc 48
    //   8117: sastore
    //   8118: dup
    //   8119: sipush 422
    //   8122: ldc -58
    //   8124: sastore
    //   8125: dup
    //   8126: sipush 423
    //   8129: ldc -17
    //   8131: sastore
    //   8132: dup
    //   8133: sipush 424
    //   8136: ldc -50
    //   8138: sastore
    //   8139: dup
    //   8140: sipush 425
    //   8143: ldc 126
    //   8145: sastore
    //   8146: dup
    //   8147: sipush 426
    //   8150: ldc 123
    //   8152: sastore
    //   8153: dup
    //   8154: sipush 427
    //   8157: ldc -110
    //   8159: sastore
    //   8160: dup
    //   8161: sipush 428
    //   8164: ldc 122
    //   8166: sastore
    //   8167: dup
    //   8168: sipush 429
    //   8171: ldc_w 266
    //   8174: sastore
    //   8175: dup
    //   8176: sipush 430
    //   8179: ldc -85
    //   8181: sastore
    //   8182: dup
    //   8183: sipush 431
    //   8186: ldc 119
    //   8188: sastore
    //   8189: dup
    //   8190: sipush 432
    //   8193: ldc 105
    //   8195: sastore
    //   8196: dup
    //   8197: sipush 433
    //   8200: ldc -17
    //   8202: sastore
    //   8203: dup
    //   8204: sipush 434
    //   8207: ldc -65
    //   8209: sastore
    //   8210: dup
    //   8211: sipush 435
    //   8214: ldc_w 277
    //   8217: sastore
    //   8218: dup
    //   8219: sipush 436
    //   8222: ldc 91
    //   8224: sastore
    //   8225: dup
    //   8226: sipush 437
    //   8229: ldc 48
    //   8231: sastore
    //   8232: dup
    //   8233: sipush 438
    //   8236: ldc 125
    //   8238: sastore
    //   8239: dup
    //   8240: sipush 439
    //   8243: ldc 74
    //   8245: sastore
    //   8246: dup
    //   8247: sipush 440
    //   8250: ldc 111
    //   8252: sastore
    //   8253: dup
    //   8254: sipush 441
    //   8257: ldc 122
    //   8259: sastore
    //   8260: dup
    //   8261: sipush 442
    //   8264: ldc -56
    //   8266: sastore
    //   8267: dup
    //   8268: sipush 443
    //   8271: ldc 82
    //   8273: sastore
    //   8274: dup
    //   8275: sipush 444
    //   8278: ldc -97
    //   8280: sastore
    //   8281: dup
    //   8282: sipush 445
    //   8285: ldc -113
    //   8287: sastore
    //   8288: dup
    //   8289: sipush 446
    //   8292: ldc -49
    //   8294: sastore
    //   8295: dup
    //   8296: sipush 447
    //   8299: ldc 114
    //   8301: sastore
    //   8302: dup
    //   8303: sipush 448
    //   8306: ldc 105
    //   8308: sastore
    //   8309: dup
    //   8310: sipush 449
    //   8313: ldc -74
    //   8315: sastore
    //   8316: dup
    //   8317: sipush 450
    //   8320: ldc -50
    //   8322: sastore
    //   8323: dup
    //   8324: sipush 451
    //   8327: ldc 80
    //   8329: sastore
    //   8330: dup
    //   8331: sipush 452
    //   8334: ldc 122
    //   8336: sastore
    //   8337: dup
    //   8338: sipush 453
    //   8341: ldc 122
    //   8343: sastore
    //   8344: dup
    //   8345: sipush 454
    //   8348: ldc 113
    //   8350: sastore
    //   8351: dup
    //   8352: sipush 455
    //   8355: ldc 122
    //   8357: sastore
    //   8358: dup
    //   8359: sipush 456
    //   8362: ldc 82
    //   8364: sastore
    //   8365: dup
    //   8366: sipush 457
    //   8369: ldc_w 265
    //   8372: sastore
    //   8373: dup
    //   8374: sipush 458
    //   8377: ldc 115
    //   8379: sastore
    //   8380: dup
    //   8381: sipush 459
    //   8384: ldc 63
    //   8386: sastore
    //   8387: dup
    //   8388: sipush 460
    //   8391: ldc_w 266
    //   8394: sastore
    //   8395: dup
    //   8396: sipush 461
    //   8399: ldc 105
    //   8401: sastore
    //   8402: dup
    //   8403: sipush 462
    //   8406: ldc -17
    //   8408: sastore
    //   8409: dup
    //   8410: sipush 463
    //   8413: ldc -65
    //   8415: sastore
    //   8416: dup
    //   8417: sipush 464
    //   8420: ldc_w 277
    //   8423: sastore
    //   8424: dup
    //   8425: sipush 465
    //   8428: ldc 91
    //   8430: sastore
    //   8431: dup
    //   8432: sipush 466
    //   8435: ldc 48
    //   8437: sastore
    //   8438: dup
    //   8439: sipush 467
    //   8442: ldc 125
    //   8444: sastore
    //   8445: dup
    //   8446: sipush 468
    //   8449: ldc -36
    //   8451: sastore
    //   8452: dup
    //   8453: sipush 469
    //   8456: ldc -1
    //   8458: sastore
    //   8459: dup
    //   8460: sipush 470
    //   8463: ldc -54
    //   8465: sastore
    //   8466: dup
    //   8467: sipush 471
    //   8470: ldc 83
    //   8472: sastore
    //   8473: dup
    //   8474: sipush 472
    //   8477: ldc 107
    //   8479: sastore
    //   8480: dup
    //   8481: sipush 473
    //   8484: ldc 82
    //   8486: sastore
    //   8487: dup
    //   8488: sipush 474
    //   8491: ldc -97
    //   8493: sastore
    //   8494: dup
    //   8495: sipush 475
    //   8498: ldc 112
    //   8500: sastore
    //   8501: dup
    //   8502: sipush 476
    //   8505: ldc 57
    //   8507: sastore
    //   8508: dup
    //   8509: sipush 477
    //   8512: ldc 127
    //   8514: sastore
    //   8515: dup
    //   8516: sipush 478
    //   8519: ldc -88
    //   8521: sastore
    //   8522: putstatic 310	o/O:ʿ	[S
    //   8525: bipush 90
    //   8527: putstatic 429	o/O:ˈ	I
    //   8530: invokestatic 461	o/O:$$a	()V
    //   8533: goto +912 -> 9445
    //   8536: aload 12
    //   8538: arraylength
    //   8539: istore_3
    //   8540: sipush 1024
    //   8543: iload_1
    //   8544: invokestatic 465	java/lang/Math:min	(II)I
    //   8547: istore 4
    //   8549: goto +557 -> 9106
    //   8552: astore 10
    //   8554: aload 10
    //   8556: invokevirtual 349	java/lang/Throwable:getCause	()Ljava/lang/Throwable;
    //   8559: astore 11
    //   8561: aload 11
    //   8563: ifnull +6 -> 8569
    //   8566: goto +1767 -> 10333
    //   8569: goto +1394 -> 9963
    //   8572: aload 11
    //   8574: athrow
    //   8575: astore 10
    //   8577: aload 10
    //   8579: invokevirtual 349	java/lang/Throwable:getCause	()Ljava/lang/Throwable;
    //   8582: astore 11
    //   8584: aload 11
    //   8586: ifnull +6 -> 8592
    //   8589: goto -17 -> 8572
    //   8592: goto -3475 -> 5117
    //   8595: astore 10
    //   8597: aload 10
    //   8599: invokevirtual 349	java/lang/Throwable:getCause	()Ljava/lang/Throwable;
    //   8602: astore 11
    //   8604: aload 11
    //   8606: ifnull +6 -> 8612
    //   8609: goto -8456 -> 153
    //   8612: goto -7118 -> 1494
    //   8615: astore 10
    //   8617: aload 10
    //   8619: invokevirtual 349	java/lang/Throwable:getCause	()Ljava/lang/Throwable;
    //   8622: astore 11
    //   8624: aload 11
    //   8626: ifnull +6 -> 8632
    //   8629: goto -7880 -> 749
    //   8632: goto -4813 -> 3819
    //   8635: getstatic 28	o/O:ʽॱ	I
    //   8638: bipush 47
    //   8640: iadd
    //   8641: istore_3
    //   8642: iload_3
    //   8643: sipush 128
    //   8646: irem
    //   8647: putstatic 30	o/O:ʼॱ	I
    //   8650: iload_3
    //   8651: iconst_2
    //   8652: irem
    //   8653: ifne +6 -> 8659
    //   8656: goto +1378 -> 10034
    //   8659: goto -4086 -> 4573
    //   8662: bipush 76
    //   8664: getstatic 310	o/O:ʿ	[S
    //   8667: bipush 45
    //   8669: saload
    //   8670: i2b
    //   8671: sipush 618
    //   8674: invokestatic 331	o/O:$$d	(IIS)Ljava/lang/String;
    //   8677: invokestatic 335	java/lang/Class:forName	(Ljava/lang/String;)Ljava/lang/Class;
    //   8680: sipush 277
    //   8683: getstatic 310	o/O:ʿ	[S
    //   8686: bipush 6
    //   8688: saload
    //   8689: i2b
    //   8690: sipush 619
    //   8693: invokestatic 331	o/O:$$d	(IIS)Ljava/lang/String;
    //   8696: aconst_null
    //   8697: invokevirtual 393	java/lang/Class:getMethod	(Ljava/lang/String;[Ljava/lang/Class;)Ljava/lang/reflect/Method;
    //   8700: aload 10
    //   8702: aconst_null
    //   8703: invokevirtual 376	java/lang/reflect/Method:invoke	(Ljava/lang/Object;[Ljava/lang/Object;)Ljava/lang/Object;
    //   8706: pop
    //   8707: goto -7541 -> 1166
    //   8710: aload 12
    //   8712: athrow
    //   8713: iload_1
    //   8714: i2b
    //   8715: istore_1
    //   8716: iload_1
    //   8717: sipush 581
    //   8720: ixor
    //   8721: iload_1
    //   8722: sipush 581
    //   8725: iand
    //   8726: ior
    //   8727: i2s
    //   8728: istore_0
    //   8729: aload 13
    //   8731: astore 11
    //   8733: aload 20
    //   8735: astore 10
    //   8737: aload 24
    //   8739: sipush 324
    //   8742: iload_1
    //   8743: iload_0
    //   8744: invokestatic 331	o/O:$$d	(IIS)Ljava/lang/String;
    //   8747: invokevirtual 469	java/lang/Class:getField	(Ljava/lang/String;)Ljava/lang/reflect/Field;
    //   8750: astore 12
    //   8752: goto -6523 -> 2229
    //   8755: getstatic 28	o/O:ʽॱ	I
    //   8758: istore_1
    //   8759: iload_1
    //   8760: bipush 73
    //   8762: ior
    //   8763: iconst_1
    //   8764: ishl
    //   8765: iload_1
    //   8766: bipush 73
    //   8768: ixor
    //   8769: isub
    //   8770: istore_1
    //   8771: iload_1
    //   8772: sipush 128
    //   8775: irem
    //   8776: putstatic 30	o/O:ʼॱ	I
    //   8779: iload_1
    //   8780: iconst_2
    //   8781: irem
    //   8782: ifne +6 -> 8788
    //   8785: goto -6767 -> 2018
    //   8788: goto -5967 -> 2821
    //   8791: iconst_2
    //   8792: istore_3
    //   8793: goto -5913 -> 2880
    //   8796: goto +387 -> 9183
    //   8799: aload 10
    //   8801: athrow
    //   8802: aload 16
    //   8804: iconst_1
    //   8805: anewarray 329	java/lang/Class
    //   8808: dup
    //   8809: iconst_0
    //   8810: ldc 4
    //   8812: aastore
    //   8813: invokevirtual 339	java/lang/Class:getDeclaredConstructor	([Ljava/lang/Class;)Ljava/lang/reflect/Constructor;
    //   8816: astore 11
    //   8818: goto -4875 -> 3943
    //   8821: astore 10
    //   8823: aload 10
    //   8825: invokevirtual 349	java/lang/Throwable:getCause	()Ljava/lang/Throwable;
    //   8828: astore 11
    //   8830: aload 11
    //   8832: ifnull +6 -> 8838
    //   8835: goto +1800 -> 10635
    //   8838: goto +2075 -> 10913
    //   8841: iconst_0
    //   8842: istore_1
    //   8843: goto -5440 -> 3403
    //   8846: getstatic 310	o/O:ʿ	[S
    //   8849: bipush 45
    //   8851: saload
    //   8852: istore_1
    //   8853: iload_1
    //   8854: i2b
    //   8855: istore_1
    //   8856: goto +194 -> 9050
    //   8859: getstatic 28	o/O:ʽॱ	I
    //   8862: bipush 120
    //   8864: iadd
    //   8865: iconst_1
    //   8866: isub
    //   8867: istore_1
    //   8868: iload_1
    //   8869: sipush 128
    //   8872: irem
    //   8873: putstatic 30	o/O:ʼॱ	I
    //   8876: iload_1
    //   8877: iconst_2
    //   8878: irem
    //   8879: ifne +6 -> 8885
    //   8882: goto -5928 -> 2954
    //   8885: goto -6872 -> 2013
    //   8888: goto -6662 -> 2226
    //   8891: new 312	java/lang/String
    //   8894: dup
    //   8895: aload 11
    //   8897: invokespecial 315	java/lang/String:<init>	([C)V
    //   8900: astore 11
    //   8902: goto +385 -> 9287
    //   8905: getstatic 310	o/O:ʿ	[S
    //   8908: astore 10
    //   8910: goto +2069 -> 10979
    //   8913: aload 11
    //   8915: aload 13
    //   8917: iconst_3
    //   8918: anewarray 4	java/lang/Object
    //   8921: dup
    //   8922: iconst_0
    //   8923: aload 10
    //   8925: aastore
    //   8926: dup
    //   8927: iconst_1
    //   8928: aload 12
    //   8930: aastore
    //   8931: dup
    //   8932: iconst_2
    //   8933: iconst_1
    //   8934: invokestatic 413	java/lang/Boolean:valueOf	(Z)Ljava/lang/Boolean;
    //   8937: aastore
    //   8938: invokevirtual 376	java/lang/reflect/Method:invoke	(Ljava/lang/Object;[Ljava/lang/Object;)Ljava/lang/Object;
    //   8941: pop
    //   8942: aload 18
    //   8944: astore 10
    //   8946: goto -3898 -> 5048
    //   8949: astore 10
    //   8951: aload 10
    //   8953: invokevirtual 349	java/lang/Throwable:getCause	()Ljava/lang/Throwable;
    //   8956: astore 11
    //   8958: aload 11
    //   8960: ifnull +6 -> 8966
    //   8963: goto -4598 -> 4365
    //   8966: goto -167 -> 8799
    //   8969: aload 12
    //   8971: invokestatic 335	java/lang/Class:forName	(Ljava/lang/String;)Ljava/lang/Class;
    //   8974: astore 12
    //   8976: getstatic 310	o/O:ʿ	[S
    //   8979: astore 13
    //   8981: goto +2282 -> 11263
    //   8984: iload_1
    //   8985: tableswitch	default:+23->9008, 0:+-8441->544, 1:+-8581->404
    //   9008: goto -8464 -> 544
    //   9011: goto +2327 -> 11338
    //   9014: getstatic 28	o/O:ʽॱ	I
    //   9017: istore_3
    //   9018: iload_3
    //   9019: bipush 57
    //   9021: ior
    //   9022: iconst_1
    //   9023: ishl
    //   9024: iload_3
    //   9025: bipush 57
    //   9027: ixor
    //   9028: isub
    //   9029: istore_3
    //   9030: iload_3
    //   9031: sipush 128
    //   9034: irem
    //   9035: putstatic 30	o/O:ʼॱ	I
    //   9038: iload_3
    //   9039: iconst_2
    //   9040: irem
    //   9041: ifne +6 -> 9047
    //   9044: goto -3902 -> 5142
    //   9047: goto -256 -> 8791
    //   9050: bipush 76
    //   9052: iload_1
    //   9053: sipush 618
    //   9056: invokestatic 331	o/O:$$d	(IIS)Ljava/lang/String;
    //   9059: invokestatic 335	java/lang/Class:forName	(Ljava/lang/String;)Ljava/lang/Class;
    //   9062: astore 11
    //   9064: getstatic 310	o/O:ʿ	[S
    //   9067: astore 13
    //   9069: goto -8556 -> 513
    //   9072: iconst_1
    //   9073: istore_1
    //   9074: goto -4057 -> 5017
    //   9077: aload 10
    //   9079: athrow
    //   9080: astore 10
    //   9082: aload 10
    //   9084: invokevirtual 349	java/lang/Throwable:getCause	()Ljava/lang/Throwable;
    //   9087: astore 11
    //   9089: aload 11
    //   9091: ifnull +6 -> 9097
    //   9094: goto -5739 -> 3355
    //   9097: goto -8564 -> 533
    //   9100: aconst_null
    //   9101: astore 16
    //   9103: goto -8129 -> 974
    //   9106: goto -4905 -> 4201
    //   9109: sipush 178
    //   9112: getstatic 310	o/O:ʿ	[S
    //   9115: bipush 80
    //   9117: saload
    //   9118: i2b
    //   9119: sipush 612
    //   9122: invokestatic 331	o/O:$$d	(IIS)Ljava/lang/String;
    //   9125: invokestatic 335	java/lang/Class:forName	(Ljava/lang/String;)Ljava/lang/Class;
    //   9128: sipush 277
    //   9131: getstatic 310	o/O:ʿ	[S
    //   9134: bipush 6
    //   9136: saload
    //   9137: i2b
    //   9138: sipush 619
    //   9141: invokestatic 331	o/O:$$d	(IIS)Ljava/lang/String;
    //   9144: aconst_null
    //   9145: invokevirtual 393	java/lang/Class:getMethod	(Ljava/lang/String;[Ljava/lang/Class;)Ljava/lang/reflect/Method;
    //   9148: aload 12
    //   9150: aconst_null
    //   9151: invokevirtual 376	java/lang/reflect/Method:invoke	(Ljava/lang/Object;[Ljava/lang/Object;)Ljava/lang/Object;
    //   9154: pop
    //   9155: goto -6030 -> 3125
    //   9158: iload_1
    //   9159: tableswitch	default:+21->9180, 0:+-7993->1166, 1:+-7662->1497
    //   9180: goto -8014 -> 1166
    //   9183: iload_1
    //   9184: iload_2
    //   9185: sipush 612
    //   9188: invokestatic 331	o/O:$$d	(IIS)Ljava/lang/String;
    //   9191: invokestatic 335	java/lang/Class:forName	(Ljava/lang/String;)Ljava/lang/Class;
    //   9194: astore 11
    //   9196: getstatic 310	o/O:ʿ	[S
    //   9199: astore 12
    //   9201: goto -5542 -> 3659
    //   9204: aload 11
    //   9206: athrow
    //   9207: sipush 393
    //   9210: getstatic 310	o/O:ʿ	[S
    //   9213: sipush 142
    //   9216: saload
    //   9217: i2b
    //   9218: sipush 612
    //   9221: invokestatic 331	o/O:$$d	(IIS)Ljava/lang/String;
    //   9224: invokestatic 335	java/lang/Class:forName	(Ljava/lang/String;)Ljava/lang/Class;
    //   9227: sipush 325
    //   9230: getstatic 310	o/O:ʿ	[S
    //   9233: bipush 9
    //   9235: saload
    //   9236: i2b
    //   9237: sipush 615
    //   9240: invokestatic 331	o/O:$$d	(IIS)Ljava/lang/String;
    //   9243: aconst_null
    //   9244: invokevirtual 393	java/lang/Class:getMethod	(Ljava/lang/String;[Ljava/lang/Class;)Ljava/lang/reflect/Method;
    //   9247: aload 15
    //   9249: aconst_null
    //   9250: invokevirtual 376	java/lang/reflect/Method:invoke	(Ljava/lang/Object;[Ljava/lang/Object;)Ljava/lang/Object;
    //   9253: astore 20
    //   9255: goto -5475 -> 3780
    //   9258: aload 11
    //   9260: athrow
    //   9261: iconst_0
    //   9262: tableswitch	default:+22->9284, 0:+-6451->2811, 1:+-1->9261
    //   9284: goto -6473 -> 2811
    //   9287: goto -9131 -> 156
    //   9290: aload 12
    //   9292: ifnull +6 -> 9298
    //   9295: goto -223 -> 9072
    //   9298: goto -6451 -> 2847
    //   9301: aload 11
    //   9303: athrow
    //   9304: aload 12
    //   9306: astore 16
    //   9308: getstatic 310	o/O:ʿ	[S
    //   9311: astore 11
    //   9313: goto -6291 -> 3022
    //   9316: getstatic 30	o/O:ʼॱ	I
    //   9319: bipush 21
    //   9321: iadd
    //   9322: istore_1
    //   9323: iload_1
    //   9324: sipush 128
    //   9327: irem
    //   9328: putstatic 28	o/O:ʽॱ	I
    //   9331: iload_1
    //   9332: iconst_2
    //   9333: irem
    //   9334: ifeq +6 -> 9340
    //   9337: goto +242 -> 9579
    //   9340: goto +604 -> 9944
    //   9343: goto -7362 -> 1981
    //   9346: astore 10
    //   9348: aload 10
    //   9350: invokevirtual 349	java/lang/Throwable:getCause	()Ljava/lang/Throwable;
    //   9353: astore 11
    //   9355: aload 11
    //   9357: ifnull +6 -> 9363
    //   9360: goto -4161 -> 5199
    //   9363: goto -5525 -> 3838
    //   9366: goto -5600 -> 3766
    //   9369: getstatic 30	o/O:ʼॱ	I
    //   9372: istore_1
    //   9373: iload_1
    //   9374: bipush 51
    //   9376: ior
    //   9377: iconst_1
    //   9378: ishl
    //   9379: iload_1
    //   9380: bipush 51
    //   9382: ixor
    //   9383: isub
    //   9384: istore_1
    //   9385: iload_1
    //   9386: sipush 128
    //   9389: irem
    //   9390: putstatic 28	o/O:ʽॱ	I
    //   9393: iload_1
    //   9394: iconst_2
    //   9395: irem
    //   9396: ifeq +6 -> 9402
    //   9399: goto -6266 -> 3133
    //   9402: goto -9099 -> 303
    //   9405: astore 10
    //   9407: aload 10
    //   9409: invokevirtual 349	java/lang/Throwable:getCause	()Ljava/lang/Throwable;
    //   9412: astore 11
    //   9414: aload 11
    //   9416: ifnull +6 -> 9422
    //   9419: goto +997 -> 10416
    //   9422: goto -4408 -> 5014
    //   9425: astore 10
    //   9427: aload 10
    //   9429: invokevirtual 349	java/lang/Throwable:getCause	()Ljava/lang/Throwable;
    //   9432: astore 19
    //   9434: aload 19
    //   9436: ifnull +6 -> 9442
    //   9439: goto -8829 -> 610
    //   9442: goto +556 -> 9998
    //   9445: ldc_w 470
    //   9448: putstatic 353	o/O:ॱᐝ	I
    //   9451: ldc2_w 471
    //   9454: putstatic 351	o/O:ʻॱ	J
    //   9457: bipush 8
    //   9459: newarray byte
    //   9461: dup
    //   9462: iconst_0
    //   9463: ldc -84
    //   9465: bastore
    //   9466: dup
    //   9467: iconst_1
    //   9468: ldc -36
    //   9470: bastore
    //   9471: dup
    //   9472: iconst_2
    //   9473: ldc -128
    //   9475: bastore
    //   9476: dup
    //   9477: iconst_3
    //   9478: ldc -43
    //   9480: bastore
    //   9481: dup
    //   9482: iconst_4
    //   9483: ldc 118
    //   9485: bastore
    //   9486: dup
    //   9487: iconst_5
    //   9488: ldc -85
    //   9490: bastore
    //   9491: dup
    //   9492: bipush 6
    //   9494: ldc_w 257
    //   9497: bastore
    //   9498: dup
    //   9499: bipush 7
    //   9501: ldc -125
    //   9503: bastore
    //   9504: putstatic 355	o/O:ᐝॱ	[B
    //   9507: goto -8733 -> 774
    //   9510: aload 11
    //   9512: athrow
    //   9513: aload 10
    //   9515: sipush 325
    //   9518: aload 19
    //   9520: bipush 9
    //   9522: saload
    //   9523: i2b
    //   9524: sipush 615
    //   9527: invokestatic 331	o/O:$$d	(IIS)Ljava/lang/String;
    //   9530: aconst_null
    //   9531: invokevirtual 393	java/lang/Class:getMethod	(Ljava/lang/String;[Ljava/lang/Class;)Ljava/lang/reflect/Method;
    //   9534: astore 10
    //   9536: goto -5442 -> 4094
    //   9539: aload 19
    //   9541: astore 12
    //   9543: iload_1
    //   9544: lookupswitch	default:+28->9572, 63:+1587->11131, 94:+-5291->4253
    //   9572: aload 19
    //   9574: astore 12
    //   9576: goto +1555 -> 11131
    //   9579: goto +365 -> 9944
    //   9582: aload 11
    //   9584: ifnonnull +6 -> 9590
    //   9587: goto +1931 -> 11518
    //   9590: goto -749 -> 8841
    //   9593: aload 13
    //   9595: astore 11
    //   9597: aload 20
    //   9599: astore 10
    //   9601: aload 13
    //   9603: invokevirtual 476	java/lang/Object:getClass	()Ljava/lang/Class;
    //   9606: sipush 237
    //   9609: getstatic 310	o/O:ʿ	[S
    //   9612: bipush 107
    //   9614: saload
    //   9615: i2b
    //   9616: getstatic 429	o/O:ˈ	I
    //   9619: sipush 513
    //   9622: ior
    //   9623: i2s
    //   9624: invokestatic 331	o/O:$$d	(IIS)Ljava/lang/String;
    //   9627: iconst_3
    //   9628: anewarray 329	java/lang/Class
    //   9631: dup
    //   9632: iconst_0
    //   9633: ldc_w 312
    //   9636: aastore
    //   9637: dup
    //   9638: iconst_1
    //   9639: ldc_w 312
    //   9642: aastore
    //   9643: dup
    //   9644: iconst_2
    //   9645: getstatic 477	java/lang/Boolean:TYPE	Ljava/lang/Class;
    //   9648: aastore
    //   9649: invokevirtual 393	java/lang/Class:getMethod	(Ljava/lang/String;[Ljava/lang/Class;)Ljava/lang/reflect/Method;
    //   9652: astore 12
    //   9654: aload 13
    //   9656: astore 11
    //   9658: aload 12
    //   9660: astore 10
    //   9662: aload 13
    //   9664: invokevirtual 476	java/lang/Object:getClass	()Ljava/lang/Class;
    //   9667: sipush 281
    //   9670: getstatic 310	o/O:ʿ	[S
    //   9673: bipush 107
    //   9675: saload
    //   9676: i2b
    //   9677: sipush 615
    //   9680: invokestatic 331	o/O:$$d	(IIS)Ljava/lang/String;
    //   9683: iconst_1
    //   9684: anewarray 329	java/lang/Class
    //   9687: dup
    //   9688: iconst_0
    //   9689: ldc_w 312
    //   9692: aastore
    //   9693: invokevirtual 393	java/lang/Class:getMethod	(Ljava/lang/String;[Ljava/lang/Class;)Ljava/lang/reflect/Method;
    //   9696: astore 20
    //   9698: aload 20
    //   9700: astore 18
    //   9702: aload 13
    //   9704: astore 10
    //   9706: aload 12
    //   9708: astore 11
    //   9710: aload 18
    //   9712: astore 12
    //   9714: goto -8734 -> 980
    //   9717: aload 10
    //   9719: iconst_1
    //   9720: anewarray 329	java/lang/Class
    //   9723: dup
    //   9724: iconst_0
    //   9725: ldc_w 312
    //   9728: aastore
    //   9729: invokevirtual 339	java/lang/Class:getDeclaredConstructor	([Ljava/lang/Class;)Ljava/lang/reflect/Constructor;
    //   9732: iconst_1
    //   9733: anewarray 4	java/lang/Object
    //   9736: dup
    //   9737: iconst_0
    //   9738: aload 11
    //   9740: aastore
    //   9741: invokevirtual 404	java/lang/reflect/Constructor:newInstance	([Ljava/lang/Object;)Ljava/lang/Object;
    //   9744: astore 10
    //   9746: goto -7288 -> 2458
    //   9749: bipush 76
    //   9751: getstatic 310	o/O:ʿ	[S
    //   9754: bipush 45
    //   9756: saload
    //   9757: i2b
    //   9758: sipush 618
    //   9761: invokestatic 331	o/O:$$d	(IIS)Ljava/lang/String;
    //   9764: invokestatic 335	java/lang/Class:forName	(Ljava/lang/String;)Ljava/lang/Class;
    //   9767: sipush 200
    //   9770: getstatic 310	o/O:ʿ	[S
    //   9773: sipush 192
    //   9776: saload
    //   9777: i2b
    //   9778: sipush 610
    //   9781: invokestatic 331	o/O:$$d	(IIS)Ljava/lang/String;
    //   9784: iconst_3
    //   9785: anewarray 329	java/lang/Class
    //   9788: dup
    //   9789: iconst_0
    //   9790: ldc_w 312
    //   9793: aastore
    //   9794: dup
    //   9795: iconst_1
    //   9796: ldc_w 312
    //   9799: aastore
    //   9800: dup
    //   9801: iconst_2
    //   9802: getstatic 383	java/lang/Integer:TYPE	Ljava/lang/Class;
    //   9805: aastore
    //   9806: invokevirtual 393	java/lang/Class:getMethod	(Ljava/lang/String;[Ljava/lang/Class;)Ljava/lang/reflect/Method;
    //   9809: aconst_null
    //   9810: iconst_3
    //   9811: anewarray 4	java/lang/Object
    //   9814: dup
    //   9815: iconst_0
    //   9816: aload 11
    //   9818: aastore
    //   9819: dup
    //   9820: iconst_1
    //   9821: aload 10
    //   9823: aastore
    //   9824: dup
    //   9825: iconst_2
    //   9826: iconst_0
    //   9827: invokestatic 369	java/lang/Integer:valueOf	(I)Ljava/lang/Integer;
    //   9830: aastore
    //   9831: invokevirtual 376	java/lang/reflect/Method:invoke	(Ljava/lang/Object;[Ljava/lang/Object;)Ljava/lang/Object;
    //   9834: astore 10
    //   9836: goto -9686 -> 150
    //   9839: aload 18
    //   9841: sipush 354
    //   9844: saload
    //   9845: i2b
    //   9846: istore 5
    //   9848: iload_3
    //   9849: iload 5
    //   9851: iload 5
    //   9853: sipush 580
    //   9856: ixor
    //   9857: iload 5
    //   9859: sipush 580
    //   9862: iand
    //   9863: ior
    //   9864: i2s
    //   9865: invokestatic 331	o/O:$$d	(IIS)Ljava/lang/String;
    //   9868: astore 19
    //   9870: goto -7003 -> 2867
    //   9873: iload_3
    //   9874: istore_1
    //   9875: aload 11
    //   9877: astore 10
    //   9879: goto -8905 -> 974
    //   9882: astore 10
    //   9884: aload 10
    //   9886: invokevirtual 349	java/lang/Throwable:getCause	()Ljava/lang/Throwable;
    //   9889: astore 11
    //   9891: aload 11
    //   9893: ifnull +6 -> 9899
    //   9896: goto +1174 -> 11070
    //   9899: goto -5537 -> 4362
    //   9902: iconst_0
    //   9903: istore_1
    //   9904: goto -746 -> 9158
    //   9907: bipush 84
    //   9909: istore_1
    //   9910: goto -9339 -> 571
    //   9913: getstatic 310	o/O:ʿ	[S
    //   9916: bipush 54
    //   9918: saload
    //   9919: i2s
    //   9920: istore_1
    //   9921: getstatic 310	o/O:ʿ	[S
    //   9924: bipush 31
    //   9926: saload
    //   9927: istore_2
    //   9928: goto -7583 -> 2345
    //   9931: astore 10
    //   9933: aload 12
    //   9935: ifnonnull +6 -> 9941
    //   9938: goto -4824 -> 5114
    //   9941: goto -651 -> 9290
    //   9944: aload 12
    //   9946: iconst_1
    //   9947: anewarray 4	java/lang/Object
    //   9950: dup
    //   9951: iconst_0
    //   9952: aload 11
    //   9954: aastore
    //   9955: invokevirtual 404	java/lang/reflect/Constructor:newInstance	([Ljava/lang/Object;)Ljava/lang/Object;
    //   9958: astore 12
    //   9960: goto -6707 -> 3253
    //   9963: aload 10
    //   9965: athrow
    //   9966: sipush 393
    //   9969: iload_1
    //   9970: sipush 612
    //   9973: invokestatic 331	o/O:$$d	(IIS)Ljava/lang/String;
    //   9976: invokestatic 335	java/lang/Class:forName	(Ljava/lang/String;)Ljava/lang/Class;
    //   9979: astore 10
    //   9981: getstatic 310	o/O:ʿ	[S
    //   9984: bipush 9
    //   9986: saload
    //   9987: istore_1
    //   9988: goto -4786 -> 5202
    //   9991: getstatic 429	o/O:ˈ	I
    //   9994: istore_1
    //   9995: goto +643 -> 10638
    //   9998: aload 10
    //   10000: athrow
    //   10001: getstatic 310	o/O:ʿ	[S
    //   10004: astore 12
    //   10006: goto +413 -> 10419
    //   10009: aload 10
    //   10011: athrow
    //   10012: goto -5829 -> 4183
    //   10015: aload 10
    //   10017: athrow
    //   10018: aload 13
    //   10020: ifnull +6 -> 10026
    //   10023: goto -9823 -> 200
    //   10026: goto -8050 -> 1976
    //   10029: iconst_1
    //   10030: istore_1
    //   10031: goto -9779 -> 252
    //   10034: sipush 393
    //   10037: getstatic 310	o/O:ʿ	[S
    //   10040: sipush 21835
    //   10043: saload
    //   10044: i2b
    //   10045: sipush 26332
    //   10048: invokestatic 331	o/O:$$d	(IIS)Ljava/lang/String;
    //   10051: astore 11
    //   10053: goto -6144 -> 3909
    //   10056: aload 11
    //   10058: aload 13
    //   10060: iconst_2
    //   10061: anewarray 329	java/lang/Class
    //   10064: dup
    //   10065: iconst_0
    //   10066: ldc_w 312
    //   10069: aastore
    //   10070: dup
    //   10071: iconst_1
    //   10072: aload 18
    //   10074: invokestatic 335	java/lang/Class:forName	(Ljava/lang/String;)Ljava/lang/Class;
    //   10077: aastore
    //   10078: invokevirtual 393	java/lang/Class:getMethod	(Ljava/lang/String;[Ljava/lang/Class;)Ljava/lang/reflect/Method;
    //   10081: aload 10
    //   10083: iconst_2
    //   10084: anewarray 4	java/lang/Object
    //   10087: dup
    //   10088: iconst_0
    //   10089: aload 17
    //   10091: aastore
    //   10092: dup
    //   10093: iconst_1
    //   10094: aload 12
    //   10096: aastore
    //   10097: invokevirtual 376	java/lang/reflect/Method:invoke	(Ljava/lang/Object;[Ljava/lang/Object;)Ljava/lang/Object;
    //   10100: checkcast 329	java/lang/Class
    //   10103: astore 12
    //   10105: goto -7931 -> 2174
    //   10108: aload 10
    //   10110: athrow
    //   10111: aload 12
    //   10113: invokestatic 335	java/lang/Class:forName	(Ljava/lang/String;)Ljava/lang/Class;
    //   10116: astore 12
    //   10118: getstatic 310	o/O:ʿ	[S
    //   10121: sipush 166
    //   10124: saload
    //   10125: i2b
    //   10126: istore_3
    //   10127: getstatic 310	o/O:ʿ	[S
    //   10130: astore 13
    //   10132: goto -7505 -> 2627
    //   10135: iconst_1
    //   10136: istore_1
    //   10137: goto -4990 -> 5147
    //   10140: goto +933 -> 11073
    //   10143: aload 11
    //   10145: bipush 54
    //   10147: saload
    //   10148: i2b
    //   10149: istore 5
    //   10151: iload_3
    //   10152: iload 5
    //   10154: iload 5
    //   10156: sipush 612
    //   10159: ior
    //   10160: i2s
    //   10161: invokestatic 331	o/O:$$d	(IIS)Ljava/lang/String;
    //   10164: invokestatic 335	java/lang/Class:forName	(Ljava/lang/String;)Ljava/lang/Class;
    //   10167: astore 11
    //   10169: goto -9412 -> 757
    //   10172: astore 10
    //   10174: aload 10
    //   10176: invokevirtual 349	java/lang/Throwable:getCause	()Ljava/lang/Throwable;
    //   10179: astore 11
    //   10181: aload 11
    //   10183: ifnull +6 -> 10189
    //   10186: goto -9889 -> 297
    //   10189: goto -6632 -> 3557
    //   10192: bipush 16
    //   10194: istore_2
    //   10195: sipush 13889
    //   10198: istore_1
    //   10199: goto -1099 -> 9100
    //   10202: aload 10
    //   10204: bipush 51
    //   10206: saload
    //   10207: i2s
    //   10208: getstatic 310	o/O:ʿ	[S
    //   10211: bipush 85
    //   10213: saload
    //   10214: i2b
    //   10215: sipush 1571
    //   10218: invokestatic 331	o/O:$$d	(IIS)Ljava/lang/String;
    //   10221: astore 10
    //   10223: goto -5855 -> 4368
    //   10226: aload 10
    //   10228: athrow
    //   10229: aconst_null
    //   10230: astore 10
    //   10232: goto +255 -> 10487
    //   10235: iconst_1
    //   10236: istore_1
    //   10237: goto -5963 -> 4274
    //   10240: goto -5120 -> 5120
    //   10243: sipush 393
    //   10246: iload_1
    //   10247: sipush 612
    //   10250: invokestatic 331	o/O:$$d	(IIS)Ljava/lang/String;
    //   10253: invokestatic 335	java/lang/Class:forName	(Ljava/lang/String;)Ljava/lang/Class;
    //   10256: astore 11
    //   10258: getstatic 310	o/O:ʿ	[S
    //   10261: astore 13
    //   10263: goto -1508 -> 8755
    //   10266: aload 13
    //   10268: astore 11
    //   10270: aload 20
    //   10272: astore 10
    //   10274: bipush 105
    //   10276: iload_1
    //   10277: sipush 610
    //   10280: invokestatic 331	o/O:$$d	(IIS)Ljava/lang/String;
    //   10283: invokestatic 335	java/lang/Class:forName	(Ljava/lang/String;)Ljava/lang/Class;
    //   10286: astore 24
    //   10288: aload 24
    //   10290: ifnull +6 -> 10296
    //   10293: goto -158 -> 10135
    //   10296: goto -8024 -> 2272
    //   10299: goto -1637 -> 8662
    //   10302: bipush 63
    //   10304: istore_1
    //   10305: goto -5226 -> 5079
    //   10308: goto -8732 -> 1576
    //   10311: aload 10
    //   10313: aconst_null
    //   10314: aconst_null
    //   10315: invokevirtual 376	java/lang/reflect/Method:invoke	(Ljava/lang/Object;[Ljava/lang/Object;)Ljava/lang/Object;
    //   10318: astore 10
    //   10320: goto -5669 -> 4651
    //   10323: aload 11
    //   10325: athrow
    //   10326: iload_2
    //   10327: ineg
    //   10328: istore 6
    //   10330: goto +172 -> 10502
    //   10333: aload 11
    //   10335: athrow
    //   10336: goto -8243 -> 2093
    //   10339: getstatic 310	o/O:ʿ	[S
    //   10342: bipush 31
    //   10344: saload
    //   10345: i2b
    //   10346: istore_1
    //   10347: sipush 286
    //   10350: iload_1
    //   10351: iload_1
    //   10352: sipush 641
    //   10355: ior
    //   10356: i2s
    //   10357: invokestatic 331	o/O:$$d	(IIS)Ljava/lang/String;
    //   10360: astore 14
    //   10362: goto -7586 -> 2776
    //   10365: goto -8685 -> 1680
    //   10368: goto -9327 -> 1041
    //   10371: astore 10
    //   10373: aload 10
    //   10375: invokevirtual 349	java/lang/Throwable:getCause	()Ljava/lang/Throwable;
    //   10378: astore 19
    //   10380: aload 19
    //   10382: ifnull +6 -> 10388
    //   10385: goto -9341 -> 1044
    //   10388: goto -9847 -> 541
    //   10391: iload_1
    //   10392: sipush 641
    //   10395: ior
    //   10396: i2s
    //   10397: istore_0
    //   10398: sipush 286
    //   10401: iload_1
    //   10402: iload_0
    //   10403: invokestatic 331	o/O:$$d	(IIS)Ljava/lang/String;
    //   10406: astore 10
    //   10408: goto -1495 -> 8913
    //   10411: iconst_1
    //   10412: istore_1
    //   10413: goto -6630 -> 3783
    //   10416: aload 11
    //   10418: athrow
    //   10419: getstatic 28	o/O:ʽॱ	I
    //   10422: istore_1
    //   10423: iload_1
    //   10424: bipush 71
    //   10426: iand
    //   10427: iload_1
    //   10428: bipush 71
    //   10430: ior
    //   10431: iadd
    //   10432: istore_1
    //   10433: iload_1
    //   10434: sipush 128
    //   10437: irem
    //   10438: putstatic 30	o/O:ʼॱ	I
    //   10441: iload_1
    //   10442: iconst_2
    //   10443: irem
    //   10444: ifne +6 -> 10450
    //   10447: goto -5524 -> 4923
    //   10450: goto -10339 -> 111
    //   10453: aload 18
    //   10455: aload 19
    //   10457: iconst_3
    //   10458: anewarray 329	java/lang/Class
    //   10461: dup
    //   10462: iconst_0
    //   10463: ldc_w 379
    //   10466: aastore
    //   10467: dup
    //   10468: iconst_1
    //   10469: getstatic 383	java/lang/Integer:TYPE	Ljava/lang/Class;
    //   10472: aastore
    //   10473: dup
    //   10474: iconst_2
    //   10475: getstatic 383	java/lang/Integer:TYPE	Ljava/lang/Class;
    //   10478: aastore
    //   10479: invokevirtual 393	java/lang/Class:getMethod	(Ljava/lang/String;[Ljava/lang/Class;)Ljava/lang/reflect/Method;
    //   10482: astore 18
    //   10484: goto -1470 -> 9014
    //   10487: aload 10
    //   10489: ifnull +6 -> 10495
    //   10492: goto -5630 -> 4862
    //   10495: aload 12
    //   10497: astore 11
    //   10499: goto -917 -> 9582
    //   10502: goto -5958 -> 4544
    //   10505: aload 11
    //   10507: athrow
    //   10508: getstatic 310	o/O:ʿ	[S
    //   10511: bipush 6
    //   10513: saload
    //   10514: istore_1
    //   10515: iload_1
    //   10516: i2b
    //   10517: istore_1
    //   10518: goto -10310 -> 208
    //   10521: aload 11
    //   10523: ifnull +6 -> 10529
    //   10526: goto +97 -> 10623
    //   10529: goto +100 -> 10629
    //   10532: aload 11
    //   10534: invokestatic 335	java/lang/Class:forName	(Ljava/lang/String;)Ljava/lang/Class;
    //   10537: astore 12
    //   10539: goto -1904 -> 8635
    //   10542: aload 19
    //   10544: athrow
    //   10545: aload 10
    //   10547: aload 22
    //   10549: iconst_3
    //   10550: anewarray 329	java/lang/Class
    //   10553: dup
    //   10554: iconst_0
    //   10555: ldc_w 312
    //   10558: aastore
    //   10559: dup
    //   10560: iconst_1
    //   10561: ldc_w 312
    //   10564: aastore
    //   10565: dup
    //   10566: iconst_2
    //   10567: aload 21
    //   10569: aastore
    //   10570: invokevirtual 393	java/lang/Class:getMethod	(Ljava/lang/String;[Ljava/lang/Class;)Ljava/lang/reflect/Method;
    //   10573: aconst_null
    //   10574: iconst_3
    //   10575: anewarray 4	java/lang/Object
    //   10578: dup
    //   10579: iconst_0
    //   10580: aload 19
    //   10582: aastore
    //   10583: dup
    //   10584: iconst_1
    //   10585: aload 20
    //   10587: aastore
    //   10588: dup
    //   10589: iconst_2
    //   10590: iconst_0
    //   10591: invokestatic 369	java/lang/Integer:valueOf	(I)Ljava/lang/Integer;
    //   10594: aastore
    //   10595: invokevirtual 376	java/lang/reflect/Method:invoke	(Ljava/lang/Object;[Ljava/lang/Object;)Ljava/lang/Object;
    //   10598: astore 10
    //   10600: aload 10
    //   10602: astore 18
    //   10604: aload 12
    //   10606: ifnull +6 -> 10612
    //   10609: goto -7734 -> 2875
    //   10612: goto -201 -> 10411
    //   10615: getstatic 310	o/O:ʿ	[S
    //   10618: astore 12
    //   10620: goto -8566 -> 2054
    //   10623: bipush 94
    //   10625: istore_1
    //   10626: goto -1087 -> 9539
    //   10629: bipush 63
    //   10631: istore_1
    //   10632: goto -1093 -> 9539
    //   10635: aload 11
    //   10637: athrow
    //   10638: iload_1
    //   10639: bipush 32
    //   10641: ixor
    //   10642: iload_1
    //   10643: bipush 32
    //   10645: iand
    //   10646: ior
    //   10647: i2s
    //   10648: istore_1
    //   10649: iload_1
    //   10650: getstatic 310	o/O:ʿ	[S
    //   10653: bipush 45
    //   10655: saload
    //   10656: i2b
    //   10657: sipush 612
    //   10660: invokestatic 331	o/O:$$d	(IIS)Ljava/lang/String;
    //   10663: astore 18
    //   10665: goto -609 -> 10056
    //   10668: aload 11
    //   10670: iconst_3
    //   10671: anewarray 329	java/lang/Class
    //   10674: dup
    //   10675: iconst_0
    //   10676: ldc_w 379
    //   10679: aastore
    //   10680: dup
    //   10681: iconst_1
    //   10682: getstatic 383	java/lang/Integer:TYPE	Ljava/lang/Class;
    //   10685: aastore
    //   10686: dup
    //   10687: iconst_2
    //   10688: getstatic 383	java/lang/Integer:TYPE	Ljava/lang/Class;
    //   10691: aastore
    //   10692: invokevirtual 339	java/lang/Class:getDeclaredConstructor	([Ljava/lang/Class;)Ljava/lang/reflect/Constructor;
    //   10695: astore 11
    //   10697: goto -6281 -> 4416
    //   10700: bipush 48
    //   10702: istore_1
    //   10703: goto -9277 -> 1426
    //   10706: aload 10
    //   10708: athrow
    //   10709: getstatic 310	o/O:ʿ	[S
    //   10712: bipush 31
    //   10714: saload
    //   10715: i2b
    //   10716: istore_1
    //   10717: aload 11
    //   10719: aload 13
    //   10721: iconst_3
    //   10722: anewarray 4	java/lang/Object
    //   10725: dup
    //   10726: iconst_0
    //   10727: sipush 286
    //   10730: iload_1
    //   10731: iload_1
    //   10732: sipush 641
    //   10735: ixor
    //   10736: iload_1
    //   10737: sipush 641
    //   10740: iand
    //   10741: ior
    //   10742: i2s
    //   10743: invokestatic 331	o/O:$$d	(IIS)Ljava/lang/String;
    //   10746: aastore
    //   10747: dup
    //   10748: iconst_1
    //   10749: aload 12
    //   10751: aastore
    //   10752: dup
    //   10753: iconst_2
    //   10754: iconst_1
    //   10755: invokestatic 413	java/lang/Boolean:valueOf	(Z)Ljava/lang/Boolean;
    //   10758: aastore
    //   10759: invokevirtual 376	java/lang/reflect/Method:invoke	(Ljava/lang/Object;[Ljava/lang/Object;)Ljava/lang/Object;
    //   10762: pop
    //   10763: aload 18
    //   10765: astore 10
    //   10767: goto -5719 -> 5048
    //   10770: ldc_w 329
    //   10773: sipush 245
    //   10776: getstatic 310	o/O:ʿ	[S
    //   10779: sipush 315
    //   10782: saload
    //   10783: i2b
    //   10784: sipush 615
    //   10787: invokestatic 331	o/O:$$d	(IIS)Ljava/lang/String;
    //   10790: aconst_null
    //   10791: invokevirtual 393	java/lang/Class:getMethod	(Ljava/lang/String;[Ljava/lang/Class;)Ljava/lang/reflect/Method;
    //   10794: ldc 2
    //   10796: aconst_null
    //   10797: invokevirtual 376	java/lang/reflect/Method:invoke	(Ljava/lang/Object;[Ljava/lang/Object;)Ljava/lang/Object;
    //   10800: astore 12
    //   10802: goto -7843 -> 2959
    //   10805: getstatic 30	o/O:ʼॱ	I
    //   10808: bipush 6
    //   10810: iadd
    //   10811: iconst_1
    //   10812: isub
    //   10813: istore_1
    //   10814: iload_1
    //   10815: sipush 128
    //   10818: irem
    //   10819: putstatic 28	o/O:ʽॱ	I
    //   10822: iload_1
    //   10823: iconst_2
    //   10824: irem
    //   10825: ifeq +6 -> 10831
    //   10828: goto -9637 -> 1191
    //   10831: goto -7711 -> 3120
    //   10834: aload 12
    //   10836: iconst_2
    //   10837: anewarray 4	java/lang/Object
    //   10840: dup
    //   10841: iconst_0
    //   10842: aload 11
    //   10844: aastore
    //   10845: dup
    //   10846: iconst_1
    //   10847: aload 10
    //   10849: aastore
    //   10850: invokevirtual 404	java/lang/reflect/Constructor:newInstance	([Ljava/lang/Object;)Ljava/lang/Object;
    //   10853: checkcast 345	java/lang/Throwable
    //   10856: athrow
    //   10857: goto -6262 -> 4595
    //   10860: aload 15
    //   10862: ifnonnull +6 -> 10868
    //   10865: goto -9498 -> 1367
    //   10868: goto -6895 -> 3973
    //   10871: goto +531 -> 11402
    //   10874: iload_3
    //   10875: sipush 513
    //   10878: ixor
    //   10879: iload_3
    //   10880: sipush 513
    //   10883: iand
    //   10884: ior
    //   10885: i2s
    //   10886: istore_0
    //   10887: sipush 142
    //   10890: iload_2
    //   10891: iload_0
    //   10892: invokestatic 331	o/O:$$d	(IIS)Ljava/lang/String;
    //   10895: astore 11
    //   10897: iconst_1
    //   10898: anewarray 329	java/lang/Class
    //   10901: astore 12
    //   10903: iconst_0
    //   10904: istore_1
    //   10905: getstatic 390	java/lang/Long:TYPE	Ljava/lang/Class;
    //   10908: astore 13
    //   10910: goto -9687 -> 1223
    //   10913: aload 10
    //   10915: athrow
    //   10916: iload_1
    //   10917: i2b
    //   10918: istore_1
    //   10919: aload 11
    //   10921: sipush 362
    //   10924: iload_1
    //   10925: sipush 619
    //   10928: invokestatic 331	o/O:$$d	(IIS)Ljava/lang/String;
    //   10931: aconst_null
    //   10932: invokevirtual 393	java/lang/Class:getMethod	(Ljava/lang/String;[Ljava/lang/Class;)Ljava/lang/reflect/Method;
    //   10935: aload 10
    //   10937: aconst_null
    //   10938: invokevirtual 376	java/lang/reflect/Method:invoke	(Ljava/lang/Object;[Ljava/lang/Object;)Ljava/lang/Object;
    //   10941: astore 11
    //   10943: goto -6739 -> 4204
    //   10946: getstatic 310	o/O:ʿ	[S
    //   10949: sipush 142
    //   10952: saload
    //   10953: istore_1
    //   10954: iload_1
    //   10955: i2b
    //   10956: istore_1
    //   10957: goto -714 -> 10243
    //   10960: aload 10
    //   10962: athrow
    //   10963: aload 10
    //   10965: athrow
    //   10966: getstatic 310	o/O:ʿ	[S
    //   10969: bipush 61
    //   10971: saload
    //   10972: istore_1
    //   10973: iload_1
    //   10974: i2b
    //   10975: istore_1
    //   10976: goto -6214 -> 4762
    //   10979: sipush 178
    //   10982: aload 10
    //   10984: bipush 80
    //   10986: saload
    //   10987: i2b
    //   10988: sipush 612
    //   10991: invokestatic 331	o/O:$$d	(IIS)Ljava/lang/String;
    //   10994: invokestatic 335	java/lang/Class:forName	(Ljava/lang/String;)Ljava/lang/Class;
    //   10997: astore 13
    //   10999: getstatic 310	o/O:ʿ	[S
    //   11002: astore 10
    //   11004: goto -7640 -> 3364
    //   11007: goto -7568 -> 3439
    //   11010: astore 10
    //   11012: new 441	java/lang/StringBuilder
    //   11015: dup
    //   11016: invokespecial 442	java/lang/StringBuilder:<init>	()V
    //   11019: sipush 404
    //   11022: getstatic 310	o/O:ʿ	[S
    //   11025: bipush 6
    //   11027: saload
    //   11028: i2b
    //   11029: sipush 649
    //   11032: invokestatic 331	o/O:$$d	(IIS)Ljava/lang/String;
    //   11035: invokevirtual 446	java/lang/StringBuilder:append	(Ljava/lang/String;)Ljava/lang/StringBuilder;
    //   11038: aload 11
    //   11040: invokevirtual 449	java/lang/StringBuilder:append	(Ljava/lang/Object;)Ljava/lang/StringBuilder;
    //   11043: bipush 76
    //   11045: getstatic 310	o/O:ʿ	[S
    //   11048: sipush 166
    //   11051: saload
    //   11052: i2b
    //   11053: sipush 677
    //   11056: invokestatic 331	o/O:$$d	(IIS)Ljava/lang/String;
    //   11059: invokevirtual 446	java/lang/StringBuilder:append	(Ljava/lang/String;)Ljava/lang/StringBuilder;
    //   11062: invokevirtual 453	java/lang/StringBuilder:toString	()Ljava/lang/String;
    //   11065: astore 11
    //   11067: goto -196 -> 10871
    //   11070: aload 11
    //   11072: athrow
    //   11073: aload 12
    //   11075: iconst_0
    //   11076: saload
    //   11077: i2b
    //   11078: istore_1
    //   11079: sipush 339
    //   11082: iload_1
    //   11083: iload_1
    //   11084: sipush 608
    //   11087: ixor
    //   11088: iload_1
    //   11089: sipush 608
    //   11092: iand
    //   11093: ior
    //   11094: i2s
    //   11095: invokestatic 331	o/O:$$d	(IIS)Ljava/lang/String;
    //   11098: invokestatic 335	java/lang/Class:forName	(Ljava/lang/String;)Ljava/lang/Class;
    //   11101: astore 13
    //   11103: goto -1102 -> 10001
    //   11106: iconst_1
    //   11107: istore_1
    //   11108: goto -1950 -> 9158
    //   11111: aload 11
    //   11113: iconst_1
    //   11114: anewarray 4	java/lang/Object
    //   11117: dup
    //   11118: iconst_0
    //   11119: aload 10
    //   11121: aastore
    //   11122: invokevirtual 404	java/lang/reflect/Constructor:newInstance	([Ljava/lang/Object;)Ljava/lang/Object;
    //   11125: putstatic 378	o/O:ॱˋ	Ljava/lang/Object;
    //   11128: goto -9839 -> 1289
    //   11131: aconst_null
    //   11132: astore 18
    //   11134: goto -8152 -> 2982
    //   11137: aload 10
    //   11139: bipush 12
    //   11141: saload
    //   11142: i2s
    //   11143: getstatic 310	o/O:ʿ	[S
    //   11146: bipush 50
    //   11148: saload
    //   11149: i2b
    //   11150: sipush 604
    //   11153: invokestatic 331	o/O:$$d	(IIS)Ljava/lang/String;
    //   11156: astore 10
    //   11158: goto -6790 -> 4368
    //   11161: aload 11
    //   11163: athrow
    //   11164: sipush 457
    //   11167: getstatic 310	o/O:ʿ	[S
    //   11170: bipush 11
    //   11172: saload
    //   11173: i2b
    //   11174: sipush 612
    //   11177: invokestatic 331	o/O:$$d	(IIS)Ljava/lang/String;
    //   11180: invokestatic 335	java/lang/Class:forName	(Ljava/lang/String;)Ljava/lang/Class;
    //   11183: astore 12
    //   11185: getstatic 310	o/O:ʿ	[S
    //   11188: sipush 354
    //   11191: saload
    //   11192: i2b
    //   11193: istore_3
    //   11194: aload 12
    //   11196: sipush 242
    //   11199: iload_3
    //   11200: iload_3
    //   11201: sipush 579
    //   11204: ixor
    //   11205: iload_3
    //   11206: sipush 579
    //   11209: iand
    //   11210: ior
    //   11211: i2s
    //   11212: invokestatic 331	o/O:$$d	(IIS)Ljava/lang/String;
    //   11215: iconst_1
    //   11216: anewarray 329	java/lang/Class
    //   11219: dup
    //   11220: iconst_0
    //   11221: getstatic 390	java/lang/Long:TYPE	Ljava/lang/Class;
    //   11224: aastore
    //   11225: invokevirtual 393	java/lang/Class:getMethod	(Ljava/lang/String;[Ljava/lang/Class;)Ljava/lang/reflect/Method;
    //   11228: aload 10
    //   11230: iconst_1
    //   11231: anewarray 4	java/lang/Object
    //   11234: dup
    //   11235: iconst_0
    //   11236: ldc2_w 478
    //   11239: invokestatic 398	java/lang/Long:valueOf	(J)Ljava/lang/Long;
    //   11242: aastore
    //   11243: invokevirtual 376	java/lang/reflect/Method:invoke	(Ljava/lang/Object;[Ljava/lang/Object;)Ljava/lang/Object;
    //   11246: checkcast 389	java/lang/Long
    //   11249: invokevirtual 418	java/lang/Long:longValue	()J
    //   11252: pop2
    //   11253: sipush 1024
    //   11256: newarray byte
    //   11258: astore 12
    //   11260: goto -9216 -> 2044
    //   11263: getstatic 30	o/O:ʼॱ	I
    //   11266: istore_1
    //   11267: iload_1
    //   11268: bipush 101
    //   11270: ixor
    //   11271: iload_1
    //   11272: bipush 101
    //   11274: iand
    //   11275: iconst_1
    //   11276: ishl
    //   11277: iadd
    //   11278: istore_1
    //   11279: iload_1
    //   11280: sipush 128
    //   11283: irem
    //   11284: putstatic 28	o/O:ʽॱ	I
    //   11287: iload_1
    //   11288: iconst_2
    //   11289: irem
    //   11290: ifeq +6 -> 11296
    //   11293: goto -1950 -> 9343
    //   11296: goto -9315 -> 1981
    //   11299: aload 10
    //   11301: athrow
    //   11302: aload 13
    //   11304: iconst_0
    //   11305: aload 15
    //   11307: invokestatic 335	java/lang/Class:forName	(Ljava/lang/String;)Ljava/lang/Class;
    //   11310: aastore
    //   11311: aload 13
    //   11313: iconst_1
    //   11314: ldc_w 312
    //   11317: aastore
    //   11318: aload 11
    //   11320: aload 13
    //   11322: invokevirtual 339	java/lang/Class:getDeclaredConstructor	([Ljava/lang/Class;)Ljava/lang/reflect/Constructor;
    //   11325: astore 11
    //   11327: goto -9113 -> 2214
    //   11330: aload 11
    //   11332: athrow
    //   11333: iconst_4
    //   11334: istore_1
    //   11335: goto -475 -> 10860
    //   11338: sipush 393
    //   11341: getstatic 310	o/O:ʿ	[S
    //   11344: sipush 142
    //   11347: saload
    //   11348: i2b
    //   11349: sipush 612
    //   11352: invokestatic 331	o/O:$$d	(IIS)Ljava/lang/String;
    //   11355: invokestatic 335	java/lang/Class:forName	(Ljava/lang/String;)Ljava/lang/Class;
    //   11358: sipush 268
    //   11361: getstatic 310	o/O:ʿ	[S
    //   11364: bipush 107
    //   11366: saload
    //   11367: i2b
    //   11368: sipush 618
    //   11371: invokestatic 331	o/O:$$d	(IIS)Ljava/lang/String;
    //   11374: aconst_null
    //   11375: invokevirtual 393	java/lang/Class:getMethod	(Ljava/lang/String;[Ljava/lang/Class;)Ljava/lang/reflect/Method;
    //   11378: aload 15
    //   11380: aconst_null
    //   11381: invokevirtual 376	java/lang/reflect/Method:invoke	(Ljava/lang/Object;[Ljava/lang/Object;)Ljava/lang/Object;
    //   11384: checkcast 406	java/lang/Boolean
    //   11387: invokevirtual 410	java/lang/Boolean:booleanValue	()Z
    //   11390: pop
    //   11391: aload 12
    //   11393: ifnull +6 -> 11399
    //   11396: goto -2092 -> 9304
    //   11399: goto -6276 -> 5123
    //   11402: sipush 369
    //   11405: getstatic 310	o/O:ʿ	[S
    //   11408: bipush 11
    //   11410: saload
    //   11411: i2b
    //   11412: sipush 612
    //   11415: invokestatic 331	o/O:$$d	(IIS)Ljava/lang/String;
    //   11418: invokestatic 335	java/lang/Class:forName	(Ljava/lang/String;)Ljava/lang/Class;
    //   11421: astore 12
    //   11423: goto -6876 -> 4547
    //   11426: sipush 301
    //   11429: getstatic 310	o/O:ʿ	[S
    //   11432: sipush 315
    //   11435: saload
    //   11436: i2b
    //   11437: sipush 612
    //   11440: invokestatic 331	o/O:$$d	(IIS)Ljava/lang/String;
    //   11443: astore 10
    //   11445: goto -8449 -> 2996
    //   11448: iload_1
    //   11449: sipush 614
    //   11452: ixor
    //   11453: iload_1
    //   11454: sipush 614
    //   11457: iand
    //   11458: ior
    //   11459: i2s
    //   11460: istore_0
    //   11461: aload 10
    //   11463: sipush 152
    //   11466: iload_1
    //   11467: iload_0
    //   11468: invokestatic 331	o/O:$$d	(IIS)Ljava/lang/String;
    //   11471: aconst_null
    //   11472: invokevirtual 393	java/lang/Class:getMethod	(Ljava/lang/String;[Ljava/lang/Class;)Ljava/lang/reflect/Method;
    //   11475: astore 10
    //   11477: goto -1166 -> 10311
    //   11480: aload 11
    //   11482: aload 12
    //   11484: iconst_1
    //   11485: anewarray 329	java/lang/Class
    //   11488: dup
    //   11489: iconst_0
    //   11490: ldc_w 312
    //   11493: aastore
    //   11494: invokevirtual 393	java/lang/Class:getMethod	(Ljava/lang/String;[Ljava/lang/Class;)Ljava/lang/reflect/Method;
    //   11497: aconst_null
    //   11498: iconst_1
    //   11499: anewarray 4	java/lang/Object
    //   11502: dup
    //   11503: iconst_0
    //   11504: aload 10
    //   11506: aastore
    //   11507: invokevirtual 376	java/lang/reflect/Method:invoke	(Ljava/lang/Object;[Ljava/lang/Object;)Ljava/lang/Object;
    //   11510: astore 11
    //   11512: goto -9572 -> 1940
    //   11515: goto -2146 -> 9369
    //   11518: iconst_1
    //   11519: istore_1
    //   11520: goto -8117 -> 3403
    //   11523: goto -1650 -> 9873
    // Local variable table:
    //   start	length	slot	name	signature
    //   214	11254	0	s	short
    //   45	11475	1	i	int
    //   858	10033	2	j	int
    //   441	10769	3	k	int
    //   25	8523	4	m	int
    //   451	9709	5	n	int
    //   461	9868	6	i1	int
    //   1748	2467	7	bool	boolean
    //   1246	1	8	localObject1	Object
    //   2857	1	8	l	long
    //   11	290	10	localObject2	Object
    //   317	151	10	localInputStream1	java.io.InputStream
    //   508	320	10	localObject3	Object
    //   877	3	10	localObject4	Object
    //   909	78	10	localObject5	Object
    //   1001	3	10	localObject6	Object
    //   1021	71	10	localObject7	Object
    //   1146	3	10	localObject8	Object
    //   1269	73	10	localObject9	Object
    //   1344	80	10	localObject10	Object
    //   1474	53	10	localObject11	Object
    //   1571	166	10	localObject12	Object
    //   1797	3	10	localObject13	Object
    //   1833	1	10	str1	String
    //   2128	3	10	localObject14	Object
    //   2154	3	10	localObject15	Object
    //   2204	36	10	localObject16	Object
    //   2252	88	10	localObject17	Object
    //   2367	3	10	localIndexOutOfBoundsException	IndexOutOfBoundsException
    //   2381	195	10	localObject18	Object
    //   2604	3	10	localObject19	Object
    //   2661	3	10	localObject20	Object
    //   2729	3	10	localObject21	Object
    //   2862	3	10	localRuntimeException	RuntimeException
    //   2911	24	10	localObject22	Object
    //   2962	3	10	localObject23	Object
    //   3053	3	10	localObject24	Object
    //   3073	72	10	localException1	Exception
    //   3312	3	10	localObject25	Object
    //   3332	3	10	localObject26	Object
    //   3405	156	10	localObject27	Object
    //   3574	49	10	localObject28	Object
    //   3785	221	10	localObject29	Object
    //   4026	69	10	localException2	Exception
    //   4154	172	10	localObject30	Object
    //   4328	43	10	str2	String
    //   4403	22	10	localObject31	Object
    //   4457	1	10	localInputStream2	java.io.InputStream
    //   4518	3	10	localObject32	Object
    //   4654	78	10	localObject33	Object
    //   4775	274	10	localObject34	Object
    //   5059	59	10	localObject35	Object
    //   5149	57	10	localObject36	Object
    //   8552	3	10	localObject37	Object
    //   8575	3	10	localObject38	Object
    //   8595	3	10	localObject39	Object
    //   8615	86	10	localObject40	Object
    //   8735	65	10	localObject41	Object
    //   8821	3	10	localObject42	Object
    //   8908	37	10	localObject43	Object
    //   8949	129	10	localObject44	Object
    //   9080	3	10	localObject45	Object
    //   9346	3	10	localObject46	Object
    //   9405	3	10	localObject47	Object
    //   9425	89	10	localObject48	Object
    //   9534	344	10	localObject49	Object
    //   9882	3	10	localObject50	Object
    //   9931	33	10	localException3	Exception
    //   9979	130	10	localClass1	Class
    //   10172	31	10	localObject51	Object
    //   10221	98	10	localObject52	Object
    //   10371	3	10	localObject53	Object
    //   10406	597	10	localObject54	Object
    //   11010	128	10	localException4	Exception
    //   11156	349	10	localObject55	Object
    //   61	11450	11	localObject56	Object
    //   65	888	12	localObject57	Object
    //   957	28	12	localException5	Exception
    //   1076	10407	12	localObject58	Object
    //   17	11304	13	localObject59	Object
    //   1229	9132	14	localObject60	Object
    //   233	11146	15	localObject61	Object
    //   1238	8069	16	localObject62	Object
    //   3048	7042	17	str3	String
    //   852	10281	18	localObject63	Object
    //   610	9971	19	localObject64	Object
    //   185	10401	20	localObject65	Object
    //   63	10505	21	localObject66	Object
    //   59	10489	22	str4	String
    //   2237	2948	23	localObject67	Object
    //   8737	1552	24	localClass2	Class
    // Exception table:
    //   from	to	target	type
    //   9109	9155	317	finally
    //   9749	9836	877	finally
    //   189	197	957	java/lang/Exception
    //   2383	2391	957	java/lang/Exception
    //   4007	4015	957	java/lang/Exception
    //   8737	8752	957	java/lang/Exception
    //   9601	9654	957	java/lang/Exception
    //   9662	9698	957	java/lang/Exception
    //   10274	10288	957	java/lang/Exception
    //   11164	11253	1001	finally
    //   2277	2336	1021	finally
    //   2713	2726	1146	finally
    //   4416	4459	1146	finally
    //   10151	10169	1146	finally
    //   10668	10697	1146	finally
    //   1196	1212	1269	finally
    //   2106	2114	1269	finally
    //   2120	2125	1269	finally
    //   2431	2455	1269	finally
    //   3004	3014	1269	finally
    //   3100	3109	1269	finally
    //   4183	4198	1269	finally
    //   4926	4936	1269	finally
    //   10453	10484	1269	finally
    //   409	415	1344	finally
    //   544	550	1344	finally
    //   2348	2361	1344	finally
    //   2852	2859	1344	finally
    //   4835	4859	1344	finally
    //   9913	9928	1344	finally
    //   2749	2770	1474	finally
    //   3766	3774	1474	finally
    //   4204	4214	1474	finally
    //   10919	10943	1474	finally
    //   3909	3940	1797	finally
    //   4573	4592	1797	finally
    //   4595	4623	1797	finally
    //   10034	10053	1797	finally
    //   10532	10539	1797	finally
    //   111	144	2128	finally
    //   9944	9960	2128	finally
    //   10001	10006	2128	finally
    //   10615	10620	2128	finally
    //   11079	11103	2128	finally
    //   1558	1573	2154	finally
    //   4798	4806	2154	finally
    //   9717	9746	2154	finally
    //   3493	3554	2252	finally
    //   1761	1765	2367	java/lang/IndexOutOfBoundsException
    //   1777	1785	2367	java/lang/IndexOutOfBoundsException
    //   1855	1863	2367	java/lang/UnsupportedOperationException
    //   11263	11267	2367	java/lang/IndexOutOfBoundsException
    //   11279	11287	2367	java/lang/IndexOutOfBoundsException
    //   1696	1750	2604	finally
    //   17	27	2661	finally
    //   383	401	2661	finally
    //   833	854	2661	finally
    //   2867	2872	2661	finally
    //   3594	3653	2661	finally
    //   9848	9870	2661	finally
    //   1169	1188	2729	finally
    //   1680	1696	2729	finally
    //   4107	4127	2729	finally
    //   1289	1293	2862	java/lang/RuntimeException
    //   1300	1308	2862	java/lang/ArrayStoreException
    //   1777	1785	2862	java/lang/IllegalArgumentException
    //   1847	1851	2862	java/lang/IndexOutOfBoundsException
    //   9014	9018	2862	java/lang/Exception
    //   9030	9038	2862	java/lang/RuntimeException
    //   4368	4400	2911	finally
    //   8905	8910	2911	finally
    //   10202	10223	2911	finally
    //   10979	11004	2911	finally
    //   11137	11158	2911	finally
    //   8662	8707	2962	finally
    //   1576	1653	3053	finally
    //   11	14	3073	java/lang/Exception
    //   147	150	3073	java/lang/Exception
    //   153	156	3073	java/lang/Exception
    //   178	181	3073	java/lang/Exception
    //   215	230	3073	java/lang/Exception
    //   291	294	3073	java/lang/Exception
    //   297	300	3073	java/lang/Exception
    //   319	326	3073	java/lang/Exception
    //   369	380	3073	java/lang/Exception
    //   434	510	3073	java/lang/Exception
    //   533	536	3073	java/lang/Exception
    //   749	752	3073	java/lang/Exception
    //   760	763	3073	java/lang/Exception
    //   763	768	3073	java/lang/Exception
    //   771	774	3073	java/lang/Exception
    //   781	786	3073	java/lang/Exception
    //   827	830	3073	java/lang/Exception
    //   879	886	3073	java/lang/Exception
    //   977	980	3073	java/lang/Exception
    //   1003	1010	3073	java/lang/Exception
    //   1023	1030	3073	java/lang/Exception
    //   1143	1146	3073	java/lang/Exception
    //   1148	1155	3073	java/lang/Exception
    //   1220	1223	3073	java/lang/Exception
    //   1271	1278	3073	java/lang/Exception
    //   1320	1323	3073	java/lang/Exception
    //   1323	1326	3073	java/lang/Exception
    //   1346	1353	3073	java/lang/Exception
    //   1367	1378	3073	java/lang/Exception
    //   1423	1426	3073	java/lang/Exception
    //   1476	1483	3073	java/lang/Exception
    //   1494	1497	3073	java/lang/Exception
    //   1526	1529	3073	java/lang/Exception
    //   1817	1835	3073	java/lang/Exception
    //   2093	2100	3073	java/lang/Exception
    //   2148	2151	3073	java/lang/Exception
    //   2151	2154	3073	java/lang/Exception
    //   2156	2163	3073	java/lang/Exception
    //   2254	2261	3073	java/lang/Exception
    //   2339	2342	3073	java/lang/Exception
    //   2372	2375	3073	java/lang/Exception
    //   2546	2549	3073	java/lang/Exception
    //   2606	2613	3073	java/lang/Exception
    //   2663	2670	3073	java/lang/Exception
    //   2731	2738	3073	java/lang/Exception
    //   2776	2805	3073	java/lang/Exception
    //   2811	2818	3073	java/lang/Exception
    //   2913	2920	3073	java/lang/Exception
    //   2964	2971	3073	java/lang/Exception
    //   3029	3050	3073	java/lang/Exception
    //   3055	3062	3073	java/lang/Exception
    //   3112	3117	3073	java/lang/Exception
    //   3125	3130	3073	java/lang/Exception
    //   3136	3250	3073	java/lang/Exception
    //   3334	3341	3073	java/lang/Exception
    //   3355	3358	3073	java/lang/Exception
    //   3361	3364	3073	java/lang/Exception
    //   3490	3493	3073	java/lang/Exception
    //   3557	3560	3073	java/lang/Exception
    //   3560	3563	3073	java/lang/Exception
    //   3819	3822	3073	java/lang/Exception
    //   3838	3841	3073	java/lang/Exception
    //   3841	3844	3073	java/lang/Exception
    //   3883	3888	3073	java/lang/Exception
    //   3943	3949	3073	java/lang/Exception
    //   3973	3996	3073	java/lang/Exception
    //   4028	4082	3073	java/lang/Exception
    //   4091	4094	3073	java/lang/Exception
    //   4156	4163	3073	java/lang/Exception
    //   4174	4177	3073	java/lang/Exception
    //   4177	4180	3073	java/lang/Exception
    //   4325	4328	3073	java/lang/Exception
    //   4330	4337	3073	java/lang/Exception
    //   4362	4365	3073	java/lang/Exception
    //   4365	4368	3073	java/lang/Exception
    //   4459	4464	3073	java/lang/Exception
    //   4509	4515	3073	java/lang/Exception
    //   4520	4527	3073	java/lang/Exception
    //   4656	4663	3073	java/lang/Exception
    //   4780	4797	3073	java/lang/Exception
    //   4812	4815	3073	java/lang/Exception
    //   4862	4913	3073	java/lang/Exception
    //   5014	5017	3073	java/lang/Exception
    //   5061	5068	3073	java/lang/Exception
    //   5111	5114	3073	java/lang/Exception
    //   5117	5120	3073	java/lang/Exception
    //   5123	5139	3073	java/lang/Exception
    //   5199	5202	3073	java/lang/Exception
    //   5232	5235	3073	java/lang/Exception
    //   8536	8549	3073	java/lang/Exception
    //   8554	8561	3073	java/lang/Exception
    //   8572	8575	3073	java/lang/Exception
    //   8577	8584	3073	java/lang/Exception
    //   8597	8604	3073	java/lang/Exception
    //   8617	8624	3073	java/lang/Exception
    //   8799	8802	3073	java/lang/Exception
    //   8802	8818	3073	java/lang/Exception
    //   8823	8830	3073	java/lang/Exception
    //   8891	8902	3073	java/lang/Exception
    //   8913	8942	3073	java/lang/Exception
    //   8951	8958	3073	java/lang/Exception
    //   9077	9080	3073	java/lang/Exception
    //   9082	9089	3073	java/lang/Exception
    //   9204	9207	3073	java/lang/Exception
    //   9301	9304	3073	java/lang/Exception
    //   9308	9313	3073	java/lang/Exception
    //   9348	9355	3073	java/lang/Exception
    //   9407	9414	3073	java/lang/Exception
    //   9510	9513	3073	java/lang/Exception
    //   9884	9891	3073	java/lang/Exception
    //   9963	9966	3073	java/lang/Exception
    //   10009	10012	3073	java/lang/Exception
    //   10015	10018	3073	java/lang/Exception
    //   10108	10111	3073	java/lang/Exception
    //   10174	10181	3073	java/lang/Exception
    //   10226	10229	3073	java/lang/Exception
    //   10323	10326	3073	java/lang/Exception
    //   10333	10336	3073	java/lang/Exception
    //   10339	10362	3073	java/lang/Exception
    //   10398	10408	3073	java/lang/Exception
    //   10416	10419	3073	java/lang/Exception
    //   10505	10508	3073	java/lang/Exception
    //   10508	10515	3073	java/lang/Exception
    //   10635	10638	3073	java/lang/Exception
    //   10706	10709	3073	java/lang/Exception
    //   10709	10763	3073	java/lang/Exception
    //   10913	10916	3073	java/lang/Exception
    //   10963	10966	3073	java/lang/Exception
    //   11012	11067	3073	java/lang/Exception
    //   11070	11073	3073	java/lang/Exception
    //   11111	11128	3073	java/lang/Exception
    //   11161	11164	3073	java/lang/Exception
    //   11253	11260	3073	java/lang/Exception
    //   11299	11302	3073	java/lang/Exception
    //   11330	11333	3073	java/lang/Exception
    //   11426	11445	3073	java/lang/Exception
    //   3253	3309	3312	finally
    //   2591	2598	3332	finally
    //   4762	4777	3332	finally
    //   10311	10320	3332	finally
    //   10966	10973	3332	finally
    //   11461	11477	3332	finally
    //   39	46	3574	finally
    //   897	916	3574	finally
    //   2397	2402	3574	finally
    //   3952	3970	3574	finally
    //   10545	10600	3574	finally
    //   300	303	4026	java/lang/Exception
    //   1799	1806	4026	java/lang/Exception
    //   9258	9261	4026	java/lang/Exception
    //   613	746	4154	finally
    //   919	954	4154	finally
    //   1884	1916	4154	finally
    //   2627	2647	4154	finally
    //   4225	4250	4154	finally
    //   4299	4304	4154	finally
    //   10111	10132	4154	finally
    //   1062	1078	4328	finally
    //   1080	1085	4328	finally
    //   1229	1260	4328	finally
    //   1458	1471	4328	finally
    //   3822	3835	4328	finally
    //   3891	3906	4328	finally
    //   10887	10903	4328	finally
    //   10905	10910	4328	finally
    //   541	544	4403	finally
    //   610	613	4403	finally
    //   1044	1047	4403	finally
    //   1341	1344	4403	finally
    //   3576	3583	4403	finally
    //   5114	5117	4403	finally
    //   9427	9434	4403	finally
    //   9998	10001	4403	finally
    //   10373	10380	4403	finally
    //   10542	10545	4403	finally
    //   857	874	4518	finally
    //   1919	1934	4518	finally
    //   3563	3571	4518	finally
    //   513	530	4654	finally
    //   8846	8853	4654	finally
    //   9050	9069	4654	finally
    //   9991	9995	4654	finally
    //   10056	10105	4654	finally
    //   10649	10665	4654	finally
    //   4677	4739	5059	finally
    //   11338	11391	8552	finally
    //   3686	3742	8575	finally
    //   156	175	8595	finally
    //   1981	2002	8595	finally
    //   2549	2588	8595	finally
    //   8969	8981	8595	finally
    //   2996	3001	8615	finally
    //   4749	4756	8615	finally
    //   4815	4832	8615	finally
    //   9183	9201	8615	finally
    //   11480	11512	8615	finally
    //   303	311	8821	finally
    //   5205	5229	8821	finally
    //   9966	9988	8821	finally
    //   10770	10802	8949	finally
    //   4954	5011	9080	finally
    //   4547	4570	9346	finally
    //   10834	10857	9346	finally
    //   11402	11423	9346	finally
    //   2018	2041	9405	finally
    //   2821	2844	9405	finally
    //   4307	4322	9405	finally
    //   10243	10263	9405	finally
    //   10946	10954	9405	finally
    //   2191	2211	9425	finally
    //   2982	2990	9425	finally
    //   4094	4104	9425	finally
    //   9513	9536	9425	finally
    //   1099	1104	9882	finally
    //   1326	1332	9882	finally
    //   2214	2223	9882	finally
    //   2405	2422	9882	finally
    //   2518	2527	9882	finally
    //   2534	2543	9882	finally
    //   2942	2947	9882	finally
    //   4130	4148	9882	finally
    //   4348	4359	9882	finally
    //   11302	11311	9882	finally
    //   11318	11327	9882	finally
    //   541	544	9931	java/lang/Exception
    //   610	613	9931	java/lang/Exception
    //   1044	1047	9931	java/lang/Exception
    //   1341	1344	9931	java/lang/Exception
    //   3576	3583	9931	java/lang/Exception
    //   9427	9434	9931	java/lang/Exception
    //   9998	10001	9931	java/lang/Exception
    //   10373	10380	9931	java/lang/Exception
    //   10542	10545	9931	java/lang/Exception
    //   3439	3487	10172	finally
    //   9207	9255	10371	finally
    //   240	243	11010	java/lang/Exception
    //   2130	2137	11010	java/lang/Exception
    //   3314	3321	11010	java/lang/Exception
    //   4674	4677	11010	java/lang/Exception
    //   8710	8713	11010	java/lang/Exception
    //   10960	10963	11010	java/lang/Exception
  }
  
  private O() {}
  
  /* Error */
  public static int ˊ(int paramInt)
  {
    // Byte code:
    //   0: goto +455 -> 455
    //   3: getstatic 30	o/O:ʼॱ	I
    //   6: istore 4
    //   8: iload 4
    //   10: bipush 115
    //   12: ior
    //   13: iconst_1
    //   14: ishl
    //   15: iload 4
    //   17: bipush 115
    //   19: ixor
    //   20: isub
    //   21: istore 4
    //   23: iload 4
    //   25: sipush 128
    //   28: irem
    //   29: putstatic 28	o/O:ʽॱ	I
    //   32: iload 4
    //   34: iconst_2
    //   35: irem
    //   36: ifeq +6 -> 42
    //   39: goto +511 -> 550
    //   42: goto +288 -> 330
    //   45: iconst_1
    //   46: anewarray 4	java/lang/Object
    //   49: astore 8
    //   51: iload_0
    //   52: invokestatic 369	java/lang/Integer:valueOf	(I)Ljava/lang/Integer;
    //   55: astore 6
    //   57: goto +364 -> 421
    //   60: getstatic 28	o/O:ʽॱ	I
    //   63: istore_0
    //   64: iload_0
    //   65: iconst_5
    //   66: ixor
    //   67: iload_0
    //   68: iconst_5
    //   69: iand
    //   70: iconst_1
    //   71: ishl
    //   72: iadd
    //   73: istore_0
    //   74: iload_0
    //   75: sipush 128
    //   78: irem
    //   79: putstatic 30	o/O:ʼॱ	I
    //   82: iload_0
    //   83: iconst_2
    //   84: irem
    //   85: ifne +6 -> 91
    //   88: goto +147 -> 235
    //   91: goto +113 -> 204
    //   94: aload 8
    //   96: iconst_0
    //   97: aload 6
    //   99: aastore
    //   100: getstatic 310	o/O:ʿ	[S
    //   103: sipush 10013
    //   106: saload
    //   107: ineg
    //   108: i2s
    //   109: istore_0
    //   110: getstatic 310	o/O:ʿ	[S
    //   113: astore 6
    //   115: goto +489 -> 604
    //   118: bipush 76
    //   120: istore_2
    //   121: goto +6 -> 127
    //   124: bipush 83
    //   126: istore_2
    //   127: iload_2
    //   128: lookupswitch	default:+28->156, 76:+468->596, 83:+455->583
    //   156: goto +427 -> 583
    //   159: astore 5
    //   161: aload 5
    //   163: athrow
    //   164: goto +473 -> 637
    //   167: iload_2
    //   168: lookupswitch	default:+28->196, 12:+129->297, 64:+358->526
    //   196: goto +101 -> 297
    //   199: astore 5
    //   201: aload 5
    //   203: athrow
    //   204: aload 6
    //   206: aload 7
    //   208: iconst_1
    //   209: anewarray 329	java/lang/Class
    //   212: dup
    //   213: iconst_0
    //   214: aload 9
    //   216: aastore
    //   217: invokevirtual 393	java/lang/Class:getMethod	(Ljava/lang/String;[Ljava/lang/Class;)Ljava/lang/reflect/Method;
    //   220: aload 5
    //   222: aload 8
    //   224: invokevirtual 376	java/lang/reflect/Method:invoke	(Ljava/lang/Object;[Ljava/lang/Object;)Ljava/lang/Object;
    //   227: checkcast 323	java/lang/Integer
    //   230: astore 5
    //   232: goto +9 -> 241
    //   235: goto -31 -> 204
    //   238: goto +83 -> 321
    //   241: getstatic 30	o/O:ʼॱ	I
    //   244: bipush 111
    //   246: iadd
    //   247: istore_0
    //   248: iload_0
    //   249: sipush 128
    //   252: irem
    //   253: putstatic 28	o/O:ʽॱ	I
    //   256: iload_0
    //   257: iconst_2
    //   258: irem
    //   259: ifeq +6 -> 265
    //   262: goto -24 -> 238
    //   265: goto +56 -> 321
    //   268: getstatic 28	o/O:ʽॱ	I
    //   271: bipush 42
    //   273: iadd
    //   274: iconst_1
    //   275: isub
    //   276: istore_2
    //   277: iload_2
    //   278: sipush 128
    //   281: irem
    //   282: putstatic 30	o/O:ʼॱ	I
    //   285: iload_2
    //   286: iconst_2
    //   287: irem
    //   288: ifne +6 -> 294
    //   291: goto -167 -> 124
    //   294: goto -176 -> 118
    //   297: iload_0
    //   298: iload_3
    //   299: iload_1
    //   300: invokestatic 331	o/O:$$d	(IIS)Ljava/lang/String;
    //   303: invokestatic 335	java/lang/Class:forName	(Ljava/lang/String;)Ljava/lang/Class;
    //   306: astore 6
    //   308: sipush 258
    //   311: i2s
    //   312: istore_0
    //   313: getstatic 310	o/O:ʿ	[S
    //   316: astore 7
    //   318: goto +82 -> 400
    //   321: aload 5
    //   323: invokevirtual 327	java/lang/Integer:intValue	()I
    //   326: istore_0
    //   327: goto +231 -> 558
    //   330: iload_3
    //   331: i2s
    //   332: istore_1
    //   333: iload_0
    //   334: iload_2
    //   335: iload_1
    //   336: invokestatic 331	o/O:$$d	(IIS)Ljava/lang/String;
    //   339: astore 7
    //   341: getstatic 383	java/lang/Integer:TYPE	Ljava/lang/Class;
    //   344: astore 9
    //   346: goto -286 -> 60
    //   349: aload 8
    //   351: iconst_0
    //   352: aload 6
    //   354: aastore
    //   355: getstatic 310	o/O:ʿ	[S
    //   358: sipush 413
    //   361: saload
    //   362: ineg
    //   363: i2s
    //   364: istore_0
    //   365: getstatic 310	o/O:ʿ	[S
    //   368: astore 6
    //   370: goto +234 -> 604
    //   373: getstatic 30	o/O:ʼॱ	I
    //   376: bipush 75
    //   378: iadd
    //   379: istore_2
    //   380: iload_2
    //   381: sipush 128
    //   384: irem
    //   385: putstatic 28	o/O:ʽॱ	I
    //   388: iload_2
    //   389: iconst_2
    //   390: irem
    //   391: ifeq +6 -> 397
    //   394: goto +121 -> 515
    //   397: goto +61 -> 458
    //   400: aload 7
    //   402: sipush 166
    //   405: saload
    //   406: i2b
    //   407: istore_2
    //   408: getstatic 310	o/O:ʿ	[S
    //   411: bipush 24
    //   413: saload
    //   414: istore_3
    //   415: goto -412 -> 3
    //   418: aload 5
    //   420: athrow
    //   421: getstatic 28	o/O:ʽॱ	I
    //   424: istore_0
    //   425: iload_0
    //   426: bipush 109
    //   428: iand
    //   429: iload_0
    //   430: bipush 109
    //   432: ior
    //   433: iadd
    //   434: istore_0
    //   435: iload_0
    //   436: sipush 128
    //   439: irem
    //   440: putstatic 30	o/O:ʼॱ	I
    //   443: iload_0
    //   444: iconst_2
    //   445: irem
    //   446: ifne +6 -> 452
    //   449: goto +72 -> 521
    //   452: goto +101 -> 553
    //   455: goto -187 -> 268
    //   458: bipush 12
    //   460: istore_2
    //   461: goto -294 -> 167
    //   464: goto -419 -> 45
    //   467: iload_0
    //   468: tableswitch	default:+24->492, 0:+-119->349, 1:+-374->94
    //   492: goto -398 -> 94
    //   495: astore 5
    //   497: aload 5
    //   499: invokevirtual 349	java/lang/Throwable:getCause	()Ljava/lang/Throwable;
    //   502: astore 6
    //   504: aload 6
    //   506: ifnull +6 -> 512
    //   509: goto +146 -> 655
    //   512: goto -94 -> 418
    //   515: bipush 64
    //   517: istore_2
    //   518: goto -351 -> 167
    //   521: iconst_1
    //   522: istore_0
    //   523: goto -56 -> 467
    //   526: iload_0
    //   527: iload_3
    //   528: iload_1
    //   529: invokestatic 331	o/O:$$d	(IIS)Ljava/lang/String;
    //   532: invokestatic 335	java/lang/Class:forName	(Ljava/lang/String;)Ljava/lang/Class;
    //   535: astore 6
    //   537: sipush 28877
    //   540: i2s
    //   541: istore_0
    //   542: getstatic 310	o/O:ʿ	[S
    //   545: astore 7
    //   547: goto -147 -> 400
    //   550: goto -220 -> 330
    //   553: iconst_0
    //   554: istore_0
    //   555: goto -88 -> 467
    //   558: getstatic 30	o/O:ʼॱ	I
    //   561: bipush 11
    //   563: iadd
    //   564: istore_2
    //   565: iload_2
    //   566: sipush 128
    //   569: irem
    //   570: putstatic 28	o/O:ʽॱ	I
    //   573: iload_2
    //   574: iconst_2
    //   575: irem
    //   576: ifeq +5 -> 581
    //   579: iload_0
    //   580: ireturn
    //   581: iload_0
    //   582: ireturn
    //   583: getstatic 378	o/O:ॱˋ	Ljava/lang/Object;
    //   586: astore 5
    //   588: bipush 83
    //   590: iconst_0
    //   591: idiv
    //   592: istore_2
    //   593: goto -129 -> 464
    //   596: getstatic 378	o/O:ॱˋ	Ljava/lang/Object;
    //   599: astore 5
    //   601: goto -137 -> 464
    //   604: getstatic 28	o/O:ʽॱ	I
    //   607: istore_2
    //   608: iload_2
    //   609: bipush 107
    //   611: ixor
    //   612: iload_2
    //   613: bipush 107
    //   615: iand
    //   616: iconst_1
    //   617: ishl
    //   618: iadd
    //   619: istore_2
    //   620: iload_2
    //   621: sipush 128
    //   624: irem
    //   625: putstatic 30	o/O:ʼॱ	I
    //   628: iload_2
    //   629: iconst_2
    //   630: irem
    //   631: ifne +6 -> 637
    //   634: goto -470 -> 164
    //   637: aload 6
    //   639: sipush 368
    //   642: saload
    //   643: i2b
    //   644: istore_3
    //   645: iload_3
    //   646: sipush 582
    //   649: ior
    //   650: i2s
    //   651: istore_1
    //   652: goto -279 -> 373
    //   655: aload 6
    //   657: athrow
    // Local variable table:
    //   start	length	slot	name	signature
    //   0	658	0	paramInt	int
    //   299	353	1	s	short
    //   120	511	2	i	int
    //   298	352	3	j	int
    //   6	30	4	k	int
    //   159	3	5	localIllegalArgumentException	IllegalArgumentException
    //   199	22	5	localIndexOutOfBoundsException	IndexOutOfBoundsException
    //   230	189	5	localInteger	Integer
    //   495	3	5	localObject1	Object
    //   586	14	5	localObject2	Object
    //   55	601	6	localObject3	Object
    //   206	340	7	localObject4	Object
    //   49	301	8	arrayOfObject	Object[]
    //   214	131	9	localClass	Class
    // Exception table:
    //   from	to	target	type
    //   3	8	159	java/lang/IllegalArgumentException
    //   23	32	159	java/lang/IllegalArgumentException
    //   373	380	159	java/lang/IndexOutOfBoundsException
    //   380	388	159	java/lang/IndexOutOfBoundsException
    //   380	388	159	java/lang/Exception
    //   421	425	159	java/lang/IllegalArgumentException
    //   435	443	159	java/lang/IllegalArgumentException
    //   435	443	159	java/lang/ArrayStoreException
    //   565	573	159	java/lang/IllegalArgumentException
    //   23	32	199	java/lang/IndexOutOfBoundsException
    //   558	565	199	java/lang/IndexOutOfBoundsException
    //   565	573	199	java/lang/IndexOutOfBoundsException
    //   596	601	199	java/lang/ClassCastException
    //   604	608	199	java/lang/IllegalArgumentException
    //   45	57	495	finally
    //   100	115	495	finally
    //   204	232	495	finally
    //   297	308	495	finally
    //   313	318	495	finally
    //   321	327	495	finally
    //   333	346	495	finally
    //   355	370	495	finally
    //   408	415	495	finally
    //   526	537	495	finally
    //   542	547	495	finally
  }
  
  /* Error */
  public static Object ˋ(int paramInt1, int paramInt2, char paramChar)
  {
    // Byte code:
    //   0: goto +158 -> 158
    //   3: astore 4
    //   5: aload 4
    //   7: invokevirtual 349	java/lang/Throwable:getCause	()Ljava/lang/Throwable;
    //   10: astore 5
    //   12: aload 5
    //   14: ifnull +6 -> 20
    //   17: goto +452 -> 469
    //   20: goto +312 -> 332
    //   23: iload_3
    //   24: tableswitch	default:+24->48, 0:+311->335, 1:+511->535
    //   48: goto +287 -> 335
    //   51: iconst_3
    //   52: anewarray 4	java/lang/Object
    //   55: astore 5
    //   57: aload 5
    //   59: iconst_2
    //   60: iload_2
    //   61: invokestatic 490	java/lang/Character:valueOf	(C)Ljava/lang/Character;
    //   64: aastore
    //   65: goto +226 -> 291
    //   68: aload 5
    //   70: iconst_1
    //   71: iload_1
    //   72: invokestatic 369	java/lang/Integer:valueOf	(I)Ljava/lang/Integer;
    //   75: aastore
    //   76: aload 5
    //   78: iconst_1
    //   79: iload_3
    //   80: invokestatic 369	java/lang/Integer:valueOf	(I)Ljava/lang/Integer;
    //   83: aastore
    //   84: goto +113 -> 197
    //   87: getstatic 28	o/O:ʽॱ	I
    //   90: istore_3
    //   91: iload_3
    //   92: bipush 25
    //   94: ior
    //   95: iconst_1
    //   96: ishl
    //   97: iload_3
    //   98: bipush 25
    //   100: ixor
    //   101: isub
    //   102: istore_3
    //   103: iload_3
    //   104: sipush 128
    //   107: irem
    //   108: putstatic 30	o/O:ʼॱ	I
    //   111: iload_3
    //   112: iconst_2
    //   113: irem
    //   114: ifne +6 -> 120
    //   117: goto +231 -> 348
    //   120: iconst_0
    //   121: istore_3
    //   122: goto -99 -> 23
    //   125: iconst_1
    //   126: istore_0
    //   127: iload_0
    //   128: tableswitch	default:+24->152, 0:+-60->68, 1:+418->546
    //   152: goto -84 -> 68
    //   155: goto +251 -> 406
    //   158: goto -71 -> 87
    //   161: iconst_0
    //   162: istore_0
    //   163: goto -36 -> 127
    //   166: getstatic 30	o/O:ʼॱ	I
    //   169: istore_0
    //   170: iload_0
    //   171: bipush 58
    //   173: iadd
    //   174: iconst_1
    //   175: isub
    //   176: istore_0
    //   177: iload_0
    //   178: sipush 128
    //   181: irem
    //   182: putstatic 28	o/O:ʽॱ	I
    //   185: iload_0
    //   186: iconst_2
    //   187: irem
    //   188: ifeq +6 -> 194
    //   191: goto -36 -> 155
    //   194: goto +212 -> 406
    //   197: getstatic 310	o/O:ʿ	[S
    //   200: sipush 413
    //   203: saload
    //   204: ineg
    //   205: i2s
    //   206: istore_0
    //   207: getstatic 310	o/O:ʿ	[S
    //   210: astore 6
    //   212: goto +407 -> 619
    //   215: getstatic 28	o/O:ʽॱ	I
    //   218: istore_0
    //   219: iload_0
    //   220: bipush 23
    //   222: iadd
    //   223: istore_0
    //   224: iload_0
    //   225: sipush 128
    //   228: irem
    //   229: putstatic 30	o/O:ʼॱ	I
    //   232: iload_0
    //   233: iconst_2
    //   234: irem
    //   235: ifne +6 -> 241
    //   238: goto +201 -> 439
    //   241: goto +407 -> 648
    //   244: sipush 258
    //   247: iload_0
    //   248: aload 7
    //   250: iconst_0
    //   251: saload
    //   252: i2s
    //   253: invokestatic 331	o/O:$$d	(IIS)Ljava/lang/String;
    //   256: astore 7
    //   258: getstatic 383	java/lang/Integer:TYPE	Ljava/lang/Class;
    //   261: astore 8
    //   263: goto -97 -> 166
    //   266: goto +242 -> 508
    //   269: aload 6
    //   271: aload 4
    //   273: aload 5
    //   275: invokevirtual 376	java/lang/reflect/Method:invoke	(Ljava/lang/Object;[Ljava/lang/Object;)Ljava/lang/Object;
    //   278: astore 4
    //   280: aconst_null
    //   281: arraylength
    //   282: istore_0
    //   283: aload 4
    //   285: areturn
    //   286: astore 4
    //   288: aload 4
    //   290: athrow
    //   291: getstatic 30	o/O:ʼॱ	I
    //   294: bipush 69
    //   296: iadd
    //   297: istore_0
    //   298: iload_0
    //   299: sipush 128
    //   302: irem
    //   303: putstatic 28	o/O:ʽॱ	I
    //   306: iload_0
    //   307: iconst_2
    //   308: irem
    //   309: ifeq +6 -> 315
    //   312: goto -151 -> 161
    //   315: goto -190 -> 125
    //   318: aload 6
    //   320: aload 4
    //   322: aload 5
    //   324: invokevirtual 376	java/lang/reflect/Method:invoke	(Ljava/lang/Object;[Ljava/lang/Object;)Ljava/lang/Object;
    //   327: astore 4
    //   329: aload 4
    //   331: areturn
    //   332: aload 4
    //   334: athrow
    //   335: getstatic 378	o/O:ॱˋ	Ljava/lang/Object;
    //   338: astore 4
    //   340: goto +35 -> 375
    //   343: astore 4
    //   345: aload 4
    //   347: athrow
    //   348: iconst_1
    //   349: istore_3
    //   350: goto -327 -> 23
    //   353: getstatic 310	o/O:ʿ	[S
    //   356: sipush 166
    //   359: saload
    //   360: i2b
    //   361: istore_0
    //   362: getstatic 310	o/O:ʿ	[S
    //   365: astore 7
    //   367: goto -123 -> 244
    //   370: iconst_0
    //   371: istore_0
    //   372: goto +193 -> 565
    //   375: iload_0
    //   376: istore_3
    //   377: getstatic 30	o/O:ʼॱ	I
    //   380: istore_0
    //   381: iload_0
    //   382: bipush 45
    //   384: iadd
    //   385: istore_0
    //   386: iload_0
    //   387: sipush 128
    //   390: irem
    //   391: putstatic 28	o/O:ʽॱ	I
    //   394: iload_0
    //   395: iconst_2
    //   396: irem
    //   397: ifeq +6 -> 403
    //   400: goto +44 -> 444
    //   403: goto +250 -> 653
    //   406: aload 6
    //   408: aload 7
    //   410: iconst_3
    //   411: anewarray 329	java/lang/Class
    //   414: dup
    //   415: iconst_0
    //   416: aload 8
    //   418: aastore
    //   419: dup
    //   420: iconst_1
    //   421: getstatic 383	java/lang/Integer:TYPE	Ljava/lang/Class;
    //   424: aastore
    //   425: dup
    //   426: iconst_2
    //   427: getstatic 491	java/lang/Character:TYPE	Ljava/lang/Class;
    //   430: aastore
    //   431: invokevirtual 393	java/lang/Class:getMethod	(Ljava/lang/String;[Ljava/lang/Class;)Ljava/lang/reflect/Method;
    //   434: astore 6
    //   436: goto +36 -> 472
    //   439: iconst_0
    //   440: istore_0
    //   441: goto +150 -> 591
    //   444: goto +209 -> 653
    //   447: iconst_3
    //   448: anewarray 4	java/lang/Object
    //   451: astore 5
    //   453: aload 5
    //   455: iconst_2
    //   456: iload_2
    //   457: invokestatic 490	java/lang/Character:valueOf	(C)Ljava/lang/Character;
    //   460: aastore
    //   461: goto -170 -> 291
    //   464: iconst_1
    //   465: istore_0
    //   466: goto +99 -> 565
    //   469: aload 5
    //   471: athrow
    //   472: getstatic 28	o/O:ʽॱ	I
    //   475: istore_0
    //   476: iload_0
    //   477: bipush 55
    //   479: ixor
    //   480: iload_0
    //   481: bipush 55
    //   483: iand
    //   484: iconst_1
    //   485: ishl
    //   486: iadd
    //   487: istore_0
    //   488: iload_0
    //   489: sipush 128
    //   492: irem
    //   493: putstatic 30	o/O:ʼॱ	I
    //   496: iload_0
    //   497: iconst_2
    //   498: irem
    //   499: ifne +6 -> 505
    //   502: goto -132 -> 370
    //   505: goto -41 -> 464
    //   508: aload 6
    //   510: sipush 368
    //   513: saload
    //   514: i2b
    //   515: istore_1
    //   516: iload_0
    //   517: iload_1
    //   518: iload_1
    //   519: sipush 582
    //   522: ior
    //   523: i2s
    //   524: invokestatic 331	o/O:$$d	(IIS)Ljava/lang/String;
    //   527: invokestatic 335	java/lang/Class:forName	(Ljava/lang/String;)Ljava/lang/Class;
    //   530: astore 6
    //   532: goto -179 -> 353
    //   535: getstatic 378	o/O:ॱˋ	Ljava/lang/Object;
    //   538: astore 4
    //   540: aconst_null
    //   541: arraylength
    //   542: istore_3
    //   543: goto -168 -> 375
    //   546: aload 5
    //   548: iconst_1
    //   549: iload_1
    //   550: invokestatic 369	java/lang/Integer:valueOf	(I)Ljava/lang/Integer;
    //   553: aastore
    //   554: aload 5
    //   556: iconst_0
    //   557: iload_3
    //   558: invokestatic 369	java/lang/Integer:valueOf	(I)Ljava/lang/Integer;
    //   561: aastore
    //   562: goto -365 -> 197
    //   565: iload_0
    //   566: tableswitch	default:+22->588, 0:+-297->269, 1:+-248->318
    //   588: goto -319 -> 269
    //   591: iload_0
    //   592: tableswitch	default:+24->616, 0:+-541->51, 1:+-145->447
    //   616: goto -565 -> 51
    //   619: getstatic 28	o/O:ʽॱ	I
    //   622: istore_1
    //   623: iload_1
    //   624: bipush 109
    //   626: iadd
    //   627: istore_1
    //   628: iload_1
    //   629: sipush 128
    //   632: irem
    //   633: putstatic 30	o/O:ʼॱ	I
    //   636: iload_1
    //   637: iconst_2
    //   638: irem
    //   639: ifne +6 -> 645
    //   642: goto -376 -> 266
    //   645: goto -137 -> 508
    //   648: iconst_1
    //   649: istore_0
    //   650: goto -59 -> 591
    //   653: goto -438 -> 215
    // Local variable table:
    //   start	length	slot	name	signature
    //   0	656	0	paramInt1	int
    //   0	656	1	paramInt2	int
    //   0	656	2	paramChar	char
    //   23	535	3	i	int
    //   3	269	4	localObject1	Object
    //   278	6	4	localObject2	Object
    //   286	35	4	localClassCastException	ClassCastException
    //   327	12	4	localObject3	Object
    //   343	3	4	localIllegalArgumentException	IllegalArgumentException
    //   538	1	4	localObject4	Object
    //   10	545	5	localObject5	Object
    //   210	321	6	localObject6	Object
    //   248	161	7	localObject7	Object
    //   261	156	8	localClass	Class
    // Exception table:
    //   from	to	target	type
    //   51	65	3	finally
    //   68	84	3	finally
    //   197	212	3	finally
    //   244	263	3	finally
    //   269	283	3	finally
    //   318	329	3	finally
    //   353	367	3	finally
    //   406	436	3	finally
    //   447	461	3	finally
    //   516	532	3	finally
    //   546	562	3	finally
    //   166	170	286	java/lang/ClassCastException
    //   224	232	286	java/lang/NullPointerException
    //   335	340	286	java/lang/ArrayStoreException
    //   377	381	286	java/lang/RuntimeException
    //   619	623	286	java/lang/UnsupportedOperationException
    //   628	636	286	java/lang/Exception
    //   177	185	343	java/lang/IllegalArgumentException
    //   215	219	343	java/lang/ClassCastException
    //   386	394	343	java/lang/IllegalArgumentException
    //   472	476	343	java/lang/IllegalArgumentException
  }
  
  /* Error */
  public static int ˏ(Object paramObject)
  {
    // Byte code:
    //   0: goto +211 -> 211
    //   3: iload_2
    //   4: lookupswitch	default:+28->32, 0:+327->331, 56:+395->399
    //   32: goto +299 -> 331
    //   35: goto +204 -> 239
    //   38: goto +10 -> 48
    //   41: aload_0
    //   42: athrow
    //   43: iconst_0
    //   44: istore_2
    //   45: goto -42 -> 3
    //   48: iload_3
    //   49: sipush 582
    //   52: ixor
    //   53: iload_3
    //   54: sipush 582
    //   57: iand
    //   58: ior
    //   59: i2s
    //   60: istore_1
    //   61: iload_2
    //   62: iload_3
    //   63: iload_1
    //   64: invokestatic 331	o/O:$$d	(IIS)Ljava/lang/String;
    //   67: invokestatic 335	java/lang/Class:forName	(Ljava/lang/String;)Ljava/lang/Class;
    //   70: astore 7
    //   72: getstatic 310	o/O:ʿ	[S
    //   75: astore 5
    //   77: getstatic 30	o/O:ʼॱ	I
    //   80: istore_2
    //   81: iload_2
    //   82: bipush 15
    //   84: iand
    //   85: iload_2
    //   86: bipush 15
    //   88: ior
    //   89: iadd
    //   90: istore_2
    //   91: iload_2
    //   92: sipush 128
    //   95: irem
    //   96: putstatic 28	o/O:ʽॱ	I
    //   99: iload_2
    //   100: iconst_2
    //   101: irem
    //   102: ifeq +6 -> 108
    //   105: goto +379 -> 484
    //   108: goto +293 -> 401
    //   111: iconst_0
    //   112: istore_2
    //   113: goto +260 -> 373
    //   116: getstatic 28	o/O:ʽॱ	I
    //   119: bipush 92
    //   121: iadd
    //   122: iconst_1
    //   123: isub
    //   124: istore_2
    //   125: iload_2
    //   126: sipush 128
    //   129: irem
    //   130: putstatic 30	o/O:ʼॱ	I
    //   133: iload_2
    //   134: iconst_2
    //   135: irem
    //   136: ifne +6 -> 142
    //   139: goto +210 -> 349
    //   142: goto +196 -> 338
    //   145: astore_0
    //   146: aload_0
    //   147: athrow
    //   148: bipush 56
    //   150: istore_2
    //   151: goto -148 -> 3
    //   154: astore 5
    //   156: aload 5
    //   158: invokevirtual 349	java/lang/Throwable:getCause	()Ljava/lang/Throwable;
    //   161: astore_0
    //   162: aload_0
    //   163: ifnull +6 -> 169
    //   166: goto -125 -> 41
    //   169: goto +177 -> 346
    //   172: goto +180 -> 352
    //   175: iconst_1
    //   176: istore_2
    //   177: goto +196 -> 373
    //   180: getstatic 28	o/O:ʽॱ	I
    //   183: istore_2
    //   184: iload_2
    //   185: bipush 76
    //   187: iadd
    //   188: iconst_1
    //   189: isub
    //   190: istore_2
    //   191: iload_2
    //   192: sipush 128
    //   195: irem
    //   196: putstatic 30	o/O:ʼॱ	I
    //   199: iload_2
    //   200: iconst_2
    //   201: irem
    //   202: ifne +6 -> 208
    //   205: goto -33 -> 172
    //   208: goto +144 -> 352
    //   211: goto +237 -> 448
    //   214: sipush 273
    //   217: aload 5
    //   219: sipush 166
    //   222: saload
    //   223: i2b
    //   224: getstatic 310	o/O:ʿ	[S
    //   227: bipush 54
    //   229: saload
    //   230: i2s
    //   231: invokestatic 331	o/O:$$d	(IIS)Ljava/lang/String;
    //   234: astore 5
    //   236: goto -56 -> 180
    //   239: aload 5
    //   241: aload 6
    //   243: iconst_1
    //   244: anewarray 4	java/lang/Object
    //   247: dup
    //   248: iconst_0
    //   249: aload_0
    //   250: aastore
    //   251: invokevirtual 376	java/lang/reflect/Method:invoke	(Ljava/lang/Object;[Ljava/lang/Object;)Ljava/lang/Object;
    //   254: checkcast 323	java/lang/Integer
    //   257: invokevirtual 327	java/lang/Integer:intValue	()I
    //   260: istore_3
    //   261: goto +261 -> 522
    //   264: iload_2
    //   265: tableswitch	default:+23->288, 0:+224->489, 1:+-51->214
    //   288: goto -74 -> 214
    //   291: getstatic 30	o/O:ʼॱ	I
    //   294: istore 4
    //   296: iload 4
    //   298: iconst_5
    //   299: ior
    //   300: iconst_1
    //   301: ishl
    //   302: iload 4
    //   304: iconst_5
    //   305: ixor
    //   306: isub
    //   307: istore 4
    //   309: iload 4
    //   311: sipush 128
    //   314: irem
    //   315: putstatic 28	o/O:ʽॱ	I
    //   318: iload 4
    //   320: iconst_2
    //   321: irem
    //   322: ifeq +6 -> 328
    //   325: goto -287 -> 38
    //   328: goto -280 -> 48
    //   331: bipush 90
    //   333: iconst_0
    //   334: idiv
    //   335: istore_2
    //   336: iload_3
    //   337: ireturn
    //   338: getstatic 310	o/O:ʿ	[S
    //   341: astore 5
    //   343: goto +227 -> 570
    //   346: aload 5
    //   348: athrow
    //   349: goto -11 -> 338
    //   352: aload 7
    //   354: aload 5
    //   356: iconst_1
    //   357: anewarray 329	java/lang/Class
    //   360: dup
    //   361: iconst_0
    //   362: ldc 4
    //   364: aastore
    //   365: invokevirtual 393	java/lang/Class:getMethod	(Ljava/lang/String;[Ljava/lang/Class;)Ljava/lang/reflect/Method;
    //   368: astore 5
    //   370: goto +39 -> 409
    //   373: iload_2
    //   374: tableswitch	default:+22->396, 0:+140->514, 1:+184->558
    //   396: goto +162 -> 558
    //   399: iload_3
    //   400: ireturn
    //   401: iconst_1
    //   402: istore_2
    //   403: goto -139 -> 264
    //   406: astore_0
    //   407: aload_0
    //   408: athrow
    //   409: getstatic 30	o/O:ʼॱ	I
    //   412: istore_2
    //   413: iload_2
    //   414: bipush 107
    //   416: ior
    //   417: iconst_1
    //   418: ishl
    //   419: iload_2
    //   420: bipush 107
    //   422: ixor
    //   423: isub
    //   424: istore_2
    //   425: iload_2
    //   426: sipush 128
    //   429: irem
    //   430: putstatic 28	o/O:ʽॱ	I
    //   433: iload_2
    //   434: iconst_2
    //   435: irem
    //   436: ifeq +6 -> 442
    //   439: goto -404 -> 35
    //   442: goto -203 -> 239
    //   445: goto -329 -> 116
    //   448: getstatic 28	o/O:ʽॱ	I
    //   451: istore_2
    //   452: iload_2
    //   453: bipush 67
    //   455: ixor
    //   456: iload_2
    //   457: bipush 67
    //   459: iand
    //   460: iconst_1
    //   461: ishl
    //   462: iadd
    //   463: istore_2
    //   464: iload_2
    //   465: sipush 128
    //   468: irem
    //   469: putstatic 30	o/O:ʼॱ	I
    //   472: iload_2
    //   473: iconst_2
    //   474: irem
    //   475: ifne +6 -> 481
    //   478: goto -303 -> 175
    //   481: goto -370 -> 111
    //   484: iconst_0
    //   485: istore_2
    //   486: goto -222 -> 264
    //   489: sipush 273
    //   492: aload 5
    //   494: sipush 25487
    //   497: saload
    //   498: i2b
    //   499: getstatic 310	o/O:ʿ	[S
    //   502: bipush 59
    //   504: saload
    //   505: i2s
    //   506: invokestatic 331	o/O:$$d	(IIS)Ljava/lang/String;
    //   509: astore 5
    //   511: goto -331 -> 180
    //   514: getstatic 378	o/O:ॱˋ	Ljava/lang/Object;
    //   517: astore 6
    //   519: goto -74 -> 445
    //   522: getstatic 28	o/O:ʽॱ	I
    //   525: istore_2
    //   526: iload_2
    //   527: bipush 119
    //   529: ixor
    //   530: iload_2
    //   531: bipush 119
    //   533: iand
    //   534: iconst_1
    //   535: ishl
    //   536: iadd
    //   537: istore_2
    //   538: iload_2
    //   539: sipush 128
    //   542: irem
    //   543: putstatic 30	o/O:ʼॱ	I
    //   546: iload_2
    //   547: iconst_2
    //   548: irem
    //   549: ifne +6 -> 555
    //   552: goto -509 -> 43
    //   555: goto -407 -> 148
    //   558: getstatic 378	o/O:ॱˋ	Ljava/lang/Object;
    //   561: astore_0
    //   562: new 290	java/lang/NullPointerException
    //   565: dup
    //   566: invokespecial 293	java/lang/NullPointerException:<init>	()V
    //   569: athrow
    //   570: aload 5
    //   572: sipush 413
    //   575: saload
    //   576: ineg
    //   577: i2s
    //   578: istore_2
    //   579: getstatic 310	o/O:ʿ	[S
    //   582: sipush 368
    //   585: saload
    //   586: istore_3
    //   587: iload_3
    //   588: i2b
    //   589: istore_3
    //   590: goto -299 -> 291
    // Local variable table:
    //   start	length	slot	name	signature
    //   0	593	0	paramObject	Object
    //   60	4	1	s	short
    //   3	576	2	i	int
    //   48	542	3	j	int
    //   294	28	4	k	int
    //   75	1	5	arrayOfShort	short[]
    //   154	64	5	localObject1	Object
    //   234	337	5	localObject2	Object
    //   241	277	6	localObject3	Object
    //   70	283	7	localClass	Class
    // Exception table:
    //   from	to	target	type
    //   116	133	145	java/lang/IllegalArgumentException
    //   180	184	145	java/lang/IndexOutOfBoundsException
    //   191	199	145	java/lang/RuntimeException
    //   425	433	145	java/lang/NullPointerException
    //   538	546	145	java/lang/NullPointerException
    //   61	77	154	finally
    //   214	236	154	finally
    //   239	261	154	finally
    //   338	343	154	finally
    //   352	370	154	finally
    //   489	511	154	finally
    //   579	587	154	finally
    //   409	413	406	java/lang/UnsupportedOperationException
    //   448	452	406	java/lang/UnsupportedOperationException
    //   464	472	406	java/lang/UnsupportedOperationException
    //   464	472	406	java/lang/IllegalStateException
    //   522	526	406	java/lang/IllegalStateException
    //   558	562	406	java/lang/ArrayStoreException
  }
}
