package o;

import java.lang.reflect.Type;
import java.util.ArrayList;
import java.util.Iterator;
import java.util.List;
import java.util.Map;
import java.util.Map.Entry;
import java.util.Set;

public final class oj
  implements nS
{
  private final nU ˊ;
  final boolean ˏ;
  
  public oj(nU paramNU, boolean paramBoolean)
  {
    this.ˊ = paramNU;
    this.ˏ = paramBoolean;
  }
  
  private nR<?> ॱ(nw paramNw, Type paramType)
  {
    if ((paramType == Boolean.TYPE) || (paramType == Boolean.class)) {
      return ow.ʼ;
    }
    return paramNw.ˎ(ox.ˎ(paramType));
  }
  
  public <T> nR<T> ˊ(nw paramNw, ox<T> paramOx)
  {
    Object localObject = paramOx.ˏ();
    if (!Map.class.isAssignableFrom(paramOx.ॱ())) {
      return null;
    }
    localObject = nV.ॱ((Type)localObject, nV.ˏ((Type)localObject));
    nR localNR1 = ॱ(paramNw, localObject[0]);
    nR localNR2 = paramNw.ˎ(ox.ˎ(localObject[1]));
    paramOx = this.ˊ.ˎ(paramOx);
    return new ˋ(paramNw, localObject[0], localNR1, localObject[1], localNR2, paramOx);
  }
  
  final class ˋ<K, V>
    extends nR<Map<K, V>>
  {
    private static int ʻ = 2052647665;
    private static int ʼ = 0;
    private static long ˊ;
    private static int ॱॱ = 1;
    private static char ᐝ = '\000';
    private final oa<? extends Map<K, V>> ˎ;
    private final nR<K> ˏ;
    private final nR<V> ॱ;
    
    static
    {
      ˊ = 0L;
    }
    
    public ˋ(Type paramType1, nR<K> paramNR, Type paramType2, nR<V> paramNR1, oa<? extends Map<K, V>> paramOa)
    {
      this.ˏ = new ot(paramType1, paramType2, paramNR);
      this.ॱ = new ot(paramType1, paramOa, paramNR1);
      Object localObject;
      this.ˎ = localObject;
    }
    
    private static String ˋ(char[] paramArrayOfChar1, char paramChar, char[] paramArrayOfChar2, int paramInt, char[] paramArrayOfChar3)
    {
      char c;
      label45:
      char[] arrayOfChar;
      for (;;)
      {
        if (paramChar >= c)
        {
          break label236;
          continue;
          paramInt = ʼ + 95;
          ॱॱ = paramInt % 128;
          if (paramInt % 2 == 0) {
            break label310;
          }
          break label376;
          switch (paramInt)
          {
          default: 
            break;
            paramInt = ॱॱ + 7;
            ʼ = paramInt % 128;
            if (paramInt % 2 == 0) {
              break label371;
            }
            paramInt = 1;
            break;
          }
          for (;;)
          {
            c = ʼ + 73;
            ॱॱ = c % '';
            if (c % '\002' == 0) {
              break label382;
            }
            break label241;
            oJ.ˏ(paramArrayOfChar1, paramArrayOfChar3, paramChar);
            arrayOfChar[paramChar] = ((char)(int)(paramArrayOfChar2[paramChar] ^ paramArrayOfChar1[((paramChar + '\003') % 4)] ^ ˊ ^ ʻ ^ ᐝ));
            paramChar += '\001';
            break;
            oJ.ˏ(paramArrayOfChar1, paramArrayOfChar3, paramChar);
            arrayOfChar[paramChar] = ((char)(int)((paramArrayOfChar2[paramChar] ^ paramArrayOfChar1[(paramChar % '\005' - 4)]) / ˊ * ʻ | ᐝ));
            paramChar += 'v';
            break;
          }
          continue;
          label236:
          paramInt = 1;
          break label316;
        }
      }
      label241:
      label310:
      label316:
      label371:
      label376:
      label382:
      for (;;)
      {
        paramArrayOfChar1 = (char[])paramArrayOfChar1.clone();
        paramArrayOfChar3 = (char[])paramArrayOfChar3.clone();
        paramArrayOfChar1[0] = ((char)(paramArrayOfChar1[0] ^ paramChar));
        paramArrayOfChar3[2] = ((char)(paramArrayOfChar3[2] + (char)paramInt));
        c = paramArrayOfChar2.length;
        arrayOfChar = new char[c];
        paramChar = '\000';
        break;
        for (;;)
        {
          return new String(arrayOfChar);
          paramInt = 0;
          break label316;
          paramInt = 30;
          break;
          switch (paramInt)
          {
          }
        }
        for (;;)
        {
          switch (paramInt)
          {
          }
          break;
          paramInt = 0;
        }
        paramInt = 18;
        break label45;
      }
    }
    
    private String ˏ(nG paramNG)
    {
      break label297;
      int i;
      label102:
      label118:
      label143:
      boolean bool;
      for (;;)
      {
        try
        {
          i = ॱॱ + 11;
          ʼ = i % 128;
          if (i % 2 == 0)
          {
            continue;
            switch (i)
            {
            default: 
              continue;
              i = ॱॱ + 17;
              ʼ = i % 128;
              if (i % 2 == 0) {
                return "null";
              }
              throw new NullPointerException();
              throw new AssertionError();
              continue;
              if (!paramNG.ᐝ())
              {
                continue;
                switch (i)
                {
                default: 
                  continue;
                  bool = paramNG.ʼ();
                }
              }
              break;
            }
          }
        }
        catch (Exception paramNG)
        {
          label172:
          throw paramNG;
        }
        try
        {
          paramNG = Boolean.toString(bool);
          return paramNG;
        }
        catch (Exception paramNG)
        {
          throw paramNG;
        }
        i = 1;
        continue;
        paramNG = paramNG.ॱ();
        i = 81 / 0;
        return paramNG;
        throw new AssertionError();
        i = 75;
      }
      label186:
      paramNG = paramNG.ˊॱ();
      if (!paramNG.ॱˎ()) {
        break label276;
      }
      for (;;)
      {
        switch (i)
        {
        case 78: 
        default: 
          break label339;
          i = 25;
          break;
          return String.valueOf(paramNG.ˏ());
          i = 0;
          break label118;
          do
          {
            i = 90;
            break label204;
            while (!paramNG.ॱˋ())
            {
              break label172;
              if (paramNG.ॱˊ()) {
                break label143;
              }
            }
            return paramNG.ॱ();
            i = ॱॱ;
            i += 109;
            ʼ = i % 128;
          } while (i % 2 != 0);
          break;
        case 90: 
          for (;;)
          {
            label204:
            label276:
            label297:
            if (paramNG.ॱॱ()) {
              break label102;
            }
            break;
            label339:
            bool = paramNG.ᐝ();
            i = null.length;
            if (bool) {
              break label186;
            }
          }
          i = 78;
        }
      }
    }
    
    public void ˋ(oC paramOC, Map<K, V> paramMap)
    {
      int i;
      Object localObject;
      label100:
      int j;
      label135:
      label151:
      label219:
      label266:
      label312:
      label343:
      label368:
      label369:
      label375:
      ArrayList localArrayList;
      for (;;)
      {
        int k;
        switch (i)
        {
        default: 
          break;
          for (;;)
          {
            break label531;
            i = ʼ + 101;
            ॱॱ = i % 128;
            if (i % 2 != 0)
            {
              break label948;
              paramOC.ˏ();
              i = 0;
              k = ((List)localObject).size();
              break label100;
              i = 44;
              break label312;
              if (i != 0) {
                break label824;
              }
              break label943;
              j = ʼ + 51;
              ॱॱ = j % 128;
              if (j % 2 != 0)
              {
                break label531;
                for (;;)
                {
                  i = 0;
                  break label641;
                  if (paramMap == null) {
                    break;
                  }
                }
                i = 48;
                break label582;
                if (i < j) {
                  break label867;
                }
                do
                {
                  j = 0;
                  break label758;
                  paramMap = (Map.Entry)((Iterator)localObject).next();
                  paramOC.ˎ(String.valueOf(paramMap.getKey()));
                  this.ॱ.ˎ(paramOC, paramMap.getValue());
                  break label968;
                  paramOC.ˊ();
                  break label368;
                  paramMap = (Map.Entry)((Iterator)localObject).next();
                  paramOC.ˎ(String.valueOf(paramMap.getKey()));
                  this.ॱ.ˎ(paramOC, paramMap.getValue());
                  throw new NullPointerException();
                  try
                  {
                    localObject = oj.this;
                    try
                    {
                      boolean bool = ((oj)localObject).ˏ;
                      if (bool)
                      {
                        break;
                        paramOC.ॱ();
                        i = 0;
                        j = ((List)localObject).size();
                        break label151;
                      }
                      i = 98;
                      switch (i)
                      {
                      }
                    }
                    catch (Exception paramOC)
                    {
                      throw paramOC;
                    }
                  }
                  catch (Exception paramOC)
                  {
                    throw paramOC;
                  }
                  j = 0;
                  break label954;
                } while (paramMap.ʻ());
                break label962;
                return;
                i = 70;
                break label582;
                paramOC.ˎ(ˏ((nG)((List)localObject).get(i)));
                this.ॱ.ˎ(paramOC, localArrayList.get(i));
                i += 1;
                break label806;
                label418:
                break label790;
              }
            }
            else
            {
              break label948;
              label427:
              paramOC.ˎ(ˏ((nG)((List)localObject).get(i)));
              this.ॱ.ˎ(paramOC, localArrayList.get(i));
              i += 107;
              break label806;
              i = 1;
              break label641;
              label476:
              j = 1;
              break label954;
              i = 81;
              break;
            }
          }
        }
        for (;;)
        {
          j = 99;
          break label834;
          i = ʼ + 9;
          ॱॱ = i % 128;
          label531:
          Iterator localIterator;
          if (i % 2 != 0)
          {
            break label984;
            paramOC.ˎ();
            return;
            break label135;
            break label806;
            i = 0;
            localObject = new ArrayList(paramMap.size());
            localArrayList = new ArrayList(paramMap.size());
            localIterator = paramMap.entrySet().iterator();
            break label790;
            label582:
            switch (i)
            {
            }
            break label219;
            label611:
            j = ॱॱ + 75;
            ʼ = j % 128;
            if (j % 2 != 0) {
              break label427;
            }
            break label375;
            label641:
            switch (i)
            {
            }
            break label266;
            i = ॱॱ + 11;
            ʼ = i % 128;
            if (i % 2 != 0) {
              break label369;
            }
          }
          label758:
          label790:
          while (localIterator.hasNext())
          {
            Map.Entry localEntry = (Map.Entry)localIterator.next();
            paramMap = this.ˏ.ˎ(localEntry.getKey());
            ((List)localObject).add(paramMap);
            localArrayList.add(localEntry.getValue());
            if (!paramMap.ʽ()) {
              break;
            }
            break label476;
            switch (j)
            {
            }
            break label476;
            break label984;
          }
          break;
          label806:
          if (i < k) {
            break label1005;
          }
        }
        paramOC.ˎ();
        return;
        label824:
        i = 1;
        break label915;
        label829:
        i = 1;
      }
      for (;;)
      {
        label834:
        switch (j)
        {
        }
        break label611;
        label867:
        paramOC.ॱ();
        oi.ˋ((nG)((List)localObject).get(i), paramOC);
        this.ॱ.ˎ(paramOC, localArrayList.get(i));
        paramOC.ˊ();
        i += 1;
        break label343;
        for (;;)
        {
          label915:
          switch (i)
          {
          }
          break;
          label943:
          i = 0;
        }
        label948:
        paramOC.ॱॱ();
        return;
        label954:
        i |= j;
        break label418;
        label962:
        j = 1;
        break label758;
        for (;;)
        {
          label968:
          if (((Iterator)localObject).hasNext()) {
            break label1003;
          }
          break;
          label984:
          paramOC.ˏ();
          localObject = paramMap.entrySet().iterator();
        }
        label1003:
        break label829;
        label1005:
        j = 65;
      }
    }
    
    /* Error */
    public Map<K, V> ˏ(ov paramOv)
    {
      // Byte code:
      //   0: goto +200 -> 200
      //   3: astore_1
      //   4: aload_1
      //   5: athrow
      //   6: aload_1
      //   7: invokevirtual 223	o/ov:ˊ	()Z
      //   10: ifeq +6 -> 16
      //   13: goto +474 -> 487
      //   16: goto +391 -> 407
      //   19: getstatic 31	o/oj$ˋ:ॱॱ	I
      //   22: bipush 87
      //   24: iadd
      //   25: istore_2
      //   26: iload_2
      //   27: sipush 128
      //   30: irem
      //   31: putstatic 29	o/oj$ˋ:ʼ	I
      //   34: iload_2
      //   35: iconst_2
      //   36: irem
      //   37: ifeq +6 -> 43
      //   40: goto +148 -> 188
      //   43: goto +713 -> 756
      //   46: getstatic 29	o/oj$ˋ:ʼ	I
      //   49: bipush 29
      //   51: iadd
      //   52: istore_2
      //   53: iload_2
      //   54: sipush 128
      //   57: irem
      //   58: putstatic 31	o/oj$ˋ:ॱॱ	I
      //   61: iload_2
      //   62: iconst_2
      //   63: irem
      //   64: ifne +6 -> 70
      //   67: goto +474 -> 541
      //   70: goto +344 -> 414
      //   73: aload_1
      //   74: invokevirtual 225	o/ov:ॱ	()V
      //   77: aload_0
      //   78: getfield 52	o/oj$ˋ:ˏ	Lo/nR;
      //   81: aload_1
      //   82: invokevirtual 227	o/nR:ˊ	(Lo/ov;)Ljava/lang/Object;
      //   85: astore_3
      //   86: aload 4
      //   88: aload_3
      //   89: aload_0
      //   90: getfield 54	o/oj$ˋ:ॱ	Lo/nR;
      //   93: aload_1
      //   94: invokevirtual 227	o/nR:ˊ	(Lo/ov;)Ljava/lang/Object;
      //   97: invokeinterface 231 3 0
      //   102: ifnull +6 -> 108
      //   105: goto +98 -> 203
      //   108: goto +14 -> 122
      //   111: aload 4
      //   113: areturn
      //   114: iconst_1
      //   115: istore_2
      //   116: goto +31 -> 147
      //   119: astore_1
      //   120: aload_1
      //   121: athrow
      //   122: aload_1
      //   123: invokevirtual 233	o/ov:ˋ	()V
      //   126: goto -120 -> 6
      //   129: aload_1
      //   130: invokevirtual 236	o/ov:ॱॱ	()Lo/oz;
      //   133: astore_3
      //   134: aload_3
      //   135: getstatic 241	o/oz:ʼ	Lo/oz;
      //   138: if_acmpne +6 -> 144
      //   141: goto +610 -> 751
      //   144: goto -30 -> 114
      //   147: iload_2
      //   148: tableswitch	default:+24->172, 0:+366->514, 1:+307->455
      //   172: goto +283 -> 455
      //   175: aload_1
      //   176: invokevirtual 223	o/ov:ˊ	()Z
      //   179: ifeq +6 -> 185
      //   182: goto -136 -> 46
      //   185: goto +371 -> 556
      //   188: aload_1
      //   189: invokevirtual 225	o/ov:ॱ	()V
      //   192: bipush 66
      //   194: iconst_0
      //   195: idiv
      //   196: istore_2
      //   197: goto -191 -> 6
      //   200: goto -71 -> 129
      //   203: new 243	o/nM
      //   206: dup
      //   207: new 245	java/lang/StringBuilder
      //   210: dup
      //   211: invokespecial 246	java/lang/StringBuilder:<init>	()V
      //   214: iconst_4
      //   215: newarray char
      //   217: dup
      //   218: iconst_0
      //   219: ldc -9
      //   221: castore
      //   222: dup
      //   223: iconst_1
      //   224: ldc -8
      //   226: castore
      //   227: dup
      //   228: iconst_2
      //   229: ldc -7
      //   231: castore
      //   232: dup
      //   233: iconst_3
      //   234: ldc -6
      //   236: castore
      //   237: ldc -5
      //   239: bipush 15
      //   241: newarray char
      //   243: dup
      //   244: iconst_0
      //   245: ldc -4
      //   247: castore
      //   248: dup
      //   249: iconst_1
      //   250: ldc -3
      //   252: castore
      //   253: dup
      //   254: iconst_2
      //   255: ldc -2
      //   257: castore
      //   258: dup
      //   259: iconst_3
      //   260: ldc -1
      //   262: castore
      //   263: dup
      //   264: iconst_4
      //   265: ldc_w 256
      //   268: castore
      //   269: dup
      //   270: iconst_5
      //   271: ldc_w 257
      //   274: castore
      //   275: dup
      //   276: bipush 6
      //   278: ldc_w 258
      //   281: castore
      //   282: dup
      //   283: bipush 7
      //   285: ldc_w 259
      //   288: castore
      //   289: dup
      //   290: bipush 8
      //   292: ldc_w 260
      //   295: castore
      //   296: dup
      //   297: bipush 9
      //   299: ldc_w 261
      //   302: castore
      //   303: dup
      //   304: bipush 10
      //   306: ldc_w 262
      //   309: castore
      //   310: dup
      //   311: bipush 11
      //   313: ldc_w 263
      //   316: castore
      //   317: dup
      //   318: bipush 12
      //   320: ldc_w 264
      //   323: castore
      //   324: dup
      //   325: bipush 13
      //   327: ldc_w 265
      //   330: castore
      //   331: dup
      //   332: bipush 14
      //   334: ldc_w 266
      //   337: castore
      //   338: ldc_w 267
      //   341: iconst_4
      //   342: newarray char
      //   344: dup
      //   345: iconst_0
      //   346: ldc_w 268
      //   349: castore
      //   350: dup
      //   351: iconst_1
      //   352: ldc_w 268
      //   355: castore
      //   356: dup
      //   357: iconst_2
      //   358: ldc_w 268
      //   361: castore
      //   362: dup
      //   363: iconst_3
      //   364: ldc_w 268
      //   367: castore
      //   368: invokestatic 270	o/oj$ˋ:ˋ	([CC[CI[C)Ljava/lang/String;
      //   371: invokevirtual 273	java/lang/String:intern	()Ljava/lang/String;
      //   374: invokevirtual 277	java/lang/StringBuilder:append	(Ljava/lang/String;)Ljava/lang/StringBuilder;
      //   377: aload_3
      //   378: invokevirtual 280	java/lang/StringBuilder:append	(Ljava/lang/Object;)Ljava/lang/StringBuilder;
      //   381: invokevirtual 282	java/lang/StringBuilder:toString	()Ljava/lang/String;
      //   384: invokespecial 285	o/nM:<init>	(Ljava/lang/String;)V
      //   387: athrow
      //   388: goto +8 -> 396
      //   391: iconst_1
      //   392: istore_2
      //   393: goto +438 -> 831
      //   396: aload_1
      //   397: invokevirtual 287	o/ov:ʼ	()V
      //   400: aconst_null
      //   401: areturn
      //   402: iconst_0
      //   403: istore_2
      //   404: goto +427 -> 831
      //   407: aload_1
      //   408: invokevirtual 233	o/ov:ˋ	()V
      //   411: goto -300 -> 111
      //   414: getstatic 292	o/oc:ˎ	Lo/oc;
      //   417: aload_1
      //   418: invokevirtual 295	o/oc:ˎ	(Lo/ov;)V
      //   421: aload_0
      //   422: getfield 52	o/oj$ˋ:ˏ	Lo/nR;
      //   425: aload_1
      //   426: invokevirtual 227	o/nR:ˊ	(Lo/ov;)Ljava/lang/Object;
      //   429: astore_3
      //   430: aload 4
      //   432: aload_3
      //   433: aload_0
      //   434: getfield 54	o/oj$ˋ:ॱ	Lo/nR;
      //   437: aload_1
      //   438: invokevirtual 227	o/nR:ˊ	(Lo/ov;)Ljava/lang/Object;
      //   441: invokeinterface 231 3 0
      //   446: ifnull +6 -> 452
      //   449: goto +117 -> 566
      //   452: goto +111 -> 563
      //   455: aload_0
      //   456: getfield 56	o/oj$ˋ:ˎ	Lo/oa;
      //   459: invokeinterface 299 1 0
      //   464: checkcast 182	java/util/Map
      //   467: astore 4
      //   469: aload_3
      //   470: getstatic 301	o/oz:ॱ	Lo/oz;
      //   473: if_acmpne +6 -> 479
      //   476: goto -85 -> 391
      //   479: goto -77 -> 402
      //   482: iconst_0
      //   483: istore_2
      //   484: goto +279 -> 763
      //   487: getstatic 31	o/oj$ˋ:ॱॱ	I
      //   490: bipush 117
      //   492: iadd
      //   493: istore_2
      //   494: iload_2
      //   495: sipush 128
      //   498: irem
      //   499: putstatic 29	o/oj$ˋ:ʼ	I
      //   502: iload_2
      //   503: iconst_2
      //   504: irem
      //   505: ifeq +6 -> 511
      //   508: goto -26 -> 482
      //   511: goto +40 -> 551
      //   514: getstatic 29	o/oj$ˋ:ʼ	I
      //   517: bipush 87
      //   519: iadd
      //   520: istore_2
      //   521: iload_2
      //   522: sipush 128
      //   525: irem
      //   526: putstatic 31	o/oj$ˋ:ॱॱ	I
      //   529: iload_2
      //   530: iconst_2
      //   531: irem
      //   532: ifne +6 -> 538
      //   535: goto -147 -> 388
      //   538: goto -142 -> 396
      //   541: goto -127 -> 414
      //   544: aload_1
      //   545: invokevirtual 303	o/ov:ˏ	()V
      //   548: goto -373 -> 175
      //   551: iconst_1
      //   552: istore_2
      //   553: goto +210 -> 763
      //   556: aload_1
      //   557: invokevirtual 305	o/ov:ˎ	()V
      //   560: aload 4
      //   562: areturn
      //   563: goto -388 -> 175
      //   566: new 243	o/nM
      //   569: dup
      //   570: new 245	java/lang/StringBuilder
      //   573: dup
      //   574: invokespecial 246	java/lang/StringBuilder:<init>	()V
      //   577: iconst_4
      //   578: newarray char
      //   580: dup
      //   581: iconst_0
      //   582: ldc -9
      //   584: castore
      //   585: dup
      //   586: iconst_1
      //   587: ldc -8
      //   589: castore
      //   590: dup
      //   591: iconst_2
      //   592: ldc -7
      //   594: castore
      //   595: dup
      //   596: iconst_3
      //   597: ldc -6
      //   599: castore
      //   600: ldc -5
      //   602: bipush 15
      //   604: newarray char
      //   606: dup
      //   607: iconst_0
      //   608: ldc -4
      //   610: castore
      //   611: dup
      //   612: iconst_1
      //   613: ldc -3
      //   615: castore
      //   616: dup
      //   617: iconst_2
      //   618: ldc -2
      //   620: castore
      //   621: dup
      //   622: iconst_3
      //   623: ldc -1
      //   625: castore
      //   626: dup
      //   627: iconst_4
      //   628: ldc_w 256
      //   631: castore
      //   632: dup
      //   633: iconst_5
      //   634: ldc_w 257
      //   637: castore
      //   638: dup
      //   639: bipush 6
      //   641: ldc_w 258
      //   644: castore
      //   645: dup
      //   646: bipush 7
      //   648: ldc_w 259
      //   651: castore
      //   652: dup
      //   653: bipush 8
      //   655: ldc_w 260
      //   658: castore
      //   659: dup
      //   660: bipush 9
      //   662: ldc_w 261
      //   665: castore
      //   666: dup
      //   667: bipush 10
      //   669: ldc_w 262
      //   672: castore
      //   673: dup
      //   674: bipush 11
      //   676: ldc_w 263
      //   679: castore
      //   680: dup
      //   681: bipush 12
      //   683: ldc_w 264
      //   686: castore
      //   687: dup
      //   688: bipush 13
      //   690: ldc_w 265
      //   693: castore
      //   694: dup
      //   695: bipush 14
      //   697: ldc_w 266
      //   700: castore
      //   701: ldc_w 267
      //   704: iconst_4
      //   705: newarray char
      //   707: dup
      //   708: iconst_0
      //   709: ldc_w 268
      //   712: castore
      //   713: dup
      //   714: iconst_1
      //   715: ldc_w 268
      //   718: castore
      //   719: dup
      //   720: iconst_2
      //   721: ldc_w 268
      //   724: castore
      //   725: dup
      //   726: iconst_3
      //   727: ldc_w 268
      //   730: castore
      //   731: invokestatic 270	o/oj$ˋ:ˋ	([CC[CI[C)Ljava/lang/String;
      //   734: invokevirtual 273	java/lang/String:intern	()Ljava/lang/String;
      //   737: invokevirtual 277	java/lang/StringBuilder:append	(Ljava/lang/String;)Ljava/lang/StringBuilder;
      //   740: aload_3
      //   741: invokevirtual 280	java/lang/StringBuilder:append	(Ljava/lang/Object;)Ljava/lang/StringBuilder;
      //   744: invokevirtual 282	java/lang/StringBuilder:toString	()Ljava/lang/String;
      //   747: invokespecial 285	o/nM:<init>	(Ljava/lang/String;)V
      //   750: athrow
      //   751: iconst_0
      //   752: istore_2
      //   753: goto -606 -> 147
      //   756: aload_1
      //   757: invokevirtual 225	o/ov:ॱ	()V
      //   760: goto -754 -> 6
      //   763: iload_2
      //   764: tableswitch	default:+24->788, 0:+27->791, 1:+-691->73
      //   788: goto -715 -> 73
      //   791: aload_1
      //   792: invokevirtual 225	o/ov:ॱ	()V
      //   795: aload_0
      //   796: getfield 52	o/oj$ˋ:ˏ	Lo/nR;
      //   799: astore_3
      //   800: aload_3
      //   801: aload_1
      //   802: invokevirtual 227	o/nR:ˊ	(Lo/ov;)Ljava/lang/Object;
      //   805: astore_3
      //   806: aload 4
      //   808: aload_3
      //   809: aload_0
      //   810: getfield 54	o/oj$ˋ:ॱ	Lo/nR;
      //   813: aload_1
      //   814: invokevirtual 227	o/nR:ˊ	(Lo/ov;)Ljava/lang/Object;
      //   817: invokeinterface 231 3 0
      //   822: pop
      //   823: new 82	java/lang/NullPointerException
      //   826: dup
      //   827: invokespecial 83	java/lang/NullPointerException:<init>	()V
      //   830: athrow
      //   831: iload_2
      //   832: tableswitch	default:+24->856, 0:+-288->544, 1:+-813->19
      //   856: goto -312 -> 544
      // Local variable table:
      //   start	length	slot	name	signature
      //   0	859	0	this	ˋ
      //   0	859	1	paramOv	ov
      //   25	807	2	i	int
      //   85	724	3	localObject1	Object
      //   86	721	4	localObject2	Object
      // Exception table:
      //   from	to	target	type
      //   791	795	3	java/lang/Exception
      //   795	800	3	java/lang/Exception
      //   800	806	3	java/lang/Exception
      //   806	831	3	java/lang/Exception
      //   122	126	119	java/lang/Exception
      //   756	760	119	java/lang/Exception
    }
  }
}
