package o;

import com.insidesecure.hce.MatrixHCEServerConfiguration;

public class pE
  extends pw
  implements MatrixHCEServerConfiguration
{
  private static int ʻ;
  private static byte[] ʼ;
  private static short[] ˊॱ;
  private static final String ˎ;
  private static int ˏॱ;
  private static int ͺ;
  private static int ॱॱ;
  private static int ᐝ;
  private String ʽ = null;
  private String ˊ = null;
  private String ˋ = null;
  private String ˏ;
  private long ॱ = 0L;
  
  static
  {
    break label43;
    int i = 69;
    break label100;
    for (;;)
    {
      i = ͺ + 45;
      ˏॱ = i % 128;
      if (i % 2 != 0) {
        break;
      }
      i = 18;
      break label100;
      return;
      label43:
      ͺ = 0;
      ˏॱ = 1;
      ˊ();
      ˎ = ॱ((short)0, -1082379490, (byte)57, -1855951549, -97).intern() + pE.class.getSimpleName();
    }
    for (;;)
    {
      i = null.length;
      return;
      label100:
      switch (i)
      {
      }
    }
  }
  
  public pE() {}
  
  static void ˊ()
  {
    ॱॱ = 96;
    ʼ = new byte[] { -55, -20, -36, -15, -9, 1, -31, 2, 15, 67, -89, 0, 67, -66, 1, -31, 14, 7, -5, 12, 47, 35, -65, 2, -12, -9, 15, 73, -79, -13, 9, 13, -7, 40, 39, -20, -62, 9, -9, 10, 39, -71, 33, -42, 38, 111, -116, 43, 104, -102, -44, -42, 4, -61, 44, -50, 37, 44, -45, 114, -57, -23, 34, -36, 33, 12, -77, -4, -64, 54, 13, -11, -46, 44, -50, 5, -48, 59, -62, -23, 54, -50, -57, 42, 45 };
    ᐝ = 1855951626;
    ʻ = 1082379556;
  }
  
  /* Error */
  private static String ॱ(short paramShort, int paramInt1, byte paramByte, int paramInt2, int paramInt3)
  {
    // Byte code:
    //   0: goto +162 -> 162
    //   3: getstatic 144	o/pE:ʻ	I
    //   6: istore 7
    //   8: iload 6
    //   10: ifeq +6 -> 16
    //   13: goto +178 -> 191
    //   16: goto +452 -> 468
    //   19: iload_1
    //   20: iload 4
    //   22: iadd
    //   23: iconst_2
    //   24: isub
    //   25: iload 7
    //   27: iadd
    //   28: iload 6
    //   30: iadd
    //   31: istore_1
    //   32: getstatic 141	o/pE:ᐝ	I
    //   35: iload_3
    //   36: iadd
    //   37: i2c
    //   38: istore 5
    //   40: aload 8
    //   42: iload 5
    //   44: invokevirtual 149	java/lang/StringBuilder:append	(C)Ljava/lang/StringBuilder;
    //   47: pop
    //   48: iconst_1
    //   49: istore_3
    //   50: goto +255 -> 305
    //   53: iconst_0
    //   54: istore 6
    //   56: goto +63 -> 119
    //   59: getstatic 28	o/pE:ͺ	I
    //   62: istore 6
    //   64: iload 6
    //   66: iconst_3
    //   67: iadd
    //   68: istore 6
    //   70: iload 6
    //   72: sipush 128
    //   75: irem
    //   76: putstatic 30	o/pE:ˏॱ	I
    //   79: iload 6
    //   81: iconst_2
    //   82: irem
    //   83: ifne +6 -> 89
    //   86: goto +179 -> 265
    //   89: goto +373 -> 462
    //   92: astore 8
    //   94: aload 8
    //   96: athrow
    //   97: getstatic 138	o/pE:ʼ	[B
    //   100: ifnull +6 -> 106
    //   103: goto +53 -> 156
    //   106: goto +62 -> 168
    //   109: aload 8
    //   111: invokevirtual 60	java/lang/StringBuilder:toString	()Ljava/lang/String;
    //   114: astore 8
    //   116: aload 8
    //   118: areturn
    //   119: getstatic 28	o/pE:ͺ	I
    //   122: bipush 25
    //   124: iadd
    //   125: istore 7
    //   127: iload 7
    //   129: sipush 128
    //   132: irem
    //   133: putstatic 30	o/pE:ˏॱ	I
    //   136: iload 7
    //   138: iconst_2
    //   139: irem
    //   140: ifne +6 -> 146
    //   143: goto +22 -> 165
    //   146: goto +156 -> 302
    //   149: iload 5
    //   151: istore 7
    //   153: goto +137 -> 290
    //   156: iconst_1
    //   157: istore 4
    //   159: goto +352 -> 511
    //   162: goto +172 -> 334
    //   165: goto +205 -> 370
    //   168: iconst_0
    //   169: istore 4
    //   171: goto +340 -> 511
    //   174: iload 4
    //   176: ifle +6 -> 182
    //   179: goto +461 -> 640
    //   182: goto -73 -> 109
    //   185: iconst_1
    //   186: istore 6
    //   188: goto +182 -> 370
    //   191: bipush 76
    //   193: istore 6
    //   195: goto +283 -> 478
    //   198: iload 6
    //   200: tableswitch	default:+24->224, 0:+-15->185, 1:+59->259
    //   224: goto +35 -> 259
    //   227: getstatic 151	o/pE:ˊॱ	[S
    //   230: getstatic 144	o/pE:ʻ	I
    //   233: iload_1
    //   234: iadd
    //   235: saload
    //   236: getstatic 74	o/pE:ॱॱ	I
    //   239: iadd
    //   240: i2s
    //   241: istore 4
    //   243: goto -69 -> 174
    //   246: iload 5
    //   248: istore 7
    //   250: goto +40 -> 290
    //   253: iload 6
    //   255: istore_1
    //   256: goto +191 -> 447
    //   259: iconst_0
    //   260: istore 6
    //   262: goto +108 -> 370
    //   265: iconst_1
    //   266: istore 6
    //   268: goto -70 -> 198
    //   271: getstatic 138	o/pE:ʼ	[B
    //   274: getstatic 144	o/pE:ʻ	I
    //   277: iload_1
    //   278: iadd
    //   279: baload
    //   280: getstatic 74	o/pE:ॱॱ	I
    //   283: iadd
    //   284: i2b
    //   285: istore 4
    //   287: goto -113 -> 174
    //   290: iload_3
    //   291: iload 4
    //   293: if_icmpge +6 -> 299
    //   296: goto +283 -> 579
    //   299: goto -190 -> 109
    //   302: goto +68 -> 370
    //   305: getstatic 28	o/pE:ͺ	I
    //   308: iconst_1
    //   309: iadd
    //   310: istore 6
    //   312: iload 6
    //   314: sipush 128
    //   317: irem
    //   318: putstatic 30	o/pE:ˏॱ	I
    //   321: iload 6
    //   323: iconst_2
    //   324: irem
    //   325: ifne +6 -> 331
    //   328: goto -179 -> 149
    //   331: goto -85 -> 246
    //   334: new 34	java/lang/StringBuilder
    //   337: dup
    //   338: invokespecial 37	java/lang/StringBuilder:<init>	()V
    //   341: astore 8
    //   343: getstatic 74	o/pE:ॱॱ	I
    //   346: iload 4
    //   348: iadd
    //   349: istore 6
    //   351: iload 6
    //   353: istore 4
    //   355: iload 6
    //   357: iconst_m1
    //   358: if_icmpne +6 -> 364
    //   361: goto +61 -> 422
    //   364: goto +52 -> 416
    //   367: goto +200 -> 567
    //   370: iload 6
    //   372: ifeq +6 -> 378
    //   375: goto -278 -> 97
    //   378: goto -204 -> 174
    //   381: astore 8
    //   383: aload 8
    //   385: athrow
    //   386: getstatic 138	o/pE:ʼ	[B
    //   389: astore 9
    //   391: iload_1
    //   392: iconst_1
    //   393: isub
    //   394: istore 6
    //   396: aload 9
    //   398: iload_1
    //   399: baload
    //   400: istore_1
    //   401: iload_1
    //   402: iload_0
    //   403: iadd
    //   404: i2b
    //   405: iload_2
    //   406: ixor
    //   407: iload 7
    //   409: iadd
    //   410: i2c
    //   411: istore 5
    //   413: goto -160 -> 253
    //   416: iconst_0
    //   417: istore 6
    //   419: goto +120 -> 539
    //   422: iconst_1
    //   423: istore 6
    //   425: goto +114 -> 539
    //   428: iload 5
    //   430: istore 7
    //   432: goto -142 -> 290
    //   435: iconst_1
    //   436: istore 6
    //   438: goto -419 -> 19
    //   441: iconst_0
    //   442: istore 6
    //   444: goto -425 -> 19
    //   447: aload 8
    //   449: iload 5
    //   451: invokevirtual 149	java/lang/StringBuilder:append	(C)Ljava/lang/StringBuilder;
    //   454: pop
    //   455: iload_3
    //   456: iconst_1
    //   457: iadd
    //   458: istore_3
    //   459: goto -31 -> 428
    //   462: iconst_0
    //   463: istore 6
    //   465: goto -267 -> 198
    //   468: bipush 44
    //   470: istore 6
    //   472: goto +6 -> 478
    //   475: goto -472 -> 3
    //   478: iload 6
    //   480: lookupswitch	default:+28->508, 44:+-39->441, 76:+-45->435
    //   508: goto -67 -> 441
    //   511: iload 4
    //   513: tableswitch	default:+23->536, 0:+-286->227, 1:+-242->271
    //   536: goto -265 -> 271
    //   539: iload 6
    //   541: tableswitch	default:+23->564, 0:+-488->53, 1:+-482->59
    //   564: goto -511 -> 53
    //   567: getstatic 138	o/pE:ʼ	[B
    //   570: ifnull +6 -> 576
    //   573: goto -187 -> 386
    //   576: goto +33 -> 609
    //   579: getstatic 30	o/pE:ˏॱ	I
    //   582: bipush 21
    //   584: iadd
    //   585: istore 6
    //   587: iload 6
    //   589: sipush 128
    //   592: irem
    //   593: putstatic 28	o/pE:ͺ	I
    //   596: iload 6
    //   598: iconst_2
    //   599: irem
    //   600: ifeq +6 -> 606
    //   603: goto -236 -> 367
    //   606: goto -39 -> 567
    //   609: getstatic 151	o/pE:ˊॱ	[S
    //   612: astore 9
    //   614: iload_1
    //   615: iconst_1
    //   616: isub
    //   617: istore 6
    //   619: aload 9
    //   621: iload_1
    //   622: saload
    //   623: iload_0
    //   624: iadd
    //   625: i2s
    //   626: iload_2
    //   627: ixor
    //   628: iload 7
    //   630: iadd
    //   631: i2c
    //   632: istore 5
    //   634: iload 6
    //   636: istore_1
    //   637: goto -190 -> 447
    //   640: getstatic 28	o/pE:ͺ	I
    //   643: bipush 125
    //   645: iadd
    //   646: istore 7
    //   648: iload 7
    //   650: sipush 128
    //   653: irem
    //   654: putstatic 30	o/pE:ˏॱ	I
    //   657: iload 7
    //   659: iconst_2
    //   660: irem
    //   661: ifne +6 -> 667
    //   664: goto -189 -> 475
    //   667: goto -664 -> 3
    // Local variable table:
    //   start	length	slot	name	signature
    //   0	670	0	paramShort	short
    //   0	670	1	paramInt1	int
    //   0	670	2	paramByte	byte
    //   0	670	3	paramInt2	int
    //   0	670	4	paramInt3	int
    //   38	595	5	i	int
    //   8	627	6	j	int
    //   6	655	7	k	int
    //   40	1	8	localObject1	Object
    //   92	18	8	localException1	Exception
    //   114	228	8	localObject2	Object
    //   381	67	8	localException2	Exception
    //   389	231	9	localObject3	Object
    // Exception table:
    //   from	to	target	type
    //   59	64	92	java/lang/Exception
    //   386	391	92	java/lang/Exception
    //   447	455	92	java/lang/Exception
    //   70	79	381	java/lang/Exception
    //   109	116	381	java/lang/Exception
  }
  
  public String getMapType()
  {
    for (;;)
    {
      try
      {
        i = ͺ + 97;
        ˏॱ = i % 128;
        if (i % 2 != 0) {
          break label67;
        }
      }
      catch (Exception localException)
      {
        int i;
        String str1;
        throw localException;
      }
      i = ˏॱ + 11;
      ͺ = i % 128;
      if (i % 2 == 0)
      {
        return str1;
      }
      else
      {
        return localException;
        label67:
        String str2 = this.ˏ;
      }
    }
  }
  
  /* Error */
  public long getMobileCheckInterval()
  {
    // Byte code:
    //   0: goto +76 -> 76
    //   3: astore 4
    //   5: aload 4
    //   7: athrow
    //   8: iconst_1
    //   9: istore_1
    //   10: goto +32 -> 42
    //   13: getstatic 30	o/pE:ˏॱ	I
    //   16: bipush 113
    //   18: iadd
    //   19: istore_1
    //   20: iload_1
    //   21: sipush 128
    //   24: irem
    //   25: putstatic 28	o/pE:ͺ	I
    //   28: iload_1
    //   29: iconst_2
    //   30: irem
    //   31: ifeq +6 -> 37
    //   34: goto +6 -> 40
    //   37: goto -29 -> 8
    //   40: iconst_0
    //   41: istore_1
    //   42: iload_1
    //   43: tableswitch	default:+21->64, 0:+21->64, 1:+36->79
    //   64: aload_0
    //   65: getfield 70	o/pE:ॱ	J
    //   68: lstore_2
    //   69: bipush 44
    //   71: iconst_0
    //   72: idiv
    //   73: istore_1
    //   74: lload_2
    //   75: lreturn
    //   76: goto -63 -> 13
    //   79: aload_0
    //   80: getfield 70	o/pE:ॱ	J
    //   83: lstore_2
    //   84: lload_2
    //   85: lreturn
    // Local variable table:
    //   start	length	slot	name	signature
    //   0	86	0	this	pE
    //   9	65	1	i	int
    //   68	17	2	l	long
    //   3	3	4	localException	Exception
    // Exception table:
    //   from	to	target	type
    //   79	84	3	java/lang/Exception
  }
  
  public String getName()
  {
    for (;;)
    {
      int i = 75;
      do
      {
        i = 77;
        for (;;)
        {
          return this.ˋ;
          switch (i)
          {
          }
        }
        i = ˏॱ + 35;
        ͺ = i % 128;
      } while (i % 2 != 0);
    }
    String str = this.ˋ;
    throw new NullPointerException();
  }
  
  /* Error */
  public String getServerType()
  {
    // Byte code:
    //   0: goto +13 -> 13
    //   3: iconst_1
    //   4: istore_1
    //   5: goto +29 -> 34
    //   8: iconst_0
    //   9: istore_1
    //   10: goto +24 -> 34
    //   13: goto +46 -> 59
    //   16: astore_2
    //   17: aload_2
    //   18: athrow
    //   19: aload_0
    //   20: getfield 68	o/pE:ˊ	Ljava/lang/String;
    //   23: areturn
    //   24: aload_0
    //   25: getfield 68	o/pE:ˊ	Ljava/lang/String;
    //   28: astore_2
    //   29: aconst_null
    //   30: arraylength
    //   31: istore_1
    //   32: aload_2
    //   33: areturn
    //   34: iload_1
    //   35: tableswitch	default:+21->56, 0:+-16->19, 1:+-11->24
    //   56: goto -32 -> 24
    //   59: getstatic 30	o/pE:ˏॱ	I
    //   62: bipush 25
    //   64: iadd
    //   65: istore_1
    //   66: iload_1
    //   67: sipush 128
    //   70: irem
    //   71: putstatic 28	o/pE:ͺ	I
    //   74: iload_1
    //   75: iconst_2
    //   76: irem
    //   77: ifeq +6 -> 83
    //   80: goto -77 -> 3
    //   83: goto -75 -> 8
    // Local variable table:
    //   start	length	slot	name	signature
    //   0	86	0	this	pE
    //   4	73	1	i	int
    //   16	2	2	localException	Exception
    //   28	5	2	str	String
    // Exception table:
    //   from	to	target	type
    //   24	32	16	java/lang/Exception
  }
  
  public String getVisaSigningPublicKey()
  {
    break label112;
    int i = ͺ + 81;
    ˏॱ = i % 128;
    String str;
    if (i % 2 != 0)
    {
      break label99;
      return str;
      label32:
      break label104;
    }
    label99:
    label104:
    label112:
    for (;;)
    {
      i = ͺ + 115;
      ˏॱ = i % 128;
      if (i % 2 == 0) {
        break label32;
      }
      break label104;
      for (;;)
      {
        switch (i)
        {
        case 1: 
        default: 
          return str;
          i = 0;
          break;
        case 0: 
          throw new NullPointerException();
          i = 1;
        }
      }
      str = this.ʽ;
      break;
    }
  }
  
  public void setMapType(String paramString)
  {
    for (;;)
    {
      int i = ˏॱ + 121;
      ͺ = i % 128;
      if (i % 2 != 0) {
        break;
      }
      return;
      do
      {
        break;
        i = ˏॱ + 1;
        ͺ = i % 128;
      } while (i % 2 != 0);
      this.ˏ = paramString;
    }
  }
  
  public void setMobileCheckInterval(long paramLong)
  {
    break label38;
    int i = ˏॱ + 123;
    ͺ = i % 128;
    if (i % 2 == 0) {
      break label41;
    }
    for (;;)
    {
      this.ॱ = paramLong;
      break;
      label38:
      break label95;
      label41:
      i = 22;
      break label64;
      i = 23;
      label64:
      label95:
      do
      {
        break;
        for (;;)
        {
          throw new NullPointerException();
          switch (i)
          {
          }
        }
        i = ˏॱ + 97;
        ͺ = i % 128;
      } while (i % 2 != 0);
    }
  }
  
  public void setName(String paramString)
  {
    for (;;)
    {
      try
      {
        this.ˋ = paramString;
      }
      catch (Exception paramString)
      {
        throw paramString;
      }
      break label43;
      int i = ͺ + 19;
      ˏॱ = i % 128;
      if (i % 2 != 0) {
        return;
      }
      return;
      label43:
      i = ˏॱ + 113;
      ͺ = i % 128;
      if (i % 2 == 0) {}
    }
  }
  
  public void setServerType(String paramString)
  {
    break label66;
    this.ˊ = paramString;
    break label74;
    return;
    label66:
    label69:
    for (int i = 0;; i = 1) {
      switch (i)
      {
      case 0: 
      default: 
        break label99;
        for (;;)
        {
          i = ˏॱ + 89;
          ͺ = i % 128;
          if (i % 2 != 0) {
            break label69;
          }
          break;
        }
      }
    }
    for (;;)
    {
      label74:
      i = ˏॱ + 71;
      ͺ = i % 128;
      if (i % 2 != 0) {
        break;
      }
      return;
      label99:
      this.ˊ = paramString;
      i = null.length;
    }
  }
  
  public void setVisaSigningPublicKey(String paramString)
  {
    break label64;
    this.ʽ = paramString;
    label64:
    for (;;)
    {
      int i = ˏॱ + 13;
      ͺ = i % 128;
      if (i % 2 != 0) {
        break;
      }
      break;
      i = ˏॱ + 77;
      ͺ = i % 128;
      if (i % 2 != 0) {
        return;
      }
      return;
    }
  }
  
  /* Error */
  public boolean ˎ()
  {
    // Byte code:
    //   0: goto +65 -> 65
    //   3: goto +209 -> 212
    //   6: iload_1
    //   7: lookupswitch	default:+25->32, 11:+127->134, 76:+154->161
    //   32: goto +102 -> 134
    //   35: getstatic 62	o/pE:ˎ	Ljava/lang/String;
    //   38: iconst_0
    //   39: ldc -85
    //   41: bipush 33
    //   43: ldc -84
    //   45: bipush -97
    //   47: invokestatic 42	o/pE:ॱ	(SIBII)Ljava/lang/String;
    //   50: invokevirtual 48	java/lang/String:intern	()Ljava/lang/String;
    //   53: invokestatic 178	o/pD:e	(Ljava/lang/String;Ljava/lang/String;)V
    //   56: iconst_0
    //   57: ireturn
    //   58: iconst_1
    //   59: ireturn
    //   60: astore 4
    //   62: aload 4
    //   64: athrow
    //   65: aload_0
    //   66: invokespecial 180	o/pw:ˎ	()Z
    //   69: ifne +6 -> 75
    //   72: goto +51 -> 123
    //   75: goto +164 -> 239
    //   78: getstatic 62	o/pE:ˎ	Ljava/lang/String;
    //   81: new 34	java/lang/StringBuilder
    //   84: dup
    //   85: invokespecial 37	java/lang/StringBuilder:<init>	()V
    //   88: iconst_0
    //   89: ldc -75
    //   91: bipush 10
    //   93: ldc -84
    //   95: bipush -97
    //   97: invokestatic 42	o/pE:ॱ	(SIBII)Ljava/lang/String;
    //   100: invokevirtual 48	java/lang/String:intern	()Ljava/lang/String;
    //   103: invokevirtual 52	java/lang/StringBuilder:append	(Ljava/lang/String;)Ljava/lang/StringBuilder;
    //   106: aload_0
    //   107: getfield 70	o/pE:ॱ	J
    //   110: invokevirtual 184	java/lang/StringBuilder:append	(J)Ljava/lang/StringBuilder;
    //   113: invokevirtual 60	java/lang/StringBuilder:toString	()Ljava/lang/String;
    //   116: invokestatic 178	o/pD:e	(Ljava/lang/String;Ljava/lang/String;)V
    //   119: iconst_0
    //   120: ireturn
    //   121: iconst_0
    //   122: ireturn
    //   123: bipush 11
    //   125: istore_1
    //   126: goto -120 -> 6
    //   129: iconst_1
    //   130: istore_1
    //   131: goto +50 -> 181
    //   134: getstatic 28	o/pE:ͺ	I
    //   137: bipush 25
    //   139: iadd
    //   140: istore_1
    //   141: iload_1
    //   142: sipush 128
    //   145: irem
    //   146: putstatic 30	o/pE:ˏॱ	I
    //   149: iload_1
    //   150: iconst_2
    //   151: irem
    //   152: ifne +6 -> 158
    //   155: goto +23 -> 178
    //   158: goto -155 -> 3
    //   161: aload_0
    //   162: getfield 70	o/pE:ॱ	J
    //   165: lstore_2
    //   166: lload_2
    //   167: lconst_0
    //   168: lcmp
    //   169: ifge +6 -> 175
    //   172: goto -94 -> 78
    //   175: goto +70 -> 245
    //   178: goto -175 -> 3
    //   181: iload_1
    //   182: tableswitch	default:+22->204, 0:+-124->58, 1:+-147->35
    //   204: goto -169 -> 35
    //   207: aconst_null
    //   208: arraylength
    //   209: istore_1
    //   210: iconst_0
    //   211: ireturn
    //   212: getstatic 28	o/pE:ͺ	I
    //   215: bipush 101
    //   217: iadd
    //   218: istore_1
    //   219: iload_1
    //   220: sipush 128
    //   223: irem
    //   224: putstatic 30	o/pE:ˏॱ	I
    //   227: iload_1
    //   228: iconst_2
    //   229: irem
    //   230: ifne +6 -> 236
    //   233: goto -26 -> 207
    //   236: goto -115 -> 121
    //   239: bipush 76
    //   241: istore_1
    //   242: goto -236 -> 6
    //   245: aload_0
    //   246: getfield 68	o/pE:ˊ	Ljava/lang/String;
    //   249: ifnonnull +6 -> 255
    //   252: goto -123 -> 129
    //   255: iconst_0
    //   256: istore_1
    //   257: goto -76 -> 181
    // Local variable table:
    //   start	length	slot	name	signature
    //   0	260	0	this	pE
    //   6	251	1	i	int
    //   165	2	2	l	long
    //   60	3	4	localException	Exception
    // Exception table:
    //   from	to	target	type
    //   161	166	60	java/lang/Exception
  }
}
