package o;

import com.insidesecure.hce.MatrixHCECard;
import java.util.Iterator;
import java.util.List;

public class pF
{
  private static char[] ˊ;
  private static long ˋ;
  private static final String ˎ;
  private static int ˏ;
  private static int ॱ;
  
  static
  {
    for (int i = 1;; i = 0)
    {
      switch (i)
      {
      default: 
        return;
        ॱ = 0;
        ˏ = 1;
        ˋ();
        ˎ = ˋ(3128, 52527, 19).intern() + pF.class.getSimpleName();
        break;
      case 1: 
        i = null.length;
        return;
      case 0: 
        return;
      }
      i = ˏ + 19;
      ॱ = i % 128;
      if (i % 2 != 0) {
        break;
      }
    }
  }
  
  public pF() {}
  
  /* Error */
  public static boolean notificationCallBack(android.content.Context paramContext, String paramString1, String paramString2)
  {
    // Byte code:
    //   0: goto +184 -> 184
    //   3: iconst_0
    //   4: istore 6
    //   6: aconst_null
    //   7: astore 8
    //   9: aload 11
    //   11: invokevirtual 62	o/pz:getPaymentAccounts	()Ljava/util/List;
    //   14: astore 10
    //   16: iconst_0
    //   17: istore 4
    //   19: goto +278 -> 297
    //   22: iconst_1
    //   23: istore_3
    //   24: aload 8
    //   26: astore 9
    //   28: goto +31 -> 59
    //   31: astore_0
    //   32: aload_0
    //   33: athrow
    //   34: iconst_0
    //   35: ireturn
    //   36: aload 10
    //   38: invokeinterface 68 1 0
    //   43: istore_3
    //   44: iload 4
    //   46: iload_3
    //   47: if_icmpge +6 -> 53
    //   50: goto +346 -> 396
    //   53: goto +81 -> 134
    //   56: goto +183 -> 239
    //   59: iload_3
    //   60: ifne +6 -> 66
    //   63: goto +261 -> 324
    //   66: goto +403 -> 469
    //   69: getstatic 19	o/pF:ˏ	I
    //   72: bipush 17
    //   74: iadd
    //   75: istore_3
    //   76: iload_3
    //   77: sipush 128
    //   80: irem
    //   81: putstatic 17	o/pF:ॱ	I
    //   84: iload_3
    //   85: iconst_2
    //   86: irem
    //   87: ifeq +6 -> 93
    //   90: goto -34 -> 56
    //   93: goto +146 -> 239
    //   96: iconst_0
    //   97: istore_3
    //   98: goto +305 -> 403
    //   101: iload 4
    //   103: iconst_1
    //   104: iadd
    //   105: istore 4
    //   107: goto -71 -> 36
    //   110: aload_0
    //   111: invokevirtual 74	android/content/Context:getApplicationContext	()Landroid/content/Context;
    //   114: astore 8
    //   116: aload 8
    //   118: invokestatic 80	o/pD:getInstance	(Landroid/content/Context;)Lo/pz;
    //   121: astore 11
    //   123: aload 11
    //   125: ifnonnull +6 -> 131
    //   128: goto +59 -> 187
    //   131: goto +10 -> 141
    //   134: bipush 20
    //   136: istore 5
    //   138: goto +111 -> 249
    //   141: iconst_1
    //   142: istore_3
    //   143: goto +71 -> 214
    //   146: iconst_0
    //   147: ireturn
    //   148: iconst_1
    //   149: istore_3
    //   150: aload 8
    //   152: astore 9
    //   154: goto -95 -> 59
    //   157: getstatic 19	o/pF:ˏ	I
    //   160: bipush 19
    //   162: iadd
    //   163: istore_3
    //   164: iload_3
    //   165: sipush 128
    //   168: irem
    //   169: putstatic 17	o/pF:ॱ	I
    //   172: iload_3
    //   173: iconst_2
    //   174: irem
    //   175: ifeq +6 -> 181
    //   178: goto +285 -> 463
    //   181: goto -85 -> 96
    //   184: goto +251 -> 435
    //   187: iconst_0
    //   188: istore_3
    //   189: goto +25 -> 214
    //   192: goto +129 -> 321
    //   195: aload 9
    //   197: aload_1
    //   198: invokevirtual 84	java/lang/String:equals	(Ljava/lang/Object;)Z
    //   201: istore 7
    //   203: iload 7
    //   205: ifeq +6 -> 211
    //   208: goto -51 -> 157
    //   211: goto -110 -> 101
    //   214: iload_3
    //   215: tableswitch	default:+21->236, 0:+-181->34, 1:+-212->3
    //   236: goto -202 -> 34
    //   239: aload_1
    //   240: ifnonnull +6 -> 246
    //   243: goto +199 -> 442
    //   246: goto -136 -> 110
    //   249: iload 6
    //   251: istore_3
    //   252: aload 8
    //   254: astore 9
    //   256: iload 5
    //   258: lookupswitch	default:+26->284, 20:+-199->59, 68:+103->361
    //   284: iload 6
    //   286: istore_3
    //   287: aload 8
    //   289: astore 9
    //   291: goto -232 -> 59
    //   294: astore_0
    //   295: aload_0
    //   296: athrow
    //   297: getstatic 17	o/pF:ॱ	I
    //   300: bipush 61
    //   302: iadd
    //   303: istore_3
    //   304: iload_3
    //   305: sipush 128
    //   308: irem
    //   309: putstatic 19	o/pF:ˏ	I
    //   312: iload_3
    //   313: iconst_2
    //   314: irem
    //   315: ifne +6 -> 321
    //   318: goto -126 -> 192
    //   321: goto -285 -> 36
    //   324: getstatic 50	o/pF:ˎ	Ljava/lang/String;
    //   327: new 23	java/lang/StringBuilder
    //   330: dup
    //   331: invokespecial 26	java/lang/StringBuilder:<init>	()V
    //   334: bipush 37
    //   336: iconst_0
    //   337: bipush 47
    //   339: invokestatic 30	o/pF:ˋ	(ICI)Ljava/lang/String;
    //   342: invokevirtual 36	java/lang/String:intern	()Ljava/lang/String;
    //   345: invokevirtual 40	java/lang/StringBuilder:append	(Ljava/lang/String;)Ljava/lang/StringBuilder;
    //   348: aload_1
    //   349: invokevirtual 40	java/lang/StringBuilder:append	(Ljava/lang/String;)Ljava/lang/StringBuilder;
    //   352: invokevirtual 48	java/lang/StringBuilder:toString	()Ljava/lang/String;
    //   355: invokestatic 88	o/pD:e	(Ljava/lang/String;Ljava/lang/String;)V
    //   358: goto +126 -> 484
    //   361: aload 10
    //   363: iload 4
    //   365: invokeinterface 92 2 0
    //   370: checkcast 94	com/insidesecure/hce/MatrixHCEAccount
    //   373: astore 8
    //   375: aload 8
    //   377: checkcast 96	o/pk
    //   380: invokevirtual 98	o/pk:ˏ	()Ljava/lang/String;
    //   383: astore 9
    //   385: aload 9
    //   387: ifnull +6 -> 393
    //   390: goto -195 -> 195
    //   393: goto -292 -> 101
    //   396: bipush 68
    //   398: istore 5
    //   400: goto -151 -> 249
    //   403: iload_3
    //   404: lookupswitch	default:+28->432, 0:+-256->148, 96:+-382->22
    //   432: goto -410 -> 22
    //   435: aload_2
    //   436: ifnull +6 -> 442
    //   439: goto -370 -> 69
    //   442: getstatic 50	o/pF:ˎ	Ljava/lang/String;
    //   445: iconst_0
    //   446: sipush 25349
    //   449: bipush 37
    //   451: invokestatic 30	o/pF:ˋ	(ICI)Ljava/lang/String;
    //   454: invokevirtual 36	java/lang/String:intern	()Ljava/lang/String;
    //   457: invokestatic 101	o/pD:i	(Ljava/lang/String;Ljava/lang/String;)V
    //   460: goto -314 -> 146
    //   463: bipush 96
    //   465: istore_3
    //   466: goto -63 -> 403
    //   469: aload_0
    //   470: aload 11
    //   472: aload 9
    //   474: invokeinterface 104 1 0
    //   479: aload_2
    //   480: invokestatic 107	o/pF:notificationCallBack	(Landroid/content/Context;Lo/pz;Ljava/lang/String;Ljava/lang/String;)Z
    //   483: ireturn
    //   484: iconst_0
    //   485: ireturn
    // Local variable table:
    //   start	length	slot	name	signature
    //   0	486	0	paramContext	android.content.Context
    //   0	486	1	paramString1	String
    //   0	486	2	paramString2	String
    //   23	443	3	i	int
    //   17	347	4	j	int
    //   136	263	5	k	int
    //   4	281	6	m	int
    //   201	3	7	bool	boolean
    //   7	369	8	localObject1	Object
    //   26	447	9	localObject2	Object
    //   14	348	10	localList	List
    //   9	462	11	localPz	pz
    // Exception table:
    //   from	to	target	type
    //   116	123	31	java/lang/Exception
    //   195	203	31	java/lang/Exception
    //   9	16	294	java/lang/Exception
    //   36	44	294	java/lang/Exception
    //   110	116	294	java/lang/Exception
    //   116	123	294	java/lang/Exception
  }
  
  /* Error */
  public static boolean notificationCallBack(android.content.Context paramContext, pz paramPz, String paramString1, String paramString2)
  {
    // Byte code:
    //   0: goto +1274 -> 1274
    //   3: bipush 76
    //   5: istore 4
    //   7: goto +525 -> 532
    //   10: getstatic 17	o/pF:ॱ	I
    //   13: bipush 79
    //   15: iadd
    //   16: istore 4
    //   18: iload 4
    //   20: sipush 128
    //   23: irem
    //   24: putstatic 19	o/pF:ˏ	I
    //   27: iload 4
    //   29: iconst_2
    //   30: irem
    //   31: ifne +6 -> 37
    //   34: goto +493 -> 527
    //   37: goto +1510 -> 1547
    //   40: aload_3
    //   41: getfield 115	com/insidesecure/hce/internal/MatrixHCENativeBridge$SessionResponse:sessionType	Lcom/insidesecure/hce/internal/MatrixHCENativeBridge$NetworkSessionType;
    //   44: astore_2
    //   45: getstatic 120	com/insidesecure/hce/internal/MatrixHCENativeBridge$NetworkSessionType:MASTERCARD_PROVISION_SESSION	Lcom/insidesecure/hce/internal/MatrixHCENativeBridge$NetworkSessionType;
    //   48: astore 6
    //   50: aload_2
    //   51: aload 6
    //   53: if_acmpne +6 -> 59
    //   56: goto +91 -> 147
    //   59: goto +254 -> 313
    //   62: new 23	java/lang/StringBuilder
    //   65: dup
    //   66: invokespecial 26	java/lang/StringBuilder:<init>	()V
    //   69: sipush 794
    //   72: sipush 29186
    //   75: bipush 8
    //   77: invokestatic 30	o/pF:ˋ	(ICI)Ljava/lang/String;
    //   80: invokevirtual 36	java/lang/String:intern	()Ljava/lang/String;
    //   83: invokevirtual 40	java/lang/StringBuilder:append	(Ljava/lang/String;)Ljava/lang/StringBuilder;
    //   86: aload_3
    //   87: getfield 124	com/insidesecure/hce/internal/MatrixHCENativeBridge$SessionResponse:error	Lcom/insidesecure/hce/internal/account/mdes/SessionError;
    //   90: invokevirtual 127	com/insidesecure/hce/internal/account/mdes/SessionError:toString	()Ljava/lang/String;
    //   93: invokevirtual 40	java/lang/StringBuilder:append	(Ljava/lang/String;)Ljava/lang/StringBuilder;
    //   96: invokevirtual 48	java/lang/StringBuilder:toString	()Ljava/lang/String;
    //   99: astore_0
    //   100: goto +1261 -> 1361
    //   103: getstatic 50	o/pF:ˎ	Ljava/lang/String;
    //   106: sipush 1336
    //   109: sipush 1422
    //   112: bipush 50
    //   114: invokestatic 30	o/pF:ˋ	(ICI)Ljava/lang/String;
    //   117: invokevirtual 36	java/lang/String:intern	()Ljava/lang/String;
    //   120: invokestatic 101	o/pD:i	(Ljava/lang/String;Ljava/lang/String;)V
    //   123: goto +181 -> 304
    //   126: aload_3
    //   127: getfield 124	com/insidesecure/hce/internal/MatrixHCENativeBridge$SessionResponse:error	Lcom/insidesecure/hce/internal/account/mdes/SessionError;
    //   130: astore 7
    //   132: aload 7
    //   134: ifnull +6 -> 140
    //   137: goto +685 -> 822
    //   140: bipush 87
    //   142: istore 4
    //   144: goto +449 -> 593
    //   147: getstatic 50	o/pF:ˎ	Ljava/lang/String;
    //   150: sipush 972
    //   153: sipush 29661
    //   156: bipush 35
    //   158: invokestatic 30	o/pF:ˋ	(ICI)Ljava/lang/String;
    //   161: invokevirtual 36	java/lang/String:intern	()Ljava/lang/String;
    //   164: invokestatic 130	o/pD:d	(Ljava/lang/String;Ljava/lang/String;)V
    //   167: new 132	android/content/Intent
    //   170: dup
    //   171: sipush 1007
    //   174: ldc -123
    //   176: bipush 51
    //   178: invokestatic 30	o/pF:ˋ	(ICI)Ljava/lang/String;
    //   181: invokevirtual 36	java/lang/String:intern	()Ljava/lang/String;
    //   184: invokespecial 136	android/content/Intent:<init>	(Ljava/lang/String;)V
    //   187: astore_1
    //   188: aload_1
    //   189: sipush 1058
    //   192: ldc -119
    //   194: bipush 25
    //   196: invokestatic 30	o/pF:ˋ	(ICI)Ljava/lang/String;
    //   199: invokevirtual 36	java/lang/String:intern	()Ljava/lang/String;
    //   202: aload_3
    //   203: getfield 140	com/insidesecure/hce/internal/MatrixHCENativeBridge$SessionResponse:tokenUniqueReference	Ljava/lang/String;
    //   206: invokevirtual 144	android/content/Intent:putExtra	(Ljava/lang/String;Ljava/lang/String;)Landroid/content/Intent;
    //   209: pop
    //   210: aload_0
    //   211: aload_1
    //   212: invokestatic 148	o/pD:sendBroadcast	(Landroid/content/Context;Landroid/content/Intent;)V
    //   215: goto +56 -> 271
    //   218: goto +611 -> 829
    //   221: getstatic 50	o/pF:ˎ	Ljava/lang/String;
    //   224: sipush 1442
    //   227: iconst_0
    //   228: bipush 30
    //   230: invokestatic 30	o/pF:ˋ	(ICI)Ljava/lang/String;
    //   233: invokevirtual 36	java/lang/String:intern	()Ljava/lang/String;
    //   236: invokestatic 151	o/pD:w	(Ljava/lang/String;Ljava/lang/String;)V
    //   239: iconst_0
    //   240: ireturn
    //   241: getstatic 50	o/pF:ˎ	Ljava/lang/String;
    //   244: sipush 934
    //   247: iconst_0
    //   248: bipush 38
    //   250: invokestatic 30	o/pF:ˋ	(ICI)Ljava/lang/String;
    //   253: invokevirtual 36	java/lang/String:intern	()Ljava/lang/String;
    //   256: invokestatic 88	o/pD:e	(Ljava/lang/String;Ljava/lang/String;)V
    //   259: aload_1
    //   260: aload_2
    //   261: aconst_null
    //   262: invokestatic 154	o/pF:ˏ	(Lo/pz;Ljava/lang/String;Lorg/json/JSONObject;)V
    //   265: goto +6 -> 271
    //   268: goto +1015 -> 1283
    //   271: goto -53 -> 218
    //   274: getstatic 19	o/pF:ˏ	I
    //   277: bipush 87
    //   279: iadd
    //   280: istore 4
    //   282: iload 4
    //   284: sipush 128
    //   287: irem
    //   288: putstatic 17	o/pF:ॱ	I
    //   291: iload 4
    //   293: iconst_2
    //   294: irem
    //   295: ifeq +6 -> 301
    //   298: goto +9 -> 307
    //   301: goto +229 -> 530
    //   304: goto -83 -> 221
    //   307: aconst_null
    //   308: arraylength
    //   309: istore 4
    //   311: iconst_0
    //   312: ireturn
    //   313: aload_3
    //   314: getfield 115	com/insidesecure/hce/internal/MatrixHCENativeBridge$SessionResponse:sessionType	Lcom/insidesecure/hce/internal/MatrixHCENativeBridge$NetworkSessionType;
    //   317: astore_2
    //   318: getstatic 157	com/insidesecure/hce/internal/MatrixHCENativeBridge$NetworkSessionType:MASTERCARD_MOBILE_PIN_RESET	Lcom/insidesecure/hce/internal/MatrixHCENativeBridge$NetworkSessionType;
    //   321: astore 6
    //   323: aload_2
    //   324: aload 6
    //   326: if_acmpne +6 -> 332
    //   329: goto +1211 -> 1540
    //   332: goto -329 -> 3
    //   335: getstatic 50	o/pF:ˎ	Ljava/lang/String;
    //   338: astore_1
    //   339: new 23	java/lang/StringBuilder
    //   342: dup
    //   343: invokespecial 26	java/lang/StringBuilder:<init>	()V
    //   346: sipush 749
    //   349: iconst_0
    //   350: bipush 45
    //   352: invokestatic 30	o/pF:ˋ	(ICI)Ljava/lang/String;
    //   355: invokevirtual 36	java/lang/String:intern	()Ljava/lang/String;
    //   358: invokevirtual 40	java/lang/StringBuilder:append	(Ljava/lang/String;)Ljava/lang/StringBuilder;
    //   361: astore_2
    //   362: aload_3
    //   363: ifnonnull +6 -> 369
    //   366: goto +911 -> 1277
    //   369: goto -307 -> 62
    //   372: astore_0
    //   373: getstatic 50	o/pF:ˎ	Ljava/lang/String;
    //   376: sipush 1386
    //   379: sipush 30317
    //   382: bipush 56
    //   384: invokestatic 30	o/pF:ˋ	(ICI)Ljava/lang/String;
    //   387: invokevirtual 36	java/lang/String:intern	()Ljava/lang/String;
    //   390: invokestatic 101	o/pD:i	(Ljava/lang/String;Ljava/lang/String;)V
    //   393: goto -172 -> 221
    //   396: getstatic 50	o/pF:ˎ	Ljava/lang/String;
    //   399: sipush 586
    //   402: iconst_0
    //   403: bipush 55
    //   405: invokestatic 30	o/pF:ˋ	(ICI)Ljava/lang/String;
    //   408: invokevirtual 36	java/lang/String:intern	()Ljava/lang/String;
    //   411: invokestatic 101	o/pD:i	(Ljava/lang/String;Ljava/lang/String;)V
    //   414: aload_2
    //   415: aload_3
    //   416: invokestatic 163	com/insidesecure/hce/internal/MatrixHCENativeBridge:setNetworkSessionData	(Ljava/lang/String;Ljava/lang/String;)Lcom/insidesecure/hce/internal/MatrixHCENativeBridge$SessionResponse;
    //   419: astore_3
    //   420: aload_3
    //   421: ifnull +6 -> 427
    //   424: goto +1055 -> 1479
    //   427: goto +263 -> 690
    //   430: goto -420 -> 10
    //   433: getstatic 50	o/pF:ˎ	Ljava/lang/String;
    //   436: new 23	java/lang/StringBuilder
    //   439: dup
    //   440: invokespecial 26	java/lang/StringBuilder:<init>	()V
    //   443: sipush 1125
    //   446: iconst_0
    //   447: bipush 44
    //   449: invokestatic 30	o/pF:ˋ	(ICI)Ljava/lang/String;
    //   452: invokevirtual 36	java/lang/String:intern	()Ljava/lang/String;
    //   455: invokevirtual 40	java/lang/StringBuilder:append	(Ljava/lang/String;)Ljava/lang/StringBuilder;
    //   458: aload_2
    //   459: invokeinterface 168 1 0
    //   464: invokevirtual 40	java/lang/StringBuilder:append	(Ljava/lang/String;)Ljava/lang/StringBuilder;
    //   467: invokevirtual 48	java/lang/StringBuilder:toString	()Ljava/lang/String;
    //   470: invokestatic 101	o/pD:i	(Ljava/lang/String;Ljava/lang/String;)V
    //   473: new 132	android/content/Intent
    //   476: dup
    //   477: sipush 1169
    //   480: iconst_0
    //   481: bipush 51
    //   483: invokestatic 30	o/pF:ˋ	(ICI)Ljava/lang/String;
    //   486: invokevirtual 36	java/lang/String:intern	()Ljava/lang/String;
    //   489: invokespecial 136	android/content/Intent:<init>	(Ljava/lang/String;)V
    //   492: astore_1
    //   493: aload_1
    //   494: sipush 1220
    //   497: iconst_0
    //   498: bipush 13
    //   500: invokestatic 30	o/pF:ˋ	(ICI)Ljava/lang/String;
    //   503: invokevirtual 36	java/lang/String:intern	()Ljava/lang/String;
    //   506: aload_2
    //   507: invokeinterface 168 1 0
    //   512: invokevirtual 144	android/content/Intent:putExtra	(Ljava/lang/String;Ljava/lang/String;)Landroid/content/Intent;
    //   515: pop
    //   516: aload_0
    //   517: aload_1
    //   518: invokestatic 148	o/pD:sendBroadcast	(Landroid/content/Context;Landroid/content/Intent;)V
    //   521: goto -91 -> 430
    //   524: goto -253 -> 271
    //   527: goto +1020 -> 1547
    //   530: iconst_0
    //   531: ireturn
    //   532: iload 4
    //   534: lookupswitch	default:+26->560, 67:+792->1326, 76:+841->1375
    //   560: goto +766 -> 1326
    //   563: getstatic 19	o/pF:ˏ	I
    //   566: bipush 123
    //   568: iadd
    //   569: istore 4
    //   571: iload 4
    //   573: sipush 128
    //   576: irem
    //   577: putstatic 17	o/pF:ॱ	I
    //   580: iload 4
    //   582: iconst_2
    //   583: irem
    //   584: ifeq +6 -> 590
    //   587: goto -319 -> 268
    //   590: goto +693 -> 1283
    //   593: iload 4
    //   595: lookupswitch	default:+25->620, 10:+576->1171, 87:+-260->335
    //   620: goto +551 -> 1171
    //   623: aload 6
    //   625: invokeinterface 174 1 0
    //   630: checkcast 165	com/insidesecure/hce/MatrixHCECard
    //   633: astore_2
    //   634: aload_2
    //   635: invokeinterface 177 1 0
    //   640: aload_3
    //   641: getfield 140	com/insidesecure/hce/internal/MatrixHCENativeBridge$SessionResponse:tokenUniqueReference	Ljava/lang/String;
    //   644: invokevirtual 84	java/lang/String:equals	(Ljava/lang/Object;)Z
    //   647: istore 5
    //   649: iload 5
    //   651: ifeq +6 -> 657
    //   654: goto -221 -> 433
    //   657: goto -227 -> 430
    //   660: aload 6
    //   662: sipush 570
    //   665: iconst_0
    //   666: bipush 16
    //   668: invokestatic 30	o/pF:ˋ	(ICI)Ljava/lang/String;
    //   671: invokevirtual 36	java/lang/String:intern	()Ljava/lang/String;
    //   674: invokevirtual 183	org/json/JSONObject:isNull	(Ljava/lang/String;)Z
    //   677: istore 5
    //   679: iload 5
    //   681: ifne +6 -> 687
    //   684: goto -288 -> 396
    //   687: goto +636 -> 1323
    //   690: iconst_1
    //   691: istore 4
    //   693: goto +188 -> 881
    //   696: astore 6
    //   698: getstatic 50	o/pF:ˎ	Ljava/lang/String;
    //   701: sipush 264
    //   704: ldc -72
    //   706: bipush 63
    //   708: invokestatic 30	o/pF:ˋ	(ICI)Ljava/lang/String;
    //   711: invokevirtual 36	java/lang/String:intern	()Ljava/lang/String;
    //   714: invokestatic 101	o/pD:i	(Ljava/lang/String;Ljava/lang/String;)V
    //   717: new 179	org/json/JSONObject
    //   720: dup
    //   721: aload_3
    //   722: invokespecial 185	org/json/JSONObject:<init>	(Ljava/lang/String;)V
    //   725: sipush 176
    //   728: ldc -70
    //   730: bipush 7
    //   732: invokestatic 30	o/pF:ˋ	(ICI)Ljava/lang/String;
    //   735: invokevirtual 36	java/lang/String:intern	()Ljava/lang/String;
    //   738: invokevirtual 190	org/json/JSONObject:getJSONObject	(Ljava/lang/String;)Lorg/json/JSONObject;
    //   741: astore 7
    //   743: new 32	java/lang/String
    //   746: dup
    //   747: aload 7
    //   749: sipush 183
    //   752: iconst_0
    //   753: bipush 12
    //   755: invokestatic 30	o/pF:ˋ	(ICI)Ljava/lang/String;
    //   758: invokevirtual 36	java/lang/String:intern	()Ljava/lang/String;
    //   761: invokevirtual 194	org/json/JSONObject:getString	(Ljava/lang/String;)Ljava/lang/String;
    //   764: invokespecial 195	java/lang/String:<init>	(Ljava/lang/String;)V
    //   767: astore 6
    //   769: aload 7
    //   771: sipush 195
    //   774: ldc -60
    //   776: bipush 12
    //   778: invokestatic 30	o/pF:ˋ	(ICI)Ljava/lang/String;
    //   781: invokevirtual 36	java/lang/String:intern	()Ljava/lang/String;
    //   784: invokevirtual 194	org/json/JSONObject:getString	(Ljava/lang/String;)Ljava/lang/String;
    //   787: astore 7
    //   789: getstatic 50	o/pF:ˎ	Ljava/lang/String;
    //   792: sipush 327
    //   795: sipush 19826
    //   798: bipush 58
    //   800: invokestatic 30	o/pF:ˋ	(ICI)Ljava/lang/String;
    //   803: invokevirtual 36	java/lang/String:intern	()Ljava/lang/String;
    //   806: invokestatic 101	o/pD:i	(Ljava/lang/String;Ljava/lang/String;)V
    //   809: aload_1
    //   810: aload 6
    //   812: aload 7
    //   814: invokestatic 199	o/pF:ˏ	(Lo/pz;Ljava/lang/String;Ljava/lang/String;)Z
    //   817: istore 5
    //   819: iload 5
    //   821: ireturn
    //   822: bipush 10
    //   824: istore 4
    //   826: goto -233 -> 593
    //   829: iconst_1
    //   830: ireturn
    //   831: getstatic 50	o/pF:ˎ	Ljava/lang/String;
    //   834: sipush 802
    //   837: sipush 18868
    //   840: bipush 58
    //   842: invokestatic 30	o/pF:ˋ	(ICI)Ljava/lang/String;
    //   845: invokevirtual 36	java/lang/String:intern	()Ljava/lang/String;
    //   848: invokestatic 101	o/pD:i	(Ljava/lang/String;Ljava/lang/String;)V
    //   851: aload_2
    //   852: aload_3
    //   853: invokestatic 163	com/insidesecure/hce/internal/MatrixHCENativeBridge:setNetworkSessionData	(Ljava/lang/String;Ljava/lang/String;)Lcom/insidesecure/hce/internal/MatrixHCENativeBridge$SessionResponse;
    //   856: astore_3
    //   857: aload_3
    //   858: getfield 115	com/insidesecure/hce/internal/MatrixHCENativeBridge$SessionResponse:sessionType	Lcom/insidesecure/hce/internal/MatrixHCENativeBridge$NetworkSessionType;
    //   861: astore 7
    //   863: getstatic 202	com/insidesecure/hce/internal/MatrixHCENativeBridge$NetworkSessionType:MASTERCARD_SESSION	Lcom/insidesecure/hce/internal/MatrixHCENativeBridge$NetworkSessionType;
    //   866: astore 8
    //   868: aload 7
    //   870: aload 8
    //   872: if_acmpne +6 -> 878
    //   875: goto -312 -> 563
    //   878: goto -838 -> 40
    //   881: iload 4
    //   883: tableswitch	default:+21->904, 0:+-757->126, 1:+285->1168
    //   904: goto -778 -> 126
    //   907: getstatic 50	o/pF:ˎ	Ljava/lang/String;
    //   910: new 23	java/lang/StringBuilder
    //   913: dup
    //   914: invokespecial 26	java/lang/StringBuilder:<init>	()V
    //   917: bipush 84
    //   919: ldc -53
    //   921: bipush 21
    //   923: invokestatic 30	o/pF:ˋ	(ICI)Ljava/lang/String;
    //   926: invokevirtual 36	java/lang/String:intern	()Ljava/lang/String;
    //   929: invokevirtual 40	java/lang/StringBuilder:append	(Ljava/lang/String;)Ljava/lang/StringBuilder;
    //   932: aload_3
    //   933: invokevirtual 40	java/lang/StringBuilder:append	(Ljava/lang/String;)Ljava/lang/StringBuilder;
    //   936: bipush 105
    //   938: iconst_0
    //   939: bipush 13
    //   941: invokestatic 30	o/pF:ˋ	(ICI)Ljava/lang/String;
    //   944: invokevirtual 36	java/lang/String:intern	()Ljava/lang/String;
    //   947: invokevirtual 40	java/lang/StringBuilder:append	(Ljava/lang/String;)Ljava/lang/StringBuilder;
    //   950: aload_2
    //   951: invokevirtual 40	java/lang/StringBuilder:append	(Ljava/lang/String;)Ljava/lang/StringBuilder;
    //   954: invokevirtual 48	java/lang/StringBuilder:toString	()Ljava/lang/String;
    //   957: invokestatic 101	o/pD:i	(Ljava/lang/String;Ljava/lang/String;)V
    //   960: getstatic 50	o/pF:ˎ	Ljava/lang/String;
    //   963: bipush 118
    //   965: iconst_0
    //   966: bipush 58
    //   968: invokestatic 30	o/pF:ˋ	(ICI)Ljava/lang/String;
    //   971: invokevirtual 36	java/lang/String:intern	()Ljava/lang/String;
    //   974: invokestatic 101	o/pD:i	(Ljava/lang/String;Ljava/lang/String;)V
    //   977: new 179	org/json/JSONObject
    //   980: dup
    //   981: aload_3
    //   982: invokespecial 185	org/json/JSONObject:<init>	(Ljava/lang/String;)V
    //   985: sipush 176
    //   988: ldc -70
    //   990: bipush 7
    //   992: invokestatic 30	o/pF:ˋ	(ICI)Ljava/lang/String;
    //   995: invokevirtual 36	java/lang/String:intern	()Ljava/lang/String;
    //   998: invokevirtual 190	org/json/JSONObject:getJSONObject	(Ljava/lang/String;)Lorg/json/JSONObject;
    //   1001: astore 7
    //   1003: new 32	java/lang/String
    //   1006: dup
    //   1007: aload 7
    //   1009: sipush 183
    //   1012: iconst_0
    //   1013: bipush 12
    //   1015: invokestatic 30	o/pF:ˋ	(ICI)Ljava/lang/String;
    //   1018: invokevirtual 36	java/lang/String:intern	()Ljava/lang/String;
    //   1021: invokevirtual 194	org/json/JSONObject:getString	(Ljava/lang/String;)Ljava/lang/String;
    //   1024: invokespecial 195	java/lang/String:<init>	(Ljava/lang/String;)V
    //   1027: astore 6
    //   1029: aload 7
    //   1031: sipush 195
    //   1034: ldc -60
    //   1036: bipush 12
    //   1038: invokestatic 30	o/pF:ˋ	(ICI)Ljava/lang/String;
    //   1041: invokevirtual 36	java/lang/String:intern	()Ljava/lang/String;
    //   1044: invokevirtual 190	org/json/JSONObject:getJSONObject	(Ljava/lang/String;)Lorg/json/JSONObject;
    //   1047: astore 7
    //   1049: getstatic 50	o/pF:ˎ	Ljava/lang/String;
    //   1052: sipush 207
    //   1055: iconst_0
    //   1056: bipush 57
    //   1058: invokestatic 30	o/pF:ˋ	(ICI)Ljava/lang/String;
    //   1061: invokevirtual 36	java/lang/String:intern	()Ljava/lang/String;
    //   1064: invokestatic 101	o/pD:i	(Ljava/lang/String;Ljava/lang/String;)V
    //   1067: aload_1
    //   1068: aload 6
    //   1070: aload 7
    //   1072: invokestatic 206	o/pF:ˊ	(Lo/pz;Ljava/lang/String;Lorg/json/JSONObject;)Z
    //   1075: istore 5
    //   1077: iload 5
    //   1079: ireturn
    //   1080: aload 6
    //   1082: sipush 570
    //   1085: iconst_0
    //   1086: bipush 16
    //   1088: invokestatic 30	o/pF:ˋ	(ICI)Ljava/lang/String;
    //   1091: invokevirtual 36	java/lang/String:intern	()Ljava/lang/String;
    //   1094: invokevirtual 210	org/json/JSONObject:remove	(Ljava/lang/String;)Ljava/lang/Object;
    //   1097: pop
    //   1098: aload_1
    //   1099: aload_2
    //   1100: aload 6
    //   1102: invokevirtual 213	o/pz:ˋ	(Ljava/lang/String;Lorg/json/JSONObject;)V
    //   1105: getstatic 50	o/pF:ˎ	Ljava/lang/String;
    //   1108: sipush 641
    //   1111: ldc -42
    //   1113: bipush 40
    //   1115: invokestatic 30	o/pF:ˋ	(ICI)Ljava/lang/String;
    //   1118: invokevirtual 36	java/lang/String:intern	()Ljava/lang/String;
    //   1121: invokestatic 101	o/pD:i	(Ljava/lang/String;Ljava/lang/String;)V
    //   1124: new 132	android/content/Intent
    //   1127: dup
    //   1128: sipush 681
    //   1131: iconst_0
    //   1132: bipush 52
    //   1134: invokestatic 30	o/pF:ˋ	(ICI)Ljava/lang/String;
    //   1137: invokevirtual 36	java/lang/String:intern	()Ljava/lang/String;
    //   1140: invokespecial 136	android/content/Intent:<init>	(Ljava/lang/String;)V
    //   1143: astore_1
    //   1144: aload_1
    //   1145: sipush 733
    //   1148: ldc -41
    //   1150: bipush 16
    //   1152: invokestatic 30	o/pF:ˋ	(ICI)Ljava/lang/String;
    //   1155: invokevirtual 36	java/lang/String:intern	()Ljava/lang/String;
    //   1158: aload_2
    //   1159: invokevirtual 144	android/content/Intent:putExtra	(Ljava/lang/String;Ljava/lang/String;)Landroid/content/Intent;
    //   1162: pop
    //   1163: aload_0
    //   1164: aload_1
    //   1165: invokestatic 148	o/pD:sendBroadcast	(Landroid/content/Context;Landroid/content/Intent;)V
    //   1168: goto -950 -> 218
    //   1171: aload_3
    //   1172: getfield 124	com/insidesecure/hce/internal/MatrixHCENativeBridge$SessionResponse:error	Lcom/insidesecure/hce/internal/account/mdes/SessionError;
    //   1175: astore 7
    //   1177: getstatic 218	com/insidesecure/hce/internal/account/mdes/SessionError:SUCCESS	Lcom/insidesecure/hce/internal/account/mdes/SessionError;
    //   1180: astore 8
    //   1182: aload 7
    //   1184: aload 8
    //   1186: if_acmpne +6 -> 1192
    //   1189: goto -109 -> 1080
    //   1192: goto -857 -> 335
    //   1195: astore 6
    //   1197: getstatic 50	o/pF:ˎ	Ljava/lang/String;
    //   1200: sipush 385
    //   1203: iconst_0
    //   1204: bipush 64
    //   1206: invokestatic 30	o/pF:ˋ	(ICI)Ljava/lang/String;
    //   1209: invokevirtual 36	java/lang/String:intern	()Ljava/lang/String;
    //   1212: invokestatic 101	o/pD:i	(Ljava/lang/String;Ljava/lang/String;)V
    //   1215: getstatic 50	o/pF:ˎ	Ljava/lang/String;
    //   1218: sipush 449
    //   1221: ldc -37
    //   1223: bipush 55
    //   1225: invokestatic 30	o/pF:ˋ	(ICI)Ljava/lang/String;
    //   1228: invokevirtual 36	java/lang/String:intern	()Ljava/lang/String;
    //   1231: invokestatic 101	o/pD:i	(Ljava/lang/String;Ljava/lang/String;)V
    //   1234: new 179	org/json/JSONObject
    //   1237: dup
    //   1238: aload_3
    //   1239: invokespecial 185	org/json/JSONObject:<init>	(Ljava/lang/String;)V
    //   1242: astore 6
    //   1244: aload 6
    //   1246: sipush 504
    //   1249: iconst_0
    //   1250: bipush 14
    //   1252: invokestatic 30	o/pF:ˋ	(ICI)Ljava/lang/String;
    //   1255: invokevirtual 36	java/lang/String:intern	()Ljava/lang/String;
    //   1258: invokevirtual 222	org/json/JSONObject:has	(Ljava/lang/String;)Z
    //   1261: istore 5
    //   1263: iload 5
    //   1265: ifeq +6 -> 1271
    //   1268: goto +217 -> 1485
    //   1271: goto -1168 -> 103
    //   1274: goto -367 -> 907
    //   1277: ldc -32
    //   1279: astore_0
    //   1280: goto +81 -> 1361
    //   1283: getstatic 50	o/pF:ˎ	Ljava/lang/String;
    //   1286: sipush 860
    //   1289: sipush 5721
    //   1292: bipush 33
    //   1294: invokestatic 30	o/pF:ˋ	(ICI)Ljava/lang/String;
    //   1297: invokevirtual 36	java/lang/String:intern	()Ljava/lang/String;
    //   1300: invokestatic 130	o/pD:d	(Ljava/lang/String;Ljava/lang/String;)V
    //   1303: aload_3
    //   1304: getfield 124	com/insidesecure/hce/internal/MatrixHCENativeBridge$SessionResponse:error	Lcom/insidesecure/hce/internal/account/mdes/SessionError;
    //   1307: astore_0
    //   1308: getstatic 218	com/insidesecure/hce/internal/account/mdes/SessionError:SUCCESS	Lcom/insidesecure/hce/internal/account/mdes/SessionError;
    //   1311: astore_3
    //   1312: aload_0
    //   1313: aload_3
    //   1314: if_acmpne +6 -> 1320
    //   1317: goto +108 -> 1425
    //   1320: goto +213 -> 1533
    //   1323: goto -492 -> 831
    //   1326: getstatic 50	o/pF:ˎ	Ljava/lang/String;
    //   1329: sipush 1083
    //   1332: sipush 6828
    //   1335: bipush 42
    //   1337: invokestatic 30	o/pF:ˋ	(ICI)Ljava/lang/String;
    //   1340: invokevirtual 36	java/lang/String:intern	()Ljava/lang/String;
    //   1343: invokestatic 130	o/pD:d	(Ljava/lang/String;Ljava/lang/String;)V
    //   1346: aload_1
    //   1347: aconst_null
    //   1348: invokevirtual 228	o/pz:getCards	(Ljava/lang/String;)Ljava/util/List;
    //   1351: invokeinterface 232 1 0
    //   1356: astore 6
    //   1358: goto +101 -> 1459
    //   1361: aload_1
    //   1362: aload_2
    //   1363: aload_0
    //   1364: invokevirtual 40	java/lang/StringBuilder:append	(Ljava/lang/String;)Ljava/lang/StringBuilder;
    //   1367: invokevirtual 48	java/lang/StringBuilder:toString	()Ljava/lang/String;
    //   1370: invokestatic 101	o/pD:i	(Ljava/lang/String;Ljava/lang/String;)V
    //   1373: iconst_0
    //   1374: ireturn
    //   1375: getstatic 50	o/pF:ˎ	Ljava/lang/String;
    //   1378: sipush 1233
    //   1381: iconst_0
    //   1382: bipush 41
    //   1384: invokestatic 30	o/pF:ˋ	(ICI)Ljava/lang/String;
    //   1387: invokevirtual 36	java/lang/String:intern	()Ljava/lang/String;
    //   1390: invokestatic 151	o/pD:w	(Ljava/lang/String;Ljava/lang/String;)V
    //   1393: goto -1119 -> 274
    //   1396: getstatic 50	o/pF:ˎ	Ljava/lang/String;
    //   1399: sipush 893
    //   1402: ldc -23
    //   1404: bipush 41
    //   1406: invokestatic 30	o/pF:ˋ	(ICI)Ljava/lang/String;
    //   1409: invokevirtual 36	java/lang/String:intern	()Ljava/lang/String;
    //   1412: invokestatic 88	o/pD:e	(Ljava/lang/String;Ljava/lang/String;)V
    //   1415: aload_1
    //   1416: aload_2
    //   1417: aload 6
    //   1419: invokestatic 154	o/pF:ˏ	(Lo/pz;Ljava/lang/String;Lorg/json/JSONObject;)V
    //   1422: goto -1151 -> 271
    //   1425: bipush 30
    //   1427: istore 4
    //   1429: iload 4
    //   1431: lookupswitch	default:+25->1456, 28:+-1190->241, 30:+-35->1396
    //   1456: goto -1215 -> 241
    //   1459: aload 6
    //   1461: invokeinterface 237 1 0
    //   1466: istore 5
    //   1468: iload 5
    //   1470: ifeq +6 -> 1476
    //   1473: goto -850 -> 623
    //   1476: goto -952 -> 524
    //   1479: iconst_0
    //   1480: istore 4
    //   1482: goto -601 -> 881
    //   1485: getstatic 50	o/pF:ˎ	Ljava/lang/String;
    //   1488: sipush 518
    //   1491: iconst_0
    //   1492: bipush 52
    //   1494: invokestatic 30	o/pF:ˋ	(ICI)Ljava/lang/String;
    //   1497: invokevirtual 36	java/lang/String:intern	()Ljava/lang/String;
    //   1500: invokestatic 101	o/pD:i	(Ljava/lang/String;Ljava/lang/String;)V
    //   1503: aload 6
    //   1505: sipush 570
    //   1508: iconst_0
    //   1509: bipush 16
    //   1511: invokestatic 30	o/pF:ˋ	(ICI)Ljava/lang/String;
    //   1514: invokevirtual 36	java/lang/String:intern	()Ljava/lang/String;
    //   1517: invokevirtual 222	org/json/JSONObject:has	(Ljava/lang/String;)Z
    //   1520: istore 5
    //   1522: iload 5
    //   1524: ifeq +6 -> 1530
    //   1527: goto -867 -> 660
    //   1530: goto -207 -> 1323
    //   1533: bipush 28
    //   1535: istore 4
    //   1537: goto -108 -> 1429
    //   1540: bipush 67
    //   1542: istore 4
    //   1544: goto -1012 -> 532
    //   1547: goto -88 -> 1459
    // Local variable table:
    //   start	length	slot	name	signature
    //   0	1550	0	paramContext	android.content.Context
    //   0	1550	1	paramPz	pz
    //   0	1550	2	paramString1	String
    //   0	1550	3	paramString2	String
    //   5	1538	4	i	int
    //   647	876	5	bool	boolean
    //   48	613	6	localNetworkSessionType	com.insidesecure.hce.internal.MatrixHCENativeBridge.NetworkSessionType
    //   696	1	6	localJSONException1	org.json.JSONException
    //   767	334	6	str	String
    //   1195	1	6	localJSONException2	org.json.JSONException
    //   1242	262	6	localObject1	Object
    //   130	1053	7	localObject2	Object
    //   866	319	8	localObject3	Object
    // Exception table:
    //   from	to	target	type
    //   40	50	372	org/json/JSONException
    //   62	100	372	org/json/JSONException
    //   103	123	372	org/json/JSONException
    //   126	132	372	org/json/JSONException
    //   147	215	372	org/json/JSONException
    //   241	265	372	org/json/JSONException
    //   313	323	372	org/json/JSONException
    //   335	362	372	org/json/JSONException
    //   396	420	372	org/json/JSONException
    //   433	521	372	org/json/JSONException
    //   623	649	372	org/json/JSONException
    //   660	679	372	org/json/JSONException
    //   831	868	372	org/json/JSONException
    //   1080	1168	372	org/json/JSONException
    //   1171	1182	372	org/json/JSONException
    //   1234	1263	372	org/json/JSONException
    //   1283	1312	372	org/json/JSONException
    //   1326	1358	372	org/json/JSONException
    //   1361	1373	372	org/json/JSONException
    //   1375	1393	372	org/json/JSONException
    //   1396	1422	372	org/json/JSONException
    //   1459	1468	372	org/json/JSONException
    //   1485	1522	372	org/json/JSONException
    //   977	1077	696	org/json/JSONException
    //   717	819	1195	org/json/JSONException
  }
  
  /* Error */
  private static boolean ˊ(pz paramPz, String paramString, org.json.JSONObject paramJSONObject)
  {
    // Byte code:
    //   0: goto +1496 -> 1496
    //   3: aload 11
    //   5: instanceof 32
    //   8: istore 4
    //   10: new 239	java/lang/NullPointerException
    //   13: dup
    //   14: invokespecial 240	java/lang/NullPointerException:<init>	()V
    //   17: athrow
    //   18: iconst_0
    //   19: istore_3
    //   20: goto +724 -> 744
    //   23: goto +1602 -> 1625
    //   26: goto +1332 -> 1358
    //   29: astore_0
    //   30: aload_0
    //   31: athrow
    //   32: getstatic 50	o/pF:ˎ	Ljava/lang/String;
    //   35: sipush 2478
    //   38: sipush 28299
    //   41: bipush 75
    //   43: invokestatic 30	o/pF:ˋ	(ICI)Ljava/lang/String;
    //   46: invokevirtual 36	java/lang/String:intern	()Ljava/lang/String;
    //   49: invokestatic 88	o/pD:e	(Ljava/lang/String;Ljava/lang/String;)V
    //   52: iconst_0
    //   53: ireturn
    //   54: aconst_null
    //   55: astore 5
    //   57: aconst_null
    //   58: astore 6
    //   60: aconst_null
    //   61: astore 7
    //   63: aconst_null
    //   64: astore 8
    //   66: aload_0
    //   67: invokevirtual 242	o/pz:ˏ	()Landroid/content/Context;
    //   70: astore 10
    //   72: new 32	java/lang/String
    //   75: dup
    //   76: aload_2
    //   77: sipush 2336
    //   80: sipush 30842
    //   83: bipush 19
    //   85: invokestatic 30	o/pF:ˋ	(ICI)Ljava/lang/String;
    //   88: invokevirtual 36	java/lang/String:intern	()Ljava/lang/String;
    //   91: invokevirtual 194	org/json/JSONObject:getString	(Ljava/lang/String;)Ljava/lang/String;
    //   94: invokespecial 195	java/lang/String:<init>	(Ljava/lang/String;)V
    //   97: astore 9
    //   99: aload 9
    //   101: astore 5
    //   103: goto +1341 -> 1444
    //   106: getstatic 50	o/pF:ˎ	Ljava/lang/String;
    //   109: new 23	java/lang/StringBuilder
    //   112: dup
    //   113: invokespecial 26	java/lang/StringBuilder:<init>	()V
    //   116: sipush 3106
    //   119: iconst_0
    //   120: bipush 21
    //   122: invokestatic 30	o/pF:ˋ	(ICI)Ljava/lang/String;
    //   125: invokevirtual 36	java/lang/String:intern	()Ljava/lang/String;
    //   128: invokevirtual 40	java/lang/StringBuilder:append	(Ljava/lang/String;)Ljava/lang/StringBuilder;
    //   131: aload_1
    //   132: invokevirtual 40	java/lang/StringBuilder:append	(Ljava/lang/String;)Ljava/lang/StringBuilder;
    //   135: sipush 3127
    //   138: ldc -13
    //   140: iconst_1
    //   141: invokestatic 30	o/pF:ˋ	(ICI)Ljava/lang/String;
    //   144: invokevirtual 36	java/lang/String:intern	()Ljava/lang/String;
    //   147: invokevirtual 40	java/lang/StringBuilder:append	(Ljava/lang/String;)Ljava/lang/StringBuilder;
    //   150: invokevirtual 48	java/lang/StringBuilder:toString	()Ljava/lang/String;
    //   153: invokestatic 88	o/pD:e	(Ljava/lang/String;Ljava/lang/String;)V
    //   156: iconst_0
    //   157: ireturn
    //   158: bipush 17
    //   160: istore_3
    //   161: goto +653 -> 814
    //   164: iconst_0
    //   165: istore_3
    //   166: goto +966 -> 1132
    //   169: iconst_1
    //   170: istore_3
    //   171: goto +573 -> 744
    //   174: aload 5
    //   176: ifnull +6 -> 182
    //   179: goto +1524 -> 1703
    //   182: goto +9 -> 191
    //   185: bipush 29
    //   187: istore_3
    //   188: goto +626 -> 814
    //   191: goto +1431 -> 1622
    //   194: getstatic 50	o/pF:ˎ	Ljava/lang/String;
    //   197: astore_0
    //   198: sipush 2855
    //   201: sipush 31904
    //   204: bipush 53
    //   206: invokestatic 30	o/pF:ˋ	(ICI)Ljava/lang/String;
    //   209: astore_1
    //   210: aload_1
    //   211: invokevirtual 36	java/lang/String:intern	()Ljava/lang/String;
    //   214: astore_1
    //   215: aload_0
    //   216: aload_1
    //   217: invokestatic 101	o/pD:i	(Ljava/lang/String;Ljava/lang/String;)V
    //   220: goto +1518 -> 1738
    //   223: getstatic 50	o/pF:ˎ	Ljava/lang/String;
    //   226: new 23	java/lang/StringBuilder
    //   229: dup
    //   230: invokespecial 26	java/lang/StringBuilder:<init>	()V
    //   233: sipush 2553
    //   236: iconst_0
    //   237: bipush 42
    //   239: invokestatic 30	o/pF:ˋ	(ICI)Ljava/lang/String;
    //   242: invokevirtual 36	java/lang/String:intern	()Ljava/lang/String;
    //   245: invokevirtual 40	java/lang/StringBuilder:append	(Ljava/lang/String;)Ljava/lang/StringBuilder;
    //   248: aload 5
    //   250: invokevirtual 40	java/lang/StringBuilder:append	(Ljava/lang/String;)Ljava/lang/StringBuilder;
    //   253: invokevirtual 48	java/lang/StringBuilder:toString	()Ljava/lang/String;
    //   256: invokestatic 101	o/pD:i	(Ljava/lang/String;Ljava/lang/String;)V
    //   259: aload_0
    //   260: aconst_null
    //   261: invokevirtual 228	o/pz:getCards	(Ljava/lang/String;)Ljava/util/List;
    //   264: invokeinterface 232 1 0
    //   269: astore 7
    //   271: goto +1448 -> 1719
    //   274: getstatic 19	o/pF:ˏ	I
    //   277: bipush 107
    //   279: iadd
    //   280: istore_3
    //   281: iload_3
    //   282: sipush 128
    //   285: irem
    //   286: putstatic 17	o/pF:ॱ	I
    //   289: iload_3
    //   290: iconst_2
    //   291: irem
    //   292: ifeq +6 -> 298
    //   295: goto +931 -> 1226
    //   298: goto +1077 -> 1375
    //   301: aload 5
    //   303: ifnull +6 -> 309
    //   306: goto -83 -> 223
    //   309: goto +34 -> 343
    //   312: iload_3
    //   313: lookupswitch	default:+27->340, 49:+-310->3, 90:+986->1299
    //   340: goto -337 -> 3
    //   343: getstatic 50	o/pF:ˎ	Ljava/lang/String;
    //   346: new 23	java/lang/StringBuilder
    //   349: dup
    //   350: invokespecial 26	java/lang/StringBuilder:<init>	()V
    //   353: sipush 2656
    //   356: iconst_0
    //   357: bipush 39
    //   359: invokestatic 30	o/pF:ˋ	(ICI)Ljava/lang/String;
    //   362: invokevirtual 36	java/lang/String:intern	()Ljava/lang/String;
    //   365: invokevirtual 40	java/lang/StringBuilder:append	(Ljava/lang/String;)Ljava/lang/StringBuilder;
    //   368: aload 6
    //   370: invokevirtual 40	java/lang/StringBuilder:append	(Ljava/lang/String;)Ljava/lang/StringBuilder;
    //   373: invokevirtual 48	java/lang/StringBuilder:toString	()Ljava/lang/String;
    //   376: invokestatic 101	o/pD:i	(Ljava/lang/String;Ljava/lang/String;)V
    //   379: aload_0
    //   380: aconst_null
    //   381: invokevirtual 228	o/pz:getCards	(Ljava/lang/String;)Ljava/util/List;
    //   384: invokeinterface 232 1 0
    //   389: astore 9
    //   391: goto +11 -> 402
    //   394: iconst_1
    //   395: istore_3
    //   396: goto +736 -> 1132
    //   399: goto +1339 -> 1738
    //   402: aload 9
    //   404: invokeinterface 237 1 0
    //   409: ifeq +6 -> 415
    //   412: goto -254 -> 158
    //   415: goto -230 -> 185
    //   418: iload_3
    //   419: tableswitch	default:+21->440, 0:+-228->191, 1:+205->624
    //   440: goto +184 -> 624
    //   443: getstatic 50	o/pF:ˎ	Ljava/lang/String;
    //   446: new 23	java/lang/StringBuilder
    //   449: dup
    //   450: invokespecial 26	java/lang/StringBuilder:<init>	()V
    //   453: sipush 2711
    //   456: ldc -12
    //   458: bipush 39
    //   460: invokestatic 30	o/pF:ˋ	(ICI)Ljava/lang/String;
    //   463: invokevirtual 36	java/lang/String:intern	()Ljava/lang/String;
    //   466: invokevirtual 40	java/lang/StringBuilder:append	(Ljava/lang/String;)Ljava/lang/StringBuilder;
    //   469: aload 5
    //   471: invokeinterface 168 1 0
    //   476: invokevirtual 40	java/lang/StringBuilder:append	(Ljava/lang/String;)Ljava/lang/StringBuilder;
    //   479: invokevirtual 48	java/lang/StringBuilder:toString	()Ljava/lang/String;
    //   482: invokestatic 101	o/pD:i	(Ljava/lang/String;Ljava/lang/String;)V
    //   485: aload_1
    //   486: sipush 2750
    //   489: ldc -11
    //   491: bipush 20
    //   493: invokestatic 30	o/pF:ˋ	(ICI)Ljava/lang/String;
    //   496: invokevirtual 36	java/lang/String:intern	()Ljava/lang/String;
    //   499: invokevirtual 84	java/lang/String:equals	(Ljava/lang/Object;)Z
    //   502: ifeq +6 -> 508
    //   505: goto +6 -> 511
    //   508: goto +1165 -> 1673
    //   511: getstatic 50	o/pF:ˎ	Ljava/lang/String;
    //   514: sipush 2770
    //   517: iconst_0
    //   518: bipush 23
    //   520: invokestatic 30	o/pF:ˋ	(ICI)Ljava/lang/String;
    //   523: invokevirtual 36	java/lang/String:intern	()Ljava/lang/String;
    //   526: invokestatic 101	o/pD:i	(Ljava/lang/String;Ljava/lang/String;)V
    //   529: new 132	android/content/Intent
    //   532: dup
    //   533: sipush 2793
    //   536: iconst_0
    //   537: bipush 49
    //   539: invokestatic 30	o/pF:ˋ	(ICI)Ljava/lang/String;
    //   542: invokevirtual 36	java/lang/String:intern	()Ljava/lang/String;
    //   545: invokespecial 136	android/content/Intent:<init>	(Ljava/lang/String;)V
    //   548: astore_1
    //   549: aload_1
    //   550: sipush 733
    //   553: ldc -41
    //   555: bipush 16
    //   557: invokestatic 30	o/pF:ˋ	(ICI)Ljava/lang/String;
    //   560: invokevirtual 36	java/lang/String:intern	()Ljava/lang/String;
    //   563: aload 5
    //   565: invokeinterface 246 1 0
    //   570: invokevirtual 144	android/content/Intent:putExtra	(Ljava/lang/String;Ljava/lang/String;)Landroid/content/Intent;
    //   573: pop
    //   574: aload_1
    //   575: sipush 1220
    //   578: iconst_0
    //   579: bipush 13
    //   581: invokestatic 30	o/pF:ˋ	(ICI)Ljava/lang/String;
    //   584: invokevirtual 36	java/lang/String:intern	()Ljava/lang/String;
    //   587: aload 5
    //   589: invokeinterface 168 1 0
    //   594: invokevirtual 144	android/content/Intent:putExtra	(Ljava/lang/String;Ljava/lang/String;)Landroid/content/Intent;
    //   597: pop
    //   598: aload 10
    //   600: aload_1
    //   601: invokestatic 148	o/pD:sendBroadcast	(Landroid/content/Context;Landroid/content/Intent;)V
    //   604: aload_0
    //   605: aload 5
    //   607: invokeinterface 246 1 0
    //   612: invokevirtual 248	o/pz:ˋ	(Ljava/lang/String;)V
    //   615: goto +757 -> 1372
    //   618: goto +1042 -> 1660
    //   621: goto +783 -> 1404
    //   624: getstatic 19	o/pF:ˏ	I
    //   627: bipush 69
    //   629: iadd
    //   630: istore_3
    //   631: iload_3
    //   632: sipush 128
    //   635: irem
    //   636: putstatic 17	o/pF:ॱ	I
    //   639: iload_3
    //   640: iconst_2
    //   641: irem
    //   642: ifeq +6 -> 648
    //   645: goto +324 -> 969
    //   648: goto -30 -> 618
    //   651: iconst_1
    //   652: istore_3
    //   653: goto -235 -> 418
    //   656: aload 8
    //   658: astore 5
    //   660: iload_3
    //   661: lookupswitch	default:+27->688, 32:+907->1568, 84:+-487->174
    //   688: aload 8
    //   690: astore 5
    //   692: goto -518 -> 174
    //   695: iload_3
    //   696: tableswitch	default:+24->720, 0:+-422->274, 1:+-395->301
    //   720: goto -446 -> 274
    //   723: getstatic 50	o/pF:ˎ	Ljava/lang/String;
    //   726: sipush 2614
    //   729: ldc -7
    //   731: bipush 42
    //   733: invokestatic 30	o/pF:ˋ	(ICI)Ljava/lang/String;
    //   736: invokevirtual 36	java/lang/String:intern	()Ljava/lang/String;
    //   739: invokestatic 151	o/pD:w	(Ljava/lang/String;Ljava/lang/String;)V
    //   742: iconst_0
    //   743: ireturn
    //   744: aload_2
    //   745: astore 5
    //   747: iload_3
    //   748: tableswitch	default:+24->772, 0:+-305->443, 1:+778->1526
    //   772: aload_2
    //   773: astore 5
    //   775: goto -332 -> 443
    //   778: bipush 49
    //   780: istore_3
    //   781: goto -469 -> 312
    //   784: iconst_0
    //   785: istore_3
    //   786: goto -91 -> 695
    //   789: iconst_0
    //   790: istore_3
    //   791: goto -373 -> 418
    //   794: bipush 90
    //   796: istore_3
    //   797: goto -485 -> 312
    //   800: aconst_null
    //   801: arraylength
    //   802: istore_3
    //   803: aload 6
    //   805: ifnonnull +6 -> 811
    //   808: goto -414 -> 394
    //   811: goto -647 -> 164
    //   814: aload 7
    //   816: astore_2
    //   817: iload_3
    //   818: lookupswitch	default:+26->844, 17:+495->1313, 29:+842->1660
    //   844: goto +469 -> 1313
    //   847: getstatic 50	o/pF:ˎ	Ljava/lang/String;
    //   850: sipush 1928
    //   853: iconst_0
    //   854: bipush 40
    //   856: invokestatic 30	o/pF:ˋ	(ICI)Ljava/lang/String;
    //   859: invokevirtual 36	java/lang/String:intern	()Ljava/lang/String;
    //   862: invokestatic 101	o/pD:i	(Ljava/lang/String;Ljava/lang/String;)V
    //   865: new 132	android/content/Intent
    //   868: dup
    //   869: sipush 1968
    //   872: iconst_0
    //   873: bipush 53
    //   875: invokestatic 30	o/pF:ˋ	(ICI)Ljava/lang/String;
    //   878: invokevirtual 36	java/lang/String:intern	()Ljava/lang/String;
    //   881: invokespecial 136	android/content/Intent:<init>	(Ljava/lang/String;)V
    //   884: astore_0
    //   885: aload_0
    //   886: sipush 1220
    //   889: iconst_0
    //   890: bipush 13
    //   892: invokestatic 30	o/pF:ˋ	(ICI)Ljava/lang/String;
    //   895: invokevirtual 36	java/lang/String:intern	()Ljava/lang/String;
    //   898: aload 5
    //   900: invokeinterface 168 1 0
    //   905: invokevirtual 144	android/content/Intent:putExtra	(Ljava/lang/String;Ljava/lang/String;)Landroid/content/Intent;
    //   908: pop
    //   909: aload 10
    //   911: aload_0
    //   912: invokestatic 148	o/pD:sendBroadcast	(Landroid/content/Context;Landroid/content/Intent;)V
    //   915: goto -516 -> 399
    //   918: getstatic 19	o/pF:ˏ	I
    //   921: bipush 79
    //   923: iadd
    //   924: istore_3
    //   925: iload_3
    //   926: sipush 128
    //   929: irem
    //   930: putstatic 17	o/pF:ॱ	I
    //   933: iload_3
    //   934: iconst_2
    //   935: irem
    //   936: ifeq +6 -> 942
    //   939: goto -913 -> 26
    //   942: goto +416 -> 1358
    //   945: getstatic 50	o/pF:ˎ	Ljava/lang/String;
    //   948: sipush 2614
    //   951: ldc -7
    //   953: bipush 42
    //   955: invokestatic 30	o/pF:ˋ	(ICI)Ljava/lang/String;
    //   958: invokevirtual 36	java/lang/String:intern	()Ljava/lang/String;
    //   961: invokestatic 151	o/pD:w	(Ljava/lang/String;Ljava/lang/String;)V
    //   964: iconst_0
    //   965: ireturn
    //   966: astore_0
    //   967: aload_0
    //   968: athrow
    //   969: new 239	java/lang/NullPointerException
    //   972: dup
    //   973: invokespecial 240	java/lang/NullPointerException:<init>	()V
    //   976: athrow
    //   977: goto -32 -> 945
    //   980: aload 6
    //   982: ifnonnull +6 -> 988
    //   985: goto -953 -> 32
    //   988: goto -687 -> 301
    //   991: aload 8
    //   993: astore 5
    //   995: iload_3
    //   996: tableswitch	default:+24->1020, 0:+557->1553, 1:+-822->174
    //   1020: goto +533 -> 1553
    //   1023: bipush 84
    //   1025: istore_3
    //   1026: goto -370 -> 656
    //   1029: getstatic 50	o/pF:ˎ	Ljava/lang/String;
    //   1032: sipush 3040
    //   1035: ldc -6
    //   1037: bipush 46
    //   1039: invokestatic 30	o/pF:ˋ	(ICI)Ljava/lang/String;
    //   1042: invokevirtual 36	java/lang/String:intern	()Ljava/lang/String;
    //   1045: invokestatic 101	o/pD:i	(Ljava/lang/String;Ljava/lang/String;)V
    //   1048: new 132	android/content/Intent
    //   1051: dup
    //   1052: sipush 2249
    //   1055: sipush 15434
    //   1058: bipush 53
    //   1060: invokestatic 30	o/pF:ˋ	(ICI)Ljava/lang/String;
    //   1063: invokevirtual 36	java/lang/String:intern	()Ljava/lang/String;
    //   1066: invokespecial 136	android/content/Intent:<init>	(Ljava/lang/String;)V
    //   1069: astore_0
    //   1070: aload_0
    //   1071: sipush 1220
    //   1074: iconst_0
    //   1075: bipush 13
    //   1077: invokestatic 30	o/pF:ˋ	(ICI)Ljava/lang/String;
    //   1080: invokevirtual 36	java/lang/String:intern	()Ljava/lang/String;
    //   1083: aload 5
    //   1085: invokeinterface 168 1 0
    //   1090: invokevirtual 144	android/content/Intent:putExtra	(Ljava/lang/String;Ljava/lang/String;)Landroid/content/Intent;
    //   1093: pop
    //   1094: aload 10
    //   1096: aload_0
    //   1097: invokestatic 148	o/pD:sendBroadcast	(Landroid/content/Context;Landroid/content/Intent;)V
    //   1100: goto +638 -> 1738
    //   1103: bipush 32
    //   1105: istore_3
    //   1106: goto -450 -> 656
    //   1109: astore 9
    //   1111: getstatic 50	o/pF:ˎ	Ljava/lang/String;
    //   1114: sipush 2355
    //   1117: iconst_0
    //   1118: bipush 55
    //   1120: invokestatic 30	o/pF:ˋ	(ICI)Ljava/lang/String;
    //   1123: invokevirtual 36	java/lang/String:intern	()Ljava/lang/String;
    //   1126: invokestatic 130	o/pD:d	(Ljava/lang/String;Ljava/lang/String;)V
    //   1129: goto +315 -> 1444
    //   1132: iload_3
    //   1133: tableswitch	default:+23->1156, 0:+-832->301, 1:+-1101->32
    //   1156: goto -1124 -> 32
    //   1159: aload 9
    //   1161: checkcast 32	java/lang/String
    //   1164: astore_2
    //   1165: goto -1142 -> 23
    //   1168: aload 7
    //   1170: invokeinterface 174 1 0
    //   1175: checkcast 165	com/insidesecure/hce/MatrixHCECard
    //   1178: astore 6
    //   1180: aload 6
    //   1182: sipush 2595
    //   1185: ldc -5
    //   1187: bipush 19
    //   1189: invokestatic 30	o/pF:ˋ	(ICI)Ljava/lang/String;
    //   1192: invokevirtual 36	java/lang/String:intern	()Ljava/lang/String;
    //   1195: invokeinterface 254 2 0
    //   1200: astore 9
    //   1202: aconst_null
    //   1203: astore_2
    //   1204: aload 9
    //   1206: ifnull +6 -> 1212
    //   1209: goto -291 -> 918
    //   1212: goto +413 -> 1625
    //   1215: iconst_0
    //   1216: istore_3
    //   1217: goto -226 -> 991
    //   1220: aload 6
    //   1222: astore_2
    //   1223: goto +157 -> 1380
    //   1226: iconst_1
    //   1227: istore_3
    //   1228: goto +46 -> 1274
    //   1231: getstatic 50	o/pF:ˎ	Ljava/lang/String;
    //   1234: sipush 2926
    //   1237: ldc -1
    //   1239: bipush 40
    //   1241: invokestatic 30	o/pF:ˋ	(ICI)Ljava/lang/String;
    //   1244: invokevirtual 36	java/lang/String:intern	()Ljava/lang/String;
    //   1247: invokestatic 101	o/pD:i	(Ljava/lang/String;Ljava/lang/String;)V
    //   1250: aload 5
    //   1252: checkcast 257	o/pr
    //   1255: sipush 2966
    //   1258: iconst_0
    //   1259: bipush 55
    //   1261: invokestatic 30	o/pF:ˋ	(ICI)Ljava/lang/String;
    //   1264: invokevirtual 36	java/lang/String:intern	()Ljava/lang/String;
    //   1267: invokevirtual 259	o/pr:ˋ	(Ljava/lang/String;)Z
    //   1270: pop
    //   1271: goto +467 -> 1738
    //   1274: iload_3
    //   1275: tableswitch	default:+21->1296, 0:+-295->980, 1:+-475->800
    //   1296: goto -316 -> 980
    //   1299: aload 11
    //   1301: instanceof 32
    //   1304: ifeq +6 -> 1310
    //   1307: goto -92 -> 1215
    //   1310: goto +388 -> 1698
    //   1313: aload 9
    //   1315: invokeinterface 174 1 0
    //   1320: checkcast 165	com/insidesecure/hce/MatrixHCECard
    //   1323: astore_2
    //   1324: aload_2
    //   1325: sipush 2695
    //   1328: iconst_0
    //   1329: bipush 16
    //   1331: invokestatic 30	o/pF:ˋ	(ICI)Ljava/lang/String;
    //   1334: invokevirtual 36	java/lang/String:intern	()Ljava/lang/String;
    //   1337: invokeinterface 254 2 0
    //   1342: astore 11
    //   1344: aconst_null
    //   1345: astore 8
    //   1347: aload 11
    //   1349: ifnull +6 -> 1355
    //   1352: goto -249 -> 1103
    //   1355: goto -332 -> 1023
    //   1358: aload 9
    //   1360: instanceof 32
    //   1363: ifeq +6 -> 1369
    //   1366: goto -207 -> 1159
    //   1369: goto +256 -> 1625
    //   1372: goto +366 -> 1738
    //   1375: iconst_0
    //   1376: istore_3
    //   1377: goto -103 -> 1274
    //   1380: aload_2
    //   1381: ifnonnull +6 -> 1387
    //   1384: goto -1215 -> 169
    //   1387: goto -1369 -> 18
    //   1390: goto +329 -> 1719
    //   1393: aload 5
    //   1395: ifnonnull +6 -> 1401
    //   1398: goto -614 -> 784
    //   1401: goto +162 -> 1563
    //   1404: aload_2
    //   1405: aload 5
    //   1407: invokevirtual 84	java/lang/String:equals	(Ljava/lang/Object;)Z
    //   1410: ifeq +6 -> 1416
    //   1413: goto -193 -> 1220
    //   1416: goto -26 -> 1390
    //   1419: aload_1
    //   1420: sipush 3021
    //   1423: iconst_0
    //   1424: bipush 19
    //   1426: invokestatic 30	o/pF:ˋ	(ICI)Ljava/lang/String;
    //   1429: invokevirtual 36	java/lang/String:intern	()Ljava/lang/String;
    //   1432: invokevirtual 84	java/lang/String:equals	(Ljava/lang/Object;)Z
    //   1435: ifeq +6 -> 1441
    //   1438: goto -409 -> 1029
    //   1441: goto +58 -> 1499
    //   1444: new 32	java/lang/String
    //   1447: dup
    //   1448: aload_2
    //   1449: sipush 2410
    //   1452: iconst_0
    //   1453: bipush 16
    //   1455: invokestatic 30	o/pF:ˋ	(ICI)Ljava/lang/String;
    //   1458: invokevirtual 36	java/lang/String:intern	()Ljava/lang/String;
    //   1461: invokevirtual 194	org/json/JSONObject:getString	(Ljava/lang/String;)Ljava/lang/String;
    //   1464: invokespecial 195	java/lang/String:<init>	(Ljava/lang/String;)V
    //   1467: astore_2
    //   1468: aload_2
    //   1469: astore 6
    //   1471: goto -78 -> 1393
    //   1474: astore_2
    //   1475: getstatic 50	o/pF:ˎ	Ljava/lang/String;
    //   1478: sipush 2426
    //   1481: iconst_0
    //   1482: bipush 52
    //   1484: invokestatic 30	o/pF:ˋ	(ICI)Ljava/lang/String;
    //   1487: invokevirtual 36	java/lang/String:intern	()Ljava/lang/String;
    //   1490: invokestatic 130	o/pD:d	(Ljava/lang/String;Ljava/lang/String;)V
    //   1493: goto -100 -> 1393
    //   1496: goto -1442 -> 54
    //   1499: aload_1
    //   1500: sipush 3086
    //   1503: ldc_w 260
    //   1506: bipush 20
    //   1508: invokestatic 30	o/pF:ˋ	(ICI)Ljava/lang/String;
    //   1511: invokevirtual 36	java/lang/String:intern	()Ljava/lang/String;
    //   1514: invokevirtual 84	java/lang/String:equals	(Ljava/lang/Object;)Z
    //   1517: ifeq +6 -> 1523
    //   1520: goto -673 -> 847
    //   1523: goto -1417 -> 106
    //   1526: getstatic 19	o/pF:ˏ	I
    //   1529: bipush 89
    //   1531: iadd
    //   1532: istore_3
    //   1533: iload_3
    //   1534: sipush 128
    //   1537: irem
    //   1538: putstatic 17	o/pF:ॱ	I
    //   1541: iload_3
    //   1542: iconst_2
    //   1543: irem
    //   1544: ifeq +6 -> 1550
    //   1547: goto -570 -> 977
    //   1550: goto -605 -> 945
    //   1553: aload 11
    //   1555: checkcast 32	java/lang/String
    //   1558: astore 5
    //   1560: goto -1386 -> 174
    //   1563: iconst_1
    //   1564: istore_3
    //   1565: goto -870 -> 695
    //   1568: getstatic 19	o/pF:ˏ	I
    //   1571: bipush 17
    //   1573: iadd
    //   1574: istore_3
    //   1575: iload_3
    //   1576: sipush 128
    //   1579: irem
    //   1580: putstatic 17	o/pF:ॱ	I
    //   1583: iload_3
    //   1584: iconst_2
    //   1585: irem
    //   1586: ifeq +6 -> 1592
    //   1589: goto -811 -> 778
    //   1592: goto -798 -> 794
    //   1595: getstatic 19	o/pF:ˏ	I
    //   1598: bipush 103
    //   1600: iadd
    //   1601: istore_3
    //   1602: iload_3
    //   1603: sipush 128
    //   1606: irem
    //   1607: putstatic 17	o/pF:ॱ	I
    //   1610: iload_3
    //   1611: iconst_2
    //   1612: irem
    //   1613: ifeq +6 -> 1619
    //   1616: goto -995 -> 621
    //   1619: goto -215 -> 1404
    //   1622: goto -1220 -> 402
    //   1625: aload_2
    //   1626: ifnull +6 -> 1632
    //   1629: goto -34 -> 1595
    //   1632: goto -242 -> 1390
    //   1635: aload_1
    //   1636: sipush 2908
    //   1639: iconst_0
    //   1640: bipush 18
    //   1642: invokestatic 30	o/pF:ˋ	(ICI)Ljava/lang/String;
    //   1645: invokevirtual 36	java/lang/String:intern	()Ljava/lang/String;
    //   1648: invokevirtual 84	java/lang/String:equals	(Ljava/lang/Object;)Z
    //   1651: ifeq +6 -> 1657
    //   1654: goto -423 -> 1231
    //   1657: goto -238 -> 1419
    //   1660: aload_2
    //   1661: ifnonnull +6 -> 1667
    //   1664: goto -941 -> 723
    //   1667: aload_2
    //   1668: astore 5
    //   1670: goto -1227 -> 443
    //   1673: aload_1
    //   1674: sipush 2842
    //   1677: iconst_0
    //   1678: bipush 13
    //   1680: invokestatic 30	o/pF:ˋ	(ICI)Ljava/lang/String;
    //   1683: invokevirtual 36	java/lang/String:intern	()Ljava/lang/String;
    //   1686: invokevirtual 84	java/lang/String:equals	(Ljava/lang/Object;)Z
    //   1689: ifeq +6 -> 1695
    //   1692: goto -1498 -> 194
    //   1695: goto -60 -> 1635
    //   1698: iconst_1
    //   1699: istore_3
    //   1700: goto -709 -> 991
    //   1703: aload 5
    //   1705: aload 6
    //   1707: invokevirtual 84	java/lang/String:equals	(Ljava/lang/Object;)Z
    //   1710: ifeq +6 -> 1716
    //   1713: goto -1062 -> 651
    //   1716: goto -927 -> 789
    //   1719: aload 7
    //   1721: invokeinterface 237 1 0
    //   1726: ifeq +6 -> 1732
    //   1729: goto -561 -> 1168
    //   1732: aload 8
    //   1734: astore_2
    //   1735: goto -355 -> 1380
    //   1738: iconst_1
    //   1739: ireturn
    // Local variable table:
    //   start	length	slot	name	signature
    //   0	1740	0	paramPz	pz
    //   0	1740	1	paramString	String
    //   0	1740	2	paramJSONObject	org.json.JSONObject
    //   19	1681	3	i	int
    //   8	1	4	bool	boolean
    //   55	1649	5	localObject1	Object
    //   58	1648	6	localObject2	Object
    //   61	1659	7	localIterator	Iterator
    //   64	1669	8	localObject3	Object
    //   97	306	9	localObject4	Object
    //   1109	51	9	localJSONException	org.json.JSONException
    //   1200	159	9	localObject5	Object
    //   70	1025	10	localContext	android.content.Context
    //   3	1551	11	localObject6	Object
    // Exception table:
    //   from	to	target	type
    //   194	198	29	java/lang/Exception
    //   198	210	29	java/lang/Exception
    //   210	215	29	java/lang/Exception
    //   215	220	29	java/lang/Exception
    //   198	210	966	java/lang/Exception
    //   1159	1165	966	java/lang/Exception
    //   72	99	1109	org/json/JSONException
    //   1444	1468	1474	org/json/JSONException
  }
  
  private static String ˋ(int paramInt1, char paramChar, int paramInt2)
  {
    break label239;
    label3:
    int j;
    label61:
    char[] arrayOfChar;
    for (;;)
    {
      switch (j)
      {
      default: 
        break;
      case 0: 
        j = ˏ + 75;
        ॱ = j % 128;
        if (j % 2 != 0) {
          break label103;
        }
        break label200;
        arrayOfChar = new char[paramInt2];
        break label160;
        j = 1;
      }
    }
    label75:
    label103:
    label106:
    label125:
    label128:
    for (int i = 1;; i = 0) {
      switch (i)
      {
      case 0: 
      default: 
        break label61;
        break label200;
        j = 0;
        break label3;
        for (;;)
        {
          break;
          return new String(arrayOfChar);
        }
      }
    }
    label160:
    label200:
    label239:
    for (;;)
    {
      i = ॱ + 101;
      ˏ = i % 128;
      if (i % 2 == 0) {
        break label128;
      }
      break label75;
      for (;;)
      {
        i = 0;
        j = ॱ + 37;
        ˏ = j % 128;
        if (j % 2 == 0) {
          break label125;
        }
        break;
        arrayOfChar = new char[paramInt2];
      }
      arrayOfChar[i] = ((char)(int)(ˊ[(paramInt1 + i)] ^ i * ˋ ^ paramChar));
      i += 1;
      if (i < paramInt2) {
        break label106;
      }
      break;
    }
  }
  
  static void ˋ()
  {
    ˋ = 7228817601914331544L;
    ˊ = new char[] { 25431, -32008, -24488, -14430, -6895, 1176, 10933, 18531, 28586, -29399, -21348, -11541, -4020, 6110, 13620, 21657, 31468, -26510, -16421, -8851, -886, -7665, 53, 10206, 17696, 25779, -30191, -22424, -12329, -4835, 3260, 12830, 20517, 30707, -27328, -19295, -9719, 67, -7689, -15547, -23388, -31228, 26584, 18942, 11079, 3252, -4488, -12394, -19999, -27826, 29916, 22128, 14245, 6625, -1172, -9022, -16863, -24680, -32464, 25427, 17645, 9729, 1979, -5869, -13465, -21291, -29098, 28580, 20808, 13158, 5367, -2494, -10264, -18137, -25925, 31965, 24072, 16307, 8509, 670, -6932, -14779, -22582, -30352, -20274, 20833, 29633, 5179, 13960, -10495, -1748, -25606, -17357, 24240, 32517, 370, 9173, -15289, -6483, -30976, -22155, 19435, 27714, 3822, 12124, 32, -7682, -15521, -23366, -31168, 26521, 18931, 11083, 3247, -4563, -12386, -19972, -27904, 67, -7696, -15531, -23381, -31221, 26513, 18942, 11087, 3296, -4559, -12394, -20056, -27790, 29917, 22077, 14215, 6644, -1155, -9072, -16890, -24689, -32500, 25465, 17614, 9769, 1979, -5871, -13444, -21303, -29097, 28606, 20808, 13161, 5355, -2544, -10335, -18162, -25896, 31943, 24137, 16300, 8500, 661, -6916, -14848, -22549, -30411, 27290, 19702, 11901, 4034, -3736, -11642, -19433, -27038, 30661, 22817, 15020, -30144, 27600, 18798, 11926, 3116, -4686, -15400, 109, -7683, -15549, -23365, -31231, 26527, 18933, 11013, 3252, -4575, -12416, -19987, -15827, 9149, 259, 26363, 17473, -23073, -29771, -5819, -12572, 11385, 3524, 29609, 82, -7683, -15523, -23385, -31212, 26525, 18864, 11110, 3247, -4564, -12391, -19986, -27831, 29915, 22065, 14236, 6633, -1161, -8994, -16792, -24695, -32501, 25392, 17601, 9774, 2040, -5849, -13463, -21300, -29100, 28597, 20764, 13088, 5323, -2475, -10310, -18154, -25955, 31970, 24072, 16278, 8460, 675, -7000, -14778, -22569, -30430, 27269, 19628, 11832, 4032, -3799, -11630, -19445, -27015, 30662, 22823, -24631, 32358, 23752, 15158, 6546, -2027, -10642, -19241, -27781, 29073, 20494, 11902, 3284, -5289, -13906, -22445, -31147, 25836, 17247, 8634, 29, 7818, -792, -9390, -18001, -26582, 30340, 21757, 13083, 4554, -4040, -12589, -21259, -29844, 27103, 18547, 9874, 1293, -7381, -15900, -24518, -16721, -25337, 31606, 22991, 14339, 5784, -2794, -11415, -19979, -28594, 28321, 19803, 11189, 2527, -6048, -14597, -23259, -31868, 25057, 16470, 24258, 15679, 19744, -21361, -29137, -5675, -13466, 10991, 1218, 26132, 16861, -23714, -32021, -868, -8645, 14761, 6979, 31470, 21659, -18939, -28244, -3302, -11525, -13191, 11842, 2483, 27484, 19082, -23467, -31205, -7746, -15578, 8903, 7278, 32338, 22969, -17625, -25912, -2972, -10257, 12688, 4986, 29439, 27758, 20423, -22103, -29838, -5460, -15283, 10216, 415, 25414, 17122, -17334, -24589, -1672, -9455, 15027, 5212, 30669, 82, -7683, -15533, -23379, -31223, 26510, 18933, 11084, 3296, -4598, -12395, -19995, -27825, 29900, 22069, 14280, 6606, -1161, -9020, -16863, -24698, -32495, 25459, 17609, 9780, 1969, -5857, -13466, -21376, -29103, 28579, 20808, 13166, 5367, -2492, -10264, -18167, -25962, 31920, 24191, 16289, 8500, 668, -6931, -14764, -22632, -30461, 27277, 19698, 11886, 4053, -3782, -11584, -19403, -27052, 30701, 22803, 15096, 7190, -409, -8238, -16043, -23887, -31716, -4122, 3669, 11504, 19214, 27054, -30668, -22949, -15126, -7355, 404, 8243, 24077, 31959, -25736, -18024, -10206, -2479, 5336, 13109, 20899, 28714, 28329, -29476, -21653, -13940, -6114, 1716, 9433, 17260, 25074, -32741, -16659, -9012, -1202, 6581, 14340, 22187, 30077, -27784, -19988, -12266, -12663, -4816, 2911, 10694, 18556, 26247, -31447, -23803, -15909, -8070, 7839, 15656, 23484, 31169, 109, -7689, -15534, -23391, -31220, 26525, 18907, 11085, 3257, -4565, -12395, -19972, -27799, 29916, 82, -7683, -15523, -23385, -31212, 26525, 18864, 11110, 3247, -4564, -12391, -19986, -27831, 29915, 22065, 14236, 6633, -1161, -8994, -16792, -24695, -32501, 25392, 17601, 9774, 2040, -5827, -13463, -21293, -29108, 28597, 20762, 13123, 5369, -2494, -10324, -18112, -25954, 31999, 24154, 16301, 8505, 644, -7004, -14848, -22584, -30415, 27290, 19699, 11889, 4062, -3793, 114, -7683, -15529, -23391, -31213, 26508, 18914, 11081, 3252, -4559, -12385, -19994, -27804, 29913, 22052, 14217, 82, -7683, -15523, -23385, -31212, 26525, 18864, 11078, 3247, -4564, -12391, -19986, -27831, 29915, 22065, 14236, 6633, -1161, -8994, -16792, -24684, -32489, 25392, 17601, 9774, 1969, -5884, -13471, -21311, -29108, 28597, 20808, 13170, 5373, -2473, -10335, -18157, -25972, 31989, 24154, 16352, 8510, 671, -6918, -14848, -22571, -30415, 27291, 19700, 11901, 4034, -3797, -11647, -19446, -27020, -5788, 2250, 10857, 19867, 28478, -29023, -24384, -15809, -6754, 1793, 9907, 22746, 31353, -25093, -16569, -8519, -3880, 4701, 13735, 22285, 30386, 26668, -30142, -21002, -12543, -4470, 35, 8735, 17913, 26464, -31085, -18378, -9647, -570, 8036, 16030, 20515, 29606, -27192, -18575, 99, -7689, -15523, -23322, -31223, 26518, 18915, 11073, 3236, -4547, -12413, -19987, -27837, 29901, 22050, 14221, 6574, -1168, -9005, -16851, -24626, -32495, 25470, 17628, 9765, 1974, -5884, -13530, -21272, -29061, 28565, 20791, 13140, 5322, -2439, -10353, -18137, -25923, 31938, 24183, 16274, 8477, 695, -6975, -14733, -22548, -30462, 27305, 19668, 11857, 4095, -3834, -9049, 15668, 8090, 30808, 23246, -17580, -27332, -2168, -12166, 13049, 4939, 27928, 20353, -22506, -29966, -5310, 78, -7689, -15548, -23320, -31213, 26525, 18942, 11084, 3241, -4554, -12393, -20056, -27831, 29910, 22052, 14221, 6638, -1172, -9072, -16850, -24689, -32502, 25392, 17626, 9765, 1979, -5867, -13471, -21290, -29091, 28596, 20808, 13166, 5367, -2492, -10335, -18170, -25967, 31987, 24137, 16308, 8497, 671, -6938, -14834, 29218, -27681, -20160, -10568, -3059, 5512, 15272, 22794, 18933, -22449, -29977, -4845, -12383, 11810, 80, 25276, 17692, -22643, -31177, -2020, -9482, 15721, 8065, 32306, 20500, -19746, -27295, -2149, -10691, -14145, 10960, 3449, 28550, 19977, -24416, -32112, -6860, -14364, 9733, 6322, 31440, 23872, -16403, -25070, -3917, -11412, 13654, 6137, 30233, 26755, 19248, -21159, -28748, -4510, -16245, 9000, 1373, 26570, 18029, -18273, -25803, -584, -8243, 15987, 4250, 29506, 5652, -2171, -10964, -19774, -28647, 29139, 24492, 15644, 6902, -1931, -9780, -22543, -31465, 25230, 16509, 8664, 4031, -4824, -13686, -22416, -30259, -26808, 29990, 21151, 12323, 4513, -166, -8908, -17782, -26606, 31200, 18270, 9527, -21716, 19090, 26668, 4052, 11642, -13068, -7524, -32719, -22582, 17739, 25827, 6798, 14463, -8268, -694, -25373, -19745, 20499, 30631, 5458, 13503, 10857, -14326, -4189, -29368, -21304, 17021, 24604, 2047, 9524, -15158, -1436, -26612, -16498, 23840, 31961, 4671, 12771, -10354, -2781, -27426, 67, -7689, -15547, -23388, -31228, 26584, 18942, 11079, 3252, -4488, -12413, -19987, -27820, 29848, 22052, 14208, 6629, -1224, -8994, -16851, -24684, -32497, 25471, 17626, 9771, 2040, -5885, -13459, -21293, -29109, 28601, 20743, 13166, 5304, -2476, -10327, -18156, -25959, 29584, -28159, -20312, -10426, -2659, 5207, 14888, 22680, 32626, -25103, -17336, -15755, -8045, 1802, 9721, 17500, 27195, -30548, -20722, -12812, -5047, -3380, 4258, 14107, 21927, 29733, -25891, -18265, -8430, -621, 7268, 8902, 16564, 26410, -31357, -22529, 18027, 25793, 890, 8597, -16374, -4481, -29475, -21704, 18849, 26655, 5745, 13535, -11439, -3650, -28655, -16846, 23788, 31567, 6577, 14418, 9869, -15134, -7360, -32327, -24534, 20120, 27834, 2932, 10727, -14327, -2389, -27442, -19647, 20973, 28688, 7845, 15675, -9398, -1541, -26610, -31077, -23236, 17222, 25075, 114, 11909, -13017, -5291, -30261, -22430, -31378, 25853, 18003, 8593, 773, -7521, -13084, -20918, -30311, 27435, 19096, 13543, 5719, -3637, -11469, -19791, -25356, 32379, 22992, 15147, 6804, 1051, -6536, -15923, -23773, 6881, -1168, -9767, -16841, -25364, 32038, 21337, 12777, 5635, -2944, -10951, -21756, -30238, 28283, 19592, 11565, 842, -7715, -14721, -23419, -31432, -25667, 31187, 24170, 15574, 7508, -3151, -11829, -18834, -27395, 29968, 19361, 10636, 3652, -4875, -13046, -23572, -32730, 26201, 17655, 9481, 15232, 83, -7683, -15522, -23380, -31223, 26518, 18935, 11016, 3216, -4591, -12354, -20056, -27805, 29904, 22065, 14214, 6631, -1155, -9072, -16870, -24699, -32503, 25445, 17601, 9778, 1981, -5868, -13528, -21307, -29106, 28597, 20742, 13172, 5304, -2474, -10329, -18158, -25896, 31987, 24137, 16306, 8508, 714, -7000, 99, -7689, -15523, -23322, -31223, 26518, 18915, 11073, 3236, -4547, -12413, -19987, -27837, 29901, 22050, 14221, 6574, -1168, -9005, -16851, -24626, -32495, 25470, 17628, 9765, 1974, -5884, -13530, -21272, -29061, 28565, 20791, 13136, 5329, -2434, -10345, -18141, -25936, 31953, 24166, 16263, 8477, 687, -6950, -14747, -22551, -30459, 27297, 19666, 11869, 4084, 104, -7685, -15531, -23401, -31229, 26521, 18914, 11084, 3231, -4554, -12399, -19995, -27835, 85, -7690, -15525, -23386, -31217, 26511, 18942, 11016, 3252, -4575, -12416, -19987, -27904, 29918, 22079, 14234, 6560, -1195, -8972, -16883, -24653, -32424, 25442, 17613, 9773, 1975, -5884, -13459, -21376, -29098, 28607, 20764, 13161, 5374, -2471, -10325, -18175, -25972, 31993, 24135, 16302, -23664, 16938, 24706, 1910, 9668, -15289, -5579, -30503, -20615, 19944, 27730, 4729, 12447, -10490, -2571, -27623, -17869, 22700, 32516, 7671, 15377, 8923, -16220, -6370, -31240, -23430, 19157, 26812, 3843, 11660, -13211, -3435, -28431, -18630, 21909, 29816, 6850, 14657, -8408, -617, -25482, -32087, -24237, 18236, 26012, 1030, 10997, -13988, -4239, -29273, -21490, 21229, 29016, 6095, 13736, -11238, -1296, -26243, -16440, 23990, 31775, 25287, 1500, -7053, -14627, -24285, -31865, 25088, 19579, 11970, 2414, -5244, -13797, -19349, -26943, 28994, 21435, 12870, 7232, -263, -9910, -17489, -26104, -31585, 26365, 16711, 9146, 575, -4975, -12568, -22258, -29729, 27181, 21702, 14048, 4473, -3126, -11674, -17273, -24808, 31038, 23532, 14909, 9401, 1808, -7898, -15416, -23975, -29524, 28427, 18799, 11234, 30271, -26736, -19138, -11584, -3996, 4579, 16280, 23841, 31373, -26521, -17928, -14456, -6878, 673, 8280, 16805, 28579, -29414, -21847, -14260, -5653, -2180, 5406, 12964, 20569, 29148, -24718, -17141, -9491, -1988, 6606, 10021, 17667, 25242, -32727, -24187, -12444, -4869, 2781, 10248, 18892, 22342, 29929, -28032, -20417, -11882, -164, 7415, 14985, 22613, 31163, -30902, -23297, -15752, -8164, 433, 82, -7683, -15523, -23385, -31212, 26525, 18864, 11110, 3247, -4564, -12391, -19986, -27831, 29915, 22065, 14236, 6633, -1161, -8994, -16792, -24695, -32501, 25392, 17601, 9774, 1966, -5871, -13468, -21303, -29092, 21279, -19794, -28663, -2053, -10917, 13510, 6825, 30744, 24503, -17086, -25372, -7425, -16379, 10122, 1386, 25808, 19107, -22486, -28729, -4751, -13096, -11685, 12334, 6041, 30078, 21740, -17850, -26581, -98, -8960, 15593, 543, 24625, 18336, -23275, -31553, -5546, -13876, 12196, 3344, 27874, 29281, 20947, -18433, 20051, -20483, -29372, -5444, -14327, 10646, 2039, 25864, 17037, -24548, -32331, -37, -8960, 15083, 6197, 31131, 22515, -19087, -27937, -4058, -11840, -12495, 11646, 2766, 26671, 18936, -22780, -31385, -7552, -16295, 8627, 7947, 32111, 23277, -18338, -26180, -2240, -11046, 34, -7752, -15535, -23386, -31228, 26584, 18931, 11081, 3244, -4556, -12391, -19994, -27833, 29848, 22078, 14215, 6644, -1167, -9002, -16847, 28455, -29048, -21466, -13352, -5764, 2299, 9856, 17465, 25493, -32418, -24352, -8562, -986, 7076, 14666, 22771, 30421, -27644, -19541, -11941, -3846, -4575, 3141, 11199, 18752, 26841, -31195, -23543, -15427, -7896, 215, 15992, 23637, 31620, -26314, -18275, -10629, -2590, 5061, 12590, 20688, 20062, 28150, -29804, -22214, -14173, -6651, 1522, 9093, 16648, 24747, -25004, -16901, -9366, -1723, 6331, 13914, 21983, 29477, -28407, -20291, -20956, -12842, -5315, 2324, 10382, 17958, 26066, -31904, -23837, -16239, -4810, 3247, 11804, 18937, 27486, -29991, -23323, -14844, -7689, 875, 8909, 23742, 32341, -26219, -17544, -9516, -2887, 5684, 12685, 21364, -905, 7624, 16232, 22677, 31284, -25683, -19071, -10387, -3938, 4681, 13221, 19932, 28530, -30469, -21992, -13399, -6715, 1801, 8431, 16918, 25509, 32032, -24761, -18192, -9710, -1144, 5429, 14160, 20734, 29287, -27711, -21207, -12464, -5936, 2669, 11158, 17712, 26285, -32639, -23939, -15472, -8931, -352, 116, -7689, -15525, -23379, -31218, 26507, 25719, -31244, -22696, -16210, -7667, 942, 11773, 20290, 26802, -30162, -21610, -10791, -2234, 4317, 12854, 21401, 32230, -24715, -18224, -9682, 18127, -22704, -31251, -7680, -16215, 8503, 70, -7687, -15527, -23388, -31227, 26524, 18864, 11100, 3247, -4488, -12394, -19999, -27826, 29916, 22128, 14219, 6625, -1174, -9004, -16792, -24698, -32489, 25442, 17544, 9780, 1975, -5861, -13459, -21298, -29160, 28581, 20742, 13161, 5353, -2491, -10323, -18112, -25974, 31989, 24142, 16293, 8490, 661, -6938, -14781, -22563, -30358, 2693, -5370, -13910, -20900, -29441, 27968, 17167, 8639, 1630, -9027, 15618, 8098, 30815, 23294, -17561, -27317, -2137, -12204, 12931, 4974, 27915, 20399, -22479, -30006, -5264, -15089, 10179, 63, 25308, 17264, 24038, -16507, -26598, -1323, -9403, 13796, 6099, 28733, 21169, -19644, -29186, -4133, -14323, 10916, 2887, 26098, 18021, -24558, -32121, -7340, -568, -8594, 14365, 6798, 31539, 21967, -18830, -28657, -3450, -11473, 11667, 3691, 26870, 19096, -21701, -31333, -6578, -16146, 8832, 808, 7586, 32332, 22774, -17727, -25789, 65, -7717, -15516, -23423, -31178, 26557, 12354, -11796, -3243, -27475, -18920, 22407, 31206, 6937, 15538, -8664, -109, -32259, -23791, 17626, 26165, 1944, 10725, -13460, -4991, -29139, -20578, -20151, 21312, 29946, 5637, 14208, -9929, -1188, -25455, -16817, 24494, 24843, 817, 104, -7685, -15531, -23401, -31220, 26513, 18934, 11085, 3235, -4575, -12397, -19996, -27835, 29927, 22065, 14219, 6644, -1167, -8993, -16858, -24641, -32502, 25461, 17627, 9781, 1973, -5867, 83, -7683, -15522, -23380, -31223, 26518, 18935, 11016, 3241, -4554, -12412, -19987, -27826, 29900, 22128, 14222, 6639, -1174, -9072, -16853, -24703, -32502, 25460, 17544, 9773, 1981, -5884, -13463, -21308, -29095, 28580, 20745, 13088, 5357, -2496, -10324, -18175, -25972, 31989, 24140, 99, -7689, -15523, -23322, -31223, 26518, 18915, 11073, 3236, -4547, -12413, -19987, -27837, 29901, 22050, 14221, 6574, -1168, -9005, -16851, -24626, -32495, 25470, 17628, 9765, 1974, -5884, -13530, -21272, -29061, 28565, 20791, 13123, 5337, -2462, -10356, -18113, -25931, 31957, 24188, 16257, 8476, 689, -6948, -14751, -22553, -30459, 27320, 19652, 11865, 4068, -3827, -11612, 13314, -10863, -2241, -28419, -19865, 21495, 32142, 7971, 14542, -9645, -1042, -31357, -22763, 16545, 25166, 1008, 11651, -12516, -5955, 20873, -20457, -27975, -2750, -10241, 13932, 6158, 31415, 23902, 14349, -9821, -1254, -25374, -16809, 24520, 29097, 4950, 13565, -10649, -2084, -30286, -21666, 19605, 28282, 4055, 8618, -15581, -6962, -31134, -22575, -18170, 23325, 31907, 7757, 16342, -11925, -3304, -27462, -18909, 22474, 26902, 2872, 11433, -12772, -4170, 104, -7685, -15531, -23401, -31220, 26513, 18934, 11085, 3235, -4575, -12397, -19996, -27835, 29927, 22065, 14219, 6644, -1167, -8993, -16858, -24641, -32501, 25445, 17627, 9776, 1981, -5858, -13460, 68, -7715, -15503, -23413, -31180, 26545, 18886, 11113, 3220, -4579, -12364, 99, -7689, -15523, -23322, -31223, 26518, 18915, 11073, 3236, -4547, -12413, -19987, -27837, 29901, 22050, 14221, 6574, -1168, -9005, -16851, -24626, -32495, 25470, 17628, 9765, 1974, -5884, -13530, -21272, -29061, 28565, 20791, 13132, 5329, -2442, -10355, -18141, -25951, 31955, 24164, 16261, 8455, 692, -6963, -14740, -22531, -30460, 27309, 19679, 11850, 4085, -3815, -11595, -19407, -27070, 30701, 22788, 74, -7733, -15489, -23418, -31168, 26525, 18920, 11083, 3237, -4568, -12412, -19999, -27825, 29910, 22128, 14209, 6638, -1224, -9000, -16855, -24690, -32484, 25468, 17601, 9774, 1983, -5808, -13499, -21276, -29059, 28547, 20808, 13138, 5334, -2461, -10264, -18162, -25961, 31972, 24129, 16294, 8481, 714, -7000, -848, 7469, 16259, 22624, 31373, -25780, -19166, -10359, -3986, 4843, 13137, 19755, 28564, -30703, -21761, -13498, -6803, 1980, 8213, 17148, 25409, 32209, -24644, -18405, 15401, -8771, -233, -26452, -17853, 23516, 30121, 5899, 12526, -11657, -3127, -29273, -20727, 18567, 27240, 3015, 9700, -14534, -8039, -32153, -23676, -17061, 24372, 30870, 6767, 15356, -10930, -2196, -28510, -19919, 21471, 28029, 3870, 10368, -13765, -5172, -31367, -22797, 16537, 25142, 963, 7517, 16116, -10083, -1495, -25667, -19113, 22258, 28806, 4631, 13230, -12985, -4370, 7988, -382, -9181, -17446, -26257, 30956, 22147, 13362, 5021, -3760, -12061, -20834, -29645, 27562, 18778, 10491, 1757, -7113, -15485, -24218, -32579, -24984, 31752, 23462, 14670, 6340, -2454, -11248, -19459, -28367, 28884, 20069, 11288, 3039, 30732, -26190, -17608, -8995, -404, 8171, 12697, 21307, 29909, -27060, -18449, -13930, -5362, 3245, 11841, 20471, 24980, -31957, -23410, 86, -7695, -15549, -23383, -31168, 26506, 18933, 11077, 3247, -4564, -12395, -20056, -27826, 29911, 22052, 14209, 6630, -1183, -9072, -16852, -24689, -32483, 25443, 17544, 9774, 1975, -5884, -13528, -21309, -29097, 28606, 20764, 13153, 5361, -2466, -10264, -18154, -25944, 31970, 24135, 16310, 8497, 643, -6943, -14769, -22570, -30411, 27276, 19668, 11895, 4059, -3795, -11634, -19407, -27052, 118, -7736, -15535, -23386, -31195, 26518, 18914, 11079, 3244, -4556, -12387, -19987, -27826, 29900, 22041, 14252, 86, -7695, -15549, -23383, -31168, 26506, 18933, 11077, 3247, -4564, -12395, -20056, -27826, 29911, 22052, 14209, 6630, -1183, -9072, -16852, -24689, -32483, 25443, 17544, 9774, 1975, -5884, -13528, -21309, -29097, 28606, 20764, 13153, 5361, -2466, -10264, -18154, -25944, 31985, 24134, 16261, 8502, 642, -6937, -14772, -22572, -30403, 27277, 19694, 11884, 4089, -3828, 28381, -28806, -21048, -13790, -5941, 2305, 10110, 17870, 25124, -32601, -24290, -8413, -571, 6748, 14511, 22794, 30573, -27158, -19941, -12121, -3836, -4202, 3560, 10755, 18597, 26940, -30833, -23133, -15800, -7972, 309, 16279, 24042, 31354, -26411, -18077, -10339, -3037, 4730, 12493, 20750, 20413, 27657, -30100, -22329, -13985, -6218, 1030, 8805, 16615, 24946, -24697, -17333, -9572, -1815, 6403, 14269, 21507, 29321, -28436, -20131, -20518, -13272, -5494, 2276, 10621, 18398, 25639, -32065, -23780, -16016, -58, 7205, 15002, 23359, 83, -7683, -15535, -23366, -31229, 26512, 18864, 11086, 3247, -4566, -12336, -19989, -27839, 29898, 22068, 14280, 6647, -1167, -9020, -16864, -24640, -32498, 25408, 17626, 9775, 1966, -5863, -13445, -21303, -29097, 28606, 20749, 13156, 5324, -2465, -10333, -18171, -25962, 31961, 24172, 16378, 8568, -18074, 22744, 31314, 7607, 16134, -8575, -3853, -28079, -19009, 22310, 30341, 2300, 10852, -12857, -4309, -29027, -24322, 16961, 26052, -2781, 5274, 13949, 20934, 29548, -27929, -17255, -8603, -1588, 6982, 15086, 17546, 26158, -32324, -23716, -15631, -4984, 3601, 10749, 19282, 27364, 29793, -27115, -19995, -11397, -3364, 7278, 15876, 23021, 31527, -25896, -23448, -14846, -7807, 824, 8837, 19555, 28666, -30327, -21716, -13621, -11188, 83, -7683, -15535, -23366, -31229, 26512, 18864, 11086, 3247, -4566, -12336, -19989, -27839, 29898, 22068, 14280, 6647, -1167, -9020, -16864, -24640, -32498, 25408, 17609, 9774, 1949, -5858, -13446, -21297, -29100, 28604, 20741, 13157, 5366, -2492, -10367, -18140, -25918, 31920, 118, -7736, -15535, -23386, -31195, 26518, 18914, 11079, 3244, -4556, -12387, -19987, -27826, 29900, 22041, 14220, -13766, 11152, 2360, 28380, 19576, -21014, -31862, -7897, -14626, 9287, 1451, 31653, 22834, -16720, -25526, -589, -11383, 12550, 5798, 29788, 21999, 19302, -22197, -28995, -5036, -12841, 9058, 277, 26274, 17507, -23073, -25732, -1701, -8576, 15402, 7617, 29567, 20665, -18741, -9926, 14521, 6677, 32227, 24384, -16741, -28499, -3566, -10769, 14178, 5835, 26805, 19011, -21117, -28818, -4414, -16209, 8738, 1435, 26466, 73, -7690, -15527, -23364, -31223, 26521, 18916, 11073, 3246, -4545, -12336, -20027, -27825, 29914, 22073, 14212, 6629, -1224, -8973, -16864, -24699, -32485, 25467, 99, -7689, -15523, -23322, -31223, 26518, 18915, 11073, 3236, -4547, -12413, -19987, -27837, 29901, 22050, 14221, 6574, -1168, -9005, -16851, -24626, -32495, 25470, 17628, 9765, 1974, -5884, -13530, -21272, -29061, 28565, 20791, 13133, 5335, -2446, -10367, -18132, -25923, 31951, 24171, 16264, 8477, 691, -6973, -14721, -22548, -30439, 27301, 19653, 116, -7689, -15525, -23379, -31218, 26581, 18931, 11098, 3237, -4551, -12412, -19987, -27836, 31986, -25251, -16397, -10227, -1367, 6958, 13653, 22508, 28736, -28020, -19649, -12989, -4123, 2166, 10960, 19243, 25938, -30755, -24463, -15716, -7387, -580, 8080, 14438, 23183, 31500, -27207, -18482, -12183, -3333, 4881, 11708, 20425, 26711, -29954, -21690, -14880, -6634, 95, 8872, 17153, 23963, 32292, -26559, -17681, -9354, -2608, 5670, 12357, 21213, 29556, -29299, -20956, 107, -7683, -15543, -23323, -31213, 26508, 18929, 11100, 3253, -4565, -12323, -19971, -27824, 29916, 22065, 14236, 6629, -1156, -15174, 9493, 1979, 24645, 17121, -23706, -29411, -4188, -14328, 10971, 2941, 29977, 22504, -20445, -27956, -3231, -8932, 16261, 6187, 31360, 23421, 17888, -22628, -32735, -7460, -15531, 11772, 4032, 26662, 19135, -21684, -27159, -2162, -12263, 12987, 4929, 32252, 24185, -18409, -25938, 104, -7685, -15531, -23401, -31220, 26513, 18934, 11085, 3235, -4575, -12397, -19996, -27835, 29927, 22050, 14221, 6630, -1167, -8996, -16860, -24641, -32502, 25461, 17625, 9781, 1969, -5886, -13459, -21308, -29081, 28578, 20749, 13153, 5355, -2465, -10330, -18113, -25964, 31973, 24131, 16287, 8492, 664, -6918, -14779, -22581, -30408, 27271, 19692, 11900, 4079, -3802, -11643, -19431, -27038, 112, -7687, -15543, -23387, -31227, 26518, 18916, 11013, 3252, -4566, -12399, -19994, -27821, 29913, 22067, 14236, 6633, -1161, -8994, -26701, 30237, 21694, 13132, 4585, -3978, -8681, -17176, -25783, 31190, 22628, 9741, 1198, -7380, -15984, -24466, -29169, 27786, 19312, 10703, 2149, 5868, -2940, -11487, -20018, -28577, 32432, 23708, 15154, 6585, -1954, -14597, -23423, -31973, 24996, 16449, 12015, 3446, -5296, -13920, -22455, -18741, -27292, 29447, 20914, 12321, -10980, 13446, 5693, 29139, 21298, -19734, -25462, -477, -9762, 15171, 6894, 25731, 17982, -24086, -31910, -7449, -13157, 11782, 2491, 27474, 85, -7690, -15525, -23386, -31217, 26511, 18942, 11016, 3245, -4547, -12413, -19973, -27839, 29919, 22069, 14268, 6649, -1176, -9003, -16792, -24633, -28673, -12958, 11478, 3691, 27029, 19238, -21841, -31497, -6588, -15958, 9049, 693, 31942, 24185, -17930, -25774, -1370, -11041, 13918, 4529 };
  }
  
  /* Error */
  private static void ˏ(pz paramPz, String paramString, org.json.JSONObject paramJSONObject)
  {
    // Byte code:
    //   0: goto +4 -> 4
    //   3: return
    //   4: goto +30 -> 34
    //   7: astore_0
    //   8: aload_0
    //   9: athrow
    //   10: astore_0
    //   11: aload_0
    //   12: athrow
    //   13: getstatic 50	o/pF:ˎ	Ljava/lang/String;
    //   16: sipush 1574
    //   19: sipush 28533
    //   22: bipush 71
    //   24: invokestatic 30	o/pF:ˋ	(ICI)Ljava/lang/String;
    //   27: invokevirtual 36	java/lang/String:intern	()Ljava/lang/String;
    //   30: invokestatic 101	o/pD:i	(Ljava/lang/String;Ljava/lang/String;)V
    //   33: return
    //   34: getstatic 50	o/pF:ˎ	Ljava/lang/String;
    //   37: new 23	java/lang/StringBuilder
    //   40: dup
    //   41: invokespecial 26	java/lang/StringBuilder:<init>	()V
    //   44: sipush 1472
    //   47: sipush 21335
    //   50: bipush 44
    //   52: invokestatic 30	o/pF:ˋ	(ICI)Ljava/lang/String;
    //   55: invokevirtual 36	java/lang/String:intern	()Ljava/lang/String;
    //   58: invokevirtual 40	java/lang/StringBuilder:append	(Ljava/lang/String;)Ljava/lang/StringBuilder;
    //   61: aload_1
    //   62: invokevirtual 40	java/lang/StringBuilder:append	(Ljava/lang/String;)Ljava/lang/StringBuilder;
    //   65: invokevirtual 48	java/lang/StringBuilder:toString	()Ljava/lang/String;
    //   68: invokestatic 88	o/pD:e	(Ljava/lang/String;Ljava/lang/String;)V
    //   71: aload_0
    //   72: aload_1
    //   73: invokevirtual 2675	o/pz:ˎ	(Ljava/lang/String;)Lo/pp;
    //   76: astore_0
    //   77: aload_0
    //   78: invokevirtual 2679	o/pp:ˋ	()Z
    //   81: ifeq +6 -> 87
    //   84: goto +39 -> 123
    //   87: goto -74 -> 13
    //   90: getstatic 17	o/pF:ॱ	I
    //   93: bipush 115
    //   95: iadd
    //   96: istore_3
    //   97: iload_3
    //   98: sipush 128
    //   101: irem
    //   102: putstatic 19	o/pF:ˏ	I
    //   105: iload_3
    //   106: iconst_2
    //   107: irem
    //   108: ifne +6 -> 114
    //   111: goto +6 -> 117
    //   114: goto +94 -> 208
    //   117: bipush 14
    //   119: istore_3
    //   120: goto +91 -> 211
    //   123: getstatic 50	o/pF:ˎ	Ljava/lang/String;
    //   126: astore 4
    //   128: new 23	java/lang/StringBuilder
    //   131: dup
    //   132: invokespecial 26	java/lang/StringBuilder:<init>	()V
    //   135: astore 5
    //   137: sipush 1516
    //   140: sipush 19968
    //   143: bipush 38
    //   145: invokestatic 30	o/pF:ˋ	(ICI)Ljava/lang/String;
    //   148: astore 6
    //   150: aload 6
    //   152: invokevirtual 36	java/lang/String:intern	()Ljava/lang/String;
    //   155: astore 6
    //   157: aload 4
    //   159: aload 5
    //   161: aload 6
    //   163: invokevirtual 40	java/lang/StringBuilder:append	(Ljava/lang/String;)Ljava/lang/StringBuilder;
    //   166: aload_1
    //   167: invokevirtual 40	java/lang/StringBuilder:append	(Ljava/lang/String;)Ljava/lang/StringBuilder;
    //   170: sipush 1554
    //   173: iconst_0
    //   174: bipush 20
    //   176: invokestatic 30	o/pF:ˋ	(ICI)Ljava/lang/String;
    //   179: invokevirtual 36	java/lang/String:intern	()Ljava/lang/String;
    //   182: invokevirtual 40	java/lang/StringBuilder:append	(Ljava/lang/String;)Ljava/lang/StringBuilder;
    //   185: invokevirtual 48	java/lang/StringBuilder:toString	()Ljava/lang/String;
    //   188: invokestatic 130	o/pD:d	(Ljava/lang/String;Ljava/lang/String;)V
    //   191: aload_0
    //   192: aload_2
    //   193: invokevirtual 2682	o/pp:ॱ	(Lorg/json/JSONObject;)V
    //   196: aload_0
    //   197: invokevirtual 2684	o/pp:ˊ	()V
    //   200: aload_0
    //   201: invokevirtual 2686	o/pp:ˏ	()V
    //   204: goto -114 -> 90
    //   207: return
    //   208: bipush 20
    //   210: istore_3
    //   211: iload_3
    //   212: lookupswitch	default:+28->240, 14:+-5->207, 20:+-209->3
    //   240: goto -237 -> 3
    // Local variable table:
    //   start	length	slot	name	signature
    //   0	243	0	paramPz	pz
    //   0	243	1	paramString	String
    //   0	243	2	paramJSONObject	org.json.JSONObject
    //   96	116	3	i	int
    //   126	32	4	str1	String
    //   135	25	5	localStringBuilder	StringBuilder
    //   148	14	6	str2	String
    // Exception table:
    //   from	to	target	type
    //   123	137	7	java/lang/Exception
    //   137	150	7	java/lang/Exception
    //   150	157	7	java/lang/Exception
    //   157	204	7	java/lang/Exception
    //   137	150	10	java/lang/Exception
  }
  
  /* Error */
  private static boolean ˏ(pz paramPz, String paramString1, String paramString2)
  {
    // Byte code:
    //   0: goto +941 -> 941
    //   3: iconst_1
    //   4: istore_3
    //   5: goto +57 -> 62
    //   8: iload 4
    //   10: tableswitch	default:+22->32, 0:+948->958, 1:+306->316
    //   32: goto +926 -> 958
    //   35: aload_1
    //   36: sipush 2225
    //   39: ldc_w 2687
    //   42: bipush 24
    //   44: invokestatic 30	o/pF:ˋ	(ICI)Ljava/lang/String;
    //   47: invokevirtual 36	java/lang/String:intern	()Ljava/lang/String;
    //   50: invokevirtual 84	java/lang/String:equals	(Ljava/lang/Object;)Z
    //   53: ifeq +6 -> 59
    //   56: goto +1137 -> 1193
    //   59: goto +60 -> 119
    //   62: iload_3
    //   63: tableswitch	default:+21->84, 0:+881->944, 1:+107->170
    //   84: goto +86 -> 170
    //   87: iconst_1
    //   88: ireturn
    //   89: new 179	org/json/JSONObject
    //   92: dup
    //   93: aload_1
    //   94: invokespecial 185	org/json/JSONObject:<init>	(Ljava/lang/String;)V
    //   97: sipush 1708
    //   100: iconst_0
    //   101: bipush 6
    //   103: invokestatic 30	o/pF:ˋ	(ICI)Ljava/lang/String;
    //   106: invokevirtual 36	java/lang/String:intern	()Ljava/lang/String;
    //   109: invokevirtual 2691	org/json/JSONObject:getJSONArray	(Ljava/lang/String;)Lorg/json/JSONArray;
    //   112: astore 6
    //   114: iconst_0
    //   115: istore_3
    //   116: goto +598 -> 714
    //   119: getstatic 50	o/pF:ˎ	Ljava/lang/String;
    //   122: astore_0
    //   123: new 23	java/lang/StringBuilder
    //   126: dup
    //   127: invokespecial 26	java/lang/StringBuilder:<init>	()V
    //   130: astore_2
    //   131: sipush 2302
    //   134: sipush 8061
    //   137: bipush 34
    //   139: invokestatic 30	o/pF:ˋ	(ICI)Ljava/lang/String;
    //   142: astore 6
    //   144: aload 6
    //   146: invokevirtual 36	java/lang/String:intern	()Ljava/lang/String;
    //   149: astore 6
    //   151: aload_0
    //   152: aload_2
    //   153: aload 6
    //   155: invokevirtual 40	java/lang/StringBuilder:append	(Ljava/lang/String;)Ljava/lang/StringBuilder;
    //   158: aload_1
    //   159: invokevirtual 40	java/lang/StringBuilder:append	(Ljava/lang/String;)Ljava/lang/StringBuilder;
    //   162: invokevirtual 48	java/lang/StringBuilder:toString	()Ljava/lang/String;
    //   165: invokestatic 101	o/pD:i	(Ljava/lang/String;Ljava/lang/String;)V
    //   168: iconst_0
    //   169: ireturn
    //   170: aload_2
    //   171: invokestatic 2695	com/insidesecure/hce/internal/MatrixHCENativeBridge:processMdesRnsPushTransactionDetails	(Ljava/lang/String;)[Ljava/lang/String;
    //   174: astore_1
    //   175: aload_1
    //   176: arraylength
    //   177: istore_3
    //   178: goto +774 -> 952
    //   181: iload_3
    //   182: iconst_1
    //   183: iadd
    //   184: istore_3
    //   185: goto +1035 -> 1220
    //   188: getstatic 50	o/pF:ˎ	Ljava/lang/String;
    //   191: new 23	java/lang/StringBuilder
    //   194: dup
    //   195: invokespecial 26	java/lang/StringBuilder:<init>	()V
    //   198: sipush 1740
    //   201: iconst_0
    //   202: bipush 47
    //   204: invokestatic 30	o/pF:ˋ	(ICI)Ljava/lang/String;
    //   207: invokevirtual 36	java/lang/String:intern	()Ljava/lang/String;
    //   210: invokevirtual 40	java/lang/StringBuilder:append	(Ljava/lang/String;)Ljava/lang/StringBuilder;
    //   213: aload_1
    //   214: invokevirtual 40	java/lang/StringBuilder:append	(Ljava/lang/String;)Ljava/lang/StringBuilder;
    //   217: invokevirtual 48	java/lang/StringBuilder:toString	()Ljava/lang/String;
    //   220: invokestatic 151	o/pD:w	(Ljava/lang/String;Ljava/lang/String;)V
    //   223: goto -42 -> 181
    //   226: aload_2
    //   227: invokestatic 2698	com/insidesecure/hce/internal/MatrixHCENativeBridge:decryptMdesRnsNotifyTokenUpdated	(Ljava/lang/String;)Ljava/lang/String;
    //   230: astore_1
    //   231: aload_1
    //   232: ifnonnull +6 -> 238
    //   235: goto +755 -> 990
    //   238: goto -149 -> 89
    //   241: goto +187 -> 428
    //   244: goto +443 -> 687
    //   247: aload_1
    //   248: iload 4
    //   250: aaload
    //   251: astore_2
    //   252: aload_0
    //   253: invokevirtual 242	o/pz:ˏ	()Landroid/content/Context;
    //   256: astore 6
    //   258: new 132	android/content/Intent
    //   261: dup
    //   262: sipush 2249
    //   265: sipush 15434
    //   268: bipush 53
    //   270: invokestatic 30	o/pF:ˋ	(ICI)Ljava/lang/String;
    //   273: invokevirtual 36	java/lang/String:intern	()Ljava/lang/String;
    //   276: invokespecial 136	android/content/Intent:<init>	(Ljava/lang/String;)V
    //   279: astore 7
    //   281: aload 7
    //   283: sipush 1220
    //   286: iconst_0
    //   287: bipush 13
    //   289: invokestatic 30	o/pF:ˋ	(ICI)Ljava/lang/String;
    //   292: invokevirtual 36	java/lang/String:intern	()Ljava/lang/String;
    //   295: aload_2
    //   296: invokevirtual 144	android/content/Intent:putExtra	(Ljava/lang/String;Ljava/lang/String;)Landroid/content/Intent;
    //   299: pop
    //   300: aload 6
    //   302: aload 7
    //   304: invokestatic 148	o/pD:sendBroadcast	(Landroid/content/Context;Landroid/content/Intent;)V
    //   307: iload 4
    //   309: iconst_1
    //   310: iadd
    //   311: istore 4
    //   313: goto +118 -> 431
    //   316: aload 7
    //   318: invokevirtual 2702	o/pr:getState	()Lcom/insidesecure/hce/MatrixHCECardState;
    //   321: getstatic 2708	com/insidesecure/hce/MatrixHCECardState:SUSPENDED	Lcom/insidesecure/hce/MatrixHCECardState;
    //   324: invokevirtual 2709	com/insidesecure/hce/MatrixHCECardState:equals	(Ljava/lang/Object;)Z
    //   327: istore 5
    //   329: iload 5
    //   331: ifeq +6 -> 337
    //   334: goto +719 -> 1053
    //   337: goto +186 -> 523
    //   340: aload_0
    //   341: invokevirtual 242	o/pz:ˏ	()Landroid/content/Context;
    //   344: astore_2
    //   345: new 132	android/content/Intent
    //   348: dup
    //   349: sipush 1968
    //   352: iconst_0
    //   353: bipush 53
    //   355: invokestatic 30	o/pF:ˋ	(ICI)Ljava/lang/String;
    //   358: invokevirtual 36	java/lang/String:intern	()Ljava/lang/String;
    //   361: invokespecial 136	android/content/Intent:<init>	(Ljava/lang/String;)V
    //   364: astore 8
    //   366: aload 8
    //   368: sipush 1220
    //   371: iconst_0
    //   372: bipush 13
    //   374: invokestatic 30	o/pF:ˋ	(ICI)Ljava/lang/String;
    //   377: invokevirtual 36	java/lang/String:intern	()Ljava/lang/String;
    //   380: aload 7
    //   382: invokevirtual 2710	o/pr:getCardName	()Ljava/lang/String;
    //   385: invokevirtual 144	android/content/Intent:putExtra	(Ljava/lang/String;Ljava/lang/String;)Landroid/content/Intent;
    //   388: pop
    //   389: aload 8
    //   391: sipush 2021
    //   394: sipush 13418
    //   397: bipush 19
    //   399: invokestatic 30	o/pF:ˋ	(ICI)Ljava/lang/String;
    //   402: invokevirtual 36	java/lang/String:intern	()Ljava/lang/String;
    //   405: aload_1
    //   406: invokevirtual 144	android/content/Intent:putExtra	(Ljava/lang/String;Ljava/lang/String;)Landroid/content/Intent;
    //   409: pop
    //   410: aload_2
    //   411: aload 8
    //   413: invokestatic 148	o/pD:sendBroadcast	(Landroid/content/Context;Landroid/content/Intent;)V
    //   416: goto -235 -> 181
    //   419: astore_0
    //   420: aload_0
    //   421: athrow
    //   422: iconst_1
    //   423: istore 4
    //   425: goto +233 -> 658
    //   428: goto -247 -> 181
    //   431: iload 4
    //   433: iload_3
    //   434: if_icmpge +6 -> 440
    //   437: goto -190 -> 247
    //   440: goto -353 -> 87
    //   443: astore_2
    //   444: getstatic 50	o/pF:ˎ	Ljava/lang/String;
    //   447: new 23	java/lang/StringBuilder
    //   450: dup
    //   451: invokespecial 26	java/lang/StringBuilder:<init>	()V
    //   454: sipush 1796
    //   457: ldc_w 2711
    //   460: bipush 66
    //   462: invokestatic 30	o/pF:ˋ	(ICI)Ljava/lang/String;
    //   465: invokevirtual 36	java/lang/String:intern	()Ljava/lang/String;
    //   468: invokevirtual 40	java/lang/StringBuilder:append	(Ljava/lang/String;)Ljava/lang/StringBuilder;
    //   471: aload_2
    //   472: invokevirtual 2714	org/json/JSONException:getMessage	()Ljava/lang/String;
    //   475: invokevirtual 40	java/lang/StringBuilder:append	(Ljava/lang/String;)Ljava/lang/StringBuilder;
    //   478: invokevirtual 48	java/lang/StringBuilder:toString	()Ljava/lang/String;
    //   481: invokestatic 88	o/pD:e	(Ljava/lang/String;Ljava/lang/String;)V
    //   484: goto +427 -> 911
    //   487: getstatic 17	o/pF:ॱ	I
    //   490: bipush 63
    //   492: iadd
    //   493: istore 4
    //   495: iload 4
    //   497: sipush 128
    //   500: irem
    //   501: putstatic 19	o/pF:ˏ	I
    //   504: iload 4
    //   506: iconst_2
    //   507: irem
    //   508: ifne +6 -> 514
    //   511: goto -270 -> 241
    //   514: goto -86 -> 428
    //   517: iconst_0
    //   518: istore 4
    //   520: goto -512 -> 8
    //   523: getstatic 50	o/pF:ˎ	Ljava/lang/String;
    //   526: sipush 1928
    //   529: iconst_0
    //   530: bipush 40
    //   532: invokestatic 30	o/pF:ˋ	(ICI)Ljava/lang/String;
    //   535: invokevirtual 36	java/lang/String:intern	()Ljava/lang/String;
    //   538: invokestatic 101	o/pD:i	(Ljava/lang/String;Ljava/lang/String;)V
    //   541: aload_0
    //   542: invokevirtual 242	o/pz:ˏ	()Landroid/content/Context;
    //   545: astore_2
    //   546: new 132	android/content/Intent
    //   549: dup
    //   550: sipush 1968
    //   553: iconst_0
    //   554: bipush 53
    //   556: invokestatic 30	o/pF:ˋ	(ICI)Ljava/lang/String;
    //   559: invokevirtual 36	java/lang/String:intern	()Ljava/lang/String;
    //   562: invokespecial 136	android/content/Intent:<init>	(Ljava/lang/String;)V
    //   565: astore 8
    //   567: aload 8
    //   569: sipush 1220
    //   572: iconst_0
    //   573: bipush 13
    //   575: invokestatic 30	o/pF:ˋ	(ICI)Ljava/lang/String;
    //   578: invokevirtual 36	java/lang/String:intern	()Ljava/lang/String;
    //   581: aload 7
    //   583: invokevirtual 2710	o/pr:getCardName	()Ljava/lang/String;
    //   586: invokevirtual 144	android/content/Intent:putExtra	(Ljava/lang/String;Ljava/lang/String;)Landroid/content/Intent;
    //   589: pop
    //   590: aload 8
    //   592: sipush 2021
    //   595: sipush 13418
    //   598: bipush 19
    //   600: invokestatic 30	o/pF:ˋ	(ICI)Ljava/lang/String;
    //   603: invokevirtual 36	java/lang/String:intern	()Ljava/lang/String;
    //   606: aload_1
    //   607: invokevirtual 144	android/content/Intent:putExtra	(Ljava/lang/String;Ljava/lang/String;)Landroid/content/Intent;
    //   610: pop
    //   611: aload_2
    //   612: aload 8
    //   614: invokestatic 148	o/pD:sendBroadcast	(Landroid/content/Context;Landroid/content/Intent;)V
    //   617: goto -436 -> 181
    //   620: iconst_1
    //   621: istore 4
    //   623: goto -615 -> 8
    //   626: aload_1
    //   627: sipush 1645
    //   630: ldc_w 2715
    //   633: bipush 20
    //   635: invokestatic 30	o/pF:ˋ	(ICI)Ljava/lang/String;
    //   638: invokevirtual 36	java/lang/String:intern	()Ljava/lang/String;
    //   641: invokevirtual 84	java/lang/String:equals	(Ljava/lang/Object;)Z
    //   644: ifeq +6 -> 650
    //   647: goto -421 -> 226
    //   650: goto -615 -> 35
    //   653: iconst_0
    //   654: istore_3
    //   655: goto -593 -> 62
    //   658: iload 4
    //   660: tableswitch	default:+24->684, 0:+73->733, 1:+-416->244
    //   684: goto +49 -> 733
    //   687: getstatic 17	o/pF:ॱ	I
    //   690: bipush 95
    //   692: iadd
    //   693: istore_3
    //   694: iload_3
    //   695: sipush 128
    //   698: irem
    //   699: putstatic 19	o/pF:ˏ	I
    //   702: iload_3
    //   703: iconst_2
    //   704: irem
    //   705: ifne +6 -> 711
    //   708: goto +526 -> 1234
    //   711: goto +518 -> 1229
    //   714: aload 6
    //   716: invokevirtual 2720	org/json/JSONArray:length	()I
    //   719: istore 4
    //   721: iload_3
    //   722: iload 4
    //   724: if_icmpge +6 -> 730
    //   727: goto +496 -> 1223
    //   730: goto -308 -> 422
    //   733: aload 6
    //   735: iload_3
    //   736: invokevirtual 2723	org/json/JSONArray:getJSONObject	(I)Lorg/json/JSONObject;
    //   739: astore_2
    //   740: aload_2
    //   741: sipush 1714
    //   744: sipush 25603
    //   747: bipush 20
    //   749: invokestatic 30	o/pF:ˋ	(ICI)Ljava/lang/String;
    //   752: invokevirtual 36	java/lang/String:intern	()Ljava/lang/String;
    //   755: invokevirtual 194	org/json/JSONObject:getString	(Ljava/lang/String;)Ljava/lang/String;
    //   758: astore_1
    //   759: aload_2
    //   760: sipush 1734
    //   763: sipush 18108
    //   766: bipush 6
    //   768: invokestatic 30	o/pF:ˋ	(ICI)Ljava/lang/String;
    //   771: invokevirtual 36	java/lang/String:intern	()Ljava/lang/String;
    //   774: invokevirtual 194	org/json/JSONObject:getString	(Ljava/lang/String;)Ljava/lang/String;
    //   777: astore 8
    //   779: aload_0
    //   780: aload_1
    //   781: invokestatic 2726	o/pF:ॱ	(Lo/pz;Ljava/lang/String;)Lcom/insidesecure/hce/MatrixHCECard;
    //   784: checkcast 257	o/pr
    //   787: astore 7
    //   789: aload 7
    //   791: ifnonnull +6 -> 797
    //   794: goto -606 -> 188
    //   797: goto +88 -> 885
    //   800: aload 8
    //   802: sipush 2113
    //   805: iconst_0
    //   806: bipush 11
    //   808: invokestatic 30	o/pF:ˋ	(ICI)Ljava/lang/String;
    //   811: invokevirtual 36	java/lang/String:intern	()Ljava/lang/String;
    //   814: invokevirtual 84	java/lang/String:equals	(Ljava/lang/Object;)Z
    //   817: istore 5
    //   819: iload 5
    //   821: ifeq +6 -> 827
    //   824: goto +6 -> 830
    //   827: goto -487 -> 340
    //   830: aload_0
    //   831: invokevirtual 242	o/pz:ˏ	()Landroid/content/Context;
    //   834: astore_1
    //   835: new 132	android/content/Intent
    //   838: dup
    //   839: sipush 2124
    //   842: iconst_0
    //   843: bipush 57
    //   845: invokestatic 30	o/pF:ˋ	(ICI)Ljava/lang/String;
    //   848: invokevirtual 36	java/lang/String:intern	()Ljava/lang/String;
    //   851: invokespecial 136	android/content/Intent:<init>	(Ljava/lang/String;)V
    //   854: astore_2
    //   855: aload_2
    //   856: sipush 1220
    //   859: iconst_0
    //   860: bipush 13
    //   862: invokestatic 30	o/pF:ˋ	(ICI)Ljava/lang/String;
    //   865: invokevirtual 36	java/lang/String:intern	()Ljava/lang/String;
    //   868: aload 7
    //   870: invokevirtual 2710	o/pr:getCardName	()Ljava/lang/String;
    //   873: invokevirtual 144	android/content/Intent:putExtra	(Ljava/lang/String;Ljava/lang/String;)Landroid/content/Intent;
    //   876: pop
    //   877: aload_1
    //   878: aload_2
    //   879: invokestatic 148	o/pD:sendBroadcast	(Landroid/content/Context;Landroid/content/Intent;)V
    //   882: goto -701 -> 181
    //   885: aconst_null
    //   886: astore_1
    //   887: aload_2
    //   888: sipush 1787
    //   891: sipush 2801
    //   894: bipush 9
    //   896: invokestatic 30	o/pF:ˋ	(ICI)Ljava/lang/String;
    //   899: invokevirtual 36	java/lang/String:intern	()Ljava/lang/String;
    //   902: invokevirtual 190	org/json/JSONObject:getJSONObject	(Ljava/lang/String;)Lorg/json/JSONObject;
    //   905: invokevirtual 2727	org/json/JSONObject:toString	()Ljava/lang/String;
    //   908: astore_2
    //   909: aload_2
    //   910: astore_1
    //   911: aload 8
    //   913: sipush 1862
    //   916: iconst_0
    //   917: bipush 6
    //   919: invokestatic 30	o/pF:ˋ	(ICI)Ljava/lang/String;
    //   922: invokevirtual 36	java/lang/String:intern	()Ljava/lang/String;
    //   925: invokevirtual 84	java/lang/String:equals	(Ljava/lang/Object;)Z
    //   928: istore 5
    //   930: iload 5
    //   932: ifeq +6 -> 938
    //   935: goto -315 -> 620
    //   938: goto -421 -> 517
    //   941: goto -315 -> 626
    //   944: aload_2
    //   945: invokestatic 2695	com/insidesecure/hce/internal/MatrixHCENativeBridge:processMdesRnsPushTransactionDetails	(Ljava/lang/String;)[Ljava/lang/String;
    //   948: astore_1
    //   949: aload_1
    //   950: arraylength
    //   951: istore_3
    //   952: iconst_0
    //   953: istore 4
    //   955: goto -524 -> 431
    //   958: aload 8
    //   960: sipush 2040
    //   963: sipush 20954
    //   966: bipush 9
    //   968: invokestatic 30	o/pF:ˋ	(ICI)Ljava/lang/String;
    //   971: invokevirtual 36	java/lang/String:intern	()Ljava/lang/String;
    //   974: invokevirtual 84	java/lang/String:equals	(Ljava/lang/Object;)Z
    //   977: istore 5
    //   979: iload 5
    //   981: ifeq +6 -> 987
    //   984: goto +139 -> 1123
    //   987: goto -187 -> 800
    //   990: getstatic 50	o/pF:ˎ	Ljava/lang/String;
    //   993: sipush 1665
    //   996: ldc_w 2728
    //   999: bipush 43
    //   1001: invokestatic 30	o/pF:ˋ	(ICI)Ljava/lang/String;
    //   1004: invokevirtual 36	java/lang/String:intern	()Ljava/lang/String;
    //   1007: invokestatic 88	o/pD:e	(Ljava/lang/String;Ljava/lang/String;)V
    //   1010: iconst_0
    //   1011: ireturn
    //   1012: astore_0
    //   1013: getstatic 50	o/pF:ˎ	Ljava/lang/String;
    //   1016: new 23	java/lang/StringBuilder
    //   1019: dup
    //   1020: invokespecial 26	java/lang/StringBuilder:<init>	()V
    //   1023: sipush 2181
    //   1026: iconst_0
    //   1027: bipush 44
    //   1029: invokestatic 30	o/pF:ˋ	(ICI)Ljava/lang/String;
    //   1032: invokevirtual 36	java/lang/String:intern	()Ljava/lang/String;
    //   1035: invokevirtual 40	java/lang/StringBuilder:append	(Ljava/lang/String;)Ljava/lang/StringBuilder;
    //   1038: aload_0
    //   1039: invokevirtual 2714	org/json/JSONException:getMessage	()Ljava/lang/String;
    //   1042: invokevirtual 40	java/lang/StringBuilder:append	(Ljava/lang/String;)Ljava/lang/StringBuilder;
    //   1045: invokevirtual 48	java/lang/StringBuilder:toString	()Ljava/lang/String;
    //   1048: invokestatic 88	o/pD:e	(Ljava/lang/String;Ljava/lang/String;)V
    //   1051: iconst_0
    //   1052: ireturn
    //   1053: getstatic 50	o/pF:ˎ	Ljava/lang/String;
    //   1056: new 23	java/lang/StringBuilder
    //   1059: dup
    //   1060: invokespecial 26	java/lang/StringBuilder:<init>	()V
    //   1063: sipush 1868
    //   1066: sipush 12305
    //   1069: bipush 33
    //   1071: invokestatic 30	o/pF:ˋ	(ICI)Ljava/lang/String;
    //   1074: invokevirtual 36	java/lang/String:intern	()Ljava/lang/String;
    //   1077: invokevirtual 40	java/lang/StringBuilder:append	(Ljava/lang/String;)Ljava/lang/StringBuilder;
    //   1080: aload 7
    //   1082: invokevirtual 2710	o/pr:getCardName	()Ljava/lang/String;
    //   1085: invokevirtual 40	java/lang/StringBuilder:append	(Ljava/lang/String;)Ljava/lang/StringBuilder;
    //   1088: invokevirtual 48	java/lang/StringBuilder:toString	()Ljava/lang/String;
    //   1091: invokestatic 101	o/pD:i	(Ljava/lang/String;Ljava/lang/String;)V
    //   1094: aload 7
    //   1096: getstatic 2734	com/insidesecure/hce/MatrixHCECardSuspendedState:CARD_STATE_NOT_SUSPENDED	Lcom/insidesecure/hce/MatrixHCECardSuspendedState;
    //   1099: invokevirtual 2738	o/pr:setCardSuspendedState	(Lcom/insidesecure/hce/MatrixHCECardSuspendedState;)Z
    //   1102: pop
    //   1103: aload 7
    //   1105: sipush 1901
    //   1108: iconst_0
    //   1109: bipush 27
    //   1111: invokestatic 30	o/pF:ˋ	(ICI)Ljava/lang/String;
    //   1114: invokevirtual 36	java/lang/String:intern	()Ljava/lang/String;
    //   1117: invokevirtual 2740	o/pr:ˎ	(Ljava/lang/String;)V
    //   1120: goto -939 -> 181
    //   1123: getstatic 50	o/pF:ˎ	Ljava/lang/String;
    //   1126: new 23	java/lang/StringBuilder
    //   1129: dup
    //   1130: invokespecial 26	java/lang/StringBuilder:<init>	()V
    //   1133: sipush 2049
    //   1136: sipush 14430
    //   1139: bipush 36
    //   1141: invokestatic 30	o/pF:ˋ	(ICI)Ljava/lang/String;
    //   1144: invokevirtual 36	java/lang/String:intern	()Ljava/lang/String;
    //   1147: invokevirtual 40	java/lang/StringBuilder:append	(Ljava/lang/String;)Ljava/lang/StringBuilder;
    //   1150: aload 7
    //   1152: invokevirtual 2710	o/pr:getCardName	()Ljava/lang/String;
    //   1155: invokevirtual 40	java/lang/StringBuilder:append	(Ljava/lang/String;)Ljava/lang/StringBuilder;
    //   1158: invokevirtual 48	java/lang/StringBuilder:toString	()Ljava/lang/String;
    //   1161: invokestatic 101	o/pD:i	(Ljava/lang/String;Ljava/lang/String;)V
    //   1164: aload 7
    //   1166: getstatic 2743	com/insidesecure/hce/MatrixHCECardSuspendedState:CARD_STATE_SUSPENDED	Lcom/insidesecure/hce/MatrixHCECardSuspendedState;
    //   1169: invokevirtual 2738	o/pr:setCardSuspendedState	(Lcom/insidesecure/hce/MatrixHCECardSuspendedState;)Z
    //   1172: pop
    //   1173: aload 7
    //   1175: sipush 2085
    //   1178: iconst_0
    //   1179: bipush 28
    //   1181: invokestatic 30	o/pF:ˋ	(ICI)Ljava/lang/String;
    //   1184: invokevirtual 36	java/lang/String:intern	()Ljava/lang/String;
    //   1187: invokevirtual 2740	o/pr:ˎ	(Ljava/lang/String;)V
    //   1190: goto -703 -> 487
    //   1193: getstatic 17	o/pF:ॱ	I
    //   1196: bipush 59
    //   1198: iadd
    //   1199: istore_3
    //   1200: iload_3
    //   1201: sipush 128
    //   1204: irem
    //   1205: putstatic 19	o/pF:ˏ	I
    //   1208: iload_3
    //   1209: iconst_2
    //   1210: irem
    //   1211: ifne +6 -> 1217
    //   1214: goto -1211 -> 3
    //   1217: goto -564 -> 653
    //   1220: goto -506 -> 714
    //   1223: iconst_0
    //   1224: istore 4
    //   1226: goto -568 -> 658
    //   1229: iconst_1
    //   1230: ireturn
    //   1231: astore_0
    //   1232: aload_0
    //   1233: athrow
    //   1234: goto -5 -> 1229
    // Local variable table:
    //   start	length	slot	name	signature
    //   0	1237	0	paramPz	pz
    //   0	1237	1	paramString1	String
    //   0	1237	2	paramString2	String
    //   4	1207	3	i	int
    //   8	1217	4	j	int
    //   327	653	5	bool	boolean
    //   112	622	6	localObject1	Object
    //   279	895	7	localObject2	Object
    //   364	595	8	localObject3	Object
    // Exception table:
    //   from	to	target	type
    //   119	131	419	java/lang/Exception
    //   131	144	419	java/lang/Exception
    //   144	151	419	java/lang/Exception
    //   151	168	419	java/lang/Exception
    //   887	909	443	org/json/JSONException
    //   89	114	1012	org/json/JSONException
    //   188	223	1012	org/json/JSONException
    //   316	329	1012	org/json/JSONException
    //   340	416	1012	org/json/JSONException
    //   444	484	1012	org/json/JSONException
    //   523	617	1012	org/json/JSONException
    //   714	721	1012	org/json/JSONException
    //   733	789	1012	org/json/JSONException
    //   800	819	1012	org/json/JSONException
    //   830	882	1012	org/json/JSONException
    //   911	930	1012	org/json/JSONException
    //   958	979	1012	org/json/JSONException
    //   1053	1120	1012	org/json/JSONException
    //   1123	1190	1012	org/json/JSONException
    //   131	144	1231	java/lang/Exception
  }
  
  private static MatrixHCECard ॱ(pz paramPz, String paramString)
  {
    break label231;
    paramPz = paramPz.getCards(null).iterator();
    break label75;
    label22:
    label48:
    do
    {
      i = 1;
      break label85;
      i = ˏ + 1;
      ॱ = i % 128;
      if (i % 2 != 0) {
        break label119;
      }
      break;
      i = ˏ + 35;
      ॱ = i % 128;
    } while (i % 2 != 0);
    break label83;
    label75:
    break label234;
    label78:
    int i = 0;
    break label168;
    label83:
    i = 0;
    switch (i)
    {
    default: 
      label85:
      break;
    }
    for (;;)
    {
      return null;
      Object localObject;
      return localObject;
      label119:
      break;
      try
      {
        localObject = paramPz.next();
        localObject = (MatrixHCECard)localObject;
        String str = ((MatrixHCECard)localObject).getTokenReferenceId();
        bool = str.equals(paramString);
        if (bool) {
          return localObject;
        }
      }
      catch (Exception paramPz)
      {
        throw paramPz;
      }
      label168:
      do
      {
        i = 1;
        switch (i)
        {
        }
        break;
        localObject = (MatrixHCECard)paramPz.next();
        bool = ((MatrixHCECard)localObject).getTokenReferenceId().equals(paramString);
        i = null.length;
      } while (bool);
      break label78;
      label231:
      break label22;
      label234:
      boolean bool = paramPz.hasNext();
      if (bool) {
        break label48;
      }
    }
  }
}
