package o;

import com.insidesecure.hce.MatrixHCEError;
import com.insidesecure.hce.MatrixHCEException;
import com.insidesecure.hce.MatrixHCENetworkData;
import com.insidesecure.hce.MatrixHCENetworkOperationCallback;
import com.insidesecure.hce.NetworkOperationPreparationInfo.NetworkOperation;

public class ph
  extends pk
{
  private static int ʻ = 0;
  private static char[] ˊ = { 48, 98, 99, 105, 114, 113, 113, 74, 71, 106, 67, 74, 118, 116, 106, 66, 33, 57, 76, 75, 55, 71, 110, 113, 74, 73, 116, 114, 112, 111, 112, 115, 108, 100, 66, 67, 106, 112, 73, 90, 79, 178, 195, 190, 196, 200, 198, 197, 158, 163, 195, 200, 206, 196, 196, 204, 165, 160, 195, 202, 209, 164, 159, 201, 164, 162, 201, 204, 165, 164, 207, 205, 203, 202, 203, 206, 199, 191, 157, 158, 197, 203, 164, 155, 189, 190, 196, 205, 204, 204, 165, 162, 197, 158, 165, 209, 207, 197, 157, 124 };
  private static int ᐝ = 1;
  
  public ph(String paramString1, String paramString2, String paramString3, String paramString4, String paramString5, long paramLong) {}
  
  private static String ˋ(int[] paramArrayOfInt, byte[] paramArrayOfByte, boolean paramBoolean)
  {
    break label559;
    char[] arrayOfChar2;
    int j;
    char[] arrayOfChar1;
    int i;
    arrayOfChar2[j] = ((char)((arrayOfChar1[j] << '\001') - i));
    int i1;
    label32:
    label50:
    label53:
    int k;
    label94:
    int m;
    if (i1 <= 0)
    {
      break label143;
      paramArrayOfByte[i] = ((char)(paramArrayOfByte[i] - paramArrayOfInt[2]));
      i += 1;
      break label568;
      break label149;
      switch (k)
      {
      default: 
        break;
        label105:
        for (;;)
        {
          i = arrayOfChar2[j];
          j += 1;
          break;
          arrayOfChar1 = new char[m];
          i = 0;
          break label655;
        }
        j = 0;
        break label627;
        for (;;)
        {
          switch (i)
          {
          default: 
            label114:
            break label255;
            label143:
            i = 6;
          }
        }
      }
      for (;;)
      {
        label149:
        if (paramArrayOfByte[j] != 1)
        {
          break;
          arrayOfChar1 = new char[m];
          System.arraycopy(paramArrayOfByte, 0, arrayOfChar1, 0, m);
          System.arraycopy(arrayOfChar1, 0, paramArrayOfByte, m - i1, i1);
          System.arraycopy(arrayOfChar1, i1, paramArrayOfByte, 0, m - i1);
          break label392;
          if (j >= m)
          {
            break label403;
            for (;;)
            {
              label223:
              i = 0;
              break label568;
              i = ʻ + 13;
              ᐝ = i % 128;
              if (i % 2 == 0) {
                break;
              }
            }
            label255:
            if (paramBoolean) {
              break label94;
            }
            break label496;
            paramArrayOfByte = arrayOfChar2;
            break label565;
          }
          k = 1;
          break label53;
          k = ʻ + 85;
          ᐝ = k % 128;
          if (k % 2 == 0) {
            break label50;
          }
          continue;
          label307:
          paramArrayOfByte = arrayOfChar1;
        }
      }
    }
    for (;;)
    {
      j = 82;
      label329:
      label338:
      label392:
      label395:
      label400:
      label403:
      label428:
      label496:
      label559:
      label562:
      label565:
      label568:
      do
      {
        j = 1;
        break label627;
        break label223;
        return new String(paramArrayOfByte);
        int n;
        for (;;)
        {
          i = paramArrayOfInt[0];
          m = paramArrayOfInt[1];
          n = paramArrayOfInt[2];
          i1 = paramArrayOfInt[3];
          arrayOfChar2 = ˊ;
          arrayOfChar1 = new char[m];
          System.arraycopy(arrayOfChar2, i, arrayOfChar1, 0, m);
          if (paramArrayOfByte != null) {
            break label587;
          }
          paramArrayOfByte = arrayOfChar1;
          break;
          break label255;
          i = 0;
          break label601;
        }
        k = 0;
        break label53;
        arrayOfChar1[i] = paramArrayOfByte[(m - i - 1)];
        i += 1;
        break label655;
        i = 1;
        break label601;
        i = 13;
        break label114;
        for (;;)
        {
          i = ʻ + 15;
          ᐝ = i % 128;
          if (i % 2 == 0) {
            break label400;
          }
          break label338;
          j = ᐝ + 19;
          ʻ = j % 128;
          if (j % 2 != 0) {
            break label562;
          }
          break;
          if (n > 0) {
            break label395;
          }
          break label428;
          arrayOfChar2[j] = ((char)((arrayOfChar1[j] << '\001') + 1 - i));
          break label105;
          switch (j)
          {
          }
          break label307;
        }
        break label32;
        break;
      } while (i < m);
      label587:
      label601:
      label627:
      label655:
      while (i < m)
      {
        for (;;)
        {
          j = 89;
        }
        arrayOfChar2 = new char[m];
        i = 0;
        j = 0;
        break;
        switch (i)
        {
        }
        break label329;
        switch (j)
        {
        }
        break label329;
      }
    }
  }
  
  public void clearNetworkSession()
  {
    for (;;)
    {
      switch (i)
      {
      default: 
        return;
      case 1: 
        do
        {
          i = 1;
          break label6;
          i = null.length;
          return;
          break;
          i = ᐝ + 93;
          ʻ = i % 128;
        } while (i % 2 != 0);
        break;
      case 0: 
        label6:
        return;
      }
      int i = 0;
    }
  }
  
  public void clearPaymentKeys()
  {
    throw new MatrixHCEException(ˋ(new int[] { 40, 60, 91, 0 }, new byte[] { 0, 1, 1, 0, 1, 1, 1, 1, 1, 0, 1, 0, 0, 0, 1, 0, 0, 1, 0, 0, 0, 1, 1, 0, 1, 0, 1, 1, 0, 1, 0, 1, 0, 1, 1, 0, 1, 1, 0, 0, 1, 1, 0, 1, 0, 0, 0, 0, 1, 0, 0, 1, 1, 0, 0, 1, 1, 1, 1, 0 }, false).intern() + this.ˎ + ˋ(new int[] { 39, 1, 147, 1 }, new byte[] { 1 }, false).intern(), MatrixHCEError.UNSUPPORTED);
  }
  
  public byte[] getEncryptedPin(byte[] paramArrayOfByte)
  {
    for (;;)
    {
      throw new MatrixHCEException(ˋ(new int[] { 0, 39, 0, 17 }, new byte[] { 1, 0, 0, 0, 0, 1, 0, 0, 1, 1, 0, 0, 1, 1, 1, 1, 0, 0, 1, 1, 0, 0, 1, 1, 0, 1, 0, 1, 0, 1, 1, 0, 1, 1, 0, 0, 1, 1, 0 }, false).intern() + this.ˎ + ˋ(new int[] { 39, 1, 147, 1 }, new byte[] { 1 }, false).intern(), MatrixHCEError.UNSUPPORTED);
    }
  }
  
  public long getNetworkSessionValidity()
  {
    int i;
    for (;;)
    {
      switch (i)
      {
      case 5: 
      default: 
        throw new NullPointerException();
        break label57;
        label43:
        i = 5;
      }
    }
    for (;;)
    {
      i = 39;
      break;
      break label84;
      label57:
      i = ʻ + 15;
      ᐝ = i % 128;
      if (i % 2 == 0) {
        break label43;
      }
    }
    label84:
    return -1L;
  }
  
  /* Error */
  public MatrixHCENetworkData openNetworkSession()
  {
    // Byte code:
    //   0: goto +35 -> 35
    //   3: iload_1
    //   4: lookupswitch	default:+28->32, 30:+100->104, 81:+43->47
    //   32: goto +15 -> 47
    //   35: goto +49 -> 84
    //   38: astore_2
    //   39: aload_2
    //   40: athrow
    //   41: bipush 30
    //   43: istore_1
    //   44: goto -41 -> 3
    //   47: bipush 18
    //   49: iconst_0
    //   50: idiv
    //   51: istore_1
    //   52: aload_2
    //   53: areturn
    //   54: astore_2
    //   55: aload_2
    //   56: athrow
    //   57: getstatic 13	o/ph:ʻ	I
    //   60: bipush 111
    //   62: iadd
    //   63: istore_1
    //   64: iload_1
    //   65: sipush 128
    //   68: irem
    //   69: putstatic 15	o/ph:ᐝ	I
    //   72: iload_1
    //   73: iconst_2
    //   74: irem
    //   75: ifne +6 -> 81
    //   78: goto +28 -> 106
    //   81: goto -40 -> 41
    //   84: new 141	com/insidesecure/hce/MatrixHCENetworkData
    //   87: dup
    //   88: getstatic 147	com/insidesecure/hce/NetworkOperationPreparationInfo$NetworkOperation:MASTERCARD_REQUEST_SESSION	Lcom/insidesecure/hce/NetworkOperationPreparationInfo$NetworkOperation;
    //   91: getstatic 123	com/insidesecure/hce/MatrixHCEError:UNSUPPORTED	Lcom/insidesecure/hce/MatrixHCEError;
    //   94: aconst_null
    //   95: aconst_null
    //   96: aconst_null
    //   97: invokespecial 150	com/insidesecure/hce/MatrixHCENetworkData:<init>	(Lcom/insidesecure/hce/NetworkOperationPreparationInfo$NetworkOperation;Lcom/insidesecure/hce/MatrixHCEError;[BLjava/lang/String;Ljava/lang/String;)V
    //   100: astore_2
    //   101: goto -44 -> 57
    //   104: aload_2
    //   105: areturn
    //   106: bipush 81
    //   108: istore_1
    //   109: goto -106 -> 3
    // Local variable table:
    //   start	length	slot	name	signature
    //   0	112	0	this	ph
    //   3	106	1	i	int
    //   38	15	2	localException1	Exception
    //   54	2	2	localException2	Exception
    //   100	5	2	localMatrixHCENetworkData	MatrixHCENetworkData
    // Exception table:
    //   from	to	target	type
    //   64	72	38	java/lang/Exception
    //   57	64	54	java/lang/Exception
    //   64	72	54	java/lang/Exception
  }
  
  @Deprecated
  public MatrixHCENetworkData registerAccountToServer(String paramString1, String paramString2)
  {
    try
    {
      paramString1 = NetworkOperationPreparationInfo.NetworkOperation.UNKNOWN;
      paramString1 = new MatrixHCENetworkData(paramString1, MatrixHCEError.UNSUPPORTED, null, null, null);
    }
    catch (Exception paramString1)
    {
      throw paramString1;
    }
    int i = ʻ + 41;
    ᐝ = i % 128;
    if (i % 2 == 0) {
      return paramString1;
    }
    return paramString1;
  }
  
  public MatrixHCENetworkData registerAccountToServer(String paramString, byte[] paramArrayOfByte)
  {
    for (;;)
    {
      int i = ʻ + 33;
      ᐝ = i % 128;
      if (i % 2 != 0)
      {
        return paramString;
        try
        {
          paramString = NetworkOperationPreparationInfo.NetworkOperation.UNKNOWN;
          paramString = new MatrixHCENetworkData(paramString, MatrixHCEError.UNSUPPORTED, null, null, null);
        }
        catch (Exception paramString)
        {
          throw paramString;
        }
      }
    }
    return paramString;
  }
  
  /* Error */
  @Deprecated
  public void registerAccountToServer(String paramString1, String paramString2, MatrixHCENetworkOperationCallback paramMatrixHCENetworkOperationCallback)
  {
    // Byte code:
    //   0: goto +43 -> 43
    //   3: getstatic 13	o/ph:ʻ	I
    //   6: bipush 25
    //   8: iadd
    //   9: istore 4
    //   11: iload 4
    //   13: sipush 128
    //   16: irem
    //   17: putstatic 15	o/ph:ᐝ	I
    //   20: iload 4
    //   22: iconst_2
    //   23: irem
    //   24: ifne +6 -> 30
    //   27: goto +167 -> 194
    //   30: goto +6 -> 36
    //   33: astore_1
    //   34: aload_1
    //   35: athrow
    //   36: iconst_0
    //   37: istore 4
    //   39: goto +114 -> 153
    //   42: return
    //   43: goto -40 -> 3
    //   46: iload 4
    //   48: lookupswitch	default:+28->76, 74:+-6->42, 93:+138->186
    //   76: goto +110 -> 186
    //   79: aload_3
    //   80: getstatic 162	com/insidesecure/hce/NetworkOperationPreparationInfo$NetworkOperation:MASTERCARD_REGISTER_TO_SERVER	Lcom/insidesecure/hce/NetworkOperationPreparationInfo$NetworkOperation;
    //   83: aload_0
    //   84: getfield 114	o/ph:ˎ	Ljava/lang/String;
    //   87: invokestatic 166	o/ph:unsupportedNetworkOperation	(Lcom/insidesecure/hce/MatrixHCENetworkOperationCallback;Lcom/insidesecure/hce/NetworkOperationPreparationInfo$NetworkOperation;Ljava/lang/String;)V
    //   90: goto +29 -> 119
    //   93: aload_3
    //   94: getstatic 162	com/insidesecure/hce/NetworkOperationPreparationInfo$NetworkOperation:MASTERCARD_REGISTER_TO_SERVER	Lcom/insidesecure/hce/NetworkOperationPreparationInfo$NetworkOperation;
    //   97: aload_0
    //   98: getfield 114	o/ph:ˎ	Ljava/lang/String;
    //   101: invokestatic 166	o/ph:unsupportedNetworkOperation	(Lcom/insidesecure/hce/MatrixHCENetworkOperationCallback;Lcom/insidesecure/hce/NetworkOperationPreparationInfo$NetworkOperation;Ljava/lang/String;)V
    //   104: new 132	java/lang/NullPointerException
    //   107: dup
    //   108: invokespecial 133	java/lang/NullPointerException:<init>	()V
    //   111: athrow
    //   112: bipush 93
    //   114: istore 4
    //   116: goto -70 -> 46
    //   119: getstatic 13	o/ph:ʻ	I
    //   122: istore 4
    //   124: iload 4
    //   126: bipush 107
    //   128: iadd
    //   129: istore 4
    //   131: iload 4
    //   133: sipush 128
    //   136: irem
    //   137: putstatic 15	o/ph:ᐝ	I
    //   140: iload 4
    //   142: iconst_2
    //   143: irem
    //   144: ifne +6 -> 150
    //   147: goto -35 -> 112
    //   150: goto +29 -> 179
    //   153: iload 4
    //   155: tableswitch	default:+21->176, 0:+-76->79, 1:+-62->93
    //   176: goto -83 -> 93
    //   179: bipush 74
    //   181: istore 4
    //   183: goto -137 -> 46
    //   186: new 132	java/lang/NullPointerException
    //   189: dup
    //   190: invokespecial 133	java/lang/NullPointerException:<init>	()V
    //   193: athrow
    //   194: iconst_1
    //   195: istore 4
    //   197: goto -44 -> 153
    // Local variable table:
    //   start	length	slot	name	signature
    //   0	200	0	this	ph
    //   0	200	1	paramString1	String
    //   0	200	2	paramString2	String
    //   0	200	3	paramMatrixHCENetworkOperationCallback	MatrixHCENetworkOperationCallback
    //   9	187	4	i	int
    // Exception table:
    //   from	to	target	type
    //   119	124	33	java/lang/Exception
    //   131	140	33	java/lang/Exception
  }
  
  public void registerAccountToServer(String paramString, byte[] paramArrayOfByte, MatrixHCENetworkOperationCallback paramMatrixHCENetworkOperationCallback)
  {
    int i = ᐝ + 67;
    ʻ = i % 128;
    if (i % 2 == 0) {
      unsupportedNetworkOperation(paramMatrixHCENetworkOperationCallback, NetworkOperationPreparationInfo.NetworkOperation.MASTERCARD_REGISTER_TO_SERVER, this.ˎ);
    }
    do
    {
      return;
      break;
      i = ʻ + 119;
      ᐝ = i % 128;
    } while (i % 2 == 0);
  }
  
  @Deprecated
  public MatrixHCENetworkData signIn(String paramString1, String paramString2)
  {
    for (;;)
    {
      try
      {
        int i = ᐝ;
        i += 3;
        ʻ = i % 128;
        if (i % 2 != 0) {
          return paramString1;
        }
        return paramString1;
      }
      catch (Exception paramString1)
      {
        throw paramString1;
      }
      paramString1 = new MatrixHCENetworkData(NetworkOperationPreparationInfo.NetworkOperation.MAP_SIGN_IN, MatrixHCEError.UNSUPPORTED, null, null, null);
    }
  }
  
  /* Error */
  public MatrixHCENetworkData signIn(String paramString, byte[] paramArrayOfByte)
  {
    // Byte code:
    //   0: goto +31 -> 31
    //   3: getstatic 15	o/ph:ᐝ	I
    //   6: bipush 67
    //   8: iadd
    //   9: istore_3
    //   10: iload_3
    //   11: sipush 128
    //   14: irem
    //   15: putstatic 13	o/ph:ʻ	I
    //   18: iload_3
    //   19: iconst_2
    //   20: irem
    //   21: ifeq +6 -> 27
    //   24: goto +5 -> 29
    //   27: aload_1
    //   28: areturn
    //   29: aload_1
    //   30: areturn
    //   31: goto +6 -> 37
    //   34: astore_1
    //   35: aload_1
    //   36: athrow
    //   37: getstatic 171	com/insidesecure/hce/NetworkOperationPreparationInfo$NetworkOperation:MAP_SIGN_IN	Lcom/insidesecure/hce/NetworkOperationPreparationInfo$NetworkOperation;
    //   40: astore_1
    //   41: getstatic 123	com/insidesecure/hce/MatrixHCEError:UNSUPPORTED	Lcom/insidesecure/hce/MatrixHCEError;
    //   44: astore_2
    //   45: new 141	com/insidesecure/hce/MatrixHCENetworkData
    //   48: dup
    //   49: aload_1
    //   50: aload_2
    //   51: aconst_null
    //   52: aconst_null
    //   53: aconst_null
    //   54: invokespecial 150	com/insidesecure/hce/MatrixHCENetworkData:<init>	(Lcom/insidesecure/hce/NetworkOperationPreparationInfo$NetworkOperation;Lcom/insidesecure/hce/MatrixHCEError;[BLjava/lang/String;Ljava/lang/String;)V
    //   57: astore_1
    //   58: goto -55 -> 3
    // Local variable table:
    //   start	length	slot	name	signature
    //   0	61	0	this	ph
    //   0	61	1	paramString	String
    //   0	61	2	paramArrayOfByte	byte[]
    //   9	12	3	i	int
    // Exception table:
    //   from	to	target	type
    //   37	41	34	java/lang/Exception
    //   41	45	34	java/lang/Exception
  }
  
  @Deprecated
  public void signIn(MatrixHCENetworkOperationCallback paramMatrixHCENetworkOperationCallback, String paramString1, String paramString2)
  {
    int i;
    for (;;)
    {
      i = 1;
      break label84;
      unsupportedNetworkOperation(paramMatrixHCENetworkOperationCallback, NetworkOperationPreparationInfo.NetworkOperation.MAP_SIGN_IN, this.ˎ);
      break;
      i = ᐝ + 49;
      ʻ = i % 128;
      if (i % 2 == 0) {
        break label128;
      }
    }
    for (;;)
    {
      try
      {
        i = ʻ + 89;
        ᐝ = i % 128;
        if (i % 2 == 0) {
          break;
        }
        return;
      }
      catch (Exception paramMatrixHCENetworkOperationCallback)
      {
        label84:
        label128:
        throw paramMatrixHCENetworkOperationCallback;
      }
      switch (i)
      {
      }
      unsupportedNetworkOperation(paramMatrixHCENetworkOperationCallback, NetworkOperationPreparationInfo.NetworkOperation.MAP_SIGN_IN, this.ˎ);
      i = 65 / 0;
      continue;
      i = 0;
    }
  }
  
  public void signIn(MatrixHCENetworkOperationCallback paramMatrixHCENetworkOperationCallback, String paramString, byte[] paramArrayOfByte)
  {
    for (;;)
    {
      i = ᐝ + 25;
      ʻ = i % 128;
      if (i % 2 != 0) {
        break;
      }
      break;
    }
    break label45;
    int i = 0;
    break label70;
    try
    {
      label45:
      paramArrayOfByte = NetworkOperationPreparationInfo.NetworkOperation.MAP_SIGN_IN;
      return;
    }
    catch (Exception paramMatrixHCENetworkOperationCallback)
    {
      try
      {
        paramString = this.ˎ;
        unsupportedNetworkOperation(paramMatrixHCENetworkOperationCallback, paramArrayOfByte, paramString);
      }
      catch (Exception paramMatrixHCENetworkOperationCallback)
      {
        throw paramMatrixHCENetworkOperationCallback;
      }
      paramMatrixHCENetworkOperationCallback = paramMatrixHCENetworkOperationCallback;
      throw paramMatrixHCENetworkOperationCallback;
    }
    for (;;)
    {
      switch (i)
      {
      case 0: 
      default: 
        return;
        i = ʻ + 67;
        ᐝ = i % 128;
        if (i % 2 == 0) {}
        break;
      case 1: 
        label70:
        throw new NullPointerException();
        i = 1;
      }
    }
  }
}
