package o;

public class pI
  extends pH
{
  private static int ˊ;
  private static final String ˋ;
  private static long ˎ;
  private static char[] ˏ;
  private static int ॱ;
  
  static
  {
    int i;
    do
    {
      return;
      ˊ = 0;
      ॱ = 1;
      ˊ();
      ˋ = ˋ(575, '\000', 19).intern() + pI.class.getSimpleName();
      i = ॱ + 107;
      ˊ = i % 128;
    } while (i % 2 != 0);
  }
  
  public pI() {}
  
  static void ˊ()
  {
    ˎ = -2485533835970195895L;
    ˏ = new char[] { 25094, 11364, -338, -30492, 23299, -6825, -18539, 16791, 4211, -23891, 27891, 16159, -13999, -25714, 9622, -2964, -31056, 20720, -7420, -21180, 32665, 2513, -10206, 27367, 13555, -14591, -28345, 9112, -4641, -17308, 20136, 6392, -21688, 30024, 1948, -11885, 24687, 12964, -788, -28877, 22867, -5159, -18980, 17518, 5793, -24327, 29558, 15709, -12387, -26153, 10339, -1361, -31504, 22332, -7872, -19584, 65, 20010, -25373, -5458, 14669, -30945, -10785, 9105, 29231, -16207, 3735, 23874, -21736, -1593, 18327, -27073, -6992, 12945, -32415, -12498, 7572, 27540, -17880, 2300, 22188, -23232, -3324, 16848, -28775, 77, 20008, -25370, -5463, 14669, -30955, -10754, 9148, 29197, -16207, 3763, 23885, -21729, -1599, 18335, -27095, -6925, 12988, -32510, -12542, 7642, 27613, -17880, 2272, 22188, -23295, -3325, 16861, -28779, -8655, 11495, 31414, -14004, 5888, 26056, -19554, 544, 20641, -24842, -4746, 15119, -30241, -10347, 9777, 29925, -15685, 4473, 24391, -21026, -1124, 18998, -26372, -6469, 13679, -31987, -11889, 8075, 28213, -17173, 2727, 22905, -22715, -2611, 17311, -28127, -7961, 11957, 32126, -13500, 6600, 26496, -18854, 1254, 21157, 67, 20008, -25376, -5441, 14596, -30972, -10811, 9183, 29222, -16130, 3758, 23811, -21757, -1581, 18398, -27085, -6935, 12969, -32441, -12469, 7673, 27548, -17870, 2301, 22193, -23207, -3294, 16880, -28743, -8698, 11503, 31397, -14012, 5920, 26079, -19573, 552, -11838, -24653, 19818, 15162, -5947, 22165, 1097, -3575, -23559, 4453, -8397, -29502, 31380, 10326, -27122, 18338, 13672, -7385, 20701, 7898, -13242, -17916, 27570, -9859, -30942, 29840, 8861, -28595, 24095, 4084, -644, -21721, 6339, -14692, -19453, 27259, 9317, -2400, -32524, 21271, -4842, -16482, 18896, 6258, -21826, 25828, 14168, -22435, -6606, 13562, 17084, -28322, 12037, 32220, -29822, -9688, 26871, -22851, -2727, 837, 20942, -4206, 15907, 19704, -25927, 10565, 26379, -18989, -15469, 4725, -24410, 84, 20027, -25357, -5451, 14679, -30964, -10795, 9099, 29217, -16130, 3764, 23811, -21745, -1574, 18315, -27095, -6940, 12988, -32432, -12469, 7645, 27534, -17818, 2282, 22176, -23230, -3313, 16854, -28776, -8672, 11498, 67, 20006, -25369, -5449, 14656, -30899, -10792, 9104, 29244, -16207, 3752, 23878, -21736, -1593, 18327, -27102, -6938, 12988, -32510, -12519, 7633, 27536, -17881, 2278, 22198, -23224, -3324, 16852, -28708, -8655, 11516, 31414, -14002, 5914, 26067, -19560, 560, 20708, -24903, -4751, 15176, -30254, -10347, 9782, 29922, -15711, 4475, 24341, 69, 20017, -25374, -5454, 14678, -30964, -10814, 9110, 29223, -16129, 3834, 23895, -21755, -1576, 18331, -27084, -6940, 12984, -32433, -12517, 7566, 27613, 67, 20028, -25376, -5463, 14657, -30973, -10814, 9183, 29244, -16136, 3767, 23878, -21729, -1599, 18335, -27094, -6944, 13027, -32510, 84, 19997, -25378, -5381, 14669, -30946, -10858, 9114, 29232, -16142, 3775, 23878, -21752, -1584, 18330, 86, 20008, -25346, -5454, 14656, 13849, 30844, -21827, -8979, 3866, -20201, -7294, 5578, 17510, -2325, 14578, 27420, -25278, -12387, 29133, -24456, -11588, 1254, -18600, -1708, 11158, 24023, -29579, 16039, 24803, -27889, -15015, 30598, -17976, -6081, 6816, 19684, -233, 8534, 21403, -31275, 13439, 26298, -22276, -30373, -14556, 5620, 25527, -20411, 3595, 23769, -21801, -1230, 18940, -30796, -11198, 8712, 28881, -12586, 7974, 28150, -17499, 2127, 17933, -27448, -7467, 13096, -32280, -8286, 11273, 6495, 22301, -31296, -3149, 8319, -25037, -13081, 15021, 27420, -9761, 6030, 17528, -19906, -7971, 24251, -28907, -575, 11143, -26503, -10704, 1244, 29368, -23788, 4553, 20378, -17281, -5585, 22753, -26961, -14547, 13771, 25477, -12170, 3629, 31978, -21854, 6956, 18902, -30828, -3005, 8704, -28430, -12635, 16134, 28126, -9327, 2113, 17983, -19221, -7510, 21290, -32302, -122, 11339, -26077, -12394, -32300, 21257, 9594, -2378, 18682, 6702, -5020, -16939, 3862, -16057, -27983, 25847, 13844, -30606, 23004, 11016, -690, 20144, 249, -11755, -23439, 30173, -14592, -26285, 27318, 15590, -29144, 16486, 4580, -7422, -19124, 1727, -10012, -21981, 31851, -12827, -24804, 20829, 8853, -2871, 17952, 6242, -5662, -17663, 3422, -8565, -28438, 77, 20008, -25370, -5463, 14669, -30955, -10754, 9148, 29197, -16193, 3760, 23874, -21734, -1580, 18387, -27098, -6944, 12976, -32500 };
  }
  
  private static String ˋ(int paramInt1, char paramChar, int paramInt2)
  {
    break label279;
    label3:
    int j = ˊ + 95;
    ॱ = j % 128;
    if (j % 2 != 0)
    {
      j = 0;
      break label66;
      j = ॱ + 123;
      ˊ = j % 128;
      if (j % 2 != 0) {
        break label247;
      }
      break label250;
    }
    for (;;)
    {
      switch (j)
      {
      default: 
        label66:
        break;
      }
      try
      {
        j = ˏ[(paramInt1 + i)];
        long l1 = j;
        long l2 = i;
        try
        {
          long l3 = ˎ;
          arrayOfChar1[i] = ((char)(int)(l1 ^ l2 * l3 ^ paramChar));
          i += 1;
        }
        catch (Exception localException1)
        {
          char[] arrayOfChar1;
          label142:
          throw localException1;
        }
        arrayOfChar1 = new char[paramInt2];
        i = 1;
      }
      catch (Exception localException2)
      {
        throw localException2;
      }
      j = 1;
    }
    label158:
    int i = 36;
    break label215;
    label164:
    i = 62;
    label200:
    label215:
    label247:
    label250:
    label279:
    for (;;)
    {
      i = ˊ + 103;
      ॱ = i % 128;
      if (i % 2 == 0) {
        break label164;
      }
      break label158;
      return new String(arrayOfChar1);
      switch (i)
      {
      case 62: 
      default: 
        break label142;
        break;
        while (i >= paramInt2) {
          break label200;
        }
      case 36: 
        char[] arrayOfChar2 = new char[paramInt2];
        i = 0;
        break label3;
      }
    }
  }
  
  /* Error */
  public void ˋ()
  {
    // Byte code:
    //   0: goto +747 -> 747
    //   3: goto +18 -> 21
    //   6: goto +1015 -> 1021
    //   9: bipush 12
    //   11: istore_2
    //   12: goto +340 -> 352
    //   15: goto +1006 -> 1021
    //   18: goto +268 -> 286
    //   21: aload 10
    //   23: aload 9
    //   25: invokeinterface 609 1 0
    //   30: checkcast 611	com/insidesecure/hce/MatrixHCEAccount
    //   33: invokeinterface 614 1 0
    //   38: invokeinterface 620 2 0
    //   43: invokeinterface 626 1 0
    //   48: astore 8
    //   50: goto +971 -> 1021
    //   53: getstatic 49	o/pI:ˋ	Ljava/lang/String;
    //   56: sipush 159
    //   59: iconst_0
    //   60: bipush 37
    //   62: invokestatic 29	o/pI:ˋ	(ICI)Ljava/lang/String;
    //   65: invokevirtual 35	java/lang/String:intern	()Ljava/lang/String;
    //   68: invokestatic 632	o/pD:e	(Ljava/lang/String;Ljava/lang/String;)V
    //   71: goto +950 -> 1021
    //   74: aload 11
    //   76: sipush 472
    //   79: sipush 6455
    //   82: bipush 55
    //   84: invokestatic 29	o/pI:ˋ	(ICI)Ljava/lang/String;
    //   87: invokevirtual 35	java/lang/String:intern	()Ljava/lang/String;
    //   90: invokevirtual 637	o/pr:ˋ	(Ljava/lang/String;)Z
    //   93: pop
    //   94: goto +525 -> 619
    //   97: getstatic 49	o/pI:ˋ	Ljava/lang/String;
    //   100: new 23	java/lang/StringBuilder
    //   103: dup
    //   104: invokespecial 26	java/lang/StringBuilder:<init>	()V
    //   107: sipush 196
    //   110: ldc_w 638
    //   113: bipush 35
    //   115: invokestatic 29	o/pI:ˋ	(ICI)Ljava/lang/String;
    //   118: invokevirtual 35	java/lang/String:intern	()Ljava/lang/String;
    //   121: invokevirtual 39	java/lang/StringBuilder:append	(Ljava/lang/String;)Ljava/lang/StringBuilder;
    //   124: aload 12
    //   126: invokevirtual 39	java/lang/StringBuilder:append	(Ljava/lang/String;)Ljava/lang/StringBuilder;
    //   129: sipush 231
    //   132: sipush 27227
    //   135: bipush 12
    //   137: invokestatic 29	o/pI:ˋ	(ICI)Ljava/lang/String;
    //   140: invokevirtual 35	java/lang/String:intern	()Ljava/lang/String;
    //   143: invokevirtual 39	java/lang/StringBuilder:append	(Ljava/lang/String;)Ljava/lang/StringBuilder;
    //   146: aload 11
    //   148: invokeinterface 644 1 0
    //   153: invokevirtual 647	com/insidesecure/hce/MatrixHCECardState:toString	()Ljava/lang/String;
    //   156: invokevirtual 39	java/lang/StringBuilder:append	(Ljava/lang/String;)Ljava/lang/StringBuilder;
    //   159: invokevirtual 47	java/lang/StringBuilder:toString	()Ljava/lang/String;
    //   162: invokestatic 650	o/pD:d	(Ljava/lang/String;Ljava/lang/String;)V
    //   165: goto +135 -> 300
    //   168: iload_1
    //   169: istore_2
    //   170: getstatic 49	o/pI:ˋ	Ljava/lang/String;
    //   173: sipush 402
    //   176: iconst_0
    //   177: iconst_5
    //   178: invokestatic 29	o/pI:ˋ	(ICI)Ljava/lang/String;
    //   181: invokevirtual 35	java/lang/String:intern	()Ljava/lang/String;
    //   184: invokestatic 650	o/pD:d	(Ljava/lang/String;Ljava/lang/String;)V
    //   187: goto +557 -> 744
    //   190: aload 11
    //   192: invokevirtual 654	o/pr:getPaymentScheme	()Lcom/insidesecure/hce/MatrixHCEPaymentScheme;
    //   195: astore 12
    //   197: getstatic 660	com/insidesecure/hce/MatrixHCEPaymentScheme:MASTERCARD	Lcom/insidesecure/hce/MatrixHCEPaymentScheme;
    //   200: astore 13
    //   202: aload 12
    //   204: aload 13
    //   206: if_acmpne +6 -> 212
    //   209: goto +714 -> 923
    //   212: goto +407 -> 619
    //   215: goto -197 -> 18
    //   218: getstatic 19	o/pI:ॱ	I
    //   221: bipush 37
    //   223: iadd
    //   224: istore_1
    //   225: iload_1
    //   226: sipush 128
    //   229: irem
    //   230: putstatic 17	o/pI:ˊ	I
    //   233: iload_1
    //   234: iconst_2
    //   235: irem
    //   236: ifeq +6 -> 242
    //   239: goto +566 -> 805
    //   242: goto +201 -> 443
    //   245: astore 8
    //   247: aload 8
    //   249: athrow
    //   250: goto +36 -> 286
    //   253: iload_1
    //   254: ifeq +6 -> 260
    //   257: goto +493 -> 750
    //   260: goto +359 -> 619
    //   263: astore 13
    //   265: getstatic 49	o/pI:ˋ	Ljava/lang/String;
    //   268: sipush 298
    //   271: iconst_0
    //   272: bipush 48
    //   274: invokestatic 29	o/pI:ˋ	(ICI)Ljava/lang/String;
    //   277: invokevirtual 35	java/lang/String:intern	()Ljava/lang/String;
    //   280: invokestatic 650	o/pD:d	(Ljava/lang/String;Ljava/lang/String;)V
    //   283: goto +203 -> 486
    //   286: aload 9
    //   288: invokeinterface 664 1 0
    //   293: ifeq +6 -> 299
    //   296: goto +660 -> 956
    //   299: return
    //   300: getstatic 17	o/pI:ˊ	I
    //   303: bipush 83
    //   305: iadd
    //   306: istore_1
    //   307: iload_1
    //   308: sipush 128
    //   311: irem
    //   312: putstatic 19	o/pI:ॱ	I
    //   315: iload_1
    //   316: iconst_2
    //   317: irem
    //   318: ifne +6 -> 324
    //   321: goto -306 -> 15
    //   324: goto -318 -> 6
    //   327: iload_2
    //   328: istore_1
    //   329: goto +591 -> 920
    //   332: goto -82 -> 250
    //   335: aload 10
    //   337: invokeinterface 668 1 0
    //   342: invokeinterface 626 1 0
    //   347: astore 9
    //   349: goto +243 -> 592
    //   352: iload_3
    //   353: istore_1
    //   354: iload_2
    //   355: lookupswitch	default:+25->380, 12:+330->685, 75:+565->920
    //   380: goto +305 -> 685
    //   383: iload_1
    //   384: lookupswitch	default:+28->412, 22:+459->843, 72:+598->982
    //   412: goto +570 -> 982
    //   415: aload 11
    //   417: invokeinterface 671 1 0
    //   422: astore 12
    //   424: aload 11
    //   426: invokeinterface 644 1 0
    //   431: getstatic 675	com/insidesecure/hce/MatrixHCECardState:INITIALIZED	Lcom/insidesecure/hce/MatrixHCECardState;
    //   434: if_acmpeq +6 -> 440
    //   437: goto +210 -> 647
    //   440: goto +510 -> 950
    //   443: getstatic 49	o/pI:ˋ	Ljava/lang/String;
    //   446: iconst_0
    //   447: sipush 25160
    //   450: bipush 56
    //   452: invokestatic 29	o/pI:ˋ	(ICI)Ljava/lang/String;
    //   455: invokevirtual 35	java/lang/String:intern	()Ljava/lang/String;
    //   458: invokestatic 650	o/pD:d	(Ljava/lang/String;Ljava/lang/String;)V
    //   461: getstatic 49	o/pI:ˋ	Ljava/lang/String;
    //   464: bipush 56
    //   466: iconst_0
    //   467: bipush 29
    //   469: invokestatic 29	o/pI:ˋ	(ICI)Ljava/lang/String;
    //   472: invokevirtual 35	java/lang/String:intern	()Ljava/lang/String;
    //   475: invokestatic 650	o/pD:d	(Ljava/lang/String;Ljava/lang/String;)V
    //   478: invokestatic 681	com/insidesecure/hce/MatrixHCE$MatrixHCEFactory:getInstance	()Lcom/insidesecure/hce/MatrixHCE;
    //   481: astore 10
    //   483: goto -148 -> 335
    //   486: iload_1
    //   487: istore_2
    //   488: aload 11
    //   490: invokevirtual 685	o/pr:getExpirationTimestamp	()J
    //   493: lstore 4
    //   495: iload_1
    //   496: istore_2
    //   497: invokestatic 690	java/lang/System:currentTimeMillis	()J
    //   500: lstore 6
    //   502: iload_1
    //   503: istore_2
    //   504: getstatic 49	o/pI:ˋ	Ljava/lang/String;
    //   507: new 23	java/lang/StringBuilder
    //   510: dup
    //   511: invokespecial 26	java/lang/StringBuilder:<init>	()V
    //   514: sipush 346
    //   517: iconst_0
    //   518: bipush 22
    //   520: invokestatic 29	o/pI:ˋ	(ICI)Ljava/lang/String;
    //   523: invokevirtual 35	java/lang/String:intern	()Ljava/lang/String;
    //   526: invokevirtual 39	java/lang/StringBuilder:append	(Ljava/lang/String;)Ljava/lang/StringBuilder;
    //   529: lload 4
    //   531: invokevirtual 693	java/lang/StringBuilder:append	(J)Ljava/lang/StringBuilder;
    //   534: invokevirtual 47	java/lang/StringBuilder:toString	()Ljava/lang/String;
    //   537: invokestatic 650	o/pD:d	(Ljava/lang/String;Ljava/lang/String;)V
    //   540: iload_1
    //   541: istore_2
    //   542: getstatic 49	o/pI:ˋ	Ljava/lang/String;
    //   545: new 23	java/lang/StringBuilder
    //   548: dup
    //   549: invokespecial 26	java/lang/StringBuilder:<init>	()V
    //   552: sipush 368
    //   555: iconst_0
    //   556: bipush 19
    //   558: invokestatic 29	o/pI:ˋ	(ICI)Ljava/lang/String;
    //   561: invokevirtual 35	java/lang/String:intern	()Ljava/lang/String;
    //   564: invokevirtual 39	java/lang/StringBuilder:append	(Ljava/lang/String;)Ljava/lang/StringBuilder;
    //   567: lload 6
    //   569: invokevirtual 693	java/lang/StringBuilder:append	(J)Ljava/lang/StringBuilder;
    //   572: invokevirtual 47	java/lang/StringBuilder:toString	()Ljava/lang/String;
    //   575: invokestatic 650	o/pD:d	(Ljava/lang/String;Ljava/lang/String;)V
    //   578: lload 6
    //   580: lload 4
    //   582: lcmp
    //   583: iflt +6 -> 589
    //   586: goto +67 -> 653
    //   589: goto +219 -> 808
    //   592: getstatic 19	o/pI:ॱ	I
    //   595: bipush 89
    //   597: iadd
    //   598: istore_1
    //   599: iload_1
    //   600: sipush 128
    //   603: irem
    //   604: putstatic 17	o/pI:ˊ	I
    //   607: iload_1
    //   608: iconst_2
    //   609: irem
    //   610: ifeq +6 -> 616
    //   613: goto -281 -> 332
    //   616: goto -366 -> 250
    //   619: goto +402 -> 1021
    //   622: iload_2
    //   623: tableswitch	default:+21->644, 0:+467->1090, 1:+-455->168
    //   644: goto -476 -> 168
    //   647: bipush 72
    //   649: istore_1
    //   650: goto -267 -> 383
    //   653: iconst_0
    //   654: istore_2
    //   655: goto -33 -> 622
    //   658: astore 13
    //   660: getstatic 49	o/pI:ˋ	Ljava/lang/String;
    //   663: sipush 407
    //   666: sipush 13914
    //   669: bipush 39
    //   671: invokestatic 29	o/pI:ˋ	(ICI)Ljava/lang/String;
    //   674: invokevirtual 35	java/lang/String:intern	()Ljava/lang/String;
    //   677: invokestatic 650	o/pD:d	(Ljava/lang/String;Ljava/lang/String;)V
    //   680: iload_2
    //   681: istore_1
    //   682: goto -429 -> 253
    //   685: getstatic 19	o/pI:ॱ	I
    //   688: bipush 31
    //   690: iadd
    //   691: istore_1
    //   692: iload_1
    //   693: sipush 128
    //   696: irem
    //   697: putstatic 17	o/pI:ˊ	I
    //   700: iload_1
    //   701: iconst_2
    //   702: irem
    //   703: ifeq +6 -> 709
    //   706: goto +6 -> 712
    //   709: goto +109 -> 818
    //   712: goto +106 -> 818
    //   715: bipush 75
    //   717: istore_2
    //   718: goto -366 -> 352
    //   721: aload 11
    //   723: sipush 7539
    //   726: ldc_w 694
    //   729: bipush 27
    //   731: invokestatic 29	o/pI:ˋ	(ICI)Ljava/lang/String;
    //   734: invokevirtual 35	java/lang/String:intern	()Ljava/lang/String;
    //   737: invokevirtual 637	o/pr:ˋ	(Ljava/lang/String;)Z
    //   740: pop
    //   741: goto -122 -> 619
    //   744: goto -491 -> 253
    //   747: goto -529 -> 218
    //   750: getstatic 49	o/pI:ˋ	Ljava/lang/String;
    //   753: new 23	java/lang/StringBuilder
    //   756: dup
    //   757: invokespecial 26	java/lang/StringBuilder:<init>	()V
    //   760: sipush 446
    //   763: ldc_w 695
    //   766: bipush 26
    //   768: invokestatic 29	o/pI:ˋ	(ICI)Ljava/lang/String;
    //   771: invokevirtual 35	java/lang/String:intern	()Ljava/lang/String;
    //   774: invokevirtual 39	java/lang/StringBuilder:append	(Ljava/lang/String;)Ljava/lang/StringBuilder;
    //   777: aload 12
    //   779: invokevirtual 39	java/lang/StringBuilder:append	(Ljava/lang/String;)Ljava/lang/StringBuilder;
    //   782: invokevirtual 47	java/lang/StringBuilder:toString	()Ljava/lang/String;
    //   785: invokestatic 698	o/pD:i	(Ljava/lang/String;Ljava/lang/String;)V
    //   788: aload 11
    //   790: invokevirtual 654	o/pr:getPaymentScheme	()Lcom/insidesecure/hce/MatrixHCEPaymentScheme;
    //   793: getstatic 701	com/insidesecure/hce/MatrixHCEPaymentScheme:VISA	Lcom/insidesecure/hce/MatrixHCEPaymentScheme;
    //   796: if_acmpne +6 -> 802
    //   799: goto -725 -> 74
    //   802: goto -612 -> 190
    //   805: goto -362 -> 443
    //   808: iconst_1
    //   809: istore_2
    //   810: goto -188 -> 622
    //   813: astore 8
    //   815: aload 8
    //   817: athrow
    //   818: iconst_1
    //   819: istore_2
    //   820: iconst_1
    //   821: istore_1
    //   822: getstatic 49	o/pI:ˋ	Ljava/lang/String;
    //   825: sipush 267
    //   828: iconst_0
    //   829: bipush 31
    //   831: invokestatic 29	o/pI:ˋ	(ICI)Ljava/lang/String;
    //   834: invokevirtual 35	java/lang/String:intern	()Ljava/lang/String;
    //   837: invokestatic 650	o/pD:d	(Ljava/lang/String;Ljava/lang/String;)V
    //   840: goto -513 -> 327
    //   843: aload 11
    //   845: checkcast 634	o/pr
    //   848: astore 11
    //   850: iconst_0
    //   851: istore_3
    //   852: iconst_0
    //   853: istore_2
    //   854: iload_2
    //   855: istore_1
    //   856: aload 11
    //   858: invokevirtual 705	o/pr:ʽ	()Ljava/lang/Integer;
    //   861: invokevirtual 711	java/lang/Integer:intValue	()I
    //   864: i2l
    //   865: lstore 4
    //   867: iload_2
    //   868: istore_1
    //   869: getstatic 49	o/pI:ˋ	Ljava/lang/String;
    //   872: new 23	java/lang/StringBuilder
    //   875: dup
    //   876: invokespecial 26	java/lang/StringBuilder:<init>	()V
    //   879: sipush 243
    //   882: ldc_w 712
    //   885: bipush 24
    //   887: invokestatic 29	o/pI:ˋ	(ICI)Ljava/lang/String;
    //   890: invokevirtual 35	java/lang/String:intern	()Ljava/lang/String;
    //   893: invokevirtual 39	java/lang/StringBuilder:append	(Ljava/lang/String;)Ljava/lang/StringBuilder;
    //   896: lload 4
    //   898: invokevirtual 693	java/lang/StringBuilder:append	(J)Ljava/lang/StringBuilder;
    //   901: invokevirtual 47	java/lang/StringBuilder:toString	()Ljava/lang/String;
    //   904: invokestatic 650	o/pD:d	(Ljava/lang/String;Ljava/lang/String;)V
    //   907: lload 4
    //   909: lconst_0
    //   910: lcmp
    //   911: ifgt +6 -> 917
    //   914: goto -905 -> 9
    //   917: goto -202 -> 715
    //   920: goto -434 -> 486
    //   923: getstatic 19	o/pI:ॱ	I
    //   926: bipush 73
    //   928: iadd
    //   929: istore_1
    //   930: iload_1
    //   931: sipush 128
    //   934: irem
    //   935: putstatic 17	o/pI:ˊ	I
    //   938: iload_1
    //   939: iconst_2
    //   940: irem
    //   941: ifeq +6 -> 947
    //   944: goto -223 -> 721
    //   947: goto +120 -> 1067
    //   950: bipush 22
    //   952: istore_1
    //   953: goto -570 -> 383
    //   956: getstatic 19	o/pI:ॱ	I
    //   959: iconst_1
    //   960: iadd
    //   961: istore_1
    //   962: iload_1
    //   963: sipush 128
    //   966: irem
    //   967: putstatic 17	o/pI:ˊ	I
    //   970: iload_1
    //   971: iconst_2
    //   972: irem
    //   973: ifeq +6 -> 979
    //   976: goto -973 -> 3
    //   979: goto -958 -> 21
    //   982: aload 11
    //   984: invokeinterface 644 1 0
    //   989: getstatic 715	com/insidesecure/hce/MatrixHCECardState:ACTIVE	Lcom/insidesecure/hce/MatrixHCECardState;
    //   992: if_acmpeq +6 -> 998
    //   995: goto -898 -> 97
    //   998: goto -155 -> 843
    //   1001: astore 8
    //   1003: getstatic 49	o/pI:ˋ	Ljava/lang/String;
    //   1006: bipush 85
    //   1008: iconst_0
    //   1009: bipush 74
    //   1011: invokestatic 29	o/pI:ˋ	(ICI)Ljava/lang/String;
    //   1014: invokevirtual 35	java/lang/String:intern	()Ljava/lang/String;
    //   1017: invokestatic 632	o/pD:e	(Ljava/lang/String;Ljava/lang/String;)V
    //   1020: return
    //   1021: aload 8
    //   1023: invokeinterface 664 1 0
    //   1028: ifeq +6 -> 1034
    //   1031: goto +6 -> 1037
    //   1034: goto -819 -> 215
    //   1037: aload 8
    //   1039: invokeinterface 609 1 0
    //   1044: astore 11
    //   1046: aload 11
    //   1048: checkcast 640	com/insidesecure/hce/MatrixHCECard
    //   1051: astore 11
    //   1053: aload 11
    //   1055: instanceof 634
    //   1058: ifne +6 -> 1064
    //   1061: goto -1008 -> 53
    //   1064: goto -649 -> 415
    //   1067: aload 11
    //   1069: sipush 527
    //   1072: ldc_w 694
    //   1075: bipush 48
    //   1077: invokestatic 29	o/pI:ˋ	(ICI)Ljava/lang/String;
    //   1080: invokevirtual 35	java/lang/String:intern	()Ljava/lang/String;
    //   1083: invokevirtual 637	o/pr:ˋ	(Ljava/lang/String;)Z
    //   1086: pop
    //   1087: goto -468 -> 619
    //   1090: iconst_1
    //   1091: istore_1
    //   1092: iconst_1
    //   1093: istore_2
    //   1094: getstatic 49	o/pI:ˋ	Ljava/lang/String;
    //   1097: sipush 387
    //   1100: iconst_0
    //   1101: bipush 15
    //   1103: invokestatic 29	o/pI:ˋ	(ICI)Ljava/lang/String;
    //   1106: invokevirtual 35	java/lang/String:intern	()Ljava/lang/String;
    //   1109: invokestatic 650	o/pD:d	(Ljava/lang/String;Ljava/lang/String;)V
    //   1112: goto -368 -> 744
    // Local variable table:
    //   start	length	slot	name	signature
    //   0	1115	0	this	pI
    //   168	924	1	i	int
    //   11	1083	2	j	int
    //   352	500	3	k	int
    //   493	415	4	l1	long
    //   500	79	6	l2	long
    //   48	1	8	localIterator1	java.util.Iterator
    //   245	3	8	localException1	Exception
    //   813	3	8	localException2	Exception
    //   1001	37	8	localMatrixHCEException1	com.insidesecure.hce.MatrixHCEException
    //   23	325	9	localIterator2	java.util.Iterator
    //   21	461	10	localMatrixHCE	com.insidesecure.hce.MatrixHCE
    //   74	994	11	localObject1	Object
    //   124	654	12	localObject2	Object
    //   200	5	13	localMatrixHCEPaymentScheme	com.insidesecure.hce.MatrixHCEPaymentScheme
    //   263	1	13	localMatrixHCEException2	com.insidesecure.hce.MatrixHCEException
    //   658	1	13	localMatrixHCEException3	com.insidesecure.hce.MatrixHCEException
    // Exception table:
    //   from	to	target	type
    //   1037	1046	245	java/lang/Exception
    //   1046	1053	245	java/lang/Exception
    //   822	840	263	com/insidesecure/hce/MatrixHCEException
    //   856	867	263	com/insidesecure/hce/MatrixHCEException
    //   869	907	263	com/insidesecure/hce/MatrixHCEException
    //   170	187	658	com/insidesecure/hce/MatrixHCEException
    //   488	495	658	com/insidesecure/hce/MatrixHCEException
    //   497	502	658	com/insidesecure/hce/MatrixHCEException
    //   504	540	658	com/insidesecure/hce/MatrixHCEException
    //   542	578	658	com/insidesecure/hce/MatrixHCEException
    //   1094	1112	658	com/insidesecure/hce/MatrixHCEException
    //   190	197	813	java/lang/Exception
    //   197	202	813	java/lang/Exception
    //   461	483	1001	com/insidesecure/hce/MatrixHCEException
  }
}
