package o;

import android.content.Context;
import android.content.res.Resources;
import android.os.Handler;
import android.os.Looper;

public class pJ
  extends gU
{
  private static int ʼ;
  private static int ˋ;
  private static final String ˎ;
  private static long ˏ;
  private static char[] ॱ;
  
  static
  {
    break label10;
    return;
    int i = 66 / 0;
    return;
    label10:
    ˋ = 0;
    ʼ = 1;
    ॱ();
    ˎ = ˎ(325, '囲', 19).intern() + pJ.class.getSimpleName();
    for (;;)
    {
      i = 0;
      break;
      i = ˋ + 13;
      ʼ = i % 128;
      if (i % 2 == 0) {
        break label117;
      }
    }
    for (;;)
    {
      switch (i)
      {
      }
      return;
      label117:
      i = 1;
    }
  }
  
  public pJ() {}
  
  private static String ˎ(int paramInt1, char paramChar, int paramInt2)
  {
    break label242;
    Object localObject;
    int i;
    localObject[i] = ((char)(int)(ॱ[(paramInt1 + i)] ^ i * ˏ ^ paramChar));
    i += 1;
    break label91;
    return localObject;
    label47:
    int j;
    for (;;)
    {
      localObject = new char[paramInt2];
      i = 0;
      break label91;
      localObject[i] = ((char)(int)(ॱ[(paramInt1 % i)] - (i - ˏ) & paramChar));
      i += 26;
      for (;;)
      {
        j = 0;
        break;
        label91:
        do
        {
          j = 1;
          break;
        } while (i < paramInt2);
      }
      label102:
      paramInt1 = 1;
      label110:
      label140:
      label167:
      do
      {
        break;
        switch (paramInt1)
        {
        }
        paramInt1 = 63 / 0;
        return localObject;
        paramInt1 = ˋ + 41;
        ʼ = paramInt1 % 128;
        if (paramInt1 % 2 == 0) {
          break label102;
        }
        break label223;
        i = ˋ + 39;
        ʼ = i % 128;
      } while (i % 2 == 0);
    }
    for (;;)
    {
      j = ʼ + 5;
      ˋ = j % 128;
      if (j % 2 != 0) {
        break label47;
      }
      break;
      label223:
      paramInt1 = 0;
      break label110;
      localObject = new String((char[])localObject);
      break label140;
      label242:
      break label167;
      switch (j)
      {
      }
    }
  }
  
  static void ॱ()
  {
    ˏ = -4605002898401368771L;
    ॱ = new char[] { 111, 25939, -13778, 12248, -27489, -1452, 24320, -15111, 10637, -28861, -3056, 23034, -16721, 9329, -30338, -4422, 21488, -18066, 7723, -31765, -5976, 20068, -19622, 6235, 32222, -7526, 18496, -21169, 4843, 30634, -8853, 16963, -22551, 3251, 29289, -10461, 15605, -24129, 1901, 27694, -11864, 13964, -25530, 30973, 7650, -19803, 22372, -5059, -32029, 10150, -17363, 20852, 32, 25872, -13734, 12272, -27493, -1442, 24329, -15161, 10637, -28923, -3054, 23021, -16717, 9331, -30413, -4368, 21412, -18131, 7683, -31805, -5890, 20001, -18231, -8711, 29363, -26863, 11377, 17084, -6233, 31760, -28316, 14251, 19682, -7931, 1601, -25455, 12747, 22035, -5290, 394, -22909, 15143, 20585, -2350, 3063, 12245, 19180, -6747, 2377, 27769, -15565, 9872, -25096, -3281, 22055, -12912, 8420, -31189, -670, 20613, -18495, 11537, -32693, -6253, 23254, -20470, 5891, -30041, -7703, 18258, -17801, 67, 25938, -13809, 12251, -27504, -1519, 24320, -15164, 10652, -28923, -3067, 23034, -16728, 9273, -30447, -4400, 21405, -18131, 7742, -31768, -5969, 20068, -19632, 6235, 32222, -7545, 18525, -21246, 4748, 30592, -8888, 16912, -22572, 3260, 29300, -10444, 15601, -24079, 1863, 27663, -11854, 14053, 82, 25944, -13795, 12254, -27513, -1467, 24348, -15158, 10652, -28852, -3059, 23025, -16644, 9296, -30446, -4429, 21430, -18078, 7736, -31833, -5979, 20066, -19619, 6164, 32205, -7525, 18502, -21169, 31034, 7246, -19693, 22157, -4709, -31931, 9751, -16935, 20627, -2479, -29409, 8416, -14430, 23853, -3988, -26681, 10917, -16329, 26417, -1282, -28246, 14194, -13749, 24847, 1154, -25727, 12621, -11248, 27602, 3734, -23464, 32, 25941, -13797, 12228, -27436, -1454, 24326, -15158, 10630, -28862, -3065, 23035, -16654, 9273, -30433, -4355, 21430, -18078, 7736, -31766, -5916, 20085, -19626, 6174, 32152, -7532, 18498, -21217, 4800, 30592, -8891, 16898, -22572, 3252, 29301, -10439, -4552, -29943, 9292, -15934, 31430, 5124, -20154, 10905, -14377, 24859, 6730, -18527, 20708, -13769, 26495, 173, -16987, 22334, -3982, 28089, 1713, -24525, 23819, -2476, -27770, 3264, -23011, 17178, -833, -26127, 13112, -21401, 18857, -7480, -25582, 14675, -11621, 20421, -5858, -32171, 16285, -10047, 29196, -4300, -30621, 9635, -8455, 30765, 5487, 28663, 2753, -23168, 16503, -1270, -27187, 12434, -21669, 17922, -7980, -25719, 13919, -11987, 19431, -6492, -32407, 22207, 13230, -25348, 31031, -15761, -21317, 2516, -28134, 32607, -9735, -23814, 3852, -6056, 29322, -8311, -18432, 1362, -4202, 18582 };
  }
  
  /* Error */
  private void ॱ(Context paramContext)
  {
    // Byte code:
    //   0: goto +326 -> 326
    //   3: aload_1
    //   4: aload 6
    //   6: invokevirtual 397	java/lang/String:equals	(Ljava/lang/Object;)Z
    //   9: ifeq +6 -> 15
    //   12: goto +39 -> 51
    //   15: goto +616 -> 631
    //   18: goto +291 -> 309
    //   21: iload_2
    //   22: lookupswitch	default:+26->48, 2:+907->929, 8:+992->1014
    //   48: goto +881 -> 929
    //   51: getstatic 51	o/pJ:ˎ	Ljava/lang/String;
    //   54: astore 6
    //   56: new 25	java/lang/StringBuilder
    //   59: dup
    //   60: invokespecial 28	java/lang/StringBuilder:<init>	()V
    //   63: astore_1
    //   64: aload_0
    //   65: invokevirtual 403	android/content/Context:getResources	()Landroid/content/res/Resources;
    //   68: astore 7
    //   70: aload 7
    //   72: ldc_w 404
    //   75: invokevirtual 410	android/content/res/Resources:getString	(I)Ljava/lang/String;
    //   78: astore 7
    //   80: aload 7
    //   82: iconst_0
    //   83: iconst_4
    //   84: invokevirtual 414	java/lang/String:substring	(II)Ljava/lang/String;
    //   87: astore 7
    //   89: aload 6
    //   91: aload_1
    //   92: aload 7
    //   94: invokevirtual 418	java/lang/String:length	()I
    //   97: sipush 161
    //   100: iadd
    //   101: aload_0
    //   102: invokevirtual 403	android/content/Context:getResources	()Landroid/content/res/Resources;
    //   105: ldc_w 419
    //   108: invokevirtual 410	android/content/res/Resources:getString	(I)Ljava/lang/String;
    //   111: iconst_0
    //   112: iconst_4
    //   113: invokevirtual 414	java/lang/String:substring	(II)Ljava/lang/String;
    //   116: invokevirtual 418	java/lang/String:length	()I
    //   119: iconst_4
    //   120: isub
    //   121: i2c
    //   122: aload_0
    //   123: invokevirtual 423	android/content/Context:getApplicationInfo	()Landroid/content/pm/ApplicationInfo;
    //   126: getfield 428	android/content/pm/ApplicationInfo:targetSdkVersion	I
    //   129: iconst_3
    //   130: iadd
    //   131: invokestatic 31	o/pJ:ˎ	(ICI)Ljava/lang/String;
    //   134: invokevirtual 37	java/lang/String:intern	()Ljava/lang/String;
    //   137: invokevirtual 41	java/lang/StringBuilder:append	(Ljava/lang/String;)Ljava/lang/StringBuilder;
    //   140: aload 5
    //   142: invokeinterface 433 1 0
    //   147: invokevirtual 41	java/lang/StringBuilder:append	(Ljava/lang/String;)Ljava/lang/StringBuilder;
    //   150: aload_0
    //   151: invokevirtual 423	android/content/Context:getApplicationInfo	()Landroid/content/pm/ApplicationInfo;
    //   154: getfield 428	android/content/pm/ApplicationInfo:targetSdkVersion	I
    //   157: sipush 168
    //   160: iadd
    //   161: aload_0
    //   162: invokevirtual 403	android/content/Context:getResources	()Landroid/content/res/Resources;
    //   165: ldc_w 434
    //   168: invokevirtual 410	android/content/res/Resources:getString	(I)Ljava/lang/String;
    //   171: iconst_0
    //   172: iconst_4
    //   173: invokevirtual 414	java/lang/String:substring	(II)Ljava/lang/String;
    //   176: invokevirtual 418	java/lang/String:length	()I
    //   179: sipush 30998
    //   182: iadd
    //   183: i2c
    //   184: aload_0
    //   185: invokevirtual 403	android/content/Context:getResources	()Landroid/content/res/Resources;
    //   188: ldc_w 435
    //   191: invokevirtual 410	android/content/res/Resources:getString	(I)Ljava/lang/String;
    //   194: iconst_0
    //   195: iconst_4
    //   196: invokevirtual 414	java/lang/String:substring	(II)Ljava/lang/String;
    //   199: invokevirtual 418	java/lang/String:length	()I
    //   202: bipush 27
    //   204: iadd
    //   205: invokestatic 31	o/pJ:ˎ	(ICI)Ljava/lang/String;
    //   208: invokevirtual 37	java/lang/String:intern	()Ljava/lang/String;
    //   211: invokevirtual 41	java/lang/StringBuilder:append	(Ljava/lang/String;)Ljava/lang/StringBuilder;
    //   214: invokevirtual 49	java/lang/StringBuilder:toString	()Ljava/lang/String;
    //   217: invokestatic 441	o/pD:i	(Ljava/lang/String;Ljava/lang/String;)V
    //   220: goto +89 -> 309
    //   223: bipush 8
    //   225: istore_2
    //   226: goto -205 -> 21
    //   229: getstatic 21	o/pJ:ʼ	I
    //   232: bipush 15
    //   234: iadd
    //   235: istore_2
    //   236: iload_2
    //   237: sipush 128
    //   240: irem
    //   241: putstatic 19	o/pJ:ˋ	I
    //   244: iload_2
    //   245: iconst_2
    //   246: irem
    //   247: ifeq +6 -> 253
    //   250: goto +770 -> 1020
    //   253: goto -30 -> 223
    //   256: getstatic 19	o/pJ:ˋ	I
    //   259: bipush 37
    //   261: iadd
    //   262: istore_2
    //   263: iload_2
    //   264: sipush 128
    //   267: irem
    //   268: putstatic 21	o/pJ:ʼ	I
    //   271: iload_2
    //   272: iconst_2
    //   273: irem
    //   274: ifne +6 -> 280
    //   277: goto +748 -> 1025
    //   280: goto +955 -> 1235
    //   283: aload_1
    //   284: invokevirtual 445	android/content/Context:getApplicationContext	()Landroid/content/Context;
    //   287: invokestatic 449	o/pD:getInstance	(Landroid/content/Context;)Lo/pz;
    //   290: astore_1
    //   291: new 451	java/lang/NullPointerException
    //   294: dup
    //   295: invokespecial 452	java/lang/NullPointerException:<init>	()V
    //   298: athrow
    //   299: aload_1
    //   300: ifnonnull +6 -> 306
    //   303: goto -285 -> 18
    //   306: goto -303 -> 3
    //   309: aload 4
    //   311: invokeinterface 458 1 0
    //   316: ifeq +6 -> 322
    //   319: goto +32 -> 351
    //   322: return
    //   323: astore_1
    //   324: aload_1
    //   325: athrow
    //   326: goto -70 -> 256
    //   329: goto -20 -> 309
    //   332: aload_0
    //   333: invokestatic 464	o/gT:ˊ	(Landroid/content/Context;)Lo/gT;
    //   336: astore_3
    //   337: aload_1
    //   338: invokevirtual 470	o/pz:getPaymentAccounts	()Ljava/util/List;
    //   341: invokeinterface 476 1 0
    //   346: astore 4
    //   348: goto -39 -> 309
    //   351: aload 4
    //   353: invokeinterface 480 1 0
    //   358: checkcast 430	com/insidesecure/hce/MatrixHCEAccount
    //   361: astore 5
    //   363: aload 5
    //   365: checkcast 482	o/pk
    //   368: invokevirtual 484	o/pk:ˏ	()Ljava/lang/String;
    //   371: astore_1
    //   372: aload 5
    //   374: invokeinterface 487 1 0
    //   379: astore 6
    //   381: getstatic 51	o/pJ:ˎ	Ljava/lang/String;
    //   384: new 25	java/lang/StringBuilder
    //   387: dup
    //   388: invokespecial 28	java/lang/StringBuilder:<init>	()V
    //   391: aload_0
    //   392: invokevirtual 423	android/content/Context:getApplicationInfo	()Landroid/content/pm/ApplicationInfo;
    //   395: getfield 428	android/content/pm/ApplicationInfo:targetSdkVersion	I
    //   398: bipush 18
    //   400: iadd
    //   401: aload_0
    //   402: invokevirtual 403	android/content/Context:getResources	()Landroid/content/res/Resources;
    //   405: ldc_w 488
    //   408: invokevirtual 410	android/content/res/Resources:getString	(I)Ljava/lang/String;
    //   411: iconst_0
    //   412: iconst_4
    //   413: invokevirtual 414	java/lang/String:substring	(II)Ljava/lang/String;
    //   416: invokevirtual 418	java/lang/String:length	()I
    //   419: sipush 30904
    //   422: iadd
    //   423: i2c
    //   424: aload_0
    //   425: invokevirtual 423	android/content/Context:getApplicationInfo	()Landroid/content/pm/ApplicationInfo;
    //   428: getfield 428	android/content/pm/ApplicationInfo:targetSdkVersion	I
    //   431: bipush 16
    //   433: isub
    //   434: invokestatic 31	o/pJ:ˎ	(ICI)Ljava/lang/String;
    //   437: invokevirtual 37	java/lang/String:intern	()Ljava/lang/String;
    //   440: invokevirtual 41	java/lang/StringBuilder:append	(Ljava/lang/String;)Ljava/lang/StringBuilder;
    //   443: aload 5
    //   445: invokeinterface 433 1 0
    //   450: invokevirtual 41	java/lang/StringBuilder:append	(Ljava/lang/String;)Ljava/lang/StringBuilder;
    //   453: invokevirtual 49	java/lang/StringBuilder:toString	()Ljava/lang/String;
    //   456: invokestatic 441	o/pD:i	(Ljava/lang/String;Ljava/lang/String;)V
    //   459: getstatic 51	o/pJ:ˎ	Ljava/lang/String;
    //   462: new 25	java/lang/StringBuilder
    //   465: dup
    //   466: invokespecial 28	java/lang/StringBuilder:<init>	()V
    //   469: aload_0
    //   470: invokevirtual 403	android/content/Context:getResources	()Landroid/content/res/Resources;
    //   473: ldc_w 489
    //   476: invokevirtual 410	android/content/res/Resources:getString	(I)Ljava/lang/String;
    //   479: iconst_0
    //   480: bipush 8
    //   482: invokevirtual 414	java/lang/String:substring	(II)Ljava/lang/String;
    //   485: iconst_1
    //   486: invokevirtual 493	java/lang/String:codePointAt	(I)I
    //   489: bipush 26
    //   491: iadd
    //   492: aload_0
    //   493: invokevirtual 403	android/content/Context:getResources	()Landroid/content/res/Resources;
    //   496: ldc_w 494
    //   499: invokevirtual 410	android/content/res/Resources:getString	(I)Ljava/lang/String;
    //   502: iconst_0
    //   503: iconst_4
    //   504: invokevirtual 414	java/lang/String:substring	(II)Ljava/lang/String;
    //   507: iconst_1
    //   508: invokevirtual 493	java/lang/String:codePointAt	(I)I
    //   511: bipush 26
    //   513: isub
    //   514: i2c
    //   515: aload_0
    //   516: invokevirtual 423	android/content/Context:getApplicationInfo	()Landroid/content/pm/ApplicationInfo;
    //   519: getfield 428	android/content/pm/ApplicationInfo:targetSdkVersion	I
    //   522: iconst_3
    //   523: isub
    //   524: invokestatic 31	o/pJ:ˎ	(ICI)Ljava/lang/String;
    //   527: invokevirtual 37	java/lang/String:intern	()Ljava/lang/String;
    //   530: invokevirtual 41	java/lang/StringBuilder:append	(Ljava/lang/String;)Ljava/lang/StringBuilder;
    //   533: aload_1
    //   534: invokevirtual 41	java/lang/StringBuilder:append	(Ljava/lang/String;)Ljava/lang/StringBuilder;
    //   537: invokevirtual 49	java/lang/StringBuilder:toString	()Ljava/lang/String;
    //   540: invokestatic 441	o/pD:i	(Ljava/lang/String;Ljava/lang/String;)V
    //   543: getstatic 51	o/pJ:ˎ	Ljava/lang/String;
    //   546: new 25	java/lang/StringBuilder
    //   549: dup
    //   550: invokespecial 28	java/lang/StringBuilder:<init>	()V
    //   553: aload_0
    //   554: invokevirtual 403	android/content/Context:getResources	()Landroid/content/res/Resources;
    //   557: ldc_w 495
    //   560: invokevirtual 410	android/content/res/Resources:getString	(I)Ljava/lang/String;
    //   563: bipush 6
    //   565: bipush 16
    //   567: invokevirtual 414	java/lang/String:substring	(II)Ljava/lang/String;
    //   570: iconst_1
    //   571: invokevirtual 493	java/lang/String:codePointAt	(I)I
    //   574: sipush 169
    //   577: isub
    //   578: aload_0
    //   579: invokevirtual 423	android/content/Context:getApplicationInfo	()Landroid/content/pm/ApplicationInfo;
    //   582: getfield 428	android/content/pm/ApplicationInfo:targetSdkVersion	I
    //   585: ldc_w 496
    //   588: iadd
    //   589: i2c
    //   590: aload_0
    //   591: invokevirtual 499	android/content/Context:getPackageName	()Ljava/lang/String;
    //   594: iconst_3
    //   595: invokevirtual 493	java/lang/String:codePointAt	(I)I
    //   598: bipush 75
    //   600: isub
    //   601: invokestatic 31	o/pJ:ˎ	(ICI)Ljava/lang/String;
    //   604: invokevirtual 37	java/lang/String:intern	()Ljava/lang/String;
    //   607: invokevirtual 41	java/lang/StringBuilder:append	(Ljava/lang/String;)Ljava/lang/StringBuilder;
    //   610: aload 6
    //   612: invokevirtual 41	java/lang/StringBuilder:append	(Ljava/lang/String;)Ljava/lang/StringBuilder;
    //   615: invokevirtual 49	java/lang/StringBuilder:toString	()Ljava/lang/String;
    //   618: invokestatic 441	o/pD:i	(Ljava/lang/String;Ljava/lang/String;)V
    //   621: aload_1
    //   622: ifnonnull +6 -> 628
    //   625: goto -296 -> 329
    //   628: goto +451 -> 1079
    //   631: aload 5
    //   633: invokeinterface 433 1 0
    //   638: astore 5
    //   640: aload 5
    //   642: aload_1
    //   643: invokestatic 505	com/insidesecure/hce/internal/MatrixHCENativeBridge:setRegistrationId	(Ljava/lang/String;Ljava/lang/String;)Z
    //   646: pop
    //   647: getstatic 51	o/pJ:ˎ	Ljava/lang/String;
    //   650: new 25	java/lang/StringBuilder
    //   653: dup
    //   654: invokespecial 28	java/lang/StringBuilder:<init>	()V
    //   657: aload_0
    //   658: invokevirtual 403	android/content/Context:getResources	()Landroid/content/res/Resources;
    //   661: ldc_w 506
    //   664: invokevirtual 410	android/content/res/Resources:getString	(I)Ljava/lang/String;
    //   667: bipush 24
    //   669: bipush 26
    //   671: invokevirtual 414	java/lang/String:substring	(II)Ljava/lang/String;
    //   674: invokevirtual 418	java/lang/String:length	()I
    //   677: sipush 163
    //   680: iadd
    //   681: aload_0
    //   682: invokevirtual 403	android/content/Context:getResources	()Landroid/content/res/Resources;
    //   685: ldc_w 507
    //   688: invokevirtual 410	android/content/res/Resources:getString	(I)Ljava/lang/String;
    //   691: bipush 11
    //   693: bipush 16
    //   695: invokevirtual 414	java/lang/String:substring	(II)Ljava/lang/String;
    //   698: invokevirtual 418	java/lang/String:length	()I
    //   701: iconst_5
    //   702: isub
    //   703: i2c
    //   704: aload_0
    //   705: invokevirtual 423	android/content/Context:getApplicationInfo	()Landroid/content/pm/ApplicationInfo;
    //   708: getfield 428	android/content/pm/ApplicationInfo:targetSdkVersion	I
    //   711: iconst_3
    //   712: iadd
    //   713: invokestatic 31	o/pJ:ˎ	(ICI)Ljava/lang/String;
    //   716: invokevirtual 37	java/lang/String:intern	()Ljava/lang/String;
    //   719: invokevirtual 41	java/lang/StringBuilder:append	(Ljava/lang/String;)Ljava/lang/StringBuilder;
    //   722: aload 5
    //   724: invokevirtual 41	java/lang/StringBuilder:append	(Ljava/lang/String;)Ljava/lang/StringBuilder;
    //   727: aload_0
    //   728: invokevirtual 423	android/content/Context:getApplicationInfo	()Landroid/content/pm/ApplicationInfo;
    //   731: getfield 428	android/content/pm/ApplicationInfo:targetSdkVersion	I
    //   734: sipush 199
    //   737: iadd
    //   738: aload_0
    //   739: invokevirtual 423	android/content/Context:getApplicationInfo	()Landroid/content/pm/ApplicationInfo;
    //   742: getfield 428	android/content/pm/ApplicationInfo:targetSdkVersion	I
    //   745: bipush 25
    //   747: isub
    //   748: i2c
    //   749: aload_0
    //   750: invokevirtual 403	android/content/Context:getResources	()Landroid/content/res/Resources;
    //   753: ldc_w 508
    //   756: invokevirtual 410	android/content/res/Resources:getString	(I)Ljava/lang/String;
    //   759: bipush 7
    //   761: bipush 74
    //   763: invokevirtual 414	java/lang/String:substring	(II)Ljava/lang/String;
    //   766: bipush 51
    //   768: invokevirtual 493	java/lang/String:codePointAt	(I)I
    //   771: sipush 213
    //   774: isub
    //   775: invokestatic 31	o/pJ:ˎ	(ICI)Ljava/lang/String;
    //   778: invokevirtual 37	java/lang/String:intern	()Ljava/lang/String;
    //   781: invokevirtual 41	java/lang/StringBuilder:append	(Ljava/lang/String;)Ljava/lang/StringBuilder;
    //   784: invokevirtual 49	java/lang/StringBuilder:toString	()Ljava/lang/String;
    //   787: invokestatic 441	o/pD:i	(Ljava/lang/String;Ljava/lang/String;)V
    //   790: new 510	android/content/Intent
    //   793: dup
    //   794: aload_0
    //   795: invokevirtual 403	android/content/Context:getResources	()Landroid/content/res/Resources;
    //   798: ldc_w 511
    //   801: invokevirtual 410	android/content/res/Resources:getString	(I)Ljava/lang/String;
    //   804: iconst_0
    //   805: iconst_4
    //   806: invokevirtual 414	java/lang/String:substring	(II)Ljava/lang/String;
    //   809: invokevirtual 418	java/lang/String:length	()I
    //   812: sipush 256
    //   815: iadd
    //   816: aload_0
    //   817: invokevirtual 499	android/content/Context:getPackageName	()Ljava/lang/String;
    //   820: invokevirtual 418	java/lang/String:length	()I
    //   823: ldc_w 512
    //   826: iadd
    //   827: i2c
    //   828: aload_0
    //   829: invokevirtual 423	android/content/Context:getApplicationInfo	()Landroid/content/pm/ApplicationInfo;
    //   832: getfield 428	android/content/pm/ApplicationInfo:targetSdkVersion	I
    //   835: bipush 24
    //   837: iadd
    //   838: invokestatic 31	o/pJ:ˎ	(ICI)Ljava/lang/String;
    //   841: invokevirtual 37	java/lang/String:intern	()Ljava/lang/String;
    //   844: invokespecial 515	android/content/Intent:<init>	(Ljava/lang/String;)V
    //   847: astore_1
    //   848: aload_1
    //   849: aload_0
    //   850: invokevirtual 499	android/content/Context:getPackageName	()Ljava/lang/String;
    //   853: bipush 10
    //   855: invokevirtual 493	java/lang/String:codePointAt	(I)I
    //   858: sipush 188
    //   861: iadd
    //   862: aload_0
    //   863: invokevirtual 403	android/content/Context:getResources	()Landroid/content/res/Resources;
    //   866: ldc_w 516
    //   869: invokevirtual 410	android/content/res/Resources:getString	(I)Ljava/lang/String;
    //   872: iconst_0
    //   873: iconst_4
    //   874: invokevirtual 414	java/lang/String:substring	(II)Ljava/lang/String;
    //   877: iconst_2
    //   878: invokevirtual 493	java/lang/String:codePointAt	(I)I
    //   881: sipush 28564
    //   884: iadd
    //   885: i2c
    //   886: aload_0
    //   887: invokevirtual 403	android/content/Context:getResources	()Landroid/content/res/Resources;
    //   890: ldc_w 517
    //   893: invokevirtual 410	android/content/res/Resources:getString	(I)Ljava/lang/String;
    //   896: iconst_0
    //   897: iconst_5
    //   898: invokevirtual 414	java/lang/String:substring	(II)Ljava/lang/String;
    //   901: iconst_4
    //   902: invokevirtual 493	java/lang/String:codePointAt	(I)I
    //   905: sipush 149
    //   908: isub
    //   909: invokestatic 31	o/pJ:ˎ	(ICI)Ljava/lang/String;
    //   912: invokevirtual 37	java/lang/String:intern	()Ljava/lang/String;
    //   915: aload 5
    //   917: invokevirtual 521	android/content/Intent:putExtra	(Ljava/lang/String;Ljava/lang/String;)Landroid/content/Intent;
    //   920: pop
    //   921: aload_0
    //   922: aload_1
    //   923: invokestatic 525	o/pD:sendBroadcast	(Landroid/content/Context;Landroid/content/Intent;)V
    //   926: goto -617 -> 309
    //   929: goto -630 -> 299
    //   932: astore_1
    //   933: getstatic 51	o/pJ:ˎ	Ljava/lang/String;
    //   936: new 25	java/lang/StringBuilder
    //   939: dup
    //   940: invokespecial 28	java/lang/StringBuilder:<init>	()V
    //   943: aload_0
    //   944: invokevirtual 403	android/content/Context:getResources	()Landroid/content/res/Resources;
    //   947: ldc_w 526
    //   950: invokevirtual 410	android/content/res/Resources:getString	(I)Ljava/lang/String;
    //   953: iconst_0
    //   954: bipush 8
    //   956: invokevirtual 414	java/lang/String:substring	(II)Ljava/lang/String;
    //   959: iconst_1
    //   960: invokevirtual 493	java/lang/String:codePointAt	(I)I
    //   963: bipush 97
    //   965: iadd
    //   966: aload_0
    //   967: invokevirtual 423	android/content/Context:getApplicationInfo	()Landroid/content/pm/ApplicationInfo;
    //   970: getfield 428	android/content/pm/ApplicationInfo:targetSdkVersion	I
    //   973: bipush 25
    //   975: isub
    //   976: i2c
    //   977: aload_0
    //   978: invokevirtual 423	android/content/Context:getApplicationInfo	()Landroid/content/pm/ApplicationInfo;
    //   981: getfield 428	android/content/pm/ApplicationInfo:targetSdkVersion	I
    //   984: bipush 17
    //   986: iadd
    //   987: invokestatic 31	o/pJ:ˎ	(ICI)Ljava/lang/String;
    //   990: invokevirtual 37	java/lang/String:intern	()Ljava/lang/String;
    //   993: invokevirtual 41	java/lang/StringBuilder:append	(Ljava/lang/String;)Ljava/lang/StringBuilder;
    //   996: aload_1
    //   997: invokevirtual 529	java/io/IOException:getMessage	()Ljava/lang/String;
    //   1000: invokevirtual 41	java/lang/StringBuilder:append	(Ljava/lang/String;)Ljava/lang/StringBuilder;
    //   1003: invokevirtual 49	java/lang/StringBuilder:toString	()Ljava/lang/String;
    //   1006: invokestatic 532	o/pD:e	(Ljava/lang/String;Ljava/lang/String;)V
    //   1009: aconst_null
    //   1010: astore_1
    //   1011: goto -712 -> 299
    //   1014: goto -715 -> 299
    //   1017: astore_1
    //   1018: aload_1
    //   1019: athrow
    //   1020: iconst_2
    //   1021: istore_2
    //   1022: goto -1001 -> 21
    //   1025: bipush 83
    //   1027: istore_2
    //   1028: goto +19 -> 1047
    //   1031: aload_1
    //   1032: invokevirtual 445	android/content/Context:getApplicationContext	()Landroid/content/Context;
    //   1035: invokestatic 449	o/pD:getInstance	(Landroid/content/Context;)Lo/pz;
    //   1038: astore_1
    //   1039: aload_1
    //   1040: ifnonnull +4 -> 1044
    //   1043: return
    //   1044: goto -712 -> 332
    //   1047: iload_2
    //   1048: lookupswitch	default:+28->1076, 8:+-17->1031, 83:+-765->283
    //   1076: goto -45 -> 1031
    //   1079: aload_3
    //   1080: aload_1
    //   1081: aload_0
    //   1082: invokevirtual 403	android/content/Context:getResources	()Landroid/content/res/Resources;
    //   1085: ldc_w 533
    //   1088: invokevirtual 410	android/content/res/Resources:getString	(I)Ljava/lang/String;
    //   1091: bipush 11
    //   1093: bipush 12
    //   1095: invokevirtual 414	java/lang/String:substring	(II)Ljava/lang/String;
    //   1098: iconst_0
    //   1099: invokevirtual 493	java/lang/String:codePointAt	(I)I
    //   1102: bipush 19
    //   1104: isub
    //   1105: aload_0
    //   1106: invokevirtual 403	android/content/Context:getResources	()Landroid/content/res/Resources;
    //   1109: ldc_w 534
    //   1112: invokevirtual 410	android/content/res/Resources:getString	(I)Ljava/lang/String;
    //   1115: iconst_0
    //   1116: iconst_5
    //   1117: invokevirtual 414	java/lang/String:substring	(II)Ljava/lang/String;
    //   1120: invokevirtual 418	java/lang/String:length	()I
    //   1123: sipush 12173
    //   1126: iadd
    //   1127: i2c
    //   1128: aload_0
    //   1129: invokevirtual 403	android/content/Context:getResources	()Landroid/content/res/Resources;
    //   1132: ldc_w 535
    //   1135: invokevirtual 410	android/content/res/Resources:getString	(I)Ljava/lang/String;
    //   1138: iconst_0
    //   1139: bipush 9
    //   1141: invokevirtual 414	java/lang/String:substring	(II)Ljava/lang/String;
    //   1144: invokevirtual 418	java/lang/String:length	()I
    //   1147: bipush 6
    //   1149: isub
    //   1150: invokestatic 31	o/pJ:ˎ	(ICI)Ljava/lang/String;
    //   1153: invokevirtual 37	java/lang/String:intern	()Ljava/lang/String;
    //   1156: invokevirtual 538	o/gT:ˊ	(Ljava/lang/String;Ljava/lang/String;)Ljava/lang/String;
    //   1159: astore_1
    //   1160: getstatic 51	o/pJ:ˎ	Ljava/lang/String;
    //   1163: new 25	java/lang/StringBuilder
    //   1166: dup
    //   1167: invokespecial 28	java/lang/StringBuilder:<init>	()V
    //   1170: aload_0
    //   1171: invokevirtual 499	android/content/Context:getPackageName	()Ljava/lang/String;
    //   1174: iconst_5
    //   1175: invokevirtual 493	java/lang/String:codePointAt	(I)I
    //   1178: bipush 14
    //   1180: isub
    //   1181: aload_0
    //   1182: invokevirtual 403	android/content/Context:getResources	()Landroid/content/res/Resources;
    //   1185: ldc_w 539
    //   1188: invokevirtual 410	android/content/res/Resources:getString	(I)Ljava/lang/String;
    //   1191: iconst_0
    //   1192: iconst_4
    //   1193: invokevirtual 414	java/lang/String:substring	(II)Ljava/lang/String;
    //   1196: invokevirtual 418	java/lang/String:length	()I
    //   1199: sipush 2405
    //   1202: iadd
    //   1203: i2c
    //   1204: aload_0
    //   1205: invokevirtual 423	android/content/Context:getApplicationInfo	()Landroid/content/pm/ApplicationInfo;
    //   1208: getfield 428	android/content/pm/ApplicationInfo:targetSdkVersion	I
    //   1211: iconst_2
    //   1212: isub
    //   1213: invokestatic 31	o/pJ:ˎ	(ICI)Ljava/lang/String;
    //   1216: invokevirtual 37	java/lang/String:intern	()Ljava/lang/String;
    //   1219: invokevirtual 41	java/lang/StringBuilder:append	(Ljava/lang/String;)Ljava/lang/StringBuilder;
    //   1222: aload_1
    //   1223: invokevirtual 41	java/lang/StringBuilder:append	(Ljava/lang/String;)Ljava/lang/StringBuilder;
    //   1226: invokevirtual 49	java/lang/StringBuilder:toString	()Ljava/lang/String;
    //   1229: invokestatic 441	o/pD:i	(Ljava/lang/String;Ljava/lang/String;)V
    //   1232: goto -1003 -> 229
    //   1235: bipush 8
    //   1237: istore_2
    //   1238: goto -191 -> 1047
    // Local variable table:
    //   start	length	slot	name	signature
    //   0	1241	0	this	pJ
    //   0	1241	1	paramContext	Context
    //   21	1217	2	i	int
    //   336	744	3	localGT	gT
    //   309	43	4	localIterator	java.util.Iterator
    //   140	776	5	localObject1	Object
    //   4	607	6	localObject2	Object
    //   68	25	7	localObject3	Object
    // Exception table:
    //   from	to	target	type
    //   64	70	323	java/lang/Exception
    //   1079	1232	932	java/io/IOException
    //   51	64	1017	java/lang/Exception
    //   64	70	1017	java/lang/Exception
    //   70	80	1017	java/lang/Exception
    //   80	89	1017	java/lang/Exception
    //   89	220	1017	java/lang/Exception
  }
  
  public Resources getResources()
  {
    for (;;)
    {
      Resources localResources = oH.ˊ(super.getResources());
      int i = ʼ + 1;
      ˋ = i % 128;
      if (i % 2 != 0) {
        return localResources;
      }
      return localResources;
      do
      {
        break;
        i = ˋ + 63;
        ʼ = i % 128;
      } while (i % 2 == 0);
    }
  }
  
  public void onTokenRefresh()
  {
    for (;;)
    {
      int i;
      switch (i)
      {
      case 39: 
      default: 
        i = 91 / 0;
        return;
        for (;;)
        {
          pD.w(ˎ, ˎ(getResources().getString(2131755501).substring(0, 4).codePointAt(0) - 5, (char)(getResources().getString(2131755045).substring(0, 4).length() - 4), getPackageName().codePointAt(3) - 55).intern());
          Runnable local5 = new Runnable()
          {
            public void run()
            {
              pJ.ॱ(pJ.this, pJ.this);
            }
          };
          new Handler(Looper.getMainLooper()).post(local5);
          do
          {
            i = 39;
            break;
            i = ʼ + 1;
            ˋ = i % 128;
          } while (i % 2 != 0);
          break label165;
        }
        label165:
        i = 97;
      }
    }
  }
}
