package o;

import android.content.Context;
import android.os.AsyncTask;
import android.os.Handler;

public class pM
{
  private static char[] ʽ;
  private static long ˊॱ;
  private static final String ˋ;
  private static int ˋॱ;
  private static int ॱˊ;
  private final Handler ʻ = new Handler();
  private pH ʼ;
  private Runnable ˊ;
  private int ˎ = -1;
  pz ˏ;
  private String ॱ;
  private String ॱॱ;
  private Context ᐝ;
  
  static
  {
    break label39;
    int i = 49;
    break label10;
    return;
    for (;;)
    {
      switch (i)
      {
      case 49: 
      default: 
        break label114;
        ˋॱ = 0;
        ॱˊ = 1;
        ˋ();
        ˋ = ॱ(299, 64114, 19).intern() + pM.class.getSimpleName();
        i = ॱˊ + 121;
        ˋॱ = i % 128;
        if (i % 2 != 0) {}
        break;
      case 75: 
        label10:
        label39:
        label114:
        throw new NullPointerException();
        i = 75;
      }
    }
  }
  
  public pM(Context paramContext, pz paramPz, String paramString1, String paramString2)
  {
    this.ᐝ = paramContext;
    this.ˏ = paramPz;
    this.ʼ = null;
    this.ॱ = paramString1;
    this.ॱॱ = paramString2;
  }
  
  private void ʽ()
  {
    break label36;
    return;
    int i = 0;
    for (;;)
    {
      i = ॱˊ + 79;
      ˋॱ = i % 128;
      if (i % 2 == 0)
      {
        break;
        label36:
        break label78;
        throw new NullPointerException();
      }
      for (;;)
      {
        switch (i)
        {
        }
        return;
        i = 1;
      }
      label78:
      new AsyncTask()
      {
        private static int ˊ = 1;
        private static int ˋ = 0;
        private static int[] ॱ = { -756796179, -147858908, 206094150, 224672167, 1241561108, -888311960, 1509356818, -1720274577, 1963038962, 978471205, -1148610766, -671020601, -1266234856, 399316871, 57771465, -430261208, 841884857, 793013977 };
        
        private static String ˎ(int[] paramAnonymousArrayOfInt, int paramAnonymousInt)
        {
          break label126;
          char[] arrayOfChar1 = new char[4];
          char[] arrayOfChar2 = new char[paramAnonymousArrayOfInt.length << 1];
          int[] arrayOfInt1 = (int[])ॱ.clone();
          int i = 0;
          break label75;
          return new String(arrayOfChar2, 0, paramAnonymousInt);
          for (;;)
          {
            label44:
            int j;
            label75:
            int[] arrayOfInt2;
            switch (j)
            {
            case 74: 
            default: 
              break;
              for (;;)
              {
                arrayOfInt2 = paramAnonymousArrayOfInt;
                if (i < arrayOfInt2.length) {
                  break label333;
                }
                break;
                arrayOfChar1 = new char[3];
                arrayOfChar2 = new char[paramAnonymousArrayOfInt.length >> 1];
                arrayOfInt1 = (int[])ॱ.clone();
                i = 0;
              }
              for (;;)
              {
                i = 48;
                break;
                i = ˋ + 125;
                ˊ = i % 128;
                if (i % 2 != 0) {
                  break label327;
                }
              }
            case 80: 
              for (;;)
              {
                label126:
                switch (i)
                {
                }
                break;
                j = 74;
                break label44;
                for (;;)
                {
                  arrayOfChar1[0] = ((char)(arrayOfInt2[i] >> 16));
                  arrayOfChar1[1] = ((char)arrayOfInt2[i]);
                  arrayOfChar1[2] = ((char)(arrayOfInt2[(i + 1)] >> 16));
                  arrayOfChar1[3] = ((char)arrayOfInt2[(i + 1)]);
                  oN.ˏ(arrayOfChar1, arrayOfInt1, false);
                  arrayOfChar2[(i << 1)] = arrayOfChar1[0];
                  arrayOfChar2[((i << 1) + 1)] = arrayOfChar1[1];
                  arrayOfChar2[((i << 1) + 2)] = arrayOfChar1[2];
                  arrayOfChar2[((i << 1) + 3)] = arrayOfChar1[3];
                  i += 2;
                  break;
                  do
                  {
                    break;
                    j = ˋ + 125;
                    ˊ = j % 128;
                  } while (j % 2 == 0);
                }
                label327:
                i = 70;
              }
              label333:
              j = 80;
            }
          }
        }
        
        /* Error */
        protected void ˊ(String arg1)
        {
          // Byte code:
          //   0: goto +319 -> 319
          //   3: iload_2
          //   4: tableswitch	default:+24->28, 0:+621->625, 1:+122->126
          //   28: goto +597 -> 625
          //   31: bipush 6
          //   33: istore_2
          //   34: goto +35 -> 69
          //   37: getstatic 22	o/pM$2:ˊ	I
          //   40: bipush 31
          //   42: iadd
          //   43: istore_2
          //   44: iload_2
          //   45: sipush 128
          //   48: irem
          //   49: putstatic 20	o/pM$2:ˋ	I
          //   52: iload_2
          //   53: iconst_2
          //   54: irem
          //   55: ifeq +6 -> 61
          //   58: goto +60 -> 118
          //   61: goto +257 -> 318
          //   64: iconst_1
          //   65: istore_2
          //   66: goto -63 -> 3
          //   69: iload_2
          //   70: lookupswitch	default:+26->96, 6:+56->126, 95:+555->625
          //   96: goto +30 -> 126
          //   99: bipush 95
          //   101: istore_2
          //   102: goto -33 -> 69
          //   105: aload_1
          //   106: ifnull +6 -> 112
          //   109: goto -10 -> 99
          //   112: goto -81 -> 31
          //   115: astore_1
          //   116: aload_1
          //   117: athrow
          //   118: goto +200 -> 318
          //   121: iconst_0
          //   122: istore_2
          //   123: goto -120 -> 3
          //   126: invokestatic 83	o/pM:ˊ	()Ljava/lang/String;
          //   129: new 85	java/lang/StringBuilder
          //   132: dup
          //   133: invokespecial 86	java/lang/StringBuilder:<init>	()V
          //   136: bipush 24
          //   138: newarray int
          //   140: dup
          //   141: iconst_0
          //   142: ldc 87
          //   144: iastore
          //   145: dup
          //   146: iconst_1
          //   147: ldc 88
          //   149: iastore
          //   150: dup
          //   151: iconst_2
          //   152: ldc 89
          //   154: iastore
          //   155: dup
          //   156: iconst_3
          //   157: ldc 90
          //   159: iastore
          //   160: dup
          //   161: iconst_4
          //   162: ldc 91
          //   164: iastore
          //   165: dup
          //   166: iconst_5
          //   167: ldc 92
          //   169: iastore
          //   170: dup
          //   171: bipush 6
          //   173: ldc 93
          //   175: iastore
          //   176: dup
          //   177: bipush 7
          //   179: ldc 94
          //   181: iastore
          //   182: dup
          //   183: bipush 8
          //   185: ldc 95
          //   187: iastore
          //   188: dup
          //   189: bipush 9
          //   191: ldc 96
          //   193: iastore
          //   194: dup
          //   195: bipush 10
          //   197: ldc 97
          //   199: iastore
          //   200: dup
          //   201: bipush 11
          //   203: ldc 98
          //   205: iastore
          //   206: dup
          //   207: bipush 12
          //   209: ldc 99
          //   211: iastore
          //   212: dup
          //   213: bipush 13
          //   215: ldc 100
          //   217: iastore
          //   218: dup
          //   219: bipush 14
          //   221: ldc 101
          //   223: iastore
          //   224: dup
          //   225: bipush 15
          //   227: ldc 102
          //   229: iastore
          //   230: dup
          //   231: bipush 16
          //   233: ldc 103
          //   235: iastore
          //   236: dup
          //   237: bipush 17
          //   239: ldc 104
          //   241: iastore
          //   242: dup
          //   243: bipush 18
          //   245: ldc 105
          //   247: iastore
          //   248: dup
          //   249: bipush 19
          //   251: ldc 106
          //   253: iastore
          //   254: dup
          //   255: bipush 20
          //   257: ldc 107
          //   259: iastore
          //   260: dup
          //   261: bipush 21
          //   263: ldc 108
          //   265: iastore
          //   266: dup
          //   267: bipush 22
          //   269: ldc 109
          //   271: iastore
          //   272: dup
          //   273: bipush 23
          //   275: ldc 110
          //   277: iastore
          //   278: bipush 48
          //   280: invokestatic 112	o/pM$2:ˎ	([II)Ljava/lang/String;
          //   283: invokevirtual 115	java/lang/String:intern	()Ljava/lang/String;
          //   286: invokevirtual 119	java/lang/StringBuilder:append	(Ljava/lang/String;)Ljava/lang/StringBuilder;
          //   289: aload_0
          //   290: getfield 47	o/pM$2:ˎ	Lo/pM;
          //   293: invokestatic 123	o/pM:ᐝ	(Lo/pM;)Ljava/lang/String;
          //   296: invokevirtual 119	java/lang/StringBuilder:append	(Ljava/lang/String;)Ljava/lang/StringBuilder;
          //   299: invokevirtual 126	java/lang/StringBuilder:toString	()Ljava/lang/String;
          //   302: invokestatic 132	o/pD:w	(Ljava/lang/String;Ljava/lang/String;)V
          //   305: aload_0
          //   306: getfield 47	o/pM$2:ˎ	Lo/pM;
          //   309: getstatic 137	o/pM$If:ˎ	Lo/pM$If;
          //   312: ldc -117
          //   314: invokestatic 142	o/pM:ˋ	(Lo/pM;Lo/pM$If;Ljava/lang/String;)V
          //   317: return
          //   318: return
          //   319: goto +279 -> 598
          //   322: invokestatic 83	o/pM:ˊ	()Ljava/lang/String;
          //   325: astore_3
          //   326: new 85	java/lang/StringBuilder
          //   329: dup
          //   330: invokespecial 86	java/lang/StringBuilder:<init>	()V
          //   333: astore 4
          //   335: bipush 20
          //   337: newarray int
          //   339: dup
          //   340: iconst_0
          //   341: ldc -113
          //   343: iastore
          //   344: dup
          //   345: iconst_1
          //   346: ldc -112
          //   348: iastore
          //   349: dup
          //   350: iconst_2
          //   351: ldc -111
          //   353: iastore
          //   354: dup
          //   355: iconst_3
          //   356: ldc -110
          //   358: iastore
          //   359: dup
          //   360: iconst_4
          //   361: ldc -109
          //   363: iastore
          //   364: dup
          //   365: iconst_5
          //   366: ldc -108
          //   368: iastore
          //   369: dup
          //   370: bipush 6
          //   372: ldc -107
          //   374: iastore
          //   375: dup
          //   376: bipush 7
          //   378: ldc -106
          //   380: iastore
          //   381: dup
          //   382: bipush 8
          //   384: ldc -105
          //   386: iastore
          //   387: dup
          //   388: bipush 9
          //   390: ldc -104
          //   392: iastore
          //   393: dup
          //   394: bipush 10
          //   396: ldc -103
          //   398: iastore
          //   399: dup
          //   400: bipush 11
          //   402: ldc -102
          //   404: iastore
          //   405: dup
          //   406: bipush 12
          //   408: ldc -101
          //   410: iastore
          //   411: dup
          //   412: bipush 13
          //   414: ldc -100
          //   416: iastore
          //   417: dup
          //   418: bipush 14
          //   420: ldc -99
          //   422: iastore
          //   423: dup
          //   424: bipush 15
          //   426: ldc -98
          //   428: iastore
          //   429: dup
          //   430: bipush 16
          //   432: ldc -97
          //   434: iastore
          //   435: dup
          //   436: bipush 17
          //   438: ldc -96
          //   440: iastore
          //   441: dup
          //   442: bipush 18
          //   444: ldc -95
          //   446: iastore
          //   447: dup
          //   448: bipush 19
          //   450: ldc -94
          //   452: iastore
          //   453: bipush 39
          //   455: invokestatic 112	o/pM$2:ˎ	([II)Ljava/lang/String;
          //   458: astore 5
          //   460: aload 5
          //   462: invokevirtual 115	java/lang/String:intern	()Ljava/lang/String;
          //   465: astore 5
          //   467: aload 4
          //   469: aload 5
          //   471: invokevirtual 119	java/lang/StringBuilder:append	(Ljava/lang/String;)Ljava/lang/StringBuilder;
          //   474: astore 4
          //   476: aload_3
          //   477: aload 4
          //   479: aload_0
          //   480: getfield 47	o/pM$2:ˎ	Lo/pM;
          //   483: invokestatic 123	o/pM:ᐝ	(Lo/pM;)Ljava/lang/String;
          //   486: invokevirtual 119	java/lang/StringBuilder:append	(Ljava/lang/String;)Ljava/lang/StringBuilder;
          //   489: bipush 10
          //   491: newarray int
          //   493: dup
          //   494: iconst_0
          //   495: ldc -93
          //   497: iastore
          //   498: dup
          //   499: iconst_1
          //   500: ldc -92
          //   502: iastore
          //   503: dup
          //   504: iconst_2
          //   505: ldc -91
          //   507: iastore
          //   508: dup
          //   509: iconst_3
          //   510: ldc -90
          //   512: iastore
          //   513: dup
          //   514: iconst_4
          //   515: ldc -89
          //   517: iastore
          //   518: dup
          //   519: iconst_5
          //   520: ldc -88
          //   522: iastore
          //   523: dup
          //   524: bipush 6
          //   526: ldc -87
          //   528: iastore
          //   529: dup
          //   530: bipush 7
          //   532: ldc -86
          //   534: iastore
          //   535: dup
          //   536: bipush 8
          //   538: ldc -85
          //   540: iastore
          //   541: dup
          //   542: bipush 9
          //   544: ldc -84
          //   546: iastore
          //   547: bipush 19
          //   549: invokestatic 112	o/pM$2:ˎ	([II)Ljava/lang/String;
          //   552: invokevirtual 115	java/lang/String:intern	()Ljava/lang/String;
          //   555: invokevirtual 119	java/lang/StringBuilder:append	(Ljava/lang/String;)Ljava/lang/StringBuilder;
          //   558: aload_1
          //   559: invokevirtual 119	java/lang/StringBuilder:append	(Ljava/lang/String;)Ljava/lang/StringBuilder;
          //   562: invokevirtual 126	java/lang/StringBuilder:toString	()Ljava/lang/String;
          //   565: invokestatic 175	o/pD:d	(Ljava/lang/String;Ljava/lang/String;)V
          //   568: aload_0
          //   569: getfield 47	o/pM$2:ˎ	Lo/pM;
          //   572: getstatic 177	o/pM$If:ˋ	Lo/pM$If;
          //   575: aload_1
          //   576: invokestatic 142	o/pM:ˋ	(Lo/pM;Lo/pM$If;Ljava/lang/String;)V
          //   579: goto -542 -> 37
          //   582: aconst_null
          //   583: arraylength
          //   584: istore_2
          //   585: aload_1
          //   586: ifnull +6 -> 592
          //   589: goto -468 -> 121
          //   592: goto -528 -> 64
          //   595: astore_1
          //   596: aload_1
          //   597: athrow
          //   598: getstatic 22	o/pM$2:ˊ	I
          //   601: bipush 29
          //   603: iadd
          //   604: istore_2
          //   605: iload_2
          //   606: sipush 128
          //   609: irem
          //   610: putstatic 20	o/pM$2:ˋ	I
          //   613: iload_2
          //   614: iconst_2
          //   615: irem
          //   616: ifeq +6 -> 622
          //   619: goto -37 -> 582
          //   622: goto -517 -> 105
          //   625: aload_1
          //   626: invokestatic 183	android/text/TextUtils:isEmpty	(Ljava/lang/CharSequence;)Z
          //   629: ifeq +6 -> 635
          //   632: goto -506 -> 126
          //   635: goto -313 -> 322
          // Exception table:
          //   from	to	target	type
          //   322	335	115	java/lang/Exception
          //   335	460	115	java/lang/Exception
          //   460	467	115	java/lang/Exception
          //   467	476	115	java/lang/Exception
          //   476	579	115	java/lang/Exception
        }
        
        /* Error */
        protected String ˎ(Void... paramAnonymousVarArgs)
        {
          // Byte code:
          //   0: goto +202 -> 202
          //   3: astore_1
          //   4: invokestatic 83	o/pM:ˊ	()Ljava/lang/String;
          //   7: new 85	java/lang/StringBuilder
          //   10: dup
          //   11: invokespecial 86	java/lang/StringBuilder:<init>	()V
          //   14: bipush 16
          //   16: newarray int
          //   18: dup
          //   19: iconst_0
          //   20: ldc -70
          //   22: iastore
          //   23: dup
          //   24: iconst_1
          //   25: ldc -69
          //   27: iastore
          //   28: dup
          //   29: iconst_2
          //   30: ldc -68
          //   32: iastore
          //   33: dup
          //   34: iconst_3
          //   35: ldc -67
          //   37: iastore
          //   38: dup
          //   39: iconst_4
          //   40: ldc -66
          //   42: iastore
          //   43: dup
          //   44: iconst_5
          //   45: ldc -65
          //   47: iastore
          //   48: dup
          //   49: bipush 6
          //   51: ldc -91
          //   53: iastore
          //   54: dup
          //   55: bipush 7
          //   57: ldc -90
          //   59: iastore
          //   60: dup
          //   61: bipush 8
          //   63: ldc -64
          //   65: iastore
          //   66: dup
          //   67: bipush 9
          //   69: ldc -63
          //   71: iastore
          //   72: dup
          //   73: bipush 10
          //   75: ldc -107
          //   77: iastore
          //   78: dup
          //   79: bipush 11
          //   81: ldc -106
          //   83: iastore
          //   84: dup
          //   85: bipush 12
          //   87: ldc -62
          //   89: iastore
          //   90: dup
          //   91: bipush 13
          //   93: ldc -61
          //   95: iastore
          //   96: dup
          //   97: bipush 14
          //   99: ldc -60
          //   101: iastore
          //   102: dup
          //   103: bipush 15
          //   105: ldc -59
          //   107: iastore
          //   108: bipush 29
          //   110: invokestatic 112	o/pM$2:ˎ	([II)Ljava/lang/String;
          //   113: invokevirtual 115	java/lang/String:intern	()Ljava/lang/String;
          //   116: invokevirtual 119	java/lang/StringBuilder:append	(Ljava/lang/String;)Ljava/lang/StringBuilder;
          //   119: aload_1
          //   120: invokevirtual 200	java/io/IOException:getMessage	()Ljava/lang/String;
          //   123: invokevirtual 119	java/lang/StringBuilder:append	(Ljava/lang/String;)Ljava/lang/StringBuilder;
          //   126: invokevirtual 126	java/lang/StringBuilder:toString	()Ljava/lang/String;
          //   129: invokestatic 175	o/pD:d	(Ljava/lang/String;Ljava/lang/String;)V
          //   132: aconst_null
          //   133: areturn
          //   134: getstatic 22	o/pM$2:ˊ	I
          //   137: bipush 15
          //   139: iadd
          //   140: istore_2
          //   141: iload_2
          //   142: sipush 128
          //   145: irem
          //   146: putstatic 20	o/pM$2:ˋ	I
          //   149: iload_2
          //   150: iconst_2
          //   151: irem
          //   152: ifeq +6 -> 158
          //   155: goto +309 -> 464
          //   158: aload_0
          //   159: getfield 47	o/pM$2:ˎ	Lo/pM;
          //   162: invokestatic 203	o/pM:ˋ	(Lo/pM;)Landroid/content/Context;
          //   165: invokestatic 208	o/gT:ˊ	(Landroid/content/Context;)Lo/gT;
          //   168: aload_0
          //   169: getfield 47	o/pM$2:ˎ	Lo/pM;
          //   172: invokestatic 210	o/pM:ˎ	(Lo/pM;)Ljava/lang/String;
          //   175: iconst_2
          //   176: newarray int
          //   178: dup
          //   179: iconst_0
          //   180: ldc -45
          //   182: iastore
          //   183: dup
          //   184: iconst_1
          //   185: ldc -44
          //   187: iastore
          //   188: iconst_3
          //   189: invokestatic 112	o/pM$2:ˎ	([II)Ljava/lang/String;
          //   192: invokevirtual 115	java/lang/String:intern	()Ljava/lang/String;
          //   195: invokevirtual 215	o/gT:ˊ	(Ljava/lang/String;Ljava/lang/String;)Ljava/lang/String;
          //   198: astore_1
          //   199: goto +268 -> 467
          //   202: goto -68 -> 134
          //   205: aload_1
          //   206: areturn
          //   207: astore_1
          //   208: invokestatic 83	o/pM:ˊ	()Ljava/lang/String;
          //   211: new 85	java/lang/StringBuilder
          //   214: dup
          //   215: invokespecial 86	java/lang/StringBuilder:<init>	()V
          //   218: bipush 16
          //   220: newarray int
          //   222: dup
          //   223: iconst_0
          //   224: ldc -70
          //   226: iastore
          //   227: dup
          //   228: iconst_1
          //   229: ldc -69
          //   231: iastore
          //   232: dup
          //   233: iconst_2
          //   234: ldc -68
          //   236: iastore
          //   237: dup
          //   238: iconst_3
          //   239: ldc -67
          //   241: iastore
          //   242: dup
          //   243: iconst_4
          //   244: ldc -66
          //   246: iastore
          //   247: dup
          //   248: iconst_5
          //   249: ldc -65
          //   251: iastore
          //   252: dup
          //   253: bipush 6
          //   255: ldc -91
          //   257: iastore
          //   258: dup
          //   259: bipush 7
          //   261: ldc -90
          //   263: iastore
          //   264: dup
          //   265: bipush 8
          //   267: ldc -64
          //   269: iastore
          //   270: dup
          //   271: bipush 9
          //   273: ldc -63
          //   275: iastore
          //   276: dup
          //   277: bipush 10
          //   279: ldc -107
          //   281: iastore
          //   282: dup
          //   283: bipush 11
          //   285: ldc -106
          //   287: iastore
          //   288: dup
          //   289: bipush 12
          //   291: ldc -62
          //   293: iastore
          //   294: dup
          //   295: bipush 13
          //   297: ldc -61
          //   299: iastore
          //   300: dup
          //   301: bipush 14
          //   303: ldc -60
          //   305: iastore
          //   306: dup
          //   307: bipush 15
          //   309: ldc -59
          //   311: iastore
          //   312: bipush 29
          //   314: invokestatic 112	o/pM$2:ˎ	([II)Ljava/lang/String;
          //   317: invokevirtual 115	java/lang/String:intern	()Ljava/lang/String;
          //   320: invokevirtual 119	java/lang/StringBuilder:append	(Ljava/lang/String;)Ljava/lang/StringBuilder;
          //   323: aload_1
          //   324: invokevirtual 216	java/lang/Exception:getMessage	()Ljava/lang/String;
          //   327: invokevirtual 119	java/lang/StringBuilder:append	(Ljava/lang/String;)Ljava/lang/StringBuilder;
          //   330: invokevirtual 126	java/lang/StringBuilder:toString	()Ljava/lang/String;
          //   333: invokestatic 219	o/pD:e	(Ljava/lang/String;Ljava/lang/String;)V
          //   336: invokestatic 83	o/pM:ˊ	()Ljava/lang/String;
          //   339: bipush 18
          //   341: newarray int
          //   343: dup
          //   344: iconst_0
          //   345: ldc -36
          //   347: iastore
          //   348: dup
          //   349: iconst_1
          //   350: ldc -35
          //   352: iastore
          //   353: dup
          //   354: iconst_2
          //   355: ldc -34
          //   357: iastore
          //   358: dup
          //   359: iconst_3
          //   360: ldc -33
          //   362: iastore
          //   363: dup
          //   364: iconst_4
          //   365: ldc -32
          //   367: iastore
          //   368: dup
          //   369: iconst_5
          //   370: ldc -31
          //   372: iastore
          //   373: dup
          //   374: bipush 6
          //   376: ldc -30
          //   378: iastore
          //   379: dup
          //   380: bipush 7
          //   382: ldc -29
          //   384: iastore
          //   385: dup
          //   386: bipush 8
          //   388: ldc -28
          //   390: iastore
          //   391: dup
          //   392: bipush 9
          //   394: ldc -27
          //   396: iastore
          //   397: dup
          //   398: bipush 10
          //   400: ldc -26
          //   402: iastore
          //   403: dup
          //   404: bipush 11
          //   406: ldc -25
          //   408: iastore
          //   409: dup
          //   410: bipush 12
          //   412: ldc -24
          //   414: iastore
          //   415: dup
          //   416: bipush 13
          //   418: ldc -23
          //   420: iastore
          //   421: dup
          //   422: bipush 14
          //   424: ldc -22
          //   426: iastore
          //   427: dup
          //   428: bipush 15
          //   430: ldc -21
          //   432: iastore
          //   433: dup
          //   434: bipush 16
          //   436: ldc -20
          //   438: iastore
          //   439: dup
          //   440: bipush 17
          //   442: ldc -19
          //   444: iastore
          //   445: bipush 34
          //   447: invokestatic 112	o/pM$2:ˎ	([II)Ljava/lang/String;
          //   450: invokevirtual 115	java/lang/String:intern	()Ljava/lang/String;
          //   453: invokestatic 219	o/pD:e	(Ljava/lang/String;Ljava/lang/String;)V
          //   456: aconst_null
          //   457: areturn
          //   458: astore_1
          //   459: aload_1
          //   460: athrow
          //   461: goto -256 -> 205
          //   464: goto -306 -> 158
          //   467: getstatic 22	o/pM$2:ˊ	I
          //   470: bipush 107
          //   472: iadd
          //   473: istore_2
          //   474: iload_2
          //   475: sipush 128
          //   478: irem
          //   479: putstatic 20	o/pM$2:ˋ	I
          //   482: iload_2
          //   483: iconst_2
          //   484: irem
          //   485: ifeq +6 -> 491
          //   488: goto -27 -> 461
          //   491: goto -286 -> 205
          // Local variable table:
          //   start	length	slot	name	signature
          //   0	494	0	this	2
          //   0	494	1	paramAnonymousVarArgs	Void[]
          //   140	345	2	i	int
          // Exception table:
          //   from	to	target	type
          //   158	199	3	java/io/IOException
          //   158	199	207	java/lang/Exception
          //   134	141	458	java/lang/Exception
          //   141	149	458	java/lang/Exception
        }
      }.execute(new Void[] { null, null, null });
    }
  }
  
  static void ˋ()
  {
    ˊॱ = 8911804051842840345L;
    ʽ = new char[] { -28848, 14446, -7856, -21958, 21267, 7195, -14863, -29044, 14265, -8057, -22114, 20857, 6748, -15566, -29649, 13589, -281, -22589, 20654, 6582, -15657, -30104, 13130, -946, -23173, 32, -18578, 28251, 9535, -9204, -27811, 19142, 477, -18265, 28555, 9887, -8592, -27304, 19557, 791, -17869, 29104, 25033, -10599, 4021, 17538, -16913, -3339, 11036, 24621, -9914, 3706, 18300, -16497, -2901, 11720, 82, -18564, 28245, 9506, -9193, -27895, 19172, 462, -18244, 28552, 9877, -8579, -27380, 19468, 794, -17833, 29169, 10437, -8272, -26946, 19861, 1385, -17313, 29471, 10809, -7929, -26389, 20426, 1744, -16972, 29836, 11371, -7355, 85, -18569, 28224, 9518, -9213, -27884, 19173, 475, -18259, 28563, 9875, -8579, -27317, 19557, 793, -17868, 29149, 10377, -8276, -26946, 19840, 1402, -17335, 29517, 10803, -7855, -26376, 20422, 1759, -16976, 29831, 11377, -7355, -26037, 71, -18598, 28287, 9579, -9194, -27880, 19185, 454, -18245, 28565, 9864, -8590, -27304, 19500, 817, -17895, 29104, 10459, -8281, -26968, 19841, 1377, -17326, 29445, 10872, -22694, 4193, -14011, -32207, 31512, 13320, -4637, -22817, 8127, -14177, -32317, 31096, 12880, -5336, -23499, 7447, -10583, -28712, 30906, 12716, -5495, -23944, 7002, -11180, 71, -18598, 28287, 9579, -9162, -27880, 19185, 454, -18245, 28565, 9864, -8590, -27304, 19500, 817, -17895, 29104, 10464, -8314, -26911, 19924, 85, -18569, 28224, 9518, -9213, -27884, 19173, 475, -18259, 28563, 9875, -8579, -27317, 19557, 816, -17902, 29156, 10462, -8275, -26967, 19871, 1325, -17323, 29515, 10809, -7931, -26385, 20355, 1742, -16976, 29837, 11362, -7351, -26033, 20791, 2073, 82, -18564, 28245, 9506, -9193, -27895, 19187, 477, -18271, 28559, 9885, -8653, -27326, 19488, 810, -17920, 29183, 10459, -8279, -26885, 19847, 1401, -17337, 29515, 10813, -7855, -26376, 20422, 1759, -16976, 29831, 11377, -7355, -26037, -31953, 13369, -4840, -22921, 24389, 4186, -13892, -32049, 15336, -4918, -23104, 23923, 5633, -12444, -32642, 14679, -3344, -21596, 23747, 5595, -12556, -31226, 16171, -4059, -22177, 25193, 7053, -13127, -31317, 16068, -2077, -20735, 24623, 6457, -11685, -29856, -1473, 19722, -27596, -8373, 9855, 26999, -20308, -1122, 17151, -27203, -8990, 9216, 28456, -18858, -1791, 16484, -29806, -11598, 9630 };
  }
  
  /* Error */
  private void ˏ(If paramIf, String paramString)
  {
    // Byte code:
    //   0: goto +106 -> 106
    //   3: aload_0
    //   4: new 8	o/pM$4
    //   7: dup
    //   8: aload_0
    //   9: invokespecial 387	o/pM$4:<init>	(Lo/pM;)V
    //   12: putfield 91	o/pM:ʼ	Lo/pH;
    //   15: getstatic 72	o/pM:ˋ	Ljava/lang/String;
    //   18: sipush 229
    //   21: iconst_0
    //   22: bipush 34
    //   24: invokestatic 52	o/pM:ॱ	(ICI)Ljava/lang/String;
    //   27: invokevirtual 58	java/lang/String:intern	()Ljava/lang/String;
    //   30: invokestatic 393	o/pD:d	(Ljava/lang/String;Ljava/lang/String;)V
    //   33: aload_0
    //   34: getfield 87	o/pM:ᐝ	Landroid/content/Context;
    //   37: aload_0
    //   38: getfield 91	o/pM:ʼ	Lo/pH;
    //   41: new 395	android/content/IntentFilter
    //   44: dup
    //   45: sipush 263
    //   48: ldc_w 396
    //   51: bipush 36
    //   53: invokestatic 52	o/pM:ॱ	(ICI)Ljava/lang/String;
    //   56: invokevirtual 58	java/lang/String:intern	()Ljava/lang/String;
    //   59: invokespecial 399	android/content/IntentFilter:<init>	(Ljava/lang/String;)V
    //   62: invokevirtual 405	android/content/Context:registerReceiver	(Landroid/content/BroadcastReceiver;Landroid/content/IntentFilter;)Landroid/content/Intent;
    //   65: pop
    //   66: goto +297 -> 363
    //   69: getstatic 41	o/pM:ॱˊ	I
    //   72: bipush 111
    //   74: iadd
    //   75: istore_3
    //   76: iload_3
    //   77: sipush 128
    //   80: irem
    //   81: putstatic 39	o/pM:ˋॱ	I
    //   84: iload_3
    //   85: iconst_2
    //   86: irem
    //   87: ifeq +6 -> 93
    //   90: goto +209 -> 299
    //   93: aload_0
    //   94: getfield 110	o/pM:ˊ	Ljava/lang/Runnable;
    //   97: ifnull +6 -> 103
    //   100: goto +77 -> 177
    //   103: goto +335 -> 438
    //   106: goto +282 -> 388
    //   109: astore_1
    //   110: aload_1
    //   111: athrow
    //   112: getstatic 41	o/pM:ॱˊ	I
    //   115: bipush 7
    //   117: iadd
    //   118: istore_3
    //   119: iload_3
    //   120: sipush 128
    //   123: irem
    //   124: putstatic 39	o/pM:ˋॱ	I
    //   127: iload_3
    //   128: iconst_2
    //   129: irem
    //   130: ifeq +6 -> 136
    //   133: goto +74 -> 207
    //   136: goto +166 -> 302
    //   139: bipush 17
    //   141: istore_3
    //   142: goto +353 -> 495
    //   145: iload_3
    //   146: tableswitch	default:+22->168, 0:+-77->69, 1:+292->438
    //   168: goto -99 -> 69
    //   171: iconst_0
    //   172: istore_3
    //   173: goto -28 -> 145
    //   176: return
    //   177: getstatic 39	o/pM:ˋॱ	I
    //   180: bipush 67
    //   182: iadd
    //   183: istore_3
    //   184: iload_3
    //   185: sipush 128
    //   188: irem
    //   189: putstatic 41	o/pM:ॱˊ	I
    //   192: iload_3
    //   193: iconst_2
    //   194: irem
    //   195: ifne +6 -> 201
    //   198: goto +162 -> 360
    //   201: goto +41 -> 242
    //   204: astore_1
    //   205: aload_1
    //   206: athrow
    //   207: getstatic 72	o/pM:ˋ	Ljava/lang/String;
    //   210: sipush 14516
    //   213: iconst_0
    //   214: bipush 10
    //   216: invokestatic 52	o/pM:ॱ	(ICI)Ljava/lang/String;
    //   219: invokevirtual 58	java/lang/String:intern	()Ljava/lang/String;
    //   222: invokestatic 393	o/pD:d	(Ljava/lang/String;Ljava/lang/String;)V
    //   225: aload_0
    //   226: getfield 87	o/pM:ᐝ	Landroid/content/Context;
    //   229: aload_0
    //   230: getfield 91	o/pM:ʼ	Lo/pH;
    //   233: invokevirtual 409	android/content/Context:unregisterReceiver	(Landroid/content/BroadcastReceiver;)V
    //   236: aload_0
    //   237: aconst_null
    //   238: putfield 91	o/pM:ʼ	Lo/pH;
    //   241: return
    //   242: getstatic 72	o/pM:ˋ	Ljava/lang/String;
    //   245: astore_1
    //   246: sipush 148
    //   249: ldc_w 410
    //   252: bipush 24
    //   254: invokestatic 52	o/pM:ॱ	(ICI)Ljava/lang/String;
    //   257: astore 4
    //   259: aload 4
    //   261: invokevirtual 58	java/lang/String:intern	()Ljava/lang/String;
    //   264: astore 4
    //   266: aload_1
    //   267: aload 4
    //   269: invokestatic 393	o/pD:d	(Ljava/lang/String;Ljava/lang/String;)V
    //   272: aload_0
    //   273: getfield 85	o/pM:ʻ	Landroid/os/Handler;
    //   276: aload_0
    //   277: getfield 110	o/pM:ˊ	Ljava/lang/Runnable;
    //   280: invokevirtual 414	android/os/Handler:removeCallbacks	(Ljava/lang/Runnable;)V
    //   283: goto +155 -> 438
    //   286: aload_0
    //   287: getfield 85	o/pM:ʻ	Landroid/os/Handler;
    //   290: ifnull +6 -> 296
    //   293: goto -122 -> 171
    //   296: goto +47 -> 343
    //   299: goto -206 -> 93
    //   302: getstatic 72	o/pM:ˋ	Ljava/lang/String;
    //   305: sipush 193
    //   308: iconst_0
    //   309: bipush 36
    //   311: invokestatic 52	o/pM:ॱ	(ICI)Ljava/lang/String;
    //   314: invokevirtual 58	java/lang/String:intern	()Ljava/lang/String;
    //   317: invokestatic 393	o/pD:d	(Ljava/lang/String;Ljava/lang/String;)V
    //   320: aload_0
    //   321: getfield 87	o/pM:ᐝ	Landroid/content/Context;
    //   324: aload_0
    //   325: getfield 91	o/pM:ʼ	Lo/pH;
    //   328: invokevirtual 409	android/content/Context:unregisterReceiver	(Landroid/content/BroadcastReceiver;)V
    //   331: aload_0
    //   332: aconst_null
    //   333: putfield 91	o/pM:ʼ	Lo/pH;
    //   336: return
    //   337: bipush 69
    //   339: istore_3
    //   340: goto +155 -> 495
    //   343: iconst_1
    //   344: istore_3
    //   345: goto -200 -> 145
    //   348: return
    //   349: aload_0
    //   350: getfield 91	o/pM:ʼ	Lo/pH;
    //   353: ifnonnull +6 -> 359
    //   356: goto -353 -> 3
    //   359: return
    //   360: goto -118 -> 242
    //   363: getstatic 41	o/pM:ॱˊ	I
    //   366: bipush 95
    //   368: iadd
    //   369: istore_3
    //   370: iload_3
    //   371: sipush 128
    //   374: irem
    //   375: putstatic 39	o/pM:ˋॱ	I
    //   378: iload_3
    //   379: iconst_2
    //   380: irem
    //   381: ifeq +4 -> 385
    //   384: return
    //   385: goto -209 -> 176
    //   388: getstatic 72	o/pM:ˋ	Ljava/lang/String;
    //   391: new 45	java/lang/StringBuilder
    //   394: dup
    //   395: invokespecial 48	java/lang/StringBuilder:<init>	()V
    //   398: bipush 123
    //   400: iconst_0
    //   401: bipush 25
    //   403: invokestatic 52	o/pM:ॱ	(ICI)Ljava/lang/String;
    //   406: invokevirtual 58	java/lang/String:intern	()Ljava/lang/String;
    //   409: invokevirtual 62	java/lang/StringBuilder:append	(Ljava/lang/String;)Ljava/lang/StringBuilder;
    //   412: aload_1
    //   413: invokevirtual 415	o/pM$If:toString	()Ljava/lang/String;
    //   416: invokevirtual 62	java/lang/StringBuilder:append	(Ljava/lang/String;)Ljava/lang/StringBuilder;
    //   419: invokevirtual 70	java/lang/StringBuilder:toString	()Ljava/lang/String;
    //   422: invokestatic 418	o/pD:i	(Ljava/lang/String;Ljava/lang/String;)V
    //   425: aload_1
    //   426: getstatic 421	o/pM$If:ˎ	Lo/pM$If;
    //   429: if_acmpeq +6 -> 435
    //   432: goto -146 -> 286
    //   435: goto -86 -> 349
    //   438: getstatic 72	o/pM:ˋ	Ljava/lang/String;
    //   441: new 45	java/lang/StringBuilder
    //   444: dup
    //   445: invokespecial 48	java/lang/StringBuilder:<init>	()V
    //   448: sipush 172
    //   451: iconst_0
    //   452: bipush 21
    //   454: invokestatic 52	o/pM:ॱ	(ICI)Ljava/lang/String;
    //   457: invokevirtual 58	java/lang/String:intern	()Ljava/lang/String;
    //   460: invokevirtual 62	java/lang/StringBuilder:append	(Ljava/lang/String;)Ljava/lang/StringBuilder;
    //   463: aload_2
    //   464: invokevirtual 62	java/lang/StringBuilder:append	(Ljava/lang/String;)Ljava/lang/StringBuilder;
    //   467: invokevirtual 70	java/lang/StringBuilder:toString	()Ljava/lang/String;
    //   470: invokestatic 418	o/pD:i	(Ljava/lang/String;Ljava/lang/String;)V
    //   473: aload_0
    //   474: getfield 93	o/pM:ॱ	Ljava/lang/String;
    //   477: aload_2
    //   478: invokestatic 427	com/insidesecure/hce/internal/MatrixHCENativeBridge:setRegistrationId	(Ljava/lang/String;Ljava/lang/String;)Z
    //   481: pop
    //   482: aload_0
    //   483: getfield 91	o/pM:ʼ	Lo/pH;
    //   486: ifnull +6 -> 492
    //   489: goto -152 -> 337
    //   492: goto -353 -> 139
    //   495: iload_3
    //   496: lookupswitch	default:+28->524, 17:+-148->348, 69:+-384->112
    //   524: return
    // Local variable table:
    //   start	length	slot	name	signature
    //   0	525	0	this	pM
    //   0	525	1	paramIf	If
    //   0	525	2	paramString	String
    //   75	421	3	i	int
    //   257	11	4	str	String
    // Exception table:
    //   from	to	target	type
    //   266	283	109	java/lang/Exception
    //   242	246	204	java/lang/Exception
    //   246	259	204	java/lang/Exception
    //   259	266	204	java/lang/Exception
    //   266	283	204	java/lang/Exception
  }
  
  /* Error */
  private String ॱ()
  {
    // Byte code:
    //   0: goto +98 -> 98
    //   3: astore_2
    //   4: aload_2
    //   5: athrow
    //   6: bipush 14
    //   8: istore_1
    //   9: goto +95 -> 104
    //   12: getstatic 39	o/pM:ˋॱ	I
    //   15: istore_1
    //   16: iload_1
    //   17: bipush 125
    //   19: iadd
    //   20: istore_1
    //   21: iload_1
    //   22: sipush 128
    //   25: irem
    //   26: putstatic 41	o/pM:ॱˊ	I
    //   29: iload_1
    //   30: iconst_2
    //   31: irem
    //   32: ifne +6 -> 38
    //   35: goto -29 -> 6
    //   38: goto +63 -> 101
    //   41: getstatic 39	o/pM:ˋॱ	I
    //   44: bipush 71
    //   46: iadd
    //   47: istore_1
    //   48: iload_1
    //   49: sipush 128
    //   52: irem
    //   53: putstatic 41	o/pM:ॱˊ	I
    //   56: iload_1
    //   57: iconst_2
    //   58: irem
    //   59: ifne +5 -> 64
    //   62: aload_2
    //   63: areturn
    //   64: aload_2
    //   65: areturn
    //   66: astore_2
    //   67: aload_2
    //   68: athrow
    //   69: aload_0
    //   70: getfield 89	o/pM:ˏ	Lo/pz;
    //   73: astore_2
    //   74: aload_0
    //   75: getfield 93	o/pM:ॱ	Ljava/lang/String;
    //   78: astore_3
    //   79: aload_2
    //   80: aload_3
    //   81: invokevirtual 434	o/pz:getPaymentAccount	(Ljava/lang/String;)Lcom/insidesecure/hce/MatrixHCEAccount;
    //   84: astore_2
    //   85: aload_2
    //   86: invokeinterface 439 1 0
    //   91: astore_2
    //   92: aconst_null
    //   93: arraylength
    //   94: istore_1
    //   95: goto -54 -> 41
    //   98: goto -86 -> 12
    //   101: bipush 63
    //   103: istore_1
    //   104: iload_1
    //   105: lookupswitch	default:+27->132, 14:+-36->69, 63:+30->135
    //   132: goto -63 -> 69
    //   135: aload_0
    //   136: getfield 89	o/pM:ˏ	Lo/pz;
    //   139: aload_0
    //   140: getfield 93	o/pM:ॱ	Ljava/lang/String;
    //   143: invokevirtual 434	o/pz:getPaymentAccount	(Ljava/lang/String;)Lcom/insidesecure/hce/MatrixHCEAccount;
    //   146: invokeinterface 439 1 0
    //   151: astore_2
    //   152: goto -111 -> 41
    // Local variable table:
    //   start	length	slot	name	signature
    //   0	155	0	this	pM
    //   8	97	1	i	int
    //   3	62	2	localException1	Exception
    //   66	2	2	localException2	Exception
    //   73	79	2	localObject	Object
    //   78	3	3	str	String
    // Exception table:
    //   from	to	target	type
    //   12	16	3	java/lang/Exception
    //   21	29	3	java/lang/Exception
    //   69	74	66	java/lang/Exception
    //   74	79	66	java/lang/Exception
    //   79	85	66	java/lang/Exception
  }
  
  /* Error */
  private static String ॱ(int paramInt1, char paramChar, int paramInt2)
  {
    // Byte code:
    //   0: goto +235 -> 235
    //   3: astore 11
    //   5: aload 11
    //   7: athrow
    //   8: iconst_0
    //   9: istore 4
    //   11: goto +40 -> 51
    //   14: new 74	java/lang/NullPointerException
    //   17: dup
    //   18: invokespecial 75	java/lang/NullPointerException:<init>	()V
    //   21: athrow
    //   22: goto +140 -> 162
    //   25: getstatic 41	o/pM:ॱˊ	I
    //   28: iconst_5
    //   29: iadd
    //   30: istore_3
    //   31: iload_3
    //   32: sipush 128
    //   35: irem
    //   36: putstatic 39	o/pM:ˋॱ	I
    //   39: iload_3
    //   40: iconst_2
    //   41: irem
    //   42: ifeq +6 -> 48
    //   45: goto -23 -> 22
    //   48: goto +114 -> 162
    //   51: iload 4
    //   53: tableswitch	default:+23->76, 0:+199->252, 1:+59->112
    //   76: goto +36 -> 112
    //   79: getstatic 41	o/pM:ॱˊ	I
    //   82: bipush 73
    //   84: iadd
    //   85: istore 4
    //   87: iload 4
    //   89: sipush 128
    //   92: irem
    //   93: putstatic 39	o/pM:ˋॱ	I
    //   96: iload 4
    //   98: iconst_2
    //   99: irem
    //   100: ifeq +6 -> 106
    //   103: goto -95 -> 8
    //   106: iconst_1
    //   107: istore 4
    //   109: goto -58 -> 51
    //   112: getstatic 380	o/pM:ʽ	[C
    //   115: astore 11
    //   117: aload 11
    //   119: iload_0
    //   120: iload_3
    //   121: iadd
    //   122: caload
    //   123: i2l
    //   124: lstore 5
    //   126: iload_3
    //   127: i2l
    //   128: lstore 9
    //   130: getstatic 116	o/pM:ˊॱ	J
    //   133: lstore 7
    //   135: aload 12
    //   137: iload_3
    //   138: lload 5
    //   140: lload 9
    //   142: lload 7
    //   144: lmul
    //   145: lxor
    //   146: iload_1
    //   147: i2l
    //   148: lxor
    //   149: l2i
    //   150: i2c
    //   151: castore
    //   152: iload_3
    //   153: iconst_1
    //   154: iadd
    //   155: istore_3
    //   156: goto +27 -> 183
    //   159: goto +24 -> 183
    //   162: iload_2
    //   163: newarray char
    //   165: astore 12
    //   167: iconst_0
    //   168: istore_3
    //   169: goto -10 -> 159
    //   172: iconst_0
    //   173: istore 4
    //   175: goto +141 -> 316
    //   178: astore 11
    //   180: aload 11
    //   182: athrow
    //   183: iload_3
    //   184: iload_2
    //   185: if_icmpge +6 -> 191
    //   188: goto +6 -> 194
    //   191: goto -19 -> 172
    //   194: iconst_1
    //   195: istore 4
    //   197: goto +119 -> 316
    //   200: getstatic 41	o/pM:ॱˊ	I
    //   203: bipush 7
    //   205: iadd
    //   206: istore_0
    //   207: iload_0
    //   208: sipush 128
    //   211: irem
    //   212: putstatic 39	o/pM:ˋॱ	I
    //   215: iload_0
    //   216: iconst_2
    //   217: irem
    //   218: ifeq +6 -> 224
    //   221: goto +6 -> 227
    //   224: goto +87 -> 311
    //   227: iconst_0
    //   228: istore_0
    //   229: goto +55 -> 284
    //   232: aload 11
    //   234: areturn
    //   235: goto -210 -> 25
    //   238: new 54	java/lang/String
    //   241: dup
    //   242: aload 12
    //   244: invokespecial 442	java/lang/String:<init>	([C)V
    //   247: astore 11
    //   249: goto -49 -> 200
    //   252: aload 12
    //   254: iload_3
    //   255: getstatic 380	o/pM:ʽ	[C
    //   258: iload_0
    //   259: iload_3
    //   260: irem
    //   261: caload
    //   262: i2l
    //   263: iload_3
    //   264: i2l
    //   265: getstatic 116	o/pM:ˊॱ	J
    //   268: lsub
    //   269: lmul
    //   270: iload_1
    //   271: i2l
    //   272: ldiv
    //   273: l2i
    //   274: i2c
    //   275: castore
    //   276: iload_3
    //   277: bipush 125
    //   279: iadd
    //   280: istore_3
    //   281: goto -98 -> 183
    //   284: iload_0
    //   285: tableswitch	default:+23->308, 0:+-271->14, 1:+-53->232
    //   308: goto -294 -> 14
    //   311: iconst_1
    //   312: istore_0
    //   313: goto -29 -> 284
    //   316: iload 4
    //   318: tableswitch	default:+22->340, 0:+-80->238, 1:+-239->79
    //   340: goto -102 -> 238
    // Local variable table:
    //   start	length	slot	name	signature
    //   0	343	0	paramInt1	int
    //   0	343	1	paramChar	char
    //   0	343	2	paramInt2	int
    //   30	251	3	i	int
    //   9	308	4	j	int
    //   124	15	5	l1	long
    //   133	10	7	l2	long
    //   128	13	9	l3	long
    //   3	3	11	localException1	Exception
    //   115	3	11	arrayOfChar1	char[]
    //   178	55	11	localException2	Exception
    //   247	1	11	str	String
    //   135	118	12	arrayOfChar2	char[]
    // Exception table:
    //   from	to	target	type
    //   25	31	3	java/lang/Exception
    //   31	39	3	java/lang/Exception
    //   112	117	3	java/lang/Exception
    //   130	135	3	java/lang/Exception
    //   31	39	178	java/lang/Exception
  }
  
  public void ˎ()
  {
    break label112;
    int i = ˋॱ + 53;
    ॱˊ = i % 128;
    String str;
    if (i % 2 != 0)
    {
      break label234;
      return;
      str = this.ॱॱ;
      throw new NullPointerException();
      i = 72;
      break label239;
    }
    else
    {
      for (;;)
      {
        switch (i)
        {
        case 0: 
        default: 
          label50:
          return;
        }
        label112:
        for (;;)
        {
          i = ॱˊ + 109;
          ˋॱ = i % 128;
          if (i % 2 != 0) {
            break;
          }
          break label115;
          if (this.ॱॱ == null) {
            return;
          }
          break label271;
          return;
        }
        label115:
        i = 69;
        break label239;
        i = 0;
      }
    }
    for (;;)
    {
      pD.d(ˋ, ॱ(56, '\000', 33).intern());
      ˏ(If.ˏ, str);
      break;
      label234:
      label239:
      label271:
      do
      {
        pD.d(ˋ, ॱ(0, 36611, 25).intern() + this.ॱ + ॱ(25, '\000', 17).intern() + this.ॱॱ + ॱ(42, '懩', 14).intern());
        ʽ();
        return;
        i = 1;
        break label50;
        switch (i)
        {
        }
        break;
        str = ॱ();
      } while (str == null);
    }
  }
  
  public void ˏ()
  {
    break label80;
    int i;
    try
    {
      i = ॱˊ;
      i += 15;
      try
      {
        ˋॱ = i % 128;
        if (i % 2 != 0) {
          break label83;
        }
      }
      catch (Exception localException1)
      {
        throw localException1;
      }
    }
    catch (Exception localException2)
    {
      throw localException2;
    }
    if (this.ʼ == null) {
      break label239;
    }
    for (;;)
    {
      switch (i)
      {
      default: 
        return;
        break;
        pH localPH = this.ʼ;
        throw new NullPointerException();
        for (;;)
        {
          i = ˋॱ + 83;
          ॱˊ = i % 128;
          if (i % 2 != 0) {
            break label205;
          }
          i = 0;
          break;
        }
        i = 38;
        break;
      case 0: 
        for (;;)
        {
          pD.i(ˋ, ॱ(89, '\000', 34).intern());
          this.ᐝ.unregisterReceiver(this.ʼ);
          this.ʼ = null;
          break label128;
          i = null.length;
          return;
          i = ˋॱ + 89;
          ॱˊ = i % 128;
          if (i % 2 == 0) {
            break;
          }
        }
      case 1: 
        label80:
        label83:
        label128:
        return;
        label205:
        i = 1;
      }
    }
    for (;;)
    {
      switch (i)
      {
      }
      break;
      label239:
      i = 22;
    }
  }
  
  static enum If
  {
    private static char ʼ;
    private static int ʽ;
    private static char[] ˊ;
    private static int ᐝ;
    
    static
    {
      break label9;
      int i = 13;
      for (;;)
      {
        try
        {
          label9:
          ᐝ = 0;
          try
          {
            ʽ = 1;
            ˏ();
            ˏ = new If(ˏ(new char[] { 1, 2, 3, 4, 0, 9, 1, 5, 8, 0, 8, 9, 5, 7, 15, 5, 6, 11, 12, 13, 8, 14, 9, 12, 20, 15, 0, 6, 132 }, 29, (byte)63).intern(), 0);
            ˋ = new If(ˏ(new char[] { 1, 2, 3, 4, 0, 9, 1, 5, 8, 0, 8, 9, 8, 14, 9, 12, 20, 15, 0, 6, 106 }, 21, (byte)37).intern(), 1);
            ˎ = new If(ˏ(new char[] { 1, 2, 3, 4, 0, 9, 1, 5, 8, 0, 8, 9, 6, 19, 8, 1, 11, 0, 185 }, 19, (byte)117).intern(), 2);
            ॱ = new If[] { ˏ, ˋ, ˎ };
          }
          catch (Exception localException1)
          {
            throw localException1;
          }
          i = 43;
          switch (i)
          {
          case 43: 
          default: 
            return;
          }
          i = null.length;
          return;
        }
        catch (Exception localException2)
        {
          throw localException2;
        }
        i = ʽ + 81;
        ᐝ = i % 128;
        if (i % 2 != 0) {
          break;
        }
      }
    }
    
    private If() {}
    
    private static String ˏ(char[] paramArrayOfChar, int paramInt, byte paramByte)
    {
      for (;;)
      {
        byte b3;
        int j;
        byte b2;
        int k;
        int m;
        char[] arrayOfChar2;
        char[] arrayOfChar1;
        try
        {
          b1 = oO.ˊ(b3, j);
          try
          {
            b2 = oO.ˊ(b2, j);
            b1 = oO.ˏ(b1, k, j);
            b2 = oO.ˏ(b2, m, j);
            arrayOfChar2[i] = arrayOfChar1[b1];
            arrayOfChar2[(i + 1)] = arrayOfChar1[b2];
          }
          catch (Exception paramArrayOfChar)
          {
            throw paramArrayOfChar;
          }
          b3 = ʽ + 51;
          ᐝ = b3 % 128;
          if (b3 % 2 != 0) {
            break label479;
          }
          continue;
          continue;
          b1 = 1;
          continue;
          b1 = 41;
          break label383;
          break label372;
          break label418;
          arrayOfChar2[i] = ((char)(b2 - paramByte));
          arrayOfChar2[(i + 1)] = ((char)(b1 - paramByte));
          break label560;
          paramInt = i;
          switch (b1)
          {
          default: 
            paramInt = i;
            break;
          case 0: 
            paramInt = i - 1;
            arrayOfChar2[paramInt] = ((char)(paramArrayOfChar[paramInt] - paramByte));
            break;
            label193:
            i += 2;
            break label372;
            b1 = ʽ + 41;
            ᐝ = b1 % 128;
            if (b1 % 2 != 0) {
              break label415;
            }
            break label557;
            switch (i)
            {
            default: 
              label230:
              break label587;
              b2 = paramArrayOfChar[i];
              b1 = paramArrayOfChar[(i + 1)];
              if (b2 == b1) {
                continue;
              }
              b3 = oO.ॱ(b2, j);
              k = oO.ˋ(b2, j);
              b2 = oO.ॱ(b1, j);
              m = oO.ˋ(b1, j);
              if (k == m) {
                continue;
              }
              break label629;
              i = ʽ + 63;
              ᐝ = i % 128;
              if (i % 2 != 0) {
                continue;
              }
              break;
            }
            break;
          }
        }
        catch (Exception paramArrayOfChar)
        {
          throw paramArrayOfChar;
        }
        int i = 0;
        continue;
        byte b1 = 43;
        label372:
        if (i >= paramInt)
        {
          continue;
          switch (b1)
          {
          case 41: 
          default: 
            break label587;
            continue;
            arrayOfChar1 = ˊ;
            i = paramInt;
            j = ʼ;
            arrayOfChar2 = new char[i];
            if (i % 2 == 0) {}
            for (;;)
            {
              switch (b1)
              {
              default: 
                break label642;
                break;
              case 85: 
                for (;;)
                {
                  i = 78;
                  break label230;
                  b1 = oO.ˊ(k, j);
                  k = oO.ˊ(m, j);
                  b1 = oO.ˏ(b3, b1, j);
                  b2 = oO.ˏ(b2, k, j);
                  arrayOfChar2[i] = arrayOfChar1[b1];
                  arrayOfChar2[(i + 1)] = arrayOfChar1[b2];
                  break label193;
                  do
                  {
                    i = 96;
                    break label230;
                    break label193;
                    break label193;
                    b1 = 0;
                    break;
                  } while (paramInt > 1);
                }
                b1 = 85;
              }
            }
          case 43: 
            label383:
            label415:
            label418:
            label479:
            label557:
            label560:
            label580:
            label587:
            paramArrayOfChar = new String(arrayOfChar2);
            paramInt = ʽ + 39;
            ᐝ = paramInt % 128;
            if (paramInt % 2 != 0) {
              return paramArrayOfChar;
            }
            return paramArrayOfChar;
            for (;;)
            {
              b1 = 7;
              break;
              label629:
              if (b3 == b2) {
                break label580;
              }
            }
            label642:
            b1 = oO.ˏ(b3, m, j);
            b2 = oO.ˏ(b2, k, j);
            arrayOfChar2[i] = arrayOfChar1[b1];
            arrayOfChar2[(i + 1)] = arrayOfChar1[b2];
          }
        }
      }
    }
    
    static void ˏ()
    {
      ˊ = new char[] { 82, 69, 71, 73, 83, 84, 65, 79, 78, 95, 76, 68, 89, 67, 77, 80, 70, 85, 86, 87, 88, 90, 91, 92, 93 };
      ʼ = '\005';
    }
  }
}
