package o;

import com.insidesecure.hce.MatrixHCEError;
import com.insidesecure.hce.MatrixHCEException;
import com.insidesecure.hce.MatrixHCENetworkData;
import com.insidesecure.hce.MatrixHCENetworkOperationCallback;
import com.insidesecure.hce.NetworkOperationPreparationInfo.NetworkOperation;
import com.insidesecure.hce.internal.MatrixHCENativeBridge;
import com.insidesecure.hce.internal.MatrixHCENetworkOperationResponse;
import java.util.Arrays;

public class pn
  extends pk
{
  private static long ʻ;
  private static int ʼ;
  private static final String ˊ;
  private static int ॱॱ;
  private static char[] ᐝ;
  
  static
  {
    break label68;
    int i = 0;
    for (;;)
    {
      try
      {
        i = ॱॱ;
        i += 119;
        ʼ = i % 128;
        if (i % 2 == 0) {
          break;
        }
      }
      catch (Exception localException)
      {
        throw localException;
      }
      switch (i)
      {
      default: 
        return;
      case 0: 
        i = null.length;
        return;
        ॱॱ = 0;
        ʼ = 1;
        ˊ();
        ˊ = ˊ(707, 62973, 19).intern() + pn.class.getSimpleName();
        break;
      case 1: 
        label68:
        return;
        i = 1;
      }
    }
  }
  
  public pn(String paramString1, String paramString2, String paramString3, String paramString4, String paramString5, long paramLong) {}
  
  /* Error */
  private void ʼ()
  {
    // Byte code:
    //   0: goto +192 -> 192
    //   3: getstatic 58	o/pn:ˊ	Ljava/lang/String;
    //   6: new 31	java/lang/StringBuilder
    //   9: dup
    //   10: invokespecial 34	java/lang/StringBuilder:<init>	()V
    //   13: sipush 450
    //   16: ldc 63
    //   18: bipush 53
    //   20: invokestatic 38	o/pn:ˊ	(ICI)Ljava/lang/String;
    //   23: invokevirtual 44	java/lang/String:intern	()Ljava/lang/String;
    //   26: invokevirtual 48	java/lang/StringBuilder:append	(Ljava/lang/String;)Ljava/lang/StringBuilder;
    //   29: aload 4
    //   31: getfield 69	com/insidesecure/hce/internal/MatrixHCENativeBridge$SessionResponse:error	Lcom/insidesecure/hce/internal/account/mdes/SessionError;
    //   34: invokevirtual 72	com/insidesecure/hce/internal/account/mdes/SessionError:toString	()Ljava/lang/String;
    //   37: invokevirtual 48	java/lang/StringBuilder:append	(Ljava/lang/String;)Ljava/lang/StringBuilder;
    //   40: invokevirtual 56	java/lang/StringBuilder:toString	()Ljava/lang/String;
    //   43: invokestatic 78	o/pD:e	(Ljava/lang/String;Ljava/lang/String;)V
    //   46: goto +97 -> 143
    //   49: aload_3
    //   50: invokeinterface 84 1 0
    //   55: ifeq +6 -> 61
    //   58: goto +169 -> 227
    //   61: goto +82 -> 143
    //   64: getstatic 58	o/pn:ˊ	Ljava/lang/String;
    //   67: sipush 7465
    //   70: sipush 1715
    //   73: bipush 73
    //   75: invokestatic 38	o/pn:ˊ	(ICI)Ljava/lang/String;
    //   78: invokevirtual 44	java/lang/String:intern	()Ljava/lang/String;
    //   81: invokestatic 78	o/pD:e	(Ljava/lang/String;Ljava/lang/String;)V
    //   84: goto +214 -> 298
    //   87: getstatic 58	o/pn:ˊ	Ljava/lang/String;
    //   90: sipush 377
    //   93: sipush 1715
    //   96: bipush 34
    //   98: invokestatic 38	o/pn:ˊ	(ICI)Ljava/lang/String;
    //   101: invokevirtual 44	java/lang/String:intern	()Ljava/lang/String;
    //   104: invokestatic 78	o/pD:e	(Ljava/lang/String;Ljava/lang/String;)V
    //   107: goto +191 -> 298
    //   110: getstatic 27	o/pn:ʼ	I
    //   113: bipush 91
    //   115: iadd
    //   116: istore_1
    //   117: iload_1
    //   118: sipush 128
    //   121: irem
    //   122: putstatic 25	o/pn:ॱॱ	I
    //   125: iload_1
    //   126: iconst_2
    //   127: irem
    //   128: ifeq +6 -> 134
    //   131: goto +6 -> 137
    //   134: goto +273 -> 407
    //   137: bipush 82
    //   139: istore_1
    //   140: goto +236 -> 376
    //   143: getstatic 58	o/pn:ˊ	Ljava/lang/String;
    //   146: sipush 671
    //   149: ldc 85
    //   151: bipush 36
    //   153: invokestatic 38	o/pn:ˊ	(ICI)Ljava/lang/String;
    //   156: invokevirtual 44	java/lang/String:intern	()Ljava/lang/String;
    //   159: invokestatic 88	o/pD:d	(Ljava/lang/String;Ljava/lang/String;)V
    //   162: return
    //   163: invokestatic 94	com/insidesecure/hce/MatrixHCE$MatrixHCEFactory:getInstance	()Lcom/insidesecure/hce/MatrixHCE;
    //   166: astore_2
    //   167: aload_2
    //   168: instanceof 96
    //   171: ifne +6 -> 177
    //   174: goto +115 -> 289
    //   177: goto +9 -> 186
    //   180: goto -131 -> 49
    //   183: astore_2
    //   184: aload_2
    //   185: athrow
    //   186: bipush 57
    //   188: istore_1
    //   189: goto +6 -> 195
    //   192: goto -29 -> 163
    //   195: iload_1
    //   196: lookupswitch	default:+28->224, 57:+102->298, 63:+-86->110
    //   224: goto +74 -> 298
    //   227: aload_3
    //   228: invokeinterface 100 1 0
    //   233: astore 4
    //   235: aload 4
    //   237: checkcast 102	org/json/JSONObject
    //   240: astore 5
    //   242: aload_0
    //   243: getfield 105	o/pn:ˏ	Ljava/lang/String;
    //   246: astore 4
    //   248: aload 5
    //   250: invokevirtual 106	org/json/JSONObject:toString	()Ljava/lang/String;
    //   253: astore 5
    //   255: aload 4
    //   257: aload 5
    //   259: invokestatic 112	com/insidesecure/hce/internal/MatrixHCENativeBridge:setNetworkSessionData	(Ljava/lang/String;Ljava/lang/String;)Lcom/insidesecure/hce/internal/MatrixHCENativeBridge$SessionResponse;
    //   262: astore 4
    //   264: aload 4
    //   266: getfield 69	com/insidesecure/hce/internal/MatrixHCENativeBridge$SessionResponse:error	Lcom/insidesecure/hce/internal/account/mdes/SessionError;
    //   269: astore 5
    //   271: getstatic 115	com/insidesecure/hce/internal/account/mdes/SessionError:SUCCESS	Lcom/insidesecure/hce/internal/account/mdes/SessionError;
    //   274: astore 6
    //   276: aload 5
    //   278: aload 6
    //   280: if_acmpeq +6 -> 286
    //   283: goto -280 -> 3
    //   286: goto +157 -> 443
    //   289: bipush 63
    //   291: istore_1
    //   292: goto -97 -> 195
    //   295: goto -115 -> 180
    //   298: aload_2
    //   299: checkcast 96	o/pz
    //   302: aload_0
    //   303: getfield 105	o/pn:ˏ	Ljava/lang/String;
    //   306: invokevirtual 118	o/pz:ˏ	(Ljava/lang/String;)Ljava/util/List;
    //   309: astore_3
    //   310: getstatic 58	o/pn:ˊ	Ljava/lang/String;
    //   313: new 31	java/lang/StringBuilder
    //   316: dup
    //   317: invokespecial 34	java/lang/StringBuilder:<init>	()V
    //   320: sipush 411
    //   323: iconst_0
    //   324: iconst_4
    //   325: invokestatic 38	o/pn:ˊ	(ICI)Ljava/lang/String;
    //   328: invokevirtual 44	java/lang/String:intern	()Ljava/lang/String;
    //   331: invokevirtual 48	java/lang/StringBuilder:append	(Ljava/lang/String;)Ljava/lang/StringBuilder;
    //   334: aload_3
    //   335: invokeinterface 124 1 0
    //   340: invokevirtual 127	java/lang/StringBuilder:append	(I)Ljava/lang/StringBuilder;
    //   343: sipush 415
    //   346: sipush 11720
    //   349: bipush 35
    //   351: invokestatic 38	o/pn:ˊ	(ICI)Ljava/lang/String;
    //   354: invokevirtual 44	java/lang/String:intern	()Ljava/lang/String;
    //   357: invokevirtual 48	java/lang/StringBuilder:append	(Ljava/lang/String;)Ljava/lang/StringBuilder;
    //   360: invokevirtual 56	java/lang/StringBuilder:toString	()Ljava/lang/String;
    //   363: invokestatic 88	o/pD:d	(Ljava/lang/String;Ljava/lang/String;)V
    //   366: aload_3
    //   367: invokeinterface 131 1 0
    //   372: astore_3
    //   373: goto -324 -> 49
    //   376: iload_1
    //   377: lookupswitch	default:+27->404, 29:+-290->87, 82:+-313->64
    //   404: goto -340 -> 64
    //   407: bipush 29
    //   409: istore_1
    //   410: goto -34 -> 376
    //   413: getstatic 25	o/pn:ॱॱ	I
    //   416: bipush 105
    //   418: iadd
    //   419: istore_1
    //   420: iload_1
    //   421: sipush 128
    //   424: irem
    //   425: putstatic 27	o/pn:ʼ	I
    //   428: iload_1
    //   429: iconst_2
    //   430: irem
    //   431: ifne +6 -> 437
    //   434: goto -139 -> 295
    //   437: goto -257 -> 180
    //   440: astore_2
    //   441: aload_2
    //   442: athrow
    //   443: getstatic 58	o/pn:ˊ	Ljava/lang/String;
    //   446: new 31	java/lang/StringBuilder
    //   449: dup
    //   450: invokespecial 34	java/lang/StringBuilder:<init>	()V
    //   453: sipush 503
    //   456: sipush 32746
    //   459: bipush 92
    //   461: invokestatic 38	o/pn:ˊ	(ICI)Ljava/lang/String;
    //   464: invokevirtual 44	java/lang/String:intern	()Ljava/lang/String;
    //   467: invokevirtual 48	java/lang/StringBuilder:append	(Ljava/lang/String;)Ljava/lang/StringBuilder;
    //   470: aload 4
    //   472: getfield 134	com/insidesecure/hce/internal/MatrixHCENativeBridge$SessionResponse:tokenUniqueReference	Ljava/lang/String;
    //   475: invokevirtual 48	java/lang/StringBuilder:append	(Ljava/lang/String;)Ljava/lang/StringBuilder;
    //   478: invokevirtual 56	java/lang/StringBuilder:toString	()Ljava/lang/String;
    //   481: invokestatic 88	o/pD:d	(Ljava/lang/String;Ljava/lang/String;)V
    //   484: new 136	android/content/Intent
    //   487: dup
    //   488: sipush 595
    //   491: iconst_0
    //   492: bipush 51
    //   494: invokestatic 38	o/pn:ˊ	(ICI)Ljava/lang/String;
    //   497: invokevirtual 44	java/lang/String:intern	()Ljava/lang/String;
    //   500: invokespecial 139	android/content/Intent:<init>	(Ljava/lang/String;)V
    //   503: astore 5
    //   505: aload 5
    //   507: sipush 646
    //   510: iconst_0
    //   511: bipush 25
    //   513: invokestatic 38	o/pn:ˊ	(ICI)Ljava/lang/String;
    //   516: invokevirtual 44	java/lang/String:intern	()Ljava/lang/String;
    //   519: aload 4
    //   521: getfield 134	com/insidesecure/hce/internal/MatrixHCENativeBridge$SessionResponse:tokenUniqueReference	Ljava/lang/String;
    //   524: invokevirtual 143	android/content/Intent:putExtra	(Ljava/lang/String;Ljava/lang/String;)Landroid/content/Intent;
    //   527: pop
    //   528: aload_2
    //   529: checkcast 96	o/pz
    //   532: invokevirtual 146	o/pz:ˏ	()Landroid/content/Context;
    //   535: aload 5
    //   537: invokestatic 150	o/pD:sendBroadcast	(Landroid/content/Context;Landroid/content/Intent;)V
    //   540: goto -127 -> 413
    // Local variable table:
    //   start	length	slot	name	signature
    //   0	543	0	this	pn
    //   116	315	1	i	int
    //   166	2	2	localMatrixHCE	com.insidesecure.hce.MatrixHCE
    //   183	116	2	localException1	Exception
    //   440	89	2	localException2	Exception
    //   49	324	3	localObject1	Object
    //   29	491	4	localObject2	Object
    //   240	296	5	localObject3	Object
    //   274	5	6	localSessionError	com.insidesecure.hce.internal.account.mdes.SessionError
    // Exception table:
    //   from	to	target	type
    //   227	235	183	java/lang/Exception
    //   235	242	183	java/lang/Exception
    //   242	248	183	java/lang/Exception
    //   248	255	183	java/lang/Exception
    //   255	264	183	java/lang/Exception
    //   264	276	183	java/lang/Exception
    //   242	248	440	java/lang/Exception
  }
  
  /* Error */
  private static String ˊ(int paramInt1, char paramChar, int paramInt2)
  {
    // Byte code:
    //   0: goto +199 -> 199
    //   3: bipush 74
    //   5: istore_0
    //   6: goto +214 -> 220
    //   9: iload 4
    //   11: lookupswitch	default:+25->36, 76:+28->39, 85:+136->147
    //   36: goto +111 -> 147
    //   39: getstatic 25	o/pn:ॱॱ	I
    //   42: bipush 7
    //   44: iadd
    //   45: istore 4
    //   47: iload 4
    //   49: sipush 128
    //   52: irem
    //   53: putstatic 27	o/pn:ʼ	I
    //   56: iload 4
    //   58: iconst_2
    //   59: irem
    //   60: ifne +6 -> 66
    //   63: goto +146 -> 209
    //   66: goto +27 -> 93
    //   69: aload 11
    //   71: areturn
    //   72: astore 11
    //   74: aload 11
    //   76: athrow
    //   77: iload_2
    //   78: newarray char
    //   80: astore 11
    //   82: iconst_0
    //   83: istore_3
    //   84: goto +77 -> 161
    //   87: bipush 21
    //   89: istore_0
    //   90: goto +130 -> 220
    //   93: getstatic 152	o/pn:ᐝ	[C
    //   96: iload_0
    //   97: iload_3
    //   98: iadd
    //   99: caload
    //   100: istore 4
    //   102: iload 4
    //   104: i2l
    //   105: lstore 5
    //   107: iload_3
    //   108: i2l
    //   109: lstore 9
    //   111: getstatic 154	o/pn:ʻ	J
    //   114: lstore 7
    //   116: aload 11
    //   118: iload_3
    //   119: lload 5
    //   121: lload 9
    //   123: lload 7
    //   125: lmul
    //   126: lxor
    //   127: iload_1
    //   128: i2l
    //   129: lxor
    //   130: l2i
    //   131: i2c
    //   132: castore
    //   133: iload_3
    //   134: iconst_1
    //   135: iadd
    //   136: istore_3
    //   137: goto +24 -> 161
    //   140: bipush 85
    //   142: istore 4
    //   144: goto -135 -> 9
    //   147: new 40	java/lang/String
    //   150: dup
    //   151: aload 11
    //   153: invokespecial 157	java/lang/String:<init>	([C)V
    //   156: astore 11
    //   158: goto +14 -> 172
    //   161: iload_3
    //   162: iload_2
    //   163: if_icmpge +6 -> 169
    //   166: goto +36 -> 202
    //   169: goto -29 -> 140
    //   172: getstatic 27	o/pn:ʼ	I
    //   175: bipush 57
    //   177: iadd
    //   178: istore_0
    //   179: iload_0
    //   180: sipush 128
    //   183: irem
    //   184: putstatic 25	o/pn:ॱॱ	I
    //   187: iload_0
    //   188: iconst_2
    //   189: irem
    //   190: ifeq +6 -> 196
    //   193: goto -106 -> 87
    //   196: goto -193 -> 3
    //   199: goto -122 -> 77
    //   202: bipush 76
    //   204: istore 4
    //   206: goto -197 -> 9
    //   209: goto -116 -> 93
    //   212: new 159	java/lang/NullPointerException
    //   215: dup
    //   216: invokespecial 160	java/lang/NullPointerException:<init>	()V
    //   219: athrow
    //   220: iload_0
    //   221: lookupswitch	default:+27->248, 21:+-9->212, 74:+-152->69
    //   248: aload 11
    //   250: areturn
    // Local variable table:
    //   start	length	slot	name	signature
    //   0	251	0	paramInt1	int
    //   0	251	1	paramChar	char
    //   0	251	2	paramInt2	int
    //   83	81	3	i	int
    //   9	196	4	j	int
    //   105	15	5	l1	long
    //   114	10	7	l2	long
    //   109	13	9	l3	long
    //   69	1	11	str	String
    //   72	3	11	localException	Exception
    //   80	169	11	localObject	Object
    // Exception table:
    //   from	to	target	type
    //   93	102	72	java/lang/Exception
    //   111	116	72	java/lang/Exception
  }
  
  static void ˊ()
  {
    ʻ = 3941639517044232405L;
    ᐝ = new char[] { 20407, 8001, -4554, -16985, 3295, -9292, -21643, 31320, -14023, -26390, 26564, 14079, -31114, 21836, 9267, -3102, 17089, 4531, -7829, -20391, 7995, -4447, -16944, 3252, -9102, -21745, 31354, 19371, 7015, -5601, -18012, 2252, -8269, -20629, 32326, -12996, -25358, 25481, 12990, -32158, 20746, 8243, -2059, 18119, 5554, -6879, -19389, 6967, -5401, -17957, 2296, -10144, -20649, 32309, -12832, -25378, 25524, 13162, -32240, 20796, 8427, -2107, 18081, 5729, -6831, -19433, 7153, -5437, -18030, 2412, -10152, -20681, 32483, -12845, 67, 20669, -24113, -3556, 17215, -27584, -7024, 13748, -31096, -10469, 10301, 31061, -13860, 6846, 27606, -17378, 3390, 24069, -20844, -86, 20688, -24306, -3551, 17233, -27757, -6931, 13777, -31214, -10433, 10322, 30879, -13916, 6862, 27398, 79, 20645, -24113, -3567, 17213, -27577, -7015, 13811, -31013, -10472, 10273, 31060, -13931, 6846, 27592, -17317, 3382, 24138, -20856, -17, 20677, -24294, -3539, 17228, -27763, -7005, 13782, -31145, 79, 20645, -24113, -3567, 17268, -27558, -7013, 13728, -31013, -10476, 10301, 31049, -13860, 6809, 27634, -17361, 3328, 24069, -20856, -86, 20693, -24308, -3541, 17232, -27764, -6931, 13764, -31210, -10459, 10317, 30867, -13905, 6784, -8192, -20254, 16789, 4674, -23694, 29726, 1164, -10769, 26261, 14171, -14231, -26349, 10695, -1312, -29803, 23645, -4757, -16872, 20166, 8125, -20351, 16714, 4725, -23803, 29635, 1265, -10857, 26117, 14185, -14318, -26409, 10681, -1381, -29879, 23660, -4824, -16940, 20201, 8121, -20399, 16750, 4650, -23868, 29627, 82, 20656, -24121, -3568, 17184, -27572, -6946, 13757, -31033, -10487, 10299, 31041, -13931, 6834, 27591, -17393, 3385, 24138, -20844, -17, 20691, -24296, -3545, 17239, -27759, -7005, 13765, -31145, -10440, 10312, 30875, -13906, 6852, 27477, -17371, 3434, 23936, -20761, 22179, 1610, -2248, -23384, 5585, -15685, -19868, 25419, -12245, -32273, 32389, 12222, -24732, 19538, 15672, -5398, 23502, 2225, -1940, -22196, 1594, -2079, -23337, 5620, -14997, -19883, 25392, -12045, -32357, 32440, 11886, -24760, 19575, 15850, -5412, 23454, 2918, -2018, -22243, 1772, -2086, -23350, 5216, -15032, -19941, 25571, -12078, -32360, 29026, 11862, -24755, 19688, 15826, -5481, 23157, 2907, -2034, -22018, 6587, 18757, -18389, -5123, 23246, -29266, -672, 11270, -24786, -12563, 12756, 24737, -12192, 843, 29245, -23122, 5325, 18353, -18564, -6630, 18739, -18199, -5154, 23224, -30163, -681, 11303, -24601, -12585, 12721, 24935, -12258, 806, 29429, -23076, 5263, 17522, -18609, -6643, 18931, -18223, -5244, 23422, -30180, 26295, 13897, -14553, -27407, 9666, -3422, -32148, 21258, -8158, -19999, 20184, 8109, -20628, 31815, 3377, -9566, 27584, 14511, -14301, -26279, 13869, -14363, -27431, 9716, 1790, 22023, -22675, -2882, 17806, -27934, -7675, 13091, -32674, -11794, 11919, 32763, -12485, 7234, 28026, -17746, 3011, 22754, -22495, -1767, 22071, -22609, -2939, 17888, -27346, -7651, 13157, -32607, -11877, 11954, 32305, -12543, 7267, 28067, 71, 20666, -24098, -3489, 11752, 32111, -29689, -8230, 28403, -18027, -13997, 6203, -21746, -1318, 1518, 21638, -7086, 14192, 17933, -28206, 8428, 29572, -31907, -11671, 32031, -29551, -8203, 28319, -16815, -13962, 6146, -21542, -1312, 1481, 21855, -7052, 14089, 18116, -28244, -12765, -24895, 28606, 15478, -29376, 23151, 10991, -1059, 18599, 6519, -6575, -18591, 2026, -11067, -23121, 29310, -15533, -28624, 24815, 12736, -24916, 28536, 15368, -29391, 24054, 10958, -1052, 18531, 6479, -6614, -18689, 2009, -11101, -23245, 29250, -15594, -27674, 24774, 12702, -24964, 28493, 15386, -29472, 24008, 10901, -1159, 18432, 6425, -5641, -18729, 1949, -11213, -23294, 32696, 12122, -8659, -29190, 15562, -5210, -25804, 19031, -1747, -22301, 22481, 1707, -18817, 25944, 5165, -15387, 29395, 8608, -11906, -32763, 12074, -8462, -29232, 15528, -5070, -25769, 19002, -1550, -22331, 22446, 1903, -18862, 25903, 5371, -15488, 29318, 8811, -11968, -32745, 12284, -8495, -29308, 15742, -5032, -25830, 19191, -1579, -22305, 22601, 1866, -18914, 26081, 5319, -15459, 29539, 8713, -12003, -32526, 12252, -8483, -29068, 15694, -5091, -25627, 19155, -1569, -22170, 22586, 1804, -18781, 26020, 5259, -15251, 29473, 8721, -11778, -32577, 12180, -8350, -29071, 15635, -4895, -25692, 19072, -1440, -22233, 22551, 1961, -18764, 25992, 5498, -15235, 99, 20666, -24121, -3503, 17213, -27577, -7027, 13754, -31028, -10472, 10273, 31042, -13921, 6820, 27604, -17378, 3454, 24141, -20839, -86, 20618, -24304, -3552, 17239, -27747, -7005, 13782, -31143, -10492, 10338, 30899, -13932, 6898, 27440, -17397, 3419, 23981, -20842, -40, 20540, -24294, -3518, 17058, -27755, -6957, 13607, -31217, -10424, 10169, 30858, -13868, 104, 20662, -24113, -3552, 17207, -27576, -7028, 13751, -30985, -10488, 10300, 31054, -13939, 6820, 27587, -17372, 3362, 24128, -20836, -86, 20694, -24292, -3552, 17216, -27747, -6357, -18477, 18092, 5429, -23475, 29495, 1013, -11574, 25002, 12402, -12452, -24979, 12024, -556, -29512, 23416, -5540, -18138, 18931, 6340, -18502, 18042, 5451, -23513, 29921, 903, -11592, 24943, 12361, -12504, -24583, 11986, -583, -29574, 23364, -5541, -2640, -23223, 21539, 2032, -18752, 25004, 4427, -16275, 29456, 8878, -8763, -29509, 15479, -4275, -24970, 18919, -1827, -21583, 23337 };
  }
  
  public void clearNetworkSession()
  {
    break label83;
    int i;
    for (;;)
    {
      i = 0;
      break;
      MatrixHCENativeBridge.clearNetworkSessionData(this.ˏ);
      return;
      MatrixHCENativeBridge.clearNetworkSessionData(this.ˏ);
      throw new NullPointerException();
      label31:
      i = ॱॱ + 1;
      ʼ = i % 128;
      if (i % 2 != 0) {
        break label86;
      }
    }
    for (;;)
    {
      switch (i)
      {
      }
      break;
      label83:
      break label31;
      label86:
      i = 1;
    }
  }
  
  /* Error */
  public void clearPaymentKeys()
  {
    // Byte code:
    //   0: goto +230 -> 230
    //   3: getstatic 25	o/pn:ॱॱ	I
    //   6: bipush 121
    //   8: iadd
    //   9: istore_1
    //   10: iload_1
    //   11: sipush 128
    //   14: irem
    //   15: putstatic 27	o/pn:ʼ	I
    //   18: iload_1
    //   19: iconst_2
    //   20: irem
    //   21: ifne +6 -> 27
    //   24: goto +152 -> 176
    //   27: goto +90 -> 117
    //   30: astore_2
    //   31: aload_2
    //   32: athrow
    //   33: aload_2
    //   34: invokeinterface 100 1 0
    //   39: astore_3
    //   40: aload_3
    //   41: checkcast 863	com/insidesecure/hce/MatrixHCECard
    //   44: astore_3
    //   45: aload_3
    //   46: instanceof 865
    //   49: ifeq +6 -> 55
    //   52: goto +131 -> 183
    //   55: goto +133 -> 188
    //   58: iconst_1
    //   59: istore_1
    //   60: goto +84 -> 144
    //   63: astore_2
    //   64: aload_2
    //   65: athrow
    //   66: iload_1
    //   67: tableswitch	default:+21->88, 0:+21->88, 1:+71->138
    //   88: getstatic 25	o/pn:ॱॱ	I
    //   91: istore_1
    //   92: iload_1
    //   93: bipush 69
    //   95: iadd
    //   96: istore_1
    //   97: iload_1
    //   98: sipush 128
    //   101: irem
    //   102: putstatic 27	o/pn:ʼ	I
    //   105: iload_1
    //   106: iconst_2
    //   107: irem
    //   108: ifne +6 -> 114
    //   111: goto +30 -> 141
    //   114: goto +106 -> 220
    //   117: invokestatic 94	com/insidesecure/hce/MatrixHCE$MatrixHCEFactory:getInstance	()Lcom/insidesecure/hce/MatrixHCE;
    //   120: aload_0
    //   121: invokevirtual 868	o/pn:getAccountName	()Ljava/lang/String;
    //   124: invokeinterface 873 2 0
    //   129: invokeinterface 131 1 0
    //   134: astore_2
    //   135: goto +98 -> 233
    //   138: goto +95 -> 233
    //   141: goto +79 -> 220
    //   144: iload_1
    //   145: tableswitch	default:+23->168, 0:+34->179, 1:+-112->33
    //   168: goto -135 -> 33
    //   171: iconst_0
    //   172: istore_1
    //   173: goto -29 -> 144
    //   176: goto -59 -> 117
    //   179: return
    //   180: goto -42 -> 138
    //   183: iconst_0
    //   184: istore_1
    //   185: goto -119 -> 66
    //   188: iconst_1
    //   189: istore_1
    //   190: goto -124 -> 66
    //   193: getstatic 27	o/pn:ʼ	I
    //   196: bipush 9
    //   198: iadd
    //   199: istore_1
    //   200: iload_1
    //   201: sipush 128
    //   204: irem
    //   205: putstatic 25	o/pn:ॱॱ	I
    //   208: iload_1
    //   209: iconst_2
    //   210: irem
    //   211: ifeq +6 -> 217
    //   214: goto +34 -> 248
    //   217: goto -37 -> 180
    //   220: aload_3
    //   221: checkcast 865	o/pu
    //   224: invokevirtual 876	o/pu:ˊॱ	()V
    //   227: goto -34 -> 193
    //   230: goto -227 -> 3
    //   233: aload_2
    //   234: invokeinterface 84 1 0
    //   239: ifeq +6 -> 245
    //   242: goto -184 -> 58
    //   245: goto -74 -> 171
    //   248: goto -68 -> 180
    // Local variable table:
    //   start	length	slot	name	signature
    //   0	251	0	this	pn
    //   9	202	1	i	int
    //   30	4	2	localException1	Exception
    //   63	2	2	localException2	Exception
    //   134	100	2	localIterator	java.util.Iterator
    //   39	182	3	localObject	Object
    // Exception table:
    //   from	to	target	type
    //   40	45	30	java/lang/Exception
    //   88	92	30	java/lang/Exception
    //   97	105	30	java/lang/Exception
    //   33	40	63	java/lang/Exception
    //   40	45	63	java/lang/Exception
  }
  
  public byte[] getEncryptedPin(byte[] paramArrayOfByte)
  {
    for (;;)
    {
      try
      {
        String str = this.ˏ;
        paramArrayOfByte = MatrixHCENativeBridge.getEncryptedPin(str, paramArrayOfByte);
        int i = ॱॱ + 119;
        ʼ = i % 128;
        if (i % 2 != 0) {}
        i = 42;
        continue;
        if (paramArrayOfByte != null) {}
        switch (i)
        {
        default: 
          return paramArrayOfByte;
        case 42: 
          throw new NullPointerException();
          i = ʼ + 39;
          ॱॱ = i % 128;
          if (i % 2 == 0)
          {
            continue;
            i = 62;
            continue;
            throw new MatrixHCEException(ˊ(27, '䯻', 47).intern(), MatrixHCEError.UNINITIALIZED_PARAMETERS);
          }
          break;
        }
      }
      catch (Exception paramArrayOfByte)
      {
        throw paramArrayOfByte;
      }
    }
    return paramArrayOfByte;
  }
  
  public long getNetworkSessionValidity()
  {
    break label66;
    long l = MatrixHCENativeBridge.remainingSessionValidity(this.ˏ);
    break label40;
    int i = 1;
    break label95;
    label19:
    i = 0;
    for (;;)
    {
      l = MatrixHCENativeBridge.remainingSessionValidity(this.ˏ);
      throw new NullPointerException();
      label40:
      i = ॱॱ + 31;
      ʼ = i % 128;
      if (i % 2 != 0)
      {
        return l;
        label66:
        i = ʼ + 71;
        ॱॱ = i % 128;
        if (i % 2 != 0) {
          break label19;
        }
        break;
      }
      return l;
      label95:
      switch (i)
      {
      }
    }
  }
  
  /* Error */
  public MatrixHCENetworkData handleNetworkResponse(MatrixHCENetworkData paramMatrixHCENetworkData, boolean paramBoolean, byte[] paramArrayOfByte)
  {
    // Byte code:
    //   0: goto +94 -> 94
    //   3: goto +135 -> 138
    //   6: astore_1
    //   7: aload_1
    //   8: athrow
    //   9: astore_1
    //   10: aload_1
    //   11: athrow
    //   12: getstatic 27	o/pn:ʼ	I
    //   15: istore 4
    //   17: iload 4
    //   19: bipush 125
    //   21: iadd
    //   22: istore 4
    //   24: iload 4
    //   26: sipush 128
    //   29: irem
    //   30: putstatic 25	o/pn:ॱॱ	I
    //   33: iload 4
    //   35: iconst_2
    //   36: irem
    //   37: ifeq +6 -> 43
    //   40: goto -37 -> 3
    //   43: goto +95 -> 138
    //   46: getstatic 27	o/pn:ʼ	I
    //   49: bipush 87
    //   51: iadd
    //   52: istore 4
    //   54: iload 4
    //   56: sipush 128
    //   59: irem
    //   60: putstatic 25	o/pn:ॱॱ	I
    //   63: iload 4
    //   65: iconst_2
    //   66: irem
    //   67: ifeq +5 -> 72
    //   70: aload_1
    //   71: areturn
    //   72: aload_1
    //   73: areturn
    //   74: new 902	com/insidesecure/hce/MatrixHCENetworkData
    //   77: dup
    //   78: getstatic 908	com/insidesecure/hce/NetworkOperationPreparationInfo$NetworkOperation:UNKNOWN	Lcom/insidesecure/hce/NetworkOperationPreparationInfo$NetworkOperation;
    //   81: getstatic 889	com/insidesecure/hce/MatrixHCEError:UNINITIALIZED_PARAMETERS	Lcom/insidesecure/hce/MatrixHCEError;
    //   84: aconst_null
    //   85: aconst_null
    //   86: aconst_null
    //   87: invokespecial 911	com/insidesecure/hce/MatrixHCENetworkData:<init>	(Lcom/insidesecure/hce/NetworkOperationPreparationInfo$NetworkOperation;Lcom/insidesecure/hce/MatrixHCEError;[BLjava/lang/String;Ljava/lang/String;)V
    //   90: astore_1
    //   91: goto -45 -> 46
    //   94: goto -82 -> 12
    //   97: aload_0
    //   98: getfield 105	o/pn:ˏ	Ljava/lang/String;
    //   101: aload_1
    //   102: invokevirtual 915	com/insidesecure/hce/MatrixHCENetworkData:getOperation	()Lcom/insidesecure/hce/NetworkOperationPreparationInfo$NetworkOperation;
    //   105: invokevirtual 918	com/insidesecure/hce/NetworkOperationPreparationInfo$NetworkOperation:ordinal	()I
    //   108: aload_1
    //   109: invokevirtual 921	com/insidesecure/hce/MatrixHCENetworkData:getTaskId	()Ljava/lang/String;
    //   112: iload_2
    //   113: aload_3
    //   114: invokestatic 925	com/insidesecure/hce/internal/MatrixHCENativeBridge:handleAccountNetworkResponse	(Ljava/lang/String;ILjava/lang/String;Z[B)Lcom/insidesecure/hce/MatrixHCEError;
    //   117: astore_3
    //   118: aload_0
    //   119: invokespecial 856	o/pn:ʼ	()V
    //   122: new 902	com/insidesecure/hce/MatrixHCENetworkData
    //   125: dup
    //   126: aload_1
    //   127: invokevirtual 915	com/insidesecure/hce/MatrixHCENetworkData:getOperation	()Lcom/insidesecure/hce/NetworkOperationPreparationInfo$NetworkOperation;
    //   130: aload_3
    //   131: aconst_null
    //   132: aconst_null
    //   133: aconst_null
    //   134: invokespecial 911	com/insidesecure/hce/MatrixHCENetworkData:<init>	(Lcom/insidesecure/hce/NetworkOperationPreparationInfo$NetworkOperation;Lcom/insidesecure/hce/MatrixHCEError;[BLjava/lang/String;Ljava/lang/String;)V
    //   137: areturn
    //   138: aload_1
    //   139: ifnonnull +6 -> 145
    //   142: goto -68 -> 74
    //   145: goto -48 -> 97
    // Local variable table:
    //   start	length	slot	name	signature
    //   0	148	0	this	pn
    //   0	148	1	paramMatrixHCENetworkData	MatrixHCENetworkData
    //   0	148	2	paramBoolean	boolean
    //   0	148	3	paramArrayOfByte	byte[]
    //   15	52	4	i	int
    // Exception table:
    //   from	to	target	type
    //   24	33	6	java/lang/Exception
    //   12	17	9	java/lang/Exception
  }
  
  public MatrixHCENetworkData openNetworkSession()
  {
    try
    {
      for (;;)
      {
        Object localObject = this.ˏ;
        long l = MatrixHCENativeBridge.remainingSessionValidity((String)localObject);
        pD.d(ˊ, ˊ(0, '俸', 27).intern() + l);
        if (l > 0L) {
          break;
        }
        localObject = this.ˏ;
        localObject = MatrixHCENativeBridge.requestNetworkSessionRequest((String)localObject);
        break label100;
      }
      return new MatrixHCENetworkData(NetworkOperationPreparationInfo.NetworkOperation.MASTERCARD_REQUEST_SESSION, MatrixHCEError.NO_DATA_TO_SEND, null, null, null);
    }
    catch (Exception localException)
    {
      throw localException;
    }
    label100:
    int i = ॱॱ + 111;
    ʼ = i % 128;
    if (i % 2 == 0) {
      return localException;
    }
    return localException;
  }
  
  public void registerAccount(MatrixHCENetworkOperationCallback paramMatrixHCENetworkOperationCallback)
  {
    for (;;)
    {
      new Thread(new Runnable()
      {
        private static int ˊ = 0;
        private static int ˋ = 1;
        private static long ˏ = -3700963564722648540L;
        
        private static String ॱ(char[] paramAnonymousArrayOfChar)
        {
          break label157;
          int j = 54;
          label9:
          char[] arrayOfChar;
          int i;
          int k;
          switch (j)
          {
          case 88: 
          default: 
            arrayOfChar[(i >>> 1)] = ((char)(int)((paramAnonymousArrayOfChar[i] & i * k) % ˏ));
            i += 3;
            break;
            switch (j)
            {
            default: 
              break;
            case 54: 
              for (;;)
              {
                k = paramAnonymousArrayOfChar[0];
                arrayOfChar = new char[paramAnonymousArrayOfChar.length - 1];
                i = 1;
                break label131;
                j = 88;
                break;
                do
                {
                  break;
                  return new String(arrayOfChar);
                  j = ˋ + 1;
                  ˊ = j % 128;
                } while (j % 2 != 0);
                break label193;
              }
            }
            break;
          case 17: 
            label63:
            label112:
            label131:
            label157:
            arrayOfChar[(i - 1)] = ((char)(int)(paramAnonymousArrayOfChar[i] ^ i * k ^ ˏ));
            i += 1;
            break;
          }
          for (;;)
          {
            j = 17;
            break label9;
            label193:
            if (i >= paramAnonymousArrayOfChar.length) {
              break;
            }
            j = 30;
            break label63;
            j = ˊ + 89;
            ˋ = j % 128;
            if (j % 2 == 0) {
              break label112;
            }
          }
        }
        
        /* Error */
        public void run()
        {
          // Byte code:
          //   0: goto +1022 -> 1022
          //   3: getstatic 26	o/pn$1:ˋ	I
          //   6: bipush 67
          //   8: iadd
          //   9: istore_1
          //   10: iload_1
          //   11: sipush 128
          //   14: irem
          //   15: putstatic 24	o/pn$1:ˊ	I
          //   18: iload_1
          //   19: iconst_2
          //   20: irem
          //   21: ifeq +6 -> 27
          //   24: goto +915 -> 939
          //   27: goto +1036 -> 1063
          //   30: bipush 11
          //   32: istore_1
          //   33: goto +992 -> 1025
          //   36: astore_2
          //   37: aload_2
          //   38: athrow
          //   39: iconst_1
          //   40: istore_1
          //   41: goto +945 -> 986
          //   44: aload_0
          //   45: getfield 39	o/pn$1:ॱ	Lcom/insidesecure/hce/MatrixHCENetworkOperationCallback;
          //   48: aload_2
          //   49: aconst_null
          //   50: invokestatic 54	o/pD:executePostNetworkCallback	(Lcom/insidesecure/hce/MatrixHCENetworkOperationCallback;Lcom/insidesecure/hce/internal/MatrixHCENetworkOperationResponse;Ljava/lang/Integer;)Z
          //   53: pop
          //   54: return
          //   55: invokestatic 57	o/pn:ॱ	()Ljava/lang/String;
          //   58: bipush 59
          //   60: newarray char
          //   62: dup
          //   63: iconst_0
          //   64: ldc 58
          //   66: castore
          //   67: dup
          //   68: iconst_1
          //   69: ldc 59
          //   71: castore
          //   72: dup
          //   73: iconst_2
          //   74: ldc 60
          //   76: castore
          //   77: dup
          //   78: iconst_3
          //   79: ldc 61
          //   81: castore
          //   82: dup
          //   83: iconst_4
          //   84: ldc 62
          //   86: castore
          //   87: dup
          //   88: iconst_5
          //   89: ldc 63
          //   91: castore
          //   92: dup
          //   93: bipush 6
          //   95: ldc 64
          //   97: castore
          //   98: dup
          //   99: bipush 7
          //   101: ldc 65
          //   103: castore
          //   104: dup
          //   105: bipush 8
          //   107: ldc 66
          //   109: castore
          //   110: dup
          //   111: bipush 9
          //   113: ldc 67
          //   115: castore
          //   116: dup
          //   117: bipush 10
          //   119: ldc 68
          //   121: castore
          //   122: dup
          //   123: bipush 11
          //   125: ldc 69
          //   127: castore
          //   128: dup
          //   129: bipush 12
          //   131: ldc 70
          //   133: castore
          //   134: dup
          //   135: bipush 13
          //   137: ldc 71
          //   139: castore
          //   140: dup
          //   141: bipush 14
          //   143: ldc 72
          //   145: castore
          //   146: dup
          //   147: bipush 15
          //   149: ldc 73
          //   151: castore
          //   152: dup
          //   153: bipush 16
          //   155: ldc 74
          //   157: castore
          //   158: dup
          //   159: bipush 17
          //   161: ldc 75
          //   163: castore
          //   164: dup
          //   165: bipush 18
          //   167: ldc 76
          //   169: castore
          //   170: dup
          //   171: bipush 19
          //   173: ldc 77
          //   175: castore
          //   176: dup
          //   177: bipush 20
          //   179: ldc 78
          //   181: castore
          //   182: dup
          //   183: bipush 21
          //   185: ldc 79
          //   187: castore
          //   188: dup
          //   189: bipush 22
          //   191: ldc 80
          //   193: castore
          //   194: dup
          //   195: bipush 23
          //   197: ldc 81
          //   199: castore
          //   200: dup
          //   201: bipush 24
          //   203: ldc 82
          //   205: castore
          //   206: dup
          //   207: bipush 25
          //   209: ldc 83
          //   211: castore
          //   212: dup
          //   213: bipush 26
          //   215: ldc 84
          //   217: castore
          //   218: dup
          //   219: bipush 27
          //   221: ldc 85
          //   223: castore
          //   224: dup
          //   225: bipush 28
          //   227: ldc 86
          //   229: castore
          //   230: dup
          //   231: bipush 29
          //   233: ldc 87
          //   235: castore
          //   236: dup
          //   237: bipush 30
          //   239: ldc 88
          //   241: castore
          //   242: dup
          //   243: bipush 31
          //   245: ldc 89
          //   247: castore
          //   248: dup
          //   249: bipush 32
          //   251: ldc 90
          //   253: castore
          //   254: dup
          //   255: bipush 33
          //   257: ldc 91
          //   259: castore
          //   260: dup
          //   261: bipush 34
          //   263: ldc 92
          //   265: castore
          //   266: dup
          //   267: bipush 35
          //   269: ldc 93
          //   271: castore
          //   272: dup
          //   273: bipush 36
          //   275: ldc 94
          //   277: castore
          //   278: dup
          //   279: bipush 37
          //   281: ldc 95
          //   283: castore
          //   284: dup
          //   285: bipush 38
          //   287: ldc 96
          //   289: castore
          //   290: dup
          //   291: bipush 39
          //   293: ldc 97
          //   295: castore
          //   296: dup
          //   297: bipush 40
          //   299: ldc 98
          //   301: castore
          //   302: dup
          //   303: bipush 41
          //   305: ldc 99
          //   307: castore
          //   308: dup
          //   309: bipush 42
          //   311: ldc 100
          //   313: castore
          //   314: dup
          //   315: bipush 43
          //   317: ldc 101
          //   319: castore
          //   320: dup
          //   321: bipush 44
          //   323: ldc 102
          //   325: castore
          //   326: dup
          //   327: bipush 45
          //   329: ldc 103
          //   331: castore
          //   332: dup
          //   333: bipush 46
          //   335: ldc 104
          //   337: castore
          //   338: dup
          //   339: bipush 47
          //   341: ldc 105
          //   343: castore
          //   344: dup
          //   345: bipush 48
          //   347: ldc 106
          //   349: castore
          //   350: dup
          //   351: bipush 49
          //   353: ldc 107
          //   355: castore
          //   356: dup
          //   357: bipush 50
          //   359: ldc 108
          //   361: castore
          //   362: dup
          //   363: bipush 51
          //   365: ldc 109
          //   367: castore
          //   368: dup
          //   369: bipush 52
          //   371: ldc 110
          //   373: castore
          //   374: dup
          //   375: bipush 53
          //   377: ldc 111
          //   379: castore
          //   380: dup
          //   381: bipush 54
          //   383: ldc 112
          //   385: castore
          //   386: dup
          //   387: bipush 55
          //   389: ldc 113
          //   391: castore
          //   392: dup
          //   393: bipush 56
          //   395: ldc 114
          //   397: castore
          //   398: dup
          //   399: bipush 57
          //   401: ldc 115
          //   403: castore
          //   404: dup
          //   405: bipush 58
          //   407: ldc 116
          //   409: castore
          //   410: invokestatic 118	o/pn$1:ॱ	([C)Ljava/lang/String;
          //   413: invokevirtual 121	java/lang/String:intern	()Ljava/lang/String;
          //   416: invokestatic 125	o/pD:i	(Ljava/lang/String;Ljava/lang/String;)V
          //   419: aload_3
          //   420: astore_2
          //   421: goto -377 -> 44
          //   424: astore_2
          //   425: aload_2
          //   426: athrow
          //   427: invokestatic 57	o/pn:ॱ	()Ljava/lang/String;
          //   430: bipush 32
          //   432: newarray char
          //   434: dup
          //   435: iconst_0
          //   436: ldc 126
          //   438: castore
          //   439: dup
          //   440: iconst_1
          //   441: ldc 127
          //   443: castore
          //   444: dup
          //   445: iconst_2
          //   446: ldc -128
          //   448: castore
          //   449: dup
          //   450: iconst_3
          //   451: ldc -127
          //   453: castore
          //   454: dup
          //   455: iconst_4
          //   456: ldc -126
          //   458: castore
          //   459: dup
          //   460: iconst_5
          //   461: ldc -125
          //   463: castore
          //   464: dup
          //   465: bipush 6
          //   467: ldc -124
          //   469: castore
          //   470: dup
          //   471: bipush 7
          //   473: ldc -123
          //   475: castore
          //   476: dup
          //   477: bipush 8
          //   479: ldc -122
          //   481: castore
          //   482: dup
          //   483: bipush 9
          //   485: ldc -121
          //   487: castore
          //   488: dup
          //   489: bipush 10
          //   491: ldc -120
          //   493: castore
          //   494: dup
          //   495: bipush 11
          //   497: ldc -119
          //   499: castore
          //   500: dup
          //   501: bipush 12
          //   503: ldc -118
          //   505: castore
          //   506: dup
          //   507: bipush 13
          //   509: ldc -117
          //   511: castore
          //   512: dup
          //   513: bipush 14
          //   515: ldc -116
          //   517: castore
          //   518: dup
          //   519: bipush 15
          //   521: ldc -115
          //   523: castore
          //   524: dup
          //   525: bipush 16
          //   527: ldc -114
          //   529: castore
          //   530: dup
          //   531: bipush 17
          //   533: ldc -113
          //   535: castore
          //   536: dup
          //   537: bipush 18
          //   539: ldc -112
          //   541: castore
          //   542: dup
          //   543: bipush 19
          //   545: ldc -111
          //   547: castore
          //   548: dup
          //   549: bipush 20
          //   551: ldc -110
          //   553: castore
          //   554: dup
          //   555: bipush 21
          //   557: ldc -109
          //   559: castore
          //   560: dup
          //   561: bipush 22
          //   563: ldc -108
          //   565: castore
          //   566: dup
          //   567: bipush 23
          //   569: ldc -107
          //   571: castore
          //   572: dup
          //   573: bipush 24
          //   575: ldc -106
          //   577: castore
          //   578: dup
          //   579: bipush 25
          //   581: ldc -105
          //   583: castore
          //   584: dup
          //   585: bipush 26
          //   587: ldc -104
          //   589: castore
          //   590: dup
          //   591: bipush 27
          //   593: ldc -103
          //   595: castore
          //   596: dup
          //   597: bipush 28
          //   599: ldc -102
          //   601: castore
          //   602: dup
          //   603: bipush 29
          //   605: ldc -101
          //   607: castore
          //   608: dup
          //   609: bipush 30
          //   611: ldc -100
          //   613: castore
          //   614: dup
          //   615: bipush 31
          //   617: ldc -99
          //   619: castore
          //   620: invokestatic 118	o/pn$1:ॱ	([C)Ljava/lang/String;
          //   623: invokevirtual 121	java/lang/String:intern	()Ljava/lang/String;
          //   626: invokestatic 125	o/pD:i	(Ljava/lang/String;Ljava/lang/String;)V
          //   629: aload_0
          //   630: getfield 37	o/pn$1:ˎ	Lo/pn;
          //   633: invokestatic 160	o/pn:ॱ	(Lo/pn;)V
          //   636: aconst_null
          //   637: arraylength
          //   638: istore_1
          //   639: goto +416 -> 1055
          //   642: aload_0
          //   643: getfield 37	o/pn$1:ˎ	Lo/pn;
          //   646: invokestatic 163	o/pn:ˎ	(Lo/pn;)Ljava/lang/String;
          //   649: aload_0
          //   650: getfield 39	o/pn$1:ॱ	Lcom/insidesecure/hce/MatrixHCENetworkOperationCallback;
          //   653: invokestatic 168	com/insidesecure/hce/internal/MatrixHCENativeBridge:registerAccount	(Ljava/lang/String;Lcom/insidesecure/hce/MatrixHCENetworkOperationCallback;)Lcom/insidesecure/hce/internal/MatrixHCENetworkOperationResponse;
          //   656: astore 4
          //   658: aload 4
          //   660: getfield 174	com/insidesecure/hce/internal/MatrixHCENetworkOperationResponse:error	Lcom/insidesecure/hce/MatrixHCEError;
          //   663: astore_2
          //   664: getstatic 179	com/insidesecure/hce/MatrixHCEError:SUCCESS	Lcom/insidesecure/hce/MatrixHCEError;
          //   667: astore_3
          //   668: aconst_null
          //   669: arraylength
          //   670: istore_1
          //   671: aload_2
          //   672: aload_3
          //   673: if_acmpne +6 -> 679
          //   676: goto +393 -> 1069
          //   679: goto +379 -> 1058
          //   682: invokestatic 57	o/pn:ॱ	()Ljava/lang/String;
          //   685: astore_3
          //   686: bipush 32
          //   688: newarray char
          //   690: dup
          //   691: iconst_0
          //   692: ldc 126
          //   694: castore
          //   695: dup
          //   696: iconst_1
          //   697: ldc 127
          //   699: castore
          //   700: dup
          //   701: iconst_2
          //   702: ldc -128
          //   704: castore
          //   705: dup
          //   706: iconst_3
          //   707: ldc -127
          //   709: castore
          //   710: dup
          //   711: iconst_4
          //   712: ldc -126
          //   714: castore
          //   715: dup
          //   716: iconst_5
          //   717: ldc -125
          //   719: castore
          //   720: dup
          //   721: bipush 6
          //   723: ldc -124
          //   725: castore
          //   726: dup
          //   727: bipush 7
          //   729: ldc -123
          //   731: castore
          //   732: dup
          //   733: bipush 8
          //   735: ldc -122
          //   737: castore
          //   738: dup
          //   739: bipush 9
          //   741: ldc -121
          //   743: castore
          //   744: dup
          //   745: bipush 10
          //   747: ldc -120
          //   749: castore
          //   750: dup
          //   751: bipush 11
          //   753: ldc -119
          //   755: castore
          //   756: dup
          //   757: bipush 12
          //   759: ldc -118
          //   761: castore
          //   762: dup
          //   763: bipush 13
          //   765: ldc -117
          //   767: castore
          //   768: dup
          //   769: bipush 14
          //   771: ldc -116
          //   773: castore
          //   774: dup
          //   775: bipush 15
          //   777: ldc -115
          //   779: castore
          //   780: dup
          //   781: bipush 16
          //   783: ldc -114
          //   785: castore
          //   786: dup
          //   787: bipush 17
          //   789: ldc -113
          //   791: castore
          //   792: dup
          //   793: bipush 18
          //   795: ldc -112
          //   797: castore
          //   798: dup
          //   799: bipush 19
          //   801: ldc -111
          //   803: castore
          //   804: dup
          //   805: bipush 20
          //   807: ldc -110
          //   809: castore
          //   810: dup
          //   811: bipush 21
          //   813: ldc -109
          //   815: castore
          //   816: dup
          //   817: bipush 22
          //   819: ldc -108
          //   821: castore
          //   822: dup
          //   823: bipush 23
          //   825: ldc -107
          //   827: castore
          //   828: dup
          //   829: bipush 24
          //   831: ldc -106
          //   833: castore
          //   834: dup
          //   835: bipush 25
          //   837: ldc -105
          //   839: castore
          //   840: dup
          //   841: bipush 26
          //   843: ldc -104
          //   845: castore
          //   846: dup
          //   847: bipush 27
          //   849: ldc -103
          //   851: castore
          //   852: dup
          //   853: bipush 28
          //   855: ldc -102
          //   857: castore
          //   858: dup
          //   859: bipush 29
          //   861: ldc -101
          //   863: castore
          //   864: dup
          //   865: bipush 30
          //   867: ldc -100
          //   869: castore
          //   870: dup
          //   871: bipush 31
          //   873: ldc -99
          //   875: castore
          //   876: invokestatic 118	o/pn$1:ॱ	([C)Ljava/lang/String;
          //   879: astore 4
          //   881: aload 4
          //   883: invokevirtual 121	java/lang/String:intern	()Ljava/lang/String;
          //   886: astore 4
          //   888: aload_3
          //   889: aload 4
          //   891: invokestatic 125	o/pD:i	(Ljava/lang/String;Ljava/lang/String;)V
          //   894: aload_0
          //   895: getfield 37	o/pn$1:ˎ	Lo/pn;
          //   898: invokestatic 160	o/pn:ॱ	(Lo/pn;)V
          //   901: goto +154 -> 1055
          //   904: bipush 73
          //   906: istore_1
          //   907: goto +118 -> 1025
          //   910: iload_1
          //   911: lookupswitch	default:+25->936, 9:+-484->427, 89:+-229->682
          //   936: goto -509 -> 427
          //   939: bipush 9
          //   941: istore_1
          //   942: goto -32 -> 910
          //   945: iconst_0
          //   946: istore_1
          //   947: goto +39 -> 986
          //   950: aload 4
          //   952: astore_2
          //   953: aload 4
          //   955: astore_3
          //   956: iload_1
          //   957: tableswitch	default:+23->980, 0:+-902->55, 1:+-954->3
          //   980: aload 4
          //   982: astore_3
          //   983: goto -928 -> 55
          //   986: aload 4
          //   988: astore_2
          //   989: aload 4
          //   991: astore_3
          //   992: iload_1
          //   993: tableswitch	default:+23->1016, 0:+-938->55, 1:+-990->3
          //   1016: aload 4
          //   1018: astore_2
          //   1019: goto -1016 -> 3
          //   1022: goto +52 -> 1074
          //   1025: iload_1
          //   1026: lookupswitch	default:+26->1052, 11:+75->1101, 73:+-384->642
          //   1052: goto +49 -> 1101
          //   1055: goto -1011 -> 44
          //   1058: iconst_0
          //   1059: istore_1
          //   1060: goto -110 -> 950
          //   1063: bipush 89
          //   1065: istore_1
          //   1066: goto -156 -> 910
          //   1069: iconst_1
          //   1070: istore_1
          //   1071: goto -121 -> 950
          //   1074: getstatic 24	o/pn$1:ˊ	I
          //   1077: bipush 81
          //   1079: iadd
          //   1080: istore_1
          //   1081: iload_1
          //   1082: sipush 128
          //   1085: irem
          //   1086: putstatic 26	o/pn$1:ˋ	I
          //   1089: iload_1
          //   1090: iconst_2
          //   1091: irem
          //   1092: ifne +6 -> 1098
          //   1095: goto -191 -> 904
          //   1098: goto -1068 -> 30
          //   1101: aload_0
          //   1102: getfield 37	o/pn$1:ˎ	Lo/pn;
          //   1105: invokestatic 163	o/pn:ˎ	(Lo/pn;)Ljava/lang/String;
          //   1108: aload_0
          //   1109: getfield 39	o/pn$1:ॱ	Lcom/insidesecure/hce/MatrixHCENetworkOperationCallback;
          //   1112: invokestatic 168	com/insidesecure/hce/internal/MatrixHCENativeBridge:registerAccount	(Ljava/lang/String;Lcom/insidesecure/hce/MatrixHCENetworkOperationCallback;)Lcom/insidesecure/hce/internal/MatrixHCENetworkOperationResponse;
          //   1115: astore 4
          //   1117: aload 4
          //   1119: getfield 174	com/insidesecure/hce/internal/MatrixHCENetworkOperationResponse:error	Lcom/insidesecure/hce/MatrixHCEError;
          //   1122: getstatic 179	com/insidesecure/hce/MatrixHCEError:SUCCESS	Lcom/insidesecure/hce/MatrixHCEError;
          //   1125: if_acmpne +6 -> 1131
          //   1128: goto -1089 -> 39
          //   1131: goto -186 -> 945
          // Local variable table:
          //   start	length	slot	name	signature
          //   0	1134	0	this	1
          //   9	1083	1	i	int
          //   36	13	2	localException1	Exception
          //   420	1	2	localObject1	Object
          //   424	2	2	localException2	Exception
          //   663	356	2	localObject2	Object
          //   419	573	3	localObject3	Object
          //   656	462	4	localObject4	Object
          // Exception table:
          //   from	to	target	type
          //   682	686	36	java/lang/Exception
          //   686	881	36	java/lang/Exception
          //   881	888	36	java/lang/Exception
          //   888	894	36	java/lang/Exception
          //   894	901	36	java/lang/Exception
          //   881	888	424	java/lang/Exception
        }
      }).start();
      int i = ॱॱ + 11;
      ʼ = i % 128;
      if (i % 2 == 0) {
        return;
      }
      return;
    }
  }
  
  /* Error */
  @Deprecated
  public MatrixHCENetworkData registerAccountToServer(String paramString1, String paramString2)
  {
    // Byte code:
    //   0: goto +82 -> 82
    //   3: goto +24 -> 27
    //   6: aconst_null
    //   7: astore_2
    //   8: aload 4
    //   10: aload_1
    //   11: aload_2
    //   12: invokestatic 960	com/insidesecure/hce/internal/MatrixHCENativeBridge:registerAccountToServerRequest	(Ljava/lang/String;Ljava/lang/String;[B)Lcom/insidesecure/hce/MatrixHCENetworkData;
    //   15: areturn
    //   16: astore_1
    //   17: aload_1
    //   18: athrow
    //   19: goto -13 -> 6
    //   22: iconst_0
    //   23: istore_3
    //   24: goto +90 -> 114
    //   27: aload_0
    //   28: getfield 105	o/pn:ˏ	Ljava/lang/String;
    //   31: astore 4
    //   33: aload_2
    //   34: ifnonnull +6 -> 40
    //   37: goto +40 -> 77
    //   40: goto -18 -> 22
    //   43: aload_2
    //   44: invokevirtual 964	java/lang/String:getBytes	()[B
    //   47: astore_2
    //   48: goto -40 -> 8
    //   51: getstatic 27	o/pn:ʼ	I
    //   54: iconst_5
    //   55: iadd
    //   56: istore_3
    //   57: iload_3
    //   58: sipush 128
    //   61: irem
    //   62: putstatic 25	o/pn:ॱॱ	I
    //   65: iload_3
    //   66: iconst_2
    //   67: irem
    //   68: ifeq +6 -> 74
    //   71: goto -68 -> 3
    //   74: goto -47 -> 27
    //   77: iconst_1
    //   78: istore_3
    //   79: goto +35 -> 114
    //   82: goto -31 -> 51
    //   85: getstatic 27	o/pn:ʼ	I
    //   88: istore_3
    //   89: iload_3
    //   90: bipush 99
    //   92: iadd
    //   93: istore_3
    //   94: iload_3
    //   95: sipush 128
    //   98: irem
    //   99: putstatic 25	o/pn:ॱॱ	I
    //   102: iload_3
    //   103: iconst_2
    //   104: irem
    //   105: ifeq +6 -> 111
    //   108: goto -89 -> 19
    //   111: goto -105 -> 6
    //   114: iload_3
    //   115: tableswitch	default:+21->136, 0:+-72->43, 1:+-30->85
    //   136: goto -51 -> 85
    // Local variable table:
    //   start	length	slot	name	signature
    //   0	139	0	this	pn
    //   0	139	1	paramString1	String
    //   0	139	2	paramString2	String
    //   23	92	3	i	int
    //   8	24	4	str	String
    // Exception table:
    //   from	to	target	type
    //   85	89	16	java/lang/Exception
    //   94	102	16	java/lang/Exception
  }
  
  /* Error */
  public MatrixHCENetworkData registerAccountToServer(String paramString, byte[] paramArrayOfByte)
  {
    // Byte code:
    //   0: goto +45 -> 45
    //   3: iconst_1
    //   4: istore_3
    //   5: goto +43 -> 48
    //   8: aload_0
    //   9: getfield 105	o/pn:ˏ	Ljava/lang/String;
    //   12: aload_1
    //   13: aload_2
    //   14: invokestatic 960	com/insidesecure/hce/internal/MatrixHCENativeBridge:registerAccountToServerRequest	(Ljava/lang/String;Ljava/lang/String;[B)Lcom/insidesecure/hce/MatrixHCENetworkData;
    //   17: astore_1
    //   18: aload_2
    //   19: ifnull +6 -> 25
    //   22: goto +116 -> 138
    //   25: goto +15 -> 40
    //   28: aload_2
    //   29: bipush 90
    //   31: invokestatic 972	java/util/Arrays:fill	([BB)V
    //   34: goto +72 -> 106
    //   37: astore_1
    //   38: aload_1
    //   39: athrow
    //   40: iconst_0
    //   41: istore_3
    //   42: goto +98 -> 140
    //   45: goto +34 -> 79
    //   48: iload_3
    //   49: lookupswitch	default:+27->76, 1:+124->173, 40:+-21->28
    //   76: goto -48 -> 28
    //   79: getstatic 27	o/pn:ʼ	I
    //   82: bipush 31
    //   84: iadd
    //   85: istore_3
    //   86: iload_3
    //   87: sipush 128
    //   90: irem
    //   91: putstatic 25	o/pn:ॱॱ	I
    //   94: iload_3
    //   95: iconst_2
    //   96: irem
    //   97: ifeq +6 -> 103
    //   100: goto -92 -> 8
    //   103: goto -95 -> 8
    //   106: aload_1
    //   107: areturn
    //   108: astore_1
    //   109: aload_1
    //   110: athrow
    //   111: getstatic 25	o/pn:ॱॱ	I
    //   114: bipush 29
    //   116: iadd
    //   117: istore_3
    //   118: iload_3
    //   119: sipush 128
    //   122: irem
    //   123: putstatic 27	o/pn:ʼ	I
    //   126: iload_3
    //   127: iconst_2
    //   128: irem
    //   129: ifne +6 -> 135
    //   132: goto +35 -> 167
    //   135: goto -132 -> 3
    //   138: iconst_1
    //   139: istore_3
    //   140: iload_3
    //   141: tableswitch	default:+23->164, 0:+41->182, 1:+-30->111
    //   164: goto -53 -> 111
    //   167: bipush 40
    //   169: istore_3
    //   170: goto -122 -> 48
    //   173: aload_2
    //   174: bipush 48
    //   176: invokestatic 972	java/util/Arrays:fill	([BB)V
    //   179: goto -73 -> 106
    //   182: aload_1
    //   183: areturn
    // Local variable table:
    //   start	length	slot	name	signature
    //   0	184	0	this	pn
    //   0	184	1	paramString	String
    //   0	184	2	paramArrayOfByte	byte[]
    //   4	166	3	i	int
    // Exception table:
    //   from	to	target	type
    //   79	86	37	java/lang/Exception
    //   86	94	37	java/lang/Exception
    //   173	179	108	java/lang/Exception
  }
  
  @Deprecated
  public void registerAccountToServer(final String paramString1, final String paramString2, final MatrixHCENetworkOperationCallback paramMatrixHCENetworkOperationCallback)
  {
    break label39;
    int i = ॱॱ + 59;
    ʼ = i % 128;
    if (i % 2 != 0) {
      break label103;
    }
    i = 1;
    break label43;
    label39:
    break label71;
    return;
    for (;;)
    {
      switch (i)
      {
      case 0: 
      default: 
        break label95;
        new Thread(new Runnable()
        {
          public void run()
          {
            String str1 = pn.ˏ(pn.this);
            String str2 = paramString1;
            if (paramString2 == null) {
              localObject = null;
            } else {
              localObject = paramString2.getBytes();
            }
            Object localObject = MatrixHCENativeBridge.registerAccountToServer(str1, str2, (byte[])localObject, paramMatrixHCENetworkOperationCallback);
            pD.executePostNetworkCallback(paramMatrixHCENetworkOperationCallback, (MatrixHCENetworkOperationResponse)localObject, null);
          }
        }).start();
        break;
      case 1: 
        label43:
        label71:
        label95:
        throw new NullPointerException();
        label103:
        i = 0;
      }
    }
  }
  
  /* Error */
  public void registerAccountToServer(final String paramString, final byte[] paramArrayOfByte, final MatrixHCENetworkOperationCallback paramMatrixHCENetworkOperationCallback)
  {
    // Byte code:
    //   0: goto +101 -> 101
    //   3: new 944	java/lang/Thread
    //   6: dup
    //   7: new 10	o/pn$5
    //   10: dup
    //   11: aload_0
    //   12: aload_1
    //   13: aload_2
    //   14: aload_3
    //   15: invokespecial 980	o/pn$5:<init>	(Lo/pn;Ljava/lang/String;[BLcom/insidesecure/hce/MatrixHCENetworkOperationCallback;)V
    //   18: invokespecial 950	java/lang/Thread:<init>	(Ljava/lang/Runnable;)V
    //   21: astore_1
    //   22: aload_1
    //   23: invokevirtual 953	java/lang/Thread:start	()V
    //   26: goto +45 -> 71
    //   29: return
    //   30: bipush 39
    //   32: iconst_0
    //   33: idiv
    //   34: istore 4
    //   36: return
    //   37: bipush 45
    //   39: istore 4
    //   41: iload 4
    //   43: lookupswitch	default:+25->68, 45:+-13->30, 81:+-14->29
    //   68: goto -38 -> 30
    //   71: getstatic 27	o/pn:ʼ	I
    //   74: bipush 17
    //   76: iadd
    //   77: istore 4
    //   79: iload 4
    //   81: sipush 128
    //   84: irem
    //   85: putstatic 25	o/pn:ॱॱ	I
    //   88: iload 4
    //   90: iconst_2
    //   91: irem
    //   92: ifeq +6 -> 98
    //   95: goto -58 -> 37
    //   98: goto +6 -> 104
    //   101: goto -98 -> 3
    //   104: bipush 81
    //   106: istore 4
    //   108: goto -67 -> 41
    //   111: astore_1
    //   112: aload_1
    //   113: athrow
    // Local variable table:
    //   start	length	slot	name	signature
    //   0	114	0	this	pn
    //   0	114	1	paramString	String
    //   0	114	2	paramArrayOfByte	byte[]
    //   0	114	3	paramMatrixHCENetworkOperationCallback	MatrixHCENetworkOperationCallback
    //   34	73	4	i	int
    // Exception table:
    //   from	to	target	type
    //   22	26	111	java/lang/Exception
  }
  
  @Deprecated
  public MatrixHCENetworkData signIn(String paramString1, String paramString2)
  {
    for (;;)
    {
      paramString1 = new MatrixHCENetworkData(NetworkOperationPreparationInfo.NetworkOperation.MAP_SIGN_IN, MatrixHCEError.UNSUPPORTED, null, null, null);
      int i = ॱॱ + 57;
      ʼ = i % 128;
      if (i % 2 == 0) {
        break;
      }
      return paramString1;
    }
    return paramString1;
  }
  
  public MatrixHCENetworkData signIn(String paramString, byte[] paramArrayOfByte)
  {
    break label49;
    int i = ॱॱ + 117;
    ʼ = i % 128;
    if (i % 2 != 0)
    {
      return paramString;
      label49:
      for (;;)
      {
        paramString = new MatrixHCENetworkData(NetworkOperationPreparationInfo.NetworkOperation.MAP_SIGN_IN, MatrixHCEError.UNSUPPORTED, null, null, null);
        break;
      }
    }
    return paramString;
  }
  
  @Deprecated
  public void signIn(MatrixHCENetworkOperationCallback paramMatrixHCENetworkOperationCallback, String paramString1, String paramString2)
  {
    break label95;
    unsupportedNetworkOperation(paramMatrixHCENetworkOperationCallback, NetworkOperationPreparationInfo.NetworkOperation.MAP_SIGN_IN, this.ˎ);
    int i = null.length;
    return;
    try
    {
      paramString1 = NetworkOperationPreparationInfo.NetworkOperation.MAP_SIGN_IN;
      paramString2 = this.ˎ;
      unsupportedNetworkOperation(paramMatrixHCENetworkOperationCallback, paramString1, paramString2);
      return;
    }
    catch (Exception paramMatrixHCENetworkOperationCallback)
    {
      label35:
      throw paramMatrixHCENetworkOperationCallback;
    }
    i = ʼ + 109;
    ॱॱ = i % 128;
    if (i % 2 == 0) {
      break label98;
    }
    for (;;)
    {
      switch (i)
      {
      }
      break;
      label95:
      break label35;
      label98:
      i = 1;
      continue;
      i = 0;
    }
  }
  
  /* Error */
  public void signIn(MatrixHCENetworkOperationCallback paramMatrixHCENetworkOperationCallback, String paramString, byte[] paramArrayOfByte)
  {
    // Byte code:
    //   0: goto +14 -> 14
    //   3: new 159	java/lang/NullPointerException
    //   6: dup
    //   7: invokespecial 160	java/lang/NullPointerException:<init>	()V
    //   10: athrow
    //   11: astore_1
    //   12: aload_1
    //   13: athrow
    //   14: goto +120 -> 134
    //   17: iload 4
    //   19: lookupswitch	default:+25->44, 95:+162->181, 97:+101->120
    //   44: goto +76 -> 120
    //   47: bipush 40
    //   49: istore 4
    //   51: iload 4
    //   53: lookupswitch	default:+27->80, 40:+66->119, 46:+-50->3
    //   80: goto -77 -> 3
    //   83: getstatic 27	o/pn:ʼ	I
    //   86: iconst_1
    //   87: iadd
    //   88: istore 4
    //   90: iload 4
    //   92: sipush 128
    //   95: irem
    //   96: putstatic 25	o/pn:ॱॱ	I
    //   99: iload 4
    //   101: iconst_2
    //   102: irem
    //   103: ifeq +6 -> 109
    //   106: goto +68 -> 174
    //   109: goto -62 -> 47
    //   112: bipush 95
    //   114: istore 4
    //   116: goto -99 -> 17
    //   119: return
    //   120: aload_1
    //   121: getstatic 984	com/insidesecure/hce/NetworkOperationPreparationInfo$NetworkOperation:MAP_SIGN_IN	Lcom/insidesecure/hce/NetworkOperationPreparationInfo$NetworkOperation;
    //   124: aload_0
    //   125: getfield 990	o/pn:ˎ	Ljava/lang/String;
    //   128: invokestatic 994	o/pn:unsupportedNetworkOperation	(Lcom/insidesecure/hce/MatrixHCENetworkOperationCallback;Lcom/insidesecure/hce/NetworkOperationPreparationInfo$NetworkOperation;Ljava/lang/String;)V
    //   131: goto -48 -> 83
    //   134: getstatic 27	o/pn:ʼ	I
    //   137: bipush 95
    //   139: iadd
    //   140: istore 4
    //   142: iload 4
    //   144: sipush 128
    //   147: irem
    //   148: putstatic 25	o/pn:ॱॱ	I
    //   151: iload 4
    //   153: iconst_2
    //   154: irem
    //   155: ifeq +6 -> 161
    //   158: goto -46 -> 112
    //   161: goto +6 -> 167
    //   164: astore_1
    //   165: aload_1
    //   166: athrow
    //   167: bipush 97
    //   169: istore 4
    //   171: goto -154 -> 17
    //   174: bipush 46
    //   176: istore 4
    //   178: goto -127 -> 51
    //   181: getstatic 984	com/insidesecure/hce/NetworkOperationPreparationInfo$NetworkOperation:MAP_SIGN_IN	Lcom/insidesecure/hce/NetworkOperationPreparationInfo$NetworkOperation;
    //   184: astore_2
    //   185: aload_0
    //   186: getfield 990	o/pn:ˎ	Ljava/lang/String;
    //   189: astore_3
    //   190: aload_1
    //   191: aload_2
    //   192: aload_3
    //   193: invokestatic 994	o/pn:unsupportedNetworkOperation	(Lcom/insidesecure/hce/MatrixHCENetworkOperationCallback;Lcom/insidesecure/hce/NetworkOperationPreparationInfo$NetworkOperation;Ljava/lang/String;)V
    //   196: aconst_null
    //   197: arraylength
    //   198: istore 4
    //   200: goto -117 -> 83
    // Local variable table:
    //   start	length	slot	name	signature
    //   0	203	0	this	pn
    //   0	203	1	paramMatrixHCENetworkOperationCallback	MatrixHCENetworkOperationCallback
    //   0	203	2	paramString	String
    //   0	203	3	paramArrayOfByte	byte[]
    //   17	182	4	i	int
    // Exception table:
    //   from	to	target	type
    //   134	142	11	java/lang/Exception
    //   142	151	11	java/lang/Exception
    //   181	185	11	java/lang/Exception
    //   185	190	11	java/lang/Exception
    //   190	200	11	java/lang/Exception
    //   142	151	164	java/lang/Exception
  }
  
  /* Error */
  public boolean ॱ(MatrixHCENetworkOperationCallback paramMatrixHCENetworkOperationCallback)
  {
    // Byte code:
    //   0: goto +449 -> 449
    //   3: getstatic 25	o/pn:ॱॱ	I
    //   6: bipush 101
    //   8: iadd
    //   9: istore_2
    //   10: iload_2
    //   11: sipush 128
    //   14: irem
    //   15: putstatic 27	o/pn:ʼ	I
    //   18: iload_2
    //   19: iconst_2
    //   20: irem
    //   21: ifne +6 -> 27
    //   24: goto +6 -> 30
    //   27: goto +154 -> 181
    //   30: bipush 9
    //   32: istore_2
    //   33: goto +210 -> 243
    //   36: getstatic 27	o/pn:ʼ	I
    //   39: bipush 85
    //   41: iadd
    //   42: istore_2
    //   43: iload_2
    //   44: sipush 128
    //   47: irem
    //   48: putstatic 25	o/pn:ॱॱ	I
    //   51: iload_2
    //   52: iconst_2
    //   53: irem
    //   54: ifeq +6 -> 60
    //   57: goto +363 -> 420
    //   60: goto +79 -> 139
    //   63: getstatic 58	o/pn:ˊ	Ljava/lang/String;
    //   66: astore 6
    //   68: new 31	java/lang/StringBuilder
    //   71: dup
    //   72: invokespecial 34	java/lang/StringBuilder:<init>	()V
    //   75: astore 7
    //   77: bipush 108
    //   79: iconst_0
    //   80: bipush 28
    //   82: invokestatic 38	o/pn:ˊ	(ICI)Ljava/lang/String;
    //   85: astore 8
    //   87: aload 8
    //   89: invokevirtual 44	java/lang/String:intern	()Ljava/lang/String;
    //   92: astore 8
    //   94: aload 7
    //   96: aload 8
    //   98: invokevirtual 48	java/lang/StringBuilder:append	(Ljava/lang/String;)Ljava/lang/StringBuilder;
    //   101: astore 7
    //   103: aload 6
    //   105: aload 7
    //   107: aload_0
    //   108: getfield 105	o/pn:ˏ	Ljava/lang/String;
    //   111: invokevirtual 48	java/lang/StringBuilder:append	(Ljava/lang/String;)Ljava/lang/StringBuilder;
    //   114: invokevirtual 56	java/lang/StringBuilder:toString	()Ljava/lang/String;
    //   117: invokestatic 88	o/pD:d	(Ljava/lang/String;Ljava/lang/String;)V
    //   120: invokestatic 94	com/insidesecure/hce/MatrixHCE$MatrixHCEFactory:getInstance	()Lcom/insidesecure/hce/MatrixHCE;
    //   123: astore 6
    //   125: aload 6
    //   127: instanceof 96
    //   130: ifeq +6 -> 136
    //   133: goto +385 -> 518
    //   136: goto +214 -> 350
    //   139: getstatic 58	o/pn:ˊ	Ljava/lang/String;
    //   142: sipush 309
    //   145: sipush 6645
    //   148: bipush 44
    //   150: invokestatic 38	o/pn:ˊ	(ICI)Ljava/lang/String;
    //   153: invokevirtual 44	java/lang/String:intern	()Ljava/lang/String;
    //   156: invokestatic 1003	o/pD:i	(Ljava/lang/String;Ljava/lang/String;)V
    //   159: getstatic 58	o/pn:ˊ	Ljava/lang/String;
    //   162: sipush 353
    //   165: sipush 26361
    //   168: bipush 24
    //   170: invokestatic 38	o/pn:ˊ	(ICI)Ljava/lang/String;
    //   173: invokevirtual 44	java/lang/String:intern	()Ljava/lang/String;
    //   176: invokestatic 1003	o/pD:i	(Ljava/lang/String;Ljava/lang/String;)V
    //   179: iconst_1
    //   180: ireturn
    //   181: iconst_4
    //   182: istore_2
    //   183: goto +60 -> 243
    //   186: astore_1
    //   187: aload_1
    //   188: athrow
    //   189: goto +25 -> 214
    //   192: getstatic 58	o/pn:ˊ	Ljava/lang/String;
    //   195: sipush 213
    //   198: iconst_0
    //   199: bipush 38
    //   201: invokestatic 38	o/pn:ˊ	(ICI)Ljava/lang/String;
    //   204: invokevirtual 44	java/lang/String:intern	()Ljava/lang/String;
    //   207: invokestatic 78	o/pD:e	(Ljava/lang/String;Ljava/lang/String;)V
    //   210: iconst_0
    //   211: ireturn
    //   212: iconst_0
    //   213: ireturn
    //   214: getstatic 27	o/pn:ʼ	I
    //   217: bipush 119
    //   219: iadd
    //   220: istore_2
    //   221: iload_2
    //   222: sipush 128
    //   225: irem
    //   226: putstatic 25	o/pn:ॱॱ	I
    //   229: iload_2
    //   230: iconst_2
    //   231: irem
    //   232: ifeq +6 -> 238
    //   235: goto +300 -> 535
    //   238: goto -26 -> 212
    //   241: iconst_0
    //   242: ireturn
    //   243: iload_2
    //   244: lookupswitch	default:+28->272, 4:+144->388, 9:+296->540
    //   272: goto +268 -> 540
    //   275: getstatic 58	o/pn:ˊ	Ljava/lang/String;
    //   278: bipush 74
    //   280: iconst_0
    //   281: bipush 34
    //   283: invokestatic 38	o/pn:ˊ	(ICI)Ljava/lang/String;
    //   286: invokevirtual 44	java/lang/String:intern	()Ljava/lang/String;
    //   289: invokestatic 88	o/pD:d	(Ljava/lang/String;Ljava/lang/String;)V
    //   292: aload_0
    //   293: getfield 105	o/pn:ˏ	Ljava/lang/String;
    //   296: invokestatic 898	com/insidesecure/hce/internal/MatrixHCENativeBridge:remainingSessionValidity	(Ljava/lang/String;)J
    //   299: lstore 4
    //   301: getstatic 58	o/pn:ˊ	Ljava/lang/String;
    //   304: new 31	java/lang/StringBuilder
    //   307: dup
    //   308: invokespecial 34	java/lang/StringBuilder:<init>	()V
    //   311: iconst_0
    //   312: sipush 20472
    //   315: bipush 27
    //   317: invokestatic 38	o/pn:ˊ	(ICI)Ljava/lang/String;
    //   320: invokevirtual 44	java/lang/String:intern	()Ljava/lang/String;
    //   323: invokevirtual 48	java/lang/StringBuilder:append	(Ljava/lang/String;)Ljava/lang/StringBuilder;
    //   326: lload 4
    //   328: invokevirtual 930	java/lang/StringBuilder:append	(J)Ljava/lang/StringBuilder;
    //   331: invokevirtual 56	java/lang/StringBuilder:toString	()Ljava/lang/String;
    //   334: invokestatic 88	o/pD:d	(Ljava/lang/String;Ljava/lang/String;)V
    //   337: lload 4
    //   339: lconst_0
    //   340: lcmp
    //   341: ifgt +6 -> 347
    //   344: goto -281 -> 63
    //   347: goto -188 -> 159
    //   350: iconst_1
    //   351: istore_2
    //   352: iload_2
    //   353: tableswitch	default:+23->376, 0:+-350->3, 1:+-164->189
    //   376: goto -373 -> 3
    //   379: aload 6
    //   381: invokevirtual 1007	o/pp:ˎ	()Ljava/lang/String;
    //   384: pop
    //   385: goto -349 -> 36
    //   388: aload 6
    //   390: checkcast 96	o/pz
    //   393: aload_0
    //   394: getfield 105	o/pn:ˏ	Ljava/lang/String;
    //   397: invokevirtual 1010	o/pz:ˎ	(Ljava/lang/String;)Lo/pp;
    //   400: astore 6
    //   402: goto +73 -> 475
    //   405: aload 6
    //   407: invokevirtual 1011	o/pp:ˊ	()V
    //   410: iload_3
    //   411: ifne +6 -> 417
    //   414: goto +200 -> 614
    //   417: goto +202 -> 619
    //   420: goto -281 -> 139
    //   423: astore_1
    //   424: getstatic 58	o/pn:ˊ	Ljava/lang/String;
    //   427: sipush 169
    //   430: ldc_w 1012
    //   433: bipush 44
    //   435: invokestatic 38	o/pn:ˊ	(ICI)Ljava/lang/String;
    //   438: invokevirtual 44	java/lang/String:intern	()Ljava/lang/String;
    //   441: invokestatic 78	o/pD:e	(Ljava/lang/String;Ljava/lang/String;)V
    //   444: iconst_0
    //   445: ireturn
    //   446: astore_1
    //   447: aload_1
    //   448: athrow
    //   449: goto -174 -> 275
    //   452: astore_1
    //   453: getstatic 58	o/pn:ˊ	Ljava/lang/String;
    //   456: sipush 251
    //   459: sipush 22263
    //   462: bipush 58
    //   464: invokestatic 38	o/pn:ˊ	(ICI)Ljava/lang/String;
    //   467: invokevirtual 44	java/lang/String:intern	()Ljava/lang/String;
    //   470: invokestatic 78	o/pD:e	(Ljava/lang/String;Ljava/lang/String;)V
    //   473: iconst_0
    //   474: ireturn
    //   475: aload 6
    //   477: invokevirtual 1014	o/pp:ॱ	()V
    //   480: aload_0
    //   481: getfield 105	o/pn:ˏ	Ljava/lang/String;
    //   484: aload_1
    //   485: invokestatic 1018	com/insidesecure/hce/internal/MatrixHCENativeBridge:requestNetworkSession	(Ljava/lang/String;Lcom/insidesecure/hce/MatrixHCENetworkOperationCallback;)Lcom/insidesecure/hce/internal/MatrixHCENetworkOperationResponse;
    //   488: astore 7
    //   490: aload_1
    //   491: aload 7
    //   493: aconst_null
    //   494: invokestatic 1022	o/pD:executePostNetworkCallback	(Lcom/insidesecure/hce/MatrixHCENetworkOperationCallback;Lcom/insidesecure/hce/internal/MatrixHCENetworkOperationResponse;Ljava/lang/Integer;)Z
    //   497: pop
    //   498: aload 7
    //   500: getfield 1026	com/insidesecure/hce/internal/MatrixHCENetworkOperationResponse:error	Lcom/insidesecure/hce/MatrixHCEError;
    //   503: getstatic 1028	com/insidesecure/hce/MatrixHCEError:SUCCESS	Lcom/insidesecure/hce/MatrixHCEError;
    //   506: if_acmpeq +6 -> 512
    //   509: goto +118 -> 627
    //   512: goto +11 -> 523
    //   515: goto +72 -> 587
    //   518: iconst_0
    //   519: istore_2
    //   520: goto -168 -> 352
    //   523: aload 6
    //   525: ldc2_w 1029
    //   528: invokevirtual 1033	o/pp:ॱ	(J)Z
    //   531: istore_3
    //   532: goto -17 -> 515
    //   535: aconst_null
    //   536: arraylength
    //   537: istore_2
    //   538: iconst_0
    //   539: ireturn
    //   540: aload 6
    //   542: checkcast 96	o/pz
    //   545: aload_0
    //   546: getfield 105	o/pn:ˏ	Ljava/lang/String;
    //   549: invokevirtual 1010	o/pz:ˎ	(Ljava/lang/String;)Lo/pp;
    //   552: astore_1
    //   553: new 159	java/lang/NullPointerException
    //   556: dup
    //   557: invokespecial 160	java/lang/NullPointerException:<init>	()V
    //   560: athrow
    //   561: iload_2
    //   562: tableswitch	default:+22->584, 0:+-183->379, 1:+-370->192
    //   584: goto -392 -> 192
    //   587: getstatic 27	o/pn:ʼ	I
    //   590: bipush 73
    //   592: iadd
    //   593: istore_2
    //   594: iload_2
    //   595: sipush 128
    //   598: irem
    //   599: putstatic 25	o/pn:ॱॱ	I
    //   602: iload_2
    //   603: iconst_2
    //   604: irem
    //   605: ifeq +6 -> 611
    //   608: goto +16 -> 624
    //   611: goto -206 -> 405
    //   614: iconst_1
    //   615: istore_2
    //   616: goto -55 -> 561
    //   619: iconst_0
    //   620: istore_2
    //   621: goto -60 -> 561
    //   624: goto -219 -> 405
    //   627: getstatic 58	o/pn:ˊ	Ljava/lang/String;
    //   630: new 31	java/lang/StringBuilder
    //   633: dup
    //   634: invokespecial 34	java/lang/StringBuilder:<init>	()V
    //   637: sipush 136
    //   640: iconst_0
    //   641: bipush 33
    //   643: invokestatic 38	o/pn:ˊ	(ICI)Ljava/lang/String;
    //   646: invokevirtual 44	java/lang/String:intern	()Ljava/lang/String;
    //   649: invokevirtual 48	java/lang/StringBuilder:append	(Ljava/lang/String;)Ljava/lang/StringBuilder;
    //   652: aload 7
    //   654: getfield 1026	com/insidesecure/hce/internal/MatrixHCENetworkOperationResponse:error	Lcom/insidesecure/hce/MatrixHCEError;
    //   657: invokevirtual 1034	com/insidesecure/hce/MatrixHCEError:toString	()Ljava/lang/String;
    //   660: invokevirtual 48	java/lang/StringBuilder:append	(Ljava/lang/String;)Ljava/lang/StringBuilder;
    //   663: invokevirtual 56	java/lang/StringBuilder:toString	()Ljava/lang/String;
    //   666: invokestatic 1003	o/pD:i	(Ljava/lang/String;Ljava/lang/String;)V
    //   669: goto -428 -> 241
    // Local variable table:
    //   start	length	slot	name	signature
    //   0	672	0	this	pn
    //   0	672	1	paramMatrixHCENetworkOperationCallback	MatrixHCENetworkOperationCallback
    //   9	612	2	i	int
    //   410	122	3	bool	boolean
    //   299	39	4	l	long
    //   66	475	6	localObject1	Object
    //   75	578	7	localObject2	Object
    //   85	12	8	str	String
    // Exception table:
    //   from	to	target	type
    //   63	77	186	java/lang/Exception
    //   77	87	186	java/lang/Exception
    //   87	94	186	java/lang/Exception
    //   94	103	186	java/lang/Exception
    //   103	125	186	java/lang/Exception
    //   523	532	423	java/lang/InterruptedException
    //   87	94	446	java/lang/Exception
    //   379	385	452	java/lang/NoSuchFieldException
  }
}
