package o;

import com.insidesecure.hce.MatrixHCEError;
import com.insidesecure.hce.MatrixHCEException;
import com.insidesecure.hce.MatrixHCENetworkData;
import com.insidesecure.hce.MatrixHCENetworkOperationCallback;
import com.insidesecure.hce.NetworkOperationPreparationInfo.NetworkOperation;

public class po
  extends pk
{
  private static int ʼ = 1;
  private static int ʽ = 0;
  private static char[] ˊ = { 80, 73, 78, 32, 110, 111, 116, 115, 117, 112, 114, 101, 100, 102, 97, 99, 121, 34, 67, 108, 105, 103, 109, 107, 81 };
  private static char ॱॱ = '\005';
  
  public po(String paramString1, String paramString2, String paramString3, String paramString4, String paramString5, long paramLong)
  {
    super(paramString1, paramString2, paramString3, paramString4, paramString5, paramLong);
  }
  
  private static String ˋ(char[] paramArrayOfChar, int paramInt, byte paramByte)
  {
    break label331;
    int k;
    byte b1 = oO.ˊ(b4, k);
    byte b5;
    byte b4 = oO.ˊ(b5, k);
    byte b3;
    b1 = oO.ˏ(b3, b1, k);
    byte b2 = oO.ˏ(b2, b4, k);
    char[] arrayOfChar2;
    int i;
    char[] arrayOfChar1;
    arrayOfChar2[i] = arrayOfChar1[b1];
    arrayOfChar2[(i + 1)] = arrayOfChar1[b2];
    for (;;)
    {
      switch (b1)
      {
      case 41: 
      default: 
        byte b6;
        int j;
        try
        {
          b1 = ʼ;
          b1 += 85;
          try
          {
            ʽ = b1 % 128;
            if (b1 % 2 != 0) {
              break label306;
            }
          }
          catch (Exception paramArrayOfChar)
          {
            throw paramArrayOfChar;
          }
          switch (i)
          {
          }
        }
        catch (Exception paramArrayOfChar)
        {
          throw paramArrayOfChar;
        }
        switch (b1)
        {
        default: 
          break;
          b1 = 1;
          break;
        case 1: 
          break;
        }
        break label724;
        for (;;)
        {
          b3 = oO.ॱ(b2, k);
          b4 = oO.ˋ(b2, k);
          b2 = oO.ॱ(b1, k);
          b5 = oO.ˋ(b1, k);
          if (b4 == b5) {
            break label460;
          }
          break;
          b2 = b3;
          b1 = b4;
          b5 = b3;
          b6 = b4;
          switch (j)
          {
          case 52: 
          default: 
            b2 = b3;
            b1 = b4;
          }
        }
        b3 = paramArrayOfChar[i];
        b4 = paramArrayOfChar[(i * 1)];
        if (b3 != b4)
        {
          break label731;
          break label503;
          for (;;)
          {
            paramInt = i - 1;
            arrayOfChar2[paramInt] = ((char)(paramArrayOfChar[paramInt] - paramByte));
            break label744;
            for (;;)
            {
              switch (b1)
              {
              default: 
                break label609;
                b1 = ʼ + 25;
                ʽ = b1 % 128;
                if (b1 % 2 != 0) {
                  break label802;
                }
                break label425;
                for (;;)
                {
                  if (i < paramInt) {
                    break label821;
                  }
                  break;
                  i = 0;
                }
                b1 = 1;
                break label159;
                i = 58;
                break label130;
                arrayOfChar2[i] = ((char)(b5 - paramByte));
                arrayOfChar2[(i + 1)] = ((char)(b6 - paramByte));
                break label724;
                b1 = 0;
              }
            }
            paramInt = ʽ + 93;
            ʼ = paramInt % 128;
            if (paramInt % 2 == 0) {
              break label661;
            }
          }
          b1 = 83;
          continue;
          arrayOfChar1 = ˊ;
          i = paramInt;
          k = ॱॱ;
          arrayOfChar2 = new char[i];
          if (i % 2 != 0) {
            break label649;
          }
          break label655;
        }
        for (;;)
        {
          if (paramInt > 1) {
            break label431;
          }
          break label738;
          b2 = paramArrayOfChar[i];
          b1 = paramArrayOfChar[(i + 1)];
          if (b2 == b1)
          {
            b5 = b2;
            b6 = b1;
            break label437;
          }
          break label199;
          for (;;)
          {
            paramInt = i;
            switch (b1)
            {
            }
            paramInt = i;
            break label532;
            b1 = ʽ + 95;
            ʼ = b1 % 128;
            if (b1 % 2 != 0) {
              break label664;
            }
            break label664;
            j = 87;
            break;
            b1 = 0;
            continue;
            b1 = 1;
          }
          break label334;
          b1 = oO.ˊ(b3, k);
          b2 = oO.ˊ(b2, k);
          b1 = oO.ˏ(b1, b4, k);
          b2 = oO.ˏ(b2, b5, k);
          arrayOfChar2[i] = arrayOfChar1[b1];
          arrayOfChar2[(i + 1)] = arrayOfChar1[b2];
          i += 2;
          break label409;
          j = 52;
          break label248;
          i = 88;
          break;
        }
      case 83: 
        label130:
        label159:
        label199:
        label248:
        label306:
        label331:
        label334:
        label379:
        label409:
        label425:
        label431:
        label437:
        label460:
        label503:
        label532:
        label609:
        label649:
        label655:
        label661:
        label664:
        label724:
        label731:
        label738:
        label744:
        return new String(arrayOfChar2);
        for (;;)
        {
          b1 = oO.ˏ(b3, b5, k);
          b2 = oO.ˏ(b2, b4, k);
          arrayOfChar2[i] = arrayOfChar1[b1];
          arrayOfChar2[(i + 1)] = arrayOfChar1[b2];
          break label379;
          label802:
          b1 = 0;
          break label159;
          if (b3 == b2) {
            break;
          }
        }
        label821:
        b1 = 41;
      }
    }
  }
  
  public void clearNetworkSession()
  {
    try
    {
      i = ʽ + 49;
      return;
    }
    catch (Exception localException1)
    {
      try
      {
        ʼ = i % 128;
        if (i % 2 == 0) {
          break label69;
        }
      }
      catch (Exception localException2)
      {
        throw localException2;
      }
      localException1 = localException1;
      throw localException1;
    }
    int i = 0;
    break label45;
    i = 11 / 0;
    return;
    for (;;)
    {
      label45:
      switch (i)
      {
      }
      return;
      label69:
      i = 1;
    }
  }
  
  public void clearPaymentKeys()
  {
    throw new MatrixHCEException(ˋ(new char[] { 19, 15, 12, 10, 15, 0, 1, 24, 4, 8, 11, 19, 21, 12, 1, 9, 8, 3, 16, 21, 8, 2, 22, 5, 4, 0, 6, 7, 2, 8, 9, 5, 5, 6, 11, 5, 12, 13, 8, 18, 10, 15, 4, 13, 202, 202, 6, 9, 1, 9, 0, 8, 18, 8, 11, 21, 6, 14, 2, 18 }, 60, (byte)103).intern() + this.ˎ + ˋ(new char[] { 139 }, 1, (byte)105).intern(), MatrixHCEError.UNSUPPORTED);
  }
  
  public byte[] getEncryptedPin(byte[] paramArrayOfByte)
  {
    for (;;)
    {
      throw new MatrixHCEException(ˋ(new char[] { 1, 2, 3, 4, 0, 9, 8, 1, 8, 9, 225, 225, 10, 15, 11, 16, 13, 2, 10, 8, 13, 0, 10, 19, 20, 10, 9, 3, 8, 1, 8, 10, 1, 8, 19, 6, 13, 1, 147 }, 39, (byte)113).intern() + this.ˎ + ˋ(new char[] { 139 }, 1, (byte)105).intern(), MatrixHCEError.UNSUPPORTED);
    }
  }
  
  public long getNetworkSessionValidity()
  {
    for (;;)
    {
      int i = 1;
      break label41;
      break;
      for (;;)
      {
        label11:
        i = ʽ + 53;
        ʼ = i % 128;
        if (i % 2 == 0) {
          break;
        }
        break;
        break label81;
        for (;;)
        {
          switch (i)
          {
          default: 
            break;
          case 0: 
            label41:
            break label11;
            i = 0;
          }
        }
        i = null.length;
      }
      try
      {
        label81:
        i = ʽ;
        i += 17;
        ʼ = i % 128;
        if (i % 2 == 0) {}
      }
      catch (Exception localException)
      {
        throw localException;
      }
    }
    return -1L;
  }
  
  public MatrixHCENetworkData openNetworkSession()
  {
    for (;;)
    {
      int i = 90;
      break label74;
      MatrixHCENetworkData localMatrixHCENetworkData;
      for (;;)
      {
        localMatrixHCENetworkData = new MatrixHCENetworkData(NetworkOperationPreparationInfo.NetworkOperation.MASTERCARD_REQUEST_SESSION, MatrixHCEError.UNSUPPORTED, null, null, null);
        break;
        i = 64;
        break label74;
        i = 41 / 0;
        return localMatrixHCENetworkData;
      }
      try
      {
        i = ʽ + 81;
        ʼ = i % 128;
        if (i % 2 == 0) {}
      }
      catch (Exception localException)
      {
        label74:
        throw localException;
      }
    }
    return localMatrixHCENetworkData;
    switch (i)
    {
    }
    return localMatrixHCENetworkData;
  }
  
  @Deprecated
  public MatrixHCENetworkData registerAccountToServer(String paramString1, String paramString2)
  {
    break label53;
    int i = ʼ + 53;
    ʽ = i % 128;
    if (i % 2 != 0) {
      return paramString1;
    }
    return paramString1;
    label53:
    for (;;)
    {
      try
      {
        paramString1 = NetworkOperationPreparationInfo.NetworkOperation.VISA_REGISTER;
      }
      catch (Exception paramString1)
      {
        try
        {
          paramString1 = new MatrixHCENetworkData(paramString1, MatrixHCEError.UNSUPPORTED, null, null, null);
        }
        catch (Exception paramString1)
        {
          throw paramString1;
        }
        paramString1 = paramString1;
        throw paramString1;
      }
    }
  }
  
  /* Error */
  public MatrixHCENetworkData registerAccountToServer(String paramString, byte[] paramArrayOfByte)
  {
    // Byte code:
    //   0: goto +53 -> 53
    //   3: astore_1
    //   4: aload_1
    //   5: athrow
    //   6: getstatic 160	com/insidesecure/hce/NetworkOperationPreparationInfo$NetworkOperation:VISA_REGISTER	Lcom/insidesecure/hce/NetworkOperationPreparationInfo$NetworkOperation;
    //   9: astore_1
    //   10: new 145	com/insidesecure/hce/MatrixHCENetworkData
    //   13: dup
    //   14: aload_1
    //   15: getstatic 129	com/insidesecure/hce/MatrixHCEError:UNSUPPORTED	Lcom/insidesecure/hce/MatrixHCEError;
    //   18: aconst_null
    //   19: aconst_null
    //   20: aconst_null
    //   21: invokespecial 154	com/insidesecure/hce/MatrixHCENetworkData:<init>	(Lcom/insidesecure/hce/NetworkOperationPreparationInfo$NetworkOperation;Lcom/insidesecure/hce/MatrixHCEError;[BLjava/lang/String;Ljava/lang/String;)V
    //   24: astore_1
    //   25: getstatic 17	o/po:ʼ	I
    //   28: bipush 103
    //   30: iadd
    //   31: istore_3
    //   32: iload_3
    //   33: sipush 128
    //   36: irem
    //   37: putstatic 15	o/po:ʽ	I
    //   40: iload_3
    //   41: iconst_2
    //   42: irem
    //   43: ifeq +6 -> 49
    //   46: goto +5 -> 51
    //   49: aload_1
    //   50: areturn
    //   51: aload_1
    //   52: areturn
    //   53: goto -47 -> 6
    //   56: astore_1
    //   57: aload_1
    //   58: athrow
    // Local variable table:
    //   start	length	slot	name	signature
    //   0	59	0	this	po
    //   0	59	1	paramString	String
    //   0	59	2	paramArrayOfByte	byte[]
    //   31	12	3	i	int
    // Exception table:
    //   from	to	target	type
    //   6	10	3	java/lang/Exception
    //   10	25	56	java/lang/Exception
  }
  
  /* Error */
  @Deprecated
  public void registerAccountToServer(String paramString1, String paramString2, MatrixHCENetworkOperationCallback paramMatrixHCENetworkOperationCallback)
  {
    // Byte code:
    //   0: goto +59 -> 59
    //   3: astore_1
    //   4: aload_1
    //   5: athrow
    //   6: astore_1
    //   7: aload_1
    //   8: athrow
    //   9: bipush 16
    //   11: istore 4
    //   13: goto +15 -> 28
    //   16: aload_3
    //   17: getstatic 166	com/insidesecure/hce/NetworkOperationPreparationInfo$NetworkOperation:MASTERCARD_REGISTER_TO_SERVER	Lcom/insidesecure/hce/NetworkOperationPreparationInfo$NetworkOperation;
    //   20: aload_0
    //   21: getfield 119	o/po:ˎ	Ljava/lang/String;
    //   24: invokestatic 170	o/po:unsupportedNetworkOperation	(Lcom/insidesecure/hce/MatrixHCENetworkOperationCallback;Lcom/insidesecure/hce/NetworkOperationPreparationInfo$NetworkOperation;Ljava/lang/String;)V
    //   27: return
    //   28: iload 4
    //   30: lookupswitch	default:+26->56, 16:+-14->16, 28:+63->93
    //   56: goto +37 -> 93
    //   59: getstatic 15	o/po:ʽ	I
    //   62: istore 4
    //   64: iload 4
    //   66: bipush 77
    //   68: iadd
    //   69: istore 4
    //   71: iload 4
    //   73: sipush 128
    //   76: irem
    //   77: putstatic 17	o/po:ʼ	I
    //   80: iload 4
    //   82: iconst_2
    //   83: irem
    //   84: ifne +6 -> 90
    //   87: goto +25 -> 112
    //   90: goto -81 -> 9
    //   93: aload_3
    //   94: getstatic 166	com/insidesecure/hce/NetworkOperationPreparationInfo$NetworkOperation:MASTERCARD_REGISTER_TO_SERVER	Lcom/insidesecure/hce/NetworkOperationPreparationInfo$NetworkOperation;
    //   97: aload_0
    //   98: getfield 119	o/po:ˎ	Ljava/lang/String;
    //   101: invokestatic 170	o/po:unsupportedNetworkOperation	(Lcom/insidesecure/hce/MatrixHCENetworkOperationCallback;Lcom/insidesecure/hce/NetworkOperationPreparationInfo$NetworkOperation;Ljava/lang/String;)V
    //   104: new 172	java/lang/NullPointerException
    //   107: dup
    //   108: invokespecial 173	java/lang/NullPointerException:<init>	()V
    //   111: athrow
    //   112: bipush 28
    //   114: istore 4
    //   116: goto -88 -> 28
    // Local variable table:
    //   start	length	slot	name	signature
    //   0	119	0	this	po
    //   0	119	1	paramString1	String
    //   0	119	2	paramString2	String
    //   0	119	3	paramMatrixHCENetworkOperationCallback	MatrixHCENetworkOperationCallback
    //   11	104	4	i	int
    // Exception table:
    //   from	to	target	type
    //   71	80	3	java/lang/Exception
    //   59	64	6	java/lang/Exception
  }
  
  public void registerAccountToServer(String paramString, byte[] paramArrayOfByte, MatrixHCENetworkOperationCallback paramMatrixHCENetworkOperationCallback)
  {
    break label40;
    unsupportedNetworkOperation(paramMatrixHCENetworkOperationCallback, NetworkOperationPreparationInfo.NetworkOperation.MASTERCARD_REGISTER_TO_SERVER, this.ˎ);
    return;
    unsupportedNetworkOperation(paramMatrixHCENetworkOperationCallback, NetworkOperationPreparationInfo.NetworkOperation.MASTERCARD_REGISTER_TO_SERVER, this.ˎ);
    int i = 37 / 0;
    return;
    for (;;)
    {
      i = 86;
      break;
      label40:
      i = ʽ + 125;
      ʼ = i % 128;
      if (i % 2 != 0) {
        break label103;
      }
    }
    for (;;)
    {
      switch (i)
      {
      }
      break;
      label103:
      i = 53;
    }
  }
  
  @Deprecated
  public MatrixHCENetworkData signIn(String paramString1, String paramString2)
  {
    int i;
    label99:
    label120:
    label128:
    pi localPi;
    for (;;)
    {
      switch (i)
      {
      case 1: 
      default: 
        if (this.ˋ == null) {
          break label282;
        }
        do
        {
          i = ʽ + 81;
          ʼ = i % 128;
          if (i % 2 == 0) {
            break label254;
          }
          for (;;)
          {
            switch (i)
            {
            default: 
              break;
            }
            try
            {
              paramString1 = NetworkOperationPreparationInfo.NetworkOperation.MAP_SIGN_IN;
              try
              {
                paramString1 = new MatrixHCENetworkData(paramString1, MatrixHCEError.UNSUPPORTED, null, null, null);
                return paramString1;
              }
              catch (Exception paramString1)
              {
                throw paramString1;
              }
              i = 0;
            }
            catch (Exception paramString1)
            {
              throw paramString1;
            }
            paramString2 = null;
            break label262;
            i = 10;
          }
          localPi = this.ˋ;
        } while (paramString2 == null);
        break label166;
        label155:
        i = 1;
        break label179;
        break label227;
        label166:
        paramString2 = paramString2.getBytes();
        break label262;
        label174:
        i = 1;
      }
    }
    for (;;)
    {
      label179:
      switch (i)
      {
      }
      break label99;
      localPi = this.ˋ;
      i = null.length;
      if (localPi != null) {
        break label155;
      }
      break label288;
      label227:
      i = ʼ + 25;
      ʽ = i % 128;
      if (i % 2 != 0) {
        break label120;
      }
      break label174;
      label254:
      i = 73 / 0;
      break label128;
      label262:
      String str = this.ˏ;
      paramString1 = localPi.ˋ(paramString1, paramString2, str);
      return paramString1;
      label282:
      i = 44;
      break;
      label288:
      i = 0;
    }
  }
  
  /* Error */
  public MatrixHCENetworkData signIn(String paramString, byte[] paramArrayOfByte)
  {
    // Byte code:
    //   0: goto +79 -> 79
    //   3: new 145	com/insidesecure/hce/MatrixHCENetworkData
    //   6: dup
    //   7: getstatic 181	com/insidesecure/hce/NetworkOperationPreparationInfo$NetworkOperation:MAP_SIGN_IN	Lcom/insidesecure/hce/NetworkOperationPreparationInfo$NetworkOperation;
    //   10: getstatic 129	com/insidesecure/hce/MatrixHCEError:UNSUPPORTED	Lcom/insidesecure/hce/MatrixHCEError;
    //   13: aconst_null
    //   14: aconst_null
    //   15: aconst_null
    //   16: invokespecial 154	com/insidesecure/hce/MatrixHCENetworkData:<init>	(Lcom/insidesecure/hce/NetworkOperationPreparationInfo$NetworkOperation;Lcom/insidesecure/hce/MatrixHCEError;[BLjava/lang/String;Ljava/lang/String;)V
    //   19: areturn
    //   20: goto +141 -> 161
    //   23: astore_1
    //   24: aload_1
    //   25: athrow
    //   26: getstatic 15	o/po:ʽ	I
    //   29: bipush 125
    //   31: iadd
    //   32: istore_3
    //   33: iload_3
    //   34: sipush 128
    //   37: irem
    //   38: putstatic 17	o/po:ʼ	I
    //   41: iload_3
    //   42: iconst_2
    //   43: irem
    //   44: ifne +6 -> 50
    //   47: goto +45 -> 92
    //   50: goto +32 -> 82
    //   53: iload_3
    //   54: tableswitch	default:+22->76, 0:+43->97, 1:+86->140
    //   76: goto +21 -> 97
    //   79: goto +34 -> 113
    //   82: iconst_0
    //   83: istore_3
    //   84: goto -31 -> 53
    //   87: iconst_0
    //   88: istore_3
    //   89: goto +89 -> 178
    //   92: iconst_1
    //   93: istore_3
    //   94: goto -41 -> 53
    //   97: aload_0
    //   98: getfield 178	o/po:ˋ	Lo/pi;
    //   101: aload_1
    //   102: aload_2
    //   103: aload_0
    //   104: getfield 187	o/po:ˏ	Ljava/lang/String;
    //   107: invokeinterface 192 4 0
    //   112: areturn
    //   113: getstatic 17	o/po:ʼ	I
    //   116: bipush 59
    //   118: iadd
    //   119: istore_3
    //   120: iload_3
    //   121: sipush 128
    //   124: irem
    //   125: putstatic 15	o/po:ʽ	I
    //   128: iload_3
    //   129: iconst_2
    //   130: irem
    //   131: ifeq +6 -> 137
    //   134: goto -114 -> 20
    //   137: goto +24 -> 161
    //   140: aload_0
    //   141: getfield 178	o/po:ˋ	Lo/pi;
    //   144: aload_1
    //   145: aload_2
    //   146: aload_0
    //   147: getfield 187	o/po:ˏ	Ljava/lang/String;
    //   150: invokeinterface 192 4 0
    //   155: astore_1
    //   156: aconst_null
    //   157: arraylength
    //   158: istore_3
    //   159: aload_1
    //   160: areturn
    //   161: aload_0
    //   162: getfield 178	o/po:ˋ	Lo/pi;
    //   165: astore 4
    //   167: aload 4
    //   169: ifnull +6 -> 175
    //   172: goto -85 -> 87
    //   175: goto +28 -> 203
    //   178: iload_3
    //   179: tableswitch	default:+21->200, 0:+-153->26, 1:+-176->3
    //   200: goto -174 -> 26
    //   203: iconst_1
    //   204: istore_3
    //   205: goto -27 -> 178
    // Local variable table:
    //   start	length	slot	name	signature
    //   0	208	0	this	po
    //   0	208	1	paramString	String
    //   0	208	2	paramArrayOfByte	byte[]
    //   32	173	3	i	int
    //   165	3	4	localPi	pi
    // Exception table:
    //   from	to	target	type
    //   161	167	23	java/lang/Exception
  }
  
  /* Error */
  @Deprecated
  public void signIn(MatrixHCENetworkOperationCallback paramMatrixHCENetworkOperationCallback, String paramString1, String paramString2)
  {
    // Byte code:
    //   0: goto +250 -> 250
    //   3: bipush 33
    //   5: istore 4
    //   7: goto +152 -> 159
    //   10: goto +42 -> 52
    //   13: aload_1
    //   14: getstatic 181	com/insidesecure/hce/NetworkOperationPreparationInfo$NetworkOperation:MAP_SIGN_IN	Lcom/insidesecure/hce/NetworkOperationPreparationInfo$NetworkOperation;
    //   17: aload_0
    //   18: getfield 119	o/po:ˎ	Ljava/lang/String;
    //   21: invokestatic 170	o/po:unsupportedNetworkOperation	(Lcom/insidesecure/hce/MatrixHCENetworkOperationCallback;Lcom/insidesecure/hce/NetworkOperationPreparationInfo$NetworkOperation;Ljava/lang/String;)V
    //   24: goto -14 -> 10
    //   27: aload_0
    //   28: getfield 178	o/po:ˋ	Lo/pi;
    //   31: astore 7
    //   33: aload_3
    //   34: ifnonnull +6 -> 40
    //   37: goto +9 -> 46
    //   40: goto +204 -> 244
    //   43: goto +189 -> 232
    //   46: iconst_1
    //   47: istore 4
    //   49: goto +37 -> 86
    //   52: return
    //   53: astore_1
    //   54: aload_1
    //   55: athrow
    //   56: getstatic 15	o/po:ʽ	I
    //   59: bipush 35
    //   61: iadd
    //   62: istore 4
    //   64: iload 4
    //   66: sipush 128
    //   69: irem
    //   70: putstatic 17	o/po:ʼ	I
    //   73: iload 4
    //   75: iconst_2
    //   76: irem
    //   77: ifne +6 -> 83
    //   80: goto +130 -> 210
    //   83: goto +154 -> 237
    //   86: aload 7
    //   88: astore 6
    //   90: aload 7
    //   92: astore 5
    //   94: iload 4
    //   96: tableswitch	default:+24->120, 0:+102->198, 1:+171->267
    //   120: aload 7
    //   122: astore 6
    //   124: goto +74 -> 198
    //   127: iload 4
    //   129: lookupswitch	default:+27->156, 32:+171->300, 81:+-102->27
    //   156: goto -129 -> 27
    //   159: iload 4
    //   161: lookupswitch	default:+27->188, 22:+-105->56, 33:+-148->13
    //   188: goto -132 -> 56
    //   191: bipush 22
    //   193: istore 4
    //   195: goto -36 -> 159
    //   198: aload_3
    //   199: invokevirtual 185	java/lang/String:getBytes	()[B
    //   202: astore_3
    //   203: aload 6
    //   205: astore 5
    //   207: goto +10 -> 217
    //   210: bipush 32
    //   212: istore 4
    //   214: goto -87 -> 127
    //   217: aload 5
    //   219: aload_1
    //   220: aload_2
    //   221: aload_3
    //   222: aload_0
    //   223: getfield 187	o/po:ˏ	Ljava/lang/String;
    //   226: invokeinterface 196 5 0
    //   231: return
    //   232: aconst_null
    //   233: astore_3
    //   234: goto -17 -> 217
    //   237: bipush 81
    //   239: istore 4
    //   241: goto -114 -> 127
    //   244: iconst_0
    //   245: istore 4
    //   247: goto -161 -> 86
    //   250: aload_0
    //   251: getfield 178	o/po:ˋ	Lo/pi;
    //   254: astore 5
    //   256: aload 5
    //   258: ifnull +6 -> 264
    //   261: goto -70 -> 191
    //   264: goto -261 -> 3
    //   267: getstatic 17	o/po:ʼ	I
    //   270: bipush 59
    //   272: iadd
    //   273: istore 4
    //   275: iload 4
    //   277: sipush 128
    //   280: irem
    //   281: putstatic 15	o/po:ʽ	I
    //   284: iload 4
    //   286: iconst_2
    //   287: irem
    //   288: ifeq +6 -> 294
    //   291: goto -248 -> 43
    //   294: goto -62 -> 232
    //   297: astore_1
    //   298: aload_1
    //   299: athrow
    //   300: aload_0
    //   301: getfield 178	o/po:ˋ	Lo/pi;
    //   304: astore_1
    //   305: new 172	java/lang/NullPointerException
    //   308: dup
    //   309: invokespecial 173	java/lang/NullPointerException:<init>	()V
    //   312: athrow
    // Local variable table:
    //   start	length	slot	name	signature
    //   0	313	0	this	po
    //   0	313	1	paramMatrixHCENetworkOperationCallback	MatrixHCENetworkOperationCallback
    //   0	313	2	paramString1	String
    //   0	313	3	paramString2	String
    //   5	283	4	i	int
    //   92	165	5	localPi1	pi
    //   88	116	6	localPi2	pi
    //   31	90	7	localPi3	pi
    // Exception table:
    //   from	to	target	type
    //   300	313	53	java/lang/Exception
    //   250	256	297	java/lang/Exception
  }
  
  /* Error */
  public void signIn(MatrixHCENetworkOperationCallback paramMatrixHCENetworkOperationCallback, String paramString, byte[] paramArrayOfByte)
  {
    // Byte code:
    //   0: goto +177 -> 177
    //   3: bipush 97
    //   5: istore 4
    //   7: goto +216 -> 223
    //   10: getstatic 15	o/po:ʽ	I
    //   13: bipush 57
    //   15: iadd
    //   16: istore 4
    //   18: iload 4
    //   20: sipush 128
    //   23: irem
    //   24: putstatic 17	o/po:ʼ	I
    //   27: iload 4
    //   29: iconst_2
    //   30: irem
    //   31: ifne +6 -> 37
    //   34: goto +109 -> 143
    //   37: goto +147 -> 184
    //   40: astore_1
    //   41: aload_1
    //   42: athrow
    //   43: getstatic 17	o/po:ʼ	I
    //   46: bipush 99
    //   48: iadd
    //   49: istore 4
    //   51: iload 4
    //   53: sipush 128
    //   56: irem
    //   57: putstatic 15	o/po:ʽ	I
    //   60: iload 4
    //   62: iconst_2
    //   63: irem
    //   64: ifeq +6 -> 70
    //   67: goto +113 -> 180
    //   70: goto +76 -> 146
    //   73: iload 4
    //   75: lookupswitch	default:+25->100, 22:+108->183, 95:+94->169
    //   100: goto +69 -> 169
    //   103: getstatic 15	o/po:ʽ	I
    //   106: istore 4
    //   108: iload 4
    //   110: iconst_5
    //   111: iadd
    //   112: istore 4
    //   114: iload 4
    //   116: sipush 128
    //   119: irem
    //   120: putstatic 17	o/po:ʼ	I
    //   123: iload 4
    //   125: iconst_2
    //   126: irem
    //   127: ifne +6 -> 133
    //   130: goto +40 -> 170
    //   133: goto +29 -> 162
    //   136: bipush 67
    //   138: istore 4
    //   140: goto +83 -> 223
    //   143: goto +41 -> 184
    //   146: aload_0
    //   147: getfield 178	o/po:ˋ	Lo/pi;
    //   150: ifnull +6 -> 156
    //   153: goto -150 -> 3
    //   156: goto -20 -> 136
    //   159: astore_1
    //   160: aload_1
    //   161: athrow
    //   162: bipush 95
    //   164: istore 4
    //   166: goto -93 -> 73
    //   169: return
    //   170: bipush 22
    //   172: istore 4
    //   174: goto -101 -> 73
    //   177: goto -134 -> 43
    //   180: goto -34 -> 146
    //   183: return
    //   184: aload_0
    //   185: getfield 178	o/po:ˋ	Lo/pi;
    //   188: astore 5
    //   190: aload_0
    //   191: getfield 187	o/po:ˏ	Ljava/lang/String;
    //   194: astore 6
    //   196: aload 5
    //   198: aload_1
    //   199: aload_2
    //   200: aload_3
    //   201: aload 6
    //   203: invokeinterface 196 5 0
    //   208: goto -105 -> 103
    //   211: aload_1
    //   212: getstatic 181	com/insidesecure/hce/NetworkOperationPreparationInfo$NetworkOperation:MAP_SIGN_IN	Lcom/insidesecure/hce/NetworkOperationPreparationInfo$NetworkOperation;
    //   215: aload_0
    //   216: getfield 119	o/po:ˎ	Ljava/lang/String;
    //   219: invokestatic 170	o/po:unsupportedNetworkOperation	(Lcom/insidesecure/hce/MatrixHCENetworkOperationCallback;Lcom/insidesecure/hce/NetworkOperationPreparationInfo$NetworkOperation;Ljava/lang/String;)V
    //   222: return
    //   223: iload 4
    //   225: lookupswitch	default:+27->252, 67:+-14->211, 97:+-215->10
    //   252: goto -242 -> 10
    // Local variable table:
    //   start	length	slot	name	signature
    //   0	255	0	this	po
    //   0	255	1	paramMatrixHCENetworkOperationCallback	MatrixHCENetworkOperationCallback
    //   0	255	2	paramString	String
    //   0	255	3	paramArrayOfByte	byte[]
    //   5	219	4	i	int
    //   188	9	5	localPi	pi
    //   194	8	6	str	String
    // Exception table:
    //   from	to	target	type
    //   190	196	40	java/lang/Exception
    //   103	108	159	java/lang/Exception
    //   114	123	159	java/lang/Exception
    //   184	190	159	java/lang/Exception
    //   190	196	159	java/lang/Exception
    //   196	208	159	java/lang/Exception
  }
}
