package o;

import com.insidesecure.hce.MatrixHCENetworkConfiguration;

public class pw
  implements MatrixHCENetworkConfiguration
{
  private static int ʽ;
  private static int ˏॱ;
  private static final String ॱ;
  private static char[] ᐝ;
  private String ʻ = null;
  private String ʼ = null;
  private long ˊ = 0L;
  private String ˋ = null;
  private String ˎ = null;
  private String ˏ = null;
  private String ॱॱ = null;
  
  static
  {
    break label35;
    int i = 1;
    break label9;
    return;
    for (;;)
    {
      switch (i)
      {
      case 0: 
      default: 
        break label238;
        ʽ = 0;
        ˏॱ = 1;
        ॱ();
        ॱ = ॱ(new int[] { 35, 19, 0, 11 }, new byte[] { 0, 0, 1, 0, 1, 0, 1, 1, 0, 1, 0, 1, 1, 1, 1, 0, 0, 1, 1 }, true).intern() + pw.class.getSimpleName();
        i = ʽ + 63;
        ˏॱ = i % 128;
        if (i % 2 == 0) {
          break;
        }
        break;
      case 1: 
        label9:
        label35:
        label238:
        i = null.length;
        return;
        i = 0;
      }
    }
  }
  
  public pw() {}
  
  private static String ॱ(int[] paramArrayOfInt, byte[] paramArrayOfByte, boolean paramBoolean)
  {
    break label605;
    int i = 1;
    break label541;
    int i1 = ˏॱ + 99;
    ʽ = i1 % 128;
    label38:
    label44:
    int j;
    if (i1 % 2 == 0)
    {
      break label454;
      i = 67;
      break label263;
      j = 0;
      break label390;
    }
    label77:
    label108:
    label137:
    label164:
    label240:
    label257:
    label263:
    label295:
    label331:
    label339:
    label390:
    label422:
    label433:
    label444:
    label454:
    label471:
    label522:
    label539:
    label541:
    label575:
    label581:
    label602:
    label603:
    label605:
    for (;;)
    {
      i = ˏॱ + 33;
      ʽ = i % 128;
      int m;
      Object localObject;
      char[] arrayOfChar;
      if (i % 2 == 0)
      {
        break label339;
        if (m > 0) {
          break label433;
        }
        break label38;
        localObject[j] = ((char)((arrayOfChar[j] >> '\000' >> 0) + i));
        break label471;
      }
      try
      {
        i = ˏॱ;
        i += 89;
        ʽ = i % 128;
        int k;
        if (i % 2 == 0)
        {
          break label331;
          if (i < k) {
            break label575;
          }
          break label44;
          return new String((char[])localObject);
          i = 0;
          break label541;
          j = ˏॱ + 95;
          ʽ = j % 128;
          if (j % 2 == 0) {
            break label522;
          }
        }
        for (;;)
        {
          paramArrayOfByte = new char[k];
          System.arraycopy(localObject, 0, paramArrayOfByte, 0, k);
          int n;
          System.arraycopy(paramArrayOfByte, 0, localObject, k - n, n);
          System.arraycopy(paramArrayOfByte, n, localObject, 0, k - n);
          break label444;
          break label137;
          localObject = new char[k];
          i = 0;
          j = 0;
          break label295;
          localObject = paramArrayOfByte;
          break label77;
          switch (i)
          {
          }
          break label108;
          if (j >= k)
          {
            break label602;
            for (;;)
            {
              localObject[i] = ((char)(localObject[i] - paramArrayOfInt[2]));
              i += 1;
              break label240;
              break label339;
              i = 0;
              break label137;
              break label522;
              i = paramArrayOfInt[0];
              k = paramArrayOfInt[1];
              m = paramArrayOfInt[2];
              n = paramArrayOfInt[3];
              try
              {
                localObject = ᐝ;
                arrayOfChar = new char[k];
                System.arraycopy(localObject, i, arrayOfChar, 0, k);
                if (paramArrayOfByte != null) {
                  break;
                }
              }
              catch (Exception paramArrayOfInt)
              {
                throw paramArrayOfInt;
              }
              switch (j)
              {
              }
            }
          }
          for (;;)
          {
            if (n > 0) {
              break label603;
            }
            break label444;
            i = 97;
            break label263;
            i = 0;
            break label137;
            if (!paramBoolean)
            {
              break label77;
              localObject[j] = ((char)((arrayOfChar[j] << '\001') + 1 - i));
            }
            for (;;)
            {
              i = localObject[j];
              j += 1;
              break label295;
              for (;;)
              {
                if (i < k) {
                  break label539;
                }
                break label257;
                paramArrayOfByte = new char[k];
                i = 0;
                continue;
                if (paramArrayOfByte[j] == 1) {
                  break;
                }
                break label581;
                paramArrayOfByte[i] = localObject[(k - i - 1)];
                i += 1;
              }
              break label164;
              localObject = arrayOfChar;
              switch (i)
              {
              }
              localObject = arrayOfChar;
              break label422;
              j = 1;
              break label390;
              localObject[j] = ((char)((arrayOfChar[j] << '\001') - i));
            }
          }
        }
      }
      catch (Exception paramArrayOfInt)
      {
        throw paramArrayOfInt;
      }
    }
  }
  
  static void ॱ()
  {
    ᐝ = new char[] { 46, 115, 138, 136, 136, 110, 69, 81, 116, 131, 140, 133, 131, 97, 82, 118, 131, 129, 130, 138, 140, 98, 56, 92, 134, 97, 92, 131, 138, 131, 126, 130, 126, 103, 69, 53, 76, 57, 68, 69, 96, 112, 109, 115, 106, 87, 61, 75, 108, 104, 71, 71, 107, 107 };
  }
  
  public String getCaCertificate()
  {
    break label47;
    int i;
    String str;
    for (;;)
    {
      i = null.length;
      return str;
      switch (i)
      {
      }
    }
    for (;;)
    {
      label39:
      str = this.ॱॱ;
      break label58;
      label47:
      break label94;
      return str;
      for (;;)
      {
        i = 45;
        break;
        label58:
        i = ˏॱ + 41;
        ʽ = i % 128;
        if (i % 2 != 0) {
          break label88;
        }
      }
      label88:
      label94:
      do
      {
        break label39;
        i = 74;
        break;
        i = ˏॱ + 99;
        ʽ = i % 128;
      } while (i % 2 != 0);
    }
  }
  
  public String getInitData()
  {
    break label33;
    break label36;
    int i;
    label33:
    for (;;)
    {
      i = ʽ + 41;
      ˏॱ = i % 128;
      if (i % 2 == 0) {
        break;
      }
      break;
    }
    try
    {
      label36:
      String str = this.ʻ;
      i = ˏॱ + 73;
      ʽ = i % 128;
      if (i % 2 != 0) {
        return str;
      }
      return str;
    }
    catch (Exception localException)
    {
      throw localException;
    }
  }
  
  public String getRemoteNotificationServerId()
  {
    label34:
    for (int i = 1;; i = 0) {
      switch (i)
      {
      default: 
        break label88;
        break label138;
      }
    }
    for (;;)
    {
      try
      {
        i = ˏॱ;
        i += 97;
      }
      catch (Exception localException1)
      {
        String str1;
        label88:
        throw localException1;
      }
      try
      {
        ʽ = i % 128;
        if (i % 2 != 0) {
          break label34;
        }
      }
      catch (Exception localException2)
      {
        throw localException2;
      }
      i = 1;
      continue;
      str1 = this.ˏ;
      continue;
      return str1;
      i = 0;
      continue;
      i = null.length;
      return str1;
      switch (i)
      {
      case 1: 
      default: 
        break;
      case 0: 
        String str2 = this.ˏ;
        throw new NullPointerException();
        label138:
        i = ˏॱ + 77;
        ʽ = i % 128;
        if (i % 2 != 0) {}
        break;
      }
    }
  }
  
  public String getServerPublicKey()
  {
    break label53;
    int i = 1;
    break label13;
    return this.ʼ;
    for (;;)
    {
      label13:
      switch (i)
      {
      }
      try
      {
        String str = this.ʼ;
        throw new NullPointerException();
      }
      catch (Exception localException)
      {
        label53:
        throw localException;
      }
      i = ˏॱ + 39;
      ʽ = i % 128;
      if (i % 2 != 0) {
        break;
      }
      i = 73;
    }
  }
  
  public long getServerTimeout()
  {
    for (;;)
    {
      int i = ʽ + 33;
      ˏॱ = i % 128;
      Object localObject;
      if (i % 2 != 0) {
        return localObject;
      }
      for (;;)
      {
        i = ʽ + 45;
        ˏॱ = i % 128;
        if (i % 2 == 0) {
          break;
        }
        break;
        return localObject;
      }
      long l = this.ˊ;
    }
  }
  
  public String getServerUrl()
  {
    int i = ˏॱ + 121;
    ʽ = i % 128;
    if (i % 2 == 0) {
      break label27;
    }
    label27:
    String str = this.ˋ;
    i = ˏॱ + 97;
    ʽ = i % 128;
    if (i % 2 == 0) {
      return str;
    }
    return str;
  }
  
  /* Error */
  public String getSslConfig()
  {
    // Byte code:
    //   0: goto +123 -> 123
    //   3: aload_0
    //   4: getfield 65	o/pw:ˎ	Ljava/lang/String;
    //   7: astore_2
    //   8: goto +81 -> 89
    //   11: getstatic 27	o/pw:ˏॱ	I
    //   14: bipush 53
    //   16: iadd
    //   17: istore_1
    //   18: iload_1
    //   19: sipush 128
    //   22: irem
    //   23: putstatic 25	o/pw:ʽ	I
    //   26: iload_1
    //   27: iconst_2
    //   28: irem
    //   29: ifeq +6 -> 35
    //   32: goto +51 -> 83
    //   35: goto +79 -> 114
    //   38: iload_1
    //   39: lookupswitch	default:+25->64, 38:+-36->3, 44:+31->70
    //   64: goto -61 -> 3
    //   67: astore_2
    //   68: aload_2
    //   69: athrow
    //   70: aload_0
    //   71: getfield 65	o/pw:ˎ	Ljava/lang/String;
    //   74: astore_2
    //   75: new 130	java/lang/NullPointerException
    //   78: dup
    //   79: invokespecial 131	java/lang/NullPointerException:<init>	()V
    //   82: athrow
    //   83: bipush 44
    //   85: istore_1
    //   86: goto -48 -> 38
    //   89: getstatic 27	o/pw:ˏॱ	I
    //   92: bipush 95
    //   94: iadd
    //   95: istore_1
    //   96: iload_1
    //   97: sipush 128
    //   100: irem
    //   101: putstatic 25	o/pw:ʽ	I
    //   104: iload_1
    //   105: iconst_2
    //   106: irem
    //   107: ifeq +5 -> 112
    //   110: aload_2
    //   111: areturn
    //   112: aload_2
    //   113: areturn
    //   114: bipush 38
    //   116: istore_1
    //   117: goto -79 -> 38
    //   120: astore_2
    //   121: aload_2
    //   122: athrow
    //   123: goto -112 -> 11
    // Local variable table:
    //   start	length	slot	name	signature
    //   0	126	0	this	pw
    //   17	100	1	i	int
    //   7	1	2	str1	String
    //   67	2	2	localException1	Exception
    //   74	39	2	str2	String
    //   120	2	2	localException2	Exception
    // Exception table:
    //   from	to	target	type
    //   96	104	67	java/lang/Exception
    //   89	96	120	java/lang/Exception
    //   96	104	120	java/lang/Exception
  }
  
  public void setCaCertificate(String paramString)
  {
    break label112;
    int i;
    try
    {
      i = ˏॱ;
      i += 25;
      try
      {
        ʽ = i % 128;
        if (i % 2 != 0) {
          break label38;
        }
      }
      catch (Exception paramString)
      {
        throw paramString;
      }
      i = 79;
    }
    catch (Exception paramString)
    {
      throw paramString;
    }
    for (;;)
    {
      label38:
      i = ʽ;
      i += 113;
      ˏॱ = i % 128;
      if (i % 2 != 0) {
        return;
      }
      return;
      i = 92;
      switch (i)
      {
      case 92: 
      default: 
        this.ॱॱ = paramString;
        break;
      case 79: 
        label112:
        this.ॱॱ = paramString;
        i = null.length;
      }
    }
  }
  
  public void setInitData(String paramString)
  {
    do
    {
      i = 77;
      break label92;
      break;
      throw new NullPointerException();
      i = ˏॱ + 21;
      ʽ = i % 128;
    } while (i % 2 != 0);
    break label83;
    int i = ʽ + 31;
    ˏॱ = i % 128;
    if (i % 2 != 0)
    {
      break label75;
      return;
    }
    for (;;)
    {
      label75:
      this.ʻ = paramString;
      break;
      label83:
      i = 80;
      break label92;
    }
    label92:
    switch (i)
    {
    }
  }
  
  /* Error */
  public void setRemoteNotificationServerId(String paramString)
  {
    // Byte code:
    //   0: goto +9 -> 9
    //   3: bipush 27
    //   5: istore_2
    //   6: goto +6 -> 12
    //   9: goto +60 -> 69
    //   12: iload_2
    //   13: lookupswitch	default:+27->40, 27:+45->58, 29:+30->43
    //   40: goto +3 -> 43
    //   43: aload_0
    //   44: aload_1
    //   45: putfield 69	o/pw:ˏ	Ljava/lang/String;
    //   48: return
    //   49: astore_1
    //   50: aload_1
    //   51: athrow
    //   52: bipush 29
    //   54: istore_2
    //   55: goto -43 -> 12
    //   58: aload_0
    //   59: aload_1
    //   60: putfield 69	o/pw:ˏ	Ljava/lang/String;
    //   63: bipush 45
    //   65: iconst_0
    //   66: idiv
    //   67: istore_2
    //   68: return
    //   69: getstatic 25	o/pw:ʽ	I
    //   72: bipush 101
    //   74: iadd
    //   75: istore_2
    //   76: iload_2
    //   77: sipush 128
    //   80: irem
    //   81: putstatic 27	o/pw:ˏॱ	I
    //   84: iload_2
    //   85: iconst_2
    //   86: irem
    //   87: ifne +6 -> 93
    //   90: goto -87 -> 3
    //   93: goto -41 -> 52
    // Local variable table:
    //   start	length	slot	name	signature
    //   0	96	0	this	pw
    //   0	96	1	paramString	String
    //   5	82	2	i	int
    // Exception table:
    //   from	to	target	type
    //   58	63	49	java/lang/Exception
  }
  
  public void setServerPublicKey(String paramString)
  {
    break label66;
    this.ʼ = paramString;
    int i = null.length;
    break label36;
    i = 1;
    break label119;
    for (;;)
    {
      i = 0;
      break label119;
      this.ʼ = paramString;
      break label36;
      label32:
      i = null.length;
      return;
      label36:
      i = ʽ + 51;
      ˏॱ = i % 128;
      if (i % 2 == 0) {
        break label147;
      }
      i = 1;
      break label93;
      return;
      label66:
      i = ˏॱ + 121;
      ʽ = i % 128;
      if (i % 2 != 0) {
        break;
      }
    }
    for (;;)
    {
      label93:
      switch (i)
      {
      }
      break label32;
      label119:
      switch (i)
      {
      }
      break;
      label147:
      i = 0;
    }
  }
  
  /* Error */
  public void setServerTimeout(long paramLong)
  {
    // Byte code:
    //   0: goto +47 -> 47
    //   3: return
    //   4: getstatic 27	o/pw:ˏॱ	I
    //   7: bipush 113
    //   9: iadd
    //   10: istore_3
    //   11: iload_3
    //   12: sipush 128
    //   15: irem
    //   16: putstatic 25	o/pw:ʽ	I
    //   19: iload_3
    //   20: iconst_2
    //   21: irem
    //   22: ifeq +6 -> 28
    //   25: goto -22 -> 3
    //   28: return
    //   29: astore 4
    //   31: aload 4
    //   33: athrow
    //   34: astore 4
    //   36: aload 4
    //   38: athrow
    //   39: aload_0
    //   40: lload_1
    //   41: putfield 67	o/pw:ˊ	J
    //   44: goto -40 -> 4
    //   47: getstatic 27	o/pw:ˏॱ	I
    //   50: bipush 77
    //   52: iadd
    //   53: istore_3
    //   54: iload_3
    //   55: sipush 128
    //   58: irem
    //   59: putstatic 25	o/pw:ʽ	I
    //   62: iload_3
    //   63: iconst_2
    //   64: irem
    //   65: ifeq +6 -> 71
    //   68: goto -29 -> 39
    //   71: goto -32 -> 39
    // Local variable table:
    //   start	length	slot	name	signature
    //   0	74	0	this	pw
    //   0	74	1	paramLong	long
    //   10	55	3	i	int
    //   29	3	4	localException1	Exception
    //   34	3	4	localException2	Exception
    // Exception table:
    //   from	to	target	type
    //   54	62	29	java/lang/Exception
    //   4	11	34	java/lang/Exception
    //   11	19	34	java/lang/Exception
    //   47	54	34	java/lang/Exception
    //   54	62	34	java/lang/Exception
  }
  
  public void setServerUrl(String paramString)
  {
    break label95;
    try
    {
      this.ˋ = paramString;
    }
    catch (Exception paramString)
    {
      throw paramString;
    }
    int i = 0;
    break label68;
    i = 1;
    break label133;
    return;
    label22:
    i = 0;
    break label133;
    label27:
    i = 1;
    break label68;
    label35:
    i = 79 / 0;
    return;
    label68:
    label95:
    for (;;)
    {
      i = ˏॱ + 9;
      ʽ = i % 128;
      if (i % 2 != 0) {
        break label22;
      }
      break;
      switch (i)
      {
      }
      break label35;
    }
    for (;;)
    {
      this.ˋ = paramString;
      i = null.length;
      i = ˏॱ + 13;
      ʽ = i % 128;
      if (i % 2 != 0) {
        break;
      }
      break label27;
      label133:
      switch (i)
      {
      }
    }
  }
  
  public void setSslConfig(String paramString)
  {
    break label84;
    int i = 0;
    break label24;
    label8:
    i = 1;
    break label24;
    this.ˎ = paramString;
    i = 65 / 0;
    return;
    switch (i)
    {
    case 0: 
    default: 
      label24:
      break;
    }
    label84:
    for (;;)
    {
      i = ʽ + 35;
      ˏॱ = i % 128;
      if (i % 2 == 0) {
        break;
      }
      break label8;
      this.ˎ = paramString;
      return;
    }
  }
  
  /* Error */
  public boolean ˎ()
  {
    // Byte code:
    //   0: goto +308 -> 308
    //   3: new 130	java/lang/NullPointerException
    //   6: dup
    //   7: invokespecial 131	java/lang/NullPointerException:<init>	()V
    //   10: athrow
    //   11: getstatic 59	o/pw:ॱ	Ljava/lang/String;
    //   14: astore_2
    //   15: new 31	java/lang/StringBuilder
    //   18: dup
    //   19: invokespecial 34	java/lang/StringBuilder:<init>	()V
    //   22: astore_3
    //   23: iconst_4
    //   24: newarray int
    //   26: dup
    //   27: iconst_0
    //   28: iconst_0
    //   29: iastore
    //   30: dup
    //   31: iconst_1
    //   32: bipush 35
    //   34: iastore
    //   35: dup
    //   36: iconst_2
    //   37: bipush 24
    //   39: iastore
    //   40: dup
    //   41: iconst_3
    //   42: iconst_0
    //   43: iastore
    //   44: bipush 35
    //   46: newarray byte
    //   48: dup
    //   49: iconst_0
    //   50: ldc 36
    //   52: bastore
    //   53: dup
    //   54: iconst_1
    //   55: ldc 36
    //   57: bastore
    //   58: dup
    //   59: iconst_2
    //   60: ldc 35
    //   62: bastore
    //   63: dup
    //   64: iconst_3
    //   65: ldc 36
    //   67: bastore
    //   68: dup
    //   69: iconst_4
    //   70: ldc 36
    //   72: bastore
    //   73: dup
    //   74: iconst_5
    //   75: ldc 35
    //   77: bastore
    //   78: dup
    //   79: bipush 6
    //   81: ldc 35
    //   83: bastore
    //   84: dup
    //   85: bipush 7
    //   87: ldc 36
    //   89: bastore
    //   90: dup
    //   91: bipush 8
    //   93: ldc 35
    //   95: bastore
    //   96: dup
    //   97: bipush 9
    //   99: ldc 36
    //   101: bastore
    //   102: dup
    //   103: bipush 10
    //   105: ldc 35
    //   107: bastore
    //   108: dup
    //   109: bipush 11
    //   111: ldc 36
    //   113: bastore
    //   114: dup
    //   115: bipush 12
    //   117: ldc 36
    //   119: bastore
    //   120: dup
    //   121: bipush 13
    //   123: ldc 35
    //   125: bastore
    //   126: dup
    //   127: bipush 14
    //   129: ldc 35
    //   131: bastore
    //   132: dup
    //   133: bipush 15
    //   135: ldc 36
    //   137: bastore
    //   138: dup
    //   139: bipush 16
    //   141: ldc 35
    //   143: bastore
    //   144: dup
    //   145: bipush 17
    //   147: ldc 35
    //   149: bastore
    //   150: dup
    //   151: bipush 18
    //   153: ldc 35
    //   155: bastore
    //   156: dup
    //   157: bipush 19
    //   159: ldc 35
    //   161: bastore
    //   162: dup
    //   163: bipush 20
    //   165: ldc 36
    //   167: bastore
    //   168: dup
    //   169: bipush 21
    //   171: ldc 35
    //   173: bastore
    //   174: dup
    //   175: bipush 22
    //   177: ldc 35
    //   179: bastore
    //   180: dup
    //   181: bipush 23
    //   183: ldc 36
    //   185: bastore
    //   186: dup
    //   187: bipush 24
    //   189: ldc 35
    //   191: bastore
    //   192: dup
    //   193: bipush 25
    //   195: ldc 36
    //   197: bastore
    //   198: dup
    //   199: bipush 26
    //   201: ldc 36
    //   203: bastore
    //   204: dup
    //   205: bipush 27
    //   207: ldc 36
    //   209: bastore
    //   210: dup
    //   211: bipush 28
    //   213: ldc 35
    //   215: bastore
    //   216: dup
    //   217: bipush 29
    //   219: ldc 36
    //   221: bastore
    //   222: dup
    //   223: bipush 30
    //   225: ldc 36
    //   227: bastore
    //   228: dup
    //   229: bipush 31
    //   231: ldc 36
    //   233: bastore
    //   234: dup
    //   235: bipush 32
    //   237: ldc 36
    //   239: bastore
    //   240: dup
    //   241: bipush 33
    //   243: ldc 35
    //   245: bastore
    //   246: dup
    //   247: bipush 34
    //   249: ldc 35
    //   251: bastore
    //   252: iconst_0
    //   253: invokestatic 39	o/pw:ॱ	([I[BZ)Ljava/lang/String;
    //   256: astore 4
    //   258: aload 4
    //   260: invokevirtual 45	java/lang/String:intern	()Ljava/lang/String;
    //   263: astore 4
    //   265: aload_2
    //   266: aload_3
    //   267: aload 4
    //   269: invokevirtual 49	java/lang/StringBuilder:append	(Ljava/lang/String;)Ljava/lang/StringBuilder;
    //   272: aload_0
    //   273: getfield 67	o/pw:ˊ	J
    //   276: invokevirtual 149	java/lang/StringBuilder:append	(J)Ljava/lang/StringBuilder;
    //   279: invokevirtual 57	java/lang/StringBuilder:toString	()Ljava/lang/String;
    //   282: invokestatic 155	o/pD:e	(Ljava/lang/String;Ljava/lang/String;)V
    //   285: iconst_0
    //   286: ireturn
    //   287: goto +56 -> 343
    //   290: astore_2
    //   291: aload_2
    //   292: athrow
    //   293: aload_0
    //   294: getfield 67	o/pw:ˊ	J
    //   297: lconst_0
    //   298: lcmp
    //   299: ifge +6 -> 305
    //   302: goto -291 -> 11
    //   305: goto -18 -> 287
    //   308: goto +5 -> 313
    //   311: iconst_1
    //   312: ireturn
    //   313: getstatic 27	o/pw:ˏॱ	I
    //   316: bipush 77
    //   318: iadd
    //   319: istore_1
    //   320: iload_1
    //   321: sipush 128
    //   324: irem
    //   325: putstatic 25	o/pw:ʽ	I
    //   328: iload_1
    //   329: iconst_2
    //   330: irem
    //   331: ifeq +6 -> 337
    //   334: goto +66 -> 400
    //   337: goto -44 -> 293
    //   340: astore_2
    //   341: aload_2
    //   342: athrow
    //   343: getstatic 25	o/pw:ʽ	I
    //   346: bipush 119
    //   348: iadd
    //   349: istore_1
    //   350: iload_1
    //   351: sipush 128
    //   354: irem
    //   355: putstatic 27	o/pw:ˏॱ	I
    //   358: iload_1
    //   359: iconst_2
    //   360: irem
    //   361: ifne +6 -> 367
    //   364: goto +39 -> 403
    //   367: goto +28 -> 395
    //   370: iload_1
    //   371: tableswitch	default:+21->392, 0:+-60->311, 1:+-368->3
    //   392: goto -81 -> 311
    //   395: iconst_0
    //   396: istore_1
    //   397: goto -27 -> 370
    //   400: goto -107 -> 293
    //   403: iconst_1
    //   404: istore_1
    //   405: goto -35 -> 370
    // Exception table:
    //   from	to	target	type
    //   11	23	340	java/lang/Exception
    //   23	258	340	java/lang/Exception
    //   258	265	340	java/lang/Exception
    //   265	285	340	java/lang/Exception
  }
}
