package o;

public final class R
{
  private static long ʻ;
  public static final iF ˋ = new iF(null);
  private static char[] ˏ;
  private static int ॱॱ;
  private static int ᐝ = 0;
  public byte[] ˊ;
  public byte[] ˎ;
  public byte[] ॱ;
  
  static
  {
    ॱॱ = 1;
    ˎ();
    try
    {
      int i = ॱॱ + 81;
      try
      {
        ᐝ = i % 128;
        if (i % 2 == 0) {
          return;
        }
      }
      catch (Exception localException1)
      {
        throw localException1;
      }
      return;
    }
    catch (Exception localException2)
    {
      throw localException2;
    }
  }
  
  public R() {}
  
  /* Error */
  public R(String paramString)
  {
    // Byte code:
    //   0: goto +158 -> 158
    //   3: new 42	o/uH
    //   6: dup
    //   7: iconst_0
    //   8: sipush 208
    //   11: bipush 60
    //   13: invokestatic 45	o/R:ˋ	(CII)Ljava/lang/String;
    //   16: invokevirtual 51	java/lang/String:intern	()Ljava/lang/String;
    //   19: invokespecial 53	o/uH:<init>	(Ljava/lang/String;)V
    //   22: athrow
    //   23: iload_2
    //   24: tableswitch	default:+24->48, 0:+233->257, 1:+531->555
    //   48: goto +209 -> 257
    //   51: goto +463 -> 514
    //   54: new 55	java/lang/IllegalArgumentException
    //   57: dup
    //   58: ldc 56
    //   60: sipush 320
    //   63: bipush 30
    //   65: invokestatic 45	o/R:ˋ	(CII)Ljava/lang/String;
    //   68: invokevirtual 51	java/lang/String:intern	()Ljava/lang/String;
    //   71: invokespecial 57	java/lang/IllegalArgumentException:<init>	(Ljava/lang/String;)V
    //   74: checkcast 59	java/lang/Throwable
    //   77: athrow
    //   78: astore_1
    //   79: aload_1
    //   80: athrow
    //   81: iload_2
    //   82: lookupswitch	default:+26->108, 23:+400->482, 92:+71->153
    //   108: goto +374 -> 482
    //   111: new 42	o/uH
    //   114: dup
    //   115: ldc 60
    //   117: sipush 268
    //   120: bipush 52
    //   122: invokestatic 45	o/R:ˋ	(CII)Ljava/lang/String;
    //   125: invokevirtual 51	java/lang/String:intern	()Ljava/lang/String;
    //   128: invokespecial 53	o/uH:<init>	(Ljava/lang/String;)V
    //   131: athrow
    //   132: aload_1
    //   133: checkcast 62	java/util/Collection
    //   136: astore_1
    //   137: aload_1
    //   138: ifnonnull +6 -> 144
    //   141: goto -138 -> 3
    //   144: goto +385 -> 529
    //   147: goto +152 -> 299
    //   150: astore_1
    //   151: aload_1
    //   152: athrow
    //   153: iconst_0
    //   154: istore_2
    //   155: goto +317 -> 472
    //   158: aload_1
    //   159: iconst_0
    //   160: sipush 186
    //   163: bipush 21
    //   165: invokestatic 45	o/R:ˋ	(CII)Ljava/lang/String;
    //   168: invokevirtual 51	java/lang/String:intern	()Ljava/lang/String;
    //   171: invokestatic 67	o/vq:ˎ	(Ljava/lang/Object;Ljava/lang/String;)V
    //   174: aload_0
    //   175: invokespecial 68	o/R:<init>	()V
    //   178: aload_1
    //   179: checkcast 70	java/lang/CharSequence
    //   182: astore_1
    //   183: new 72	o/vR
    //   186: dup
    //   187: ldc 73
    //   189: sipush 207
    //   192: iconst_1
    //   193: invokestatic 45	o/R:ˋ	(CII)Ljava/lang/String;
    //   196: invokevirtual 51	java/lang/String:intern	()Ljava/lang/String;
    //   199: invokespecial 74	o/vR:<init>	(Ljava/lang/String;)V
    //   202: aload_1
    //   203: iconst_0
    //   204: invokevirtual 77	o/vR:ॱ	(Ljava/lang/CharSequence;I)Ljava/util/List;
    //   207: astore_1
    //   208: aload_1
    //   209: invokeinterface 83 1 0
    //   214: ifne +6 -> 220
    //   217: goto +85 -> 302
    //   220: goto +37 -> 257
    //   223: iload_2
    //   224: tableswitch	default:+24->248, 0:+-173->51, 1:+263->487
    //   248: goto +239 -> 487
    //   251: bipush 23
    //   253: istore_2
    //   254: goto -173 -> 81
    //   257: invokestatic 88	o/uQ:ॱ	()Ljava/util/List;
    //   260: astore_1
    //   261: goto -129 -> 132
    //   264: bipush 92
    //   266: istore_2
    //   267: goto -186 -> 81
    //   270: iconst_1
    //   271: istore_2
    //   272: goto -249 -> 23
    //   275: aload_1
    //   276: checkcast 90	java/lang/Iterable
    //   279: aload_3
    //   280: invokeinterface 96 1 0
    //   285: iconst_1
    //   286: iadd
    //   287: invokestatic 99	o/uQ:ˊ	(Ljava/lang/Iterable;I)Ljava/util/List;
    //   290: astore_1
    //   291: goto +55 -> 346
    //   294: iconst_0
    //   295: istore_2
    //   296: goto -73 -> 223
    //   299: goto -167 -> 132
    //   302: aload_1
    //   303: aload_1
    //   304: invokeinterface 102 1 0
    //   309: invokeinterface 106 2 0
    //   314: astore_3
    //   315: goto +199 -> 514
    //   318: aload_1
    //   319: checkcast 108	[Ljava/lang/String;
    //   322: astore_1
    //   323: aload_1
    //   324: checkcast 110	[Ljava/lang/Object;
    //   327: arraylength
    //   328: iconst_3
    //   329: if_icmpeq +6 -> 335
    //   332: goto -278 -> 54
    //   335: goto +38 -> 373
    //   338: iconst_1
    //   339: istore_2
    //   340: goto -117 -> 223
    //   343: goto -68 -> 275
    //   346: getstatic 28	o/R:ॱॱ	I
    //   349: bipush 77
    //   351: iadd
    //   352: istore_2
    //   353: iload_2
    //   354: sipush 128
    //   357: irem
    //   358: putstatic 26	o/R:ᐝ	I
    //   361: iload_2
    //   362: iconst_2
    //   363: irem
    //   364: ifeq +6 -> 370
    //   367: goto -220 -> 147
    //   370: goto -71 -> 299
    //   373: aload_1
    //   374: iconst_0
    //   375: aaload
    //   376: astore_3
    //   377: aload_3
    //   378: iconst_2
    //   379: invokestatic 116	android/util/Base64:decode	(Ljava/lang/String;I)[B
    //   382: astore_3
    //   383: iconst_0
    //   384: sipush 350
    //   387: bipush 42
    //   389: invokestatic 45	o/R:ˋ	(CII)Ljava/lang/String;
    //   392: astore 4
    //   394: aload 4
    //   396: invokevirtual 51	java/lang/String:intern	()Ljava/lang/String;
    //   399: astore 4
    //   401: aload_3
    //   402: aload 4
    //   404: invokestatic 118	o/vq:ˋ	(Ljava/lang/Object;Ljava/lang/String;)V
    //   407: aload_0
    //   408: aload_3
    //   409: putfield 120	o/R:ˊ	[B
    //   412: aload_1
    //   413: iconst_1
    //   414: aaload
    //   415: iconst_2
    //   416: invokestatic 116	android/util/Base64:decode	(Ljava/lang/String;I)[B
    //   419: astore_3
    //   420: aload_3
    //   421: iconst_0
    //   422: sipush 392
    //   425: bipush 42
    //   427: invokestatic 45	o/R:ˋ	(CII)Ljava/lang/String;
    //   430: invokevirtual 51	java/lang/String:intern	()Ljava/lang/String;
    //   433: invokestatic 118	o/vq:ˋ	(Ljava/lang/Object;Ljava/lang/String;)V
    //   436: aload_0
    //   437: aload_3
    //   438: putfield 122	o/R:ˎ	[B
    //   441: aload_1
    //   442: iconst_2
    //   443: aaload
    //   444: iconst_2
    //   445: invokestatic 116	android/util/Base64:decode	(Ljava/lang/String;I)[B
    //   448: astore_1
    //   449: aload_1
    //   450: ldc 123
    //   452: sipush 434
    //   455: bipush 42
    //   457: invokestatic 45	o/R:ˋ	(CII)Ljava/lang/String;
    //   460: invokevirtual 51	java/lang/String:intern	()Ljava/lang/String;
    //   463: invokestatic 118	o/vq:ˋ	(Ljava/lang/Object;Ljava/lang/String;)V
    //   466: aload_0
    //   467: aload_1
    //   468: putfield 125	o/R:ॱ	[B
    //   471: return
    //   472: iload_2
    //   473: ifne +6 -> 479
    //   476: goto -138 -> 338
    //   479: goto -185 -> 294
    //   482: iconst_1
    //   483: istore_2
    //   484: goto -12 -> 472
    //   487: getstatic 26	o/R:ᐝ	I
    //   490: bipush 75
    //   492: iadd
    //   493: istore_2
    //   494: iload_2
    //   495: sipush 128
    //   498: irem
    //   499: putstatic 28	o/R:ॱॱ	I
    //   502: iload_2
    //   503: iconst_2
    //   504: irem
    //   505: ifne +6 -> 511
    //   508: goto -165 -> 343
    //   511: goto -236 -> 275
    //   514: aload_3
    //   515: invokeinterface 128 1 0
    //   520: ifeq +6 -> 526
    //   523: goto -253 -> 270
    //   526: goto +24 -> 550
    //   529: aload_1
    //   530: iconst_0
    //   531: anewarray 47	java/lang/String
    //   534: invokeinterface 132 2 0
    //   539: astore_1
    //   540: aload_1
    //   541: ifnonnull +6 -> 547
    //   544: goto -433 -> 111
    //   547: goto -229 -> 318
    //   550: iconst_0
    //   551: istore_2
    //   552: goto -529 -> 23
    //   555: aload_3
    //   556: invokeinterface 136 1 0
    //   561: checkcast 47	java/lang/String
    //   564: checkcast 70	java/lang/CharSequence
    //   567: invokeinterface 139 1 0
    //   572: ifne +6 -> 578
    //   575: goto -324 -> 251
    //   578: goto -314 -> 264
    // Local variable table:
    //   start	length	slot	name	signature
    //   0	581	0	this	R
    //   0	581	1	paramString	String
    //   23	529	2	i	int
    //   279	277	3	localObject	Object
    //   392	11	4	str	String
    // Exception table:
    //   from	to	target	type
    //   377	383	78	java/lang/Exception
    //   383	394	150	java/lang/Exception
    //   394	401	150	java/lang/Exception
    //   401	471	150	java/lang/Exception
  }
  
  public R(byte[] paramArrayOfByte1, byte[] paramArrayOfByte2, byte[] paramArrayOfByte3) {}
  
  private static String ˋ(char paramChar, int paramInt1, int paramInt2)
  {
    break label103;
    Object localObject = new char[paramInt2];
    int i = 0;
    break label157;
    for (;;)
    {
      paramChar = ᐝ + 29;
      ॱॱ = paramChar % '';
      if (paramChar % '\002' == 0) {
        break;
      }
      return localObject;
      label40:
      localObject = new String((char[])localObject);
    }
    int j;
    label68:
    for (;;)
    {
      if (i < paramInt2) {
        break label190;
      }
      j = 1;
      break;
    }
    for (;;)
    {
      switch (j)
      {
      case 1: 
      default: 
        break label40;
        break;
      case 89: 
        try
        {
          label103:
          j = ˏ[(paramInt1 + i)];
          l1 = j;
          l2 = i;
        }
        catch (Exception localException1)
        {
          try
          {
            long l1;
            long l2;
            localObject[i] = ((char)(int)(l1 ^ l2 * ʻ ^ paramChar));
            i += 1;
          }
          catch (Exception localException2)
          {
            throw localException2;
          }
          localException1 = localException1;
          throw localException1;
        }
        label157:
        do
        {
          break;
          j = ॱॱ + 7;
          ᐝ = j % 128;
        } while (j % 2 != 0);
        break label68;
        return localException1;
        label190:
        j = 89;
      }
    }
  }
  
  static void ˎ()
  {
    ʻ = -3214551643457245826L;
    ˏ = new char[] { 99, 11543, 23180, -30702, -19043, -7420, 4256, 15895, 27528, -26342, -18230, -27213, -7626, 12461, 3378, 23476, -22469, -31048, -11479, 8620, 32315, 19616, -26332, -2133, -15343, 4772, 28448, -17015, -30192, -10101, 16918, 28516, 6372, 106, 11551, 23178, -30693, -18986, -7398, 4245, 15900, 27543, -26304, -14657, -3042, 8602, 20239, 31882, -22011, -10290, 1336, 12979, 24616, -29259, -17609, -5984, 5754, 17334, 28961, -24898, -13273, -1623, 10034, 21736, -32158, -20502, -8865, 2766, 14429, 26059, -27873, 110, 11531, 23184, -30698, -18984, -7403, 4245, 15900, 27550, -26367, -14696, -2998, 8586, 20227, 31940, -22015, -10367, 1325, 12968, 24698, -29268, -17607, -5900, 5692, 17343, 28960, -24863, -13276, -1603, 10026, 21672, -32158, -20556, -8889, 2764, 14431, 26008, -27819, -16165, -4513, 7070, 18763, 30402, -23474, -11831, -176, 11461, 23052, -30783, -19088, -7432, 4200, 15863, 27519, -26384, -14788, -3085, 8545, 20222, 31855, -22106, -10389, 1259, 12902, 24549, -29550, -17838, -6215, 5393, 17030, 28700, -25193, -13566, -1862, 9737, 21394, -32484, -20817, -9198, 2479, 14081, 25789, 101, 11536, 23199, -30712, -19071, -7418, 4224, 15895, 27540, -26310, -14711, -3054, 8604, 20271, 31882, -21998, -10347, 1322, -28529, -16914, -13741, 6386, 9582, 29669, -32666, 12087, 581, 30149, -22679, -25908, -13220, 16347, 4444, 98, 11551, 23183, -30689, -18994, -7358, 4285, 15876, 27569, -26368, -14712, -3031, 8577, 20246, 31884, -22009, -10350, 1290, 12985, 24610, -29268, -3694, 110, 11531, 23184, -30698, -18984, -7403, 4245, 15900, 27550, -26367, -14696, -2998, 8586, 20227, 31940, -22015, -10367, 1325, 12968, 24698, -29268, -17607, -5900, 5692, 17343, 28960, -24863, -13276, -1603, 10026, 21672, -32158, -20556, -8889, 2764, 14431, 26008, -27812, -16171, -4540, 7121, 18688, 30425, -23458, -11839, -182, 11402, 23137, -30769, -19086, -7440, 4223, 15867, 27490, -26371, -14723, -3074, 8498, 20184, 31796, -12033, -614, -30207, 22663, 25929, 13188, -16380, -4467, -17649, 18832, 5641, 9435, -3813, -24686, -21419, 31376, 1808, -10820, -7623, -20245, 23869, 27560, 14437, -14675, -27858, -24143, 20080, 7349, 10540, -2117, -31687, 21235, 32549, 3542, -9635, -5938, -19191, 17356, 4170, 16087, -13491, -26154, -22957, 29845, 376, 12229, -953, -29998, 22344, 26035, 12889, -16203, -20631, -32203, -2632, 10046, 6845, 19496, -16386, -28376, -15173, 13878, 27061, 23333, -28958, -8155, -11336, 1394, 30889, -21987, -25210, -12520, 8855, 5134, 18314, -18147, -4990, -8688, 12764, 25357, 22147, -30705, 66, 11551, 23183, -30689, -18994, -7358, 4314, 15894, 27541, -26355, -14717, -3058, 8589, 20302, 31879, -22005, -10346, 1311, 12974, 24616, -29255, -17617, -6001, 5730, 17293, 29026, -24852, -13304, -1623, 10037, 21665, -32140, -20492, -8944, 2802, 14453, 26087, -27807, -16154, -4493, 7136, 18695, 66, 11551, 23183, -30689, -18994, -7358, 4314, 15894, 27541, -26355, -14717, -3058, 8589, 20302, 31879, -22005, -10346, 1311, 12974, 24616, -29255, -17617, -6001, 5731, 17293, 29026, -24852, -13304, -1623, 10037, 21665, -32140, -20492, -8944, 2802, 14453, 26087, -27807, -16154, -4493, 7136, 18695, -15514, -4549, -26197, 19259, 30442, 8294, -11266, -718, -22351, 23081, 1447, 14122, -7511, -29590, -16477, 26927, 5298, -14789, -3702, -23796, 20125, 30731, 11179, -10940, -32599, -19898, 24008, 3884, 14989, -7151, -26747, 16720, 27856, 7732, -13866, -1199, -22845, 20549, 962, 11607, -10044, -30173 };
  }
  
  /* Error */
  public boolean equals(Object paramObject)
  {
    // Byte code:
    //   0: goto +728 -> 728
    //   3: iload_2
    //   4: tableswitch	default:+24->28, 0:+364->368, 1:+441->445
    //   28: goto +417 -> 445
    //   31: bipush 96
    //   33: istore_2
    //   34: goto +654 -> 688
    //   37: iconst_0
    //   38: istore_2
    //   39: goto +604 -> 643
    //   42: bipush 71
    //   44: istore_2
    //   45: goto +548 -> 593
    //   48: goto +763 -> 811
    //   51: goto +165 -> 216
    //   54: iload_2
    //   55: tableswitch	default:+21->76, 0:+676->731, 1:+435->490
    //   76: goto +655 -> 731
    //   79: aload 4
    //   81: aload_3
    //   82: invokestatic 550	java/util/Arrays:equals	([B[B)Z
    //   85: ifne +6 -> 91
    //   88: goto +83 -> 171
    //   91: goto +240 -> 331
    //   94: getstatic 26	o/R:ᐝ	I
    //   97: istore_2
    //   98: iload_2
    //   99: bipush 11
    //   101: iadd
    //   102: istore_2
    //   103: iload_2
    //   104: sipush 128
    //   107: irem
    //   108: putstatic 28	o/R:ॱॱ	I
    //   111: iload_2
    //   112: iconst_2
    //   113: irem
    //   114: ifne +6 -> 120
    //   117: goto -66 -> 51
    //   120: goto +96 -> 216
    //   123: aload 4
    //   125: aload_3
    //   126: invokestatic 550	java/util/Arrays:equals	([B[B)Z
    //   129: ifne +6 -> 135
    //   132: goto +78 -> 210
    //   135: goto -93 -> 42
    //   138: aconst_null
    //   139: arraylength
    //   140: istore_2
    //   141: iconst_1
    //   142: ireturn
    //   143: iconst_1
    //   144: istore_2
    //   145: goto -91 -> 54
    //   148: sipush 17019
    //   151: bipush 30
    //   153: iconst_3
    //   154: invokestatic 45	o/R:ˋ	(CII)Ljava/lang/String;
    //   157: invokevirtual 51	java/lang/String:intern	()Ljava/lang/String;
    //   160: invokestatic 142	o/vq:ˊ	(Ljava/lang/String;)V
    //   163: goto -69 -> 94
    //   166: iconst_1
    //   167: ireturn
    //   168: astore_1
    //   169: aload_1
    //   170: athrow
    //   171: iconst_0
    //   172: ireturn
    //   173: iconst_1
    //   174: istore_2
    //   175: goto -172 -> 3
    //   178: iconst_0
    //   179: istore_2
    //   180: goto -126 -> 54
    //   183: getstatic 28	o/R:ॱॱ	I
    //   186: bipush 77
    //   188: iadd
    //   189: istore_2
    //   190: iload_2
    //   191: sipush 128
    //   194: irem
    //   195: putstatic 26	o/R:ᐝ	I
    //   198: iload_2
    //   199: iconst_2
    //   200: irem
    //   201: ifeq +6 -> 207
    //   204: goto +20 -> 224
    //   207: goto -41 -> 166
    //   210: bipush 96
    //   212: istore_2
    //   213: goto +380 -> 593
    //   216: goto +132 -> 348
    //   219: iconst_0
    //   220: istore_2
    //   221: goto -218 -> 3
    //   224: iconst_0
    //   225: ireturn
    //   226: astore_1
    //   227: aload_1
    //   228: athrow
    //   229: aload_1
    //   230: checkcast 2	o/R
    //   233: getfield 120	o/R:ˊ	[B
    //   236: astore_3
    //   237: aload_3
    //   238: ifnonnull +6 -> 244
    //   241: goto +135 -> 376
    //   244: goto -121 -> 123
    //   247: iconst_0
    //   248: iconst_0
    //   249: bipush 10
    //   251: invokestatic 45	o/R:ˋ	(CII)Ljava/lang/String;
    //   254: invokevirtual 51	java/lang/String:intern	()Ljava/lang/String;
    //   257: invokestatic 142	o/vq:ˊ	(Ljava/lang/String;)V
    //   260: aload_1
    //   261: checkcast 2	o/R
    //   264: getfield 125	o/R:ॱ	[B
    //   267: astore_3
    //   268: aload_3
    //   269: ifnonnull +6 -> 275
    //   272: goto +281 -> 553
    //   275: goto -196 -> 79
    //   278: aload_3
    //   279: aload_1
    //   280: invokestatic 550	java/util/Arrays:equals	([B[B)Z
    //   283: ifne +6 -> 289
    //   286: goto +351 -> 637
    //   289: goto -258 -> 31
    //   292: sipush 17019
    //   295: bipush 86
    //   297: iconst_4
    //   298: invokestatic 45	o/R:ˋ	(CII)Ljava/lang/String;
    //   301: invokevirtual 51	java/lang/String:intern	()Ljava/lang/String;
    //   304: invokestatic 142	o/vq:ˊ	(Ljava/lang/String;)V
    //   307: goto -213 -> 94
    //   310: goto +439 -> 749
    //   313: ldc -113
    //   315: bipush 10
    //   317: bipush 20
    //   319: invokestatic 45	o/R:ˋ	(CII)Ljava/lang/String;
    //   322: invokevirtual 51	java/lang/String:intern	()Ljava/lang/String;
    //   325: invokestatic 142	o/vq:ˊ	(Ljava/lang/String;)V
    //   328: goto -99 -> 229
    //   331: aload_0
    //   332: getfield 120	o/R:ˊ	[B
    //   335: astore 4
    //   337: aload 4
    //   339: ifnonnull +6 -> 345
    //   342: goto -29 -> 313
    //   345: goto -116 -> 229
    //   348: aload_1
    //   349: checkcast 2	o/R
    //   352: astore_1
    //   353: aload_1
    //   354: getfield 122	o/R:ˎ	[B
    //   357: astore_1
    //   358: aload_1
    //   359: ifnonnull +6 -> 365
    //   362: goto +173 -> 535
    //   365: goto -87 -> 278
    //   368: aload_1
    //   369: invokevirtual 554	java/lang/Object:getClass	()Ljava/lang/Class;
    //   372: astore_3
    //   373: goto +298 -> 671
    //   376: getstatic 28	o/R:ॱॱ	I
    //   379: bipush 59
    //   381: iadd
    //   382: istore_2
    //   383: iload_2
    //   384: sipush 128
    //   387: irem
    //   388: putstatic 26	o/R:ᐝ	I
    //   391: iload_2
    //   392: iconst_2
    //   393: irem
    //   394: ifeq +6 -> 400
    //   397: goto -254 -> 143
    //   400: goto -222 -> 178
    //   403: aload_0
    //   404: getfield 122	o/R:ˎ	[B
    //   407: astore_3
    //   408: aload_3
    //   409: ifnonnull +6 -> 415
    //   412: goto +6 -> 418
    //   415: goto -67 -> 348
    //   418: getstatic 26	o/R:ᐝ	I
    //   421: bipush 105
    //   423: iadd
    //   424: istore_2
    //   425: iload_2
    //   426: sipush 128
    //   429: irem
    //   430: putstatic 28	o/R:ॱॱ	I
    //   433: iload_2
    //   434: iconst_2
    //   435: irem
    //   436: ifne +6 -> 442
    //   439: goto -402 -> 37
    //   442: goto +277 -> 719
    //   445: aconst_null
    //   446: astore_3
    //   447: goto +224 -> 671
    //   450: aload_1
    //   451: checkcast 2	o/R
    //   454: astore_3
    //   455: aload_0
    //   456: getfield 125	o/R:ॱ	[B
    //   459: astore 4
    //   461: aload 4
    //   463: ifnonnull +6 -> 469
    //   466: goto -219 -> 247
    //   469: goto -209 -> 260
    //   472: aload_0
    //   473: invokevirtual 554	java/lang/Object:getClass	()Ljava/lang/Class;
    //   476: astore 4
    //   478: aload_1
    //   479: ifnull +6 -> 485
    //   482: goto -263 -> 219
    //   485: goto -312 -> 173
    //   488: iconst_0
    //   489: ireturn
    //   490: ldc -113
    //   492: bipush 114
    //   494: bipush 100
    //   496: invokestatic 45	o/R:ˋ	(CII)Ljava/lang/String;
    //   499: invokevirtual 51	java/lang/String:intern	()Ljava/lang/String;
    //   502: invokestatic 142	o/vq:ˊ	(Ljava/lang/String;)V
    //   505: goto -382 -> 123
    //   508: getstatic 26	o/R:ᐝ	I
    //   511: bipush 49
    //   513: iadd
    //   514: istore_2
    //   515: iload_2
    //   516: sipush 128
    //   519: irem
    //   520: putstatic 28	o/R:ॱॱ	I
    //   523: iload_2
    //   524: iconst_2
    //   525: irem
    //   526: ifne +6 -> 532
    //   529: goto -481 -> 48
    //   532: goto +279 -> 811
    //   535: sipush 17019
    //   538: bipush 30
    //   540: iconst_3
    //   541: invokestatic 45	o/R:ˋ	(CII)Ljava/lang/String;
    //   544: invokevirtual 51	java/lang/String:intern	()Ljava/lang/String;
    //   547: invokestatic 142	o/vq:ˊ	(Ljava/lang/String;)V
    //   550: goto -272 -> 278
    //   553: getstatic 28	o/R:ॱॱ	I
    //   556: bipush 119
    //   558: iadd
    //   559: istore_2
    //   560: iload_2
    //   561: sipush 128
    //   564: irem
    //   565: putstatic 26	o/R:ᐝ	I
    //   568: iload_2
    //   569: iconst_2
    //   570: irem
    //   571: ifeq +6 -> 577
    //   574: goto -264 -> 310
    //   577: goto +172 -> 749
    //   580: aload_1
    //   581: ifnonnull +6 -> 587
    //   584: goto +181 -> 765
    //   587: goto -137 -> 450
    //   590: goto +194 -> 784
    //   593: iload_2
    //   594: lookupswitch	default:+26->620, 71:+-191->403, 96:+130->724
    //   620: goto +104 -> 724
    //   623: aload_0
    //   624: checkcast 2	o/R
    //   627: aload_1
    //   628: if_acmpne +6 -> 634
    //   631: goto -448 -> 183
    //   634: goto -162 -> 472
    //   637: bipush 54
    //   639: istore_2
    //   640: goto +48 -> 688
    //   643: iload_2
    //   644: tableswitch	default:+24->668, 0:+-352->292, 1:+-496->148
    //   668: goto -376 -> 292
    //   671: aload 4
    //   673: aload_3
    //   674: invokestatic 557	o/vq:ˊ	(Ljava/lang/Object;Ljava/lang/Object;)Z
    //   677: iconst_1
    //   678: ixor
    //   679: ifeq +6 -> 685
    //   682: goto -194 -> 488
    //   685: goto -105 -> 580
    //   688: iload_2
    //   689: lookupswitch	default:+27->716, 54:+-181->508, 96:+-99->590
    //   716: goto -126 -> 590
    //   719: iconst_1
    //   720: istore_2
    //   721: goto -78 -> 643
    //   724: iconst_0
    //   725: ireturn
    //   726: iconst_1
    //   727: ireturn
    //   728: goto -105 -> 623
    //   731: ldc -113
    //   733: bipush 10
    //   735: bipush 20
    //   737: invokestatic 45	o/R:ˋ	(CII)Ljava/lang/String;
    //   740: invokevirtual 51	java/lang/String:intern	()Ljava/lang/String;
    //   743: invokestatic 142	o/vq:ˊ	(Ljava/lang/String;)V
    //   746: goto -623 -> 123
    //   749: iconst_0
    //   750: iconst_0
    //   751: bipush 10
    //   753: invokestatic 45	o/R:ˋ	(CII)Ljava/lang/String;
    //   756: invokevirtual 51	java/lang/String:intern	()Ljava/lang/String;
    //   759: invokestatic 142	o/vq:ˊ	(Ljava/lang/String;)V
    //   762: goto -683 -> 79
    //   765: new 42	o/uH
    //   768: dup
    //   769: iconst_0
    //   770: bipush 71
    //   772: bipush 82
    //   774: invokestatic 45	o/R:ˋ	(CII)Ljava/lang/String;
    //   777: invokevirtual 51	java/lang/String:intern	()Ljava/lang/String;
    //   780: invokespecial 53	o/uH:<init>	(Ljava/lang/String;)V
    //   783: athrow
    //   784: getstatic 28	o/R:ॱॱ	I
    //   787: bipush 125
    //   789: iadd
    //   790: istore_2
    //   791: iload_2
    //   792: sipush 128
    //   795: irem
    //   796: putstatic 26	o/R:ᐝ	I
    //   799: iload_2
    //   800: iconst_2
    //   801: irem
    //   802: ifeq +6 -> 808
    //   805: goto -667 -> 138
    //   808: goto -82 -> 726
    //   811: iconst_0
    //   812: ireturn
    // Local variable table:
    //   start	length	slot	name	signature
    //   0	813	0	this	R
    //   0	813	1	paramObject	Object
    //   3	799	2	i	int
    //   81	593	3	localObject1	Object
    //   79	593	4	localObject2	Object
    // Exception table:
    //   from	to	target	type
    //   94	98	168	java/lang/Exception
    //   331	337	168	java/lang/Exception
    //   348	353	168	java/lang/Exception
    //   353	358	168	java/lang/Exception
    //   103	111	226	java/lang/Exception
  }
  
  /* Error */
  public int hashCode()
  {
    // Byte code:
    //   0: goto +340 -> 340
    //   3: iconst_0
    //   4: istore_1
    //   5: goto +142 -> 147
    //   8: iconst_1
    //   9: istore_1
    //   10: goto +137 -> 147
    //   13: getstatic 26	o/R:ᐝ	I
    //   16: bipush 39
    //   18: iadd
    //   19: istore_1
    //   20: iload_1
    //   21: sipush 128
    //   24: irem
    //   25: putstatic 28	o/R:ॱॱ	I
    //   28: iload_1
    //   29: iconst_2
    //   30: irem
    //   31: ifne +6 -> 37
    //   34: goto +271 -> 305
    //   37: goto +268 -> 305
    //   40: bipush 59
    //   42: istore_1
    //   43: iload_1
    //   44: lookupswitch	default:+28->72, 59:+136->180, 88:+159->203
    //   72: goto +108 -> 180
    //   75: ldc -113
    //   77: bipush 10
    //   79: bipush 20
    //   81: invokestatic 45	o/R:ˋ	(CII)Ljava/lang/String;
    //   84: invokevirtual 51	java/lang/String:intern	()Ljava/lang/String;
    //   87: invokestatic 142	o/vq:ˊ	(Ljava/lang/String;)V
    //   90: goto +148 -> 238
    //   93: iconst_0
    //   94: istore_1
    //   95: goto +164 -> 259
    //   98: astore 4
    //   100: aload 4
    //   102: athrow
    //   103: aload 4
    //   105: invokestatic 561	java/util/Arrays:hashCode	([B)I
    //   108: istore_2
    //   109: aload_0
    //   110: getfield 120	o/R:ˊ	[B
    //   113: astore 4
    //   115: aload 4
    //   117: ifnonnull +6 -> 123
    //   120: goto +112 -> 232
    //   123: goto -83 -> 40
    //   126: iconst_1
    //   127: istore_1
    //   128: goto +131 -> 259
    //   131: iconst_0
    //   132: iconst_0
    //   133: bipush 10
    //   135: invokestatic 45	o/R:ˋ	(CII)Ljava/lang/String;
    //   138: invokevirtual 51	java/lang/String:intern	()Ljava/lang/String;
    //   141: invokestatic 142	o/vq:ˊ	(Ljava/lang/String;)V
    //   144: goto -41 -> 103
    //   147: iload_1
    //   148: tableswitch	default:+24->172, 0:+174->322, 1:+139->287
    //   172: goto +115 -> 287
    //   175: astore 4
    //   177: aload 4
    //   179: athrow
    //   180: aload 4
    //   182: invokestatic 561	java/util/Arrays:hashCode	([B)I
    //   185: istore_3
    //   186: aload_0
    //   187: getfield 122	o/R:ˎ	[B
    //   190: astore 4
    //   192: aload 4
    //   194: ifnonnull +6 -> 200
    //   197: goto -194 -> 3
    //   200: goto -192 -> 8
    //   203: getstatic 28	o/R:ॱॱ	I
    //   206: istore_1
    //   207: iload_1
    //   208: bipush 67
    //   210: iadd
    //   211: istore_1
    //   212: iload_1
    //   213: sipush 128
    //   216: irem
    //   217: putstatic 26	o/R:ᐝ	I
    //   220: iload_1
    //   221: iconst_2
    //   222: irem
    //   223: ifeq +6 -> 229
    //   226: goto +15 -> 241
    //   229: goto -154 -> 75
    //   232: bipush 88
    //   234: istore_1
    //   235: goto -192 -> 43
    //   238: goto -58 -> 180
    //   241: ldc -113
    //   243: bipush 121
    //   245: bipush 116
    //   247: invokestatic 45	o/R:ˋ	(CII)Ljava/lang/String;
    //   250: invokevirtual 51	java/lang/String:intern	()Ljava/lang/String;
    //   253: invokestatic 142	o/vq:ˊ	(Ljava/lang/String;)V
    //   256: goto -18 -> 238
    //   259: iload_1
    //   260: tableswitch	default:+24->284, 0:+-129->131, 1:+-157->103
    //   284: goto -153 -> 131
    //   287: aload 4
    //   289: invokestatic 561	java/util/Arrays:hashCode	([B)I
    //   292: istore_1
    //   293: iload_2
    //   294: bipush 31
    //   296: imul
    //   297: iload_3
    //   298: iadd
    //   299: bipush 31
    //   301: imul
    //   302: iload_1
    //   303: iadd
    //   304: ireturn
    //   305: aload_0
    //   306: getfield 125	o/R:ॱ	[B
    //   309: astore 4
    //   311: aload 4
    //   313: ifnonnull +6 -> 319
    //   316: goto -223 -> 93
    //   319: goto -193 -> 126
    //   322: sipush 17019
    //   325: bipush 30
    //   327: iconst_3
    //   328: invokestatic 45	o/R:ˋ	(CII)Ljava/lang/String;
    //   331: invokevirtual 51	java/lang/String:intern	()Ljava/lang/String;
    //   334: invokestatic 142	o/vq:ˊ	(Ljava/lang/String;)V
    //   337: goto -50 -> 287
    //   340: goto -327 -> 13
    // Local variable table:
    //   start	length	slot	name	signature
    //   0	343	0	this	R
    //   4	300	1	i	int
    //   108	189	2	j	int
    //   185	114	3	k	int
    //   98	6	4	localException1	Exception
    //   113	3	4	arrayOfByte1	byte[]
    //   175	6	4	localException2	Exception
    //   190	122	4	arrayOfByte2	byte[]
    // Exception table:
    //   from	to	target	type
    //   203	207	98	java/lang/Exception
    //   287	293	98	java/lang/Exception
    //   212	220	175	java/lang/Exception
  }
  
  /* Error */
  public String toString()
  {
    // Byte code:
    //   0: goto +244 -> 244
    //   3: iconst_1
    //   4: istore_1
    //   5: goto +308 -> 313
    //   8: getstatic 26	o/R:ᐝ	I
    //   11: bipush 59
    //   13: iadd
    //   14: istore_1
    //   15: iload_1
    //   16: sipush 128
    //   19: irem
    //   20: putstatic 28	o/R:ॱॱ	I
    //   23: iload_1
    //   24: iconst_2
    //   25: irem
    //   26: ifne +6 -> 32
    //   29: goto +281 -> 310
    //   32: goto +252 -> 284
    //   35: goto +32 -> 67
    //   38: iconst_1
    //   39: istore_1
    //   40: goto +212 -> 252
    //   43: getstatic 26	o/R:ᐝ	I
    //   46: bipush 45
    //   48: iadd
    //   49: istore_1
    //   50: iload_1
    //   51: sipush 128
    //   54: irem
    //   55: putstatic 28	o/R:ॱॱ	I
    //   58: iload_1
    //   59: iconst_2
    //   60: irem
    //   61: ifne +6 -> 67
    //   64: goto -29 -> 35
    //   67: iconst_0
    //   68: iconst_0
    //   69: bipush 10
    //   71: invokestatic 45	o/R:ˋ	(CII)Ljava/lang/String;
    //   74: invokevirtual 51	java/lang/String:intern	()Ljava/lang/String;
    //   77: invokestatic 142	o/vq:ˊ	(Ljava/lang/String;)V
    //   80: goto +259 -> 339
    //   83: iconst_0
    //   84: istore_1
    //   85: goto +167 -> 252
    //   88: aload_2
    //   89: iconst_2
    //   90: invokestatic 566	android/util/Base64:encodeToString	([BI)Ljava/lang/String;
    //   93: astore_2
    //   94: aload_0
    //   95: getfield 125	o/R:ॱ	[B
    //   98: astore_3
    //   99: aload_3
    //   100: ifnonnull +6 -> 106
    //   103: goto -20 -> 83
    //   106: goto -68 -> 38
    //   109: goto +29 -> 138
    //   112: astore_2
    //   113: aload_2
    //   114: athrow
    //   115: iconst_1
    //   116: istore_1
    //   117: goto +245 -> 362
    //   120: aload_0
    //   121: getfield 120	o/R:ˊ	[B
    //   124: astore_2
    //   125: aload_2
    //   126: ifnonnull +6 -> 132
    //   129: goto +118 -> 247
    //   132: goto -17 -> 115
    //   135: astore_2
    //   136: aload_2
    //   137: athrow
    //   138: ldc -113
    //   140: bipush 10
    //   142: bipush 20
    //   144: invokestatic 45	o/R:ˋ	(CII)Ljava/lang/String;
    //   147: invokevirtual 51	java/lang/String:intern	()Ljava/lang/String;
    //   150: invokestatic 142	o/vq:ˊ	(Ljava/lang/String;)V
    //   153: goto -65 -> 88
    //   156: aload 4
    //   158: iconst_2
    //   159: invokestatic 566	android/util/Base64:encodeToString	([BI)Ljava/lang/String;
    //   162: astore 4
    //   164: getstatic 571	o/vw:ˊ	Lo/vw;
    //   167: astore 5
    //   169: new 573	java/lang/StringBuilder
    //   172: dup
    //   173: invokespecial 574	java/lang/StringBuilder:<init>	()V
    //   176: ldc_w 576
    //   179: invokevirtual 580	java/lang/StringBuilder:append	(Ljava/lang/String;)Ljava/lang/StringBuilder;
    //   182: aload_2
    //   183: invokevirtual 580	java/lang/StringBuilder:append	(Ljava/lang/String;)Ljava/lang/StringBuilder;
    //   186: bipush 58
    //   188: invokevirtual 583	java/lang/StringBuilder:append	(C)Ljava/lang/StringBuilder;
    //   191: aload 4
    //   193: invokevirtual 580	java/lang/StringBuilder:append	(Ljava/lang/String;)Ljava/lang/StringBuilder;
    //   196: bipush 58
    //   198: invokevirtual 583	java/lang/StringBuilder:append	(C)Ljava/lang/StringBuilder;
    //   201: aload_3
    //   202: invokevirtual 580	java/lang/StringBuilder:append	(Ljava/lang/String;)Ljava/lang/StringBuilder;
    //   205: invokevirtual 585	java/lang/StringBuilder:toString	()Ljava/lang/String;
    //   208: astore_2
    //   209: iconst_0
    //   210: anewarray 4	java/lang/Object
    //   213: astore_3
    //   214: aload_3
    //   215: arraylength
    //   216: istore_1
    //   217: aload_2
    //   218: aload_3
    //   219: iconst_0
    //   220: invokestatic 589	java/util/Arrays:copyOf	([Ljava/lang/Object;I)[Ljava/lang/Object;
    //   223: invokestatic 593	java/lang/String:format	(Ljava/lang/String;[Ljava/lang/Object;)Ljava/lang/String;
    //   226: astore_2
    //   227: aload_2
    //   228: iconst_0
    //   229: bipush 33
    //   231: bipush 38
    //   233: invokestatic 45	o/R:ˋ	(CII)Ljava/lang/String;
    //   236: invokevirtual 51	java/lang/String:intern	()Ljava/lang/String;
    //   239: invokestatic 118	o/vq:ˋ	(Ljava/lang/Object;Ljava/lang/String;)V
    //   242: aload_2
    //   243: areturn
    //   244: goto -124 -> 120
    //   247: iconst_0
    //   248: istore_1
    //   249: goto +113 -> 362
    //   252: iload_1
    //   253: tableswitch	default:+23->276, 0:+-210->43, 1:+86->339
    //   276: goto +63 -> 339
    //   279: iconst_0
    //   280: istore_1
    //   281: goto +32 -> 313
    //   284: sipush 17019
    //   287: bipush 30
    //   289: iconst_3
    //   290: invokestatic 45	o/R:ˋ	(CII)Ljava/lang/String;
    //   293: astore 5
    //   295: aload 5
    //   297: invokevirtual 51	java/lang/String:intern	()Ljava/lang/String;
    //   300: astore 5
    //   302: aload 5
    //   304: invokestatic 142	o/vq:ˊ	(Ljava/lang/String;)V
    //   307: goto -151 -> 156
    //   310: goto -26 -> 284
    //   313: iload_1
    //   314: tableswitch	default:+22->336, 0:+-158->156, 1:+-306->8
    //   336: goto -180 -> 156
    //   339: aload_3
    //   340: iconst_2
    //   341: invokestatic 566	android/util/Base64:encodeToString	([BI)Ljava/lang/String;
    //   344: astore_3
    //   345: aload_0
    //   346: getfield 122	o/R:ˎ	[B
    //   349: astore 4
    //   351: aload 4
    //   353: ifnonnull +6 -> 359
    //   356: goto -353 -> 3
    //   359: goto -80 -> 279
    //   362: iload_1
    //   363: tableswitch	default:+21->384, 0:+24->387, 1:+-275->88
    //   384: goto -296 -> 88
    //   387: getstatic 26	o/R:ᐝ	I
    //   390: bipush 99
    //   392: iadd
    //   393: istore_1
    //   394: iload_1
    //   395: sipush 128
    //   398: irem
    //   399: putstatic 28	o/R:ॱॱ	I
    //   402: iload_1
    //   403: iconst_2
    //   404: irem
    //   405: ifne +6 -> 411
    //   408: goto -299 -> 109
    //   411: goto -273 -> 138
    // Local variable table:
    //   start	length	slot	name	signature
    //   0	414	0	this	R
    //   4	401	1	i	int
    //   88	6	2	localObject1	Object
    //   112	2	2	localException1	Exception
    //   124	2	2	arrayOfByte	byte[]
    //   135	48	2	localException2	Exception
    //   208	35	2	str	String
    //   98	247	3	localObject2	Object
    //   156	196	4	localObject3	Object
    //   167	136	5	localObject4	Object
    // Exception table:
    //   from	to	target	type
    //   284	295	112	java/lang/Exception
    //   295	302	135	java/lang/Exception
    //   302	307	135	java/lang/Exception
    //   387	402	135	java/lang/Exception
  }
  
  /* Error */
  public final byte[] ˋ()
  {
    // Byte code:
    //   0: goto +35 -> 35
    //   3: iload_1
    //   4: lookupswitch	default:+28->32, 12:+95->99, 81:+34->38
    //   32: goto +6 -> 38
    //   35: goto +17 -> 52
    //   38: aload_2
    //   39: areturn
    //   40: goto +97 -> 137
    //   43: bipush 12
    //   45: istore_1
    //   46: goto -43 -> 3
    //   49: astore_2
    //   50: aload_2
    //   51: athrow
    //   52: getstatic 26	o/R:ᐝ	I
    //   55: iconst_3
    //   56: iadd
    //   57: istore_1
    //   58: iload_1
    //   59: sipush 128
    //   62: irem
    //   63: putstatic 28	o/R:ॱॱ	I
    //   66: iload_1
    //   67: iconst_2
    //   68: irem
    //   69: ifne +6 -> 75
    //   72: goto -32 -> 40
    //   75: goto +62 -> 137
    //   78: sipush 17019
    //   81: bipush 30
    //   83: iconst_3
    //   84: invokestatic 45	o/R:ˋ	(CII)Ljava/lang/String;
    //   87: astore_3
    //   88: aload_3
    //   89: invokevirtual 51	java/lang/String:intern	()Ljava/lang/String;
    //   92: astore_3
    //   93: aload_3
    //   94: invokestatic 142	o/vq:ˊ	(Ljava/lang/String;)V
    //   97: aload_2
    //   98: areturn
    //   99: getstatic 28	o/R:ॱॱ	I
    //   102: istore_1
    //   103: iload_1
    //   104: bipush 121
    //   106: iadd
    //   107: istore_1
    //   108: iload_1
    //   109: sipush 128
    //   112: irem
    //   113: putstatic 26	o/R:ᐝ	I
    //   116: iload_1
    //   117: iconst_2
    //   118: irem
    //   119: ifeq +6 -> 125
    //   122: goto +12 -> 134
    //   125: goto -47 -> 78
    //   128: bipush 81
    //   130: istore_1
    //   131: goto -128 -> 3
    //   134: goto -56 -> 78
    //   137: aload_0
    //   138: getfield 122	o/R:ˎ	[B
    //   141: astore_2
    //   142: aload_2
    //   143: ifnonnull +6 -> 149
    //   146: goto -103 -> 43
    //   149: goto -21 -> 128
    //   152: astore_2
    //   153: aload_2
    //   154: athrow
    // Local variable table:
    //   start	length	slot	name	signature
    //   0	155	0	this	R
    //   3	128	1	i	int
    //   38	1	2	arrayOfByte1	byte[]
    //   49	49	2	localException1	Exception
    //   141	2	2	arrayOfByte2	byte[]
    //   152	2	2	localException2	Exception
    //   87	7	3	str	String
    // Exception table:
    //   from	to	target	type
    //   78	88	49	java/lang/Exception
    //   88	93	49	java/lang/Exception
    //   93	97	49	java/lang/Exception
    //   99	103	49	java/lang/Exception
    //   108	116	152	java/lang/Exception
  }
  
  public final byte[] ˏ()
  {
    break label95;
    int i;
    switch (i)
    {
    default: 
      break;
    case 1: 
      byte[] arrayOfByte1;
      return arrayOfByte1;
      try
      {
        label33:
        String str;
        for (;;)
        {
          str = ˋ(47267, 10, 20);
        }
      }
      catch (Exception localException1)
      {
        try
        {
          str = str.intern();
          vq.ˊ(str);
          return arrayOfByte1;
        }
        catch (Exception localException2)
        {
          throw localException2;
        }
        localException1 = localException1;
        throw localException1;
      }
      label57:
      label60:
      i = ᐝ + 9;
      ॱॱ = i % 128;
      if (i % 2 != 0) {
        break label130;
      }
      break;
    }
    for (;;)
    {
      i = 1;
      break;
      label95:
      break label60;
      i = ॱॱ + 77;
      ᐝ = i % 128;
      if (i % 2 != 0) {
        break label57;
      }
      break label33;
      label130:
      byte[] arrayOfByte2;
      do
      {
        i = 0;
        break;
        arrayOfByte2 = this.ˊ;
      } while (arrayOfByte2 == null);
    }
  }
  
  /* Error */
  public final byte[] ॱ()
  {
    // Byte code:
    //   0: goto +57 -> 57
    //   3: getstatic 28	o/R:ॱॱ	I
    //   6: bipush 23
    //   8: iadd
    //   9: istore_1
    //   10: iload_1
    //   11: sipush 128
    //   14: irem
    //   15: putstatic 26	o/R:ᐝ	I
    //   18: iload_1
    //   19: iconst_2
    //   20: irem
    //   21: ifeq +6 -> 27
    //   24: goto +30 -> 54
    //   27: goto +95 -> 122
    //   30: iload_1
    //   31: tableswitch	default:+21->52, 0:+69->100, 1:+29->60
    //   52: aload_2
    //   53: areturn
    //   54: goto +68 -> 122
    //   57: goto -54 -> 3
    //   60: getstatic 26	o/R:ᐝ	I
    //   63: bipush 91
    //   65: iadd
    //   66: istore_1
    //   67: iload_1
    //   68: sipush 128
    //   71: irem
    //   72: putstatic 28	o/R:ॱॱ	I
    //   75: iload_1
    //   76: iconst_2
    //   77: irem
    //   78: ifne +6 -> 84
    //   81: goto +58 -> 139
    //   84: goto +18 -> 102
    //   87: iconst_1
    //   88: istore_1
    //   89: goto -59 -> 30
    //   92: iconst_0
    //   93: istore_1
    //   94: goto -64 -> 30
    //   97: astore_2
    //   98: aload_2
    //   99: athrow
    //   100: aload_2
    //   101: areturn
    //   102: iconst_0
    //   103: iconst_0
    //   104: bipush 10
    //   106: invokestatic 45	o/R:ˋ	(CII)Ljava/lang/String;
    //   109: astore_3
    //   110: aload_3
    //   111: invokevirtual 51	java/lang/String:intern	()Ljava/lang/String;
    //   114: astore_3
    //   115: aload_3
    //   116: invokestatic 142	o/vq:ˊ	(Ljava/lang/String;)V
    //   119: goto +18 -> 137
    //   122: aload_0
    //   123: getfield 125	o/R:ॱ	[B
    //   126: astore_2
    //   127: aload_2
    //   128: ifnonnull +6 -> 134
    //   131: goto -44 -> 87
    //   134: goto -42 -> 92
    //   137: aload_2
    //   138: areturn
    //   139: goto -37 -> 102
    // Local variable table:
    //   start	length	slot	name	signature
    //   0	142	0	this	R
    //   9	85	1	i	int
    //   52	1	2	arrayOfByte1	byte[]
    //   97	4	2	localException	Exception
    //   126	12	2	arrayOfByte2	byte[]
    //   109	7	3	str	String
    // Exception table:
    //   from	to	target	type
    //   102	110	97	java/lang/Exception
    //   110	115	97	java/lang/Exception
    //   115	119	97	java/lang/Exception
    //   122	127	97	java/lang/Exception
  }
  
  public static final class iF
  {
    private static int ʻ;
    private static short[] ˊ;
    private static int ˋ = 1172812080;
    private static int ˎ;
    private static byte[] ˏ;
    private static int ॱ;
    private static int ᐝ = 0;
    
    static
    {
      ʻ = 1;
      ॱ = 2;
      ˏ = new byte[] { 0, -37, 8, -17, 0, 2, -15, 30, -18, -21, 20, 21 };
      ˎ = 1512641566;
    }
    
    private iF() {}
    
    /* Error */
    private static String ˋ(int paramInt1, byte paramByte, int paramInt2, short paramShort, int paramInt3)
    {
      // Byte code:
      //   0: goto +602 -> 602
      //   3: iload_2
      //   4: iload 4
      //   6: if_icmpge +6 -> 12
      //   9: goto +345 -> 354
      //   12: goto +213 -> 225
      //   15: bipush 49
      //   17: istore 7
      //   19: goto +27 -> 46
      //   22: getstatic 38	o/R$iF:ˏ	[B
      //   25: ifnull +6 -> 31
      //   28: goto +287 -> 315
      //   31: goto +335 -> 366
      //   34: iconst_0
      //   35: istore 6
      //   37: goto +204 -> 241
      //   40: iconst_0
      //   41: istore 6
      //   43: goto +482 -> 525
      //   46: iload 7
      //   48: lookupswitch	default:+28->76, 49:+353->401, 59:+177->225
      //   76: goto +325 -> 401
      //   79: bipush 40
      //   81: istore 6
      //   83: goto +54 -> 137
      //   86: getstatic 38	o/R$iF:ˏ	[B
      //   89: getstatic 44	o/R$iF:ˋ	I
      //   92: iload_0
      //   93: iadd
      //   94: baload
      //   95: getstatic 25	o/R$iF:ॱ	I
      //   98: iadd
      //   99: i2b
      //   100: istore 4
      //   102: goto +32 -> 134
      //   105: bipush 59
      //   107: istore 7
      //   109: goto -63 -> 46
      //   112: getstatic 44	o/R$iF:ˋ	I
      //   115: istore 7
      //   117: iload 6
      //   119: ifeq +6 -> 125
      //   122: goto +414 -> 536
      //   125: goto +142 -> 267
      //   128: iconst_1
      //   129: istore 6
      //   131: goto +300 -> 431
      //   134: goto +139 -> 273
      //   137: iload 6
      //   139: lookupswitch	default:+25->164, 40:+209->348, 84:+-11->128
      //   164: goto -36 -> 128
      //   167: new 55	java/lang/StringBuilder
      //   170: dup
      //   171: invokespecial 56	java/lang/StringBuilder:<init>	()V
      //   174: astore 8
      //   176: getstatic 25	o/R$iF:ॱ	I
      //   179: iload 4
      //   181: iadd
      //   182: istore 6
      //   184: iload 6
      //   186: istore 4
      //   188: iload 6
      //   190: iconst_m1
      //   191: if_icmpne +6 -> 197
      //   194: goto +372 -> 566
      //   197: goto -157 -> 40
      //   200: aload 8
      //   202: iload 5
      //   204: invokevirtual 60	java/lang/StringBuilder:append	(C)Ljava/lang/StringBuilder;
      //   207: pop
      //   208: iload_2
      //   209: iconst_1
      //   210: iadd
      //   211: istore_2
      //   212: iload 5
      //   214: istore 7
      //   216: goto -213 -> 3
      //   219: iconst_0
      //   220: istore 6
      //   222: goto +303 -> 525
      //   225: aload 8
      //   227: invokevirtual 64	java/lang/StringBuilder:toString	()Ljava/lang/String;
      //   230: areturn
      //   231: astore 8
      //   233: aload 8
      //   235: athrow
      //   236: astore 8
      //   238: aload 8
      //   240: athrow
      //   241: iload 6
      //   243: tableswitch	default:+21->264, 0:+-24->219, 1:+353->596
      //   264: goto -45 -> 219
      //   267: iconst_0
      //   268: istore 6
      //   270: goto +161 -> 431
      //   273: iload 4
      //   275: ifle +6 -> 281
      //   278: goto -263 -> 15
      //   281: goto -176 -> 105
      //   284: getstatic 66	o/R$iF:ˊ	[S
      //   287: astore 9
      //   289: iload_0
      //   290: iconst_1
      //   291: isub
      //   292: istore 6
      //   294: aload 9
      //   296: iload_0
      //   297: saload
      //   298: iload_3
      //   299: iadd
      //   300: i2s
      //   301: iload_1
      //   302: ixor
      //   303: iload 7
      //   305: iadd
      //   306: i2c
      //   307: istore 5
      //   309: iload 6
      //   311: istore_0
      //   312: goto -112 -> 200
      //   315: getstatic 21	o/R$iF:ᐝ	I
      //   318: bipush 19
      //   320: iadd
      //   321: istore 4
      //   323: iload 4
      //   325: sipush 128
      //   328: irem
      //   329: putstatic 23	o/R$iF:ʻ	I
      //   332: iload 4
      //   334: iconst_2
      //   335: irem
      //   336: ifne +6 -> 342
      //   339: goto +130 -> 469
      //   342: goto -256 -> 86
      //   345: goto -233 -> 112
      //   348: iconst_1
      //   349: istore 6
      //   351: goto +80 -> 431
      //   354: getstatic 38	o/R$iF:ˏ	[B
      //   357: ifnull +6 -> 363
      //   360: goto +128 -> 488
      //   363: goto -79 -> 284
      //   366: getstatic 66	o/R$iF:ˊ	[S
      //   369: astore 9
      //   371: getstatic 44	o/R$iF:ˋ	I
      //   374: istore 4
      //   376: aload 9
      //   378: iload 4
      //   380: iload_0
      //   381: iadd
      //   382: saload
      //   383: istore 4
      //   385: getstatic 25	o/R$iF:ॱ	I
      //   388: istore 7
      //   390: iload 4
      //   392: iload 7
      //   394: iadd
      //   395: i2s
      //   396: istore 4
      //   398: goto -125 -> 273
      //   401: getstatic 23	o/R$iF:ʻ	I
      //   404: bipush 95
      //   406: iadd
      //   407: istore 7
      //   409: iload 7
      //   411: sipush 128
      //   414: irem
      //   415: putstatic 21	o/R$iF:ᐝ	I
      //   418: iload 7
      //   420: iconst_2
      //   421: irem
      //   422: ifeq +6 -> 428
      //   425: goto -80 -> 345
      //   428: goto -316 -> 112
      //   431: iload_0
      //   432: iload 4
      //   434: iadd
      //   435: iconst_2
      //   436: isub
      //   437: iload 7
      //   439: iadd
      //   440: iload 6
      //   442: iadd
      //   443: istore_0
      //   444: getstatic 41	o/R$iF:ˎ	I
      //   447: iload_2
      //   448: iadd
      //   449: i2c
      //   450: istore 5
      //   452: aload 8
      //   454: iload 5
      //   456: invokevirtual 60	java/lang/StringBuilder:append	(C)Ljava/lang/StringBuilder;
      //   459: pop
      //   460: iconst_1
      //   461: istore_2
      //   462: iload 5
      //   464: istore 7
      //   466: goto -463 -> 3
      //   469: getstatic 38	o/R$iF:ˏ	[B
      //   472: iload_0
      //   473: getstatic 44	o/R$iF:ˋ	I
      //   476: idiv
      //   477: baload
      //   478: getstatic 25	o/R$iF:ॱ	I
      //   481: irem
      //   482: i2b
      //   483: istore 4
      //   485: goto -351 -> 134
      //   488: getstatic 38	o/R$iF:ˏ	[B
      //   491: astore 9
      //   493: iload_0
      //   494: iconst_1
      //   495: isub
      //   496: istore 6
      //   498: aload 9
      //   500: iload_0
      //   501: baload
      //   502: iload_3
      //   503: iadd
      //   504: i2b
      //   505: iload_1
      //   506: ixor
      //   507: iload 7
      //   509: iadd
      //   510: i2c
      //   511: istore 5
      //   513: iload 6
      //   515: istore_0
      //   516: goto -316 -> 200
      //   519: iconst_1
      //   520: istore 6
      //   522: goto -281 -> 241
      //   525: iload 6
      //   527: ifeq +6 -> 533
      //   530: goto -508 -> 22
      //   533: goto -260 -> 273
      //   536: getstatic 23	o/R$iF:ʻ	I
      //   539: bipush 93
      //   541: iadd
      //   542: istore 6
      //   544: iload 6
      //   546: sipush 128
      //   549: irem
      //   550: putstatic 21	o/R$iF:ᐝ	I
      //   553: iload 6
      //   555: iconst_2
      //   556: irem
      //   557: ifeq +6 -> 563
      //   560: goto -481 -> 79
      //   563: goto +42 -> 605
      //   566: getstatic 23	o/R$iF:ʻ	I
      //   569: bipush 107
      //   571: iadd
      //   572: istore 6
      //   574: iload 6
      //   576: sipush 128
      //   579: irem
      //   580: putstatic 21	o/R$iF:ᐝ	I
      //   583: iload 6
      //   585: iconst_2
      //   586: irem
      //   587: ifeq +6 -> 593
      //   590: goto -556 -> 34
      //   593: goto -74 -> 519
      //   596: iconst_1
      //   597: istore 6
      //   599: goto -74 -> 525
      //   602: goto -435 -> 167
      //   605: bipush 84
      //   607: istore 6
      //   609: goto -472 -> 137
      // Local variable table:
      //   start	length	slot	name	signature
      //   0	612	0	paramInt1	int
      //   0	612	1	paramByte	byte
      //   0	612	2	paramInt2	int
      //   0	612	3	paramShort	short
      //   0	612	4	paramInt3	int
      //   202	310	5	i	int
      //   35	573	6	j	int
      //   17	493	7	k	int
      //   174	52	8	localStringBuilder	StringBuilder
      //   231	3	8	localException1	Exception
      //   236	217	8	localException2	Exception
      //   287	212	9	localObject	Object
      // Exception table:
      //   from	to	target	type
      //   284	289	231	java/lang/Exception
      //   366	371	236	java/lang/Exception
      //   371	376	236	java/lang/Exception
      //   385	390	236	java/lang/Exception
    }
    
    public final byte[] ˎ(byte[] paramArrayOfByte1, byte[] paramArrayOfByte2)
    {
      for (;;)
      {
        vq.ˎ(paramArrayOfByte1, ˋ(-1172812080, (byte)-42, -1512641461, (short)0, -3).intern());
        vq.ˎ(paramArrayOfByte2, ˋ(-1172812078, (byte)19, -1512641467, (short)0, -3).intern());
        byte[] arrayOfByte = new byte[paramArrayOfByte1.length + paramArrayOfByte2.length];
        System.arraycopy(paramArrayOfByte1, 0, arrayOfByte, 0, paramArrayOfByte1.length);
        System.arraycopy(paramArrayOfByte2, 0, arrayOfByte, paramArrayOfByte1.length, paramArrayOfByte2.length);
        int i = ʻ + 121;
        ᐝ = i % 128;
        if (i % 2 != 0) {
          return arrayOfByte;
        }
        return arrayOfByte;
        i = ʻ + 41;
        ᐝ = i % 128;
        if (i % 2 != 0) {
          break;
        }
      }
    }
  }
}
