package o;

import android.net.Uri;
import java.util.Arrays;
import java.util.Collections;
import java.util.HashSet;
import java.util.Iterator;
import java.util.LinkedHashMap;
import java.util.Map;
import java.util.Set;

class vY
{
  private static int ˋ = 100;
  private static int ˎ;
  private static int ˏ = 0;
  
  static
  {
    ˎ = 1;
  }
  
  /* Error */
  private static String ˊ(int paramInt1, int paramInt2, char[] paramArrayOfChar, int paramInt3, boolean paramBoolean)
  {
    // Byte code:
    //   0: goto +111 -> 111
    //   3: goto +99 -> 102
    //   6: goto +258 -> 264
    //   9: iload_0
    //   10: tableswitch	default:+22->32, 0:+65->75, 1:+231->241
    //   32: goto +209 -> 241
    //   35: iload_1
    //   36: newarray char
    //   38: astore 7
    //   40: iconst_0
    //   41: istore 5
    //   43: goto +233 -> 276
    //   46: getstatic 14	o/vY:ˎ	I
    //   49: iconst_3
    //   50: iadd
    //   51: istore_0
    //   52: iload_0
    //   53: sipush 128
    //   56: irem
    //   57: putstatic 12	o/vY:ˏ	I
    //   60: iload_0
    //   61: iconst_2
    //   62: irem
    //   63: ifeq +6 -> 69
    //   66: goto +162 -> 228
    //   69: goto +248 -> 317
    //   72: astore_2
    //   73: aload_2
    //   74: athrow
    //   75: getstatic 12	o/vY:ˏ	I
    //   78: bipush 21
    //   80: iadd
    //   81: istore_0
    //   82: iload_0
    //   83: sipush 128
    //   86: irem
    //   87: putstatic 14	o/vY:ˎ	I
    //   90: iload_0
    //   91: iconst_2
    //   92: irem
    //   93: ifne +6 -> 99
    //   96: goto +129 -> 225
    //   99: goto +60 -> 159
    //   102: new 23	java/lang/String
    //   105: dup
    //   106: aload_2
    //   107: invokespecial 27	java/lang/String:<init>	([C)V
    //   110: areturn
    //   111: goto -76 -> 35
    //   114: iconst_1
    //   115: istore_0
    //   116: goto -107 -> 9
    //   119: iload_0
    //   120: tableswitch	default:+24->144, 0:+135->255, 1:+30->150
    //   144: goto +6 -> 150
    //   147: goto -141 -> 6
    //   150: iload_1
    //   151: newarray char
    //   153: astore_2
    //   154: iconst_0
    //   155: istore_0
    //   156: goto +150 -> 306
    //   159: iload_1
    //   160: newarray char
    //   162: astore_2
    //   163: aload 7
    //   165: iconst_0
    //   166: aload_2
    //   167: iconst_0
    //   168: iload_1
    //   169: invokestatic 33	java/lang/System:arraycopy	(Ljava/lang/Object;ILjava/lang/Object;II)V
    //   172: aload_2
    //   173: iconst_0
    //   174: aload 7
    //   176: iload_1
    //   177: iload_3
    //   178: isub
    //   179: iload_3
    //   180: invokestatic 33	java/lang/System:arraycopy	(Ljava/lang/Object;ILjava/lang/Object;II)V
    //   183: aload_2
    //   184: iload_3
    //   185: aload 7
    //   187: iconst_0
    //   188: iload_1
    //   189: iload_3
    //   190: isub
    //   191: invokestatic 33	java/lang/System:arraycopy	(Ljava/lang/Object;ILjava/lang/Object;II)V
    //   194: goto +47 -> 241
    //   197: iload_3
    //   198: ifle +6 -> 204
    //   201: goto +32 -> 233
    //   204: goto -90 -> 114
    //   207: aload_2
    //   208: iload_0
    //   209: aload 7
    //   211: iload_1
    //   212: iload_0
    //   213: isub
    //   214: iconst_1
    //   215: isub
    //   216: caload
    //   217: castore
    //   218: iload_0
    //   219: iconst_1
    //   220: iadd
    //   221: istore_0
    //   222: goto +84 -> 306
    //   225: goto -66 -> 159
    //   228: iconst_1
    //   229: istore_0
    //   230: goto -111 -> 119
    //   233: iconst_0
    //   234: istore_0
    //   235: goto -226 -> 9
    //   238: astore_2
    //   239: aload_2
    //   240: athrow
    //   241: iload 4
    //   243: ifeq +6 -> 249
    //   246: goto -200 -> 46
    //   249: aload 7
    //   251: astore_2
    //   252: goto -150 -> 102
    //   255: iload_1
    //   256: newarray char
    //   258: astore_2
    //   259: iconst_0
    //   260: istore_0
    //   261: goto +45 -> 306
    //   264: iload 5
    //   266: iload_1
    //   267: if_icmpge +6 -> 273
    //   270: goto +52 -> 322
    //   273: goto -76 -> 197
    //   276: getstatic 14	o/vY:ˎ	I
    //   279: bipush 31
    //   281: iadd
    //   282: istore 6
    //   284: iload 6
    //   286: sipush 128
    //   289: irem
    //   290: putstatic 12	o/vY:ˏ	I
    //   293: iload 6
    //   295: iconst_2
    //   296: irem
    //   297: ifeq +6 -> 303
    //   300: goto -153 -> 147
    //   303: goto -297 -> 6
    //   306: iload_0
    //   307: iload_1
    //   308: if_icmpge +6 -> 314
    //   311: goto -104 -> 207
    //   314: goto -311 -> 3
    //   317: iconst_0
    //   318: istore_0
    //   319: goto -200 -> 119
    //   322: aload 7
    //   324: iload 5
    //   326: iload_0
    //   327: aload_2
    //   328: iload 5
    //   330: caload
    //   331: iadd
    //   332: i2c
    //   333: castore
    //   334: aload 7
    //   336: iload 5
    //   338: aload 7
    //   340: iload 5
    //   342: caload
    //   343: getstatic 16	o/vY:ˋ	I
    //   346: isub
    //   347: i2c
    //   348: castore
    //   349: iload 5
    //   351: iconst_1
    //   352: iadd
    //   353: istore 5
    //   355: goto -91 -> 264
    // Local variable table:
    //   start	length	slot	name	signature
    //   0	358	0	paramInt1	int
    //   0	358	1	paramInt2	int
    //   0	358	2	paramArrayOfChar	char[]
    //   0	358	3	paramInt3	int
    //   0	358	4	paramBoolean	boolean
    //   41	313	5	i	int
    //   282	15	6	j	int
    //   38	301	7	arrayOfChar	char[]
    // Exception table:
    //   from	to	target	type
    //   163	172	72	java/lang/Exception
    //   172	183	238	java/lang/Exception
    //   183	194	238	java/lang/Exception
  }
  
  static Map<String, String> ˋ(Uri paramUri, Set<String> paramSet)
  {
    break label189;
    int i;
    for (;;)
    {
      switch (i)
      {
      default: 
        break label103;
        label35:
        i = 96;
      }
    }
    label68:
    Object localObject1;
    label74:
    label103:
    Object localObject2;
    for (;;)
    {
      i = ˎ + 15;
      ˏ = i % 128;
      if (i % 2 != 0) {
        break label261;
      }
      break;
      break label272;
      return localObject1;
      switch (i)
      {
      case 79: 
      default: 
        break label255;
        ((Map)localObject1).put(localObject2, paramUri.getQueryParameter((String)localObject2));
      }
    }
    label145:
    label189:
    label192:
    label225:
    label255:
    label261:
    label272:
    label299:
    for (;;)
    {
      Iterator localIterator;
      try
      {
        boolean bool = localIterator.hasNext();
        if (!bool)
        {
          break label68;
          i = 0;
          break label192;
          break label299;
        }
        localObject2 = (String)localIterator.next();
        if (!paramSet.contains(localObject2)) {
          break label35;
        }
      }
      catch (Exception paramUri)
      {
        throw paramUri;
      }
      break label299;
      for (;;)
      {
        i = 79;
        break label74;
        break label225;
        switch (i)
        {
        }
        break label145;
        do
        {
          i = 28;
          break label74;
          localObject1 = new LinkedHashMap();
          localObject2 = paramUri.getQueryParameterNames();
          try
          {
            localIterator = ((Set)localObject2).iterator();
          }
          catch (Exception paramUri)
          {
            throw paramUri;
          }
          i = null.length;
          return localObject1;
          i = 1;
          break label192;
          i = 74;
          break;
          i = ˎ + 123;
          ˏ = i % 128;
        } while (i % 2 != 0);
      }
    }
  }
  
  /* Error */
  static Map<String, String> ˋ(Map<String, String> paramMap, Set<String> paramSet)
  {
    // Byte code:
    //   0: goto +223 -> 223
    //   3: iload_3
    //   4: ldc 79
    //   6: iconst_1
    //   7: anewarray 4	java/lang/Object
    //   10: dup
    //   11: iconst_0
    //   12: aload 5
    //   14: aastore
    //   15: invokestatic 84	o/wv:ˋ	(ZLjava/lang/String;[Ljava/lang/Object;)V
    //   18: aload 4
    //   20: aload 5
    //   22: aload 6
    //   24: invokeinterface 46 3 0
    //   29: pop
    //   30: goto +591 -> 621
    //   33: iload_2
    //   34: lookupswitch	default:+26->60, 36:+602->636, 66:+566->600
    //   60: goto +576 -> 636
    //   63: aload 4
    //   65: invokestatic 90	java/util/Collections:unmodifiableMap	(Ljava/util/Map;)Ljava/util/Map;
    //   68: areturn
    //   69: bipush 36
    //   71: istore_2
    //   72: goto -39 -> 33
    //   75: goto +151 -> 226
    //   78: astore_0
    //   79: aload_0
    //   80: athrow
    //   81: iconst_0
    //   82: istore_3
    //   83: goto -80 -> 3
    //   86: getstatic 14	o/vY:ˎ	I
    //   89: bipush 91
    //   91: iadd
    //   92: istore_2
    //   93: iload_2
    //   94: sipush 128
    //   97: irem
    //   98: putstatic 12	o/vY:ˏ	I
    //   101: iload_2
    //   102: iconst_2
    //   103: irem
    //   104: ifeq +6 -> 110
    //   107: goto +572 -> 679
    //   110: goto +55 -> 165
    //   113: bipush 93
    //   115: istore_2
    //   116: goto +533 -> 649
    //   119: getstatic 14	o/vY:ˎ	I
    //   122: bipush 83
    //   124: iadd
    //   125: istore_2
    //   126: iload_2
    //   127: sipush 128
    //   130: irem
    //   131: putstatic 12	o/vY:ˏ	I
    //   134: iload_2
    //   135: iconst_2
    //   136: irem
    //   137: ifeq +6 -> 143
    //   140: goto +22 -> 162
    //   143: goto +93 -> 236
    //   146: bipush 43
    //   148: istore_2
    //   149: goto +500 -> 649
    //   152: iconst_1
    //   153: istore_3
    //   154: goto -68 -> 86
    //   157: iconst_1
    //   158: istore_2
    //   159: goto +409 -> 568
    //   162: goto +74 -> 236
    //   165: goto -162 -> 3
    //   168: getstatic 14	o/vY:ˎ	I
    //   171: bipush 57
    //   173: iadd
    //   174: istore_2
    //   175: iload_2
    //   176: sipush 128
    //   179: irem
    //   180: putstatic 12	o/vY:ˏ	I
    //   183: iload_2
    //   184: iconst_2
    //   185: irem
    //   186: ifeq +5 -> 191
    //   189: aload_0
    //   190: areturn
    //   191: aload_0
    //   192: areturn
    //   193: astore_0
    //   194: aload_0
    //   195: athrow
    //   196: getstatic 14	o/vY:ˎ	I
    //   199: bipush 7
    //   201: iadd
    //   202: istore_2
    //   203: iload_2
    //   204: sipush 128
    //   207: irem
    //   208: putstatic 12	o/vY:ˏ	I
    //   211: iload_2
    //   212: iconst_2
    //   213: irem
    //   214: ifeq +6 -> 220
    //   217: goto -142 -> 75
    //   220: goto +6 -> 226
    //   223: goto -27 -> 196
    //   226: aload_0
    //   227: ifnonnull +6 -> 233
    //   230: goto -161 -> 69
    //   233: goto +410 -> 643
    //   236: aload_0
    //   237: invokeinterface 56 1 0
    //   242: astore 5
    //   244: aload 5
    //   246: checkcast 92	java/util/Map$Entry
    //   249: astore 6
    //   251: aload 6
    //   253: invokeinterface 95 1 0
    //   258: astore 5
    //   260: aload 5
    //   262: checkcast 23	java/lang/String
    //   265: astore 5
    //   267: aload 6
    //   269: invokeinterface 98 1 0
    //   274: astore 6
    //   276: aload 6
    //   278: checkcast 23	java/lang/String
    //   281: astore 6
    //   283: aload 5
    //   285: sipush 197
    //   288: bipush 40
    //   290: bipush 40
    //   292: newarray char
    //   294: dup
    //   295: iconst_0
    //   296: ldc 99
    //   298: castore
    //   299: dup
    //   300: iconst_1
    //   301: ldc 100
    //   303: castore
    //   304: dup
    //   305: iconst_2
    //   306: ldc 99
    //   308: castore
    //   309: dup
    //   310: iconst_3
    //   311: ldc 101
    //   313: castore
    //   314: dup
    //   315: iconst_4
    //   316: ldc 102
    //   318: castore
    //   319: dup
    //   320: iconst_5
    //   321: ldc 103
    //   323: castore
    //   324: dup
    //   325: bipush 6
    //   327: ldc 102
    //   329: castore
    //   330: dup
    //   331: bipush 7
    //   333: ldc 100
    //   335: castore
    //   336: dup
    //   337: bipush 8
    //   339: ldc 104
    //   341: castore
    //   342: dup
    //   343: bipush 9
    //   345: ldc 105
    //   347: castore
    //   348: dup
    //   349: bipush 10
    //   351: ldc 102
    //   353: castore
    //   354: dup
    //   355: bipush 11
    //   357: ldc 106
    //   359: castore
    //   360: dup
    //   361: bipush 12
    //   363: ldc 107
    //   365: castore
    //   366: dup
    //   367: bipush 13
    //   369: ldc 104
    //   371: castore
    //   372: dup
    //   373: bipush 14
    //   375: ldc 108
    //   377: castore
    //   378: dup
    //   379: bipush 15
    //   381: ldc 99
    //   383: castore
    //   384: dup
    //   385: bipush 16
    //   387: ldc 109
    //   389: castore
    //   390: dup
    //   391: bipush 17
    //   393: ldc 109
    //   395: castore
    //   396: dup
    //   397: bipush 18
    //   399: ldc 110
    //   401: castore
    //   402: dup
    //   403: bipush 19
    //   405: ldc 103
    //   407: castore
    //   408: dup
    //   409: bipush 20
    //   411: ldc 104
    //   413: castore
    //   414: dup
    //   415: bipush 21
    //   417: ldc 111
    //   419: castore
    //   420: dup
    //   421: bipush 22
    //   423: ldc 102
    //   425: castore
    //   426: dup
    //   427: bipush 23
    //   429: ldc 104
    //   431: castore
    //   432: dup
    //   433: bipush 24
    //   435: ldc 109
    //   437: castore
    //   438: dup
    //   439: bipush 25
    //   441: ldc 112
    //   443: castore
    //   444: dup
    //   445: bipush 26
    //   447: ldc 113
    //   449: castore
    //   450: dup
    //   451: bipush 27
    //   453: ldc 113
    //   455: castore
    //   456: dup
    //   457: bipush 28
    //   459: ldc 99
    //   461: castore
    //   462: dup
    //   463: bipush 29
    //   465: ldc 114
    //   467: castore
    //   468: dup
    //   469: bipush 30
    //   471: ldc 114
    //   473: castore
    //   474: dup
    //   475: bipush 31
    //   477: ldc 115
    //   479: castore
    //   480: dup
    //   481: bipush 32
    //   483: ldc 103
    //   485: castore
    //   486: dup
    //   487: bipush 33
    //   489: ldc 115
    //   491: castore
    //   492: dup
    //   493: bipush 34
    //   495: ldc 110
    //   497: castore
    //   498: dup
    //   499: bipush 35
    //   501: ldc 109
    //   503: castore
    //   504: dup
    //   505: bipush 36
    //   507: ldc 99
    //   509: castore
    //   510: dup
    //   511: bipush 37
    //   513: ldc 113
    //   515: castore
    //   516: dup
    //   517: bipush 38
    //   519: ldc 104
    //   521: castore
    //   522: dup
    //   523: bipush 39
    //   525: ldc 116
    //   527: castore
    //   528: bipush 28
    //   530: iconst_0
    //   531: invokestatic 118	o/vY:ˊ	(II[CIZ)Ljava/lang/String;
    //   534: invokevirtual 122	java/lang/String:intern	()Ljava/lang/String;
    //   537: invokestatic 124	o/wv:ˋ	(Ljava/lang/Object;Ljava/lang/Object;)Ljava/lang/Object;
    //   540: pop
    //   541: aload 6
    //   543: ldc 126
    //   545: invokestatic 124	o/wv:ˋ	(Ljava/lang/Object;Ljava/lang/Object;)Ljava/lang/Object;
    //   548: pop
    //   549: aload_1
    //   550: aload 5
    //   552: invokeinterface 62 2 0
    //   557: istore_3
    //   558: iload_3
    //   559: ifne +6 -> 565
    //   562: goto -405 -> 157
    //   565: goto +30 -> 595
    //   568: iload_2
    //   569: tableswitch	default:+23->592, 0:+-488->81, 1:+-417->152
    //   592: goto -440 -> 152
    //   595: iconst_0
    //   596: istore_2
    //   597: goto -29 -> 568
    //   600: new 64	java/util/LinkedHashMap
    //   603: dup
    //   604: invokespecial 66	java/util/LinkedHashMap:<init>	()V
    //   607: astore 4
    //   609: aload_0
    //   610: invokeinterface 129 1 0
    //   615: invokeinterface 74 1 0
    //   620: astore_0
    //   621: aload_0
    //   622: invokeinterface 52 1 0
    //   627: ifeq +6 -> 633
    //   630: goto -517 -> 113
    //   633: goto -487 -> 146
    //   636: invokestatic 133	java/util/Collections:emptyMap	()Ljava/util/Map;
    //   639: astore_0
    //   640: goto -472 -> 168
    //   643: bipush 66
    //   645: istore_2
    //   646: goto -613 -> 33
    //   649: iload_2
    //   650: lookupswitch	default:+26->676, 43:+-587->63, 93:+-531->119
    //   676: goto -613 -> 63
    //   679: goto -676 -> 3
    // Local variable table:
    //   start	length	slot	name	signature
    //   0	682	0	paramMap	Map<String, String>
    //   0	682	1	paramSet	Set<String>
    //   33	617	2	i	int
    //   3	556	3	bool	boolean
    //   18	590	4	localObject1	Object
    //   12	539	5	localObject2	Object
    //   22	520	6	localObject3	Object
    // Exception table:
    //   from	to	target	type
    //   236	244	78	java/lang/Exception
    //   244	251	193	java/lang/Exception
    //   251	260	193	java/lang/Exception
    //   260	267	193	java/lang/Exception
    //   267	276	193	java/lang/Exception
    //   276	558	193	java/lang/Exception
  }
  
  static Set<String> ˋ(String... paramVarArgs)
  {
    break label117;
    int i;
    for (;;)
    {
      i = paramVarArgs.length;
      throw new NullPointerException();
      i = 0;
      break label79;
      label19:
      i = 9;
      break;
      label25:
      i = 1;
      break label79;
      for (;;)
      {
        i = 54;
        break label123;
        i = 0;
        break label186;
        i = ˏ + 17;
        ˎ = i % 128;
        if (i % 2 == 0) {
          break;
        }
        break label25;
        if (paramVarArgs.length == 0) {
          break label19;
        }
      }
      label79:
      switch (i)
      {
      }
    }
    for (;;)
    {
      if (paramVarArgs != null) {
        break label211;
      }
      break;
      label117:
      label123:
      do
      {
        break;
        switch (i)
        {
        default: 
          break;
        case 9: 
          return Collections.emptySet();
          i = ˏ + 43;
          ˎ = i % 128;
        }
      } while (i % 2 == 0);
    }
    for (;;)
    {
      label186:
      switch (i)
      {
      }
      break;
      label211:
      i = 1;
    }
    return Collections.unmodifiableSet(new HashSet(Arrays.asList(paramVarArgs)));
  }
  
  /* Error */
  static Map<String, String> ˎ(org.json.JSONObject paramJSONObject, Set<String> paramSet)
  {
    // Byte code:
    //   0: goto +211 -> 211
    //   3: new 137	java/lang/NullPointerException
    //   6: dup
    //   7: invokespecial 138	java/lang/NullPointerException:<init>	()V
    //   10: athrow
    //   11: goto +106 -> 117
    //   14: bipush 39
    //   16: istore_2
    //   17: goto +36 -> 53
    //   20: goto +232 -> 252
    //   23: getstatic 14	o/vY:ˎ	I
    //   26: bipush 55
    //   28: iadd
    //   29: istore_2
    //   30: iload_2
    //   31: sipush 128
    //   34: irem
    //   35: putstatic 12	o/vY:ˏ	I
    //   38: iload_2
    //   39: iconst_2
    //   40: irem
    //   41: ifeq +6 -> 47
    //   44: goto +317 -> 361
    //   47: goto +320 -> 367
    //   50: goto +145 -> 195
    //   53: iload_2
    //   54: lookupswitch	default:+26->80, 36:+-51->3, 39:+35->89
    //   80: aload 4
    //   82: areturn
    //   83: bipush 43
    //   85: istore_2
    //   86: goto +65 -> 151
    //   89: aload 4
    //   91: areturn
    //   92: goto +125 -> 217
    //   95: aload 4
    //   97: aload 6
    //   99: aload_0
    //   100: aload 6
    //   102: invokevirtual 164	org/json/JSONObject:get	(Ljava/lang/String;)Ljava/lang/Object;
    //   105: invokevirtual 167	java/lang/Object:toString	()Ljava/lang/String;
    //   108: invokeinterface 46 3 0
    //   113: pop
    //   114: goto -91 -> 23
    //   117: goto +78 -> 195
    //   120: iload_2
    //   121: lookupswitch	default:+27->148, 41:+-110->11, 61:+93->214
    //   148: goto +66 -> 214
    //   151: iload_2
    //   152: lookupswitch	default:+28->180, 43:+-57->95, 67:+-35->117
    //   180: goto -85 -> 95
    //   183: astore_0
    //   184: aload_0
    //   185: athrow
    //   186: goto +9 -> 195
    //   189: bipush 67
    //   191: istore_2
    //   192: goto -41 -> 151
    //   195: aload 5
    //   197: invokeinterface 52 1 0
    //   202: ifeq +6 -> 208
    //   205: goto +106 -> 311
    //   208: goto -188 -> 20
    //   211: goto +132 -> 343
    //   214: goto -97 -> 117
    //   217: aload 5
    //   219: invokeinterface 56 1 0
    //   224: astore 6
    //   226: aload 6
    //   228: checkcast 23	java/lang/String
    //   231: astore 6
    //   233: aload_1
    //   234: aload 6
    //   236: invokeinterface 62 2 0
    //   241: istore_3
    //   242: iload_3
    //   243: ifne +6 -> 249
    //   246: goto -163 -> 83
    //   249: goto -60 -> 189
    //   252: getstatic 12	o/vY:ˏ	I
    //   255: bipush 63
    //   257: iadd
    //   258: istore_2
    //   259: iload_2
    //   260: sipush 128
    //   263: irem
    //   264: putstatic 14	o/vY:ˎ	I
    //   267: iload_2
    //   268: iconst_2
    //   269: irem
    //   270: ifne +6 -> 276
    //   273: goto +64 -> 337
    //   276: goto -262 -> 14
    //   279: getstatic 12	o/vY:ˏ	I
    //   282: istore_2
    //   283: iload_2
    //   284: bipush 71
    //   286: iadd
    //   287: istore_2
    //   288: iload_2
    //   289: sipush 128
    //   292: irem
    //   293: putstatic 14	o/vY:ˎ	I
    //   296: iload_2
    //   297: iconst_2
    //   298: irem
    //   299: ifne +6 -> 305
    //   302: goto -116 -> 186
    //   305: goto -255 -> 50
    //   308: astore_0
    //   309: aload_0
    //   310: athrow
    //   311: getstatic 14	o/vY:ˎ	I
    //   314: iconst_5
    //   315: iadd
    //   316: istore_2
    //   317: iload_2
    //   318: sipush 128
    //   321: irem
    //   322: putstatic 12	o/vY:ˏ	I
    //   325: iload_2
    //   326: iconst_2
    //   327: irem
    //   328: ifeq +6 -> 334
    //   331: goto -239 -> 92
    //   334: goto -117 -> 217
    //   337: bipush 36
    //   339: istore_2
    //   340: goto -287 -> 53
    //   343: new 64	java/util/LinkedHashMap
    //   346: dup
    //   347: invokespecial 66	java/util/LinkedHashMap:<init>	()V
    //   350: astore 4
    //   352: aload_0
    //   353: invokevirtual 170	org/json/JSONObject:keys	()Ljava/util/Iterator;
    //   356: astore 5
    //   358: goto -79 -> 279
    //   361: bipush 41
    //   363: istore_2
    //   364: goto -244 -> 120
    //   367: bipush 61
    //   369: istore_2
    //   370: goto -250 -> 120
    // Local variable table:
    //   start	length	slot	name	signature
    //   0	373	0	paramJSONObject	org.json.JSONObject
    //   0	373	1	paramSet	Set<String>
    //   16	354	2	i	int
    //   241	2	3	bool	boolean
    //   80	271	4	localObject1	Object
    //   195	162	5	localIterator	Iterator
    //   97	138	6	localObject2	Object
    // Exception table:
    //   from	to	target	type
    //   217	226	183	java/lang/Exception
    //   226	233	183	java/lang/Exception
    //   233	242	183	java/lang/Exception
    //   279	283	308	java/lang/Exception
    //   288	296	308	java/lang/Exception
  }
}
