package o;

import java.util.HashSet;

public final class w
  extends ᐸ
{
  public static final iF ʻॱ;
  private static int ʼॱ;
  private static char[] ʽॱ;
  private static final HashSet<String> ʾ;
  private static int ˈ;
  
  static
  {
    for (;;)
    {
      int i = ˈ + 75;
      ʼॱ = i % 128;
      if (i % 2 == 0) {
        return;
      }
      return;
      ˈ = 0;
      ʼॱ = 1;
      ˋॱ();
      ʻॱ = new iF(null);
      ʾ = new HashSet();
    }
  }
  
  /* Error */
  public w(ᐸ.If paramIf)
  {
    // Byte code:
    //   0: goto +6 -> 6
    //   3: astore_1
    //   4: aload_1
    //   5: athrow
    //   6: bipush 7
    //   8: newarray byte
    //   10: dup
    //   11: iconst_0
    //   12: ldc 43
    //   14: bastore
    //   15: dup
    //   16: iconst_1
    //   17: ldc 44
    //   19: bastore
    //   20: dup
    //   21: iconst_2
    //   22: ldc 43
    //   24: bastore
    //   25: dup
    //   26: iconst_3
    //   27: ldc 44
    //   29: bastore
    //   30: dup
    //   31: iconst_4
    //   32: ldc 43
    //   34: bastore
    //   35: dup
    //   36: iconst_5
    //   37: ldc 44
    //   39: bastore
    //   40: dup
    //   41: bipush 6
    //   43: ldc 44
    //   45: bastore
    //   46: iconst_4
    //   47: newarray int
    //   49: dup
    //   50: iconst_0
    //   51: iconst_0
    //   52: iastore
    //   53: dup
    //   54: iconst_1
    //   55: bipush 7
    //   57: iastore
    //   58: dup
    //   59: iconst_2
    //   60: iconst_0
    //   61: iastore
    //   62: dup
    //   63: iconst_3
    //   64: iconst_0
    //   65: iastore
    //   66: iconst_0
    //   67: invokestatic 48	o/w:ˋ	([B[IZ)Ljava/lang/String;
    //   70: astore_2
    //   71: aload_2
    //   72: invokevirtual 54	java/lang/String:intern	()Ljava/lang/String;
    //   75: astore_2
    //   76: aload_1
    //   77: aload_2
    //   78: invokestatic 60	o/vq:ˎ	(Ljava/lang/Object;Ljava/lang/String;)V
    //   81: aload_0
    //   82: aload_1
    //   83: invokespecial 62	o/ᐸ:<init>	(Lo/ᐸ$If;)V
    //   86: return
    //   87: astore_1
    //   88: aload_1
    //   89: athrow
    // Local variable table:
    //   start	length	slot	name	signature
    //   0	90	0	this	w
    //   0	90	1	paramIf	ᐸ.If
    //   70	8	2	str	String
    // Exception table:
    //   from	to	target	type
    //   71	76	3	java/lang/Exception
    //   76	81	3	java/lang/Exception
    //   81	86	3	java/lang/Exception
    //   6	71	87	java/lang/Exception
  }
  
  private static String ˋ(byte[] paramArrayOfByte, int[] paramArrayOfInt, boolean paramBoolean)
  {
    int j;
    label33:
    int m;
    char[] arrayOfChar1;
    int i;
    label50:
    label94:
    label147:
    label186:
    int n;
    label223:
    int i1;
    for (;;)
    {
      try
      {
        j = ˈ + 119;
        try
        {
          ʼॱ = j % 128;
          if (j % 2 == 0) {
            break;
          }
        }
        catch (Exception paramArrayOfByte)
        {
          throw paramArrayOfByte;
        }
        j = 0;
        continue;
        arrayOfChar1 = new char[m];
        i = 0;
        break label275;
        switch (j)
        {
        case 1: 
        default: 
          paramArrayOfByte[i] = ((char)(paramArrayOfByte[i] - paramArrayOfInt[2]));
          i += 1;
          break label639;
          i = ˈ + 19;
          ʼॱ = i % 128;
          if (i % 2 == 0) {
            break label596;
          }
          return paramArrayOfByte;
          break label243;
          if (paramArrayOfByte[j] == 1) {
            break label695;
          }
          break label651;
          if (paramBoolean) {
            continue;
          }
          continue;
          continue;
          i = 45;
          break label715;
          i = ˈ + 77;
          ʼॱ = i % 128;
          if (i % 2 == 0) {
            break label270;
          }
          break label461;
          if (n > 0) {
            continue;
          }
          break label627;
          switch (j)
          {
          }
          break;
        }
      }
      catch (Exception paramArrayOfByte)
      {
        label234:
        throw paramArrayOfByte;
      }
      if (i1 > 0) {
        break label549;
      }
      continue;
      paramArrayOfByte = arrayOfChar1;
      continue;
      label243:
      i = ˈ + 39;
      ʼॱ = i % 128;
      if (i % 2 == 0) {
        break label458;
      }
      break label398;
      label270:
      i = 1;
      break label395;
      label275:
      if (i < m) {
        break label515;
      }
      break label682;
      label287:
      i = ˈ + 113;
      ʼॱ = i % 128;
      if (i % 2 == 0) {
        break label601;
      }
    }
    for (;;)
    {
      label314:
      if (j < m) {
        break label688;
      }
      break;
      label327:
      i = arrayOfChar1[j];
      j += 1;
      continue;
      arrayOfChar1 = new char[m];
      i = 0;
      j = 1;
    }
    for (;;)
    {
      arrayOfChar1 = new char[m];
      i = 0;
      j = 0;
      break label314;
      j = 0;
      break label50;
      arrayOfChar1[i] = paramArrayOfByte[(m - i - 1)];
      i += 1;
      break label275;
      label395:
      label398:
      char[] arrayOfChar2;
      for (;;)
      {
        break label639;
        label452:
        label458:
        for (;;)
        {
          i = paramArrayOfInt[0];
          m = paramArrayOfInt[1];
          n = paramArrayOfInt[2];
          i1 = paramArrayOfInt[3];
          arrayOfChar1 = ʽॱ;
          arrayOfChar2 = new char[m];
          System.arraycopy(arrayOfChar1, i, arrayOfChar2, 0, m);
          if (paramArrayOfByte != null) {
            break label287;
          }
          paramArrayOfByte = arrayOfChar2;
          break label223;
          j = 1;
          break;
        }
        label461:
        i = 0;
        continue;
        paramArrayOfByte[i] = ((char)(paramArrayOfByte[i] + paramArrayOfInt[4]));
        i += 88;
      }
      for (;;)
      {
        label485:
        switch (k)
        {
        }
        break label234;
        label515:
        j = ˈ;
        j += 11;
        ʼॱ = j % 128;
        if (j % 2 == 0) {
          break label33;
        }
        break label452;
        label549:
        arrayOfChar1 = new char[m];
        System.arraycopy(paramArrayOfByte, 0, arrayOfChar1, 0, m);
        System.arraycopy(arrayOfChar1, 0, paramArrayOfByte, m - i1, i1);
        System.arraycopy(arrayOfChar1, i1, paramArrayOfByte, 0, m - i1);
        break label147;
        label596:
        return paramArrayOfByte;
        for (;;)
        {
          break label186;
          label601:
          i = 93;
          break label715;
          arrayOfChar1[i] = paramArrayOfByte[(m >> i >> 1)];
          i += 18;
          break label275;
          for (;;)
          {
            label627:
            paramArrayOfByte = new String(paramArrayOfByte);
            break label94;
            label639:
            if (i < m) {
              break;
            }
          }
          label651:
          arrayOfChar1[j] = ((char)((arrayOfChar2[j] << '\001') - i));
          break label327;
          k = 39;
          break label485;
          j = 1;
          break label50;
          label682:
          paramArrayOfByte = arrayOfChar1;
        }
        label688:
        int k = 41;
      }
      label695:
      arrayOfChar1[j] = ((char)((arrayOfChar2[j] << '\001') + 1 - i));
      break label327;
      label715:
      switch (i)
      {
      }
    }
  }
  
  static void ˋॱ()
  {
    ʽॱ = new char[] { 49, 107, 111, 106, 104, 100, 107 };
  }
  
  /* Error */
  public static final void ॱॱ()
  {
    // Byte code:
    //   0: goto +53 -> 53
    //   3: astore_1
    //   4: aload_1
    //   5: athrow
    //   6: getstatic 32	o/w:ʻॱ	Lo/w$iF;
    //   9: astore_1
    //   10: aload_1
    //   11: invokevirtual 87	o/w$iF:ˋ	()V
    //   14: goto +9 -> 23
    //   17: iconst_0
    //   18: istore_0
    //   19: goto +40 -> 59
    //   22: return
    //   23: getstatic 21	o/w:ˈ	I
    //   26: bipush 39
    //   28: iadd
    //   29: istore_0
    //   30: iload_0
    //   31: sipush 128
    //   34: irem
    //   35: putstatic 23	o/w:ʼॱ	I
    //   38: iload_0
    //   39: iconst_2
    //   40: irem
    //   41: ifne +6 -> 47
    //   44: goto +74 -> 118
    //   47: goto -30 -> 17
    //   50: goto -44 -> 6
    //   53: goto +34 -> 87
    //   56: astore_1
    //   57: aload_1
    //   58: athrow
    //   59: iload_0
    //   60: tableswitch	default:+24->84, 0:+-38->22, 1:+54->114
    //   84: goto +30 -> 114
    //   87: getstatic 21	o/w:ˈ	I
    //   90: bipush 109
    //   92: iadd
    //   93: istore_0
    //   94: iload_0
    //   95: sipush 128
    //   98: irem
    //   99: putstatic 23	o/w:ʼॱ	I
    //   102: iload_0
    //   103: iconst_2
    //   104: irem
    //   105: ifne +6 -> 111
    //   108: goto -58 -> 50
    //   111: goto -105 -> 6
    //   114: aconst_null
    //   115: arraylength
    //   116: istore_0
    //   117: return
    //   118: iconst_1
    //   119: istore_0
    //   120: goto -61 -> 59
    // Local variable table:
    //   start	length	slot	name	signature
    //   18	102	0	i	int
    //   3	2	1	localException1	Exception
    //   9	2	1	localIF	iF
    //   56	2	1	localException2	Exception
    // Exception table:
    //   from	to	target	type
    //   6	10	3	java/lang/Exception
    //   10	14	3	java/lang/Exception
    //   10	14	56	java/lang/Exception
  }
  
  public void cancel()
  {
    for (;;)
    {
      label31:
      String str;
      switch (i)
      {
      default: 
        break;
        break label231;
        for (;;)
        {
          i = ˈ + 83;
          ʼॱ = i % 128;
          if (i % 2 == 0) {
            break label31;
          }
          break label231;
          i = 0;
          break;
        }
      case 1: 
        label176:
        label181:
        for (;;)
        {
          i = ˈ + 55;
          ʼॱ = i % 128;
          if (i % 2 == 0) {
            break label223;
          }
          return;
          i = ʼॱ + 109;
          ˈ = i % 128;
          if (i % 2 != 0) {
            break;
          }
          break label244;
          for (;;)
          {
            switch (i)
            {
            case 0: 
            default: 
              break label181;
              str = ˏ().getClass().getName();
              iF.ˊ(ʻॱ).remove(str);
              super.cancel();
              break label181;
              i = 0;
            }
          }
        }
      }
      for (;;)
      {
        i = 1;
        break;
        str = ˏ().getClass().getName();
        iF.ˊ(ʻॱ).remove(str);
        super.cancel();
        i = 47 / 0;
        break label181;
        label223:
        throw new NullPointerException();
        label231:
        if (isShowing()) {
          break label176;
        }
      }
      label244:
      int i = 1;
    }
  }
  
  /* Error */
  public void dismiss()
  {
    // Byte code:
    //   0: goto +125 -> 125
    //   3: astore_2
    //   4: aload_2
    //   5: athrow
    //   6: getstatic 21	o/w:ˈ	I
    //   9: bipush 89
    //   11: iadd
    //   12: istore_1
    //   13: iload_1
    //   14: sipush 128
    //   17: irem
    //   18: putstatic 23	o/w:ʼॱ	I
    //   21: iload_1
    //   22: iconst_2
    //   23: irem
    //   24: ifne +6 -> 30
    //   27: goto +51 -> 78
    //   30: goto +129 -> 159
    //   33: aload_0
    //   34: invokevirtual 117	o/w:isShowing	()Z
    //   37: ifeq +6 -> 43
    //   40: goto +79 -> 119
    //   43: goto +67 -> 110
    //   46: aload_0
    //   47: invokevirtual 92	o/w:ˏ	()Lo/ᐸ$If;
    //   50: invokevirtual 98	java/lang/Object:getClass	()Ljava/lang/Class;
    //   53: invokevirtual 103	java/lang/Class:getName	()Ljava/lang/String;
    //   56: astore_2
    //   57: getstatic 32	o/w:ʻॱ	Lo/w$iF;
    //   60: invokestatic 107	o/w$iF:ˊ	(Lo/w$iF;)Ljava/util/HashSet;
    //   63: aload_2
    //   64: invokevirtual 111	java/util/HashSet:remove	(Ljava/lang/Object;)Z
    //   67: pop
    //   68: aload_0
    //   69: invokespecial 120	o/ᐸ:dismiss	()V
    //   72: goto -66 -> 6
    //   75: goto -42 -> 33
    //   78: goto +81 -> 159
    //   81: getstatic 21	o/w:ˈ	I
    //   84: istore_1
    //   85: iload_1
    //   86: bipush 29
    //   88: iadd
    //   89: istore_1
    //   90: iload_1
    //   91: sipush 128
    //   94: irem
    //   95: putstatic 23	o/w:ʼॱ	I
    //   98: iload_1
    //   99: iconst_2
    //   100: irem
    //   101: ifne +6 -> 107
    //   104: goto -29 -> 75
    //   107: goto -74 -> 33
    //   110: bipush 97
    //   112: istore_1
    //   113: goto +15 -> 128
    //   116: goto -70 -> 46
    //   119: bipush 69
    //   121: istore_1
    //   122: goto +6 -> 128
    //   125: goto -44 -> 81
    //   128: iload_1
    //   129: lookupswitch	default:+27->156, 69:+31->160, 97:+30->159
    //   156: goto +4 -> 160
    //   159: return
    //   160: getstatic 23	o/w:ʼॱ	I
    //   163: bipush 23
    //   165: iadd
    //   166: istore_1
    //   167: iload_1
    //   168: sipush 128
    //   171: irem
    //   172: putstatic 21	o/w:ˈ	I
    //   175: iload_1
    //   176: iconst_2
    //   177: irem
    //   178: ifeq +6 -> 184
    //   181: goto -65 -> 116
    //   184: goto -138 -> 46
    // Local variable table:
    //   start	length	slot	name	signature
    //   0	187	0	this	w
    //   12	166	1	i	int
    //   3	2	2	localException	Exception
    //   56	8	2	str	String
    // Exception table:
    //   from	to	target	type
    //   81	85	3	java/lang/Exception
    //   90	98	3	java/lang/Exception
  }
  
  /* Error */
  public void show()
  {
    // Byte code:
    //   0: goto +39 -> 39
    //   3: bipush 53
    //   5: istore_1
    //   6: goto +94 -> 100
    //   9: astore_3
    //   10: aload_3
    //   11: athrow
    //   12: iload_1
    //   13: tableswitch	default:+23->36, 0:+53->66, 1:+154->167
    //   36: goto +131 -> 167
    //   39: getstatic 23	o/w:ʼॱ	I
    //   42: bipush 27
    //   44: iadd
    //   45: istore_1
    //   46: iload_1
    //   47: sipush 128
    //   50: irem
    //   51: putstatic 21	o/w:ˈ	I
    //   54: iload_1
    //   55: iconst_2
    //   56: irem
    //   57: ifeq +6 -> 63
    //   60: goto +71 -> 131
    //   63: goto +193 -> 256
    //   66: aload_0
    //   67: invokevirtual 92	o/w:ˏ	()Lo/ᐸ$If;
    //   70: invokevirtual 98	java/lang/Object:getClass	()Ljava/lang/Class;
    //   73: invokevirtual 103	java/lang/Class:getName	()Ljava/lang/String;
    //   76: astore_3
    //   77: getstatic 32	o/w:ʻॱ	Lo/w$iF;
    //   80: invokestatic 107	o/w$iF:ˊ	(Lo/w$iF;)Ljava/util/HashSet;
    //   83: aload_3
    //   84: invokevirtual 124	java/util/HashSet:contains	(Ljava/lang/Object;)Z
    //   87: istore_2
    //   88: aconst_null
    //   89: arraylength
    //   90: istore_1
    //   91: iload_2
    //   92: ifne +6 -> 98
    //   95: goto +109 -> 204
    //   98: return
    //   99: return
    //   100: iload_1
    //   101: lookupswitch	default:+27->128, 15:+35->136, 53:+129->230
    //   128: goto +8 -> 136
    //   131: iconst_0
    //   132: istore_1
    //   133: goto -121 -> 12
    //   136: getstatic 32	o/w:ʻॱ	Lo/w$iF;
    //   139: astore 4
    //   141: aload 4
    //   143: invokestatic 107	o/w$iF:ˊ	(Lo/w$iF;)Ljava/util/HashSet;
    //   146: astore 4
    //   148: aload 4
    //   150: aload_3
    //   151: invokevirtual 127	java/util/HashSet:add	(Ljava/lang/Object;)Z
    //   154: pop
    //   155: aload_0
    //   156: invokespecial 129	o/ᐸ:show	()V
    //   159: bipush 40
    //   161: iconst_0
    //   162: idiv
    //   163: istore_1
    //   164: goto -65 -> 99
    //   167: aload_0
    //   168: invokevirtual 92	o/w:ˏ	()Lo/ᐸ$If;
    //   171: invokevirtual 98	java/lang/Object:getClass	()Ljava/lang/Class;
    //   174: invokevirtual 103	java/lang/Class:getName	()Ljava/lang/String;
    //   177: astore_3
    //   178: getstatic 32	o/w:ʻॱ	Lo/w$iF;
    //   181: invokestatic 107	o/w$iF:ˊ	(Lo/w$iF;)Ljava/util/HashSet;
    //   184: aload_3
    //   185: invokevirtual 124	java/util/HashSet:contains	(Ljava/lang/Object;)Z
    //   188: ifne +6 -> 194
    //   191: goto +13 -> 204
    //   194: return
    //   195: astore_3
    //   196: aload_3
    //   197: athrow
    //   198: bipush 15
    //   200: istore_1
    //   201: goto -101 -> 100
    //   204: getstatic 21	o/w:ˈ	I
    //   207: iconst_1
    //   208: iadd
    //   209: istore_1
    //   210: iload_1
    //   211: sipush 128
    //   214: irem
    //   215: putstatic 23	o/w:ʼॱ	I
    //   218: iload_1
    //   219: iconst_2
    //   220: irem
    //   221: ifne +6 -> 227
    //   224: goto -26 -> 198
    //   227: goto -224 -> 3
    //   230: getstatic 32	o/w:ʻॱ	Lo/w$iF;
    //   233: astore 4
    //   235: aload 4
    //   237: invokestatic 107	o/w$iF:ˊ	(Lo/w$iF;)Ljava/util/HashSet;
    //   240: astore 4
    //   242: aload 4
    //   244: aload_3
    //   245: invokevirtual 127	java/util/HashSet:add	(Ljava/lang/Object;)Z
    //   248: pop
    //   249: aload_0
    //   250: invokespecial 129	o/ᐸ:show	()V
    //   253: goto -154 -> 99
    //   256: iconst_1
    //   257: istore_1
    //   258: goto -246 -> 12
    // Local variable table:
    //   start	length	slot	name	signature
    //   0	261	0	this	w
    //   5	253	1	i	int
    //   87	5	2	bool	boolean
    //   9	2	3	localException1	Exception
    //   76	109	3	str	String
    //   195	50	3	localException2	Exception
    //   139	104	4	localObject	Object
    // Exception table:
    //   from	to	target	type
    //   141	148	9	java/lang/Exception
    //   230	235	9	java/lang/Exception
    //   235	242	9	java/lang/Exception
    //   242	249	9	java/lang/Exception
    //   249	253	9	java/lang/Exception
    //   136	141	195	java/lang/Exception
  }
  
  public static final class iF
  {
    private iF() {}
    
    private final HashSet<String> ˊ()
    {
      return w.ʽ();
    }
    
    public final void ˋ()
    {
      ((iF)this).ˊ().clear();
    }
  }
}
