package o;

import android.net.Uri;
import java.util.ArrayList;
import java.util.List;
import org.json.JSONArray;
import org.json.JSONException;
import org.json.JSONObject;

final class wn
{
  private static int ˎ = 0;
  private static int[] ˏ = { 662865153, -15335744, -61001629, -1334690200, -1024155438, 1218834085, -311526071, 507806185, 1421849661, 1773624186, 645104397, 2070264709, 2073029439, -262708720, -479426609, -1643026120, -1409135947, -1068818063 };
  private static int ॱ = 1;
  
  /* Error */
  public static java.util.Map<String, String> ʼ(JSONObject paramJSONObject, String paramString)
  {
    // Byte code:
    //   0: new 59	java/util/LinkedHashMap
    //   3: dup
    //   4: invokespecial 62	java/util/LinkedHashMap:<init>	()V
    //   7: astore_3
    //   8: aload_0
    //   9: ldc 64
    //   11: invokestatic 69	o/wv:ˋ	(Ljava/lang/Object;Ljava/lang/Object;)Ljava/lang/Object;
    //   14: pop
    //   15: aload_1
    //   16: ldc 71
    //   18: invokestatic 69	o/wv:ˋ	(Ljava/lang/Object;Ljava/lang/Object;)Ljava/lang/Object;
    //   21: pop
    //   22: aload_0
    //   23: aload_1
    //   24: invokevirtual 77	org/json/JSONObject:has	(Ljava/lang/String;)Z
    //   27: ifne +6 -> 33
    //   30: goto +42 -> 72
    //   33: goto +212 -> 245
    //   36: goto +3 -> 39
    //   39: aload 4
    //   41: invokeinterface 83 1 0
    //   46: ifeq +6 -> 52
    //   49: goto +17 -> 66
    //   52: goto +73 -> 125
    //   55: iconst_0
    //   56: istore_2
    //   57: goto +239 -> 296
    //   60: bipush 8
    //   62: istore_2
    //   63: goto +145 -> 208
    //   66: bipush 39
    //   68: istore_2
    //   69: goto +191 -> 260
    //   72: getstatic 30	o/wn:ˎ	I
    //   75: bipush 67
    //   77: iadd
    //   78: istore_2
    //   79: iload_2
    //   80: sipush 128
    //   83: irem
    //   84: putstatic 32	o/wn:ॱ	I
    //   87: iload_2
    //   88: iconst_2
    //   89: irem
    //   90: ifne +6 -> 96
    //   93: goto +84 -> 177
    //   96: aload_3
    //   97: areturn
    //   98: getstatic 30	o/wn:ˎ	I
    //   101: bipush 13
    //   103: iadd
    //   104: istore_2
    //   105: iload_2
    //   106: sipush 128
    //   109: irem
    //   110: putstatic 32	o/wn:ॱ	I
    //   113: iload_2
    //   114: iconst_2
    //   115: irem
    //   116: ifne +6 -> 122
    //   119: goto -59 -> 60
    //   122: goto +168 -> 290
    //   125: bipush 85
    //   127: istore_2
    //   128: goto +132 -> 260
    //   131: goto -92 -> 39
    //   134: iconst_1
    //   135: istore_2
    //   136: goto +160 -> 296
    //   139: aload 4
    //   141: invokeinterface 87 1 0
    //   146: checkcast 89	java/lang/String
    //   149: astore_0
    //   150: aload_3
    //   151: aload_0
    //   152: aload_1
    //   153: aload_0
    //   154: invokevirtual 93	org/json/JSONObject:getString	(Ljava/lang/String;)Ljava/lang/String;
    //   157: ldc 95
    //   159: invokestatic 69	o/wv:ˋ	(Ljava/lang/Object;Ljava/lang/Object;)Ljava/lang/Object;
    //   162: checkcast 89	java/lang/String
    //   165: invokevirtual 98	java/util/LinkedHashMap:put	(Ljava/lang/Object;Ljava/lang/Object;)Ljava/lang/Object;
    //   168: pop
    //   169: goto -71 -> 98
    //   172: aload_3
    //   173: areturn
    //   174: astore_0
    //   175: aload_0
    //   176: athrow
    //   177: aconst_null
    //   178: arraylength
    //   179: istore_2
    //   180: aload_3
    //   181: areturn
    //   182: getstatic 30	o/wn:ˎ	I
    //   185: iconst_1
    //   186: iadd
    //   187: istore_2
    //   188: iload_2
    //   189: sipush 128
    //   192: irem
    //   193: putstatic 32	o/wn:ॱ	I
    //   196: iload_2
    //   197: iconst_2
    //   198: irem
    //   199: ifne +6 -> 205
    //   202: goto -147 -> 55
    //   205: goto -71 -> 134
    //   208: iload_2
    //   209: lookupswitch	default:+27->236, 8:+30->239, 76:+-173->36
    //   236: goto -200 -> 36
    //   239: goto -200 -> 39
    //   242: astore_0
    //   243: aload_0
    //   244: athrow
    //   245: aload_0
    //   246: aload_1
    //   247: invokevirtual 102	org/json/JSONObject:getJSONObject	(Ljava/lang/String;)Lorg/json/JSONObject;
    //   250: astore_1
    //   251: aload_1
    //   252: invokevirtual 106	org/json/JSONObject:keys	()Ljava/util/Iterator;
    //   255: astore 4
    //   257: goto -75 -> 182
    //   260: iload_2
    //   261: lookupswitch	default:+27->288, 39:+-122->139, 85:+-89->172
    //   288: aload_3
    //   289: areturn
    //   290: bipush 76
    //   292: istore_2
    //   293: goto -85 -> 208
    //   296: iload_2
    //   297: tableswitch	default:+23->320, 0:+-258->39, 1:+-166->131
    //   320: goto -281 -> 39
    // Local variable table:
    //   start	length	slot	name	signature
    //   0	323	0	paramJSONObject	JSONObject
    //   0	323	1	paramString	String
    //   56	241	2	i	int
    //   7	282	3	localLinkedHashMap	java.util.LinkedHashMap
    //   39	217	4	localIterator	java.util.Iterator
    // Exception table:
    //   from	to	target	type
    //   182	188	174	java/lang/Exception
    //   188	196	174	java/lang/Exception
    //   8	15	242	java/lang/Exception
  }
  
  /* Error */
  public static List<String> ˊ(JSONArray paramJSONArray)
  {
    // Byte code:
    //   0: goto +285 -> 285
    //   3: iload_2
    //   4: lookupswitch	default:+28->32, 74:+124->128, 91:+179->183
    //   32: goto +96 -> 128
    //   35: getstatic 32	o/wn:ॱ	I
    //   38: bipush 123
    //   40: iadd
    //   41: istore_1
    //   42: iload_1
    //   43: sipush 128
    //   46: irem
    //   47: putstatic 30	o/wn:ˎ	I
    //   50: iload_1
    //   51: iconst_2
    //   52: irem
    //   53: ifeq +6 -> 59
    //   56: goto +43 -> 99
    //   59: aload_3
    //   60: areturn
    //   61: goto +64 -> 125
    //   64: iconst_1
    //   65: istore_2
    //   66: goto +225 -> 291
    //   69: astore_0
    //   70: aload_0
    //   71: athrow
    //   72: iload_1
    //   73: tableswitch	default:+23->96, 0:+215->288, 1:+170->243
    //   96: goto +192 -> 288
    //   99: aload_3
    //   100: areturn
    //   101: getstatic 30	o/wn:ˎ	I
    //   104: bipush 25
    //   106: iadd
    //   107: istore_2
    //   108: iload_2
    //   109: sipush 128
    //   112: irem
    //   113: putstatic 32	o/wn:ॱ	I
    //   116: iload_2
    //   117: iconst_2
    //   118: irem
    //   119: ifne +6 -> 125
    //   122: goto -61 -> 61
    //   125: goto +104 -> 229
    //   128: aload_0
    //   129: iload_1
    //   130: invokevirtual 115	org/json/JSONArray:get	(I)Ljava/lang/Object;
    //   133: astore 4
    //   135: aload 4
    //   137: invokestatic 118	o/wv:ˋ	(Ljava/lang/Object;)Ljava/lang/Object;
    //   140: astore 4
    //   142: aload 4
    //   144: invokevirtual 122	java/lang/Object:toString	()Ljava/lang/String;
    //   147: astore 4
    //   149: aload_3
    //   150: aload 4
    //   152: invokeinterface 128 2 0
    //   157: pop
    //   158: iload_1
    //   159: iconst_1
    //   160: iadd
    //   161: istore_1
    //   162: goto +67 -> 229
    //   165: new 130	java/util/ArrayList
    //   168: dup
    //   169: invokespecial 131	java/util/ArrayList:<init>	()V
    //   172: astore_3
    //   173: aload_0
    //   174: ifnull +6 -> 180
    //   177: goto +47 -> 224
    //   180: goto +100 -> 280
    //   183: aload_3
    //   184: aload_0
    //   185: iload_1
    //   186: invokevirtual 115	org/json/JSONArray:get	(I)Ljava/lang/Object;
    //   189: invokestatic 118	o/wv:ˋ	(Ljava/lang/Object;)Ljava/lang/Object;
    //   192: invokevirtual 122	java/lang/Object:toString	()Ljava/lang/String;
    //   195: invokeinterface 128 2 0
    //   200: pop
    //   201: iload_1
    //   202: bipush 97
    //   204: iadd
    //   205: istore_1
    //   206: goto +23 -> 229
    //   209: bipush 91
    //   211: istore_2
    //   212: goto -209 -> 3
    //   215: bipush 74
    //   217: istore_2
    //   218: goto -215 -> 3
    //   221: astore_0
    //   222: aload_0
    //   223: athrow
    //   224: iconst_1
    //   225: istore_1
    //   226: goto -154 -> 72
    //   229: iload_1
    //   230: aload_0
    //   231: invokevirtual 135	org/json/JSONArray:length	()I
    //   234: if_icmpge +6 -> 240
    //   237: goto +38 -> 275
    //   240: goto -176 -> 64
    //   243: iconst_0
    //   244: istore_1
    //   245: goto -144 -> 101
    //   248: getstatic 30	o/wn:ˎ	I
    //   251: bipush 69
    //   253: iadd
    //   254: istore_2
    //   255: iload_2
    //   256: sipush 128
    //   259: irem
    //   260: putstatic 32	o/wn:ॱ	I
    //   263: iload_2
    //   264: iconst_2
    //   265: irem
    //   266: ifne +6 -> 272
    //   269: goto -60 -> 209
    //   272: goto -57 -> 215
    //   275: iconst_0
    //   276: istore_2
    //   277: goto +14 -> 291
    //   280: iconst_0
    //   281: istore_1
    //   282: goto -210 -> 72
    //   285: goto -120 -> 165
    //   288: goto -253 -> 35
    //   291: iload_2
    //   292: tableswitch	default:+24->316, 0:+-44->248, 1:+-4->288
    //   316: goto -28 -> 288
    // Local variable table:
    //   start	length	slot	name	signature
    //   0	319	0	paramJSONArray	JSONArray
    //   41	241	1	i	int
    //   3	289	2	j	int
    //   59	125	3	localObject1	Object
    //   133	18	4	localObject2	Object
    // Exception table:
    //   from	to	target	type
    //   108	116	69	java/lang/Exception
    //   128	135	69	java/lang/Exception
    //   135	142	69	java/lang/Exception
    //   101	108	221	java/lang/Exception
    //   108	116	221	java/lang/Exception
    //   142	149	221	java/lang/Exception
  }
  
  public static List<String> ˊ(JSONObject paramJSONObject, String paramString)
  {
    for (;;)
    {
      try
      {
        i = ॱ + 59;
        try
        {
          ˎ = i % 128;
          if (i % 2 != 0) {
            break;
          }
        }
        catch (Exception paramJSONObject)
        {
          throw paramJSONObject;
        }
        i = 67;
      }
      catch (Exception paramJSONObject)
      {
        throw paramJSONObject;
      }
      paramJSONObject = paramJSONObject.getJSONArray(paramString);
      if (paramJSONObject != null)
      {
        continue;
        i = 40;
        break label149;
        paramJSONObject = ˊ(paramJSONObject);
        continue;
        return paramJSONObject;
        i = 94 / 0;
        return paramJSONObject;
        i = 88;
        break label149;
      }
      else
      {
        throw new JSONException("field \"" + paramString + "\" is mapped to a null value");
      }
      int i = ˎ + 33;
      ॱ = i % 128;
      if (i % 2 != 0)
      {
        continue;
        break label217;
        label149:
        switch (i)
        {
        }
        continue;
        switch (i)
        {
        }
        continue;
        label217:
        do
        {
          i = 88;
          break;
          wv.ˋ(paramJSONObject, "json must not be null");
          wv.ˋ(paramString, "field must not be null");
        } while (!paramJSONObject.has(paramString));
      }
    }
    for (;;)
    {
      return null;
    }
  }
  
  /* Error */
  public static JSONObject ˊ(java.util.Map<String, String> paramMap)
  {
    // Byte code:
    //   0: goto +46 -> 46
    //   3: iconst_0
    //   4: istore_1
    //   5: goto +158 -> 163
    //   8: goto +364 -> 372
    //   11: iconst_1
    //   12: istore_1
    //   13: goto +409 -> 422
    //   16: getstatic 30	o/wn:ˎ	I
    //   19: bipush 43
    //   21: iadd
    //   22: istore_1
    //   23: iload_1
    //   24: sipush 128
    //   27: irem
    //   28: putstatic 32	o/wn:ॱ	I
    //   31: iload_1
    //   32: iconst_2
    //   33: irem
    //   34: ifne +6 -> 40
    //   37: goto -34 -> 3
    //   40: goto +151 -> 191
    //   43: goto +329 -> 372
    //   46: goto +344 -> 390
    //   49: bipush 17
    //   51: istore_1
    //   52: goto +71 -> 123
    //   55: bipush 71
    //   57: istore_1
    //   58: goto +65 -> 123
    //   61: goto +311 -> 372
    //   64: astore_0
    //   65: aload_0
    //   66: athrow
    //   67: getstatic 30	o/wn:ˎ	I
    //   70: istore_1
    //   71: iload_1
    //   72: bipush 73
    //   74: iadd
    //   75: istore_1
    //   76: iload_1
    //   77: sipush 128
    //   80: irem
    //   81: putstatic 32	o/wn:ॱ	I
    //   84: iload_1
    //   85: iconst_2
    //   86: irem
    //   87: ifne +6 -> 93
    //   90: goto -35 -> 55
    //   93: goto -44 -> 49
    //   96: getstatic 32	o/wn:ॱ	I
    //   99: bipush 77
    //   101: iadd
    //   102: istore_1
    //   103: iload_1
    //   104: sipush 128
    //   107: irem
    //   108: putstatic 30	o/wn:ˎ	I
    //   111: iload_1
    //   112: iconst_2
    //   113: irem
    //   114: ifeq +6 -> 120
    //   117: goto -74 -> 43
    //   120: goto -112 -> 8
    //   123: iload_1
    //   124: lookupswitch	default:+28->152, 17:+-63->61, 71:+263->387
    //   152: goto +235 -> 387
    //   155: goto -139 -> 16
    //   158: astore_0
    //   159: aload_0
    //   160: athrow
    //   161: aload_2
    //   162: areturn
    //   163: iload_1
    //   164: tableswitch	default:+24->188, 0:+203->367, 1:+-3->161
    //   188: goto +179 -> 367
    //   191: iconst_1
    //   192: istore_1
    //   193: goto -30 -> 163
    //   196: aload_3
    //   197: invokeinterface 87 1 0
    //   202: checkcast 164	java/util/Map$Entry
    //   205: astore_0
    //   206: aload_0
    //   207: invokeinterface 167 1 0
    //   212: bipush 18
    //   214: newarray int
    //   216: dup
    //   217: iconst_0
    //   218: ldc -88
    //   220: iastore
    //   221: dup
    //   222: iconst_1
    //   223: ldc -87
    //   225: iastore
    //   226: dup
    //   227: iconst_2
    //   228: ldc -86
    //   230: iastore
    //   231: dup
    //   232: iconst_3
    //   233: ldc -85
    //   235: iastore
    //   236: dup
    //   237: iconst_4
    //   238: ldc -84
    //   240: iastore
    //   241: dup
    //   242: iconst_5
    //   243: ldc -83
    //   245: iastore
    //   246: dup
    //   247: bipush 6
    //   249: ldc -82
    //   251: iastore
    //   252: dup
    //   253: bipush 7
    //   255: ldc -81
    //   257: iastore
    //   258: dup
    //   259: bipush 8
    //   261: ldc -80
    //   263: iastore
    //   264: dup
    //   265: bipush 9
    //   267: ldc -79
    //   269: iastore
    //   270: dup
    //   271: bipush 10
    //   273: ldc -78
    //   275: iastore
    //   276: dup
    //   277: bipush 11
    //   279: ldc -77
    //   281: iastore
    //   282: dup
    //   283: bipush 12
    //   285: ldc -76
    //   287: iastore
    //   288: dup
    //   289: bipush 13
    //   291: ldc -75
    //   293: iastore
    //   294: dup
    //   295: bipush 14
    //   297: ldc -74
    //   299: iastore
    //   300: dup
    //   301: bipush 15
    //   303: ldc -73
    //   305: iastore
    //   306: dup
    //   307: bipush 16
    //   309: ldc -72
    //   311: iastore
    //   312: dup
    //   313: bipush 17
    //   315: ldc -71
    //   317: iastore
    //   318: bipush 35
    //   320: invokestatic 188	o/wn:ˋ	([II)Ljava/lang/String;
    //   323: invokevirtual 191	java/lang/String:intern	()Ljava/lang/String;
    //   326: invokestatic 69	o/wv:ˋ	(Ljava/lang/Object;Ljava/lang/Object;)Ljava/lang/Object;
    //   329: pop
    //   330: aload_0
    //   331: invokeinterface 194 1 0
    //   336: ldc -60
    //   338: invokestatic 69	o/wv:ˋ	(Ljava/lang/Object;Ljava/lang/Object;)Ljava/lang/Object;
    //   341: pop
    //   342: aload_2
    //   343: aload_0
    //   344: invokeinterface 167 1 0
    //   349: checkcast 89	java/lang/String
    //   352: aload_0
    //   353: invokeinterface 194 1 0
    //   358: checkcast 89	java/lang/String
    //   361: invokestatic 199	o/wn:ˊ	(Lorg/json/JSONObject;Ljava/lang/String;Ljava/lang/String;)V
    //   364: goto -268 -> 96
    //   367: aconst_null
    //   368: arraylength
    //   369: istore_1
    //   370: aload_2
    //   371: areturn
    //   372: aload_3
    //   373: invokeinterface 83 1 0
    //   378: ifeq +6 -> 384
    //   381: goto +39 -> 420
    //   384: goto -373 -> 11
    //   387: goto -15 -> 372
    //   390: aload_0
    //   391: invokestatic 118	o/wv:ˋ	(Ljava/lang/Object;)Ljava/lang/Object;
    //   394: pop
    //   395: new 73	org/json/JSONObject
    //   398: dup
    //   399: invokespecial 200	org/json/JSONObject:<init>	()V
    //   402: astore_2
    //   403: aload_0
    //   404: invokeinterface 206 1 0
    //   409: astore_0
    //   410: aload_0
    //   411: invokeinterface 211 1 0
    //   416: astore_3
    //   417: goto -350 -> 67
    //   420: iconst_0
    //   421: istore_1
    //   422: iload_1
    //   423: tableswitch	default:+21->444, 0:+-227->196, 1:+-268->155
    //   444: goto -248 -> 196
    // Local variable table:
    //   start	length	slot	name	signature
    //   0	447	0	paramMap	java.util.Map<String, String>
    //   4	419	1	i	int
    //   161	242	2	localJSONObject	JSONObject
    //   196	221	3	localIterator	java.util.Iterator
    // Exception table:
    //   from	to	target	type
    //   403	410	64	java/lang/Exception
    //   67	71	158	java/lang/Exception
    //   76	84	158	java/lang/Exception
    //   390	403	158	java/lang/Exception
    //   403	410	158	java/lang/Exception
    //   410	417	158	java/lang/Exception
  }
  
  /* Error */
  public static void ˊ(JSONObject paramJSONObject, String paramString, Long paramLong)
  {
    // Byte code:
    //   0: goto +138 -> 138
    //   3: goto +44 -> 47
    //   6: aload_0
    //   7: aload_1
    //   8: aload_2
    //   9: invokevirtual 216	org/json/JSONObject:put	(Ljava/lang/String;Ljava/lang/Object;)Lorg/json/JSONObject;
    //   12: pop
    //   13: goto -10 -> 3
    //   16: iload_3
    //   17: lookupswitch	default:+27->44, 7:+88->105, 64:+124->141
    //   44: goto +97 -> 141
    //   47: getstatic 32	o/wn:ॱ	I
    //   50: bipush 59
    //   52: iadd
    //   53: istore_3
    //   54: iload_3
    //   55: sipush 128
    //   58: irem
    //   59: putstatic 30	o/wn:ˎ	I
    //   62: iload_3
    //   63: iconst_2
    //   64: irem
    //   65: ifeq +6 -> 71
    //   68: goto +7 -> 75
    //   71: return
    //   72: astore_0
    //   73: aload_0
    //   74: athrow
    //   75: return
    //   76: getstatic 30	o/wn:ˎ	I
    //   79: istore_3
    //   80: iload_3
    //   81: bipush 45
    //   83: iadd
    //   84: istore_3
    //   85: iload_3
    //   86: sipush 128
    //   89: irem
    //   90: putstatic 32	o/wn:ॱ	I
    //   93: iload_3
    //   94: iconst_2
    //   95: irem
    //   96: ifne +6 -> 102
    //   99: goto +64 -> 163
    //   102: goto +30 -> 132
    //   105: aload_0
    //   106: ldc 64
    //   108: invokestatic 69	o/wv:ˋ	(Ljava/lang/Object;Ljava/lang/Object;)Ljava/lang/Object;
    //   111: pop
    //   112: aload_1
    //   113: ldc 71
    //   115: invokestatic 69	o/wv:ˋ	(Ljava/lang/Object;Ljava/lang/Object;)Ljava/lang/Object;
    //   118: pop
    //   119: bipush 63
    //   121: iconst_0
    //   122: idiv
    //   123: istore_3
    //   124: aload_2
    //   125: ifnonnull +4 -> 129
    //   128: return
    //   129: goto -123 -> 6
    //   132: bipush 64
    //   134: istore_3
    //   135: goto -119 -> 16
    //   138: goto -62 -> 76
    //   141: aload_0
    //   142: ldc 64
    //   144: invokestatic 69	o/wv:ˋ	(Ljava/lang/Object;Ljava/lang/Object;)Ljava/lang/Object;
    //   147: pop
    //   148: aload_1
    //   149: ldc 71
    //   151: invokestatic 69	o/wv:ˋ	(Ljava/lang/Object;Ljava/lang/Object;)Ljava/lang/Object;
    //   154: pop
    //   155: aload_2
    //   156: ifnonnull +4 -> 160
    //   159: return
    //   160: goto -154 -> 6
    //   163: bipush 7
    //   165: istore_3
    //   166: goto -150 -> 16
    //   169: astore_0
    //   170: new 218	java/lang/IllegalStateException
    //   173: dup
    //   174: ldc -36
    //   176: aload_0
    //   177: invokespecial 223	java/lang/IllegalStateException:<init>	(Ljava/lang/String;Ljava/lang/Throwable;)V
    //   180: athrow
    // Local variable table:
    //   start	length	slot	name	signature
    //   0	181	0	paramJSONObject	JSONObject
    //   0	181	1	paramString	String
    //   0	181	2	paramLong	Long
    //   16	150	3	i	int
    // Exception table:
    //   from	to	target	type
    //   76	80	72	java/lang/Exception
    //   85	93	72	java/lang/Exception
    //   6	13	169	org/json/JSONException
  }
  
  public static void ˊ(JSONObject paramJSONObject, String paramString1, String paramString2)
  {
    break label170;
    int i = ॱ + 71;
    ˎ = i % 128;
    if (i % 2 == 0) {}
    for (;;)
    {
      return;
      try
      {
        wv.ˋ(paramJSONObject, "json must not be null");
        wv.ˋ(paramString1, "field must not be null");
        wv.ˋ(paramString2, "value must not be null");
      }
      catch (Exception paramJSONObject)
      {
        label59:
        throw paramJSONObject;
      }
      try
      {
        paramJSONObject.put(paramString1, paramString2);
      }
      catch (JSONException paramJSONObject)
      {
        throw new IllegalStateException("JSONException thrown in violation of contract", paramJSONObject);
      }
      i = 19;
      break label100;
      label65:
      i = 96;
      label100:
      label170:
      for (;;)
      {
        i = ˎ;
        i += 87;
        ॱ = i % 128;
        if (i % 2 == 0) {
          break label65;
        }
        break label59;
        switch (i)
        {
        case 19: 
        default: 
          break;
        case 96: 
          wv.ˋ(paramJSONObject, "json must not be null");
          wv.ˋ(paramString1, "field must not be null");
          wv.ˋ(paramString2, "value must not be null");
          paramJSONObject.put(paramString1, paramString2);
          throw new NullPointerException();
        }
      }
    }
  }
  
  /* Error */
  public static Uri ˋ(JSONObject paramJSONObject, String paramString)
  {
    // Byte code:
    //   0: goto +178 -> 178
    //   3: astore_0
    //   4: aload_0
    //   5: athrow
    //   6: bipush 39
    //   8: istore_2
    //   9: goto +53 -> 62
    //   12: bipush 63
    //   14: iconst_0
    //   15: idiv
    //   16: istore_2
    //   17: aload_0
    //   18: areturn
    //   19: aload_0
    //   20: ldc 64
    //   22: invokestatic 69	o/wv:ˋ	(Ljava/lang/Object;Ljava/lang/Object;)Ljava/lang/Object;
    //   25: pop
    //   26: aload_1
    //   27: ldc 71
    //   29: invokestatic 69	o/wv:ˋ	(Ljava/lang/Object;Ljava/lang/Object;)Ljava/lang/Object;
    //   32: pop
    //   33: aload_0
    //   34: aload_1
    //   35: invokevirtual 93	org/json/JSONObject:getString	(Ljava/lang/String;)Ljava/lang/String;
    //   38: astore_0
    //   39: aconst_null
    //   40: arraylength
    //   41: istore_2
    //   42: aload_0
    //   43: ifnonnull +6 -> 49
    //   46: goto +180 -> 226
    //   49: goto +5 -> 54
    //   52: aload_0
    //   53: areturn
    //   54: aload_0
    //   55: invokestatic 235	android/net/Uri:parse	(Ljava/lang/String;)Landroid/net/Uri;
    //   58: astore_0
    //   59: goto +92 -> 151
    //   62: iload_2
    //   63: lookupswitch	default:+25->88, 39:+-44->19, 61:+130->193
    //   88: goto +105 -> 193
    //   91: iload_2
    //   92: lookupswitch	default:+28->120, 30:+-80->12, 82:+-40->52
    //   120: aload_0
    //   121: areturn
    //   122: getstatic 30	o/wn:ˎ	I
    //   125: istore_2
    //   126: iload_2
    //   127: bipush 49
    //   129: iadd
    //   130: istore_2
    //   131: iload_2
    //   132: sipush 128
    //   135: irem
    //   136: putstatic 32	o/wn:ॱ	I
    //   139: iload_2
    //   140: iconst_2
    //   141: irem
    //   142: ifne +6 -> 148
    //   145: goto -139 -> 6
    //   148: goto +39 -> 187
    //   151: getstatic 30	o/wn:ˎ	I
    //   154: bipush 55
    //   156: iadd
    //   157: istore_2
    //   158: iload_2
    //   159: sipush 128
    //   162: irem
    //   163: putstatic 32	o/wn:ॱ	I
    //   166: iload_2
    //   167: iconst_2
    //   168: irem
    //   169: ifne +6 -> 175
    //   172: goto +86 -> 258
    //   175: goto +6 -> 181
    //   178: goto -56 -> 122
    //   181: bipush 82
    //   183: istore_2
    //   184: goto -93 -> 91
    //   187: bipush 61
    //   189: istore_2
    //   190: goto -128 -> 62
    //   193: aload_0
    //   194: ldc 64
    //   196: invokestatic 69	o/wv:ˋ	(Ljava/lang/Object;Ljava/lang/Object;)Ljava/lang/Object;
    //   199: pop
    //   200: aload_1
    //   201: ldc 71
    //   203: invokestatic 69	o/wv:ˋ	(Ljava/lang/Object;Ljava/lang/Object;)Ljava/lang/Object;
    //   206: pop
    //   207: aload_0
    //   208: aload_1
    //   209: invokevirtual 93	org/json/JSONObject:getString	(Ljava/lang/String;)Ljava/lang/String;
    //   212: astore_0
    //   213: aload_0
    //   214: ifnonnull +6 -> 220
    //   217: goto +9 -> 226
    //   220: goto -166 -> 54
    //   223: astore_0
    //   224: aload_0
    //   225: athrow
    //   226: new 145	org/json/JSONException
    //   229: dup
    //   230: new 147	java/lang/StringBuilder
    //   233: dup
    //   234: invokespecial 148	java/lang/StringBuilder:<init>	()V
    //   237: ldc -106
    //   239: invokevirtual 154	java/lang/StringBuilder:append	(Ljava/lang/String;)Ljava/lang/StringBuilder;
    //   242: aload_1
    //   243: invokevirtual 154	java/lang/StringBuilder:append	(Ljava/lang/String;)Ljava/lang/StringBuilder;
    //   246: ldc -100
    //   248: invokevirtual 154	java/lang/StringBuilder:append	(Ljava/lang/String;)Ljava/lang/StringBuilder;
    //   251: invokevirtual 157	java/lang/StringBuilder:toString	()Ljava/lang/String;
    //   254: invokespecial 160	org/json/JSONException:<init>	(Ljava/lang/String;)V
    //   257: athrow
    //   258: bipush 30
    //   260: istore_2
    //   261: goto -170 -> 91
    // Local variable table:
    //   start	length	slot	name	signature
    //   0	264	0	paramJSONObject	JSONObject
    //   0	264	1	paramString	String
    //   8	253	2	i	int
    // Exception table:
    //   from	to	target	type
    //   19	26	3	java/lang/Exception
    //   26	42	3	java/lang/Exception
    //   54	59	3	java/lang/Exception
    //   122	126	3	java/lang/Exception
    //   131	139	3	java/lang/Exception
    //   19	26	223	java/lang/Exception
  }
  
  /* Error */
  public static <T> T ˋ(JSONObject paramJSONObject, ˊ<T> paramˊ)
  {
    // Byte code:
    //   0: goto +107 -> 107
    //   3: getstatic 32	o/wn:ॱ	I
    //   6: istore_2
    //   7: iload_2
    //   8: bipush 65
    //   10: iadd
    //   11: istore_2
    //   12: iload_2
    //   13: sipush 128
    //   16: irem
    //   17: putstatic 30	o/wn:ˎ	I
    //   20: iload_2
    //   21: iconst_2
    //   22: irem
    //   23: ifeq +6 -> 29
    //   26: goto +6 -> 32
    //   29: goto +53 -> 82
    //   32: goto +50 -> 82
    //   35: iload_2
    //   36: lookupswitch	default:+28->64, 29:+56->92, 65:+-33->3
    //   64: goto +28 -> 92
    //   67: astore_0
    //   68: new 218	java/lang/IllegalStateException
    //   71: dup
    //   72: ldc -18
    //   74: aload_0
    //   75: invokespecial 223	java/lang/IllegalStateException:<init>	(Ljava/lang/String;Ljava/lang/Throwable;)V
    //   78: athrow
    //   79: astore_0
    //   80: aload_0
    //   81: athrow
    //   82: aload_1
    //   83: getfield 241	o/wn$ˊ:ˋ	Ljava/lang/Object;
    //   86: astore_0
    //   87: aload_0
    //   88: areturn
    //   89: goto +21 -> 110
    //   92: aload_1
    //   93: aload_0
    //   94: aload_1
    //   95: getfield 244	o/wn$ˊ:ˎ	Ljava/lang/String;
    //   98: invokevirtual 93	org/json/JSONObject:getString	(Ljava/lang/String;)Ljava/lang/String;
    //   101: invokevirtual 247	o/wn$ˊ:ˎ	(Ljava/lang/String;)Ljava/lang/Object;
    //   104: astore_0
    //   105: aload_0
    //   106: areturn
    //   107: goto +28 -> 135
    //   110: aload_0
    //   111: aload_1
    //   112: getfield 244	o/wn$ˊ:ˎ	Ljava/lang/String;
    //   115: invokevirtual 77	org/json/JSONObject:has	(Ljava/lang/String;)Z
    //   118: istore_3
    //   119: iload_3
    //   120: ifne +6 -> 126
    //   123: goto +6 -> 129
    //   126: goto +36 -> 162
    //   129: bipush 65
    //   131: istore_2
    //   132: goto -97 -> 35
    //   135: getstatic 32	o/wn:ॱ	I
    //   138: bipush 117
    //   140: iadd
    //   141: istore_2
    //   142: iload_2
    //   143: sipush 128
    //   146: irem
    //   147: putstatic 30	o/wn:ˎ	I
    //   150: iload_2
    //   151: iconst_2
    //   152: irem
    //   153: ifeq +6 -> 159
    //   156: goto -67 -> 89
    //   159: goto -49 -> 110
    //   162: bipush 29
    //   164: istore_2
    //   165: goto -130 -> 35
    // Local variable table:
    //   start	length	slot	name	signature
    //   0	168	0	paramJSONObject	JSONObject
    //   0	168	1	paramˊ	ˊ<T>
    //   6	159	2	i	int
    //   118	2	3	bool	boolean
    // Exception table:
    //   from	to	target	type
    //   82	87	67	org/json/JSONException
    //   92	105	67	org/json/JSONException
    //   110	119	67	org/json/JSONException
    //   3	7	79	java/lang/Exception
    //   12	20	79	java/lang/Exception
  }
  
  private static String ˋ(int[] paramArrayOfInt, int paramInt)
  {
    break label240;
    char[] arrayOfChar1 = new char[4];
    char[] arrayOfChar2 = new char[paramArrayOfInt.length << 1];
    int[] arrayOfInt1 = (int[])ˏ.clone();
    int i = 0;
    break label224;
    label67:
    do
    {
      i = 1;
      break label308;
      break label224;
      j = ॱ + 101;
      ˎ = j % 128;
      if (j % 2 != 0) {
        break;
      }
      break;
      i = ˎ + 29;
      ॱ = i % 128;
    } while (i % 2 == 0);
    break label99;
    label94:
    int j = 1;
    break label243;
    label99:
    i = 0;
    break label308;
    int[] arrayOfInt2;
    arrayOfChar1[0] = ((char)(arrayOfInt2[i] >> 16));
    arrayOfChar1[1] = ((char)arrayOfInt2[i]);
    arrayOfChar1[2] = ((char)(arrayOfInt2[(i + 1)] >> 16));
    arrayOfChar1[3] = ((char)arrayOfInt2[(i + 1)]);
    for (;;)
    {
      try
      {
        oN.ˏ(arrayOfChar1, arrayOfInt1, false);
        arrayOfChar2[(i << 1)] = arrayOfChar1[0];
        arrayOfChar2[((i << 1) + 1)] = arrayOfChar1[1];
        arrayOfChar2[((i << 1) + 2)] = arrayOfChar1[2];
        arrayOfChar2[((i << 1) + 3)] = arrayOfChar1[3];
        i += 2;
      }
      catch (Exception paramArrayOfInt)
      {
        label224:
        label240:
        label243:
        throw paramArrayOfInt;
      }
      return new String(arrayOfChar2, 0, paramInt);
      arrayOfInt2 = paramArrayOfInt;
      if (i < arrayOfInt2.length) {
        break label303;
      }
      break label94;
      break label67;
      switch (j)
      {
      }
    }
    for (;;)
    {
      arrayOfChar1 = new char[2];
      arrayOfChar2 = new char[paramArrayOfInt.length % 1];
      arrayOfInt1 = (int[])ˏ.clone();
      i = 0;
      break;
      label303:
      j = 0;
      break label243;
      label308:
      switch (i)
      {
      }
    }
  }
  
  /* Error */
  public static void ˋ(JSONObject paramJSONObject, String paramString, Uri paramUri)
  {
    // Byte code:
    //   0: goto +147 -> 147
    //   3: aload_0
    //   4: ldc 64
    //   6: invokestatic 69	o/wv:ˋ	(Ljava/lang/Object;Ljava/lang/Object;)Ljava/lang/Object;
    //   9: pop
    //   10: aload_1
    //   11: ldc 71
    //   13: invokestatic 69	o/wv:ˋ	(Ljava/lang/Object;Ljava/lang/Object;)Ljava/lang/Object;
    //   16: pop
    //   17: aconst_null
    //   18: arraylength
    //   19: istore_3
    //   20: aload_2
    //   21: ifnonnull +6 -> 27
    //   24: goto +12 -> 36
    //   27: goto +77 -> 104
    //   30: bipush 6
    //   32: istore_3
    //   33: goto +82 -> 115
    //   36: goto +30 -> 66
    //   39: aload_0
    //   40: ldc 64
    //   42: invokestatic 69	o/wv:ˋ	(Ljava/lang/Object;Ljava/lang/Object;)Ljava/lang/Object;
    //   45: pop
    //   46: aload_1
    //   47: ldc 71
    //   49: invokestatic 69	o/wv:ˋ	(Ljava/lang/Object;Ljava/lang/Object;)Ljava/lang/Object;
    //   52: pop
    //   53: aload_2
    //   54: ifnonnull +6 -> 60
    //   57: goto -21 -> 36
    //   60: goto +44 -> 104
    //   63: astore_0
    //   64: aload_0
    //   65: athrow
    //   66: getstatic 32	o/wn:ॱ	I
    //   69: bipush 89
    //   71: iadd
    //   72: istore_3
    //   73: iload_3
    //   74: sipush 128
    //   77: irem
    //   78: putstatic 30	o/wn:ˎ	I
    //   81: iload_3
    //   82: iconst_2
    //   83: irem
    //   84: ifeq +6 -> 90
    //   87: goto +16 -> 103
    //   90: return
    //   91: astore_0
    //   92: new 218	java/lang/IllegalStateException
    //   95: dup
    //   96: ldc -36
    //   98: aload_0
    //   99: invokespecial 223	java/lang/IllegalStateException:<init>	(Ljava/lang/String;Ljava/lang/Throwable;)V
    //   102: athrow
    //   103: return
    //   104: aload_0
    //   105: aload_1
    //   106: aload_2
    //   107: invokevirtual 262	android/net/Uri:toString	()Ljava/lang/String;
    //   110: invokevirtual 216	org/json/JSONObject:put	(Ljava/lang/String;Ljava/lang/Object;)Lorg/json/JSONObject;
    //   113: pop
    //   114: return
    //   115: iload_3
    //   116: lookupswitch	default:+28->144, 6:+-77->39, 61:+-113->3
    //   144: goto -105 -> 39
    //   147: getstatic 30	o/wn:ˎ	I
    //   150: istore_3
    //   151: iload_3
    //   152: bipush 17
    //   154: iadd
    //   155: istore_3
    //   156: iload_3
    //   157: sipush 128
    //   160: irem
    //   161: putstatic 32	o/wn:ॱ	I
    //   164: iload_3
    //   165: iconst_2
    //   166: irem
    //   167: ifne +6 -> 173
    //   170: goto +6 -> 176
    //   173: goto -143 -> 30
    //   176: bipush 61
    //   178: istore_3
    //   179: goto -64 -> 115
    //   182: astore_0
    //   183: aload_0
    //   184: athrow
    // Local variable table:
    //   start	length	slot	name	signature
    //   0	185	0	paramJSONObject	JSONObject
    //   0	185	1	paramString	String
    //   0	185	2	paramUri	Uri
    //   19	160	3	i	int
    // Exception table:
    //   from	to	target	type
    //   147	151	63	java/lang/Exception
    //   104	114	91	org/json/JSONException
    //   156	164	182	java/lang/Exception
  }
  
  public static String ˎ(JSONObject paramJSONObject, String paramString)
  {
    for (;;)
    {
      wv.ˋ(paramJSONObject, "json must not be null");
      wv.ˋ(paramString, "field must not be null");
      if (paramJSONObject.has(paramString)) {
        break label143;
      }
      int i = 40;
      break label173;
      for (;;)
      {
        switch (i)
        {
        case 77: 
        default: 
          break label149;
          i = 45;
        }
      }
      i = ˎ + 67;
      ॱ = i % 128;
      if (i % 2 != 0) {
        break label203;
      }
      i = 88 / 0;
      return null;
      label111:
      throw new JSONException("field \"" + paramString + "\" is mapped to a null value");
      label143:
      i = 77;
      for (;;)
      {
        label149:
        paramJSONObject = paramJSONObject.getString(paramString);
        if (paramJSONObject == null) {
          break label111;
        }
        return paramJSONObject;
        label164:
        i = 77;
        break;
        break label238;
        label173:
        switch (i)
        {
        }
      }
      label203:
      return null;
      label238:
      do
      {
        wv.ˋ(paramJSONObject, "json must not be null");
        wv.ˋ(paramString, "field must not be null");
        boolean bool = paramJSONObject.has(paramString);
        i = null.length;
        if (!bool) {
          break label164;
        }
        break;
        i = ॱ + 87;
        ˎ = i % 128;
      } while (i % 2 != 0);
    }
  }
  
  /* Error */
  public static JSONArray ˎ(Iterable<?> paramIterable)
  {
    // Byte code:
    //   0: goto +55 -> 55
    //   3: aload_0
    //   4: ldc_w 266
    //   7: invokestatic 69	o/wv:ˋ	(Ljava/lang/Object;Ljava/lang/Object;)Ljava/lang/Object;
    //   10: pop
    //   11: new 111	org/json/JSONArray
    //   14: dup
    //   15: invokespecial 267	org/json/JSONArray:<init>	()V
    //   18: astore_2
    //   19: aload_0
    //   20: invokeinterface 270 1 0
    //   25: astore_0
    //   26: goto +118 -> 144
    //   29: aload_0
    //   30: invokeinterface 83 1 0
    //   35: ifeq +6 -> 41
    //   38: goto +160 -> 198
    //   41: goto +20 -> 61
    //   44: goto +127 -> 171
    //   47: new 227	java/lang/NullPointerException
    //   50: dup
    //   51: invokespecial 228	java/lang/NullPointerException:<init>	()V
    //   54: athrow
    //   55: goto -52 -> 3
    //   58: astore_0
    //   59: aload_0
    //   60: athrow
    //   61: bipush 79
    //   63: istore_1
    //   64: goto +30 -> 94
    //   67: iload_1
    //   68: tableswitch	default:+24->92, 0:+177->245, 1:+-21->47
    //   92: aload_2
    //   93: areturn
    //   94: iload_1
    //   95: lookupswitch	default:+25->120, 12:+112->207, 79:+-51->44
    //   120: goto +87 -> 207
    //   123: aload_0
    //   124: invokeinterface 87 1 0
    //   129: astore_3
    //   130: aload_3
    //   131: invokevirtual 122	java/lang/Object:toString	()Ljava/lang/String;
    //   134: astore_3
    //   135: aload_2
    //   136: aload_3
    //   137: invokevirtual 273	org/json/JSONArray:put	(Ljava/lang/Object;)Lorg/json/JSONArray;
    //   140: pop
    //   141: goto -112 -> 29
    //   144: getstatic 32	o/wn:ॱ	I
    //   147: bipush 63
    //   149: iadd
    //   150: istore_1
    //   151: iload_1
    //   152: sipush 128
    //   155: irem
    //   156: putstatic 30	o/wn:ˎ	I
    //   159: iload_1
    //   160: iconst_2
    //   161: irem
    //   162: ifeq +6 -> 168
    //   165: goto +39 -> 204
    //   168: goto +66 -> 234
    //   171: getstatic 30	o/wn:ˎ	I
    //   174: bipush 61
    //   176: iadd
    //   177: istore_1
    //   178: iload_1
    //   179: sipush 128
    //   182: irem
    //   183: putstatic 32	o/wn:ॱ	I
    //   186: iload_1
    //   187: iconst_2
    //   188: irem
    //   189: ifne +6 -> 195
    //   192: goto +55 -> 247
    //   195: goto +45 -> 240
    //   198: bipush 12
    //   200: istore_1
    //   201: goto -107 -> 94
    //   204: goto +30 -> 234
    //   207: getstatic 32	o/wn:ॱ	I
    //   210: bipush 79
    //   212: iadd
    //   213: istore_1
    //   214: iload_1
    //   215: sipush 128
    //   218: irem
    //   219: putstatic 30	o/wn:ˎ	I
    //   222: iload_1
    //   223: iconst_2
    //   224: irem
    //   225: ifeq +6 -> 231
    //   228: goto +9 -> 237
    //   231: goto -108 -> 123
    //   234: goto -205 -> 29
    //   237: goto -114 -> 123
    //   240: iconst_0
    //   241: istore_1
    //   242: goto -175 -> 67
    //   245: aload_2
    //   246: areturn
    //   247: iconst_1
    //   248: istore_1
    //   249: goto -182 -> 67
    // Local variable table:
    //   start	length	slot	name	signature
    //   0	252	0	paramIterable	Iterable<?>
    //   63	186	1	i	int
    //   18	228	2	localJSONArray	JSONArray
    //   129	8	3	localObject	Object
    // Exception table:
    //   from	to	target	type
    //   123	130	58	java/lang/Exception
    //   130	135	58	java/lang/Exception
    //   135	141	58	java/lang/Exception
  }
  
  /* Error */
  public static void ˎ(JSONObject paramJSONObject, String paramString1, String paramString2)
  {
    // Byte code:
    //   0: goto +4 -> 4
    //   3: return
    //   4: goto +76 -> 80
    //   7: goto +35 -> 42
    //   10: new 227	java/lang/NullPointerException
    //   13: dup
    //   14: invokespecial 228	java/lang/NullPointerException:<init>	()V
    //   17: athrow
    //   18: aload_0
    //   19: ldc 64
    //   21: invokestatic 69	o/wv:ˋ	(Ljava/lang/Object;Ljava/lang/Object;)Ljava/lang/Object;
    //   24: pop
    //   25: aload_1
    //   26: ldc 71
    //   28: invokestatic 69	o/wv:ˋ	(Ljava/lang/Object;Ljava/lang/Object;)Ljava/lang/Object;
    //   31: pop
    //   32: aload_2
    //   33: ifnonnull +6 -> 39
    //   36: goto -29 -> 7
    //   39: goto +115 -> 154
    //   42: getstatic 30	o/wn:ˎ	I
    //   45: bipush 121
    //   47: iadd
    //   48: istore_3
    //   49: iload_3
    //   50: sipush 128
    //   53: irem
    //   54: putstatic 32	o/wn:ॱ	I
    //   57: iload_3
    //   58: iconst_2
    //   59: irem
    //   60: ifne +6 -> 66
    //   63: goto +6 -> 69
    //   66: goto +8 -> 74
    //   69: iconst_5
    //   70: istore_3
    //   71: goto +36 -> 107
    //   74: bipush 42
    //   76: istore_3
    //   77: goto +30 -> 107
    //   80: getstatic 32	o/wn:ॱ	I
    //   83: bipush 25
    //   85: iadd
    //   86: istore_3
    //   87: iload_3
    //   88: sipush 128
    //   91: irem
    //   92: putstatic 30	o/wn:ˎ	I
    //   95: iload_3
    //   96: iconst_2
    //   97: irem
    //   98: ifeq +6 -> 104
    //   101: goto +50 -> 151
    //   104: goto -86 -> 18
    //   107: iload_3
    //   108: lookupswitch	default:+28->136, 5:+-98->10, 42:+-105->3
    //   136: goto -126 -> 10
    //   139: astore_0
    //   140: new 218	java/lang/IllegalStateException
    //   143: dup
    //   144: ldc -36
    //   146: aload_0
    //   147: invokespecial 223	java/lang/IllegalStateException:<init>	(Ljava/lang/String;Ljava/lang/Throwable;)V
    //   150: athrow
    //   151: goto -133 -> 18
    //   154: aload_0
    //   155: aload_1
    //   156: aload_2
    //   157: invokevirtual 216	org/json/JSONObject:put	(Ljava/lang/String;Ljava/lang/Object;)Lorg/json/JSONObject;
    //   160: pop
    //   161: return
    // Local variable table:
    //   start	length	slot	name	signature
    //   0	162	0	paramJSONObject	JSONObject
    //   0	162	1	paramString1	String
    //   0	162	2	paramString2	String
    //   48	60	3	i	int
    // Exception table:
    //   from	to	target	type
    //   154	161	139	org/json/JSONException
  }
  
  /* Error */
  public static void ˎ(JSONObject paramJSONObject, String paramString, JSONArray paramJSONArray)
  {
    // Byte code:
    //   0: goto +171 -> 171
    //   3: aload_0
    //   4: ldc 64
    //   6: invokestatic 69	o/wv:ˋ	(Ljava/lang/Object;Ljava/lang/Object;)Ljava/lang/Object;
    //   9: pop
    //   10: aload_1
    //   11: ldc 71
    //   13: invokestatic 69	o/wv:ˋ	(Ljava/lang/Object;Ljava/lang/Object;)Ljava/lang/Object;
    //   16: pop
    //   17: aload_2
    //   18: ldc -31
    //   20: invokestatic 69	o/wv:ˋ	(Ljava/lang/Object;Ljava/lang/Object;)Ljava/lang/Object;
    //   23: pop
    //   24: aload_0
    //   25: aload_1
    //   26: aload_2
    //   27: invokevirtual 216	org/json/JSONObject:put	(Ljava/lang/String;Ljava/lang/Object;)Lorg/json/JSONObject;
    //   30: pop
    //   31: getstatic 30	o/wn:ˎ	I
    //   34: bipush 77
    //   36: iadd
    //   37: istore_3
    //   38: iload_3
    //   39: sipush 128
    //   42: irem
    //   43: putstatic 32	o/wn:ॱ	I
    //   46: iload_3
    //   47: iconst_2
    //   48: irem
    //   49: ifne +6 -> 55
    //   52: goto +137 -> 189
    //   55: goto +57 -> 112
    //   58: getstatic 30	o/wn:ˎ	I
    //   61: bipush 67
    //   63: iadd
    //   64: istore_3
    //   65: iload_3
    //   66: sipush 128
    //   69: irem
    //   70: putstatic 32	o/wn:ॱ	I
    //   73: iload_3
    //   74: iconst_2
    //   75: irem
    //   76: ifne +6 -> 82
    //   79: goto +60 -> 139
    //   82: goto -79 -> 3
    //   85: getstatic 32	o/wn:ॱ	I
    //   88: bipush 49
    //   90: iadd
    //   91: istore_3
    //   92: iload_3
    //   93: sipush 128
    //   96: irem
    //   97: putstatic 30	o/wn:ˎ	I
    //   100: iload_3
    //   101: iconst_2
    //   102: irem
    //   103: ifeq +6 -> 109
    //   106: goto +19 -> 125
    //   109: goto +34 -> 143
    //   112: iconst_0
    //   113: istore_3
    //   114: goto +83 -> 197
    //   117: new 227	java/lang/NullPointerException
    //   120: dup
    //   121: invokespecial 228	java/lang/NullPointerException:<init>	()V
    //   124: athrow
    //   125: iconst_1
    //   126: istore_3
    //   127: goto +18 -> 145
    //   130: astore_0
    //   131: aload_0
    //   132: athrow
    //   133: goto +53 -> 186
    //   136: astore_0
    //   137: aload_0
    //   138: athrow
    //   139: goto -136 -> 3
    //   142: return
    //   143: iconst_0
    //   144: istore_3
    //   145: iload_3
    //   146: tableswitch	default:+22->168, 0:+-4->142, 1:+-29->117
    //   168: goto -51 -> 117
    //   171: goto -113 -> 58
    //   174: astore_0
    //   175: new 218	java/lang/IllegalStateException
    //   178: dup
    //   179: ldc -36
    //   181: aload_0
    //   182: invokespecial 223	java/lang/IllegalStateException:<init>	(Ljava/lang/String;Ljava/lang/Throwable;)V
    //   185: athrow
    //   186: goto -101 -> 85
    //   189: iconst_1
    //   190: istore_3
    //   191: goto +6 -> 197
    //   194: goto -8 -> 186
    //   197: iload_3
    //   198: tableswitch	default:+22->220, 0:+-4->194, 1:+-65->133
    //   220: goto -87 -> 133
    // Local variable table:
    //   start	length	slot	name	signature
    //   0	223	0	paramJSONObject	JSONObject
    //   0	223	1	paramString	String
    //   0	223	2	paramJSONArray	JSONArray
    //   37	161	3	i	int
    // Exception table:
    //   from	to	target	type
    //   3	10	130	java/lang/Exception
    //   10	17	130	java/lang/Exception
    //   17	24	130	java/lang/Exception
    //   24	31	130	java/lang/Exception
    //   10	17	136	java/lang/Exception
    //   24	31	174	org/json/JSONException
  }
  
  /* Error */
  public static void ˎ(JSONObject paramJSONObject1, String paramString, JSONObject paramJSONObject2)
  {
    // Byte code:
    //   0: goto +112 -> 112
    //   3: aload_0
    //   4: ldc 64
    //   6: invokestatic 69	o/wv:ˋ	(Ljava/lang/Object;Ljava/lang/Object;)Ljava/lang/Object;
    //   9: pop
    //   10: aload_1
    //   11: ldc 71
    //   13: invokestatic 69	o/wv:ˋ	(Ljava/lang/Object;Ljava/lang/Object;)Ljava/lang/Object;
    //   16: pop
    //   17: aload_2
    //   18: ldc -31
    //   20: invokestatic 69	o/wv:ˋ	(Ljava/lang/Object;Ljava/lang/Object;)Ljava/lang/Object;
    //   23: pop
    //   24: aload_0
    //   25: aload_1
    //   26: aload_2
    //   27: invokevirtual 216	org/json/JSONObject:put	(Ljava/lang/String;Ljava/lang/Object;)Lorg/json/JSONObject;
    //   30: pop
    //   31: getstatic 30	o/wn:ˎ	I
    //   34: bipush 105
    //   36: iadd
    //   37: istore_3
    //   38: iload_3
    //   39: sipush 128
    //   42: irem
    //   43: putstatic 32	o/wn:ॱ	I
    //   46: iload_3
    //   47: iconst_2
    //   48: irem
    //   49: ifne +6 -> 55
    //   52: goto +35 -> 87
    //   55: goto +54 -> 109
    //   58: iload_3
    //   59: tableswitch	default:+21->80, 0:+31->90, 1:+27->86
    //   80: return
    //   81: iconst_0
    //   82: istore_3
    //   83: goto -25 -> 58
    //   86: return
    //   87: goto +22 -> 109
    //   90: new 227	java/lang/NullPointerException
    //   93: dup
    //   94: invokespecial 228	java/lang/NullPointerException:<init>	()V
    //   97: athrow
    //   98: iconst_1
    //   99: istore_3
    //   100: goto -42 -> 58
    //   103: astore_0
    //   104: aload_0
    //   105: athrow
    //   106: goto +9 -> 115
    //   109: goto -3 -> 106
    //   112: goto -109 -> 3
    //   115: getstatic 30	o/wn:ˎ	I
    //   118: bipush 69
    //   120: iadd
    //   121: istore_3
    //   122: iload_3
    //   123: sipush 128
    //   126: irem
    //   127: putstatic 32	o/wn:ॱ	I
    //   130: iload_3
    //   131: iconst_2
    //   132: irem
    //   133: ifne +6 -> 139
    //   136: goto -55 -> 81
    //   139: goto -41 -> 98
    //   142: astore_0
    //   143: new 218	java/lang/IllegalStateException
    //   146: dup
    //   147: ldc -36
    //   149: aload_0
    //   150: invokespecial 223	java/lang/IllegalStateException:<init>	(Ljava/lang/String;Ljava/lang/Throwable;)V
    //   153: athrow
    //   154: astore_0
    //   155: aload_0
    //   156: athrow
    // Local variable table:
    //   start	length	slot	name	signature
    //   0	157	0	paramJSONObject1	JSONObject
    //   0	157	1	paramString	String
    //   0	157	2	paramJSONObject2	JSONObject
    //   37	96	3	i	int
    // Exception table:
    //   from	to	target	type
    //   115	122	103	java/lang/Exception
    //   122	130	103	java/lang/Exception
    //   24	31	142	org/json/JSONException
    //   122	130	154	java/lang/Exception
  }
  
  /* Error */
  public static Uri ˏ(JSONObject paramJSONObject, String paramString)
  {
    // Byte code:
    //   0: goto +31 -> 31
    //   3: aload_0
    //   4: ldc 64
    //   6: invokestatic 69	o/wv:ˋ	(Ljava/lang/Object;Ljava/lang/Object;)Ljava/lang/Object;
    //   9: pop
    //   10: aload_1
    //   11: ldc 71
    //   13: invokestatic 69	o/wv:ˋ	(Ljava/lang/Object;Ljava/lang/Object;)Ljava/lang/Object;
    //   16: pop
    //   17: aload_0
    //   18: aload_1
    //   19: invokevirtual 77	org/json/JSONObject:has	(Ljava/lang/String;)Z
    //   22: ifne +6 -> 28
    //   25: goto +24 -> 49
    //   28: goto +124 -> 152
    //   31: goto +29 -> 60
    //   34: astore_0
    //   35: aload_0
    //   36: athrow
    //   37: goto -34 -> 3
    //   40: astore_0
    //   41: aload_0
    //   42: athrow
    //   43: goto +131 -> 174
    //   46: goto -3 -> 43
    //   49: bipush 60
    //   51: istore_2
    //   52: goto +124 -> 176
    //   55: aload_0
    //   56: invokestatic 235	android/net/Uri:parse	(Ljava/lang/String;)Landroid/net/Uri;
    //   59: areturn
    //   60: getstatic 30	o/wn:ˎ	I
    //   63: bipush 109
    //   65: iadd
    //   66: istore_2
    //   67: iload_2
    //   68: sipush 128
    //   71: irem
    //   72: putstatic 32	o/wn:ॱ	I
    //   75: iload_2
    //   76: iconst_2
    //   77: irem
    //   78: ifne +6 -> 84
    //   81: goto -44 -> 37
    //   84: goto -81 -> 3
    //   87: getstatic 32	o/wn:ॱ	I
    //   90: bipush 65
    //   92: iadd
    //   93: istore_2
    //   94: iload_2
    //   95: sipush 128
    //   98: irem
    //   99: putstatic 30	o/wn:ˎ	I
    //   102: iload_2
    //   103: iconst_2
    //   104: irem
    //   105: ifeq +6 -> 111
    //   108: goto -62 -> 46
    //   111: goto -68 -> 43
    //   114: new 147	java/lang/StringBuilder
    //   117: dup
    //   118: invokespecial 148	java/lang/StringBuilder:<init>	()V
    //   121: astore_0
    //   122: aload_0
    //   123: ldc -106
    //   125: invokevirtual 154	java/lang/StringBuilder:append	(Ljava/lang/String;)Ljava/lang/StringBuilder;
    //   128: astore_0
    //   129: aload_0
    //   130: aload_1
    //   131: invokevirtual 154	java/lang/StringBuilder:append	(Ljava/lang/String;)Ljava/lang/StringBuilder;
    //   134: astore_0
    //   135: new 145	org/json/JSONException
    //   138: dup
    //   139: aload_0
    //   140: ldc -100
    //   142: invokevirtual 154	java/lang/StringBuilder:append	(Ljava/lang/String;)Ljava/lang/StringBuilder;
    //   145: invokevirtual 157	java/lang/StringBuilder:toString	()Ljava/lang/String;
    //   148: invokespecial 160	org/json/JSONException:<init>	(Ljava/lang/String;)V
    //   151: athrow
    //   152: bipush 25
    //   154: istore_2
    //   155: goto +21 -> 176
    //   158: aload_0
    //   159: aload_1
    //   160: invokevirtual 93	org/json/JSONObject:getString	(Ljava/lang/String;)Ljava/lang/String;
    //   163: astore_0
    //   164: aload_0
    //   165: ifnonnull +6 -> 171
    //   168: goto -54 -> 114
    //   171: goto -116 -> 55
    //   174: aconst_null
    //   175: areturn
    //   176: iload_2
    //   177: lookupswitch	default:+27->204, 25:+-19->158, 60:+-90->87
    //   204: goto -46 -> 158
    // Local variable table:
    //   start	length	slot	name	signature
    //   0	207	0	paramJSONObject	JSONObject
    //   0	207	1	paramString	String
    //   51	126	2	i	int
    // Exception table:
    //   from	to	target	type
    //   122	129	34	java/lang/Exception
    //   129	135	34	java/lang/Exception
    //   135	152	34	java/lang/Exception
    //   122	129	40	java/lang/Exception
  }
  
  /* Error */
  public static String ॱ(JSONObject paramJSONObject, String paramString)
  {
    // Byte code:
    //   0: goto +203 -> 203
    //   3: bipush 18
    //   5: istore_2
    //   6: goto +119 -> 125
    //   9: astore_0
    //   10: aload_0
    //   11: athrow
    //   12: aload_0
    //   13: areturn
    //   14: getstatic 32	o/wn:ॱ	I
    //   17: bipush 111
    //   19: iadd
    //   20: istore_2
    //   21: iload_2
    //   22: sipush 128
    //   25: irem
    //   26: putstatic 30	o/wn:ˎ	I
    //   29: iload_2
    //   30: iconst_2
    //   31: irem
    //   32: ifeq +6 -> 38
    //   35: goto -32 -> 3
    //   38: goto +127 -> 165
    //   41: aload_0
    //   42: aload_1
    //   43: invokevirtual 93	org/json/JSONObject:getString	(Ljava/lang/String;)Ljava/lang/String;
    //   46: astore_0
    //   47: aload_0
    //   48: ifnonnull +6 -> 54
    //   51: goto +212 -> 263
    //   54: goto +152 -> 206
    //   57: new 145	org/json/JSONException
    //   60: dup
    //   61: new 147	java/lang/StringBuilder
    //   64: dup
    //   65: invokespecial 148	java/lang/StringBuilder:<init>	()V
    //   68: ldc -106
    //   70: invokevirtual 154	java/lang/StringBuilder:append	(Ljava/lang/String;)Ljava/lang/StringBuilder;
    //   73: aload_1
    //   74: invokevirtual 154	java/lang/StringBuilder:append	(Ljava/lang/String;)Ljava/lang/StringBuilder;
    //   77: ldc_w 278
    //   80: invokevirtual 154	java/lang/StringBuilder:append	(Ljava/lang/String;)Ljava/lang/StringBuilder;
    //   83: invokevirtual 157	java/lang/StringBuilder:toString	()Ljava/lang/String;
    //   86: invokespecial 160	org/json/JSONException:<init>	(Ljava/lang/String;)V
    //   89: athrow
    //   90: aload_0
    //   91: ldc 64
    //   93: invokestatic 69	o/wv:ˋ	(Ljava/lang/Object;Ljava/lang/Object;)Ljava/lang/Object;
    //   96: pop
    //   97: aload_1
    //   98: ldc 71
    //   100: invokestatic 69	o/wv:ˋ	(Ljava/lang/Object;Ljava/lang/Object;)Ljava/lang/Object;
    //   103: pop
    //   104: aload_0
    //   105: aload_1
    //   106: invokevirtual 77	org/json/JSONObject:has	(Ljava/lang/String;)Z
    //   109: istore_3
    //   110: bipush 52
    //   112: iconst_0
    //   113: idiv
    //   114: istore_2
    //   115: iload_3
    //   116: ifne +6 -> 122
    //   119: goto -62 -> 57
    //   122: goto -81 -> 41
    //   125: iload_2
    //   126: lookupswitch	default:+26->152, 18:+-36->90, 40:+109->235
    //   152: goto -62 -> 90
    //   155: aconst_null
    //   156: arraylength
    //   157: istore_2
    //   158: aload_0
    //   159: areturn
    //   160: iconst_1
    //   161: istore_2
    //   162: goto +47 -> 209
    //   165: bipush 40
    //   167: istore_2
    //   168: goto -43 -> 125
    //   171: iconst_0
    //   172: istore_2
    //   173: goto +36 -> 209
    //   176: getstatic 32	o/wn:ॱ	I
    //   179: bipush 111
    //   181: iadd
    //   182: istore_2
    //   183: iload_2
    //   184: sipush 128
    //   187: irem
    //   188: putstatic 30	o/wn:ˎ	I
    //   191: iload_2
    //   192: iconst_2
    //   193: irem
    //   194: ifeq +6 -> 200
    //   197: goto -26 -> 171
    //   200: goto -40 -> 160
    //   203: goto -189 -> 14
    //   206: goto -30 -> 176
    //   209: iload_2
    //   210: tableswitch	default:+22->232, 0:+-55->155, 1:+-198->12
    //   232: goto -77 -> 155
    //   235: aload_0
    //   236: ldc 64
    //   238: invokestatic 69	o/wv:ˋ	(Ljava/lang/Object;Ljava/lang/Object;)Ljava/lang/Object;
    //   241: pop
    //   242: aload_1
    //   243: ldc 71
    //   245: invokestatic 69	o/wv:ˋ	(Ljava/lang/Object;Ljava/lang/Object;)Ljava/lang/Object;
    //   248: pop
    //   249: aload_0
    //   250: aload_1
    //   251: invokevirtual 77	org/json/JSONObject:has	(Ljava/lang/String;)Z
    //   254: ifne +6 -> 260
    //   257: goto -200 -> 57
    //   260: goto -219 -> 41
    //   263: new 147	java/lang/StringBuilder
    //   266: dup
    //   267: invokespecial 148	java/lang/StringBuilder:<init>	()V
    //   270: astore_0
    //   271: aload_0
    //   272: ldc -106
    //   274: invokevirtual 154	java/lang/StringBuilder:append	(Ljava/lang/String;)Ljava/lang/StringBuilder;
    //   277: astore_0
    //   278: aload_0
    //   279: aload_1
    //   280: invokevirtual 154	java/lang/StringBuilder:append	(Ljava/lang/String;)Ljava/lang/StringBuilder;
    //   283: astore_0
    //   284: new 145	org/json/JSONException
    //   287: dup
    //   288: aload_0
    //   289: ldc -100
    //   291: invokevirtual 154	java/lang/StringBuilder:append	(Ljava/lang/String;)Ljava/lang/StringBuilder;
    //   294: invokevirtual 157	java/lang/StringBuilder:toString	()Ljava/lang/String;
    //   297: invokespecial 160	org/json/JSONException:<init>	(Ljava/lang/String;)V
    //   300: athrow
    // Local variable table:
    //   start	length	slot	name	signature
    //   0	301	0	paramJSONObject	JSONObject
    //   0	301	1	paramString	String
    //   5	205	2	i	int
    //   109	7	3	bool	boolean
    // Exception table:
    //   from	to	target	type
    //   271	278	9	java/lang/Exception
    //   278	284	9	java/lang/Exception
    //   284	301	9	java/lang/Exception
  }
  
  public static List<Uri> ॱ(JSONArray paramJSONArray)
  {
    break label39;
    int i = j;
    break label97;
    label8:
    int j = 0;
    for (;;)
    {
      try
      {
        i = ॱ;
        i += 47;
        ˎ = i % 128;
        if (i % 2 == 0)
        {
          continue;
          label39:
          continue;
          i = ॱ + 101;
          ˎ = i % 128;
          if (i % 2 != 0) {
            continue;
          }
          break label8;
          ((List)localObject).add(Uri.parse(wv.ˋ(paramJSONArray.get(i)).toString()));
          i += 1;
          break label181;
          label97:
          if (i < paramJSONArray.length()) {
            break label184;
          }
          break label215;
        }
        i = 1;
        break label190;
        return localObject;
        i = 0;
        break label190;
        i = j;
        continue;
        switch (j)
        {
        }
        return localObject;
        Object localObject = new ArrayList();
        if (paramJSONArray != null) {
          continue;
        }
        return localObject;
      }
      catch (Exception paramJSONArray)
      {
        throw paramJSONArray;
      }
      label181:
      continue;
      label184:
      j = 94;
      continue;
      label190:
      switch (i)
      {
      }
      break;
      label215:
      j = 92;
    }
  }
  
  public static void ॱ(JSONObject paramJSONObject, String paramString, int paramInt)
  {
    break label103;
    int i = 0;
    break label35;
    label8:
    paramInt = ॱ + 31;
    ˎ = paramInt % 128;
    if (paramInt % 2 == 0) {
      break label92;
    }
    for (;;)
    {
      switch (i)
      {
      default: 
        break;
      case 1: 
        try
        {
          label35:
          label92:
          label103:
          for (;;)
          {
            i = ॱ;
            i += 1;
            ˎ = i % 128;
            if (i % 2 != 0) {
              break;
            }
            break label176;
            return;
            paramInt = 0;
            break label148;
            paramInt = 37 / 0;
            return;
          }
        }
        catch (Exception paramJSONObject)
        {
          try
          {
            wv.ˋ(paramJSONObject, "json must not be null");
            wv.ˋ(paramString, "field must not be null");
            wv.ˋ(Integer.valueOf(paramInt), "value must not be null");
            try
            {
              paramJSONObject.put(paramString, paramInt);
            }
            catch (JSONException paramJSONObject)
            {
              throw new IllegalStateException("JSONException thrown in violation of contract, ex");
            }
            paramInt = 1;
            break label148;
            break label8;
            label148:
            switch (paramInt)
            {
            }
            return;
          }
          catch (Exception paramJSONObject)
          {
            throw paramJSONObject;
          }
          paramJSONObject = paramJSONObject;
          throw paramJSONObject;
        }
        label176:
        i = 1;
      }
    }
    for (;;)
    {
      break;
      wv.ˋ(paramJSONObject, "json must not be null");
      wv.ˋ(paramString, "field must not be null");
      wv.ˋ(Integer.valueOf(paramInt), "value must not be null");
      paramJSONObject.put(paramString, paramInt);
      paramInt = 85 / 0;
    }
  }
  
  public static Long ॱॱ(JSONObject paramJSONObject, String paramString)
  {
    break label185;
    int i = 29;
    break label149;
    i = 87;
    label15:
    label45:
    label149:
    label185:
    for (;;)
    {
      i = ॱ + 115;
      ˎ = i % 128;
      if (i % 2 == 0) {
        break label45;
      }
      wv.ˋ(paramJSONObject, "json must not be null");
      wv.ˋ(paramString, "field must not be null");
      if (paramJSONObject.has(paramString)) {}
      for (i = 10;; i = 62) {
        switch (i)
        {
        case 62: 
        default: 
          break label15;
          i = ˎ + 21;
          ॱ = i % 128;
          if (i % 2 == 0) {
            break;
          }
          break;
        case 10: 
          for (;;)
          {
            return null;
            return Long.valueOf(paramJSONObject.getLong(paramString));
            throw new NullPointerException();
            switch (i)
            {
            }
          }
        }
      }
    }
  }
  
  /* Error */
  public static List<Uri> ᐝ(JSONObject paramJSONObject, String paramString)
  {
    // Byte code:
    //   0: goto +67 -> 67
    //   3: goto +77 -> 80
    //   6: astore_0
    //   7: aload_0
    //   8: athrow
    //   9: aload_0
    //   10: areturn
    //   11: astore_0
    //   12: aload_0
    //   13: athrow
    //   14: getstatic 32	o/wn:ॱ	I
    //   17: bipush 65
    //   19: iadd
    //   20: istore_2
    //   21: iload_2
    //   22: sipush 128
    //   25: irem
    //   26: putstatic 30	o/wn:ˎ	I
    //   29: iload_2
    //   30: iconst_2
    //   31: irem
    //   32: ifeq +6 -> 38
    //   35: goto +35 -> 70
    //   38: goto +37 -> 75
    //   41: getstatic 30	o/wn:ˎ	I
    //   44: iconst_3
    //   45: iadd
    //   46: istore_2
    //   47: iload_2
    //   48: sipush 128
    //   51: irem
    //   52: putstatic 32	o/wn:ॱ	I
    //   55: iload_2
    //   56: iconst_2
    //   57: irem
    //   58: ifne +6 -> 64
    //   61: goto -58 -> 3
    //   64: goto +16 -> 80
    //   67: goto -26 -> 41
    //   70: iconst_0
    //   71: istore_2
    //   72: goto +69 -> 141
    //   75: iconst_1
    //   76: istore_2
    //   77: goto +64 -> 141
    //   80: aload_0
    //   81: ldc 64
    //   83: invokestatic 69	o/wv:ˋ	(Ljava/lang/Object;Ljava/lang/Object;)Ljava/lang/Object;
    //   86: pop
    //   87: aload_1
    //   88: ldc 71
    //   90: invokestatic 69	o/wv:ˋ	(Ljava/lang/Object;Ljava/lang/Object;)Ljava/lang/Object;
    //   93: pop
    //   94: aload_0
    //   95: aload_1
    //   96: invokevirtual 77	org/json/JSONObject:has	(Ljava/lang/String;)Z
    //   99: ifne +6 -> 105
    //   102: goto +6 -> 108
    //   105: goto +64 -> 169
    //   108: new 145	org/json/JSONException
    //   111: dup
    //   112: new 147	java/lang/StringBuilder
    //   115: dup
    //   116: invokespecial 148	java/lang/StringBuilder:<init>	()V
    //   119: ldc -106
    //   121: invokevirtual 154	java/lang/StringBuilder:append	(Ljava/lang/String;)Ljava/lang/StringBuilder;
    //   124: aload_1
    //   125: invokevirtual 154	java/lang/StringBuilder:append	(Ljava/lang/String;)Ljava/lang/StringBuilder;
    //   128: ldc_w 278
    //   131: invokevirtual 154	java/lang/StringBuilder:append	(Ljava/lang/String;)Ljava/lang/StringBuilder;
    //   134: invokevirtual 157	java/lang/StringBuilder:toString	()Ljava/lang/String;
    //   137: invokespecial 160	org/json/JSONException:<init>	(Ljava/lang/String;)V
    //   140: athrow
    //   141: iload_2
    //   142: tableswitch	default:+22->164, 0:+22->164, 1:+-133->9
    //   164: aconst_null
    //   165: arraylength
    //   166: istore_2
    //   167: aload_0
    //   168: areturn
    //   169: aload_0
    //   170: aload_1
    //   171: invokevirtual 141	org/json/JSONObject:getJSONArray	(Ljava/lang/String;)Lorg/json/JSONArray;
    //   174: invokestatic 306	o/wn:ॱ	(Lorg/json/JSONArray;)Ljava/util/List;
    //   177: astore_0
    //   178: goto -164 -> 14
    // Local variable table:
    //   start	length	slot	name	signature
    //   0	181	0	paramJSONObject	JSONObject
    //   0	181	1	paramString	String
    //   20	147	2	i	int
    // Exception table:
    //   from	to	target	type
    //   21	29	6	java/lang/Exception
    //   14	21	11	java/lang/Exception
    //   21	29	11	java/lang/Exception
  }
  
  static final class If
    extends wn.ˊ<Boolean>
  {
    If(String paramString, boolean paramBoolean)
    {
      super(Boolean.valueOf(paramBoolean));
    }
    
    Boolean ˊ(String paramString)
    {
      return Boolean.valueOf(Boolean.parseBoolean(paramString));
    }
  }
  
  static final class iF
    extends wn.ˊ<String>
  {
    iF(String paramString)
    {
      this(paramString, null);
    }
    
    iF(String paramString1, String paramString2)
    {
      super(paramString2);
    }
    
    String ˋ(String paramString)
    {
      return paramString;
    }
  }
  
  static final class if
    extends wn.ˋ<String>
  {
    if(String paramString)
    {
      super(null);
    }
    
    if(String paramString, List<String> paramList)
    {
      super(paramList);
    }
  }
  
  static abstract class ˊ<T>
  {
    public final T ˋ;
    public final String ˎ;
    
    ˊ(String paramString, T paramT)
    {
      this.ˎ = paramString;
      this.ˋ = paramT;
    }
    
    abstract T ˎ(String paramString);
  }
  
  static abstract class ˋ<T>
  {
    public final String ˎ;
    public final List<T> ॱ;
    
    ˋ(String paramString, List<T> paramList)
    {
      this.ˎ = paramString;
      this.ॱ = paramList;
    }
  }
  
  static final class ˎ
    extends wn.ˊ<Uri>
  {
    ˎ(String paramString)
    {
      this(paramString, null);
    }
    
    ˎ(String paramString, Uri paramUri)
    {
      super(paramUri);
    }
    
    Uri ˊ(String paramString)
    {
      return Uri.parse(paramString);
    }
  }
}
