package o;

public class x
  extends ᐸ.If
{
  private static char[] ߺ = { 99, 111, 110, 116, 101, 120, 100, 102, 103 };
  private static int ॱˌ = 0;
  private static int ॱˍ = 1;
  private static char ॱـ = '\003';
  private w ॱˈ;
  
  /* Error */
  protected x(android.content.Context arg1)
  {
    // Byte code:
    //   0: bipush 7
    //   2: bipush 7
    //   4: newarray char
    //   6: dup
    //   7: iconst_0
    //   8: ldc 38
    //   10: castore
    //   11: dup
    //   12: iconst_1
    //   13: ldc 39
    //   15: castore
    //   16: dup
    //   17: iconst_2
    //   18: ldc 40
    //   20: castore
    //   21: dup
    //   22: iconst_3
    //   23: ldc 41
    //   25: castore
    //   26: dup
    //   27: iconst_4
    //   28: ldc 41
    //   30: castore
    //   31: dup
    //   32: iconst_5
    //   33: ldc 42
    //   35: castore
    //   36: dup
    //   37: bipush 6
    //   39: ldc 43
    //   41: castore
    //   42: bipush 119
    //   44: invokestatic 47	o/x:ˋ	(I[CB)Ljava/lang/String;
    //   47: astore_2
    //   48: aload_2
    //   49: invokevirtual 53	java/lang/String:intern	()Ljava/lang/String;
    //   52: astore_2
    //   53: aload_1
    //   54: aload_2
    //   55: invokestatic 59	o/vq:ˎ	(Ljava/lang/Object;Ljava/lang/String;)V
    //   58: aload_0
    //   59: aload_1
    //   60: invokespecial 61	o/ᐸ$If:<init>	(Landroid/content/Context;)V
    //   63: return
    //   64: astore_1
    //   65: aload_1
    //   66: athrow
    //   67: astore_1
    //   68: aload_1
    //   69: athrow
    // Exception table:
    //   from	to	target	type
    //   0	48	67	java/lang/Exception
    //   48	53	67	java/lang/Exception
    //   53	58	67	java/lang/Exception
    //   58	63	67	java/lang/Exception
  }
  
  private static String ˋ(int paramInt, char[] paramArrayOfChar, byte paramByte)
  {
    break label406;
    int i = 0;
    break label29;
    byte b1;
    if (paramInt <= 1)
    {
      break label266;
      b1 = 0;
    }
    label25:
    label29:
    label40:
    label73:
    label102:
    label214:
    label241:
    label266:
    label271:
    label283:
    label311:
    label317:
    label406:
    label432:
    label462:
    label497:
    label523:
    label597:
    label600:
    label630:
    label667:
    label673:
    for (;;)
    {
      i += 2;
      if (i >= paramInt) {
        break label667;
      }
      for (;;)
      {
        char[] arrayOfChar1;
        int j;
        char[] arrayOfChar2;
        byte b2;
        byte b3;
        int k;
        int m;
        switch (b1)
        {
        default: 
          break label432;
          for (;;)
          {
            b1 = 1;
            break label462;
            arrayOfChar1 = ߺ;
            i = paramInt;
            j = ॱـ;
            arrayOfChar2 = new char[i];
            if (i % 2 != 0) {
              break;
            }
          }
          b3 = oO.ॱ(b2, j);
          k = oO.ˋ(b2, j);
          b2 = oO.ॱ(b1, j);
          m = oO.ˋ(b1, j);
          if (k != m)
          {
            break label523;
            for (;;)
            {
              b1 = oO.ˊ(b3, j);
              b2 = oO.ˊ(b2, j);
              b1 = oO.ˏ(b1, k, j);
              b2 = oO.ˏ(b2, m, j);
              arrayOfChar2[i] = arrayOfChar1[b1];
              arrayOfChar2[(i + 1)] = arrayOfChar1[b2];
              break label25;
              i = ॱˌ + 53;
              ॱˍ = i % 128;
              if (i % 2 == 0) {
                break label597;
              }
              break;
              b2 = paramArrayOfChar[i];
              b1 = paramArrayOfChar[(i + 1)];
              if (b2 == b1) {
                break label600;
              }
              break label102;
              i = 0;
              break label497;
              b1 = 0;
              break label630;
              b1 = 1;
              break label40;
              switch (b1)
              {
              }
            }
            b1 = 1;
          }
          break;
        case 0: 
          return new String(arrayOfChar2);
        }
        for (;;)
        {
          try
          {
            b1 = oO.ˊ(k, j);
            k = oO.ˊ(m, j);
            try
            {
              b1 = oO.ˏ(b3, b1, j);
              b2 = oO.ˏ(b2, k, j);
              arrayOfChar2[i] = arrayOfChar1[b1];
              arrayOfChar2[(i + 1)] = arrayOfChar1[b2];
            }
            catch (Exception paramArrayOfChar)
            {
              throw paramArrayOfChar;
            }
            continue;
            if (b3 == b2) {
              break label271;
            }
            break label311;
            break label73;
            paramInt = i - 1;
            arrayOfChar2[paramInt] = ((char)(paramArrayOfChar[paramInt] - paramByte));
            break label214;
            b1 = 1;
            break label283;
            b1 = ॱˌ + 13;
            ॱˍ = b1 % 128;
            if (b1 % 2 != 0)
            {
              break label241;
              paramInt = i;
              switch (b1)
              {
              }
              continue;
            }
            break label241;
            switch (i)
            {
            }
            break label317;
            b1 = 0;
            break label283;
            b1 = oO.ˏ(b3, m, j);
            b2 = oO.ˏ(b2, k, j);
            arrayOfChar2[i] = arrayOfChar1[b1];
            arrayOfChar2[(i + 1)] = arrayOfChar1[b2];
            break label673;
            arrayOfChar2[i] = ((char)(b2 - paramByte));
            arrayOfChar2[(i + 1)] = ((char)(b1 - paramByte));
          }
          catch (Exception paramArrayOfChar)
          {
            throw paramArrayOfChar;
          }
          break;
          b3 = ॱˌ + 43;
          ॱˍ = b3 % 128;
          if (b3 % 2 != 0)
          {
            continue;
            switch (b1)
            {
            }
            continue;
            i = 1;
          }
        }
        b1 = 0;
      }
    }
  }
  
  /* Error */
  public final void ʻ()
  {
    // Byte code:
    //   0: goto +98 -> 98
    //   3: getstatic 19	o/x:ॱˍ	I
    //   6: bipush 93
    //   8: iadd
    //   9: istore_1
    //   10: iload_1
    //   11: sipush 128
    //   14: irem
    //   15: putstatic 17	o/x:ॱˌ	I
    //   18: iload_1
    //   19: iconst_2
    //   20: irem
    //   21: ifeq +6 -> 27
    //   24: goto +10 -> 34
    //   27: return
    //   28: invokestatic 82	o/vq:ˎ	()V
    //   31: goto +88 -> 119
    //   34: aconst_null
    //   35: arraylength
    //   36: istore_1
    //   37: return
    //   38: iconst_1
    //   39: istore_1
    //   40: goto +132 -> 172
    //   43: iconst_0
    //   44: istore_1
    //   45: goto +127 -> 172
    //   48: iconst_0
    //   49: istore_1
    //   50: goto +164 -> 214
    //   53: getstatic 17	o/x:ॱˌ	I
    //   56: bipush 93
    //   58: iadd
    //   59: istore_1
    //   60: iload_1
    //   61: sipush 128
    //   64: irem
    //   65: putstatic 19	o/x:ॱˍ	I
    //   68: iload_1
    //   69: iconst_2
    //   70: irem
    //   71: ifne +6 -> 77
    //   74: goto -26 -> 48
    //   77: goto +55 -> 132
    //   80: aload_0
    //   81: invokevirtual 85	o/x:ˊ	()Z
    //   84: istore_2
    //   85: aconst_null
    //   86: arraylength
    //   87: istore_1
    //   88: iload_2
    //   89: ifeq +6 -> 95
    //   92: goto -54 -> 38
    //   95: goto -52 -> 43
    //   98: goto -45 -> 53
    //   101: aload_0
    //   102: invokevirtual 85	o/x:ˊ	()Z
    //   105: istore_2
    //   106: iload_2
    //   107: ifeq +6 -> 113
    //   110: goto +89 -> 199
    //   113: goto -110 -> 3
    //   116: astore_3
    //   117: aload_3
    //   118: athrow
    //   119: goto +6 -> 125
    //   122: astore_3
    //   123: aload_3
    //   124: athrow
    //   125: aload_3
    //   126: invokevirtual 90	o/w:dismiss	()V
    //   129: goto -126 -> 3
    //   132: iconst_1
    //   133: istore_1
    //   134: goto +80 -> 214
    //   137: iconst_0
    //   138: istore_1
    //   139: iload_1
    //   140: tableswitch	default:+24->164, 0:+-112->28, 1:+-15->125
    //   164: goto -136 -> 28
    //   167: iconst_1
    //   168: istore_1
    //   169: goto -30 -> 139
    //   172: iload_1
    //   173: tableswitch	default:+23->196, 0:+-170->3, 1:+26->199
    //   196: goto -193 -> 3
    //   199: aload_0
    //   200: getfield 92	o/x:ॱˈ	Lo/w;
    //   203: astore_3
    //   204: aload_3
    //   205: ifnonnull +6 -> 211
    //   208: goto -71 -> 137
    //   211: goto -44 -> 167
    //   214: iload_1
    //   215: tableswitch	default:+21->236, 0:+-135->80, 1:+-114->101
    //   236: goto -135 -> 101
    // Local variable table:
    //   start	length	slot	name	signature
    //   0	239	0	this	x
    //   9	206	1	i	int
    //   84	23	2	bool	boolean
    //   116	2	3	localException1	Exception
    //   122	4	3	localException2	Exception
    //   203	2	3	localW	w
    // Exception table:
    //   from	to	target	type
    //   199	204	116	java/lang/Exception
    //   101	106	122	java/lang/Exception
  }
  
  /* Error */
  public final boolean ˊ()
  {
    // Byte code:
    //   0: goto +15 -> 15
    //   3: bipush 73
    //   5: istore_1
    //   6: goto +119 -> 125
    //   9: invokestatic 82	o/vq:ˎ	()V
    //   12: goto +143 -> 155
    //   15: goto +174 -> 189
    //   18: getstatic 17	o/x:ॱˌ	I
    //   21: bipush 31
    //   23: iadd
    //   24: istore_1
    //   25: iload_1
    //   26: sipush 128
    //   29: irem
    //   30: putstatic 19	o/x:ॱˍ	I
    //   33: iload_1
    //   34: iconst_2
    //   35: irem
    //   36: ifne +6 -> 42
    //   39: goto +50 -> 89
    //   42: goto +81 -> 123
    //   45: bipush 56
    //   47: istore_1
    //   48: goto +43 -> 91
    //   51: astore_2
    //   52: aload_2
    //   53: athrow
    //   54: bipush 79
    //   56: istore_1
    //   57: goto +68 -> 125
    //   60: getstatic 19	o/x:ॱˍ	I
    //   63: bipush 9
    //   65: iadd
    //   66: istore_1
    //   67: iload_1
    //   68: sipush 128
    //   71: irem
    //   72: putstatic 17	o/x:ॱˌ	I
    //   75: iload_1
    //   76: iconst_2
    //   77: irem
    //   78: ifeq +6 -> 84
    //   81: goto -27 -> 54
    //   84: goto -81 -> 3
    //   87: iconst_0
    //   88: ireturn
    //   89: iconst_0
    //   90: ireturn
    //   91: iload_1
    //   92: lookupswitch	default:+28->120, 56:+-5->87, 80:+82->174
    //   120: goto +54 -> 174
    //   123: iconst_1
    //   124: ireturn
    //   125: iload_1
    //   126: lookupswitch	default:+26->152, 73:+-117->9, 79:+76->202
    //   152: goto +50 -> 202
    //   155: aload_2
    //   156: invokevirtual 95	o/w:isShowing	()Z
    //   159: ifeq +6 -> 165
    //   162: goto -144 -> 18
    //   165: goto -78 -> 87
    //   168: bipush 80
    //   170: istore_1
    //   171: goto -80 -> 91
    //   174: aload_0
    //   175: getfield 92	o/x:ॱˈ	Lo/w;
    //   178: astore_2
    //   179: aload_2
    //   180: ifnonnull +6 -> 186
    //   183: goto -123 -> 60
    //   186: goto -31 -> 155
    //   189: aload_0
    //   190: getfield 92	o/x:ॱˈ	Lo/w;
    //   193: ifnull +6 -> 199
    //   196: goto -28 -> 168
    //   199: goto -154 -> 45
    //   202: invokestatic 82	o/vq:ˎ	()V
    //   205: aconst_null
    //   206: arraylength
    //   207: istore_1
    //   208: goto -196 -> 12
    // Local variable table:
    //   start	length	slot	name	signature
    //   0	211	0	this	x
    //   5	203	1	i	int
    //   51	105	2	localException	Exception
    //   178	2	2	localW	w
    // Exception table:
    //   from	to	target	type
    //   174	179	51	java/lang/Exception
  }
  
  /* Error */
  public ᐸ ˏ()
  {
    // Byte code:
    //   0: goto +171 -> 171
    //   3: bipush 14
    //   5: istore_1
    //   6: goto +104 -> 110
    //   9: bipush 25
    //   11: istore_1
    //   12: goto +98 -> 110
    //   15: aload_0
    //   16: invokevirtual 85	o/x:ˊ	()Z
    //   19: ifne +6 -> 25
    //   22: goto +182 -> 204
    //   25: goto +128 -> 153
    //   28: getstatic 19	o/x:ॱˍ	I
    //   31: iconst_1
    //   32: iadd
    //   33: istore_1
    //   34: iload_1
    //   35: sipush 128
    //   38: irem
    //   39: putstatic 17	o/x:ॱˌ	I
    //   42: iload_1
    //   43: iconst_2
    //   44: irem
    //   45: ifeq +6 -> 51
    //   48: goto +32 -> 80
    //   51: goto +183 -> 234
    //   54: invokestatic 82	o/vq:ˎ	()V
    //   57: bipush 21
    //   59: iconst_0
    //   60: idiv
    //   61: istore_1
    //   62: aload_2
    //   63: invokevirtual 99	o/w:show	()V
    //   66: goto +87 -> 153
    //   69: invokestatic 82	o/vq:ˎ	()V
    //   72: new 101	java/lang/NullPointerException
    //   75: dup
    //   76: invokespecial 103	java/lang/NullPointerException:<init>	()V
    //   79: athrow
    //   80: iconst_1
    //   81: istore_1
    //   82: iload_1
    //   83: tableswitch	default:+21->104, 0:+56->139, 1:+-29->54
    //   104: goto -50 -> 54
    //   107: astore_2
    //   108: aload_2
    //   109: athrow
    //   110: iload_1
    //   111: lookupswitch	default:+25->136, 14:+128->239, 25:+37->148
    //   136: goto +103 -> 239
    //   139: invokestatic 82	o/vq:ˎ	()V
    //   142: goto -80 -> 62
    //   145: invokestatic 82	o/vq:ˎ	()V
    //   148: aload_2
    //   149: checkcast 105	o/ᐸ
    //   152: areturn
    //   153: aload_0
    //   154: getfield 92	o/x:ॱˈ	Lo/w;
    //   157: astore_2
    //   158: aload_2
    //   159: ifnonnull +6 -> 165
    //   162: goto -159 -> 3
    //   165: goto -156 -> 9
    //   168: astore_2
    //   169: aload_2
    //   170: athrow
    //   171: goto +6 -> 177
    //   174: goto -159 -> 15
    //   177: getstatic 19	o/x:ॱˍ	I
    //   180: bipush 65
    //   182: iadd
    //   183: istore_1
    //   184: iload_1
    //   185: sipush 128
    //   188: irem
    //   189: putstatic 17	o/x:ॱˌ	I
    //   192: iload_1
    //   193: iconst_2
    //   194: irem
    //   195: ifeq +6 -> 201
    //   198: goto -24 -> 174
    //   201: goto -186 -> 15
    //   204: aload_0
    //   205: new 87	o/w
    //   208: dup
    //   209: aload_0
    //   210: checkcast 4	o/ᐸ$If
    //   213: invokespecial 108	o/w:<init>	(Lo/ᐸ$If;)V
    //   216: putfield 92	o/x:ॱˈ	Lo/w;
    //   219: aload_0
    //   220: getfield 92	o/x:ॱˈ	Lo/w;
    //   223: astore_2
    //   224: aload_2
    //   225: ifnonnull +6 -> 231
    //   228: goto -200 -> 28
    //   231: goto -169 -> 62
    //   234: iconst_0
    //   235: istore_1
    //   236: goto -154 -> 82
    //   239: getstatic 19	o/x:ॱˍ	I
    //   242: bipush 43
    //   244: iadd
    //   245: istore_1
    //   246: iload_1
    //   247: sipush 128
    //   250: irem
    //   251: putstatic 17	o/x:ॱˌ	I
    //   254: iload_1
    //   255: iconst_2
    //   256: irem
    //   257: ifeq +6 -> 263
    //   260: goto -191 -> 69
    //   263: goto -118 -> 145
    // Local variable table:
    //   start	length	slot	name	signature
    //   0	266	0	this	x
    //   5	252	1	i	int
    //   62	1	2	localObject	Object
    //   107	42	2	localException1	Exception
    //   157	2	2	localW1	w
    //   168	2	2	localException2	Exception
    //   223	2	2	localW2	w
    // Exception table:
    //   from	to	target	type
    //   153	158	107	java/lang/Exception
    //   139	142	168	java/lang/Exception
  }
}
