package o;

public final class y
{
  private static int ˊ;
  private static char ˋ = '\005';
  private static char[] ˎ;
  private static int ॱ = 0;
  
  static
  {
    ˊ = 1;
    ˎ = new char[] { 119, 101, 98, 86, 105, 116, 120, 47, 104, 109, 108, 59, 32, 99, 97, 114, 115, 61, 117, 102, 45, 56, 121, 122, 123 };
  }
  
  /* Error */
  public static final void ˋ(android.webkit.WebView paramWebView, String paramString)
  {
    // Byte code:
    //   0: goto +305 -> 305
    //   3: bipush 7
    //   5: bipush 7
    //   7: newarray char
    //   9: dup
    //   10: iconst_0
    //   11: ldc 51
    //   13: castore
    //   14: dup
    //   15: iconst_1
    //   16: ldc 52
    //   18: castore
    //   19: dup
    //   20: iconst_2
    //   21: ldc 53
    //   23: castore
    //   24: dup
    //   25: iconst_3
    //   26: ldc 54
    //   28: castore
    //   29: dup
    //   30: iconst_4
    //   31: ldc 55
    //   33: castore
    //   34: dup
    //   35: iconst_5
    //   36: ldc 52
    //   38: castore
    //   39: dup
    //   40: bipush 6
    //   42: ldc 56
    //   44: castore
    //   45: bipush 95
    //   47: invokestatic 60	o/y:ˏ	(I[CB)Ljava/lang/String;
    //   50: astore_3
    //   51: aload_3
    //   52: invokevirtual 66	java/lang/String:intern	()Ljava/lang/String;
    //   55: astore_3
    //   56: aload_0
    //   57: aload_3
    //   58: invokestatic 71	o/vq:ˎ	(Ljava/lang/Object;Ljava/lang/String;)V
    //   61: aload_0
    //   62: aload_1
    //   63: bipush 24
    //   65: bipush 24
    //   67: newarray char
    //   69: dup
    //   70: iconst_0
    //   71: ldc 72
    //   73: castore
    //   74: dup
    //   75: iconst_1
    //   76: ldc 55
    //   78: castore
    //   79: dup
    //   80: iconst_2
    //   81: ldc 73
    //   83: castore
    //   84: dup
    //   85: iconst_3
    //   86: ldc 72
    //   88: castore
    //   89: dup
    //   90: iconst_4
    //   91: ldc 74
    //   93: castore
    //   94: dup
    //   95: iconst_5
    //   96: ldc 75
    //   98: castore
    //   99: dup
    //   100: bipush 6
    //   102: ldc 72
    //   104: castore
    //   105: dup
    //   106: bipush 7
    //   108: ldc 76
    //   110: castore
    //   111: dup
    //   112: bipush 8
    //   114: ldc 77
    //   116: castore
    //   117: dup
    //   118: bipush 9
    //   120: ldc 78
    //   122: castore
    //   123: dup
    //   124: bipush 10
    //   126: ldc 79
    //   128: castore
    //   129: dup
    //   130: bipush 11
    //   132: ldc 80
    //   134: castore
    //   135: dup
    //   136: bipush 12
    //   138: ldc 75
    //   140: castore
    //   141: dup
    //   142: bipush 13
    //   144: ldc 79
    //   146: castore
    //   147: dup
    //   148: bipush 14
    //   150: ldc 81
    //   152: castore
    //   153: dup
    //   154: bipush 15
    //   156: ldc 82
    //   158: castore
    //   159: dup
    //   160: bipush 16
    //   162: ldc 55
    //   164: castore
    //   165: dup
    //   166: bipush 17
    //   168: ldc 72
    //   170: castore
    //   171: dup
    //   172: bipush 18
    //   174: ldc 83
    //   176: castore
    //   177: dup
    //   178: bipush 19
    //   180: ldc 84
    //   182: castore
    //   183: dup
    //   184: bipush 20
    //   186: ldc 75
    //   188: castore
    //   189: dup
    //   190: bipush 21
    //   192: ldc 85
    //   194: castore
    //   195: dup
    //   196: bipush 22
    //   198: ldc 86
    //   200: castore
    //   201: dup
    //   202: bipush 23
    //   204: ldc 87
    //   206: castore
    //   207: bipush 81
    //   209: invokestatic 60	o/y:ˏ	(I[CB)Ljava/lang/String;
    //   212: invokevirtual 66	java/lang/String:intern	()Ljava/lang/String;
    //   215: aconst_null
    //   216: invokevirtual 93	android/webkit/WebView:loadData	(Ljava/lang/String;Ljava/lang/String;Ljava/lang/String;)V
    //   219: goto +48 -> 267
    //   222: return
    //   223: goto -220 -> 3
    //   226: iload_2
    //   227: lookupswitch	default:+25->252, 5:+-5->222, 53:+67->294
    //   252: return
    //   253: astore_0
    //   254: aload_0
    //   255: athrow
    //   256: bipush 53
    //   258: istore_2
    //   259: goto -33 -> 226
    //   262: iconst_5
    //   263: istore_2
    //   264: goto -38 -> 226
    //   267: getstatic 15	o/y:ॱ	I
    //   270: bipush 111
    //   272: iadd
    //   273: istore_2
    //   274: iload_2
    //   275: sipush 128
    //   278: irem
    //   279: putstatic 17	o/y:ˊ	I
    //   282: iload_2
    //   283: iconst_2
    //   284: irem
    //   285: ifne +6 -> 291
    //   288: goto -32 -> 256
    //   291: goto -29 -> 262
    //   294: new 95	java/lang/NullPointerException
    //   297: dup
    //   298: invokespecial 98	java/lang/NullPointerException:<init>	()V
    //   301: athrow
    //   302: astore_0
    //   303: aload_0
    //   304: athrow
    //   305: getstatic 15	o/y:ॱ	I
    //   308: bipush 113
    //   310: iadd
    //   311: istore_2
    //   312: iload_2
    //   313: sipush 128
    //   316: irem
    //   317: putstatic 17	o/y:ˊ	I
    //   320: iload_2
    //   321: iconst_2
    //   322: irem
    //   323: ifne +6 -> 329
    //   326: goto -103 -> 223
    //   329: goto -326 -> 3
    // Local variable table:
    //   start	length	slot	name	signature
    //   0	332	0	paramWebView	android.webkit.WebView
    //   0	332	1	paramString	String
    //   226	97	2	i	int
    //   50	8	3	str	String
    // Exception table:
    //   from	to	target	type
    //   3	51	253	java/lang/Exception
    //   56	61	253	java/lang/Exception
    //   51	56	302	java/lang/Exception
  }
  
  /* Error */
  private static String ˏ(int paramInt, char[] paramArrayOfChar, byte paramByte)
  {
    // Byte code:
    //   0: goto +593 -> 593
    //   3: iconst_1
    //   4: istore 4
    //   6: goto +411 -> 417
    //   9: iload_3
    //   10: iconst_2
    //   11: iadd
    //   12: istore_3
    //   13: goto +288 -> 301
    //   16: astore_1
    //   17: aload_1
    //   18: athrow
    //   19: aload 11
    //   21: iload_3
    //   22: iload 6
    //   24: iload_2
    //   25: isub
    //   26: i2c
    //   27: castore
    //   28: aload 11
    //   30: iload_3
    //   31: iconst_1
    //   32: iadd
    //   33: iload 4
    //   35: iload_2
    //   36: isub
    //   37: i2c
    //   38: castore
    //   39: goto -30 -> 9
    //   42: bipush 92
    //   44: istore_3
    //   45: goto +576 -> 621
    //   48: new 62	java/lang/String
    //   51: dup
    //   52: aload 11
    //   54: invokespecial 101	java/lang/String:<init>	([C)V
    //   57: areturn
    //   58: getstatic 17	o/y:ˊ	I
    //   61: bipush 63
    //   63: iadd
    //   64: istore 4
    //   66: iload 4
    //   68: sipush 128
    //   71: irem
    //   72: putstatic 15	o/y:ॱ	I
    //   75: iload 4
    //   77: iconst_2
    //   78: irem
    //   79: ifeq +6 -> 85
    //   82: goto +466 -> 548
    //   85: goto +269 -> 354
    //   88: iload 8
    //   90: iload 5
    //   92: invokestatic 106	o/oO:ˊ	(II)I
    //   95: istore 4
    //   97: iload 9
    //   99: iload 5
    //   101: invokestatic 106	o/oO:ˊ	(II)I
    //   104: istore 8
    //   106: iload 7
    //   108: iload 4
    //   110: iload 5
    //   112: invokestatic 109	o/oO:ˏ	(III)I
    //   115: istore 4
    //   117: iload 6
    //   119: iload 8
    //   121: iload 5
    //   123: invokestatic 109	o/oO:ˏ	(III)I
    //   126: istore 6
    //   128: aload 11
    //   130: iload_3
    //   131: aload 10
    //   133: iload 4
    //   135: caload
    //   136: castore
    //   137: aload 11
    //   139: iload_3
    //   140: iconst_1
    //   141: iadd
    //   142: aload 10
    //   144: iload 6
    //   146: caload
    //   147: castore
    //   148: goto -139 -> 9
    //   151: iconst_0
    //   152: istore_3
    //   153: goto +148 -> 301
    //   156: iload 7
    //   158: iload 6
    //   160: if_icmpne +6 -> 166
    //   163: goto -75 -> 88
    //   166: goto +337 -> 503
    //   169: bipush 26
    //   171: istore_3
    //   172: goto +449 -> 621
    //   175: iload 6
    //   177: iload 5
    //   179: invokestatic 111	o/oO:ॱ	(II)I
    //   182: istore 7
    //   184: iload 6
    //   186: iload 5
    //   188: invokestatic 113	o/oO:ˋ	(II)I
    //   191: istore 8
    //   193: iload 4
    //   195: iload 5
    //   197: invokestatic 111	o/oO:ॱ	(II)I
    //   200: istore 6
    //   202: iload 4
    //   204: iload 5
    //   206: invokestatic 113	o/oO:ˋ	(II)I
    //   209: istore 9
    //   211: iload 8
    //   213: iload 9
    //   215: if_icmpne +6 -> 221
    //   218: goto +466 -> 684
    //   221: goto +347 -> 568
    //   224: goto -205 -> 19
    //   227: goto +124 -> 351
    //   230: goto +30 -> 260
    //   233: getstatic 15	o/y:ॱ	I
    //   236: bipush 53
    //   238: iadd
    //   239: istore_3
    //   240: iload_3
    //   241: sipush 128
    //   244: irem
    //   245: putstatic 17	o/y:ˊ	I
    //   248: iload_3
    //   249: iconst_2
    //   250: irem
    //   251: ifne +6 -> 257
    //   254: goto -85 -> 169
    //   257: goto -215 -> 42
    //   260: iload_0
    //   261: iconst_1
    //   262: if_icmple +6 -> 268
    //   265: goto -114 -> 151
    //   268: goto -220 -> 48
    //   271: getstatic 17	o/y:ˊ	I
    //   274: bipush 103
    //   276: iadd
    //   277: istore 4
    //   279: iload 4
    //   281: sipush 128
    //   284: irem
    //   285: putstatic 15	o/y:ॱ	I
    //   288: iload 4
    //   290: iconst_2
    //   291: irem
    //   292: ifeq +6 -> 298
    //   295: goto -68 -> 227
    //   298: goto +53 -> 351
    //   301: iload_3
    //   302: iload_0
    //   303: if_icmpge +6 -> 309
    //   306: goto -303 -> 3
    //   309: iconst_0
    //   310: istore 4
    //   312: goto +105 -> 417
    //   315: getstatic 15	o/y:ॱ	I
    //   318: bipush 51
    //   320: iadd
    //   321: istore 7
    //   323: iload 7
    //   325: sipush 128
    //   328: irem
    //   329: putstatic 17	o/y:ˊ	I
    //   332: iload 7
    //   334: iconst_2
    //   335: irem
    //   336: ifne +6 -> 342
    //   339: goto -115 -> 224
    //   342: goto -323 -> 19
    //   345: astore_1
    //   346: aload_1
    //   347: athrow
    //   348: goto -339 -> 9
    //   351: goto -342 -> 9
    //   354: iload 7
    //   356: iload 5
    //   358: invokestatic 106	o/oO:ˊ	(II)I
    //   361: istore 4
    //   363: iload 6
    //   365: iload 5
    //   367: invokestatic 106	o/oO:ˊ	(II)I
    //   370: istore 6
    //   372: iload 4
    //   374: iload 8
    //   376: iload 5
    //   378: invokestatic 109	o/oO:ˏ	(III)I
    //   381: istore 4
    //   383: iload 6
    //   385: iload 9
    //   387: iload 5
    //   389: invokestatic 109	o/oO:ˏ	(III)I
    //   392: istore 6
    //   394: aload 11
    //   396: iload_3
    //   397: aload 10
    //   399: iload 4
    //   401: caload
    //   402: castore
    //   403: aload 11
    //   405: iload_3
    //   406: iconst_1
    //   407: iadd
    //   408: aload 10
    //   410: iload 6
    //   412: caload
    //   413: castore
    //   414: goto -143 -> 271
    //   417: iload 4
    //   419: tableswitch	default:+21->440, 0:+-371->48, 1:+177->596
    //   440: goto -392 -> 48
    //   443: getstatic 44	o/y:ˎ	[C
    //   446: astore 10
    //   448: getstatic 46	o/y:ˋ	C
    //   451: istore 5
    //   453: iload_0
    //   454: newarray char
    //   456: astore 11
    //   458: iload_0
    //   459: iconst_2
    //   460: irem
    //   461: ifeq +6 -> 467
    //   464: goto -231 -> 233
    //   467: goto -207 -> 260
    //   470: iload 4
    //   472: lookupswitch	default:+28->500, 45:+-414->58, 75:+-316->156
    //   500: goto -442 -> 58
    //   503: iload 7
    //   505: iload 9
    //   507: iload 5
    //   509: invokestatic 109	o/oO:ˏ	(III)I
    //   512: istore 4
    //   514: iload 6
    //   516: iload 8
    //   518: iload 5
    //   520: invokestatic 109	o/oO:ˏ	(III)I
    //   523: istore 6
    //   525: aload 11
    //   527: iload_3
    //   528: aload 10
    //   530: iload 4
    //   532: caload
    //   533: castore
    //   534: aload 11
    //   536: iload_3
    //   537: iconst_1
    //   538: iadd
    //   539: aload 10
    //   541: iload 6
    //   543: caload
    //   544: castore
    //   545: goto +109 -> 654
    //   548: goto -194 -> 354
    //   551: iload_0
    //   552: iconst_1
    //   553: isub
    //   554: istore_0
    //   555: aload 11
    //   557: iload_0
    //   558: aload_1
    //   559: iload_0
    //   560: caload
    //   561: iload_2
    //   562: isub
    //   563: i2c
    //   564: castore
    //   565: goto -335 -> 230
    //   568: bipush 75
    //   570: istore 4
    //   572: goto -102 -> 470
    //   575: iload_0
    //   576: bipush 86
    //   578: iadd
    //   579: istore_0
    //   580: aload 11
    //   582: iload_0
    //   583: aload_1
    //   584: iload_0
    //   585: caload
    //   586: iload_2
    //   587: ishl
    //   588: i2c
    //   589: castore
    //   590: goto -360 -> 230
    //   593: goto -150 -> 443
    //   596: aload_1
    //   597: iload_3
    //   598: caload
    //   599: istore 6
    //   601: aload_1
    //   602: iload_3
    //   603: iconst_1
    //   604: iadd
    //   605: caload
    //   606: istore 4
    //   608: iload 6
    //   610: iload 4
    //   612: if_icmpne +6 -> 618
    //   615: goto -300 -> 315
    //   618: goto -443 -> 175
    //   621: iload_3
    //   622: lookupswitch	default:+26->648, 26:+-47->575, 92:+-71->551
    //   648: goto -97 -> 551
    //   651: goto -642 -> 9
    //   654: getstatic 17	o/y:ˊ	I
    //   657: bipush 11
    //   659: iadd
    //   660: istore 4
    //   662: iload 4
    //   664: sipush 128
    //   667: irem
    //   668: putstatic 15	o/y:ॱ	I
    //   671: iload 4
    //   673: iconst_2
    //   674: irem
    //   675: ifeq +6 -> 681
    //   678: goto -27 -> 651
    //   681: goto -333 -> 348
    //   684: bipush 45
    //   686: istore 4
    //   688: goto -218 -> 470
    // Local variable table:
    //   start	length	slot	name	signature
    //   0	691	0	paramInt	int
    //   0	691	1	paramArrayOfChar	char[]
    //   0	691	2	paramByte	byte
    //   9	613	3	i	int
    //   4	683	4	b1	byte
    //   90	429	5	j	int
    //   22	591	6	b2	byte
    //   106	398	7	b3	byte
    //   88	429	8	k	int
    //   97	409	9	m	int
    //   131	409	10	arrayOfChar1	char[]
    //   19	562	11	arrayOfChar2	char[]
    // Exception table:
    //   from	to	target	type
    //   315	323	16	java/lang/Exception
    //   323	332	16	java/lang/Exception
    //   443	448	16	java/lang/Exception
    //   448	458	345	java/lang/Exception
  }
}
