package o;

import java.io.IOException;

public final class yp
{
  private static int ʻ;
  private static int ʼ;
  private static int ʽ;
  static final String[] ˊ;
  private static long ˋ;
  static final yU ˎ;
  private static final String[] ˏ;
  static final String[] ॱ;
  private static char ᐝ;
  
  /* Error */
  static
  {
    // Byte code:
    //   0: goto +213 -> 213
    //   3: iload_0
    //   4: getstatic 24	o/yp:ˊ	[Ljava/lang/String;
    //   7: arraylength
    //   8: if_icmpge +6 -> 14
    //   11: goto +562 -> 573
    //   14: goto +545 -> 559
    //   17: iconst_0
    //   18: istore_0
    //   19: goto +551 -> 570
    //   22: getstatic 24	o/yp:ˊ	[Ljava/lang/String;
    //   25: iconst_4
    //   26: ldc 26
    //   28: aastore
    //   29: getstatic 24	o/yp:ˊ	[Ljava/lang/String;
    //   32: bipush 32
    //   34: ldc 28
    //   36: aastore
    //   37: getstatic 24	o/yp:ˊ	[Ljava/lang/String;
    //   40: bipush 36
    //   42: ldc 30
    //   44: aastore
    //   45: iconst_3
    //   46: newarray int
    //   48: astore 4
    //   50: aload 4
    //   52: dup
    //   53: iconst_0
    //   54: iconst_4
    //   55: iastore
    //   56: dup
    //   57: iconst_1
    //   58: bipush 32
    //   60: iastore
    //   61: dup
    //   62: iconst_2
    //   63: bipush 36
    //   65: iastore
    //   66: pop
    //   67: aload 4
    //   69: arraylength
    //   70: istore_0
    //   71: iconst_0
    //   72: istore_0
    //   73: goto +645 -> 718
    //   76: getstatic 32	o/yp:ॱ	[Ljava/lang/String;
    //   79: astore 4
    //   81: iconst_0
    //   82: anewarray 4	java/lang/Object
    //   85: astore 5
    //   87: iload_0
    //   88: invokestatic 38	java/lang/Integer:toBinaryString	(I)Ljava/lang/String;
    //   91: astore 6
    //   93: aload 5
    //   95: iconst_0
    //   96: aload 6
    //   98: aastore
    //   99: ldc 40
    //   101: aload 5
    //   103: invokestatic 45	o/xN:ˊ	(Ljava/lang/String;[Ljava/lang/Object;)Ljava/lang/String;
    //   106: astore 5
    //   108: aload 4
    //   110: iload_0
    //   111: aload 5
    //   113: bipush 57
    //   115: bipush 56
    //   117: invokevirtual 51	java/lang/String:replace	(CC)Ljava/lang/String;
    //   120: aastore
    //   121: iload_0
    //   122: bipush 100
    //   124: iadd
    //   125: istore_0
    //   126: goto +479 -> 605
    //   129: goto +589 -> 718
    //   132: iload_0
    //   133: iconst_1
    //   134: if_icmpge +6 -> 140
    //   137: goto +533 -> 670
    //   140: goto -118 -> 22
    //   143: getstatic 53	o/yp:ʽ	I
    //   146: bipush 53
    //   148: iadd
    //   149: istore_1
    //   150: iload_1
    //   151: sipush 128
    //   154: irem
    //   155: putstatic 55	o/yp:ʻ	I
    //   158: iload_1
    //   159: iconst_2
    //   160: irem
    //   161: ifne +6 -> 167
    //   164: goto -88 -> 76
    //   167: goto +334 -> 501
    //   170: getstatic 24	o/yp:ˊ	[Ljava/lang/String;
    //   173: iconst_0
    //   174: ldc 57
    //   176: aastore
    //   177: getstatic 24	o/yp:ˊ	[Ljava/lang/String;
    //   180: iconst_1
    //   181: ldc 59
    //   183: aastore
    //   184: iconst_1
    //   185: newarray int
    //   187: astore 5
    //   189: aload 5
    //   191: dup
    //   192: iconst_0
    //   193: iconst_1
    //   194: iastore
    //   195: pop
    //   196: getstatic 24	o/yp:ˊ	[Ljava/lang/String;
    //   199: bipush 8
    //   201: ldc 61
    //   203: aastore
    //   204: aload 5
    //   206: arraylength
    //   207: istore_0
    //   208: iconst_0
    //   209: istore_0
    //   210: goto +432 -> 642
    //   213: iconst_0
    //   214: putstatic 53	o/yp:ʽ	I
    //   217: iconst_1
    //   218: putstatic 55	o/yp:ʻ	I
    //   221: invokestatic 63	o/yp:ˋ	()V
    //   224: ldc 65
    //   226: invokestatic 70	o/yU:ˎ	(Ljava/lang/String;)Lo/yU;
    //   229: putstatic 72	o/yp:ˎ	Lo/yU;
    //   232: bipush 10
    //   234: anewarray 47	java/lang/String
    //   237: dup
    //   238: iconst_0
    //   239: ldc 74
    //   241: aastore
    //   242: dup
    //   243: iconst_1
    //   244: ldc 76
    //   246: aastore
    //   247: dup
    //   248: iconst_2
    //   249: ldc 28
    //   251: aastore
    //   252: dup
    //   253: iconst_3
    //   254: ldc 78
    //   256: aastore
    //   257: dup
    //   258: iconst_4
    //   259: ldc 80
    //   261: aastore
    //   262: dup
    //   263: iconst_5
    //   264: ldc 82
    //   266: aastore
    //   267: dup
    //   268: bipush 6
    //   270: iconst_4
    //   271: newarray char
    //   273: dup
    //   274: iconst_0
    //   275: ldc 83
    //   277: castore
    //   278: dup
    //   279: iconst_1
    //   280: ldc 84
    //   282: castore
    //   283: dup
    //   284: iconst_2
    //   285: ldc 85
    //   287: castore
    //   288: dup
    //   289: iconst_3
    //   290: ldc 86
    //   292: castore
    //   293: ldc 87
    //   295: iconst_4
    //   296: newarray char
    //   298: dup
    //   299: iconst_0
    //   300: ldc 88
    //   302: castore
    //   303: dup
    //   304: iconst_1
    //   305: ldc 89
    //   307: castore
    //   308: dup
    //   309: iconst_2
    //   310: ldc 90
    //   312: castore
    //   313: dup
    //   314: iconst_3
    //   315: ldc 91
    //   317: castore
    //   318: iconst_0
    //   319: iconst_4
    //   320: newarray char
    //   322: dup
    //   323: iconst_0
    //   324: ldc 92
    //   326: castore
    //   327: dup
    //   328: iconst_1
    //   329: ldc 92
    //   331: castore
    //   332: dup
    //   333: iconst_2
    //   334: ldc 92
    //   336: castore
    //   337: dup
    //   338: iconst_3
    //   339: ldc 92
    //   341: castore
    //   342: invokestatic 95	o/yp:ˎ	([CC[CI[C)Ljava/lang/String;
    //   345: invokevirtual 99	java/lang/String:intern	()Ljava/lang/String;
    //   348: aastore
    //   349: dup
    //   350: bipush 7
    //   352: ldc 101
    //   354: aastore
    //   355: dup
    //   356: bipush 8
    //   358: ldc 103
    //   360: aastore
    //   361: dup
    //   362: bipush 9
    //   364: ldc 105
    //   366: aastore
    //   367: putstatic 107	o/yp:ˏ	[Ljava/lang/String;
    //   370: bipush 64
    //   372: anewarray 47	java/lang/String
    //   375: putstatic 24	o/yp:ˊ	[Ljava/lang/String;
    //   378: sipush 256
    //   381: anewarray 47	java/lang/String
    //   384: putstatic 32	o/yp:ॱ	[Ljava/lang/String;
    //   387: iconst_0
    //   388: istore_0
    //   389: goto +216 -> 605
    //   392: iload_0
    //   393: iconst_1
    //   394: iadd
    //   395: istore_0
    //   396: goto +182 -> 578
    //   399: goto -270 -> 129
    //   402: aload 5
    //   404: iload_1
    //   405: iaload
    //   406: istore_3
    //   407: getstatic 24	o/yp:ˊ	[Ljava/lang/String;
    //   410: iload_3
    //   411: iload_2
    //   412: ior
    //   413: new 109	java/lang/StringBuilder
    //   416: dup
    //   417: invokespecial 112	java/lang/StringBuilder:<init>	()V
    //   420: getstatic 24	o/yp:ˊ	[Ljava/lang/String;
    //   423: iload_3
    //   424: aaload
    //   425: invokevirtual 116	java/lang/StringBuilder:append	(Ljava/lang/String;)Ljava/lang/StringBuilder;
    //   428: bipush 124
    //   430: invokevirtual 119	java/lang/StringBuilder:append	(C)Ljava/lang/StringBuilder;
    //   433: getstatic 24	o/yp:ˊ	[Ljava/lang/String;
    //   436: iload_2
    //   437: aaload
    //   438: invokevirtual 116	java/lang/StringBuilder:append	(Ljava/lang/String;)Ljava/lang/StringBuilder;
    //   441: invokevirtual 122	java/lang/StringBuilder:toString	()Ljava/lang/String;
    //   444: aastore
    //   445: getstatic 24	o/yp:ˊ	[Ljava/lang/String;
    //   448: iload_3
    //   449: iload_2
    //   450: ior
    //   451: bipush 8
    //   453: ior
    //   454: new 109	java/lang/StringBuilder
    //   457: dup
    //   458: invokespecial 112	java/lang/StringBuilder:<init>	()V
    //   461: getstatic 24	o/yp:ˊ	[Ljava/lang/String;
    //   464: iload_3
    //   465: aaload
    //   466: invokevirtual 116	java/lang/StringBuilder:append	(Ljava/lang/String;)Ljava/lang/StringBuilder;
    //   469: bipush 124
    //   471: invokevirtual 119	java/lang/StringBuilder:append	(C)Ljava/lang/StringBuilder;
    //   474: getstatic 24	o/yp:ˊ	[Ljava/lang/String;
    //   477: iload_2
    //   478: aaload
    //   479: invokevirtual 116	java/lang/StringBuilder:append	(Ljava/lang/String;)Ljava/lang/StringBuilder;
    //   482: ldc 124
    //   484: invokevirtual 116	java/lang/StringBuilder:append	(Ljava/lang/String;)Ljava/lang/StringBuilder;
    //   487: invokevirtual 122	java/lang/StringBuilder:toString	()Ljava/lang/String;
    //   490: aastore
    //   491: iload_1
    //   492: iconst_1
    //   493: iadd
    //   494: istore_1
    //   495: goto +41 -> 536
    //   498: goto +121 -> 619
    //   501: getstatic 32	o/yp:ॱ	[Ljava/lang/String;
    //   504: iload_0
    //   505: ldc 40
    //   507: iconst_1
    //   508: anewarray 4	java/lang/Object
    //   511: dup
    //   512: iconst_0
    //   513: iload_0
    //   514: invokestatic 38	java/lang/Integer:toBinaryString	(I)Ljava/lang/String;
    //   517: aastore
    //   518: invokestatic 45	o/xN:ˊ	(Ljava/lang/String;[Ljava/lang/Object;)Ljava/lang/String;
    //   521: bipush 32
    //   523: bipush 48
    //   525: invokevirtual 51	java/lang/String:replace	(CC)Ljava/lang/String;
    //   528: aastore
    //   529: iload_0
    //   530: iconst_1
    //   531: iadd
    //   532: istore_0
    //   533: goto +72 -> 605
    //   536: iload_1
    //   537: iconst_1
    //   538: if_icmpge +6 -> 544
    //   541: goto -139 -> 402
    //   544: goto -152 -> 392
    //   547: iload_0
    //   548: iconst_1
    //   549: iadd
    //   550: istore_0
    //   551: goto -548 -> 3
    //   554: astore 4
    //   556: aload 4
    //   558: athrow
    //   559: iconst_1
    //   560: istore_1
    //   561: goto +212 -> 773
    //   564: bipush 41
    //   566: istore_1
    //   567: goto +162 -> 729
    //   570: goto -567 -> 3
    //   573: iconst_0
    //   574: istore_1
    //   575: goto +198 -> 773
    //   578: getstatic 53	o/yp:ʽ	I
    //   581: bipush 113
    //   583: iadd
    //   584: istore_1
    //   585: iload_1
    //   586: sipush 128
    //   589: irem
    //   590: putstatic 55	o/yp:ʻ	I
    //   593: iload_1
    //   594: iconst_2
    //   595: irem
    //   596: ifne +6 -> 602
    //   599: goto -200 -> 399
    //   602: goto -473 -> 129
    //   605: iload_0
    //   606: getstatic 32	o/yp:ॱ	[Ljava/lang/String;
    //   609: arraylength
    //   610: if_icmpge +6 -> 616
    //   613: goto -470 -> 143
    //   616: goto -446 -> 170
    //   619: goto -487 -> 132
    //   622: bipush 58
    //   624: istore_1
    //   625: goto +104 -> 729
    //   628: getstatic 24	o/yp:ˊ	[Ljava/lang/String;
    //   631: iload_0
    //   632: aaload
    //   633: ifnonnull +6 -> 639
    //   636: goto +166 -> 802
    //   639: goto -92 -> 547
    //   642: getstatic 53	o/yp:ʽ	I
    //   645: bipush 79
    //   647: iadd
    //   648: istore_1
    //   649: iload_1
    //   650: sipush 128
    //   653: irem
    //   654: putstatic 55	o/yp:ʻ	I
    //   657: iload_1
    //   658: iconst_2
    //   659: irem
    //   660: ifne +6 -> 666
    //   663: goto -165 -> 498
    //   666: goto -47 -> 619
    //   669: return
    //   670: aload 5
    //   672: iload_0
    //   673: iaload
    //   674: istore_1
    //   675: getstatic 24	o/yp:ˊ	[Ljava/lang/String;
    //   678: iload_1
    //   679: bipush 8
    //   681: ior
    //   682: new 109	java/lang/StringBuilder
    //   685: dup
    //   686: invokespecial 112	java/lang/StringBuilder:<init>	()V
    //   689: getstatic 24	o/yp:ˊ	[Ljava/lang/String;
    //   692: iload_1
    //   693: aaload
    //   694: invokevirtual 116	java/lang/StringBuilder:append	(Ljava/lang/String;)Ljava/lang/StringBuilder;
    //   697: ldc 124
    //   699: invokevirtual 116	java/lang/StringBuilder:append	(Ljava/lang/String;)Ljava/lang/StringBuilder;
    //   702: invokevirtual 122	java/lang/StringBuilder:toString	()Ljava/lang/String;
    //   705: aastore
    //   706: iload_0
    //   707: iconst_1
    //   708: iadd
    //   709: istore_0
    //   710: goto -578 -> 132
    //   713: astore 4
    //   715: aload 4
    //   717: athrow
    //   718: iload_0
    //   719: iconst_3
    //   720: if_icmpge +6 -> 726
    //   723: goto -159 -> 564
    //   726: goto -104 -> 622
    //   729: iload_1
    //   730: lookupswitch	default:+26->756, 41:+29->759, 58:+-713->17
    //   756: goto -739 -> 17
    //   759: aload 4
    //   761: iload_0
    //   762: iaload
    //   763: istore_2
    //   764: aload 5
    //   766: arraylength
    //   767: istore_1
    //   768: iconst_0
    //   769: istore_1
    //   770: goto +29 -> 799
    //   773: iload_1
    //   774: tableswitch	default:+22->796, 0:+-146->628, 1:+-105->669
    //   796: goto -168 -> 628
    //   799: goto -263 -> 536
    //   802: getstatic 24	o/yp:ˊ	[Ljava/lang/String;
    //   805: iload_0
    //   806: getstatic 32	o/yp:ॱ	[Ljava/lang/String;
    //   809: iload_0
    //   810: aaload
    //   811: aastore
    //   812: goto -265 -> 547
    // Local variable table:
    //   start	length	slot	name	signature
    //   3	807	0	i	int
    //   149	625	1	j	int
    //   411	353	2	k	int
    //   406	59	3	m	int
    //   48	61	4	localObject1	Object
    //   554	3	4	localException1	Exception
    //   713	47	4	localException2	Exception
    //   85	680	5	localObject2	Object
    //   91	6	6	str	String
    // Exception table:
    //   from	to	target	type
    //   76	81	554	java/lang/Exception
    //   81	87	713	java/lang/Exception
    //   87	93	713	java/lang/Exception
    //   99	108	713	java/lang/Exception
    //   108	121	713	java/lang/Exception
  }
  
  private yp() {}
  
  static IOException ˊ(String paramString, Object... paramVarArgs)
  {
    throw new IOException(xN.ˊ(paramString, paramVarArgs));
  }
  
  static void ˋ()
  {
    ᐝ = '▬';
    ˋ = 0L;
    ʼ = 0;
  }
  
  static IllegalArgumentException ˎ(String paramString, Object... paramVarArgs)
  {
    for (;;)
    {
      throw new IllegalArgumentException(xN.ˊ(paramString, paramVarArgs));
    }
  }
  
  /* Error */
  static String ˎ(byte paramByte1, byte paramByte2)
  {
    // Byte code:
    //   0: goto +431 -> 431
    //   3: bipush 43
    //   5: istore_2
    //   6: goto +168 -> 174
    //   9: getstatic 32	o/yp:ॱ	[Ljava/lang/String;
    //   12: iload_1
    //   13: aaload
    //   14: astore_3
    //   15: goto +23 -> 38
    //   18: goto +226 -> 244
    //   21: getstatic 32	o/yp:ॱ	[Ljava/lang/String;
    //   24: iload_1
    //   25: aaload
    //   26: areturn
    //   27: astore_3
    //   28: aload_3
    //   29: athrow
    //   30: goto +8 -> 38
    //   33: iconst_1
    //   34: istore_2
    //   35: goto +59 -> 94
    //   38: iload_0
    //   39: iconst_5
    //   40: if_icmpne +6 -> 46
    //   43: goto +12 -> 55
    //   46: goto +119 -> 165
    //   49: bipush 62
    //   51: istore_2
    //   52: goto +300 -> 352
    //   55: getstatic 53	o/yp:ʽ	I
    //   58: bipush 57
    //   60: iadd
    //   61: istore_2
    //   62: iload_2
    //   63: sipush 128
    //   66: irem
    //   67: putstatic 55	o/yp:ʻ	I
    //   70: iload_2
    //   71: iconst_2
    //   72: irem
    //   73: ifne +6 -> 79
    //   76: goto +43 -> 119
    //   79: goto +174 -> 253
    //   82: bipush 19
    //   84: istore_2
    //   85: goto +267 -> 352
    //   88: bipush 71
    //   90: istore_2
    //   91: goto +83 -> 174
    //   94: iload_2
    //   95: tableswitch	default:+21->116, 0:+70->165, 1:+122->217
    //   116: goto +49 -> 165
    //   119: iload_1
    //   120: iconst_4
    //   121: iand
    //   122: ifeq +6 -> 128
    //   125: goto -37 -> 88
    //   128: goto -125 -> 3
    //   131: getstatic 53	o/yp:ʽ	I
    //   134: istore_2
    //   135: iload_2
    //   136: bipush 35
    //   138: iadd
    //   139: istore_2
    //   140: iload_2
    //   141: sipush 128
    //   144: irem
    //   145: putstatic 55	o/yp:ʻ	I
    //   148: iload_2
    //   149: iconst_2
    //   150: irem
    //   151: ifne +6 -> 157
    //   154: goto -72 -> 82
    //   157: goto -108 -> 49
    //   160: iconst_0
    //   161: istore_2
    //   162: goto -68 -> 94
    //   165: iload_0
    //   166: ifne +6 -> 172
    //   169: goto +129 -> 298
    //   172: aload_3
    //   173: areturn
    //   174: iload_2
    //   175: lookupswitch	default:+25->200, 43:+-10->165, 71:+42->217
    //   200: goto +17 -> 217
    //   203: iload_1
    //   204: getstatic 24	o/yp:ˊ	[Ljava/lang/String;
    //   207: arraylength
    //   208: if_icmpge +6 -> 214
    //   211: goto +117 -> 328
    //   214: goto -205 -> 9
    //   217: getstatic 53	o/yp:ʽ	I
    //   220: bipush 113
    //   222: iadd
    //   223: istore_0
    //   224: iload_0
    //   225: sipush 128
    //   228: irem
    //   229: putstatic 55	o/yp:ʻ	I
    //   232: iload_0
    //   233: iconst_2
    //   234: irem
    //   235: ifne +6 -> 241
    //   238: goto +43 -> 281
    //   241: goto +78 -> 319
    //   244: ldc -111
    //   246: areturn
    //   247: ldc 57
    //   249: areturn
    //   250: goto -232 -> 18
    //   253: iload_1
    //   254: iconst_4
    //   255: iand
    //   256: ifeq +6 -> 262
    //   259: goto -226 -> 33
    //   262: goto -102 -> 160
    //   265: iload_1
    //   266: ifne +6 -> 272
    //   269: goto -22 -> 247
    //   272: goto +111 -> 383
    //   275: getstatic 32	o/yp:ॱ	[Ljava/lang/String;
    //   278: iload_1
    //   279: aaload
    //   280: areturn
    //   281: aload_3
    //   282: ldc 76
    //   284: ldc 82
    //   286: invokevirtual 148	java/lang/String:replace	(Ljava/lang/CharSequence;Ljava/lang/CharSequence;)Ljava/lang/String;
    //   289: pop
    //   290: new 150	java/lang/NullPointerException
    //   293: dup
    //   294: invokespecial 151	java/lang/NullPointerException:<init>	()V
    //   297: athrow
    //   298: iload_1
    //   299: bipush 32
    //   301: iand
    //   302: ifeq +6 -> 308
    //   305: goto +5 -> 310
    //   308: aload_3
    //   309: areturn
    //   310: aload_3
    //   311: ldc 28
    //   313: ldc -103
    //   315: invokevirtual 148	java/lang/String:replace	(Ljava/lang/CharSequence;Ljava/lang/CharSequence;)Ljava/lang/String;
    //   318: areturn
    //   319: aload_3
    //   320: ldc 76
    //   322: ldc 82
    //   324: invokevirtual 148	java/lang/String:replace	(Ljava/lang/CharSequence;Ljava/lang/CharSequence;)Ljava/lang/String;
    //   327: areturn
    //   328: getstatic 24	o/yp:ˊ	[Ljava/lang/String;
    //   331: iload_1
    //   332: aaload
    //   333: astore_3
    //   334: goto -304 -> 30
    //   337: bipush 10
    //   339: iconst_0
    //   340: idiv
    //   341: istore_2
    //   342: iload_1
    //   343: ifne +6 -> 349
    //   346: goto -99 -> 247
    //   349: goto +34 -> 383
    //   352: iload_2
    //   353: lookupswitch	default:+27->380, 19:+-16->337, 62:+-88->265
    //   380: goto -43 -> 337
    //   383: iload_0
    //   384: tableswitch	default:+44->428, 2:+-363->21, 3:+-363->21, 4:+53->437, 5:+-181->203, 6:+53->437, 7:+-363->21, 8:+-363->21
    //   428: goto -225 -> 203
    //   431: goto -300 -> 131
    //   434: astore_3
    //   435: aload_3
    //   436: athrow
    //   437: iload_1
    //   438: iconst_1
    //   439: if_icmpne +6 -> 445
    //   442: goto -192 -> 250
    //   445: goto -170 -> 275
    // Local variable table:
    //   start	length	slot	name	signature
    //   0	448	0	paramByte1	byte
    //   0	448	1	paramByte2	byte
    //   5	348	2	i	int
    //   14	1	3	str1	String
    //   27	293	3	localException1	Exception
    //   333	1	3	str2	String
    //   434	2	3	localException2	Exception
    // Exception table:
    //   from	to	target	type
    //   131	135	27	java/lang/Exception
    //   140	148	434	java/lang/Exception
  }
  
  static String ˎ(boolean paramBoolean, int paramInt1, int paramInt2, byte paramByte1, byte paramByte2)
  {
    for (;;)
    {
      switch (b)
      {
      default: 
        break;
        b = 0;
        break;
      }
      for (;;)
      {
        label95:
        label109:
        String str1;
        switch (b)
        {
        case 49: 
        default: 
          break;
          try
          {
            localObject = ˏ;
            localObject = localObject[paramByte1];
            b = 65 / 0;
          }
          catch (Exception localException2)
          {
            Object localObject;
            throw localException2;
          }
          try
          {
            localObject = ˏ;
            localObject = localObject[paramByte1];
          }
          catch (Exception localException1)
          {
            throw localException1;
          }
          b = 49;
          continue;
          str1 = "<<";
          break;
        case 15: 
          String str2;
          for (;;)
          {
            return xN.ˊ("%s 0x%08x %5d %-13s %s", new Object[] { str1, Integer.valueOf(paramInt1), Integer.valueOf(paramInt2), localObject, str2 });
            for (;;)
            {
              localObject = xN.ˊ("0x%02x", new Object[] { Byte.valueOf(paramByte1) });
              break label233;
              b = ʻ + 71;
              ʽ = b % 128;
              if (b % 2 != 0) {
                break label109;
              }
              break label377;
              label223:
              b = 68;
              break;
              label230:
              break label239;
              label233:
              break label329;
              break label299;
              label239:
              b = ˏ.length;
              if (paramByte1 < b) {
                break label347;
              }
            }
            continue;
            str1 = ">>";
          }
          for (;;)
          {
            b = 1;
            switch (b)
            {
            }
            break label95;
            label299:
            b = ʽ + 57;
            ʻ = b % 128;
            if (b % 2 == 0) {
              break label230;
            }
            break label239;
            label329:
            str2 = ˎ(paramByte1, paramByte2);
            if (paramBoolean) {
              break label384;
            }
            break label223;
            label347:
            b = ʻ + 87;
            ʽ = b % 128;
            if (b % 2 != 0) {
              break;
            }
          }
          label377:
          b = 15;
        }
      }
      label384:
      byte b = 41;
    }
  }
  
  private static String ˎ(char[] paramArrayOfChar1, char paramChar, char[] paramArrayOfChar2, int paramInt, char[] paramArrayOfChar3)
  {
    break label283;
    char[] arrayOfChar;
    char c;
    for (;;)
    {
      return new String(arrayOfChar);
      paramInt = 77;
      break label49;
      c = ʽ + 23;
      ʻ = c % '';
      if (c % '\002' == 0) {
        break;
      }
      break;
      label49:
      switch (paramInt)
      {
      }
    }
    paramChar = paramInt;
    for (;;)
    {
      switch (paramChar)
      {
      case '\\': 
      default: 
        break;
        paramArrayOfChar1 = (char[])paramArrayOfChar1.clone();
        paramArrayOfChar3 = (char[])paramArrayOfChar3.clone();
        paramArrayOfChar1[0] = ((char)(paramArrayOfChar1[0] ^ paramChar));
        paramArrayOfChar3[2] = ((char)(paramArrayOfChar3[2] + (char)paramInt));
        c = paramArrayOfChar2.length;
        arrayOfChar = new char[c];
        paramInt = 0;
        break;
      }
      paramChar = paramInt;
      break label295;
      paramChar = '$';
      continue;
      paramInt = ʽ + 115;
      ʻ = paramInt % 128;
      if (paramInt % 2 != 0)
      {
        label204:
        oJ.ˏ(paramArrayOfChar1, paramArrayOfChar3, paramChar);
        arrayOfChar[paramChar] = ((char)(int)(paramArrayOfChar2[paramChar] ^ paramArrayOfChar1[((paramChar + '\003') % 4)] ^ ˋ ^ ʼ ^ ᐝ));
        paramChar += '\001';
      }
      label283:
      label295:
      while (paramChar < c)
      {
        paramInt = 18;
        break label49;
        try
        {
          paramChar = ʽ + 109;
        }
        catch (Exception paramArrayOfChar1)
        {
          throw paramArrayOfChar1;
        }
        try
        {
          ʻ = paramChar % '';
          if (paramChar % '\002' == 0) {
            break label307;
          }
        }
        catch (Exception paramArrayOfChar1)
        {
          throw paramArrayOfChar1;
        }
        break;
        break label204;
      }
      break;
      label307:
      paramChar = '\\';
    }
  }
}
