package o;

import android.view.ViewGroup;
import java.util.ArrayList;

public abstract class ɨ
  extends с
{
  private static int ʻ = 1606163149;
  private static short[] ʼ;
  private static int ʽ;
  private static int ˊॱ;
  private static int ˋॱ = 0;
  private static int ॱॱ;
  private static byte[] ᐝ;
  private ﻨ ˊ = null;
  private ArrayList<ᴷ.ˋ> ˋ = new ArrayList();
  private final ﺒ ˎ;
  private ArrayList<ᴷ> ˏ = new ArrayList();
  private ᴷ ॱ = null;
  
  static
  {
    ˊॱ = 1;
    ॱॱ = 9;
    ᐝ = new byte[] { -126, 49, -33, 110, -119, 54, 100, -119, 35, 44, -35, 35, 35, -54, 41, 99, -103, 38, 58, 0 };
    ʽ = -590492381;
  }
  
  public ɨ(ﺒ paramﺒ)
  {
    this.ˎ = paramﺒ;
  }
  
  private static String ˊ(int paramInt1, short paramShort, int paramInt2, byte paramByte, int paramInt3)
  {
    break label144;
    int j = 0;
    break label252;
    label9:
    StringBuilder localStringBuilder;
    int i;
    localStringBuilder.append(i);
    paramInt2 += 1;
    break label222;
    return localStringBuilder.toString();
    int k;
    for (;;)
    {
      switch (k)
      {
      case 12: 
      default: 
        break label387;
        label63:
        if (paramInt3 <= 0)
        {
          break label460;
          label74:
          if (ᐝ != null) {
            break label187;
          }
          break label279;
        }
        k = 92;
      }
    }
    label93:
    paramInt2 = paramInt2 + paramInt3 - 2 + k + j;
    label144:
    label187:
    label222:
    label252:
    label279:
    label387:
    label460:
    label524:
    for (;;)
    {
      try
      {
        j = ʽ;
        i = (char)(j + paramInt1);
        try
        {
          localStringBuilder.append(i);
          j = 1;
          paramInt1 = paramInt2;
          k = i;
          paramInt2 = j;
        }
        catch (Exception localException1)
        {
          throw localException1;
        }
        continue;
        continue;
        k = i;
        continue;
        localStringBuilder = new StringBuilder();
        j = ॱॱ + paramInt3;
        paramInt3 = j;
        if (j != -1)
        {
          continue;
          paramInt3 = (byte)(ᐝ[(ʻ + paramInt2)] + ॱॱ);
          break label63;
          k = ʻ;
          if (j != 0) {
            continue;
          }
          continue;
          j = ˊॱ + 23;
          ˋॱ = j % 128;
          if (j % 2 != 0) {
            continue;
          }
          continue;
        }
        Object localObject;
        switch (j)
        {
        default: 
          continue;
          localObject = ʼ;
          paramInt3 = ʻ;
          paramInt3 = localObject[(paramInt3 + paramInt2)];
          k = ॱॱ;
          paramInt3 = (short)(paramInt3 + k);
          break;
        case 0: 
          localObject = ʼ;
          j = paramInt1 - 1;
          i = (char)(((short)(localObject[paramInt1] + paramShort) ^ paramByte) + k);
          paramInt1 = j;
          break label9;
          if (ᐝ == null)
          {
            break;
            paramInt3 = ˊॱ + 57;
            ˋॱ = paramInt3 % 128;
            if (paramInt3 % 2 == 0)
            {
              break label74;
              k = ˊॱ + 111;
              ˋॱ = k % 128;
              if (k % 2 != 0) {
                continue;
              }
              continue;
              if (j == 0)
              {
                break label63;
                j = 1;
                break label524;
                j = 0;
                continue;
              }
              continue;
              continue;
              j = 1;
              break label93;
              j = 0;
              break label93;
              k = 12;
            }
          }
          break;
        case 1: 
          localObject = ᐝ;
          j = paramInt1 - 1;
          i = (char)(((byte)(localObject[paramInt1] + paramShort) ^ paramByte) + k);
          paramInt1 = j;
          break label9;
          break label74;
          j = 1;
          break;
        }
        if (paramInt2 < paramInt3) {}
      }
      catch (Exception localException2)
      {
        throw localException2;
      }
    }
  }
  
  public abstract ᴷ ˊ(int paramInt);
  
  public void ˊ(ViewGroup paramViewGroup)
  {
    break label19;
    int i = 1;
    if (this.ˊ == null)
    {
      return;
      label19:
      break label95;
      label22:
      paramViewGroup = this.ˊ;
      throw new NullPointerException();
      switch (i)
      {
      default: 
        break;
      }
    }
    for (;;)
    {
      switch (i)
      {
      }
      break label22;
      label95:
      i = ˋॱ + 79;
      ˊॱ = i % 128;
      if (i % 2 != 0)
      {
        break label171;
        return;
        label144:
        do
        {
          i = 0;
          break;
          this.ˊ.ˋ();
          this.ˊ = null;
          break label144;
          return;
          i = ˊॱ + 59;
          ˋॱ = i % 128;
        } while (i % 2 != 0);
        break;
        label171:
        i = 85;
        continue;
      }
      i = 89;
    }
  }
  
  /* Error */
  public boolean ˊ(android.view.View paramView, Object paramObject)
  {
    // Byte code:
    //   0: goto +36 -> 36
    //   3: getstatic 31	o/ɨ:ˊॱ	I
    //   6: bipush 59
    //   8: iadd
    //   9: istore_3
    //   10: iload_3
    //   11: sipush 128
    //   14: irem
    //   15: putstatic 29	o/ɨ:ˋॱ	I
    //   18: iload_3
    //   19: iconst_2
    //   20: irem
    //   21: ifeq +6 -> 27
    //   24: goto +9 -> 33
    //   27: goto +77 -> 104
    //   30: astore_1
    //   31: aload_1
    //   32: athrow
    //   33: goto +71 -> 104
    //   36: goto +106 -> 142
    //   39: bipush 86
    //   41: istore_3
    //   42: goto +68 -> 110
    //   45: aload_2
    //   46: checkcast 104	o/ᴷ
    //   49: invokevirtual 108	o/ᴷ:getView	()Landroid/view/View;
    //   52: aload_1
    //   53: if_acmpne +6 -> 59
    //   56: goto +9 -> 65
    //   59: goto -20 -> 39
    //   62: goto -17 -> 45
    //   65: bipush 97
    //   67: istore_3
    //   68: goto +42 -> 110
    //   71: getstatic 29	o/ɨ:ˋॱ	I
    //   74: bipush 115
    //   76: iadd
    //   77: istore_3
    //   78: iload_3
    //   79: sipush 128
    //   82: irem
    //   83: putstatic 31	o/ɨ:ˊॱ	I
    //   86: iload_3
    //   87: iconst_2
    //   88: irem
    //   89: ifne +6 -> 95
    //   92: iload 4
    //   94: ireturn
    //   95: iload 4
    //   97: ireturn
    //   98: iconst_0
    //   99: istore 4
    //   101: goto +68 -> 169
    //   104: iconst_1
    //   105: istore 4
    //   107: goto +62 -> 169
    //   110: iload_3
    //   111: lookupswitch	default:+25->136, 86:+-13->98, 97:+-108->3
    //   136: goto -38 -> 98
    //   139: astore_1
    //   140: aload_1
    //   141: athrow
    //   142: getstatic 31	o/ɨ:ˊॱ	I
    //   145: bipush 59
    //   147: iadd
    //   148: istore_3
    //   149: iload_3
    //   150: sipush 128
    //   153: irem
    //   154: putstatic 29	o/ɨ:ˋॱ	I
    //   157: iload_3
    //   158: iconst_2
    //   159: irem
    //   160: ifeq +6 -> 166
    //   163: goto -101 -> 62
    //   166: goto -121 -> 45
    //   169: goto -98 -> 71
    // Local variable table:
    //   start	length	slot	name	signature
    //   0	172	0	this	ɨ
    //   0	172	1	paramView	android.view.View
    //   0	172	2	paramObject	Object
    //   9	151	3	i	int
    //   92	14	4	bool	boolean
    // Exception table:
    //   from	to	target	type
    //   71	78	30	java/lang/Exception
    //   78	86	30	java/lang/Exception
    //   142	149	139	java/lang/Exception
    //   149	157	139	java/lang/Exception
  }
  
  /* Error */
  public Object ˋ(ViewGroup paramViewGroup, int paramInt)
  {
    // Byte code:
    //   0: goto +523 -> 523
    //   3: aload_0
    //   4: getfield 65	o/ɨ:ˊ	Lo/ﻨ;
    //   7: ifnonnull +6 -> 13
    //   10: goto +233 -> 243
    //   13: goto +211 -> 224
    //   16: aload_0
    //   17: getfield 72	o/ɨ:ˏ	Ljava/util/ArrayList;
    //   20: iload_2
    //   21: invokevirtual 113	java/util/ArrayList:get	(I)Ljava/lang/Object;
    //   24: checkcast 104	o/ᴷ
    //   27: astore 4
    //   29: aload 4
    //   31: ifnull +6 -> 37
    //   34: goto +234 -> 268
    //   37: goto +226 -> 263
    //   40: getstatic 31	o/ɨ:ˊॱ	I
    //   43: bipush 125
    //   45: iadd
    //   46: istore_3
    //   47: iload_3
    //   48: sipush 128
    //   51: irem
    //   52: putstatic 29	o/ɨ:ˋॱ	I
    //   55: iload_3
    //   56: iconst_2
    //   57: irem
    //   58: ifeq +6 -> 64
    //   61: goto +246 -> 307
    //   64: goto +210 -> 274
    //   67: goto +106 -> 173
    //   70: aload_0
    //   71: getfield 72	o/ɨ:ˏ	Ljava/util/ArrayList;
    //   74: aconst_null
    //   75: invokevirtual 117	java/util/ArrayList:add	(Ljava/lang/Object;)Z
    //   78: pop
    //   79: goto +47 -> 126
    //   82: iload_3
    //   83: tableswitch	default:+21->104, 0:+90->173, 1:+-43->40
    //   104: goto +69 -> 173
    //   107: aload_0
    //   108: aload_0
    //   109: getfield 76	o/ɨ:ˎ	Lo/ﺒ;
    //   112: invokevirtual 122	o/ﺒ:ˏ	()Lo/ﻨ;
    //   115: putfield 65	o/ɨ:ˊ	Lo/ﻨ;
    //   118: bipush 79
    //   120: iconst_0
    //   121: idiv
    //   122: istore_3
    //   123: goto -56 -> 67
    //   126: aload_0
    //   127: getfield 72	o/ɨ:ˏ	Ljava/util/ArrayList;
    //   130: invokevirtual 126	java/util/ArrayList:size	()I
    //   133: iload_2
    //   134: if_icmpgt +6 -> 140
    //   137: goto +218 -> 355
    //   140: goto +209 -> 349
    //   143: astore_1
    //   144: aload_1
    //   145: athrow
    //   146: getstatic 29	o/ɨ:ˋॱ	I
    //   149: bipush 9
    //   151: iadd
    //   152: istore_3
    //   153: iload_3
    //   154: sipush 128
    //   157: irem
    //   158: putstatic 31	o/ɨ:ˊॱ	I
    //   161: iload_3
    //   162: iconst_2
    //   163: irem
    //   164: ifne +6 -> 170
    //   167: goto +30 -> 197
    //   170: goto +293 -> 463
    //   173: aload_0
    //   174: iload_2
    //   175: invokevirtual 128	o/ɨ:ˊ	(I)Lo/ᴷ;
    //   178: astore 5
    //   180: aload_0
    //   181: getfield 70	o/ɨ:ˋ	Ljava/util/ArrayList;
    //   184: invokevirtual 126	java/util/ArrayList:size	()I
    //   187: iload_2
    //   188: if_icmple +6 -> 194
    //   191: goto -45 -> 146
    //   194: goto -68 -> 126
    //   197: aload_0
    //   198: getfield 70	o/ɨ:ˋ	Ljava/util/ArrayList;
    //   201: iload_2
    //   202: invokevirtual 113	java/util/ArrayList:get	(I)Ljava/lang/Object;
    //   205: checkcast 130	o/ᴷ$ˋ
    //   208: astore 4
    //   210: aconst_null
    //   211: arraylength
    //   212: istore_3
    //   213: aload 4
    //   215: ifnull +6 -> 221
    //   218: goto +143 -> 361
    //   221: goto -95 -> 126
    //   224: iconst_0
    //   225: istore_3
    //   226: goto -144 -> 82
    //   229: aload_0
    //   230: aload_0
    //   231: getfield 76	o/ɨ:ˎ	Lo/ﺒ;
    //   234: invokevirtual 122	o/ﺒ:ˏ	()Lo/ﻨ;
    //   237: putfield 65	o/ɨ:ˊ	Lo/ﻨ;
    //   240: goto -173 -> 67
    //   243: iconst_1
    //   244: istore_3
    //   245: goto -163 -> 82
    //   248: aload 5
    //   250: aload 4
    //   252: invokevirtual 133	o/ᴷ:ˎ	(Lo/ᴷ$ˋ;)V
    //   255: bipush 94
    //   257: iconst_0
    //   258: idiv
    //   259: istore_3
    //   260: goto +230 -> 490
    //   263: iconst_2
    //   264: istore_3
    //   265: goto +228 -> 493
    //   268: bipush 41
    //   270: istore_3
    //   271: goto +222 -> 493
    //   274: iconst_0
    //   275: istore_3
    //   276: goto +6 -> 282
    //   279: astore_1
    //   280: aload_1
    //   281: athrow
    //   282: iload_3
    //   283: tableswitch	default:+21->304, 0:+-54->229, 1:+-176->107
    //   304: goto -75 -> 229
    //   307: iconst_1
    //   308: istore_3
    //   309: goto -27 -> 282
    //   312: getstatic 31	o/ɨ:ˊॱ	I
    //   315: bipush 93
    //   317: iadd
    //   318: istore_2
    //   319: iload_2
    //   320: sipush 128
    //   323: irem
    //   324: putstatic 29	o/ɨ:ˋॱ	I
    //   327: iload_2
    //   328: iconst_2
    //   329: irem
    //   330: ifeq +6 -> 336
    //   333: goto +193 -> 526
    //   336: goto +151 -> 487
    //   339: aload 5
    //   341: aload 4
    //   343: invokevirtual 133	o/ᴷ:ˎ	(Lo/ᴷ$ˋ;)V
    //   346: goto +144 -> 490
    //   349: bipush 60
    //   351: istore_3
    //   352: goto +36 -> 388
    //   355: bipush 48
    //   357: istore_3
    //   358: goto +30 -> 388
    //   361: getstatic 29	o/ɨ:ˋॱ	I
    //   364: bipush 67
    //   366: iadd
    //   367: istore_3
    //   368: iload_3
    //   369: sipush 128
    //   372: irem
    //   373: putstatic 31	o/ɨ:ˊॱ	I
    //   376: iload_3
    //   377: iconst_2
    //   378: irem
    //   379: ifne +6 -> 385
    //   382: goto -134 -> 248
    //   385: goto -46 -> 339
    //   388: iload_3
    //   389: lookupswitch	default:+27->416, 48:+-319->70, 60:+30->419
    //   416: goto -346 -> 70
    //   419: aload 5
    //   421: iconst_0
    //   422: invokevirtual 136	o/ᴷ:ˏ	(Z)V
    //   425: aload 5
    //   427: iconst_0
    //   428: invokevirtual 138	o/ᴷ:ˎ	(Z)V
    //   431: aload_0
    //   432: getfield 72	o/ɨ:ˏ	Ljava/util/ArrayList;
    //   435: astore 4
    //   437: aload 4
    //   439: iload_2
    //   440: aload 5
    //   442: invokevirtual 142	java/util/ArrayList:set	(ILjava/lang/Object;)Ljava/lang/Object;
    //   445: pop
    //   446: aload_0
    //   447: getfield 65	o/ɨ:ˊ	Lo/ﻨ;
    //   450: aload_1
    //   451: invokevirtual 147	android/view/ViewGroup:getId	()I
    //   454: aload 5
    //   456: invokevirtual 150	o/ﻨ:ˎ	(ILo/ᴷ;)Lo/ﻨ;
    //   459: pop
    //   460: aload 5
    //   462: areturn
    //   463: aload_0
    //   464: getfield 70	o/ɨ:ˋ	Ljava/util/ArrayList;
    //   467: iload_2
    //   468: invokevirtual 113	java/util/ArrayList:get	(I)Ljava/lang/Object;
    //   471: checkcast 130	o/ᴷ$ˋ
    //   474: astore 4
    //   476: aload 4
    //   478: ifnull +6 -> 484
    //   481: goto -120 -> 361
    //   484: goto -358 -> 126
    //   487: aload 4
    //   489: areturn
    //   490: goto -364 -> 126
    //   493: iload_3
    //   494: lookupswitch	default:+26->520, 2:+-491->3, 41:+-182->312
    //   520: goto -208 -> 312
    //   523: goto +11 -> 534
    //   526: bipush 77
    //   528: iconst_0
    //   529: idiv
    //   530: istore_2
    //   531: aload 4
    //   533: areturn
    //   534: aload_0
    //   535: getfield 72	o/ɨ:ˏ	Ljava/util/ArrayList;
    //   538: invokevirtual 126	java/util/ArrayList:size	()I
    //   541: iload_2
    //   542: if_icmple +6 -> 548
    //   545: goto -529 -> 16
    //   548: goto -545 -> 3
    // Local variable table:
    //   start	length	slot	name	signature
    //   0	551	0	this	ɨ
    //   0	551	1	paramViewGroup	ViewGroup
    //   0	551	2	paramInt	int
    //   46	448	3	i	int
    //   27	505	4	localObject	Object
    //   178	283	5	localᴷ	ᴷ
    // Exception table:
    //   from	to	target	type
    //   425	431	143	java/lang/Exception
    //   419	425	279	java/lang/Exception
    //   425	431	279	java/lang/Exception
    //   431	437	279	java/lang/Exception
    //   437	446	279	java/lang/Exception
    //   446	460	279	java/lang/Exception
  }
  
  /* Error */
  public void ˋ(android.os.Parcelable paramParcelable, ClassLoader paramClassLoader)
  {
    // Byte code:
    //   0: goto +716 -> 716
    //   3: astore_1
    //   4: aload_1
    //   5: athrow
    //   6: iconst_1
    //   7: istore 4
    //   9: goto +175 -> 184
    //   12: iload 4
    //   14: istore_3
    //   15: goto +606 -> 621
    //   18: goto +718 -> 736
    //   21: bipush 97
    //   23: istore 4
    //   25: goto +345 -> 370
    //   28: goto +555 -> 583
    //   31: iload_3
    //   32: lookupswitch	default:+28->60, 24:+-14->18, 81:+296->328
    //   60: goto +268 -> 328
    //   63: iload 4
    //   65: lookupswitch	default:+27->92, 62:+222->287, 97:+654->719
    //   92: goto +195 -> 287
    //   95: aload 6
    //   97: invokeinterface 157 1 0
    //   102: checkcast 159	java/lang/String
    //   105: astore_2
    //   106: aload_2
    //   107: ldc -95
    //   109: invokevirtual 165	java/lang/String:startsWith	(Ljava/lang/String;)Z
    //   112: ifeq +6 -> 118
    //   115: goto +574 -> 689
    //   118: goto +27 -> 145
    //   121: iload_3
    //   122: tableswitch	default:+22->144, 0:+511->633, 1:+418->540
    //   144: return
    //   145: goto +591 -> 736
    //   148: getstatic 31	o/ɨ:ˊॱ	I
    //   151: bipush 39
    //   153: iadd
    //   154: istore_3
    //   155: iload_3
    //   156: sipush 128
    //   159: irem
    //   160: putstatic 29	o/ɨ:ˋॱ	I
    //   163: iload_3
    //   164: iconst_2
    //   165: irem
    //   166: ifeq +6 -> 172
    //   169: goto +12 -> 181
    //   172: goto +314 -> 486
    //   175: bipush 81
    //   177: istore_3
    //   178: goto -147 -> 31
    //   181: goto +305 -> 486
    //   184: iload 4
    //   186: tableswitch	default:+22->208, 0:+533->719, 1:+101->287
    //   208: goto +79 -> 287
    //   211: iconst_0
    //   212: istore_3
    //   213: goto -92 -> 121
    //   216: getstatic 29	o/ɨ:ˋॱ	I
    //   219: bipush 125
    //   221: iadd
    //   222: istore_3
    //   223: iload_3
    //   224: sipush 128
    //   227: irem
    //   228: putstatic 31	o/ɨ:ˊॱ	I
    //   231: iload_3
    //   232: iconst_2
    //   233: irem
    //   234: ifne +6 -> 240
    //   237: goto +513 -> 750
    //   240: goto +109 -> 349
    //   243: astore_1
    //   244: aload_1
    //   245: athrow
    //   246: bipush 97
    //   248: istore 4
    //   250: goto -187 -> 63
    //   253: aload_0
    //   254: getfield 70	o/ɨ:ˋ	Ljava/util/ArrayList;
    //   257: aload_1
    //   258: iload_3
    //   259: aaload
    //   260: checkcast 130	o/ᴷ$ˋ
    //   263: invokevirtual 117	java/util/ArrayList:add	(Ljava/lang/Object;)Z
    //   266: pop
    //   267: iload_3
    //   268: iconst_1
    //   269: iadd
    //   270: istore 4
    //   272: goto -56 -> 216
    //   275: iconst_0
    //   276: istore 4
    //   278: goto -94 -> 184
    //   281: iconst_0
    //   282: istore 4
    //   284: goto +119 -> 403
    //   287: ldc -89
    //   289: new 81	java/lang/StringBuilder
    //   292: dup
    //   293: invokespecial 90	java/lang/StringBuilder:<init>	()V
    //   296: ldc -88
    //   298: iconst_0
    //   299: ldc -87
    //   301: bipush 37
    //   303: bipush 11
    //   305: invokestatic 171	o/ɨ:ˊ	(ISIBI)Ljava/lang/String;
    //   308: invokevirtual 174	java/lang/String:intern	()Ljava/lang/String;
    //   311: invokevirtual 177	java/lang/StringBuilder:append	(Ljava/lang/String;)Ljava/lang/StringBuilder;
    //   314: aload_2
    //   315: invokevirtual 177	java/lang/StringBuilder:append	(Ljava/lang/String;)Ljava/lang/StringBuilder;
    //   318: invokevirtual 89	java/lang/StringBuilder:toString	()Ljava/lang/String;
    //   321: invokestatic 183	android/util/Log:w	(Ljava/lang/String;Ljava/lang/String;)I
    //   324: pop
    //   325: goto +29 -> 354
    //   328: goto +408 -> 736
    //   331: aload_1
    //   332: iconst_0
    //   333: invokevirtual 136	o/ᴷ:ˏ	(Z)V
    //   336: aload_0
    //   337: getfield 72	o/ɨ:ˏ	Ljava/util/ArrayList;
    //   340: iload_3
    //   341: aload_1
    //   342: invokevirtual 142	java/util/ArrayList:set	(ILjava/lang/Object;)Ljava/lang/Object;
    //   345: pop
    //   346: goto -201 -> 145
    //   349: iconst_1
    //   350: istore_3
    //   351: goto +80 -> 431
    //   354: goto -209 -> 145
    //   357: bipush 44
    //   359: istore 4
    //   361: goto +9 -> 370
    //   364: bipush 24
    //   366: istore_3
    //   367: goto -336 -> 31
    //   370: iload 4
    //   372: lookupswitch	default:+28->400, 44:+124->496, 97:+-119->253
    //   400: goto +96 -> 496
    //   403: iload 4
    //   405: tableswitch	default:+23->428, 0:+166->571, 1:+-74->331
    //   428: goto +143 -> 571
    //   431: iload_3
    //   432: tableswitch	default:+24->456, 0:+-420->12, 1:+186->618
    //   456: goto +162 -> 618
    //   459: getstatic 29	o/ɨ:ˋॱ	I
    //   462: bipush 33
    //   464: iadd
    //   465: istore_3
    //   466: iload_3
    //   467: sipush 128
    //   470: irem
    //   471: putstatic 31	o/ɨ:ˊॱ	I
    //   474: iload_3
    //   475: iconst_2
    //   476: irem
    //   477: ifne +6 -> 483
    //   480: goto -116 -> 364
    //   483: goto -308 -> 175
    //   486: aload_1
    //   487: ifnull +6 -> 493
    //   490: goto -279 -> 211
    //   493: goto +184 -> 677
    //   496: aload 5
    //   498: invokevirtual 189	android/os/Bundle:keySet	()Ljava/util/Set;
    //   501: astore_1
    //   502: aload_1
    //   503: invokeinterface 195 1 0
    //   508: astore 6
    //   510: goto -51 -> 459
    //   513: getstatic 29	o/ɨ:ˋॱ	I
    //   516: bipush 113
    //   518: iadd
    //   519: istore_3
    //   520: iload_3
    //   521: sipush 128
    //   524: irem
    //   525: putstatic 31	o/ɨ:ˊॱ	I
    //   528: iload_3
    //   529: iconst_2
    //   530: irem
    //   531: ifne +6 -> 537
    //   534: goto -506 -> 28
    //   537: goto +46 -> 583
    //   540: return
    //   541: aload_2
    //   542: iconst_0
    //   543: invokevirtual 199	java/lang/String:substring	(I)Ljava/lang/String;
    //   546: invokestatic 205	java/lang/Integer:parseInt	(Ljava/lang/String;)I
    //   549: istore_3
    //   550: aload_0
    //   551: getfield 76	o/ɨ:ˎ	Lo/ﺒ;
    //   554: aload 5
    //   556: aload_2
    //   557: invokevirtual 208	o/ﺒ:ॱ	(Landroid/os/Bundle;Ljava/lang/String;)Lo/ᴷ;
    //   560: astore_1
    //   561: aload_1
    //   562: ifnull +6 -> 568
    //   565: goto -290 -> 275
    //   568: goto -562 -> 6
    //   571: aload_0
    //   572: getfield 72	o/ɨ:ˏ	Ljava/util/ArrayList;
    //   575: aconst_null
    //   576: invokevirtual 117	java/util/ArrayList:add	(Ljava/lang/Object;)Z
    //   579: pop
    //   580: goto +139 -> 719
    //   583: iconst_0
    //   584: istore_3
    //   585: goto +36 -> 621
    //   588: aload_2
    //   589: iconst_1
    //   590: invokevirtual 199	java/lang/String:substring	(I)Ljava/lang/String;
    //   593: invokestatic 205	java/lang/Integer:parseInt	(Ljava/lang/String;)I
    //   596: istore_3
    //   597: aload_0
    //   598: getfield 76	o/ɨ:ˎ	Lo/ﺒ;
    //   601: aload 5
    //   603: aload_2
    //   604: invokevirtual 208	o/ﺒ:ॱ	(Landroid/os/Bundle;Ljava/lang/String;)Lo/ᴷ;
    //   607: astore_1
    //   608: aload_1
    //   609: ifnull +6 -> 615
    //   612: goto -366 -> 246
    //   615: goto +67 -> 682
    //   618: iload 4
    //   620: istore_3
    //   621: iload_3
    //   622: aload_1
    //   623: arraylength
    //   624: if_icmpge +6 -> 630
    //   627: goto -606 -> 21
    //   630: goto -273 -> 357
    //   633: aload_1
    //   634: checkcast 185	android/os/Bundle
    //   637: astore 5
    //   639: aload 5
    //   641: aload_2
    //   642: invokevirtual 212	android/os/Bundle:setClassLoader	(Ljava/lang/ClassLoader;)V
    //   645: aload 5
    //   647: ldc -42
    //   649: invokevirtual 218	android/os/Bundle:getParcelableArray	(Ljava/lang/String;)[Landroid/os/Parcelable;
    //   652: astore_1
    //   653: aload_0
    //   654: getfield 70	o/ɨ:ˋ	Ljava/util/ArrayList;
    //   657: invokevirtual 221	java/util/ArrayList:clear	()V
    //   660: aload_0
    //   661: getfield 72	o/ɨ:ˏ	Ljava/util/ArrayList;
    //   664: invokevirtual 221	java/util/ArrayList:clear	()V
    //   667: aload_1
    //   668: ifnull +6 -> 674
    //   671: goto -158 -> 513
    //   674: goto -178 -> 496
    //   677: iconst_1
    //   678: istore_3
    //   679: goto -558 -> 121
    //   682: bipush 62
    //   684: istore 4
    //   686: goto -623 -> 63
    //   689: getstatic 29	o/ɨ:ˋॱ	I
    //   692: bipush 85
    //   694: iadd
    //   695: istore_3
    //   696: iload_3
    //   697: sipush 128
    //   700: irem
    //   701: putstatic 31	o/ɨ:ˊॱ	I
    //   704: iload_3
    //   705: iconst_2
    //   706: irem
    //   707: ifne +6 -> 713
    //   710: goto -169 -> 541
    //   713: goto -125 -> 588
    //   716: goto -568 -> 148
    //   719: aload_0
    //   720: getfield 72	o/ɨ:ˏ	Ljava/util/ArrayList;
    //   723: invokevirtual 126	java/util/ArrayList:size	()I
    //   726: iload_3
    //   727: if_icmpgt +6 -> 733
    //   730: goto -449 -> 281
    //   733: goto +22 -> 755
    //   736: aload 6
    //   738: invokeinterface 225 1 0
    //   743: ifeq +6 -> 749
    //   746: goto -651 -> 95
    //   749: return
    //   750: iconst_0
    //   751: istore_3
    //   752: goto -321 -> 431
    //   755: iconst_1
    //   756: istore 4
    //   758: goto -355 -> 403
    // Local variable table:
    //   start	length	slot	name	signature
    //   0	761	0	this	ɨ
    //   0	761	1	paramParcelable	android.os.Parcelable
    //   0	761	2	paramClassLoader	ClassLoader
    //   14	738	3	i	int
    //   7	750	4	j	int
    //   496	150	5	localBundle	android.os.Bundle
    //   95	642	6	localIterator	java.util.Iterator
    // Exception table:
    //   from	to	target	type
    //   155	163	3	java/lang/Exception
    //   496	502	3	java/lang/Exception
    //   148	155	243	java/lang/Exception
    //   155	163	243	java/lang/Exception
    //   216	223	243	java/lang/Exception
    //   223	231	243	java/lang/Exception
  }
  
  public void ˋ(ViewGroup paramViewGroup)
  {
    label67:
    label109:
    for (;;)
    {
      throw new IllegalStateException("ViewPager with adapter " + this + " requires a view id");
      int i;
      for (;;)
      {
        i = ˊॱ + 77;
        ˋॱ = i % 128;
        if (i % 2 == 0) {
          return;
        }
        return;
        break;
      }
      for (;;)
      {
        if (paramViewGroup.getId() == -1) {
          break label109;
        }
        break label67;
        i = ˊॱ + 93;
        ˋॱ = i % 128;
        if (i % 2 != 0) {
          break;
        }
      }
    }
  }
  
  /* Error */
  public android.os.Parcelable ˎ()
  {
    // Byte code:
    //   0: goto +440 -> 440
    //   3: aload 4
    //   5: astore 5
    //   7: iload_2
    //   8: lookupswitch	default:+28->36, 3:+361->369, 91:+350->358
    //   36: aload 4
    //   38: astore 5
    //   40: goto +329 -> 369
    //   43: iconst_1
    //   44: istore_2
    //   45: goto +189 -> 234
    //   48: new 81	java/lang/StringBuilder
    //   51: dup
    //   52: invokespecial 90	java/lang/StringBuilder:<init>	()V
    //   55: ldc -95
    //   57: invokevirtual 177	java/lang/StringBuilder:append	(Ljava/lang/String;)Ljava/lang/StringBuilder;
    //   60: iload_1
    //   61: invokevirtual 241	java/lang/StringBuilder:append	(I)Ljava/lang/StringBuilder;
    //   64: invokevirtual 89	java/lang/StringBuilder:toString	()Ljava/lang/String;
    //   67: astore 5
    //   69: aload_0
    //   70: getfield 76	o/ɨ:ˎ	Lo/ﺒ;
    //   73: aload 4
    //   75: aload 5
    //   77: aload 6
    //   79: invokevirtual 244	o/ﺒ:ॱ	(Landroid/os/Bundle;Ljava/lang/String;Lo/ᴷ;)V
    //   82: aload 4
    //   84: astore 5
    //   86: goto +283 -> 369
    //   89: aload 4
    //   91: areturn
    //   92: iconst_3
    //   93: istore_2
    //   94: goto -91 -> 3
    //   97: aload 6
    //   99: invokevirtual 247	o/ᴷ:ʽॱ	()Z
    //   102: istore_3
    //   103: bipush 90
    //   105: iconst_0
    //   106: idiv
    //   107: istore_2
    //   108: iload_3
    //   109: ifeq +6 -> 115
    //   112: goto -69 -> 43
    //   115: goto +108 -> 223
    //   118: bipush 31
    //   120: istore_2
    //   121: goto +73 -> 194
    //   124: getstatic 29	o/ɨ:ˋॱ	I
    //   127: bipush 125
    //   129: iadd
    //   130: istore_1
    //   131: iload_1
    //   132: sipush 128
    //   135: irem
    //   136: putstatic 31	o/ɨ:ˊॱ	I
    //   139: iload_1
    //   140: iconst_2
    //   141: irem
    //   142: ifne +6 -> 148
    //   145: goto +286 -> 431
    //   148: goto +264 -> 412
    //   151: new 185	android/os/Bundle
    //   154: dup
    //   155: invokespecial 248	android/os/Bundle:<init>	()V
    //   158: astore 4
    //   160: goto -112 -> 48
    //   163: iload_1
    //   164: aload_0
    //   165: getfield 72	o/ɨ:ˏ	Ljava/util/ArrayList;
    //   168: invokevirtual 126	java/util/ArrayList:size	()I
    //   171: if_icmpge +6 -> 177
    //   174: goto -56 -> 118
    //   177: goto +51 -> 228
    //   180: aload 6
    //   182: invokevirtual 247	o/ᴷ:ʽॱ	()Z
    //   185: ifeq +6 -> 191
    //   188: goto +246 -> 434
    //   191: goto -99 -> 92
    //   194: iload_2
    //   195: lookupswitch	default:+25->220, 31:+135->330, 50:+-106->89
    //   220: goto +110 -> 330
    //   223: iconst_0
    //   224: istore_2
    //   225: goto +9 -> 234
    //   228: bipush 50
    //   230: istore_2
    //   231: goto -37 -> 194
    //   234: aload 4
    //   236: astore 5
    //   238: iload_2
    //   239: tableswitch	default:+21->260, 0:+130->369, 1:+119->358
    //   260: aload 4
    //   262: astore 5
    //   264: goto +105 -> 369
    //   267: iconst_0
    //   268: istore_1
    //   269: goto -106 -> 163
    //   272: astore 4
    //   274: aload 4
    //   276: athrow
    //   277: new 185	android/os/Bundle
    //   280: dup
    //   281: invokespecial 248	android/os/Bundle:<init>	()V
    //   284: astore 4
    //   286: aload_0
    //   287: getfield 70	o/ɨ:ˋ	Ljava/util/ArrayList;
    //   290: astore 5
    //   292: aload 5
    //   294: invokevirtual 126	java/util/ArrayList:size	()I
    //   297: istore_1
    //   298: iload_1
    //   299: anewarray 130	o/ᴷ$ˋ
    //   302: astore 5
    //   304: aload_0
    //   305: getfield 70	o/ɨ:ˋ	Ljava/util/ArrayList;
    //   308: astore 6
    //   310: aload 6
    //   312: aload 5
    //   314: invokevirtual 252	java/util/ArrayList:toArray	([Ljava/lang/Object;)[Ljava/lang/Object;
    //   317: pop
    //   318: aload 4
    //   320: ldc -42
    //   322: aload 5
    //   324: invokevirtual 256	android/os/Bundle:putParcelableArray	(Ljava/lang/String;[Landroid/os/Parcelable;)V
    //   327: goto -60 -> 267
    //   330: aload_0
    //   331: getfield 72	o/ɨ:ˏ	Ljava/util/ArrayList;
    //   334: iload_1
    //   335: invokevirtual 113	java/util/ArrayList:get	(I)Ljava/lang/Object;
    //   338: checkcast 104	o/ᴷ
    //   341: astore 6
    //   343: aload 6
    //   345: ifnull +6 -> 351
    //   348: goto +37 -> 385
    //   351: aload 4
    //   353: astore 5
    //   355: goto +14 -> 369
    //   358: aload 4
    //   360: ifnonnull +6 -> 366
    //   363: goto -212 -> 151
    //   366: goto -318 -> 48
    //   369: iload_1
    //   370: iconst_1
    //   371: iadd
    //   372: istore_1
    //   373: aload 5
    //   375: astore 4
    //   377: goto -214 -> 163
    //   380: astore 4
    //   382: aload 4
    //   384: athrow
    //   385: getstatic 31	o/ɨ:ˊॱ	I
    //   388: bipush 89
    //   390: iadd
    //   391: istore_2
    //   392: iload_2
    //   393: sipush 128
    //   396: irem
    //   397: putstatic 29	o/ɨ:ˋॱ	I
    //   400: iload_2
    //   401: iconst_2
    //   402: irem
    //   403: ifeq +6 -> 409
    //   406: goto -309 -> 97
    //   409: goto -229 -> 180
    //   412: aconst_null
    //   413: astore 4
    //   415: aload_0
    //   416: getfield 70	o/ɨ:ˋ	Ljava/util/ArrayList;
    //   419: invokevirtual 126	java/util/ArrayList:size	()I
    //   422: ifle +6 -> 428
    //   425: goto -148 -> 277
    //   428: goto -161 -> 267
    //   431: goto -19 -> 412
    //   434: bipush 91
    //   436: istore_2
    //   437: goto -434 -> 3
    //   440: goto -316 -> 124
    // Local variable table:
    //   start	length	slot	name	signature
    //   0	443	0	this	ɨ
    //   60	313	1	i	int
    //   7	430	2	j	int
    //   102	7	3	bool	boolean
    //   3	258	4	localBundle	android.os.Bundle
    //   272	3	4	localException1	Exception
    //   284	92	4	localObject1	Object
    //   380	3	4	localException2	Exception
    //   413	1	4	localObject2	Object
    //   5	369	5	localObject3	Object
    //   77	267	6	localObject4	Object
    // Exception table:
    //   from	to	target	type
    //   292	298	272	java/lang/Exception
    //   298	304	272	java/lang/Exception
    //   304	310	272	java/lang/Exception
    //   310	318	272	java/lang/Exception
    //   318	327	272	java/lang/Exception
    //   286	292	380	java/lang/Exception
  }
  
  public void ˎ(ViewGroup paramViewGroup, int paramInt, Object paramObject)
  {
    break label98;
    paramInt = ˊॱ + 1;
    ˋॱ = paramInt % 128;
    int i;
    if (paramInt % 2 == 0)
    {
      break label145;
      break label286;
      break label286;
    }
    else
    {
      for (;;)
      {
        try
        {
          paramViewGroup = this.ˎ;
          paramViewGroup = paramViewGroup.ˏ();
          try
          {
            this.ˊ = paramViewGroup;
          }
          catch (Exception paramViewGroup)
          {
            throw paramViewGroup;
          }
          paramInt = 1;
        }
        catch (Exception paramViewGroup)
        {
          throw paramViewGroup;
        }
        switch (i)
        {
        }
      }
    }
    label98:
    label101:
    label145:
    label150:
    label168:
    label224:
    ArrayList localArrayList;
    for (;;)
    {
      i = 38;
      break label101;
      break label150;
      switch (i)
      {
      }
      break;
      for (;;)
      {
        i = 22;
        break;
        do
        {
          i = 86;
          break;
          paramInt = 0;
          break label361;
          paramObject = (ᴷ)paramObject;
        } while (this.ˊ == null);
      }
      i = ˊॱ + 125;
      ˋॱ = i % 128;
      if (i % 2 == 0) {}
      for (;;)
      {
        break label224;
        paramInt = 88 / 0;
        return;
        paramViewGroup = this.ˋ;
        paramViewGroup.add(null);
        break label168;
        localArrayList.set(paramInt, paramViewGroup);
        this.ˏ.set(paramInt, null);
        this.ˊ.ॱ(paramObject);
        break;
        i = 95;
        break label101;
        label261:
        paramViewGroup = null;
      }
    }
    for (;;)
    {
      localArrayList = this.ˋ;
      if (paramObject.ʽॱ()) {
        break label331;
      }
      break label261;
      return;
      label286:
      if (this.ˋ.size() <= paramInt) {
        break;
      }
    }
    for (;;)
    {
      paramViewGroup = this.ˎ.ˏ(paramObject);
      break;
      label331:
      do
      {
        paramViewGroup = this.ˎ.ˏ(paramObject);
        i = null.length;
        break;
        i = ˊॱ + 65;
        ˋॱ = i % 128;
      } while (i % 2 != 0);
    }
    label361:
    switch (paramInt)
    {
    }
  }
  
  public void ॱ(ViewGroup paramViewGroup, int paramInt, Object paramObject)
  {
    break label123;
    paramViewGroup = (ᴷ)paramObject;
    if (paramViewGroup == this.ॱ) {
      break label53;
    }
    if (this.ॱ == null)
    {
      break label48;
      paramViewGroup.ˏ(true);
      paramViewGroup.ˎ(true);
      break label194;
      label48:
      paramInt = 0;
      break label95;
      label53:
      break label207;
    }
    else
    {
      paramInt = 1;
      break label95;
      label61:
      paramInt = 52 / 0;
      return;
      label67:
      paramInt = 0;
    }
    switch (paramInt)
    {
    case 1: 
    default: 
      label69:
      break;
      switch (paramInt)
      {
      default: 
        label95:
        break label144;
      }
      label123:
      break;
    }
    paramViewGroup = (ᴷ)paramObject;
    paramViewGroup = this.ॱ;
    throw new NullPointerException();
    label144:
    paramInt = ˊॱ + 87;
    ˋॱ = paramInt % 128;
    if (paramInt % 2 == 0) {
      break label232;
    }
    for (;;)
    {
      paramInt = 1;
      break label69;
      break label232;
      label179:
      paramInt = 0;
      break label251;
      for (;;)
      {
        if (paramViewGroup == null)
        {
          break label179;
          label194:
          this.ॱ = paramViewGroup;
          break;
        }
        paramInt = 1;
        break label251;
        label207:
        paramInt = ˋॱ + 75;
        ˊॱ = paramInt % 128;
        if (paramInt % 2 == 0) {
          break label61;
        }
        return;
        label232:
        this.ॱ.ˏ(false);
        this.ॱ.ˎ(false);
      }
      label251:
      switch (paramInt)
      {
      }
      break;
      paramInt = ˊॱ + 49;
      ˋॱ = paramInt % 128;
      if (paramInt % 2 != 0) {
        break label67;
      }
    }
  }
}
