package o;

import android.util.Log;
import java.util.ArrayList;
import java.util.List;

class צ<R>
  implements ڋ.ˊ, Runnable, Comparable<צ<?>>, п.ˊ
{
  private static byte[] ˋˋ = { -17, 20, 51, -26, 8, -71, 73, 15, -9, -16, 12, -79, 6, -18, -109, -76, 97, -113, 62, -55, 118, -121, 118, 57, -127 };
  private static int ˋᐝ = -769232451;
  private static int ˌ = 1337841715;
  private static int ˍ;
  private static short[] ˎˎ;
  private static int ˏˎ;
  private static int ˑ = 0;
  private final С ʻ = С.ॱ();
  private ڒ ʻॱ;
  private final List<Throwable> ʼ = new ArrayList();
  private Object ʼॱ;
  ڹ ʽ;
  private boolean ʽॱ;
  private ﾚ ʾ;
  private long ʿ;
  private Thread ˈ;
  private volatile boolean ˉ;
  final ب<R> ˊ = new ب();
  private ｬ ˊˊ;
  private volatile ڋ ˊˋ;
  private ᔦ ˊॱ;
  private volatile boolean ˊᐝ;
  int ˋ;
  private ʢ<?> ˋˊ;
  private final ˊ ˋॱ = new ˊ();
  final ˋ<?> ˎ = new ˋ();
  ﾚ ˏ;
  private final 丨.if<צ<?>> ˏॱ;
  private final iF ͺ;
  int ॱ;
  private ᴈ ॱˊ;
  private ˎ ॱˋ;
  private int ॱˎ;
  ʄ ॱॱ;
  private aux ॱᐝ;
  ﾚ ᐝ;
  private If<R> ᐝॱ;
  
  static
  {
    ˏˎ = 1;
    ˍ = 30;
  }
  
  צ(iF paramIF, 丨.if<צ<?>> paramIf)
  {
    this.ͺ = paramIF;
    this.ˏॱ = paramIf;
  }
  
  /* Error */
  private ڋ ʻ()
  {
    // Byte code:
    //   0: goto +183 -> 183
    //   3: goto +68 -> 71
    //   6: new 181	o/ח
    //   9: dup
    //   10: aload_0
    //   11: getfield 152	o/צ:ˊ	Lo/ب;
    //   14: aload_0
    //   15: invokespecial 184	o/ח:<init>	(Lo/ب;Lo/ڋ$ˊ;)V
    //   18: areturn
    //   19: goto +9 -> 28
    //   22: astore_2
    //   23: aload_2
    //   24: athrow
    //   25: goto +164 -> 189
    //   28: getstatic 187	o/צ$4:ˋ	[I
    //   31: aload_0
    //   32: getfield 189	o/צ:ॱˋ	Lo/צ$ˎ;
    //   35: invokevirtual 193	o/צ$ˎ:ordinal	()I
    //   38: iaload
    //   39: tableswitch	default:+29->68, 1:+59->98, 2:+-33->6, 3:+131->170, 4:+-36->3
    //   68: goto +72 -> 140
    //   71: getstatic 106	o/צ:ˑ	I
    //   74: bipush 95
    //   76: iadd
    //   77: istore_1
    //   78: iload_1
    //   79: sipush 128
    //   82: irem
    //   83: putstatic 108	o/צ:ˏˎ	I
    //   86: iload_1
    //   87: iconst_2
    //   88: irem
    //   89: ifne +6 -> 95
    //   92: goto -67 -> 25
    //   95: goto +94 -> 189
    //   98: aload_0
    //   99: getfield 152	o/צ:ˊ	Lo/ب;
    //   102: astore_2
    //   103: new 195	o/ঢ
    //   106: dup
    //   107: aload_2
    //   108: aload_0
    //   109: invokespecial 196	o/ঢ:<init>	(Lo/ب;Lo/ڋ$ˊ;)V
    //   112: areturn
    //   113: getstatic 106	o/צ:ˑ	I
    //   116: bipush 41
    //   118: iadd
    //   119: istore_1
    //   120: iload_1
    //   121: sipush 128
    //   124: irem
    //   125: putstatic 108	o/צ:ˏˎ	I
    //   128: iload_1
    //   129: iconst_2
    //   130: irem
    //   131: ifne +6 -> 137
    //   134: goto -115 -> 19
    //   137: goto -109 -> 28
    //   140: new 198	java/lang/IllegalStateException
    //   143: dup
    //   144: new 200	java/lang/StringBuilder
    //   147: dup
    //   148: invokespecial 201	java/lang/StringBuilder:<init>	()V
    //   151: ldc -53
    //   153: invokevirtual 207	java/lang/StringBuilder:append	(Ljava/lang/String;)Ljava/lang/StringBuilder;
    //   156: aload_0
    //   157: getfield 189	o/צ:ॱˋ	Lo/צ$ˎ;
    //   160: invokevirtual 210	java/lang/StringBuilder:append	(Ljava/lang/Object;)Ljava/lang/StringBuilder;
    //   163: invokevirtual 214	java/lang/StringBuilder:toString	()Ljava/lang/String;
    //   166: invokespecial 217	java/lang/IllegalStateException:<init>	(Ljava/lang/String;)V
    //   169: athrow
    //   170: new 219	o/ᒌ
    //   173: dup
    //   174: aload_0
    //   175: getfield 152	o/צ:ˊ	Lo/ب;
    //   178: aload_0
    //   179: invokespecial 220	o/ᒌ:<init>	(Lo/ب;Lo/ڋ$ˊ;)V
    //   182: areturn
    //   183: goto -70 -> 113
    //   186: astore_2
    //   187: aload_2
    //   188: athrow
    //   189: aconst_null
    //   190: areturn
    // Local variable table:
    //   start	length	slot	name	signature
    //   0	191	0	this	צ
    //   77	54	1	i	int
    //   22	2	2	localException1	Exception
    //   102	6	2	localب	ب
    //   186	2	2	localException2	Exception
    // Exception table:
    //   from	to	target	type
    //   71	78	22	java/lang/Exception
    //   78	86	22	java/lang/Exception
    //   98	103	186	java/lang/Exception
  }
  
  private void ʼ()
  {
    break label237;
    return;
    for (;;)
    {
      int i;
      switch (i)
      {
      case 40: 
      default: 
        break label225;
        this.ˋॱ.ॱ();
        this.ˎ.ˏ();
        this.ˊ.ˎ();
        this.ˊᐝ = false;
        this.ˊॱ = null;
        this.ˏ = null;
        this.ॱॱ = null;
        this.ॱˊ = null;
        this.ʻॱ = null;
        this.ᐝॱ = null;
        this.ॱˋ = null;
        this.ˊˋ = null;
        this.ˈ = null;
        this.ᐝ = null;
        this.ʼॱ = null;
        this.ˊˊ = null;
        this.ˋˊ = null;
        this.ʿ = 0L;
        this.ˉ = false;
        this.ʼ.clear();
        this.ˏॱ.ॱ(this);
        break label198;
        i = 40;
        break;
      case 77: 
        label198:
        label225:
        label237:
        for (;;)
        {
          try
          {
            i = ˑ;
            i += 37;
            try
            {
              ˏˎ = i % 128;
              if (i % 2 == 0) {
                break;
              }
            }
            catch (Exception localException1)
            {
              throw localException1;
            }
            i = ˑ + 29;
            ˏˎ = i % 128;
            if (i % 2 == 0) {
              break label240;
            }
          }
          catch (Exception localException2)
          {
            throw localException2;
          }
          i = 73 / 0;
          return;
        }
        label240:
        i = 77;
      }
    }
  }
  
  /* Error */
  private int ʽ()
  {
    // Byte code:
    //   0: goto +91 -> 91
    //   3: getstatic 106	o/צ:ˑ	I
    //   6: bipush 85
    //   8: iadd
    //   9: istore_2
    //   10: iload_2
    //   11: sipush 128
    //   14: irem
    //   15: putstatic 108	o/צ:ˏˎ	I
    //   18: iload_2
    //   19: iconst_2
    //   20: irem
    //   21: ifne +6 -> 27
    //   24: goto +70 -> 94
    //   27: iload_1
    //   28: ireturn
    //   29: astore_3
    //   30: aload_3
    //   31: athrow
    //   32: getstatic 108	o/צ:ˏˎ	I
    //   35: bipush 91
    //   37: iadd
    //   38: istore_1
    //   39: iload_1
    //   40: sipush 128
    //   43: irem
    //   44: putstatic 106	o/צ:ˑ	I
    //   47: iload_1
    //   48: iconst_2
    //   49: irem
    //   50: ifeq +6 -> 56
    //   53: goto +77 -> 130
    //   56: goto +58 -> 114
    //   59: iload_1
    //   60: lookupswitch	default:+28->88, 0:+36->96, 5:+59->119
    //   88: goto +31 -> 119
    //   91: goto -59 -> 32
    //   94: iload_1
    //   95: ireturn
    //   96: aload_0
    //   97: getfield 236	o/צ:ॱˊ	Lo/ᴈ;
    //   100: astore_3
    //   101: aload_3
    //   102: invokevirtual 269	o/ᴈ:ordinal	()I
    //   105: istore_1
    //   106: new 271	java/lang/NullPointerException
    //   109: dup
    //   110: invokespecial 272	java/lang/NullPointerException:<init>	()V
    //   113: athrow
    //   114: iconst_5
    //   115: istore_1
    //   116: goto -57 -> 59
    //   119: aload_0
    //   120: getfield 236	o/צ:ॱˊ	Lo/ᴈ;
    //   123: invokevirtual 269	o/ᴈ:ordinal	()I
    //   126: istore_1
    //   127: goto -124 -> 3
    //   130: iconst_0
    //   131: istore_1
    //   132: goto -73 -> 59
    // Local variable table:
    //   start	length	slot	name	signature
    //   0	135	0	this	צ
    //   27	105	1	i	int
    //   9	12	2	j	int
    //   29	2	3	localException	Exception
    //   100	2	3	localᴈ	ᴈ
    // Exception table:
    //   from	to	target	type
    //   96	101	29	java/lang/Exception
    //   101	114	29	java/lang/Exception
  }
  
  /* Error */
  private static String ˊ(int paramInt1, int paramInt2, int paramInt3, byte paramByte, short paramShort)
  {
    // Byte code:
    //   0: goto +231 -> 231
    //   3: bipush 67
    //   5: istore_0
    //   6: goto +21 -> 27
    //   9: goto +589 -> 598
    //   12: bipush 40
    //   14: istore_0
    //   15: goto +12 -> 27
    //   18: goto +260 -> 278
    //   21: iload 7
    //   23: istore_0
    //   24: goto +67 -> 91
    //   27: iload_0
    //   28: lookupswitch	default:+28->56, 40:+373->401, 67:+206->234
    //   56: goto +178 -> 234
    //   59: iload 6
    //   61: lookupswitch	default:+27->88, 18:+244->305, 25:+111->172
    //   88: goto +217 -> 305
    //   91: iload_0
    //   92: ifle +6 -> 98
    //   95: goto +107 -> 202
    //   98: goto +169 -> 267
    //   101: getstatic 136	o/צ:ˋˋ	[B
    //   104: astore 9
    //   106: iload_1
    //   107: bipush 65
    //   109: iadd
    //   110: istore 6
    //   112: iload 7
    //   114: aload 9
    //   116: iload_1
    //   117: baload
    //   118: iload 4
    //   120: iushr
    //   121: i2b
    //   122: iload_3
    //   123: iand
    //   124: ishl
    //   125: i2c
    //   126: istore 5
    //   128: iload 6
    //   130: istore_1
    //   131: goto +121 -> 252
    //   134: iload_2
    //   135: iload_0
    //   136: iadd
    //   137: iconst_2
    //   138: isub
    //   139: iload 7
    //   141: iadd
    //   142: iload 6
    //   144: iadd
    //   145: istore_2
    //   146: getstatic 139	o/צ:ˋᐝ	I
    //   149: istore 6
    //   151: iload 6
    //   153: iload_1
    //   154: iadd
    //   155: i2c
    //   156: istore 5
    //   158: aload 8
    //   160: iload 5
    //   162: invokevirtual 276	java/lang/StringBuilder:append	(C)Ljava/lang/StringBuilder;
    //   165: pop
    //   166: iconst_1
    //   167: istore 6
    //   169: goto +203 -> 372
    //   172: getstatic 106	o/צ:ˑ	I
    //   175: bipush 109
    //   177: iadd
    //   178: istore 6
    //   180: iload 6
    //   182: sipush 128
    //   185: irem
    //   186: putstatic 108	o/צ:ˏˎ	I
    //   189: iload 6
    //   191: iconst_2
    //   192: irem
    //   193: ifne +6 -> 199
    //   196: goto -95 -> 101
    //   199: goto +220 -> 419
    //   202: getstatic 106	o/צ:ˑ	I
    //   205: iconst_3
    //   206: iadd
    //   207: istore 7
    //   209: iload 7
    //   211: sipush 128
    //   214: irem
    //   215: putstatic 108	o/צ:ˏˎ	I
    //   218: iload 7
    //   220: iconst_2
    //   221: irem
    //   222: ifne +6 -> 228
    //   225: goto -207 -> 18
    //   228: goto +50 -> 278
    //   231: goto +103 -> 334
    //   234: getstatic 136	o/צ:ˋˋ	[B
    //   237: iload_2
    //   238: getstatic 142	o/צ:ˌ	I
    //   241: ishl
    //   242: baload
    //   243: getstatic 110	o/צ:ˍ	I
    //   246: ishl
    //   247: i2b
    //   248: istore_0
    //   249: goto -158 -> 91
    //   252: aload 8
    //   254: iload 5
    //   256: invokevirtual 276	java/lang/StringBuilder:append	(C)Ljava/lang/StringBuilder;
    //   259: pop
    //   260: iload_2
    //   261: iconst_1
    //   262: iadd
    //   263: istore_2
    //   264: goto +395 -> 659
    //   267: aload 8
    //   269: invokevirtual 214	java/lang/StringBuilder:toString	()Ljava/lang/String;
    //   272: areturn
    //   273: iconst_1
    //   274: istore_0
    //   275: goto +214 -> 489
    //   278: getstatic 142	o/צ:ˌ	I
    //   281: istore 7
    //   283: iload 6
    //   285: ifeq +6 -> 291
    //   288: goto +297 -> 585
    //   291: goto +272 -> 563
    //   294: iload_2
    //   295: iload_0
    //   296: if_icmpge +6 -> 302
    //   299: goto +240 -> 539
    //   302: goto -35 -> 267
    //   305: getstatic 278	o/צ:ˎˎ	[S
    //   308: astore 9
    //   310: iload_1
    //   311: iconst_1
    //   312: isub
    //   313: istore 6
    //   315: aload 9
    //   317: iload_1
    //   318: saload
    //   319: iload 4
    //   321: iadd
    //   322: i2s
    //   323: iload_3
    //   324: ixor
    //   325: iload 7
    //   327: iadd
    //   328: i2c
    //   329: istore 5
    //   331: goto +220 -> 551
    //   334: new 200	java/lang/StringBuilder
    //   337: dup
    //   338: invokespecial 201	java/lang/StringBuilder:<init>	()V
    //   341: astore 8
    //   343: getstatic 110	o/צ:ˍ	I
    //   346: iload_0
    //   347: iadd
    //   348: istore 6
    //   350: iload 6
    //   352: istore_0
    //   353: iload 6
    //   355: iconst_m1
    //   356: if_icmpne +6 -> 362
    //   359: goto +198 -> 557
    //   362: goto +253 -> 615
    //   365: bipush 25
    //   367: istore 6
    //   369: goto -310 -> 59
    //   372: getstatic 106	o/צ:ˑ	I
    //   375: istore_1
    //   376: iload_1
    //   377: bipush 67
    //   379: iadd
    //   380: istore_1
    //   381: iload_1
    //   382: sipush 128
    //   385: irem
    //   386: putstatic 108	o/צ:ˏˎ	I
    //   389: iload_1
    //   390: iconst_2
    //   391: irem
    //   392: ifne +6 -> 398
    //   395: goto -386 -> 9
    //   398: goto +200 -> 598
    //   401: getstatic 136	o/צ:ˋˋ	[B
    //   404: getstatic 142	o/צ:ˌ	I
    //   407: iload_2
    //   408: iadd
    //   409: baload
    //   410: getstatic 110	o/צ:ˍ	I
    //   413: iadd
    //   414: i2b
    //   415: istore_0
    //   416: goto -325 -> 91
    //   419: getstatic 136	o/צ:ˋˋ	[B
    //   422: astore 9
    //   424: iload_1
    //   425: iconst_1
    //   426: isub
    //   427: istore 6
    //   429: aload 9
    //   431: iload_1
    //   432: baload
    //   433: iload 4
    //   435: iadd
    //   436: i2b
    //   437: iload_3
    //   438: ixor
    //   439: iload 7
    //   441: iadd
    //   442: i2c
    //   443: istore 5
    //   445: iload 6
    //   447: istore_1
    //   448: goto -196 -> 252
    //   451: iload 6
    //   453: ifeq +6 -> 459
    //   456: goto +113 -> 569
    //   459: goto -368 -> 91
    //   462: getstatic 106	o/צ:ˑ	I
    //   465: bipush 125
    //   467: iadd
    //   468: istore_0
    //   469: iload_0
    //   470: sipush 128
    //   473: irem
    //   474: putstatic 108	o/צ:ˏˎ	I
    //   477: iload_0
    //   478: iconst_2
    //   479: irem
    //   480: ifne +6 -> 486
    //   483: goto -480 -> 3
    //   486: goto -474 -> 12
    //   489: iload_0
    //   490: tableswitch	default:+22->512, 0:+-469->21, 1:+131->621
    //   512: goto +109 -> 621
    //   515: astore 8
    //   517: aload 8
    //   519: athrow
    //   520: getstatic 278	o/צ:ˎˎ	[S
    //   523: getstatic 142	o/צ:ˌ	I
    //   526: iload_2
    //   527: iadd
    //   528: saload
    //   529: getstatic 110	o/צ:ˍ	I
    //   532: iadd
    //   533: i2s
    //   534: istore 7
    //   536: goto +91 -> 627
    //   539: getstatic 136	o/צ:ˋˋ	[B
    //   542: ifnull +6 -> 548
    //   545: goto -180 -> 365
    //   548: goto +43 -> 591
    //   551: iload 6
    //   553: istore_1
    //   554: goto -302 -> 252
    //   557: iconst_1
    //   558: istore 6
    //   560: goto -109 -> 451
    //   563: iconst_0
    //   564: istore 6
    //   566: goto -432 -> 134
    //   569: getstatic 136	o/צ:ˋˋ	[B
    //   572: astore 9
    //   574: aload 9
    //   576: ifnull +6 -> 582
    //   579: goto -117 -> 462
    //   582: goto -62 -> 520
    //   585: iconst_1
    //   586: istore 6
    //   588: goto -454 -> 134
    //   591: bipush 18
    //   593: istore 6
    //   595: goto -536 -> 59
    //   598: iload_2
    //   599: istore_1
    //   600: iload 5
    //   602: istore 7
    //   604: iload 6
    //   606: istore_2
    //   607: goto -313 -> 294
    //   610: astore 8
    //   612: aload 8
    //   614: athrow
    //   615: iconst_0
    //   616: istore 6
    //   618: goto -167 -> 451
    //   621: iload 7
    //   623: istore_0
    //   624: goto -533 -> 91
    //   627: getstatic 106	o/צ:ˑ	I
    //   630: bipush 69
    //   632: iadd
    //   633: istore_0
    //   634: iload_0
    //   635: sipush 128
    //   638: irem
    //   639: putstatic 108	o/צ:ˏˎ	I
    //   642: iload_0
    //   643: iconst_2
    //   644: irem
    //   645: ifne +6 -> 651
    //   648: goto +6 -> 654
    //   651: goto -378 -> 273
    //   654: iconst_0
    //   655: istore_0
    //   656: goto -167 -> 489
    //   659: iload 5
    //   661: istore 7
    //   663: goto -369 -> 294
    // Local variable table:
    //   start	length	slot	name	signature
    //   0	666	0	paramInt1	int
    //   0	666	1	paramInt2	int
    //   0	666	2	paramInt3	int
    //   0	666	3	paramByte	byte
    //   0	666	4	paramShort	short
    //   126	534	5	i	int
    //   59	558	6	j	int
    //   21	641	7	k	int
    //   158	184	8	localStringBuilder	StringBuilder
    //   515	3	8	localException1	Exception
    //   610	3	8	localException2	Exception
    //   104	471	9	localObject	Object
    // Exception table:
    //   from	to	target	type
    //   146	151	515	java/lang/Exception
    //   158	166	515	java/lang/Exception
    //   569	574	515	java/lang/Exception
    //   372	376	610	java/lang/Exception
    //   381	389	610	java/lang/Exception
  }
  
  private <Data> ก<R> ˊ(Data paramData, ｬ paramｬ)
  {
    for (;;)
    {
      int i = ˑ + 95;
      ˏˎ = i % 128;
      if (i % 2 != 0)
      {
        break label178;
        i = 4;
        try
        {
          localب = this.ˊ;
        }
        catch (Exception paramData)
        {
          ب localب;
          Class localClass;
          label72:
          throw paramData;
        }
      }
      try
      {
        localClass = paramData.getClass();
        paramData = ॱ(paramData, paramｬ, localب.ˏ(localClass));
        i = 58 / 0;
      }
      catch (Exception paramData)
      {
        label151:
        label178:
        throw paramData;
      }
      switch (i)
      {
      case 4: 
      default: 
        break;
        return paramData;
        for (;;)
        {
          i = 16;
          break label72;
          i = null.length;
          return paramData;
          i = 1;
          break label151;
          i = ˏˎ + 71;
          ˑ = i % 128;
          if (i % 2 != 0) {
            break;
          }
        }
        for (;;)
        {
          switch (i)
          {
          }
          return paramData;
          i = 0;
        }
      }
      paramData = ॱ(paramData, paramｬ, this.ˊ.ˏ(paramData.getClass()));
    }
  }
  
  private void ˊॱ()
  {
    int i;
    switch (i)
    {
    default: 
      break;
    case 1: 
      for (;;)
      {
        i = ˑ + 21;
        ˏˎ = i % 128;
        if (i % 2 != 0)
        {
          i = 1;
          break;
        }
        i = 0;
        break;
        break label69;
        return;
        label69:
        ͺ();
        ঌ localঌ = new ঌ("Failed to load resource", new ArrayList(this.ʼ));
        this.ᐝॱ.ˎ(localঌ);
        ॱॱ();
      }
    }
    throw new NullPointerException();
  }
  
  /* Error */
  private void ˋ(ก<R> paramก, ｬ paramｬ)
  {
    // Byte code:
    //   0: goto +224 -> 224
    //   3: getstatic 106	o/צ:ˑ	I
    //   6: bipush 43
    //   8: iadd
    //   9: istore_3
    //   10: iload_3
    //   11: sipush 128
    //   14: irem
    //   15: putstatic 108	o/צ:ˏˎ	I
    //   18: iload_3
    //   19: iconst_2
    //   20: irem
    //   21: ifne +6 -> 27
    //   24: goto +53 -> 77
    //   27: goto +65 -> 92
    //   30: aload_1
    //   31: checkcast 310	o/ܬ
    //   34: invokeinterface 311 1 0
    //   39: goto +62 -> 101
    //   42: iload_3
    //   43: lookupswitch	default:+25->68, 36:+88->131, 70:+75->118
    //   68: goto +50 -> 118
    //   71: bipush 66
    //   73: istore_3
    //   74: goto +116 -> 190
    //   77: goto +15 -> 92
    //   80: astore_1
    //   81: aload 6
    //   83: ifnull +6 -> 89
    //   86: goto +224 -> 310
    //   89: goto +292 -> 381
    //   92: goto +247 -> 339
    //   95: bipush 33
    //   97: istore_3
    //   98: goto +92 -> 190
    //   101: goto +49 -> 150
    //   104: astore_1
    //   105: aload_1
    //   106: athrow
    //   107: aload 6
    //   109: ifnull +6 -> 115
    //   112: goto +219 -> 331
    //   115: goto +104 -> 219
    //   118: aload_1
    //   119: instanceof 310
    //   122: ifeq +6 -> 128
    //   125: goto +53 -> 178
    //   128: goto +56 -> 184
    //   131: aload_1
    //   132: instanceof 310
    //   135: istore 4
    //   137: bipush 73
    //   139: iconst_0
    //   140: idiv
    //   141: istore_3
    //   142: iload 4
    //   144: ifeq +6 -> 150
    //   147: goto -117 -> 30
    //   150: aload_1
    //   151: astore 5
    //   153: aconst_null
    //   154: astore 6
    //   156: aload_0
    //   157: getfield 167	o/צ:ˎ	Lo/צ$ˋ;
    //   160: invokevirtual 314	o/צ$ˋ:ˊ	()Z
    //   163: ifeq +6 -> 169
    //   166: goto -71 -> 95
    //   169: goto -98 -> 71
    //   172: bipush 70
    //   174: istore_3
    //   175: goto -133 -> 42
    //   178: bipush 94
    //   180: istore_3
    //   181: goto +46 -> 227
    //   184: bipush 23
    //   186: istore_3
    //   187: goto +40 -> 227
    //   190: iload_3
    //   191: lookupswitch	default:+25->216, 33:+127->318, 66:+148->339
    //   216: goto +102 -> 318
    //   219: aload_0
    //   220: invokespecial 315	o/צ:ˎ	()V
    //   223: return
    //   224: goto +41 -> 265
    //   227: iload_3
    //   228: lookupswitch	default:+28->256, 23:+-78->150, 94:+-198->30
    //   256: goto -226 -> 30
    //   259: goto -40 -> 219
    //   262: astore_1
    //   263: aload_1
    //   264: athrow
    //   265: getstatic 108	o/צ:ˏˎ	I
    //   268: bipush 35
    //   270: iadd
    //   271: istore_3
    //   272: iload_3
    //   273: sipush 128
    //   276: irem
    //   277: putstatic 106	o/צ:ˑ	I
    //   280: iload_3
    //   281: iconst_2
    //   282: irem
    //   283: ifeq +6 -> 289
    //   286: goto +89 -> 375
    //   289: goto -117 -> 172
    //   292: aload_0
    //   293: getfield 167	o/צ:ˎ	Lo/צ$ˋ;
    //   296: aload_0
    //   297: getfield 172	o/צ:ͺ	Lo/צ$iF;
    //   300: aload_0
    //   301: getfield 234	o/צ:ॱॱ	Lo/ʄ;
    //   304: invokevirtual 318	o/צ$ˋ:ˎ	(Lo/צ$iF;Lo/ʄ;)V
    //   307: goto -200 -> 107
    //   310: aload 6
    //   312: invokevirtual 321	o/ব:ॱ	()V
    //   315: goto +66 -> 381
    //   318: aload_1
    //   319: invokestatic 324	o/ব:ˋ	(Lo/ก;)Lo/ব;
    //   322: astore 6
    //   324: aload 6
    //   326: astore 5
    //   328: goto -325 -> 3
    //   331: aload 6
    //   333: invokevirtual 321	o/ব:ॱ	()V
    //   336: goto -77 -> 259
    //   339: aload_0
    //   340: aload 5
    //   342: aload_2
    //   343: invokespecial 326	o/צ:ˎ	(Lo/ก;Lo/ｬ;)V
    //   346: getstatic 328	o/צ$ˎ:ॱ	Lo/צ$ˎ;
    //   349: astore_1
    //   350: aload_0
    //   351: aload_1
    //   352: putfield 189	o/צ:ॱˋ	Lo/צ$ˎ;
    //   355: aload_0
    //   356: getfield 167	o/צ:ˎ	Lo/צ$ˋ;
    //   359: invokevirtual 314	o/צ$ˋ:ˊ	()Z
    //   362: istore 4
    //   364: iload 4
    //   366: ifeq +6 -> 372
    //   369: goto -77 -> 292
    //   372: goto -265 -> 107
    //   375: bipush 36
    //   377: istore_3
    //   378: goto -336 -> 42
    //   381: aload_0
    //   382: invokespecial 315	o/צ:ˎ	()V
    //   385: aload_1
    //   386: athrow
    // Local variable table:
    //   start	length	slot	name	signature
    //   0	387	0	this	צ
    //   0	387	1	paramก	ก<R>
    //   0	387	2	paramｬ	ｬ
    //   9	369	3	i	int
    //   135	230	4	bool	boolean
    //   151	190	5	localObject	Object
    //   81	251	6	localব	ব
    // Exception table:
    //   from	to	target	type
    //   292	307	80	finally
    //   355	364	80	finally
    //   350	355	104	java/lang/Exception
    //   346	350	262	java/lang/Exception
  }
  
  private void ˋॱ()
  {
    break label120;
    break label433;
    break label67;
    label9:
    int i = ˏˎ + 93;
    ˑ = i % 128;
    if (i % 2 == 0)
    {
      break label597;
      for (;;)
      {
        switch (i)
        {
        default: 
          label36:
          break label499;
          label67:
          this.ॱˋ = ˏ(this.ॱˋ);
          this.ˊˋ = ʻ();
          if (this.ॱˋ == ˎ.ˋ) {
            break label9;
          }
          break label433;
          label103:
          i = 79;
          break label543;
          label109:
          i = 16;
        }
      }
      label115:
      i = 1;
      break label336;
      label120:
      break label190;
      label123:
      i = 0;
    }
    for (;;)
    {
      label155:
      boolean bool1;
      label190:
      boolean bool2;
      try
      {
        i = ˑ + 107;
        ˏˎ = i % 128;
        if (i % 2 != 0)
        {
          continue;
          ˏ();
          break label518;
          bool1 = this.ˉ;
          i = null.length;
          if (bool1) {
            break label581;
          }
          return;
          i = 93;
          continue;
          i = 57;
          break label543;
          i = ˏˎ + 69;
          ˑ = i % 128;
          if (i % 2 != 0) {
            break label109;
          }
          break label591;
          bool2 = bool1;
        }
        switch (i)
        {
        default: 
          bool2 = bool1;
          continue;
          i = ˑ + 85;
          ˏˎ = i % 128;
          if (i % 2 == 0) {
            continue;
          }
          break label452;
          ˊॱ();
          return;
        case 95: 
          bool2 = this.ˊˋ.ˎ();
          bool1 = bool2;
          if (bool2)
          {
            bool2 = bool1;
          }
          else
          {
            i = ˏˎ + 103;
            ˑ = i % 128;
            if (i % 2 != 0) {
              break;
            }
            break;
            switch (i)
            {
            case 1: 
            default: 
              continue;
              ˏ();
              i = 24 / 0;
            }
          }
          break;
        case 93: 
          label336:
          if (this.ॱˋ != ˎ.ʼ) {
            continue;
          }
          break;
        }
      }
      catch (Exception localException1)
      {
        Thread localThread;
        throw localException1;
      }
      localThread = Thread.currentThread();
      this.ˈ = localThread;
      try
      {
        this.ʿ = ϝ.ˊ();
        bool1 = true;
      }
      catch (Exception localException2)
      {
        label414:
        label427:
        label433:
        label452:
        throw localException2;
      }
      if (this.ˊˋ == null)
      {
        continue;
        i = 6 / 0;
        return;
        if (!this.ˉ) {
          break label103;
        }
        continue;
        return;
        if (!this.ˉ) {
          return;
        }
        for (;;)
        {
          switch (i)
          {
          }
          break label155;
          label499:
          this.ˈ = Thread.currentThread();
          this.ʿ = ϝ.ˊ();
          bool1 = false;
          break;
          label518:
          i = ˏˎ + 17;
          ˑ = i % 128;
          if (i % 2 != 0) {
            break label427;
          }
          return;
          label543:
          bool2 = bool1;
          switch (i)
          {
          }
          break label414;
          i = 32;
          continue;
          label581:
          if (!bool2) {
            break label115;
          }
          break label123;
          label591:
          i = 43;
          break label36;
          label597:
          i = 19;
        }
      }
      i = 95;
    }
  }
  
  /* Error */
  private ʄ ˎ(ｬ paramｬ)
  {
    // Byte code:
    //   0: goto +34 -> 34
    //   3: goto +179 -> 182
    //   6: getstatic 106	o/צ:ˑ	I
    //   9: istore_2
    //   10: iload_2
    //   11: iconst_5
    //   12: iadd
    //   13: istore_2
    //   14: iload_2
    //   15: sipush 128
    //   18: irem
    //   19: putstatic 108	o/צ:ˏˎ	I
    //   22: iload_2
    //   23: iconst_2
    //   24: irem
    //   25: ifne +6 -> 31
    //   28: goto +82 -> 110
    //   31: goto +30 -> 61
    //   34: getstatic 108	o/צ:ˏˎ	I
    //   37: bipush 99
    //   39: iadd
    //   40: istore_2
    //   41: iload_2
    //   42: sipush 128
    //   45: irem
    //   46: putstatic 106	o/צ:ˑ	I
    //   49: iload_2
    //   50: iconst_2
    //   51: irem
    //   52: ifeq +6 -> 58
    //   55: goto -52 -> 3
    //   58: goto +124 -> 182
    //   61: aload_0
    //   62: getfield 152	o/צ:ˊ	Lo/ب;
    //   65: invokevirtual 359	o/ب:ͺ	()Z
    //   68: ifeq +6 -> 74
    //   71: goto +76 -> 147
    //   74: aload_3
    //   75: areturn
    //   76: iload_2
    //   77: tableswitch	default:+23->100, 0:+151->228, 1:+36->113
    //   100: goto +13 -> 113
    //   103: aload_3
    //   104: areturn
    //   105: iconst_2
    //   106: istore_2
    //   107: goto +139 -> 246
    //   110: goto -49 -> 61
    //   113: getstatic 108	o/צ:ˏˎ	I
    //   116: bipush 43
    //   118: iadd
    //   119: istore_2
    //   120: iload_2
    //   121: sipush 128
    //   124: irem
    //   125: putstatic 106	o/צ:ˑ	I
    //   128: iload_2
    //   129: iconst_2
    //   130: irem
    //   131: ifeq +6 -> 137
    //   134: goto +107 -> 241
    //   137: aload_3
    //   138: areturn
    //   139: goto +206 -> 345
    //   142: iconst_1
    //   143: istore_2
    //   144: goto -68 -> 76
    //   147: new 361	o/ʄ
    //   150: dup
    //   151: invokespecial 362	o/ʄ:<init>	()V
    //   154: astore_1
    //   155: aload_1
    //   156: aload_0
    //   157: getfield 234	o/צ:ॱॱ	Lo/ʄ;
    //   160: invokevirtual 365	o/ʄ:ˊ	(Lo/ʄ;)V
    //   163: aload_1
    //   164: getstatic 370	o/য:ˊ	Lo/ɜ;
    //   167: iconst_1
    //   168: invokestatic 376	java/lang/Boolean:valueOf	(Z)Ljava/lang/Boolean;
    //   171: invokevirtual 379	o/ʄ:ˏ	(Lo/ɜ;Ljava/lang/Object;)Lo/ʄ;
    //   174: pop
    //   175: aload_1
    //   176: areturn
    //   177: iconst_0
    //   178: istore_2
    //   179: goto -103 -> 76
    //   182: aload_0
    //   183: getfield 234	o/צ:ॱॱ	Lo/ʄ;
    //   186: astore_3
    //   187: getstatic 384	android/os/Build$VERSION:SDK_INT	I
    //   190: bipush 26
    //   192: if_icmpge +6 -> 198
    //   195: goto +6 -> 201
    //   198: goto +123 -> 321
    //   201: getstatic 108	o/צ:ˏˎ	I
    //   204: bipush 31
    //   206: iadd
    //   207: istore_2
    //   208: iload_2
    //   209: sipush 128
    //   212: irem
    //   213: putstatic 106	o/צ:ˑ	I
    //   216: iload_2
    //   217: iconst_2
    //   218: irem
    //   219: ifeq +6 -> 225
    //   222: goto -83 -> 139
    //   225: goto +120 -> 345
    //   228: aload_1
    //   229: getstatic 388	o/ｬ:ˎ	Lo/ｬ;
    //   232: if_acmpeq +6 -> 238
    //   235: goto -229 -> 6
    //   238: goto -91 -> 147
    //   241: aconst_null
    //   242: arraylength
    //   243: istore_2
    //   244: aload_3
    //   245: areturn
    //   246: iload_2
    //   247: lookupswitch	default:+25->272, 2:+-144->103, 60:+33->280
    //   272: aload_3
    //   273: areturn
    //   274: bipush 60
    //   276: istore_2
    //   277: goto -31 -> 246
    //   280: new 271	java/lang/NullPointerException
    //   283: dup
    //   284: invokespecial 272	java/lang/NullPointerException:<init>	()V
    //   287: athrow
    //   288: astore_1
    //   289: aload_1
    //   290: athrow
    //   291: getstatic 106	o/צ:ˑ	I
    //   294: bipush 81
    //   296: iadd
    //   297: istore_2
    //   298: iload_2
    //   299: sipush 128
    //   302: irem
    //   303: putstatic 108	o/צ:ˏˎ	I
    //   306: iload_2
    //   307: iconst_2
    //   308: irem
    //   309: ifne +6 -> 315
    //   312: goto -38 -> 274
    //   315: goto -210 -> 105
    //   318: astore_1
    //   319: aload_1
    //   320: athrow
    //   321: getstatic 370	o/য:ˊ	Lo/ɜ;
    //   324: astore 4
    //   326: aload_3
    //   327: aload 4
    //   329: invokevirtual 391	o/ʄ:ˎ	(Lo/ɜ;)Ljava/lang/Object;
    //   332: astore 4
    //   334: aload 4
    //   336: ifnull +6 -> 342
    //   339: goto -197 -> 142
    //   342: goto -165 -> 177
    //   345: goto -54 -> 291
    // Local variable table:
    //   start	length	slot	name	signature
    //   0	348	0	this	צ
    //   0	348	1	paramｬ	ｬ
    //   9	300	2	i	int
    //   74	253	3	localʄ	ʄ
    //   324	11	4	localObject	Object
    // Exception table:
    //   from	to	target	type
    //   6	10	288	java/lang/Exception
    //   14	22	288	java/lang/Exception
    //   321	326	318	java/lang/Exception
    //   326	334	318	java/lang/Exception
  }
  
  private <Data> ก<R> ˎ(ʢ<?> paramʢ, Data paramData, ｬ paramｬ)
  {
    for (;;)
    {
      try
      {
        i = ˏˎ + 101;
        try
        {
          ˑ = i % 128;
          if (i % 2 == 0)
          {
            continue;
            paramʢ.ˏ();
            i = null.length;
          }
          else
          {
            continue;
          }
          return null;
        }
        catch (Exception paramʢ)
        {
          throw paramʢ;
        }
        i = 89;
      }
      catch (Exception paramʢ)
      {
        throw paramʢ;
      }
      break label128;
      int i = 30;
      break label167;
      i = ˑ + 37;
      ˏˎ = i % 128;
      if (i % 2 != 0)
      {
        continue;
        i = 40;
        break label167;
      }
      i = 38;
      break label136;
      if (paramData == null) {
        continue;
      }
      continue;
      label128:
      paramʢ.ˏ();
      return paramData;
      switch (i)
      {
      case 38: 
      default: 
        break label199;
        switch (i)
        {
        }
        break;
      case 89: 
        label136:
        label167:
        label199:
        paramʢ.ˏ();
        continue;
        continue;
        try
        {
          long l = ϝ.ˊ();
          paramData = ˊ(paramData, paramｬ);
          boolean bool = Log.isLoggable("DecodeJob", 2);
          if (!bool) {
            break label128;
          }
          ˏ("Decoded result " + paramData, l);
        }
        finally
        {
          paramʢ.ˏ();
        }
      }
    }
  }
  
  /* Error */
  private void ˎ()
  {
    // Byte code:
    //   0: goto +66 -> 66
    //   3: iconst_1
    //   4: istore_1
    //   5: goto +28 -> 33
    //   8: getstatic 106	o/צ:ˑ	I
    //   11: bipush 49
    //   13: iadd
    //   14: istore_1
    //   15: iload_1
    //   16: sipush 128
    //   19: irem
    //   20: putstatic 108	o/צ:ˏˎ	I
    //   23: iload_1
    //   24: iconst_2
    //   25: irem
    //   26: ifne +6 -> 32
    //   29: goto +57 -> 86
    //   32: return
    //   33: iload_1
    //   34: tableswitch	default:+22->56, 0:+35->69, 1:+22->56
    //   56: aload_0
    //   57: invokespecial 414	o/צ:ʼ	()V
    //   60: goto -52 -> 8
    //   63: astore_2
    //   64: aload_2
    //   65: athrow
    //   66: goto +29 -> 95
    //   69: aload_0
    //   70: invokespecial 414	o/צ:ʼ	()V
    //   73: bipush 11
    //   75: iconst_0
    //   76: idiv
    //   77: istore_1
    //   78: goto -18 -> 60
    //   81: iconst_0
    //   82: istore_1
    //   83: goto -50 -> 33
    //   86: return
    //   87: iconst_0
    //   88: istore_1
    //   89: goto +56 -> 145
    //   92: astore_2
    //   93: aload_2
    //   94: athrow
    //   95: aload_0
    //   96: getfield 170	o/צ:ˋॱ	Lo/צ$ˊ;
    //   99: invokevirtual 416	o/צ$ˊ:ˋ	()Z
    //   102: ifeq +6 -> 108
    //   105: goto +6 -> 111
    //   108: goto -21 -> 87
    //   111: iconst_1
    //   112: istore_1
    //   113: goto +32 -> 145
    //   116: getstatic 108	o/צ:ˏˎ	I
    //   119: istore_1
    //   120: iload_1
    //   121: bipush 91
    //   123: iadd
    //   124: istore_1
    //   125: iload_1
    //   126: sipush 128
    //   129: irem
    //   130: putstatic 106	o/צ:ˑ	I
    //   133: iload_1
    //   134: iconst_2
    //   135: irem
    //   136: ifeq +6 -> 142
    //   139: goto -58 -> 81
    //   142: goto -139 -> 3
    //   145: iload_1
    //   146: tableswitch	default:+22->168, 0:+-86->60, 1:+-30->116
    //   168: goto -108 -> 60
    // Local variable table:
    //   start	length	slot	name	signature
    //   0	171	0	this	צ
    //   4	142	1	i	int
    //   63	2	2	localException1	Exception
    //   92	2	2	localException2	Exception
    // Exception table:
    //   from	to	target	type
    //   125	133	63	java/lang/Exception
    //   116	120	92	java/lang/Exception
  }
  
  /* Error */
  private void ˎ(String paramString1, long paramLong, String paramString2)
  {
    // Byte code:
    //   0: goto +135 -> 135
    //   3: new 200	java/lang/StringBuilder
    //   6: dup
    //   7: invokespecial 201	java/lang/StringBuilder:<init>	()V
    //   10: aload_1
    //   11: invokevirtual 207	java/lang/StringBuilder:append	(Ljava/lang/String;)Ljava/lang/StringBuilder;
    //   14: ldc_w 419
    //   17: invokevirtual 207	java/lang/StringBuilder:append	(Ljava/lang/String;)Ljava/lang/StringBuilder;
    //   20: lload_2
    //   21: invokestatic 422	o/ϝ:ˏ	(J)D
    //   24: invokevirtual 425	java/lang/StringBuilder:append	(D)Ljava/lang/StringBuilder;
    //   27: bipush -31
    //   29: ldc_w 426
    //   32: ldc_w 427
    //   35: bipush 117
    //   37: iconst_0
    //   38: invokestatic 429	o/צ:ˊ	(IIIBS)Ljava/lang/String;
    //   41: invokevirtual 434	java/lang/String:intern	()Ljava/lang/String;
    //   44: invokevirtual 207	java/lang/StringBuilder:append	(Ljava/lang/String;)Ljava/lang/StringBuilder;
    //   47: aload_0
    //   48: getfield 238	o/צ:ʻॱ	Lo/ڒ;
    //   51: invokevirtual 210	java/lang/StringBuilder:append	(Ljava/lang/Object;)Ljava/lang/StringBuilder;
    //   54: astore 6
    //   56: aload 4
    //   58: ifnull +6 -> 64
    //   61: goto +6 -> 67
    //   64: goto +31 -> 95
    //   67: new 200	java/lang/StringBuilder
    //   70: dup
    //   71: invokespecial 201	java/lang/StringBuilder:<init>	()V
    //   74: ldc_w 436
    //   77: invokevirtual 207	java/lang/StringBuilder:append	(Ljava/lang/String;)Ljava/lang/StringBuilder;
    //   80: aload 4
    //   82: invokevirtual 207	java/lang/StringBuilder:append	(Ljava/lang/String;)Ljava/lang/StringBuilder;
    //   85: invokevirtual 214	java/lang/StringBuilder:toString	()Ljava/lang/String;
    //   88: astore_1
    //   89: goto +161 -> 250
    //   92: goto +108 -> 200
    //   95: ldc_w 438
    //   98: astore_1
    //   99: goto +68 -> 167
    //   102: iconst_1
    //   103: istore 5
    //   105: goto +33 -> 138
    //   108: iload 5
    //   110: tableswitch	default:+22->132, 0:+176->286, 1:+-18->92
    //   132: goto -40 -> 92
    //   135: goto -132 -> 3
    //   138: iload 5
    //   140: tableswitch	default:+24->164, 0:+104->244, 1:+60->200
    //   164: goto +80 -> 244
    //   167: getstatic 108	o/צ:ˏˎ	I
    //   170: bipush 65
    //   172: iadd
    //   173: istore 5
    //   175: iload 5
    //   177: sipush 128
    //   180: irem
    //   181: putstatic 106	o/צ:ˑ	I
    //   184: iload 5
    //   186: iconst_2
    //   187: irem
    //   188: ifeq +6 -> 194
    //   191: goto +89 -> 280
    //   194: goto -92 -> 102
    //   197: astore_1
    //   198: aload_1
    //   199: athrow
    //   200: aload 6
    //   202: aload_1
    //   203: invokevirtual 207	java/lang/StringBuilder:append	(Ljava/lang/String;)Ljava/lang/StringBuilder;
    //   206: astore_1
    //   207: aload_1
    //   208: ldc_w 440
    //   211: invokevirtual 207	java/lang/StringBuilder:append	(Ljava/lang/String;)Ljava/lang/StringBuilder;
    //   214: astore_1
    //   215: invokestatic 351	java/lang/Thread:currentThread	()Ljava/lang/Thread;
    //   218: astore 4
    //   220: aload 4
    //   222: invokevirtual 443	java/lang/Thread:getName	()Ljava/lang/String;
    //   225: astore 4
    //   227: ldc_w 399
    //   230: aload_1
    //   231: aload 4
    //   233: invokevirtual 207	java/lang/StringBuilder:append	(Ljava/lang/String;)Ljava/lang/StringBuilder;
    //   236: invokevirtual 214	java/lang/StringBuilder:toString	()Ljava/lang/String;
    //   239: invokestatic 447	android/util/Log:v	(Ljava/lang/String;Ljava/lang/String;)I
    //   242: pop
    //   243: return
    //   244: goto -44 -> 200
    //   247: astore_1
    //   248: aload_1
    //   249: athrow
    //   250: getstatic 108	o/צ:ˏˎ	I
    //   253: bipush 55
    //   255: iadd
    //   256: istore 5
    //   258: iload 5
    //   260: sipush 128
    //   263: irem
    //   264: putstatic 106	o/צ:ˑ	I
    //   267: iload 5
    //   269: iconst_2
    //   270: irem
    //   271: ifeq +6 -> 277
    //   274: goto +15 -> 289
    //   277: goto +18 -> 295
    //   280: iconst_0
    //   281: istore 5
    //   283: goto -145 -> 138
    //   286: goto -86 -> 200
    //   289: iconst_0
    //   290: istore 5
    //   292: goto -184 -> 108
    //   295: iconst_1
    //   296: istore 5
    //   298: goto -190 -> 108
    // Local variable table:
    //   start	length	slot	name	signature
    //   0	301	0	this	צ
    //   0	301	1	paramString1	String
    //   0	301	2	paramLong	long
    //   0	301	4	paramString2	String
    //   103	194	5	i	int
    //   54	147	6	localStringBuilder	StringBuilder
    // Exception table:
    //   from	to	target	type
    //   200	207	197	java/lang/Exception
    //   207	215	197	java/lang/Exception
    //   215	220	197	java/lang/Exception
    //   220	227	197	java/lang/Exception
    //   227	243	197	java/lang/Exception
    //   207	215	247	java/lang/Exception
  }
  
  /* Error */
  private void ˎ(ก<R> paramก, ｬ paramｬ)
  {
    // Byte code:
    //   0: goto +6 -> 6
    //   3: astore_1
    //   4: aload_1
    //   5: athrow
    //   6: goto +30 -> 36
    //   9: aload_0
    //   10: invokespecial 292	o/צ:ͺ	()V
    //   13: aload_0
    //   14: getfield 240	o/צ:ᐝॱ	Lo/צ$If;
    //   17: aload_1
    //   18: aload_2
    //   19: invokeinterface 448 3 0
    //   24: aconst_null
    //   25: arraylength
    //   26: istore_3
    //   27: goto +39 -> 66
    //   30: bipush 11
    //   32: istore_3
    //   33: goto +79 -> 112
    //   36: getstatic 108	o/צ:ˏˎ	I
    //   39: bipush 107
    //   41: iadd
    //   42: istore_3
    //   43: iload_3
    //   44: sipush 128
    //   47: irem
    //   48: putstatic 106	o/צ:ˑ	I
    //   51: iload_3
    //   52: iconst_2
    //   53: irem
    //   54: ifeq +6 -> 60
    //   57: goto +86 -> 143
    //   60: goto -30 -> 30
    //   63: astore_1
    //   64: aload_1
    //   65: athrow
    //   66: getstatic 106	o/צ:ˑ	I
    //   69: istore_3
    //   70: iload_3
    //   71: bipush 51
    //   73: iadd
    //   74: istore_3
    //   75: iload_3
    //   76: sipush 128
    //   79: irem
    //   80: putstatic 108	o/צ:ˏˎ	I
    //   83: iload_3
    //   84: iconst_2
    //   85: irem
    //   86: ifne +6 -> 92
    //   89: goto +4 -> 93
    //   92: return
    //   93: return
    //   94: aload_0
    //   95: invokespecial 292	o/צ:ͺ	()V
    //   98: aload_0
    //   99: getfield 240	o/צ:ᐝॱ	Lo/צ$If;
    //   102: aload_1
    //   103: aload_2
    //   104: invokeinterface 448 3 0
    //   109: goto -43 -> 66
    //   112: iload_3
    //   113: lookupswitch	default:+27->140, 11:+-19->94, 87:+-104->9
    //   140: goto -46 -> 94
    //   143: bipush 87
    //   145: istore_3
    //   146: goto -34 -> 112
    // Local variable table:
    //   start	length	slot	name	signature
    //   0	149	0	this	צ
    //   0	149	1	paramก	ก<R>
    //   0	149	2	paramｬ	ｬ
    //   26	120	3	i	int
    // Exception table:
    //   from	to	target	type
    //   36	43	3	java/lang/Exception
    //   43	51	3	java/lang/Exception
    //   43	51	63	java/lang/Exception
    //   66	70	63	java/lang/Exception
    //   75	83	63	java/lang/Exception
  }
  
  private ˎ ˏ(ˎ paramˎ)
  {
    break label117;
    label3:
    return ˏ(ˎ.ˎ);
    paramˎ = ˎ.ʼ;
    break label23;
    label18:
    int i = 0;
    for (;;)
    {
      try
      {
        label23:
        i = ˏˎ;
        i += 17;
        try
        {
          ˑ = i % 128;
          if (i % 2 == 0)
          {
            return paramˎ;
            throw new IllegalArgumentException("Unrecognized stage: " + paramˎ);
          }
          switch (i)
          {
          case 83: 
          default: 
            break label3;
            i = 10;
            continue;
            return ˎ.ˏ;
            label117:
            break label315;
            if (this.ʽ.ˏ()) {
              continue;
            }
            break label275;
            return paramˎ;
          }
        }
        catch (Exception paramˎ)
        {
          throw paramˎ;
        }
        switch (i)
        {
        default: 
          continue;
          i = 0;
          continue;
          if (this.ʽॱ) {
            continue;
          }
          break;
        case 0: 
          i = ˏˎ + 63;
          ˑ = i % 128;
          if (i % 2 != 0) {
            continue;
          }
          return ˎ.ʼ;
          return ˏ(ˎ.ˏ);
          i = 9;
          break label285;
          i = 32;
          continue;
          i = ˏˎ + 15;
        }
      }
      catch (Exception paramˎ)
      {
        throw paramˎ;
      }
      ˑ = i % 128;
      if (i % 2 == 0) {
        break label363;
      }
      break label363;
      label275:
      i = 83;
      continue;
      return ˎ.ˋ;
      label285:
      switch (i)
      {
      }
      continue;
      label315:
      int[] arrayOfInt = 4.ˋ;
      i = arrayOfInt[paramˎ.ordinal()];
      switch (i)
      {
      case 3: 
      case 4: 
      case 5: 
      case 2: 
      default: 
        continue;
        return ˎ.ˎ;
      case 1: 
        label363:
        if (this.ʽ.ॱ()) {
          break label18;
        }
      }
    }
  }
  
  private void ˏ(String paramString, long paramLong)
  {
    break label12;
    break label115;
    label6:
    int i = 0;
    break label87;
    label12:
    break label54;
    label15:
    throw new NullPointerException();
    return;
    for (;;)
    {
      i = ˏˎ + 47;
      ˑ = i % 128;
      if (i % 2 == 0)
      {
        break label6;
        label54:
        i = ˑ + 73;
        ˏˎ = i % 128;
        if (i % 2 == 0) {
          break;
        }
        break;
      }
      i = 1;
      label87:
      switch (i)
      {
      }
      break label15;
      label115:
      ˎ(paramString, paramLong, null);
    }
  }
  
  /* Error */
  private void ͺ()
  {
    // Byte code:
    //   0: goto +75 -> 75
    //   3: getstatic 108	o/צ:ˏˎ	I
    //   6: bipush 93
    //   8: iadd
    //   9: istore_1
    //   10: iload_1
    //   11: sipush 128
    //   14: irem
    //   15: putstatic 106	o/צ:ˑ	I
    //   18: iload_1
    //   19: iconst_2
    //   20: irem
    //   21: ifeq +6 -> 27
    //   24: goto +115 -> 139
    //   27: goto +42 -> 69
    //   30: getstatic 108	o/צ:ˏˎ	I
    //   33: bipush 15
    //   35: iadd
    //   36: istore_1
    //   37: iload_1
    //   38: sipush 128
    //   41: irem
    //   42: putstatic 106	o/צ:ˑ	I
    //   45: iload_1
    //   46: iconst_2
    //   47: irem
    //   48: ifeq +6 -> 54
    //   51: goto +27 -> 78
    //   54: return
    //   55: new 198	java/lang/IllegalStateException
    //   58: dup
    //   59: ldc_w 469
    //   62: invokespecial 217	java/lang/IllegalStateException:<init>	(Ljava/lang/String;)V
    //   65: athrow
    //   66: astore_3
    //   67: aload_3
    //   68: athrow
    //   69: bipush 49
    //   71: istore_1
    //   72: goto +10 -> 82
    //   75: goto -72 -> 3
    //   78: return
    //   79: astore_3
    //   80: aload_3
    //   81: athrow
    //   82: iload_1
    //   83: lookupswitch	default:+25->108, 49:+36->119, 89:+62->145
    //   108: goto +11 -> 119
    //   111: aload_0
    //   112: iconst_1
    //   113: putfield 228	o/צ:ˊᐝ	Z
    //   116: goto -86 -> 30
    //   119: aload_0
    //   120: getfield 164	o/צ:ʻ	Lo/С;
    //   123: invokevirtual 471	o/С:ˋ	()V
    //   126: aload_0
    //   127: getfield 228	o/צ:ˊᐝ	Z
    //   130: ifeq +6 -> 136
    //   133: goto -78 -> 55
    //   136: goto -25 -> 111
    //   139: bipush 89
    //   141: istore_1
    //   142: goto -60 -> 82
    //   145: aload_0
    //   146: getfield 164	o/צ:ʻ	Lo/С;
    //   149: invokevirtual 471	o/С:ˋ	()V
    //   152: aload_0
    //   153: getfield 228	o/צ:ˊᐝ	Z
    //   156: istore_2
    //   157: bipush 21
    //   159: iconst_0
    //   160: idiv
    //   161: istore_1
    //   162: iload_2
    //   163: ifeq +6 -> 169
    //   166: goto -111 -> 55
    //   169: goto -58 -> 111
    // Local variable table:
    //   start	length	slot	name	signature
    //   0	172	0	this	צ
    //   9	153	1	i	int
    //   156	7	2	bool	boolean
    //   66	2	3	localException1	Exception
    //   79	2	3	localException2	Exception
    // Exception table:
    //   from	to	target	type
    //   55	66	66	java/lang/Exception
    //   111	116	79	java/lang/Exception
  }
  
  private <Data, ResourceType> ก<R> ॱ(Data paramData, ｬ paramｬ, শ<Data, ResourceType, R> paramশ)
  {
    break label92;
    for (;;)
    {
      i = 1;
      break label120;
      i = ˏˎ + 85;
      ˑ = i % 128;
      if (i % 2 != 0) {
        break;
      }
    }
    for (;;)
    {
      ʄ localʄ = ˎ(paramｬ);
      paramData = this.ˊॱ.ˎ().ˎ(paramData);
      try
      {
        paramｬ = paramশ.ˋ(paramData, localʄ, this.ˋ, this.ॱ, new if(paramｬ));
        paramData.ॱ();
        break;
      }
      finally
      {
        label92:
        paramData.ॱ();
      }
    }
    int i = 0;
    break label120;
    throw new NullPointerException();
    return paramｬ;
    label120:
    switch (i)
    {
    }
    return paramｬ;
  }
  
  private void ॱˊ()
  {
    for (;;)
    {
      i = ˏˎ + 45;
      ˑ = i % 128;
      if (i % 2 != 0) {
        break;
      }
      break;
      ˎ("Retrieved data", this.ʿ, "data: " + this.ʼॱ + ˊ(-31, 769232495, -1337841715, (byte)-14, (short)0).intern() + this.ᐝ + ", fetcher: " + this.ˋˊ);
      break label167;
    }
    int i = 0;
    switch (i)
    {
    default: 
      label115:
      break;
      Object localObject;
      for (;;)
      {
        ˋ((ก)localObject, this.ˊˊ);
        i = 36 / 0;
        break label295;
        break label224;
        label167:
        localObject = null;
        for (;;)
        {
          try
          {
            ก localก = ˎ(this.ˋˊ, this.ʼॱ, this.ˊˊ);
            localObject = localก;
          }
          catch (ঌ localঌ)
          {
            localঌ.ˎ(this.ʾ, this.ˊˊ);
            this.ʼ.add(localঌ);
          }
          i = 18;
          break label115;
          label224:
          if (Log.isLoggable("DecodeJob", 2)) {
            break;
          }
          break label167;
          if (localObject != null) {
            break label250;
          }
        }
        label250:
        i = 99;
        break label115;
        label256:
        switch (i)
        {
        }
      }
      ˋ((ก)localObject, this.ˊˊ);
      label295:
      return;
    }
    for (;;)
    {
      i = 1;
      break label256;
      ˋॱ();
      return;
      i = ˑ + 13;
      ˏˎ = i % 128;
      if (i % 2 == 0) {
        break;
      }
    }
  }
  
  private void ॱॱ()
  {
    break label49;
    int i = 0;
    break label26;
    label8:
    break label52;
    label11:
    i = 1;
    break label26;
    ʼ();
    break label69;
    break label68;
    switch (i)
    {
    case 0: 
    default: 
      label26:
      return;
      label49:
      break;
    }
    label52:
    while (!this.ˋॱ.ˏ())
    {
      break label11;
      for (;;)
      {
        label68:
        return;
        label69:
        i = ˑ + 119;
        ˏˎ = i % 128;
        if (i % 2 == 0) {
          break;
        }
      }
      i = ˑ + 75;
      ˏˎ = i % 128;
      if (i % 2 == 0) {
        break label8;
      }
    }
  }
  
  private void ᐝ()
  {
    break label110;
    int i;
    for (;;)
    {
      i = ˏˎ + 7;
      ˑ = i % 128;
      if (i % 2 != 0) {
        break;
      }
      break;
      i = 1;
      break label143;
      ˋॱ();
      return;
      ॱˊ();
    }
    for (;;)
    {
      throw new IllegalStateException("Unrecognized run reason: " + this.ॱᐝ);
      this.ॱˋ = ˏ(ˎ.ˊ);
      this.ˊˋ = ʻ();
      ˋॱ();
      return;
      i = 0;
      break label143;
      try
      {
        label110:
        i = ˑ + 49;
      }
      catch (Exception localException1)
      {
        try
        {
          ˏˎ = i % 128;
          if (i % 2 == 0) {
            break;
          }
        }
        catch (Exception localException2)
        {
          throw localException2;
        }
        localException1 = localException1;
        throw localException1;
      }
      switch (i)
      {
      default: 
        break label172;
        return;
      case 1: 
        i = 4.ॱ[this.ॱᐝ.ordinal()];
        int j = null.length;
        switch (i)
        {
        }
        break;
      case 0: 
        label143:
        label172:
        switch (4.ॱ[this.ॱᐝ.ordinal()])
        {
        }
        break;
      }
    }
  }
  
  public С e_()
  {
    break label164;
    int i;
    switch (i)
    {
    default: 
      break;
    }
    label67:
    label73:
    label76:
    label133:
    label164:
    for (;;)
    {
      i = ˏˎ + 39;
      ˑ = i % 128;
      if (i % 2 == 0)
      {
        break label133;
        return localС;
        for (;;)
        {
          i = 85 / 0;
          return localС;
          i = 25;
          break label76;
          i = 81;
          switch (i)
          {
          }
        }
        for (;;)
        {
          i = ˑ + 1;
          ˏˎ = i % 128;
          if (i % 2 == 0) {
            break label73;
          }
          break label67;
          i = 0;
          break;
          localС = this.ʻ;
        }
      }
      i = 1;
      break;
      С localС = this.ʻ;
      throw new NullPointerException();
    }
  }
  
  /* Error */
  public void run()
  {
    // Byte code:
    //   0: goto +6 -> 6
    //   3: astore_3
    //   4: aload_3
    //   5: athrow
    //   6: goto +132 -> 138
    //   9: aload_0
    //   10: getfield 157	o/צ:ʼ	Ljava/util/List;
    //   13: aload 4
    //   15: invokeinterface 518 2 0
    //   20: pop
    //   21: aload_0
    //   22: invokespecial 339	o/צ:ˊॱ	()V
    //   25: goto +222 -> 247
    //   28: aload_3
    //   29: invokeinterface 395 1 0
    //   34: aconst_null
    //   35: arraylength
    //   36: istore_1
    //   37: goto +351 -> 388
    //   40: iload_1
    //   41: tableswitch	default:+23->64, 0:+218->259, 1:+167->208
    //   64: goto +144 -> 208
    //   67: aload_0
    //   68: getfield 256	o/צ:ˉ	Z
    //   71: istore_2
    //   72: iload_2
    //   73: ifne +6 -> 79
    //   76: goto +89 -> 165
    //   79: goto +273 -> 352
    //   82: goto +171 -> 253
    //   85: getstatic 106	o/צ:ˑ	I
    //   88: bipush 71
    //   90: iadd
    //   91: istore_1
    //   92: iload_1
    //   93: sipush 128
    //   96: irem
    //   97: putstatic 108	o/צ:ˏˎ	I
    //   100: iload_1
    //   101: iconst_2
    //   102: irem
    //   103: ifne +6 -> 109
    //   106: goto +144 -> 250
    //   109: goto -100 -> 9
    //   112: ldc_w 543
    //   115: invokestatic 547	o/ๅ:ˏ	(Ljava/lang/String;)V
    //   118: aload_0
    //   119: getfield 252	o/צ:ˋˊ	Lo/ʢ;
    //   122: astore_3
    //   123: aload_0
    //   124: getfield 256	o/צ:ˉ	Z
    //   127: istore_2
    //   128: iload_2
    //   129: ifeq +6 -> 135
    //   132: goto +229 -> 361
    //   135: goto +131 -> 266
    //   138: getstatic 108	o/צ:ˏˎ	I
    //   141: bipush 93
    //   143: iadd
    //   144: istore_1
    //   145: iload_1
    //   146: sipush 128
    //   149: irem
    //   150: putstatic 106	o/צ:ˑ	I
    //   153: iload_1
    //   154: iconst_2
    //   155: irem
    //   156: ifeq +6 -> 162
    //   159: goto +104 -> 263
    //   162: goto -50 -> 112
    //   165: bipush 91
    //   167: istore_1
    //   168: goto +144 -> 312
    //   171: astore 4
    //   173: ldc_w 399
    //   176: iconst_3
    //   177: invokestatic 405	android/util/Log:isLoggable	(Ljava/lang/String;I)Z
    //   180: istore_2
    //   181: iload_2
    //   182: ifeq +6 -> 188
    //   185: goto +244 -> 429
    //   188: goto +393 -> 581
    //   191: iconst_1
    //   192: istore_1
    //   193: goto -153 -> 40
    //   196: astore 4
    //   198: aload_3
    //   199: ifnull +6 -> 205
    //   202: goto +275 -> 477
    //   205: goto +48 -> 253
    //   208: aload_3
    //   209: invokeinterface 395 1 0
    //   214: goto +45 -> 259
    //   217: iconst_0
    //   218: istore_1
    //   219: goto +320 -> 539
    //   222: iconst_1
    //   223: istore_1
    //   224: goto +315 -> 539
    //   227: astore_3
    //   228: aload_3
    //   229: athrow
    //   230: invokestatic 548	o/ๅ:ॱ	()V
    //   233: return
    //   234: aload 4
    //   236: athrow
    //   237: aload_3
    //   238: ifnull +6 -> 244
    //   241: goto +44 -> 285
    //   244: goto +144 -> 388
    //   247: goto -180 -> 67
    //   250: goto -241 -> 9
    //   253: invokestatic 548	o/ๅ:ॱ	()V
    //   256: aload 4
    //   258: athrow
    //   259: invokestatic 548	o/ๅ:ॱ	()V
    //   262: return
    //   263: goto -151 -> 112
    //   266: aload_0
    //   267: invokespecial 550	o/צ:ᐝ	()V
    //   270: aload_3
    //   271: ifnull +6 -> 277
    //   274: goto -83 -> 191
    //   277: goto +120 -> 397
    //   280: iconst_1
    //   281: istore_1
    //   282: goto +230 -> 512
    //   285: getstatic 106	o/צ:ˑ	I
    //   288: bipush 109
    //   290: iadd
    //   291: istore_1
    //   292: iload_1
    //   293: sipush 128
    //   296: irem
    //   297: putstatic 108	o/צ:ˏˎ	I
    //   300: iload_1
    //   301: iconst_2
    //   302: irem
    //   303: ifne +6 -> 309
    //   306: goto -26 -> 280
    //   309: goto +83 -> 392
    //   312: iload_1
    //   313: lookupswitch	default:+27->340, 70:+-76->237, 91:+-79->234
    //   340: goto -106 -> 234
    //   343: aload_3
    //   344: invokeinterface 395 1 0
    //   349: goto -119 -> 230
    //   352: bipush 70
    //   354: istore_1
    //   355: goto -43 -> 312
    //   358: goto -105 -> 253
    //   361: getstatic 106	o/צ:ˑ	I
    //   364: bipush 121
    //   366: iadd
    //   367: istore_1
    //   368: iload_1
    //   369: sipush 128
    //   372: irem
    //   373: putstatic 108	o/צ:ˏˎ	I
    //   376: iload_1
    //   377: iconst_2
    //   378: irem
    //   379: ifne +6 -> 385
    //   382: goto +113 -> 495
    //   385: goto +182 -> 567
    //   388: invokestatic 548	o/ๅ:ॱ	()V
    //   391: return
    //   392: iconst_0
    //   393: istore_1
    //   394: goto +118 -> 512
    //   397: iconst_0
    //   398: istore_1
    //   399: goto -359 -> 40
    //   402: getstatic 108	o/צ:ˏˎ	I
    //   405: bipush 101
    //   407: iadd
    //   408: istore_1
    //   409: iload_1
    //   410: sipush 128
    //   413: irem
    //   414: putstatic 106	o/צ:ˑ	I
    //   417: iload_1
    //   418: iconst_2
    //   419: irem
    //   420: ifeq +6 -> 426
    //   423: goto -65 -> 358
    //   426: goto -344 -> 82
    //   429: ldc_w 399
    //   432: new 200	java/lang/StringBuilder
    //   435: dup
    //   436: invokespecial 201	java/lang/StringBuilder:<init>	()V
    //   439: ldc_w 552
    //   442: invokevirtual 207	java/lang/StringBuilder:append	(Ljava/lang/String;)Ljava/lang/StringBuilder;
    //   445: aload_0
    //   446: getfield 256	o/צ:ˉ	Z
    //   449: invokevirtual 555	java/lang/StringBuilder:append	(Z)Ljava/lang/StringBuilder;
    //   452: ldc_w 557
    //   455: invokevirtual 207	java/lang/StringBuilder:append	(Ljava/lang/String;)Ljava/lang/StringBuilder;
    //   458: aload_0
    //   459: getfield 189	o/צ:ॱˋ	Lo/צ$ˎ;
    //   462: invokevirtual 210	java/lang/StringBuilder:append	(Ljava/lang/Object;)Ljava/lang/StringBuilder;
    //   465: invokevirtual 214	java/lang/StringBuilder:toString	()Ljava/lang/String;
    //   468: aload 4
    //   470: invokestatic 561	android/util/Log:d	(Ljava/lang/String;Ljava/lang/String;Ljava/lang/Throwable;)I
    //   473: pop
    //   474: goto +107 -> 581
    //   477: aload_3
    //   478: invokeinterface 395 1 0
    //   483: goto -81 -> 402
    //   486: aload_3
    //   487: invokeinterface 395 1 0
    //   492: goto -104 -> 388
    //   495: aload_0
    //   496: invokespecial 339	o/צ:ˊॱ	()V
    //   499: aconst_null
    //   500: arraylength
    //   501: istore_1
    //   502: aload_3
    //   503: ifnull +6 -> 509
    //   506: goto -163 -> 343
    //   509: goto -279 -> 230
    //   512: iload_1
    //   513: tableswitch	default:+23->536, 0:+-27->486, 1:+-485->28
    //   536: goto -508 -> 28
    //   539: iload_1
    //   540: tableswitch	default:+24->564, 0:+-455->85, 1:+-473->67
    //   564: goto -479 -> 85
    //   567: aload_0
    //   568: invokespecial 339	o/צ:ˊॱ	()V
    //   571: aload_3
    //   572: ifnull +6 -> 578
    //   575: goto -232 -> 343
    //   578: goto -348 -> 230
    //   581: aload_0
    //   582: getfield 189	o/צ:ॱˋ	Lo/צ$ˎ;
    //   585: astore 5
    //   587: getstatic 328	o/צ$ˎ:ॱ	Lo/צ$ˎ;
    //   590: astore 6
    //   592: aload 5
    //   594: aload 6
    //   596: if_acmpeq +6 -> 602
    //   599: goto -382 -> 217
    //   602: goto -380 -> 222
    // Local variable table:
    //   start	length	slot	name	signature
    //   0	605	0	this	צ
    //   36	504	1	i	int
    //   71	111	2	bool	boolean
    //   3	26	3	localException1	Exception
    //   122	87	3	localʢ	ʢ
    //   227	345	3	localException2	Exception
    //   13	1	4	localObject	Object
    //   171	1	4	localThrowable1	Throwable
    //   196	273	4	localThrowable2	Throwable
    //   585	8	5	localˎ1	ˎ
    //   590	5	6	localˎ2	ˎ
    // Exception table:
    //   from	to	target	type
    //   388	391	3	java/lang/Exception
    //   123	128	171	java/lang/Throwable
    //   266	270	171	java/lang/Throwable
    //   495	499	171	java/lang/Throwable
    //   567	571	171	java/lang/Throwable
    //   9	25	196	finally
    //   67	72	196	finally
    //   123	128	196	finally
    //   173	181	196	finally
    //   234	237	196	finally
    //   266	270	196	finally
    //   429	474	196	finally
    //   495	499	196	finally
    //   567	571	196	finally
    //   581	592	196	finally
    //   208	214	227	java/lang/Exception
    //   343	349	227	java/lang/Exception
    //   486	492	227	java/lang/Exception
  }
  
  /* Error */
  public void ˊ(ﾚ paramﾚ1, Object paramObject, ʢ<?> paramʢ, ｬ paramｬ, ﾚ paramﾚ2)
  {
    // Byte code:
    //   0: goto +239 -> 239
    //   3: bipush 71
    //   5: istore 6
    //   7: goto +40 -> 47
    //   10: bipush 80
    //   12: istore 6
    //   14: goto +33 -> 47
    //   17: iload 6
    //   19: lookupswitch	default:+25->44, 71:+223->242, 85:+67->86
    //   44: goto +42 -> 86
    //   47: iload 6
    //   49: lookupswitch	default:+27->76, 71:+84->133, 80:+130->179
    //   76: goto +103 -> 179
    //   79: bipush 71
    //   81: istore 6
    //   83: goto -66 -> 17
    //   86: aload_0
    //   87: aload_1
    //   88: putfield 246	o/צ:ᐝ	Lo/ﾚ;
    //   91: aload_0
    //   92: aload_2
    //   93: putfield 248	o/צ:ʼॱ	Ljava/lang/Object;
    //   96: aload_0
    //   97: aload_3
    //   98: putfield 252	o/צ:ˋˊ	Lo/ʢ;
    //   101: aload_0
    //   102: aload 4
    //   104: putfield 250	o/צ:ˊˊ	Lo/ｬ;
    //   107: aload_0
    //   108: aload 5
    //   110: putfield 512	o/צ:ʾ	Lo/ﾚ;
    //   113: invokestatic 351	java/lang/Thread:currentThread	()Ljava/lang/Thread;
    //   116: pop
    //   117: aload_0
    //   118: getfield 244	o/צ:ˈ	Ljava/lang/Thread;
    //   121: astore_1
    //   122: new 271	java/lang/NullPointerException
    //   125: dup
    //   126: invokespecial 272	java/lang/NullPointerException:<init>	()V
    //   129: athrow
    //   130: astore_1
    //   131: aload_1
    //   132: athrow
    //   133: aload_0
    //   134: getstatic 564	o/צ$aux:ˎ	Lo/צ$aux;
    //   137: putfield 527	o/צ:ॱᐝ	Lo/צ$aux;
    //   140: aload_0
    //   141: getfield 240	o/צ:ᐝॱ	Lo/צ$If;
    //   144: aload_0
    //   145: invokeinterface 567 2 0
    //   150: return
    //   151: getstatic 106	o/צ:ˑ	I
    //   154: bipush 65
    //   156: iadd
    //   157: istore 6
    //   159: iload 6
    //   161: sipush 128
    //   164: irem
    //   165: putstatic 108	o/צ:ˏˎ	I
    //   168: iload 6
    //   170: iconst_2
    //   171: irem
    //   172: ifne +6 -> 178
    //   175: goto +26 -> 201
    //   178: return
    //   179: ldc_w 569
    //   182: invokestatic 547	o/ๅ:ˏ	(Ljava/lang/String;)V
    //   185: aload_0
    //   186: invokespecial 523	o/צ:ॱˊ	()V
    //   189: invokestatic 548	o/ๅ:ॱ	()V
    //   192: goto -41 -> 151
    //   195: astore_1
    //   196: invokestatic 548	o/ๅ:ॱ	()V
    //   199: aload_1
    //   200: athrow
    //   201: iconst_4
    //   202: iconst_4
    //   203: idiv
    //   204: istore 6
    //   206: return
    //   207: astore_1
    //   208: aload_1
    //   209: athrow
    //   210: getstatic 108	o/צ:ˏˎ	I
    //   213: iconst_3
    //   214: iadd
    //   215: istore 6
    //   217: iload 6
    //   219: sipush 128
    //   222: irem
    //   223: putstatic 106	o/צ:ˑ	I
    //   226: iload 6
    //   228: iconst_2
    //   229: irem
    //   230: ifeq +6 -> 236
    //   233: goto +56 -> 289
    //   236: goto -157 -> 79
    //   239: goto -29 -> 210
    //   242: aload_0
    //   243: aload_1
    //   244: putfield 246	o/צ:ᐝ	Lo/ﾚ;
    //   247: aload_0
    //   248: aload_2
    //   249: putfield 248	o/צ:ʼॱ	Ljava/lang/Object;
    //   252: aload_0
    //   253: aload_3
    //   254: putfield 252	o/צ:ˋˊ	Lo/ʢ;
    //   257: aload_0
    //   258: aload 4
    //   260: putfield 250	o/צ:ˊˊ	Lo/ｬ;
    //   263: aload_0
    //   264: aload 5
    //   266: putfield 512	o/צ:ʾ	Lo/ﾚ;
    //   269: invokestatic 351	java/lang/Thread:currentThread	()Ljava/lang/Thread;
    //   272: astore_1
    //   273: aload_0
    //   274: getfield 244	o/צ:ˈ	Ljava/lang/Thread;
    //   277: astore_2
    //   278: aload_1
    //   279: aload_2
    //   280: if_acmpeq +6 -> 286
    //   283: goto -280 -> 3
    //   286: goto -276 -> 10
    //   289: bipush 85
    //   291: istore 6
    //   293: goto -276 -> 17
    // Local variable table:
    //   start	length	slot	name	signature
    //   0	296	0	this	צ
    //   0	296	1	paramﾚ1	ﾚ
    //   0	296	2	paramObject	Object
    //   0	296	3	paramʢ	ʢ<?>
    //   0	296	4	paramｬ	ｬ
    //   0	296	5	paramﾚ2	ﾚ
    //   5	287	6	i	int
    // Exception table:
    //   from	to	target	type
    //   242	247	130	java/lang/Exception
    //   247	252	130	java/lang/Exception
    //   252	257	130	java/lang/Exception
    //   257	263	130	java/lang/Exception
    //   263	278	130	java/lang/Exception
    //   185	189	195	finally
    //   257	263	207	java/lang/Exception
  }
  
  public void ˋ()
  {
    for (;;)
    {
      int i = 4 / 0;
      return;
      label42:
      ڋ localڋ;
      for (;;)
      {
        switch (i)
        {
        }
        for (;;)
        {
          break label42;
          break label124;
          i = ˏˎ + 81;
          ˑ = i % 128;
          if (i % 2 != 0) {
            break label84;
          }
          break label92;
          i = 50;
          break;
          localڋ.ˋ();
        }
        label84:
        i = 1;
        break label151;
        label89:
        break;
        label92:
        i = 0;
        break label151;
        label97:
        i = 91;
      }
      for (;;)
      {
        this.ˉ = true;
        localڋ = this.ˊˋ;
        if (localڋ != null) {
          break;
        }
        break label97;
        return;
        label124:
        i = ˏˎ + 23;
        ˑ = i % 128;
        if (i % 2 != 0) {
          break label89;
        }
      }
      label151:
      switch (i)
      {
      }
    }
  }
  
  void ˎ(boolean paramBoolean)
  {
    break label37;
    return;
    int i = ˑ + 117;
    ˏˎ = i % 128;
    if (i % 2 != 0) {
      break label40;
    }
    for (;;)
    {
      label34:
      break label87;
      label37:
      break;
      label40:
      label87:
      label143:
      label148:
      do
      {
        for (;;)
        {
          try
          {
            ˊ localˊ = this.ˋॱ;
            paramBoolean = localˊ.ˏ(paramBoolean);
            if (paramBoolean) {
              break label143;
            }
            switch (i)
            {
            case 0: 
            default: 
              break label148;
              i = ˑ + 3;
              ˏˎ = i % 128;
              if (i % 2 != 0)
              {
                continue;
                i = 0;
                continue;
                ʼ();
                i = null.length;
                break label34;
                i = 83;
              }
              break;
            }
          }
          catch (Exception localException)
          {
            throw localException;
          }
          i = 93;
          break label175;
          i = 1;
        }
        i = ˏˎ + 61;
        ˑ = i % 128;
      } while (i % 2 != 0);
      switch (i)
      {
      case 83: 
      default: 
        label175:
        break label214;
        ʼ();
      }
    }
    label214:
    i = null.length;
  }
  
  /* Error */
  public void ˏ()
  {
    // Byte code:
    //   0: goto +85 -> 85
    //   3: astore_2
    //   4: aload_2
    //   5: athrow
    //   6: getstatic 106	o/צ:ˑ	I
    //   9: bipush 115
    //   11: iadd
    //   12: istore_1
    //   13: iload_1
    //   14: sipush 128
    //   17: irem
    //   18: putstatic 108	o/צ:ˏˎ	I
    //   21: iload_1
    //   22: iconst_2
    //   23: irem
    //   24: ifne +6 -> 30
    //   27: goto +55 -> 82
    //   30: goto +32 -> 62
    //   33: getstatic 108	o/צ:ˏˎ	I
    //   36: bipush 87
    //   38: iadd
    //   39: istore_1
    //   40: iload_1
    //   41: sipush 128
    //   44: irem
    //   45: putstatic 106	o/צ:ˑ	I
    //   48: iload_1
    //   49: iconst_2
    //   50: irem
    //   51: ifeq +6 -> 57
    //   54: goto +4 -> 58
    //   57: return
    //   58: return
    //   59: astore_2
    //   60: aload_2
    //   61: athrow
    //   62: aload_0
    //   63: getstatic 577	o/צ$aux:ॱ	Lo/צ$aux;
    //   66: putfield 527	o/צ:ॱᐝ	Lo/צ$aux;
    //   69: aload_0
    //   70: getfield 240	o/צ:ᐝॱ	Lo/צ$If;
    //   73: aload_0
    //   74: invokeinterface 567 2 0
    //   79: goto -46 -> 33
    //   82: goto -20 -> 62
    //   85: goto -79 -> 6
    // Local variable table:
    //   start	length	slot	name	signature
    //   0	88	0	this	צ
    //   12	39	1	i	int
    //   3	2	2	localException1	Exception
    //   59	2	2	localException2	Exception
    // Exception table:
    //   from	to	target	type
    //   33	40	3	java/lang/Exception
    //   40	48	3	java/lang/Exception
    //   40	48	59	java/lang/Exception
  }
  
  public int ॱ(צ<?> paramצ)
  {
    break label178;
    int j = 1;
    break label120;
    try
    {
      i = ˑ + 69;
      try
      {
        ˏˎ = i % 128;
        if (i % 2 == 0) {
          break label111;
        }
      }
      catch (Exception paramצ)
      {
        throw paramצ;
      }
      return i;
    }
    catch (Exception paramצ)
    {
      label37:
      throw paramצ;
    }
    j = 0;
    break label120;
    label42:
    int i = ʽ() + paramצ.ʽ();
    if (i != 0) {
      break label147;
    }
    label62:
    int k;
    for (;;)
    {
      switch (j)
      {
      case 20: 
      default: 
        break;
      }
      for (;;)
      {
        j = this.ॱˎ;
        k = paramצ.ॱˎ;
        break;
        label111:
        break label153;
        j = 68;
        break label62;
        label120:
        switch (j)
        {
        }
      }
      label147:
      j = 20;
    }
    label153:
    return j - k;
    for (;;)
    {
      i = ʽ() - paramצ.ʽ();
      if (i == 0) {
        break label37;
      }
      break;
      label178:
      i = ˑ + 61;
      ˏˎ = i % 128;
      if (i % 2 == 0) {
        break label42;
      }
    }
  }
  
  /* Error */
  צ<R> ॱ(ᔦ paramᔦ, Object paramObject, ڒ paramڒ, ﾚ paramﾚ, int paramInt1, int paramInt2, Class<?> paramClass, Class<R> paramClass1, ᴈ paramᴈ, ڹ paramڹ, java.util.Map<Class<?>, ɛ<?>> paramMap, boolean paramBoolean1, boolean paramBoolean2, boolean paramBoolean3, ʄ paramʄ, If<R> paramIf, int paramInt3)
  {
    // Byte code:
    //   0: goto +76 -> 76
    //   3: astore_1
    //   4: aload_1
    //   5: athrow
    //   6: goto +102 -> 108
    //   9: new 271	java/lang/NullPointerException
    //   12: dup
    //   13: invokespecial 272	java/lang/NullPointerException:<init>	()V
    //   16: athrow
    //   17: iconst_1
    //   18: istore 5
    //   20: iload 5
    //   22: tableswitch	default:+22->44, 0:+57->79, 1:+-13->9
    //   44: aload_0
    //   45: areturn
    //   46: getstatic 108	o/צ:ˏˎ	I
    //   49: bipush 63
    //   51: iadd
    //   52: istore 5
    //   54: iload 5
    //   56: sipush 128
    //   59: irem
    //   60: putstatic 106	o/צ:ˑ	I
    //   63: iload 5
    //   65: iconst_2
    //   66: irem
    //   67: ifeq +6 -> 73
    //   70: goto -53 -> 17
    //   73: goto +152 -> 225
    //   76: goto +5 -> 81
    //   79: aload_0
    //   80: areturn
    //   81: getstatic 108	o/צ:ˏˎ	I
    //   84: bipush 45
    //   86: iadd
    //   87: istore 18
    //   89: iload 18
    //   91: sipush 128
    //   94: irem
    //   95: putstatic 106	o/צ:ˑ	I
    //   98: iload 18
    //   100: iconst_2
    //   101: irem
    //   102: ifeq +6 -> 108
    //   105: goto -99 -> 6
    //   108: aload_0
    //   109: getfield 152	o/צ:ˊ	Lo/ب;
    //   112: astore 19
    //   114: aload_0
    //   115: getfield 172	o/צ:ͺ	Lo/צ$iF;
    //   118: astore 20
    //   120: aload 19
    //   122: aload_1
    //   123: aload_2
    //   124: aload 4
    //   126: iload 5
    //   128: iload 6
    //   130: aload 10
    //   132: aload 7
    //   134: aload 8
    //   136: aload 9
    //   138: aload 15
    //   140: aload 11
    //   142: iload 12
    //   144: iload 13
    //   146: aload 20
    //   148: invokevirtual 586	o/ب:ˋ	(Lo/ᔦ;Ljava/lang/Object;Lo/ﾚ;IILo/ڹ;Ljava/lang/Class;Ljava/lang/Class;Lo/ᴈ;Lo/ʄ;Ljava/util/Map;ZZLo/צ$iF;)V
    //   151: aload_0
    //   152: aload_1
    //   153: putfield 230	o/צ:ˊॱ	Lo/ᔦ;
    //   156: aload_0
    //   157: aload 4
    //   159: putfield 232	o/צ:ˏ	Lo/ﾚ;
    //   162: aload_0
    //   163: aload 9
    //   165: putfield 236	o/צ:ॱˊ	Lo/ᴈ;
    //   168: aload_0
    //   169: aload_3
    //   170: putfield 238	o/צ:ʻॱ	Lo/ڒ;
    //   173: aload_0
    //   174: iload 5
    //   176: putfield 485	o/צ:ˋ	I
    //   179: aload_0
    //   180: iload 6
    //   182: putfield 487	o/צ:ॱ	I
    //   185: aload_0
    //   186: aload 10
    //   188: putfield 457	o/צ:ʽ	Lo/ڹ;
    //   191: aload_0
    //   192: iload 14
    //   194: putfield 463	o/צ:ʽॱ	Z
    //   197: aload_0
    //   198: aload 15
    //   200: putfield 234	o/צ:ॱॱ	Lo/ʄ;
    //   203: aload_0
    //   204: aload 16
    //   206: putfield 240	o/צ:ᐝॱ	Lo/צ$If;
    //   209: aload_0
    //   210: iload 17
    //   212: putfield 581	o/צ:ॱˎ	I
    //   215: aload_0
    //   216: getstatic 588	o/צ$aux:ˏ	Lo/צ$aux;
    //   219: putfield 527	o/צ:ॱᐝ	Lo/צ$aux;
    //   222: goto -176 -> 46
    //   225: iconst_0
    //   226: istore 5
    //   228: goto -208 -> 20
    //   231: astore_1
    //   232: aload_1
    //   233: athrow
    // Local variable table:
    //   start	length	slot	name	signature
    //   0	234	0	this	צ
    //   0	234	1	paramᔦ	ᔦ
    //   0	234	2	paramObject	Object
    //   0	234	3	paramڒ	ڒ
    //   0	234	4	paramﾚ	ﾚ
    //   0	234	5	paramInt1	int
    //   0	234	6	paramInt2	int
    //   0	234	7	paramClass	Class<?>
    //   0	234	8	paramClass1	Class<R>
    //   0	234	9	paramᴈ	ᴈ
    //   0	234	10	paramڹ	ڹ
    //   0	234	11	paramMap	java.util.Map<Class<?>, ɛ<?>>
    //   0	234	12	paramBoolean1	boolean
    //   0	234	13	paramBoolean2	boolean
    //   0	234	14	paramBoolean3	boolean
    //   0	234	15	paramʄ	ʄ
    //   0	234	16	paramIf	If<R>
    //   0	234	17	paramInt3	int
    //   87	15	18	i	int
    //   112	9	19	localب	ب
    //   118	29	20	localIF	iF
    // Exception table:
    //   from	to	target	type
    //   114	120	3	java/lang/Exception
    //   108	114	231	java/lang/Exception
    //   114	120	231	java/lang/Exception
    //   120	151	231	java/lang/Exception
    //   151	156	231	java/lang/Exception
    //   156	222	231	java/lang/Exception
  }
  
  /* Error */
  public void ॱ(ﾚ paramﾚ, Exception paramException, ʢ<?> paramʢ, ｬ paramｬ)
  {
    // Byte code:
    //   0: goto +148 -> 148
    //   3: aload_3
    //   4: invokeinterface 395 1 0
    //   9: new 294	o/ঌ
    //   12: dup
    //   13: ldc_w 592
    //   16: aload_2
    //   17: invokespecial 595	o/ঌ:<init>	(Ljava/lang/String;Ljava/lang/Throwable;)V
    //   20: astore_2
    //   21: aload_2
    //   22: aload_1
    //   23: aload 4
    //   25: aload_3
    //   26: invokeinterface 597 1 0
    //   31: invokevirtual 600	o/ঌ:ॱ	(Lo/ﾚ;Lo/ｬ;Ljava/lang/Class;)V
    //   34: aload_0
    //   35: getfield 157	o/צ:ʼ	Ljava/util/List;
    //   38: aload_2
    //   39: invokeinterface 518 2 0
    //   44: pop
    //   45: invokestatic 351	java/lang/Thread:currentThread	()Ljava/lang/Thread;
    //   48: aload_0
    //   49: getfield 244	o/צ:ˈ	Ljava/lang/Thread;
    //   52: if_acmpeq +6 -> 58
    //   55: goto +36 -> 91
    //   58: goto +80 -> 138
    //   61: iload 5
    //   63: lookupswitch	default:+25->88, 36:+122->185, 81:+35->98
    //   88: goto +10 -> 98
    //   91: bipush 36
    //   93: istore 5
    //   95: goto -34 -> 61
    //   98: aload_0
    //   99: invokespecial 520	o/צ:ˋॱ	()V
    //   102: goto +79 -> 181
    //   105: astore_1
    //   106: aload_1
    //   107: athrow
    //   108: getstatic 108	o/צ:ˏˎ	I
    //   111: bipush 45
    //   113: iadd
    //   114: istore 5
    //   116: iload 5
    //   118: sipush 128
    //   121: irem
    //   122: putstatic 106	o/צ:ˑ	I
    //   125: iload 5
    //   127: iconst_2
    //   128: irem
    //   129: ifeq +6 -> 135
    //   132: goto +50 -> 182
    //   135: goto +16 -> 151
    //   138: bipush 81
    //   140: istore 5
    //   142: goto -81 -> 61
    //   145: astore_1
    //   146: aload_1
    //   147: athrow
    //   148: goto -145 -> 3
    //   151: goto +30 -> 181
    //   154: getstatic 577	o/צ$aux:ॱ	Lo/צ$aux;
    //   157: astore_1
    //   158: aload_0
    //   159: aload_1
    //   160: putfield 527	o/צ:ॱᐝ	Lo/צ$aux;
    //   163: aload_0
    //   164: getfield 240	o/צ:ᐝॱ	Lo/צ$If;
    //   167: astore_1
    //   168: aload_1
    //   169: aload_0
    //   170: invokeinterface 567 2 0
    //   175: goto -67 -> 108
    //   178: goto -24 -> 154
    //   181: return
    //   182: goto -31 -> 151
    //   185: getstatic 106	o/צ:ˑ	I
    //   188: bipush 39
    //   190: iadd
    //   191: istore 5
    //   193: iload 5
    //   195: sipush 128
    //   198: irem
    //   199: putstatic 108	o/צ:ˏˎ	I
    //   202: iload 5
    //   204: iconst_2
    //   205: irem
    //   206: ifne +6 -> 212
    //   209: goto -31 -> 178
    //   212: goto -58 -> 154
    // Local variable table:
    //   start	length	slot	name	signature
    //   0	215	0	this	צ
    //   0	215	1	paramﾚ	ﾚ
    //   0	215	2	paramException	Exception
    //   0	215	3	paramʢ	ʢ<?>
    //   0	215	4	paramｬ	ｬ
    //   61	145	5	i	int
    // Exception table:
    //   from	to	target	type
    //   163	168	105	java/lang/Exception
    //   154	158	145	java/lang/Exception
    //   158	163	145	java/lang/Exception
    //   163	168	145	java/lang/Exception
    //   168	175	145	java/lang/Exception
  }
  
  boolean ॱ()
  {
    break label146;
    int i = 75;
    break label76;
    label9:
    i = ˑ + 43;
    ˏˎ = i % 128;
    if (i % 2 != 0) {
      break label65;
    }
    label59:
    label65:
    label71:
    boolean bool;
    for (;;)
    {
      break label205;
      i = 2 / 5;
      break label205;
      ˎ localˎ;
      while (localˎ != ˎ.ˏ)
      {
        break label71;
        i = 85;
        break label76;
        i = 37;
        break label149;
        bool = false;
        break label205;
        switch (i)
        {
        case 85: 
        default: 
          label76:
          continue;
          i = 30 / 0;
          return bool;
        }
      }
      bool = true;
      break label9;
      i = 90;
      break label149;
      label146:
      for (;;)
      {
        localˎ = ˏ(ˎ.ˊ);
        if (localˎ != ˎ.ˎ) {
          break label59;
        }
        break;
      }
      label149:
      switch (i)
      {
      }
    }
    label205:
    for (;;)
    {
      i = ˏˎ + 111;
      ˑ = i % 128;
      if (i % 2 != 0) {
        break;
      }
      return bool;
    }
  }
  
  static abstract interface If<R>
  {
    public abstract void ˊ(צ<?> paramצ);
    
    public abstract void ˎ(ঌ paramঌ);
    
    public abstract void ˎ(ก<R> paramก, ｬ paramｬ);
  }
  
  static enum aux
  {
    static
    {
      ˎ = new aux("DECODE_DATA", 2);
    }
    
    private aux() {}
  }
  
  static abstract interface iF
  {
    public abstract ᔫ ˏ();
  }
  
  final class if<Z>
    implements م.if<Z>
  {
    private final ｬ ˋ;
    
    if(ｬ paramｬ)
    {
      this.ˋ = paramｬ;
    }
    
    private Class<Z> ˋ(ก<Z> paramก)
    {
      return paramก.ˎ().getClass();
    }
    
    public ก<Z> ˊ(ก<Z> paramก)
    {
      Class localClass = ˋ(paramก);
      Object localObject2 = null;
      Object localObject1 = paramก;
      if (this.ˋ != ｬ.ˎ)
      {
        localObject2 = צ.this.ˊ.ˎ(localClass);
        localObject1 = ((ɛ)localObject2).ˎ(צ.ˎ(צ.this), paramก, צ.this.ˋ, צ.this.ॱ);
      }
      if (!paramก.equals(localObject1)) {
        paramก.ॱॱ();
      }
      ｴ localｴ;
      if (צ.this.ˊ.ˏ((ก)localObject1))
      {
        paramก = צ.this.ˊ.ˊ((ก)localObject1);
        localｴ = paramก.ˋ(צ.this.ॱॱ);
      }
      else
      {
        paramก = null;
        localｴ = ｴ.ˊ;
      }
      Object localObject3 = localObject1;
      boolean bool;
      if (!צ.this.ˊ.ॱ(צ.this.ᐝ)) {
        bool = true;
      } else {
        bool = false;
      }
      if (צ.this.ʽ.ˏ(bool, this.ˋ, localｴ))
      {
        if (paramก == null) {
          throw new ᚐ.ˋ(((ก)localObject1).ˎ().getClass());
        }
        if (localｴ == ｴ.ˏ) {
          localObject2 = new ԁ(צ.this.ᐝ, צ.this.ˏ);
        } else if (localｴ == ｴ.ˎ) {
          localObject2 = new ঽ(צ.this.ˊ.ᐝ(), צ.this.ᐝ, צ.this.ˏ, צ.this.ˋ, צ.this.ॱ, (ɛ)localObject2, localClass, צ.this.ॱॱ);
        } else {
          throw new IllegalArgumentException("Unknown strategy: " + localｴ);
        }
        localObject3 = ব.ˋ((ก)localObject1);
        צ.this.ˎ.ˊ((ﾚ)localObject2, paramก, (ব)localObject3);
      }
      return localObject3;
    }
  }
  
  static class ˊ
  {
    private boolean ˊ;
    private boolean ˋ;
    private boolean ˎ;
    
    ˊ() {}
    
    private boolean ॱ(boolean paramBoolean)
    {
      return ((this.ˎ) || (paramBoolean) || (this.ˋ)) && (this.ˊ);
    }
    
    boolean ˋ()
    {
      try
      {
        this.ˋ = true;
        boolean bool = ॱ(false);
        return bool;
      }
      finally
      {
        localObject = finally;
        throw localObject;
      }
    }
    
    boolean ˏ()
    {
      try
      {
        this.ˎ = true;
        boolean bool = ॱ(false);
        return bool;
      }
      finally
      {
        localObject = finally;
        throw localObject;
      }
    }
    
    boolean ˏ(boolean paramBoolean)
    {
      try
      {
        this.ˊ = true;
        paramBoolean = ॱ(paramBoolean);
        return paramBoolean;
      }
      finally
      {
        localObject = finally;
        throw localObject;
      }
    }
    
    void ॱ()
    {
      try
      {
        this.ˋ = false;
        this.ˊ = false;
        this.ˎ = false;
        return;
      }
      finally
      {
        localObject = finally;
        throw localObject;
      }
    }
  }
  
  static class ˋ<Z>
  {
    private ﾚ ˊ;
    private ব<Z> ˎ;
    private ʈ<Z> ॱ;
    
    ˋ() {}
    
    <X> void ˊ(ﾚ paramﾚ, ʈ<X> paramƮ, ব<X> paramব)
    {
      this.ˊ = paramﾚ;
      this.ॱ = paramƮ;
      this.ˎ = paramব;
    }
    
    boolean ˊ()
    {
      return this.ˎ != null;
    }
    
    void ˎ(צ.iF paramIF, ʄ paramʄ)
    {
      ๅ.ˏ("DecodeJob.encode");
      try
      {
        paramIF.ˏ().ˋ(this.ˊ, new ٵ(this.ॱ, this.ˎ, paramʄ));
        return;
      }
      finally
      {
        this.ˎ.ॱ();
        ๅ.ॱ();
      }
    }
    
    void ˏ()
    {
      this.ˊ = null;
      this.ॱ = null;
      this.ˎ = null;
    }
  }
  
  static enum ˎ
  {
    static
    {
      ˋ = new ˎ("SOURCE", 3);
      ॱ = new ˎ("ENCODE", 4);
    }
    
    private ˎ() {}
  }
}
