package o;

import java.util.Map;

public class ܚ
  implements ۊ, ᘢ.iF, र.If
{
  private static long ʻ = -3466018738794423394L;
  private static int ˋॱ;
  private static int ॱˊ = 0;
  private static char[] ᐝ = { -6107, 29605, -8360, 15026, -31141, -7621, 19845, -22240, 13464 };
  private final ւ ʼ;
  private final ˊ ʽ;
  private final ˋ ˊ;
  private final ᘢ ˋ;
  private final ᐯ ˎ;
  private final ܪ ˏ;
  private final গ ॱ;
  private final if ॱॱ;
  
  static
  {
    ˋॱ = 1;
  }
  
  /* Error */
  ܚ(ᘢ paramᘢ, ᔫ.If paramIf, Ⅴ paramⅤ1, Ⅴ paramⅤ2, Ⅴ paramⅤ3, Ⅴ paramⅤ4, গ paramগ, ܪ paramܪ, ւ paramՒ, ˋ paramˋ, ˊ paramˊ, ᐯ paramᐯ, boolean paramBoolean)
  {
    // Byte code:
    //   0: goto +38 -> 38
    //   3: aload_0
    //   4: aload 7
    //   6: putfield 75	o/ܚ:ॱ	Lo/গ;
    //   9: aload 10
    //   11: ifnonnull +6 -> 17
    //   14: goto +124 -> 138
    //   17: goto +89 -> 106
    //   20: astore_1
    //   21: aload_1
    //   22: athrow
    //   23: new 77	o/গ
    //   26: dup
    //   27: invokespecial 79	o/গ:<init>	()V
    //   30: astore 7
    //   32: goto +188 -> 220
    //   35: goto +38 -> 73
    //   38: aload_0
    //   39: invokespecial 80	java/lang/Object:<init>	()V
    //   42: aload_0
    //   43: aload_1
    //   44: putfield 82	o/ܚ:ˋ	Lo/ᘢ;
    //   47: aload_0
    //   48: new 15	o/ܚ$if
    //   51: dup
    //   52: aload_2
    //   53: invokespecial 85	o/ܚ$if:<init>	(Lo/ᔫ$If;)V
    //   56: putfield 87	o/ܚ:ॱॱ	Lo/ܚ$if;
    //   59: aload 9
    //   61: ifnonnull +6 -> 67
    //   64: goto +128 -> 192
    //   67: goto +185 -> 252
    //   70: goto +65 -> 135
    //   73: aload_0
    //   74: aload 11
    //   76: putfield 89	o/ܚ:ʽ	Lo/ܚ$ˊ;
    //   79: aload 12
    //   81: ifnonnull +6 -> 87
    //   84: goto +39 -> 123
    //   87: goto +119 -> 206
    //   90: new 18	o/ܚ$ˊ
    //   93: dup
    //   94: aload_0
    //   95: getfield 87	o/ܚ:ॱॱ	Lo/ܚ$if;
    //   98: invokespecial 92	o/ܚ$ˊ:<init>	(Lo/צ$iF;)V
    //   101: astore 11
    //   103: goto +55 -> 158
    //   106: aload_0
    //   107: aload 10
    //   109: putfield 94	o/ܚ:ˊ	Lo/ܚ$ˋ;
    //   112: aload 11
    //   114: ifnonnull +6 -> 120
    //   117: goto -27 -> 90
    //   120: goto -47 -> 73
    //   123: new 96	o/ᐯ
    //   126: dup
    //   127: invokespecial 97	o/ᐯ:<init>	()V
    //   130: astore 12
    //   132: goto +143 -> 275
    //   135: goto +71 -> 206
    //   138: new 23	o/ܚ$ˋ
    //   141: dup
    //   142: aload_3
    //   143: aload 4
    //   145: aload 5
    //   147: aload 6
    //   149: aload_0
    //   150: invokespecial 100	o/ܚ$ˋ:<init>	(Lo/Ⅴ;Lo/Ⅴ;Lo/Ⅴ;Lo/Ⅴ;Lo/ۊ;)V
    //   153: astore 10
    //   155: goto -49 -> 106
    //   158: getstatic 53	o/ܚ:ˋॱ	I
    //   161: istore 14
    //   163: iload 14
    //   165: bipush 81
    //   167: iadd
    //   168: istore 14
    //   170: iload 14
    //   172: sipush 128
    //   175: irem
    //   176: putstatic 51	o/ܚ:ॱˊ	I
    //   179: iload 14
    //   181: iconst_2
    //   182: irem
    //   183: ifeq +6 -> 189
    //   186: goto +63 -> 249
    //   189: goto -154 -> 35
    //   192: new 102	o/ւ
    //   195: dup
    //   196: iload 13
    //   198: invokespecial 105	o/ւ:<init>	(Z)V
    //   201: astore 9
    //   203: goto +49 -> 252
    //   206: aload_0
    //   207: aload 12
    //   209: putfield 107	o/ܚ:ˎ	Lo/ᐯ;
    //   212: aload_1
    //   213: aload_0
    //   214: invokeinterface 112 2 0
    //   219: return
    //   220: goto -217 -> 3
    //   223: new 114	o/ܪ
    //   226: dup
    //   227: invokespecial 115	o/ܪ:<init>	()V
    //   230: astore 8
    //   232: aload_0
    //   233: aload 8
    //   235: putfield 117	o/ܚ:ˏ	Lo/ܪ;
    //   238: aload 7
    //   240: ifnonnull +6 -> 246
    //   243: goto -220 -> 23
    //   246: goto -243 -> 3
    //   249: goto -214 -> 35
    //   252: aload_0
    //   253: aload 9
    //   255: putfield 119	o/ܚ:ʼ	Lo/ւ;
    //   258: aload 9
    //   260: aload_0
    //   261: invokevirtual 122	o/ւ:ˋ	(Lo/र$If;)V
    //   264: aload 8
    //   266: ifnonnull +6 -> 272
    //   269: goto -46 -> 223
    //   272: goto -40 -> 232
    //   275: getstatic 51	o/ܚ:ॱˊ	I
    //   278: bipush 93
    //   280: iadd
    //   281: istore 14
    //   283: iload 14
    //   285: sipush 128
    //   288: irem
    //   289: putstatic 53	o/ܚ:ˋॱ	I
    //   292: iload 14
    //   294: iconst_2
    //   295: irem
    //   296: ifne +6 -> 302
    //   299: goto -229 -> 70
    //   302: goto -167 -> 135
    //   305: astore_1
    //   306: aload_1
    //   307: athrow
    // Local variable table:
    //   start	length	slot	name	signature
    //   0	308	0	this	ܚ
    //   0	308	1	paramᘢ	ᘢ
    //   0	308	2	paramIf	ᔫ.If
    //   0	308	3	paramⅤ1	Ⅴ
    //   0	308	4	paramⅤ2	Ⅴ
    //   0	308	5	paramⅤ3	Ⅴ
    //   0	308	6	paramⅤ4	Ⅴ
    //   0	308	7	paramগ	গ
    //   0	308	8	paramܪ	ܪ
    //   0	308	9	paramՒ	ւ
    //   0	308	10	paramˋ	ˋ
    //   0	308	11	paramˊ	ˊ
    //   0	308	12	paramᐯ	ᐯ
    //   0	308	13	paramBoolean	boolean
    //   161	135	14	i	int
    // Exception table:
    //   from	to	target	type
    //   106	112	20	java/lang/Exception
    //   158	163	20	java/lang/Exception
    //   170	179	20	java/lang/Exception
    //   3	9	305	java/lang/Exception
    //   73	79	305	java/lang/Exception
  }
  
  public ܚ(ᘢ paramᘢ, ᔫ.If paramIf, Ⅴ paramⅤ1, Ⅴ paramⅤ2, Ⅴ paramⅤ3, Ⅴ paramⅤ4, boolean paramBoolean)
  {
    this(paramᘢ, paramIf, paramⅤ1, paramⅤ2, paramⅤ3, paramⅤ4, null, null, null, null, null, null, paramBoolean);
  }
  
  /* Error */
  private static void ˊ(String paramString, long paramLong, ﾚ paramﾚ)
  {
    // Byte code:
    //   0: goto +138 -> 138
    //   3: astore_0
    //   4: aload_0
    //   5: athrow
    //   6: ldc -128
    //   8: new 130	java/lang/StringBuilder
    //   11: dup
    //   12: invokespecial 131	java/lang/StringBuilder:<init>	()V
    //   15: aload_0
    //   16: invokevirtual 135	java/lang/StringBuilder:append	(Ljava/lang/String;)Ljava/lang/StringBuilder;
    //   19: ldc -119
    //   21: invokevirtual 135	java/lang/StringBuilder:append	(Ljava/lang/String;)Ljava/lang/StringBuilder;
    //   24: lload_1
    //   25: invokestatic 142	o/ϝ:ˏ	(J)D
    //   28: invokevirtual 145	java/lang/StringBuilder:append	(D)Ljava/lang/StringBuilder;
    //   31: iconst_0
    //   32: ldc -110
    //   34: bipush 9
    //   36: invokestatic 149	o/ܚ:ॱ	(ICI)Ljava/lang/String;
    //   39: invokevirtual 155	java/lang/String:intern	()Ljava/lang/String;
    //   42: invokevirtual 135	java/lang/StringBuilder:append	(Ljava/lang/String;)Ljava/lang/StringBuilder;
    //   45: aload_3
    //   46: invokevirtual 158	java/lang/StringBuilder:append	(Ljava/lang/Object;)Ljava/lang/StringBuilder;
    //   49: invokevirtual 161	java/lang/StringBuilder:toString	()Ljava/lang/String;
    //   52: invokestatic 167	android/util/Log:v	(Ljava/lang/String;Ljava/lang/String;)I
    //   55: pop
    //   56: goto +48 -> 104
    //   59: iload 4
    //   61: lookupswitch	default:+27->88, 58:+28->89, 66:+80->141
    //   88: return
    //   89: new 169	java/lang/NullPointerException
    //   92: dup
    //   93: invokespecial 170	java/lang/NullPointerException:<init>	()V
    //   96: athrow
    //   97: bipush 66
    //   99: istore 4
    //   101: goto -42 -> 59
    //   104: getstatic 53	o/ܚ:ˋॱ	I
    //   107: istore 4
    //   109: iload 4
    //   111: bipush 65
    //   113: iadd
    //   114: istore 4
    //   116: iload 4
    //   118: sipush 128
    //   121: irem
    //   122: putstatic 51	o/ܚ:ॱˊ	I
    //   125: iload 4
    //   127: iconst_2
    //   128: irem
    //   129: ifeq +6 -> 135
    //   132: goto +10 -> 142
    //   135: goto -38 -> 97
    //   138: goto -132 -> 6
    //   141: return
    //   142: bipush 58
    //   144: istore 4
    //   146: goto -87 -> 59
    // Local variable table:
    //   start	length	slot	name	signature
    //   0	149	0	paramString	String
    //   0	149	1	paramLong	long
    //   0	149	3	paramﾚ	ﾚ
    //   59	86	4	i	int
    // Exception table:
    //   from	to	target	type
    //   104	109	3	java/lang/Exception
    //   116	125	3	java/lang/Exception
  }
  
  /* Error */
  private र<?> ˋ(ﾚ paramﾚ)
  {
    // Byte code:
    //   0: goto +180 -> 180
    //   3: getstatic 53	o/ܚ:ˋॱ	I
    //   6: bipush 23
    //   8: iadd
    //   9: istore_2
    //   10: iload_2
    //   11: sipush 128
    //   14: irem
    //   15: putstatic 51	o/ܚ:ॱˊ	I
    //   18: iload_2
    //   19: iconst_2
    //   20: irem
    //   21: ifeq +6 -> 27
    //   24: goto +78 -> 102
    //   27: goto +36 -> 63
    //   30: aload_1
    //   31: areturn
    //   32: iload_2
    //   33: lookupswitch	default:+27->60, 96:+165->198, 97:+-30->3
    //   60: goto +138 -> 198
    //   63: bipush 95
    //   65: istore_2
    //   66: goto +50 -> 116
    //   69: getstatic 53	o/ܚ:ˋॱ	I
    //   72: bipush 33
    //   74: iadd
    //   75: istore_2
    //   76: iload_2
    //   77: sipush 128
    //   80: irem
    //   81: putstatic 51	o/ܚ:ॱˊ	I
    //   84: iload_2
    //   85: iconst_2
    //   86: irem
    //   87: ifeq +6 -> 93
    //   90: goto +77 -> 167
    //   93: goto +98 -> 191
    //   96: bipush 96
    //   98: istore_2
    //   99: goto -67 -> 32
    //   102: bipush 50
    //   104: istore_2
    //   105: goto +11 -> 116
    //   108: new 169	java/lang/NullPointerException
    //   111: dup
    //   112: invokespecial 170	java/lang/NullPointerException:<init>	()V
    //   115: athrow
    //   116: iload_2
    //   117: lookupswitch	default:+27->144, 50:+-9->108, 95:+27->144
    //   144: goto +39 -> 183
    //   147: new 173	o/र
    //   150: dup
    //   151: aload_1
    //   152: iconst_1
    //   153: iconst_1
    //   154: invokespecial 176	o/र:<init>	(Lo/ก;ZZ)V
    //   157: astore_1
    //   158: goto -128 -> 30
    //   161: astore_1
    //   162: aload_1
    //   163: athrow
    //   164: astore_1
    //   165: aload_1
    //   166: athrow
    //   167: aload_1
    //   168: checkcast 173	o/र
    //   171: astore_1
    //   172: new 169	java/lang/NullPointerException
    //   175: dup
    //   176: invokespecial 170	java/lang/NullPointerException:<init>	()V
    //   179: athrow
    //   180: goto +31 -> 211
    //   183: aconst_null
    //   184: areturn
    //   185: bipush 97
    //   187: istore_2
    //   188: goto -156 -> 32
    //   191: aload_1
    //   192: checkcast 173	o/र
    //   195: astore_1
    //   196: aload_1
    //   197: areturn
    //   198: aload_1
    //   199: instanceof 173
    //   202: ifeq +6 -> 208
    //   205: goto -136 -> 69
    //   208: goto -61 -> 147
    //   211: aload_0
    //   212: getfield 82	o/ܚ:ˋ	Lo/ᘢ;
    //   215: aload_1
    //   216: invokeinterface 179 2 0
    //   221: astore_1
    //   222: aload_1
    //   223: ifnonnull +6 -> 229
    //   226: goto -41 -> 185
    //   229: goto -133 -> 96
    // Local variable table:
    //   start	length	slot	name	signature
    //   0	232	0	this	ܚ
    //   0	232	1	paramﾚ	ﾚ
    //   9	179	2	i	int
    // Exception table:
    //   from	to	target	type
    //   3	10	161	java/lang/Exception
    //   10	18	161	java/lang/Exception
    //   167	180	164	java/lang/Exception
    //   191	196	164	java/lang/Exception
  }
  
  private र<?> ˋ(ﾚ paramﾚ, boolean paramBoolean)
  {
    break label167;
    label5:
    for (;;)
    {
      return null;
    }
    for (;;)
    {
      paramﾚ.ʽ();
      break label175;
      int i = ॱˊ + 47;
      ˋॱ = i % 128;
      if (i % 2 == 0) {
        break label5;
      }
      break;
      switch (i)
      {
      default: 
        label42:
        break label184;
        label67:
        if (paramBoolean)
        {
          break;
          label77:
          i = ˋॱ + 27;
          ॱˊ = i % 128;
          if (i % 2 != 0) {
            return paramﾚ;
          }
          return paramﾚ;
        }
        else
        {
          for (;;)
          {
            i = 1;
            break;
            for (;;)
            {
              switch (i)
              {
              case 80: 
              default: 
                label107:
                break label145;
                i = 80;
              }
            }
            label145:
            paramﾚ = this.ʼ.ˊ(paramﾚ);
            if (paramﾚ != null) {
              break label170;
            }
          }
        }
        break;
      }
      label167:
      label170:
      label175:
      label184:
      do
      {
        break;
        break label67;
        i = 0;
        break label42;
        break label77;
        i = 84;
        break label107;
        i = ˋॱ + 77;
        ॱˊ = i % 128;
      } while (i % 2 != 0);
    }
  }
  
  /* Error */
  private static String ॱ(int paramInt1, char paramChar, int paramInt2)
  {
    // Byte code:
    //   0: goto +76 -> 76
    //   3: getstatic 51	o/ܚ:ॱˊ	I
    //   6: istore_3
    //   7: iload_3
    //   8: bipush 117
    //   10: iadd
    //   11: istore_3
    //   12: iload_3
    //   13: sipush 128
    //   16: irem
    //   17: putstatic 53	o/ܚ:ˋॱ	I
    //   20: iload_3
    //   21: iconst_2
    //   22: irem
    //   23: ifne +6 -> 29
    //   26: goto +209 -> 235
    //   29: goto +230 -> 259
    //   32: astore 7
    //   34: aload 7
    //   36: athrow
    //   37: getstatic 53	o/ܚ:ˋॱ	I
    //   40: bipush 105
    //   42: iadd
    //   43: istore_0
    //   44: iload_0
    //   45: sipush 128
    //   48: irem
    //   49: putstatic 51	o/ܚ:ॱˊ	I
    //   52: iload_0
    //   53: iconst_2
    //   54: irem
    //   55: ifeq +6 -> 61
    //   58: goto +55 -> 113
    //   61: aload 7
    //   63: areturn
    //   64: iconst_1
    //   65: istore 4
    //   67: goto +140 -> 207
    //   70: iconst_0
    //   71: istore 4
    //   73: goto +134 -> 207
    //   76: goto -73 -> 3
    //   79: aload 7
    //   81: iload_3
    //   82: getstatic 68	o/ܚ:ᐝ	[C
    //   85: iload 5
    //   87: iload_3
    //   88: iadd
    //   89: caload
    //   90: i2l
    //   91: iload_3
    //   92: i2l
    //   93: getstatic 57	o/ܚ:ʻ	J
    //   96: land
    //   97: lxor
    //   98: iload 6
    //   100: i2l
    //   101: lsub
    //   102: l2i
    //   103: i2c
    //   104: castore
    //   105: iload_3
    //   106: bipush 81
    //   108: iadd
    //   109: istore_3
    //   110: goto +132 -> 242
    //   113: aload 7
    //   115: areturn
    //   116: new 151	java/lang/String
    //   119: dup
    //   120: aload 7
    //   122: invokespecial 190	java/lang/String:<init>	([C)V
    //   125: astore 7
    //   127: goto -90 -> 37
    //   130: aload 7
    //   132: iload_3
    //   133: getstatic 68	o/ܚ:ᐝ	[C
    //   136: iload 5
    //   138: iload_3
    //   139: iadd
    //   140: caload
    //   141: i2l
    //   142: iload_3
    //   143: i2l
    //   144: getstatic 57	o/ܚ:ʻ	J
    //   147: lmul
    //   148: lxor
    //   149: iload 6
    //   151: i2l
    //   152: lxor
    //   153: l2i
    //   154: i2c
    //   155: castore
    //   156: iload_3
    //   157: iconst_1
    //   158: iadd
    //   159: istore_3
    //   160: goto +82 -> 242
    //   163: getstatic 51	o/ܚ:ॱˊ	I
    //   166: bipush 59
    //   168: iadd
    //   169: istore 4
    //   171: iload 4
    //   173: sipush 128
    //   176: irem
    //   177: putstatic 53	o/ܚ:ˋॱ	I
    //   180: iload 4
    //   182: iconst_2
    //   183: irem
    //   184: ifne +6 -> 190
    //   187: goto -123 -> 64
    //   190: goto -120 -> 70
    //   193: bipush 59
    //   195: istore 4
    //   197: goto +72 -> 269
    //   200: bipush 38
    //   202: istore 4
    //   204: goto +65 -> 269
    //   207: iload 4
    //   209: tableswitch	default:+23->232, 0:+-79->130, 1:+-130->79
    //   232: goto -102 -> 130
    //   235: iload_2
    //   236: newarray char
    //   238: astore 7
    //   240: iconst_1
    //   241: istore_3
    //   242: iload_1
    //   243: istore 6
    //   245: iload_0
    //   246: istore 5
    //   248: iload_3
    //   249: iload_2
    //   250: if_icmpge +6 -> 256
    //   253: goto -60 -> 193
    //   256: goto -56 -> 200
    //   259: iload_2
    //   260: newarray char
    //   262: astore 7
    //   264: iconst_0
    //   265: istore_3
    //   266: goto -24 -> 242
    //   269: iload 4
    //   271: lookupswitch	default:+25->296, 38:+-155->116, 59:+-108->163
    //   296: goto -133 -> 163
    //   299: astore 7
    //   301: aload 7
    //   303: athrow
    // Local variable table:
    //   start	length	slot	name	signature
    //   0	304	0	paramInt1	int
    //   0	304	1	paramChar	char
    //   0	304	2	paramInt2	int
    //   6	260	3	i	int
    //   65	205	4	j	int
    //   85	162	5	k	int
    //   98	146	6	m	int
    //   32	89	7	localException1	Exception
    //   125	138	7	localObject	Object
    //   299	3	7	localException2	Exception
    // Exception table:
    //   from	to	target	type
    //   3	7	32	java/lang/Exception
    //   12	20	299	java/lang/Exception
  }
  
  private र<?> ॱ(ﾚ paramﾚ, boolean paramBoolean)
  {
    break label138;
    label3:
    int i = 1;
    break label165;
    label8:
    i = 0;
    break label165;
    label13:
    i = ˋॱ + 47;
    ॱˊ = i % 128;
    if (i % 2 == 0)
    {
      break label67;
      label40:
      i = ॱˊ + 41;
      ˋॱ = i % 128;
      if (i % 2 == 0) {
        break label218;
      }
      break label159;
    }
    label67:
    Object localObject;
    for (;;)
    {
      return localObject;
    }
    i = 68 / 0;
    return null;
    return localObject;
    for (;;)
    {
      ((र)localObject).ʽ();
      this.ʼ.ˋ(paramﾚ, (र)localObject);
      break label13;
      for (;;)
      {
        switch (i)
        {
        case 63: 
        default: 
          label101:
          if (!paramBoolean) {
            break label223;
          }
          break label141;
          label138:
          break label40;
          label141:
          localObject = ˋ(paramﾚ);
          if (localObject != null) {
            break label3;
          }
          break label8;
          label159:
          i = 63;
        }
      }
      label165:
      switch (i)
      {
      }
    }
    label218:
    label223:
    for (;;)
    {
      i = ॱˊ + 57;
      ˋॱ = i % 128;
      if (i % 2 == 0) {
        break;
      }
      break label226;
      i = 3;
      break label101;
    }
    label226:
    return null;
    throw new NullPointerException();
  }
  
  /* Error */
  public void ˊ(ก<?> paramก)
  {
    // Byte code:
    //   0: goto +78 -> 78
    //   3: astore_1
    //   4: aload_1
    //   5: athrow
    //   6: return
    //   7: goto +54 -> 61
    //   10: getstatic 51	o/ܚ:ॱˊ	I
    //   13: bipush 33
    //   15: iadd
    //   16: istore_2
    //   17: iload_2
    //   18: sipush 128
    //   21: irem
    //   22: putstatic 53	o/ܚ:ˋॱ	I
    //   25: iload_2
    //   26: iconst_2
    //   27: irem
    //   28: ifne +6 -> 34
    //   31: goto +58 -> 89
    //   34: goto +87 -> 121
    //   37: iload_2
    //   38: tableswitch	default:+22->60, 0:+-32->6, 1:+43->81
    //   60: return
    //   61: invokestatic 200	o/Ϲ:ˋ	()V
    //   64: aload_0
    //   65: getfield 107	o/ܚ:ˎ	Lo/ᐯ;
    //   68: aload_1
    //   69: invokevirtual 202	o/ᐯ:ˎ	(Lo/ก;)V
    //   72: goto -62 -> 10
    //   75: astore_1
    //   76: aload_1
    //   77: athrow
    //   78: goto +16 -> 94
    //   81: new 169	java/lang/NullPointerException
    //   84: dup
    //   85: invokespecial 170	java/lang/NullPointerException:<init>	()V
    //   88: athrow
    //   89: iconst_1
    //   90: istore_2
    //   91: goto -54 -> 37
    //   94: getstatic 53	o/ܚ:ˋॱ	I
    //   97: bipush 51
    //   99: iadd
    //   100: istore_2
    //   101: iload_2
    //   102: sipush 128
    //   105: irem
    //   106: putstatic 51	o/ܚ:ॱˊ	I
    //   109: iload_2
    //   110: iconst_2
    //   111: irem
    //   112: ifeq +6 -> 118
    //   115: goto -108 -> 7
    //   118: goto -57 -> 61
    //   121: iconst_0
    //   122: istore_2
    //   123: goto -86 -> 37
    // Local variable table:
    //   start	length	slot	name	signature
    //   0	126	0	this	ܚ
    //   0	126	1	paramก	ก<?>
    //   16	107	2	i	int
    // Exception table:
    //   from	to	target	type
    //   17	25	3	java/lang/Exception
    //   10	17	75	java/lang/Exception
    //   17	25	75	java/lang/Exception
  }
  
  /* Error */
  public void ˋ(ڕ<?> paramڕ, ﾚ paramﾚ, र<?> paramर)
  {
    // Byte code:
    //   0: goto +243 -> 243
    //   3: getstatic 53	o/ܚ:ˋॱ	I
    //   6: bipush 23
    //   8: iadd
    //   9: istore 4
    //   11: iload 4
    //   13: sipush 128
    //   16: irem
    //   17: putstatic 51	o/ܚ:ॱˊ	I
    //   20: iload 4
    //   22: iconst_2
    //   23: irem
    //   24: ifeq +6 -> 30
    //   27: goto +132 -> 159
    //   30: goto +79 -> 109
    //   33: getstatic 53	o/ܚ:ˋॱ	I
    //   36: bipush 125
    //   38: iadd
    //   39: istore 4
    //   41: iload 4
    //   43: sipush 128
    //   46: irem
    //   47: putstatic 51	o/ܚ:ॱˊ	I
    //   50: iload 4
    //   52: iconst_2
    //   53: irem
    //   54: ifeq +6 -> 60
    //   57: goto +32 -> 89
    //   60: return
    //   61: astore_1
    //   62: aload_1
    //   63: athrow
    //   64: aload_0
    //   65: getfield 119	o/ܚ:ʼ	Lo/ւ;
    //   68: aload_2
    //   69: aload_3
    //   70: invokevirtual 193	o/ւ:ˋ	(Lo/ﾚ;Lo/र;)V
    //   73: bipush 57
    //   75: iconst_0
    //   76: idiv
    //   77: istore 4
    //   79: goto +83 -> 162
    //   82: bipush 85
    //   84: istore 4
    //   86: goto +43 -> 129
    //   89: return
    //   90: aload_3
    //   91: aload_2
    //   92: aload_0
    //   93: invokevirtual 207	o/र:ॱ	(Lo/ﾚ;Lo/र$If;)V
    //   96: aload_3
    //   97: invokevirtual 210	o/र:ॱ	()Z
    //   100: ifeq +6 -> 106
    //   103: goto +73 -> 176
    //   106: goto -24 -> 82
    //   109: invokestatic 200	o/Ϲ:ˋ	()V
    //   112: aload_3
    //   113: ifnull +6 -> 119
    //   116: goto +67 -> 183
    //   119: goto +43 -> 162
    //   122: bipush 82
    //   124: istore 4
    //   126: goto +87 -> 213
    //   129: iload 4
    //   131: lookupswitch	default:+25->156, 66:+128->259, 85:+31->162
    //   156: goto +6 -> 162
    //   159: goto -50 -> 109
    //   162: aload_0
    //   163: getfield 75	o/ܚ:ॱ	Lo/গ;
    //   166: astore_3
    //   167: aload_3
    //   168: aload_2
    //   169: aload_1
    //   170: invokevirtual 213	o/গ:ॱ	(Lo/ﾚ;Lo/ڕ;)V
    //   173: goto -140 -> 33
    //   176: bipush 66
    //   178: istore 4
    //   180: goto -51 -> 129
    //   183: getstatic 51	o/ܚ:ॱˊ	I
    //   186: bipush 113
    //   188: iadd
    //   189: istore 4
    //   191: iload 4
    //   193: sipush 128
    //   196: irem
    //   197: putstatic 53	o/ܚ:ˋॱ	I
    //   200: iload 4
    //   202: iconst_2
    //   203: irem
    //   204: ifne +6 -> 210
    //   207: goto +49 -> 256
    //   210: goto -120 -> 90
    //   213: iload 4
    //   215: lookupswitch	default:+25->240, 33:+73->288, 82:+-151->64
    //   240: goto +48 -> 288
    //   243: goto -240 -> 3
    //   246: astore_1
    //   247: aload_1
    //   248: athrow
    //   249: bipush 33
    //   251: istore 4
    //   253: goto -40 -> 213
    //   256: goto -166 -> 90
    //   259: getstatic 51	o/ܚ:ॱˊ	I
    //   262: iconst_1
    //   263: iadd
    //   264: istore 4
    //   266: iload 4
    //   268: sipush 128
    //   271: irem
    //   272: putstatic 53	o/ܚ:ˋॱ	I
    //   275: iload 4
    //   277: iconst_2
    //   278: irem
    //   279: ifne +6 -> 285
    //   282: goto -160 -> 122
    //   285: goto -36 -> 249
    //   288: aload_0
    //   289: getfield 119	o/ܚ:ʼ	Lo/ւ;
    //   292: aload_2
    //   293: aload_3
    //   294: invokevirtual 193	o/ւ:ˋ	(Lo/ﾚ;Lo/र;)V
    //   297: goto -135 -> 162
    // Local variable table:
    //   start	length	slot	name	signature
    //   0	300	0	this	ܚ
    //   0	300	1	paramڕ	ڕ<?>
    //   0	300	2	paramﾚ	ﾚ
    //   0	300	3	paramर	र<?>
    //   9	270	4	i	int
    // Exception table:
    //   from	to	target	type
    //   167	173	61	java/lang/Exception
    //   162	167	246	java/lang/Exception
  }
  
  public void ˋ(ﾚ paramﾚ, र<?> paramर)
  {
    Ϲ.ˋ();
    this.ʼ.ˋ(paramﾚ);
    int i;
    if (!paramर.ॱ())
    {
      break label95;
      try
      {
        paramﾚ = this.ˎ;
        paramﾚ.ˎ(paramर);
      }
      catch (Exception paramﾚ)
      {
        throw paramﾚ;
      }
      i = ˋॱ + 99;
      ॱˊ = i % 128;
      if (i % 2 == 0) {
        return;
      }
      for (;;)
      {
        switch (i)
        {
        default: 
          break label159;
          i = 71;
          break label129;
          return;
          i = ॱˊ + 43;
          ˋॱ = i % 128;
          if (i % 2 == 0) {
            break label187;
          }
          break label174;
          switch (i)
          {
          }
          break;
        case 1: 
          label68:
          label95:
          label129:
          label159:
          this.ˋ.ॱ(paramﾚ, paramर);
          break label179;
          label174:
          i = 1;
        }
      }
    }
    for (;;)
    {
      label179:
      break;
      i = 5;
      break label129;
      label187:
      i = 0;
      break label68;
      this.ˋ.ॱ(paramﾚ, paramर);
      i = 92 / 0;
    }
  }
  
  /* Error */
  public <R> If ˎ(ᔦ paramᔦ, Object paramObject, ﾚ paramﾚ, int paramInt1, int paramInt2, Class<?> paramClass, Class<R> paramClass1, ᴈ paramᴈ, ڹ paramڹ, Map<Class<?>, ɛ<?>> paramMap, boolean paramBoolean1, boolean paramBoolean2, ʄ paramʄ, boolean paramBoolean3, boolean paramBoolean4, boolean paramBoolean5, boolean paramBoolean6, ｌ paramＬ)
  {
    // Byte code:
    //   0: goto +205 -> 205
    //   3: getstatic 53	o/ܚ:ˋॱ	I
    //   6: istore 4
    //   8: iload 4
    //   10: bipush 109
    //   12: iadd
    //   13: istore 4
    //   15: iload 4
    //   17: sipush 128
    //   20: irem
    //   21: putstatic 51	o/ܚ:ॱˊ	I
    //   24: iload 4
    //   26: iconst_2
    //   27: irem
    //   28: ifeq +6 -> 34
    //   31: goto +614 -> 645
    //   34: goto +114 -> 148
    //   37: aload_0
    //   38: getfield 75	o/ܚ:ॱ	Lo/গ;
    //   41: aload 21
    //   43: iload 17
    //   45: invokevirtual 225	o/গ:ˋ	(Lo/ﾚ;Z)Lo/ڕ;
    //   48: astore 22
    //   50: aload 22
    //   52: ifnull +6 -> 58
    //   55: goto +198 -> 253
    //   58: goto +225 -> 283
    //   61: getstatic 51	o/ܚ:ॱˊ	I
    //   64: bipush 65
    //   66: iadd
    //   67: istore 4
    //   69: iload 4
    //   71: sipush 128
    //   74: irem
    //   75: putstatic 53	o/ܚ:ˋॱ	I
    //   78: iload 4
    //   80: iconst_2
    //   81: irem
    //   82: ifne +6 -> 88
    //   85: goto +428 -> 513
    //   88: goto +120 -> 208
    //   91: ldc -29
    //   93: lload 19
    //   95: aload 21
    //   97: invokestatic 229	o/ܚ:ˊ	(Ljava/lang/String;JLo/ﾚ;)V
    //   100: goto +18 -> 118
    //   103: ldc -25
    //   105: lload 19
    //   107: aload 21
    //   109: invokestatic 229	o/ܚ:ˊ	(Ljava/lang/String;JLo/ﾚ;)V
    //   112: goto +286 -> 398
    //   115: goto +453 -> 568
    //   118: new 12	o/ܚ$If
    //   121: dup
    //   122: aload 18
    //   124: aload 22
    //   126: invokespecial 234	o/ܚ$If:<init>	(Lo/ｌ;Lo/ڕ;)V
    //   129: areturn
    //   130: iconst_1
    //   131: istore 4
    //   133: goto +346 -> 479
    //   136: new 12	o/ܚ$If
    //   139: dup
    //   140: aload 18
    //   142: aload 22
    //   144: invokespecial 234	o/ܚ$If:<init>	(Lo/ｌ;Lo/ڕ;)V
    //   147: areturn
    //   148: aload 18
    //   150: aload 22
    //   152: getstatic 239	o/ｬ:ˋ	Lo/ｬ;
    //   155: invokeinterface 244 3 0
    //   160: ldc -128
    //   162: iconst_2
    //   163: invokestatic 248	android/util/Log:isLoggable	(Ljava/lang/String;I)Z
    //   166: ifeq +6 -> 172
    //   169: goto -108 -> 61
    //   172: goto +298 -> 470
    //   175: getstatic 51	o/ܚ:ॱˊ	I
    //   178: bipush 91
    //   180: iadd
    //   181: istore 4
    //   183: iload 4
    //   185: sipush 128
    //   188: irem
    //   189: putstatic 53	o/ܚ:ˋॱ	I
    //   192: iload 4
    //   194: iconst_2
    //   195: irem
    //   196: ifne +6 -> 202
    //   199: goto +179 -> 378
    //   202: goto +198 -> 400
    //   205: goto +311 -> 516
    //   208: ldc -6
    //   210: lload 19
    //   212: aload 21
    //   214: invokestatic 229	o/ܚ:ˊ	(Ljava/lang/String;JLo/ﾚ;)V
    //   217: goto +253 -> 470
    //   220: getstatic 51	o/ܚ:ॱˊ	I
    //   223: bipush 65
    //   225: iadd
    //   226: istore 4
    //   228: iload 4
    //   230: sipush 128
    //   233: irem
    //   234: putstatic 53	o/ܚ:ˋॱ	I
    //   237: iload 4
    //   239: iconst_2
    //   240: irem
    //   241: ifne +6 -> 247
    //   244: goto -114 -> 130
    //   247: goto +260 -> 507
    //   250: astore_1
    //   251: aload_1
    //   252: athrow
    //   253: getstatic 53	o/ܚ:ˋॱ	I
    //   256: bipush 53
    //   258: iadd
    //   259: istore 4
    //   261: iload 4
    //   263: sipush 128
    //   266: irem
    //   267: putstatic 51	o/ܚ:ॱˊ	I
    //   270: iload 4
    //   272: iconst_2
    //   273: irem
    //   274: ifeq +6 -> 280
    //   277: goto -162 -> 115
    //   280: goto +288 -> 568
    //   283: aload_0
    //   284: getfield 94	o/ܚ:ˊ	Lo/ܚ$ˋ;
    //   287: aload 21
    //   289: iload 14
    //   291: iload 15
    //   293: iload 16
    //   295: iload 17
    //   297: invokevirtual 253	o/ܚ$ˋ:ˏ	(Lo/ﾚ;ZZZZ)Lo/ڕ;
    //   300: astore 22
    //   302: aload_0
    //   303: getfield 89	o/ܚ:ʽ	Lo/ܚ$ˊ;
    //   306: aload_1
    //   307: aload_2
    //   308: aload 21
    //   310: aload_3
    //   311: iload 4
    //   313: iload 5
    //   315: aload 6
    //   317: aload 7
    //   319: aload 8
    //   321: aload 9
    //   323: aload 10
    //   325: iload 11
    //   327: iload 12
    //   329: iload 17
    //   331: aload 13
    //   333: aload 22
    //   335: invokevirtual 256	o/ܚ$ˊ:ˋ	(Lo/ᔦ;Ljava/lang/Object;Lo/ڒ;Lo/ﾚ;IILjava/lang/Class;Ljava/lang/Class;Lo/ᴈ;Lo/ڹ;Ljava/util/Map;ZZZLo/ʄ;Lo/צ$If;)Lo/צ;
    //   338: astore_1
    //   339: aload_0
    //   340: getfield 75	o/ܚ:ॱ	Lo/গ;
    //   343: aload 21
    //   345: aload 22
    //   347: invokevirtual 258	o/গ:ˋ	(Lo/ﾚ;Lo/ڕ;)V
    //   350: aload 22
    //   352: aload 18
    //   354: invokevirtual 263	o/ڕ:ॱ	(Lo/ｌ;)V
    //   357: aload 22
    //   359: aload_1
    //   360: invokevirtual 266	o/ڕ:ˋ	(Lo/צ;)V
    //   363: ldc -128
    //   365: iconst_2
    //   366: invokestatic 248	android/util/Log:isLoggable	(Ljava/lang/String;I)Z
    //   369: ifeq +6 -> 375
    //   372: goto -197 -> 175
    //   375: goto -239 -> 136
    //   378: ldc_w 268
    //   381: lload 19
    //   383: aload 21
    //   385: invokestatic 229	o/ܚ:ˊ	(Ljava/lang/String;JLo/ﾚ;)V
    //   388: aconst_null
    //   389: arraylength
    //   390: istore 4
    //   392: goto -256 -> 136
    //   395: astore_1
    //   396: aload_1
    //   397: athrow
    //   398: aconst_null
    //   399: areturn
    //   400: ldc_w 268
    //   403: lload 19
    //   405: aload 21
    //   407: invokestatic 229	o/ܚ:ˊ	(Ljava/lang/String;JLo/ﾚ;)V
    //   410: goto -274 -> 136
    //   413: iload 4
    //   415: lookupswitch	default:+25->440, 12:+-324->91, 26:+-297->118
    //   440: goto -322 -> 118
    //   443: aload 18
    //   445: aload 22
    //   447: getstatic 239	o/ｬ:ˋ	Lo/ｬ;
    //   450: invokeinterface 244 3 0
    //   455: ldc -128
    //   457: iconst_2
    //   458: invokestatic 248	android/util/Log:isLoggable	(Ljava/lang/String;I)Z
    //   461: ifeq +6 -> 467
    //   464: goto -361 -> 103
    //   467: goto -69 -> 398
    //   470: aconst_null
    //   471: areturn
    //   472: bipush 26
    //   474: istore 4
    //   476: goto -63 -> 413
    //   479: iload 4
    //   481: tableswitch	default:+23->504, 0:+109->590, 1:+-38->443
    //   504: goto -61 -> 443
    //   507: iconst_0
    //   508: istore 4
    //   510: goto -31 -> 479
    //   513: goto -305 -> 208
    //   516: invokestatic 200	o/Ϲ:ˋ	()V
    //   519: invokestatic 271	o/ϝ:ˊ	()J
    //   522: lstore 19
    //   524: aload_0
    //   525: getfield 117	o/ܚ:ˏ	Lo/ܪ;
    //   528: aload_2
    //   529: aload_3
    //   530: iload 4
    //   532: iload 5
    //   534: aload 10
    //   536: aload 6
    //   538: aload 7
    //   540: aload 13
    //   542: invokevirtual 274	o/ܪ:ˊ	(Ljava/lang/Object;Lo/ﾚ;IILjava/util/Map;Ljava/lang/Class;Ljava/lang/Class;Lo/ʄ;)Lo/ڒ;
    //   545: astore 21
    //   547: aload_0
    //   548: aload 21
    //   550: iload 14
    //   552: invokespecial 276	o/ܚ:ˋ	(Lo/ﾚ;Z)Lo/र;
    //   555: astore 22
    //   557: aload 22
    //   559: ifnull +6 -> 565
    //   562: goto -342 -> 220
    //   565: goto +59 -> 624
    //   568: aload 22
    //   570: aload 18
    //   572: invokevirtual 263	o/ڕ:ॱ	(Lo/ｌ;)V
    //   575: ldc -128
    //   577: iconst_2
    //   578: invokestatic 248	android/util/Log:isLoggable	(Ljava/lang/String;I)Z
    //   581: ifeq +6 -> 587
    //   584: goto +33 -> 617
    //   587: goto -115 -> 472
    //   590: aload 18
    //   592: aload 22
    //   594: getstatic 239	o/ｬ:ˋ	Lo/ｬ;
    //   597: invokeinterface 244 3 0
    //   602: ldc -128
    //   604: iconst_2
    //   605: invokestatic 248	android/util/Log:isLoggable	(Ljava/lang/String;I)Z
    //   608: ifeq +6 -> 614
    //   611: goto -508 -> 103
    //   614: goto -216 -> 398
    //   617: bipush 12
    //   619: istore 4
    //   621: goto -208 -> 413
    //   624: aload_0
    //   625: aload 21
    //   627: iload 14
    //   629: invokespecial 278	o/ܚ:ॱ	(Lo/ﾚ;Z)Lo/र;
    //   632: astore 22
    //   634: aload 22
    //   636: ifnull +6 -> 642
    //   639: goto -636 -> 3
    //   642: goto -605 -> 37
    //   645: aload 18
    //   647: aload 22
    //   649: getstatic 239	o/ｬ:ˋ	Lo/ｬ;
    //   652: invokeinterface 244 3 0
    //   657: ldc -128
    //   659: iconst_5
    //   660: invokestatic 248	android/util/Log:isLoggable	(Ljava/lang/String;I)Z
    //   663: ifeq +6 -> 669
    //   666: goto -605 -> 61
    //   669: goto -199 -> 470
    // Local variable table:
    //   start	length	slot	name	signature
    //   0	672	0	this	ܚ
    //   0	672	1	paramᔦ	ᔦ
    //   0	672	2	paramObject	Object
    //   0	672	3	paramﾚ	ﾚ
    //   0	672	4	paramInt1	int
    //   0	672	5	paramInt2	int
    //   0	672	6	paramClass	Class<?>
    //   0	672	7	paramClass1	Class<R>
    //   0	672	8	paramᴈ	ᴈ
    //   0	672	9	paramڹ	ڹ
    //   0	672	10	paramMap	Map<Class<?>, ɛ<?>>
    //   0	672	11	paramBoolean1	boolean
    //   0	672	12	paramBoolean2	boolean
    //   0	672	13	paramʄ	ʄ
    //   0	672	14	paramBoolean3	boolean
    //   0	672	15	paramBoolean4	boolean
    //   0	672	16	paramBoolean5	boolean
    //   0	672	17	paramBoolean6	boolean
    //   0	672	18	paramＬ	ｌ
    //   93	311	19	localObject1	Object
    //   522	1	19	l	long
    //   41	585	21	localObject2	Object
    //   48	600	22	localObject3	Object
    // Exception table:
    //   from	to	target	type
    //   3	8	250	java/lang/Exception
    //   516	519	250	java/lang/Exception
    //   519	524	250	java/lang/Exception
    //   524	557	250	java/lang/Exception
    //   15	24	395	java/lang/Exception
  }
  
  /* Error */
  public void ˎ(ڕ<?> paramڕ, ﾚ paramﾚ)
  {
    // Byte code:
    //   0: goto +103 -> 103
    //   3: invokestatic 200	o/Ϲ:ˋ	()V
    //   6: aload_0
    //   7: getfield 75	o/ܚ:ॱ	Lo/গ;
    //   10: aload_2
    //   11: aload_1
    //   12: invokevirtual 213	o/গ:ॱ	(Lo/ﾚ;Lo/ڕ;)V
    //   15: new 169	java/lang/NullPointerException
    //   18: dup
    //   19: invokespecial 170	java/lang/NullPointerException:<init>	()V
    //   22: athrow
    //   23: iload_3
    //   24: tableswitch	default:+24->48, 0:+-21->3, 1:+57->81
    //   48: goto +33 -> 81
    //   51: getstatic 53	o/ܚ:ˋॱ	I
    //   54: bipush 101
    //   56: iadd
    //   57: istore_3
    //   58: iload_3
    //   59: sipush 128
    //   62: irem
    //   63: putstatic 51	o/ܚ:ॱˊ	I
    //   66: iload_3
    //   67: iconst_2
    //   68: irem
    //   69: ifeq +6 -> 75
    //   72: goto +34 -> 106
    //   75: goto +23 -> 98
    //   78: astore_1
    //   79: aload_1
    //   80: athrow
    //   81: invokestatic 200	o/Ϲ:ˋ	()V
    //   84: aload_0
    //   85: getfield 75	o/ܚ:ॱ	Lo/গ;
    //   88: astore 4
    //   90: aload 4
    //   92: aload_2
    //   93: aload_1
    //   94: invokevirtual 213	o/গ:ॱ	(Lo/ﾚ;Lo/ڕ;)V
    //   97: return
    //   98: iconst_1
    //   99: istore_3
    //   100: goto -77 -> 23
    //   103: goto -52 -> 51
    //   106: iconst_0
    //   107: istore_3
    //   108: goto -85 -> 23
    // Local variable table:
    //   start	length	slot	name	signature
    //   0	111	0	this	ܚ
    //   0	111	1	paramڕ	ڕ<?>
    //   0	111	2	paramﾚ	ﾚ
    //   23	85	3	i	int
    //   88	3	4	localগ	গ
    // Exception table:
    //   from	to	target	type
    //   81	84	78	java/lang/Exception
    //   84	90	78	java/lang/Exception
    //   90	97	78	java/lang/Exception
  }
  
  public void ˏ(ก<?> paramก)
  {
    for (;;)
    {
      int i;
      switch (i)
      {
      default: 
        break label100;
        return;
        i = ˋॱ + 97;
        ॱˊ = i % 128;
        if (i % 2 == 0)
        {
          break label111;
          i = 0;
          continue;
          return;
          for (i = 1;; i = 0)
          {
            switch (i)
            {
            }
            break;
          }
        }
      case 1: 
        throw new IllegalArgumentException("Cannot release anything but an EngineResource");
      case 0: 
        for (;;)
        {
          label59:
          label65:
          label95:
          label100:
          label111:
          Ϲ.ˋ();
          if ((paramก instanceof र)) {
            break label59;
          }
          break label200;
          i = ˋॱ + 95;
          ॱˊ = i % 128;
          if (i % 2 == 0)
          {
            break label181;
            i = ˋॱ + 45;
            ॱˊ = i % 128;
            if (i % 2 != 0) {
              break label65;
            }
            break label95;
          }
          for (;;)
          {
            label181:
            ((र)paramก).ʼ();
            break;
          }
          break;
        }
        label200:
        i = 1;
      }
    }
  }
  
  public static class If
  {
    private final ｌ ˊ;
    private final ڕ<?> ॱ;
    
    If(ｌ paramＬ, ڕ<?> paramڕ)
    {
      this.ˊ = paramＬ;
      this.ॱ = paramڕ;
    }
    
    public void ˏ()
    {
      this.ॱ.ˊ(this.ˊ);
    }
  }
  
  static class if
    implements צ.iF
  {
    private volatile ᔫ ˊ;
    private final ᔫ.If ॱ;
    
    if(ᔫ.If paramIf)
    {
      this.ॱ = paramIf;
    }
    
    public ᔫ ˏ()
    {
      if (this.ˊ == null) {
        try
        {
          if (this.ˊ == null) {
            this.ˊ = this.ॱ.ˎ();
          }
          if (this.ˊ == null) {
            this.ˊ = new ᓘ();
          }
        }
        finally {}
      }
      return this.ˊ;
    }
  }
  
  static class ˊ
  {
    final צ.iF ˊ;
    private int ˏ;
    final 丨.if<צ<?>> ॱ = п.ˊ(150, new п.If()
    {
      public צ<?> ˋ()
      {
        return new צ(ܚ.ˊ.this.ˊ, ܚ.ˊ.this.ॱ);
      }
    });
    
    ˊ(צ.iF paramIF)
    {
      this.ˊ = paramIF;
    }
    
    <R> צ<R> ˋ(ᔦ paramᔦ, Object paramObject, ڒ paramڒ, ﾚ paramﾚ, int paramInt1, int paramInt2, Class<?> paramClass, Class<R> paramClass1, ᴈ paramᴈ, ڹ paramڹ, Map<Class<?>, ɛ<?>> paramMap, boolean paramBoolean1, boolean paramBoolean2, boolean paramBoolean3, ʄ paramʄ, צ.If<R> paramIf)
    {
      צ localצ = (צ)ϵ.ˎ((צ)this.ॱ.ˊ());
      int i = this.ˏ;
      this.ˏ = (i + 1);
      return localצ.ॱ(paramᔦ, paramObject, paramڒ, paramﾚ, paramInt1, paramInt2, paramClass, paramClass1, paramᴈ, paramڹ, paramMap, paramBoolean1, paramBoolean2, paramBoolean3, paramʄ, paramIf, i);
    }
  }
  
  static class ˋ
  {
    final 丨.if<ڕ<?>> ʼ = п.ˊ(150, new п.If()
    {
      public ڕ<?> ˋ()
      {
        return new ڕ(ܚ.ˋ.this.ˎ, ܚ.ˋ.this.ˏ, ܚ.ˋ.this.ॱ, ܚ.ˋ.this.ˊ, ܚ.ˋ.this.ˋ, ܚ.ˋ.this.ʼ);
      }
    });
    final Ⅴ ˊ;
    final ۊ ˋ;
    final Ⅴ ˎ;
    final Ⅴ ˏ;
    final Ⅴ ॱ;
    
    ˋ(Ⅴ paramⅤ1, Ⅴ paramⅤ2, Ⅴ paramⅤ3, Ⅴ paramⅤ4, ۊ paramۊ)
    {
      this.ˎ = paramⅤ1;
      this.ˏ = paramⅤ2;
      this.ॱ = paramⅤ3;
      this.ˊ = paramⅤ4;
      this.ˋ = paramۊ;
    }
    
    <R> ڕ<R> ˏ(ﾚ paramﾚ, boolean paramBoolean1, boolean paramBoolean2, boolean paramBoolean3, boolean paramBoolean4)
    {
      return ((ڕ)ϵ.ˎ((ڕ)this.ʼ.ˊ())).ॱ(paramﾚ, paramBoolean1, paramBoolean2, paramBoolean3, paramBoolean4);
    }
  }
}
