package o;

class ᒌ
  implements ڋ, ʢ.If<Object>, ڋ.ˊ
{
  private static char[] ʻ = { 300, 335, 340, 345, 334, 331, 330, 262, 329, 341, 333, 347, 344, 346, 327, 274, 337, 351, 288 };
  private static boolean ʽ;
  private static int ˊॱ = 0;
  private static boolean ˋॱ;
  private static int ͺ = 1;
  private static int ॱॱ = 230;
  private ԁ ʼ;
  private final ب<?> ˊ;
  private final ڋ.ˊ ˋ;
  private int ˎ;
  private Object ˏ;
  private ח ॱ;
  private volatile ﾜ.iF<?> ᐝ;
  
  static
  {
    ˋॱ = true;
    ʽ = true;
  }
  
  ᒌ(ب<?> paramب, ڋ.ˊ paramˊ) {}
  
  /* Error */
  private boolean ˊ()
  {
    // Byte code:
    //   0: goto +99 -> 99
    //   3: iconst_1
    //   4: istore_2
    //   5: goto +91 -> 96
    //   8: aload_0
    //   9: getfield 84	o/ᒌ:ˎ	I
    //   12: aload_0
    //   13: getfield 75	o/ᒌ:ˊ	Lo/ب;
    //   16: invokevirtual 90	o/ب:ॱˊ	()Ljava/util/List;
    //   19: invokeinterface 96 1 0
    //   24: if_icmpge +6 -> 30
    //   27: goto +104 -> 131
    //   30: goto +96 -> 126
    //   33: iload_1
    //   34: tableswitch	default:+22->56, 0:+-31->3, 1:+102->136
    //   56: goto -53 -> 3
    //   59: astore_3
    //   60: aload_3
    //   61: athrow
    //   62: iload_2
    //   63: ireturn
    //   64: astore_3
    //   65: aload_3
    //   66: athrow
    //   67: getstatic 41	o/ᒌ:ͺ	I
    //   70: bipush 89
    //   72: iadd
    //   73: istore_1
    //   74: iload_1
    //   75: sipush 128
    //   78: irem
    //   79: putstatic 39	o/ᒌ:ˊॱ	I
    //   82: iload_1
    //   83: iconst_2
    //   84: irem
    //   85: ifeq +6 -> 91
    //   88: goto -26 -> 62
    //   91: iload_2
    //   92: ireturn
    //   93: goto -85 -> 8
    //   96: goto -29 -> 67
    //   99: getstatic 39	o/ᒌ:ˊॱ	I
    //   102: bipush 119
    //   104: iadd
    //   105: istore_1
    //   106: iload_1
    //   107: sipush 128
    //   110: irem
    //   111: putstatic 41	o/ᒌ:ͺ	I
    //   114: iload_1
    //   115: iconst_2
    //   116: irem
    //   117: ifne +6 -> 123
    //   120: goto -27 -> 93
    //   123: goto -115 -> 8
    //   126: iconst_1
    //   127: istore_1
    //   128: goto -95 -> 33
    //   131: iconst_0
    //   132: istore_1
    //   133: goto -100 -> 33
    //   136: iconst_0
    //   137: istore_2
    //   138: goto -42 -> 96
    // Local variable table:
    //   start	length	slot	name	signature
    //   0	141	0	this	ᒌ
    //   33	100	1	i	int
    //   4	134	2	bool	boolean
    //   59	2	3	localException1	Exception
    //   64	2	3	localException2	Exception
    // Exception table:
    //   from	to	target	type
    //   106	114	59	java/lang/Exception
    //   99	106	64	java/lang/Exception
    //   106	114	64	java/lang/Exception
  }
  
  private static String ˎ(char[] paramArrayOfChar, byte[] paramArrayOfByte, int[] paramArrayOfInt, int paramInt)
  {
    break label106;
    break label259;
    label6:
    break label516;
    int j = 65;
    label16:
    label28:
    label55:
    label58:
    int i;
    char[] arrayOfChar;
    int m;
    int k;
    if (!ʽ)
    {
      break label425;
      switch (j)
      {
      default: 
        break;
        break label312;
        paramArrayOfByte[i] = ((char)(arrayOfChar[(paramArrayOfChar[(m % 0 % i)] >>> paramInt)] / k));
        i += 24;
        break;
      }
      label103:
      label106:
      label167:
      label238:
      label253:
      label259:
      label312:
      for (;;)
      {
        if (i < m) {
          break label503;
        }
        break label253;
        break label6;
        i = ˊॱ + 33;
        ͺ = i % 128;
        if (i % 2 == 0) {
          break;
        }
        break;
        for (;;)
        {
          paramArrayOfByte[i] = ((char)(arrayOfChar[(paramArrayOfChar[(m - 1 - i)] - paramInt)] - k));
          i += 1;
          break label412;
          switch (j)
          {
          default: 
            break label238;
            return new String(paramArrayOfChar);
            j = ͺ + 71;
            ˊॱ = j % 128;
            if (j % 2 != 0) {
              break label58;
            }
          }
        }
        return new String(paramArrayOfChar);
        j = 0;
        break label315;
        j = 0;
        break label28;
        arrayOfChar = ʻ;
        k = ॱॱ;
        if (ˋॱ) {
          break label343;
        }
        break label16;
        paramArrayOfChar[i] = ((char)(arrayOfChar[(paramArrayOfInt[(m - 1 - i)] - paramInt)] - k));
        i += 1;
      }
    }
    for (;;)
    {
      switch (j)
      {
      case 0: 
      default: 
        label315:
        break;
        label343:
        m = paramArrayOfByte.length;
        paramArrayOfChar = new char[m];
        i = 0;
        break;
      }
      for (;;)
      {
        m = paramArrayOfChar.length;
        paramArrayOfByte = new char[m];
        i = 0;
        break label412;
        i = ͺ + 13;
        ˊॱ = i % 128;
        if (i % 2 == 0)
        {
          continue;
          return new String(paramArrayOfByte);
          label412:
          if (i < m) {
            break;
          }
          break label560;
          label425:
          m = paramArrayOfInt.length;
          paramArrayOfChar = new char[m];
          i = 0;
          break label473;
        }
      }
      for (;;)
      {
        j = ˊॱ + 117;
        ͺ = j % 128;
        if (j % 2 == 0) {
          break label103;
        }
        break;
        label473:
        j = ͺ + 111;
        ˊॱ = j % 128;
        if (j % 2 != 0) {
          break label55;
        }
        break label312;
        label503:
        j = 1;
        break label28;
        for (;;)
        {
          j = 57;
          break label167;
          label516:
          if (i < m) {
            break;
          }
        }
        paramArrayOfChar[i] = ((char)(arrayOfChar[(paramArrayOfByte[(m - 1 - i)] + paramInt)] - k));
        i += 1;
      }
      label560:
      j = 1;
    }
  }
  
  /* Error */
  private void ˏ(Object paramObject)
  {
    // Byte code:
    //   0: goto +350 -> 350
    //   3: goto +344 -> 347
    //   6: aload_0
    //   7: getfield 105	o/ᒌ:ᐝ	Lo/ﾜ$iF;
    //   10: getfield 110	o/ﾜ$iF:ˋ	Lo/ʢ;
    //   13: invokeinterface 114 1 0
    //   18: goto +454 -> 472
    //   21: astore_1
    //   22: aload_1
    //   23: athrow
    //   24: astore_1
    //   25: aload_0
    //   26: getfield 105	o/ᒌ:ᐝ	Lo/ﾜ$iF;
    //   29: getfield 110	o/ﾜ$iF:ˋ	Lo/ʢ;
    //   32: invokeinterface 114 1 0
    //   37: aload_1
    //   38: athrow
    //   39: ldc 116
    //   41: new 118	java/lang/StringBuilder
    //   44: dup
    //   45: invokespecial 119	java/lang/StringBuilder:<init>	()V
    //   48: aconst_null
    //   49: bipush 40
    //   51: newarray byte
    //   53: dup
    //   54: iconst_0
    //   55: ldc 120
    //   57: bastore
    //   58: dup
    //   59: iconst_1
    //   60: ldc 121
    //   62: bastore
    //   63: dup
    //   64: iconst_2
    //   65: ldc 122
    //   67: bastore
    //   68: dup
    //   69: iconst_3
    //   70: ldc 123
    //   72: bastore
    //   73: dup
    //   74: iconst_4
    //   75: ldc 124
    //   77: bastore
    //   78: dup
    //   79: iconst_5
    //   80: ldc 120
    //   82: bastore
    //   83: dup
    //   84: bipush 6
    //   86: ldc 125
    //   88: bastore
    //   89: dup
    //   90: bipush 7
    //   92: ldc 123
    //   94: bastore
    //   95: dup
    //   96: bipush 8
    //   98: ldc 126
    //   100: bastore
    //   101: dup
    //   102: bipush 9
    //   104: ldc 127
    //   106: bastore
    //   107: dup
    //   108: bipush 10
    //   110: ldc -128
    //   112: bastore
    //   113: dup
    //   114: bipush 11
    //   116: ldc 127
    //   118: bastore
    //   119: dup
    //   120: bipush 12
    //   122: ldc 120
    //   124: bastore
    //   125: dup
    //   126: bipush 13
    //   128: ldc -127
    //   130: bastore
    //   131: dup
    //   132: bipush 14
    //   134: ldc -126
    //   136: bastore
    //   137: dup
    //   138: bipush 15
    //   140: ldc 120
    //   142: bastore
    //   143: dup
    //   144: bipush 16
    //   146: ldc 123
    //   148: bastore
    //   149: dup
    //   150: bipush 17
    //   152: ldc 127
    //   154: bastore
    //   155: dup
    //   156: bipush 18
    //   158: ldc -125
    //   160: bastore
    //   161: dup
    //   162: bipush 19
    //   164: ldc -124
    //   166: bastore
    //   167: dup
    //   168: bipush 20
    //   170: ldc -127
    //   172: bastore
    //   173: dup
    //   174: bipush 21
    //   176: ldc -123
    //   178: bastore
    //   179: dup
    //   180: bipush 22
    //   182: ldc 120
    //   184: bastore
    //   185: dup
    //   186: bipush 23
    //   188: ldc -122
    //   190: bastore
    //   191: dup
    //   192: bipush 24
    //   194: ldc -121
    //   196: bastore
    //   197: dup
    //   198: bipush 25
    //   200: ldc -120
    //   202: bastore
    //   203: dup
    //   204: bipush 26
    //   206: ldc -119
    //   208: bastore
    //   209: dup
    //   210: bipush 27
    //   212: ldc -127
    //   214: bastore
    //   215: dup
    //   216: bipush 28
    //   218: ldc 127
    //   220: bastore
    //   221: dup
    //   222: bipush 29
    //   224: ldc -121
    //   226: bastore
    //   227: dup
    //   228: bipush 30
    //   230: ldc 123
    //   232: bastore
    //   233: dup
    //   234: bipush 31
    //   236: ldc 120
    //   238: bastore
    //   239: dup
    //   240: bipush 32
    //   242: ldc -119
    //   244: bastore
    //   245: dup
    //   246: bipush 33
    //   248: ldc 123
    //   250: bastore
    //   251: dup
    //   252: bipush 34
    //   254: ldc 126
    //   256: bastore
    //   257: dup
    //   258: bipush 35
    //   260: ldc -123
    //   262: bastore
    //   263: dup
    //   264: bipush 36
    //   266: ldc -120
    //   268: bastore
    //   269: dup
    //   270: bipush 37
    //   272: ldc -121
    //   274: bastore
    //   275: dup
    //   276: bipush 38
    //   278: ldc -120
    //   280: bastore
    //   281: dup
    //   282: bipush 39
    //   284: ldc -118
    //   286: bastore
    //   287: aconst_null
    //   288: bipush 127
    //   290: invokestatic 140	o/ᒌ:ˎ	([C[B[II)Ljava/lang/String;
    //   293: invokevirtual 144	java/lang/String:intern	()Ljava/lang/String;
    //   296: invokevirtual 148	java/lang/StringBuilder:append	(Ljava/lang/String;)Ljava/lang/StringBuilder;
    //   299: aload_0
    //   300: getfield 150	o/ᒌ:ʼ	Lo/ԁ;
    //   303: invokevirtual 153	java/lang/StringBuilder:append	(Ljava/lang/Object;)Ljava/lang/StringBuilder;
    //   306: ldc -101
    //   308: invokevirtual 148	java/lang/StringBuilder:append	(Ljava/lang/String;)Ljava/lang/StringBuilder;
    //   311: aload_1
    //   312: invokevirtual 153	java/lang/StringBuilder:append	(Ljava/lang/Object;)Ljava/lang/StringBuilder;
    //   315: ldc -99
    //   317: invokevirtual 148	java/lang/StringBuilder:append	(Ljava/lang/String;)Ljava/lang/StringBuilder;
    //   320: aload 6
    //   322: invokevirtual 153	java/lang/StringBuilder:append	(Ljava/lang/Object;)Ljava/lang/StringBuilder;
    //   325: ldc -97
    //   327: invokevirtual 148	java/lang/StringBuilder:append	(Ljava/lang/String;)Ljava/lang/StringBuilder;
    //   330: lload_3
    //   331: invokestatic 164	o/ϝ:ˏ	(J)D
    //   334: invokevirtual 167	java/lang/StringBuilder:append	(D)Ljava/lang/StringBuilder;
    //   337: invokevirtual 170	java/lang/StringBuilder:toString	()Ljava/lang/String;
    //   340: invokestatic 176	android/util/Log:v	(Ljava/lang/String;Ljava/lang/String;)I
    //   343: pop
    //   344: goto -338 -> 6
    //   347: goto +98 -> 445
    //   350: invokestatic 179	o/ϝ:ˊ	()J
    //   353: lstore_3
    //   354: aload_0
    //   355: getfield 75	o/ᒌ:ˊ	Lo/ب;
    //   358: aload_1
    //   359: invokevirtual 182	o/ب:ˏ	(Ljava/lang/Object;)Lo/ﾐ;
    //   362: astore 6
    //   364: new 184	o/ٵ
    //   367: dup
    //   368: aload 6
    //   370: aload_1
    //   371: aload_0
    //   372: getfield 75	o/ᒌ:ˊ	Lo/ب;
    //   375: invokevirtual 187	o/ب:ˋ	()Lo/ʄ;
    //   378: invokespecial 190	o/ٵ:<init>	(Lo/ﾐ;Ljava/lang/Object;Lo/ʄ;)V
    //   381: astore 7
    //   383: aload_0
    //   384: new 192	o/ԁ
    //   387: dup
    //   388: aload_0
    //   389: getfield 105	o/ᒌ:ᐝ	Lo/ﾜ$iF;
    //   392: getfield 195	o/ﾜ$iF:ˊ	Lo/ﾚ;
    //   395: aload_0
    //   396: getfield 75	o/ᒌ:ˊ	Lo/ب;
    //   399: invokevirtual 198	o/ب:ʽ	()Lo/ﾚ;
    //   402: invokespecial 201	o/ԁ:<init>	(Lo/ﾚ;Lo/ﾚ;)V
    //   405: putfield 150	o/ᒌ:ʼ	Lo/ԁ;
    //   408: aload_0
    //   409: getfield 75	o/ᒌ:ˊ	Lo/ب;
    //   412: invokevirtual 204	o/ب:ॱ	()Lo/ᔫ;
    //   415: aload_0
    //   416: getfield 150	o/ᒌ:ʼ	Lo/ԁ;
    //   419: aload 7
    //   421: invokeinterface 209 3 0
    //   426: ldc 116
    //   428: iconst_2
    //   429: invokestatic 213	android/util/Log:isLoggable	(Ljava/lang/String;I)Z
    //   432: istore 5
    //   434: iload 5
    //   436: ifeq +6 -> 442
    //   439: goto -400 -> 39
    //   442: goto -436 -> 6
    //   445: aload_0
    //   446: new 215	o/ח
    //   449: dup
    //   450: aload_0
    //   451: getfield 105	o/ᒌ:ᐝ	Lo/ﾜ$iF;
    //   454: getfield 195	o/ﾜ$iF:ˊ	Lo/ﾚ;
    //   457: invokestatic 221	java/util/Collections:singletonList	(Ljava/lang/Object;)Ljava/util/List;
    //   460: aload_0
    //   461: getfield 75	o/ᒌ:ˊ	Lo/ب;
    //   464: aload_0
    //   465: invokespecial 224	o/ח:<init>	(Ljava/util/List;Lo/ب;Lo/ڋ$ˊ;)V
    //   468: putfield 226	o/ᒌ:ॱ	Lo/ח;
    //   471: return
    //   472: getstatic 39	o/ᒌ:ˊॱ	I
    //   475: bipush 83
    //   477: iadd
    //   478: istore_2
    //   479: iload_2
    //   480: sipush 128
    //   483: irem
    //   484: putstatic 41	o/ᒌ:ͺ	I
    //   487: iload_2
    //   488: iconst_2
    //   489: irem
    //   490: ifne +6 -> 496
    //   493: goto -490 -> 3
    //   496: goto -149 -> 347
    // Local variable table:
    //   start	length	slot	name	signature
    //   0	499	0	this	ᒌ
    //   0	499	1	paramObject	Object
    //   478	12	2	i	int
    //   330	1	3	localObject1	Object
    //   353	1	3	l	long
    //   432	3	5	bool	boolean
    //   320	49	6	localObject2	Object
    //   381	39	7	localٵ	ٵ
    // Exception table:
    //   from	to	target	type
    //   350	354	21	java/lang/Exception
    //   39	344	24	finally
    //   354	434	24	finally
  }
  
  /* Error */
  public void ˊ(ﾚ paramﾚ1, Object paramObject, ʢ<?> paramʢ, ｬ paramｬ, ﾚ paramﾚ2)
  {
    // Byte code:
    //   0: goto +103 -> 103
    //   3: aload_0
    //   4: getfield 77	o/ᒌ:ˋ	Lo/ڋ$ˊ;
    //   7: aload_1
    //   8: aload_2
    //   9: aload_3
    //   10: aload_0
    //   11: getfield 105	o/ᒌ:ᐝ	Lo/ﾜ$iF;
    //   14: getfield 110	o/ﾜ$iF:ˋ	Lo/ʢ;
    //   17: invokeinterface 230 1 0
    //   22: aload_1
    //   23: invokeinterface 232 6 0
    //   28: goto +12 -> 40
    //   31: goto -28 -> 3
    //   34: astore_1
    //   35: aload_1
    //   36: athrow
    //   37: astore_1
    //   38: aload_1
    //   39: athrow
    //   40: getstatic 41	o/ᒌ:ͺ	I
    //   43: bipush 125
    //   45: iadd
    //   46: istore 6
    //   48: iload 6
    //   50: sipush 128
    //   53: irem
    //   54: putstatic 39	o/ᒌ:ˊॱ	I
    //   57: iload 6
    //   59: iconst_2
    //   60: irem
    //   61: ifeq +6 -> 67
    //   64: goto +4 -> 68
    //   67: return
    //   68: return
    //   69: getstatic 41	o/ᒌ:ͺ	I
    //   72: istore 6
    //   74: iload 6
    //   76: bipush 93
    //   78: iadd
    //   79: istore 6
    //   81: iload 6
    //   83: sipush 128
    //   86: irem
    //   87: putstatic 39	o/ᒌ:ˊॱ	I
    //   90: iload 6
    //   92: iconst_2
    //   93: irem
    //   94: ifeq +6 -> 100
    //   97: goto -66 -> 31
    //   100: goto -97 -> 3
    //   103: goto -34 -> 69
    // Local variable table:
    //   start	length	slot	name	signature
    //   0	106	0	this	ᒌ
    //   0	106	1	paramﾚ1	ﾚ
    //   0	106	2	paramObject	Object
    //   0	106	3	paramʢ	ʢ<?>
    //   0	106	4	paramｬ	ｬ
    //   0	106	5	paramﾚ2	ﾚ
    //   46	48	6	i	int
    // Exception table:
    //   from	to	target	type
    //   81	90	34	java/lang/Exception
    //   69	74	37	java/lang/Exception
  }
  
  /* Error */
  public void ˋ()
  {
    // Byte code:
    //   0: goto +10 -> 10
    //   3: bipush 12
    //   5: istore_1
    //   6: goto +64 -> 70
    //   9: return
    //   10: goto +101 -> 111
    //   13: goto +149 -> 162
    //   16: getstatic 41	o/ᒌ:ͺ	I
    //   19: bipush 115
    //   21: iadd
    //   22: istore_1
    //   23: iload_1
    //   24: sipush 128
    //   27: irem
    //   28: putstatic 39	o/ᒌ:ˊॱ	I
    //   31: iload_1
    //   32: iconst_2
    //   33: irem
    //   34: ifeq +6 -> 40
    //   37: goto +143 -> 180
    //   40: goto +119 -> 159
    //   43: getstatic 39	o/ᒌ:ˊॱ	I
    //   46: bipush 121
    //   48: iadd
    //   49: istore_1
    //   50: iload_1
    //   51: sipush 128
    //   54: irem
    //   55: putstatic 41	o/ᒌ:ͺ	I
    //   58: iload_1
    //   59: iconst_2
    //   60: irem
    //   61: ifne +6 -> 67
    //   64: goto +35 -> 99
    //   67: goto +59 -> 126
    //   70: iload_1
    //   71: lookupswitch	default:+25->96, 12:+61->132, 98:+34->105
    //   96: goto +36 -> 132
    //   99: bipush 12
    //   101: istore_1
    //   102: goto +89 -> 191
    //   105: goto -62 -> 43
    //   108: astore_2
    //   109: aload_2
    //   110: athrow
    //   111: aload_0
    //   112: getfield 105	o/ᒌ:ᐝ	Lo/ﾜ$iF;
    //   115: astore_2
    //   116: aload_2
    //   117: ifnull +6 -> 123
    //   120: goto -117 -> 3
    //   123: goto +51 -> 174
    //   126: bipush 21
    //   128: istore_1
    //   129: goto +62 -> 191
    //   132: getstatic 41	o/ᒌ:ͺ	I
    //   135: bipush 75
    //   137: iadd
    //   138: istore_1
    //   139: iload_1
    //   140: sipush 128
    //   143: irem
    //   144: putstatic 39	o/ᒌ:ˊॱ	I
    //   147: iload_1
    //   148: iconst_2
    //   149: irem
    //   150: ifeq +6 -> 156
    //   153: goto -140 -> 13
    //   156: goto +6 -> 162
    //   159: goto -54 -> 105
    //   162: aload_2
    //   163: getfield 110	o/ﾜ$iF:ˋ	Lo/ʢ;
    //   166: invokeinterface 235 1 0
    //   171: goto -155 -> 16
    //   174: bipush 98
    //   176: istore_1
    //   177: goto -107 -> 70
    //   180: goto -21 -> 159
    //   183: new 237	java/lang/NullPointerException
    //   186: dup
    //   187: invokespecial 238	java/lang/NullPointerException:<init>	()V
    //   190: athrow
    //   191: iload_1
    //   192: lookupswitch	default:+28->220, 12:+-9->183, 21:+-183->9
    //   220: return
    // Local variable table:
    //   start	length	slot	name	signature
    //   0	221	0	this	ᒌ
    //   5	187	1	i	int
    //   108	2	2	localException	Exception
    //   115	48	2	localIF	ﾜ.iF
    // Exception table:
    //   from	to	target	type
    //   132	139	108	java/lang/Exception
    //   139	147	108	java/lang/Exception
  }
  
  /* Error */
  public void ˋ(Object paramObject)
  {
    // Byte code:
    //   0: goto +54 -> 54
    //   3: iconst_0
    //   4: istore_2
    //   5: goto +219 -> 224
    //   8: astore_1
    //   9: aload_1
    //   10: athrow
    //   11: bipush 6
    //   13: istore_2
    //   14: goto +237 -> 251
    //   17: astore_1
    //   18: aload_1
    //   19: athrow
    //   20: iconst_1
    //   21: istore_2
    //   22: goto +202 -> 224
    //   25: return
    //   26: getstatic 39	o/ᒌ:ˊॱ	I
    //   29: istore_2
    //   30: iload_2
    //   31: iconst_3
    //   32: iadd
    //   33: istore_2
    //   34: iload_2
    //   35: sipush 128
    //   38: irem
    //   39: putstatic 41	o/ᒌ:ͺ	I
    //   42: iload_2
    //   43: iconst_2
    //   44: irem
    //   45: ifne +6 -> 51
    //   48: goto +126 -> 174
    //   51: goto +24 -> 75
    //   54: aload_0
    //   55: getfield 75	o/ᒌ:ˊ	Lo/ب;
    //   58: invokevirtual 241	o/ب:ˊ	()Lo/ڹ;
    //   61: astore_3
    //   62: aload_1
    //   63: ifnull +6 -> 69
    //   66: goto +10 -> 76
    //   69: goto +112 -> 181
    //   72: goto +85 -> 157
    //   75: return
    //   76: aload_3
    //   77: aload_0
    //   78: getfield 105	o/ᒌ:ᐝ	Lo/ﾜ$iF;
    //   81: getfield 110	o/ﾜ$iF:ˋ	Lo/ʢ;
    //   84: invokeinterface 230 1 0
    //   89: invokevirtual 246	o/ڹ:ˊ	(Lo/ｬ;)Z
    //   92: ifeq +6 -> 98
    //   95: goto +80 -> 175
    //   98: goto -87 -> 11
    //   101: getstatic 41	o/ᒌ:ͺ	I
    //   104: istore_2
    //   105: iload_2
    //   106: bipush 43
    //   108: iadd
    //   109: istore_2
    //   110: iload_2
    //   111: sipush 128
    //   114: irem
    //   115: putstatic 39	o/ᒌ:ˊॱ	I
    //   118: iload_2
    //   119: iconst_2
    //   120: irem
    //   121: ifeq +6 -> 127
    //   124: goto -52 -> 72
    //   127: goto +30 -> 157
    //   130: getstatic 39	o/ᒌ:ˊॱ	I
    //   133: bipush 29
    //   135: iadd
    //   136: istore_2
    //   137: iload_2
    //   138: sipush 128
    //   141: irem
    //   142: putstatic 41	o/ᒌ:ͺ	I
    //   145: iload_2
    //   146: iconst_2
    //   147: irem
    //   148: ifne +6 -> 154
    //   151: goto -148 -> 3
    //   154: goto -134 -> 20
    //   157: aload_0
    //   158: aload_1
    //   159: putfield 248	o/ᒌ:ˏ	Ljava/lang/Object;
    //   162: aload_0
    //   163: getfield 77	o/ᒌ:ˋ	Lo/ڋ$ˊ;
    //   166: invokeinterface 249 1 0
    //   171: goto -41 -> 130
    //   174: return
    //   175: bipush 59
    //   177: istore_2
    //   178: goto +73 -> 251
    //   181: aload_0
    //   182: getfield 77	o/ᒌ:ˋ	Lo/ڋ$ˊ;
    //   185: aload_0
    //   186: getfield 105	o/ᒌ:ᐝ	Lo/ﾜ$iF;
    //   189: getfield 195	o/ﾜ$iF:ˊ	Lo/ﾚ;
    //   192: aload_1
    //   193: aload_0
    //   194: getfield 105	o/ᒌ:ᐝ	Lo/ﾜ$iF;
    //   197: getfield 110	o/ﾜ$iF:ˋ	Lo/ʢ;
    //   200: aload_0
    //   201: getfield 105	o/ᒌ:ᐝ	Lo/ﾜ$iF;
    //   204: getfield 110	o/ﾜ$iF:ˋ	Lo/ʢ;
    //   207: invokeinterface 230 1 0
    //   212: aload_0
    //   213: getfield 150	o/ᒌ:ʼ	Lo/ԁ;
    //   216: invokeinterface 232 6 0
    //   221: goto -195 -> 26
    //   224: iload_2
    //   225: tableswitch	default:+23->248, 0:+58->283, 1:+-200->25
    //   248: goto -223 -> 25
    //   251: iload_2
    //   252: lookupswitch	default:+28->280, 6:+-71->181, 59:+-151->101
    //   280: goto -179 -> 101
    //   283: return
    // Local variable table:
    //   start	length	slot	name	signature
    //   0	284	0	this	ᒌ
    //   0	284	1	paramObject	Object
    //   4	248	2	i	int
    //   61	16	3	localڹ	ڹ
    // Exception table:
    //   from	to	target	type
    //   26	30	8	java/lang/Exception
    //   101	105	8	java/lang/Exception
    //   34	42	17	java/lang/Exception
    //   110	118	17	java/lang/Exception
  }
  
  /* Error */
  public boolean ˎ()
  {
    // Byte code:
    //   0: goto +380 -> 380
    //   3: aload_0
    //   4: aconst_null
    //   5: putfield 226	o/ᒌ:ॱ	Lo/ח;
    //   8: aload_0
    //   9: aconst_null
    //   10: putfield 105	o/ᒌ:ᐝ	Lo/ﾜ$iF;
    //   13: iconst_0
    //   14: istore_2
    //   15: goto +123 -> 138
    //   18: aload_0
    //   19: getfield 226	o/ᒌ:ॱ	Lo/ח;
    //   22: invokevirtual 251	o/ח:ˎ	()Z
    //   25: ifeq +6 -> 31
    //   28: goto +398 -> 426
    //   31: goto -28 -> 3
    //   34: iconst_1
    //   35: ireturn
    //   36: astore_3
    //   37: aload_3
    //   38: athrow
    //   39: iload_1
    //   40: tableswitch	default:+24->64, 0:+253->293, 1:+98->138
    //   64: goto +74 -> 138
    //   67: astore_3
    //   68: aload_3
    //   69: athrow
    //   70: aload_0
    //   71: getfield 248	o/ᒌ:ˏ	Ljava/lang/Object;
    //   74: astore_3
    //   75: aload_0
    //   76: aconst_null
    //   77: putfield 248	o/ᒌ:ˏ	Ljava/lang/Object;
    //   80: aload_0
    //   81: aload_3
    //   82: invokespecial 253	o/ᒌ:ˏ	(Ljava/lang/Object;)V
    //   85: goto +168 -> 253
    //   88: goto +50 -> 138
    //   91: getstatic 39	o/ᒌ:ˊॱ	I
    //   94: bipush 85
    //   96: iadd
    //   97: istore_1
    //   98: iload_1
    //   99: sipush 128
    //   102: irem
    //   103: putstatic 41	o/ᒌ:ͺ	I
    //   106: iload_1
    //   107: iconst_2
    //   108: irem
    //   109: ifne +6 -> 115
    //   112: goto +18 -> 130
    //   115: goto +110 -> 225
    //   118: aload_0
    //   119: invokespecial 255	o/ᒌ:ˊ	()Z
    //   122: ifeq +6 -> 128
    //   125: goto +136 -> 261
    //   128: iload_2
    //   129: ireturn
    //   130: bipush 34
    //   132: istore_1
    //   133: goto +185 -> 318
    //   136: iconst_0
    //   137: ireturn
    //   138: iload_2
    //   139: ifne +6 -> 145
    //   142: goto -24 -> 118
    //   145: iload_2
    //   146: ireturn
    //   147: aload_0
    //   148: getfield 75	o/ᒌ:ˊ	Lo/ب;
    //   151: invokevirtual 241	o/ب:ˊ	()Lo/ڹ;
    //   154: aload_0
    //   155: getfield 105	o/ᒌ:ᐝ	Lo/ﾜ$iF;
    //   158: getfield 110	o/ﾜ$iF:ˋ	Lo/ʢ;
    //   161: invokeinterface 230 1 0
    //   166: invokevirtual 246	o/ڹ:ˊ	(Lo/ｬ;)Z
    //   169: ifne +6 -> 175
    //   172: goto +175 -> 347
    //   175: goto +118 -> 293
    //   178: aload_0
    //   179: getfield 75	o/ᒌ:ˊ	Lo/ب;
    //   182: invokevirtual 90	o/ب:ॱˊ	()Ljava/util/List;
    //   185: astore_3
    //   186: aload_0
    //   187: getfield 84	o/ᒌ:ˎ	I
    //   190: istore_1
    //   191: aload_0
    //   192: iload_1
    //   193: iconst_1
    //   194: iadd
    //   195: putfield 84	o/ᒌ:ˎ	I
    //   198: aload_0
    //   199: aload_3
    //   200: iload_1
    //   201: invokeinterface 259 2 0
    //   206: checkcast 107	o/ﾜ$iF
    //   209: putfield 105	o/ᒌ:ᐝ	Lo/ﾜ$iF;
    //   212: aload_0
    //   213: getfield 105	o/ᒌ:ᐝ	Lo/ﾜ$iF;
    //   216: ifnull +6 -> 222
    //   219: goto -72 -> 147
    //   222: goto -84 -> 138
    //   225: bipush 59
    //   227: istore_1
    //   228: goto +90 -> 318
    //   231: aload_0
    //   232: getfield 248	o/ᒌ:ˏ	Ljava/lang/Object;
    //   235: astore_3
    //   236: iconst_1
    //   237: iconst_0
    //   238: idiv
    //   239: istore_1
    //   240: aload_3
    //   241: ifnull +6 -> 247
    //   244: goto -174 -> 70
    //   247: goto +164 -> 411
    //   250: goto -72 -> 178
    //   253: goto +158 -> 411
    //   256: iconst_1
    //   257: istore_1
    //   258: goto +127 -> 385
    //   261: getstatic 41	o/ᒌ:ͺ	I
    //   264: bipush 95
    //   266: iadd
    //   267: istore_1
    //   268: iload_1
    //   269: sipush 128
    //   272: irem
    //   273: putstatic 39	o/ᒌ:ˊॱ	I
    //   276: iload_1
    //   277: iconst_2
    //   278: irem
    //   279: ifeq +6 -> 285
    //   282: goto -32 -> 250
    //   285: goto -107 -> 178
    //   288: iconst_1
    //   289: istore_1
    //   290: goto -251 -> 39
    //   293: iconst_1
    //   294: istore_2
    //   295: aload_0
    //   296: getfield 105	o/ᒌ:ᐝ	Lo/ﾜ$iF;
    //   299: getfield 110	o/ﾜ$iF:ˋ	Lo/ʢ;
    //   302: aload_0
    //   303: getfield 75	o/ᒌ:ˊ	Lo/ب;
    //   306: invokevirtual 262	o/ب:ˏ	()Lo/ᴈ;
    //   309: aload_0
    //   310: invokeinterface 265 3 0
    //   315: goto -227 -> 88
    //   318: iload_1
    //   319: lookupswitch	default:+25->344, 34:+-88->231, 59:+133->452
    //   344: goto -113 -> 231
    //   347: aload_0
    //   348: getfield 75	o/ᒌ:ˊ	Lo/ب;
    //   351: aload_0
    //   352: getfield 105	o/ᒌ:ᐝ	Lo/ﾜ$iF;
    //   355: getfield 110	o/ﾜ$iF:ˋ	Lo/ʢ;
    //   358: invokeinterface 268 1 0
    //   363: invokevirtual 271	o/ب:ˋ	(Ljava/lang/Class;)Z
    //   366: ifeq +6 -> 372
    //   369: goto +6 -> 375
    //   372: goto -84 -> 288
    //   375: iconst_0
    //   376: istore_1
    //   377: goto -338 -> 39
    //   380: goto -289 -> 91
    //   383: iconst_0
    //   384: istore_1
    //   385: iload_1
    //   386: tableswitch	default:+22->408, 0:+-368->18, 1:+-383->3
    //   408: goto -390 -> 18
    //   411: aload_0
    //   412: getfield 226	o/ᒌ:ॱ	Lo/ח;
    //   415: astore_3
    //   416: aload_3
    //   417: ifnull +6 -> 423
    //   420: goto -37 -> 383
    //   423: goto -167 -> 256
    //   426: getstatic 41	o/ᒌ:ͺ	I
    //   429: iconst_5
    //   430: iadd
    //   431: istore_1
    //   432: iload_1
    //   433: sipush 128
    //   436: irem
    //   437: putstatic 39	o/ᒌ:ˊॱ	I
    //   440: iload_1
    //   441: iconst_2
    //   442: irem
    //   443: ifeq +6 -> 449
    //   446: goto -310 -> 136
    //   449: goto -415 -> 34
    //   452: aload_0
    //   453: getfield 248	o/ᒌ:ˏ	Ljava/lang/Object;
    //   456: ifnull +6 -> 462
    //   459: goto -389 -> 70
    //   462: goto -51 -> 411
    // Local variable table:
    //   start	length	slot	name	signature
    //   0	465	0	this	ᒌ
    //   39	404	1	i	int
    //   14	281	2	bool	boolean
    //   36	2	3	localException1	Exception
    //   67	2	3	localException2	Exception
    //   74	343	3	localObject	Object
    // Exception table:
    //   from	to	target	type
    //   75	80	36	java/lang/Exception
    //   70	75	67	java/lang/Exception
    //   75	80	67	java/lang/Exception
    //   80	85	67	java/lang/Exception
    //   231	236	67	java/lang/Exception
    //   411	416	67	java/lang/Exception
  }
  
  public void ˏ()
  {
    throw new UnsupportedOperationException();
  }
  
  public void ˏ(Exception paramException)
  {
    break label65;
    this.ˋ.ॱ(this.ʼ, paramException, this.ᐝ.ˋ, this.ᐝ.ˋ.ˎ());
    int i;
    for (;;)
    {
      i = ˊॱ + 49;
      ͺ = i % 128;
      if (i % 2 != 0) {
        return;
      }
      return;
      label65:
      i = ͺ + 57;
      ˊॱ = i % 128;
      if (i % 2 == 0) {
        break label163;
      }
      i = 1;
      break;
      this.ˋ.ॱ(this.ʼ, paramException, this.ᐝ.ˋ, this.ᐝ.ˋ.ˎ());
      i = null.length;
    }
    for (;;)
    {
      switch (i)
      {
      }
      break;
      label163:
      i = 0;
    }
  }
  
  public void ॱ(ﾚ paramﾚ, Exception paramException, ʢ<?> paramʢ, ｬ paramｬ)
  {
    break label156;
    break label99;
    return;
    int i;
    for (;;)
    {
      i = 1;
      do
      {
        i = 0;
        switch (i)
        {
        case 1: 
        default: 
          break label148;
          i = ͺ + 3;
          ˊॱ = i % 128;
        }
      } while (i % 2 != 0);
    }
    label99:
    label148:
    label156:
    for (;;)
    {
      i = ͺ + 47;
      ˊॱ = i % 128;
      if (i % 2 != 0) {
        break;
      }
      try
      {
        paramｬ = this.ˋ;
        localObject = this.ᐝ;
        localObject = ((ﾜ.iF)localObject).ˋ;
        localObject = ((ʢ)localObject).ˎ();
      }
      catch (Exception paramﾚ)
      {
        try
        {
          Object localObject;
          paramｬ.ॱ(paramﾚ, paramException, paramʢ, (ｬ)localObject);
        }
        catch (Exception paramﾚ)
        {
          throw paramﾚ;
        }
        paramﾚ = paramﾚ;
        throw paramﾚ;
      }
      throw new NullPointerException();
    }
  }
}
