package o;

import android.animation.Animator;
import android.animation.Keyframe;
import android.animation.PropertyValuesHolder;
import android.animation.TypeEvaluator;
import android.animation.ValueAnimator;
import android.content.Context;
import android.content.res.Resources;
import android.content.res.Resources.Theme;
import android.content.res.TypedArray;
import android.util.AttributeSet;
import android.util.TypedValue;
import android.util.Xml;
import java.util.ArrayList;
import org.xmlpull.v1.XmlPullParser;

public class ᒻ
{
  private static int ˊ = 1;
  private static long ˋ = -6766666191623872980L;
  private static int ˏ = 0;
  private static char[] ॱ = { 10900, 13494, 5854, 28701, 21053, -17342, -24678, -1618 };
  
  public ᒻ() {}
  
  /* Error */
  private static int ˊ(Resources paramResources, Resources.Theme paramTheme, AttributeSet paramAttributeSet, XmlPullParser paramXmlPullParser)
  {
    // Byte code:
    //   0: goto +14 -> 14
    //   3: iload 4
    //   5: ifeq +6 -> 11
    //   8: goto +93 -> 101
    //   11: goto +193 -> 204
    //   14: goto +6 -> 20
    //   17: goto +114 -> 131
    //   20: getstatic 49	o/ˤ:ᐝ	[I
    //   23: astore 6
    //   25: aload_0
    //   26: aload_1
    //   27: aload_2
    //   28: aload 6
    //   30: invokestatic 54	o/ᵁ:ॱ	(Landroid/content/res/Resources;Landroid/content/res/Resources$Theme;Landroid/util/AttributeSet;[I)Landroid/content/res/TypedArray;
    //   33: astore_0
    //   34: aload_0
    //   35: aload_3
    //   36: ldc 56
    //   38: iconst_0
    //   39: invokestatic 60	o/ᵁ:ˎ	(Landroid/content/res/TypedArray;Lorg/xmlpull/v1/XmlPullParser;Ljava/lang/String;I)Landroid/util/TypedValue;
    //   42: astore_1
    //   43: aload_1
    //   44: ifnull +6 -> 50
    //   47: goto +120 -> 167
    //   50: goto +222 -> 272
    //   53: iconst_1
    //   54: istore 4
    //   56: goto -53 -> 3
    //   59: goto +189 -> 248
    //   62: goto -59 -> 3
    //   65: iconst_0
    //   66: istore 4
    //   68: goto +142 -> 210
    //   71: getstatic 20	o/ᒻ:ˏ	I
    //   74: bipush 101
    //   76: iadd
    //   77: istore 5
    //   79: iload 5
    //   81: sipush 128
    //   84: irem
    //   85: putstatic 22	o/ᒻ:ˊ	I
    //   88: iload 5
    //   90: iconst_2
    //   91: irem
    //   92: ifne +6 -> 98
    //   95: goto +169 -> 264
    //   98: goto -36 -> 62
    //   101: getstatic 20	o/ᒻ:ˏ	I
    //   104: bipush 125
    //   106: iadd
    //   107: istore 4
    //   109: iload 4
    //   111: sipush 128
    //   114: irem
    //   115: putstatic 22	o/ᒻ:ˊ	I
    //   118: iload 4
    //   120: iconst_2
    //   121: irem
    //   122: ifne +6 -> 128
    //   125: goto -66 -> 59
    //   128: goto +120 -> 248
    //   131: iconst_3
    //   132: istore 4
    //   134: goto +145 -> 279
    //   137: iload 4
    //   139: lookupswitch	default:+25->164, 27:+150->289, 43:+-86->53
    //   164: goto -111 -> 53
    //   167: bipush 43
    //   169: istore 4
    //   171: goto -34 -> 137
    //   174: getstatic 22	o/ᒻ:ˊ	I
    //   177: bipush 19
    //   179: iadd
    //   180: istore 4
    //   182: iload 4
    //   184: sipush 128
    //   187: irem
    //   188: putstatic 20	o/ᒻ:ˏ	I
    //   191: iload 4
    //   193: iconst_2
    //   194: irem
    //   195: ifeq +6 -> 201
    //   198: goto -181 -> 17
    //   201: goto -70 -> 131
    //   204: iconst_0
    //   205: istore 4
    //   207: goto +72 -> 279
    //   210: iload 4
    //   212: tableswitch	default:+24->236, 0:+-8->204, 1:+-38->174
    //   236: goto -62 -> 174
    //   239: astore_0
    //   240: aload_0
    //   241: athrow
    //   242: iconst_1
    //   243: istore 4
    //   245: goto -35 -> 210
    //   248: aload_1
    //   249: getfield 65	android/util/TypedValue:type	I
    //   252: invokestatic 68	o/ᒻ:ˋ	(I)Z
    //   255: ifeq +6 -> 261
    //   258: goto -16 -> 242
    //   261: goto -196 -> 65
    //   264: iconst_2
    //   265: iconst_3
    //   266: idiv
    //   267: istore 5
    //   269: goto -266 -> 3
    //   272: bipush 27
    //   274: istore 4
    //   276: goto -139 -> 137
    //   279: aload_0
    //   280: invokevirtual 73	android/content/res/TypedArray:recycle	()V
    //   283: iload 4
    //   285: ireturn
    //   286: astore_0
    //   287: aload_0
    //   288: athrow
    //   289: iconst_0
    //   290: istore 4
    //   292: goto -221 -> 71
    // Local variable table:
    //   start	length	slot	name	signature
    //   0	295	0	paramResources	Resources
    //   0	295	1	paramTheme	Resources.Theme
    //   0	295	2	paramAttributeSet	AttributeSet
    //   0	295	3	paramXmlPullParser	XmlPullParser
    //   3	288	4	i	int
    //   77	191	5	j	int
    //   23	6	6	arrayOfInt	int[]
    // Exception table:
    //   from	to	target	type
    //   20	25	239	java/lang/Exception
    //   25	34	286	java/lang/Exception
    //   34	43	286	java/lang/Exception
  }
  
  private static Keyframe ˊ(Context paramContext, Resources paramResources, Resources.Theme paramTheme, AttributeSet paramAttributeSet, int paramInt, XmlPullParser paramXmlPullParser)
  {
    break label338;
    label15:
    label31:
    int i;
    int j;
    label65:
    Object localObject;
    if (paramInt != 4)
    {
      break label214;
      for (;;)
      {
        if (ˋ(paramResources.type)) {
          break label503;
        }
        break label341;
        i = ᵁ.ॱ(paramAttributeSet, paramXmlPullParser, "interpolator", 1, 0);
        if (i > 0) {
          break label226;
        }
        break label232;
        if (j != 0) {
          break label259;
        }
        break label540;
        paramResources = Keyframe.ofInt(localObject);
        break;
        switch (paramInt)
        {
        default: 
          label74:
          break label534;
          switch (paramInt)
          {
          default: 
            break label341;
            break;
          case 26: 
            label107:
            label139:
            paramInt = ˊ + 119;
            ˏ = paramInt % 128;
            if (paramInt % 2 != 0) {
              break label493;
            }
          }
          break;
        }
      }
    }
    for (;;)
    {
      paramResources.setInterpolator(ᔅ.ˋ(paramContext, i));
      label185:
      label214:
      int k;
      switch (i)
      {
      default: 
        break label509;
        break label537;
        k = 0;
        break label347;
        for (;;)
        {
          paramAttributeSet.recycle();
          return paramResources;
          paramInt = 1;
          break label547;
          paramInt = 0;
          break label547;
          paramResources = Keyframe.ofFloat(localObject);
          break label139;
          i = 0;
          break label185;
          i = 1;
          break label185;
          paramInt = 26;
          break;
        }
      case 1: 
        j = 0;
        break;
        paramResources = Keyframe.ofInt(localObject, ᵁ.ˏ(paramAttributeSet, paramXmlPullParser, "value", 0, 0));
      case 0: 
        label226:
        label232:
        label238:
        label247:
        label253:
        label259:
        label291:
        label327:
        label338:
        label341:
        label347:
        label383:
        label434:
        label493:
        label496:
        label503:
        label509:
        label534:
        for (;;)
        {
          break label31;
          for (;;)
          {
            paramInt = ˏ + 49;
            ˊ = paramInt % 128;
            float f;
            if (paramInt % 2 != 0)
            {
              break label496;
              break label291;
              if (i == 0) {
                break label238;
              }
              break label65;
              break label383;
              i = 0;
              break label434;
              for (;;)
              {
                i = paramInt;
                switch (k)
                {
                case 1: 
                default: 
                  i = paramInt;
                  break label434;
                  paramAttributeSet = ᵁ.ॱ(paramResources, paramTheme, paramAttributeSet, ˤ.ᐝ);
                  paramTheme = null;
                  f = ᵁ.ˏ(paramAttributeSet, paramXmlPullParser, "fraction", 3, -1.0F);
                  paramResources = ᵁ.ˎ(paramAttributeSet, paramXmlPullParser, "value", 0);
                  if (paramResources != null) {
                    break label247;
                  }
                  break label253;
                  k = 1;
                }
              }
            }
            for (;;)
            {
              if (j == 0)
              {
                break label327;
                paramInt = 65;
                break label74;
              }
              paramResources = paramTheme;
              switch (i)
              {
              case 1: 
              case 3: 
              case 2: 
              default: 
                paramResources = paramTheme;
                break label291;
                break label15;
                paramInt = 21;
                break label74;
                i = 3;
              }
            }
            j = 1;
            break;
            paramResources = Keyframe.ofFloat(f, ᵁ.ˏ(paramAttributeSet, paramXmlPullParser, "value", 0, 0.0F));
          }
        }
        label537:
        break label31;
        label540:
        paramInt = 59;
        break label107;
        label547:
        switch (paramInt)
        {
        }
        break;
      }
    }
  }
  
  /* Error */
  private static android.animation.ObjectAnimator ˊ(Context paramContext, Resources paramResources, Resources.Theme paramTheme, AttributeSet paramAttributeSet, float paramFloat, XmlPullParser paramXmlPullParser)
  {
    // Byte code:
    //   0: goto +59 -> 59
    //   3: astore_0
    //   4: aload_0
    //   5: athrow
    //   6: new 114	android/animation/ObjectAnimator
    //   9: dup
    //   10: invokespecial 115	android/animation/ObjectAnimator:<init>	()V
    //   13: astore 7
    //   15: aload_0
    //   16: aload_1
    //   17: aload_2
    //   18: aload_3
    //   19: aload 7
    //   21: fload 4
    //   23: aload 5
    //   25: invokestatic 118	o/ᒻ:ˏ	(Landroid/content/Context;Landroid/content/res/Resources;Landroid/content/res/Resources$Theme;Landroid/util/AttributeSet;Landroid/animation/ValueAnimator;FLorg/xmlpull/v1/XmlPullParser;)Landroid/animation/ValueAnimator;
    //   28: pop
    //   29: getstatic 22	o/ᒻ:ˊ	I
    //   32: bipush 67
    //   34: iadd
    //   35: istore 6
    //   37: iload 6
    //   39: sipush 128
    //   42: irem
    //   43: putstatic 20	o/ᒻ:ˏ	I
    //   46: iload 6
    //   48: iconst_2
    //   49: irem
    //   50: ifeq +6 -> 56
    //   53: aload 7
    //   55: areturn
    //   56: aload 7
    //   58: areturn
    //   59: goto -53 -> 6
    // Local variable table:
    //   start	length	slot	name	signature
    //   0	62	0	paramContext	Context
    //   0	62	1	paramResources	Resources
    //   0	62	2	paramTheme	Resources.Theme
    //   0	62	3	paramAttributeSet	AttributeSet
    //   0	62	4	paramFloat	float
    //   0	62	5	paramXmlPullParser	XmlPullParser
    //   35	15	6	i	int
    //   13	44	7	localObjectAnimator	android.animation.ObjectAnimator
    // Exception table:
    //   from	to	target	type
    //   15	29	3	java/lang/Exception
  }
  
  /* Error */
  public static Animator ˋ(Context paramContext, int paramInt)
  {
    // Byte code:
    //   0: goto +78 -> 78
    //   3: goto +29 -> 32
    //   6: bipush 89
    //   8: istore_2
    //   9: goto +113 -> 122
    //   12: getstatic 124	android/os/Build$VERSION:SDK_INT	I
    //   15: bipush 24
    //   17: if_icmplt +6 -> 23
    //   20: goto +6 -> 26
    //   23: goto -17 -> 6
    //   26: bipush 72
    //   28: istore_2
    //   29: goto +93 -> 122
    //   32: aload_0
    //   33: areturn
    //   34: getstatic 20	o/ᒻ:ˏ	I
    //   37: bipush 83
    //   39: iadd
    //   40: istore_2
    //   41: iload_2
    //   42: sipush 128
    //   45: irem
    //   46: putstatic 22	o/ᒻ:ˊ	I
    //   49: iload_2
    //   50: iconst_2
    //   51: irem
    //   52: ifne +6 -> 58
    //   55: goto +26 -> 81
    //   58: goto +23 -> 81
    //   61: astore_0
    //   62: aload_0
    //   63: athrow
    //   64: aload_0
    //   65: aload_0
    //   66: invokevirtual 130	android/content/Context:getResources	()Landroid/content/res/Resources;
    //   69: aload_0
    //   70: invokevirtual 134	android/content/Context:getTheme	()Landroid/content/res/Resources$Theme;
    //   73: iload_1
    //   74: invokestatic 137	o/ᒻ:ˏ	(Landroid/content/Context;Landroid/content/res/Resources;Landroid/content/res/Resources$Theme;I)Landroid/animation/Animator;
    //   77: areturn
    //   78: goto -66 -> 12
    //   81: aload_0
    //   82: iload_1
    //   83: invokestatic 142	android/animation/AnimatorInflater:loadAnimator	(Landroid/content/Context;I)Landroid/animation/Animator;
    //   86: astore_0
    //   87: goto +6 -> 93
    //   90: astore_0
    //   91: aload_0
    //   92: athrow
    //   93: getstatic 22	o/ᒻ:ˊ	I
    //   96: istore_1
    //   97: iload_1
    //   98: bipush 125
    //   100: iadd
    //   101: istore_1
    //   102: iload_1
    //   103: sipush 128
    //   106: irem
    //   107: putstatic 20	o/ᒻ:ˏ	I
    //   110: iload_1
    //   111: iconst_2
    //   112: irem
    //   113: ifeq +6 -> 119
    //   116: goto -113 -> 3
    //   119: goto -87 -> 32
    //   122: iload_2
    //   123: lookupswitch	default:+25->148, 72:+-89->34, 89:+-59->64
    //   148: goto -84 -> 64
    // Local variable table:
    //   start	length	slot	name	signature
    //   0	151	0	paramContext	Context
    //   0	151	1	paramInt	int
    //   8	115	2	i	int
    // Exception table:
    //   from	to	target	type
    //   34	41	61	java/lang/Exception
    //   41	49	61	java/lang/Exception
    //   93	97	90	java/lang/Exception
    //   102	110	90	java/lang/Exception
  }
  
  /* Error */
  public static Animator ˋ(Context paramContext, Resources paramResources, Resources.Theme paramTheme, int paramInt, float paramFloat)
  {
    // Byte code:
    //   0: goto +184 -> 184
    //   3: iload_3
    //   4: tableswitch	default:+24->28, 0:+322->326, 1:+248->252
    //   28: goto +224 -> 252
    //   31: getstatic 20	o/ᒻ:ˏ	I
    //   34: bipush 117
    //   36: iadd
    //   37: istore_3
    //   38: iload_3
    //   39: sipush 128
    //   42: irem
    //   43: putstatic 22	o/ᒻ:ˊ	I
    //   46: iload_3
    //   47: iconst_2
    //   48: irem
    //   49: ifne +6 -> 55
    //   52: goto +269 -> 321
    //   55: goto +257 -> 312
    //   58: iload_3
    //   59: lookupswitch	default:+25->84, 79:+-28->31, 85:+258->317
    //   84: goto -53 -> 31
    //   87: goto +103 -> 190
    //   90: bipush 79
    //   92: istore_3
    //   93: goto -35 -> 58
    //   96: astore_1
    //   97: aload 6
    //   99: astore 5
    //   101: new 149	android/content/res/Resources$NotFoundException
    //   104: dup
    //   105: new 151	java/lang/StringBuilder
    //   108: dup
    //   109: invokespecial 152	java/lang/StringBuilder:<init>	()V
    //   112: ldc -102
    //   114: invokevirtual 158	java/lang/StringBuilder:append	(Ljava/lang/String;)Ljava/lang/StringBuilder;
    //   117: iload_3
    //   118: invokestatic 164	java/lang/Integer:toHexString	(I)Ljava/lang/String;
    //   121: invokevirtual 158	java/lang/StringBuilder:append	(Ljava/lang/String;)Ljava/lang/StringBuilder;
    //   124: invokevirtual 168	java/lang/StringBuilder:toString	()Ljava/lang/String;
    //   127: invokespecial 171	android/content/res/Resources$NotFoundException:<init>	(Ljava/lang/String;)V
    //   130: astore_0
    //   131: aload 6
    //   133: astore 5
    //   135: aload_0
    //   136: aload_1
    //   137: invokevirtual 175	android/content/res/Resources$NotFoundException:initCause	(Ljava/lang/Throwable;)Ljava/lang/Throwable;
    //   140: pop
    //   141: aload 6
    //   143: astore 5
    //   145: aload_0
    //   146: athrow
    //   147: getstatic 22	o/ᒻ:ˊ	I
    //   150: bipush 113
    //   152: iadd
    //   153: istore_3
    //   154: iload_3
    //   155: sipush 128
    //   158: irem
    //   159: putstatic 20	o/ᒻ:ˏ	I
    //   162: iload_3
    //   163: iconst_2
    //   164: irem
    //   165: ifeq +6 -> 171
    //   168: goto +30 -> 198
    //   171: goto -84 -> 87
    //   174: aload 5
    //   176: invokeinterface 180 1 0
    //   181: goto -34 -> 147
    //   184: goto +78 -> 262
    //   187: astore_0
    //   188: aload_0
    //   189: athrow
    //   190: aload_0
    //   191: athrow
    //   192: bipush 85
    //   194: istore_3
    //   195: goto -137 -> 58
    //   198: goto -111 -> 87
    //   201: astore_0
    //   202: aload 7
    //   204: astore 5
    //   206: new 149	android/content/res/Resources$NotFoundException
    //   209: dup
    //   210: new 151	java/lang/StringBuilder
    //   213: dup
    //   214: invokespecial 152	java/lang/StringBuilder:<init>	()V
    //   217: ldc -102
    //   219: invokevirtual 158	java/lang/StringBuilder:append	(Ljava/lang/String;)Ljava/lang/StringBuilder;
    //   222: iload_3
    //   223: invokestatic 164	java/lang/Integer:toHexString	(I)Ljava/lang/String;
    //   226: invokevirtual 158	java/lang/StringBuilder:append	(Ljava/lang/String;)Ljava/lang/StringBuilder;
    //   229: invokevirtual 168	java/lang/StringBuilder:toString	()Ljava/lang/String;
    //   232: invokespecial 171	android/content/res/Resources$NotFoundException:<init>	(Ljava/lang/String;)V
    //   235: astore_1
    //   236: aload 7
    //   238: astore 5
    //   240: aload_1
    //   241: aload_0
    //   242: invokevirtual 175	android/content/res/Resources$NotFoundException:initCause	(Ljava/lang/Throwable;)Ljava/lang/Throwable;
    //   245: pop
    //   246: aload 7
    //   248: astore 5
    //   250: aload_1
    //   251: athrow
    //   252: aload 8
    //   254: invokeinterface 180 1 0
    //   259: goto +60 -> 319
    //   262: aconst_null
    //   263: astore 7
    //   265: aconst_null
    //   266: astore 5
    //   268: aconst_null
    //   269: astore 6
    //   271: aload_1
    //   272: iload_3
    //   273: invokevirtual 186	android/content/res/Resources:getAnimation	(I)Landroid/content/res/XmlResourceParser;
    //   276: astore 8
    //   278: aload 8
    //   280: astore 6
    //   282: aload 8
    //   284: astore 7
    //   286: aload 8
    //   288: astore 5
    //   290: aload_0
    //   291: aload_1
    //   292: aload_2
    //   293: aload 8
    //   295: fload 4
    //   297: invokestatic 189	o/ᒻ:ˋ	(Landroid/content/Context;Landroid/content/res/Resources;Landroid/content/res/Resources$Theme;Lorg/xmlpull/v1/XmlPullParser;F)Landroid/animation/Animator;
    //   300: astore_0
    //   301: aload 8
    //   303: ifnull +6 -> 309
    //   306: goto -216 -> 90
    //   309: goto -117 -> 192
    //   312: iconst_1
    //   313: istore_3
    //   314: goto -311 -> 3
    //   317: aload_0
    //   318: areturn
    //   319: aload_0
    //   320: areturn
    //   321: iconst_0
    //   322: istore_3
    //   323: goto -320 -> 3
    //   326: aload 8
    //   328: invokeinterface 180 1 0
    //   333: new 191	java/lang/NullPointerException
    //   336: dup
    //   337: invokespecial 192	java/lang/NullPointerException:<init>	()V
    //   340: athrow
    //   341: astore_0
    //   342: aload 5
    //   344: ifnull +6 -> 350
    //   347: goto -173 -> 174
    //   350: goto -160 -> 190
    // Local variable table:
    //   start	length	slot	name	signature
    //   0	353	0	paramContext	Context
    //   0	353	1	paramResources	Resources
    //   0	353	2	paramTheme	Resources.Theme
    //   0	353	3	paramInt	int
    //   0	353	4	paramFloat	float
    //   99	244	5	localObject1	Object
    //   97	184	6	localObject2	Object
    //   202	83	7	localObject3	Object
    //   252	75	8	localXmlResourceParser	android.content.res.XmlResourceParser
    // Exception table:
    //   from	to	target	type
    //   271	278	96	java/io/IOException
    //   290	301	96	java/io/IOException
    //   31	38	187	java/lang/Exception
    //   38	46	187	java/lang/Exception
    //   147	154	187	java/lang/Exception
    //   154	162	187	java/lang/Exception
    //   271	278	201	org/xmlpull/v1/XmlPullParserException
    //   290	301	201	org/xmlpull/v1/XmlPullParserException
    //   101	131	341	finally
    //   135	141	341	finally
    //   145	147	341	finally
    //   206	236	341	finally
    //   240	246	341	finally
    //   250	252	341	finally
    //   271	278	341	finally
    //   290	301	341	finally
  }
  
  private static Animator ˋ(Context paramContext, Resources paramResources, Resources.Theme paramTheme, XmlPullParser paramXmlPullParser, float paramFloat)
  {
    break label92;
    int i = ˊ + 95;
    ˏ = i % 128;
    if (i % 2 == 0)
    {
      break label134;
      label52:
      for (;;)
      {
        paramContext = ˎ(paramContext, paramResources, paramTheme, paramXmlPullParser, Xml.asAttributeSet(paramXmlPullParser), null, 0, paramFloat);
        break;
      }
    }
    else
    {
      label92:
      for (;;)
      {
        i = ˊ + 63;
        ˏ = i % 128;
        if (i % 2 != 0) {
          break label52;
        }
        break;
        i = 24;
        break label103;
      }
      i = 99 / 0;
      return paramContext;
    }
    for (;;)
    {
      switch (i)
      {
      case 24: 
      default: 
        label103:
        return paramContext;
        label134:
        i = 13;
      }
    }
    return paramContext;
  }
  
  /* Error */
  private static PropertyValuesHolder ˋ(TypedArray paramTypedArray, int paramInt1, int paramInt2, int paramInt3, String paramString)
  {
    // Byte code:
    //   0: goto +355 -> 355
    //   3: astore_0
    //   4: aload_0
    //   5: athrow
    //   6: goto +706 -> 712
    //   9: aconst_null
    //   10: arraylength
    //   11: istore_1
    //   12: iload 9
    //   14: ifeq +6 -> 20
    //   17: goto +1479 -> 1496
    //   20: goto +124 -> 144
    //   23: aload_0
    //   24: iload_2
    //   25: fconst_0
    //   26: invokevirtual 206	android/content/res/TypedArray:getDimension	(IF)F
    //   29: f2i
    //   30: istore_2
    //   31: goto +1583 -> 1614
    //   34: iconst_0
    //   35: istore_1
    //   36: goto +1271 -> 1307
    //   39: aload_0
    //   40: iload_3
    //   41: invokevirtual 210	android/content/res/TypedArray:peekValue	(I)Landroid/util/TypedValue;
    //   44: astore 14
    //   46: aload 14
    //   48: ifnull +6 -> 54
    //   51: goto +422 -> 473
    //   54: goto +1413 -> 1467
    //   57: aload 4
    //   59: iconst_1
    //   60: newarray float
    //   62: dup
    //   63: iconst_0
    //   64: fload 5
    //   66: fastore
    //   67: invokestatic 215	android/animation/PropertyValuesHolder:ofFloat	(Ljava/lang/String;[F)Landroid/animation/PropertyValuesHolder;
    //   70: astore_0
    //   71: goto +1268 -> 1339
    //   74: aload 4
    //   76: aload 17
    //   78: iconst_2
    //   79: anewarray 4	java/lang/Object
    //   82: dup
    //   83: iconst_0
    //   84: aload 15
    //   86: aastore
    //   87: dup
    //   88: iconst_1
    //   89: aload 16
    //   91: aastore
    //   92: invokestatic 219	android/animation/PropertyValuesHolder:ofObject	(Ljava/lang/String;Landroid/animation/TypeEvaluator;[Ljava/lang/Object;)Landroid/animation/PropertyValuesHolder;
    //   95: astore_0
    //   96: goto +82 -> 178
    //   99: aload_0
    //   100: iload_2
    //   101: fconst_0
    //   102: invokevirtual 222	android/content/res/TypedArray:getFloat	(IF)F
    //   105: fstore 5
    //   107: goto +1069 -> 1176
    //   110: aload_0
    //   111: iload_2
    //   112: iconst_0
    //   113: invokevirtual 226	android/content/res/TypedArray:getInt	(II)I
    //   116: istore_2
    //   117: goto +1497 -> 1614
    //   120: iconst_2
    //   121: istore_1
    //   122: goto +1065 -> 1187
    //   125: goto +1228 -> 1353
    //   128: iconst_1
    //   129: istore 12
    //   131: goto +932 -> 1063
    //   134: aload_0
    //   135: iload_3
    //   136: iconst_0
    //   137: invokevirtual 226	android/content/res/TypedArray:getInt	(II)I
    //   140: istore_1
    //   141: goto +850 -> 991
    //   144: iload 7
    //   146: ifeq +6 -> 152
    //   149: goto +1451 -> 1600
    //   152: goto +1321 -> 1473
    //   155: bipush 33
    //   157: istore 8
    //   159: goto +865 -> 1024
    //   162: aload 4
    //   164: iconst_1
    //   165: newarray int
    //   167: dup
    //   168: iconst_0
    //   169: iload_1
    //   170: iastore
    //   171: invokestatic 229	android/animation/PropertyValuesHolder:ofInt	(Ljava/lang/String;[I)Landroid/animation/PropertyValuesHolder;
    //   174: astore_0
    //   175: goto +1450 -> 1625
    //   178: goto +282 -> 460
    //   181: getstatic 22	o/ᒻ:ˊ	I
    //   184: bipush 33
    //   186: iadd
    //   187: istore_1
    //   188: iload_1
    //   189: sipush 128
    //   192: irem
    //   193: putstatic 20	o/ᒻ:ˏ	I
    //   196: iload_1
    //   197: iconst_2
    //   198: irem
    //   199: ifeq +6 -> 205
    //   202: goto +1210 -> 1412
    //   205: goto +448 -> 653
    //   208: aload_0
    //   209: iload_2
    //   210: invokevirtual 210	android/content/res/TypedArray:peekValue	(I)Landroid/util/TypedValue;
    //   213: astore 16
    //   215: bipush 72
    //   217: iconst_0
    //   218: idiv
    //   219: istore 7
    //   221: aload 16
    //   223: ifnull +6 -> 229
    //   226: goto +202 -> 428
    //   229: goto +119 -> 348
    //   232: iconst_0
    //   233: istore 7
    //   235: goto +80 -> 315
    //   238: aload 15
    //   240: ifnull +6 -> 246
    //   243: goto +643 -> 886
    //   246: goto +440 -> 686
    //   249: iload 10
    //   251: iconst_5
    //   252: if_icmpne +6 -> 258
    //   255: goto +1255 -> 1510
    //   258: goto -159 -> 99
    //   261: goto +646 -> 907
    //   264: aconst_null
    //   265: astore 15
    //   267: iload_1
    //   268: iconst_2
    //   269: if_icmpne +6 -> 275
    //   272: goto -144 -> 128
    //   275: goto +653 -> 928
    //   278: aload_0
    //   279: iload_2
    //   280: invokevirtual 232	android/content/res/TypedArray:getString	(I)Ljava/lang/String;
    //   283: astore 14
    //   285: aload_0
    //   286: iload_3
    //   287: invokevirtual 232	android/content/res/TypedArray:getString	(I)Ljava/lang/String;
    //   290: astore_0
    //   291: aload 14
    //   293: invokestatic 237	o/ᵉ:ˎ	(Ljava/lang/String;)[Lo/ᵉ$If;
    //   296: astore 15
    //   298: aload_0
    //   299: invokestatic 237	o/ᵉ:ˎ	(Ljava/lang/String;)[Lo/ᵉ$If;
    //   302: astore 16
    //   304: aload 15
    //   306: ifnonnull +6 -> 312
    //   309: goto +486 -> 795
    //   312: goto -74 -> 238
    //   315: iload 7
    //   317: tableswitch	default:+23->340, 0:+837->1154, 1:+-109->208
    //   340: goto -132 -> 208
    //   343: iconst_1
    //   344: istore_1
    //   345: goto +589 -> 934
    //   348: bipush 13
    //   350: istore 7
    //   352: goto +379 -> 731
    //   355: goto +864 -> 1219
    //   358: new 239	android/view/InflateException
    //   361: dup
    //   362: new 151	java/lang/StringBuilder
    //   365: dup
    //   366: invokespecial 152	java/lang/StringBuilder:<init>	()V
    //   369: ldc -15
    //   371: invokevirtual 158	java/lang/StringBuilder:append	(Ljava/lang/String;)Ljava/lang/StringBuilder;
    //   374: aload 14
    //   376: invokevirtual 158	java/lang/StringBuilder:append	(Ljava/lang/String;)Ljava/lang/StringBuilder;
    //   379: ldc -13
    //   381: invokevirtual 158	java/lang/StringBuilder:append	(Ljava/lang/String;)Ljava/lang/StringBuilder;
    //   384: aload_0
    //   385: invokevirtual 158	java/lang/StringBuilder:append	(Ljava/lang/String;)Ljava/lang/StringBuilder;
    //   388: invokevirtual 168	java/lang/StringBuilder:toString	()Ljava/lang/String;
    //   391: invokespecial 244	android/view/InflateException:<init>	(Ljava/lang/String;)V
    //   394: athrow
    //   395: goto +1062 -> 1457
    //   398: getstatic 22	o/ᒻ:ˊ	I
    //   401: bipush 119
    //   403: iadd
    //   404: istore 11
    //   406: iload 11
    //   408: sipush 128
    //   411: irem
    //   412: putstatic 20	o/ᒻ:ˏ	I
    //   415: iload 11
    //   417: iconst_2
    //   418: irem
    //   419: ifeq +6 -> 425
    //   422: goto +141 -> 563
    //   425: goto +184 -> 609
    //   428: bipush 22
    //   430: istore 7
    //   432: goto +299 -> 731
    //   435: iconst_0
    //   436: istore 8
    //   438: goto +586 -> 1024
    //   441: iload_1
    //   442: iconst_4
    //   443: if_icmpne +6 -> 449
    //   446: goto +55 -> 501
    //   449: goto +458 -> 907
    //   452: invokestatic 249	o/ᔊ:ˊ	()Lo/ᔊ;
    //   455: astore 14
    //   457: goto +95 -> 552
    //   460: aload_0
    //   461: areturn
    //   462: iload 9
    //   464: ifeq +6 -> 470
    //   467: goto +1029 -> 1496
    //   470: goto -326 -> 144
    //   473: iconst_1
    //   474: istore 7
    //   476: goto +353 -> 829
    //   479: aload 4
    //   481: iconst_2
    //   482: newarray float
    //   484: dup
    //   485: iconst_0
    //   486: fload 5
    //   488: fastore
    //   489: dup
    //   490: iconst_1
    //   491: fload 6
    //   493: fastore
    //   494: invokestatic 215	android/animation/PropertyValuesHolder:ofFloat	(Ljava/lang/String;[F)Landroid/animation/PropertyValuesHolder;
    //   497: astore_0
    //   498: goto +841 -> 1339
    //   501: getstatic 22	o/ᒻ:ˊ	I
    //   504: istore_1
    //   505: iload_1
    //   506: bipush 103
    //   508: iadd
    //   509: istore_1
    //   510: iload_1
    //   511: sipush 128
    //   514: irem
    //   515: putstatic 20	o/ᒻ:ˏ	I
    //   518: iload_1
    //   519: iconst_2
    //   520: irem
    //   521: ifeq +6 -> 527
    //   524: goto -515 -> 9
    //   527: goto -65 -> 462
    //   530: iconst_0
    //   531: istore 11
    //   533: goto -269 -> 264
    //   536: aload 15
    //   538: aload 16
    //   540: invokestatic 252	o/ᵉ:ˋ	([Lo/ᵉ$If;[Lo/ᵉ$If;)Z
    //   543: ifne +6 -> 549
    //   546: goto -188 -> 358
    //   549: goto -475 -> 74
    //   552: iload 11
    //   554: ifeq +6 -> 560
    //   557: goto +1116 -> 1673
    //   560: goto -440 -> 120
    //   563: goto +46 -> 609
    //   566: aload 4
    //   568: aload 17
    //   570: iconst_1
    //   571: anewarray 4	java/lang/Object
    //   574: dup
    //   575: iconst_0
    //   576: aload 15
    //   578: aastore
    //   579: invokestatic 219	android/animation/PropertyValuesHolder:ofObject	(Ljava/lang/String;Landroid/animation/TypeEvaluator;[Ljava/lang/Object;)Landroid/animation/PropertyValuesHolder;
    //   582: astore_0
    //   583: goto -405 -> 178
    //   586: iload 8
    //   588: iconst_5
    //   589: if_icmpne +6 -> 595
    //   592: goto +685 -> 1277
    //   595: goto +883 -> 1478
    //   598: aload_0
    //   599: iload_3
    //   600: fconst_0
    //   601: invokevirtual 206	android/content/res/TypedArray:getDimension	(IF)F
    //   604: f2i
    //   605: istore_1
    //   606: goto -444 -> 162
    //   609: iconst_1
    //   610: istore 11
    //   612: goto -348 -> 264
    //   615: iconst_1
    //   616: istore 9
    //   618: goto +768 -> 1386
    //   621: iload 11
    //   623: tableswitch	default:+21->644, 0:+-225->398, 1:+-93->530
    //   644: goto -114 -> 530
    //   647: iconst_1
    //   648: istore 11
    //   650: goto -29 -> 621
    //   653: aload_0
    //   654: iload_3
    //   655: fconst_0
    //   656: invokevirtual 206	android/content/res/TypedArray:getDimension	(IF)F
    //   659: f2i
    //   660: istore_1
    //   661: goto +330 -> 991
    //   664: aload 14
    //   666: ifnull +6 -> 672
    //   669: goto +54 -> 723
    //   672: aload_0
    //   673: areturn
    //   674: iload 8
    //   676: iconst_5
    //   677: if_icmpne +6 -> 683
    //   680: goto +999 -> 1679
    //   683: goto +101 -> 784
    //   686: aload 16
    //   688: ifnull +6 -> 694
    //   691: goto +999 -> 1690
    //   694: aconst_null
    //   695: areturn
    //   696: aload 4
    //   698: iconst_1
    //   699: newarray int
    //   701: dup
    //   702: iconst_0
    //   703: iload_2
    //   704: iastore
    //   705: invokestatic 229	android/animation/PropertyValuesHolder:ofInt	(Ljava/lang/String;[I)Landroid/animation/PropertyValuesHolder;
    //   708: astore_0
    //   709: goto +916 -> 1625
    //   712: aload_0
    //   713: iload_2
    //   714: fconst_0
    //   715: invokevirtual 206	android/content/res/TypedArray:getDimension	(IF)F
    //   718: fstore 5
    //   720: goto +456 -> 1176
    //   723: aload_0
    //   724: aload 14
    //   726: invokevirtual 256	android/animation/PropertyValuesHolder:setEvaluator	(Landroid/animation/TypeEvaluator;)V
    //   729: aload_0
    //   730: areturn
    //   731: aload 16
    //   733: astore 14
    //   735: aload 16
    //   737: astore 15
    //   739: iload 7
    //   741: lookupswitch	default:+27->768, 13:+526->1267, 22:+-126->615
    //   768: aload 16
    //   770: astore 14
    //   772: goto -157 -> 615
    //   775: goto +44 -> 819
    //   778: iconst_1
    //   779: istore 7
    //   781: goto -466 -> 315
    //   784: aload_0
    //   785: iload_3
    //   786: fconst_0
    //   787: invokevirtual 222	android/content/res/TypedArray:getFloat	(IF)F
    //   790: fstore 5
    //   792: goto +648 -> 1440
    //   795: getstatic 22	o/ᒻ:ˊ	I
    //   798: bipush 71
    //   800: iadd
    //   801: istore_1
    //   802: iload_1
    //   803: sipush 128
    //   806: irem
    //   807: putstatic 20	o/ᒻ:ˏ	I
    //   810: iload_1
    //   811: iconst_2
    //   812: irem
    //   813: ifeq +6 -> 819
    //   816: goto -41 -> 775
    //   819: aload 16
    //   821: ifnull +6 -> 827
    //   824: goto -586 -> 238
    //   827: aconst_null
    //   828: areturn
    //   829: goto +546 -> 1375
    //   832: getstatic 20	o/ᒻ:ˏ	I
    //   835: bipush 49
    //   837: iadd
    //   838: istore_1
    //   839: iload_1
    //   840: sipush 128
    //   843: irem
    //   844: putstatic 22	o/ᒻ:ˊ	I
    //   847: iload_1
    //   848: iconst_2
    //   849: irem
    //   850: ifne +6 -> 856
    //   853: goto -728 -> 125
    //   856: goto +497 -> 1353
    //   859: iload_1
    //   860: tableswitch	default:+24->884, 0:+713->1573, 1:+24->884
    //   884: aload_0
    //   885: areturn
    //   886: new 8	o/ᒻ$iF
    //   889: dup
    //   890: aconst_null
    //   891: invokespecial 259	o/ᒻ$iF:<init>	(Lo/ᒻ$2;)V
    //   894: astore 17
    //   896: aload 16
    //   898: ifnull +6 -> 904
    //   901: goto +446 -> 1347
    //   904: goto -870 -> 34
    //   907: iload_1
    //   908: ifne +6 -> 914
    //   911: goto +180 -> 1091
    //   914: goto -267 -> 647
    //   917: aload_0
    //   918: iload_3
    //   919: fconst_0
    //   920: invokevirtual 206	android/content/res/TypedArray:getDimension	(IF)F
    //   923: fstore 6
    //   925: goto -446 -> 479
    //   928: iconst_0
    //   929: istore 12
    //   931: goto +132 -> 1063
    //   934: iload_1
    //   935: tableswitch	default:+21->956, 0:+538->1473, 1:+203->1138
    //   956: goto +517 -> 1473
    //   959: iload_1
    //   960: lookupswitch	default:+28->988, 12:+323->1283, 83:+-779->181
    //   988: goto -807 -> 181
    //   991: aload 4
    //   993: iconst_2
    //   994: newarray int
    //   996: dup
    //   997: iconst_0
    //   998: iload_2
    //   999: iastore
    //   1000: dup
    //   1001: iconst_1
    //   1002: iload_1
    //   1003: iastore
    //   1004: invokestatic 229	android/animation/PropertyValuesHolder:ofInt	(Ljava/lang/String;[I)Landroid/animation/PropertyValuesHolder;
    //   1007: astore_0
    //   1008: goto +617 -> 1625
    //   1011: aload 14
    //   1013: getfield 65	android/util/TypedValue:type	I
    //   1016: istore 10
    //   1018: goto -979 -> 39
    //   1021: goto -580 -> 441
    //   1024: iload 8
    //   1026: lookupswitch	default:+26->1052, 0:+71->1097, 33:+529->1555
    //   1052: goto +503 -> 1555
    //   1055: astore_0
    //   1056: aload_0
    //   1057: athrow
    //   1058: iconst_0
    //   1059: istore_1
    //   1060: goto -126 -> 934
    //   1063: iload 12
    //   1065: tableswitch	default:+23->1088, 0:+358->1423, 1:+-787->278
    //   1088: goto +335 -> 1423
    //   1091: iconst_0
    //   1092: istore 11
    //   1094: goto -473 -> 621
    //   1097: aload 14
    //   1099: getfield 65	android/util/TypedValue:type	I
    //   1102: istore 8
    //   1104: goto -83 -> 1021
    //   1107: iload 9
    //   1109: ifeq +6 -> 1115
    //   1112: goto -863 -> 249
    //   1115: goto -441 -> 674
    //   1118: iload 7
    //   1120: ifeq +6 -> 1126
    //   1123: goto +240 -> 1363
    //   1126: aload 15
    //   1128: astore_0
    //   1129: goto +496 -> 1625
    //   1132: iconst_0
    //   1133: istore 10
    //   1135: goto -1096 -> 39
    //   1138: iconst_3
    //   1139: istore_1
    //   1140: goto -879 -> 261
    //   1143: aload_0
    //   1144: iload_3
    //   1145: fconst_0
    //   1146: invokevirtual 222	android/content/res/TypedArray:getFloat	(IF)F
    //   1149: fstore 6
    //   1151: goto -672 -> 479
    //   1154: aload_0
    //   1155: iload_2
    //   1156: invokevirtual 210	android/content/res/TypedArray:peekValue	(I)Landroid/util/TypedValue;
    //   1159: astore 14
    //   1161: aload 14
    //   1163: ifnull +6 -> 1169
    //   1166: goto -551 -> 615
    //   1169: aload 14
    //   1171: astore 15
    //   1173: goto +94 -> 1267
    //   1176: iload 7
    //   1178: ifeq +6 -> 1184
    //   1181: goto +303 -> 1484
    //   1184: goto -1127 -> 57
    //   1187: iload_1
    //   1188: lookupswitch	default:+28->1216, 2:+474->1662, 32:+-81->1107
    //   1216: goto -109 -> 1107
    //   1219: getstatic 22	o/ᒻ:ˊ	I
    //   1222: bipush 87
    //   1224: iadd
    //   1225: istore 7
    //   1227: iload 7
    //   1229: sipush 128
    //   1232: irem
    //   1233: putstatic 20	o/ᒻ:ˏ	I
    //   1236: iload 7
    //   1238: iconst_2
    //   1239: irem
    //   1240: ifeq +6 -> 1246
    //   1243: goto -465 -> 778
    //   1246: goto -1014 -> 232
    //   1249: iload 8
    //   1251: invokestatic 68	o/ᒻ:ˋ	(I)Z
    //   1254: istore 13
    //   1256: iload 13
    //   1258: ifeq +6 -> 1264
    //   1261: goto +36 -> 1297
    //   1264: goto +138 -> 1402
    //   1267: iconst_0
    //   1268: istore 9
    //   1270: aload 15
    //   1272: astore 14
    //   1274: goto +112 -> 1386
    //   1277: bipush 83
    //   1279: istore_1
    //   1280: goto -321 -> 959
    //   1283: iload 8
    //   1285: invokestatic 68	o/ᒻ:ˋ	(I)Z
    //   1288: ifeq +6 -> 1294
    //   1291: goto +344 -> 1635
    //   1294: goto -1160 -> 134
    //   1297: aload_0
    //   1298: iload_3
    //   1299: iconst_0
    //   1300: invokevirtual 262	android/content/res/TypedArray:getColor	(II)I
    //   1303: istore_1
    //   1304: goto -1142 -> 162
    //   1307: iload_1
    //   1308: lookupswitch	default:+28->1336, 0:+-742->566, 96:+-772->536
    //   1336: goto -800 -> 536
    //   1339: goto +286 -> 1625
    //   1342: iconst_0
    //   1343: istore_1
    //   1344: goto -485 -> 859
    //   1347: bipush 96
    //   1349: istore_1
    //   1350: goto -43 -> 1307
    //   1353: aload_0
    //   1354: iload_2
    //   1355: iconst_0
    //   1356: invokevirtual 262	android/content/res/TypedArray:getColor	(II)I
    //   1359: istore_2
    //   1360: goto +254 -> 1614
    //   1363: iload 8
    //   1365: iconst_5
    //   1366: if_icmpne +6 -> 1372
    //   1369: goto -771 -> 598
    //   1372: goto -123 -> 1249
    //   1375: iload 7
    //   1377: ifeq +6 -> 1383
    //   1380: goto -945 -> 435
    //   1383: goto -1228 -> 155
    //   1386: iload 9
    //   1388: ifeq +6 -> 1394
    //   1391: goto -380 -> 1011
    //   1394: goto -262 -> 1132
    //   1397: iconst_1
    //   1398: istore_1
    //   1399: goto -540 -> 859
    //   1402: aload_0
    //   1403: iload_3
    //   1404: iconst_0
    //   1405: invokevirtual 226	android/content/res/TypedArray:getInt	(II)I
    //   1408: istore_1
    //   1409: goto -1247 -> 162
    //   1412: aload_0
    //   1413: iload_3
    //   1414: fconst_0
    //   1415: invokevirtual 206	android/content/res/TypedArray:getDimension	(IF)F
    //   1418: f2i
    //   1419: istore_1
    //   1420: goto -429 -> 991
    //   1423: aconst_null
    //   1424: astore 14
    //   1426: iload_1
    //   1427: iconst_3
    //   1428: if_icmpne +6 -> 1434
    //   1431: goto -979 -> 452
    //   1434: goto -882 -> 552
    //   1437: goto -773 -> 664
    //   1440: aload 4
    //   1442: iconst_1
    //   1443: newarray float
    //   1445: dup
    //   1446: iconst_0
    //   1447: fload 5
    //   1449: fastore
    //   1450: invokestatic 215	android/animation/PropertyValuesHolder:ofFloat	(Ljava/lang/String;[F)Landroid/animation/PropertyValuesHolder;
    //   1453: astore_0
    //   1454: goto -115 -> 1339
    //   1457: aload_0
    //   1458: iload_3
    //   1459: iconst_0
    //   1460: invokevirtual 262	android/content/res/TypedArray:getColor	(II)I
    //   1463: istore_1
    //   1464: goto -473 -> 991
    //   1467: iconst_0
    //   1468: istore 7
    //   1470: goto -95 -> 1375
    //   1473: iconst_0
    //   1474: istore_1
    //   1475: goto -568 -> 907
    //   1478: bipush 12
    //   1480: istore_1
    //   1481: goto -522 -> 959
    //   1484: iload 8
    //   1486: iconst_5
    //   1487: if_icmpne +6 -> 1493
    //   1490: goto -573 -> 917
    //   1493: goto -350 -> 1143
    //   1496: iload 10
    //   1498: invokestatic 68	o/ᒻ:ˋ	(I)Z
    //   1501: ifne +6 -> 1507
    //   1504: goto -1360 -> 144
    //   1507: goto -369 -> 1138
    //   1510: getstatic 20	o/ᒻ:ˏ	I
    //   1513: bipush 13
    //   1515: iadd
    //   1516: istore_1
    //   1517: iload_1
    //   1518: sipush 128
    //   1521: irem
    //   1522: putstatic 22	o/ᒻ:ˊ	I
    //   1525: iload_1
    //   1526: iconst_2
    //   1527: irem
    //   1528: ifne +6 -> 1534
    //   1531: goto -1525 -> 6
    //   1534: goto -822 -> 712
    //   1537: iload 10
    //   1539: invokestatic 68	o/ᒻ:ˋ	(I)Z
    //   1542: istore 13
    //   1544: iload 13
    //   1546: ifeq +6 -> 1552
    //   1549: goto -717 -> 832
    //   1552: goto -1442 -> 110
    //   1555: iconst_0
    //   1556: istore 8
    //   1558: goto -1117 -> 441
    //   1561: iload 10
    //   1563: iconst_5
    //   1564: if_icmpne +6 -> 1570
    //   1567: goto -1544 -> 23
    //   1570: goto -33 -> 1537
    //   1573: getstatic 20	o/ᒻ:ˏ	I
    //   1576: bipush 31
    //   1578: iadd
    //   1579: istore_1
    //   1580: iload_1
    //   1581: sipush 128
    //   1584: irem
    //   1585: putstatic 22	o/ᒻ:ˊ	I
    //   1588: iload_1
    //   1589: iconst_2
    //   1590: irem
    //   1591: ifne +6 -> 1597
    //   1594: goto -157 -> 1437
    //   1597: goto -933 -> 664
    //   1600: iload 8
    //   1602: invokestatic 68	o/ᒻ:ˋ	(I)Z
    //   1605: ifeq +6 -> 1611
    //   1608: goto -1265 -> 343
    //   1611: goto -553 -> 1058
    //   1614: iload 7
    //   1616: ifeq +6 -> 1622
    //   1619: goto -1033 -> 586
    //   1622: goto -926 -> 696
    //   1625: aload_0
    //   1626: ifnull +6 -> 1632
    //   1629: goto -287 -> 1342
    //   1632: goto -235 -> 1397
    //   1635: getstatic 22	o/ᒻ:ˊ	I
    //   1638: bipush 85
    //   1640: iadd
    //   1641: istore_1
    //   1642: iload_1
    //   1643: sipush 128
    //   1646: irem
    //   1647: putstatic 20	o/ᒻ:ˏ	I
    //   1650: iload_1
    //   1651: iconst_2
    //   1652: irem
    //   1653: ifeq +6 -> 1659
    //   1656: goto -1261 -> 395
    //   1659: goto -202 -> 1457
    //   1662: iload 9
    //   1664: ifeq +6 -> 1670
    //   1667: goto -106 -> 1561
    //   1670: goto -552 -> 1118
    //   1673: bipush 32
    //   1675: istore_1
    //   1676: goto -489 -> 1187
    //   1679: aload_0
    //   1680: iload_3
    //   1681: fconst_0
    //   1682: invokevirtual 206	android/content/res/TypedArray:getDimension	(IF)F
    //   1685: fstore 5
    //   1687: goto -247 -> 1440
    //   1690: aload 4
    //   1692: new 8	o/ᒻ$iF
    //   1695: dup
    //   1696: aconst_null
    //   1697: invokespecial 259	o/ᒻ$iF:<init>	(Lo/ᒻ$2;)V
    //   1700: iconst_1
    //   1701: anewarray 4	java/lang/Object
    //   1704: dup
    //   1705: iconst_0
    //   1706: aload 16
    //   1708: aastore
    //   1709: invokestatic 219	android/animation/PropertyValuesHolder:ofObject	(Ljava/lang/String;Landroid/animation/TypeEvaluator;[Ljava/lang/Object;)Landroid/animation/PropertyValuesHolder;
    //   1712: areturn
    // Local variable table:
    //   start	length	slot	name	signature
    //   0	1713	0	paramTypedArray	TypedArray
    //   0	1713	1	paramInt1	int
    //   0	1713	2	paramInt2	int
    //   0	1713	3	paramInt3	int
    //   0	1713	4	paramString	String
    //   64	1	5	localObject1	Object
    //   105	1581	5	f1	float
    //   491	1	6	localObject2	Object
    //   923	227	6	f2	float
    //   144	1471	7	i	int
    //   157	1444	8	j	int
    //   12	1651	9	k	int
    //   249	1316	10	m	int
    //   404	689	11	n	int
    //   129	935	12	i1	int
    //   1254	291	13	bool	boolean
    //   44	1381	14	localObject3	Object
    //   84	1187	15	localObject4	Object
    //   89	1618	16	localObject5	Object
    //   76	819	17	localObject6	Object
    // Exception table:
    //   from	to	target	type
    //   110	117	3	java/lang/Exception
    //   1537	1544	3	java/lang/Exception
    //   501	505	1055	java/lang/Exception
    //   510	518	1055	java/lang/Exception
    //   1249	1256	1055	java/lang/Exception
  }
  
  private static boolean ˋ(int paramInt)
  {
    break label38;
    int i = 33;
    switch (i)
    {
    default: 
      break;
    case 1: 
      for (;;)
      {
        label9:
        break label189;
        label38:
        while (paramInt > 31)
        {
          break label181;
          label53:
          return false;
          if (paramInt >= 57) {
            break label176;
          }
          break label184;
          i = ˏ + 125;
          ˊ = i % 128;
          if (i % 2 == 0) {
            break label159;
          }
          break label154;
          label94:
          i = 11;
          switch (i)
          {
          }
        }
        paramInt = ˏ + 49;
        ˊ = paramInt % 128;
        if (paramInt % 2 != 0)
        {
          break label189;
          label154:
          i = 0;
          break label191;
          label159:
          i = 1;
          break label191;
        }
      }
    }
    while (paramInt < 28)
    {
      break label94;
      label176:
      i = 1;
      break label9;
      label181:
      break label53;
      label184:
      i = 0;
      break label9;
      label189:
      return true;
      label191:
      switch (i)
      {
      }
    }
  }
  
  private static PropertyValuesHolder[] ˋ(Context paramContext, Resources paramResources, Resources.Theme paramTheme, XmlPullParser paramXmlPullParser, AttributeSet paramAttributeSet)
  {
    break label587;
    label3:
    int i;
    switch (i)
    {
    default: 
      break label731;
      label35:
      i = ˊ + 39;
      ˏ = i % 128;
      if (i % 2 == 0)
      {
        break;
        label65:
        break label530;
      }
      label68:
      break;
    }
    for (;;)
    {
      int j;
      TypedArray localTypedArray;
      String str;
      PropertyValuesHolder localPropertyValuesHolder;
      label530:
      label587:
      int k;
      try
      {
        i = ˏ + 89;
        ArrayList localArrayList;
        Object localObject;
        try
        {
          ˊ = i % 128;
          if (i % 2 == 0) {
            continue;
          }
          continue;
          j = 36;
          continue;
          j = 0;
          continue;
          i = 0;
          continue;
          switch (j)
          {
          case 0: 
          default: 
            break label68;
            localArrayList = new ArrayList();
            continue;
            localObject = ˋ(localTypedArray, j, 0, 1, str);
            continue;
            if (paramXmlPullParser.getName().equals("propertyValuesHolder")) {
              break label803;
            }
            continue;
            i = null.length;
            return paramContext;
            localTypedArray.recycle();
            continue;
            paramResources[i] = ((PropertyValuesHolder)localArrayList.get(i));
            i += 9;
            continue;
            i = 62;
            break label3;
            continue;
            j = 1;
            continue;
            localObject = localPropertyValuesHolder;
            switch (i)
            {
            case 85: 
            default: 
              localObject = localPropertyValuesHolder;
              continue;
              j = ˊ + 97;
              ˏ = j % 128;
              if (j % 2 != 0) {
                continue;
              }
              continue;
              paramContext = null;
              if (localArrayList != null) {
                continue;
              }
              break label65;
              if (j != 1) {
                continue;
              }
              continue;
              i = 28;
              continue;
              i = j;
              break label790;
              if (localArrayList == null) {
                continue;
              }
              continue;
              localArrayList = null;
              continue;
              paramXmlPullParser.next();
            }
            break;
          }
        }
        catch (Exception paramContext)
        {
          throw paramContext;
        }
        continue;
        i = 85;
        continue;
        j = 98;
        continue;
        i = 15;
        break;
        switch (i)
        {
        }
        paramXmlPullParser.next();
        continue;
        break label790;
        if (j != 2) {
          continue;
        }
        continue;
        switch (j)
        {
        case 98: 
        default: 
          continue;
          j = paramXmlPullParser.getEventType();
          if (j != 3) {
            continue;
          }
          continue;
          localArrayList.add(localObject);
          continue;
          i = ˏ + 75;
          ˊ = i % 128;
          if (i % 2 == 0) {
            continue;
          }
          return paramContext;
          switch (i)
          {
          }
          continue;
          continue;
          if (j != 1) {
            break label784;
          }
          break;
        case 36: 
          paramResources[i] = ((PropertyValuesHolder)localArrayList.get(i));
          i += 1;
          break;
        }
        i = 24;
        continue;
        paramContext = paramResources;
        switch (j)
        {
        case 0: 
        default: 
          paramContext = paramResources;
          break;
          k = localArrayList.size();
          paramResources = new PropertyValuesHolder[k];
          j = 0;
          break;
        case 1: 
          j = ˏ + 65;
          ˊ = j % 128;
          if (j % 2 == 0) {
            continue;
          }
          continue;
          if (localObject != null) {
            break label35;
          }
          continue;
          j = 1;
          continue;
          label731:
          i = j;
          break label790;
          i = ˊ + 75;
          ˏ = i % 128;
          if (i % 2 != 0) {
            continue;
          }
          continue;
          j = 0;
          continue;
          i = 97;
          continue;
          i = 1;
        }
      }
      catch (Exception paramContext)
      {
        throw paramContext;
      }
      label784:
      continue;
      label790:
      if (i >= k)
      {
        continue;
        label803:
        localTypedArray = ᵁ.ॱ(paramResources, paramTheme, paramAttributeSet, ˤ.ʻ);
        str = ᵁ.ˋ(localTypedArray, paramXmlPullParser, "propertyName", 3);
        j = ᵁ.ˏ(localTypedArray, paramXmlPullParser, "valueType", 2, 4);
        localPropertyValuesHolder = ˏ(paramContext, paramResources, paramTheme, paramXmlPullParser, str, j);
        if (localPropertyValuesHolder == null) {}
      }
    }
  }
  
  /* Error */
  private static Animator ˎ(Context paramContext, Resources paramResources, Resources.Theme paramTheme, XmlPullParser paramXmlPullParser, AttributeSet paramAttributeSet, android.animation.AnimatorSet paramAnimatorSet, int paramInt, float paramFloat)
  {
    // Byte code:
    //   0: goto +977 -> 977
    //   3: iconst_0
    //   4: istore 8
    //   6: goto +891 -> 897
    //   9: getstatic 20	o/ᒻ:ˏ	I
    //   12: istore 8
    //   14: iload 8
    //   16: bipush 97
    //   18: iadd
    //   19: istore 8
    //   21: iload 8
    //   23: sipush 128
    //   26: irem
    //   27: putstatic 22	o/ᒻ:ˊ	I
    //   30: iload 8
    //   32: iconst_2
    //   33: irem
    //   34: ifne +6 -> 40
    //   37: goto +93 -> 130
    //   40: goto +627 -> 667
    //   43: goto +565 -> 608
    //   46: bipush 91
    //   48: istore 8
    //   50: goto +127 -> 177
    //   53: iconst_0
    //   54: istore 8
    //   56: goto +461 -> 517
    //   59: iload 10
    //   61: iconst_2
    //   62: if_icmpeq +6 -> 68
    //   65: goto +953 -> 1018
    //   68: goto +421 -> 489
    //   71: astore_0
    //   72: aload_0
    //   73: athrow
    //   74: aload 11
    //   76: instanceof 313
    //   79: ifeq +6 -> 85
    //   82: goto -73 -> 9
    //   85: goto +517 -> 602
    //   88: aload 13
    //   90: ldc_w 315
    //   93: invokevirtual 281	java/lang/String:equals	(Ljava/lang/Object;)Z
    //   96: ifeq +6 -> 102
    //   99: goto +578 -> 677
    //   102: goto +193 -> 295
    //   105: goto -31 -> 74
    //   108: aload 12
    //   110: ifnonnull +6 -> 116
    //   113: goto +724 -> 837
    //   116: goto +730 -> 846
    //   119: aload 12
    //   121: ifnull +6 -> 127
    //   124: goto +614 -> 738
    //   127: aload 11
    //   129: areturn
    //   130: bipush 85
    //   132: istore 8
    //   134: goto +310 -> 444
    //   137: new 151	java/lang/StringBuilder
    //   140: dup
    //   141: invokespecial 152	java/lang/StringBuilder:<init>	()V
    //   144: astore_0
    //   145: aload_0
    //   146: ldc_w 317
    //   149: invokevirtual 158	java/lang/StringBuilder:append	(Ljava/lang/String;)Ljava/lang/StringBuilder;
    //   152: astore_0
    //   153: new 319	java/lang/RuntimeException
    //   156: dup
    //   157: aload_0
    //   158: aload_3
    //   159: invokeinterface 273 1 0
    //   164: invokevirtual 158	java/lang/StringBuilder:append	(Ljava/lang/String;)Ljava/lang/StringBuilder;
    //   167: invokevirtual 168	java/lang/StringBuilder:toString	()Ljava/lang/String;
    //   170: invokespecial 320	java/lang/RuntimeException:<init>	(Ljava/lang/String;)V
    //   173: athrow
    //   174: goto +476 -> 650
    //   177: iload 8
    //   179: lookupswitch	default:+25->204, 24:+449->628, 91:+423->602
    //   204: goto +424 -> 628
    //   207: getstatic 22	o/ᒻ:ˊ	I
    //   210: bipush 105
    //   212: iadd
    //   213: istore 10
    //   215: iload 10
    //   217: sipush 128
    //   220: irem
    //   221: putstatic 20	o/ᒻ:ˏ	I
    //   224: iload 10
    //   226: iconst_2
    //   227: irem
    //   228: ifeq +6 -> 234
    //   231: goto +244 -> 475
    //   234: goto +630 -> 864
    //   237: iload 10
    //   239: iconst_1
    //   240: if_icmpeq +6 -> 246
    //   243: goto -184 -> 59
    //   246: goto +393 -> 639
    //   249: aload 13
    //   251: ldc_w 322
    //   254: invokevirtual 281	java/lang/String:equals	(Ljava/lang/Object;)Z
    //   257: ifeq +6 -> 263
    //   260: goto +687 -> 947
    //   263: goto -175 -> 88
    //   266: getstatic 20	o/ᒻ:ˏ	I
    //   269: iconst_3
    //   270: iadd
    //   271: istore 8
    //   273: iload 8
    //   275: sipush 128
    //   278: irem
    //   279: putstatic 22	o/ᒻ:ˊ	I
    //   282: iload 8
    //   284: iconst_2
    //   285: irem
    //   286: ifne +6 -> 292
    //   289: goto -184 -> 105
    //   292: goto -218 -> 74
    //   295: aload 13
    //   297: ldc_w 275
    //   300: invokevirtual 281	java/lang/String:equals	(Ljava/lang/Object;)Z
    //   303: ifeq +6 -> 309
    //   306: goto +617 -> 923
    //   309: goto -172 -> 137
    //   312: aload_3
    //   313: invokeinterface 325 1 0
    //   318: iload 9
    //   320: if_icmple +6 -> 326
    //   323: goto +486 -> 809
    //   326: goto -323 -> 3
    //   329: aload_1
    //   330: invokeinterface 330 1 0
    //   335: checkcast 332	android/animation/Animator
    //   338: astore_2
    //   339: iload 8
    //   341: iconst_1
    //   342: iadd
    //   343: istore 9
    //   345: aload_0
    //   346: iload 8
    //   348: aload_2
    //   349: aastore
    //   350: iload 9
    //   352: istore 8
    //   354: goto +468 -> 822
    //   357: goto +317 -> 674
    //   360: aload 11
    //   362: checkcast 313	android/animation/ValueAnimator
    //   365: aload 13
    //   367: invokevirtual 336	android/animation/ValueAnimator:setValues	([Landroid/animation/PropertyValuesHolder;)V
    //   370: new 191	java/lang/NullPointerException
    //   373: dup
    //   374: invokespecial 192	java/lang/NullPointerException:<init>	()V
    //   377: athrow
    //   378: iload 8
    //   380: lookupswitch	default:+28->408, 21:+-114->266, 30:+222->602
    //   408: goto -142 -> 266
    //   411: aload 5
    //   413: ifnull +6 -> 419
    //   416: goto +62 -> 478
    //   419: goto -376 -> 43
    //   422: astore_0
    //   423: aload_0
    //   424: athrow
    //   425: aload_0
    //   426: aload_1
    //   427: aload_2
    //   428: aload 4
    //   430: fload 7
    //   432: aload_3
    //   433: invokestatic 338	o/ᒻ:ˊ	(Landroid/content/Context;Landroid/content/res/Resources;Landroid/content/res/Resources$Theme;Landroid/util/AttributeSet;FLorg/xmlpull/v1/XmlPullParser;)Landroid/animation/ObjectAnimator;
    //   436: astore 11
    //   438: goto -27 -> 411
    //   441: goto +539 -> 980
    //   444: iload 8
    //   446: lookupswitch	default:+26->472, 22:+104->550, 85:+-86->360
    //   472: goto -112 -> 360
    //   475: goto +389 -> 864
    //   478: iload 8
    //   480: ifne +6 -> 486
    //   483: goto -375 -> 108
    //   486: goto -443 -> 43
    //   489: aload_3
    //   490: invokeinterface 273 1 0
    //   495: astore 13
    //   497: iconst_0
    //   498: istore 8
    //   500: aload 13
    //   502: ldc_w 340
    //   505: invokevirtual 281	java/lang/String:equals	(Ljava/lang/Object;)Z
    //   508: ifeq +6 -> 514
    //   511: goto -86 -> 425
    //   514: goto -265 -> 249
    //   517: iload 8
    //   519: tableswitch	default:+21->540, 0:+478->997, 1:+-400->119
    //   540: goto -421 -> 119
    //   543: bipush 21
    //   545: istore 8
    //   547: goto -169 -> 378
    //   550: aload 11
    //   552: checkcast 313	android/animation/ValueAnimator
    //   555: aload 13
    //   557: invokevirtual 336	android/animation/ValueAnimator:setValues	([Landroid/animation/PropertyValuesHolder;)V
    //   560: goto +42 -> 602
    //   563: aload 5
    //   565: aload_0
    //   566: invokevirtual 346	android/animation/AnimatorSet:playSequentially	([Landroid/animation/Animator;)V
    //   569: goto +210 -> 779
    //   572: getstatic 22	o/ᒻ:ˊ	I
    //   575: bipush 49
    //   577: iadd
    //   578: istore 8
    //   580: iload 8
    //   582: sipush 128
    //   585: irem
    //   586: putstatic 20	o/ᒻ:ˏ	I
    //   589: iload 8
    //   591: iconst_2
    //   592: irem
    //   593: ifeq +6 -> 599
    //   596: goto -155 -> 441
    //   599: goto +381 -> 980
    //   602: iconst_1
    //   603: istore 8
    //   605: goto -398 -> 207
    //   608: aload_3
    //   609: invokeinterface 289 1 0
    //   614: istore 10
    //   616: iload 10
    //   618: iconst_3
    //   619: if_icmpne +6 -> 625
    //   622: goto -310 -> 312
    //   625: goto -388 -> 237
    //   628: aload 11
    //   630: ifnull +6 -> 636
    //   633: goto -90 -> 543
    //   636: goto +221 -> 857
    //   639: aload 5
    //   641: ifnull +6 -> 647
    //   644: goto +223 -> 867
    //   647: aload 11
    //   649: areturn
    //   650: aload_0
    //   651: aload_1
    //   652: aload_2
    //   653: aload 4
    //   655: aconst_null
    //   656: fload 7
    //   658: aload_3
    //   659: invokestatic 118	o/ᒻ:ˏ	(Landroid/content/Context;Landroid/content/res/Resources;Landroid/content/res/Resources$Theme;Landroid/util/AttributeSet;Landroid/animation/ValueAnimator;FLorg/xmlpull/v1/XmlPullParser;)Landroid/animation/ValueAnimator;
    //   662: astore 11
    //   664: goto -253 -> 411
    //   667: bipush 22
    //   669: istore 8
    //   671: goto -227 -> 444
    //   674: aload 11
    //   676: areturn
    //   677: new 342	android/animation/AnimatorSet
    //   680: dup
    //   681: invokespecial 347	android/animation/AnimatorSet:<init>	()V
    //   684: astore 11
    //   686: aload_1
    //   687: aload_2
    //   688: aload 4
    //   690: getstatic 350	o/ˤ:ॱॱ	[I
    //   693: invokestatic 54	o/ᵁ:ॱ	(Landroid/content/res/Resources;Landroid/content/res/Resources$Theme;Landroid/util/AttributeSet;[I)Landroid/content/res/TypedArray;
    //   696: astore 13
    //   698: aload 13
    //   700: aload_3
    //   701: ldc_w 352
    //   704: iconst_0
    //   705: iconst_0
    //   706: invokestatic 99	o/ᵁ:ˏ	(Landroid/content/res/TypedArray;Lorg/xmlpull/v1/XmlPullParser;Ljava/lang/String;II)I
    //   709: istore 10
    //   711: aload_0
    //   712: aload_1
    //   713: aload_2
    //   714: aload_3
    //   715: aload 4
    //   717: aload 11
    //   719: checkcast 342	android/animation/AnimatorSet
    //   722: iload 10
    //   724: fload 7
    //   726: invokestatic 201	o/ᒻ:ˎ	(Landroid/content/Context;Landroid/content/res/Resources;Landroid/content/res/Resources$Theme;Lorg/xmlpull/v1/XmlPullParser;Landroid/util/AttributeSet;Landroid/animation/AnimatorSet;IF)Landroid/animation/Animator;
    //   729: pop
    //   730: aload 13
    //   732: invokevirtual 73	android/content/res/TypedArray:recycle	()V
    //   735: goto -324 -> 411
    //   738: aload 12
    //   740: invokevirtual 298	java/util/ArrayList:size	()I
    //   743: anewarray 332	android/animation/Animator
    //   746: astore_0
    //   747: iconst_0
    //   748: istore 8
    //   750: aload 12
    //   752: invokevirtual 356	java/util/ArrayList:iterator	()Ljava/util/Iterator;
    //   755: astore_1
    //   756: goto +66 -> 822
    //   759: iload 6
    //   761: ifne +6 -> 767
    //   764: goto +6 -> 770
    //   767: goto -204 -> 563
    //   770: aload 5
    //   772: aload_0
    //   773: invokevirtual 359	android/animation/AnimatorSet:playTogether	([Landroid/animation/Animator;)V
    //   776: aload 11
    //   778: areturn
    //   779: getstatic 22	o/ᒻ:ˊ	I
    //   782: bipush 17
    //   784: iadd
    //   785: istore 6
    //   787: iload 6
    //   789: sipush 128
    //   792: irem
    //   793: putstatic 20	o/ᒻ:ˏ	I
    //   796: iload 6
    //   798: iconst_2
    //   799: irem
    //   800: ifeq +6 -> 806
    //   803: goto -446 -> 357
    //   806: goto -132 -> 674
    //   809: iconst_1
    //   810: istore 8
    //   812: goto +85 -> 897
    //   815: bipush 24
    //   817: istore 8
    //   819: goto -642 -> 177
    //   822: aload_1
    //   823: invokeinterface 363 1 0
    //   828: ifeq +6 -> 834
    //   831: goto -502 -> 329
    //   834: goto -75 -> 759
    //   837: new 265	java/util/ArrayList
    //   840: dup
    //   841: invokespecial 266	java/util/ArrayList:<init>	()V
    //   844: astore 12
    //   846: aload 12
    //   848: aload 11
    //   850: invokevirtual 295	java/util/ArrayList:add	(Ljava/lang/Object;)Z
    //   853: pop
    //   854: goto -811 -> 43
    //   857: bipush 30
    //   859: istore 8
    //   861: goto -483 -> 378
    //   864: goto -453 -> 411
    //   867: getstatic 22	o/ᒻ:ˊ	I
    //   870: bipush 31
    //   872: iadd
    //   873: istore 8
    //   875: iload 8
    //   877: sipush 128
    //   880: irem
    //   881: putstatic 20	o/ᒻ:ˏ	I
    //   884: iload 8
    //   886: iconst_2
    //   887: irem
    //   888: ifeq +6 -> 894
    //   891: goto -838 -> 53
    //   894: goto +118 -> 1012
    //   897: iload 8
    //   899: tableswitch	default:+21->920, 0:+-260->639, 1:+-662->237
    //   920: goto -281 -> 639
    //   923: aload_0
    //   924: aload_1
    //   925: aload_2
    //   926: aload_3
    //   927: aload_3
    //   928: invokestatic 198	android/util/Xml:asAttributeSet	(Lorg/xmlpull/v1/XmlPullParser;)Landroid/util/AttributeSet;
    //   931: invokestatic 365	o/ᒻ:ˋ	(Landroid/content/Context;Landroid/content/res/Resources;Landroid/content/res/Resources$Theme;Lorg/xmlpull/v1/XmlPullParser;Landroid/util/AttributeSet;)[Landroid/animation/PropertyValuesHolder;
    //   934: astore 13
    //   936: aload 13
    //   938: ifnull +6 -> 944
    //   941: goto -126 -> 815
    //   944: goto -898 -> 46
    //   947: getstatic 20	o/ᒻ:ˏ	I
    //   950: bipush 43
    //   952: iadd
    //   953: istore 10
    //   955: iload 10
    //   957: sipush 128
    //   960: irem
    //   961: putstatic 22	o/ᒻ:ˊ	I
    //   964: iload 10
    //   966: iconst_2
    //   967: irem
    //   968: ifne +6 -> 974
    //   971: goto -797 -> 174
    //   974: goto -324 -> 650
    //   977: goto -405 -> 572
    //   980: aconst_null
    //   981: astore 11
    //   983: aconst_null
    //   984: astore 12
    //   986: aload_3
    //   987: invokeinterface 325 1 0
    //   992: istore 9
    //   994: goto -386 -> 608
    //   997: aconst_null
    //   998: arraylength
    //   999: istore 8
    //   1001: aload 12
    //   1003: ifnull +6 -> 1009
    //   1006: goto -268 -> 738
    //   1009: aload 11
    //   1011: areturn
    //   1012: iconst_1
    //   1013: istore 8
    //   1015: goto -498 -> 517
    //   1018: goto -410 -> 608
    // Local variable table:
    //   start	length	slot	name	signature
    //   0	1021	0	paramContext	Context
    //   0	1021	1	paramResources	Resources
    //   0	1021	2	paramTheme	Resources.Theme
    //   0	1021	3	paramXmlPullParser	XmlPullParser
    //   0	1021	4	paramAttributeSet	AttributeSet
    //   0	1021	5	paramAnimatorSet	android.animation.AnimatorSet
    //   0	1021	6	paramInt	int
    //   0	1021	7	paramFloat	float
    //   4	1010	8	i	int
    //   318	675	9	j	int
    //   59	909	10	k	int
    //   74	936	11	localObject1	Object
    //   108	894	12	localArrayList	ArrayList
    //   88	849	13	localObject2	Object
    // Exception table:
    //   from	to	target	type
    //   145	153	71	java/lang/Exception
    //   9	14	422	java/lang/Exception
    //   21	30	422	java/lang/Exception
    //   608	616	422	java/lang/Exception
  }
  
  private static void ˎ(Keyframe[] paramArrayOfKeyframe, float paramFloat, int paramInt1, int paramInt2)
  {
    break label84;
    paramArrayOfKeyframe[paramInt1].setFraction(paramArrayOfKeyframe[(paramInt1 - 1)].getFraction() + paramFloat);
    paramInt1 += 1;
    break label73;
    label26:
    int i = 77;
    break label91;
    i = 50;
    break label123;
    paramFloat /= (paramInt2 - paramInt1 + 2);
    break label73;
    paramArrayOfKeyframe[paramInt1].setFraction(paramArrayOfKeyframe[(paramInt1 >> 1)].getFraction() % paramFloat);
    paramInt1 += 79;
    label73:
    label84:
    if (paramInt1 > paramInt2) {
      break label155;
    }
    for (;;)
    {
      i = 97;
      label91:
      switch (i)
      {
      }
      break;
      for (;;)
      {
        switch (i)
        {
        case 50: 
        default: 
          label123:
          break;
          label155:
          return;
        }
        paramFloat *= paramInt2 * paramInt1 % 3;
        break label73;
        i = ˏ + 29;
        ˊ = i % 128;
        if (i % 2 != 0) {
          break;
        }
        i = 56;
      }
      i = ˏ + 3;
      ˊ = i % 128;
      if (i % 2 == 0) {
        break label26;
      }
    }
  }
  
  /* Error */
  private static int ˏ(TypedArray paramTypedArray, int paramInt1, int paramInt2)
  {
    // Byte code:
    //   0: goto +391 -> 391
    //   3: iconst_0
    //   4: ireturn
    //   5: iload_1
    //   6: lookupswitch	default:+26->32, 19:+-3->3, 54:+243->249
    //   32: goto +217 -> 249
    //   35: iload_3
    //   36: invokestatic 68	o/ᒻ:ˋ	(I)Z
    //   39: ifne +6 -> 45
    //   42: goto +268 -> 310
    //   45: goto +204 -> 249
    //   48: bipush 19
    //   50: istore_1
    //   51: goto -46 -> 5
    //   54: iload_1
    //   55: ifeq +6 -> 61
    //   58: goto +123 -> 181
    //   61: goto +125 -> 186
    //   64: goto +39 -> 103
    //   67: iload_1
    //   68: ifeq +6 -> 74
    //   71: goto +288 -> 359
    //   74: goto +94 -> 168
    //   77: iload_1
    //   78: tableswitch	default:+22->100, 0:+-43->35, 1:+232->310
    //   100: goto -65 -> 35
    //   103: goto -36 -> 67
    //   106: iconst_0
    //   107: istore_1
    //   108: goto +327 -> 435
    //   111: aload 5
    //   113: getfield 65	android/util/TypedValue:type	I
    //   116: istore_3
    //   117: goto +79 -> 196
    //   120: iload_2
    //   121: invokestatic 68	o/ᒻ:ˋ	(I)Z
    //   124: ifeq +6 -> 130
    //   127: goto +116 -> 243
    //   130: goto -82 -> 48
    //   133: goto +264 -> 397
    //   136: goto +261 -> 397
    //   139: bipush 9
    //   141: istore_3
    //   142: goto +70 -> 212
    //   145: aload_0
    //   146: iload_1
    //   147: invokevirtual 210	android/content/res/TypedArray:peekValue	(I)Landroid/util/TypedValue;
    //   150: astore 5
    //   152: bipush 97
    //   154: iconst_0
    //   155: idiv
    //   156: istore_1
    //   157: aload 5
    //   159: ifnull +6 -> 165
    //   162: goto +89 -> 251
    //   165: goto +26 -> 191
    //   168: iconst_1
    //   169: istore_3
    //   170: goto +238 -> 408
    //   173: aload_0
    //   174: getfield 65	android/util/TypedValue:type	I
    //   177: istore_2
    //   178: goto -124 -> 54
    //   181: iconst_0
    //   182: istore_1
    //   183: goto -106 -> 77
    //   186: iconst_1
    //   187: istore_1
    //   188: goto -111 -> 77
    //   191: iconst_0
    //   192: istore_1
    //   193: goto +68 -> 261
    //   196: aload_0
    //   197: iload_2
    //   198: invokevirtual 210	android/content/res/TypedArray:peekValue	(I)Landroid/util/TypedValue;
    //   201: astore_0
    //   202: aload_0
    //   203: ifnull +6 -> 209
    //   206: goto +275 -> 481
    //   209: goto +298 -> 507
    //   212: iload_3
    //   213: lookupswitch	default:+27->240, 9:+250->463, 67:+-68->145
    //   240: goto +223 -> 463
    //   243: bipush 54
    //   245: istore_1
    //   246: goto -241 -> 5
    //   249: iconst_3
    //   250: ireturn
    //   251: iconst_1
    //   252: istore_1
    //   253: goto +111 -> 364
    //   256: iconst_0
    //   257: istore_3
    //   258: goto -62 -> 196
    //   261: goto -194 -> 67
    //   264: getstatic 20	o/ᒻ:ˏ	I
    //   267: istore_3
    //   268: iload_3
    //   269: bipush 113
    //   271: iadd
    //   272: istore_3
    //   273: iload_3
    //   274: sipush 128
    //   277: irem
    //   278: putstatic 22	o/ᒻ:ˊ	I
    //   281: iload_3
    //   282: iconst_2
    //   283: irem
    //   284: ifne +6 -> 290
    //   287: goto +12 -> 299
    //   290: goto -151 -> 139
    //   293: iconst_1
    //   294: istore 4
    //   296: goto +101 -> 397
    //   299: bipush 67
    //   301: istore_3
    //   302: goto -90 -> 212
    //   305: iconst_1
    //   306: istore_1
    //   307: goto +128 -> 435
    //   310: iload 4
    //   312: ifeq +6 -> 318
    //   315: goto -10 -> 305
    //   318: goto -212 -> 106
    //   321: iconst_0
    //   322: istore_2
    //   323: goto -269 -> 54
    //   326: astore_0
    //   327: aload_0
    //   328: athrow
    //   329: getstatic 22	o/ᒻ:ˊ	I
    //   332: bipush 35
    //   334: iadd
    //   335: istore_2
    //   336: iload_2
    //   337: sipush 128
    //   340: irem
    //   341: putstatic 20	o/ᒻ:ˏ	I
    //   344: iload_2
    //   345: iconst_2
    //   346: irem
    //   347: ifeq +6 -> 353
    //   350: goto -214 -> 136
    //   353: goto -220 -> 133
    //   356: astore_0
    //   357: aload_0
    //   358: athrow
    //   359: iconst_0
    //   360: istore_3
    //   361: goto +47 -> 408
    //   364: getstatic 20	o/ᒻ:ˏ	I
    //   367: bipush 81
    //   369: iadd
    //   370: istore_3
    //   371: iload_3
    //   372: sipush 128
    //   375: irem
    //   376: putstatic 22	o/ᒻ:ˊ	I
    //   379: iload_3
    //   380: iconst_2
    //   381: irem
    //   382: ifne +6 -> 388
    //   385: goto -321 -> 64
    //   388: goto -285 -> 103
    //   391: goto -127 -> 264
    //   394: goto -101 -> 293
    //   397: iload 4
    //   399: ifeq +6 -> 405
    //   402: goto -229 -> 173
    //   405: goto -84 -> 321
    //   408: iload_3
    //   409: tableswitch	default:+23->432, 0:+-298->111, 1:+-153->256
    //   432: goto -321 -> 111
    //   435: iload_1
    //   436: tableswitch	default:+24->460, 0:+-433->3, 1:+-316->120
    //   460: goto -340 -> 120
    //   463: aload_0
    //   464: iload_1
    //   465: invokevirtual 210	android/content/res/TypedArray:peekValue	(I)Landroid/util/TypedValue;
    //   468: astore 5
    //   470: aload 5
    //   472: ifnull +6 -> 478
    //   475: goto -224 -> 251
    //   478: goto -287 -> 191
    //   481: getstatic 20	o/ᒻ:ˏ	I
    //   484: iconst_3
    //   485: iadd
    //   486: istore_2
    //   487: iload_2
    //   488: sipush 128
    //   491: irem
    //   492: putstatic 22	o/ᒻ:ˊ	I
    //   495: iload_2
    //   496: iconst_2
    //   497: irem
    //   498: ifne +6 -> 504
    //   501: goto -107 -> 394
    //   504: goto -211 -> 293
    //   507: iconst_0
    //   508: istore 4
    //   510: goto -181 -> 329
    // Local variable table:
    //   start	length	slot	name	signature
    //   0	513	0	paramTypedArray	TypedArray
    //   0	513	1	paramInt1	int
    //   0	513	2	paramInt2	int
    //   35	374	3	i	int
    //   294	215	4	j	int
    //   111	360	5	localTypedValue	TypedValue
    // Exception table:
    //   from	to	target	type
    //   463	470	326	java/lang/Exception
    //   264	268	356	java/lang/Exception
    //   273	281	356	java/lang/Exception
  }
  
  public static Animator ˏ(Context paramContext, Resources paramResources, Resources.Theme paramTheme, int paramInt)
  {
    break label92;
    paramInt = 34;
    try
    {
      label9:
      int i = ˏ + 33;
      try
      {
        ˊ = i % 128;
        if (i % 2 == 0) {
          break label83;
        }
      }
      catch (Exception paramContext)
      {
        label39:
        throw paramContext;
      }
      switch (paramInt)
      {
      default: 
        return paramContext;
      case 34: 
        throw new NullPointerException();
      }
      return paramContext;
    }
    catch (Exception paramContext)
    {
      label83:
      label92:
      throw paramContext;
    }
    for (;;)
    {
      paramInt = 37;
      break label39;
      break label9;
      paramContext = ˋ(paramContext, paramResources, paramTheme, paramInt, 1.0F);
      paramInt = ˏ + 89;
      ˊ = paramInt % 128;
      if (paramInt % 2 == 0) {
        break;
      }
    }
  }
  
  /* Error */
  private static Keyframe ˏ(Keyframe paramKeyframe, float paramFloat)
  {
    // Byte code:
    //   0: getstatic 20	o/ᒻ:ˏ	I
    //   3: bipush 23
    //   5: iadd
    //   6: istore_2
    //   7: iload_2
    //   8: sipush 128
    //   11: irem
    //   12: putstatic 22	o/ᒻ:ˊ	I
    //   15: iload_2
    //   16: iconst_2
    //   17: irem
    //   18: ifne +6 -> 24
    //   21: goto +58 -> 79
    //   24: goto +95 -> 119
    //   27: astore_0
    //   28: aload_0
    //   29: athrow
    //   30: aload_0
    //   31: areturn
    //   32: fload_1
    //   33: invokestatic 380	android/animation/Keyframe:ofObject	(F)Landroid/animation/Keyframe;
    //   36: areturn
    //   37: getstatic 22	o/ᒻ:ˊ	I
    //   40: bipush 17
    //   42: iadd
    //   43: istore_2
    //   44: iload_2
    //   45: sipush 128
    //   48: irem
    //   49: putstatic 20	o/ᒻ:ˏ	I
    //   52: iload_2
    //   53: iconst_2
    //   54: irem
    //   55: ifeq +6 -> 61
    //   58: goto +83 -> 141
    //   61: fload_1
    //   62: invokestatic 97	android/animation/Keyframe:ofFloat	(F)Landroid/animation/Keyframe;
    //   65: astore_0
    //   66: goto -36 -> 30
    //   69: iconst_0
    //   70: istore_2
    //   71: goto +73 -> 144
    //   74: iconst_1
    //   75: istore_2
    //   76: goto +16 -> 92
    //   79: goto +40 -> 119
    //   82: iconst_0
    //   83: istore_2
    //   84: goto +8 -> 92
    //   87: fload_1
    //   88: invokestatic 85	android/animation/Keyframe:ofInt	(F)Landroid/animation/Keyframe;
    //   91: areturn
    //   92: iload_2
    //   93: tableswitch	default:+23->116, 0:+78->171, 1:+-56->37
    //   116: goto -79 -> 37
    //   119: aload_0
    //   120: invokevirtual 384	android/animation/Keyframe:getType	()Ljava/lang/Class;
    //   123: astore_3
    //   124: getstatic 390	java/lang/Float:TYPE	Ljava/lang/Class;
    //   127: astore 4
    //   129: aload_3
    //   130: aload 4
    //   132: if_acmpne +6 -> 138
    //   135: goto -61 -> 74
    //   138: goto -56 -> 82
    //   141: goto -80 -> 61
    //   144: iload_2
    //   145: tableswitch	default:+23->168, 0:+-113->32, 1:+-58->87
    //   168: goto -81 -> 87
    //   171: aload_0
    //   172: invokevirtual 384	android/animation/Keyframe:getType	()Ljava/lang/Class;
    //   175: getstatic 391	java/lang/Integer:TYPE	Ljava/lang/Class;
    //   178: if_acmpne +6 -> 184
    //   181: goto +9 -> 190
    //   184: goto -115 -> 69
    //   187: astore_0
    //   188: aload_0
    //   189: athrow
    //   190: iconst_1
    //   191: istore_2
    //   192: goto -48 -> 144
    // Local variable table:
    //   start	length	slot	name	signature
    //   0	195	0	paramKeyframe	Keyframe
    //   0	195	1	paramFloat	float
    //   6	186	2	i	int
    //   123	7	3	localClass1	Class
    //   127	4	4	localClass2	Class
    // Exception table:
    //   from	to	target	type
    //   119	124	27	java/lang/Exception
    //   124	129	187	java/lang/Exception
  }
  
  /* Error */
  private static PropertyValuesHolder ˏ(Context paramContext, Resources paramResources, Resources.Theme paramTheme, XmlPullParser paramXmlPullParser, String paramString, int paramInt)
  {
    // Byte code:
    //   0: goto +1032 -> 1032
    //   3: fload 6
    //   5: fconst_0
    //   6: fcmpg
    //   7: ifge +6 -> 13
    //   10: goto +519 -> 529
    //   13: goto +894 -> 907
    //   16: iload 5
    //   18: iconst_4
    //   19: if_icmpne +6 -> 25
    //   22: goto +975 -> 997
    //   25: goto +368 -> 393
    //   28: iconst_0
    //   29: istore 7
    //   31: goto +708 -> 739
    //   34: getstatic 20	o/ᒻ:ˏ	I
    //   37: istore 8
    //   39: iload 8
    //   41: bipush 103
    //   43: iadd
    //   44: istore 8
    //   46: iload 8
    //   48: sipush 128
    //   51: irem
    //   52: putstatic 22	o/ᒻ:ˊ	I
    //   55: iload 8
    //   57: iconst_2
    //   58: irem
    //   59: ifne +6 -> 65
    //   62: goto +328 -> 390
    //   65: goto +487 -> 552
    //   68: getstatic 20	o/ᒻ:ˏ	I
    //   71: bipush 121
    //   73: iadd
    //   74: istore 5
    //   76: iload 5
    //   78: sipush 128
    //   81: irem
    //   82: putstatic 22	o/ᒻ:ˊ	I
    //   85: iload 5
    //   87: iconst_2
    //   88: irem
    //   89: ifne +6 -> 95
    //   92: goto +471 -> 563
    //   95: aload_0
    //   96: areturn
    //   97: iload 8
    //   99: lookupswitch	default:+25->124, 49:+373->472, 56:+51->150
    //   124: goto +348 -> 472
    //   127: aload_0
    //   128: invokevirtual 370	android/animation/Keyframe:getFraction	()F
    //   131: fstore 6
    //   133: fload 6
    //   135: fconst_0
    //   136: fcmpl
    //   137: ifeq +6 -> 143
    //   140: goto +226 -> 366
    //   143: iload 7
    //   145: istore 9
    //   147: goto +459 -> 606
    //   150: aload_0
    //   151: fconst_0
    //   152: invokevirtual 374	android/animation/Keyframe:setFraction	(F)V
    //   155: goto +830 -> 985
    //   158: iload 7
    //   160: iload 9
    //   162: iconst_1
    //   163: isub
    //   164: if_icmpne +6 -> 170
    //   167: goto +651 -> 818
    //   170: goto +635 -> 805
    //   173: bipush 56
    //   175: istore 8
    //   177: goto -80 -> 97
    //   180: aload_1
    //   181: iload 8
    //   183: aaload
    //   184: astore_0
    //   185: aload_0
    //   186: invokevirtual 370	android/animation/Keyframe:getFraction	()F
    //   189: fstore 6
    //   191: fload 6
    //   193: fconst_0
    //   194: fcmpl
    //   195: iflt +6 -> 201
    //   198: goto +487 -> 685
    //   201: goto +286 -> 487
    //   204: aload_0
    //   205: fconst_0
    //   206: invokevirtual 374	android/animation/Keyframe:setFraction	(F)V
    //   209: goto +776 -> 985
    //   212: iconst_0
    //   213: istore 8
    //   215: goto +494 -> 709
    //   218: aload 4
    //   220: aload_1
    //   221: invokestatic 395	android/animation/PropertyValuesHolder:ofKeyframe	(Ljava/lang/String;[Landroid/animation/Keyframe;)Landroid/animation/PropertyValuesHolder;
    //   224: astore_0
    //   225: iload 5
    //   227: iconst_3
    //   228: if_icmpne +6 -> 234
    //   231: goto +666 -> 897
    //   234: goto +856 -> 1090
    //   237: iload 7
    //   239: iload 9
    //   241: if_icmpge +6 -> 247
    //   244: goto +623 -> 867
    //   247: goto -29 -> 218
    //   250: aload 12
    //   252: ifnull +6 -> 258
    //   255: goto +313 -> 568
    //   258: aload 14
    //   260: astore_0
    //   261: goto +829 -> 1090
    //   264: getstatic 20	o/ᒻ:ˏ	I
    //   267: bipush 39
    //   269: iadd
    //   270: istore 8
    //   272: iload 8
    //   274: sipush 128
    //   277: irem
    //   278: putstatic 22	o/ᒻ:ˊ	I
    //   281: iload 8
    //   283: iconst_2
    //   284: irem
    //   285: ifne +6 -> 291
    //   288: goto +315 -> 603
    //   291: goto +787 -> 1078
    //   294: aload 12
    //   296: iconst_0
    //   297: invokevirtual 285	java/util/ArrayList:get	(I)Ljava/lang/Object;
    //   300: checkcast 81	android/animation/Keyframe
    //   303: astore_0
    //   304: aload 12
    //   306: iload 7
    //   308: iconst_1
    //   309: isub
    //   310: invokevirtual 285	java/util/ArrayList:get	(I)Ljava/lang/Object;
    //   313: checkcast 81	android/animation/Keyframe
    //   316: astore_1
    //   317: aload_1
    //   318: invokevirtual 370	android/animation/Keyframe:getFraction	()F
    //   321: fstore 6
    //   323: fload 6
    //   325: fconst_1
    //   326: fcmpg
    //   327: ifge +6 -> 333
    //   330: goto -327 -> 3
    //   333: goto -206 -> 127
    //   336: getstatic 22	o/ᒻ:ˊ	I
    //   339: bipush 69
    //   341: iadd
    //   342: istore 8
    //   344: iload 8
    //   346: sipush 128
    //   349: irem
    //   350: putstatic 20	o/ᒻ:ˏ	I
    //   353: iload 8
    //   355: iconst_2
    //   356: irem
    //   357: ifeq +6 -> 363
    //   360: goto -148 -> 212
    //   363: goto +117 -> 480
    //   366: fload 6
    //   368: fconst_0
    //   369: fcmpg
    //   370: ifge +6 -> 376
    //   373: goto -109 -> 264
    //   376: goto +589 -> 965
    //   379: aload 12
    //   381: ifnonnull +6 -> 387
    //   384: goto +547 -> 931
    //   387: goto +150 -> 537
    //   390: goto +162 -> 552
    //   393: aload_0
    //   394: aload_1
    //   395: aload_2
    //   396: aload_3
    //   397: invokestatic 198	android/util/Xml:asAttributeSet	(Lorg/xmlpull/v1/XmlPullParser;)Landroid/util/AttributeSet;
    //   400: iload 5
    //   402: aload_3
    //   403: invokestatic 397	o/ᒻ:ˊ	(Landroid/content/Context;Landroid/content/res/Resources;Landroid/content/res/Resources$Theme;Landroid/util/AttributeSet;ILorg/xmlpull/v1/XmlPullParser;)Landroid/animation/Keyframe;
    //   406: astore 15
    //   408: aload 15
    //   410: ifnull +6 -> 416
    //   413: goto +110 -> 523
    //   416: goto -388 -> 28
    //   419: astore_0
    //   420: aload_0
    //   421: athrow
    //   422: aload_1
    //   423: aload_1
    //   424: iload 10
    //   426: iconst_1
    //   427: iadd
    //   428: aaload
    //   429: invokevirtual 370	android/animation/Keyframe:getFraction	()F
    //   432: aload_1
    //   433: iload 7
    //   435: iconst_1
    //   436: isub
    //   437: aaload
    //   438: invokevirtual 370	android/animation/Keyframe:getFraction	()F
    //   441: fsub
    //   442: iload 7
    //   444: iload 10
    //   446: invokestatic 399	o/ᒻ:ˎ	([Landroid/animation/Keyframe;FII)V
    //   449: goto +536 -> 985
    //   452: aload_1
    //   453: iload 7
    //   455: aaload
    //   456: astore_0
    //   457: aload_0
    //   458: invokevirtual 370	android/animation/Keyframe:getFraction	()F
    //   461: fconst_0
    //   462: fcmpg
    //   463: ifge +6 -> 469
    //   466: goto -432 -> 34
    //   469: goto +516 -> 985
    //   472: aload_0
    //   473: fconst_1
    //   474: invokevirtual 374	android/animation/Keyframe:setFraction	(F)V
    //   477: goto +508 -> 985
    //   480: bipush 15
    //   482: istore 8
    //   484: goto +225 -> 709
    //   487: iload 8
    //   489: istore 10
    //   491: iload 8
    //   493: iconst_1
    //   494: iadd
    //   495: istore 8
    //   497: goto +355 -> 852
    //   500: astore_0
    //   501: aload_0
    //   502: athrow
    //   503: aload_3
    //   504: invokeinterface 289 1 0
    //   509: istore 7
    //   511: iload 7
    //   513: iconst_3
    //   514: if_icmpeq +6 -> 520
    //   517: goto +433 -> 950
    //   520: goto -270 -> 250
    //   523: iconst_1
    //   524: istore 7
    //   526: goto +213 -> 739
    //   529: aload_1
    //   530: fconst_1
    //   531: invokevirtual 374	android/animation/Keyframe:setFraction	(F)V
    //   534: goto -407 -> 127
    //   537: aload 12
    //   539: aload 15
    //   541: invokevirtual 295	java/util/ArrayList:add	(Ljava/lang/Object;)Z
    //   544: pop
    //   545: aload 12
    //   547: astore 13
    //   549: goto +146 -> 695
    //   552: iload 7
    //   554: ifne +6 -> 560
    //   557: goto -353 -> 204
    //   560: goto -402 -> 158
    //   563: aload_0
    //   564: areturn
    //   565: goto -271 -> 294
    //   568: aload 12
    //   570: invokevirtual 298	java/util/ArrayList:size	()I
    //   573: istore 8
    //   575: iload 8
    //   577: istore 7
    //   579: iload 8
    //   581: ifle +6 -> 587
    //   584: goto +191 -> 775
    //   587: aload 14
    //   589: astore_0
    //   590: goto +500 -> 1090
    //   593: goto -466 -> 127
    //   596: iload 11
    //   598: istore 8
    //   600: goto +252 -> 852
    //   603: goto +475 -> 1078
    //   606: iload 9
    //   608: anewarray 81	android/animation/Keyframe
    //   611: astore_1
    //   612: aload 12
    //   614: aload_1
    //   615: invokevirtual 403	java/util/ArrayList:toArray	([Ljava/lang/Object;)[Ljava/lang/Object;
    //   618: pop
    //   619: iconst_0
    //   620: istore 7
    //   622: goto -385 -> 237
    //   625: iload 11
    //   627: lookupswitch	default:+25->652, 42:+-447->180, 90:+-205->422
    //   652: goto -230 -> 422
    //   655: getstatic 20	o/ᒻ:ˏ	I
    //   658: bipush 81
    //   660: iadd
    //   661: istore 7
    //   663: iload 7
    //   665: sipush 128
    //   668: irem
    //   669: putstatic 22	o/ᒻ:ˊ	I
    //   672: iload 7
    //   674: iconst_2
    //   675: irem
    //   676: ifne +6 -> 682
    //   679: goto +283 -> 962
    //   682: goto -303 -> 379
    //   685: goto -263 -> 422
    //   688: iload 11
    //   690: istore 8
    //   692: goto +160 -> 852
    //   695: aload_3
    //   696: invokeinterface 289 1 0
    //   701: pop
    //   702: aload 13
    //   704: astore 12
    //   706: goto +288 -> 994
    //   709: iload 8
    //   711: lookupswitch	default:+25->736, 0:+-115->596, 15:+-23->688
    //   736: goto -48 -> 688
    //   739: aload 12
    //   741: astore 13
    //   743: iload 7
    //   745: tableswitch	default:+23->768, 0:+-50->695, 1:+-90->655
    //   768: aload 12
    //   770: astore 13
    //   772: goto -77 -> 695
    //   775: getstatic 20	o/ᒻ:ˏ	I
    //   778: bipush 105
    //   780: iadd
    //   781: istore 8
    //   783: iload 8
    //   785: sipush 128
    //   788: irem
    //   789: putstatic 22	o/ᒻ:ˊ	I
    //   792: iload 8
    //   794: iconst_2
    //   795: irem
    //   796: ifne +6 -> 802
    //   799: goto -234 -> 565
    //   802: goto -508 -> 294
    //   805: iload 7
    //   807: istore 10
    //   809: iload 7
    //   811: iconst_1
    //   812: iadd
    //   813: istore 11
    //   815: goto -479 -> 336
    //   818: getstatic 22	o/ᒻ:ˊ	I
    //   821: bipush 117
    //   823: iadd
    //   824: istore 8
    //   826: iload 8
    //   828: sipush 128
    //   831: irem
    //   832: putstatic 20	o/ᒻ:ˏ	I
    //   835: iload 8
    //   837: iconst_2
    //   838: irem
    //   839: ifeq +6 -> 845
    //   842: goto -669 -> 173
    //   845: bipush 49
    //   847: istore 8
    //   849: goto -752 -> 97
    //   852: iload 8
    //   854: iload 9
    //   856: iconst_1
    //   857: isub
    //   858: if_icmpge +6 -> 864
    //   861: goto +82 -> 943
    //   864: goto +177 -> 1041
    //   867: getstatic 20	o/ᒻ:ˏ	I
    //   870: bipush 89
    //   872: iadd
    //   873: istore 8
    //   875: iload 8
    //   877: sipush 128
    //   880: irem
    //   881: putstatic 22	o/ᒻ:ˊ	I
    //   884: iload 8
    //   886: iconst_2
    //   887: irem
    //   888: ifne +6 -> 894
    //   891: goto +121 -> 1012
    //   894: goto -442 -> 452
    //   897: aload_0
    //   898: invokestatic 249	o/ᔊ:ˊ	()Lo/ᔊ;
    //   901: invokevirtual 256	android/animation/PropertyValuesHolder:setEvaluator	(Landroid/animation/TypeEvaluator;)V
    //   904: goto +186 -> 1090
    //   907: aload 12
    //   909: aload 12
    //   911: invokevirtual 298	java/util/ArrayList:size	()I
    //   914: aload_1
    //   915: fconst_1
    //   916: invokestatic 405	o/ᒻ:ˏ	(Landroid/animation/Keyframe;F)Landroid/animation/Keyframe;
    //   919: invokevirtual 408	java/util/ArrayList:add	(ILjava/lang/Object;)V
    //   922: iload 7
    //   924: iconst_1
    //   925: iadd
    //   926: istore 7
    //   928: goto -335 -> 593
    //   931: new 265	java/util/ArrayList
    //   934: dup
    //   935: invokespecial 266	java/util/ArrayList:<init>	()V
    //   938: astore 12
    //   940: goto -403 -> 537
    //   943: bipush 42
    //   945: istore 11
    //   947: goto -322 -> 625
    //   950: iload 7
    //   952: iconst_1
    //   953: if_icmpeq +6 -> 959
    //   956: goto +92 -> 1048
    //   959: goto -709 -> 250
    //   962: goto -583 -> 379
    //   965: aload 12
    //   967: iconst_0
    //   968: aload_0
    //   969: fconst_0
    //   970: invokestatic 405	o/ᒻ:ˏ	(Landroid/animation/Keyframe;F)Landroid/animation/Keyframe;
    //   973: invokevirtual 408	java/util/ArrayList:add	(ILjava/lang/Object;)V
    //   976: iload 7
    //   978: iconst_1
    //   979: iadd
    //   980: istore 9
    //   982: goto -376 -> 606
    //   985: iload 7
    //   987: iconst_1
    //   988: iadd
    //   989: istore 7
    //   991: goto -754 -> 237
    //   994: goto -491 -> 503
    //   997: aload_1
    //   998: aload_2
    //   999: aload_3
    //   1000: invokestatic 198	android/util/Xml:asAttributeSet	(Lorg/xmlpull/v1/XmlPullParser;)Landroid/util/AttributeSet;
    //   1003: aload_3
    //   1004: invokestatic 410	o/ᒻ:ˊ	(Landroid/content/res/Resources;Landroid/content/res/Resources$Theme;Landroid/util/AttributeSet;Lorg/xmlpull/v1/XmlPullParser;)I
    //   1007: istore 5
    //   1009: goto -616 -> 393
    //   1012: aload_1
    //   1013: iload 7
    //   1015: aaload
    //   1016: astore_0
    //   1017: aload_0
    //   1018: invokevirtual 370	android/animation/Keyframe:getFraction	()F
    //   1021: fconst_1
    //   1022: fcmpg
    //   1023: ifge +6 -> 1029
    //   1026: goto -992 -> 34
    //   1029: goto -44 -> 985
    //   1032: aconst_null
    //   1033: astore 14
    //   1035: aconst_null
    //   1036: astore 12
    //   1038: goto -535 -> 503
    //   1041: bipush 90
    //   1043: istore 11
    //   1045: goto -420 -> 625
    //   1048: aload_3
    //   1049: invokeinterface 273 1 0
    //   1054: bipush 8
    //   1056: iconst_0
    //   1057: sipush 11007
    //   1060: invokestatic 413	o/ᒻ:ˏ	(IIC)Ljava/lang/String;
    //   1063: invokevirtual 416	java/lang/String:intern	()Ljava/lang/String;
    //   1066: invokevirtual 281	java/lang/String:equals	(Ljava/lang/Object;)Z
    //   1069: ifeq +6 -> 1075
    //   1072: goto -1056 -> 16
    //   1075: goto -81 -> 994
    //   1078: aload_0
    //   1079: fconst_0
    //   1080: invokevirtual 374	android/animation/Keyframe:setFraction	(F)V
    //   1083: iload 7
    //   1085: istore 9
    //   1087: goto -481 -> 606
    //   1090: goto -1022 -> 68
    // Local variable table:
    //   start	length	slot	name	signature
    //   0	1093	0	paramContext	Context
    //   0	1093	1	paramResources	Resources
    //   0	1093	2	paramTheme	Resources.Theme
    //   0	1093	3	paramXmlPullParser	XmlPullParser
    //   0	1093	4	paramString	String
    //   0	1093	5	paramInt	int
    //   3	1	6	localObject1	Object
    //   131	236	6	f	float
    //   29	1055	7	i	int
    //   37	851	8	j	int
    //   145	941	9	k	int
    //   424	384	10	m	int
    //   596	448	11	n	int
    //   250	787	12	localObject2	Object
    //   547	224	13	localObject3	Object
    //   258	776	14	localObject4	Object
    //   406	134	15	localKeyframe	Keyframe
    // Exception table:
    //   from	to	target	type
    //   34	39	419	java/lang/Exception
    //   46	55	500	java/lang/Exception
    //   68	76	500	java/lang/Exception
    //   76	85	500	java/lang/Exception
    //   185	191	500	java/lang/Exception
  }
  
  private static ValueAnimator ˏ(Context paramContext, Resources paramResources, Resources.Theme paramTheme, AttributeSet paramAttributeSet, ValueAnimator paramValueAnimator, float paramFloat, XmlPullParser paramXmlPullParser)
  {
    break label169;
    paramValueAnimator = new ValueAnimator();
    break label95;
    for (;;)
    {
      switch (i)
      {
      default: 
        break label131;
        label43:
        i = 0;
        continue;
        label49:
        i = 1;
      }
    }
    label55:
    break label320;
    label58:
    int i = 70;
    break label269;
    switch (i)
    {
    default: 
      label65:
      break;
    }
    label95:
    label131:
    label169:
    label269:
    label320:
    for (;;)
    {
      try
      {
        ॱ(paramValueAnimator, (TypedArray)localObject, paramResources, paramFloat, paramXmlPullParser);
        int j = ᵁ.ॱ((TypedArray)localObject, paramXmlPullParser, "interpolator", 0, 0);
        if (j > 0) {
          break label58;
        }
        continue;
        throw new NullPointerException();
        i = ˊ + 23;
        ˏ = i % 128;
        if (i % 2 != 0) {
          break label49;
        }
        break label43;
        continue;
        i = 63;
        continue;
        i = 19;
        break label65;
        return paramValueAnimator;
        i = ˏ + 33;
        ˊ = i % 128;
        if (i % 2 == 0) {
          break label55;
        }
        break label320;
        i = 68;
        break label65;
        paramResources.recycle();
        continue;
        Object localObject = ˤ.ʼ;
        try
        {
          localObject = ᵁ.ॱ(paramResources, paramTheme, paramAttributeSet, (int[])localObject);
          paramResources = ᵁ.ॱ(paramResources, paramTheme, paramAttributeSet, ˤ.ˊॱ);
          if (paramValueAnimator == null) {
            break;
          }
        }
        catch (Exception paramContext)
        {
          throw paramContext;
        }
        switch (i)
        {
        case 70: 
        default: 
          break;
        }
        ((TypedArray)localObject).recycle();
        if (paramResources == null)
        {
          continue;
          paramValueAnimator.setInterpolator(ᔅ.ˋ(paramContext, j));
        }
      }
      catch (Exception paramContext)
      {
        throw paramContext;
      }
    }
  }
  
  /* Error */
  private static String ˏ(int paramInt1, int paramInt2, char paramChar)
  {
    // Byte code:
    //   0: goto +143 -> 143
    //   3: iload_0
    //   4: newarray char
    //   6: astore 9
    //   8: iconst_0
    //   9: istore_3
    //   10: goto +201 -> 211
    //   13: iload_3
    //   14: iload_0
    //   15: if_icmpge +6 -> 21
    //   18: goto +239 -> 257
    //   21: goto +155 -> 176
    //   24: iconst_1
    //   25: istore 4
    //   27: goto +88 -> 115
    //   30: new 277	java/lang/String
    //   33: dup
    //   34: aload 9
    //   36: invokespecial 430	java/lang/String:<init>	([C)V
    //   39: areturn
    //   40: aload 9
    //   42: iload_3
    //   43: getstatic 36	o/ᒻ:ॱ	[C
    //   46: iload_1
    //   47: iload_3
    //   48: ishr
    //   49: caload
    //   50: i2l
    //   51: iload_3
    //   52: i2l
    //   53: getstatic 26	o/ᒻ:ˋ	J
    //   56: lrem
    //   57: ladd
    //   58: iload_2
    //   59: i2l
    //   60: ldiv
    //   61: l2i
    //   62: i2c
    //   63: castore
    //   64: iload_3
    //   65: bipush 68
    //   67: iadd
    //   68: istore_3
    //   69: goto -56 -> 13
    //   72: astore 9
    //   74: aload 9
    //   76: athrow
    //   77: goto -74 -> 3
    //   80: astore 9
    //   82: aload 9
    //   84: athrow
    //   85: getstatic 22	o/ᒻ:ˊ	I
    //   88: bipush 79
    //   90: iadd
    //   91: istore 4
    //   93: iload 4
    //   95: sipush 128
    //   98: irem
    //   99: putstatic 20	o/ᒻ:ˏ	I
    //   102: iload 4
    //   104: iconst_2
    //   105: irem
    //   106: ifeq +6 -> 112
    //   109: goto +61 -> 170
    //   112: goto -88 -> 24
    //   115: iload 4
    //   117: tableswitch	default:+23->140, 0:+-77->40, 1:+97->214
    //   140: goto +74 -> 214
    //   143: getstatic 20	o/ᒻ:ˏ	I
    //   146: bipush 85
    //   148: iadd
    //   149: istore_3
    //   150: iload_3
    //   151: sipush 128
    //   154: irem
    //   155: putstatic 22	o/ᒻ:ˊ	I
    //   158: iload_3
    //   159: iconst_2
    //   160: irem
    //   161: ifne +6 -> 167
    //   164: goto -87 -> 77
    //   167: goto -164 -> 3
    //   170: iconst_0
    //   171: istore 4
    //   173: goto -58 -> 115
    //   176: bipush 52
    //   178: istore 4
    //   180: iload 4
    //   182: lookupswitch	default:+26->208, 52:+-152->30, 95:+-97->85
    //   208: goto -123 -> 85
    //   211: goto -198 -> 13
    //   214: getstatic 36	o/ᒻ:ॱ	[C
    //   217: astore 10
    //   219: aload 10
    //   221: iload_1
    //   222: iload_3
    //   223: iadd
    //   224: caload
    //   225: i2l
    //   226: lstore 5
    //   228: iload_3
    //   229: i2l
    //   230: lstore 7
    //   232: aload 9
    //   234: iload_3
    //   235: lload 5
    //   237: lload 7
    //   239: getstatic 26	o/ᒻ:ˋ	J
    //   242: lmul
    //   243: lxor
    //   244: iload_2
    //   245: i2l
    //   246: lxor
    //   247: l2i
    //   248: i2c
    //   249: castore
    //   250: iload_3
    //   251: iconst_1
    //   252: iadd
    //   253: istore_3
    //   254: goto -241 -> 13
    //   257: bipush 95
    //   259: istore 4
    //   261: goto -81 -> 180
    // Local variable table:
    //   start	length	slot	name	signature
    //   0	264	0	paramInt1	int
    //   0	264	1	paramInt2	int
    //   0	264	2	paramChar	char
    //   9	245	3	i	int
    //   25	235	4	j	int
    //   226	10	5	l1	long
    //   230	8	7	l2	long
    //   6	35	9	arrayOfChar1	char[]
    //   72	3	9	localException1	Exception
    //   80	153	9	localException2	Exception
    //   217	3	10	arrayOfChar2	char[]
    // Exception table:
    //   from	to	target	type
    //   214	219	72	java/lang/Exception
    //   232	250	80	java/lang/Exception
  }
  
  /* Error */
  private static void ॱ(ValueAnimator paramValueAnimator, TypedArray paramTypedArray, int paramInt, float paramFloat, XmlPullParser paramXmlPullParser)
  {
    // Byte code:
    //   0: goto +39 -> 39
    //   3: getstatic 20	o/ᒻ:ˏ	I
    //   6: bipush 19
    //   8: iadd
    //   9: istore 5
    //   11: iload 5
    //   13: sipush 128
    //   16: irem
    //   17: putstatic 22	o/ᒻ:ˊ	I
    //   20: iload 5
    //   22: iconst_2
    //   23: irem
    //   24: ifne +6 -> 30
    //   27: goto +399 -> 426
    //   30: goto +402 -> 432
    //   33: goto +273 -> 306
    //   36: goto +109 -> 145
    //   39: goto -36 -> 3
    //   42: getstatic 22	o/ᒻ:ˊ	I
    //   45: bipush 43
    //   47: iadd
    //   48: istore 5
    //   50: iload 5
    //   52: sipush 128
    //   55: irem
    //   56: putstatic 20	o/ᒻ:ˏ	I
    //   59: iload 5
    //   61: iconst_2
    //   62: irem
    //   63: ifeq +6 -> 69
    //   66: goto +281 -> 347
    //   69: goto +203 -> 272
    //   72: aload 7
    //   74: invokestatic 434	o/ᵉ:ˋ	(Ljava/lang/String;)Landroid/graphics/Path;
    //   77: aload 6
    //   79: ldc_w 435
    //   82: fload_3
    //   83: fmul
    //   84: aload_0
    //   85: aload 4
    //   87: invokestatic 438	o/ᒻ:ॱ	(Landroid/graphics/Path;Landroid/animation/ObjectAnimator;FLjava/lang/String;Ljava/lang/String;)V
    //   90: goto +55 -> 145
    //   93: aload_0
    //   94: checkcast 114	android/animation/ObjectAnimator
    //   97: astore 8
    //   99: aload_1
    //   100: aload 4
    //   102: ldc_w 440
    //   105: iconst_1
    //   106: invokestatic 306	o/ᵁ:ˋ	(Landroid/content/res/TypedArray;Lorg/xmlpull/v1/XmlPullParser;Ljava/lang/String;I)Ljava/lang/String;
    //   109: astore 9
    //   111: aload 9
    //   113: ifnull +6 -> 119
    //   116: goto +23 -> 139
    //   119: goto +136 -> 255
    //   122: bipush 61
    //   124: istore_2
    //   125: goto +191 -> 316
    //   128: iload_2
    //   129: iconst_4
    //   130: if_icmpne +6 -> 136
    //   133: goto -100 -> 33
    //   136: goto +170 -> 306
    //   139: iconst_0
    //   140: istore 5
    //   142: goto +65 -> 207
    //   145: goto +258 -> 403
    //   148: new 239	android/view/InflateException
    //   151: dup
    //   152: new 151	java/lang/StringBuilder
    //   155: dup
    //   156: invokespecial 152	java/lang/StringBuilder:<init>	()V
    //   159: aload_1
    //   160: invokevirtual 443	android/content/res/TypedArray:getPositionDescription	()Ljava/lang/String;
    //   163: invokevirtual 158	java/lang/StringBuilder:append	(Ljava/lang/String;)Ljava/lang/StringBuilder;
    //   166: ldc_w 445
    //   169: invokevirtual 158	java/lang/StringBuilder:append	(Ljava/lang/String;)Ljava/lang/StringBuilder;
    //   172: invokevirtual 168	java/lang/StringBuilder:toString	()Ljava/lang/String;
    //   175: invokespecial 244	android/view/InflateException:<init>	(Ljava/lang/String;)V
    //   178: athrow
    //   179: iload 5
    //   181: tableswitch	default:+23->204, 0:+-88->93, 1:+263->444
    //   204: goto +240 -> 444
    //   207: aload 8
    //   209: astore 6
    //   211: aload 9
    //   213: astore 7
    //   215: aload 8
    //   217: astore_0
    //   218: iload 5
    //   220: tableswitch	default:+24->244, 0:+-178->42, 1:+164->384
    //   244: aload 8
    //   246: astore 6
    //   248: aload 9
    //   250: astore 7
    //   252: goto -210 -> 42
    //   255: iconst_1
    //   256: istore 5
    //   258: goto -51 -> 207
    //   261: aload 4
    //   263: ifnonnull +6 -> 269
    //   266: goto -118 -> 148
    //   269: goto -197 -> 72
    //   272: aload_1
    //   273: aload 4
    //   275: ldc_w 447
    //   278: iconst_2
    //   279: invokestatic 306	o/ᵁ:ˋ	(Landroid/content/res/TypedArray;Lorg/xmlpull/v1/XmlPullParser;Ljava/lang/String;I)Ljava/lang/String;
    //   282: astore_0
    //   283: aload_1
    //   284: aload 4
    //   286: ldc_w 449
    //   289: iconst_3
    //   290: invokestatic 306	o/ᵁ:ˋ	(Landroid/content/res/TypedArray;Lorg/xmlpull/v1/XmlPullParser;Ljava/lang/String;I)Ljava/lang/String;
    //   293: astore 4
    //   295: iload_2
    //   296: iconst_2
    //   297: if_icmpeq +6 -> 303
    //   300: goto -172 -> 128
    //   303: goto -270 -> 33
    //   306: aload_0
    //   307: ifnonnull +6 -> 313
    //   310: goto +128 -> 438
    //   313: goto -191 -> 122
    //   316: iload_2
    //   317: lookupswitch	default:+27->344, 58:+-56->261, 61:+-245->72
    //   344: goto -272 -> 72
    //   347: aload_1
    //   348: aload 4
    //   350: ldc_w 447
    //   353: iconst_4
    //   354: invokestatic 306	o/ᵁ:ˋ	(Landroid/content/res/TypedArray;Lorg/xmlpull/v1/XmlPullParser;Ljava/lang/String;I)Ljava/lang/String;
    //   357: astore_0
    //   358: aload_1
    //   359: aload 4
    //   361: ldc_w 449
    //   364: iconst_5
    //   365: invokestatic 306	o/ᵁ:ˋ	(Landroid/content/res/TypedArray;Lorg/xmlpull/v1/XmlPullParser;Ljava/lang/String;I)Ljava/lang/String;
    //   368: astore 4
    //   370: iload_2
    //   371: iconst_4
    //   372: if_icmpeq +6 -> 378
    //   375: goto -247 -> 128
    //   378: goto -345 -> 33
    //   381: astore_0
    //   382: aload_0
    //   383: athrow
    //   384: aload_1
    //   385: aload 4
    //   387: ldc_w 303
    //   390: iconst_0
    //   391: invokestatic 306	o/ᵁ:ˋ	(Landroid/content/res/TypedArray;Lorg/xmlpull/v1/XmlPullParser;Ljava/lang/String;I)Ljava/lang/String;
    //   394: astore_1
    //   395: aload_0
    //   396: aload_1
    //   397: invokevirtual 452	android/animation/ObjectAnimator:setPropertyName	(Ljava/lang/String;)V
    //   400: goto -364 -> 36
    //   403: getstatic 20	o/ᒻ:ˏ	I
    //   406: bipush 11
    //   408: iadd
    //   409: istore_2
    //   410: iload_2
    //   411: sipush 128
    //   414: irem
    //   415: putstatic 22	o/ᒻ:ˊ	I
    //   418: iload_2
    //   419: iconst_2
    //   420: irem
    //   421: ifne +4 -> 425
    //   424: return
    //   425: return
    //   426: iconst_1
    //   427: istore 5
    //   429: goto -250 -> 179
    //   432: iconst_0
    //   433: istore 5
    //   435: goto -256 -> 179
    //   438: bipush 58
    //   440: istore_2
    //   441: goto -125 -> 316
    //   444: aload_0
    //   445: checkcast 114	android/animation/ObjectAnimator
    //   448: astore_0
    //   449: aload_1
    //   450: aload 4
    //   452: ldc_w 440
    //   455: iconst_1
    //   456: invokestatic 306	o/ᵁ:ˋ	(Landroid/content/res/TypedArray;Lorg/xmlpull/v1/XmlPullParser;Ljava/lang/String;I)Ljava/lang/String;
    //   459: astore 7
    //   461: aload 7
    //   463: ifnull +9 -> 472
    //   466: aload_0
    //   467: astore 6
    //   469: goto -427 -> 42
    //   472: goto -88 -> 384
    //   475: astore_0
    //   476: aload_0
    //   477: athrow
    // Local variable table:
    //   start	length	slot	name	signature
    //   0	478	0	paramValueAnimator	ValueAnimator
    //   0	478	1	paramTypedArray	TypedArray
    //   0	478	2	paramInt	int
    //   0	478	3	paramFloat	float
    //   0	478	4	paramXmlPullParser	XmlPullParser
    //   9	425	5	i	int
    //   77	391	6	localObject1	Object
    //   72	390	7	localObject2	Object
    //   97	148	8	localObjectAnimator	android.animation.ObjectAnimator
    //   109	140	9	str	String
    // Exception table:
    //   from	to	target	type
    //   11	20	381	java/lang/Exception
    //   395	400	381	java/lang/Exception
    //   3	11	475	java/lang/Exception
    //   11	20	475	java/lang/Exception
    //   384	395	475	java/lang/Exception
  }
  
  /* Error */
  private static void ॱ(ValueAnimator paramValueAnimator, TypedArray paramTypedArray1, TypedArray paramTypedArray2, float paramFloat, XmlPullParser paramXmlPullParser)
  {
    // Byte code:
    //   0: goto +31 -> 31
    //   3: iload 5
    //   5: tableswitch	default:+23->28, 0:+182->187, 1:+397->402
    //   28: goto +159 -> 187
    //   31: goto +116 -> 147
    //   34: goto +410 -> 444
    //   37: iconst_1
    //   38: istore 5
    //   40: goto -37 -> 3
    //   43: iconst_0
    //   44: istore 7
    //   46: goto +197 -> 243
    //   49: iload 5
    //   51: istore 6
    //   53: iload 7
    //   55: tableswitch	default:+21->76, 0:+221->276, 1:+490->545
    //   76: goto +469 -> 545
    //   79: getstatic 22	o/ᒻ:ˊ	I
    //   82: iconst_1
    //   83: iadd
    //   84: istore 6
    //   86: iload 6
    //   88: sipush 128
    //   91: irem
    //   92: putstatic 20	o/ᒻ:ˏ	I
    //   95: iload 6
    //   97: iconst_2
    //   98: irem
    //   99: ifeq +6 -> 105
    //   102: goto -68 -> 34
    //   105: goto +339 -> 444
    //   108: astore_0
    //   109: aload_0
    //   110: athrow
    //   111: iconst_0
    //   112: istore 7
    //   114: goto -65 -> 49
    //   117: getstatic 20	o/ᒻ:ˏ	I
    //   120: bipush 47
    //   122: iadd
    //   123: istore 5
    //   125: iload 5
    //   127: sipush 128
    //   130: irem
    //   131: putstatic 22	o/ᒻ:ˊ	I
    //   134: iload 5
    //   136: iconst_2
    //   137: irem
    //   138: ifne +6 -> 144
    //   141: goto +416 -> 557
    //   144: goto -107 -> 37
    //   147: getstatic 22	o/ᒻ:ˊ	I
    //   150: bipush 45
    //   152: iadd
    //   153: istore 5
    //   155: iload 5
    //   157: sipush 128
    //   160: irem
    //   161: putstatic 20	o/ᒻ:ˏ	I
    //   164: iload 5
    //   166: iconst_2
    //   167: irem
    //   168: ifeq +6 -> 174
    //   171: goto +203 -> 374
    //   174: goto +300 -> 474
    //   177: bipush 30
    //   179: istore 5
    //   181: goto +18 -> 199
    //   184: astore_0
    //   185: aload_0
    //   186: athrow
    //   187: aload_1
    //   188: iconst_5
    //   189: bipush 36
    //   191: invokestatic 454	o/ᒻ:ˏ	(Landroid/content/res/TypedArray;II)I
    //   194: istore 5
    //   196: goto +33 -> 229
    //   199: iload 5
    //   201: lookupswitch	default:+27->228, 30:+41->242, 74:+31->232
    //   228: return
    //   229: goto +148 -> 377
    //   232: aload_0
    //   233: aload_2
    //   234: iload 6
    //   236: fload_3
    //   237: aload 4
    //   239: invokestatic 456	o/ᒻ:ॱ	(Landroid/animation/ValueAnimator;Landroid/content/res/TypedArray;IFLorg/xmlpull/v1/XmlPullParser;)V
    //   242: return
    //   243: iload 5
    //   245: istore 6
    //   247: iload 7
    //   249: tableswitch	default:+23->272, 0:+27->276, 1:+165->414
    //   272: iload 5
    //   274: istore 6
    //   276: aload_0
    //   277: lload 8
    //   279: invokevirtual 460	android/animation/ValueAnimator:setDuration	(J)Landroid/animation/ValueAnimator;
    //   282: pop
    //   283: aload_0
    //   284: lload 10
    //   286: invokevirtual 464	android/animation/ValueAnimator:setStartDelay	(J)V
    //   289: aload_0
    //   290: aload_1
    //   291: aload 4
    //   293: ldc_w 466
    //   296: iconst_3
    //   297: iconst_0
    //   298: invokestatic 99	o/ᵁ:ˏ	(Landroid/content/res/TypedArray;Lorg/xmlpull/v1/XmlPullParser;Ljava/lang/String;II)I
    //   301: invokevirtual 470	android/animation/ValueAnimator:setRepeatCount	(I)V
    //   304: aload_0
    //   305: aload_1
    //   306: aload 4
    //   308: ldc_w 472
    //   311: iconst_4
    //   312: iconst_1
    //   313: invokestatic 99	o/ᵁ:ˏ	(Landroid/content/res/TypedArray;Lorg/xmlpull/v1/XmlPullParser;Ljava/lang/String;II)I
    //   316: invokevirtual 475	android/animation/ValueAnimator:setRepeatMode	(I)V
    //   319: aload_2
    //   320: ifnull +6 -> 326
    //   323: goto +138 -> 461
    //   326: goto -149 -> 177
    //   329: iconst_0
    //   330: anewarray 212	android/animation/PropertyValuesHolder
    //   333: astore 12
    //   335: aload 12
    //   337: iconst_0
    //   338: aload 13
    //   340: aastore
    //   341: aload_0
    //   342: aload 12
    //   344: invokevirtual 336	android/animation/ValueAnimator:setValues	([Landroid/animation/PropertyValuesHolder;)V
    //   347: iload 5
    //   349: istore 6
    //   351: goto -75 -> 276
    //   354: aload_0
    //   355: iconst_1
    //   356: anewarray 212	android/animation/PropertyValuesHolder
    //   359: dup
    //   360: iconst_0
    //   361: aload 13
    //   363: aastore
    //   364: invokevirtual 336	android/animation/ValueAnimator:setValues	([Landroid/animation/PropertyValuesHolder;)V
    //   367: iload 5
    //   369: istore 6
    //   371: goto -95 -> 276
    //   374: goto +100 -> 474
    //   377: aload_1
    //   378: iload 5
    //   380: iconst_5
    //   381: bipush 6
    //   383: ldc_w 477
    //   386: invokestatic 268	o/ᒻ:ˋ	(Landroid/content/res/TypedArray;IIILjava/lang/String;)Landroid/animation/PropertyValuesHolder;
    //   389: astore 13
    //   391: aload 13
    //   393: ifnull +6 -> 399
    //   396: goto +72 -> 468
    //   399: goto -356 -> 43
    //   402: aload_1
    //   403: iconst_5
    //   404: bipush 6
    //   406: invokestatic 454	o/ᒻ:ˏ	(Landroid/content/res/TypedArray;II)I
    //   409: istore 5
    //   411: goto -182 -> 229
    //   414: getstatic 20	o/ᒻ:ˏ	I
    //   417: bipush 85
    //   419: iadd
    //   420: istore 6
    //   422: iload 6
    //   424: sipush 128
    //   427: irem
    //   428: putstatic 22	o/ᒻ:ˊ	I
    //   431: iload 6
    //   433: iconst_2
    //   434: irem
    //   435: ifne +6 -> 441
    //   438: goto -109 -> 329
    //   441: goto -87 -> 354
    //   444: aload 4
    //   446: ldc_w 479
    //   449: invokestatic 482	o/ᵁ:ˎ	(Lorg/xmlpull/v1/XmlPullParser;Ljava/lang/String;)Z
    //   452: ifeq +6 -> 458
    //   455: goto +84 -> 539
    //   458: goto -347 -> 111
    //   461: bipush 74
    //   463: istore 5
    //   465: goto -266 -> 199
    //   468: iconst_1
    //   469: istore 7
    //   471: goto -228 -> 243
    //   474: aload_1
    //   475: aload 4
    //   477: ldc_w 484
    //   480: iconst_1
    //   481: sipush 300
    //   484: invokestatic 99	o/ᵁ:ˏ	(Landroid/content/res/TypedArray;Lorg/xmlpull/v1/XmlPullParser;Ljava/lang/String;II)I
    //   487: i2l
    //   488: lstore 8
    //   490: aload_1
    //   491: aload 4
    //   493: ldc_w 486
    //   496: iconst_2
    //   497: iconst_0
    //   498: invokestatic 99	o/ᵁ:ˏ	(Landroid/content/res/TypedArray;Lorg/xmlpull/v1/XmlPullParser;Ljava/lang/String;II)I
    //   501: i2l
    //   502: lstore 10
    //   504: aload_1
    //   505: aload 4
    //   507: ldc_w 308
    //   510: bipush 7
    //   512: iconst_4
    //   513: invokestatic 99	o/ᵁ:ˏ	(Landroid/content/res/TypedArray;Lorg/xmlpull/v1/XmlPullParser;Ljava/lang/String;II)I
    //   516: istore 5
    //   518: aload 4
    //   520: ldc_w 488
    //   523: invokestatic 482	o/ᵁ:ˎ	(Lorg/xmlpull/v1/XmlPullParser;Ljava/lang/String;)Z
    //   526: ifeq +6 -> 532
    //   529: goto -450 -> 79
    //   532: iload 5
    //   534: istore 6
    //   536: goto -260 -> 276
    //   539: iconst_1
    //   540: istore 7
    //   542: goto -493 -> 49
    //   545: iload 5
    //   547: iconst_4
    //   548: if_icmpne +6 -> 554
    //   551: goto -434 -> 117
    //   554: goto -177 -> 377
    //   557: iconst_0
    //   558: istore 5
    //   560: goto -557 -> 3
    // Local variable table:
    //   start	length	slot	name	signature
    //   0	563	0	paramValueAnimator	ValueAnimator
    //   0	563	1	paramTypedArray1	TypedArray
    //   0	563	2	paramTypedArray2	TypedArray
    //   0	563	3	paramFloat	float
    //   0	563	4	paramXmlPullParser	XmlPullParser
    //   3	556	5	i	int
    //   51	484	6	j	int
    //   44	497	7	k	int
    //   277	1	8	localObject1	Object
    //   488	1	8	l1	long
    //   284	1	10	localObject2	Object
    //   502	1	10	l2	long
    //   333	10	12	arrayOfPropertyValuesHolder	PropertyValuesHolder[]
    //   338	54	13	localPropertyValuesHolder	PropertyValuesHolder
    // Exception table:
    //   from	to	target	type
    //   377	391	108	java/lang/Exception
    //   414	422	108	java/lang/Exception
    //   422	431	108	java/lang/Exception
    //   422	431	184	java/lang/Exception
  }
  
  /* Error */
  private static void ॱ(android.graphics.Path paramPath, android.animation.ObjectAnimator paramObjectAnimator, float paramFloat, String paramString1, String paramString2)
  {
    // Byte code:
    //   0: goto +454 -> 454
    //   3: astore_0
    //   4: aload_0
    //   5: athrow
    //   6: iload 8
    //   8: iconst_1
    //   9: iadd
    //   10: istore 8
    //   12: goto +765 -> 777
    //   15: aload_1
    //   16: iconst_2
    //   17: anewarray 212	android/animation/PropertyValuesHolder
    //   20: dup
    //   21: iconst_0
    //   22: aload_0
    //   23: aastore
    //   24: dup
    //   25: iconst_1
    //   26: aload_3
    //   27: aastore
    //   28: invokevirtual 489	android/animation/ObjectAnimator:setValues	([Landroid/animation/PropertyValuesHolder;)V
    //   31: return
    //   32: aload_0
    //   33: fload_2
    //   34: aload 12
    //   36: aconst_null
    //   37: invokevirtual 495	android/graphics/PathMeasure:getPosTan	(F[F[F)Z
    //   40: pop
    //   41: aload 14
    //   43: iload 8
    //   45: aload 12
    //   47: iconst_0
    //   48: faload
    //   49: fastore
    //   50: aload 13
    //   52: iload 8
    //   54: aload 12
    //   56: iconst_1
    //   57: faload
    //   58: fastore
    //   59: fload_2
    //   60: fload 5
    //   62: fadd
    //   63: fstore_2
    //   64: aload 11
    //   66: invokevirtual 298	java/util/ArrayList:size	()I
    //   69: istore 9
    //   71: iload 7
    //   73: iconst_1
    //   74: iadd
    //   75: iload 9
    //   77: if_icmpge +6 -> 83
    //   80: goto +6 -> 86
    //   83: goto -77 -> 6
    //   86: aload 11
    //   88: iload 7
    //   90: iconst_1
    //   91: iadd
    //   92: invokevirtual 285	java/util/ArrayList:get	(I)Ljava/lang/Object;
    //   95: astore 15
    //   97: aload 15
    //   99: checkcast 386	java/lang/Float
    //   102: astore 15
    //   104: aload 15
    //   106: invokevirtual 498	java/lang/Float:floatValue	()F
    //   109: fstore 6
    //   111: fload_2
    //   112: fload 6
    //   114: fcmpl
    //   115: ifle +6 -> 121
    //   118: goto +629 -> 747
    //   121: goto -115 -> 6
    //   124: aload 12
    //   126: astore_0
    //   127: iload 7
    //   129: tableswitch	default:+23->152, 0:+416->545, 1:+29->158
    //   152: aload 12
    //   154: astore_0
    //   155: goto +390 -> 545
    //   158: aload_3
    //   159: aload 14
    //   161: invokestatic 215	android/animation/PropertyValuesHolder:ofFloat	(Ljava/lang/String;[F)Landroid/animation/PropertyValuesHolder;
    //   164: astore_0
    //   165: goto +380 -> 545
    //   168: goto +465 -> 633
    //   171: iload 9
    //   173: tableswitch	default:+23->196, 0:+500->673, 1:+323->496
    //   196: goto +477 -> 673
    //   199: getstatic 22	o/ᒻ:ˊ	I
    //   202: bipush 73
    //   204: iadd
    //   205: istore 9
    //   207: iload 9
    //   209: sipush 128
    //   212: irem
    //   213: putstatic 20	o/ᒻ:ˏ	I
    //   216: iload 9
    //   218: iconst_2
    //   219: irem
    //   220: ifeq +6 -> 226
    //   223: goto +68 -> 291
    //   226: goto -194 -> 32
    //   229: new 491	android/graphics/PathMeasure
    //   232: dup
    //   233: aload_0
    //   234: iconst_0
    //   235: invokespecial 501	android/graphics/PathMeasure:<init>	(Landroid/graphics/Path;Z)V
    //   238: astore_0
    //   239: bipush 100
    //   241: fload 5
    //   243: fload_2
    //   244: fdiv
    //   245: f2i
    //   246: iconst_1
    //   247: iadd
    //   248: invokestatic 506	java/lang/Math:min	(II)I
    //   251: istore 10
    //   253: iload 10
    //   255: newarray float
    //   257: astore 14
    //   259: iload 10
    //   261: newarray float
    //   263: astore 13
    //   265: iconst_2
    //   266: newarray float
    //   268: astore 12
    //   270: iconst_0
    //   271: istore 7
    //   273: fload 5
    //   275: iload 10
    //   277: iconst_1
    //   278: isub
    //   279: i2f
    //   280: fdiv
    //   281: fstore 5
    //   283: fconst_0
    //   284: fstore_2
    //   285: iconst_0
    //   286: istore 8
    //   288: goto +69 -> 357
    //   291: aload_0
    //   292: fload_2
    //   293: aload 12
    //   295: aconst_null
    //   296: invokevirtual 495	android/graphics/PathMeasure:getPosTan	(F[F[F)Z
    //   299: pop
    //   300: aload 14
    //   302: iload 8
    //   304: aload 12
    //   306: iconst_0
    //   307: faload
    //   308: fastore
    //   309: aload 13
    //   311: iload 8
    //   313: aload 12
    //   315: iconst_1
    //   316: faload
    //   317: fastore
    //   318: fload_2
    //   319: fload 5
    //   321: fsub
    //   322: fstore_2
    //   323: iload 7
    //   325: iconst_1
    //   326: ishr
    //   327: aload 11
    //   329: invokevirtual 298	java/util/ArrayList:size	()I
    //   332: if_icmpge +6 -> 338
    //   335: goto -249 -> 86
    //   338: goto -332 -> 6
    //   341: iconst_0
    //   342: istore 7
    //   344: goto +295 -> 639
    //   347: aload_0
    //   348: ifnonnull +6 -> 354
    //   351: goto +377 -> 728
    //   354: goto +453 -> 807
    //   357: iload 8
    //   359: iload 10
    //   361: if_icmpge +6 -> 367
    //   364: goto -165 -> 199
    //   367: goto +345 -> 712
    //   370: iconst_1
    //   371: istore 7
    //   373: goto +189 -> 562
    //   376: fload 5
    //   378: aload 12
    //   380: invokevirtual 509	android/graphics/PathMeasure:getLength	()F
    //   383: fadd
    //   384: fstore 5
    //   386: aload 11
    //   388: fload 5
    //   390: invokestatic 513	java/lang/Float:valueOf	(F)Ljava/lang/Float;
    //   393: invokevirtual 295	java/util/ArrayList:add	(Ljava/lang/Object;)Z
    //   396: pop
    //   397: aload 12
    //   399: invokevirtual 516	android/graphics/PathMeasure:nextContour	()Z
    //   402: ifne +6 -> 408
    //   405: goto -176 -> 229
    //   408: goto -32 -> 376
    //   411: getstatic 20	o/ᒻ:ˏ	I
    //   414: bipush 7
    //   416: iadd
    //   417: istore 7
    //   419: iload 7
    //   421: sipush 128
    //   424: irem
    //   425: putstatic 22	o/ᒻ:ˊ	I
    //   428: iload 7
    //   430: iconst_2
    //   431: irem
    //   432: ifne +6 -> 438
    //   435: goto -65 -> 370
    //   438: goto +121 -> 559
    //   441: aload_1
    //   442: iconst_1
    //   443: anewarray 212	android/animation/PropertyValuesHolder
    //   446: dup
    //   447: iconst_0
    //   448: aload_0
    //   449: aastore
    //   450: invokevirtual 489	android/animation/ObjectAnimator:setValues	([Landroid/animation/PropertyValuesHolder;)V
    //   453: return
    //   454: goto +6 -> 460
    //   457: goto +77 -> 534
    //   460: new 491	android/graphics/PathMeasure
    //   463: dup
    //   464: aload_0
    //   465: iconst_0
    //   466: invokespecial 501	android/graphics/PathMeasure:<init>	(Landroid/graphics/Path;Z)V
    //   469: astore 12
    //   471: fconst_0
    //   472: fstore 5
    //   474: new 265	java/util/ArrayList
    //   477: dup
    //   478: invokespecial 266	java/util/ArrayList:<init>	()V
    //   481: astore 11
    //   483: aload 11
    //   485: fconst_0
    //   486: invokestatic 513	java/lang/Float:valueOf	(F)Ljava/lang/Float;
    //   489: invokevirtual 295	java/util/ArrayList:add	(Ljava/lang/Object;)Z
    //   492: pop
    //   493: goto -82 -> 411
    //   496: fload_2
    //   497: aload 11
    //   499: iload 7
    //   501: iconst_1
    //   502: iadd
    //   503: invokevirtual 285	java/util/ArrayList:get	(I)Ljava/lang/Object;
    //   506: checkcast 386	java/lang/Float
    //   509: invokevirtual 498	java/lang/Float:floatValue	()F
    //   512: fsub
    //   513: fstore_2
    //   514: iload 7
    //   516: iconst_1
    //   517: iadd
    //   518: istore 7
    //   520: aload_0
    //   521: invokevirtual 516	android/graphics/PathMeasure:nextContour	()Z
    //   524: pop
    //   525: goto -519 -> 6
    //   528: iconst_1
    //   529: istore 7
    //   531: goto -407 -> 124
    //   534: aload 4
    //   536: aload 13
    //   538: invokestatic 215	android/animation/PropertyValuesHolder:ofFloat	(Ljava/lang/String;[F)Landroid/animation/PropertyValuesHolder;
    //   541: astore_3
    //   542: goto -195 -> 347
    //   545: aload 4
    //   547: ifnull +6 -> 553
    //   550: goto +53 -> 603
    //   553: aload 11
    //   555: astore_3
    //   556: goto -209 -> 347
    //   559: iconst_0
    //   560: istore 7
    //   562: iload 7
    //   564: tableswitch	default:+24->588, 0:+72->636, 1:+106->670
    //   588: goto +48 -> 636
    //   591: iconst_1
    //   592: istore 9
    //   594: goto -423 -> 171
    //   597: iconst_1
    //   598: istore 7
    //   600: goto +39 -> 639
    //   603: getstatic 22	o/ᒻ:ˊ	I
    //   606: bipush 91
    //   608: iadd
    //   609: istore 7
    //   611: iload 7
    //   613: sipush 128
    //   616: irem
    //   617: putstatic 20	o/ᒻ:ˏ	I
    //   620: iload 7
    //   622: iconst_2
    //   623: irem
    //   624: ifeq +6 -> 630
    //   627: goto -170 -> 457
    //   630: goto -96 -> 534
    //   633: goto -276 -> 357
    //   636: goto -260 -> 376
    //   639: iload 7
    //   641: tableswitch	default:+23->664, 0:+-626->15, 1:+-200->441
    //   664: goto -223 -> 441
    //   667: astore_0
    //   668: aload_0
    //   669: athrow
    //   670: goto -294 -> 376
    //   673: fload_2
    //   674: aload 11
    //   676: iload 7
    //   678: iconst_1
    //   679: idiv
    //   680: invokevirtual 285	java/util/ArrayList:get	(I)Ljava/lang/Object;
    //   683: checkcast 386	java/lang/Float
    //   686: invokevirtual 498	java/lang/Float:floatValue	()F
    //   689: fdiv
    //   690: fstore_2
    //   691: iload 7
    //   693: bipush 71
    //   695: iadd
    //   696: istore 7
    //   698: aload_0
    //   699: invokevirtual 516	android/graphics/PathMeasure:nextContour	()Z
    //   702: pop
    //   703: goto -697 -> 6
    //   706: iconst_0
    //   707: istore 7
    //   709: goto -585 -> 124
    //   712: aconst_null
    //   713: astore 12
    //   715: aconst_null
    //   716: astore 11
    //   718: aload_3
    //   719: ifnull +6 -> 725
    //   722: goto -194 -> 528
    //   725: goto -19 -> 706
    //   728: aload_1
    //   729: iconst_1
    //   730: anewarray 212	android/animation/PropertyValuesHolder
    //   733: dup
    //   734: iconst_0
    //   735: aload_3
    //   736: aastore
    //   737: invokevirtual 489	android/animation/ObjectAnimator:setValues	([Landroid/animation/PropertyValuesHolder;)V
    //   740: return
    //   741: iconst_0
    //   742: istore 9
    //   744: goto -573 -> 171
    //   747: getstatic 22	o/ᒻ:ˊ	I
    //   750: bipush 113
    //   752: iadd
    //   753: istore 9
    //   755: iload 9
    //   757: sipush 128
    //   760: irem
    //   761: putstatic 20	o/ᒻ:ˏ	I
    //   764: iload 9
    //   766: iconst_2
    //   767: irem
    //   768: ifeq +6 -> 774
    //   771: goto -30 -> 741
    //   774: goto -183 -> 591
    //   777: getstatic 22	o/ᒻ:ˊ	I
    //   780: bipush 103
    //   782: iadd
    //   783: istore 9
    //   785: iload 9
    //   787: sipush 128
    //   790: irem
    //   791: putstatic 20	o/ᒻ:ˏ	I
    //   794: iload 9
    //   796: iconst_2
    //   797: irem
    //   798: ifeq +6 -> 804
    //   801: goto -633 -> 168
    //   804: goto -171 -> 633
    //   807: aload_3
    //   808: ifnonnull +6 -> 814
    //   811: goto -214 -> 597
    //   814: goto -473 -> 341
    // Local variable table:
    //   start	length	slot	name	signature
    //   0	817	0	paramPath	android.graphics.Path
    //   0	817	1	paramObjectAnimator	android.animation.ObjectAnimator
    //   0	817	2	paramFloat	float
    //   0	817	3	paramString1	String
    //   0	817	4	paramString2	String
    //   60	214	5	localObject1	Object
    //   281	192	5	f1	float
    //   109	4	6	f2	float
    //   71	637	7	i	int
    //   6	356	8	j	int
    //   69	729	9	k	int
    //   251	111	10	m	int
    //   64	653	11	localArrayList	ArrayList
    //   34	680	12	localObject2	Object
    //   50	487	13	arrayOfFloat1	float[]
    //   41	260	14	arrayOfFloat2	float[]
    //   95	10	15	localObject3	Object
    // Exception table:
    //   from	to	target	type
    //   64	71	3	java/lang/Exception
    //   32	41	667	java/lang/Exception
    //   86	97	667	java/lang/Exception
    //   97	104	667	java/lang/Exception
    //   104	111	667	java/lang/Exception
  }
  
  static class iF
    implements TypeEvaluator<ᵉ.If[]>
  {
    private ᵉ.If[] ˋ;
    
    private iF() {}
    
    public ᵉ.If[] ˊ(float paramFloat, ᵉ.If[] paramArrayOfIf1, ᵉ.If[] paramArrayOfIf2)
    {
      if (!ᵉ.ˋ(paramArrayOfIf1, paramArrayOfIf2)) {
        throw new IllegalArgumentException("Can't interpolate between two incompatible pathData");
      }
      if ((this.ˋ == null) || (!ᵉ.ˋ(this.ˋ, paramArrayOfIf1))) {
        this.ˋ = ᵉ.ˎ(paramArrayOfIf1);
      }
      int i = 0;
      while (i < paramArrayOfIf1.length)
      {
        this.ˋ[i].ˋ(paramArrayOfIf1[i], paramArrayOfIf2[i], paramFloat);
        i += 1;
      }
      return this.ˋ;
    }
  }
}
