package o;

import android.graphics.Rect;
import android.os.Build.VERSION;
import android.view.View;
import android.view.accessibility.AccessibilityNodeInfo;
import android.view.accessibility.AccessibilityNodeInfo.AccessibilityAction;
import android.view.accessibility.AccessibilityNodeInfo.CollectionInfo;
import android.view.accessibility.AccessibilityNodeInfo.CollectionItemInfo;

public class ᓵ
{
  private static int ˋ = 0;
  private static int ˎ = 1;
  private static int[] ˏ = { 326755794, 1677609147, 108222687, 18011220, -852870876, -370200455, 721976455, 1753086101, 747649510, 35636895, -1659240694, -814087930, -893896580, -1407126616, -635151607, 1620836272, -1240929183, -1215755461 };
  public int ˊ = -1;
  private final AccessibilityNodeInfo ॱ;
  
  private ᓵ(AccessibilityNodeInfo paramAccessibilityNodeInfo)
  {
    this.ॱ = paramAccessibilityNodeInfo;
  }
  
  /* Error */
  private static String ˋ(int[] paramArrayOfInt, int paramInt)
  {
    // Byte code:
    //   0: goto +298 -> 298
    //   3: iconst_0
    //   4: istore_2
    //   5: goto +259 -> 264
    //   8: iconst_1
    //   9: istore_2
    //   10: goto +254 -> 264
    //   13: astore_0
    //   14: aload_0
    //   15: athrow
    //   16: iload_3
    //   17: tableswitch	default:+23->40, 0:+26->43, 1:+232->249
    //   40: goto +3 -> 43
    //   43: aload 4
    //   45: iconst_0
    //   46: aload_0
    //   47: iload_2
    //   48: iaload
    //   49: bipush 16
    //   51: ishr
    //   52: i2c
    //   53: castore
    //   54: aload 4
    //   56: iconst_1
    //   57: aload_0
    //   58: iload_2
    //   59: iaload
    //   60: i2c
    //   61: castore
    //   62: aload 4
    //   64: iconst_2
    //   65: aload_0
    //   66: iload_2
    //   67: iconst_1
    //   68: iadd
    //   69: iaload
    //   70: bipush 16
    //   72: ishr
    //   73: i2c
    //   74: castore
    //   75: aload 4
    //   77: iconst_3
    //   78: aload_0
    //   79: iload_2
    //   80: iconst_1
    //   81: iadd
    //   82: iaload
    //   83: i2c
    //   84: castore
    //   85: aload 4
    //   87: aload 6
    //   89: iconst_0
    //   90: invokestatic 62	o/oN:ˏ	([C[IZ)[I
    //   93: pop
    //   94: aload 5
    //   96: iload_2
    //   97: iconst_1
    //   98: ishl
    //   99: aload 4
    //   101: iconst_0
    //   102: caload
    //   103: castore
    //   104: aload 5
    //   106: iload_2
    //   107: iconst_1
    //   108: ishl
    //   109: iconst_1
    //   110: iadd
    //   111: aload 4
    //   113: iconst_1
    //   114: caload
    //   115: castore
    //   116: aload 5
    //   118: iload_2
    //   119: iconst_1
    //   120: ishl
    //   121: iconst_2
    //   122: iadd
    //   123: aload 4
    //   125: iconst_2
    //   126: caload
    //   127: castore
    //   128: aload 5
    //   130: iload_2
    //   131: iconst_1
    //   132: ishl
    //   133: iconst_3
    //   134: iadd
    //   135: aload 4
    //   137: iconst_3
    //   138: caload
    //   139: castore
    //   140: iload_2
    //   141: iconst_2
    //   142: iadd
    //   143: istore_2
    //   144: goto +64 -> 208
    //   147: getstatic 23	o/ᓵ:ˋ	I
    //   150: bipush 105
    //   152: iadd
    //   153: istore_2
    //   154: iload_2
    //   155: sipush 128
    //   158: irem
    //   159: putstatic 25	o/ᓵ:ˎ	I
    //   162: iload_2
    //   163: iconst_2
    //   164: irem
    //   165: ifne +6 -> 171
    //   168: goto +93 -> 261
    //   171: goto +49 -> 220
    //   174: getstatic 23	o/ᓵ:ˋ	I
    //   177: istore_2
    //   178: iload_2
    //   179: bipush 103
    //   181: iadd
    //   182: istore_2
    //   183: iload_2
    //   184: sipush 128
    //   187: irem
    //   188: putstatic 25	o/ᓵ:ˎ	I
    //   191: iload_2
    //   192: iconst_2
    //   193: irem
    //   194: ifne +6 -> 200
    //   197: goto -194 -> 3
    //   200: goto -192 -> 8
    //   203: iconst_0
    //   204: istore_3
    //   205: goto -189 -> 16
    //   208: iload_2
    //   209: aload_0
    //   210: arraylength
    //   211: if_icmpge +6 -> 217
    //   214: goto -11 -> 203
    //   217: goto +84 -> 301
    //   220: iconst_4
    //   221: newarray char
    //   223: astore 4
    //   225: aload_0
    //   226: arraylength
    //   227: iconst_1
    //   228: ishl
    //   229: newarray char
    //   231: astore 5
    //   233: getstatic 45	o/ᓵ:ˏ	[I
    //   236: invokevirtual 67	[I:clone	()Ljava/lang/Object;
    //   239: checkcast 63	[I
    //   242: astore 6
    //   244: iconst_0
    //   245: istore_3
    //   246: goto -72 -> 174
    //   249: new 69	java/lang/String
    //   252: dup
    //   253: aload 5
    //   255: iconst_0
    //   256: iload_1
    //   257: invokespecial 72	java/lang/String:<init>	([CII)V
    //   260: areturn
    //   261: goto -41 -> 220
    //   264: iload_2
    //   265: tableswitch	default:+23->288, 0:+23->288, 1:+28->293
    //   288: iload_3
    //   289: istore_2
    //   290: goto -82 -> 208
    //   293: iload_3
    //   294: istore_2
    //   295: goto -87 -> 208
    //   298: goto -151 -> 147
    //   301: iconst_1
    //   302: istore_3
    //   303: goto -287 -> 16
    // Local variable table:
    //   start	length	slot	name	signature
    //   0	306	0	paramArrayOfInt	int[]
    //   0	306	1	paramInt	int
    //   4	291	2	i	int
    //   16	287	3	j	int
    //   43	181	4	arrayOfChar1	char[]
    //   94	160	5	arrayOfChar2	char[]
    //   87	156	6	arrayOfInt	int[]
    // Exception table:
    //   from	to	target	type
    //   174	178	13	java/lang/Exception
    //   183	191	13	java/lang/Exception
  }
  
  /* Error */
  public static ᓵ ˋ(ᓵ paramᓵ)
  {
    // Byte code:
    //   0: goto +42 -> 42
    //   3: iload_1
    //   4: tableswitch	default:+24->28, 0:+93->97, 1:+41->45
    //   28: goto +17 -> 45
    //   31: astore_0
    //   32: aload_0
    //   33: athrow
    //   34: iconst_1
    //   35: istore_1
    //   36: goto -33 -> 3
    //   39: astore_0
    //   40: aload_0
    //   41: athrow
    //   42: goto +28 -> 70
    //   45: aload_0
    //   46: getfield 54	o/ᓵ:ॱ	Landroid/view/accessibility/AccessibilityNodeInfo;
    //   49: astore_0
    //   50: aload_0
    //   51: invokestatic 79	android/view/accessibility/AccessibilityNodeInfo:obtain	(Landroid/view/accessibility/AccessibilityNodeInfo;)Landroid/view/accessibility/AccessibilityNodeInfo;
    //   54: astore_0
    //   55: aload_0
    //   56: invokestatic 82	o/ᓵ:ˏ	(Landroid/view/accessibility/AccessibilityNodeInfo;)Lo/ᓵ;
    //   59: astore_0
    //   60: aconst_null
    //   61: arraylength
    //   62: istore_1
    //   63: aload_0
    //   64: areturn
    //   65: iconst_0
    //   66: istore_1
    //   67: goto -64 -> 3
    //   70: getstatic 23	o/ᓵ:ˋ	I
    //   73: bipush 51
    //   75: iadd
    //   76: istore_1
    //   77: iload_1
    //   78: sipush 128
    //   81: irem
    //   82: putstatic 25	o/ᓵ:ˎ	I
    //   85: iload_1
    //   86: iconst_2
    //   87: irem
    //   88: ifne +6 -> 94
    //   91: goto -57 -> 34
    //   94: goto -29 -> 65
    //   97: aload_0
    //   98: getfield 54	o/ᓵ:ॱ	Landroid/view/accessibility/AccessibilityNodeInfo;
    //   101: invokestatic 79	android/view/accessibility/AccessibilityNodeInfo:obtain	(Landroid/view/accessibility/AccessibilityNodeInfo;)Landroid/view/accessibility/AccessibilityNodeInfo;
    //   104: invokestatic 82	o/ᓵ:ˏ	(Landroid/view/accessibility/AccessibilityNodeInfo;)Lo/ᓵ;
    //   107: areturn
    // Local variable table:
    //   start	length	slot	name	signature
    //   0	108	0	paramᓵ	ᓵ
    //   3	85	1	i	int
    // Exception table:
    //   from	to	target	type
    //   50	55	31	java/lang/Exception
    //   45	50	39	java/lang/Exception
    //   55	63	39	java/lang/Exception
  }
  
  private static String ˎ(int paramInt)
  {
    for (;;)
    {
      try
      {
        paramInt = ˋ + 7;
        ˎ = paramInt % 128;
        if (paramInt % 2 == 0) {
          break label398;
        }
        switch (paramInt)
        {
        default: 
          return "ACTION_SET_SELECTION";
          return "ACTION_SELECT";
          return "ACTION_SCROLL_FORWARD";
          return "ACTION_CLEAR_SELECTION";
          switch (paramInt)
          {
          default: 
            return "ACTION_PASTE";
            return "ACTION_CUT";
            paramInt = 2;
            continue;
            return "ACTION_NEXT_AT_MOVEMENT_GRANULARITY";
            return "ACTION_CLEAR_FOCUS";
            paramInt = 0;
            continue;
            continue;
            paramInt = 82;
            break;
          case 0: 
            return "ACTION_PASTE";
            return "ACTION_ACCESSIBILITY_FOCUS";
            return "ACTION_COPY";
            return "ACTION_PREVIOUS_AT_MOVEMENT_GRANULARITY";
            switch (paramInt)
            {
            case 4: 
            case 4096: 
            case 8: 
            case 65536: 
            case 256: 
            case 2: 
            case 32768: 
            case 64: 
            case 16384: 
            case 512: 
            default: 
              break;
            case 8192: 
              return "ACTION_SCROLL_BACKWARD";
            case 32: 
              return "ACTION_LONG_CLICK";
            }
          case 1: 
            throw new NullPointerException();
            return "ACTION_CLEAR_ACCESSIBILITY_FOCUS";
            return "ACTION_UNKNOWN";
            return "ACTION_NEXT_HTML_ELEMENT";
            return "ACTION_FOCUS";
            paramInt = ˎ + 69;
            ˋ = paramInt % 128;
            if (paramInt % 2 != 0) {
              continue;
            }
            continue;
            continue;
            paramInt = ˎ + 87;
            ˋ = paramInt % 128;
            if (paramInt % 2 != 0) {
              return "ACTION_PREVIOUS_HTML_ELEMENT";
            }
            return "ACTION_PREVIOUS_HTML_ELEMENT";
          }
          break;
        case 2: 
          return "ACTION_SET_SELECTION";
        case 82: 
          paramInt = 30 / 0;
          return "ACTION_SET_SELECTION";
        }
      }
      catch (Exception localException)
      {
        throw localException;
      }
      continue;
      return "ACTION_CLICK";
      label398:
      paramInt = 1;
    }
  }
  
  public static ᓵ ˏ(AccessibilityNodeInfo paramAccessibilityNodeInfo)
  {
    for (;;)
    {
      int i = ˋ + 109;
      ˎ = i % 128;
      if (i % 2 == 0) {
        return paramAccessibilityNodeInfo;
      }
      return paramAccessibilityNodeInfo;
      paramAccessibilityNodeInfo = new ᓵ(paramAccessibilityNodeInfo);
    }
  }
  
  /* Error */
  public boolean equals(Object paramObject)
  {
    // Byte code:
    //   0: goto +163 -> 163
    //   3: aload_1
    //   4: getfield 54	o/ᓵ:ॱ	Landroid/view/accessibility/AccessibilityNodeInfo;
    //   7: astore_1
    //   8: new 111	java/lang/NullPointerException
    //   11: dup
    //   12: invokespecial 112	java/lang/NullPointerException:<init>	()V
    //   15: athrow
    //   16: iconst_0
    //   17: ireturn
    //   18: iconst_0
    //   19: ireturn
    //   20: aload_0
    //   21: aload_1
    //   22: if_acmpne +6 -> 28
    //   25: goto +198 -> 223
    //   28: goto +258 -> 286
    //   31: bipush 71
    //   33: istore_2
    //   34: goto +158 -> 192
    //   37: bipush 14
    //   39: istore_2
    //   40: goto +301 -> 341
    //   43: getstatic 25	o/ᓵ:ˎ	I
    //   46: bipush 21
    //   48: iadd
    //   49: istore_2
    //   50: iload_2
    //   51: sipush 128
    //   54: irem
    //   55: putstatic 23	o/ᓵ:ˋ	I
    //   58: iload_2
    //   59: iconst_2
    //   60: irem
    //   61: ifeq +6 -> 67
    //   64: goto +341 -> 405
    //   67: goto +332 -> 399
    //   70: iload_2
    //   71: tableswitch	default:+21->92, 0:+267->338, 1:+24->95
    //   92: goto +246 -> 338
    //   95: iconst_1
    //   96: ireturn
    //   97: iconst_0
    //   98: ireturn
    //   99: iload_2
    //   100: tableswitch	default:+24->124, 0:+303->403, 1:+71->171
    //   124: goto +279 -> 403
    //   127: aload_0
    //   128: getfield 54	o/ᓵ:ॱ	Landroid/view/accessibility/AccessibilityNodeInfo;
    //   131: aload_1
    //   132: getfield 54	o/ᓵ:ॱ	Landroid/view/accessibility/AccessibilityNodeInfo;
    //   135: invokevirtual 130	android/view/accessibility/AccessibilityNodeInfo:equals	(Ljava/lang/Object;)Z
    //   138: ifne +6 -> 144
    //   141: goto +165 -> 306
    //   144: goto +9 -> 153
    //   147: bipush 42
    //   149: istore_2
    //   150: goto +42 -> 192
    //   153: iconst_1
    //   154: istore_2
    //   155: goto +216 -> 371
    //   158: iconst_0
    //   159: istore_2
    //   160: goto -90 -> 70
    //   163: goto -143 -> 20
    //   166: iconst_1
    //   167: istore_2
    //   168: goto -98 -> 70
    //   171: aload_1
    //   172: checkcast 2	o/ᓵ
    //   175: astore_1
    //   176: aload_0
    //   177: getfield 54	o/ᓵ:ॱ	Landroid/view/accessibility/AccessibilityNodeInfo;
    //   180: ifnonnull +6 -> 186
    //   183: goto +128 -> 311
    //   186: goto -59 -> 127
    //   189: astore_1
    //   190: aload_1
    //   191: athrow
    //   192: iload_2
    //   193: lookupswitch	default:+27->220, 42:+-150->43, 71:+57->250
    //   220: goto -177 -> 43
    //   223: getstatic 23	o/ᓵ:ˋ	I
    //   226: bipush 115
    //   228: iadd
    //   229: istore_2
    //   230: iload_2
    //   231: sipush 128
    //   234: irem
    //   235: putstatic 25	o/ᓵ:ˎ	I
    //   238: iload_2
    //   239: iconst_2
    //   240: irem
    //   241: ifne +6 -> 247
    //   244: goto +164 -> 408
    //   247: goto -210 -> 37
    //   250: aload_0
    //   251: invokevirtual 134	java/lang/Object:getClass	()Ljava/lang/Class;
    //   254: astore_3
    //   255: aload_1
    //   256: invokevirtual 134	java/lang/Object:getClass	()Ljava/lang/Class;
    //   259: astore 4
    //   261: aload_3
    //   262: aload 4
    //   264: if_acmpeq +6 -> 270
    //   267: goto +29 -> 296
    //   270: goto +31 -> 301
    //   273: aload_1
    //   274: getfield 54	o/ᓵ:ॱ	Landroid/view/accessibility/AccessibilityNodeInfo;
    //   277: ifnull +6 -> 283
    //   280: goto -122 -> 158
    //   283: goto -117 -> 166
    //   286: aload_1
    //   287: ifnonnull +6 -> 293
    //   290: goto -143 -> 147
    //   293: goto -262 -> 31
    //   296: iconst_0
    //   297: istore_2
    //   298: goto -199 -> 99
    //   301: iconst_1
    //   302: istore_2
    //   303: goto -204 -> 99
    //   306: iconst_0
    //   307: istore_2
    //   308: goto +63 -> 371
    //   311: getstatic 25	o/ᓵ:ˎ	I
    //   314: bipush 119
    //   316: iadd
    //   317: istore_2
    //   318: iload_2
    //   319: sipush 128
    //   322: irem
    //   323: putstatic 23	o/ᓵ:ˋ	I
    //   326: iload_2
    //   327: iconst_2
    //   328: irem
    //   329: ifeq +6 -> 335
    //   332: goto -329 -> 3
    //   335: goto -62 -> 273
    //   338: goto -241 -> 97
    //   341: iload_2
    //   342: lookupswitch	default:+26->368, 14:+59->401, 35:+-326->16
    //   368: goto -352 -> 16
    //   371: iload_2
    //   372: tableswitch	default:+24->396, 0:+-354->18, 1:+-277->95
    //   396: goto -301 -> 95
    //   399: iconst_0
    //   400: ireturn
    //   401: iconst_1
    //   402: ireturn
    //   403: iconst_0
    //   404: ireturn
    //   405: goto -6 -> 399
    //   408: bipush 35
    //   410: istore_2
    //   411: goto -70 -> 341
    // Local variable table:
    //   start	length	slot	name	signature
    //   0	414	0	this	ᓵ
    //   0	414	1	paramObject	Object
    //   33	378	2	i	int
    //   254	8	3	localClass1	Class
    //   259	4	4	localClass2	Class
    // Exception table:
    //   from	to	target	type
    //   250	255	189	java/lang/Exception
    //   255	261	189	java/lang/Exception
  }
  
  /* Error */
  public int hashCode()
  {
    // Byte code:
    //   0: goto +138 -> 138
    //   3: bipush 93
    //   5: istore_1
    //   6: goto +151 -> 157
    //   9: iload_1
    //   10: ireturn
    //   11: iload_1
    //   12: tableswitch	default:+24->36, 0:+24->36, 1:+29->41
    //   36: iload_2
    //   37: istore_1
    //   38: goto +180 -> 218
    //   41: iload_2
    //   42: istore_1
    //   43: goto +175 -> 218
    //   46: bipush 50
    //   48: iconst_0
    //   49: idiv
    //   50: istore_2
    //   51: iload_1
    //   52: ireturn
    //   53: getstatic 25	o/ᓵ:ˎ	I
    //   56: bipush 89
    //   58: iadd
    //   59: istore_2
    //   60: iload_2
    //   61: sipush 128
    //   64: irem
    //   65: putstatic 23	o/ᓵ:ˋ	I
    //   68: iload_2
    //   69: iconst_2
    //   70: irem
    //   71: ifeq +6 -> 77
    //   74: goto +49 -> 123
    //   77: goto +56 -> 133
    //   80: aload_0
    //   81: getfield 54	o/ᓵ:ॱ	Landroid/view/accessibility/AccessibilityNodeInfo;
    //   84: ifnonnull +6 -> 90
    //   87: goto +134 -> 221
    //   90: goto -87 -> 3
    //   93: astore_3
    //   94: aload_3
    //   95: athrow
    //   96: getstatic 25	o/ᓵ:ˎ	I
    //   99: bipush 81
    //   101: iadd
    //   102: istore_1
    //   103: iload_1
    //   104: sipush 128
    //   107: irem
    //   108: putstatic 23	o/ᓵ:ˋ	I
    //   111: iload_1
    //   112: iconst_2
    //   113: irem
    //   114: ifeq +6 -> 120
    //   117: goto +11 -> 128
    //   120: goto +67 -> 187
    //   123: iconst_1
    //   124: istore_2
    //   125: goto +67 -> 192
    //   128: iconst_1
    //   129: istore_1
    //   130: goto -119 -> 11
    //   133: iconst_0
    //   134: istore_2
    //   135: goto +57 -> 192
    //   138: goto -58 -> 80
    //   141: aload_0
    //   142: getfield 54	o/ᓵ:ॱ	Landroid/view/accessibility/AccessibilityNodeInfo;
    //   145: invokevirtual 138	android/view/accessibility/AccessibilityNodeInfo:hashCode	()I
    //   148: istore_1
    //   149: goto +69 -> 218
    //   152: iconst_0
    //   153: istore_2
    //   154: goto -58 -> 96
    //   157: iload_1
    //   158: lookupswitch	default:+26->184, 83:+-6->152, 93:+-17->141
    //   184: goto -32 -> 152
    //   187: iconst_0
    //   188: istore_1
    //   189: goto -178 -> 11
    //   192: iload_2
    //   193: tableswitch	default:+23->216, 0:+-184->9, 1:+-147->46
    //   216: iload_1
    //   217: ireturn
    //   218: goto -165 -> 53
    //   221: bipush 83
    //   223: istore_1
    //   224: goto -67 -> 157
    // Local variable table:
    //   start	length	slot	name	signature
    //   0	227	0	this	ᓵ
    //   5	219	1	i	int
    //   36	157	2	j	int
    //   93	2	3	localException	Exception
    // Exception table:
    //   from	to	target	type
    //   96	103	93	java/lang/Exception
    //   103	111	93	java/lang/Exception
  }
  
  /* Error */
  public String toString()
  {
    // Byte code:
    //   0: goto +625 -> 625
    //   3: astore 5
    //   5: aload 5
    //   7: athrow
    //   8: aload 5
    //   10: ldc -114
    //   12: invokevirtual 148	java/lang/StringBuilder:append	(Ljava/lang/String;)Ljava/lang/StringBuilder;
    //   15: pop
    //   16: aload 5
    //   18: invokevirtual 150	java/lang/StringBuilder:toString	()Ljava/lang/String;
    //   21: areturn
    //   22: bipush 68
    //   24: istore 4
    //   26: goto +562 -> 588
    //   29: goto +476 -> 505
    //   32: goto -3 -> 29
    //   35: iconst_1
    //   36: istore_2
    //   37: goto +481 -> 518
    //   40: bipush 57
    //   42: istore 4
    //   44: goto +544 -> 588
    //   47: getstatic 23	o/ᓵ:ˋ	I
    //   50: istore_2
    //   51: iload_2
    //   52: iconst_1
    //   53: iadd
    //   54: istore_2
    //   55: iload_2
    //   56: sipush 128
    //   59: irem
    //   60: putstatic 25	o/ᓵ:ˎ	I
    //   63: iload_2
    //   64: iconst_2
    //   65: irem
    //   66: ifne +6 -> 72
    //   69: goto -37 -> 32
    //   72: goto -43 -> 29
    //   75: getstatic 23	o/ᓵ:ˋ	I
    //   78: istore_2
    //   79: iload_2
    //   80: bipush 43
    //   82: iadd
    //   83: istore_2
    //   84: iload_2
    //   85: sipush 128
    //   88: irem
    //   89: putstatic 25	o/ᓵ:ˎ	I
    //   92: iload_2
    //   93: iconst_2
    //   94: irem
    //   95: ifne +6 -> 101
    //   98: goto +530 -> 628
    //   101: goto +442 -> 543
    //   104: new 144	java/lang/StringBuilder
    //   107: dup
    //   108: invokespecial 151	java/lang/StringBuilder:<init>	()V
    //   111: astore 5
    //   113: aload 5
    //   115: aload_0
    //   116: invokespecial 152	java/lang/Object:toString	()Ljava/lang/String;
    //   119: invokevirtual 148	java/lang/StringBuilder:append	(Ljava/lang/String;)Ljava/lang/StringBuilder;
    //   122: pop
    //   123: new 154	android/graphics/Rect
    //   126: dup
    //   127: invokespecial 155	android/graphics/Rect:<init>	()V
    //   130: astore 6
    //   132: aload_0
    //   133: aload 6
    //   135: invokevirtual 158	o/ᓵ:ˊ	(Landroid/graphics/Rect;)V
    //   138: aload 5
    //   140: new 144	java/lang/StringBuilder
    //   143: dup
    //   144: invokespecial 151	java/lang/StringBuilder:<init>	()V
    //   147: ldc -96
    //   149: invokevirtual 148	java/lang/StringBuilder:append	(Ljava/lang/String;)Ljava/lang/StringBuilder;
    //   152: aload 6
    //   154: invokevirtual 163	java/lang/StringBuilder:append	(Ljava/lang/Object;)Ljava/lang/StringBuilder;
    //   157: invokevirtual 150	java/lang/StringBuilder:toString	()Ljava/lang/String;
    //   160: invokevirtual 148	java/lang/StringBuilder:append	(Ljava/lang/String;)Ljava/lang/StringBuilder;
    //   163: pop
    //   164: aload_0
    //   165: aload 6
    //   167: invokevirtual 165	o/ᓵ:ˎ	(Landroid/graphics/Rect;)V
    //   170: aload 5
    //   172: new 144	java/lang/StringBuilder
    //   175: dup
    //   176: invokespecial 151	java/lang/StringBuilder:<init>	()V
    //   179: ldc -89
    //   181: invokevirtual 148	java/lang/StringBuilder:append	(Ljava/lang/String;)Ljava/lang/StringBuilder;
    //   184: aload 6
    //   186: invokevirtual 163	java/lang/StringBuilder:append	(Ljava/lang/Object;)Ljava/lang/StringBuilder;
    //   189: invokevirtual 150	java/lang/StringBuilder:toString	()Ljava/lang/String;
    //   192: invokevirtual 148	java/lang/StringBuilder:append	(Ljava/lang/String;)Ljava/lang/StringBuilder;
    //   195: pop
    //   196: aload 5
    //   198: ldc -87
    //   200: invokevirtual 148	java/lang/StringBuilder:append	(Ljava/lang/String;)Ljava/lang/StringBuilder;
    //   203: aload_0
    //   204: invokevirtual 173	o/ᓵ:ͺ	()Ljava/lang/CharSequence;
    //   207: invokevirtual 176	java/lang/StringBuilder:append	(Ljava/lang/CharSequence;)Ljava/lang/StringBuilder;
    //   210: pop
    //   211: aload 5
    //   213: ldc -78
    //   215: invokevirtual 148	java/lang/StringBuilder:append	(Ljava/lang/String;)Ljava/lang/StringBuilder;
    //   218: aload_0
    //   219: invokevirtual 181	o/ᓵ:ॱˋ	()Ljava/lang/CharSequence;
    //   222: invokevirtual 176	java/lang/StringBuilder:append	(Ljava/lang/CharSequence;)Ljava/lang/StringBuilder;
    //   225: pop
    //   226: aload 5
    //   228: ldc -73
    //   230: invokevirtual 148	java/lang/StringBuilder:append	(Ljava/lang/String;)Ljava/lang/StringBuilder;
    //   233: aload_0
    //   234: invokevirtual 186	o/ᓵ:ॱˎ	()Ljava/lang/CharSequence;
    //   237: invokevirtual 176	java/lang/StringBuilder:append	(Ljava/lang/CharSequence;)Ljava/lang/StringBuilder;
    //   240: pop
    //   241: aload 5
    //   243: ldc -68
    //   245: invokevirtual 148	java/lang/StringBuilder:append	(Ljava/lang/String;)Ljava/lang/StringBuilder;
    //   248: aload_0
    //   249: invokevirtual 191	o/ᓵ:ॱᐝ	()Ljava/lang/CharSequence;
    //   252: invokevirtual 176	java/lang/StringBuilder:append	(Ljava/lang/CharSequence;)Ljava/lang/StringBuilder;
    //   255: pop
    //   256: aload 5
    //   258: ldc -63
    //   260: invokevirtual 148	java/lang/StringBuilder:append	(Ljava/lang/String;)Ljava/lang/StringBuilder;
    //   263: aload_0
    //   264: invokevirtual 196	o/ᓵ:ʻॱ	()Ljava/lang/String;
    //   267: invokevirtual 148	java/lang/StringBuilder:append	(Ljava/lang/String;)Ljava/lang/StringBuilder;
    //   270: pop
    //   271: aload 5
    //   273: ldc -58
    //   275: invokevirtual 148	java/lang/StringBuilder:append	(Ljava/lang/String;)Ljava/lang/StringBuilder;
    //   278: aload_0
    //   279: invokevirtual 201	o/ᓵ:ˎ	()Z
    //   282: invokevirtual 204	java/lang/StringBuilder:append	(Z)Ljava/lang/StringBuilder;
    //   285: pop
    //   286: aload 5
    //   288: ldc -50
    //   290: invokevirtual 148	java/lang/StringBuilder:append	(Ljava/lang/String;)Ljava/lang/StringBuilder;
    //   293: aload_0
    //   294: invokevirtual 208	o/ᓵ:ˊ	()Z
    //   297: invokevirtual 204	java/lang/StringBuilder:append	(Z)Ljava/lang/StringBuilder;
    //   300: pop
    //   301: aload 5
    //   303: ldc -46
    //   305: invokevirtual 148	java/lang/StringBuilder:append	(Ljava/lang/String;)Ljava/lang/StringBuilder;
    //   308: aload_0
    //   309: invokevirtual 212	o/ᓵ:ˋ	()Z
    //   312: invokevirtual 204	java/lang/StringBuilder:append	(Z)Ljava/lang/StringBuilder;
    //   315: pop
    //   316: aload 5
    //   318: ldc -42
    //   320: invokevirtual 148	java/lang/StringBuilder:append	(Ljava/lang/String;)Ljava/lang/StringBuilder;
    //   323: aload_0
    //   324: invokevirtual 217	o/ᓵ:ᐝ	()Z
    //   327: invokevirtual 204	java/lang/StringBuilder:append	(Z)Ljava/lang/StringBuilder;
    //   330: pop
    //   331: aload 5
    //   333: ldc -37
    //   335: invokevirtual 148	java/lang/StringBuilder:append	(Ljava/lang/String;)Ljava/lang/StringBuilder;
    //   338: aload_0
    //   339: invokevirtual 222	o/ᓵ:ʻ	()Z
    //   342: invokevirtual 204	java/lang/StringBuilder:append	(Z)Ljava/lang/StringBuilder;
    //   345: pop
    //   346: aload 5
    //   348: ldc -32
    //   350: invokevirtual 148	java/lang/StringBuilder:append	(Ljava/lang/String;)Ljava/lang/StringBuilder;
    //   353: aload_0
    //   354: invokevirtual 227	o/ᓵ:ॱॱ	()Z
    //   357: invokevirtual 204	java/lang/StringBuilder:append	(Z)Ljava/lang/StringBuilder;
    //   360: pop
    //   361: aload 5
    //   363: ldc -27
    //   365: invokevirtual 148	java/lang/StringBuilder:append	(Ljava/lang/String;)Ljava/lang/StringBuilder;
    //   368: aload_0
    //   369: invokevirtual 232	o/ᓵ:ˊॱ	()Z
    //   372: invokevirtual 204	java/lang/StringBuilder:append	(Z)Ljava/lang/StringBuilder;
    //   375: pop
    //   376: aload 5
    //   378: ldc -22
    //   380: invokevirtual 148	java/lang/StringBuilder:append	(Ljava/lang/String;)Ljava/lang/StringBuilder;
    //   383: aload_0
    //   384: invokevirtual 237	o/ᓵ:ˋॱ	()Z
    //   387: invokevirtual 204	java/lang/StringBuilder:append	(Z)Ljava/lang/StringBuilder;
    //   390: pop
    //   391: aload 5
    //   393: bipush 6
    //   395: newarray int
    //   397: dup
    //   398: iconst_0
    //   399: ldc -18
    //   401: iastore
    //   402: dup
    //   403: iconst_1
    //   404: ldc -17
    //   406: iastore
    //   407: dup
    //   408: iconst_2
    //   409: ldc -16
    //   411: iastore
    //   412: dup
    //   413: iconst_3
    //   414: ldc -15
    //   416: iastore
    //   417: dup
    //   418: iconst_4
    //   419: ldc -14
    //   421: iastore
    //   422: dup
    //   423: iconst_5
    //   424: ldc -13
    //   426: iastore
    //   427: bipush 12
    //   429: invokestatic 245	o/ᓵ:ˋ	([II)Ljava/lang/String;
    //   432: invokevirtual 248	java/lang/String:intern	()Ljava/lang/String;
    //   435: invokevirtual 148	java/lang/StringBuilder:append	(Ljava/lang/String;)Ljava/lang/StringBuilder;
    //   438: aload_0
    //   439: invokevirtual 251	o/ᓵ:ˏॱ	()Z
    //   442: invokevirtual 204	java/lang/StringBuilder:append	(Z)Ljava/lang/StringBuilder;
    //   445: pop
    //   446: aload 5
    //   448: new 144	java/lang/StringBuilder
    //   451: dup
    //   452: invokespecial 151	java/lang/StringBuilder:<init>	()V
    //   455: ldc -3
    //   457: invokevirtual 148	java/lang/StringBuilder:append	(Ljava/lang/String;)Ljava/lang/StringBuilder;
    //   460: aload_0
    //   461: invokevirtual 256	o/ᓵ:ॱˊ	()Z
    //   464: invokevirtual 204	java/lang/StringBuilder:append	(Z)Ljava/lang/StringBuilder;
    //   467: invokevirtual 150	java/lang/StringBuilder:toString	()Ljava/lang/String;
    //   470: invokevirtual 148	java/lang/StringBuilder:append	(Ljava/lang/String;)Ljava/lang/StringBuilder;
    //   473: pop
    //   474: aload 5
    //   476: ldc_w 258
    //   479: invokevirtual 148	java/lang/StringBuilder:append	(Ljava/lang/String;)Ljava/lang/StringBuilder;
    //   482: pop
    //   483: aload_0
    //   484: invokevirtual 260	o/ᓵ:ॱ	()I
    //   487: istore_1
    //   488: goto +17 -> 505
    //   491: aload 5
    //   493: ldc_w 262
    //   496: invokevirtual 148	java/lang/StringBuilder:append	(Ljava/lang/String;)Ljava/lang/StringBuilder;
    //   499: pop
    //   500: iload_2
    //   501: istore_1
    //   502: goto +13 -> 515
    //   505: iload_1
    //   506: ifeq +6 -> 512
    //   509: goto -474 -> 35
    //   512: goto +71 -> 583
    //   515: goto -468 -> 47
    //   518: iload_2
    //   519: tableswitch	default:+21->540, 0:+-511->8, 1:+-444->75
    //   540: goto -532 -> 8
    //   543: iconst_1
    //   544: iload_1
    //   545: invokestatic 268	java/lang/Integer:numberOfTrailingZeros	(I)I
    //   548: ishl
    //   549: istore_2
    //   550: iload_1
    //   551: iload_2
    //   552: iconst_m1
    //   553: ixor
    //   554: iand
    //   555: istore_1
    //   556: aload 5
    //   558: iload_2
    //   559: invokestatic 270	o/ᓵ:ˎ	(I)Ljava/lang/String;
    //   562: invokevirtual 148	java/lang/StringBuilder:append	(Ljava/lang/String;)Ljava/lang/StringBuilder;
    //   565: pop
    //   566: iload_1
    //   567: ifeq +8 -> 575
    //   570: iload_1
    //   571: istore_2
    //   572: goto -81 -> 491
    //   575: goto -60 -> 515
    //   578: astore 5
    //   580: aload 5
    //   582: athrow
    //   583: iconst_0
    //   584: istore_2
    //   585: goto -67 -> 518
    //   588: iload_3
    //   589: istore_2
    //   590: iload_3
    //   591: istore_1
    //   592: iload 4
    //   594: lookupswitch	default:+26->620, 57:+-79->515, 68:+-103->491
    //   620: iload_3
    //   621: istore_2
    //   622: goto -131 -> 491
    //   625: goto -521 -> 104
    //   628: iconst_0
    //   629: iload_1
    //   630: invokestatic 268	java/lang/Integer:numberOfTrailingZeros	(I)I
    //   633: ishl
    //   634: istore_2
    //   635: iload_1
    //   636: iload_2
    //   637: iconst_m1
    //   638: ior
    //   639: ior
    //   640: istore_3
    //   641: aload 5
    //   643: iload_2
    //   644: invokestatic 270	o/ᓵ:ˎ	(I)Ljava/lang/String;
    //   647: invokevirtual 148	java/lang/StringBuilder:append	(Ljava/lang/String;)Ljava/lang/StringBuilder;
    //   650: pop
    //   651: iload_3
    //   652: ifeq +6 -> 658
    //   655: goto -633 -> 22
    //   658: goto -618 -> 40
    // Local variable table:
    //   start	length	slot	name	signature
    //   0	661	0	this	ᓵ
    //   487	153	1	i	int
    //   36	608	2	j	int
    //   588	64	3	k	int
    //   24	569	4	m	int
    //   3	14	5	localException1	Exception
    //   111	446	5	localStringBuilder	StringBuilder
    //   578	64	5	localException2	Exception
    //   130	55	6	localRect	Rect
    // Exception table:
    //   from	to	target	type
    //   75	79	3	java/lang/Exception
    //   84	92	3	java/lang/Exception
    //   47	51	578	java/lang/Exception
    //   55	63	578	java/lang/Exception
  }
  
  public void ʻ(boolean paramBoolean)
  {
    break label34;
    return;
    for (;;)
    {
      switch (i)
      {
      }
      int i = 25 / 0;
      return;
      label34:
      i = ˎ + 27;
      ˋ = i % 128;
      if (i % 2 == 0) {
        break label69;
      }
      for (;;)
      {
        i = 0;
        break;
        label69:
        this.ॱ.setLongClickable(paramBoolean);
        i = ˋ + 87;
        ˎ = i % 128;
        if (i % 2 == 0) {
          break label104;
        }
      }
      label104:
      i = 1;
    }
  }
  
  public boolean ʻ()
  {
    int i = ˋ + 43;
    ˎ = i % 128;
    if (i % 2 != 0) {
      break label27;
    }
    label27:
    boolean bool;
    for (;;)
    {
      bool = this.ॱ.isSelected();
      break;
    }
    i = ˎ + 19;
    ˋ = i % 128;
    if (i % 2 != 0) {
      return bool;
    }
    return bool;
  }
  
  public String ʻॱ()
  {
    break label185;
    int i = 1;
    for (;;)
    {
      try
      {
        i = Build.VERSION.SDK_INT;
        Object localObject;
        if (i < 18)
        {
          break label179;
          continue;
          return localObject;
        }
        else
        {
          i = 35;
          break label188;
          i = 0;
          continue;
          i = 48 / 0;
          return localObject;
          localObject = this.ॱ;
          localObject = ((AccessibilityNodeInfo)localObject).getViewIdResourceName();
          continue;
          i = 32;
          continue;
        }
        return null;
        switch (i)
        {
        }
        return localObject;
        switch (i)
        {
        case 32: 
        default: 
          continue;
          i = ˋ + 3;
          ˎ = i % 128;
          if (i % 2 == 0) {
            continue;
          }
          break;
        }
      }
      catch (Exception localException)
      {
        throw localException;
      }
      i = ˎ + 55;
      ˋ = i % 128;
      if (i % 2 == 0)
      {
        continue;
        label179:
        i = 94;
        break label188;
        label185:
        continue;
        label188:
        switch (i)
        {
        }
        continue;
        if (Build.VERSION.SDK_INT >= 65) {}
      }
      else
      {
        i = 65;
      }
    }
  }
  
  /* Error */
  public void ʼ(boolean paramBoolean)
  {
    // Byte code:
    //   0: goto +57 -> 57
    //   3: getstatic 25	o/ᓵ:ˎ	I
    //   6: bipush 47
    //   8: iadd
    //   9: istore_2
    //   10: iload_2
    //   11: sipush 128
    //   14: irem
    //   15: putstatic 23	o/ᓵ:ˋ	I
    //   18: iload_2
    //   19: iconst_2
    //   20: irem
    //   21: ifeq +6 -> 27
    //   24: goto +95 -> 119
    //   27: goto +33 -> 60
    //   30: getstatic 23	o/ᓵ:ˋ	I
    //   33: bipush 21
    //   35: iadd
    //   36: istore_2
    //   37: iload_2
    //   38: sipush 128
    //   41: irem
    //   42: putstatic 25	o/ᓵ:ˎ	I
    //   45: iload_2
    //   46: iconst_2
    //   47: irem
    //   48: ifne +6 -> 54
    //   51: goto +32 -> 83
    //   54: goto +68 -> 122
    //   57: goto -54 -> 3
    //   60: getstatic 282	android/os/Build$VERSION:SDK_INT	I
    //   63: istore_2
    //   64: iload_2
    //   65: bipush 16
    //   67: if_icmplt +6 -> 73
    //   70: goto +7 -> 77
    //   73: goto +14 -> 87
    //   76: return
    //   77: bipush 63
    //   79: istore_2
    //   80: goto +10 -> 90
    //   83: goto +39 -> 122
    //   86: return
    //   87: bipush 38
    //   89: istore_2
    //   90: iload_2
    //   91: lookupswitch	default:+25->116, 38:+-5->86, 63:+-61->30
    //   116: goto -86 -> 30
    //   119: goto -59 -> 60
    //   122: aload_0
    //   123: getfield 54	o/ᓵ:ॱ	Landroid/view/accessibility/AccessibilityNodeInfo;
    //   126: iload_1
    //   127: invokevirtual 289	android/view/accessibility/AccessibilityNodeInfo:setAccessibilityFocused	(Z)V
    //   130: getstatic 25	o/ᓵ:ˎ	I
    //   133: bipush 65
    //   135: iadd
    //   136: istore_2
    //   137: iload_2
    //   138: sipush 128
    //   141: irem
    //   142: putstatic 23	o/ᓵ:ˋ	I
    //   145: iload_2
    //   146: iconst_2
    //   147: irem
    //   148: ifeq +6 -> 154
    //   151: goto +6 -> 157
    //   154: goto -78 -> 76
    //   157: goto -81 -> 76
    //   160: astore_3
    //   161: aload_3
    //   162: athrow
    // Local variable table:
    //   start	length	slot	name	signature
    //   0	163	0	this	ᓵ
    //   0	163	1	paramBoolean	boolean
    //   9	139	2	i	int
    //   160	2	3	localException	Exception
    // Exception table:
    //   from	to	target	type
    //   60	64	160	java/lang/Exception
  }
  
  /* Error */
  public boolean ʼ()
  {
    // Byte code:
    //   0: goto +127 -> 127
    //   3: getstatic 25	o/ᓵ:ˎ	I
    //   6: iconst_1
    //   7: iadd
    //   8: istore_1
    //   9: iload_1
    //   10: sipush 128
    //   13: irem
    //   14: putstatic 23	o/ᓵ:ˋ	I
    //   17: iload_1
    //   18: iconst_2
    //   19: irem
    //   20: ifeq +6 -> 26
    //   23: goto +6 -> 29
    //   26: goto +104 -> 130
    //   29: goto +101 -> 130
    //   32: astore_3
    //   33: aload_3
    //   34: athrow
    //   35: astore_3
    //   36: aload_3
    //   37: athrow
    //   38: getstatic 282	android/os/Build$VERSION:SDK_INT	I
    //   41: istore_1
    //   42: iload_1
    //   43: bipush 16
    //   45: if_icmplt +6 -> 51
    //   48: goto +9 -> 57
    //   51: goto +70 -> 121
    //   54: goto -16 -> 38
    //   57: bipush 6
    //   59: istore_1
    //   60: goto +30 -> 90
    //   63: getstatic 25	o/ᓵ:ˎ	I
    //   66: bipush 63
    //   68: iadd
    //   69: istore_1
    //   70: iload_1
    //   71: sipush 128
    //   74: irem
    //   75: putstatic 23	o/ᓵ:ˋ	I
    //   78: iload_1
    //   79: iconst_2
    //   80: irem
    //   81: ifeq +6 -> 87
    //   84: goto -30 -> 54
    //   87: goto -49 -> 38
    //   90: iload_1
    //   91: lookupswitch	default:+25->116, 6:+-88->3, 35:+28->119
    //   116: goto -113 -> 3
    //   119: iconst_0
    //   120: ireturn
    //   121: bipush 35
    //   123: istore_1
    //   124: goto -34 -> 90
    //   127: goto -64 -> 63
    //   130: aload_0
    //   131: getfield 54	o/ᓵ:ॱ	Landroid/view/accessibility/AccessibilityNodeInfo;
    //   134: astore_3
    //   135: aload_3
    //   136: invokevirtual 292	android/view/accessibility/AccessibilityNodeInfo:isAccessibilityFocused	()Z
    //   139: istore_2
    //   140: iload_2
    //   141: ireturn
    // Local variable table:
    //   start	length	slot	name	signature
    //   0	142	0	this	ᓵ
    //   8	116	1	i	int
    //   139	2	2	bool	boolean
    //   32	2	3	localException1	Exception
    //   35	2	3	localException2	Exception
    //   134	2	3	localAccessibilityNodeInfo	AccessibilityNodeInfo
    // Exception table:
    //   from	to	target	type
    //   135	140	32	java/lang/Exception
    //   38	42	35	java/lang/Exception
    //   130	135	35	java/lang/Exception
  }
  
  /* Error */
  public ˊ ʼॱ()
  {
    // Byte code:
    //   0: goto +143 -> 143
    //   3: aload_0
    //   4: getfield 54	o/ᓵ:ॱ	Landroid/view/accessibility/AccessibilityNodeInfo;
    //   7: astore_2
    //   8: aload_2
    //   9: invokevirtual 298	android/view/accessibility/AccessibilityNodeInfo:getCollectionItemInfo	()Landroid/view/accessibility/AccessibilityNodeInfo$CollectionItemInfo;
    //   12: astore_2
    //   13: aload_2
    //   14: ifnull +6 -> 20
    //   17: goto +85 -> 102
    //   20: goto +44 -> 64
    //   23: getstatic 25	o/ᓵ:ˎ	I
    //   26: bipush 25
    //   28: iadd
    //   29: istore_1
    //   30: iload_1
    //   31: sipush 128
    //   34: irem
    //   35: putstatic 23	o/ᓵ:ˋ	I
    //   38: iload_1
    //   39: iconst_2
    //   40: irem
    //   41: ifeq +6 -> 47
    //   44: goto -41 -> 3
    //   47: goto -44 -> 3
    //   50: getstatic 282	android/os/Build$VERSION:SDK_INT	I
    //   53: bipush 19
    //   55: if_icmplt +6 -> 61
    //   58: goto +53 -> 111
    //   61: goto +36 -> 97
    //   64: goto +52 -> 116
    //   67: getstatic 23	o/ᓵ:ˋ	I
    //   70: bipush 89
    //   72: iadd
    //   73: istore_1
    //   74: iload_1
    //   75: sipush 128
    //   78: irem
    //   79: putstatic 25	o/ᓵ:ˎ	I
    //   82: iload_1
    //   83: iconst_2
    //   84: irem
    //   85: ifne +6 -> 91
    //   88: goto -38 -> 50
    //   91: goto -41 -> 50
    //   94: astore_2
    //   95: aload_2
    //   96: athrow
    //   97: iconst_0
    //   98: istore_1
    //   99: goto +19 -> 118
    //   102: new 9	o/ᓵ$ˊ
    //   105: dup
    //   106: aload_2
    //   107: invokespecial 301	o/ᓵ$ˊ:<init>	(Ljava/lang/Object;)V
    //   110: areturn
    //   111: iconst_1
    //   112: istore_1
    //   113: goto +5 -> 118
    //   116: aconst_null
    //   117: areturn
    //   118: iload_1
    //   119: tableswitch	default:+21->140, 0:+-55->64, 1:+-96->23
    //   140: goto -117 -> 23
    //   143: goto -76 -> 67
    //   146: astore_2
    //   147: aload_2
    //   148: athrow
    // Local variable table:
    //   start	length	slot	name	signature
    //   0	149	0	this	ᓵ
    //   29	90	1	i	int
    //   7	7	2	localObject	Object
    //   94	13	2	localException1	Exception
    //   146	2	2	localException2	Exception
    // Exception table:
    //   from	to	target	type
    //   8	13	94	java/lang/Exception
    //   3	8	146	java/lang/Exception
    //   8	13	146	java/lang/Exception
  }
  
  public void ʽ(boolean paramBoolean)
  {
    break label70;
    label14:
    for (;;)
    {
      this.ॱ.setEnabled(paramBoolean);
      break;
    }
    label70:
    for (;;)
    {
      int i = ˎ + 119;
      ˋ = i % 128;
      if (i % 2 != 0) {
        break label14;
      }
      break;
      i = ˋ + 123;
      ˎ = i % 128;
      if (i % 2 != 0) {
        return;
      }
      return;
    }
  }
  
  /* Error */
  public boolean ʽ()
  {
    // Byte code:
    //   0: goto +183 -> 183
    //   3: iconst_0
    //   4: istore_1
    //   5: goto +152 -> 157
    //   8: getstatic 25	o/ᓵ:ˎ	I
    //   11: bipush 13
    //   13: iadd
    //   14: istore_1
    //   15: iload_1
    //   16: sipush 128
    //   19: irem
    //   20: putstatic 23	o/ᓵ:ˋ	I
    //   23: iload_1
    //   24: iconst_2
    //   25: irem
    //   26: ifeq +6 -> 32
    //   29: goto +106 -> 135
    //   32: goto +47 -> 79
    //   35: getstatic 282	android/os/Build$VERSION:SDK_INT	I
    //   38: bipush 16
    //   40: if_icmplt +6 -> 46
    //   43: goto +75 -> 118
    //   46: goto +30 -> 76
    //   49: getstatic 25	o/ᓵ:ˎ	I
    //   52: bipush 47
    //   54: iadd
    //   55: istore_1
    //   56: iload_1
    //   57: sipush 128
    //   60: irem
    //   61: putstatic 23	o/ᓵ:ˋ	I
    //   64: iload_1
    //   65: iconst_2
    //   66: irem
    //   67: ifeq +6 -> 73
    //   70: goto +11 -> 81
    //   73: goto -70 -> 3
    //   76: goto -68 -> 8
    //   79: iconst_0
    //   80: ireturn
    //   81: iconst_1
    //   82: istore_1
    //   83: goto +74 -> 157
    //   86: astore_3
    //   87: aload_3
    //   88: athrow
    //   89: iload_1
    //   90: tableswitch	default:+22->112, 0:+-14->76, 1:+28->118
    //   112: goto -36 -> 76
    //   115: astore_3
    //   116: aload_3
    //   117: athrow
    //   118: aload_0
    //   119: getfield 54	o/ᓵ:ॱ	Landroid/view/accessibility/AccessibilityNodeInfo;
    //   122: astore_3
    //   123: aload_3
    //   124: invokevirtual 308	android/view/accessibility/AccessibilityNodeInfo:isVisibleToUser	()Z
    //   127: istore_2
    //   128: iload_2
    //   129: ireturn
    //   130: iconst_0
    //   131: istore_1
    //   132: goto -43 -> 89
    //   135: goto -56 -> 79
    //   138: iconst_1
    //   139: istore_1
    //   140: goto -51 -> 89
    //   143: getstatic 282	android/os/Build$VERSION:SDK_INT	I
    //   146: bipush 32
    //   148: if_icmplt +6 -> 154
    //   151: goto -13 -> 138
    //   154: goto -24 -> 130
    //   157: iload_1
    //   158: tableswitch	default:+22->180, 0:+-123->35, 1:+-15->143
    //   180: goto -37 -> 143
    //   183: goto -134 -> 49
    // Local variable table:
    //   start	length	slot	name	signature
    //   0	186	0	this	ᓵ
    //   4	154	1	i	int
    //   127	2	2	bool	boolean
    //   86	2	3	localException1	Exception
    //   115	2	3	localException2	Exception
    //   122	2	3	localAccessibilityNodeInfo	AccessibilityNodeInfo
    // Exception table:
    //   from	to	target	type
    //   118	123	86	java/lang/Exception
    //   123	128	86	java/lang/Exception
    //   123	128	115	java/lang/Exception
  }
  
  /* Error */
  public void ˊ(Rect paramRect)
  {
    // Byte code:
    //   0: goto +39 -> 39
    //   3: astore_1
    //   4: aload_1
    //   5: athrow
    //   6: bipush 84
    //   8: istore_2
    //   9: iload_2
    //   10: lookupswitch	default:+26->36, 59:+43->53, 84:+32->42
    //   36: goto +17 -> 53
    //   39: goto +26 -> 65
    //   42: aload_0
    //   43: getfield 54	o/ᓵ:ॱ	Landroid/view/accessibility/AccessibilityNodeInfo;
    //   46: astore_3
    //   47: aload_3
    //   48: aload_1
    //   49: invokevirtual 311	android/view/accessibility/AccessibilityNodeInfo:getBoundsInParent	(Landroid/graphics/Rect;)V
    //   52: return
    //   53: aload_0
    //   54: getfield 54	o/ᓵ:ॱ	Landroid/view/accessibility/AccessibilityNodeInfo;
    //   57: aload_1
    //   58: invokevirtual 311	android/view/accessibility/AccessibilityNodeInfo:getBoundsInParent	(Landroid/graphics/Rect;)V
    //   61: aconst_null
    //   62: arraylength
    //   63: istore_2
    //   64: return
    //   65: getstatic 25	o/ᓵ:ˎ	I
    //   68: bipush 29
    //   70: iadd
    //   71: istore_2
    //   72: iload_2
    //   73: sipush 128
    //   76: irem
    //   77: putstatic 23	o/ᓵ:ˋ	I
    //   80: iload_2
    //   81: iconst_2
    //   82: irem
    //   83: ifeq +6 -> 89
    //   86: goto +6 -> 92
    //   89: goto -83 -> 6
    //   92: bipush 59
    //   94: istore_2
    //   95: goto -86 -> 9
    // Local variable table:
    //   start	length	slot	name	signature
    //   0	98	0	this	ᓵ
    //   0	98	1	paramRect	Rect
    //   8	87	2	i	int
    //   46	2	3	localAccessibilityNodeInfo	AccessibilityNodeInfo
    // Exception table:
    //   from	to	target	type
    //   42	47	3	java/lang/Exception
    //   47	52	3	java/lang/Exception
  }
  
  /* Error */
  public void ˊ(View paramView)
  {
    // Byte code:
    //   0: goto +53 -> 53
    //   3: aconst_null
    //   4: arraylength
    //   5: istore_2
    //   6: return
    //   7: return
    //   8: bipush 34
    //   10: istore_2
    //   11: goto +14 -> 25
    //   14: bipush 20
    //   16: istore_2
    //   17: goto +8 -> 25
    //   20: iconst_0
    //   21: istore_2
    //   22: goto +85 -> 107
    //   25: iload_2
    //   26: lookupswitch	default:+26->52, 20:+-23->3, 34:+-19->7
    //   52: return
    //   53: getstatic 25	o/ᓵ:ˎ	I
    //   56: bipush 51
    //   58: iadd
    //   59: istore_2
    //   60: iload_2
    //   61: sipush 128
    //   64: irem
    //   65: putstatic 23	o/ᓵ:ˋ	I
    //   68: iload_2
    //   69: iconst_2
    //   70: irem
    //   71: ifeq +6 -> 77
    //   74: goto -54 -> 20
    //   77: goto +90 -> 167
    //   80: getstatic 25	o/ᓵ:ˎ	I
    //   83: bipush 101
    //   85: iadd
    //   86: istore_2
    //   87: iload_2
    //   88: sipush 128
    //   91: irem
    //   92: putstatic 23	o/ᓵ:ˋ	I
    //   95: iload_2
    //   96: iconst_2
    //   97: irem
    //   98: ifeq +6 -> 104
    //   101: goto -87 -> 14
    //   104: goto -96 -> 8
    //   107: iload_2
    //   108: tableswitch	default:+24->132, 0:+30->138, 1:+48->156
    //   132: goto +6 -> 138
    //   135: astore_1
    //   136: aload_1
    //   137: athrow
    //   138: aload_0
    //   139: getfield 54	o/ᓵ:ॱ	Landroid/view/accessibility/AccessibilityNodeInfo;
    //   142: astore_3
    //   143: aload_3
    //   144: aload_1
    //   145: invokevirtual 315	android/view/accessibility/AccessibilityNodeInfo:addChild	(Landroid/view/View;)V
    //   148: new 111	java/lang/NullPointerException
    //   151: dup
    //   152: invokespecial 112	java/lang/NullPointerException:<init>	()V
    //   155: athrow
    //   156: aload_0
    //   157: getfield 54	o/ᓵ:ॱ	Landroid/view/accessibility/AccessibilityNodeInfo;
    //   160: aload_1
    //   161: invokevirtual 315	android/view/accessibility/AccessibilityNodeInfo:addChild	(Landroid/view/View;)V
    //   164: goto -84 -> 80
    //   167: iconst_1
    //   168: istore_2
    //   169: goto -62 -> 107
    // Local variable table:
    //   start	length	slot	name	signature
    //   0	172	0	this	ᓵ
    //   0	172	1	paramView	View
    //   5	164	2	i	int
    //   142	2	3	localAccessibilityNodeInfo	AccessibilityNodeInfo
    // Exception table:
    //   from	to	target	type
    //   138	143	135	java/lang/Exception
    //   143	156	135	java/lang/Exception
  }
  
  public void ˊ(CharSequence paramCharSequence)
  {
    break label101;
    this.ॱ.setPackageName(paramCharSequence);
    for (;;)
    {
      int i;
      switch (i)
      {
      default: 
        break label110;
        i = ˎ + 89;
        ˋ = i % 128;
        if (i % 2 != 0) {}
        break;
      case 12: 
        return;
        for (;;)
        {
          i = ˎ + 97;
          ˋ = i % 128;
          if (i % 2 == 0) {
            break;
          }
          break;
        }
        i = 39;
        break;
      case 39: 
        label101:
        label110:
        i = 46 / 0;
        return;
        i = 12;
      }
    }
  }
  
  public void ˊ(boolean paramBoolean)
  {
    int i;
    for (;;)
    {
      this.ॱ.setCheckable(paramBoolean);
      break label87;
      i = 30;
      break;
      i = ˎ + 123;
      ˋ = i % 128;
      if (i % 2 == 0) {}
    }
    return;
    for (;;)
    {
      switch (i)
      {
      case 30: 
      default: 
        return;
      }
      i = 25 / 0;
      return;
      label87:
      i = ˎ + 53;
      ˋ = i % 128;
      if (i % 2 == 0) {
        break;
      }
      i = 67;
    }
  }
  
  public boolean ˊ()
  {
    for (;;)
    {
      label39:
      boolean bool;
      switch (i)
      {
      default: 
        break;
        break label101;
        for (;;)
        {
          i = 1;
          break;
          i = ˋ + 115;
          ˎ = i % 128;
          if (i % 2 == 0) {
            break label115;
          }
        }
      case 0: 
        i = 4 / 0;
        return bool;
      }
      for (;;)
      {
        i = ˋ + 69;
        ˎ = i % 128;
        if (i % 2 == 0) {
          break;
        }
        break;
        return bool;
        label101:
        bool = this.ॱ.isChecked();
        break label39;
      }
      label115:
      int i = 0;
    }
  }
  
  public void ˊॱ(boolean paramBoolean)
  {
    break label47;
    int i;
    if (Build.VERSION.SDK_INT < 19) {
      i = 0;
    }
    for (;;)
    {
      i = ˋ + 95;
      ˎ = i % 128;
      if (i % 2 != 0) {
        break label46;
      }
      label46:
      return;
      label47:
      break label56;
      return;
      i = 1;
      break label86;
      label56:
      i = ˎ + 61;
      ˋ = i % 128;
      if (i % 2 == 0) {
        break;
      }
      break;
      switch (i)
      {
      case 0: 
      default: 
        label86:
        return;
      }
      this.ॱ.setContentInvalid(paramBoolean);
    }
  }
  
  public boolean ˊॱ()
  {
    break label35;
    break label66;
    for (;;)
    {
      try
      {
        i = ˎ;
        i += 47;
        ˋ = i % 128;
        if (i % 2 != 0) {
          break;
        }
      }
      catch (Exception localException)
      {
        int i;
        label35:
        throw localException;
      }
    }
    for (;;)
    {
      i = ˋ + 75;
      ˎ = i % 128;
      if (i % 2 == 0) {
        return bool;
      }
      return bool;
      label66:
      boolean bool = this.ॱ.isLongClickable();
    }
  }
  
  public void ˋ(CharSequence paramCharSequence)
  {
    label174:
    for (;;)
    {
      try
      {
        int i = ˋ;
        i += 29;
        ˎ = i % 128;
        if (i % 2 != 0)
        {
          continue;
          i = 26;
          continue;
          i = 1;
          continue;
          i = 39;
          continue;
          this.ॱ.setError(paramCharSequence);
          switch (i)
          {
          case 39: 
          default: 
            continue;
            return;
            i = ˎ + 87;
          }
        }
        try
        {
          ˋ = i % 128;
          if (i % 2 != 0) {
            break label174;
          }
        }
        catch (Exception paramCharSequence)
        {
          throw paramCharSequence;
        }
        return;
        return;
        continue;
        switch (i)
        {
        }
        continue;
        if (Build.VERSION.SDK_INT < 21)
        {
          continue;
        }
        else
        {
          continue;
          i = 0;
        }
      }
      catch (Exception paramCharSequence)
      {
        throw paramCharSequence;
      }
    }
  }
  
  /* Error */
  public void ˋ(boolean paramBoolean)
  {
    // Byte code:
    //   0: goto +35 -> 35
    //   3: iconst_1
    //   4: istore_2
    //   5: goto +86 -> 91
    //   8: getstatic 25	o/ᓵ:ˎ	I
    //   11: bipush 43
    //   13: iadd
    //   14: istore_2
    //   15: iload_2
    //   16: sipush 128
    //   19: irem
    //   20: putstatic 23	o/ᓵ:ˋ	I
    //   23: iload_2
    //   24: iconst_2
    //   25: irem
    //   26: ifeq +6 -> 32
    //   29: goto +163 -> 192
    //   32: goto +95 -> 127
    //   35: goto +126 -> 161
    //   38: getstatic 25	o/ᓵ:ˎ	I
    //   41: bipush 119
    //   43: iadd
    //   44: istore_2
    //   45: iload_2
    //   46: sipush 128
    //   49: irem
    //   50: putstatic 23	o/ᓵ:ˋ	I
    //   53: iload_2
    //   54: iconst_2
    //   55: irem
    //   56: ifeq +6 -> 62
    //   59: goto +79 -> 138
    //   62: goto +55 -> 117
    //   65: return
    //   66: iload_2
    //   67: tableswitch	default:+21->88, 0:+90->157, 1:+124->191
    //   88: goto +69 -> 157
    //   91: iload_2
    //   92: tableswitch	default:+24->116, 0:+-84->8, 1:+-27->65
    //   116: return
    //   117: iconst_0
    //   118: istore_2
    //   119: goto -53 -> 66
    //   122: iconst_0
    //   123: istore_2
    //   124: goto -33 -> 91
    //   127: aload_0
    //   128: getfield 54	o/ᓵ:ॱ	Landroid/view/accessibility/AccessibilityNodeInfo;
    //   131: iload_1
    //   132: invokevirtual 337	android/view/accessibility/AccessibilityNodeInfo:setVisibleToUser	(Z)V
    //   135: goto -97 -> 38
    //   138: iconst_1
    //   139: istore_2
    //   140: goto -74 -> 66
    //   143: getstatic 282	android/os/Build$VERSION:SDK_INT	I
    //   146: bipush 16
    //   148: if_icmplt +6 -> 154
    //   151: goto -29 -> 122
    //   154: goto -151 -> 3
    //   157: return
    //   158: astore_3
    //   159: aload_3
    //   160: athrow
    //   161: getstatic 23	o/ᓵ:ˋ	I
    //   164: bipush 99
    //   166: iadd
    //   167: istore_2
    //   168: iload_2
    //   169: sipush 128
    //   172: irem
    //   173: putstatic 25	o/ᓵ:ˎ	I
    //   176: iload_2
    //   177: iconst_2
    //   178: irem
    //   179: ifne +6 -> 185
    //   182: goto +6 -> 188
    //   185: goto -42 -> 143
    //   188: goto -45 -> 143
    //   191: return
    //   192: goto -65 -> 127
    // Local variable table:
    //   start	length	slot	name	signature
    //   0	195	0	this	ᓵ
    //   0	195	1	paramBoolean	boolean
    //   4	175	2	i	int
    //   158	2	3	localException	Exception
    // Exception table:
    //   from	to	target	type
    //   161	168	158	java/lang/Exception
    //   168	176	158	java/lang/Exception
  }
  
  public boolean ˋ()
  {
    break label80;
    boolean bool;
    return bool;
    label80:
    for (;;)
    {
      int i;
      try
      {
        AccessibilityNodeInfo localAccessibilityNodeInfo = this.ॱ;
        try
        {
          bool = localAccessibilityNodeInfo.isFocusable();
        }
        catch (Exception localException1)
        {
          throw localException1;
        }
        continue;
        i = ˋ + 65;
        ˎ = i % 128;
        if (i % 2 == 0) {
          continue;
        }
        continue;
        i = ˎ + 87;
      }
      catch (Exception localException2)
      {
        throw localException2;
      }
      ˋ = i % 128;
      if (i % 2 != 0) {
        break;
      }
      return bool;
    }
  }
  
  public void ˋॱ(boolean paramBoolean)
  {
    for (int i = 1;; i = 0) {
      switch (i)
      {
      default: 
        break label58;
        i = ˋ + 33;
        ˎ = i % 128;
        if (i % 2 == 0) {
          break;
        }
        break;
      case 0: 
        label58:
        this.ॱ.setScrollable(paramBoolean);
        return;
      }
    }
    this.ॱ.setScrollable(paramBoolean);
    i = null.length;
  }
  
  public boolean ˋॱ()
  {
    break label36;
    for (;;)
    {
      switch (i)
      {
      default: 
        break label39;
        label31:
        i = 0;
      }
    }
    label36:
    break label65;
    label39:
    boolean bool = this.ॱ.isEnabled();
    int i = null.length;
    return bool;
    for (;;)
    {
      i = 1;
      break;
      return this.ॱ.isEnabled();
      label65:
      i = ˎ + 87;
      ˋ = i % 128;
      if (i % 2 != 0) {
        break label31;
      }
    }
  }
  
  public void ˎ(Rect paramRect)
  {
    break label29;
    return;
    for (;;)
    {
      int i = ˋ + 109;
      ˎ = i % 128;
      if (i % 2 == 0) {
        break;
      }
      return;
      label29:
      do
      {
        break;
        i = ˋ + 67;
        ˎ = i % 128;
      } while (i % 2 == 0);
      this.ॱ.getBoundsInScreen(paramRect);
    }
  }
  
  /* Error */
  public void ˎ(View paramView)
  {
    // Byte code:
    //   0: goto +70 -> 70
    //   3: astore_1
    //   4: aload_1
    //   5: athrow
    //   6: bipush 31
    //   8: istore_2
    //   9: iload_2
    //   10: lookupswitch	default:+26->36, 31:+96->106, 94:+90->100
    //   36: return
    //   37: bipush 39
    //   39: istore_2
    //   40: goto +67 -> 107
    //   43: getstatic 25	o/ᓵ:ˎ	I
    //   46: bipush 109
    //   48: iadd
    //   49: istore_2
    //   50: iload_2
    //   51: sipush 128
    //   54: irem
    //   55: putstatic 23	o/ᓵ:ˋ	I
    //   58: iload_2
    //   59: iconst_2
    //   60: irem
    //   61: ifeq +6 -> 67
    //   64: goto -27 -> 37
    //   67: goto +72 -> 139
    //   70: goto -27 -> 43
    //   73: getstatic 23	o/ᓵ:ˋ	I
    //   76: bipush 99
    //   78: iadd
    //   79: istore_2
    //   80: iload_2
    //   81: sipush 128
    //   84: irem
    //   85: putstatic 25	o/ᓵ:ˎ	I
    //   88: iload_2
    //   89: iconst_2
    //   90: irem
    //   91: ifne +6 -> 97
    //   94: goto +76 -> 170
    //   97: goto -91 -> 6
    //   100: bipush 49
    //   102: iconst_0
    //   103: idiv
    //   104: istore_2
    //   105: return
    //   106: return
    //   107: iload_2
    //   108: lookupswitch	default:+28->136, 39:+48->156, 86:+37->145
    //   136: goto +20 -> 156
    //   139: bipush 86
    //   141: istore_2
    //   142: goto -35 -> 107
    //   145: aload_0
    //   146: getfield 54	o/ᓵ:ॱ	Landroid/view/accessibility/AccessibilityNodeInfo;
    //   149: aload_1
    //   150: invokevirtual 352	android/view/accessibility/AccessibilityNodeInfo:setSource	(Landroid/view/View;)V
    //   153: goto -80 -> 73
    //   156: aload_0
    //   157: getfield 54	o/ᓵ:ॱ	Landroid/view/accessibility/AccessibilityNodeInfo;
    //   160: aload_1
    //   161: invokevirtual 352	android/view/accessibility/AccessibilityNodeInfo:setSource	(Landroid/view/View;)V
    //   164: aconst_null
    //   165: arraylength
    //   166: istore_2
    //   167: goto -94 -> 73
    //   170: bipush 94
    //   172: istore_2
    //   173: goto -164 -> 9
    // Local variable table:
    //   start	length	slot	name	signature
    //   0	176	0	this	ᓵ
    //   0	176	1	paramView	View
    //   8	165	2	i	int
    // Exception table:
    //   from	to	target	type
    //   73	80	3	java/lang/Exception
    //   80	88	3	java/lang/Exception
  }
  
  /* Error */
  public void ˎ(CharSequence paramCharSequence)
  {
    // Byte code:
    //   0: goto +22 -> 22
    //   3: aload_0
    //   4: getfield 54	o/ᓵ:ॱ	Landroid/view/accessibility/AccessibilityNodeInfo;
    //   7: astore_3
    //   8: aload_3
    //   9: aload_1
    //   10: invokevirtual 355	android/view/accessibility/AccessibilityNodeInfo:setText	(Ljava/lang/CharSequence;)V
    //   13: aconst_null
    //   14: arraylength
    //   15: istore_2
    //   16: goto +90 -> 106
    //   19: astore_1
    //   20: aload_1
    //   21: athrow
    //   22: goto +49 -> 71
    //   25: astore_1
    //   26: aload_1
    //   27: athrow
    //   28: aload_0
    //   29: getfield 54	o/ᓵ:ॱ	Landroid/view/accessibility/AccessibilityNodeInfo;
    //   32: aload_1
    //   33: invokevirtual 355	android/view/accessibility/AccessibilityNodeInfo:setText	(Ljava/lang/CharSequence;)V
    //   36: goto +70 -> 106
    //   39: iload_2
    //   40: lookupswitch	default:+28->68, 51:+-37->3, 85:+-12->28
    //   68: goto -40 -> 28
    //   71: getstatic 23	o/ᓵ:ˋ	I
    //   74: istore_2
    //   75: iload_2
    //   76: bipush 23
    //   78: iadd
    //   79: istore_2
    //   80: iload_2
    //   81: sipush 128
    //   84: irem
    //   85: putstatic 25	o/ᓵ:ˎ	I
    //   88: iload_2
    //   89: iconst_2
    //   90: irem
    //   91: ifne +6 -> 97
    //   94: goto +6 -> 100
    //   97: goto +31 -> 128
    //   100: bipush 51
    //   102: istore_2
    //   103: goto -64 -> 39
    //   106: getstatic 25	o/ᓵ:ˎ	I
    //   109: iconst_1
    //   110: iadd
    //   111: istore_2
    //   112: iload_2
    //   113: sipush 128
    //   116: irem
    //   117: putstatic 23	o/ᓵ:ˋ	I
    //   120: iload_2
    //   121: iconst_2
    //   122: irem
    //   123: ifeq +4 -> 127
    //   126: return
    //   127: return
    //   128: bipush 85
    //   130: istore_2
    //   131: goto -92 -> 39
    // Local variable table:
    //   start	length	slot	name	signature
    //   0	134	0	this	ᓵ
    //   0	134	1	paramCharSequence	CharSequence
    //   15	116	2	i	int
    //   7	2	3	localAccessibilityNodeInfo	AccessibilityNodeInfo
    // Exception table:
    //   from	to	target	type
    //   80	88	19	java/lang/Exception
    //   3	8	25	java/lang/Exception
    //   8	13	25	java/lang/Exception
    //   13	16	25	java/lang/Exception
    //   71	75	25	java/lang/Exception
  }
  
  /* Error */
  public void ˎ(Object paramObject)
  {
    // Byte code:
    //   0: goto +33 -> 33
    //   3: astore_1
    //   4: aload_1
    //   5: athrow
    //   6: bipush 79
    //   8: istore_2
    //   9: goto +176 -> 185
    //   12: aload_0
    //   13: getfield 54	o/ᓵ:ॱ	Landroid/view/accessibility/AccessibilityNodeInfo;
    //   16: aload_1
    //   17: checkcast 9	o/ᓵ$ˊ
    //   20: getfield 358	o/ᓵ$ˊ:ˎ	Ljava/lang/Object;
    //   23: checkcast 360	android/view/accessibility/AccessibilityNodeInfo$CollectionItemInfo
    //   26: invokevirtual 364	android/view/accessibility/AccessibilityNodeInfo:setCollectionItemInfo	(Landroid/view/accessibility/AccessibilityNodeInfo$CollectionItemInfo;)V
    //   29: goto +136 -> 165
    //   32: return
    //   33: goto +103 -> 136
    //   36: iconst_0
    //   37: istore_2
    //   38: goto +9 -> 47
    //   41: astore_1
    //   42: aload_1
    //   43: athrow
    //   44: goto -32 -> 12
    //   47: iload_2
    //   48: tableswitch	default:+24->72, 0:+55->103, 1:+-16->32
    //   72: goto +31 -> 103
    //   75: iload_2
    //   76: tableswitch	default:+24->100, 0:+149->225, 1:+95->171
    //   100: goto +125 -> 225
    //   103: getstatic 23	o/ᓵ:ˋ	I
    //   106: bipush 51
    //   108: iadd
    //   109: istore_2
    //   110: iload_2
    //   111: sipush 128
    //   114: irem
    //   115: putstatic 25	o/ᓵ:ˎ	I
    //   118: iload_2
    //   119: iconst_2
    //   120: irem
    //   121: ifne +6 -> 127
    //   124: goto -80 -> 44
    //   127: goto -115 -> 12
    //   130: bipush 60
    //   132: istore_2
    //   133: goto +52 -> 185
    //   136: getstatic 23	o/ᓵ:ˋ	I
    //   139: istore_2
    //   140: iload_2
    //   141: bipush 65
    //   143: iadd
    //   144: istore_2
    //   145: iload_2
    //   146: sipush 128
    //   149: irem
    //   150: putstatic 25	o/ᓵ:ˎ	I
    //   153: iload_2
    //   154: iconst_2
    //   155: irem
    //   156: ifne +6 -> 162
    //   159: goto +56 -> 215
    //   162: goto +4 -> 166
    //   165: return
    //   166: iconst_0
    //   167: istore_2
    //   168: goto -93 -> 75
    //   171: getstatic 282	android/os/Build$VERSION:SDK_INT	I
    //   174: bipush 14
    //   176: if_icmplt +6 -> 182
    //   179: goto -143 -> 36
    //   182: goto +38 -> 220
    //   185: iload_2
    //   186: lookupswitch	default:+26->212, 60:+-83->103, 79:+-154->32
    //   212: goto -109 -> 103
    //   215: iconst_1
    //   216: istore_2
    //   217: goto -142 -> 75
    //   220: iconst_1
    //   221: istore_2
    //   222: goto -175 -> 47
    //   225: getstatic 282	android/os/Build$VERSION:SDK_INT	I
    //   228: bipush 19
    //   230: if_icmplt +6 -> 236
    //   233: goto -103 -> 130
    //   236: goto -230 -> 6
    // Local variable table:
    //   start	length	slot	name	signature
    //   0	239	0	this	ᓵ
    //   0	239	1	paramObject	Object
    //   8	214	2	i	int
    // Exception table:
    //   from	to	target	type
    //   136	140	3	java/lang/Exception
    //   145	153	41	java/lang/Exception
  }
  
  /* Error */
  public void ˎ(boolean paramBoolean)
  {
    // Byte code:
    //   0: goto +124 -> 124
    //   3: getstatic 23	o/ᓵ:ˋ	I
    //   6: bipush 91
    //   8: iadd
    //   9: istore_2
    //   10: iload_2
    //   11: sipush 128
    //   14: irem
    //   15: putstatic 25	o/ᓵ:ˎ	I
    //   18: iload_2
    //   19: iconst_2
    //   20: irem
    //   21: ifne +6 -> 27
    //   24: goto +94 -> 118
    //   27: bipush 20
    //   29: istore_2
    //   30: goto +56 -> 86
    //   33: aload_0
    //   34: getfield 54	o/ᓵ:ॱ	Landroid/view/accessibility/AccessibilityNodeInfo;
    //   37: iload_1
    //   38: invokevirtual 367	android/view/accessibility/AccessibilityNodeInfo:setFocused	(Z)V
    //   41: new 111	java/lang/NullPointerException
    //   44: dup
    //   45: invokespecial 112	java/lang/NullPointerException:<init>	()V
    //   48: athrow
    //   49: getstatic 25	o/ᓵ:ˎ	I
    //   52: bipush 113
    //   54: iadd
    //   55: istore_2
    //   56: iload_2
    //   57: sipush 128
    //   60: irem
    //   61: putstatic 23	o/ᓵ:ˋ	I
    //   64: iload_2
    //   65: iconst_2
    //   66: irem
    //   67: ifeq +6 -> 73
    //   70: goto +4 -> 74
    //   73: return
    //   74: return
    //   75: aload_0
    //   76: getfield 54	o/ᓵ:ॱ	Landroid/view/accessibility/AccessibilityNodeInfo;
    //   79: iload_1
    //   80: invokevirtual 367	android/view/accessibility/AccessibilityNodeInfo:setFocused	(Z)V
    //   83: goto -34 -> 49
    //   86: iload_2
    //   87: lookupswitch	default:+25->112, 20:+-12->75, 84:+-54->33
    //   112: goto -37 -> 75
    //   115: astore_3
    //   116: aload_3
    //   117: athrow
    //   118: bipush 84
    //   120: istore_2
    //   121: goto -35 -> 86
    //   124: goto -121 -> 3
    //   127: astore_3
    //   128: aload_3
    //   129: athrow
    // Local variable table:
    //   start	length	slot	name	signature
    //   0	130	0	this	ᓵ
    //   0	130	1	paramBoolean	boolean
    //   9	112	2	i	int
    //   115	2	3	localException1	Exception
    //   127	2	3	localException2	Exception
    // Exception table:
    //   from	to	target	type
    //   3	10	115	java/lang/Exception
    //   10	18	115	java/lang/Exception
    //   10	18	127	java/lang/Exception
  }
  
  /* Error */
  public boolean ˎ()
  {
    // Byte code:
    //   0: goto +169 -> 169
    //   3: iconst_1
    //   4: istore_1
    //   5: goto +25 -> 30
    //   8: astore_3
    //   9: aload_3
    //   10: athrow
    //   11: aload_0
    //   12: getfield 54	o/ᓵ:ॱ	Landroid/view/accessibility/AccessibilityNodeInfo;
    //   15: invokevirtual 370	android/view/accessibility/AccessibilityNodeInfo:isCheckable	()Z
    //   18: istore_2
    //   19: goto +119 -> 138
    //   22: bipush 63
    //   24: istore_1
    //   25: goto +55 -> 80
    //   28: iload_2
    //   29: ireturn
    //   30: iload_1
    //   31: tableswitch	default:+21->52, 0:+-3->28, 1:+141->172
    //   52: goto +120 -> 172
    //   55: aload_0
    //   56: getfield 54	o/ᓵ:ॱ	Landroid/view/accessibility/AccessibilityNodeInfo;
    //   59: invokevirtual 370	android/view/accessibility/AccessibilityNodeInfo:isCheckable	()Z
    //   62: istore_2
    //   63: new 111	java/lang/NullPointerException
    //   66: dup
    //   67: invokespecial 112	java/lang/NullPointerException:<init>	()V
    //   70: athrow
    //   71: bipush 72
    //   73: istore_1
    //   74: goto +6 -> 80
    //   77: astore_3
    //   78: aload_3
    //   79: athrow
    //   80: iload_1
    //   81: lookupswitch	default:+27->108, 63:+-70->11, 72:+-26->55
    //   108: goto -53 -> 55
    //   111: getstatic 23	o/ᓵ:ˋ	I
    //   114: bipush 79
    //   116: iadd
    //   117: istore_1
    //   118: iload_1
    //   119: sipush 128
    //   122: irem
    //   123: putstatic 25	o/ᓵ:ˎ	I
    //   126: iload_1
    //   127: iconst_2
    //   128: irem
    //   129: ifne +6 -> 135
    //   132: goto -61 -> 71
    //   135: goto -113 -> 22
    //   138: getstatic 25	o/ᓵ:ˎ	I
    //   141: istore_1
    //   142: iload_1
    //   143: bipush 29
    //   145: iadd
    //   146: istore_1
    //   147: iload_1
    //   148: sipush 128
    //   151: irem
    //   152: putstatic 23	o/ᓵ:ˋ	I
    //   155: iload_1
    //   156: iconst_2
    //   157: irem
    //   158: ifeq +6 -> 164
    //   161: goto -158 -> 3
    //   164: iconst_0
    //   165: istore_1
    //   166: goto -136 -> 30
    //   169: goto -58 -> 111
    //   172: bipush 74
    //   174: iconst_0
    //   175: idiv
    //   176: istore_1
    //   177: iload_2
    //   178: ireturn
    // Local variable table:
    //   start	length	slot	name	signature
    //   0	179	0	this	ᓵ
    //   4	173	1	i	int
    //   18	160	2	bool	boolean
    //   8	2	3	localException1	Exception
    //   77	2	3	localException2	Exception
    // Exception table:
    //   from	to	target	type
    //   147	155	8	java/lang/Exception
    //   138	142	77	java/lang/Exception
  }
  
  /* Error */
  public AccessibilityNodeInfo ˏ()
  {
    // Byte code:
    //   0: goto +25 -> 25
    //   3: bipush 50
    //   5: istore_1
    //   6: goto +49 -> 55
    //   9: bipush 22
    //   11: istore_1
    //   12: goto +43 -> 55
    //   15: astore_2
    //   16: aload_2
    //   17: athrow
    //   18: aload_0
    //   19: getfield 54	o/ᓵ:ॱ	Landroid/view/accessibility/AccessibilityNodeInfo;
    //   22: astore_2
    //   23: aload_2
    //   24: areturn
    //   25: goto +3 -> 28
    //   28: getstatic 25	o/ᓵ:ˎ	I
    //   31: bipush 13
    //   33: iadd
    //   34: istore_1
    //   35: iload_1
    //   36: sipush 128
    //   39: irem
    //   40: putstatic 23	o/ᓵ:ˋ	I
    //   43: iload_1
    //   44: iconst_2
    //   45: irem
    //   46: ifeq +6 -> 52
    //   49: goto -46 -> 3
    //   52: goto -43 -> 9
    //   55: iload_1
    //   56: lookupswitch	default:+28->84, 22:+-38->18, 50:+31->87
    //   84: goto -66 -> 18
    //   87: aload_0
    //   88: getfield 54	o/ᓵ:ॱ	Landroid/view/accessibility/AccessibilityNodeInfo;
    //   91: astore_2
    //   92: bipush 76
    //   94: iconst_0
    //   95: idiv
    //   96: istore_1
    //   97: aload_2
    //   98: areturn
    // Local variable table:
    //   start	length	slot	name	signature
    //   0	99	0	this	ᓵ
    //   5	92	1	i	int
    //   15	2	2	localException	Exception
    //   22	76	2	localAccessibilityNodeInfo	AccessibilityNodeInfo
    // Exception table:
    //   from	to	target	type
    //   18	23	15	java/lang/Exception
  }
  
  public void ˏ(Rect paramRect)
  {
    break label142;
    int i = ˋ + 69;
    ˎ = i % 128;
    if (i % 2 != 0) {
      break label88;
    }
    for (;;)
    {
      i = 29 / 0;
      return;
      do
      {
        i = 21;
        try
        {
          AccessibilityNodeInfo localAccessibilityNodeInfo = this.ॱ;
          localAccessibilityNodeInfo.setBoundsInScreen(paramRect);
        }
        catch (Exception paramRect)
        {
          throw paramRect;
        }
        i = 1;
        break label151;
        return;
        i = ˋ + 115;
        ˎ = i % 128;
      } while (i % 2 == 0);
      break label145;
      label88:
      i = 0;
      break label151;
      for (;;)
      {
        switch (i)
        {
        case 55: 
        default: 
          break;
        }
        this.ॱ.setBoundsInScreen(paramRect);
        throw new NullPointerException();
        label142:
        break;
        label145:
        i = 55;
      }
      label151:
      switch (i)
      {
      }
    }
  }
  
  /* Error */
  public void ˏ(View paramView)
  {
    // Byte code:
    //   0: goto +151 -> 151
    //   3: getstatic 282	android/os/Build$VERSION:SDK_INT	I
    //   6: bipush 113
    //   8: if_icmplt +6 -> 14
    //   11: goto +9 -> 20
    //   14: goto +63 -> 77
    //   17: astore_1
    //   18: aload_1
    //   19: athrow
    //   20: getstatic 25	o/ᓵ:ˎ	I
    //   23: bipush 93
    //   25: iadd
    //   26: istore_2
    //   27: iload_2
    //   28: sipush 128
    //   31: irem
    //   32: putstatic 23	o/ᓵ:ˋ	I
    //   35: iload_2
    //   36: iconst_2
    //   37: irem
    //   38: ifeq +6 -> 44
    //   41: goto +150 -> 191
    //   44: goto +102 -> 146
    //   47: getstatic 25	o/ᓵ:ˎ	I
    //   50: bipush 13
    //   52: iadd
    //   53: istore_2
    //   54: iload_2
    //   55: sipush 128
    //   58: irem
    //   59: putstatic 23	o/ᓵ:ˋ	I
    //   62: iload_2
    //   63: iconst_2
    //   64: irem
    //   65: ifeq +6 -> 71
    //   68: goto +39 -> 107
    //   71: goto +53 -> 124
    //   74: astore_1
    //   75: aload_1
    //   76: athrow
    //   77: return
    //   78: iload_2
    //   79: lookupswitch	default:+25->104, 34:+-76->3, 61:+100->179
    //   104: goto -101 -> 3
    //   107: bipush 34
    //   109: istore_2
    //   110: goto -32 -> 78
    //   113: aload_0
    //   114: getfield 54	o/ᓵ:ॱ	Landroid/view/accessibility/AccessibilityNodeInfo;
    //   117: astore_3
    //   118: aload_3
    //   119: aload_1
    //   120: invokevirtual 377	android/view/accessibility/AccessibilityNodeInfo:setLabelFor	(Landroid/view/View;)V
    //   123: return
    //   124: bipush 61
    //   126: istore_2
    //   127: goto -49 -> 78
    //   130: aload_0
    //   131: getfield 54	o/ᓵ:ॱ	Landroid/view/accessibility/AccessibilityNodeInfo;
    //   134: aload_1
    //   135: invokevirtual 377	android/view/accessibility/AccessibilityNodeInfo:setLabelFor	(Landroid/view/View;)V
    //   138: new 111	java/lang/NullPointerException
    //   141: dup
    //   142: invokespecial 112	java/lang/NullPointerException:<init>	()V
    //   145: athrow
    //   146: iconst_0
    //   147: istore_2
    //   148: goto +6 -> 154
    //   151: goto -104 -> 47
    //   154: iload_2
    //   155: tableswitch	default:+21->176, 0:+-42->113, 1:+-25->130
    //   176: goto -46 -> 130
    //   179: getstatic 282	android/os/Build$VERSION:SDK_INT	I
    //   182: bipush 17
    //   184: if_icmplt +6 -> 190
    //   187: goto -167 -> 20
    //   190: return
    //   191: iconst_1
    //   192: istore_2
    //   193: goto -39 -> 154
    // Local variable table:
    //   start	length	slot	name	signature
    //   0	196	0	this	ᓵ
    //   0	196	1	paramView	View
    //   26	167	2	i	int
    //   117	2	3	localAccessibilityNodeInfo	AccessibilityNodeInfo
    // Exception table:
    //   from	to	target	type
    //   118	123	17	java/lang/Exception
    //   113	118	74	java/lang/Exception
    //   118	123	74	java/lang/Exception
  }
  
  public void ˏ(CharSequence paramCharSequence)
  {
    for (;;)
    {
      int i = 1;
      break label10;
      label8:
      i = 0;
      switch (i)
      {
      default: 
        break;
      case 1: 
        label10:
        return;
      }
      for (;;)
      {
        this.ॱ.setContentDescription(paramCharSequence);
        break;
        do
        {
          break;
          i = null.length;
          return;
          i = ˎ + 105;
          ˋ = i % 128;
        } while (i % 2 != 0);
      }
      try
      {
        i = ˋ;
        i += 27;
        try
        {
          ˎ = i % 128;
          if (i % 2 == 0) {
            break label8;
          }
        }
        catch (Exception paramCharSequence)
        {
          throw paramCharSequence;
        }
      }
      catch (Exception paramCharSequence)
      {
        throw paramCharSequence;
      }
    }
  }
  
  public void ˏ(Object paramObject)
  {
    break label150;
    int i;
    for (;;)
    {
      i = 72;
      break;
      i = ˎ + 47;
      ˋ = i % 128;
      if (i % 2 == 0)
      {
        i = 6;
        break label203;
        i = ˋ + 63;
        ˎ = i % 128;
        if (i % 2 != 0) {
          break label132;
        }
      }
    }
    for (;;)
    {
      label66:
      break;
      return;
      label70:
      i = 67;
      break label153;
      for (;;)
      {
        switch (i)
        {
        default: 
          break label235;
          try
          {
            label107:
            i = Build.VERSION.SDK_INT;
            if (i >= 19) {
              break label70;
            }
          }
          catch (Exception paramObject)
          {
            throw paramObject;
          }
          i = 90;
          break label203;
          label132:
          i = 14;
        }
      }
      for (;;)
      {
        i = 83 / 0;
        return;
        i = 95;
        break label153;
        label150:
        break label107;
        label153:
        switch (i)
        {
        }
        break;
        this.ॱ.setCollectionInfo((AccessibilityNodeInfo.CollectionInfo)((ˋ)paramObject).ˋ);
        break label66;
        label203:
        switch (i)
        {
        }
      }
      label235:
      this.ॱ.setCollectionInfo((AccessibilityNodeInfo.CollectionInfo)((ˋ)paramObject).ˋ);
      i = null.length;
    }
  }
  
  public void ˏ(boolean paramBoolean)
  {
    break label110;
    int i = null.length;
    return;
    return;
    try
    {
      i = ˋ;
      i += 89;
      for (;;)
      {
        try
        {
          ˎ = i % 128;
          if (i % 2 != 0)
          {
            continue;
            switch (i)
            {
            }
            return;
            i = 88;
            continue;
            i = ˎ + 93;
            ˋ = i % 128;
            if (i % 2 != 0) {
              break;
            }
          }
        }
        catch (Exception localException1)
        {
          throw localException1;
        }
        i = 30;
      }
    }
    catch (Exception localException2)
    {
      throw localException2;
    }
    for (;;)
    {
      label110:
      this.ॱ.setFocusable(paramBoolean);
      break;
    }
  }
  
  public boolean ˏॱ()
  {
    break label66;
    return this.ॱ.isPassword();
    for (;;)
    {
      int i;
      switch (i)
      {
      case 0: 
      default: 
        break;
        for (;;)
        {
          i = ˎ + 25;
          ˋ = i % 128;
          if (i % 2 != 0) {
            break;
          }
          break label87;
        }
        i = 1;
        break;
      case 1: 
        label66:
        boolean bool = this.ॱ.isPassword();
        i = null.length;
        return bool;
        label87:
        i = 0;
      }
    }
  }
  
  public CharSequence ͺ()
  {
    for (;;)
    {
      Object localObject = this.ॱ.getPackageName();
      int i = 13 / 0;
      return localObject;
      try
      {
        localObject = this.ॱ;
        localObject = ((AccessibilityNodeInfo)localObject).getPackageName();
        return localObject;
      }
      catch (Exception localException1)
      {
        throw localException1;
      }
      label33:
      i = 19;
      try
      {
        i = ˎ;
        i += 107;
        ˋ = i % 128;
        if (i % 2 != 0) {
          break label33;
        }
        i = 63;
        switch (i)
        {
        }
      }
      catch (Exception localException2)
      {
        throw localException2;
      }
    }
  }
  
  public void ͺ(boolean paramBoolean)
  {
    break label130;
    label6:
    label101:
    label130:
    for (;;)
    {
      int i = ˋ + 77;
      ˎ = i % 128;
      if (i % 2 == 0) {
        break label6;
      }
      break label101;
      for (;;)
      {
        i = ˋ + 117;
        ˎ = i % 128;
        if (i % 2 == 0) {
          break;
        }
        break;
        switch (i)
        {
        }
      }
      for (;;)
      {
        return;
        do
        {
          i = 3;
          break;
        } while (Build.VERSION.SDK_INT >= 19);
        i = 26;
        break;
        return;
        this.ॱ.setCanOpenPopup(paramBoolean);
      }
    }
  }
  
  /* Error */
  public int ॱ()
  {
    // Byte code:
    //   0: goto +124 -> 124
    //   3: astore_3
    //   4: aload_3
    //   5: athrow
    //   6: getstatic 25	o/ᓵ:ˎ	I
    //   9: bipush 107
    //   11: iadd
    //   12: istore_1
    //   13: iload_1
    //   14: sipush 128
    //   17: irem
    //   18: putstatic 23	o/ᓵ:ˋ	I
    //   21: iload_1
    //   22: iconst_2
    //   23: irem
    //   24: ifeq +6 -> 30
    //   27: goto +52 -> 79
    //   30: goto +99 -> 129
    //   33: aload_0
    //   34: getfield 54	o/ᓵ:ॱ	Landroid/view/accessibility/AccessibilityNodeInfo;
    //   37: invokevirtual 403	android/view/accessibility/AccessibilityNodeInfo:getActions	()I
    //   40: istore_1
    //   41: bipush 81
    //   43: iconst_0
    //   44: idiv
    //   45: istore_2
    //   46: goto +39 -> 85
    //   49: iload_1
    //   50: lookupswitch	default:+26->76, 35:+-17->33, 65:+61->111
    //   76: goto +35 -> 111
    //   79: bipush 35
    //   81: istore_1
    //   82: goto -33 -> 49
    //   85: getstatic 23	o/ᓵ:ˋ	I
    //   88: bipush 113
    //   90: iadd
    //   91: istore_2
    //   92: iload_2
    //   93: sipush 128
    //   96: irem
    //   97: putstatic 25	o/ᓵ:ˎ	I
    //   100: iload_2
    //   101: iconst_2
    //   102: irem
    //   103: ifne +6 -> 109
    //   106: goto +21 -> 127
    //   109: iload_1
    //   110: ireturn
    //   111: aload_0
    //   112: getfield 54	o/ᓵ:ॱ	Landroid/view/accessibility/AccessibilityNodeInfo;
    //   115: astore_3
    //   116: aload_3
    //   117: invokevirtual 403	android/view/accessibility/AccessibilityNodeInfo:getActions	()I
    //   120: istore_1
    //   121: goto -36 -> 85
    //   124: goto -118 -> 6
    //   127: iload_1
    //   128: ireturn
    //   129: bipush 65
    //   131: istore_1
    //   132: goto -83 -> 49
    // Local variable table:
    //   start	length	slot	name	signature
    //   0	135	0	this	ᓵ
    //   12	120	1	i	int
    //   45	58	2	j	int
    //   3	2	3	localException	Exception
    //   115	2	3	localAccessibilityNodeInfo	AccessibilityNodeInfo
    // Exception table:
    //   from	to	target	type
    //   111	116	3	java/lang/Exception
    //   116	121	3	java/lang/Exception
  }
  
  public void ॱ(int paramInt)
  {
    break label55;
    this.ॱ.addAction(paramInt);
    throw new NullPointerException();
    label22:
    int i = 0;
    for (;;)
    {
      i = 1;
      switch (i)
      {
      case 0: 
      default: 
        break label82;
        label55:
        i = ˎ + 123;
        ˋ = i % 128;
        if (i % 2 != 0) {
          break label22;
        }
      }
    }
    label82:
    this.ॱ.addAction(paramInt);
  }
  
  public void ॱ(Rect paramRect)
  {
    for (;;)
    {
      int i;
      try
      {
        localAccessibilityNodeInfo = this.ॱ;
      }
      catch (Exception paramRect)
      {
        AccessibilityNodeInfo localAccessibilityNodeInfo;
        throw paramRect;
      }
      try
      {
        localAccessibilityNodeInfo.setBoundsInParent(paramRect);
        return;
      }
      catch (Exception paramRect)
      {
        throw paramRect;
      }
      switch (i)
      {
      case 22: 
      default: 
        break;
      case 59: 
        this.ॱ.setBoundsInParent(paramRect);
        i = null.length;
        return;
        i = ˋ + 57;
        ˎ = i % 128;
        if (i % 2 != 0) {
          i = 22;
        } else {
          i = 59;
        }
        break;
      }
    }
  }
  
  public void ॱ(View paramView)
  {
    break label57;
    this.ॱ.setParent(paramView);
    throw new NullPointerException();
    for (;;)
    {
      try
      {
        localAccessibilityNodeInfo = this.ॱ;
      }
      catch (Exception paramView)
      {
        AccessibilityNodeInfo localAccessibilityNodeInfo;
        label57:
        throw paramView;
      }
      try
      {
        localAccessibilityNodeInfo.setParent(paramView);
        i = ˋ;
        i += 21;
        ˎ = i % 128;
        if (i % 2 != 0) {
          return;
        }
        return;
      }
      catch (Exception paramView)
      {
        throw paramView;
      }
      int i = ˎ + 63;
      ˋ = i % 128;
      if (i % 2 == 0) {
        i = 52;
      } else {
        i = 79;
      }
      switch (i)
      {
      }
    }
  }
  
  public void ॱ(CharSequence paramCharSequence)
  {
    for (;;)
    {
      switch (i)
      {
      default: 
        return;
      }
      for (;;)
      {
        i = ˎ + 121;
        ˋ = i % 128;
        if (i % 2 != 0) {
          break label104;
        }
        i = 1;
        break;
        break label69;
        return;
        label69:
        do
        {
          break;
          i = null.length;
          return;
          i = ˋ + 67;
          ˎ = i % 128;
        } while (i % 2 == 0);
        this.ॱ.setClassName(paramCharSequence);
      }
      label104:
      int i = 0;
    }
  }
  
  /* Error */
  public void ॱ(boolean paramBoolean)
  {
    // Byte code:
    //   0: goto +42 -> 42
    //   3: iconst_0
    //   4: istore_2
    //   5: goto +40 -> 45
    //   8: aload_0
    //   9: getfield 54	o/ᓵ:ॱ	Landroid/view/accessibility/AccessibilityNodeInfo;
    //   12: astore_3
    //   13: aload_3
    //   14: iload_1
    //   15: invokevirtual 419	android/view/accessibility/AccessibilityNodeInfo:setChecked	(Z)V
    //   18: goto +53 -> 71
    //   21: astore_3
    //   22: aload_3
    //   23: athrow
    //   24: aload_0
    //   25: getfield 54	o/ᓵ:ॱ	Landroid/view/accessibility/AccessibilityNodeInfo;
    //   28: astore_3
    //   29: aload_3
    //   30: iload_1
    //   31: invokevirtual 419	android/view/accessibility/AccessibilityNodeInfo:setChecked	(Z)V
    //   34: new 111	java/lang/NullPointerException
    //   37: dup
    //   38: invokespecial 112	java/lang/NullPointerException:<init>	()V
    //   41: athrow
    //   42: goto +60 -> 102
    //   45: iload_2
    //   46: tableswitch	default:+22->68, 0:+-38->8, 1:+-22->24
    //   68: goto -44 -> 24
    //   71: getstatic 25	o/ᓵ:ˎ	I
    //   74: bipush 79
    //   76: iadd
    //   77: istore_2
    //   78: iload_2
    //   79: sipush 128
    //   82: irem
    //   83: putstatic 23	o/ᓵ:ˋ	I
    //   86: iload_2
    //   87: iconst_2
    //   88: irem
    //   89: ifeq +6 -> 95
    //   92: goto +4 -> 96
    //   95: return
    //   96: return
    //   97: iconst_1
    //   98: istore_2
    //   99: goto -54 -> 45
    //   102: getstatic 25	o/ᓵ:ˎ	I
    //   105: iconst_1
    //   106: iadd
    //   107: istore_2
    //   108: iload_2
    //   109: sipush 128
    //   112: irem
    //   113: putstatic 23	o/ᓵ:ˋ	I
    //   116: iload_2
    //   117: iconst_2
    //   118: irem
    //   119: ifeq +6 -> 125
    //   122: goto -25 -> 97
    //   125: goto -122 -> 3
    //   128: astore_3
    //   129: aload_3
    //   130: athrow
    // Local variable table:
    //   start	length	slot	name	signature
    //   0	131	0	this	ᓵ
    //   0	131	1	paramBoolean	boolean
    //   4	115	2	i	int
    //   12	2	3	localAccessibilityNodeInfo1	AccessibilityNodeInfo
    //   21	2	3	localException1	Exception
    //   28	2	3	localAccessibilityNodeInfo2	AccessibilityNodeInfo
    //   128	2	3	localException2	Exception
    // Exception table:
    //   from	to	target	type
    //   24	29	21	java/lang/Exception
    //   29	42	21	java/lang/Exception
    //   8	13	128	java/lang/Exception
    //   13	18	128	java/lang/Exception
  }
  
  public boolean ॱ(if paramIf)
  {
    break label110;
    int i = 75;
    switch (i)
    {
    default: 
      break;
      for (;;)
      {
        try
        {
          AccessibilityNodeInfo localAccessibilityNodeInfo = this.ॱ;
          paramIf = paramIf.ˋᐝ;
          paramIf = (AccessibilityNodeInfo.AccessibilityAction)paramIf;
          try
          {
            boolean bool = localAccessibilityNodeInfo.removeAction(paramIf);
            return bool;
          }
          catch (Exception paramIf)
          {
            throw paramIf;
          }
          this.ॱ.removeAction((AccessibilityNodeInfo.AccessibilityAction)paramIf.ˋᐝ);
          throw new NullPointerException();
        }
        catch (Exception paramIf)
        {
          throw paramIf;
        }
        i = ˎ + 39;
        ˋ = i % 128;
        if (i % 2 != 0) {
          continue;
        }
        break label198;
      }
    case 75: 
      label6:
      label35:
      label60:
      label110:
      label198:
      label204:
      label210:
      do
      {
        i = ˎ + 37;
        ˋ = i % 128;
        if (i % 2 != 0) {
          break label60;
        }
        break label35;
        if (Build.VERSION.SDK_INT >= 21) {
          break;
        }
        break label204;
        i = 90;
        for (;;)
        {
          switch (i)
          {
          case 40: 
          default: 
            break label210;
            i = 40;
          }
        }
        i = 98;
        break label6;
      } while (Build.VERSION.SDK_INT >= 34);
    }
    return false;
  }
  
  /* Error */
  public boolean ॱˊ()
  {
    // Byte code:
    //   0: goto +64 -> 64
    //   3: getstatic 23	o/ᓵ:ˋ	I
    //   6: bipush 117
    //   8: iadd
    //   9: istore_1
    //   10: iload_1
    //   11: sipush 128
    //   14: irem
    //   15: putstatic 25	o/ᓵ:ˎ	I
    //   18: iload_1
    //   19: iconst_2
    //   20: irem
    //   21: ifne +6 -> 27
    //   24: goto +35 -> 59
    //   27: iload_2
    //   28: ireturn
    //   29: astore_3
    //   30: aload_3
    //   31: athrow
    //   32: getstatic 23	o/ᓵ:ˋ	I
    //   35: bipush 39
    //   37: iadd
    //   38: istore_1
    //   39: iload_1
    //   40: sipush 128
    //   43: irem
    //   44: putstatic 25	o/ᓵ:ˎ	I
    //   47: iload_1
    //   48: iconst_2
    //   49: irem
    //   50: ifne +6 -> 56
    //   53: goto +8 -> 61
    //   56: goto +11 -> 67
    //   59: iload_2
    //   60: ireturn
    //   61: goto +6 -> 67
    //   64: goto -32 -> 32
    //   67: aload_0
    //   68: getfield 54	o/ᓵ:ॱ	Landroid/view/accessibility/AccessibilityNodeInfo;
    //   71: invokevirtual 432	android/view/accessibility/AccessibilityNodeInfo:isScrollable	()Z
    //   74: istore_2
    //   75: goto -72 -> 3
    //   78: astore_3
    //   79: aload_3
    //   80: athrow
    // Local variable table:
    //   start	length	slot	name	signature
    //   0	81	0	this	ᓵ
    //   9	41	1	i	int
    //   27	48	2	bool	boolean
    //   29	2	3	localException1	Exception
    //   78	2	3	localException2	Exception
    // Exception table:
    //   from	to	target	type
    //   39	47	29	java/lang/Exception
    //   32	39	78	java/lang/Exception
    //   39	47	78	java/lang/Exception
  }
  
  public CharSequence ॱˋ()
  {
    break label89;
    int i;
    do
    {
      i = 0;
      break;
      i = ˎ + 69;
      ˋ = i % 128;
    } while (i % 2 != 0);
    break label84;
    CharSequence localCharSequence;
    return localCharSequence;
    switch (i)
    {
    case 1: 
    default: 
      break;
    }
    for (;;)
    {
      label63:
      localCharSequence = this.ॱ.getClassName();
      break;
      label84:
      label89:
      do
      {
        break label63;
        i = 28 / 0;
        return localCharSequence;
        i = 1;
        break;
        i = ˎ + 89;
        ˋ = i % 128;
      } while (i % 2 != 0);
    }
  }
  
  public CharSequence ॱˎ()
  {
    int i;
    for (;;)
    {
      i = ˎ + 57;
      ˋ = i % 128;
      if (i % 2 == 0) {
        break;
      }
      break;
    }
    for (;;)
    {
      i = ˎ + 21;
      ˋ = i % 128;
      if (i % 2 == 0)
      {
        Object localObject;
        return localObject;
        try
        {
          localObject = this.ॱ;
          localObject = ((AccessibilityNodeInfo)localObject).getText();
        }
        catch (Exception localException)
        {
          throw localException;
        }
      }
    }
    return localException;
  }
  
  public void ॱॱ(boolean paramBoolean)
  {
    break label6;
    for (;;)
    {
      label6:
      this.ॱ.setSelected(paramBoolean);
      break label47;
      i = ˋ + 21;
      ˎ = i % 128;
      if (i % 2 == 0) {
        break;
      }
    }
    label47:
    int i = ˎ + 43;
    ˋ = i % 128;
    if (i % 2 != 0) {}
  }
  
  public boolean ॱॱ()
  {
    break label72;
    int i = ˎ + 37;
    ˋ = i % 128;
    boolean bool;
    label29:
    if (i % 2 == 0) {
      return bool;
    }
    label72:
    for (;;)
    {
      i = ˋ + 51;
      ˎ = i % 128;
      if (i % 2 == 0) {
        break label29;
      }
      bool = this.ॱ.isClickable();
      break;
      return bool;
    }
  }
  
  public CharSequence ॱᐝ()
  {
    for (;;)
    {
      try
      {
        CharSequence localCharSequence = this.ॱ.getContentDescription();
        break label44;
        i = ˋ + 37;
      }
      catch (Exception localException1)
      {
        try
        {
          ˎ = i % 128;
          if (i % 2 == 0) {
            continue;
          }
        }
        catch (Exception localException2)
        {
          int i;
          throw localException2;
        }
        localException1 = localException1;
        throw localException1;
      }
      label44:
      i = ˋ + 99;
      ˎ = i % 128;
      if (i % 2 == 0) {
        return localException1;
      }
      return localException1;
    }
  }
  
  /* Error */
  public void ᐝ(boolean paramBoolean)
  {
    // Byte code:
    //   0: goto +6 -> 6
    //   3: astore_3
    //   4: aload_3
    //   5: athrow
    //   6: goto +40 -> 46
    //   9: astore_3
    //   10: aload_3
    //   11: athrow
    //   12: getstatic 23	o/ᓵ:ˋ	I
    //   15: bipush 93
    //   17: iadd
    //   18: istore_2
    //   19: iload_2
    //   20: sipush 128
    //   23: irem
    //   24: putstatic 25	o/ᓵ:ˎ	I
    //   27: iload_2
    //   28: iconst_2
    //   29: irem
    //   30: ifne +4 -> 34
    //   33: return
    //   34: return
    //   35: aload_0
    //   36: getfield 54	o/ᓵ:ॱ	Landroid/view/accessibility/AccessibilityNodeInfo;
    //   39: iload_1
    //   40: invokevirtual 450	android/view/accessibility/AccessibilityNodeInfo:setClickable	(Z)V
    //   43: goto -31 -> 12
    //   46: getstatic 23	o/ᓵ:ˋ	I
    //   49: bipush 61
    //   51: iadd
    //   52: istore_2
    //   53: iload_2
    //   54: sipush 128
    //   57: irem
    //   58: putstatic 25	o/ᓵ:ˎ	I
    //   61: iload_2
    //   62: iconst_2
    //   63: irem
    //   64: ifne +6 -> 70
    //   67: goto -32 -> 35
    //   70: goto -35 -> 35
    // Local variable table:
    //   start	length	slot	name	signature
    //   0	73	0	this	ᓵ
    //   0	73	1	paramBoolean	boolean
    //   18	46	2	i	int
    //   3	2	3	localException1	Exception
    //   9	2	3	localException2	Exception
    // Exception table:
    //   from	to	target	type
    //   12	19	3	java/lang/Exception
    //   19	27	3	java/lang/Exception
    //   19	27	9	java/lang/Exception
    //   46	53	9	java/lang/Exception
    //   53	61	9	java/lang/Exception
  }
  
  /* Error */
  public boolean ᐝ()
  {
    // Byte code:
    //   0: goto +3 -> 3
    //   3: goto +56 -> 59
    //   6: bipush 84
    //   8: istore_1
    //   9: goto +19 -> 28
    //   12: aload_0
    //   13: getfield 54	o/ᓵ:ॱ	Landroid/view/accessibility/AccessibilityNodeInfo;
    //   16: astore_3
    //   17: aload_3
    //   18: invokevirtual 453	android/view/accessibility/AccessibilityNodeInfo:isFocused	()Z
    //   21: istore_2
    //   22: goto +64 -> 86
    //   25: bipush 78
    //   27: istore_1
    //   28: iload_1
    //   29: lookupswitch	default:+27->56, 78:+82->111, 84:+-17->12
    //   56: goto -44 -> 12
    //   59: getstatic 23	o/ᓵ:ˋ	I
    //   62: bipush 73
    //   64: iadd
    //   65: istore_1
    //   66: iload_1
    //   67: sipush 128
    //   70: irem
    //   71: putstatic 25	o/ᓵ:ˎ	I
    //   74: iload_1
    //   75: iconst_2
    //   76: irem
    //   77: ifne +6 -> 83
    //   80: goto -55 -> 25
    //   83: goto -77 -> 6
    //   86: getstatic 25	o/ᓵ:ˎ	I
    //   89: bipush 53
    //   91: iadd
    //   92: istore_1
    //   93: iload_1
    //   94: sipush 128
    //   97: irem
    //   98: putstatic 23	o/ᓵ:ˋ	I
    //   101: iload_1
    //   102: iconst_2
    //   103: irem
    //   104: ifeq +5 -> 109
    //   107: iload_2
    //   108: ireturn
    //   109: iload_2
    //   110: ireturn
    //   111: aload_0
    //   112: getfield 54	o/ᓵ:ॱ	Landroid/view/accessibility/AccessibilityNodeInfo;
    //   115: invokevirtual 453	android/view/accessibility/AccessibilityNodeInfo:isFocused	()Z
    //   118: istore_2
    //   119: iconst_5
    //   120: iconst_0
    //   121: idiv
    //   122: istore_1
    //   123: goto -37 -> 86
    //   126: astore_3
    //   127: aload_3
    //   128: athrow
    // Local variable table:
    //   start	length	slot	name	signature
    //   0	129	0	this	ᓵ
    //   8	115	1	i	int
    //   21	98	2	bool	boolean
    //   16	2	3	localAccessibilityNodeInfo	AccessibilityNodeInfo
    //   126	2	3	localException	Exception
    // Exception table:
    //   from	to	target	type
    //   12	17	126	java/lang/Exception
    //   17	22	126	java/lang/Exception
  }
  
  public void ᐝॱ()
  {
    break label95;
    int i = 1;
    break label9;
    return;
    for (;;)
    {
      switch (i)
      {
      case 1: 
      default: 
        label9:
        return;
        label33:
        i = ˎ + 91;
        ˋ = i % 128;
        if (i % 2 != 0) {
          break label65;
        }
        break label102;
        label60:
        i = 0;
      }
    }
    for (;;)
    {
      label65:
      i = ˎ + 61;
      ˋ = i % 128;
      if (i % 2 != 0) {
        break label60;
      }
      break;
      label95:
      break label33;
      i = null.length;
      return;
      label102:
      this.ॱ.recycle();
    }
  }
  
  public static class if
  {
    public static final if ʻ;
    public static final if ʻॱ;
    public static final if ʼ;
    public static final if ʼॱ;
    public static final if ʽ;
    public static final if ʽॱ;
    public static final if ʾ;
    public static final if ʿ;
    public static final if ˈ;
    public static final if ˉ;
    public static final if ˊ;
    public static final if ˊˊ;
    public static final if ˊˋ;
    public static final if ˊॱ;
    public static final if ˊᐝ;
    public static final if ˋ;
    public static final if ˋˊ;
    public static final if ˋॱ;
    public static final if ˎ;
    public static final if ˏ = new if(1, null);
    public static final if ˏॱ;
    public static final if ͺ;
    public static final if ॱ = new if(2, null);
    public static final if ॱˊ;
    public static final if ॱˋ;
    public static final if ॱˎ;
    public static final if ॱॱ;
    public static final if ॱᐝ;
    public static final if ᐝ;
    public static final if ᐝॱ;
    final Object ˋᐝ;
    
    static
    {
      ˋ = new if(4, null);
      ˎ = new if(8, null);
      ˊ = new if(16, null);
      ʽ = new if(32, null);
      ॱॱ = new if(64, null);
      ᐝ = new if(128, null);
      ʻ = new if(256, null);
      ʼ = new if(512, null);
      ॱˊ = new if(1024, null);
      ˋॱ = new if(2048, null);
      ͺ = new if(4096, null);
      ˏॱ = new if(8192, null);
      ˊॱ = new if(16384, null);
      ᐝॱ = new if(32768, null);
      ॱˎ = new if(65536, null);
      ॱᐝ = new if(131072, null);
      ʻॱ = new if(262144, null);
      ॱˋ = new if(524288, null);
      ʿ = new if(1048576, null);
      ˈ = new if(2097152, null);
      AccessibilityNodeInfo.AccessibilityAction localAccessibilityAction;
      if (Build.VERSION.SDK_INT >= 23) {
        localAccessibilityAction = AccessibilityNodeInfo.AccessibilityAction.ACTION_SHOW_ON_SCREEN;
      } else {
        localAccessibilityAction = null;
      }
      ʾ = new if(localAccessibilityAction);
      if (Build.VERSION.SDK_INT >= 23) {
        localAccessibilityAction = AccessibilityNodeInfo.AccessibilityAction.ACTION_SCROLL_TO_POSITION;
      } else {
        localAccessibilityAction = null;
      }
      ʼॱ = new if(localAccessibilityAction);
      if (Build.VERSION.SDK_INT >= 23) {
        localAccessibilityAction = AccessibilityNodeInfo.AccessibilityAction.ACTION_SCROLL_UP;
      } else {
        localAccessibilityAction = null;
      }
      ʽॱ = new if(localAccessibilityAction);
      if (Build.VERSION.SDK_INT >= 23) {
        localAccessibilityAction = AccessibilityNodeInfo.AccessibilityAction.ACTION_SCROLL_LEFT;
      } else {
        localAccessibilityAction = null;
      }
      ˉ = new if(localAccessibilityAction);
      if (Build.VERSION.SDK_INT >= 23) {
        localAccessibilityAction = AccessibilityNodeInfo.AccessibilityAction.ACTION_SCROLL_DOWN;
      } else {
        localAccessibilityAction = null;
      }
      ˊᐝ = new if(localAccessibilityAction);
      if (Build.VERSION.SDK_INT >= 23) {
        localAccessibilityAction = AccessibilityNodeInfo.AccessibilityAction.ACTION_SCROLL_RIGHT;
      } else {
        localAccessibilityAction = null;
      }
      ˋˊ = new if(localAccessibilityAction);
      if (Build.VERSION.SDK_INT >= 23) {
        localAccessibilityAction = AccessibilityNodeInfo.AccessibilityAction.ACTION_CONTEXT_CLICK;
      } else {
        localAccessibilityAction = null;
      }
      ˊˊ = new if(localAccessibilityAction);
      if (Build.VERSION.SDK_INT >= 24) {
        localAccessibilityAction = AccessibilityNodeInfo.AccessibilityAction.ACTION_SET_PROGRESS;
      } else {
        localAccessibilityAction = null;
      }
      ˊˋ = new if(localAccessibilityAction);
    }
    
    public if(int paramInt, CharSequence paramCharSequence)
    {
      this(paramCharSequence);
    }
    
    if(Object paramObject)
    {
      this.ˋᐝ = paramObject;
    }
  }
  
  public static class ˊ
  {
    final Object ˎ;
    
    ˊ(Object paramObject)
    {
      this.ˎ = paramObject;
    }
    
    public static ˊ ˎ(int paramInt1, int paramInt2, int paramInt3, int paramInt4, boolean paramBoolean1, boolean paramBoolean2)
    {
      if (Build.VERSION.SDK_INT >= 21) {
        return new ˊ(AccessibilityNodeInfo.CollectionItemInfo.obtain(paramInt1, paramInt2, paramInt3, paramInt4, paramBoolean1, paramBoolean2));
      }
      if (Build.VERSION.SDK_INT >= 19) {
        return new ˊ(AccessibilityNodeInfo.CollectionItemInfo.obtain(paramInt1, paramInt2, paramInt3, paramInt4, paramBoolean1));
      }
      return new ˊ(null);
    }
    
    public int ˊ()
    {
      if (Build.VERSION.SDK_INT >= 19) {
        return ((AccessibilityNodeInfo.CollectionItemInfo)this.ˎ).getColumnIndex();
      }
      return 0;
    }
    
    public int ˋ()
    {
      if (Build.VERSION.SDK_INT >= 19) {
        return ((AccessibilityNodeInfo.CollectionItemInfo)this.ˎ).getRowIndex();
      }
      return 0;
    }
    
    public boolean ˎ()
    {
      if (Build.VERSION.SDK_INT >= 21) {
        return ((AccessibilityNodeInfo.CollectionItemInfo)this.ˎ).isSelected();
      }
      return false;
    }
    
    public int ˏ()
    {
      if (Build.VERSION.SDK_INT >= 19) {
        return ((AccessibilityNodeInfo.CollectionItemInfo)this.ˎ).getRowSpan();
      }
      return 0;
    }
    
    public int ॱ()
    {
      if (Build.VERSION.SDK_INT >= 19) {
        return ((AccessibilityNodeInfo.CollectionItemInfo)this.ˎ).getColumnSpan();
      }
      return 0;
    }
  }
  
  public static class ˋ
  {
    final Object ˋ;
    
    ˋ(Object paramObject)
    {
      this.ˋ = paramObject;
    }
    
    public static ˋ ˏ(int paramInt1, int paramInt2, boolean paramBoolean, int paramInt3)
    {
      if (Build.VERSION.SDK_INT >= 21) {
        return new ˋ(AccessibilityNodeInfo.CollectionInfo.obtain(paramInt1, paramInt2, paramBoolean, paramInt3));
      }
      if (Build.VERSION.SDK_INT >= 19) {
        return new ˋ(AccessibilityNodeInfo.CollectionInfo.obtain(paramInt1, paramInt2, paramBoolean));
      }
      return new ˋ(null);
    }
  }
}
