package o;

class 乁
  extends qG
  implements ゥ
{
  private static int ˊ = 0;
  private static int[] ˎ = { 371402226, -1465183225, -504738276, 1315075412, -159459333, -1081451336, 772605454, 1991808675, -812992824, -156467531, 1566664287, -2021067170, -1475503889, -883133208, -859986817, -590122837, -641869934, 20503899 };
  private static int ˏ = 1;
  
  public 乁(qw paramQw, String paramString1, String paramString2, rG paramRG)
  {
    super(paramQw, paramString1, paramString2, paramRG, rE.ˋ);
  }
  
  /* Error */
  private static String ˋ(int[] paramArrayOfInt, int paramInt)
  {
    // Byte code:
    //   0: goto +6 -> 6
    //   3: goto +6 -> 9
    //   6: goto +168 -> 174
    //   9: aload 4
    //   11: iconst_0
    //   12: aload_0
    //   13: iload_2
    //   14: iaload
    //   15: bipush 16
    //   17: ishr
    //   18: i2c
    //   19: castore
    //   20: aload 4
    //   22: iconst_1
    //   23: aload_0
    //   24: iload_2
    //   25: iaload
    //   26: i2c
    //   27: castore
    //   28: aload 4
    //   30: iconst_2
    //   31: aload_0
    //   32: iload_2
    //   33: iconst_1
    //   34: iadd
    //   35: iaload
    //   36: bipush 16
    //   38: ishr
    //   39: i2c
    //   40: castore
    //   41: aload 4
    //   43: iconst_3
    //   44: aload_0
    //   45: iload_2
    //   46: iconst_1
    //   47: iadd
    //   48: iaload
    //   49: i2c
    //   50: castore
    //   51: aload 4
    //   53: aload 6
    //   55: iconst_0
    //   56: invokestatic 57	o/oN:ˏ	([C[IZ)[I
    //   59: pop
    //   60: aload 5
    //   62: iload_2
    //   63: iconst_1
    //   64: ishl
    //   65: aload 4
    //   67: iconst_0
    //   68: caload
    //   69: castore
    //   70: aload 5
    //   72: iload_2
    //   73: iconst_1
    //   74: ishl
    //   75: iconst_1
    //   76: iadd
    //   77: aload 4
    //   79: iconst_1
    //   80: caload
    //   81: castore
    //   82: aload 5
    //   84: iload_2
    //   85: iconst_1
    //   86: ishl
    //   87: iconst_2
    //   88: iadd
    //   89: aload 4
    //   91: iconst_2
    //   92: caload
    //   93: castore
    //   94: aload 5
    //   96: iload_2
    //   97: iconst_1
    //   98: ishl
    //   99: iconst_3
    //   100: iadd
    //   101: aload 4
    //   103: iconst_3
    //   104: caload
    //   105: castore
    //   106: iload_2
    //   107: iconst_2
    //   108: iadd
    //   109: istore_2
    //   110: goto +12 -> 122
    //   113: bipush 27
    //   115: istore_3
    //   116: goto +133 -> 249
    //   119: goto +18 -> 137
    //   122: iload_2
    //   123: aload_0
    //   124: arraylength
    //   125: if_icmpge +6 -> 131
    //   128: goto +76 -> 204
    //   131: goto -18 -> 113
    //   134: astore_0
    //   135: aload_0
    //   136: athrow
    //   137: iconst_4
    //   138: newarray char
    //   140: astore 4
    //   142: aload_0
    //   143: arraylength
    //   144: iconst_1
    //   145: ishl
    //   146: newarray char
    //   148: astore 5
    //   150: getstatic 37	o/乁:ˎ	[I
    //   153: astore 6
    //   155: aload 6
    //   157: invokevirtual 62	[I:clone	()Ljava/lang/Object;
    //   160: astore 6
    //   162: aload 6
    //   164: checkcast 58	[I
    //   167: astore 6
    //   169: iconst_0
    //   170: istore_2
    //   171: goto -49 -> 122
    //   174: getstatic 17	o/乁:ˏ	I
    //   177: bipush 65
    //   179: iadd
    //   180: istore_2
    //   181: iload_2
    //   182: sipush 128
    //   185: irem
    //   186: putstatic 15	o/乁:ˊ	I
    //   189: iload_2
    //   190: iconst_2
    //   191: irem
    //   192: ifeq +6 -> 198
    //   195: goto -76 -> 119
    //   198: goto -61 -> 137
    //   201: astore_0
    //   202: aload_0
    //   203: athrow
    //   204: bipush 78
    //   206: istore_3
    //   207: goto +42 -> 249
    //   210: new 64	java/lang/String
    //   213: dup
    //   214: aload 5
    //   216: iconst_0
    //   217: iload_1
    //   218: invokespecial 67	java/lang/String:<init>	([CII)V
    //   221: areturn
    //   222: getstatic 17	o/乁:ˏ	I
    //   225: bipush 63
    //   227: iadd
    //   228: istore_3
    //   229: iload_3
    //   230: sipush 128
    //   233: irem
    //   234: putstatic 15	o/乁:ˊ	I
    //   237: iload_3
    //   238: iconst_2
    //   239: irem
    //   240: ifeq +6 -> 246
    //   243: goto -240 -> 3
    //   246: goto -237 -> 9
    //   249: iload_3
    //   250: lookupswitch	default:+26->276, 27:+-40->210, 78:+-28->222
    //   276: goto -54 -> 222
    // Local variable table:
    //   start	length	slot	name	signature
    //   0	279	0	paramArrayOfInt	int[]
    //   0	279	1	paramInt	int
    //   13	179	2	i	int
    //   115	135	3	j	int
    //   9	132	4	arrayOfChar1	char[]
    //   60	155	5	arrayOfChar2	char[]
    //   53	115	6	localObject	Object
    // Exception table:
    //   from	to	target	type
    //   150	155	134	java/lang/Exception
    //   155	162	134	java/lang/Exception
    //   162	169	134	java/lang/Exception
    //   174	189	134	java/lang/Exception
    //   51	60	201	java/lang/Exception
  }
  
  private rD ˋ(rD paramRD, String paramString)
  {
    paramRD.ˏ("User-Agent", "Crashlytics Android SDK/" + this.ॱ.ॱ()).ˏ("X-CRASHLYTICS-API-CLIENT-TYPE", "android").ˏ("X-CRASHLYTICS-API-CLIENT-VERSION", this.ॱ.ॱ()).ˏ("X-CRASHLYTICS-API-KEY", paramString);
    try
    {
      int i = ˏ + 113;
      ˊ = i % 128;
      if (i % 2 != 0) {
        return paramRD;
      }
      return paramRD;
    }
    catch (Exception paramRD)
    {
      throw paramRD;
    }
  }
  
  /* Error */
  private rD ˎ(rD paramRD, ﻐ paramﻐ)
  {
    // Byte code:
    //   0: goto +6 -> 6
    //   3: astore_1
    //   4: aload_1
    //   5: athrow
    //   6: goto +102 -> 108
    //   9: aload_1
    //   10: ldc 108
    //   12: aload 7
    //   14: invokevirtual 113	java/io/File:getName	()Ljava/lang/String;
    //   17: ldc 115
    //   19: aload 7
    //   21: invokevirtual 118	o/rD:ˏ	(Ljava/lang/String;Ljava/lang/String;Ljava/lang/String;Ljava/io/File;)Lo/rD;
    //   24: pop
    //   25: iload_3
    //   26: iconst_1
    //   27: iadd
    //   28: istore_3
    //   29: goto +907 -> 936
    //   32: aload_1
    //   33: ldc 120
    //   35: aload 7
    //   37: invokevirtual 113	java/io/File:getName	()Ljava/lang/String;
    //   40: ldc 115
    //   42: aload 7
    //   44: invokevirtual 118	o/rD:ˏ	(Ljava/lang/String;Ljava/lang/String;Ljava/lang/String;Ljava/io/File;)Lo/rD;
    //   47: pop
    //   48: goto +764 -> 812
    //   51: aload 7
    //   53: invokevirtual 113	java/io/File:getName	()Ljava/lang/String;
    //   56: ldc 122
    //   58: invokevirtual 126	java/lang/String:equals	(Ljava/lang/Object;)Z
    //   61: ifeq +6 -> 67
    //   64: goto -32 -> 32
    //   67: goto +126 -> 193
    //   70: aload_1
    //   71: ldc -128
    //   73: aload 7
    //   75: invokevirtual 113	java/io/File:getName	()Ljava/lang/String;
    //   78: ldc 115
    //   80: aload 7
    //   82: invokevirtual 118	o/rD:ˏ	(Ljava/lang/String;Ljava/lang/String;Ljava/lang/String;Ljava/io/File;)Lo/rD;
    //   85: pop
    //   86: goto -61 -> 25
    //   89: aload 7
    //   91: invokevirtual 113	java/io/File:getName	()Ljava/lang/String;
    //   94: ldc -126
    //   96: invokevirtual 126	java/lang/String:equals	(Ljava/lang/Object;)Z
    //   99: ifeq +6 -> 105
    //   102: goto +489 -> 591
    //   105: goto +843 -> 948
    //   108: getstatic 15	o/乁:ˊ	I
    //   111: bipush 117
    //   113: iadd
    //   114: istore_3
    //   115: iload_3
    //   116: sipush 128
    //   119: irem
    //   120: putstatic 17	o/乁:ˏ	I
    //   123: iload_3
    //   124: iconst_2
    //   125: irem
    //   126: ifne +6 -> 132
    //   129: goto +29 -> 158
    //   132: goto +102 -> 234
    //   135: aload_1
    //   136: ldc -124
    //   138: aload 7
    //   140: invokevirtual 113	java/io/File:getName	()Ljava/lang/String;
    //   143: ldc 115
    //   145: aload 7
    //   147: invokevirtual 118	o/rD:ˏ	(Ljava/lang/String;Ljava/lang/String;Ljava/lang/String;Ljava/io/File;)Lo/rD;
    //   150: pop
    //   151: aconst_null
    //   152: arraylength
    //   153: istore 5
    //   155: goto -130 -> 25
    //   158: aload_1
    //   159: ldc -122
    //   161: aload_2
    //   162: invokeinterface 138 1 0
    //   167: invokevirtual 140	o/rD:ˋ	(Ljava/lang/String;Ljava/lang/String;)Lo/rD;
    //   170: pop
    //   171: aload_2
    //   172: invokeinterface 143 1 0
    //   177: astore_2
    //   178: aload_2
    //   179: arraylength
    //   180: istore 4
    //   182: iconst_1
    //   183: istore_3
    //   184: goto +752 -> 936
    //   187: iconst_0
    //   188: istore 5
    //   190: goto +170 -> 360
    //   193: aload 7
    //   195: invokevirtual 113	java/io/File:getName	()Ljava/lang/String;
    //   198: ldc -111
    //   200: invokevirtual 126	java/lang/String:equals	(Ljava/lang/Object;)Z
    //   203: ifeq +6 -> 209
    //   206: goto -19 -> 187
    //   209: goto +833 -> 1042
    //   212: aload 7
    //   214: invokevirtual 113	java/io/File:getName	()Ljava/lang/String;
    //   217: ldc -109
    //   219: invokevirtual 126	java/lang/String:equals	(Ljava/lang/Object;)Z
    //   222: ifeq +6 -> 228
    //   225: goto +429 -> 654
    //   228: goto +795 -> 1023
    //   231: goto -206 -> 25
    //   234: aload_1
    //   235: ldc -122
    //   237: aload_2
    //   238: invokeinterface 138 1 0
    //   243: invokevirtual 140	o/rD:ˋ	(Ljava/lang/String;Ljava/lang/String;)Lo/rD;
    //   246: pop
    //   247: aload_2
    //   248: invokeinterface 143 1 0
    //   253: astore_2
    //   254: aload_2
    //   255: arraylength
    //   256: istore 4
    //   258: iconst_0
    //   259: istore_3
    //   260: goto +676 -> 936
    //   263: goto -238 -> 25
    //   266: goto -241 -> 25
    //   269: iconst_1
    //   270: istore 5
    //   272: goto +115 -> 387
    //   275: aload_1
    //   276: areturn
    //   277: getstatic 15	o/乁:ˊ	I
    //   280: istore 5
    //   282: iload 5
    //   284: bipush 51
    //   286: iadd
    //   287: istore 5
    //   289: iload 5
    //   291: sipush 128
    //   294: irem
    //   295: putstatic 17	o/乁:ˏ	I
    //   298: iload 5
    //   300: iconst_2
    //   301: irem
    //   302: ifne +6 -> 308
    //   305: goto +501 -> 806
    //   308: goto +167 -> 475
    //   311: aload_1
    //   312: ldc -107
    //   314: aload 7
    //   316: invokevirtual 113	java/io/File:getName	()Ljava/lang/String;
    //   319: ldc 115
    //   321: aload 7
    //   323: invokevirtual 118	o/rD:ˏ	(Ljava/lang/String;Ljava/lang/String;Ljava/lang/String;Ljava/io/File;)Lo/rD;
    //   326: pop
    //   327: goto +666 -> 993
    //   330: getstatic 15	o/乁:ˊ	I
    //   333: bipush 17
    //   335: iadd
    //   336: istore 5
    //   338: iload 5
    //   340: sipush 128
    //   343: irem
    //   344: putstatic 17	o/乁:ˏ	I
    //   347: iload 5
    //   349: iconst_2
    //   350: irem
    //   351: ifne +6 -> 357
    //   354: goto +205 -> 559
    //   357: goto -287 -> 70
    //   360: iload 5
    //   362: tableswitch	default:+22->384, 0:+-51->311, 1:+549->911
    //   384: goto -73 -> 311
    //   387: iload 5
    //   389: tableswitch	default:+23->412, 0:+-380->9, 1:+478->867
    //   412: goto -403 -> 9
    //   415: goto +652 -> 1067
    //   418: getstatic 15	o/乁:ˊ	I
    //   421: bipush 101
    //   423: iadd
    //   424: istore 5
    //   426: iload 5
    //   428: sipush 128
    //   431: irem
    //   432: putstatic 17	o/乁:ˏ	I
    //   435: iload 5
    //   437: iconst_2
    //   438: irem
    //   439: ifne +6 -> 445
    //   442: goto -27 -> 415
    //   445: goto +622 -> 1067
    //   448: iload 5
    //   450: tableswitch	default:+22->472, 0:+598->1048, 1:+90->540
    //   472: goto +68 -> 540
    //   475: aload_1
    //   476: bipush 6
    //   478: newarray int
    //   480: dup
    //   481: iconst_0
    //   482: ldc -106
    //   484: iastore
    //   485: dup
    //   486: iconst_1
    //   487: ldc -105
    //   489: iastore
    //   490: dup
    //   491: iconst_2
    //   492: ldc -104
    //   494: iastore
    //   495: dup
    //   496: iconst_3
    //   497: ldc -103
    //   499: iastore
    //   500: dup
    //   501: iconst_4
    //   502: ldc -102
    //   504: iastore
    //   505: dup
    //   506: iconst_5
    //   507: ldc -101
    //   509: iastore
    //   510: bipush 9
    //   512: invokestatic 157	o/乁:ˋ	([II)Ljava/lang/String;
    //   515: invokevirtual 160	java/lang/String:intern	()Ljava/lang/String;
    //   518: aload 7
    //   520: invokevirtual 113	java/io/File:getName	()Ljava/lang/String;
    //   523: ldc 115
    //   525: aload 7
    //   527: invokevirtual 118	o/rD:ˏ	(Ljava/lang/String;Ljava/lang/String;Ljava/lang/String;Ljava/io/File;)Lo/rD;
    //   530: pop
    //   531: goto -506 -> 25
    //   534: iconst_1
    //   535: istore 5
    //   537: goto +235 -> 772
    //   540: aload 7
    //   542: invokevirtual 113	java/io/File:getName	()Ljava/lang/String;
    //   545: ldc -94
    //   547: invokevirtual 126	java/lang/String:equals	(Ljava/lang/Object;)Z
    //   550: ifeq +6 -> 556
    //   553: goto -223 -> 330
    //   556: goto -505 -> 51
    //   559: goto -489 -> 70
    //   562: iload 5
    //   564: tableswitch	default:+24->588, 0:+181->745, 1:+-289->275
    //   588: goto +157 -> 745
    //   591: getstatic 15	o/乁:ˊ	I
    //   594: bipush 109
    //   596: iadd
    //   597: istore 5
    //   599: iload 5
    //   601: sipush 128
    //   604: irem
    //   605: putstatic 17	o/乁:ˏ	I
    //   608: iload 5
    //   610: iconst_2
    //   611: irem
    //   612: ifne +6 -> 618
    //   615: goto +107 -> 722
    //   618: goto +452 -> 1070
    //   621: iload 5
    //   623: lookupswitch	default:+25->648, 21:+-411->212, 43:+219->842
    //   648: goto -436 -> 212
    //   651: goto -626 -> 25
    //   654: getstatic 17	o/乁:ˏ	I
    //   657: bipush 77
    //   659: iadd
    //   660: istore 5
    //   662: iload 5
    //   664: sipush 128
    //   667: irem
    //   668: putstatic 15	o/乁:ˊ	I
    //   671: iload 5
    //   673: iconst_2
    //   674: irem
    //   675: ifeq +6 -> 681
    //   678: goto -543 -> 135
    //   681: goto +22 -> 703
    //   684: aload_1
    //   685: ldc -92
    //   687: aload 7
    //   689: invokevirtual 113	java/io/File:getName	()Ljava/lang/String;
    //   692: ldc 115
    //   694: aload 7
    //   696: invokevirtual 118	o/rD:ˏ	(Ljava/lang/String;Ljava/lang/String;Ljava/lang/String;Ljava/io/File;)Lo/rD;
    //   699: pop
    //   700: goto -675 -> 25
    //   703: aload_1
    //   704: ldc -124
    //   706: aload 7
    //   708: invokevirtual 113	java/io/File:getName	()Ljava/lang/String;
    //   711: ldc 115
    //   713: aload 7
    //   715: invokevirtual 118	o/rD:ˏ	(Ljava/lang/String;Ljava/lang/String;Ljava/lang/String;Ljava/io/File;)Lo/rD;
    //   718: pop
    //   719: goto -694 -> 25
    //   722: aload_1
    //   723: ldc -90
    //   725: aload 7
    //   727: invokevirtual 113	java/io/File:getName	()Ljava/lang/String;
    //   730: ldc 115
    //   732: aload 7
    //   734: invokevirtual 118	o/rD:ˏ	(Ljava/lang/String;Ljava/lang/String;Ljava/lang/String;Ljava/io/File;)Lo/rD;
    //   737: pop
    //   738: aconst_null
    //   739: arraylength
    //   740: istore 5
    //   742: goto -717 -> 25
    //   745: aload_2
    //   746: iload_3
    //   747: aaload
    //   748: astore 7
    //   750: aload 7
    //   752: invokevirtual 113	java/io/File:getName	()Ljava/lang/String;
    //   755: ldc -88
    //   757: invokevirtual 126	java/lang/String:equals	(Ljava/lang/Object;)Z
    //   760: ifeq +6 -> 766
    //   763: goto +167 -> 930
    //   766: iconst_1
    //   767: istore 5
    //   769: goto -321 -> 448
    //   772: iload 5
    //   774: tableswitch	default:+22->796, 0:+-749->25, 1:+-497->277
    //   796: goto -519 -> 277
    //   799: bipush 43
    //   801: istore 5
    //   803: goto -182 -> 621
    //   806: goto -331 -> 475
    //   809: astore_1
    //   810: aload_1
    //   811: athrow
    //   812: getstatic 15	o/乁:ˊ	I
    //   815: bipush 23
    //   817: iadd
    //   818: istore 5
    //   820: iload 5
    //   822: sipush 128
    //   825: irem
    //   826: putstatic 17	o/乁:ˏ	I
    //   829: iload 5
    //   831: iconst_2
    //   832: irem
    //   833: ifne +6 -> 839
    //   836: goto -573 -> 263
    //   839: goto -188 -> 651
    //   842: aload_1
    //   843: ldc -86
    //   845: aload 7
    //   847: invokevirtual 113	java/io/File:getName	()Ljava/lang/String;
    //   850: ldc 115
    //   852: aload 7
    //   854: invokevirtual 118	o/rD:ˏ	(Ljava/lang/String;Ljava/lang/String;Ljava/lang/String;Ljava/io/File;)Lo/rD;
    //   857: pop
    //   858: goto -833 -> 25
    //   861: iconst_0
    //   862: istore 5
    //   864: goto -302 -> 562
    //   867: aload 7
    //   869: invokevirtual 113	java/io/File:getName	()Ljava/lang/String;
    //   872: ldc -84
    //   874: invokevirtual 126	java/lang/String:equals	(Ljava/lang/Object;)Z
    //   877: ifeq +6 -> 883
    //   880: goto -81 -> 799
    //   883: goto +9 -> 892
    //   886: iconst_0
    //   887: istore 5
    //   889: goto -117 -> 772
    //   892: bipush 21
    //   894: istore 5
    //   896: goto -275 -> 621
    //   899: iconst_0
    //   900: istore 5
    //   902: goto -515 -> 387
    //   905: iconst_1
    //   906: istore 5
    //   908: goto -346 -> 562
    //   911: aload 7
    //   913: invokevirtual 113	java/io/File:getName	()Ljava/lang/String;
    //   916: ldc -82
    //   918: invokevirtual 126	java/lang/String:equals	(Ljava/lang/Object;)Z
    //   921: ifeq +6 -> 927
    //   924: goto -25 -> 899
    //   927: goto -658 -> 269
    //   930: iconst_0
    //   931: istore 5
    //   933: goto -485 -> 448
    //   936: iload_3
    //   937: iload 4
    //   939: if_icmpge +6 -> 945
    //   942: goto -81 -> 861
    //   945: goto -40 -> 905
    //   948: aload 7
    //   950: invokevirtual 113	java/io/File:getName	()Ljava/lang/String;
    //   953: astore 8
    //   955: aload 8
    //   957: iconst_2
    //   958: newarray int
    //   960: dup
    //   961: iconst_0
    //   962: ldc -106
    //   964: iastore
    //   965: dup
    //   966: iconst_1
    //   967: ldc -105
    //   969: iastore
    //   970: iconst_4
    //   971: invokestatic 157	o/乁:ˋ	([II)Ljava/lang/String;
    //   974: invokevirtual 160	java/lang/String:intern	()Ljava/lang/String;
    //   977: invokevirtual 126	java/lang/String:equals	(Ljava/lang/Object;)Z
    //   980: istore 6
    //   982: iload 6
    //   984: ifeq +6 -> 990
    //   987: goto -453 -> 534
    //   990: goto -104 -> 886
    //   993: getstatic 17	o/乁:ˏ	I
    //   996: bipush 105
    //   998: iadd
    //   999: istore 5
    //   1001: iload 5
    //   1003: sipush 128
    //   1006: irem
    //   1007: putstatic 15	o/乁:ˊ	I
    //   1010: iload 5
    //   1012: iconst_2
    //   1013: irem
    //   1014: ifeq +6 -> 1020
    //   1017: goto -751 -> 266
    //   1020: goto -789 -> 231
    //   1023: aload 7
    //   1025: invokevirtual 113	java/io/File:getName	()Ljava/lang/String;
    //   1028: ldc -80
    //   1030: invokevirtual 126	java/lang/String:equals	(Ljava/lang/Object;)Z
    //   1033: ifeq +6 -> 1039
    //   1036: goto -352 -> 684
    //   1039: goto -950 -> 89
    //   1042: iconst_1
    //   1043: istore 5
    //   1045: goto -685 -> 360
    //   1048: aload_1
    //   1049: ldc -78
    //   1051: aload 7
    //   1053: invokevirtual 113	java/io/File:getName	()Ljava/lang/String;
    //   1056: ldc 115
    //   1058: aload 7
    //   1060: invokevirtual 118	o/rD:ˏ	(Ljava/lang/String;Ljava/lang/String;Ljava/lang/String;Ljava/io/File;)Lo/rD;
    //   1063: pop
    //   1064: goto -646 -> 418
    //   1067: goto -1042 -> 25
    //   1070: aload_1
    //   1071: ldc -90
    //   1073: aload 7
    //   1075: invokevirtual 113	java/io/File:getName	()Ljava/lang/String;
    //   1078: ldc 115
    //   1080: aload 7
    //   1082: invokevirtual 118	o/rD:ˏ	(Ljava/lang/String;Ljava/lang/String;Ljava/lang/String;Ljava/io/File;)Lo/rD;
    //   1085: pop
    //   1086: goto -1061 -> 25
    // Local variable table:
    //   start	length	slot	name	signature
    //   0	1089	0	this	乁
    //   0	1089	1	paramRD	rD
    //   0	1089	2	paramﻐ	ﻐ
    //   25	915	3	i	int
    //   180	760	4	j	int
    //   153	891	5	k	int
    //   980	3	6	bool	boolean
    //   12	1069	7	localFile	java.io.File
    //   953	3	8	str	String
    // Exception table:
    //   from	to	target	type
    //   289	298	3	java/lang/Exception
    //   277	282	809	java/lang/Exception
    //   948	955	809	java/lang/Exception
    //   955	982	809	java/lang/Exception
  }
  
  public boolean ˋ(Ↄ paramↃ)
  {
    break label291;
    int i = 9;
    break label251;
    label9:
    boolean bool;
    for (;;)
    {
      switch (i)
      {
      default: 
        return bool;
        label38:
        i = 30;
      }
    }
    i = ˊ + 39;
    ˏ = i % 128;
    if (i % 2 != 0)
    {
      break label190;
      return bool;
    }
    label190:
    label251:
    label291:
    for (;;)
    {
      try
      {
        Object localObject = ˏ();
        localObject = ˋ((rD)localObject, paramↃ.ˏ);
        try
        {
          paramↃ = ˎ((rD)localObject, paramↃ.ˎ);
          localObject = qr.ʼ();
          ((qC)localObject).ॱ("CrashlyticsCore", "Sending report to: " + ॱ());
          i = paramↃ.ˏ();
          qr.ʼ().ॱ("CrashlyticsCore", "Result was: " + i);
          i = qT.ˏ(i);
          if (i == 0) {
            break;
          }
          continue;
          continue;
          continue;
          i = 99;
        }
        catch (Exception paramↃ)
        {
          throw paramↃ;
        }
        continue;
        bool = true;
        continue;
        bool = false;
      }
      catch (Exception paramↃ)
      {
        throw paramↃ;
      }
      i = ˊ + 83;
      ˏ = i % 128;
      if (i % 2 == 0) {
        break label38;
      }
      i = 16;
      break label9;
      switch (i)
      {
      }
      continue;
      throw new NullPointerException();
    }
  }
}
