package o;

import java.util.LinkedHashMap;

public class 氵<K, V>
{
  private static int ॱˊ = 1;
  private static int ॱॱ = 0;
  private static long ᐝ = -2318987718539358590L;
  private int ʻ;
  private int ʼ;
  private int ʽ;
  private final LinkedHashMap<K, V> ˊ;
  private int ˋ;
  private int ˎ;
  private int ˏ;
  private int ॱ;
  
  public 氵(int paramInt) {}
  
  /* Error */
  private static String ˎ(char[] paramArrayOfChar)
  {
    // Byte code:
    //   0: goto +238 -> 238
    //   3: bipush 18
    //   5: istore_3
    //   6: goto +235 -> 241
    //   9: bipush 31
    //   11: istore_3
    //   12: goto +229 -> 241
    //   15: iload_3
    //   16: tableswitch	default:+24->40, 0:+283->299, 1:+24->40
    //   40: aload 4
    //   42: iload_1
    //   43: iconst_0
    //   44: imul
    //   45: aload_0
    //   46: iload_1
    //   47: caload
    //   48: iload_1
    //   49: iload_2
    //   50: idiv
    //   51: iand
    //   52: i2l
    //   53: getstatic 30	o/氵:ᐝ	J
    //   56: lsub
    //   57: l2i
    //   58: i2c
    //   59: castore
    //   60: iload_1
    //   61: bipush 21
    //   63: iadd
    //   64: istore_1
    //   65: goto +117 -> 182
    //   68: goto +114 -> 182
    //   71: iconst_1
    //   72: istore_3
    //   73: goto -58 -> 15
    //   76: new 57	java/lang/String
    //   79: dup
    //   80: aload 4
    //   82: invokespecial 60	java/lang/String:<init>	([C)V
    //   85: areturn
    //   86: getstatic 24	o/氵:ॱॱ	I
    //   89: bipush 115
    //   91: iadd
    //   92: istore_1
    //   93: iload_1
    //   94: sipush 128
    //   97: irem
    //   98: putstatic 26	o/氵:ॱˊ	I
    //   101: iload_1
    //   102: iconst_2
    //   103: irem
    //   104: ifne +6 -> 110
    //   107: goto +109 -> 216
    //   110: goto +84 -> 194
    //   113: astore_0
    //   114: aload_0
    //   115: athrow
    //   116: iconst_0
    //   117: istore_3
    //   118: goto +153 -> 271
    //   121: iconst_0
    //   122: istore_3
    //   123: goto -108 -> 15
    //   126: getstatic 24	o/氵:ॱॱ	I
    //   129: bipush 69
    //   131: iadd
    //   132: istore_3
    //   133: iload_3
    //   134: sipush 128
    //   137: irem
    //   138: putstatic 26	o/氵:ॱˊ	I
    //   141: iload_3
    //   142: iconst_2
    //   143: irem
    //   144: ifne +6 -> 150
    //   147: goto -76 -> 71
    //   150: goto -29 -> 121
    //   153: getstatic 26	o/氵:ॱˊ	I
    //   156: istore_3
    //   157: iload_3
    //   158: bipush 125
    //   160: iadd
    //   161: istore_3
    //   162: iload_3
    //   163: sipush 128
    //   166: irem
    //   167: putstatic 24	o/氵:ॱॱ	I
    //   170: iload_3
    //   171: iconst_2
    //   172: irem
    //   173: ifeq +6 -> 179
    //   176: goto -167 -> 9
    //   179: goto -176 -> 3
    //   182: iload_1
    //   183: aload_0
    //   184: arraylength
    //   185: if_icmpge +6 -> 191
    //   188: goto -72 -> 116
    //   191: goto +138 -> 329
    //   194: aload_0
    //   195: astore 4
    //   197: aload 4
    //   199: iconst_0
    //   200: caload
    //   201: istore_2
    //   202: aload 4
    //   204: arraylength
    //   205: iconst_1
    //   206: isub
    //   207: newarray char
    //   209: astore 4
    //   211: iconst_1
    //   212: istore_1
    //   213: goto -60 -> 153
    //   216: aload_0
    //   217: astore 4
    //   219: aload 4
    //   221: iconst_1
    //   222: caload
    //   223: istore_2
    //   224: aload 4
    //   226: arraylength
    //   227: iconst_1
    //   228: iadd
    //   229: newarray char
    //   231: astore 4
    //   233: iconst_0
    //   234: istore_1
    //   235: goto -82 -> 153
    //   238: goto -152 -> 86
    //   241: iload_3
    //   242: lookupswitch	default:+26->268, 18:+26->268, 31:+-174->68
    //   268: goto -86 -> 182
    //   271: iload_3
    //   272: tableswitch	default:+24->296, 0:+-146->126, 1:+-196->76
    //   296: goto -170 -> 126
    //   299: aload 4
    //   301: iload_1
    //   302: iconst_1
    //   303: isub
    //   304: aload_0
    //   305: iload_1
    //   306: caload
    //   307: iload_1
    //   308: iload_2
    //   309: imul
    //   310: ixor
    //   311: i2l
    //   312: getstatic 30	o/氵:ᐝ	J
    //   315: lxor
    //   316: l2i
    //   317: i2c
    //   318: castore
    //   319: iload_1
    //   320: iconst_1
    //   321: iadd
    //   322: istore_1
    //   323: goto -141 -> 182
    //   326: astore_0
    //   327: aload_0
    //   328: athrow
    //   329: iconst_1
    //   330: istore_3
    //   331: goto -60 -> 271
    // Local variable table:
    //   start	length	slot	name	signature
    //   0	334	0	paramArrayOfChar	char[]
    //   42	281	1	i	int
    //   49	261	2	j	int
    //   5	326	3	k	int
    //   40	260	4	arrayOfChar	char[]
    // Exception table:
    //   from	to	target	type
    //   162	170	113	java/lang/Exception
    //   153	157	326	java/lang/Exception
  }
  
  /* Error */
  private int ॱ(K paramK, V paramV)
  {
    // Byte code:
    //   0: goto +176 -> 176
    //   3: getstatic 24	o/氵:ॱॱ	I
    //   6: bipush 71
    //   8: iadd
    //   9: istore_3
    //   10: iload_3
    //   11: sipush 128
    //   14: irem
    //   15: putstatic 26	o/氵:ॱˊ	I
    //   18: iload_3
    //   19: iconst_2
    //   20: irem
    //   21: ifne +6 -> 27
    //   24: goto +71 -> 95
    //   27: goto +63 -> 90
    //   30: getstatic 26	o/氵:ॱˊ	I
    //   33: bipush 21
    //   35: iadd
    //   36: istore 4
    //   38: iload 4
    //   40: sipush 128
    //   43: irem
    //   44: putstatic 24	o/氵:ॱॱ	I
    //   47: iload 4
    //   49: iconst_2
    //   50: irem
    //   51: ifeq +6 -> 57
    //   54: goto +120 -> 174
    //   57: iload_3
    //   58: ireturn
    //   59: iload_3
    //   60: tableswitch	default:+24->84, 0:+97->157, 1:+82->142
    //   84: goto +73 -> 157
    //   87: goto -57 -> 30
    //   90: iconst_0
    //   91: istore_3
    //   92: goto -33 -> 59
    //   95: iconst_1
    //   96: istore_3
    //   97: goto -38 -> 59
    //   100: new 63	java/lang/IllegalStateException
    //   103: dup
    //   104: new 65	java/lang/StringBuilder
    //   107: dup
    //   108: invokespecial 66	java/lang/StringBuilder:<init>	()V
    //   111: ldc 68
    //   113: invokevirtual 72	java/lang/StringBuilder:append	(Ljava/lang/String;)Ljava/lang/StringBuilder;
    //   116: aload_1
    //   117: invokevirtual 75	java/lang/StringBuilder:append	(Ljava/lang/Object;)Ljava/lang/StringBuilder;
    //   120: ldc 77
    //   122: invokevirtual 72	java/lang/StringBuilder:append	(Ljava/lang/String;)Ljava/lang/StringBuilder;
    //   125: aload_2
    //   126: invokevirtual 75	java/lang/StringBuilder:append	(Ljava/lang/Object;)Ljava/lang/StringBuilder;
    //   129: invokevirtual 81	java/lang/StringBuilder:toString	()Ljava/lang/String;
    //   132: invokespecial 82	java/lang/IllegalStateException:<init>	(Ljava/lang/String;)V
    //   135: athrow
    //   136: astore_1
    //   137: aload_1
    //   138: athrow
    //   139: astore_1
    //   140: aload_1
    //   141: athrow
    //   142: aload_0
    //   143: aload_1
    //   144: aload_2
    //   145: invokevirtual 84	o/氵:ˋ	(Ljava/lang/Object;Ljava/lang/Object;)I
    //   148: istore_3
    //   149: new 86	java/lang/NullPointerException
    //   152: dup
    //   153: invokespecial 87	java/lang/NullPointerException:<init>	()V
    //   156: athrow
    //   157: aload_0
    //   158: aload_1
    //   159: aload_2
    //   160: invokevirtual 84	o/氵:ˋ	(Ljava/lang/Object;Ljava/lang/Object;)I
    //   163: istore_3
    //   164: iload_3
    //   165: ifge +6 -> 171
    //   168: goto -68 -> 100
    //   171: goto -84 -> 87
    //   174: iload_3
    //   175: ireturn
    //   176: goto -173 -> 3
    // Local variable table:
    //   start	length	slot	name	signature
    //   0	179	0	this	氵
    //   0	179	1	paramK	K
    //   0	179	2	paramV	V
    //   9	166	3	i	int
    //   36	15	4	j	int
    // Exception table:
    //   from	to	target	type
    //   157	164	136	java/lang/Exception
    //   142	149	139	java/lang/Exception
  }
  
  /* Error */
  public final String toString()
  {
    // Byte code:
    //   0: aload_0
    //   1: monitorenter
    //   2: goto +104 -> 106
    //   5: astore_3
    //   6: aload_3
    //   7: athrow
    //   8: getstatic 24	o/氵:ॱॱ	I
    //   11: bipush 91
    //   13: iadd
    //   14: istore_1
    //   15: iload_1
    //   16: sipush 128
    //   19: irem
    //   20: putstatic 26	o/氵:ॱˊ	I
    //   23: iload_1
    //   24: iconst_2
    //   25: irem
    //   26: ifne +6 -> 32
    //   29: goto +162 -> 191
    //   32: goto +223 -> 255
    //   35: iconst_0
    //   36: istore_2
    //   37: goto -29 -> 8
    //   40: iconst_1
    //   41: istore_1
    //   42: goto +186 -> 228
    //   45: iconst_0
    //   46: istore_1
    //   47: goto +181 -> 228
    //   50: getstatic 95	java/util/Locale:US	Ljava/util/Locale;
    //   53: astore_3
    //   54: aload_3
    //   55: ldc 97
    //   57: iconst_4
    //   58: anewarray 5	java/lang/Object
    //   61: dup
    //   62: iconst_0
    //   63: aload_0
    //   64: getfield 37	o/氵:ˎ	I
    //   67: invokestatic 103	java/lang/Integer:valueOf	(I)Ljava/lang/Integer;
    //   70: aastore
    //   71: dup
    //   72: iconst_1
    //   73: aload_0
    //   74: getfield 105	o/氵:ʽ	I
    //   77: invokestatic 103	java/lang/Integer:valueOf	(I)Ljava/lang/Integer;
    //   80: aastore
    //   81: dup
    //   82: iconst_2
    //   83: aload_0
    //   84: getfield 107	o/氵:ʻ	I
    //   87: invokestatic 103	java/lang/Integer:valueOf	(I)Ljava/lang/Integer;
    //   90: aastore
    //   91: dup
    //   92: iconst_3
    //   93: iload_1
    //   94: invokestatic 103	java/lang/Integer:valueOf	(I)Ljava/lang/Integer;
    //   97: aastore
    //   98: invokestatic 111	java/lang/String:format	(Ljava/util/Locale;Ljava/lang/String;[Ljava/lang/Object;)Ljava/lang/String;
    //   101: astore_3
    //   102: aload_0
    //   103: monitorexit
    //   104: aload_3
    //   105: areturn
    //   106: goto +53 -> 159
    //   109: astore_3
    //   110: aload_3
    //   111: athrow
    //   112: getstatic 26	o/氵:ॱˊ	I
    //   115: bipush 109
    //   117: iadd
    //   118: istore_1
    //   119: iload_1
    //   120: sipush 128
    //   123: irem
    //   124: putstatic 24	o/氵:ॱॱ	I
    //   127: iload_1
    //   128: iconst_2
    //   129: irem
    //   130: ifeq +6 -> 136
    //   133: goto -88 -> 45
    //   136: goto -96 -> 40
    //   139: iload_2
    //   140: istore_1
    //   141: goto -91 -> 50
    //   144: aload_0
    //   145: getfield 105	o/氵:ʽ	I
    //   148: istore_1
    //   149: iload_1
    //   150: bipush 100
    //   152: imul
    //   153: iload_2
    //   154: idiv
    //   155: istore_1
    //   156: goto -106 -> 50
    //   159: aload_0
    //   160: getfield 105	o/氵:ʽ	I
    //   163: aload_0
    //   164: getfield 107	o/氵:ʻ	I
    //   167: iadd
    //   168: istore_2
    //   169: iload_2
    //   170: ifeq +91 -> 261
    //   173: goto -61 -> 112
    //   176: aload_0
    //   177: getfield 105	o/氵:ʽ	I
    //   180: istore_1
    //   181: bipush 62
    //   183: iload_1
    //   184: irem
    //   185: iload_2
    //   186: iushr
    //   187: istore_1
    //   188: goto -138 -> 50
    //   191: bipush 97
    //   193: istore_1
    //   194: iload_1
    //   195: lookupswitch	default:+25->220, 85:+69->264, 97:+-56->139
    //   220: goto +44 -> 264
    //   223: astore_3
    //   224: aload_0
    //   225: monitorexit
    //   226: aload_3
    //   227: athrow
    //   228: iload_1
    //   229: tableswitch	default:+23->252, 0:+-53->176, 1:+-85->144
    //   252: goto -108 -> 144
    //   255: bipush 85
    //   257: istore_1
    //   258: goto -64 -> 194
    //   261: goto -226 -> 35
    //   264: iload_2
    //   265: istore_1
    //   266: goto -216 -> 50
    // Exception table:
    //   from	to	target	type
    //   50	54	5	java/lang/Exception
    //   54	102	5	java/lang/Exception
    //   144	149	5	java/lang/Exception
    //   6	8	223	finally
    //   8	23	223	finally
    //   50	54	223	finally
    //   54	102	223	finally
    //   110	112	223	finally
    //   112	127	223	finally
    //   144	149	223	finally
    //   149	156	223	finally
    //   159	169	223	finally
    //   176	181	223	finally
  }
  
  public final V ˊ(K paramK)
  {
    if (paramK == null) {
      throw new NullPointerException(ˎ(new char[] { -11855, 8024, 28037, -17432, -30618, -10550, 9369, 30069, 17252, -28210, -508, -13195 }).intern());
    }
    try
    {
      localObject1 = this.ˊ.get(paramK);
      if (localObject1 != null)
      {
        this.ʽ += 1;
        return localObject1;
      }
      this.ʻ += 1;
    }
    finally {}
    Object localObject1 = ˎ(paramK);
    if (localObject1 == null) {
      return null;
    }
    Object localObject2;
    try
    {
      this.ˏ += 1;
      localObject2 = this.ˊ.put(paramK, localObject1);
      if (localObject2 != null) {
        this.ˊ.put(paramK, localObject2);
      } else {
        this.ˋ += ॱ(paramK, localObject1);
      }
    }
    finally {}
    if (localObject2 != null)
    {
      ˏ(false, paramK, localObject1, localObject2);
      return localObject2;
    }
    ˋ(this.ˎ);
    return localObject1;
  }
  
  protected int ˋ(K paramK, V paramV)
  {
    int j;
    label37:
    int i;
    switch (j)
    {
    default: 
      break;
      for (;;)
      {
        j = 0;
        break;
        j = ॱˊ + 113;
        ॱॱ = j % 128;
        if (j % 2 == 0) {
          break label130;
        }
      }
    case 0: 
      for (;;)
      {
        switch (i)
        {
        default: 
          break label141;
          i = ॱॱ + 95;
          ॱˊ = i % 128;
          if (i % 2 != 0)
          {
            break label146;
            throw new NullPointerException();
            j = 1;
          }
          break;
        case 0: 
          i = 1;
          break;
        case 1: 
          label130:
          label141:
          i = 0;
          break label37;
          label146:
          i = 0;
          continue;
          i = 1;
        }
      }
    }
    return i;
  }
  
  /* Error */
  public void ˋ(int paramInt)
  {
    // Byte code:
    //   0: aload_0
    //   1: monitorenter
    //   2: aload_0
    //   3: getfield 143	o/氵:ˋ	I
    //   6: iflt +20 -> 26
    //   9: aload_0
    //   10: getfield 45	o/氵:ˊ	Ljava/util/LinkedHashMap;
    //   13: invokevirtual 155	java/util/LinkedHashMap:isEmpty	()Z
    //   16: ifeq +43 -> 59
    //   19: aload_0
    //   20: getfield 143	o/氵:ˋ	I
    //   23: ifeq +36 -> 59
    //   26: new 63	java/lang/IllegalStateException
    //   29: dup
    //   30: new 65	java/lang/StringBuilder
    //   33: dup
    //   34: invokespecial 66	java/lang/StringBuilder:<init>	()V
    //   37: aload_0
    //   38: invokevirtual 159	java/lang/Object:getClass	()Ljava/lang/Class;
    //   41: invokevirtual 164	java/lang/Class:getName	()Ljava/lang/String;
    //   44: invokevirtual 72	java/lang/StringBuilder:append	(Ljava/lang/String;)Ljava/lang/StringBuilder;
    //   47: ldc -90
    //   49: invokevirtual 72	java/lang/StringBuilder:append	(Ljava/lang/String;)Ljava/lang/StringBuilder;
    //   52: invokevirtual 81	java/lang/StringBuilder:toString	()Ljava/lang/String;
    //   55: invokespecial 82	java/lang/IllegalStateException:<init>	(Ljava/lang/String;)V
    //   58: athrow
    //   59: aload_0
    //   60: getfield 143	o/氵:ˋ	I
    //   63: iload_1
    //   64: if_icmple +15 -> 79
    //   67: aload_0
    //   68: getfield 45	o/氵:ˊ	Ljava/util/LinkedHashMap;
    //   71: invokevirtual 155	java/util/LinkedHashMap:isEmpty	()Z
    //   74: istore_2
    //   75: iload_2
    //   76: ifeq +6 -> 82
    //   79: aload_0
    //   80: monitorexit
    //   81: return
    //   82: aload_0
    //   83: getfield 45	o/氵:ˊ	Ljava/util/LinkedHashMap;
    //   86: invokevirtual 170	java/util/LinkedHashMap:entrySet	()Ljava/util/Set;
    //   89: invokeinterface 176 1 0
    //   94: invokeinterface 182 1 0
    //   99: checkcast 184	java/util/Map$Entry
    //   102: astore 4
    //   104: aload 4
    //   106: invokeinterface 187 1 0
    //   111: astore_3
    //   112: aload 4
    //   114: invokeinterface 190 1 0
    //   119: astore 4
    //   121: aload_0
    //   122: getfield 45	o/氵:ˊ	Ljava/util/LinkedHashMap;
    //   125: aload_3
    //   126: invokevirtual 193	java/util/LinkedHashMap:remove	(Ljava/lang/Object;)Ljava/lang/Object;
    //   129: pop
    //   130: aload_0
    //   131: aload_0
    //   132: getfield 143	o/氵:ˋ	I
    //   135: aload_0
    //   136: aload_3
    //   137: aload 4
    //   139: invokespecial 145	o/氵:ॱ	(Ljava/lang/Object;Ljava/lang/Object;)I
    //   142: isub
    //   143: putfield 143	o/氵:ˋ	I
    //   146: aload_0
    //   147: aload_0
    //   148: getfield 195	o/氵:ʼ	I
    //   151: iconst_1
    //   152: iadd
    //   153: putfield 195	o/氵:ʼ	I
    //   156: aload_0
    //   157: monitorexit
    //   158: goto +8 -> 166
    //   161: astore_3
    //   162: aload_0
    //   163: monitorexit
    //   164: aload_3
    //   165: athrow
    //   166: aload_0
    //   167: iconst_1
    //   168: aload_3
    //   169: aload 4
    //   171: aconst_null
    //   172: invokevirtual 148	o/氵:ˏ	(ZLjava/lang/Object;Ljava/lang/Object;Ljava/lang/Object;)V
    //   175: goto -175 -> 0
    // Local variable table:
    //   start	length	slot	name	signature
    //   0	178	0	this	氵
    //   0	178	1	paramInt	int
    //   74	2	2	bool	boolean
    //   111	26	3	localObject1	Object
    //   161	8	3	localObject2	Object
    //   102	68	4	localObject3	Object
    // Exception table:
    //   from	to	target	type
    //   2	26	161	finally
    //   26	59	161	finally
    //   59	75	161	finally
    //   82	156	161	finally
  }
  
  /* Error */
  protected V ˎ(K paramK)
  {
    // Byte code:
    //   0: goto +84 -> 84
    //   3: astore_1
    //   4: aload_1
    //   5: athrow
    //   6: getstatic 24	o/氵:ॱॱ	I
    //   9: istore_2
    //   10: iload_2
    //   11: bipush 59
    //   13: iadd
    //   14: istore_2
    //   15: iload_2
    //   16: sipush 128
    //   19: irem
    //   20: putstatic 26	o/氵:ॱˊ	I
    //   23: iload_2
    //   24: iconst_2
    //   25: irem
    //   26: ifne +6 -> 32
    //   29: goto +45 -> 74
    //   32: goto +83 -> 115
    //   35: goto -29 -> 6
    //   38: bipush 74
    //   40: iconst_0
    //   41: idiv
    //   42: istore_2
    //   43: aconst_null
    //   44: areturn
    //   45: getstatic 26	o/氵:ॱˊ	I
    //   48: istore_2
    //   49: iload_2
    //   50: bipush 49
    //   52: iadd
    //   53: istore_2
    //   54: iload_2
    //   55: sipush 128
    //   58: irem
    //   59: putstatic 24	o/氵:ॱॱ	I
    //   62: iload_2
    //   63: iconst_2
    //   64: irem
    //   65: ifeq +6 -> 71
    //   68: goto +11 -> 79
    //   71: goto -36 -> 35
    //   74: iconst_0
    //   75: istore_2
    //   76: goto +11 -> 87
    //   79: goto -44 -> 35
    //   82: aconst_null
    //   83: areturn
    //   84: goto -39 -> 45
    //   87: iload_2
    //   88: tableswitch	default:+24->112, 0:+-50->38, 1:+-6->82
    //   112: goto -30 -> 82
    //   115: iconst_1
    //   116: istore_2
    //   117: goto -30 -> 87
    //   120: astore_1
    //   121: aload_1
    //   122: athrow
    // Local variable table:
    //   start	length	slot	name	signature
    //   0	123	0	this	氵
    //   0	123	1	paramK	K
    //   9	108	2	i	int
    // Exception table:
    //   from	to	target	type
    //   6	10	3	java/lang/Exception
    //   15	23	3	java/lang/Exception
    //   45	49	120	java/lang/Exception
    //   54	62	120	java/lang/Exception
  }
  
  public final V ˎ(K paramK, V paramV)
  {
    if ((paramK == null) || (paramV == null)) {
      throw new NullPointerException(ˎ(new char[] { -7025, 10854, 2041, 25430, 23710, -18316, -27163, -3765, -5484, -14352, 9080, 7371, 30742, 21949, -20180, -21821, -31228, -7268, -8992, 14442, 5579, 28953, 27381, 18022, -23606, -24805, -1935, -10757, 12618 }).intern());
    }
    Object localObject;
    try
    {
      this.ॱ += 1;
      this.ˋ += ॱ(paramK, paramV);
      localObject = this.ˊ.put(paramK, paramV);
      if (localObject != null) {
        this.ˋ -= ॱ(paramK, localObject);
      }
    }
    finally {}
    if (localObject != null) {
      ˏ(false, paramK, localObject, paramV);
    }
    ˋ(this.ˎ);
    return localObject;
  }
  
  protected void ˏ(boolean paramBoolean, K paramK, V paramV1, V paramV2)
  {
    int i;
    for (;;)
    {
      switch (i)
      {
      default: 
        return;
      case 72: 
        i = 19 / 0;
        return;
        break label87;
        i = 72;
        continue;
        label50:
        i = 94;
      }
    }
    label87:
    for (;;)
    {
      i = ॱˊ + 113;
      ॱॱ = i % 128;
      if (i % 2 != 0) {
        break;
      }
      break label50;
    }
  }
}
