package com.db.pwcc.dbmobile.mobile_payment.processor;

import android.content.Intent;
import com.google.android.gms.gcm.GcmReceiver;
import java.lang.reflect.InvocationTargetException;
import java.lang.reflect.Method;
import javax.inject.Inject;
import uuuuuu.opoooo;
import uuuuuu.ppphhp;
import uuuuuu.rvvvrv;
import uuuuuu.tttyyt;
import uuuuuu.yttttt;
import uuuuuu.yytytt;
import uuuuuu.yyytyt;
import xxxxxx.uxxxxx;

public class GcmPushReceiver
  extends GcmReceiver
{
  private static final String TAG = GcmPushReceiver.class.getSimpleName();
  public static int b006A006Ajjj006A006Aj = 95;
  public static int b006Aj006Ajj006A006Aj = 1;
  public static int bj006A006Ajj006A006Aj = 2;
  public static int bjj006Ajj006A006Aj;
  @Inject
  public yttttt cpController;
  @Inject
  public opoooo gcmTokenHandler;
  
  static
  {
    int i = b006A006Ajjj006A006Aj;
    int j = b006Aj006Ajj006A006Aj;
    int k = b006A006Ajjj006A006Aj;
    int m = bj006A006Ajj006A006Aj;
    int n = b006A006Ajjj006A006Aj;
    switch (n * (b006Aj006Ajj006A006Aj + n) % bj006A006Ajj006A006Aj)
    {
    default: 
      b006A006Ajjj006A006Aj = 67;
      bjj006Ajj006A006Aj = b006A006A006Ajj006A006Aj();
    }
    if ((i + j) * k % m != bjj006Ajj006A006Aj)
    {
      b006A006Ajjj006A006Aj = b006A006A006Ajj006A006Aj();
      bjj006Ajj006A006Aj = 7;
    }
  }
  
  public GcmPushReceiver()
  {
    tttyyt.bq0071qqqqq007100710071().bp0070pp0070ppppp(this);
  }
  
  public static int b006A006A006Ajj006A006Aj()
  {
    return 91;
  }
  
  public static int b006Ajj006Aj006A006Aj()
  {
    return 1;
  }
  
  public static int bjjj006Aj006A006Aj()
  {
    return 0;
  }
  
  private void handleReceivedNotification(Intent paramIntent)
  {
    Object localObject = paramIntent.getAction();
    if (localObject != null)
    {
      if (isGcmMessage((String)localObject))
      {
        initCpClient();
        if ((b006A006Ajjj006A006Aj + b006Aj006Ajj006A006Aj) * b006A006Ajjj006A006Aj % bj006A006Ajj006A006Aj != bjj006Ajj006A006Aj)
        {
          b006A006Ajjj006A006Aj = b006A006A006Ajj006A006Aj();
          bjj006Ajj006A006Aj = 95;
          if ((b006A006A006Ajj006A006Aj() + b006Aj006Ajj006A006Aj) * b006A006A006Ajj006A006Aj() % bj006A006Ajj006A006Aj != bjjj006Aj006A006Aj())
          {
            b006A006Ajjj006A006Aj = 80;
            bjj006Ajj006A006Aj = 6;
          }
        }
        processNotification(paramIntent);
      }
      return;
    }
    paramIntent = TAG;
    localObject = ppphhp.class.getMethod(uxxxxx.bbbb0062b0062b0062b0062("o\004\003\002\00187=<4398w/.43+*0/n", 'Ì', 'Z', '\001'), new Class[] { String.class, Character.TYPE, Character.TYPE });
    try
    {
      localObject = ((Method)localObject).invoke(null, new Object[] { "geHZWX[gU\027\027\rUY^NV['HXLQOHQ|AHJMQ", Character.valueOf('¬'), Character.valueOf('\005') });
      rvvvrv.b0071qq007100710071q0071q0071(paramIntent, (String)localObject);
      return;
    }
    catch (InvocationTargetException paramIntent)
    {
      throw paramIntent.getCause();
    }
  }
  
  /* Error */
  private void initCpClient()
  {
    // Byte code:
    //   0: aload_0
    //   1: getfield 130	com/db/pwcc/dbmobile/mobile_payment/processor/GcmPushReceiver:cpController	Luuuuuu/yttttt;
    //   4: invokeinterface 135 1 0
    //   9: getstatic 31	com/db/pwcc/dbmobile/mobile_payment/processor/GcmPushReceiver:b006A006Ajjj006A006Aj	I
    //   12: istore_1
    //   13: iload_1
    //   14: invokestatic 137	com/db/pwcc/dbmobile/mobile_payment/processor/GcmPushReceiver:b006Ajj006Aj006A006Aj	()I
    //   17: iload_1
    //   18: iadd
    //   19: imul
    //   20: getstatic 35	com/db/pwcc/dbmobile/mobile_payment/processor/GcmPushReceiver:bj006A006Ajj006A006Aj	I
    //   23: irem
    //   24: tableswitch	default:+20->44, 0:+31->55
    //   44: invokestatic 39	com/db/pwcc/dbmobile/mobile_payment/processor/GcmPushReceiver:b006A006A006Ajj006A006Aj	()I
    //   47: putstatic 31	com/db/pwcc/dbmobile/mobile_payment/processor/GcmPushReceiver:b006A006Ajjj006A006Aj	I
    //   50: bipush 43
    //   52: putstatic 41	com/db/pwcc/dbmobile/mobile_payment/processor/GcmPushReceiver:bjj006Ajj006A006Aj	I
    //   55: aload_0
    //   56: getfield 130	com/db/pwcc/dbmobile/mobile_payment/processor/GcmPushReceiver:cpController	Luuuuuu/yttttt;
    //   59: invokeinterface 141 1 0
    //   64: ifne +171 -> 235
    //   67: getstatic 29	com/db/pwcc/dbmobile/mobile_payment/processor/GcmPushReceiver:TAG	Ljava/lang/String;
    //   70: astore_2
    //   71: ldc 82
    //   73: ldc -113
    //   75: sipush 144
    //   78: iconst_5
    //   79: invokestatic 147	xxxxxx/uxxxxx:bb00620062bb0062b0062b0062	(Ljava/lang/String;CC)Ljava/lang/String;
    //   82: iconst_3
    //   83: anewarray 23	java/lang/Class
    //   86: dup
    //   87: iconst_0
    //   88: ldc 92
    //   90: aastore
    //   91: dup
    //   92: iconst_1
    //   93: getstatic 98	java/lang/Character:TYPE	Ljava/lang/Class;
    //   96: aastore
    //   97: dup
    //   98: iconst_2
    //   99: getstatic 98	java/lang/Character:TYPE	Ljava/lang/Class;
    //   102: aastore
    //   103: invokevirtual 102	java/lang/Class:getMethod	(Ljava/lang/String;[Ljava/lang/Class;)Ljava/lang/reflect/Method;
    //   106: astore_3
    //   107: aload_3
    //   108: aconst_null
    //   109: iconst_3
    //   110: anewarray 104	java/lang/Object
    //   113: dup
    //   114: iconst_0
    //   115: ldc -107
    //   117: aastore
    //   118: dup
    //   119: iconst_1
    //   120: sipush 182
    //   123: invokestatic 110	java/lang/Character:valueOf	(C)Ljava/lang/Character;
    //   126: aastore
    //   127: dup
    //   128: iconst_2
    //   129: iconst_0
    //   130: invokestatic 110	java/lang/Character:valueOf	(C)Ljava/lang/Character;
    //   133: aastore
    //   134: invokevirtual 116	java/lang/reflect/Method:invoke	(Ljava/lang/Object;[Ljava/lang/Object;)Ljava/lang/Object;
    //   137: astore_3
    //   138: aload_2
    //   139: aload_3
    //   140: checkcast 92	java/lang/String
    //   143: invokestatic 152	uuuuuu/rvvvrv:b007100710071q00710071q0071q0071	(Ljava/lang/String;Ljava/lang/String;)V
    //   146: aload_0
    //   147: getfield 130	com/db/pwcc/dbmobile/mobile_payment/processor/GcmPushReceiver:cpController	Luuuuuu/yttttt;
    //   150: aconst_null
    //   151: invokeinterface 156 2 0
    //   156: getstatic 29	com/db/pwcc/dbmobile/mobile_payment/processor/GcmPushReceiver:TAG	Ljava/lang/String;
    //   159: astore_2
    //   160: ldc 82
    //   162: ldc -98
    //   164: sipush 185
    //   167: bipush 58
    //   169: iconst_0
    //   170: invokestatic 90	xxxxxx/uxxxxx:bbbb0062b0062b0062b0062	(Ljava/lang/String;CCC)Ljava/lang/String;
    //   173: iconst_3
    //   174: anewarray 23	java/lang/Class
    //   177: dup
    //   178: iconst_0
    //   179: ldc 92
    //   181: aastore
    //   182: dup
    //   183: iconst_1
    //   184: getstatic 98	java/lang/Character:TYPE	Ljava/lang/Class;
    //   187: aastore
    //   188: dup
    //   189: iconst_2
    //   190: getstatic 98	java/lang/Character:TYPE	Ljava/lang/Class;
    //   193: aastore
    //   194: invokevirtual 102	java/lang/Class:getMethod	(Ljava/lang/String;[Ljava/lang/Class;)Ljava/lang/reflect/Method;
    //   197: astore_3
    //   198: aload_3
    //   199: aconst_null
    //   200: iconst_3
    //   201: anewarray 104	java/lang/Object
    //   204: dup
    //   205: iconst_0
    //   206: ldc -96
    //   208: aastore
    //   209: dup
    //   210: iconst_1
    //   211: iconst_1
    //   212: invokestatic 110	java/lang/Character:valueOf	(C)Ljava/lang/Character;
    //   215: aastore
    //   216: dup
    //   217: iconst_2
    //   218: iconst_3
    //   219: invokestatic 110	java/lang/Character:valueOf	(C)Ljava/lang/Character;
    //   222: aastore
    //   223: invokevirtual 116	java/lang/reflect/Method:invoke	(Ljava/lang/Object;[Ljava/lang/Object;)Ljava/lang/Object;
    //   226: astore_3
    //   227: aload_2
    //   228: aload_3
    //   229: checkcast 92	java/lang/String
    //   232: invokestatic 152	uuuuuu/rvvvrv:b007100710071q00710071q0071q0071	(Ljava/lang/String;Ljava/lang/String;)V
    //   235: return
    //   236: astore_2
    //   237: getstatic 29	com/db/pwcc/dbmobile/mobile_payment/processor/GcmPushReceiver:TAG	Ljava/lang/String;
    //   240: astore_2
    //   241: ldc 82
    //   243: ldc -94
    //   245: bipush 124
    //   247: iconst_4
    //   248: invokestatic 147	xxxxxx/uxxxxx:bb00620062bb0062b0062b0062	(Ljava/lang/String;CC)Ljava/lang/String;
    //   251: iconst_3
    //   252: anewarray 23	java/lang/Class
    //   255: dup
    //   256: iconst_0
    //   257: ldc 92
    //   259: aastore
    //   260: dup
    //   261: iconst_1
    //   262: getstatic 98	java/lang/Character:TYPE	Ljava/lang/Class;
    //   265: aastore
    //   266: dup
    //   267: iconst_2
    //   268: getstatic 98	java/lang/Character:TYPE	Ljava/lang/Class;
    //   271: aastore
    //   272: invokevirtual 102	java/lang/Class:getMethod	(Ljava/lang/String;[Ljava/lang/Class;)Ljava/lang/reflect/Method;
    //   275: astore_3
    //   276: aload_3
    //   277: aconst_null
    //   278: iconst_3
    //   279: anewarray 104	java/lang/Object
    //   282: dup
    //   283: iconst_0
    //   284: ldc -92
    //   286: aastore
    //   287: dup
    //   288: iconst_1
    //   289: bipush 76
    //   291: invokestatic 110	java/lang/Character:valueOf	(C)Ljava/lang/Character;
    //   294: aastore
    //   295: dup
    //   296: iconst_2
    //   297: iconst_3
    //   298: invokestatic 110	java/lang/Character:valueOf	(C)Ljava/lang/Character;
    //   301: aastore
    //   302: invokevirtual 116	java/lang/reflect/Method:invoke	(Ljava/lang/Object;[Ljava/lang/Object;)Ljava/lang/Object;
    //   305: astore_3
    //   306: aload_2
    //   307: aload_3
    //   308: checkcast 92	java/lang/String
    //   311: invokestatic 167	uuuuuu/rvvvrv:bq0071qq00710071q0071q0071	(Ljava/lang/String;Ljava/lang/String;)V
    //   314: getstatic 31	com/db/pwcc/dbmobile/mobile_payment/processor/GcmPushReceiver:b006A006Ajjj006A006Aj	I
    //   317: getstatic 33	com/db/pwcc/dbmobile/mobile_payment/processor/GcmPushReceiver:b006Aj006Ajj006A006Aj	I
    //   320: iadd
    //   321: getstatic 31	com/db/pwcc/dbmobile/mobile_payment/processor/GcmPushReceiver:b006A006Ajjj006A006Aj	I
    //   324: imul
    //   325: getstatic 35	com/db/pwcc/dbmobile/mobile_payment/processor/GcmPushReceiver:bj006A006Ajj006A006Aj	I
    //   328: irem
    //   329: getstatic 41	com/db/pwcc/dbmobile/mobile_payment/processor/GcmPushReceiver:bjj006Ajj006A006Aj	I
    //   332: if_icmpeq -176 -> 156
    //   335: invokestatic 39	com/db/pwcc/dbmobile/mobile_payment/processor/GcmPushReceiver:b006A006A006Ajj006A006Aj	()I
    //   338: putstatic 31	com/db/pwcc/dbmobile/mobile_payment/processor/GcmPushReceiver:b006A006Ajjj006A006Aj	I
    //   341: invokestatic 39	com/db/pwcc/dbmobile/mobile_payment/processor/GcmPushReceiver:b006A006A006Ajj006A006Aj	()I
    //   344: putstatic 41	com/db/pwcc/dbmobile/mobile_payment/processor/GcmPushReceiver:bjj006Ajj006A006Aj	I
    //   347: goto -191 -> 156
    //   350: astore_2
    //   351: aload_2
    //   352: invokevirtual 126	java/lang/reflect/InvocationTargetException:getCause	()Ljava/lang/Throwable;
    //   355: athrow
    //   356: astore_2
    //   357: aload_2
    //   358: invokevirtual 126	java/lang/reflect/InvocationTargetException:getCause	()Ljava/lang/Throwable;
    //   361: athrow
    //   362: astore_2
    //   363: aload_2
    //   364: invokevirtual 126	java/lang/reflect/InvocationTargetException:getCause	()Ljava/lang/Throwable;
    //   367: athrow
    // Local variable table:
    //   start	length	slot	name	signature
    //   0	368	0	this	GcmPushReceiver
    //   12	8	1	i	int
    //   70	158	2	str1	String
    //   236	1	2	localYytytt	yytytt
    //   240	67	2	str2	String
    //   350	2	2	localInvocationTargetException1	InvocationTargetException
    //   356	2	2	localInvocationTargetException2	InvocationTargetException
    //   362	2	2	localInvocationTargetException3	InvocationTargetException
    //   106	202	3	localObject	Object
    // Exception table:
    //   from	to	target	type
    //   146	156	236	uuuuuu/yytytt
    //   276	306	350	java/lang/reflect/InvocationTargetException
    //   198	227	356	java/lang/reflect/InvocationTargetException
    //   107	138	362	java/lang/reflect/InvocationTargetException
  }
  
  /* Error */
  private boolean isGcmMessage(String paramString)
  {
    // Byte code:
    //   0: ldc 82
    //   2: ldc -87
    //   4: iconst_3
    //   5: bipush 98
    //   7: iconst_3
    //   8: invokestatic 90	xxxxxx/uxxxxx:bbbb0062b0062b0062b0062	(Ljava/lang/String;CCC)Ljava/lang/String;
    //   11: iconst_4
    //   12: anewarray 23	java/lang/Class
    //   15: dup
    //   16: iconst_0
    //   17: ldc 92
    //   19: aastore
    //   20: dup
    //   21: iconst_1
    //   22: getstatic 98	java/lang/Character:TYPE	Ljava/lang/Class;
    //   25: aastore
    //   26: dup
    //   27: iconst_2
    //   28: getstatic 98	java/lang/Character:TYPE	Ljava/lang/Class;
    //   31: aastore
    //   32: dup
    //   33: iconst_3
    //   34: getstatic 98	java/lang/Character:TYPE	Ljava/lang/Class;
    //   37: aastore
    //   38: invokevirtual 102	java/lang/Class:getMethod	(Ljava/lang/String;[Ljava/lang/Class;)Ljava/lang/reflect/Method;
    //   41: astore_3
    //   42: aload_3
    //   43: aconst_null
    //   44: iconst_4
    //   45: anewarray 104	java/lang/Object
    //   48: dup
    //   49: iconst_0
    //   50: ldc -85
    //   52: aastore
    //   53: dup
    //   54: iconst_1
    //   55: bipush 93
    //   57: invokestatic 110	java/lang/Character:valueOf	(C)Ljava/lang/Character;
    //   60: aastore
    //   61: dup
    //   62: iconst_2
    //   63: bipush 74
    //   65: invokestatic 110	java/lang/Character:valueOf	(C)Ljava/lang/Character;
    //   68: aastore
    //   69: dup
    //   70: iconst_3
    //   71: iconst_2
    //   72: invokestatic 110	java/lang/Character:valueOf	(C)Ljava/lang/Character;
    //   75: aastore
    //   76: invokevirtual 116	java/lang/reflect/Method:invoke	(Ljava/lang/Object;[Ljava/lang/Object;)Ljava/lang/Object;
    //   79: astore_3
    //   80: aload_1
    //   81: aload_3
    //   82: checkcast 92	java/lang/String
    //   85: invokevirtual 175	java/lang/String:equals	(Ljava/lang/Object;)Z
    //   88: istore_2
    //   89: iload_2
    //   90: ifne +173 -> 263
    //   93: getstatic 29	com/db/pwcc/dbmobile/mobile_payment/processor/GcmPushReceiver:TAG	Ljava/lang/String;
    //   96: astore_3
    //   97: new 177	java/lang/StringBuilder
    //   100: dup
    //   101: invokespecial 178	java/lang/StringBuilder:<init>	()V
    //   104: astore 4
    //   106: ldc 82
    //   108: ldc -76
    //   110: sipush 183
    //   113: iconst_5
    //   114: invokestatic 147	xxxxxx/uxxxxx:bb00620062bb0062b0062b0062	(Ljava/lang/String;CC)Ljava/lang/String;
    //   117: iconst_3
    //   118: anewarray 23	java/lang/Class
    //   121: dup
    //   122: iconst_0
    //   123: ldc 92
    //   125: aastore
    //   126: dup
    //   127: iconst_1
    //   128: getstatic 98	java/lang/Character:TYPE	Ljava/lang/Class;
    //   131: aastore
    //   132: dup
    //   133: iconst_2
    //   134: getstatic 98	java/lang/Character:TYPE	Ljava/lang/Class;
    //   137: aastore
    //   138: invokevirtual 102	java/lang/Class:getMethod	(Ljava/lang/String;[Ljava/lang/Class;)Ljava/lang/reflect/Method;
    //   141: astore 5
    //   143: aload 5
    //   145: aconst_null
    //   146: iconst_3
    //   147: anewarray 104	java/lang/Object
    //   150: dup
    //   151: iconst_0
    //   152: ldc -74
    //   154: aastore
    //   155: dup
    //   156: iconst_1
    //   157: bipush 11
    //   159: invokestatic 110	java/lang/Character:valueOf	(C)Ljava/lang/Character;
    //   162: aastore
    //   163: dup
    //   164: iconst_2
    //   165: iconst_4
    //   166: invokestatic 110	java/lang/Character:valueOf	(C)Ljava/lang/Character;
    //   169: aastore
    //   170: invokevirtual 116	java/lang/reflect/Method:invoke	(Ljava/lang/Object;[Ljava/lang/Object;)Ljava/lang/Object;
    //   173: astore 5
    //   175: aload 4
    //   177: aload 5
    //   179: checkcast 92	java/lang/String
    //   182: invokevirtual 186	java/lang/StringBuilder:append	(Ljava/lang/String;)Ljava/lang/StringBuilder;
    //   185: astore 4
    //   187: getstatic 31	com/db/pwcc/dbmobile/mobile_payment/processor/GcmPushReceiver:b006A006Ajjj006A006Aj	I
    //   190: invokestatic 137	com/db/pwcc/dbmobile/mobile_payment/processor/GcmPushReceiver:b006Ajj006Aj006A006Aj	()I
    //   193: iadd
    //   194: getstatic 31	com/db/pwcc/dbmobile/mobile_payment/processor/GcmPushReceiver:b006A006Ajjj006A006Aj	I
    //   197: imul
    //   198: getstatic 35	com/db/pwcc/dbmobile/mobile_payment/processor/GcmPushReceiver:bj006A006Ajj006A006Aj	I
    //   201: irem
    //   202: getstatic 41	com/db/pwcc/dbmobile/mobile_payment/processor/GcmPushReceiver:bjj006Ajj006A006Aj	I
    //   205: if_icmpeq +45 -> 250
    //   208: iconst_1
    //   209: putstatic 31	com/db/pwcc/dbmobile/mobile_payment/processor/GcmPushReceiver:b006A006Ajjj006A006Aj	I
    //   212: invokestatic 39	com/db/pwcc/dbmobile/mobile_payment/processor/GcmPushReceiver:b006A006A006Ajj006A006Aj	()I
    //   215: putstatic 41	com/db/pwcc/dbmobile/mobile_payment/processor/GcmPushReceiver:bjj006Ajj006A006Aj	I
    //   218: getstatic 31	com/db/pwcc/dbmobile/mobile_payment/processor/GcmPushReceiver:b006A006Ajjj006A006Aj	I
    //   221: getstatic 33	com/db/pwcc/dbmobile/mobile_payment/processor/GcmPushReceiver:b006Aj006Ajj006A006Aj	I
    //   224: iadd
    //   225: getstatic 31	com/db/pwcc/dbmobile/mobile_payment/processor/GcmPushReceiver:b006A006Ajjj006A006Aj	I
    //   228: imul
    //   229: getstatic 35	com/db/pwcc/dbmobile/mobile_payment/processor/GcmPushReceiver:bj006A006Ajj006A006Aj	I
    //   232: irem
    //   233: getstatic 41	com/db/pwcc/dbmobile/mobile_payment/processor/GcmPushReceiver:bjj006Ajj006A006Aj	I
    //   236: if_icmpeq +14 -> 250
    //   239: invokestatic 39	com/db/pwcc/dbmobile/mobile_payment/processor/GcmPushReceiver:b006A006A006Ajj006A006Aj	()I
    //   242: putstatic 31	com/db/pwcc/dbmobile/mobile_payment/processor/GcmPushReceiver:b006A006Ajjj006A006Aj	I
    //   245: bipush 26
    //   247: putstatic 41	com/db/pwcc/dbmobile/mobile_payment/processor/GcmPushReceiver:bjj006Ajj006A006Aj	I
    //   250: aload_3
    //   251: aload 4
    //   253: aload_1
    //   254: invokevirtual 186	java/lang/StringBuilder:append	(Ljava/lang/String;)Ljava/lang/StringBuilder;
    //   257: invokevirtual 189	java/lang/StringBuilder:toString	()Ljava/lang/String;
    //   260: invokestatic 122	uuuuuu/rvvvrv:b0071qq007100710071q0071q0071	(Ljava/lang/String;Ljava/lang/String;)V
    //   263: iload_2
    //   264: ireturn
    //   265: astore_1
    //   266: aload_1
    //   267: invokevirtual 126	java/lang/reflect/InvocationTargetException:getCause	()Ljava/lang/Throwable;
    //   270: athrow
    //   271: astore_1
    //   272: aload_1
    //   273: invokevirtual 126	java/lang/reflect/InvocationTargetException:getCause	()Ljava/lang/Throwable;
    //   276: athrow
    // Local variable table:
    //   start	length	slot	name	signature
    //   0	277	0	this	GcmPushReceiver
    //   0	277	1	paramString	String
    //   88	176	2	bool	boolean
    //   41	210	3	localObject1	Object
    //   104	148	4	localStringBuilder	StringBuilder
    //   141	37	5	localObject2	Object
    // Exception table:
    //   from	to	target	type
    //   42	80	265	java/lang/reflect/InvocationTargetException
    //   143	175	271	java/lang/reflect/InvocationTargetException
  }
  
  /* Error */
  private boolean isMessage(android.content.Context paramContext, Intent paramIntent)
  {
    // Byte code:
    //   0: getstatic 31	com/db/pwcc/dbmobile/mobile_payment/processor/GcmPushReceiver:b006A006Ajjj006A006Aj	I
    //   3: getstatic 33	com/db/pwcc/dbmobile/mobile_payment/processor/GcmPushReceiver:b006Aj006Ajj006A006Aj	I
    //   6: iadd
    //   7: getstatic 31	com/db/pwcc/dbmobile/mobile_payment/processor/GcmPushReceiver:b006A006Ajjj006A006Aj	I
    //   10: imul
    //   11: getstatic 35	com/db/pwcc/dbmobile/mobile_payment/processor/GcmPushReceiver:bj006A006Ajj006A006Aj	I
    //   14: irem
    //   15: getstatic 41	com/db/pwcc/dbmobile/mobile_payment/processor/GcmPushReceiver:bjj006Ajj006A006Aj	I
    //   18: if_icmpeq +15 -> 33
    //   21: invokestatic 39	com/db/pwcc/dbmobile/mobile_payment/processor/GcmPushReceiver:b006A006A006Ajj006A006Aj	()I
    //   24: putstatic 31	com/db/pwcc/dbmobile/mobile_payment/processor/GcmPushReceiver:b006A006Ajjj006A006Aj	I
    //   27: invokestatic 39	com/db/pwcc/dbmobile/mobile_payment/processor/GcmPushReceiver:b006A006A006Ajj006A006Aj	()I
    //   30: putstatic 41	com/db/pwcc/dbmobile/mobile_payment/processor/GcmPushReceiver:bjj006Ajj006A006Aj	I
    //   33: ldc 82
    //   35: ldc -87
    //   37: sipush 228
    //   40: iconst_2
    //   41: invokestatic 147	xxxxxx/uxxxxx:bb00620062bb0062b0062b0062	(Ljava/lang/String;CC)Ljava/lang/String;
    //   44: iconst_4
    //   45: anewarray 23	java/lang/Class
    //   48: dup
    //   49: iconst_0
    //   50: ldc 92
    //   52: aastore
    //   53: dup
    //   54: iconst_1
    //   55: getstatic 98	java/lang/Character:TYPE	Ljava/lang/Class;
    //   58: aastore
    //   59: dup
    //   60: iconst_2
    //   61: getstatic 98	java/lang/Character:TYPE	Ljava/lang/Class;
    //   64: aastore
    //   65: dup
    //   66: iconst_3
    //   67: getstatic 98	java/lang/Character:TYPE	Ljava/lang/Class;
    //   70: aastore
    //   71: invokevirtual 102	java/lang/Class:getMethod	(Ljava/lang/String;[Ljava/lang/Class;)Ljava/lang/reflect/Method;
    //   74: astore 4
    //   76: aload 4
    //   78: aconst_null
    //   79: iconst_4
    //   80: anewarray 104	java/lang/Object
    //   83: dup
    //   84: iconst_0
    //   85: ldc -63
    //   87: aastore
    //   88: dup
    //   89: iconst_1
    //   90: bipush 83
    //   92: invokestatic 110	java/lang/Character:valueOf	(C)Ljava/lang/Character;
    //   95: aastore
    //   96: dup
    //   97: iconst_2
    //   98: sipush 145
    //   101: invokestatic 110	java/lang/Character:valueOf	(C)Ljava/lang/Character;
    //   104: aastore
    //   105: dup
    //   106: iconst_3
    //   107: iconst_0
    //   108: invokestatic 110	java/lang/Character:valueOf	(C)Ljava/lang/Character;
    //   111: aastore
    //   112: invokevirtual 116	java/lang/reflect/Method:invoke	(Ljava/lang/Object;[Ljava/lang/Object;)Ljava/lang/Object;
    //   115: astore 4
    //   117: aload 4
    //   119: checkcast 92	java/lang/String
    //   122: aload_1
    //   123: invokestatic 199	com/google/android/gms/gcm/GoogleCloudMessaging:getInstance	(Landroid/content/Context;)Lcom/google/android/gms/gcm/GoogleCloudMessaging;
    //   126: aload_2
    //   127: invokevirtual 203	com/google/android/gms/gcm/GoogleCloudMessaging:getMessageType	(Landroid/content/Intent;)Ljava/lang/String;
    //   130: invokevirtual 175	java/lang/String:equals	(Ljava/lang/Object;)Z
    //   133: istore_3
    //   134: iload_3
    //   135: ifeq +133 -> 268
    //   138: getstatic 29	com/db/pwcc/dbmobile/mobile_payment/processor/GcmPushReceiver:TAG	Ljava/lang/String;
    //   141: astore_1
    //   142: ldc 82
    //   144: ldc -51
    //   146: bipush 13
    //   148: sipush 196
    //   151: iconst_1
    //   152: invokestatic 90	xxxxxx/uxxxxx:bbbb0062b0062b0062b0062	(Ljava/lang/String;CCC)Ljava/lang/String;
    //   155: iconst_4
    //   156: anewarray 23	java/lang/Class
    //   159: dup
    //   160: iconst_0
    //   161: ldc 92
    //   163: aastore
    //   164: dup
    //   165: iconst_1
    //   166: getstatic 98	java/lang/Character:TYPE	Ljava/lang/Class;
    //   169: aastore
    //   170: dup
    //   171: iconst_2
    //   172: getstatic 98	java/lang/Character:TYPE	Ljava/lang/Class;
    //   175: aastore
    //   176: dup
    //   177: iconst_3
    //   178: getstatic 98	java/lang/Character:TYPE	Ljava/lang/Class;
    //   181: aastore
    //   182: invokevirtual 102	java/lang/Class:getMethod	(Ljava/lang/String;[Ljava/lang/Class;)Ljava/lang/reflect/Method;
    //   185: astore_2
    //   186: aload_2
    //   187: aconst_null
    //   188: iconst_4
    //   189: anewarray 104	java/lang/Object
    //   192: dup
    //   193: iconst_0
    //   194: ldc -49
    //   196: aastore
    //   197: dup
    //   198: iconst_1
    //   199: sipush 234
    //   202: invokestatic 110	java/lang/Character:valueOf	(C)Ljava/lang/Character;
    //   205: aastore
    //   206: dup
    //   207: iconst_2
    //   208: sipush 128
    //   211: invokestatic 110	java/lang/Character:valueOf	(C)Ljava/lang/Character;
    //   214: aastore
    //   215: dup
    //   216: iconst_3
    //   217: iconst_0
    //   218: invokestatic 110	java/lang/Character:valueOf	(C)Ljava/lang/Character;
    //   221: aastore
    //   222: invokevirtual 116	java/lang/reflect/Method:invoke	(Ljava/lang/Object;[Ljava/lang/Object;)Ljava/lang/Object;
    //   225: astore_2
    //   226: aload_2
    //   227: checkcast 92	java/lang/String
    //   230: astore_2
    //   231: getstatic 31	com/db/pwcc/dbmobile/mobile_payment/processor/GcmPushReceiver:b006A006Ajjj006A006Aj	I
    //   234: invokestatic 137	com/db/pwcc/dbmobile/mobile_payment/processor/GcmPushReceiver:b006Ajj006Aj006A006Aj	()I
    //   237: iadd
    //   238: getstatic 31	com/db/pwcc/dbmobile/mobile_payment/processor/GcmPushReceiver:b006A006Ajjj006A006Aj	I
    //   241: imul
    //   242: getstatic 35	com/db/pwcc/dbmobile/mobile_payment/processor/GcmPushReceiver:bj006A006Ajj006A006Aj	I
    //   245: irem
    //   246: getstatic 41	com/db/pwcc/dbmobile/mobile_payment/processor/GcmPushReceiver:bjj006Ajj006A006Aj	I
    //   249: if_icmpeq +14 -> 263
    //   252: invokestatic 39	com/db/pwcc/dbmobile/mobile_payment/processor/GcmPushReceiver:b006A006A006Ajj006A006Aj	()I
    //   255: putstatic 31	com/db/pwcc/dbmobile/mobile_payment/processor/GcmPushReceiver:b006A006Ajjj006A006Aj	I
    //   258: bipush 95
    //   260: putstatic 41	com/db/pwcc/dbmobile/mobile_payment/processor/GcmPushReceiver:bjj006Ajj006A006Aj	I
    //   263: aload_1
    //   264: aload_2
    //   265: invokestatic 210	uuuuuu/rvvvrv:bqqqq00710071q0071q0071	(Ljava/lang/String;Ljava/lang/String;)V
    //   268: iload_3
    //   269: ireturn
    //   270: astore_1
    //   271: aload_1
    //   272: invokevirtual 126	java/lang/reflect/InvocationTargetException:getCause	()Ljava/lang/Throwable;
    //   275: athrow
    //   276: astore_1
    //   277: aload_1
    //   278: invokevirtual 126	java/lang/reflect/InvocationTargetException:getCause	()Ljava/lang/Throwable;
    //   281: athrow
    // Local variable table:
    //   start	length	slot	name	signature
    //   0	282	0	this	GcmPushReceiver
    //   0	282	1	paramContext	android.content.Context
    //   0	282	2	paramIntent	Intent
    //   133	136	3	bool	boolean
    //   74	44	4	localObject	Object
    // Exception table:
    //   from	to	target	type
    //   186	226	270	java/lang/reflect/InvocationTargetException
    //   76	117	276	java/lang/reflect/InvocationTargetException
  }
  
  private void processNotification(Intent paramIntent)
  {
    try
    {
      this.cpController.bu0075u0075uuuuuu(paramIntent);
      return;
    }
    catch (yytytt paramIntent)
    {
      paramIntent = TAG;
      int i = b006A006Ajjj006A006Aj;
      switch (i * (b006Aj006Ajj006A006Aj + i) % bj006A006Ajj006A006Aj)
      {
      default: 
        b006A006Ajjj006A006Aj = 29;
        bjj006Ajj006A006Aj = b006A006A006Ajj006A006Aj();
      }
      if ((b006A006Ajjj006A006Aj + b006Aj006Ajj006A006Aj) * b006A006Ajjj006A006Aj % bj006A006Ajj006A006Aj != bjj006Ajj006A006Aj)
      {
        b006A006Ajjj006A006Aj = b006A006A006Ajj006A006Aj();
        bjj006Ajj006A006Aj = 17;
      }
      Object localObject = ppphhp.class.getMethod(uxxxxx.bb00620062bb0062b0062b0062("Ocba`\030\027\035\034\024\023\031\030W\017\016\024\023\013\n\020\017N", '', '\003'), new Class[] { String.class, Character.TYPE, Character.TYPE });
      try
      {
        localObject = ((Method)localObject).invoke(null, new Object[] { "Gkh\\\023``dXTVOL^RWU\006HEQ\002OOS}?AzB:F;B:8r4JoC62k\016\032\f40+38p", Character.valueOf(''), Character.valueOf('\003') });
        rvvvrv.bq0071qq00710071q0071q0071(paramIntent, (String)localObject);
        return;
      }
      catch (InvocationTargetException paramIntent)
      {
        throw paramIntent.getCause();
      }
    }
  }
  
  /* Error */
  public void onReceive(android.content.Context paramContext, Intent paramIntent)
  {
    // Byte code:
    //   0: ldc -35
    //   2: ldc -33
    //   4: bipush 107
    //   6: sipush 252
    //   9: iconst_3
    //   10: invokestatic 90	xxxxxx/uxxxxx:bbbb0062b0062b0062b0062	(Ljava/lang/String;CCC)Ljava/lang/String;
    //   13: iconst_1
    //   14: anewarray 23	java/lang/Class
    //   17: dup
    //   18: iconst_0
    //   19: ldc -31
    //   21: aastore
    //   22: invokevirtual 102	java/lang/Class:getMethod	(Ljava/lang/String;[Ljava/lang/Class;)Ljava/lang/reflect/Method;
    //   25: astore_3
    //   26: aload_3
    //   27: aconst_null
    //   28: iconst_1
    //   29: anewarray 104	java/lang/Object
    //   32: dup
    //   33: iconst_0
    //   34: aload_1
    //   35: aastore
    //   36: invokevirtual 116	java/lang/reflect/Method:invoke	(Ljava/lang/Object;[Ljava/lang/Object;)Ljava/lang/Object;
    //   39: pop
    //   40: getstatic 31	com/db/pwcc/dbmobile/mobile_payment/processor/GcmPushReceiver:b006A006Ajjj006A006Aj	I
    //   43: getstatic 33	com/db/pwcc/dbmobile/mobile_payment/processor/GcmPushReceiver:b006Aj006Ajj006A006Aj	I
    //   46: iadd
    //   47: getstatic 31	com/db/pwcc/dbmobile/mobile_payment/processor/GcmPushReceiver:b006A006Ajjj006A006Aj	I
    //   50: imul
    //   51: getstatic 35	com/db/pwcc/dbmobile/mobile_payment/processor/GcmPushReceiver:bj006A006Ajj006A006Aj	I
    //   54: irem
    //   55: invokestatic 77	com/db/pwcc/dbmobile/mobile_payment/processor/GcmPushReceiver:bjjj006Aj006A006Aj	()I
    //   58: if_icmpeq +13 -> 71
    //   61: bipush 30
    //   63: putstatic 31	com/db/pwcc/dbmobile/mobile_payment/processor/GcmPushReceiver:b006A006Ajjj006A006Aj	I
    //   66: bipush 16
    //   68: putstatic 41	com/db/pwcc/dbmobile/mobile_payment/processor/GcmPushReceiver:bjj006Ajj006A006Aj	I
    //   71: ldc -29
    //   73: ldc -27
    //   75: sipush 164
    //   78: sipush 143
    //   81: iconst_0
    //   82: invokestatic 90	xxxxxx/uxxxxx:bbbb0062b0062b0062b0062	(Ljava/lang/String;CCC)Ljava/lang/String;
    //   85: iconst_1
    //   86: anewarray 23	java/lang/Class
    //   89: dup
    //   90: iconst_0
    //   91: ldc -31
    //   93: aastore
    //   94: invokevirtual 102	java/lang/Class:getMethod	(Ljava/lang/String;[Ljava/lang/Class;)Ljava/lang/reflect/Method;
    //   97: astore_3
    //   98: aload_3
    //   99: aconst_null
    //   100: iconst_1
    //   101: anewarray 104	java/lang/Object
    //   104: dup
    //   105: iconst_0
    //   106: aload_1
    //   107: aastore
    //   108: invokevirtual 116	java/lang/reflect/Method:invoke	(Ljava/lang/Object;[Ljava/lang/Object;)Ljava/lang/Object;
    //   111: pop
    //   112: aload_1
    //   113: invokestatic 235	uuuuuu/uppupu:b0072r0072r00720072rr0072	(Landroid/content/Context;)V
    //   116: aload_2
    //   117: invokevirtual 68	android/content/Intent:getAction	()Ljava/lang/String;
    //   120: astore_3
    //   121: ldc 82
    //   123: ldc -19
    //   125: bipush 97
    //   127: iconst_5
    //   128: invokestatic 147	xxxxxx/uxxxxx:bb00620062bb0062b0062b0062	(Ljava/lang/String;CC)Ljava/lang/String;
    //   131: iconst_4
    //   132: anewarray 23	java/lang/Class
    //   135: dup
    //   136: iconst_0
    //   137: ldc 92
    //   139: aastore
    //   140: dup
    //   141: iconst_1
    //   142: getstatic 98	java/lang/Character:TYPE	Ljava/lang/Class;
    //   145: aastore
    //   146: dup
    //   147: iconst_2
    //   148: getstatic 98	java/lang/Character:TYPE	Ljava/lang/Class;
    //   151: aastore
    //   152: dup
    //   153: iconst_3
    //   154: getstatic 98	java/lang/Character:TYPE	Ljava/lang/Class;
    //   157: aastore
    //   158: invokevirtual 102	java/lang/Class:getMethod	(Ljava/lang/String;[Ljava/lang/Class;)Ljava/lang/reflect/Method;
    //   161: astore 4
    //   163: aload 4
    //   165: aconst_null
    //   166: iconst_4
    //   167: anewarray 104	java/lang/Object
    //   170: dup
    //   171: iconst_0
    //   172: ldc -17
    //   174: aastore
    //   175: dup
    //   176: iconst_1
    //   177: bipush 77
    //   179: invokestatic 110	java/lang/Character:valueOf	(C)Ljava/lang/Character;
    //   182: aastore
    //   183: dup
    //   184: iconst_2
    //   185: bipush 23
    //   187: invokestatic 110	java/lang/Character:valueOf	(C)Ljava/lang/Character;
    //   190: aastore
    //   191: dup
    //   192: iconst_3
    //   193: iconst_0
    //   194: invokestatic 110	java/lang/Character:valueOf	(C)Ljava/lang/Character;
    //   197: aastore
    //   198: invokevirtual 116	java/lang/reflect/Method:invoke	(Ljava/lang/Object;[Ljava/lang/Object;)Ljava/lang/Object;
    //   201: astore 4
    //   203: aload 4
    //   205: checkcast 92	java/lang/String
    //   208: astore 4
    //   210: getstatic 31	com/db/pwcc/dbmobile/mobile_payment/processor/GcmPushReceiver:b006A006Ajjj006A006Aj	I
    //   213: getstatic 33	com/db/pwcc/dbmobile/mobile_payment/processor/GcmPushReceiver:b006Aj006Ajj006A006Aj	I
    //   216: iadd
    //   217: getstatic 31	com/db/pwcc/dbmobile/mobile_payment/processor/GcmPushReceiver:b006A006Ajjj006A006Aj	I
    //   220: imul
    //   221: getstatic 35	com/db/pwcc/dbmobile/mobile_payment/processor/GcmPushReceiver:bj006A006Ajj006A006Aj	I
    //   224: irem
    //   225: getstatic 41	com/db/pwcc/dbmobile/mobile_payment/processor/GcmPushReceiver:bjj006Ajj006A006Aj	I
    //   228: if_icmpeq +15 -> 243
    //   231: invokestatic 39	com/db/pwcc/dbmobile/mobile_payment/processor/GcmPushReceiver:b006A006A006Ajj006A006Aj	()I
    //   234: putstatic 31	com/db/pwcc/dbmobile/mobile_payment/processor/GcmPushReceiver:b006A006Ajjj006A006Aj	I
    //   237: invokestatic 39	com/db/pwcc/dbmobile/mobile_payment/processor/GcmPushReceiver:b006A006A006Ajj006A006Aj	()I
    //   240: putstatic 41	com/db/pwcc/dbmobile/mobile_payment/processor/GcmPushReceiver:bjj006Ajj006A006Aj	I
    //   243: aload_3
    //   244: aload 4
    //   246: invokevirtual 175	java/lang/String:equals	(Ljava/lang/Object;)Z
    //   249: ifeq +120 -> 369
    //   252: ldc 82
    //   254: ldc -15
    //   256: bipush 62
    //   258: iconst_5
    //   259: invokestatic 147	xxxxxx/uxxxxx:bb00620062bb0062b0062b0062	(Ljava/lang/String;CC)Ljava/lang/String;
    //   262: iconst_4
    //   263: anewarray 23	java/lang/Class
    //   266: dup
    //   267: iconst_0
    //   268: ldc 92
    //   270: aastore
    //   271: dup
    //   272: iconst_1
    //   273: getstatic 98	java/lang/Character:TYPE	Ljava/lang/Class;
    //   276: aastore
    //   277: dup
    //   278: iconst_2
    //   279: getstatic 98	java/lang/Character:TYPE	Ljava/lang/Class;
    //   282: aastore
    //   283: dup
    //   284: iconst_3
    //   285: getstatic 98	java/lang/Character:TYPE	Ljava/lang/Class;
    //   288: aastore
    //   289: invokevirtual 102	java/lang/Class:getMethod	(Ljava/lang/String;[Ljava/lang/Class;)Ljava/lang/reflect/Method;
    //   292: astore_1
    //   293: aload_1
    //   294: aconst_null
    //   295: iconst_4
    //   296: anewarray 104	java/lang/Object
    //   299: dup
    //   300: iconst_0
    //   301: ldc -13
    //   303: aastore
    //   304: dup
    //   305: iconst_1
    //   306: bipush 108
    //   308: invokestatic 110	java/lang/Character:valueOf	(C)Ljava/lang/Character;
    //   311: aastore
    //   312: dup
    //   313: iconst_2
    //   314: bipush 33
    //   316: invokestatic 110	java/lang/Character:valueOf	(C)Ljava/lang/Character;
    //   319: aastore
    //   320: dup
    //   321: iconst_3
    //   322: iconst_2
    //   323: invokestatic 110	java/lang/Character:valueOf	(C)Ljava/lang/Character;
    //   326: aastore
    //   327: invokevirtual 116	java/lang/reflect/Method:invoke	(Ljava/lang/Object;[Ljava/lang/Object;)Ljava/lang/Object;
    //   330: astore_1
    //   331: aload_2
    //   332: aload_1
    //   333: checkcast 92	java/lang/String
    //   336: iconst_0
    //   337: invokevirtual 247	android/content/Intent:getBooleanExtra	(Ljava/lang/String;Z)Z
    //   340: ifeq +16 -> 356
    //   343: getstatic 253	uuuuuu/vvrvrv:bhhh006800680068h00680068	Luuuuuu/vvrvrv;
    //   346: invokestatic 259	uuuuuu/rrvvrv:b00710071qqq0071q0071q0071	(Luuuuuu/vvrvrv;)V
    //   349: aload_0
    //   350: getfield 261	com/db/pwcc/dbmobile/mobile_payment/processor/GcmPushReceiver:gcmTokenHandler	Luuuuuu/opoooo;
    //   353: invokevirtual 266	uuuuuu/opoooo:bu0075u00750075uuuuu	()V
    //   356: return
    //   357: astore_1
    //   358: aload_1
    //   359: invokevirtual 126	java/lang/reflect/InvocationTargetException:getCause	()Ljava/lang/Throwable;
    //   362: athrow
    //   363: astore_1
    //   364: aload_1
    //   365: invokevirtual 126	java/lang/reflect/InvocationTargetException:getCause	()Ljava/lang/Throwable;
    //   368: athrow
    //   369: aload_0
    //   370: aload_1
    //   371: aload_2
    //   372: invokespecial 268	com/db/pwcc/dbmobile/mobile_payment/processor/GcmPushReceiver:isMessage	(Landroid/content/Context;Landroid/content/Intent;)Z
    //   375: ifeq -19 -> 356
    //   378: getstatic 271	uuuuuu/vvrvrv:b006800680068h00680068h00680068	Luuuuuu/vvrvrv;
    //   381: invokestatic 259	uuuuuu/rrvvrv:b00710071qqq0071q0071q0071	(Luuuuuu/vvrvrv;)V
    //   384: aload_0
    //   385: aload_2
    //   386: invokespecial 273	com/db/pwcc/dbmobile/mobile_payment/processor/GcmPushReceiver:handleReceivedNotification	(Landroid/content/Intent;)V
    //   389: return
    //   390: astore_1
    //   391: aload_1
    //   392: invokevirtual 126	java/lang/reflect/InvocationTargetException:getCause	()Ljava/lang/Throwable;
    //   395: athrow
    //   396: astore_1
    //   397: aload_1
    //   398: invokevirtual 126	java/lang/reflect/InvocationTargetException:getCause	()Ljava/lang/Throwable;
    //   401: athrow
    // Local variable table:
    //   start	length	slot	name	signature
    //   0	402	0	this	GcmPushReceiver
    //   0	402	1	paramContext	android.content.Context
    //   0	402	2	paramIntent	Intent
    //   25	219	3	localObject1	Object
    //   161	84	4	localObject2	Object
    // Exception table:
    //   from	to	target	type
    //   98	112	357	java/lang/reflect/InvocationTargetException
    //   163	203	363	java/lang/reflect/InvocationTargetException
    //   293	331	390	java/lang/reflect/InvocationTargetException
    //   26	40	396	java/lang/reflect/InvocationTargetException
  }
}
