package com.google.android.gms.internal;

import android.support.v4.h.a;
import android.text.TextUtils;
import com.google.android.gms.common.internal.zzbq;
import java.math.BigDecimal;
import java.util.ArrayList;
import java.util.Arrays;
import java.util.HashSet;
import java.util.List;
import java.util.Locale;
import java.util.Map;
import java.util.Set;
import java.util.regex.Matcher;
import java.util.regex.Pattern;
import java.util.regex.PatternSyntaxException;

final class zzcii
  extends zzclj
{
  zzcii(zzckk paramZzckk)
  {
    super(paramZzckk);
  }
  
  private final Boolean zza(double paramDouble, zzcnv paramZzcnv)
  {
    try
    {
      paramZzcnv = zza(new BigDecimal(paramDouble), paramZzcnv, Math.ulp(paramDouble));
      return paramZzcnv;
    }
    catch (NumberFormatException paramZzcnv)
    {
      for (;;) {}
    }
    return null;
  }
  
  private final Boolean zza(long paramLong, zzcnv paramZzcnv)
  {
    try
    {
      paramZzcnv = zza(new BigDecimal(paramLong), paramZzcnv, 0.0D);
      return paramZzcnv;
    }
    catch (NumberFormatException paramZzcnv)
    {
      for (;;) {}
    }
    return null;
  }
  
  private final Boolean zza(zzcnt paramZzcnt, String paramString, zzcod[] paramArrayOfZzcod, long paramLong)
  {
    if (paramZzcnt.zzd != null)
    {
      localObject1 = zza(paramLong, paramZzcnt.zzd);
      if (localObject1 == null) {
        return null;
      }
      if (!((Boolean)localObject1).booleanValue()) {
        return Boolean.valueOf(false);
      }
    }
    HashSet localHashSet = new HashSet();
    Object localObject1 = paramZzcnt.zzc;
    int j = localObject1.length;
    int i = 0;
    Object localObject2;
    while (i < j)
    {
      localObject2 = localObject1[i];
      if (TextUtils.isEmpty(((zzcnu)localObject2).zzd))
      {
        zzt().zzaa().zza("null or empty param name in filter. event", zzo().zza(paramString));
        return null;
      }
      localHashSet.add(((zzcnu)localObject2).zzd);
      i += 1;
    }
    a localA = new a();
    j = paramArrayOfZzcod.length;
    i = 0;
    while (i < j)
    {
      localObject1 = paramArrayOfZzcod[i];
      if (localHashSet.contains(((zzcod)localObject1).zza))
      {
        if (((zzcod)localObject1).zzc != null)
        {
          localObject2 = ((zzcod)localObject1).zza;
          localObject1 = ((zzcod)localObject1).zzc;
        }
        for (;;)
        {
          localA.put(localObject2, localObject1);
          break label296;
          if (((zzcod)localObject1).zzd != null)
          {
            localObject2 = ((zzcod)localObject1).zza;
            localObject1 = ((zzcod)localObject1).zzd;
          }
          else
          {
            if (((zzcod)localObject1).zzb == null) {
              break;
            }
            localObject2 = ((zzcod)localObject1).zza;
            localObject1 = ((zzcod)localObject1).zzb;
          }
        }
        zzt().zzaa().zza("Unknown value for param. event, param", zzo().zza(paramString), zzo().zzb(((zzcod)localObject1).zza));
        return null;
      }
      label296:
      i += 1;
    }
    paramArrayOfZzcod = paramZzcnt.zzc;
    j = paramArrayOfZzcod.length;
    i = 0;
    while (i < j)
    {
      paramZzcnt = paramArrayOfZzcod[i];
      boolean bool = Boolean.TRUE.equals(paramZzcnt.zzc);
      localObject1 = paramZzcnt.zzd;
      if (TextUtils.isEmpty((CharSequence)localObject1))
      {
        zzt().zzaa().zza("Event has empty param name. event", zzo().zza(paramString));
        return null;
      }
      localObject2 = localA.get(localObject1);
      if ((localObject2 instanceof Long))
      {
        if (paramZzcnt.zzb == null)
        {
          zzt().zzaa().zza("No number filter for long param. event, param", zzo().zza(paramString), zzo().zzb((String)localObject1));
          return null;
        }
        paramZzcnt = zza(((Long)localObject2).longValue(), paramZzcnt.zzb);
        if (paramZzcnt == null) {
          return null;
        }
        if ((true ^ paramZzcnt.booleanValue() ^ bool)) {
          return Boolean.valueOf(false);
        }
      }
      else if ((localObject2 instanceof Double))
      {
        if (paramZzcnt.zzb == null)
        {
          zzt().zzaa().zza("No number filter for double param. event, param", zzo().zza(paramString), zzo().zzb((String)localObject1));
          return null;
        }
        paramZzcnt = zza(((Double)localObject2).doubleValue(), paramZzcnt.zzb);
        if (paramZzcnt == null) {
          return null;
        }
        if ((true ^ paramZzcnt.booleanValue() ^ bool)) {
          return Boolean.valueOf(false);
        }
      }
      else
      {
        if (!(localObject2 instanceof String)) {
          break label719;
        }
        if (paramZzcnt.zza != null)
        {
          paramZzcnt = zza((String)localObject2, paramZzcnt.zza);
        }
        else
        {
          if (paramZzcnt.zzb == null) {
            break label688;
          }
          localObject2 = (String)localObject2;
          if (!zzcnp.zzj((String)localObject2)) {
            break label657;
          }
          paramZzcnt = zza((String)localObject2, paramZzcnt.zzb);
        }
        if (paramZzcnt == null) {
          return null;
        }
        if ((true ^ paramZzcnt.booleanValue() ^ bool)) {
          return Boolean.valueOf(false);
        }
      }
      i += 1;
      continue;
      label657:
      zzt().zzaa().zza("Invalid param value for number filter. event, param", zzo().zza(paramString), zzo().zzb((String)localObject1));
      return null;
      label688:
      zzt().zzaa().zza("No filter for String param. event, param", zzo().zza(paramString), zzo().zzb((String)localObject1));
      return null;
      label719:
      if (localObject2 == null)
      {
        zzt().zzae().zza("Missing param for filter. event, param", zzo().zza(paramString), zzo().zzb((String)localObject1));
        return Boolean.valueOf(false);
      }
      zzt().zzaa().zza("Unknown param type. event, param", zzo().zza(paramString), zzo().zzb((String)localObject1));
      return null;
    }
    return Boolean.valueOf(true);
  }
  
  private static Boolean zza(Boolean paramBoolean, boolean paramBoolean1)
  {
    if (paramBoolean == null) {
      return null;
    }
    return Boolean.valueOf(paramBoolean.booleanValue() ^ paramBoolean1);
  }
  
  private final Boolean zza(String paramString1, int paramInt, boolean paramBoolean, String paramString2, List<String> paramList, String paramString3)
  {
    if (paramString1 == null) {
      return null;
    }
    if (paramInt == 6)
    {
      if ((paramList == null) || (paramList.size() == 0)) {
        return null;
      }
    }
    else if (paramString2 == null) {
      return null;
    }
    String str = paramString1;
    if (!paramBoolean) {
      if (paramInt == 1) {
        str = paramString1;
      } else {
        str = paramString1.toUpperCase(Locale.ENGLISH);
      }
    }
    switch (paramInt)
    {
    default: 
      return null;
    case 6: 
      paramBoolean = paramList.contains(str);
    case 5: 
    case 4: 
    case 3: 
    case 2: 
      for (;;)
      {
        return Boolean.valueOf(paramBoolean);
        paramBoolean = str.equals(paramString2);
        continue;
        paramBoolean = str.contains(paramString2);
        continue;
        paramBoolean = str.endsWith(paramString2);
        continue;
        paramBoolean = str.startsWith(paramString2);
      }
    }
    if (paramBoolean) {
      paramInt = 0;
    } else {
      paramInt = 66;
    }
    try
    {
      paramBoolean = Pattern.compile(paramString3, paramInt).matcher(str).matches();
      return Boolean.valueOf(paramBoolean);
    }
    catch (PatternSyntaxException paramString1)
    {
      for (;;) {}
    }
    zzt().zzaa().zza("Invalid regular expression in REGEXP audience filter. expression", paramString3);
    return null;
  }
  
  private final Boolean zza(String paramString, zzcnv paramZzcnv)
  {
    if (!zzcnp.zzj(paramString)) {
      return null;
    }
    try
    {
      paramString = zza(new BigDecimal(paramString), paramZzcnv, 0.0D);
      return paramString;
    }
    catch (NumberFormatException paramString) {}
    return null;
  }
  
  private final Boolean zza(String paramString, zzcnx paramZzcnx)
  {
    zzbq.zza(paramZzcnx);
    if (paramString == null) {
      return null;
    }
    if (paramZzcnx.zza != null)
    {
      if (paramZzcnx.zza.intValue() == 0) {
        return null;
      }
      if (paramZzcnx.zza.intValue() == 6)
      {
        if ((paramZzcnx.zzd == null) || (paramZzcnx.zzd.length == 0)) {
          return null;
        }
      }
      else if (paramZzcnx.zzb == null) {
        return null;
      }
      int j = paramZzcnx.zza.intValue();
      Object localObject1 = paramZzcnx.zzc;
      int i = 0;
      boolean bool;
      if ((localObject1 != null) && (paramZzcnx.zzc.booleanValue())) {
        bool = true;
      } else {
        bool = false;
      }
      if ((!bool) && (j != 1) && (j != 6)) {
        localObject1 = paramZzcnx.zzb.toUpperCase(Locale.ENGLISH);
      } else {
        localObject1 = paramZzcnx.zzb;
      }
      Object localObject2;
      if (paramZzcnx.zzd == null)
      {
        paramZzcnx = null;
      }
      else
      {
        localObject2 = paramZzcnx.zzd;
        if (bool)
        {
          paramZzcnx = Arrays.asList((Object[])localObject2);
        }
        else
        {
          paramZzcnx = new ArrayList();
          int k = localObject2.length;
          while (i < k)
          {
            paramZzcnx.add(localObject2[i].toUpperCase(Locale.ENGLISH));
            i += 1;
          }
        }
      }
      if (j == 1) {
        localObject2 = localObject1;
      } else {
        localObject2 = null;
      }
      return zza(paramString, j, bool, (String)localObject1, paramZzcnx, (String)localObject2);
    }
    return null;
  }
  
  /* Error */
  private static Boolean zza(BigDecimal paramBigDecimal, zzcnv paramZzcnv, double paramDouble)
  {
    // Byte code:
    //   0: aload_1
    //   1: invokestatic 255	com/google/android/gms/common/internal/zzbq:zza	(Ljava/lang/Object;)Ljava/lang/Object;
    //   4: pop
    //   5: aload_1
    //   6: getfield 285	com/google/android/gms/internal/zzcnv:zza	Ljava/lang/Integer;
    //   9: ifnull +412 -> 421
    //   12: aload_1
    //   13: getfield 285	com/google/android/gms/internal/zzcnv:zza	Ljava/lang/Integer;
    //   16: invokevirtual 265	java/lang/Integer:intValue	()I
    //   19: ifne +5 -> 24
    //   22: aconst_null
    //   23: areturn
    //   24: aload_1
    //   25: getfield 285	com/google/android/gms/internal/zzcnv:zza	Ljava/lang/Integer;
    //   28: invokevirtual 265	java/lang/Integer:intValue	()I
    //   31: iconst_4
    //   32: if_icmpne +19 -> 51
    //   35: aload_1
    //   36: getfield 286	com/google/android/gms/internal/zzcnv:zzd	Ljava/lang/String;
    //   39: ifnull +10 -> 49
    //   42: aload_1
    //   43: getfield 289	com/google/android/gms/internal/zzcnv:zze	Ljava/lang/String;
    //   46: ifnonnull +14 -> 60
    //   49: aconst_null
    //   50: areturn
    //   51: aload_1
    //   52: getfield 291	com/google/android/gms/internal/zzcnv:zzc	Ljava/lang/String;
    //   55: ifnonnull +5 -> 60
    //   58: aconst_null
    //   59: areturn
    //   60: aload_1
    //   61: getfield 285	com/google/android/gms/internal/zzcnv:zza	Ljava/lang/Integer;
    //   64: invokevirtual 265	java/lang/Integer:intValue	()I
    //   67: istore 4
    //   69: aload_1
    //   70: getfield 285	com/google/android/gms/internal/zzcnv:zza	Ljava/lang/Integer;
    //   73: invokevirtual 265	java/lang/Integer:intValue	()I
    //   76: iconst_4
    //   77: if_icmpne +62 -> 139
    //   80: aload_1
    //   81: getfield 286	com/google/android/gms/internal/zzcnv:zzd	Ljava/lang/String;
    //   84: invokestatic 185	com/google/android/gms/internal/zzcnp:zzj	(Ljava/lang/String;)Z
    //   87: ifeq +50 -> 137
    //   90: aload_1
    //   91: getfield 289	com/google/android/gms/internal/zzcnv:zze	Ljava/lang/String;
    //   94: invokestatic 185	com/google/android/gms/internal/zzcnp:zzj	(Ljava/lang/String;)Z
    //   97: ifne +5 -> 102
    //   100: aconst_null
    //   101: areturn
    //   102: new 15	java/math/BigDecimal
    //   105: dup
    //   106: aload_1
    //   107: getfield 286	com/google/android/gms/internal/zzcnv:zzd	Ljava/lang/String;
    //   110: invokespecial 251	java/math/BigDecimal:<init>	(Ljava/lang/String;)V
    //   113: astore 10
    //   115: new 15	java/math/BigDecimal
    //   118: dup
    //   119: aload_1
    //   120: getfield 289	com/google/android/gms/internal/zzcnv:zze	Ljava/lang/String;
    //   123: invokespecial 251	java/math/BigDecimal:<init>	(Ljava/lang/String;)V
    //   126: astore 11
    //   128: aload 10
    //   130: astore_1
    //   131: aconst_null
    //   132: astore 10
    //   134: goto +35 -> 169
    //   137: aconst_null
    //   138: areturn
    //   139: aload_1
    //   140: getfield 291	com/google/android/gms/internal/zzcnv:zzc	Ljava/lang/String;
    //   143: invokestatic 185	com/google/android/gms/internal/zzcnp:zzj	(Ljava/lang/String;)Z
    //   146: ifne +5 -> 151
    //   149: aconst_null
    //   150: areturn
    //   151: new 15	java/math/BigDecimal
    //   154: dup
    //   155: aload_1
    //   156: getfield 291	com/google/android/gms/internal/zzcnv:zzc	Ljava/lang/String;
    //   159: invokespecial 251	java/math/BigDecimal:<init>	(Ljava/lang/String;)V
    //   162: astore 10
    //   164: aconst_null
    //   165: astore_1
    //   166: aload_1
    //   167: astore 11
    //   169: iload 4
    //   171: iconst_4
    //   172: if_icmpne +9 -> 181
    //   175: aload_1
    //   176: ifnonnull +10 -> 186
    //   179: aconst_null
    //   180: areturn
    //   181: aload 10
    //   183: ifnull +238 -> 421
    //   186: iconst_0
    //   187: istore 7
    //   189: iconst_0
    //   190: istore 5
    //   192: iconst_0
    //   193: istore 8
    //   195: iconst_0
    //   196: istore 9
    //   198: iconst_0
    //   199: istore 6
    //   201: iload 4
    //   203: tableswitch	default:+29->232, 1:+195->398, 2:+172->375, 3:+67->270, 4:+31->234
    //   232: aconst_null
    //   233: areturn
    //   234: iload 6
    //   236: istore 5
    //   238: aload_0
    //   239: aload_1
    //   240: invokevirtual 295	java/math/BigDecimal:compareTo	(Ljava/math/BigDecimal;)I
    //   243: iconst_m1
    //   244: if_icmpeq +20 -> 264
    //   247: iload 6
    //   249: istore 5
    //   251: aload_0
    //   252: aload 11
    //   254: invokevirtual 295	java/math/BigDecimal:compareTo	(Ljava/math/BigDecimal;)I
    //   257: iconst_1
    //   258: if_icmpeq +6 -> 264
    //   261: iconst_1
    //   262: istore 5
    //   264: iload 5
    //   266: invokestatic 50	java/lang/Boolean:valueOf	(Z)Ljava/lang/Boolean;
    //   269: areturn
    //   270: dload_2
    //   271: dconst_0
    //   272: dcmpl
    //   273: ifeq +84 -> 357
    //   276: iload 7
    //   278: istore 5
    //   280: aload_0
    //   281: aload 10
    //   283: new 15	java/math/BigDecimal
    //   286: dup
    //   287: dload_2
    //   288: invokespecial 18	java/math/BigDecimal:<init>	(D)V
    //   291: new 15	java/math/BigDecimal
    //   294: dup
    //   295: iconst_2
    //   296: invokespecial 298	java/math/BigDecimal:<init>	(I)V
    //   299: invokevirtual 302	java/math/BigDecimal:multiply	(Ljava/math/BigDecimal;)Ljava/math/BigDecimal;
    //   302: invokevirtual 305	java/math/BigDecimal:subtract	(Ljava/math/BigDecimal;)Ljava/math/BigDecimal;
    //   305: invokevirtual 295	java/math/BigDecimal:compareTo	(Ljava/math/BigDecimal;)I
    //   308: iconst_1
    //   309: if_icmpne +42 -> 351
    //   312: iload 7
    //   314: istore 5
    //   316: aload_0
    //   317: aload 10
    //   319: new 15	java/math/BigDecimal
    //   322: dup
    //   323: dload_2
    //   324: invokespecial 18	java/math/BigDecimal:<init>	(D)V
    //   327: new 15	java/math/BigDecimal
    //   330: dup
    //   331: iconst_2
    //   332: invokespecial 298	java/math/BigDecimal:<init>	(I)V
    //   335: invokevirtual 302	java/math/BigDecimal:multiply	(Ljava/math/BigDecimal;)Ljava/math/BigDecimal;
    //   338: invokevirtual 307	java/math/BigDecimal:add	(Ljava/math/BigDecimal;)Ljava/math/BigDecimal;
    //   341: invokevirtual 295	java/math/BigDecimal:compareTo	(Ljava/math/BigDecimal;)I
    //   344: iconst_m1
    //   345: if_icmpne +6 -> 351
    //   348: iconst_1
    //   349: istore 5
    //   351: iload 5
    //   353: invokestatic 50	java/lang/Boolean:valueOf	(Z)Ljava/lang/Boolean;
    //   356: areturn
    //   357: aload_0
    //   358: aload 10
    //   360: invokevirtual 295	java/math/BigDecimal:compareTo	(Ljava/math/BigDecimal;)I
    //   363: ifne +6 -> 369
    //   366: iconst_1
    //   367: istore 5
    //   369: iload 5
    //   371: invokestatic 50	java/lang/Boolean:valueOf	(Z)Ljava/lang/Boolean;
    //   374: areturn
    //   375: iload 8
    //   377: istore 5
    //   379: aload_0
    //   380: aload 10
    //   382: invokevirtual 295	java/math/BigDecimal:compareTo	(Ljava/math/BigDecimal;)I
    //   385: iconst_1
    //   386: if_icmpne +6 -> 392
    //   389: iconst_1
    //   390: istore 5
    //   392: iload 5
    //   394: invokestatic 50	java/lang/Boolean:valueOf	(Z)Ljava/lang/Boolean;
    //   397: areturn
    //   398: iload 9
    //   400: istore 5
    //   402: aload_0
    //   403: aload 10
    //   405: invokevirtual 295	java/math/BigDecimal:compareTo	(Ljava/math/BigDecimal;)I
    //   408: iconst_m1
    //   409: if_icmpne +6 -> 415
    //   412: iconst_1
    //   413: istore 5
    //   415: iload 5
    //   417: invokestatic 50	java/lang/Boolean:valueOf	(Z)Ljava/lang/Boolean;
    //   420: areturn
    //   421: aconst_null
    //   422: areturn
    //   423: astore_0
    //   424: aconst_null
    //   425: areturn
    //   426: astore_0
    //   427: aconst_null
    //   428: areturn
    // Local variable table:
    //   start	length	slot	name	signature
    //   0	429	0	paramBigDecimal	BigDecimal
    //   0	429	1	paramZzcnv	zzcnv
    //   0	429	2	paramDouble	double
    //   67	135	4	i	int
    //   190	226	5	bool1	boolean
    //   199	49	6	bool2	boolean
    //   187	126	7	bool3	boolean
    //   193	183	8	bool4	boolean
    //   196	203	9	bool5	boolean
    //   113	291	10	localBigDecimal	BigDecimal
    //   126	127	11	localObject	Object
    // Exception table:
    //   from	to	target	type
    //   102	128	423	java/lang/NumberFormatException
    //   151	164	426	java/lang/NumberFormatException
  }
  
  /* Error */
  final zzcob[] zza(String arg1, zzcoc[] arg2, zzcoh[] arg3)
  {
    // Byte code:
    //   0: aload_2
    //   1: astore 28
    //   3: aload_3
    //   4: astore 15
    //   6: aload_1
    //   7: invokestatic 313	com/google/android/gms/common/internal/zzbq:zza	(Ljava/lang/String;)Ljava/lang/String;
    //   10: pop
    //   11: new 52	java/util/HashSet
    //   14: dup
    //   15: invokespecial 55	java/util/HashSet:<init>	()V
    //   18: astore 22
    //   20: new 106	android/support/v4/h/a
    //   23: dup
    //   24: invokespecial 107	android/support/v4/h/a:<init>	()V
    //   27: astore 27
    //   29: new 106	android/support/v4/h/a
    //   32: dup
    //   33: invokespecial 107	android/support/v4/h/a:<init>	()V
    //   36: astore 18
    //   38: new 106	android/support/v4/h/a
    //   41: dup
    //   42: invokespecial 107	android/support/v4/h/a:<init>	()V
    //   45: astore 17
    //   47: aload_0
    //   48: invokevirtual 317	com/google/android/gms/internal/zzcli:zzn	()Lcom/google/android/gms/internal/zzcim;
    //   51: aload_1
    //   52: invokevirtual 322	com/google/android/gms/internal/zzcim:zze	(Ljava/lang/String;)Ljava/util/Map;
    //   55: astore 21
    //   57: aload 17
    //   59: astore 20
    //   61: aload 18
    //   63: astore 19
    //   65: aload 21
    //   67: ifnull +331 -> 398
    //   70: aload 21
    //   72: invokeinterface 326 1 0
    //   77: invokeinterface 330 1 0
    //   82: astore 16
    //   84: aload 17
    //   86: astore 20
    //   88: aload 18
    //   90: astore 19
    //   92: aload 16
    //   94: invokeinterface 335 1 0
    //   99: ifeq +299 -> 398
    //   102: aload 16
    //   104: invokeinterface 339 1 0
    //   109: checkcast 262	java/lang/Integer
    //   112: invokevirtual 265	java/lang/Integer:intValue	()I
    //   115: istore 5
    //   117: aload 21
    //   119: iload 5
    //   121: invokestatic 342	java/lang/Integer:valueOf	(I)Ljava/lang/Integer;
    //   124: invokeinterface 151 2 0
    //   129: checkcast 344	com/google/android/gms/internal/zzcog
    //   132: astore 24
    //   134: aload 18
    //   136: iload 5
    //   138: invokestatic 342	java/lang/Integer:valueOf	(I)Ljava/lang/Integer;
    //   141: invokeinterface 151 2 0
    //   146: checkcast 346	java/util/BitSet
    //   149: astore 23
    //   151: aload 17
    //   153: iload 5
    //   155: invokestatic 342	java/lang/Integer:valueOf	(I)Ljava/lang/Integer;
    //   158: invokeinterface 151 2 0
    //   163: checkcast 346	java/util/BitSet
    //   166: astore 20
    //   168: aload 23
    //   170: astore 19
    //   172: aload 23
    //   174: ifnonnull +51 -> 225
    //   177: new 346	java/util/BitSet
    //   180: dup
    //   181: invokespecial 347	java/util/BitSet:<init>	()V
    //   184: astore 19
    //   186: aload 18
    //   188: iload 5
    //   190: invokestatic 342	java/lang/Integer:valueOf	(I)Ljava/lang/Integer;
    //   193: aload 19
    //   195: invokeinterface 123 3 0
    //   200: pop
    //   201: new 346	java/util/BitSet
    //   204: dup
    //   205: invokespecial 347	java/util/BitSet:<init>	()V
    //   208: astore 20
    //   210: aload 17
    //   212: iload 5
    //   214: invokestatic 342	java/lang/Integer:valueOf	(I)Ljava/lang/Integer;
    //   217: aload 20
    //   219: invokeinterface 123 3 0
    //   224: pop
    //   225: iconst_0
    //   226: istore 4
    //   228: iload 4
    //   230: aload 24
    //   232: getfield 350	com/google/android/gms/internal/zzcog:zza	[J
    //   235: arraylength
    //   236: bipush 6
    //   238: ishl
    //   239: if_icmpge +78 -> 317
    //   242: aload 24
    //   244: getfield 350	com/google/android/gms/internal/zzcog:zza	[J
    //   247: iload 4
    //   249: invokestatic 353	com/google/android/gms/internal/zzcnp:zza	([JI)Z
    //   252: ifeq +56 -> 308
    //   255: aload_0
    //   256: invokevirtual 76	com/google/android/gms/internal/zzcli:zzt	()Lcom/google/android/gms/internal/zzcjk;
    //   259: invokevirtual 195	com/google/android/gms/internal/zzcjk:zzae	()Lcom/google/android/gms/internal/zzcjm;
    //   262: ldc_w 355
    //   265: iload 5
    //   267: invokestatic 342	java/lang/Integer:valueOf	(I)Ljava/lang/Integer;
    //   270: iload 4
    //   272: invokestatic 342	java/lang/Integer:valueOf	(I)Ljava/lang/Integer;
    //   275: invokevirtual 136	com/google/android/gms/internal/zzcjm:zza	(Ljava/lang/String;Ljava/lang/Object;Ljava/lang/Object;)V
    //   278: aload 20
    //   280: iload 4
    //   282: invokevirtual 358	java/util/BitSet:set	(I)V
    //   285: aload 24
    //   287: getfield 360	com/google/android/gms/internal/zzcog:zzb	[J
    //   290: iload 4
    //   292: invokestatic 353	com/google/android/gms/internal/zzcnp:zza	([JI)Z
    //   295: ifeq +13 -> 308
    //   298: aload 19
    //   300: iload 4
    //   302: invokevirtual 358	java/util/BitSet:set	(I)V
    //   305: goto +3 -> 308
    //   308: iload 4
    //   310: iconst_1
    //   311: iadd
    //   312: istore 4
    //   314: goto -86 -> 228
    //   317: new 362	com/google/android/gms/internal/zzcob
    //   320: dup
    //   321: invokespecial 363	com/google/android/gms/internal/zzcob:<init>	()V
    //   324: astore 23
    //   326: aload 27
    //   328: iload 5
    //   330: invokestatic 342	java/lang/Integer:valueOf	(I)Ljava/lang/Integer;
    //   333: aload 23
    //   335: invokeinterface 123 3 0
    //   340: pop
    //   341: aload 23
    //   343: iconst_0
    //   344: invokestatic 50	java/lang/Boolean:valueOf	(Z)Ljava/lang/Boolean;
    //   347: putfield 365	com/google/android/gms/internal/zzcob:zzd	Ljava/lang/Boolean;
    //   350: aload 23
    //   352: aload 24
    //   354: putfield 368	com/google/android/gms/internal/zzcob:zzc	Lcom/google/android/gms/internal/zzcog;
    //   357: aload 23
    //   359: new 344	com/google/android/gms/internal/zzcog
    //   362: dup
    //   363: invokespecial 369	com/google/android/gms/internal/zzcog:<init>	()V
    //   366: putfield 371	com/google/android/gms/internal/zzcob:zzb	Lcom/google/android/gms/internal/zzcog;
    //   369: aload 23
    //   371: getfield 371	com/google/android/gms/internal/zzcob:zzb	Lcom/google/android/gms/internal/zzcog;
    //   374: aload 19
    //   376: invokestatic 374	com/google/android/gms/internal/zzcnp:zza	(Ljava/util/BitSet;)[J
    //   379: putfield 360	com/google/android/gms/internal/zzcog:zzb	[J
    //   382: aload 23
    //   384: getfield 371	com/google/android/gms/internal/zzcob:zzb	Lcom/google/android/gms/internal/zzcog;
    //   387: aload 20
    //   389: invokestatic 374	com/google/android/gms/internal/zzcnp:zza	(Ljava/util/BitSet;)[J
    //   392: putfield 350	com/google/android/gms/internal/zzcog:zza	[J
    //   395: goto -311 -> 84
    //   398: aload 20
    //   400: astore 16
    //   402: aload 19
    //   404: astore 17
    //   406: aload 22
    //   408: astore 26
    //   410: aload 27
    //   412: astore 24
    //   414: aload 15
    //   416: astore 25
    //   418: aload 16
    //   420: astore 23
    //   422: aload 17
    //   424: astore 21
    //   426: aload 28
    //   428: ifnull +1729 -> 2157
    //   431: new 106	android/support/v4/h/a
    //   434: dup
    //   435: invokespecial 107	android/support/v4/h/a:<init>	()V
    //   438: astore 21
    //   440: aload 28
    //   442: arraylength
    //   443: istore 5
    //   445: iconst_0
    //   446: istore 4
    //   448: aconst_null
    //   449: astore 23
    //   451: aconst_null
    //   452: astore 20
    //   454: lconst_0
    //   455: lstore 10
    //   457: aload 15
    //   459: astore 25
    //   461: aload 27
    //   463: astore 19
    //   465: aload 22
    //   467: astore 18
    //   469: aload 23
    //   471: astore 22
    //   473: aload 21
    //   475: astore 15
    //   477: aload_1
    //   478: astore 28
    //   480: aload 18
    //   482: astore 26
    //   484: aload 19
    //   486: astore 24
    //   488: aload 16
    //   490: astore 23
    //   492: aload 17
    //   494: astore 21
    //   496: iload 4
    //   498: iload 5
    //   500: if_icmpge +1657 -> 2157
    //   503: aload_2
    //   504: iload 4
    //   506: aaload
    //   507: astore 26
    //   509: aload 26
    //   511: getfield 377	com/google/android/gms/internal/zzcoc:zzb	Ljava/lang/String;
    //   514: astore 23
    //   516: aload 26
    //   518: getfield 380	com/google/android/gms/internal/zzcoc:zza	[Lcom/google/android/gms/internal/zzcod;
    //   521: astore 21
    //   523: aload_0
    //   524: invokevirtual 384	com/google/android/gms/internal/zzcli:zzv	()Lcom/google/android/gms/internal/zzcil;
    //   527: aload 28
    //   529: getstatic 390	com/google/android/gms/internal/zzcja:zzao	Lcom/google/android/gms/internal/zzcjb;
    //   532: invokevirtual 395	com/google/android/gms/internal/zzcil:zzc	(Ljava/lang/String;Lcom/google/android/gms/internal/zzcjb;)Z
    //   535: ifeq +742 -> 1277
    //   538: aload_0
    //   539: invokevirtual 399	com/google/android/gms/internal/zzcli:zzp	()Lcom/google/android/gms/internal/zzcnp;
    //   542: pop
    //   543: aload 26
    //   545: ldc_w 401
    //   548: invokestatic 404	com/google/android/gms/internal/zzcnp:zzb	(Lcom/google/android/gms/internal/zzcoc;Ljava/lang/String;)Ljava/lang/Object;
    //   551: checkcast 153	java/lang/Long
    //   554: astore 27
    //   556: aload 27
    //   558: ifnull +9 -> 567
    //   561: iconst_1
    //   562: istore 6
    //   564: goto +6 -> 570
    //   567: iconst_0
    //   568: istore 6
    //   570: iload 6
    //   572: ifeq +20 -> 592
    //   575: aload 23
    //   577: ldc_w 406
    //   580: invokevirtual 221	java/lang/String:equals	(Ljava/lang/Object;)Z
    //   583: ifeq +9 -> 592
    //   586: iconst_1
    //   587: istore 7
    //   589: goto +6 -> 595
    //   592: iconst_0
    //   593: istore 7
    //   595: iload 7
    //   597: ifeq +560 -> 1157
    //   600: aload_0
    //   601: invokevirtual 399	com/google/android/gms/internal/zzcli:zzp	()Lcom/google/android/gms/internal/zzcnp;
    //   604: pop
    //   605: aload 26
    //   607: ldc_w 408
    //   610: invokestatic 404	com/google/android/gms/internal/zzcnp:zzb	(Lcom/google/android/gms/internal/zzcoc;Ljava/lang/String;)Ljava/lang/Object;
    //   613: checkcast 173	java/lang/String
    //   616: astore 25
    //   618: aload 25
    //   620: invokestatic 70	android/text/TextUtils:isEmpty	(Ljava/lang/CharSequence;)Z
    //   623: ifeq +21 -> 644
    //   626: aload_0
    //   627: invokevirtual 76	com/google/android/gms/internal/zzcli:zzt	()Lcom/google/android/gms/internal/zzcjk;
    //   630: invokevirtual 411	com/google/android/gms/internal/zzcjk:zzy	()Lcom/google/android/gms/internal/zzcjm;
    //   633: ldc_w 413
    //   636: aload 27
    //   638: invokevirtual 98	com/google/android/gms/internal/zzcjm:zza	(Ljava/lang/String;Ljava/lang/Object;)V
    //   641: goto +486 -> 1127
    //   644: aload 20
    //   646: ifnull +40 -> 686
    //   649: aload 22
    //   651: ifnull +35 -> 686
    //   654: aload 27
    //   656: invokevirtual 161	java/lang/Long:longValue	()J
    //   659: aload 22
    //   661: invokevirtual 161	java/lang/Long:longValue	()J
    //   664: lcmp
    //   665: ifeq +6 -> 671
    //   668: goto +18 -> 686
    //   671: aload 22
    //   673: astore 23
    //   675: aload 20
    //   677: astore 22
    //   679: aload 23
    //   681: astore 20
    //   683: goto +73 -> 756
    //   686: aload_0
    //   687: invokevirtual 317	com/google/android/gms/internal/zzcli:zzn	()Lcom/google/android/gms/internal/zzcim;
    //   690: aload 28
    //   692: aload 27
    //   694: invokevirtual 416	com/google/android/gms/internal/zzcim:zza	(Ljava/lang/String;Ljava/lang/Long;)Landroid/util/Pair;
    //   697: astore 23
    //   699: aload 23
    //   701: ifnull +409 -> 1110
    //   704: aload 23
    //   706: getfield 422	android/util/Pair:first	Ljava/lang/Object;
    //   709: ifnonnull +6 -> 715
    //   712: goto +398 -> 1110
    //   715: aload 23
    //   717: getfield 422	android/util/Pair:first	Ljava/lang/Object;
    //   720: checkcast 376	com/google/android/gms/internal/zzcoc
    //   723: astore 22
    //   725: aload 23
    //   727: getfield 425	android/util/Pair:second	Ljava/lang/Object;
    //   730: checkcast 153	java/lang/Long
    //   733: invokevirtual 161	java/lang/Long:longValue	()J
    //   736: lstore 10
    //   738: aload_0
    //   739: invokevirtual 399	com/google/android/gms/internal/zzcli:zzp	()Lcom/google/android/gms/internal/zzcnp;
    //   742: pop
    //   743: aload 22
    //   745: ldc_w 401
    //   748: invokestatic 404	com/google/android/gms/internal/zzcnp:zzb	(Lcom/google/android/gms/internal/zzcoc;Ljava/lang/String;)Ljava/lang/Object;
    //   751: checkcast 153	java/lang/Long
    //   754: astore 20
    //   756: lload 10
    //   758: lconst_1
    //   759: lsub
    //   760: lstore 10
    //   762: lload 10
    //   764: lconst_0
    //   765: lcmp
    //   766: ifgt +95 -> 861
    //   769: aload_0
    //   770: invokevirtual 317	com/google/android/gms/internal/zzcli:zzn	()Lcom/google/android/gms/internal/zzcim;
    //   773: astore 24
    //   775: aload 24
    //   777: invokevirtual 427	com/google/android/gms/internal/zzcli:zzc	()V
    //   780: aload 24
    //   782: invokevirtual 76	com/google/android/gms/internal/zzcli:zzt	()Lcom/google/android/gms/internal/zzcjk;
    //   785: invokevirtual 195	com/google/android/gms/internal/zzcjk:zzae	()Lcom/google/android/gms/internal/zzcjm;
    //   788: ldc_w 429
    //   791: aload 28
    //   793: invokevirtual 98	com/google/android/gms/internal/zzcjm:zza	(Ljava/lang/String;Ljava/lang/Object;)V
    //   796: aload 24
    //   798: invokevirtual 432	com/google/android/gms/internal/zzcim:zzaa	()Landroid/database/sqlite/SQLiteDatabase;
    //   801: astore 23
    //   803: aload 23
    //   805: ldc_w 434
    //   808: iconst_1
    //   809: anewarray 173	java/lang/String
    //   812: dup
    //   813: iconst_0
    //   814: aload 28
    //   816: aastore
    //   817: invokevirtual 440	android/database/sqlite/SQLiteDatabase:execSQL	(Ljava/lang/String;[Ljava/lang/Object;)V
    //   820: goto +30 -> 850
    //   823: astore 23
    //   825: goto +9 -> 834
    //   828: astore_1
    //   829: goto +5 -> 834
    //   832: astore 23
    //   834: aload 24
    //   836: invokevirtual 76	com/google/android/gms/internal/zzcli:zzt	()Lcom/google/android/gms/internal/zzcjk;
    //   839: invokevirtual 411	com/google/android/gms/internal/zzcjk:zzy	()Lcom/google/android/gms/internal/zzcjm;
    //   842: ldc_w 442
    //   845: aload 23
    //   847: invokevirtual 98	com/google/android/gms/internal/zzcjm:zza	(Ljava/lang/String;Ljava/lang/Object;)V
    //   850: aload 15
    //   852: astore 24
    //   854: aload 21
    //   856: astore 15
    //   858: goto +31 -> 889
    //   861: aload_0
    //   862: invokevirtual 317	com/google/android/gms/internal/zzcli:zzn	()Lcom/google/android/gms/internal/zzcim;
    //   865: astore 23
    //   867: aload 23
    //   869: aload 28
    //   871: aload 27
    //   873: lload 10
    //   875: aload 22
    //   877: invokevirtual 445	com/google/android/gms/internal/zzcim:zza	(Ljava/lang/String;Ljava/lang/Long;JLcom/google/android/gms/internal/zzcoc;)Z
    //   880: pop
    //   881: aload 15
    //   883: astore 24
    //   885: aload 21
    //   887: astore 15
    //   889: iload 4
    //   891: istore 6
    //   893: aload 22
    //   895: getfield 380	com/google/android/gms/internal/zzcoc:zza	[Lcom/google/android/gms/internal/zzcod;
    //   898: arraylength
    //   899: aload 15
    //   901: arraylength
    //   902: iadd
    //   903: anewarray 109	com/google/android/gms/internal/zzcod
    //   906: astore 21
    //   908: aload 22
    //   910: getfield 380	com/google/android/gms/internal/zzcoc:zza	[Lcom/google/android/gms/internal/zzcod;
    //   913: astore 23
    //   915: aload 23
    //   917: arraylength
    //   918: istore 9
    //   920: iconst_0
    //   921: istore 7
    //   923: iload 7
    //   925: istore 4
    //   927: iload 7
    //   929: iload 9
    //   931: if_icmpge +58 -> 989
    //   934: aload 23
    //   936: iload 7
    //   938: aaload
    //   939: astore 27
    //   941: aload_0
    //   942: invokevirtual 399	com/google/android/gms/internal/zzcli:zzp	()Lcom/google/android/gms/internal/zzcnp;
    //   945: pop
    //   946: iload 4
    //   948: istore 8
    //   950: aload 26
    //   952: aload 27
    //   954: getfield 111	com/google/android/gms/internal/zzcod:zza	Ljava/lang/String;
    //   957: invokestatic 448	com/google/android/gms/internal/zzcnp:zza	(Lcom/google/android/gms/internal/zzcoc;Ljava/lang/String;)Lcom/google/android/gms/internal/zzcod;
    //   960: ifnonnull +16 -> 976
    //   963: aload 21
    //   965: iload 4
    //   967: aload 27
    //   969: aastore
    //   970: iload 4
    //   972: iconst_1
    //   973: iadd
    //   974: istore 8
    //   976: iload 7
    //   978: iconst_1
    //   979: iadd
    //   980: istore 7
    //   982: iload 8
    //   984: istore 4
    //   986: goto -59 -> 927
    //   989: iload 4
    //   991: ifle +77 -> 1068
    //   994: aload 15
    //   996: arraylength
    //   997: istore 8
    //   999: iconst_0
    //   1000: istore 7
    //   1002: iload 7
    //   1004: iload 8
    //   1006: if_icmpge +28 -> 1034
    //   1009: aload 21
    //   1011: iload 4
    //   1013: aload 15
    //   1015: iload 7
    //   1017: aaload
    //   1018: aastore
    //   1019: iload 7
    //   1021: iconst_1
    //   1022: iadd
    //   1023: istore 7
    //   1025: iload 4
    //   1027: iconst_1
    //   1028: iadd
    //   1029: istore 4
    //   1031: goto -29 -> 1002
    //   1034: iload 4
    //   1036: aload 21
    //   1038: arraylength
    //   1039: if_icmpne +10 -> 1049
    //   1042: aload 21
    //   1044: astore 15
    //   1046: goto +15 -> 1061
    //   1049: aload 21
    //   1051: iload 4
    //   1053: invokestatic 452	java/util/Arrays:copyOf	([Ljava/lang/Object;I)[Ljava/lang/Object;
    //   1056: checkcast 453	[Lcom/google/android/gms/internal/zzcod;
    //   1059: astore 15
    //   1061: aload 15
    //   1063: astore 23
    //   1065: goto +22 -> 1087
    //   1068: aload_0
    //   1069: invokevirtual 76	com/google/android/gms/internal/zzcli:zzt	()Lcom/google/android/gms/internal/zzcjk;
    //   1072: invokevirtual 82	com/google/android/gms/internal/zzcjk:zzaa	()Lcom/google/android/gms/internal/zzcjm;
    //   1075: ldc_w 455
    //   1078: aload 25
    //   1080: invokevirtual 98	com/google/android/gms/internal/zzcjm:zza	(Ljava/lang/String;Ljava/lang/Object;)V
    //   1083: aload 15
    //   1085: astore 23
    //   1087: aload 25
    //   1089: astore 15
    //   1091: aload 20
    //   1093: astore 21
    //   1095: iload 6
    //   1097: istore 4
    //   1099: aload 22
    //   1101: astore 20
    //   1103: aload 24
    //   1105: astore 22
    //   1107: goto +194 -> 1301
    //   1110: aload_0
    //   1111: invokevirtual 76	com/google/android/gms/internal/zzcli:zzt	()Lcom/google/android/gms/internal/zzcjk;
    //   1114: invokevirtual 411	com/google/android/gms/internal/zzcjk:zzy	()Lcom/google/android/gms/internal/zzcjm;
    //   1117: ldc_w 457
    //   1120: aload 25
    //   1122: aload 27
    //   1124: invokevirtual 136	com/google/android/gms/internal/zzcjm:zza	(Ljava/lang/String;Ljava/lang/Object;Ljava/lang/Object;)V
    //   1127: aload 18
    //   1129: astore 21
    //   1131: aload 19
    //   1133: astore 23
    //   1135: aload 16
    //   1137: astore 18
    //   1139: aload 17
    //   1141: astore 16
    //   1143: aload 15
    //   1145: astore 19
    //   1147: aload_3
    //   1148: astore 15
    //   1150: aload 23
    //   1152: astore 17
    //   1154: goto +958 -> 2112
    //   1157: aload 15
    //   1159: astore 24
    //   1161: iload 6
    //   1163: ifeq +111 -> 1274
    //   1166: aload_0
    //   1167: invokevirtual 399	com/google/android/gms/internal/zzcli:zzp	()Lcom/google/android/gms/internal/zzcnp;
    //   1170: pop
    //   1171: aload 26
    //   1173: ldc_w 459
    //   1176: invokestatic 404	com/google/android/gms/internal/zzcnp:zzb	(Lcom/google/android/gms/internal/zzcoc;Ljava/lang/String;)Ljava/lang/Object;
    //   1179: astore 20
    //   1181: aload 20
    //   1183: astore 15
    //   1185: aload 20
    //   1187: ifnonnull +9 -> 1196
    //   1190: lconst_0
    //   1191: invokestatic 462	java/lang/Long:valueOf	(J)Ljava/lang/Long;
    //   1194: astore 15
    //   1196: aload 15
    //   1198: checkcast 153	java/lang/Long
    //   1201: invokevirtual 161	java/lang/Long:longValue	()J
    //   1204: lstore 10
    //   1206: lload 10
    //   1208: lconst_0
    //   1209: lcmp
    //   1210: ifgt +21 -> 1231
    //   1213: aload_0
    //   1214: invokevirtual 76	com/google/android/gms/internal/zzcli:zzt	()Lcom/google/android/gms/internal/zzcjk;
    //   1217: invokevirtual 82	com/google/android/gms/internal/zzcjk:zzaa	()Lcom/google/android/gms/internal/zzcjm;
    //   1220: ldc_w 464
    //   1223: aload 23
    //   1225: invokevirtual 98	com/google/android/gms/internal/zzcjm:zza	(Ljava/lang/String;Ljava/lang/Object;)V
    //   1228: goto +19 -> 1247
    //   1231: aload_0
    //   1232: invokevirtual 317	com/google/android/gms/internal/zzcli:zzn	()Lcom/google/android/gms/internal/zzcim;
    //   1235: aload 28
    //   1237: aload 27
    //   1239: lload 10
    //   1241: aload 26
    //   1243: invokevirtual 445	com/google/android/gms/internal/zzcim:zza	(Ljava/lang/String;Ljava/lang/Long;JLcom/google/android/gms/internal/zzcoc;)Z
    //   1246: pop
    //   1247: aload 27
    //   1249: astore 22
    //   1251: aload 26
    //   1253: astore 20
    //   1255: aload 23
    //   1257: astore 15
    //   1259: aload 21
    //   1261: astore 23
    //   1263: aload 22
    //   1265: astore 21
    //   1267: aload 24
    //   1269: astore 22
    //   1271: goto +30 -> 1301
    //   1274: goto +3 -> 1277
    //   1277: aload 15
    //   1279: astore 25
    //   1281: aload 22
    //   1283: astore 24
    //   1285: aload 23
    //   1287: astore 15
    //   1289: aload 25
    //   1291: astore 22
    //   1293: aload 21
    //   1295: astore 23
    //   1297: aload 24
    //   1299: astore 21
    //   1301: aload_0
    //   1302: invokevirtual 317	com/google/android/gms/internal/zzcli:zzn	()Lcom/google/android/gms/internal/zzcim;
    //   1305: aload 28
    //   1307: aload 26
    //   1309: getfield 377	com/google/android/gms/internal/zzcoc:zzb	Ljava/lang/String;
    //   1312: invokevirtual 467	com/google/android/gms/internal/zzcim:zza	(Ljava/lang/String;Ljava/lang/String;)Lcom/google/android/gms/internal/zzciu;
    //   1315: astore 24
    //   1317: aload 24
    //   1319: ifnonnull +62 -> 1381
    //   1322: aload_0
    //   1323: invokevirtual 76	com/google/android/gms/internal/zzcli:zzt	()Lcom/google/android/gms/internal/zzcjk;
    //   1326: invokevirtual 82	com/google/android/gms/internal/zzcjk:zzaa	()Lcom/google/android/gms/internal/zzcjm;
    //   1329: ldc_w 469
    //   1332: aload_1
    //   1333: invokestatic 472	com/google/android/gms/internal/zzcjk:zza	(Ljava/lang/String;)Ljava/lang/Object;
    //   1336: aload_0
    //   1337: invokevirtual 88	com/google/android/gms/internal/zzcli:zzo	()Lcom/google/android/gms/internal/zzcji;
    //   1340: aload 15
    //   1342: invokevirtual 93	com/google/android/gms/internal/zzcji:zza	(Ljava/lang/String;)Ljava/lang/String;
    //   1345: invokevirtual 136	com/google/android/gms/internal/zzcjm:zza	(Ljava/lang/String;Ljava/lang/Object;Ljava/lang/Object;)V
    //   1348: new 474	com/google/android/gms/internal/zzciu
    //   1351: dup
    //   1352: aload 28
    //   1354: aload 26
    //   1356: getfield 377	com/google/android/gms/internal/zzcoc:zzb	Ljava/lang/String;
    //   1359: lconst_1
    //   1360: lconst_1
    //   1361: aload 26
    //   1363: getfield 475	com/google/android/gms/internal/zzcoc:zzc	Ljava/lang/Long;
    //   1366: invokevirtual 161	java/lang/Long:longValue	()J
    //   1369: lconst_0
    //   1370: aconst_null
    //   1371: aconst_null
    //   1372: aconst_null
    //   1373: invokespecial 478	com/google/android/gms/internal/zzciu:<init>	(Ljava/lang/String;Ljava/lang/String;JJJJLjava/lang/Long;Ljava/lang/Long;Ljava/lang/Boolean;)V
    //   1376: astore 27
    //   1378: goto +10 -> 1388
    //   1381: aload 24
    //   1383: invokevirtual 481	com/google/android/gms/internal/zzciu:zza	()Lcom/google/android/gms/internal/zzciu;
    //   1386: astore 27
    //   1388: aload 18
    //   1390: astore 26
    //   1392: aload 17
    //   1394: astore 18
    //   1396: aload 16
    //   1398: astore 24
    //   1400: aload_3
    //   1401: astore 25
    //   1403: aload_0
    //   1404: invokevirtual 317	com/google/android/gms/internal/zzcli:zzn	()Lcom/google/android/gms/internal/zzcim;
    //   1407: aload 27
    //   1409: invokevirtual 484	com/google/android/gms/internal/zzcim:zza	(Lcom/google/android/gms/internal/zzciu;)V
    //   1412: aload 27
    //   1414: getfield 487	com/google/android/gms/internal/zzciu:zzc	J
    //   1417: lstore 12
    //   1419: aload 22
    //   1421: aload 15
    //   1423: invokeinterface 151 2 0
    //   1428: checkcast 119	java/util/Map
    //   1431: astore 17
    //   1433: aload 17
    //   1435: astore 16
    //   1437: aload 17
    //   1439: ifnonnull +46 -> 1485
    //   1442: aload_0
    //   1443: invokevirtual 317	com/google/android/gms/internal/zzcli:zzn	()Lcom/google/android/gms/internal/zzcim;
    //   1446: aload 28
    //   1448: aload 15
    //   1450: invokevirtual 491	com/google/android/gms/internal/zzcim:zzf	(Ljava/lang/String;Ljava/lang/String;)Ljava/util/Map;
    //   1453: astore 17
    //   1455: aload 17
    //   1457: astore 16
    //   1459: aload 17
    //   1461: ifnonnull +12 -> 1473
    //   1464: new 106	android/support/v4/h/a
    //   1467: dup
    //   1468: invokespecial 107	android/support/v4/h/a:<init>	()V
    //   1471: astore 16
    //   1473: aload 22
    //   1475: aload 15
    //   1477: aload 16
    //   1479: invokeinterface 123 3 0
    //   1484: pop
    //   1485: aload 16
    //   1487: astore 27
    //   1489: aload 27
    //   1491: invokeinterface 326 1 0
    //   1496: invokeinterface 330 1 0
    //   1501: astore 28
    //   1503: aload 26
    //   1505: astore 17
    //   1507: aload 24
    //   1509: astore 16
    //   1511: aload 28
    //   1513: astore 24
    //   1515: aload 27
    //   1517: astore 26
    //   1519: aload 15
    //   1521: astore 28
    //   1523: aload 24
    //   1525: invokeinterface 335 1 0
    //   1530: ifeq +542 -> 2072
    //   1533: aload 24
    //   1535: invokeinterface 339 1 0
    //   1540: checkcast 262	java/lang/Integer
    //   1543: invokevirtual 265	java/lang/Integer:intValue	()I
    //   1546: istore 6
    //   1548: aload 17
    //   1550: iload 6
    //   1552: invokestatic 342	java/lang/Integer:valueOf	(I)Ljava/lang/Integer;
    //   1555: invokeinterface 114 2 0
    //   1560: ifeq +24 -> 1584
    //   1563: aload_0
    //   1564: invokevirtual 76	com/google/android/gms/internal/zzcli:zzt	()Lcom/google/android/gms/internal/zzcjk;
    //   1567: invokevirtual 195	com/google/android/gms/internal/zzcjk:zzae	()Lcom/google/android/gms/internal/zzcjm;
    //   1570: ldc_w 493
    //   1573: iload 6
    //   1575: invokestatic 342	java/lang/Integer:valueOf	(I)Ljava/lang/Integer;
    //   1578: invokevirtual 98	com/google/android/gms/internal/zzcjm:zza	(Ljava/lang/String;Ljava/lang/Object;)V
    //   1581: goto -58 -> 1523
    //   1584: aload 19
    //   1586: iload 6
    //   1588: invokestatic 342	java/lang/Integer:valueOf	(I)Ljava/lang/Integer;
    //   1591: invokeinterface 151 2 0
    //   1596: checkcast 362	com/google/android/gms/internal/zzcob
    //   1599: astore 29
    //   1601: aload 18
    //   1603: astore 15
    //   1605: aload 15
    //   1607: iload 6
    //   1609: invokestatic 342	java/lang/Integer:valueOf	(I)Ljava/lang/Integer;
    //   1612: invokeinterface 151 2 0
    //   1617: checkcast 346	java/util/BitSet
    //   1620: astore 27
    //   1622: aload 16
    //   1624: iload 6
    //   1626: invokestatic 342	java/lang/Integer:valueOf	(I)Ljava/lang/Integer;
    //   1629: invokeinterface 151 2 0
    //   1634: checkcast 346	java/util/BitSet
    //   1637: astore 18
    //   1639: aload 29
    //   1641: ifnonnull +84 -> 1725
    //   1644: new 362	com/google/android/gms/internal/zzcob
    //   1647: dup
    //   1648: invokespecial 363	com/google/android/gms/internal/zzcob:<init>	()V
    //   1651: astore 18
    //   1653: aload 19
    //   1655: iload 6
    //   1657: invokestatic 342	java/lang/Integer:valueOf	(I)Ljava/lang/Integer;
    //   1660: aload 18
    //   1662: invokeinterface 123 3 0
    //   1667: pop
    //   1668: aload 18
    //   1670: iconst_1
    //   1671: invokestatic 50	java/lang/Boolean:valueOf	(Z)Ljava/lang/Boolean;
    //   1674: putfield 365	com/google/android/gms/internal/zzcob:zzd	Ljava/lang/Boolean;
    //   1677: new 346	java/util/BitSet
    //   1680: dup
    //   1681: invokespecial 347	java/util/BitSet:<init>	()V
    //   1684: astore 27
    //   1686: aload 15
    //   1688: iload 6
    //   1690: invokestatic 342	java/lang/Integer:valueOf	(I)Ljava/lang/Integer;
    //   1693: aload 27
    //   1695: invokeinterface 123 3 0
    //   1700: pop
    //   1701: new 346	java/util/BitSet
    //   1704: dup
    //   1705: invokespecial 347	java/util/BitSet:<init>	()V
    //   1708: astore 18
    //   1710: aload 16
    //   1712: iload 6
    //   1714: invokestatic 342	java/lang/Integer:valueOf	(I)Ljava/lang/Integer;
    //   1717: aload 18
    //   1719: invokeinterface 123 3 0
    //   1724: pop
    //   1725: aload 26
    //   1727: iload 6
    //   1729: invokestatic 342	java/lang/Integer:valueOf	(I)Ljava/lang/Integer;
    //   1732: invokeinterface 151 2 0
    //   1737: checkcast 205	java/util/List
    //   1740: invokeinterface 494 1 0
    //   1745: astore 30
    //   1747: aload 27
    //   1749: astore 29
    //   1751: aload 25
    //   1753: astore 27
    //   1755: aload 30
    //   1757: astore 25
    //   1759: aload 25
    //   1761: invokeinterface 335 1 0
    //   1766: ifeq +295 -> 2061
    //   1769: aload 25
    //   1771: invokeinterface 339 1 0
    //   1776: checkcast 34	com/google/android/gms/internal/zzcnt
    //   1779: astore 31
    //   1781: aload_0
    //   1782: invokevirtual 76	com/google/android/gms/internal/zzcli:zzt	()Lcom/google/android/gms/internal/zzcjk;
    //   1785: iconst_2
    //   1786: invokevirtual 497	com/google/android/gms/internal/zzcjk:zza	(I)Z
    //   1789: ifeq +63 -> 1852
    //   1792: aload_0
    //   1793: invokevirtual 76	com/google/android/gms/internal/zzcli:zzt	()Lcom/google/android/gms/internal/zzcjk;
    //   1796: invokevirtual 195	com/google/android/gms/internal/zzcjk:zzae	()Lcom/google/android/gms/internal/zzcjm;
    //   1799: ldc_w 499
    //   1802: iload 6
    //   1804: invokestatic 342	java/lang/Integer:valueOf	(I)Ljava/lang/Integer;
    //   1807: aload 31
    //   1809: getfield 500	com/google/android/gms/internal/zzcnt:zza	Ljava/lang/Integer;
    //   1812: aload_0
    //   1813: invokevirtual 88	com/google/android/gms/internal/zzcli:zzo	()Lcom/google/android/gms/internal/zzcji;
    //   1816: aload 31
    //   1818: getfield 501	com/google/android/gms/internal/zzcnt:zzb	Ljava/lang/String;
    //   1821: invokevirtual 93	com/google/android/gms/internal/zzcji:zza	(Ljava/lang/String;)Ljava/lang/String;
    //   1824: invokevirtual 504	com/google/android/gms/internal/zzcjm:zza	(Ljava/lang/String;Ljava/lang/Object;Ljava/lang/Object;Ljava/lang/Object;)V
    //   1827: aload_0
    //   1828: invokevirtual 76	com/google/android/gms/internal/zzcli:zzt	()Lcom/google/android/gms/internal/zzcjk;
    //   1831: invokevirtual 195	com/google/android/gms/internal/zzcjk:zzae	()Lcom/google/android/gms/internal/zzcjm;
    //   1834: ldc_w 506
    //   1837: aload_0
    //   1838: invokevirtual 88	com/google/android/gms/internal/zzcli:zzo	()Lcom/google/android/gms/internal/zzcji;
    //   1841: aload 31
    //   1843: invokevirtual 509	com/google/android/gms/internal/zzcji:zza	(Lcom/google/android/gms/internal/zzcnt;)Ljava/lang/String;
    //   1846: invokevirtual 98	com/google/android/gms/internal/zzcjm:zza	(Ljava/lang/String;Ljava/lang/Object;)V
    //   1849: goto +3 -> 1852
    //   1852: aload 31
    //   1854: getfield 500	com/google/android/gms/internal/zzcnt:zza	Ljava/lang/Integer;
    //   1857: ifnull +173 -> 2030
    //   1860: aload 31
    //   1862: getfield 500	com/google/android/gms/internal/zzcnt:zza	Ljava/lang/Integer;
    //   1865: invokevirtual 265	java/lang/Integer:intValue	()I
    //   1868: sipush 256
    //   1871: if_icmple +6 -> 1877
    //   1874: goto +156 -> 2030
    //   1877: aload 29
    //   1879: aload 31
    //   1881: getfield 500	com/google/android/gms/internal/zzcnt:zza	Ljava/lang/Integer;
    //   1884: invokevirtual 265	java/lang/Integer:intValue	()I
    //   1887: invokevirtual 511	java/util/BitSet:get	(I)Z
    //   1890: ifeq +32 -> 1922
    //   1893: aload_0
    //   1894: invokevirtual 76	com/google/android/gms/internal/zzcli:zzt	()Lcom/google/android/gms/internal/zzcjk;
    //   1897: invokevirtual 195	com/google/android/gms/internal/zzcjk:zzae	()Lcom/google/android/gms/internal/zzcjm;
    //   1900: ldc_w 513
    //   1903: iload 6
    //   1905: invokestatic 342	java/lang/Integer:valueOf	(I)Ljava/lang/Integer;
    //   1908: aload 31
    //   1910: getfield 500	com/google/android/gms/internal/zzcnt:zza	Ljava/lang/Integer;
    //   1913: invokevirtual 136	com/google/android/gms/internal/zzcjm:zza	(Ljava/lang/String;Ljava/lang/Object;Ljava/lang/Object;)V
    //   1916: aload_3
    //   1917: astore 27
    //   1919: goto -160 -> 1759
    //   1922: aload_0
    //   1923: aload 31
    //   1925: aload 28
    //   1927: aload 23
    //   1929: lload 12
    //   1931: invokespecial 515	com/google/android/gms/internal/zzcii:zza	(Lcom/google/android/gms/internal/zzcnt;Ljava/lang/String;[Lcom/google/android/gms/internal/zzcod;J)Ljava/lang/Boolean;
    //   1934: astore 30
    //   1936: aload_0
    //   1937: invokevirtual 76	com/google/android/gms/internal/zzcli:zzt	()Lcom/google/android/gms/internal/zzcjk;
    //   1940: invokevirtual 195	com/google/android/gms/internal/zzcjk:zzae	()Lcom/google/android/gms/internal/zzcjm;
    //   1943: astore 32
    //   1945: aload 30
    //   1947: ifnonnull +11 -> 1958
    //   1950: ldc_w 517
    //   1953: astore 27
    //   1955: goto +7 -> 1962
    //   1958: aload 30
    //   1960: astore 27
    //   1962: aload 32
    //   1964: ldc_w 519
    //   1967: aload 27
    //   1969: invokevirtual 98	com/google/android/gms/internal/zzcjm:zza	(Ljava/lang/String;Ljava/lang/Object;)V
    //   1972: aload 30
    //   1974: ifnonnull +19 -> 1993
    //   1977: aload 17
    //   1979: iload 6
    //   1981: invokestatic 342	java/lang/Integer:valueOf	(I)Ljava/lang/Integer;
    //   1984: invokeinterface 104 2 0
    //   1989: pop
    //   1990: goto +65 -> 2055
    //   1993: aload 18
    //   1995: aload 31
    //   1997: getfield 500	com/google/android/gms/internal/zzcnt:zza	Ljava/lang/Integer;
    //   2000: invokevirtual 265	java/lang/Integer:intValue	()I
    //   2003: invokevirtual 358	java/util/BitSet:set	(I)V
    //   2006: aload 30
    //   2008: invokevirtual 46	java/lang/Boolean:booleanValue	()Z
    //   2011: ifeq +44 -> 2055
    //   2014: aload 29
    //   2016: aload 31
    //   2018: getfield 500	com/google/android/gms/internal/zzcnt:zza	Ljava/lang/Integer;
    //   2021: invokevirtual 265	java/lang/Integer:intValue	()I
    //   2024: invokevirtual 358	java/util/BitSet:set	(I)V
    //   2027: goto +28 -> 2055
    //   2030: aload_0
    //   2031: invokevirtual 76	com/google/android/gms/internal/zzcli:zzt	()Lcom/google/android/gms/internal/zzcjk;
    //   2034: invokevirtual 82	com/google/android/gms/internal/zzcjk:zzaa	()Lcom/google/android/gms/internal/zzcjm;
    //   2037: ldc_w 521
    //   2040: aload_1
    //   2041: invokestatic 472	com/google/android/gms/internal/zzcjk:zza	(Ljava/lang/String;)Ljava/lang/Object;
    //   2044: aload 31
    //   2046: getfield 500	com/google/android/gms/internal/zzcnt:zza	Ljava/lang/Integer;
    //   2049: invokestatic 524	java/lang/String:valueOf	(Ljava/lang/Object;)Ljava/lang/String;
    //   2052: invokevirtual 136	com/google/android/gms/internal/zzcjm:zza	(Ljava/lang/String;Ljava/lang/Object;Ljava/lang/Object;)V
    //   2055: aload_3
    //   2056: astore 27
    //   2058: goto -299 -> 1759
    //   2061: aload 27
    //   2063: astore 25
    //   2065: aload 15
    //   2067: astore 18
    //   2069: goto -546 -> 1523
    //   2072: aload 16
    //   2074: astore 23
    //   2076: aload 18
    //   2078: astore 16
    //   2080: aload 17
    //   2082: astore 15
    //   2084: aload 19
    //   2086: astore 17
    //   2088: aload 21
    //   2090: astore 24
    //   2092: aload 23
    //   2094: astore 18
    //   2096: aload 22
    //   2098: astore 19
    //   2100: aload 15
    //   2102: astore 21
    //   2104: aload 25
    //   2106: astore 15
    //   2108: aload 24
    //   2110: astore 22
    //   2112: iload 4
    //   2114: iconst_1
    //   2115: iadd
    //   2116: istore 4
    //   2118: aload 21
    //   2120: astore 23
    //   2122: aload 19
    //   2124: astore 24
    //   2126: aload 18
    //   2128: astore 21
    //   2130: aload 17
    //   2132: astore 19
    //   2134: aload 16
    //   2136: astore 17
    //   2138: aload 15
    //   2140: astore 25
    //   2142: aload 24
    //   2144: astore 15
    //   2146: aload 23
    //   2148: astore 18
    //   2150: aload 21
    //   2152: astore 16
    //   2154: goto -1677 -> 477
    //   2157: aload 24
    //   2159: astore 16
    //   2161: aload 23
    //   2163: astore_2
    //   2164: aload 21
    //   2166: astore 15
    //   2168: aload_2
    //   2169: astore 18
    //   2171: aload 16
    //   2173: astore 17
    //   2175: aload 15
    //   2177: astore 19
    //   2179: aload 25
    //   2181: ifnull +1012 -> 3193
    //   2184: new 106	android/support/v4/h/a
    //   2187: dup
    //   2188: invokespecial 107	android/support/v4/h/a:<init>	()V
    //   2191: astore 20
    //   2193: aload 25
    //   2195: arraylength
    //   2196: istore 4
    //   2198: iconst_0
    //   2199: istore 5
    //   2201: aload_2
    //   2202: astore 18
    //   2204: aload 16
    //   2206: astore 17
    //   2208: aload 15
    //   2210: astore 19
    //   2212: iload 5
    //   2214: iload 4
    //   2216: if_icmpge +977 -> 3193
    //   2219: aload 25
    //   2221: iload 5
    //   2223: aaload
    //   2224: astore 25
    //   2226: aload 20
    //   2228: aload 25
    //   2230: getfield 527	com/google/android/gms/internal/zzcoh:zzb	Ljava/lang/String;
    //   2233: invokeinterface 151 2 0
    //   2238: checkcast 119	java/util/Map
    //   2241: astore 19
    //   2243: aload 19
    //   2245: ifnonnull +54 -> 2299
    //   2248: aload_0
    //   2249: invokevirtual 317	com/google/android/gms/internal/zzcli:zzn	()Lcom/google/android/gms/internal/zzcim;
    //   2252: aload_1
    //   2253: aload 25
    //   2255: getfield 527	com/google/android/gms/internal/zzcoh:zzb	Ljava/lang/String;
    //   2258: invokevirtual 530	com/google/android/gms/internal/zzcim:zzg	(Ljava/lang/String;Ljava/lang/String;)Ljava/util/Map;
    //   2261: astore 17
    //   2263: aload 17
    //   2265: astore 19
    //   2267: aload 17
    //   2269: ifnonnull +12 -> 2281
    //   2272: new 106	android/support/v4/h/a
    //   2275: dup
    //   2276: invokespecial 107	android/support/v4/h/a:<init>	()V
    //   2279: astore 19
    //   2281: aload 20
    //   2283: aload 25
    //   2285: getfield 527	com/google/android/gms/internal/zzcoh:zzb	Ljava/lang/String;
    //   2288: aload 19
    //   2290: invokeinterface 123 3 0
    //   2295: pop
    //   2296: goto +3 -> 2299
    //   2299: aload 19
    //   2301: invokeinterface 326 1 0
    //   2306: invokeinterface 330 1 0
    //   2311: astore 18
    //   2313: aload 20
    //   2315: astore 17
    //   2317: aload 18
    //   2319: invokeinterface 335 1 0
    //   2324: ifeq +853 -> 3177
    //   2327: aload 18
    //   2329: invokeinterface 339 1 0
    //   2334: checkcast 262	java/lang/Integer
    //   2337: invokevirtual 265	java/lang/Integer:intValue	()I
    //   2340: istore 6
    //   2342: aload 26
    //   2344: iload 6
    //   2346: invokestatic 342	java/lang/Integer:valueOf	(I)Ljava/lang/Integer;
    //   2349: invokeinterface 114 2 0
    //   2354: ifeq +24 -> 2378
    //   2357: aload_0
    //   2358: invokevirtual 76	com/google/android/gms/internal/zzcli:zzt	()Lcom/google/android/gms/internal/zzcjk;
    //   2361: invokevirtual 195	com/google/android/gms/internal/zzcjk:zzae	()Lcom/google/android/gms/internal/zzcjm;
    //   2364: ldc_w 493
    //   2367: iload 6
    //   2369: invokestatic 342	java/lang/Integer:valueOf	(I)Ljava/lang/Integer;
    //   2372: invokevirtual 98	com/google/android/gms/internal/zzcjm:zza	(Ljava/lang/String;Ljava/lang/Object;)V
    //   2375: goto -58 -> 2317
    //   2378: aload 16
    //   2380: astore 20
    //   2382: aload 20
    //   2384: iload 6
    //   2386: invokestatic 342	java/lang/Integer:valueOf	(I)Ljava/lang/Integer;
    //   2389: invokeinterface 151 2 0
    //   2394: checkcast 362	com/google/android/gms/internal/zzcob
    //   2397: astore 16
    //   2399: aload 15
    //   2401: iload 6
    //   2403: invokestatic 342	java/lang/Integer:valueOf	(I)Ljava/lang/Integer;
    //   2406: invokeinterface 151 2 0
    //   2411: checkcast 346	java/util/BitSet
    //   2414: astore 23
    //   2416: aload_2
    //   2417: iload 6
    //   2419: invokestatic 342	java/lang/Integer:valueOf	(I)Ljava/lang/Integer;
    //   2422: invokeinterface 151 2 0
    //   2427: checkcast 346	java/util/BitSet
    //   2430: astore 22
    //   2432: aload 16
    //   2434: ifnonnull +83 -> 2517
    //   2437: new 362	com/google/android/gms/internal/zzcob
    //   2440: dup
    //   2441: invokespecial 363	com/google/android/gms/internal/zzcob:<init>	()V
    //   2444: astore 16
    //   2446: aload 20
    //   2448: iload 6
    //   2450: invokestatic 342	java/lang/Integer:valueOf	(I)Ljava/lang/Integer;
    //   2453: aload 16
    //   2455: invokeinterface 123 3 0
    //   2460: pop
    //   2461: aload 16
    //   2463: iconst_1
    //   2464: invokestatic 50	java/lang/Boolean:valueOf	(Z)Ljava/lang/Boolean;
    //   2467: putfield 365	com/google/android/gms/internal/zzcob:zzd	Ljava/lang/Boolean;
    //   2470: new 346	java/util/BitSet
    //   2473: dup
    //   2474: invokespecial 347	java/util/BitSet:<init>	()V
    //   2477: astore 23
    //   2479: aload 15
    //   2481: iload 6
    //   2483: invokestatic 342	java/lang/Integer:valueOf	(I)Ljava/lang/Integer;
    //   2486: aload 23
    //   2488: invokeinterface 123 3 0
    //   2493: pop
    //   2494: new 346	java/util/BitSet
    //   2497: dup
    //   2498: invokespecial 347	java/util/BitSet:<init>	()V
    //   2501: astore 22
    //   2503: aload_2
    //   2504: iload 6
    //   2506: invokestatic 342	java/lang/Integer:valueOf	(I)Ljava/lang/Integer;
    //   2509: aload 22
    //   2511: invokeinterface 123 3 0
    //   2516: pop
    //   2517: aload 19
    //   2519: iload 6
    //   2521: invokestatic 342	java/lang/Integer:valueOf	(I)Ljava/lang/Integer;
    //   2524: invokeinterface 151 2 0
    //   2529: checkcast 205	java/util/List
    //   2532: invokeinterface 494 1 0
    //   2537: astore 24
    //   2539: aload 15
    //   2541: astore 16
    //   2543: aload 20
    //   2545: astore 15
    //   2547: aload 24
    //   2549: invokeinterface 335 1 0
    //   2554: ifeq +608 -> 3162
    //   2557: aload 24
    //   2559: invokeinterface 339 1 0
    //   2564: checkcast 532	com/google/android/gms/internal/zzcnw
    //   2567: astore 27
    //   2569: aload_0
    //   2570: invokevirtual 76	com/google/android/gms/internal/zzcli:zzt	()Lcom/google/android/gms/internal/zzcjk;
    //   2573: iconst_2
    //   2574: invokevirtual 497	com/google/android/gms/internal/zzcjk:zza	(I)Z
    //   2577: ifeq +63 -> 2640
    //   2580: aload_0
    //   2581: invokevirtual 76	com/google/android/gms/internal/zzcli:zzt	()Lcom/google/android/gms/internal/zzcjk;
    //   2584: invokevirtual 195	com/google/android/gms/internal/zzcjk:zzae	()Lcom/google/android/gms/internal/zzcjm;
    //   2587: ldc_w 534
    //   2590: iload 6
    //   2592: invokestatic 342	java/lang/Integer:valueOf	(I)Ljava/lang/Integer;
    //   2595: aload 27
    //   2597: getfield 535	com/google/android/gms/internal/zzcnw:zza	Ljava/lang/Integer;
    //   2600: aload_0
    //   2601: invokevirtual 88	com/google/android/gms/internal/zzcli:zzo	()Lcom/google/android/gms/internal/zzcji;
    //   2604: aload 27
    //   2606: getfield 536	com/google/android/gms/internal/zzcnw:zzb	Ljava/lang/String;
    //   2609: invokevirtual 538	com/google/android/gms/internal/zzcji:zzc	(Ljava/lang/String;)Ljava/lang/String;
    //   2612: invokevirtual 504	com/google/android/gms/internal/zzcjm:zza	(Ljava/lang/String;Ljava/lang/Object;Ljava/lang/Object;Ljava/lang/Object;)V
    //   2615: aload_0
    //   2616: invokevirtual 76	com/google/android/gms/internal/zzcli:zzt	()Lcom/google/android/gms/internal/zzcjk;
    //   2619: invokevirtual 195	com/google/android/gms/internal/zzcjk:zzae	()Lcom/google/android/gms/internal/zzcjm;
    //   2622: ldc_w 506
    //   2625: aload_0
    //   2626: invokevirtual 88	com/google/android/gms/internal/zzcli:zzo	()Lcom/google/android/gms/internal/zzcji;
    //   2629: aload 27
    //   2631: invokevirtual 541	com/google/android/gms/internal/zzcji:zza	(Lcom/google/android/gms/internal/zzcnw;)Ljava/lang/String;
    //   2634: invokevirtual 98	com/google/android/gms/internal/zzcjm:zza	(Ljava/lang/String;Ljava/lang/Object;)V
    //   2637: goto +3 -> 2640
    //   2640: aload 15
    //   2642: astore 20
    //   2644: aload_2
    //   2645: astore 21
    //   2647: aload 27
    //   2649: getfield 535	com/google/android/gms/internal/zzcnw:zza	Ljava/lang/Integer;
    //   2652: ifnull +458 -> 3110
    //   2655: aload 27
    //   2657: getfield 535	com/google/android/gms/internal/zzcnw:zza	Ljava/lang/Integer;
    //   2660: invokevirtual 265	java/lang/Integer:intValue	()I
    //   2663: sipush 256
    //   2666: if_icmple +6 -> 2672
    //   2669: goto +441 -> 3110
    //   2672: aload 23
    //   2674: aload 27
    //   2676: getfield 535	com/google/android/gms/internal/zzcnw:zza	Ljava/lang/Integer;
    //   2679: invokevirtual 265	java/lang/Integer:intValue	()I
    //   2682: invokevirtual 511	java/util/BitSet:get	(I)Z
    //   2685: ifeq +36 -> 2721
    //   2688: aload_0
    //   2689: invokevirtual 76	com/google/android/gms/internal/zzcli:zzt	()Lcom/google/android/gms/internal/zzcjk;
    //   2692: invokevirtual 195	com/google/android/gms/internal/zzcjk:zzae	()Lcom/google/android/gms/internal/zzcjm;
    //   2695: ldc_w 543
    //   2698: iload 6
    //   2700: invokestatic 342	java/lang/Integer:valueOf	(I)Ljava/lang/Integer;
    //   2703: aload 27
    //   2705: getfield 535	com/google/android/gms/internal/zzcnw:zza	Ljava/lang/Integer;
    //   2708: invokevirtual 136	com/google/android/gms/internal/zzcjm:zza	(Ljava/lang/String;Ljava/lang/Object;Ljava/lang/Object;)V
    //   2711: aload 21
    //   2713: astore_2
    //   2714: aload 20
    //   2716: astore 15
    //   2718: goto -171 -> 2547
    //   2721: aload 27
    //   2723: getfield 546	com/google/android/gms/internal/zzcnw:zzc	Lcom/google/android/gms/internal/zzcnu;
    //   2726: astore_2
    //   2727: aload_2
    //   2728: ifnonnull +39 -> 2767
    //   2731: aload_0
    //   2732: invokevirtual 76	com/google/android/gms/internal/zzcli:zzt	()Lcom/google/android/gms/internal/zzcjk;
    //   2735: invokevirtual 82	com/google/android/gms/internal/zzcjk:zzaa	()Lcom/google/android/gms/internal/zzcjm;
    //   2738: astore_2
    //   2739: ldc_w 548
    //   2742: astore 15
    //   2744: aload_2
    //   2745: aload 15
    //   2747: aload_0
    //   2748: invokevirtual 88	com/google/android/gms/internal/zzcli:zzo	()Lcom/google/android/gms/internal/zzcji;
    //   2751: aload 25
    //   2753: getfield 527	com/google/android/gms/internal/zzcoh:zzb	Ljava/lang/String;
    //   2756: invokevirtual 538	com/google/android/gms/internal/zzcji:zzc	(Ljava/lang/String;)Ljava/lang/String;
    //   2759: invokevirtual 98	com/google/android/gms/internal/zzcjm:zza	(Ljava/lang/String;Ljava/lang/Object;)V
    //   2762: aconst_null
    //   2763: astore_2
    //   2764: goto +256 -> 3020
    //   2767: getstatic 140	java/lang/Boolean:TRUE	Ljava/lang/Boolean;
    //   2770: aload_2
    //   2771: getfield 142	com/google/android/gms/internal/zzcnu:zzc	Ljava/lang/Boolean;
    //   2774: invokevirtual 145	java/lang/Boolean:equals	(Ljava/lang/Object;)Z
    //   2777: istore 14
    //   2779: aload 25
    //   2781: getfield 550	com/google/android/gms/internal/zzcoh:zzd	Ljava/lang/Long;
    //   2784: ifnull +53 -> 2837
    //   2787: aload_2
    //   2788: getfield 155	com/google/android/gms/internal/zzcnu:zzb	Lcom/google/android/gms/internal/zzcnv;
    //   2791: ifnonnull +19 -> 2810
    //   2794: aload_0
    //   2795: invokevirtual 76	com/google/android/gms/internal/zzcli:zzt	()Lcom/google/android/gms/internal/zzcjk;
    //   2798: invokevirtual 82	com/google/android/gms/internal/zzcjk:zzaa	()Lcom/google/android/gms/internal/zzcjm;
    //   2801: astore_2
    //   2802: ldc_w 552
    //   2805: astore 15
    //   2807: goto -63 -> 2744
    //   2810: aload_0
    //   2811: aload 25
    //   2813: getfield 550	com/google/android/gms/internal/zzcoh:zzd	Ljava/lang/Long;
    //   2816: invokevirtual 161	java/lang/Long:longValue	()J
    //   2819: aload_2
    //   2820: getfield 155	com/google/android/gms/internal/zzcnu:zzb	Lcom/google/android/gms/internal/zzcnv;
    //   2823: invokespecial 40	com/google/android/gms/internal/zzcii:zza	(JLcom/google/android/gms/internal/zzcnv;)Ljava/lang/Boolean;
    //   2826: astore_2
    //   2827: aload_2
    //   2828: iload 14
    //   2830: invokestatic 554	com/google/android/gms/internal/zzcii:zza	(Ljava/lang/Boolean;Z)Ljava/lang/Boolean;
    //   2833: astore_2
    //   2834: goto +186 -> 3020
    //   2837: aload 25
    //   2839: getfield 556	com/google/android/gms/internal/zzcoh:zze	Ljava/lang/Double;
    //   2842: ifnull +46 -> 2888
    //   2845: aload_2
    //   2846: getfield 155	com/google/android/gms/internal/zzcnu:zzb	Lcom/google/android/gms/internal/zzcnv;
    //   2849: ifnonnull +19 -> 2868
    //   2852: aload_0
    //   2853: invokevirtual 76	com/google/android/gms/internal/zzcli:zzt	()Lcom/google/android/gms/internal/zzcjk;
    //   2856: invokevirtual 82	com/google/android/gms/internal/zzcjk:zzaa	()Lcom/google/android/gms/internal/zzcjm;
    //   2859: astore_2
    //   2860: ldc_w 558
    //   2863: astore 15
    //   2865: goto -121 -> 2744
    //   2868: aload_0
    //   2869: aload 25
    //   2871: getfield 556	com/google/android/gms/internal/zzcoh:zze	Ljava/lang/Double;
    //   2874: invokevirtual 169	java/lang/Double:doubleValue	()D
    //   2877: aload_2
    //   2878: getfield 155	com/google/android/gms/internal/zzcnu:zzb	Lcom/google/android/gms/internal/zzcnv;
    //   2881: invokespecial 171	com/google/android/gms/internal/zzcii:zza	(DLcom/google/android/gms/internal/zzcnv;)Ljava/lang/Boolean;
    //   2884: astore_2
    //   2885: goto -58 -> 2827
    //   2888: aload 25
    //   2890: getfield 559	com/google/android/gms/internal/zzcoh:zzc	Ljava/lang/String;
    //   2893: ifnull +111 -> 3004
    //   2896: aload_2
    //   2897: getfield 176	com/google/android/gms/internal/zzcnu:zza	Lcom/google/android/gms/internal/zzcnx;
    //   2900: ifnonnull +87 -> 2987
    //   2903: aload_2
    //   2904: getfield 155	com/google/android/gms/internal/zzcnu:zzb	Lcom/google/android/gms/internal/zzcnv;
    //   2907: ifnonnull +19 -> 2926
    //   2910: aload_0
    //   2911: invokevirtual 76	com/google/android/gms/internal/zzcli:zzt	()Lcom/google/android/gms/internal/zzcjk;
    //   2914: invokevirtual 82	com/google/android/gms/internal/zzcjk:zzaa	()Lcom/google/android/gms/internal/zzcjm;
    //   2917: astore_2
    //   2918: ldc_w 561
    //   2921: astore 15
    //   2923: goto -179 -> 2744
    //   2926: aload 25
    //   2928: getfield 559	com/google/android/gms/internal/zzcoh:zzc	Ljava/lang/String;
    //   2931: invokestatic 185	com/google/android/gms/internal/zzcnp:zzj	(Ljava/lang/String;)Z
    //   2934: ifeq +20 -> 2954
    //   2937: aload_0
    //   2938: aload 25
    //   2940: getfield 559	com/google/android/gms/internal/zzcoh:zzc	Ljava/lang/String;
    //   2943: aload_2
    //   2944: getfield 155	com/google/android/gms/internal/zzcnu:zzb	Lcom/google/android/gms/internal/zzcnv;
    //   2947: invokespecial 188	com/google/android/gms/internal/zzcii:zza	(Ljava/lang/String;Lcom/google/android/gms/internal/zzcnv;)Ljava/lang/Boolean;
    //   2950: astore_2
    //   2951: goto -124 -> 2827
    //   2954: aload_0
    //   2955: invokevirtual 76	com/google/android/gms/internal/zzcli:zzt	()Lcom/google/android/gms/internal/zzcjk;
    //   2958: invokevirtual 82	com/google/android/gms/internal/zzcjk:zzaa	()Lcom/google/android/gms/internal/zzcjm;
    //   2961: ldc_w 563
    //   2964: aload_0
    //   2965: invokevirtual 88	com/google/android/gms/internal/zzcli:zzo	()Lcom/google/android/gms/internal/zzcji;
    //   2968: aload 25
    //   2970: getfield 527	com/google/android/gms/internal/zzcoh:zzb	Ljava/lang/String;
    //   2973: invokevirtual 538	com/google/android/gms/internal/zzcji:zzc	(Ljava/lang/String;)Ljava/lang/String;
    //   2976: aload 25
    //   2978: getfield 559	com/google/android/gms/internal/zzcoh:zzc	Ljava/lang/String;
    //   2981: invokevirtual 136	com/google/android/gms/internal/zzcjm:zza	(Ljava/lang/String;Ljava/lang/Object;Ljava/lang/Object;)V
    //   2984: goto -222 -> 2762
    //   2987: aload_0
    //   2988: aload 25
    //   2990: getfield 559	com/google/android/gms/internal/zzcoh:zzc	Ljava/lang/String;
    //   2993: aload_2
    //   2994: getfield 176	com/google/android/gms/internal/zzcnu:zza	Lcom/google/android/gms/internal/zzcnx;
    //   2997: invokespecial 179	com/google/android/gms/internal/zzcii:zza	(Ljava/lang/String;Lcom/google/android/gms/internal/zzcnx;)Ljava/lang/Boolean;
    //   3000: astore_2
    //   3001: goto -174 -> 2827
    //   3004: aload_0
    //   3005: invokevirtual 76	com/google/android/gms/internal/zzcli:zzt	()Lcom/google/android/gms/internal/zzcjk;
    //   3008: invokevirtual 82	com/google/android/gms/internal/zzcjk:zzaa	()Lcom/google/android/gms/internal/zzcjm;
    //   3011: astore_2
    //   3012: ldc_w 565
    //   3015: astore 15
    //   3017: goto -273 -> 2744
    //   3020: aload_0
    //   3021: invokevirtual 76	com/google/android/gms/internal/zzcli:zzt	()Lcom/google/android/gms/internal/zzcjk;
    //   3024: invokevirtual 195	com/google/android/gms/internal/zzcjk:zzae	()Lcom/google/android/gms/internal/zzcjm;
    //   3027: astore 28
    //   3029: aload_2
    //   3030: ifnonnull +11 -> 3041
    //   3033: ldc_w 517
    //   3036: astore 15
    //   3038: goto +6 -> 3044
    //   3041: aload_2
    //   3042: astore 15
    //   3044: aload 28
    //   3046: ldc_w 567
    //   3049: aload 15
    //   3051: invokevirtual 98	com/google/android/gms/internal/zzcjm:zza	(Ljava/lang/String;Ljava/lang/Object;)V
    //   3054: aload_2
    //   3055: ifnonnull +19 -> 3074
    //   3058: aload 26
    //   3060: iload 6
    //   3062: invokestatic 342	java/lang/Integer:valueOf	(I)Ljava/lang/Integer;
    //   3065: invokeinterface 104 2 0
    //   3070: pop
    //   3071: goto -360 -> 2711
    //   3074: aload 22
    //   3076: aload 27
    //   3078: getfield 535	com/google/android/gms/internal/zzcnw:zza	Ljava/lang/Integer;
    //   3081: invokevirtual 265	java/lang/Integer:intValue	()I
    //   3084: invokevirtual 358	java/util/BitSet:set	(I)V
    //   3087: aload_2
    //   3088: invokevirtual 46	java/lang/Boolean:booleanValue	()Z
    //   3091: ifeq -380 -> 2711
    //   3094: aload 23
    //   3096: aload 27
    //   3098: getfield 535	com/google/android/gms/internal/zzcnw:zza	Ljava/lang/Integer;
    //   3101: invokevirtual 265	java/lang/Integer:intValue	()I
    //   3104: invokevirtual 358	java/util/BitSet:set	(I)V
    //   3107: goto -396 -> 2711
    //   3110: aload_0
    //   3111: invokevirtual 76	com/google/android/gms/internal/zzcli:zzt	()Lcom/google/android/gms/internal/zzcjk;
    //   3114: invokevirtual 82	com/google/android/gms/internal/zzcjk:zzaa	()Lcom/google/android/gms/internal/zzcjm;
    //   3117: ldc_w 569
    //   3120: aload_1
    //   3121: invokestatic 472	com/google/android/gms/internal/zzcjk:zza	(Ljava/lang/String;)Ljava/lang/Object;
    //   3124: aload 27
    //   3126: getfield 535	com/google/android/gms/internal/zzcnw:zza	Ljava/lang/Integer;
    //   3129: invokestatic 524	java/lang/String:valueOf	(Ljava/lang/Object;)Ljava/lang/String;
    //   3132: invokevirtual 136	com/google/android/gms/internal/zzcjm:zza	(Ljava/lang/String;Ljava/lang/Object;Ljava/lang/Object;)V
    //   3135: aload 26
    //   3137: iload 6
    //   3139: invokestatic 342	java/lang/Integer:valueOf	(I)Ljava/lang/Integer;
    //   3142: invokeinterface 104 2 0
    //   3147: pop
    //   3148: aload 21
    //   3150: astore_2
    //   3151: aload 16
    //   3153: astore 15
    //   3155: aload 20
    //   3157: astore 16
    //   3159: goto -842 -> 2317
    //   3162: aload 16
    //   3164: astore 20
    //   3166: aload 15
    //   3168: astore 16
    //   3170: aload 20
    //   3172: astore 15
    //   3174: goto -857 -> 2317
    //   3177: iload 5
    //   3179: iconst_1
    //   3180: iadd
    //   3181: istore 5
    //   3183: aload_3
    //   3184: astore 25
    //   3186: aload 17
    //   3188: astore 20
    //   3190: goto -989 -> 2201
    //   3193: aload 18
    //   3195: astore_3
    //   3196: aload 17
    //   3198: astore 15
    //   3200: aload 19
    //   3202: invokeinterface 570 1 0
    //   3207: anewarray 362	com/google/android/gms/internal/zzcob
    //   3210: astore 18
    //   3212: aload 19
    //   3214: invokeinterface 326 1 0
    //   3219: invokeinterface 330 1 0
    //   3224: astore 20
    //   3226: iconst_0
    //   3227: istore 4
    //   3229: aload 20
    //   3231: invokeinterface 335 1 0
    //   3236: ifeq +348 -> 3584
    //   3239: aload 20
    //   3241: invokeinterface 339 1 0
    //   3246: checkcast 262	java/lang/Integer
    //   3249: invokevirtual 265	java/lang/Integer:intValue	()I
    //   3252: istore 5
    //   3254: aload 26
    //   3256: iload 5
    //   3258: invokestatic 342	java/lang/Integer:valueOf	(I)Ljava/lang/Integer;
    //   3261: invokeinterface 114 2 0
    //   3266: ifne -37 -> 3229
    //   3269: aload 15
    //   3271: iload 5
    //   3273: invokestatic 342	java/lang/Integer:valueOf	(I)Ljava/lang/Integer;
    //   3276: invokeinterface 151 2 0
    //   3281: checkcast 362	com/google/android/gms/internal/zzcob
    //   3284: astore 16
    //   3286: aload 16
    //   3288: astore_2
    //   3289: aload 16
    //   3291: ifnonnull +11 -> 3302
    //   3294: new 362	com/google/android/gms/internal/zzcob
    //   3297: dup
    //   3298: invokespecial 363	com/google/android/gms/internal/zzcob:<init>	()V
    //   3301: astore_2
    //   3302: aload 18
    //   3304: iload 4
    //   3306: aload_2
    //   3307: aastore
    //   3308: aload_2
    //   3309: iload 5
    //   3311: invokestatic 342	java/lang/Integer:valueOf	(I)Ljava/lang/Integer;
    //   3314: putfield 571	com/google/android/gms/internal/zzcob:zza	Ljava/lang/Integer;
    //   3317: aload_2
    //   3318: new 344	com/google/android/gms/internal/zzcog
    //   3321: dup
    //   3322: invokespecial 369	com/google/android/gms/internal/zzcog:<init>	()V
    //   3325: putfield 371	com/google/android/gms/internal/zzcob:zzb	Lcom/google/android/gms/internal/zzcog;
    //   3328: aload_2
    //   3329: getfield 371	com/google/android/gms/internal/zzcob:zzb	Lcom/google/android/gms/internal/zzcog;
    //   3332: aload 19
    //   3334: iload 5
    //   3336: invokestatic 342	java/lang/Integer:valueOf	(I)Ljava/lang/Integer;
    //   3339: invokeinterface 151 2 0
    //   3344: checkcast 346	java/util/BitSet
    //   3347: invokestatic 374	com/google/android/gms/internal/zzcnp:zza	(Ljava/util/BitSet;)[J
    //   3350: putfield 360	com/google/android/gms/internal/zzcog:zzb	[J
    //   3353: aload_2
    //   3354: getfield 371	com/google/android/gms/internal/zzcob:zzb	Lcom/google/android/gms/internal/zzcog;
    //   3357: aload_3
    //   3358: iload 5
    //   3360: invokestatic 342	java/lang/Integer:valueOf	(I)Ljava/lang/Integer;
    //   3363: invokeinterface 151 2 0
    //   3368: checkcast 346	java/util/BitSet
    //   3371: invokestatic 374	com/google/android/gms/internal/zzcnp:zza	(Ljava/util/BitSet;)[J
    //   3374: putfield 350	com/google/android/gms/internal/zzcog:zza	[J
    //   3377: aload_0
    //   3378: invokevirtual 317	com/google/android/gms/internal/zzcli:zzn	()Lcom/google/android/gms/internal/zzcim;
    //   3381: astore 16
    //   3383: aload_2
    //   3384: getfield 371	com/google/android/gms/internal/zzcob:zzb	Lcom/google/android/gms/internal/zzcog;
    //   3387: astore 17
    //   3389: aload 16
    //   3391: invokevirtual 574	com/google/android/gms/internal/zzclj:zzaq	()V
    //   3394: aload 16
    //   3396: invokevirtual 427	com/google/android/gms/internal/zzcli:zzc	()V
    //   3399: aload_1
    //   3400: invokestatic 313	com/google/android/gms/common/internal/zzbq:zza	(Ljava/lang/String;)Ljava/lang/String;
    //   3403: pop
    //   3404: aload 17
    //   3406: invokestatic 255	com/google/android/gms/common/internal/zzbq:zza	(Ljava/lang/Object;)Ljava/lang/Object;
    //   3409: pop
    //   3410: aload 17
    //   3412: invokevirtual 578	com/google/android/gms/internal/zzeue:zzf	()I
    //   3415: newarray byte
    //   3417: astore_2
    //   3418: aload_2
    //   3419: iconst_0
    //   3420: aload_2
    //   3421: arraylength
    //   3422: invokestatic 583	com/google/android/gms/internal/zzetw:zza	([BII)Lcom/google/android/gms/internal/zzetw;
    //   3425: astore 21
    //   3427: aload 17
    //   3429: aload 21
    //   3431: invokevirtual 586	com/google/android/gms/internal/zzeue:zza	(Lcom/google/android/gms/internal/zzetw;)V
    //   3434: aload 21
    //   3436: invokevirtual 588	com/google/android/gms/internal/zzetw:zza	()V
    //   3439: new 590	android/content/ContentValues
    //   3442: dup
    //   3443: invokespecial 591	android/content/ContentValues:<init>	()V
    //   3446: astore 17
    //   3448: aload 17
    //   3450: ldc_w 593
    //   3453: aload_1
    //   3454: invokevirtual 596	android/content/ContentValues:put	(Ljava/lang/String;Ljava/lang/String;)V
    //   3457: aload 17
    //   3459: ldc_w 598
    //   3462: iload 5
    //   3464: invokestatic 342	java/lang/Integer:valueOf	(I)Ljava/lang/Integer;
    //   3467: invokevirtual 601	android/content/ContentValues:put	(Ljava/lang/String;Ljava/lang/Integer;)V
    //   3470: aload 17
    //   3472: ldc_w 603
    //   3475: aload_2
    //   3476: invokevirtual 606	android/content/ContentValues:put	(Ljava/lang/String;[B)V
    //   3479: aload 16
    //   3481: invokevirtual 432	com/google/android/gms/internal/zzcim:zzaa	()Landroid/database/sqlite/SQLiteDatabase;
    //   3484: astore_2
    //   3485: aload_2
    //   3486: ldc_w 608
    //   3489: aconst_null
    //   3490: aload 17
    //   3492: iconst_5
    //   3493: invokevirtual 612	android/database/sqlite/SQLiteDatabase:insertWithOnConflict	(Ljava/lang/String;Ljava/lang/String;Landroid/content/ContentValues;I)J
    //   3496: ldc2_w 613
    //   3499: lcmp
    //   3500: ifne +75 -> 3575
    //   3503: aload 16
    //   3505: invokevirtual 76	com/google/android/gms/internal/zzcli:zzt	()Lcom/google/android/gms/internal/zzcjk;
    //   3508: invokevirtual 411	com/google/android/gms/internal/zzcjk:zzy	()Lcom/google/android/gms/internal/zzcjm;
    //   3511: ldc_w 616
    //   3514: aload_1
    //   3515: invokestatic 472	com/google/android/gms/internal/zzcjk:zza	(Ljava/lang/String;)Ljava/lang/Object;
    //   3518: invokevirtual 98	com/google/android/gms/internal/zzcjm:zza	(Ljava/lang/String;Ljava/lang/Object;)V
    //   3521: goto +54 -> 3575
    //   3524: astore_2
    //   3525: goto +4 -> 3529
    //   3528: astore_2
    //   3529: aload 16
    //   3531: invokevirtual 76	com/google/android/gms/internal/zzcli:zzt	()Lcom/google/android/gms/internal/zzcjk;
    //   3534: invokevirtual 411	com/google/android/gms/internal/zzcjk:zzy	()Lcom/google/android/gms/internal/zzcjm;
    //   3537: astore 16
    //   3539: ldc_w 618
    //   3542: astore 17
    //   3544: goto +19 -> 3563
    //   3547: astore_2
    //   3548: aload 16
    //   3550: invokevirtual 76	com/google/android/gms/internal/zzcli:zzt	()Lcom/google/android/gms/internal/zzcjk;
    //   3553: invokevirtual 411	com/google/android/gms/internal/zzcjk:zzy	()Lcom/google/android/gms/internal/zzcjm;
    //   3556: astore 16
    //   3558: ldc_w 620
    //   3561: astore 17
    //   3563: aload 16
    //   3565: aload 17
    //   3567: aload_1
    //   3568: invokestatic 472	com/google/android/gms/internal/zzcjk:zza	(Ljava/lang/String;)Ljava/lang/Object;
    //   3571: aload_2
    //   3572: invokevirtual 136	com/google/android/gms/internal/zzcjm:zza	(Ljava/lang/String;Ljava/lang/Object;Ljava/lang/Object;)V
    //   3575: iload 4
    //   3577: iconst_1
    //   3578: iadd
    //   3579: istore 4
    //   3581: goto -352 -> 3229
    //   3584: aload 18
    //   3586: iload 4
    //   3588: invokestatic 452	java/util/Arrays:copyOf	([Ljava/lang/Object;I)[Ljava/lang/Object;
    //   3591: checkcast 622	[Lcom/google/android/gms/internal/zzcob;
    //   3594: areturn
    // Exception table:
    //   from	to	target	type
    //   803	820	823	android/database/sqlite/SQLiteException
    //   796	803	832	android/database/sqlite/SQLiteException
    //   3485	3521	3524	android/database/sqlite/SQLiteException
    //   3479	3485	3528	android/database/sqlite/SQLiteException
    //   3410	3439	3547	java/io/IOException
  }
  
  protected final boolean zzw()
  {
    return false;
  }
}
