package com.mobile.ui.reactivateisa.activity;

import android.content.Context;
import android.os.Bundle;
import android.support.v4.app.Fragment;
import android.support.v4.app.FragmentManager;
import android.support.v4.app.FragmentTransaction;
import com.mobile.ui.R.id;
import com.mobile.ui.common.activity.AppTimeoutActivity;
import com.mobile.ui.common.activity.BaseActivity.rrrggg;
import com.mobile.ui.home.activity.HomeActivity;
import com.mobile.ui.reactivateisa.fragment.ReactivateIsaFragment.isiisi;
import com.mobile.ui.reactivateisa.fragment.ReactivateIsaSuccessFragment;
import java.util.Map;
import javax.inject.Inject;
import kkkkkk.bfbfff;
import kkkkkk.ccrrcc;
import kkkkkk.gguuuu;
import kkkkkk.nuuuun.uunuun;
import kkkkkk.ssisii;

public class ReactivateIsaActivity
  extends AppTimeoutActivity
  implements ReactivateIsaFragment.isiisi
{
  private static final String EXTRA_ARRANGEMENT_ID = "\007\033\030\027\007&\t\033\034\f\032\024\023\034\025\037&2\035\031";
  public static int b04170417ЗЗЗЗЗЗ0417 = 7;
  public static int b0417З0417ЗЗЗЗЗ0417 = 1;
  public static int bЗ04170417ЗЗЗЗЗ0417 = 2;
  public static int bЗЗ0417ЗЗЗЗЗ0417;
  @Inject
  public bfbfff mFeatureConfig;
  
  static
  {
    try
    {
      String str = EXTRA_ARRANGEMENT_ID;
      if ((b04170417ЗЗЗЗЗЗ0417 + b0417З0417ЗЗЗЗЗ0417) * b04170417ЗЗЗЗЗЗ0417 % bЗЗЗ0417ЗЗЗЗ0417() != b0417ЗЗ0417ЗЗЗЗ0417())
      {
        if ((b04170417ЗЗЗЗЗЗ0417 + b0417З0417ЗЗЗЗЗ0417) * b04170417ЗЗЗЗЗЗ0417 % bЗЗЗ0417ЗЗЗЗ0417() != b0417ЗЗ0417ЗЗЗЗ0417())
        {
          b04170417ЗЗЗЗЗЗ0417 = 8;
          bЗЗ0417ЗЗЗЗЗ0417 = b041704170417ЗЗЗЗЗ0417();
        }
        b04170417ЗЗЗЗЗЗ0417 = 26;
        bЗЗ0417ЗЗЗЗЗ0417 = b041704170417ЗЗЗЗЗ0417();
      }
      EXTRA_ARRANGEMENT_ID = gguuuu.bк043Aккк043Aкк043A043A(str, '§', 'f', '\001');
      return;
    }
    catch (Exception localException)
    {
      throw localException;
    }
  }
  
  public ReactivateIsaActivity() {}
  
  public static int b041704170417ЗЗЗЗЗ0417()
  {
    return 51;
  }
  
  public static int b0417ЗЗ0417ЗЗЗЗ0417()
  {
    return 0;
  }
  
  public static int bЗ0417З0417ЗЗЗЗ0417()
  {
    return 1;
  }
  
  public static int bЗЗЗ0417ЗЗЗЗ0417()
  {
    return 2;
  }
  
  /* Error */
  public static android.content.Intent getIntent(Context paramContext, String paramString)
  {
    // Byte code:
    //   0: new 58	android/content/Intent
    //   3: dup
    //   4: aload_0
    //   5: ldc 2
    //   7: invokespecial 61	android/content/Intent:<init>	(Landroid/content/Context;Ljava/lang/Class;)V
    //   10: astore_0
    //   11: aload_0
    //   12: ldc 63
    //   14: bipush 8
    //   16: iconst_2
    //   17: invokestatic 67	kkkkkk/gguuuu:bккккк043Aкк043A043A	(Ljava/lang/String;CC)Ljava/lang/String;
    //   20: aload_1
    //   21: invokevirtual 71	android/content/Intent:putExtra	(Ljava/lang/String;Ljava/lang/String;)Landroid/content/Intent;
    //   24: pop
    //   25: getstatic 29	com/mobile/ui/reactivateisa/activity/ReactivateIsaActivity:b04170417ЗЗЗЗЗЗ0417	I
    //   28: istore_2
    //   29: iload_2
    //   30: getstatic 31	com/mobile/ui/reactivateisa/activity/ReactivateIsaActivity:b0417З0417ЗЗЗЗЗ0417	I
    //   33: iload_2
    //   34: iadd
    //   35: imul
    //   36: invokestatic 35	com/mobile/ui/reactivateisa/activity/ReactivateIsaActivity:bЗЗЗ0417ЗЗЗЗ0417	()I
    //   39: irem
    //   40: tableswitch	default:+20->60, 0:+32->72
    //   60: invokestatic 41	com/mobile/ui/reactivateisa/activity/ReactivateIsaActivity:b041704170417ЗЗЗЗЗ0417	()I
    //   63: putstatic 29	com/mobile/ui/reactivateisa/activity/ReactivateIsaActivity:b04170417ЗЗЗЗЗЗ0417	I
    //   66: invokestatic 41	com/mobile/ui/reactivateisa/activity/ReactivateIsaActivity:b041704170417ЗЗЗЗЗ0417	()I
    //   69: putstatic 43	com/mobile/ui/reactivateisa/activity/ReactivateIsaActivity:bЗЗ0417ЗЗЗЗЗ0417	I
    //   72: getstatic 29	com/mobile/ui/reactivateisa/activity/ReactivateIsaActivity:b04170417ЗЗЗЗЗЗ0417	I
    //   75: getstatic 31	com/mobile/ui/reactivateisa/activity/ReactivateIsaActivity:b0417З0417ЗЗЗЗЗ0417	I
    //   78: iadd
    //   79: getstatic 29	com/mobile/ui/reactivateisa/activity/ReactivateIsaActivity:b04170417ЗЗЗЗЗЗ0417	I
    //   82: imul
    //   83: getstatic 73	com/mobile/ui/reactivateisa/activity/ReactivateIsaActivity:bЗ04170417ЗЗЗЗЗ0417	I
    //   86: irem
    //   87: getstatic 43	com/mobile/ui/reactivateisa/activity/ReactivateIsaActivity:bЗЗ0417ЗЗЗЗЗ0417	I
    //   90: if_icmpeq +14 -> 104
    //   93: bipush 29
    //   95: putstatic 29	com/mobile/ui/reactivateisa/activity/ReactivateIsaActivity:b04170417ЗЗЗЗЗЗ0417	I
    //   98: invokestatic 41	com/mobile/ui/reactivateisa/activity/ReactivateIsaActivity:b041704170417ЗЗЗЗЗ0417	()I
    //   101: putstatic 43	com/mobile/ui/reactivateisa/activity/ReactivateIsaActivity:bЗЗ0417ЗЗЗЗЗ0417	I
    //   104: aload_0
    //   105: areturn
    //   106: astore_0
    //   107: aload_0
    //   108: athrow
    //   109: astore_0
    //   110: aload_0
    //   111: athrow
    //   112: astore_0
    //   113: aload_0
    //   114: athrow
    // Local variable table:
    //   start	length	slot	name	signature
    //   0	115	0	paramContext	Context
    //   0	115	1	paramString	String
    //   28	8	2	i	int
    // Exception table:
    //   from	to	target	type
    //   0	11	106	java/lang/Exception
    //   11	25	106	java/lang/Exception
    //   107	109	109	java/lang/Exception
    //   72	104	112	java/lang/Exception
  }
  
  public Map<String, Bundle> getDeepLinkMap(Context paramContext)
  {
    int i = b04170417ЗЗЗЗЗЗ0417;
    switch (i * (b0417З0417ЗЗЗЗЗ0417 + i) % bЗ04170417ЗЗЗЗЗ0417)
    {
    default: 
      b04170417ЗЗЗЗЗЗ0417 = b041704170417ЗЗЗЗЗ0417();
      bЗЗ0417ЗЗЗЗЗ0417 = 92;
      if ((b041704170417ЗЗЗЗЗ0417() + b0417З0417ЗЗЗЗЗ0417) * b041704170417ЗЗЗЗЗ0417() % bЗ04170417ЗЗЗЗЗ0417 != bЗЗ0417ЗЗЗЗЗ0417)
      {
        b04170417ЗЗЗЗЗЗ0417 = 23;
        bЗЗ0417ЗЗЗЗЗ0417 = 0;
      }
      break;
    }
    switch (1)
    {
    case 0: 
    default: 
      for (;;)
      {
        switch (1)
        {
        }
      }
    }
    return nuuuun.uunuun.bп043F043F043Fпп043F043F043Fп().b043Fпп043Fпп043F043F043Fп(gguuuu.bккккк043Aкк043A043A("\023\005\001\021\005\021z\r|C~\bt", '_', '\005'), HomeActivity.class).bпп043F043Fпп043F043F043Fп();
  }
  
  /* Error */
  public int getLayoutId()
  {
    // Byte code:
    //   0: getstatic 29	com/mobile/ui/reactivateisa/activity/ReactivateIsaActivity:b04170417ЗЗЗЗЗЗ0417	I
    //   3: istore_1
    //   4: iload_1
    //   5: getstatic 31	com/mobile/ui/reactivateisa/activity/ReactivateIsaActivity:b0417З0417ЗЗЗЗЗ0417	I
    //   8: iload_1
    //   9: iadd
    //   10: imul
    //   11: getstatic 73	com/mobile/ui/reactivateisa/activity/ReactivateIsaActivity:bЗ04170417ЗЗЗЗЗ0417	I
    //   14: irem
    //   15: tableswitch	default:+17->32, 0:+27->42
    //   32: iconst_1
    //   33: putstatic 29	com/mobile/ui/reactivateisa/activity/ReactivateIsaActivity:b04170417ЗЗЗЗЗЗ0417	I
    //   36: invokestatic 41	com/mobile/ui/reactivateisa/activity/ReactivateIsaActivity:b041704170417ЗЗЗЗЗ0417	()I
    //   39: putstatic 43	com/mobile/ui/reactivateisa/activity/ReactivateIsaActivity:bЗЗ0417ЗЗЗЗЗ0417	I
    //   42: getstatic 101	com/mobile/ui/R$layout:activity_reactivate_isa	I
    //   45: istore_1
    //   46: getstatic 29	com/mobile/ui/reactivateisa/activity/ReactivateIsaActivity:b04170417ЗЗЗЗЗЗ0417	I
    //   49: istore_2
    //   50: getstatic 31	com/mobile/ui/reactivateisa/activity/ReactivateIsaActivity:b0417З0417ЗЗЗЗЗ0417	I
    //   53: istore_3
    //   54: getstatic 29	com/mobile/ui/reactivateisa/activity/ReactivateIsaActivity:b04170417ЗЗЗЗЗЗ0417	I
    //   57: istore 4
    //   59: getstatic 73	com/mobile/ui/reactivateisa/activity/ReactivateIsaActivity:bЗ04170417ЗЗЗЗЗ0417	I
    //   62: istore 5
    //   64: iload_2
    //   65: iload_3
    //   66: iadd
    //   67: iload 4
    //   69: imul
    //   70: iload 5
    //   72: irem
    //   73: getstatic 43	com/mobile/ui/reactivateisa/activity/ReactivateIsaActivity:bЗЗ0417ЗЗЗЗЗ0417	I
    //   76: if_icmpeq +14 -> 90
    //   79: invokestatic 41	com/mobile/ui/reactivateisa/activity/ReactivateIsaActivity:b041704170417ЗЗЗЗЗ0417	()I
    //   82: putstatic 29	com/mobile/ui/reactivateisa/activity/ReactivateIsaActivity:b04170417ЗЗЗЗЗЗ0417	I
    //   85: bipush 49
    //   87: putstatic 43	com/mobile/ui/reactivateisa/activity/ReactivateIsaActivity:bЗЗ0417ЗЗЗЗЗ0417	I
    //   90: iconst_0
    //   91: tableswitch	default:+21->112, 0:+48->139, 1:+-1->90
    //   112: iconst_1
    //   113: tableswitch	default:+23->136, 0:+-23->90, 1:+26->139
    //   136: goto -24 -> 112
    //   139: iload_1
    //   140: ireturn
    //   141: astore 6
    //   143: aload 6
    //   145: athrow
    //   146: astore 6
    //   148: aload 6
    //   150: athrow
    // Local variable table:
    //   start	length	slot	name	signature
    //   0	151	0	this	ReactivateIsaActivity
    //   3	137	1	i	int
    //   49	18	2	j	int
    //   53	14	3	k	int
    //   57	13	4	m	int
    //   62	11	5	n	int
    //   141	3	6	localException1	Exception
    //   146	3	6	localException2	Exception
    // Exception table:
    //   from	to	target	type
    //   42	64	141	java/lang/Exception
    //   64	90	146	java/lang/Exception
  }
  
  public BaseActivity.rrrggg getMenuType()
  {
    int i = b04170417ЗЗЗЗЗЗ0417;
    switch (i * (b0417З0417ЗЗЗЗЗ0417 + i) % bЗ04170417ЗЗЗЗЗ0417)
    {
    default: 
      b04170417ЗЗЗЗЗЗ0417 = b041704170417ЗЗЗЗЗ0417();
      bЗЗ0417ЗЗЗЗЗ0417 = 62;
    }
    BaseActivity.rrrggg localRrrggg = BaseActivity.rrrggg.GLOBAL;
    switch (0)
    {
    case 1: 
    default: 
      for (;;)
      {
        switch (0)
        {
        }
      }
    }
    return localRrrggg;
  }
  
  public void onBackPressed()
  {
    Fragment localFragment = getSupportFragmentManager().findFragmentById(R.id.reactivateIsaContainer);
    if ((b04170417ЗЗЗЗЗЗ0417 + b0417З0417ЗЗЗЗЗ0417) * b04170417ЗЗЗЗЗЗ0417 % bЗ04170417ЗЗЗЗЗ0417 != bЗЗ0417ЗЗЗЗЗ0417)
    {
      b04170417ЗЗЗЗЗЗ0417 = b041704170417ЗЗЗЗЗ0417();
      bЗЗ0417ЗЗЗЗЗ0417 = b041704170417ЗЗЗЗЗ0417();
    }
    if ((localFragment instanceof ssisii)) {}
    for (boolean bool = ((ssisii)localFragment).onBackPressed();; bool = false)
    {
      switch (1)
      {
      case 0: 
      default: 
        for (;;)
        {
          switch (0)
          {
          }
        }
      }
      if (!bool) {
        super.onBackPressed();
      }
      return;
    }
  }
  
  /* Error */
  public void onCreate(@android.support.annotation.Nullable Bundle paramBundle)
  {
    // Byte code:
    //   0: aload_0
    //   1: invokevirtual 139	com/mobile/ui/reactivateisa/activity/ReactivateIsaActivity:getApplicationContext	()Landroid/content/Context;
    //   4: invokestatic 145	kkkkkk/nkkkkk:bЗЗ0417З0417З0417041704170417	(Landroid/content/Context;)V
    //   7: aload_0
    //   8: invokevirtual 139	com/mobile/ui/reactivateisa/activity/ReactivateIsaActivity:getApplicationContext	()Landroid/content/Context;
    //   11: invokestatic 150	kkkkkk/nnnkkk:bхх0445ххххххх	(Landroid/content/Context;)V
    //   14: aload_0
    //   15: invokevirtual 139	com/mobile/ui/reactivateisa/activity/ReactivateIsaActivity:getApplicationContext	()Landroid/content/Context;
    //   18: invokestatic 155	kkkkkk/nknnkk:bх0445ххх04450445ххх	(Landroid/content/Context;)V
    //   21: aload_0
    //   22: aload_1
    //   23: invokespecial 157	com/mobile/ui/common/activity/AppTimeoutActivity:onCreate	(Landroid/os/Bundle;)V
    //   26: invokestatic 163	com/mobile/ui/App:get	()Lcom/mobile/ui/App;
    //   29: invokevirtual 167	com/mobile/ui/App:getAppComponent	()Lkkkkkk/uyyyyy;
    //   32: astore 6
    //   34: getstatic 29	com/mobile/ui/reactivateisa/activity/ReactivateIsaActivity:b04170417ЗЗЗЗЗЗ0417	I
    //   37: invokestatic 169	com/mobile/ui/reactivateisa/activity/ReactivateIsaActivity:bЗ0417З0417ЗЗЗЗ0417	()I
    //   40: iadd
    //   41: getstatic 29	com/mobile/ui/reactivateisa/activity/ReactivateIsaActivity:b04170417ЗЗЗЗЗЗ0417	I
    //   44: imul
    //   45: getstatic 73	com/mobile/ui/reactivateisa/activity/ReactivateIsaActivity:bЗ04170417ЗЗЗЗЗ0417	I
    //   48: irem
    //   49: getstatic 43	com/mobile/ui/reactivateisa/activity/ReactivateIsaActivity:bЗЗ0417ЗЗЗЗЗ0417	I
    //   52: if_icmpeq +15 -> 67
    //   55: invokestatic 41	com/mobile/ui/reactivateisa/activity/ReactivateIsaActivity:b041704170417ЗЗЗЗЗ0417	()I
    //   58: putstatic 29	com/mobile/ui/reactivateisa/activity/ReactivateIsaActivity:b04170417ЗЗЗЗЗЗ0417	I
    //   61: invokestatic 41	com/mobile/ui/reactivateisa/activity/ReactivateIsaActivity:b041704170417ЗЗЗЗЗ0417	()I
    //   64: putstatic 43	com/mobile/ui/reactivateisa/activity/ReactivateIsaActivity:bЗЗ0417ЗЗЗЗЗ0417	I
    //   67: aload 6
    //   69: aload_0
    //   70: invokeinterface 175 2 0
    //   75: ldc -79
    //   77: sipush 233
    //   80: iconst_2
    //   81: invokestatic 67	kkkkkk/gguuuu:bккккк043Aкк043A043A	(Ljava/lang/String;CC)Ljava/lang/String;
    //   84: astore 6
    //   86: aload 6
    //   88: iconst_1
    //   89: invokestatic 183	com/appdynamics/eumagent/runtime/Instrumentation:leaveBreadcrumb	(Ljava/lang/String;I)V
    //   92: aload_1
    //   93: ifnonnull +58 -> 151
    //   96: invokestatic 41	com/mobile/ui/reactivateisa/activity/ReactivateIsaActivity:b041704170417ЗЗЗЗЗ0417	()I
    //   99: istore_2
    //   100: getstatic 31	com/mobile/ui/reactivateisa/activity/ReactivateIsaActivity:b0417З0417ЗЗЗЗЗ0417	I
    //   103: istore_3
    //   104: getstatic 73	com/mobile/ui/reactivateisa/activity/ReactivateIsaActivity:bЗ04170417ЗЗЗЗЗ0417	I
    //   107: istore 4
    //   109: iload_2
    //   110: iload_3
    //   111: iload_2
    //   112: iadd
    //   113: imul
    //   114: iload 4
    //   116: irem
    //   117: tableswitch	default:+19->136, 0:+30->147
    //   136: bipush 91
    //   138: putstatic 29	com/mobile/ui/reactivateisa/activity/ReactivateIsaActivity:b04170417ЗЗЗЗЗЗ0417	I
    //   141: invokestatic 41	com/mobile/ui/reactivateisa/activity/ReactivateIsaActivity:b041704170417ЗЗЗЗЗ0417	()I
    //   144: putstatic 43	com/mobile/ui/reactivateisa/activity/ReactivateIsaActivity:bЗЗ0417ЗЗЗЗЗ0417	I
    //   147: aload_0
    //   148: invokevirtual 186	com/mobile/ui/reactivateisa/activity/ReactivateIsaActivity:showReactivateIsaFragment	()V
    //   151: aload_0
    //   152: getfield 188	com/mobile/ui/reactivateisa/activity/ReactivateIsaActivity:mFeatureConfig	Lkkkkkk/bfbfff;
    //   155: invokevirtual 193	kkkkkk/bfbfff:b04120412041204120412ВВВВ0412	()Z
    //   158: istore 5
    //   160: iconst_0
    //   161: tableswitch	default:+23->184, 0:+50->211, 1:+-1->160
    //   184: iconst_0
    //   185: tableswitch	default:+23->208, 0:+26->211, 1:+-25->160
    //   208: goto -24 -> 184
    //   211: iload 5
    //   213: ifne +7 -> 220
    //   216: aload_0
    //   217: invokevirtual 196	com/mobile/ui/reactivateisa/activity/ReactivateIsaActivity:finish	()V
    //   220: return
    //   221: astore_1
    //   222: aload_1
    //   223: athrow
    //   224: astore_1
    //   225: aload_1
    //   226: athrow
    // Local variable table:
    //   start	length	slot	name	signature
    //   0	227	0	this	ReactivateIsaActivity
    //   0	227	1	paramBundle	Bundle
    //   99	15	2	i	int
    //   103	10	3	j	int
    //   107	10	4	k	int
    //   158	54	5	bool	boolean
    //   32	55	6	localObject	Object
    // Exception table:
    //   from	to	target	type
    //   0	34	221	java/lang/Exception
    //   67	86	221	java/lang/Exception
    //   104	109	221	java/lang/Exception
    //   147	151	221	java/lang/Exception
    //   216	220	221	java/lang/Exception
    //   86	92	224	java/lang/Exception
    //   96	104	224	java/lang/Exception
    //   136	147	224	java/lang/Exception
    //   151	160	224	java/lang/Exception
  }
  
  public void onReactivateIsaSuccess(String paramString1, String paramString2, String paramString3, String paramString4, String paramString5, ccrrcc paramCcrrcc)
  {
    if ((b04170417ЗЗЗЗЗЗ0417 + b0417З0417ЗЗЗЗЗ0417) * b04170417ЗЗЗЗЗЗ0417 % bЗ04170417ЗЗЗЗЗ0417 != bЗЗ0417ЗЗЗЗЗ0417)
    {
      b04170417ЗЗЗЗЗЗ0417 = b041704170417ЗЗЗЗЗ0417();
      bЗЗ0417ЗЗЗЗЗ0417 = b041704170417ЗЗЗЗЗ0417();
    }
    paramString1 = ReactivateIsaSuccessFragment.newInstance(paramString1, paramString2, paramString3, paramString4, paramString5, paramCcrrcc);
    paramString2 = getSupportFragmentManager().beginTransaction();
    int i = R.id.reactivateIsaContainer;
    int j = b04170417ЗЗЗЗЗЗ0417;
    switch (j * (b0417З0417ЗЗЗЗЗ0417 + j) % bЗ04170417ЗЗЗЗЗ0417)
    {
    default: 
      b04170417ЗЗЗЗЗЗ0417 = b041704170417ЗЗЗЗЗ0417();
      bЗЗ0417ЗЗЗЗЗ0417 = 88;
    }
    paramString1 = paramString2.replace(i, paramString1);
    switch (0)
    {
    case 1: 
    default: 
      for (;;)
      {
        switch (0)
        {
        case 1: 
        default: 
          for (;;)
          {
            switch (1)
            {
            }
          }
        }
        switch (1)
        {
        }
      }
    }
    paramString1.commit();
  }
  
  public boolean shouldRestartAppIfSecureCoreNotInitialized()
  {
    if ((b04170417ЗЗЗЗЗЗ0417 + b0417З0417ЗЗЗЗЗ0417) * b04170417ЗЗЗЗЗЗ0417 % bЗ04170417ЗЗЗЗЗ0417 != b0417ЗЗ0417ЗЗЗЗ0417())
    {
      if ((b04170417ЗЗЗЗЗЗ0417 + b0417З0417ЗЗЗЗЗ0417) * b04170417ЗЗЗЗЗЗ0417 % bЗЗЗ0417ЗЗЗЗ0417() != bЗЗ0417ЗЗЗЗЗ0417)
      {
        b04170417ЗЗЗЗЗЗ0417 = b041704170417ЗЗЗЗЗ0417();
        bЗЗ0417ЗЗЗЗЗ0417 = b041704170417ЗЗЗЗЗ0417();
      }
      b04170417ЗЗЗЗЗЗ0417 = b041704170417ЗЗЗЗЗ0417();
      bЗЗ0417ЗЗЗЗЗ0417 = b041704170417ЗЗЗЗЗ0417();
    }
    return false;
  }
  
  /* Error */
  public void showReactivateIsaFragment()
  {
    // Byte code:
    //   0: aload_0
    //   1: invokevirtual 222	com/mobile/ui/reactivateisa/activity/ReactivateIsaActivity:getIntent	()Landroid/content/Intent;
    //   4: astore 6
    //   6: getstatic 29	com/mobile/ui/reactivateisa/activity/ReactivateIsaActivity:b04170417ЗЗЗЗЗЗ0417	I
    //   9: istore_1
    //   10: getstatic 31	com/mobile/ui/reactivateisa/activity/ReactivateIsaActivity:b0417З0417ЗЗЗЗЗ0417	I
    //   13: istore_2
    //   14: getstatic 29	com/mobile/ui/reactivateisa/activity/ReactivateIsaActivity:b04170417ЗЗЗЗЗЗ0417	I
    //   17: istore_3
    //   18: getstatic 73	com/mobile/ui/reactivateisa/activity/ReactivateIsaActivity:bЗ04170417ЗЗЗЗЗ0417	I
    //   21: istore 4
    //   23: getstatic 43	com/mobile/ui/reactivateisa/activity/ReactivateIsaActivity:bЗЗ0417ЗЗЗЗЗ0417	I
    //   26: istore 5
    //   28: iload_1
    //   29: iload_2
    //   30: iadd
    //   31: iload_3
    //   32: imul
    //   33: iload 4
    //   35: irem
    //   36: iload 5
    //   38: if_icmpeq +14 -> 52
    //   41: invokestatic 41	com/mobile/ui/reactivateisa/activity/ReactivateIsaActivity:b041704170417ЗЗЗЗЗ0417	()I
    //   44: putstatic 29	com/mobile/ui/reactivateisa/activity/ReactivateIsaActivity:b04170417ЗЗЗЗЗЗ0417	I
    //   47: bipush 26
    //   49: putstatic 43	com/mobile/ui/reactivateisa/activity/ReactivateIsaActivity:bЗЗ0417ЗЗЗЗЗ0417	I
    //   52: iconst_0
    //   53: tableswitch	default:+23->76, 0:+50->103, 1:+-1->52
    //   76: iconst_0
    //   77: tableswitch	default:+23->100, 0:+26->103, 1:+-25->52
    //   100: goto -24 -> 76
    //   103: ldc -32
    //   105: bipush 116
    //   107: iconst_1
    //   108: invokestatic 67	kkkkkk/gguuuu:bккккк043Aкк043A043A	(Ljava/lang/String;CC)Ljava/lang/String;
    //   111: astore 7
    //   113: aload 6
    //   115: aload 7
    //   117: invokevirtual 228	android/content/Intent:getStringExtra	(Ljava/lang/String;)Ljava/lang/String;
    //   120: astore 6
    //   122: getstatic 29	com/mobile/ui/reactivateisa/activity/ReactivateIsaActivity:b04170417ЗЗЗЗЗЗ0417	I
    //   125: getstatic 31	com/mobile/ui/reactivateisa/activity/ReactivateIsaActivity:b0417З0417ЗЗЗЗЗ0417	I
    //   128: iadd
    //   129: getstatic 29	com/mobile/ui/reactivateisa/activity/ReactivateIsaActivity:b04170417ЗЗЗЗЗЗ0417	I
    //   132: imul
    //   133: getstatic 73	com/mobile/ui/reactivateisa/activity/ReactivateIsaActivity:bЗ04170417ЗЗЗЗЗ0417	I
    //   136: irem
    //   137: invokestatic 38	com/mobile/ui/reactivateisa/activity/ReactivateIsaActivity:b0417ЗЗ0417ЗЗЗЗ0417	()I
    //   140: if_icmpeq +12 -> 152
    //   143: iconst_5
    //   144: putstatic 29	com/mobile/ui/reactivateisa/activity/ReactivateIsaActivity:b04170417ЗЗЗЗЗЗ0417	I
    //   147: bipush 13
    //   149: putstatic 43	com/mobile/ui/reactivateisa/activity/ReactivateIsaActivity:bЗЗ0417ЗЗЗЗЗ0417	I
    //   152: aload_0
    //   153: invokevirtual 114	com/mobile/ui/reactivateisa/activity/ReactivateIsaActivity:getSupportFragmentManager	()Landroid/support/v4/app/FragmentManager;
    //   156: invokevirtual 209	android/support/v4/app/FragmentManager:beginTransaction	()Landroid/support/v4/app/FragmentTransaction;
    //   159: getstatic 119	com/mobile/ui/R$id:reactivateIsaContainer	I
    //   162: aload 6
    //   164: invokestatic 233	com/mobile/ui/reactivateisa/fragment/ReactivateIsaFragment:newInstance	(Ljava/lang/String;)Lcom/mobile/ui/reactivateisa/fragment/ReactivateIsaFragment;
    //   167: invokevirtual 215	android/support/v4/app/FragmentTransaction:replace	(ILandroid/support/v4/app/Fragment;)Landroid/support/v4/app/FragmentTransaction;
    //   170: invokevirtual 218	android/support/v4/app/FragmentTransaction:commit	()I
    //   173: pop
    //   174: return
    //   175: astore 6
    //   177: aload 6
    //   179: athrow
    //   180: astore 6
    //   182: aload 6
    //   184: athrow
    // Local variable table:
    //   start	length	slot	name	signature
    //   0	185	0	this	ReactivateIsaActivity
    //   9	22	1	i	int
    //   13	18	2	j	int
    //   17	16	3	k	int
    //   21	15	4	m	int
    //   26	13	5	n	int
    //   4	159	6	localObject	Object
    //   175	3	6	localException1	Exception
    //   180	3	6	localException2	Exception
    //   111	5	7	str	String
    // Exception table:
    //   from	to	target	type
    //   0	28	175	java/lang/Exception
    //   113	122	175	java/lang/Exception
    //   152	174	175	java/lang/Exception
    //   41	52	180	java/lang/Exception
    //   103	113	180	java/lang/Exception
  }
}
