package com.db.pwcc.dbmobile.multi_bank_aggregator.model;

import uuuuuu.popopp;

public class EfiSuggestion
  implements popopp
{
  public static int b00640064d00640064006400640064 = 0;
  public static int b0064d006400640064006400640064 = 2;
  public static int bd0064d00640064006400640064 = 96;
  public static int bdd006400640064006400640064 = 1;
  private String displayedName;
  private String groupName;
  private Integer iconRes;
  private String searchName;
  
  public EfiSuggestion() {}
  
  public static int b0066fffffff()
  {
    return 80;
  }
  
  public static int bd0064006400640064006400640064()
  {
    return 1;
  }
  
  public String getDisplayName()
  {
    if ((bd0064d00640064006400640064 + bdd006400640064006400640064) * bd0064d00640064006400640064 % b0064d006400640064006400640064 != b00640064d00640064006400640064)
    {
      if ((bd0064d00640064006400640064 + bd0064006400640064006400640064()) * bd0064d00640064006400640064 % b0064d006400640064006400640064 != b00640064d00640064006400640064)
      {
        bd0064d00640064006400640064 = b0066fffffff();
        b00640064d00640064006400640064 = 62;
      }
      bd0064d00640064006400640064 = 52;
      b00640064d00640064006400640064 = 89;
    }
    return this.displayedName;
  }
  
  public String getGroupName()
  {
    if ((bd0064d00640064006400640064 + bdd006400640064006400640064) * bd0064d00640064006400640064 % b0064d006400640064006400640064 != b00640064d00640064006400640064)
    {
      bd0064d00640064006400640064 = 29;
      b00640064d00640064006400640064 = b0066fffffff();
    }
    return this.groupName;
  }
  
  public Integer getIconRes()
  {
    if ((bd0064d00640064006400640064 + bdd006400640064006400640064) * bd0064d00640064006400640064 % b0064d006400640064006400640064 != b00640064d00640064006400640064)
    {
      bd0064d00640064006400640064 = 46;
      b00640064d00640064006400640064 = 19;
    }
    if ((bd0064d00640064006400640064 + bdd006400640064006400640064) * bd0064d00640064006400640064 % b0064d006400640064006400640064 != b00640064d00640064006400640064)
    {
      bd0064d00640064006400640064 = b0066fffffff();
      b00640064d00640064006400640064 = b0066fffffff();
    }
    return this.iconRes;
  }
  
  public String getSearchName()
  {
    if ((bd0064d00640064006400640064 + bdd006400640064006400640064) * bd0064d00640064006400640064 % b0064d006400640064006400640064 != b00640064d00640064006400640064)
    {
      if ((bd0064d00640064006400640064 + bdd006400640064006400640064) * bd0064d00640064006400640064 % b0064d006400640064006400640064 != b00640064d00640064006400640064)
      {
        bd0064d00640064006400640064 = 45;
        b00640064d00640064006400640064 = b0066fffffff();
      }
      bd0064d00640064006400640064 = 66;
      b00640064d00640064006400640064 = 82;
    }
    return this.searchName;
  }
  
  public void setDisplayedName(String paramString)
  {
    if ((bd0064d00640064006400640064 + bdd006400640064006400640064) * bd0064d00640064006400640064 % b0064d006400640064006400640064 != b00640064d00640064006400640064)
    {
      bd0064d00640064006400640064 = 54;
      b00640064d00640064006400640064 = 56;
    }
    int i = bd0064d00640064006400640064;
    switch (i * (bdd006400640064006400640064 + i) % b0064d006400640064006400640064)
    {
    default: 
      bd0064d00640064006400640064 = b0066fffffff();
      b00640064d00640064006400640064 = b0066fffffff();
    }
    this.displayedName = paramString;
  }
  
  public void setGroupName(String paramString)
  {
    int i = bd0064d00640064006400640064;
    switch (i * (bd0064006400640064006400640064() + i) % b0064d006400640064006400640064)
    {
    default: 
      if ((b0066fffffff() + bd0064006400640064006400640064()) * b0066fffffff() % b0064d006400640064006400640064 != b00640064d00640064006400640064)
      {
        bd0064d00640064006400640064 = b0066fffffff();
        b00640064d00640064006400640064 = 32;
      }
      bd0064d00640064006400640064 = b0066fffffff();
      b00640064d00640064006400640064 = b0066fffffff();
    }
    this.groupName = paramString;
  }
  
  public void setIconRes(Integer paramInteger)
  {
    int i = bd0064d00640064006400640064;
    switch (i * (bdd006400640064006400640064 + i) % b0064d006400640064006400640064)
    {
    default: 
      bd0064d00640064006400640064 = 96;
      i = bd0064d00640064006400640064;
      switch (i * (bdd006400640064006400640064 + i) % b0064d006400640064006400640064)
      {
      default: 
        bd0064d00640064006400640064 = 45;
        b00640064d00640064006400640064 = 43;
      }
      b00640064d00640064006400640064 = 36;
    }
    this.iconRes = paramInteger;
  }
  
  public void setSearchName(String paramString)
  {
    if ((bd0064d00640064006400640064 + bdd006400640064006400640064) * bd0064d00640064006400640064 % b0064d006400640064006400640064 != b00640064d00640064006400640064)
    {
      if ((bd0064d00640064006400640064 + bdd006400640064006400640064) * bd0064d00640064006400640064 % b0064d006400640064006400640064 != b00640064d00640064006400640064)
      {
        bd0064d00640064006400640064 = 65;
        b00640064d00640064006400640064 = 25;
      }
      bd0064d00640064006400640064 = 88;
      b00640064d00640064006400640064 = b0066fffffff();
    }
    this.searchName = paramString;
  }
  
  /* Error */
  public String toString()
  {
    // Byte code:
    //   0: new 66	java/lang/StringBuilder
    //   3: dup
    //   4: invokespecial 67	java/lang/StringBuilder:<init>	()V
    //   7: astore_2
    //   8: getstatic 33	com/db/pwcc/dbmobile/multi_bank_aggregator/model/EfiSuggestion:bd0064d00640064006400640064	I
    //   11: istore_1
    //   12: iload_1
    //   13: getstatic 35	com/db/pwcc/dbmobile/multi_bank_aggregator/model/EfiSuggestion:bdd006400640064006400640064	I
    //   16: iload_1
    //   17: iadd
    //   18: imul
    //   19: getstatic 37	com/db/pwcc/dbmobile/multi_bank_aggregator/model/EfiSuggestion:b0064d006400640064006400640064	I
    //   22: irem
    //   23: tableswitch	default:+17->40, 0:+27->50
    //   40: bipush 34
    //   42: putstatic 33	com/db/pwcc/dbmobile/multi_bank_aggregator/model/EfiSuggestion:bd0064d00640064006400640064	I
    //   45: bipush 78
    //   47: putstatic 39	com/db/pwcc/dbmobile/multi_bank_aggregator/model/EfiSuggestion:b00640064d00640064006400640064	I
    //   50: ldc 69
    //   52: ldc 71
    //   54: bipush 80
    //   56: iconst_0
    //   57: invokestatic 77	xxxxxx/uxxxxx:bb00620062bb0062b0062b0062	(Ljava/lang/String;CC)Ljava/lang/String;
    //   60: iconst_4
    //   61: anewarray 79	java/lang/Class
    //   64: dup
    //   65: iconst_0
    //   66: ldc 81
    //   68: aastore
    //   69: dup
    //   70: iconst_1
    //   71: getstatic 87	java/lang/Character:TYPE	Ljava/lang/Class;
    //   74: aastore
    //   75: dup
    //   76: iconst_2
    //   77: getstatic 87	java/lang/Character:TYPE	Ljava/lang/Class;
    //   80: aastore
    //   81: dup
    //   82: iconst_3
    //   83: getstatic 87	java/lang/Character:TYPE	Ljava/lang/Class;
    //   86: aastore
    //   87: invokevirtual 91	java/lang/Class:getMethod	(Ljava/lang/String;[Ljava/lang/Class;)Ljava/lang/reflect/Method;
    //   90: astore_3
    //   91: aload_3
    //   92: aconst_null
    //   93: iconst_4
    //   94: anewarray 4	java/lang/Object
    //   97: dup
    //   98: iconst_0
    //   99: ldc 93
    //   101: aastore
    //   102: dup
    //   103: iconst_1
    //   104: sipush 189
    //   107: invokestatic 97	java/lang/Character:valueOf	(C)Ljava/lang/Character;
    //   110: aastore
    //   111: dup
    //   112: iconst_2
    //   113: bipush 108
    //   115: invokestatic 97	java/lang/Character:valueOf	(C)Ljava/lang/Character;
    //   118: aastore
    //   119: dup
    //   120: iconst_3
    //   121: iconst_0
    //   122: invokestatic 97	java/lang/Character:valueOf	(C)Ljava/lang/Character;
    //   125: aastore
    //   126: invokevirtual 103	java/lang/reflect/Method:invoke	(Ljava/lang/Object;[Ljava/lang/Object;)Ljava/lang/Object;
    //   129: astore_3
    //   130: aload_2
    //   131: aload_3
    //   132: checkcast 81	java/lang/String
    //   135: invokevirtual 107	java/lang/StringBuilder:append	(Ljava/lang/String;)Ljava/lang/StringBuilder;
    //   138: aload_0
    //   139: getfield 45	com/db/pwcc/dbmobile/multi_bank_aggregator/model/EfiSuggestion:displayedName	Ljava/lang/String;
    //   142: invokevirtual 107	java/lang/StringBuilder:append	(Ljava/lang/String;)Ljava/lang/StringBuilder;
    //   145: astore_2
    //   146: invokestatic 43	com/db/pwcc/dbmobile/multi_bank_aggregator/model/EfiSuggestion:b0066fffffff	()I
    //   149: istore_1
    //   150: iload_1
    //   151: getstatic 35	com/db/pwcc/dbmobile/multi_bank_aggregator/model/EfiSuggestion:bdd006400640064006400640064	I
    //   154: iload_1
    //   155: iadd
    //   156: imul
    //   157: getstatic 37	com/db/pwcc/dbmobile/multi_bank_aggregator/model/EfiSuggestion:b0064d006400640064006400640064	I
    //   160: irem
    //   161: tableswitch	default:+19->180, 0:+29->190
    //   180: bipush 91
    //   182: putstatic 33	com/db/pwcc/dbmobile/multi_bank_aggregator/model/EfiSuggestion:bd0064d00640064006400640064	I
    //   185: bipush 17
    //   187: putstatic 39	com/db/pwcc/dbmobile/multi_bank_aggregator/model/EfiSuggestion:b00640064d00640064006400640064	I
    //   190: ldc 69
    //   192: ldc 109
    //   194: bipush 56
    //   196: iconst_4
    //   197: invokestatic 77	xxxxxx/uxxxxx:bb00620062bb0062b0062b0062	(Ljava/lang/String;CC)Ljava/lang/String;
    //   200: iconst_3
    //   201: anewarray 79	java/lang/Class
    //   204: dup
    //   205: iconst_0
    //   206: ldc 81
    //   208: aastore
    //   209: dup
    //   210: iconst_1
    //   211: getstatic 87	java/lang/Character:TYPE	Ljava/lang/Class;
    //   214: aastore
    //   215: dup
    //   216: iconst_2
    //   217: getstatic 87	java/lang/Character:TYPE	Ljava/lang/Class;
    //   220: aastore
    //   221: invokevirtual 91	java/lang/Class:getMethod	(Ljava/lang/String;[Ljava/lang/Class;)Ljava/lang/reflect/Method;
    //   224: astore_3
    //   225: aload_3
    //   226: aconst_null
    //   227: iconst_3
    //   228: anewarray 4	java/lang/Object
    //   231: dup
    //   232: iconst_0
    //   233: ldc 111
    //   235: aastore
    //   236: dup
    //   237: iconst_1
    //   238: sipush 229
    //   241: invokestatic 97	java/lang/Character:valueOf	(C)Ljava/lang/Character;
    //   244: aastore
    //   245: dup
    //   246: iconst_2
    //   247: iconst_1
    //   248: invokestatic 97	java/lang/Character:valueOf	(C)Ljava/lang/Character;
    //   251: aastore
    //   252: invokevirtual 103	java/lang/reflect/Method:invoke	(Ljava/lang/Object;[Ljava/lang/Object;)Ljava/lang/Object;
    //   255: astore_3
    //   256: aload_2
    //   257: aload_3
    //   258: checkcast 81	java/lang/String
    //   261: invokevirtual 107	java/lang/StringBuilder:append	(Ljava/lang/String;)Ljava/lang/StringBuilder;
    //   264: aload_0
    //   265: getfield 55	com/db/pwcc/dbmobile/multi_bank_aggregator/model/EfiSuggestion:searchName	Ljava/lang/String;
    //   268: invokevirtual 107	java/lang/StringBuilder:append	(Ljava/lang/String;)Ljava/lang/StringBuilder;
    //   271: bipush 125
    //   273: invokevirtual 114	java/lang/StringBuilder:append	(C)Ljava/lang/StringBuilder;
    //   276: invokevirtual 116	java/lang/StringBuilder:toString	()Ljava/lang/String;
    //   279: areturn
    //   280: astore_2
    //   281: aload_2
    //   282: invokevirtual 120	java/lang/reflect/InvocationTargetException:getCause	()Ljava/lang/Throwable;
    //   285: athrow
    //   286: astore_2
    //   287: aload_2
    //   288: invokevirtual 120	java/lang/reflect/InvocationTargetException:getCause	()Ljava/lang/Throwable;
    //   291: athrow
    // Local variable table:
    //   start	length	slot	name	signature
    //   0	292	0	this	EfiSuggestion
    //   11	146	1	i	int
    //   7	250	2	localStringBuilder	StringBuilder
    //   280	2	2	localInvocationTargetException1	java.lang.reflect.InvocationTargetException
    //   286	2	2	localInvocationTargetException2	java.lang.reflect.InvocationTargetException
    //   90	168	3	localObject	Object
    // Exception table:
    //   from	to	target	type
    //   225	256	280	java/lang/reflect/InvocationTargetException
    //   91	130	286	java/lang/reflect/InvocationTargetException
  }
}
