package com.db.pwcc.dbmobile.multi_bank_aggregator.model;

import com.google.gson.annotations.SerializedName;
import uuuuuu.popopp;

public enum MbaErrorCode
  implements popopp
{
  private boolean syncError;
  
  /* Error */
  static
  {
    // Byte code:
    //   0: ldc 70
    //   2: ldc 72
    //   4: sipush 130
    //   7: iconst_2
    //   8: invokestatic 78	xxxxxx/uxxxxx:bb00620062bb0062b0062b0062	(Ljava/lang/String;CC)Ljava/lang/String;
    //   11: iconst_4
    //   12: anewarray 80	java/lang/Class
    //   15: dup
    //   16: iconst_0
    //   17: ldc 82
    //   19: aastore
    //   20: dup
    //   21: iconst_1
    //   22: getstatic 88	java/lang/Character:TYPE	Ljava/lang/Class;
    //   25: aastore
    //   26: dup
    //   27: iconst_2
    //   28: getstatic 88	java/lang/Character:TYPE	Ljava/lang/Class;
    //   31: aastore
    //   32: dup
    //   33: iconst_3
    //   34: getstatic 88	java/lang/Character:TYPE	Ljava/lang/Class;
    //   37: aastore
    //   38: invokevirtual 92	java/lang/Class:getMethod	(Ljava/lang/String;[Ljava/lang/Class;)Ljava/lang/reflect/Method;
    //   41: astore_1
    //   42: aload_1
    //   43: aconst_null
    //   44: iconst_4
    //   45: anewarray 94	java/lang/Object
    //   48: dup
    //   49: iconst_0
    //   50: ldc 96
    //   52: aastore
    //   53: dup
    //   54: iconst_1
    //   55: sipush 200
    //   58: invokestatic 100	java/lang/Character:valueOf	(C)Ljava/lang/Character;
    //   61: aastore
    //   62: dup
    //   63: iconst_2
    //   64: sipush 202
    //   67: invokestatic 100	java/lang/Character:valueOf	(C)Ljava/lang/Character;
    //   70: aastore
    //   71: dup
    //   72: iconst_3
    //   73: iconst_1
    //   74: invokestatic 100	java/lang/Character:valueOf	(C)Ljava/lang/Character;
    //   77: aastore
    //   78: invokevirtual 106	java/lang/reflect/Method:invoke	(Ljava/lang/Object;[Ljava/lang/Object;)Ljava/lang/Object;
    //   81: astore_1
    //   82: new 2	com/db/pwcc/dbmobile/multi_bank_aggregator/model/MbaErrorCode
    //   85: dup
    //   86: aload_1
    //   87: checkcast 82	java/lang/String
    //   90: iconst_0
    //   91: iconst_0
    //   92: invokespecial 110	com/db/pwcc/dbmobile/multi_bank_aggregator/model/MbaErrorCode:<init>	(Ljava/lang/String;IZ)V
    //   95: putstatic 112	com/db/pwcc/dbmobile/multi_bank_aggregator/model/MbaErrorCode:ADD_MBA_ACCOUNT_SAME_USER	Lcom/db/pwcc/dbmobile/multi_bank_aggregator/model/MbaErrorCode;
    //   98: ldc 70
    //   100: ldc 114
    //   102: bipush 51
    //   104: iconst_1
    //   105: invokestatic 78	xxxxxx/uxxxxx:bb00620062bb0062b0062b0062	(Ljava/lang/String;CC)Ljava/lang/String;
    //   108: iconst_4
    //   109: anewarray 80	java/lang/Class
    //   112: dup
    //   113: iconst_0
    //   114: ldc 82
    //   116: aastore
    //   117: dup
    //   118: iconst_1
    //   119: getstatic 88	java/lang/Character:TYPE	Ljava/lang/Class;
    //   122: aastore
    //   123: dup
    //   124: iconst_2
    //   125: getstatic 88	java/lang/Character:TYPE	Ljava/lang/Class;
    //   128: aastore
    //   129: dup
    //   130: iconst_3
    //   131: getstatic 88	java/lang/Character:TYPE	Ljava/lang/Class;
    //   134: aastore
    //   135: invokevirtual 92	java/lang/Class:getMethod	(Ljava/lang/String;[Ljava/lang/Class;)Ljava/lang/reflect/Method;
    //   138: astore_1
    //   139: aload_1
    //   140: aconst_null
    //   141: iconst_4
    //   142: anewarray 94	java/lang/Object
    //   145: dup
    //   146: iconst_0
    //   147: ldc 116
    //   149: aastore
    //   150: dup
    //   151: iconst_1
    //   152: bipush 115
    //   154: invokestatic 100	java/lang/Character:valueOf	(C)Ljava/lang/Character;
    //   157: aastore
    //   158: dup
    //   159: iconst_2
    //   160: sipush 234
    //   163: invokestatic 100	java/lang/Character:valueOf	(C)Ljava/lang/Character;
    //   166: aastore
    //   167: dup
    //   168: iconst_3
    //   169: iconst_2
    //   170: invokestatic 100	java/lang/Character:valueOf	(C)Ljava/lang/Character;
    //   173: aastore
    //   174: invokevirtual 106	java/lang/reflect/Method:invoke	(Ljava/lang/Object;[Ljava/lang/Object;)Ljava/lang/Object;
    //   177: astore_1
    //   178: new 2	com/db/pwcc/dbmobile/multi_bank_aggregator/model/MbaErrorCode
    //   181: dup
    //   182: aload_1
    //   183: checkcast 82	java/lang/String
    //   186: iconst_1
    //   187: iconst_0
    //   188: invokespecial 110	com/db/pwcc/dbmobile/multi_bank_aggregator/model/MbaErrorCode:<init>	(Ljava/lang/String;IZ)V
    //   191: putstatic 118	com/db/pwcc/dbmobile/multi_bank_aggregator/model/MbaErrorCode:ADD_PRODUCT_ERROR	Lcom/db/pwcc/dbmobile/multi_bank_aggregator/model/MbaErrorCode;
    //   194: ldc 70
    //   196: ldc 120
    //   198: sipush 191
    //   201: iconst_5
    //   202: invokestatic 78	xxxxxx/uxxxxx:bb00620062bb0062b0062b0062	(Ljava/lang/String;CC)Ljava/lang/String;
    //   205: iconst_3
    //   206: anewarray 80	java/lang/Class
    //   209: dup
    //   210: iconst_0
    //   211: ldc 82
    //   213: aastore
    //   214: dup
    //   215: iconst_1
    //   216: getstatic 88	java/lang/Character:TYPE	Ljava/lang/Class;
    //   219: aastore
    //   220: dup
    //   221: iconst_2
    //   222: getstatic 88	java/lang/Character:TYPE	Ljava/lang/Class;
    //   225: aastore
    //   226: invokevirtual 92	java/lang/Class:getMethod	(Ljava/lang/String;[Ljava/lang/Class;)Ljava/lang/reflect/Method;
    //   229: astore_1
    //   230: aload_1
    //   231: aconst_null
    //   232: iconst_3
    //   233: anewarray 94	java/lang/Object
    //   236: dup
    //   237: iconst_0
    //   238: ldc 122
    //   240: aastore
    //   241: dup
    //   242: iconst_1
    //   243: bipush 77
    //   245: invokestatic 100	java/lang/Character:valueOf	(C)Ljava/lang/Character;
    //   248: aastore
    //   249: dup
    //   250: iconst_2
    //   251: iconst_0
    //   252: invokestatic 100	java/lang/Character:valueOf	(C)Ljava/lang/Character;
    //   255: aastore
    //   256: invokevirtual 106	java/lang/reflect/Method:invoke	(Ljava/lang/Object;[Ljava/lang/Object;)Ljava/lang/Object;
    //   259: astore_1
    //   260: new 2	com/db/pwcc/dbmobile/multi_bank_aggregator/model/MbaErrorCode
    //   263: dup
    //   264: aload_1
    //   265: checkcast 82	java/lang/String
    //   268: iconst_2
    //   269: iconst_0
    //   270: invokespecial 110	com/db/pwcc/dbmobile/multi_bank_aggregator/model/MbaErrorCode:<init>	(Ljava/lang/String;IZ)V
    //   273: putstatic 124	com/db/pwcc/dbmobile/multi_bank_aggregator/model/MbaErrorCode:DELETE_PRODUCT_ERROR	Lcom/db/pwcc/dbmobile/multi_bank_aggregator/model/MbaErrorCode;
    //   276: ldc 70
    //   278: ldc 126
    //   280: bipush 72
    //   282: iconst_2
    //   283: invokestatic 78	xxxxxx/uxxxxx:bb00620062bb0062b0062b0062	(Ljava/lang/String;CC)Ljava/lang/String;
    //   286: iconst_4
    //   287: anewarray 80	java/lang/Class
    //   290: dup
    //   291: iconst_0
    //   292: ldc 82
    //   294: aastore
    //   295: dup
    //   296: iconst_1
    //   297: getstatic 88	java/lang/Character:TYPE	Ljava/lang/Class;
    //   300: aastore
    //   301: dup
    //   302: iconst_2
    //   303: getstatic 88	java/lang/Character:TYPE	Ljava/lang/Class;
    //   306: aastore
    //   307: dup
    //   308: iconst_3
    //   309: getstatic 88	java/lang/Character:TYPE	Ljava/lang/Class;
    //   312: aastore
    //   313: invokevirtual 92	java/lang/Class:getMethod	(Ljava/lang/String;[Ljava/lang/Class;)Ljava/lang/reflect/Method;
    //   316: astore_1
    //   317: aload_1
    //   318: aconst_null
    //   319: iconst_4
    //   320: anewarray 94	java/lang/Object
    //   323: dup
    //   324: iconst_0
    //   325: ldc -128
    //   327: aastore
    //   328: dup
    //   329: iconst_1
    //   330: bipush 109
    //   332: invokestatic 100	java/lang/Character:valueOf	(C)Ljava/lang/Character;
    //   335: aastore
    //   336: dup
    //   337: iconst_2
    //   338: sipush 173
    //   341: invokestatic 100	java/lang/Character:valueOf	(C)Ljava/lang/Character;
    //   344: aastore
    //   345: dup
    //   346: iconst_3
    //   347: iconst_3
    //   348: invokestatic 100	java/lang/Character:valueOf	(C)Ljava/lang/Character;
    //   351: aastore
    //   352: invokevirtual 106	java/lang/reflect/Method:invoke	(Ljava/lang/Object;[Ljava/lang/Object;)Ljava/lang/Object;
    //   355: astore_1
    //   356: new 2	com/db/pwcc/dbmobile/multi_bank_aggregator/model/MbaErrorCode
    //   359: dup
    //   360: aload_1
    //   361: checkcast 82	java/lang/String
    //   364: iconst_3
    //   365: iconst_0
    //   366: invokespecial 110	com/db/pwcc/dbmobile/multi_bank_aggregator/model/MbaErrorCode:<init>	(Ljava/lang/String;IZ)V
    //   369: putstatic 130	com/db/pwcc/dbmobile/multi_bank_aggregator/model/MbaErrorCode:NO_RESULTS	Lcom/db/pwcc/dbmobile/multi_bank_aggregator/model/MbaErrorCode;
    //   372: invokestatic 134	com/db/pwcc/dbmobile/multi_bank_aggregator/model/MbaErrorCode:bf00660066f00660066ff	()I
    //   375: invokestatic 137	com/db/pwcc/dbmobile/multi_bank_aggregator/model/MbaErrorCode:bfff006600660066ff	()I
    //   378: iadd
    //   379: invokestatic 134	com/db/pwcc/dbmobile/multi_bank_aggregator/model/MbaErrorCode:bf00660066f00660066ff	()I
    //   382: imul
    //   383: invokestatic 140	com/db/pwcc/dbmobile/multi_bank_aggregator/model/MbaErrorCode:b0066ff006600660066ff	()I
    //   386: irem
    //   387: invokestatic 143	com/db/pwcc/dbmobile/multi_bank_aggregator/model/MbaErrorCode:b006600660066f00660066ff	()I
    //   390: if_icmpeq +3 -> 393
    //   393: ldc 70
    //   395: ldc -111
    //   397: bipush 29
    //   399: bipush 10
    //   401: iconst_1
    //   402: invokestatic 149	xxxxxx/uxxxxx:bbbb0062b0062b0062b0062	(Ljava/lang/String;CCC)Ljava/lang/String;
    //   405: iconst_3
    //   406: anewarray 80	java/lang/Class
    //   409: dup
    //   410: iconst_0
    //   411: ldc 82
    //   413: aastore
    //   414: dup
    //   415: iconst_1
    //   416: getstatic 88	java/lang/Character:TYPE	Ljava/lang/Class;
    //   419: aastore
    //   420: dup
    //   421: iconst_2
    //   422: getstatic 88	java/lang/Character:TYPE	Ljava/lang/Class;
    //   425: aastore
    //   426: invokevirtual 92	java/lang/Class:getMethod	(Ljava/lang/String;[Ljava/lang/Class;)Ljava/lang/reflect/Method;
    //   429: astore_1
    //   430: aload_1
    //   431: aconst_null
    //   432: iconst_3
    //   433: anewarray 94	java/lang/Object
    //   436: dup
    //   437: iconst_0
    //   438: ldc -105
    //   440: aastore
    //   441: dup
    //   442: iconst_1
    //   443: bipush 30
    //   445: invokestatic 100	java/lang/Character:valueOf	(C)Ljava/lang/Character;
    //   448: aastore
    //   449: dup
    //   450: iconst_2
    //   451: iconst_1
    //   452: invokestatic 100	java/lang/Character:valueOf	(C)Ljava/lang/Character;
    //   455: aastore
    //   456: invokevirtual 106	java/lang/reflect/Method:invoke	(Ljava/lang/Object;[Ljava/lang/Object;)Ljava/lang/Object;
    //   459: astore_1
    //   460: new 2	com/db/pwcc/dbmobile/multi_bank_aggregator/model/MbaErrorCode
    //   463: dup
    //   464: aload_1
    //   465: checkcast 82	java/lang/String
    //   468: iconst_4
    //   469: iconst_0
    //   470: invokespecial 110	com/db/pwcc/dbmobile/multi_bank_aggregator/model/MbaErrorCode:<init>	(Ljava/lang/String;IZ)V
    //   473: putstatic 153	com/db/pwcc/dbmobile/multi_bank_aggregator/model/MbaErrorCode:TERMS_AND_CONDITIONS_NOT_ACCEPTED	Lcom/db/pwcc/dbmobile/multi_bank_aggregator/model/MbaErrorCode;
    //   476: ldc 70
    //   478: ldc -101
    //   480: sipush 153
    //   483: iconst_3
    //   484: invokestatic 78	xxxxxx/uxxxxx:bb00620062bb0062b0062b0062	(Ljava/lang/String;CC)Ljava/lang/String;
    //   487: iconst_3
    //   488: anewarray 80	java/lang/Class
    //   491: dup
    //   492: iconst_0
    //   493: ldc 82
    //   495: aastore
    //   496: dup
    //   497: iconst_1
    //   498: getstatic 88	java/lang/Character:TYPE	Ljava/lang/Class;
    //   501: aastore
    //   502: dup
    //   503: iconst_2
    //   504: getstatic 88	java/lang/Character:TYPE	Ljava/lang/Class;
    //   507: aastore
    //   508: invokevirtual 92	java/lang/Class:getMethod	(Ljava/lang/String;[Ljava/lang/Class;)Ljava/lang/reflect/Method;
    //   511: astore_1
    //   512: aload_1
    //   513: aconst_null
    //   514: iconst_3
    //   515: anewarray 94	java/lang/Object
    //   518: dup
    //   519: iconst_0
    //   520: ldc -99
    //   522: aastore
    //   523: dup
    //   524: iconst_1
    //   525: bipush 66
    //   527: invokestatic 100	java/lang/Character:valueOf	(C)Ljava/lang/Character;
    //   530: aastore
    //   531: dup
    //   532: iconst_2
    //   533: iconst_2
    //   534: invokestatic 100	java/lang/Character:valueOf	(C)Ljava/lang/Character;
    //   537: aastore
    //   538: invokevirtual 106	java/lang/reflect/Method:invoke	(Ljava/lang/Object;[Ljava/lang/Object;)Ljava/lang/Object;
    //   541: astore_1
    //   542: new 2	com/db/pwcc/dbmobile/multi_bank_aggregator/model/MbaErrorCode
    //   545: dup
    //   546: aload_1
    //   547: checkcast 82	java/lang/String
    //   550: iconst_5
    //   551: iconst_0
    //   552: invokespecial 110	com/db/pwcc/dbmobile/multi_bank_aggregator/model/MbaErrorCode:<init>	(Ljava/lang/String;IZ)V
    //   555: putstatic 159	com/db/pwcc/dbmobile/multi_bank_aggregator/model/MbaErrorCode:NON_EXISTING_BANK	Lcom/db/pwcc/dbmobile/multi_bank_aggregator/model/MbaErrorCode;
    //   558: ldc 70
    //   560: ldc -95
    //   562: sipush 248
    //   565: iconst_4
    //   566: invokestatic 78	xxxxxx/uxxxxx:bb00620062bb0062b0062b0062	(Ljava/lang/String;CC)Ljava/lang/String;
    //   569: iconst_3
    //   570: anewarray 80	java/lang/Class
    //   573: dup
    //   574: iconst_0
    //   575: ldc 82
    //   577: aastore
    //   578: dup
    //   579: iconst_1
    //   580: getstatic 88	java/lang/Character:TYPE	Ljava/lang/Class;
    //   583: aastore
    //   584: dup
    //   585: iconst_2
    //   586: getstatic 88	java/lang/Character:TYPE	Ljava/lang/Class;
    //   589: aastore
    //   590: invokevirtual 92	java/lang/Class:getMethod	(Ljava/lang/String;[Ljava/lang/Class;)Ljava/lang/reflect/Method;
    //   593: astore_1
    //   594: aload_1
    //   595: aconst_null
    //   596: iconst_3
    //   597: anewarray 94	java/lang/Object
    //   600: dup
    //   601: iconst_0
    //   602: ldc -93
    //   604: aastore
    //   605: dup
    //   606: iconst_1
    //   607: sipush 147
    //   610: invokestatic 100	java/lang/Character:valueOf	(C)Ljava/lang/Character;
    //   613: aastore
    //   614: dup
    //   615: iconst_2
    //   616: iconst_0
    //   617: invokestatic 100	java/lang/Character:valueOf	(C)Ljava/lang/Character;
    //   620: aastore
    //   621: invokevirtual 106	java/lang/reflect/Method:invoke	(Ljava/lang/Object;[Ljava/lang/Object;)Ljava/lang/Object;
    //   624: astore_1
    //   625: new 2	com/db/pwcc/dbmobile/multi_bank_aggregator/model/MbaErrorCode
    //   628: dup
    //   629: aload_1
    //   630: checkcast 82	java/lang/String
    //   633: bipush 6
    //   635: iconst_0
    //   636: invokespecial 110	com/db/pwcc/dbmobile/multi_bank_aggregator/model/MbaErrorCode:<init>	(Ljava/lang/String;IZ)V
    //   639: putstatic 165	com/db/pwcc/dbmobile/multi_bank_aggregator/model/MbaErrorCode:MBA_CREDENTIALS_ERROR	Lcom/db/pwcc/dbmobile/multi_bank_aggregator/model/MbaErrorCode;
    //   642: ldc 70
    //   644: ldc -89
    //   646: sipush 210
    //   649: sipush 200
    //   652: iconst_3
    //   653: invokestatic 149	xxxxxx/uxxxxx:bbbb0062b0062b0062b0062	(Ljava/lang/String;CCC)Ljava/lang/String;
    //   656: iconst_3
    //   657: anewarray 80	java/lang/Class
    //   660: dup
    //   661: iconst_0
    //   662: ldc 82
    //   664: aastore
    //   665: dup
    //   666: iconst_1
    //   667: getstatic 88	java/lang/Character:TYPE	Ljava/lang/Class;
    //   670: aastore
    //   671: dup
    //   672: iconst_2
    //   673: getstatic 88	java/lang/Character:TYPE	Ljava/lang/Class;
    //   676: aastore
    //   677: invokevirtual 92	java/lang/Class:getMethod	(Ljava/lang/String;[Ljava/lang/Class;)Ljava/lang/reflect/Method;
    //   680: astore_1
    //   681: aload_1
    //   682: aconst_null
    //   683: iconst_3
    //   684: anewarray 94	java/lang/Object
    //   687: dup
    //   688: iconst_0
    //   689: ldc -87
    //   691: aastore
    //   692: dup
    //   693: iconst_1
    //   694: sipush 211
    //   697: invokestatic 100	java/lang/Character:valueOf	(C)Ljava/lang/Character;
    //   700: aastore
    //   701: dup
    //   702: iconst_2
    //   703: iconst_1
    //   704: invokestatic 100	java/lang/Character:valueOf	(C)Ljava/lang/Character;
    //   707: aastore
    //   708: invokevirtual 106	java/lang/reflect/Method:invoke	(Ljava/lang/Object;[Ljava/lang/Object;)Ljava/lang/Object;
    //   711: astore_1
    //   712: new 2	com/db/pwcc/dbmobile/multi_bank_aggregator/model/MbaErrorCode
    //   715: dup
    //   716: aload_1
    //   717: checkcast 82	java/lang/String
    //   720: bipush 7
    //   722: iconst_0
    //   723: invokespecial 110	com/db/pwcc/dbmobile/multi_bank_aggregator/model/MbaErrorCode:<init>	(Ljava/lang/String;IZ)V
    //   726: putstatic 171	com/db/pwcc/dbmobile/multi_bank_aggregator/model/MbaErrorCode:FUNCTION_NOT_AVAILABLE	Lcom/db/pwcc/dbmobile/multi_bank_aggregator/model/MbaErrorCode;
    //   729: ldc 70
    //   731: ldc -83
    //   733: bipush 42
    //   735: iconst_5
    //   736: invokestatic 78	xxxxxx/uxxxxx:bb00620062bb0062b0062b0062	(Ljava/lang/String;CC)Ljava/lang/String;
    //   739: iconst_3
    //   740: anewarray 80	java/lang/Class
    //   743: dup
    //   744: iconst_0
    //   745: ldc 82
    //   747: aastore
    //   748: dup
    //   749: iconst_1
    //   750: getstatic 88	java/lang/Character:TYPE	Ljava/lang/Class;
    //   753: aastore
    //   754: dup
    //   755: iconst_2
    //   756: getstatic 88	java/lang/Character:TYPE	Ljava/lang/Class;
    //   759: aastore
    //   760: invokevirtual 92	java/lang/Class:getMethod	(Ljava/lang/String;[Ljava/lang/Class;)Ljava/lang/reflect/Method;
    //   763: astore_1
    //   764: aload_1
    //   765: aconst_null
    //   766: iconst_3
    //   767: anewarray 94	java/lang/Object
    //   770: dup
    //   771: iconst_0
    //   772: ldc -81
    //   774: aastore
    //   775: dup
    //   776: iconst_1
    //   777: sipush 203
    //   780: invokestatic 100	java/lang/Character:valueOf	(C)Ljava/lang/Character;
    //   783: aastore
    //   784: dup
    //   785: iconst_2
    //   786: iconst_3
    //   787: invokestatic 100	java/lang/Character:valueOf	(C)Ljava/lang/Character;
    //   790: aastore
    //   791: invokevirtual 106	java/lang/reflect/Method:invoke	(Ljava/lang/Object;[Ljava/lang/Object;)Ljava/lang/Object;
    //   794: astore_1
    //   795: new 2	com/db/pwcc/dbmobile/multi_bank_aggregator/model/MbaErrorCode
    //   798: dup
    //   799: aload_1
    //   800: checkcast 82	java/lang/String
    //   803: bipush 8
    //   805: iconst_0
    //   806: invokespecial 110	com/db/pwcc/dbmobile/multi_bank_aggregator/model/MbaErrorCode:<init>	(Ljava/lang/String;IZ)V
    //   809: putstatic 177	com/db/pwcc/dbmobile/multi_bank_aggregator/model/MbaErrorCode:UNEXPECTED_FAILURE	Lcom/db/pwcc/dbmobile/multi_bank_aggregator/model/MbaErrorCode;
    //   812: ldc 70
    //   814: ldc -77
    //   816: bipush 51
    //   818: iconst_0
    //   819: invokestatic 78	xxxxxx/uxxxxx:bb00620062bb0062b0062b0062	(Ljava/lang/String;CC)Ljava/lang/String;
    //   822: iconst_3
    //   823: anewarray 80	java/lang/Class
    //   826: dup
    //   827: iconst_0
    //   828: ldc 82
    //   830: aastore
    //   831: dup
    //   832: iconst_1
    //   833: getstatic 88	java/lang/Character:TYPE	Ljava/lang/Class;
    //   836: aastore
    //   837: dup
    //   838: iconst_2
    //   839: getstatic 88	java/lang/Character:TYPE	Ljava/lang/Class;
    //   842: aastore
    //   843: invokevirtual 92	java/lang/Class:getMethod	(Ljava/lang/String;[Ljava/lang/Class;)Ljava/lang/reflect/Method;
    //   846: astore_1
    //   847: aload_1
    //   848: aconst_null
    //   849: iconst_3
    //   850: anewarray 94	java/lang/Object
    //   853: dup
    //   854: iconst_0
    //   855: ldc -75
    //   857: aastore
    //   858: dup
    //   859: iconst_1
    //   860: bipush 31
    //   862: invokestatic 100	java/lang/Character:valueOf	(C)Ljava/lang/Character;
    //   865: aastore
    //   866: dup
    //   867: iconst_2
    //   868: iconst_0
    //   869: invokestatic 100	java/lang/Character:valueOf	(C)Ljava/lang/Character;
    //   872: aastore
    //   873: invokevirtual 106	java/lang/reflect/Method:invoke	(Ljava/lang/Object;[Ljava/lang/Object;)Ljava/lang/Object;
    //   876: astore_1
    //   877: new 2	com/db/pwcc/dbmobile/multi_bank_aggregator/model/MbaErrorCode
    //   880: dup
    //   881: aload_1
    //   882: checkcast 82	java/lang/String
    //   885: bipush 9
    //   887: iconst_0
    //   888: invokespecial 110	com/db/pwcc/dbmobile/multi_bank_aggregator/model/MbaErrorCode:<init>	(Ljava/lang/String;IZ)V
    //   891: putstatic 183	com/db/pwcc/dbmobile/multi_bank_aggregator/model/MbaErrorCode:DEACTIVATE_MBA_ERROR	Lcom/db/pwcc/dbmobile/multi_bank_aggregator/model/MbaErrorCode;
    //   894: ldc 70
    //   896: ldc -71
    //   898: bipush 32
    //   900: iconst_0
    //   901: invokestatic 78	xxxxxx/uxxxxx:bb00620062bb0062b0062b0062	(Ljava/lang/String;CC)Ljava/lang/String;
    //   904: iconst_3
    //   905: anewarray 80	java/lang/Class
    //   908: dup
    //   909: iconst_0
    //   910: ldc 82
    //   912: aastore
    //   913: dup
    //   914: iconst_1
    //   915: getstatic 88	java/lang/Character:TYPE	Ljava/lang/Class;
    //   918: aastore
    //   919: dup
    //   920: iconst_2
    //   921: getstatic 88	java/lang/Character:TYPE	Ljava/lang/Class;
    //   924: aastore
    //   925: invokevirtual 92	java/lang/Class:getMethod	(Ljava/lang/String;[Ljava/lang/Class;)Ljava/lang/reflect/Method;
    //   928: astore_1
    //   929: aload_1
    //   930: aconst_null
    //   931: iconst_3
    //   932: anewarray 94	java/lang/Object
    //   935: dup
    //   936: iconst_0
    //   937: ldc -69
    //   939: aastore
    //   940: dup
    //   941: iconst_1
    //   942: sipush 169
    //   945: invokestatic 100	java/lang/Character:valueOf	(C)Ljava/lang/Character;
    //   948: aastore
    //   949: dup
    //   950: iconst_2
    //   951: iconst_3
    //   952: invokestatic 100	java/lang/Character:valueOf	(C)Ljava/lang/Character;
    //   955: aastore
    //   956: invokevirtual 106	java/lang/reflect/Method:invoke	(Ljava/lang/Object;[Ljava/lang/Object;)Ljava/lang/Object;
    //   959: astore_1
    //   960: new 2	com/db/pwcc/dbmobile/multi_bank_aggregator/model/MbaErrorCode
    //   963: dup
    //   964: aload_1
    //   965: checkcast 82	java/lang/String
    //   968: bipush 10
    //   970: iconst_0
    //   971: invokespecial 110	com/db/pwcc/dbmobile/multi_bank_aggregator/model/MbaErrorCode:<init>	(Ljava/lang/String;IZ)V
    //   974: putstatic 189	com/db/pwcc/dbmobile/multi_bank_aggregator/model/MbaErrorCode:TAN_PROCESS_FAILURE	Lcom/db/pwcc/dbmobile/multi_bank_aggregator/model/MbaErrorCode;
    //   977: ldc 70
    //   979: ldc -65
    //   981: bipush 36
    //   983: iconst_0
    //   984: invokestatic 78	xxxxxx/uxxxxx:bb00620062bb0062b0062b0062	(Ljava/lang/String;CC)Ljava/lang/String;
    //   987: iconst_4
    //   988: anewarray 80	java/lang/Class
    //   991: dup
    //   992: iconst_0
    //   993: ldc 82
    //   995: aastore
    //   996: dup
    //   997: iconst_1
    //   998: getstatic 88	java/lang/Character:TYPE	Ljava/lang/Class;
    //   1001: aastore
    //   1002: dup
    //   1003: iconst_2
    //   1004: getstatic 88	java/lang/Character:TYPE	Ljava/lang/Class;
    //   1007: aastore
    //   1008: dup
    //   1009: iconst_3
    //   1010: getstatic 88	java/lang/Character:TYPE	Ljava/lang/Class;
    //   1013: aastore
    //   1014: invokevirtual 92	java/lang/Class:getMethod	(Ljava/lang/String;[Ljava/lang/Class;)Ljava/lang/reflect/Method;
    //   1017: astore_1
    //   1018: aload_1
    //   1019: aconst_null
    //   1020: iconst_4
    //   1021: anewarray 94	java/lang/Object
    //   1024: dup
    //   1025: iconst_0
    //   1026: ldc -63
    //   1028: aastore
    //   1029: dup
    //   1030: iconst_1
    //   1031: bipush 113
    //   1033: invokestatic 100	java/lang/Character:valueOf	(C)Ljava/lang/Character;
    //   1036: aastore
    //   1037: dup
    //   1038: iconst_2
    //   1039: bipush 82
    //   1041: invokestatic 100	java/lang/Character:valueOf	(C)Ljava/lang/Character;
    //   1044: aastore
    //   1045: dup
    //   1046: iconst_3
    //   1047: iconst_3
    //   1048: invokestatic 100	java/lang/Character:valueOf	(C)Ljava/lang/Character;
    //   1051: aastore
    //   1052: invokevirtual 106	java/lang/reflect/Method:invoke	(Ljava/lang/Object;[Ljava/lang/Object;)Ljava/lang/Object;
    //   1055: astore_1
    //   1056: new 2	com/db/pwcc/dbmobile/multi_bank_aggregator/model/MbaErrorCode
    //   1059: dup
    //   1060: aload_1
    //   1061: checkcast 82	java/lang/String
    //   1064: bipush 11
    //   1066: iconst_0
    //   1067: invokespecial 110	com/db/pwcc/dbmobile/multi_bank_aggregator/model/MbaErrorCode:<init>	(Ljava/lang/String;IZ)V
    //   1070: putstatic 195	com/db/pwcc/dbmobile/multi_bank_aggregator/model/MbaErrorCode:FUNCTION_OUT_OF_SCOPE	Lcom/db/pwcc/dbmobile/multi_bank_aggregator/model/MbaErrorCode;
    //   1073: ldc 70
    //   1075: ldc -59
    //   1077: bipush 25
    //   1079: iconst_1
    //   1080: invokestatic 78	xxxxxx/uxxxxx:bb00620062bb0062b0062b0062	(Ljava/lang/String;CC)Ljava/lang/String;
    //   1083: iconst_3
    //   1084: anewarray 80	java/lang/Class
    //   1087: dup
    //   1088: iconst_0
    //   1089: ldc 82
    //   1091: aastore
    //   1092: dup
    //   1093: iconst_1
    //   1094: getstatic 88	java/lang/Character:TYPE	Ljava/lang/Class;
    //   1097: aastore
    //   1098: dup
    //   1099: iconst_2
    //   1100: getstatic 88	java/lang/Character:TYPE	Ljava/lang/Class;
    //   1103: aastore
    //   1104: invokevirtual 92	java/lang/Class:getMethod	(Ljava/lang/String;[Ljava/lang/Class;)Ljava/lang/reflect/Method;
    //   1107: astore_1
    //   1108: aload_1
    //   1109: aconst_null
    //   1110: iconst_3
    //   1111: anewarray 94	java/lang/Object
    //   1114: dup
    //   1115: iconst_0
    //   1116: ldc -57
    //   1118: aastore
    //   1119: dup
    //   1120: iconst_1
    //   1121: sipush 161
    //   1124: invokestatic 100	java/lang/Character:valueOf	(C)Ljava/lang/Character;
    //   1127: aastore
    //   1128: dup
    //   1129: iconst_2
    //   1130: iconst_5
    //   1131: invokestatic 100	java/lang/Character:valueOf	(C)Ljava/lang/Character;
    //   1134: aastore
    //   1135: invokevirtual 106	java/lang/reflect/Method:invoke	(Ljava/lang/Object;[Ljava/lang/Object;)Ljava/lang/Object;
    //   1138: astore_1
    //   1139: new 2	com/db/pwcc/dbmobile/multi_bank_aggregator/model/MbaErrorCode
    //   1142: dup
    //   1143: aload_1
    //   1144: checkcast 82	java/lang/String
    //   1147: bipush 12
    //   1149: iconst_0
    //   1150: invokespecial 110	com/db/pwcc/dbmobile/multi_bank_aggregator/model/MbaErrorCode:<init>	(Ljava/lang/String;IZ)V
    //   1153: putstatic 201	com/db/pwcc/dbmobile/multi_bank_aggregator/model/MbaErrorCode:DEACTIVATE_MBA_ACCEPT_TERMS	Lcom/db/pwcc/dbmobile/multi_bank_aggregator/model/MbaErrorCode;
    //   1156: ldc 70
    //   1158: ldc -53
    //   1160: bipush 53
    //   1162: iconst_4
    //   1163: invokestatic 78	xxxxxx/uxxxxx:bb00620062bb0062b0062b0062	(Ljava/lang/String;CC)Ljava/lang/String;
    //   1166: iconst_3
    //   1167: anewarray 80	java/lang/Class
    //   1170: dup
    //   1171: iconst_0
    //   1172: ldc 82
    //   1174: aastore
    //   1175: dup
    //   1176: iconst_1
    //   1177: getstatic 88	java/lang/Character:TYPE	Ljava/lang/Class;
    //   1180: aastore
    //   1181: dup
    //   1182: iconst_2
    //   1183: getstatic 88	java/lang/Character:TYPE	Ljava/lang/Class;
    //   1186: aastore
    //   1187: invokevirtual 92	java/lang/Class:getMethod	(Ljava/lang/String;[Ljava/lang/Class;)Ljava/lang/reflect/Method;
    //   1190: astore_1
    //   1191: aload_1
    //   1192: aconst_null
    //   1193: iconst_3
    //   1194: anewarray 94	java/lang/Object
    //   1197: dup
    //   1198: iconst_0
    //   1199: ldc -51
    //   1201: aastore
    //   1202: dup
    //   1203: iconst_1
    //   1204: sipush 251
    //   1207: invokestatic 100	java/lang/Character:valueOf	(C)Ljava/lang/Character;
    //   1210: aastore
    //   1211: dup
    //   1212: iconst_2
    //   1213: iconst_4
    //   1214: invokestatic 100	java/lang/Character:valueOf	(C)Ljava/lang/Character;
    //   1217: aastore
    //   1218: invokevirtual 106	java/lang/reflect/Method:invoke	(Ljava/lang/Object;[Ljava/lang/Object;)Ljava/lang/Object;
    //   1221: astore_1
    //   1222: new 2	com/db/pwcc/dbmobile/multi_bank_aggregator/model/MbaErrorCode
    //   1225: dup
    //   1226: aload_1
    //   1227: checkcast 82	java/lang/String
    //   1230: bipush 13
    //   1232: iconst_0
    //   1233: invokespecial 110	com/db/pwcc/dbmobile/multi_bank_aggregator/model/MbaErrorCode:<init>	(Ljava/lang/String;IZ)V
    //   1236: putstatic 207	com/db/pwcc/dbmobile/multi_bank_aggregator/model/MbaErrorCode:FORBIDDEN	Lcom/db/pwcc/dbmobile/multi_bank_aggregator/model/MbaErrorCode;
    //   1239: ldc 70
    //   1241: ldc -47
    //   1243: bipush 32
    //   1245: iconst_3
    //   1246: invokestatic 78	xxxxxx/uxxxxx:bb00620062bb0062b0062b0062	(Ljava/lang/String;CC)Ljava/lang/String;
    //   1249: iconst_3
    //   1250: anewarray 80	java/lang/Class
    //   1253: dup
    //   1254: iconst_0
    //   1255: ldc 82
    //   1257: aastore
    //   1258: dup
    //   1259: iconst_1
    //   1260: getstatic 88	java/lang/Character:TYPE	Ljava/lang/Class;
    //   1263: aastore
    //   1264: dup
    //   1265: iconst_2
    //   1266: getstatic 88	java/lang/Character:TYPE	Ljava/lang/Class;
    //   1269: aastore
    //   1270: invokevirtual 92	java/lang/Class:getMethod	(Ljava/lang/String;[Ljava/lang/Class;)Ljava/lang/reflect/Method;
    //   1273: astore_1
    //   1274: aload_1
    //   1275: aconst_null
    //   1276: iconst_3
    //   1277: anewarray 94	java/lang/Object
    //   1280: dup
    //   1281: iconst_0
    //   1282: ldc -45
    //   1284: aastore
    //   1285: dup
    //   1286: iconst_1
    //   1287: sipush 228
    //   1290: invokestatic 100	java/lang/Character:valueOf	(C)Ljava/lang/Character;
    //   1293: aastore
    //   1294: dup
    //   1295: iconst_2
    //   1296: iconst_3
    //   1297: invokestatic 100	java/lang/Character:valueOf	(C)Ljava/lang/Character;
    //   1300: aastore
    //   1301: invokevirtual 106	java/lang/reflect/Method:invoke	(Ljava/lang/Object;[Ljava/lang/Object;)Ljava/lang/Object;
    //   1304: astore_1
    //   1305: new 2	com/db/pwcc/dbmobile/multi_bank_aggregator/model/MbaErrorCode
    //   1308: dup
    //   1309: aload_1
    //   1310: checkcast 82	java/lang/String
    //   1313: bipush 14
    //   1315: iconst_1
    //   1316: invokespecial 110	com/db/pwcc/dbmobile/multi_bank_aggregator/model/MbaErrorCode:<init>	(Ljava/lang/String;IZ)V
    //   1319: putstatic 213	com/db/pwcc/dbmobile/multi_bank_aggregator/model/MbaErrorCode:SYNCHRONIZATION_FAILURE	Lcom/db/pwcc/dbmobile/multi_bank_aggregator/model/MbaErrorCode;
    //   1322: ldc 70
    //   1324: ldc -41
    //   1326: bipush 83
    //   1328: iconst_4
    //   1329: invokestatic 78	xxxxxx/uxxxxx:bb00620062bb0062b0062b0062	(Ljava/lang/String;CC)Ljava/lang/String;
    //   1332: iconst_3
    //   1333: anewarray 80	java/lang/Class
    //   1336: dup
    //   1337: iconst_0
    //   1338: ldc 82
    //   1340: aastore
    //   1341: dup
    //   1342: iconst_1
    //   1343: getstatic 88	java/lang/Character:TYPE	Ljava/lang/Class;
    //   1346: aastore
    //   1347: dup
    //   1348: iconst_2
    //   1349: getstatic 88	java/lang/Character:TYPE	Ljava/lang/Class;
    //   1352: aastore
    //   1353: invokevirtual 92	java/lang/Class:getMethod	(Ljava/lang/String;[Ljava/lang/Class;)Ljava/lang/reflect/Method;
    //   1356: astore_1
    //   1357: aload_1
    //   1358: aconst_null
    //   1359: iconst_3
    //   1360: anewarray 94	java/lang/Object
    //   1363: dup
    //   1364: iconst_0
    //   1365: ldc -39
    //   1367: aastore
    //   1368: dup
    //   1369: iconst_1
    //   1370: bipush 19
    //   1372: invokestatic 100	java/lang/Character:valueOf	(C)Ljava/lang/Character;
    //   1375: aastore
    //   1376: dup
    //   1377: iconst_2
    //   1378: iconst_2
    //   1379: invokestatic 100	java/lang/Character:valueOf	(C)Ljava/lang/Character;
    //   1382: aastore
    //   1383: invokevirtual 106	java/lang/reflect/Method:invoke	(Ljava/lang/Object;[Ljava/lang/Object;)Ljava/lang/Object;
    //   1386: astore_1
    //   1387: new 2	com/db/pwcc/dbmobile/multi_bank_aggregator/model/MbaErrorCode
    //   1390: dup
    //   1391: aload_1
    //   1392: checkcast 82	java/lang/String
    //   1395: bipush 15
    //   1397: iconst_1
    //   1398: invokespecial 110	com/db/pwcc/dbmobile/multi_bank_aggregator/model/MbaErrorCode:<init>	(Ljava/lang/String;IZ)V
    //   1401: putstatic 219	com/db/pwcc/dbmobile/multi_bank_aggregator/model/MbaErrorCode:SYNCHRONIZATION_INCORRECT_CREDENTIALS	Lcom/db/pwcc/dbmobile/multi_bank_aggregator/model/MbaErrorCode;
    //   1404: ldc 70
    //   1406: ldc -35
    //   1408: bipush 44
    //   1410: bipush 80
    //   1412: iconst_1
    //   1413: invokestatic 149	xxxxxx/uxxxxx:bbbb0062b0062b0062b0062	(Ljava/lang/String;CCC)Ljava/lang/String;
    //   1416: iconst_3
    //   1417: anewarray 80	java/lang/Class
    //   1420: dup
    //   1421: iconst_0
    //   1422: ldc 82
    //   1424: aastore
    //   1425: dup
    //   1426: iconst_1
    //   1427: getstatic 88	java/lang/Character:TYPE	Ljava/lang/Class;
    //   1430: aastore
    //   1431: dup
    //   1432: iconst_2
    //   1433: getstatic 88	java/lang/Character:TYPE	Ljava/lang/Class;
    //   1436: aastore
    //   1437: invokevirtual 92	java/lang/Class:getMethod	(Ljava/lang/String;[Ljava/lang/Class;)Ljava/lang/reflect/Method;
    //   1440: astore_1
    //   1441: aload_1
    //   1442: aconst_null
    //   1443: iconst_3
    //   1444: anewarray 94	java/lang/Object
    //   1447: dup
    //   1448: iconst_0
    //   1449: ldc -33
    //   1451: aastore
    //   1452: dup
    //   1453: iconst_1
    //   1454: sipush 186
    //   1457: invokestatic 100	java/lang/Character:valueOf	(C)Ljava/lang/Character;
    //   1460: aastore
    //   1461: dup
    //   1462: iconst_2
    //   1463: iconst_4
    //   1464: invokestatic 100	java/lang/Character:valueOf	(C)Ljava/lang/Character;
    //   1467: aastore
    //   1468: invokevirtual 106	java/lang/reflect/Method:invoke	(Ljava/lang/Object;[Ljava/lang/Object;)Ljava/lang/Object;
    //   1471: astore_1
    //   1472: new 2	com/db/pwcc/dbmobile/multi_bank_aggregator/model/MbaErrorCode
    //   1475: dup
    //   1476: aload_1
    //   1477: checkcast 82	java/lang/String
    //   1480: bipush 16
    //   1482: iconst_1
    //   1483: invokespecial 110	com/db/pwcc/dbmobile/multi_bank_aggregator/model/MbaErrorCode:<init>	(Ljava/lang/String;IZ)V
    //   1486: putstatic 225	com/db/pwcc/dbmobile/multi_bank_aggregator/model/MbaErrorCode:BANK_COMMUNICATION_FAILURE	Lcom/db/pwcc/dbmobile/multi_bank_aggregator/model/MbaErrorCode;
    //   1489: ldc 70
    //   1491: ldc -29
    //   1493: bipush 67
    //   1495: bipush 95
    //   1497: iconst_0
    //   1498: invokestatic 149	xxxxxx/uxxxxx:bbbb0062b0062b0062b0062	(Ljava/lang/String;CCC)Ljava/lang/String;
    //   1501: iconst_3
    //   1502: anewarray 80	java/lang/Class
    //   1505: dup
    //   1506: iconst_0
    //   1507: ldc 82
    //   1509: aastore
    //   1510: dup
    //   1511: iconst_1
    //   1512: getstatic 88	java/lang/Character:TYPE	Ljava/lang/Class;
    //   1515: aastore
    //   1516: dup
    //   1517: iconst_2
    //   1518: getstatic 88	java/lang/Character:TYPE	Ljava/lang/Class;
    //   1521: aastore
    //   1522: invokevirtual 92	java/lang/Class:getMethod	(Ljava/lang/String;[Ljava/lang/Class;)Ljava/lang/reflect/Method;
    //   1525: astore_1
    //   1526: aload_1
    //   1527: aconst_null
    //   1528: iconst_3
    //   1529: anewarray 94	java/lang/Object
    //   1532: dup
    //   1533: iconst_0
    //   1534: ldc -27
    //   1536: aastore
    //   1537: dup
    //   1538: iconst_1
    //   1539: sipush 163
    //   1542: invokestatic 100	java/lang/Character:valueOf	(C)Ljava/lang/Character;
    //   1545: aastore
    //   1546: dup
    //   1547: iconst_2
    //   1548: iconst_0
    //   1549: invokestatic 100	java/lang/Character:valueOf	(C)Ljava/lang/Character;
    //   1552: aastore
    //   1553: invokevirtual 106	java/lang/reflect/Method:invoke	(Ljava/lang/Object;[Ljava/lang/Object;)Ljava/lang/Object;
    //   1556: astore_1
    //   1557: new 2	com/db/pwcc/dbmobile/multi_bank_aggregator/model/MbaErrorCode
    //   1560: dup
    //   1561: aload_1
    //   1562: checkcast 82	java/lang/String
    //   1565: bipush 17
    //   1567: iconst_1
    //   1568: invokespecial 110	com/db/pwcc/dbmobile/multi_bank_aggregator/model/MbaErrorCode:<init>	(Ljava/lang/String;IZ)V
    //   1571: putstatic 231	com/db/pwcc/dbmobile/multi_bank_aggregator/model/MbaErrorCode:BANK_NOT_AVAILABLE	Lcom/db/pwcc/dbmobile/multi_bank_aggregator/model/MbaErrorCode;
    //   1574: ldc 70
    //   1576: ldc -23
    //   1578: sipush 148
    //   1581: sipush 231
    //   1584: iconst_1
    //   1585: invokestatic 149	xxxxxx/uxxxxx:bbbb0062b0062b0062b0062	(Ljava/lang/String;CCC)Ljava/lang/String;
    //   1588: iconst_3
    //   1589: anewarray 80	java/lang/Class
    //   1592: dup
    //   1593: iconst_0
    //   1594: ldc 82
    //   1596: aastore
    //   1597: dup
    //   1598: iconst_1
    //   1599: getstatic 88	java/lang/Character:TYPE	Ljava/lang/Class;
    //   1602: aastore
    //   1603: dup
    //   1604: iconst_2
    //   1605: getstatic 88	java/lang/Character:TYPE	Ljava/lang/Class;
    //   1608: aastore
    //   1609: invokevirtual 92	java/lang/Class:getMethod	(Ljava/lang/String;[Ljava/lang/Class;)Ljava/lang/reflect/Method;
    //   1612: astore_1
    //   1613: aload_1
    //   1614: aconst_null
    //   1615: iconst_3
    //   1616: anewarray 94	java/lang/Object
    //   1619: dup
    //   1620: iconst_0
    //   1621: ldc -21
    //   1623: aastore
    //   1624: dup
    //   1625: iconst_1
    //   1626: bipush 75
    //   1628: invokestatic 100	java/lang/Character:valueOf	(C)Ljava/lang/Character;
    //   1631: aastore
    //   1632: dup
    //   1633: iconst_2
    //   1634: iconst_2
    //   1635: invokestatic 100	java/lang/Character:valueOf	(C)Ljava/lang/Character;
    //   1638: aastore
    //   1639: invokevirtual 106	java/lang/reflect/Method:invoke	(Ljava/lang/Object;[Ljava/lang/Object;)Ljava/lang/Object;
    //   1642: astore_1
    //   1643: new 2	com/db/pwcc/dbmobile/multi_bank_aggregator/model/MbaErrorCode
    //   1646: dup
    //   1647: aload_1
    //   1648: checkcast 82	java/lang/String
    //   1651: bipush 18
    //   1653: iconst_1
    //   1654: invokespecial 110	com/db/pwcc/dbmobile/multi_bank_aggregator/model/MbaErrorCode:<init>	(Ljava/lang/String;IZ)V
    //   1657: putstatic 237	com/db/pwcc/dbmobile/multi_bank_aggregator/model/MbaErrorCode:PIN_CHANGE_REQUIRED	Lcom/db/pwcc/dbmobile/multi_bank_aggregator/model/MbaErrorCode;
    //   1660: ldc 70
    //   1662: ldc -17
    //   1664: sipush 177
    //   1667: bipush 8
    //   1669: iconst_1
    //   1670: invokestatic 149	xxxxxx/uxxxxx:bbbb0062b0062b0062b0062	(Ljava/lang/String;CCC)Ljava/lang/String;
    //   1673: iconst_4
    //   1674: anewarray 80	java/lang/Class
    //   1677: dup
    //   1678: iconst_0
    //   1679: ldc 82
    //   1681: aastore
    //   1682: dup
    //   1683: iconst_1
    //   1684: getstatic 88	java/lang/Character:TYPE	Ljava/lang/Class;
    //   1687: aastore
    //   1688: dup
    //   1689: iconst_2
    //   1690: getstatic 88	java/lang/Character:TYPE	Ljava/lang/Class;
    //   1693: aastore
    //   1694: dup
    //   1695: iconst_3
    //   1696: getstatic 88	java/lang/Character:TYPE	Ljava/lang/Class;
    //   1699: aastore
    //   1700: invokevirtual 92	java/lang/Class:getMethod	(Ljava/lang/String;[Ljava/lang/Class;)Ljava/lang/reflect/Method;
    //   1703: astore_1
    //   1704: aload_1
    //   1705: aconst_null
    //   1706: iconst_4
    //   1707: anewarray 94	java/lang/Object
    //   1710: dup
    //   1711: iconst_0
    //   1712: ldc -15
    //   1714: aastore
    //   1715: dup
    //   1716: iconst_1
    //   1717: sipush 131
    //   1720: invokestatic 100	java/lang/Character:valueOf	(C)Ljava/lang/Character;
    //   1723: aastore
    //   1724: dup
    //   1725: iconst_2
    //   1726: sipush 180
    //   1729: invokestatic 100	java/lang/Character:valueOf	(C)Ljava/lang/Character;
    //   1732: aastore
    //   1733: dup
    //   1734: iconst_3
    //   1735: iconst_3
    //   1736: invokestatic 100	java/lang/Character:valueOf	(C)Ljava/lang/Character;
    //   1739: aastore
    //   1740: invokevirtual 106	java/lang/reflect/Method:invoke	(Ljava/lang/Object;[Ljava/lang/Object;)Ljava/lang/Object;
    //   1743: astore_1
    //   1744: new 2	com/db/pwcc/dbmobile/multi_bank_aggregator/model/MbaErrorCode
    //   1747: dup
    //   1748: aload_1
    //   1749: checkcast 82	java/lang/String
    //   1752: bipush 19
    //   1754: iconst_1
    //   1755: invokespecial 110	com/db/pwcc/dbmobile/multi_bank_aggregator/model/MbaErrorCode:<init>	(Ljava/lang/String;IZ)V
    //   1758: putstatic 243	com/db/pwcc/dbmobile/multi_bank_aggregator/model/MbaErrorCode:ONLINE_ACCOUNT_BLOCKED	Lcom/db/pwcc/dbmobile/multi_bank_aggregator/model/MbaErrorCode;
    //   1761: ldc 70
    //   1763: ldc -11
    //   1765: bipush 55
    //   1767: sipush 150
    //   1770: iconst_3
    //   1771: invokestatic 149	xxxxxx/uxxxxx:bbbb0062b0062b0062b0062	(Ljava/lang/String;CCC)Ljava/lang/String;
    //   1774: iconst_3
    //   1775: anewarray 80	java/lang/Class
    //   1778: dup
    //   1779: iconst_0
    //   1780: ldc 82
    //   1782: aastore
    //   1783: dup
    //   1784: iconst_1
    //   1785: getstatic 88	java/lang/Character:TYPE	Ljava/lang/Class;
    //   1788: aastore
    //   1789: dup
    //   1790: iconst_2
    //   1791: getstatic 88	java/lang/Character:TYPE	Ljava/lang/Class;
    //   1794: aastore
    //   1795: invokevirtual 92	java/lang/Class:getMethod	(Ljava/lang/String;[Ljava/lang/Class;)Ljava/lang/reflect/Method;
    //   1798: astore_1
    //   1799: aload_1
    //   1800: aconst_null
    //   1801: iconst_3
    //   1802: anewarray 94	java/lang/Object
    //   1805: dup
    //   1806: iconst_0
    //   1807: ldc -9
    //   1809: aastore
    //   1810: dup
    //   1811: iconst_1
    //   1812: bipush 125
    //   1814: invokestatic 100	java/lang/Character:valueOf	(C)Ljava/lang/Character;
    //   1817: aastore
    //   1818: dup
    //   1819: iconst_2
    //   1820: iconst_3
    //   1821: invokestatic 100	java/lang/Character:valueOf	(C)Ljava/lang/Character;
    //   1824: aastore
    //   1825: invokevirtual 106	java/lang/reflect/Method:invoke	(Ljava/lang/Object;[Ljava/lang/Object;)Ljava/lang/Object;
    //   1828: astore_1
    //   1829: new 2	com/db/pwcc/dbmobile/multi_bank_aggregator/model/MbaErrorCode
    //   1832: dup
    //   1833: aload_1
    //   1834: checkcast 82	java/lang/String
    //   1837: bipush 20
    //   1839: iconst_1
    //   1840: invokespecial 110	com/db/pwcc/dbmobile/multi_bank_aggregator/model/MbaErrorCode:<init>	(Ljava/lang/String;IZ)V
    //   1843: putstatic 249	com/db/pwcc/dbmobile/multi_bank_aggregator/model/MbaErrorCode:HBCI_NOT_ACTIVE	Lcom/db/pwcc/dbmobile/multi_bank_aggregator/model/MbaErrorCode;
    //   1846: invokestatic 134	com/db/pwcc/dbmobile/multi_bank_aggregator/model/MbaErrorCode:bf00660066f00660066ff	()I
    //   1849: istore_0
    //   1850: iload_0
    //   1851: invokestatic 137	com/db/pwcc/dbmobile/multi_bank_aggregator/model/MbaErrorCode:bfff006600660066ff	()I
    //   1854: iload_0
    //   1855: iadd
    //   1856: imul
    //   1857: invokestatic 140	com/db/pwcc/dbmobile/multi_bank_aggregator/model/MbaErrorCode:b0066ff006600660066ff	()I
    //   1860: irem
    //   1861: tableswitch	default:+19->1880, 0:+19->1880
    //   1880: ldc 70
    //   1882: ldc -95
    //   1884: sipush 250
    //   1887: iconst_5
    //   1888: invokestatic 78	xxxxxx/uxxxxx:bb00620062bb0062b0062b0062	(Ljava/lang/String;CC)Ljava/lang/String;
    //   1891: iconst_3
    //   1892: anewarray 80	java/lang/Class
    //   1895: dup
    //   1896: iconst_0
    //   1897: ldc 82
    //   1899: aastore
    //   1900: dup
    //   1901: iconst_1
    //   1902: getstatic 88	java/lang/Character:TYPE	Ljava/lang/Class;
    //   1905: aastore
    //   1906: dup
    //   1907: iconst_2
    //   1908: getstatic 88	java/lang/Character:TYPE	Ljava/lang/Class;
    //   1911: aastore
    //   1912: invokevirtual 92	java/lang/Class:getMethod	(Ljava/lang/String;[Ljava/lang/Class;)Ljava/lang/reflect/Method;
    //   1915: astore_1
    //   1916: aload_1
    //   1917: aconst_null
    //   1918: iconst_3
    //   1919: anewarray 94	java/lang/Object
    //   1922: dup
    //   1923: iconst_0
    //   1924: ldc -5
    //   1926: aastore
    //   1927: dup
    //   1928: iconst_1
    //   1929: sipush 254
    //   1932: invokestatic 100	java/lang/Character:valueOf	(C)Ljava/lang/Character;
    //   1935: aastore
    //   1936: dup
    //   1937: iconst_2
    //   1938: iconst_5
    //   1939: invokestatic 100	java/lang/Character:valueOf	(C)Ljava/lang/Character;
    //   1942: aastore
    //   1943: invokevirtual 106	java/lang/reflect/Method:invoke	(Ljava/lang/Object;[Ljava/lang/Object;)Ljava/lang/Object;
    //   1946: astore_1
    //   1947: new 2	com/db/pwcc/dbmobile/multi_bank_aggregator/model/MbaErrorCode
    //   1950: dup
    //   1951: aload_1
    //   1952: checkcast 82	java/lang/String
    //   1955: bipush 21
    //   1957: iconst_1
    //   1958: invokespecial 110	com/db/pwcc/dbmobile/multi_bank_aggregator/model/MbaErrorCode:<init>	(Ljava/lang/String;IZ)V
    //   1961: putstatic 253	com/db/pwcc/dbmobile/multi_bank_aggregator/model/MbaErrorCode:ACCOUNT_DOES_NOT_EXIST	Lcom/db/pwcc/dbmobile/multi_bank_aggregator/model/MbaErrorCode;
    //   1964: ldc 70
    //   1966: ldc -1
    //   1968: sipush 129
    //   1971: sipush 192
    //   1974: iconst_1
    //   1975: invokestatic 149	xxxxxx/uxxxxx:bbbb0062b0062b0062b0062	(Ljava/lang/String;CCC)Ljava/lang/String;
    //   1978: iconst_3
    //   1979: anewarray 80	java/lang/Class
    //   1982: dup
    //   1983: iconst_0
    //   1984: ldc 82
    //   1986: aastore
    //   1987: dup
    //   1988: iconst_1
    //   1989: getstatic 88	java/lang/Character:TYPE	Ljava/lang/Class;
    //   1992: aastore
    //   1993: dup
    //   1994: iconst_2
    //   1995: getstatic 88	java/lang/Character:TYPE	Ljava/lang/Class;
    //   1998: aastore
    //   1999: invokevirtual 92	java/lang/Class:getMethod	(Ljava/lang/String;[Ljava/lang/Class;)Ljava/lang/reflect/Method;
    //   2002: astore_1
    //   2003: aload_1
    //   2004: aconst_null
    //   2005: iconst_3
    //   2006: anewarray 94	java/lang/Object
    //   2009: dup
    //   2010: iconst_0
    //   2011: ldc_w 257
    //   2014: aastore
    //   2015: dup
    //   2016: iconst_1
    //   2017: sipush 207
    //   2020: invokestatic 100	java/lang/Character:valueOf	(C)Ljava/lang/Character;
    //   2023: aastore
    //   2024: dup
    //   2025: iconst_2
    //   2026: iconst_1
    //   2027: invokestatic 100	java/lang/Character:valueOf	(C)Ljava/lang/Character;
    //   2030: aastore
    //   2031: invokevirtual 106	java/lang/reflect/Method:invoke	(Ljava/lang/Object;[Ljava/lang/Object;)Ljava/lang/Object;
    //   2034: astore_1
    //   2035: aload_1
    //   2036: checkcast 82	java/lang/String
    //   2039: astore_1
    //   2040: invokestatic 134	com/db/pwcc/dbmobile/multi_bank_aggregator/model/MbaErrorCode:bf00660066f00660066ff	()I
    //   2043: istore_0
    //   2044: iload_0
    //   2045: invokestatic 137	com/db/pwcc/dbmobile/multi_bank_aggregator/model/MbaErrorCode:bfff006600660066ff	()I
    //   2048: iload_0
    //   2049: iadd
    //   2050: imul
    //   2051: invokestatic 140	com/db/pwcc/dbmobile/multi_bank_aggregator/model/MbaErrorCode:b0066ff006600660066ff	()I
    //   2054: irem
    //   2055: tableswitch	default:+17->2072, 0:+17->2072
    //   2072: new 2	com/db/pwcc/dbmobile/multi_bank_aggregator/model/MbaErrorCode
    //   2075: dup
    //   2076: aload_1
    //   2077: bipush 22
    //   2079: iconst_1
    //   2080: invokespecial 110	com/db/pwcc/dbmobile/multi_bank_aggregator/model/MbaErrorCode:<init>	(Ljava/lang/String;IZ)V
    //   2083: putstatic 259	com/db/pwcc/dbmobile/multi_bank_aggregator/model/MbaErrorCode:NO_RIGHTS_FOR_ACCOUNT	Lcom/db/pwcc/dbmobile/multi_bank_aggregator/model/MbaErrorCode;
    //   2086: ldc 70
    //   2088: ldc_w 261
    //   2091: bipush 44
    //   2093: bipush 34
    //   2095: iconst_0
    //   2096: invokestatic 149	xxxxxx/uxxxxx:bbbb0062b0062b0062b0062	(Ljava/lang/String;CCC)Ljava/lang/String;
    //   2099: iconst_3
    //   2100: anewarray 80	java/lang/Class
    //   2103: dup
    //   2104: iconst_0
    //   2105: ldc 82
    //   2107: aastore
    //   2108: dup
    //   2109: iconst_1
    //   2110: getstatic 88	java/lang/Character:TYPE	Ljava/lang/Class;
    //   2113: aastore
    //   2114: dup
    //   2115: iconst_2
    //   2116: getstatic 88	java/lang/Character:TYPE	Ljava/lang/Class;
    //   2119: aastore
    //   2120: invokevirtual 92	java/lang/Class:getMethod	(Ljava/lang/String;[Ljava/lang/Class;)Ljava/lang/reflect/Method;
    //   2123: astore_1
    //   2124: aload_1
    //   2125: aconst_null
    //   2126: iconst_3
    //   2127: anewarray 94	java/lang/Object
    //   2130: dup
    //   2131: iconst_0
    //   2132: ldc_w 263
    //   2135: aastore
    //   2136: dup
    //   2137: iconst_1
    //   2138: bipush 121
    //   2140: invokestatic 100	java/lang/Character:valueOf	(C)Ljava/lang/Character;
    //   2143: aastore
    //   2144: dup
    //   2145: iconst_2
    //   2146: iconst_3
    //   2147: invokestatic 100	java/lang/Character:valueOf	(C)Ljava/lang/Character;
    //   2150: aastore
    //   2151: invokevirtual 106	java/lang/reflect/Method:invoke	(Ljava/lang/Object;[Ljava/lang/Object;)Ljava/lang/Object;
    //   2154: astore_1
    //   2155: new 2	com/db/pwcc/dbmobile/multi_bank_aggregator/model/MbaErrorCode
    //   2158: dup
    //   2159: aload_1
    //   2160: checkcast 82	java/lang/String
    //   2163: bipush 23
    //   2165: iconst_1
    //   2166: invokespecial 110	com/db/pwcc/dbmobile/multi_bank_aggregator/model/MbaErrorCode:<init>	(Ljava/lang/String;IZ)V
    //   2169: putstatic 265	com/db/pwcc/dbmobile/multi_bank_aggregator/model/MbaErrorCode:ACCOUNT_BLOCKED	Lcom/db/pwcc/dbmobile/multi_bank_aggregator/model/MbaErrorCode;
    //   2172: ldc 70
    //   2174: ldc_w 267
    //   2177: sipush 131
    //   2180: iconst_3
    //   2181: invokestatic 78	xxxxxx/uxxxxx:bb00620062bb0062b0062b0062	(Ljava/lang/String;CC)Ljava/lang/String;
    //   2184: iconst_4
    //   2185: anewarray 80	java/lang/Class
    //   2188: dup
    //   2189: iconst_0
    //   2190: ldc 82
    //   2192: aastore
    //   2193: dup
    //   2194: iconst_1
    //   2195: getstatic 88	java/lang/Character:TYPE	Ljava/lang/Class;
    //   2198: aastore
    //   2199: dup
    //   2200: iconst_2
    //   2201: getstatic 88	java/lang/Character:TYPE	Ljava/lang/Class;
    //   2204: aastore
    //   2205: dup
    //   2206: iconst_3
    //   2207: getstatic 88	java/lang/Character:TYPE	Ljava/lang/Class;
    //   2210: aastore
    //   2211: invokevirtual 92	java/lang/Class:getMethod	(Ljava/lang/String;[Ljava/lang/Class;)Ljava/lang/reflect/Method;
    //   2214: astore_1
    //   2215: aload_1
    //   2216: aconst_null
    //   2217: iconst_4
    //   2218: anewarray 94	java/lang/Object
    //   2221: dup
    //   2222: iconst_0
    //   2223: ldc_w 269
    //   2226: aastore
    //   2227: dup
    //   2228: iconst_1
    //   2229: sipush 150
    //   2232: invokestatic 100	java/lang/Character:valueOf	(C)Ljava/lang/Character;
    //   2235: aastore
    //   2236: dup
    //   2237: iconst_2
    //   2238: bipush 81
    //   2240: invokestatic 100	java/lang/Character:valueOf	(C)Ljava/lang/Character;
    //   2243: aastore
    //   2244: dup
    //   2245: iconst_3
    //   2246: iconst_0
    //   2247: invokestatic 100	java/lang/Character:valueOf	(C)Ljava/lang/Character;
    //   2250: aastore
    //   2251: invokevirtual 106	java/lang/reflect/Method:invoke	(Ljava/lang/Object;[Ljava/lang/Object;)Ljava/lang/Object;
    //   2254: astore_1
    //   2255: new 2	com/db/pwcc/dbmobile/multi_bank_aggregator/model/MbaErrorCode
    //   2258: dup
    //   2259: aload_1
    //   2260: checkcast 82	java/lang/String
    //   2263: bipush 24
    //   2265: iconst_1
    //   2266: invokespecial 110	com/db/pwcc/dbmobile/multi_bank_aggregator/model/MbaErrorCode:<init>	(Ljava/lang/String;IZ)V
    //   2269: putstatic 271	com/db/pwcc/dbmobile/multi_bank_aggregator/model/MbaErrorCode:UNKNOWN_ACCOUNT	Lcom/db/pwcc/dbmobile/multi_bank_aggregator/model/MbaErrorCode;
    //   2272: ldc 70
    //   2274: ldc_w 273
    //   2277: sipush 147
    //   2280: bipush 23
    //   2282: iconst_1
    //   2283: invokestatic 149	xxxxxx/uxxxxx:bbbb0062b0062b0062b0062	(Ljava/lang/String;CCC)Ljava/lang/String;
    //   2286: iconst_3
    //   2287: anewarray 80	java/lang/Class
    //   2290: dup
    //   2291: iconst_0
    //   2292: ldc 82
    //   2294: aastore
    //   2295: dup
    //   2296: iconst_1
    //   2297: getstatic 88	java/lang/Character:TYPE	Ljava/lang/Class;
    //   2300: aastore
    //   2301: dup
    //   2302: iconst_2
    //   2303: getstatic 88	java/lang/Character:TYPE	Ljava/lang/Class;
    //   2306: aastore
    //   2307: invokevirtual 92	java/lang/Class:getMethod	(Ljava/lang/String;[Ljava/lang/Class;)Ljava/lang/reflect/Method;
    //   2310: astore_1
    //   2311: aload_1
    //   2312: aconst_null
    //   2313: iconst_3
    //   2314: anewarray 94	java/lang/Object
    //   2317: dup
    //   2318: iconst_0
    //   2319: ldc_w 275
    //   2322: aastore
    //   2323: dup
    //   2324: iconst_1
    //   2325: bipush 102
    //   2327: invokestatic 100	java/lang/Character:valueOf	(C)Ljava/lang/Character;
    //   2330: aastore
    //   2331: dup
    //   2332: iconst_2
    //   2333: iconst_1
    //   2334: invokestatic 100	java/lang/Character:valueOf	(C)Ljava/lang/Character;
    //   2337: aastore
    //   2338: invokevirtual 106	java/lang/reflect/Method:invoke	(Ljava/lang/Object;[Ljava/lang/Object;)Ljava/lang/Object;
    //   2341: astore_1
    //   2342: new 2	com/db/pwcc/dbmobile/multi_bank_aggregator/model/MbaErrorCode
    //   2345: dup
    //   2346: aload_1
    //   2347: checkcast 82	java/lang/String
    //   2350: bipush 25
    //   2352: iconst_0
    //   2353: invokespecial 110	com/db/pwcc/dbmobile/multi_bank_aggregator/model/MbaErrorCode:<init>	(Ljava/lang/String;IZ)V
    //   2356: putstatic 277	com/db/pwcc/dbmobile/multi_bank_aggregator/model/MbaErrorCode:DEFAULT_CODE	Lcom/db/pwcc/dbmobile/multi_bank_aggregator/model/MbaErrorCode;
    //   2359: bipush 26
    //   2361: anewarray 2	com/db/pwcc/dbmobile/multi_bank_aggregator/model/MbaErrorCode
    //   2364: dup
    //   2365: iconst_0
    //   2366: getstatic 112	com/db/pwcc/dbmobile/multi_bank_aggregator/model/MbaErrorCode:ADD_MBA_ACCOUNT_SAME_USER	Lcom/db/pwcc/dbmobile/multi_bank_aggregator/model/MbaErrorCode;
    //   2369: aastore
    //   2370: dup
    //   2371: iconst_1
    //   2372: getstatic 118	com/db/pwcc/dbmobile/multi_bank_aggregator/model/MbaErrorCode:ADD_PRODUCT_ERROR	Lcom/db/pwcc/dbmobile/multi_bank_aggregator/model/MbaErrorCode;
    //   2375: aastore
    //   2376: dup
    //   2377: iconst_2
    //   2378: getstatic 124	com/db/pwcc/dbmobile/multi_bank_aggregator/model/MbaErrorCode:DELETE_PRODUCT_ERROR	Lcom/db/pwcc/dbmobile/multi_bank_aggregator/model/MbaErrorCode;
    //   2381: aastore
    //   2382: dup
    //   2383: iconst_3
    //   2384: getstatic 130	com/db/pwcc/dbmobile/multi_bank_aggregator/model/MbaErrorCode:NO_RESULTS	Lcom/db/pwcc/dbmobile/multi_bank_aggregator/model/MbaErrorCode;
    //   2387: aastore
    //   2388: dup
    //   2389: iconst_4
    //   2390: getstatic 153	com/db/pwcc/dbmobile/multi_bank_aggregator/model/MbaErrorCode:TERMS_AND_CONDITIONS_NOT_ACCEPTED	Lcom/db/pwcc/dbmobile/multi_bank_aggregator/model/MbaErrorCode;
    //   2393: aastore
    //   2394: dup
    //   2395: iconst_5
    //   2396: getstatic 159	com/db/pwcc/dbmobile/multi_bank_aggregator/model/MbaErrorCode:NON_EXISTING_BANK	Lcom/db/pwcc/dbmobile/multi_bank_aggregator/model/MbaErrorCode;
    //   2399: aastore
    //   2400: dup
    //   2401: bipush 6
    //   2403: getstatic 165	com/db/pwcc/dbmobile/multi_bank_aggregator/model/MbaErrorCode:MBA_CREDENTIALS_ERROR	Lcom/db/pwcc/dbmobile/multi_bank_aggregator/model/MbaErrorCode;
    //   2406: aastore
    //   2407: dup
    //   2408: bipush 7
    //   2410: getstatic 171	com/db/pwcc/dbmobile/multi_bank_aggregator/model/MbaErrorCode:FUNCTION_NOT_AVAILABLE	Lcom/db/pwcc/dbmobile/multi_bank_aggregator/model/MbaErrorCode;
    //   2413: aastore
    //   2414: dup
    //   2415: bipush 8
    //   2417: getstatic 177	com/db/pwcc/dbmobile/multi_bank_aggregator/model/MbaErrorCode:UNEXPECTED_FAILURE	Lcom/db/pwcc/dbmobile/multi_bank_aggregator/model/MbaErrorCode;
    //   2420: aastore
    //   2421: dup
    //   2422: bipush 9
    //   2424: getstatic 183	com/db/pwcc/dbmobile/multi_bank_aggregator/model/MbaErrorCode:DEACTIVATE_MBA_ERROR	Lcom/db/pwcc/dbmobile/multi_bank_aggregator/model/MbaErrorCode;
    //   2427: aastore
    //   2428: dup
    //   2429: bipush 10
    //   2431: getstatic 189	com/db/pwcc/dbmobile/multi_bank_aggregator/model/MbaErrorCode:TAN_PROCESS_FAILURE	Lcom/db/pwcc/dbmobile/multi_bank_aggregator/model/MbaErrorCode;
    //   2434: aastore
    //   2435: dup
    //   2436: bipush 11
    //   2438: getstatic 195	com/db/pwcc/dbmobile/multi_bank_aggregator/model/MbaErrorCode:FUNCTION_OUT_OF_SCOPE	Lcom/db/pwcc/dbmobile/multi_bank_aggregator/model/MbaErrorCode;
    //   2441: aastore
    //   2442: dup
    //   2443: bipush 12
    //   2445: getstatic 201	com/db/pwcc/dbmobile/multi_bank_aggregator/model/MbaErrorCode:DEACTIVATE_MBA_ACCEPT_TERMS	Lcom/db/pwcc/dbmobile/multi_bank_aggregator/model/MbaErrorCode;
    //   2448: aastore
    //   2449: dup
    //   2450: bipush 13
    //   2452: getstatic 207	com/db/pwcc/dbmobile/multi_bank_aggregator/model/MbaErrorCode:FORBIDDEN	Lcom/db/pwcc/dbmobile/multi_bank_aggregator/model/MbaErrorCode;
    //   2455: aastore
    //   2456: dup
    //   2457: bipush 14
    //   2459: getstatic 213	com/db/pwcc/dbmobile/multi_bank_aggregator/model/MbaErrorCode:SYNCHRONIZATION_FAILURE	Lcom/db/pwcc/dbmobile/multi_bank_aggregator/model/MbaErrorCode;
    //   2462: aastore
    //   2463: dup
    //   2464: bipush 15
    //   2466: getstatic 219	com/db/pwcc/dbmobile/multi_bank_aggregator/model/MbaErrorCode:SYNCHRONIZATION_INCORRECT_CREDENTIALS	Lcom/db/pwcc/dbmobile/multi_bank_aggregator/model/MbaErrorCode;
    //   2469: aastore
    //   2470: dup
    //   2471: bipush 16
    //   2473: getstatic 225	com/db/pwcc/dbmobile/multi_bank_aggregator/model/MbaErrorCode:BANK_COMMUNICATION_FAILURE	Lcom/db/pwcc/dbmobile/multi_bank_aggregator/model/MbaErrorCode;
    //   2476: aastore
    //   2477: dup
    //   2478: bipush 17
    //   2480: getstatic 231	com/db/pwcc/dbmobile/multi_bank_aggregator/model/MbaErrorCode:BANK_NOT_AVAILABLE	Lcom/db/pwcc/dbmobile/multi_bank_aggregator/model/MbaErrorCode;
    //   2483: aastore
    //   2484: dup
    //   2485: bipush 18
    //   2487: getstatic 237	com/db/pwcc/dbmobile/multi_bank_aggregator/model/MbaErrorCode:PIN_CHANGE_REQUIRED	Lcom/db/pwcc/dbmobile/multi_bank_aggregator/model/MbaErrorCode;
    //   2490: aastore
    //   2491: dup
    //   2492: bipush 19
    //   2494: getstatic 243	com/db/pwcc/dbmobile/multi_bank_aggregator/model/MbaErrorCode:ONLINE_ACCOUNT_BLOCKED	Lcom/db/pwcc/dbmobile/multi_bank_aggregator/model/MbaErrorCode;
    //   2497: aastore
    //   2498: dup
    //   2499: bipush 20
    //   2501: getstatic 249	com/db/pwcc/dbmobile/multi_bank_aggregator/model/MbaErrorCode:HBCI_NOT_ACTIVE	Lcom/db/pwcc/dbmobile/multi_bank_aggregator/model/MbaErrorCode;
    //   2504: aastore
    //   2505: dup
    //   2506: bipush 21
    //   2508: getstatic 253	com/db/pwcc/dbmobile/multi_bank_aggregator/model/MbaErrorCode:ACCOUNT_DOES_NOT_EXIST	Lcom/db/pwcc/dbmobile/multi_bank_aggregator/model/MbaErrorCode;
    //   2511: aastore
    //   2512: dup
    //   2513: bipush 22
    //   2515: getstatic 259	com/db/pwcc/dbmobile/multi_bank_aggregator/model/MbaErrorCode:NO_RIGHTS_FOR_ACCOUNT	Lcom/db/pwcc/dbmobile/multi_bank_aggregator/model/MbaErrorCode;
    //   2518: aastore
    //   2519: dup
    //   2520: bipush 23
    //   2522: getstatic 265	com/db/pwcc/dbmobile/multi_bank_aggregator/model/MbaErrorCode:ACCOUNT_BLOCKED	Lcom/db/pwcc/dbmobile/multi_bank_aggregator/model/MbaErrorCode;
    //   2525: aastore
    //   2526: dup
    //   2527: bipush 24
    //   2529: getstatic 271	com/db/pwcc/dbmobile/multi_bank_aggregator/model/MbaErrorCode:UNKNOWN_ACCOUNT	Lcom/db/pwcc/dbmobile/multi_bank_aggregator/model/MbaErrorCode;
    //   2532: aastore
    //   2533: dup
    //   2534: bipush 25
    //   2536: getstatic 277	com/db/pwcc/dbmobile/multi_bank_aggregator/model/MbaErrorCode:DEFAULT_CODE	Lcom/db/pwcc/dbmobile/multi_bank_aggregator/model/MbaErrorCode;
    //   2539: aastore
    //   2540: putstatic 279	com/db/pwcc/dbmobile/multi_bank_aggregator/model/MbaErrorCode:$VALUES	[Lcom/db/pwcc/dbmobile/multi_bank_aggregator/model/MbaErrorCode;
    //   2543: return
    //   2544: astore_1
    //   2545: aload_1
    //   2546: invokevirtual 283	java/lang/reflect/InvocationTargetException:getCause	()Ljava/lang/Throwable;
    //   2549: athrow
    //   2550: astore_1
    //   2551: aload_1
    //   2552: invokevirtual 283	java/lang/reflect/InvocationTargetException:getCause	()Ljava/lang/Throwable;
    //   2555: athrow
    //   2556: astore_1
    //   2557: aload_1
    //   2558: invokevirtual 283	java/lang/reflect/InvocationTargetException:getCause	()Ljava/lang/Throwable;
    //   2561: athrow
    //   2562: astore_1
    //   2563: aload_1
    //   2564: invokevirtual 283	java/lang/reflect/InvocationTargetException:getCause	()Ljava/lang/Throwable;
    //   2567: athrow
    //   2568: astore_1
    //   2569: aload_1
    //   2570: invokevirtual 283	java/lang/reflect/InvocationTargetException:getCause	()Ljava/lang/Throwable;
    //   2573: athrow
    //   2574: astore_1
    //   2575: aload_1
    //   2576: invokevirtual 283	java/lang/reflect/InvocationTargetException:getCause	()Ljava/lang/Throwable;
    //   2579: athrow
    //   2580: astore_1
    //   2581: aload_1
    //   2582: invokevirtual 283	java/lang/reflect/InvocationTargetException:getCause	()Ljava/lang/Throwable;
    //   2585: athrow
    //   2586: astore_1
    //   2587: aload_1
    //   2588: invokevirtual 283	java/lang/reflect/InvocationTargetException:getCause	()Ljava/lang/Throwable;
    //   2591: athrow
    //   2592: astore_1
    //   2593: aload_1
    //   2594: invokevirtual 283	java/lang/reflect/InvocationTargetException:getCause	()Ljava/lang/Throwable;
    //   2597: athrow
    //   2598: astore_1
    //   2599: aload_1
    //   2600: invokevirtual 283	java/lang/reflect/InvocationTargetException:getCause	()Ljava/lang/Throwable;
    //   2603: athrow
    //   2604: astore_1
    //   2605: aload_1
    //   2606: invokevirtual 283	java/lang/reflect/InvocationTargetException:getCause	()Ljava/lang/Throwable;
    //   2609: athrow
    //   2610: astore_1
    //   2611: aload_1
    //   2612: invokevirtual 283	java/lang/reflect/InvocationTargetException:getCause	()Ljava/lang/Throwable;
    //   2615: athrow
    //   2616: astore_1
    //   2617: aload_1
    //   2618: invokevirtual 283	java/lang/reflect/InvocationTargetException:getCause	()Ljava/lang/Throwable;
    //   2621: athrow
    //   2622: astore_1
    //   2623: aload_1
    //   2624: invokevirtual 283	java/lang/reflect/InvocationTargetException:getCause	()Ljava/lang/Throwable;
    //   2627: athrow
    //   2628: astore_1
    //   2629: aload_1
    //   2630: invokevirtual 283	java/lang/reflect/InvocationTargetException:getCause	()Ljava/lang/Throwable;
    //   2633: athrow
    //   2634: astore_1
    //   2635: aload_1
    //   2636: invokevirtual 283	java/lang/reflect/InvocationTargetException:getCause	()Ljava/lang/Throwable;
    //   2639: athrow
    //   2640: astore_1
    //   2641: aload_1
    //   2642: invokevirtual 283	java/lang/reflect/InvocationTargetException:getCause	()Ljava/lang/Throwable;
    //   2645: athrow
    //   2646: astore_1
    //   2647: aload_1
    //   2648: invokevirtual 283	java/lang/reflect/InvocationTargetException:getCause	()Ljava/lang/Throwable;
    //   2651: athrow
    //   2652: astore_1
    //   2653: aload_1
    //   2654: invokevirtual 283	java/lang/reflect/InvocationTargetException:getCause	()Ljava/lang/Throwable;
    //   2657: athrow
    //   2658: astore_1
    //   2659: aload_1
    //   2660: invokevirtual 283	java/lang/reflect/InvocationTargetException:getCause	()Ljava/lang/Throwable;
    //   2663: athrow
    //   2664: astore_1
    //   2665: aload_1
    //   2666: invokevirtual 283	java/lang/reflect/InvocationTargetException:getCause	()Ljava/lang/Throwable;
    //   2669: athrow
    //   2670: astore_1
    //   2671: aload_1
    //   2672: invokevirtual 283	java/lang/reflect/InvocationTargetException:getCause	()Ljava/lang/Throwable;
    //   2675: athrow
    //   2676: astore_1
    //   2677: aload_1
    //   2678: invokevirtual 283	java/lang/reflect/InvocationTargetException:getCause	()Ljava/lang/Throwable;
    //   2681: athrow
    //   2682: astore_1
    //   2683: aload_1
    //   2684: invokevirtual 283	java/lang/reflect/InvocationTargetException:getCause	()Ljava/lang/Throwable;
    //   2687: athrow
    //   2688: astore_1
    //   2689: aload_1
    //   2690: invokevirtual 283	java/lang/reflect/InvocationTargetException:getCause	()Ljava/lang/Throwable;
    //   2693: athrow
    //   2694: astore_1
    //   2695: aload_1
    //   2696: invokevirtual 283	java/lang/reflect/InvocationTargetException:getCause	()Ljava/lang/Throwable;
    //   2699: athrow
    // Local variable table:
    //   start	length	slot	name	signature
    //   1849	202	0	i	int
    //   41	2306	1	localObject	Object
    //   2544	2	1	localInvocationTargetException1	java.lang.reflect.InvocationTargetException
    //   2550	2	1	localInvocationTargetException2	java.lang.reflect.InvocationTargetException
    //   2556	2	1	localInvocationTargetException3	java.lang.reflect.InvocationTargetException
    //   2562	2	1	localInvocationTargetException4	java.lang.reflect.InvocationTargetException
    //   2568	2	1	localInvocationTargetException5	java.lang.reflect.InvocationTargetException
    //   2574	2	1	localInvocationTargetException6	java.lang.reflect.InvocationTargetException
    //   2580	2	1	localInvocationTargetException7	java.lang.reflect.InvocationTargetException
    //   2586	2	1	localInvocationTargetException8	java.lang.reflect.InvocationTargetException
    //   2592	2	1	localInvocationTargetException9	java.lang.reflect.InvocationTargetException
    //   2598	2	1	localInvocationTargetException10	java.lang.reflect.InvocationTargetException
    //   2604	2	1	localInvocationTargetException11	java.lang.reflect.InvocationTargetException
    //   2610	2	1	localInvocationTargetException12	java.lang.reflect.InvocationTargetException
    //   2616	2	1	localInvocationTargetException13	java.lang.reflect.InvocationTargetException
    //   2622	2	1	localInvocationTargetException14	java.lang.reflect.InvocationTargetException
    //   2628	2	1	localInvocationTargetException15	java.lang.reflect.InvocationTargetException
    //   2634	2	1	localInvocationTargetException16	java.lang.reflect.InvocationTargetException
    //   2640	2	1	localInvocationTargetException17	java.lang.reflect.InvocationTargetException
    //   2646	2	1	localInvocationTargetException18	java.lang.reflect.InvocationTargetException
    //   2652	2	1	localInvocationTargetException19	java.lang.reflect.InvocationTargetException
    //   2658	2	1	localInvocationTargetException20	java.lang.reflect.InvocationTargetException
    //   2664	2	1	localInvocationTargetException21	java.lang.reflect.InvocationTargetException
    //   2670	2	1	localInvocationTargetException22	java.lang.reflect.InvocationTargetException
    //   2676	2	1	localInvocationTargetException23	java.lang.reflect.InvocationTargetException
    //   2682	2	1	localInvocationTargetException24	java.lang.reflect.InvocationTargetException
    //   2688	2	1	localInvocationTargetException25	java.lang.reflect.InvocationTargetException
    //   2694	2	1	localInvocationTargetException26	java.lang.reflect.InvocationTargetException
    // Exception table:
    //   from	to	target	type
    //   2215	2255	2544	java/lang/reflect/InvocationTargetException
    //   1441	1472	2550	java/lang/reflect/InvocationTargetException
    //   594	625	2556	java/lang/reflect/InvocationTargetException
    //   512	542	2562	java/lang/reflect/InvocationTargetException
    //   1018	1056	2568	java/lang/reflect/InvocationTargetException
    //   764	795	2574	java/lang/reflect/InvocationTargetException
    //   929	960	2580	java/lang/reflect/InvocationTargetException
    //   317	356	2586	java/lang/reflect/InvocationTargetException
    //   1357	1387	2592	java/lang/reflect/InvocationTargetException
    //   1526	1557	2598	java/lang/reflect/InvocationTargetException
    //   1704	1744	2604	java/lang/reflect/InvocationTargetException
    //   847	877	2610	java/lang/reflect/InvocationTargetException
    //   1108	1139	2616	java/lang/reflect/InvocationTargetException
    //   1916	1947	2622	java/lang/reflect/InvocationTargetException
    //   2003	2035	2628	java/lang/reflect/InvocationTargetException
    //   2124	2155	2634	java/lang/reflect/InvocationTargetException
    //   2311	2342	2640	java/lang/reflect/InvocationTargetException
    //   430	460	2646	java/lang/reflect/InvocationTargetException
    //   1613	1643	2652	java/lang/reflect/InvocationTargetException
    //   1191	1222	2658	java/lang/reflect/InvocationTargetException
    //   681	712	2664	java/lang/reflect/InvocationTargetException
    //   139	178	2670	java/lang/reflect/InvocationTargetException
    //   230	260	2676	java/lang/reflect/InvocationTargetException
    //   1799	1829	2682	java/lang/reflect/InvocationTargetException
    //   1274	1305	2688	java/lang/reflect/InvocationTargetException
    //   42	82	2694	java/lang/reflect/InvocationTargetException
  }
  
  private MbaErrorCode(boolean paramBoolean)
  {
    this.syncError = paramBoolean;
  }
  
  public static int b006600660066f00660066ff()
  {
    return 0;
  }
  
  public static int b0066ff006600660066ff()
  {
    return 2;
  }
  
  public static int bf00660066f00660066ff()
  {
    return 71;
  }
  
  public static int bfff006600660066ff()
  {
    return 1;
  }
  
  public boolean isSyncError()
  {
    boolean bool = this.syncError;
    if ((bf00660066f00660066ff() + bfff006600660066ff()) * bf00660066f00660066ff() % b0066ff006600660066ff() != b006600660066f00660066ff())
    {
      int i = bf00660066f00660066ff();
      switch (i * (bfff006600660066ff() + i) % b0066ff006600660066ff())
      {
      }
    }
    return bool;
  }
}
