package com.appdynamics.eumagent.runtime.events;

import com.appdynamics.eumagent.runtime.r;
import com.appdynamics.repacked.gson.stream.c;

public abstract class f
  extends d
{
  public static int b043A043Aк043Aк043A = 1;
  public static int bк043A043Aкк043A = 51;
  public static int bкк043A043Aк043A = 0;
  public static int bккк043Aк043A = 2;
  public long b;
  public e c;
  public Boolean d;
  public final r e;
  public final r f;
  private String g;
  
  public f(String paramString, r paramR)
  {
    this(paramString, paramR, null);
  }
  
  public f(String paramString, r paramR1, r paramR2)
  {
    super(System.currentTimeMillis());
    this.g = paramString;
    this.e = paramR1;
    this.f = paramR2;
  }
  
  public static int b043A043A043Aкк043A()
  {
    return 1;
  }
  
  public static int b043Aкк043Aк043A()
  {
    return 53;
  }
  
  public static int bк043Aк043Aк043A()
  {
    return 0;
  }
  
  public final String a()
  {
    throw new Runtime("d2j fail translate: java.lang.IndexOutOfBoundsException: fromIndex < 0: -1\n\tat java.util.BitSet.nextSetBit(BitSet.java:712)\n\tat com.googlecode.dex2jar.ir.ts.array.FillArrayTransformer.makeSureAllElementAreAssigned(FillArrayTransformer.java:505)\n\tat com.googlecode.dex2jar.ir.ts.array.FillArrayTransformer.transformReportChanged(FillArrayTransformer.java:123)\n\tat com.googlecode.dex2jar.ir.ts.StatedTransformer.transform(StatedTransformer.java:10)\n\tat com.googlecode.d2j.dex.Dex2jar$2.optimize(Dex2jar.java:149)\n\tat com.googlecode.d2j.dex.Dex2Asm.convertCode(Dex2Asm.java:414)\n\tat com.googlecode.d2j.dex.ExDex2Asm.convertCode(ExDex2Asm.java:42)\n\tat com.googlecode.d2j.dex.Dex2jar$2.convertCode(Dex2jar.java:128)\n\tat com.googlecode.d2j.dex.Dex2Asm.convertMethod(Dex2Asm.java:509)\n\tat com.googlecode.d2j.dex.Dex2Asm.convertClass(Dex2Asm.java:406)\n\tat com.googlecode.d2j.dex.Dex2Asm.convertDex(Dex2Asm.java:422)\n\tat com.googlecode.d2j.dex.Dex2jar.doTranslate(Dex2jar.java:172)\n\tat com.googlecode.d2j.dex.Dex2jar.to(Dex2jar.java:272)\n\tat com.googlecode.dex2jar.tools.Dex2jarCmd.doCommandLine(Dex2jarCmd.java:108)\n\tat com.googlecode.dex2jar.tools.BaseCmd.doMain(BaseCmd.java:288)\n\tat com.googlecode.dex2jar.tools.Dex2jarCmd.main(Dex2jarCmd.java:32)\n");
  }
  
  abstract void a(c paramC);
  
  /* Error */
  public final void a(java.io.Writer paramWriter)
  {
    // Byte code:
    //   0: getstatic 66	com/appdynamics/eumagent/runtime/events/f:bк043A043Aкк043A	I
    //   3: istore_2
    //   4: iload_2
    //   5: invokestatic 68	com/appdynamics/eumagent/runtime/events/f:b043A043A043Aкк043A	()I
    //   8: iload_2
    //   9: iadd
    //   10: imul
    //   11: getstatic 70	com/appdynamics/eumagent/runtime/events/f:bккк043Aк043A	I
    //   14: irem
    //   15: tableswitch	default:+17->32, 0:+27->42
    //   32: bipush 71
    //   34: putstatic 66	com/appdynamics/eumagent/runtime/events/f:bк043A043Aкк043A	I
    //   37: bipush 20
    //   39: putstatic 72	com/appdynamics/eumagent/runtime/events/f:b043A043Aк043Aк043A	I
    //   42: new 74	com/appdynamics/repacked/gson/stream/c
    //   45: dup
    //   46: aload_1
    //   47: invokespecial 76	com/appdynamics/repacked/gson/stream/c:<init>	(Ljava/io/Writer;)V
    //   50: astore_1
    //   51: getstatic 66	com/appdynamics/eumagent/runtime/events/f:bк043A043Aкк043A	I
    //   54: getstatic 72	com/appdynamics/eumagent/runtime/events/f:b043A043Aк043Aк043A	I
    //   57: iadd
    //   58: getstatic 66	com/appdynamics/eumagent/runtime/events/f:bк043A043Aкк043A	I
    //   61: imul
    //   62: getstatic 70	com/appdynamics/eumagent/runtime/events/f:bккк043Aк043A	I
    //   65: irem
    //   66: invokestatic 78	com/appdynamics/eumagent/runtime/events/f:bк043Aк043Aк043A	()I
    //   69: if_icmpeq +66 -> 135
    //   72: invokestatic 80	com/appdynamics/eumagent/runtime/events/f:b043Aкк043Aк043A	()I
    //   75: putstatic 66	com/appdynamics/eumagent/runtime/events/f:bк043A043Aкк043A	I
    //   78: bipush 6
    //   80: putstatic 72	com/appdynamics/eumagent/runtime/events/f:b043A043Aк043Aк043A	I
    //   83: iconst_0
    //   84: tableswitch	default:+24->108, 0:+51->135, 1:+-1->83
    //   108: iconst_1
    //   109: tableswitch	default:+23->132, 0:+-26->83, 1:+26->135
    //   132: goto -24 -> 108
    //   135: aload_0
    //   136: aload_1
    //   137: invokevirtual 82	com/appdynamics/eumagent/runtime/events/f:b	(Lcom/appdynamics/repacked/gson/stream/c;)V
    //   140: return
    //   141: astore_1
    //   142: aload_1
    //   143: athrow
    //   144: astore_1
    //   145: aload_1
    //   146: athrow
    // Local variable table:
    //   start	length	slot	name	signature
    //   0	147	0	this	f
    //   0	147	1	paramWriter	java.io.Writer
    //   3	8	2	i	int
    // Exception table:
    //   from	to	target	type
    //   135	140	141	java/lang/Exception
    //   42	51	144	java/lang/Exception
  }
  
  /* Error */
  public final void b(c paramC)
  {
    // Byte code:
    //   0: aload_1
    //   1: invokevirtual 85	com/appdynamics/repacked/gson/stream/c:c	()Lcom/appdynamics/repacked/gson/stream/c;
    //   4: pop
    //   5: aload_1
    //   6: ldc 87
    //   8: sipush 128
    //   11: bipush 46
    //   13: iconst_3
    //   14: invokestatic 93	kkkkkk/gguuuu:bк043Aккк043Aкк043A043A	(Ljava/lang/String;CCC)Ljava/lang/String;
    //   17: invokevirtual 96	com/appdynamics/repacked/gson/stream/c:a	(Ljava/lang/String;)Lcom/appdynamics/repacked/gson/stream/c;
    //   20: aload_0
    //   21: getfield 41	com/appdynamics/eumagent/runtime/events/f:g	Ljava/lang/String;
    //   24: invokevirtual 98	com/appdynamics/repacked/gson/stream/c:b	(Ljava/lang/String;)Lcom/appdynamics/repacked/gson/stream/c;
    //   27: pop
    //   28: aload_1
    //   29: ldc 100
    //   31: bipush 43
    //   33: iconst_5
    //   34: invokestatic 104	kkkkkk/gguuuu:bккккк043Aкк043A043A	(Ljava/lang/String;CC)Ljava/lang/String;
    //   37: invokevirtual 96	com/appdynamics/repacked/gson/stream/c:a	(Ljava/lang/String;)Lcom/appdynamics/repacked/gson/stream/c;
    //   40: aload_0
    //   41: getfield 106	com/appdynamics/eumagent/runtime/events/f:b	J
    //   44: invokevirtual 109	com/appdynamics/repacked/gson/stream/c:a	(J)Lcom/appdynamics/repacked/gson/stream/c;
    //   47: pop
    //   48: aload_0
    //   49: getfield 43	com/appdynamics/eumagent/runtime/events/f:e	Lcom/appdynamics/eumagent/runtime/r;
    //   52: astore 9
    //   54: aload 9
    //   56: ifnull +93 -> 149
    //   59: aload_1
    //   60: ldc 111
    //   62: sipush 161
    //   65: sipush 253
    //   68: iconst_1
    //   69: invokestatic 93	kkkkkk/gguuuu:bк043Aккк043Aкк043A043A	(Ljava/lang/String;CCC)Ljava/lang/String;
    //   72: invokevirtual 96	com/appdynamics/repacked/gson/stream/c:a	(Ljava/lang/String;)Lcom/appdynamics/repacked/gson/stream/c;
    //   75: astore 9
    //   77: aload_0
    //   78: getfield 43	com/appdynamics/eumagent/runtime/events/f:e	Lcom/appdynamics/eumagent/runtime/r;
    //   81: astore 10
    //   83: getstatic 66	com/appdynamics/eumagent/runtime/events/f:bк043A043Aкк043A	I
    //   86: getstatic 72	com/appdynamics/eumagent/runtime/events/f:b043A043Aк043Aк043A	I
    //   89: iadd
    //   90: getstatic 66	com/appdynamics/eumagent/runtime/events/f:bк043A043Aкк043A	I
    //   93: imul
    //   94: getstatic 70	com/appdynamics/eumagent/runtime/events/f:bккк043Aк043A	I
    //   97: irem
    //   98: getstatic 113	com/appdynamics/eumagent/runtime/events/f:bкк043A043Aк043A	I
    //   101: if_icmpeq +14 -> 115
    //   104: invokestatic 80	com/appdynamics/eumagent/runtime/events/f:b043Aкк043Aк043A	()I
    //   107: putstatic 66	com/appdynamics/eumagent/runtime/events/f:bк043A043Aкк043A	I
    //   110: bipush 76
    //   112: putstatic 113	com/appdynamics/eumagent/runtime/events/f:bкк043A043Aк043A	I
    //   115: aload 9
    //   117: aload 10
    //   119: getfield 116	com/appdynamics/eumagent/runtime/r:b	J
    //   122: invokevirtual 109	com/appdynamics/repacked/gson/stream/c:a	(J)Lcom/appdynamics/repacked/gson/stream/c;
    //   125: pop
    //   126: aload_1
    //   127: ldc 118
    //   129: bipush 68
    //   131: iconst_5
    //   132: invokestatic 104	kkkkkk/gguuuu:bккккк043Aкк043A043A	(Ljava/lang/String;CC)Ljava/lang/String;
    //   135: invokevirtual 96	com/appdynamics/repacked/gson/stream/c:a	(Ljava/lang/String;)Lcom/appdynamics/repacked/gson/stream/c;
    //   138: aload_0
    //   139: getfield 43	com/appdynamics/eumagent/runtime/events/f:e	Lcom/appdynamics/eumagent/runtime/r;
    //   142: getfield 120	com/appdynamics/eumagent/runtime/r:a	J
    //   145: invokevirtual 109	com/appdynamics/repacked/gson/stream/c:a	(J)Lcom/appdynamics/repacked/gson/stream/c;
    //   148: pop
    //   149: aload_0
    //   150: getfield 45	com/appdynamics/eumagent/runtime/events/f:f	Lcom/appdynamics/eumagent/runtime/r;
    //   153: ifnull +57 -> 210
    //   156: aload_1
    //   157: ldc 122
    //   159: bipush 26
    //   161: iconst_4
    //   162: invokestatic 104	kkkkkk/gguuuu:bккккк043Aкк043A043A	(Ljava/lang/String;CC)Ljava/lang/String;
    //   165: invokevirtual 96	com/appdynamics/repacked/gson/stream/c:a	(Ljava/lang/String;)Lcom/appdynamics/repacked/gson/stream/c;
    //   168: aload_0
    //   169: getfield 45	com/appdynamics/eumagent/runtime/events/f:f	Lcom/appdynamics/eumagent/runtime/r;
    //   172: getfield 116	com/appdynamics/eumagent/runtime/r:b	J
    //   175: invokevirtual 109	com/appdynamics/repacked/gson/stream/c:a	(J)Lcom/appdynamics/repacked/gson/stream/c;
    //   178: pop
    //   179: aload_1
    //   180: ldc 124
    //   182: bipush 59
    //   184: iconst_2
    //   185: invokestatic 104	kkkkkk/gguuuu:bккккк043Aкк043A043A	(Ljava/lang/String;CC)Ljava/lang/String;
    //   188: invokevirtual 96	com/appdynamics/repacked/gson/stream/c:a	(Ljava/lang/String;)Lcom/appdynamics/repacked/gson/stream/c;
    //   191: astore 9
    //   193: aload_0
    //   194: getfield 45	com/appdynamics/eumagent/runtime/events/f:f	Lcom/appdynamics/eumagent/runtime/r;
    //   197: getfield 120	com/appdynamics/eumagent/runtime/r:a	J
    //   200: lstore 7
    //   202: aload 9
    //   204: lload 7
    //   206: invokevirtual 109	com/appdynamics/repacked/gson/stream/c:a	(J)Lcom/appdynamics/repacked/gson/stream/c;
    //   209: pop
    //   210: aload_0
    //   211: getfield 126	com/appdynamics/eumagent/runtime/events/f:d	Ljava/lang/Boolean;
    //   214: ifnull +29 -> 243
    //   217: aload_1
    //   218: ldc -128
    //   220: bipush 43
    //   222: sipush 235
    //   225: iconst_2
    //   226: invokestatic 93	kkkkkk/gguuuu:bк043Aккк043Aкк043A043A	(Ljava/lang/String;CCC)Ljava/lang/String;
    //   229: invokevirtual 96	com/appdynamics/repacked/gson/stream/c:a	(Ljava/lang/String;)Lcom/appdynamics/repacked/gson/stream/c;
    //   232: aload_0
    //   233: getfield 126	com/appdynamics/eumagent/runtime/events/f:d	Ljava/lang/Boolean;
    //   236: invokevirtual 134	java/lang/Boolean:booleanValue	()Z
    //   239: invokevirtual 137	com/appdynamics/repacked/gson/stream/c:a	(Z)Lcom/appdynamics/repacked/gson/stream/c;
    //   242: pop
    //   243: aload_0
    //   244: aload_1
    //   245: invokevirtual 139	com/appdynamics/eumagent/runtime/events/f:a	(Lcom/appdynamics/repacked/gson/stream/c;)V
    //   248: aload_0
    //   249: getfield 141	com/appdynamics/eumagent/runtime/events/f:c	Lcom/appdynamics/eumagent/runtime/events/e;
    //   252: ifnull +538 -> 790
    //   255: aload_0
    //   256: getfield 141	com/appdynamics/eumagent/runtime/events/f:c	Lcom/appdynamics/eumagent/runtime/events/e;
    //   259: astore 9
    //   261: aload 9
    //   263: getfield 145	com/appdynamics/eumagent/runtime/events/e:b	I
    //   266: iconst_m1
    //   267: if_icmpeq +26 -> 293
    //   270: aload_1
    //   271: ldc -109
    //   273: sipush 226
    //   276: iconst_0
    //   277: invokestatic 104	kkkkkk/gguuuu:bккккк043Aкк043A043A	(Ljava/lang/String;CC)Ljava/lang/String;
    //   280: invokevirtual 96	com/appdynamics/repacked/gson/stream/c:a	(Ljava/lang/String;)Lcom/appdynamics/repacked/gson/stream/c;
    //   283: aload 9
    //   285: getfield 145	com/appdynamics/eumagent/runtime/events/e:b	I
    //   288: i2l
    //   289: invokevirtual 109	com/appdynamics/repacked/gson/stream/c:a	(J)Lcom/appdynamics/repacked/gson/stream/c;
    //   292: pop
    //   293: aload_1
    //   294: ldc -107
    //   296: sipush 245
    //   299: iconst_0
    //   300: invokestatic 104	kkkkkk/gguuuu:bккккк043Aкк043A043A	(Ljava/lang/String;CC)Ljava/lang/String;
    //   303: invokevirtual 96	com/appdynamics/repacked/gson/stream/c:a	(Ljava/lang/String;)Lcom/appdynamics/repacked/gson/stream/c;
    //   306: astore 10
    //   308: aload 9
    //   310: getfield 151	com/appdynamics/eumagent/runtime/events/e:a	Ljava/lang/String;
    //   313: astore 11
    //   315: aload 10
    //   317: aload 11
    //   319: invokevirtual 98	com/appdynamics/repacked/gson/stream/c:b	(Ljava/lang/String;)Lcom/appdynamics/repacked/gson/stream/c;
    //   322: astore 10
    //   324: aload 10
    //   326: ldc -103
    //   328: bipush 20
    //   330: sipush 149
    //   333: iconst_2
    //   334: invokestatic 93	kkkkkk/gguuuu:bк043Aккк043Aкк043A043A	(Ljava/lang/String;CCC)Ljava/lang/String;
    //   337: invokevirtual 96	com/appdynamics/repacked/gson/stream/c:a	(Ljava/lang/String;)Lcom/appdynamics/repacked/gson/stream/c;
    //   340: aload 9
    //   342: getfield 155	com/appdynamics/eumagent/runtime/events/e:d	Ljava/lang/String;
    //   345: invokevirtual 98	com/appdynamics/repacked/gson/stream/c:b	(Ljava/lang/String;)Lcom/appdynamics/repacked/gson/stream/c;
    //   348: astore 10
    //   350: aload 10
    //   352: ldc -99
    //   354: sipush 212
    //   357: bipush 6
    //   359: iconst_1
    //   360: invokestatic 93	kkkkkk/gguuuu:bк043Aккк043Aкк043A043A	(Ljava/lang/String;CCC)Ljava/lang/String;
    //   363: invokevirtual 96	com/appdynamics/repacked/gson/stream/c:a	(Ljava/lang/String;)Lcom/appdynamics/repacked/gson/stream/c;
    //   366: aload 9
    //   368: getfield 159	com/appdynamics/eumagent/runtime/events/e:e	Ljava/lang/String;
    //   371: invokevirtual 98	com/appdynamics/repacked/gson/stream/c:b	(Ljava/lang/String;)Lcom/appdynamics/repacked/gson/stream/c;
    //   374: astore 10
    //   376: aload 10
    //   378: ldc -95
    //   380: sipush 181
    //   383: iconst_3
    //   384: invokestatic 104	kkkkkk/gguuuu:bккккк043Aкк043A043A	(Ljava/lang/String;CC)Ljava/lang/String;
    //   387: invokevirtual 96	com/appdynamics/repacked/gson/stream/c:a	(Ljava/lang/String;)Lcom/appdynamics/repacked/gson/stream/c;
    //   390: aload 9
    //   392: getfield 163	com/appdynamics/eumagent/runtime/events/e:f	Ljava/lang/String;
    //   395: invokevirtual 98	com/appdynamics/repacked/gson/stream/c:b	(Ljava/lang/String;)Lcom/appdynamics/repacked/gson/stream/c;
    //   398: ldc -91
    //   400: sipush 187
    //   403: sipush 165
    //   406: iconst_1
    //   407: invokestatic 93	kkkkkk/gguuuu:bк043Aккк043Aкк043A043A	(Ljava/lang/String;CCC)Ljava/lang/String;
    //   410: invokevirtual 96	com/appdynamics/repacked/gson/stream/c:a	(Ljava/lang/String;)Lcom/appdynamics/repacked/gson/stream/c;
    //   413: astore 10
    //   415: aload 9
    //   417: getfield 166	com/appdynamics/eumagent/runtime/events/e:g	Ljava/lang/String;
    //   420: astore 11
    //   422: aload 10
    //   424: aload 11
    //   426: invokevirtual 98	com/appdynamics/repacked/gson/stream/c:b	(Ljava/lang/String;)Lcom/appdynamics/repacked/gson/stream/c;
    //   429: ldc -88
    //   431: bipush 97
    //   433: iconst_0
    //   434: invokestatic 104	kkkkkk/gguuuu:bккккк043Aкк043A043A	(Ljava/lang/String;CC)Ljava/lang/String;
    //   437: invokevirtual 96	com/appdynamics/repacked/gson/stream/c:a	(Ljava/lang/String;)Lcom/appdynamics/repacked/gson/stream/c;
    //   440: aload 9
    //   442: getfield 172	com/appdynamics/eumagent/runtime/events/e:h	Ljava/lang/Long;
    //   445: invokevirtual 175	com/appdynamics/repacked/gson/stream/c:a	(Ljava/lang/Number;)Lcom/appdynamics/repacked/gson/stream/c;
    //   448: ldc -79
    //   450: bipush 36
    //   452: sipush 137
    //   455: iconst_2
    //   456: invokestatic 93	kkkkkk/gguuuu:bк043Aккк043Aкк043A043A	(Ljava/lang/String;CCC)Ljava/lang/String;
    //   459: invokevirtual 96	com/appdynamics/repacked/gson/stream/c:a	(Ljava/lang/String;)Lcom/appdynamics/repacked/gson/stream/c;
    //   462: aload 9
    //   464: getfield 180	com/appdynamics/eumagent/runtime/events/e:i	Ljava/lang/String;
    //   467: invokevirtual 98	com/appdynamics/repacked/gson/stream/c:b	(Ljava/lang/String;)Lcom/appdynamics/repacked/gson/stream/c;
    //   470: ldc -74
    //   472: sipush 191
    //   475: iconst_5
    //   476: invokestatic 104	kkkkkk/gguuuu:bккккк043Aкк043A043A	(Ljava/lang/String;CC)Ljava/lang/String;
    //   479: invokevirtual 96	com/appdynamics/repacked/gson/stream/c:a	(Ljava/lang/String;)Lcom/appdynamics/repacked/gson/stream/c;
    //   482: aload 9
    //   484: getfield 185	com/appdynamics/eumagent/runtime/events/e:j	Ljava/lang/String;
    //   487: invokevirtual 98	com/appdynamics/repacked/gson/stream/c:b	(Ljava/lang/String;)Lcom/appdynamics/repacked/gson/stream/c;
    //   490: ldc -69
    //   492: sipush 197
    //   495: bipush 99
    //   497: iconst_3
    //   498: invokestatic 93	kkkkkk/gguuuu:bк043Aккк043Aкк043A043A	(Ljava/lang/String;CCC)Ljava/lang/String;
    //   501: invokevirtual 96	com/appdynamics/repacked/gson/stream/c:a	(Ljava/lang/String;)Lcom/appdynamics/repacked/gson/stream/c;
    //   504: aload 9
    //   506: getfield 191	com/appdynamics/eumagent/runtime/events/e:k	Ljava/lang/Integer;
    //   509: invokevirtual 175	com/appdynamics/repacked/gson/stream/c:a	(Ljava/lang/Number;)Lcom/appdynamics/repacked/gson/stream/c;
    //   512: astore 10
    //   514: getstatic 66	com/appdynamics/eumagent/runtime/events/f:bк043A043Aкк043A	I
    //   517: istore_2
    //   518: getstatic 72	com/appdynamics/eumagent/runtime/events/f:b043A043Aк043Aк043A	I
    //   521: istore_3
    //   522: getstatic 66	com/appdynamics/eumagent/runtime/events/f:bк043A043Aкк043A	I
    //   525: istore 4
    //   527: getstatic 70	com/appdynamics/eumagent/runtime/events/f:bккк043Aк043A	I
    //   530: istore 5
    //   532: invokestatic 78	com/appdynamics/eumagent/runtime/events/f:bк043Aк043Aк043A	()I
    //   535: istore 6
    //   537: iload_2
    //   538: iload_3
    //   539: iadd
    //   540: iload 4
    //   542: imul
    //   543: iload 5
    //   545: irem
    //   546: iload 6
    //   548: if_icmpeq +15 -> 563
    //   551: invokestatic 80	com/appdynamics/eumagent/runtime/events/f:b043Aкк043Aк043A	()I
    //   554: putstatic 66	com/appdynamics/eumagent/runtime/events/f:bк043A043Aкк043A	I
    //   557: invokestatic 80	com/appdynamics/eumagent/runtime/events/f:b043Aкк043Aк043A	()I
    //   560: putstatic 72	com/appdynamics/eumagent/runtime/events/f:b043A043Aк043Aк043A	I
    //   563: aload 10
    //   565: ldc -63
    //   567: bipush 73
    //   569: sipush 238
    //   572: iconst_0
    //   573: invokestatic 93	kkkkkk/gguuuu:bк043Aккк043Aкк043A043A	(Ljava/lang/String;CCC)Ljava/lang/String;
    //   576: invokevirtual 96	com/appdynamics/repacked/gson/stream/c:a	(Ljava/lang/String;)Lcom/appdynamics/repacked/gson/stream/c;
    //   579: astore 10
    //   581: aload 9
    //   583: getfield 196	com/appdynamics/eumagent/runtime/events/e:l	Ljava/lang/String;
    //   586: astore 11
    //   588: aload 10
    //   590: aload 11
    //   592: invokevirtual 98	com/appdynamics/repacked/gson/stream/c:b	(Ljava/lang/String;)Lcom/appdynamics/repacked/gson/stream/c;
    //   595: ldc -58
    //   597: bipush 57
    //   599: iconst_5
    //   600: invokestatic 104	kkkkkk/gguuuu:bккккк043Aкк043A043A	(Ljava/lang/String;CC)Ljava/lang/String;
    //   603: invokevirtual 96	com/appdynamics/repacked/gson/stream/c:a	(Ljava/lang/String;)Lcom/appdynamics/repacked/gson/stream/c;
    //   606: aload 9
    //   608: getfield 201	com/appdynamics/eumagent/runtime/events/e:m	Ljava/lang/String;
    //   611: invokevirtual 98	com/appdynamics/repacked/gson/stream/c:b	(Ljava/lang/String;)Lcom/appdynamics/repacked/gson/stream/c;
    //   614: astore 10
    //   616: ldc -53
    //   618: bipush 49
    //   620: iconst_1
    //   621: invokestatic 104	kkkkkk/gguuuu:bккккк043Aкк043A043A	(Ljava/lang/String;CC)Ljava/lang/String;
    //   624: astore 11
    //   626: aload 10
    //   628: aload 11
    //   630: invokevirtual 96	com/appdynamics/repacked/gson/stream/c:a	(Ljava/lang/String;)Lcom/appdynamics/repacked/gson/stream/c;
    //   633: astore 10
    //   635: aload 10
    //   637: aload 9
    //   639: getfield 206	com/appdynamics/eumagent/runtime/events/e:n	Ljava/lang/String;
    //   642: invokevirtual 98	com/appdynamics/repacked/gson/stream/c:b	(Ljava/lang/String;)Lcom/appdynamics/repacked/gson/stream/c;
    //   645: pop
    //   646: aload 9
    //   648: getfield 208	com/appdynamics/eumagent/runtime/events/e:c	Ljava/lang/String;
    //   651: ifnull +24 -> 675
    //   654: aload_1
    //   655: ldc -46
    //   657: bipush 109
    //   659: iconst_3
    //   660: invokestatic 104	kkkkkk/gguuuu:bккккк043Aкк043A043A	(Ljava/lang/String;CC)Ljava/lang/String;
    //   663: invokevirtual 96	com/appdynamics/repacked/gson/stream/c:a	(Ljava/lang/String;)Lcom/appdynamics/repacked/gson/stream/c;
    //   666: aload 9
    //   668: getfield 208	com/appdynamics/eumagent/runtime/events/e:c	Ljava/lang/String;
    //   671: invokevirtual 98	com/appdynamics/repacked/gson/stream/c:b	(Ljava/lang/String;)Lcom/appdynamics/repacked/gson/stream/c;
    //   674: pop
    //   675: aload 9
    //   677: getfield 214	com/appdynamics/eumagent/runtime/events/e:o	Ljava/util/Map;
    //   680: ifnull +110 -> 790
    //   683: aload 9
    //   685: getfield 214	com/appdynamics/eumagent/runtime/events/e:o	Ljava/util/Map;
    //   688: invokeinterface 219 1 0
    //   693: ifle +97 -> 790
    //   696: aload_1
    //   697: ldc -35
    //   699: bipush 18
    //   701: iconst_4
    //   702: invokestatic 104	kkkkkk/gguuuu:bккккк043Aкк043A043A	(Ljava/lang/String;CC)Ljava/lang/String;
    //   705: invokevirtual 96	com/appdynamics/repacked/gson/stream/c:a	(Ljava/lang/String;)Lcom/appdynamics/repacked/gson/stream/c;
    //   708: invokevirtual 85	com/appdynamics/repacked/gson/stream/c:c	()Lcom/appdynamics/repacked/gson/stream/c;
    //   711: pop
    //   712: aload 9
    //   714: getfield 214	com/appdynamics/eumagent/runtime/events/e:o	Ljava/util/Map;
    //   717: invokeinterface 225 1 0
    //   722: invokeinterface 231 1 0
    //   727: astore 9
    //   729: aload 9
    //   731: invokeinterface 236 1 0
    //   736: ifeq +49 -> 785
    //   739: aload 9
    //   741: invokeinterface 240 1 0
    //   746: checkcast 242	java/util/Map$Entry
    //   749: astore 10
    //   751: aload_1
    //   752: aload 10
    //   754: invokeinterface 245 1 0
    //   759: checkcast 247	java/lang/String
    //   762: invokevirtual 96	com/appdynamics/repacked/gson/stream/c:a	(Ljava/lang/String;)Lcom/appdynamics/repacked/gson/stream/c;
    //   765: aload 10
    //   767: invokeinterface 250 1 0
    //   772: checkcast 247	java/lang/String
    //   775: invokevirtual 98	com/appdynamics/repacked/gson/stream/c:b	(Ljava/lang/String;)Lcom/appdynamics/repacked/gson/stream/c;
    //   778: pop
    //   779: goto -50 -> 729
    //   782: astore_1
    //   783: aload_1
    //   784: athrow
    //   785: aload_1
    //   786: invokevirtual 252	com/appdynamics/repacked/gson/stream/c:d	()Lcom/appdynamics/repacked/gson/stream/c;
    //   789: pop
    //   790: aload_1
    //   791: invokevirtual 252	com/appdynamics/repacked/gson/stream/c:d	()Lcom/appdynamics/repacked/gson/stream/c;
    //   794: pop
    //   795: return
    //   796: astore_1
    //   797: aload_1
    //   798: athrow
    // Local variable table:
    //   start	length	slot	name	signature
    //   0	799	0	this	f
    //   0	799	1	paramC	c
    //   517	23	2	i	int
    //   521	19	3	j	int
    //   525	18	4	k	int
    //   530	16	5	m	int
    //   535	14	6	n	int
    //   200	5	7	l	long
    //   52	688	9	localObject1	Object
    //   81	685	10	localObject2	Object
    //   313	316	11	str	String
    // Exception table:
    //   from	to	target	type
    //   0	54	782	java/lang/Exception
    //   59	83	782	java/lang/Exception
    //   115	149	782	java/lang/Exception
    //   149	202	782	java/lang/Exception
    //   210	243	782	java/lang/Exception
    //   243	270	782	java/lang/Exception
    //   293	315	782	java/lang/Exception
    //   324	350	782	java/lang/Exception
    //   376	422	782	java/lang/Exception
    //   551	557	782	java/lang/Exception
    //   581	588	782	java/lang/Exception
    //   616	626	782	java/lang/Exception
    //   635	675	782	java/lang/Exception
    //   675	696	782	java/lang/Exception
    //   712	729	782	java/lang/Exception
    //   729	779	782	java/lang/Exception
    //   785	790	782	java/lang/Exception
    //   790	795	782	java/lang/Exception
    //   202	210	796	java/lang/Exception
    //   270	293	796	java/lang/Exception
    //   315	324	796	java/lang/Exception
    //   350	376	796	java/lang/Exception
    //   422	537	796	java/lang/Exception
    //   557	563	796	java/lang/Exception
    //   563	581	796	java/lang/Exception
    //   588	616	796	java/lang/Exception
    //   626	635	796	java/lang/Exception
    //   696	712	796	java/lang/Exception
  }
}
