package com.appdynamics.eumagent.runtime.events;

public class k
{
  public static int b043D043Dн043Dнн = 2;
  public static int b043Dнн043Dнн = 0;
  public static int bн043Dн043Dнн = 1;
  public static int bннн043Dнн = 90;
  public final long a;
  
  public k()
  {
    this(0L);
  }
  
  public k(long paramLong)
  {
    this.a = paramLong;
  }
  
  public static int bнн043D043Dнн()
  {
    return 38;
  }
  
  /* Error */
  public String toString()
  {
    // Byte code:
    //   0: new 33	java/lang/StringBuilder
    //   3: dup
    //   4: ldc 35
    //   6: sipush 184
    //   9: bipush 113
    //   11: iconst_0
    //   12: invokestatic 41	kkkkkk/gguuuu:bк043Aккк043Aкк043A043A	(Ljava/lang/String;CCC)Ljava/lang/String;
    //   15: invokespecial 44	java/lang/StringBuilder:<init>	(Ljava/lang/String;)V
    //   18: astore 6
    //   20: getstatic 46	com/appdynamics/eumagent/runtime/events/k:bннн043Dнн	I
    //   23: istore_1
    //   24: getstatic 48	com/appdynamics/eumagent/runtime/events/k:bн043Dн043Dнн	I
    //   27: istore_2
    //   28: getstatic 46	com/appdynamics/eumagent/runtime/events/k:bннн043Dнн	I
    //   31: istore_3
    //   32: getstatic 50	com/appdynamics/eumagent/runtime/events/k:b043D043Dн043Dнн	I
    //   35: istore 4
    //   37: getstatic 52	com/appdynamics/eumagent/runtime/events/k:b043Dнн043Dнн	I
    //   40: istore 5
    //   42: iload_1
    //   43: iload_2
    //   44: iadd
    //   45: iload_3
    //   46: imul
    //   47: iload 4
    //   49: irem
    //   50: iload 5
    //   52: if_icmpeq +47 -> 99
    //   55: getstatic 46	com/appdynamics/eumagent/runtime/events/k:bннн043Dнн	I
    //   58: getstatic 48	com/appdynamics/eumagent/runtime/events/k:bн043Dн043Dнн	I
    //   61: iadd
    //   62: getstatic 46	com/appdynamics/eumagent/runtime/events/k:bннн043Dнн	I
    //   65: imul
    //   66: getstatic 50	com/appdynamics/eumagent/runtime/events/k:b043D043Dн043Dнн	I
    //   69: irem
    //   70: getstatic 52	com/appdynamics/eumagent/runtime/events/k:b043Dнн043Dнн	I
    //   73: if_icmpeq +14 -> 87
    //   76: bipush 70
    //   78: putstatic 46	com/appdynamics/eumagent/runtime/events/k:bннн043Dнн	I
    //   81: invokestatic 54	com/appdynamics/eumagent/runtime/events/k:bнн043D043Dнн	()I
    //   84: putstatic 52	com/appdynamics/eumagent/runtime/events/k:b043Dнн043Dнн	I
    //   87: invokestatic 54	com/appdynamics/eumagent/runtime/events/k:bнн043D043Dнн	()I
    //   90: putstatic 46	com/appdynamics/eumagent/runtime/events/k:bннн043Dнн	I
    //   93: invokestatic 54	com/appdynamics/eumagent/runtime/events/k:bнн043D043Dнн	()I
    //   96: putstatic 52	com/appdynamics/eumagent/runtime/events/k:b043Dнн043Dнн	I
    //   99: aload 6
    //   101: aload_0
    //   102: getfield 25	com/appdynamics/eumagent/runtime/events/k:a	J
    //   105: invokevirtual 58	java/lang/StringBuilder:append	(J)Ljava/lang/StringBuilder;
    //   108: bipush 125
    //   110: invokevirtual 61	java/lang/StringBuilder:append	(C)Ljava/lang/StringBuilder;
    //   113: invokevirtual 63	java/lang/StringBuilder:toString	()Ljava/lang/String;
    //   116: astore 6
    //   118: aload 6
    //   120: areturn
    //   121: astore 6
    //   123: aload 6
    //   125: athrow
    //   126: astore 6
    //   128: aload 6
    //   130: athrow
    // Local variable table:
    //   start	length	slot	name	signature
    //   0	131	0	this	k
    //   23	22	1	i	int
    //   27	18	2	j	int
    //   31	16	3	k	int
    //   35	15	4	m	int
    //   40	13	5	n	int
    //   18	101	6	localObject	Object
    //   121	3	6	localException1	Exception
    //   126	3	6	localException2	Exception
    // Exception table:
    //   from	to	target	type
    //   20	42	121	java/lang/Exception
    //   99	118	121	java/lang/Exception
    //   0	20	126	java/lang/Exception
    //   87	99	126	java/lang/Exception
  }
}
