package com.insidesecure.hce.MasterCardTransactionCallback;

public enum ValidityUmd
{
  private static char[] ˊ;
  private static int ˋ;
  private static int ˏ;
  
  /* Error */
  static
  {
    // Byte code:
    //   0: goto +71 -> 71
    //   3: iload_0
    //   4: tableswitch	default:+24->28, 0:+27->31, 1:+31->35
    //   28: goto +7 -> 35
    //   31: return
    //   32: astore_1
    //   33: aload_1
    //   34: athrow
    //   35: aconst_null
    //   36: arraylength
    //   37: istore_0
    //   38: return
    //   39: getstatic 22	com/insidesecure/hce/MasterCardTransactionCallback/ValidityUmd:ˏ	I
    //   42: bipush 115
    //   44: iadd
    //   45: istore_0
    //   46: iload_0
    //   47: sipush 128
    //   50: irem
    //   51: putstatic 24	com/insidesecure/hce/MasterCardTransactionCallback/ValidityUmd:ˋ	I
    //   54: iload_0
    //   55: iconst_2
    //   56: irem
    //   57: ifne +6 -> 63
    //   60: goto +291 -> 351
    //   63: iconst_0
    //   64: istore_0
    //   65: goto -62 -> 3
    //   68: astore_1
    //   69: aload_1
    //   70: athrow
    //   71: iconst_0
    //   72: putstatic 22	com/insidesecure/hce/MasterCardTransactionCallback/ValidityUmd:ˏ	I
    //   75: iconst_1
    //   76: putstatic 24	com/insidesecure/hce/MasterCardTransactionCallback/ValidityUmd:ˋ	I
    //   79: invokestatic 27	com/insidesecure/hce/MasterCardTransactionCallback/ValidityUmd:ॱ	()V
    //   82: new 2	com/insidesecure/hce/MasterCardTransactionCallback/ValidityUmd
    //   85: dup
    //   86: iconst_4
    //   87: newarray int
    //   89: dup
    //   90: iconst_0
    //   91: iconst_0
    //   92: iastore
    //   93: dup
    //   94: iconst_1
    //   95: bipush 6
    //   97: iastore
    //   98: dup
    //   99: iconst_2
    //   100: iconst_0
    //   101: iastore
    //   102: dup
    //   103: iconst_3
    //   104: iconst_4
    //   105: iastore
    //   106: bipush 6
    //   108: newarray byte
    //   110: dup
    //   111: iconst_0
    //   112: ldc 28
    //   114: bastore
    //   115: dup
    //   116: iconst_1
    //   117: ldc 29
    //   119: bastore
    //   120: dup
    //   121: iconst_2
    //   122: ldc 28
    //   124: bastore
    //   125: dup
    //   126: iconst_3
    //   127: ldc 28
    //   129: bastore
    //   130: dup
    //   131: iconst_4
    //   132: ldc 29
    //   134: bastore
    //   135: dup
    //   136: iconst_5
    //   137: ldc 29
    //   139: bastore
    //   140: iconst_1
    //   141: invokestatic 32	com/insidesecure/hce/MasterCardTransactionCallback/ValidityUmd:ˊ	([I[BZ)Ljava/lang/String;
    //   144: invokevirtual 38	java/lang/String:intern	()Ljava/lang/String;
    //   147: iconst_0
    //   148: invokespecial 42	com/insidesecure/hce/MasterCardTransactionCallback/ValidityUmd:<init>	(Ljava/lang/String;I)V
    //   151: putstatic 44	com/insidesecure/hce/MasterCardTransactionCallback/ValidityUmd:ALWAYS	Lcom/insidesecure/hce/MasterCardTransactionCallback/ValidityUmd;
    //   154: new 2	com/insidesecure/hce/MasterCardTransactionCallback/ValidityUmd
    //   157: dup
    //   158: iconst_4
    //   159: newarray int
    //   161: dup
    //   162: iconst_0
    //   163: bipush 6
    //   165: iastore
    //   166: dup
    //   167: iconst_1
    //   168: bipush 11
    //   170: iastore
    //   171: dup
    //   172: iconst_2
    //   173: iconst_0
    //   174: iastore
    //   175: dup
    //   176: iconst_3
    //   177: iconst_0
    //   178: iastore
    //   179: bipush 11
    //   181: newarray byte
    //   183: dup
    //   184: iconst_0
    //   185: ldc 29
    //   187: bastore
    //   188: dup
    //   189: iconst_1
    //   190: ldc 28
    //   192: bastore
    //   193: dup
    //   194: iconst_2
    //   195: ldc 28
    //   197: bastore
    //   198: dup
    //   199: iconst_3
    //   200: ldc 28
    //   202: bastore
    //   203: dup
    //   204: iconst_4
    //   205: ldc 29
    //   207: bastore
    //   208: dup
    //   209: iconst_5
    //   210: ldc 28
    //   212: bastore
    //   213: dup
    //   214: bipush 6
    //   216: ldc 28
    //   218: bastore
    //   219: dup
    //   220: bipush 7
    //   222: ldc 28
    //   224: bastore
    //   225: dup
    //   226: bipush 8
    //   228: ldc 29
    //   230: bastore
    //   231: dup
    //   232: bipush 9
    //   234: ldc 28
    //   236: bastore
    //   237: dup
    //   238: bipush 10
    //   240: ldc 29
    //   242: bastore
    //   243: iconst_1
    //   244: invokestatic 32	com/insidesecure/hce/MasterCardTransactionCallback/ValidityUmd:ˊ	([I[BZ)Ljava/lang/String;
    //   247: invokevirtual 38	java/lang/String:intern	()Ljava/lang/String;
    //   250: iconst_1
    //   251: invokespecial 42	com/insidesecure/hce/MasterCardTransactionCallback/ValidityUmd:<init>	(Ljava/lang/String;I)V
    //   254: putstatic 46	com/insidesecure/hce/MasterCardTransactionCallback/ValidityUmd:CONDITIONAL	Lcom/insidesecure/hce/MasterCardTransactionCallback/ValidityUmd;
    //   257: new 2	com/insidesecure/hce/MasterCardTransactionCallback/ValidityUmd
    //   260: dup
    //   261: iconst_4
    //   262: newarray int
    //   264: dup
    //   265: iconst_0
    //   266: bipush 17
    //   268: iastore
    //   269: dup
    //   270: iconst_1
    //   271: iconst_5
    //   272: iastore
    //   273: dup
    //   274: iconst_2
    //   275: iconst_0
    //   276: iastore
    //   277: dup
    //   278: iconst_3
    //   279: iconst_0
    //   280: iastore
    //   281: iconst_5
    //   282: newarray byte
    //   284: dup
    //   285: iconst_0
    //   286: ldc 29
    //   288: bastore
    //   289: dup
    //   290: iconst_1
    //   291: ldc 28
    //   293: bastore
    //   294: dup
    //   295: iconst_2
    //   296: ldc 28
    //   298: bastore
    //   299: dup
    //   300: iconst_3
    //   301: ldc 28
    //   303: bastore
    //   304: dup
    //   305: iconst_4
    //   306: ldc 28
    //   308: bastore
    //   309: iconst_1
    //   310: invokestatic 32	com/insidesecure/hce/MasterCardTransactionCallback/ValidityUmd:ˊ	([I[BZ)Ljava/lang/String;
    //   313: invokevirtual 38	java/lang/String:intern	()Ljava/lang/String;
    //   316: iconst_2
    //   317: invokespecial 42	com/insidesecure/hce/MasterCardTransactionCallback/ValidityUmd:<init>	(Ljava/lang/String;I)V
    //   320: putstatic 48	com/insidesecure/hce/MasterCardTransactionCallback/ValidityUmd:NEVER	Lcom/insidesecure/hce/MasterCardTransactionCallback/ValidityUmd;
    //   323: iconst_3
    //   324: anewarray 2	com/insidesecure/hce/MasterCardTransactionCallback/ValidityUmd
    //   327: dup
    //   328: iconst_0
    //   329: getstatic 44	com/insidesecure/hce/MasterCardTransactionCallback/ValidityUmd:ALWAYS	Lcom/insidesecure/hce/MasterCardTransactionCallback/ValidityUmd;
    //   332: aastore
    //   333: dup
    //   334: iconst_1
    //   335: getstatic 46	com/insidesecure/hce/MasterCardTransactionCallback/ValidityUmd:CONDITIONAL	Lcom/insidesecure/hce/MasterCardTransactionCallback/ValidityUmd;
    //   338: aastore
    //   339: dup
    //   340: iconst_2
    //   341: getstatic 48	com/insidesecure/hce/MasterCardTransactionCallback/ValidityUmd:NEVER	Lcom/insidesecure/hce/MasterCardTransactionCallback/ValidityUmd;
    //   344: aastore
    //   345: putstatic 50	com/insidesecure/hce/MasterCardTransactionCallback/ValidityUmd:$VALUES	[Lcom/insidesecure/hce/MasterCardTransactionCallback/ValidityUmd;
    //   348: goto -309 -> 39
    //   351: iconst_1
    //   352: istore_0
    //   353: goto -350 -> 3
    // Local variable table:
    //   start	length	slot	name	signature
    //   3	350	0	i	int
    //   32	2	1	localException1	Exception
    //   68	2	1	localException2	Exception
    // Exception table:
    //   from	to	target	type
    //   71	75	32	java/lang/Exception
    //   75	79	68	java/lang/Exception
    //   79	82	68	java/lang/Exception
    //   82	348	68	java/lang/Exception
  }
  
  private ValidityUmd() {}
  
  /* Error */
  private static String ˊ(int[] paramArrayOfInt, byte[] paramArrayOfByte, boolean paramBoolean)
  {
    // Byte code:
    //   0: goto +427 -> 427
    //   3: goto +650 -> 653
    //   6: iload 8
    //   8: ifle +6 -> 14
    //   11: goto +496 -> 507
    //   14: goto +477 -> 491
    //   17: astore_0
    //   18: aload_0
    //   19: athrow
    //   20: goto +364 -> 384
    //   23: iconst_0
    //   24: istore_3
    //   25: goto +359 -> 384
    //   28: getstatic 24	com/insidesecure/hce/MasterCardTransactionCallback/ValidityUmd:ˋ	I
    //   31: bipush 7
    //   33: iadd
    //   34: istore 4
    //   36: iload 4
    //   38: sipush 128
    //   41: irem
    //   42: putstatic 22	com/insidesecure/hce/MasterCardTransactionCallback/ValidityUmd:ˏ	I
    //   45: iload 4
    //   47: iconst_2
    //   48: irem
    //   49: ifeq +6 -> 55
    //   52: goto +210 -> 262
    //   55: goto +68 -> 123
    //   58: bipush 46
    //   60: istore_3
    //   61: goto +335 -> 396
    //   64: aload 10
    //   66: iload 4
    //   68: caload
    //   69: istore_3
    //   70: iload 4
    //   72: iconst_1
    //   73: iadd
    //   74: istore 4
    //   76: goto +469 -> 545
    //   79: aload_1
    //   80: iload 4
    //   82: baload
    //   83: iconst_1
    //   84: if_icmpne +6 -> 90
    //   87: goto +211 -> 298
    //   90: goto +617 -> 707
    //   93: getstatic 22	com/insidesecure/hce/MasterCardTransactionCallback/ValidityUmd:ˏ	I
    //   96: bipush 83
    //   98: iadd
    //   99: istore 4
    //   101: iload 4
    //   103: sipush 128
    //   106: irem
    //   107: putstatic 24	com/insidesecure/hce/MasterCardTransactionCallback/ValidityUmd:ˋ	I
    //   110: iload 4
    //   112: iconst_2
    //   113: irem
    //   114: ifne +6 -> 120
    //   117: goto +25 -> 142
    //   120: goto +310 -> 430
    //   123: aload 9
    //   125: iload_3
    //   126: aload_1
    //   127: iload 6
    //   129: iload_3
    //   130: isub
    //   131: iconst_1
    //   132: isub
    //   133: caload
    //   134: castore
    //   135: iload_3
    //   136: iconst_1
    //   137: iadd
    //   138: istore_3
    //   139: goto +469 -> 608
    //   142: bipush 20
    //   144: istore 4
    //   146: goto +312 -> 458
    //   149: iload 5
    //   151: istore_3
    //   152: goto +393 -> 545
    //   155: iload 6
    //   157: newarray char
    //   159: astore 10
    //   161: iconst_0
    //   162: istore 5
    //   164: iconst_0
    //   165: istore 4
    //   167: goto +391 -> 558
    //   170: iload 6
    //   172: newarray char
    //   174: astore 9
    //   176: aload_1
    //   177: iconst_0
    //   178: aload 9
    //   180: iconst_0
    //   181: iload 6
    //   183: invokestatic 71	java/lang/System:arraycopy	(Ljava/lang/Object;ILjava/lang/Object;II)V
    //   186: aload 9
    //   188: iconst_0
    //   189: aload_1
    //   190: iload 6
    //   192: iload 8
    //   194: isub
    //   195: iload 8
    //   197: invokestatic 71	java/lang/System:arraycopy	(Ljava/lang/Object;ILjava/lang/Object;II)V
    //   200: aload 9
    //   202: iload 8
    //   204: aload_1
    //   205: iconst_0
    //   206: iload 6
    //   208: iload 8
    //   210: isub
    //   211: invokestatic 71	java/lang/System:arraycopy	(Ljava/lang/Object;ILjava/lang/Object;II)V
    //   214: goto +277 -> 491
    //   217: iload 5
    //   219: istore_3
    //   220: goto +325 -> 545
    //   223: iload 4
    //   225: lookupswitch	default:+27->252, 18:+422->647, 47:+-197->28
    //   252: goto -224 -> 28
    //   255: bipush 47
    //   257: istore 4
    //   259: goto -36 -> 223
    //   262: aload 9
    //   264: iload_3
    //   265: aload_1
    //   266: iload 6
    //   268: iload_3
    //   269: iushr
    //   270: iconst_0
    //   271: irem
    //   272: caload
    //   273: castore
    //   274: iload_3
    //   275: bipush 97
    //   277: iadd
    //   278: istore_3
    //   279: goto +329 -> 608
    //   282: bipush 18
    //   284: istore 4
    //   286: goto -63 -> 223
    //   289: astore_0
    //   290: aload_0
    //   291: athrow
    //   292: aload 10
    //   294: astore_1
    //   295: goto -289 -> 6
    //   298: aload 10
    //   300: iload 4
    //   302: aload 9
    //   304: iload 4
    //   306: caload
    //   307: iconst_1
    //   308: ishl
    //   309: iconst_1
    //   310: iadd
    //   311: iload_3
    //   312: isub
    //   313: i2c
    //   314: castore
    //   315: goto -251 -> 64
    //   318: aload 9
    //   320: iload_3
    //   321: aload 9
    //   323: iload_3
    //   324: caload
    //   325: aload_0
    //   326: iconst_2
    //   327: iaload
    //   328: isub
    //   329: i2c
    //   330: castore
    //   331: iload_3
    //   332: iconst_1
    //   333: iadd
    //   334: istore_3
    //   335: goto -315 -> 20
    //   338: aload_1
    //   339: astore 9
    //   341: iload_3
    //   342: lookupswitch	default:+26->368, 15:+192->534, 16:+243->585
    //   368: aload_1
    //   369: astore 9
    //   371: goto +163 -> 534
    //   374: new 34	java/lang/String
    //   377: dup
    //   378: aload 9
    //   380: invokespecial 74	java/lang/String:<init>	([C)V
    //   383: areturn
    //   384: iload_3
    //   385: iload 6
    //   387: if_icmpge +6 -> 393
    //   390: goto -297 -> 93
    //   393: goto -19 -> 374
    //   396: iload_3
    //   397: lookupswitch	default:+27->424, 12:+-180->217, 46:+-248->149
    //   424: goto -207 -> 217
    //   427: goto +193 -> 620
    //   430: bipush 76
    //   432: istore 4
    //   434: goto +24 -> 458
    //   437: aload 9
    //   439: iload_3
    //   440: aload 9
    //   442: iload_3
    //   443: caload
    //   444: aload_0
    //   445: iconst_3
    //   446: iaload
    //   447: iushr
    //   448: i2c
    //   449: castore
    //   450: iload_3
    //   451: bipush 27
    //   453: iadd
    //   454: istore_3
    //   455: goto -435 -> 20
    //   458: iload 4
    //   460: lookupswitch	default:+28->488, 20:+-23->437, 76:+-142->318
    //   488: goto -170 -> 318
    //   491: iload_2
    //   492: ifeq +6 -> 498
    //   495: goto +101 -> 596
    //   498: goto +104 -> 602
    //   501: bipush 12
    //   503: istore_3
    //   504: goto -108 -> 396
    //   507: getstatic 24	com/insidesecure/hce/MasterCardTransactionCallback/ValidityUmd:ˋ	I
    //   510: bipush 65
    //   512: iadd
    //   513: istore_3
    //   514: iload_3
    //   515: sipush 128
    //   518: irem
    //   519: putstatic 22	com/insidesecure/hce/MasterCardTransactionCallback/ValidityUmd:ˏ	I
    //   522: iload_3
    //   523: iconst_2
    //   524: irem
    //   525: ifeq +6 -> 531
    //   528: goto +122 -> 650
    //   531: goto -361 -> 170
    //   534: iload 7
    //   536: ifle +6 -> 542
    //   539: goto -516 -> 23
    //   542: goto -168 -> 374
    //   545: iload 4
    //   547: iload 6
    //   549: if_icmpge +6 -> 555
    //   552: goto -473 -> 79
    //   555: goto -263 -> 292
    //   558: getstatic 22	com/insidesecure/hce/MasterCardTransactionCallback/ValidityUmd:ˏ	I
    //   561: bipush 103
    //   563: iadd
    //   564: istore_3
    //   565: iload_3
    //   566: sipush 128
    //   569: irem
    //   570: putstatic 24	com/insidesecure/hce/MasterCardTransactionCallback/ValidityUmd:ˋ	I
    //   573: iload_3
    //   574: iconst_2
    //   575: irem
    //   576: ifne +6 -> 582
    //   579: goto -521 -> 58
    //   582: goto -81 -> 501
    //   585: iload 6
    //   587: newarray char
    //   589: astore 9
    //   591: iconst_0
    //   592: istore_3
    //   593: goto +15 -> 608
    //   596: bipush 16
    //   598: istore_3
    //   599: goto -261 -> 338
    //   602: bipush 15
    //   604: istore_3
    //   605: goto -267 -> 338
    //   608: iload_3
    //   609: iload 6
    //   611: if_icmpge +6 -> 617
    //   614: goto -359 -> 255
    //   617: goto -335 -> 282
    //   620: getstatic 22	com/insidesecure/hce/MasterCardTransactionCallback/ValidityUmd:ˏ	I
    //   623: bipush 81
    //   625: iadd
    //   626: istore_3
    //   627: iload_3
    //   628: sipush 128
    //   631: irem
    //   632: putstatic 24	com/insidesecure/hce/MasterCardTransactionCallback/ValidityUmd:ˋ	I
    //   635: iload_3
    //   636: iconst_2
    //   637: irem
    //   638: ifne +6 -> 644
    //   641: goto -638 -> 3
    //   644: goto +9 -> 653
    //   647: goto -113 -> 534
    //   650: goto -480 -> 170
    //   653: aload_0
    //   654: iconst_0
    //   655: iaload
    //   656: istore_3
    //   657: aload_0
    //   658: iconst_1
    //   659: iaload
    //   660: istore 6
    //   662: aload_0
    //   663: iconst_2
    //   664: iaload
    //   665: istore 7
    //   667: aload_0
    //   668: iconst_3
    //   669: iaload
    //   670: istore 8
    //   672: getstatic 76	com/insidesecure/hce/MasterCardTransactionCallback/ValidityUmd:ˊ	[C
    //   675: astore 10
    //   677: iload 6
    //   679: newarray char
    //   681: astore 9
    //   683: aload 10
    //   685: iload_3
    //   686: aload 9
    //   688: iconst_0
    //   689: iload 6
    //   691: invokestatic 71	java/lang/System:arraycopy	(Ljava/lang/Object;ILjava/lang/Object;II)V
    //   694: aload_1
    //   695: ifnull +6 -> 701
    //   698: goto -543 -> 155
    //   701: aload 9
    //   703: astore_1
    //   704: goto -698 -> 6
    //   707: aload 10
    //   709: iload 4
    //   711: aload 9
    //   713: iload 4
    //   715: caload
    //   716: iconst_1
    //   717: ishl
    //   718: iload_3
    //   719: isub
    //   720: i2c
    //   721: castore
    //   722: goto -658 -> 64
    // Local variable table:
    //   start	length	slot	name	signature
    //   0	725	0	paramArrayOfInt	int[]
    //   0	725	1	paramArrayOfByte	byte[]
    //   0	725	2	paramBoolean	boolean
    //   24	696	3	i	int
    //   34	680	4	j	int
    //   149	69	5	k	int
    //   127	563	6	m	int
    //   534	132	7	n	int
    //   6	665	8	i1	int
    //   123	589	9	localObject	Object
    //   64	644	10	arrayOfChar	char[]
    // Exception table:
    //   from	to	target	type
    //   93	101	17	java/lang/Exception
    //   101	110	17	java/lang/Exception
    //   101	110	289	java/lang/Exception
  }
  
  static void ॱ()
  {
    ˊ = new char[] { 32, 76, 81, 70, 74, 86, 38, 70, 71, 78, 76, 78, 78, 70, 73, 78, 73, 41, 75, 77, 77, 73 };
  }
}
