import java.util.Map;

final class dbe
  implements gbh<Map<det<?>, String>>
{
  private dbe(dbc paramDbc) {}
  
  /* Error */
  public final void onComplete(gbl<Map<det<?>, String>> paramGbl)
  {
    // Byte code:
    //   0: aload_0
    //   1: getfield 13	dbe:a	Ldbc;
    //   4: invokestatic 27	dbc:a	(Ldbc;)Ljava/util/concurrent/locks/Lock;
    //   7: invokeinterface 32 1 0
    //   12: aload_0
    //   13: getfield 13	dbe:a	Ldbc;
    //   16: invokestatic 36	dbc:b	(Ldbc;)Z
    //   19: istore_2
    //   20: iload_2
    //   21: ifne +16 -> 37
    //   24: aload_0
    //   25: getfield 13	dbe:a	Ldbc;
    //   28: invokestatic 27	dbc:a	(Ldbc;)Ljava/util/concurrent/locks/Lock;
    //   31: invokeinterface 39 1 0
    //   36: return
    //   37: aload_1
    //   38: invokevirtual 44	gbl:a	()Z
    //   41: ifeq +90 -> 131
    //   44: aload_0
    //   45: getfield 13	dbe:a	Ldbc;
    //   48: new 46	android/support/v4/util/ArrayMap
    //   51: dup
    //   52: aload_0
    //   53: getfield 13	dbe:a	Ldbc;
    //   56: invokestatic 50	dbc:c	(Ldbc;)Ljava/util/Map;
    //   59: invokeinterface 56 1 0
    //   64: invokespecial 59	android/support/v4/util/ArrayMap:<init>	(I)V
    //   67: invokestatic 62	dbc:a	(Ldbc;Ljava/util/Map;)Ljava/util/Map;
    //   70: pop
    //   71: aload_0
    //   72: getfield 13	dbe:a	Ldbc;
    //   75: invokestatic 50	dbc:c	(Ldbc;)Ljava/util/Map;
    //   78: invokeinterface 66 1 0
    //   83: invokeinterface 72 1 0
    //   88: astore_1
    //   89: aload_1
    //   90: invokeinterface 77 1 0
    //   95: ifeq +275 -> 370
    //   98: aload_1
    //   99: invokeinterface 81 1 0
    //   104: checkcast 83	dfm
    //   107: astore_3
    //   108: aload_0
    //   109: getfield 13	dbe:a	Ldbc;
    //   112: invokestatic 86	dbc:d	(Ldbc;)Ljava/util/Map;
    //   115: aload_3
    //   116: invokevirtual 91	dah:d	()Ldet;
    //   119: getstatic 96	com/google/android/gms/common/ConnectionResult:a	Lcom/google/android/gms/common/ConnectionResult;
    //   122: invokeinterface 100 3 0
    //   127: pop
    //   128: goto -39 -> 89
    //   131: aload_1
    //   132: invokevirtual 103	gbl:c	()Ljava/lang/Exception;
    //   135: instanceof 105
    //   138: ifeq +191 -> 329
    //   141: aload_1
    //   142: invokevirtual 103	gbl:c	()Ljava/lang/Exception;
    //   145: checkcast 105	dae
    //   148: astore 4
    //   150: aload_0
    //   151: getfield 13	dbe:a	Ldbc;
    //   154: invokestatic 108	dbc:e	(Ldbc;)Z
    //   157: ifeq +137 -> 294
    //   160: aload_0
    //   161: getfield 13	dbe:a	Ldbc;
    //   164: new 46	android/support/v4/util/ArrayMap
    //   167: dup
    //   168: aload_0
    //   169: getfield 13	dbe:a	Ldbc;
    //   172: invokestatic 50	dbc:c	(Ldbc;)Ljava/util/Map;
    //   175: invokeinterface 56 1 0
    //   180: invokespecial 59	android/support/v4/util/ArrayMap:<init>	(I)V
    //   183: invokestatic 62	dbc:a	(Ldbc;Ljava/util/Map;)Ljava/util/Map;
    //   186: pop
    //   187: aload_0
    //   188: getfield 13	dbe:a	Ldbc;
    //   191: invokestatic 50	dbc:c	(Ldbc;)Ljava/util/Map;
    //   194: invokeinterface 66 1 0
    //   199: invokeinterface 72 1 0
    //   204: astore 5
    //   206: aload 5
    //   208: invokeinterface 77 1 0
    //   213: ifeq +94 -> 307
    //   216: aload 5
    //   218: invokeinterface 81 1 0
    //   223: checkcast 83	dfm
    //   226: astore_1
    //   227: aload_1
    //   228: invokevirtual 91	dah:d	()Ldet;
    //   231: astore 6
    //   233: aload 4
    //   235: aload_1
    //   236: invokevirtual 111	dae:a	(Ldah;)Lcom/google/android/gms/common/ConnectionResult;
    //   239: astore_3
    //   240: aload_0
    //   241: getfield 13	dbe:a	Ldbc;
    //   244: aload_1
    //   245: aload_3
    //   246: invokestatic 114	dbc:a	(Ldbc;Ldfm;Lcom/google/android/gms/common/ConnectionResult;)Z
    //   249: ifeq +34 -> 283
    //   252: aload_0
    //   253: getfield 13	dbe:a	Ldbc;
    //   256: invokestatic 86	dbc:d	(Ldbc;)Ljava/util/Map;
    //   259: astore_1
    //   260: new 93	com/google/android/gms/common/ConnectionResult
    //   263: dup
    //   264: bipush 16
    //   266: invokespecial 115	com/google/android/gms/common/ConnectionResult:<init>	(I)V
    //   269: astore_3
    //   270: aload_1
    //   271: aload 6
    //   273: aload_3
    //   274: invokeinterface 100 3 0
    //   279: pop
    //   280: goto -74 -> 206
    //   283: aload_0
    //   284: getfield 13	dbe:a	Ldbc;
    //   287: invokestatic 86	dbc:d	(Ldbc;)Ljava/util/Map;
    //   290: astore_1
    //   291: goto -21 -> 270
    //   294: aload_0
    //   295: getfield 13	dbe:a	Ldbc;
    //   298: aload 4
    //   300: invokevirtual 118	dae:a	()Landroid/support/v4/util/ArrayMap;
    //   303: invokestatic 62	dbc:a	(Ldbc;Ljava/util/Map;)Ljava/util/Map;
    //   306: pop
    //   307: aload_0
    //   308: getfield 13	dbe:a	Ldbc;
    //   311: astore_3
    //   312: aload_0
    //   313: getfield 13	dbe:a	Ldbc;
    //   316: invokestatic 122	dbc:f	(Ldbc;)Lcom/google/android/gms/common/ConnectionResult;
    //   319: astore_1
    //   320: aload_3
    //   321: aload_1
    //   322: invokestatic 125	dbc:a	(Ldbc;Lcom/google/android/gms/common/ConnectionResult;)Lcom/google/android/gms/common/ConnectionResult;
    //   325: pop
    //   326: goto +44 -> 370
    //   329: ldc 127
    //   331: ldc -127
    //   333: aload_1
    //   334: invokevirtual 103	gbl:c	()Ljava/lang/Exception;
    //   337: invokestatic 134	android/util/Log:e	(Ljava/lang/String;Ljava/lang/String;Ljava/lang/Throwable;)I
    //   340: pop
    //   341: aload_0
    //   342: getfield 13	dbe:a	Ldbc;
    //   345: invokestatic 140	java/util/Collections:emptyMap	()Ljava/util/Map;
    //   348: invokestatic 62	dbc:a	(Ldbc;Ljava/util/Map;)Ljava/util/Map;
    //   351: pop
    //   352: aload_0
    //   353: getfield 13	dbe:a	Ldbc;
    //   356: astore_3
    //   357: new 93	com/google/android/gms/common/ConnectionResult
    //   360: dup
    //   361: bipush 8
    //   363: invokespecial 115	com/google/android/gms/common/ConnectionResult:<init>	(I)V
    //   366: astore_1
    //   367: goto -47 -> 320
    //   370: aload_0
    //   371: getfield 13	dbe:a	Ldbc;
    //   374: invokestatic 143	dbc:g	(Ldbc;)Ljava/util/Map;
    //   377: ifnull +37 -> 414
    //   380: aload_0
    //   381: getfield 13	dbe:a	Ldbc;
    //   384: invokestatic 86	dbc:d	(Ldbc;)Ljava/util/Map;
    //   387: aload_0
    //   388: getfield 13	dbe:a	Ldbc;
    //   391: invokestatic 143	dbc:g	(Ldbc;)Ljava/util/Map;
    //   394: invokeinterface 147 2 0
    //   399: aload_0
    //   400: getfield 13	dbe:a	Ldbc;
    //   403: aload_0
    //   404: getfield 13	dbe:a	Ldbc;
    //   407: invokestatic 122	dbc:f	(Ldbc;)Lcom/google/android/gms/common/ConnectionResult;
    //   410: invokestatic 125	dbc:a	(Ldbc;Lcom/google/android/gms/common/ConnectionResult;)Lcom/google/android/gms/common/ConnectionResult;
    //   413: pop
    //   414: aload_0
    //   415: getfield 13	dbe:a	Ldbc;
    //   418: invokestatic 150	dbc:h	(Ldbc;)Lcom/google/android/gms/common/ConnectionResult;
    //   421: ifnonnull +20 -> 441
    //   424: aload_0
    //   425: getfield 13	dbe:a	Ldbc;
    //   428: invokestatic 153	dbc:i	(Ldbc;)V
    //   431: aload_0
    //   432: getfield 13	dbe:a	Ldbc;
    //   435: invokestatic 156	dbc:j	(Ldbc;)V
    //   438: goto +29 -> 467
    //   441: aload_0
    //   442: getfield 13	dbe:a	Ldbc;
    //   445: iconst_0
    //   446: invokestatic 159	dbc:a	(Ldbc;Z)Z
    //   449: pop
    //   450: aload_0
    //   451: getfield 13	dbe:a	Ldbc;
    //   454: invokestatic 163	dbc:k	(Ldbc;)Ldcb;
    //   457: aload_0
    //   458: getfield 13	dbe:a	Ldbc;
    //   461: invokestatic 150	dbc:h	(Ldbc;)Lcom/google/android/gms/common/ConnectionResult;
    //   464: invokevirtual 168	dcb:a	(Lcom/google/android/gms/common/ConnectionResult;)V
    //   467: aload_0
    //   468: getfield 13	dbe:a	Ldbc;
    //   471: invokestatic 172	dbc:l	(Ldbc;)Ljava/util/concurrent/locks/Condition;
    //   474: invokeinterface 177 1 0
    //   479: goto -455 -> 24
    //   482: astore_1
    //   483: aload_0
    //   484: getfield 13	dbe:a	Ldbc;
    //   487: invokestatic 27	dbc:a	(Ldbc;)Ljava/util/concurrent/locks/Lock;
    //   490: invokeinterface 39 1 0
    //   495: aload_1
    //   496: athrow
    // Local variable table:
    //   start	length	slot	name	signature
    //   0	497	0	this	dbe
    //   0	497	1	paramGbl	gbl<Map<det<?>, String>>
    //   19	2	2	bool	boolean
    //   107	250	3	localObject	Object
    //   148	151	4	localDae	dae
    //   204	13	5	localIterator	java.util.Iterator
    //   231	41	6	localDet	det
    // Exception table:
    //   from	to	target	type
    //   12	20	482	finally
    //   37	89	482	finally
    //   89	128	482	finally
    //   131	206	482	finally
    //   206	270	482	finally
    //   270	280	482	finally
    //   283	291	482	finally
    //   294	307	482	finally
    //   307	320	482	finally
    //   320	326	482	finally
    //   329	367	482	finally
    //   370	414	482	finally
    //   414	438	482	finally
    //   441	467	482	finally
    //   467	479	482	finally
  }
}
