final class dej
  implements Runnable
{
  dej(dei paramDei, dau paramDau) {}
  
  /* Error */
  public final void run()
  {
    // Byte code:
    //   0: getstatic 28	com/google/android/gms/common/api/internal/BasePendingResult:a	Ljava/lang/ThreadLocal;
    //   3: iconst_1
    //   4: invokestatic 34	java/lang/Boolean:valueOf	(Z)Ljava/lang/Boolean;
    //   7: invokevirtual 40	java/lang/ThreadLocal:set	(Ljava/lang/Object;)V
    //   10: aload_0
    //   11: getfield 14	dej:b	Ldei;
    //   14: invokestatic 45	dei:a	(Ldei;)Ldax;
    //   17: aload_0
    //   18: getfield 16	dej:a	Ldau;
    //   21: invokevirtual 50	dax:a	(Ldau;)Ldan;
    //   24: astore_1
    //   25: aload_0
    //   26: getfield 14	dej:b	Ldei;
    //   29: invokestatic 53	dei:b	(Ldei;)Ldek;
    //   32: aload_0
    //   33: getfield 14	dej:b	Ldei;
    //   36: invokestatic 53	dei:b	(Ldei;)Ldek;
    //   39: iconst_0
    //   40: aload_1
    //   41: invokevirtual 59	dek:obtainMessage	(ILjava/lang/Object;)Landroid/os/Message;
    //   44: invokevirtual 63	dek:sendMessage	(Landroid/os/Message;)Z
    //   47: pop
    //   48: getstatic 28	com/google/android/gms/common/api/internal/BasePendingResult:a	Ljava/lang/ThreadLocal;
    //   51: iconst_0
    //   52: invokestatic 34	java/lang/Boolean:valueOf	(Z)Ljava/lang/Boolean;
    //   55: invokevirtual 40	java/lang/ThreadLocal:set	(Ljava/lang/Object;)V
    //   58: aload_0
    //   59: getfield 14	dej:b	Ldei;
    //   62: aload_0
    //   63: getfield 16	dej:a	Ldau;
    //   66: invokestatic 65	dei:a	(Ldei;Ldau;)V
    //   69: aload_0
    //   70: getfield 14	dej:b	Ldei;
    //   73: invokestatic 69	dei:c	(Ldei;)Ljava/lang/ref/WeakReference;
    //   76: invokevirtual 75	java/lang/ref/WeakReference:get	()Ljava/lang/Object;
    //   79: checkcast 77	daj
    //   82: astore_1
    //   83: aload_1
    //   84: ifnull +11 -> 95
    //   87: aload_1
    //   88: aload_0
    //   89: getfield 14	dej:b	Ldei;
    //   92: invokevirtual 80	daj:b	(Ldei;)V
    //   95: return
    //   96: astore_1
    //   97: goto +75 -> 172
    //   100: astore_1
    //   101: aload_0
    //   102: getfield 14	dej:b	Ldei;
    //   105: invokestatic 53	dei:b	(Ldei;)Ldek;
    //   108: aload_0
    //   109: getfield 14	dej:b	Ldei;
    //   112: invokestatic 53	dei:b	(Ldei;)Ldek;
    //   115: iconst_1
    //   116: aload_1
    //   117: invokevirtual 59	dek:obtainMessage	(ILjava/lang/Object;)Landroid/os/Message;
    //   120: invokevirtual 63	dek:sendMessage	(Landroid/os/Message;)Z
    //   123: pop
    //   124: getstatic 28	com/google/android/gms/common/api/internal/BasePendingResult:a	Ljava/lang/ThreadLocal;
    //   127: iconst_0
    //   128: invokestatic 34	java/lang/Boolean:valueOf	(Z)Ljava/lang/Boolean;
    //   131: invokevirtual 40	java/lang/ThreadLocal:set	(Ljava/lang/Object;)V
    //   134: aload_0
    //   135: getfield 14	dej:b	Ldei;
    //   138: aload_0
    //   139: getfield 16	dej:a	Ldau;
    //   142: invokestatic 65	dei:a	(Ldei;Ldau;)V
    //   145: aload_0
    //   146: getfield 14	dej:b	Ldei;
    //   149: invokestatic 69	dei:c	(Ldei;)Ljava/lang/ref/WeakReference;
    //   152: invokevirtual 75	java/lang/ref/WeakReference:get	()Ljava/lang/Object;
    //   155: checkcast 77	daj
    //   158: astore_1
    //   159: aload_1
    //   160: ifnull +11 -> 171
    //   163: aload_1
    //   164: aload_0
    //   165: getfield 14	dej:b	Ldei;
    //   168: invokevirtual 80	daj:b	(Ldei;)V
    //   171: return
    //   172: getstatic 28	com/google/android/gms/common/api/internal/BasePendingResult:a	Ljava/lang/ThreadLocal;
    //   175: iconst_0
    //   176: invokestatic 34	java/lang/Boolean:valueOf	(Z)Ljava/lang/Boolean;
    //   179: invokevirtual 40	java/lang/ThreadLocal:set	(Ljava/lang/Object;)V
    //   182: aload_0
    //   183: getfield 14	dej:b	Ldei;
    //   186: aload_0
    //   187: getfield 16	dej:a	Ldau;
    //   190: invokestatic 65	dei:a	(Ldei;Ldau;)V
    //   193: aload_0
    //   194: getfield 14	dej:b	Ldei;
    //   197: invokestatic 69	dei:c	(Ldei;)Ljava/lang/ref/WeakReference;
    //   200: invokevirtual 75	java/lang/ref/WeakReference:get	()Ljava/lang/Object;
    //   203: checkcast 77	daj
    //   206: astore_2
    //   207: aload_2
    //   208: ifnull +11 -> 219
    //   211: aload_2
    //   212: aload_0
    //   213: getfield 14	dej:b	Ldei;
    //   216: invokevirtual 80	daj:b	(Ldei;)V
    //   219: aload_1
    //   220: athrow
    // Local variable table:
    //   start	length	slot	name	signature
    //   0	221	0	this	dej
    //   24	64	1	localObject1	Object
    //   96	1	1	localObject2	Object
    //   100	17	1	localRuntimeException	RuntimeException
    //   158	62	1	localDaj1	daj
    //   206	6	2	localDaj2	daj
    // Exception table:
    //   from	to	target	type
    //   0	48	96	finally
    //   101	124	96	finally
    //   0	48	100	java/lang/RuntimeException
  }
}
