package com.mobile.ui.termsandconditions.fragment;

import android.os.Bundle;
import android.support.annotation.Nullable;
import android.view.View;
import android.widget.TextView;
import com.mobile.ui.App;
import com.mobile.ui.R.string;
import kkkkkk.bbpbpp;
import kkkkkk.gguuuu;
import kkkkkk.pbbbpp;
import kkkkkk.uyuuuu;
import kkkkkk.uyyyyy;

public class IBTermsAndConditionsFragment
  extends TermsAndConditionsFragment<pbbbpp, bbpbpp>
  implements pbbbpp
{
  private static final String ARG_SHOULD_SHOW_ENROLMENT_SCREEN = ",<0G:.49/&@3'-4; (+'##\032\"'1$\023!\023\022\032";
  public static int b042F042F042FЯ042F042FЯЯЯ = 0;
  public static int b042FЯЯ042F042F042FЯЯЯ = 2;
  public static int bЯ042F042FЯ042F042FЯЯЯ = 73;
  public static int bЯЯЯ042F042F042FЯЯЯ = 1;
  
  static
  {
    String str = ARG_SHOULD_SHOW_ENROLMENT_SCREEN;
    int i = bЯ042F042FЯ042F042FЯЯЯ;
    switch (i * (bЯЯЯ042F042F042FЯЯЯ + i) % b042FЯЯ042F042F042FЯЯЯ)
    {
    default: 
      bЯ042F042FЯ042F042FЯЯЯ = 48;
      b042F042F042FЯ042F042FЯЯЯ = bЯ042FЯ042F042F042FЯЯЯ();
    }
    str = gguuuu.bк043Aккк043Aкк043A043A(str, '«', '\027', '\000');
    if ((bЯ042F042FЯ042F042FЯЯЯ + bЯЯЯ042F042F042FЯЯЯ) * bЯ042F042FЯ042F042FЯЯЯ % b042FЯЯ042F042F042FЯЯЯ != b042F042F042FЯ042F042FЯЯЯ)
    {
      bЯ042F042FЯ042F042FЯЯЯ = 61;
      b042F042F042FЯ042F042FЯЯЯ = bЯ042FЯ042F042F042FЯЯЯ();
    }
    switch (1)
    {
    case 0: 
    default: 
      for (;;)
      {
        switch (1)
        {
        }
      }
    }
    ARG_SHOULD_SHOW_ENROLMENT_SCREEN = str;
  }
  
  public IBTermsAndConditionsFragment() {}
  
  public static int b042F042FЯ042F042F042FЯЯЯ()
  {
    return 2;
  }
  
  public static int b042FЯ042F042F042F042FЯЯЯ()
  {
    return 0;
  }
  
  public static int bЯ042FЯ042F042F042FЯЯЯ()
  {
    return 82;
  }
  
  public static int bЯЯ042F042F042F042FЯЯЯ()
  {
    return 1;
  }
  
  /* Error */
  public static IBTermsAndConditionsFragment newInstance(boolean paramBoolean)
  {
    // Byte code:
    //   0: new 2	com/mobile/ui/termsandconditions/fragment/IBTermsAndConditionsFragment
    //   3: dup
    //   4: invokespecial 54	com/mobile/ui/termsandconditions/fragment/IBTermsAndConditionsFragment:<init>	()V
    //   7: astore 6
    //   9: getstatic 26	com/mobile/ui/termsandconditions/fragment/IBTermsAndConditionsFragment:bЯ042F042FЯ042F042FЯЯЯ	I
    //   12: istore_1
    //   13: iload_1
    //   14: getstatic 28	com/mobile/ui/termsandconditions/fragment/IBTermsAndConditionsFragment:bЯЯЯ042F042F042FЯЯЯ	I
    //   17: iload_1
    //   18: iadd
    //   19: imul
    //   20: getstatic 30	com/mobile/ui/termsandconditions/fragment/IBTermsAndConditionsFragment:b042FЯЯ042F042F042FЯЯЯ	I
    //   23: irem
    //   24: tableswitch	default:+20->44, 0:+32->56
    //   44: invokestatic 34	com/mobile/ui/termsandconditions/fragment/IBTermsAndConditionsFragment:bЯ042FЯ042F042F042FЯЯЯ	()I
    //   47: putstatic 26	com/mobile/ui/termsandconditions/fragment/IBTermsAndConditionsFragment:bЯ042F042FЯ042F042FЯЯЯ	I
    //   50: invokestatic 34	com/mobile/ui/termsandconditions/fragment/IBTermsAndConditionsFragment:bЯ042FЯ042F042F042FЯЯЯ	()I
    //   53: putstatic 36	com/mobile/ui/termsandconditions/fragment/IBTermsAndConditionsFragment:b042F042F042FЯ042F042FЯЯЯ	I
    //   56: new 56	android/os/Bundle
    //   59: dup
    //   60: invokespecial 57	android/os/Bundle:<init>	()V
    //   63: astore 7
    //   65: ldc 59
    //   67: sipush 216
    //   70: iconst_3
    //   71: invokestatic 63	kkkkkk/gguuuu:bккккк043Aкк043A043A	(Ljava/lang/String;CC)Ljava/lang/String;
    //   74: astore 8
    //   76: goto +78 -> 154
    //   79: aload 7
    //   81: aload 8
    //   83: iload_0
    //   84: invokevirtual 67	android/os/Bundle:putBoolean	(Ljava/lang/String;Z)V
    //   87: getstatic 26	com/mobile/ui/termsandconditions/fragment/IBTermsAndConditionsFragment:bЯ042F042FЯ042F042FЯЯЯ	I
    //   90: istore_1
    //   91: getstatic 28	com/mobile/ui/termsandconditions/fragment/IBTermsAndConditionsFragment:bЯЯЯ042F042F042FЯЯЯ	I
    //   94: istore_2
    //   95: getstatic 26	com/mobile/ui/termsandconditions/fragment/IBTermsAndConditionsFragment:bЯ042F042FЯ042F042FЯЯЯ	I
    //   98: istore_3
    //   99: getstatic 30	com/mobile/ui/termsandconditions/fragment/IBTermsAndConditionsFragment:b042FЯЯ042F042F042FЯЯЯ	I
    //   102: istore 4
    //   104: getstatic 36	com/mobile/ui/termsandconditions/fragment/IBTermsAndConditionsFragment:b042F042F042FЯ042F042FЯЯЯ	I
    //   107: istore 5
    //   109: iload_1
    //   110: iload_2
    //   111: iadd
    //   112: iload_3
    //   113: imul
    //   114: iload 4
    //   116: irem
    //   117: iload 5
    //   119: if_icmpeq +15 -> 134
    //   122: invokestatic 34	com/mobile/ui/termsandconditions/fragment/IBTermsAndConditionsFragment:bЯ042FЯ042F042F042FЯЯЯ	()I
    //   125: putstatic 26	com/mobile/ui/termsandconditions/fragment/IBTermsAndConditionsFragment:bЯ042F042FЯ042F042FЯЯЯ	I
    //   128: invokestatic 34	com/mobile/ui/termsandconditions/fragment/IBTermsAndConditionsFragment:bЯ042FЯ042F042F042FЯЯЯ	()I
    //   131: putstatic 36	com/mobile/ui/termsandconditions/fragment/IBTermsAndConditionsFragment:b042F042F042FЯ042F042FЯЯЯ	I
    //   134: aload 6
    //   136: aload 7
    //   138: invokevirtual 71	com/mobile/ui/termsandconditions/fragment/IBTermsAndConditionsFragment:setArguments	(Landroid/os/Bundle;)V
    //   141: aload 6
    //   143: areturn
    //   144: astore 6
    //   146: aload 6
    //   148: athrow
    //   149: astore 6
    //   151: aload 6
    //   153: athrow
    //   154: iconst_0
    //   155: tableswitch	default:+21->176, 0:+-76->79, 1:+-1->154
    //   176: iconst_0
    //   177: tableswitch	default:+23->200, 0:+-98->79, 1:+-23->154
    //   200: goto -24 -> 176
    // Local variable table:
    //   start	length	slot	name	signature
    //   0	203	0	paramBoolean	boolean
    //   12	100	1	i	int
    //   94	18	2	j	int
    //   98	16	3	k	int
    //   102	15	4	m	int
    //   107	13	5	n	int
    //   7	135	6	localIBTermsAndConditionsFragment	IBTermsAndConditionsFragment
    //   144	3	6	localException1	Exception
    //   149	3	6	localException2	Exception
    //   63	74	7	localBundle	Bundle
    //   74	8	8	str	String
    // Exception table:
    //   from	to	target	type
    //   0	9	144	java/lang/Exception
    //   56	76	144	java/lang/Exception
    //   79	109	144	java/lang/Exception
    //   134	141	144	java/lang/Exception
    //   122	134	149	java/lang/Exception
  }
  
  public void onCreate(@Nullable Bundle paramBundle)
  {
    try
    {
      super.onCreate(paramBundle);
      paramBundle = App.get();
      int i = bЯ042F042FЯ042F042FЯЯЯ;
      int j = bЯЯЯ042F042F042FЯЯЯ;
      for (;;)
      {
        try
        {
          switch (i * (j + i) % b042FЯЯ042F042F042FЯЯЯ)
          {
          case 0: 
            bЯ042F042FЯ042F042FЯЯЯ = 15;
            b042F042F042FЯ042F042FЯЯЯ = bЯ042FЯ042F042F042FЯЯЯ();
            paramBundle = paramBundle.getAppComponent();
            i = bЯ042F042FЯ042F042FЯЯЯ;
            switch (i * (bЯЯЯ042F042F042FЯЯЯ + i) % b042F042FЯ042F042F042FЯЯЯ())
            {
            default: 
              bЯ042F042FЯ042F042FЯЯЯ = bЯ042FЯ042F042F042FЯЯЯ();
              b042F042F042FЯ042F042FЯЯЯ = bЯ042FЯ042F042F042FЯЯЯ();
            }
            switch (0)
            {
            case 1: 
            default: 
              switch (1)
              {
              }
              break;
            }
            paramBundle.b041804180418И04180418ИИИ0418(this);
            return;
          }
        }
        catch (Exception paramBundle)
        {
          throw paramBundle;
        }
      }
    }
    catch (Exception paramBundle)
    {
      throw paramBundle;
    }
  }
  
  /* Error */
  public void onPrimaryButtonPressed(TextView paramTextView)
  {
    // Byte code:
    //   0: aload_0
    //   1: getfield 100	com/mobile/ui/termsandconditions/fragment/IBTermsAndConditionsFragment:mPresenter	Lkkkkkk/gggggr;
    //   4: astore_1
    //   5: getstatic 26	com/mobile/ui/termsandconditions/fragment/IBTermsAndConditionsFragment:bЯ042F042FЯ042F042FЯЯЯ	I
    //   8: istore_2
    //   9: getstatic 28	com/mobile/ui/termsandconditions/fragment/IBTermsAndConditionsFragment:bЯЯЯ042F042F042FЯЯЯ	I
    //   12: istore_3
    //   13: getstatic 26	com/mobile/ui/termsandconditions/fragment/IBTermsAndConditionsFragment:bЯ042F042FЯ042F042FЯЯЯ	I
    //   16: istore 4
    //   18: getstatic 30	com/mobile/ui/termsandconditions/fragment/IBTermsAndConditionsFragment:b042FЯЯ042F042F042FЯЯЯ	I
    //   21: istore 5
    //   23: getstatic 26	com/mobile/ui/termsandconditions/fragment/IBTermsAndConditionsFragment:bЯ042F042FЯ042F042FЯЯЯ	I
    //   26: invokestatic 102	com/mobile/ui/termsandconditions/fragment/IBTermsAndConditionsFragment:bЯЯ042F042F042F042FЯЯЯ	()I
    //   29: iadd
    //   30: getstatic 26	com/mobile/ui/termsandconditions/fragment/IBTermsAndConditionsFragment:bЯ042F042FЯ042F042FЯЯЯ	I
    //   33: imul
    //   34: getstatic 30	com/mobile/ui/termsandconditions/fragment/IBTermsAndConditionsFragment:b042FЯЯ042F042F042FЯЯЯ	I
    //   37: irem
    //   38: getstatic 36	com/mobile/ui/termsandconditions/fragment/IBTermsAndConditionsFragment:b042F042F042FЯ042F042FЯЯЯ	I
    //   41: if_icmpeq +12 -> 53
    //   44: iconst_0
    //   45: putstatic 26	com/mobile/ui/termsandconditions/fragment/IBTermsAndConditionsFragment:bЯ042F042FЯ042F042FЯЯЯ	I
    //   48: bipush 95
    //   50: putstatic 36	com/mobile/ui/termsandconditions/fragment/IBTermsAndConditionsFragment:b042F042F042FЯ042F042FЯЯЯ	I
    //   53: iload_2
    //   54: iload_3
    //   55: iadd
    //   56: iload 4
    //   58: imul
    //   59: iload 5
    //   61: irem
    //   62: getstatic 36	com/mobile/ui/termsandconditions/fragment/IBTermsAndConditionsFragment:b042F042F042FЯ042F042FЯЯЯ	I
    //   65: if_icmpeq +13 -> 78
    //   68: bipush 38
    //   70: putstatic 26	com/mobile/ui/termsandconditions/fragment/IBTermsAndConditionsFragment:bЯ042F042FЯ042F042FЯЯЯ	I
    //   73: bipush 60
    //   75: putstatic 36	com/mobile/ui/termsandconditions/fragment/IBTermsAndConditionsFragment:b042F042F042FЯ042F042FЯЯЯ	I
    //   78: aload_1
    //   79: checkcast 104	kkkkkk/bbpbpp
    //   82: astore_1
    //   83: aload_1
    //   84: invokevirtual 107	kkkkkk/bbpbpp:bННННН041DН041D041DН	()V
    //   87: return
    //   88: astore_1
    //   89: aload_1
    //   90: athrow
    //   91: astore_1
    //   92: iconst_1
    //   93: tableswitch	default:+23->116, 0:+-1->92, 1:+50->143
    //   116: iconst_0
    //   117: tableswitch	default:+23->140, 0:+26->143, 1:+-25->92
    //   140: goto -24 -> 116
    //   143: aload_1
    //   144: athrow
    // Local variable table:
    //   start	length	slot	name	signature
    //   0	145	0	this	IBTermsAndConditionsFragment
    //   0	145	1	paramTextView	TextView
    //   8	48	2	i	int
    //   12	44	3	j	int
    //   16	43	4	k	int
    //   21	41	5	m	int
    // Exception table:
    //   from	to	target	type
    //   0	5	88	java/lang/Exception
    //   78	83	88	java/lang/Exception
    //   83	87	91	java/lang/Exception
  }
  
  public void onSecondaryButtonPressed(TextView paramTextView)
  {
    ((uyuuuu)getActivity()).showTermsAndConditionsDeclinedScreen();
  }
  
  public void onViewCreated(View paramView, @Nullable Bundle paramBundle)
  {
    try
    {
      super.onViewCreated(paramView, paramBundle);
      i = R.string.ib_terms_and_conditions_view_primary_button_text;
    }
    catch (Exception paramView)
    {
      int i;
      boolean bool;
      throw paramView;
    }
    try
    {
      setPrimaryButtonViewText(i);
      setSecondaryButtonViewText(R.string.ib_terms_and_conditions_view_secondary_button_text);
    }
    catch (Exception paramView)
    {
      throw paramView;
    }
    paramView = getArguments();
    bool = paramView.getBoolean(gguuuu.bк043Aккк043Aкк043A043A("Yi]tg[af\\Sm`TZahMUXTPPGOT^Q@N@?G", 'è', '}', '\002'));
    i = bЯ042FЯ042F042F042FЯЯЯ();
    switch (i * (bЯЯЯ042F042F042FЯЯЯ + i) % b042FЯЯ042F042F042FЯЯЯ)
    {
    default: 
      bЯ042F042FЯ042F042FЯЯЯ = 92;
      b042F042F042FЯ042F042FЯЯЯ = bЯ042FЯ042F042F042FЯЯЯ();
    }
    i = bЯ042F042FЯ042F042FЯЯЯ;
    switch (i * (bЯЯЯ042F042F042FЯЯЯ + i) % b042FЯЯ042F042F042FЯЯЯ)
    {
    default: 
      bЯ042F042FЯ042F042FЯЯЯ = bЯ042FЯ042F042F042FЯЯЯ();
      b042F042F042FЯ042F042FЯЯЯ = bЯ042FЯ042F042F042FЯЯЯ();
    }
    ((bbpbpp)this.mPresenter).bННН041DН041DН041D041DН(bool);
    return;
    switch (0)
    {
    }
    for (;;)
    {
      switch (1)
      {
      }
    }
  }
  
  public void showEnrolmentScreen()
  {
    try
    {
      uyuuuu localUyuuuu = (uyuuuu)getActivity();
      int i = bЯ042F042FЯ042F042FЯЯЯ;
      switch (i * (bЯЯЯ042F042F042FЯЯЯ + i) % b042FЯЯ042F042F042FЯЯЯ)
      {
      default: 
        bЯ042F042FЯ042F042FЯЯЯ = bЯ042FЯ042F042F042FЯЯЯ();
        b042F042F042FЯ042F042FЯЯЯ = 82;
      }
      localUyuuuu.showEnrollmentScreen();
      return;
    }
    catch (Exception localException)
    {
      throw localException;
    }
  }
  
  public void trackScreenView()
  {
    switch (0)
    {
    case 1: 
    default: 
      for (;;)
      {
        switch (1)
        {
        }
      }
    }
  }
}
