package com.mobile.ui.termsandconditions.fragment;

import android.os.Bundle;
import android.support.annotation.Nullable;
import android.support.v4.app.FragmentActivity;
import android.view.LayoutInflater;
import android.view.View;
import android.view.ViewGroup;
import android.widget.TextView;
import butterknife.OnClick;
import com.mobile.ui.App;
import com.mobile.ui.R.layout;
import com.mobile.ui.R.string;
import com.mobile.ui.common.fragment.BaseRequestFragment;
import kkkkkk.bbbbpp;
import kkkkkk.rgrrrg.ggrgrg;
import kkkkkk.uyyyyy;

public class TermsAndConditionsWinBackFragment
  extends BaseRequestFragment<rgrrrg.ggrgrg, bbbbpp>
  implements rgrrrg.ggrgrg
{
  public static int b042F042F042FЯЯ042F042FЯЯ = 2;
  public static int b042FЯ042FЯЯ042F042FЯЯ = 58;
  public static int b042FЯЯ042FЯ042F042FЯЯ = 0;
  public static int bЯ042F042FЯЯ042F042FЯЯ = 1;
  
  public TermsAndConditionsWinBackFragment() {}
  
  public static int b042F042FЯ042FЯ042F042FЯЯ()
  {
    return 2;
  }
  
  public static int bЯ042FЯ042FЯ042F042FЯЯ()
  {
    return 0;
  }
  
  public static int bЯЯЯ042FЯ042F042FЯЯ()
  {
    return 97;
  }
  
  /* Error */
  public static TermsAndConditionsWinBackFragment newInstance()
  {
    // Byte code:
    //   0: getstatic 31	com/mobile/ui/termsandconditions/fragment/TermsAndConditionsWinBackFragment:b042FЯ042FЯЯ042F042FЯЯ	I
    //   3: istore_0
    //   4: iload_0
    //   5: getstatic 33	com/mobile/ui/termsandconditions/fragment/TermsAndConditionsWinBackFragment:bЯ042F042FЯЯ042F042FЯЯ	I
    //   8: iload_0
    //   9: iadd
    //   10: imul
    //   11: getstatic 35	com/mobile/ui/termsandconditions/fragment/TermsAndConditionsWinBackFragment:b042F042F042FЯЯ042F042FЯЯ	I
    //   14: irem
    //   15: tableswitch	default:+17->32, 0:+29->44
    //   32: invokestatic 37	com/mobile/ui/termsandconditions/fragment/TermsAndConditionsWinBackFragment:bЯЯЯ042FЯ042F042FЯЯ	()I
    //   35: putstatic 31	com/mobile/ui/termsandconditions/fragment/TermsAndConditionsWinBackFragment:b042FЯ042FЯЯ042F042FЯЯ	I
    //   38: invokestatic 37	com/mobile/ui/termsandconditions/fragment/TermsAndConditionsWinBackFragment:bЯЯЯ042FЯ042F042FЯЯ	()I
    //   41: putstatic 33	com/mobile/ui/termsandconditions/fragment/TermsAndConditionsWinBackFragment:bЯ042F042FЯЯ042F042FЯЯ	I
    //   44: new 2	com/mobile/ui/termsandconditions/fragment/TermsAndConditionsWinBackFragment
    //   47: dup
    //   48: invokespecial 38	com/mobile/ui/termsandconditions/fragment/TermsAndConditionsWinBackFragment:<init>	()V
    //   51: astore_3
    //   52: getstatic 31	com/mobile/ui/termsandconditions/fragment/TermsAndConditionsWinBackFragment:b042FЯ042FЯЯ042F042FЯЯ	I
    //   55: istore_0
    //   56: getstatic 33	com/mobile/ui/termsandconditions/fragment/TermsAndConditionsWinBackFragment:bЯ042F042FЯЯ042F042FЯЯ	I
    //   59: istore_1
    //   60: getstatic 35	com/mobile/ui/termsandconditions/fragment/TermsAndConditionsWinBackFragment:b042F042F042FЯЯ042F042FЯЯ	I
    //   63: istore_2
    //   64: iload_0
    //   65: iload_1
    //   66: iload_0
    //   67: iadd
    //   68: imul
    //   69: iload_2
    //   70: irem
    //   71: tableswitch	default:+17->88, 0:+38->109
    //   88: bipush 38
    //   90: putstatic 31	com/mobile/ui/termsandconditions/fragment/TermsAndConditionsWinBackFragment:b042FЯ042FЯЯ042F042FЯЯ	I
    //   93: bipush 49
    //   95: putstatic 33	com/mobile/ui/termsandconditions/fragment/TermsAndConditionsWinBackFragment:bЯ042F042FЯЯ042F042FЯЯ	I
    //   98: aload_3
    //   99: areturn
    //   100: astore_3
    //   101: aload_3
    //   102: athrow
    //   103: astore_3
    //   104: aload_3
    //   105: athrow
    //   106: astore_3
    //   107: aload_3
    //   108: athrow
    //   109: aload_3
    //   110: areturn
    // Local variable table:
    //   start	length	slot	name	signature
    //   3	66	0	i	int
    //   59	9	1	j	int
    //   63	8	2	k	int
    //   51	48	3	localTermsAndConditionsWinBackFragment	TermsAndConditionsWinBackFragment
    //   100	2	3	localException1	Exception
    //   103	2	3	localException2	Exception
    //   106	4	3	localException3	Exception
    // Exception table:
    //   from	to	target	type
    //   44	52	100	java/lang/Exception
    //   88	98	103	java/lang/Exception
    //   101	103	103	java/lang/Exception
    //   52	64	106	java/lang/Exception
  }
  
  public void onCreate(@Nullable Bundle paramBundle)
  {
    if ((b042FЯ042FЯЯ042F042FЯЯ + bЯ042F042FЯЯ042F042FЯЯ) * b042FЯ042FЯЯ042F042FЯЯ % b042F042F042FЯЯ042F042FЯЯ != b042FЯЯ042FЯ042F042FЯЯ)
    {
      b042FЯ042FЯЯ042F042FЯЯ = bЯЯЯ042FЯ042F042FЯЯ();
      b042FЯЯ042FЯ042F042FЯЯ = 64;
    }
    try
    {
      super.onCreate(paramBundle);
      paramBundle = App.get().getAppComponent();
    }
    catch (Exception paramBundle)
    {
      try
      {
        int i;
        int j;
        int k;
        int m;
        int n;
        b042FЯ042FЯЯ042F042FЯЯ = bЯЯЯ042FЯ042F042FЯЯ();
        b042FЯЯ042FЯ042F042FЯЯ = 9;
        return;
      }
      catch (Exception paramBundle)
      {
        throw paramBundle;
      }
      paramBundle = paramBundle;
      throw paramBundle;
    }
    paramBundle.bИ041804180418И0418ИИИ0418(this);
    i = b042FЯ042FЯЯ042F042FЯЯ;
    j = bЯ042F042FЯЯ042F042FЯЯ;
    k = b042FЯ042FЯЯ042F042FЯЯ;
    m = b042F042F042FЯЯ042F042FЯЯ;
    n = b042FЯЯ042FЯ042F042FЯЯ;
    if ((i + j) * k % m != n) {}
    switch (0)
    {
    }
    for (;;)
    {
      switch (0)
      {
      }
    }
  }
  
  @Nullable
  public View onCreateView(LayoutInflater paramLayoutInflater, @Nullable ViewGroup paramViewGroup, @Nullable Bundle paramBundle)
  {
    switch (0)
    {
    case 1: 
    default: 
      for (;;)
      {
        switch (0)
        {
        }
      }
    }
    int i = R.layout.fragment_terms_and_conditions_win_back;
    if ((b042FЯ042FЯЯ042F042FЯЯ + bЯ042F042FЯЯ042F042FЯЯ) * b042FЯ042FЯЯ042F042FЯЯ % b042F042F042FЯЯ042F042FЯЯ != b042FЯЯ042FЯ042F042FЯЯ)
    {
      b042FЯ042FЯЯ042F042FЯЯ = 90;
      b042FЯЯ042FЯ042F042FЯЯ = 64;
      if ((b042FЯ042FЯЯ042F042FЯЯ + bЯ042F042FЯЯ042F042FЯЯ) * b042FЯ042FЯЯ042F042FЯЯ % b042F042FЯ042FЯ042F042FЯЯ() != bЯ042FЯ042FЯ042F042FЯЯ())
      {
        b042FЯ042FЯЯ042F042FЯЯ = bЯЯЯ042FЯ042F042FЯЯ();
        b042FЯЯ042FЯ042F042FЯЯ = 70;
      }
    }
    return paramLayoutInflater.inflate(i, paramViewGroup, false);
  }
  
  @OnClick({2131494524})
  public void onPrimaryButtonPressed(TextView paramTextView)
  {
    int i = R.string.fragment_common_terms_and_conditions_error_content_text;
    switch (1)
    {
    case 0: 
    default: 
      for (;;)
      {
        switch (1)
        {
        }
      }
    }
    if ((bЯЯЯ042FЯ042F042FЯЯ() + bЯ042F042FЯЯ042F042FЯЯ) * bЯЯЯ042FЯ042F042FЯЯ() % b042F042F042FЯЯ042F042FЯЯ != b042FЯЯ042FЯ042F042FЯЯ)
    {
      if ((b042FЯ042FЯЯ042F042FЯЯ + bЯ042F042FЯЯ042F042FЯЯ) * b042FЯ042FЯЯ042F042FЯЯ % b042F042F042FЯЯ042F042FЯЯ != b042FЯЯ042FЯ042F042FЯЯ)
      {
        b042FЯ042FЯЯ042F042FЯЯ = bЯЯЯ042FЯ042F042FЯЯ();
        b042FЯЯ042FЯ042F042FЯЯ = 85;
      }
      b042FЯ042FЯЯ042F042FЯЯ = 79;
      b042FЯЯ042FЯ042F042FЯЯ = bЯЯЯ042FЯ042F042FЯЯ();
    }
    showLoggedOutErrorScreen(i);
  }
  
  @OnClick({2131494523})
  public void onSecondaryButtonPressed(TextView paramTextView)
  {
    switch (1)
    {
    case 0: 
    default: 
      for (;;)
      {
        switch (1)
        {
        }
      }
    }
    paramTextView = getActivity();
    if ((b042FЯ042FЯЯ042F042FЯЯ + bЯ042F042FЯЯ042F042FЯЯ) * b042FЯ042FЯЯ042F042FЯЯ % b042F042FЯ042FЯ042F042FЯЯ() != b042FЯЯ042FЯ042F042FЯЯ)
    {
      b042FЯ042FЯЯ042F042FЯЯ = 43;
      b042FЯЯ042FЯ042F042FЯЯ = 27;
    }
    if ((b042FЯ042FЯЯ042F042FЯЯ + bЯ042F042FЯЯ042F042FЯЯ) * b042FЯ042FЯЯ042F042FЯЯ % b042F042F042FЯЯ042F042FЯЯ != b042FЯЯ042FЯ042F042FЯЯ)
    {
      b042FЯ042FЯЯ042F042FЯЯ = 29;
      b042FЯЯ042FЯ042F042FЯЯ = 81;
    }
    paramTextView.onBackPressed();
  }
  
  public void trackScreenView() {}
}
