package com.mobile.ui.enrollment.fragment;

import android.os.Bundle;
import android.support.annotation.Nullable;
import android.view.LayoutInflater;
import android.view.View;
import android.view.ViewGroup;
import com.mobile.ui.R.layout;
import com.mobile.ui.common.fragment.BaseRequestFragment;
import com.mobile.ui.enrollment.activity.EnrollmentActivity.kkttkk;
import java.util.UUID;
import kkkkkk.gguuuu;
import kkkkkk.ktkttk;
import kkkkkk.kttttk;
import kkkkkk.qiiiii;

public class EnrollmentBypassFragment
  extends BaseRequestFragment<kttttk, ktkttk>
  implements kttttk
{
  private static final String ARG_TRANSACTION_ID = "^pfutdrxgj|ryy\fvr";
  public static int b04490449044904490449щ0449щ = 1;
  public static int b04490449щщщ04490449щ = 0;
  public static int bщ0449044904490449щ0449щ = 60;
  public static int bщщщщщ04490449щ = 2;
  
  static
  {
    try
    {
      str = ARG_TRANSACTION_ID;
    }
    catch (Exception localException1)
    {
      try
      {
        String str;
        i = bщ0449044904490449щ0449щ;
        switch (i * (b04490449044904490449щ0449щ + i) % bщщщщщ04490449щ)
        {
        case 0: 
          bщ0449044904490449щ0449щ = 39;
          b04490449щщщ04490449щ = b0449щщщщ04490449щ();
          if ((bщ0449044904490449щ0449щ + b04490449044904490449щ0449щ) * bщ0449044904490449щ0449щ % bщщщщщ04490449щ != b04490449щщщ04490449щ)
          {
            bщ0449044904490449щ0449щ = b0449щщщщ04490449щ();
            b04490449щщщ04490449щ = 93;
          }
          ARG_TRANSACTION_ID = str;
          return;
        }
      }
      catch (Exception localException2)
      {
        throw localException2;
      }
      localException1 = localException1;
      throw localException1;
    }
    str = gguuuu.bк043Aккк043Aкк043A043A(str, '+', '', '\001');
    for (;;)
    {
      int i;
      switch (0)
      {
      }
      for (;;)
      {
        switch (0)
        {
        }
      }
    }
  }
  
  public EnrollmentBypassFragment() {}
  
  public static int b0449щщщщ04490449щ()
  {
    return 83;
  }
  
  public static int bщ0449щщщ04490449щ()
  {
    return 1;
  }
  
  public static int bщщ0449щщ04490449щ()
  {
    return 2;
  }
  
  public static EnrollmentBypassFragment newInstance(UUID paramUUID)
  {
    try
    {
      EnrollmentBypassFragment localEnrollmentBypassFragment = new EnrollmentBypassFragment();
      Bundle localBundle;
      int i;
      for (;;) {}
    }
    catch (Exception paramUUID)
    {
      try
      {
        localBundle = new Bundle();
        i = bщ0449044904490449щ0449щ;
        switch (i * (b04490449044904490449щ0449щ + i) % bщщщщщ04490449щ)
        {
        case 0: 
          bщ0449044904490449щ0449щ = 38;
          b04490449044904490449щ0449щ = 49;
          i = b0449щщщщ04490449щ();
          switch (i * (bщ0449щщщ04490449щ() + i) % bщщщщщ04490449щ)
          {
          default: 
            bщ0449044904490449щ0449щ = b0449щщщщ04490449щ();
            b04490449044904490449щ0449щ = b0449щщщщ04490449щ();
          }
          localBundle.putSerializable(gguuuu.bккккк043Aкк043A043A("\016\036\022)\035\032\b\024\030\005\006\026\n\017\r\035\006", '²', '\005'), paramUUID);
          localEnrollmentBypassFragment.setArguments(localBundle);
          return localEnrollmentBypassFragment;
        }
      }
      catch (Exception paramUUID)
      {
        throw paramUUID;
      }
      paramUUID = paramUUID;
      throw paramUUID;
    }
  }
  
  /* Error */
  @butterknife.OnClick({2131493385})
  public void onClickContinue(android.widget.TextView paramTextView)
  {
    // Byte code:
    //   0: aload_0
    //   1: invokevirtual 81	com/mobile/ui/enrollment/fragment/EnrollmentBypassFragment:getArguments	()Landroid/os/Bundle;
    //   4: astore_2
    //   5: aload_2
    //   6: ldc 83
    //   8: bipush 71
    //   10: iconst_4
    //   11: invokestatic 64	kkkkkk/gguuuu:bккккк043Aкк043A043A	(Ljava/lang/String;CC)Ljava/lang/String;
    //   14: invokevirtual 87	android/os/Bundle:getSerializable	(Ljava/lang/String;)Ljava/io/Serializable;
    //   17: checkcast 89	java/util/UUID
    //   20: astore_2
    //   21: getstatic 34	com/mobile/ui/enrollment/fragment/EnrollmentBypassFragment:bщ0449044904490449щ0449щ	I
    //   24: getstatic 36	com/mobile/ui/enrollment/fragment/EnrollmentBypassFragment:b04490449044904490449щ0449щ	I
    //   27: iadd
    //   28: getstatic 34	com/mobile/ui/enrollment/fragment/EnrollmentBypassFragment:bщ0449044904490449щ0449щ	I
    //   31: imul
    //   32: getstatic 38	com/mobile/ui/enrollment/fragment/EnrollmentBypassFragment:bщщщщщ04490449щ	I
    //   35: irem
    //   36: getstatic 44	com/mobile/ui/enrollment/fragment/EnrollmentBypassFragment:b04490449щщщ04490449щ	I
    //   39: if_icmpeq +14 -> 53
    //   42: invokestatic 42	com/mobile/ui/enrollment/fragment/EnrollmentBypassFragment:b0449щщщщ04490449щ	()I
    //   45: putstatic 34	com/mobile/ui/enrollment/fragment/EnrollmentBypassFragment:bщ0449044904490449щ0449щ	I
    //   48: bipush 9
    //   50: putstatic 44	com/mobile/ui/enrollment/fragment/EnrollmentBypassFragment:b04490449щщщ04490449щ	I
    //   53: getstatic 34	com/mobile/ui/enrollment/fragment/EnrollmentBypassFragment:bщ0449044904490449щ0449щ	I
    //   56: getstatic 36	com/mobile/ui/enrollment/fragment/EnrollmentBypassFragment:b04490449044904490449щ0449щ	I
    //   59: iadd
    //   60: getstatic 34	com/mobile/ui/enrollment/fragment/EnrollmentBypassFragment:bщ0449044904490449щ0449щ	I
    //   63: imul
    //   64: getstatic 38	com/mobile/ui/enrollment/fragment/EnrollmentBypassFragment:bщщщщщ04490449щ	I
    //   67: irem
    //   68: getstatic 44	com/mobile/ui/enrollment/fragment/EnrollmentBypassFragment:b04490449щщщ04490449щ	I
    //   71: if_icmpeq +15 -> 86
    //   74: invokestatic 42	com/mobile/ui/enrollment/fragment/EnrollmentBypassFragment:b0449щщщщ04490449щ	()I
    //   77: putstatic 34	com/mobile/ui/enrollment/fragment/EnrollmentBypassFragment:bщ0449044904490449щ0449щ	I
    //   80: invokestatic 42	com/mobile/ui/enrollment/fragment/EnrollmentBypassFragment:b0449щщщщ04490449щ	()I
    //   83: putstatic 44	com/mobile/ui/enrollment/fragment/EnrollmentBypassFragment:b04490449щщщ04490449щ	I
    //   86: aload_0
    //   87: getfield 93	com/mobile/ui/enrollment/fragment/EnrollmentBypassFragment:mPresenter	Lkkkkkk/gggggr;
    //   90: checkcast 95	kkkkkk/ktkttk
    //   93: aload_2
    //   94: aload_1
    //   95: invokevirtual 101	android/widget/TextView:getText	()Ljava/lang/CharSequence;
    //   98: invokevirtual 105	kkkkkk/ktkttk:b0410А0410ААААА0410А	(Ljava/util/UUID;Ljava/lang/CharSequence;)V
    //   101: return
    //   102: astore_1
    //   103: aload_1
    //   104: athrow
    //   105: astore_1
    //   106: aload_1
    //   107: athrow
    // Local variable table:
    //   start	length	slot	name	signature
    //   0	108	0	this	EnrollmentBypassFragment
    //   0	108	1	paramTextView	android.widget.TextView
    //   4	90	2	localObject	Object
    // Exception table:
    //   from	to	target	type
    //   0	5	102	java/lang/Exception
    //   86	101	102	java/lang/Exception
    //   5	21	105	java/lang/Exception
  }
  
  /* Error */
  public void onCreate(@Nullable Bundle paramBundle)
  {
    // Byte code:
    //   0: invokestatic 42	com/mobile/ui/enrollment/fragment/EnrollmentBypassFragment:b0449щщщщ04490449щ	()I
    //   3: istore_2
    //   4: invokestatic 58	com/mobile/ui/enrollment/fragment/EnrollmentBypassFragment:bщ0449щщщ04490449щ	()I
    //   7: istore_3
    //   8: invokestatic 42	com/mobile/ui/enrollment/fragment/EnrollmentBypassFragment:b0449щщщщ04490449щ	()I
    //   11: istore 4
    //   13: invokestatic 110	com/mobile/ui/enrollment/fragment/EnrollmentBypassFragment:bщщ0449щщ04490449щ	()I
    //   16: istore 5
    //   18: getstatic 44	com/mobile/ui/enrollment/fragment/EnrollmentBypassFragment:b04490449щщщ04490449щ	I
    //   21: istore 6
    //   23: iload_2
    //   24: iload_3
    //   25: iadd
    //   26: iload 4
    //   28: imul
    //   29: iload 5
    //   31: irem
    //   32: iload 6
    //   34: if_icmpeq +45 -> 79
    //   37: invokestatic 42	com/mobile/ui/enrollment/fragment/EnrollmentBypassFragment:b0449щщщщ04490449щ	()I
    //   40: putstatic 34	com/mobile/ui/enrollment/fragment/EnrollmentBypassFragment:bщ0449044904490449щ0449щ	I
    //   43: getstatic 34	com/mobile/ui/enrollment/fragment/EnrollmentBypassFragment:bщ0449044904490449щ0449щ	I
    //   46: getstatic 36	com/mobile/ui/enrollment/fragment/EnrollmentBypassFragment:b04490449044904490449щ0449щ	I
    //   49: iadd
    //   50: getstatic 34	com/mobile/ui/enrollment/fragment/EnrollmentBypassFragment:bщ0449044904490449щ0449щ	I
    //   53: imul
    //   54: getstatic 38	com/mobile/ui/enrollment/fragment/EnrollmentBypassFragment:bщщщщщ04490449щ	I
    //   57: irem
    //   58: getstatic 44	com/mobile/ui/enrollment/fragment/EnrollmentBypassFragment:b04490449щщщ04490449щ	I
    //   61: if_icmpeq +13 -> 74
    //   64: bipush 6
    //   66: putstatic 34	com/mobile/ui/enrollment/fragment/EnrollmentBypassFragment:bщ0449044904490449щ0449щ	I
    //   69: bipush 72
    //   71: putstatic 44	com/mobile/ui/enrollment/fragment/EnrollmentBypassFragment:b04490449щщщ04490449щ	I
    //   74: bipush 55
    //   76: putstatic 44	com/mobile/ui/enrollment/fragment/EnrollmentBypassFragment:b04490449щщщ04490449щ	I
    //   79: aload_0
    //   80: aload_1
    //   81: invokespecial 112	com/mobile/ui/common/fragment/BaseRequestFragment:onCreate	(Landroid/os/Bundle;)V
    //   84: invokestatic 118	com/mobile/ui/App:get	()Lcom/mobile/ui/App;
    //   87: invokevirtual 122	com/mobile/ui/App:getAppComponent	()Lkkkkkk/uyyyyy;
    //   90: astore_1
    //   91: aload_1
    //   92: aload_0
    //   93: invokeinterface 128 2 0
    //   98: return
    //   99: astore_1
    //   100: aload_1
    //   101: athrow
    //   102: astore_1
    //   103: aload_1
    //   104: athrow
    //   105: astore_1
    //   106: aload_1
    //   107: athrow
    //   108: astore_1
    //   109: aload_1
    //   110: athrow
    // Local variable table:
    //   start	length	slot	name	signature
    //   0	111	0	this	EnrollmentBypassFragment
    //   0	111	1	paramBundle	Bundle
    //   3	23	2	i	int
    //   7	19	3	j	int
    //   11	18	4	k	int
    //   16	16	5	m	int
    //   21	14	6	n	int
    // Exception table:
    //   from	to	target	type
    //   79	91	99	java/lang/Exception
    //   37	43	102	java/lang/Exception
    //   100	102	102	java/lang/Exception
    //   106	108	102	java/lang/Exception
    //   91	98	105	java/lang/Exception
    //   0	23	108	java/lang/Exception
    //   74	79	108	java/lang/Exception
  }
  
  public View onCreateView(LayoutInflater paramLayoutInflater, @Nullable ViewGroup paramViewGroup, @Nullable Bundle paramBundle)
  {
    int i = bщ0449044904490449щ0449щ;
    switch (i * (b04490449044904490449щ0449щ + i) % bщщщщщ04490449щ)
    {
    default: 
      i = b0449щщщщ04490449щ();
      switch (1)
      {
      case 0: 
      default: 
        for (;;)
        {
          switch (1)
          {
          }
        }
      }
      bщ0449044904490449щ0449щ = i;
      b04490449щщщ04490449щ = b0449щщщщ04490449щ();
    }
    try
    {
      i = R.layout.fragment_enrollment_bypass;
      if ((bщ0449044904490449щ0449щ + b04490449044904490449щ0449щ) * bщ0449044904490449щ0449щ % bщщщщщ04490449щ != b04490449щщщ04490449щ)
      {
        bщ0449044904490449щ0449щ = 43;
        b04490449щщщ04490449щ = 99;
      }
      paramLayoutInflater = paramLayoutInflater.inflate(i, paramViewGroup, false);
      return paramLayoutInflater;
    }
    catch (Exception paramLayoutInflater)
    {
      throw paramLayoutInflater;
    }
  }
  
  public void showCongratulationsScreen()
  {
    int i = 4;
    for (;;)
    {
      int j = b0449щщщщ04490449щ();
      switch (j * (b04490449044904490449щ0449щ + j) % bщщщщщ04490449щ)
      {
      default: 
        bщ0449044904490449щ0449щ = 22;
        b04490449щщщ04490449щ = b0449щщщщ04490449щ();
      }
      try
      {
        i /= 0;
      }
      catch (Exception localException)
      {
        bщ0449044904490449щ0449щ = 10;
        switch (1)
        {
        case 0: 
        default: 
          for (;;)
          {
            switch (0)
            {
            }
          }
        }
        ((qiiiii)getActivity()).showCongratulationsScreen(EnrollmentActivity.kkttkk.DEFAULT);
      }
    }
  }
  
  public void trackScreenView()
  {
    Object localObject = this.mPresenter;
    int i = bщ0449044904490449щ0449щ;
    switch (i * (b04490449044904490449щ0449щ + i) % bщщ0449щщ04490449щ())
    {
    default: 
      bщ0449044904490449щ0449щ = b0449щщщщ04490449щ();
      b04490449щщщ04490449щ = b0449щщщщ04490449щ();
    }
    localObject = (ktkttk)localObject;
    i = bщ0449044904490449щ0449щ;
    switch (i * (b04490449044904490449щ0449щ + i) % bщщщщщ04490449щ)
    {
    default: 
      bщ0449044904490449щ0449щ = 95;
      b04490449щщщ04490449щ = b0449щщщщ04490449щ();
    }
    switch (0)
    {
    case 1: 
    default: 
      for (;;)
      {
        switch (0)
        {
        case 1: 
        default: 
          for (;;)
          {
            switch (1)
            {
            }
          }
        }
        switch (1)
        {
        }
      }
    }
    ((ktkttk)localObject).bА04100410ААААА0410А();
  }
}
