package ro.btrl.boot.ui.activity;

import android.content.Context;
import android.content.Intent;
import android.content.pm.PackageManager;
import android.content.res.Resources;
import o.Cv;
import o.Dw;
import o.ES;
import o.EX;
import o.En;
import o.Fc;
import o.Fg;
import o.Gn;
import o.Gv;
import o.IB;
import o.Ik;
import o.ca;
import o.oH;
import o.sH;
import o.sW;

public class SplashScreenActivity
  extends IB<Dw>
{
  private static long ʼॱ = 6484231617605893714L;
  private static int ʾ = 0;
  private static char[] ʿ = { 55, 32324, -863, 31468, -1704, 30604, -19365, -13784, 18637, -12672, 19764, -15392, 16851, -16312, 18172, -15139, 23362, -9737, 24484, -8614, 23566, -11615, 20830, -10471, 21938, -11157, 27163, -5952, 28477, -4753, 25473, 68, 32311, -814, 31391, -1749, 30719, -2612, 29783, -3357, 28866, -4282, 28137, -5193, 27230, -6119, 26282, -6898, 25436, -7702, 24630, -8694, 23766, -9363, 22845, -10277, 22126, -11203, 21205, -12148, 20259, -12814, 19337, -13728, 18678, -14719, 17728, -15391, 16825, -16311, 15966, -17231, 15180, -18160, 14310, -18820, 13327, -19760, 12651, -20716, 11739, -21398, 10801, -22392, 9881, -23251, 9196, -24172, 8290, -24848, 7300, -25834, 6564, -26638, 12377, 19975, -13069, 19170, -14061, 18382, -14926, 17526, -15675, 16561, -8342, 23954, -9324, 23157, -10200, 22160, -10893, 21286, -11879, 21761, 11096, -22109, 12279, -21439, 8889, -24322, 8492, -22597, 9710, -17857, 14480, -16685, 16169, -17038, 13253, -20424, 13937, -19246, 13597, -29851, 2486, -29106, 3078, -32014, -31619, -1500, 30943, -373, 32061, -3131, 29058, -4016, 30407, -2926, 27459, -5652, 28591, -4523, 27662, -7495, 24900, -6387, 26030, -7071, 23065, -10038, -25590, -7599, 24744, -6416, 25926, -5219, 27097, -6083, 28318, -4884, 29491, -3696, 30707, -2522, 29815, -1320, 31019, -143, 32202, -995, 17008, -16199, 18202, -15019, 19389, -13810, 18454, -12546, 19642, 44, 32370, -11463, -21150, 12187, -22077, 10869, -23378, 9962, -22770, 8621, -23585, 15360, -16733, 14528, -18155, 15172, -18965, 13848, -20414, 13049, -19666, 3395, -28790, 2089, -30106, 1166, -31427, 1829, -32307, 905, -25480, 7845, -26406, 6514, -25688, 5627, -27134, 4269, -27908, 4882, -4771, 28650, -6096, 27210, -6919, 25895, -6306, 24974, -7637, 31832, -372, 32571, 70, 32315, -810, 31379, -1750, 30715, -2657, 29787, -3408, 28843, -4240, 28092, -5128, 70, 32315, -810, 31379, -1750, 30715, -2657, 29787, -3408, 28854, -4261, 28141, -5187, 27204, -6074, 26350, 3059, 30083, -2206, 28935, -3442, 31838, -474, 32750, -1721, 31524, -6939, 26226, -8166, 25061, -7245, 27912, -4361, -13670, -19222, 13835, -20370, 13287, -17097, 16207, -16761, 14382, -17843, 9612, -22676, 8570, -24447, 8901, -21468, 12172, -22055, 11111, -21840, 5319, -27116, 4582, -27719, 7514, -25426, 7927, -26594, 6743, -31262, 1847, -32425, 239, -32136, 3162, -28781, 2345, -29835, 2696, -2924, 30323, -3685, 29598, -670, 31911, -308, 30746, -1052, 26053, -6390, 26350, -7943, 25103, -5056, 28658, -5843 };
  private static int ˈ = 1;
  private sH ʽॱ;
  
  public SplashScreenActivity() {}
  
  private void ʾ()
  {
    break label243;
    int i = 84;
    break label195;
    ca localCa;
    int j;
    localCa.ˊ(this, j, 53);
    return;
    for (;;)
    {
      i = 37;
      break label145;
      for (;;)
      {
        try
        {
          i = ˈ;
          i += 77;
          ʾ = i % 128;
          if (i % 2 != 0) {
            break label227;
          }
        }
        catch (Exception localException)
        {
          throw localException;
        }
        switch (i)
        {
        }
      }
      label83:
      i = 11 / 0;
      return;
      i = ʾ + 39;
      ˈ = i % 128;
      if (i % 2 == 0) {
        break label136;
      }
    }
    label136:
    label145:
    label189:
    label195:
    label227:
    label233:
    label243:
    for (;;)
    {
      localCa = ca.ˊ();
      j = localCa.ˏ(this);
      if (j == 0)
      {
        break label189;
        i = 92;
      }
      switch (i)
      {
      case 92: 
      default: 
        break label83;
        i = 57;
        break;
        ˊᐝ();
        break;
      case 37: 
        return;
      }
      i = 29;
      break;
      for (;;)
      {
        switch (i)
        {
        case 49: 
        default: 
          break label233;
          i = 49;
        }
      }
      localException.ˊ(this, j, 26);
      return;
    }
  }
  
  /* Error */
  private void ˉ()
  {
    // Byte code:
    //   0: goto +43 -> 43
    //   3: aload_0
    //   4: invokestatic 402	o/Ic:ˏ	(Landroid/content/Context;)Lo/Ic;
    //   7: iconst_0
    //   8: iconst_0
    //   9: invokevirtual 405	o/Ic:ˏ	(ZZ)Lo/j;
    //   12: invokevirtual 410	o/j:ˎ	()V
    //   15: goto +92 -> 107
    //   18: astore_3
    //   19: aload_3
    //   20: athrow
    //   21: iconst_1
    //   22: istore_1
    //   23: goto +28 -> 51
    //   26: aload_0
    //   27: invokespecial 413	ro/btrl/boot/ui/activity/SplashScreenActivity:ˊˊ	()V
    //   30: aconst_null
    //   31: arraylength
    //   32: istore_1
    //   33: goto +74 -> 107
    //   36: aload_0
    //   37: invokespecial 413	ro/btrl/boot/ui/activity/SplashScreenActivity:ˊˊ	()V
    //   40: goto +67 -> 107
    //   43: goto +67 -> 110
    //   46: iconst_1
    //   47: istore_1
    //   48: goto +289 -> 337
    //   51: iload_1
    //   52: tableswitch	default:+24->76, 0:+-26->26, 1:+-16->36
    //   76: goto -50 -> 26
    //   79: iconst_0
    //   80: istore_1
    //   81: goto +256 -> 337
    //   84: getstatic 32	ro/btrl/boot/ui/activity/SplashScreenActivity:ʾ	I
    //   87: bipush 41
    //   89: iadd
    //   90: istore_1
    //   91: iload_1
    //   92: sipush 128
    //   95: irem
    //   96: putstatic 34	ro/btrl/boot/ui/activity/SplashScreenActivity:ˈ	I
    //   99: iload_1
    //   100: iconst_2
    //   101: irem
    //   102: ifne +4 -> 106
    //   105: return
    //   106: return
    //   107: goto -23 -> 84
    //   110: goto +20 -> 130
    //   113: astore_3
    //   114: aload_3
    //   115: invokevirtual 419	java/lang/Throwable:getCause	()Ljava/lang/Throwable;
    //   118: astore 4
    //   120: aload 4
    //   122: ifnull +6 -> 128
    //   125: aload 4
    //   127: athrow
    //   128: aload_3
    //   129: athrow
    //   130: aload_0
    //   131: invokevirtual 425	android/content/Context:getPackageName	()Ljava/lang/String;
    //   134: invokevirtual 431	java/lang/String:length	()I
    //   137: bipush 8
    //   139: isub
    //   140: aload_0
    //   141: invokevirtual 435	android/content/Context:getResources	()Landroid/content/res/Resources;
    //   144: ldc_w 436
    //   147: invokevirtual 442	android/content/res/Resources:getString	(I)Ljava/lang/String;
    //   150: iconst_0
    //   151: bipush 10
    //   153: invokevirtual 446	java/lang/String:substring	(II)Ljava/lang/String;
    //   156: invokevirtual 431	java/lang/String:length	()I
    //   159: bipush 14
    //   161: iadd
    //   162: aload_0
    //   163: invokevirtual 425	android/content/Context:getPackageName	()Ljava/lang/String;
    //   166: bipush 6
    //   168: invokevirtual 450	java/lang/String:codePointAt	(I)I
    //   171: bipush 108
    //   173: isub
    //   174: i2c
    //   175: invokestatic 456	o/O:ˋ	(IIC)Ljava/lang/Object;
    //   178: checkcast 458	java/lang/Class
    //   181: ldc_w 459
    //   184: aconst_null
    //   185: invokevirtual 463	java/lang/Class:getMethod	(Ljava/lang/String;[Ljava/lang/Class;)Ljava/lang/reflect/Method;
    //   188: aconst_null
    //   189: aconst_null
    //   190: invokevirtual 469	java/lang/reflect/Method:invoke	(Ljava/lang/Object;[Ljava/lang/Object;)Ljava/lang/Object;
    //   193: astore_3
    //   194: aload_0
    //   195: invokevirtual 473	ro/btrl/boot/ui/activity/SplashScreenActivity:ॱˊ	()Landroid/content/Context;
    //   198: astore 4
    //   200: goto +20 -> 220
    //   203: astore_3
    //   204: aload_3
    //   205: invokevirtual 419	java/lang/Throwable:getCause	()Ljava/lang/Throwable;
    //   208: astore 4
    //   210: aload 4
    //   212: ifnull +6 -> 218
    //   215: aload 4
    //   217: athrow
    //   218: aload_3
    //   219: athrow
    //   220: aload_0
    //   221: invokevirtual 435	android/content/Context:getResources	()Landroid/content/res/Resources;
    //   224: ldc_w 474
    //   227: invokevirtual 442	android/content/res/Resources:getString	(I)Ljava/lang/String;
    //   230: iconst_0
    //   231: iconst_4
    //   232: invokevirtual 446	java/lang/String:substring	(II)Ljava/lang/String;
    //   235: invokevirtual 431	java/lang/String:length	()I
    //   238: iconst_1
    //   239: isub
    //   240: aload_0
    //   241: invokevirtual 435	android/content/Context:getResources	()Landroid/content/res/Resources;
    //   244: ldc_w 475
    //   247: invokevirtual 442	android/content/res/Resources:getString	(I)Ljava/lang/String;
    //   250: iconst_0
    //   251: bipush 6
    //   253: invokevirtual 446	java/lang/String:substring	(II)Ljava/lang/String;
    //   256: invokevirtual 431	java/lang/String:length	()I
    //   259: bipush 18
    //   261: iadd
    //   262: aload_0
    //   263: invokevirtual 435	android/content/Context:getResources	()Landroid/content/res/Resources;
    //   266: ldc_w 476
    //   269: invokevirtual 442	android/content/res/Resources:getString	(I)Ljava/lang/String;
    //   272: iconst_0
    //   273: iconst_5
    //   274: invokevirtual 446	java/lang/String:substring	(II)Ljava/lang/String;
    //   277: iconst_1
    //   278: invokevirtual 450	java/lang/String:codePointAt	(I)I
    //   281: bipush 26
    //   283: isub
    //   284: i2c
    //   285: invokestatic 456	o/O:ˋ	(IIC)Ljava/lang/Object;
    //   288: checkcast 458	java/lang/Class
    //   291: ldc_w 459
    //   294: iconst_1
    //   295: anewarray 458	java/lang/Class
    //   298: dup
    //   299: iconst_0
    //   300: ldc_w 421
    //   303: aastore
    //   304: invokevirtual 463	java/lang/Class:getMethod	(Ljava/lang/String;[Ljava/lang/Class;)Ljava/lang/reflect/Method;
    //   307: aload_3
    //   308: iconst_1
    //   309: anewarray 478	java/lang/Object
    //   312: dup
    //   313: iconst_0
    //   314: aload 4
    //   316: aastore
    //   317: invokevirtual 469	java/lang/reflect/Method:invoke	(Ljava/lang/Object;[Ljava/lang/Object;)Ljava/lang/Object;
    //   320: checkcast 480	java/lang/Boolean
    //   323: invokevirtual 484	java/lang/Boolean:booleanValue	()Z
    //   326: istore_2
    //   327: iload_2
    //   328: ifeq +6 -> 334
    //   331: goto -285 -> 46
    //   334: goto -255 -> 79
    //   337: iload_1
    //   338: tableswitch	default:+22->360, 0:+-335->3, 1:+22->360
    //   360: getstatic 34	ro/btrl/boot/ui/activity/SplashScreenActivity:ˈ	I
    //   363: bipush 101
    //   365: iadd
    //   366: istore_1
    //   367: iload_1
    //   368: sipush 128
    //   371: irem
    //   372: putstatic 32	ro/btrl/boot/ui/activity/SplashScreenActivity:ʾ	I
    //   375: iload_1
    //   376: iconst_2
    //   377: irem
    //   378: ifeq +6 -> 384
    //   381: goto +6 -> 387
    //   384: goto -363 -> 21
    //   387: iconst_0
    //   388: istore_1
    //   389: goto -338 -> 51
    // Local variable table:
    //   start	length	slot	name	signature
    //   0	392	0	this	SplashScreenActivity
    //   22	367	1	i	int
    //   326	2	2	bool	boolean
    //   18	2	3	localException	Exception
    //   113	16	3	localObject1	Object
    //   193	1	3	localObject2	Object
    //   203	105	3	localObject3	Object
    //   118	197	4	localObject4	Object
    // Exception table:
    //   from	to	target	type
    //   114	120	18	java/lang/Exception
    //   125	128	18	java/lang/Exception
    //   128	130	18	java/lang/Exception
    //   194	200	18	java/lang/Exception
    //   204	210	18	java/lang/Exception
    //   215	218	18	java/lang/Exception
    //   218	220	18	java/lang/Exception
    //   130	194	113	finally
    //   220	327	203	finally
  }
  
  private static String ˊ(int paramInt1, char paramChar, int paramInt2)
  {
    break label171;
    int j;
    int i;
    label60:
    char[] arrayOfChar2;
    for (;;)
    {
      j = ʾ + 79;
      ˈ = j % 128;
      if (j % 2 == 0) {
        break label114;
      }
      break;
      i = ʾ + 53;
      ˈ = i % 128;
      if (i % 2 != 0) {
        break label128;
      }
      try
      {
        char[] arrayOfChar1 = ʿ;
        long l1 = arrayOfChar1[(paramInt1 + i)];
        long l2 = i;
        arrayOfChar2[i] = ((char)(int)(l1 ^ l2 * ʼॱ ^ paramChar));
        i += 1;
      }
      catch (Exception localException)
      {
        throw localException;
      }
    }
    break label128;
    label114:
    for (;;)
    {
      break;
    }
    while (i >= paramInt2)
    {
      break label191;
      label128:
      arrayOfChar2 = new char[paramInt2];
      i = 0;
    }
    for (;;)
    {
      switch (j)
      {
      case 92: 
      default: 
        break label60;
        break;
      case 61: 
        label171:
        return new String(arrayOfChar2);
        j = 92;
        continue;
        label191:
        j = 61;
      }
    }
  }
  
  /* Error */
  private void ˊˊ()
  {
    // Byte code:
    //   0: goto +140 -> 140
    //   3: goto +17 -> 20
    //   6: astore_2
    //   7: aload_2
    //   8: invokevirtual 419	java/lang/Throwable:getCause	()Ljava/lang/Throwable;
    //   11: astore_3
    //   12: aload_3
    //   13: ifnull +5 -> 18
    //   16: aload_3
    //   17: athrow
    //   18: aload_2
    //   19: athrow
    //   20: aload_0
    //   21: invokevirtual 435	android/content/Context:getResources	()Landroid/content/res/Resources;
    //   24: ldc_w 489
    //   27: invokevirtual 442	android/content/res/Resources:getString	(I)Ljava/lang/String;
    //   30: iconst_0
    //   31: iconst_4
    //   32: invokevirtual 446	java/lang/String:substring	(II)Ljava/lang/String;
    //   35: iconst_2
    //   36: invokevirtual 450	java/lang/String:codePointAt	(I)I
    //   39: bipush 7
    //   41: isub
    //   42: aload_0
    //   43: invokevirtual 425	android/content/Context:getPackageName	()Ljava/lang/String;
    //   46: invokevirtual 431	java/lang/String:length	()I
    //   49: bipush 124
    //   51: iadd
    //   52: aload_0
    //   53: invokevirtual 435	android/content/Context:getResources	()Landroid/content/res/Resources;
    //   56: ldc_w 490
    //   59: invokevirtual 442	android/content/res/Resources:getString	(I)Ljava/lang/String;
    //   62: bipush 6
    //   64: bipush 18
    //   66: invokevirtual 446	java/lang/String:substring	(II)Ljava/lang/String;
    //   69: iconst_1
    //   70: invokevirtual 450	java/lang/String:codePointAt	(I)I
    //   73: ldc_w 491
    //   76: iadd
    //   77: i2c
    //   78: invokestatic 456	o/O:ˋ	(IIC)Ljava/lang/Object;
    //   81: checkcast 458	java/lang/Class
    //   84: ldc_w 492
    //   87: aconst_null
    //   88: invokevirtual 463	java/lang/Class:getMethod	(Ljava/lang/String;[Ljava/lang/Class;)Ljava/lang/reflect/Method;
    //   91: aconst_null
    //   92: aconst_null
    //   93: invokevirtual 469	java/lang/reflect/Method:invoke	(Ljava/lang/Object;[Ljava/lang/Object;)Ljava/lang/Object;
    //   96: checkcast 494	o/It
    //   99: astore_2
    //   100: aload_2
    //   101: invokeinterface 498 1 0
    //   106: new 17	ro/btrl/boot/ui/activity/SplashScreenActivity$6
    //   109: dup
    //   110: aload_0
    //   111: aload_0
    //   112: invokespecial 501	ro/btrl/boot/ui/activity/SplashScreenActivity$6:<init>	(Lro/btrl/boot/ui/activity/SplashScreenActivity;Landroid/content/Context;)V
    //   115: invokeinterface 506 2 0
    //   120: goto +53 -> 173
    //   123: bipush 72
    //   125: istore_1
    //   126: goto +17 -> 143
    //   129: aconst_null
    //   130: arraylength
    //   131: istore_1
    //   132: return
    //   133: bipush 30
    //   135: istore_1
    //   136: goto +7 -> 143
    //   139: return
    //   140: goto -137 -> 3
    //   143: iload_1
    //   144: lookupswitch	default:+28->172, 30:+-15->129, 72:+-5->139
    //   172: return
    //   173: getstatic 32	ro/btrl/boot/ui/activity/SplashScreenActivity:ʾ	I
    //   176: bipush 19
    //   178: iadd
    //   179: istore_1
    //   180: iload_1
    //   181: sipush 128
    //   184: irem
    //   185: putstatic 34	ro/btrl/boot/ui/activity/SplashScreenActivity:ˈ	I
    //   188: iload_1
    //   189: iconst_2
    //   190: irem
    //   191: ifne +6 -> 197
    //   194: goto -61 -> 133
    //   197: goto -74 -> 123
    // Local variable table:
    //   start	length	slot	name	signature
    //   0	200	0	this	SplashScreenActivity
    //   125	66	1	i	int
    //   6	13	2	localObject	Object
    //   99	2	2	localIt	o.It
    //   11	6	3	localThrowable	Throwable
    // Exception table:
    //   from	to	target	type
    //   20	100	6	finally
  }
  
  /* Error */
  private void ˊˋ()
  {
    // Byte code:
    //   0: goto +149 -> 149
    //   3: bipush 84
    //   5: istore_1
    //   6: goto +147 -> 153
    //   9: bipush 53
    //   11: istore_1
    //   12: goto +141 -> 153
    //   15: getstatic 34	ro/btrl/boot/ui/activity/SplashScreenActivity:ˈ	I
    //   18: bipush 99
    //   20: iadd
    //   21: istore_1
    //   22: iload_1
    //   23: sipush 128
    //   26: irem
    //   27: putstatic 32	ro/btrl/boot/ui/activity/SplashScreenActivity:ʾ	I
    //   30: iload_1
    //   31: iconst_2
    //   32: irem
    //   33: ifeq +6 -> 39
    //   36: goto -27 -> 9
    //   39: goto -36 -> 3
    //   42: goto +17 -> 59
    //   45: astore_2
    //   46: aload_2
    //   47: invokevirtual 419	java/lang/Throwable:getCause	()Ljava/lang/Throwable;
    //   50: astore_3
    //   51: aload_3
    //   52: ifnull +5 -> 57
    //   55: aload_3
    //   56: athrow
    //   57: aload_2
    //   58: athrow
    //   59: aload_0
    //   60: invokevirtual 425	android/content/Context:getPackageName	()Ljava/lang/String;
    //   63: iconst_1
    //   64: invokevirtual 450	java/lang/String:codePointAt	(I)I
    //   67: bipush 107
    //   69: isub
    //   70: aload_0
    //   71: invokevirtual 435	android/content/Context:getResources	()Landroid/content/res/Resources;
    //   74: ldc_w 508
    //   77: invokevirtual 442	android/content/res/Resources:getString	(I)Ljava/lang/String;
    //   80: iconst_0
    //   81: iconst_4
    //   82: invokevirtual 446	java/lang/String:substring	(II)Ljava/lang/String;
    //   85: invokevirtual 431	java/lang/String:length	()I
    //   88: sipush 131
    //   91: iadd
    //   92: aload_0
    //   93: invokevirtual 425	android/content/Context:getPackageName	()Ljava/lang/String;
    //   96: invokevirtual 431	java/lang/String:length	()I
    //   99: ldc_w 509
    //   102: iadd
    //   103: i2c
    //   104: invokestatic 456	o/O:ˋ	(IIC)Ljava/lang/Object;
    //   107: checkcast 458	java/lang/Class
    //   110: ldc_w 492
    //   113: aconst_null
    //   114: invokevirtual 463	java/lang/Class:getMethod	(Ljava/lang/String;[Ljava/lang/Class;)Ljava/lang/reflect/Method;
    //   117: aconst_null
    //   118: aconst_null
    //   119: invokevirtual 469	java/lang/reflect/Method:invoke	(Ljava/lang/Object;[Ljava/lang/Object;)Ljava/lang/Object;
    //   122: checkcast 494	o/It
    //   125: astore_2
    //   126: aload_2
    //   127: invokeinterface 511 1 0
    //   132: new 19	ro/btrl/boot/ui/activity/SplashScreenActivity$8
    //   135: dup
    //   136: aload_0
    //   137: aload_0
    //   138: invokespecial 512	ro/btrl/boot/ui/activity/SplashScreenActivity$8:<init>	(Lro/btrl/boot/ui/activity/SplashScreenActivity;Landroid/content/Context;)V
    //   141: invokeinterface 506 2 0
    //   146: goto -131 -> 15
    //   149: goto -107 -> 42
    //   152: return
    //   153: iload_1
    //   154: lookupswitch	default:+26->180, 53:+26->180, 84:+-2->152
    //   180: bipush 61
    //   182: iconst_0
    //   183: idiv
    //   184: istore_1
    //   185: return
    // Local variable table:
    //   start	length	slot	name	signature
    //   0	186	0	this	SplashScreenActivity
    //   5	180	1	i	int
    //   45	13	2	localObject	Object
    //   125	2	2	localIt	o.It
    //   50	6	3	localThrowable	Throwable
    // Exception table:
    //   from	to	target	type
    //   59	126	45	finally
  }
  
  /* Error */
  private void ˊᐝ()
  {
    // Byte code:
    //   0: goto +1423 -> 1423
    //   3: iconst_3
    //   4: iconst_5
    //   5: idiv
    //   6: istore_1
    //   7: goto +1368 -> 1375
    //   10: aload_0
    //   11: invokevirtual 425	android/content/Context:getPackageName	()Ljava/lang/String;
    //   14: invokevirtual 431	java/lang/String:length	()I
    //   17: bipush 11
    //   19: isub
    //   20: aload_0
    //   21: invokevirtual 516	android/content/Context:getApplicationInfo	()Landroid/content/pm/ApplicationInfo;
    //   24: getfield 521	android/content/pm/ApplicationInfo:targetSdkVersion	I
    //   27: bipush 90
    //   29: iadd
    //   30: i2c
    //   31: aload_0
    //   32: invokevirtual 425	android/content/Context:getPackageName	()Ljava/lang/String;
    //   35: invokevirtual 431	java/lang/String:length	()I
    //   38: iconst_5
    //   39: isub
    //   40: invokestatic 523	ro/btrl/boot/ui/activity/SplashScreenActivity:ˊ	(ICI)Ljava/lang/String;
    //   43: invokevirtual 526	java/lang/String:intern	()Ljava/lang/String;
    //   46: astore 4
    //   48: aload_0
    //   49: invokevirtual 516	android/content/Context:getApplicationInfo	()Landroid/content/pm/ApplicationInfo;
    //   52: getfield 521	android/content/pm/ApplicationInfo:targetSdkVersion	I
    //   55: bipush 113
    //   57: iadd
    //   58: aload_0
    //   59: invokevirtual 435	android/content/Context:getResources	()Landroid/content/res/Resources;
    //   62: ldc_w 527
    //   65: invokevirtual 442	android/content/res/Resources:getString	(I)Ljava/lang/String;
    //   68: iconst_0
    //   69: iconst_4
    //   70: invokevirtual 446	java/lang/String:substring	(II)Ljava/lang/String;
    //   73: invokevirtual 431	java/lang/String:length	()I
    //   76: ldc_w 528
    //   79: iadd
    //   80: i2c
    //   81: aload_0
    //   82: invokevirtual 435	android/content/Context:getResources	()Landroid/content/res/Resources;
    //   85: ldc_w 529
    //   88: invokevirtual 442	android/content/res/Resources:getString	(I)Ljava/lang/String;
    //   91: iconst_0
    //   92: iconst_5
    //   93: invokevirtual 446	java/lang/String:substring	(II)Ljava/lang/String;
    //   96: invokevirtual 431	java/lang/String:length	()I
    //   99: bipush 17
    //   101: iadd
    //   102: invokestatic 523	ro/btrl/boot/ui/activity/SplashScreenActivity:ˊ	(ICI)Ljava/lang/String;
    //   105: invokevirtual 526	java/lang/String:intern	()Ljava/lang/String;
    //   108: astore 5
    //   110: goto +20 -> 130
    //   113: astore_3
    //   114: aload_3
    //   115: invokevirtual 419	java/lang/Throwable:getCause	()Ljava/lang/Throwable;
    //   118: astore 4
    //   120: aload 4
    //   122: ifnull +6 -> 128
    //   125: aload 4
    //   127: athrow
    //   128: aload_3
    //   129: athrow
    //   130: aload_0
    //   131: invokevirtual 435	android/content/Context:getResources	()Landroid/content/res/Resources;
    //   134: ldc_w 530
    //   137: invokevirtual 442	android/content/res/Resources:getString	(I)Ljava/lang/String;
    //   140: iconst_0
    //   141: iconst_4
    //   142: invokevirtual 446	java/lang/String:substring	(II)Ljava/lang/String;
    //   145: invokevirtual 431	java/lang/String:length	()I
    //   148: iconst_0
    //   149: iadd
    //   150: aload_0
    //   151: invokevirtual 435	android/content/Context:getResources	()Landroid/content/res/Resources;
    //   154: ldc_w 531
    //   157: invokevirtual 442	android/content/res/Resources:getString	(I)Ljava/lang/String;
    //   160: iconst_0
    //   161: iconst_5
    //   162: invokevirtual 446	java/lang/String:substring	(II)Ljava/lang/String;
    //   165: invokevirtual 431	java/lang/String:length	()I
    //   168: bipush 37
    //   170: iadd
    //   171: aload_0
    //   172: invokevirtual 435	android/content/Context:getResources	()Landroid/content/res/Resources;
    //   175: ldc_w 532
    //   178: invokevirtual 442	android/content/res/Resources:getString	(I)Ljava/lang/String;
    //   181: iconst_0
    //   182: iconst_4
    //   183: invokevirtual 446	java/lang/String:substring	(II)Ljava/lang/String;
    //   186: iconst_0
    //   187: invokevirtual 450	java/lang/String:codePointAt	(I)I
    //   190: ldc_w 533
    //   193: iadd
    //   194: i2c
    //   195: invokestatic 456	o/O:ˋ	(IIC)Ljava/lang/Object;
    //   198: checkcast 458	java/lang/Class
    //   201: ldc_w 459
    //   204: iconst_2
    //   205: anewarray 458	java/lang/Class
    //   208: dup
    //   209: iconst_0
    //   210: ldc_w 427
    //   213: aastore
    //   214: dup
    //   215: iconst_1
    //   216: ldc_w 427
    //   219: aastore
    //   220: invokevirtual 463	java/lang/Class:getMethod	(Ljava/lang/String;[Ljava/lang/Class;)Ljava/lang/reflect/Method;
    //   223: aconst_null
    //   224: iconst_2
    //   225: anewarray 478	java/lang/Object
    //   228: dup
    //   229: iconst_0
    //   230: aload 4
    //   232: aastore
    //   233: dup
    //   234: iconst_1
    //   235: aload 5
    //   237: aastore
    //   238: invokevirtual 469	java/lang/reflect/Method:invoke	(Ljava/lang/Object;[Ljava/lang/Object;)Ljava/lang/Object;
    //   241: pop
    //   242: aload_0
    //   243: aload_3
    //   244: invokespecial 536	ro/btrl/boot/ui/activity/SplashScreenActivity:ˏ	(Lo/Gw;)V
    //   247: goto +1133 -> 1380
    //   250: iload_1
    //   251: tableswitch	default:+21->272, 0:+1128->1379, 1:+-248->3
    //   272: goto +1107 -> 1379
    //   275: astore_3
    //   276: aload_3
    //   277: athrow
    //   278: bipush 28
    //   280: istore_1
    //   281: goto +1356 -> 1637
    //   284: aload_0
    //   285: invokevirtual 435	android/content/Context:getResources	()Landroid/content/res/Resources;
    //   288: ldc_w 537
    //   291: invokevirtual 442	android/content/res/Resources:getString	(I)Ljava/lang/String;
    //   294: iconst_0
    //   295: iconst_5
    //   296: invokevirtual 446	java/lang/String:substring	(II)Ljava/lang/String;
    //   299: iconst_1
    //   300: invokevirtual 450	java/lang/String:codePointAt	(I)I
    //   303: bipush 26
    //   305: isub
    //   306: aload_0
    //   307: invokevirtual 516	android/content/Context:getApplicationInfo	()Landroid/content/pm/ApplicationInfo;
    //   310: getfield 521	android/content/pm/ApplicationInfo:targetSdkVersion	I
    //   313: bipush 90
    //   315: iadd
    //   316: i2c
    //   317: aload_0
    //   318: invokevirtual 425	android/content/Context:getPackageName	()Ljava/lang/String;
    //   321: invokevirtual 431	java/lang/String:length	()I
    //   324: iconst_5
    //   325: isub
    //   326: invokestatic 523	ro/btrl/boot/ui/activity/SplashScreenActivity:ˊ	(ICI)Ljava/lang/String;
    //   329: invokevirtual 526	java/lang/String:intern	()Ljava/lang/String;
    //   332: astore_3
    //   333: new 539	java/lang/StringBuilder
    //   336: dup
    //   337: invokespecial 540	java/lang/StringBuilder:<init>	()V
    //   340: aload_0
    //   341: invokevirtual 516	android/content/Context:getApplicationInfo	()Landroid/content/pm/ApplicationInfo;
    //   344: getfield 521	android/content/pm/ApplicationInfo:targetSdkVersion	I
    //   347: bipush 88
    //   349: iadd
    //   350: aload_0
    //   351: invokevirtual 425	android/content/Context:getPackageName	()Ljava/lang/String;
    //   354: iconst_0
    //   355: invokevirtual 450	java/lang/String:codePointAt	(I)I
    //   358: sipush 21744
    //   361: iadd
    //   362: i2c
    //   363: aload_0
    //   364: invokevirtual 435	android/content/Context:getResources	()Landroid/content/res/Resources;
    //   367: ldc_w 541
    //   370: invokevirtual 442	android/content/res/Resources:getString	(I)Ljava/lang/String;
    //   373: iconst_0
    //   374: iconst_4
    //   375: invokevirtual 446	java/lang/String:substring	(II)Ljava/lang/String;
    //   378: invokevirtual 431	java/lang/String:length	()I
    //   381: bipush 21
    //   383: iadd
    //   384: invokestatic 523	ro/btrl/boot/ui/activity/SplashScreenActivity:ˊ	(ICI)Ljava/lang/String;
    //   387: invokevirtual 526	java/lang/String:intern	()Ljava/lang/String;
    //   390: invokevirtual 545	java/lang/StringBuilder:append	(Ljava/lang/String;)Ljava/lang/StringBuilder;
    //   393: getstatic 551	o/Gw:INACTIVE_PHONE_NUMBER	Lo/Gw;
    //   396: invokevirtual 554	java/lang/StringBuilder:append	(Ljava/lang/Object;)Ljava/lang/StringBuilder;
    //   399: invokevirtual 557	java/lang/StringBuilder:toString	()Ljava/lang/String;
    //   402: astore 4
    //   404: goto +20 -> 424
    //   407: astore_3
    //   408: aload_3
    //   409: invokevirtual 419	java/lang/Throwable:getCause	()Ljava/lang/Throwable;
    //   412: astore 4
    //   414: aload 4
    //   416: ifnull +6 -> 422
    //   419: aload 4
    //   421: athrow
    //   422: aload_3
    //   423: athrow
    //   424: aload_0
    //   425: invokevirtual 435	android/content/Context:getResources	()Landroid/content/res/Resources;
    //   428: ldc_w 558
    //   431: invokevirtual 442	android/content/res/Resources:getString	(I)Ljava/lang/String;
    //   434: iconst_0
    //   435: iconst_4
    //   436: invokevirtual 446	java/lang/String:substring	(II)Ljava/lang/String;
    //   439: iconst_1
    //   440: invokevirtual 450	java/lang/String:codePointAt	(I)I
    //   443: bipush 22
    //   445: isub
    //   446: aload_0
    //   447: invokevirtual 435	android/content/Context:getResources	()Landroid/content/res/Resources;
    //   450: ldc_w 559
    //   453: invokevirtual 442	android/content/res/Resources:getString	(I)Ljava/lang/String;
    //   456: iconst_0
    //   457: iconst_4
    //   458: invokevirtual 446	java/lang/String:substring	(II)Ljava/lang/String;
    //   461: invokevirtual 431	java/lang/String:length	()I
    //   464: bipush 38
    //   466: iadd
    //   467: aload_0
    //   468: invokevirtual 435	android/content/Context:getResources	()Landroid/content/res/Resources;
    //   471: ldc_w 560
    //   474: invokevirtual 442	android/content/res/Resources:getString	(I)Ljava/lang/String;
    //   477: iconst_0
    //   478: bipush 23
    //   480: invokevirtual 446	java/lang/String:substring	(II)Ljava/lang/String;
    //   483: bipush 16
    //   485: invokevirtual 450	java/lang/String:codePointAt	(I)I
    //   488: ldc_w 561
    //   491: iadd
    //   492: i2c
    //   493: invokestatic 456	o/O:ˋ	(IIC)Ljava/lang/Object;
    //   496: checkcast 458	java/lang/Class
    //   499: ldc_w 459
    //   502: iconst_2
    //   503: anewarray 458	java/lang/Class
    //   506: dup
    //   507: iconst_0
    //   508: ldc_w 427
    //   511: aastore
    //   512: dup
    //   513: iconst_1
    //   514: ldc_w 427
    //   517: aastore
    //   518: invokevirtual 463	java/lang/Class:getMethod	(Ljava/lang/String;[Ljava/lang/Class;)Ljava/lang/reflect/Method;
    //   521: aconst_null
    //   522: iconst_2
    //   523: anewarray 478	java/lang/Object
    //   526: dup
    //   527: iconst_0
    //   528: aload_3
    //   529: aastore
    //   530: dup
    //   531: iconst_1
    //   532: aload 4
    //   534: aastore
    //   535: invokevirtual 469	java/lang/reflect/Method:invoke	(Ljava/lang/Object;[Ljava/lang/Object;)Ljava/lang/Object;
    //   538: pop
    //   539: goto +20 -> 559
    //   542: astore_3
    //   543: aload_3
    //   544: invokevirtual 419	java/lang/Throwable:getCause	()Ljava/lang/Throwable;
    //   547: astore 4
    //   549: aload 4
    //   551: ifnull +6 -> 557
    //   554: aload 4
    //   556: athrow
    //   557: aload_3
    //   558: athrow
    //   559: aload_0
    //   560: invokevirtual 435	android/content/Context:getResources	()Landroid/content/res/Resources;
    //   563: ldc_w 562
    //   566: invokevirtual 442	android/content/res/Resources:getString	(I)Ljava/lang/String;
    //   569: iconst_0
    //   570: iconst_5
    //   571: invokevirtual 446	java/lang/String:substring	(II)Ljava/lang/String;
    //   574: invokevirtual 431	java/lang/String:length	()I
    //   577: iconst_1
    //   578: isub
    //   579: aload_0
    //   580: invokevirtual 425	android/content/Context:getPackageName	()Ljava/lang/String;
    //   583: invokevirtual 431	java/lang/String:length	()I
    //   586: bipush 124
    //   588: iadd
    //   589: aload_0
    //   590: invokevirtual 435	android/content/Context:getResources	()Landroid/content/res/Resources;
    //   593: ldc_w 563
    //   596: invokevirtual 442	android/content/res/Resources:getString	(I)Ljava/lang/String;
    //   599: iconst_0
    //   600: iconst_1
    //   601: invokevirtual 446	java/lang/String:substring	(II)Ljava/lang/String;
    //   604: iconst_0
    //   605: invokevirtual 450	java/lang/String:codePointAt	(I)I
    //   608: ldc_w 564
    //   611: iadd
    //   612: i2c
    //   613: invokestatic 456	o/O:ˋ	(IIC)Ljava/lang/Object;
    //   616: checkcast 458	java/lang/Class
    //   619: ldc_w 492
    //   622: aconst_null
    //   623: invokevirtual 463	java/lang/Class:getMethod	(Ljava/lang/String;[Ljava/lang/Class;)Ljava/lang/reflect/Method;
    //   626: aconst_null
    //   627: aconst_null
    //   628: invokevirtual 469	java/lang/reflect/Method:invoke	(Ljava/lang/Object;[Ljava/lang/Object;)Ljava/lang/Object;
    //   631: checkcast 494	o/It
    //   634: astore_3
    //   635: aload_3
    //   636: invokeinterface 567 1 0
    //   641: new 7	ro/btrl/boot/ui/activity/SplashScreenActivity$1
    //   644: dup
    //   645: aload_0
    //   646: aload_0
    //   647: invokespecial 568	ro/btrl/boot/ui/activity/SplashScreenActivity$1:<init>	(Lro/btrl/boot/ui/activity/SplashScreenActivity;Landroid/content/Context;)V
    //   650: invokeinterface 506 2 0
    //   655: goto +720 -> 1375
    //   658: astore_3
    //   659: aload_3
    //   660: athrow
    //   661: goto +20 -> 681
    //   664: astore_3
    //   665: aload_3
    //   666: invokevirtual 419	java/lang/Throwable:getCause	()Ljava/lang/Throwable;
    //   669: astore 4
    //   671: aload 4
    //   673: ifnull +6 -> 679
    //   676: aload 4
    //   678: athrow
    //   679: aload_3
    //   680: athrow
    //   681: aload_0
    //   682: invokevirtual 425	android/content/Context:getPackageName	()Ljava/lang/String;
    //   685: bipush 6
    //   687: invokevirtual 450	java/lang/String:codePointAt	(I)I
    //   690: bipush 104
    //   692: isub
    //   693: aload_0
    //   694: invokevirtual 425	android/content/Context:getPackageName	()Ljava/lang/String;
    //   697: bipush 8
    //   699: invokevirtual 450	java/lang/String:codePointAt	(I)I
    //   702: sipush 301
    //   705: iadd
    //   706: aload_0
    //   707: invokevirtual 435	android/content/Context:getResources	()Landroid/content/res/Resources;
    //   710: ldc_w 569
    //   713: invokevirtual 442	android/content/res/Resources:getString	(I)Ljava/lang/String;
    //   716: iconst_0
    //   717: bipush 9
    //   719: invokevirtual 446	java/lang/String:substring	(II)Ljava/lang/String;
    //   722: bipush 6
    //   724: invokevirtual 450	java/lang/String:codePointAt	(I)I
    //   727: sipush 30002
    //   730: iadd
    //   731: i2c
    //   732: invokestatic 456	o/O:ˋ	(IIC)Ljava/lang/Object;
    //   735: checkcast 458	java/lang/Class
    //   738: ldc_w 570
    //   741: aconst_null
    //   742: invokevirtual 463	java/lang/Class:getMethod	(Ljava/lang/String;[Ljava/lang/Class;)Ljava/lang/reflect/Method;
    //   745: aconst_null
    //   746: aconst_null
    //   747: invokevirtual 469	java/lang/reflect/Method:invoke	(Ljava/lang/Object;[Ljava/lang/Object;)Ljava/lang/Object;
    //   750: astore_3
    //   751: getstatic 573	o/Gw:NOT_REGISTERED	Lo/Gw;
    //   754: astore 4
    //   756: goto +20 -> 776
    //   759: astore_3
    //   760: aload_3
    //   761: invokevirtual 419	java/lang/Throwable:getCause	()Ljava/lang/Throwable;
    //   764: astore 4
    //   766: aload 4
    //   768: ifnull +6 -> 774
    //   771: aload 4
    //   773: athrow
    //   774: aload_3
    //   775: athrow
    //   776: aload_0
    //   777: invokevirtual 435	android/content/Context:getResources	()Landroid/content/res/Resources;
    //   780: ldc_w 574
    //   783: invokevirtual 442	android/content/res/Resources:getString	(I)Ljava/lang/String;
    //   786: iconst_0
    //   787: iconst_4
    //   788: invokevirtual 446	java/lang/String:substring	(II)Ljava/lang/String;
    //   791: iconst_2
    //   792: invokevirtual 450	java/lang/String:codePointAt	(I)I
    //   795: bipush 7
    //   797: isub
    //   798: aload_0
    //   799: invokevirtual 435	android/content/Context:getResources	()Landroid/content/res/Resources;
    //   802: ldc_w 575
    //   805: invokevirtual 442	android/content/res/Resources:getString	(I)Ljava/lang/String;
    //   808: iconst_0
    //   809: iconst_4
    //   810: invokevirtual 446	java/lang/String:substring	(II)Ljava/lang/String;
    //   813: iconst_1
    //   814: invokevirtual 450	java/lang/String:codePointAt	(I)I
    //   817: sipush 387
    //   820: iadd
    //   821: aload_0
    //   822: invokevirtual 516	android/content/Context:getApplicationInfo	()Landroid/content/pm/ApplicationInfo;
    //   825: getfield 521	android/content/pm/ApplicationInfo:targetSdkVersion	I
    //   828: sipush 30228
    //   831: iadd
    //   832: i2c
    //   833: invokestatic 456	o/O:ˋ	(IIC)Ljava/lang/Object;
    //   836: checkcast 458	java/lang/Class
    //   839: ldc_w 576
    //   842: iconst_1
    //   843: anewarray 458	java/lang/Class
    //   846: dup
    //   847: iconst_0
    //   848: ldc_w 547
    //   851: aastore
    //   852: invokevirtual 463	java/lang/Class:getMethod	(Ljava/lang/String;[Ljava/lang/Class;)Ljava/lang/reflect/Method;
    //   855: aload_3
    //   856: iconst_1
    //   857: anewarray 478	java/lang/Object
    //   860: dup
    //   861: iconst_0
    //   862: aload 4
    //   864: aastore
    //   865: invokevirtual 469	java/lang/reflect/Method:invoke	(Ljava/lang/Object;[Ljava/lang/Object;)Ljava/lang/Object;
    //   868: pop
    //   869: aload_0
    //   870: getstatic 573	o/Gw:NOT_REGISTERED	Lo/Gw;
    //   873: invokespecial 536	ro/btrl/boot/ui/activity/SplashScreenActivity:ˏ	(Lo/Gw;)V
    //   876: aload_0
    //   877: invokevirtual 435	android/content/Context:getResources	()Landroid/content/res/Resources;
    //   880: ldc_w 577
    //   883: invokevirtual 442	android/content/res/Resources:getString	(I)Ljava/lang/String;
    //   886: iconst_0
    //   887: iconst_5
    //   888: invokevirtual 446	java/lang/String:substring	(II)Ljava/lang/String;
    //   891: invokevirtual 431	java/lang/String:length	()I
    //   894: iconst_5
    //   895: isub
    //   896: aload_0
    //   897: invokevirtual 425	android/content/Context:getPackageName	()Ljava/lang/String;
    //   900: iconst_4
    //   901: invokevirtual 450	java/lang/String:codePointAt	(I)I
    //   904: iconst_1
    //   905: isub
    //   906: i2c
    //   907: aload_0
    //   908: invokevirtual 435	android/content/Context:getResources	()Landroid/content/res/Resources;
    //   911: ldc_w 578
    //   914: invokevirtual 442	android/content/res/Resources:getString	(I)Ljava/lang/String;
    //   917: iconst_0
    //   918: iconst_4
    //   919: invokevirtual 446	java/lang/String:substring	(II)Ljava/lang/String;
    //   922: invokevirtual 431	java/lang/String:length	()I
    //   925: iconst_2
    //   926: iadd
    //   927: invokestatic 523	ro/btrl/boot/ui/activity/SplashScreenActivity:ˊ	(ICI)Ljava/lang/String;
    //   930: invokevirtual 526	java/lang/String:intern	()Ljava/lang/String;
    //   933: astore_3
    //   934: new 539	java/lang/StringBuilder
    //   937: dup
    //   938: invokespecial 540	java/lang/StringBuilder:<init>	()V
    //   941: aload_0
    //   942: invokevirtual 425	android/content/Context:getPackageName	()Ljava/lang/String;
    //   945: bipush 10
    //   947: invokevirtual 450	java/lang/String:codePointAt	(I)I
    //   950: bipush 8
    //   952: isub
    //   953: aload_0
    //   954: invokevirtual 516	android/content/Context:getApplicationInfo	()Landroid/content/pm/ApplicationInfo;
    //   957: getfield 521	android/content/pm/ApplicationInfo:targetSdkVersion	I
    //   960: sipush 21833
    //   963: iadd
    //   964: i2c
    //   965: aload_0
    //   966: invokevirtual 516	android/content/Context:getApplicationInfo	()Landroid/content/pm/ApplicationInfo;
    //   969: getfield 521	android/content/pm/ApplicationInfo:targetSdkVersion	I
    //   972: iconst_0
    //   973: iadd
    //   974: invokestatic 523	ro/btrl/boot/ui/activity/SplashScreenActivity:ˊ	(ICI)Ljava/lang/String;
    //   977: invokevirtual 526	java/lang/String:intern	()Ljava/lang/String;
    //   980: invokevirtual 545	java/lang/StringBuilder:append	(Ljava/lang/String;)Ljava/lang/StringBuilder;
    //   983: getstatic 573	o/Gw:NOT_REGISTERED	Lo/Gw;
    //   986: invokevirtual 554	java/lang/StringBuilder:append	(Ljava/lang/Object;)Ljava/lang/StringBuilder;
    //   989: invokevirtual 557	java/lang/StringBuilder:toString	()Ljava/lang/String;
    //   992: astore 4
    //   994: goto +20 -> 1014
    //   997: astore_3
    //   998: aload_3
    //   999: invokevirtual 419	java/lang/Throwable:getCause	()Ljava/lang/Throwable;
    //   1002: astore 4
    //   1004: aload 4
    //   1006: ifnull +6 -> 1012
    //   1009: aload 4
    //   1011: athrow
    //   1012: aload_3
    //   1013: athrow
    //   1014: aload_0
    //   1015: invokevirtual 435	android/content/Context:getResources	()Landroid/content/res/Resources;
    //   1018: ldc_w 579
    //   1021: invokevirtual 442	android/content/res/Resources:getString	(I)Ljava/lang/String;
    //   1024: iconst_0
    //   1025: bipush 17
    //   1027: invokevirtual 446	java/lang/String:substring	(II)Ljava/lang/String;
    //   1030: invokevirtual 431	java/lang/String:length	()I
    //   1033: bipush 13
    //   1035: isub
    //   1036: aload_0
    //   1037: invokevirtual 435	android/content/Context:getResources	()Landroid/content/res/Resources;
    //   1040: ldc_w 580
    //   1043: invokevirtual 442	android/content/res/Resources:getString	(I)Ljava/lang/String;
    //   1046: iconst_0
    //   1047: iconst_4
    //   1048: invokevirtual 446	java/lang/String:substring	(II)Ljava/lang/String;
    //   1051: iconst_1
    //   1052: invokevirtual 450	java/lang/String:codePointAt	(I)I
    //   1055: bipush 16
    //   1057: iadd
    //   1058: aload_0
    //   1059: invokevirtual 435	android/content/Context:getResources	()Landroid/content/res/Resources;
    //   1062: ldc_w 581
    //   1065: invokevirtual 442	android/content/res/Resources:getString	(I)Ljava/lang/String;
    //   1068: iconst_0
    //   1069: bipush 7
    //   1071: invokevirtual 446	java/lang/String:substring	(II)Ljava/lang/String;
    //   1074: invokevirtual 431	java/lang/String:length	()I
    //   1077: ldc_w 582
    //   1080: iadd
    //   1081: i2c
    //   1082: invokestatic 456	o/O:ˋ	(IIC)Ljava/lang/Object;
    //   1085: checkcast 458	java/lang/Class
    //   1088: ldc_w 459
    //   1091: iconst_2
    //   1092: anewarray 458	java/lang/Class
    //   1095: dup
    //   1096: iconst_0
    //   1097: ldc_w 427
    //   1100: aastore
    //   1101: dup
    //   1102: iconst_1
    //   1103: ldc_w 427
    //   1106: aastore
    //   1107: invokevirtual 463	java/lang/Class:getMethod	(Ljava/lang/String;[Ljava/lang/Class;)Ljava/lang/reflect/Method;
    //   1110: aconst_null
    //   1111: iconst_2
    //   1112: anewarray 478	java/lang/Object
    //   1115: dup
    //   1116: iconst_0
    //   1117: aload_3
    //   1118: aastore
    //   1119: dup
    //   1120: iconst_1
    //   1121: aload 4
    //   1123: aastore
    //   1124: invokevirtual 469	java/lang/reflect/Method:invoke	(Ljava/lang/Object;[Ljava/lang/Object;)Ljava/lang/Object;
    //   1127: pop
    //   1128: goto +247 -> 1375
    //   1131: iconst_0
    //   1132: istore_1
    //   1133: goto -883 -> 250
    //   1136: aload_0
    //   1137: invokespecial 585	ro/btrl/boot/ui/activity/SplashScreenActivity:ˎˎ	()V
    //   1140: goto +20 -> 1160
    //   1143: astore_3
    //   1144: aload_3
    //   1145: invokevirtual 419	java/lang/Throwable:getCause	()Ljava/lang/Throwable;
    //   1148: astore 4
    //   1150: aload 4
    //   1152: ifnull +6 -> 1158
    //   1155: aload 4
    //   1157: athrow
    //   1158: aload_3
    //   1159: athrow
    //   1160: aload_0
    //   1161: invokevirtual 425	android/content/Context:getPackageName	()Ljava/lang/String;
    //   1164: invokevirtual 431	java/lang/String:length	()I
    //   1167: bipush 7
    //   1169: isub
    //   1170: aload_0
    //   1171: invokevirtual 516	android/content/Context:getApplicationInfo	()Landroid/content/pm/ApplicationInfo;
    //   1174: getfield 521	android/content/pm/ApplicationInfo:targetSdkVersion	I
    //   1177: sipush 388
    //   1180: iadd
    //   1181: aload_0
    //   1182: invokevirtual 425	android/content/Context:getPackageName	()Ljava/lang/String;
    //   1185: bipush 6
    //   1187: invokevirtual 450	java/lang/String:codePointAt	(I)I
    //   1190: sipush 30145
    //   1193: iadd
    //   1194: i2c
    //   1195: invokestatic 456	o/O:ˋ	(IIC)Ljava/lang/Object;
    //   1198: checkcast 458	java/lang/Class
    //   1201: ldc_w 570
    //   1204: aconst_null
    //   1205: invokevirtual 463	java/lang/Class:getMethod	(Ljava/lang/String;[Ljava/lang/Class;)Ljava/lang/reflect/Method;
    //   1208: aconst_null
    //   1209: aconst_null
    //   1210: invokevirtual 469	java/lang/reflect/Method:invoke	(Ljava/lang/Object;[Ljava/lang/Object;)Ljava/lang/Object;
    //   1213: astore_3
    //   1214: goto +20 -> 1234
    //   1217: astore_3
    //   1218: aload_3
    //   1219: invokevirtual 419	java/lang/Throwable:getCause	()Ljava/lang/Throwable;
    //   1222: astore 4
    //   1224: aload 4
    //   1226: ifnull +6 -> 1232
    //   1229: aload 4
    //   1231: athrow
    //   1232: aload_3
    //   1233: athrow
    //   1234: aload_0
    //   1235: invokevirtual 435	android/content/Context:getResources	()Landroid/content/res/Resources;
    //   1238: ldc_w 586
    //   1241: invokevirtual 442	android/content/res/Resources:getString	(I)Ljava/lang/String;
    //   1244: iconst_0
    //   1245: iconst_4
    //   1246: invokevirtual 446	java/lang/String:substring	(II)Ljava/lang/String;
    //   1249: invokevirtual 431	java/lang/String:length	()I
    //   1252: iconst_0
    //   1253: iadd
    //   1254: aload_0
    //   1255: invokevirtual 435	android/content/Context:getResources	()Landroid/content/res/Resources;
    //   1258: ldc_w 587
    //   1261: invokevirtual 442	android/content/res/Resources:getString	(I)Ljava/lang/String;
    //   1264: iconst_0
    //   1265: iconst_4
    //   1266: invokevirtual 446	java/lang/String:substring	(II)Ljava/lang/String;
    //   1269: invokevirtual 431	java/lang/String:length	()I
    //   1272: sipush 409
    //   1275: iadd
    //   1276: aload_0
    //   1277: invokevirtual 435	android/content/Context:getResources	()Landroid/content/res/Resources;
    //   1280: ldc_w 588
    //   1283: invokevirtual 442	android/content/res/Resources:getString	(I)Ljava/lang/String;
    //   1286: iconst_0
    //   1287: iconst_5
    //   1288: invokevirtual 446	java/lang/String:substring	(II)Ljava/lang/String;
    //   1291: invokevirtual 431	java/lang/String:length	()I
    //   1294: sipush 30248
    //   1297: iadd
    //   1298: i2c
    //   1299: invokestatic 456	o/O:ˋ	(IIC)Ljava/lang/Object;
    //   1302: checkcast 458	java/lang/Class
    //   1305: ldc_w 590
    //   1308: aconst_null
    //   1309: invokevirtual 463	java/lang/Class:getMethod	(Ljava/lang/String;[Ljava/lang/Class;)Ljava/lang/reflect/Method;
    //   1312: aload_3
    //   1313: aconst_null
    //   1314: invokevirtual 469	java/lang/reflect/Method:invoke	(Ljava/lang/Object;[Ljava/lang/Object;)Ljava/lang/Object;
    //   1317: checkcast 547	o/Gw
    //   1320: astore_3
    //   1321: aload_3
    //   1322: getstatic 593	o/Gw:UNKNOWN	Lo/Gw;
    //   1325: invokevirtual 597	o/Gw:equals	(Ljava/lang/Object;)Z
    //   1328: ifeq +6 -> 1334
    //   1331: goto -670 -> 661
    //   1334: goto +73 -> 1407
    //   1337: bipush 26
    //   1339: istore_1
    //   1340: goto +297 -> 1637
    //   1343: iconst_1
    //   1344: istore_1
    //   1345: goto -1095 -> 250
    //   1348: getstatic 34	ro/btrl/boot/ui/activity/SplashScreenActivity:ˈ	I
    //   1351: bipush 93
    //   1353: iadd
    //   1354: istore_1
    //   1355: iload_1
    //   1356: sipush 128
    //   1359: irem
    //   1360: putstatic 32	ro/btrl/boot/ui/activity/SplashScreenActivity:ʾ	I
    //   1363: iload_1
    //   1364: iconst_2
    //   1365: irem
    //   1366: ifeq +6 -> 1372
    //   1369: goto +7 -> 1376
    //   1372: goto -236 -> 1136
    //   1375: return
    //   1376: goto -240 -> 1136
    //   1379: return
    //   1380: getstatic 34	ro/btrl/boot/ui/activity/SplashScreenActivity:ˈ	I
    //   1383: bipush 125
    //   1385: iadd
    //   1386: istore_1
    //   1387: iload_1
    //   1388: sipush 128
    //   1391: irem
    //   1392: putstatic 32	ro/btrl/boot/ui/activity/SplashScreenActivity:ʾ	I
    //   1395: iload_1
    //   1396: iconst_2
    //   1397: irem
    //   1398: ifeq +6 -> 1404
    //   1401: goto -58 -> 1343
    //   1404: goto -273 -> 1131
    //   1407: aload_3
    //   1408: getstatic 551	o/Gw:INACTIVE_PHONE_NUMBER	Lo/Gw;
    //   1411: invokevirtual 597	o/Gw:equals	(Ljava/lang/Object;)Z
    //   1414: ifeq +6 -> 1420
    //   1417: goto -1139 -> 278
    //   1420: goto -83 -> 1337
    //   1423: goto -75 -> 1348
    //   1426: goto +20 -> 1446
    //   1429: astore_3
    //   1430: aload_3
    //   1431: invokevirtual 419	java/lang/Throwable:getCause	()Ljava/lang/Throwable;
    //   1434: astore 4
    //   1436: aload 4
    //   1438: ifnull +6 -> 1444
    //   1441: aload 4
    //   1443: athrow
    //   1444: aload_3
    //   1445: athrow
    //   1446: aload_0
    //   1447: invokevirtual 435	android/content/Context:getResources	()Landroid/content/res/Resources;
    //   1450: ldc_w 532
    //   1453: invokevirtual 442	android/content/res/Resources:getString	(I)Ljava/lang/String;
    //   1456: iconst_0
    //   1457: iconst_4
    //   1458: invokevirtual 446	java/lang/String:substring	(II)Ljava/lang/String;
    //   1461: invokevirtual 431	java/lang/String:length	()I
    //   1464: iconst_1
    //   1465: isub
    //   1466: aload_0
    //   1467: invokevirtual 516	android/content/Context:getApplicationInfo	()Landroid/content/pm/ApplicationInfo;
    //   1470: getfield 521	android/content/pm/ApplicationInfo:targetSdkVersion	I
    //   1473: iconst_1
    //   1474: isub
    //   1475: aload_0
    //   1476: invokevirtual 435	android/content/Context:getResources	()Landroid/content/res/Resources;
    //   1479: ldc_w 598
    //   1482: invokevirtual 442	android/content/res/Resources:getString	(I)Ljava/lang/String;
    //   1485: iconst_0
    //   1486: bipush 9
    //   1488: invokevirtual 446	java/lang/String:substring	(II)Ljava/lang/String;
    //   1491: invokevirtual 431	java/lang/String:length	()I
    //   1494: bipush 9
    //   1496: isub
    //   1497: i2c
    //   1498: invokestatic 456	o/O:ˋ	(IIC)Ljava/lang/Object;
    //   1501: checkcast 458	java/lang/Class
    //   1504: ldc_w 459
    //   1507: aconst_null
    //   1508: invokevirtual 463	java/lang/Class:getMethod	(Ljava/lang/String;[Ljava/lang/Class;)Ljava/lang/reflect/Method;
    //   1511: aconst_null
    //   1512: aconst_null
    //   1513: invokevirtual 469	java/lang/reflect/Method:invoke	(Ljava/lang/Object;[Ljava/lang/Object;)Ljava/lang/Object;
    //   1516: astore 4
    //   1518: aload_0
    //   1519: invokevirtual 473	ro/btrl/boot/ui/activity/SplashScreenActivity:ॱˊ	()Landroid/content/Context;
    //   1522: astore 5
    //   1524: goto +20 -> 1544
    //   1527: astore_3
    //   1528: aload_3
    //   1529: invokevirtual 419	java/lang/Throwable:getCause	()Ljava/lang/Throwable;
    //   1532: astore 4
    //   1534: aload 4
    //   1536: ifnull +6 -> 1542
    //   1539: aload 4
    //   1541: athrow
    //   1542: aload_3
    //   1543: athrow
    //   1544: aload_0
    //   1545: invokevirtual 435	android/content/Context:getResources	()Landroid/content/res/Resources;
    //   1548: ldc_w 599
    //   1551: invokevirtual 442	android/content/res/Resources:getString	(I)Ljava/lang/String;
    //   1554: iconst_0
    //   1555: iconst_4
    //   1556: invokevirtual 446	java/lang/String:substring	(II)Ljava/lang/String;
    //   1559: invokevirtual 431	java/lang/String:length	()I
    //   1562: iconst_1
    //   1563: isub
    //   1564: aload_0
    //   1565: invokevirtual 516	android/content/Context:getApplicationInfo	()Landroid/content/pm/ApplicationInfo;
    //   1568: getfield 521	android/content/pm/ApplicationInfo:targetSdkVersion	I
    //   1571: iconst_1
    //   1572: isub
    //   1573: aload_0
    //   1574: invokevirtual 516	android/content/Context:getApplicationInfo	()Landroid/content/pm/ApplicationInfo;
    //   1577: getfield 521	android/content/pm/ApplicationInfo:targetSdkVersion	I
    //   1580: bipush 25
    //   1582: isub
    //   1583: i2c
    //   1584: invokestatic 456	o/O:ˋ	(IIC)Ljava/lang/Object;
    //   1587: checkcast 458	java/lang/Class
    //   1590: ldc_w 600
    //   1593: iconst_1
    //   1594: anewarray 458	java/lang/Class
    //   1597: dup
    //   1598: iconst_0
    //   1599: ldc_w 421
    //   1602: aastore
    //   1603: invokevirtual 463	java/lang/Class:getMethod	(Ljava/lang/String;[Ljava/lang/Class;)Ljava/lang/reflect/Method;
    //   1606: aload 4
    //   1608: iconst_1
    //   1609: anewarray 478	java/lang/Object
    //   1612: dup
    //   1613: iconst_0
    //   1614: aload 5
    //   1616: aastore
    //   1617: invokevirtual 469	java/lang/reflect/Method:invoke	(Ljava/lang/Object;[Ljava/lang/Object;)Ljava/lang/Object;
    //   1620: checkcast 480	java/lang/Boolean
    //   1623: invokevirtual 484	java/lang/Boolean:booleanValue	()Z
    //   1626: istore_2
    //   1627: iload_2
    //   1628: ifeq +6 -> 1634
    //   1631: goto -1347 -> 284
    //   1634: goto -1624 -> 10
    //   1637: iload_1
    //   1638: lookupswitch	default:+26->1664, 26:+-1628->10, 28:+-212->1426
    //   1664: goto -1654 -> 10
    // Local variable table:
    //   start	length	slot	name	signature
    //   0	1667	0	this	SplashScreenActivity
    //   6	1632	1	i	int
    //   1626	2	2	bool	boolean
    //   113	131	3	localGw1	o.Gw
    //   275	2	3	localException1	Exception
    //   332	1	3	str1	String
    //   407	122	3	localObject1	Object
    //   542	16	3	localObject2	Object
    //   634	2	3	localIt	o.It
    //   658	2	3	localException2	Exception
    //   664	16	3	localObject3	Object
    //   750	1	3	localObject4	Object
    //   759	97	3	localObject5	Object
    //   933	1	3	str2	String
    //   997	121	3	localObject6	Object
    //   1143	16	3	localObject7	Object
    //   1213	1	3	localObject8	Object
    //   1217	96	3	localObject9	Object
    //   1320	88	3	localGw2	o.Gw
    //   1429	16	3	localObject10	Object
    //   1527	16	3	localObject11	Object
    //   46	1561	4	localObject12	Object
    //   108	1507	5	localObject13	Object
    // Exception table:
    //   from	to	target	type
    //   130	242	113	finally
    //   1528	1534	275	java/lang/Exception
    //   1539	1542	275	java/lang/Exception
    //   1542	1544	275	java/lang/Exception
    //   424	539	407	finally
    //   559	635	542	finally
    //   1430	1436	658	java/lang/Exception
    //   1441	1444	658	java/lang/Exception
    //   1444	1446	658	java/lang/Exception
    //   1518	1524	658	java/lang/Exception
    //   1528	1534	658	java/lang/Exception
    //   1539	1542	658	java/lang/Exception
    //   1542	1544	658	java/lang/Exception
    //   681	751	664	finally
    //   776	869	759	finally
    //   1014	1128	997	finally
    //   1160	1214	1143	finally
    //   1234	1321	1217	finally
    //   1446	1518	1429	finally
    //   1544	1627	1527	finally
  }
  
  /* Error */
  private void ˋˊ()
  {
    // Byte code:
    //   0: goto +176 -> 176
    //   3: iload_1
    //   4: tableswitch	default:+24->28, 0:+134->138, 1:+24->28
    //   28: new 607	java/lang/NullPointerException
    //   31: dup
    //   32: invokespecial 608	java/lang/NullPointerException:<init>	()V
    //   35: athrow
    //   36: astore_2
    //   37: aload_2
    //   38: athrow
    //   39: goto +17 -> 56
    //   42: astore_3
    //   43: aload_3
    //   44: invokevirtual 419	java/lang/Throwable:getCause	()Ljava/lang/Throwable;
    //   47: astore_2
    //   48: aload_2
    //   49: ifnull +5 -> 54
    //   52: aload_2
    //   53: athrow
    //   54: aload_3
    //   55: athrow
    //   56: aload_0
    //   57: invokevirtual 425	android/content/Context:getPackageName	()Ljava/lang/String;
    //   60: invokevirtual 431	java/lang/String:length	()I
    //   63: bipush 7
    //   65: isub
    //   66: aload_0
    //   67: invokevirtual 425	android/content/Context:getPackageName	()Ljava/lang/String;
    //   70: iconst_3
    //   71: invokevirtual 450	java/lang/String:codePointAt	(I)I
    //   74: bipush 37
    //   76: iadd
    //   77: aload_0
    //   78: invokevirtual 516	android/content/Context:getApplicationInfo	()Landroid/content/pm/ApplicationInfo;
    //   81: getfield 521	android/content/pm/ApplicationInfo:targetSdkVersion	I
    //   84: ldc_w 609
    //   87: iadd
    //   88: i2c
    //   89: invokestatic 456	o/O:ˋ	(IIC)Ljava/lang/Object;
    //   92: checkcast 458	java/lang/Class
    //   95: ldc_w 492
    //   98: aconst_null
    //   99: invokevirtual 463	java/lang/Class:getMethod	(Ljava/lang/String;[Ljava/lang/Class;)Ljava/lang/reflect/Method;
    //   102: aconst_null
    //   103: aconst_null
    //   104: invokevirtual 469	java/lang/reflect/Method:invoke	(Ljava/lang/Object;[Ljava/lang/Object;)Ljava/lang/Object;
    //   107: checkcast 494	o/It
    //   110: astore_2
    //   111: aload_2
    //   112: invokeinterface 611 1 0
    //   117: astore_3
    //   118: new 15	ro/btrl/boot/ui/activity/SplashScreenActivity$5
    //   121: dup
    //   122: aload_0
    //   123: aload_0
    //   124: invokespecial 612	ro/btrl/boot/ui/activity/SplashScreenActivity$5:<init>	(Lro/btrl/boot/ui/activity/SplashScreenActivity;Landroid/content/Context;)V
    //   127: astore_2
    //   128: aload_3
    //   129: aload_2
    //   130: invokeinterface 506 2 0
    //   135: goto +9 -> 144
    //   138: return
    //   139: iconst_0
    //   140: istore_1
    //   141: goto -138 -> 3
    //   144: getstatic 34	ro/btrl/boot/ui/activity/SplashScreenActivity:ˈ	I
    //   147: bipush 113
    //   149: iadd
    //   150: istore_1
    //   151: iload_1
    //   152: sipush 128
    //   155: irem
    //   156: putstatic 32	ro/btrl/boot/ui/activity/SplashScreenActivity:ʾ	I
    //   159: iload_1
    //   160: iconst_2
    //   161: irem
    //   162: ifeq +6 -> 168
    //   165: goto +6 -> 171
    //   168: goto -29 -> 139
    //   171: iconst_1
    //   172: istore_1
    //   173: goto -170 -> 3
    //   176: goto -137 -> 39
    // Local variable table:
    //   start	length	slot	name	signature
    //   0	179	0	this	SplashScreenActivity
    //   3	170	1	i	int
    //   36	2	2	localException	Exception
    //   47	83	2	localObject1	Object
    //   42	13	3	localObject2	Object
    //   117	12	3	localCv	Cv
    // Exception table:
    //   from	to	target	type
    //   43	48	36	java/lang/Exception
    //   52	54	36	java/lang/Exception
    //   54	56	36	java/lang/Exception
    //   111	118	36	java/lang/Exception
    //   128	135	36	java/lang/Exception
    //   56	111	42	finally
  }
  
  /* Error */
  private void ˍ()
  {
    // Byte code:
    //   0: goto +260 -> 260
    //   3: bipush 46
    //   5: istore_1
    //   6: goto +490 -> 496
    //   9: goto +34 -> 43
    //   12: getstatic 32	ro/btrl/boot/ui/activity/SplashScreenActivity:ʾ	I
    //   15: bipush 29
    //   17: iadd
    //   18: istore_1
    //   19: iload_1
    //   20: sipush 128
    //   23: irem
    //   24: putstatic 34	ro/btrl/boot/ui/activity/SplashScreenActivity:ˈ	I
    //   27: iload_1
    //   28: iconst_2
    //   29: irem
    //   30: ifne +6 -> 36
    //   33: goto +39 -> 72
    //   36: aload_0
    //   37: invokespecial 615	ro/btrl/boot/ui/activity/SplashScreenActivity:ˋˊ	()V
    //   40: goto -31 -> 9
    //   43: getstatic 32	ro/btrl/boot/ui/activity/SplashScreenActivity:ʾ	I
    //   46: bipush 15
    //   48: iadd
    //   49: istore_1
    //   50: iload_1
    //   51: sipush 128
    //   54: irem
    //   55: putstatic 34	ro/btrl/boot/ui/activity/SplashScreenActivity:ˈ	I
    //   58: iload_1
    //   59: iconst_2
    //   60: irem
    //   61: ifne +6 -> 67
    //   64: goto +7 -> 71
    //   67: return
    //   68: astore_3
    //   69: aload_3
    //   70: athrow
    //   71: return
    //   72: goto -36 -> 36
    //   75: goto +20 -> 95
    //   78: astore_3
    //   79: aload_3
    //   80: invokevirtual 419	java/lang/Throwable:getCause	()Ljava/lang/Throwable;
    //   83: astore 4
    //   85: aload 4
    //   87: ifnull +6 -> 93
    //   90: aload 4
    //   92: athrow
    //   93: aload_3
    //   94: athrow
    //   95: aload_0
    //   96: invokevirtual 516	android/content/Context:getApplicationInfo	()Landroid/content/pm/ApplicationInfo;
    //   99: getfield 521	android/content/pm/ApplicationInfo:targetSdkVersion	I
    //   102: bipush 21
    //   104: isub
    //   105: aload_0
    //   106: invokevirtual 425	android/content/Context:getPackageName	()Ljava/lang/String;
    //   109: invokevirtual 431	java/lang/String:length	()I
    //   112: sipush 402
    //   115: iadd
    //   116: aload_0
    //   117: invokevirtual 435	android/content/Context:getResources	()Landroid/content/res/Resources;
    //   120: ldc_w 616
    //   123: invokevirtual 442	android/content/res/Resources:getString	(I)Ljava/lang/String;
    //   126: iconst_0
    //   127: iconst_4
    //   128: invokevirtual 446	java/lang/String:substring	(II)Ljava/lang/String;
    //   131: iconst_1
    //   132: invokevirtual 450	java/lang/String:codePointAt	(I)I
    //   135: sipush 30227
    //   138: iadd
    //   139: i2c
    //   140: invokestatic 456	o/O:ˋ	(IIC)Ljava/lang/Object;
    //   143: checkcast 458	java/lang/Class
    //   146: ldc_w 570
    //   149: aconst_null
    //   150: invokevirtual 463	java/lang/Class:getMethod	(Ljava/lang/String;[Ljava/lang/Class;)Ljava/lang/reflect/Method;
    //   153: aconst_null
    //   154: aconst_null
    //   155: invokevirtual 469	java/lang/reflect/Method:invoke	(Ljava/lang/Object;[Ljava/lang/Object;)Ljava/lang/Object;
    //   158: astore_3
    //   159: goto +20 -> 179
    //   162: astore_3
    //   163: aload_3
    //   164: invokevirtual 419	java/lang/Throwable:getCause	()Ljava/lang/Throwable;
    //   167: astore 4
    //   169: aload 4
    //   171: ifnull +6 -> 177
    //   174: aload 4
    //   176: athrow
    //   177: aload_3
    //   178: athrow
    //   179: aload_0
    //   180: invokevirtual 425	android/content/Context:getPackageName	()Ljava/lang/String;
    //   183: bipush 9
    //   185: invokevirtual 450	java/lang/String:codePointAt	(I)I
    //   188: bipush 93
    //   190: isub
    //   191: aload_0
    //   192: invokevirtual 425	android/content/Context:getPackageName	()Ljava/lang/String;
    //   195: iconst_4
    //   196: invokevirtual 450	java/lang/String:codePointAt	(I)I
    //   199: sipush 297
    //   202: iadd
    //   203: aload_0
    //   204: invokevirtual 435	android/content/Context:getResources	()Landroid/content/res/Resources;
    //   207: ldc_w 617
    //   210: invokevirtual 442	android/content/res/Resources:getString	(I)Ljava/lang/String;
    //   213: iconst_0
    //   214: iconst_4
    //   215: invokevirtual 446	java/lang/String:substring	(II)Ljava/lang/String;
    //   218: iconst_1
    //   219: invokevirtual 450	java/lang/String:codePointAt	(I)I
    //   222: sipush 30227
    //   225: iadd
    //   226: i2c
    //   227: invokestatic 456	o/O:ˋ	(IIC)Ljava/lang/Object;
    //   230: checkcast 458	java/lang/Class
    //   233: ldc_w 619
    //   236: aconst_null
    //   237: invokevirtual 463	java/lang/Class:getMethod	(Ljava/lang/String;[Ljava/lang/Class;)Ljava/lang/reflect/Method;
    //   240: aload_3
    //   241: aconst_null
    //   242: invokevirtual 469	java/lang/reflect/Method:invoke	(Ljava/lang/Object;[Ljava/lang/Object;)Ljava/lang/Object;
    //   245: checkcast 480	java/lang/Boolean
    //   248: invokevirtual 484	java/lang/Boolean:booleanValue	()Z
    //   251: istore_2
    //   252: aload_0
    //   253: iload_2
    //   254: invokespecial 604	ro/btrl/boot/ui/activity/SplashScreenActivity:ˎ	(Z)V
    //   257: goto -248 -> 9
    //   260: goto +20 -> 280
    //   263: astore_3
    //   264: aload_3
    //   265: invokevirtual 419	java/lang/Throwable:getCause	()Ljava/lang/Throwable;
    //   268: astore 4
    //   270: aload 4
    //   272: ifnull +6 -> 278
    //   275: aload 4
    //   277: athrow
    //   278: aload_3
    //   279: athrow
    //   280: aload_0
    //   281: invokevirtual 435	android/content/Context:getResources	()Landroid/content/res/Resources;
    //   284: ldc_w 620
    //   287: invokevirtual 442	android/content/res/Resources:getString	(I)Ljava/lang/String;
    //   290: iconst_0
    //   291: iconst_4
    //   292: invokevirtual 446	java/lang/String:substring	(II)Ljava/lang/String;
    //   295: iconst_2
    //   296: invokevirtual 450	java/lang/String:codePointAt	(I)I
    //   299: bipush 8
    //   301: isub
    //   302: aload_0
    //   303: invokevirtual 435	android/content/Context:getResources	()Landroid/content/res/Resources;
    //   306: ldc_w 621
    //   309: invokevirtual 442	android/content/res/Resources:getString	(I)Ljava/lang/String;
    //   312: iconst_0
    //   313: bipush 20
    //   315: invokevirtual 446	java/lang/String:substring	(II)Ljava/lang/String;
    //   318: invokevirtual 431	java/lang/String:length	()I
    //   321: iconst_4
    //   322: iadd
    //   323: aload_0
    //   324: invokevirtual 435	android/content/Context:getResources	()Landroid/content/res/Resources;
    //   327: ldc_w 622
    //   330: invokevirtual 442	android/content/res/Resources:getString	(I)Ljava/lang/String;
    //   333: iconst_0
    //   334: iconst_1
    //   335: invokevirtual 446	java/lang/String:substring	(II)Ljava/lang/String;
    //   338: invokevirtual 431	java/lang/String:length	()I
    //   341: iconst_1
    //   342: isub
    //   343: i2c
    //   344: invokestatic 456	o/O:ˋ	(IIC)Ljava/lang/Object;
    //   347: checkcast 458	java/lang/Class
    //   350: ldc_w 459
    //   353: aconst_null
    //   354: invokevirtual 463	java/lang/Class:getMethod	(Ljava/lang/String;[Ljava/lang/Class;)Ljava/lang/reflect/Method;
    //   357: aconst_null
    //   358: aconst_null
    //   359: invokevirtual 469	java/lang/reflect/Method:invoke	(Ljava/lang/Object;[Ljava/lang/Object;)Ljava/lang/Object;
    //   362: astore_3
    //   363: goto +20 -> 383
    //   366: astore_3
    //   367: aload_3
    //   368: invokevirtual 419	java/lang/Throwable:getCause	()Ljava/lang/Throwable;
    //   371: astore 4
    //   373: aload 4
    //   375: ifnull +6 -> 381
    //   378: aload 4
    //   380: athrow
    //   381: aload_3
    //   382: athrow
    //   383: aload_0
    //   384: invokevirtual 435	android/content/Context:getResources	()Landroid/content/res/Resources;
    //   387: ldc_w 623
    //   390: invokevirtual 442	android/content/res/Resources:getString	(I)Ljava/lang/String;
    //   393: iconst_0
    //   394: iconst_4
    //   395: invokevirtual 446	java/lang/String:substring	(II)Ljava/lang/String;
    //   398: iconst_2
    //   399: invokevirtual 450	java/lang/String:codePointAt	(I)I
    //   402: bipush 8
    //   404: isub
    //   405: aload_0
    //   406: invokevirtual 435	android/content/Context:getResources	()Landroid/content/res/Resources;
    //   409: ldc_w 624
    //   412: invokevirtual 442	android/content/res/Resources:getString	(I)Ljava/lang/String;
    //   415: bipush 11
    //   417: bipush 22
    //   419: invokevirtual 446	java/lang/String:substring	(II)Ljava/lang/String;
    //   422: iconst_3
    //   423: invokevirtual 450	java/lang/String:codePointAt	(I)I
    //   426: sipush 144
    //   429: isub
    //   430: aload_0
    //   431: invokevirtual 425	android/content/Context:getPackageName	()Ljava/lang/String;
    //   434: iconst_2
    //   435: invokevirtual 450	java/lang/String:codePointAt	(I)I
    //   438: bipush 46
    //   440: isub
    //   441: i2c
    //   442: invokestatic 456	o/O:ˋ	(IIC)Ljava/lang/Object;
    //   445: checkcast 458	java/lang/Class
    //   448: ldc_w 459
    //   451: iconst_1
    //   452: anewarray 458	java/lang/Class
    //   455: dup
    //   456: iconst_0
    //   457: ldc_w 421
    //   460: aastore
    //   461: invokevirtual 463	java/lang/Class:getMethod	(Ljava/lang/String;[Ljava/lang/Class;)Ljava/lang/reflect/Method;
    //   464: aload_3
    //   465: iconst_1
    //   466: anewarray 478	java/lang/Object
    //   469: dup
    //   470: iconst_0
    //   471: aload_0
    //   472: aastore
    //   473: invokevirtual 469	java/lang/reflect/Method:invoke	(Ljava/lang/Object;[Ljava/lang/Object;)Ljava/lang/Object;
    //   476: checkcast 480	java/lang/Boolean
    //   479: invokevirtual 484	java/lang/Boolean:booleanValue	()Z
    //   482: istore_2
    //   483: iload_2
    //   484: ifeq +6 -> 490
    //   487: goto +40 -> 527
    //   490: goto -487 -> 3
    //   493: astore_3
    //   494: aload_3
    //   495: athrow
    //   496: iload_1
    //   497: lookupswitch	default:+27->524, 46:+-422->75, 78:+-485->12
    //   524: goto -512 -> 12
    //   527: bipush 78
    //   529: istore_1
    //   530: goto -34 -> 496
    // Local variable table:
    //   start	length	slot	name	signature
    //   0	533	0	this	SplashScreenActivity
    //   5	525	1	i	int
    //   251	233	2	bool	boolean
    //   68	2	3	localException1	Exception
    //   78	16	3	localObject1	Object
    //   158	1	3	localObject2	Object
    //   162	79	3	localObject3	Object
    //   263	16	3	localObject4	Object
    //   362	1	3	localObject5	Object
    //   366	99	3	localObject6	Object
    //   493	2	3	localException2	Exception
    //   83	296	4	localThrowable	Throwable
    // Exception table:
    //   from	to	target	type
    //   163	169	68	java/lang/Exception
    //   174	177	68	java/lang/Exception
    //   177	179	68	java/lang/Exception
    //   95	159	78	finally
    //   179	252	162	finally
    //   280	363	263	finally
    //   383	483	366	finally
    //   79	85	493	java/lang/Exception
    //   90	93	493	java/lang/Exception
    //   93	95	493	java/lang/Exception
    //   163	169	493	java/lang/Exception
    //   174	177	493	java/lang/Exception
    //   177	179	493	java/lang/Exception
    //   252	257	493	java/lang/Exception
  }
  
  /* Error */
  private void ˎ(En paramEn)
  {
    // Byte code:
    //   0: goto +369 -> 369
    //   3: aload_3
    //   4: invokeinterface 631 1 0
    //   9: checkcast 633	o/Ec
    //   12: astore_1
    //   13: goto +17 -> 30
    //   16: astore_3
    //   17: aload_3
    //   18: invokevirtual 419	java/lang/Throwable:getCause	()Ljava/lang/Throwable;
    //   21: astore_1
    //   22: aload_1
    //   23: ifnull +5 -> 28
    //   26: aload_1
    //   27: athrow
    //   28: aload_3
    //   29: athrow
    //   30: aload_0
    //   31: invokevirtual 516	android/content/Context:getApplicationInfo	()Landroid/content/pm/ApplicationInfo;
    //   34: getfield 521	android/content/pm/ApplicationInfo:targetSdkVersion	I
    //   37: bipush 21
    //   39: isub
    //   40: aload_0
    //   41: invokevirtual 516	android/content/Context:getApplicationInfo	()Landroid/content/pm/ApplicationInfo;
    //   44: getfield 521	android/content/pm/ApplicationInfo:targetSdkVersion	I
    //   47: sipush 242
    //   50: iadd
    //   51: aload_0
    //   52: invokevirtual 516	android/content/Context:getApplicationInfo	()Landroid/content/pm/ApplicationInfo;
    //   55: getfield 521	android/content/pm/ApplicationInfo:targetSdkVersion	I
    //   58: sipush 14763
    //   61: iadd
    //   62: i2c
    //   63: invokestatic 456	o/O:ˋ	(IIC)Ljava/lang/Object;
    //   66: checkcast 458	java/lang/Class
    //   69: ldc_w 492
    //   72: aconst_null
    //   73: invokevirtual 463	java/lang/Class:getMethod	(Ljava/lang/String;[Ljava/lang/Class;)Ljava/lang/reflect/Method;
    //   76: aconst_null
    //   77: aconst_null
    //   78: invokevirtual 469	java/lang/reflect/Method:invoke	(Ljava/lang/Object;[Ljava/lang/Object;)Ljava/lang/Object;
    //   81: astore 5
    //   83: aload_1
    //   84: invokevirtual 635	o/Ec:ˋ	()Ljava/lang/String;
    //   87: astore 4
    //   89: goto +17 -> 106
    //   92: astore_3
    //   93: aload_3
    //   94: invokevirtual 419	java/lang/Throwable:getCause	()Ljava/lang/Throwable;
    //   97: astore_1
    //   98: aload_1
    //   99: ifnull +5 -> 104
    //   102: aload_1
    //   103: athrow
    //   104: aload_3
    //   105: athrow
    //   106: aload_0
    //   107: invokevirtual 425	android/content/Context:getPackageName	()Ljava/lang/String;
    //   110: iconst_1
    //   111: invokevirtual 450	java/lang/String:codePointAt	(I)I
    //   114: bipush 107
    //   116: isub
    //   117: aload_0
    //   118: invokevirtual 435	android/content/Context:getResources	()Landroid/content/res/Resources;
    //   121: ldc_w 620
    //   124: invokevirtual 442	android/content/res/Resources:getString	(I)Ljava/lang/String;
    //   127: iconst_0
    //   128: iconst_4
    //   129: invokevirtual 446	java/lang/String:substring	(II)Ljava/lang/String;
    //   132: iconst_1
    //   133: invokevirtual 450	java/lang/String:codePointAt	(I)I
    //   136: sipush 241
    //   139: iadd
    //   140: aload_0
    //   141: invokevirtual 435	android/content/Context:getResources	()Landroid/content/res/Resources;
    //   144: ldc_w 636
    //   147: invokevirtual 442	android/content/res/Resources:getString	(I)Ljava/lang/String;
    //   150: iconst_0
    //   151: bipush 15
    //   153: invokevirtual 446	java/lang/String:substring	(II)Ljava/lang/String;
    //   156: invokevirtual 431	java/lang/String:length	()I
    //   159: sipush 14773
    //   162: iadd
    //   163: i2c
    //   164: invokestatic 456	o/O:ˋ	(IIC)Ljava/lang/Object;
    //   167: checkcast 458	java/lang/Class
    //   170: ldc_w 637
    //   173: iconst_1
    //   174: anewarray 458	java/lang/Class
    //   177: dup
    //   178: iconst_0
    //   179: ldc_w 427
    //   182: aastore
    //   183: invokevirtual 463	java/lang/Class:getMethod	(Ljava/lang/String;[Ljava/lang/Class;)Ljava/lang/reflect/Method;
    //   186: aload 5
    //   188: iconst_1
    //   189: anewarray 478	java/lang/Object
    //   192: dup
    //   193: iconst_0
    //   194: aload 4
    //   196: aastore
    //   197: invokevirtual 469	java/lang/reflect/Method:invoke	(Ljava/lang/Object;[Ljava/lang/Object;)Ljava/lang/Object;
    //   200: checkcast 639	com/insidesecure/hce/MatrixHCECard
    //   203: astore 4
    //   205: aload 4
    //   207: ifnull +6 -> 213
    //   210: goto +46 -> 256
    //   213: goto +48 -> 261
    //   216: goto +88 -> 304
    //   219: astore_1
    //   220: aload_1
    //   221: athrow
    //   222: iconst_0
    //   223: istore_2
    //   224: iload_2
    //   225: tableswitch	default:+23->248, 0:+-222->3, 1:+141->366
    //   248: goto -245 -> 3
    //   251: iconst_1
    //   252: istore_2
    //   253: goto -29 -> 224
    //   256: iconst_0
    //   257: istore_2
    //   258: goto +24 -> 282
    //   261: iconst_1
    //   262: istore_2
    //   263: goto +19 -> 282
    //   266: aload 4
    //   268: invokestatic 644	o/HQ:ˏ	(Lcom/insidesecure/hce/MatrixHCECard;)Lo/HQ;
    //   271: astore 4
    //   273: aload 4
    //   275: aload_1
    //   276: invokevirtual 647	o/HQ:ॱ	(Lo/Ec;)V
    //   279: goto -63 -> 216
    //   282: iload_2
    //   283: tableswitch	default:+21->304, 0:+36->319, 1:+21->304
    //   304: aload_3
    //   305: invokeinterface 650 1 0
    //   310: ifeq +6 -> 316
    //   313: goto -91 -> 222
    //   316: goto -65 -> 251
    //   319: getstatic 32	ro/btrl/boot/ui/activity/SplashScreenActivity:ʾ	I
    //   322: bipush 49
    //   324: iadd
    //   325: istore_2
    //   326: iload_2
    //   327: sipush 128
    //   330: irem
    //   331: putstatic 34	ro/btrl/boot/ui/activity/SplashScreenActivity:ˈ	I
    //   334: iload_2
    //   335: iconst_2
    //   336: irem
    //   337: ifne +6 -> 343
    //   340: goto +9 -> 349
    //   343: goto -77 -> 266
    //   346: astore_1
    //   347: aload_1
    //   348: athrow
    //   349: aload 4
    //   351: invokestatic 644	o/HQ:ˏ	(Lcom/insidesecure/hce/MatrixHCECard;)Lo/HQ;
    //   354: aload_1
    //   355: invokevirtual 647	o/HQ:ॱ	(Lo/Ec;)V
    //   358: bipush 82
    //   360: iconst_0
    //   361: idiv
    //   362: istore_2
    //   363: goto -147 -> 216
    //   366: goto +6 -> 372
    //   369: goto +38 -> 407
    //   372: getstatic 34	ro/btrl/boot/ui/activity/SplashScreenActivity:ˈ	I
    //   375: istore_2
    //   376: iload_2
    //   377: bipush 103
    //   379: iadd
    //   380: istore_2
    //   381: iload_2
    //   382: sipush 128
    //   385: irem
    //   386: putstatic 32	ro/btrl/boot/ui/activity/SplashScreenActivity:ʾ	I
    //   389: iload_2
    //   390: iconst_2
    //   391: irem
    //   392: ifeq +6 -> 398
    //   395: goto +4 -> 399
    //   398: return
    //   399: new 607	java/lang/NullPointerException
    //   402: dup
    //   403: invokespecial 608	java/lang/NullPointerException:<init>	()V
    //   406: athrow
    //   407: aload_1
    //   408: invokevirtual 655	o/En:ˋ	()Ljava/util/List;
    //   411: invokeinterface 661 1 0
    //   416: astore_3
    //   417: goto -113 -> 304
    // Local variable table:
    //   start	length	slot	name	signature
    //   0	420	0	this	SplashScreenActivity
    //   0	420	1	paramEn	En
    //   223	169	2	i	int
    //   3	1	3	localObject1	Object
    //   16	13	3	localObject2	Object
    //   92	213	3	localObject3	Object
    //   416	1	3	localIterator	java.util.Iterator
    //   87	263	4	localObject4	Object
    //   81	106	5	localObject5	Object
    // Exception table:
    //   from	to	target	type
    //   30	83	16	finally
    //   106	205	92	finally
    //   3	13	219	java/lang/Exception
    //   17	22	219	java/lang/Exception
    //   26	28	219	java/lang/Exception
    //   28	30	219	java/lang/Exception
    //   83	89	219	java/lang/Exception
    //   93	98	219	java/lang/Exception
    //   102	104	219	java/lang/Exception
    //   104	106	219	java/lang/Exception
    //   266	273	219	java/lang/Exception
    //   273	279	219	java/lang/Exception
    //   381	389	219	java/lang/Exception
    //   372	376	346	java/lang/Exception
  }
  
  /* Error */
  private void ˎ(boolean paramBoolean)
  {
    // Byte code:
    //   0: goto +4 -> 4
    //   3: return
    //   4: goto +249 -> 253
    //   7: bipush 74
    //   9: iconst_0
    //   10: idiv
    //   11: istore_2
    //   12: iload_1
    //   13: ifeq +6 -> 19
    //   16: goto +177 -> 193
    //   19: goto +86 -> 105
    //   22: iload_2
    //   23: lookupswitch	default:+25->48, 6:+257->280, 86:+493->516
    //   48: goto +232 -> 280
    //   51: aload_0
    //   52: invokestatic 402	o/Ic:ˏ	(Landroid/content/Context;)Lo/Ic;
    //   55: iconst_0
    //   56: iconst_0
    //   57: invokevirtual 405	o/Ic:ˏ	(ZZ)Lo/j;
    //   60: invokevirtual 410	o/j:ˎ	()V
    //   63: goto +53 -> 116
    //   66: getstatic 32	ro/btrl/boot/ui/activity/SplashScreenActivity:ʾ	I
    //   69: istore_2
    //   70: iload_2
    //   71: bipush 65
    //   73: iadd
    //   74: istore_2
    //   75: iload_2
    //   76: sipush 128
    //   79: irem
    //   80: putstatic 34	ro/btrl/boot/ui/activity/SplashScreenActivity:ˈ	I
    //   83: iload_2
    //   84: iconst_2
    //   85: irem
    //   86: ifne +6 -> 92
    //   89: goto -82 -> 7
    //   92: goto +623 -> 715
    //   95: iconst_0
    //   96: istore_2
    //   97: goto +46 -> 143
    //   100: iconst_1
    //   101: istore_2
    //   102: goto +118 -> 220
    //   105: aload_0
    //   106: invokestatic 402	o/Ic:ˏ	(Landroid/content/Context;)Lo/Ic;
    //   109: invokevirtual 671	o/Ic:ʽ	()Lo/j;
    //   112: invokevirtual 410	o/j:ˎ	()V
    //   115: return
    //   116: getstatic 32	ro/btrl/boot/ui/activity/SplashScreenActivity:ʾ	I
    //   119: bipush 17
    //   121: iadd
    //   122: istore_2
    //   123: iload_2
    //   124: sipush 128
    //   127: irem
    //   128: putstatic 34	ro/btrl/boot/ui/activity/SplashScreenActivity:ˈ	I
    //   131: iload_2
    //   132: iconst_2
    //   133: irem
    //   134: ifne +6 -> 140
    //   137: goto +378 -> 515
    //   140: goto -137 -> 3
    //   143: iload_2
    //   144: tableswitch	default:+24->168, 0:+-141->3, 1:+-78->66
    //   168: return
    //   169: iconst_1
    //   170: istore_2
    //   171: goto -28 -> 143
    //   174: goto -123 -> 51
    //   177: iconst_0
    //   178: istore_2
    //   179: goto +41 -> 220
    //   182: astore 4
    //   184: aload 4
    //   186: athrow
    //   187: bipush 6
    //   189: istore_2
    //   190: goto -168 -> 22
    //   193: getstatic 34	ro/btrl/boot/ui/activity/SplashScreenActivity:ˈ	I
    //   196: bipush 11
    //   198: iadd
    //   199: istore_2
    //   200: iload_2
    //   201: sipush 128
    //   204: irem
    //   205: putstatic 32	ro/btrl/boot/ui/activity/SplashScreenActivity:ʾ	I
    //   208: iload_2
    //   209: iconst_2
    //   210: irem
    //   211: ifeq +6 -> 217
    //   214: goto -40 -> 174
    //   217: goto -166 -> 51
    //   220: iload_2
    //   221: tableswitch	default:+23->244, 0:+-116->105, 1:+-28->193
    //   244: goto -51 -> 193
    //   247: bipush 86
    //   249: istore_2
    //   250: goto -228 -> 22
    //   253: getstatic 32	ro/btrl/boot/ui/activity/SplashScreenActivity:ʾ	I
    //   256: bipush 69
    //   258: iadd
    //   259: istore_2
    //   260: iload_2
    //   261: sipush 128
    //   264: irem
    //   265: putstatic 34	ro/btrl/boot/ui/activity/SplashScreenActivity:ˈ	I
    //   268: iload_2
    //   269: iconst_2
    //   270: irem
    //   271: ifne +6 -> 277
    //   274: goto -87 -> 187
    //   277: goto -30 -> 247
    //   280: goto +23 -> 303
    //   283: astore 4
    //   285: aload 4
    //   287: invokevirtual 419	java/lang/Throwable:getCause	()Ljava/lang/Throwable;
    //   290: astore 5
    //   292: aload 5
    //   294: ifnull +6 -> 300
    //   297: aload 5
    //   299: athrow
    //   300: aload 4
    //   302: athrow
    //   303: aload_0
    //   304: invokevirtual 435	android/content/Context:getResources	()Landroid/content/res/Resources;
    //   307: ldc_w 672
    //   310: invokevirtual 442	android/content/res/Resources:getString	(I)Ljava/lang/String;
    //   313: iconst_5
    //   314: bipush 15
    //   316: invokevirtual 446	java/lang/String:substring	(II)Ljava/lang/String;
    //   319: iconst_4
    //   320: invokevirtual 450	java/lang/String:codePointAt	(I)I
    //   323: bipush 112
    //   325: isub
    //   326: aload_0
    //   327: invokevirtual 425	android/content/Context:getPackageName	()Ljava/lang/String;
    //   330: iconst_5
    //   331: invokevirtual 450	java/lang/String:codePointAt	(I)I
    //   334: sipush 299
    //   337: iadd
    //   338: aload_0
    //   339: invokevirtual 435	android/content/Context:getResources	()Landroid/content/res/Resources;
    //   342: ldc_w 579
    //   345: invokevirtual 442	android/content/res/Resources:getString	(I)Ljava/lang/String;
    //   348: iconst_0
    //   349: bipush 17
    //   351: invokevirtual 446	java/lang/String:substring	(II)Ljava/lang/String;
    //   354: iconst_1
    //   355: invokevirtual 450	java/lang/String:codePointAt	(I)I
    //   358: sipush 30227
    //   361: iadd
    //   362: i2c
    //   363: invokestatic 456	o/O:ˋ	(IIC)Ljava/lang/Object;
    //   366: checkcast 458	java/lang/Class
    //   369: ldc_w 570
    //   372: aconst_null
    //   373: invokevirtual 463	java/lang/Class:getMethod	(Ljava/lang/String;[Ljava/lang/Class;)Ljava/lang/reflect/Method;
    //   376: aconst_null
    //   377: aconst_null
    //   378: invokevirtual 469	java/lang/reflect/Method:invoke	(Ljava/lang/Object;[Ljava/lang/Object;)Ljava/lang/Object;
    //   381: astore 4
    //   383: goto +23 -> 406
    //   386: astore 4
    //   388: aload 4
    //   390: invokevirtual 419	java/lang/Throwable:getCause	()Ljava/lang/Throwable;
    //   393: astore 5
    //   395: aload 5
    //   397: ifnull +6 -> 403
    //   400: aload 5
    //   402: athrow
    //   403: aload 4
    //   405: athrow
    //   406: aload_0
    //   407: invokevirtual 435	android/content/Context:getResources	()Landroid/content/res/Resources;
    //   410: ldc_w 673
    //   413: invokevirtual 442	android/content/res/Resources:getString	(I)Ljava/lang/String;
    //   416: bipush 11
    //   418: bipush 16
    //   420: invokevirtual 446	java/lang/String:substring	(II)Ljava/lang/String;
    //   423: iconst_1
    //   424: invokevirtual 450	java/lang/String:codePointAt	(I)I
    //   427: sipush 247
    //   430: isub
    //   431: aload_0
    //   432: invokevirtual 435	android/content/Context:getResources	()Landroid/content/res/Resources;
    //   435: ldc_w 674
    //   438: invokevirtual 442	android/content/res/Resources:getString	(I)Ljava/lang/String;
    //   441: iconst_0
    //   442: bipush 7
    //   444: invokevirtual 446	java/lang/String:substring	(II)Ljava/lang/String;
    //   447: invokevirtual 431	java/lang/String:length	()I
    //   450: sipush 406
    //   453: iadd
    //   454: aload_0
    //   455: invokevirtual 516	android/content/Context:getApplicationInfo	()Landroid/content/pm/ApplicationInfo;
    //   458: getfield 521	android/content/pm/ApplicationInfo:targetSdkVersion	I
    //   461: sipush 30228
    //   464: iadd
    //   465: i2c
    //   466: invokestatic 456	o/O:ˋ	(IIC)Ljava/lang/Object;
    //   469: checkcast 458	java/lang/Class
    //   472: ldc_w 590
    //   475: aconst_null
    //   476: invokevirtual 463	java/lang/Class:getMethod	(Ljava/lang/String;[Ljava/lang/Class;)Ljava/lang/reflect/Method;
    //   479: aload 4
    //   481: aconst_null
    //   482: invokevirtual 469	java/lang/reflect/Method:invoke	(Ljava/lang/Object;[Ljava/lang/Object;)Ljava/lang/Object;
    //   485: checkcast 547	o/Gw
    //   488: astore 4
    //   490: getstatic 551	o/Gw:INACTIVE_PHONE_NUMBER	Lo/Gw;
    //   493: astore 5
    //   495: aload 4
    //   497: aload 5
    //   499: invokevirtual 597	o/Gw:equals	(Ljava/lang/Object;)Z
    //   502: istore_3
    //   503: iconst_0
    //   504: iconst_0
    //   505: idiv
    //   506: istore_2
    //   507: iload_3
    //   508: ifne +6 -> 514
    //   511: goto -445 -> 66
    //   514: return
    //   515: return
    //   516: goto +23 -> 539
    //   519: astore 4
    //   521: aload 4
    //   523: invokevirtual 419	java/lang/Throwable:getCause	()Ljava/lang/Throwable;
    //   526: astore 5
    //   528: aload 5
    //   530: ifnull +6 -> 536
    //   533: aload 5
    //   535: athrow
    //   536: aload 4
    //   538: athrow
    //   539: aload_0
    //   540: invokevirtual 516	android/content/Context:getApplicationInfo	()Landroid/content/pm/ApplicationInfo;
    //   543: getfield 521	android/content/pm/ApplicationInfo:targetSdkVersion	I
    //   546: bipush 21
    //   548: isub
    //   549: aload_0
    //   550: invokevirtual 435	android/content/Context:getResources	()Landroid/content/res/Resources;
    //   553: ldc_w 675
    //   556: invokevirtual 442	android/content/res/Resources:getString	(I)Ljava/lang/String;
    //   559: iconst_0
    //   560: iconst_5
    //   561: invokevirtual 446	java/lang/String:substring	(II)Ljava/lang/String;
    //   564: invokevirtual 431	java/lang/String:length	()I
    //   567: sipush 408
    //   570: iadd
    //   571: aload_0
    //   572: invokevirtual 425	android/content/Context:getPackageName	()Ljava/lang/String;
    //   575: iconst_1
    //   576: invokevirtual 450	java/lang/String:codePointAt	(I)I
    //   579: sipush 30142
    //   582: iadd
    //   583: i2c
    //   584: invokestatic 456	o/O:ˋ	(IIC)Ljava/lang/Object;
    //   587: checkcast 458	java/lang/Class
    //   590: ldc_w 570
    //   593: aconst_null
    //   594: invokevirtual 463	java/lang/Class:getMethod	(Ljava/lang/String;[Ljava/lang/Class;)Ljava/lang/reflect/Method;
    //   597: aconst_null
    //   598: aconst_null
    //   599: invokevirtual 469	java/lang/reflect/Method:invoke	(Ljava/lang/Object;[Ljava/lang/Object;)Ljava/lang/Object;
    //   602: astore 4
    //   604: goto +23 -> 627
    //   607: astore 4
    //   609: aload 4
    //   611: invokevirtual 419	java/lang/Throwable:getCause	()Ljava/lang/Throwable;
    //   614: astore 5
    //   616: aload 5
    //   618: ifnull +6 -> 624
    //   621: aload 5
    //   623: athrow
    //   624: aload 4
    //   626: athrow
    //   627: aload_0
    //   628: invokevirtual 435	android/content/Context:getResources	()Landroid/content/res/Resources;
    //   631: ldc_w 676
    //   634: invokevirtual 442	android/content/res/Resources:getString	(I)Ljava/lang/String;
    //   637: iconst_0
    //   638: bipush 10
    //   640: invokevirtual 446	java/lang/String:substring	(II)Ljava/lang/String;
    //   643: invokevirtual 431	java/lang/String:length	()I
    //   646: bipush 6
    //   648: isub
    //   649: aload_0
    //   650: invokevirtual 425	android/content/Context:getPackageName	()Ljava/lang/String;
    //   653: invokevirtual 431	java/lang/String:length	()I
    //   656: sipush 402
    //   659: iadd
    //   660: aload_0
    //   661: invokevirtual 425	android/content/Context:getPackageName	()Ljava/lang/String;
    //   664: bipush 9
    //   666: invokevirtual 450	java/lang/String:codePointAt	(I)I
    //   669: sipush 30156
    //   672: iadd
    //   673: i2c
    //   674: invokestatic 456	o/O:ˋ	(IIC)Ljava/lang/Object;
    //   677: checkcast 458	java/lang/Class
    //   680: ldc_w 590
    //   683: aconst_null
    //   684: invokevirtual 463	java/lang/Class:getMethod	(Ljava/lang/String;[Ljava/lang/Class;)Ljava/lang/reflect/Method;
    //   687: aload 4
    //   689: aconst_null
    //   690: invokevirtual 469	java/lang/reflect/Method:invoke	(Ljava/lang/Object;[Ljava/lang/Object;)Ljava/lang/Object;
    //   693: checkcast 547	o/Gw
    //   696: astore 4
    //   698: aload 4
    //   700: getstatic 551	o/Gw:INACTIVE_PHONE_NUMBER	Lo/Gw;
    //   703: invokevirtual 597	o/Gw:equals	(Ljava/lang/Object;)Z
    //   706: ifne +6 -> 712
    //   709: goto -540 -> 169
    //   712: goto -617 -> 95
    //   715: iload_1
    //   716: ifeq +6 -> 722
    //   719: goto -619 -> 100
    //   722: goto -545 -> 177
    // Local variable table:
    //   start	length	slot	name	signature
    //   0	725	0	this	SplashScreenActivity
    //   0	725	1	paramBoolean	boolean
    //   11	496	2	i	int
    //   502	6	3	bool	boolean
    //   182	3	4	localException	Exception
    //   283	18	4	localObject1	Object
    //   381	1	4	localObject2	Object
    //   386	94	4	localObject3	Object
    //   488	8	4	localGw1	o.Gw
    //   519	18	4	localObject4	Object
    //   602	1	4	localObject5	Object
    //   607	81	4	localObject6	Object
    //   696	3	4	localGw2	o.Gw
    //   290	332	5	localObject7	Object
    // Exception table:
    //   from	to	target	type
    //   66	70	182	java/lang/Exception
    //   75	83	182	java/lang/Exception
    //   285	292	182	java/lang/Exception
    //   297	300	182	java/lang/Exception
    //   300	303	182	java/lang/Exception
    //   388	395	182	java/lang/Exception
    //   400	403	182	java/lang/Exception
    //   403	406	182	java/lang/Exception
    //   490	495	182	java/lang/Exception
    //   495	507	182	java/lang/Exception
    //   303	383	283	finally
    //   406	490	386	finally
    //   539	604	519	finally
    //   627	698	607	finally
  }
  
  /* Error */
  private void ˎˎ()
  {
    // Byte code:
    //   0: goto +415 -> 415
    //   3: goto +17 -> 20
    //   6: astore_2
    //   7: aload_2
    //   8: invokevirtual 419	java/lang/Throwable:getCause	()Ljava/lang/Throwable;
    //   11: astore_3
    //   12: aload_3
    //   13: ifnull +5 -> 18
    //   16: aload_3
    //   17: athrow
    //   18: aload_2
    //   19: athrow
    //   20: aload_0
    //   21: invokevirtual 425	android/content/Context:getPackageName	()Ljava/lang/String;
    //   24: bipush 8
    //   26: invokevirtual 450	java/lang/String:codePointAt	(I)I
    //   29: bipush 108
    //   31: isub
    //   32: aload_0
    //   33: invokevirtual 435	android/content/Context:getResources	()Landroid/content/res/Resources;
    //   36: ldc_w 677
    //   39: invokevirtual 442	android/content/res/Resources:getString	(I)Ljava/lang/String;
    //   42: iconst_0
    //   43: iconst_5
    //   44: invokevirtual 446	java/lang/String:substring	(II)Ljava/lang/String;
    //   47: invokevirtual 431	java/lang/String:length	()I
    //   50: sipush 408
    //   53: iadd
    //   54: aload_0
    //   55: invokevirtual 435	android/content/Context:getResources	()Landroid/content/res/Resources;
    //   58: ldc_w 678
    //   61: invokevirtual 442	android/content/res/Resources:getString	(I)Ljava/lang/String;
    //   64: iconst_0
    //   65: iconst_5
    //   66: invokevirtual 446	java/lang/String:substring	(II)Ljava/lang/String;
    //   69: iconst_4
    //   70: invokevirtual 450	java/lang/String:codePointAt	(I)I
    //   73: sipush 30073
    //   76: iadd
    //   77: i2c
    //   78: invokestatic 456	o/O:ˋ	(IIC)Ljava/lang/Object;
    //   81: checkcast 458	java/lang/Class
    //   84: ldc_w 570
    //   87: aconst_null
    //   88: invokevirtual 463	java/lang/Class:getMethod	(Ljava/lang/String;[Ljava/lang/Class;)Ljava/lang/reflect/Method;
    //   91: aconst_null
    //   92: aconst_null
    //   93: invokevirtual 469	java/lang/reflect/Method:invoke	(Ljava/lang/Object;[Ljava/lang/Object;)Ljava/lang/Object;
    //   96: astore_2
    //   97: goto +17 -> 114
    //   100: astore_2
    //   101: aload_2
    //   102: invokevirtual 419	java/lang/Throwable:getCause	()Ljava/lang/Throwable;
    //   105: astore_3
    //   106: aload_3
    //   107: ifnull +5 -> 112
    //   110: aload_3
    //   111: athrow
    //   112: aload_2
    //   113: athrow
    //   114: aload_0
    //   115: invokevirtual 435	android/content/Context:getResources	()Landroid/content/res/Resources;
    //   118: ldc_w 679
    //   121: invokevirtual 442	android/content/res/Resources:getString	(I)Ljava/lang/String;
    //   124: iconst_0
    //   125: iconst_4
    //   126: invokevirtual 446	java/lang/String:substring	(II)Ljava/lang/String;
    //   129: iconst_2
    //   130: invokevirtual 450	java/lang/String:codePointAt	(I)I
    //   133: bipush 7
    //   135: isub
    //   136: aload_0
    //   137: invokevirtual 516	android/content/Context:getApplicationInfo	()Landroid/content/pm/ApplicationInfo;
    //   140: getfield 521	android/content/pm/ApplicationInfo:targetSdkVersion	I
    //   143: sipush 388
    //   146: iadd
    //   147: aload_0
    //   148: invokevirtual 435	android/content/Context:getResources	()Landroid/content/res/Resources;
    //   151: ldc_w 680
    //   154: invokevirtual 442	android/content/res/Resources:getString	(I)Ljava/lang/String;
    //   157: iconst_0
    //   158: iconst_4
    //   159: invokevirtual 446	java/lang/String:substring	(II)Ljava/lang/String;
    //   162: invokevirtual 431	java/lang/String:length	()I
    //   165: sipush 30249
    //   168: iadd
    //   169: i2c
    //   170: invokestatic 456	o/O:ˋ	(IIC)Ljava/lang/Object;
    //   173: checkcast 458	java/lang/Class
    //   176: ldc_w 682
    //   179: iconst_1
    //   180: anewarray 458	java/lang/Class
    //   183: dup
    //   184: iconst_0
    //   185: ldc_w 427
    //   188: aastore
    //   189: invokevirtual 463	java/lang/Class:getMethod	(Ljava/lang/String;[Ljava/lang/Class;)Ljava/lang/reflect/Method;
    //   192: aload_2
    //   193: iconst_1
    //   194: anewarray 478	java/lang/Object
    //   197: dup
    //   198: iconst_0
    //   199: ldc_w 684
    //   202: aastore
    //   203: invokevirtual 469	java/lang/reflect/Method:invoke	(Ljava/lang/Object;[Ljava/lang/Object;)Ljava/lang/Object;
    //   206: pop
    //   207: return
    //   208: astore_2
    //   209: aload_2
    //   210: athrow
    //   211: goto +17 -> 228
    //   214: astore_2
    //   215: aload_2
    //   216: invokevirtual 419	java/lang/Throwable:getCause	()Ljava/lang/Throwable;
    //   219: astore_3
    //   220: aload_3
    //   221: ifnull +5 -> 226
    //   224: aload_3
    //   225: athrow
    //   226: aload_2
    //   227: athrow
    //   228: aload_0
    //   229: invokevirtual 425	android/content/Context:getPackageName	()Ljava/lang/String;
    //   232: invokevirtual 431	java/lang/String:length	()I
    //   235: bipush 7
    //   237: isub
    //   238: aload_0
    //   239: invokevirtual 435	android/content/Context:getResources	()Landroid/content/res/Resources;
    //   242: ldc_w 685
    //   245: invokevirtual 442	android/content/res/Resources:getString	(I)Ljava/lang/String;
    //   248: iconst_0
    //   249: iconst_4
    //   250: invokevirtual 446	java/lang/String:substring	(II)Ljava/lang/String;
    //   253: invokevirtual 431	java/lang/String:length	()I
    //   256: sipush 409
    //   259: iadd
    //   260: aload_0
    //   261: invokevirtual 516	android/content/Context:getApplicationInfo	()Landroid/content/pm/ApplicationInfo;
    //   264: getfield 521	android/content/pm/ApplicationInfo:targetSdkVersion	I
    //   267: sipush 30228
    //   270: iadd
    //   271: i2c
    //   272: invokestatic 456	o/O:ˋ	(IIC)Ljava/lang/Object;
    //   275: checkcast 458	java/lang/Class
    //   278: ldc_w 570
    //   281: aconst_null
    //   282: invokevirtual 463	java/lang/Class:getMethod	(Ljava/lang/String;[Ljava/lang/Class;)Ljava/lang/reflect/Method;
    //   285: aconst_null
    //   286: aconst_null
    //   287: invokevirtual 469	java/lang/reflect/Method:invoke	(Ljava/lang/Object;[Ljava/lang/Object;)Ljava/lang/Object;
    //   290: astore_2
    //   291: goto +17 -> 308
    //   294: astore_3
    //   295: aload_3
    //   296: invokevirtual 419	java/lang/Throwable:getCause	()Ljava/lang/Throwable;
    //   299: astore_2
    //   300: aload_2
    //   301: ifnull +5 -> 306
    //   304: aload_2
    //   305: athrow
    //   306: aload_3
    //   307: athrow
    //   308: aload_0
    //   309: invokevirtual 435	android/content/Context:getResources	()Landroid/content/res/Resources;
    //   312: ldc_w 686
    //   315: invokevirtual 442	android/content/res/Resources:getString	(I)Ljava/lang/String;
    //   318: bipush 7
    //   320: bipush 74
    //   322: invokevirtual 446	java/lang/String:substring	(II)Ljava/lang/String;
    //   325: bipush 6
    //   327: invokevirtual 450	java/lang/String:codePointAt	(I)I
    //   330: sipush 240
    //   333: isub
    //   334: aload_0
    //   335: invokevirtual 435	android/content/Context:getResources	()Landroid/content/res/Resources;
    //   338: ldc_w 687
    //   341: invokevirtual 442	android/content/res/Resources:getString	(I)Ljava/lang/String;
    //   344: iconst_0
    //   345: bipush 7
    //   347: invokevirtual 446	java/lang/String:substring	(II)Ljava/lang/String;
    //   350: iconst_5
    //   351: invokevirtual 450	java/lang/String:codePointAt	(I)I
    //   354: sipush 222
    //   357: iadd
    //   358: aload_0
    //   359: invokevirtual 516	android/content/Context:getApplicationInfo	()Landroid/content/pm/ApplicationInfo;
    //   362: getfield 521	android/content/pm/ApplicationInfo:targetSdkVersion	I
    //   365: sipush 30228
    //   368: iadd
    //   369: i2c
    //   370: invokestatic 456	o/O:ˋ	(IIC)Ljava/lang/Object;
    //   373: checkcast 458	java/lang/Class
    //   376: ldc_w 682
    //   379: iconst_1
    //   380: anewarray 458	java/lang/Class
    //   383: dup
    //   384: iconst_0
    //   385: ldc_w 427
    //   388: aastore
    //   389: invokevirtual 463	java/lang/Class:getMethod	(Ljava/lang/String;[Ljava/lang/Class;)Ljava/lang/reflect/Method;
    //   392: aload_2
    //   393: iconst_1
    //   394: anewarray 478	java/lang/Object
    //   397: dup
    //   398: iconst_0
    //   399: ldc_w 684
    //   402: aastore
    //   403: invokevirtual 469	java/lang/reflect/Method:invoke	(Ljava/lang/Object;[Ljava/lang/Object;)Ljava/lang/Object;
    //   406: pop
    //   407: new 607	java/lang/NullPointerException
    //   410: dup
    //   411: invokespecial 608	java/lang/NullPointerException:<init>	()V
    //   414: athrow
    //   415: getstatic 32	ro/btrl/boot/ui/activity/SplashScreenActivity:ʾ	I
    //   418: bipush 33
    //   420: iadd
    //   421: istore_1
    //   422: iload_1
    //   423: sipush 128
    //   426: irem
    //   427: putstatic 34	ro/btrl/boot/ui/activity/SplashScreenActivity:ˈ	I
    //   430: iload_1
    //   431: iconst_2
    //   432: irem
    //   433: ifne +6 -> 439
    //   436: goto +35 -> 471
    //   439: goto +38 -> 477
    //   442: iload_1
    //   443: lookupswitch	default:+25->468, 39:+-232->211, 90:+-440->3
    //   468: goto -257 -> 211
    //   471: bipush 39
    //   473: istore_1
    //   474: goto -32 -> 442
    //   477: bipush 90
    //   479: istore_1
    //   480: goto -38 -> 442
    // Local variable table:
    //   start	length	slot	name	signature
    //   0	483	0	this	SplashScreenActivity
    //   421	59	1	i	int
    //   6	13	2	localObject1	Object
    //   96	1	2	localObject2	Object
    //   100	93	2	localObject3	Object
    //   208	2	2	localException	Exception
    //   214	13	2	localObject4	Object
    //   290	103	2	localObject5	Object
    //   11	214	3	localThrowable	Throwable
    //   294	13	3	localObject6	Object
    // Exception table:
    //   from	to	target	type
    //   20	97	6	finally
    //   114	207	100	finally
    //   215	220	208	java/lang/Exception
    //   224	226	208	java/lang/Exception
    //   226	228	208	java/lang/Exception
    //   295	300	208	java/lang/Exception
    //   304	306	208	java/lang/Exception
    //   306	308	208	java/lang/Exception
    //   407	415	208	java/lang/Exception
    //   228	291	214	finally
    //   308	407	294	finally
  }
  
  /* Error */
  private void ˏ(o.Gw paramGw)
  {
    // Byte code:
    //   0: goto +1197 -> 1197
    //   3: aload_1
    //   4: iconst_2
    //   5: anewarray 547	o/Gw
    //   8: dup
    //   9: iconst_0
    //   10: getstatic 690	o/Gw:ACTIVE_REGISTERED	Lo/Gw;
    //   13: aastore
    //   14: dup
    //   15: iconst_1
    //   16: getstatic 693	o/Gw:PRE_REGISTERED	Lo/Gw;
    //   19: aastore
    //   20: invokevirtual 696	o/Gw:ˎ	([Lo/Gw;)Z
    //   23: ifeq +6 -> 29
    //   26: goto +734 -> 760
    //   29: aload_0
    //   30: invokevirtual 425	android/content/Context:getPackageName	()Ljava/lang/String;
    //   33: invokevirtual 431	java/lang/String:length	()I
    //   36: bipush 11
    //   38: isub
    //   39: aload_0
    //   40: invokevirtual 516	android/content/Context:getApplicationInfo	()Landroid/content/pm/ApplicationInfo;
    //   43: getfield 521	android/content/pm/ApplicationInfo:targetSdkVersion	I
    //   46: bipush 90
    //   48: iadd
    //   49: i2c
    //   50: aload_0
    //   51: invokevirtual 435	android/content/Context:getResources	()Landroid/content/res/Resources;
    //   54: ldc_w 697
    //   57: invokevirtual 442	android/content/res/Resources:getString	(I)Ljava/lang/String;
    //   60: iconst_0
    //   61: iconst_1
    //   62: invokevirtual 446	java/lang/String:substring	(II)Ljava/lang/String;
    //   65: invokevirtual 431	java/lang/String:length	()I
    //   68: iconst_5
    //   69: iadd
    //   70: invokestatic 523	ro/btrl/boot/ui/activity/SplashScreenActivity:ˊ	(ICI)Ljava/lang/String;
    //   73: invokevirtual 526	java/lang/String:intern	()Ljava/lang/String;
    //   76: astore_1
    //   77: aload_0
    //   78: invokevirtual 425	android/content/Context:getPackageName	()Ljava/lang/String;
    //   81: invokevirtual 431	java/lang/String:length	()I
    //   84: sipush 180
    //   87: iadd
    //   88: aload_0
    //   89: invokevirtual 425	android/content/Context:getPackageName	()Ljava/lang/String;
    //   92: invokevirtual 431	java/lang/String:length	()I
    //   95: ldc_w 698
    //   98: iadd
    //   99: i2c
    //   100: aload_0
    //   101: invokevirtual 435	android/content/Context:getResources	()Landroid/content/res/Resources;
    //   104: ldc_w 699
    //   107: invokevirtual 442	android/content/res/Resources:getString	(I)Ljava/lang/String;
    //   110: iconst_0
    //   111: iconst_4
    //   112: invokevirtual 446	java/lang/String:substring	(II)Ljava/lang/String;
    //   115: invokevirtual 431	java/lang/String:length	()I
    //   118: bipush 47
    //   120: iadd
    //   121: invokestatic 523	ro/btrl/boot/ui/activity/SplashScreenActivity:ˊ	(ICI)Ljava/lang/String;
    //   124: invokevirtual 526	java/lang/String:intern	()Ljava/lang/String;
    //   127: astore_3
    //   128: goto +17 -> 145
    //   131: astore_1
    //   132: aload_1
    //   133: invokevirtual 419	java/lang/Throwable:getCause	()Ljava/lang/Throwable;
    //   136: astore_3
    //   137: aload_3
    //   138: ifnull +5 -> 143
    //   141: aload_3
    //   142: athrow
    //   143: aload_1
    //   144: athrow
    //   145: aload_0
    //   146: invokevirtual 435	android/content/Context:getResources	()Landroid/content/res/Resources;
    //   149: ldc_w 700
    //   152: invokevirtual 442	android/content/res/Resources:getString	(I)Ljava/lang/String;
    //   155: iconst_0
    //   156: iconst_4
    //   157: invokevirtual 446	java/lang/String:substring	(II)Ljava/lang/String;
    //   160: invokevirtual 431	java/lang/String:length	()I
    //   163: iconst_0
    //   164: iadd
    //   165: aload_0
    //   166: invokevirtual 435	android/content/Context:getResources	()Landroid/content/res/Resources;
    //   169: ldc_w 701
    //   172: invokevirtual 442	android/content/res/Resources:getString	(I)Ljava/lang/String;
    //   175: iconst_0
    //   176: iconst_5
    //   177: invokevirtual 446	java/lang/String:substring	(II)Ljava/lang/String;
    //   180: iconst_0
    //   181: invokevirtual 450	java/lang/String:codePointAt	(I)I
    //   184: bipush 37
    //   186: iadd
    //   187: aload_0
    //   188: invokevirtual 516	android/content/Context:getApplicationInfo	()Landroid/content/pm/ApplicationInfo;
    //   191: getfield 521	android/content/pm/ApplicationInfo:targetSdkVersion	I
    //   194: ldc_w 702
    //   197: iadd
    //   198: i2c
    //   199: invokestatic 456	o/O:ˋ	(IIC)Ljava/lang/Object;
    //   202: checkcast 458	java/lang/Class
    //   205: ldc_w 459
    //   208: iconst_2
    //   209: anewarray 458	java/lang/Class
    //   212: dup
    //   213: iconst_0
    //   214: ldc_w 427
    //   217: aastore
    //   218: dup
    //   219: iconst_1
    //   220: ldc_w 427
    //   223: aastore
    //   224: invokevirtual 463	java/lang/Class:getMethod	(Ljava/lang/String;[Ljava/lang/Class;)Ljava/lang/reflect/Method;
    //   227: aconst_null
    //   228: iconst_2
    //   229: anewarray 478	java/lang/Object
    //   232: dup
    //   233: iconst_0
    //   234: aload_1
    //   235: aastore
    //   236: dup
    //   237: iconst_1
    //   238: aload_3
    //   239: aastore
    //   240: invokevirtual 469	java/lang/reflect/Method:invoke	(Ljava/lang/Object;[Ljava/lang/Object;)Ljava/lang/Object;
    //   243: pop
    //   244: goto +17 -> 261
    //   247: astore_1
    //   248: aload_1
    //   249: invokevirtual 419	java/lang/Throwable:getCause	()Ljava/lang/Throwable;
    //   252: astore_3
    //   253: aload_3
    //   254: ifnull +5 -> 259
    //   257: aload_3
    //   258: athrow
    //   259: aload_1
    //   260: athrow
    //   261: aload_0
    //   262: invokevirtual 425	android/content/Context:getPackageName	()Ljava/lang/String;
    //   265: bipush 6
    //   267: invokevirtual 450	java/lang/String:codePointAt	(I)I
    //   270: bipush 105
    //   272: isub
    //   273: aload_0
    //   274: invokevirtual 516	android/content/Context:getApplicationInfo	()Landroid/content/pm/ApplicationInfo;
    //   277: getfield 521	android/content/pm/ApplicationInfo:targetSdkVersion	I
    //   280: iconst_1
    //   281: isub
    //   282: aload_0
    //   283: invokevirtual 435	android/content/Context:getResources	()Landroid/content/res/Resources;
    //   286: ldc_w 703
    //   289: invokevirtual 442	android/content/res/Resources:getString	(I)Ljava/lang/String;
    //   292: iconst_0
    //   293: iconst_5
    //   294: invokevirtual 446	java/lang/String:substring	(II)Ljava/lang/String;
    //   297: invokevirtual 431	java/lang/String:length	()I
    //   300: iconst_5
    //   301: isub
    //   302: i2c
    //   303: invokestatic 456	o/O:ˋ	(IIC)Ljava/lang/Object;
    //   306: checkcast 458	java/lang/Class
    //   309: ldc_w 459
    //   312: aconst_null
    //   313: invokevirtual 463	java/lang/Class:getMethod	(Ljava/lang/String;[Ljava/lang/Class;)Ljava/lang/reflect/Method;
    //   316: aconst_null
    //   317: aconst_null
    //   318: invokevirtual 469	java/lang/reflect/Method:invoke	(Ljava/lang/Object;[Ljava/lang/Object;)Ljava/lang/Object;
    //   321: astore_3
    //   322: aload_0
    //   323: invokevirtual 473	ro/btrl/boot/ui/activity/SplashScreenActivity:ॱˊ	()Landroid/content/Context;
    //   326: astore_1
    //   327: goto +17 -> 344
    //   330: astore_1
    //   331: aload_1
    //   332: invokevirtual 419	java/lang/Throwable:getCause	()Ljava/lang/Throwable;
    //   335: astore_3
    //   336: aload_3
    //   337: ifnull +5 -> 342
    //   340: aload_3
    //   341: athrow
    //   342: aload_1
    //   343: athrow
    //   344: aload_0
    //   345: invokevirtual 425	android/content/Context:getPackageName	()Ljava/lang/String;
    //   348: invokevirtual 431	java/lang/String:length	()I
    //   351: bipush 8
    //   353: isub
    //   354: aload_0
    //   355: invokevirtual 435	android/content/Context:getResources	()Landroid/content/res/Resources;
    //   358: ldc_w 704
    //   361: invokevirtual 442	android/content/res/Resources:getString	(I)Ljava/lang/String;
    //   364: iconst_0
    //   365: iconst_5
    //   366: invokevirtual 446	java/lang/String:substring	(II)Ljava/lang/String;
    //   369: iconst_0
    //   370: invokevirtual 450	java/lang/String:codePointAt	(I)I
    //   373: bipush 19
    //   375: iadd
    //   376: aload_0
    //   377: invokevirtual 425	android/content/Context:getPackageName	()Ljava/lang/String;
    //   380: invokevirtual 431	java/lang/String:length	()I
    //   383: bipush 11
    //   385: isub
    //   386: i2c
    //   387: invokestatic 456	o/O:ˋ	(IIC)Ljava/lang/Object;
    //   390: checkcast 458	java/lang/Class
    //   393: ldc_w 600
    //   396: iconst_1
    //   397: anewarray 458	java/lang/Class
    //   400: dup
    //   401: iconst_0
    //   402: ldc_w 421
    //   405: aastore
    //   406: invokevirtual 463	java/lang/Class:getMethod	(Ljava/lang/String;[Ljava/lang/Class;)Ljava/lang/reflect/Method;
    //   409: aload_3
    //   410: iconst_1
    //   411: anewarray 478	java/lang/Object
    //   414: dup
    //   415: iconst_0
    //   416: aload_1
    //   417: aastore
    //   418: invokevirtual 469	java/lang/reflect/Method:invoke	(Ljava/lang/Object;[Ljava/lang/Object;)Ljava/lang/Object;
    //   421: checkcast 480	java/lang/Boolean
    //   424: invokevirtual 484	java/lang/Boolean:booleanValue	()Z
    //   427: pop
    //   428: goto +35 -> 463
    //   431: iload_2
    //   432: lookupswitch	default:+28->460, 17:+696->1128, 89:+712->1144
    //   460: goto +668 -> 1128
    //   463: goto +697 -> 1160
    //   466: aload_0
    //   467: invokevirtual 435	android/content/Context:getResources	()Landroid/content/res/Resources;
    //   470: ldc_w 705
    //   473: invokevirtual 442	android/content/res/Resources:getString	(I)Ljava/lang/String;
    //   476: iconst_0
    //   477: iconst_4
    //   478: invokevirtual 446	java/lang/String:substring	(II)Ljava/lang/String;
    //   481: iconst_2
    //   482: invokevirtual 450	java/lang/String:codePointAt	(I)I
    //   485: bipush 11
    //   487: isub
    //   488: aload_0
    //   489: invokevirtual 425	android/content/Context:getPackageName	()Ljava/lang/String;
    //   492: invokevirtual 431	java/lang/String:length	()I
    //   495: bipush 104
    //   497: iadd
    //   498: i2c
    //   499: aload_0
    //   500: invokevirtual 435	android/content/Context:getResources	()Landroid/content/res/Resources;
    //   503: ldc_w 675
    //   506: invokevirtual 442	android/content/res/Resources:getString	(I)Ljava/lang/String;
    //   509: iconst_0
    //   510: iconst_5
    //   511: invokevirtual 446	java/lang/String:substring	(II)Ljava/lang/String;
    //   514: iconst_0
    //   515: invokevirtual 450	java/lang/String:codePointAt	(I)I
    //   518: iconst_1
    //   519: iadd
    //   520: invokestatic 523	ro/btrl/boot/ui/activity/SplashScreenActivity:ˊ	(ICI)Ljava/lang/String;
    //   523: invokevirtual 526	java/lang/String:intern	()Ljava/lang/String;
    //   526: astore_1
    //   527: new 539	java/lang/StringBuilder
    //   530: dup
    //   531: invokespecial 540	java/lang/StringBuilder:<init>	()V
    //   534: aload_0
    //   535: invokevirtual 425	android/content/Context:getPackageName	()Ljava/lang/String;
    //   538: invokevirtual 431	java/lang/String:length	()I
    //   541: sipush 149
    //   544: iadd
    //   545: aload_0
    //   546: invokevirtual 435	android/content/Context:getResources	()Landroid/content/res/Resources;
    //   549: ldc_w 706
    //   552: invokevirtual 442	android/content/res/Resources:getString	(I)Ljava/lang/String;
    //   555: iconst_0
    //   556: iconst_5
    //   557: invokevirtual 446	java/lang/String:substring	(II)Ljava/lang/String;
    //   560: invokevirtual 431	java/lang/String:length	()I
    //   563: ldc_w 707
    //   566: iadd
    //   567: i2c
    //   568: aload_0
    //   569: invokevirtual 425	android/content/Context:getPackageName	()Ljava/lang/String;
    //   572: invokevirtual 431	java/lang/String:length	()I
    //   575: bipush 18
    //   577: iadd
    //   578: invokestatic 523	ro/btrl/boot/ui/activity/SplashScreenActivity:ˊ	(ICI)Ljava/lang/String;
    //   581: invokevirtual 526	java/lang/String:intern	()Ljava/lang/String;
    //   584: invokevirtual 545	java/lang/StringBuilder:append	(Ljava/lang/String;)Ljava/lang/StringBuilder;
    //   587: getstatic 573	o/Gw:NOT_REGISTERED	Lo/Gw;
    //   590: invokevirtual 554	java/lang/StringBuilder:append	(Ljava/lang/Object;)Ljava/lang/StringBuilder;
    //   593: invokevirtual 557	java/lang/StringBuilder:toString	()Ljava/lang/String;
    //   596: astore_3
    //   597: goto +17 -> 614
    //   600: astore_3
    //   601: aload_3
    //   602: invokevirtual 419	java/lang/Throwable:getCause	()Ljava/lang/Throwable;
    //   605: astore_1
    //   606: aload_1
    //   607: ifnull +5 -> 612
    //   610: aload_1
    //   611: athrow
    //   612: aload_3
    //   613: athrow
    //   614: aload_0
    //   615: invokevirtual 435	android/content/Context:getResources	()Landroid/content/res/Resources;
    //   618: ldc_w 708
    //   621: invokevirtual 442	android/content/res/Resources:getString	(I)Ljava/lang/String;
    //   624: iconst_0
    //   625: iconst_5
    //   626: invokevirtual 446	java/lang/String:substring	(II)Ljava/lang/String;
    //   629: iconst_2
    //   630: invokevirtual 450	java/lang/String:codePointAt	(I)I
    //   633: bipush 7
    //   635: isub
    //   636: aload_0
    //   637: invokevirtual 435	android/content/Context:getResources	()Landroid/content/res/Resources;
    //   640: ldc_w 709
    //   643: invokevirtual 442	android/content/res/Resources:getString	(I)Ljava/lang/String;
    //   646: iconst_0
    //   647: iconst_4
    //   648: invokevirtual 446	java/lang/String:substring	(II)Ljava/lang/String;
    //   651: iconst_0
    //   652: invokevirtual 450	java/lang/String:codePointAt	(I)I
    //   655: bipush 37
    //   657: iadd
    //   658: aload_0
    //   659: invokevirtual 516	android/content/Context:getApplicationInfo	()Landroid/content/pm/ApplicationInfo;
    //   662: getfield 521	android/content/pm/ApplicationInfo:targetSdkVersion	I
    //   665: ldc_w 702
    //   668: iadd
    //   669: i2c
    //   670: invokestatic 456	o/O:ˋ	(IIC)Ljava/lang/Object;
    //   673: checkcast 458	java/lang/Class
    //   676: ldc_w 459
    //   679: iconst_2
    //   680: anewarray 458	java/lang/Class
    //   683: dup
    //   684: iconst_0
    //   685: ldc_w 427
    //   688: aastore
    //   689: dup
    //   690: iconst_1
    //   691: ldc_w 427
    //   694: aastore
    //   695: invokevirtual 463	java/lang/Class:getMethod	(Ljava/lang/String;[Ljava/lang/Class;)Ljava/lang/reflect/Method;
    //   698: aconst_null
    //   699: iconst_2
    //   700: anewarray 478	java/lang/Object
    //   703: dup
    //   704: iconst_0
    //   705: aload_1
    //   706: aastore
    //   707: dup
    //   708: iconst_1
    //   709: aload_3
    //   710: aastore
    //   711: invokevirtual 469	java/lang/reflect/Method:invoke	(Ljava/lang/Object;[Ljava/lang/Object;)Ljava/lang/Object;
    //   714: pop
    //   715: aload_0
    //   716: getstatic 714	o/Ea:ˋ	Lo/Ea$ˋ;
    //   719: aload_0
    //   720: invokevirtual 719	o/Ea$ˋ:ˋ	(Landroid/content/Context;)Lo/sz;
    //   723: invokestatic 724	o/ur:ˊ	()Lo/sy;
    //   726: invokevirtual 729	o/sz:ˎ	(Lo/sy;)Lo/sz;
    //   729: invokestatic 733	o/sB:ˋ	()Lo/sy;
    //   732: invokevirtual 735	o/sz:ˋ	(Lo/sy;)Lo/sz;
    //   735: new 11	ro/btrl/boot/ui/activity/SplashScreenActivity$3
    //   738: dup
    //   739: aload_0
    //   740: invokespecial 737	ro/btrl/boot/ui/activity/SplashScreenActivity$3:<init>	(Lro/btrl/boot/ui/activity/SplashScreenActivity;)V
    //   743: new 9	ro/btrl/boot/ui/activity/SplashScreenActivity$2
    //   746: dup
    //   747: aload_0
    //   748: invokespecial 738	ro/btrl/boot/ui/activity/SplashScreenActivity$2:<init>	(Lro/btrl/boot/ui/activity/SplashScreenActivity;)V
    //   751: invokevirtual 741	o/sz:ˊ	(Lo/sW;Lo/sW;)Lo/sH;
    //   754: putfield 743	ro/btrl/boot/ui/activity/SplashScreenActivity:ʽॱ	Lo/sH;
    //   757: goto +443 -> 1200
    //   760: aload_0
    //   761: invokevirtual 435	android/content/Context:getResources	()Landroid/content/res/Resources;
    //   764: ldc_w 529
    //   767: invokevirtual 442	android/content/res/Resources:getString	(I)Ljava/lang/String;
    //   770: iconst_0
    //   771: iconst_5
    //   772: invokevirtual 446	java/lang/String:substring	(II)Ljava/lang/String;
    //   775: invokevirtual 431	java/lang/String:length	()I
    //   778: iconst_5
    //   779: isub
    //   780: aload_0
    //   781: invokevirtual 435	android/content/Context:getResources	()Landroid/content/res/Resources;
    //   784: ldc_w 744
    //   787: invokevirtual 442	android/content/res/Resources:getString	(I)Ljava/lang/String;
    //   790: bipush 58
    //   792: bipush 64
    //   794: invokevirtual 446	java/lang/String:substring	(II)Ljava/lang/String;
    //   797: iconst_0
    //   798: invokevirtual 450	java/lang/String:codePointAt	(I)I
    //   801: bipush 71
    //   803: isub
    //   804: i2c
    //   805: aload_0
    //   806: invokevirtual 435	android/content/Context:getResources	()Landroid/content/res/Resources;
    //   809: ldc_w 558
    //   812: invokevirtual 442	android/content/res/Resources:getString	(I)Ljava/lang/String;
    //   815: iconst_0
    //   816: iconst_4
    //   817: invokevirtual 446	java/lang/String:substring	(II)Ljava/lang/String;
    //   820: iconst_2
    //   821: invokevirtual 450	java/lang/String:codePointAt	(I)I
    //   824: iconst_5
    //   825: isub
    //   826: invokestatic 523	ro/btrl/boot/ui/activity/SplashScreenActivity:ˊ	(ICI)Ljava/lang/String;
    //   829: invokevirtual 526	java/lang/String:intern	()Ljava/lang/String;
    //   832: astore_3
    //   833: new 539	java/lang/StringBuilder
    //   836: dup
    //   837: invokespecial 540	java/lang/StringBuilder:<init>	()V
    //   840: aload_0
    //   841: invokevirtual 516	android/content/Context:getApplicationInfo	()Landroid/content/pm/ApplicationInfo;
    //   844: getfield 521	android/content/pm/ApplicationInfo:targetSdkVersion	I
    //   847: sipush 135
    //   850: iadd
    //   851: aload_0
    //   852: invokevirtual 425	android/content/Context:getPackageName	()Ljava/lang/String;
    //   855: bipush 9
    //   857: invokevirtual 450	java/lang/String:codePointAt	(I)I
    //   860: ldc_w 745
    //   863: iadd
    //   864: i2c
    //   865: aload_0
    //   866: invokevirtual 435	android/content/Context:getResources	()Landroid/content/res/Resources;
    //   869: ldc_w 746
    //   872: invokevirtual 442	android/content/res/Resources:getString	(I)Ljava/lang/String;
    //   875: iconst_0
    //   876: iconst_4
    //   877: invokevirtual 446	java/lang/String:substring	(II)Ljava/lang/String;
    //   880: invokevirtual 431	java/lang/String:length	()I
    //   883: bipush 25
    //   885: iadd
    //   886: invokestatic 523	ro/btrl/boot/ui/activity/SplashScreenActivity:ˊ	(ICI)Ljava/lang/String;
    //   889: invokevirtual 526	java/lang/String:intern	()Ljava/lang/String;
    //   892: invokevirtual 545	java/lang/StringBuilder:append	(Ljava/lang/String;)Ljava/lang/StringBuilder;
    //   895: getstatic 690	o/Gw:ACTIVE_REGISTERED	Lo/Gw;
    //   898: invokevirtual 554	java/lang/StringBuilder:append	(Ljava/lang/Object;)Ljava/lang/StringBuilder;
    //   901: aload_0
    //   902: invokevirtual 435	android/content/Context:getResources	()Landroid/content/res/Resources;
    //   905: ldc_w 747
    //   908: invokevirtual 442	android/content/res/Resources:getString	(I)Ljava/lang/String;
    //   911: bipush 35
    //   913: bipush 40
    //   915: invokevirtual 446	java/lang/String:substring	(II)Ljava/lang/String;
    //   918: iconst_3
    //   919: invokevirtual 450	java/lang/String:codePointAt	(I)I
    //   922: bipush 63
    //   924: isub
    //   925: aload_0
    //   926: invokevirtual 435	android/content/Context:getResources	()Landroid/content/res/Resources;
    //   929: ldc_w 598
    //   932: invokevirtual 442	android/content/res/Resources:getString	(I)Ljava/lang/String;
    //   935: iconst_0
    //   936: bipush 9
    //   938: invokevirtual 446	java/lang/String:substring	(II)Ljava/lang/String;
    //   941: invokevirtual 431	java/lang/String:length	()I
    //   944: bipush 9
    //   946: isub
    //   947: i2c
    //   948: aload_0
    //   949: invokevirtual 435	android/content/Context:getResources	()Landroid/content/res/Resources;
    //   952: ldc_w 748
    //   955: invokevirtual 442	android/content/res/Resources:getString	(I)Ljava/lang/String;
    //   958: iconst_0
    //   959: iconst_5
    //   960: invokevirtual 446	java/lang/String:substring	(II)Ljava/lang/String;
    //   963: invokevirtual 431	java/lang/String:length	()I
    //   966: iconst_3
    //   967: isub
    //   968: invokestatic 523	ro/btrl/boot/ui/activity/SplashScreenActivity:ˊ	(ICI)Ljava/lang/String;
    //   971: invokevirtual 526	java/lang/String:intern	()Ljava/lang/String;
    //   974: invokevirtual 545	java/lang/StringBuilder:append	(Ljava/lang/String;)Ljava/lang/StringBuilder;
    //   977: getstatic 693	o/Gw:PRE_REGISTERED	Lo/Gw;
    //   980: invokevirtual 554	java/lang/StringBuilder:append	(Ljava/lang/Object;)Ljava/lang/StringBuilder;
    //   983: invokevirtual 557	java/lang/StringBuilder:toString	()Ljava/lang/String;
    //   986: astore_1
    //   987: goto +17 -> 1004
    //   990: astore_1
    //   991: aload_1
    //   992: invokevirtual 419	java/lang/Throwable:getCause	()Ljava/lang/Throwable;
    //   995: astore_3
    //   996: aload_3
    //   997: ifnull +5 -> 1002
    //   1000: aload_3
    //   1001: athrow
    //   1002: aload_1
    //   1003: athrow
    //   1004: aload_0
    //   1005: invokevirtual 425	android/content/Context:getPackageName	()Ljava/lang/String;
    //   1008: iconst_4
    //   1009: invokevirtual 450	java/lang/String:codePointAt	(I)I
    //   1012: bipush 112
    //   1014: isub
    //   1015: aload_0
    //   1016: invokevirtual 435	android/content/Context:getResources	()Landroid/content/res/Resources;
    //   1019: ldc_w 749
    //   1022: invokevirtual 442	android/content/res/Resources:getString	(I)Ljava/lang/String;
    //   1025: iconst_0
    //   1026: iconst_4
    //   1027: invokevirtual 446	java/lang/String:substring	(II)Ljava/lang/String;
    //   1030: iconst_2
    //   1031: invokevirtual 450	java/lang/String:codePointAt	(I)I
    //   1034: bipush 31
    //   1036: iadd
    //   1037: aload_0
    //   1038: invokevirtual 516	android/content/Context:getApplicationInfo	()Landroid/content/pm/ApplicationInfo;
    //   1041: getfield 521	android/content/pm/ApplicationInfo:targetSdkVersion	I
    //   1044: ldc_w 702
    //   1047: iadd
    //   1048: i2c
    //   1049: invokestatic 456	o/O:ˋ	(IIC)Ljava/lang/Object;
    //   1052: checkcast 458	java/lang/Class
    //   1055: ldc_w 459
    //   1058: iconst_2
    //   1059: anewarray 458	java/lang/Class
    //   1062: dup
    //   1063: iconst_0
    //   1064: ldc_w 427
    //   1067: aastore
    //   1068: dup
    //   1069: iconst_1
    //   1070: ldc_w 427
    //   1073: aastore
    //   1074: invokevirtual 463	java/lang/Class:getMethod	(Ljava/lang/String;[Ljava/lang/Class;)Ljava/lang/reflect/Method;
    //   1077: aconst_null
    //   1078: iconst_2
    //   1079: anewarray 478	java/lang/Object
    //   1082: dup
    //   1083: iconst_0
    //   1084: aload_3
    //   1085: aastore
    //   1086: dup
    //   1087: iconst_1
    //   1088: aload_1
    //   1089: aastore
    //   1090: invokevirtual 469	java/lang/reflect/Method:invoke	(Ljava/lang/Object;[Ljava/lang/Object;)Ljava/lang/Object;
    //   1093: pop
    //   1094: aload_0
    //   1095: invokespecial 751	ro/btrl/boot/ui/activity/SplashScreenActivity:ˉ	()V
    //   1098: goto -635 -> 463
    //   1101: getstatic 34	ro/btrl/boot/ui/activity/SplashScreenActivity:ˈ	I
    //   1104: bipush 71
    //   1106: iadd
    //   1107: istore_2
    //   1108: iload_2
    //   1109: sipush 128
    //   1112: irem
    //   1113: putstatic 32	ro/btrl/boot/ui/activity/SplashScreenActivity:ʾ	I
    //   1116: iload_2
    //   1117: iconst_2
    //   1118: irem
    //   1119: ifeq +6 -> 1125
    //   1122: goto +69 -> 1191
    //   1125: goto +60 -> 1185
    //   1128: aload_1
    //   1129: getstatic 573	o/Gw:NOT_REGISTERED	Lo/Gw;
    //   1132: invokevirtual 597	o/Gw:equals	(Ljava/lang/Object;)Z
    //   1135: ifeq +6 -> 1141
    //   1138: goto -672 -> 466
    //   1141: goto -1138 -> 3
    //   1144: aload_1
    //   1145: getstatic 573	o/Gw:NOT_REGISTERED	Lo/Gw;
    //   1148: invokevirtual 597	o/Gw:equals	(Ljava/lang/Object;)Z
    //   1151: pop
    //   1152: new 607	java/lang/NullPointerException
    //   1155: dup
    //   1156: invokespecial 608	java/lang/NullPointerException:<init>	()V
    //   1159: athrow
    //   1160: getstatic 32	ro/btrl/boot/ui/activity/SplashScreenActivity:ʾ	I
    //   1163: bipush 19
    //   1165: iadd
    //   1166: istore_2
    //   1167: iload_2
    //   1168: sipush 128
    //   1171: irem
    //   1172: putstatic 34	ro/btrl/boot/ui/activity/SplashScreenActivity:ˈ	I
    //   1175: iload_2
    //   1176: iconst_2
    //   1177: irem
    //   1178: ifne +6 -> 1184
    //   1181: goto +22 -> 1203
    //   1184: return
    //   1185: bipush 17
    //   1187: istore_2
    //   1188: goto -757 -> 431
    //   1191: bipush 89
    //   1193: istore_2
    //   1194: goto -763 -> 431
    //   1197: goto -96 -> 1101
    //   1200: goto -737 -> 463
    //   1203: return
    // Local variable table:
    //   start	length	slot	name	signature
    //   0	1204	0	this	SplashScreenActivity
    //   0	1204	1	paramGw	o.Gw
    //   431	763	2	i	int
    //   127	470	3	localObject1	Object
    //   600	110	3	localObject2	Object
    //   832	253	3	localObject3	Object
    // Exception table:
    //   from	to	target	type
    //   145	244	131	finally
    //   261	322	247	finally
    //   344	428	330	finally
    //   614	715	600	finally
    //   1004	1094	990	finally
  }
  
  /* Error */
  private void ॱ(String paramString)
  {
    // Byte code:
    //   0: goto +243 -> 243
    //   3: aload_0
    //   4: invokevirtual 435	android/content/Context:getResources	()Landroid/content/res/Resources;
    //   7: ldc_w 756
    //   10: invokevirtual 442	android/content/res/Resources:getString	(I)Ljava/lang/String;
    //   13: iconst_0
    //   14: iconst_5
    //   15: invokevirtual 446	java/lang/String:substring	(II)Ljava/lang/String;
    //   18: iconst_2
    //   19: invokevirtual 450	java/lang/String:codePointAt	(I)I
    //   22: bipush 11
    //   24: isub
    //   25: aload_0
    //   26: invokevirtual 516	android/content/Context:getApplicationInfo	()Landroid/content/pm/ApplicationInfo;
    //   29: getfield 521	android/content/pm/ApplicationInfo:targetSdkVersion	I
    //   32: bipush 90
    //   34: iadd
    //   35: i2c
    //   36: aload_0
    //   37: invokevirtual 435	android/content/Context:getResources	()Landroid/content/res/Resources;
    //   40: ldc_w 757
    //   43: invokevirtual 442	android/content/res/Resources:getString	(I)Ljava/lang/String;
    //   46: iconst_0
    //   47: iconst_4
    //   48: invokevirtual 446	java/lang/String:substring	(II)Ljava/lang/String;
    //   51: invokevirtual 431	java/lang/String:length	()I
    //   54: iconst_2
    //   55: iadd
    //   56: invokestatic 523	ro/btrl/boot/ui/activity/SplashScreenActivity:ˊ	(ICI)Ljava/lang/String;
    //   59: invokevirtual 526	java/lang/String:intern	()Ljava/lang/String;
    //   62: astore_1
    //   63: aload_0
    //   64: invokevirtual 516	android/content/Context:getApplicationInfo	()Landroid/content/pm/ApplicationInfo;
    //   67: getfield 521	android/content/pm/ApplicationInfo:targetSdkVersion	I
    //   70: sipush 263
    //   73: iadd
    //   74: aload_0
    //   75: invokevirtual 516	android/content/Context:getApplicationInfo	()Landroid/content/pm/ApplicationInfo;
    //   78: getfield 521	android/content/pm/ApplicationInfo:targetSdkVersion	I
    //   81: ldc_w 758
    //   84: iadd
    //   85: i2c
    //   86: aload_0
    //   87: invokevirtual 435	android/content/Context:getResources	()Landroid/content/res/Resources;
    //   90: ldc_w 759
    //   93: invokevirtual 442	android/content/res/Resources:getString	(I)Ljava/lang/String;
    //   96: iconst_0
    //   97: iconst_4
    //   98: invokevirtual 446	java/lang/String:substring	(II)Ljava/lang/String;
    //   101: invokevirtual 431	java/lang/String:length	()I
    //   104: bipush 52
    //   106: iadd
    //   107: invokestatic 523	ro/btrl/boot/ui/activity/SplashScreenActivity:ˊ	(ICI)Ljava/lang/String;
    //   110: invokevirtual 526	java/lang/String:intern	()Ljava/lang/String;
    //   113: astore_3
    //   114: goto +17 -> 131
    //   117: astore_1
    //   118: aload_1
    //   119: invokevirtual 419	java/lang/Throwable:getCause	()Ljava/lang/Throwable;
    //   122: astore_3
    //   123: aload_3
    //   124: ifnull +5 -> 129
    //   127: aload_3
    //   128: athrow
    //   129: aload_1
    //   130: athrow
    //   131: aload_0
    //   132: invokevirtual 435	android/content/Context:getResources	()Landroid/content/res/Resources;
    //   135: ldc_w 760
    //   138: invokevirtual 442	android/content/res/Resources:getString	(I)Ljava/lang/String;
    //   141: iconst_0
    //   142: iconst_4
    //   143: invokevirtual 446	java/lang/String:substring	(II)Ljava/lang/String;
    //   146: invokevirtual 431	java/lang/String:length	()I
    //   149: iconst_0
    //   150: iadd
    //   151: aload_0
    //   152: invokevirtual 516	android/content/Context:getApplicationInfo	()Landroid/content/pm/ApplicationInfo;
    //   155: getfield 521	android/content/pm/ApplicationInfo:targetSdkVersion	I
    //   158: bipush 17
    //   160: iadd
    //   161: aload_0
    //   162: invokevirtual 516	android/content/Context:getApplicationInfo	()Landroid/content/pm/ApplicationInfo;
    //   165: getfield 521	android/content/pm/ApplicationInfo:targetSdkVersion	I
    //   168: ldc_w 702
    //   171: iadd
    //   172: i2c
    //   173: invokestatic 456	o/O:ˋ	(IIC)Ljava/lang/Object;
    //   176: checkcast 458	java/lang/Class
    //   179: ldc_w 637
    //   182: iconst_2
    //   183: anewarray 458	java/lang/Class
    //   186: dup
    //   187: iconst_0
    //   188: ldc_w 427
    //   191: aastore
    //   192: dup
    //   193: iconst_1
    //   194: ldc_w 427
    //   197: aastore
    //   198: invokevirtual 463	java/lang/Class:getMethod	(Ljava/lang/String;[Ljava/lang/Class;)Ljava/lang/reflect/Method;
    //   201: aconst_null
    //   202: iconst_2
    //   203: anewarray 478	java/lang/Object
    //   206: dup
    //   207: iconst_0
    //   208: aload_1
    //   209: aastore
    //   210: dup
    //   211: iconst_1
    //   212: aload_3
    //   213: aastore
    //   214: invokevirtual 469	java/lang/reflect/Method:invoke	(Ljava/lang/Object;[Ljava/lang/Object;)Ljava/lang/Object;
    //   217: pop
    //   218: getstatic 34	ro/btrl/boot/ui/activity/SplashScreenActivity:ˈ	I
    //   221: bipush 81
    //   223: iadd
    //   224: istore_2
    //   225: iload_2
    //   226: sipush 128
    //   229: irem
    //   230: putstatic 32	ro/btrl/boot/ui/activity/SplashScreenActivity:ʾ	I
    //   233: iload_2
    //   234: iconst_2
    //   235: irem
    //   236: ifeq +6 -> 242
    //   239: goto +1166 -> 1405
    //   242: return
    //   243: goto +652 -> 895
    //   246: aload_0
    //   247: invokevirtual 435	android/content/Context:getResources	()Landroid/content/res/Resources;
    //   250: ldc_w 761
    //   253: invokevirtual 442	android/content/res/Resources:getString	(I)Ljava/lang/String;
    //   256: iconst_0
    //   257: iconst_4
    //   258: invokevirtual 446	java/lang/String:substring	(II)Ljava/lang/String;
    //   261: iconst_1
    //   262: invokevirtual 450	java/lang/String:codePointAt	(I)I
    //   265: bipush 26
    //   267: isub
    //   268: aload_0
    //   269: invokevirtual 516	android/content/Context:getApplicationInfo	()Landroid/content/pm/ApplicationInfo;
    //   272: getfield 521	android/content/pm/ApplicationInfo:targetSdkVersion	I
    //   275: bipush 90
    //   277: iadd
    //   278: i2c
    //   279: aload_0
    //   280: invokevirtual 435	android/content/Context:getResources	()Landroid/content/res/Resources;
    //   283: ldc_w 476
    //   286: invokevirtual 442	android/content/res/Resources:getString	(I)Ljava/lang/String;
    //   289: iconst_0
    //   290: iconst_5
    //   291: invokevirtual 446	java/lang/String:substring	(II)Ljava/lang/String;
    //   294: iconst_1
    //   295: invokevirtual 450	java/lang/String:codePointAt	(I)I
    //   298: bipush 20
    //   300: isub
    //   301: invokestatic 523	ro/btrl/boot/ui/activity/SplashScreenActivity:ˊ	(ICI)Ljava/lang/String;
    //   304: invokevirtual 526	java/lang/String:intern	()Ljava/lang/String;
    //   307: astore_3
    //   308: aload_0
    //   309: invokevirtual 425	android/content/Context:getPackageName	()Ljava/lang/String;
    //   312: invokevirtual 431	java/lang/String:length	()I
    //   315: sipush 260
    //   318: iadd
    //   319: aload_0
    //   320: invokevirtual 435	android/content/Context:getResources	()Landroid/content/res/Resources;
    //   323: ldc_w 672
    //   326: invokevirtual 442	android/content/res/Resources:getString	(I)Ljava/lang/String;
    //   329: iconst_5
    //   330: bipush 15
    //   332: invokevirtual 446	java/lang/String:substring	(II)Ljava/lang/String;
    //   335: invokevirtual 431	java/lang/String:length	()I
    //   338: sipush 2969
    //   341: iadd
    //   342: i2c
    //   343: aload_0
    //   344: invokevirtual 516	android/content/Context:getApplicationInfo	()Landroid/content/pm/ApplicationInfo;
    //   347: getfield 521	android/content/pm/ApplicationInfo:targetSdkVersion	I
    //   350: bipush 8
    //   352: isub
    //   353: invokestatic 523	ro/btrl/boot/ui/activity/SplashScreenActivity:ˊ	(ICI)Ljava/lang/String;
    //   356: invokevirtual 526	java/lang/String:intern	()Ljava/lang/String;
    //   359: astore 4
    //   361: goto +17 -> 378
    //   364: astore_1
    //   365: aload_1
    //   366: invokevirtual 419	java/lang/Throwable:getCause	()Ljava/lang/Throwable;
    //   369: astore_3
    //   370: aload_3
    //   371: ifnull +5 -> 376
    //   374: aload_3
    //   375: athrow
    //   376: aload_1
    //   377: athrow
    //   378: aload_0
    //   379: invokevirtual 435	android/content/Context:getResources	()Landroid/content/res/Resources;
    //   382: ldc_w 762
    //   385: invokevirtual 442	android/content/res/Resources:getString	(I)Ljava/lang/String;
    //   388: iconst_0
    //   389: iconst_5
    //   390: invokevirtual 446	java/lang/String:substring	(II)Ljava/lang/String;
    //   393: invokevirtual 431	java/lang/String:length	()I
    //   396: iconst_1
    //   397: isub
    //   398: aload_0
    //   399: invokevirtual 516	android/content/Context:getApplicationInfo	()Landroid/content/pm/ApplicationInfo;
    //   402: getfield 521	android/content/pm/ApplicationInfo:targetSdkVersion	I
    //   405: bipush 17
    //   407: iadd
    //   408: aload_0
    //   409: invokevirtual 516	android/content/Context:getApplicationInfo	()Landroid/content/pm/ApplicationInfo;
    //   412: getfield 521	android/content/pm/ApplicationInfo:targetSdkVersion	I
    //   415: ldc_w 702
    //   418: iadd
    //   419: i2c
    //   420: invokestatic 456	o/O:ˋ	(IIC)Ljava/lang/Object;
    //   423: checkcast 458	java/lang/Class
    //   426: ldc_w 459
    //   429: iconst_2
    //   430: anewarray 458	java/lang/Class
    //   433: dup
    //   434: iconst_0
    //   435: ldc_w 427
    //   438: aastore
    //   439: dup
    //   440: iconst_1
    //   441: ldc_w 427
    //   444: aastore
    //   445: invokevirtual 463	java/lang/Class:getMethod	(Ljava/lang/String;[Ljava/lang/Class;)Ljava/lang/reflect/Method;
    //   448: aconst_null
    //   449: iconst_2
    //   450: anewarray 478	java/lang/Object
    //   453: dup
    //   454: iconst_0
    //   455: aload_3
    //   456: aastore
    //   457: dup
    //   458: iconst_1
    //   459: aload 4
    //   461: aastore
    //   462: invokevirtual 469	java/lang/reflect/Method:invoke	(Ljava/lang/Object;[Ljava/lang/Object;)Ljava/lang/Object;
    //   465: pop
    //   466: invokestatic 767	o/Dt:ॱॱ	()Lo/Dt;
    //   469: invokestatic 772	com/google/firebase/iid/FirebaseInstanceId:ˊ	()Lcom/google/firebase/iid/FirebaseInstanceId;
    //   472: invokevirtual 774	com/google/firebase/iid/FirebaseInstanceId:ˏ	()Ljava/lang/String;
    //   475: invokevirtual 775	o/Dt:ˋ	(Ljava/lang/String;)V
    //   478: goto +17 -> 495
    //   481: astore_1
    //   482: aload_1
    //   483: invokevirtual 419	java/lang/Throwable:getCause	()Ljava/lang/Throwable;
    //   486: astore_3
    //   487: aload_3
    //   488: ifnull +5 -> 493
    //   491: aload_3
    //   492: athrow
    //   493: aload_1
    //   494: athrow
    //   495: aload_0
    //   496: invokevirtual 435	android/content/Context:getResources	()Landroid/content/res/Resources;
    //   499: ldc_w 776
    //   502: invokevirtual 442	android/content/res/Resources:getString	(I)Ljava/lang/String;
    //   505: iconst_0
    //   506: iconst_4
    //   507: invokevirtual 446	java/lang/String:substring	(II)Ljava/lang/String;
    //   510: iconst_3
    //   511: invokevirtual 450	java/lang/String:codePointAt	(I)I
    //   514: bipush 8
    //   516: isub
    //   517: aload_0
    //   518: invokevirtual 435	android/content/Context:getResources	()Landroid/content/res/Resources;
    //   521: ldc_w 624
    //   524: invokevirtual 442	android/content/res/Resources:getString	(I)Ljava/lang/String;
    //   527: bipush 11
    //   529: bipush 22
    //   531: invokevirtual 446	java/lang/String:substring	(II)Ljava/lang/String;
    //   534: invokevirtual 431	java/lang/String:length	()I
    //   537: bipush 124
    //   539: iadd
    //   540: aload_0
    //   541: invokevirtual 425	android/content/Context:getPackageName	()Ljava/lang/String;
    //   544: invokevirtual 431	java/lang/String:length	()I
    //   547: ldc_w 509
    //   550: iadd
    //   551: i2c
    //   552: invokestatic 456	o/O:ˋ	(IIC)Ljava/lang/Object;
    //   555: checkcast 458	java/lang/Class
    //   558: ldc_w 492
    //   561: aconst_null
    //   562: invokevirtual 463	java/lang/Class:getMethod	(Ljava/lang/String;[Ljava/lang/Class;)Ljava/lang/reflect/Method;
    //   565: aconst_null
    //   566: aconst_null
    //   567: invokevirtual 469	java/lang/reflect/Method:invoke	(Ljava/lang/Object;[Ljava/lang/Object;)Ljava/lang/Object;
    //   570: checkcast 494	o/It
    //   573: astore_3
    //   574: aload_0
    //   575: invokevirtual 435	android/content/Context:getResources	()Landroid/content/res/Resources;
    //   578: ldc_w 777
    //   581: invokevirtual 442	android/content/res/Resources:getString	(I)Ljava/lang/String;
    //   584: iconst_0
    //   585: iconst_4
    //   586: invokevirtual 446	java/lang/String:substring	(II)Ljava/lang/String;
    //   589: iconst_1
    //   590: invokevirtual 450	java/lang/String:codePointAt	(I)I
    //   593: bipush 22
    //   595: isub
    //   596: aload_0
    //   597: invokevirtual 435	android/content/Context:getResources	()Landroid/content/res/Resources;
    //   600: ldc_w 778
    //   603: invokevirtual 442	android/content/res/Resources:getString	(I)Ljava/lang/String;
    //   606: bipush 33
    //   608: bipush 34
    //   610: invokevirtual 446	java/lang/String:substring	(II)Ljava/lang/String;
    //   613: iconst_0
    //   614: invokevirtual 450	java/lang/String:codePointAt	(I)I
    //   617: sipush 254
    //   620: iadd
    //   621: aload_0
    //   622: invokevirtual 435	android/content/Context:getResources	()Landroid/content/res/Resources;
    //   625: ldc_w 779
    //   628: invokevirtual 442	android/content/res/Resources:getString	(I)Ljava/lang/String;
    //   631: iconst_0
    //   632: bipush 15
    //   634: invokevirtual 446	java/lang/String:substring	(II)Ljava/lang/String;
    //   637: invokevirtual 431	java/lang/String:length	()I
    //   640: ldc_w 780
    //   643: iadd
    //   644: i2c
    //   645: invokestatic 456	o/O:ˋ	(IIC)Ljava/lang/Object;
    //   648: checkcast 458	java/lang/Class
    //   651: ldc_w 459
    //   654: invokevirtual 784	java/lang/Class:getField	(Ljava/lang/String;)Ljava/lang/reflect/Field;
    //   657: aconst_null
    //   658: invokevirtual 790	java/lang/reflect/Field:get	(Ljava/lang/Object;)Ljava/lang/Object;
    //   661: astore 4
    //   663: goto +17 -> 680
    //   666: astore_1
    //   667: aload_1
    //   668: invokevirtual 419	java/lang/Throwable:getCause	()Ljava/lang/Throwable;
    //   671: astore_3
    //   672: aload_3
    //   673: ifnull +5 -> 678
    //   676: aload_3
    //   677: athrow
    //   678: aload_1
    //   679: athrow
    //   680: aload_0
    //   681: invokevirtual 435	android/content/Context:getResources	()Landroid/content/res/Resources;
    //   684: ldc_w 791
    //   687: invokevirtual 442	android/content/res/Resources:getString	(I)Ljava/lang/String;
    //   690: iconst_0
    //   691: bipush 8
    //   693: invokevirtual 446	java/lang/String:substring	(II)Ljava/lang/String;
    //   696: invokevirtual 431	java/lang/String:length	()I
    //   699: iconst_1
    //   700: isub
    //   701: aload_0
    //   702: invokevirtual 435	android/content/Context:getResources	()Landroid/content/res/Resources;
    //   705: ldc_w 792
    //   708: invokevirtual 442	android/content/res/Resources:getString	(I)Ljava/lang/String;
    //   711: iconst_0
    //   712: iconst_4
    //   713: invokevirtual 446	java/lang/String:substring	(II)Ljava/lang/String;
    //   716: iconst_2
    //   717: invokevirtual 450	java/lang/String:codePointAt	(I)I
    //   720: sipush 355
    //   723: iadd
    //   724: aload_0
    //   725: invokevirtual 425	android/content/Context:getPackageName	()Ljava/lang/String;
    //   728: invokevirtual 431	java/lang/String:length	()I
    //   731: bipush 11
    //   733: isub
    //   734: i2c
    //   735: invokestatic 456	o/O:ˋ	(IIC)Ljava/lang/Object;
    //   738: checkcast 458	java/lang/Class
    //   741: ldc_w 492
    //   744: aconst_null
    //   745: invokevirtual 463	java/lang/Class:getMethod	(Ljava/lang/String;[Ljava/lang/Class;)Ljava/lang/reflect/Method;
    //   748: aload 4
    //   750: aconst_null
    //   751: invokevirtual 469	java/lang/reflect/Method:invoke	(Ljava/lang/Object;[Ljava/lang/Object;)Ljava/lang/Object;
    //   754: astore 4
    //   756: goto +17 -> 773
    //   759: astore_1
    //   760: aload_1
    //   761: invokevirtual 419	java/lang/Throwable:getCause	()Ljava/lang/Throwable;
    //   764: astore_3
    //   765: aload_3
    //   766: ifnull +5 -> 771
    //   769: aload_3
    //   770: athrow
    //   771: aload_1
    //   772: athrow
    //   773: aload_0
    //   774: invokevirtual 425	android/content/Context:getPackageName	()Ljava/lang/String;
    //   777: invokevirtual 431	java/lang/String:length	()I
    //   780: bipush 7
    //   782: isub
    //   783: aload_0
    //   784: invokevirtual 425	android/content/Context:getPackageName	()Ljava/lang/String;
    //   787: iconst_2
    //   788: invokevirtual 450	java/lang/String:codePointAt	(I)I
    //   791: sipush 316
    //   794: iadd
    //   795: aload_0
    //   796: invokevirtual 435	android/content/Context:getResources	()Landroid/content/res/Resources;
    //   799: ldc_w 793
    //   802: invokevirtual 442	android/content/res/Resources:getString	(I)Ljava/lang/String;
    //   805: iconst_0
    //   806: iconst_4
    //   807: invokevirtual 446	java/lang/String:substring	(II)Ljava/lang/String;
    //   810: iconst_1
    //   811: invokevirtual 450	java/lang/String:codePointAt	(I)I
    //   814: ldc_w 794
    //   817: iadd
    //   818: i2c
    //   819: invokestatic 456	o/O:ˋ	(IIC)Ljava/lang/Object;
    //   822: checkcast 458	java/lang/Class
    //   825: ldc_w 492
    //   828: aconst_null
    //   829: invokevirtual 463	java/lang/Class:getMethod	(Ljava/lang/String;[Ljava/lang/Class;)Ljava/lang/reflect/Method;
    //   832: aload 4
    //   834: aconst_null
    //   835: invokevirtual 469	java/lang/reflect/Method:invoke	(Ljava/lang/Object;[Ljava/lang/Object;)Ljava/lang/Object;
    //   838: checkcast 427	java/lang/String
    //   841: astore 4
    //   843: aload_3
    //   844: new 796	o/EJ
    //   847: dup
    //   848: aload_1
    //   849: aload 4
    //   851: new 798	o/EE
    //   854: dup
    //   855: invokespecial 799	o/EE:<init>	()V
    //   858: invokespecial 802	o/EJ:<init>	(Ljava/lang/String;Ljava/lang/String;Lo/EE;)V
    //   861: invokeinterface 805 2 0
    //   866: new 13	ro/btrl/boot/ui/activity/SplashScreenActivity$4
    //   869: dup
    //   870: aload_0
    //   871: aload_0
    //   872: invokevirtual 808	ro/btrl/boot/ui/activity/SplashScreenActivity:getApplicationContext	()Landroid/content/Context;
    //   875: invokespecial 809	ro/btrl/boot/ui/activity/SplashScreenActivity$4:<init>	(Lro/btrl/boot/ui/activity/SplashScreenActivity;Landroid/content/Context;)V
    //   878: invokevirtual 813	ro/btrl/boot/ui/activity/SplashScreenActivity$4:ᐝ	()Lo/Ik;
    //   881: invokeinterface 506 2 0
    //   886: goto -668 -> 218
    //   889: astore_1
    //   890: aload_1
    //   891: athrow
    //   892: astore_1
    //   893: aload_1
    //   894: athrow
    //   895: aload_0
    //   896: invokevirtual 435	android/content/Context:getResources	()Landroid/content/res/Resources;
    //   899: ldc_w 814
    //   902: invokevirtual 442	android/content/res/Resources:getString	(I)Ljava/lang/String;
    //   905: iconst_0
    //   906: bipush 11
    //   908: invokevirtual 446	java/lang/String:substring	(II)Ljava/lang/String;
    //   911: iconst_3
    //   912: invokevirtual 450	java/lang/String:codePointAt	(I)I
    //   915: bipush 12
    //   917: isub
    //   918: aload_0
    //   919: invokevirtual 435	android/content/Context:getResources	()Landroid/content/res/Resources;
    //   922: ldc_w 815
    //   925: invokevirtual 442	android/content/res/Resources:getString	(I)Ljava/lang/String;
    //   928: iconst_0
    //   929: bipush 7
    //   931: invokevirtual 446	java/lang/String:substring	(II)Ljava/lang/String;
    //   934: iconst_5
    //   935: invokevirtual 450	java/lang/String:codePointAt	(I)I
    //   938: bipush 76
    //   940: isub
    //   941: i2c
    //   942: aload_0
    //   943: invokevirtual 516	android/content/Context:getApplicationInfo	()Landroid/content/pm/ApplicationInfo;
    //   946: getfield 521	android/content/pm/ApplicationInfo:targetSdkVersion	I
    //   949: bipush 19
    //   951: isub
    //   952: invokestatic 523	ro/btrl/boot/ui/activity/SplashScreenActivity:ˊ	(ICI)Ljava/lang/String;
    //   955: invokevirtual 526	java/lang/String:intern	()Ljava/lang/String;
    //   958: astore_3
    //   959: new 539	java/lang/StringBuilder
    //   962: dup
    //   963: invokespecial 540	java/lang/StringBuilder:<init>	()V
    //   966: aload_0
    //   967: invokevirtual 425	android/content/Context:getPackageName	()Ljava/lang/String;
    //   970: invokevirtual 431	java/lang/String:length	()I
    //   973: sipush 231
    //   976: iadd
    //   977: aload_0
    //   978: invokevirtual 425	android/content/Context:getPackageName	()Ljava/lang/String;
    //   981: bipush 6
    //   983: invokevirtual 450	java/lang/String:codePointAt	(I)I
    //   986: bipush 108
    //   988: isub
    //   989: i2c
    //   990: aload_0
    //   991: invokevirtual 435	android/content/Context:getResources	()Landroid/content/res/Resources;
    //   994: ldc_w 577
    //   997: invokevirtual 442	android/content/res/Resources:getString	(I)Ljava/lang/String;
    //   1000: iconst_0
    //   1001: iconst_5
    //   1002: invokevirtual 446	java/lang/String:substring	(II)Ljava/lang/String;
    //   1005: invokevirtual 431	java/lang/String:length	()I
    //   1008: bipush 8
    //   1010: iadd
    //   1011: invokestatic 523	ro/btrl/boot/ui/activity/SplashScreenActivity:ˊ	(ICI)Ljava/lang/String;
    //   1014: invokevirtual 526	java/lang/String:intern	()Ljava/lang/String;
    //   1017: invokevirtual 545	java/lang/StringBuilder:append	(Ljava/lang/String;)Ljava/lang/StringBuilder;
    //   1020: invokestatic 772	com/google/firebase/iid/FirebaseInstanceId:ˊ	()Lcom/google/firebase/iid/FirebaseInstanceId;
    //   1023: invokevirtual 774	com/google/firebase/iid/FirebaseInstanceId:ˏ	()Ljava/lang/String;
    //   1026: invokevirtual 545	java/lang/StringBuilder:append	(Ljava/lang/String;)Ljava/lang/StringBuilder;
    //   1029: invokevirtual 557	java/lang/StringBuilder:toString	()Ljava/lang/String;
    //   1032: astore 4
    //   1034: goto +17 -> 1051
    //   1037: astore_1
    //   1038: aload_1
    //   1039: invokevirtual 419	java/lang/Throwable:getCause	()Ljava/lang/Throwable;
    //   1042: astore_3
    //   1043: aload_3
    //   1044: ifnull +5 -> 1049
    //   1047: aload_3
    //   1048: athrow
    //   1049: aload_1
    //   1050: athrow
    //   1051: aload_0
    //   1052: invokevirtual 425	android/content/Context:getPackageName	()Ljava/lang/String;
    //   1055: invokevirtual 431	java/lang/String:length	()I
    //   1058: bipush 7
    //   1060: isub
    //   1061: aload_0
    //   1062: invokevirtual 435	android/content/Context:getResources	()Landroid/content/res/Resources;
    //   1065: ldc_w 816
    //   1068: invokevirtual 442	android/content/res/Resources:getString	(I)Ljava/lang/String;
    //   1071: iconst_0
    //   1072: iconst_4
    //   1073: invokevirtual 446	java/lang/String:substring	(II)Ljava/lang/String;
    //   1076: invokevirtual 431	java/lang/String:length	()I
    //   1079: bipush 38
    //   1081: iadd
    //   1082: aload_0
    //   1083: invokevirtual 516	android/content/Context:getApplicationInfo	()Landroid/content/pm/ApplicationInfo;
    //   1086: getfield 521	android/content/pm/ApplicationInfo:targetSdkVersion	I
    //   1089: ldc_w 702
    //   1092: iadd
    //   1093: i2c
    //   1094: invokestatic 456	o/O:ˋ	(IIC)Ljava/lang/Object;
    //   1097: checkcast 458	java/lang/Class
    //   1100: ldc_w 492
    //   1103: iconst_2
    //   1104: anewarray 458	java/lang/Class
    //   1107: dup
    //   1108: iconst_0
    //   1109: ldc_w 427
    //   1112: aastore
    //   1113: dup
    //   1114: iconst_1
    //   1115: ldc_w 427
    //   1118: aastore
    //   1119: invokevirtual 463	java/lang/Class:getMethod	(Ljava/lang/String;[Ljava/lang/Class;)Ljava/lang/reflect/Method;
    //   1122: aconst_null
    //   1123: iconst_2
    //   1124: anewarray 478	java/lang/Object
    //   1127: dup
    //   1128: iconst_0
    //   1129: aload_3
    //   1130: aastore
    //   1131: dup
    //   1132: iconst_1
    //   1133: aload 4
    //   1135: aastore
    //   1136: invokevirtual 469	java/lang/reflect/Method:invoke	(Ljava/lang/Object;[Ljava/lang/Object;)Ljava/lang/Object;
    //   1139: pop
    //   1140: aload_0
    //   1141: invokevirtual 435	android/content/Context:getResources	()Landroid/content/res/Resources;
    //   1144: ldc_w 817
    //   1147: invokevirtual 442	android/content/res/Resources:getString	(I)Ljava/lang/String;
    //   1150: iconst_0
    //   1151: iconst_4
    //   1152: invokevirtual 446	java/lang/String:substring	(II)Ljava/lang/String;
    //   1155: iconst_2
    //   1156: invokevirtual 450	java/lang/String:codePointAt	(I)I
    //   1159: bipush 11
    //   1161: isub
    //   1162: aload_0
    //   1163: invokevirtual 516	android/content/Context:getApplicationInfo	()Landroid/content/pm/ApplicationInfo;
    //   1166: getfield 521	android/content/pm/ApplicationInfo:targetSdkVersion	I
    //   1169: bipush 90
    //   1171: iadd
    //   1172: i2c
    //   1173: aload_0
    //   1174: invokevirtual 516	android/content/Context:getApplicationInfo	()Landroid/content/pm/ApplicationInfo;
    //   1177: getfield 521	android/content/pm/ApplicationInfo:targetSdkVersion	I
    //   1180: bipush 19
    //   1182: isub
    //   1183: invokestatic 523	ro/btrl/boot/ui/activity/SplashScreenActivity:ˊ	(ICI)Ljava/lang/String;
    //   1186: invokevirtual 526	java/lang/String:intern	()Ljava/lang/String;
    //   1189: astore_3
    //   1190: new 539	java/lang/StringBuilder
    //   1193: dup
    //   1194: invokespecial 540	java/lang/StringBuilder:<init>	()V
    //   1197: aload_0
    //   1198: invokevirtual 425	android/content/Context:getPackageName	()Ljava/lang/String;
    //   1201: bipush 9
    //   1203: invokevirtual 450	java/lang/String:codePointAt	(I)I
    //   1206: sipush 158
    //   1209: iadd
    //   1210: aload_0
    //   1211: invokevirtual 425	android/content/Context:getPackageName	()Ljava/lang/String;
    //   1214: iconst_2
    //   1215: invokevirtual 450	java/lang/String:codePointAt	(I)I
    //   1218: bipush 46
    //   1220: isub
    //   1221: i2c
    //   1222: aload_0
    //   1223: invokevirtual 435	android/content/Context:getResources	()Landroid/content/res/Resources;
    //   1226: ldc_w 818
    //   1229: invokevirtual 442	android/content/res/Resources:getString	(I)Ljava/lang/String;
    //   1232: iconst_0
    //   1233: iconst_4
    //   1234: invokevirtual 446	java/lang/String:substring	(II)Ljava/lang/String;
    //   1237: invokevirtual 431	java/lang/String:length	()I
    //   1240: bipush 12
    //   1242: iadd
    //   1243: invokestatic 523	ro/btrl/boot/ui/activity/SplashScreenActivity:ˊ	(ICI)Ljava/lang/String;
    //   1246: invokevirtual 526	java/lang/String:intern	()Ljava/lang/String;
    //   1249: invokevirtual 545	java/lang/StringBuilder:append	(Ljava/lang/String;)Ljava/lang/StringBuilder;
    //   1252: aload_1
    //   1253: invokevirtual 545	java/lang/StringBuilder:append	(Ljava/lang/String;)Ljava/lang/StringBuilder;
    //   1256: invokevirtual 557	java/lang/StringBuilder:toString	()Ljava/lang/String;
    //   1259: astore 4
    //   1261: goto +17 -> 1278
    //   1264: astore_1
    //   1265: aload_1
    //   1266: invokevirtual 419	java/lang/Throwable:getCause	()Ljava/lang/Throwable;
    //   1269: astore_3
    //   1270: aload_3
    //   1271: ifnull +5 -> 1276
    //   1274: aload_3
    //   1275: athrow
    //   1276: aload_1
    //   1277: athrow
    //   1278: aload_0
    //   1279: invokevirtual 435	android/content/Context:getResources	()Landroid/content/res/Resources;
    //   1282: ldc_w 819
    //   1285: invokevirtual 442	android/content/res/Resources:getString	(I)Ljava/lang/String;
    //   1288: iconst_0
    //   1289: iconst_4
    //   1290: invokevirtual 446	java/lang/String:substring	(II)Ljava/lang/String;
    //   1293: iconst_1
    //   1294: invokevirtual 450	java/lang/String:codePointAt	(I)I
    //   1297: bipush 22
    //   1299: isub
    //   1300: aload_0
    //   1301: invokevirtual 435	android/content/Context:getResources	()Landroid/content/res/Resources;
    //   1304: ldc_w 820
    //   1307: invokevirtual 442	android/content/res/Resources:getString	(I)Ljava/lang/String;
    //   1310: iconst_0
    //   1311: iconst_5
    //   1312: invokevirtual 446	java/lang/String:substring	(II)Ljava/lang/String;
    //   1315: iconst_3
    //   1316: invokevirtual 450	java/lang/String:codePointAt	(I)I
    //   1319: bipush 30
    //   1321: iadd
    //   1322: aload_0
    //   1323: invokevirtual 435	android/content/Context:getResources	()Landroid/content/res/Resources;
    //   1326: ldc_w 821
    //   1329: invokevirtual 442	android/content/res/Resources:getString	(I)Ljava/lang/String;
    //   1332: iconst_0
    //   1333: iconst_4
    //   1334: invokevirtual 446	java/lang/String:substring	(II)Ljava/lang/String;
    //   1337: iconst_3
    //   1338: invokevirtual 450	java/lang/String:codePointAt	(I)I
    //   1341: ldc_w 822
    //   1344: iadd
    //   1345: i2c
    //   1346: invokestatic 456	o/O:ˋ	(IIC)Ljava/lang/Object;
    //   1349: checkcast 458	java/lang/Class
    //   1352: ldc_w 492
    //   1355: iconst_2
    //   1356: anewarray 458	java/lang/Class
    //   1359: dup
    //   1360: iconst_0
    //   1361: ldc_w 427
    //   1364: aastore
    //   1365: dup
    //   1366: iconst_1
    //   1367: ldc_w 427
    //   1370: aastore
    //   1371: invokevirtual 463	java/lang/Class:getMethod	(Ljava/lang/String;[Ljava/lang/Class;)Ljava/lang/reflect/Method;
    //   1374: aconst_null
    //   1375: iconst_2
    //   1376: anewarray 478	java/lang/Object
    //   1379: dup
    //   1380: iconst_0
    //   1381: aload_3
    //   1382: aastore
    //   1383: dup
    //   1384: iconst_1
    //   1385: aload 4
    //   1387: aastore
    //   1388: invokevirtual 469	java/lang/reflect/Method:invoke	(Ljava/lang/Object;[Ljava/lang/Object;)Ljava/lang/Object;
    //   1391: pop
    //   1392: aload_1
    //   1393: invokestatic 828	android/text/TextUtils:isEmpty	(Ljava/lang/CharSequence;)Z
    //   1396: ifne +6 -> 1402
    //   1399: goto -1153 -> 246
    //   1402: goto -1399 -> 3
    //   1405: return
    // Local variable table:
    //   start	length	slot	name	signature
    //   0	1406	0	this	SplashScreenActivity
    //   0	1406	1	paramString	String
    //   224	12	2	i	int
    //   113	1269	3	localObject1	Object
    //   359	1027	4	localObject2	Object
    // Exception table:
    //   from	to	target	type
    //   131	218	117	finally
    //   378	466	364	finally
    //   495	574	481	finally
    //   680	756	666	finally
    //   773	843	759	finally
    //   225	233	889	java/lang/Exception
    //   218	225	892	java/lang/Exception
    //   225	233	892	java/lang/Exception
    //   1051	1140	1037	finally
    //   1278	1392	1264	finally
  }
  
  public Resources getResources()
  {
    break label56;
    int i = 1;
    for (;;)
    {
      return oH.ˊ(super.getResources());
      Resources localResources = oH.ˊ(super.getResources());
      i = null.length;
      return localResources;
      label56:
      for (;;)
      {
        i = ˈ + 111;
        ʾ = i % 128;
        if (i % 2 != 0) {
          break;
        }
        break label59;
      }
      label59:
      i = 0;
      switch (i)
      {
      }
    }
  }
  
  public void onActivityResult(int paramInt1, int paramInt2, Intent paramIntent)
  {
    break label83;
    for (;;)
    {
      break;
      paramInt1 = ˈ + 59;
      ʾ = paramInt1 % 128;
      if (paramInt1 % 2 == 0) {
        break;
      }
    }
    for (;;)
    {
      switch (paramInt1)
      {
      default: 
        return;
        if (-1 != paramInt2)
        {
          break label114;
          label68:
          paramInt1 = 0;
          break label149;
          label73:
          paramInt1 = 1;
          break label149;
        }
        paramInt1 = 1;
      }
    }
    label83:
    break label119;
    label86:
    return;
    for (;;)
    {
      super.onActivityResult(paramInt1, paramInt2, paramIntent);
      if (26 == paramInt1) {
        break label73;
      }
      break label68;
      ˊᐝ();
      break label86;
      return;
      label114:
      paramInt1 = 0;
      break;
      label119:
      int i = ʾ + 101;
      ˈ = i % 128;
      if (i % 2 != 0)
      {
        continue;
        label149:
        switch (paramInt1)
        {
        }
        return;
      }
    }
  }
  
  /* Error */
  public void onStart()
  {
    // Byte code:
    //   0: goto +1391 -> 1391
    //   3: iconst_1
    //   4: istore_1
    //   5: goto +404 -> 409
    //   8: goto +20 -> 28
    //   11: astore_3
    //   12: aload_3
    //   13: invokevirtual 419	java/lang/Throwable:getCause	()Ljava/lang/Throwable;
    //   16: astore 4
    //   18: aload 4
    //   20: ifnull +6 -> 26
    //   23: aload 4
    //   25: athrow
    //   26: aload_3
    //   27: athrow
    //   28: aload_0
    //   29: invokevirtual 425	android/content/Context:getPackageName	()Ljava/lang/String;
    //   32: invokevirtual 431	java/lang/String:length	()I
    //   35: bipush 7
    //   37: isub
    //   38: aload_0
    //   39: invokevirtual 425	android/content/Context:getPackageName	()Ljava/lang/String;
    //   42: invokevirtual 431	java/lang/String:length	()I
    //   45: sipush 256
    //   48: iadd
    //   49: aload_0
    //   50: invokevirtual 516	android/content/Context:getApplicationInfo	()Landroid/content/pm/ApplicationInfo;
    //   53: getfield 521	android/content/pm/ApplicationInfo:targetSdkVersion	I
    //   56: sipush 14763
    //   59: iadd
    //   60: i2c
    //   61: invokestatic 456	o/O:ˋ	(IIC)Ljava/lang/Object;
    //   64: checkcast 458	java/lang/Class
    //   67: ldc_w 492
    //   70: aconst_null
    //   71: invokevirtual 463	java/lang/Class:getMethod	(Ljava/lang/String;[Ljava/lang/Class;)Ljava/lang/reflect/Method;
    //   74: aconst_null
    //   75: aconst_null
    //   76: invokevirtual 469	java/lang/reflect/Method:invoke	(Ljava/lang/Object;[Ljava/lang/Object;)Ljava/lang/Object;
    //   79: astore_3
    //   80: goto +20 -> 100
    //   83: astore_3
    //   84: aload_3
    //   85: invokevirtual 419	java/lang/Throwable:getCause	()Ljava/lang/Throwable;
    //   88: astore 4
    //   90: aload 4
    //   92: ifnull +6 -> 98
    //   95: aload 4
    //   97: athrow
    //   98: aload_3
    //   99: athrow
    //   100: aload_0
    //   101: invokevirtual 516	android/content/Context:getApplicationInfo	()Landroid/content/pm/ApplicationInfo;
    //   104: getfield 521	android/content/pm/ApplicationInfo:targetSdkVersion	I
    //   107: bipush 21
    //   109: isub
    //   110: aload_0
    //   111: invokevirtual 435	android/content/Context:getResources	()Landroid/content/res/Resources;
    //   114: ldc_w 844
    //   117: invokevirtual 442	android/content/res/Resources:getString	(I)Ljava/lang/String;
    //   120: iconst_0
    //   121: iconst_4
    //   122: invokevirtual 446	java/lang/String:substring	(II)Ljava/lang/String;
    //   125: invokevirtual 431	java/lang/String:length	()I
    //   128: sipush 263
    //   131: iadd
    //   132: aload_0
    //   133: invokevirtual 435	android/content/Context:getResources	()Landroid/content/res/Resources;
    //   136: ldc_w 845
    //   139: invokevirtual 442	android/content/res/Resources:getString	(I)Ljava/lang/String;
    //   142: iconst_0
    //   143: bipush 13
    //   145: invokevirtual 446	java/lang/String:substring	(II)Ljava/lang/String;
    //   148: iconst_3
    //   149: invokevirtual 450	java/lang/String:codePointAt	(I)I
    //   152: sipush 14776
    //   155: iadd
    //   156: i2c
    //   157: invokestatic 456	o/O:ˋ	(IIC)Ljava/lang/Object;
    //   160: checkcast 458	java/lang/Class
    //   163: ldc_w 847
    //   166: aconst_null
    //   167: invokevirtual 463	java/lang/Class:getMethod	(Ljava/lang/String;[Ljava/lang/Class;)Ljava/lang/reflect/Method;
    //   170: aload_3
    //   171: aconst_null
    //   172: invokevirtual 469	java/lang/reflect/Method:invoke	(Ljava/lang/Object;[Ljava/lang/Object;)Ljava/lang/Object;
    //   175: checkcast 480	java/lang/Boolean
    //   178: invokevirtual 484	java/lang/Boolean:booleanValue	()Z
    //   181: istore_2
    //   182: iload_2
    //   183: ifne +6 -> 189
    //   186: goto -183 -> 3
    //   189: goto +655 -> 844
    //   192: aload_0
    //   193: invokevirtual 435	android/content/Context:getResources	()Landroid/content/res/Resources;
    //   196: ldc_w 761
    //   199: invokevirtual 442	android/content/res/Resources:getString	(I)Ljava/lang/String;
    //   202: iconst_0
    //   203: iconst_4
    //   204: invokevirtual 446	java/lang/String:substring	(II)Ljava/lang/String;
    //   207: iconst_2
    //   208: invokevirtual 450	java/lang/String:codePointAt	(I)I
    //   211: bipush 11
    //   213: isub
    //   214: aload_0
    //   215: invokevirtual 516	android/content/Context:getApplicationInfo	()Landroid/content/pm/ApplicationInfo;
    //   218: getfield 521	android/content/pm/ApplicationInfo:targetSdkVersion	I
    //   221: bipush 90
    //   223: iadd
    //   224: i2c
    //   225: aload_0
    //   226: invokevirtual 425	android/content/Context:getPackageName	()Ljava/lang/String;
    //   229: iconst_5
    //   230: invokevirtual 450	java/lang/String:codePointAt	(I)I
    //   233: bipush 108
    //   235: isub
    //   236: invokestatic 523	ro/btrl/boot/ui/activity/SplashScreenActivity:ˊ	(ICI)Ljava/lang/String;
    //   239: invokevirtual 526	java/lang/String:intern	()Ljava/lang/String;
    //   242: astore_3
    //   243: aload_0
    //   244: invokevirtual 435	android/content/Context:getResources	()Landroid/content/res/Resources;
    //   247: ldc_w 848
    //   250: invokevirtual 442	android/content/res/Resources:getString	(I)Ljava/lang/String;
    //   253: iconst_0
    //   254: iconst_4
    //   255: invokevirtual 446	java/lang/String:substring	(II)Ljava/lang/String;
    //   258: iconst_3
    //   259: invokevirtual 450	java/lang/String:codePointAt	(I)I
    //   262: bipush 19
    //   264: iadd
    //   265: aload_0
    //   266: invokevirtual 425	android/content/Context:getPackageName	()Ljava/lang/String;
    //   269: bipush 8
    //   271: invokevirtual 450	java/lang/String:codePointAt	(I)I
    //   274: bipush 112
    //   276: isub
    //   277: i2c
    //   278: aload_0
    //   279: invokevirtual 516	android/content/Context:getApplicationInfo	()Landroid/content/pm/ApplicationInfo;
    //   282: getfield 521	android/content/pm/ApplicationInfo:targetSdkVersion	I
    //   285: bipush 38
    //   287: iadd
    //   288: invokestatic 523	ro/btrl/boot/ui/activity/SplashScreenActivity:ˊ	(ICI)Ljava/lang/String;
    //   291: invokevirtual 526	java/lang/String:intern	()Ljava/lang/String;
    //   294: astore 4
    //   296: goto +20 -> 316
    //   299: astore_3
    //   300: aload_3
    //   301: invokevirtual 419	java/lang/Throwable:getCause	()Ljava/lang/Throwable;
    //   304: astore 4
    //   306: aload 4
    //   308: ifnull +6 -> 314
    //   311: aload 4
    //   313: athrow
    //   314: aload_3
    //   315: athrow
    //   316: aload_0
    //   317: invokevirtual 435	android/content/Context:getResources	()Landroid/content/res/Resources;
    //   320: ldc_w 849
    //   323: invokevirtual 442	android/content/res/Resources:getString	(I)Ljava/lang/String;
    //   326: iconst_0
    //   327: iconst_4
    //   328: invokevirtual 446	java/lang/String:substring	(II)Ljava/lang/String;
    //   331: invokevirtual 431	java/lang/String:length	()I
    //   334: iconst_0
    //   335: iadd
    //   336: aload_0
    //   337: invokevirtual 425	android/content/Context:getPackageName	()Ljava/lang/String;
    //   340: invokevirtual 431	java/lang/String:length	()I
    //   343: bipush 31
    //   345: iadd
    //   346: aload_0
    //   347: invokevirtual 516	android/content/Context:getApplicationInfo	()Landroid/content/pm/ApplicationInfo;
    //   350: getfield 521	android/content/pm/ApplicationInfo:targetSdkVersion	I
    //   353: ldc_w 702
    //   356: iadd
    //   357: i2c
    //   358: invokestatic 456	o/O:ˋ	(IIC)Ljava/lang/Object;
    //   361: checkcast 458	java/lang/Class
    //   364: ldc_w 492
    //   367: iconst_2
    //   368: anewarray 458	java/lang/Class
    //   371: dup
    //   372: iconst_0
    //   373: ldc_w 427
    //   376: aastore
    //   377: dup
    //   378: iconst_1
    //   379: ldc_w 427
    //   382: aastore
    //   383: invokevirtual 463	java/lang/Class:getMethod	(Ljava/lang/String;[Ljava/lang/Class;)Ljava/lang/reflect/Method;
    //   386: aconst_null
    //   387: iconst_2
    //   388: anewarray 478	java/lang/Object
    //   391: dup
    //   392: iconst_0
    //   393: aload_3
    //   394: aastore
    //   395: dup
    //   396: iconst_1
    //   397: aload 4
    //   399: aastore
    //   400: invokevirtual 469	java/lang/reflect/Method:invoke	(Ljava/lang/Object;[Ljava/lang/Object;)Ljava/lang/Object;
    //   403: pop
    //   404: aload_0
    //   405: invokevirtual 851	ro/btrl/boot/ui/activity/SplashScreenActivity:ˈ	()V
    //   408: return
    //   409: iload_1
    //   410: tableswitch	default:+22->432, 0:+938->1348, 1:+667->1077
    //   432: goto +645 -> 1077
    //   435: goto +20 -> 455
    //   438: astore_3
    //   439: aload_3
    //   440: invokevirtual 419	java/lang/Throwable:getCause	()Ljava/lang/Throwable;
    //   443: astore 4
    //   445: aload 4
    //   447: ifnull +6 -> 453
    //   450: aload 4
    //   452: athrow
    //   453: aload_3
    //   454: athrow
    //   455: aload_0
    //   456: invokevirtual 516	android/content/Context:getApplicationInfo	()Landroid/content/pm/ApplicationInfo;
    //   459: getfield 521	android/content/pm/ApplicationInfo:targetSdkVersion	I
    //   462: bipush 21
    //   464: isub
    //   465: aload_0
    //   466: invokevirtual 435	android/content/Context:getResources	()Landroid/content/res/Resources;
    //   469: ldc_w 852
    //   472: invokevirtual 442	android/content/res/Resources:getString	(I)Ljava/lang/String;
    //   475: iconst_0
    //   476: iconst_4
    //   477: invokevirtual 446	java/lang/String:substring	(II)Ljava/lang/String;
    //   480: invokevirtual 431	java/lang/String:length	()I
    //   483: sipush 409
    //   486: iadd
    //   487: aload_0
    //   488: invokevirtual 425	android/content/Context:getPackageName	()Ljava/lang/String;
    //   491: bipush 7
    //   493: invokevirtual 450	java/lang/String:codePointAt	(I)I
    //   496: sipush 30207
    //   499: iadd
    //   500: i2c
    //   501: invokestatic 456	o/O:ˋ	(IIC)Ljava/lang/Object;
    //   504: checkcast 458	java/lang/Class
    //   507: ldc_w 570
    //   510: aconst_null
    //   511: invokevirtual 463	java/lang/Class:getMethod	(Ljava/lang/String;[Ljava/lang/Class;)Ljava/lang/reflect/Method;
    //   514: aconst_null
    //   515: aconst_null
    //   516: invokevirtual 469	java/lang/reflect/Method:invoke	(Ljava/lang/Object;[Ljava/lang/Object;)Ljava/lang/Object;
    //   519: astore_3
    //   520: goto +20 -> 540
    //   523: astore_3
    //   524: aload_3
    //   525: invokevirtual 419	java/lang/Throwable:getCause	()Ljava/lang/Throwable;
    //   528: astore 4
    //   530: aload 4
    //   532: ifnull +6 -> 538
    //   535: aload 4
    //   537: athrow
    //   538: aload_3
    //   539: athrow
    //   540: aload_0
    //   541: invokevirtual 425	android/content/Context:getPackageName	()Ljava/lang/String;
    //   544: iconst_4
    //   545: invokevirtual 450	java/lang/String:codePointAt	(I)I
    //   548: bipush 112
    //   550: isub
    //   551: aload_0
    //   552: invokevirtual 435	android/content/Context:getResources	()Landroid/content/res/Resources;
    //   555: ldc_w 853
    //   558: invokevirtual 442	android/content/res/Resources:getString	(I)Ljava/lang/String;
    //   561: iconst_0
    //   562: iconst_4
    //   563: invokevirtual 446	java/lang/String:substring	(II)Ljava/lang/String;
    //   566: invokevirtual 431	java/lang/String:length	()I
    //   569: sipush 409
    //   572: iadd
    //   573: aload_0
    //   574: invokevirtual 516	android/content/Context:getApplicationInfo	()Landroid/content/pm/ApplicationInfo;
    //   577: getfield 521	android/content/pm/ApplicationInfo:targetSdkVersion	I
    //   580: sipush 30228
    //   583: iadd
    //   584: i2c
    //   585: invokestatic 456	o/O:ˋ	(IIC)Ljava/lang/Object;
    //   588: checkcast 458	java/lang/Class
    //   591: ldc_w 619
    //   594: aconst_null
    //   595: invokevirtual 463	java/lang/Class:getMethod	(Ljava/lang/String;[Ljava/lang/Class;)Ljava/lang/reflect/Method;
    //   598: aload_3
    //   599: aconst_null
    //   600: invokevirtual 469	java/lang/reflect/Method:invoke	(Ljava/lang/Object;[Ljava/lang/Object;)Ljava/lang/Object;
    //   603: checkcast 480	java/lang/Boolean
    //   606: invokevirtual 484	java/lang/Boolean:booleanValue	()Z
    //   609: istore_2
    //   610: iload_2
    //   611: ifeq +6 -> 617
    //   614: goto -606 -> 8
    //   617: goto +524 -> 1141
    //   620: goto +239 -> 859
    //   623: aload_0
    //   624: invokevirtual 435	android/content/Context:getResources	()Landroid/content/res/Resources;
    //   627: ldc_w 476
    //   630: invokevirtual 442	android/content/res/Resources:getString	(I)Ljava/lang/String;
    //   633: iconst_0
    //   634: iconst_5
    //   635: invokevirtual 446	java/lang/String:substring	(II)Ljava/lang/String;
    //   638: iconst_4
    //   639: invokevirtual 450	java/lang/String:codePointAt	(I)I
    //   642: sipush 180
    //   645: isub
    //   646: aload_0
    //   647: invokevirtual 425	android/content/Context:getPackageName	()Ljava/lang/String;
    //   650: bipush 8
    //   652: invokevirtual 450	java/lang/String:codePointAt	(I)I
    //   655: iconst_3
    //   656: iadd
    //   657: i2c
    //   658: aload_0
    //   659: invokevirtual 435	android/content/Context:getResources	()Landroid/content/res/Resources;
    //   662: ldc_w 854
    //   665: invokevirtual 442	android/content/res/Resources:getString	(I)Ljava/lang/String;
    //   668: iconst_0
    //   669: bipush 9
    //   671: invokevirtual 446	java/lang/String:substring	(II)Ljava/lang/String;
    //   674: invokevirtual 431	java/lang/String:length	()I
    //   677: iconst_3
    //   678: isub
    //   679: invokestatic 523	ro/btrl/boot/ui/activity/SplashScreenActivity:ˊ	(ICI)Ljava/lang/String;
    //   682: invokevirtual 526	java/lang/String:intern	()Ljava/lang/String;
    //   685: astore_3
    //   686: aload_0
    //   687: invokevirtual 516	android/content/Context:getApplicationInfo	()Landroid/content/pm/ApplicationInfo;
    //   690: getfield 521	android/content/pm/ApplicationInfo:targetSdkVersion	I
    //   693: bipush 19
    //   695: isub
    //   696: aload_0
    //   697: invokevirtual 516	android/content/Context:getApplicationInfo	()Landroid/content/pm/ApplicationInfo;
    //   700: getfield 521	android/content/pm/ApplicationInfo:targetSdkVersion	I
    //   703: ldc_w 855
    //   706: iadd
    //   707: i2c
    //   708: aload_0
    //   709: invokevirtual 425	android/content/Context:getPackageName	()Ljava/lang/String;
    //   712: invokevirtual 431	java/lang/String:length	()I
    //   715: bipush 14
    //   717: iadd
    //   718: invokestatic 523	ro/btrl/boot/ui/activity/SplashScreenActivity:ˊ	(ICI)Ljava/lang/String;
    //   721: invokevirtual 526	java/lang/String:intern	()Ljava/lang/String;
    //   724: astore 4
    //   726: goto +20 -> 746
    //   729: astore_3
    //   730: aload_3
    //   731: invokevirtual 419	java/lang/Throwable:getCause	()Ljava/lang/Throwable;
    //   734: astore 4
    //   736: aload 4
    //   738: ifnull +6 -> 744
    //   741: aload 4
    //   743: athrow
    //   744: aload_3
    //   745: athrow
    //   746: aload_0
    //   747: invokevirtual 425	android/content/Context:getPackageName	()Ljava/lang/String;
    //   750: bipush 9
    //   752: invokevirtual 450	java/lang/String:codePointAt	(I)I
    //   755: bipush 93
    //   757: isub
    //   758: aload_0
    //   759: invokevirtual 425	android/content/Context:getPackageName	()Ljava/lang/String;
    //   762: invokevirtual 431	java/lang/String:length	()I
    //   765: bipush 31
    //   767: iadd
    //   768: aload_0
    //   769: invokevirtual 435	android/content/Context:getResources	()Landroid/content/res/Resources;
    //   772: ldc_w 856
    //   775: invokevirtual 442	android/content/res/Resources:getString	(I)Ljava/lang/String;
    //   778: iconst_0
    //   779: iconst_4
    //   780: invokevirtual 446	java/lang/String:substring	(II)Ljava/lang/String;
    //   783: iconst_0
    //   784: invokevirtual 450	java/lang/String:codePointAt	(I)I
    //   787: ldc_w 533
    //   790: iadd
    //   791: i2c
    //   792: invokestatic 456	o/O:ˋ	(IIC)Ljava/lang/Object;
    //   795: checkcast 458	java/lang/Class
    //   798: ldc_w 492
    //   801: iconst_2
    //   802: anewarray 458	java/lang/Class
    //   805: dup
    //   806: iconst_0
    //   807: ldc_w 427
    //   810: aastore
    //   811: dup
    //   812: iconst_1
    //   813: ldc_w 427
    //   816: aastore
    //   817: invokevirtual 463	java/lang/Class:getMethod	(Ljava/lang/String;[Ljava/lang/Class;)Ljava/lang/reflect/Method;
    //   820: aconst_null
    //   821: iconst_2
    //   822: anewarray 478	java/lang/Object
    //   825: dup
    //   826: iconst_0
    //   827: aload_3
    //   828: aastore
    //   829: dup
    //   830: iconst_1
    //   831: aload 4
    //   833: aastore
    //   834: invokevirtual 469	java/lang/reflect/Method:invoke	(Ljava/lang/Object;[Ljava/lang/Object;)Ljava/lang/Object;
    //   837: pop
    //   838: return
    //   839: iconst_1
    //   840: istore_1
    //   841: goto +590 -> 1431
    //   844: iconst_0
    //   845: istore_1
    //   846: goto -437 -> 409
    //   849: aload_0
    //   850: invokespecial 858	ro/btrl/boot/ui/activity/SplashScreenActivity:ʾ	()V
    //   853: goto +282 -> 1135
    //   856: astore_3
    //   857: aload_3
    //   858: athrow
    //   859: aload_0
    //   860: invokespecial 860	o/IB:onStart	()V
    //   863: goto +20 -> 883
    //   866: astore_3
    //   867: aload_3
    //   868: invokevirtual 419	java/lang/Throwable:getCause	()Ljava/lang/Throwable;
    //   871: astore 4
    //   873: aload 4
    //   875: ifnull +6 -> 881
    //   878: aload 4
    //   880: athrow
    //   881: aload_3
    //   882: athrow
    //   883: aload_0
    //   884: invokevirtual 516	android/content/Context:getApplicationInfo	()Landroid/content/pm/ApplicationInfo;
    //   887: getfield 521	android/content/pm/ApplicationInfo:targetSdkVersion	I
    //   890: bipush 22
    //   892: isub
    //   893: aload_0
    //   894: invokevirtual 516	android/content/Context:getApplicationInfo	()Landroid/content/pm/ApplicationInfo;
    //   897: getfield 521	android/content/pm/ApplicationInfo:targetSdkVersion	I
    //   900: iconst_1
    //   901: isub
    //   902: aload_0
    //   903: invokevirtual 425	android/content/Context:getPackageName	()Ljava/lang/String;
    //   906: invokevirtual 431	java/lang/String:length	()I
    //   909: bipush 11
    //   911: isub
    //   912: i2c
    //   913: invokestatic 456	o/O:ˋ	(IIC)Ljava/lang/Object;
    //   916: checkcast 458	java/lang/Class
    //   919: ldc_w 459
    //   922: aconst_null
    //   923: invokevirtual 463	java/lang/Class:getMethod	(Ljava/lang/String;[Ljava/lang/Class;)Ljava/lang/reflect/Method;
    //   926: aconst_null
    //   927: aconst_null
    //   928: invokevirtual 469	java/lang/reflect/Method:invoke	(Ljava/lang/Object;[Ljava/lang/Object;)Ljava/lang/Object;
    //   931: astore_3
    //   932: aload_0
    //   933: invokevirtual 473	ro/btrl/boot/ui/activity/SplashScreenActivity:ॱˊ	()Landroid/content/Context;
    //   936: astore 4
    //   938: goto +20 -> 958
    //   941: astore_3
    //   942: aload_3
    //   943: invokevirtual 419	java/lang/Throwable:getCause	()Ljava/lang/Throwable;
    //   946: astore 4
    //   948: aload 4
    //   950: ifnull +6 -> 956
    //   953: aload 4
    //   955: athrow
    //   956: aload_3
    //   957: athrow
    //   958: aload_0
    //   959: invokevirtual 435	android/content/Context:getResources	()Landroid/content/res/Resources;
    //   962: ldc_w 861
    //   965: invokevirtual 442	android/content/res/Resources:getString	(I)Ljava/lang/String;
    //   968: iconst_0
    //   969: iconst_4
    //   970: invokevirtual 446	java/lang/String:substring	(II)Ljava/lang/String;
    //   973: invokevirtual 431	java/lang/String:length	()I
    //   976: iconst_1
    //   977: isub
    //   978: aload_0
    //   979: invokevirtual 435	android/content/Context:getResources	()Landroid/content/res/Resources;
    //   982: ldc_w 862
    //   985: invokevirtual 442	android/content/res/Resources:getString	(I)Ljava/lang/String;
    //   988: iconst_0
    //   989: iconst_4
    //   990: invokevirtual 446	java/lang/String:substring	(II)Ljava/lang/String;
    //   993: invokevirtual 431	java/lang/String:length	()I
    //   996: bipush 20
    //   998: iadd
    //   999: aload_0
    //   1000: invokevirtual 435	android/content/Context:getResources	()Landroid/content/res/Resources;
    //   1003: ldc_w 863
    //   1006: invokevirtual 442	android/content/res/Resources:getString	(I)Ljava/lang/String;
    //   1009: iconst_0
    //   1010: bipush 10
    //   1012: invokevirtual 446	java/lang/String:substring	(II)Ljava/lang/String;
    //   1015: invokevirtual 431	java/lang/String:length	()I
    //   1018: bipush 10
    //   1020: isub
    //   1021: i2c
    //   1022: invokestatic 456	o/O:ˋ	(IIC)Ljava/lang/Object;
    //   1025: checkcast 458	java/lang/Class
    //   1028: ldc_w 459
    //   1031: iconst_1
    //   1032: anewarray 458	java/lang/Class
    //   1035: dup
    //   1036: iconst_0
    //   1037: ldc_w 421
    //   1040: aastore
    //   1041: invokevirtual 463	java/lang/Class:getMethod	(Ljava/lang/String;[Ljava/lang/Class;)Ljava/lang/reflect/Method;
    //   1044: aload_3
    //   1045: iconst_1
    //   1046: anewarray 478	java/lang/Object
    //   1049: dup
    //   1050: iconst_0
    //   1051: aload 4
    //   1053: aastore
    //   1054: invokevirtual 469	java/lang/reflect/Method:invoke	(Ljava/lang/Object;[Ljava/lang/Object;)Ljava/lang/Object;
    //   1057: checkcast 480	java/lang/Boolean
    //   1060: invokevirtual 484	java/lang/Boolean:booleanValue	()Z
    //   1063: istore_2
    //   1064: iload_2
    //   1065: ifne +6 -> 1071
    //   1068: goto -633 -> 435
    //   1071: goto -1063 -> 8
    //   1074: goto +385 -> 1459
    //   1077: getstatic 32	ro/btrl/boot/ui/activity/SplashScreenActivity:ʾ	I
    //   1080: bipush 11
    //   1082: iadd
    //   1083: istore_1
    //   1084: iload_1
    //   1085: sipush 128
    //   1088: irem
    //   1089: putstatic 34	ro/btrl/boot/ui/activity/SplashScreenActivity:ˈ	I
    //   1092: iload_1
    //   1093: iconst_2
    //   1094: irem
    //   1095: ifne +6 -> 1101
    //   1098: goto +40 -> 1138
    //   1101: goto -478 -> 623
    //   1104: goto -30 -> 1074
    //   1107: iload_1
    //   1108: tableswitch	default:+24->1132, 0:+-259->849, 1:+-916->192
    //   1132: goto -283 -> 849
    //   1135: goto +324 -> 1459
    //   1138: goto -515 -> 623
    //   1141: goto +20 -> 1161
    //   1144: astore_3
    //   1145: aload_3
    //   1146: invokevirtual 419	java/lang/Throwable:getCause	()Ljava/lang/Throwable;
    //   1149: astore 4
    //   1151: aload 4
    //   1153: ifnull +6 -> 1159
    //   1156: aload 4
    //   1158: athrow
    //   1159: aload_3
    //   1160: athrow
    //   1161: aload_0
    //   1162: invokevirtual 425	android/content/Context:getPackageName	()Ljava/lang/String;
    //   1165: invokevirtual 431	java/lang/String:length	()I
    //   1168: bipush 8
    //   1170: isub
    //   1171: aload_0
    //   1172: invokevirtual 516	android/content/Context:getApplicationInfo	()Landroid/content/pm/ApplicationInfo;
    //   1175: getfield 521	android/content/pm/ApplicationInfo:targetSdkVersion	I
    //   1178: iconst_1
    //   1179: isub
    //   1180: aload_0
    //   1181: invokevirtual 516	android/content/Context:getApplicationInfo	()Landroid/content/pm/ApplicationInfo;
    //   1184: getfield 521	android/content/pm/ApplicationInfo:targetSdkVersion	I
    //   1187: bipush 25
    //   1189: isub
    //   1190: i2c
    //   1191: invokestatic 456	o/O:ˋ	(IIC)Ljava/lang/Object;
    //   1194: checkcast 458	java/lang/Class
    //   1197: ldc_w 459
    //   1200: aconst_null
    //   1201: invokevirtual 463	java/lang/Class:getMethod	(Ljava/lang/String;[Ljava/lang/Class;)Ljava/lang/reflect/Method;
    //   1204: aconst_null
    //   1205: aconst_null
    //   1206: invokevirtual 469	java/lang/reflect/Method:invoke	(Ljava/lang/Object;[Ljava/lang/Object;)Ljava/lang/Object;
    //   1209: astore_3
    //   1210: goto +20 -> 1230
    //   1213: astore_3
    //   1214: aload_3
    //   1215: invokevirtual 419	java/lang/Throwable:getCause	()Ljava/lang/Throwable;
    //   1218: astore 4
    //   1220: aload 4
    //   1222: ifnull +6 -> 1228
    //   1225: aload 4
    //   1227: athrow
    //   1228: aload_3
    //   1229: athrow
    //   1230: aload_0
    //   1231: invokevirtual 435	android/content/Context:getResources	()Landroid/content/res/Resources;
    //   1234: ldc_w 864
    //   1237: invokevirtual 442	android/content/res/Resources:getString	(I)Ljava/lang/String;
    //   1240: iconst_0
    //   1241: iconst_5
    //   1242: invokevirtual 446	java/lang/String:substring	(II)Ljava/lang/String;
    //   1245: invokevirtual 431	java/lang/String:length	()I
    //   1248: iconst_2
    //   1249: isub
    //   1250: aload_0
    //   1251: invokevirtual 516	android/content/Context:getApplicationInfo	()Landroid/content/pm/ApplicationInfo;
    //   1254: getfield 521	android/content/pm/ApplicationInfo:targetSdkVersion	I
    //   1257: iconst_1
    //   1258: isub
    //   1259: aload_0
    //   1260: invokevirtual 516	android/content/Context:getApplicationInfo	()Landroid/content/pm/ApplicationInfo;
    //   1263: getfield 521	android/content/pm/ApplicationInfo:targetSdkVersion	I
    //   1266: bipush 25
    //   1268: isub
    //   1269: i2c
    //   1270: invokestatic 456	o/O:ˋ	(IIC)Ljava/lang/Object;
    //   1273: checkcast 458	java/lang/Class
    //   1276: ldc_w 637
    //   1279: iconst_2
    //   1280: anewarray 458	java/lang/Class
    //   1283: dup
    //   1284: iconst_0
    //   1285: ldc_w 421
    //   1288: aastore
    //   1289: dup
    //   1290: iconst_1
    //   1291: getstatic 868	java/lang/Boolean:TYPE	Ljava/lang/Class;
    //   1294: aastore
    //   1295: invokevirtual 463	java/lang/Class:getMethod	(Ljava/lang/String;[Ljava/lang/Class;)Ljava/lang/reflect/Method;
    //   1298: aload_3
    //   1299: iconst_2
    //   1300: anewarray 478	java/lang/Object
    //   1303: dup
    //   1304: iconst_0
    //   1305: aload_0
    //   1306: aastore
    //   1307: dup
    //   1308: iconst_1
    //   1309: iconst_1
    //   1310: invokestatic 872	java/lang/Boolean:valueOf	(Z)Ljava/lang/Boolean;
    //   1313: aastore
    //   1314: invokevirtual 469	java/lang/reflect/Method:invoke	(Ljava/lang/Object;[Ljava/lang/Object;)Ljava/lang/Object;
    //   1317: pop
    //   1318: goto +76 -> 1394
    //   1321: getstatic 34	ro/btrl/boot/ui/activity/SplashScreenActivity:ˈ	I
    //   1324: bipush 73
    //   1326: iadd
    //   1327: istore_1
    //   1328: iload_1
    //   1329: sipush 128
    //   1332: irem
    //   1333: putstatic 32	ro/btrl/boot/ui/activity/SplashScreenActivity:ʾ	I
    //   1336: iload_1
    //   1337: iconst_2
    //   1338: irem
    //   1339: ifeq +6 -> 1345
    //   1342: goto -722 -> 620
    //   1345: goto -486 -> 859
    //   1348: aload_0
    //   1349: invokestatic 877	o/Gz:ˏ	(Landroid/content/Context;)Lo/Gz;
    //   1352: ldc_w 878
    //   1355: invokevirtual 881	o/Gz:ॱ	(I)Z
    //   1358: ifne +6 -> 1364
    //   1361: goto -522 -> 839
    //   1364: goto +22 -> 1386
    //   1367: aload_0
    //   1368: invokestatic 877	o/Gz:ˏ	(Landroid/content/Context;)Lo/Gz;
    //   1371: ldc_w 882
    //   1374: invokevirtual 884	o/Gz:ˊ	(I)Z
    //   1377: ifeq +6 -> 1383
    //   1380: goto +41 -> 1421
    //   1383: goto +43 -> 1426
    //   1386: iconst_0
    //   1387: istore_1
    //   1388: goto +43 -> 1431
    //   1391: goto -70 -> 1321
    //   1394: getstatic 32	ro/btrl/boot/ui/activity/SplashScreenActivity:ʾ	I
    //   1397: bipush 23
    //   1399: iadd
    //   1400: istore_1
    //   1401: iload_1
    //   1402: sipush 128
    //   1405: irem
    //   1406: putstatic 34	ro/btrl/boot/ui/activity/SplashScreenActivity:ˈ	I
    //   1409: iload_1
    //   1410: iconst_2
    //   1411: irem
    //   1412: ifne +6 -> 1418
    //   1415: goto -311 -> 1104
    //   1418: goto -344 -> 1074
    //   1421: iconst_1
    //   1422: istore_1
    //   1423: goto -316 -> 1107
    //   1426: iconst_0
    //   1427: istore_1
    //   1428: goto -321 -> 1107
    //   1431: iload_1
    //   1432: tableswitch	default:+24->1456, 0:+-1240->192, 1:+-65->1367
    //   1456: goto -89 -> 1367
    //   1459: return
    //   1460: astore_3
    //   1461: aload_3
    //   1462: athrow
    // Local variable table:
    //   start	length	slot	name	signature
    //   0	1463	0	this	SplashScreenActivity
    //   4	1428	1	i	int
    //   181	884	2	bool	boolean
    //   11	16	3	localObject1	Object
    //   79	1	3	localObject2	Object
    //   83	88	3	localObject3	Object
    //   242	1	3	str1	String
    //   299	95	3	localObject4	Object
    //   438	16	3	localObject5	Object
    //   519	1	3	localObject6	Object
    //   523	76	3	localObject7	Object
    //   685	1	3	str2	String
    //   729	99	3	localObject8	Object
    //   856	2	3	localException1	Exception
    //   866	16	3	localObject9	Object
    //   931	1	3	localObject10	Object
    //   941	104	3	localObject11	Object
    //   1144	16	3	localObject12	Object
    //   1209	1	3	localObject13	Object
    //   1213	86	3	localObject14	Object
    //   1460	2	3	localException2	Exception
    //   16	1210	4	localObject15	Object
    // Exception table:
    //   from	to	target	type
    //   28	80	11	finally
    //   100	182	83	finally
    //   316	404	299	finally
    //   455	520	438	finally
    //   540	610	523	finally
    //   746	838	729	finally
    //   1321	1328	856	java/lang/Exception
    //   1328	1336	856	java/lang/Exception
    //   883	932	866	finally
    //   958	1064	941	finally
    //   1161	1210	1144	finally
    //   1230	1318	1213	finally
    //   1145	1151	1460	java/lang/Exception
    //   1156	1159	1460	java/lang/Exception
    //   1159	1161	1460	java/lang/Exception
    //   1214	1220	1460	java/lang/Exception
    //   1225	1228	1460	java/lang/Exception
    //   1228	1230	1460	java/lang/Exception
  }
  
  public void onStop()
  {
    break label12;
    int i = 39;
    break label102;
    for (;;)
    {
      label12:
      i = 1;
      break label193;
      label20:
      i = 46;
      break label102;
      super.onStop();
      try
      {
        sH localSH = this.ʽॱ;
        if (localSH != null) {
          break label20;
        }
      }
      catch (Exception localException)
      {
        throw localException;
      }
      for (;;)
      {
        i = ʾ + 117;
        ˈ = i % 128;
        if (i % 2 == 0) {
          break label169;
        }
        break label175;
        i = ˈ + 55;
        ʾ = i % 128;
        if (i % 2 != 0) {
          break;
        }
        break;
        label102:
        switch (i)
        {
        }
      }
      i = ˈ + 25;
      ʾ = i % 128;
      if (i % 2 != 0) {
        return;
      }
      return;
      this.ʽॱ.ॱ();
      for (;;)
      {
        break;
        label169:
        break label175;
      }
      label175:
      if (this.ʽॱ.ˎ()) {
        break label219;
      }
    }
    for (;;)
    {
      label193:
      switch (i)
      {
      }
      break;
      label219:
      i = 0;
    }
  }
  
  public void ʻॱ()
  {
    break label60;
    int i = 14;
    break label89;
    i = ʾ + 5;
    ˈ = i % 128;
    if (i % 2 != 0)
    {
      return;
      label60:
      for (;;)
      {
        i = ʾ + 71;
        ˈ = i % 128;
        if (i % 2 == 0) {
          break label75;
        }
        break;
      }
      ॱˋ();
      throw new NullPointerException();
      label75:
      i = 79;
    }
    for (;;)
    {
      ॱˋ();
      break;
      return;
      label89:
      switch (i)
      {
      }
    }
  }
  
  /* Error */
  public void ˋ(Fg paramFg, boolean paramBoolean)
  {
    // Byte code:
    //   0: goto +78 -> 78
    //   3: getstatic 32	ro/btrl/boot/ui/activity/SplashScreenActivity:ʾ	I
    //   6: bipush 65
    //   8: iadd
    //   9: istore_3
    //   10: iload_3
    //   11: sipush 128
    //   14: irem
    //   15: putstatic 34	ro/btrl/boot/ui/activity/SplashScreenActivity:ˈ	I
    //   18: iload_3
    //   19: iconst_2
    //   20: irem
    //   21: ifne +6 -> 27
    //   24: goto +636 -> 660
    //   27: goto +251 -> 278
    //   30: return
    //   31: aload_1
    //   32: ifnull +6 -> 38
    //   35: goto +912 -> 947
    //   38: goto +255 -> 293
    //   41: iconst_0
    //   42: istore_3
    //   43: goto +110 -> 153
    //   46: iload_3
    //   47: tableswitch	default:+21->68, 0:+-17->30, 1:+868->915
    //   68: return
    //   69: iconst_1
    //   70: istore_3
    //   71: goto +254 -> 325
    //   74: astore_1
    //   75: aload_1
    //   76: athrow
    //   77: return
    //   78: goto +173 -> 251
    //   81: new 607	java/lang/NullPointerException
    //   84: dup
    //   85: invokespecial 608	java/lang/NullPointerException:<init>	()V
    //   88: athrow
    //   89: astore_1
    //   90: aload_1
    //   91: athrow
    //   92: invokestatic 903	o/Il:ˋ	()Lo/Il;
    //   95: aload_0
    //   96: invokevirtual 473	ro/btrl/boot/ui/activity/SplashScreenActivity:ॱˊ	()Landroid/content/Context;
    //   99: aload_1
    //   100: invokevirtual 908	o/Fg:ˎ	()Lo/Fd;
    //   103: invokevirtual 911	o/Il:ˊ	(Landroid/content/Context;Lo/Fd;)Z
    //   106: ifeq +6 -> 112
    //   109: goto +108 -> 217
    //   112: goto +191 -> 303
    //   115: goto +268 -> 383
    //   118: iload_3
    //   119: tableswitch	default:+21->140, 0:+-116->3, 1:+179->298
    //   140: goto -137 -> 3
    //   143: iconst_0
    //   144: istore_3
    //   145: goto +180 -> 325
    //   148: iconst_1
    //   149: istore_3
    //   150: goto -35 -> 115
    //   153: iload_3
    //   154: tableswitch	default:+22->176, 0:+-6->148, 1:+144->298
    //   176: goto -28 -> 148
    //   179: bipush 10
    //   181: istore_3
    //   182: goto +734 -> 916
    //   185: aload_0
    //   186: invokevirtual 914	ro/btrl/boot/ui/activity/SplashScreenActivity:finish	()V
    //   189: return
    //   190: iload_3
    //   191: lookupswitch	default:+25->216, 21:+-110->81, 67:+-114->77
    //   216: return
    //   217: goto +134 -> 351
    //   220: iload_3
    //   221: lookupswitch	default:+27->248, 57:+217->438, 70:+444->665
    //   248: goto +190 -> 438
    //   251: getstatic 34	ro/btrl/boot/ui/activity/SplashScreenActivity:ˈ	I
    //   254: bipush 69
    //   256: iadd
    //   257: istore_3
    //   258: iload_3
    //   259: sipush 128
    //   262: irem
    //   263: putstatic 32	ro/btrl/boot/ui/activity/SplashScreenActivity:ʾ	I
    //   266: iload_3
    //   267: iconst_2
    //   268: irem
    //   269: ifeq +6 -> 275
    //   272: goto +147 -> 419
    //   275: goto +138 -> 413
    //   278: iconst_0
    //   279: istore_3
    //   280: goto +610 -> 890
    //   283: iconst_0
    //   284: istore_3
    //   285: goto -239 -> 46
    //   288: iconst_1
    //   289: istore_3
    //   290: goto -244 -> 46
    //   293: iconst_1
    //   294: istore_3
    //   295: goto -177 -> 118
    //   298: iconst_0
    //   299: istore_3
    //   300: goto +83 -> 383
    //   303: new 916	o/IG
    //   306: dup
    //   307: aload_0
    //   308: iconst_1
    //   309: invokespecial 919	o/IG:<init>	(Landroid/content/Context;Z)V
    //   312: invokevirtual 922	o/IG:ˏ	()Lo/ᐸ;
    //   315: pop
    //   316: goto +636 -> 952
    //   319: bipush 67
    //   321: istore_3
    //   322: goto -132 -> 190
    //   325: iload_3
    //   326: tableswitch	default:+22->348, 0:+-141->185, 1:+-295->31
    //   348: goto -163 -> 185
    //   351: getstatic 32	ro/btrl/boot/ui/activity/SplashScreenActivity:ʾ	I
    //   354: bipush 25
    //   356: iadd
    //   357: istore_3
    //   358: iload_3
    //   359: sipush 128
    //   362: irem
    //   363: putstatic 34	ro/btrl/boot/ui/activity/SplashScreenActivity:ˈ	I
    //   366: iload_3
    //   367: iconst_2
    //   368: irem
    //   369: ifne +6 -> 375
    //   372: goto +282 -> 654
    //   375: goto -56 -> 319
    //   378: iconst_1
    //   379: istore_3
    //   380: goto -227 -> 153
    //   383: iload_3
    //   384: ifeq +6 -> 390
    //   387: goto -295 -> 92
    //   390: goto -87 -> 303
    //   393: aload_1
    //   394: invokevirtual 908	o/Fg:ˎ	()Lo/Fd;
    //   397: astore 4
    //   399: aconst_null
    //   400: arraylength
    //   401: istore_3
    //   402: aload 4
    //   404: ifnull +6 -> 410
    //   407: goto +478 -> 885
    //   410: goto -231 -> 179
    //   413: bipush 57
    //   415: istore_3
    //   416: goto -196 -> 220
    //   419: bipush 70
    //   421: istore_3
    //   422: goto -202 -> 220
    //   425: aload_1
    //   426: invokevirtual 908	o/Fg:ˎ	()Lo/Fd;
    //   429: ifnull +6 -> 435
    //   432: goto -391 -> 41
    //   435: goto -57 -> 378
    //   438: goto +20 -> 458
    //   441: astore 4
    //   443: aload 4
    //   445: invokevirtual 419	java/lang/Throwable:getCause	()Ljava/lang/Throwable;
    //   448: astore_1
    //   449: aload_1
    //   450: ifnull +5 -> 455
    //   453: aload_1
    //   454: athrow
    //   455: aload 4
    //   457: athrow
    //   458: aload_0
    //   459: invokevirtual 425	android/content/Context:getPackageName	()Ljava/lang/String;
    //   462: invokevirtual 431	java/lang/String:length	()I
    //   465: bipush 7
    //   467: isub
    //   468: aload_0
    //   469: invokevirtual 516	android/content/Context:getApplicationInfo	()Landroid/content/pm/ApplicationInfo;
    //   472: getfield 521	android/content/pm/ApplicationInfo:targetSdkVersion	I
    //   475: sipush 388
    //   478: iadd
    //   479: aload_0
    //   480: invokevirtual 425	android/content/Context:getPackageName	()Ljava/lang/String;
    //   483: invokevirtual 431	java/lang/String:length	()I
    //   486: sipush 30242
    //   489: iadd
    //   490: i2c
    //   491: invokestatic 456	o/O:ˋ	(IIC)Ljava/lang/Object;
    //   494: checkcast 458	java/lang/Class
    //   497: ldc_w 570
    //   500: aconst_null
    //   501: invokevirtual 463	java/lang/Class:getMethod	(Ljava/lang/String;[Ljava/lang/Class;)Ljava/lang/reflect/Method;
    //   504: aconst_null
    //   505: aconst_null
    //   506: invokevirtual 469	java/lang/reflect/Method:invoke	(Ljava/lang/Object;[Ljava/lang/Object;)Ljava/lang/Object;
    //   509: astore 4
    //   511: getstatic 573	o/Gw:NOT_REGISTERED	Lo/Gw;
    //   514: astore 5
    //   516: goto +20 -> 536
    //   519: astore 4
    //   521: aload 4
    //   523: invokevirtual 419	java/lang/Throwable:getCause	()Ljava/lang/Throwable;
    //   526: astore_1
    //   527: aload_1
    //   528: ifnull +5 -> 533
    //   531: aload_1
    //   532: athrow
    //   533: aload 4
    //   535: athrow
    //   536: aload_0
    //   537: invokevirtual 435	android/content/Context:getResources	()Landroid/content/res/Resources;
    //   540: ldc_w 747
    //   543: invokevirtual 442	android/content/res/Resources:getString	(I)Ljava/lang/String;
    //   546: bipush 35
    //   548: bipush 40
    //   550: invokevirtual 446	java/lang/String:substring	(II)Ljava/lang/String;
    //   553: iconst_3
    //   554: invokevirtual 450	java/lang/String:codePointAt	(I)I
    //   557: sipush 248
    //   560: isub
    //   561: aload_0
    //   562: invokevirtual 435	android/content/Context:getResources	()Landroid/content/res/Resources;
    //   565: ldc_w 923
    //   568: invokevirtual 442	android/content/res/Resources:getString	(I)Ljava/lang/String;
    //   571: iconst_0
    //   572: iconst_4
    //   573: invokevirtual 446	java/lang/String:substring	(II)Ljava/lang/String;
    //   576: invokevirtual 431	java/lang/String:length	()I
    //   579: sipush 409
    //   582: iadd
    //   583: aload_0
    //   584: invokevirtual 435	android/content/Context:getResources	()Landroid/content/res/Resources;
    //   587: ldc_w 924
    //   590: invokevirtual 442	android/content/res/Resources:getString	(I)Ljava/lang/String;
    //   593: iconst_0
    //   594: iconst_4
    //   595: invokevirtual 446	java/lang/String:substring	(II)Ljava/lang/String;
    //   598: iconst_2
    //   599: invokevirtual 450	java/lang/String:codePointAt	(I)I
    //   602: sipush 30242
    //   605: iadd
    //   606: i2c
    //   607: invokestatic 456	o/O:ˋ	(IIC)Ljava/lang/Object;
    //   610: checkcast 458	java/lang/Class
    //   613: ldc_w 576
    //   616: iconst_1
    //   617: anewarray 458	java/lang/Class
    //   620: dup
    //   621: iconst_0
    //   622: ldc_w 547
    //   625: aastore
    //   626: invokevirtual 463	java/lang/Class:getMethod	(Ljava/lang/String;[Ljava/lang/Class;)Ljava/lang/reflect/Method;
    //   629: aload 4
    //   631: iconst_1
    //   632: anewarray 478	java/lang/Object
    //   635: dup
    //   636: iconst_0
    //   637: aload 5
    //   639: aastore
    //   640: invokevirtual 469	java/lang/reflect/Method:invoke	(Ljava/lang/Object;[Ljava/lang/Object;)Ljava/lang/Object;
    //   643: pop
    //   644: iload_2
    //   645: ifeq +6 -> 651
    //   648: goto -505 -> 143
    //   651: goto -582 -> 69
    //   654: bipush 21
    //   656: istore_3
    //   657: goto -467 -> 190
    //   660: iconst_1
    //   661: istore_3
    //   662: goto +228 -> 890
    //   665: goto +20 -> 685
    //   668: astore_1
    //   669: aload_1
    //   670: invokevirtual 419	java/lang/Throwable:getCause	()Ljava/lang/Throwable;
    //   673: astore 4
    //   675: aload 4
    //   677: ifnull +6 -> 683
    //   680: aload 4
    //   682: athrow
    //   683: aload_1
    //   684: athrow
    //   685: aload_0
    //   686: invokevirtual 425	android/content/Context:getPackageName	()Ljava/lang/String;
    //   689: iconst_1
    //   690: invokevirtual 450	java/lang/String:codePointAt	(I)I
    //   693: bipush 107
    //   695: isub
    //   696: aload_0
    //   697: invokevirtual 435	android/content/Context:getResources	()Landroid/content/res/Resources;
    //   700: ldc_w 925
    //   703: invokevirtual 442	android/content/res/Resources:getString	(I)Ljava/lang/String;
    //   706: iconst_0
    //   707: iconst_4
    //   708: invokevirtual 446	java/lang/String:substring	(II)Ljava/lang/String;
    //   711: iconst_1
    //   712: invokevirtual 450	java/lang/String:codePointAt	(I)I
    //   715: sipush 387
    //   718: iadd
    //   719: aload_0
    //   720: invokevirtual 435	android/content/Context:getResources	()Landroid/content/res/Resources;
    //   723: ldc_w 926
    //   726: invokevirtual 442	android/content/res/Resources:getString	(I)Ljava/lang/String;
    //   729: iconst_0
    //   730: iconst_4
    //   731: invokevirtual 446	java/lang/String:substring	(II)Ljava/lang/String;
    //   734: iconst_1
    //   735: invokevirtual 450	java/lang/String:codePointAt	(I)I
    //   738: sipush 30227
    //   741: iadd
    //   742: i2c
    //   743: invokestatic 456	o/O:ˋ	(IIC)Ljava/lang/Object;
    //   746: checkcast 458	java/lang/Class
    //   749: ldc_w 570
    //   752: aconst_null
    //   753: invokevirtual 463	java/lang/Class:getMethod	(Ljava/lang/String;[Ljava/lang/Class;)Ljava/lang/reflect/Method;
    //   756: aconst_null
    //   757: aconst_null
    //   758: invokevirtual 469	java/lang/reflect/Method:invoke	(Ljava/lang/Object;[Ljava/lang/Object;)Ljava/lang/Object;
    //   761: astore 5
    //   763: getstatic 573	o/Gw:NOT_REGISTERED	Lo/Gw;
    //   766: astore 4
    //   768: goto +20 -> 788
    //   771: astore 4
    //   773: aload 4
    //   775: invokevirtual 419	java/lang/Throwable:getCause	()Ljava/lang/Throwable;
    //   778: astore_1
    //   779: aload_1
    //   780: ifnull +5 -> 785
    //   783: aload_1
    //   784: athrow
    //   785: aload 4
    //   787: athrow
    //   788: aload_0
    //   789: invokevirtual 435	android/content/Context:getResources	()Landroid/content/res/Resources;
    //   792: ldc_w 927
    //   795: invokevirtual 442	android/content/res/Resources:getString	(I)Ljava/lang/String;
    //   798: iconst_0
    //   799: iconst_5
    //   800: invokevirtual 446	java/lang/String:substring	(II)Ljava/lang/String;
    //   803: iconst_3
    //   804: invokevirtual 450	java/lang/String:codePointAt	(I)I
    //   807: bipush 8
    //   809: isub
    //   810: aload_0
    //   811: invokevirtual 516	android/content/Context:getApplicationInfo	()Landroid/content/pm/ApplicationInfo;
    //   814: getfield 521	android/content/pm/ApplicationInfo:targetSdkVersion	I
    //   817: sipush 388
    //   820: iadd
    //   821: aload_0
    //   822: invokevirtual 516	android/content/Context:getApplicationInfo	()Landroid/content/pm/ApplicationInfo;
    //   825: getfield 521	android/content/pm/ApplicationInfo:targetSdkVersion	I
    //   828: sipush 30228
    //   831: iadd
    //   832: i2c
    //   833: invokestatic 456	o/O:ˋ	(IIC)Ljava/lang/Object;
    //   836: checkcast 458	java/lang/Class
    //   839: ldc_w 576
    //   842: iconst_1
    //   843: anewarray 458	java/lang/Class
    //   846: dup
    //   847: iconst_0
    //   848: ldc_w 547
    //   851: aastore
    //   852: invokevirtual 463	java/lang/Class:getMethod	(Ljava/lang/String;[Ljava/lang/Class;)Ljava/lang/reflect/Method;
    //   855: aload 5
    //   857: iconst_1
    //   858: anewarray 478	java/lang/Object
    //   861: dup
    //   862: iconst_0
    //   863: aload 4
    //   865: aastore
    //   866: invokevirtual 469	java/lang/reflect/Method:invoke	(Ljava/lang/Object;[Ljava/lang/Object;)Ljava/lang/Object;
    //   869: pop
    //   870: bipush 63
    //   872: iconst_0
    //   873: idiv
    //   874: istore_3
    //   875: iload_2
    //   876: ifeq +6 -> 882
    //   879: goto -694 -> 185
    //   882: goto -851 -> 31
    //   885: iconst_0
    //   886: istore_3
    //   887: goto +29 -> 916
    //   890: iload_3
    //   891: tableswitch	default:+21->912, 0:+-466->425, 1:+-498->393
    //   912: goto -487 -> 425
    //   915: return
    //   916: iload_3
    //   917: lookupswitch	default:+27->944, 0:+-769->148, 10:+-619->298
    //   944: goto -796 -> 148
    //   947: iconst_0
    //   948: istore_3
    //   949: goto -831 -> 118
    //   952: getstatic 34	ro/btrl/boot/ui/activity/SplashScreenActivity:ˈ	I
    //   955: istore_3
    //   956: iload_3
    //   957: bipush 65
    //   959: iadd
    //   960: istore_3
    //   961: iload_3
    //   962: sipush 128
    //   965: irem
    //   966: putstatic 32	ro/btrl/boot/ui/activity/SplashScreenActivity:ʾ	I
    //   969: iload_3
    //   970: iconst_2
    //   971: irem
    //   972: ifeq +6 -> 978
    //   975: goto -692 -> 283
    //   978: goto -690 -> 288
    // Local variable table:
    //   start	length	slot	name	signature
    //   0	981	0	this	SplashScreenActivity
    //   0	981	1	paramFg	Fg
    //   0	981	2	paramBoolean	boolean
    //   9	963	3	i	int
    //   397	6	4	localFd	o.Fd
    //   441	15	4	localObject1	Object
    //   509	1	4	localObject2	Object
    //   519	111	4	localObject3	Object
    //   673	94	4	localObject4	Object
    //   771	93	4	localObject5	Object
    //   514	342	5	localObject6	Object
    // Exception table:
    //   from	to	target	type
    //   669	675	74	java/lang/Exception
    //   680	683	74	java/lang/Exception
    //   683	685	74	java/lang/Exception
    //   961	969	74	java/lang/Exception
    //   763	768	89	java/lang/Exception
    //   773	779	89	java/lang/Exception
    //   783	785	89	java/lang/Exception
    //   785	788	89	java/lang/Exception
    //   952	956	89	java/lang/Exception
    //   458	511	441	finally
    //   536	644	519	finally
    //   685	763	668	finally
    //   788	870	771	finally
  }
  
  /* Error */
  public int ˎ()
  {
    // Byte code:
    //   0: goto +155 -> 155
    //   3: iload_2
    //   4: lookupswitch	default:+28->32, 1:+31->35, 57:+97->101
    //   32: goto +69 -> 101
    //   35: iload_1
    //   36: ireturn
    //   37: iload_1
    //   38: lookupswitch	default:+26->64, 24:+120->158, 73:+56->94
    //   64: goto +94 -> 158
    //   67: getstatic 34	ro/btrl/boot/ui/activity/SplashScreenActivity:ˈ	I
    //   70: bipush 23
    //   72: iadd
    //   73: istore_2
    //   74: iload_2
    //   75: sipush 128
    //   78: irem
    //   79: putstatic 32	ro/btrl/boot/ui/activity/SplashScreenActivity:ʾ	I
    //   82: iload_2
    //   83: iconst_2
    //   84: irem
    //   85: ifeq +6 -> 91
    //   88: goto +20 -> 108
    //   91: goto +23 -> 114
    //   94: getstatic 932	o/Dv$ˋ:activity_splash_screen	I
    //   97: istore_1
    //   98: goto -31 -> 67
    //   101: bipush 32
    //   103: iconst_0
    //   104: idiv
    //   105: istore_2
    //   106: iload_1
    //   107: ireturn
    //   108: bipush 57
    //   110: istore_2
    //   111: goto -108 -> 3
    //   114: iconst_1
    //   115: istore_2
    //   116: goto -113 -> 3
    //   119: astore_3
    //   120: aload_3
    //   121: athrow
    //   122: bipush 73
    //   124: istore_1
    //   125: goto -88 -> 37
    //   128: getstatic 34	ro/btrl/boot/ui/activity/SplashScreenActivity:ˈ	I
    //   131: bipush 103
    //   133: iadd
    //   134: istore_1
    //   135: iload_1
    //   136: sipush 128
    //   139: irem
    //   140: putstatic 32	ro/btrl/boot/ui/activity/SplashScreenActivity:ʾ	I
    //   143: iload_1
    //   144: iconst_2
    //   145: irem
    //   146: ifeq +6 -> 152
    //   149: goto +21 -> 170
    //   152: goto -30 -> 122
    //   155: goto -27 -> 128
    //   158: getstatic 932	o/Dv$ˋ:activity_splash_screen	I
    //   161: istore_1
    //   162: bipush 8
    //   164: iconst_0
    //   165: idiv
    //   166: istore_2
    //   167: goto -100 -> 67
    //   170: bipush 24
    //   172: istore_1
    //   173: goto -136 -> 37
    // Local variable table:
    //   start	length	slot	name	signature
    //   0	176	0	this	SplashScreenActivity
    //   35	138	1	i	int
    //   3	164	2	j	int
    //   119	2	3	localException	Exception
    // Exception table:
    //   from	to	target	type
    //   158	162	119	java/lang/Exception
  }
  
  public void ॱˋ()
  {
    for (;;)
    {
      label3:
      int i = 1;
      break label81;
      label11:
      ˊ(getPackageName().codePointAt(3) - 4, (char)(getPackageName().codePointAt(3) + 12248), getResources().getString(2131755379).substring(0, 1).length() + 18).intern();
      getPackageManager().getInstallerPackageName(getPackageName());
      ˉ();
      break label144;
      for (;;)
      {
        switch (i)
        {
        default: 
          label81:
          return;
          i = ˈ + 43;
          ʾ = i % 128;
          if (i % 2 != 0) {
            break label3;
          }
          break label11;
          i = 0;
        }
      }
      i = 81 / 0;
      return;
      return;
      try
      {
        label144:
        i = ˈ;
        i += 107;
        ʾ = i % 128;
        if (i % 2 != 0) {}
      }
      catch (Exception localException)
      {
        throw localException;
      }
    }
  }
  
  public boolean ॱᐝ()
  {
    break label38;
    label5:
    int i;
    for (;;)
    {
      return false;
      i = ˈ + 79;
      ʾ = i % 128;
      if (i % 2 != 0) {
        break label47;
      }
      break;
    }
    for (;;)
    {
      break;
      label38:
      break label5;
      i = 52;
      break label50;
      label47:
      i = 16;
      label50:
      switch (i)
      {
      }
    }
  }
}
