package ro.btrl.boot.ui.activity;

import android.content.Context;
import android.content.Intent;
import android.content.pm.ApplicationInfo;
import android.content.res.Resources;
import android.databinding.ViewDataBinding;
import android.view.View;
import android.view.ViewTreeObserver.OnGlobalLayoutListener;
import android.webkit.WebView;
import android.webkit.WebViewClient;
import android.widget.Button;
import android.widget.EditText;
import java.util.Arrays;
import o.DK.iF;
import o.DK.ˋ;
import o.Dv.iF;
import o.Dv.ˋ;
import o.Dx;
import o.H;
import o.Hp;
import o.Ic;
import o.Ix;
import o.aA;
import o.aD.If;
import o.j;
import o.oN;
import o.oP;
import o.uv;
import o.vq;
import o.vw;

public final class TncActivity
  extends Ix<DK.iF, Dx>
  implements DK.ˋ
{
  private static long ʼॱ;
  private static char[] ʽॱ;
  private static int ʾ;
  private static int ʿ = 0;
  private static byte ॱˎ;
  @uv
  public DK.iF mPresenter;
  
  static
  {
    ʾ = 1;
    ˊˊ();
    ॱˎ = -102;
    int i = ʾ + 113;
    ʿ = i % 128;
    if (i % 2 != 0) {}
  }
  
  public TncActivity() {}
  
  static void ˊˊ()
  {
    ʼॱ = -2450657152492633407L;
    ʽॱ = new char[] { -23181, -22641, -24338, -21192, -20887, -22338, -18954, -18899, -19597, -16987, 12398, 12928, 13800, 14382, 15203, 15791, 8427, 8995, 21903, 22369, 20489, 24015, 24194, 22606, 17674, 18114, 17348, 19807, 19981, 19419, 29827, 30300, 29485, 31939, 31126, 31600, 25631, 25055, 25234, 27742, 26880, 27356, 6037, 4437, 4619, -3586, -3285, -2967, -1612, -1318, -967, -7814, -7497, -6174, -5832, -5535, 8818, 8361, 10215, 10760, 10605, 12199, 13029, 12589, 108, 680, 1521, 2103, 2913, 3499, 4323, 4917, -15966, -15509, -15324, -13843, -13649, -13245, -11995, -11548, -10307, -9877, -9666, -8193, 23016, 23350, 23652, 20898, 103, 676, 1526, 2064, 2928, 3511, 4335, 4905, 5743, 6369, 7128, 7781, 8575, 9145, 9980, 10534, 11390, 11958, 12732, 13366, 14201, 14772, 15615, 16187, 16967, 17578, 18431, 18997, 19816, 20468, 28462, 28132, 27312, 26470, 25710, 25325, 32675, 31853, 31019, 30627, 29853, 29051, 20026, 19680, 18852, 18028, 17274, 16883, 24249, 23397, 22589, 22256, 21414, 20539, 11578, 11250, 10412, 9586, 8761, 8429, 15862, 14907, 14158, 13764, 12948, 3904, 3091, 2696, 109, 643, 1515, 2093, 2912, 3500, 4328, 4896, 5670, 6330, 7151, 7717, 8552, 9096, 9955, 10542, 11385, 11965, 12752, 13351, 14202, -13612, -14278, -12462, -15724, -15911, -14571, -9647, -9831, -9057, -11759, -11952, -11119, -5168, -5884, -5053, -7262, -6456, -7127, 118, 680, 1511, 2100, 11787, 11493, 11149, 9803, 9478, 9162, 16014, 15686, 14400, 14026, 13697, 12364, 3843, 3527, 2221, 1869, 543, 195, 8096, 6736, 6410, 6087, 99, 686, 1519, 2157, 2915, 3498, 4329, 4896, 5732, 6316, -9189, -8512, -9825, -11204, -10386, -11857, -13087, -12500, -13705, -15190, 85, 661, 1476, 2158, 2876 };
  }
  
  private final void ˎˏ()
  {
    for (;;)
    {
      ((Dx)this.ॱˊ).ʽ.setMOnScrollStatusChangedListener((aD.If)new If(this));
      ((Dx)this.ॱˊ).ʽ.setMOnGlobalLayoutListener((ViewTreeObserver.OnGlobalLayoutListener)new ˊ(this));
      break;
    }
    int i;
    do
    {
      return;
      i = ʿ + 121;
      ʾ = i % 128;
    } while (i % 2 == 0);
  }
  
  /* Error */
  private final void ˏˏ()
  {
    // Byte code:
    //   0: goto +241 -> 241
    //   3: goto +265 -> 268
    //   6: astore_2
    //   7: aload_0
    //   8: getfield 305	ro/btrl/boot/ui/activity/TncActivity:ॱˊ	Landroid/databinding/ViewDataBinding;
    //   11: astore_2
    //   12: aload_2
    //   13: aload_0
    //   14: invokevirtual 337	android/content/Context:getResources	()Landroid/content/res/Resources;
    //   17: ldc_w 338
    //   20: invokevirtual 344	android/content/res/Resources:getString	(I)Ljava/lang/String;
    //   23: iconst_0
    //   24: iconst_4
    //   25: invokevirtual 350	java/lang/String:substring	(II)Ljava/lang/String;
    //   28: iconst_2
    //   29: invokevirtual 354	java/lang/String:codePointAt	(I)I
    //   32: iconst_1
    //   33: isub
    //   34: aload_0
    //   35: invokevirtual 337	android/content/Context:getResources	()Landroid/content/res/Resources;
    //   38: ldc_w 355
    //   41: invokevirtual 344	android/content/res/Resources:getString	(I)Ljava/lang/String;
    //   44: iconst_0
    //   45: bipush 7
    //   47: invokevirtual 350	java/lang/String:substring	(II)Ljava/lang/String;
    //   50: invokevirtual 359	java/lang/String:length	()I
    //   53: sipush 12284
    //   56: iadd
    //   57: i2c
    //   58: aload_0
    //   59: invokevirtual 337	android/content/Context:getResources	()Landroid/content/res/Resources;
    //   62: ldc_w 360
    //   65: invokevirtual 344	android/content/res/Resources:getString	(I)Ljava/lang/String;
    //   68: iconst_0
    //   69: bipush 8
    //   71: invokevirtual 350	java/lang/String:substring	(II)Ljava/lang/String;
    //   74: iconst_0
    //   75: invokevirtual 354	java/lang/String:codePointAt	(I)I
    //   78: iconst_3
    //   79: iadd
    //   80: invokestatic 364	ro/btrl/boot/ui/activity/TncActivity:ॱ	(ICI)Ljava/lang/String;
    //   83: invokevirtual 368	java/lang/String:intern	()Ljava/lang/String;
    //   86: invokestatic 373	o/vq:ˋ	(Ljava/lang/Object;Ljava/lang/String;)V
    //   89: aload_2
    //   90: checkcast 307	o/Dx
    //   93: iconst_1
    //   94: invokevirtual 376	o/Dx:ॱ	(Z)V
    //   97: goto +6 -> 103
    //   100: goto +28 -> 128
    //   103: getstatic 34	ro/btrl/boot/ui/activity/TncActivity:ʾ	I
    //   106: istore_1
    //   107: iload_1
    //   108: bipush 121
    //   110: iadd
    //   111: istore_1
    //   112: iload_1
    //   113: sipush 128
    //   116: irem
    //   117: putstatic 32	ro/btrl/boot/ui/activity/TncActivity:ʿ	I
    //   120: iload_1
    //   121: iconst_2
    //   122: irem
    //   123: ifeq +4 -> 127
    //   126: return
    //   127: return
    //   128: aload_0
    //   129: aconst_null
    //   130: aconst_null
    //   131: iconst_1
    //   132: anewarray 346	java/lang/String
    //   135: dup
    //   136: iconst_0
    //   137: aload_0
    //   138: invokevirtual 380	android/content/Context:getApplicationInfo	()Landroid/content/pm/ApplicationInfo;
    //   141: getfield 385	android/content/pm/ApplicationInfo:targetSdkVersion	I
    //   144: sipush 196
    //   147: iadd
    //   148: aload_0
    //   149: invokevirtual 337	android/content/Context:getResources	()Landroid/content/res/Resources;
    //   152: ldc_w 386
    //   155: invokevirtual 344	android/content/res/Resources:getString	(I)Ljava/lang/String;
    //   158: iconst_0
    //   159: iconst_5
    //   160: invokevirtual 350	java/lang/String:substring	(II)Ljava/lang/String;
    //   163: invokevirtual 359	java/lang/String:length	()I
    //   166: iconst_5
    //   167: isub
    //   168: i2c
    //   169: aload_0
    //   170: invokevirtual 337	android/content/Context:getResources	()Landroid/content/res/Resources;
    //   173: ldc_w 387
    //   176: invokevirtual 344	android/content/res/Resources:getString	(I)Ljava/lang/String;
    //   179: iconst_0
    //   180: iconst_5
    //   181: invokevirtual 350	java/lang/String:substring	(II)Ljava/lang/String;
    //   184: invokevirtual 359	java/lang/String:length	()I
    //   187: iconst_5
    //   188: iadd
    //   189: invokestatic 364	ro/btrl/boot/ui/activity/TncActivity:ॱ	(ICI)Ljava/lang/String;
    //   192: invokevirtual 368	java/lang/String:intern	()Ljava/lang/String;
    //   195: aastore
    //   196: iconst_0
    //   197: aconst_null
    //   198: aconst_null
    //   199: aconst_null
    //   200: aconst_null
    //   201: invokestatic 393	o/bZ:ˎ	(Landroid/accounts/Account;Ljava/util/ArrayList;[Ljava/lang/String;ZLjava/lang/String;Ljava/lang/String;[Ljava/lang/String;Landroid/os/Bundle;)Landroid/content/Intent;
    //   204: iconst_5
    //   205: invokevirtual 397	ro/btrl/boot/ui/activity/TncActivity:startActivityForResult	(Landroid/content/Intent;I)V
    //   208: goto +36 -> 244
    //   211: getstatic 32	ro/btrl/boot/ui/activity/TncActivity:ʿ	I
    //   214: bipush 113
    //   216: iadd
    //   217: istore_1
    //   218: iload_1
    //   219: sipush 128
    //   222: irem
    //   223: putstatic 34	ro/btrl/boot/ui/activity/TncActivity:ʾ	I
    //   226: iload_1
    //   227: iconst_2
    //   228: irem
    //   229: ifne +6 -> 235
    //   232: goto -132 -> 100
    //   235: goto -107 -> 128
    //   238: astore_2
    //   239: aload_2
    //   240: athrow
    //   241: goto -30 -> 211
    //   244: getstatic 34	ro/btrl/boot/ui/activity/TncActivity:ʾ	I
    //   247: bipush 61
    //   249: iadd
    //   250: istore_1
    //   251: iload_1
    //   252: sipush 128
    //   255: irem
    //   256: putstatic 32	ro/btrl/boot/ui/activity/TncActivity:ʿ	I
    //   259: iload_1
    //   260: iconst_2
    //   261: irem
    //   262: ifeq +6 -> 268
    //   265: goto -262 -> 3
    //   268: goto -165 -> 103
    // Local variable table:
    //   start	length	slot	name	signature
    //   0	271	0	this	TncActivity
    //   106	156	1	i	int
    //   6	1	2	localActivityNotFoundException	android.content.ActivityNotFoundException
    //   11	79	2	localViewDataBinding	ViewDataBinding
    //   238	2	2	localException	Exception
    // Exception table:
    //   from	to	target	type
    //   128	208	6	android/content/ActivityNotFoundException
    //   103	107	238	java/lang/Exception
    //   112	120	238	java/lang/Exception
  }
  
  /* Error */
  private static String ॱ(int paramInt1, char paramChar, int paramInt2)
  {
    // Byte code:
    //   0: goto +18 -> 18
    //   3: astore 5
    //   5: aload 5
    //   7: athrow
    //   8: goto +239 -> 247
    //   11: bipush 60
    //   13: istore 4
    //   15: goto +199 -> 214
    //   18: goto +79 -> 97
    //   21: new 346	java/lang/String
    //   24: dup
    //   25: aload 5
    //   27: invokespecial 400	java/lang/String:<init>	([C)V
    //   30: areturn
    //   31: iload_2
    //   32: newarray char
    //   34: astore 5
    //   36: iconst_0
    //   37: istore_3
    //   38: goto +209 -> 247
    //   41: iconst_0
    //   42: istore 4
    //   44: goto +112 -> 156
    //   47: iconst_1
    //   48: istore 4
    //   50: goto +106 -> 156
    //   53: bipush 36
    //   55: istore 4
    //   57: goto +157 -> 214
    //   60: getstatic 34	ro/btrl/boot/ui/activity/TncActivity:ʾ	I
    //   63: istore 4
    //   65: iload 4
    //   67: bipush 113
    //   69: iadd
    //   70: istore 4
    //   72: iload 4
    //   74: sipush 128
    //   77: irem
    //   78: putstatic 32	ro/btrl/boot/ui/activity/TncActivity:ʿ	I
    //   81: iload 4
    //   83: iconst_2
    //   84: irem
    //   85: ifeq +6 -> 91
    //   88: goto -41 -> 47
    //   91: goto -50 -> 41
    //   94: goto -63 -> 31
    //   97: getstatic 32	ro/btrl/boot/ui/activity/TncActivity:ʿ	I
    //   100: bipush 73
    //   102: iadd
    //   103: istore_3
    //   104: iload_3
    //   105: sipush 128
    //   108: irem
    //   109: putstatic 34	ro/btrl/boot/ui/activity/TncActivity:ʾ	I
    //   112: iload_3
    //   113: iconst_2
    //   114: irem
    //   115: ifne +6 -> 121
    //   118: goto -24 -> 94
    //   121: goto -90 -> 31
    //   124: aload 5
    //   126: iload_3
    //   127: getstatic 298	ro/btrl/boot/ui/activity/TncActivity:ʽॱ	[C
    //   130: iload_0
    //   131: iload_3
    //   132: iushr
    //   133: caload
    //   134: i2l
    //   135: iload_3
    //   136: i2l
    //   137: getstatic 52	ro/btrl/boot/ui/activity/TncActivity:ʼॱ	J
    //   140: lrem
    //   141: land
    //   142: iload_1
    //   143: i2l
    //   144: land
    //   145: l2i
    //   146: i2c
    //   147: castore
    //   148: iload_3
    //   149: bipush 81
    //   151: iadd
    //   152: istore_3
    //   153: goto -145 -> 8
    //   156: iload 4
    //   158: tableswitch	default:+22->180, 0:+25->183, 1:+-34->124
    //   180: goto -56 -> 124
    //   183: aload 5
    //   185: iload_3
    //   186: getstatic 298	ro/btrl/boot/ui/activity/TncActivity:ʽॱ	[C
    //   189: iload_0
    //   190: iload_3
    //   191: iadd
    //   192: caload
    //   193: i2l
    //   194: iload_3
    //   195: i2l
    //   196: getstatic 52	ro/btrl/boot/ui/activity/TncActivity:ʼॱ	J
    //   199: lmul
    //   200: lxor
    //   201: iload_1
    //   202: i2l
    //   203: lxor
    //   204: l2i
    //   205: i2c
    //   206: castore
    //   207: iload_3
    //   208: iconst_1
    //   209: iadd
    //   210: istore_3
    //   211: goto -203 -> 8
    //   214: iload 4
    //   216: lookupswitch	default:+28->244, 36:+-156->60, 60:+-195->21
    //   244: goto -184 -> 60
    //   247: iload_3
    //   248: iload_2
    //   249: if_icmpge +6 -> 255
    //   252: goto -199 -> 53
    //   255: goto -244 -> 11
    // Local variable table:
    //   start	length	slot	name	signature
    //   0	258	0	paramInt1	int
    //   0	258	1	paramChar	char
    //   0	258	2	paramInt2	int
    //   37	213	3	i	int
    //   13	202	4	j	int
    //   3	23	5	localException	Exception
    //   34	150	5	arrayOfChar	char[]
    // Exception table:
    //   from	to	target	type
    //   60	65	3	java/lang/Exception
    //   72	81	3	java/lang/Exception
  }
  
  /* Error */
  private String ॱ(String paramString)
  {
    // Byte code:
    //   0: goto +201 -> 201
    //   3: astore_1
    //   4: new 405	java/lang/RuntimeException
    //   7: dup
    //   8: aload_1
    //   9: invokespecial 408	java/lang/RuntimeException:<init>	(Ljava/lang/Throwable;)V
    //   12: athrow
    //   13: goto +105 -> 118
    //   16: aload 4
    //   18: iload_2
    //   19: aload_1
    //   20: aload_1
    //   21: arraylength
    //   22: iload_2
    //   23: isub
    //   24: iconst_1
    //   25: isub
    //   26: baload
    //   27: getstatic 39	ro/btrl/boot/ui/activity/TncActivity:ॱˎ	B
    //   30: ixor
    //   31: i2b
    //   32: bastore
    //   33: iload_2
    //   34: iconst_1
    //   35: iadd
    //   36: istore_2
    //   37: goto +167 -> 204
    //   40: new 346	java/lang/String
    //   43: dup
    //   44: aload 4
    //   46: aload_0
    //   47: invokevirtual 411	android/content/Context:getPackageName	()Ljava/lang/String;
    //   50: iconst_2
    //   51: invokevirtual 354	java/lang/String:codePointAt	(I)I
    //   54: sipush 195
    //   57: iadd
    //   58: aload_0
    //   59: invokevirtual 337	android/content/Context:getResources	()Landroid/content/res/Resources;
    //   62: ldc_w 412
    //   65: invokevirtual 344	android/content/res/Resources:getString	(I)Ljava/lang/String;
    //   68: iconst_0
    //   69: iconst_4
    //   70: invokevirtual 350	java/lang/String:substring	(II)Ljava/lang/String;
    //   73: iconst_1
    //   74: invokevirtual 354	java/lang/String:codePointAt	(I)I
    //   77: bipush 26
    //   79: isub
    //   80: i2c
    //   81: aload_0
    //   82: invokevirtual 337	android/content/Context:getResources	()Landroid/content/res/Resources;
    //   85: ldc_w 413
    //   88: invokevirtual 344	android/content/res/Resources:getString	(I)Ljava/lang/String;
    //   91: bipush 6
    //   93: bipush 12
    //   95: invokevirtual 350	java/lang/String:substring	(II)Ljava/lang/String;
    //   98: iconst_0
    //   99: invokevirtual 354	java/lang/String:codePointAt	(I)I
    //   102: sipush 227
    //   105: isub
    //   106: invokestatic 364	ro/btrl/boot/ui/activity/TncActivity:ॱ	(ICI)Ljava/lang/String;
    //   109: invokevirtual 368	java/lang/String:intern	()Ljava/lang/String;
    //   112: invokespecial 416	java/lang/String:<init>	([BLjava/lang/String;)V
    //   115: astore_1
    //   116: aload_1
    //   117: areturn
    //   118: aload_1
    //   119: aload_0
    //   120: invokevirtual 337	android/content/Context:getResources	()Landroid/content/res/Resources;
    //   123: ldc_w 417
    //   126: invokevirtual 344	android/content/res/Resources:getString	(I)Ljava/lang/String;
    //   129: bipush 7
    //   131: bipush 8
    //   133: invokevirtual 350	java/lang/String:substring	(II)Ljava/lang/String;
    //   136: iconst_0
    //   137: invokevirtual 354	java/lang/String:codePointAt	(I)I
    //   140: sipush 134
    //   143: iadd
    //   144: aload_0
    //   145: invokevirtual 380	android/content/Context:getApplicationInfo	()Landroid/content/pm/ApplicationInfo;
    //   148: getfield 385	android/content/pm/ApplicationInfo:targetSdkVersion	I
    //   151: ldc_w 418
    //   154: iadd
    //   155: i2c
    //   156: aload_0
    //   157: invokevirtual 337	android/content/Context:getResources	()Landroid/content/res/Resources;
    //   160: ldc_w 419
    //   163: invokevirtual 344	android/content/res/Resources:getString	(I)Ljava/lang/String;
    //   166: iconst_0
    //   167: iconst_4
    //   168: invokevirtual 350	java/lang/String:substring	(II)Ljava/lang/String;
    //   171: invokevirtual 359	java/lang/String:length	()I
    //   174: bipush 6
    //   176: iadd
    //   177: invokestatic 364	ro/btrl/boot/ui/activity/TncActivity:ॱ	(ICI)Ljava/lang/String;
    //   180: invokevirtual 368	java/lang/String:intern	()Ljava/lang/String;
    //   183: invokevirtual 423	java/lang/String:getBytes	(Ljava/lang/String;)[B
    //   186: astore_1
    //   187: aload_1
    //   188: arraylength
    //   189: newarray byte
    //   191: astore 4
    //   193: iconst_0
    //   194: istore_2
    //   195: goto +110 -> 305
    //   198: astore_1
    //   199: aload_1
    //   200: athrow
    //   201: goto +75 -> 276
    //   204: goto +101 -> 305
    //   207: goto -191 -> 16
    //   210: iconst_1
    //   211: istore_3
    //   212: goto +33 -> 245
    //   215: getstatic 34	ro/btrl/boot/ui/activity/TncActivity:ʾ	I
    //   218: bipush 47
    //   220: iadd
    //   221: istore_3
    //   222: iload_3
    //   223: sipush 128
    //   226: irem
    //   227: putstatic 32	ro/btrl/boot/ui/activity/TncActivity:ʿ	I
    //   230: iload_3
    //   231: iconst_2
    //   232: irem
    //   233: ifeq +6 -> 239
    //   236: goto -29 -> 207
    //   239: goto -223 -> 16
    //   242: astore_1
    //   243: aload_1
    //   244: athrow
    //   245: iload_3
    //   246: tableswitch	default:+22->268, 0:+-31->215, 1:+-206->40
    //   268: goto -53 -> 215
    //   271: iconst_0
    //   272: istore_3
    //   273: goto -28 -> 245
    //   276: getstatic 32	ro/btrl/boot/ui/activity/TncActivity:ʿ	I
    //   279: istore_2
    //   280: iload_2
    //   281: bipush 77
    //   283: iadd
    //   284: istore_2
    //   285: iload_2
    //   286: sipush 128
    //   289: irem
    //   290: putstatic 34	ro/btrl/boot/ui/activity/TncActivity:ʾ	I
    //   293: iload_2
    //   294: iconst_2
    //   295: irem
    //   296: ifne +6 -> 302
    //   299: goto -286 -> 13
    //   302: goto -184 -> 118
    //   305: aload_1
    //   306: arraylength
    //   307: istore_3
    //   308: iload_2
    //   309: iload_3
    //   310: if_icmpge +6 -> 316
    //   313: goto -42 -> 271
    //   316: goto -106 -> 210
    // Local variable table:
    //   start	length	slot	name	signature
    //   0	319	0	this	TncActivity
    //   0	319	1	paramString	String
    //   18	293	2	i	int
    //   211	100	3	j	int
    //   16	176	4	arrayOfByte	byte[]
    // Exception table:
    //   from	to	target	type
    //   16	33	3	java/io/UnsupportedEncodingException
    //   40	116	3	java/io/UnsupportedEncodingException
    //   118	193	3	java/io/UnsupportedEncodingException
    //   305	308	3	java/io/UnsupportedEncodingException
    //   285	293	198	java/lang/Exception
    //   276	280	242	java/lang/Exception
  }
  
  /* Error */
  public Resources getResources()
  {
    // Byte code:
    //   0: goto +75 -> 75
    //   3: aload_0
    //   4: invokespecial 424	o/Ix:getResources	()Landroid/content/res/Resources;
    //   7: invokestatic 429	o/oH:ˊ	(Landroid/content/res/Resources;)Landroid/content/res/Resources;
    //   10: astore_2
    //   11: bipush 80
    //   13: iconst_0
    //   14: idiv
    //   15: istore_1
    //   16: aload_2
    //   17: areturn
    //   18: astore_2
    //   19: aload_2
    //   20: athrow
    //   21: iload_1
    //   22: lookupswitch	default:+26->48, 26:+-19->3, 72:+35->57
    //   48: goto +9 -> 57
    //   51: bipush 26
    //   53: istore_1
    //   54: goto -33 -> 21
    //   57: aload_0
    //   58: invokespecial 424	o/Ix:getResources	()Landroid/content/res/Resources;
    //   61: astore_2
    //   62: aload_2
    //   63: invokestatic 429	o/oH:ˊ	(Landroid/content/res/Resources;)Landroid/content/res/Resources;
    //   66: astore_2
    //   67: aload_2
    //   68: areturn
    //   69: bipush 72
    //   71: istore_1
    //   72: goto -51 -> 21
    //   75: getstatic 34	ro/btrl/boot/ui/activity/TncActivity:ʾ	I
    //   78: bipush 61
    //   80: iadd
    //   81: istore_1
    //   82: iload_1
    //   83: sipush 128
    //   86: irem
    //   87: putstatic 32	ro/btrl/boot/ui/activity/TncActivity:ʿ	I
    //   90: iload_1
    //   91: iconst_2
    //   92: irem
    //   93: ifeq +6 -> 99
    //   96: goto -45 -> 51
    //   99: goto -30 -> 69
    // Local variable table:
    //   start	length	slot	name	signature
    //   0	102	0	this	TncActivity
    //   15	78	1	i	int
    //   10	7	2	localResources1	Resources
    //   18	2	2	localException	Exception
    //   61	7	2	localResources2	Resources
    // Exception table:
    //   from	to	target	type
    //   62	67	18	java/lang/Exception
  }
  
  public void onActivityResult(int paramInt1, int paramInt2, Intent paramIntent)
  {
    break label33;
    break label113;
    for (;;)
    {
      paramInt1 = 1;
      break label337;
      paramInt1 = 82;
      break;
      if (paramIntent != null) {
        break label393;
      }
    }
    for (;;)
    {
      break label431;
      break label431;
      label33:
      break;
      label36:
      switch (paramInt1)
      {
      }
    }
    super.onActivityResult(paramInt1, paramInt2, paramIntent);
    if (paramInt1 != 5)
    {
      break label398;
      for (;;)
      {
        try
        {
          paramInt1 = ʿ + 87;
          ʾ = paramInt1 % 128;
          if (paramInt1 % 2 == 0) {
            break label326;
          }
        }
        catch (Exception paramIntent)
        {
          label113:
          label198:
          label225:
          throw paramIntent;
        }
        return;
        paramIntent = paramIntent.getStringExtra(ॱ(getApplicationInfo().targetSdkVersion + 20, (char)(getResources().getString(2131755337).substring(0, 4).codePointAt(3) + 61843), getApplicationInfo().targetSdkVersion - 14).intern());
        break label431;
        paramInt1 = ʿ + 65;
        ʾ = paramInt1 % 128;
        if (paramInt1 % 2 == 0) {
          break;
        }
        continue;
        switch (paramInt1)
        {
        case 85: 
        default: 
          return;
          paramIntent = null;
        }
      }
    }
    for (;;)
    {
      label230:
      localViewDataBinding = this.ॱˊ;
      vq.ˋ(localViewDataBinding, ॱ(getPackageName().codePointAt(6) - 98, (char)(getResources().getString(2131755428).substring(0, 4).length() + 12287), getResources().getString(2131755627).substring(0, 4).length() + 4).intern());
      ((Dx)localViewDataBinding).ॱ(true);
      if (paramInt2 != -1) {
        return;
      }
      label326:
      label337:
      label393:
      label398:
      do
      {
        break label230;
        paramInt1 = 31;
        break label36;
        paramInt1 = 5;
        break label198;
        for (;;)
        {
          switch (paramInt1)
          {
          }
          break label225;
          paramInt1 = ʿ + 27;
          ʾ = paramInt1 % 128;
          if (paramInt1 % 2 != 0) {
            break;
          }
          break;
          paramInt1 = 0;
        }
        paramInt1 = 85;
        break label198;
        paramInt1 = ʿ + 49;
        ʾ = paramInt1 % 128;
      } while (paramInt1 % 2 == 0);
    }
    label431:
    ViewDataBinding localViewDataBinding = this.ॱˊ;
    vq.ˋ(localViewDataBinding, ॱ(getResources().getString(2131755562).substring(0, 16).codePointAt(13) - 235, (char)(getApplicationInfo().targetSdkVersion + 12266), getApplicationInfo().targetSdkVersion - 17).intern());
    ((Dx)localViewDataBinding).ˊ(paramIntent);
  }
  
  /* Error */
  public void onCreate(android.os.Bundle paramBundle)
  {
    // Byte code:
    //   0: goto +255 -> 255
    //   3: return
    //   4: aload_0
    //   5: aload_1
    //   6: invokespecial 450	o/Ix:onCreate	(Landroid/os/Bundle;)V
    //   9: aload_0
    //   10: getfield 305	ro/btrl/boot/ui/activity/TncActivity:ॱˊ	Landroid/databinding/ViewDataBinding;
    //   13: astore_1
    //   14: aload_1
    //   15: aload_0
    //   16: invokevirtual 411	android/content/Context:getPackageName	()Ljava/lang/String;
    //   19: bipush 8
    //   21: invokevirtual 354	java/lang/String:codePointAt	(I)I
    //   24: bipush 102
    //   26: isub
    //   27: aload_0
    //   28: invokevirtual 337	android/content/Context:getResources	()Landroid/content/res/Resources;
    //   31: ldc_w 451
    //   34: invokevirtual 344	android/content/res/Resources:getString	(I)Ljava/lang/String;
    //   37: iconst_0
    //   38: iconst_4
    //   39: invokevirtual 350	java/lang/String:substring	(II)Ljava/lang/String;
    //   42: iconst_2
    //   43: invokevirtual 354	java/lang/String:codePointAt	(I)I
    //   46: sipush 12280
    //   49: iadd
    //   50: i2c
    //   51: aload_0
    //   52: invokevirtual 337	android/content/Context:getResources	()Landroid/content/res/Resources;
    //   55: ldc_w 452
    //   58: invokevirtual 344	android/content/res/Resources:getString	(I)Ljava/lang/String;
    //   61: iconst_0
    //   62: iconst_5
    //   63: invokevirtual 350	java/lang/String:substring	(II)Ljava/lang/String;
    //   66: iconst_4
    //   67: invokevirtual 354	java/lang/String:codePointAt	(I)I
    //   70: sipush 172
    //   73: isub
    //   74: invokestatic 364	ro/btrl/boot/ui/activity/TncActivity:ॱ	(ICI)Ljava/lang/String;
    //   77: invokevirtual 368	java/lang/String:intern	()Ljava/lang/String;
    //   80: invokestatic 373	o/vq:ˋ	(Ljava/lang/Object;Ljava/lang/String;)V
    //   83: aload_1
    //   84: checkcast 307	o/Dx
    //   87: aload_0
    //   88: invokevirtual 456	ro/btrl/boot/ui/activity/TncActivity:ॱᐝ	()Lo/DK$iF;
    //   91: invokevirtual 459	o/Dx:ˎ	(Lo/DK$iF;)V
    //   94: aload_0
    //   95: getfield 305	ro/btrl/boot/ui/activity/TncActivity:ॱˊ	Landroid/databinding/ViewDataBinding;
    //   98: astore_1
    //   99: aload_1
    //   100: aload_0
    //   101: invokevirtual 337	android/content/Context:getResources	()Landroid/content/res/Resources;
    //   104: ldc_w 460
    //   107: invokevirtual 344	android/content/res/Resources:getString	(I)Ljava/lang/String;
    //   110: iconst_3
    //   111: iconst_4
    //   112: invokevirtual 350	java/lang/String:substring	(II)Ljava/lang/String;
    //   115: invokevirtual 359	java/lang/String:length	()I
    //   118: bipush 9
    //   120: iadd
    //   121: aload_0
    //   122: invokevirtual 380	android/content/Context:getApplicationInfo	()Landroid/content/pm/ApplicationInfo;
    //   125: getfield 385	android/content/pm/ApplicationInfo:targetSdkVersion	I
    //   128: sipush 12266
    //   131: iadd
    //   132: i2c
    //   133: aload_0
    //   134: invokevirtual 337	android/content/Context:getResources	()Landroid/content/res/Resources;
    //   137: ldc_w 461
    //   140: invokevirtual 344	android/content/res/Resources:getString	(I)Ljava/lang/String;
    //   143: iconst_0
    //   144: iconst_4
    //   145: invokevirtual 350	java/lang/String:substring	(II)Ljava/lang/String;
    //   148: iconst_2
    //   149: invokevirtual 354	java/lang/String:codePointAt	(I)I
    //   152: iconst_3
    //   153: isub
    //   154: invokestatic 364	ro/btrl/boot/ui/activity/TncActivity:ॱ	(ICI)Ljava/lang/String;
    //   157: invokevirtual 368	java/lang/String:intern	()Ljava/lang/String;
    //   160: invokestatic 373	o/vq:ˋ	(Ljava/lang/Object;Ljava/lang/String;)V
    //   163: aload_1
    //   164: checkcast 307	o/Dx
    //   167: iconst_1
    //   168: invokevirtual 463	o/Dx:ˋ	(Z)V
    //   171: aload_0
    //   172: getfield 305	ro/btrl/boot/ui/activity/TncActivity:ॱˊ	Landroid/databinding/ViewDataBinding;
    //   175: checkcast 307	o/Dx
    //   178: getfield 467	o/Dx:ˊॱ	Landroid/webkit/WebView;
    //   181: astore_1
    //   182: aload_1
    //   183: aload_0
    //   184: invokevirtual 411	android/content/Context:getPackageName	()Ljava/lang/String;
    //   187: iconst_2
    //   188: invokevirtual 354	java/lang/String:codePointAt	(I)I
    //   191: bipush 28
    //   193: isub
    //   194: aload_0
    //   195: invokevirtual 411	android/content/Context:getPackageName	()Ljava/lang/String;
    //   198: invokevirtual 359	java/lang/String:length	()I
    //   201: sipush 21975
    //   204: iadd
    //   205: i2c
    //   206: aload_0
    //   207: invokevirtual 411	android/content/Context:getPackageName	()Ljava/lang/String;
    //   210: invokevirtual 359	java/lang/String:length	()I
    //   213: bipush 16
    //   215: iadd
    //   216: invokestatic 364	ro/btrl/boot/ui/activity/TncActivity:ॱ	(ICI)Ljava/lang/String;
    //   219: invokevirtual 368	java/lang/String:intern	()Ljava/lang/String;
    //   222: invokestatic 373	o/vq:ˋ	(Ljava/lang/Object;Ljava/lang/String;)V
    //   225: aload_1
    //   226: new 15	ro/btrl/boot/ui/activity/TncActivity$ˋ
    //   229: dup
    //   230: aload_0
    //   231: invokespecial 468	ro/btrl/boot/ui/activity/TncActivity$ˋ:<init>	(Lro/btrl/boot/ui/activity/TncActivity;)V
    //   234: checkcast 470	android/webkit/WebViewClient
    //   237: invokevirtual 476	android/webkit/WebView:setWebViewClient	(Landroid/webkit/WebViewClient;)V
    //   240: aload_0
    //   241: invokevirtual 456	ro/btrl/boot/ui/activity/TncActivity:ॱᐝ	()Lo/DK$iF;
    //   244: invokeinterface 480 1 0
    //   249: goto +9 -> 258
    //   252: astore_1
    //   253: aload_1
    //   254: athrow
    //   255: goto -251 -> 4
    //   258: getstatic 32	ro/btrl/boot/ui/activity/TncActivity:ʿ	I
    //   261: istore_2
    //   262: iload_2
    //   263: bipush 31
    //   265: iadd
    //   266: istore_2
    //   267: iload_2
    //   268: sipush 128
    //   271: irem
    //   272: putstatic 34	ro/btrl/boot/ui/activity/TncActivity:ʾ	I
    //   275: iload_2
    //   276: iconst_2
    //   277: irem
    //   278: ifne +6 -> 284
    //   281: goto -278 -> 3
    //   284: return
    // Local variable table:
    //   start	length	slot	name	signature
    //   0	285	0	this	TncActivity
    //   0	285	1	paramBundle	android.os.Bundle
    //   261	17	2	i	int
    // Exception table:
    //   from	to	target	type
    //   258	262	252	java/lang/Exception
    //   267	275	252	java/lang/Exception
  }
  
  public final void tncToEmailActionClicked(View paramView)
  {
    break label4;
    return;
    label4:
    int i = ʿ + 107;
    ʾ = i % 128;
    if (i % 2 != 0) {
      break label56;
    }
    for (;;)
    {
      i = ʿ + 11;
      ʾ = i % 128;
      if (i % 2 == 0) {
        break;
      }
      return;
      label56:
      vq.ˎ(paramView, ॱ(getApplicationInfo().targetSdkVersion + 170, (char)(getApplicationInfo().targetSdkVersion - 25), getPackageName().codePointAt(6) - 104).intern());
      paramView = ((Dx)this.ॱˊ).ॱ;
      vq.ˋ(paramView, ॱ(getResources().getString(2131755154).substring(0, 4).length() + 195, (char)(getResources().getString(2131755175).substring(0, 10).codePointAt(7) + 11687), getResources().getString(2131755372).substring(0, 9).codePointAt(4) - 232).intern());
      paramView = paramView.getText().toString();
      ॱᐝ().ˋ(paramView);
    }
  }
  
  /* Error */
  public void ʼॱ()
  {
    // Byte code:
    //   0: goto +9 -> 9
    //   3: bipush 58
    //   5: iconst_0
    //   6: idiv
    //   7: istore_1
    //   8: return
    //   9: goto +17 -> 26
    //   12: astore_2
    //   13: aload_2
    //   14: invokevirtual 509	java/lang/Throwable:getCause	()Ljava/lang/Throwable;
    //   17: astore_3
    //   18: aload_3
    //   19: ifnull +5 -> 24
    //   22: aload_3
    //   23: athrow
    //   24: aload_2
    //   25: athrow
    //   26: aload_0
    //   27: invokevirtual 337	android/content/Context:getResources	()Landroid/content/res/Resources;
    //   30: ldc_w 510
    //   33: invokevirtual 344	android/content/res/Resources:getString	(I)Ljava/lang/String;
    //   36: iconst_0
    //   37: iconst_4
    //   38: invokevirtual 350	java/lang/String:substring	(II)Ljava/lang/String;
    //   41: invokevirtual 359	java/lang/String:length	()I
    //   44: iconst_1
    //   45: isub
    //   46: aload_0
    //   47: invokevirtual 411	android/content/Context:getPackageName	()Ljava/lang/String;
    //   50: invokevirtual 359	java/lang/String:length	()I
    //   53: bipush 11
    //   55: isub
    //   56: aload_0
    //   57: invokevirtual 380	android/content/Context:getApplicationInfo	()Landroid/content/pm/ApplicationInfo;
    //   60: getfield 385	android/content/pm/ApplicationInfo:targetSdkVersion	I
    //   63: ldc_w 511
    //   66: iadd
    //   67: i2c
    //   68: invokestatic 516	o/O:ˋ	(IIC)Ljava/lang/Object;
    //   71: checkcast 518	java/lang/Class
    //   74: ldc_w 519
    //   77: aconst_null
    //   78: invokevirtual 523	java/lang/Class:getMethod	(Ljava/lang/String;[Ljava/lang/Class;)Ljava/lang/reflect/Method;
    //   81: aconst_null
    //   82: aconst_null
    //   83: invokevirtual 529	java/lang/reflect/Method:invoke	(Ljava/lang/Object;[Ljava/lang/Object;)Ljava/lang/Object;
    //   86: astore_2
    //   87: aload_0
    //   88: checkcast 531	android/app/Activity
    //   91: astore_3
    //   92: goto +17 -> 109
    //   95: astore_2
    //   96: aload_2
    //   97: invokevirtual 509	java/lang/Throwable:getCause	()Ljava/lang/Throwable;
    //   100: astore_3
    //   101: aload_3
    //   102: ifnull +5 -> 107
    //   105: aload_3
    //   106: athrow
    //   107: aload_2
    //   108: athrow
    //   109: aload_0
    //   110: invokevirtual 411	android/content/Context:getPackageName	()Ljava/lang/String;
    //   113: invokevirtual 359	java/lang/String:length	()I
    //   116: bipush 8
    //   118: isub
    //   119: aload_0
    //   120: invokevirtual 337	android/content/Context:getResources	()Landroid/content/res/Resources;
    //   123: ldc_w 532
    //   126: invokevirtual 344	android/content/res/Resources:getString	(I)Ljava/lang/String;
    //   129: iconst_0
    //   130: bipush 16
    //   132: invokevirtual 350	java/lang/String:substring	(II)Ljava/lang/String;
    //   135: invokevirtual 359	java/lang/String:length	()I
    //   138: bipush 16
    //   140: isub
    //   141: aload_0
    //   142: invokevirtual 380	android/content/Context:getApplicationInfo	()Landroid/content/pm/ApplicationInfo;
    //   145: getfield 385	android/content/pm/ApplicationInfo:targetSdkVersion	I
    //   148: ldc_w 511
    //   151: iadd
    //   152: i2c
    //   153: invokestatic 516	o/O:ˋ	(IIC)Ljava/lang/Object;
    //   156: checkcast 518	java/lang/Class
    //   159: ldc_w 533
    //   162: iconst_1
    //   163: anewarray 518	java/lang/Class
    //   166: dup
    //   167: iconst_0
    //   168: ldc_w 531
    //   171: aastore
    //   172: invokevirtual 523	java/lang/Class:getMethod	(Ljava/lang/String;[Ljava/lang/Class;)Ljava/lang/reflect/Method;
    //   175: aload_2
    //   176: iconst_1
    //   177: anewarray 498	java/lang/Object
    //   180: dup
    //   181: iconst_0
    //   182: aload_3
    //   183: aastore
    //   184: invokevirtual 529	java/lang/reflect/Method:invoke	(Ljava/lang/Object;[Ljava/lang/Object;)Ljava/lang/Object;
    //   187: pop
    //   188: aload_0
    //   189: getfield 305	ro/btrl/boot/ui/activity/TncActivity:ॱˊ	Landroid/databinding/ViewDataBinding;
    //   192: checkcast 307	o/Dx
    //   195: getfield 537	o/Dx:ʼ	Lo/ap;
    //   198: astore_2
    //   199: aload_2
    //   200: aload_0
    //   201: invokevirtual 337	android/content/Context:getResources	()Landroid/content/res/Resources;
    //   204: ldc_w 538
    //   207: invokevirtual 344	android/content/res/Resources:getString	(I)Ljava/lang/String;
    //   210: iconst_0
    //   211: iconst_5
    //   212: invokevirtual 350	java/lang/String:substring	(II)Ljava/lang/String;
    //   215: invokevirtual 359	java/lang/String:length	()I
    //   218: sipush 151
    //   221: iadd
    //   222: aload_0
    //   223: invokevirtual 411	android/content/Context:getPackageName	()Ljava/lang/String;
    //   226: bipush 7
    //   228: invokevirtual 354	java/lang/String:codePointAt	(I)I
    //   231: bipush 46
    //   233: isub
    //   234: i2c
    //   235: aload_0
    //   236: invokevirtual 337	android/content/Context:getResources	()Landroid/content/res/Resources;
    //   239: ldc_w 539
    //   242: invokevirtual 344	android/content/res/Resources:getString	(I)Ljava/lang/String;
    //   245: bipush 26
    //   247: bipush 34
    //   249: invokevirtual 350	java/lang/String:substring	(II)Ljava/lang/String;
    //   252: invokevirtual 359	java/lang/String:length	()I
    //   255: bipush 13
    //   257: iadd
    //   258: invokestatic 364	ro/btrl/boot/ui/activity/TncActivity:ॱ	(ICI)Ljava/lang/String;
    //   261: invokevirtual 368	java/lang/String:intern	()Ljava/lang/String;
    //   264: invokestatic 373	o/vq:ˋ	(Ljava/lang/Object;Ljava/lang/String;)V
    //   267: aload_2
    //   268: iconst_0
    //   269: invokevirtual 544	o/ap:setEnabled	(Z)V
    //   272: aload_0
    //   273: getfield 305	ro/btrl/boot/ui/activity/TncActivity:ॱˊ	Landroid/databinding/ViewDataBinding;
    //   276: checkcast 307	o/Dx
    //   279: getfield 537	o/Dx:ʼ	Lo/ap;
    //   282: invokevirtual 546	o/ap:ˊ	()V
    //   285: aload_0
    //   286: getfield 305	ro/btrl/boot/ui/activity/TncActivity:ॱˊ	Landroid/databinding/ViewDataBinding;
    //   289: checkcast 307	o/Dx
    //   292: getfield 487	o/Dx:ॱ	Landroid/widget/EditText;
    //   295: new 11	ro/btrl/boot/ui/activity/TncActivity$iF
    //   298: dup
    //   299: aload_0
    //   300: invokespecial 547	ro/btrl/boot/ui/activity/TncActivity$iF:<init>	(Lro/btrl/boot/ui/activity/TncActivity;)V
    //   303: checkcast 549	android/text/TextWatcher
    //   306: invokevirtual 553	android/widget/EditText:addTextChangedListener	(Landroid/text/TextWatcher;)V
    //   309: goto +34 -> 343
    //   312: iload_1
    //   313: lookupswitch	default:+27->340, 17:+-310->3, 89:+66->379
    //   340: goto -337 -> 3
    //   343: getstatic 34	ro/btrl/boot/ui/activity/TncActivity:ʾ	I
    //   346: bipush 29
    //   348: iadd
    //   349: istore_1
    //   350: iload_1
    //   351: sipush 128
    //   354: irem
    //   355: putstatic 32	ro/btrl/boot/ui/activity/TncActivity:ʿ	I
    //   358: iload_1
    //   359: iconst_2
    //   360: irem
    //   361: ifeq +6 -> 367
    //   364: goto +9 -> 373
    //   367: bipush 89
    //   369: istore_1
    //   370: goto -58 -> 312
    //   373: bipush 17
    //   375: istore_1
    //   376: goto -64 -> 312
    //   379: return
    // Local variable table:
    //   start	length	slot	name	signature
    //   0	380	0	this	TncActivity
    //   7	369	1	i	int
    //   12	13	2	localObject1	Object
    //   86	1	2	localObject2	Object
    //   95	81	2	localObject3	Object
    //   198	70	2	localAp	o.ap
    //   17	166	3	localObject4	Object
    // Exception table:
    //   from	to	target	type
    //   26	87	12	finally
    //   109	188	95	finally
  }
  
  public void ʽॱ()
  {
    for (;;)
    {
      int i = ʾ + 15;
      ʿ = i % 128;
      if (i % 2 == 0) {
        return;
      }
      return;
      i = ʾ + 41;
      ʿ = i % 128;
      if (i % 2 == 0) {
        break label59;
      }
      label59:
      ˍ();
      Ic.ˏ(ॱˊ()).ˏ(false, false).ˎ();
      finish();
    }
  }
  
  /* Error */
  public void ʾ()
  {
    // Byte code:
    //   0: goto +9 -> 9
    //   3: bipush 14
    //   5: iconst_0
    //   6: idiv
    //   7: istore_1
    //   8: return
    //   9: goto +42 -> 51
    //   12: iconst_1
    //   13: istore_1
    //   14: goto +9 -> 23
    //   17: astore_2
    //   18: aload_2
    //   19: athrow
    //   20: astore_2
    //   21: aload_2
    //   22: athrow
    //   23: iload_1
    //   24: tableswitch	default:+24->48, 0:+61->85, 1:+-21->3
    //   48: goto -45 -> 3
    //   51: getstatic 32	ro/btrl/boot/ui/activity/TncActivity:ʿ	I
    //   54: iconst_5
    //   55: iadd
    //   56: istore_1
    //   57: iload_1
    //   58: sipush 128
    //   61: irem
    //   62: putstatic 34	ro/btrl/boot/ui/activity/TncActivity:ʾ	I
    //   65: iload_1
    //   66: iconst_2
    //   67: irem
    //   68: ifne +6 -> 74
    //   71: goto +6 -> 77
    //   74: goto +39 -> 113
    //   77: goto +36 -> 113
    //   80: iconst_0
    //   81: istore_1
    //   82: goto -59 -> 23
    //   85: return
    //   86: getstatic 34	ro/btrl/boot/ui/activity/TncActivity:ʾ	I
    //   89: bipush 105
    //   91: iadd
    //   92: istore_1
    //   93: iload_1
    //   94: sipush 128
    //   97: irem
    //   98: putstatic 32	ro/btrl/boot/ui/activity/TncActivity:ʿ	I
    //   101: iload_1
    //   102: iconst_2
    //   103: irem
    //   104: ifeq +6 -> 110
    //   107: goto -95 -> 12
    //   110: goto -30 -> 80
    //   113: goto +17 -> 130
    //   116: astore_2
    //   117: aload_2
    //   118: invokevirtual 509	java/lang/Throwable:getCause	()Ljava/lang/Throwable;
    //   121: astore_3
    //   122: aload_3
    //   123: ifnull +5 -> 128
    //   126: aload_3
    //   127: athrow
    //   128: aload_2
    //   129: athrow
    //   130: aload_0
    //   131: invokevirtual 411	android/content/Context:getPackageName	()Ljava/lang/String;
    //   134: bipush 9
    //   136: invokevirtual 354	java/lang/String:codePointAt	(I)I
    //   139: bipush 94
    //   141: isub
    //   142: aload_0
    //   143: invokevirtual 337	android/content/Context:getResources	()Landroid/content/res/Resources;
    //   146: ldc_w 576
    //   149: invokevirtual 344	android/content/res/Resources:getString	(I)Ljava/lang/String;
    //   152: iconst_0
    //   153: iconst_5
    //   154: invokevirtual 350	java/lang/String:substring	(II)Ljava/lang/String;
    //   157: invokevirtual 359	java/lang/String:length	()I
    //   160: iconst_5
    //   161: isub
    //   162: aload_0
    //   163: invokevirtual 337	android/content/Context:getResources	()Landroid/content/res/Resources;
    //   166: ldc_w 577
    //   169: invokevirtual 344	android/content/res/Resources:getString	(I)Ljava/lang/String;
    //   172: iconst_0
    //   173: iconst_1
    //   174: invokevirtual 350	java/lang/String:substring	(II)Ljava/lang/String;
    //   177: iconst_0
    //   178: invokevirtual 354	java/lang/String:codePointAt	(I)I
    //   181: ldc_w 578
    //   184: iadd
    //   185: i2c
    //   186: invokestatic 516	o/O:ˋ	(IIC)Ljava/lang/Object;
    //   189: checkcast 518	java/lang/Class
    //   192: ldc_w 519
    //   195: aconst_null
    //   196: invokevirtual 523	java/lang/Class:getMethod	(Ljava/lang/String;[Ljava/lang/Class;)Ljava/lang/reflect/Method;
    //   199: aconst_null
    //   200: aconst_null
    //   201: invokevirtual 529	java/lang/reflect/Method:invoke	(Ljava/lang/Object;[Ljava/lang/Object;)Ljava/lang/Object;
    //   204: astore_2
    //   205: aload_0
    //   206: checkcast 531	android/app/Activity
    //   209: astore_3
    //   210: goto +17 -> 227
    //   213: astore_2
    //   214: aload_2
    //   215: invokevirtual 509	java/lang/Throwable:getCause	()Ljava/lang/Throwable;
    //   218: astore_3
    //   219: aload_3
    //   220: ifnull +5 -> 225
    //   223: aload_3
    //   224: athrow
    //   225: aload_2
    //   226: athrow
    //   227: aload_0
    //   228: invokevirtual 337	android/content/Context:getResources	()Landroid/content/res/Resources;
    //   231: ldc_w 579
    //   234: invokevirtual 344	android/content/res/Resources:getString	(I)Ljava/lang/String;
    //   237: iconst_0
    //   238: iconst_4
    //   239: invokevirtual 350	java/lang/String:substring	(II)Ljava/lang/String;
    //   242: iconst_1
    //   243: invokevirtual 354	java/lang/String:codePointAt	(I)I
    //   246: bipush 23
    //   248: isub
    //   249: aload_0
    //   250: invokevirtual 411	android/content/Context:getPackageName	()Ljava/lang/String;
    //   253: invokevirtual 359	java/lang/String:length	()I
    //   256: bipush 11
    //   258: isub
    //   259: aload_0
    //   260: invokevirtual 411	android/content/Context:getPackageName	()Ljava/lang/String;
    //   263: invokevirtual 359	java/lang/String:length	()I
    //   266: ldc_w 580
    //   269: iadd
    //   270: i2c
    //   271: invokestatic 516	o/O:ˋ	(IIC)Ljava/lang/Object;
    //   274: checkcast 518	java/lang/Class
    //   277: ldc_w 533
    //   280: iconst_1
    //   281: anewarray 518	java/lang/Class
    //   284: dup
    //   285: iconst_0
    //   286: ldc_w 531
    //   289: aastore
    //   290: invokevirtual 523	java/lang/Class:getMethod	(Ljava/lang/String;[Ljava/lang/Class;)Ljava/lang/reflect/Method;
    //   293: aload_2
    //   294: iconst_1
    //   295: anewarray 498	java/lang/Object
    //   298: dup
    //   299: iconst_0
    //   300: aload_3
    //   301: aastore
    //   302: invokevirtual 529	java/lang/reflect/Method:invoke	(Ljava/lang/Object;[Ljava/lang/Object;)Ljava/lang/Object;
    //   305: pop
    //   306: getstatic 585	o/Dv$iF:email_not_valid	I
    //   309: istore_1
    //   310: aload_0
    //   311: iload_1
    //   312: invokevirtual 588	ro/btrl/boot/ui/activity/TncActivity:ˊ	(I)V
    //   315: goto -229 -> 86
    // Local variable table:
    //   start	length	slot	name	signature
    //   0	318	0	this	TncActivity
    //   7	305	1	i	int
    //   17	2	2	localException1	Exception
    //   20	2	2	localException2	Exception
    //   116	13	2	localObject1	Object
    //   204	1	2	localObject2	Object
    //   213	81	2	localObject3	Object
    //   121	180	3	localObject4	Object
    // Exception table:
    //   from	to	target	type
    //   214	219	17	java/lang/Exception
    //   223	225	17	java/lang/Exception
    //   225	227	17	java/lang/Exception
    //   306	310	17	java/lang/Exception
    //   310	315	17	java/lang/Exception
    //   117	122	20	java/lang/Exception
    //   126	128	20	java/lang/Exception
    //   128	130	20	java/lang/Exception
    //   205	210	20	java/lang/Exception
    //   130	205	116	finally
    //   227	306	213	finally
  }
  
  public void ʿ()
  {
    for (;;)
    {
      int i;
      try
      {
        i = ʾ + 107;
        try
        {
          ʿ = i % 128;
          if (i % 2 != 0) {
            continue;
          }
        }
        catch (Exception localException1)
        {
          throw localException1;
        }
        continue;
        switch (i)
        {
        default: 
          return;
        case 0: 
          throw new NullPointerException();
        }
        return;
        break label186;
        i = 0;
        continue;
        Button localButton = ((Dx)this.ॱˊ).ˎ;
        vq.ˋ(localButton, ॱ(getResources().getString(2131755385).substring(0, 1).codePointAt(0) + 127, (char)(getResources().getString(2131755330).substring(0, 4).codePointAt(2) + 51886), getResources().getString(2131755589).substring(0, 4).codePointAt(2) + 7).intern());
        localButton.setEnabled(true);
        ˍ();
        continue;
        i = 1;
        continue;
        i = ʾ + 55;
      }
      catch (Exception localException2)
      {
        throw localException2;
      }
      label186:
      ʿ = i % 128;
      if (i % 2 != 0) {}
    }
  }
  
  public void ˈ()
  {
    break label148;
    try
    {
      Object localObject;
      Resources localResources;
      for (;;)
      {
        localObject = this.ॱˊ;
      }
    }
    catch (Exception localException1)
    {
      try
      {
        localObject = (Dx)localObject;
        localObject = ((Dx)localObject).ˎ;
        localResources = getResources();
        vq.ˋ(localObject, ॱ(localResources.getString(2131755639).substring(0, 4).length() + 173, (char)(getResources().getString(2131755502).substring(0, 5).length() + 51892), getResources().getString(2131755101).substring(0, 5).codePointAt(0) + 13).intern());
        ((Button)localObject).setEnabled(false);
        ˋ(Dv.iF.loading);
      }
      catch (Exception localException2)
      {
        throw localException2;
      }
      localException1 = localException1;
      throw localException1;
    }
    label148:
    for (;;)
    {
      i = ʾ + 73;
      ʿ = i % 128;
      if (i % 2 == 0) {
        break;
      }
    }
    int i = ʿ + 49;
    ʾ = i % 128;
    if (i % 2 != 0) {}
  }
  
  public void ˋ(String paramString)
  {
    break label373;
    for (;;)
    {
      label6:
      int i = ʾ + 5;
      ʿ = i % 128;
      if (i % 2 != 0) {
        break label6;
      }
      try
      {
        label35:
        Object localObject2 = getResources();
        try
        {
          localObject2 = ((Resources)localObject2).getString(2131755421);
          vq.ˋ(localObject1, ॱ(((String)localObject2).substring(0, 5).codePointAt(1) + 62, (char)(getResources().getString(2131755532).substring(56, 61).length() - 5), getResources().getString(2131755265).substring(0, 5).codePointAt(4) - 150).intern());
          localObject2 = new Object[1];
          localObject2[0] = paramString;
          i = localObject2.length;
          paramString = String.format((String)localObject1, Arrays.copyOf((Object[])localObject2, 1));
          vq.ˋ(paramString, ॱ(getPackageName().length() + 107, (char)(getApplicationInfo().targetSdkVersion + 28459), getResources().getString(2131755371).substring(0, 9).length() + 29).intern());
          ˎ(paramString);
          return;
        }
        catch (Exception paramString)
        {
          throw paramString;
        }
        label210:
        i = 1;
        for (;;)
        {
          vq.ˎ(paramString, ॱ(getPackageName().length() + 61, (char)(getApplicationInfo().targetSdkVersion + 49582), getResources().getString(2131755593).substring(0, 4).length() + 8).intern());
          localObject1 = vw.ˊ;
          localObject2 = getString(Dv.iF.email_sent);
          if (!((String)localObject2).startsWith(ॱ(getPackageName().codePointAt(8) - 28, (char)(getResources().getString(2131755060).substring(0, 4).length() + 23017), getApplicationInfo().targetSdkVersion - 21).intern()))
          {
            break label376;
            label346:
            i = ʾ + 29;
            ʿ = i % 128;
            if (i % 2 != 0) {
              break label210;
            }
            break label460;
            label373:
            break label465;
            label376:
            i = 0;
          }
          for (;;)
          {
            switch (i)
            {
            default: 
              break;
            case 0: 
              for (;;)
              {
                localObject1 = localObject2;
                switch (i)
                {
                }
                break label346;
                localObject1 = ॱ(((String)localObject2).substring(4)).intern();
                break;
                i = 1;
              }
              break label35;
              label460:
              i = 0;
            }
          }
          label465:
          i = ʿ + 91;
          ʾ = i % 128;
          if (i % 2 == 0) {
            break;
          }
        }
        Object localObject1 = ॱ(((String)localObject2).substring(4)).intern();
      }
      catch (Exception paramString)
      {
        throw paramString;
      }
      i = null.length;
    }
  }
  
  public int ˎ()
  {
    break label67;
    int i = 7;
    for (;;)
    {
      try
      {
        i = ʿ;
        i += 5;
        ʾ = i % 128;
        if (i % 2 == 0) {
          break label88;
        }
      }
      catch (Exception localException)
      {
        label67:
        throw localException;
      }
      switch (i)
      {
      default: 
        break;
      case 28: 
        i = Dv.ˋ.activity_tnc;
        int j = 65 / 0;
        return i;
      case 7: 
        return Dv.ˋ.activity_tnc;
        label88:
        i = 28;
      }
    }
  }
  
  /* Error */
  public void ˎ(android.content.DialogInterface.OnCancelListener paramOnCancelListener)
  {
    // Byte code:
    //   0: goto +3 -> 3
    //   3: goto +9 -> 12
    //   6: astore_1
    //   7: aload_1
    //   8: athrow
    //   9: astore_1
    //   10: aload_1
    //   11: athrow
    //   12: getstatic 34	ro/btrl/boot/ui/activity/TncActivity:ʾ	I
    //   15: istore_2
    //   16: iload_2
    //   17: bipush 15
    //   19: iadd
    //   20: istore_2
    //   21: iload_2
    //   22: sipush 128
    //   25: irem
    //   26: putstatic 32	ro/btrl/boot/ui/activity/TncActivity:ʿ	I
    //   29: iload_2
    //   30: iconst_2
    //   31: irem
    //   32: ifeq +6 -> 38
    //   35: goto +94 -> 129
    //   38: goto +28 -> 66
    //   41: getstatic 34	ro/btrl/boot/ui/activity/TncActivity:ʾ	I
    //   44: istore_2
    //   45: iload_2
    //   46: bipush 109
    //   48: iadd
    //   49: istore_2
    //   50: iload_2
    //   51: sipush 128
    //   54: irem
    //   55: putstatic 32	ro/btrl/boot/ui/activity/TncActivity:ʿ	I
    //   58: iload_2
    //   59: iconst_2
    //   60: irem
    //   61: ifeq +4 -> 65
    //   64: return
    //   65: return
    //   66: aload_0
    //   67: invokevirtual 411	android/content/Context:getPackageName	()Ljava/lang/String;
    //   70: astore_3
    //   71: aload_1
    //   72: aload_3
    //   73: bipush 9
    //   75: invokevirtual 354	java/lang/String:codePointAt	(I)I
    //   78: bipush 33
    //   80: isub
    //   81: aload_0
    //   82: invokevirtual 337	android/content/Context:getResources	()Landroid/content/res/Resources;
    //   85: ldc_w 653
    //   88: invokevirtual 344	android/content/res/Resources:getString	(I)Ljava/lang/String;
    //   91: iconst_0
    //   92: bipush 8
    //   94: invokevirtual 350	java/lang/String:substring	(II)Ljava/lang/String;
    //   97: iconst_4
    //   98: invokevirtual 354	java/lang/String:codePointAt	(I)I
    //   101: sipush 201
    //   104: isub
    //   105: i2c
    //   106: aload_0
    //   107: invokevirtual 411	android/content/Context:getPackageName	()Ljava/lang/String;
    //   110: iconst_3
    //   111: invokevirtual 354	java/lang/String:codePointAt	(I)I
    //   114: bipush 90
    //   116: isub
    //   117: invokestatic 364	ro/btrl/boot/ui/activity/TncActivity:ॱ	(ICI)Ljava/lang/String;
    //   120: invokevirtual 368	java/lang/String:intern	()Ljava/lang/String;
    //   123: invokestatic 484	o/vq:ˎ	(Ljava/lang/Object;Ljava/lang/String;)V
    //   126: goto -85 -> 41
    //   129: goto -63 -> 66
    // Local variable table:
    //   start	length	slot	name	signature
    //   0	132	0	this	TncActivity
    //   0	132	1	paramOnCancelListener	android.content.DialogInterface.OnCancelListener
    //   15	46	2	i	int
    //   70	3	3	str	String
    // Exception table:
    //   from	to	target	type
    //   12	16	6	java/lang/Exception
    //   66	71	6	java/lang/Exception
    //   21	29	9	java/lang/Exception
    //   41	45	9	java/lang/Exception
    //   50	58	9	java/lang/Exception
  }
  
  /* Error */
  public void ॱ(o.DE paramDE)
  {
    // Byte code:
    //   0: goto +6 -> 6
    //   3: astore_1
    //   4: aload_1
    //   5: athrow
    //   6: goto +9 -> 15
    //   9: astore_1
    //   10: aload_1
    //   11: athrow
    //   12: goto +27 -> 39
    //   15: getstatic 32	ro/btrl/boot/ui/activity/TncActivity:ʿ	I
    //   18: bipush 117
    //   20: iadd
    //   21: istore_3
    //   22: iload_3
    //   23: sipush 128
    //   26: irem
    //   27: putstatic 34	ro/btrl/boot/ui/activity/TncActivity:ʾ	I
    //   30: iload_3
    //   31: iconst_2
    //   32: irem
    //   33: ifne +6 -> 39
    //   36: goto -24 -> 12
    //   39: aload_0
    //   40: invokevirtual 380	android/content/Context:getApplicationInfo	()Landroid/content/pm/ApplicationInfo;
    //   43: astore 5
    //   45: aload 5
    //   47: getfield 385	android/content/pm/ApplicationInfo:targetSdkVersion	I
    //   50: istore_3
    //   51: aload_0
    //   52: invokevirtual 380	android/content/Context:getApplicationInfo	()Landroid/content/pm/ApplicationInfo;
    //   55: astore 5
    //   57: aload 5
    //   59: getfield 385	android/content/pm/ApplicationInfo:targetSdkVersion	I
    //   62: istore 4
    //   64: iload 4
    //   66: sipush 8685
    //   69: iadd
    //   70: i2c
    //   71: istore_2
    //   72: aload_0
    //   73: invokevirtual 337	android/content/Context:getResources	()Landroid/content/res/Resources;
    //   76: astore 5
    //   78: aload_1
    //   79: iload_3
    //   80: bipush 31
    //   82: iadd
    //   83: iload_2
    //   84: aload 5
    //   86: ldc_w 655
    //   89: invokevirtual 344	android/content/res/Resources:getString	(I)Ljava/lang/String;
    //   92: iconst_0
    //   93: iconst_4
    //   94: invokevirtual 350	java/lang/String:substring	(II)Ljava/lang/String;
    //   97: iconst_0
    //   98: invokevirtual 354	java/lang/String:codePointAt	(I)I
    //   101: iconst_3
    //   102: iadd
    //   103: invokestatic 364	ro/btrl/boot/ui/activity/TncActivity:ॱ	(ICI)Ljava/lang/String;
    //   106: invokevirtual 368	java/lang/String:intern	()Ljava/lang/String;
    //   109: invokestatic 484	o/vq:ˎ	(Ljava/lang/Object;Ljava/lang/String;)V
    //   112: aload_0
    //   113: getfield 305	ro/btrl/boot/ui/activity/TncActivity:ॱˊ	Landroid/databinding/ViewDataBinding;
    //   116: astore 5
    //   118: aload 5
    //   120: aload_0
    //   121: invokevirtual 337	android/content/Context:getResources	()Landroid/content/res/Resources;
    //   124: ldc_w 656
    //   127: invokevirtual 344	android/content/res/Resources:getString	(I)Ljava/lang/String;
    //   130: iconst_0
    //   131: iconst_4
    //   132: invokevirtual 350	java/lang/String:substring	(II)Ljava/lang/String;
    //   135: iconst_0
    //   136: invokevirtual 354	java/lang/String:codePointAt	(I)I
    //   139: iconst_5
    //   140: iadd
    //   141: aload_0
    //   142: invokevirtual 411	android/content/Context:getPackageName	()Ljava/lang/String;
    //   145: iconst_5
    //   146: invokevirtual 354	java/lang/String:codePointAt	(I)I
    //   149: sipush 12177
    //   152: iadd
    //   153: i2c
    //   154: aload_0
    //   155: invokevirtual 337	android/content/Context:getResources	()Landroid/content/res/Resources;
    //   158: ldc_w 657
    //   161: invokevirtual 344	android/content/res/Resources:getString	(I)Ljava/lang/String;
    //   164: iconst_0
    //   165: iconst_4
    //   166: invokevirtual 350	java/lang/String:substring	(II)Ljava/lang/String;
    //   169: invokevirtual 359	java/lang/String:length	()I
    //   172: iconst_4
    //   173: iadd
    //   174: invokestatic 364	ro/btrl/boot/ui/activity/TncActivity:ॱ	(ICI)Ljava/lang/String;
    //   177: invokevirtual 368	java/lang/String:intern	()Ljava/lang/String;
    //   180: invokestatic 373	o/vq:ˋ	(Ljava/lang/Object;Ljava/lang/String;)V
    //   183: aload 5
    //   185: checkcast 307	o/Dx
    //   188: aload_1
    //   189: invokevirtual 659	o/Dx:ˎ	(Lo/DE;)V
    //   192: goto +3 -> 195
    //   195: getstatic 34	ro/btrl/boot/ui/activity/TncActivity:ʾ	I
    //   198: bipush 57
    //   200: iadd
    //   201: istore_3
    //   202: iload_3
    //   203: sipush 128
    //   206: irem
    //   207: putstatic 32	ro/btrl/boot/ui/activity/TncActivity:ʿ	I
    //   210: iload_3
    //   211: iconst_2
    //   212: irem
    //   213: ifeq +4 -> 217
    //   216: return
    //   217: return
    // Local variable table:
    //   start	length	slot	name	signature
    //   0	218	0	this	TncActivity
    //   0	218	1	paramDE	o.DE
    //   71	13	2	c	char
    //   21	192	3	i	int
    //   62	8	4	j	int
    //   43	141	5	localObject	Object
    // Exception table:
    //   from	to	target	type
    //   57	64	3	java/lang/Exception
    //   39	45	9	java/lang/Exception
    //   45	51	9	java/lang/Exception
    //   51	57	9	java/lang/Exception
    //   57	64	9	java/lang/Exception
    //   72	78	9	java/lang/Exception
    //   78	192	9	java/lang/Exception
  }
  
  public void ॱˎ()
  {
    try
    {
      i = ʾ;
      i += 31;
      ʿ = i % 128;
      if (i % 2 != 0) {
        break label85;
      }
      return;
    }
    catch (Exception localException)
    {
      label30:
      throw localException;
    }
    int i = 0;
    break label93;
    for (;;)
    {
      i = ʾ + 25;
      ʿ = i % 128;
      if (i % 2 != 0) {
        break label30;
      }
      break label80;
      ˏˏ();
      i = 62 / 0;
      break;
    }
    label80:
    i = 1;
    break label93;
    label85:
    return;
    for (;;)
    {
      ˏˏ();
      break;
      label93:
      switch (i)
      {
      }
    }
  }
  
  /* Error */
  protected DK.iF ॱᐝ()
  {
    // Byte code:
    //   0: aload_0
    //   1: getfield 667	ro/btrl/boot/ui/activity/TncActivity:mPresenter	Lo/DK$iF;
    //   4: astore_2
    //   5: aload_2
    //   6: ifnonnull +6 -> 12
    //   9: goto +6 -> 15
    //   12: goto +12 -> 24
    //   15: bipush 50
    //   17: istore_1
    //   18: goto +202 -> 220
    //   21: goto +15 -> 36
    //   24: bipush 36
    //   26: istore_1
    //   27: goto +193 -> 220
    //   30: goto +124 -> 154
    //   33: astore_2
    //   34: aload_2
    //   35: athrow
    //   36: aload_0
    //   37: invokevirtual 337	android/content/Context:getResources	()Landroid/content/res/Resources;
    //   40: astore_3
    //   41: aload_3
    //   42: ldc_w 668
    //   45: invokevirtual 344	android/content/res/Resources:getString	(I)Ljava/lang/String;
    //   48: iconst_0
    //   49: iconst_4
    //   50: invokevirtual 350	java/lang/String:substring	(II)Ljava/lang/String;
    //   53: iconst_1
    //   54: invokevirtual 354	java/lang/String:codePointAt	(I)I
    //   57: bipush 26
    //   59: isub
    //   60: aload_0
    //   61: invokevirtual 337	android/content/Context:getResources	()Landroid/content/res/Resources;
    //   64: ldc_w 669
    //   67: invokevirtual 344	android/content/res/Resources:getString	(I)Ljava/lang/String;
    //   70: iconst_0
    //   71: iconst_4
    //   72: invokevirtual 350	java/lang/String:substring	(II)Ljava/lang/String;
    //   75: invokevirtual 359	java/lang/String:length	()I
    //   78: ldc_w 670
    //   81: iadd
    //   82: i2c
    //   83: aload_0
    //   84: invokevirtual 337	android/content/Context:getResources	()Landroid/content/res/Resources;
    //   87: ldc_w 532
    //   90: invokevirtual 344	android/content/res/Resources:getString	(I)Ljava/lang/String;
    //   93: iconst_0
    //   94: bipush 16
    //   96: invokevirtual 350	java/lang/String:substring	(II)Ljava/lang/String;
    //   99: invokevirtual 359	java/lang/String:length	()I
    //   102: bipush 6
    //   104: isub
    //   105: invokestatic 364	ro/btrl/boot/ui/activity/TncActivity:ॱ	(ICI)Ljava/lang/String;
    //   108: invokevirtual 368	java/lang/String:intern	()Ljava/lang/String;
    //   111: invokestatic 671	o/vq:ˊ	(Ljava/lang/String;)V
    //   114: goto -84 -> 30
    //   117: aload_2
    //   118: areturn
    //   119: getstatic 32	ro/btrl/boot/ui/activity/TncActivity:ʿ	I
    //   122: bipush 109
    //   124: iadd
    //   125: istore_1
    //   126: iload_1
    //   127: sipush 128
    //   130: irem
    //   131: putstatic 34	ro/btrl/boot/ui/activity/TncActivity:ʾ	I
    //   134: iload_1
    //   135: iconst_2
    //   136: irem
    //   137: ifne +6 -> 143
    //   140: goto -119 -> 21
    //   143: goto -107 -> 36
    //   146: astore_2
    //   147: aload_2
    //   148: athrow
    //   149: iconst_0
    //   150: istore_1
    //   151: goto +32 -> 183
    //   154: getstatic 32	ro/btrl/boot/ui/activity/TncActivity:ʿ	I
    //   157: istore_1
    //   158: iload_1
    //   159: bipush 23
    //   161: iadd
    //   162: istore_1
    //   163: iload_1
    //   164: sipush 128
    //   167: irem
    //   168: putstatic 34	ro/btrl/boot/ui/activity/TncActivity:ʾ	I
    //   171: iload_1
    //   172: iconst_2
    //   173: irem
    //   174: ifne +6 -> 180
    //   177: goto +38 -> 215
    //   180: goto -31 -> 149
    //   183: iload_1
    //   184: tableswitch	default:+24->208, 0:+-67->117, 1:+24->208
    //   208: bipush 6
    //   210: iconst_0
    //   211: idiv
    //   212: istore_1
    //   213: aload_2
    //   214: areturn
    //   215: iconst_1
    //   216: istore_1
    //   217: goto -34 -> 183
    //   220: iload_1
    //   221: lookupswitch	default:+27->248, 36:+-191->30, 50:+-102->119
    //   248: goto -218 -> 30
    // Local variable table:
    //   start	length	slot	name	signature
    //   0	251	0	this	TncActivity
    //   17	204	1	i	int
    //   4	2	2	localIF	DK.iF
    //   33	85	2	localException1	Exception
    //   146	68	2	localException2	Exception
    //   40	2	3	localResources	Resources
    // Exception table:
    //   from	to	target	type
    //   36	41	33	java/lang/Exception
    //   154	158	33	java/lang/Exception
    //   163	171	33	java/lang/Exception
    //   0	5	146	java/lang/Exception
    //   41	114	146	java/lang/Exception
  }
  
  public static final class If
    implements aD.If
  {
    private static int ʻ = 0;
    private static char ˊ = 55487;
    private static char ˋ;
    private static char ˎ;
    private static char ˏ;
    private static int ॱॱ = 1;
    
    static
    {
      ˋ = 'Ḍ';
      ˏ = '⽌';
      ˎ = 42176;
    }
    
    If() {}
    
    private static String ॱ(char[] paramArrayOfChar)
    {
      char[] arrayOfChar1;
      int j;
      char[] arrayOfChar2;
      for (;;)
      {
        arrayOfChar1 = new char[paramArrayOfChar.length];
        j = 0;
        arrayOfChar2 = new char[2];
        break;
      }
      label225:
      for (;;)
      {
        try
        {
          int i = ॱॱ;
          i += 83;
          ʻ = i % 128;
          if (i % 2 == 0)
          {
            i = 48;
            continue;
            i = j;
            continue;
            j = 14;
            break label225;
            return new String(arrayOfChar1, 1, arrayOfChar1[0]);
            if (i < paramArrayOfChar.length) {
              continue;
            }
            continue;
            i = j;
            continue;
            continue;
            switch (i)
            {
            }
            continue;
            j = ʻ + 117;
            ॱॱ = j % 128;
            if (j % 2 == 0) {
              continue;
            }
            arrayOfChar2[0] = paramArrayOfChar[i];
            arrayOfChar2[1] = paramArrayOfChar[(i + 1)];
            oP.ˏ(arrayOfChar2, ˊ, ˏ, ˎ, ˋ);
            arrayOfChar1[i] = arrayOfChar2[0];
            arrayOfChar1[(i + 1)] = arrayOfChar2[1];
            i += 2;
            continue;
            j = 66;
            break label225;
          }
          else
          {
            i = 12;
            continue;
          }
          continue;
          continue;
          switch (j)
          {
          }
        }
        catch (Exception paramArrayOfChar)
        {
          throw paramArrayOfChar;
        }
      }
    }
    
    public void ˋ(H paramH)
    {
      break label212;
      switch (i)
      {
      default: 
        return;
        i = 4 / 5;
        return;
        label38:
        return;
        label39:
        if (vq.ˊ(paramH, H.ˎ)) {
          break;
        }
        break;
      }
      label55:
      for (int i = 2;; i = 86)
      {
        switch (i)
        {
        }
        break label38;
        i = 9;
        break;
        return;
        label94:
        break label39;
        i = ʻ + 73;
        ॱॱ = i % 128;
        if (i % 2 == 0) {
          break label55;
        }
        try
        {
          paramH = this.ॱ;
          try
          {
            paramH = TncActivity.ˋ(paramH);
            String str = ॱ(new char[] { -6046, 2366, 1183, 21492, -19849, -11483, -23576, -20201, 4106, -27428 });
            vq.ˋ(paramH, str.intern());
            paramH.ˏ(true);
          }
          catch (Exception paramH)
          {
            label212:
            throw paramH;
          }
          i = ʻ + 9;
          ॱॱ = i % 128;
          if (i % 2 == 0) {
            break label94;
          }
        }
        catch (Exception paramH)
        {
          throw paramH;
        }
        i = 55;
        break;
      }
    }
  }
  
  public static final class iF
    extends Hp
  {
    private static int ʻ;
    private static int ʼ = 0;
    private static boolean ˊ;
    private static boolean ˋ;
    private static int ˏ = 112;
    private static char[] ॱ;
    
    static
    {
      ʻ = 1;
      ˋ = true;
      ˊ = true;
      ॱ = new char[] { 228, 213, 232, 221, 178, 217, 222, 212, 215, 158, 227, 181, 209, 220 };
    }
    
    iF() {}
    
    private static String ˋ(byte[] paramArrayOfByte, int[] paramArrayOfInt, char[] paramArrayOfChar, int paramInt)
    {
      break label185;
      int m = ʼ + 111;
      ʻ = m % 128;
      int j;
      label45:
      int i;
      char[] arrayOfChar3;
      int k;
      char[] arrayOfChar2;
      if (m % 2 != 0)
      {
        break label494;
        char[] arrayOfChar1;
        if (paramInt >= j)
        {
          break label485;
          i = ʼ + 117;
          ʻ = i % 128;
          if (i % 2 != 0)
          {
            break label339;
            m = paramArrayOfInt.length;
            paramArrayOfByte = new char[m];
            paramInt = 0;
            break label173;
            arrayOfChar1 = arrayOfChar3;
            i = k;
            arrayOfChar2 = arrayOfChar3;
            j = k;
            switch (m)
            {
            default: 
              arrayOfChar1 = arrayOfChar3;
              i = k;
              break;
            }
          }
        }
        for (;;)
        {
          j = ʻ + 67;
          ʼ = j % 128;
          if (j % 2 != 0) {
            break label562;
          }
          break label447;
          label173:
          if (paramInt >= m)
          {
            break label195;
            label185:
            break label45;
            i = 92;
            break label525;
            label195:
            j = 64;
            break label389;
            label202:
            if (i < k) {
              break;
            }
          }
          for (;;)
          {
            return new String(paramArrayOfByte);
            label254:
            label261:
            label288:
            for (;;)
            {
              k = paramInt;
              if (ˊ) {
                break label319;
              }
              break;
              for (;;)
              {
                k = paramArrayOfByte.length;
                paramArrayOfInt = new char[k];
                i = 0;
                break label202;
                m = 17;
                break;
                arrayOfChar1 = ॱ;
                i = ˏ;
                if (!ˋ) {
                  break label288;
                }
                arrayOfChar2 = arrayOfChar1;
                j = i;
              }
            }
            for (;;)
            {
              label291:
              paramArrayOfByte[paramInt] = ((char)(arrayOfChar1[(paramArrayOfChar[(j - 1 - paramInt)] - k)] - i));
              paramInt += 1;
              break;
              label319:
              j = paramArrayOfChar.length;
              paramArrayOfByte = new char[j];
              paramInt = 0;
              break;
              label336:
              label339:
              do
              {
                break label291;
                break;
                i = 46;
                break label525;
                return new String(paramArrayOfInt);
                m = ʻ + 125;
                ʼ = m % 128;
              } while (m % 2 != 0);
            }
            j = 45;
            label389:
            switch (j)
            {
            }
          }
          paramArrayOfByte[paramInt] = ((char)(arrayOfChar1[(paramArrayOfInt[(m - 1 - paramInt)] - k)] - i));
          paramInt += 1;
        }
      }
      label447:
      label485:
      label494:
      label525:
      label555:
      label562:
      for (;;)
      {
        break label173;
        break label494;
        arrayOfChar3 = ॱ;
        k = ˏ;
        boolean bool = ˋ;
        i = 64 / 0;
        if (bool) {
          break label254;
        }
        break label555;
        return new String(paramArrayOfByte);
        paramArrayOfInt[i] = ((char)(arrayOfChar2[(paramArrayOfByte[(k - 1 - i)] + paramInt)] - j));
        i += 1;
        break label336;
        switch (i)
        {
        }
        break label261;
        m = 58;
        break;
      }
    }
    
    /* Error */
    public void ˏ(String paramString)
    {
      // Byte code:
      //   0: goto +6 -> 6
      //   3: astore_1
      //   4: aload_1
      //   5: athrow
      //   6: goto +19 -> 25
      //   9: aload_0
      //   10: getfield 54	ro/btrl/boot/ui/activity/TncActivity$iF:ˎ	Lro/btrl/boot/ui/activity/TncActivity;
      //   13: invokestatic 67	ro/btrl/boot/ui/activity/TncActivity:ˋ	(Lro/btrl/boot/ui/activity/TncActivity;)Lo/Dx;
      //   16: getfield 72	o/Dx:ʼ	Lo/ap;
      //   19: invokevirtual 76	o/ap:ˊ	()V
      //   22: goto +58 -> 80
      //   25: getstatic 25	ro/btrl/boot/ui/activity/TncActivity$iF:ʻ	I
      //   28: bipush 121
      //   30: iadd
      //   31: istore_2
      //   32: iload_2
      //   33: sipush 128
      //   36: irem
      //   37: putstatic 23	ro/btrl/boot/ui/activity/TncActivity$iF:ʼ	I
      //   40: iload_2
      //   41: iconst_2
      //   42: irem
      //   43: ifeq +6 -> 49
      //   46: goto +449 -> 495
      //   49: goto +88 -> 137
      //   52: getstatic 25	ro/btrl/boot/ui/activity/TncActivity$iF:ʻ	I
      //   55: istore_2
      //   56: iload_2
      //   57: bipush 125
      //   59: iadd
      //   60: istore_2
      //   61: iload_2
      //   62: sipush 128
      //   65: irem
      //   66: putstatic 23	ro/btrl/boot/ui/activity/TncActivity$iF:ʼ	I
      //   69: iload_2
      //   70: iconst_2
      //   71: irem
      //   72: ifeq +6 -> 78
      //   75: goto +4 -> 79
      //   78: return
      //   79: return
      //   80: aload_0
      //   81: getfield 54	ro/btrl/boot/ui/activity/TncActivity$iF:ˎ	Lro/btrl/boot/ui/activity/TncActivity;
      //   84: invokestatic 67	ro/btrl/boot/ui/activity/TncActivity:ˋ	(Lro/btrl/boot/ui/activity/TncActivity;)Lo/Dx;
      //   87: getfield 79	o/Dx:ॱ	Landroid/widget/EditText;
      //   90: aload_0
      //   91: checkcast 81	android/text/TextWatcher
      //   94: invokevirtual 87	android/widget/EditText:removeTextChangedListener	(Landroid/text/TextWatcher;)V
      //   97: goto -45 -> 52
      //   100: iload_2
      //   101: lookupswitch	default:+27->128, 1:+-92->9, 10:+-21->80
      //   128: goto -48 -> 80
      //   131: bipush 10
      //   133: istore_2
      //   134: goto -34 -> 100
      //   137: aload_1
      //   138: iconst_4
      //   139: newarray byte
      //   141: dup
      //   142: iconst_0
      //   143: ldc 88
      //   145: bastore
      //   146: dup
      //   147: iconst_1
      //   148: ldc 89
      //   150: bastore
      //   151: dup
      //   152: iconst_2
      //   153: ldc 90
      //   155: bastore
      //   156: dup
      //   157: iconst_3
      //   158: ldc 88
      //   160: bastore
      //   161: aconst_null
      //   162: aconst_null
      //   163: bipush 127
      //   165: invokestatic 92	ro/btrl/boot/ui/activity/TncActivity$iF:ˋ	([B[I[CI)Ljava/lang/String;
      //   168: invokevirtual 96	java/lang/String:intern	()Ljava/lang/String;
      //   171: invokestatic 101	o/vq:ˎ	(Ljava/lang/Object;Ljava/lang/String;)V
      //   174: aload_0
      //   175: getfield 54	ro/btrl/boot/ui/activity/TncActivity$iF:ˎ	Lro/btrl/boot/ui/activity/TncActivity;
      //   178: invokestatic 67	ro/btrl/boot/ui/activity/TncActivity:ˋ	(Lro/btrl/boot/ui/activity/TncActivity;)Lo/Dx;
      //   181: getfield 72	o/Dx:ʼ	Lo/ap;
      //   184: astore_1
      //   185: aload_1
      //   186: bipush 21
      //   188: newarray byte
      //   190: dup
      //   191: iconst_0
      //   192: ldc 102
      //   194: bastore
      //   195: dup
      //   196: iconst_1
      //   197: ldc 88
      //   199: bastore
      //   200: dup
      //   201: iconst_2
      //   202: ldc 103
      //   204: bastore
      //   205: dup
      //   206: iconst_3
      //   207: ldc 104
      //   209: bastore
      //   210: dup
      //   211: iconst_4
      //   212: ldc 105
      //   214: bastore
      //   215: dup
      //   216: iconst_5
      //   217: ldc 106
      //   219: bastore
      //   220: dup
      //   221: bipush 6
      //   223: ldc 107
      //   225: bastore
      //   226: dup
      //   227: bipush 7
      //   229: ldc 108
      //   231: bastore
      //   232: dup
      //   233: bipush 8
      //   235: ldc 109
      //   237: bastore
      //   238: dup
      //   239: bipush 9
      //   241: ldc 102
      //   243: bastore
      //   244: dup
      //   245: bipush 10
      //   247: ldc 90
      //   249: bastore
      //   250: dup
      //   251: bipush 11
      //   253: ldc 110
      //   255: bastore
      //   256: dup
      //   257: bipush 12
      //   259: ldc 111
      //   261: bastore
      //   262: dup
      //   263: bipush 13
      //   265: ldc 112
      //   267: bastore
      //   268: dup
      //   269: bipush 14
      //   271: ldc 102
      //   273: bastore
      //   274: dup
      //   275: bipush 15
      //   277: ldc 105
      //   279: bastore
      //   280: dup
      //   281: bipush 16
      //   283: ldc 109
      //   285: bastore
      //   286: dup
      //   287: bipush 17
      //   289: ldc 102
      //   291: bastore
      //   292: dup
      //   293: bipush 18
      //   295: ldc 105
      //   297: bastore
      //   298: dup
      //   299: bipush 19
      //   301: ldc 103
      //   303: bastore
      //   304: dup
      //   305: bipush 20
      //   307: ldc 107
      //   309: bastore
      //   310: aconst_null
      //   311: aconst_null
      //   312: bipush 127
      //   314: invokestatic 92	ro/btrl/boot/ui/activity/TncActivity$iF:ˋ	([B[I[CI)Ljava/lang/String;
      //   317: invokevirtual 96	java/lang/String:intern	()Ljava/lang/String;
      //   320: invokestatic 114	o/vq:ˋ	(Ljava/lang/Object;Ljava/lang/String;)V
      //   323: aload_1
      //   324: iconst_1
      //   325: invokevirtual 118	o/ap:setEnabled	(Z)V
      //   328: aload_0
      //   329: getfield 54	ro/btrl/boot/ui/activity/TncActivity$iF:ˎ	Lro/btrl/boot/ui/activity/TncActivity;
      //   332: invokestatic 67	ro/btrl/boot/ui/activity/TncActivity:ˋ	(Lro/btrl/boot/ui/activity/TncActivity;)Lo/Dx;
      //   335: getfield 72	o/Dx:ʼ	Lo/ap;
      //   338: astore_1
      //   339: aload_1
      //   340: bipush 21
      //   342: newarray byte
      //   344: dup
      //   345: iconst_0
      //   346: ldc 102
      //   348: bastore
      //   349: dup
      //   350: iconst_1
      //   351: ldc 88
      //   353: bastore
      //   354: dup
      //   355: iconst_2
      //   356: ldc 103
      //   358: bastore
      //   359: dup
      //   360: iconst_3
      //   361: ldc 104
      //   363: bastore
      //   364: dup
      //   365: iconst_4
      //   366: ldc 105
      //   368: bastore
      //   369: dup
      //   370: iconst_5
      //   371: ldc 106
      //   373: bastore
      //   374: dup
      //   375: bipush 6
      //   377: ldc 107
      //   379: bastore
      //   380: dup
      //   381: bipush 7
      //   383: ldc 108
      //   385: bastore
      //   386: dup
      //   387: bipush 8
      //   389: ldc 109
      //   391: bastore
      //   392: dup
      //   393: bipush 9
      //   395: ldc 102
      //   397: bastore
      //   398: dup
      //   399: bipush 10
      //   401: ldc 90
      //   403: bastore
      //   404: dup
      //   405: bipush 11
      //   407: ldc 110
      //   409: bastore
      //   410: dup
      //   411: bipush 12
      //   413: ldc 111
      //   415: bastore
      //   416: dup
      //   417: bipush 13
      //   419: ldc 112
      //   421: bastore
      //   422: dup
      //   423: bipush 14
      //   425: ldc 102
      //   427: bastore
      //   428: dup
      //   429: bipush 15
      //   431: ldc 105
      //   433: bastore
      //   434: dup
      //   435: bipush 16
      //   437: ldc 109
      //   439: bastore
      //   440: dup
      //   441: bipush 17
      //   443: ldc 102
      //   445: bastore
      //   446: dup
      //   447: bipush 18
      //   449: ldc 105
      //   451: bastore
      //   452: dup
      //   453: bipush 19
      //   455: ldc 103
      //   457: bastore
      //   458: dup
      //   459: bipush 20
      //   461: ldc 107
      //   463: bastore
      //   464: aconst_null
      //   465: aconst_null
      //   466: bipush 127
      //   468: invokestatic 92	ro/btrl/boot/ui/activity/TncActivity$iF:ˋ	([B[I[CI)Ljava/lang/String;
      //   471: invokevirtual 96	java/lang/String:intern	()Ljava/lang/String;
      //   474: invokestatic 114	o/vq:ˋ	(Ljava/lang/Object;Ljava/lang/String;)V
      //   477: aload_1
      //   478: invokevirtual 121	o/ap:ʼ	()Z
      //   481: ifne +6 -> 487
      //   484: goto +6 -> 490
      //   487: goto -356 -> 131
      //   490: iconst_1
      //   491: istore_2
      //   492: goto -392 -> 100
      //   495: goto -358 -> 137
      // Local variable table:
      //   start	length	slot	name	signature
      //   0	498	0	this	iF
      //   0	498	1	paramString	String
      //   31	461	2	i	int
      // Exception table:
      //   from	to	target	type
      //   52	56	3	java/lang/Exception
      //   61	69	3	java/lang/Exception
    }
  }
  
  static final class ˊ
    implements ViewTreeObserver.OnGlobalLayoutListener
  {
    private static int[] ˋ = { -1217103821, -1311353424, 1745246873, 1876135855, -1853839264, -2083779441, 1800346406, -1824981432, 1040751166, -87028145, 1709005146, 701607707, -1398891615, 1719791893, 734210536, 412457606, -1632565355, -559131072 };
    private static int ˏ = 0;
    private static int ॱ = 1;
    
    ˊ(TncActivity paramTncActivity) {}
    
    private static String ˎ(int[] paramArrayOfInt, int paramInt)
    {
      break label203;
      break label118;
      label6:
      int j = 1;
      break label176;
      label11:
      char[] arrayOfChar2;
      label118:
      label176:
      label203:
      label226:
      label253:
      for (;;)
      {
        char[] arrayOfChar1;
        int i;
        arrayOfChar1[0] = ((char)(paramArrayOfInt[i] >> 16));
        arrayOfChar1[1] = ((char)paramArrayOfInt[i]);
        arrayOfChar1[2] = ((char)(paramArrayOfInt[(i + 1)] >> 16));
        arrayOfChar1[3] = ((char)paramArrayOfInt[(i + 1)]);
        int[] arrayOfInt;
        oN.ˏ(arrayOfChar1, arrayOfInt, false);
        arrayOfChar2[(i << 1)] = arrayOfChar1[0];
        arrayOfChar2[((i << 1) + 1)] = arrayOfChar1[1];
        arrayOfChar2[((i << 1) + 2)] = arrayOfChar1[2];
        arrayOfChar2[((i << 1) + 3)] = arrayOfChar1[3];
        i += 2;
        for (;;)
        {
          arrayOfChar1 = new char[4];
          arrayOfChar2 = new char[paramArrayOfInt.length << 1];
          arrayOfInt = (int[])ˋ.clone();
          i = 0;
          break label11;
          for (;;)
          {
            try
            {
              j = ˏ;
              j += 35;
              ॱ = j % 128;
              if (j % 2 == 0) {
                break label253;
              }
            }
            catch (Exception paramArrayOfInt)
            {
              throw paramArrayOfInt;
            }
            switch (j)
            {
            case 1: 
            default: 
              continue;
              break label226;
              if (i < paramArrayOfInt.length) {
                break label6;
              }
              j = 0;
            }
          }
          i = ˏ + 45;
          ॱ = i % 128;
          if (i % 2 == 0) {
            break;
          }
        }
      }
      return new String(arrayOfChar2, 0, paramInt);
    }
    
    /* Error */
    public final void onGlobalLayout()
    {
      // Byte code:
      //   0: goto +66 -> 66
      //   3: iload_1
      //   4: lookupswitch	default:+28->32, 25:+243->247, 95:+197->201
      //   32: return
      //   33: astore_3
      //   34: aload_3
      //   35: athrow
      //   36: goto +177 -> 213
      //   39: getstatic 21	ro/btrl/boot/ui/activity/TncActivity$ˊ:ˏ	I
      //   42: bipush 51
      //   44: iadd
      //   45: istore_1
      //   46: iload_1
      //   47: sipush 128
      //   50: irem
      //   51: putstatic 23	ro/btrl/boot/ui/activity/TncActivity$ˊ:ॱ	I
      //   54: iload_1
      //   55: iconst_2
      //   56: irem
      //   57: ifne +6 -> 63
      //   60: goto +83 -> 143
      //   63: goto +118 -> 181
      //   66: aload_0
      //   67: getfield 48	ro/btrl/boot/ui/activity/TncActivity$ˊ:ˎ	Lro/btrl/boot/ui/activity/TncActivity;
      //   70: astore_3
      //   71: aload_3
      //   72: invokestatic 72	ro/btrl/boot/ui/activity/TncActivity:ˋ	(Lro/btrl/boot/ui/activity/TncActivity;)Lo/Dx;
      //   75: astore_3
      //   76: iconst_4
      //   77: newarray int
      //   79: dup
      //   80: iconst_0
      //   81: ldc 73
      //   83: iastore
      //   84: dup
      //   85: iconst_1
      //   86: ldc 74
      //   88: iastore
      //   89: dup
      //   90: iconst_2
      //   91: ldc 75
      //   93: iastore
      //   94: dup
      //   95: iconst_3
      //   96: ldc 76
      //   98: iastore
      //   99: bipush 8
      //   101: invokestatic 78	ro/btrl/boot/ui/activity/TncActivity$ˊ:ˎ	([II)Ljava/lang/String;
      //   104: astore 4
      //   106: aload 4
      //   108: invokevirtual 82	java/lang/String:intern	()Ljava/lang/String;
      //   111: astore 4
      //   113: aload_3
      //   114: aload 4
      //   116: invokestatic 87	o/vq:ˋ	(Ljava/lang/Object;Ljava/lang/String;)V
      //   119: aload_0
      //   120: getfield 48	ro/btrl/boot/ui/activity/TncActivity$ˊ:ˎ	Lro/btrl/boot/ui/activity/TncActivity;
      //   123: invokestatic 72	ro/btrl/boot/ui/activity/TncActivity:ˋ	(Lro/btrl/boot/ui/activity/TncActivity;)Lo/Dx;
      //   126: getfield 93	o/Dx:ʽ	Lo/aA;
      //   129: invokevirtual 98	o/aA:ˎ	()Z
      //   132: istore_2
      //   133: iload_2
      //   134: ifne +6 -> 140
      //   137: goto +50 -> 187
      //   140: goto +67 -> 207
      //   143: bipush 95
      //   145: istore_1
      //   146: goto -143 -> 3
      //   149: getstatic 23	ro/btrl/boot/ui/activity/TncActivity$ˊ:ॱ	I
      //   152: bipush 71
      //   154: iadd
      //   155: istore_1
      //   156: iload_1
      //   157: sipush 128
      //   160: irem
      //   161: putstatic 21	ro/btrl/boot/ui/activity/TncActivity$ˊ:ˏ	I
      //   164: iload_1
      //   165: iconst_2
      //   166: irem
      //   167: ifeq +6 -> 173
      //   170: goto -134 -> 36
      //   173: goto +40 -> 213
      //   176: iconst_1
      //   177: istore_2
      //   178: goto -29 -> 149
      //   181: bipush 25
      //   183: istore_1
      //   184: goto -181 -> 3
      //   187: bipush 83
      //   189: istore_1
      //   190: goto +26 -> 216
      //   193: iconst_0
      //   194: istore_2
      //   195: goto +53 -> 248
      //   198: astore_3
      //   199: aload_3
      //   200: athrow
      //   201: bipush 70
      //   203: iconst_0
      //   204: idiv
      //   205: istore_1
      //   206: return
      //   207: bipush 68
      //   209: istore_1
      //   210: goto +6 -> 216
      //   213: goto +35 -> 248
      //   216: iload_1
      //   217: lookupswitch	default:+27->244, 68:+-24->193, 83:+-41->176
      //   244: goto -68 -> 176
      //   247: return
      //   248: aload_3
      //   249: iload_2
      //   250: invokevirtual 101	o/Dx:ˏ	(Z)V
      //   253: goto -214 -> 39
      // Local variable table:
      //   start	length	slot	name	signature
      //   0	256	0	this	ˊ
      //   3	214	1	i	int
      //   132	118	2	bool	boolean
      //   33	2	3	localException1	Exception
      //   70	44	3	localObject	Object
      //   198	51	3	localException2	Exception
      //   104	11	4	str	String
      // Exception table:
      //   from	to	target	type
      //   66	71	33	java/lang/Exception
      //   71	76	33	java/lang/Exception
      //   76	106	198	java/lang/Exception
      //   106	113	198	java/lang/Exception
      //   113	133	198	java/lang/Exception
    }
  }
  
  final class ˋ
    extends WebViewClient
  {
    private static int ˋ = 1;
    private static char[] ˏ = { 138, 268, 261, 269, 58, 112, 111, 50, 105, 107, 85, 87, 106, 106, 107, 88, 170, 170, 178, 172, 171, 178 };
    private static int ॱ = 0;
    
    public ˋ() {}
    
    /* Error */
    private static String ˎ(int[] paramArrayOfInt, byte[] paramArrayOfByte, boolean paramBoolean)
    {
      // Byte code:
      //   0: goto +324 -> 324
      //   3: getstatic 19	ro/btrl/boot/ui/activity/TncActivity$ˋ:ˋ	I
      //   6: bipush 31
      //   8: iadd
      //   9: istore_3
      //   10: iload_3
      //   11: sipush 128
      //   14: irem
      //   15: putstatic 17	ro/btrl/boot/ui/activity/TncActivity$ˋ:ॱ	I
      //   18: iload_3
      //   19: iconst_2
      //   20: irem
      //   21: ifeq +6 -> 27
      //   24: goto +335 -> 359
      //   27: goto +180 -> 207
      //   30: aload 9
      //   32: astore_1
      //   33: goto +329 -> 362
      //   36: bipush 6
      //   38: istore_3
      //   39: goto +15 -> 54
      //   42: astore_0
      //   43: aload_0
      //   44: athrow
      //   45: new 53	java/lang/String
      //   48: dup
      //   49: aload_1
      //   50: invokespecial 56	java/lang/String:<init>	([C)V
      //   53: areturn
      //   54: iload_3
      //   55: lookupswitch	default:+25->80, 6:+330->385, 96:+68->123
      //   80: goto +43 -> 123
      //   83: getstatic 19	ro/btrl/boot/ui/activity/TncActivity$ˋ:ˋ	I
      //   86: istore 4
      //   88: iload 4
      //   90: bipush 125
      //   92: iadd
      //   93: istore 4
      //   95: iload 4
      //   97: sipush 128
      //   100: irem
      //   101: putstatic 17	ro/btrl/boot/ui/activity/TncActivity$ˋ:ॱ	I
      //   104: iload 4
      //   106: iconst_2
      //   107: irem
      //   108: ifeq +6 -> 114
      //   111: goto +59 -> 170
      //   114: goto +481 -> 595
      //   117: iconst_0
      //   118: istore 4
      //   120: goto +449 -> 569
      //   123: iload 6
      //   125: newarray char
      //   127: astore 9
      //   129: aload_1
      //   130: iconst_0
      //   131: aload 9
      //   133: iconst_0
      //   134: iload 6
      //   136: invokestatic 62	java/lang/System:arraycopy	(Ljava/lang/Object;ILjava/lang/Object;II)V
      //   139: aload 9
      //   141: iconst_0
      //   142: aload_1
      //   143: iload 6
      //   145: iload 8
      //   147: isub
      //   148: iload 8
      //   150: invokestatic 62	java/lang/System:arraycopy	(Ljava/lang/Object;ILjava/lang/Object;II)V
      //   153: aload 9
      //   155: iload 8
      //   157: aload_1
      //   158: iconst_0
      //   159: iload 6
      //   161: iload 8
      //   163: isub
      //   164: invokestatic 62	java/lang/System:arraycopy	(Ljava/lang/Object;ILjava/lang/Object;II)V
      //   167: goto +218 -> 385
      //   170: goto +425 -> 595
      //   173: getstatic 19	ro/btrl/boot/ui/activity/TncActivity$ˋ:ˋ	I
      //   176: bipush 97
      //   178: iadd
      //   179: istore_3
      //   180: iload_3
      //   181: sipush 128
      //   184: irem
      //   185: putstatic 17	ro/btrl/boot/ui/activity/TncActivity$ˋ:ॱ	I
      //   188: iload_3
      //   189: iconst_2
      //   190: irem
      //   191: ifeq +6 -> 197
      //   194: goto +283 -> 477
      //   197: goto +94 -> 291
      //   200: bipush 98
      //   202: istore 5
      //   204: goto +57 -> 261
      //   207: aload_0
      //   208: iconst_0
      //   209: iaload
      //   210: istore_3
      //   211: aload_0
      //   212: iconst_1
      //   213: iaload
      //   214: istore 6
      //   216: aload_0
      //   217: iconst_2
      //   218: iaload
      //   219: istore 7
      //   221: aload_0
      //   222: iconst_3
      //   223: iaload
      //   224: istore 8
      //   226: getstatic 39	ro/btrl/boot/ui/activity/TncActivity$ˋ:ˏ	[C
      //   229: astore 10
      //   231: iload 6
      //   233: newarray char
      //   235: astore 9
      //   237: aload 10
      //   239: iload_3
      //   240: aload 9
      //   242: iconst_0
      //   243: iload 6
      //   245: invokestatic 62	java/lang/System:arraycopy	(Ljava/lang/Object;ILjava/lang/Object;II)V
      //   248: aload_1
      //   249: ifnull +6 -> 255
      //   252: goto +211 -> 463
      //   255: aload 9
      //   257: astore_1
      //   258: goto +173 -> 431
      //   261: iload 5
      //   263: lookupswitch	default:+25->288, 79:+286->549, 98:+64->327
      //   288: goto +39 -> 327
      //   291: iload 6
      //   293: newarray char
      //   295: astore 9
      //   297: iconst_0
      //   298: istore_3
      //   299: goto +74 -> 373
      //   302: iload 4
      //   304: iload 6
      //   306: if_icmpge +6 -> 312
      //   309: goto +234 -> 543
      //   312: goto +83 -> 395
      //   315: goto +58 -> 373
      //   318: goto +83 -> 401
      //   321: goto +182 -> 503
      //   324: goto -321 -> 3
      //   327: aload 10
      //   329: iload 4
      //   331: aload 9
      //   333: iload 4
      //   335: caload
      //   336: iconst_1
      //   337: ishl
      //   338: iload_3
      //   339: isub
      //   340: i2c
      //   341: castore
      //   342: goto -24 -> 318
      //   345: aload_1
      //   346: iload 4
      //   348: baload
      //   349: iconst_1
      //   350: if_icmpne +6 -> 356
      //   353: goto +103 -> 456
      //   356: goto -156 -> 200
      //   359: goto -152 -> 207
      //   362: iload 7
      //   364: ifle +6 -> 370
      //   367: goto +78 -> 445
      //   370: goto -325 -> 45
      //   373: iload_3
      //   374: iload 6
      //   376: if_icmpge +6 -> 382
      //   379: goto -296 -> 83
      //   382: goto -352 -> 30
      //   385: iload_2
      //   386: ifeq +6 -> 392
      //   389: goto -216 -> 173
      //   392: goto -30 -> 362
      //   395: iconst_0
      //   396: istore 5
      //   398: goto +117 -> 515
      //   401: aload 10
      //   403: iload 4
      //   405: caload
      //   406: istore_3
      //   407: iload 4
      //   409: iconst_1
      //   410: iadd
      //   411: istore 4
      //   413: goto +29 -> 442
      //   416: astore_0
      //   417: aload_0
      //   418: athrow
      //   419: bipush 96
      //   421: istore_3
      //   422: goto -368 -> 54
      //   425: iconst_1
      //   426: istore 4
      //   428: goto +141 -> 569
      //   431: iload 8
      //   433: ifle +6 -> 439
      //   436: goto -17 -> 419
      //   439: goto -403 -> 36
      //   442: goto -140 -> 302
      //   445: iconst_0
      //   446: istore_3
      //   447: goto -126 -> 321
      //   450: aload 10
      //   452: astore_1
      //   453: goto -22 -> 431
      //   456: bipush 79
      //   458: istore 5
      //   460: goto -199 -> 261
      //   463: iload 6
      //   465: newarray char
      //   467: astore 10
      //   469: iconst_0
      //   470: istore_3
      //   471: iconst_0
      //   472: istore 4
      //   474: goto -172 -> 302
      //   477: iload 6
      //   479: newarray char
      //   481: astore 9
      //   483: iconst_1
      //   484: istore_3
      //   485: goto -112 -> 373
      //   488: aload_1
      //   489: iload_3
      //   490: aload_1
      //   491: iload_3
      //   492: caload
      //   493: aload_0
      //   494: iconst_2
      //   495: iaload
      //   496: isub
      //   497: i2c
      //   498: castore
      //   499: iload_3
      //   500: iconst_1
      //   501: iadd
      //   502: istore_3
      //   503: iload_3
      //   504: iload 6
      //   506: if_icmpge +6 -> 512
      //   509: goto -392 -> 117
      //   512: goto -87 -> 425
      //   515: iload 5
      //   517: tableswitch	default:+23->540, 0:+-67->450, 1:+-172->345
      //   540: goto -90 -> 450
      //   543: iconst_1
      //   544: istore 5
      //   546: goto -31 -> 515
      //   549: aload 10
      //   551: iload 4
      //   553: aload 9
      //   555: iload 4
      //   557: caload
      //   558: iconst_1
      //   559: ishl
      //   560: iconst_1
      //   561: iadd
      //   562: iload_3
      //   563: isub
      //   564: i2c
      //   565: castore
      //   566: goto -165 -> 401
      //   569: iload 4
      //   571: tableswitch	default:+21->592, 0:+-83->488, 1:+-526->45
      //   592: goto -104 -> 488
      //   595: aload 9
      //   597: iload_3
      //   598: aload_1
      //   599: iload 6
      //   601: iload_3
      //   602: isub
      //   603: iconst_1
      //   604: isub
      //   605: caload
      //   606: castore
      //   607: iload_3
      //   608: iconst_1
      //   609: iadd
      //   610: istore_3
      //   611: goto -296 -> 315
      // Local variable table:
      //   start	length	slot	name	signature
      //   0	614	0	paramArrayOfInt	int[]
      //   0	614	1	paramArrayOfByte	byte[]
      //   0	614	2	paramBoolean	boolean
      //   9	602	3	i	int
      //   86	484	4	j	int
      //   202	343	5	k	int
      //   123	480	6	m	int
      //   219	144	7	n	int
      //   145	287	8	i1	int
      //   30	566	9	arrayOfChar1	char[]
      //   229	321	10	arrayOfChar2	char[]
      // Exception table:
      //   from	to	target	type
      //   95	104	42	java/lang/Exception
      //   129	139	42	java/lang/Exception
      //   83	88	416	java/lang/Exception
      //   139	153	416	java/lang/Exception
      //   153	167	416	java/lang/Exception
    }
    
    public void onPageFinished(WebView paramWebView, String paramString)
    {
      break label305;
      int i;
      for (;;)
      {
        vq.ˎ(paramWebView, ˎ(new int[] { 0, 4, 158, 0 }, new byte[] { 1, 0, 0, 1 }, true).intern());
        vq.ˎ(paramString, ˎ(new int[] { 4, 3, 0, 1 }, new byte[] { 1, 1, 0 }, true).intern());
        super.onPageFinished(paramWebView, paramString);
        paramWebView = TncActivity.ˋ(this.ˊ);
        vq.ˋ(paramWebView, ˎ(new int[] { 7, 8, 0, 5 }, new byte[] { 0, 0, 1, 1, 1, 0, 1, 1 }, true).intern());
        paramWebView.ˋ(false);
        TncActivity.ˊ(this.ˊ);
        i = ˋ + 77;
        ॱ = i % 128;
        if (i % 2 != 0) {
          break label308;
        }
        i = 80;
        break;
        return;
        i = ॱ + 73;
        ˋ = i % 128;
        if (i % 2 == 0) {}
      }
      for (;;)
      {
        switch (i)
        {
        case 80: 
        default: 
          return;
        }
        throw new NullPointerException();
        label305:
        break;
        label308:
        i = 55;
      }
    }
    
    /* Error */
    public boolean shouldOverrideUrlLoading(WebView paramWebView, android.webkit.WebResourceRequest paramWebResourceRequest)
    {
      // Byte code:
      //   0: goto +186 -> 186
      //   3: aload_1
      //   4: iconst_4
      //   5: newarray int
      //   7: dup
      //   8: iconst_0
      //   9: iconst_0
      //   10: iastore
      //   11: dup
      //   12: iconst_1
      //   13: iconst_4
      //   14: iastore
      //   15: dup
      //   16: iconst_2
      //   17: sipush 158
      //   20: iastore
      //   21: dup
      //   22: iconst_3
      //   23: iconst_0
      //   24: iastore
      //   25: iconst_4
      //   26: newarray byte
      //   28: dup
      //   29: iconst_0
      //   30: ldc 65
      //   32: bastore
      //   33: dup
      //   34: iconst_1
      //   35: ldc 66
      //   37: bastore
      //   38: dup
      //   39: iconst_2
      //   40: ldc 66
      //   42: bastore
      //   43: dup
      //   44: iconst_3
      //   45: ldc 65
      //   47: bastore
      //   48: iconst_1
      //   49: invokestatic 68	ro/btrl/boot/ui/activity/TncActivity$ˋ:ˎ	([I[BZ)Ljava/lang/String;
      //   52: invokevirtual 72	java/lang/String:intern	()Ljava/lang/String;
      //   55: invokestatic 77	o/vq:ˎ	(Ljava/lang/Object;Ljava/lang/String;)V
      //   58: aload_2
      //   59: iconst_4
      //   60: newarray int
      //   62: dup
      //   63: iconst_0
      //   64: bipush 15
      //   66: iastore
      //   67: dup
      //   68: iconst_1
      //   69: bipush 7
      //   71: iastore
      //   72: dup
      //   73: iconst_2
      //   74: bipush 63
      //   76: iastore
      //   77: dup
      //   78: iconst_3
      //   79: iconst_0
      //   80: iastore
      //   81: bipush 7
      //   83: newarray byte
      //   85: dup
      //   86: iconst_0
      //   87: ldc 65
      //   89: bastore
      //   90: dup
      //   91: iconst_1
      //   92: ldc 65
      //   94: bastore
      //   95: dup
      //   96: iconst_2
      //   97: ldc 66
      //   99: bastore
      //   100: dup
      //   101: iconst_3
      //   102: ldc 66
      //   104: bastore
      //   105: dup
      //   106: iconst_4
      //   107: ldc 66
      //   109: bastore
      //   110: dup
      //   111: iconst_5
      //   112: ldc 66
      //   114: bastore
      //   115: dup
      //   116: bipush 6
      //   118: ldc 65
      //   120: bastore
      //   121: iconst_0
      //   122: invokestatic 68	ro/btrl/boot/ui/activity/TncActivity$ˋ:ˎ	([I[BZ)Ljava/lang/String;
      //   125: invokevirtual 72	java/lang/String:intern	()Ljava/lang/String;
      //   128: invokestatic 77	o/vq:ˎ	(Ljava/lang/Object;Ljava/lang/String;)V
      //   131: aload_0
      //   132: getfield 44	ro/btrl/boot/ui/activity/TncActivity$ˋ:ˊ	Lro/btrl/boot/ui/activity/TncActivity;
      //   135: checkcast 98	android/content/Context
      //   138: invokestatic 103	o/Ic:ˏ	(Landroid/content/Context;)Lo/Ic;
      //   141: aload_2
      //   142: invokeinterface 109 1 0
      //   147: invokevirtual 112	o/Ic:ॱ	(Landroid/net/Uri;)Lo/j;
      //   150: invokevirtual 116	o/j:ˎ	()V
      //   153: goto +6 -> 159
      //   156: goto +66 -> 222
      //   159: getstatic 17	ro/btrl/boot/ui/activity/TncActivity$ˋ:ॱ	I
      //   162: bipush 29
      //   164: iadd
      //   165: istore_3
      //   166: iload_3
      //   167: sipush 128
      //   170: irem
      //   171: putstatic 19	ro/btrl/boot/ui/activity/TncActivity$ˋ:ˋ	I
      //   174: iload_3
      //   175: iconst_2
      //   176: irem
      //   177: ifne +6 -> 183
      //   180: goto -24 -> 156
      //   183: goto +39 -> 222
      //   186: goto +9 -> 195
      //   189: goto -186 -> 3
      //   192: astore_1
      //   193: aload_1
      //   194: athrow
      //   195: getstatic 17	ro/btrl/boot/ui/activity/TncActivity$ˋ:ॱ	I
      //   198: bipush 113
      //   200: iadd
      //   201: istore_3
      //   202: iload_3
      //   203: sipush 128
      //   206: irem
      //   207: putstatic 19	ro/btrl/boot/ui/activity/TncActivity$ˋ:ˋ	I
      //   210: iload_3
      //   211: iconst_2
      //   212: irem
      //   213: ifne +6 -> 219
      //   216: goto -27 -> 189
      //   219: goto -216 -> 3
      //   222: iconst_1
      //   223: ireturn
      // Local variable table:
      //   start	length	slot	name	signature
      //   0	224	0	this	ˋ
      //   0	224	1	paramWebView	WebView
      //   0	224	2	paramWebResourceRequest	android.webkit.WebResourceRequest
      //   165	48	3	i	int
      // Exception table:
      //   from	to	target	type
      //   195	202	192	java/lang/Exception
      //   202	210	192	java/lang/Exception
    }
    
    /* Error */
    public boolean shouldOverrideUrlLoading(WebView arg1, String arg2)
    {
      // Byte code:
      //   0: goto +158 -> 158
      //   3: iload_3
      //   4: tableswitch	default:+24->28, 0:+24->28, 1:+230->234
      //   28: iconst_4
      //   29: newarray int
      //   31: dup
      //   32: iconst_0
      //   33: iconst_0
      //   34: iastore
      //   35: dup
      //   36: iconst_1
      //   37: iconst_4
      //   38: iastore
      //   39: dup
      //   40: iconst_2
      //   41: sipush 158
      //   44: iastore
      //   45: dup
      //   46: iconst_3
      //   47: iconst_0
      //   48: iastore
      //   49: iconst_4
      //   50: newarray byte
      //   52: dup
      //   53: iconst_0
      //   54: ldc 65
      //   56: bastore
      //   57: dup
      //   58: iconst_1
      //   59: ldc 66
      //   61: bastore
      //   62: dup
      //   63: iconst_2
      //   64: ldc 66
      //   66: bastore
      //   67: dup
      //   68: iconst_3
      //   69: ldc 65
      //   71: bastore
      //   72: iconst_1
      //   73: invokestatic 68	ro/btrl/boot/ui/activity/TncActivity$ˋ:ˎ	([I[BZ)Ljava/lang/String;
      //   76: astore 5
      //   78: aload_1
      //   79: aload 5
      //   81: invokevirtual 72	java/lang/String:intern	()Ljava/lang/String;
      //   84: invokestatic 77	o/vq:ˎ	(Ljava/lang/Object;Ljava/lang/String;)V
      //   87: aload_2
      //   88: iconst_4
      //   89: newarray int
      //   91: dup
      //   92: iconst_0
      //   93: iconst_4
      //   94: iastore
      //   95: dup
      //   96: iconst_1
      //   97: iconst_3
      //   98: iastore
      //   99: dup
      //   100: iconst_2
      //   101: iconst_0
      //   102: iastore
      //   103: dup
      //   104: iconst_3
      //   105: iconst_1
      //   106: iastore
      //   107: iconst_3
      //   108: newarray byte
      //   110: dup
      //   111: iconst_0
      //   112: ldc 65
      //   114: bastore
      //   115: dup
      //   116: iconst_1
      //   117: ldc 65
      //   119: bastore
      //   120: dup
      //   121: iconst_2
      //   122: ldc 66
      //   124: bastore
      //   125: iconst_1
      //   126: invokestatic 68	ro/btrl/boot/ui/activity/TncActivity$ˋ:ˎ	([I[BZ)Ljava/lang/String;
      //   129: invokevirtual 72	java/lang/String:intern	()Ljava/lang/String;
      //   132: invokestatic 77	o/vq:ˎ	(Ljava/lang/Object;Ljava/lang/String;)V
      //   135: aload_0
      //   136: getfield 44	ro/btrl/boot/ui/activity/TncActivity$ˋ:ˊ	Lro/btrl/boot/ui/activity/TncActivity;
      //   139: checkcast 98	android/content/Context
      //   142: invokestatic 103	o/Ic:ˏ	(Landroid/content/Context;)Lo/Ic;
      //   145: aload_2
      //   146: invokevirtual 121	o/Ic:ᐝ	(Ljava/lang/String;)Lo/j;
      //   149: invokevirtual 116	o/j:ˎ	()V
      //   152: iconst_1
      //   153: istore 4
      //   155: goto +6 -> 161
      //   158: goto +35 -> 193
      //   161: getstatic 17	ro/btrl/boot/ui/activity/TncActivity$ˋ:ॱ	I
      //   164: bipush 123
      //   166: iadd
      //   167: istore_3
      //   168: iload_3
      //   169: sipush 128
      //   172: irem
      //   173: putstatic 19	ro/btrl/boot/ui/activity/TncActivity$ˋ:ˋ	I
      //   176: iload_3
      //   177: iconst_2
      //   178: irem
      //   179: ifne +6 -> 185
      //   182: goto +49 -> 231
      //   185: iload 4
      //   187: ireturn
      //   188: iconst_0
      //   189: istore_3
      //   190: goto -187 -> 3
      //   193: getstatic 17	ro/btrl/boot/ui/activity/TncActivity$ˋ:ॱ	I
      //   196: bipush 125
      //   198: iadd
      //   199: istore_3
      //   200: iload_3
      //   201: sipush 128
      //   204: irem
      //   205: putstatic 19	ro/btrl/boot/ui/activity/TncActivity$ˋ:ˋ	I
      //   208: iload_3
      //   209: iconst_2
      //   210: irem
      //   211: ifne +6 -> 217
      //   214: goto +9 -> 223
      //   217: goto -29 -> 188
      //   220: astore_1
      //   221: aload_1
      //   222: athrow
      //   223: iconst_1
      //   224: istore_3
      //   225: goto -222 -> 3
      //   228: astore_1
      //   229: aload_1
      //   230: athrow
      //   231: iload 4
      //   233: ireturn
      //   234: aload_1
      //   235: iconst_4
      //   236: newarray int
      //   238: dup
      //   239: iconst_0
      //   240: iconst_0
      //   241: iastore
      //   242: dup
      //   243: iconst_1
      //   244: iconst_4
      //   245: iastore
      //   246: dup
      //   247: iconst_2
      //   248: sipush 158
      //   251: iastore
      //   252: dup
      //   253: iconst_3
      //   254: iconst_0
      //   255: iastore
      //   256: iconst_4
      //   257: newarray byte
      //   259: dup
      //   260: iconst_0
      //   261: ldc 65
      //   263: bastore
      //   264: dup
      //   265: iconst_1
      //   266: ldc 66
      //   268: bastore
      //   269: dup
      //   270: iconst_2
      //   271: ldc 66
      //   273: bastore
      //   274: dup
      //   275: iconst_3
      //   276: ldc 65
      //   278: bastore
      //   279: iconst_1
      //   280: invokestatic 68	ro/btrl/boot/ui/activity/TncActivity$ˋ:ˎ	([I[BZ)Ljava/lang/String;
      //   283: invokevirtual 72	java/lang/String:intern	()Ljava/lang/String;
      //   286: invokestatic 77	o/vq:ˎ	(Ljava/lang/Object;Ljava/lang/String;)V
      //   289: aload_2
      //   290: iconst_4
      //   291: newarray int
      //   293: dup
      //   294: iconst_0
      //   295: iconst_4
      //   296: iastore
      //   297: dup
      //   298: iconst_1
      //   299: iconst_3
      //   300: iastore
      //   301: dup
      //   302: iconst_2
      //   303: iconst_0
      //   304: iastore
      //   305: dup
      //   306: iconst_3
      //   307: iconst_1
      //   308: iastore
      //   309: iconst_3
      //   310: newarray byte
      //   312: dup
      //   313: iconst_0
      //   314: ldc 65
      //   316: bastore
      //   317: dup
      //   318: iconst_1
      //   319: ldc 65
      //   321: bastore
      //   322: dup
      //   323: iconst_2
      //   324: ldc 66
      //   326: bastore
      //   327: iconst_1
      //   328: invokestatic 68	ro/btrl/boot/ui/activity/TncActivity$ˋ:ˎ	([I[BZ)Ljava/lang/String;
      //   331: invokevirtual 72	java/lang/String:intern	()Ljava/lang/String;
      //   334: invokestatic 77	o/vq:ˎ	(Ljava/lang/Object;Ljava/lang/String;)V
      //   337: aload_0
      //   338: getfield 44	ro/btrl/boot/ui/activity/TncActivity$ˋ:ˊ	Lro/btrl/boot/ui/activity/TncActivity;
      //   341: checkcast 98	android/content/Context
      //   344: invokestatic 103	o/Ic:ˏ	(Landroid/content/Context;)Lo/Ic;
      //   347: aload_2
      //   348: invokevirtual 121	o/Ic:ᐝ	(Ljava/lang/String;)Lo/j;
      //   351: invokevirtual 116	o/j:ˎ	()V
      //   354: iconst_0
      //   355: istore 4
      //   357: goto -196 -> 161
      // Exception table:
      //   from	to	target	type
      //   28	78	220	java/lang/Exception
      //   78	152	220	java/lang/Exception
      //   193	200	220	java/lang/Exception
      //   200	208	220	java/lang/Exception
    }
  }
}
