package com.mobile.ui.interstitial.fragment;

import com.mobile.ui.common.fragment.BasePreHomeScreenFragment;
import kkkkkk.uyuuyu;
import kkkkkk.yuuuyu;

public class KycInterstitialFragment
  extends BasePreHomeScreenFragment<yuuuyu, uyuuyu>
{
  public static int b0411041104110411Б0411Б0411 = 0;
  public static int bБ041104110411Б0411Б0411 = 1;
  public static int bБ0411Б0411Б0411Б0411 = 66;
  public static int bББ04110411Б0411Б0411 = 2;
  
  public KycInterstitialFragment() {}
  
  public static int b04110411Б0411Б0411Б0411()
  {
    return 1;
  }
  
  public static int b0411Б04110411Б0411Б0411()
  {
    return 94;
  }
  
  public static int bББББ04110411Б0411()
  {
    return 2;
  }
  
  /* Error */
  public static KycInterstitialFragment newInstance()
  {
    // Byte code:
    //   0: getstatic 29	com/mobile/ui/interstitial/fragment/KycInterstitialFragment:bБ0411Б0411Б0411Б0411	I
    //   3: istore_0
    //   4: invokestatic 31	com/mobile/ui/interstitial/fragment/KycInterstitialFragment:b04110411Б0411Б0411Б0411	()I
    //   7: istore_1
    //   8: getstatic 33	com/mobile/ui/interstitial/fragment/KycInterstitialFragment:bББ04110411Б0411Б0411	I
    //   11: istore_2
    //   12: iload_0
    //   13: iload_1
    //   14: iload_0
    //   15: iadd
    //   16: imul
    //   17: iload_2
    //   18: irem
    //   19: tableswitch	default:+17->36, 0:+74->93
    //   36: getstatic 29	com/mobile/ui/interstitial/fragment/KycInterstitialFragment:bБ0411Б0411Б0411Б0411	I
    //   39: istore_0
    //   40: iload_0
    //   41: getstatic 35	com/mobile/ui/interstitial/fragment/KycInterstitialFragment:bБ041104110411Б0411Б0411	I
    //   44: iload_0
    //   45: iadd
    //   46: imul
    //   47: getstatic 33	com/mobile/ui/interstitial/fragment/KycInterstitialFragment:bББ04110411Б0411Б0411	I
    //   50: irem
    //   51: tableswitch	default:+17->68, 0:+29->80
    //   68: invokestatic 37	com/mobile/ui/interstitial/fragment/KycInterstitialFragment:b0411Б04110411Б0411Б0411	()I
    //   71: putstatic 29	com/mobile/ui/interstitial/fragment/KycInterstitialFragment:bБ0411Б0411Б0411Б0411	I
    //   74: invokestatic 37	com/mobile/ui/interstitial/fragment/KycInterstitialFragment:b0411Б04110411Б0411Б0411	()I
    //   77: putstatic 35	com/mobile/ui/interstitial/fragment/KycInterstitialFragment:bБ041104110411Б0411Б0411	I
    //   80: bipush 89
    //   82: putstatic 29	com/mobile/ui/interstitial/fragment/KycInterstitialFragment:bБ0411Б0411Б0411Б0411	I
    //   85: invokestatic 37	com/mobile/ui/interstitial/fragment/KycInterstitialFragment:b0411Б04110411Б0411Б0411	()I
    //   88: istore_0
    //   89: iload_0
    //   90: putstatic 33	com/mobile/ui/interstitial/fragment/KycInterstitialFragment:bББ04110411Б0411Б0411	I
    //   93: new 2	com/mobile/ui/interstitial/fragment/KycInterstitialFragment
    //   96: dup
    //   97: invokespecial 38	com/mobile/ui/interstitial/fragment/KycInterstitialFragment:<init>	()V
    //   100: astore_3
    //   101: aload_3
    //   102: areturn
    //   103: astore_3
    //   104: aload_3
    //   105: athrow
    //   106: astore_3
    //   107: aload_3
    //   108: athrow
    // Local variable table:
    //   start	length	slot	name	signature
    //   3	87	0	i	int
    //   7	9	1	j	int
    //   11	8	2	k	int
    //   100	2	3	localKycInterstitialFragment	KycInterstitialFragment
    //   103	2	3	localException1	Exception
    //   106	2	3	localException2	Exception
    // Exception table:
    //   from	to	target	type
    //   0	12	103	java/lang/Exception
    //   89	93	103	java/lang/Exception
    //   93	101	103	java/lang/Exception
    //   80	89	106	java/lang/Exception
  }
  
  public void trackScreenView()
  {
    switch (0)
    {
    case 1: 
    default: 
      for (;;)
      {
        switch (0)
        {
        case 1: 
        default: 
          for (;;)
          {
            switch (0)
            {
            }
          }
        }
        if ((bБ0411Б0411Б0411Б0411 + bБ041104110411Б0411Б0411) * bБ0411Б0411Б0411Б0411 % bББББ04110411Б0411() != b0411041104110411Б0411Б0411)
        {
          bБ0411Б0411Б0411Б0411 = 87;
          b0411041104110411Б0411Б0411 = 15;
        }
        switch (0)
        {
        }
      }
    }
  }
}
