package com.db.pwcc.dbmobile.model.sepa;

import android.support.annotation.NonNull;
import java.lang.reflect.InvocationTargetException;
import java.lang.reflect.Method;
import java.text.Collator;
import java.util.Objects;
import uuuuuu.popopp;
import uuuuuu.ppphhp;
import xxxxxx.uxxxxx;

public class StandingOrder
  implements popopp, Comparable<StandingOrder>
{
  public static int b0061006100610061aa00610061 = 32;
  public static int b00610061aa0061a00610061 = 0;
  public static int b0061aaa0061a00610061 = 2;
  public static int baaaa0061a00610061 = 1;
  private String amount;
  private String beneficiary;
  private String executionOn;
  private String firstExecutionDate;
  private String frequency;
  private String id;
  private String lastChangeDate;
  private boolean modifiable;
  private String nextExecutionDate;
  private String purpose;
  private String reference;
  private String sourceAccount;
  private String targetAccount;
  private String targetBic;
  private String validUntil;
  
  public StandingOrder() {}
  
  public static int b0061a0061a0061a00610061()
  {
    return 0;
  }
  
  public static int ba00610061a0061a00610061()
  {
    return 1;
  }
  
  public static int ba0061aa0061a00610061()
  {
    return 54;
  }
  
  public static int baa0061a0061a00610061()
  {
    return 2;
  }
  
  public int compareTo(@NonNull StandingOrder paramStandingOrder)
  {
    int i = -1;
    label11:
    label12:
    int j;
    if (paramStandingOrder.equals(this))
    {
      i = 0;
      while (j < 65) {
        return i;
      }
      return Collator.getInstance().compare(this.beneficiary, paramStandingOrder);
    }
    do
    {
      if (this.beneficiary == null)
      {
        i = 1;
        if ((b0061006100610061aa00610061 + baaaa0061a00610061) * b0061006100610061aa00610061 % b0061aaa0061a00610061 == b00610061aa0061a00610061) {
          break label12;
        }
        b0061006100610061aa00610061 = ba0061aa0061a00610061();
        b00610061aa0061a00610061 = ba0061aa0061a00610061();
        return 1;
      }
      int k = this.beneficiary.toLowerCase().charAt(0);
      j = paramStandingOrder.toLowerCase().charAt(0);
      if (k >= 65) {
        break label11;
      }
      i = Integer.MAX_VALUE;
      j = b0061006100610061aa00610061;
      switch (j * (baaaa0061a00610061 + j) % b0061aaa0061a00610061)
      {
      }
      b0061006100610061aa00610061 = 62;
      baaaa0061a00610061 = ba0061aa0061a00610061();
      return Integer.MAX_VALUE;
      paramStandingOrder = paramStandingOrder.getBeneficiary();
      if ((this.beneficiary == null) && (paramStandingOrder == null)) {
        break;
      }
    } while ((this.beneficiary == null) || (paramStandingOrder != null));
    return -1;
  }
  
  public boolean equals(Object paramObject)
  {
    if (this == paramObject) {
      return true;
    }
    if ((paramObject != null) && (getClass() == paramObject.getClass()))
    {
      paramObject = (StandingOrder)paramObject;
      if (this.modifiable == paramObject.modifiable)
      {
        if (this.id != null)
        {
          if (!this.id.equals(paramObject.id)) {
            break label519;
          }
          label59:
          if (this.amount != null)
          {
            if (!this.amount.equals(paramObject.amount)) {
              break label519;
            }
            label80:
            if (this.beneficiary == null) {
              break label453;
            }
            if (!this.beneficiary.equals(paramObject.beneficiary)) {
              break label519;
            }
            label101:
            if (this.purpose == null) {
              break label462;
            }
            if (!this.purpose.equals(paramObject.purpose)) {
              break label519;
            }
            label122:
            if (this.nextExecutionDate == null) {
              break label435;
            }
            if (!this.nextExecutionDate.equals(paramObject.nextExecutionDate)) {
              break label519;
            }
            label143:
            if (this.sourceAccount == null) {
              break label426;
            }
            if (!this.sourceAccount.equals(paramObject.sourceAccount)) {
              break label519;
            }
            label164:
            if (this.targetAccount != null)
            {
              if (!this.targetAccount.equals(paramObject.targetAccount)) {
                break label519;
              }
              label185:
              if (this.targetBic == null) {
                break label339;
              }
              if (!this.targetBic.equals(paramObject.targetBic)) {
                break label519;
              }
              label206:
              if (this.reference == null) {
                break label348;
              }
              if (!this.reference.equals(paramObject.reference)) {
                break label519;
              }
              label227:
              if (this.firstExecutionDate == null) {
                break label357;
              }
              if (!this.firstExecutionDate.equals(paramObject.firstExecutionDate)) {
                break label519;
              }
              label248:
              if (this.lastChangeDate == null) {
                break label510;
              }
              if (!this.lastChangeDate.equals(paramObject.lastChangeDate)) {
                break label519;
              }
            }
          }
        }
        label290:
        label339:
        label348:
        label357:
        label426:
        label435:
        label453:
        label462:
        label501:
        label510:
        while (paramObject.lastChangeDate == null)
        {
          if (this.validUntil != null)
          {
            if (!this.validUntil.equals(paramObject.validUntil)) {
              break label519;
            }
            if (this.executionOn == null) {
              break label501;
            }
            if (!this.executionOn.equals(paramObject.executionOn)) {
              break label519;
            }
          }
          while (paramObject.executionOn == null)
          {
            if (this.frequency != null)
            {
              return this.frequency.equals(paramObject.frequency);
              if (paramObject.targetAccount == null) {
                break label185;
              }
              return false;
              if (paramObject.targetBic == null) {
                break label206;
              }
              return false;
              if (paramObject.reference == null) {
                break label227;
              }
              return false;
              if (paramObject.firstExecutionDate == null) {
                break label248;
              }
              return false;
              if (paramObject.validUntil == null) {
                break label290;
              }
              return false;
            }
            if (paramObject.frequency == null) {
              break;
            }
            return false;
            if (paramObject.amount == null) {
              break label80;
            }
            if ((b0061006100610061aa00610061 + baaaa0061a00610061) * b0061006100610061aa00610061 % b0061aaa0061a00610061 != b00610061aa0061a00610061)
            {
              b0061006100610061aa00610061 = ba0061aa0061a00610061();
              b00610061aa0061a00610061 = ba0061aa0061a00610061();
            }
            return false;
            if (paramObject.sourceAccount == null) {
              break label164;
            }
            return false;
            if (paramObject.nextExecutionDate == null) {
              break label143;
            }
            return false;
            if (paramObject.id == null) {
              break label59;
            }
            return false;
            if (paramObject.beneficiary == null) {
              break label101;
            }
            return false;
            if (paramObject.purpose == null) {
              break label122;
            }
            if ((b0061006100610061aa00610061 + baaaa0061a00610061) * b0061006100610061aa00610061 % b0061aaa0061a00610061 == b00610061aa0061a00610061) {
              break label519;
            }
            b0061006100610061aa00610061 = 4;
            b00610061aa0061a00610061 = 90;
            return false;
          }
          return false;
        }
        return false;
      }
    }
    label519:
    return false;
  }
  
  public String getAmount()
  {
    if ((b0061006100610061aa00610061 + baaaa0061a00610061) * b0061006100610061aa00610061 % b0061aaa0061a00610061 != b00610061aa0061a00610061)
    {
      b0061006100610061aa00610061 = ba0061aa0061a00610061();
      b00610061aa0061a00610061 = ba0061aa0061a00610061();
    }
    String str = this.amount;
    if ((b0061006100610061aa00610061 + baaaa0061a00610061) * b0061006100610061aa00610061 % b0061aaa0061a00610061 != b00610061aa0061a00610061)
    {
      b0061006100610061aa00610061 = 78;
      b00610061aa0061a00610061 = 37;
    }
    return str;
  }
  
  public String getBeneficiary()
  {
    String str = this.beneficiary;
    int i = b0061006100610061aa00610061;
    switch (i * (baaaa0061a00610061 + i) % baa0061a0061a00610061())
    {
    default: 
      b0061006100610061aa00610061 = ba0061aa0061a00610061();
      b00610061aa0061a00610061 = ba0061aa0061a00610061();
      i = b0061006100610061aa00610061;
      switch (i * (baaaa0061a00610061 + i) % b0061aaa0061a00610061)
      {
      default: 
        b0061006100610061aa00610061 = 43;
        b00610061aa0061a00610061 = ba0061aa0061a00610061();
      }
      break;
    }
    return str;
  }
  
  public String getExecutionOn()
  {
    String str = this.executionOn;
    if ((b0061006100610061aa00610061 + baaaa0061a00610061) * b0061006100610061aa00610061 % b0061aaa0061a00610061 != b0061a0061a0061a00610061())
    {
      b0061006100610061aa00610061 = 72;
      b00610061aa0061a00610061 = 97;
      if ((b0061006100610061aa00610061 + baaaa0061a00610061) * b0061006100610061aa00610061 % b0061aaa0061a00610061 != b0061a0061a0061a00610061())
      {
        b0061006100610061aa00610061 = 50;
        b00610061aa0061a00610061 = ba0061aa0061a00610061();
      }
    }
    return str;
  }
  
  public String getFirstExecutionDate()
  {
    int i = b0061006100610061aa00610061;
    int j = baaaa0061a00610061;
    if ((b0061006100610061aa00610061 + baaaa0061a00610061) * b0061006100610061aa00610061 % b0061aaa0061a00610061 != b00610061aa0061a00610061)
    {
      b0061006100610061aa00610061 = 66;
      b00610061aa0061a00610061 = ba0061aa0061a00610061();
    }
    switch (i * (j + i) % b0061aaa0061a00610061)
    {
    default: 
      b0061006100610061aa00610061 = ba0061aa0061a00610061();
      b00610061aa0061a00610061 = 11;
    }
    return this.firstExecutionDate;
  }
  
  public String getFrequency()
  {
    String str = this.frequency;
    int i = b0061006100610061aa00610061;
    switch (i * (baaaa0061a00610061 + i) % b0061aaa0061a00610061)
    {
    default: 
      i = b0061006100610061aa00610061;
      switch (i * (baaaa0061a00610061 + i) % b0061aaa0061a00610061)
      {
      default: 
        b0061006100610061aa00610061 = ba0061aa0061a00610061();
        b00610061aa0061a00610061 = ba0061aa0061a00610061();
      }
      b0061006100610061aa00610061 = ba0061aa0061a00610061();
      b00610061aa0061a00610061 = ba0061aa0061a00610061();
    }
    return str;
  }
  
  public String getId()
  {
    int i = b0061006100610061aa00610061;
    int j = b0061006100610061aa00610061;
    switch (j * (baaaa0061a00610061 + j) % b0061aaa0061a00610061)
    {
    default: 
      b0061006100610061aa00610061 = 24;
      b00610061aa0061a00610061 = ba0061aa0061a00610061();
    }
    if ((i + baaaa0061a00610061) * b0061006100610061aa00610061 % baa0061a0061a00610061() != b0061a0061a0061a00610061())
    {
      b0061006100610061aa00610061 = 7;
      b00610061aa0061a00610061 = 48;
    }
    return this.id;
  }
  
  public String getLastChangeDate()
  {
    if ((b0061006100610061aa00610061 + baaaa0061a00610061) * b0061006100610061aa00610061 % b0061aaa0061a00610061 != b00610061aa0061a00610061)
    {
      b0061006100610061aa00610061 = 85;
      b00610061aa0061a00610061 = ba0061aa0061a00610061();
    }
    String str = this.lastChangeDate;
    if ((b0061006100610061aa00610061 + baaaa0061a00610061) * b0061006100610061aa00610061 % b0061aaa0061a00610061 != b00610061aa0061a00610061)
    {
      b0061006100610061aa00610061 = 55;
      b00610061aa0061a00610061 = 34;
    }
    return str;
  }
  
  public String getNextExecutionDate()
  {
    if ((b0061006100610061aa00610061 + baaaa0061a00610061) * b0061006100610061aa00610061 % b0061aaa0061a00610061 != b00610061aa0061a00610061)
    {
      b0061006100610061aa00610061 = 85;
      b00610061aa0061a00610061 = 67;
      if ((b0061006100610061aa00610061 + baaaa0061a00610061) * b0061006100610061aa00610061 % b0061aaa0061a00610061 != b00610061aa0061a00610061)
      {
        b0061006100610061aa00610061 = 30;
        b00610061aa0061a00610061 = 53;
      }
    }
    return this.nextExecutionDate;
  }
  
  public String getPurpose()
  {
    if ((b0061006100610061aa00610061 + baaaa0061a00610061) * b0061006100610061aa00610061 % b0061aaa0061a00610061 != b0061a0061a0061a00610061())
    {
      b0061006100610061aa00610061 = ba0061aa0061a00610061();
      b00610061aa0061a00610061 = 72;
    }
    String str = this.purpose;
    if ((b0061006100610061aa00610061 + baaaa0061a00610061) * b0061006100610061aa00610061 % baa0061a0061a00610061() != b00610061aa0061a00610061)
    {
      b0061006100610061aa00610061 = 87;
      b00610061aa0061a00610061 = 0;
    }
    return str;
  }
  
  public String getPurposeValidated()
  {
    Object localObject;
    if ((this.purpose == null) || (this.purpose.isEmpty()))
    {
      if ((b0061006100610061aa00610061 + baaaa0061a00610061) * b0061006100610061aa00610061 % b0061aaa0061a00610061 != b0061a0061a0061a00610061())
      {
        b0061006100610061aa00610061 = 35;
        b00610061aa0061a00610061 = ba0061aa0061a00610061();
      }
      localObject = ppphhp.class.getMethod(uxxxxx.bb00620062bb0062b0062b0062("DZ[\\]\027\030 !\033\034$%f !)*$%-.o", 'ï', '\001'), new Class[] { String.class, Character.TYPE, Character.TYPE });
    }
    do
    {
      try
      {
        localObject = ((Method)localObject).invoke(null, new Object[] { "\036", Character.valueOf('ï'), Character.valueOf('\002') });
        localObject = (String)localObject;
        return localObject;
      }
      catch (InvocationTargetException localInvocationTargetException)
      {
        String str;
        throw localInvocationTargetException.getCause();
      }
      str = this.purpose;
      localObject = str;
    } while ((b0061006100610061aa00610061 + ba00610061a0061a00610061()) * b0061006100610061aa00610061 % b0061aaa0061a00610061 == b00610061aa0061a00610061);
    b0061006100610061aa00610061 = 68;
    b00610061aa0061a00610061 = 20;
    return str;
  }
  
  public String getReference()
  {
    String str = this.reference;
    int i = b0061006100610061aa00610061;
    switch (i * (baaaa0061a00610061 + i) % b0061aaa0061a00610061)
    {
    default: 
      b0061006100610061aa00610061 = ba0061aa0061a00610061();
      b00610061aa0061a00610061 = 99;
      i = b0061006100610061aa00610061;
      switch (i * (baaaa0061a00610061 + i) % b0061aaa0061a00610061)
      {
      default: 
        b0061006100610061aa00610061 = ba0061aa0061a00610061();
        b00610061aa0061a00610061 = ba0061aa0061a00610061();
      }
      break;
    }
    return str;
  }
  
  public String getSourceAccount()
  {
    int i = b0061006100610061aa00610061;
    int j = baaaa0061a00610061;
    int k = b0061006100610061aa00610061;
    int m = b0061006100610061aa00610061;
    switch (m * (baaaa0061a00610061 + m) % b0061aaa0061a00610061)
    {
    default: 
      b0061006100610061aa00610061 = ba0061aa0061a00610061();
      b00610061aa0061a00610061 = 19;
    }
    if ((i + j) * k % baa0061a0061a00610061() != b00610061aa0061a00610061)
    {
      b0061006100610061aa00610061 = 21;
      b00610061aa0061a00610061 = 96;
    }
    return this.sourceAccount;
  }
  
  public String getTargetAccount()
  {
    int i = b0061006100610061aa00610061;
    int j = ba00610061a0061a00610061();
    if ((b0061006100610061aa00610061 + baaaa0061a00610061) * b0061006100610061aa00610061 % b0061aaa0061a00610061 != b00610061aa0061a00610061)
    {
      b0061006100610061aa00610061 = 49;
      b00610061aa0061a00610061 = ba0061aa0061a00610061();
    }
    if ((i + j) * b0061006100610061aa00610061 % b0061aaa0061a00610061 != b00610061aa0061a00610061)
    {
      b0061006100610061aa00610061 = ba0061aa0061a00610061();
      b00610061aa0061a00610061 = 54;
    }
    return this.targetAccount;
  }
  
  public String getTargetBic()
  {
    if ((b0061006100610061aa00610061 + baaaa0061a00610061) * b0061006100610061aa00610061 % b0061aaa0061a00610061 != b00610061aa0061a00610061)
    {
      if ((b0061006100610061aa00610061 + ba00610061a0061a00610061()) * b0061006100610061aa00610061 % b0061aaa0061a00610061 != b00610061aa0061a00610061)
      {
        b0061006100610061aa00610061 = 54;
        b00610061aa0061a00610061 = ba0061aa0061a00610061();
      }
      b0061006100610061aa00610061 = 87;
      b00610061aa0061a00610061 = ba0061aa0061a00610061();
    }
    return this.targetBic;
  }
  
  public String getValidUntil()
  {
    int i = b0061006100610061aa00610061;
    switch (i * (baaaa0061a00610061 + i) % baa0061a0061a00610061())
    {
    default: 
      if ((b0061006100610061aa00610061 + baaaa0061a00610061) * b0061006100610061aa00610061 % b0061aaa0061a00610061 != b00610061aa0061a00610061)
      {
        b0061006100610061aa00610061 = 5;
        b00610061aa0061a00610061 = 35;
      }
      b0061006100610061aa00610061 = 57;
      b00610061aa0061a00610061 = 98;
    }
    return this.validUntil;
  }
  
  public int hashCode()
  {
    String str1 = this.id;
    String str2 = this.amount;
    if ((b0061006100610061aa00610061 + baaaa0061a00610061) * b0061006100610061aa00610061 % b0061aaa0061a00610061 != b0061a0061a0061a00610061())
    {
      b0061006100610061aa00610061 = ba0061aa0061a00610061();
      b00610061aa0061a00610061 = 33;
    }
    String str3 = this.beneficiary;
    String str4 = this.purpose;
    String str5 = this.nextExecutionDate;
    boolean bool = this.modifiable;
    String str6 = this.sourceAccount;
    String str7 = this.targetAccount;
    String str8 = this.targetBic;
    String str9 = this.reference;
    String str10 = this.firstExecutionDate;
    String str11 = this.lastChangeDate;
    String str12 = this.validUntil;
    String str13 = this.executionOn;
    int i = b0061006100610061aa00610061;
    switch (i * (baaaa0061a00610061 + i) % baa0061a0061a00610061())
    {
    default: 
      b0061006100610061aa00610061 = 66;
      b00610061aa0061a00610061 = ba0061aa0061a00610061();
    }
    return Objects.hash(new Object[] { str1, str2, str3, str4, str5, Boolean.valueOf(bool), str6, str7, str8, str9, str10, str11, str12, str13, this.frequency });
  }
  
  public boolean isModifiable()
  {
    int i = b0061006100610061aa00610061;
    int j = ba00610061a0061a00610061();
    int k = b0061006100610061aa00610061;
    if ((b0061006100610061aa00610061 + baaaa0061a00610061) * b0061006100610061aa00610061 % baa0061a0061a00610061() != b00610061aa0061a00610061)
    {
      b0061006100610061aa00610061 = ba0061aa0061a00610061();
      b00610061aa0061a00610061 = ba0061aa0061a00610061();
    }
    if ((i + j) * k % baa0061a0061a00610061() != b0061a0061a0061a00610061())
    {
      b0061006100610061aa00610061 = ba0061aa0061a00610061();
      b00610061aa0061a00610061 = 35;
    }
    return this.modifiable;
  }
  
  public void setAmount(String paramString)
  {
    this.amount = paramString;
    int i = b0061006100610061aa00610061;
    switch (i * (baaaa0061a00610061 + i) % baa0061a0061a00610061())
    {
    default: 
      b0061006100610061aa00610061 = ba0061aa0061a00610061();
      b00610061aa0061a00610061 = ba0061aa0061a00610061();
      if ((b0061006100610061aa00610061 + baaaa0061a00610061) * b0061006100610061aa00610061 % b0061aaa0061a00610061 != b00610061aa0061a00610061)
      {
        b0061006100610061aa00610061 = ba0061aa0061a00610061();
        b00610061aa0061a00610061 = 77;
      }
      break;
    }
  }
  
  public void setBeneficiary(String paramString)
  {
    int i = b0061006100610061aa00610061;
    int j = baaaa0061a00610061;
    if ((b0061006100610061aa00610061 + baaaa0061a00610061) * b0061006100610061aa00610061 % b0061aaa0061a00610061 != b00610061aa0061a00610061)
    {
      b0061006100610061aa00610061 = 19;
      b00610061aa0061a00610061 = ba0061aa0061a00610061();
    }
    switch (i * (j + i) % b0061aaa0061a00610061)
    {
    default: 
      b0061006100610061aa00610061 = ba0061aa0061a00610061();
      b00610061aa0061a00610061 = ba0061aa0061a00610061();
    }
    this.beneficiary = paramString;
  }
  
  public void setExecutionOn(String paramString)
  {
    int i = b0061006100610061aa00610061;
    int j = baaaa0061a00610061;
    int k = b0061aaa0061a00610061;
    if ((b0061006100610061aa00610061 + baaaa0061a00610061) * b0061006100610061aa00610061 % b0061aaa0061a00610061 != b00610061aa0061a00610061)
    {
      b0061006100610061aa00610061 = ba0061aa0061a00610061();
      b00610061aa0061a00610061 = ba0061aa0061a00610061();
    }
    switch (i * (j + i) % k)
    {
    default: 
      b0061006100610061aa00610061 = 57;
      b00610061aa0061a00610061 = 51;
    }
    this.executionOn = paramString;
  }
  
  public void setFirstExecutionDate(String paramString)
  {
    if ((ba0061aa0061a00610061() + baaaa0061a00610061) * ba0061aa0061a00610061() % b0061aaa0061a00610061 != b00610061aa0061a00610061)
    {
      b0061006100610061aa00610061 = ba0061aa0061a00610061();
      b00610061aa0061a00610061 = ba0061aa0061a00610061();
    }
    int i = b0061006100610061aa00610061;
    switch (i * (baaaa0061a00610061 + i) % b0061aaa0061a00610061)
    {
    default: 
      b0061006100610061aa00610061 = 37;
      b00610061aa0061a00610061 = 35;
    }
    this.firstExecutionDate = paramString;
  }
  
  public void setFrequency(String paramString)
  {
    if ((b0061006100610061aa00610061 + baaaa0061a00610061) * b0061006100610061aa00610061 % b0061aaa0061a00610061 != b00610061aa0061a00610061)
    {
      b0061006100610061aa00610061 = 96;
      b00610061aa0061a00610061 = 22;
    }
    if ((b0061006100610061aa00610061 + baaaa0061a00610061) * b0061006100610061aa00610061 % b0061aaa0061a00610061 != b00610061aa0061a00610061)
    {
      b0061006100610061aa00610061 = ba0061aa0061a00610061();
      b00610061aa0061a00610061 = ba0061aa0061a00610061();
    }
    this.frequency = paramString;
  }
  
  public void setId(String paramString)
  {
    int i = b0061006100610061aa00610061;
    int j = baaaa0061a00610061;
    if ((b0061006100610061aa00610061 + baaaa0061a00610061) * b0061006100610061aa00610061 % b0061aaa0061a00610061 != b00610061aa0061a00610061)
    {
      b0061006100610061aa00610061 = 77;
      b00610061aa0061a00610061 = 43;
    }
    if ((i + j) * b0061006100610061aa00610061 % b0061aaa0061a00610061 != b00610061aa0061a00610061)
    {
      b0061006100610061aa00610061 = 87;
      b00610061aa0061a00610061 = ba0061aa0061a00610061();
    }
    this.id = paramString;
  }
  
  public void setLastChangeDate(String paramString)
  {
    if ((b0061006100610061aa00610061 + baaaa0061a00610061) * b0061006100610061aa00610061 % b0061aaa0061a00610061 != b00610061aa0061a00610061)
    {
      b0061006100610061aa00610061 = ba0061aa0061a00610061();
      b00610061aa0061a00610061 = 97;
    }
    int i = ba0061aa0061a00610061();
    switch (i * (ba00610061a0061a00610061() + i) % b0061aaa0061a00610061)
    {
    default: 
      b0061006100610061aa00610061 = 80;
      b00610061aa0061a00610061 = 73;
    }
    this.lastChangeDate = paramString;
  }
  
  public void setModifiable(boolean paramBoolean)
  {
    if ((b0061006100610061aa00610061 + baaaa0061a00610061) * b0061006100610061aa00610061 % b0061aaa0061a00610061 != b00610061aa0061a00610061)
    {
      b0061006100610061aa00610061 = 34;
      b00610061aa0061a00610061 = 79;
      if ((b0061006100610061aa00610061 + ba00610061a0061a00610061()) * b0061006100610061aa00610061 % b0061aaa0061a00610061 != b0061a0061a0061a00610061())
      {
        b0061006100610061aa00610061 = ba0061aa0061a00610061();
        b00610061aa0061a00610061 = 84;
      }
    }
    this.modifiable = paramBoolean;
  }
  
  public void setNextExecutionDate(String paramString)
  {
    if ((b0061006100610061aa00610061 + baaaa0061a00610061) * b0061006100610061aa00610061 % baa0061a0061a00610061() != b00610061aa0061a00610061)
    {
      b0061006100610061aa00610061 = 62;
      b00610061aa0061a00610061 = ba0061aa0061a00610061();
      if ((b0061006100610061aa00610061 + baaaa0061a00610061) * b0061006100610061aa00610061 % b0061aaa0061a00610061 != b0061a0061a0061a00610061())
      {
        b0061006100610061aa00610061 = ba0061aa0061a00610061();
        b00610061aa0061a00610061 = 53;
      }
    }
    this.nextExecutionDate = paramString;
  }
  
  public void setPurpose(String paramString)
  {
    int i = b0061006100610061aa00610061;
    switch (i * (baaaa0061a00610061 + i) % b0061aaa0061a00610061)
    {
    default: 
      b0061006100610061aa00610061 = 98;
      b00610061aa0061a00610061 = ba0061aa0061a00610061();
    }
    this.purpose = paramString;
    if ((b0061006100610061aa00610061 + baaaa0061a00610061) * b0061006100610061aa00610061 % b0061aaa0061a00610061 != b00610061aa0061a00610061)
    {
      b0061006100610061aa00610061 = ba0061aa0061a00610061();
      b00610061aa0061a00610061 = 71;
    }
  }
  
  public void setReference(String paramString)
  {
    int i = ba0061aa0061a00610061();
    int j = baaaa0061a00610061;
    if ((b0061006100610061aa00610061 + baaaa0061a00610061) * b0061006100610061aa00610061 % b0061aaa0061a00610061 != b00610061aa0061a00610061)
    {
      b0061006100610061aa00610061 = ba0061aa0061a00610061();
      b00610061aa0061a00610061 = ba0061aa0061a00610061();
    }
    if ((i + j) * ba0061aa0061a00610061() % b0061aaa0061a00610061 != b00610061aa0061a00610061)
    {
      b0061006100610061aa00610061 = 45;
      b00610061aa0061a00610061 = ba0061aa0061a00610061();
    }
    this.reference = paramString;
  }
  
  public void setSourceAccount(String paramString)
  {
    int i = b0061006100610061aa00610061;
    switch (i * (baaaa0061a00610061 + i) % b0061aaa0061a00610061)
    {
    default: 
      b0061006100610061aa00610061 = ba0061aa0061a00610061();
      if ((b0061006100610061aa00610061 + baaaa0061a00610061) * b0061006100610061aa00610061 % b0061aaa0061a00610061 != b0061a0061a0061a00610061())
      {
        b0061006100610061aa00610061 = ba0061aa0061a00610061();
        b00610061aa0061a00610061 = 99;
      }
      b00610061aa0061a00610061 = ba0061aa0061a00610061();
    }
    this.sourceAccount = paramString;
  }
  
  public void setTargetAccount(String paramString)
  {
    int i = b0061006100610061aa00610061;
    int j = baaaa0061a00610061;
    int k = b0061aaa0061a00610061;
    int m = b0061006100610061aa00610061;
    switch (m * (baaaa0061a00610061 + m) % b0061aaa0061a00610061)
    {
    default: 
      b0061006100610061aa00610061 = ba0061aa0061a00610061();
      b00610061aa0061a00610061 = ba0061aa0061a00610061();
    }
    switch (i * (j + i) % k)
    {
    default: 
      b0061006100610061aa00610061 = ba0061aa0061a00610061();
      b00610061aa0061a00610061 = 97;
    }
    this.targetAccount = paramString;
  }
  
  public void setTargetBic(String paramString)
  {
    if ((b0061006100610061aa00610061 + baaaa0061a00610061) * b0061006100610061aa00610061 % b0061aaa0061a00610061 != b00610061aa0061a00610061)
    {
      b0061006100610061aa00610061 = ba0061aa0061a00610061();
      int i = b0061006100610061aa00610061;
      switch (i * (ba00610061a0061a00610061() + i) % b0061aaa0061a00610061)
      {
      default: 
        b0061006100610061aa00610061 = 91;
        b00610061aa0061a00610061 = 43;
      }
      b00610061aa0061a00610061 = 43;
    }
    this.targetBic = paramString;
  }
  
  public void setValidUntil(String paramString)
  {
    if ((b0061006100610061aa00610061 + ba00610061a0061a00610061()) * b0061006100610061aa00610061 % b0061aaa0061a00610061 != b00610061aa0061a00610061)
    {
      b0061006100610061aa00610061 = ba0061aa0061a00610061();
      b00610061aa0061a00610061 = 65;
      int i = b0061006100610061aa00610061;
      switch (i * (baaaa0061a00610061 + i) % b0061aaa0061a00610061)
      {
      default: 
        b0061006100610061aa00610061 = ba0061aa0061a00610061();
        b00610061aa0061a00610061 = 42;
      }
    }
    this.validUntil = paramString;
  }
  
  /* Error */
  public String toString()
  {
    // Byte code:
    //   0: new 222	java/lang/StringBuilder
    //   3: dup
    //   4: invokespecial 223	java/lang/StringBuilder:<init>	()V
    //   7: astore_1
    //   8: ldc -110
    //   10: ldc -31
    //   12: sipush 140
    //   15: sipush 148
    //   18: iconst_2
    //   19: invokestatic 229	xxxxxx/uxxxxx:bbbb0062b0062b0062b0062	(Ljava/lang/String;CCC)Ljava/lang/String;
    //   22: iconst_3
    //   23: anewarray 156	java/lang/Class
    //   26: dup
    //   27: iconst_0
    //   28: ldc 76
    //   30: aastore
    //   31: dup
    //   32: iconst_1
    //   33: getstatic 162	java/lang/Character:TYPE	Ljava/lang/Class;
    //   36: aastore
    //   37: dup
    //   38: iconst_2
    //   39: getstatic 162	java/lang/Character:TYPE	Ljava/lang/Class;
    //   42: aastore
    //   43: invokevirtual 166	java/lang/Class:getMethod	(Ljava/lang/String;[Ljava/lang/Class;)Ljava/lang/reflect/Method;
    //   46: astore_2
    //   47: aload_2
    //   48: aconst_null
    //   49: iconst_3
    //   50: anewarray 5	java/lang/Object
    //   53: dup
    //   54: iconst_0
    //   55: ldc -25
    //   57: aastore
    //   58: dup
    //   59: iconst_1
    //   60: sipush 212
    //   63: invokestatic 172	java/lang/Character:valueOf	(C)Ljava/lang/Character;
    //   66: aastore
    //   67: dup
    //   68: iconst_2
    //   69: iconst_5
    //   70: invokestatic 172	java/lang/Character:valueOf	(C)Ljava/lang/Character;
    //   73: aastore
    //   74: invokevirtual 178	java/lang/reflect/Method:invoke	(Ljava/lang/Object;[Ljava/lang/Object;)Ljava/lang/Object;
    //   77: astore_2
    //   78: aload_1
    //   79: aload_2
    //   80: checkcast 76	java/lang/String
    //   83: invokevirtual 235	java/lang/StringBuilder:append	(Ljava/lang/String;)Ljava/lang/StringBuilder;
    //   86: aload_0
    //   87: getfield 100	com/db/pwcc/dbmobile/model/sepa/StandingOrder:id	Ljava/lang/String;
    //   90: invokevirtual 235	java/lang/StringBuilder:append	(Ljava/lang/String;)Ljava/lang/StringBuilder;
    //   93: bipush 39
    //   95: invokevirtual 238	java/lang/StringBuilder:append	(C)Ljava/lang/StringBuilder;
    //   98: astore_1
    //   99: ldc -110
    //   101: ldc -16
    //   103: bipush 114
    //   105: iconst_2
    //   106: invokestatic 154	xxxxxx/uxxxxx:bb00620062bb0062b0062b0062	(Ljava/lang/String;CC)Ljava/lang/String;
    //   109: iconst_4
    //   110: anewarray 156	java/lang/Class
    //   113: dup
    //   114: iconst_0
    //   115: ldc 76
    //   117: aastore
    //   118: dup
    //   119: iconst_1
    //   120: getstatic 162	java/lang/Character:TYPE	Ljava/lang/Class;
    //   123: aastore
    //   124: dup
    //   125: iconst_2
    //   126: getstatic 162	java/lang/Character:TYPE	Ljava/lang/Class;
    //   129: aastore
    //   130: dup
    //   131: iconst_3
    //   132: getstatic 162	java/lang/Character:TYPE	Ljava/lang/Class;
    //   135: aastore
    //   136: invokevirtual 166	java/lang/Class:getMethod	(Ljava/lang/String;[Ljava/lang/Class;)Ljava/lang/reflect/Method;
    //   139: astore_2
    //   140: aload_2
    //   141: aconst_null
    //   142: iconst_4
    //   143: anewarray 5	java/lang/Object
    //   146: dup
    //   147: iconst_0
    //   148: ldc -14
    //   150: aastore
    //   151: dup
    //   152: iconst_1
    //   153: bipush 75
    //   155: invokestatic 172	java/lang/Character:valueOf	(C)Ljava/lang/Character;
    //   158: aastore
    //   159: dup
    //   160: iconst_2
    //   161: sipush 204
    //   164: invokestatic 172	java/lang/Character:valueOf	(C)Ljava/lang/Character;
    //   167: aastore
    //   168: dup
    //   169: iconst_3
    //   170: iconst_3
    //   171: invokestatic 172	java/lang/Character:valueOf	(C)Ljava/lang/Character;
    //   174: aastore
    //   175: invokevirtual 178	java/lang/reflect/Method:invoke	(Ljava/lang/Object;[Ljava/lang/Object;)Ljava/lang/Object;
    //   178: astore_2
    //   179: aload_1
    //   180: aload_2
    //   181: checkcast 76	java/lang/String
    //   184: invokevirtual 235	java/lang/StringBuilder:append	(Ljava/lang/String;)Ljava/lang/StringBuilder;
    //   187: aload_0
    //   188: getfield 103	com/db/pwcc/dbmobile/model/sepa/StandingOrder:amount	Ljava/lang/String;
    //   191: invokevirtual 235	java/lang/StringBuilder:append	(Ljava/lang/String;)Ljava/lang/StringBuilder;
    //   194: bipush 39
    //   196: invokevirtual 238	java/lang/StringBuilder:append	(C)Ljava/lang/StringBuilder;
    //   199: astore_1
    //   200: ldc -110
    //   202: ldc -12
    //   204: bipush 55
    //   206: sipush 148
    //   209: iconst_2
    //   210: invokestatic 229	xxxxxx/uxxxxx:bbbb0062b0062b0062b0062	(Ljava/lang/String;CCC)Ljava/lang/String;
    //   213: iconst_3
    //   214: anewarray 156	java/lang/Class
    //   217: dup
    //   218: iconst_0
    //   219: ldc 76
    //   221: aastore
    //   222: dup
    //   223: iconst_1
    //   224: getstatic 162	java/lang/Character:TYPE	Ljava/lang/Class;
    //   227: aastore
    //   228: dup
    //   229: iconst_2
    //   230: getstatic 162	java/lang/Character:TYPE	Ljava/lang/Class;
    //   233: aastore
    //   234: invokevirtual 166	java/lang/Class:getMethod	(Ljava/lang/String;[Ljava/lang/Class;)Ljava/lang/reflect/Method;
    //   237: astore_2
    //   238: aload_2
    //   239: aconst_null
    //   240: iconst_3
    //   241: anewarray 5	java/lang/Object
    //   244: dup
    //   245: iconst_0
    //   246: ldc -10
    //   248: aastore
    //   249: dup
    //   250: iconst_1
    //   251: bipush 32
    //   253: invokestatic 172	java/lang/Character:valueOf	(C)Ljava/lang/Character;
    //   256: aastore
    //   257: dup
    //   258: iconst_2
    //   259: iconst_0
    //   260: invokestatic 172	java/lang/Character:valueOf	(C)Ljava/lang/Character;
    //   263: aastore
    //   264: invokevirtual 178	java/lang/reflect/Method:invoke	(Ljava/lang/Object;[Ljava/lang/Object;)Ljava/lang/Object;
    //   267: astore_2
    //   268: aload_1
    //   269: aload_2
    //   270: checkcast 76	java/lang/String
    //   273: invokevirtual 235	java/lang/StringBuilder:append	(Ljava/lang/String;)Ljava/lang/StringBuilder;
    //   276: aload_0
    //   277: getfield 60	com/db/pwcc/dbmobile/model/sepa/StandingOrder:beneficiary	Ljava/lang/String;
    //   280: invokevirtual 235	java/lang/StringBuilder:append	(Ljava/lang/String;)Ljava/lang/StringBuilder;
    //   283: bipush 39
    //   285: invokevirtual 238	java/lang/StringBuilder:append	(C)Ljava/lang/StringBuilder;
    //   288: astore_1
    //   289: ldc -110
    //   291: ldc -8
    //   293: bipush 90
    //   295: bipush 88
    //   297: iconst_1
    //   298: invokestatic 229	xxxxxx/uxxxxx:bbbb0062b0062b0062b0062	(Ljava/lang/String;CCC)Ljava/lang/String;
    //   301: iconst_4
    //   302: anewarray 156	java/lang/Class
    //   305: dup
    //   306: iconst_0
    //   307: ldc 76
    //   309: aastore
    //   310: dup
    //   311: iconst_1
    //   312: getstatic 162	java/lang/Character:TYPE	Ljava/lang/Class;
    //   315: aastore
    //   316: dup
    //   317: iconst_2
    //   318: getstatic 162	java/lang/Character:TYPE	Ljava/lang/Class;
    //   321: aastore
    //   322: dup
    //   323: iconst_3
    //   324: getstatic 162	java/lang/Character:TYPE	Ljava/lang/Class;
    //   327: aastore
    //   328: invokevirtual 166	java/lang/Class:getMethod	(Ljava/lang/String;[Ljava/lang/Class;)Ljava/lang/reflect/Method;
    //   331: astore_2
    //   332: aload_2
    //   333: aconst_null
    //   334: iconst_4
    //   335: anewarray 5	java/lang/Object
    //   338: dup
    //   339: iconst_0
    //   340: ldc -6
    //   342: aastore
    //   343: dup
    //   344: iconst_1
    //   345: bipush 125
    //   347: invokestatic 172	java/lang/Character:valueOf	(C)Ljava/lang/Character;
    //   350: aastore
    //   351: dup
    //   352: iconst_2
    //   353: sipush 255
    //   356: invokestatic 172	java/lang/Character:valueOf	(C)Ljava/lang/Character;
    //   359: aastore
    //   360: dup
    //   361: iconst_3
    //   362: iconst_2
    //   363: invokestatic 172	java/lang/Character:valueOf	(C)Ljava/lang/Character;
    //   366: aastore
    //   367: invokevirtual 178	java/lang/reflect/Method:invoke	(Ljava/lang/Object;[Ljava/lang/Object;)Ljava/lang/Object;
    //   370: astore_2
    //   371: aload_1
    //   372: aload_2
    //   373: checkcast 76	java/lang/String
    //   376: invokevirtual 235	java/lang/StringBuilder:append	(Ljava/lang/String;)Ljava/lang/StringBuilder;
    //   379: aload_0
    //   380: getfield 105	com/db/pwcc/dbmobile/model/sepa/StandingOrder:purpose	Ljava/lang/String;
    //   383: invokevirtual 235	java/lang/StringBuilder:append	(Ljava/lang/String;)Ljava/lang/StringBuilder;
    //   386: bipush 39
    //   388: invokevirtual 238	java/lang/StringBuilder:append	(C)Ljava/lang/StringBuilder;
    //   391: astore_1
    //   392: ldc -110
    //   394: ldc -4
    //   396: bipush 45
    //   398: sipush 170
    //   401: iconst_2
    //   402: invokestatic 229	xxxxxx/uxxxxx:bbbb0062b0062b0062b0062	(Ljava/lang/String;CCC)Ljava/lang/String;
    //   405: iconst_3
    //   406: anewarray 156	java/lang/Class
    //   409: dup
    //   410: iconst_0
    //   411: ldc 76
    //   413: aastore
    //   414: dup
    //   415: iconst_1
    //   416: getstatic 162	java/lang/Character:TYPE	Ljava/lang/Class;
    //   419: aastore
    //   420: dup
    //   421: iconst_2
    //   422: getstatic 162	java/lang/Character:TYPE	Ljava/lang/Class;
    //   425: aastore
    //   426: invokevirtual 166	java/lang/Class:getMethod	(Ljava/lang/String;[Ljava/lang/Class;)Ljava/lang/reflect/Method;
    //   429: astore_2
    //   430: aload_2
    //   431: aconst_null
    //   432: iconst_3
    //   433: anewarray 5	java/lang/Object
    //   436: dup
    //   437: iconst_0
    //   438: ldc -2
    //   440: aastore
    //   441: dup
    //   442: iconst_1
    //   443: bipush 70
    //   445: invokestatic 172	java/lang/Character:valueOf	(C)Ljava/lang/Character;
    //   448: aastore
    //   449: dup
    //   450: iconst_2
    //   451: iconst_0
    //   452: invokestatic 172	java/lang/Character:valueOf	(C)Ljava/lang/Character;
    //   455: aastore
    //   456: invokevirtual 178	java/lang/reflect/Method:invoke	(Ljava/lang/Object;[Ljava/lang/Object;)Ljava/lang/Object;
    //   459: astore_2
    //   460: aload_1
    //   461: aload_2
    //   462: checkcast 76	java/lang/String
    //   465: invokevirtual 235	java/lang/StringBuilder:append	(Ljava/lang/String;)Ljava/lang/StringBuilder;
    //   468: aload_0
    //   469: getfield 107	com/db/pwcc/dbmobile/model/sepa/StandingOrder:nextExecutionDate	Ljava/lang/String;
    //   472: invokevirtual 235	java/lang/StringBuilder:append	(Ljava/lang/String;)Ljava/lang/StringBuilder;
    //   475: bipush 39
    //   477: invokevirtual 238	java/lang/StringBuilder:append	(C)Ljava/lang/StringBuilder;
    //   480: astore_1
    //   481: ldc -110
    //   483: ldc_w 256
    //   486: bipush 33
    //   488: iconst_1
    //   489: invokestatic 154	xxxxxx/uxxxxx:bb00620062bb0062b0062b0062	(Ljava/lang/String;CC)Ljava/lang/String;
    //   492: iconst_3
    //   493: anewarray 156	java/lang/Class
    //   496: dup
    //   497: iconst_0
    //   498: ldc 76
    //   500: aastore
    //   501: dup
    //   502: iconst_1
    //   503: getstatic 162	java/lang/Character:TYPE	Ljava/lang/Class;
    //   506: aastore
    //   507: dup
    //   508: iconst_2
    //   509: getstatic 162	java/lang/Character:TYPE	Ljava/lang/Class;
    //   512: aastore
    //   513: invokevirtual 166	java/lang/Class:getMethod	(Ljava/lang/String;[Ljava/lang/Class;)Ljava/lang/reflect/Method;
    //   516: astore_2
    //   517: aload_2
    //   518: aconst_null
    //   519: iconst_3
    //   520: anewarray 5	java/lang/Object
    //   523: dup
    //   524: iconst_0
    //   525: ldc_w 258
    //   528: aastore
    //   529: dup
    //   530: iconst_1
    //   531: sipush 199
    //   534: invokestatic 172	java/lang/Character:valueOf	(C)Ljava/lang/Character;
    //   537: aastore
    //   538: dup
    //   539: iconst_2
    //   540: iconst_5
    //   541: invokestatic 172	java/lang/Character:valueOf	(C)Ljava/lang/Character;
    //   544: aastore
    //   545: invokevirtual 178	java/lang/reflect/Method:invoke	(Ljava/lang/Object;[Ljava/lang/Object;)Ljava/lang/Object;
    //   548: astore_2
    //   549: aload_1
    //   550: aload_2
    //   551: checkcast 76	java/lang/String
    //   554: invokevirtual 235	java/lang/StringBuilder:append	(Ljava/lang/String;)Ljava/lang/StringBuilder;
    //   557: aload_0
    //   558: getfield 98	com/db/pwcc/dbmobile/model/sepa/StandingOrder:modifiable	Z
    //   561: invokevirtual 261	java/lang/StringBuilder:append	(Z)Ljava/lang/StringBuilder;
    //   564: bipush 39
    //   566: invokevirtual 238	java/lang/StringBuilder:append	(C)Ljava/lang/StringBuilder;
    //   569: astore_1
    //   570: getstatic 66	com/db/pwcc/dbmobile/model/sepa/StandingOrder:b0061006100610061aa00610061	I
    //   573: invokestatic 180	com/db/pwcc/dbmobile/model/sepa/StandingOrder:ba00610061a0061a00610061	()I
    //   576: iadd
    //   577: getstatic 66	com/db/pwcc/dbmobile/model/sepa/StandingOrder:b0061006100610061aa00610061	I
    //   580: imul
    //   581: getstatic 70	com/db/pwcc/dbmobile/model/sepa/StandingOrder:b0061aaa0061a00610061	I
    //   584: irem
    //   585: getstatic 72	com/db/pwcc/dbmobile/model/sepa/StandingOrder:b00610061aa0061a00610061	I
    //   588: if_icmpeq +14 -> 602
    //   591: bipush 57
    //   593: putstatic 66	com/db/pwcc/dbmobile/model/sepa/StandingOrder:b0061006100610061aa00610061	I
    //   596: invokestatic 74	com/db/pwcc/dbmobile/model/sepa/StandingOrder:ba0061aa0061a00610061	()I
    //   599: putstatic 72	com/db/pwcc/dbmobile/model/sepa/StandingOrder:b00610061aa0061a00610061	I
    //   602: ldc -110
    //   604: ldc_w 263
    //   607: bipush 58
    //   609: iconst_2
    //   610: invokestatic 154	xxxxxx/uxxxxx:bb00620062bb0062b0062b0062	(Ljava/lang/String;CC)Ljava/lang/String;
    //   613: iconst_3
    //   614: anewarray 156	java/lang/Class
    //   617: dup
    //   618: iconst_0
    //   619: ldc 76
    //   621: aastore
    //   622: dup
    //   623: iconst_1
    //   624: getstatic 162	java/lang/Character:TYPE	Ljava/lang/Class;
    //   627: aastore
    //   628: dup
    //   629: iconst_2
    //   630: getstatic 162	java/lang/Character:TYPE	Ljava/lang/Class;
    //   633: aastore
    //   634: invokevirtual 166	java/lang/Class:getMethod	(Ljava/lang/String;[Ljava/lang/Class;)Ljava/lang/reflect/Method;
    //   637: astore_2
    //   638: aload_2
    //   639: aconst_null
    //   640: iconst_3
    //   641: anewarray 5	java/lang/Object
    //   644: dup
    //   645: iconst_0
    //   646: ldc_w 265
    //   649: aastore
    //   650: dup
    //   651: iconst_1
    //   652: bipush 100
    //   654: invokestatic 172	java/lang/Character:valueOf	(C)Ljava/lang/Character;
    //   657: aastore
    //   658: dup
    //   659: iconst_2
    //   660: iconst_4
    //   661: invokestatic 172	java/lang/Character:valueOf	(C)Ljava/lang/Character;
    //   664: aastore
    //   665: invokevirtual 178	java/lang/reflect/Method:invoke	(Ljava/lang/Object;[Ljava/lang/Object;)Ljava/lang/Object;
    //   668: astore_2
    //   669: aload_1
    //   670: aload_2
    //   671: checkcast 76	java/lang/String
    //   674: invokevirtual 235	java/lang/StringBuilder:append	(Ljava/lang/String;)Ljava/lang/StringBuilder;
    //   677: aload_0
    //   678: getfield 109	com/db/pwcc/dbmobile/model/sepa/StandingOrder:sourceAccount	Ljava/lang/String;
    //   681: invokevirtual 235	java/lang/StringBuilder:append	(Ljava/lang/String;)Ljava/lang/StringBuilder;
    //   684: bipush 39
    //   686: invokevirtual 238	java/lang/StringBuilder:append	(C)Ljava/lang/StringBuilder;
    //   689: astore_1
    //   690: ldc -110
    //   692: ldc_w 267
    //   695: bipush 39
    //   697: iconst_4
    //   698: invokestatic 154	xxxxxx/uxxxxx:bb00620062bb0062b0062b0062	(Ljava/lang/String;CC)Ljava/lang/String;
    //   701: iconst_3
    //   702: anewarray 156	java/lang/Class
    //   705: dup
    //   706: iconst_0
    //   707: ldc 76
    //   709: aastore
    //   710: dup
    //   711: iconst_1
    //   712: getstatic 162	java/lang/Character:TYPE	Ljava/lang/Class;
    //   715: aastore
    //   716: dup
    //   717: iconst_2
    //   718: getstatic 162	java/lang/Character:TYPE	Ljava/lang/Class;
    //   721: aastore
    //   722: invokevirtual 166	java/lang/Class:getMethod	(Ljava/lang/String;[Ljava/lang/Class;)Ljava/lang/reflect/Method;
    //   725: astore_2
    //   726: aload_2
    //   727: aconst_null
    //   728: iconst_3
    //   729: anewarray 5	java/lang/Object
    //   732: dup
    //   733: iconst_0
    //   734: ldc_w 269
    //   737: aastore
    //   738: dup
    //   739: iconst_1
    //   740: bipush 78
    //   742: invokestatic 172	java/lang/Character:valueOf	(C)Ljava/lang/Character;
    //   745: aastore
    //   746: dup
    //   747: iconst_2
    //   748: iconst_3
    //   749: invokestatic 172	java/lang/Character:valueOf	(C)Ljava/lang/Character;
    //   752: aastore
    //   753: invokevirtual 178	java/lang/reflect/Method:invoke	(Ljava/lang/Object;[Ljava/lang/Object;)Ljava/lang/Object;
    //   756: astore_2
    //   757: aload_1
    //   758: aload_2
    //   759: checkcast 76	java/lang/String
    //   762: invokevirtual 235	java/lang/StringBuilder:append	(Ljava/lang/String;)Ljava/lang/StringBuilder;
    //   765: aload_0
    //   766: getfield 111	com/db/pwcc/dbmobile/model/sepa/StandingOrder:targetAccount	Ljava/lang/String;
    //   769: invokevirtual 235	java/lang/StringBuilder:append	(Ljava/lang/String;)Ljava/lang/StringBuilder;
    //   772: bipush 39
    //   774: invokevirtual 238	java/lang/StringBuilder:append	(C)Ljava/lang/StringBuilder;
    //   777: astore_1
    //   778: ldc -110
    //   780: ldc_w 271
    //   783: sipush 249
    //   786: iconst_4
    //   787: invokestatic 154	xxxxxx/uxxxxx:bb00620062bb0062b0062b0062	(Ljava/lang/String;CC)Ljava/lang/String;
    //   790: iconst_4
    //   791: anewarray 156	java/lang/Class
    //   794: dup
    //   795: iconst_0
    //   796: ldc 76
    //   798: aastore
    //   799: dup
    //   800: iconst_1
    //   801: getstatic 162	java/lang/Character:TYPE	Ljava/lang/Class;
    //   804: aastore
    //   805: dup
    //   806: iconst_2
    //   807: getstatic 162	java/lang/Character:TYPE	Ljava/lang/Class;
    //   810: aastore
    //   811: dup
    //   812: iconst_3
    //   813: getstatic 162	java/lang/Character:TYPE	Ljava/lang/Class;
    //   816: aastore
    //   817: invokevirtual 166	java/lang/Class:getMethod	(Ljava/lang/String;[Ljava/lang/Class;)Ljava/lang/reflect/Method;
    //   820: astore_2
    //   821: aload_2
    //   822: aconst_null
    //   823: iconst_4
    //   824: anewarray 5	java/lang/Object
    //   827: dup
    //   828: iconst_0
    //   829: ldc_w 273
    //   832: aastore
    //   833: dup
    //   834: iconst_1
    //   835: bipush 98
    //   837: invokestatic 172	java/lang/Character:valueOf	(C)Ljava/lang/Character;
    //   840: aastore
    //   841: dup
    //   842: iconst_2
    //   843: sipush 223
    //   846: invokestatic 172	java/lang/Character:valueOf	(C)Ljava/lang/Character;
    //   849: aastore
    //   850: dup
    //   851: iconst_3
    //   852: iconst_3
    //   853: invokestatic 172	java/lang/Character:valueOf	(C)Ljava/lang/Character;
    //   856: aastore
    //   857: invokevirtual 178	java/lang/reflect/Method:invoke	(Ljava/lang/Object;[Ljava/lang/Object;)Ljava/lang/Object;
    //   860: astore_2
    //   861: aload_1
    //   862: aload_2
    //   863: checkcast 76	java/lang/String
    //   866: invokevirtual 235	java/lang/StringBuilder:append	(Ljava/lang/String;)Ljava/lang/StringBuilder;
    //   869: aload_0
    //   870: getfield 113	com/db/pwcc/dbmobile/model/sepa/StandingOrder:targetBic	Ljava/lang/String;
    //   873: invokevirtual 235	java/lang/StringBuilder:append	(Ljava/lang/String;)Ljava/lang/StringBuilder;
    //   876: bipush 39
    //   878: invokevirtual 238	java/lang/StringBuilder:append	(C)Ljava/lang/StringBuilder;
    //   881: astore_1
    //   882: ldc -110
    //   884: ldc_w 275
    //   887: sipush 189
    //   890: iconst_5
    //   891: invokestatic 154	xxxxxx/uxxxxx:bb00620062bb0062b0062b0062	(Ljava/lang/String;CC)Ljava/lang/String;
    //   894: iconst_3
    //   895: anewarray 156	java/lang/Class
    //   898: dup
    //   899: iconst_0
    //   900: ldc 76
    //   902: aastore
    //   903: dup
    //   904: iconst_1
    //   905: getstatic 162	java/lang/Character:TYPE	Ljava/lang/Class;
    //   908: aastore
    //   909: dup
    //   910: iconst_2
    //   911: getstatic 162	java/lang/Character:TYPE	Ljava/lang/Class;
    //   914: aastore
    //   915: invokevirtual 166	java/lang/Class:getMethod	(Ljava/lang/String;[Ljava/lang/Class;)Ljava/lang/reflect/Method;
    //   918: astore_2
    //   919: aload_2
    //   920: aconst_null
    //   921: iconst_3
    //   922: anewarray 5	java/lang/Object
    //   925: dup
    //   926: iconst_0
    //   927: ldc_w 277
    //   930: aastore
    //   931: dup
    //   932: iconst_1
    //   933: sipush 184
    //   936: invokestatic 172	java/lang/Character:valueOf	(C)Ljava/lang/Character;
    //   939: aastore
    //   940: dup
    //   941: iconst_2
    //   942: iconst_0
    //   943: invokestatic 172	java/lang/Character:valueOf	(C)Ljava/lang/Character;
    //   946: aastore
    //   947: invokevirtual 178	java/lang/reflect/Method:invoke	(Ljava/lang/Object;[Ljava/lang/Object;)Ljava/lang/Object;
    //   950: astore_2
    //   951: aload_1
    //   952: aload_2
    //   953: checkcast 76	java/lang/String
    //   956: invokevirtual 235	java/lang/StringBuilder:append	(Ljava/lang/String;)Ljava/lang/StringBuilder;
    //   959: aload_0
    //   960: getfield 115	com/db/pwcc/dbmobile/model/sepa/StandingOrder:reference	Ljava/lang/String;
    //   963: invokevirtual 235	java/lang/StringBuilder:append	(Ljava/lang/String;)Ljava/lang/StringBuilder;
    //   966: bipush 39
    //   968: invokevirtual 238	java/lang/StringBuilder:append	(C)Ljava/lang/StringBuilder;
    //   971: astore_1
    //   972: ldc -110
    //   974: ldc_w 279
    //   977: bipush 95
    //   979: iconst_4
    //   980: invokestatic 154	xxxxxx/uxxxxx:bb00620062bb0062b0062b0062	(Ljava/lang/String;CC)Ljava/lang/String;
    //   983: iconst_3
    //   984: anewarray 156	java/lang/Class
    //   987: dup
    //   988: iconst_0
    //   989: ldc 76
    //   991: aastore
    //   992: dup
    //   993: iconst_1
    //   994: getstatic 162	java/lang/Character:TYPE	Ljava/lang/Class;
    //   997: aastore
    //   998: dup
    //   999: iconst_2
    //   1000: getstatic 162	java/lang/Character:TYPE	Ljava/lang/Class;
    //   1003: aastore
    //   1004: invokevirtual 166	java/lang/Class:getMethod	(Ljava/lang/String;[Ljava/lang/Class;)Ljava/lang/reflect/Method;
    //   1007: astore_2
    //   1008: aload_2
    //   1009: aconst_null
    //   1010: iconst_3
    //   1011: anewarray 5	java/lang/Object
    //   1014: dup
    //   1015: iconst_0
    //   1016: ldc_w 281
    //   1019: aastore
    //   1020: dup
    //   1021: iconst_1
    //   1022: bipush 92
    //   1024: invokestatic 172	java/lang/Character:valueOf	(C)Ljava/lang/Character;
    //   1027: aastore
    //   1028: dup
    //   1029: iconst_2
    //   1030: iconst_2
    //   1031: invokestatic 172	java/lang/Character:valueOf	(C)Ljava/lang/Character;
    //   1034: aastore
    //   1035: invokevirtual 178	java/lang/reflect/Method:invoke	(Ljava/lang/Object;[Ljava/lang/Object;)Ljava/lang/Object;
    //   1038: astore_2
    //   1039: aload_1
    //   1040: aload_2
    //   1041: checkcast 76	java/lang/String
    //   1044: invokevirtual 235	java/lang/StringBuilder:append	(Ljava/lang/String;)Ljava/lang/StringBuilder;
    //   1047: aload_0
    //   1048: getfield 117	com/db/pwcc/dbmobile/model/sepa/StandingOrder:firstExecutionDate	Ljava/lang/String;
    //   1051: invokevirtual 235	java/lang/StringBuilder:append	(Ljava/lang/String;)Ljava/lang/StringBuilder;
    //   1054: bipush 39
    //   1056: invokevirtual 238	java/lang/StringBuilder:append	(C)Ljava/lang/StringBuilder;
    //   1059: astore_1
    //   1060: ldc -110
    //   1062: ldc_w 283
    //   1065: sipush 244
    //   1068: iconst_4
    //   1069: invokestatic 154	xxxxxx/uxxxxx:bb00620062bb0062b0062b0062	(Ljava/lang/String;CC)Ljava/lang/String;
    //   1072: iconst_4
    //   1073: anewarray 156	java/lang/Class
    //   1076: dup
    //   1077: iconst_0
    //   1078: ldc 76
    //   1080: aastore
    //   1081: dup
    //   1082: iconst_1
    //   1083: getstatic 162	java/lang/Character:TYPE	Ljava/lang/Class;
    //   1086: aastore
    //   1087: dup
    //   1088: iconst_2
    //   1089: getstatic 162	java/lang/Character:TYPE	Ljava/lang/Class;
    //   1092: aastore
    //   1093: dup
    //   1094: iconst_3
    //   1095: getstatic 162	java/lang/Character:TYPE	Ljava/lang/Class;
    //   1098: aastore
    //   1099: invokevirtual 166	java/lang/Class:getMethod	(Ljava/lang/String;[Ljava/lang/Class;)Ljava/lang/reflect/Method;
    //   1102: astore_2
    //   1103: aload_2
    //   1104: aconst_null
    //   1105: iconst_4
    //   1106: anewarray 5	java/lang/Object
    //   1109: dup
    //   1110: iconst_0
    //   1111: ldc_w 285
    //   1114: aastore
    //   1115: dup
    //   1116: iconst_1
    //   1117: bipush 53
    //   1119: invokestatic 172	java/lang/Character:valueOf	(C)Ljava/lang/Character;
    //   1122: aastore
    //   1123: dup
    //   1124: iconst_2
    //   1125: sipush 236
    //   1128: invokestatic 172	java/lang/Character:valueOf	(C)Ljava/lang/Character;
    //   1131: aastore
    //   1132: dup
    //   1133: iconst_3
    //   1134: iconst_2
    //   1135: invokestatic 172	java/lang/Character:valueOf	(C)Ljava/lang/Character;
    //   1138: aastore
    //   1139: invokevirtual 178	java/lang/reflect/Method:invoke	(Ljava/lang/Object;[Ljava/lang/Object;)Ljava/lang/Object;
    //   1142: astore_2
    //   1143: aload_1
    //   1144: aload_2
    //   1145: checkcast 76	java/lang/String
    //   1148: invokevirtual 235	java/lang/StringBuilder:append	(Ljava/lang/String;)Ljava/lang/StringBuilder;
    //   1151: aload_0
    //   1152: getfield 119	com/db/pwcc/dbmobile/model/sepa/StandingOrder:lastChangeDate	Ljava/lang/String;
    //   1155: invokevirtual 235	java/lang/StringBuilder:append	(Ljava/lang/String;)Ljava/lang/StringBuilder;
    //   1158: bipush 39
    //   1160: invokevirtual 238	java/lang/StringBuilder:append	(C)Ljava/lang/StringBuilder;
    //   1163: astore_1
    //   1164: ldc -110
    //   1166: ldc_w 287
    //   1169: bipush 88
    //   1171: iconst_0
    //   1172: invokestatic 154	xxxxxx/uxxxxx:bb00620062bb0062b0062b0062	(Ljava/lang/String;CC)Ljava/lang/String;
    //   1175: iconst_3
    //   1176: anewarray 156	java/lang/Class
    //   1179: dup
    //   1180: iconst_0
    //   1181: ldc 76
    //   1183: aastore
    //   1184: dup
    //   1185: iconst_1
    //   1186: getstatic 162	java/lang/Character:TYPE	Ljava/lang/Class;
    //   1189: aastore
    //   1190: dup
    //   1191: iconst_2
    //   1192: getstatic 162	java/lang/Character:TYPE	Ljava/lang/Class;
    //   1195: aastore
    //   1196: invokevirtual 166	java/lang/Class:getMethod	(Ljava/lang/String;[Ljava/lang/Class;)Ljava/lang/reflect/Method;
    //   1199: astore_2
    //   1200: aload_2
    //   1201: aconst_null
    //   1202: iconst_3
    //   1203: anewarray 5	java/lang/Object
    //   1206: dup
    //   1207: iconst_0
    //   1208: ldc_w 289
    //   1211: aastore
    //   1212: dup
    //   1213: iconst_1
    //   1214: bipush 22
    //   1216: invokestatic 172	java/lang/Character:valueOf	(C)Ljava/lang/Character;
    //   1219: aastore
    //   1220: dup
    //   1221: iconst_2
    //   1222: iconst_1
    //   1223: invokestatic 172	java/lang/Character:valueOf	(C)Ljava/lang/Character;
    //   1226: aastore
    //   1227: invokevirtual 178	java/lang/reflect/Method:invoke	(Ljava/lang/Object;[Ljava/lang/Object;)Ljava/lang/Object;
    //   1230: astore_2
    //   1231: aload_1
    //   1232: aload_2
    //   1233: checkcast 76	java/lang/String
    //   1236: invokevirtual 235	java/lang/StringBuilder:append	(Ljava/lang/String;)Ljava/lang/StringBuilder;
    //   1239: aload_0
    //   1240: getfield 121	com/db/pwcc/dbmobile/model/sepa/StandingOrder:validUntil	Ljava/lang/String;
    //   1243: invokevirtual 235	java/lang/StringBuilder:append	(Ljava/lang/String;)Ljava/lang/StringBuilder;
    //   1246: bipush 39
    //   1248: invokevirtual 238	java/lang/StringBuilder:append	(C)Ljava/lang/StringBuilder;
    //   1251: astore_1
    //   1252: ldc -110
    //   1254: ldc_w 291
    //   1257: bipush 19
    //   1259: iconst_2
    //   1260: invokestatic 154	xxxxxx/uxxxxx:bb00620062bb0062b0062b0062	(Ljava/lang/String;CC)Ljava/lang/String;
    //   1263: iconst_3
    //   1264: anewarray 156	java/lang/Class
    //   1267: dup
    //   1268: iconst_0
    //   1269: ldc 76
    //   1271: aastore
    //   1272: dup
    //   1273: iconst_1
    //   1274: getstatic 162	java/lang/Character:TYPE	Ljava/lang/Class;
    //   1277: aastore
    //   1278: dup
    //   1279: iconst_2
    //   1280: getstatic 162	java/lang/Character:TYPE	Ljava/lang/Class;
    //   1283: aastore
    //   1284: invokevirtual 166	java/lang/Class:getMethod	(Ljava/lang/String;[Ljava/lang/Class;)Ljava/lang/reflect/Method;
    //   1287: astore_2
    //   1288: aload_2
    //   1289: aconst_null
    //   1290: iconst_3
    //   1291: anewarray 5	java/lang/Object
    //   1294: dup
    //   1295: iconst_0
    //   1296: ldc_w 293
    //   1299: aastore
    //   1300: dup
    //   1301: iconst_1
    //   1302: bipush 17
    //   1304: invokestatic 172	java/lang/Character:valueOf	(C)Ljava/lang/Character;
    //   1307: aastore
    //   1308: dup
    //   1309: iconst_2
    //   1310: iconst_0
    //   1311: invokestatic 172	java/lang/Character:valueOf	(C)Ljava/lang/Character;
    //   1314: aastore
    //   1315: invokevirtual 178	java/lang/reflect/Method:invoke	(Ljava/lang/Object;[Ljava/lang/Object;)Ljava/lang/Object;
    //   1318: astore_2
    //   1319: aload_1
    //   1320: aload_2
    //   1321: checkcast 76	java/lang/String
    //   1324: invokevirtual 235	java/lang/StringBuilder:append	(Ljava/lang/String;)Ljava/lang/StringBuilder;
    //   1327: astore_1
    //   1328: getstatic 66	com/db/pwcc/dbmobile/model/sepa/StandingOrder:b0061006100610061aa00610061	I
    //   1331: getstatic 68	com/db/pwcc/dbmobile/model/sepa/StandingOrder:baaaa0061a00610061	I
    //   1334: iadd
    //   1335: getstatic 66	com/db/pwcc/dbmobile/model/sepa/StandingOrder:b0061006100610061aa00610061	I
    //   1338: imul
    //   1339: invokestatic 128	com/db/pwcc/dbmobile/model/sepa/StandingOrder:baa0061a0061a00610061	()I
    //   1342: irem
    //   1343: getstatic 72	com/db/pwcc/dbmobile/model/sepa/StandingOrder:b00610061aa0061a00610061	I
    //   1346: if_icmpeq +14 -> 1360
    //   1349: bipush 23
    //   1351: putstatic 66	com/db/pwcc/dbmobile/model/sepa/StandingOrder:b0061006100610061aa00610061	I
    //   1354: invokestatic 74	com/db/pwcc/dbmobile/model/sepa/StandingOrder:ba0061aa0061a00610061	()I
    //   1357: putstatic 72	com/db/pwcc/dbmobile/model/sepa/StandingOrder:b00610061aa0061a00610061	I
    //   1360: aload_1
    //   1361: aload_0
    //   1362: getfield 123	com/db/pwcc/dbmobile/model/sepa/StandingOrder:executionOn	Ljava/lang/String;
    //   1365: invokevirtual 235	java/lang/StringBuilder:append	(Ljava/lang/String;)Ljava/lang/StringBuilder;
    //   1368: bipush 39
    //   1370: invokevirtual 238	java/lang/StringBuilder:append	(C)Ljava/lang/StringBuilder;
    //   1373: astore_1
    //   1374: ldc -110
    //   1376: ldc_w 295
    //   1379: sipush 179
    //   1382: iconst_3
    //   1383: invokestatic 154	xxxxxx/uxxxxx:bb00620062bb0062b0062b0062	(Ljava/lang/String;CC)Ljava/lang/String;
    //   1386: iconst_3
    //   1387: anewarray 156	java/lang/Class
    //   1390: dup
    //   1391: iconst_0
    //   1392: ldc 76
    //   1394: aastore
    //   1395: dup
    //   1396: iconst_1
    //   1397: getstatic 162	java/lang/Character:TYPE	Ljava/lang/Class;
    //   1400: aastore
    //   1401: dup
    //   1402: iconst_2
    //   1403: getstatic 162	java/lang/Character:TYPE	Ljava/lang/Class;
    //   1406: aastore
    //   1407: invokevirtual 166	java/lang/Class:getMethod	(Ljava/lang/String;[Ljava/lang/Class;)Ljava/lang/reflect/Method;
    //   1410: astore_2
    //   1411: aload_2
    //   1412: aconst_null
    //   1413: iconst_3
    //   1414: anewarray 5	java/lang/Object
    //   1417: dup
    //   1418: iconst_0
    //   1419: ldc_w 297
    //   1422: aastore
    //   1423: dup
    //   1424: iconst_1
    //   1425: bipush 25
    //   1427: invokestatic 172	java/lang/Character:valueOf	(C)Ljava/lang/Character;
    //   1430: aastore
    //   1431: dup
    //   1432: iconst_2
    //   1433: iconst_4
    //   1434: invokestatic 172	java/lang/Character:valueOf	(C)Ljava/lang/Character;
    //   1437: aastore
    //   1438: invokevirtual 178	java/lang/reflect/Method:invoke	(Ljava/lang/Object;[Ljava/lang/Object;)Ljava/lang/Object;
    //   1441: astore_2
    //   1442: aload_1
    //   1443: aload_2
    //   1444: checkcast 76	java/lang/String
    //   1447: invokevirtual 235	java/lang/StringBuilder:append	(Ljava/lang/String;)Ljava/lang/StringBuilder;
    //   1450: aload_0
    //   1451: getfield 125	com/db/pwcc/dbmobile/model/sepa/StandingOrder:frequency	Ljava/lang/String;
    //   1454: invokevirtual 235	java/lang/StringBuilder:append	(Ljava/lang/String;)Ljava/lang/StringBuilder;
    //   1457: bipush 39
    //   1459: invokevirtual 238	java/lang/StringBuilder:append	(C)Ljava/lang/StringBuilder;
    //   1462: bipush 125
    //   1464: invokevirtual 238	java/lang/StringBuilder:append	(C)Ljava/lang/StringBuilder;
    //   1467: invokevirtual 299	java/lang/StringBuilder:toString	()Ljava/lang/String;
    //   1470: areturn
    //   1471: astore_1
    //   1472: aload_1
    //   1473: invokevirtual 184	java/lang/reflect/InvocationTargetException:getCause	()Ljava/lang/Throwable;
    //   1476: athrow
    //   1477: astore_1
    //   1478: aload_1
    //   1479: invokevirtual 184	java/lang/reflect/InvocationTargetException:getCause	()Ljava/lang/Throwable;
    //   1482: athrow
    //   1483: astore_1
    //   1484: aload_1
    //   1485: invokevirtual 184	java/lang/reflect/InvocationTargetException:getCause	()Ljava/lang/Throwable;
    //   1488: athrow
    //   1489: astore_1
    //   1490: aload_1
    //   1491: invokevirtual 184	java/lang/reflect/InvocationTargetException:getCause	()Ljava/lang/Throwable;
    //   1494: athrow
    //   1495: astore_1
    //   1496: aload_1
    //   1497: invokevirtual 184	java/lang/reflect/InvocationTargetException:getCause	()Ljava/lang/Throwable;
    //   1500: athrow
    //   1501: astore_1
    //   1502: aload_1
    //   1503: invokevirtual 184	java/lang/reflect/InvocationTargetException:getCause	()Ljava/lang/Throwable;
    //   1506: athrow
    //   1507: astore_1
    //   1508: aload_1
    //   1509: invokevirtual 184	java/lang/reflect/InvocationTargetException:getCause	()Ljava/lang/Throwable;
    //   1512: athrow
    //   1513: astore_1
    //   1514: aload_1
    //   1515: invokevirtual 184	java/lang/reflect/InvocationTargetException:getCause	()Ljava/lang/Throwable;
    //   1518: athrow
    //   1519: astore_1
    //   1520: aload_1
    //   1521: invokevirtual 184	java/lang/reflect/InvocationTargetException:getCause	()Ljava/lang/Throwable;
    //   1524: athrow
    //   1525: astore_1
    //   1526: aload_1
    //   1527: invokevirtual 184	java/lang/reflect/InvocationTargetException:getCause	()Ljava/lang/Throwable;
    //   1530: athrow
    //   1531: astore_1
    //   1532: aload_1
    //   1533: invokevirtual 184	java/lang/reflect/InvocationTargetException:getCause	()Ljava/lang/Throwable;
    //   1536: athrow
    //   1537: astore_1
    //   1538: aload_1
    //   1539: invokevirtual 184	java/lang/reflect/InvocationTargetException:getCause	()Ljava/lang/Throwable;
    //   1542: athrow
    //   1543: astore_1
    //   1544: aload_1
    //   1545: invokevirtual 184	java/lang/reflect/InvocationTargetException:getCause	()Ljava/lang/Throwable;
    //   1548: athrow
    //   1549: astore_1
    //   1550: aload_1
    //   1551: invokevirtual 184	java/lang/reflect/InvocationTargetException:getCause	()Ljava/lang/Throwable;
    //   1554: athrow
    //   1555: astore_1
    //   1556: aload_1
    //   1557: invokevirtual 184	java/lang/reflect/InvocationTargetException:getCause	()Ljava/lang/Throwable;
    //   1560: athrow
    // Local variable table:
    //   start	length	slot	name	signature
    //   0	1561	0	this	StandingOrder
    //   7	1436	1	localStringBuilder	StringBuilder
    //   1471	2	1	localInvocationTargetException1	InvocationTargetException
    //   1477	2	1	localInvocationTargetException2	InvocationTargetException
    //   1483	2	1	localInvocationTargetException3	InvocationTargetException
    //   1489	2	1	localInvocationTargetException4	InvocationTargetException
    //   1495	2	1	localInvocationTargetException5	InvocationTargetException
    //   1501	2	1	localInvocationTargetException6	InvocationTargetException
    //   1507	2	1	localInvocationTargetException7	InvocationTargetException
    //   1513	2	1	localInvocationTargetException8	InvocationTargetException
    //   1519	2	1	localInvocationTargetException9	InvocationTargetException
    //   1525	2	1	localInvocationTargetException10	InvocationTargetException
    //   1531	2	1	localInvocationTargetException11	InvocationTargetException
    //   1537	2	1	localInvocationTargetException12	InvocationTargetException
    //   1543	2	1	localInvocationTargetException13	InvocationTargetException
    //   1549	2	1	localInvocationTargetException14	InvocationTargetException
    //   1555	2	1	localInvocationTargetException15	InvocationTargetException
    //   46	1398	2	localObject	Object
    // Exception table:
    //   from	to	target	type
    //   821	861	1471	java/lang/reflect/InvocationTargetException
    //   517	549	1477	java/lang/reflect/InvocationTargetException
    //   919	951	1483	java/lang/reflect/InvocationTargetException
    //   1288	1319	1489	java/lang/reflect/InvocationTargetException
    //   47	78	1495	java/lang/reflect/InvocationTargetException
    //   140	179	1501	java/lang/reflect/InvocationTargetException
    //   638	669	1507	java/lang/reflect/InvocationTargetException
    //   726	757	1513	java/lang/reflect/InvocationTargetException
    //   1200	1231	1519	java/lang/reflect/InvocationTargetException
    //   332	371	1525	java/lang/reflect/InvocationTargetException
    //   238	268	1531	java/lang/reflect/InvocationTargetException
    //   430	460	1537	java/lang/reflect/InvocationTargetException
    //   1103	1143	1543	java/lang/reflect/InvocationTargetException
    //   1008	1039	1549	java/lang/reflect/InvocationTargetException
    //   1411	1442	1555	java/lang/reflect/InvocationTargetException
  }
}
