package ro.btrl.enrollment.di.module;

public final class EnrollmentModule
{
  private static long ˊ = 7657169957479425431L;
  private static int ˎ;
  private static char[] ˏ = { -4831, 18601, -23012, 7653, -15773, 26595, -30385, 12987, 21566, -1653, 9199, 17759, -4389, 4135 };
  private static int ॱ = 0;
  
  static
  {
    ˎ = 1;
  }
  
  public EnrollmentModule() {}
  
  /* Error */
  private static String ˏ(int paramInt1, char paramChar, int paramInt2)
  {
    // Byte code:
    //   0: goto +51 -> 51
    //   3: goto +111 -> 114
    //   6: iload 4
    //   8: lookupswitch	default:+28->36, 12:+28->36, 23:+117->125
    //   36: new 46	java/lang/String
    //   39: dup
    //   40: aload 9
    //   42: invokespecial 49	java/lang/String:<init>	([C)V
    //   45: areturn
    //   46: astore 9
    //   48: aload 9
    //   50: athrow
    //   51: goto +153 -> 204
    //   54: iload_2
    //   55: newarray char
    //   57: astore 9
    //   59: iconst_0
    //   60: istore_3
    //   61: goto +202 -> 263
    //   64: getstatic 37	ro/btrl/enrollment/di/module/EnrollmentModule:ˏ	[C
    //   67: astore 10
    //   69: aload 10
    //   71: iload_0
    //   72: iload_3
    //   73: iadd
    //   74: caload
    //   75: i2l
    //   76: lstore 5
    //   78: iload_3
    //   79: i2l
    //   80: lstore 7
    //   82: aload 9
    //   84: iload_3
    //   85: lload 5
    //   87: lload 7
    //   89: getstatic 21	ro/btrl/enrollment/di/module/EnrollmentModule:ˊ	J
    //   92: lmul
    //   93: lxor
    //   94: iload_1
    //   95: i2l
    //   96: lxor
    //   97: l2i
    //   98: i2c
    //   99: castore
    //   100: iload_3
    //   101: iconst_1
    //   102: iadd
    //   103: istore_3
    //   104: goto +10 -> 114
    //   107: bipush 12
    //   109: istore 4
    //   111: goto -105 -> 6
    //   114: iload_3
    //   115: iload_2
    //   116: if_icmpge +6 -> 122
    //   119: goto +174 -> 293
    //   122: goto -15 -> 107
    //   125: getstatic 17	ro/btrl/enrollment/di/module/EnrollmentModule:ˎ	I
    //   128: bipush 25
    //   130: iadd
    //   131: istore 4
    //   133: iload 4
    //   135: sipush 128
    //   138: irem
    //   139: putstatic 15	ro/btrl/enrollment/di/module/EnrollmentModule:ॱ	I
    //   142: iload 4
    //   144: iconst_2
    //   145: irem
    //   146: ifeq +6 -> 152
    //   149: goto +38 -> 187
    //   152: goto +148 -> 300
    //   155: aload 9
    //   157: iload_3
    //   158: getstatic 37	ro/btrl/enrollment/di/module/EnrollmentModule:ˏ	[C
    //   161: iload_0
    //   162: iload_3
    //   163: idiv
    //   164: caload
    //   165: i2l
    //   166: iload_3
    //   167: i2l
    //   168: getstatic 21	ro/btrl/enrollment/di/module/EnrollmentModule:ˊ	J
    //   171: lrem
    //   172: land
    //   173: iload_1
    //   174: i2l
    //   175: lor
    //   176: l2i
    //   177: i2c
    //   178: castore
    //   179: iload_3
    //   180: bipush 127
    //   182: iadd
    //   183: istore_3
    //   184: goto -70 -> 114
    //   187: iconst_2
    //   188: istore 4
    //   190: goto +41 -> 231
    //   193: goto -139 -> 54
    //   196: goto -193 -> 3
    //   199: astore 9
    //   201: aload 9
    //   203: athrow
    //   204: getstatic 15	ro/btrl/enrollment/di/module/EnrollmentModule:ॱ	I
    //   207: bipush 99
    //   209: iadd
    //   210: istore_3
    //   211: iload_3
    //   212: sipush 128
    //   215: irem
    //   216: putstatic 17	ro/btrl/enrollment/di/module/EnrollmentModule:ˎ	I
    //   219: iload_3
    //   220: iconst_2
    //   221: irem
    //   222: ifne +6 -> 228
    //   225: goto -32 -> 193
    //   228: goto -174 -> 54
    //   231: iload 4
    //   233: lookupswitch	default:+27->260, 2:+-78->155, 66:+-169->64
    //   260: goto -105 -> 155
    //   263: getstatic 17	ro/btrl/enrollment/di/module/EnrollmentModule:ˎ	I
    //   266: bipush 89
    //   268: iadd
    //   269: istore 4
    //   271: iload 4
    //   273: sipush 128
    //   276: irem
    //   277: putstatic 15	ro/btrl/enrollment/di/module/EnrollmentModule:ॱ	I
    //   280: iload 4
    //   282: iconst_2
    //   283: irem
    //   284: ifeq +6 -> 290
    //   287: goto -91 -> 196
    //   290: goto -287 -> 3
    //   293: bipush 23
    //   295: istore 4
    //   297: goto -291 -> 6
    //   300: bipush 66
    //   302: istore 4
    //   304: goto -73 -> 231
    // Local variable table:
    //   start	length	slot	name	signature
    //   0	307	0	paramInt1	int
    //   0	307	1	paramChar	char
    //   0	307	2	paramInt2	int
    //   60	162	3	i	int
    //   6	297	4	j	int
    //   76	10	5	l1	long
    //   80	8	7	l2	long
    //   40	1	9	arrayOfChar1	char[]
    //   46	3	9	localException1	Exception
    //   57	99	9	arrayOfChar2	char[]
    //   199	3	9	localException2	Exception
    //   67	3	10	arrayOfChar3	char[]
    // Exception table:
    //   from	to	target	type
    //   82	100	46	java/lang/Exception
    //   204	211	46	java/lang/Exception
    //   211	219	46	java/lang/Exception
    //   64	69	199	java/lang/Exception
  }
  
  /* Error */
  public final o.KO.iF ˏ(o.KO.ˋ paramˋ, o.Kk paramKk)
  {
    // Byte code:
    //   0: goto +87 -> 87
    //   3: astore_1
    //   4: aload_1
    //   5: athrow
    //   6: astore_1
    //   7: aload_1
    //   8: athrow
    //   9: getstatic 15	ro/btrl/enrollment/di/module/EnrollmentModule:ॱ	I
    //   12: bipush 125
    //   14: iadd
    //   15: istore_3
    //   16: iload_3
    //   17: sipush 128
    //   20: irem
    //   21: putstatic 17	ro/btrl/enrollment/di/module/EnrollmentModule:ˎ	I
    //   24: iload_3
    //   25: iconst_2
    //   26: irem
    //   27: ifne +5 -> 32
    //   30: aload_1
    //   31: areturn
    //   32: aload_1
    //   33: areturn
    //   34: iconst_0
    //   35: ldc 51
    //   37: iconst_4
    //   38: invokestatic 53	ro/btrl/enrollment/di/module/EnrollmentModule:ˏ	(ICI)Ljava/lang/String;
    //   41: astore 4
    //   43: aload 4
    //   45: invokevirtual 57	java/lang/String:intern	()Ljava/lang/String;
    //   48: astore 4
    //   50: aload_1
    //   51: aload 4
    //   53: invokestatic 62	o/vq:ˎ	(Ljava/lang/Object;Ljava/lang/String;)V
    //   56: aload_2
    //   57: iconst_4
    //   58: ldc 63
    //   60: bipush 10
    //   62: invokestatic 53	ro/btrl/enrollment/di/module/EnrollmentModule:ˏ	(ICI)Ljava/lang/String;
    //   65: invokevirtual 57	java/lang/String:intern	()Ljava/lang/String;
    //   68: invokestatic 62	o/vq:ˎ	(Ljava/lang/Object;Ljava/lang/String;)V
    //   71: new 65	o/KS
    //   74: dup
    //   75: aload_1
    //   76: aload_2
    //   77: invokespecial 68	o/KS:<init>	(Lo/KO$ˋ;Lo/Kk;)V
    //   80: checkcast 70	o/KO$iF
    //   83: astore_1
    //   84: goto -75 -> 9
    //   87: goto -53 -> 34
    // Local variable table:
    //   start	length	slot	name	signature
    //   0	90	0	this	EnrollmentModule
    //   0	90	1	paramˋ	o.KO.ˋ
    //   0	90	2	paramKk	o.Kk
    //   15	12	3	i	int
    //   41	11	4	str	String
    // Exception table:
    //   from	to	target	type
    //   34	43	3	java/lang/Exception
    //   43	50	3	java/lang/Exception
    //   50	56	3	java/lang/Exception
    //   56	84	3	java/lang/Exception
    //   34	43	6	java/lang/Exception
  }
}
