package com.mobile.ui.globalmenu.fragment;

import kkkkkk.eeuuuu;
import kkkkkk.euuuuu;

public class GlobalMenuFragment
  extends BaseGlobalMenuFragment<euuuuu, eeuuuu>
  implements euuuuu
{
  public static int b043104310431б0431б0431б = 22;
  public static int b0431б0431б0431б0431б = 1;
  public static int bб04310431б0431б0431б = 2;
  
  public GlobalMenuFragment() {}
  
  public static int b04310431бб0431б0431б()
  {
    return 35;
  }
  
  public static int bбб0431б0431б0431б()
  {
    return 0;
  }
  
  /* Error */
  public void onCreate(@android.support.annotation.Nullable android.os.Bundle paramBundle)
  {
    // Byte code:
    //   0: aload_0
    //   1: aload_1
    //   2: invokespecial 29	com/mobile/ui/globalmenu/fragment/BaseGlobalMenuFragment:onCreate	(Landroid/os/Bundle;)V
    //   5: invokestatic 35	com/mobile/ui/App:get	()Lcom/mobile/ui/App;
    //   8: astore_1
    //   9: invokestatic 37	com/mobile/ui/globalmenu/fragment/GlobalMenuFragment:b04310431бб0431б0431б	()I
    //   12: istore_2
    //   13: getstatic 39	com/mobile/ui/globalmenu/fragment/GlobalMenuFragment:b0431б0431б0431б0431б	I
    //   16: istore_3
    //   17: invokestatic 37	com/mobile/ui/globalmenu/fragment/GlobalMenuFragment:b04310431бб0431б0431б	()I
    //   20: istore 4
    //   22: getstatic 41	com/mobile/ui/globalmenu/fragment/GlobalMenuFragment:bб04310431б0431б0431б	I
    //   25: istore 5
    //   27: invokestatic 43	com/mobile/ui/globalmenu/fragment/GlobalMenuFragment:bбб0431б0431б0431б	()I
    //   30: istore 6
    //   32: iload_2
    //   33: iload_3
    //   34: iadd
    //   35: iload 4
    //   37: imul
    //   38: iload 5
    //   40: irem
    //   41: iload 6
    //   43: if_icmpeq +56 -> 99
    //   46: getstatic 45	com/mobile/ui/globalmenu/fragment/GlobalMenuFragment:b043104310431б0431б0431б	I
    //   49: istore_2
    //   50: iload_2
    //   51: getstatic 39	com/mobile/ui/globalmenu/fragment/GlobalMenuFragment:b0431б0431б0431б0431б	I
    //   54: iload_2
    //   55: iadd
    //   56: imul
    //   57: getstatic 41	com/mobile/ui/globalmenu/fragment/GlobalMenuFragment:bб04310431б0431б0431б	I
    //   60: irem
    //   61: tableswitch	default:+19->80, 0:+30->91
    //   80: bipush 95
    //   82: putstatic 45	com/mobile/ui/globalmenu/fragment/GlobalMenuFragment:b043104310431б0431б0431б	I
    //   85: invokestatic 37	com/mobile/ui/globalmenu/fragment/GlobalMenuFragment:b04310431бб0431б0431б	()I
    //   88: putstatic 39	com/mobile/ui/globalmenu/fragment/GlobalMenuFragment:b0431б0431б0431б0431б	I
    //   91: invokestatic 37	com/mobile/ui/globalmenu/fragment/GlobalMenuFragment:b04310431бб0431б0431б	()I
    //   94: istore_2
    //   95: iload_2
    //   96: putstatic 39	com/mobile/ui/globalmenu/fragment/GlobalMenuFragment:b0431б0431б0431б0431б	I
    //   99: aload_1
    //   100: invokevirtual 49	com/mobile/ui/App:getAppComponent	()Lkkkkkk/uyyyyy;
    //   103: aload_0
    //   104: invokeinterface 55 2 0
    //   109: return
    //   110: astore_1
    //   111: aload_1
    //   112: athrow
    //   113: astore_1
    //   114: aload_1
    //   115: athrow
    // Local variable table:
    //   start	length	slot	name	signature
    //   0	116	0	this	GlobalMenuFragment
    //   0	116	1	paramBundle	android.os.Bundle
    //   12	84	2	i	int
    //   16	19	3	j	int
    //   20	18	4	k	int
    //   25	16	5	m	int
    //   30	14	6	n	int
    // Exception table:
    //   from	to	target	type
    //   5	9	110	java/lang/Exception
    //   17	32	110	java/lang/Exception
    //   95	99	110	java/lang/Exception
    //   99	109	110	java/lang/Exception
    //   0	5	113	java/lang/Exception
    //   9	17	113	java/lang/Exception
    //   91	95	113	java/lang/Exception
  }
}
