package android.support.v7.app;

import android.content.Context;
import android.content.ContextWrapper;
import android.content.res.Resources;
import android.content.res.TypedArray;
import android.os.Build.VERSION;
import android.support.v4.util.ArrayMap;
import android.support.v4.view.ai;
import android.support.v7.a.a.j;
import android.support.v7.view.d;
import android.support.v7.widget.aa;
import android.support.v7.widget.bb;
import android.support.v7.widget.f;
import android.support.v7.widget.h;
import android.support.v7.widget.i;
import android.support.v7.widget.j;
import android.support.v7.widget.m;
import android.support.v7.widget.p;
import android.support.v7.widget.q;
import android.support.v7.widget.t;
import android.support.v7.widget.u;
import android.support.v7.widget.v;
import android.support.v7.widget.x;
import android.util.AttributeSet;
import android.util.Log;
import android.view.View;
import android.view.View.OnClickListener;
import java.lang.reflect.Constructor;
import java.lang.reflect.InvocationTargetException;
import java.lang.reflect.Method;
import java.util.Map;

class n
{
  private static final Class<?>[] a = { Context.class, AttributeSet.class };
  private static final int[] b = { 16843375 };
  private static final String[] c = { "android.widget.", "android.view.", "android.webkit." };
  private static final Map<String, Constructor<? extends View>> d = new ArrayMap();
  private final Object[] e = new Object[2];
  
  n() {}
  
  private static Context a(Context paramContext, AttributeSet paramAttributeSet, boolean paramBoolean1, boolean paramBoolean2)
  {
    paramAttributeSet = paramContext.obtainStyledAttributes(paramAttributeSet, a.j.View, 0, 0);
    if (paramBoolean1) {}
    for (int i = paramAttributeSet.getResourceId(a.j.View_android_theme, 0);; i = 0)
    {
      int j = i;
      if (paramBoolean2)
      {
        j = i;
        if (i == 0)
        {
          i = paramAttributeSet.getResourceId(a.j.View_theme, 0);
          j = i;
          if (i != 0)
          {
            Log.i("AppCompatViewInflater", "app:theme is now deprecated. Please move to using android:theme instead.");
            j = i;
          }
        }
      }
      paramAttributeSet.recycle();
      paramAttributeSet = paramContext;
      if (j != 0) {
        if ((paramContext instanceof d))
        {
          paramAttributeSet = paramContext;
          if (((d)paramContext).a() == j) {}
        }
        else
        {
          paramAttributeSet = new d(paramContext, j);
        }
      }
      return paramAttributeSet;
    }
  }
  
  /* Error */
  private View a(Context paramContext, String paramString, AttributeSet paramAttributeSet)
  {
    // Byte code:
    //   0: aload_2
    //   1: astore 5
    //   3: aload_2
    //   4: ldc 101
    //   6: invokevirtual 105	java/lang/String:equals	(Ljava/lang/Object;)Z
    //   9: ifeq +14 -> 23
    //   12: aload_3
    //   13: aconst_null
    //   14: ldc 107
    //   16: invokeinterface 111 3 0
    //   21: astore 5
    //   23: aload_0
    //   24: getfield 52	android/support/v7/app/n:e	[Ljava/lang/Object;
    //   27: iconst_0
    //   28: aload_1
    //   29: aastore
    //   30: aload_0
    //   31: getfield 52	android/support/v7/app/n:e	[Ljava/lang/Object;
    //   34: iconst_1
    //   35: aload_3
    //   36: aastore
    //   37: iconst_m1
    //   38: aload 5
    //   40: bipush 46
    //   42: invokevirtual 115	java/lang/String:indexOf	(I)I
    //   45: if_icmpne +74 -> 119
    //   48: iconst_0
    //   49: istore 4
    //   51: iload 4
    //   53: getstatic 41	android/support/v7/app/n:c	[Ljava/lang/String;
    //   56: arraylength
    //   57: if_icmpge +46 -> 103
    //   60: aload_0
    //   61: aload_1
    //   62: aload 5
    //   64: getstatic 41	android/support/v7/app/n:c	[Ljava/lang/String;
    //   67: iload 4
    //   69: aaload
    //   70: invokespecial 118	android/support/v7/app/n:a	(Landroid/content/Context;Ljava/lang/String;Ljava/lang/String;)Landroid/view/View;
    //   73: astore_2
    //   74: aload_2
    //   75: ifnull +19 -> 94
    //   78: aload_0
    //   79: getfield 52	android/support/v7/app/n:e	[Ljava/lang/Object;
    //   82: iconst_0
    //   83: aconst_null
    //   84: aastore
    //   85: aload_0
    //   86: getfield 52	android/support/v7/app/n:e	[Ljava/lang/Object;
    //   89: iconst_1
    //   90: aconst_null
    //   91: aastore
    //   92: aload_2
    //   93: areturn
    //   94: iload 4
    //   96: iconst_1
    //   97: iadd
    //   98: istore 4
    //   100: goto -49 -> 51
    //   103: aload_0
    //   104: getfield 52	android/support/v7/app/n:e	[Ljava/lang/Object;
    //   107: iconst_0
    //   108: aconst_null
    //   109: aastore
    //   110: aload_0
    //   111: getfield 52	android/support/v7/app/n:e	[Ljava/lang/Object;
    //   114: iconst_1
    //   115: aconst_null
    //   116: aastore
    //   117: aconst_null
    //   118: areturn
    //   119: aload_0
    //   120: aload_1
    //   121: aload 5
    //   123: aconst_null
    //   124: invokespecial 118	android/support/v7/app/n:a	(Landroid/content/Context;Ljava/lang/String;Ljava/lang/String;)Landroid/view/View;
    //   127: astore_1
    //   128: aload_0
    //   129: getfield 52	android/support/v7/app/n:e	[Ljava/lang/Object;
    //   132: iconst_0
    //   133: aconst_null
    //   134: aastore
    //   135: aload_0
    //   136: getfield 52	android/support/v7/app/n:e	[Ljava/lang/Object;
    //   139: iconst_1
    //   140: aconst_null
    //   141: aastore
    //   142: aload_1
    //   143: areturn
    //   144: astore_1
    //   145: aload_0
    //   146: getfield 52	android/support/v7/app/n:e	[Ljava/lang/Object;
    //   149: iconst_0
    //   150: aconst_null
    //   151: aastore
    //   152: aload_0
    //   153: getfield 52	android/support/v7/app/n:e	[Ljava/lang/Object;
    //   156: iconst_1
    //   157: aconst_null
    //   158: aastore
    //   159: aconst_null
    //   160: areturn
    //   161: astore_1
    //   162: aload_0
    //   163: getfield 52	android/support/v7/app/n:e	[Ljava/lang/Object;
    //   166: iconst_0
    //   167: aconst_null
    //   168: aastore
    //   169: aload_0
    //   170: getfield 52	android/support/v7/app/n:e	[Ljava/lang/Object;
    //   173: iconst_1
    //   174: aconst_null
    //   175: aastore
    //   176: aload_1
    //   177: athrow
    // Local variable table:
    //   start	length	slot	name	signature
    //   0	178	0	this	n
    //   0	178	1	paramContext	Context
    //   0	178	2	paramString	String
    //   0	178	3	paramAttributeSet	AttributeSet
    //   49	50	4	i	int
    //   1	121	5	str	String
    // Exception table:
    //   from	to	target	type
    //   23	48	144	java/lang/Exception
    //   51	74	144	java/lang/Exception
    //   119	128	144	java/lang/Exception
    //   23	48	161	finally
    //   51	74	161	finally
    //   119	128	161	finally
  }
  
  private View a(Context paramContext, String paramString1, String paramString2)
  {
    Constructor localConstructor = (Constructor)d.get(paramString1);
    Object localObject = localConstructor;
    if (localConstructor == null) {}
    try
    {
      localObject = paramContext.getClassLoader();
      if (paramString2 != null) {}
      for (paramContext = paramString2 + paramString1;; paramContext = paramString1)
      {
        localObject = ((ClassLoader)localObject).loadClass(paramContext).asSubclass(View.class).getConstructor(a);
        d.put(paramString1, localObject);
        ((Constructor)localObject).setAccessible(true);
        paramContext = (View)((Constructor)localObject).newInstance(this.e);
        return paramContext;
      }
      return null;
    }
    catch (Exception paramContext) {}
  }
  
  private void a(View paramView, AttributeSet paramAttributeSet)
  {
    Object localObject = paramView.getContext();
    if ((!(localObject instanceof ContextWrapper)) || ((Build.VERSION.SDK_INT >= 15) && (!ai.G(paramView)))) {
      return;
    }
    paramAttributeSet = ((Context)localObject).obtainStyledAttributes(paramAttributeSet, b);
    localObject = paramAttributeSet.getString(0);
    if (localObject != null) {
      paramView.setOnClickListener(new a(paramView, (String)localObject));
    }
    paramAttributeSet.recycle();
  }
  
  public final View a(View paramView, String paramString, Context paramContext, AttributeSet paramAttributeSet, boolean paramBoolean1, boolean paramBoolean2, boolean paramBoolean3, boolean paramBoolean4)
  {
    if ((paramBoolean1) && (paramView != null)) {}
    for (Object localObject = paramView.getContext();; localObject = paramContext)
    {
      if (!paramBoolean2)
      {
        paramView = (View)localObject;
        if (!paramBoolean3) {}
      }
      else
      {
        paramView = a((Context)localObject, paramAttributeSet, paramBoolean2, paramBoolean3);
      }
      localObject = paramView;
      if (paramBoolean4) {
        localObject = bb.a(paramView);
      }
      paramView = null;
      int i = -1;
      switch (paramString.hashCode())
      {
      default: 
        switch (i)
        {
        default: 
          label244:
          if ((paramView == null) && (paramContext != localObject)) {
            paramView = a((Context)localObject, paramString, paramAttributeSet);
          }
          break;
        }
        break;
      }
      for (;;)
      {
        if (paramView != null) {
          a(paramView, paramAttributeSet);
        }
        return paramView;
        if (!paramString.equals("TextView")) {
          break;
        }
        i = 0;
        break;
        if (!paramString.equals("ImageView")) {
          break;
        }
        i = 1;
        break;
        if (!paramString.equals("Button")) {
          break;
        }
        i = 2;
        break;
        if (!paramString.equals("EditText")) {
          break;
        }
        i = 3;
        break;
        if (!paramString.equals("Spinner")) {
          break;
        }
        i = 4;
        break;
        if (!paramString.equals("ImageButton")) {
          break;
        }
        i = 5;
        break;
        if (!paramString.equals("CheckBox")) {
          break;
        }
        i = 6;
        break;
        if (!paramString.equals("RadioButton")) {
          break;
        }
        i = 7;
        break;
        if (!paramString.equals("CheckedTextView")) {
          break;
        }
        i = 8;
        break;
        if (!paramString.equals("AutoCompleteTextView")) {
          break;
        }
        i = 9;
        break;
        if (!paramString.equals("MultiAutoCompleteTextView")) {
          break;
        }
        i = 10;
        break;
        if (!paramString.equals("RatingBar")) {
          break;
        }
        i = 11;
        break;
        if (!paramString.equals("SeekBar")) {
          break;
        }
        i = 12;
        break;
        paramView = new aa((Context)localObject, paramAttributeSet);
        break label244;
        paramView = new p((Context)localObject, paramAttributeSet);
        break label244;
        paramView = new h((Context)localObject, paramAttributeSet);
        break label244;
        paramView = new m((Context)localObject, paramAttributeSet);
        break label244;
        paramView = new x((Context)localObject, paramAttributeSet);
        break label244;
        paramView = new android.support.v7.widget.n((Context)localObject, paramAttributeSet);
        break label244;
        paramView = new i((Context)localObject, paramAttributeSet);
        break label244;
        paramView = new t((Context)localObject, paramAttributeSet);
        break label244;
        paramView = new j((Context)localObject, paramAttributeSet);
        break label244;
        paramView = new f((Context)localObject, paramAttributeSet);
        break label244;
        paramView = new q((Context)localObject, paramAttributeSet);
        break label244;
        paramView = new u((Context)localObject, paramAttributeSet);
        break label244;
        paramView = new v((Context)localObject, paramAttributeSet);
        break label244;
      }
    }
  }
  
  private static class a
    implements View.OnClickListener
  {
    private final View a;
    private final String b;
    private Method c;
    private Context d;
    
    public a(View paramView, String paramString)
    {
      this.a = paramView;
      this.b = paramString;
    }
    
    private void a(Context paramContext, String paramString)
    {
      while (paramContext != null) {
        try
        {
          if (!paramContext.isRestricted())
          {
            paramString = paramContext.getClass().getMethod(this.b, new Class[] { View.class });
            if (paramString != null)
            {
              this.c = paramString;
              this.d = paramContext;
              return;
            }
          }
        }
        catch (NoSuchMethodException paramString)
        {
          if ((paramContext instanceof ContextWrapper)) {
            paramContext = ((ContextWrapper)paramContext).getBaseContext();
          } else {
            paramContext = null;
          }
        }
      }
      int i = this.a.getId();
      if (i == -1) {}
      for (paramContext = "";; paramContext = " with id '" + this.a.getContext().getResources().getResourceEntryName(i) + "'") {
        throw new IllegalStateException("Could not find method " + this.b + "(View) in a parent or ancestor Context for android:onClick " + "attribute defined on view " + this.a.getClass() + paramContext);
      }
    }
    
    public void onClick(View paramView)
    {
      if (this.c == null) {
        a(this.a.getContext(), this.b);
      }
      try
      {
        this.c.invoke(this.d, new Object[] { paramView });
        return;
      }
      catch (IllegalAccessException paramView)
      {
        throw new IllegalStateException("Could not execute non-public method for android:onClick", paramView);
      }
      catch (InvocationTargetException paramView)
      {
        throw new IllegalStateException("Could not execute method for android:onClick", paramView);
      }
    }
  }
}
