package com.mobile.ui.settings.activity;

import android.content.Context;
import android.content.Intent;
import android.os.Bundle;
import android.support.v4.app.Fragment;
import com.mobile.ui.settings.fragment.DarkUrlFragment;
import java.util.Map;
import kkkkkk.gguuuu;

public class DarkUrlSettingsActivity
  extends SettingsActivity
{
  private static final String EXTRA_TARGET_SCREEN = "\020$! \020/%\023%\033\032*6+\034, !+";
  public static int b04250425ХХХ0425ХХХ = 2;
  public static int b0425ХХХХ0425ХХХ = 4;
  public static int bХ0425ХХХ0425ХХХ = 1;
  public static int bХХ0425ХХ0425ХХХ;
  
  static
  {
    throw new Runtime("d2j fail translate: java.lang.IndexOutOfBoundsException: fromIndex < 0: -1\n\tat java.util.BitSet.nextSetBit(BitSet.java:712)\n\tat com.googlecode.dex2jar.ir.ts.array.FillArrayTransformer.makeSureAllElementAreAssigned(FillArrayTransformer.java:505)\n\tat com.googlecode.dex2jar.ir.ts.array.FillArrayTransformer.transformReportChanged(FillArrayTransformer.java:123)\n\tat com.googlecode.dex2jar.ir.ts.StatedTransformer.transform(StatedTransformer.java:10)\n\tat com.googlecode.d2j.dex.Dex2jar$2.optimize(Dex2jar.java:149)\n\tat com.googlecode.d2j.dex.Dex2Asm.convertCode(Dex2Asm.java:414)\n\tat com.googlecode.d2j.dex.ExDex2Asm.convertCode(ExDex2Asm.java:42)\n\tat com.googlecode.d2j.dex.Dex2jar$2.convertCode(Dex2jar.java:128)\n\tat com.googlecode.d2j.dex.Dex2Asm.convertMethod(Dex2Asm.java:509)\n\tat com.googlecode.d2j.dex.Dex2Asm.convertClass(Dex2Asm.java:406)\n\tat com.googlecode.d2j.dex.Dex2Asm.convertDex(Dex2Asm.java:422)\n\tat com.googlecode.d2j.dex.Dex2jar.doTranslate(Dex2jar.java:172)\n\tat com.googlecode.d2j.dex.Dex2jar.to(Dex2jar.java:272)\n\tat com.googlecode.dex2jar.tools.Dex2jarCmd.doCommandLine(Dex2jarCmd.java:108)\n\tat com.googlecode.dex2jar.tools.BaseCmd.doMain(BaseCmd.java:288)\n\tat com.googlecode.dex2jar.tools.Dex2jarCmd.main(Dex2jarCmd.java:32)\n");
  }
  
  public DarkUrlSettingsActivity() {}
  
  public static int b042504250425ХХ0425ХХХ()
  {
    return 90;
  }
  
  public static int b0425Х0425ХХ0425ХХХ()
  {
    return 2;
  }
  
  public static int bХ04250425ХХ0425ХХХ()
  {
    return 1;
  }
  
  public static int bХХХ0425Х0425ХХХ()
  {
    return 0;
  }
  
  public static Intent getIntent(Context paramContext)
  {
    int i = b0425ХХХХ0425ХХХ;
    if ((b0425ХХХХ0425ХХХ + bХ0425ХХХ0425ХХХ) * b0425ХХХХ0425ХХХ % b0425Х0425ХХ0425ХХХ() != bХХ0425ХХ0425ХХХ)
    {
      b0425ХХХХ0425ХХХ = 24;
      bХХ0425ХХ0425ХХХ = 60;
    }
    switch (i * (bХ0425ХХХ0425ХХХ + i) % b04250425ХХХ0425ХХХ)
    {
    default: 
      switch (0)
      {
      case 1: 
      default: 
        for (;;)
        {
          switch (0)
          {
          }
        }
      }
      b0425ХХХХ0425ХХХ = 26;
      bХ0425ХХХ0425ХХХ = 2;
    }
    return new Intent(paramContext, DarkUrlSettingsActivity.class);
  }
  
  public static Intent getIntentForWebView(Context paramContext)
  {
    paramContext = new Intent(paramContext, DarkUrlSettingsActivity.class);
    switch (1)
    {
    case 0: 
    default: 
      for (;;)
      {
        switch (0)
        {
        }
      }
    }
    if ((b0425ХХХХ0425ХХХ + bХ04250425ХХ0425ХХХ()) * b0425ХХХХ0425ХХХ % b04250425ХХХ0425ХХХ != bХХ0425ХХ0425ХХХ)
    {
      if ((b0425ХХХХ0425ХХХ + bХ0425ХХХ0425ХХХ) * b0425ХХХХ0425ХХХ % b04250425ХХХ0425ХХХ != bХХ0425ХХ0425ХХХ)
      {
        b0425ХХХХ0425ХХХ = b042504250425ХХ0425ХХХ();
        bХХ0425ХХ0425ХХХ = b042504250425ХХ0425ХХХ();
      }
      b0425ХХХХ0425ХХХ = b042504250425ХХ0425ХХХ();
      bХХ0425ХХ0425ХХХ = b042504250425ХХ0425ХХХ();
    }
    paramContext.putExtra(gguuuu.bк043Aккк043Aкк043A043A("';87'F<*<21AMB3C78B", 'x', '\027', '\001'), true);
    return paramContext;
  }
  
  public Map<String, Bundle> getDeepLinkMap(Context paramContext)
  {
    if ((b0425ХХХХ0425ХХХ + bХ0425ХХХ0425ХХХ) * b0425ХХХХ0425ХХХ % b04250425ХХХ0425ХХХ != bХХ0425ХХ0425ХХХ)
    {
      switch (0)
      {
      case 1: 
      default: 
        for (;;)
        {
          switch (0)
          {
          }
        }
      }
      b0425ХХХХ0425ХХХ = b042504250425ХХ0425ХХХ();
      bХХ0425ХХ0425ХХХ = b042504250425ХХ0425ХХХ();
      if ((b0425ХХХХ0425ХХХ + bХ0425ХХХ0425ХХХ) * b0425ХХХХ0425ХХХ % b04250425ХХХ0425ХХХ != bХХ0425ХХ0425ХХХ)
      {
        b0425ХХХХ0425ХХХ = 89;
        bХХ0425ХХ0425ХХХ = b042504250425ХХ0425ХХХ();
      }
    }
    paramContext = NOT_LINKABLE_MAP;
    switch (0)
    {
    case 1: 
    default: 
      for (;;)
      {
        switch (1)
        {
        }
      }
    }
    return paramContext;
  }
  
  public Fragment getFragment()
  {
    DarkUrlFragment localDarkUrlFragment = DarkUrlFragment.newInstance();
    int i = b0425ХХХХ0425ХХХ;
    switch (i * (bХ0425ХХХ0425ХХХ + i) % b04250425ХХХ0425ХХХ)
    {
    default: 
      b0425ХХХХ0425ХХХ = 20;
      bХХ0425ХХ0425ХХХ = b042504250425ХХ0425ХХХ();
    }
    return localDarkUrlFragment;
  }
  
  /* Error */
  public void onCreate(Bundle paramBundle)
  {
    // Byte code:
    //   0: invokestatic 58	com/mobile/ui/settings/activity/DarkUrlSettingsActivity:b042504250425ХХ0425ХХХ	()I
    //   3: istore_2
    //   4: invokestatic 56	com/mobile/ui/settings/activity/DarkUrlSettingsActivity:bХ04250425ХХ0425ХХХ	()I
    //   7: istore_3
    //   8: invokestatic 58	com/mobile/ui/settings/activity/DarkUrlSettingsActivity:b042504250425ХХ0425ХХХ	()I
    //   11: istore 4
    //   13: getstatic 48	com/mobile/ui/settings/activity/DarkUrlSettingsActivity:b04250425ХХХ0425ХХХ	I
    //   16: istore 5
    //   18: iconst_0
    //   19: tableswitch	default:+21->40, 0:+48->67, 1:+-1->18
    //   40: iconst_1
    //   41: tableswitch	default:+23->64, 0:+-23->18, 1:+26->67
    //   64: goto -24 -> 40
    //   67: iload_2
    //   68: iload_3
    //   69: iadd
    //   70: iload 4
    //   72: imul
    //   73: iload 5
    //   75: irem
    //   76: getstatic 46	com/mobile/ui/settings/activity/DarkUrlSettingsActivity:bХХ0425ХХ0425ХХХ	I
    //   79: if_icmpeq +58 -> 137
    //   82: getstatic 40	com/mobile/ui/settings/activity/DarkUrlSettingsActivity:b0425ХХХХ0425ХХХ	I
    //   85: istore_2
    //   86: iload_2
    //   87: getstatic 42	com/mobile/ui/settings/activity/DarkUrlSettingsActivity:bХ0425ХХХ0425ХХХ	I
    //   90: iload_2
    //   91: iadd
    //   92: imul
    //   93: getstatic 48	com/mobile/ui/settings/activity/DarkUrlSettingsActivity:b04250425ХХХ0425ХХХ	I
    //   96: irem
    //   97: tableswitch	default:+19->116, 0:+29->126
    //   116: bipush 78
    //   118: putstatic 40	com/mobile/ui/settings/activity/DarkUrlSettingsActivity:b0425ХХХХ0425ХХХ	I
    //   121: bipush 62
    //   123: putstatic 46	com/mobile/ui/settings/activity/DarkUrlSettingsActivity:bХХ0425ХХ0425ХХХ	I
    //   126: bipush 34
    //   128: putstatic 40	com/mobile/ui/settings/activity/DarkUrlSettingsActivity:b0425ХХХХ0425ХХХ	I
    //   131: invokestatic 58	com/mobile/ui/settings/activity/DarkUrlSettingsActivity:b042504250425ХХ0425ХХХ	()I
    //   134: putstatic 46	com/mobile/ui/settings/activity/DarkUrlSettingsActivity:bХХ0425ХХ0425ХХХ	I
    //   137: aload_0
    //   138: invokevirtual 94	com/mobile/ui/settings/activity/DarkUrlSettingsActivity:getApplicationContext	()Landroid/content/Context;
    //   141: invokestatic 100	kkkkkk/nkkkkk:bЗЗ0417З0417З0417041704170417	(Landroid/content/Context;)V
    //   144: aload_0
    //   145: invokevirtual 94	com/mobile/ui/settings/activity/DarkUrlSettingsActivity:getApplicationContext	()Landroid/content/Context;
    //   148: astore 6
    //   150: aload 6
    //   152: invokestatic 105	kkkkkk/nnnkkk:bхх0445ххххххх	(Landroid/content/Context;)V
    //   155: aload_0
    //   156: invokevirtual 94	com/mobile/ui/settings/activity/DarkUrlSettingsActivity:getApplicationContext	()Landroid/content/Context;
    //   159: invokestatic 110	kkkkkk/nknnkk:bх0445ххх04450445ххх	(Landroid/content/Context;)V
    //   162: aload_0
    //   163: aload_1
    //   164: invokespecial 112	com/mobile/ui/settings/activity/SettingsActivity:onCreate	(Landroid/os/Bundle;)V
    //   167: return
    //   168: astore_1
    //   169: aload_1
    //   170: athrow
    //   171: astore_1
    //   172: aload_1
    //   173: athrow
    // Local variable table:
    //   start	length	slot	name	signature
    //   0	174	0	this	DarkUrlSettingsActivity
    //   0	174	1	paramBundle	Bundle
    //   3	90	2	i	int
    //   7	63	3	j	int
    //   11	62	4	k	int
    //   16	60	5	m	int
    //   148	3	6	localContext	Context
    // Exception table:
    //   from	to	target	type
    //   137	144	168	java/lang/Exception
    //   150	162	168	java/lang/Exception
    //   144	150	171	java/lang/Exception
    //   162	167	171	java/lang/Exception
  }
}
