package com.mobile.ui.settings.activity;

import android.content.Context;
import android.os.Bundle;
import java.util.Map;
import kkkkkk.nkkkkk;
import kkkkkk.nknnkk;
import kkkkkk.nnnkkk;

public class RealTimeAlertsSettingsActivity
  extends SettingsActivity
{
  public static int b04250425Х0425ХХ0425ХХ = 2;
  public static int b0425Х04250425ХХ0425ХХ = 0;
  public static int b0425ХХ0425ХХ0425ХХ = 53;
  public static int bХ0425Х0425ХХ0425ХХ = 1;
  
  public RealTimeAlertsSettingsActivity() {}
  
  public static int bХ042504250425ХХ0425ХХ()
  {
    return 2;
  }
  
  public static int bХХ04250425ХХ0425ХХ()
  {
    return 72;
  }
  
  /* Error */
  public static android.content.Intent getIntent(Context paramContext)
  {
    // Byte code:
    //   0: getstatic 27	com/mobile/ui/settings/activity/RealTimeAlertsSettingsActivity:b0425ХХ0425ХХ0425ХХ	I
    //   3: istore_1
    //   4: getstatic 29	com/mobile/ui/settings/activity/RealTimeAlertsSettingsActivity:bХ0425Х0425ХХ0425ХХ	I
    //   7: istore_2
    //   8: getstatic 31	com/mobile/ui/settings/activity/RealTimeAlertsSettingsActivity:b04250425Х0425ХХ0425ХХ	I
    //   11: istore_3
    //   12: iload_1
    //   13: iload_2
    //   14: iload_1
    //   15: iadd
    //   16: imul
    //   17: iload_3
    //   18: irem
    //   19: tableswitch	default:+17->36, 0:+62->81
    //   36: invokestatic 33	com/mobile/ui/settings/activity/RealTimeAlertsSettingsActivity:bХХ04250425ХХ0425ХХ	()I
    //   39: putstatic 27	com/mobile/ui/settings/activity/RealTimeAlertsSettingsActivity:b0425ХХ0425ХХ0425ХХ	I
    //   42: invokestatic 33	com/mobile/ui/settings/activity/RealTimeAlertsSettingsActivity:bХХ04250425ХХ0425ХХ	()I
    //   45: putstatic 29	com/mobile/ui/settings/activity/RealTimeAlertsSettingsActivity:bХ0425Х0425ХХ0425ХХ	I
    //   48: invokestatic 33	com/mobile/ui/settings/activity/RealTimeAlertsSettingsActivity:bХХ04250425ХХ0425ХХ	()I
    //   51: getstatic 29	com/mobile/ui/settings/activity/RealTimeAlertsSettingsActivity:bХ0425Х0425ХХ0425ХХ	I
    //   54: iadd
    //   55: invokestatic 33	com/mobile/ui/settings/activity/RealTimeAlertsSettingsActivity:bХХ04250425ХХ0425ХХ	()I
    //   58: imul
    //   59: getstatic 31	com/mobile/ui/settings/activity/RealTimeAlertsSettingsActivity:b04250425Х0425ХХ0425ХХ	I
    //   62: irem
    //   63: getstatic 35	com/mobile/ui/settings/activity/RealTimeAlertsSettingsActivity:b0425Х04250425ХХ0425ХХ	I
    //   66: if_icmpeq +15 -> 81
    //   69: invokestatic 33	com/mobile/ui/settings/activity/RealTimeAlertsSettingsActivity:bХХ04250425ХХ0425ХХ	()I
    //   72: putstatic 27	com/mobile/ui/settings/activity/RealTimeAlertsSettingsActivity:b0425ХХ0425ХХ0425ХХ	I
    //   75: invokestatic 33	com/mobile/ui/settings/activity/RealTimeAlertsSettingsActivity:bХХ04250425ХХ0425ХХ	()I
    //   78: putstatic 35	com/mobile/ui/settings/activity/RealTimeAlertsSettingsActivity:b0425Х04250425ХХ0425ХХ	I
    //   81: new 37	android/content/Intent
    //   84: dup
    //   85: aload_0
    //   86: ldc 2
    //   88: invokespecial 40	android/content/Intent:<init>	(Landroid/content/Context;Ljava/lang/Class;)V
    //   91: astore_0
    //   92: aload_0
    //   93: areturn
    //   94: astore_0
    //   95: aload_0
    //   96: athrow
    //   97: astore_0
    //   98: aload_0
    //   99: athrow
    // Local variable table:
    //   start	length	slot	name	signature
    //   0	100	0	paramContext	Context
    //   3	14	1	i	int
    //   7	9	2	j	int
    //   11	8	3	k	int
    // Exception table:
    //   from	to	target	type
    //   0	12	94	java/lang/Exception
    //   81	92	94	java/lang/Exception
    //   36	48	97	java/lang/Exception
  }
  
  public Map<String, Bundle> getDeepLinkMap(Context paramContext)
  {
    try
    {
      paramContext = NOT_LINKABLE_MAP;
      int i = b0425ХХ0425ХХ0425ХХ;
      int j = b0425ХХ0425ХХ0425ХХ;
      switch (j * (bХ0425Х0425ХХ0425ХХ + j) % b04250425Х0425ХХ0425ХХ)
      {
      default: 
        b0425ХХ0425ХХ0425ХХ = bХХ04250425ХХ0425ХХ();
        b0425Х04250425ХХ0425ХХ = 69;
      }
      switch (i * (bХ0425Х0425ХХ0425ХХ + i) % bХ042504250425ХХ0425ХХ())
      {
      default: 
        b0425ХХ0425ХХ0425ХХ = bХХ04250425ХХ0425ХХ();
        b0425Х04250425ХХ0425ХХ = bХХ04250425ХХ0425ХХ();
      }
      return paramContext;
    }
    catch (Exception paramContext)
    {
      throw paramContext;
    }
  }
  
  /* Error */
  public android.support.v4.app.Fragment getFragment()
  {
    // Byte code:
    //   0: iconst_3
    //   1: istore_1
    //   2: iload_1
    //   3: iconst_0
    //   4: idiv
    //   5: istore_2
    //   6: iload_2
    //   7: istore_1
    //   8: goto -6 -> 2
    //   11: astore_3
    //   12: bipush 86
    //   14: putstatic 27	com/mobile/ui/settings/activity/RealTimeAlertsSettingsActivity:b0425ХХ0425ХХ0425ХХ	I
    //   17: iconst_0
    //   18: tableswitch	default:+22->40, 0:+49->67, 1:+-1->17
    //   40: iconst_0
    //   41: tableswitch	default:+23->64, 0:+26->67, 1:+-24->17
    //   64: goto -24 -> 40
    //   67: invokestatic 58	com/mobile/ui/settings/fragment/RealTimeAlertsSettingsFragment:newInstance	()Lcom/mobile/ui/settings/fragment/RealTimeAlertsSettingsFragment;
    //   70: astore_3
    //   71: aload_3
    //   72: areturn
    //   73: astore_3
    //   74: bipush 6
    //   76: putstatic 27	com/mobile/ui/settings/activity/RealTimeAlertsSettingsActivity:b0425ХХ0425ХХ0425ХХ	I
    //   79: iload_1
    //   80: iconst_0
    //   81: idiv
    //   82: istore_1
    //   83: goto -4 -> 79
    //   86: astore_3
    //   87: invokestatic 33	com/mobile/ui/settings/activity/RealTimeAlertsSettingsActivity:bХХ04250425ХХ0425ХХ	()I
    //   90: putstatic 27	com/mobile/ui/settings/activity/RealTimeAlertsSettingsActivity:b0425ХХ0425ХХ0425ХХ	I
    //   93: new 60	java/lang/NullPointerException
    //   96: dup
    //   97: invokespecial 61	java/lang/NullPointerException:<init>	()V
    //   100: athrow
    //   101: astore_3
    //   102: aload_3
    //   103: athrow
    //   104: astore_3
    //   105: aload_3
    //   106: athrow
    // Local variable table:
    //   start	length	slot	name	signature
    //   0	107	0	this	RealTimeAlertsSettingsActivity
    //   1	82	1	i	int
    //   5	2	2	j	int
    //   11	1	3	localException1	Exception
    //   70	2	3	localRealTimeAlertsSettingsFragment	com.mobile.ui.settings.fragment.RealTimeAlertsSettingsFragment
    //   73	1	3	localException2	Exception
    //   86	1	3	localException3	Exception
    //   101	2	3	localException4	Exception
    //   104	2	3	localException5	Exception
    // Exception table:
    //   from	to	target	type
    //   93	101	11	java/lang/Exception
    //   2	6	73	java/lang/Exception
    //   79	83	86	java/lang/Exception
    //   67	71	101	java/lang/Exception
    //   74	79	104	java/lang/Exception
    //   87	93	104	java/lang/Exception
  }
  
  public void onCreate(Bundle paramBundle)
  {
    nkkkkk.bЗЗ0417З0417З0417041704170417(getApplicationContext());
    nnnkkk.bхх0445ххххххх(getApplicationContext());
    nknnkk.bх0445ххх04450445ххх(getApplicationContext());
    int i = b0425ХХ0425ХХ0425ХХ;
    switch (i * (bХ0425Х0425ХХ0425ХХ + i) % b04250425Х0425ХХ0425ХХ)
    {
    default: 
      b0425ХХ0425ХХ0425ХХ = 86;
      b0425Х04250425ХХ0425ХХ = bХХ04250425ХХ0425ХХ();
    }
    super.onCreate(paramBundle);
  }
}
