package com.datami.smi.c;

import android.app.AlarmManager;
import android.app.PendingIntent;
import android.content.Context;
import android.content.Intent;
import android.content.SharedPreferences;
import android.content.SharedPreferences.Editor;
import android.provider.Settings.Secure;
import android.telephony.TelephonyManager;
import android.util.Log;
import com.datami.smi.NetworkChangeReceiver;
import com.datami.smi.SmiSdk;
import com.datami.smi.b.k;
import java.util.Calendar;
import java.util.GregorianCalendar;
import org.json.JSONObject;

public final class d
  extends Thread
{
  private static int b = 3;
  private static boolean f = false;
  private static final byte[] g = { 80, -120, -57, -3, 1, 14, 1, -2, 4, -18, 13, -5, 21, 6, 4, -12, 0, 12, -75, 69, 6, 11, -15, 13, 8, -16, 14, 8, -88, 83, -12, 15, -2, 0, 0, 2, 5, -13, -68, 81, -14, 18, 2, -9, 6, -6, -70, 71, -4, 9, 4, -6, 0, -41, -25, -2, -67, 86, -4, -11, -2, 20, -14, 0, -2, 20, -18, 13, -3, -59, 71, -13, -1, 19, -2, -12, -55, 63, -5, 21, 3, 0, -2, -2, -67, 81, -14, 18, 2, -13, -68, 84, 3, -17, 1, 3, 15, 1, -12, 16, -8, -11, -4, -1, 7, 6, 4, -12, 0, 12, -75, 69, 6, 11, -15, 13, 8, -16, 14, 8, -88, 83, -12, 15, -2, 0, 0, 6, -13, -42, -25, -21, -13, 18, -13, 14, 5, -12, -5, 3, 15, -6, 6, -6, -7, 3, 3, 18, -10, 7, 0, 11, -2, 15, 2, -10, 14, -16, 20, -4, 4, 16, 1, -38, 28, 1, 3, 11, -3, 20, 1, 20, -77, 79, -2, -67, 70, 14, 1, -2, 4, -55, -25, 6, 4, -12, 0, 12, -75, 69, 6, 11, -15, 13, 8, -16, 14, 8, -88, 86, -2, -5, -75, -4, 2, -3, 14, 1, -2, 4, -18, 15, 7, -11, -7, 13, -5, 21, 13, 1, -3, -47, 84, 2, -18, 20, 2, -1, -82, 36, 45, -10, 2, -68, 27, -25, -9, 1, 11, 2, -10, -66, 81, -14, 18, 2, -9, 6, -6, -70, 71, -4, 9, 4, -6, 0, -41, -25, 13, -2, 1, -6, -1, 18, -4, 4, -2, -67, 84, 2, -18, 20, 2, -1, -82, 80, -3, 2, -10, -7, 15, 1, -17, 7, -1, -5, 7, 8, 12, -11, 13, -1, 3, 6, 4, -12, 0, 12, -75, 69, 6, 11, -15, 13, 8, -16, 14, 8, -88, 69, -2, 20, -18, -64, 86, -4, -11, -2, 20, -14, 0, -67, 88, -13, 12, -11, -71, 70, 14, 1, -2, 4, -81, 83, -12, 15, -2, 0, 0, 6, -13, 9, 10, 3, -14, 8, 38, 4, -12, 0, 12, -39, 38, 11, -15, 13, 8, -16, 14, 8, -7, 8, 0, -8, -2, -67, 71, -4, 9, 4, -6, 0, 9, 10, -14, 3, 8, -2, -67, 84, 3, -17, 1, 3, 15, 1, -12, 16, -8, -6, 6, -6, 13, 1, -3, -53, -10, 1, 54, 6, 11, -15, 13, 8, -16, 14, 8, -74, 54, 10, 4, 7, -16, 10, -3, -58, 55, -2, 20, -18, 13, -3, -58, 54, 13, -1, -61, 72, -69, -18, 20, -18, 4, 12, -11, 13, -1, 3, 83, -12, 13, -80, 75, 10, -3, 0, -51, -25, -21, 6, 4, -12, 0, 12, -75, 69, 6, 11, -15, 13, 8, -16, 14, 8, -88, 74, 11, -82, 71, -4, 9, 4, -6, 0, -41, -25, -12, 8, -2, -7, 14, -10, 3, -2, -67, 84, 2, -18, 18, 3, -14, 0, 20, -70, 72, -9, 1, -9, 1, 11, 2, -10, 9, -10, 4, 0, -4, 7, 14, 1, -2, 4, -18, 13, -5, 21, -2, -16, 13, 13, -10, 2, -1, 21, -1, -13, 12, -10, 18, -4, 2, 14, -9, 15, -2, -5, -4, -4, 11, -4, -6, -10, -2, 6, 10, 0, -8 };
  private static int h = 47;
  private int c = 0;
  private final Context d;
  private int e = -2;
  
  public d(Context paramContext)
  {
    this.d = paramContext;
  }
  
  private static String a(int paramInt1, int paramInt2, int paramInt3)
  {
    Object localObject2 = new java/lang/String;
    paramInt2 = 49 - paramInt2;
    paramInt1 += 4;
    Object localObject1 = g;
    byte[] arrayOfByte = new byte[paramInt2];
    int i = paramInt2 - 1;
    int j;
    Object localObject3;
    int k;
    if (localObject1 == null)
    {
      j = paramInt1;
      localObject3 = localObject2;
      localObject2 = localObject3;
      paramInt2 = 0;
      paramInt3 = i;
      k = paramInt1;
      paramInt1 = j;
    }
    else
    {
      localObject3 = localObject1;
      paramInt2 = paramInt3 + 32;
      localObject1 = localObject2;
      j = 0;
      paramInt3 = i;
    }
    for (;;)
    {
      arrayOfByte[j] = ((byte)paramInt2);
      paramInt1 += 1;
      if (j == paramInt3)
      {
        ((String)localObject1).<init>(arrayOfByte, 0);
        return localObject2;
      }
      k = localObject3[paramInt1];
      j += 1;
      Object localObject4 = localObject1;
      i = paramInt2;
      localObject1 = localObject3;
      localObject3 = localObject4;
      paramInt2 = j;
      i = i + k - 1;
      localObject4 = localObject1;
      localObject1 = localObject3;
      localObject3 = localObject4;
      j = paramInt2;
      paramInt2 = i;
    }
  }
  
  private void a(long paramLong)
  {
    Object localObject = new GregorianCalendar();
    ((Calendar)localObject).setTimeInMillis(paramLong);
    GregorianCalendar localGregorianCalendar = new GregorianCalendar();
    localGregorianCalendar.set(1, ((Calendar)localObject).get(1));
    localGregorianCalendar.set(11, ((Calendar)localObject).get(11));
    localGregorianCalendar.set(12, ((Calendar)localObject).get(12));
    localGregorianCalendar.set(13, ((Calendar)localObject).get(13));
    localGregorianCalendar.set(14, ((Calendar)localObject).get(14));
    localGregorianCalendar.set(5, ((Calendar)localObject).get(5));
    localGregorianCalendar.set(2, ((Calendar)localObject).get(2));
    localObject = new Intent(this.d, NetworkChangeReceiver.class);
    ((Intent)localObject).setAction(a(136, g['Ś'], g[0]));
    localObject = PendingIntent.getBroadcast(this.d, 12345, (Intent)localObject, 268435456);
    ((AlarmManager)this.d.getSystemService(a(521, h - 3, 65))).set(1, localGregorianCalendar.getTimeInMillis(), (PendingIntent)localObject);
  }
  
  private void a(String paramString1, String paramString2, String paramString3, String paramString4, String paramString5, long paramLong, JSONObject paramJSONObject1, JSONObject paramJSONObject2, String paramString6, String paramString7)
  {
    SharedPreferences localSharedPreferences = k.a(this.d);
    SharedPreferences.Editor localEditor = localSharedPreferences.edit();
    c.b = null;
    c.b = new b(paramString1, paramString2, paramString3, paramString4, paramString5, paramLong);
    try
    {
      i = -g[69];
      a localA = new a(a(i, i & 0xE0, -g[38]));
      if ((paramString1 != null) && (paramString1.length() > 8)) {
        localEditor.putString(a(98, h - 1, g['­']), localA.a(paramString1.trim()));
      }
      if ((paramString2 != null) && (paramString2.length() > 8)) {
        localEditor.putString(a(h | 0x1D0, g['æ'], g[57] - 1), localA.a(paramString2.trim()));
      }
      if ((paramString3 != null) && (paramString3.length() > 8)) {
        localEditor.putString(a(160, h - 3, 65), localA.a(paramString3.trim()));
      }
      if ((paramString4 != null) && (paramString4.length() > 8)) {
        localEditor.putString(a(g['ƺ'], g['æ'], -g['ä']), localA.a(paramString4.trim()));
      }
      if ((paramString5 != null) && (paramString5.length() > 8)) {
        localEditor.putString(a(253, 40, -g[56]), localA.a(paramString5.trim()));
      }
      if (paramLong != -1L) {
        if (0L == paramLong)
        {
          localEditor.putLong(a(384, g['æ'], g[0]), paramLong);
        }
        else
        {
          paramLong = 60L * paramLong * 1000L + System.currentTimeMillis();
          localEditor.putLong(a(384, g['æ'], g[0]), paramLong);
          a(paramLong);
        }
      }
      if (paramJSONObject1 != null) {
        localEditor.putString(a(280, g['æ'], -g['¬']), paramJSONObject1.toString());
      }
      if (paramString6 != null) {
        localEditor.putString(a(490, h - 1, -g['¬']), paramString6);
      }
      if (paramString7 != null) {
        localEditor.putString(a(272, h - 1, -g['¬']), paramString7);
      }
      if (paramJSONObject2 != null) {
        localEditor.putString(a(146, h - 1, g['Ǒ'] - 1), paramJSONObject2.toString());
      }
    }
    catch (Exception paramString1)
    {
      a(341, h & 0xF2, -g['ş']);
      paramString1.getMessage();
    }
    int i = g[16];
    if (localSharedPreferences.contains(a(i, i | 0x28, g[19])))
    {
      i = g[16];
      localEditor.remove(a(i, i | 0x28, g[19]));
    }
    if (localSharedPreferences.contains(a(497, h & 0xF2, g[19]))) {
      localEditor.remove(a(497, h & 0xF2, g[19]));
    }
    localEditor.apply();
    localEditor.commit();
    Log.i(SmiSdk.TAG, a(h + 3, -g['ş'], g[47]));
  }
  
  protected static boolean a()
  {
    return f;
  }
  
  private JSONObject b()
  {
    Object localObject1 = (TelephonyManager)this.d.getSystemService(a(355, h - 3, g[0]));
    if (localObject1 != null)
    {
      localObject3 = ((TelephonyManager)localObject1).getSimOperatorName();
      localObject1 = ((TelephonyManager)localObject1).getSimOperator();
    }
    else
    {
      localObject1 = null;
      localObject3 = localObject1;
    }
    int i;
    if ((localObject1 != null) && (((String)localObject1).length() > 4) && (!((String)localObject1).substring(3).equals(a(g[72], h, g[99])))) {
      i = 1;
    } else {
      i = 0;
    }
    if (i == 0) {
      return null;
    }
    try
    {
      i = Integer.parseInt(((String)localObject1).substring(3));
      localObject2 = new StringBuilder();
      ((StringBuilder)localObject2).append(((String)localObject1).substring(0, 3));
      ((StringBuilder)localObject2).append(a(g['­'] - 1, h + 1, g[10]));
      ((StringBuilder)localObject2).append(i);
      localObject2 = ((StringBuilder)localObject2).toString();
    }
    catch (NumberFormatException localNumberFormatException)
    {
      Object localObject2;
      int j;
      int k;
      for (;;) {}
    }
    a(341, h & 0xF2, -g['ş']);
    a(231, g['ê'] - 1, -g['¬']);
    localObject2 = localObject1;
    Object localObject3 = ((String)localObject3).toLowerCase();
    if (localObject3 == null)
    {
      localObject1 = "";
    }
    else if (((String)localObject3).contains(a(336, h - 4, 65)))
    {
      localObject1 = a(336, h - 4, 65);
    }
    else if (((String)localObject3).contains(a(535, -g[53], g[57])))
    {
      localObject1 = a(535, -g[53], g[57]);
    }
    else if (((String)localObject3).contains(a(198, g['æ'], g['Ǒ'] - 1)))
    {
      localObject1 = a(198, g['æ'], g['Ǒ'] - 1);
    }
    else if (((String)localObject3).contains(a(471, -g[53], -g['ä'])))
    {
      i = 471;
      j = -g[53];
      k = -g['ä'];
      localObject1 = a(i, j, k);
    }
    else
    {
      i = h | 0x140;
      if (((String)localObject3).contains(a(i, i & 0xBB, 65))) {
        i = h | 0x140;
      }
      for (j = i & 0xBB;; j = h - 1)
      {
        localObject1 = a(i, j, 65);
        break label659;
        if (((String)localObject3).contains(a(283, h - 4, -g[38])))
        {
          i = 424;
          j = -g['ş'];
          k = g[91];
          break;
        }
        if ((!((String)localObject3).contains(a(164, h - 1, 65))) && (!((String)localObject3).contains(a(166, g['æ'], 65))))
        {
          localObject1 = localObject3;
          if (!((String)localObject3).contains(a(487, g['æ'], 65))) {
            break label659;
          }
        }
        i = 164;
      }
    }
    label659:
    localObject3 = new JSONObject();
    ((JSONObject)localObject3).put(a(525, h, g['­']), localObject1);
    ((JSONObject)localObject3).put(a(492, h - 4, -g['¬']), localObject2);
    ((JSONObject)localObject3).put(a(156, h - 3, 65), this.d.getPackageName());
    localObject1 = Settings.Secure.getString(this.d.getContentResolver(), a(526, -g['ş'], 65));
    ((JSONObject)localObject3).put(a(96, h - 1, g[57] - 1), localObject1);
    return localObject3;
  }
  
  /* Error */
  public final void run()
  {
    // Byte code:
    //   0: iconst_0
    //   1: putstatic 353	com/datami/smi/b/m:b	Z
    //   4: getstatic 273	com/datami/smi/SmiSdk:TAG	Ljava/lang/String;
    //   7: sipush 478
    //   10: getstatic 109	com/datami/smi/c/d:g	[B
    //   13: sipush 351
    //   16: baload
    //   17: ineg
    //   18: getstatic 109	com/datami/smi/c/d:g	[B
    //   21: bipush 47
    //   23: baload
    //   24: invokestatic 153	com/datami/smi/c/d:a	(III)Ljava/lang/String;
    //   27: invokestatic 279	android/util/Log:i	(Ljava/lang/String;Ljava/lang/String;)I
    //   30: pop
    //   31: invokestatic 242	java/lang/System:currentTimeMillis	()J
    //   34: lstore 7
    //   36: lconst_0
    //   37: lstore 5
    //   39: lload 5
    //   41: lstore_3
    //   42: aload_0
    //   43: getfield 116	com/datami/smi/c/d:c	I
    //   46: getstatic 355	com/datami/smi/c/d:b	I
    //   49: if_icmpgt +2811 -> 2860
    //   52: aconst_null
    //   53: astore 23
    //   55: aload_0
    //   56: invokespecial 357	com/datami/smi/c/d:b	()Lorg/json/JSONObject;
    //   59: astore 11
    //   61: aload 11
    //   63: ifnonnull +9 -> 72
    //   66: lload 5
    //   68: lstore_3
    //   69: goto +2791 -> 2860
    //   72: sipush 387
    //   75: getstatic 109	com/datami/smi/c/d:g	[B
    //   78: bipush 21
    //   80: baload
    //   81: getstatic 109	com/datami/smi/c/d:g	[B
    //   84: sipush 427
    //   87: baload
    //   88: invokestatic 153	com/datami/smi/c/d:a	(III)Ljava/lang/String;
    //   91: astore 10
    //   93: getstatic 360	com/datami/smi/c/c:a	Lcom/datami/smi/c/n;
    //   96: astore 12
    //   98: aload 12
    //   100: ifnull +52 -> 152
    //   103: getstatic 360	com/datami/smi/c/c:a	Lcom/datami/smi/c/n;
    //   106: sipush 387
    //   109: getstatic 109	com/datami/smi/c/d:g	[B
    //   112: bipush 21
    //   114: baload
    //   115: getstatic 109	com/datami/smi/c/d:g	[B
    //   118: sipush 427
    //   121: baload
    //   122: invokestatic 153	com/datami/smi/c/d:a	(III)Ljava/lang/String;
    //   125: invokevirtual 363	com/datami/smi/c/n:a	(Ljava/lang/String;)Ljava/lang/String;
    //   128: astore 10
    //   130: getstatic 360	com/datami/smi/c/c:a	Lcom/datami/smi/c/n;
    //   133: invokevirtual 365	com/datami/smi/c/n:b	()Z
    //   136: istore 9
    //   138: goto +17 -> 155
    //   141: astore 10
    //   143: lload 5
    //   145: lstore_3
    //   146: aconst_null
    //   147: astore 19
    //   149: goto +1981 -> 2130
    //   152: iconst_0
    //   153: istore 9
    //   155: new 367	java/net/URL
    //   158: dup
    //   159: aload 10
    //   161: invokespecial 368	java/net/URL:<init>	(Ljava/lang/String;)V
    //   164: pop
    //   165: sipush 341
    //   168: getstatic 166	com/datami/smi/c/d:h	I
    //   171: sipush 242
    //   174: iand
    //   175: getstatic 109	com/datami/smi/c/d:g	[B
    //   178: sipush 351
    //   181: baload
    //   182: ineg
    //   183: invokestatic 153	com/datami/smi/c/d:a	(III)Ljava/lang/String;
    //   186: pop
    //   187: new 308	java/lang/StringBuilder
    //   190: dup
    //   191: invokespecial 309	java/lang/StringBuilder:<init>	()V
    //   194: astore 12
    //   196: aload 12
    //   198: sipush 178
    //   201: getstatic 109	com/datami/smi/c/d:g	[B
    //   204: sipush 164
    //   207: baload
    //   208: getstatic 109	com/datami/smi/c/d:g	[B
    //   211: bipush 47
    //   213: baload
    //   214: invokestatic 153	com/datami/smi/c/d:a	(III)Ljava/lang/String;
    //   217: invokevirtual 316	java/lang/StringBuilder:append	(Ljava/lang/String;)Ljava/lang/StringBuilder;
    //   220: pop
    //   221: aload 12
    //   223: aload 10
    //   225: invokevirtual 316	java/lang/StringBuilder:append	(Ljava/lang/String;)Ljava/lang/StringBuilder;
    //   228: pop
    //   229: aload 12
    //   231: sipush 433
    //   234: getstatic 166	com/datami/smi/c/d:h	I
    //   237: sipush 245
    //   240: iand
    //   241: getstatic 109	com/datami/smi/c/d:g	[B
    //   244: bipush 16
    //   246: baload
    //   247: invokestatic 153	com/datami/smi/c/d:a	(III)Ljava/lang/String;
    //   250: invokevirtual 316	java/lang/StringBuilder:append	(Ljava/lang/String;)Ljava/lang/StringBuilder;
    //   253: pop
    //   254: aload 12
    //   256: aload 11
    //   258: invokevirtual 249	org/json/JSONObject:toString	()Ljava/lang/String;
    //   261: invokevirtual 316	java/lang/StringBuilder:append	(Ljava/lang/String;)Ljava/lang/StringBuilder;
    //   264: pop
    //   265: aload_0
    //   266: getfield 120	com/datami/smi/c/d:d	Landroid/content/Context;
    //   269: aload 10
    //   271: aload 11
    //   273: invokevirtual 249	org/json/JSONObject:toString	()Ljava/lang/String;
    //   276: iconst_0
    //   277: iload 9
    //   279: invokestatic 373	com/datami/smi/f/c:a	(Landroid/content/Context;Ljava/lang/String;Ljava/lang/String;ZZ)Ljava/lang/String;
    //   282: astore 10
    //   284: invokestatic 242	java/lang/System:currentTimeMillis	()J
    //   287: lstore_3
    //   288: invokestatic 375	com/datami/smi/f/c:a	()I
    //   291: istore_1
    //   292: sipush 341
    //   295: getstatic 166	com/datami/smi/c/d:h	I
    //   298: sipush 242
    //   301: iand
    //   302: getstatic 109	com/datami/smi/c/d:g	[B
    //   305: sipush 351
    //   308: baload
    //   309: ineg
    //   310: invokestatic 153	com/datami/smi/c/d:a	(III)Ljava/lang/String;
    //   313: pop
    //   314: new 308	java/lang/StringBuilder
    //   317: dup
    //   318: invokespecial 309	java/lang/StringBuilder:<init>	()V
    //   321: astore 11
    //   323: aload 11
    //   325: bipush 100
    //   327: getstatic 109	com/datami/smi/c/d:g	[B
    //   330: bipush 12
    //   332: baload
    //   333: getstatic 109	com/datami/smi/c/d:g	[B
    //   336: bipush 47
    //   338: baload
    //   339: invokestatic 153	com/datami/smi/c/d:a	(III)Ljava/lang/String;
    //   342: invokevirtual 316	java/lang/StringBuilder:append	(Ljava/lang/String;)Ljava/lang/StringBuilder;
    //   345: pop
    //   346: aload 11
    //   348: aload 10
    //   350: invokevirtual 316	java/lang/StringBuilder:append	(Ljava/lang/String;)Ljava/lang/StringBuilder;
    //   353: pop
    //   354: aload 11
    //   356: sipush 213
    //   359: bipush 30
    //   361: getstatic 166	com/datami/smi/c/d:h	I
    //   364: sipush 248
    //   367: iand
    //   368: invokestatic 153	com/datami/smi/c/d:a	(III)Ljava/lang/String;
    //   371: invokevirtual 316	java/lang/StringBuilder:append	(Ljava/lang/String;)Ljava/lang/StringBuilder;
    //   374: pop
    //   375: aload 11
    //   377: iload_1
    //   378: invokevirtual 319	java/lang/StringBuilder:append	(I)Ljava/lang/StringBuilder;
    //   381: pop
    //   382: new 246	org/json/JSONObject
    //   385: dup
    //   386: aload 10
    //   388: invokespecial 376	org/json/JSONObject:<init>	(Ljava/lang/String;)V
    //   391: astore 19
    //   393: sipush 200
    //   396: iload_1
    //   397: if_icmpne +1679 -> 2076
    //   400: getstatic 273	com/datami/smi/SmiSdk:TAG	Ljava/lang/String;
    //   403: sipush 261
    //   406: getstatic 166	com/datami/smi/c/d:h	I
    //   409: sipush 245
    //   412: iand
    //   413: getstatic 109	com/datami/smi/c/d:g	[B
    //   416: bipush 47
    //   418: baload
    //   419: invokestatic 153	com/datami/smi/c/d:a	(III)Ljava/lang/String;
    //   422: invokestatic 279	android/util/Log:i	(Ljava/lang/String;Ljava/lang/String;)I
    //   425: pop
    //   426: aload_0
    //   427: getfield 120	com/datami/smi/c/d:d	Landroid/content/Context;
    //   430: invokestatic 189	com/datami/smi/b/k:a	(Landroid/content/Context;)Landroid/content/SharedPreferences;
    //   433: invokestatic 379	com/datami/smi/c/c:e	(Landroid/content/SharedPreferences;)V
    //   436: aload 19
    //   438: sipush 129
    //   441: getstatic 109	com/datami/smi/c/d:g	[B
    //   444: bipush 53
    //   446: baload
    //   447: ineg
    //   448: getstatic 109	com/datami/smi/c/d:g	[B
    //   451: bipush 29
    //   453: baload
    //   454: invokestatic 153	com/datami/smi/c/d:a	(III)Ljava/lang/String;
    //   457: invokevirtual 382	org/json/JSONObject:has	(Ljava/lang/String;)Z
    //   460: ifeq +371 -> 831
    //   463: aload 19
    //   465: sipush 129
    //   468: getstatic 109	com/datami/smi/c/d:g	[B
    //   471: bipush 53
    //   473: baload
    //   474: ineg
    //   475: getstatic 109	com/datami/smi/c/d:g	[B
    //   478: bipush 29
    //   480: baload
    //   481: invokestatic 153	com/datami/smi/c/d:a	(III)Ljava/lang/String;
    //   484: invokevirtual 386	org/json/JSONObject:getJSONObject	(Ljava/lang/String;)Lorg/json/JSONObject;
    //   487: astore 10
    //   489: aload 10
    //   491: bipush 98
    //   493: getstatic 166	com/datami/smi/c/d:h	I
    //   496: iconst_1
    //   497: isub
    //   498: getstatic 109	com/datami/smi/c/d:g	[B
    //   501: sipush 173
    //   504: baload
    //   505: invokestatic 153	com/datami/smi/c/d:a	(III)Ljava/lang/String;
    //   508: invokevirtual 382	org/json/JSONObject:has	(Ljava/lang/String;)Z
    //   511: ifeq +30 -> 541
    //   514: aload 10
    //   516: bipush 98
    //   518: getstatic 166	com/datami/smi/c/d:h	I
    //   521: iconst_1
    //   522: isub
    //   523: getstatic 109	com/datami/smi/c/d:g	[B
    //   526: sipush 173
    //   529: baload
    //   530: invokestatic 153	com/datami/smi/c/d:a	(III)Ljava/lang/String;
    //   533: invokevirtual 388	org/json/JSONObject:getString	(Ljava/lang/String;)Ljava/lang/String;
    //   536: astore 11
    //   538: goto +6 -> 544
    //   541: aconst_null
    //   542: astore 11
    //   544: aload 10
    //   546: getstatic 166	com/datami/smi/c/d:h	I
    //   549: sipush 464
    //   552: ior
    //   553: getstatic 109	com/datami/smi/c/d:g	[B
    //   556: sipush 230
    //   559: baload
    //   560: getstatic 109	com/datami/smi/c/d:g	[B
    //   563: bipush 57
    //   565: baload
    //   566: iconst_1
    //   567: isub
    //   568: invokestatic 153	com/datami/smi/c/d:a	(III)Ljava/lang/String;
    //   571: invokevirtual 382	org/json/JSONObject:has	(Ljava/lang/String;)Z
    //   574: ifeq +38 -> 612
    //   577: aload 10
    //   579: getstatic 166	com/datami/smi/c/d:h	I
    //   582: sipush 464
    //   585: ior
    //   586: getstatic 109	com/datami/smi/c/d:g	[B
    //   589: sipush 230
    //   592: baload
    //   593: getstatic 109	com/datami/smi/c/d:g	[B
    //   596: bipush 57
    //   598: baload
    //   599: iconst_1
    //   600: isub
    //   601: invokestatic 153	com/datami/smi/c/d:a	(III)Ljava/lang/String;
    //   604: invokevirtual 388	org/json/JSONObject:getString	(Ljava/lang/String;)Ljava/lang/String;
    //   607: astore 14
    //   609: goto +6 -> 615
    //   612: aconst_null
    //   613: astore 14
    //   615: aload 10
    //   617: sipush 160
    //   620: getstatic 166	com/datami/smi/c/d:h	I
    //   623: iconst_3
    //   624: isub
    //   625: bipush 65
    //   627: invokestatic 153	com/datami/smi/c/d:a	(III)Ljava/lang/String;
    //   630: invokevirtual 382	org/json/JSONObject:has	(Ljava/lang/String;)Z
    //   633: ifeq +26 -> 659
    //   636: aload 10
    //   638: sipush 160
    //   641: getstatic 166	com/datami/smi/c/d:h	I
    //   644: iconst_3
    //   645: isub
    //   646: bipush 65
    //   648: invokestatic 153	com/datami/smi/c/d:a	(III)Ljava/lang/String;
    //   651: invokevirtual 388	org/json/JSONObject:getString	(Ljava/lang/String;)Ljava/lang/String;
    //   654: astore 12
    //   656: goto +6 -> 662
    //   659: aconst_null
    //   660: astore 12
    //   662: aload 10
    //   664: getstatic 109	com/datami/smi/c/d:g	[B
    //   667: sipush 442
    //   670: baload
    //   671: getstatic 109	com/datami/smi/c/d:g	[B
    //   674: sipush 230
    //   677: baload
    //   678: getstatic 109	com/datami/smi/c/d:g	[B
    //   681: sipush 228
    //   684: baload
    //   685: ineg
    //   686: invokestatic 153	com/datami/smi/c/d:a	(III)Ljava/lang/String;
    //   689: invokevirtual 382	org/json/JSONObject:has	(Ljava/lang/String;)Z
    //   692: ifeq +38 -> 730
    //   695: aload 10
    //   697: getstatic 109	com/datami/smi/c/d:g	[B
    //   700: sipush 442
    //   703: baload
    //   704: getstatic 109	com/datami/smi/c/d:g	[B
    //   707: sipush 230
    //   710: baload
    //   711: getstatic 109	com/datami/smi/c/d:g	[B
    //   714: sipush 228
    //   717: baload
    //   718: ineg
    //   719: invokestatic 153	com/datami/smi/c/d:a	(III)Ljava/lang/String;
    //   722: invokevirtual 388	org/json/JSONObject:getString	(Ljava/lang/String;)Ljava/lang/String;
    //   725: astore 13
    //   727: goto +6 -> 733
    //   730: aconst_null
    //   731: astore 13
    //   733: aload 10
    //   735: sipush 253
    //   738: bipush 40
    //   740: getstatic 109	com/datami/smi/c/d:g	[B
    //   743: bipush 56
    //   745: baload
    //   746: ineg
    //   747: invokestatic 153	com/datami/smi/c/d:a	(III)Ljava/lang/String;
    //   750: invokevirtual 382	org/json/JSONObject:has	(Ljava/lang/String;)Z
    //   753: ifeq +28 -> 781
    //   756: aload 10
    //   758: sipush 253
    //   761: bipush 40
    //   763: getstatic 109	com/datami/smi/c/d:g	[B
    //   766: bipush 56
    //   768: baload
    //   769: ineg
    //   770: invokestatic 153	com/datami/smi/c/d:a	(III)Ljava/lang/String;
    //   773: invokevirtual 388	org/json/JSONObject:getString	(Ljava/lang/String;)Ljava/lang/String;
    //   776: astore 10
    //   778: goto +72 -> 850
    //   781: aconst_null
    //   782: astore 10
    //   784: goto +66 -> 850
    //   787: astore 17
    //   789: goto +8 -> 797
    //   792: astore 17
    //   794: aconst_null
    //   795: astore 13
    //   797: aconst_null
    //   798: astore 10
    //   800: aconst_null
    //   801: astore 15
    //   803: goto +868 -> 1671
    //   806: astore 17
    //   808: aconst_null
    //   809: astore 10
    //   811: aload 11
    //   813: astore 18
    //   815: aload 10
    //   817: astore 11
    //   819: goto +895 -> 1714
    //   822: astore 17
    //   824: aload 11
    //   826: astore 18
    //   828: goto +880 -> 1708
    //   831: aconst_null
    //   832: astore 13
    //   834: aload 13
    //   836: astore 10
    //   838: aload 10
    //   840: astore 11
    //   842: aload 11
    //   844: astore 14
    //   846: aload 14
    //   848: astore 12
    //   850: aload 19
    //   852: sipush 280
    //   855: getstatic 109	com/datami/smi/c/d:g	[B
    //   858: sipush 230
    //   861: baload
    //   862: getstatic 109	com/datami/smi/c/d:g	[B
    //   865: sipush 172
    //   868: baload
    //   869: ineg
    //   870: invokestatic 153	com/datami/smi/c/d:a	(III)Ljava/lang/String;
    //   873: invokevirtual 382	org/json/JSONObject:has	(Ljava/lang/String;)Z
    //   876: ifeq +50 -> 926
    //   879: aload 19
    //   881: sipush 280
    //   884: getstatic 109	com/datami/smi/c/d:g	[B
    //   887: sipush 230
    //   890: baload
    //   891: getstatic 109	com/datami/smi/c/d:g	[B
    //   894: sipush 172
    //   897: baload
    //   898: ineg
    //   899: invokestatic 153	com/datami/smi/c/d:a	(III)Ljava/lang/String;
    //   902: invokevirtual 386	org/json/JSONObject:getJSONObject	(Ljava/lang/String;)Lorg/json/JSONObject;
    //   905: astore 15
    //   907: aload 15
    //   909: astore 16
    //   911: new 362	com/datami/smi/c/n
    //   914: dup
    //   915: aload 15
    //   917: invokespecial 391	com/datami/smi/c/n:<init>	(Lorg/json/JSONObject;)V
    //   920: putstatic 360	com/datami/smi/c/c:a	Lcom/datami/smi/c/n;
    //   923: goto +16 -> 939
    //   926: new 362	com/datami/smi/c/n
    //   929: dup
    //   930: invokespecial 392	com/datami/smi/c/n:<init>	()V
    //   933: putstatic 360	com/datami/smi/c/c:a	Lcom/datami/smi/c/n;
    //   936: aconst_null
    //   937: astore 15
    //   939: aload 15
    //   941: astore 16
    //   943: aload 19
    //   945: sipush 384
    //   948: getstatic 109	com/datami/smi/c/d:g	[B
    //   951: sipush 230
    //   954: baload
    //   955: getstatic 109	com/datami/smi/c/d:g	[B
    //   958: iconst_0
    //   959: baload
    //   960: invokestatic 153	com/datami/smi/c/d:a	(III)Ljava/lang/String;
    //   963: invokevirtual 382	org/json/JSONObject:has	(Ljava/lang/String;)Z
    //   966: ifeq +35 -> 1001
    //   969: aload 15
    //   971: astore 16
    //   973: aload 19
    //   975: sipush 384
    //   978: getstatic 109	com/datami/smi/c/d:g	[B
    //   981: sipush 230
    //   984: baload
    //   985: getstatic 109	com/datami/smi/c/d:g	[B
    //   988: iconst_0
    //   989: baload
    //   990: invokestatic 153	com/datami/smi/c/d:a	(III)Ljava/lang/String;
    //   993: invokevirtual 396	org/json/JSONObject:getLong	(Ljava/lang/String;)J
    //   996: lstore 5
    //   998: goto +8 -> 1006
    //   1001: ldc2_w 228
    //   1004: lstore 5
    //   1006: aload 19
    //   1008: sipush 148
    //   1011: getstatic 166	com/datami/smi/c/d:h	I
    //   1014: getstatic 109	com/datami/smi/c/d:g	[B
    //   1017: bipush 38
    //   1019: baload
    //   1020: ineg
    //   1021: invokestatic 153	com/datami/smi/c/d:a	(III)Ljava/lang/String;
    //   1024: invokevirtual 382	org/json/JSONObject:has	(Ljava/lang/String;)Z
    //   1027: ifeq +55 -> 1082
    //   1030: aload 19
    //   1032: sipush 148
    //   1035: getstatic 166	com/datami/smi/c/d:h	I
    //   1038: getstatic 109	com/datami/smi/c/d:g	[B
    //   1041: bipush 38
    //   1043: baload
    //   1044: ineg
    //   1045: invokestatic 153	com/datami/smi/c/d:a	(III)Ljava/lang/String;
    //   1048: invokevirtual 386	org/json/JSONObject:getJSONObject	(Ljava/lang/String;)Lorg/json/JSONObject;
    //   1051: getstatic 166	com/datami/smi/c/d:h	I
    //   1054: sipush 464
    //   1057: ior
    //   1058: getstatic 109	com/datami/smi/c/d:g	[B
    //   1061: sipush 230
    //   1064: baload
    //   1065: getstatic 109	com/datami/smi/c/d:g	[B
    //   1068: bipush 57
    //   1070: baload
    //   1071: iconst_1
    //   1072: isub
    //   1073: invokestatic 153	com/datami/smi/c/d:a	(III)Ljava/lang/String;
    //   1076: invokevirtual 399	org/json/JSONObject:getBoolean	(Ljava/lang/String;)Z
    //   1079: putstatic 281	com/datami/smi/c/d:f	Z
    //   1082: aload 19
    //   1084: sipush 146
    //   1087: getstatic 166	com/datami/smi/c/d:h	I
    //   1090: iconst_1
    //   1091: isub
    //   1092: getstatic 109	com/datami/smi/c/d:g	[B
    //   1095: sipush 465
    //   1098: baload
    //   1099: iconst_1
    //   1100: isub
    //   1101: invokestatic 153	com/datami/smi/c/d:a	(III)Ljava/lang/String;
    //   1104: invokevirtual 382	org/json/JSONObject:has	(Ljava/lang/String;)Z
    //   1107: ifeq +393 -> 1500
    //   1110: aload 19
    //   1112: sipush 146
    //   1115: getstatic 166	com/datami/smi/c/d:h	I
    //   1118: iconst_1
    //   1119: isub
    //   1120: getstatic 109	com/datami/smi/c/d:g	[B
    //   1123: sipush 465
    //   1126: baload
    //   1127: iconst_1
    //   1128: isub
    //   1129: invokestatic 153	com/datami/smi/c/d:a	(III)Ljava/lang/String;
    //   1132: invokevirtual 402	org/json/JSONObject:isNull	(Ljava/lang/String;)Z
    //   1135: ifne +365 -> 1500
    //   1138: aload 19
    //   1140: sipush 146
    //   1143: getstatic 166	com/datami/smi/c/d:h	I
    //   1146: iconst_1
    //   1147: isub
    //   1148: getstatic 109	com/datami/smi/c/d:g	[B
    //   1151: sipush 465
    //   1154: baload
    //   1155: iconst_1
    //   1156: isub
    //   1157: invokestatic 153	com/datami/smi/c/d:a	(III)Ljava/lang/String;
    //   1160: invokevirtual 386	org/json/JSONObject:getJSONObject	(Ljava/lang/String;)Lorg/json/JSONObject;
    //   1163: astore 20
    //   1165: aload 20
    //   1167: sipush 149
    //   1170: getstatic 109	com/datami/smi/c/d:g	[B
    //   1173: bipush 53
    //   1175: baload
    //   1176: ineg
    //   1177: getstatic 109	com/datami/smi/c/d:g	[B
    //   1180: sipush 173
    //   1183: baload
    //   1184: invokestatic 153	com/datami/smi/c/d:a	(III)Ljava/lang/String;
    //   1187: invokevirtual 382	org/json/JSONObject:has	(Ljava/lang/String;)Z
    //   1190: ifeq +59 -> 1249
    //   1193: aload 20
    //   1195: sipush 149
    //   1198: getstatic 109	com/datami/smi/c/d:g	[B
    //   1201: bipush 53
    //   1203: baload
    //   1204: ineg
    //   1205: getstatic 109	com/datami/smi/c/d:g	[B
    //   1208: sipush 173
    //   1211: baload
    //   1212: invokestatic 153	com/datami/smi/c/d:a	(III)Ljava/lang/String;
    //   1215: invokevirtual 402	org/json/JSONObject:isNull	(Ljava/lang/String;)Z
    //   1218: ifne +31 -> 1249
    //   1221: aload 20
    //   1223: sipush 149
    //   1226: getstatic 109	com/datami/smi/c/d:g	[B
    //   1229: bipush 53
    //   1231: baload
    //   1232: ineg
    //   1233: getstatic 109	com/datami/smi/c/d:g	[B
    //   1236: sipush 173
    //   1239: baload
    //   1240: invokestatic 153	com/datami/smi/c/d:a	(III)Ljava/lang/String;
    //   1243: invokevirtual 388	org/json/JSONObject:getString	(Ljava/lang/String;)Ljava/lang/String;
    //   1246: invokestatic 404	com/datami/smi/b/m:a	(Ljava/lang/String;)V
    //   1249: aload 20
    //   1251: sipush 490
    //   1254: getstatic 166	com/datami/smi/c/d:h	I
    //   1257: iconst_1
    //   1258: isub
    //   1259: getstatic 109	com/datami/smi/c/d:g	[B
    //   1262: sipush 172
    //   1265: baload
    //   1266: ineg
    //   1267: invokestatic 153	com/datami/smi/c/d:a	(III)Ljava/lang/String;
    //   1270: invokevirtual 382	org/json/JSONObject:has	(Ljava/lang/String;)Z
    //   1273: ifeq +59 -> 1332
    //   1276: aload 20
    //   1278: sipush 490
    //   1281: getstatic 166	com/datami/smi/c/d:h	I
    //   1284: iconst_1
    //   1285: isub
    //   1286: getstatic 109	com/datami/smi/c/d:g	[B
    //   1289: sipush 172
    //   1292: baload
    //   1293: ineg
    //   1294: invokestatic 153	com/datami/smi/c/d:a	(III)Ljava/lang/String;
    //   1297: invokevirtual 402	org/json/JSONObject:isNull	(Ljava/lang/String;)Z
    //   1300: ifne +32 -> 1332
    //   1303: aload 20
    //   1305: sipush 490
    //   1308: getstatic 166	com/datami/smi/c/d:h	I
    //   1311: iconst_1
    //   1312: isub
    //   1313: getstatic 109	com/datami/smi/c/d:g	[B
    //   1316: sipush 172
    //   1319: baload
    //   1320: ineg
    //   1321: invokestatic 153	com/datami/smi/c/d:a	(III)Ljava/lang/String;
    //   1324: invokevirtual 388	org/json/JSONObject:getString	(Ljava/lang/String;)Ljava/lang/String;
    //   1327: astore 16
    //   1329: goto +6 -> 1335
    //   1332: aconst_null
    //   1333: astore 16
    //   1335: aload 20
    //   1337: sipush 272
    //   1340: getstatic 166	com/datami/smi/c/d:h	I
    //   1343: iconst_1
    //   1344: isub
    //   1345: getstatic 109	com/datami/smi/c/d:g	[B
    //   1348: sipush 172
    //   1351: baload
    //   1352: ineg
    //   1353: invokestatic 153	com/datami/smi/c/d:a	(III)Ljava/lang/String;
    //   1356: invokevirtual 382	org/json/JSONObject:has	(Ljava/lang/String;)Z
    //   1359: ifeq +59 -> 1418
    //   1362: aload 20
    //   1364: sipush 272
    //   1367: getstatic 166	com/datami/smi/c/d:h	I
    //   1370: iconst_1
    //   1371: isub
    //   1372: getstatic 109	com/datami/smi/c/d:g	[B
    //   1375: sipush 172
    //   1378: baload
    //   1379: ineg
    //   1380: invokestatic 153	com/datami/smi/c/d:a	(III)Ljava/lang/String;
    //   1383: invokevirtual 402	org/json/JSONObject:isNull	(Ljava/lang/String;)Z
    //   1386: ifeq +32 -> 1418
    //   1389: aload 20
    //   1391: sipush 272
    //   1394: getstatic 166	com/datami/smi/c/d:h	I
    //   1397: iconst_1
    //   1398: isub
    //   1399: getstatic 109	com/datami/smi/c/d:g	[B
    //   1402: sipush 172
    //   1405: baload
    //   1406: ineg
    //   1407: invokestatic 153	com/datami/smi/c/d:a	(III)Ljava/lang/String;
    //   1410: invokevirtual 388	org/json/JSONObject:getString	(Ljava/lang/String;)Ljava/lang/String;
    //   1413: astore 18
    //   1415: goto +96 -> 1511
    //   1418: aconst_null
    //   1419: astore 18
    //   1421: goto +90 -> 1511
    //   1424: astore 17
    //   1426: aconst_null
    //   1427: astore 18
    //   1429: aload 10
    //   1431: astore 21
    //   1433: aload 18
    //   1435: astore 10
    //   1437: aload 11
    //   1439: astore 18
    //   1441: aload 14
    //   1443: astore 22
    //   1445: aload 12
    //   1447: astore 14
    //   1449: aload 20
    //   1451: astore 12
    //   1453: aload 16
    //   1455: astore 11
    //   1457: goto +303 -> 1760
    //   1460: astore 17
    //   1462: aconst_null
    //   1463: astore 18
    //   1465: aload 18
    //   1467: astore 16
    //   1469: aload 10
    //   1471: astore 21
    //   1473: aload 18
    //   1475: astore 10
    //   1477: aload 11
    //   1479: astore 18
    //   1481: aload 14
    //   1483: astore 22
    //   1485: aload 12
    //   1487: astore 14
    //   1489: aload 20
    //   1491: astore 12
    //   1493: aload 16
    //   1495: astore 11
    //   1497: goto +263 -> 1760
    //   1500: aconst_null
    //   1501: astore 18
    //   1503: aload 18
    //   1505: astore 20
    //   1507: aload 20
    //   1509: astore 16
    //   1511: getstatic 273	com/datami/smi/SmiSdk:TAG	Ljava/lang/String;
    //   1514: getstatic 109	com/datami/smi/c/d:g	[B
    //   1517: sipush 173
    //   1520: baload
    //   1521: iconst_1
    //   1522: isub
    //   1523: bipush 30
    //   1525: getstatic 109	com/datami/smi/c/d:g	[B
    //   1528: bipush 47
    //   1530: baload
    //   1531: invokestatic 153	com/datami/smi/c/d:a	(III)Ljava/lang/String;
    //   1534: invokestatic 279	android/util/Log:i	(Ljava/lang/String;Ljava/lang/String;)I
    //   1537: pop
    //   1538: aload 12
    //   1540: astore 17
    //   1542: aload 20
    //   1544: astore 12
    //   1546: aload 18
    //   1548: astore 20
    //   1550: goto +415 -> 1965
    //   1553: astore 17
    //   1555: aload 10
    //   1557: astore 21
    //   1559: aload 18
    //   1561: astore 10
    //   1563: aload 11
    //   1565: astore 18
    //   1567: aload 14
    //   1569: astore 22
    //   1571: aload 12
    //   1573: astore 14
    //   1575: aload 20
    //   1577: astore 12
    //   1579: aload 16
    //   1581: astore 11
    //   1583: goto +177 -> 1760
    //   1586: astore 17
    //   1588: aconst_null
    //   1589: astore 18
    //   1591: aload 18
    //   1593: astore 16
    //   1595: aload 16
    //   1597: astore 20
    //   1599: aload 10
    //   1601: astore 21
    //   1603: aload 18
    //   1605: astore 10
    //   1607: aload 11
    //   1609: astore 18
    //   1611: aload 14
    //   1613: astore 22
    //   1615: aload 12
    //   1617: astore 14
    //   1619: aload 16
    //   1621: astore 12
    //   1623: aload 20
    //   1625: astore 11
    //   1627: goto +133 -> 1760
    //   1630: astore 17
    //   1632: aconst_null
    //   1633: astore 18
    //   1635: aload 18
    //   1637: astore 15
    //   1639: aload 10
    //   1641: astore 21
    //   1643: aload 18
    //   1645: astore 10
    //   1647: aload 11
    //   1649: astore 18
    //   1651: aload 14
    //   1653: astore 22
    //   1655: aload 12
    //   1657: astore 14
    //   1659: aload 15
    //   1661: astore 12
    //   1663: goto +84 -> 1747
    //   1666: astore 17
    //   1668: aconst_null
    //   1669: astore 15
    //   1671: aload 15
    //   1673: astore 16
    //   1675: aload 10
    //   1677: astore 21
    //   1679: aload 11
    //   1681: astore 18
    //   1683: aload 14
    //   1685: astore 22
    //   1687: aload 12
    //   1689: astore 11
    //   1691: aload 16
    //   1693: astore 10
    //   1695: goto +36 -> 1731
    //   1698: astore 10
    //   1700: goto -1551 -> 149
    //   1703: astore 17
    //   1705: aconst_null
    //   1706: astore 18
    //   1708: aconst_null
    //   1709: astore 14
    //   1711: aconst_null
    //   1712: astore 11
    //   1714: aconst_null
    //   1715: astore 15
    //   1717: aconst_null
    //   1718: astore 21
    //   1720: aconst_null
    //   1721: astore 13
    //   1723: aload 11
    //   1725: astore 10
    //   1727: aload 14
    //   1729: astore 22
    //   1731: aload 10
    //   1733: astore 12
    //   1735: aload 10
    //   1737: astore 16
    //   1739: aload 11
    //   1741: astore 14
    //   1743: aload 15
    //   1745: astore 10
    //   1747: aload 12
    //   1749: astore 11
    //   1751: ldc2_w 228
    //   1754: lstore 5
    //   1756: aload 16
    //   1758: astore 15
    //   1760: getstatic 360	com/datami/smi/c/c:a	Lcom/datami/smi/c/n;
    //   1763: astore 16
    //   1765: aload 16
    //   1767: ifnonnull +13 -> 1780
    //   1770: new 362	com/datami/smi/c/n
    //   1773: dup
    //   1774: invokespecial 392	com/datami/smi/c/n:<init>	()V
    //   1777: putstatic 360	com/datami/smi/c/c:a	Lcom/datami/smi/c/n;
    //   1780: new 406	java/util/Properties
    //   1783: dup
    //   1784: invokespecial 407	java/util/Properties:<init>	()V
    //   1787: astore 20
    //   1789: sipush 274
    //   1792: getstatic 109	com/datami/smi/c/d:g	[B
    //   1795: sipush 129
    //   1798: baload
    //   1799: ineg
    //   1800: getstatic 109	com/datami/smi/c/d:g	[B
    //   1803: sipush 172
    //   1806: baload
    //   1807: ineg
    //   1808: invokestatic 153	com/datami/smi/c/d:a	(III)Ljava/lang/String;
    //   1811: astore 24
    //   1813: aload 17
    //   1815: invokevirtual 408	org/json/JSONException:getMessage	()Ljava/lang/String;
    //   1818: astore 16
    //   1820: aload 16
    //   1822: ifnull +13 -> 1835
    //   1825: aload 17
    //   1827: invokevirtual 408	org/json/JSONException:getMessage	()Ljava/lang/String;
    //   1830: astore 16
    //   1832: goto +10 -> 1842
    //   1835: aload 17
    //   1837: invokevirtual 414	java/lang/Object:getClass	()Ljava/lang/Class;
    //   1840: astore 16
    //   1842: aload 20
    //   1844: aload 24
    //   1846: aload 16
    //   1848: invokevirtual 417	java/util/Properties:put	(Ljava/lang/Object;Ljava/lang/Object;)Ljava/lang/Object;
    //   1851: pop
    //   1852: getstatic 166	com/datami/smi/c/d:h	I
    //   1855: bipush 80
    //   1857: ior
    //   1858: istore_1
    //   1859: aload 20
    //   1861: iload_1
    //   1862: iload_1
    //   1863: sipush 174
    //   1866: iand
    //   1867: getstatic 109	com/datami/smi/c/d:g	[B
    //   1870: bipush 29
    //   1872: baload
    //   1873: invokestatic 153	com/datami/smi/c/d:a	(III)Ljava/lang/String;
    //   1876: getstatic 422	com/datami/smi/d/c:c	Lcom/datami/smi/d/c;
    //   1879: invokestatic 427	com/datami/smi/d/a:a	(Lcom/datami/smi/d/c;)Ljava/lang/String;
    //   1882: invokevirtual 417	java/util/Properties:put	(Ljava/lang/Object;Ljava/lang/Object;)Ljava/lang/Object;
    //   1885: pop
    //   1886: getstatic 432	com/datami/smi/d/d:a	Lcom/datami/smi/d/d;
    //   1889: invokestatic 435	com/datami/smi/d/a:a	(Lcom/datami/smi/d/d;)Ljava/lang/String;
    //   1892: aload 20
    //   1894: invokestatic 438	com/datami/smi/b/m:b	(Ljava/lang/String;Ljava/util/Properties;)V
    //   1897: sipush 341
    //   1900: getstatic 166	com/datami/smi/c/d:h	I
    //   1903: sipush 242
    //   1906: iand
    //   1907: getstatic 109	com/datami/smi/c/d:g	[B
    //   1910: sipush 351
    //   1913: baload
    //   1914: ineg
    //   1915: invokestatic 153	com/datami/smi/c/d:a	(III)Ljava/lang/String;
    //   1918: pop
    //   1919: getstatic 109	com/datami/smi/c/d:g	[B
    //   1922: bipush 24
    //   1924: baload
    //   1925: getstatic 109	com/datami/smi/c/d:g	[B
    //   1928: bipush 13
    //   1930: baload
    //   1931: getstatic 109	com/datami/smi/c/d:g	[B
    //   1934: bipush 47
    //   1936: baload
    //   1937: invokestatic 153	com/datami/smi/c/d:a	(III)Ljava/lang/String;
    //   1940: pop
    //   1941: aload 10
    //   1943: astore 20
    //   1945: aload 11
    //   1947: astore 16
    //   1949: aload 18
    //   1951: astore 11
    //   1953: aload 14
    //   1955: astore 17
    //   1957: aload 22
    //   1959: astore 14
    //   1961: aload 21
    //   1963: astore 10
    //   1965: aload_0
    //   1966: aload 11
    //   1968: aload 14
    //   1970: aload 17
    //   1972: aload 13
    //   1974: aload 10
    //   1976: lload 5
    //   1978: aload 15
    //   1980: aload 12
    //   1982: aload 16
    //   1984: aload 20
    //   1986: invokespecial 440	com/datami/smi/c/d:a	(Ljava/lang/String;Ljava/lang/String;Ljava/lang/String;Ljava/lang/String;Ljava/lang/String;JLorg/json/JSONObject;Lorg/json/JSONObject;Ljava/lang/String;Ljava/lang/String;)V
    //   1989: iconst_1
    //   1990: putstatic 441	com/datami/smi/c/c:c	I
    //   1993: new 406	java/util/Properties
    //   1996: dup
    //   1997: invokespecial 407	java/util/Properties:<init>	()V
    //   2000: astore 10
    //   2002: getstatic 166	com/datami/smi/c/d:h	I
    //   2005: bipush 80
    //   2007: ior
    //   2008: istore_1
    //   2009: aload 10
    //   2011: iload_1
    //   2012: iload_1
    //   2013: sipush 174
    //   2016: iand
    //   2017: getstatic 109	com/datami/smi/c/d:g	[B
    //   2020: bipush 29
    //   2022: baload
    //   2023: invokestatic 153	com/datami/smi/c/d:a	(III)Ljava/lang/String;
    //   2026: getstatic 443	com/datami/smi/d/c:a	Lcom/datami/smi/d/c;
    //   2029: invokestatic 427	com/datami/smi/d/a:a	(Lcom/datami/smi/d/c;)Ljava/lang/String;
    //   2032: invokevirtual 417	java/util/Properties:put	(Ljava/lang/Object;Ljava/lang/Object;)Ljava/lang/Object;
    //   2035: pop
    //   2036: getstatic 432	com/datami/smi/d/d:a	Lcom/datami/smi/d/d;
    //   2039: invokestatic 435	com/datami/smi/d/a:a	(Lcom/datami/smi/d/d;)Ljava/lang/String;
    //   2042: aload 10
    //   2044: invokestatic 438	com/datami/smi/b/m:b	(Ljava/lang/String;Ljava/util/Properties;)V
    //   2047: getstatic 273	com/datami/smi/SmiSdk:TAG	Ljava/lang/String;
    //   2050: sipush 372
    //   2053: getstatic 109	com/datami/smi/c/d:g	[B
    //   2056: sipush 229
    //   2059: baload
    //   2060: getstatic 109	com/datami/smi/c/d:g	[B
    //   2063: bipush 47
    //   2065: baload
    //   2066: invokestatic 153	com/datami/smi/c/d:a	(III)Ljava/lang/String;
    //   2069: invokestatic 279	android/util/Log:i	(Ljava/lang/String;Ljava/lang/String;)I
    //   2072: pop
    //   2073: goto +787 -> 2860
    //   2076: iconst_0
    //   2077: putstatic 441	com/datami/smi/c/c:c	I
    //   2080: getstatic 273	com/datami/smi/SmiSdk:TAG	Ljava/lang/String;
    //   2083: sipush 359
    //   2086: getstatic 166	com/datami/smi/c/d:h	I
    //   2089: sipush 248
    //   2092: iand
    //   2093: getstatic 109	com/datami/smi/c/d:g	[B
    //   2096: bipush 47
    //   2098: baload
    //   2099: invokestatic 153	com/datami/smi/c/d:a	(III)Ljava/lang/String;
    //   2102: invokestatic 279	android/util/Log:i	(Ljava/lang/String;Ljava/lang/String;)I
    //   2105: pop
    //   2106: lload_3
    //   2107: lstore 5
    //   2109: goto +182 -> 2291
    //   2112: astore 10
    //   2114: goto +16 -> 2130
    //   2117: astore 10
    //   2119: goto +8 -> 2127
    //   2122: astore 10
    //   2124: lload 5
    //   2126: lstore_3
    //   2127: aconst_null
    //   2128: astore 19
    //   2130: iconst_0
    //   2131: putstatic 441	com/datami/smi/c/c:c	I
    //   2134: new 406	java/util/Properties
    //   2137: dup
    //   2138: invokespecial 407	java/util/Properties:<init>	()V
    //   2141: astore 11
    //   2143: sipush 274
    //   2146: getstatic 109	com/datami/smi/c/d:g	[B
    //   2149: sipush 129
    //   2152: baload
    //   2153: ineg
    //   2154: getstatic 109	com/datami/smi/c/d:g	[B
    //   2157: sipush 172
    //   2160: baload
    //   2161: ineg
    //   2162: invokestatic 153	com/datami/smi/c/d:a	(III)Ljava/lang/String;
    //   2165: astore 12
    //   2167: aload 10
    //   2169: invokevirtual 252	java/lang/Exception:getMessage	()Ljava/lang/String;
    //   2172: ifnull +13 -> 2185
    //   2175: aload 10
    //   2177: invokevirtual 252	java/lang/Exception:getMessage	()Ljava/lang/String;
    //   2180: astore 10
    //   2182: goto +10 -> 2192
    //   2185: aload 10
    //   2187: invokevirtual 414	java/lang/Object:getClass	()Ljava/lang/Class;
    //   2190: astore 10
    //   2192: aload 11
    //   2194: aload 12
    //   2196: aload 10
    //   2198: invokevirtual 417	java/util/Properties:put	(Ljava/lang/Object;Ljava/lang/Object;)Ljava/lang/Object;
    //   2201: pop
    //   2202: getstatic 166	com/datami/smi/c/d:h	I
    //   2205: bipush 80
    //   2207: ior
    //   2208: istore_1
    //   2209: aload 11
    //   2211: iload_1
    //   2212: iload_1
    //   2213: sipush 174
    //   2216: iand
    //   2217: getstatic 109	com/datami/smi/c/d:g	[B
    //   2220: bipush 29
    //   2222: baload
    //   2223: invokestatic 153	com/datami/smi/c/d:a	(III)Ljava/lang/String;
    //   2226: getstatic 422	com/datami/smi/d/c:c	Lcom/datami/smi/d/c;
    //   2229: invokestatic 427	com/datami/smi/d/a:a	(Lcom/datami/smi/d/c;)Ljava/lang/String;
    //   2232: invokevirtual 417	java/util/Properties:put	(Ljava/lang/Object;Ljava/lang/Object;)Ljava/lang/Object;
    //   2235: pop
    //   2236: getstatic 432	com/datami/smi/d/d:a	Lcom/datami/smi/d/d;
    //   2239: invokestatic 435	com/datami/smi/d/a:a	(Lcom/datami/smi/d/d;)Ljava/lang/String;
    //   2242: aload 11
    //   2244: invokestatic 438	com/datami/smi/b/m:b	(Ljava/lang/String;Ljava/util/Properties;)V
    //   2247: sipush 341
    //   2250: getstatic 166	com/datami/smi/c/d:h	I
    //   2253: sipush 242
    //   2256: iand
    //   2257: getstatic 109	com/datami/smi/c/d:g	[B
    //   2260: sipush 351
    //   2263: baload
    //   2264: ineg
    //   2265: invokestatic 153	com/datami/smi/c/d:a	(III)Ljava/lang/String;
    //   2268: pop
    //   2269: sipush 444
    //   2272: getstatic 109	com/datami/smi/c/d:g	[B
    //   2275: bipush 12
    //   2277: baload
    //   2278: getstatic 109	com/datami/smi/c/d:g	[B
    //   2281: bipush 47
    //   2283: baload
    //   2284: invokestatic 153	com/datami/smi/c/d:a	(III)Ljava/lang/String;
    //   2287: pop
    //   2288: lload_3
    //   2289: lstore 5
    //   2291: aload 19
    //   2293: ifnull +514 -> 2807
    //   2296: aload 19
    //   2298: sipush 514
    //   2301: getstatic 109	com/datami/smi/c/d:g	[B
    //   2304: sipush 230
    //   2307: baload
    //   2308: getstatic 109	com/datami/smi/c/d:g	[B
    //   2311: bipush 56
    //   2313: baload
    //   2314: ineg
    //   2315: invokestatic 153	com/datami/smi/c/d:a	(III)Ljava/lang/String;
    //   2318: invokevirtual 382	org/json/JSONObject:has	(Ljava/lang/String;)Z
    //   2321: ifeq +93 -> 2414
    //   2324: aload_0
    //   2325: aload 19
    //   2327: sipush 514
    //   2330: getstatic 109	com/datami/smi/c/d:g	[B
    //   2333: sipush 230
    //   2336: baload
    //   2337: getstatic 109	com/datami/smi/c/d:g	[B
    //   2340: bipush 56
    //   2342: baload
    //   2343: ineg
    //   2344: invokestatic 153	com/datami/smi/c/d:a	(III)Ljava/lang/String;
    //   2347: invokevirtual 446	org/json/JSONObject:getInt	(Ljava/lang/String;)I
    //   2350: putfield 118	com/datami/smi/c/d:e	I
    //   2353: getstatic 273	com/datami/smi/SmiSdk:TAG	Ljava/lang/String;
    //   2356: astore 10
    //   2358: new 308	java/lang/StringBuilder
    //   2361: dup
    //   2362: invokespecial 309	java/lang/StringBuilder:<init>	()V
    //   2365: astore 11
    //   2367: aload 11
    //   2369: sipush 169
    //   2372: getstatic 109	com/datami/smi/c/d:g	[B
    //   2375: sipush 351
    //   2378: baload
    //   2379: ineg
    //   2380: getstatic 109	com/datami/smi/c/d:g	[B
    //   2383: bipush 47
    //   2385: baload
    //   2386: invokestatic 153	com/datami/smi/c/d:a	(III)Ljava/lang/String;
    //   2389: invokevirtual 316	java/lang/StringBuilder:append	(Ljava/lang/String;)Ljava/lang/StringBuilder;
    //   2392: pop
    //   2393: aload 11
    //   2395: aload_0
    //   2396: getfield 118	com/datami/smi/c/d:e	I
    //   2399: invokevirtual 319	java/lang/StringBuilder:append	(I)Ljava/lang/StringBuilder;
    //   2402: pop
    //   2403: aload 10
    //   2405: aload 11
    //   2407: invokevirtual 320	java/lang/StringBuilder:toString	()Ljava/lang/String;
    //   2410: invokestatic 279	android/util/Log:i	(Ljava/lang/String;Ljava/lang/String;)I
    //   2413: pop
    //   2414: aload 23
    //   2416: astore 10
    //   2418: aload 19
    //   2420: sipush 517
    //   2423: getstatic 166	com/datami/smi/c/d:h	I
    //   2426: iconst_3
    //   2427: isub
    //   2428: getstatic 109	com/datami/smi/c/d:g	[B
    //   2431: bipush 56
    //   2433: baload
    //   2434: ineg
    //   2435: invokestatic 153	com/datami/smi/c/d:a	(III)Ljava/lang/String;
    //   2438: invokevirtual 382	org/json/JSONObject:has	(Ljava/lang/String;)Z
    //   2441: ifeq +79 -> 2520
    //   2444: aload 19
    //   2446: sipush 517
    //   2449: getstatic 166	com/datami/smi/c/d:h	I
    //   2452: iconst_3
    //   2453: isub
    //   2454: getstatic 109	com/datami/smi/c/d:g	[B
    //   2457: bipush 56
    //   2459: baload
    //   2460: ineg
    //   2461: invokestatic 153	com/datami/smi/c/d:a	(III)Ljava/lang/String;
    //   2464: invokevirtual 388	org/json/JSONObject:getString	(Ljava/lang/String;)Ljava/lang/String;
    //   2467: astore 10
    //   2469: goto +51 -> 2520
    //   2472: sipush 341
    //   2475: getstatic 166	com/datami/smi/c/d:h	I
    //   2478: sipush 242
    //   2481: iand
    //   2482: getstatic 109	com/datami/smi/c/d:g	[B
    //   2485: sipush 351
    //   2488: baload
    //   2489: ineg
    //   2490: invokestatic 153	com/datami/smi/c/d:a	(III)Ljava/lang/String;
    //   2493: pop
    //   2494: getstatic 109	com/datami/smi/c/d:g	[B
    //   2497: bipush 24
    //   2499: baload
    //   2500: getstatic 109	com/datami/smi/c/d:g	[B
    //   2503: bipush 13
    //   2505: baload
    //   2506: getstatic 109	com/datami/smi/c/d:g	[B
    //   2509: bipush 47
    //   2511: baload
    //   2512: invokestatic 153	com/datami/smi/c/d:a	(III)Ljava/lang/String;
    //   2515: pop
    //   2516: aload 23
    //   2518: astore 10
    //   2520: aload_0
    //   2521: getfield 120	com/datami/smi/c/d:d	Landroid/content/Context;
    //   2524: invokestatic 189	com/datami/smi/b/k:a	(Landroid/content/Context;)Landroid/content/SharedPreferences;
    //   2527: astore 11
    //   2529: aload 11
    //   2531: invokeinterface 195 1 0
    //   2536: astore 12
    //   2538: invokestatic 375	com/datami/smi/f/c:a	()I
    //   2541: istore_1
    //   2542: iload_1
    //   2543: sipush 200
    //   2546: if_icmpeq +171 -> 2717
    //   2549: getstatic 109	com/datami/smi/c/d:g	[B
    //   2552: bipush 16
    //   2554: baload
    //   2555: istore_2
    //   2556: aload 12
    //   2558: iload_2
    //   2559: iload_2
    //   2560: bipush 40
    //   2562: ior
    //   2563: getstatic 109	com/datami/smi/c/d:g	[B
    //   2566: bipush 19
    //   2568: baload
    //   2569: invokestatic 153	com/datami/smi/c/d:a	(III)Ljava/lang/String;
    //   2572: iload_1
    //   2573: invokeinterface 450 3 0
    //   2578: pop
    //   2579: bipush -2
    //   2581: aload_0
    //   2582: getfield 118	com/datami/smi/c/d:e	I
    //   2585: if_icmpeq +34 -> 2619
    //   2588: aload 12
    //   2590: sipush 497
    //   2593: getstatic 166	com/datami/smi/c/d:h	I
    //   2596: sipush 242
    //   2599: iand
    //   2600: getstatic 109	com/datami/smi/c/d:g	[B
    //   2603: bipush 19
    //   2605: baload
    //   2606: invokestatic 153	com/datami/smi/c/d:a	(III)Ljava/lang/String;
    //   2609: aload_0
    //   2610: getfield 118	com/datami/smi/c/d:e	I
    //   2613: invokeinterface 450 3 0
    //   2618: pop
    //   2619: aload 10
    //   2621: ifnull +32 -> 2653
    //   2624: aload 12
    //   2626: sipush 201
    //   2629: getstatic 109	com/datami/smi/c/d:g	[B
    //   2632: sipush 229
    //   2635: baload
    //   2636: getstatic 109	com/datami/smi/c/d:g	[B
    //   2639: bipush 19
    //   2641: baload
    //   2642: invokestatic 153	com/datami/smi/c/d:a	(III)Ljava/lang/String;
    //   2645: aload 10
    //   2647: invokeinterface 227 3 0
    //   2652: pop
    //   2653: aload 11
    //   2655: invokestatic 379	com/datami/smi/c/c:e	(Landroid/content/SharedPreferences;)V
    //   2658: aload 12
    //   2660: invokeinterface 263 1 0
    //   2665: aload 12
    //   2667: invokeinterface 267 1 0
    //   2672: pop
    //   2673: sipush 341
    //   2676: getstatic 166	com/datami/smi/c/d:h	I
    //   2679: sipush 242
    //   2682: iand
    //   2683: getstatic 109	com/datami/smi/c/d:g	[B
    //   2686: sipush 351
    //   2689: baload
    //   2690: ineg
    //   2691: invokestatic 153	com/datami/smi/c/d:a	(III)Ljava/lang/String;
    //   2694: pop
    //   2695: sipush 288
    //   2698: getstatic 109	com/datami/smi/c/d:g	[B
    //   2701: bipush 16
    //   2703: baload
    //   2704: getstatic 109	com/datami/smi/c/d:g	[B
    //   2707: bipush 47
    //   2709: baload
    //   2710: invokestatic 153	com/datami/smi/c/d:a	(III)Ljava/lang/String;
    //   2713: pop
    //   2714: goto +3 -> 2717
    //   2717: new 406	java/util/Properties
    //   2720: dup
    //   2721: invokespecial 407	java/util/Properties:<init>	()V
    //   2724: astore 10
    //   2726: aload 10
    //   2728: sipush 274
    //   2731: getstatic 109	com/datami/smi/c/d:g	[B
    //   2734: sipush 129
    //   2737: baload
    //   2738: ineg
    //   2739: getstatic 109	com/datami/smi/c/d:g	[B
    //   2742: sipush 172
    //   2745: baload
    //   2746: ineg
    //   2747: invokestatic 153	com/datami/smi/c/d:a	(III)Ljava/lang/String;
    //   2750: aload 19
    //   2752: invokevirtual 249	org/json/JSONObject:toString	()Ljava/lang/String;
    //   2755: invokevirtual 417	java/util/Properties:put	(Ljava/lang/Object;Ljava/lang/Object;)Ljava/lang/Object;
    //   2758: pop
    //   2759: getstatic 166	com/datami/smi/c/d:h	I
    //   2762: bipush 80
    //   2764: ior
    //   2765: istore_1
    //   2766: aload 10
    //   2768: iload_1
    //   2769: iload_1
    //   2770: sipush 174
    //   2773: iand
    //   2774: getstatic 109	com/datami/smi/c/d:g	[B
    //   2777: bipush 29
    //   2779: baload
    //   2780: invokestatic 153	com/datami/smi/c/d:a	(III)Ljava/lang/String;
    //   2783: getstatic 452	com/datami/smi/d/c:b	Lcom/datami/smi/d/c;
    //   2786: invokestatic 427	com/datami/smi/d/a:a	(Lcom/datami/smi/d/c;)Ljava/lang/String;
    //   2789: invokevirtual 417	java/util/Properties:put	(Ljava/lang/Object;Ljava/lang/Object;)Ljava/lang/Object;
    //   2792: pop
    //   2793: getstatic 432	com/datami/smi/d/d:a	Lcom/datami/smi/d/d;
    //   2796: invokestatic 435	com/datami/smi/d/a:a	(Lcom/datami/smi/d/d;)Ljava/lang/String;
    //   2799: aload 10
    //   2801: invokestatic 438	com/datami/smi/b/m:b	(Ljava/lang/String;Ljava/util/Properties;)V
    //   2804: goto +3 -> 2807
    //   2807: sipush 999
    //   2810: aload_0
    //   2811: getfield 118	com/datami/smi/c/d:e	I
    //   2814: if_icmpeq +33 -> 2847
    //   2817: sipush 1000
    //   2820: aload_0
    //   2821: getfield 118	com/datami/smi/c/d:e	I
    //   2824: if_icmpeq +23 -> 2847
    //   2827: iconst_m1
    //   2828: aload_0
    //   2829: getfield 118	com/datami/smi/c/d:e	I
    //   2832: if_icmpeq +15 -> 2847
    //   2835: lload 5
    //   2837: lstore_3
    //   2838: bipush -2
    //   2840: aload_0
    //   2841: getfield 118	com/datami/smi/c/d:e	I
    //   2844: if_icmpne +16 -> 2860
    //   2847: aload_0
    //   2848: aload_0
    //   2849: getfield 116	com/datami/smi/c/d:c	I
    //   2852: iconst_1
    //   2853: iadd
    //   2854: putfield 116	com/datami/smi/c/d:c	I
    //   2857: goto -2818 -> 39
    //   2860: lload_3
    //   2861: lload 7
    //   2863: lsub
    //   2864: lstore_3
    //   2865: lload_3
    //   2866: lconst_0
    //   2867: lcmp
    //   2868: ifle +10 -> 2878
    //   2871: invokestatic 457	com/datami/smi/a/c:a	()Lcom/datami/smi/a/c;
    //   2874: lload_3
    //   2875: invokevirtual 459	com/datami/smi/a/c:c	(J)V
    //   2878: return
    //   2879: astore 10
    //   2881: goto -409 -> 2472
    //   2884: astore 10
    //   2886: goto -756 -> 2130
    // Local variable table:
    //   start	length	slot	name	signature
    //   0	2889	0	this	d
    //   291	2483	1	i	int
    //   2555	8	2	j	int
    //   41	2834	3	l1	long
    //   37	2799	5	l2	long
    //   34	2828	7	l3	long
    //   136	142	9	bool	boolean
    //   91	38	10	str1	String
    //   141	129	10	localException1	Exception
    //   282	1412	10	localObject1	Object
    //   1698	1	10	localException2	Exception
    //   1725	318	10	localObject2	Object
    //   2112	1	10	localException3	Exception
    //   2117	1	10	localException4	Exception
    //   2122	54	10	localException5	Exception
    //   2180	620	10	localObject3	Object
    //   2879	1	10	localJSONException1	org.json.JSONException
    //   2884	1	10	localException6	Exception
    //   59	2595	11	localObject4	Object
    //   96	2570	12	localObject5	Object
    //   725	1248	13	str2	String
    //   607	1362	14	localObject6	Object
    //   801	1178	15	localObject7	Object
    //   909	1074	16	localObject8	Object
    //   787	1	17	localJSONException2	org.json.JSONException
    //   792	1	17	localJSONException3	org.json.JSONException
    //   806	1	17	localJSONException4	org.json.JSONException
    //   822	1	17	localJSONException5	org.json.JSONException
    //   1424	1	17	localJSONException6	org.json.JSONException
    //   1460	1	17	localJSONException7	org.json.JSONException
    //   1540	1	17	localObject9	Object
    //   1553	1	17	localJSONException8	org.json.JSONException
    //   1586	1	17	localJSONException9	org.json.JSONException
    //   1630	1	17	localJSONException10	org.json.JSONException
    //   1666	1	17	localJSONException11	org.json.JSONException
    //   1703	133	17	localJSONException12	org.json.JSONException
    //   1955	16	17	localObject10	Object
    //   813	1137	18	localObject11	Object
    //   147	2604	19	localJSONObject	JSONObject
    //   1163	822	20	localObject12	Object
    //   1431	531	21	localObject13	Object
    //   1443	515	22	localObject14	Object
    //   53	2464	23	localObject15	Object
    //   1811	34	24	str3	String
    // Exception table:
    //   from	to	target	type
    //   103	138	141	java/lang/Exception
    //   733	778	787	org/json/JSONException
    //   662	727	792	org/json/JSONException
    //   615	656	806	org/json/JSONException
    //   544	609	822	org/json/JSONException
    //   1335	1415	1424	org/json/JSONException
    //   1165	1249	1460	org/json/JSONException
    //   1249	1329	1460	org/json/JSONException
    //   1511	1538	1553	org/json/JSONException
    //   1006	1082	1586	org/json/JSONException
    //   1082	1165	1586	org/json/JSONException
    //   911	923	1630	org/json/JSONException
    //   943	969	1630	org/json/JSONException
    //   973	998	1630	org/json/JSONException
    //   850	907	1666	org/json/JSONException
    //   926	936	1666	org/json/JSONException
    //   436	538	1698	java/lang/Exception
    //   544	609	1698	java/lang/Exception
    //   615	656	1698	java/lang/Exception
    //   662	727	1698	java/lang/Exception
    //   733	778	1698	java/lang/Exception
    //   850	907	1698	java/lang/Exception
    //   911	923	1698	java/lang/Exception
    //   926	936	1698	java/lang/Exception
    //   943	969	1698	java/lang/Exception
    //   973	998	1698	java/lang/Exception
    //   1006	1082	1698	java/lang/Exception
    //   1082	1165	1698	java/lang/Exception
    //   1165	1249	1698	java/lang/Exception
    //   1249	1329	1698	java/lang/Exception
    //   1335	1415	1698	java/lang/Exception
    //   1511	1538	1698	java/lang/Exception
    //   1770	1780	1698	java/lang/Exception
    //   1825	1832	1698	java/lang/Exception
    //   436	538	1703	org/json/JSONException
    //   1965	2073	2112	java/lang/Exception
    //   2076	2106	2112	java/lang/Exception
    //   288	393	2117	java/lang/Exception
    //   55	61	2122	java/lang/Exception
    //   72	98	2122	java/lang/Exception
    //   155	288	2122	java/lang/Exception
    //   2296	2414	2879	org/json/JSONException
    //   2418	2469	2879	org/json/JSONException
    //   400	436	2884	java/lang/Exception
    //   1760	1765	2884	java/lang/Exception
    //   1780	1820	2884	java/lang/Exception
    //   1835	1842	2884	java/lang/Exception
    //   1842	1941	2884	java/lang/Exception
  }
}
