package com.mobile.ui.producthub.activity;

import android.content.Context;
import android.os.Bundle;
import android.support.annotation.Nullable;
import android.support.v4.app.FragmentManager;
import android.support.v4.app.FragmentTransaction;
import com.mobile.ui.R.id;
import com.mobile.ui.R.layout;
import com.mobile.ui.common.activity.AppTimeoutActivity;
import com.mobile.ui.common.activity.BaseActivity.rrrggg;
import com.mobile.ui.producthub.fragment.ProductHubFragment;
import java.util.Map;
import kkkkkk.gguuuu;
import kkkkkk.nkkkkk;
import kkkkkk.nknnkk;
import kkkkkk.nnnkkk;
import kkkkkk.nuuuun.uunuun;

public class ProductHubActivity
  extends AppTimeoutActivity
{
  public static int b04170417З04170417З0417ЗЗ = 1;
  public static int b0417ЗЗ04170417З0417ЗЗ = 27;
  public static int bЗ0417З04170417З0417ЗЗ = 0;
  public static int bЗЗ041704170417З0417ЗЗ = 2;
  
  public ProductHubActivity() {}
  
  public static int b04170417041704170417З0417ЗЗ()
  {
    return 0;
  }
  
  public static int b0417З041704170417З0417ЗЗ()
  {
    return 2;
  }
  
  public static int bЗ0417041704170417З0417ЗЗ()
  {
    return 65;
  }
  
  public static int bЗЗЗЗЗ04170417ЗЗ()
  {
    return 1;
  }
  
  /* Error */
  public static android.content.Intent getIntent(Context paramContext)
  {
    // Byte code:
    //   0: getstatic 29	com/mobile/ui/producthub/activity/ProductHubActivity:b0417ЗЗ04170417З0417ЗЗ	I
    //   3: istore_1
    //   4: getstatic 31	com/mobile/ui/producthub/activity/ProductHubActivity:b04170417З04170417З0417ЗЗ	I
    //   7: istore_2
    //   8: getstatic 29	com/mobile/ui/producthub/activity/ProductHubActivity:b0417ЗЗ04170417З0417ЗЗ	I
    //   11: istore_3
    //   12: getstatic 33	com/mobile/ui/producthub/activity/ProductHubActivity:bЗЗ041704170417З0417ЗЗ	I
    //   15: istore 4
    //   17: getstatic 35	com/mobile/ui/producthub/activity/ProductHubActivity:bЗ0417З04170417З0417ЗЗ	I
    //   20: istore 5
    //   22: iload_1
    //   23: iload_2
    //   24: iadd
    //   25: iload_3
    //   26: imul
    //   27: iload 4
    //   29: irem
    //   30: iload 5
    //   32: if_icmpeq +46 -> 78
    //   35: bipush 11
    //   37: putstatic 29	com/mobile/ui/producthub/activity/ProductHubActivity:b0417ЗЗ04170417З0417ЗЗ	I
    //   40: bipush 94
    //   42: putstatic 35	com/mobile/ui/producthub/activity/ProductHubActivity:bЗ0417З04170417З0417ЗЗ	I
    //   45: getstatic 29	com/mobile/ui/producthub/activity/ProductHubActivity:b0417ЗЗ04170417З0417ЗЗ	I
    //   48: getstatic 31	com/mobile/ui/producthub/activity/ProductHubActivity:b04170417З04170417З0417ЗЗ	I
    //   51: iadd
    //   52: getstatic 29	com/mobile/ui/producthub/activity/ProductHubActivity:b0417ЗЗ04170417З0417ЗЗ	I
    //   55: imul
    //   56: invokestatic 37	com/mobile/ui/producthub/activity/ProductHubActivity:b0417З041704170417З0417ЗЗ	()I
    //   59: irem
    //   60: getstatic 35	com/mobile/ui/producthub/activity/ProductHubActivity:bЗ0417З04170417З0417ЗЗ	I
    //   63: if_icmpeq +15 -> 78
    //   66: invokestatic 39	com/mobile/ui/producthub/activity/ProductHubActivity:bЗ0417041704170417З0417ЗЗ	()I
    //   69: putstatic 29	com/mobile/ui/producthub/activity/ProductHubActivity:b0417ЗЗ04170417З0417ЗЗ	I
    //   72: invokestatic 39	com/mobile/ui/producthub/activity/ProductHubActivity:bЗ0417041704170417З0417ЗЗ	()I
    //   75: putstatic 35	com/mobile/ui/producthub/activity/ProductHubActivity:bЗ0417З04170417З0417ЗЗ	I
    //   78: new 41	android/content/Intent
    //   81: dup
    //   82: aload_0
    //   83: ldc 2
    //   85: invokespecial 44	android/content/Intent:<init>	(Landroid/content/Context;Ljava/lang/Class;)V
    //   88: astore_0
    //   89: iconst_1
    //   90: tableswitch	default:+22->112, 0:+-1->89, 1:+49->139
    //   112: iconst_0
    //   113: tableswitch	default:+23->136, 0:+26->139, 1:+-24->89
    //   136: goto -24 -> 112
    //   139: aload_0
    //   140: areturn
    //   141: astore_0
    //   142: aload_0
    //   143: athrow
    //   144: astore_0
    //   145: aload_0
    //   146: athrow
    // Local variable table:
    //   start	length	slot	name	signature
    //   0	147	0	paramContext	Context
    //   3	22	1	i	int
    //   7	18	2	j	int
    //   11	16	3	k	int
    //   15	15	4	m	int
    //   20	13	5	n	int
    // Exception table:
    //   from	to	target	type
    //   0	22	141	java/lang/Exception
    //   78	89	141	java/lang/Exception
    //   35	45	144	java/lang/Exception
  }
  
  public Map<String, Bundle> getDeepLinkMap(Context paramContext)
  {
    return nuuuun.uunuun.b043F043F043F043Fпп043F043F043Fп(gguuuu.bккккк043Aкк043A043A("#&$\032,\033-f#1\037", 'º', '\001'));
  }
  
  public int getLayoutId()
  {
    try
    {
      int i = R.layout.activity_product_hub;
      int j = b0417ЗЗ04170417З0417ЗЗ;
      int k = b0417ЗЗ04170417З0417ЗЗ;
      switch (k * (b04170417З04170417З0417ЗЗ + k) % b0417З041704170417З0417ЗЗ())
      {
      default: 
        b0417ЗЗ04170417З0417ЗЗ = 17;
        bЗ0417З04170417З0417ЗЗ = 24;
      }
      k = bЗЗЗЗЗ04170417ЗЗ();
      switch (0)
      {
      case 1: 
      default: 
        for (;;)
        {
          switch (0)
          {
          }
        }
      }
      switch (j * (k + j) % bЗЗ041704170417З0417ЗЗ)
      {
      default: 
        b0417ЗЗ04170417З0417ЗЗ = 66;
        bЗ0417З04170417З0417ЗЗ = 29;
      }
      return i;
    }
    catch (Exception localException)
    {
      throw localException;
    }
  }
  
  public BaseActivity.rrrggg getMenuType()
  {
    throw new Runtime("d2j fail translate: java.lang.IndexOutOfBoundsException: fromIndex < 0: -1\n\tat java.util.BitSet.nextSetBit(BitSet.java:712)\n\tat com.googlecode.dex2jar.ir.ts.array.FillArrayTransformer.makeSureAllElementAreAssigned(FillArrayTransformer.java:505)\n\tat com.googlecode.dex2jar.ir.ts.array.FillArrayTransformer.transformReportChanged(FillArrayTransformer.java:123)\n\tat com.googlecode.dex2jar.ir.ts.StatedTransformer.transform(StatedTransformer.java:10)\n\tat com.googlecode.d2j.dex.Dex2jar$2.optimize(Dex2jar.java:149)\n\tat com.googlecode.d2j.dex.Dex2Asm.convertCode(Dex2Asm.java:414)\n\tat com.googlecode.d2j.dex.ExDex2Asm.convertCode(ExDex2Asm.java:42)\n\tat com.googlecode.d2j.dex.Dex2jar$2.convertCode(Dex2jar.java:128)\n\tat com.googlecode.d2j.dex.Dex2Asm.convertMethod(Dex2Asm.java:509)\n\tat com.googlecode.d2j.dex.Dex2Asm.convertClass(Dex2Asm.java:406)\n\tat com.googlecode.d2j.dex.Dex2Asm.convertDex(Dex2Asm.java:422)\n\tat com.googlecode.d2j.dex.Dex2jar.doTranslate(Dex2jar.java:172)\n\tat com.googlecode.d2j.dex.Dex2jar.to(Dex2jar.java:272)\n\tat com.googlecode.dex2jar.tools.Dex2jarCmd.doCommandLine(Dex2jarCmd.java:108)\n\tat com.googlecode.dex2jar.tools.BaseCmd.doMain(BaseCmd.java:288)\n\tat com.googlecode.dex2jar.tools.Dex2jarCmd.main(Dex2jarCmd.java:32)\n");
  }
  
  public void onCreate(@Nullable Bundle paramBundle)
  {
    nkkkkk.bЗЗ0417З0417З0417041704170417(getApplicationContext());
    nnnkkk.bхх0445ххххххх(getApplicationContext());
    nknnkk.bх0445ххх04450445ххх(getApplicationContext());
    super.onCreate(paramBundle);
    if (paramBundle == null) {
      getSupportFragmentManager().beginTransaction().replace(R.id.productHubContainer, ProductHubFragment.newInstance()).commit();
    }
  }
  
  public boolean shouldRestartAppIfSecureCoreNotInitialized()
  {
    if ((bЗ0417041704170417З0417ЗЗ() + b04170417З04170417З0417ЗЗ) * bЗ0417041704170417З0417ЗЗ() % bЗЗ041704170417З0417ЗЗ != b04170417041704170417З0417ЗЗ())
    {
      b0417ЗЗ04170417З0417ЗЗ = bЗ0417041704170417З0417ЗЗ();
      bЗ0417З04170417З0417ЗЗ = 40;
    }
    if ((b0417ЗЗ04170417З0417ЗЗ + b04170417З04170417З0417ЗЗ) * b0417ЗЗ04170417З0417ЗЗ % bЗЗ041704170417З0417ЗЗ != bЗ0417З04170417З0417ЗЗ)
    {
      switch (1)
      {
      case 0: 
      default: 
        for (;;)
        {
          switch (1)
          {
          }
        }
      }
      b0417ЗЗ04170417З0417ЗЗ = 48;
      bЗ0417З04170417З0417ЗЗ = bЗ0417041704170417З0417ЗЗ();
    }
    return true;
  }
}
