package com.db.pwcc.dbmobile.model.gini;

import uuuuuu.popopp;

public class GiniCredentials
  implements popopp
{
  public static int b00710071qqq007100710071 = 1;
  public static int b0071qqqq007100710071 = 84;
  public static int bq0071qqq007100710071 = 0;
  public static int bqq0071qq007100710071 = 2;
  private String licenseKey;
  private String userId;
  
  public GiniCredentials() {}
  
  public GiniCredentials(String paramString1, String paramString2)
  {
    this();
    this.userId = paramString1;
    this.licenseKey = paramString2;
  }
  
  public static int b007100710071qq007100710071()
  {
    return 1;
  }
  
  public static int b0071q0071qq007100710071()
  {
    return 82;
  }
  
  public static int bq00710071qq007100710071()
  {
    return 0;
  }
  
  public static int bqqq0071q007100710071()
  {
    return 2;
  }
  
  public String getLicenseKey()
  {
    String str = this.licenseKey;
    if ((b0071qqqq007100710071 + b00710071qqq007100710071) * b0071qqqq007100710071 % bqq0071qq007100710071 != bq0071qqq007100710071)
    {
      if ((b0071qqqq007100710071 + b00710071qqq007100710071) * b0071qqqq007100710071 % bqq0071qq007100710071 != bq0071qqq007100710071)
      {
        b0071qqqq007100710071 = 6;
        bq0071qqq007100710071 = 57;
      }
      b0071qqqq007100710071 = 68;
      bq0071qqq007100710071 = 28;
    }
    return str;
  }
  
  public String getUserId()
  {
    String str = this.userId;
    int i = b0071q0071qq007100710071();
    int j = b00710071qqq007100710071;
    int k = b0071q0071qq007100710071();
    int m = bqq0071qq007100710071;
    int n = bq0071qqq007100710071;
    if ((b0071qqqq007100710071 + b00710071qqq007100710071) * b0071qqqq007100710071 % bqq0071qq007100710071 != bq0071qqq007100710071)
    {
      b0071qqqq007100710071 = b0071q0071qq007100710071();
      bq0071qqq007100710071 = 72;
    }
    if ((i + j) * k % m != n)
    {
      b0071qqqq007100710071 = 25;
      bq0071qqq007100710071 = 29;
    }
    return str;
  }
  
  public void setLicenseKey(String paramString)
  {
    this.licenseKey = paramString;
    if ((b0071qqqq007100710071 + b00710071qqq007100710071) * b0071qqqq007100710071 % bqq0071qq007100710071 != bq0071qqq007100710071)
    {
      if ((b0071qqqq007100710071 + b00710071qqq007100710071) * b0071qqqq007100710071 % bqq0071qq007100710071 != bq0071qqq007100710071)
      {
        b0071qqqq007100710071 = 27;
        bq0071qqq007100710071 = 65;
      }
      b0071qqqq007100710071 = 17;
      bq0071qqq007100710071 = 49;
    }
  }
  
  public void setUserId(String paramString)
  {
    if ((b0071qqqq007100710071 + b007100710071qq007100710071()) * b0071qqqq007100710071 % bqqq0071q007100710071() != bq00710071qq007100710071())
    {
      b0071qqqq007100710071 = b0071q0071qq007100710071();
      bq0071qqq007100710071 = 19;
    }
    this.userId = paramString;
    if ((b0071qqqq007100710071 + b00710071qqq007100710071) * b0071qqqq007100710071 % bqq0071qq007100710071 != bq0071qqq007100710071)
    {
      b0071qqqq007100710071 = 0;
      bq0071qqq007100710071 = b0071q0071qq007100710071();
    }
  }
  
  /* Error */
  public String toString()
  {
    // Byte code:
    //   0: new 61	java/lang/StringBuilder
    //   3: dup
    //   4: invokespecial 62	java/lang/StringBuilder:<init>	()V
    //   7: astore_1
    //   8: ldc 64
    //   10: ldc 66
    //   12: sipush 224
    //   15: iconst_0
    //   16: invokestatic 72	xxxxxx/uxxxxx:bb00620062bb0062b0062b0062	(Ljava/lang/String;CC)Ljava/lang/String;
    //   19: iconst_4
    //   20: anewarray 74	java/lang/Class
    //   23: dup
    //   24: iconst_0
    //   25: ldc 76
    //   27: aastore
    //   28: dup
    //   29: iconst_1
    //   30: getstatic 82	java/lang/Character:TYPE	Ljava/lang/Class;
    //   33: aastore
    //   34: dup
    //   35: iconst_2
    //   36: getstatic 82	java/lang/Character:TYPE	Ljava/lang/Class;
    //   39: aastore
    //   40: dup
    //   41: iconst_3
    //   42: getstatic 82	java/lang/Character:TYPE	Ljava/lang/Class;
    //   45: aastore
    //   46: invokevirtual 86	java/lang/Class:getMethod	(Ljava/lang/String;[Ljava/lang/Class;)Ljava/lang/reflect/Method;
    //   49: astore_2
    //   50: aload_2
    //   51: aconst_null
    //   52: iconst_4
    //   53: anewarray 4	java/lang/Object
    //   56: dup
    //   57: iconst_0
    //   58: ldc 88
    //   60: aastore
    //   61: dup
    //   62: iconst_1
    //   63: sipush 158
    //   66: invokestatic 92	java/lang/Character:valueOf	(C)Ljava/lang/Character;
    //   69: aastore
    //   70: dup
    //   71: iconst_2
    //   72: sipush 199
    //   75: invokestatic 92	java/lang/Character:valueOf	(C)Ljava/lang/Character;
    //   78: aastore
    //   79: dup
    //   80: iconst_3
    //   81: iconst_3
    //   82: invokestatic 92	java/lang/Character:valueOf	(C)Ljava/lang/Character;
    //   85: aastore
    //   86: invokevirtual 98	java/lang/reflect/Method:invoke	(Ljava/lang/Object;[Ljava/lang/Object;)Ljava/lang/Object;
    //   89: astore_2
    //   90: aload_1
    //   91: aload_2
    //   92: checkcast 76	java/lang/String
    //   95: invokevirtual 102	java/lang/StringBuilder:append	(Ljava/lang/String;)Ljava/lang/StringBuilder;
    //   98: aload_0
    //   99: getfield 27	com/db/pwcc/dbmobile/model/gini/GiniCredentials:userId	Ljava/lang/String;
    //   102: invokevirtual 102	java/lang/StringBuilder:append	(Ljava/lang/String;)Ljava/lang/StringBuilder;
    //   105: bipush 39
    //   107: invokevirtual 105	java/lang/StringBuilder:append	(C)Ljava/lang/StringBuilder;
    //   110: astore_1
    //   111: getstatic 38	com/db/pwcc/dbmobile/model/gini/GiniCredentials:b0071qqqq007100710071	I
    //   114: getstatic 40	com/db/pwcc/dbmobile/model/gini/GiniCredentials:b00710071qqq007100710071	I
    //   117: iadd
    //   118: getstatic 38	com/db/pwcc/dbmobile/model/gini/GiniCredentials:b0071qqqq007100710071	I
    //   121: imul
    //   122: invokestatic 54	com/db/pwcc/dbmobile/model/gini/GiniCredentials:bqqq0071q007100710071	()I
    //   125: irem
    //   126: getstatic 44	com/db/pwcc/dbmobile/model/gini/GiniCredentials:bq0071qqq007100710071	I
    //   129: if_icmpeq +47 -> 176
    //   132: getstatic 38	com/db/pwcc/dbmobile/model/gini/GiniCredentials:b0071qqqq007100710071	I
    //   135: getstatic 40	com/db/pwcc/dbmobile/model/gini/GiniCredentials:b00710071qqq007100710071	I
    //   138: iadd
    //   139: getstatic 38	com/db/pwcc/dbmobile/model/gini/GiniCredentials:b0071qqqq007100710071	I
    //   142: imul
    //   143: invokestatic 54	com/db/pwcc/dbmobile/model/gini/GiniCredentials:bqqq0071q007100710071	()I
    //   146: irem
    //   147: getstatic 44	com/db/pwcc/dbmobile/model/gini/GiniCredentials:bq0071qqq007100710071	I
    //   150: if_icmpeq +14 -> 164
    //   153: invokestatic 47	com/db/pwcc/dbmobile/model/gini/GiniCredentials:b0071q0071qq007100710071	()I
    //   156: putstatic 38	com/db/pwcc/dbmobile/model/gini/GiniCredentials:b0071qqqq007100710071	I
    //   159: bipush 87
    //   161: putstatic 44	com/db/pwcc/dbmobile/model/gini/GiniCredentials:bq0071qqq007100710071	I
    //   164: invokestatic 47	com/db/pwcc/dbmobile/model/gini/GiniCredentials:b0071q0071qq007100710071	()I
    //   167: putstatic 38	com/db/pwcc/dbmobile/model/gini/GiniCredentials:b0071qqqq007100710071	I
    //   170: invokestatic 47	com/db/pwcc/dbmobile/model/gini/GiniCredentials:b0071q0071qq007100710071	()I
    //   173: putstatic 44	com/db/pwcc/dbmobile/model/gini/GiniCredentials:bq0071qqq007100710071	I
    //   176: ldc 64
    //   178: ldc 107
    //   180: bipush 109
    //   182: iconst_3
    //   183: iconst_2
    //   184: invokestatic 111	xxxxxx/uxxxxx:bbbb0062b0062b0062b0062	(Ljava/lang/String;CCC)Ljava/lang/String;
    //   187: iconst_3
    //   188: anewarray 74	java/lang/Class
    //   191: dup
    //   192: iconst_0
    //   193: ldc 76
    //   195: aastore
    //   196: dup
    //   197: iconst_1
    //   198: getstatic 82	java/lang/Character:TYPE	Ljava/lang/Class;
    //   201: aastore
    //   202: dup
    //   203: iconst_2
    //   204: getstatic 82	java/lang/Character:TYPE	Ljava/lang/Class;
    //   207: aastore
    //   208: invokevirtual 86	java/lang/Class:getMethod	(Ljava/lang/String;[Ljava/lang/Class;)Ljava/lang/reflect/Method;
    //   211: astore_2
    //   212: aload_2
    //   213: aconst_null
    //   214: iconst_3
    //   215: anewarray 4	java/lang/Object
    //   218: dup
    //   219: iconst_0
    //   220: ldc 113
    //   222: aastore
    //   223: dup
    //   224: iconst_1
    //   225: bipush 103
    //   227: invokestatic 92	java/lang/Character:valueOf	(C)Ljava/lang/Character;
    //   230: aastore
    //   231: dup
    //   232: iconst_2
    //   233: iconst_4
    //   234: invokestatic 92	java/lang/Character:valueOf	(C)Ljava/lang/Character;
    //   237: aastore
    //   238: invokevirtual 98	java/lang/reflect/Method:invoke	(Ljava/lang/Object;[Ljava/lang/Object;)Ljava/lang/Object;
    //   241: astore_2
    //   242: aload_1
    //   243: aload_2
    //   244: checkcast 76	java/lang/String
    //   247: invokevirtual 102	java/lang/StringBuilder:append	(Ljava/lang/String;)Ljava/lang/StringBuilder;
    //   250: aload_0
    //   251: getfield 29	com/db/pwcc/dbmobile/model/gini/GiniCredentials:licenseKey	Ljava/lang/String;
    //   254: invokevirtual 102	java/lang/StringBuilder:append	(Ljava/lang/String;)Ljava/lang/StringBuilder;
    //   257: bipush 39
    //   259: invokevirtual 105	java/lang/StringBuilder:append	(C)Ljava/lang/StringBuilder;
    //   262: bipush 125
    //   264: invokevirtual 105	java/lang/StringBuilder:append	(C)Ljava/lang/StringBuilder;
    //   267: invokevirtual 115	java/lang/StringBuilder:toString	()Ljava/lang/String;
    //   270: areturn
    //   271: astore_1
    //   272: aload_1
    //   273: invokevirtual 119	java/lang/reflect/InvocationTargetException:getCause	()Ljava/lang/Throwable;
    //   276: athrow
    //   277: astore_1
    //   278: aload_1
    //   279: invokevirtual 119	java/lang/reflect/InvocationTargetException:getCause	()Ljava/lang/Throwable;
    //   282: athrow
    // Local variable table:
    //   start	length	slot	name	signature
    //   0	283	0	this	GiniCredentials
    //   7	236	1	localStringBuilder	StringBuilder
    //   271	2	1	localInvocationTargetException1	java.lang.reflect.InvocationTargetException
    //   277	2	1	localInvocationTargetException2	java.lang.reflect.InvocationTargetException
    //   49	195	2	localObject	Object
    // Exception table:
    //   from	to	target	type
    //   212	242	271	java/lang/reflect/InvocationTargetException
    //   50	90	277	java/lang/reflect/InvocationTargetException
  }
}
