package com.liveperson.infra.messaging_ui.view.adapter.viewholder;

import android.os.Bundle;
import android.view.View;
import com.liveperson.infra.messaging_ui.R.id;
import com.liveperson.infra.ui.view.adapter.viewholder.MiddleViewHolder;
import java.util.HashMap;
import kkkkkk.gguuuu;
import kkkkkk.hbhbhb;
import kkkkkk.jjjmjj;
import kkkkkk.jmjmjj;
import kkkkkk.oovvoo;
import kkkkkk.xtxxtx.txxxtx;

public class AmsSystemMaskedViewHolder
  extends MiddleViewHolder
  implements jmjmjj
{
  private static final String TAG = AmsSystemMaskedViewHolder.class.getSimpleName();
  public static int b04220422Т0422Т04220422 = 0;
  public static int b0422Т04220422Т04220422 = 2;
  public static int bТ042204220422Т04220422 = 12;
  public static int bТТ04220422Т04220422 = 1;
  public long mMessageSequence;
  
  static
  {
    if ((bТ0422Т0422Т04220422() + bТТ04220422Т04220422) * bТ0422Т0422Т04220422() % b0422Т04220422Т04220422 != b04220422Т0422Т04220422)
    {
      b04220422Т0422Т04220422 = 23;
      int i = bТ042204220422Т04220422;
      switch (i * (bТТ04220422Т04220422 + i) % b0422Т04220422Т04220422)
      {
      default: 
        bТ042204220422Т04220422 = bТ0422Т0422Т04220422();
        b04220422Т0422Т04220422 = bТ0422Т0422Т04220422();
      }
    }
    switch (0)
    {
    case 1: 
    default: 
      for (;;)
      {
        switch (0)
        {
        }
      }
    }
    switch (0)
    {
    case 1: 
    default: 
      for (;;)
      {
        switch (1)
        {
        }
      }
    }
  }
  
  public AmsSystemMaskedViewHolder(View paramView)
  {
    super(paramView);
    applyColors();
  }
  
  public static int b0422042204220422Т04220422()
  {
    return 0;
  }
  
  public static int bТ0422Т0422Т04220422()
  {
    return 59;
  }
  
  public static int bТТТТ042204220422()
  {
    return 2;
  }
  
  public void applyChanges(Bundle paramBundle, jjjmjj paramJjjmjj)
  {
    super.applyChanges(paramBundle, paramJjjmjj);
    int i = bТ042204220422Т04220422;
    switch (i * (bТТ04220422Т04220422 + i) % b0422Т04220422Т04220422)
    {
    default: 
      bТ042204220422Т04220422 = 96;
      b04220422Т0422Т04220422 = bТ0422Т0422Т04220422();
    }
    long l = paramBundle.getLong(gguuuu.bк043Aккк043Aкк043A043A("|\021\016\r|\034\021\004\022\027\007\025#\030\013\030\035\016\030\016\021", '§', 'ï', '\001'), -1L);
    if (l > -1L) {
      setMessageSequence(l);
    }
  }
  
  public void applyColors()
  {
    try
    {
      localHashMap = hbhbhb.bШШ0428ШШШШ04280428Ш().b04280428ШШШШШ04280428Ш();
      if (localHashMap.isEmpty()) {
        break label132;
      }
      localOovvoo = new oovvoo(this.itemView);
      i = R.id.lpui_message_text;
    }
    catch (Exception localException1)
    {
      try
      {
        HashMap localHashMap;
        oovvoo localOovvoo;
        int i;
        int j;
        int k;
        int m;
        int n;
        bТ042204220422Т04220422 = bТ0422Т0422Т04220422();
        b04220422Т0422Т04220422 = bТ0422Т0422Т04220422();
        if ((bТ042204220422Т04220422 + bТТ04220422Т04220422) * bТ042204220422Т04220422 % bТТТТ042204220422() != b0422042204220422Т04220422())
        {
          bТ042204220422Т04220422 = bТ0422Т0422Т04220422();
          b04220422Т0422Т04220422 = 88;
        }
        label132:
        return;
      }
      catch (Exception localException2)
      {
        throw localException2;
      }
      localException1 = localException1;
      throw localException1;
    }
    localOovvoo.b04280428ШШШ0428ШШ0428Ш(i, (String)localHashMap.get(xtxxtx.txxxtx.SYSTEM_BUBBLE_TEXT_COLOR));
    i = bТ042204220422Т04220422;
    j = bТТ04220422Т04220422;
    k = bТ042204220422Т04220422;
    m = b0422Т04220422Т04220422;
    n = b04220422Т0422Т04220422;
    if ((i + j) * k % m != n) {}
    switch (0)
    {
    }
    for (;;)
    {
      switch (0)
      {
      }
    }
  }
  
  public long getMessageSequence()
  {
    if ((bТ042204220422Т04220422 + bТТ04220422Т04220422) * bТ042204220422Т04220422 % b0422Т04220422Т04220422 != b04220422Т0422Т04220422)
    {
      if ((bТ042204220422Т04220422 + bТТ04220422Т04220422) * bТ042204220422Т04220422 % b0422Т04220422Т04220422 != b04220422Т0422Т04220422)
      {
        bТ042204220422Т04220422 = bТ0422Т0422Т04220422();
        b04220422Т0422Т04220422 = bТ0422Т0422Т04220422();
      }
      bТ042204220422Т04220422 = 98;
      b04220422Т0422Т04220422 = 18;
    }
    long l = this.mMessageSequence;
    switch (1)
    {
    case 0: 
    default: 
      for (;;)
      {
        switch (0)
        {
        }
      }
    }
    return l;
  }
  
  public void setMessageSequence(long paramLong)
  {
    try
    {
      this.mMessageSequence = paramLong;
      int i = bТ042204220422Т04220422;
      int j = bТТ04220422Т04220422;
      int k = b0422Т04220422Т04220422;
      switch (i * (j + i) % k)
      {
      }
      for (;;)
      {
        try
        {
          bТ042204220422Т04220422 = bТ0422Т0422Т04220422();
          b04220422Т0422Т04220422 = 17;
          i = bТ042204220422Т04220422;
          switch (i * (bТТ04220422Т04220422 + i) % b0422Т04220422Т04220422)
          {
          default: 
            bТ042204220422Т04220422 = 80;
            b04220422Т0422Т04220422 = 56;
          }
          switch (1)
          {
          case 0: 
          default: 
            switch (1)
            {
            }
            break;
          }
          return;
        }
        catch (Exception localException1)
        {
          throw localException1;
        }
      }
    }
    catch (Exception localException2)
    {
      throw localException2;
    }
  }
  
  /* Error */
  public void updateContentDescription()
  {
    // Byte code:
    //   0: aload_0
    //   1: getfield 134	com/liveperson/infra/messaging_ui/view/adapter/viewholder/AmsSystemMaskedViewHolder:mMessageTextView	Landroid/widget/TextView;
    //   4: invokevirtual 140	android/widget/TextView:getText	()Ljava/lang/CharSequence;
    //   7: astore 6
    //   9: getstatic 41	com/liveperson/infra/messaging_ui/view/adapter/viewholder/AmsSystemMaskedViewHolder:bТ042204220422Т04220422	I
    //   12: istore_1
    //   13: getstatic 35	com/liveperson/infra/messaging_ui/view/adapter/viewholder/AmsSystemMaskedViewHolder:bТТ04220422Т04220422	I
    //   16: istore_2
    //   17: getstatic 41	com/liveperson/infra/messaging_ui/view/adapter/viewholder/AmsSystemMaskedViewHolder:bТ042204220422Т04220422	I
    //   20: istore_3
    //   21: getstatic 37	com/liveperson/infra/messaging_ui/view/adapter/viewholder/AmsSystemMaskedViewHolder:b0422Т04220422Т04220422	I
    //   24: istore 4
    //   26: getstatic 39	com/liveperson/infra/messaging_ui/view/adapter/viewholder/AmsSystemMaskedViewHolder:b04220422Т0422Т04220422	I
    //   29: istore 5
    //   31: iload_1
    //   32: iload_2
    //   33: iadd
    //   34: iload_3
    //   35: imul
    //   36: iload 4
    //   38: irem
    //   39: iload 5
    //   41: if_icmpeq +57 -> 98
    //   44: bipush 56
    //   46: putstatic 41	com/liveperson/infra/messaging_ui/view/adapter/viewholder/AmsSystemMaskedViewHolder:bТ042204220422Т04220422	I
    //   49: bipush 55
    //   51: putstatic 39	com/liveperson/infra/messaging_ui/view/adapter/viewholder/AmsSystemMaskedViewHolder:b04220422Т0422Т04220422	I
    //   54: getstatic 41	com/liveperson/infra/messaging_ui/view/adapter/viewholder/AmsSystemMaskedViewHolder:bТ042204220422Т04220422	I
    //   57: istore_1
    //   58: iload_1
    //   59: getstatic 35	com/liveperson/infra/messaging_ui/view/adapter/viewholder/AmsSystemMaskedViewHolder:bТТ04220422Т04220422	I
    //   62: iload_1
    //   63: iadd
    //   64: imul
    //   65: invokestatic 123	com/liveperson/infra/messaging_ui/view/adapter/viewholder/AmsSystemMaskedViewHolder:bТТТТ042204220422	()I
    //   68: irem
    //   69: tableswitch	default:+19->88, 0:+29->98
    //   88: invokestatic 33	com/liveperson/infra/messaging_ui/view/adapter/viewholder/AmsSystemMaskedViewHolder:bТ0422Т0422Т04220422	()I
    //   91: putstatic 41	com/liveperson/infra/messaging_ui/view/adapter/viewholder/AmsSystemMaskedViewHolder:bТ042204220422Т04220422	I
    //   94: iconst_2
    //   95: putstatic 39	com/liveperson/infra/messaging_ui/view/adapter/viewholder/AmsSystemMaskedViewHolder:b04220422Т0422Т04220422	I
    //   98: aload_0
    //   99: aload 6
    //   101: invokeinterface 145 1 0
    //   106: invokevirtual 149	com/liveperson/infra/messaging_ui/view/adapter/viewholder/AmsSystemMaskedViewHolder:setContentDescription	(Ljava/lang/String;)V
    //   109: return
    //   110: astore 6
    //   112: aload 6
    //   114: athrow
    //   115: astore 6
    //   117: aload 6
    //   119: athrow
    //   120: astore 6
    //   122: aload 6
    //   124: athrow
    //   125: astore 6
    //   127: aload 6
    //   129: athrow
    // Local variable table:
    //   start	length	slot	name	signature
    //   0	130	0	this	AmsSystemMaskedViewHolder
    //   12	53	1	i	int
    //   16	18	2	j	int
    //   20	16	3	k	int
    //   24	15	4	m	int
    //   29	13	5	n	int
    //   7	93	6	localCharSequence	CharSequence
    //   110	3	6	localException1	Exception
    //   115	3	6	localException2	Exception
    //   120	3	6	localException3	Exception
    //   125	3	6	localException4	Exception
    // Exception table:
    //   from	to	target	type
    //   98	109	110	java/lang/Exception
    //   44	54	115	java/lang/Exception
    //   112	115	115	java/lang/Exception
    //   122	125	115	java/lang/Exception
    //   0	9	120	java/lang/Exception
    //   9	31	125	java/lang/Exception
  }
}
