package com.liveperson.infra.messaging_ui.view.adapter.viewholder;

import android.view.View;
import com.liveperson.infra.ui.view.adapter.viewholder.MiddleViewHolder;
import kkkkkk.jmjmjj;

public class UiUnreadIndicatorViewHolder
  extends MiddleViewHolder
  implements jmjmjj
{
  private static final String TAG;
  public static int b04220422Т0422042204220422 = 1;
  public static int b0422ТТ0422042204220422 = 10;
  public static int bТ0422Т0422042204220422 = 0;
  public static int bТТ04220422042204220422 = 2;
  
  /* Error */
  static
  {
    // Byte code:
    //   0: ldc 2
    //   2: invokevirtual 27	java/lang/Class:getSimpleName	()Ljava/lang/String;
    //   5: astore 5
    //   7: getstatic 29	com/liveperson/infra/messaging_ui/view/adapter/viewholder/UiUnreadIndicatorViewHolder:b0422ТТ0422042204220422	I
    //   10: istore_0
    //   11: getstatic 31	com/liveperson/infra/messaging_ui/view/adapter/viewholder/UiUnreadIndicatorViewHolder:b04220422Т0422042204220422	I
    //   14: istore_1
    //   15: getstatic 29	com/liveperson/infra/messaging_ui/view/adapter/viewholder/UiUnreadIndicatorViewHolder:b0422ТТ0422042204220422	I
    //   18: istore_2
    //   19: getstatic 33	com/liveperson/infra/messaging_ui/view/adapter/viewholder/UiUnreadIndicatorViewHolder:bТТ04220422042204220422	I
    //   22: istore_3
    //   23: getstatic 35	com/liveperson/infra/messaging_ui/view/adapter/viewholder/UiUnreadIndicatorViewHolder:bТ0422Т0422042204220422	I
    //   26: istore 4
    //   28: iload_0
    //   29: iload_1
    //   30: iadd
    //   31: iload_2
    //   32: imul
    //   33: iload_3
    //   34: irem
    //   35: iload 4
    //   37: if_icmpeq +58 -> 95
    //   40: getstatic 29	com/liveperson/infra/messaging_ui/view/adapter/viewholder/UiUnreadIndicatorViewHolder:b0422ТТ0422042204220422	I
    //   43: istore_0
    //   44: iload_0
    //   45: getstatic 31	com/liveperson/infra/messaging_ui/view/adapter/viewholder/UiUnreadIndicatorViewHolder:b04220422Т0422042204220422	I
    //   48: iload_0
    //   49: iadd
    //   50: imul
    //   51: invokestatic 39	com/liveperson/infra/messaging_ui/view/adapter/viewholder/UiUnreadIndicatorViewHolder:bТ042204220422042204220422	()I
    //   54: irem
    //   55: tableswitch	default:+17->72, 0:+29->84
    //   72: invokestatic 42	com/liveperson/infra/messaging_ui/view/adapter/viewholder/UiUnreadIndicatorViewHolder:b0422Т04220422042204220422	()I
    //   75: putstatic 29	com/liveperson/infra/messaging_ui/view/adapter/viewholder/UiUnreadIndicatorViewHolder:b0422ТТ0422042204220422	I
    //   78: invokestatic 42	com/liveperson/infra/messaging_ui/view/adapter/viewholder/UiUnreadIndicatorViewHolder:b0422Т04220422042204220422	()I
    //   81: putstatic 35	com/liveperson/infra/messaging_ui/view/adapter/viewholder/UiUnreadIndicatorViewHolder:bТ0422Т0422042204220422	I
    //   84: bipush 43
    //   86: putstatic 29	com/liveperson/infra/messaging_ui/view/adapter/viewholder/UiUnreadIndicatorViewHolder:b0422ТТ0422042204220422	I
    //   89: invokestatic 42	com/liveperson/infra/messaging_ui/view/adapter/viewholder/UiUnreadIndicatorViewHolder:b0422Т04220422042204220422	()I
    //   92: putstatic 35	com/liveperson/infra/messaging_ui/view/adapter/viewholder/UiUnreadIndicatorViewHolder:bТ0422Т0422042204220422	I
    //   95: aload 5
    //   97: putstatic 44	com/liveperson/infra/messaging_ui/view/adapter/viewholder/UiUnreadIndicatorViewHolder:TAG	Ljava/lang/String;
    //   100: return
    //   101: astore 5
    //   103: aload 5
    //   105: athrow
    //   106: astore 5
    //   108: aload 5
    //   110: athrow
    // Local variable table:
    //   start	length	slot	name	signature
    //   10	41	0	i	int
    //   14	17	1	j	int
    //   18	15	2	k	int
    //   22	13	3	m	int
    //   26	12	4	n	int
    //   5	91	5	str	String
    //   101	3	5	localException1	Exception
    //   106	3	5	localException2	Exception
    // Exception table:
    //   from	to	target	type
    //   0	19	101	java/lang/Exception
    //   23	28	101	java/lang/Exception
    //   95	100	101	java/lang/Exception
    //   19	23	106	java/lang/Exception
    //   84	95	106	java/lang/Exception
  }
  
  public UiUnreadIndicatorViewHolder(View paramView)
  {
    super(paramView);
    applyColors();
  }
  
  public static int b0421СССССС()
  {
    return 0;
  }
  
  public static int b0422Т04220422042204220422()
  {
    return 74;
  }
  
  public static int bС0421ССССС()
  {
    return 1;
  }
  
  public static int bТ042204220422042204220422()
  {
    return 2;
  }
  
  /* Error */
  public void applyChanges(android.os.Bundle paramBundle, kkkkkk.jjjmjj paramJjjmjj)
  {
    // Byte code:
    //   0: aload_0
    //   1: aload_1
    //   2: aload_2
    //   3: invokespecial 58	com/liveperson/infra/ui/view/adapter/viewholder/MiddleViewHolder:applyChanges	(Landroid/os/Bundle;Lkkkkkk/jjjmjj;)V
    //   6: getstatic 29	com/liveperson/infra/messaging_ui/view/adapter/viewholder/UiUnreadIndicatorViewHolder:b0422ТТ0422042204220422	I
    //   9: getstatic 31	com/liveperson/infra/messaging_ui/view/adapter/viewholder/UiUnreadIndicatorViewHolder:b04220422Т0422042204220422	I
    //   12: iadd
    //   13: getstatic 29	com/liveperson/infra/messaging_ui/view/adapter/viewholder/UiUnreadIndicatorViewHolder:b0422ТТ0422042204220422	I
    //   16: imul
    //   17: getstatic 33	com/liveperson/infra/messaging_ui/view/adapter/viewholder/UiUnreadIndicatorViewHolder:bТТ04220422042204220422	I
    //   20: irem
    //   21: invokestatic 60	com/liveperson/infra/messaging_ui/view/adapter/viewholder/UiUnreadIndicatorViewHolder:b0421СССССС	()I
    //   24: if_icmpeq +14 -> 38
    //   27: bipush 60
    //   29: putstatic 29	com/liveperson/infra/messaging_ui/view/adapter/viewholder/UiUnreadIndicatorViewHolder:b0422ТТ0422042204220422	I
    //   32: invokestatic 42	com/liveperson/infra/messaging_ui/view/adapter/viewholder/UiUnreadIndicatorViewHolder:b0422Т04220422042204220422	()I
    //   35: putstatic 35	com/liveperson/infra/messaging_ui/view/adapter/viewholder/UiUnreadIndicatorViewHolder:bТ0422Т0422042204220422	I
    //   38: getstatic 29	com/liveperson/infra/messaging_ui/view/adapter/viewholder/UiUnreadIndicatorViewHolder:b0422ТТ0422042204220422	I
    //   41: istore_3
    //   42: getstatic 31	com/liveperson/infra/messaging_ui/view/adapter/viewholder/UiUnreadIndicatorViewHolder:b04220422Т0422042204220422	I
    //   45: istore 4
    //   47: getstatic 29	com/liveperson/infra/messaging_ui/view/adapter/viewholder/UiUnreadIndicatorViewHolder:b0422ТТ0422042204220422	I
    //   50: istore 5
    //   52: getstatic 33	com/liveperson/infra/messaging_ui/view/adapter/viewholder/UiUnreadIndicatorViewHolder:bТТ04220422042204220422	I
    //   55: istore 6
    //   57: getstatic 35	com/liveperson/infra/messaging_ui/view/adapter/viewholder/UiUnreadIndicatorViewHolder:bТ0422Т0422042204220422	I
    //   60: istore 7
    //   62: iload_3
    //   63: iload 4
    //   65: iadd
    //   66: iload 5
    //   68: imul
    //   69: iload 6
    //   71: irem
    //   72: iload 7
    //   74: if_icmpeq +15 -> 89
    //   77: invokestatic 42	com/liveperson/infra/messaging_ui/view/adapter/viewholder/UiUnreadIndicatorViewHolder:b0422Т04220422042204220422	()I
    //   80: putstatic 29	com/liveperson/infra/messaging_ui/view/adapter/viewholder/UiUnreadIndicatorViewHolder:b0422ТТ0422042204220422	I
    //   83: invokestatic 42	com/liveperson/infra/messaging_ui/view/adapter/viewholder/UiUnreadIndicatorViewHolder:b0422Т04220422042204220422	()I
    //   86: putstatic 35	com/liveperson/infra/messaging_ui/view/adapter/viewholder/UiUnreadIndicatorViewHolder:bТ0422Т0422042204220422	I
    //   89: aload_1
    //   90: ldc 62
    //   92: bipush 53
    //   94: bipush 77
    //   96: iconst_0
    //   97: invokestatic 68	kkkkkk/gguuuu:bк043Aккк043Aкк043A043A	(Ljava/lang/String;CCC)Ljava/lang/String;
    //   100: aconst_null
    //   101: invokevirtual 74	android/os/Bundle:getString	(Ljava/lang/String;Ljava/lang/String;)Ljava/lang/String;
    //   104: astore_1
    //   105: aload_1
    //   106: invokestatic 80	android/text/TextUtils:isEmpty	(Ljava/lang/CharSequence;)Z
    //   109: istore 8
    //   111: iload 8
    //   113: ifne +8 -> 121
    //   116: aload_0
    //   117: aload_1
    //   118: invokevirtual 84	com/liveperson/infra/messaging_ui/view/adapter/viewholder/UiUnreadIndicatorViewHolder:setMessageTextView	(Ljava/lang/String;)V
    //   121: aload_0
    //   122: invokevirtual 87	com/liveperson/infra/messaging_ui/view/adapter/viewholder/UiUnreadIndicatorViewHolder:updateContentDescription	()V
    //   125: return
    //   126: astore_1
    //   127: aload_1
    //   128: athrow
    //   129: astore_1
    //   130: aload_1
    //   131: athrow
    //   132: astore_1
    //   133: aload_1
    //   134: athrow
    //   135: astore_1
    //   136: aload_1
    //   137: athrow
    // Local variable table:
    //   start	length	slot	name	signature
    //   0	138	0	this	UiUnreadIndicatorViewHolder
    //   0	138	1	paramBundle	android.os.Bundle
    //   0	138	2	paramJjjmjj	kkkkkk.jjjmjj
    //   41	25	3	i	int
    //   45	21	4	j	int
    //   50	19	5	k	int
    //   55	17	6	m	int
    //   60	15	7	n	int
    //   109	3	8	bool	boolean
    // Exception table:
    //   from	to	target	type
    //   0	6	126	java/lang/Exception
    //   116	121	126	java/lang/Exception
    //   121	125	126	java/lang/Exception
    //   38	62	129	java/lang/Exception
    //   127	129	129	java/lang/Exception
    //   133	135	129	java/lang/Exception
    //   89	111	132	java/lang/Exception
    //   77	89	135	java/lang/Exception
  }
  
  /* Error */
  public void applyColors()
  {
    // Byte code:
    //   0: invokestatic 93	kkkkkk/hbhbhb:bШШ0428ШШШШ04280428Ш	()Lkkkkkk/hbhbhb;
    //   3: invokevirtual 97	kkkkkk/hbhbhb:b04280428ШШШШШ04280428Ш	()Ljava/util/HashMap;
    //   6: astore 7
    //   8: aload 7
    //   10: invokevirtual 102	java/util/HashMap:isEmpty	()Z
    //   13: ifne +141 -> 154
    //   16: new 104	kkkkkk/oovvoo
    //   19: dup
    //   20: aload_0
    //   21: getfield 108	com/liveperson/infra/messaging_ui/view/adapter/viewholder/UiUnreadIndicatorViewHolder:itemView	Landroid/view/View;
    //   24: invokespecial 109	kkkkkk/oovvoo:<init>	(Landroid/view/View;)V
    //   27: astore 6
    //   29: goto +136 -> 165
    //   32: getstatic 114	com/liveperson/infra/messaging_ui/R$id:lpui_message_text	I
    //   35: istore_1
    //   36: aload 7
    //   38: getstatic 120	kkkkkk/xtxxtx$txxxtx:UNREAD_INDICATOR_BUBBLE_TEXT_COLOR	Lkkkkkk/xtxxtx$txxxtx;
    //   41: invokevirtual 124	java/util/HashMap:get	(Ljava/lang/Object;)Ljava/lang/Object;
    //   44: checkcast 126	java/lang/String
    //   47: astore 7
    //   49: getstatic 29	com/liveperson/infra/messaging_ui/view/adapter/viewholder/UiUnreadIndicatorViewHolder:b0422ТТ0422042204220422	I
    //   52: istore_2
    //   53: getstatic 31	com/liveperson/infra/messaging_ui/view/adapter/viewholder/UiUnreadIndicatorViewHolder:b04220422Т0422042204220422	I
    //   56: istore_3
    //   57: getstatic 33	com/liveperson/infra/messaging_ui/view/adapter/viewholder/UiUnreadIndicatorViewHolder:bТТ04220422042204220422	I
    //   60: istore 4
    //   62: getstatic 29	com/liveperson/infra/messaging_ui/view/adapter/viewholder/UiUnreadIndicatorViewHolder:b0422ТТ0422042204220422	I
    //   65: istore 5
    //   67: iload 5
    //   69: invokestatic 128	com/liveperson/infra/messaging_ui/view/adapter/viewholder/UiUnreadIndicatorViewHolder:bС0421ССССС	()I
    //   72: iload 5
    //   74: iadd
    //   75: imul
    //   76: getstatic 33	com/liveperson/infra/messaging_ui/view/adapter/viewholder/UiUnreadIndicatorViewHolder:bТТ04220422042204220422	I
    //   79: irem
    //   80: tableswitch	default:+20->100, 0:+31->111
    //   100: invokestatic 42	com/liveperson/infra/messaging_ui/view/adapter/viewholder/UiUnreadIndicatorViewHolder:b0422Т04220422042204220422	()I
    //   103: putstatic 29	com/liveperson/infra/messaging_ui/view/adapter/viewholder/UiUnreadIndicatorViewHolder:b0422ТТ0422042204220422	I
    //   106: bipush 25
    //   108: putstatic 35	com/liveperson/infra/messaging_ui/view/adapter/viewholder/UiUnreadIndicatorViewHolder:bТ0422Т0422042204220422	I
    //   111: iload_2
    //   112: iload_3
    //   113: iload_2
    //   114: iadd
    //   115: imul
    //   116: iload 4
    //   118: irem
    //   119: tableswitch	default:+17->136, 0:+27->146
    //   136: bipush 22
    //   138: putstatic 29	com/liveperson/infra/messaging_ui/view/adapter/viewholder/UiUnreadIndicatorViewHolder:b0422ТТ0422042204220422	I
    //   141: bipush 20
    //   143: putstatic 35	com/liveperson/infra/messaging_ui/view/adapter/viewholder/UiUnreadIndicatorViewHolder:bТ0422Т0422042204220422	I
    //   146: aload 6
    //   148: iload_1
    //   149: aload 7
    //   151: invokevirtual 132	kkkkkk/oovvoo:b04280428ШШШ0428ШШ0428Ш	(ILjava/lang/String;)V
    //   154: return
    //   155: astore 6
    //   157: aload 6
    //   159: athrow
    //   160: astore 6
    //   162: aload 6
    //   164: athrow
    //   165: iconst_0
    //   166: tableswitch	default:+22->188, 0:+-134->32, 1:+-1->165
    //   188: iconst_0
    //   189: tableswitch	default:+23->212, 0:+-157->32, 1:+-24->165
    //   212: goto -24 -> 188
    // Local variable table:
    //   start	length	slot	name	signature
    //   0	215	0	this	UiUnreadIndicatorViewHolder
    //   35	114	1	i	int
    //   52	64	2	j	int
    //   56	59	3	k	int
    //   60	59	4	m	int
    //   65	11	5	n	int
    //   27	120	6	localOovvoo	kkkkkk.oovvoo
    //   155	3	6	localException1	Exception
    //   160	3	6	localException2	Exception
    //   6	144	7	localObject	Object
    // Exception table:
    //   from	to	target	type
    //   0	29	155	java/lang/Exception
    //   32	36	155	java/lang/Exception
    //   146	154	155	java/lang/Exception
    //   36	49	160	java/lang/Exception
  }
  
  /* Error */
  public void updateContentDescription()
  {
    // Byte code:
    //   0: getstatic 29	com/liveperson/infra/messaging_ui/view/adapter/viewholder/UiUnreadIndicatorViewHolder:b0422ТТ0422042204220422	I
    //   3: getstatic 31	com/liveperson/infra/messaging_ui/view/adapter/viewholder/UiUnreadIndicatorViewHolder:b04220422Т0422042204220422	I
    //   6: iadd
    //   7: getstatic 29	com/liveperson/infra/messaging_ui/view/adapter/viewholder/UiUnreadIndicatorViewHolder:b0422ТТ0422042204220422	I
    //   10: imul
    //   11: getstatic 33	com/liveperson/infra/messaging_ui/view/adapter/viewholder/UiUnreadIndicatorViewHolder:bТТ04220422042204220422	I
    //   14: irem
    //   15: getstatic 35	com/liveperson/infra/messaging_ui/view/adapter/viewholder/UiUnreadIndicatorViewHolder:bТ0422Т0422042204220422	I
    //   18: if_icmpeq +13 -> 31
    //   21: bipush 62
    //   23: putstatic 29	com/liveperson/infra/messaging_ui/view/adapter/viewholder/UiUnreadIndicatorViewHolder:b0422ТТ0422042204220422	I
    //   26: bipush 96
    //   28: putstatic 35	com/liveperson/infra/messaging_ui/view/adapter/viewholder/UiUnreadIndicatorViewHolder:bТ0422Т0422042204220422	I
    //   31: aload_0
    //   32: getfield 136	com/liveperson/infra/messaging_ui/view/adapter/viewholder/UiUnreadIndicatorViewHolder:mMessageTextView	Landroid/widget/TextView;
    //   35: astore 4
    //   37: aload 4
    //   39: invokevirtual 142	android/widget/TextView:getText	()Ljava/lang/CharSequence;
    //   42: invokeinterface 147 1 0
    //   47: astore 4
    //   49: getstatic 29	com/liveperson/infra/messaging_ui/view/adapter/viewholder/UiUnreadIndicatorViewHolder:b0422ТТ0422042204220422	I
    //   52: istore_1
    //   53: getstatic 31	com/liveperson/infra/messaging_ui/view/adapter/viewholder/UiUnreadIndicatorViewHolder:b04220422Т0422042204220422	I
    //   56: istore_2
    //   57: getstatic 33	com/liveperson/infra/messaging_ui/view/adapter/viewholder/UiUnreadIndicatorViewHolder:bТТ04220422042204220422	I
    //   60: istore_3
    //   61: iload_1
    //   62: iload_2
    //   63: iload_1
    //   64: iadd
    //   65: imul
    //   66: iload_3
    //   67: irem
    //   68: tableswitch	default:+20->88, 0:+32->100
    //   88: invokestatic 42	com/liveperson/infra/messaging_ui/view/adapter/viewholder/UiUnreadIndicatorViewHolder:b0422Т04220422042204220422	()I
    //   91: putstatic 29	com/liveperson/infra/messaging_ui/view/adapter/viewholder/UiUnreadIndicatorViewHolder:b0422ТТ0422042204220422	I
    //   94: invokestatic 42	com/liveperson/infra/messaging_ui/view/adapter/viewholder/UiUnreadIndicatorViewHolder:b0422Т04220422042204220422	()I
    //   97: putstatic 35	com/liveperson/infra/messaging_ui/view/adapter/viewholder/UiUnreadIndicatorViewHolder:bТ0422Т0422042204220422	I
    //   100: aload_0
    //   101: aload 4
    //   103: invokevirtual 150	com/liveperson/infra/messaging_ui/view/adapter/viewholder/UiUnreadIndicatorViewHolder:setContentDescription	(Ljava/lang/String;)V
    //   106: return
    //   107: astore 4
    //   109: aload 4
    //   111: athrow
    //   112: astore 4
    //   114: aload 4
    //   116: athrow
    //   117: astore 4
    //   119: aload 4
    //   121: athrow
    //   122: astore 4
    //   124: aload 4
    //   126: athrow
    // Local variable table:
    //   start	length	slot	name	signature
    //   0	127	0	this	UiUnreadIndicatorViewHolder
    //   52	14	1	i	int
    //   56	9	2	j	int
    //   60	8	3	k	int
    //   35	67	4	localObject	Object
    //   107	3	4	localException1	Exception
    //   112	3	4	localException2	Exception
    //   117	3	4	localException3	Exception
    //   122	3	4	localException4	Exception
    // Exception table:
    //   from	to	target	type
    //   31	37	107	java/lang/Exception
    //   100	106	107	java/lang/Exception
    //   88	100	112	java/lang/Exception
    //   109	112	112	java/lang/Exception
    //   119	122	112	java/lang/Exception
    //   37	49	117	java/lang/Exception
    //   49	61	122	java/lang/Exception
  }
}
