package com.mobile.ui.registration.success;

import android.widget.TextView;
import butterknife.BindView;
import butterknife.OnClick;
import com.mobile.ui.common.fragment.BasePresentationFragment;
import kkkkkk.ffrfrf;
import kkkkkk.frffrf;
import kkkkkk.iiisis.siisis;

public class RegistrationSuccessFragment
  extends BasePresentationFragment<frffrf, ffrfrf>
  implements iiisis.siisis, frffrf
{
  public static int b042C042C042CЬ042CЬЬ042C042C = 1;
  public static int b042CЬ042CЬ042CЬЬ042C042C = 69;
  public static int bЬ042C042CЬ042CЬЬ042C042C = 0;
  public static int bЬЬЬ042C042CЬЬ042C042C = 2;
  @BindView(2131494293)
  public TextView mTextView;
  
  public RegistrationSuccessFragment() {}
  
  public static int b042C042C042C042C042CЬЬ042C042C()
  {
    return 1;
  }
  
  public static int b042CЬЬ042C042CЬЬ042C042C()
  {
    return 80;
  }
  
  public static int bЬ042CЬ042C042CЬЬ042C042C()
  {
    return 2;
  }
  
  public static int bЬ042CЬЬЬ042CЬ042C042C()
  {
    return 0;
  }
  
  /* Error */
  public static RegistrationSuccessFragment newInstance()
  {
    // Byte code:
    //   0: new 2	com/mobile/ui/registration/success/RegistrationSuccessFragment
    //   3: dup
    //   4: invokespecial 38	com/mobile/ui/registration/success/RegistrationSuccessFragment:<init>	()V
    //   7: astore 5
    //   9: getstatic 40	com/mobile/ui/registration/success/RegistrationSuccessFragment:b042CЬ042CЬ042CЬЬ042C042C	I
    //   12: istore_0
    //   13: getstatic 42	com/mobile/ui/registration/success/RegistrationSuccessFragment:b042C042C042CЬ042CЬЬ042C042C	I
    //   16: istore_1
    //   17: getstatic 40	com/mobile/ui/registration/success/RegistrationSuccessFragment:b042CЬ042CЬ042CЬЬ042C042C	I
    //   20: istore_2
    //   21: iload_2
    //   22: getstatic 42	com/mobile/ui/registration/success/RegistrationSuccessFragment:b042C042C042CЬ042CЬЬ042C042C	I
    //   25: iload_2
    //   26: iadd
    //   27: imul
    //   28: getstatic 44	com/mobile/ui/registration/success/RegistrationSuccessFragment:bЬЬЬ042C042CЬЬ042C042C	I
    //   31: irem
    //   32: tableswitch	default:+20->52, 0:+32->64
    //   52: invokestatic 46	com/mobile/ui/registration/success/RegistrationSuccessFragment:b042CЬЬ042C042CЬЬ042C042C	()I
    //   55: putstatic 40	com/mobile/ui/registration/success/RegistrationSuccessFragment:b042CЬ042CЬ042CЬЬ042C042C	I
    //   58: invokestatic 46	com/mobile/ui/registration/success/RegistrationSuccessFragment:b042CЬЬ042C042CЬЬ042C042C	()I
    //   61: putstatic 48	com/mobile/ui/registration/success/RegistrationSuccessFragment:bЬ042C042CЬ042CЬЬ042C042C	I
    //   64: getstatic 40	com/mobile/ui/registration/success/RegistrationSuccessFragment:b042CЬ042CЬ042CЬЬ042C042C	I
    //   67: istore_2
    //   68: getstatic 44	com/mobile/ui/registration/success/RegistrationSuccessFragment:bЬЬЬ042C042CЬЬ042C042C	I
    //   71: istore_3
    //   72: getstatic 48	com/mobile/ui/registration/success/RegistrationSuccessFragment:bЬ042C042CЬ042CЬЬ042C042C	I
    //   75: istore 4
    //   77: iload_0
    //   78: iload_1
    //   79: iadd
    //   80: iload_2
    //   81: imul
    //   82: iload_3
    //   83: irem
    //   84: iload 4
    //   86: if_icmpeq +15 -> 101
    //   89: invokestatic 46	com/mobile/ui/registration/success/RegistrationSuccessFragment:b042CЬЬ042C042CЬЬ042C042C	()I
    //   92: putstatic 40	com/mobile/ui/registration/success/RegistrationSuccessFragment:b042CЬ042CЬ042CЬЬ042C042C	I
    //   95: invokestatic 46	com/mobile/ui/registration/success/RegistrationSuccessFragment:b042CЬЬ042C042CЬЬ042C042C	()I
    //   98: putstatic 48	com/mobile/ui/registration/success/RegistrationSuccessFragment:bЬ042C042CЬ042CЬЬ042C042C	I
    //   101: aload 5
    //   103: areturn
    //   104: astore 5
    //   106: aload 5
    //   108: athrow
    //   109: astore 5
    //   111: aload 5
    //   113: athrow
    // Local variable table:
    //   start	length	slot	name	signature
    //   12	68	0	i	int
    //   16	64	1	j	int
    //   20	62	2	k	int
    //   71	13	3	m	int
    //   75	12	4	n	int
    //   7	95	5	localRegistrationSuccessFragment	RegistrationSuccessFragment
    //   104	3	5	localException1	Exception
    //   109	3	5	localException2	Exception
    // Exception table:
    //   from	to	target	type
    //   9	17	104	java/lang/Exception
    //   64	77	104	java/lang/Exception
    //   0	9	109	java/lang/Exception
    //   89	101	109	java/lang/Exception
  }
  
  /* Error */
  @android.support.annotation.Nullable
  public String getAccessibilityScreenTitle()
  {
    // Byte code:
    //   0: getstatic 40	com/mobile/ui/registration/success/RegistrationSuccessFragment:b042CЬ042CЬ042CЬЬ042C042C	I
    //   3: getstatic 42	com/mobile/ui/registration/success/RegistrationSuccessFragment:b042C042C042CЬ042CЬЬ042C042C	I
    //   6: iadd
    //   7: getstatic 40	com/mobile/ui/registration/success/RegistrationSuccessFragment:b042CЬ042CЬ042CЬЬ042C042C	I
    //   10: imul
    //   11: getstatic 44	com/mobile/ui/registration/success/RegistrationSuccessFragment:bЬЬЬ042C042CЬЬ042C042C	I
    //   14: irem
    //   15: getstatic 48	com/mobile/ui/registration/success/RegistrationSuccessFragment:bЬ042C042CЬ042CЬЬ042C042C	I
    //   18: if_icmpeq +17 -> 35
    //   21: invokestatic 46	com/mobile/ui/registration/success/RegistrationSuccessFragment:b042CЬЬ042C042CЬЬ042C042C	()I
    //   24: istore_1
    //   25: iload_1
    //   26: putstatic 40	com/mobile/ui/registration/success/RegistrationSuccessFragment:b042CЬ042CЬ042CЬЬ042C042C	I
    //   29: invokestatic 46	com/mobile/ui/registration/success/RegistrationSuccessFragment:b042CЬЬ042C042CЬЬ042C042C	()I
    //   32: putstatic 48	com/mobile/ui/registration/success/RegistrationSuccessFragment:bЬ042C042CЬ042CЬЬ042C042C	I
    //   35: getstatic 56	com/mobile/ui/R$string:accessibility_registration_success_screen_title	I
    //   38: istore_1
    //   39: aload_0
    //   40: iload_1
    //   41: invokevirtual 60	com/mobile/ui/registration/success/RegistrationSuccessFragment:getString	(I)Ljava/lang/String;
    //   44: astore_2
    //   45: getstatic 40	com/mobile/ui/registration/success/RegistrationSuccessFragment:b042CЬ042CЬ042CЬЬ042C042C	I
    //   48: getstatic 42	com/mobile/ui/registration/success/RegistrationSuccessFragment:b042C042C042CЬ042CЬЬ042C042C	I
    //   51: iadd
    //   52: getstatic 40	com/mobile/ui/registration/success/RegistrationSuccessFragment:b042CЬ042CЬ042CЬЬ042C042C	I
    //   55: imul
    //   56: invokestatic 62	com/mobile/ui/registration/success/RegistrationSuccessFragment:bЬ042CЬ042C042CЬЬ042C042C	()I
    //   59: irem
    //   60: getstatic 48	com/mobile/ui/registration/success/RegistrationSuccessFragment:bЬ042C042CЬ042CЬЬ042C042C	I
    //   63: if_icmpeq +14 -> 77
    //   66: bipush 34
    //   68: putstatic 40	com/mobile/ui/registration/success/RegistrationSuccessFragment:b042CЬ042CЬ042CЬЬ042C042C	I
    //   71: invokestatic 46	com/mobile/ui/registration/success/RegistrationSuccessFragment:b042CЬЬ042C042CЬЬ042C042C	()I
    //   74: putstatic 48	com/mobile/ui/registration/success/RegistrationSuccessFragment:bЬ042C042CЬ042CЬЬ042C042C	I
    //   77: aload_2
    //   78: areturn
    //   79: astore_2
    //   80: aload_2
    //   81: athrow
    //   82: astore_2
    //   83: aload_2
    //   84: athrow
    //   85: astore_2
    //   86: aload_2
    //   87: athrow
    //   88: astore_2
    //   89: aload_2
    //   90: athrow
    // Local variable table:
    //   start	length	slot	name	signature
    //   0	91	0	this	RegistrationSuccessFragment
    //   24	17	1	i	int
    //   44	34	2	str	String
    //   79	2	2	localException1	Exception
    //   82	2	2	localException2	Exception
    //   85	2	2	localException3	Exception
    //   88	2	2	localException4	Exception
    // Exception table:
    //   from	to	target	type
    //   35	39	79	java/lang/Exception
    //   0	25	82	java/lang/Exception
    //   80	82	82	java/lang/Exception
    //   39	45	85	java/lang/Exception
    //   25	35	88	java/lang/Exception
    //   86	88	88	java/lang/Exception
  }
  
  public boolean onBackPressed()
  {
    if ((b042CЬ042CЬ042CЬЬ042C042C + b042C042C042CЬ042CЬЬ042C042C) * b042CЬ042CЬ042CЬЬ042C042C % bЬЬЬ042C042CЬЬ042C042C != bЬ042C042CЬ042CЬЬ042C042C)
    {
      b042CЬ042CЬ042CЬЬ042C042C = b042CЬЬ042C042CЬЬ042C042C();
      bЬ042C042CЬ042CЬЬ042C042C = b042CЬЬ042C042CЬЬ042C042C();
    }
    return true;
  }
  
  @OnClick({2131494294})
  public void onContinuePressed(TextView paramTextView)
  {
    throw new Runtime("d2j fail translate: java.lang.IndexOutOfBoundsException: fromIndex < 0: -1\n\tat java.util.BitSet.nextSetBit(BitSet.java:712)\n\tat com.googlecode.dex2jar.ir.ts.array.FillArrayTransformer.makeSureAllElementAreAssigned(FillArrayTransformer.java:505)\n\tat com.googlecode.dex2jar.ir.ts.array.FillArrayTransformer.transformReportChanged(FillArrayTransformer.java:123)\n\tat com.googlecode.dex2jar.ir.ts.StatedTransformer.transform(StatedTransformer.java:10)\n\tat com.googlecode.d2j.dex.Dex2jar$2.optimize(Dex2jar.java:149)\n\tat com.googlecode.d2j.dex.Dex2Asm.convertCode(Dex2Asm.java:414)\n\tat com.googlecode.d2j.dex.ExDex2Asm.convertCode(ExDex2Asm.java:42)\n\tat com.googlecode.d2j.dex.Dex2jar$2.convertCode(Dex2jar.java:128)\n\tat com.googlecode.d2j.dex.Dex2Asm.convertMethod(Dex2Asm.java:509)\n\tat com.googlecode.d2j.dex.Dex2Asm.convertClass(Dex2Asm.java:406)\n\tat com.googlecode.d2j.dex.Dex2Asm.convertDex(Dex2Asm.java:422)\n\tat com.googlecode.d2j.dex.Dex2jar.doTranslate(Dex2jar.java:172)\n\tat com.googlecode.d2j.dex.Dex2jar.to(Dex2jar.java:272)\n\tat com.googlecode.dex2jar.tools.Dex2jarCmd.doCommandLine(Dex2jarCmd.java:108)\n\tat com.googlecode.dex2jar.tools.BaseCmd.doMain(BaseCmd.java:288)\n\tat com.googlecode.dex2jar.tools.Dex2jarCmd.main(Dex2jarCmd.java:32)\n");
  }
  
  /* Error */
  public void onCreate(@android.support.annotation.Nullable android.os.Bundle paramBundle)
  {
    // Byte code:
    //   0: iconst_4
    //   1: istore_2
    //   2: aload_0
    //   3: aload_1
    //   4: invokespecial 82	com/mobile/ui/common/fragment/BasePresentationFragment:onCreate	(Landroid/os/Bundle;)V
    //   7: invokestatic 88	com/mobile/ui/App:get	()Lcom/mobile/ui/App;
    //   10: invokevirtual 92	com/mobile/ui/App:getAppComponent	()Lkkkkkk/uyyyyy;
    //   13: aload_0
    //   14: invokeinterface 98 2 0
    //   19: iload_2
    //   20: iconst_0
    //   21: idiv
    //   22: istore_2
    //   23: goto -4 -> 19
    //   26: astore_1
    //   27: aload_1
    //   28: athrow
    //   29: astore_1
    //   30: bipush 7
    //   32: putstatic 40	com/mobile/ui/registration/success/RegistrationSuccessFragment:b042CЬ042CЬ042CЬЬ042C042C	I
    //   35: return
    // Local variable table:
    //   start	length	slot	name	signature
    //   0	36	0	this	RegistrationSuccessFragment
    //   0	36	1	paramBundle	android.os.Bundle
    //   1	22	2	i	int
    // Exception table:
    //   from	to	target	type
    //   2	19	26	java/lang/Exception
    //   19	23	29	java/lang/Exception
  }
  
  /* Error */
  @android.support.annotation.Nullable
  public android.view.View onCreateView(android.view.LayoutInflater paramLayoutInflater, @android.support.annotation.Nullable android.view.ViewGroup paramViewGroup, @android.support.annotation.Nullable android.os.Bundle paramBundle)
  {
    // Byte code:
    //   0: iconst_0
    //   1: tableswitch	default:+23->24, 0:+50->51, 1:+-1->0
    //   24: iconst_1
    //   25: tableswitch	default:+23->48, 0:+-25->0, 1:+26->51
    //   48: goto -24 -> 24
    //   51: getstatic 106	com/mobile/ui/R$layout:fragment_registration_success	I
    //   54: istore 4
    //   56: getstatic 40	com/mobile/ui/registration/success/RegistrationSuccessFragment:b042CЬ042CЬ042CЬЬ042C042C	I
    //   59: istore 5
    //   61: getstatic 42	com/mobile/ui/registration/success/RegistrationSuccessFragment:b042C042C042CЬ042CЬЬ042C042C	I
    //   64: istore 6
    //   66: getstatic 40	com/mobile/ui/registration/success/RegistrationSuccessFragment:b042CЬ042CЬ042CЬЬ042C042C	I
    //   69: istore 7
    //   71: getstatic 44	com/mobile/ui/registration/success/RegistrationSuccessFragment:bЬЬЬ042C042CЬЬ042C042C	I
    //   74: istore 8
    //   76: getstatic 48	com/mobile/ui/registration/success/RegistrationSuccessFragment:bЬ042C042CЬ042CЬЬ042C042C	I
    //   79: istore 9
    //   81: getstatic 40	com/mobile/ui/registration/success/RegistrationSuccessFragment:b042CЬ042CЬ042CЬЬ042C042C	I
    //   84: getstatic 42	com/mobile/ui/registration/success/RegistrationSuccessFragment:b042C042C042CЬ042CЬЬ042C042C	I
    //   87: iadd
    //   88: getstatic 40	com/mobile/ui/registration/success/RegistrationSuccessFragment:b042CЬ042CЬ042CЬЬ042C042C	I
    //   91: imul
    //   92: getstatic 44	com/mobile/ui/registration/success/RegistrationSuccessFragment:bЬЬЬ042C042CЬЬ042C042C	I
    //   95: irem
    //   96: invokestatic 108	com/mobile/ui/registration/success/RegistrationSuccessFragment:bЬ042CЬЬЬ042CЬ042C042C	()I
    //   99: if_icmpeq +14 -> 113
    //   102: bipush 93
    //   104: putstatic 40	com/mobile/ui/registration/success/RegistrationSuccessFragment:b042CЬ042CЬ042CЬЬ042C042C	I
    //   107: invokestatic 46	com/mobile/ui/registration/success/RegistrationSuccessFragment:b042CЬЬ042C042CЬЬ042C042C	()I
    //   110: putstatic 48	com/mobile/ui/registration/success/RegistrationSuccessFragment:bЬ042C042CЬ042CЬЬ042C042C	I
    //   113: iload 5
    //   115: iload 6
    //   117: iadd
    //   118: iload 7
    //   120: imul
    //   121: iload 8
    //   123: irem
    //   124: iload 9
    //   126: if_icmpeq +14 -> 140
    //   129: invokestatic 46	com/mobile/ui/registration/success/RegistrationSuccessFragment:b042CЬЬ042C042CЬЬ042C042C	()I
    //   132: putstatic 40	com/mobile/ui/registration/success/RegistrationSuccessFragment:b042CЬ042CЬ042CЬЬ042C042C	I
    //   135: bipush 33
    //   137: putstatic 48	com/mobile/ui/registration/success/RegistrationSuccessFragment:bЬ042C042CЬ042CЬЬ042C042C	I
    //   140: aload_1
    //   141: iload 4
    //   143: aload_2
    //   144: iconst_0
    //   145: invokevirtual 114	android/view/LayoutInflater:inflate	(ILandroid/view/ViewGroup;Z)Landroid/view/View;
    //   148: astore_1
    //   149: aload_1
    //   150: areturn
    //   151: astore_1
    //   152: aload_1
    //   153: athrow
    //   154: astore_1
    //   155: aload_1
    //   156: athrow
    // Local variable table:
    //   start	length	slot	name	signature
    //   0	157	0	this	RegistrationSuccessFragment
    //   0	157	1	paramLayoutInflater	android.view.LayoutInflater
    //   0	157	2	paramViewGroup	android.view.ViewGroup
    //   0	157	3	paramBundle	android.os.Bundle
    //   54	88	4	i	int
    //   59	59	5	j	int
    //   64	54	6	k	int
    //   69	52	7	m	int
    //   74	50	8	n	int
    //   79	48	9	i1	int
    // Exception table:
    //   from	to	target	type
    //   129	135	151	java/lang/Exception
    //   140	149	151	java/lang/Exception
    //   51	81	154	java/lang/Exception
    //   135	140	154	java/lang/Exception
  }
  
  public void showSuccessMessageForCommercialUser()
  {
    throw new Runtime("d2j fail translate: java.lang.IndexOutOfBoundsException: fromIndex < 0: -1\n\tat java.util.BitSet.nextSetBit(BitSet.java:712)\n\tat com.googlecode.dex2jar.ir.ts.array.FillArrayTransformer.makeSureAllElementAreAssigned(FillArrayTransformer.java:505)\n\tat com.googlecode.dex2jar.ir.ts.array.FillArrayTransformer.transformReportChanged(FillArrayTransformer.java:123)\n\tat com.googlecode.dex2jar.ir.ts.StatedTransformer.transform(StatedTransformer.java:10)\n\tat com.googlecode.d2j.dex.Dex2jar$2.optimize(Dex2jar.java:149)\n\tat com.googlecode.d2j.dex.Dex2Asm.convertCode(Dex2Asm.java:414)\n\tat com.googlecode.d2j.dex.ExDex2Asm.convertCode(ExDex2Asm.java:42)\n\tat com.googlecode.d2j.dex.Dex2jar$2.convertCode(Dex2jar.java:128)\n\tat com.googlecode.d2j.dex.Dex2Asm.convertMethod(Dex2Asm.java:509)\n\tat com.googlecode.d2j.dex.Dex2Asm.convertClass(Dex2Asm.java:406)\n\tat com.googlecode.d2j.dex.Dex2Asm.convertDex(Dex2Asm.java:422)\n\tat com.googlecode.d2j.dex.Dex2jar.doTranslate(Dex2jar.java:172)\n\tat com.googlecode.d2j.dex.Dex2jar.to(Dex2jar.java:272)\n\tat com.googlecode.dex2jar.tools.Dex2jarCmd.doCommandLine(Dex2jarCmd.java:108)\n\tat com.googlecode.dex2jar.tools.BaseCmd.doMain(BaseCmd.java:288)\n\tat com.googlecode.dex2jar.tools.Dex2jarCmd.main(Dex2jarCmd.java:32)\n");
  }
  
  public void trackScreenView()
  {
    try
    {
      ((ffrfrf)this.mPresenter).bшшшш0448044804480448шш();
      return;
    }
    catch (Exception localException)
    {
      throw localException;
    }
  }
}
