package com.mobile.ui.mobilechat.activity;

import android.content.Context;
import android.content.Intent;
import android.content.res.Resources;
import android.os.Build.VERSION;
import android.os.Bundle;
import android.support.annotation.NonNull;
import android.view.Window;
import com.liveperson.api.sdk.LPConversationData;
import com.liveperson.messaging.model.AgentData;
import com.mobile.ui.R.color;
import com.mobile.ui.R.string;
import com.mobile.ui.common.activity.AppTimeoutActivity;
import kkkkkk.dxdddx;
import kkkkkk.gguuuu;
import kkkkkk.jaajaa;
import kkkkkk.nkkkkk;
import kkkkkk.nknnkk;
import kkkkkk.nnnkkk;
import kkkkkk.wnwnwn;
import kkkkkk.xddxdd;
import kkkkkk.xdxxdx;
import kkkkkk.xxxxdd;
import kkkkkk.ykkyky;

public class MobileChatActivity
  extends AppTimeoutActivity
  implements wnwnwn
{
  private static final String ARG_USER_FIRST_NAME = "\003\025\013$\033\032\r\033)\021\025\037!#/\037\023 \031";
  private static final String ARG_USER_LAST_NAME = "[mc|sres\002oexz\007vjwp";
  public static int b04270427Ч042704270427ЧЧ = 29;
  public static int b0427Ч0427042704270427ЧЧ = 2;
  public static int b0427ЧЧ0427ЧЧ0427Ч = 0;
  public static int bЧЧ0427042704270427ЧЧ = 1;
  
  static
  {
    String str = ARG_USER_FIRST_NAME;
    switch (0)
    {
    case 1: 
    default: 
      for (;;)
      {
        switch (0)
        {
        }
      }
    }
    ARG_USER_FIRST_NAME = gguuuu.bккккк043Aкк043A043A(str, '`', '\004');
    str = ARG_USER_LAST_NAME;
    switch (0)
    {
    case 1: 
    default: 
      for (;;)
      {
        switch (1)
        {
        }
      }
    }
    int i = b04270427Ч042704270427ЧЧ;
    int j = bЧЧ0427042704270427ЧЧ;
    int k = b0427Ч0427042704270427ЧЧ;
    int m = b04270427Ч042704270427ЧЧ;
    switch (m * (bЧЧ0427042704270427ЧЧ + m) % bЧ042704270427ЧЧ0427Ч())
    {
    default: 
      b04270427Ч042704270427ЧЧ = bЧ04270427042704270427ЧЧ();
      b0427ЧЧ0427ЧЧ0427Ч = bЧ04270427042704270427ЧЧ();
    }
    switch (i * (j + i) % k)
    {
    default: 
      b04270427Ч042704270427ЧЧ = 51;
      b0427ЧЧ0427ЧЧ0427Ч = bЧ04270427042704270427ЧЧ();
    }
    ARG_USER_LAST_NAME = gguuuu.bккккк043Aкк043A043A(str, '3', '\001');
  }
  
  public MobileChatActivity() {}
  
  public static int b042704270427042704270427ЧЧ()
  {
    return 1;
  }
  
  public static int bЧ04270427042704270427ЧЧ()
  {
    return 40;
  }
  
  public static int bЧ042704270427ЧЧ0427Ч()
  {
    return 2;
  }
  
  public static int bЧЧЧ0427ЧЧ0427Ч()
  {
    return 0;
  }
  
  public static Intent getIntent(@NonNull Context paramContext, @NonNull String paramString1, @NonNull String paramString2)
  {
    paramContext = new Intent(paramContext, MobileChatActivity.class);
    int i = b04270427Ч042704270427ЧЧ;
    switch (i * (bЧЧ0427042704270427ЧЧ + i) % b0427Ч0427042704270427ЧЧ)
    {
    default: 
      b04270427Ч042704270427ЧЧ = 20;
      bЧЧ0427042704270427ЧЧ = bЧ04270427042704270427ЧЧ();
    }
    switch (0)
    {
    case 1: 
    default: 
      for (;;)
      {
        switch (0)
        {
        }
      }
    }
    i = b04270427Ч042704270427ЧЧ;
    switch (i * (bЧЧ0427042704270427ЧЧ + i) % b0427Ч0427042704270427ЧЧ)
    {
    default: 
      b04270427Ч042704270427ЧЧ = 61;
      bЧЧ0427042704270427ЧЧ = bЧ04270427042704270427ЧЧ();
    }
    paramContext.putExtra(gguuuu.bк043Aккк043Aкк043A043A("\030(\0343(%\026\".\024\026\036\036\036(\026\b\023\n", 'j', 'A', '\000'), paramString1);
    paramContext.putExtra(gguuuu.bккккк043Aкк043A043A("]oe~utgu\004qgz|\txlyr", '', '\004'), paramString2);
    return paramContext;
  }
  
  /* Error */
  public java.util.Map<String, Bundle> getDeepLinkMap(Context paramContext)
  {
    // Byte code:
    //   0: getstatic 38	com/mobile/ui/mobilechat/activity/MobileChatActivity:b04270427Ч042704270427ЧЧ	I
    //   3: istore_2
    //   4: getstatic 40	com/mobile/ui/mobilechat/activity/MobileChatActivity:bЧЧ0427042704270427ЧЧ	I
    //   7: istore_3
    //   8: getstatic 42	com/mobile/ui/mobilechat/activity/MobileChatActivity:b0427Ч0427042704270427ЧЧ	I
    //   11: istore 4
    //   13: iload_2
    //   14: iload_3
    //   15: iload_2
    //   16: iadd
    //   17: imul
    //   18: iload 4
    //   20: irem
    //   21: tableswitch	default:+19->40, 0:+71->92
    //   40: getstatic 38	com/mobile/ui/mobilechat/activity/MobileChatActivity:b04270427Ч042704270427ЧЧ	I
    //   43: istore_2
    //   44: iload_2
    //   45: invokestatic 84	com/mobile/ui/mobilechat/activity/MobileChatActivity:b042704270427042704270427ЧЧ	()I
    //   48: iload_2
    //   49: iadd
    //   50: imul
    //   51: getstatic 42	com/mobile/ui/mobilechat/activity/MobileChatActivity:b0427Ч0427042704270427ЧЧ	I
    //   54: irem
    //   55: tableswitch	default:+17->72, 0:+27->82
    //   72: bipush 12
    //   74: putstatic 38	com/mobile/ui/mobilechat/activity/MobileChatActivity:b04270427Ч042704270427ЧЧ	I
    //   77: bipush 22
    //   79: putstatic 40	com/mobile/ui/mobilechat/activity/MobileChatActivity:bЧЧ0427042704270427ЧЧ	I
    //   82: bipush 54
    //   84: putstatic 38	com/mobile/ui/mobilechat/activity/MobileChatActivity:b04270427Ч042704270427ЧЧ	I
    //   87: bipush 80
    //   89: putstatic 40	com/mobile/ui/mobilechat/activity/MobileChatActivity:bЧЧ0427042704270427ЧЧ	I
    //   92: iconst_0
    //   93: tableswitch	default:+23->116, 0:+50->143, 1:+-1->92
    //   116: iconst_1
    //   117: tableswitch	default:+23->140, 0:+-25->92, 1:+26->143
    //   140: goto -24 -> 116
    //   143: getstatic 88	com/mobile/ui/mobilechat/activity/MobileChatActivity:NOT_LINKABLE_MAP	Ljava/util/Map;
    //   146: astore_1
    //   147: aload_1
    //   148: areturn
    //   149: astore_1
    //   150: aload_1
    //   151: athrow
    //   152: astore_1
    //   153: aload_1
    //   154: athrow
    // Local variable table:
    //   start	length	slot	name	signature
    //   0	155	0	this	MobileChatActivity
    //   0	155	1	paramContext	Context
    //   3	48	2	i	int
    //   7	10	3	j	int
    //   11	10	4	k	int
    // Exception table:
    //   from	to	target	type
    //   0	13	149	java/lang/Exception
    //   143	147	149	java/lang/Exception
    //   82	92	152	java/lang/Exception
  }
  
  protected int getLayoutId()
  {
    throw new Runtime("d2j fail translate: java.lang.IndexOutOfBoundsException: fromIndex < 0: -1\n\tat java.util.BitSet.nextSetBit(BitSet.java:712)\n\tat com.googlecode.dex2jar.ir.ts.array.FillArrayTransformer.makeSureAllElementAreAssigned(FillArrayTransformer.java:505)\n\tat com.googlecode.dex2jar.ir.ts.array.FillArrayTransformer.transformReportChanged(FillArrayTransformer.java:123)\n\tat com.googlecode.dex2jar.ir.ts.StatedTransformer.transform(StatedTransformer.java:10)\n\tat com.googlecode.d2j.dex.Dex2jar$2.optimize(Dex2jar.java:149)\n\tat com.googlecode.d2j.dex.Dex2Asm.convertCode(Dex2Asm.java:414)\n\tat com.googlecode.d2j.dex.ExDex2Asm.convertCode(ExDex2Asm.java:42)\n\tat com.googlecode.d2j.dex.Dex2jar$2.convertCode(Dex2jar.java:128)\n\tat com.googlecode.d2j.dex.Dex2Asm.convertMethod(Dex2Asm.java:509)\n\tat com.googlecode.d2j.dex.Dex2Asm.convertClass(Dex2Asm.java:406)\n\tat com.googlecode.d2j.dex.Dex2Asm.convertDex(Dex2Asm.java:422)\n\tat com.googlecode.d2j.dex.Dex2jar.doTranslate(Dex2jar.java:172)\n\tat com.googlecode.d2j.dex.Dex2jar.to(Dex2jar.java:272)\n\tat com.googlecode.dex2jar.tools.Dex2jarCmd.doCommandLine(Dex2jarCmd.java:108)\n\tat com.googlecode.dex2jar.tools.BaseCmd.doMain(BaseCmd.java:288)\n\tat com.googlecode.dex2jar.tools.Dex2jarCmd.main(Dex2jarCmd.java:32)\n");
  }
  
  /* Error */
  protected com.mobile.ui.common.activity.BaseActivity.rrrggg getMenuType()
  {
    // Byte code:
    //   0: iconst_0
    //   1: istore_1
    //   2: iconst_4
    //   3: istore_2
    //   4: iload_2
    //   5: iconst_0
    //   6: idiv
    //   7: istore_3
    //   8: iload_1
    //   9: iconst_0
    //   10: idiv
    //   11: istore_2
    //   12: iload_2
    //   13: istore_1
    //   14: goto -6 -> 8
    //   17: astore 4
    //   19: bipush 40
    //   21: putstatic 38	com/mobile/ui/mobilechat/activity/MobileChatActivity:b04270427Ч042704270427ЧЧ	I
    //   24: new 104	java/lang/NullPointerException
    //   27: dup
    //   28: invokespecial 105	java/lang/NullPointerException:<init>	()V
    //   31: athrow
    //   32: astore 4
    //   34: invokestatic 49	com/mobile/ui/mobilechat/activity/MobileChatActivity:bЧ04270427042704270427ЧЧ	()I
    //   37: putstatic 38	com/mobile/ui/mobilechat/activity/MobileChatActivity:b04270427Ч042704270427ЧЧ	I
    //   40: iload_2
    //   41: iconst_0
    //   42: idiv
    //   43: istore_2
    //   44: goto -4 -> 40
    //   47: astore 4
    //   49: aload 4
    //   51: athrow
    //   52: astore 4
    //   54: bipush 80
    //   56: putstatic 38	com/mobile/ui/mobilechat/activity/MobileChatActivity:b04270427Ч042704270427ЧЧ	I
    //   59: getstatic 111	com/mobile/ui/common/activity/BaseActivity$rrrggg:MODAL_WINDOW	Lcom/mobile/ui/common/activity/BaseActivity$rrrggg;
    //   62: astore 4
    //   64: aload 4
    //   66: areturn
    //   67: astore 4
    //   69: bipush 20
    //   71: putstatic 38	com/mobile/ui/mobilechat/activity/MobileChatActivity:b04270427Ч042704270427ЧЧ	I
    //   74: iload_3
    //   75: istore_2
    //   76: goto -72 -> 4
    // Local variable table:
    //   start	length	slot	name	signature
    //   0	79	0	this	MobileChatActivity
    //   1	13	1	i	int
    //   3	73	2	j	int
    //   7	68	3	k	int
    //   17	1	4	localException1	Exception
    //   32	1	4	localException2	Exception
    //   47	3	4	localException3	Exception
    //   52	1	4	localException4	Exception
    //   62	3	4	localRrrggg	com.mobile.ui.common.activity.BaseActivity.rrrggg
    //   67	1	4	localException5	Exception
    // Exception table:
    //   from	to	target	type
    //   4	8	17	java/lang/Exception
    //   24	32	32	java/lang/Exception
    //   59	64	47	java/lang/Exception
    //   40	44	52	java/lang/Exception
    //   8	12	67	java/lang/Exception
  }
  
  public void initMobileChat()
  {
    dxdddx localDxdddx = new dxdddx(getString(R.string.mobile_chat_application_id), getPackageName(), new xdxxdx()
    {
      public static int b043204320432в04320432в043204320432 = 2;
      public static int b0432в0432в04320432в043204320432 = 0;
      public static int bв04320432в04320432в043204320432 = 1;
      public static int bввв043204320432в043204320432 = 19;
      
      public static int b0435е0435е0435е0435е0435е()
      {
        return 1;
      }
      
      public static int bее0435е0435е0435е0435е()
      {
        return 7;
      }
      
      /* Error */
      public void b04380438ииииииии()
      {
        // Byte code:
        //   0: new 37	com/liveperson/infra/LPAuthenticationParams
        //   3: dup
        //   4: invokespecial 38	com/liveperson/infra/LPAuthenticationParams:<init>	()V
        //   7: astore 6
        //   9: aload 6
        //   11: ldc 40
        //   13: invokevirtual 44	com/liveperson/infra/LPAuthenticationParams:setAuthKey	(Ljava/lang/String;)Lcom/liveperson/infra/LPAuthenticationParams;
        //   16: ldc 40
        //   18: invokevirtual 47	com/liveperson/infra/LPAuthenticationParams:addCertificatePinningKey	(Ljava/lang/String;)Lcom/liveperson/infra/LPAuthenticationParams;
        //   21: new 49	com/liveperson/infra/ConversationViewParams
        //   24: dup
        //   25: iconst_0
        //   26: invokespecial 52	com/liveperson/infra/ConversationViewParams:<init>	(Z)V
        //   29: invokestatic 58	kkkkkk/jaajaa:b0436жжжжж0436жжж	(Lcom/liveperson/infra/LPAuthenticationParams;Lcom/liveperson/infra/ConversationViewParams;)Landroid/support/v4/app/Fragment;
        //   32: checkcast 60	com/liveperson/infra/messaging_ui/fragment/ConversationFragment
        //   35: astore 6
        //   37: aload_0
        //   38: getfield 26	com/mobile/ui/mobilechat/activity/MobileChatActivity$1:bвв0432в04320432в043204320432	Lcom/mobile/ui/mobilechat/activity/MobileChatActivity;
        //   41: invokevirtual 64	com/mobile/ui/mobilechat/activity/MobileChatActivity:getSupportFragmentManager	()Landroid/support/v4/app/FragmentManager;
        //   44: invokevirtual 70	android/support/v4/app/FragmentManager:beginTransaction	()Landroid/support/v4/app/FragmentTransaction;
        //   47: getstatic 75	com/mobile/ui/R$id:chatContainer	I
        //   50: aload 6
        //   52: invokevirtual 81	android/support/v4/app/FragmentTransaction:replace	(ILandroid/support/v4/app/Fragment;)Landroid/support/v4/app/FragmentTransaction;
        //   55: invokevirtual 84	android/support/v4/app/FragmentTransaction:commit	()I
        //   58: pop
        //   59: aload_0
        //   60: getfield 26	com/mobile/ui/mobilechat/activity/MobileChatActivity$1:bвв0432в04320432в043204320432	Lcom/mobile/ui/mobilechat/activity/MobileChatActivity;
        //   63: invokevirtual 88	com/mobile/ui/mobilechat/activity/MobileChatActivity:getIntent	()Landroid/content/Intent;
        //   66: astore 6
        //   68: new 90	kkkkkk/ajaaja$aajaja
        //   71: dup
        //   72: invokespecial 91	kkkkkk/ajaaja$aajaja:<init>	()V
        //   75: astore 7
        //   77: getstatic 93	com/mobile/ui/mobilechat/activity/MobileChatActivity$1:bввв043204320432в043204320432	I
        //   80: istore_1
        //   81: iload_1
        //   82: invokestatic 95	com/mobile/ui/mobilechat/activity/MobileChatActivity$1:b0435е0435е0435е0435е0435е	()I
        //   85: iload_1
        //   86: iadd
        //   87: imul
        //   88: getstatic 97	com/mobile/ui/mobilechat/activity/MobileChatActivity$1:b043204320432в04320432в043204320432	I
        //   91: irem
        //   92: tableswitch	default:+20->112, 0:+31->123
        //   112: bipush 43
        //   114: putstatic 93	com/mobile/ui/mobilechat/activity/MobileChatActivity$1:bввв043204320432в043204320432	I
        //   117: invokestatic 99	com/mobile/ui/mobilechat/activity/MobileChatActivity$1:bее0435е0435е0435е0435е	()I
        //   120: putstatic 101	com/mobile/ui/mobilechat/activity/MobileChatActivity$1:b0432в0432в04320432в043204320432	I
        //   123: getstatic 93	com/mobile/ui/mobilechat/activity/MobileChatActivity$1:bввв043204320432в043204320432	I
        //   126: istore_1
        //   127: getstatic 103	com/mobile/ui/mobilechat/activity/MobileChatActivity$1:bв04320432в04320432в043204320432	I
        //   130: istore_2
        //   131: getstatic 93	com/mobile/ui/mobilechat/activity/MobileChatActivity$1:bввв043204320432в043204320432	I
        //   134: istore_3
        //   135: getstatic 97	com/mobile/ui/mobilechat/activity/MobileChatActivity$1:b043204320432в04320432в043204320432	I
        //   138: istore 4
        //   140: getstatic 101	com/mobile/ui/mobilechat/activity/MobileChatActivity$1:b0432в0432в04320432в043204320432	I
        //   143: istore 5
        //   145: iload_1
        //   146: iload_2
        //   147: iadd
        //   148: iload_3
        //   149: imul
        //   150: iload 4
        //   152: irem
        //   153: iload 5
        //   155: if_icmpeq +13 -> 168
        //   158: bipush 72
        //   160: putstatic 93	com/mobile/ui/mobilechat/activity/MobileChatActivity$1:bввв043204320432в043204320432	I
        //   163: bipush 70
        //   165: putstatic 101	com/mobile/ui/mobilechat/activity/MobileChatActivity$1:b0432в0432в04320432в043204320432	I
        //   168: aload 7
        //   170: aload 6
        //   172: ldc 105
        //   174: bipush 54
        //   176: iconst_0
        //   177: invokestatic 111	kkkkkk/gguuuu:bккккк043Aкк043A043A	(Ljava/lang/String;CC)Ljava/lang/String;
        //   180: invokevirtual 117	android/content/Intent:getStringExtra	(Ljava/lang/String;)Ljava/lang/String;
        //   183: invokevirtual 121	kkkkkk/ajaaja$aajaja:b0436жжж043604360436жжж	(Ljava/lang/String;)Lkkkkkk/ajaaja$aajaja;
        //   186: astore 7
        //   188: aload 6
        //   190: ldc 123
        //   192: sipush 233
        //   195: iconst_0
        //   196: invokestatic 111	kkkkkk/gguuuu:bккккк043Aкк043A043A	(Ljava/lang/String;CC)Ljava/lang/String;
        //   199: invokevirtual 117	android/content/Intent:getStringExtra	(Ljava/lang/String;)Ljava/lang/String;
        //   202: astore 6
        //   204: aload 7
        //   206: aload 6
        //   208: invokevirtual 126	kkkkkk/ajaaja$aajaja:bж0436жж043604360436жжж	(Ljava/lang/String;)Lkkkkkk/ajaaja$aajaja;
        //   211: invokevirtual 130	kkkkkk/ajaaja$aajaja:bж043604360436ж04360436жжж	()Lkkkkkk/ajaaja;
        //   214: invokestatic 134	kkkkkk/jaajaa:bж0436ж04360436ж0436жжж	(Lkkkkkk/ajaaja;)V
        //   217: aload_0
        //   218: getfield 26	com/mobile/ui/mobilechat/activity/MobileChatActivity$1:bвв0432в04320432в043204320432	Lcom/mobile/ui/mobilechat/activity/MobileChatActivity;
        //   221: invokestatic 138	kkkkkk/jaajaa:b0436ж0436ж0436ж0436жжж	(Lkkkkkk/wnwnwn;)V
        //   224: return
        //   225: astore 6
        //   227: aload 6
        //   229: athrow
        //   230: astore 6
        //   232: aload 6
        //   234: athrow
        //   235: astore 6
        //   237: aload 6
        //   239: athrow
        //   240: astore 6
        //   242: aload 6
        //   244: athrow
        // Local variable table:
        //   start	length	slot	name	signature
        //   0	245	0	this	1
        //   80	68	1	i	int
        //   130	18	2	j	int
        //   134	16	3	k	int
        //   138	15	4	m	int
        //   143	13	5	n	int
        //   7	200	6	localObject	Object
        //   225	3	6	localException1	Exception
        //   230	3	6	localException2	Exception
        //   235	3	6	localException3	Exception
        //   240	3	6	localException4	Exception
        //   75	130	7	localAajaja	kkkkkk.ajaaja.aajaja
        // Exception table:
        //   from	to	target	type
        //   0	9	225	java/lang/Exception
        //   37	77	225	java/lang/Exception
        //   168	204	225	java/lang/Exception
        //   158	168	230	java/lang/Exception
        //   227	230	230	java/lang/Exception
        //   237	240	230	java/lang/Exception
        //   9	37	235	java/lang/Exception
        //   204	224	235	java/lang/Exception
        //   123	145	240	java/lang/Exception
      }
      
      /* Error */
      public void bи0438ииииииии(Exception paramAnonymousException)
      {
        // Byte code:
        //   0: aload_0
        //   1: getfield 26	com/mobile/ui/mobilechat/activity/MobileChatActivity$1:bвв0432в04320432в043204320432	Lcom/mobile/ui/mobilechat/activity/MobileChatActivity;
        //   4: astore_3
        //   5: getstatic 93	com/mobile/ui/mobilechat/activity/MobileChatActivity$1:bввв043204320432в043204320432	I
        //   8: istore_2
        //   9: iload_2
        //   10: getstatic 103	com/mobile/ui/mobilechat/activity/MobileChatActivity$1:bв04320432в04320432в043204320432	I
        //   13: iload_2
        //   14: iadd
        //   15: imul
        //   16: getstatic 97	com/mobile/ui/mobilechat/activity/MobileChatActivity$1:b043204320432в04320432в043204320432	I
        //   19: irem
        //   20: tableswitch	default:+20->40, 0:+31->51
        //   40: bipush 73
        //   42: putstatic 93	com/mobile/ui/mobilechat/activity/MobileChatActivity$1:bввв043204320432в043204320432	I
        //   45: invokestatic 99	com/mobile/ui/mobilechat/activity/MobileChatActivity$1:bее0435е0435е0435е0435е	()I
        //   48: putstatic 101	com/mobile/ui/mobilechat/activity/MobileChatActivity$1:b0432в0432в04320432в043204320432	I
        //   51: aload_0
        //   52: getfield 26	com/mobile/ui/mobilechat/activity/MobileChatActivity$1:bвв0432в04320432в043204320432	Lcom/mobile/ui/mobilechat/activity/MobileChatActivity;
        //   55: invokevirtual 144	com/mobile/ui/mobilechat/activity/MobileChatActivity:getBaseContext	()Landroid/content/Context;
        //   58: astore 4
        //   60: invokestatic 99	com/mobile/ui/mobilechat/activity/MobileChatActivity$1:bее0435е0435е0435е0435е	()I
        //   63: getstatic 103	com/mobile/ui/mobilechat/activity/MobileChatActivity$1:bв04320432в04320432в043204320432	I
        //   66: iadd
        //   67: invokestatic 99	com/mobile/ui/mobilechat/activity/MobileChatActivity$1:bее0435е0435е0435е0435е	()I
        //   70: imul
        //   71: getstatic 97	com/mobile/ui/mobilechat/activity/MobileChatActivity$1:b043204320432в04320432в043204320432	I
        //   74: irem
        //   75: getstatic 101	com/mobile/ui/mobilechat/activity/MobileChatActivity$1:b0432в0432в04320432в043204320432	I
        //   78: if_icmpeq +8 -> 86
        //   81: bipush 63
        //   83: putstatic 101	com/mobile/ui/mobilechat/activity/MobileChatActivity$1:b0432в0432в04320432в043204320432	I
        //   86: getstatic 150	com/mobile/ui/error/ErrorActivity$uueeee:LOGGED_OUT	Lcom/mobile/ui/error/ErrorActivity$uueeee;
        //   89: astore 5
        //   91: aload_3
        //   92: aload 4
        //   94: aload 5
        //   96: aload_1
        //   97: invokevirtual 154	java/lang/Exception:getLocalizedMessage	()Ljava/lang/String;
        //   100: invokestatic 160	com/mobile/ui/error/ErrorActivity:getErrorIntent	(Landroid/content/Context;Lcom/mobile/ui/error/ErrorActivity$uueeee;Ljava/lang/String;)Landroid/content/Intent;
        //   103: invokevirtual 164	com/mobile/ui/mobilechat/activity/MobileChatActivity:startActivity	(Landroid/content/Intent;)V
        //   106: return
        //   107: astore_1
        //   108: aload_1
        //   109: athrow
        //   110: astore_1
        //   111: aload_1
        //   112: athrow
        // Local variable table:
        //   start	length	slot	name	signature
        //   0	113	0	this	1
        //   0	113	1	paramAnonymousException	Exception
        //   8	8	2	i	int
        //   4	88	3	localMobileChatActivity	MobileChatActivity
        //   58	35	4	localContext	Context
        //   89	6	5	localUueeee	com.mobile.ui.error.ErrorActivity.uueeee
        // Exception table:
        //   from	to	target	type
        //   0	5	107	java/lang/Exception
        //   51	60	107	java/lang/Exception
        //   86	91	107	java/lang/Exception
        //   91	106	110	java/lang/Exception
      }
    });
    switch (0)
    {
    case 1: 
    default: 
      for (;;)
      {
        switch (1)
        {
        }
      }
    }
    if ((bЧ04270427042704270427ЧЧ() + bЧЧ0427042704270427ЧЧ) * bЧ04270427042704270427ЧЧ() % b0427Ч0427042704270427ЧЧ != bЧЧЧ0427ЧЧ0427Ч())
    {
      int i = bЧ04270427042704270427ЧЧ();
      switch (i * (bЧЧ0427042704270427ЧЧ + i) % b0427Ч0427042704270427ЧЧ)
      {
      default: 
        b04270427Ч042704270427ЧЧ = bЧ04270427042704270427ЧЧ();
        bЧЧ0427042704270427ЧЧ = bЧ04270427042704270427ЧЧ();
      }
      b04270427Ч042704270427ЧЧ = 55;
      bЧЧ0427042704270427ЧЧ = bЧ04270427042704270427ЧЧ();
    }
    jaajaa.b0436жж0436жж0436жжж(this, localDxdddx);
  }
  
  public void onAgentAvatarTapped(AgentData paramAgentData)
  {
    switch (1)
    {
    case 0: 
    default: 
      for (;;)
      {
        switch (1)
        {
        }
      }
    }
    switch (1)
    {
    case 0: 
    default: 
      for (;;)
      {
        if ((b04270427Ч042704270427ЧЧ + bЧЧ0427042704270427ЧЧ) * b04270427Ч042704270427ЧЧ % b0427Ч0427042704270427ЧЧ != b0427ЧЧ0427ЧЧ0427Ч)
        {
          b04270427Ч042704270427ЧЧ = bЧ04270427042704270427ЧЧ();
          b0427ЧЧ0427ЧЧ0427Ч = 24;
        }
        switch (0)
        {
        }
      }
    }
  }
  
  public void onAgentDetailsChanged(AgentData paramAgentData)
  {
    switch (0)
    {
    case 1: 
    default: 
      for (;;)
      {
        if ((b04270427Ч042704270427ЧЧ + bЧЧ0427042704270427ЧЧ) * b04270427Ч042704270427ЧЧ % b0427Ч0427042704270427ЧЧ != bЧЧЧ0427ЧЧ0427Ч())
        {
          b04270427Ч042704270427ЧЧ = bЧ04270427042704270427ЧЧ();
          b0427ЧЧ0427ЧЧ0427Ч = bЧ04270427042704270427ЧЧ();
        }
        switch (0)
        {
        }
      }
    }
  }
  
  public void onAgentTyping(boolean paramBoolean) {}
  
  public void onConnectionChanged(boolean paramBoolean) {}
  
  public void onConversationMarkedAsNormal()
  {
    switch (0)
    {
    case 1: 
    default: 
      for (;;)
      {
        switch (0)
        {
        }
      }
    }
  }
  
  public void onConversationMarkedAsUrgent() {}
  
  public void onConversationResolved()
  {
    switch (0)
    {
    case 1: 
    default: 
      for (;;)
      {
        switch (1)
        {
        }
      }
    }
  }
  
  public void onConversationResolved(LPConversationData paramLPConversationData)
  {
    int i = b04270427Ч042704270427ЧЧ;
    switch (i * (b042704270427042704270427ЧЧ() + i) % b0427Ч0427042704270427ЧЧ)
    {
    default: 
      b04270427Ч042704270427ЧЧ = bЧ04270427042704270427ЧЧ();
      b0427ЧЧ0427ЧЧ0427Ч = bЧ04270427042704270427ЧЧ();
    }
  }
  
  public void onConversationResolved(xddxdd paramXddxdd)
  {
    switch (1)
    {
    case 0: 
    default: 
      for (;;)
      {
        int i = b04270427Ч042704270427ЧЧ;
        switch (i * (bЧЧ0427042704270427ЧЧ + i) % bЧ042704270427ЧЧ0427Ч())
        {
        default: 
          b04270427Ч042704270427ЧЧ = 25;
          b0427ЧЧ0427ЧЧ0427Ч = bЧ04270427042704270427ЧЧ();
        }
        switch (0)
        {
        }
      }
    }
  }
  
  public void onConversationStarted()
  {
    switch (0)
    {
    case 1: 
    default: 
      for (;;)
      {
        switch (1)
        {
        }
      }
    }
    switch (1)
    {
    case 0: 
    default: 
      for (;;)
      {
        if ((b04270427Ч042704270427ЧЧ + bЧЧ0427042704270427ЧЧ) * b04270427Ч042704270427ЧЧ % b0427Ч0427042704270427ЧЧ != b0427ЧЧ0427ЧЧ0427Ч)
        {
          b04270427Ч042704270427ЧЧ = bЧ04270427042704270427ЧЧ();
          b0427ЧЧ0427ЧЧ0427Ч = 53;
        }
        switch (1)
        {
        }
      }
    }
  }
  
  public void onConversationStarted(LPConversationData paramLPConversationData)
  {
    if ((b04270427Ч042704270427ЧЧ + bЧЧ0427042704270427ЧЧ) * b04270427Ч042704270427ЧЧ % b0427Ч0427042704270427ЧЧ != b0427ЧЧ0427ЧЧ0427Ч)
    {
      b04270427Ч042704270427ЧЧ = 59;
      b0427ЧЧ0427ЧЧ0427Ч = bЧ04270427042704270427ЧЧ();
    }
    switch (0)
    {
    case 1: 
    default: 
      for (;;)
      {
        switch (1)
        {
        }
      }
    }
  }
  
  public void onCreate(Bundle paramBundle)
  {
    for (;;)
    {
      try
      {
        nkkkkk.bЗЗ0417З0417З0417041704170417(getApplicationContext());
        nnnkkk.bхх0445ххххххх(getApplicationContext());
        nknnkk.bх0445ххх04450445ххх(getApplicationContext());
        super.onCreate(paramBundle);
        if (Build.VERSION.SDK_INT >= 21) {
          getWindow().setStatusBarColor(getResources().getColor(R.color.toolbar_modal_menu_color));
        }
      }
      catch (Exception paramBundle)
      {
        Window localWindow;
        int i;
        throw paramBundle;
      }
      try
      {
        getWindow().setNavigationBarColor(getResources().getColor(R.color.mobile_chat_navigation_menu_color));
        if (paramBundle == null) {
          initMobileChat();
        }
        return;
      }
      catch (Exception paramBundle)
      {
        throw paramBundle;
      }
      localWindow = getWindow();
      localWindow.addFlags(67108864);
      i = b04270427Ч042704270427ЧЧ;
      switch (i * (bЧЧ0427042704270427ЧЧ + i) % b0427Ч0427042704270427ЧЧ)
      {
      }
      b04270427Ч042704270427ЧЧ = 65;
      b0427ЧЧ0427ЧЧ0427Ч = bЧ04270427042704270427ЧЧ();
      if ((b04270427Ч042704270427ЧЧ + bЧЧ0427042704270427ЧЧ) * b04270427Ч042704270427ЧЧ % b0427Ч0427042704270427ЧЧ != b0427ЧЧ0427ЧЧ0427Ч)
      {
        b04270427Ч042704270427ЧЧ = bЧ04270427042704270427ЧЧ();
        b0427ЧЧ0427ЧЧ0427Ч = bЧ04270427042704270427ЧЧ();
      }
    }
  }
  
  public void onCsatDismissed()
  {
    switch (0)
    {
    case 1: 
    default: 
      for (;;)
      {
        switch (0)
        {
        }
      }
    }
  }
  
  public void onCsatLaunched()
  {
    switch (0)
    {
    case 1: 
    default: 
      for (;;)
      {
        if ((b04270427Ч042704270427ЧЧ + bЧЧ0427042704270427ЧЧ) * b04270427Ч042704270427ЧЧ % b0427Ч0427042704270427ЧЧ != b0427ЧЧ0427ЧЧ0427Ч)
        {
          b04270427Ч042704270427ЧЧ = 27;
          b0427ЧЧ0427ЧЧ0427Ч = bЧ04270427042704270427ЧЧ();
        }
        switch (0)
        {
        }
      }
    }
  }
  
  public void onCsatSkipped()
  {
    switch (0)
    {
    case 1: 
    default: 
      for (;;)
      {
        if ((b04270427Ч042704270427ЧЧ + bЧЧ0427042704270427ЧЧ) * b04270427Ч042704270427ЧЧ % b0427Ч0427042704270427ЧЧ != b0427ЧЧ0427ЧЧ0427Ч)
        {
          b04270427Ч042704270427ЧЧ = 30;
          b0427ЧЧ0427ЧЧ0427Ч = 77;
        }
        switch (1)
        {
        }
      }
    }
  }
  
  public void onCsatSubmitted(String paramString)
  {
    switch (0)
    {
    case 1: 
    default: 
      for (;;)
      {
        switch (0)
        {
        }
      }
    }
    int i = bЧ04270427042704270427ЧЧ();
    switch (i * (bЧЧ0427042704270427ЧЧ + i) % bЧ042704270427ЧЧ0427Ч())
    {
    default: 
      b04270427Ч042704270427ЧЧ = 7;
      b0427ЧЧ0427ЧЧ0427Ч = bЧ04270427042704270427ЧЧ();
    }
  }
  
  public void onError(ykkyky paramYkkyky, String paramString) {}
  
  public void onOfflineHoursChanges(boolean paramBoolean)
  {
    switch (1)
    {
    case 0: 
    default: 
      for (;;)
      {
        if ((b04270427Ч042704270427ЧЧ + bЧЧ0427042704270427ЧЧ) * b04270427Ч042704270427ЧЧ % b0427Ч0427042704270427ЧЧ != b0427ЧЧ0427ЧЧ0427Ч)
        {
          b04270427Ч042704270427ЧЧ = bЧ04270427042704270427ЧЧ();
          b0427ЧЧ0427ЧЧ0427Ч = 74;
        }
        switch (1)
        {
        }
      }
    }
  }
  
  /* Error */
  public void onStructuredContentLinkClicked(String paramString)
  {
    // Byte code:
    //   0: invokestatic 233	kkkkkk/nuuuun:b043F043Fп043F043Fп043F043F043Fп	()Lkkkkkk/nuuuun;
    //   3: astore_2
    //   4: aload_2
    //   5: aload_0
    //   6: aload_1
    //   7: invokevirtual 237	kkkkkk/nuuuun:b043F043F043F043F043Fп043F043F043Fп	(Landroid/content/Context;Ljava/lang/String;)V
    //   10: getstatic 38	com/mobile/ui/mobilechat/activity/MobileChatActivity:b04270427Ч042704270427ЧЧ	I
    //   13: getstatic 40	com/mobile/ui/mobilechat/activity/MobileChatActivity:bЧЧ0427042704270427ЧЧ	I
    //   16: iadd
    //   17: getstatic 38	com/mobile/ui/mobilechat/activity/MobileChatActivity:b04270427Ч042704270427ЧЧ	I
    //   20: imul
    //   21: getstatic 42	com/mobile/ui/mobilechat/activity/MobileChatActivity:b0427Ч0427042704270427ЧЧ	I
    //   24: irem
    //   25: getstatic 51	com/mobile/ui/mobilechat/activity/MobileChatActivity:b0427ЧЧ0427ЧЧ0427Ч	I
    //   28: if_icmpeq +13 -> 41
    //   31: bipush 92
    //   33: putstatic 38	com/mobile/ui/mobilechat/activity/MobileChatActivity:b04270427Ч042704270427ЧЧ	I
    //   36: bipush 44
    //   38: putstatic 51	com/mobile/ui/mobilechat/activity/MobileChatActivity:b0427ЧЧ0427ЧЧ0427Ч	I
    //   41: return
    //   42: astore_1
    //   43: aload_1
    //   44: athrow
    //   45: astore_1
    //   46: aload_1
    //   47: athrow
    // Local variable table:
    //   start	length	slot	name	signature
    //   0	48	0	this	MobileChatActivity
    //   0	48	1	paramString	String
    //   3	2	2	localNuuuun	kkkkkk.nuuuun
    // Exception table:
    //   from	to	target	type
    //   0	4	42	java/lang/Exception
    //   4	10	45	java/lang/Exception
  }
  
  public void onTokenExpired()
  {
    if ((b04270427Ч042704270427ЧЧ + bЧЧ0427042704270427ЧЧ) * b04270427Ч042704270427ЧЧ % bЧ042704270427ЧЧ0427Ч() != b0427ЧЧ0427ЧЧ0427Ч)
    {
      b04270427Ч042704270427ЧЧ = 38;
      b0427ЧЧ0427ЧЧ0427Ч = 18;
    }
    switch (0)
    {
    case 1: 
    default: 
      for (;;)
      {
        switch (0)
        {
        }
      }
    }
  }
  
  public void onUserActionOnPreventedPermission(xxxxdd paramXxxxdd)
  {
    switch (1)
    {
    case 0: 
    default: 
      for (;;)
      {
        if ((b04270427Ч042704270427ЧЧ + b042704270427042704270427ЧЧ()) * b04270427Ч042704270427ЧЧ % b0427Ч0427042704270427ЧЧ != b0427ЧЧ0427ЧЧ0427Ч)
        {
          b04270427Ч042704270427ЧЧ = 38;
          b0427ЧЧ0427ЧЧ0427Ч = bЧ04270427042704270427ЧЧ();
        }
        switch (1)
        {
        }
      }
    }
    switch (0)
    {
    case 1: 
    default: 
      for (;;)
      {
        switch (1)
        {
        }
      }
    }
  }
  
  public void onUserDeniedPermission(xxxxdd paramXxxxdd, boolean paramBoolean)
  {
    try
    {
      throw new NullPointerException();
    }
    catch (Exception paramXxxxdd)
    {
      b04270427Ч042704270427ЧЧ = 44;
      switch (1)
      {
      case 0: 
      default: 
        for (;;)
        {
          switch (0)
          {
          case 1: 
          default: 
            for (;;)
            {
              switch (1)
              {
              }
            }
          }
          switch (1)
          {
          }
        }
      }
    }
  }
  
  protected boolean shouldRestartAppIfSecureCoreNotInitialized()
  {
    int i = b04270427Ч042704270427ЧЧ;
    switch (i * (bЧЧ0427042704270427ЧЧ + i) % b0427Ч0427042704270427ЧЧ)
    {
    default: 
      b04270427Ч042704270427ЧЧ = bЧ04270427042704270427ЧЧ();
      b0427ЧЧ0427ЧЧ0427Ч = bЧ04270427042704270427ЧЧ();
    }
    if ((bЧ04270427042704270427ЧЧ() + bЧЧ0427042704270427ЧЧ) * bЧ04270427042704270427ЧЧ() % b0427Ч0427042704270427ЧЧ != b0427ЧЧ0427ЧЧ0427Ч)
    {
      switch (1)
      {
      case 0: 
      default: 
        for (;;)
        {
          switch (1)
          {
          }
        }
      }
      b04270427Ч042704270427ЧЧ = 69;
      b0427ЧЧ0427ЧЧ0427Ч = bЧ04270427042704270427ЧЧ();
    }
    switch (0)
    {
    case 1: 
    default: 
      for (;;)
      {
        switch (0)
        {
        }
      }
    }
    return true;
  }
}
