package com.mobile.ui.fingerprint.fragment;

import android.os.Bundle;
import android.support.annotation.Nullable;
import android.support.v4.app.FragmentActivity;
import android.support.v4.app.FragmentManager;
import com.mobile.ui.App;
import com.mobile.ui.R.string;
import com.mobile.ui.common.fragment.BaseRequestFragment;
import com.mobile.ui.home.activity.HomeActivity;
import kkkkkk.euuuee;
import kkkkkk.gggggr;
import kkkkkk.uyuyyu;
import kkkkkk.uyyyyy;
import kkkkkk.yyyyyu;

public class ShouldShowFingerprintsChangedDialogFragment
  extends BaseRequestFragment<uyuyyu, yyyyyu>
  implements uyuyyu, euuuee
{
  public static int b042904290429ЩЩ0429ЩЩ = 69;
  public static int b0429ЩЩ0429Щ0429ЩЩ = 1;
  public static int bЩ0429Щ0429Щ0429ЩЩ = 2;
  public static int bЩЩЩ0429Щ0429ЩЩ;
  
  public ShouldShowFingerprintsChangedDialogFragment() {}
  
  public static int b04290429Щ0429Щ0429ЩЩ()
  {
    return 79;
  }
  
  public static int b0429Щ04290429Щ0429ЩЩ()
  {
    return 1;
  }
  
  public static int bЩЩ04290429Щ0429ЩЩ()
  {
    return 2;
  }
  
  public static int bЩЩЩЩ04290429ЩЩ()
  {
    return 0;
  }
  
  public static ShouldShowFingerprintsChangedDialogFragment newInstance()
  {
    int i = b042904290429ЩЩ0429ЩЩ;
    int j = b0429ЩЩ0429Щ0429ЩЩ;
    int k = b042904290429ЩЩ0429ЩЩ;
    switch (1)
    {
    case 0: 
    default: 
      for (;;)
      {
        switch (1)
        {
        }
      }
    }
    if ((i + j) * k % bЩ0429Щ0429Щ0429ЩЩ != bЩЩЩ0429Щ0429ЩЩ)
    {
      if ((b042904290429ЩЩ0429ЩЩ + b0429ЩЩ0429Щ0429ЩЩ) * b042904290429ЩЩ0429ЩЩ % bЩ0429Щ0429Щ0429ЩЩ != bЩЩЩ0429Щ0429ЩЩ)
      {
        b042904290429ЩЩ0429ЩЩ = 75;
        bЩЩЩ0429Щ0429ЩЩ = 96;
      }
      b042904290429ЩЩ0429ЩЩ = b04290429Щ0429Щ0429ЩЩ();
      bЩЩЩ0429Щ0429ЩЩ = b04290429Щ0429Щ0429ЩЩ();
    }
    try
    {
      ShouldShowFingerprintsChangedDialogFragment localShouldShowFingerprintsChangedDialogFragment = new ShouldShowFingerprintsChangedDialogFragment();
      return localShouldShowFingerprintsChangedDialogFragment;
    }
    catch (Exception localException)
    {
      throw localException;
    }
  }
  
  public void onCreate(@Nullable Bundle paramBundle)
  {
    super.onCreate(paramBundle);
    paramBundle = App.get().getAppComponent();
    if ((b042904290429ЩЩ0429ЩЩ + b0429ЩЩ0429Щ0429ЩЩ) * b042904290429ЩЩ0429ЩЩ % bЩ0429Щ0429Щ0429ЩЩ != bЩЩЩ0429Щ0429ЩЩ)
    {
      b042904290429ЩЩ0429ЩЩ = b04290429Щ0429Щ0429ЩЩ();
      bЩЩЩ0429Щ0429ЩЩ = 13;
    }
    paramBundle.bИ041804180418ИИ041804180418И(this);
    paramBundle = this.mPresenter;
    switch (1)
    {
    case 0: 
    default: 
      for (;;)
      {
        if ((b042904290429ЩЩ0429ЩЩ + b0429ЩЩ0429Щ0429ЩЩ) * b042904290429ЩЩ0429ЩЩ % bЩ0429Щ0429Щ0429ЩЩ != bЩЩЩ0429Щ0429ЩЩ)
        {
          b042904290429ЩЩ0429ЩЩ = 25;
          bЩЩЩ0429Щ0429ЩЩ = b04290429Щ0429Щ0429ЩЩ();
        }
        switch (1)
        {
        }
      }
    }
    ((yyyyyu)paramBundle).b0418И0418ИИИ0418ИИИ(this);
    if (((yyyyyu)this.mPresenter).bъ044Aъъ044A044A044A044Aъ044A())
    {
      showRiskDialog();
      ((yyyyyu)this.mPresenter).b044Aъъъ044A044A044A044Aъ044A();
    }
  }
  
  public void onDismissNoFingerprintsDialog()
  {
    if ((b042904290429ЩЩ0429ЩЩ + b0429ЩЩ0429Щ0429ЩЩ) * b042904290429ЩЩ0429ЩЩ % bЩ0429Щ0429Щ0429ЩЩ != bЩЩЩ0429Щ0429ЩЩ)
    {
      b042904290429ЩЩ0429ЩЩ = 73;
      bЩЩЩ0429Щ0429ЩЩ = 40;
    }
    switch (1)
    {
    case 0: 
    default: 
      for (;;)
      {
        switch (0)
        {
        }
      }
    }
  }
  
  public void optInFromRiskDialog()
  {
    try
    {
      gggggr localGggggr = this.mPresenter;
      int i = b042904290429ЩЩ0429ЩЩ;
      int j = b0429ЩЩ0429Щ0429ЩЩ;
      int k = b042904290429ЩЩ0429ЩЩ;
      int m = bЩ0429Щ0429Щ0429ЩЩ;
      int n = bЩЩЩ0429Щ0429ЩЩ;
      if ((b04290429Щ0429Щ0429ЩЩ() + b0429ЩЩ0429Щ0429ЩЩ) * b04290429Щ0429Щ0429ЩЩ() % bЩ0429Щ0429Щ0429ЩЩ != bЩЩЩ0429Щ0429ЩЩ)
      {
        b042904290429ЩЩ0429ЩЩ = 32;
        bЩЩЩ0429Щ0429ЩЩ = 92;
      }
      if ((i + j) * k % m != n)
      {
        switch (1)
        {
        case 0: 
        default: 
          for (;;)
          {
            switch (0)
            {
            }
          }
        }
        b042904290429ЩЩ0429ЩЩ = 3;
        bЩЩЩ0429Щ0429ЩЩ = b04290429Щ0429Щ0429ЩЩ();
      }
      ((yyyyyu)localGggggr).bъъ044A044Aъ044A044A044Aъ044A();
      return;
    }
    catch (Exception localException)
    {
      throw localException;
    }
  }
  
  public void optOutFromRiskDialog()
  {
    int i = b042904290429ЩЩ0429ЩЩ;
    switch (i * (b0429ЩЩ0429Щ0429ЩЩ + i) % bЩЩ04290429Щ0429ЩЩ())
    {
    default: 
      b042904290429ЩЩ0429ЩЩ = 28;
      bЩЩЩ0429Щ0429ЩЩ = b04290429Щ0429Щ0429ЩЩ();
    }
    gggggr localGggggr = this.mPresenter;
    switch (0)
    {
    case 1: 
    default: 
      for (;;)
      {
        switch (1)
        {
        }
      }
    }
    i = b042904290429ЩЩ0429ЩЩ;
    switch (i * (b0429ЩЩ0429Щ0429ЩЩ + i) % bЩ0429Щ0429Щ0429ЩЩ)
    {
    default: 
      b042904290429ЩЩ0429ЩЩ = b04290429Щ0429Щ0429ЩЩ();
      bЩЩЩ0429Щ0429ЩЩ = b04290429Щ0429Щ0429ЩЩ();
    }
    switch (0)
    {
    case 1: 
    default: 
      for (;;)
      {
        switch (0)
        {
        }
      }
    }
    ((yyyyyu)localGggggr).b044Aъ044A044Aъ044A044A044Aъ044A();
  }
  
  public void optedInFromDialog()
  {
    yyyyyu localYyyyyu = (yyyyyu)this.mPresenter;
    int i = b042904290429ЩЩ0429ЩЩ;
    int j = b0429Щ04290429Щ0429ЩЩ();
    int k = b042904290429ЩЩ0429ЩЩ;
    switch (k * (b0429ЩЩ0429Щ0429ЩЩ + k) % bЩ0429Щ0429Щ0429ЩЩ)
    {
    default: 
      b042904290429ЩЩ0429ЩЩ = 84;
      bЩЩЩ0429Щ0429ЩЩ = 57;
    }
    if ((i + j) * b042904290429ЩЩ0429ЩЩ % bЩ0429Щ0429Щ0429ЩЩ != bЩЩЩ0429Щ0429ЩЩ)
    {
      b042904290429ЩЩ0429ЩЩ = 61;
      bЩЩЩ0429Щ0429ЩЩ = 78;
    }
    localYyyyyu.b044A044A044A044Aъ044A044A044Aъ044A();
  }
  
  /* Error */
  public void optedOutFromDialog()
  {
    // Byte code:
    //   0: iconst_3
    //   1: istore_1
    //   2: getstatic 33	com/mobile/ui/fingerprint/fragment/ShouldShowFingerprintsChangedDialogFragment:b042904290429ЩЩ0429ЩЩ	I
    //   5: invokestatic 98	com/mobile/ui/fingerprint/fragment/ShouldShowFingerprintsChangedDialogFragment:b0429Щ04290429Щ0429ЩЩ	()I
    //   8: iadd
    //   9: getstatic 33	com/mobile/ui/fingerprint/fragment/ShouldShowFingerprintsChangedDialogFragment:b042904290429ЩЩ0429ЩЩ	I
    //   12: imul
    //   13: getstatic 37	com/mobile/ui/fingerprint/fragment/ShouldShowFingerprintsChangedDialogFragment:bЩ0429Щ0429Щ0429ЩЩ	I
    //   16: irem
    //   17: getstatic 39	com/mobile/ui/fingerprint/fragment/ShouldShowFingerprintsChangedDialogFragment:bЩЩЩ0429Щ0429ЩЩ	I
    //   20: if_icmpeq +14 -> 34
    //   23: bipush 71
    //   25: putstatic 33	com/mobile/ui/fingerprint/fragment/ShouldShowFingerprintsChangedDialogFragment:b042904290429ЩЩ0429ЩЩ	I
    //   28: invokestatic 41	com/mobile/ui/fingerprint/fragment/ShouldShowFingerprintsChangedDialogFragment:b04290429Щ0429Щ0429ЩЩ	()I
    //   31: putstatic 39	com/mobile/ui/fingerprint/fragment/ShouldShowFingerprintsChangedDialogFragment:bЩЩЩ0429Щ0429ЩЩ	I
    //   34: iload_1
    //   35: iconst_0
    //   36: idiv
    //   37: istore_1
    //   38: goto -36 -> 2
    //   41: astore_2
    //   42: bipush 53
    //   44: putstatic 33	com/mobile/ui/fingerprint/fragment/ShouldShowFingerprintsChangedDialogFragment:b042904290429ЩЩ0429ЩЩ	I
    //   47: aload_0
    //   48: getfield 67	com/mobile/ui/fingerprint/fragment/ShouldShowFingerprintsChangedDialogFragment:mPresenter	Lkkkkkk/gggggr;
    //   51: checkcast 69	kkkkkk/yyyyyu
    //   54: astore_2
    //   55: aload_2
    //   56: invokevirtual 105	kkkkkk/yyyyyu:bъъъъ044A044A044A044Aъ044A	()V
    //   59: return
    //   60: astore_2
    //   61: aload_2
    //   62: athrow
    //   63: astore_2
    //   64: iconst_1
    //   65: tableswitch	default:+23->88, 0:+-1->64, 1:+50->115
    //   88: iconst_0
    //   89: tableswitch	default:+23->112, 0:+26->115, 1:+-25->64
    //   112: goto -24 -> 88
    //   115: aload_2
    //   116: athrow
    // Local variable table:
    //   start	length	slot	name	signature
    //   0	117	0	this	ShouldShowFingerprintsChangedDialogFragment
    //   1	37	1	i	int
    //   41	1	2	localException1	Exception
    //   54	2	2	localYyyyyu	yyyyyu
    //   60	2	2	localException2	Exception
    //   63	53	2	localException3	Exception
    // Exception table:
    //   from	to	target	type
    //   34	38	41	java/lang/Exception
    //   47	55	60	java/lang/Exception
    //   55	59	63	java/lang/Exception
  }
  
  /* Error */
  public void showNoFingerprintsDialog()
  {
    // Byte code:
    //   0: new 108	com/mobile/ui/fingerprint/fragment/NoFingerprintsDialogFragment
    //   3: dup
    //   4: invokespecial 109	com/mobile/ui/fingerprint/fragment/NoFingerprintsDialogFragment:<init>	()V
    //   7: astore_1
    //   8: aload_1
    //   9: aload_0
    //   10: iconst_0
    //   11: invokevirtual 113	com/mobile/ui/fingerprint/fragment/NoFingerprintsDialogFragment:setTargetFragment	(Landroid/support/v4/app/Fragment;I)V
    //   14: iconst_0
    //   15: tableswitch	default:+21->36, 0:+48->63, 1:+-1->14
    //   36: iconst_0
    //   37: tableswitch	default:+23->60, 0:+26->63, 1:+-23->14
    //   60: goto -24 -> 36
    //   63: getstatic 33	com/mobile/ui/fingerprint/fragment/ShouldShowFingerprintsChangedDialogFragment:b042904290429ЩЩ0429ЩЩ	I
    //   66: invokestatic 98	com/mobile/ui/fingerprint/fragment/ShouldShowFingerprintsChangedDialogFragment:b0429Щ04290429Щ0429ЩЩ	()I
    //   69: iadd
    //   70: getstatic 33	com/mobile/ui/fingerprint/fragment/ShouldShowFingerprintsChangedDialogFragment:b042904290429ЩЩ0429ЩЩ	I
    //   73: imul
    //   74: getstatic 37	com/mobile/ui/fingerprint/fragment/ShouldShowFingerprintsChangedDialogFragment:bЩ0429Щ0429Щ0429ЩЩ	I
    //   77: irem
    //   78: invokestatic 115	com/mobile/ui/fingerprint/fragment/ShouldShowFingerprintsChangedDialogFragment:bЩЩЩЩ04290429ЩЩ	()I
    //   81: if_icmpeq +46 -> 127
    //   84: bipush 42
    //   86: putstatic 33	com/mobile/ui/fingerprint/fragment/ShouldShowFingerprintsChangedDialogFragment:b042904290429ЩЩ0429ЩЩ	I
    //   89: getstatic 33	com/mobile/ui/fingerprint/fragment/ShouldShowFingerprintsChangedDialogFragment:b042904290429ЩЩ0429ЩЩ	I
    //   92: getstatic 35	com/mobile/ui/fingerprint/fragment/ShouldShowFingerprintsChangedDialogFragment:b0429ЩЩ0429Щ0429ЩЩ	I
    //   95: iadd
    //   96: getstatic 33	com/mobile/ui/fingerprint/fragment/ShouldShowFingerprintsChangedDialogFragment:b042904290429ЩЩ0429ЩЩ	I
    //   99: imul
    //   100: getstatic 37	com/mobile/ui/fingerprint/fragment/ShouldShowFingerprintsChangedDialogFragment:bЩ0429Щ0429Щ0429ЩЩ	I
    //   103: irem
    //   104: invokestatic 115	com/mobile/ui/fingerprint/fragment/ShouldShowFingerprintsChangedDialogFragment:bЩЩЩЩ04290429ЩЩ	()I
    //   107: if_icmpeq +15 -> 122
    //   110: invokestatic 41	com/mobile/ui/fingerprint/fragment/ShouldShowFingerprintsChangedDialogFragment:b04290429Щ0429Щ0429ЩЩ	()I
    //   113: putstatic 33	com/mobile/ui/fingerprint/fragment/ShouldShowFingerprintsChangedDialogFragment:b042904290429ЩЩ0429ЩЩ	I
    //   116: invokestatic 41	com/mobile/ui/fingerprint/fragment/ShouldShowFingerprintsChangedDialogFragment:b04290429Щ0429Щ0429ЩЩ	()I
    //   119: putstatic 39	com/mobile/ui/fingerprint/fragment/ShouldShowFingerprintsChangedDialogFragment:bЩЩЩ0429Щ0429ЩЩ	I
    //   122: bipush 86
    //   124: putstatic 39	com/mobile/ui/fingerprint/fragment/ShouldShowFingerprintsChangedDialogFragment:bЩЩЩ0429Щ0429ЩЩ	I
    //   127: aload_0
    //   128: invokevirtual 119	com/mobile/ui/fingerprint/fragment/ShouldShowFingerprintsChangedDialogFragment:getActivity	()Landroid/support/v4/app/FragmentActivity;
    //   131: invokevirtual 125	android/support/v4/app/FragmentActivity:getSupportFragmentManager	()Landroid/support/v4/app/FragmentManager;
    //   134: astore_2
    //   135: ldc 2
    //   137: invokevirtual 131	java/lang/Class:getSimpleName	()Ljava/lang/String;
    //   140: astore_3
    //   141: aload_1
    //   142: aload_2
    //   143: aload_3
    //   144: invokevirtual 135	com/mobile/ui/fingerprint/fragment/NoFingerprintsDialogFragment:show	(Landroid/support/v4/app/FragmentManager;Ljava/lang/String;)V
    //   147: return
    //   148: astore_1
    //   149: aload_1
    //   150: athrow
    //   151: astore_1
    //   152: aload_1
    //   153: athrow
    // Local variable table:
    //   start	length	slot	name	signature
    //   0	154	0	this	ShouldShowFingerprintsChangedDialogFragment
    //   7	135	1	localNoFingerprintsDialogFragment	NoFingerprintsDialogFragment
    //   148	2	1	localException1	Exception
    //   151	2	1	localException2	Exception
    //   134	9	2	localFragmentManager	FragmentManager
    //   140	4	3	str	String
    // Exception table:
    //   from	to	target	type
    //   0	8	148	java/lang/Exception
    //   127	141	148	java/lang/Exception
    //   8	14	151	java/lang/Exception
    //   141	147	151	java/lang/Exception
  }
  
  public void showOptInFailed()
  {
    HomeActivity localHomeActivity = (HomeActivity)getActivity();
    switch (0)
    {
    case 1: 
    default: 
      for (;;)
      {
        if ((b04290429Щ0429Щ0429ЩЩ() + b0429ЩЩ0429Щ0429ЩЩ) * b04290429Щ0429Щ0429ЩЩ() % bЩ0429Щ0429Щ0429ЩЩ != bЩЩЩ0429Щ0429ЩЩ)
        {
          b042904290429ЩЩ0429ЩЩ = b04290429Щ0429Щ0429ЩЩ();
          bЩЩЩ0429Щ0429ЩЩ = 24;
        }
        switch (0)
        {
        }
      }
    }
    if ((b042904290429ЩЩ0429ЩЩ + b0429Щ04290429Щ0429ЩЩ()) * b042904290429ЩЩ0429ЩЩ % bЩЩ04290429Щ0429ЩЩ() != bЩЩЩ0429Щ0429ЩЩ)
    {
      b042904290429ЩЩ0429ЩЩ = 70;
      bЩЩЩ0429Щ0429ЩЩ = 33;
    }
    int i = R.string.fingerprint_opt_in_failed_alert;
    switch (0)
    {
    case 1: 
    default: 
      for (;;)
      {
        switch (1)
        {
        }
      }
    }
    localHomeActivity.showErrorNotification(getString(i));
  }
  
  /* Error */
  public void showOptedInDialog()
  {
    // Byte code:
    //   0: new 154	com/mobile/ui/fingerprint/fragment/FingerprintOptedInDialogFragment
    //   3: dup
    //   4: invokespecial 155	com/mobile/ui/fingerprint/fragment/FingerprintOptedInDialogFragment:<init>	()V
    //   7: astore_1
    //   8: aload_1
    //   9: aload_0
    //   10: iconst_0
    //   11: invokevirtual 156	com/mobile/ui/fingerprint/fragment/FingerprintOptedInDialogFragment:setTargetFragment	(Landroid/support/v4/app/Fragment;I)V
    //   14: getstatic 33	com/mobile/ui/fingerprint/fragment/ShouldShowFingerprintsChangedDialogFragment:b042904290429ЩЩ0429ЩЩ	I
    //   17: getstatic 35	com/mobile/ui/fingerprint/fragment/ShouldShowFingerprintsChangedDialogFragment:b0429ЩЩ0429Щ0429ЩЩ	I
    //   20: iadd
    //   21: getstatic 33	com/mobile/ui/fingerprint/fragment/ShouldShowFingerprintsChangedDialogFragment:b042904290429ЩЩ0429ЩЩ	I
    //   24: imul
    //   25: getstatic 37	com/mobile/ui/fingerprint/fragment/ShouldShowFingerprintsChangedDialogFragment:bЩ0429Щ0429Щ0429ЩЩ	I
    //   28: irem
    //   29: getstatic 39	com/mobile/ui/fingerprint/fragment/ShouldShowFingerprintsChangedDialogFragment:bЩЩЩ0429Щ0429ЩЩ	I
    //   32: if_icmpeq +46 -> 78
    //   35: bipush 44
    //   37: putstatic 33	com/mobile/ui/fingerprint/fragment/ShouldShowFingerprintsChangedDialogFragment:b042904290429ЩЩ0429ЩЩ	I
    //   40: invokestatic 41	com/mobile/ui/fingerprint/fragment/ShouldShowFingerprintsChangedDialogFragment:b04290429Щ0429Щ0429ЩЩ	()I
    //   43: putstatic 39	com/mobile/ui/fingerprint/fragment/ShouldShowFingerprintsChangedDialogFragment:bЩЩЩ0429Щ0429ЩЩ	I
    //   46: invokestatic 41	com/mobile/ui/fingerprint/fragment/ShouldShowFingerprintsChangedDialogFragment:b04290429Щ0429Щ0429ЩЩ	()I
    //   49: getstatic 35	com/mobile/ui/fingerprint/fragment/ShouldShowFingerprintsChangedDialogFragment:b0429ЩЩ0429Щ0429ЩЩ	I
    //   52: iadd
    //   53: invokestatic 41	com/mobile/ui/fingerprint/fragment/ShouldShowFingerprintsChangedDialogFragment:b04290429Щ0429Щ0429ЩЩ	()I
    //   56: imul
    //   57: getstatic 37	com/mobile/ui/fingerprint/fragment/ShouldShowFingerprintsChangedDialogFragment:bЩ0429Щ0429Щ0429ЩЩ	I
    //   60: irem
    //   61: invokestatic 115	com/mobile/ui/fingerprint/fragment/ShouldShowFingerprintsChangedDialogFragment:bЩЩЩЩ04290429ЩЩ	()I
    //   64: if_icmpeq +14 -> 78
    //   67: bipush 99
    //   69: putstatic 33	com/mobile/ui/fingerprint/fragment/ShouldShowFingerprintsChangedDialogFragment:b042904290429ЩЩ0429ЩЩ	I
    //   72: invokestatic 41	com/mobile/ui/fingerprint/fragment/ShouldShowFingerprintsChangedDialogFragment:b04290429Щ0429Щ0429ЩЩ	()I
    //   75: putstatic 39	com/mobile/ui/fingerprint/fragment/ShouldShowFingerprintsChangedDialogFragment:bЩЩЩ0429Щ0429ЩЩ	I
    //   78: aload_1
    //   79: aload_0
    //   80: invokevirtual 119	com/mobile/ui/fingerprint/fragment/ShouldShowFingerprintsChangedDialogFragment:getActivity	()Landroid/support/v4/app/FragmentActivity;
    //   83: invokevirtual 125	android/support/v4/app/FragmentActivity:getSupportFragmentManager	()Landroid/support/v4/app/FragmentManager;
    //   86: ldc 2
    //   88: invokevirtual 131	java/lang/Class:getSimpleName	()Ljava/lang/String;
    //   91: invokevirtual 157	com/mobile/ui/fingerprint/fragment/FingerprintOptedInDialogFragment:show	(Landroid/support/v4/app/FragmentManager;Ljava/lang/String;)V
    //   94: return
    //   95: astore_1
    //   96: aload_1
    //   97: athrow
    //   98: astore_1
    //   99: aload_1
    //   100: athrow
    // Local variable table:
    //   start	length	slot	name	signature
    //   0	101	0	this	ShouldShowFingerprintsChangedDialogFragment
    //   7	72	1	localFingerprintOptedInDialogFragment	FingerprintOptedInDialogFragment
    //   95	2	1	localException1	Exception
    //   98	2	1	localException2	Exception
    // Exception table:
    //   from	to	target	type
    //   0	14	95	java/lang/Exception
    //   78	94	98	java/lang/Exception
  }
  
  public void showOptedOutDialog()
  {
    FingerprintOptedOutDialogFragment localFingerprintOptedOutDialogFragment = new FingerprintOptedOutDialogFragment();
    localFingerprintOptedOutDialogFragment.setTargetFragment(this, 0);
    FragmentManager localFragmentManager = getActivity().getSupportFragmentManager();
    String str = ShouldShowFingerprintsChangedDialogFragment.class.getSimpleName();
    if ((b042904290429ЩЩ0429ЩЩ + b0429ЩЩ0429Щ0429ЩЩ) * b042904290429ЩЩ0429ЩЩ % bЩ0429Щ0429Щ0429ЩЩ != bЩЩЩ0429Щ0429ЩЩ)
    {
      b042904290429ЩЩ0429ЩЩ = b04290429Щ0429Щ0429ЩЩ();
      bЩЩЩ0429Щ0429ЩЩ = b04290429Щ0429Щ0429ЩЩ();
    }
    localFingerprintOptedOutDialogFragment.show(localFragmentManager, str);
  }
  
  /* Error */
  public void showRiskDialog()
  {
    // Byte code:
    //   0: getstatic 33	com/mobile/ui/fingerprint/fragment/ShouldShowFingerprintsChangedDialogFragment:b042904290429ЩЩ0429ЩЩ	I
    //   3: istore_1
    //   4: iload_1
    //   5: getstatic 35	com/mobile/ui/fingerprint/fragment/ShouldShowFingerprintsChangedDialogFragment:b0429ЩЩ0429Щ0429ЩЩ	I
    //   8: iload_1
    //   9: iadd
    //   10: imul
    //   11: getstatic 37	com/mobile/ui/fingerprint/fragment/ShouldShowFingerprintsChangedDialogFragment:bЩ0429Щ0429Щ0429ЩЩ	I
    //   14: irem
    //   15: tableswitch	default:+17->32, 0:+28->43
    //   32: bipush 48
    //   34: putstatic 33	com/mobile/ui/fingerprint/fragment/ShouldShowFingerprintsChangedDialogFragment:b042904290429ЩЩ0429ЩЩ	I
    //   37: invokestatic 41	com/mobile/ui/fingerprint/fragment/ShouldShowFingerprintsChangedDialogFragment:b04290429Щ0429Щ0429ЩЩ	()I
    //   40: putstatic 39	com/mobile/ui/fingerprint/fragment/ShouldShowFingerprintsChangedDialogFragment:bЩЩЩ0429Щ0429ЩЩ	I
    //   43: new 165	com/mobile/ui/fingerprint/fragment/FingerprintsChangedRiskDialogFragment
    //   46: dup
    //   47: invokespecial 166	com/mobile/ui/fingerprint/fragment/FingerprintsChangedRiskDialogFragment:<init>	()V
    //   50: astore 6
    //   52: aload 6
    //   54: aload_0
    //   55: iconst_0
    //   56: invokevirtual 167	com/mobile/ui/fingerprint/fragment/FingerprintsChangedRiskDialogFragment:setTargetFragment	(Landroid/support/v4/app/Fragment;I)V
    //   59: aload_0
    //   60: invokevirtual 119	com/mobile/ui/fingerprint/fragment/ShouldShowFingerprintsChangedDialogFragment:getActivity	()Landroid/support/v4/app/FragmentActivity;
    //   63: astore 7
    //   65: getstatic 33	com/mobile/ui/fingerprint/fragment/ShouldShowFingerprintsChangedDialogFragment:b042904290429ЩЩ0429ЩЩ	I
    //   68: istore_1
    //   69: getstatic 35	com/mobile/ui/fingerprint/fragment/ShouldShowFingerprintsChangedDialogFragment:b0429ЩЩ0429Щ0429ЩЩ	I
    //   72: istore_2
    //   73: getstatic 33	com/mobile/ui/fingerprint/fragment/ShouldShowFingerprintsChangedDialogFragment:b042904290429ЩЩ0429ЩЩ	I
    //   76: istore_3
    //   77: getstatic 37	com/mobile/ui/fingerprint/fragment/ShouldShowFingerprintsChangedDialogFragment:bЩ0429Щ0429Щ0429ЩЩ	I
    //   80: istore 4
    //   82: invokestatic 115	com/mobile/ui/fingerprint/fragment/ShouldShowFingerprintsChangedDialogFragment:bЩЩЩЩ04290429ЩЩ	()I
    //   85: istore 5
    //   87: iload_1
    //   88: iload_2
    //   89: iadd
    //   90: iload_3
    //   91: imul
    //   92: iload 4
    //   94: irem
    //   95: iload 5
    //   97: if_icmpeq +14 -> 111
    //   100: bipush 74
    //   102: putstatic 33	com/mobile/ui/fingerprint/fragment/ShouldShowFingerprintsChangedDialogFragment:b042904290429ЩЩ0429ЩЩ	I
    //   105: invokestatic 41	com/mobile/ui/fingerprint/fragment/ShouldShowFingerprintsChangedDialogFragment:b04290429Щ0429Щ0429ЩЩ	()I
    //   108: putstatic 39	com/mobile/ui/fingerprint/fragment/ShouldShowFingerprintsChangedDialogFragment:bЩЩЩ0429Щ0429ЩЩ	I
    //   111: aload 7
    //   113: invokevirtual 125	android/support/v4/app/FragmentActivity:getSupportFragmentManager	()Landroid/support/v4/app/FragmentManager;
    //   116: astore 7
    //   118: aload 6
    //   120: aload 7
    //   122: ldc 2
    //   124: invokevirtual 131	java/lang/Class:getSimpleName	()Ljava/lang/String;
    //   127: invokevirtual 168	com/mobile/ui/fingerprint/fragment/FingerprintsChangedRiskDialogFragment:show	(Landroid/support/v4/app/FragmentManager;Ljava/lang/String;)V
    //   130: return
    //   131: astore 6
    //   133: aload 6
    //   135: athrow
    //   136: astore 6
    //   138: aload 6
    //   140: athrow
    //   141: astore 6
    //   143: aload 6
    //   145: athrow
    //   146: astore 6
    //   148: aload 6
    //   150: athrow
    // Local variable table:
    //   start	length	slot	name	signature
    //   0	151	0	this	ShouldShowFingerprintsChangedDialogFragment
    //   3	87	1	i	int
    //   72	18	2	j	int
    //   76	16	3	k	int
    //   80	15	4	m	int
    //   85	13	5	n	int
    //   50	69	6	localFingerprintsChangedRiskDialogFragment	FingerprintsChangedRiskDialogFragment
    //   131	3	6	localException1	Exception
    //   136	3	6	localException2	Exception
    //   141	3	6	localException3	Exception
    //   146	3	6	localException4	Exception
    //   63	58	7	localObject	Object
    // Exception table:
    //   from	to	target	type
    //   43	59	131	java/lang/Exception
    //   111	118	131	java/lang/Exception
    //   65	87	136	java/lang/Exception
    //   133	136	136	java/lang/Exception
    //   143	146	136	java/lang/Exception
    //   59	65	141	java/lang/Exception
    //   118	130	141	java/lang/Exception
    //   100	111	146	java/lang/Exception
  }
  
  public void trackScreenView() {}
}
