package com.appdynamics.eumagent.runtime.correlation;

import java.io.UnsupportedEncodingException;
import java.net.URLDecoder;
import java.util.ArrayList;
import java.util.Collections;
import java.util.Iterator;
import java.util.List;
import java.util.UUID;
import kkkkkk.gguuuu;

public class b
{
  public static int b0431б04310431бб = 89;
  public static int b0431ббб0431б = 2;
  public static int bб043104310431бб = 1;
  public static int bб0431бб0431б;
  private final List a = new ArrayList();
  
  public b() {}
  
  private static Long a(String paramString)
  {
    try
    {
      Long localLong = Long.valueOf(paramString);
      long l = localLong.longValue();
      if (l >= 0L)
      {
        i = b0431б04310431бб;
        paramString = localLong;
        switch (i * (bб043104310431бб + i) % b0431ббб0431б)
        {
        default: 
          b0431б04310431бб = 0;
          bб043104310431бб = 22;
          paramString = localLong;
        }
        return paramString;
      }
    }
    catch (NumberFormatException paramString)
    {
      paramString = null;
      int i = b0431б04310431бб;
      try
      {
        int j = bб043104310431бб;
        int k = b0431043104310431бб();
        switch (i * (j + i) % k)
        {
        }
        b0431б04310431бб = bбббб0431б();
        i = bбббб0431б();
        bб043104310431бб = i;
        return null;
      }
      catch (Exception paramString)
      {
        throw paramString;
      }
    }
    catch (Exception paramString)
    {
      throw paramString;
    }
  }
  
  private static String b(String paramString)
  {
    try
    {
      str = gguuuu.bккккк043Aкк043A043A("\001~oU_", '©', '\003');
    }
    catch (UnsupportedEncodingException paramString)
    {
      String str;
      if ((b0431б04310431бб + bб043104310431бб) * b0431б04310431бб % b0431ббб0431б == bб0431бб0431б) {
        break label88;
      }
      b0431б04310431бб = bбббб0431б();
      bб0431бб0431б = bбббб0431б();
      label88:
      paramString = new RuntimeException(paramString);
      switch (1)
      {
      case 0: 
      default: 
        for (;;)
        {
          switch (0)
          {
          }
        }
      }
      throw paramString;
    }
    paramString = URLDecoder.decode(paramString, str);
    if ((b0431б04310431бб + bб043104310431бб) * b0431б04310431бб % b0431ббб0431б != bб0431бб0431б)
    {
      b0431б04310431бб = bбббб0431б();
      bб0431бб0431б = bбббб0431б();
    }
    return paramString;
    switch (0)
    {
    }
    for (;;)
    {
      switch (0)
      {
      }
    }
  }
  
  public static int b0431043104310431бб()
  {
    return 2;
  }
  
  public static int bбббб0431б()
  {
    return 21;
  }
  
  public final a a()
  {
    Collections.sort(this.a);
    ArrayList localArrayList = new ArrayList();
    Object localObject2 = null;
    String str1 = null;
    boolean bool = false;
    Iterator localIterator = this.a.iterator();
    long l1 = -1L;
    long l2 = -1L;
    Object localObject3 = null;
    Object localObject1 = null;
    Object localObject4;
    while (localIterator.hasNext())
    {
      localObject4 = a.a((a)localIterator.next()).split(gguuuu.bккккк043Aкк043A043A("g", 'Õ', '\004'));
      if (localObject4.length == 2)
      {
        if (!gguuuu.bк043Aккк043Aкк043A043A("Wj<JM", '', 'h', '\003').equalsIgnoreCase(localObject4[0])) {
          break label299;
        }
        l1 = a(localObject4[1]).longValue();
      }
    }
    if (localObject3 != null) {
      localArrayList.add(new a.a((String)localObject3, Long.valueOf(l1), Long.valueOf(l2)));
    }
    localObject3 = localObject1;
    if (localObject1 == null) {
      localObject3 = UUID.randomUUID().toString();
    }
    return new a((String)localObject3, (String)localObject2, localArrayList, str1, bool);
    label194:
    if (gguuuu.bккккк043Aкк043A043A("\b\031l\007", '-', '\003').equalsIgnoreCase(localObject4[0]))
    {
      if (localObject3 == null) {
        break label550;
      }
      localArrayList.add(new a.a((String)localObject3, Long.valueOf(l1), Long.valueOf(l2)));
      l2 = -1L;
      l1 = -1L;
    }
    for (;;)
    {
      localObject3 = localObject4[1];
      long l3 = l2;
      l2 = l1;
      l1 = l3;
      break;
      if (gguuuu.bккккк043Aкк043A043A("\023\035\033\030\")\b\034).\037.0\004\023\b\004", '¹', '\001').equalsIgnoreCase(localObject4[0]))
      {
        localObject1 = localObject4[1];
        break;
        label299:
        String str2 = gguuuu.bк043Aккк043Aкк043A043A("p\004T\007\005t\t~\006\006", '¢', 'j', '\003');
        int i = b0431б04310431бб;
        switch (i * (bб043104310431бб + i) % b0431ббб0431б)
        {
        default: 
          b0431б04310431бб = bбббб0431б();
          bб0431бб0431б = 65;
        }
        if (!str2.equalsIgnoreCase(localObject4[0])) {
          break label194;
        }
        l2 = a(localObject4[1]).longValue();
        break;
      }
      for (;;)
      {
        if (gguuuu.bккккк043Aкк043A043A("\f\020\022\004\002\f_\001\013\020\b\rew\003y", 'Ú', '\005').equalsIgnoreCase(localObject4[0]))
        {
          str1 = localObject4[1];
          break;
          switch (0)
          {
          case 1: 
          default: 
            for (;;)
            {
              switch (1)
              {
              }
            }
          }
          if (gguuuu.bккккк043Aкк043A043A("RCOR@L,F8FH<BF%I?3", ' ', '\005').equalsIgnoreCase(localObject4[0]))
          {
            localObject4 = localObject4[1];
            localObject2 = localObject4;
            if ((b0431б04310431бб + bб043104310431бб) * b0431б04310431бб % b0431ббб0431б == bб0431бб0431б) {
              break;
            }
            b0431б04310431бб = 98;
            bб0431бб0431б = 87;
            localObject2 = localObject4;
            break;
          }
        }
      }
      if (!gguuuu.bккккк043Aкк043A043A("LFY,V]\\d<\\W]d6decgi", 'ð', '\004').equalsIgnoreCase(localObject4[0])) {
        break;
      }
      bool = true;
      break;
      label550:
      l3 = l1;
      l1 = l2;
      l2 = l3;
    }
  }
  
  /* Error */
  public final void a(String paramString, List paramList)
  {
    // Byte code:
    //   0: aload_1
    //   1: ifnull +199 -> 200
    //   4: aload_2
    //   5: invokeinterface 169 1 0
    //   10: iconst_1
    //   11: if_icmpne +189 -> 200
    //   14: aload_1
    //   15: ldc -85
    //   17: sipush 195
    //   20: iconst_5
    //   21: invokestatic 65	kkkkkk/gguuuu:bккккк043Aкк043A043A	(Ljava/lang/String;CC)Ljava/lang/String;
    //   24: invokevirtual 114	java/lang/String:split	(Ljava/lang/String;)[Ljava/lang/String;
    //   27: astore_1
    //   28: aload_1
    //   29: arraylength
    //   30: istore_3
    //   31: iload_3
    //   32: iconst_2
    //   33: if_icmpne +167 -> 200
    //   36: ldc -83
    //   38: bipush 29
    //   40: iconst_3
    //   41: invokestatic 65	kkkkkk/gguuuu:bккккк043Aкк043A043A	(Ljava/lang/String;CC)Ljava/lang/String;
    //   44: astore 9
    //   46: getstatic 42	com/appdynamics/eumagent/runtime/correlation/b:b0431б04310431бб	I
    //   49: istore_3
    //   50: getstatic 44	com/appdynamics/eumagent/runtime/correlation/b:bб043104310431бб	I
    //   53: istore 4
    //   55: getstatic 42	com/appdynamics/eumagent/runtime/correlation/b:b0431б04310431бб	I
    //   58: istore 5
    //   60: getstatic 46	com/appdynamics/eumagent/runtime/correlation/b:b0431ббб0431б	I
    //   63: istore 6
    //   65: getstatic 73	com/appdynamics/eumagent/runtime/correlation/b:bб0431бб0431б	I
    //   68: istore 7
    //   70: iload_3
    //   71: iload 4
    //   73: iadd
    //   74: iload 5
    //   76: imul
    //   77: iload 6
    //   79: irem
    //   80: iload 7
    //   82: if_icmpeq +14 -> 96
    //   85: invokestatic 53	com/appdynamics/eumagent/runtime/correlation/b:bбббб0431б	()I
    //   88: putstatic 42	com/appdynamics/eumagent/runtime/correlation/b:b0431б04310431бб	I
    //   91: bipush 58
    //   93: putstatic 73	com/appdynamics/eumagent/runtime/correlation/b:bб0431бб0431б	I
    //   96: aload 9
    //   98: aload_1
    //   99: iconst_0
    //   100: aaload
    //   101: invokevirtual 124	java/lang/String:equalsIgnoreCase	(Ljava/lang/String;)Z
    //   104: istore 8
    //   106: iload 8
    //   108: ifeq +92 -> 200
    //   111: getstatic 42	com/appdynamics/eumagent/runtime/correlation/b:b0431б04310431бб	I
    //   114: istore_3
    //   115: iload_3
    //   116: getstatic 44	com/appdynamics/eumagent/runtime/correlation/b:bб043104310431бб	I
    //   119: iload_3
    //   120: iadd
    //   121: imul
    //   122: getstatic 46	com/appdynamics/eumagent/runtime/correlation/b:b0431ббб0431б	I
    //   125: irem
    //   126: tableswitch	default:+18->144, 0:+29->155
    //   144: invokestatic 53	com/appdynamics/eumagent/runtime/correlation/b:bбббб0431б	()I
    //   147: putstatic 42	com/appdynamics/eumagent/runtime/correlation/b:b0431б04310431бб	I
    //   150: bipush 6
    //   152: putstatic 73	com/appdynamics/eumagent/runtime/correlation/b:bб0431бб0431б	I
    //   155: aload_1
    //   156: iconst_1
    //   157: aaload
    //   158: invokestatic 126	com/appdynamics/eumagent/runtime/correlation/b:a	(Ljava/lang/String;)Ljava/lang/Long;
    //   161: astore_1
    //   162: aload_1
    //   163: ifnull +37 -> 200
    //   166: new 6	com/appdynamics/eumagent/runtime/correlation/b$a
    //   169: dup
    //   170: aload_1
    //   171: aload_2
    //   172: iconst_0
    //   173: invokeinterface 177 2 0
    //   178: checkcast 110	java/lang/String
    //   181: invokestatic 179	com/appdynamics/eumagent/runtime/correlation/b:b	(Ljava/lang/String;)Ljava/lang/String;
    //   184: iconst_0
    //   185: invokespecial 182	com/appdynamics/eumagent/runtime/correlation/b$a:<init>	(Ljava/lang/Long;Ljava/lang/String;B)V
    //   188: astore_1
    //   189: aload_0
    //   190: getfield 25	com/appdynamics/eumagent/runtime/correlation/b:a	Ljava/util/List;
    //   193: aload_1
    //   194: invokeinterface 138 2 0
    //   199: pop
    //   200: return
    //   201: astore_1
    //   202: aload_1
    //   203: athrow
    //   204: astore_1
    //   205: aload_1
    //   206: athrow
    // Local variable table:
    //   start	length	slot	name	signature
    //   0	207	0	this	b
    //   0	207	1	paramString	String
    //   0	207	2	paramList	List
    //   30	92	3	i	int
    //   53	21	4	j	int
    //   58	19	5	k	int
    //   63	17	6	m	int
    //   68	15	7	n	int
    //   104	3	8	bool	boolean
    //   44	53	9	str	String
    // Exception table:
    //   from	to	target	type
    //   4	14	201	java/lang/Exception
    //   36	70	201	java/lang/Exception
    //   96	106	201	java/lang/Exception
    //   155	162	201	java/lang/Exception
    //   166	189	201	java/lang/Exception
    //   14	31	204	java/lang/Exception
    //   85	96	204	java/lang/Exception
    //   189	200	204	java/lang/Exception
  }
  
  static final class a
    implements Comparable
  {
    public static int b043104310431б0431б = 1;
    public static int b04310431б04310431б = 2;
    public static int b0431б0431б0431б = 37;
    public static int bб0431б04310431б;
    private final Long a;
    private final String b;
    
    private a(Long paramLong, String paramString)
    {
      this.a = paramLong;
      this.b = paramString;
    }
    
    public static int b0431бб04310431б()
    {
      return 14;
    }
    
    public static int bб04310431б0431б()
    {
      return 0;
    }
    
    public static int bббб04310431б()
    {
      return 2;
    }
  }
}
