package com.mobile.halifax;

import android.content.Context;
import com.mobile.ui.App;
import kkkkkk.nkkkkk;
import kkkkkk.nknnkk;
import kkkkkk.nnnkkk;

public class HalifaxApp
  extends App
{
  public static int b044104410441с0441044104410441 = 72;
  public static int b0441сс04410441044104410441 = 1;
  public static int bсс044104410441044104410441 = 2;
  public static int bссс04410441044104410441;
  
  public HalifaxApp() {}
  
  public static int b04410441с04410441044104410441()
  {
    return 89;
  }
  
  public static int bс0441с04410441044104410441()
  {
    return 2;
  }
  
  public void attachBaseContext(Context paramContext)
  {
    super.attachBaseContext(paramContext);
    nknnkk.bх0445ххх04450445ххх(this);
    switch (1)
    {
    case 0: 
    default: 
      for (;;)
      {
        switch (0)
        {
        }
      }
    }
    int i = b044104410441с0441044104410441;
    int j = b0441сс04410441044104410441;
    int k = b044104410441с0441044104410441;
    if ((b044104410441с0441044104410441 + b0441сс04410441044104410441) * b044104410441с0441044104410441 % bсс044104410441044104410441 != bссс04410441044104410441)
    {
      b044104410441с0441044104410441 = 69;
      bссс04410441044104410441 = 44;
    }
    if ((i + j) * k % bсс044104410441044104410441 != bссс04410441044104410441)
    {
      b044104410441с0441044104410441 = 5;
      bссс04410441044104410441 = 37;
    }
    nnnkkk.bхх0445ххххххх(this);
    nkkkkk.bЗЗ0417З0417З0417041704170417(this);
  }
  
  /* Error */
  public kkkkkk.uuuuun getAppConfig()
  {
    // Byte code:
    //   0: getstatic 31	com/mobile/halifax/HalifaxApp:b044104410441с0441044104410441	I
    //   3: getstatic 33	com/mobile/halifax/HalifaxApp:b0441сс04410441044104410441	I
    //   6: iadd
    //   7: getstatic 31	com/mobile/halifax/HalifaxApp:b044104410441с0441044104410441	I
    //   10: imul
    //   11: getstatic 35	com/mobile/halifax/HalifaxApp:bсс044104410441044104410441	I
    //   14: irem
    //   15: getstatic 37	com/mobile/halifax/HalifaxApp:bссс04410441044104410441	I
    //   18: if_icmpeq +14 -> 32
    //   21: bipush 16
    //   23: putstatic 31	com/mobile/halifax/HalifaxApp:b044104410441с0441044104410441	I
    //   26: invokestatic 53	com/mobile/halifax/HalifaxApp:b04410441с04410441044104410441	()I
    //   29: putstatic 37	com/mobile/halifax/HalifaxApp:bссс04410441044104410441	I
    //   32: new 55	kkkkkk/dpppdd
    //   35: dup
    //   36: invokespecial 56	kkkkkk/dpppdd:<init>	()V
    //   39: astore 5
    //   41: getstatic 31	com/mobile/halifax/HalifaxApp:b044104410441с0441044104410441	I
    //   44: istore_1
    //   45: getstatic 33	com/mobile/halifax/HalifaxApp:b0441сс04410441044104410441	I
    //   48: istore_2
    //   49: getstatic 31	com/mobile/halifax/HalifaxApp:b044104410441с0441044104410441	I
    //   52: istore_3
    //   53: invokestatic 58	com/mobile/halifax/HalifaxApp:bс0441с04410441044104410441	()I
    //   56: istore 4
    //   58: iload_1
    //   59: iload_2
    //   60: iadd
    //   61: iload_3
    //   62: imul
    //   63: iload 4
    //   65: irem
    //   66: getstatic 37	com/mobile/halifax/HalifaxApp:bссс04410441044104410441	I
    //   69: if_icmpeq +15 -> 84
    //   72: invokestatic 53	com/mobile/halifax/HalifaxApp:b04410441с04410441044104410441	()I
    //   75: putstatic 31	com/mobile/halifax/HalifaxApp:b044104410441с0441044104410441	I
    //   78: invokestatic 53	com/mobile/halifax/HalifaxApp:b04410441с04410441044104410441	()I
    //   81: putstatic 37	com/mobile/halifax/HalifaxApp:bссс04410441044104410441	I
    //   84: aload 5
    //   86: areturn
    //   87: astore 5
    //   89: aload 5
    //   91: athrow
    //   92: astore 5
    //   94: aload 5
    //   96: athrow
    //   97: astore 5
    //   99: aload 5
    //   101: athrow
    // Local variable table:
    //   start	length	slot	name	signature
    //   0	102	0	this	HalifaxApp
    //   44	17	1	i	int
    //   48	13	2	j	int
    //   52	11	3	k	int
    //   56	10	4	m	int
    //   39	46	5	localDpppdd	kkkkkk.dpppdd
    //   87	3	5	localException1	Exception
    //   92	3	5	localException2	Exception
    //   97	3	5	localException3	Exception
    // Exception table:
    //   from	to	target	type
    //   32	41	87	java/lang/Exception
    //   49	58	92	java/lang/Exception
    //   89	92	92	java/lang/Exception
    //   41	49	97	java/lang/Exception
    //   58	84	97	java/lang/Exception
  }
}
