package com.mobile.ui.login.fragment;

import android.support.annotation.Nullable;
import android.support.v4.app.FragmentActivity;
import com.mobile.ui.R.id;
import com.mobile.ui.R.string;
import com.mobile.ui.error.ErrorActivity.eueeee;

public class AppVersionWarnFragment
  extends AppVersionBanFragment
{
  private static final String ARG_CONTINUE_NAVIGATION = "%7-F+88?5;C4O?3I=<7KAHH";
  private static final String ARG_MI_INDICES = "OaWp_\\s^d[a\\_n";
  public static int b041B041B041B041B041BЛ041B041B = 2;
  public static int b041BЛ041B041B041BЛ041B041B = 0;
  public static int bЛ041B041B041B041BЛ041B041B = 1;
  public static int bЛЛ041B041B041BЛ041B041B = 49;
  
  /* Error */
  static
  {
    // Byte code:
    //   0: getstatic 26	com/mobile/ui/login/fragment/AppVersionWarnFragment:ARG_CONTINUE_NAVIGATION	Ljava/lang/String;
    //   3: astore 5
    //   5: getstatic 28	com/mobile/ui/login/fragment/AppVersionWarnFragment:bЛЛ041B041B041BЛ041B041B	I
    //   8: istore_0
    //   9: getstatic 30	com/mobile/ui/login/fragment/AppVersionWarnFragment:bЛ041B041B041B041BЛ041B041B	I
    //   12: istore_1
    //   13: getstatic 28	com/mobile/ui/login/fragment/AppVersionWarnFragment:bЛЛ041B041B041BЛ041B041B	I
    //   16: istore_2
    //   17: getstatic 32	com/mobile/ui/login/fragment/AppVersionWarnFragment:b041B041B041B041B041BЛ041B041B	I
    //   20: istore_3
    //   21: getstatic 34	com/mobile/ui/login/fragment/AppVersionWarnFragment:b041BЛ041B041B041BЛ041B041B	I
    //   24: istore 4
    //   26: iload_0
    //   27: iload_1
    //   28: iadd
    //   29: iload_2
    //   30: imul
    //   31: iload_3
    //   32: irem
    //   33: iload 4
    //   35: if_icmpeq +14 -> 49
    //   38: bipush 70
    //   40: putstatic 28	com/mobile/ui/login/fragment/AppVersionWarnFragment:bЛЛ041B041B041BЛ041B041B	I
    //   43: invokestatic 38	com/mobile/ui/login/fragment/AppVersionWarnFragment:bЛЛЛЛЛ041B041B041B	()I
    //   46: putstatic 34	com/mobile/ui/login/fragment/AppVersionWarnFragment:b041BЛ041B041B041BЛ041B041B	I
    //   49: aload 5
    //   51: sipush 143
    //   54: sipush 210
    //   57: iconst_3
    //   58: invokestatic 44	kkkkkk/gguuuu:bк043Aккк043Aкк043A043A	(Ljava/lang/String;CCC)Ljava/lang/String;
    //   61: putstatic 26	com/mobile/ui/login/fragment/AppVersionWarnFragment:ARG_CONTINUE_NAVIGATION	Ljava/lang/String;
    //   64: getstatic 46	com/mobile/ui/login/fragment/AppVersionWarnFragment:ARG_MI_INDICES	Ljava/lang/String;
    //   67: astore 5
    //   69: getstatic 28	com/mobile/ui/login/fragment/AppVersionWarnFragment:bЛЛ041B041B041BЛ041B041B	I
    //   72: istore_0
    //   73: iload_0
    //   74: getstatic 30	com/mobile/ui/login/fragment/AppVersionWarnFragment:bЛ041B041B041B041BЛ041B041B	I
    //   77: iload_0
    //   78: iadd
    //   79: imul
    //   80: getstatic 32	com/mobile/ui/login/fragment/AppVersionWarnFragment:b041B041B041B041B041BЛ041B041B	I
    //   83: irem
    //   84: tableswitch	default:+20->104, 0:+31->115
    //   104: invokestatic 38	com/mobile/ui/login/fragment/AppVersionWarnFragment:bЛЛЛЛЛ041B041B041B	()I
    //   107: putstatic 28	com/mobile/ui/login/fragment/AppVersionWarnFragment:bЛЛ041B041B041BЛ041B041B	I
    //   110: bipush 46
    //   112: putstatic 34	com/mobile/ui/login/fragment/AppVersionWarnFragment:b041BЛ041B041B041BЛ041B041B	I
    //   115: iconst_1
    //   116: tableswitch	default:+24->140, 0:+-47->69, 1:+51->167
    //   140: iconst_0
    //   141: tableswitch	default:+23->164, 0:+26->167, 1:+-72->69
    //   164: goto -24 -> 140
    //   167: aload 5
    //   169: bipush 78
    //   171: sipush 190
    //   174: iconst_3
    //   175: invokestatic 44	kkkkkk/gguuuu:bк043Aккк043Aкк043A043A	(Ljava/lang/String;CCC)Ljava/lang/String;
    //   178: putstatic 46	com/mobile/ui/login/fragment/AppVersionWarnFragment:ARG_MI_INDICES	Ljava/lang/String;
    //   181: return
    //   182: astore 5
    //   184: aload 5
    //   186: athrow
    //   187: astore 5
    //   189: aload 5
    //   191: athrow
    // Local variable table:
    //   start	length	slot	name	signature
    //   8	72	0	i	int
    //   12	17	1	j	int
    //   16	15	2	k	int
    //   20	13	3	m	int
    //   24	12	4	n	int
    //   3	165	5	str	String
    //   182	3	5	localException1	Exception
    //   187	3	5	localException2	Exception
    // Exception table:
    //   from	to	target	type
    //   0	26	182	java/lang/Exception
    //   49	69	182	java/lang/Exception
    //   38	49	187	java/lang/Exception
    //   167	181	187	java/lang/Exception
  }
  
  public AppVersionWarnFragment() {}
  
  public static int b041BЛЛЛЛ041B041B041B()
  {
    return 2;
  }
  
  public static int bЛ041BЛЛЛ041B041B041B()
  {
    return 1;
  }
  
  public static int bЛЛЛЛЛ041B041B041B()
  {
    return 32;
  }
  
  public static AppVersionWarnFragment newInstance(int[] paramArrayOfInt, ErrorActivity.eueeee paramEueeee)
  {
    throw new Runtime("d2j fail translate: java.lang.IndexOutOfBoundsException: fromIndex < 0: -1\n\tat java.util.BitSet.nextSetBit(BitSet.java:712)\n\tat com.googlecode.dex2jar.ir.ts.array.FillArrayTransformer.makeSureAllElementAreAssigned(FillArrayTransformer.java:505)\n\tat com.googlecode.dex2jar.ir.ts.array.FillArrayTransformer.transformReportChanged(FillArrayTransformer.java:123)\n\tat com.googlecode.dex2jar.ir.ts.StatedTransformer.transform(StatedTransformer.java:10)\n\tat com.googlecode.d2j.dex.Dex2jar$2.optimize(Dex2jar.java:149)\n\tat com.googlecode.d2j.dex.Dex2Asm.convertCode(Dex2Asm.java:414)\n\tat com.googlecode.d2j.dex.ExDex2Asm.convertCode(ExDex2Asm.java:42)\n\tat com.googlecode.d2j.dex.Dex2jar$2.convertCode(Dex2jar.java:128)\n\tat com.googlecode.d2j.dex.Dex2Asm.convertMethod(Dex2Asm.java:509)\n\tat com.googlecode.d2j.dex.Dex2Asm.convertClass(Dex2Asm.java:406)\n\tat com.googlecode.d2j.dex.Dex2Asm.convertDex(Dex2Asm.java:422)\n\tat com.googlecode.d2j.dex.Dex2jar.doTranslate(Dex2jar.java:172)\n\tat com.googlecode.d2j.dex.Dex2jar.to(Dex2jar.java:272)\n\tat com.googlecode.dex2jar.tools.Dex2jarCmd.doCommandLine(Dex2jarCmd.java:108)\n\tat com.googlecode.dex2jar.tools.BaseCmd.doMain(BaseCmd.java:288)\n\tat com.googlecode.dex2jar.tools.Dex2jarCmd.main(Dex2jarCmd.java:32)\n");
  }
  
  public String getAccessibilityErrorMessage()
  {
    String str = getFormattedAccessibilityErrorMessage(getString(R.string.accessibility_warn_screen_error_message));
    switch (0)
    {
    case 1: 
    default: 
      for (;;)
      {
        switch (0)
        {
        }
      }
    }
    if ((bЛЛЛЛЛ041B041B041B() + bЛ041B041B041B041BЛ041B041B) * bЛЛЛЛЛ041B041B041B() % b041B041B041B041B041BЛ041B041B != b041BЛ041B041B041BЛ041B041B)
    {
      bЛЛ041B041B041BЛ041B041B = 57;
      int i = bЛЛ041B041B041BЛ041B041B;
      switch (i * (bЛ041B041B041B041BЛ041B041B + i) % b041B041B041B041B041BЛ041B041B)
      {
      default: 
        bЛЛ041B041B041BЛ041B041B = 48;
        b041BЛ041B041B041BЛ041B041B = 15;
      }
      b041BЛ041B041B041BЛ041B041B = 80;
    }
    return str;
  }
  
  /* Error */
  public String getAccessibilityTitle()
  {
    // Byte code:
    //   0: getstatic 82	com/mobile/ui/R$string:accessibility_warn_screen_title_message	I
    //   3: istore_1
    //   4: aload_0
    //   5: iload_1
    //   6: invokevirtual 74	com/mobile/ui/login/fragment/AppVersionWarnFragment:getString	(I)Ljava/lang/String;
    //   9: astore 5
    //   11: getstatic 28	com/mobile/ui/login/fragment/AppVersionWarnFragment:bЛЛ041B041B041BЛ041B041B	I
    //   14: istore_1
    //   15: getstatic 30	com/mobile/ui/login/fragment/AppVersionWarnFragment:bЛ041B041B041B041BЛ041B041B	I
    //   18: istore_2
    //   19: getstatic 28	com/mobile/ui/login/fragment/AppVersionWarnFragment:bЛЛ041B041B041BЛ041B041B	I
    //   22: istore_3
    //   23: getstatic 32	com/mobile/ui/login/fragment/AppVersionWarnFragment:b041B041B041B041B041BЛ041B041B	I
    //   26: istore 4
    //   28: getstatic 28	com/mobile/ui/login/fragment/AppVersionWarnFragment:bЛЛ041B041B041BЛ041B041B	I
    //   31: getstatic 30	com/mobile/ui/login/fragment/AppVersionWarnFragment:bЛ041B041B041B041BЛ041B041B	I
    //   34: iadd
    //   35: getstatic 28	com/mobile/ui/login/fragment/AppVersionWarnFragment:bЛЛ041B041B041BЛ041B041B	I
    //   38: imul
    //   39: invokestatic 84	com/mobile/ui/login/fragment/AppVersionWarnFragment:b041BЛЛЛЛ041B041B041B	()I
    //   42: irem
    //   43: getstatic 34	com/mobile/ui/login/fragment/AppVersionWarnFragment:b041BЛ041B041B041BЛ041B041B	I
    //   46: if_icmpeq +15 -> 61
    //   49: invokestatic 38	com/mobile/ui/login/fragment/AppVersionWarnFragment:bЛЛЛЛЛ041B041B041B	()I
    //   52: putstatic 28	com/mobile/ui/login/fragment/AppVersionWarnFragment:bЛЛ041B041B041BЛ041B041B	I
    //   55: invokestatic 38	com/mobile/ui/login/fragment/AppVersionWarnFragment:bЛЛЛЛЛ041B041B041B	()I
    //   58: putstatic 34	com/mobile/ui/login/fragment/AppVersionWarnFragment:b041BЛ041B041B041BЛ041B041B	I
    //   61: iload_1
    //   62: iload_2
    //   63: iadd
    //   64: iload_3
    //   65: imul
    //   66: iload 4
    //   68: irem
    //   69: getstatic 34	com/mobile/ui/login/fragment/AppVersionWarnFragment:b041BЛ041B041B041BЛ041B041B	I
    //   72: if_icmpeq +15 -> 87
    //   75: invokestatic 38	com/mobile/ui/login/fragment/AppVersionWarnFragment:bЛЛЛЛЛ041B041B041B	()I
    //   78: putstatic 28	com/mobile/ui/login/fragment/AppVersionWarnFragment:bЛЛ041B041B041BЛ041B041B	I
    //   81: invokestatic 38	com/mobile/ui/login/fragment/AppVersionWarnFragment:bЛЛЛЛЛ041B041B041B	()I
    //   84: putstatic 34	com/mobile/ui/login/fragment/AppVersionWarnFragment:b041BЛ041B041B041BЛ041B041B	I
    //   87: aload 5
    //   89: areturn
    //   90: astore 5
    //   92: aload 5
    //   94: athrow
    //   95: astore 5
    //   97: aload 5
    //   99: athrow
    //   100: astore 5
    //   102: aload 5
    //   104: athrow
    //   105: astore 5
    //   107: aload 5
    //   109: athrow
    // Local variable table:
    //   start	length	slot	name	signature
    //   0	110	0	this	AppVersionWarnFragment
    //   3	61	1	i	int
    //   18	46	2	j	int
    //   22	44	3	k	int
    //   26	43	4	m	int
    //   9	79	5	str	String
    //   90	3	5	localException1	Exception
    //   95	3	5	localException2	Exception
    //   100	3	5	localException3	Exception
    //   105	3	5	localException4	Exception
    // Exception table:
    //   from	to	target	type
    //   0	4	90	java/lang/Exception
    //   11	19	95	java/lang/Exception
    //   23	28	95	java/lang/Exception
    //   92	95	95	java/lang/Exception
    //   102	105	95	java/lang/Exception
    //   4	11	100	java/lang/Exception
    //   19	23	105	java/lang/Exception
    //   61	87	105	java/lang/Exception
  }
  
  public String getErrorMessage()
  {
    FragmentActivity localFragmentActivity = getActivity();
    int i = R.string.warn_screen_error_message;
    if ((bЛЛЛЛЛ041B041B041B() + bЛ041B041B041B041BЛ041B041B) * bЛЛЛЛЛ041B041B041B() % b041B041B041B041B041BЛ041B041B != b041BЛ041B041B041BЛ041B041B)
    {
      bЛЛ041B041B041BЛ041B041B = 90;
      b041BЛ041B041B041BЛ041B041B = bЛЛЛЛЛ041B041B041B();
    }
    return localFragmentActivity.getString(i);
  }
  
  /* Error */
  public String getPrimaryButtonAccessibilityTitle()
  {
    // Byte code:
    //   0: getstatic 99	com/mobile/ui/R$string:accessibility_warn_ban_screen_primary_button_message	I
    //   3: istore_1
    //   4: aload_0
    //   5: iload_1
    //   6: invokevirtual 74	com/mobile/ui/login/fragment/AppVersionWarnFragment:getString	(I)Ljava/lang/String;
    //   9: astore_2
    //   10: aload_2
    //   11: areturn
    //   12: astore_2
    //   13: aload_2
    //   14: athrow
    //   15: astore_2
    //   16: aload_2
    //   17: athrow
    // Local variable table:
    //   start	length	slot	name	signature
    //   0	18	0	this	AppVersionWarnFragment
    //   3	3	1	i	int
    //   9	2	2	str	String
    //   12	2	2	localException1	Exception
    //   15	2	2	localException2	Exception
    // Exception table:
    //   from	to	target	type
    //   4	10	12	java/lang/Exception
    //   0	4	15	java/lang/Exception
  }
  
  public int getScreenId()
  {
    int i = bЛЛ041B041B041BЛ041B041B;
    switch (i * (bЛ041BЛЛЛ041B041B041B() + i) % b041B041B041B041B041BЛ041B041B)
    {
    default: 
      bЛЛ041B041B041BЛ041B041B = bЛЛЛЛЛ041B041B041B();
      b041BЛ041B041B041BЛ041B041B = bЛЛЛЛЛ041B041B041B();
    }
    try
    {
      i = R.id.appWarnErrorScreen;
      return i;
    }
    catch (Exception localException)
    {
      throw localException;
    }
  }
  
  @Nullable
  public String getSecondaryButtonTitle()
  {
    switch (0)
    {
    case 1: 
    default: 
      for (;;)
      {
        switch (0)
        {
        }
      }
    }
    int i = bЛЛ041B041B041BЛ041B041B;
    int j = bЛ041B041B041B041BЛ041B041B;
    int k = bЛЛ041B041B041BЛ041B041B;
    switch (k * (bЛ041B041B041B041BЛ041B041B + k) % b041B041B041B041B041BЛ041B041B)
    {
    default: 
      bЛЛ041B041B041BЛ041B041B = 70;
      b041BЛ041B041B041BЛ041B041B = 71;
    }
    switch (i * (j + i) % b041B041B041B041B041BЛ041B041B)
    {
    default: 
      bЛЛ041B041B041BЛ041B041B = bЛЛЛЛЛ041B041B041B();
      b041BЛ041B041B041BЛ041B041B = 55;
    }
    return getString(R.string.warn_screen_secondary_button_text);
  }
  
  public String getTitle()
  {
    int i = bЛЛЛЛЛ041B041B041B();
    switch (i * (bЛ041BЛЛЛ041B041B041B() + i) % b041B041B041B041B041BЛ041B041B)
    {
    default: 
      bЛЛ041B041B041BЛ041B041B = bЛЛЛЛЛ041B041B041B();
      b041BЛ041B041B041BЛ041B041B = 96;
    }
    try
    {
      String str = getString(R.string.warn_screen_title_text);
      return str;
    }
    catch (Exception localException)
    {
      throw localException;
    }
  }
  
  /* Error */
  public void onClickButtonSecondary()
  {
    // Byte code:
    //   0: aload_0
    //   1: invokevirtual 122	com/mobile/ui/login/fragment/AppVersionWarnFragment:getArguments	()Landroid/os/Bundle;
    //   4: ldc 124
    //   6: bipush 31
    //   8: iconst_4
    //   9: invokestatic 128	kkkkkk/gguuuu:bккккк043Aкк043A043A	(Ljava/lang/String;CC)Ljava/lang/String;
    //   12: invokevirtual 134	android/os/Bundle:getInt	(Ljava/lang/String;)I
    //   15: istore_1
    //   16: invokestatic 140	com/mobile/ui/error/ErrorActivity$eueeee:values	()[Lcom/mobile/ui/error/ErrorActivity$eueeee;
    //   19: iload_1
    //   20: aaload
    //   21: astore 6
    //   23: getstatic 28	com/mobile/ui/login/fragment/AppVersionWarnFragment:bЛЛ041B041B041BЛ041B041B	I
    //   26: istore_1
    //   27: iload_1
    //   28: getstatic 30	com/mobile/ui/login/fragment/AppVersionWarnFragment:bЛ041B041B041B041BЛ041B041B	I
    //   31: iload_1
    //   32: iadd
    //   33: imul
    //   34: getstatic 32	com/mobile/ui/login/fragment/AppVersionWarnFragment:b041B041B041B041B041BЛ041B041B	I
    //   37: irem
    //   38: tableswitch	default:+18->56, 0:+29->67
    //   56: invokestatic 38	com/mobile/ui/login/fragment/AppVersionWarnFragment:bЛЛЛЛЛ041B041B041B	()I
    //   59: putstatic 28	com/mobile/ui/login/fragment/AppVersionWarnFragment:bЛЛ041B041B041BЛ041B041B	I
    //   62: bipush 65
    //   64: putstatic 34	com/mobile/ui/login/fragment/AppVersionWarnFragment:b041BЛ041B041B041BЛ041B041B	I
    //   67: iconst_1
    //   68: tableswitch	default:+24->92, 0:+-1->67, 1:+51->119
    //   92: iconst_0
    //   93: tableswitch	default:+23->116, 0:+26->119, 1:+-26->67
    //   116: goto -24 -> 92
    //   119: getstatic 28	com/mobile/ui/login/fragment/AppVersionWarnFragment:bЛЛ041B041B041BЛ041B041B	I
    //   122: istore_1
    //   123: getstatic 30	com/mobile/ui/login/fragment/AppVersionWarnFragment:bЛ041B041B041B041BЛ041B041B	I
    //   126: istore_2
    //   127: getstatic 28	com/mobile/ui/login/fragment/AppVersionWarnFragment:bЛЛ041B041B041BЛ041B041B	I
    //   130: istore_3
    //   131: getstatic 32	com/mobile/ui/login/fragment/AppVersionWarnFragment:b041B041B041B041B041BЛ041B041B	I
    //   134: istore 4
    //   136: getstatic 34	com/mobile/ui/login/fragment/AppVersionWarnFragment:b041BЛ041B041B041BЛ041B041B	I
    //   139: istore 5
    //   141: iload_1
    //   142: iload_2
    //   143: iadd
    //   144: iload_3
    //   145: imul
    //   146: iload 4
    //   148: irem
    //   149: iload 5
    //   151: if_icmpeq +13 -> 164
    //   154: bipush 90
    //   156: putstatic 28	com/mobile/ui/login/fragment/AppVersionWarnFragment:bЛЛ041B041B041BЛ041B041B	I
    //   159: bipush 51
    //   161: putstatic 34	com/mobile/ui/login/fragment/AppVersionWarnFragment:b041BЛ041B041B041BЛ041B041B	I
    //   164: aload_0
    //   165: invokevirtual 122	com/mobile/ui/login/fragment/AppVersionWarnFragment:getArguments	()Landroid/os/Bundle;
    //   168: ldc -114
    //   170: bipush 71
    //   172: sipush 174
    //   175: iconst_3
    //   176: invokestatic 44	kkkkkk/gguuuu:bк043Aккк043Aкк043A043A	(Ljava/lang/String;CCC)Ljava/lang/String;
    //   179: invokevirtual 146	android/os/Bundle:getIntArray	(Ljava/lang/String;)[I
    //   182: astore 7
    //   184: aload_0
    //   185: invokevirtual 89	com/mobile/ui/login/fragment/AppVersionWarnFragment:getActivity	()Landroid/support/v4/app/FragmentActivity;
    //   188: checkcast 148	com/mobile/ui/error/ErrorActivity
    //   191: aload 6
    //   193: aload 7
    //   195: invokevirtual 152	com/mobile/ui/error/ErrorActivity:appWarnContinueNavigation	(Lcom/mobile/ui/error/ErrorActivity$eueeee;[I)V
    //   198: return
    //   199: astore 6
    //   201: aload 6
    //   203: athrow
    //   204: astore 6
    //   206: aload 6
    //   208: athrow
    // Local variable table:
    //   start	length	slot	name	signature
    //   0	209	0	this	AppVersionWarnFragment
    //   15	129	1	i	int
    //   126	18	2	j	int
    //   130	16	3	k	int
    //   134	15	4	m	int
    //   139	13	5	n	int
    //   21	171	6	localEueeee	ErrorActivity.eueeee
    //   199	3	6	localException1	Exception
    //   204	3	6	localException2	Exception
    //   182	12	7	arrayOfInt	int[]
    // Exception table:
    //   from	to	target	type
    //   0	23	199	java/lang/Exception
    //   119	141	199	java/lang/Exception
    //   164	184	199	java/lang/Exception
    //   154	164	204	java/lang/Exception
    //   184	198	204	java/lang/Exception
  }
}
