package com.mobile.ui.login.fragment;

import android.content.Context;
import android.os.Bundle;
import android.support.annotation.Nullable;
import android.widget.Button;
import butterknife.BindView;
import butterknife.OnClick;
import com.mobile.ui.App;
import com.mobile.ui.R.string;
import com.mobile.ui.common.fragment.BasePreHomeScreenFragment;
import com.mobile.ui.common.view.InputField;
import kkkkkk.daaada;
import kkkkkk.daadda;
import kkkkkk.dadada;
import kkkkkk.gguuuu;
import kkkkkk.nmmmnn;
import kkkkkk.uyuuuu;
import kkkkkk.uyyyyy;

public class EnterMiPasswordFragment
  extends BasePreHomeScreenFragment<dadada, daadda>
  implements dadada
{
  private static final String ARG_ENTER_MI_VIEW_MODEL = ";MC\\CMTFTbQNe]QNajY\\RT\\";
  public static int b0414041404140414041404140414Д = 4;
  public static int b04140414ДДДДД0414 = 0;
  public static int b0414ДДДДДД0414 = 2;
  public static int bДДДДДДД0414 = 1;
  @BindView(2131493396)
  public Button mContinueButton;
  @BindView(2131494001)
  public InputField mPasswordInput;
  
  /* Error */
  static
  {
    // Byte code:
    //   0: getstatic 34	com/mobile/ui/login/fragment/EnterMiPasswordFragment:b0414041404140414041404140414Д	I
    //   3: istore_0
    //   4: iload_0
    //   5: getstatic 36	com/mobile/ui/login/fragment/EnterMiPasswordFragment:bДДДДДДД0414	I
    //   8: iload_0
    //   9: iadd
    //   10: imul
    //   11: getstatic 38	com/mobile/ui/login/fragment/EnterMiPasswordFragment:b0414ДДДДДД0414	I
    //   14: irem
    //   15: tableswitch	default:+17->32, 0:+112->127
    //   32: getstatic 34	com/mobile/ui/login/fragment/EnterMiPasswordFragment:b0414041404140414041404140414Д	I
    //   35: getstatic 36	com/mobile/ui/login/fragment/EnterMiPasswordFragment:bДДДДДДД0414	I
    //   38: iadd
    //   39: getstatic 34	com/mobile/ui/login/fragment/EnterMiPasswordFragment:b0414041404140414041404140414Д	I
    //   42: imul
    //   43: getstatic 38	com/mobile/ui/login/fragment/EnterMiPasswordFragment:b0414ДДДДДД0414	I
    //   46: irem
    //   47: getstatic 40	com/mobile/ui/login/fragment/EnterMiPasswordFragment:b04140414ДДДДД0414	I
    //   50: if_icmpeq +15 -> 65
    //   53: invokestatic 44	com/mobile/ui/login/fragment/EnterMiPasswordFragment:bД0414ДДДДД0414	()I
    //   56: putstatic 34	com/mobile/ui/login/fragment/EnterMiPasswordFragment:b0414041404140414041404140414Д	I
    //   59: invokestatic 44	com/mobile/ui/login/fragment/EnterMiPasswordFragment:bД0414ДДДДД0414	()I
    //   62: putstatic 40	com/mobile/ui/login/fragment/EnterMiPasswordFragment:b04140414ДДДДД0414	I
    //   65: bipush 91
    //   67: putstatic 34	com/mobile/ui/login/fragment/EnterMiPasswordFragment:b0414041404140414041404140414Д	I
    //   70: bipush 94
    //   72: putstatic 40	com/mobile/ui/login/fragment/EnterMiPasswordFragment:b04140414ДДДДД0414	I
    //   75: iconst_0
    //   76: tableswitch	default:+24->100, 0:+51->127, 1:+-1->75
    //   100: iconst_1
    //   101: tableswitch	default:+23->124, 0:+-26->75, 1:+26->127
    //   124: goto -24 -> 100
    //   127: getstatic 46	com/mobile/ui/login/fragment/EnterMiPasswordFragment:ARG_ENTER_MI_VIEW_MODEL	Ljava/lang/String;
    //   130: sipush 251
    //   133: iconst_4
    //   134: invokestatic 52	kkkkkk/gguuuu:bккккк043Aкк043A043A	(Ljava/lang/String;CC)Ljava/lang/String;
    //   137: astore_1
    //   138: aload_1
    //   139: putstatic 46	com/mobile/ui/login/fragment/EnterMiPasswordFragment:ARG_ENTER_MI_VIEW_MODEL	Ljava/lang/String;
    //   142: return
    //   143: astore_1
    //   144: aload_1
    //   145: athrow
    //   146: astore_1
    //   147: aload_1
    //   148: athrow
    // Local variable table:
    //   start	length	slot	name	signature
    //   3	8	0	i	int
    //   137	2	1	str	String
    //   143	2	1	localException1	Exception
    //   146	2	1	localException2	Exception
    // Exception table:
    //   from	to	target	type
    //   127	138	143	java/lang/Exception
    //   138	142	146	java/lang/Exception
  }
  
  public EnterMiPasswordFragment() {}
  
  public static int b041404140414ДДДД0414()
  {
    return 0;
  }
  
  public static int bД0414ДДДДД0414()
  {
    return 72;
  }
  
  public static int bДД0414ДДДД0414()
  {
    return 1;
  }
  
  public static int bДДД0414ДДД0414()
  {
    return 2;
  }
  
  private daaada getEnterMiViewModel()
  {
    switch (1)
    {
    case 0: 
    default: 
      for (;;)
      {
        int i = b0414041404140414041404140414Д;
        switch (i * (bДДДДДДД0414 + i) % b0414ДДДДДД0414)
        {
        default: 
          b0414041404140414041404140414Д = bД0414ДДДДД0414();
          b04140414ДДДДД0414 = 9;
        }
        switch (1)
        {
        }
      }
    }
    Bundle localBundle = getArguments();
    if ((b0414041404140414041404140414Д + bДДДДДДД0414) * b0414041404140414041404140414Д % b0414ДДДДДД0414 != b04140414ДДДДД0414)
    {
      b0414041404140414041404140414Д = 15;
      b04140414ДДДДД0414 = 5;
    }
    return (daaada)localBundle.getSerializable(gguuuu.bккккк043Aкк043A043A("\034, 7\034$)\031%1\036\031.$\026\021\")\026\027\013\013\021", 'R', '\003'));
  }
  
  public static EnterMiPasswordFragment newInstance(daaada paramDaaada)
  {
    EnterMiPasswordFragment localEnterMiPasswordFragment = new EnterMiPasswordFragment();
    Bundle localBundle = new Bundle();
    if ((b0414041404140414041404140414Д + bДДДДДДД0414) * b0414041404140414041404140414Д % b0414ДДДДДД0414 != b04140414ДДДДД0414)
    {
      b0414041404140414041404140414Д = 68;
      b04140414ДДДДД0414 = 35;
    }
    localBundle.putSerializable(gguuuu.bккккк043Aкк043A043A("y\n}\025y\002\007v\003\017{v\f\002sn\007sthhn", 'Á', '\002'), paramDaaada);
    localEnterMiPasswordFragment.setArguments(localBundle);
    return localEnterMiPasswordFragment;
  }
  
  private void setOnEditorActionListenerOnPasswordInput()
  {
    if ((b0414041404140414041404140414Д + bДД0414ДДДД0414()) * b0414041404140414041404140414Д % b0414ДДДДДД0414 != b04140414ДДДДД0414)
    {
      b0414041404140414041404140414Д = bД0414ДДДДД0414();
      b04140414ДДДДД0414 = 23;
    }
    this.mPasswordInput.setOnEditorActionListener(new EnterMiPasswordFragment.2(this));
    switch (0)
    {
    case 1: 
    default: 
      for (;;)
      {
        switch (0)
        {
        }
      }
    }
    int i = bД0414ДДДДД0414();
    switch (i * (bДДДДДДД0414 + i) % b0414ДДДДДД0414)
    {
    default: 
      b0414041404140414041404140414Д = 60;
      b04140414ДДДДД0414 = 51;
    }
    switch (1)
    {
    case 0: 
    default: 
      for (;;)
      {
        switch (0)
        {
        }
      }
    }
  }
  
  private void submitPassword()
  {
    int i = b0414041404140414041404140414Д;
    switch (i * (bДДДДДДД0414 + i) % b0414ДДДДДД0414)
    {
    default: 
      b0414041404140414041404140414Д = 83;
      b04140414ДДДДД0414 = 41;
    }
    switch (0)
    {
    case 1: 
    default: 
      for (;;)
      {
        switch (1)
        {
        }
      }
    }
    InputField localInputField = this.mPasswordInput;
    if ((bД0414ДДДДД0414() + bДДДДДДД0414) * bД0414ДДДДД0414() % b0414ДДДДДД0414 != b04140414ДДДДД0414)
    {
      b0414041404140414041404140414Д = bД0414ДДДДД0414();
      b04140414ДДДДД0414 = 64;
    }
    submitPassword(localInputField.getText().toString());
  }
  
  private void submitPassword(String paramString)
  {
    try
    {
      String[] arrayOfString = getEnterMiViewModel().bее0435ее0435ееее();
      ((daadda)this.mPresenter).b0435043504350435ееееее(arrayOfString, paramString);
      int i = b0414041404140414041404140414Д;
      int j = bДДДДДДД0414;
      int k = b0414041404140414041404140414Д;
      switch (k * (bДДДДДДД0414 + k) % b0414ДДДДДД0414)
      {
      default: 
        b0414041404140414041404140414Д = bД0414ДДДДД0414();
        b04140414ДДДДД0414 = 32;
      }
      switch (i * (j + i) % b0414ДДДДДД0414)
      {
      default: 
        b0414041404140414041404140414Д = bД0414ДДДДД0414();
        b04140414ДДДДД0414 = bД0414ДДДДД0414();
      }
      return;
    }
    catch (Exception paramString)
    {
      throw paramString;
    }
  }
  
  @OnClick({2131493393})
  public void onClickForgotDetails()
  {
    Context localContext = getContext();
    switch (1)
    {
    case 0: 
    default: 
      for (;;)
      {
        switch (0)
        {
        }
      }
    }
    switch (0)
    {
    case 1: 
    default: 
      for (;;)
      {
        switch (0)
        {
        }
      }
    }
    int i = R.string.mi_forgot_logon_details_url;
    if ((bД0414ДДДДД0414() + bДДДДДДД0414) * bД0414ДДДДД0414() % b0414ДДДДДД0414 != b04140414ДДДДД0414)
    {
      if ((b0414041404140414041404140414Д + bДДДДДДД0414) * b0414041404140414041404140414Д % b0414ДДДДДД0414 != b04140414ДДДДД0414)
      {
        b0414041404140414041404140414Д = 93;
        b04140414ДДДДД0414 = 44;
      }
      b0414041404140414041404140414Д = bД0414ДДДДД0414();
      b04140414ДДДДД0414 = 33;
    }
    nmmmnn.b0418И041804180418041804180418И0418(localContext, getString(i));
  }
  
  /* Error */
  @OnClick({2131493396})
  public void onContinueButtonClicked()
  {
    // Byte code:
    //   0: getstatic 34	com/mobile/ui/login/fragment/EnterMiPasswordFragment:b0414041404140414041404140414Д	I
    //   3: istore_1
    //   4: iload_1
    //   5: invokestatic 61	com/mobile/ui/login/fragment/EnterMiPasswordFragment:bДД0414ДДДД0414	()I
    //   8: iload_1
    //   9: iadd
    //   10: imul
    //   11: getstatic 38	com/mobile/ui/login/fragment/EnterMiPasswordFragment:b0414ДДДДДД0414	I
    //   14: irem
    //   15: tableswitch	default:+17->32, 0:+29->44
    //   32: invokestatic 44	com/mobile/ui/login/fragment/EnterMiPasswordFragment:bД0414ДДДДД0414	()I
    //   35: putstatic 34	com/mobile/ui/login/fragment/EnterMiPasswordFragment:b0414041404140414041404140414Д	I
    //   38: invokestatic 44	com/mobile/ui/login/fragment/EnterMiPasswordFragment:bД0414ДДДДД0414	()I
    //   41: putstatic 40	com/mobile/ui/login/fragment/EnterMiPasswordFragment:b04140414ДДДДД0414	I
    //   44: getstatic 34	com/mobile/ui/login/fragment/EnterMiPasswordFragment:b0414041404140414041404140414Д	I
    //   47: istore_1
    //   48: getstatic 36	com/mobile/ui/login/fragment/EnterMiPasswordFragment:bДДДДДДД0414	I
    //   51: istore_2
    //   52: getstatic 38	com/mobile/ui/login/fragment/EnterMiPasswordFragment:b0414ДДДДДД0414	I
    //   55: istore_3
    //   56: iload_1
    //   57: iload_2
    //   58: iload_1
    //   59: iadd
    //   60: imul
    //   61: iload_3
    //   62: irem
    //   63: tableswitch	default:+17->80, 0:+28->91
    //   80: invokestatic 44	com/mobile/ui/login/fragment/EnterMiPasswordFragment:bД0414ДДДДД0414	()I
    //   83: putstatic 34	com/mobile/ui/login/fragment/EnterMiPasswordFragment:b0414041404140414041404140414Д	I
    //   86: bipush 63
    //   88: putstatic 40	com/mobile/ui/login/fragment/EnterMiPasswordFragment:b04140414ДДДДД0414	I
    //   91: aload_0
    //   92: invokespecial 73	com/mobile/ui/login/fragment/EnterMiPasswordFragment:submitPassword	()V
    //   95: return
    //   96: astore 4
    //   98: aload 4
    //   100: athrow
    //   101: astore 4
    //   103: aload 4
    //   105: athrow
    //   106: astore 4
    //   108: aload 4
    //   110: athrow
    // Local variable table:
    //   start	length	slot	name	signature
    //   0	111	0	this	EnterMiPasswordFragment
    //   3	58	1	i	int
    //   51	9	2	j	int
    //   55	8	3	k	int
    //   96	3	4	localException1	Exception
    //   101	3	4	localException2	Exception
    //   106	3	4	localException3	Exception
    // Exception table:
    //   from	to	target	type
    //   91	95	96	java/lang/Exception
    //   80	91	101	java/lang/Exception
    //   98	101	101	java/lang/Exception
    //   44	56	106	java/lang/Exception
  }
  
  public void onCreate(@Nullable Bundle paramBundle)
  {
    if ((b0414041404140414041404140414Д + bДДДДДДД0414) * b0414041404140414041404140414Д % b0414ДДДДДД0414 != b04140414ДДДДД0414)
    {
      b0414041404140414041404140414Д = 57;
      b04140414ДДДДД0414 = 23;
    }
    switch (0)
    {
    case 1: 
    default: 
      for (;;)
      {
        switch (0)
        {
        }
      }
    }
    super.onCreate(paramBundle);
    App.get().getAppComponent().b041804180418ИИ0418041804180418И(this);
  }
  
  /* Error */
  public android.view.View onCreateView(android.view.LayoutInflater paramLayoutInflater, @Nullable android.view.ViewGroup paramViewGroup, @Nullable Bundle paramBundle)
  {
    // Byte code:
    //   0: getstatic 194	com/mobile/ui/R$layout:fragment_enter_mi_password	I
    //   3: istore 4
    //   5: getstatic 34	com/mobile/ui/login/fragment/EnterMiPasswordFragment:b0414041404140414041404140414Д	I
    //   8: istore 5
    //   10: getstatic 36	com/mobile/ui/login/fragment/EnterMiPasswordFragment:bДДДДДДД0414	I
    //   13: istore 6
    //   15: getstatic 34	com/mobile/ui/login/fragment/EnterMiPasswordFragment:b0414041404140414041404140414Д	I
    //   18: istore 7
    //   20: getstatic 38	com/mobile/ui/login/fragment/EnterMiPasswordFragment:b0414ДДДДДД0414	I
    //   23: istore 8
    //   25: iload 5
    //   27: iload 6
    //   29: iadd
    //   30: iload 7
    //   32: imul
    //   33: iload 8
    //   35: irem
    //   36: getstatic 40	com/mobile/ui/login/fragment/EnterMiPasswordFragment:b04140414ДДДДД0414	I
    //   39: if_icmpeq +45 -> 84
    //   42: bipush 46
    //   44: putstatic 34	com/mobile/ui/login/fragment/EnterMiPasswordFragment:b0414041404140414041404140414Д	I
    //   47: bipush 30
    //   49: putstatic 40	com/mobile/ui/login/fragment/EnterMiPasswordFragment:b04140414ДДДДД0414	I
    //   52: getstatic 34	com/mobile/ui/login/fragment/EnterMiPasswordFragment:b0414041404140414041404140414Д	I
    //   55: getstatic 36	com/mobile/ui/login/fragment/EnterMiPasswordFragment:bДДДДДДД0414	I
    //   58: iadd
    //   59: getstatic 34	com/mobile/ui/login/fragment/EnterMiPasswordFragment:b0414041404140414041404140414Д	I
    //   62: imul
    //   63: getstatic 38	com/mobile/ui/login/fragment/EnterMiPasswordFragment:b0414ДДДДДД0414	I
    //   66: irem
    //   67: getstatic 40	com/mobile/ui/login/fragment/EnterMiPasswordFragment:b04140414ДДДДД0414	I
    //   70: if_icmpeq +14 -> 84
    //   73: bipush 52
    //   75: putstatic 34	com/mobile/ui/login/fragment/EnterMiPasswordFragment:b0414041404140414041404140414Д	I
    //   78: invokestatic 44	com/mobile/ui/login/fragment/EnterMiPasswordFragment:bД0414ДДДДД0414	()I
    //   81: putstatic 40	com/mobile/ui/login/fragment/EnterMiPasswordFragment:b04140414ДДДДД0414	I
    //   84: aload_1
    //   85: iload 4
    //   87: aload_2
    //   88: iconst_0
    //   89: invokevirtual 200	android/view/LayoutInflater:inflate	(ILandroid/view/ViewGroup;Z)Landroid/view/View;
    //   92: astore_1
    //   93: aload_1
    //   94: areturn
    //   95: astore_1
    //   96: aload_1
    //   97: athrow
    //   98: astore_1
    //   99: aload_1
    //   100: athrow
    // Local variable table:
    //   start	length	slot	name	signature
    //   0	101	0	this	EnterMiPasswordFragment
    //   0	101	1	paramLayoutInflater	android.view.LayoutInflater
    //   0	101	2	paramViewGroup	android.view.ViewGroup
    //   0	101	3	paramBundle	Bundle
    //   3	83	4	i	int
    //   8	22	5	j	int
    //   13	17	6	k	int
    //   18	15	7	m	int
    //   23	13	8	n	int
    // Exception table:
    //   from	to	target	type
    //   0	5	95	java/lang/Exception
    //   10	25	95	java/lang/Exception
    //   84	93	95	java/lang/Exception
    //   5	10	98	java/lang/Exception
    //   25	52	98	java/lang/Exception
  }
  
  /* Error */
  public void onViewCreated(android.view.View paramView, @Nullable Bundle paramBundle)
  {
    // Byte code:
    //   0: aload_0
    //   1: aload_1
    //   2: aload_2
    //   3: invokespecial 204	com/mobile/ui/common/fragment/BasePreHomeScreenFragment:onViewCreated	(Landroid/view/View;Landroid/os/Bundle;)V
    //   6: aload_0
    //   7: getfield 65	com/mobile/ui/login/fragment/EnterMiPasswordFragment:mPresenter	Lkkkkkk/gggggr;
    //   10: astore_1
    //   11: aload_1
    //   12: checkcast 139	kkkkkk/daadda
    //   15: aload_0
    //   16: invokevirtual 208	kkkkkk/daadda:b0418И0418ИИИ0418ИИИ	(Lkkkkkk/gggggr$grrrrg;)V
    //   19: iconst_0
    //   20: tableswitch	default:+24->44, 0:+51->71, 1:+-1->19
    //   44: iconst_1
    //   45: tableswitch	default:+23->68, 0:+-26->19, 1:+26->71
    //   68: goto -24 -> 44
    //   71: aload_0
    //   72: invokespecial 210	com/mobile/ui/login/fragment/EnterMiPasswordFragment:setOnEditorActionListenerOnPasswordInput	()V
    //   75: aload_0
    //   76: getfield 108	com/mobile/ui/login/fragment/EnterMiPasswordFragment:mPasswordInput	Lcom/mobile/ui/common/view/InputField;
    //   79: astore_1
    //   80: getstatic 34	com/mobile/ui/login/fragment/EnterMiPasswordFragment:b0414041404140414041404140414Д	I
    //   83: istore_3
    //   84: getstatic 36	com/mobile/ui/login/fragment/EnterMiPasswordFragment:bДДДДДДД0414	I
    //   87: istore 4
    //   89: getstatic 34	com/mobile/ui/login/fragment/EnterMiPasswordFragment:b0414041404140414041404140414Д	I
    //   92: istore 5
    //   94: invokestatic 212	com/mobile/ui/login/fragment/EnterMiPasswordFragment:bДДД0414ДДД0414	()I
    //   97: istore 6
    //   99: getstatic 40	com/mobile/ui/login/fragment/EnterMiPasswordFragment:b04140414ДДДДД0414	I
    //   102: istore 7
    //   104: iload_3
    //   105: iload 4
    //   107: iadd
    //   108: iload 5
    //   110: imul
    //   111: iload 6
    //   113: irem
    //   114: iload 7
    //   116: if_icmpeq +46 -> 162
    //   119: invokestatic 44	com/mobile/ui/login/fragment/EnterMiPasswordFragment:bД0414ДДДДД0414	()I
    //   122: putstatic 34	com/mobile/ui/login/fragment/EnterMiPasswordFragment:b0414041404140414041404140414Д	I
    //   125: getstatic 34	com/mobile/ui/login/fragment/EnterMiPasswordFragment:b0414041404140414041404140414Д	I
    //   128: getstatic 36	com/mobile/ui/login/fragment/EnterMiPasswordFragment:bДДДДДДД0414	I
    //   131: iadd
    //   132: getstatic 34	com/mobile/ui/login/fragment/EnterMiPasswordFragment:b0414041404140414041404140414Д	I
    //   135: imul
    //   136: getstatic 38	com/mobile/ui/login/fragment/EnterMiPasswordFragment:b0414ДДДДДД0414	I
    //   139: irem
    //   140: invokestatic 214	com/mobile/ui/login/fragment/EnterMiPasswordFragment:b041404140414ДДДД0414	()I
    //   143: if_icmpeq +14 -> 157
    //   146: invokestatic 44	com/mobile/ui/login/fragment/EnterMiPasswordFragment:bД0414ДДДДД0414	()I
    //   149: putstatic 34	com/mobile/ui/login/fragment/EnterMiPasswordFragment:b0414041404140414041404140414Д	I
    //   152: bipush 87
    //   154: putstatic 40	com/mobile/ui/login/fragment/EnterMiPasswordFragment:b04140414ДДДДД0414	I
    //   157: bipush 41
    //   159: putstatic 40	com/mobile/ui/login/fragment/EnterMiPasswordFragment:b04140414ДДДДД0414	I
    //   162: new 216	com/mobile/ui/login/fragment/EnterMiPasswordFragment$1
    //   165: dup
    //   166: aload_0
    //   167: invokespecial 217	com/mobile/ui/login/fragment/EnterMiPasswordFragment$1:<init>	(Lcom/mobile/ui/login/fragment/EnterMiPasswordFragment;)V
    //   170: astore_2
    //   171: aload_1
    //   172: aload_2
    //   173: invokevirtual 221	com/mobile/ui/common/view/InputField:addTextChangedListener	(Landroid/text/TextWatcher;)V
    //   176: return
    //   177: astore_1
    //   178: aload_1
    //   179: athrow
    //   180: astore_1
    //   181: aload_1
    //   182: athrow
    // Local variable table:
    //   start	length	slot	name	signature
    //   0	183	0	this	EnterMiPasswordFragment
    //   0	183	1	paramView	android.view.View
    //   0	183	2	paramBundle	Bundle
    //   83	25	3	i	int
    //   87	21	4	j	int
    //   92	19	5	k	int
    //   97	17	6	m	int
    //   102	15	7	n	int
    // Exception table:
    //   from	to	target	type
    //   0	11	177	java/lang/Exception
    //   71	104	177	java/lang/Exception
    //   157	162	177	java/lang/Exception
    //   171	176	177	java/lang/Exception
    //   11	19	180	java/lang/Exception
    //   119	125	180	java/lang/Exception
    //   162	171	180	java/lang/Exception
  }
  
  public void showEnrollmentScreen()
  {
    try
    {
      uyuuuu localUyuuuu = (uyuuuu)getActivity();
      if ((b0414041404140414041404140414Д + bДДДДДДД0414) * b0414041404140414041404140414Д % b0414ДДДДДД0414 != b041404140414ДДДД0414())
      {
        if ((b0414041404140414041404140414Д + bДДДДДДД0414) * b0414041404140414041404140414Д % b0414ДДДДДД0414 != b04140414ДДДДД0414)
        {
          b0414041404140414041404140414Д = 41;
          b04140414ДДДДД0414 = 79;
        }
        switch (1)
        {
        case 0: 
        default: 
          for (;;)
          {
            switch (1)
            {
            }
          }
        }
        b0414041404140414041404140414Д = 79;
        b04140414ДДДДД0414 = 33;
      }
      localUyuuuu.showEnrollmentScreen();
      return;
    }
    catch (Exception localException)
    {
      throw localException;
    }
  }
  
  public void showEnterMiScreen(String paramString)
  {
    uyuuuu localUyuuuu = (uyuuuu)getActivity();
    int i = b0414041404140414041404140414Д;
    switch (i * (bДДДДДДД0414 + i) % b0414ДДДДДД0414)
    {
    default: 
      b0414041404140414041404140414Д = bД0414ДДДДД0414();
      b04140414ДДДДД0414 = bД0414ДДДДД0414();
    }
    localUyuuuu.showReenterMiScreen(getEnterMiViewModel(), paramString);
  }
  
  public void trackScreenView()
  {
    switch (1)
    {
    case 0: 
    default: 
      for (;;)
      {
        int i = b0414041404140414041404140414Д;
        switch (i * (bДДДДДДД0414 + i) % b0414ДДДДДД0414)
        {
        default: 
          b0414041404140414041404140414Д = 29;
          b04140414ДДДДД0414 = 52;
        }
        switch (1)
        {
        }
      }
    }
  }
  
  /* Error */
  public void updateContinueButton(boolean paramBoolean)
  {
    // Byte code:
    //   0: getstatic 34	com/mobile/ui/login/fragment/EnterMiPasswordFragment:b0414041404140414041404140414Д	I
    //   3: istore_2
    //   4: getstatic 36	com/mobile/ui/login/fragment/EnterMiPasswordFragment:bДДДДДДД0414	I
    //   7: istore_3
    //   8: invokestatic 212	com/mobile/ui/login/fragment/EnterMiPasswordFragment:bДДД0414ДДД0414	()I
    //   11: istore 4
    //   13: getstatic 34	com/mobile/ui/login/fragment/EnterMiPasswordFragment:b0414041404140414041404140414Д	I
    //   16: getstatic 36	com/mobile/ui/login/fragment/EnterMiPasswordFragment:bДДДДДДД0414	I
    //   19: iadd
    //   20: getstatic 34	com/mobile/ui/login/fragment/EnterMiPasswordFragment:b0414041404140414041404140414Д	I
    //   23: imul
    //   24: getstatic 38	com/mobile/ui/login/fragment/EnterMiPasswordFragment:b0414ДДДДДД0414	I
    //   27: irem
    //   28: getstatic 40	com/mobile/ui/login/fragment/EnterMiPasswordFragment:b04140414ДДДДД0414	I
    //   31: if_icmpeq +14 -> 45
    //   34: invokestatic 44	com/mobile/ui/login/fragment/EnterMiPasswordFragment:bД0414ДДДДД0414	()I
    //   37: putstatic 34	com/mobile/ui/login/fragment/EnterMiPasswordFragment:b0414041404140414041404140414Д	I
    //   40: bipush 85
    //   42: putstatic 40	com/mobile/ui/login/fragment/EnterMiPasswordFragment:b04140414ДДДДД0414	I
    //   45: iload_2
    //   46: iload_3
    //   47: iload_2
    //   48: iadd
    //   49: imul
    //   50: iload 4
    //   52: irem
    //   53: tableswitch	default:+19->72, 0:+31->84
    //   72: invokestatic 44	com/mobile/ui/login/fragment/EnterMiPasswordFragment:bД0414ДДДДД0414	()I
    //   75: putstatic 34	com/mobile/ui/login/fragment/EnterMiPasswordFragment:b0414041404140414041404140414Д	I
    //   78: invokestatic 44	com/mobile/ui/login/fragment/EnterMiPasswordFragment:bД0414ДДДДД0414	()I
    //   81: putstatic 40	com/mobile/ui/login/fragment/EnterMiPasswordFragment:b04140414ДДДДД0414	I
    //   84: aload_0
    //   85: getfield 240	com/mobile/ui/login/fragment/EnterMiPasswordFragment:mContinueButton	Landroid/widget/Button;
    //   88: astore 5
    //   90: aload 5
    //   92: iload_1
    //   93: invokevirtual 245	android/widget/Button:setEnabled	(Z)V
    //   96: return
    //   97: astore 5
    //   99: aload 5
    //   101: athrow
    //   102: astore 5
    //   104: aload 5
    //   106: athrow
    // Local variable table:
    //   start	length	slot	name	signature
    //   0	107	0	this	EnterMiPasswordFragment
    //   0	107	1	paramBoolean	boolean
    //   3	47	2	i	int
    //   7	42	3	j	int
    //   11	42	4	k	int
    //   88	3	5	localButton	Button
    //   97	3	5	localException1	Exception
    //   102	3	5	localException2	Exception
    // Exception table:
    //   from	to	target	type
    //   84	90	97	java/lang/Exception
    //   90	96	102	java/lang/Exception
  }
}
