package com.mobile.ui.registration.eia.fragment;

import android.view.ViewStub;
import butterknife.BindView;
import com.mobile.ui.R.string;
import com.mobile.ui.eia.fragment.EiaCallFragment;
import kkkkkk.iiisis;
import kkkkkk.isisss.iissss;
import kkkkkk.wdwwww;
import kkkkkk.wwwdww;

public class RegistrationEiaCallFragment
  extends EiaCallFragment<wdwwww, wwwdww>
  implements wdwwww
{
  public static int b0433043304330433г0433г04330433 = 1;
  public static int b04330433гг04330433г04330433 = 2;
  public static int bг043304330433г0433г04330433 = 98;
  public static int bгг0433г04330433г04330433;
  @BindView(2131494292)
  public ViewStub mProgressViewStub;
  
  public RegistrationEiaCallFragment() {}
  
  public static int b0433г0433г04330433г04330433()
  {
    return 1;
  }
  
  public static int b0433ггг04330433г04330433()
  {
    return 10;
  }
  
  public static int bг0433гг04330433г04330433()
  {
    return 0;
  }
  
  public static int bгггг04330433г04330433()
  {
    return 2;
  }
  
  /* Error */
  public static RegistrationEiaCallFragment newInstance(kkkkkk.ttktkk paramTtktkk)
  {
    // Byte code:
    //   0: iconst_1
    //   1: istore_1
    //   2: iload_1
    //   3: iconst_0
    //   4: idiv
    //   5: istore_1
    //   6: goto -4 -> 2
    //   9: getstatic 36	com/mobile/ui/registration/eia/fragment/RegistrationEiaCallFragment:bг043304330433г0433г04330433	I
    //   12: istore_1
    //   13: iload_1
    //   14: getstatic 38	com/mobile/ui/registration/eia/fragment/RegistrationEiaCallFragment:b0433043304330433г0433г04330433	I
    //   17: iload_1
    //   18: iadd
    //   19: imul
    //   20: invokestatic 40	com/mobile/ui/registration/eia/fragment/RegistrationEiaCallFragment:bгггг04330433г04330433	()I
    //   23: irem
    //   24: tableswitch	default:+20->44, 0:+31->55
    //   44: bipush 77
    //   46: putstatic 36	com/mobile/ui/registration/eia/fragment/RegistrationEiaCallFragment:bг043304330433г0433г04330433	I
    //   49: invokestatic 42	com/mobile/ui/registration/eia/fragment/RegistrationEiaCallFragment:b0433ггг04330433г04330433	()I
    //   52: putstatic 38	com/mobile/ui/registration/eia/fragment/RegistrationEiaCallFragment:b0433043304330433г0433г04330433	I
    //   55: aload_3
    //   56: ldc 44
    //   58: bipush 47
    //   60: bipush 49
    //   62: iconst_3
    //   63: invokestatic 50	kkkkkk/gguuuu:bк043Aккк043Aкк043A043A	(Ljava/lang/String;CCC)Ljava/lang/String;
    //   66: aload_0
    //   67: invokevirtual 56	android/os/Bundle:putSerializable	(Ljava/lang/String;Ljava/io/Serializable;)V
    //   70: aload_2
    //   71: aload_3
    //   72: invokevirtual 60	com/mobile/ui/registration/eia/fragment/RegistrationEiaCallFragment:setArguments	(Landroid/os/Bundle;)V
    //   75: aload_2
    //   76: areturn
    //   77: astore_2
    //   78: new 2	com/mobile/ui/registration/eia/fragment/RegistrationEiaCallFragment
    //   81: dup
    //   82: invokespecial 61	com/mobile/ui/registration/eia/fragment/RegistrationEiaCallFragment:<init>	()V
    //   85: astore_2
    //   86: new 52	android/os/Bundle
    //   89: dup
    //   90: invokespecial 62	android/os/Bundle:<init>	()V
    //   93: astore_3
    //   94: iconst_1
    //   95: tableswitch	default:+21->116, 0:+-1->94, 1:+-86->9
    //   116: iconst_1
    //   117: tableswitch	default:+23->140, 0:+-23->94, 1:+-108->9
    //   140: goto -24 -> 116
    //   143: astore_0
    //   144: aload_0
    //   145: athrow
    // Local variable table:
    //   start	length	slot	name	signature
    //   0	146	0	paramTtktkk	kkkkkk.ttktkk
    //   1	19	1	i	int
    //   70	6	2	localRegistrationEiaCallFragment1	RegistrationEiaCallFragment
    //   77	1	2	localException	Exception
    //   85	1	2	localRegistrationEiaCallFragment2	RegistrationEiaCallFragment
    //   55	39	3	localBundle	android.os.Bundle
    // Exception table:
    //   from	to	target	type
    //   2	6	77	java/lang/Exception
    //   55	75	143	java/lang/Exception
    //   78	94	143	java/lang/Exception
  }
  
  /* Error */
  public void onCreate(@android.support.annotation.Nullable android.os.Bundle paramBundle)
  {
    // Byte code:
    //   0: aload_0
    //   1: aload_1
    //   2: invokespecial 66	com/mobile/ui/eia/fragment/EiaCallFragment:onCreate	(Landroid/os/Bundle;)V
    //   5: invokestatic 72	com/mobile/ui/App:get	()Lcom/mobile/ui/App;
    //   8: invokevirtual 76	com/mobile/ui/App:getAppComponent	()Lkkkkkk/uyyyyy;
    //   11: astore_1
    //   12: getstatic 36	com/mobile/ui/registration/eia/fragment/RegistrationEiaCallFragment:bг043304330433г0433г04330433	I
    //   15: istore_2
    //   16: getstatic 38	com/mobile/ui/registration/eia/fragment/RegistrationEiaCallFragment:b0433043304330433г0433г04330433	I
    //   19: istore_3
    //   20: getstatic 36	com/mobile/ui/registration/eia/fragment/RegistrationEiaCallFragment:bг043304330433г0433г04330433	I
    //   23: istore 4
    //   25: getstatic 36	com/mobile/ui/registration/eia/fragment/RegistrationEiaCallFragment:bг043304330433г0433г04330433	I
    //   28: getstatic 38	com/mobile/ui/registration/eia/fragment/RegistrationEiaCallFragment:b0433043304330433г0433г04330433	I
    //   31: iadd
    //   32: getstatic 36	com/mobile/ui/registration/eia/fragment/RegistrationEiaCallFragment:bг043304330433г0433г04330433	I
    //   35: imul
    //   36: getstatic 78	com/mobile/ui/registration/eia/fragment/RegistrationEiaCallFragment:b04330433гг04330433г04330433	I
    //   39: irem
    //   40: getstatic 80	com/mobile/ui/registration/eia/fragment/RegistrationEiaCallFragment:bгг0433г04330433г04330433	I
    //   43: if_icmpeq +15 -> 58
    //   46: invokestatic 42	com/mobile/ui/registration/eia/fragment/RegistrationEiaCallFragment:b0433ггг04330433г04330433	()I
    //   49: putstatic 36	com/mobile/ui/registration/eia/fragment/RegistrationEiaCallFragment:bг043304330433г0433г04330433	I
    //   52: invokestatic 42	com/mobile/ui/registration/eia/fragment/RegistrationEiaCallFragment:b0433ггг04330433г04330433	()I
    //   55: putstatic 80	com/mobile/ui/registration/eia/fragment/RegistrationEiaCallFragment:bгг0433г04330433г04330433	I
    //   58: getstatic 78	com/mobile/ui/registration/eia/fragment/RegistrationEiaCallFragment:b04330433гг04330433г04330433	I
    //   61: istore 5
    //   63: invokestatic 82	com/mobile/ui/registration/eia/fragment/RegistrationEiaCallFragment:bг0433гг04330433г04330433	()I
    //   66: istore 6
    //   68: iload_2
    //   69: iload_3
    //   70: iadd
    //   71: iload 4
    //   73: imul
    //   74: iload 5
    //   76: irem
    //   77: iload 6
    //   79: if_icmpeq +15 -> 94
    //   82: invokestatic 42	com/mobile/ui/registration/eia/fragment/RegistrationEiaCallFragment:b0433ггг04330433г04330433	()I
    //   85: putstatic 36	com/mobile/ui/registration/eia/fragment/RegistrationEiaCallFragment:bг043304330433г0433г04330433	I
    //   88: invokestatic 42	com/mobile/ui/registration/eia/fragment/RegistrationEiaCallFragment:b0433ггг04330433г04330433	()I
    //   91: putstatic 38	com/mobile/ui/registration/eia/fragment/RegistrationEiaCallFragment:b0433043304330433г0433г04330433	I
    //   94: aload_1
    //   95: aload_0
    //   96: invokeinterface 88 2 0
    //   101: return
    //   102: astore_1
    //   103: aload_1
    //   104: athrow
    //   105: astore_1
    //   106: aload_1
    //   107: athrow
    // Local variable table:
    //   start	length	slot	name	signature
    //   0	108	0	this	RegistrationEiaCallFragment
    //   0	108	1	paramBundle	android.os.Bundle
    //   15	56	2	i	int
    //   19	52	3	j	int
    //   23	51	4	k	int
    //   61	16	5	m	int
    //   66	14	6	n	int
    // Exception table:
    //   from	to	target	type
    //   58	68	102	java/lang/Exception
    //   94	101	102	java/lang/Exception
    //   0	25	105	java/lang/Exception
    //   82	94	105	java/lang/Exception
  }
  
  /* Error */
  public void onViewCreated(android.view.View paramView, @android.support.annotation.Nullable android.os.Bundle paramBundle)
  {
    // Byte code:
    //   0: aload_0
    //   1: aload_1
    //   2: aload_2
    //   3: invokespecial 93	com/mobile/ui/eia/fragment/EiaCallFragment:onViewCreated	(Landroid/view/View;Landroid/os/Bundle;)V
    //   6: getstatic 36	com/mobile/ui/registration/eia/fragment/RegistrationEiaCallFragment:bг043304330433г0433г04330433	I
    //   9: istore_3
    //   10: getstatic 38	com/mobile/ui/registration/eia/fragment/RegistrationEiaCallFragment:b0433043304330433г0433г04330433	I
    //   13: istore 4
    //   15: getstatic 36	com/mobile/ui/registration/eia/fragment/RegistrationEiaCallFragment:bг043304330433г0433г04330433	I
    //   18: istore 5
    //   20: invokestatic 40	com/mobile/ui/registration/eia/fragment/RegistrationEiaCallFragment:bгггг04330433г04330433	()I
    //   23: istore 6
    //   25: getstatic 80	com/mobile/ui/registration/eia/fragment/RegistrationEiaCallFragment:bгг0433г04330433г04330433	I
    //   28: istore 7
    //   30: iload_3
    //   31: iload 4
    //   33: iadd
    //   34: iload 5
    //   36: imul
    //   37: iload 6
    //   39: irem
    //   40: iload 7
    //   42: if_icmpeq +13 -> 55
    //   45: bipush 96
    //   47: putstatic 36	com/mobile/ui/registration/eia/fragment/RegistrationEiaCallFragment:bг043304330433г0433г04330433	I
    //   50: bipush 18
    //   52: putstatic 80	com/mobile/ui/registration/eia/fragment/RegistrationEiaCallFragment:bгг0433г04330433г04330433	I
    //   55: aload_0
    //   56: getfield 95	com/mobile/ui/registration/eia/fragment/RegistrationEiaCallFragment:mProgressViewStub	Landroid/view/ViewStub;
    //   59: astore_1
    //   60: getstatic 36	com/mobile/ui/registration/eia/fragment/RegistrationEiaCallFragment:bг043304330433г0433г04330433	I
    //   63: istore_3
    //   64: iload_3
    //   65: getstatic 38	com/mobile/ui/registration/eia/fragment/RegistrationEiaCallFragment:b0433043304330433г0433г04330433	I
    //   68: iload_3
    //   69: iadd
    //   70: imul
    //   71: getstatic 78	com/mobile/ui/registration/eia/fragment/RegistrationEiaCallFragment:b04330433гг04330433г04330433	I
    //   74: irem
    //   75: tableswitch	default:+17->92, 0:+28->103
    //   92: invokestatic 42	com/mobile/ui/registration/eia/fragment/RegistrationEiaCallFragment:b0433ггг04330433г04330433	()I
    //   95: putstatic 36	com/mobile/ui/registration/eia/fragment/RegistrationEiaCallFragment:bг043304330433г0433г04330433	I
    //   98: bipush 86
    //   100: putstatic 80	com/mobile/ui/registration/eia/fragment/RegistrationEiaCallFragment:bгг0433г04330433г04330433	I
    //   103: aload_1
    //   104: invokevirtual 101	android/view/ViewStub:inflate	()Landroid/view/View;
    //   107: pop
    //   108: return
    //   109: astore_1
    //   110: aload_1
    //   111: athrow
    //   112: astore_1
    //   113: aload_1
    //   114: athrow
    //   115: astore_1
    //   116: aload_1
    //   117: athrow
    //   118: astore_1
    //   119: aload_1
    //   120: athrow
    // Local variable table:
    //   start	length	slot	name	signature
    //   0	121	0	this	RegistrationEiaCallFragment
    //   0	121	1	paramView	android.view.View
    //   0	121	2	paramBundle	android.os.Bundle
    //   9	62	3	i	int
    //   13	21	4	j	int
    //   18	19	5	k	int
    //   23	17	6	m	int
    //   28	15	7	n	int
    // Exception table:
    //   from	to	target	type
    //   0	6	109	java/lang/Exception
    //   45	55	112	java/lang/Exception
    //   110	112	112	java/lang/Exception
    //   116	118	112	java/lang/Exception
    //   55	60	115	java/lang/Exception
    //   103	108	115	java/lang/Exception
    //   6	30	118	java/lang/Exception
  }
  
  /* Error */
  public void showCongratulationsScreen()
  {
    // Byte code:
    //   0: getstatic 36	com/mobile/ui/registration/eia/fragment/RegistrationEiaCallFragment:bг043304330433г0433г04330433	I
    //   3: istore_1
    //   4: invokestatic 104	com/mobile/ui/registration/eia/fragment/RegistrationEiaCallFragment:b0433г0433г04330433г04330433	()I
    //   7: istore_2
    //   8: getstatic 36	com/mobile/ui/registration/eia/fragment/RegistrationEiaCallFragment:bг043304330433г0433г04330433	I
    //   11: getstatic 38	com/mobile/ui/registration/eia/fragment/RegistrationEiaCallFragment:b0433043304330433г0433г04330433	I
    //   14: iadd
    //   15: getstatic 36	com/mobile/ui/registration/eia/fragment/RegistrationEiaCallFragment:bг043304330433г0433г04330433	I
    //   18: imul
    //   19: getstatic 78	com/mobile/ui/registration/eia/fragment/RegistrationEiaCallFragment:b04330433гг04330433г04330433	I
    //   22: irem
    //   23: invokestatic 82	com/mobile/ui/registration/eia/fragment/RegistrationEiaCallFragment:bг0433гг04330433г04330433	()I
    //   26: if_icmpeq +15 -> 41
    //   29: invokestatic 42	com/mobile/ui/registration/eia/fragment/RegistrationEiaCallFragment:b0433ггг04330433г04330433	()I
    //   32: putstatic 36	com/mobile/ui/registration/eia/fragment/RegistrationEiaCallFragment:bг043304330433г0433г04330433	I
    //   35: invokestatic 42	com/mobile/ui/registration/eia/fragment/RegistrationEiaCallFragment:b0433ггг04330433г04330433	()I
    //   38: putstatic 80	com/mobile/ui/registration/eia/fragment/RegistrationEiaCallFragment:bгг0433г04330433г04330433	I
    //   41: getstatic 36	com/mobile/ui/registration/eia/fragment/RegistrationEiaCallFragment:bг043304330433г0433г04330433	I
    //   44: istore_3
    //   45: getstatic 78	com/mobile/ui/registration/eia/fragment/RegistrationEiaCallFragment:b04330433гг04330433г04330433	I
    //   48: istore 4
    //   50: getstatic 80	com/mobile/ui/registration/eia/fragment/RegistrationEiaCallFragment:bгг0433г04330433г04330433	I
    //   53: istore 5
    //   55: iload_1
    //   56: iload_2
    //   57: iadd
    //   58: iload_3
    //   59: imul
    //   60: iload 4
    //   62: irem
    //   63: iload 5
    //   65: if_icmpeq +13 -> 78
    //   68: bipush 57
    //   70: putstatic 36	com/mobile/ui/registration/eia/fragment/RegistrationEiaCallFragment:bг043304330433г0433г04330433	I
    //   73: bipush 89
    //   75: putstatic 80	com/mobile/ui/registration/eia/fragment/RegistrationEiaCallFragment:bгг0433г04330433г04330433	I
    //   78: aload_0
    //   79: invokevirtual 108	com/mobile/ui/registration/eia/fragment/RegistrationEiaCallFragment:getActivity	()Landroid/support/v4/app/FragmentActivity;
    //   82: checkcast 110	kkkkkk/iiisis
    //   85: astore 6
    //   87: aload 6
    //   89: invokeinterface 112 1 0
    //   94: return
    //   95: astore 6
    //   97: aload 6
    //   99: athrow
    //   100: astore 6
    //   102: aload 6
    //   104: athrow
    //   105: astore 6
    //   107: aload 6
    //   109: athrow
    //   110: astore 6
    //   112: aload 6
    //   114: athrow
    // Local variable table:
    //   start	length	slot	name	signature
    //   0	115	0	this	RegistrationEiaCallFragment
    //   3	55	1	i	int
    //   7	51	2	j	int
    //   44	16	3	k	int
    //   48	15	4	m	int
    //   53	13	5	n	int
    //   85	3	6	localIiisis	iiisis
    //   95	3	6	localException1	Exception
    //   100	3	6	localException2	Exception
    //   105	3	6	localException3	Exception
    //   110	3	6	localException4	Exception
    // Exception table:
    //   from	to	target	type
    //   78	87	95	java/lang/Exception
    //   68	73	100	java/lang/Exception
    //   97	100	100	java/lang/Exception
    //   107	110	100	java/lang/Exception
    //   87	94	105	java/lang/Exception
    //   0	8	110	java/lang/Exception
    //   41	55	110	java/lang/Exception
    //   73	78	110	java/lang/Exception
  }
  
  public void showFraudDetectedScreen()
  {
    ((iiisis)getActivity()).showMessageScreenForUnrecoverableError(getString(R.string.registration_technical_error_title), getString(R.string.message_mg_1997), isisss.iissss.NONE);
  }
  
  /* Error */
  public void showHelpDeskScreen(String paramString)
  {
    // Byte code:
    //   0: aload_0
    //   1: invokevirtual 108	com/mobile/ui/registration/eia/fragment/RegistrationEiaCallFragment:getActivity	()Landroid/support/v4/app/FragmentActivity;
    //   4: checkcast 110	kkkkkk/iiisis
    //   7: astore 7
    //   9: getstatic 36	com/mobile/ui/registration/eia/fragment/RegistrationEiaCallFragment:bг043304330433г0433г04330433	I
    //   12: istore_2
    //   13: invokestatic 104	com/mobile/ui/registration/eia/fragment/RegistrationEiaCallFragment:b0433г0433г04330433г04330433	()I
    //   16: istore_3
    //   17: getstatic 36	com/mobile/ui/registration/eia/fragment/RegistrationEiaCallFragment:bг043304330433г0433г04330433	I
    //   20: istore 4
    //   22: getstatic 78	com/mobile/ui/registration/eia/fragment/RegistrationEiaCallFragment:b04330433гг04330433г04330433	I
    //   25: istore 5
    //   27: getstatic 80	com/mobile/ui/registration/eia/fragment/RegistrationEiaCallFragment:bгг0433г04330433г04330433	I
    //   30: istore 6
    //   32: iload_2
    //   33: iload_3
    //   34: iadd
    //   35: iload 4
    //   37: imul
    //   38: iload 5
    //   40: irem
    //   41: iload 6
    //   43: if_icmpeq +46 -> 89
    //   46: getstatic 36	com/mobile/ui/registration/eia/fragment/RegistrationEiaCallFragment:bг043304330433г0433г04330433	I
    //   49: getstatic 38	com/mobile/ui/registration/eia/fragment/RegistrationEiaCallFragment:b0433043304330433г0433г04330433	I
    //   52: iadd
    //   53: getstatic 36	com/mobile/ui/registration/eia/fragment/RegistrationEiaCallFragment:bг043304330433г0433г04330433	I
    //   56: imul
    //   57: invokestatic 40	com/mobile/ui/registration/eia/fragment/RegistrationEiaCallFragment:bгггг04330433г04330433	()I
    //   60: irem
    //   61: invokestatic 82	com/mobile/ui/registration/eia/fragment/RegistrationEiaCallFragment:bг0433гг04330433г04330433	()I
    //   64: if_icmpeq +14 -> 78
    //   67: invokestatic 42	com/mobile/ui/registration/eia/fragment/RegistrationEiaCallFragment:b0433ггг04330433г04330433	()I
    //   70: putstatic 36	com/mobile/ui/registration/eia/fragment/RegistrationEiaCallFragment:bг043304330433г0433г04330433	I
    //   73: bipush 92
    //   75: putstatic 80	com/mobile/ui/registration/eia/fragment/RegistrationEiaCallFragment:bгг0433г04330433г04330433	I
    //   78: bipush 32
    //   80: putstatic 36	com/mobile/ui/registration/eia/fragment/RegistrationEiaCallFragment:bг043304330433г0433г04330433	I
    //   83: invokestatic 42	com/mobile/ui/registration/eia/fragment/RegistrationEiaCallFragment:b0433ггг04330433г04330433	()I
    //   86: putstatic 80	com/mobile/ui/registration/eia/fragment/RegistrationEiaCallFragment:bгг0433г04330433г04330433	I
    //   89: aload 7
    //   91: aload_1
    //   92: invokeinterface 140 2 0
    //   97: return
    //   98: astore_1
    //   99: aload_1
    //   100: athrow
    //   101: astore_1
    //   102: aload_1
    //   103: athrow
    //   104: astore_1
    //   105: aload_1
    //   106: athrow
    // Local variable table:
    //   start	length	slot	name	signature
    //   0	107	0	this	RegistrationEiaCallFragment
    //   0	107	1	paramString	String
    //   12	23	2	i	int
    //   16	19	3	j	int
    //   20	18	4	k	int
    //   25	16	5	m	int
    //   30	14	6	n	int
    //   7	83	7	localIiisis	iiisis
    // Exception table:
    //   from	to	target	type
    //   0	9	98	java/lang/Exception
    //   89	97	98	java/lang/Exception
    //   78	89	101	java/lang/Exception
    //   99	101	101	java/lang/Exception
    //   9	32	104	java/lang/Exception
  }
  
  /* Error */
  public void showLetterSentScreen()
  {
    // Byte code:
    //   0: aload_0
    //   1: invokevirtual 108	com/mobile/ui/registration/eia/fragment/RegistrationEiaCallFragment:getActivity	()Landroid/support/v4/app/FragmentActivity;
    //   4: astore 4
    //   6: aload 4
    //   8: checkcast 110	kkkkkk/iiisis
    //   11: astore 4
    //   13: getstatic 36	com/mobile/ui/registration/eia/fragment/RegistrationEiaCallFragment:bг043304330433г0433г04330433	I
    //   16: istore_1
    //   17: getstatic 38	com/mobile/ui/registration/eia/fragment/RegistrationEiaCallFragment:b0433043304330433г0433г04330433	I
    //   20: istore_2
    //   21: getstatic 36	com/mobile/ui/registration/eia/fragment/RegistrationEiaCallFragment:bг043304330433г0433г04330433	I
    //   24: istore_3
    //   25: iload_3
    //   26: getstatic 38	com/mobile/ui/registration/eia/fragment/RegistrationEiaCallFragment:b0433043304330433г0433г04330433	I
    //   29: iload_3
    //   30: iadd
    //   31: imul
    //   32: getstatic 78	com/mobile/ui/registration/eia/fragment/RegistrationEiaCallFragment:b04330433гг04330433г04330433	I
    //   35: irem
    //   36: tableswitch	default:+20->56, 0:+31->67
    //   56: invokestatic 42	com/mobile/ui/registration/eia/fragment/RegistrationEiaCallFragment:b0433ггг04330433г04330433	()I
    //   59: putstatic 36	com/mobile/ui/registration/eia/fragment/RegistrationEiaCallFragment:bг043304330433г0433г04330433	I
    //   62: bipush 63
    //   64: putstatic 80	com/mobile/ui/registration/eia/fragment/RegistrationEiaCallFragment:bгг0433г04330433г04330433	I
    //   67: iload_1
    //   68: iload_2
    //   69: iadd
    //   70: getstatic 36	com/mobile/ui/registration/eia/fragment/RegistrationEiaCallFragment:bг043304330433г0433г04330433	I
    //   73: imul
    //   74: getstatic 78	com/mobile/ui/registration/eia/fragment/RegistrationEiaCallFragment:b04330433гг04330433г04330433	I
    //   77: irem
    //   78: invokestatic 82	com/mobile/ui/registration/eia/fragment/RegistrationEiaCallFragment:bг0433гг04330433г04330433	()I
    //   81: if_icmpeq +17 -> 98
    //   84: invokestatic 42	com/mobile/ui/registration/eia/fragment/RegistrationEiaCallFragment:b0433ггг04330433г04330433	()I
    //   87: putstatic 36	com/mobile/ui/registration/eia/fragment/RegistrationEiaCallFragment:bг043304330433г0433г04330433	I
    //   90: invokestatic 42	com/mobile/ui/registration/eia/fragment/RegistrationEiaCallFragment:b0433ггг04330433г04330433	()I
    //   93: istore_1
    //   94: iload_1
    //   95: putstatic 80	com/mobile/ui/registration/eia/fragment/RegistrationEiaCallFragment:bгг0433г04330433г04330433	I
    //   98: aload 4
    //   100: invokeinterface 143 1 0
    //   105: return
    //   106: astore 4
    //   108: aload 4
    //   110: athrow
    //   111: astore 4
    //   113: aload 4
    //   115: athrow
    //   116: astore 4
    //   118: aload 4
    //   120: athrow
    //   121: astore 4
    //   123: aload 4
    //   125: athrow
    // Local variable table:
    //   start	length	slot	name	signature
    //   0	126	0	this	RegistrationEiaCallFragment
    //   16	79	1	i	int
    //   20	50	2	j	int
    //   24	8	3	k	int
    //   4	95	4	localObject	Object
    //   106	3	4	localException1	Exception
    //   111	3	4	localException2	Exception
    //   116	3	4	localException3	Exception
    //   121	3	4	localException4	Exception
    // Exception table:
    //   from	to	target	type
    //   0	6	106	java/lang/Exception
    //   98	105	106	java/lang/Exception
    //   94	98	111	java/lang/Exception
    //   108	111	111	java/lang/Exception
    //   118	121	111	java/lang/Exception
    //   6	13	116	java/lang/Exception
    //   13	21	121	java/lang/Exception
    //   67	94	121	java/lang/Exception
  }
}
