package com.db.pwcc.dbmobile.transfer.standingorder.confirm;

import android.content.Context;
import android.content.Intent;
import android.os.Bundle;
import android.text.Html;
import android.widget.TextView;
import com.db.pwcc.dbmobile.model.error.DbError;
import com.db.pwcc.dbmobile.model.tan.Authorization;
import com.db.pwcc.dbmobile.model.tan.AuthorizationStatus;
import com.db.pwcc.dbmobile.model.tan.ChallengeResponse;
import com.db.pwcc.dbmobile.tan.ui.TanModule;
import com.db.pwcc.dbmobile.transfer.R.id;
import com.db.pwcc.dbmobile.transfer.R.layout;
import com.db.pwcc.dbmobile.transfer.R.string;
import com.db.pwcc.dbmobile.transfer.inputscreen.activities.ConfirmationActivity;
import com.db.pwcc.dbmobile.transfer.inputscreen.activities.StandingOrderDetailsActivity;
import com.db.pwcc.dbmobile.transfer.inputscreen.activities.StandingOrdersActivity;
import com.db.pwcc.dbmobile.transfer.standingorder.model.StandingOrderRequestResponse;
import com.db.pwcc.dbmobile.transfer.standingorder.model.StandingOrderTemplate;
import com.db.pwcc.dbmobile.transfer.standingorder.model.StandingOrderTransaction;
import java.lang.reflect.InvocationTargetException;
import java.lang.reflect.Method;
import java.text.ParseException;
import java.text.SimpleDateFormat;
import java.util.Calendar;
import java.util.Date;
import java.util.Locale;
import uuuuuu.kkkklk;
import uuuuuu.llvvll.lvvvll;
import uuuuuu.llvvll.vlvvll;
import uuuuuu.ppphhp;
import uuuuuu.pqpppq;
import uuuuuu.vvrvrv;
import uuuuuu.xxsxsx;
import xxxxxx.uxxxxx;

public class StandingOrderConfirmationActivity
  extends ConfirmationActivity
  implements llvvll.lvvvll
{
  public static final String EXTRA_BIC = "N\003~nPxs";
  public static final String EXTRA_FROM_TRANSACTIONS_LIST = "ITPM3P>JN;<L@ECG\037;DD";
  public static final String EXTRA_FROM_TRANSACTION_DETAILS = "\004\021\017\016u\025\005\023\031\b\013\035\023\032\032p\023#\021\032\036&";
  public static final String EXTRA_STANDING_ORDER_REQUEST_RESPONSE = "g\nw\006|\003\t\003k\020\003\005\023s\b\025\032\013\032\034z\017\036\034\034\034\"\025";
  public static final String EXTRA_TAN_CHALLENGE = "\"VSRB6DR(NHTUOYSR";
  public static final String EXTRA_TEMPLATE = "\t\033\026\023\001r\003\n\f\007z\r|";
  public static int b006D006D006D006Dm006Dmm006D = 1;
  public static int b006Dmm006Dm006Dmm006D = 6;
  public static int bm006Dm006Dm006Dmm006D = 0;
  public static int bmm006D006Dm006Dmm006D = 2;
  private ChallengeResponse challengeResponse = null;
  private llvvll.vlvvll presenter = null;
  private StandingOrderRequestResponse standingOrderRequestResponse = null;
  private StandingOrderTemplate standingOrderTemplate = null;
  
  public StandingOrderConfirmationActivity() {}
  
  public static int b006D006Dm006Dm006Dmm006D()
  {
    return 1;
  }
  
  public static int b006Dm006D006Dm006Dmm006D()
  {
    return 60;
  }
  
  public static int bm006D006D006Dm006Dmm006D()
  {
    return 0;
  }
  
  public static int bmmmm006D006Dmm006D()
  {
    return 2;
  }
  
  private boolean isDeleteMode()
  {
    StandingOrderTransaction localStandingOrderTransaction = this.standingOrderRequestResponse.getTransaction();
    if ((b006Dmm006Dm006Dmm006D + b006D006D006D006Dm006Dmm006D) * b006Dmm006Dm006Dmm006D % bmm006D006Dm006Dmm006D != bm006D006D006Dm006Dmm006D())
    {
      if ((b006Dmm006Dm006Dmm006D + b006D006D006D006Dm006Dmm006D) * b006Dmm006Dm006Dmm006D % bmm006D006Dm006Dmm006D != bm006Dm006Dm006Dmm006D)
      {
        b006Dmm006Dm006Dmm006D = 50;
        bm006Dm006Dm006Dmm006D = 35;
      }
      b006Dmm006Dm006Dmm006D = 21;
      bm006Dm006Dm006Dmm006D = 99;
    }
    String str1 = localStandingOrderTransaction.getType();
    if ((b006Dmm006Dm006Dmm006D + b006D006Dm006Dm006Dmm006D()) * b006Dmm006Dm006Dmm006D % bmm006D006Dm006Dmm006D != bm006Dm006Dm006Dmm006D)
    {
      b006Dmm006Dm006Dmm006D = 62;
      int i = b006Dm006D006Dm006Dmm006D();
      int j = b006Dm006D006Dm006Dmm006D();
      switch (j * (j + b006D006D006D006Dm006Dmm006D) % bmm006D006Dm006Dmm006D)
      {
      default: 
        b006Dmm006Dm006Dmm006D = 67;
        bm006Dm006Dm006Dmm006D = b006Dm006D006Dm006Dmm006D();
      }
      bm006Dm006Dm006Dmm006D = i;
    }
    String str2 = uxxxxx.bb00620062bb0062b0062b0062("\013!\"#$]^fgabjk-fgopjkst6", '(', '\002');
    Class[] arrayOfClass = new Class[3];
    arrayOfClass[0] = String.class;
    arrayOfClass[1] = Character.TYPE;
    arrayOfClass[2] = Character.TYPE;
    Method localMethod = ppphhp.class.getMethod(str2, arrayOfClass);
    Object[] arrayOfObject = new Object[3];
    arrayOfObject[0] = "MOWQaSnceSaX^d^whl_ao";
    arrayOfObject[1] = Character.valueOf('D');
    arrayOfObject[2] = Character.valueOf('\001');
    try
    {
      Object localObject = localMethod.invoke(null, arrayOfObject);
      return str1.equals((String)localObject);
    }
    catch (InvocationTargetException localInvocationTargetException)
    {
      throw localInvocationTargetException.getCause();
    }
  }
  
  private boolean isUpdateMode()
  {
    int i = b006Dmm006Dm006Dmm006D;
    switch (i * (i + b006D006D006D006Dm006Dmm006D) % bmm006D006Dm006Dmm006D)
    {
    default: 
      b006Dmm006Dm006Dmm006D = b006Dm006D006Dm006Dmm006D();
      bm006Dm006Dm006Dmm006D = b006Dm006D006Dm006Dmm006D();
      int k = b006Dmm006Dm006Dmm006D;
      switch (k * (k + b006D006D006D006Dm006Dmm006D) % bmm006D006Dm006Dmm006D)
      {
      default: 
        b006Dmm006Dm006Dmm006D = b006Dm006D006Dm006Dmm006D();
        bm006Dm006Dm006Dmm006D = b006Dm006D006Dm006Dmm006D();
      }
      break;
    }
    String str1 = this.standingOrderRequestResponse.getTransaction().getType();
    String str2 = uxxxxx.bb00620062bb0062b0062b0062("\005\033\034\035\036WX`a[\\de'`aijdemn0", '\021', '\001');
    Class[] arrayOfClass = new Class[3];
    arrayOfClass[0] = String.class;
    arrayOfClass[1] = Character.TYPE;
    arrayOfClass[2] = Character.TYPE;
    Method localMethod = ppphhp.class.getMethod(str2, arrayOfClass);
    Object[] arrayOfObject = new Object[3];
    arrayOfObject[0] = "A=20D6QFH6D;AGAZKOBDR";
    arrayOfObject[1] = Character.valueOf('N');
    arrayOfObject[2] = Character.valueOf('\000');
    try
    {
      Object localObject = localMethod.invoke(null, arrayOfObject);
      String str3 = (String)localObject;
      if ((b006Dmm006Dm006Dmm006D + b006D006D006D006Dm006Dmm006D) * b006Dmm006Dm006Dmm006D % bmm006D006Dm006Dmm006D != bm006Dm006Dm006Dmm006D)
      {
        b006Dmm006Dm006Dmm006D = 83;
        bm006Dm006Dm006Dmm006D = b006Dm006D006Dm006Dmm006D();
        int j = b006Dmm006Dm006Dmm006D;
        switch (j * (j + b006D006D006D006Dm006Dmm006D) % bmm006D006Dm006Dmm006D)
        {
        default: 
          b006Dmm006Dm006Dmm006D = b006Dm006D006Dm006Dmm006D();
          bm006Dm006Dm006Dmm006D = 6;
        }
      }
      return str1.equals(str3);
    }
    catch (InvocationTargetException localInvocationTargetException)
    {
      throw localInvocationTargetException.getCause();
    }
  }
  
  public static Intent makeIntent(Context paramContext, StandingOrderRequestResponse paramStandingOrderRequestResponse, ChallengeResponse paramChallengeResponse, Authorization paramAuthorization, AuthorizationStatus paramAuthorizationStatus, String paramString)
  {
    Intent localIntent = makeIntent(paramContext, paramStandingOrderRequestResponse, paramChallengeResponse, paramAuthorization, paramAuthorizationStatus, paramString, null, null, null);
    if ((b006Dmm006Dm006Dmm006D + b006D006D006D006Dm006Dmm006D) * b006Dmm006Dm006Dmm006D % bmm006D006Dm006Dmm006D != bm006Dm006Dm006Dmm006D)
    {
      int i = b006Dmm006Dm006Dmm006D;
      switch (i * (i + b006D006D006D006Dm006Dmm006D) % bmm006D006Dm006Dmm006D)
      {
      default: 
        b006Dmm006Dm006Dmm006D = 43;
        bm006Dm006Dm006Dmm006D = 52;
        if ((b006Dmm006Dm006Dmm006D + b006D006D006D006Dm006Dmm006D) * b006Dmm006Dm006Dmm006D % bmm006D006Dm006Dmm006D != bm006Dm006Dm006Dmm006D)
        {
          b006Dmm006Dm006Dmm006D = 85;
          bm006Dm006Dm006Dmm006D = 60;
        }
        break;
      }
      b006Dmm006Dm006Dmm006D = 48;
      bm006Dm006Dm006Dmm006D = 50;
      int j = b006Dmm006Dm006Dmm006D;
      switch (j * (j + b006D006D006D006Dm006Dmm006D) % bmm006D006Dm006Dmm006D)
      {
      default: 
        b006Dmm006Dm006Dmm006D = b006Dm006D006Dm006Dmm006D();
        bm006Dm006Dm006Dmm006D = 37;
      }
    }
    return localIntent;
  }
  
  public static Intent makeIntent(Context paramContext, StandingOrderRequestResponse paramStandingOrderRequestResponse, ChallengeResponse paramChallengeResponse, Authorization paramAuthorization, AuthorizationStatus paramAuthorizationStatus, String paramString1, String paramString2)
  {
    if ((b006Dmm006Dm006Dmm006D + b006D006D006D006Dm006Dmm006D) * b006Dmm006Dm006Dmm006D % bmmmm006D006Dmm006D() != bm006D006D006Dm006Dmm006D())
    {
      b006Dmm006Dm006Dmm006D = b006Dm006D006Dm006Dmm006D();
      bm006Dm006Dm006Dmm006D = b006Dm006D006Dm006Dmm006D();
    }
    if ((b006Dm006D006Dm006Dmm006D() + b006D006D006D006Dm006Dmm006D) * b006Dm006D006Dm006Dmm006D() % bmm006D006Dm006Dmm006D != bm006Dm006Dm006Dmm006D)
    {
      if ((b006Dmm006Dm006Dmm006D + b006D006D006D006Dm006Dmm006D) * b006Dmm006Dm006Dmm006D % bmm006D006Dm006Dmm006D != bm006Dm006Dm006Dmm006D)
      {
        if ((b006Dmm006Dm006Dmm006D + b006D006Dm006Dm006Dmm006D()) * b006Dmm006Dm006Dmm006D % bmm006D006Dm006Dmm006D != bm006Dm006Dm006Dmm006D)
        {
          b006Dmm006Dm006Dmm006D = b006Dm006D006Dm006Dmm006D();
          bm006Dm006Dm006Dmm006D = 25;
        }
        b006Dmm006Dm006Dmm006D = b006Dm006D006Dm006Dmm006D();
        bm006Dm006Dm006Dmm006D = b006Dm006D006Dm006Dmm006D();
      }
      b006Dmm006Dm006Dmm006D = 32;
      bm006Dm006Dm006Dmm006D = b006Dm006D006Dm006Dmm006D();
    }
    return makeIntent(paramContext, paramStandingOrderRequestResponse, paramChallengeResponse, paramAuthorization, paramAuthorizationStatus, paramString1, paramString2, null, null);
  }
  
  public static Intent makeIntent(Context paramContext, StandingOrderRequestResponse paramStandingOrderRequestResponse, ChallengeResponse paramChallengeResponse, Authorization paramAuthorization, AuthorizationStatus paramAuthorizationStatus, String paramString1, String paramString2, StandingOrderTemplate paramStandingOrderTemplate)
  {
    int i = b006Dmm006Dm006Dmm006D;
    switch (i * (i + b006D006D006D006Dm006Dmm006D) % bmm006D006Dm006Dmm006D)
    {
    default: 
      b006Dmm006Dm006Dmm006D = b006Dm006D006Dm006Dmm006D();
      bm006Dm006Dm006Dmm006D = b006Dm006D006Dm006Dmm006D();
    }
    int j = b006Dm006D006Dm006Dmm006D() + b006D006D006D006Dm006Dmm006D;
    int k = b006Dm006D006Dm006Dmm006D();
    int m = b006Dmm006Dm006Dmm006D;
    switch (m * (m + b006D006D006D006Dm006Dmm006D) % bmm006D006Dm006Dmm006D)
    {
    default: 
      b006Dmm006Dm006Dmm006D = b006Dm006D006Dm006Dmm006D();
      bm006Dm006Dm006Dmm006D = b006Dm006D006Dm006Dmm006D();
      if ((b006Dmm006Dm006Dmm006D + b006D006D006D006Dm006Dmm006D) * b006Dmm006Dm006Dmm006D % bmm006D006Dm006Dmm006D != bm006Dm006Dm006Dmm006D)
      {
        b006Dmm006Dm006Dmm006D = 22;
        bm006Dm006Dm006Dmm006D = 96;
      }
      break;
    }
    if (j * k % bmm006D006Dm006Dmm006D != bm006Dm006Dm006Dmm006D)
    {
      b006Dmm006Dm006Dmm006D = 86;
      bm006Dm006Dm006Dmm006D = 13;
    }
    return makeIntent(paramContext, paramStandingOrderRequestResponse, paramChallengeResponse, paramAuthorization, paramAuthorizationStatus, paramString1, paramString2, paramStandingOrderTemplate, null);
  }
  
  /* Error */
  public static Intent makeIntent(Context paramContext, StandingOrderRequestResponse paramStandingOrderRequestResponse, ChallengeResponse paramChallengeResponse, Authorization paramAuthorization, AuthorizationStatus paramAuthorizationStatus, String paramString1, String paramString2, StandingOrderTemplate paramStandingOrderTemplate, String paramString3)
  {
    // Byte code:
    //   0: new 151	android/content/Intent
    //   3: dup
    //   4: aload_0
    //   5: ldc 2
    //   7: invokespecial 154	android/content/Intent:<init>	(Landroid/content/Context;Ljava/lang/Class;)V
    //   10: astore 9
    //   12: ldc -100
    //   14: bipush 76
    //   16: iconst_1
    //   17: invokestatic 97	xxxxxx/uxxxxx:bb00620062bb0062b0062b0062	(Ljava/lang/String;CC)Ljava/lang/String;
    //   20: astore 10
    //   22: iconst_3
    //   23: anewarray 99	java/lang/Class
    //   26: astore 11
    //   28: aload 11
    //   30: iconst_0
    //   31: ldc 101
    //   33: aastore
    //   34: aload 11
    //   36: iconst_1
    //   37: getstatic 107	java/lang/Character:TYPE	Ljava/lang/Class;
    //   40: aastore
    //   41: aload 11
    //   43: iconst_2
    //   44: getstatic 107	java/lang/Character:TYPE	Ljava/lang/Class;
    //   47: aastore
    //   48: ldc 109
    //   50: aload 10
    //   52: aload 11
    //   54: invokevirtual 113	java/lang/Class:getMethod	(Ljava/lang/String;[Ljava/lang/Class;)Ljava/lang/reflect/Method;
    //   57: astore 12
    //   59: iconst_3
    //   60: anewarray 115	java/lang/Object
    //   63: astore 13
    //   65: aload 13
    //   67: iconst_0
    //   68: ldc -98
    //   70: aastore
    //   71: aload 13
    //   73: iconst_1
    //   74: sipush 131
    //   77: invokestatic 121	java/lang/Character:valueOf	(C)Ljava/lang/Character;
    //   80: aastore
    //   81: aload 13
    //   83: iconst_2
    //   84: iconst_2
    //   85: invokestatic 121	java/lang/Character:valueOf	(C)Ljava/lang/Character;
    //   88: aastore
    //   89: aload 12
    //   91: aconst_null
    //   92: aload 13
    //   94: invokevirtual 127	java/lang/reflect/Method:invoke	(Ljava/lang/Object;[Ljava/lang/Object;)Ljava/lang/Object;
    //   97: astore 15
    //   99: aload 9
    //   101: aload 15
    //   103: checkcast 101	java/lang/String
    //   106: aload_1
    //   107: invokevirtual 162	android/content/Intent:putExtra	(Ljava/lang/String;Ljava/io/Serializable;)Landroid/content/Intent;
    //   110: pop
    //   111: getstatic 71	com/db/pwcc/dbmobile/transfer/standingorder/confirm/StandingOrderConfirmationActivity:b006Dmm006Dm006Dmm006D	I
    //   114: istore 17
    //   116: iload 17
    //   118: iload 17
    //   120: getstatic 73	com/db/pwcc/dbmobile/transfer/standingorder/confirm/StandingOrderConfirmationActivity:b006D006D006D006Dm006Dmm006D	I
    //   123: iadd
    //   124: imul
    //   125: getstatic 75	com/db/pwcc/dbmobile/transfer/standingorder/confirm/StandingOrderConfirmationActivity:bmm006D006Dm006Dmm006D	I
    //   128: irem
    //   129: tableswitch	default:+19->148, 0:+29->158
    //   148: bipush 13
    //   150: putstatic 71	com/db/pwcc/dbmobile/transfer/standingorder/confirm/StandingOrderConfirmationActivity:b006Dmm006Dm006Dmm006D	I
    //   153: bipush 25
    //   155: putstatic 79	com/db/pwcc/dbmobile/transfer/standingorder/confirm/StandingOrderConfirmationActivity:bm006Dm006Dm006Dmm006D	I
    //   158: ldc -92
    //   160: sipush 137
    //   163: iconst_1
    //   164: invokestatic 97	xxxxxx/uxxxxx:bb00620062bb0062b0062b0062	(Ljava/lang/String;CC)Ljava/lang/String;
    //   167: astore 18
    //   169: iconst_3
    //   170: anewarray 99	java/lang/Class
    //   173: astore 19
    //   175: aload 19
    //   177: iconst_0
    //   178: ldc 101
    //   180: aastore
    //   181: aload 19
    //   183: iconst_1
    //   184: getstatic 107	java/lang/Character:TYPE	Ljava/lang/Class;
    //   187: aastore
    //   188: aload 19
    //   190: iconst_2
    //   191: getstatic 107	java/lang/Character:TYPE	Ljava/lang/Class;
    //   194: aastore
    //   195: ldc 109
    //   197: aload 18
    //   199: aload 19
    //   201: invokevirtual 113	java/lang/Class:getMethod	(Ljava/lang/String;[Ljava/lang/Class;)Ljava/lang/reflect/Method;
    //   204: astore 20
    //   206: iconst_3
    //   207: anewarray 115	java/lang/Object
    //   210: astore 21
    //   212: aload 21
    //   214: iconst_0
    //   215: ldc -90
    //   217: aastore
    //   218: aload 21
    //   220: iconst_1
    //   221: sipush 137
    //   224: invokestatic 121	java/lang/Character:valueOf	(C)Ljava/lang/Character;
    //   227: aastore
    //   228: aload 21
    //   230: iconst_2
    //   231: iconst_1
    //   232: invokestatic 121	java/lang/Character:valueOf	(C)Ljava/lang/Character;
    //   235: aastore
    //   236: aload 20
    //   238: aconst_null
    //   239: aload 21
    //   241: invokevirtual 127	java/lang/reflect/Method:invoke	(Ljava/lang/Object;[Ljava/lang/Object;)Ljava/lang/Object;
    //   244: astore 23
    //   246: aload 9
    //   248: aload 23
    //   250: checkcast 101	java/lang/String
    //   253: aload_2
    //   254: invokevirtual 169	android/content/Intent:putExtra	(Ljava/lang/String;Landroid/os/Parcelable;)Landroid/content/Intent;
    //   257: pop
    //   258: ldc -85
    //   260: bipush 115
    //   262: iconst_0
    //   263: invokestatic 97	xxxxxx/uxxxxx:bb00620062bb0062b0062b0062	(Ljava/lang/String;CC)Ljava/lang/String;
    //   266: astore 25
    //   268: iconst_3
    //   269: anewarray 99	java/lang/Class
    //   272: astore 26
    //   274: aload 26
    //   276: iconst_0
    //   277: ldc 101
    //   279: aastore
    //   280: aload 26
    //   282: iconst_1
    //   283: getstatic 107	java/lang/Character:TYPE	Ljava/lang/Class;
    //   286: aastore
    //   287: aload 26
    //   289: iconst_2
    //   290: getstatic 107	java/lang/Character:TYPE	Ljava/lang/Class;
    //   293: aastore
    //   294: ldc 109
    //   296: aload 25
    //   298: aload 26
    //   300: invokevirtual 113	java/lang/Class:getMethod	(Ljava/lang/String;[Ljava/lang/Class;)Ljava/lang/reflect/Method;
    //   303: astore 27
    //   305: iconst_3
    //   306: anewarray 115	java/lang/Object
    //   309: astore 28
    //   311: aload 28
    //   313: iconst_0
    //   314: ldc -83
    //   316: aastore
    //   317: aload 28
    //   319: iconst_1
    //   320: bipush 49
    //   322: invokestatic 121	java/lang/Character:valueOf	(C)Ljava/lang/Character;
    //   325: aastore
    //   326: aload 28
    //   328: iconst_2
    //   329: iconst_4
    //   330: invokestatic 121	java/lang/Character:valueOf	(C)Ljava/lang/Character;
    //   333: aastore
    //   334: aload 27
    //   336: aconst_null
    //   337: aload 28
    //   339: invokevirtual 127	java/lang/reflect/Method:invoke	(Ljava/lang/Object;[Ljava/lang/Object;)Ljava/lang/Object;
    //   342: astore 30
    //   344: aload 9
    //   346: aload 30
    //   348: checkcast 101	java/lang/String
    //   351: aload 5
    //   353: invokevirtual 176	android/content/Intent:putExtra	(Ljava/lang/String;Ljava/lang/String;)Landroid/content/Intent;
    //   356: pop
    //   357: ldc -78
    //   359: bipush 28
    //   361: iconst_5
    //   362: invokestatic 97	xxxxxx/uxxxxx:bb00620062bb0062b0062b0062	(Ljava/lang/String;CC)Ljava/lang/String;
    //   365: astore 32
    //   367: iconst_3
    //   368: anewarray 99	java/lang/Class
    //   371: astore 33
    //   373: aload 33
    //   375: iconst_0
    //   376: ldc 101
    //   378: aastore
    //   379: aload 33
    //   381: iconst_1
    //   382: getstatic 107	java/lang/Character:TYPE	Ljava/lang/Class;
    //   385: aastore
    //   386: aload 33
    //   388: iconst_2
    //   389: getstatic 107	java/lang/Character:TYPE	Ljava/lang/Class;
    //   392: aastore
    //   393: ldc 109
    //   395: aload 32
    //   397: aload 33
    //   399: invokevirtual 113	java/lang/Class:getMethod	(Ljava/lang/String;[Ljava/lang/Class;)Ljava/lang/reflect/Method;
    //   402: astore 34
    //   404: iconst_3
    //   405: anewarray 115	java/lang/Object
    //   408: astore 35
    //   410: aload 35
    //   412: iconst_0
    //   413: ldc -76
    //   415: aastore
    //   416: aload 35
    //   418: iconst_1
    //   419: sipush 172
    //   422: invokestatic 121	java/lang/Character:valueOf	(C)Ljava/lang/Character;
    //   425: aastore
    //   426: aload 35
    //   428: iconst_2
    //   429: iconst_2
    //   430: invokestatic 121	java/lang/Character:valueOf	(C)Ljava/lang/Character;
    //   433: aastore
    //   434: aload 34
    //   436: aconst_null
    //   437: aload 35
    //   439: invokevirtual 127	java/lang/reflect/Method:invoke	(Ljava/lang/Object;[Ljava/lang/Object;)Ljava/lang/Object;
    //   442: astore 37
    //   444: aload 9
    //   446: aload 37
    //   448: checkcast 101	java/lang/String
    //   451: aload_3
    //   452: invokevirtual 162	android/content/Intent:putExtra	(Ljava/lang/String;Ljava/io/Serializable;)Landroid/content/Intent;
    //   455: pop
    //   456: ldc -74
    //   458: sipush 172
    //   461: bipush 39
    //   463: iconst_1
    //   464: invokestatic 186	xxxxxx/uxxxxx:bbbb0062b0062b0062b0062	(Ljava/lang/String;CCC)Ljava/lang/String;
    //   467: astore 39
    //   469: iconst_3
    //   470: anewarray 99	java/lang/Class
    //   473: astore 40
    //   475: aload 40
    //   477: iconst_0
    //   478: ldc 101
    //   480: aastore
    //   481: aload 40
    //   483: iconst_1
    //   484: getstatic 107	java/lang/Character:TYPE	Ljava/lang/Class;
    //   487: aastore
    //   488: aload 40
    //   490: iconst_2
    //   491: getstatic 107	java/lang/Character:TYPE	Ljava/lang/Class;
    //   494: aastore
    //   495: ldc 109
    //   497: aload 39
    //   499: aload 40
    //   501: invokevirtual 113	java/lang/Class:getMethod	(Ljava/lang/String;[Ljava/lang/Class;)Ljava/lang/reflect/Method;
    //   504: astore 41
    //   506: iconst_3
    //   507: anewarray 115	java/lang/Object
    //   510: astore 42
    //   512: aload 42
    //   514: iconst_0
    //   515: ldc -68
    //   517: aastore
    //   518: aload 42
    //   520: iconst_1
    //   521: sipush 163
    //   524: invokestatic 121	java/lang/Character:valueOf	(C)Ljava/lang/Character;
    //   527: aastore
    //   528: aload 42
    //   530: iconst_2
    //   531: iconst_2
    //   532: invokestatic 121	java/lang/Character:valueOf	(C)Ljava/lang/Character;
    //   535: aastore
    //   536: aload 41
    //   538: aconst_null
    //   539: aload 42
    //   541: invokevirtual 127	java/lang/reflect/Method:invoke	(Ljava/lang/Object;[Ljava/lang/Object;)Ljava/lang/Object;
    //   544: astore 44
    //   546: aload 9
    //   548: aload 44
    //   550: checkcast 101	java/lang/String
    //   553: aload 4
    //   555: invokevirtual 162	android/content/Intent:putExtra	(Ljava/lang/String;Ljava/io/Serializable;)Landroid/content/Intent;
    //   558: pop
    //   559: getstatic 71	com/db/pwcc/dbmobile/transfer/standingorder/confirm/StandingOrderConfirmationActivity:b006Dmm006Dm006Dmm006D	I
    //   562: istore 46
    //   564: iload 46
    //   566: iload 46
    //   568: getstatic 73	com/db/pwcc/dbmobile/transfer/standingorder/confirm/StandingOrderConfirmationActivity:b006D006D006D006Dm006Dmm006D	I
    //   571: iadd
    //   572: imul
    //   573: getstatic 75	com/db/pwcc/dbmobile/transfer/standingorder/confirm/StandingOrderConfirmationActivity:bmm006D006Dm006Dmm006D	I
    //   576: irem
    //   577: tableswitch	default:+19->596, 0:+75->652
    //   596: getstatic 71	com/db/pwcc/dbmobile/transfer/standingorder/confirm/StandingOrderConfirmationActivity:b006Dmm006Dm006Dmm006D	I
    //   599: istore 70
    //   601: iload 70
    //   603: iload 70
    //   605: invokestatic 87	com/db/pwcc/dbmobile/transfer/standingorder/confirm/StandingOrderConfirmationActivity:b006D006Dm006Dm006Dmm006D	()I
    //   608: iadd
    //   609: imul
    //   610: getstatic 75	com/db/pwcc/dbmobile/transfer/standingorder/confirm/StandingOrderConfirmationActivity:bmm006D006Dm006Dmm006D	I
    //   613: irem
    //   614: tableswitch	default:+18->632, 0:+28->642
    //   632: bipush 99
    //   634: putstatic 71	com/db/pwcc/dbmobile/transfer/standingorder/confirm/StandingOrderConfirmationActivity:b006Dmm006Dm006Dmm006D	I
    //   637: bipush 99
    //   639: putstatic 79	com/db/pwcc/dbmobile/transfer/standingorder/confirm/StandingOrderConfirmationActivity:bm006Dm006Dm006Dmm006D	I
    //   642: bipush 51
    //   644: putstatic 71	com/db/pwcc/dbmobile/transfer/standingorder/confirm/StandingOrderConfirmationActivity:b006Dmm006Dm006Dmm006D	I
    //   647: bipush 79
    //   649: putstatic 79	com/db/pwcc/dbmobile/transfer/standingorder/confirm/StandingOrderConfirmationActivity:bm006Dm006Dm006Dmm006D	I
    //   652: aload 6
    //   654: ifnull +123 -> 777
    //   657: ldc -66
    //   659: bipush 87
    //   661: sipush 148
    //   664: iconst_2
    //   665: invokestatic 186	xxxxxx/uxxxxx:bbbb0062b0062b0062b0062	(Ljava/lang/String;CCC)Ljava/lang/String;
    //   668: astore 63
    //   670: iconst_4
    //   671: anewarray 99	java/lang/Class
    //   674: astore 64
    //   676: aload 64
    //   678: iconst_0
    //   679: ldc 101
    //   681: aastore
    //   682: aload 64
    //   684: iconst_1
    //   685: getstatic 107	java/lang/Character:TYPE	Ljava/lang/Class;
    //   688: aastore
    //   689: aload 64
    //   691: iconst_2
    //   692: getstatic 107	java/lang/Character:TYPE	Ljava/lang/Class;
    //   695: aastore
    //   696: aload 64
    //   698: iconst_3
    //   699: getstatic 107	java/lang/Character:TYPE	Ljava/lang/Class;
    //   702: aastore
    //   703: ldc 109
    //   705: aload 63
    //   707: aload 64
    //   709: invokevirtual 113	java/lang/Class:getMethod	(Ljava/lang/String;[Ljava/lang/Class;)Ljava/lang/reflect/Method;
    //   712: astore 65
    //   714: iconst_4
    //   715: anewarray 115	java/lang/Object
    //   718: astore 66
    //   720: aload 66
    //   722: iconst_0
    //   723: ldc -64
    //   725: aastore
    //   726: aload 66
    //   728: iconst_1
    //   729: sipush 128
    //   732: invokestatic 121	java/lang/Character:valueOf	(C)Ljava/lang/Character;
    //   735: aastore
    //   736: aload 66
    //   738: iconst_2
    //   739: sipush 210
    //   742: invokestatic 121	java/lang/Character:valueOf	(C)Ljava/lang/Character;
    //   745: aastore
    //   746: aload 66
    //   748: iconst_3
    //   749: iconst_1
    //   750: invokestatic 121	java/lang/Character:valueOf	(C)Ljava/lang/Character;
    //   753: aastore
    //   754: aload 65
    //   756: aconst_null
    //   757: aload 66
    //   759: invokevirtual 127	java/lang/reflect/Method:invoke	(Ljava/lang/Object;[Ljava/lang/Object;)Ljava/lang/Object;
    //   762: astore 68
    //   764: aload 9
    //   766: aload 68
    //   768: checkcast 101	java/lang/String
    //   771: aload 6
    //   773: invokevirtual 176	android/content/Intent:putExtra	(Ljava/lang/String;Ljava/lang/String;)Landroid/content/Intent;
    //   776: pop
    //   777: aload 7
    //   779: ifnull +174 -> 953
    //   782: ldc -62
    //   784: bipush 38
    //   786: sipush 172
    //   789: iconst_1
    //   790: invokestatic 186	xxxxxx/uxxxxx:bbbb0062b0062b0062b0062	(Ljava/lang/String;CCC)Ljava/lang/String;
    //   793: astore 54
    //   795: iconst_4
    //   796: anewarray 99	java/lang/Class
    //   799: astore 55
    //   801: aload 55
    //   803: iconst_0
    //   804: ldc 101
    //   806: aastore
    //   807: aload 55
    //   809: iconst_1
    //   810: getstatic 107	java/lang/Character:TYPE	Ljava/lang/Class;
    //   813: aastore
    //   814: aload 55
    //   816: iconst_2
    //   817: getstatic 107	java/lang/Character:TYPE	Ljava/lang/Class;
    //   820: aastore
    //   821: aload 55
    //   823: iconst_3
    //   824: getstatic 107	java/lang/Character:TYPE	Ljava/lang/Class;
    //   827: aastore
    //   828: ldc 109
    //   830: aload 54
    //   832: aload 55
    //   834: invokevirtual 113	java/lang/Class:getMethod	(Ljava/lang/String;[Ljava/lang/Class;)Ljava/lang/reflect/Method;
    //   837: astore 56
    //   839: iconst_4
    //   840: anewarray 115	java/lang/Object
    //   843: astore 57
    //   845: aload 57
    //   847: iconst_0
    //   848: ldc -60
    //   850: aastore
    //   851: aload 57
    //   853: iconst_1
    //   854: bipush 83
    //   856: invokestatic 121	java/lang/Character:valueOf	(C)Ljava/lang/Character;
    //   859: aastore
    //   860: aload 57
    //   862: iconst_2
    //   863: sipush 251
    //   866: invokestatic 121	java/lang/Character:valueOf	(C)Ljava/lang/Character;
    //   869: aastore
    //   870: aload 57
    //   872: iconst_3
    //   873: iconst_0
    //   874: invokestatic 121	java/lang/Character:valueOf	(C)Ljava/lang/Character;
    //   877: aastore
    //   878: aload 56
    //   880: aconst_null
    //   881: aload 57
    //   883: invokevirtual 127	java/lang/reflect/Method:invoke	(Ljava/lang/Object;[Ljava/lang/Object;)Ljava/lang/Object;
    //   886: astore 59
    //   888: aload 59
    //   890: checkcast 101	java/lang/String
    //   893: astore 60
    //   895: getstatic 71	com/db/pwcc/dbmobile/transfer/standingorder/confirm/StandingOrderConfirmationActivity:b006Dmm006Dm006Dmm006D	I
    //   898: istore 61
    //   900: iload 61
    //   902: iload 61
    //   904: getstatic 73	com/db/pwcc/dbmobile/transfer/standingorder/confirm/StandingOrderConfirmationActivity:b006D006D006D006Dm006Dmm006D	I
    //   907: iadd
    //   908: imul
    //   909: getstatic 75	com/db/pwcc/dbmobile/transfer/standingorder/confirm/StandingOrderConfirmationActivity:bmm006D006Dm006Dmm006D	I
    //   912: irem
    //   913: tableswitch	default:+19->932, 0:+30->943
    //   932: bipush 12
    //   934: putstatic 71	com/db/pwcc/dbmobile/transfer/standingorder/confirm/StandingOrderConfirmationActivity:b006Dmm006Dm006Dmm006D	I
    //   937: invokestatic 89	com/db/pwcc/dbmobile/transfer/standingorder/confirm/StandingOrderConfirmationActivity:b006Dm006D006Dm006Dmm006D	()I
    //   940: putstatic 79	com/db/pwcc/dbmobile/transfer/standingorder/confirm/StandingOrderConfirmationActivity:bm006Dm006Dm006Dmm006D	I
    //   943: aload 9
    //   945: aload 60
    //   947: aload 7
    //   949: invokevirtual 169	android/content/Intent:putExtra	(Ljava/lang/String;Landroid/os/Parcelable;)Landroid/content/Intent;
    //   952: pop
    //   953: ldc -58
    //   955: sipush 215
    //   958: iconst_1
    //   959: invokestatic 97	xxxxxx/uxxxxx:bb00620062bb0062b0062b0062	(Ljava/lang/String;CC)Ljava/lang/String;
    //   962: astore 47
    //   964: iconst_3
    //   965: anewarray 99	java/lang/Class
    //   968: astore 48
    //   970: aload 48
    //   972: iconst_0
    //   973: ldc 101
    //   975: aastore
    //   976: aload 48
    //   978: iconst_1
    //   979: getstatic 107	java/lang/Character:TYPE	Ljava/lang/Class;
    //   982: aastore
    //   983: aload 48
    //   985: iconst_2
    //   986: getstatic 107	java/lang/Character:TYPE	Ljava/lang/Class;
    //   989: aastore
    //   990: ldc 109
    //   992: aload 47
    //   994: aload 48
    //   996: invokevirtual 113	java/lang/Class:getMethod	(Ljava/lang/String;[Ljava/lang/Class;)Ljava/lang/reflect/Method;
    //   999: astore 49
    //   1001: iconst_3
    //   1002: anewarray 115	java/lang/Object
    //   1005: astore 50
    //   1007: aload 50
    //   1009: iconst_0
    //   1010: ldc -56
    //   1012: aastore
    //   1013: aload 50
    //   1015: iconst_1
    //   1016: sipush 166
    //   1019: invokestatic 121	java/lang/Character:valueOf	(C)Ljava/lang/Character;
    //   1022: aastore
    //   1023: aload 50
    //   1025: iconst_2
    //   1026: iconst_2
    //   1027: invokestatic 121	java/lang/Character:valueOf	(C)Ljava/lang/Character;
    //   1030: aastore
    //   1031: aload 49
    //   1033: aconst_null
    //   1034: aload 50
    //   1036: invokevirtual 127	java/lang/reflect/Method:invoke	(Ljava/lang/Object;[Ljava/lang/Object;)Ljava/lang/Object;
    //   1039: astore 52
    //   1041: aload 9
    //   1043: aload 52
    //   1045: checkcast 101	java/lang/String
    //   1048: aload 8
    //   1050: invokevirtual 176	android/content/Intent:putExtra	(Ljava/lang/String;Ljava/lang/String;)Landroid/content/Intent;
    //   1053: pop
    //   1054: aload 9
    //   1056: areturn
    //   1057: astore 14
    //   1059: aload 14
    //   1061: invokevirtual 135	java/lang/reflect/InvocationTargetException:getCause	()Ljava/lang/Throwable;
    //   1064: athrow
    //   1065: astore 29
    //   1067: aload 29
    //   1069: invokevirtual 135	java/lang/reflect/InvocationTargetException:getCause	()Ljava/lang/Throwable;
    //   1072: athrow
    //   1073: astore 51
    //   1075: aload 51
    //   1077: invokevirtual 135	java/lang/reflect/InvocationTargetException:getCause	()Ljava/lang/Throwable;
    //   1080: athrow
    //   1081: astore 43
    //   1083: aload 43
    //   1085: invokevirtual 135	java/lang/reflect/InvocationTargetException:getCause	()Ljava/lang/Throwable;
    //   1088: athrow
    //   1089: astore 67
    //   1091: aload 67
    //   1093: invokevirtual 135	java/lang/reflect/InvocationTargetException:getCause	()Ljava/lang/Throwable;
    //   1096: athrow
    //   1097: astore 58
    //   1099: aload 58
    //   1101: invokevirtual 135	java/lang/reflect/InvocationTargetException:getCause	()Ljava/lang/Throwable;
    //   1104: athrow
    //   1105: astore 36
    //   1107: aload 36
    //   1109: invokevirtual 135	java/lang/reflect/InvocationTargetException:getCause	()Ljava/lang/Throwable;
    //   1112: athrow
    //   1113: astore 22
    //   1115: aload 22
    //   1117: invokevirtual 135	java/lang/reflect/InvocationTargetException:getCause	()Ljava/lang/Throwable;
    //   1120: athrow
    // Local variable table:
    //   start	length	slot	name	signature
    //   0	1121	0	paramContext	Context
    //   0	1121	1	paramStandingOrderRequestResponse	StandingOrderRequestResponse
    //   0	1121	2	paramChallengeResponse	ChallengeResponse
    //   0	1121	3	paramAuthorization	Authorization
    //   0	1121	4	paramAuthorizationStatus	AuthorizationStatus
    //   0	1121	5	paramString1	String
    //   0	1121	6	paramString2	String
    //   0	1121	7	paramStandingOrderTemplate	StandingOrderTemplate
    //   0	1121	8	paramString3	String
    //   10	1045	9	localIntent	Intent
    //   20	31	10	str1	String
    //   26	27	11	arrayOfClass1	Class[]
    //   57	33	12	localMethod1	Method
    //   63	30	13	arrayOfObject1	Object[]
    //   1057	3	14	localInvocationTargetException1	InvocationTargetException
    //   97	5	15	localObject1	Object
    //   114	11	17	i	int
    //   167	31	18	str2	String
    //   173	27	19	arrayOfClass2	Class[]
    //   204	33	20	localMethod2	Method
    //   210	30	21	arrayOfObject2	Object[]
    //   1113	3	22	localInvocationTargetException2	InvocationTargetException
    //   244	5	23	localObject2	Object
    //   266	31	25	str3	String
    //   272	27	26	arrayOfClass3	Class[]
    //   303	32	27	localMethod3	Method
    //   309	29	28	arrayOfObject3	Object[]
    //   1065	3	29	localInvocationTargetException3	InvocationTargetException
    //   342	5	30	localObject3	Object
    //   365	31	32	str4	String
    //   371	27	33	arrayOfClass4	Class[]
    //   402	33	34	localMethod4	Method
    //   408	30	35	arrayOfObject4	Object[]
    //   1105	3	36	localInvocationTargetException4	InvocationTargetException
    //   442	5	37	localObject4	Object
    //   467	31	39	str5	String
    //   473	27	40	arrayOfClass5	Class[]
    //   504	33	41	localMethod5	Method
    //   510	30	42	arrayOfObject5	Object[]
    //   1081	3	43	localInvocationTargetException5	InvocationTargetException
    //   544	5	44	localObject5	Object
    //   562	11	46	j	int
    //   962	31	47	str6	String
    //   968	27	48	arrayOfClass6	Class[]
    //   999	33	49	localMethod6	Method
    //   1005	30	50	arrayOfObject6	Object[]
    //   1073	3	51	localInvocationTargetException6	InvocationTargetException
    //   1039	5	52	localObject6	Object
    //   793	38	54	str7	String
    //   799	34	55	arrayOfClass7	Class[]
    //   837	42	56	localMethod7	Method
    //   843	39	57	arrayOfObject7	Object[]
    //   1097	3	58	localInvocationTargetException7	InvocationTargetException
    //   886	3	59	localObject7	Object
    //   893	53	60	str8	String
    //   898	11	61	k	int
    //   668	38	63	str9	String
    //   674	34	64	arrayOfClass8	Class[]
    //   712	43	65	localMethod8	Method
    //   718	40	66	arrayOfObject8	Object[]
    //   1089	3	67	localInvocationTargetException8	InvocationTargetException
    //   762	5	68	localObject8	Object
    //   599	11	70	m	int
    // Exception table:
    //   from	to	target	type
    //   89	99	1057	java/lang/reflect/InvocationTargetException
    //   334	344	1065	java/lang/reflect/InvocationTargetException
    //   1031	1041	1073	java/lang/reflect/InvocationTargetException
    //   536	546	1081	java/lang/reflect/InvocationTargetException
    //   754	764	1089	java/lang/reflect/InvocationTargetException
    //   878	888	1097	java/lang/reflect/InvocationTargetException
    //   434	444	1105	java/lang/reflect/InvocationTargetException
    //   236	246	1113	java/lang/reflect/InvocationTargetException
  }
  
  private void navigateToActivity(Class<?> paramClass)
  {
    if ((b006Dmm006Dm006Dmm006D + b006D006D006D006Dm006Dmm006D) * b006Dmm006Dm006Dmm006D % bmm006D006Dm006Dmm006D != bm006Dm006Dm006Dmm006D)
    {
      int j = (b006Dm006D006Dm006Dmm006D() + b006D006D006D006Dm006Dmm006D) * b006Dm006D006Dm006Dmm006D();
      int k = b006Dmm006Dm006Dmm006D;
      switch (k * (k + b006D006D006D006Dm006Dmm006D) % bmm006D006Dm006Dmm006D)
      {
      default: 
        b006Dmm006Dm006Dmm006D = b006Dm006D006Dm006Dmm006D();
        bm006Dm006Dm006Dmm006D = 35;
      }
      if (j % bmm006D006Dm006Dmm006D != bm006Dm006Dm006Dmm006D)
      {
        b006Dmm006Dm006Dmm006D = b006Dm006D006Dm006Dmm006D();
        bm006Dm006Dm006Dmm006D = b006Dm006D006Dm006Dmm006D();
      }
      b006Dmm006Dm006Dmm006D = b006Dm006D006Dm006Dmm006D();
      bm006Dm006Dm006Dmm006D = b006Dm006D006Dm006Dmm006D();
    }
    Intent localIntent = new Intent(this, paramClass);
    localIntent.addFlags(872415232);
    int i = b006Dmm006Dm006Dmm006D;
    switch (i * (i + b006D006Dm006Dm006Dmm006D()) % bmm006D006Dm006Dmm006D)
    {
    default: 
      b006Dmm006Dm006Dmm006D = 24;
      bm006Dm006Dm006Dmm006D = b006Dm006D006Dm006Dmm006D();
    }
    startActivity(localIntent);
    finish();
  }
  
  private Date parseTemplateDateString(String paramString)
  {
    String str = uxxxxx.bb00620062bb0062b0062b0062("g}~\001:;CD>?GH\nCDLMGHPQ\023", '«', '\000');
    Class[] arrayOfClass = new Class[3];
    arrayOfClass[0] = String.class;
    arrayOfClass[1] = Character.TYPE;
    arrayOfClass[2] = Character.TYPE;
    Method localMethod = ppphhp.class.getMethod(str, arrayOfClass);
    Object[] arrayOfObject = new Object[3];
    arrayOfObject[0] = "mnop%FG(`a";
    arrayOfObject[1] = Character.valueOf('s');
    arrayOfObject[2] = Character.valueOf('\002');
    try
    {
      Object localObject = localMethod.invoke(null, arrayOfObject);
      SimpleDateFormat localSimpleDateFormat = new SimpleDateFormat((String)localObject, Locale.getDefault());
      try
      {
        Date localDate2 = localSimpleDateFormat.parse(paramString);
        localDate1 = localDate2;
      }
      catch (ParseException localParseException)
      {
        for (;;)
        {
          int i;
          Date localDate1 = null;
        }
      }
      i = b006Dmm006Dm006Dmm006D;
      if ((b006Dmm006Dm006Dmm006D + b006D006D006D006Dm006Dmm006D) * b006Dmm006Dm006Dmm006D % bmm006D006Dm006Dmm006D != bm006D006D006Dm006Dmm006D())
      {
        b006Dmm006Dm006Dmm006D = 88;
        bm006Dm006Dm006Dmm006D = 98;
      }
      switch (i * (i + b006D006D006D006Dm006Dmm006D) % bmm006D006Dm006Dmm006D)
      {
      default: 
        b006Dmm006Dm006Dmm006D = b006Dm006D006Dm006Dmm006D();
        if ((b006Dmm006Dm006Dmm006D + b006D006Dm006Dm006Dmm006D()) * b006Dmm006Dm006Dmm006D % bmm006D006Dm006Dmm006D != bm006Dm006Dm006Dmm006D)
        {
          b006Dmm006Dm006Dmm006D = b006Dm006D006Dm006Dmm006D();
          bm006Dm006Dm006Dmm006D = b006Dm006D006Dm006Dmm006D();
        }
        bm006Dm006Dm006Dmm006D = 46;
        int j = b006Dmm006Dm006Dmm006D;
        switch (j * (j + b006D006D006D006Dm006Dmm006D) % bmm006D006Dm006Dmm006D)
        {
        default: 
          b006Dmm006Dm006Dmm006D = 18;
          bm006Dm006Dm006Dmm006D = b006Dm006D006Dm006Dmm006D();
        }
        break;
      }
      return localDate1;
    }
    catch (InvocationTargetException localInvocationTargetException)
    {
      throw localInvocationTargetException.getCause();
    }
  }
  
  private void setFormattedFrequencyText(TextView paramTextView, int paramInt, String paramString)
  {
    int i;
    label91:
    Method localMethod9;
    Object[] arrayOfObject10;
    switch (paramString.hashCode())
    {
    default: 
      i = -1;
      switch (i)
      {
      default: 
        return;
      }
    case 1720567065: 
      String str11 = uxxxxx.bb00620062bb0062b0062b0062("\024('&%\\[a`XW]\\\034SRXWONTS\023", '\032', '\005');
      Class[] arrayOfClass9 = new Class[3];
      arrayOfClass9[0] = String.class;
      arrayOfClass9[1] = Character.TYPE;
      arrayOfClass9[2] = Character.TYPE;
      localMethod9 = ppphhp.class.getMethod(str11, arrayOfClass9);
      arrayOfObject10 = new Object[3];
      arrayOfObject10[0] = "\003\006p\001\002q}v\003";
      arrayOfObject10[1] = Character.valueOf('Í');
      arrayOfObject10[2] = Character.valueOf('\003');
    }
    for (;;)
    {
      try
      {
        Object localObject9 = localMethod9.invoke(null, arrayOfObject10);
        if (!paramString.equals((String)localObject9)) {
          break;
        }
        i = 6;
        break label91;
        String str10 = uxxxxx.bb00620062bb0062b0062b0062("4H~\005\004CByx~}utzy9poutlkqp0", '\027', '\004');
        Class[] arrayOfClass8 = new Class[4];
        arrayOfClass8[0] = String.class;
        arrayOfClass8[1] = Character.TYPE;
        arrayOfClass8[2] = Character.TYPE;
        arrayOfClass8[3] = Character.TYPE;
        Method localMethod8 = ppphhp.class.getMethod(str10, arrayOfClass8);
        Object[] arrayOfObject9 = new Object[4];
        arrayOfObject9[0] = "\b\004\013\r\031";
        arrayOfObject9[1] = Character.valueOf('r');
        arrayOfObject9[2] = Character.valueOf('È');
        arrayOfObject9[3] = Character.valueOf('\000');
        try
        {
          Object localObject8 = localMethod8.invoke(null, arrayOfObject9);
          if (!paramString.equals((String)localObject8)) {
            break;
          }
          i = 0;
        }
        catch (InvocationTargetException localInvocationTargetException8)
        {
          int m;
          String str9;
          Class[] arrayOfClass7;
          Method localMethod7;
          Object[] arrayOfObject8;
          throw localInvocationTargetException8.getCause();
        }
        m = b006Dmm006Dm006Dmm006D;
        switch (m * (m + b006D006D006D006Dm006Dmm006D) % bmm006D006Dm006Dmm006D)
        {
        default: 
          b006Dmm006Dm006Dmm006D = 82;
          bm006Dm006Dm006Dmm006D = b006Dm006D006Dm006Dmm006D();
        }
        str9 = uxxxxx.bb00620062bb0062b0062b0062("0DCBAxw}|tsyx8ontskjpo/", '2', '\003');
        arrayOfClass7 = new Class[3];
        arrayOfClass7[0] = String.class;
        arrayOfClass7[1] = Character.TYPE;
        arrayOfClass7[2] = Character.TYPE;
        localMethod7 = ppphhp.class.getMethod(str9, arrayOfClass7);
        arrayOfObject8 = new Object[3];
        arrayOfObject8[0] = "~\002\002\t\002\020\027\020\003\017\004\f\023\023\037\013\003\021\031\006\030 '\n\030\017+\027#\033)";
        arrayOfObject8[1] = Character.valueOf('X');
        arrayOfObject8[2] = Character.valueOf('\001');
        try
        {
          Object localObject7 = localMethod7.invoke(null, arrayOfObject8);
          if (!paramString.equals((String)localObject7)) {
            break;
          }
          i = 3;
        }
        catch (InvocationTargetException localInvocationTargetException7)
        {
          int k;
          StringBuilder localStringBuilder1;
          String str2;
          Object[] arrayOfObject2;
          StringBuilder localStringBuilder2;
          String str3;
          String str8;
          Class[] arrayOfClass6;
          Method localMethod6;
          Object[] arrayOfObject7;
          String str7;
          Class[] arrayOfClass5;
          Method localMethod5;
          Object[] arrayOfObject6;
          String str6;
          Class[] arrayOfClass4;
          Method localMethod4;
          Object[] arrayOfObject5;
          throw localInvocationTargetException7.getCause();
        }
        paramTextView.setText(getString(R.string.standing_order_frequency_weekly));
        k = b006Dmm006Dm006Dmm006D;
        switch (k * (k + b006D006D006D006Dm006Dmm006D) % bmm006D006Dm006Dmm006D)
        {
        }
        b006Dmm006Dm006Dmm006D = b006Dm006D006Dm006Dmm006D();
        bm006Dm006Dm006Dmm006D = 58;
        return;
        j = R.string.standing_order_frequency_bimonthly_formatted;
        localStringBuilder1 = new StringBuilder();
        str2 = getString(j);
        arrayOfObject2 = new Object[1];
        arrayOfObject2[0] = Integer.valueOf(paramInt);
        localStringBuilder2 = localStringBuilder1.append(String.format(str2, arrayOfObject2));
        str3 = pqpppq.bkk006Bk006B006Bkkkk(Locale.getDefault(), paramInt);
        if ((b006Dmm006Dm006Dmm006D + b006D006D006D006Dm006Dmm006D) * b006Dmm006Dm006Dmm006D % bmm006D006Dm006Dmm006D != bm006D006D006Dm006Dmm006D())
        {
          b006Dmm006Dm006Dmm006D = 21;
          bm006Dm006Dm006Dmm006D = b006Dm006D006Dm006Dmm006D();
        }
        paramTextView.setText(Html.fromHtml(str3));
        return;
        str8 = uxxxxx.bbbb0062b0062b0062b0062("\026,efno12kltuopxy;tu}~xy\002\003D", 'À', '', '\002');
        arrayOfClass6 = new Class[4];
        arrayOfClass6[0] = String.class;
        arrayOfClass6[1] = Character.TYPE;
        arrayOfClass6[2] = Character.TYPE;
        arrayOfClass6[3] = Character.TYPE;
        localMethod6 = ppphhp.class.getMethod(str8, arrayOfClass6);
        arrayOfObject7 = new Object[4];
        arrayOfObject7[0] = "knnujo}";
        arrayOfObject7[1] = Character.valueOf('p');
        arrayOfObject7[2] = Character.valueOf('R');
        arrayOfObject7[3] = Character.valueOf('\002');
        try
        {
          Object localObject6 = localMethod6.invoke(null, arrayOfObject7);
          if (!paramString.equals((String)localObject6)) {
            break;
          }
          i = 2;
        }
        catch (InvocationTargetException localInvocationTargetException6)
        {
          throw localInvocationTargetException6.getCause();
        }
        str7 = uxxxxx.bb00620062bb0062b0062b0062("Wmnop*+34./78y34<=78@A\003", 'Ð', '\000');
        arrayOfClass5 = new Class[3];
        arrayOfClass5[0] = String.class;
        arrayOfClass5[1] = Character.TYPE;
        arrayOfClass5[2] = Character.TYPE;
        localMethod5 = ppphhp.class.getMethod(str7, arrayOfClass5);
        arrayOfObject6 = new Object[3];
        arrayOfObject6[0] = "$\023\024\033\035+";
        arrayOfObject6[1] = Character.valueOf('&');
        arrayOfObject6[2] = Character.valueOf('\001');
        try
        {
          Object localObject5 = localMethod5.invoke(null, arrayOfObject6);
          if (!paramString.equals((String)localObject5)) {
            break;
          }
          i = 1;
        }
        catch (InvocationTargetException localInvocationTargetException5)
        {
          throw localInvocationTargetException5.getCause();
        }
        str6 = uxxxxx.bb00620062bb0062b0062b0062("\0340gflk+*a`fe]\\ba!XW]\\TSYX\030", '#', '\004');
        arrayOfClass4 = new Class[4];
        arrayOfClass4[0] = String.class;
        arrayOfClass4[1] = Character.TYPE;
        arrayOfClass4[2] = Character.TYPE;
        arrayOfClass4[3] = Character.TYPE;
        localMethod4 = ppphhp.class.getMethod(str6, arrayOfClass4);
        arrayOfObject5 = new Object[4];
        arrayOfObject5[0] = "\027\n\023\f\033\035\017\035";
        arrayOfObject5[1] = Character.valueOf('^');
        arrayOfObject5[2] = Character.valueOf('\033');
        arrayOfObject5[3] = Character.valueOf('\002');
        try
        {
          Object localObject4 = localMethod4.invoke(null, arrayOfObject5);
          if (!paramString.equals((String)localObject4)) {
            break;
          }
          i = 7;
        }
        catch (InvocationTargetException localInvocationTargetException4)
        {
          String str5;
          Class[] arrayOfClass3;
          Method localMethod3;
          Object[] arrayOfObject4;
          String str4;
          Class[] arrayOfClass2;
          Method localMethod2;
          Object[] arrayOfObject3;
          throw localInvocationTargetException4.getCause();
        }
        paramTextView.setText(R.string.standing_order_frequency_daily);
        return;
        str5 = uxxxxx.bbbb0062b0062b0062b0062("]qpon&%+*\"!'&e\035\034\"!\031\030\036\035\\", 'n', '\026', '\000');
        arrayOfClass3 = new Class[3];
        arrayOfClass3[0] = String.class;
        arrayOfClass3[1] = Character.TYPE;
        arrayOfClass3[2] = Character.TYPE;
        localMethod3 = ppphhp.class.getMethod(str5, arrayOfClass3);
        arrayOfObject4 = new Object[3];
        arrayOfObject4[0] = "\025\033\036\037\035\"\025\030$";
        arrayOfObject4[1] = Character.valueOf('¬');
        arrayOfObject4[2] = Character.valueOf('\003');
        try
        {
          Object localObject3 = localMethod3.invoke(null, arrayOfObject4);
          if (!paramString.equals((String)localObject3)) {
            break;
          }
          i = 5;
        }
        catch (InvocationTargetException localInvocationTargetException3)
        {
          throw localInvocationTargetException3.getCause();
        }
        j = R.string.standing_order_frequency_monthly_without_jan_jul_formatted;
        continue;
        if ((b006Dmm006Dm006Dmm006D + b006D006D006D006Dm006Dmm006D) * b006Dmm006Dm006Dmm006D % bmm006D006Dm006Dmm006D != bm006D006D006Dm006Dmm006D())
        {
          b006Dmm006Dm006Dmm006D = 77;
          bm006Dm006Dm006Dmm006D = 94;
        }
        str4 = uxxxxx.bb00620062bb0062b0062b0062("h~89AB\004\005>?GHBCKL\016GHPQKLTU\027", '', '\000');
        arrayOfClass2 = new Class[4];
        arrayOfClass2[0] = String.class;
        arrayOfClass2[1] = Character.TYPE;
        arrayOfClass2[2] = Character.TYPE;
        arrayOfClass2[3] = Character.TYPE;
        localMethod2 = ppphhp.class.getMethod(str4, arrayOfClass2);
        arrayOfObject3 = new Object[4];
        arrayOfObject3[0] = "#12:'3";
        arrayOfObject3[1] = Character.valueOf('\033');
        arrayOfObject3[2] = Character.valueOf('¸');
        arrayOfObject3[3] = Character.valueOf('\002');
        try
        {
          Object localObject2 = localMethod2.invoke(null, arrayOfObject3);
          if (!paramString.equals((String)localObject2)) {
            break;
          }
          i = 8;
        }
        catch (InvocationTargetException localInvocationTargetException2)
        {
          String str1;
          Class[] arrayOfClass1;
          Method localMethod1;
          Object[] arrayOfObject1;
          Object localObject1;
          throw localInvocationTargetException2.getCause();
        }
        j = R.string.standing_order_frequency_monthly_formatted;
        continue;
        str1 = uxxxxx.bb00620062bb0062b0062b0062("Kabcd\036\037'(\"#+,m'(01+,45v", 'h', '\002');
        arrayOfClass1 = new Class[3];
        arrayOfClass1[0] = String.class;
        arrayOfClass1[1] = Character.TYPE;
        arrayOfClass1[2] = Character.TYPE;
        localMethod1 = ppphhp.class.getMethod(str1, arrayOfClass1);
        arrayOfObject1 = new Object[3];
        arrayOfObject1[0] = "x{{\003w|\013\022\013}\n~\007\016\016\032\006}\f\024\001\023\033\"\005\023\n&\022\036\026$";
        arrayOfObject1[1] = Character.valueOf('U');
        arrayOfObject1[2] = Character.valueOf('\001');
      }
      catch (InvocationTargetException localInvocationTargetException9)
      {
        try
        {
          localObject1 = localMethod1.invoke(null, arrayOfObject1);
          if (!paramString.equals((String)localObject1)) {
            break;
          }
          i = 4;
        }
        catch (InvocationTargetException localInvocationTargetException1)
        {
          throw localInvocationTargetException1.getCause();
        }
        localInvocationTargetException9 = localInvocationTargetException9;
        throw localInvocationTargetException9.getCause();
      }
      int j = R.string.standing_order_frequency_quarterly_formatted;
      continue;
      j = R.string.standing_order_frequency_half_year_formatted;
      continue;
      j = R.string.standing_order_frequency_yearly_formatted;
    }
  }
  
  private void setFormattedFrequencyText(TextView paramTextView, StandingOrderTemplate paramStandingOrderTemplate)
  {
    String str1 = paramStandingOrderTemplate.getExecutionOn();
    String str2 = uxxxxx.bbbb0062b0062b0062b0062("\001\027\030\031\032ST\\]WX`a#\\]ef`aij,", 'p', 'R', '\002');
    Class[] arrayOfClass = new Class[3];
    arrayOfClass[0] = String.class;
    arrayOfClass[1] = Character.TYPE;
    arrayOfClass[2] = Character.TYPE;
    Method localMethod = ppphhp.class.getMethod(str2, arrayOfClass);
    Object[] arrayOfObject = new Object[3];
    arrayOfObject[0] = "`";
    arrayOfObject[1] = Character.valueOf('@');
    arrayOfObject[2] = Character.valueOf('\001');
    try
    {
      Object localObject = localMethod.invoke(null, arrayOfObject);
      String str3 = str1.replace((String)localObject, "").trim();
      int i = (b006Dmm006Dm006Dmm006D + b006D006D006D006Dm006Dmm006D) * b006Dmm006Dm006Dmm006D % bmmmm006D006Dmm006D();
      int j = bm006Dm006Dm006Dmm006D;
      int k = b006Dmm006Dm006Dmm006D;
      switch (k * (k + b006D006D006D006Dm006Dmm006D) % bmm006D006Dm006Dmm006D)
      {
      default: 
        b006Dmm006Dm006Dmm006D = 46;
        bm006Dm006Dm006Dmm006D = b006Dm006D006Dm006Dmm006D();
      }
      if (i != j)
      {
        b006Dmm006Dm006Dmm006D = 41;
        bm006Dm006Dm006Dmm006D = 56;
        if ((b006Dmm006Dm006Dmm006D + b006D006D006D006Dm006Dmm006D) * b006Dmm006Dm006Dmm006D % bmm006D006Dm006Dmm006D != bm006Dm006Dm006Dmm006D)
        {
          int m = b006Dmm006Dm006Dmm006D;
          switch (m * (m + b006D006D006D006Dm006Dmm006D) % bmm006D006Dm006Dmm006D)
          {
          default: 
            b006Dmm006Dm006Dmm006D = 40;
            bm006Dm006Dm006Dmm006D = 8;
          }
          b006Dmm006Dm006Dmm006D = b006Dm006D006Dm006Dmm006D();
          bm006Dm006Dm006Dmm006D = 8;
        }
      }
      setFormattedFrequencyText(paramTextView, Integer.parseInt(str3), paramStandingOrderTemplate.getFrequency());
      return;
    }
    catch (InvocationTargetException localInvocationTargetException)
    {
      throw localInvocationTargetException.getCause();
    }
  }
  
  private void setFormattedFrequencyText(TextView paramTextView, StandingOrderTransaction paramStandingOrderTransaction)
  {
    int i = b006Dmm006Dm006Dmm006D;
    switch (i * (i + b006D006D006D006Dm006Dmm006D) % bmm006D006Dm006Dmm006D)
    {
    default: 
      b006Dmm006Dm006Dmm006D = 51;
      bm006Dm006Dm006Dmm006D = b006Dm006D006Dm006Dmm006D();
      int k = b006Dmm006Dm006Dmm006D;
      switch (k * (k + b006D006D006D006Dm006Dmm006D) % bmm006D006Dm006Dmm006D)
      {
      default: 
        b006Dmm006Dm006Dmm006D = b006Dm006D006Dm006Dmm006D();
        bm006Dm006Dm006Dmm006D = b006Dm006D006Dm006Dmm006D();
      }
      break;
    }
    String str1 = paramStandingOrderTransaction.getExecutionOn();
    String str2 = uxxxxx.bb00620062bb0062b0062b0062("\024(_^dc#\"YX^]UTZY\031POUTLKQP\020", 'Í', '\003');
    Class[] arrayOfClass = new Class[4];
    arrayOfClass[0] = String.class;
    arrayOfClass[1] = Character.TYPE;
    arrayOfClass[2] = Character.TYPE;
    arrayOfClass[3] = Character.TYPE;
    Method localMethod = ppphhp.class.getMethod(str2, arrayOfClass);
    Object[] arrayOfObject = new Object[4];
    arrayOfObject[0] = "U";
    arrayOfObject[1] = Character.valueOf('»');
    arrayOfObject[2] = Character.valueOf('F');
    arrayOfObject[3] = Character.valueOf('\002');
    try
    {
      Object localObject = localMethod.invoke(null, arrayOfObject);
      String str3 = (String)localObject;
      if ((b006Dmm006Dm006Dmm006D + b006D006D006D006Dm006Dmm006D) * b006Dmm006Dm006Dmm006D % bmm006D006Dm006Dmm006D != bm006Dm006Dm006Dmm006D)
      {
        b006Dmm006Dm006Dmm006D = 77;
        bm006Dm006Dm006Dmm006D = b006Dm006D006Dm006Dmm006D();
      }
      int j = Integer.parseInt(str1.replace(str3, "").trim());
      String str4 = paramStandingOrderTransaction.getFrequency();
      if ((b006Dmm006Dm006Dmm006D + b006D006Dm006Dm006Dmm006D()) * b006Dmm006Dm006Dmm006D % bmmmm006D006Dmm006D() != bm006Dm006Dm006Dmm006D)
      {
        b006Dmm006Dm006Dmm006D = b006Dm006D006Dm006Dmm006D();
        bm006Dm006Dm006Dmm006D = b006Dm006D006Dm006Dmm006D();
      }
      setFormattedFrequencyText(paramTextView, j, str4);
      return;
    }
    catch (InvocationTargetException localInvocationTargetException)
    {
      throw localInvocationTargetException.getCause();
    }
  }
  
  private void setValidUntilText(TextView paramTextView, StandingOrderTemplate paramStandingOrderTemplate)
  {
    String str1 = paramStandingOrderTemplate.getValidUntil();
    int i = b006Dmm006Dm006Dmm006D;
    int j = i * (i + b006D006D006D006Dm006Dmm006D) % bmm006D006Dm006Dmm006D;
    if ((b006Dmm006Dm006Dmm006D + b006D006D006D006Dm006Dmm006D) * b006Dmm006Dm006Dmm006D % bmm006D006Dm006Dmm006D != bm006Dm006Dm006Dmm006D)
    {
      b006Dmm006Dm006Dmm006D = 24;
      bm006Dm006Dm006Dmm006D = b006Dm006D006Dm006Dmm006D();
    }
    switch (j)
    {
    default: 
      b006Dmm006Dm006Dmm006D = b006Dm006D006Dm006Dmm006D();
      bm006Dm006Dm006Dmm006D = b006Dm006D006Dm006Dmm006D();
    }
    String str2 = uxxxxx.bb00620062bb0062b0062b0062("9MLKJ\002\001\007\006}|\003\002Axw}|tsyx8", 'T', '\004');
    Class[] arrayOfClass = new Class[3];
    arrayOfClass[0] = String.class;
    arrayOfClass[1] = Character.TYPE;
    arrayOfClass[2] = Character.TYPE;
    Method localMethod = ppphhp.class.getMethod(str2, arrayOfClass);
    Object[] arrayOfObject = new Object[3];
    arrayOfObject[0] = "\006\007\b\t=^_";
    arrayOfObject[1] = Character.valueOf('\004');
    arrayOfObject[2] = Character.valueOf('\000');
    try
    {
      Object localObject = localMethod.invoke(null, arrayOfObject);
      String str3 = (String)localObject;
      Locale localLocale = Locale.getDefault();
      if ((b006Dmm006Dm006Dmm006D + b006D006D006D006Dm006Dmm006D) * b006Dmm006Dm006Dmm006D % bmm006D006Dm006Dmm006D != bm006Dm006Dm006Dmm006D)
      {
        b006Dmm006Dm006Dmm006D = b006Dm006D006Dm006Dmm006D();
        bm006Dm006Dm006Dmm006D = b006Dm006D006Dm006Dmm006D();
      }
      Date localDate = new SimpleDateFormat(str3, localLocale).parse(str1);
      Calendar localCalendar = Calendar.getInstance();
      localCalendar.set(1, 9000);
      if (localDate.after(localCalendar.getTime()))
      {
        paramTextView.setText(R.string.standing_order_valid_unlimited);
        return;
      }
      if ((b006Dmm006Dm006Dmm006D + b006D006D006D006Dm006Dmm006D) * b006Dmm006Dm006Dmm006D % bmm006D006Dm006Dmm006D != bm006Dm006Dm006Dmm006D)
      {
        b006Dmm006Dm006Dmm006D = 17;
        bm006Dm006Dm006Dmm006D = b006Dm006D006Dm006Dmm006D();
      }
      paramTextView.setText(pqpppq.b006Bkkk006B006Bkkkk(Locale.getDefault(), localDate));
      return;
    }
    catch (InvocationTargetException localInvocationTargetException)
    {
      throw localInvocationTargetException.getCause();
    }
    catch (ParseException localParseException) {}
  }
  
  /* Error */
  public void closeActivity()
  {
    // Byte code:
    //   0: aload_0
    //   1: invokevirtual 424	com/db/pwcc/dbmobile/transfer/standingorder/confirm/StandingOrderConfirmationActivity:getIntent	()Landroid/content/Intent;
    //   4: astore_1
    //   5: getstatic 71	com/db/pwcc/dbmobile/transfer/standingorder/confirm/StandingOrderConfirmationActivity:b006Dmm006Dm006Dmm006D	I
    //   8: istore_2
    //   9: iload_2
    //   10: iload_2
    //   11: invokestatic 87	com/db/pwcc/dbmobile/transfer/standingorder/confirm/StandingOrderConfirmationActivity:b006D006Dm006Dm006Dmm006D	()I
    //   14: iadd
    //   15: imul
    //   16: getstatic 75	com/db/pwcc/dbmobile/transfer/standingorder/confirm/StandingOrderConfirmationActivity:bmm006D006Dm006Dmm006D	I
    //   19: irem
    //   20: tableswitch	default:+20->40, 0:+66->86
    //   40: invokestatic 89	com/db/pwcc/dbmobile/transfer/standingorder/confirm/StandingOrderConfirmationActivity:b006Dm006D006Dm006Dmm006D	()I
    //   43: istore 16
    //   45: invokestatic 89	com/db/pwcc/dbmobile/transfer/standingorder/confirm/StandingOrderConfirmationActivity:b006Dm006D006Dm006Dmm006D	()I
    //   48: getstatic 73	com/db/pwcc/dbmobile/transfer/standingorder/confirm/StandingOrderConfirmationActivity:b006D006D006D006Dm006Dmm006D	I
    //   51: iadd
    //   52: invokestatic 89	com/db/pwcc/dbmobile/transfer/standingorder/confirm/StandingOrderConfirmationActivity:b006Dm006D006Dm006Dmm006D	()I
    //   55: imul
    //   56: getstatic 75	com/db/pwcc/dbmobile/transfer/standingorder/confirm/StandingOrderConfirmationActivity:bmm006D006Dm006Dmm006D	I
    //   59: irem
    //   60: getstatic 79	com/db/pwcc/dbmobile/transfer/standingorder/confirm/StandingOrderConfirmationActivity:bm006Dm006Dm006Dmm006D	I
    //   63: if_icmpeq +12 -> 75
    //   66: bipush 27
    //   68: putstatic 71	com/db/pwcc/dbmobile/transfer/standingorder/confirm/StandingOrderConfirmationActivity:b006Dmm006Dm006Dmm006D	I
    //   71: iconst_0
    //   72: putstatic 79	com/db/pwcc/dbmobile/transfer/standingorder/confirm/StandingOrderConfirmationActivity:bm006Dm006Dm006Dmm006D	I
    //   75: iload 16
    //   77: putstatic 71	com/db/pwcc/dbmobile/transfer/standingorder/confirm/StandingOrderConfirmationActivity:b006Dmm006Dm006Dmm006D	I
    //   80: invokestatic 89	com/db/pwcc/dbmobile/transfer/standingorder/confirm/StandingOrderConfirmationActivity:b006Dm006D006Dm006Dmm006D	()I
    //   83: putstatic 79	com/db/pwcc/dbmobile/transfer/standingorder/confirm/StandingOrderConfirmationActivity:bm006Dm006Dm006Dmm006D	I
    //   86: ldc_w 426
    //   89: sipush 175
    //   92: sipush 250
    //   95: iconst_1
    //   96: invokestatic 186	xxxxxx/uxxxxx:bbbb0062b0062b0062b0062	(Ljava/lang/String;CCC)Ljava/lang/String;
    //   99: astore_3
    //   100: iconst_4
    //   101: anewarray 99	java/lang/Class
    //   104: astore 4
    //   106: aload 4
    //   108: iconst_0
    //   109: ldc 101
    //   111: aastore
    //   112: aload 4
    //   114: iconst_1
    //   115: getstatic 107	java/lang/Character:TYPE	Ljava/lang/Class;
    //   118: aastore
    //   119: aload 4
    //   121: iconst_2
    //   122: getstatic 107	java/lang/Character:TYPE	Ljava/lang/Class;
    //   125: aastore
    //   126: aload 4
    //   128: iconst_3
    //   129: getstatic 107	java/lang/Character:TYPE	Ljava/lang/Class;
    //   132: aastore
    //   133: ldc 109
    //   135: aload_3
    //   136: aload 4
    //   138: invokevirtual 113	java/lang/Class:getMethod	(Ljava/lang/String;[Ljava/lang/Class;)Ljava/lang/reflect/Method;
    //   141: astore 5
    //   143: iconst_4
    //   144: anewarray 115	java/lang/Object
    //   147: astore 6
    //   149: aload 6
    //   151: iconst_0
    //   152: ldc_w 428
    //   155: aastore
    //   156: aload 6
    //   158: iconst_1
    //   159: sipush 178
    //   162: invokestatic 121	java/lang/Character:valueOf	(C)Ljava/lang/Character;
    //   165: aastore
    //   166: aload 6
    //   168: iconst_2
    //   169: sipush 154
    //   172: invokestatic 121	java/lang/Character:valueOf	(C)Ljava/lang/Character;
    //   175: aastore
    //   176: aload 6
    //   178: iconst_3
    //   179: iconst_2
    //   180: invokestatic 121	java/lang/Character:valueOf	(C)Ljava/lang/Character;
    //   183: aastore
    //   184: aload 5
    //   186: aconst_null
    //   187: aload 6
    //   189: invokevirtual 127	java/lang/reflect/Method:invoke	(Ljava/lang/Object;[Ljava/lang/Object;)Ljava/lang/Object;
    //   192: astore 8
    //   194: aload_1
    //   195: aload 8
    //   197: checkcast 101	java/lang/String
    //   200: invokevirtual 432	android/content/Intent:getStringExtra	(Ljava/lang/String;)Ljava/lang/String;
    //   203: astore 9
    //   205: aload 9
    //   207: invokestatic 438	uuuuuu/sxsxsx:bk006Bkkk006Bk006B006B006B	(Ljava/lang/String;)Z
    //   210: ifeq +83 -> 293
    //   213: aload_0
    //   214: getfield 442	com/db/pwcc/dbmobile/transfer/standingorder/confirm/StandingOrderConfirmationActivity:redirectFacade	Luuuuuu/mbmbbb;
    //   217: aload_0
    //   218: aload 9
    //   220: invokeinterface 448 3 0
    //   225: return
    //   226: astore 13
    //   228: iconst_3
    //   229: putstatic 71	com/db/pwcc/dbmobile/transfer/standingorder/confirm/StandingOrderConfirmationActivity:b006Dmm006Dm006Dmm006D	I
    //   232: getstatic 71	com/db/pwcc/dbmobile/transfer/standingorder/confirm/StandingOrderConfirmationActivity:b006Dmm006Dm006Dmm006D	I
    //   235: getstatic 73	com/db/pwcc/dbmobile/transfer/standingorder/confirm/StandingOrderConfirmationActivity:b006D006D006D006Dm006Dmm006D	I
    //   238: iadd
    //   239: getstatic 71	com/db/pwcc/dbmobile/transfer/standingorder/confirm/StandingOrderConfirmationActivity:b006Dmm006Dm006Dmm006D	I
    //   242: imul
    //   243: getstatic 75	com/db/pwcc/dbmobile/transfer/standingorder/confirm/StandingOrderConfirmationActivity:bmm006D006Dm006Dmm006D	I
    //   246: irem
    //   247: getstatic 79	com/db/pwcc/dbmobile/transfer/standingorder/confirm/StandingOrderConfirmationActivity:bm006Dm006Dm006Dmm006D	I
    //   250: if_icmpeq -25 -> 225
    //   253: invokestatic 89	com/db/pwcc/dbmobile/transfer/standingorder/confirm/StandingOrderConfirmationActivity:b006Dm006D006Dm006Dmm006D	()I
    //   256: putstatic 71	com/db/pwcc/dbmobile/transfer/standingorder/confirm/StandingOrderConfirmationActivity:b006Dmm006Dm006Dmm006D	I
    //   259: invokestatic 89	com/db/pwcc/dbmobile/transfer/standingorder/confirm/StandingOrderConfirmationActivity:b006Dm006D006Dm006Dmm006D	()I
    //   262: putstatic 79	com/db/pwcc/dbmobile/transfer/standingorder/confirm/StandingOrderConfirmationActivity:bm006Dm006Dm006Dmm006D	I
    //   265: return
    //   266: aload_0
    //   267: invokevirtual 451	com/db/pwcc/dbmobile/transfer/standingorder/confirm/StandingOrderConfirmationActivity:navigateToStandingOrdersActivity	()V
    //   270: aconst_null
    //   271: invokevirtual 454	java/lang/String:length	()I
    //   274: pop
    //   275: goto -5 -> 270
    //   278: astore 10
    //   280: invokestatic 89	com/db/pwcc/dbmobile/transfer/standingorder/confirm/StandingOrderConfirmationActivity:b006Dm006D006Dm006Dmm006D	()I
    //   283: putstatic 71	com/db/pwcc/dbmobile/transfer/standingorder/confirm/StandingOrderConfirmationActivity:b006Dmm006Dm006Dmm006D	I
    //   286: iconst_m1
    //   287: newarray int
    //   289: pop
    //   290: goto -4 -> 286
    //   293: aload_0
    //   294: invokespecial 456	com/db/pwcc/dbmobile/transfer/standingorder/confirm/StandingOrderConfirmationActivity:isUpdateMode	()Z
    //   297: ifeq -31 -> 266
    //   300: aload_0
    //   301: invokevirtual 459	com/db/pwcc/dbmobile/transfer/standingorder/confirm/StandingOrderConfirmationActivity:navigateToStandingOrderDetailsActivity	()V
    //   304: return
    //   305: astore 11
    //   307: invokestatic 89	com/db/pwcc/dbmobile/transfer/standingorder/confirm/StandingOrderConfirmationActivity:b006Dm006D006Dm006Dmm006D	()I
    //   310: putstatic 71	com/db/pwcc/dbmobile/transfer/standingorder/confirm/StandingOrderConfirmationActivity:b006Dmm006Dm006Dmm006D	I
    //   313: aconst_null
    //   314: invokevirtual 454	java/lang/String:length	()I
    //   317: pop
    //   318: goto -5 -> 313
    //   321: astore 7
    //   323: aload 7
    //   325: invokevirtual 135	java/lang/reflect/InvocationTargetException:getCause	()Ljava/lang/Throwable;
    //   328: athrow
    // Local variable table:
    //   start	length	slot	name	signature
    //   0	329	0	this	StandingOrderConfirmationActivity
    //   4	191	1	localIntent	Intent
    //   8	8	2	i	int
    //   99	37	3	str1	String
    //   104	33	4	arrayOfClass	Class[]
    //   141	44	5	localMethod	Method
    //   147	41	6	arrayOfObject	Object[]
    //   321	3	7	localInvocationTargetException	InvocationTargetException
    //   192	4	8	localObject	Object
    //   203	16	9	str2	String
    //   278	1	10	localException1	Exception
    //   305	1	11	localException2	Exception
    //   226	1	13	localException3	Exception
    //   43	33	16	j	int
    // Exception table:
    //   from	to	target	type
    //   313	318	226	java/lang/Exception
    //   270	275	278	java/lang/Exception
    //   286	290	305	java/lang/Exception
    //   184	194	321	java/lang/reflect/InvocationTargetException
  }
  
  public int getLayout()
  {
    int i = R.layout.activity_standing_order_confirmation;
    if ((b006Dmm006Dm006Dmm006D + b006D006D006D006Dm006Dmm006D) * b006Dmm006Dm006Dmm006D % bmm006D006Dm006Dmm006D != bm006Dm006Dm006Dmm006D)
    {
      if ((b006Dmm006Dm006Dmm006D + b006D006D006D006Dm006Dmm006D) * b006Dmm006Dm006Dmm006D % bmm006D006Dm006Dmm006D != bm006Dm006Dm006Dmm006D)
      {
        int k = b006Dm006D006Dm006Dmm006D();
        if ((b006Dmm006Dm006Dmm006D + b006D006D006D006Dm006Dmm006D) * b006Dmm006Dm006Dmm006D % bmm006D006Dm006Dmm006D != bm006Dm006Dm006Dmm006D)
        {
          b006Dmm006Dm006Dmm006D = 31;
          bm006Dm006Dm006Dmm006D = b006Dm006D006Dm006Dmm006D();
        }
        b006Dmm006Dm006Dmm006D = k;
        bm006Dm006Dm006Dmm006D = 48;
      }
      b006Dmm006Dm006Dmm006D = 79;
      int j = b006Dmm006Dm006Dmm006D;
      switch (j * (j + b006D006D006D006Dm006Dmm006D) % bmm006D006Dm006Dmm006D)
      {
      default: 
        b006Dmm006Dm006Dmm006D = 73;
        bm006Dm006Dm006Dmm006D = b006Dm006D006Dm006Dmm006D();
      }
      bm006Dm006Dm006Dmm006D = 48;
    }
    return i;
  }
  
  public vvrvrv getResultSharedMetric()
  {
    if ((b006Dmm006Dm006Dmm006D + b006D006D006D006Dm006Dmm006D) * b006Dmm006Dm006Dmm006D % bmmmm006D006Dmm006D() != bm006D006D006Dm006Dmm006D())
    {
      b006Dmm006Dm006Dmm006D = b006Dm006D006Dm006Dmm006D();
      bm006Dm006Dm006Dmm006D = b006Dm006D006Dm006Dmm006D();
    }
    int i = (b006Dmm006Dm006Dmm006D + b006D006D006D006Dm006Dmm006D) * b006Dmm006Dm006Dmm006D % bmm006D006Dm006Dmm006D;
    int j = bm006Dm006Dm006Dmm006D;
    if ((b006Dmm006Dm006Dmm006D + b006D006D006D006Dm006Dmm006D) * b006Dmm006Dm006Dmm006D % bmmmm006D006Dmm006D() != bm006Dm006Dm006Dmm006D)
    {
      b006Dmm006Dm006Dmm006D = 35;
      bm006Dm006Dm006Dmm006D = b006Dm006D006Dm006Dmm006D();
    }
    if (i != j)
    {
      if ((b006Dmm006Dm006Dmm006D + b006D006D006D006Dm006Dmm006D) * b006Dmm006Dm006Dmm006D % bmm006D006Dm006Dmm006D != bm006Dm006Dm006Dmm006D)
      {
        b006Dmm006Dm006Dmm006D = 15;
        bm006Dm006Dm006Dmm006D = b006Dm006D006Dm006Dmm006D();
      }
      b006Dmm006Dm006Dmm006D = b006Dm006D006Dm006Dmm006D();
      bm006Dm006Dm006Dmm006D = b006Dm006D006Dm006Dmm006D();
    }
    return null;
  }
  
  /* Error */
  public void initDbToolbar()
  {
    // Byte code:
    //   0: aload_0
    //   1: invokespecial 470	com/db/pwcc/dbmobile/transfer/inputscreen/activities/ConfirmationActivity:initDbToolbar	()V
    //   4: aload_0
    //   5: getfield 50	com/db/pwcc/dbmobile/transfer/standingorder/confirm/StandingOrderConfirmationActivity:standingOrderRequestResponse	Lcom/db/pwcc/dbmobile/transfer/standingorder/model/StandingOrderRequestResponse;
    //   8: invokevirtual 69	com/db/pwcc/dbmobile/transfer/standingorder/model/StandingOrderRequestResponse:getTransaction	()Lcom/db/pwcc/dbmobile/transfer/standingorder/model/StandingOrderTransaction;
    //   11: invokevirtual 85	com/db/pwcc/dbmobile/transfer/standingorder/model/StandingOrderTransaction:getType	()Ljava/lang/String;
    //   14: astore_1
    //   15: aload_1
    //   16: invokevirtual 241	java/lang/String:hashCode	()I
    //   19: lookupswitch	default:+33->52, -1410683983:+505->524, 1634254479:+224->243, 1712813854:+348->367
    //   52: iconst_m1
    //   53: istore 8
    //   55: iload 8
    //   57: tableswitch	default:+27->84, 0:+42->99, 1:+126->183, 2:+587->644
    //   84: ldc_w 359
    //   87: astore 9
    //   89: aload_0
    //   90: invokevirtual 474	com/db/pwcc/dbmobile/transfer/standingorder/confirm/StandingOrderConfirmationActivity:getActionToolbar	()Lcom/db/pwcc/dbmobile/foundation/views/toolbar/DbToolbar;
    //   93: aload 9
    //   95: invokevirtual 480	com/db/pwcc/dbmobile/foundation/views/toolbar/DbToolbar:setTitle	(Ljava/lang/String;)V
    //   98: return
    //   99: aload_0
    //   100: getstatic 483	com/db/pwcc/dbmobile/transfer/R$string:standing_order_add_title	I
    //   103: invokevirtual 262	com/db/pwcc/dbmobile/transfer/standingorder/confirm/StandingOrderConfirmationActivity:getString	(I)Ljava/lang/String;
    //   106: astore 9
    //   108: invokestatic 89	com/db/pwcc/dbmobile/transfer/standingorder/confirm/StandingOrderConfirmationActivity:b006Dm006D006Dm006Dmm006D	()I
    //   111: getstatic 73	com/db/pwcc/dbmobile/transfer/standingorder/confirm/StandingOrderConfirmationActivity:b006D006D006D006Dm006Dmm006D	I
    //   114: iadd
    //   115: invokestatic 89	com/db/pwcc/dbmobile/transfer/standingorder/confirm/StandingOrderConfirmationActivity:b006Dm006D006Dm006Dmm006D	()I
    //   118: imul
    //   119: istore 11
    //   121: invokestatic 148	com/db/pwcc/dbmobile/transfer/standingorder/confirm/StandingOrderConfirmationActivity:bmmmm006D006Dmm006D	()I
    //   124: istore 12
    //   126: getstatic 71	com/db/pwcc/dbmobile/transfer/standingorder/confirm/StandingOrderConfirmationActivity:b006Dmm006Dm006Dmm006D	I
    //   129: getstatic 73	com/db/pwcc/dbmobile/transfer/standingorder/confirm/StandingOrderConfirmationActivity:b006D006D006D006Dm006Dmm006D	I
    //   132: iadd
    //   133: getstatic 71	com/db/pwcc/dbmobile/transfer/standingorder/confirm/StandingOrderConfirmationActivity:b006Dmm006Dm006Dmm006D	I
    //   136: imul
    //   137: getstatic 75	com/db/pwcc/dbmobile/transfer/standingorder/confirm/StandingOrderConfirmationActivity:bmm006D006Dm006Dmm006D	I
    //   140: irem
    //   141: getstatic 79	com/db/pwcc/dbmobile/transfer/standingorder/confirm/StandingOrderConfirmationActivity:bm006Dm006Dm006Dmm006D	I
    //   144: if_icmpeq +15 -> 159
    //   147: invokestatic 89	com/db/pwcc/dbmobile/transfer/standingorder/confirm/StandingOrderConfirmationActivity:b006Dm006D006Dm006Dmm006D	()I
    //   150: putstatic 71	com/db/pwcc/dbmobile/transfer/standingorder/confirm/StandingOrderConfirmationActivity:b006Dmm006Dm006Dmm006D	I
    //   153: invokestatic 89	com/db/pwcc/dbmobile/transfer/standingorder/confirm/StandingOrderConfirmationActivity:b006Dm006D006Dm006Dmm006D	()I
    //   156: putstatic 79	com/db/pwcc/dbmobile/transfer/standingorder/confirm/StandingOrderConfirmationActivity:bm006Dm006Dm006Dmm006D	I
    //   159: iload 11
    //   161: iload 12
    //   163: irem
    //   164: getstatic 79	com/db/pwcc/dbmobile/transfer/standingorder/confirm/StandingOrderConfirmationActivity:bm006Dm006Dm006Dmm006D	I
    //   167: if_icmpeq -78 -> 89
    //   170: invokestatic 89	com/db/pwcc/dbmobile/transfer/standingorder/confirm/StandingOrderConfirmationActivity:b006Dm006D006Dm006Dmm006D	()I
    //   173: putstatic 71	com/db/pwcc/dbmobile/transfer/standingorder/confirm/StandingOrderConfirmationActivity:b006Dmm006Dm006Dmm006D	I
    //   176: iconst_1
    //   177: putstatic 79	com/db/pwcc/dbmobile/transfer/standingorder/confirm/StandingOrderConfirmationActivity:bm006Dm006Dm006Dmm006D	I
    //   180: goto -91 -> 89
    //   183: aload_0
    //   184: getstatic 486	com/db/pwcc/dbmobile/transfer/R$string:edit_standing_order_title	I
    //   187: invokevirtual 262	com/db/pwcc/dbmobile/transfer/standingorder/confirm/StandingOrderConfirmationActivity:getString	(I)Ljava/lang/String;
    //   190: astore 9
    //   192: getstatic 71	com/db/pwcc/dbmobile/transfer/standingorder/confirm/StandingOrderConfirmationActivity:b006Dmm006Dm006Dmm006D	I
    //   195: istore 10
    //   197: iload 10
    //   199: iload 10
    //   201: getstatic 73	com/db/pwcc/dbmobile/transfer/standingorder/confirm/StandingOrderConfirmationActivity:b006D006D006D006Dm006Dmm006D	I
    //   204: iadd
    //   205: imul
    //   206: getstatic 75	com/db/pwcc/dbmobile/transfer/standingorder/confirm/StandingOrderConfirmationActivity:bmm006D006Dm006Dmm006D	I
    //   209: irem
    //   210: tableswitch	default:+18->228, 0:+-121->89
    //   228: invokestatic 89	com/db/pwcc/dbmobile/transfer/standingorder/confirm/StandingOrderConfirmationActivity:b006Dm006D006Dm006Dmm006D	()I
    //   231: putstatic 71	com/db/pwcc/dbmobile/transfer/standingorder/confirm/StandingOrderConfirmationActivity:b006Dmm006Dm006Dmm006D	I
    //   234: invokestatic 89	com/db/pwcc/dbmobile/transfer/standingorder/confirm/StandingOrderConfirmationActivity:b006Dm006D006Dm006Dmm006D	()I
    //   237: putstatic 79	com/db/pwcc/dbmobile/transfer/standingorder/confirm/StandingOrderConfirmationActivity:bm006Dm006Dm006Dmm006D	I
    //   240: goto -151 -> 89
    //   243: ldc_w 426
    //   246: bipush 102
    //   248: iconst_5
    //   249: invokestatic 97	xxxxxx/uxxxxx:bb00620062bb0062b0062b0062	(Ljava/lang/String;CC)Ljava/lang/String;
    //   252: astore 19
    //   254: iconst_4
    //   255: anewarray 99	java/lang/Class
    //   258: astore 20
    //   260: aload 20
    //   262: iconst_0
    //   263: ldc 101
    //   265: aastore
    //   266: aload 20
    //   268: iconst_1
    //   269: getstatic 107	java/lang/Character:TYPE	Ljava/lang/Class;
    //   272: aastore
    //   273: aload 20
    //   275: iconst_2
    //   276: getstatic 107	java/lang/Character:TYPE	Ljava/lang/Class;
    //   279: aastore
    //   280: aload 20
    //   282: iconst_3
    //   283: getstatic 107	java/lang/Character:TYPE	Ljava/lang/Class;
    //   286: aastore
    //   287: ldc 109
    //   289: aload 19
    //   291: aload 20
    //   293: invokevirtual 113	java/lang/Class:getMethod	(Ljava/lang/String;[Ljava/lang/Class;)Ljava/lang/reflect/Method;
    //   296: astore 21
    //   298: iconst_4
    //   299: anewarray 115	java/lang/Object
    //   302: astore 22
    //   304: aload 22
    //   306: iconst_0
    //   307: ldc_w 488
    //   310: aastore
    //   311: aload 22
    //   313: iconst_1
    //   314: sipush 134
    //   317: invokestatic 121	java/lang/Character:valueOf	(C)Ljava/lang/Character;
    //   320: aastore
    //   321: aload 22
    //   323: iconst_2
    //   324: sipush 220
    //   327: invokestatic 121	java/lang/Character:valueOf	(C)Ljava/lang/Character;
    //   330: aastore
    //   331: aload 22
    //   333: iconst_3
    //   334: iconst_3
    //   335: invokestatic 121	java/lang/Character:valueOf	(C)Ljava/lang/Character;
    //   338: aastore
    //   339: aload 21
    //   341: aconst_null
    //   342: aload 22
    //   344: invokevirtual 127	java/lang/reflect/Method:invoke	(Ljava/lang/Object;[Ljava/lang/Object;)Ljava/lang/Object;
    //   347: astore 24
    //   349: aload_1
    //   350: aload 24
    //   352: checkcast 101	java/lang/String
    //   355: invokevirtual 131	java/lang/String:equals	(Ljava/lang/Object;)Z
    //   358: ifeq -306 -> 52
    //   361: iconst_2
    //   362: istore 8
    //   364: goto -309 -> 55
    //   367: getstatic 71	com/db/pwcc/dbmobile/transfer/standingorder/confirm/StandingOrderConfirmationActivity:b006Dmm006Dm006Dmm006D	I
    //   370: getstatic 73	com/db/pwcc/dbmobile/transfer/standingorder/confirm/StandingOrderConfirmationActivity:b006D006D006D006Dm006Dmm006D	I
    //   373: iadd
    //   374: getstatic 71	com/db/pwcc/dbmobile/transfer/standingorder/confirm/StandingOrderConfirmationActivity:b006Dmm006Dm006Dmm006D	I
    //   377: imul
    //   378: getstatic 75	com/db/pwcc/dbmobile/transfer/standingorder/confirm/StandingOrderConfirmationActivity:bmm006D006Dm006Dmm006D	I
    //   381: irem
    //   382: getstatic 79	com/db/pwcc/dbmobile/transfer/standingorder/confirm/StandingOrderConfirmationActivity:bm006Dm006Dm006Dmm006D	I
    //   385: if_icmpeq +14 -> 399
    //   388: bipush 63
    //   390: putstatic 71	com/db/pwcc/dbmobile/transfer/standingorder/confirm/StandingOrderConfirmationActivity:b006Dmm006Dm006Dmm006D	I
    //   393: invokestatic 89	com/db/pwcc/dbmobile/transfer/standingorder/confirm/StandingOrderConfirmationActivity:b006Dm006D006Dm006Dmm006D	()I
    //   396: putstatic 79	com/db/pwcc/dbmobile/transfer/standingorder/confirm/StandingOrderConfirmationActivity:bm006Dm006Dm006Dmm006D	I
    //   399: ldc_w 490
    //   402: sipush 145
    //   405: iconst_1
    //   406: invokestatic 97	xxxxxx/uxxxxx:bb00620062bb0062b0062b0062	(Ljava/lang/String;CC)Ljava/lang/String;
    //   409: astore 13
    //   411: iconst_4
    //   412: anewarray 99	java/lang/Class
    //   415: astore 14
    //   417: aload 14
    //   419: iconst_0
    //   420: ldc 101
    //   422: aastore
    //   423: aload 14
    //   425: iconst_1
    //   426: getstatic 107	java/lang/Character:TYPE	Ljava/lang/Class;
    //   429: aastore
    //   430: aload 14
    //   432: iconst_2
    //   433: getstatic 107	java/lang/Character:TYPE	Ljava/lang/Class;
    //   436: aastore
    //   437: aload 14
    //   439: iconst_3
    //   440: getstatic 107	java/lang/Character:TYPE	Ljava/lang/Class;
    //   443: aastore
    //   444: ldc 109
    //   446: aload 13
    //   448: aload 14
    //   450: invokevirtual 113	java/lang/Class:getMethod	(Ljava/lang/String;[Ljava/lang/Class;)Ljava/lang/reflect/Method;
    //   453: astore 15
    //   455: iconst_4
    //   456: anewarray 115	java/lang/Object
    //   459: astore 16
    //   461: aload 16
    //   463: iconst_0
    //   464: ldc_w 492
    //   467: aastore
    //   468: aload 16
    //   470: iconst_1
    //   471: sipush 175
    //   474: invokestatic 121	java/lang/Character:valueOf	(C)Ljava/lang/Character;
    //   477: aastore
    //   478: aload 16
    //   480: iconst_2
    //   481: sipush 236
    //   484: invokestatic 121	java/lang/Character:valueOf	(C)Ljava/lang/Character;
    //   487: aastore
    //   488: aload 16
    //   490: iconst_3
    //   491: iconst_3
    //   492: invokestatic 121	java/lang/Character:valueOf	(C)Ljava/lang/Character;
    //   495: aastore
    //   496: aload 15
    //   498: aconst_null
    //   499: aload 16
    //   501: invokevirtual 127	java/lang/reflect/Method:invoke	(Ljava/lang/Object;[Ljava/lang/Object;)Ljava/lang/Object;
    //   504: astore 18
    //   506: aload_1
    //   507: aload 18
    //   509: checkcast 101	java/lang/String
    //   512: invokevirtual 131	java/lang/String:equals	(Ljava/lang/Object;)Z
    //   515: ifeq -463 -> 52
    //   518: iconst_0
    //   519: istore 8
    //   521: goto -466 -> 55
    //   524: ldc_w 494
    //   527: sipush 200
    //   530: sipush 157
    //   533: iconst_2
    //   534: invokestatic 186	xxxxxx/uxxxxx:bbbb0062b0062b0062b0062	(Ljava/lang/String;CCC)Ljava/lang/String;
    //   537: astore_2
    //   538: iconst_3
    //   539: anewarray 99	java/lang/Class
    //   542: astore_3
    //   543: aload_3
    //   544: iconst_0
    //   545: ldc 101
    //   547: aastore
    //   548: aload_3
    //   549: iconst_1
    //   550: getstatic 107	java/lang/Character:TYPE	Ljava/lang/Class;
    //   553: aastore
    //   554: aload_3
    //   555: iconst_2
    //   556: getstatic 107	java/lang/Character:TYPE	Ljava/lang/Class;
    //   559: aastore
    //   560: ldc 109
    //   562: aload_2
    //   563: aload_3
    //   564: invokevirtual 113	java/lang/Class:getMethod	(Ljava/lang/String;[Ljava/lang/Class;)Ljava/lang/reflect/Method;
    //   567: astore 4
    //   569: iconst_3
    //   570: anewarray 115	java/lang/Object
    //   573: astore 5
    //   575: aload 5
    //   577: iconst_0
    //   578: ldc_w 496
    //   581: aastore
    //   582: aload 5
    //   584: iconst_1
    //   585: sipush 250
    //   588: invokestatic 121	java/lang/Character:valueOf	(C)Ljava/lang/Character;
    //   591: aastore
    //   592: aload 5
    //   594: iconst_2
    //   595: iconst_4
    //   596: invokestatic 121	java/lang/Character:valueOf	(C)Ljava/lang/Character;
    //   599: aastore
    //   600: aload 4
    //   602: aconst_null
    //   603: aload 5
    //   605: invokevirtual 127	java/lang/reflect/Method:invoke	(Ljava/lang/Object;[Ljava/lang/Object;)Ljava/lang/Object;
    //   608: astore 7
    //   610: aload_1
    //   611: aload 7
    //   613: checkcast 101	java/lang/String
    //   616: invokevirtual 131	java/lang/String:equals	(Ljava/lang/Object;)Z
    //   619: ifeq -567 -> 52
    //   622: iconst_1
    //   623: istore 8
    //   625: goto -570 -> 55
    //   628: astore 23
    //   630: aload 23
    //   632: invokevirtual 135	java/lang/reflect/InvocationTargetException:getCause	()Ljava/lang/Throwable;
    //   635: athrow
    //   636: astore 17
    //   638: aload 17
    //   640: invokevirtual 135	java/lang/reflect/InvocationTargetException:getCause	()Ljava/lang/Throwable;
    //   643: athrow
    //   644: aload_0
    //   645: getstatic 499	com/db/pwcc/dbmobile/transfer/R$string:delete_standing_order_title	I
    //   648: invokevirtual 262	com/db/pwcc/dbmobile/transfer/standingorder/confirm/StandingOrderConfirmationActivity:getString	(I)Ljava/lang/String;
    //   651: astore 9
    //   653: goto -564 -> 89
    //   656: astore 6
    //   658: aload 6
    //   660: invokevirtual 135	java/lang/reflect/InvocationTargetException:getCause	()Ljava/lang/Throwable;
    //   663: athrow
    // Local variable table:
    //   start	length	slot	name	signature
    //   0	664	0	this	StandingOrderConfirmationActivity
    //   14	597	1	str1	String
    //   537	26	2	str2	String
    //   542	22	3	arrayOfClass1	Class[]
    //   567	34	4	localMethod1	Method
    //   573	31	5	arrayOfObject1	Object[]
    //   656	3	6	localInvocationTargetException1	InvocationTargetException
    //   608	4	7	localObject1	Object
    //   53	571	8	i	int
    //   87	565	9	str3	String
    //   195	11	10	j	int
    //   119	45	11	k	int
    //   124	40	12	m	int
    //   409	38	13	str4	String
    //   415	34	14	arrayOfClass2	Class[]
    //   453	44	15	localMethod2	Method
    //   459	41	16	arrayOfObject2	Object[]
    //   636	3	17	localInvocationTargetException2	InvocationTargetException
    //   504	4	18	localObject2	Object
    //   252	38	19	str5	String
    //   258	34	20	arrayOfClass3	Class[]
    //   296	44	21	localMethod3	Method
    //   302	41	22	arrayOfObject3	Object[]
    //   628	3	23	localInvocationTargetException3	InvocationTargetException
    //   347	4	24	localObject3	Object
    // Exception table:
    //   from	to	target	type
    //   339	349	628	java/lang/reflect/InvocationTargetException
    //   496	506	636	java/lang/reflect/InvocationTargetException
    //   600	610	656	java/lang/reflect/InvocationTargetException
  }
  
  /* Error */
  public void initView()
  {
    // Byte code:
    //   0: getstatic 71	com/db/pwcc/dbmobile/transfer/standingorder/confirm/StandingOrderConfirmationActivity:b006Dmm006Dm006Dmm006D	I
    //   3: istore_1
    //   4: iload_1
    //   5: iload_1
    //   6: invokestatic 87	com/db/pwcc/dbmobile/transfer/standingorder/confirm/StandingOrderConfirmationActivity:b006D006Dm006Dm006Dmm006D	()I
    //   9: iadd
    //   10: imul
    //   11: getstatic 75	com/db/pwcc/dbmobile/transfer/standingorder/confirm/StandingOrderConfirmationActivity:bmm006D006Dm006Dmm006D	I
    //   14: irem
    //   15: tableswitch	default:+17->32, 0:+29->44
    //   32: invokestatic 89	com/db/pwcc/dbmobile/transfer/standingorder/confirm/StandingOrderConfirmationActivity:b006Dm006D006Dm006Dmm006D	()I
    //   35: putstatic 71	com/db/pwcc/dbmobile/transfer/standingorder/confirm/StandingOrderConfirmationActivity:b006Dmm006Dm006Dmm006D	I
    //   38: invokestatic 89	com/db/pwcc/dbmobile/transfer/standingorder/confirm/StandingOrderConfirmationActivity:b006Dm006D006Dm006Dmm006D	()I
    //   41: putstatic 79	com/db/pwcc/dbmobile/transfer/standingorder/confirm/StandingOrderConfirmationActivity:bm006Dm006Dm006Dmm006D	I
    //   44: aload_0
    //   45: invokespecial 502	com/db/pwcc/dbmobile/transfer/inputscreen/activities/ConfirmationActivity:initView	()V
    //   48: aload_0
    //   49: invokespecial 456	com/db/pwcc/dbmobile/transfer/standingorder/confirm/StandingOrderConfirmationActivity:isUpdateMode	()Z
    //   52: ifeq +499 -> 551
    //   55: aload_0
    //   56: getfield 506	com/db/pwcc/dbmobile/transfer/standingorder/confirm/StandingOrderConfirmationActivity:tanModule	Lcom/db/pwcc/dbmobile/tan/ui/TanModule;
    //   59: aload_0
    //   60: getstatic 509	com/db/pwcc/dbmobile/transfer/R$string:standingorder_verify_edit_inputtan_message	I
    //   63: invokevirtual 262	com/db/pwcc/dbmobile/transfer/standingorder/confirm/StandingOrderConfirmationActivity:getString	(I)Ljava/lang/String;
    //   66: invokevirtual 514	com/db/pwcc/dbmobile/tan/ui/TanModule:setItanDescriptionText	(Ljava/lang/String;)V
    //   69: aload_0
    //   70: getfield 506	com/db/pwcc/dbmobile/transfer/standingorder/confirm/StandingOrderConfirmationActivity:tanModule	Lcom/db/pwcc/dbmobile/tan/ui/TanModule;
    //   73: aload_0
    //   74: getstatic 517	com/db/pwcc/dbmobile/transfer/R$string:standingorder_verify_edit_success_label_format	I
    //   77: invokevirtual 262	com/db/pwcc/dbmobile/transfer/standingorder/confirm/StandingOrderConfirmationActivity:getString	(I)Ljava/lang/String;
    //   80: invokevirtual 520	com/db/pwcc/dbmobile/tan/ui/TanModule:setDescriptionResult	(Ljava/lang/String;)V
    //   83: aload_0
    //   84: getfield 506	com/db/pwcc/dbmobile/transfer/standingorder/confirm/StandingOrderConfirmationActivity:tanModule	Lcom/db/pwcc/dbmobile/tan/ui/TanModule;
    //   87: aload_0
    //   88: getfield 48	com/db/pwcc/dbmobile/transfer/standingorder/confirm/StandingOrderConfirmationActivity:presenter	Luuuuuu/llvvll$vlvvll;
    //   91: checkcast 522	uuuuuu/kkkklk
    //   94: invokevirtual 526	com/db/pwcc/dbmobile/tan/ui/TanModule:setTanModuleActivityActions	(Luuuuuu/kkkklk;)V
    //   97: aload_0
    //   98: invokevirtual 424	com/db/pwcc/dbmobile/transfer/standingorder/confirm/StandingOrderConfirmationActivity:getIntent	()Landroid/content/Intent;
    //   101: invokevirtual 530	android/content/Intent:getExtras	()Landroid/os/Bundle;
    //   104: astore_3
    //   105: ldc_w 532
    //   108: sipush 154
    //   111: bipush 121
    //   113: iconst_0
    //   114: invokestatic 186	xxxxxx/uxxxxx:bbbb0062b0062b0062b0062	(Ljava/lang/String;CCC)Ljava/lang/String;
    //   117: astore 4
    //   119: iconst_3
    //   120: anewarray 99	java/lang/Class
    //   123: astore 5
    //   125: aload 5
    //   127: iconst_0
    //   128: ldc 101
    //   130: aastore
    //   131: aload 5
    //   133: iconst_1
    //   134: getstatic 107	java/lang/Character:TYPE	Ljava/lang/Class;
    //   137: aastore
    //   138: aload 5
    //   140: iconst_2
    //   141: getstatic 107	java/lang/Character:TYPE	Ljava/lang/Class;
    //   144: aastore
    //   145: ldc 109
    //   147: aload 4
    //   149: aload 5
    //   151: invokevirtual 113	java/lang/Class:getMethod	(Ljava/lang/String;[Ljava/lang/Class;)Ljava/lang/reflect/Method;
    //   154: astore 6
    //   156: iconst_3
    //   157: anewarray 115	java/lang/Object
    //   160: astore 7
    //   162: aload 7
    //   164: iconst_0
    //   165: ldc_w 534
    //   168: aastore
    //   169: aload 7
    //   171: iconst_1
    //   172: bipush 13
    //   174: invokestatic 121	java/lang/Character:valueOf	(C)Ljava/lang/Character;
    //   177: aastore
    //   178: aload 7
    //   180: iconst_2
    //   181: iconst_0
    //   182: invokestatic 121	java/lang/Character:valueOf	(C)Ljava/lang/Character;
    //   185: aastore
    //   186: aload 6
    //   188: aconst_null
    //   189: aload 7
    //   191: invokevirtual 127	java/lang/reflect/Method:invoke	(Ljava/lang/Object;[Ljava/lang/Object;)Ljava/lang/Object;
    //   194: astore 9
    //   196: aload_3
    //   197: aload 9
    //   199: checkcast 101	java/lang/String
    //   202: invokevirtual 540	android/os/Bundle:get	(Ljava/lang/String;)Ljava/lang/Object;
    //   205: checkcast 542	com/db/pwcc/dbmobile/model/tan/AuthorizationStatus
    //   208: astore 10
    //   210: aload_0
    //   211: invokevirtual 424	com/db/pwcc/dbmobile/transfer/standingorder/confirm/StandingOrderConfirmationActivity:getIntent	()Landroid/content/Intent;
    //   214: invokevirtual 530	android/content/Intent:getExtras	()Landroid/os/Bundle;
    //   217: astore 11
    //   219: ldc_w 544
    //   222: bipush 120
    //   224: iconst_0
    //   225: invokestatic 97	xxxxxx/uxxxxx:bb00620062bb0062b0062b0062	(Ljava/lang/String;CC)Ljava/lang/String;
    //   228: astore 12
    //   230: iconst_3
    //   231: anewarray 99	java/lang/Class
    //   234: astore 13
    //   236: aload 13
    //   238: iconst_0
    //   239: ldc 101
    //   241: aastore
    //   242: aload 13
    //   244: iconst_1
    //   245: getstatic 107	java/lang/Character:TYPE	Ljava/lang/Class;
    //   248: aastore
    //   249: aload 13
    //   251: iconst_2
    //   252: getstatic 107	java/lang/Character:TYPE	Ljava/lang/Class;
    //   255: aastore
    //   256: ldc 109
    //   258: aload 12
    //   260: aload 13
    //   262: invokevirtual 113	java/lang/Class:getMethod	(Ljava/lang/String;[Ljava/lang/Class;)Ljava/lang/reflect/Method;
    //   265: astore 14
    //   267: iconst_3
    //   268: anewarray 115	java/lang/Object
    //   271: astore 15
    //   273: aload 15
    //   275: iconst_0
    //   276: ldc_w 546
    //   279: aastore
    //   280: aload 15
    //   282: iconst_1
    //   283: bipush 114
    //   285: invokestatic 121	java/lang/Character:valueOf	(C)Ljava/lang/Character;
    //   288: aastore
    //   289: aload 15
    //   291: iconst_2
    //   292: iconst_4
    //   293: invokestatic 121	java/lang/Character:valueOf	(C)Ljava/lang/Character;
    //   296: aastore
    //   297: aload 14
    //   299: aconst_null
    //   300: aload 15
    //   302: invokevirtual 127	java/lang/reflect/Method:invoke	(Ljava/lang/Object;[Ljava/lang/Object;)Ljava/lang/Object;
    //   305: astore 17
    //   307: aload 11
    //   309: aload 17
    //   311: checkcast 101	java/lang/String
    //   314: invokevirtual 540	android/os/Bundle:get	(Ljava/lang/String;)Ljava/lang/Object;
    //   317: checkcast 548	com/db/pwcc/dbmobile/model/tan/Authorization
    //   320: astore 18
    //   322: aload_0
    //   323: getfield 506	com/db/pwcc/dbmobile/transfer/standingorder/confirm/StandingOrderConfirmationActivity:tanModule	Lcom/db/pwcc/dbmobile/tan/ui/TanModule;
    //   326: aload_0
    //   327: getfield 52	com/db/pwcc/dbmobile/transfer/standingorder/confirm/StandingOrderConfirmationActivity:challengeResponse	Lcom/db/pwcc/dbmobile/model/tan/ChallengeResponse;
    //   330: aload_0
    //   331: getfield 50	com/db/pwcc/dbmobile/transfer/standingorder/confirm/StandingOrderConfirmationActivity:standingOrderRequestResponse	Lcom/db/pwcc/dbmobile/transfer/standingorder/model/StandingOrderRequestResponse;
    //   334: invokevirtual 69	com/db/pwcc/dbmobile/transfer/standingorder/model/StandingOrderRequestResponse:getTransaction	()Lcom/db/pwcc/dbmobile/transfer/standingorder/model/StandingOrderTransaction;
    //   337: aload 18
    //   339: aload 10
    //   341: aload_0
    //   342: getfield 50	com/db/pwcc/dbmobile/transfer/standingorder/confirm/StandingOrderConfirmationActivity:standingOrderRequestResponse	Lcom/db/pwcc/dbmobile/transfer/standingorder/model/StandingOrderRequestResponse;
    //   345: invokevirtual 551	com/db/pwcc/dbmobile/transfer/standingorder/model/StandingOrderRequestResponse:getCorrelationId	()Ljava/lang/String;
    //   348: invokevirtual 555	com/db/pwcc/dbmobile/tan/ui/TanModule:initializeTanModule	(Lcom/db/pwcc/dbmobile/model/tan/ChallengeResponse;Lcom/db/pwcc/dbmobile/model/common/Transaction;Lcom/db/pwcc/dbmobile/model/tan/Authorization;Lcom/db/pwcc/dbmobile/model/tan/AuthorizationStatus;Ljava/lang/String;)V
    //   351: aload_0
    //   352: getfield 506	com/db/pwcc/dbmobile/transfer/standingorder/confirm/StandingOrderConfirmationActivity:tanModule	Lcom/db/pwcc/dbmobile/tan/ui/TanModule;
    //   355: invokevirtual 558	com/db/pwcc/dbmobile/tan/ui/TanModule:disableNewTransferButton	()V
    //   358: aload_0
    //   359: getfield 506	com/db/pwcc/dbmobile/transfer/standingorder/confirm/StandingOrderConfirmationActivity:tanModule	Lcom/db/pwcc/dbmobile/tan/ui/TanModule;
    //   362: new 560	uuuuuu/vllvlv
    //   365: dup
    //   366: invokespecial 561	uuuuuu/vllvlv:<init>	()V
    //   369: invokevirtual 565	com/db/pwcc/dbmobile/tan/ui/TanModule:setGetTanChallengeInteractor	(Luuuuuu/vpvppv;)V
    //   372: invokestatic 89	com/db/pwcc/dbmobile/transfer/standingorder/confirm/StandingOrderConfirmationActivity:b006Dm006D006Dm006Dmm006D	()I
    //   375: getstatic 73	com/db/pwcc/dbmobile/transfer/standingorder/confirm/StandingOrderConfirmationActivity:b006D006D006D006Dm006Dmm006D	I
    //   378: iadd
    //   379: invokestatic 89	com/db/pwcc/dbmobile/transfer/standingorder/confirm/StandingOrderConfirmationActivity:b006Dm006D006Dm006Dmm006D	()I
    //   382: imul
    //   383: invokestatic 148	com/db/pwcc/dbmobile/transfer/standingorder/confirm/StandingOrderConfirmationActivity:bmmmm006D006Dmm006D	()I
    //   386: irem
    //   387: getstatic 79	com/db/pwcc/dbmobile/transfer/standingorder/confirm/StandingOrderConfirmationActivity:bm006Dm006Dm006Dmm006D	I
    //   390: if_icmpeq +14 -> 404
    //   393: invokestatic 89	com/db/pwcc/dbmobile/transfer/standingorder/confirm/StandingOrderConfirmationActivity:b006Dm006D006Dm006Dmm006D	()I
    //   396: putstatic 71	com/db/pwcc/dbmobile/transfer/standingorder/confirm/StandingOrderConfirmationActivity:b006Dmm006Dm006Dmm006D	I
    //   399: bipush 90
    //   401: putstatic 79	com/db/pwcc/dbmobile/transfer/standingorder/confirm/StandingOrderConfirmationActivity:bm006Dm006Dm006Dmm006D	I
    //   404: aload_0
    //   405: getfield 48	com/db/pwcc/dbmobile/transfer/standingorder/confirm/StandingOrderConfirmationActivity:presenter	Luuuuuu/llvvll$vlvvll;
    //   408: invokeinterface 570 1 0
    //   413: aload_0
    //   414: getfield 50	com/db/pwcc/dbmobile/transfer/standingorder/confirm/StandingOrderConfirmationActivity:standingOrderRequestResponse	Lcom/db/pwcc/dbmobile/transfer/standingorder/model/StandingOrderRequestResponse;
    //   417: invokevirtual 69	com/db/pwcc/dbmobile/transfer/standingorder/model/StandingOrderRequestResponse:getTransaction	()Lcom/db/pwcc/dbmobile/transfer/standingorder/model/StandingOrderTransaction;
    //   420: astore 19
    //   422: aload_0
    //   423: aload_0
    //   424: invokevirtual 574	com/db/pwcc/dbmobile/transfer/standingorder/confirm/StandingOrderConfirmationActivity:setBoldText	(Landroid/app/Activity;)V
    //   427: aload_0
    //   428: getfield 50	com/db/pwcc/dbmobile/transfer/standingorder/confirm/StandingOrderConfirmationActivity:standingOrderRequestResponse	Lcom/db/pwcc/dbmobile/transfer/standingorder/model/StandingOrderRequestResponse;
    //   431: astore 20
    //   433: getstatic 71	com/db/pwcc/dbmobile/transfer/standingorder/confirm/StandingOrderConfirmationActivity:b006Dmm006Dm006Dmm006D	I
    //   436: getstatic 73	com/db/pwcc/dbmobile/transfer/standingorder/confirm/StandingOrderConfirmationActivity:b006D006D006D006Dm006Dmm006D	I
    //   439: iadd
    //   440: getstatic 71	com/db/pwcc/dbmobile/transfer/standingorder/confirm/StandingOrderConfirmationActivity:b006Dmm006Dm006Dmm006D	I
    //   443: imul
    //   444: getstatic 75	com/db/pwcc/dbmobile/transfer/standingorder/confirm/StandingOrderConfirmationActivity:bmm006D006Dm006Dmm006D	I
    //   447: irem
    //   448: getstatic 79	com/db/pwcc/dbmobile/transfer/standingorder/confirm/StandingOrderConfirmationActivity:bm006Dm006Dm006Dmm006D	I
    //   451: if_icmpeq +14 -> 465
    //   454: invokestatic 89	com/db/pwcc/dbmobile/transfer/standingorder/confirm/StandingOrderConfirmationActivity:b006Dm006D006Dm006Dmm006D	()I
    //   457: putstatic 71	com/db/pwcc/dbmobile/transfer/standingorder/confirm/StandingOrderConfirmationActivity:b006Dmm006Dm006Dmm006D	I
    //   460: bipush 58
    //   462: putstatic 79	com/db/pwcc/dbmobile/transfer/standingorder/confirm/StandingOrderConfirmationActivity:bm006Dm006Dm006Dmm006D	I
    //   465: aload_0
    //   466: aload 20
    //   468: invokevirtual 578	com/db/pwcc/dbmobile/transfer/standingorder/confirm/StandingOrderConfirmationActivity:setTransactionData	(Lcom/db/pwcc/dbmobile/transfer/standingorder/model/StandingOrderRequestResponse;)V
    //   471: aload_0
    //   472: aload 19
    //   474: invokevirtual 581	com/db/pwcc/dbmobile/transfer/standingorder/model/StandingOrderTransaction:getTargetAccount	()Ljava/lang/String;
    //   477: aload 19
    //   479: invokevirtual 584	com/db/pwcc/dbmobile/transfer/standingorder/model/StandingOrderTransaction:getBeneficiary	()Ljava/lang/String;
    //   482: aload 19
    //   484: invokevirtual 587	com/db/pwcc/dbmobile/transfer/standingorder/model/StandingOrderTransaction:getSourceAccount	()Ljava/lang/String;
    //   487: invokevirtual 591	com/db/pwcc/dbmobile/transfer/standingorder/confirm/StandingOrderConfirmationActivity:setFriendPicture	(Ljava/lang/String;Ljava/lang/String;Ljava/lang/String;)V
    //   490: aload_0
    //   491: getfield 48	com/db/pwcc/dbmobile/transfer/standingorder/confirm/StandingOrderConfirmationActivity:presenter	Luuuuuu/llvvll$vlvvll;
    //   494: astore 21
    //   496: aload_0
    //   497: getfield 50	com/db/pwcc/dbmobile/transfer/standingorder/confirm/StandingOrderConfirmationActivity:standingOrderRequestResponse	Lcom/db/pwcc/dbmobile/transfer/standingorder/model/StandingOrderRequestResponse;
    //   500: astore 22
    //   502: ldc_w 567
    //   505: ldc_w 593
    //   508: sipush 250
    //   511: iconst_5
    //   512: invokestatic 97	xxxxxx/uxxxxx:bb00620062bb0062b0062b0062	(Ljava/lang/String;CC)Ljava/lang/String;
    //   515: iconst_1
    //   516: anewarray 99	java/lang/Class
    //   519: dup
    //   520: iconst_0
    //   521: ldc 65
    //   523: aastore
    //   524: invokevirtual 113	java/lang/Class:getMethod	(Ljava/lang/String;[Ljava/lang/Class;)Ljava/lang/reflect/Method;
    //   527: astore 23
    //   529: iconst_1
    //   530: anewarray 115	java/lang/Object
    //   533: dup
    //   534: iconst_0
    //   535: aload 22
    //   537: aastore
    //   538: astore 24
    //   540: aload 23
    //   542: aload 21
    //   544: aload 24
    //   546: invokevirtual 127	java/lang/reflect/Method:invoke	(Ljava/lang/Object;[Ljava/lang/Object;)Ljava/lang/Object;
    //   549: pop
    //   550: return
    //   551: aload_0
    //   552: invokespecial 595	com/db/pwcc/dbmobile/transfer/standingorder/confirm/StandingOrderConfirmationActivity:isDeleteMode	()Z
    //   555: ifeq -472 -> 83
    //   558: aload_0
    //   559: getfield 506	com/db/pwcc/dbmobile/transfer/standingorder/confirm/StandingOrderConfirmationActivity:tanModule	Lcom/db/pwcc/dbmobile/tan/ui/TanModule;
    //   562: aload_0
    //   563: getstatic 598	com/db/pwcc/dbmobile/transfer/R$string:standingorder_verify_delete_inputtan_message	I
    //   566: invokevirtual 262	com/db/pwcc/dbmobile/transfer/standingorder/confirm/StandingOrderConfirmationActivity:getString	(I)Ljava/lang/String;
    //   569: invokevirtual 514	com/db/pwcc/dbmobile/tan/ui/TanModule:setItanDescriptionText	(Ljava/lang/String;)V
    //   572: aload_0
    //   573: getfield 506	com/db/pwcc/dbmobile/transfer/standingorder/confirm/StandingOrderConfirmationActivity:tanModule	Lcom/db/pwcc/dbmobile/tan/ui/TanModule;
    //   576: aload_0
    //   577: getstatic 601	com/db/pwcc/dbmobile/transfer/R$string:standingorder_verify_delete_success_label_format	I
    //   580: invokevirtual 262	com/db/pwcc/dbmobile/transfer/standingorder/confirm/StandingOrderConfirmationActivity:getString	(I)Ljava/lang/String;
    //   583: invokevirtual 520	com/db/pwcc/dbmobile/tan/ui/TanModule:setDescriptionResult	(Ljava/lang/String;)V
    //   586: iconst_m1
    //   587: newarray int
    //   589: pop
    //   590: goto -4 -> 586
    //   593: astore 25
    //   595: aload 25
    //   597: invokevirtual 135	java/lang/reflect/InvocationTargetException:getCause	()Ljava/lang/Throwable;
    //   600: athrow
    //   601: astore 16
    //   603: aload 16
    //   605: invokevirtual 135	java/lang/reflect/InvocationTargetException:getCause	()Ljava/lang/Throwable;
    //   608: athrow
    //   609: astore 8
    //   611: aload 8
    //   613: invokevirtual 135	java/lang/reflect/InvocationTargetException:getCause	()Ljava/lang/Throwable;
    //   616: athrow
    //   617: astore_2
    //   618: invokestatic 89	com/db/pwcc/dbmobile/transfer/standingorder/confirm/StandingOrderConfirmationActivity:b006Dm006D006Dm006Dmm006D	()I
    //   621: putstatic 71	com/db/pwcc/dbmobile/transfer/standingorder/confirm/StandingOrderConfirmationActivity:b006Dmm006Dm006Dmm006D	I
    //   624: goto -541 -> 83
    // Local variable table:
    //   start	length	slot	name	signature
    //   0	627	0	this	StandingOrderConfirmationActivity
    //   3	8	1	i	int
    //   617	1	2	localException	Exception
    //   104	93	3	localBundle1	Bundle
    //   117	31	4	str1	String
    //   123	27	5	arrayOfClass1	Class[]
    //   154	33	6	localMethod1	Method
    //   160	30	7	arrayOfObject1	Object[]
    //   609	3	8	localInvocationTargetException1	InvocationTargetException
    //   194	4	9	localObject1	Object
    //   208	132	10	localAuthorizationStatus	AuthorizationStatus
    //   217	91	11	localBundle2	Bundle
    //   228	31	12	str2	String
    //   234	27	13	arrayOfClass2	Class[]
    //   265	33	14	localMethod2	Method
    //   271	30	15	arrayOfObject2	Object[]
    //   601	3	16	localInvocationTargetException2	InvocationTargetException
    //   305	5	17	localObject2	Object
    //   320	18	18	localAuthorization	Authorization
    //   420	63	19	localStandingOrderTransaction	StandingOrderTransaction
    //   431	36	20	localStandingOrderRequestResponse1	StandingOrderRequestResponse
    //   494	49	21	localVlvvll	llvvll.vlvvll
    //   500	36	22	localStandingOrderRequestResponse2	StandingOrderRequestResponse
    //   527	14	23	localMethod3	Method
    //   538	7	24	arrayOfObject3	Object[]
    //   593	3	25	localInvocationTargetException3	InvocationTargetException
    // Exception table:
    //   from	to	target	type
    //   540	550	593	java/lang/reflect/InvocationTargetException
    //   297	307	601	java/lang/reflect/InvocationTargetException
    //   186	196	609	java/lang/reflect/InvocationTargetException
    //   586	590	617	java/lang/Exception
  }
  
  public void navigateToStandingOrderDetailsActivity()
  {
    if ((b006Dmm006Dm006Dmm006D + b006D006D006D006Dm006Dmm006D) * b006Dmm006Dm006Dmm006D % bmm006D006Dm006Dmm006D != bm006D006D006Dm006Dmm006D())
    {
      b006Dmm006Dm006Dmm006D = 27;
      bm006Dm006Dm006Dmm006D = b006Dm006D006Dm006Dmm006D();
    }
    if ((b006Dmm006Dm006Dmm006D + b006D006D006D006Dm006Dmm006D) * b006Dmm006Dm006Dmm006D % bmm006D006Dm006Dmm006D != bm006Dm006Dm006Dmm006D)
    {
      b006Dmm006Dm006Dmm006D = 75;
      bm006Dm006Dm006Dmm006D = 88;
      int i = b006Dm006D006Dm006Dmm006D();
      switch (i * (i + b006D006D006D006Dm006Dmm006D) % bmmmm006D006Dmm006D())
      {
      default: 
        if ((b006Dmm006Dm006Dmm006D + b006D006D006D006Dm006Dmm006D) * b006Dmm006Dm006Dmm006D % bmmmm006D006Dmm006D() != bm006Dm006Dm006Dmm006D)
        {
          b006Dmm006Dm006Dmm006D = 20;
          bm006Dm006Dm006Dmm006D = b006Dm006D006Dm006Dmm006D();
        }
        b006Dmm006Dm006Dmm006D = b006Dm006D006Dm006Dmm006D();
        bm006Dm006Dm006Dmm006D = b006Dm006D006Dm006Dmm006D();
      }
    }
    navigateToActivity(StandingOrderDetailsActivity.class);
  }
  
  public void navigateToStandingOrdersActivity()
  {
    int i = b006Dmm006Dm006Dmm006D;
    switch (i * (i + b006D006D006D006Dm006Dmm006D) % bmm006D006Dm006Dmm006D)
    {
    default: 
      b006Dmm006Dm006Dmm006D = b006Dm006D006Dm006Dmm006D();
      bm006Dm006Dm006Dmm006D = b006Dm006D006Dm006Dmm006D();
      if ((b006Dmm006Dm006Dmm006D + b006D006D006D006Dm006Dmm006D) * b006Dmm006Dm006Dmm006D % bmm006D006Dm006Dmm006D != bm006D006D006Dm006Dmm006D())
      {
        b006Dmm006Dm006Dmm006D = b006Dm006D006Dm006Dmm006D();
        bm006Dm006Dm006Dmm006D = 36;
      }
      if ((b006Dmm006Dm006Dmm006D + b006D006D006D006Dm006Dmm006D) * b006Dmm006Dm006Dmm006D % bmm006D006Dm006Dmm006D != bm006Dm006Dm006Dmm006D)
      {
        b006Dmm006Dm006Dmm006D = 77;
        bm006Dm006Dm006Dmm006D = b006Dm006D006Dm006Dmm006D();
      }
      break;
    }
    navigateToActivity(StandingOrdersActivity.class);
    try
    {
      for (;;)
      {
        null.length();
      }
      return;
    }
    catch (Exception localException)
    {
      b006Dmm006Dm006Dmm006D = b006Dm006D006Dm006Dmm006D();
    }
  }
  
  public void onBackPressed()
  {
    if ((b006Dmm006Dm006Dmm006D + b006D006D006D006Dm006Dmm006D) * b006Dmm006Dm006Dmm006D % bmm006D006Dm006Dmm006D != bm006Dm006Dm006Dmm006D)
    {
      b006Dmm006Dm006Dmm006D = 64;
      bm006Dm006Dm006Dmm006D = b006Dm006D006Dm006Dmm006D();
    }
    llvvll.vlvvll localVlvvll;
    Method localMethod;
    Object[] arrayOfObject;
    if (!this.isUiDisabled)
    {
      super.onBackPressed();
      localVlvvll = this.presenter;
      localMethod = llvvll.vlvvll.class.getMethod(uxxxxx.bb00620062bb0062b0062b0062("|\005\006MNUY\013RSZ^\020\021\022YZae]^ei", '\r', '\001'), new Class[0]);
      arrayOfObject = new Object[0];
    }
    try
    {
      Object localObject = localMethod.invoke(localVlvvll, arrayOfObject);
      if (((Boolean)localObject).booleanValue()) {
        closeActivity();
      }
      TanModule localTanModule = this.tanModule;
      int i = b006Dmm006Dm006Dmm006D;
      switch (i * (i + b006D006D006D006Dm006Dmm006D) % bmm006D006Dm006Dmm006D)
      {
      default: 
        b006Dmm006Dm006Dmm006D = 76;
        bm006Dm006Dm006Dmm006D = b006Dm006D006Dm006Dmm006D();
        if ((b006Dmm006Dm006Dmm006D + b006D006D006D006Dm006Dmm006D) * b006Dmm006Dm006Dmm006D % bmm006D006Dm006Dmm006D != bm006Dm006Dm006Dmm006D)
        {
          b006Dmm006Dm006Dmm006D = 74;
          bm006Dm006Dm006Dmm006D = 28;
        }
        break;
      }
      if (localTanModule.isAnyTanMethodAvailable())
      {
        finish();
        return;
      }
      if ((b006Dmm006Dm006Dmm006D + b006D006Dm006Dm006Dmm006D()) * b006Dmm006Dm006Dmm006D % bmm006D006Dm006Dmm006D != bm006Dm006Dm006Dmm006D)
      {
        b006Dmm006Dm006Dmm006D = b006Dm006D006Dm006Dmm006D();
        bm006Dm006Dm006Dmm006D = b006Dm006D006Dm006Dmm006D();
      }
      closeActivity();
      return;
    }
    catch (InvocationTargetException localInvocationTargetException)
    {
      throw localInvocationTargetException.getCause();
    }
  }
  
  /* Error */
  public void onCreate(Bundle paramBundle)
  {
    // Byte code:
    //   0: aload_0
    //   1: invokevirtual 632	com/db/pwcc/dbmobile/transfer/standingorder/confirm/StandingOrderConfirmationActivity:getApplicationContext	()Landroid/content/Context;
    //   4: astore_2
    //   5: ldc_w 634
    //   8: ldc_w 636
    //   11: sipush 223
    //   14: sipush 212
    //   17: iconst_0
    //   18: invokestatic 186	xxxxxx/uxxxxx:bbbb0062b0062b0062b0062	(Ljava/lang/String;CCC)Ljava/lang/String;
    //   21: iconst_1
    //   22: anewarray 99	java/lang/Class
    //   25: dup
    //   26: iconst_0
    //   27: ldc_w 638
    //   30: aastore
    //   31: invokevirtual 113	java/lang/Class:getMethod	(Ljava/lang/String;[Ljava/lang/Class;)Ljava/lang/reflect/Method;
    //   34: astore_3
    //   35: iconst_1
    //   36: anewarray 115	java/lang/Object
    //   39: dup
    //   40: iconst_0
    //   41: aload_2
    //   42: aastore
    //   43: astore 4
    //   45: aload_3
    //   46: aconst_null
    //   47: aload 4
    //   49: invokevirtual 127	java/lang/reflect/Method:invoke	(Ljava/lang/Object;[Ljava/lang/Object;)Ljava/lang/Object;
    //   52: pop
    //   53: aload_0
    //   54: invokevirtual 632	com/db/pwcc/dbmobile/transfer/standingorder/confirm/StandingOrderConfirmationActivity:getApplicationContext	()Landroid/content/Context;
    //   57: astore 7
    //   59: ldc_w 640
    //   62: ldc_w 642
    //   65: bipush 15
    //   67: sipush 201
    //   70: iconst_2
    //   71: invokestatic 186	xxxxxx/uxxxxx:bbbb0062b0062b0062b0062	(Ljava/lang/String;CCC)Ljava/lang/String;
    //   74: iconst_1
    //   75: anewarray 99	java/lang/Class
    //   78: dup
    //   79: iconst_0
    //   80: ldc_w 638
    //   83: aastore
    //   84: invokevirtual 113	java/lang/Class:getMethod	(Ljava/lang/String;[Ljava/lang/Class;)Ljava/lang/reflect/Method;
    //   87: astore 8
    //   89: iconst_1
    //   90: anewarray 115	java/lang/Object
    //   93: dup
    //   94: iconst_0
    //   95: aload 7
    //   97: aastore
    //   98: astore 9
    //   100: aload 8
    //   102: aconst_null
    //   103: aload 9
    //   105: invokevirtual 127	java/lang/reflect/Method:invoke	(Ljava/lang/Object;[Ljava/lang/Object;)Ljava/lang/Object;
    //   108: pop
    //   109: aload_0
    //   110: invokevirtual 632	com/db/pwcc/dbmobile/transfer/standingorder/confirm/StandingOrderConfirmationActivity:getApplicationContext	()Landroid/content/Context;
    //   113: invokestatic 648	uuuuuu/uppupu:b0072r0072r00720072rr0072	(Landroid/content/Context;)V
    //   116: getstatic 71	com/db/pwcc/dbmobile/transfer/standingorder/confirm/StandingOrderConfirmationActivity:b006Dmm006Dm006Dmm006D	I
    //   119: getstatic 73	com/db/pwcc/dbmobile/transfer/standingorder/confirm/StandingOrderConfirmationActivity:b006D006D006D006Dm006Dmm006D	I
    //   122: iadd
    //   123: getstatic 71	com/db/pwcc/dbmobile/transfer/standingorder/confirm/StandingOrderConfirmationActivity:b006Dmm006Dm006Dmm006D	I
    //   126: imul
    //   127: invokestatic 148	com/db/pwcc/dbmobile/transfer/standingorder/confirm/StandingOrderConfirmationActivity:bmmmm006D006Dmm006D	()I
    //   130: irem
    //   131: getstatic 79	com/db/pwcc/dbmobile/transfer/standingorder/confirm/StandingOrderConfirmationActivity:bm006Dm006Dm006Dmm006D	I
    //   134: if_icmpeq +14 -> 148
    //   137: invokestatic 89	com/db/pwcc/dbmobile/transfer/standingorder/confirm/StandingOrderConfirmationActivity:b006Dm006D006Dm006Dmm006D	()I
    //   140: putstatic 71	com/db/pwcc/dbmobile/transfer/standingorder/confirm/StandingOrderConfirmationActivity:b006Dmm006Dm006Dmm006D	I
    //   143: bipush 58
    //   145: putstatic 79	com/db/pwcc/dbmobile/transfer/standingorder/confirm/StandingOrderConfirmationActivity:bm006Dm006Dm006Dmm006D	I
    //   148: aload_0
    //   149: aload_1
    //   150: invokespecial 650	com/db/pwcc/dbmobile/transfer/inputscreen/activities/ConfirmationActivity:onCreate	(Landroid/os/Bundle;)V
    //   153: aload_0
    //   154: invokestatic 656	uuuuuu/lklkkk:bi0069i0069iii00690069i	(Landroid/content/Context;)Luuuuuu/kklkkk;
    //   157: aload_0
    //   158: invokeinterface 662 2 0
    //   163: aload_0
    //   164: invokevirtual 424	com/db/pwcc/dbmobile/transfer/standingorder/confirm/StandingOrderConfirmationActivity:getIntent	()Landroid/content/Intent;
    //   167: astore 12
    //   169: ldc_w 664
    //   172: sipush 165
    //   175: bipush 58
    //   177: iconst_3
    //   178: invokestatic 186	xxxxxx/uxxxxx:bbbb0062b0062b0062b0062	(Ljava/lang/String;CCC)Ljava/lang/String;
    //   181: astore 13
    //   183: iconst_3
    //   184: anewarray 99	java/lang/Class
    //   187: astore 14
    //   189: aload 14
    //   191: iconst_0
    //   192: ldc 101
    //   194: aastore
    //   195: aload 14
    //   197: iconst_1
    //   198: getstatic 107	java/lang/Character:TYPE	Ljava/lang/Class;
    //   201: aastore
    //   202: aload 14
    //   204: iconst_2
    //   205: getstatic 107	java/lang/Character:TYPE	Ljava/lang/Class;
    //   208: aastore
    //   209: ldc 109
    //   211: aload 13
    //   213: aload 14
    //   215: invokevirtual 113	java/lang/Class:getMethod	(Ljava/lang/String;[Ljava/lang/Class;)Ljava/lang/reflect/Method;
    //   218: astore 15
    //   220: iconst_3
    //   221: anewarray 115	java/lang/Object
    //   224: astore 16
    //   226: aload 16
    //   228: iconst_0
    //   229: ldc_w 666
    //   232: aastore
    //   233: aload 16
    //   235: iconst_1
    //   236: bipush 87
    //   238: invokestatic 121	java/lang/Character:valueOf	(C)Ljava/lang/Character;
    //   241: aastore
    //   242: aload 16
    //   244: iconst_2
    //   245: iconst_5
    //   246: invokestatic 121	java/lang/Character:valueOf	(C)Ljava/lang/Character;
    //   249: aastore
    //   250: aload 15
    //   252: aconst_null
    //   253: aload 16
    //   255: invokevirtual 127	java/lang/reflect/Method:invoke	(Ljava/lang/Object;[Ljava/lang/Object;)Ljava/lang/Object;
    //   258: astore 18
    //   260: aload_0
    //   261: aload 12
    //   263: aload 18
    //   265: checkcast 101	java/lang/String
    //   268: invokevirtual 670	android/content/Intent:getSerializableExtra	(Ljava/lang/String;)Ljava/io/Serializable;
    //   271: checkcast 65	com/db/pwcc/dbmobile/transfer/standingorder/model/StandingOrderRequestResponse
    //   274: putfield 50	com/db/pwcc/dbmobile/transfer/standingorder/confirm/StandingOrderConfirmationActivity:standingOrderRequestResponse	Lcom/db/pwcc/dbmobile/transfer/standingorder/model/StandingOrderRequestResponse;
    //   277: aload_0
    //   278: invokevirtual 424	com/db/pwcc/dbmobile/transfer/standingorder/confirm/StandingOrderConfirmationActivity:getIntent	()Landroid/content/Intent;
    //   281: astore 19
    //   283: ldc_w 672
    //   286: sipush 166
    //   289: iconst_1
    //   290: invokestatic 97	xxxxxx/uxxxxx:bb00620062bb0062b0062b0062	(Ljava/lang/String;CC)Ljava/lang/String;
    //   293: astore 20
    //   295: iconst_3
    //   296: anewarray 99	java/lang/Class
    //   299: astore 21
    //   301: aload 21
    //   303: iconst_0
    //   304: ldc 101
    //   306: aastore
    //   307: aload 21
    //   309: iconst_1
    //   310: getstatic 107	java/lang/Character:TYPE	Ljava/lang/Class;
    //   313: aastore
    //   314: aload 21
    //   316: iconst_2
    //   317: getstatic 107	java/lang/Character:TYPE	Ljava/lang/Class;
    //   320: aastore
    //   321: ldc 109
    //   323: aload 20
    //   325: aload 21
    //   327: invokevirtual 113	java/lang/Class:getMethod	(Ljava/lang/String;[Ljava/lang/Class;)Ljava/lang/reflect/Method;
    //   330: astore 22
    //   332: iconst_3
    //   333: anewarray 115	java/lang/Object
    //   336: astore 23
    //   338: aload 23
    //   340: iconst_0
    //   341: ldc_w 674
    //   344: aastore
    //   345: aload 23
    //   347: iconst_1
    //   348: bipush 87
    //   350: invokestatic 121	java/lang/Character:valueOf	(C)Ljava/lang/Character;
    //   353: aastore
    //   354: aload 23
    //   356: iconst_2
    //   357: iconst_5
    //   358: invokestatic 121	java/lang/Character:valueOf	(C)Ljava/lang/Character;
    //   361: aastore
    //   362: aload 22
    //   364: aconst_null
    //   365: aload 23
    //   367: invokevirtual 127	java/lang/reflect/Method:invoke	(Ljava/lang/Object;[Ljava/lang/Object;)Ljava/lang/Object;
    //   370: astore 25
    //   372: aload_0
    //   373: aload 19
    //   375: aload 25
    //   377: checkcast 101	java/lang/String
    //   380: invokevirtual 678	android/content/Intent:getParcelableExtra	(Ljava/lang/String;)Landroid/os/Parcelable;
    //   383: checkcast 680	com/db/pwcc/dbmobile/model/tan/ChallengeResponse
    //   386: putfield 52	com/db/pwcc/dbmobile/transfer/standingorder/confirm/StandingOrderConfirmationActivity:challengeResponse	Lcom/db/pwcc/dbmobile/model/tan/ChallengeResponse;
    //   389: aload_0
    //   390: invokevirtual 424	com/db/pwcc/dbmobile/transfer/standingorder/confirm/StandingOrderConfirmationActivity:getIntent	()Landroid/content/Intent;
    //   393: astore 26
    //   395: getstatic 71	com/db/pwcc/dbmobile/transfer/standingorder/confirm/StandingOrderConfirmationActivity:b006Dmm006Dm006Dmm006D	I
    //   398: istore 27
    //   400: getstatic 71	com/db/pwcc/dbmobile/transfer/standingorder/confirm/StandingOrderConfirmationActivity:b006Dmm006Dm006Dmm006D	I
    //   403: getstatic 73	com/db/pwcc/dbmobile/transfer/standingorder/confirm/StandingOrderConfirmationActivity:b006D006D006D006Dm006Dmm006D	I
    //   406: iadd
    //   407: getstatic 71	com/db/pwcc/dbmobile/transfer/standingorder/confirm/StandingOrderConfirmationActivity:b006Dmm006Dm006Dmm006D	I
    //   410: imul
    //   411: getstatic 75	com/db/pwcc/dbmobile/transfer/standingorder/confirm/StandingOrderConfirmationActivity:bmm006D006Dm006Dmm006D	I
    //   414: irem
    //   415: getstatic 79	com/db/pwcc/dbmobile/transfer/standingorder/confirm/StandingOrderConfirmationActivity:bm006Dm006Dm006Dmm006D	I
    //   418: if_icmpeq +15 -> 433
    //   421: invokestatic 89	com/db/pwcc/dbmobile/transfer/standingorder/confirm/StandingOrderConfirmationActivity:b006Dm006D006Dm006Dmm006D	()I
    //   424: putstatic 71	com/db/pwcc/dbmobile/transfer/standingorder/confirm/StandingOrderConfirmationActivity:b006Dmm006Dm006Dmm006D	I
    //   427: invokestatic 89	com/db/pwcc/dbmobile/transfer/standingorder/confirm/StandingOrderConfirmationActivity:b006Dm006D006Dm006Dmm006D	()I
    //   430: putstatic 79	com/db/pwcc/dbmobile/transfer/standingorder/confirm/StandingOrderConfirmationActivity:bm006Dm006Dm006Dmm006D	I
    //   433: iload 27
    //   435: getstatic 73	com/db/pwcc/dbmobile/transfer/standingorder/confirm/StandingOrderConfirmationActivity:b006D006D006D006Dm006Dmm006D	I
    //   438: iadd
    //   439: getstatic 71	com/db/pwcc/dbmobile/transfer/standingorder/confirm/StandingOrderConfirmationActivity:b006Dmm006Dm006Dmm006D	I
    //   442: imul
    //   443: istore 28
    //   445: getstatic 71	com/db/pwcc/dbmobile/transfer/standingorder/confirm/StandingOrderConfirmationActivity:b006Dmm006Dm006Dmm006D	I
    //   448: istore 29
    //   450: iload 29
    //   452: iload 29
    //   454: getstatic 73	com/db/pwcc/dbmobile/transfer/standingorder/confirm/StandingOrderConfirmationActivity:b006D006D006D006Dm006Dmm006D	I
    //   457: iadd
    //   458: imul
    //   459: invokestatic 148	com/db/pwcc/dbmobile/transfer/standingorder/confirm/StandingOrderConfirmationActivity:bmmmm006D006Dmm006D	()I
    //   462: irem
    //   463: tableswitch	default:+17->480, 0:+28->491
    //   480: invokestatic 89	com/db/pwcc/dbmobile/transfer/standingorder/confirm/StandingOrderConfirmationActivity:b006Dm006D006Dm006Dmm006D	()I
    //   483: putstatic 71	com/db/pwcc/dbmobile/transfer/standingorder/confirm/StandingOrderConfirmationActivity:b006Dmm006Dm006Dmm006D	I
    //   486: bipush 83
    //   488: putstatic 79	com/db/pwcc/dbmobile/transfer/standingorder/confirm/StandingOrderConfirmationActivity:bm006Dm006Dm006Dmm006D	I
    //   491: iload 28
    //   493: getstatic 75	com/db/pwcc/dbmobile/transfer/standingorder/confirm/StandingOrderConfirmationActivity:bmm006D006Dm006Dmm006D	I
    //   496: irem
    //   497: getstatic 79	com/db/pwcc/dbmobile/transfer/standingorder/confirm/StandingOrderConfirmationActivity:bm006Dm006Dm006Dmm006D	I
    //   500: if_icmpeq +14 -> 514
    //   503: invokestatic 89	com/db/pwcc/dbmobile/transfer/standingorder/confirm/StandingOrderConfirmationActivity:b006Dm006D006Dm006Dmm006D	()I
    //   506: putstatic 71	com/db/pwcc/dbmobile/transfer/standingorder/confirm/StandingOrderConfirmationActivity:b006Dmm006Dm006Dmm006D	I
    //   509: bipush 25
    //   511: putstatic 79	com/db/pwcc/dbmobile/transfer/standingorder/confirm/StandingOrderConfirmationActivity:bm006Dm006Dm006Dmm006D	I
    //   514: ldc_w 682
    //   517: bipush 13
    //   519: iconst_1
    //   520: invokestatic 97	xxxxxx/uxxxxx:bb00620062bb0062b0062b0062	(Ljava/lang/String;CC)Ljava/lang/String;
    //   523: astore 30
    //   525: iconst_3
    //   526: anewarray 99	java/lang/Class
    //   529: astore 31
    //   531: aload 31
    //   533: iconst_0
    //   534: ldc 101
    //   536: aastore
    //   537: aload 31
    //   539: iconst_1
    //   540: getstatic 107	java/lang/Character:TYPE	Ljava/lang/Class;
    //   543: aastore
    //   544: aload 31
    //   546: iconst_2
    //   547: getstatic 107	java/lang/Character:TYPE	Ljava/lang/Class;
    //   550: aastore
    //   551: ldc 109
    //   553: aload 30
    //   555: aload 31
    //   557: invokevirtual 113	java/lang/Class:getMethod	(Ljava/lang/String;[Ljava/lang/Class;)Ljava/lang/reflect/Method;
    //   560: astore 32
    //   562: iconst_3
    //   563: anewarray 115	java/lang/Object
    //   566: astore 33
    //   568: aload 33
    //   570: iconst_0
    //   571: ldc_w 684
    //   574: aastore
    //   575: aload 33
    //   577: iconst_1
    //   578: bipush 46
    //   580: invokestatic 121	java/lang/Character:valueOf	(C)Ljava/lang/Character;
    //   583: aastore
    //   584: aload 33
    //   586: iconst_2
    //   587: iconst_5
    //   588: invokestatic 121	java/lang/Character:valueOf	(C)Ljava/lang/Character;
    //   591: aastore
    //   592: aload 32
    //   594: aconst_null
    //   595: aload 33
    //   597: invokevirtual 127	java/lang/reflect/Method:invoke	(Ljava/lang/Object;[Ljava/lang/Object;)Ljava/lang/Object;
    //   600: astore 35
    //   602: aload_0
    //   603: aload 26
    //   605: aload 35
    //   607: checkcast 101	java/lang/String
    //   610: invokevirtual 678	android/content/Intent:getParcelableExtra	(Ljava/lang/String;)Landroid/os/Parcelable;
    //   613: checkcast 350	com/db/pwcc/dbmobile/transfer/standingorder/model/StandingOrderTemplate
    //   616: putfield 54	com/db/pwcc/dbmobile/transfer/standingorder/confirm/StandingOrderConfirmationActivity:standingOrderTemplate	Lcom/db/pwcc/dbmobile/transfer/standingorder/model/StandingOrderTemplate;
    //   619: aload_0
    //   620: new 686	uuuuuu/vvvvll
    //   623: dup
    //   624: invokespecial 687	uuuuuu/vvvvll:<init>	()V
    //   627: putfield 48	com/db/pwcc/dbmobile/transfer/standingorder/confirm/StandingOrderConfirmationActivity:presenter	Luuuuuu/llvvll$vlvvll;
    //   630: aload_0
    //   631: getfield 48	com/db/pwcc/dbmobile/transfer/standingorder/confirm/StandingOrderConfirmationActivity:presenter	Luuuuuu/llvvll$vlvvll;
    //   634: astore 36
    //   636: ldc_w 567
    //   639: ldc_w 689
    //   642: sipush 167
    //   645: bipush 118
    //   647: iconst_2
    //   648: invokestatic 186	xxxxxx/uxxxxx:bbbb0062b0062b0062b0062	(Ljava/lang/String;CCC)Ljava/lang/String;
    //   651: iconst_1
    //   652: anewarray 99	java/lang/Class
    //   655: dup
    //   656: iconst_0
    //   657: ldc 6
    //   659: aastore
    //   660: invokevirtual 113	java/lang/Class:getMethod	(Ljava/lang/String;[Ljava/lang/Class;)Ljava/lang/reflect/Method;
    //   663: astore 37
    //   665: iconst_1
    //   666: anewarray 115	java/lang/Object
    //   669: dup
    //   670: iconst_0
    //   671: aload_0
    //   672: aastore
    //   673: astore 38
    //   675: aload 37
    //   677: aload 36
    //   679: aload 38
    //   681: invokevirtual 127	java/lang/reflect/Method:invoke	(Ljava/lang/Object;[Ljava/lang/Object;)Ljava/lang/Object;
    //   684: pop
    //   685: aload_0
    //   686: invokevirtual 690	com/db/pwcc/dbmobile/transfer/standingorder/confirm/StandingOrderConfirmationActivity:initView	()V
    //   689: aload_0
    //   690: invokevirtual 691	com/db/pwcc/dbmobile/transfer/standingorder/confirm/StandingOrderConfirmationActivity:initDbToolbar	()V
    //   693: return
    //   694: astore 5
    //   696: aload 5
    //   698: invokevirtual 135	java/lang/reflect/InvocationTargetException:getCause	()Ljava/lang/Throwable;
    //   701: athrow
    //   702: astore 10
    //   704: aload 10
    //   706: invokevirtual 135	java/lang/reflect/InvocationTargetException:getCause	()Ljava/lang/Throwable;
    //   709: athrow
    //   710: astore 24
    //   712: aload 24
    //   714: invokevirtual 135	java/lang/reflect/InvocationTargetException:getCause	()Ljava/lang/Throwable;
    //   717: athrow
    //   718: astore 17
    //   720: aload 17
    //   722: invokevirtual 135	java/lang/reflect/InvocationTargetException:getCause	()Ljava/lang/Throwable;
    //   725: athrow
    //   726: astore 34
    //   728: aload 34
    //   730: invokevirtual 135	java/lang/reflect/InvocationTargetException:getCause	()Ljava/lang/Throwable;
    //   733: athrow
    //   734: astore 39
    //   736: aload 39
    //   738: invokevirtual 135	java/lang/reflect/InvocationTargetException:getCause	()Ljava/lang/Throwable;
    //   741: athrow
    // Local variable table:
    //   start	length	slot	name	signature
    //   0	742	0	this	StandingOrderConfirmationActivity
    //   0	742	1	paramBundle	Bundle
    //   4	38	2	localContext1	Context
    //   34	12	3	localMethod1	Method
    //   43	5	4	arrayOfObject1	Object[]
    //   694	3	5	localInvocationTargetException1	InvocationTargetException
    //   57	39	7	localContext2	Context
    //   87	14	8	localMethod2	Method
    //   98	6	9	arrayOfObject2	Object[]
    //   702	3	10	localInvocationTargetException2	InvocationTargetException
    //   167	95	12	localIntent1	Intent
    //   181	31	13	str1	String
    //   187	27	14	arrayOfClass1	Class[]
    //   218	33	15	localMethod3	Method
    //   224	30	16	arrayOfObject3	Object[]
    //   718	3	17	localInvocationTargetException3	InvocationTargetException
    //   258	6	18	localObject1	Object
    //   281	93	19	localIntent2	Intent
    //   293	31	20	str2	String
    //   299	27	21	arrayOfClass2	Class[]
    //   330	33	22	localMethod4	Method
    //   336	30	23	arrayOfObject4	Object[]
    //   710	3	24	localInvocationTargetException4	InvocationTargetException
    //   370	6	25	localObject2	Object
    //   393	211	26	localIntent3	Intent
    //   398	41	27	i	int
    //   443	54	28	j	int
    //   448	11	29	k	int
    //   523	31	30	str3	String
    //   529	27	31	arrayOfClass3	Class[]
    //   560	33	32	localMethod5	Method
    //   566	30	33	arrayOfObject5	Object[]
    //   726	3	34	localInvocationTargetException5	InvocationTargetException
    //   600	6	35	localObject3	Object
    //   634	44	36	localVlvvll	llvvll.vlvvll
    //   663	13	37	localMethod6	Method
    //   673	7	38	arrayOfObject6	Object[]
    //   734	3	39	localInvocationTargetException6	InvocationTargetException
    // Exception table:
    //   from	to	target	type
    //   45	53	694	java/lang/reflect/InvocationTargetException
    //   100	109	702	java/lang/reflect/InvocationTargetException
    //   362	372	710	java/lang/reflect/InvocationTargetException
    //   250	260	718	java/lang/reflect/InvocationTargetException
    //   592	602	726	java/lang/reflect/InvocationTargetException
    //   675	685	734	java/lang/reflect/InvocationTargetException
  }
  
  public void onRestoreInstanceState(Bundle paramBundle)
  {
    super.onRestoreInstanceState(paramBundle);
    String str1 = uxxxxx.bbbb0062b0062b0062b0062("\0364567pqyztu}~@yz\003\004}~\007\bI", ',', '', '\003');
    Class[] arrayOfClass1 = new Class[3];
    arrayOfClass1[0] = String.class;
    arrayOfClass1[1] = Character.TYPE;
    arrayOfClass1[2] = Character.TYPE;
    Method localMethod1 = ppphhp.class.getMethod(str1, arrayOfClass1);
    Object[] arrayOfObject1 = new Object[3];
    arrayOfObject1[0] = "\035*)j\"!m19&'r*)58,482{CB2@F::H\005,\032(:),\"4,&A'-863)B=J>2AD<E";
    arrayOfObject1[1] = Character.valueOf('\023');
    arrayOfObject1[2] = Character.valueOf('\000');
    DbError localDbError;
    try
    {
      Object localObject1 = localMethod1.invoke(null, arrayOfObject1);
      Method localMethod2;
      Object[] arrayOfObject2;
      if (paramBundle.getBoolean((String)localObject1))
      {
        String str2 = uxxxxx.bb00620062bb0062b0062b0062(" 6opxy;<uv~yz\003\004E~\b\t\003\004\f\rN", '¼', '\002');
        Class[] arrayOfClass2 = new Class[4];
        arrayOfClass2[0] = String.class;
        arrayOfClass2[1] = Character.TYPE;
        arrayOfClass2[2] = Character.TYPE;
        arrayOfClass2[3] = Character.TYPE;
        localMethod2 = ppphhp.class.getMethod(str2, arrayOfClass2);
        arrayOfObject2 = new Object[4];
        arrayOfObject2[0] = "`ml.ed1t|ij6mlx{ow{u?\007\006u\004\n}}\fHo]k}loewoi\005jp{yvl\006\001\016t\003\004\002\006";
        arrayOfObject2[1] = Character.valueOf('Q');
        arrayOfObject2[2] = Character.valueOf('ª');
        arrayOfObject2[3] = Character.valueOf('\003');
      }
      Object localObject2;
      int j;
      localAuthorizationStatus = xxsxsx.b006B006B006B006Bk006Bk006B006B006B(localDbError);
    }
    catch (InvocationTargetException localInvocationTargetException1)
    {
      try
      {
        localObject2 = localMethod2.invoke(null, arrayOfObject2);
        localDbError = (DbError)paramBundle.getSerializable((String)localObject2);
        if (localDbError != null) {
          break label430;
        }
        this.tanModule.showSuccessLayoutView();
        j = b006Dm006D006Dm006Dmm006D();
        switch (j * (j + b006D006Dm006Dm006Dmm006D()) % bmm006D006Dm006Dmm006D)
        {
        default: 
          b006Dmm006Dm006Dmm006D = 69;
          bm006Dm006Dm006Dmm006D = 68;
        }
        showShareableToolbar();
        return;
      }
      catch (InvocationTargetException localInvocationTargetException2)
      {
        throw localInvocationTargetException2.getCause();
      }
      localInvocationTargetException1 = localInvocationTargetException1;
      throw localInvocationTargetException1.getCause();
    }
    label430:
    do
    {
      AuthorizationStatus localAuthorizationStatus;
      if ((b006Dmm006Dm006Dmm006D + b006D006D006D006Dm006Dmm006D) * b006Dmm006Dm006Dmm006D % bmm006D006Dm006Dmm006D != bm006Dm006Dm006Dmm006D)
      {
        b006Dmm006Dm006Dmm006D = b006Dm006D006Dm006Dmm006D();
        bm006Dm006Dm006Dmm006D = 90;
      }
      this.tanModule.showErrorLayoutView(localAuthorizationStatus);
      int i = b006Dmm006Dm006Dmm006D;
      switch (i * (i + b006D006D006D006Dm006Dmm006D) % bmmmm006D006Dmm006D())
      {
      }
      b006Dmm006Dm006Dmm006D = b006Dm006D006Dm006Dmm006D();
      bm006Dm006Dm006Dmm006D = b006Dm006D006Dm006Dmm006D();
      if ((b006Dmm006Dm006Dmm006D + b006D006D006D006Dm006Dmm006D) * b006Dmm006Dm006Dmm006D % bmm006D006Dm006Dmm006D == bm006Dm006Dm006Dmm006D) {
        break;
      }
      b006Dmm006Dm006Dmm006D = b006Dm006D006Dm006Dmm006D();
      bm006Dm006Dm006Dmm006D = b006Dm006D006Dm006Dmm006D();
      return;
    } while (!xxsxsx.bkk006Bk006B006Bk006B006B006B(localDbError));
    ((kkkklk)this.presenter).onTransactionAuthenticationFailure(R.string.check_internet_connection);
  }
  
  /* Error */
  public void onSaveInstanceState(Bundle paramBundle)
  {
    // Byte code:
    //   0: getstatic 71	com/db/pwcc/dbmobile/transfer/standingorder/confirm/StandingOrderConfirmationActivity:b006Dmm006Dm006Dmm006D	I
    //   3: getstatic 73	com/db/pwcc/dbmobile/transfer/standingorder/confirm/StandingOrderConfirmationActivity:b006D006D006D006Dm006Dmm006D	I
    //   6: iadd
    //   7: getstatic 71	com/db/pwcc/dbmobile/transfer/standingorder/confirm/StandingOrderConfirmationActivity:b006Dmm006Dm006Dmm006D	I
    //   10: imul
    //   11: getstatic 75	com/db/pwcc/dbmobile/transfer/standingorder/confirm/StandingOrderConfirmationActivity:bmm006D006Dm006Dmm006D	I
    //   14: irem
    //   15: getstatic 79	com/db/pwcc/dbmobile/transfer/standingorder/confirm/StandingOrderConfirmationActivity:bm006Dm006Dm006Dmm006D	I
    //   18: if_icmpeq +91 -> 109
    //   21: getstatic 71	com/db/pwcc/dbmobile/transfer/standingorder/confirm/StandingOrderConfirmationActivity:b006Dmm006Dm006Dmm006D	I
    //   24: istore 20
    //   26: iload 20
    //   28: iload 20
    //   30: getstatic 73	com/db/pwcc/dbmobile/transfer/standingorder/confirm/StandingOrderConfirmationActivity:b006D006D006D006Dm006Dmm006D	I
    //   33: iadd
    //   34: imul
    //   35: getstatic 75	com/db/pwcc/dbmobile/transfer/standingorder/confirm/StandingOrderConfirmationActivity:bmm006D006Dm006Dmm006D	I
    //   38: irem
    //   39: tableswitch	default:+17->56, 0:+27->66
    //   56: bipush 14
    //   58: putstatic 71	com/db/pwcc/dbmobile/transfer/standingorder/confirm/StandingOrderConfirmationActivity:b006Dmm006Dm006Dmm006D	I
    //   61: bipush 67
    //   63: putstatic 79	com/db/pwcc/dbmobile/transfer/standingorder/confirm/StandingOrderConfirmationActivity:bm006Dm006Dm006Dmm006D	I
    //   66: bipush 35
    //   68: putstatic 71	com/db/pwcc/dbmobile/transfer/standingorder/confirm/StandingOrderConfirmationActivity:b006Dmm006Dm006Dmm006D	I
    //   71: invokestatic 89	com/db/pwcc/dbmobile/transfer/standingorder/confirm/StandingOrderConfirmationActivity:b006Dm006D006Dm006Dmm006D	()I
    //   74: putstatic 79	com/db/pwcc/dbmobile/transfer/standingorder/confirm/StandingOrderConfirmationActivity:bm006Dm006Dm006Dmm006D	I
    //   77: invokestatic 89	com/db/pwcc/dbmobile/transfer/standingorder/confirm/StandingOrderConfirmationActivity:b006Dm006D006Dm006Dmm006D	()I
    //   80: getstatic 73	com/db/pwcc/dbmobile/transfer/standingorder/confirm/StandingOrderConfirmationActivity:b006D006D006D006Dm006Dmm006D	I
    //   83: iadd
    //   84: invokestatic 89	com/db/pwcc/dbmobile/transfer/standingorder/confirm/StandingOrderConfirmationActivity:b006Dm006D006Dm006Dmm006D	()I
    //   87: imul
    //   88: getstatic 75	com/db/pwcc/dbmobile/transfer/standingorder/confirm/StandingOrderConfirmationActivity:bmm006D006Dm006Dmm006D	I
    //   91: irem
    //   92: getstatic 79	com/db/pwcc/dbmobile/transfer/standingorder/confirm/StandingOrderConfirmationActivity:bm006Dm006Dm006Dmm006D	I
    //   95: if_icmpeq +14 -> 109
    //   98: bipush 31
    //   100: putstatic 71	com/db/pwcc/dbmobile/transfer/standingorder/confirm/StandingOrderConfirmationActivity:b006Dmm006Dm006Dmm006D	I
    //   103: invokestatic 89	com/db/pwcc/dbmobile/transfer/standingorder/confirm/StandingOrderConfirmationActivity:b006Dm006D006Dm006Dmm006D	()I
    //   106: putstatic 79	com/db/pwcc/dbmobile/transfer/standingorder/confirm/StandingOrderConfirmationActivity:bm006Dm006Dm006Dmm006D	I
    //   109: ldc_w 739
    //   112: sipush 160
    //   115: bipush 120
    //   117: iconst_2
    //   118: invokestatic 186	xxxxxx/uxxxxx:bbbb0062b0062b0062b0062	(Ljava/lang/String;CCC)Ljava/lang/String;
    //   121: astore_2
    //   122: iconst_4
    //   123: anewarray 99	java/lang/Class
    //   126: astore_3
    //   127: aload_3
    //   128: iconst_0
    //   129: ldc 101
    //   131: aastore
    //   132: aload_3
    //   133: iconst_1
    //   134: getstatic 107	java/lang/Character:TYPE	Ljava/lang/Class;
    //   137: aastore
    //   138: aload_3
    //   139: iconst_2
    //   140: getstatic 107	java/lang/Character:TYPE	Ljava/lang/Class;
    //   143: aastore
    //   144: aload_3
    //   145: iconst_3
    //   146: getstatic 107	java/lang/Character:TYPE	Ljava/lang/Class;
    //   149: aastore
    //   150: ldc 109
    //   152: aload_2
    //   153: aload_3
    //   154: invokevirtual 113	java/lang/Class:getMethod	(Ljava/lang/String;[Ljava/lang/Class;)Ljava/lang/reflect/Method;
    //   157: astore 4
    //   159: iconst_4
    //   160: anewarray 115	java/lang/Object
    //   163: astore 5
    //   165: aload 5
    //   167: iconst_0
    //   168: ldc_w 698
    //   171: aastore
    //   172: aload 5
    //   174: iconst_1
    //   175: bipush 56
    //   177: invokestatic 121	java/lang/Character:valueOf	(C)Ljava/lang/Character;
    //   180: aastore
    //   181: aload 5
    //   183: iconst_2
    //   184: sipush 128
    //   187: invokestatic 121	java/lang/Character:valueOf	(C)Ljava/lang/Character;
    //   190: aastore
    //   191: aload 5
    //   193: iconst_3
    //   194: iconst_3
    //   195: invokestatic 121	java/lang/Character:valueOf	(C)Ljava/lang/Character;
    //   198: aastore
    //   199: aload 4
    //   201: aconst_null
    //   202: aload 5
    //   204: invokevirtual 127	java/lang/reflect/Method:invoke	(Ljava/lang/Object;[Ljava/lang/Object;)Ljava/lang/Object;
    //   207: astore 7
    //   209: aload 7
    //   211: checkcast 101	java/lang/String
    //   214: astore 8
    //   216: invokestatic 89	com/db/pwcc/dbmobile/transfer/standingorder/confirm/StandingOrderConfirmationActivity:b006Dm006D006Dm006Dmm006D	()I
    //   219: getstatic 73	com/db/pwcc/dbmobile/transfer/standingorder/confirm/StandingOrderConfirmationActivity:b006D006D006D006Dm006Dmm006D	I
    //   222: iadd
    //   223: invokestatic 89	com/db/pwcc/dbmobile/transfer/standingorder/confirm/StandingOrderConfirmationActivity:b006Dm006D006Dm006Dmm006D	()I
    //   226: imul
    //   227: invokestatic 148	com/db/pwcc/dbmobile/transfer/standingorder/confirm/StandingOrderConfirmationActivity:bmmmm006D006Dmm006D	()I
    //   230: irem
    //   231: getstatic 79	com/db/pwcc/dbmobile/transfer/standingorder/confirm/StandingOrderConfirmationActivity:bm006Dm006Dm006Dmm006D	I
    //   234: if_icmpeq +14 -> 248
    //   237: bipush 72
    //   239: putstatic 71	com/db/pwcc/dbmobile/transfer/standingorder/confirm/StandingOrderConfirmationActivity:b006Dmm006Dm006Dmm006D	I
    //   242: invokestatic 89	com/db/pwcc/dbmobile/transfer/standingorder/confirm/StandingOrderConfirmationActivity:b006Dm006D006Dm006Dmm006D	()I
    //   245: putstatic 79	com/db/pwcc/dbmobile/transfer/standingorder/confirm/StandingOrderConfirmationActivity:bm006Dm006Dm006Dmm006D	I
    //   248: aload_0
    //   249: getfield 48	com/db/pwcc/dbmobile/transfer/standingorder/confirm/StandingOrderConfirmationActivity:presenter	Luuuuuu/llvvll$vlvvll;
    //   252: astore 9
    //   254: ldc_w 567
    //   257: ldc_w 741
    //   260: bipush 56
    //   262: sipush 148
    //   265: iconst_3
    //   266: invokestatic 186	xxxxxx/uxxxxx:bbbb0062b0062b0062b0062	(Ljava/lang/String;CCC)Ljava/lang/String;
    //   269: iconst_0
    //   270: anewarray 99	java/lang/Class
    //   273: invokevirtual 113	java/lang/Class:getMethod	(Ljava/lang/String;[Ljava/lang/Class;)Ljava/lang/reflect/Method;
    //   276: astore 10
    //   278: iconst_0
    //   279: anewarray 115	java/lang/Object
    //   282: astore 11
    //   284: aload 10
    //   286: aload 9
    //   288: aload 11
    //   290: invokevirtual 127	java/lang/reflect/Method:invoke	(Ljava/lang/Object;[Ljava/lang/Object;)Ljava/lang/Object;
    //   293: astore 13
    //   295: aload_1
    //   296: aload 8
    //   298: aload 13
    //   300: checkcast 618	java/lang/Boolean
    //   303: invokevirtual 621	java/lang/Boolean:booleanValue	()Z
    //   306: invokevirtual 745	android/os/Bundle:putBoolean	(Ljava/lang/String;Z)V
    //   309: ldc_w 544
    //   312: sipush 180
    //   315: iconst_1
    //   316: invokestatic 97	xxxxxx/uxxxxx:bb00620062bb0062b0062b0062	(Ljava/lang/String;CC)Ljava/lang/String;
    //   319: astore 14
    //   321: iconst_3
    //   322: anewarray 99	java/lang/Class
    //   325: astore 15
    //   327: aload 15
    //   329: iconst_0
    //   330: ldc 101
    //   332: aastore
    //   333: aload 15
    //   335: iconst_1
    //   336: getstatic 107	java/lang/Character:TYPE	Ljava/lang/Class;
    //   339: aastore
    //   340: aload 15
    //   342: iconst_2
    //   343: getstatic 107	java/lang/Character:TYPE	Ljava/lang/Class;
    //   346: aastore
    //   347: ldc 109
    //   349: aload 14
    //   351: aload 15
    //   353: invokevirtual 113	java/lang/Class:getMethod	(Ljava/lang/String;[Ljava/lang/Class;)Ljava/lang/reflect/Method;
    //   356: astore 16
    //   358: iconst_3
    //   359: anewarray 115	java/lang/Object
    //   362: astore 17
    //   364: aload 17
    //   366: iconst_0
    //   367: ldc_w 747
    //   370: aastore
    //   371: aload 17
    //   373: iconst_1
    //   374: sipush 247
    //   377: invokestatic 121	java/lang/Character:valueOf	(C)Ljava/lang/Character;
    //   380: aastore
    //   381: aload 17
    //   383: iconst_2
    //   384: iconst_2
    //   385: invokestatic 121	java/lang/Character:valueOf	(C)Ljava/lang/Character;
    //   388: aastore
    //   389: aload 16
    //   391: aconst_null
    //   392: aload 17
    //   394: invokevirtual 127	java/lang/reflect/Method:invoke	(Ljava/lang/Object;[Ljava/lang/Object;)Ljava/lang/Object;
    //   397: astore 19
    //   399: aload_1
    //   400: aload 19
    //   402: checkcast 101	java/lang/String
    //   405: aload_0
    //   406: getfield 48	com/db/pwcc/dbmobile/transfer/standingorder/confirm/StandingOrderConfirmationActivity:presenter	Luuuuuu/llvvll$vlvvll;
    //   409: invokeinterface 751 1 0
    //   414: invokevirtual 755	android/os/Bundle:putSerializable	(Ljava/lang/String;Ljava/io/Serializable;)V
    //   417: aload_0
    //   418: aload_1
    //   419: invokespecial 757	com/db/pwcc/dbmobile/transfer/inputscreen/activities/ConfirmationActivity:onSaveInstanceState	(Landroid/os/Bundle;)V
    //   422: return
    //   423: astore 6
    //   425: aload 6
    //   427: invokevirtual 135	java/lang/reflect/InvocationTargetException:getCause	()Ljava/lang/Throwable;
    //   430: athrow
    //   431: astore 18
    //   433: aload 18
    //   435: invokevirtual 135	java/lang/reflect/InvocationTargetException:getCause	()Ljava/lang/Throwable;
    //   438: athrow
    //   439: astore 12
    //   441: aload 12
    //   443: invokevirtual 135	java/lang/reflect/InvocationTargetException:getCause	()Ljava/lang/Throwable;
    //   446: athrow
    // Local variable table:
    //   start	length	slot	name	signature
    //   0	447	0	this	StandingOrderConfirmationActivity
    //   0	447	1	paramBundle	Bundle
    //   121	32	2	str1	String
    //   126	28	3	arrayOfClass1	Class[]
    //   157	43	4	localMethod1	Method
    //   163	40	5	arrayOfObject1	Object[]
    //   423	3	6	localInvocationTargetException1	InvocationTargetException
    //   207	3	7	localObject1	Object
    //   214	83	8	str2	String
    //   252	35	9	localVlvvll	llvvll.vlvvll
    //   276	9	10	localMethod2	Method
    //   282	7	11	arrayOfObject2	Object[]
    //   439	3	12	localInvocationTargetException2	InvocationTargetException
    //   293	6	13	localObject2	Object
    //   319	31	14	str3	String
    //   325	27	15	arrayOfClass2	Class[]
    //   356	34	16	localMethod3	Method
    //   362	31	17	arrayOfObject3	Object[]
    //   431	3	18	localInvocationTargetException3	InvocationTargetException
    //   397	4	19	localObject3	Object
    //   24	11	20	i	int
    // Exception table:
    //   from	to	target	type
    //   199	209	423	java/lang/reflect/InvocationTargetException
    //   389	399	431	java/lang/reflect/InvocationTargetException
    //   284	295	439	java/lang/reflect/InvocationTargetException
  }
  
  public void retrievePrincipalAccountDetails(String paramString)
  {
    if ((b006Dmm006Dm006Dmm006D + b006D006Dm006Dm006Dmm006D()) * b006Dmm006Dm006Dmm006D % bmm006D006Dm006Dmm006D != bm006D006D006Dm006Dmm006D())
    {
      if ((b006Dmm006Dm006Dmm006D + b006D006Dm006Dm006Dmm006D()) * b006Dmm006Dm006Dmm006D % bmm006D006Dm006Dmm006D != bm006Dm006Dm006Dmm006D)
      {
        b006Dmm006Dm006Dmm006D = 7;
        bm006Dm006Dm006Dmm006D = b006Dm006D006Dm006Dmm006D();
      }
      if ((b006Dmm006Dm006Dmm006D + b006D006D006D006Dm006Dmm006D) * b006Dmm006Dm006Dmm006D % bmm006D006Dm006Dmm006D != bm006Dm006Dm006Dmm006D)
      {
        b006Dmm006Dm006Dmm006D = 47;
        bm006Dm006Dm006Dmm006D = 1;
      }
      b006Dmm006Dm006Dmm006D = b006Dm006D006Dm006Dmm006D();
      bm006Dm006Dm006Dmm006D = b006Dm006D006Dm006Dmm006D();
    }
    int i = b006Dmm006Dm006Dmm006D;
    switch (i * (i + b006D006D006D006Dm006Dmm006D) % bmm006D006Dm006Dmm006D)
    {
    default: 
      b006Dmm006Dm006Dmm006D = b006Dm006D006Dm006Dmm006D();
      bm006Dm006Dm006Dmm006D = b006Dm006D006Dm006Dmm006D();
    }
    llvvll.vlvvll localVlvvll = this.presenter;
    Method localMethod = llvvll.vlvvll.class.getMethod(uxxxxx.bbbb0062b0062b0062b0062("6\003\002\007\t8}|\002\0043xw|~.-,qpuwmlqs", '\002', 'U', '\001'), new Class[] { String.class });
    Object[] arrayOfObject = { paramString };
    try
    {
      localMethod.invoke(localVlvvll, arrayOfObject);
      return;
    }
    catch (InvocationTargetException localInvocationTargetException)
    {
      throw localInvocationTargetException.getCause();
    }
  }
  
  public void setAccountName(String paramString)
  {
    int i = 5;
    if ((b006Dmm006Dm006Dmm006D + b006D006Dm006Dm006Dmm006D()) * b006Dmm006Dm006Dmm006D % bmmmm006D006Dmm006D() != bm006D006D006Dm006Dmm006D())
    {
      b006Dmm006Dm006Dmm006D = 14;
      bm006Dm006Dm006Dmm006D = b006Dm006D006Dm006Dmm006D();
    }
    try
    {
      for (;;)
      {
        i /= 0;
        if ((b006Dmm006Dm006Dmm006D + b006D006D006D006Dm006Dmm006D) * b006Dmm006Dm006Dmm006D % bmm006D006Dm006Dmm006D != bm006D006D006Dm006Dmm006D())
        {
          b006Dmm006Dm006Dmm006D = b006Dm006D006Dm006Dmm006D();
          bm006Dm006Dm006Dmm006D = b006Dm006D006Dm006Dmm006D();
          int j = b006Dmm006Dm006Dmm006D;
          switch (j * (j + b006D006D006D006Dm006Dmm006D) % bmm006D006Dm006Dmm006D)
          {
          }
          b006Dmm006Dm006Dmm006D = b006Dm006D006Dm006Dmm006D();
          bm006Dm006Dm006Dmm006D = b006Dm006D006Dm006Dmm006D();
        }
      }
      return;
    }
    catch (Exception localException)
    {
      b006Dmm006Dm006Dmm006D = b006Dm006D006Dm006Dmm006D();
      ((TextView)findViewById(R.id.confirmation_principalCurrentBalance)).setText(paramString);
    }
  }
  
  public void setPrincipalName(String paramString1, String paramString2)
  {
    int i = b006Dm006D006Dm006Dmm006D();
    int j = i * (i + b006D006Dm006Dm006Dmm006D());
    int k = bmm006D006Dm006Dmm006D;
    if ((b006Dmm006Dm006Dmm006D + b006D006D006D006Dm006Dmm006D) * b006Dmm006Dm006Dmm006D % bmm006D006Dm006Dmm006D != bm006Dm006Dm006Dmm006D)
    {
      b006Dmm006Dm006Dmm006D = b006Dm006D006Dm006Dmm006D();
      bm006Dm006Dm006Dmm006D = b006Dm006D006Dm006Dmm006D();
      int n = b006Dmm006Dm006Dmm006D;
      switch (n * (n + b006D006D006D006Dm006Dmm006D) % bmm006D006Dm006Dmm006D)
      {
      default: 
        b006Dmm006Dm006Dmm006D = 6;
        bm006Dm006Dm006Dmm006D = 87;
      }
    }
    switch (j % k)
    {
    default: 
      int m = b006Dmm006Dm006Dmm006D;
      switch (m * (m + b006D006Dm006Dm006Dmm006D()) % bmm006D006Dm006Dmm006D)
      {
      default: 
        b006Dmm006Dm006Dmm006D = 95;
        bm006Dm006Dm006Dmm006D = b006Dm006D006Dm006Dmm006D();
      }
      b006Dmm006Dm006Dmm006D = b006Dm006D006Dm006Dmm006D();
      bm006Dm006Dm006Dmm006D = 88;
    }
    TextView localTextView = (TextView)findViewById(R.id.confirmation_principalInitials);
    ((TextView)findViewById(R.id.confirmation_principalName)).setText(paramString1);
    localTextView.setText(paramString2);
  }
  
  /* Error */
  public void setTransactionData(StandingOrderRequestResponse paramStandingOrderRequestResponse)
  {
    // Byte code:
    //   0: aload_0
    //   1: getstatic 781	com/db/pwcc/dbmobile/transfer/R$id:confirmation_beneficiaryName	I
    //   4: invokevirtual 770	com/db/pwcc/dbmobile/transfer/standingorder/confirm/StandingOrderConfirmationActivity:findViewById	(I)Landroid/view/View;
    //   7: checkcast 264	android/widget/TextView
    //   10: astore_2
    //   11: aload_0
    //   12: getstatic 784	com/db/pwcc/dbmobile/transfer/R$id:confirmation_beneficiaryIban	I
    //   15: invokevirtual 770	com/db/pwcc/dbmobile/transfer/standingorder/confirm/StandingOrderConfirmationActivity:findViewById	(I)Landroid/view/View;
    //   18: checkcast 264	android/widget/TextView
    //   21: astore_3
    //   22: aload_0
    //   23: getstatic 787	com/db/pwcc/dbmobile/transfer/R$id:bic	I
    //   26: invokevirtual 770	com/db/pwcc/dbmobile/transfer/standingorder/confirm/StandingOrderConfirmationActivity:findViewById	(I)Landroid/view/View;
    //   29: checkcast 264	android/widget/TextView
    //   32: astore 4
    //   34: aload_0
    //   35: getstatic 790	com/db/pwcc/dbmobile/transfer/R$id:description	I
    //   38: invokevirtual 770	com/db/pwcc/dbmobile/transfer/standingorder/confirm/StandingOrderConfirmationActivity:findViewById	(I)Landroid/view/View;
    //   41: checkcast 264	android/widget/TextView
    //   44: astore 5
    //   46: aload_0
    //   47: getstatic 793	com/db/pwcc/dbmobile/transfer/R$id:confirmation_reference	I
    //   50: invokevirtual 770	com/db/pwcc/dbmobile/transfer/standingorder/confirm/StandingOrderConfirmationActivity:findViewById	(I)Landroid/view/View;
    //   53: checkcast 264	android/widget/TextView
    //   56: astore 6
    //   58: aload_0
    //   59: getstatic 796	com/db/pwcc/dbmobile/transfer/R$id:amountValue	I
    //   62: invokevirtual 770	com/db/pwcc/dbmobile/transfer/standingorder/confirm/StandingOrderConfirmationActivity:findViewById	(I)Landroid/view/View;
    //   65: checkcast 264	android/widget/TextView
    //   68: astore 7
    //   70: aload_0
    //   71: getstatic 799	com/db/pwcc/dbmobile/transfer/R$id:confirmation_principalIban	I
    //   74: invokevirtual 770	com/db/pwcc/dbmobile/transfer/standingorder/confirm/StandingOrderConfirmationActivity:findViewById	(I)Landroid/view/View;
    //   77: checkcast 264	android/widget/TextView
    //   80: astore 8
    //   82: getstatic 71	com/db/pwcc/dbmobile/transfer/standingorder/confirm/StandingOrderConfirmationActivity:b006Dmm006Dm006Dmm006D	I
    //   85: istore 9
    //   87: iload 9
    //   89: iload 9
    //   91: getstatic 73	com/db/pwcc/dbmobile/transfer/standingorder/confirm/StandingOrderConfirmationActivity:b006D006D006D006Dm006Dmm006D	I
    //   94: iadd
    //   95: imul
    //   96: getstatic 75	com/db/pwcc/dbmobile/transfer/standingorder/confirm/StandingOrderConfirmationActivity:bmm006D006Dm006Dmm006D	I
    //   99: irem
    //   100: tableswitch	default:+20->120, 0:+31->131
    //   120: bipush 20
    //   122: putstatic 71	com/db/pwcc/dbmobile/transfer/standingorder/confirm/StandingOrderConfirmationActivity:b006Dmm006Dm006Dmm006D	I
    //   125: invokestatic 89	com/db/pwcc/dbmobile/transfer/standingorder/confirm/StandingOrderConfirmationActivity:b006Dm006D006Dm006Dmm006D	()I
    //   128: putstatic 79	com/db/pwcc/dbmobile/transfer/standingorder/confirm/StandingOrderConfirmationActivity:bm006Dm006Dm006Dmm006D	I
    //   131: aload_0
    //   132: getstatic 802	com/db/pwcc/dbmobile/transfer/R$id:confirmation_executionDate	I
    //   135: invokevirtual 770	com/db/pwcc/dbmobile/transfer/standingorder/confirm/StandingOrderConfirmationActivity:findViewById	(I)Landroid/view/View;
    //   138: checkcast 264	android/widget/TextView
    //   141: astore 10
    //   143: aload_0
    //   144: getstatic 805	com/db/pwcc/dbmobile/transfer/R$id:confirmation_frequency	I
    //   147: invokevirtual 770	com/db/pwcc/dbmobile/transfer/standingorder/confirm/StandingOrderConfirmationActivity:findViewById	(I)Landroid/view/View;
    //   150: checkcast 264	android/widget/TextView
    //   153: astore 11
    //   155: aload_0
    //   156: getstatic 808	com/db/pwcc/dbmobile/transfer/R$id:confirmation_validUntil	I
    //   159: invokevirtual 770	com/db/pwcc/dbmobile/transfer/standingorder/confirm/StandingOrderConfirmationActivity:findViewById	(I)Landroid/view/View;
    //   162: checkcast 264	android/widget/TextView
    //   165: astore 12
    //   167: aload 10
    //   169: invokestatic 814	uuuuuu/xsxxxs:bkk006Bkk006B006Bk006B006B	(Landroid/view/View;)V
    //   172: aload 12
    //   174: invokestatic 814	uuuuuu/xsxxxs:bkk006Bkk006B006Bk006B006B	(Landroid/view/View;)V
    //   177: aload_1
    //   178: ifnull +668 -> 846
    //   181: aload_1
    //   182: invokevirtual 69	com/db/pwcc/dbmobile/transfer/standingorder/model/StandingOrderRequestResponse:getTransaction	()Lcom/db/pwcc/dbmobile/transfer/standingorder/model/StandingOrderTransaction;
    //   185: ifnull +661 -> 846
    //   188: aload_1
    //   189: invokevirtual 69	com/db/pwcc/dbmobile/transfer/standingorder/model/StandingOrderRequestResponse:getTransaction	()Lcom/db/pwcc/dbmobile/transfer/standingorder/model/StandingOrderTransaction;
    //   192: astore 13
    //   194: aload 13
    //   196: invokevirtual 817	com/db/pwcc/dbmobile/transfer/standingorder/model/StandingOrderTransaction:getPurpose	()Ljava/lang/String;
    //   199: astore 14
    //   201: aload 13
    //   203: invokevirtual 820	com/db/pwcc/dbmobile/transfer/standingorder/model/StandingOrderTransaction:getReference	()Ljava/lang/String;
    //   206: astore 15
    //   208: aload 13
    //   210: invokevirtual 584	com/db/pwcc/dbmobile/transfer/standingorder/model/StandingOrderTransaction:getBeneficiary	()Ljava/lang/String;
    //   213: astore 16
    //   215: getstatic 71	com/db/pwcc/dbmobile/transfer/standingorder/confirm/StandingOrderConfirmationActivity:b006Dmm006Dm006Dmm006D	I
    //   218: getstatic 73	com/db/pwcc/dbmobile/transfer/standingorder/confirm/StandingOrderConfirmationActivity:b006D006D006D006Dm006Dmm006D	I
    //   221: iadd
    //   222: getstatic 71	com/db/pwcc/dbmobile/transfer/standingorder/confirm/StandingOrderConfirmationActivity:b006Dmm006Dm006Dmm006D	I
    //   225: imul
    //   226: getstatic 75	com/db/pwcc/dbmobile/transfer/standingorder/confirm/StandingOrderConfirmationActivity:bmm006D006Dm006Dmm006D	I
    //   229: irem
    //   230: getstatic 79	com/db/pwcc/dbmobile/transfer/standingorder/confirm/StandingOrderConfirmationActivity:bm006Dm006Dm006Dmm006D	I
    //   233: if_icmpeq +13 -> 246
    //   236: iconst_2
    //   237: putstatic 71	com/db/pwcc/dbmobile/transfer/standingorder/confirm/StandingOrderConfirmationActivity:b006Dmm006Dm006Dmm006D	I
    //   240: invokestatic 89	com/db/pwcc/dbmobile/transfer/standingorder/confirm/StandingOrderConfirmationActivity:b006Dm006D006Dm006Dmm006D	()I
    //   243: putstatic 79	com/db/pwcc/dbmobile/transfer/standingorder/confirm/StandingOrderConfirmationActivity:bm006Dm006Dm006Dmm006D	I
    //   246: aload 16
    //   248: invokestatic 825	uuuuuu/oononn:b006Bk006B006Bk006Bk006Bk006B	(Ljava/lang/String;)Ljava/lang/String;
    //   251: astore 17
    //   253: aload_2
    //   254: aload 16
    //   256: invokevirtual 268	android/widget/TextView:setText	(Ljava/lang/CharSequence;)V
    //   259: aload_0
    //   260: getfield 829	com/db/pwcc/dbmobile/transfer/standingorder/confirm/StandingOrderConfirmationActivity:beneficiaryAvatar	Lcom/db/pwcc/dbmobile/foundation/widgets/UserAvatar;
    //   263: aload 17
    //   265: invokevirtual 832	com/db/pwcc/dbmobile/foundation/widgets/UserAvatar:setText	(Ljava/lang/CharSequence;)V
    //   268: aload_0
    //   269: invokevirtual 424	com/db/pwcc/dbmobile/transfer/standingorder/confirm/StandingOrderConfirmationActivity:getIntent	()Landroid/content/Intent;
    //   272: astore 18
    //   274: ldc_w 834
    //   277: bipush 12
    //   279: iconst_2
    //   280: iconst_0
    //   281: invokestatic 186	xxxxxx/uxxxxx:bbbb0062b0062b0062b0062	(Ljava/lang/String;CCC)Ljava/lang/String;
    //   284: astore 19
    //   286: iconst_4
    //   287: anewarray 99	java/lang/Class
    //   290: astore 20
    //   292: aload 20
    //   294: iconst_0
    //   295: ldc 101
    //   297: aastore
    //   298: aload 20
    //   300: iconst_1
    //   301: getstatic 107	java/lang/Character:TYPE	Ljava/lang/Class;
    //   304: aastore
    //   305: aload 20
    //   307: iconst_2
    //   308: getstatic 107	java/lang/Character:TYPE	Ljava/lang/Class;
    //   311: aastore
    //   312: aload 20
    //   314: iconst_3
    //   315: getstatic 107	java/lang/Character:TYPE	Ljava/lang/Class;
    //   318: aastore
    //   319: ldc 109
    //   321: aload 19
    //   323: aload 20
    //   325: invokevirtual 113	java/lang/Class:getMethod	(Ljava/lang/String;[Ljava/lang/Class;)Ljava/lang/reflect/Method;
    //   328: astore 21
    //   330: iconst_4
    //   331: anewarray 115	java/lang/Object
    //   334: astore 22
    //   336: aload 22
    //   338: iconst_0
    //   339: ldc_w 836
    //   342: aastore
    //   343: aload 22
    //   345: iconst_1
    //   346: bipush 32
    //   348: invokestatic 121	java/lang/Character:valueOf	(C)Ljava/lang/Character;
    //   351: aastore
    //   352: aload 22
    //   354: iconst_2
    //   355: sipush 166
    //   358: invokestatic 121	java/lang/Character:valueOf	(C)Ljava/lang/Character;
    //   361: aastore
    //   362: aload 22
    //   364: iconst_3
    //   365: iconst_3
    //   366: invokestatic 121	java/lang/Character:valueOf	(C)Ljava/lang/Character;
    //   369: aastore
    //   370: aload 21
    //   372: aconst_null
    //   373: aload 22
    //   375: invokevirtual 127	java/lang/reflect/Method:invoke	(Ljava/lang/Object;[Ljava/lang/Object;)Ljava/lang/Object;
    //   378: astore 24
    //   380: aload 18
    //   382: aload 24
    //   384: checkcast 101	java/lang/String
    //   387: invokevirtual 839	android/content/Intent:hasExtra	(Ljava/lang/String;)Z
    //   390: ifeq +497 -> 887
    //   393: aload_0
    //   394: invokevirtual 424	com/db/pwcc/dbmobile/transfer/standingorder/confirm/StandingOrderConfirmationActivity:getIntent	()Landroid/content/Intent;
    //   397: astore 36
    //   399: ldc_w 841
    //   402: sipush 137
    //   405: iconst_3
    //   406: invokestatic 97	xxxxxx/uxxxxx:bb00620062bb0062b0062b0062	(Ljava/lang/String;CC)Ljava/lang/String;
    //   409: astore 37
    //   411: iconst_4
    //   412: anewarray 99	java/lang/Class
    //   415: astore 38
    //   417: aload 38
    //   419: iconst_0
    //   420: ldc 101
    //   422: aastore
    //   423: aload 38
    //   425: iconst_1
    //   426: getstatic 107	java/lang/Character:TYPE	Ljava/lang/Class;
    //   429: aastore
    //   430: aload 38
    //   432: iconst_2
    //   433: getstatic 107	java/lang/Character:TYPE	Ljava/lang/Class;
    //   436: aastore
    //   437: aload 38
    //   439: iconst_3
    //   440: getstatic 107	java/lang/Character:TYPE	Ljava/lang/Class;
    //   443: aastore
    //   444: ldc 109
    //   446: aload 37
    //   448: aload 38
    //   450: invokevirtual 113	java/lang/Class:getMethod	(Ljava/lang/String;[Ljava/lang/Class;)Ljava/lang/reflect/Method;
    //   453: astore 39
    //   455: iconst_4
    //   456: anewarray 115	java/lang/Object
    //   459: astore 40
    //   461: aload 40
    //   463: iconst_0
    //   464: ldc_w 843
    //   467: aastore
    //   468: aload 40
    //   470: iconst_1
    //   471: sipush 147
    //   474: invokestatic 121	java/lang/Character:valueOf	(C)Ljava/lang/Character;
    //   477: aastore
    //   478: aload 40
    //   480: iconst_2
    //   481: sipush 172
    //   484: invokestatic 121	java/lang/Character:valueOf	(C)Ljava/lang/Character;
    //   487: aastore
    //   488: aload 40
    //   490: iconst_3
    //   491: iconst_3
    //   492: invokestatic 121	java/lang/Character:valueOf	(C)Ljava/lang/Character;
    //   495: aastore
    //   496: aload 39
    //   498: aconst_null
    //   499: aload 40
    //   501: invokevirtual 127	java/lang/reflect/Method:invoke	(Ljava/lang/Object;[Ljava/lang/Object;)Ljava/lang/Object;
    //   504: astore 42
    //   506: aload 4
    //   508: aload 36
    //   510: aload 42
    //   512: checkcast 101	java/lang/String
    //   515: invokevirtual 432	android/content/Intent:getStringExtra	(Ljava/lang/String;)Ljava/lang/String;
    //   518: invokevirtual 268	android/widget/TextView:setText	(Ljava/lang/CharSequence;)V
    //   521: aload 14
    //   523: ifnull +464 -> 987
    //   526: aload 14
    //   528: invokevirtual 366	java/lang/String:trim	()Ljava/lang/String;
    //   531: ldc_w 359
    //   534: invokevirtual 131	java/lang/String:equals	(Ljava/lang/Object;)Z
    //   537: ifne +450 -> 987
    //   540: aload 5
    //   542: aload 14
    //   544: invokevirtual 268	android/widget/TextView:setText	(Ljava/lang/CharSequence;)V
    //   547: aload 15
    //   549: ifnull +348 -> 897
    //   552: aload 15
    //   554: invokevirtual 366	java/lang/String:trim	()Ljava/lang/String;
    //   557: ldc_w 359
    //   560: invokevirtual 131	java/lang/String:equals	(Ljava/lang/Object;)Z
    //   563: ifne +334 -> 897
    //   566: aload 6
    //   568: aload 15
    //   570: invokevirtual 268	android/widget/TextView:setText	(Ljava/lang/CharSequence;)V
    //   573: aload_3
    //   574: aload 13
    //   576: invokevirtual 581	com/db/pwcc/dbmobile/transfer/standingorder/model/StandingOrderTransaction:getTargetAccount	()Ljava/lang/String;
    //   579: invokevirtual 268	android/widget/TextView:setText	(Ljava/lang/CharSequence;)V
    //   582: invokestatic 230	java/util/Locale:getDefault	()Ljava/util/Locale;
    //   585: astore 25
    //   587: aload 7
    //   589: new 845	java/math/BigDecimal
    //   592: dup
    //   593: aload 13
    //   595: invokevirtual 848	com/db/pwcc/dbmobile/transfer/standingorder/model/StandingOrderTransaction:getAmount	()Ljava/lang/String;
    //   598: invokespecial 850	java/math/BigDecimal:<init>	(Ljava/lang/String;)V
    //   601: getstatic 856	uuuuuu/hhhpph:by0079y007900790079yy0079	Ljava/util/Currency;
    //   604: invokevirtual 861	java/util/Currency:getCurrencyCode	()Ljava/lang/String;
    //   607: aload 25
    //   609: invokestatic 865	uuuuuu/hhhpph:bw0077wwwwww0077w	(Ljava/math/BigDecimal;Ljava/lang/String;Ljava/util/Locale;)Ljava/lang/String;
    //   612: invokevirtual 268	android/widget/TextView:setText	(Ljava/lang/CharSequence;)V
    //   615: aload 8
    //   617: aload 13
    //   619: invokevirtual 587	com/db/pwcc/dbmobile/transfer/standingorder/model/StandingOrderTransaction:getSourceAccount	()Ljava/lang/String;
    //   622: invokevirtual 268	android/widget/TextView:setText	(Ljava/lang/CharSequence;)V
    //   625: ldc_w 867
    //   628: bipush 50
    //   630: sipush 193
    //   633: iconst_3
    //   634: invokestatic 186	xxxxxx/uxxxxx:bbbb0062b0062b0062b0062	(Ljava/lang/String;CCC)Ljava/lang/String;
    //   637: astore 26
    //   639: iconst_4
    //   640: anewarray 99	java/lang/Class
    //   643: astore 27
    //   645: aload 27
    //   647: iconst_0
    //   648: ldc 101
    //   650: aastore
    //   651: aload 27
    //   653: iconst_1
    //   654: getstatic 107	java/lang/Character:TYPE	Ljava/lang/Class;
    //   657: aastore
    //   658: aload 27
    //   660: iconst_2
    //   661: getstatic 107	java/lang/Character:TYPE	Ljava/lang/Class;
    //   664: aastore
    //   665: aload 27
    //   667: iconst_3
    //   668: getstatic 107	java/lang/Character:TYPE	Ljava/lang/Class;
    //   671: aastore
    //   672: ldc 109
    //   674: aload 26
    //   676: aload 27
    //   678: invokevirtual 113	java/lang/Class:getMethod	(Ljava/lang/String;[Ljava/lang/Class;)Ljava/lang/reflect/Method;
    //   681: astore 28
    //   683: iconst_4
    //   684: anewarray 115	java/lang/Object
    //   687: astore 29
    //   689: aload 29
    //   691: iconst_0
    //   692: ldc_w 869
    //   695: aastore
    //   696: aload 29
    //   698: iconst_1
    //   699: sipush 138
    //   702: invokestatic 121	java/lang/Character:valueOf	(C)Ljava/lang/Character;
    //   705: aastore
    //   706: aload 29
    //   708: iconst_2
    //   709: sipush 186
    //   712: invokestatic 121	java/lang/Character:valueOf	(C)Ljava/lang/Character;
    //   715: aastore
    //   716: aload 29
    //   718: iconst_3
    //   719: iconst_0
    //   720: invokestatic 121	java/lang/Character:valueOf	(C)Ljava/lang/Character;
    //   723: aastore
    //   724: aload 28
    //   726: aconst_null
    //   727: aload 29
    //   729: invokevirtual 127	java/lang/reflect/Method:invoke	(Ljava/lang/Object;[Ljava/lang/Object;)Ljava/lang/Object;
    //   732: astore 31
    //   734: aload 31
    //   736: checkcast 101	java/lang/String
    //   739: astore 32
    //   741: aload 13
    //   743: invokevirtual 85	com/db/pwcc/dbmobile/transfer/standingorder/model/StandingOrderTransaction:getType	()Ljava/lang/String;
    //   746: astore 33
    //   748: getstatic 71	com/db/pwcc/dbmobile/transfer/standingorder/confirm/StandingOrderConfirmationActivity:b006Dmm006Dm006Dmm006D	I
    //   751: istore 34
    //   753: iload 34
    //   755: iload 34
    //   757: getstatic 73	com/db/pwcc/dbmobile/transfer/standingorder/confirm/StandingOrderConfirmationActivity:b006D006D006D006Dm006Dmm006D	I
    //   760: iadd
    //   761: imul
    //   762: getstatic 75	com/db/pwcc/dbmobile/transfer/standingorder/confirm/StandingOrderConfirmationActivity:bmm006D006Dm006Dmm006D	I
    //   765: irem
    //   766: tableswitch	default:+18->784, 0:+29->795
    //   784: bipush 43
    //   786: putstatic 71	com/db/pwcc/dbmobile/transfer/standingorder/confirm/StandingOrderConfirmationActivity:b006Dmm006Dm006Dmm006D	I
    //   789: invokestatic 89	com/db/pwcc/dbmobile/transfer/standingorder/confirm/StandingOrderConfirmationActivity:b006Dm006D006Dm006Dmm006D	()I
    //   792: putstatic 79	com/db/pwcc/dbmobile/transfer/standingorder/confirm/StandingOrderConfirmationActivity:bm006Dm006Dm006Dmm006D	I
    //   795: aload 32
    //   797: aload 33
    //   799: invokevirtual 131	java/lang/String:equals	(Ljava/lang/Object;)Z
    //   802: ifeq +45 -> 847
    //   805: aload 10
    //   807: aload 25
    //   809: aload_0
    //   810: aload_0
    //   811: getfield 54	com/db/pwcc/dbmobile/transfer/standingorder/confirm/StandingOrderConfirmationActivity:standingOrderTemplate	Lcom/db/pwcc/dbmobile/transfer/standingorder/model/StandingOrderTemplate;
    //   814: invokevirtual 872	com/db/pwcc/dbmobile/transfer/standingorder/model/StandingOrderTemplate:getValidFrom	()Ljava/lang/String;
    //   817: invokespecial 874	com/db/pwcc/dbmobile/transfer/standingorder/confirm/StandingOrderConfirmationActivity:parseTemplateDateString	(Ljava/lang/String;)Ljava/util/Date;
    //   820: invokestatic 417	uuuuuu/pqpppq:b006Bkkk006B006Bkkkk	(Ljava/util/Locale;Ljava/util/Date;)Ljava/lang/String;
    //   823: invokevirtual 268	android/widget/TextView:setText	(Ljava/lang/CharSequence;)V
    //   826: aload_0
    //   827: aload 11
    //   829: aload_0
    //   830: getfield 54	com/db/pwcc/dbmobile/transfer/standingorder/confirm/StandingOrderConfirmationActivity:standingOrderTemplate	Lcom/db/pwcc/dbmobile/transfer/standingorder/model/StandingOrderTemplate;
    //   833: invokespecial 876	com/db/pwcc/dbmobile/transfer/standingorder/confirm/StandingOrderConfirmationActivity:setFormattedFrequencyText	(Landroid/widget/TextView;Lcom/db/pwcc/dbmobile/transfer/standingorder/model/StandingOrderTemplate;)V
    //   836: aload_0
    //   837: aload 12
    //   839: aload_0
    //   840: getfield 54	com/db/pwcc/dbmobile/transfer/standingorder/confirm/StandingOrderConfirmationActivity:standingOrderTemplate	Lcom/db/pwcc/dbmobile/transfer/standingorder/model/StandingOrderTemplate;
    //   843: invokespecial 878	com/db/pwcc/dbmobile/transfer/standingorder/confirm/StandingOrderConfirmationActivity:setValidUntilText	(Landroid/widget/TextView;Lcom/db/pwcc/dbmobile/transfer/standingorder/model/StandingOrderTemplate;)V
    //   846: return
    //   847: aload 10
    //   849: aload 25
    //   851: aload 13
    //   853: invokevirtual 880	com/db/pwcc/dbmobile/transfer/standingorder/model/StandingOrderTransaction:getValidFrom	()Ljava/util/Date;
    //   856: invokestatic 417	uuuuuu/pqpppq:b006Bkkk006B006Bkkkk	(Ljava/util/Locale;Ljava/util/Date;)Ljava/lang/String;
    //   859: invokevirtual 268	android/widget/TextView:setText	(Ljava/lang/CharSequence;)V
    //   862: aload_0
    //   863: aload 11
    //   865: aload 13
    //   867: invokespecial 882	com/db/pwcc/dbmobile/transfer/standingorder/confirm/StandingOrderConfirmationActivity:setFormattedFrequencyText	(Landroid/widget/TextView;Lcom/db/pwcc/dbmobile/transfer/standingorder/model/StandingOrderTransaction;)V
    //   870: aload 13
    //   872: invokevirtual 884	com/db/pwcc/dbmobile/transfer/standingorder/model/StandingOrderTransaction:getValidUntil	()Ljava/util/Date;
    //   875: ifnonnull +40 -> 915
    //   878: aload 12
    //   880: getstatic 413	com/db/pwcc/dbmobile/transfer/R$string:standing_order_valid_unlimited	I
    //   883: invokevirtual 320	android/widget/TextView:setText	(I)V
    //   886: return
    //   887: aload 4
    //   889: bipush 8
    //   891: invokevirtual 887	android/widget/TextView:setVisibility	(I)V
    //   894: goto -373 -> 521
    //   897: aload 6
    //   899: bipush 8
    //   901: invokevirtual 887	android/widget/TextView:setVisibility	(I)V
    //   904: goto -331 -> 573
    //   907: astore 41
    //   909: aload 41
    //   911: invokevirtual 135	java/lang/reflect/InvocationTargetException:getCause	()Ljava/lang/Throwable;
    //   914: athrow
    //   915: aload 12
    //   917: aload 25
    //   919: aload 13
    //   921: invokevirtual 884	com/db/pwcc/dbmobile/transfer/standingorder/model/StandingOrderTransaction:getValidUntil	()Ljava/util/Date;
    //   924: invokestatic 417	uuuuuu/pqpppq:b006Bkkk006B006Bkkkk	(Ljava/util/Locale;Ljava/util/Date;)Ljava/lang/String;
    //   927: invokevirtual 268	android/widget/TextView:setText	(Ljava/lang/CharSequence;)V
    //   930: invokestatic 89	com/db/pwcc/dbmobile/transfer/standingorder/confirm/StandingOrderConfirmationActivity:b006Dm006D006Dm006Dmm006D	()I
    //   933: istore 35
    //   935: iload 35
    //   937: iload 35
    //   939: getstatic 73	com/db/pwcc/dbmobile/transfer/standingorder/confirm/StandingOrderConfirmationActivity:b006D006D006D006Dm006Dmm006D	I
    //   942: iadd
    //   943: imul
    //   944: invokestatic 148	com/db/pwcc/dbmobile/transfer/standingorder/confirm/StandingOrderConfirmationActivity:bmmmm006D006Dmm006D	()I
    //   947: irem
    //   948: tableswitch	default:+20->968, 0:+-102->846
    //   968: bipush 28
    //   970: putstatic 71	com/db/pwcc/dbmobile/transfer/standingorder/confirm/StandingOrderConfirmationActivity:b006Dmm006Dm006Dmm006D	I
    //   973: bipush 74
    //   975: putstatic 79	com/db/pwcc/dbmobile/transfer/standingorder/confirm/StandingOrderConfirmationActivity:bm006Dm006Dm006Dmm006D	I
    //   978: return
    //   979: astore 23
    //   981: aload 23
    //   983: invokevirtual 135	java/lang/reflect/InvocationTargetException:getCause	()Ljava/lang/Throwable;
    //   986: athrow
    //   987: aload 5
    //   989: bipush 8
    //   991: invokevirtual 887	android/widget/TextView:setVisibility	(I)V
    //   994: goto -447 -> 547
    //   997: astore 30
    //   999: aload 30
    //   1001: invokevirtual 135	java/lang/reflect/InvocationTargetException:getCause	()Ljava/lang/Throwable;
    //   1004: athrow
    // Local variable table:
    //   start	length	slot	name	signature
    //   0	1005	0	this	StandingOrderConfirmationActivity
    //   0	1005	1	paramStandingOrderRequestResponse	StandingOrderRequestResponse
    //   10	244	2	localTextView1	TextView
    //   21	553	3	localTextView2	TextView
    //   32	856	4	localTextView3	TextView
    //   44	944	5	localTextView4	TextView
    //   56	842	6	localTextView5	TextView
    //   68	520	7	localTextView6	TextView
    //   80	536	8	localTextView7	TextView
    //   85	11	9	i	int
    //   141	707	10	localTextView8	TextView
    //   153	711	11	localTextView9	TextView
    //   165	751	12	localTextView10	TextView
    //   192	728	13	localStandingOrderTransaction	StandingOrderTransaction
    //   199	344	14	str1	String
    //   206	363	15	str2	String
    //   213	42	16	str3	String
    //   251	13	17	str4	String
    //   272	109	18	localIntent1	Intent
    //   284	38	19	str5	String
    //   290	34	20	arrayOfClass1	Class[]
    //   328	43	21	localMethod1	Method
    //   334	40	22	arrayOfObject1	Object[]
    //   979	3	23	localInvocationTargetException1	InvocationTargetException
    //   378	5	24	localObject1	Object
    //   585	333	25	localLocale	Locale
    //   637	38	26	str6	String
    //   643	34	27	arrayOfClass2	Class[]
    //   681	44	28	localMethod2	Method
    //   687	41	29	arrayOfObject2	Object[]
    //   997	3	30	localInvocationTargetException2	InvocationTargetException
    //   732	3	31	localObject2	Object
    //   739	57	32	str7	String
    //   746	52	33	str8	String
    //   751	11	34	j	int
    //   933	11	35	k	int
    //   397	112	36	localIntent2	Intent
    //   409	38	37	str9	String
    //   415	34	38	arrayOfClass3	Class[]
    //   453	44	39	localMethod3	Method
    //   459	41	40	arrayOfObject3	Object[]
    //   907	3	41	localInvocationTargetException3	InvocationTargetException
    //   504	7	42	localObject3	Object
    // Exception table:
    //   from	to	target	type
    //   496	506	907	java/lang/reflect/InvocationTargetException
    //   370	380	979	java/lang/reflect/InvocationTargetException
    //   724	734	997	java/lang/reflect/InvocationTargetException
  }
  
  public void showTanError(int paramInt)
  {
    TanModule localTanModule = this.tanModule;
    int i = b006Dmm006Dm006Dmm006D;
    int j = i * (i + b006D006D006D006Dm006Dmm006D);
    int k = b006Dmm006Dm006Dmm006D;
    switch (k * (k + b006D006D006D006Dm006Dmm006D) % bmm006D006Dm006Dmm006D)
    {
    default: 
      b006Dmm006Dm006Dmm006D = 42;
      bm006Dm006Dm006Dmm006D = b006Dm006D006Dm006Dmm006D();
      int n = b006Dmm006Dm006Dmm006D;
      switch (n * (n + b006D006Dm006Dm006Dmm006D()) % bmm006D006Dm006Dmm006D)
      {
      default: 
        b006Dmm006Dm006Dmm006D = 7;
        bm006Dm006Dm006Dmm006D = 0;
      }
      break;
    }
    switch (j % bmm006D006Dm006Dmm006D)
    {
    default: 
      int m = b006Dm006D006Dm006Dmm006D();
      if ((b006Dm006D006Dm006Dmm006D() + b006D006D006D006Dm006Dmm006D) * b006Dm006D006Dm006Dmm006D() % bmm006D006Dm006Dmm006D != bm006Dm006Dm006Dmm006D)
      {
        b006Dmm006Dm006Dmm006D = 90;
        bm006Dm006Dm006Dmm006D = 30;
      }
      b006Dmm006Dm006Dmm006D = m;
      bm006Dm006Dm006Dmm006D = 55;
    }
    localTanModule.showErrorLayoutView(paramInt);
  }
  
  public void showTanError(AuthorizationStatus paramAuthorizationStatus)
  {
    this.tanModule.showErrorLayoutView(paramAuthorizationStatus);
    if ((b006Dmm006Dm006Dmm006D + b006D006D006D006Dm006Dmm006D) * b006Dmm006Dm006Dmm006D % bmm006D006Dm006Dmm006D != bm006D006D006Dm006Dmm006D())
    {
      int i = b006Dm006D006Dm006Dmm006D();
      switch (i * (i + b006D006D006D006Dm006Dmm006D) % bmm006D006Dm006Dmm006D)
      {
      default: 
        b006Dmm006Dm006Dmm006D = b006Dm006D006Dm006Dmm006D();
        bm006Dm006Dm006Dmm006D = 10;
      }
      if ((b006Dmm006Dm006Dmm006D + b006D006Dm006Dm006Dmm006D()) * b006Dmm006Dm006Dmm006D % bmmmm006D006Dmm006D() != bm006Dm006Dm006Dmm006D)
      {
        b006Dmm006Dm006Dmm006D = 78;
        bm006Dm006Dm006Dmm006D = 90;
        if ((b006Dmm006Dm006Dmm006D + b006D006Dm006Dm006Dmm006D()) * b006Dmm006Dm006Dmm006D % bmm006D006Dm006Dmm006D != bm006Dm006Dm006Dmm006D)
        {
          b006Dmm006Dm006Dmm006D = b006Dm006D006Dm006Dmm006D();
          bm006Dm006Dm006Dmm006D = 40;
        }
      }
      b006Dmm006Dm006Dmm006D = 98;
      bm006Dm006Dm006Dmm006D = 52;
    }
  }
  
  public void showTanSuccess(Date paramDate)
  {
    int i = 0;
    TanModule localTanModule = this.tanModule;
    if ((b006Dmm006Dm006Dmm006D + b006D006Dm006Dm006Dmm006D()) * b006Dmm006Dm006Dmm006D % bmm006D006Dm006Dmm006D != bm006Dm006Dm006Dmm006D)
    {
      if ((b006Dmm006Dm006Dmm006D + b006D006D006D006Dm006Dmm006D) * b006Dmm006Dm006Dmm006D % bmm006D006Dm006Dmm006D != bm006Dm006Dm006Dmm006D)
      {
        b006Dmm006Dm006Dmm006D = b006Dm006D006Dm006Dmm006D();
        bm006Dm006Dm006Dmm006D = b006Dm006D006Dm006Dmm006D();
      }
      b006Dmm006Dm006Dmm006D = 43;
      bm006Dm006Dm006Dmm006D = b006Dm006D006Dm006Dmm006D();
    }
    localTanModule.showSuccessLayoutView(paramDate);
    try
    {
      for (;;)
      {
        i /= 0;
      }
      int j;
      return;
    }
    catch (Exception localException)
    {
      b006Dmm006Dm006Dmm006D = 2;
      j = b006Dmm006Dm006Dmm006D;
      switch (j * (j + b006D006D006D006Dm006Dmm006D) % bmm006D006Dm006Dmm006D)
      {
      default: 
        b006Dmm006Dm006Dmm006D = b006Dm006D006Dm006Dmm006D();
        bm006Dm006Dm006Dmm006D = 61;
      }
    }
  }
}
