package com.google.android.gms.internal;

import android.app.Application;
import android.content.Context;
import android.content.pm.ApplicationInfo;
import android.content.pm.PackageInfo;
import android.content.pm.PackageManager;
import android.content.pm.PackageManager.NameNotFoundException;
import android.database.sqlite.SQLiteDatabase;
import android.database.sqlite.SQLiteException;
import android.net.Uri;
import android.net.Uri.Builder;
import android.os.Build;
import android.os.Build.VERSION;
import android.os.Bundle;
import android.provider.Settings.Secure;
import android.support.annotation.NonNull;
import android.support.annotation.Size;
import android.support.annotation.WorkerThread;
import android.support.v4.util.ArrayMap;
import android.text.TextUtils;
import android.util.Pair;
import com.google.android.gms.common.api.internal.zzbz;
import com.google.android.gms.common.internal.zzbq;
import com.google.android.gms.common.util.zzd;
import com.google.android.gms.common.util.zzh;
import com.google.android.gms.measurement.AppMeasurement;
import com.google.firebase.analytics.FirebaseAnalytics;
import java.io.File;
import java.io.FileNotFoundException;
import java.io.IOException;
import java.io.RandomAccessFile;
import java.net.MalformedURLException;
import java.net.URL;
import java.nio.ByteBuffer;
import java.nio.channels.FileChannel;
import java.nio.channels.FileLock;
import java.security.SecureRandom;
import java.util.ArrayList;
import java.util.Collection;
import java.util.Collections;
import java.util.Iterator;
import java.util.List;
import java.util.Locale;
import java.util.Map;
import java.util.concurrent.ExecutionException;
import java.util.concurrent.Future;
import java.util.concurrent.TimeUnit;
import java.util.concurrent.TimeoutException;
import java.util.concurrent.atomic.AtomicReference;

public class zzcim
{
  private static volatile zzcim zzjev;
  private final Context mContext;
  private final zzd zzata;
  private boolean zzdtb = false;
  private final zzcgn zzjew;
  private final zzchx zzjex;
  private final zzchm zzjey;
  private final zzcih zzjez;
  private final zzclf zzjfa;
  private final zzcig zzjfb;
  private final AppMeasurement zzjfc;
  private final FirebaseAnalytics zzjfd;
  private final zzclq zzjfe;
  private final zzchk zzjff;
  private final zzcgo zzjfg;
  private final zzchi zzjfh;
  private final zzchq zzjfi;
  private final zzckc zzjfj;
  private final zzckg zzjfk;
  private final zzcgu zzjfl;
  private final zzcjn zzjfm;
  private final zzchh zzjfn;
  private final zzchv zzjfo;
  private final zzcll zzjfp;
  private final zzcgk zzjfq;
  private final zzcgd zzjfr;
  private boolean zzjfs;
  private Boolean zzjft;
  private long zzjfu;
  private FileLock zzjfv;
  private FileChannel zzjfw;
  private List<Long> zzjfx;
  private List<Runnable> zzjfy;
  private int zzjfz;
  private int zzjga;
  private long zzjgb;
  private long zzjgc;
  private boolean zzjgd;
  private boolean zzjge;
  private boolean zzjgf;
  private final long zzjgg;
  
  private zzcim(zzcjm paramZzcjm)
  {
    zzbq.checkNotNull(paramZzcjm);
    this.mContext = paramZzcjm.mContext;
    this.zzjgb = -1L;
    this.zzata = zzh.zzamg();
    this.zzjgg = this.zzata.currentTimeMillis();
    this.zzjew = new zzcgn(this);
    paramZzcjm = new zzchx(this);
    paramZzcjm.initialize();
    this.zzjex = paramZzcjm;
    paramZzcjm = new zzchm(this);
    paramZzcjm.initialize();
    this.zzjey = paramZzcjm;
    paramZzcjm = new zzclq(this);
    paramZzcjm.initialize();
    this.zzjfe = paramZzcjm;
    paramZzcjm = new zzchk(this);
    paramZzcjm.initialize();
    this.zzjff = paramZzcjm;
    paramZzcjm = new zzcgu(this);
    paramZzcjm.initialize();
    this.zzjfl = paramZzcjm;
    paramZzcjm = new zzchh(this);
    paramZzcjm.initialize();
    this.zzjfn = paramZzcjm;
    paramZzcjm = new zzcgo(this);
    paramZzcjm.initialize();
    this.zzjfg = paramZzcjm;
    paramZzcjm = new zzchi(this);
    paramZzcjm.initialize();
    this.zzjfh = paramZzcjm;
    paramZzcjm = new zzcgk(this);
    paramZzcjm.initialize();
    this.zzjfq = paramZzcjm;
    this.zzjfr = new zzcgd(this);
    paramZzcjm = new zzchq(this);
    paramZzcjm.initialize();
    this.zzjfi = paramZzcjm;
    paramZzcjm = new zzckc(this);
    paramZzcjm.initialize();
    this.zzjfj = paramZzcjm;
    paramZzcjm = new zzckg(this);
    paramZzcjm.initialize();
    this.zzjfk = paramZzcjm;
    paramZzcjm = new zzcjn(this);
    paramZzcjm.initialize();
    this.zzjfm = paramZzcjm;
    paramZzcjm = new zzcll(this);
    paramZzcjm.initialize();
    this.zzjfp = paramZzcjm;
    this.zzjfo = new zzchv(this);
    this.zzjfc = new AppMeasurement(this);
    this.zzjfd = new FirebaseAnalytics(this);
    paramZzcjm = new zzclf(this);
    paramZzcjm.initialize();
    this.zzjfa = paramZzcjm;
    paramZzcjm = new zzcig(this);
    paramZzcjm.initialize();
    this.zzjfb = paramZzcjm;
    paramZzcjm = new zzcih(this);
    paramZzcjm.initialize();
    this.zzjez = paramZzcjm;
    if ((this.mContext.getApplicationContext() instanceof Application))
    {
      paramZzcjm = zzawm();
      if ((paramZzcjm.getContext().getApplicationContext() instanceof Application))
      {
        Application localApplication = (Application)paramZzcjm.getContext().getApplicationContext();
        if (paramZzcjm.zzjgx == null) {
          paramZzcjm.zzjgx = new zzckb(paramZzcjm, null);
        }
        localApplication.unregisterActivityLifecycleCallbacks(paramZzcjm.zzjgx);
        localApplication.registerActivityLifecycleCallbacks(paramZzcjm.zzjgx);
        paramZzcjm.zzawy().zzazj().log("Registered activity lifecycle callback");
      }
    }
    for (;;)
    {
      this.zzjez.zzg(new zzcin(this));
      return;
      zzawy().zzazf().log("Application context is not an Application");
    }
  }
  
  @WorkerThread
  private final int zza(FileChannel paramFileChannel)
  {
    zzawx().zzve();
    if ((paramFileChannel == null) || (!paramFileChannel.isOpen())) {
      zzawy().zzazd().log("Bad chanel to read from");
    }
    ByteBuffer localByteBuffer;
    for (;;)
    {
      return 0;
      localByteBuffer = ByteBuffer.allocate(4);
      try
      {
        paramFileChannel.position(0L);
        i = paramFileChannel.read(localByteBuffer);
        if (i != 4)
        {
          if (i == -1) {
            continue;
          }
          zzawy().zzazf().zzj("Unexpected data length. Bytes read", Integer.valueOf(i));
          return 0;
        }
      }
      catch (IOException paramFileChannel)
      {
        zzawy().zzazd().zzj("Failed to read from channel", paramFileChannel);
        return 0;
      }
    }
    localByteBuffer.flip();
    int i = localByteBuffer.getInt();
    return i;
  }
  
  private final zzcgi zza(Context paramContext, String paramString1, String paramString2, boolean paramBoolean1, boolean paramBoolean2)
  {
    Object localObject3 = "Unknown";
    String str = "Unknown";
    int i = Integer.MIN_VALUE;
    Object localObject1 = paramContext.getPackageManager();
    if (localObject1 == null)
    {
      zzawy().zzazd().log("PackageManager is null, can not log app install information");
      return null;
    }
    try
    {
      localObject1 = ((PackageManager)localObject1).getInstallerPackageName(paramString1);
      localObject3 = localObject1;
    }
    catch (IllegalArgumentException localIllegalArgumentException)
    {
      for (;;)
      {
        try
        {
          localPackageInfo = zzbhf.zzdb(paramContext).getPackageInfo(paramString1, 0);
          localObject3 = str;
          if (localPackageInfo != null)
          {
            localObject3 = zzbhf.zzdb(paramContext).zzgt(paramString1);
            if (TextUtils.isEmpty((CharSequence)localObject3)) {
              break label241;
            }
            localObject3 = ((CharSequence)localObject3).toString();
          }
        }
        catch (PackageManager.NameNotFoundException paramContext)
        {
          localObject3 = "Unknown";
        }
        try
        {
          str = localPackageInfo.versionName;
          i = localPackageInfo.versionCode;
          localObject3 = str;
          return new zzcgi(paramString1, paramString2, (String)localObject3, i, (String)localObject1, 11910L, zzawu().zzaf(paramContext, paramString1), null, paramBoolean1, false, "", 0L, 0L, 0, paramBoolean2);
        }
        catch (PackageManager.NameNotFoundException paramContext)
        {
          for (;;) {}
        }
        localIllegalArgumentException = localIllegalArgumentException;
        zzawy().zzazd().zzj("Error retrieving installer package name. appId", zzchm.zzjk(paramString1));
        continue;
        localObject2 = localObject3;
        if ("com.android.vending".equals(localObject3)) {
          localObject2 = "";
        }
      }
    }
    if (localObject3 == null) {
      localObject1 = "manual_install";
    }
    for (;;)
    {
      PackageInfo localPackageInfo;
      Object localObject2;
      zzawy().zzazd().zze("Error retrieving newly installed package info. appId, appName", zzchm.zzjk(paramString1), localObject3);
      return null;
      label241:
      localObject3 = "Unknown";
    }
  }
  
  private static void zza(zzcjk paramZzcjk)
  {
    if (paramZzcjk == null) {
      throw new IllegalStateException("Component not created");
    }
  }
  
  private static void zza(zzcjl paramZzcjl)
  {
    if (paramZzcjl == null) {
      throw new IllegalStateException("Component not created");
    }
    if (!paramZzcjl.isInitialized()) {
      throw new IllegalStateException("Component not initialized");
    }
  }
  
  @WorkerThread
  private final boolean zza(int paramInt, FileChannel paramFileChannel)
  {
    boolean bool = true;
    zzawx().zzve();
    if ((paramFileChannel == null) || (!paramFileChannel.isOpen()))
    {
      zzawy().zzazd().log("Bad chanel to read from");
      bool = false;
    }
    for (;;)
    {
      return bool;
      ByteBuffer localByteBuffer = ByteBuffer.allocate(4);
      localByteBuffer.putInt(paramInt);
      localByteBuffer.flip();
      try
      {
        paramFileChannel.truncate(0L);
        paramFileChannel.write(localByteBuffer);
        paramFileChannel.force(true);
        if (paramFileChannel.size() != 4L)
        {
          zzawy().zzazd().zzj("Error writing to channel. Bytes written", Long.valueOf(paramFileChannel.size()));
          return true;
        }
      }
      catch (IOException paramFileChannel)
      {
        zzawy().zzazd().zzj("Failed to write to channel", paramFileChannel);
      }
    }
    return false;
  }
  
  private static boolean zza(zzcmb paramZzcmb, String paramString, Object paramObject)
  {
    if ((TextUtils.isEmpty(paramString)) || (paramObject == null)) {}
    label111:
    for (;;)
    {
      return false;
      paramZzcmb = paramZzcmb.zzjlh;
      int j = paramZzcmb.length;
      int i = 0;
      for (;;)
      {
        if (i >= j) {
          break label111;
        }
        Object localObject = paramZzcmb[i];
        if (paramString.equals(localObject.name))
        {
          if (((!(paramObject instanceof Long)) || (!paramObject.equals(localObject.zzjll))) && ((!(paramObject instanceof String)) || (!paramObject.equals(localObject.zzgcc))) && ((!(paramObject instanceof Double)) || (!paramObject.equals(localObject.zzjjl)))) {
            break;
          }
          return true;
        }
        i += 1;
      }
    }
  }
  
  private final boolean zza(String paramString, zzcha paramZzcha)
  {
    String str = paramZzcha.zzizt.getString("currency");
    double d1;
    long l1;
    Object localObject;
    int i;
    if ("ecommerce_purchase".equals(paramZzcha.name))
    {
      double d2 = paramZzcha.zzizt.getDouble("value").doubleValue() * 1000000.0D;
      d1 = d2;
      if (d2 == 0.0D) {
        d1 = paramZzcha.zzizt.getLong("value").longValue() * 1000000.0D;
      }
      if ((d1 <= 9.223372036854776E18D) && (d1 >= -9.223372036854776E18D))
      {
        l1 = Math.round(d1);
        if (!TextUtils.isEmpty(str))
        {
          localObject = str.toUpperCase(Locale.US);
          if (((String)localObject).matches("[A-Z]{3}"))
          {
            str = String.valueOf("_ltv_");
            localObject = String.valueOf(localObject);
            if (((String)localObject).length() == 0) {
              break label379;
            }
            str = str.concat((String)localObject);
            localObject = zzaws().zzag(paramString, str);
            if ((localObject != null) && ((((zzclp)localObject).mValue instanceof Long))) {
              break label418;
            }
            localObject = zzaws();
            i = this.zzjew.zzb(paramString, zzchc.zzjbh);
            zzbq.zzgm(paramString);
            ((zzcjk)localObject).zzve();
            ((zzcjl)localObject).zzxf();
          }
        }
      }
    }
    for (;;)
    {
      try
      {
        ((zzcgo)localObject).getWritableDatabase().execSQL("delete from user_attributes where app_id=? and name in (select name from user_attributes where app_id=? and name like '_ltv_%' order by set_timestamp desc limit ?,10);", new String[] { paramString, paramString, String.valueOf(i - 1) });
        paramZzcha = new zzclp(paramString, paramZzcha.zziyf, str, this.zzata.currentTimeMillis(), Long.valueOf(l1));
        if (!zzaws().zza(paramZzcha))
        {
          zzawy().zzazd().zzd("Too many unique user properties are set. Ignoring user property. appId", zzchm.zzjk(paramString), zzawt().zzjj(paramZzcha.mName), paramZzcha.mValue);
          zzawu().zza(paramString, 9, null, null, 0);
        }
        return true;
        zzawy().zzazf().zze("Data lost. Currency value is too big. appId", zzchm.zzjk(paramString), Double.valueOf(d1));
        return false;
        l1 = paramZzcha.zzizt.getLong("value").longValue();
        break;
        label379:
        str = new String(str);
      }
      catch (SQLiteException localSQLiteException)
      {
        ((zzcjk)localObject).zzawy().zzazd().zze("Error pruning currencies. appId", zzchm.zzjk(paramString), localSQLiteException);
        continue;
      }
      label418:
      long l2 = ((Long)((zzclp)localObject).mValue).longValue();
      paramZzcha = new zzclp(paramString, paramZzcha.zziyf, str, this.zzata.currentTimeMillis(), Long.valueOf(l1 + l2));
    }
  }
  
  private final zzcma[] zza(String paramString, zzcmg[] paramArrayOfZzcmg, zzcmb[] paramArrayOfZzcmb)
  {
    zzbq.zzgm(paramString);
    return zzawl().zza(paramString, paramArrayOfZzcmb, paramArrayOfZzcmg);
  }
  
  static void zzawi()
  {
    throw new IllegalStateException("Unexpected call on client side");
  }
  
  @WorkerThread
  private final void zzazw()
  {
    zzawx().zzve();
    this.zzjfe.zzazw();
    this.zzjex.zzazw();
    this.zzjfn.zzazw();
    zzawy().zzazh().zzj("App measurement is starting up, version", Long.valueOf(11910L));
    zzawy().zzazh().log("To enable debug logging run: adb shell setprop log.tag.FA VERBOSE");
    String str = this.zzjfn.getAppId();
    zzcho localZzcho;
    if (zzawu().zzkj(str))
    {
      localZzcho = zzawy().zzazh();
      str = "Faster debug mode event logging enabled. To disable, run:\n  adb shell setprop debug.firebase.analytics.app .none.";
    }
    for (;;)
    {
      localZzcho.log(str);
      zzawy().zzazi().log("Debug-level message logging enabled");
      if (this.zzjfz != this.zzjga) {
        zzawy().zzazd().zze("Not all components initialized", Integer.valueOf(this.zzjfz), Integer.valueOf(this.zzjga));
      }
      this.zzdtb = true;
      return;
      localZzcho = zzawy().zzazh();
      str = String.valueOf(str);
      if (str.length() != 0) {
        str = "To enable faster debug mode event logging run:\n  adb shell setprop debug.firebase.analytics.app ".concat(str);
      } else {
        str = new String("To enable faster debug mode event logging run:\n  adb shell setprop debug.firebase.analytics.app ");
      }
    }
  }
  
  @WorkerThread
  private final void zzb(zzcgh paramZzcgh)
  {
    zzawx().zzve();
    if (TextUtils.isEmpty(paramZzcgh.getGmpAppId()))
    {
      zzb(paramZzcgh.getAppId(), 204, null, null, null);
      return;
    }
    Object localObject1 = paramZzcgh.getGmpAppId();
    String str2 = paramZzcgh.getAppInstanceId();
    Object localObject2 = new Uri.Builder();
    Object localObject3 = ((Uri.Builder)localObject2).scheme((String)zzchc.zzjah.get()).encodedAuthority((String)zzchc.zzjai.get());
    localObject1 = String.valueOf(localObject1);
    if (((String)localObject1).length() != 0)
    {
      localObject1 = "config/app/".concat((String)localObject1);
      ((Uri.Builder)localObject3).path((String)localObject1).appendQueryParameter("app_instance_id", str2).appendQueryParameter("platform", "android").appendQueryParameter("gmp_version", "11910");
      str2 = ((Uri.Builder)localObject2).build().toString();
    }
    for (;;)
    {
      try
      {
        localObject2 = new URL(str2);
        zzawy().zzazj().zzj("Fetching remote configuration", paramZzcgh.getAppId());
        localObject1 = zzawv().zzjs(paramZzcgh.getAppId());
        localObject3 = zzawv().zzjt(paramZzcgh.getAppId());
        if ((localObject1 == null) || (TextUtils.isEmpty((CharSequence)localObject3))) {
          break label336;
        }
        localObject1 = new ArrayMap();
        ((Map)localObject1).put("If-Modified-Since", localObject3);
        this.zzjgd = true;
        localObject3 = zzbab();
        String str3 = paramZzcgh.getAppId();
        zzciq localZzciq = new zzciq(this);
        ((zzcjk)localObject3).zzve();
        ((zzcjl)localObject3).zzxf();
        zzbq.checkNotNull(localObject2);
        zzbq.checkNotNull(localZzciq);
        ((zzcjk)localObject3).zzawx().zzh(new zzchu((zzchq)localObject3, str3, (URL)localObject2, null, (Map)localObject1, localZzciq));
        return;
      }
      catch (MalformedURLException localMalformedURLException)
      {
        zzawy().zzazd().zze("Failed to parse config URL. Not fetching. appId", zzchm.zzjk(paramZzcgh.getAppId()), str2);
        return;
      }
      String str1 = new String("config/app/");
      break;
      label336:
      str1 = null;
    }
  }
  
  private final zzchv zzbac()
  {
    if (this.zzjfo == null) {
      throw new IllegalStateException("Network broadcast receiver not created");
    }
    return this.zzjfo;
  }
  
  private final zzcll zzbad()
  {
    zza(this.zzjfp);
    return this.zzjfp;
  }
  
  @WorkerThread
  private final boolean zzbae()
  {
    zzawx().zzve();
    File localFile = new File(this.mContext.getFilesDir(), "google_app_measurement.db");
    try
    {
      this.zzjfw = new RandomAccessFile(localFile, "rw").getChannel();
      this.zzjfv = this.zzjfw.tryLock();
      if (this.zzjfv != null)
      {
        zzawy().zzazj().log("Storage concurrent access okay");
        return true;
      }
      zzawy().zzazd().log("Storage concurrent data access panic");
    }
    catch (FileNotFoundException localFileNotFoundException)
    {
      for (;;)
      {
        zzawy().zzazd().zzj("Failed to acquire storage lock", localFileNotFoundException);
      }
    }
    catch (IOException localIOException)
    {
      for (;;)
      {
        zzawy().zzazd().zzj("Failed to access storage lock file", localIOException);
      }
    }
    return false;
  }
  
  private final long zzbag()
  {
    long l3 = this.zzata.currentTimeMillis();
    zzchx localZzchx = zzawz();
    localZzchx.zzxf();
    localZzchx.zzve();
    long l2 = localZzchx.zzjcv.get();
    long l1 = l2;
    if (l2 == 0L)
    {
      l1 = 1L + localZzchx.zzawu().zzbaz().nextInt(86400000);
      localZzchx.zzjcv.set(l1);
    }
    return (l1 + l3) / 1000L / 60L / 60L / 24L;
  }
  
  private final boolean zzbai()
  {
    zzawx().zzve();
    zzxf();
    return (zzaws().zzayk()) || (!TextUtils.isEmpty(zzaws().zzayf()));
  }
  
  @WorkerThread
  private final void zzbaj()
  {
    zzawx().zzve();
    zzxf();
    if (!zzbam()) {
      return;
    }
    long l1;
    if (this.zzjgc > 0L)
    {
      l1 = 3600000L - Math.abs(this.zzata.elapsedRealtime() - this.zzjgc);
      if (l1 > 0L)
      {
        zzawy().zzazj().zzj("Upload has been suspended. Will update scheduling later in approximately ms", Long.valueOf(l1));
        zzbac().unregister();
        zzbad().cancel();
        return;
      }
      this.zzjgc = 0L;
    }
    if ((!zzazv()) || (!zzbai()))
    {
      zzawy().zzazj().log("Nothing to upload or uploading impossible");
      zzbac().unregister();
      zzbad().cancel();
      return;
    }
    long l3 = this.zzata.currentTimeMillis();
    long l2 = Math.max(0L, ((Long)zzchc.zzjbd.get()).longValue());
    int i;
    if ((zzaws().zzayl()) || (zzaws().zzayg()))
    {
      i = 1;
      if (i == 0) {
        break label346;
      }
      String str = this.zzjew.zzayd();
      if ((TextUtils.isEmpty(str)) || (".none.".equals(str))) {
        break label326;
      }
      l1 = Math.max(0L, ((Long)zzchc.zzjay.get()).longValue());
    }
    for (;;)
    {
      l6 = zzawz().zzjcr.get();
      l4 = zzawz().zzjcs.get();
      l5 = Math.max(zzaws().zzayi(), zzaws().zzayj());
      if (l5 != 0L) {
        break label366;
      }
      l1 = 0L;
      if (l1 != 0L) {
        break label562;
      }
      zzawy().zzazj().log("Next upload time is 0");
      zzbac().unregister();
      zzbad().cancel();
      return;
      i = 0;
      break;
      label326:
      l1 = Math.max(0L, ((Long)zzchc.zzjax.get()).longValue());
      continue;
      label346:
      l1 = Math.max(0L, ((Long)zzchc.zzjaw.get()).longValue());
    }
    label366:
    long l5 = l3 - Math.abs(l5 - l3);
    long l6 = Math.abs(l6 - l3);
    long l4 = l3 - Math.abs(l4 - l3);
    l6 = Math.max(l3 - l6, l4);
    l3 = l5 + l2;
    l2 = l3;
    if (i != 0)
    {
      l2 = l3;
      if (l6 > 0L) {
        l2 = Math.min(l5, l6) + l1;
      }
    }
    if (!zzawu().zzf(l6, l1)) {}
    for (l1 += l6;; l1 = l2)
    {
      l2 = l1;
      if (l4 != 0L)
      {
        l2 = l1;
        if (l4 >= l5)
        {
          i = 0;
          while (i < Math.min(20, Math.max(0, ((Integer)zzchc.zzjbf.get()).intValue())))
          {
            l1 = Math.max(0L, ((Long)zzchc.zzjbe.get()).longValue()) * (1L << i) + l1;
            l2 = l1;
            if (l1 > l4) {
              break label749;
            }
            i += 1;
          }
          l1 = 0L;
          break;
          label562:
          if (!zzbab().zzzs())
          {
            zzawy().zzazj().log("No network");
            zzbac().zzzp();
            zzbad().cancel();
            return;
          }
          l2 = zzawz().zzjct.get();
          l3 = Math.max(0L, ((Long)zzchc.zzjau.get()).longValue());
          if (!zzawu().zzf(l2, l3)) {
            l1 = Math.max(l1, l3 + l2);
          }
          for (;;)
          {
            zzbac().unregister();
            l2 = l1 - this.zzata.currentTimeMillis();
            l1 = l2;
            if (l2 <= 0L)
            {
              l1 = Math.max(0L, ((Long)zzchc.zzjaz.get()).longValue());
              zzawz().zzjcr.set(this.zzata.currentTimeMillis());
            }
            zzawy().zzazj().zzj("Upload scheduled in approximately ms", Long.valueOf(l1));
            zzbad().zzs(l1);
            return;
          }
        }
      }
      label749:
      l1 = l2;
      break;
    }
  }
  
  @WorkerThread
  private final boolean zzbam()
  {
    zzawx().zzve();
    zzxf();
    return this.zzjfs;
  }
  
  @WorkerThread
  private final void zzban()
  {
    zzawx().zzve();
    if ((this.zzjgd) || (this.zzjge) || (this.zzjgf)) {
      zzawy().zzazj().zzd("Not stopping services. fetch, network, upload", Boolean.valueOf(this.zzjgd), Boolean.valueOf(this.zzjge), Boolean.valueOf(this.zzjgf));
    }
    do
    {
      return;
      zzawy().zzazj().log("Stopping uploading service(s)");
    } while (this.zzjfy == null);
    Iterator localIterator = this.zzjfy.iterator();
    while (localIterator.hasNext()) {
      ((Runnable)localIterator.next()).run();
    }
    this.zzjfy.clear();
  }
  
  @WorkerThread
  private final void zzc(zzcha paramZzcha, zzcgi paramZzcgi)
  {
    zzbq.checkNotNull(paramZzcgi);
    zzbq.zzgm(paramZzcgi.packageName);
    long l1 = System.nanoTime();
    zzawx().zzve();
    zzxf();
    localObject1 = paramZzcgi.packageName;
    zzawu();
    if (!zzclq.zzd(paramZzcha, paramZzcgi)) {
      return;
    }
    if (!paramZzcgi.zzixx)
    {
      zzg(paramZzcgi);
      return;
    }
    if (zzawv().zzan((String)localObject1, paramZzcha.name))
    {
      zzawy().zzazf().zze("Dropping blacklisted event. appId", zzchm.zzjk((String)localObject1), zzawt().zzjh(paramZzcha.name));
      if ((zzawu().zzkl((String)localObject1)) || (zzawu().zzkm((String)localObject1))) {}
      for (i = 1;; i = 0)
      {
        if ((i == 0) && (!"_err".equals(paramZzcha.name))) {
          zzawu().zza((String)localObject1, 11, "_ev", paramZzcha.name, 0);
        }
        if (i == 0) {
          break;
        }
        paramZzcha = zzaws().zzjb((String)localObject1);
        if (paramZzcha == null) {
          break;
        }
        l1 = Math.max(paramZzcha.zzaxn(), paramZzcha.zzaxm());
        if (Math.abs(this.zzata.currentTimeMillis() - l1) <= ((Long)zzchc.zzjbc.get()).longValue()) {
          break;
        }
        zzawy().zzazi().log("Fetching config for blacklisted app");
        zzb(paramZzcha);
        return;
      }
    }
    if (zzawy().zzae(2)) {
      zzawy().zzazj().zzj("Logging event", zzawt().zzb(paramZzcha));
    }
    zzaws().beginTransaction();
    long l2;
    for (;;)
    {
      Object localObject2;
      try
      {
        zzg(paramZzcgi);
        if ((("_iap".equals(paramZzcha.name)) || ("ecommerce_purchase".equals(paramZzcha.name))) && (!zza((String)localObject1, paramZzcha)))
        {
          zzaws().setTransactionSuccessful();
          return;
        }
        bool1 = zzclq.zzjz(paramZzcha.name);
        boolean bool2 = "_err".equals(paramZzcha.name);
        localObject2 = zzaws().zza(zzbag(), (String)localObject1, true, bool1, false, bool2, false);
        l2 = ((zzcgp)localObject2).zziyy;
        i = ((Integer)zzchc.zzjan.get()).intValue();
        l2 -= i;
        if (l2 > 0L)
        {
          if (l2 % 1000L == 1L) {
            zzawy().zzazd().zze("Data loss. Too many events logged. appId, count", zzchm.zzjk((String)localObject1), Long.valueOf(((zzcgp)localObject2).zziyy));
          }
          zzaws().setTransactionSuccessful();
          return;
        }
        if (bool1)
        {
          l2 = ((zzcgp)localObject2).zziyx;
          i = ((Integer)zzchc.zzjap.get()).intValue();
          l2 -= i;
          if (l2 > 0L)
          {
            if (l2 % 1000L == 1L) {
              zzawy().zzazd().zze("Data loss. Too many public events logged. appId, count", zzchm.zzjk((String)localObject1), Long.valueOf(((zzcgp)localObject2).zziyx));
            }
            zzawu().zza((String)localObject1, 16, "_ev", paramZzcha.name, 0);
            zzaws().setTransactionSuccessful();
            return;
          }
        }
        if (bool2)
        {
          l2 = ((zzcgp)localObject2).zziza - Math.max(0, Math.min(1000000, this.zzjew.zzb(paramZzcgi.packageName, zzchc.zzjao)));
          if (l2 > 0L)
          {
            if (l2 == 1L) {
              zzawy().zzazd().zze("Too many error events logged. appId, count", zzchm.zzjk((String)localObject1), Long.valueOf(((zzcgp)localObject2).zziza));
            }
            zzaws().setTransactionSuccessful();
            return;
          }
        }
        localObject2 = paramZzcha.zzizt.zzayx();
        zzawu().zza((Bundle)localObject2, "_o", paramZzcha.zziyf);
        if (zzawu().zzkj((String)localObject1))
        {
          zzawu().zza((Bundle)localObject2, "_dbg", Long.valueOf(1L));
          zzawu().zza((Bundle)localObject2, "_r", Long.valueOf(1L));
        }
        l2 = zzaws().zzjc((String)localObject1);
        if (l2 > 0L) {
          zzawy().zzazf().zze("Data lost. Too many events stored on disk, deleted. appId", zzchm.zzjk((String)localObject1), Long.valueOf(l2));
        }
        paramZzcha = new zzcgv(this, paramZzcha.zziyf, (String)localObject1, paramZzcha.name, paramZzcha.zzizu, 0L, (Bundle)localObject2);
        localObject2 = zzaws().zzae((String)localObject1, paramZzcha.mName);
        if (localObject2 == null)
        {
          if ((zzaws().zzjf((String)localObject1) >= 500L) && (bool1))
          {
            zzawy().zzazd().zzd("Too many event names used, ignoring event. appId, name, supported count", zzchm.zzjk((String)localObject1), zzawt().zzjh(paramZzcha.mName), Integer.valueOf(500));
            zzawu().zza((String)localObject1, 8, null, null, 0);
            return;
          }
          localObject1 = new zzcgw((String)localObject1, paramZzcha.mName, 0L, 0L, paramZzcha.zzfij, 0L, null, null, null);
          zzaws().zza((zzcgw)localObject1);
          zzawx().zzve();
          zzxf();
          zzbq.checkNotNull(paramZzcha);
          zzbq.checkNotNull(paramZzcgi);
          zzbq.zzgm(paramZzcha.mAppId);
          zzbq.checkArgument(paramZzcha.mAppId.equals(paramZzcgi.packageName));
          localZzcme = new zzcme();
          localZzcme.zzjlo = Integer.valueOf(1);
          localZzcme.zzjlw = "android";
          localZzcme.zzcn = paramZzcgi.packageName;
          localZzcme.zzixt = paramZzcgi.zzixt;
          localZzcme.zzifm = paramZzcgi.zzifm;
          if (paramZzcgi.zzixz == -2147483648L)
          {
            localObject1 = null;
            localZzcme.zzjmj = ((Integer)localObject1);
            localZzcme.zzjma = Long.valueOf(paramZzcgi.zzixu);
            localZzcme.zzixs = paramZzcgi.zzixs;
            if (paramZzcgi.zzixv != 0L) {
              continue;
            }
            localObject1 = null;
            localZzcme.zzjmf = ((Long)localObject1);
            localObject1 = zzawz().zzjm(paramZzcgi.packageName);
            if ((localObject1 == null) || (TextUtils.isEmpty((CharSequence)((Pair)localObject1).first))) {
              continue;
            }
            if (paramZzcgi.zziye)
            {
              localZzcme.zzjmc = ((String)((Pair)localObject1).first);
              localZzcme.zzjmd = ((Boolean)((Pair)localObject1).second);
            }
            zzawo().zzxf();
            localZzcme.zzjlx = Build.MODEL;
            zzawo().zzxf();
            localZzcme.zzdb = Build.VERSION.RELEASE;
            localZzcme.zzjlz = Integer.valueOf((int)zzawo().zzayu());
            localZzcme.zzjly = zzawo().zzayv();
            localZzcme.zzjmb = null;
            localZzcme.zzjlr = null;
            localZzcme.zzjls = null;
            localZzcme.zzjlt = null;
            localZzcme.zzfkk = Long.valueOf(paramZzcgi.zziyb);
            if ((isEnabled()) && (zzcgn.zzaye()))
            {
              zzawn();
              localZzcme.zzjmo = null;
            }
            localObject2 = zzaws().zzjb(paramZzcgi.packageName);
            localObject1 = localObject2;
            if (localObject2 == null)
            {
              localObject1 = new zzcgh(this, paramZzcgi.packageName);
              ((zzcgh)localObject1).zzir(zzawn().zzayz());
              ((zzcgh)localObject1).zziu(paramZzcgi.zziya);
              ((zzcgh)localObject1).zzis(paramZzcgi.zzixs);
              ((zzcgh)localObject1).zzit(zzawz().zzjn(paramZzcgi.packageName));
              ((zzcgh)localObject1).zzaq(0L);
              ((zzcgh)localObject1).zzal(0L);
              ((zzcgh)localObject1).zzam(0L);
              ((zzcgh)localObject1).setAppVersion(paramZzcgi.zzifm);
              ((zzcgh)localObject1).zzan(paramZzcgi.zzixz);
              ((zzcgh)localObject1).zziv(paramZzcgi.zzixt);
              ((zzcgh)localObject1).zzao(paramZzcgi.zzixu);
              ((zzcgh)localObject1).zzap(paramZzcgi.zzixv);
              ((zzcgh)localObject1).setMeasurementEnabled(paramZzcgi.zzixx);
              ((zzcgh)localObject1).zzaz(paramZzcgi.zziyb);
              zzaws().zza((zzcgh)localObject1);
            }
            localZzcme.zzjme = ((zzcgh)localObject1).getAppInstanceId();
            localZzcme.zziya = ((zzcgh)localObject1).zzaxd();
            paramZzcgi = zzaws().zzja(paramZzcgi.packageName);
            localZzcme.zzjlq = new zzcmg[paramZzcgi.size()];
            i = 0;
            if (i >= paramZzcgi.size()) {
              break;
            }
            localObject1 = new zzcmg();
            localZzcme.zzjlq[i] = localObject1;
            ((zzcmg)localObject1).name = ((zzclp)paramZzcgi.get(i)).mName;
            ((zzcmg)localObject1).zzjms = Long.valueOf(((zzclp)paramZzcgi.get(i)).zzjjm);
            zzawu().zza((zzcmg)localObject1, ((zzclp)paramZzcgi.get(i)).mValue);
            i += 1;
            continue;
          }
        }
        else
        {
          paramZzcha = paramZzcha.zza(this, ((zzcgw)localObject2).zzizm);
          localObject1 = ((zzcgw)localObject2).zzbb(paramZzcha.zzfij);
          continue;
        }
        localObject1 = Integer.valueOf((int)paramZzcgi.zzixz);
        continue;
        localObject1 = Long.valueOf(paramZzcgi.zzixv);
        continue;
        if (zzawo().zzdw(this.mContext)) {
          continue;
        }
        localObject2 = Settings.Secure.getString(this.mContext.getContentResolver(), "android_id");
        if (localObject2 == null)
        {
          zzawy().zzazf().zzj("null secure ID. appId", zzchm.zzjk(localZzcme.zzcn));
          localObject1 = "null";
          localZzcme.zzjmm = ((String)localObject1);
          continue;
        }
        localObject1 = localObject2;
      }
      finally
      {
        zzaws().endTransaction();
      }
      if (((String)localObject2).isEmpty())
      {
        zzawy().zzazf().zzj("empty secure ID. appId", zzchm.zzjk(localZzcme.zzcn));
        localObject1 = localObject2;
      }
    }
    try
    {
      l2 = zzaws().zza(localZzcme);
      paramZzcgi = zzaws();
      if (paramZzcha.zzizj == null) {
        break label2041;
      }
      localObject1 = paramZzcha.zzizj.iterator();
      do
      {
        if (!((Iterator)localObject1).hasNext()) {
          break;
        }
      } while (!"_r".equals((String)((Iterator)localObject1).next()));
      bool1 = true;
    }
    catch (IOException paramZzcgi)
    {
      for (;;)
      {
        zzawy().zzazd().zze("Data loss. Failed to insert raw event metadata. appId", zzchm.zzjk(localZzcme.zzcn), paramZzcgi);
        continue;
        bool1 = zzawv().zzao(paramZzcha.mAppId, paramZzcha.mName);
        localObject1 = zzaws().zza(zzbag(), paramZzcha.mAppId, false, false, false, false, false);
        if (bool1)
        {
          long l3 = ((zzcgp)localObject1).zzizb;
          i = this.zzjew.zzix(paramZzcha.mAppId);
          if (l3 < i)
          {
            bool1 = true;
            continue;
          }
        }
        bool1 = false;
      }
    }
    if (paramZzcgi.zza(paramZzcha, l2, bool1)) {
      this.zzjgc = 0L;
    }
    zzaws().setTransactionSuccessful();
    if (zzawy().zzae(2)) {
      zzawy().zzazj().zzj("Event recorded", zzawt().zza(paramZzcha));
    }
    zzaws().endTransaction();
    zzbaj();
    zzawy().zzazj().zzj("Background event processing time, ms", Long.valueOf((System.nanoTime() - l1 + 500000L) / 1000000L));
  }
  
  public static zzcim zzdx(Context paramContext)
  {
    zzbq.checkNotNull(paramContext);
    zzbq.checkNotNull(paramContext.getApplicationContext());
    if (zzjev == null) {}
    try
    {
      if (zzjev == null) {
        zzjev = new zzcim(new zzcjm(paramContext));
      }
      return zzjev;
    }
    finally {}
  }
  
  @WorkerThread
  private final void zzg(zzcgi paramZzcgi)
  {
    int k = 1;
    zzawx().zzve();
    zzxf();
    zzbq.checkNotNull(paramZzcgi);
    zzbq.zzgm(paramZzcgi.packageName);
    zzcgh localZzcgh2 = zzaws().zzjb(paramZzcgi.packageName);
    String str = zzawz().zzjn(paramZzcgi.packageName);
    int i = 0;
    zzcgh localZzcgh1;
    int j;
    if (localZzcgh2 == null)
    {
      localZzcgh1 = new zzcgh(this, paramZzcgi.packageName);
      localZzcgh1.zzir(zzawn().zzayz());
      localZzcgh1.zzit(str);
      i = 1;
      j = i;
      if (!TextUtils.isEmpty(paramZzcgi.zzixs))
      {
        j = i;
        if (!paramZzcgi.zzixs.equals(localZzcgh1.getGmpAppId()))
        {
          localZzcgh1.zzis(paramZzcgi.zzixs);
          j = 1;
        }
      }
      i = j;
      if (!TextUtils.isEmpty(paramZzcgi.zziya))
      {
        i = j;
        if (!paramZzcgi.zziya.equals(localZzcgh1.zzaxd()))
        {
          localZzcgh1.zziu(paramZzcgi.zziya);
          i = 1;
        }
      }
      j = i;
      if (paramZzcgi.zzixu != 0L)
      {
        j = i;
        if (paramZzcgi.zzixu != localZzcgh1.zzaxi())
        {
          localZzcgh1.zzao(paramZzcgi.zzixu);
          j = 1;
        }
      }
      i = j;
      if (!TextUtils.isEmpty(paramZzcgi.zzifm))
      {
        i = j;
        if (!paramZzcgi.zzifm.equals(localZzcgh1.zzvj()))
        {
          localZzcgh1.setAppVersion(paramZzcgi.zzifm);
          i = 1;
        }
      }
      if (paramZzcgi.zzixz != localZzcgh1.zzaxg())
      {
        localZzcgh1.zzan(paramZzcgi.zzixz);
        i = 1;
      }
      j = i;
      if (paramZzcgi.zzixt != null)
      {
        j = i;
        if (!paramZzcgi.zzixt.equals(localZzcgh1.zzaxh()))
        {
          localZzcgh1.zziv(paramZzcgi.zzixt);
          j = 1;
        }
      }
      i = j;
      if (paramZzcgi.zzixv != localZzcgh1.zzaxj())
      {
        localZzcgh1.zzap(paramZzcgi.zzixv);
        i = 1;
      }
      if (paramZzcgi.zzixx != localZzcgh1.zzaxk())
      {
        localZzcgh1.setMeasurementEnabled(paramZzcgi.zzixx);
        i = 1;
      }
      j = i;
      if (!TextUtils.isEmpty(paramZzcgi.zzixw))
      {
        j = i;
        if (!paramZzcgi.zzixw.equals(localZzcgh1.zzaxv()))
        {
          localZzcgh1.zziw(paramZzcgi.zzixw);
          j = 1;
        }
      }
      if (paramZzcgi.zziyb != localZzcgh1.zzaxx())
      {
        localZzcgh1.zzaz(paramZzcgi.zziyb);
        j = 1;
      }
      if (paramZzcgi.zziye == localZzcgh1.zzaxy()) {
        break label509;
      }
      localZzcgh1.zzbl(paramZzcgi.zziye);
    }
    label509:
    for (i = k;; i = j)
    {
      if (i != 0) {
        zzaws().zza(localZzcgh1);
      }
      return;
      localZzcgh1 = localZzcgh2;
      if (str.equals(localZzcgh2.zzaxc())) {
        break;
      }
      localZzcgh2.zzit(str);
      localZzcgh2.zzir(zzawn().zzayz());
      i = 1;
      localZzcgh1 = localZzcgh2;
      break;
    }
  }
  
  /* Error */
  private final boolean zzg(String paramString, long paramLong)
  {
    // Byte code:
    //   0: aload_0
    //   1: invokevirtual 604	com/google/android/gms/internal/zzcim:zzaws	()Lcom/google/android/gms/internal/zzcgo;
    //   4: invokevirtual 1146	com/google/android/gms/internal/zzcgo:beginTransaction	()V
    //   7: new 6	com/google/android/gms/internal/zzcim$zza
    //   10: dup
    //   11: aload_0
    //   12: aconst_null
    //   13: invokespecial 1584	com/google/android/gms/internal/zzcim$zza:<init>	(Lcom/google/android/gms/internal/zzcim;Lcom/google/android/gms/internal/zzcin;)V
    //   16: astore 22
    //   18: aload_0
    //   19: invokevirtual 604	com/google/android/gms/internal/zzcim:zzaws	()Lcom/google/android/gms/internal/zzcgo;
    //   22: astore 23
    //   24: aload_0
    //   25: getfield 103	com/google/android/gms/internal/zzcim:zzjgb	J
    //   28: lstore 10
    //   30: aload 22
    //   32: invokestatic 94	com/google/android/gms/common/internal/zzbq:checkNotNull	(Ljava/lang/Object;)Ljava/lang/Object;
    //   35: pop
    //   36: aload 23
    //   38: invokevirtual 311	com/google/android/gms/internal/zzcjk:zzve	()V
    //   41: aload 23
    //   43: invokevirtual 630	com/google/android/gms/internal/zzcjl:zzxf	()V
    //   46: aload 23
    //   48: invokevirtual 634	com/google/android/gms/internal/zzcgo:getWritableDatabase	()Landroid/database/sqlite/SQLiteDatabase;
    //   51: astore 24
    //   53: aconst_null
    //   54: invokestatic 403	android/text/TextUtils:isEmpty	(Ljava/lang/CharSequence;)Z
    //   57: ifeq +586 -> 643
    //   60: lload 10
    //   62: ldc2_w 100
    //   65: lcmp
    //   66: ifeq +394 -> 460
    //   69: iconst_2
    //   70: anewarray 445	java/lang/String
    //   73: dup
    //   74: iconst_0
    //   75: lload 10
    //   77: invokestatic 1587	java/lang/String:valueOf	(J)Ljava/lang/String;
    //   80: aastore
    //   81: dup
    //   82: iconst_1
    //   83: lload_2
    //   84: invokestatic 1587	java/lang/String:valueOf	(J)Ljava/lang/String;
    //   87: aastore
    //   88: astore_1
    //   89: lload 10
    //   91: ldc2_w 100
    //   94: lcmp
    //   95: ifeq +380 -> 475
    //   98: ldc_w 1589
    //   101: astore 16
    //   103: aload 24
    //   105: new 1591	java/lang/StringBuilder
    //   108: dup
    //   109: aload 16
    //   111: invokestatic 594	java/lang/String:valueOf	(Ljava/lang/Object;)Ljava/lang/String;
    //   114: invokevirtual 597	java/lang/String:length	()I
    //   117: sipush 148
    //   120: iadd
    //   121: invokespecial 1594	java/lang/StringBuilder:<init>	(I)V
    //   124: ldc_w 1596
    //   127: invokevirtual 1600	java/lang/StringBuilder:append	(Ljava/lang/String;)Ljava/lang/StringBuilder;
    //   130: aload 16
    //   132: invokevirtual 1600	java/lang/StringBuilder:append	(Ljava/lang/String;)Ljava/lang/StringBuilder;
    //   135: ldc_w 1602
    //   138: invokevirtual 1600	java/lang/StringBuilder:append	(Ljava/lang/String;)Ljava/lang/StringBuilder;
    //   141: invokevirtual 1603	java/lang/StringBuilder:toString	()Ljava/lang/String;
    //   144: aload_1
    //   145: invokevirtual 1607	android/database/sqlite/SQLiteDatabase:rawQuery	(Ljava/lang/String;[Ljava/lang/String;)Landroid/database/Cursor;
    //   148: astore_1
    //   149: aload_1
    //   150: astore 16
    //   152: aload_1
    //   153: astore 17
    //   155: aload_1
    //   156: invokeinterface 1612 1 0
    //   161: istore 12
    //   163: iload 12
    //   165: ifne +318 -> 483
    //   168: aload_1
    //   169: ifnull +9 -> 178
    //   172: aload_1
    //   173: invokeinterface 1615 1 0
    //   178: aload 22
    //   180: getfield 1618	com/google/android/gms/internal/zzcim$zza:zzapa	Ljava/util/List;
    //   183: ifnull +3900 -> 4083
    //   186: aload 22
    //   188: getfield 1618	com/google/android/gms/internal/zzcim$zza:zzapa	Ljava/util/List;
    //   191: invokeinterface 1619 1 0
    //   196: ifeq +3906 -> 4102
    //   199: goto +3884 -> 4083
    //   202: iload 4
    //   204: ifne +3774 -> 3978
    //   207: iconst_0
    //   208: istore 12
    //   210: aload 22
    //   212: getfield 1623	com/google/android/gms/internal/zzcim$zza:zzjgi	Lcom/google/android/gms/internal/zzcme;
    //   215: astore 17
    //   217: aload 17
    //   219: aload 22
    //   221: getfield 1618	com/google/android/gms/internal/zzcim$zza:zzapa	Ljava/util/List;
    //   224: invokeinterface 1442 1 0
    //   229: anewarray 502	com/google/android/gms/internal/zzcmb
    //   232: putfield 1627	com/google/android/gms/internal/zzcme:zzjlp	[Lcom/google/android/gms/internal/zzcmb;
    //   235: iconst_0
    //   236: istore 4
    //   238: iconst_0
    //   239: istore 6
    //   241: iload 6
    //   243: aload 22
    //   245: getfield 1618	com/google/android/gms/internal/zzcim$zza:zzapa	Ljava/util/List;
    //   248: invokeinterface 1442 1 0
    //   253: if_icmpge +2189 -> 2442
    //   256: aload_0
    //   257: invokevirtual 793	com/google/android/gms/internal/zzcim:zzawv	()Lcom/google/android/gms/internal/zzcig;
    //   260: aload 22
    //   262: getfield 1623	com/google/android/gms/internal/zzcim$zza:zzjgi	Lcom/google/android/gms/internal/zzcme;
    //   265: getfield 1259	com/google/android/gms/internal/zzcme:zzcn	Ljava/lang/String;
    //   268: aload 22
    //   270: getfield 1618	com/google/android/gms/internal/zzcim$zza:zzapa	Ljava/util/List;
    //   273: iload 6
    //   275: invokeinterface 1452 2 0
    //   280: checkcast 502	com/google/android/gms/internal/zzcmb
    //   283: getfield 1628	com/google/android/gms/internal/zzcmb:name	Ljava/lang/String;
    //   286: invokevirtual 1102	com/google/android/gms/internal/zzcig:zzan	(Ljava/lang/String;Ljava/lang/String;)Z
    //   289: ifeq +1143 -> 1432
    //   292: aload_0
    //   293: invokevirtual 293	com/google/android/gms/internal/zzcim:zzawy	()Lcom/google/android/gms/internal/zzchm;
    //   296: invokevirtual 296	com/google/android/gms/internal/zzchm:zzazf	()Lcom/google/android/gms/internal/zzcho;
    //   299: ldc_w 1630
    //   302: aload 22
    //   304: getfield 1623	com/google/android/gms/internal/zzcim$zza:zzjgi	Lcom/google/android/gms/internal/zzcme;
    //   307: getfield 1259	com/google/android/gms/internal/zzcme:zzcn	Ljava/lang/String;
    //   310: invokestatic 441	com/google/android/gms/internal/zzchm:zzjk	(Ljava/lang/String;)Ljava/lang/Object;
    //   313: aload_0
    //   314: invokevirtual 660	com/google/android/gms/internal/zzcim:zzawt	()Lcom/google/android/gms/internal/zzchk;
    //   317: aload 22
    //   319: getfield 1618	com/google/android/gms/internal/zzcim$zza:zzapa	Ljava/util/List;
    //   322: iload 6
    //   324: invokeinterface 1452 2 0
    //   329: checkcast 502	com/google/android/gms/internal/zzcmb
    //   332: getfield 1628	com/google/android/gms/internal/zzcmb:name	Ljava/lang/String;
    //   335: invokevirtual 1107	com/google/android/gms/internal/zzchk:zzjh	(Ljava/lang/String;)Ljava/lang/String;
    //   338: invokevirtual 455	com/google/android/gms/internal/zzcho:zze	(Ljava/lang/String;Ljava/lang/Object;Ljava/lang/Object;)V
    //   341: aload_0
    //   342: invokevirtual 426	com/google/android/gms/internal/zzcim:zzawu	()Lcom/google/android/gms/internal/zzclq;
    //   345: aload 22
    //   347: getfield 1623	com/google/android/gms/internal/zzcim$zza:zzjgi	Lcom/google/android/gms/internal/zzcme;
    //   350: getfield 1259	com/google/android/gms/internal/zzcme:zzcn	Ljava/lang/String;
    //   353: invokevirtual 1110	com/google/android/gms/internal/zzclq:zzkl	(Ljava/lang/String;)Z
    //   356: ifne +3733 -> 4089
    //   359: aload_0
    //   360: invokevirtual 426	com/google/android/gms/internal/zzcim:zzawu	()Lcom/google/android/gms/internal/zzclq;
    //   363: aload 22
    //   365: getfield 1623	com/google/android/gms/internal/zzcim$zza:zzjgi	Lcom/google/android/gms/internal/zzcme;
    //   368: getfield 1259	com/google/android/gms/internal/zzcme:zzcn	Ljava/lang/String;
    //   371: invokevirtual 1113	com/google/android/gms/internal/zzclq:zzkm	(Ljava/lang/String;)Z
    //   374: ifeq +3734 -> 4108
    //   377: goto +3712 -> 4089
    //   380: iload 5
    //   382: ifne +3639 -> 4021
    //   385: ldc_w 1115
    //   388: aload 22
    //   390: getfield 1618	com/google/android/gms/internal/zzcim$zza:zzapa	Ljava/util/List;
    //   393: iload 6
    //   395: invokeinterface 1452 2 0
    //   400: checkcast 502	com/google/android/gms/internal/zzcmb
    //   403: getfield 1628	com/google/android/gms/internal/zzcmb:name	Ljava/lang/String;
    //   406: invokevirtual 449	java/lang/String:equals	(Ljava/lang/Object;)Z
    //   409: ifne +3612 -> 4021
    //   412: aload_0
    //   413: invokevirtual 426	com/google/android/gms/internal/zzcim:zzawu	()Lcom/google/android/gms/internal/zzclq;
    //   416: aload 22
    //   418: getfield 1623	com/google/android/gms/internal/zzcim$zza:zzjgi	Lcom/google/android/gms/internal/zzcme;
    //   421: getfield 1259	com/google/android/gms/internal/zzcme:zzcn	Ljava/lang/String;
    //   424: bipush 11
    //   426: ldc_w 1117
    //   429: aload 22
    //   431: getfield 1618	com/google/android/gms/internal/zzcim$zza:zzapa	Ljava/util/List;
    //   434: iload 6
    //   436: invokeinterface 1452 2 0
    //   441: checkcast 502	com/google/android/gms/internal/zzcmb
    //   444: getfield 1628	com/google/android/gms/internal/zzcmb:name	Ljava/lang/String;
    //   447: iconst_0
    //   448: invokevirtual 673	com/google/android/gms/internal/zzclq:zza	(Ljava/lang/String;ILjava/lang/String;Ljava/lang/String;I)V
    //   451: iload 6
    //   453: iconst_1
    //   454: iadd
    //   455: istore 6
    //   457: goto -216 -> 241
    //   460: iconst_1
    //   461: anewarray 445	java/lang/String
    //   464: dup
    //   465: iconst_0
    //   466: lload_2
    //   467: invokestatic 1587	java/lang/String:valueOf	(J)Ljava/lang/String;
    //   470: aastore
    //   471: astore_1
    //   472: goto -383 -> 89
    //   475: ldc_w 432
    //   478: astore 16
    //   480: goto -377 -> 103
    //   483: aload_1
    //   484: astore 16
    //   486: aload_1
    //   487: astore 17
    //   489: aload_1
    //   490: iconst_0
    //   491: invokeinterface 1632 2 0
    //   496: astore 18
    //   498: aload_1
    //   499: astore 17
    //   501: aload_1
    //   502: iconst_1
    //   503: invokeinterface 1632 2 0
    //   508: astore 16
    //   510: aload_1
    //   511: astore 17
    //   513: aload_1
    //   514: invokeinterface 1615 1 0
    //   519: aload 18
    //   521: astore 17
    //   523: aload 16
    //   525: astore 18
    //   527: aload_1
    //   528: astore 16
    //   530: aload 24
    //   532: ldc_w 1634
    //   535: iconst_1
    //   536: anewarray 445	java/lang/String
    //   539: dup
    //   540: iconst_0
    //   541: ldc_w 1636
    //   544: aastore
    //   545: ldc_w 1638
    //   548: iconst_2
    //   549: anewarray 445	java/lang/String
    //   552: dup
    //   553: iconst_0
    //   554: aload 17
    //   556: aastore
    //   557: dup
    //   558: iconst_1
    //   559: aload 18
    //   561: aastore
    //   562: aconst_null
    //   563: aconst_null
    //   564: ldc_w 1640
    //   567: ldc_w 1642
    //   570: invokevirtual 1646	android/database/sqlite/SQLiteDatabase:query	(Ljava/lang/String;[Ljava/lang/String;Ljava/lang/String;[Ljava/lang/String;Ljava/lang/String;Ljava/lang/String;Ljava/lang/String;Ljava/lang/String;)Landroid/database/Cursor;
    //   573: astore 19
    //   575: aload 19
    //   577: astore 16
    //   579: aload 19
    //   581: astore_1
    //   582: aload 19
    //   584: invokeinterface 1612 1 0
    //   589: ifne +224 -> 813
    //   592: aload 19
    //   594: astore 16
    //   596: aload 19
    //   598: astore_1
    //   599: aload 23
    //   601: invokevirtual 273	com/google/android/gms/internal/zzcjk:zzawy	()Lcom/google/android/gms/internal/zzchm;
    //   604: invokevirtual 320	com/google/android/gms/internal/zzchm:zzazd	()Lcom/google/android/gms/internal/zzcho;
    //   607: ldc_w 1648
    //   610: aload 17
    //   612: invokestatic 441	com/google/android/gms/internal/zzchm:zzjk	(Ljava/lang/String;)Ljava/lang/Object;
    //   615: invokevirtual 348	com/google/android/gms/internal/zzcho:zzj	(Ljava/lang/String;Ljava/lang/Object;)V
    //   618: aload 19
    //   620: ifnull -442 -> 178
    //   623: aload 19
    //   625: invokeinterface 1615 1 0
    //   630: goto -452 -> 178
    //   633: astore_1
    //   634: aload_0
    //   635: invokevirtual 604	com/google/android/gms/internal/zzcim:zzaws	()Lcom/google/android/gms/internal/zzcgo;
    //   638: invokevirtual 1156	com/google/android/gms/internal/zzcgo:endTransaction	()V
    //   641: aload_1
    //   642: athrow
    //   643: lload 10
    //   645: ldc2_w 100
    //   648: lcmp
    //   649: ifeq +111 -> 760
    //   652: iconst_2
    //   653: anewarray 445	java/lang/String
    //   656: dup
    //   657: iconst_0
    //   658: aconst_null
    //   659: aastore
    //   660: dup
    //   661: iconst_1
    //   662: lload 10
    //   664: invokestatic 1587	java/lang/String:valueOf	(J)Ljava/lang/String;
    //   667: aastore
    //   668: astore_1
    //   669: lload 10
    //   671: ldc2_w 100
    //   674: lcmp
    //   675: ifeq +97 -> 772
    //   678: ldc_w 1650
    //   681: astore 16
    //   683: aload 24
    //   685: new 1591	java/lang/StringBuilder
    //   688: dup
    //   689: aload 16
    //   691: invokestatic 594	java/lang/String:valueOf	(Ljava/lang/Object;)Ljava/lang/String;
    //   694: invokevirtual 597	java/lang/String:length	()I
    //   697: bipush 84
    //   699: iadd
    //   700: invokespecial 1594	java/lang/StringBuilder:<init>	(I)V
    //   703: ldc_w 1652
    //   706: invokevirtual 1600	java/lang/StringBuilder:append	(Ljava/lang/String;)Ljava/lang/StringBuilder;
    //   709: aload 16
    //   711: invokevirtual 1600	java/lang/StringBuilder:append	(Ljava/lang/String;)Ljava/lang/StringBuilder;
    //   714: ldc_w 1654
    //   717: invokevirtual 1600	java/lang/StringBuilder:append	(Ljava/lang/String;)Ljava/lang/StringBuilder;
    //   720: invokevirtual 1603	java/lang/StringBuilder:toString	()Ljava/lang/String;
    //   723: aload_1
    //   724: invokevirtual 1607	android/database/sqlite/SQLiteDatabase:rawQuery	(Ljava/lang/String;[Ljava/lang/String;)Landroid/database/Cursor;
    //   727: astore_1
    //   728: aload_1
    //   729: astore 16
    //   731: aload_1
    //   732: astore 17
    //   734: aload_1
    //   735: invokeinterface 1612 1 0
    //   740: istore 12
    //   742: iload 12
    //   744: ifne +36 -> 780
    //   747: aload_1
    //   748: ifnull -570 -> 178
    //   751: aload_1
    //   752: invokeinterface 1615 1 0
    //   757: goto -579 -> 178
    //   760: iconst_1
    //   761: anewarray 445	java/lang/String
    //   764: dup
    //   765: iconst_0
    //   766: aconst_null
    //   767: aastore
    //   768: astore_1
    //   769: goto -100 -> 669
    //   772: ldc_w 432
    //   775: astore 16
    //   777: goto -94 -> 683
    //   780: aload_1
    //   781: astore 16
    //   783: aload_1
    //   784: astore 17
    //   786: aload_1
    //   787: iconst_0
    //   788: invokeinterface 1632 2 0
    //   793: astore 18
    //   795: aload_1
    //   796: astore 16
    //   798: aload_1
    //   799: astore 17
    //   801: aload_1
    //   802: invokeinterface 1615 1 0
    //   807: aconst_null
    //   808: astore 17
    //   810: goto -283 -> 527
    //   813: aload 19
    //   815: astore 16
    //   817: aload 19
    //   819: astore_1
    //   820: aload 19
    //   822: iconst_0
    //   823: invokeinterface 1658 2 0
    //   828: astore 20
    //   830: aload 19
    //   832: astore 16
    //   834: aload 19
    //   836: astore_1
    //   837: aload 20
    //   839: iconst_0
    //   840: aload 20
    //   842: arraylength
    //   843: invokestatic 1664	com/google/android/gms/internal/zzfjj:zzn	([BII)Lcom/google/android/gms/internal/zzfjj;
    //   846: astore 20
    //   848: aload 19
    //   850: astore 16
    //   852: aload 19
    //   854: astore_1
    //   855: new 1248	com/google/android/gms/internal/zzcme
    //   858: dup
    //   859: invokespecial 1249	com/google/android/gms/internal/zzcme:<init>	()V
    //   862: astore 21
    //   864: aload 19
    //   866: astore 16
    //   868: aload 19
    //   870: astore_1
    //   871: aload 21
    //   873: aload 20
    //   875: invokevirtual 1669	com/google/android/gms/internal/zzfjs:zza	(Lcom/google/android/gms/internal/zzfjj;)Lcom/google/android/gms/internal/zzfjs;
    //   878: pop
    //   879: aload 19
    //   881: astore 16
    //   883: aload 19
    //   885: astore_1
    //   886: aload 19
    //   888: invokeinterface 1672 1 0
    //   893: ifeq +29 -> 922
    //   896: aload 19
    //   898: astore 16
    //   900: aload 19
    //   902: astore_1
    //   903: aload 23
    //   905: invokevirtual 273	com/google/android/gms/internal/zzcjk:zzawy	()Lcom/google/android/gms/internal/zzchm;
    //   908: invokevirtual 296	com/google/android/gms/internal/zzchm:zzazf	()Lcom/google/android/gms/internal/zzcho;
    //   911: ldc_w 1674
    //   914: aload 17
    //   916: invokestatic 441	com/google/android/gms/internal/zzchm:zzjk	(Ljava/lang/String;)Ljava/lang/Object;
    //   919: invokevirtual 348	com/google/android/gms/internal/zzcho:zzj	(Ljava/lang/String;Ljava/lang/Object;)V
    //   922: aload 19
    //   924: astore 16
    //   926: aload 19
    //   928: astore_1
    //   929: aload 19
    //   931: invokeinterface 1615 1 0
    //   936: aload 19
    //   938: astore 16
    //   940: aload 19
    //   942: astore_1
    //   943: aload 22
    //   945: aload 21
    //   947: invokeinterface 1679 2 0
    //   952: lload 10
    //   954: ldc2_w 100
    //   957: lcmp
    //   958: ifeq +203 -> 1161
    //   961: ldc_w 1681
    //   964: astore 21
    //   966: aload 19
    //   968: astore 16
    //   970: aload 19
    //   972: astore_1
    //   973: iconst_3
    //   974: anewarray 445	java/lang/String
    //   977: astore 20
    //   979: aload 20
    //   981: iconst_0
    //   982: aload 17
    //   984: aastore
    //   985: aload 20
    //   987: iconst_1
    //   988: aload 18
    //   990: aastore
    //   991: aload 19
    //   993: astore 16
    //   995: aload 19
    //   997: astore_1
    //   998: aload 20
    //   1000: iconst_2
    //   1001: lload 10
    //   1003: invokestatic 1587	java/lang/String:valueOf	(J)Ljava/lang/String;
    //   1006: aastore
    //   1007: aload 21
    //   1009: astore 18
    //   1011: aload 19
    //   1013: astore 16
    //   1015: aload 19
    //   1017: astore_1
    //   1018: aload 24
    //   1020: ldc_w 1683
    //   1023: iconst_4
    //   1024: anewarray 445	java/lang/String
    //   1027: dup
    //   1028: iconst_0
    //   1029: ldc_w 1640
    //   1032: aastore
    //   1033: dup
    //   1034: iconst_1
    //   1035: ldc_w 1684
    //   1038: aastore
    //   1039: dup
    //   1040: iconst_2
    //   1041: ldc_w 1686
    //   1044: aastore
    //   1045: dup
    //   1046: iconst_3
    //   1047: ldc_w 1688
    //   1050: aastore
    //   1051: aload 18
    //   1053: aload 20
    //   1055: aconst_null
    //   1056: aconst_null
    //   1057: ldc_w 1640
    //   1060: aconst_null
    //   1061: invokevirtual 1646	android/database/sqlite/SQLiteDatabase:query	(Ljava/lang/String;[Ljava/lang/String;Ljava/lang/String;[Ljava/lang/String;Ljava/lang/String;Ljava/lang/String;Ljava/lang/String;Ljava/lang/String;)Landroid/database/Cursor;
    //   1064: astore 18
    //   1066: aload 18
    //   1068: astore_1
    //   1069: aload_1
    //   1070: astore 18
    //   1072: aload_1
    //   1073: invokeinterface 1612 1 0
    //   1078: ifne +159 -> 1237
    //   1081: aload_1
    //   1082: astore 18
    //   1084: aload 23
    //   1086: invokevirtual 273	com/google/android/gms/internal/zzcjk:zzawy	()Lcom/google/android/gms/internal/zzchm;
    //   1089: invokevirtual 296	com/google/android/gms/internal/zzchm:zzazf	()Lcom/google/android/gms/internal/zzcho;
    //   1092: ldc_w 1690
    //   1095: aload 17
    //   1097: invokestatic 441	com/google/android/gms/internal/zzchm:zzjk	(Ljava/lang/String;)Ljava/lang/Object;
    //   1100: invokevirtual 348	com/google/android/gms/internal/zzcho:zzj	(Ljava/lang/String;Ljava/lang/Object;)V
    //   1103: aload_1
    //   1104: ifnull -926 -> 178
    //   1107: aload_1
    //   1108: invokeinterface 1615 1 0
    //   1113: goto -935 -> 178
    //   1116: astore 18
    //   1118: aload 19
    //   1120: astore 16
    //   1122: aload 19
    //   1124: astore_1
    //   1125: aload 23
    //   1127: invokevirtual 273	com/google/android/gms/internal/zzcjk:zzawy	()Lcom/google/android/gms/internal/zzchm;
    //   1130: invokevirtual 320	com/google/android/gms/internal/zzchm:zzazd	()Lcom/google/android/gms/internal/zzcho;
    //   1133: ldc_w 1692
    //   1136: aload 17
    //   1138: invokestatic 441	com/google/android/gms/internal/zzchm:zzjk	(Ljava/lang/String;)Ljava/lang/Object;
    //   1141: aload 18
    //   1143: invokevirtual 455	com/google/android/gms/internal/zzcho:zze	(Ljava/lang/String;Ljava/lang/Object;Ljava/lang/Object;)V
    //   1146: aload 19
    //   1148: ifnull -970 -> 178
    //   1151: aload 19
    //   1153: invokeinterface 1615 1 0
    //   1158: goto -980 -> 178
    //   1161: ldc_w 1638
    //   1164: astore 21
    //   1166: aload 19
    //   1168: astore 16
    //   1170: aload 19
    //   1172: astore_1
    //   1173: iconst_2
    //   1174: anewarray 445	java/lang/String
    //   1177: astore 20
    //   1179: aload 20
    //   1181: iconst_0
    //   1182: aload 17
    //   1184: aastore
    //   1185: aload 20
    //   1187: iconst_1
    //   1188: aload 18
    //   1190: aastore
    //   1191: aload 21
    //   1193: astore 18
    //   1195: goto -184 -> 1011
    //   1198: astore 16
    //   1200: aload_1
    //   1201: astore 18
    //   1203: aload 23
    //   1205: invokevirtual 273	com/google/android/gms/internal/zzcjk:zzawy	()Lcom/google/android/gms/internal/zzchm;
    //   1208: invokevirtual 320	com/google/android/gms/internal/zzchm:zzazd	()Lcom/google/android/gms/internal/zzcho;
    //   1211: ldc_w 1694
    //   1214: aload 17
    //   1216: invokestatic 441	com/google/android/gms/internal/zzchm:zzjk	(Ljava/lang/String;)Ljava/lang/Object;
    //   1219: aload 16
    //   1221: invokevirtual 455	com/google/android/gms/internal/zzcho:zze	(Ljava/lang/String;Ljava/lang/Object;Ljava/lang/Object;)V
    //   1224: aload_1
    //   1225: ifnull -1047 -> 178
    //   1228: aload_1
    //   1229: invokeinterface 1615 1 0
    //   1234: goto -1056 -> 178
    //   1237: aload_1
    //   1238: astore 18
    //   1240: aload_1
    //   1241: iconst_0
    //   1242: invokeinterface 1697 2 0
    //   1247: lstore_2
    //   1248: aload_1
    //   1249: astore 18
    //   1251: aload_1
    //   1252: iconst_3
    //   1253: invokeinterface 1658 2 0
    //   1258: astore 16
    //   1260: aload_1
    //   1261: astore 18
    //   1263: aload 16
    //   1265: iconst_0
    //   1266: aload 16
    //   1268: arraylength
    //   1269: invokestatic 1664	com/google/android/gms/internal/zzfjj:zzn	([BII)Lcom/google/android/gms/internal/zzfjj;
    //   1272: astore 16
    //   1274: aload_1
    //   1275: astore 18
    //   1277: new 502	com/google/android/gms/internal/zzcmb
    //   1280: dup
    //   1281: invokespecial 1698	com/google/android/gms/internal/zzcmb:<init>	()V
    //   1284: astore 19
    //   1286: aload_1
    //   1287: astore 18
    //   1289: aload 19
    //   1291: aload 16
    //   1293: invokevirtual 1669	com/google/android/gms/internal/zzfjs:zza	(Lcom/google/android/gms/internal/zzfjj;)Lcom/google/android/gms/internal/zzfjs;
    //   1296: pop
    //   1297: aload_1
    //   1298: astore 18
    //   1300: aload 19
    //   1302: aload_1
    //   1303: iconst_1
    //   1304: invokeinterface 1632 2 0
    //   1309: putfield 1628	com/google/android/gms/internal/zzcmb:name	Ljava/lang/String;
    //   1312: aload_1
    //   1313: astore 18
    //   1315: aload 19
    //   1317: aload_1
    //   1318: iconst_2
    //   1319: invokeinterface 1697 2 0
    //   1324: invokestatic 497	java/lang/Long:valueOf	(J)Ljava/lang/Long;
    //   1327: putfield 1701	com/google/android/gms/internal/zzcmb:zzjli	Ljava/lang/Long;
    //   1330: aload_1
    //   1331: astore 18
    //   1333: aload 22
    //   1335: lload_2
    //   1336: aload 19
    //   1338: invokeinterface 1704 4 0
    //   1343: istore 12
    //   1345: iload 12
    //   1347: ifne +42 -> 1389
    //   1350: aload_1
    //   1351: ifnull -1173 -> 178
    //   1354: aload_1
    //   1355: invokeinterface 1615 1 0
    //   1360: goto -1182 -> 178
    //   1363: astore 16
    //   1365: aload_1
    //   1366: astore 18
    //   1368: aload 23
    //   1370: invokevirtual 273	com/google/android/gms/internal/zzcjk:zzawy	()Lcom/google/android/gms/internal/zzchm;
    //   1373: invokevirtual 320	com/google/android/gms/internal/zzchm:zzazd	()Lcom/google/android/gms/internal/zzcho;
    //   1376: ldc_w 1706
    //   1379: aload 17
    //   1381: invokestatic 441	com/google/android/gms/internal/zzchm:zzjk	(Ljava/lang/String;)Ljava/lang/Object;
    //   1384: aload 16
    //   1386: invokevirtual 455	com/google/android/gms/internal/zzcho:zze	(Ljava/lang/String;Ljava/lang/Object;Ljava/lang/Object;)V
    //   1389: aload_1
    //   1390: astore 18
    //   1392: aload_1
    //   1393: invokeinterface 1672 1 0
    //   1398: istore 12
    //   1400: iload 12
    //   1402: ifne -165 -> 1237
    //   1405: aload_1
    //   1406: ifnull -1228 -> 178
    //   1409: aload_1
    //   1410: invokeinterface 1615 1 0
    //   1415: goto -1237 -> 178
    //   1418: aload 16
    //   1420: ifnull +10 -> 1430
    //   1423: aload 16
    //   1425: invokeinterface 1615 1 0
    //   1430: aload_1
    //   1431: athrow
    //   1432: aload_0
    //   1433: invokevirtual 793	com/google/android/gms/internal/zzcim:zzawv	()Lcom/google/android/gms/internal/zzcig;
    //   1436: aload 22
    //   1438: getfield 1623	com/google/android/gms/internal/zzcim$zza:zzjgi	Lcom/google/android/gms/internal/zzcme;
    //   1441: getfield 1259	com/google/android/gms/internal/zzcme:zzcn	Ljava/lang/String;
    //   1444: aload 22
    //   1446: getfield 1618	com/google/android/gms/internal/zzcim$zza:zzapa	Ljava/util/List;
    //   1449: iload 6
    //   1451: invokeinterface 1452 2 0
    //   1456: checkcast 502	com/google/android/gms/internal/zzcmb
    //   1459: getfield 1628	com/google/android/gms/internal/zzcmb:name	Ljava/lang/String;
    //   1462: invokevirtual 1525	com/google/android/gms/internal/zzcig:zzao	(Ljava/lang/String;Ljava/lang/String;)Z
    //   1465: istore 15
    //   1467: iload 15
    //   1469: ifne +36 -> 1505
    //   1472: aload_0
    //   1473: invokevirtual 426	com/google/android/gms/internal/zzcim:zzawu	()Lcom/google/android/gms/internal/zzclq;
    //   1476: pop
    //   1477: iload 12
    //   1479: istore 14
    //   1481: aload 22
    //   1483: getfield 1618	com/google/android/gms/internal/zzcim$zza:zzapa	Ljava/util/List;
    //   1486: iload 6
    //   1488: invokeinterface 1452 2 0
    //   1493: checkcast 502	com/google/android/gms/internal/zzcmb
    //   1496: getfield 1628	com/google/android/gms/internal/zzcmb:name	Ljava/lang/String;
    //   1499: invokestatic 1709	com/google/android/gms/internal/zzclq:zzkn	(Ljava/lang/String;)Z
    //   1502: ifeq +2639 -> 4141
    //   1505: iconst_0
    //   1506: istore 5
    //   1508: aload 22
    //   1510: getfield 1618	com/google/android/gms/internal/zzcim$zza:zzapa	Ljava/util/List;
    //   1513: iload 6
    //   1515: invokeinterface 1452 2 0
    //   1520: checkcast 502	com/google/android/gms/internal/zzcmb
    //   1523: getfield 506	com/google/android/gms/internal/zzcmb:zzjlh	[Lcom/google/android/gms/internal/zzcmc;
    //   1526: ifnonnull +25 -> 1551
    //   1529: aload 22
    //   1531: getfield 1618	com/google/android/gms/internal/zzcim$zza:zzapa	Ljava/util/List;
    //   1534: iload 6
    //   1536: invokeinterface 1452 2 0
    //   1541: checkcast 502	com/google/android/gms/internal/zzcmb
    //   1544: iconst_0
    //   1545: anewarray 508	com/google/android/gms/internal/zzcmc
    //   1548: putfield 506	com/google/android/gms/internal/zzcmb:zzjlh	[Lcom/google/android/gms/internal/zzcmc;
    //   1551: aload 22
    //   1553: getfield 1618	com/google/android/gms/internal/zzcim$zza:zzapa	Ljava/util/List;
    //   1556: iload 6
    //   1558: invokeinterface 1452 2 0
    //   1563: checkcast 502	com/google/android/gms/internal/zzcmb
    //   1566: getfield 506	com/google/android/gms/internal/zzcmb:zzjlh	[Lcom/google/android/gms/internal/zzcmc;
    //   1569: astore_1
    //   1570: aload_1
    //   1571: arraylength
    //   1572: istore 9
    //   1574: iconst_0
    //   1575: istore 7
    //   1577: iconst_0
    //   1578: istore 8
    //   1580: iload 7
    //   1582: iload 9
    //   1584: if_icmpge +67 -> 1651
    //   1587: aload_1
    //   1588: iload 7
    //   1590: aaload
    //   1591: astore 16
    //   1593: ldc_w 1711
    //   1596: aload 16
    //   1598: getfield 511	com/google/android/gms/internal/zzcmc:name	Ljava/lang/String;
    //   1601: invokevirtual 449	java/lang/String:equals	(Ljava/lang/Object;)Z
    //   1604: ifeq +18 -> 1622
    //   1607: aload 16
    //   1609: lconst_1
    //   1610: invokestatic 497	java/lang/Long:valueOf	(J)Ljava/lang/Long;
    //   1613: putfield 515	com/google/android/gms/internal/zzcmc:zzjll	Ljava/lang/Long;
    //   1616: iconst_1
    //   1617: istore 8
    //   1619: goto +2495 -> 4114
    //   1622: ldc_w 1204
    //   1625: aload 16
    //   1627: getfield 511	com/google/android/gms/internal/zzcmc:name	Ljava/lang/String;
    //   1630: invokevirtual 449	java/lang/String:equals	(Ljava/lang/Object;)Z
    //   1633: ifeq +2385 -> 4018
    //   1636: aload 16
    //   1638: lconst_1
    //   1639: invokestatic 497	java/lang/Long:valueOf	(J)Ljava/lang/Long;
    //   1642: putfield 515	com/google/android/gms/internal/zzcmc:zzjll	Ljava/lang/Long;
    //   1645: iconst_1
    //   1646: istore 5
    //   1648: goto +2466 -> 4114
    //   1651: iload 8
    //   1653: ifne +145 -> 1798
    //   1656: iload 15
    //   1658: ifeq +140 -> 1798
    //   1661: aload_0
    //   1662: invokevirtual 293	com/google/android/gms/internal/zzcim:zzawy	()Lcom/google/android/gms/internal/zzchm;
    //   1665: invokevirtual 277	com/google/android/gms/internal/zzchm:zzazj	()Lcom/google/android/gms/internal/zzcho;
    //   1668: ldc_w 1713
    //   1671: aload_0
    //   1672: invokevirtual 660	com/google/android/gms/internal/zzcim:zzawt	()Lcom/google/android/gms/internal/zzchk;
    //   1675: aload 22
    //   1677: getfield 1618	com/google/android/gms/internal/zzcim$zza:zzapa	Ljava/util/List;
    //   1680: iload 6
    //   1682: invokeinterface 1452 2 0
    //   1687: checkcast 502	com/google/android/gms/internal/zzcmb
    //   1690: getfield 1628	com/google/android/gms/internal/zzcmb:name	Ljava/lang/String;
    //   1693: invokevirtual 1107	com/google/android/gms/internal/zzchk:zzjh	(Ljava/lang/String;)Ljava/lang/String;
    //   1696: invokevirtual 348	com/google/android/gms/internal/zzcho:zzj	(Ljava/lang/String;Ljava/lang/Object;)V
    //   1699: aload 22
    //   1701: getfield 1618	com/google/android/gms/internal/zzcim$zza:zzapa	Ljava/util/List;
    //   1704: iload 6
    //   1706: invokeinterface 1452 2 0
    //   1711: checkcast 502	com/google/android/gms/internal/zzcmb
    //   1714: getfield 506	com/google/android/gms/internal/zzcmb:zzjlh	[Lcom/google/android/gms/internal/zzcmc;
    //   1717: aload 22
    //   1719: getfield 1618	com/google/android/gms/internal/zzcim$zza:zzapa	Ljava/util/List;
    //   1722: iload 6
    //   1724: invokeinterface 1452 2 0
    //   1729: checkcast 502	com/google/android/gms/internal/zzcmb
    //   1732: getfield 506	com/google/android/gms/internal/zzcmb:zzjlh	[Lcom/google/android/gms/internal/zzcmc;
    //   1735: arraylength
    //   1736: iconst_1
    //   1737: iadd
    //   1738: invokestatic 1719	java/util/Arrays:copyOf	([Ljava/lang/Object;I)[Ljava/lang/Object;
    //   1741: checkcast 1720	[Lcom/google/android/gms/internal/zzcmc;
    //   1744: astore_1
    //   1745: new 508	com/google/android/gms/internal/zzcmc
    //   1748: dup
    //   1749: invokespecial 1721	com/google/android/gms/internal/zzcmc:<init>	()V
    //   1752: astore 16
    //   1754: aload 16
    //   1756: ldc_w 1711
    //   1759: putfield 511	com/google/android/gms/internal/zzcmc:name	Ljava/lang/String;
    //   1762: aload 16
    //   1764: lconst_1
    //   1765: invokestatic 497	java/lang/Long:valueOf	(J)Ljava/lang/Long;
    //   1768: putfield 515	com/google/android/gms/internal/zzcmc:zzjll	Ljava/lang/Long;
    //   1771: aload_1
    //   1772: aload_1
    //   1773: arraylength
    //   1774: iconst_1
    //   1775: isub
    //   1776: aload 16
    //   1778: aastore
    //   1779: aload 22
    //   1781: getfield 1618	com/google/android/gms/internal/zzcim$zza:zzapa	Ljava/util/List;
    //   1784: iload 6
    //   1786: invokeinterface 1452 2 0
    //   1791: checkcast 502	com/google/android/gms/internal/zzcmb
    //   1794: aload_1
    //   1795: putfield 506	com/google/android/gms/internal/zzcmb:zzjlh	[Lcom/google/android/gms/internal/zzcmc;
    //   1798: iload 5
    //   1800: ifne +140 -> 1940
    //   1803: aload_0
    //   1804: invokevirtual 293	com/google/android/gms/internal/zzcim:zzawy	()Lcom/google/android/gms/internal/zzchm;
    //   1807: invokevirtual 277	com/google/android/gms/internal/zzchm:zzazj	()Lcom/google/android/gms/internal/zzcho;
    //   1810: ldc_w 1723
    //   1813: aload_0
    //   1814: invokevirtual 660	com/google/android/gms/internal/zzcim:zzawt	()Lcom/google/android/gms/internal/zzchk;
    //   1817: aload 22
    //   1819: getfield 1618	com/google/android/gms/internal/zzcim$zza:zzapa	Ljava/util/List;
    //   1822: iload 6
    //   1824: invokeinterface 1452 2 0
    //   1829: checkcast 502	com/google/android/gms/internal/zzcmb
    //   1832: getfield 1628	com/google/android/gms/internal/zzcmb:name	Ljava/lang/String;
    //   1835: invokevirtual 1107	com/google/android/gms/internal/zzchk:zzjh	(Ljava/lang/String;)Ljava/lang/String;
    //   1838: invokevirtual 348	com/google/android/gms/internal/zzcho:zzj	(Ljava/lang/String;Ljava/lang/Object;)V
    //   1841: aload 22
    //   1843: getfield 1618	com/google/android/gms/internal/zzcim$zza:zzapa	Ljava/util/List;
    //   1846: iload 6
    //   1848: invokeinterface 1452 2 0
    //   1853: checkcast 502	com/google/android/gms/internal/zzcmb
    //   1856: getfield 506	com/google/android/gms/internal/zzcmb:zzjlh	[Lcom/google/android/gms/internal/zzcmc;
    //   1859: aload 22
    //   1861: getfield 1618	com/google/android/gms/internal/zzcim$zza:zzapa	Ljava/util/List;
    //   1864: iload 6
    //   1866: invokeinterface 1452 2 0
    //   1871: checkcast 502	com/google/android/gms/internal/zzcmb
    //   1874: getfield 506	com/google/android/gms/internal/zzcmb:zzjlh	[Lcom/google/android/gms/internal/zzcmc;
    //   1877: arraylength
    //   1878: iconst_1
    //   1879: iadd
    //   1880: invokestatic 1719	java/util/Arrays:copyOf	([Ljava/lang/Object;I)[Ljava/lang/Object;
    //   1883: checkcast 1720	[Lcom/google/android/gms/internal/zzcmc;
    //   1886: astore_1
    //   1887: new 508	com/google/android/gms/internal/zzcmc
    //   1890: dup
    //   1891: invokespecial 1721	com/google/android/gms/internal/zzcmc:<init>	()V
    //   1894: astore 16
    //   1896: aload 16
    //   1898: ldc_w 1204
    //   1901: putfield 511	com/google/android/gms/internal/zzcmc:name	Ljava/lang/String;
    //   1904: aload 16
    //   1906: lconst_1
    //   1907: invokestatic 497	java/lang/Long:valueOf	(J)Ljava/lang/Long;
    //   1910: putfield 515	com/google/android/gms/internal/zzcmc:zzjll	Ljava/lang/Long;
    //   1913: aload_1
    //   1914: aload_1
    //   1915: arraylength
    //   1916: iconst_1
    //   1917: isub
    //   1918: aload 16
    //   1920: aastore
    //   1921: aload 22
    //   1923: getfield 1618	com/google/android/gms/internal/zzcim$zza:zzapa	Ljava/util/List;
    //   1926: iload 6
    //   1928: invokeinterface 1452 2 0
    //   1933: checkcast 502	com/google/android/gms/internal/zzcmb
    //   1936: aload_1
    //   1937: putfield 506	com/google/android/gms/internal/zzcmb:zzjlh	[Lcom/google/android/gms/internal/zzcmc;
    //   1940: aload_0
    //   1941: invokevirtual 604	com/google/android/gms/internal/zzcim:zzaws	()Lcom/google/android/gms/internal/zzcgo;
    //   1944: aload_0
    //   1945: invokespecial 1161	com/google/android/gms/internal/zzcim:zzbag	()J
    //   1948: aload 22
    //   1950: getfield 1623	com/google/android/gms/internal/zzcim$zza:zzjgi	Lcom/google/android/gms/internal/zzcme;
    //   1953: getfield 1259	com/google/android/gms/internal/zzcme:zzcn	Ljava/lang/String;
    //   1956: iconst_0
    //   1957: iconst_0
    //   1958: iconst_0
    //   1959: iconst_0
    //   1960: iconst_1
    //   1961: invokevirtual 1164	com/google/android/gms/internal/zzcgo:zza	(JLjava/lang/String;ZZZZZ)Lcom/google/android/gms/internal/zzcgp;
    //   1964: getfield 1528	com/google/android/gms/internal/zzcgp:zzizb	J
    //   1967: aload_0
    //   1968: getfield 126	com/google/android/gms/internal/zzcim:zzjew	Lcom/google/android/gms/internal/zzcgn;
    //   1971: aload 22
    //   1973: getfield 1623	com/google/android/gms/internal/zzcim$zza:zzjgi	Lcom/google/android/gms/internal/zzcme;
    //   1976: getfield 1259	com/google/android/gms/internal/zzcme:zzcn	Ljava/lang/String;
    //   1979: invokevirtual 1532	com/google/android/gms/internal/zzcgn:zzix	(Ljava/lang/String;)I
    //   1982: i2l
    //   1983: lcmp
    //   1984: ifle +2028 -> 4012
    //   1987: aload 22
    //   1989: getfield 1618	com/google/android/gms/internal/zzcim$zza:zzapa	Ljava/util/List;
    //   1992: iload 6
    //   1994: invokeinterface 1452 2 0
    //   1999: checkcast 502	com/google/android/gms/internal/zzcmb
    //   2002: astore_1
    //   2003: iconst_0
    //   2004: istore 5
    //   2006: iload 12
    //   2008: istore 13
    //   2010: iload 5
    //   2012: aload_1
    //   2013: getfield 506	com/google/android/gms/internal/zzcmb:zzjlh	[Lcom/google/android/gms/internal/zzcmc;
    //   2016: arraylength
    //   2017: if_icmpge +91 -> 2108
    //   2020: ldc_w 1204
    //   2023: aload_1
    //   2024: getfield 506	com/google/android/gms/internal/zzcmb:zzjlh	[Lcom/google/android/gms/internal/zzcmc;
    //   2027: iload 5
    //   2029: aaload
    //   2030: getfield 511	com/google/android/gms/internal/zzcmc:name	Ljava/lang/String;
    //   2033: invokevirtual 449	java/lang/String:equals	(Ljava/lang/Object;)Z
    //   2036: ifeq +2096 -> 4132
    //   2039: aload_1
    //   2040: getfield 506	com/google/android/gms/internal/zzcmb:zzjlh	[Lcom/google/android/gms/internal/zzcmc;
    //   2043: arraylength
    //   2044: iconst_1
    //   2045: isub
    //   2046: anewarray 508	com/google/android/gms/internal/zzcmc
    //   2049: astore 16
    //   2051: iload 5
    //   2053: ifle +16 -> 2069
    //   2056: aload_1
    //   2057: getfield 506	com/google/android/gms/internal/zzcmb:zzjlh	[Lcom/google/android/gms/internal/zzcmc;
    //   2060: iconst_0
    //   2061: aload 16
    //   2063: iconst_0
    //   2064: iload 5
    //   2066: invokestatic 1727	java/lang/System:arraycopy	(Ljava/lang/Object;ILjava/lang/Object;II)V
    //   2069: iload 5
    //   2071: aload 16
    //   2073: arraylength
    //   2074: if_icmpge +24 -> 2098
    //   2077: aload_1
    //   2078: getfield 506	com/google/android/gms/internal/zzcmb:zzjlh	[Lcom/google/android/gms/internal/zzcmc;
    //   2081: iload 5
    //   2083: iconst_1
    //   2084: iadd
    //   2085: aload 16
    //   2087: iload 5
    //   2089: aload 16
    //   2091: arraylength
    //   2092: iload 5
    //   2094: isub
    //   2095: invokestatic 1727	java/lang/System:arraycopy	(Ljava/lang/Object;ILjava/lang/Object;II)V
    //   2098: aload_1
    //   2099: aload 16
    //   2101: putfield 506	com/google/android/gms/internal/zzcmb:zzjlh	[Lcom/google/android/gms/internal/zzcmc;
    //   2104: iload 12
    //   2106: istore 13
    //   2108: iload 13
    //   2110: istore 14
    //   2112: aload 22
    //   2114: getfield 1618	com/google/android/gms/internal/zzcim$zza:zzapa	Ljava/util/List;
    //   2117: iload 6
    //   2119: invokeinterface 1452 2 0
    //   2124: checkcast 502	com/google/android/gms/internal/zzcmb
    //   2127: getfield 1628	com/google/android/gms/internal/zzcmb:name	Ljava/lang/String;
    //   2130: invokestatic 1159	com/google/android/gms/internal/zzclq:zzjz	(Ljava/lang/String;)Z
    //   2133: ifeq +2008 -> 4141
    //   2136: iload 13
    //   2138: istore 14
    //   2140: iload 15
    //   2142: ifeq +1999 -> 4141
    //   2145: iload 13
    //   2147: istore 14
    //   2149: aload_0
    //   2150: invokevirtual 604	com/google/android/gms/internal/zzcim:zzaws	()Lcom/google/android/gms/internal/zzcgo;
    //   2153: aload_0
    //   2154: invokespecial 1161	com/google/android/gms/internal/zzcim:zzbag	()J
    //   2157: aload 22
    //   2159: getfield 1623	com/google/android/gms/internal/zzcim$zza:zzjgi	Lcom/google/android/gms/internal/zzcme;
    //   2162: getfield 1259	com/google/android/gms/internal/zzcme:zzcn	Ljava/lang/String;
    //   2165: iconst_0
    //   2166: iconst_0
    //   2167: iconst_1
    //   2168: iconst_0
    //   2169: iconst_0
    //   2170: invokevirtual 1164	com/google/android/gms/internal/zzcgo:zza	(JLjava/lang/String;ZZZZZ)Lcom/google/android/gms/internal/zzcgp;
    //   2173: getfield 1730	com/google/android/gms/internal/zzcgp:zziyz	J
    //   2176: aload_0
    //   2177: getfield 126	com/google/android/gms/internal/zzcim:zzjew	Lcom/google/android/gms/internal/zzcgn;
    //   2180: aload 22
    //   2182: getfield 1623	com/google/android/gms/internal/zzcim$zza:zzjgi	Lcom/google/android/gms/internal/zzcme;
    //   2185: getfield 1259	com/google/android/gms/internal/zzcme:zzcn	Ljava/lang/String;
    //   2188: getstatic 1733	com/google/android/gms/internal/zzchc:zzjaq	Lcom/google/android/gms/internal/zzchd;
    //   2191: invokevirtual 624	com/google/android/gms/internal/zzcgn:zzb	(Ljava/lang/String;Lcom/google/android/gms/internal/zzchd;)I
    //   2194: i2l
    //   2195: lcmp
    //   2196: ifle +1945 -> 4141
    //   2199: aload_0
    //   2200: invokevirtual 293	com/google/android/gms/internal/zzcim:zzawy	()Lcom/google/android/gms/internal/zzchm;
    //   2203: invokevirtual 296	com/google/android/gms/internal/zzchm:zzazf	()Lcom/google/android/gms/internal/zzcho;
    //   2206: ldc_w 1735
    //   2209: aload 22
    //   2211: getfield 1623	com/google/android/gms/internal/zzcim$zza:zzjgi	Lcom/google/android/gms/internal/zzcme;
    //   2214: getfield 1259	com/google/android/gms/internal/zzcme:zzcn	Ljava/lang/String;
    //   2217: invokestatic 441	com/google/android/gms/internal/zzchm:zzjk	(Ljava/lang/String;)Ljava/lang/Object;
    //   2220: invokevirtual 348	com/google/android/gms/internal/zzcho:zzj	(Ljava/lang/String;Ljava/lang/Object;)V
    //   2223: aload 22
    //   2225: getfield 1618	com/google/android/gms/internal/zzcim$zza:zzapa	Ljava/util/List;
    //   2228: iload 6
    //   2230: invokeinterface 1452 2 0
    //   2235: checkcast 502	com/google/android/gms/internal/zzcmb
    //   2238: astore 18
    //   2240: aconst_null
    //   2241: astore_1
    //   2242: aload 18
    //   2244: getfield 506	com/google/android/gms/internal/zzcmb:zzjlh	[Lcom/google/android/gms/internal/zzcmc;
    //   2247: astore 19
    //   2249: aload 19
    //   2251: arraylength
    //   2252: istore 8
    //   2254: iconst_0
    //   2255: istore 5
    //   2257: iconst_0
    //   2258: istore 7
    //   2260: iload 5
    //   2262: iload 8
    //   2264: if_icmpge +50 -> 2314
    //   2267: aload 19
    //   2269: iload 5
    //   2271: aaload
    //   2272: astore 16
    //   2274: ldc_w 1711
    //   2277: aload 16
    //   2279: getfield 511	com/google/android/gms/internal/zzcmc:name	Ljava/lang/String;
    //   2282: invokevirtual 449	java/lang/String:equals	(Ljava/lang/Object;)Z
    //   2285: ifeq +9 -> 2294
    //   2288: aload 16
    //   2290: astore_1
    //   2291: goto +1832 -> 4123
    //   2294: ldc_w 1115
    //   2297: aload 16
    //   2299: getfield 511	com/google/android/gms/internal/zzcmc:name	Ljava/lang/String;
    //   2302: invokevirtual 449	java/lang/String:equals	(Ljava/lang/Object;)Z
    //   2305: ifeq +1704 -> 4009
    //   2308: iconst_1
    //   2309: istore 7
    //   2311: goto +1812 -> 4123
    //   2314: iload 7
    //   2316: ifeq +67 -> 2383
    //   2319: aload_1
    //   2320: ifnull +63 -> 2383
    //   2323: aload 18
    //   2325: aload 18
    //   2327: getfield 506	com/google/android/gms/internal/zzcmb:zzjlh	[Lcom/google/android/gms/internal/zzcmc;
    //   2330: iconst_1
    //   2331: anewarray 508	com/google/android/gms/internal/zzcmc
    //   2334: dup
    //   2335: iconst_0
    //   2336: aload_1
    //   2337: aastore
    //   2338: invokestatic 1740	com/google/android/gms/common/util/zza:zza	([Ljava/lang/Object;[Ljava/lang/Object;)[Ljava/lang/Object;
    //   2341: checkcast 1720	[Lcom/google/android/gms/internal/zzcmc;
    //   2344: putfield 506	com/google/android/gms/internal/zzcmb:zzjlh	[Lcom/google/android/gms/internal/zzcmc;
    //   2347: iload 13
    //   2349: istore 12
    //   2351: aload 17
    //   2353: getfield 1627	com/google/android/gms/internal/zzcme:zzjlp	[Lcom/google/android/gms/internal/zzcmb;
    //   2356: iload 4
    //   2358: aload 22
    //   2360: getfield 1618	com/google/android/gms/internal/zzcim$zza:zzapa	Ljava/util/List;
    //   2363: iload 6
    //   2365: invokeinterface 1452 2 0
    //   2370: checkcast 502	com/google/android/gms/internal/zzcmb
    //   2373: aastore
    //   2374: iload 4
    //   2376: iconst_1
    //   2377: iadd
    //   2378: istore 4
    //   2380: goto -1929 -> 451
    //   2383: aload_1
    //   2384: ifnull +27 -> 2411
    //   2387: aload_1
    //   2388: ldc_w 1115
    //   2391: putfield 511	com/google/android/gms/internal/zzcmc:name	Ljava/lang/String;
    //   2394: aload_1
    //   2395: ldc2_w 1741
    //   2398: invokestatic 497	java/lang/Long:valueOf	(J)Ljava/lang/Long;
    //   2401: putfield 515	com/google/android/gms/internal/zzcmc:zzjll	Ljava/lang/Long;
    //   2404: iload 13
    //   2406: istore 12
    //   2408: goto -57 -> 2351
    //   2411: aload_0
    //   2412: invokevirtual 293	com/google/android/gms/internal/zzcim:zzawy	()Lcom/google/android/gms/internal/zzchm;
    //   2415: invokevirtual 320	com/google/android/gms/internal/zzchm:zzazd	()Lcom/google/android/gms/internal/zzcho;
    //   2418: ldc_w 1744
    //   2421: aload 22
    //   2423: getfield 1623	com/google/android/gms/internal/zzcim$zza:zzjgi	Lcom/google/android/gms/internal/zzcme;
    //   2426: getfield 1259	com/google/android/gms/internal/zzcme:zzcn	Ljava/lang/String;
    //   2429: invokestatic 441	com/google/android/gms/internal/zzchm:zzjk	(Ljava/lang/String;)Ljava/lang/Object;
    //   2432: invokevirtual 348	com/google/android/gms/internal/zzcho:zzj	(Ljava/lang/String;Ljava/lang/Object;)V
    //   2435: iload 13
    //   2437: istore 14
    //   2439: goto +1702 -> 4141
    //   2442: iload 4
    //   2444: aload 22
    //   2446: getfield 1618	com/google/android/gms/internal/zzcim$zza:zzapa	Ljava/util/List;
    //   2449: invokeinterface 1442 1 0
    //   2454: if_icmpge +21 -> 2475
    //   2457: aload 17
    //   2459: aload 17
    //   2461: getfield 1627	com/google/android/gms/internal/zzcme:zzjlp	[Lcom/google/android/gms/internal/zzcmb;
    //   2464: iload 4
    //   2466: invokestatic 1719	java/util/Arrays:copyOf	([Ljava/lang/Object;I)[Ljava/lang/Object;
    //   2469: checkcast 1745	[Lcom/google/android/gms/internal/zzcmb;
    //   2472: putfield 1627	com/google/android/gms/internal/zzcme:zzjlp	[Lcom/google/android/gms/internal/zzcmb;
    //   2475: aload 17
    //   2477: aload_0
    //   2478: aload 22
    //   2480: getfield 1623	com/google/android/gms/internal/zzcim$zza:zzjgi	Lcom/google/android/gms/internal/zzcme;
    //   2483: getfield 1259	com/google/android/gms/internal/zzcme:zzcn	Ljava/lang/String;
    //   2486: aload 22
    //   2488: getfield 1623	com/google/android/gms/internal/zzcim$zza:zzjgi	Lcom/google/android/gms/internal/zzcme;
    //   2491: getfield 1448	com/google/android/gms/internal/zzcme:zzjlq	[Lcom/google/android/gms/internal/zzcmg;
    //   2494: aload 17
    //   2496: getfield 1627	com/google/android/gms/internal/zzcme:zzjlp	[Lcom/google/android/gms/internal/zzcmb;
    //   2499: invokespecial 1747	com/google/android/gms/internal/zzcim:zza	(Ljava/lang/String;[Lcom/google/android/gms/internal/zzcmg;[Lcom/google/android/gms/internal/zzcmb;)[Lcom/google/android/gms/internal/zzcma;
    //   2502: putfield 1751	com/google/android/gms/internal/zzcme:zzjmi	[Lcom/google/android/gms/internal/zzcma;
    //   2505: getstatic 1754	com/google/android/gms/internal/zzchc:zzjac	Lcom/google/android/gms/internal/zzchd;
    //   2508: invokevirtual 748	com/google/android/gms/internal/zzchd:get	()Ljava/lang/Object;
    //   2511: checkcast 1050	java/lang/Boolean
    //   2514: invokevirtual 1757	java/lang/Boolean:booleanValue	()Z
    //   2517: ifeq +979 -> 3496
    //   2520: aload_0
    //   2521: getfield 126	com/google/android/gms/internal/zzcim:zzjew	Lcom/google/android/gms/internal/zzcgn;
    //   2524: astore_1
    //   2525: aload 22
    //   2527: getfield 1623	com/google/android/gms/internal/zzcim$zza:zzjgi	Lcom/google/android/gms/internal/zzcme;
    //   2530: getfield 1259	com/google/android/gms/internal/zzcme:zzcn	Ljava/lang/String;
    //   2533: astore 16
    //   2535: ldc_w 1759
    //   2538: aload_1
    //   2539: invokevirtual 1760	com/google/android/gms/internal/zzcjk:zzawv	()Lcom/google/android/gms/internal/zzcig;
    //   2542: aload 16
    //   2544: ldc_w 1762
    //   2547: invokevirtual 1765	com/google/android/gms/internal/zzcig:zzam	(Ljava/lang/String;Ljava/lang/String;)Ljava/lang/String;
    //   2550: invokevirtual 449	java/lang/String:equals	(Ljava/lang/Object;)Z
    //   2553: ifeq +943 -> 3496
    //   2556: new 1767	java/util/HashMap
    //   2559: dup
    //   2560: invokespecial 1768	java/util/HashMap:<init>	()V
    //   2563: astore 18
    //   2565: aload 17
    //   2567: getfield 1627	com/google/android/gms/internal/zzcme:zzjlp	[Lcom/google/android/gms/internal/zzcmb;
    //   2570: arraylength
    //   2571: anewarray 502	com/google/android/gms/internal/zzcmb
    //   2574: astore 19
    //   2576: iconst_0
    //   2577: istore 4
    //   2579: aload_0
    //   2580: invokevirtual 426	com/google/android/gms/internal/zzcim:zzawu	()Lcom/google/android/gms/internal/zzclq;
    //   2583: invokevirtual 896	com/google/android/gms/internal/zzclq:zzbaz	()Ljava/security/SecureRandom;
    //   2586: astore 20
    //   2588: aload 17
    //   2590: getfield 1627	com/google/android/gms/internal/zzcme:zzjlp	[Lcom/google/android/gms/internal/zzcmb;
    //   2593: astore 21
    //   2595: aload 21
    //   2597: arraylength
    //   2598: istore 8
    //   2600: iconst_0
    //   2601: istore 5
    //   2603: iload 5
    //   2605: iload 8
    //   2607: if_icmpge +810 -> 3417
    //   2610: aload 21
    //   2612: iload 5
    //   2614: aaload
    //   2615: astore 23
    //   2617: aload 23
    //   2619: getfield 1628	com/google/android/gms/internal/zzcmb:name	Ljava/lang/String;
    //   2622: ldc_w 1770
    //   2625: invokevirtual 449	java/lang/String:equals	(Ljava/lang/Object;)Z
    //   2628: ifeq +184 -> 2812
    //   2631: aload_0
    //   2632: invokevirtual 426	com/google/android/gms/internal/zzcim:zzawu	()Lcom/google/android/gms/internal/zzclq;
    //   2635: pop
    //   2636: aload 23
    //   2638: ldc_w 1772
    //   2641: invokestatic 1775	com/google/android/gms/internal/zzclq:zza	(Lcom/google/android/gms/internal/zzcmb;Ljava/lang/String;)Ljava/lang/Object;
    //   2644: checkcast 445	java/lang/String
    //   2647: astore 24
    //   2649: aload 18
    //   2651: aload 24
    //   2653: invokeinterface 1777 2 0
    //   2658: checkcast 1231	com/google/android/gms/internal/zzcgw
    //   2661: astore 16
    //   2663: aload 16
    //   2665: astore_1
    //   2666: aload 16
    //   2668: ifnonnull +32 -> 2700
    //   2671: aload_0
    //   2672: invokevirtual 604	com/google/android/gms/internal/zzcim:zzaws	()Lcom/google/android/gms/internal/zzcgo;
    //   2675: aload 22
    //   2677: getfield 1623	com/google/android/gms/internal/zzcim$zza:zzjgi	Lcom/google/android/gms/internal/zzcme;
    //   2680: getfield 1259	com/google/android/gms/internal/zzcme:zzcn	Ljava/lang/String;
    //   2683: aload 24
    //   2685: invokevirtual 1222	com/google/android/gms/internal/zzcgo:zzae	(Ljava/lang/String;Ljava/lang/String;)Lcom/google/android/gms/internal/zzcgw;
    //   2688: astore_1
    //   2689: aload 18
    //   2691: aload 24
    //   2693: aload_1
    //   2694: invokeinterface 811 3 0
    //   2699: pop
    //   2700: aload_1
    //   2701: getfield 1780	com/google/android/gms/internal/zzcgw:zzizo	Ljava/lang/Long;
    //   2704: ifnonnull +1450 -> 4154
    //   2707: aload_1
    //   2708: getfield 1783	com/google/android/gms/internal/zzcgw:zzizp	Ljava/lang/Long;
    //   2711: invokevirtual 563	java/lang/Long:longValue	()J
    //   2714: lconst_1
    //   2715: lcmp
    //   2716: ifle +28 -> 2744
    //   2719: aload_0
    //   2720: invokevirtual 426	com/google/android/gms/internal/zzcim:zzawu	()Lcom/google/android/gms/internal/zzclq;
    //   2723: pop
    //   2724: aload 23
    //   2726: aload 23
    //   2728: getfield 506	com/google/android/gms/internal/zzcmb:zzjlh	[Lcom/google/android/gms/internal/zzcmc;
    //   2731: ldc_w 1785
    //   2734: aload_1
    //   2735: getfield 1783	com/google/android/gms/internal/zzcgw:zzizp	Ljava/lang/Long;
    //   2738: invokestatic 1788	com/google/android/gms/internal/zzclq:zza	([Lcom/google/android/gms/internal/zzcmc;Ljava/lang/String;Ljava/lang/Object;)[Lcom/google/android/gms/internal/zzcmc;
    //   2741: putfield 506	com/google/android/gms/internal/zzcmb:zzjlh	[Lcom/google/android/gms/internal/zzcmc;
    //   2744: aload_1
    //   2745: getfield 1791	com/google/android/gms/internal/zzcgw:zzizq	Ljava/lang/Boolean;
    //   2748: ifnull +38 -> 2786
    //   2751: aload_1
    //   2752: getfield 1791	com/google/android/gms/internal/zzcgw:zzizq	Ljava/lang/Boolean;
    //   2755: invokevirtual 1757	java/lang/Boolean:booleanValue	()Z
    //   2758: ifeq +28 -> 2786
    //   2761: aload_0
    //   2762: invokevirtual 426	com/google/android/gms/internal/zzcim:zzawu	()Lcom/google/android/gms/internal/zzclq;
    //   2765: pop
    //   2766: aload 23
    //   2768: aload 23
    //   2770: getfield 506	com/google/android/gms/internal/zzcmb:zzjlh	[Lcom/google/android/gms/internal/zzcmc;
    //   2773: ldc_w 1793
    //   2776: lconst_1
    //   2777: invokestatic 497	java/lang/Long:valueOf	(J)Ljava/lang/Long;
    //   2780: invokestatic 1788	com/google/android/gms/internal/zzclq:zza	([Lcom/google/android/gms/internal/zzcmc;Ljava/lang/String;Ljava/lang/Object;)[Lcom/google/android/gms/internal/zzcmc;
    //   2783: putfield 506	com/google/android/gms/internal/zzcmb:zzjlh	[Lcom/google/android/gms/internal/zzcmc;
    //   2786: iload 4
    //   2788: iconst_1
    //   2789: iadd
    //   2790: istore 6
    //   2792: aload 19
    //   2794: iload 4
    //   2796: aload 23
    //   2798: aastore
    //   2799: iload 6
    //   2801: istore 4
    //   2803: iload 5
    //   2805: iconst_1
    //   2806: iadd
    //   2807: istore 5
    //   2809: goto -206 -> 2603
    //   2812: aload 23
    //   2814: ldc_w 1202
    //   2817: lconst_1
    //   2818: invokestatic 497	java/lang/Long:valueOf	(J)Ljava/lang/Long;
    //   2821: invokestatic 1795	com/google/android/gms/internal/zzcim:zza	(Lcom/google/android/gms/internal/zzcmb;Ljava/lang/String;Ljava/lang/Object;)Z
    //   2824: ifne +1179 -> 4003
    //   2827: aload_0
    //   2828: invokevirtual 793	com/google/android/gms/internal/zzcim:zzawv	()Lcom/google/android/gms/internal/zzcig;
    //   2831: aload 22
    //   2833: getfield 1623	com/google/android/gms/internal/zzcim$zza:zzjgi	Lcom/google/android/gms/internal/zzcme;
    //   2836: getfield 1259	com/google/android/gms/internal/zzcme:zzcn	Ljava/lang/String;
    //   2839: aload 23
    //   2841: getfield 1628	com/google/android/gms/internal/zzcmb:name	Ljava/lang/String;
    //   2844: invokevirtual 1798	com/google/android/gms/internal/zzcig:zzap	(Ljava/lang/String;Ljava/lang/String;)I
    //   2847: istore 6
    //   2849: iload 6
    //   2851: ifgt +46 -> 2897
    //   2854: aload_0
    //   2855: invokevirtual 293	com/google/android/gms/internal/zzcim:zzawy	()Lcom/google/android/gms/internal/zzchm;
    //   2858: invokevirtual 296	com/google/android/gms/internal/zzchm:zzazf	()Lcom/google/android/gms/internal/zzcho;
    //   2861: ldc_w 1800
    //   2864: aload 23
    //   2866: getfield 1628	com/google/android/gms/internal/zzcmb:name	Ljava/lang/String;
    //   2869: iload 6
    //   2871: invokestatic 344	java/lang/Integer:valueOf	(I)Ljava/lang/Integer;
    //   2874: invokevirtual 455	com/google/android/gms/internal/zzcho:zze	(Ljava/lang/String;Ljava/lang/Object;Ljava/lang/Object;)V
    //   2877: iload 4
    //   2879: iconst_1
    //   2880: iadd
    //   2881: istore 6
    //   2883: aload 19
    //   2885: iload 4
    //   2887: aload 23
    //   2889: aastore
    //   2890: iload 6
    //   2892: istore 4
    //   2894: goto -91 -> 2803
    //   2897: aload 18
    //   2899: aload 23
    //   2901: getfield 1628	com/google/android/gms/internal/zzcmb:name	Ljava/lang/String;
    //   2904: invokeinterface 1777 2 0
    //   2909: checkcast 1231	com/google/android/gms/internal/zzcgw
    //   2912: astore_1
    //   2913: aload_1
    //   2914: ifnonnull +1086 -> 4000
    //   2917: aload_0
    //   2918: invokevirtual 604	com/google/android/gms/internal/zzcim:zzaws	()Lcom/google/android/gms/internal/zzcgo;
    //   2921: aload 22
    //   2923: getfield 1623	com/google/android/gms/internal/zzcim$zza:zzjgi	Lcom/google/android/gms/internal/zzcme;
    //   2926: getfield 1259	com/google/android/gms/internal/zzcme:zzcn	Ljava/lang/String;
    //   2929: aload 23
    //   2931: getfield 1628	com/google/android/gms/internal/zzcmb:name	Ljava/lang/String;
    //   2934: invokevirtual 1222	com/google/android/gms/internal/zzcgo:zzae	(Ljava/lang/String;Ljava/lang/String;)Lcom/google/android/gms/internal/zzcgw;
    //   2937: astore 16
    //   2939: aload 16
    //   2941: astore_1
    //   2942: aload 16
    //   2944: ifnonnull +64 -> 3008
    //   2947: aload_0
    //   2948: invokevirtual 293	com/google/android/gms/internal/zzcim:zzawy	()Lcom/google/android/gms/internal/zzchm;
    //   2951: invokevirtual 296	com/google/android/gms/internal/zzchm:zzazf	()Lcom/google/android/gms/internal/zzcho;
    //   2954: ldc_w 1802
    //   2957: aload 22
    //   2959: getfield 1623	com/google/android/gms/internal/zzcim$zza:zzjgi	Lcom/google/android/gms/internal/zzcme;
    //   2962: getfield 1259	com/google/android/gms/internal/zzcme:zzcn	Ljava/lang/String;
    //   2965: aload 23
    //   2967: getfield 1628	com/google/android/gms/internal/zzcmb:name	Ljava/lang/String;
    //   2970: invokevirtual 455	com/google/android/gms/internal/zzcho:zze	(Ljava/lang/String;Ljava/lang/Object;Ljava/lang/Object;)V
    //   2973: new 1231	com/google/android/gms/internal/zzcgw
    //   2976: dup
    //   2977: aload 22
    //   2979: getfield 1623	com/google/android/gms/internal/zzcim$zza:zzjgi	Lcom/google/android/gms/internal/zzcme;
    //   2982: getfield 1259	com/google/android/gms/internal/zzcme:zzcn	Ljava/lang/String;
    //   2985: aload 23
    //   2987: getfield 1628	com/google/android/gms/internal/zzcmb:name	Ljava/lang/String;
    //   2990: lconst_1
    //   2991: lconst_1
    //   2992: aload 23
    //   2994: getfield 1701	com/google/android/gms/internal/zzcmb:zzjli	Ljava/lang/Long;
    //   2997: invokevirtual 563	java/lang/Long:longValue	()J
    //   3000: lconst_0
    //   3001: aconst_null
    //   3002: aconst_null
    //   3003: aconst_null
    //   3004: invokespecial 1237	com/google/android/gms/internal/zzcgw:<init>	(Ljava/lang/String;Ljava/lang/String;JJJJLjava/lang/Long;Ljava/lang/Long;Ljava/lang/Boolean;)V
    //   3007: astore_1
    //   3008: aload_0
    //   3009: invokevirtual 426	com/google/android/gms/internal/zzcim:zzawu	()Lcom/google/android/gms/internal/zzclq;
    //   3012: pop
    //   3013: aload 23
    //   3015: ldc_w 1804
    //   3018: invokestatic 1775	com/google/android/gms/internal/zzclq:zza	(Lcom/google/android/gms/internal/zzcmb;Ljava/lang/String;)Ljava/lang/Object;
    //   3021: checkcast 494	java/lang/Long
    //   3024: astore 16
    //   3026: aload 16
    //   3028: ifnull +1120 -> 4148
    //   3031: iconst_1
    //   3032: istore 13
    //   3034: iload 13
    //   3036: invokestatic 1053	java/lang/Boolean:valueOf	(Z)Ljava/lang/Boolean;
    //   3039: astore 24
    //   3041: iload 6
    //   3043: iconst_1
    //   3044: if_icmpne +82 -> 3126
    //   3047: iload 4
    //   3049: iconst_1
    //   3050: iadd
    //   3051: istore 6
    //   3053: aload 19
    //   3055: iload 4
    //   3057: aload 23
    //   3059: aastore
    //   3060: iload 6
    //   3062: istore 4
    //   3064: aload 24
    //   3066: invokevirtual 1757	java/lang/Boolean:booleanValue	()Z
    //   3069: ifeq -266 -> 2803
    //   3072: aload_1
    //   3073: getfield 1780	com/google/android/gms/internal/zzcgw:zzizo	Ljava/lang/Long;
    //   3076: ifnonnull +21 -> 3097
    //   3079: aload_1
    //   3080: getfield 1783	com/google/android/gms/internal/zzcgw:zzizp	Ljava/lang/Long;
    //   3083: ifnonnull +14 -> 3097
    //   3086: iload 6
    //   3088: istore 4
    //   3090: aload_1
    //   3091: getfield 1791	com/google/android/gms/internal/zzcgw:zzizq	Ljava/lang/Boolean;
    //   3094: ifnull -291 -> 2803
    //   3097: aload_1
    //   3098: aconst_null
    //   3099: aconst_null
    //   3100: aconst_null
    //   3101: invokevirtual 1807	com/google/android/gms/internal/zzcgw:zza	(Ljava/lang/Long;Ljava/lang/Long;Ljava/lang/Boolean;)Lcom/google/android/gms/internal/zzcgw;
    //   3104: astore_1
    //   3105: aload 18
    //   3107: aload 23
    //   3109: getfield 1628	com/google/android/gms/internal/zzcmb:name	Ljava/lang/String;
    //   3112: aload_1
    //   3113: invokeinterface 811 3 0
    //   3118: pop
    //   3119: iload 6
    //   3121: istore 4
    //   3123: goto -320 -> 2803
    //   3126: aload 20
    //   3128: iload 6
    //   3130: invokevirtual 903	java/security/SecureRandom:nextInt	(I)I
    //   3133: ifne +101 -> 3234
    //   3136: aload_0
    //   3137: invokevirtual 426	com/google/android/gms/internal/zzcim:zzawu	()Lcom/google/android/gms/internal/zzclq;
    //   3140: pop
    //   3141: aload 23
    //   3143: aload 23
    //   3145: getfield 506	com/google/android/gms/internal/zzcmb:zzjlh	[Lcom/google/android/gms/internal/zzcmc;
    //   3148: ldc_w 1785
    //   3151: iload 6
    //   3153: i2l
    //   3154: invokestatic 497	java/lang/Long:valueOf	(J)Ljava/lang/Long;
    //   3157: invokestatic 1788	com/google/android/gms/internal/zzclq:zza	([Lcom/google/android/gms/internal/zzcmc;Ljava/lang/String;Ljava/lang/Object;)[Lcom/google/android/gms/internal/zzcmc;
    //   3160: putfield 506	com/google/android/gms/internal/zzcmb:zzjlh	[Lcom/google/android/gms/internal/zzcmc;
    //   3163: iload 4
    //   3165: iconst_1
    //   3166: iadd
    //   3167: istore 7
    //   3169: aload 19
    //   3171: iload 4
    //   3173: aload 23
    //   3175: aastore
    //   3176: aload_1
    //   3177: astore 16
    //   3179: aload 24
    //   3181: invokevirtual 1757	java/lang/Boolean:booleanValue	()Z
    //   3184: ifeq +17 -> 3201
    //   3187: aload_1
    //   3188: aconst_null
    //   3189: iload 6
    //   3191: i2l
    //   3192: invokestatic 497	java/lang/Long:valueOf	(J)Ljava/lang/Long;
    //   3195: aconst_null
    //   3196: invokevirtual 1807	com/google/android/gms/internal/zzcgw:zza	(Ljava/lang/Long;Ljava/lang/Long;Ljava/lang/Boolean;)Lcom/google/android/gms/internal/zzcgw;
    //   3199: astore 16
    //   3201: aload 18
    //   3203: aload 23
    //   3205: getfield 1628	com/google/android/gms/internal/zzcmb:name	Ljava/lang/String;
    //   3208: aload 16
    //   3210: aload 23
    //   3212: getfield 1701	com/google/android/gms/internal/zzcmb:zzjli	Ljava/lang/Long;
    //   3215: invokevirtual 563	java/lang/Long:longValue	()J
    //   3218: invokevirtual 1810	com/google/android/gms/internal/zzcgw:zzbc	(J)Lcom/google/android/gms/internal/zzcgw;
    //   3221: invokeinterface 811 3 0
    //   3226: pop
    //   3227: iload 7
    //   3229: istore 4
    //   3231: goto -428 -> 2803
    //   3234: aload_1
    //   3235: getfield 1813	com/google/android/gms/internal/zzcgw:zzizn	J
    //   3238: lstore_2
    //   3239: aload 23
    //   3241: getfield 1701	com/google/android/gms/internal/zzcmb:zzjli	Ljava/lang/Long;
    //   3244: invokevirtual 563	java/lang/Long:longValue	()J
    //   3247: lload_2
    //   3248: lsub
    //   3249: invokestatic 936	java/lang/Math:abs	(J)J
    //   3252: ldc2_w 1814
    //   3255: lcmp
    //   3256: iflt +129 -> 3385
    //   3259: aload_0
    //   3260: invokevirtual 426	com/google/android/gms/internal/zzcim:zzawu	()Lcom/google/android/gms/internal/zzclq;
    //   3263: pop
    //   3264: aload 23
    //   3266: aload 23
    //   3268: getfield 506	com/google/android/gms/internal/zzcmb:zzjlh	[Lcom/google/android/gms/internal/zzcmc;
    //   3271: ldc_w 1793
    //   3274: lconst_1
    //   3275: invokestatic 497	java/lang/Long:valueOf	(J)Ljava/lang/Long;
    //   3278: invokestatic 1788	com/google/android/gms/internal/zzclq:zza	([Lcom/google/android/gms/internal/zzcmc;Ljava/lang/String;Ljava/lang/Object;)[Lcom/google/android/gms/internal/zzcmc;
    //   3281: putfield 506	com/google/android/gms/internal/zzcmb:zzjlh	[Lcom/google/android/gms/internal/zzcmc;
    //   3284: aload_0
    //   3285: invokevirtual 426	com/google/android/gms/internal/zzcim:zzawu	()Lcom/google/android/gms/internal/zzclq;
    //   3288: pop
    //   3289: aload 23
    //   3291: aload 23
    //   3293: getfield 506	com/google/android/gms/internal/zzcmb:zzjlh	[Lcom/google/android/gms/internal/zzcmc;
    //   3296: ldc_w 1785
    //   3299: iload 6
    //   3301: i2l
    //   3302: invokestatic 497	java/lang/Long:valueOf	(J)Ljava/lang/Long;
    //   3305: invokestatic 1788	com/google/android/gms/internal/zzclq:zza	([Lcom/google/android/gms/internal/zzcmc;Ljava/lang/String;Ljava/lang/Object;)[Lcom/google/android/gms/internal/zzcmc;
    //   3308: putfield 506	com/google/android/gms/internal/zzcmb:zzjlh	[Lcom/google/android/gms/internal/zzcmc;
    //   3311: iload 4
    //   3313: iconst_1
    //   3314: iadd
    //   3315: istore 7
    //   3317: aload 19
    //   3319: iload 4
    //   3321: aload 23
    //   3323: aastore
    //   3324: aload_1
    //   3325: astore 16
    //   3327: aload 24
    //   3329: invokevirtual 1757	java/lang/Boolean:booleanValue	()Z
    //   3332: ifeq +20 -> 3352
    //   3335: aload_1
    //   3336: aconst_null
    //   3337: iload 6
    //   3339: i2l
    //   3340: invokestatic 497	java/lang/Long:valueOf	(J)Ljava/lang/Long;
    //   3343: iconst_1
    //   3344: invokestatic 1053	java/lang/Boolean:valueOf	(Z)Ljava/lang/Boolean;
    //   3347: invokevirtual 1807	com/google/android/gms/internal/zzcgw:zza	(Ljava/lang/Long;Ljava/lang/Long;Ljava/lang/Boolean;)Lcom/google/android/gms/internal/zzcgw;
    //   3350: astore 16
    //   3352: aload 18
    //   3354: aload 23
    //   3356: getfield 1628	com/google/android/gms/internal/zzcmb:name	Ljava/lang/String;
    //   3359: aload 16
    //   3361: aload 23
    //   3363: getfield 1701	com/google/android/gms/internal/zzcmb:zzjli	Ljava/lang/Long;
    //   3366: invokevirtual 563	java/lang/Long:longValue	()J
    //   3369: invokevirtual 1810	com/google/android/gms/internal/zzcgw:zzbc	(J)Lcom/google/android/gms/internal/zzcgw;
    //   3372: invokeinterface 811 3 0
    //   3377: pop
    //   3378: iload 7
    //   3380: istore 4
    //   3382: goto -579 -> 2803
    //   3385: aload 24
    //   3387: invokevirtual 1757	java/lang/Boolean:booleanValue	()Z
    //   3390: ifeq +764 -> 4154
    //   3393: aload 18
    //   3395: aload 23
    //   3397: getfield 1628	com/google/android/gms/internal/zzcmb:name	Ljava/lang/String;
    //   3400: aload_1
    //   3401: aload 16
    //   3403: aconst_null
    //   3404: aconst_null
    //   3405: invokevirtual 1807	com/google/android/gms/internal/zzcgw:zza	(Ljava/lang/Long;Ljava/lang/Long;Ljava/lang/Boolean;)Lcom/google/android/gms/internal/zzcgw;
    //   3408: invokeinterface 811 3 0
    //   3413: pop
    //   3414: goto +740 -> 4154
    //   3417: iload 4
    //   3419: aload 17
    //   3421: getfield 1627	com/google/android/gms/internal/zzcme:zzjlp	[Lcom/google/android/gms/internal/zzcmb;
    //   3424: arraylength
    //   3425: if_icmpge +18 -> 3443
    //   3428: aload 17
    //   3430: aload 19
    //   3432: iload 4
    //   3434: invokestatic 1719	java/util/Arrays:copyOf	([Ljava/lang/Object;I)[Ljava/lang/Object;
    //   3437: checkcast 1745	[Lcom/google/android/gms/internal/zzcmb;
    //   3440: putfield 1627	com/google/android/gms/internal/zzcme:zzjlp	[Lcom/google/android/gms/internal/zzcmb;
    //   3443: aload 18
    //   3445: invokeinterface 1819 1 0
    //   3450: invokeinterface 1822 1 0
    //   3455: astore_1
    //   3456: aload_1
    //   3457: invokeinterface 1068 1 0
    //   3462: ifeq +34 -> 3496
    //   3465: aload_1
    //   3466: invokeinterface 1071 1 0
    //   3471: checkcast 1824	java/util/Map$Entry
    //   3474: astore 16
    //   3476: aload_0
    //   3477: invokevirtual 604	com/google/android/gms/internal/zzcim:zzaws	()Lcom/google/android/gms/internal/zzcgo;
    //   3480: aload 16
    //   3482: invokeinterface 1827 1 0
    //   3487: checkcast 1231	com/google/android/gms/internal/zzcgw
    //   3490: invokevirtual 1240	com/google/android/gms/internal/zzcgo:zza	(Lcom/google/android/gms/internal/zzcgw;)V
    //   3493: goto -37 -> 3456
    //   3496: aload 17
    //   3498: ldc2_w 1828
    //   3501: invokestatic 497	java/lang/Long:valueOf	(J)Ljava/lang/Long;
    //   3504: putfield 1352	com/google/android/gms/internal/zzcme:zzjls	Ljava/lang/Long;
    //   3507: aload 17
    //   3509: ldc2_w 1830
    //   3512: invokestatic 497	java/lang/Long:valueOf	(J)Ljava/lang/Long;
    //   3515: putfield 1355	com/google/android/gms/internal/zzcme:zzjlt	Ljava/lang/Long;
    //   3518: iconst_0
    //   3519: istore 4
    //   3521: iload 4
    //   3523: aload 17
    //   3525: getfield 1627	com/google/android/gms/internal/zzcme:zzjlp	[Lcom/google/android/gms/internal/zzcmb;
    //   3528: arraylength
    //   3529: if_icmpge +71 -> 3600
    //   3532: aload 17
    //   3534: getfield 1627	com/google/android/gms/internal/zzcme:zzjlp	[Lcom/google/android/gms/internal/zzcmb;
    //   3537: iload 4
    //   3539: aaload
    //   3540: astore_1
    //   3541: aload_1
    //   3542: getfield 1701	com/google/android/gms/internal/zzcmb:zzjli	Ljava/lang/Long;
    //   3545: invokevirtual 563	java/lang/Long:longValue	()J
    //   3548: aload 17
    //   3550: getfield 1352	com/google/android/gms/internal/zzcme:zzjls	Ljava/lang/Long;
    //   3553: invokevirtual 563	java/lang/Long:longValue	()J
    //   3556: lcmp
    //   3557: ifge +12 -> 3569
    //   3560: aload 17
    //   3562: aload_1
    //   3563: getfield 1701	com/google/android/gms/internal/zzcmb:zzjli	Ljava/lang/Long;
    //   3566: putfield 1352	com/google/android/gms/internal/zzcme:zzjls	Ljava/lang/Long;
    //   3569: aload_1
    //   3570: getfield 1701	com/google/android/gms/internal/zzcmb:zzjli	Ljava/lang/Long;
    //   3573: invokevirtual 563	java/lang/Long:longValue	()J
    //   3576: aload 17
    //   3578: getfield 1355	com/google/android/gms/internal/zzcme:zzjlt	Ljava/lang/Long;
    //   3581: invokevirtual 563	java/lang/Long:longValue	()J
    //   3584: lcmp
    //   3585: ifle +572 -> 4157
    //   3588: aload 17
    //   3590: aload_1
    //   3591: getfield 1701	com/google/android/gms/internal/zzcmb:zzjli	Ljava/lang/Long;
    //   3594: putfield 1355	com/google/android/gms/internal/zzcme:zzjlt	Ljava/lang/Long;
    //   3597: goto +560 -> 4157
    //   3600: aload 22
    //   3602: getfield 1623	com/google/android/gms/internal/zzcim$zza:zzjgi	Lcom/google/android/gms/internal/zzcme;
    //   3605: getfield 1259	com/google/android/gms/internal/zzcme:zzcn	Ljava/lang/String;
    //   3608: astore 16
    //   3610: aload_0
    //   3611: invokevirtual 604	com/google/android/gms/internal/zzcim:zzaws	()Lcom/google/android/gms/internal/zzcgo;
    //   3614: aload 16
    //   3616: invokevirtual 1121	com/google/android/gms/internal/zzcgo:zzjb	(Ljava/lang/String;)Lcom/google/android/gms/internal/zzcgh;
    //   3619: astore 18
    //   3621: aload 18
    //   3623: ifnonnull +161 -> 3784
    //   3626: aload_0
    //   3627: invokevirtual 293	com/google/android/gms/internal/zzcim:zzawy	()Lcom/google/android/gms/internal/zzchm;
    //   3630: invokevirtual 320	com/google/android/gms/internal/zzchm:zzazd	()Lcom/google/android/gms/internal/zzcho;
    //   3633: ldc_w 1833
    //   3636: aload 22
    //   3638: getfield 1623	com/google/android/gms/internal/zzcim$zza:zzjgi	Lcom/google/android/gms/internal/zzcme;
    //   3641: getfield 1259	com/google/android/gms/internal/zzcme:zzcn	Ljava/lang/String;
    //   3644: invokestatic 441	com/google/android/gms/internal/zzchm:zzjk	(Ljava/lang/String;)Ljava/lang/Object;
    //   3647: invokevirtual 348	com/google/android/gms/internal/zzcho:zzj	(Ljava/lang/String;Ljava/lang/Object;)V
    //   3650: aload 17
    //   3652: getfield 1627	com/google/android/gms/internal/zzcme:zzjlp	[Lcom/google/android/gms/internal/zzcmb;
    //   3655: arraylength
    //   3656: ifle +67 -> 3723
    //   3659: aload_0
    //   3660: invokevirtual 793	com/google/android/gms/internal/zzcim:zzawv	()Lcom/google/android/gms/internal/zzcig;
    //   3663: aload 22
    //   3665: getfield 1623	com/google/android/gms/internal/zzcim$zza:zzjgi	Lcom/google/android/gms/internal/zzcme;
    //   3668: getfield 1259	com/google/android/gms/internal/zzcme:zzcn	Ljava/lang/String;
    //   3671: invokevirtual 797	com/google/android/gms/internal/zzcig:zzjs	(Ljava/lang/String;)Lcom/google/android/gms/internal/zzcly;
    //   3674: astore_1
    //   3675: aload_1
    //   3676: ifnull +10 -> 3686
    //   3679: aload_1
    //   3680: getfield 1838	com/google/android/gms/internal/zzcly:zzjkw	Ljava/lang/Long;
    //   3683: ifnonnull +258 -> 3941
    //   3686: aload 22
    //   3688: getfield 1623	com/google/android/gms/internal/zzcim$zza:zzjgi	Lcom/google/android/gms/internal/zzcme;
    //   3691: getfield 1285	com/google/android/gms/internal/zzcme:zzixs	Ljava/lang/String;
    //   3694: invokestatic 403	android/text/TextUtils:isEmpty	(Ljava/lang/CharSequence;)Z
    //   3697: ifeq +217 -> 3914
    //   3700: aload 17
    //   3702: ldc2_w 100
    //   3705: invokestatic 497	java/lang/Long:valueOf	(J)Ljava/lang/Long;
    //   3708: putfield 1841	com/google/android/gms/internal/zzcme:zzjmn	Ljava/lang/Long;
    //   3711: aload_0
    //   3712: invokevirtual 604	com/google/android/gms/internal/zzcim:zzaws	()Lcom/google/android/gms/internal/zzcgo;
    //   3715: aload 17
    //   3717: iload 12
    //   3719: invokevirtual 1844	com/google/android/gms/internal/zzcgo:zza	(Lcom/google/android/gms/internal/zzcme;Z)Z
    //   3722: pop
    //   3723: aload_0
    //   3724: invokevirtual 604	com/google/android/gms/internal/zzcim:zzaws	()Lcom/google/android/gms/internal/zzcgo;
    //   3727: aload 22
    //   3729: getfield 1847	com/google/android/gms/internal/zzcim$zza:zzjgj	Ljava/util/List;
    //   3732: invokevirtual 1851	com/google/android/gms/internal/zzcgo:zzah	(Ljava/util/List;)V
    //   3735: aload_0
    //   3736: invokevirtual 604	com/google/android/gms/internal/zzcim:zzaws	()Lcom/google/android/gms/internal/zzcgo;
    //   3739: astore_1
    //   3740: aload_1
    //   3741: invokevirtual 634	com/google/android/gms/internal/zzcgo:getWritableDatabase	()Landroid/database/sqlite/SQLiteDatabase;
    //   3744: astore 17
    //   3746: aload 17
    //   3748: ldc_w 1853
    //   3751: iconst_2
    //   3752: anewarray 445	java/lang/String
    //   3755: dup
    //   3756: iconst_0
    //   3757: aload 16
    //   3759: aastore
    //   3760: dup
    //   3761: iconst_1
    //   3762: aload 16
    //   3764: aastore
    //   3765: invokevirtual 645	android/database/sqlite/SQLiteDatabase:execSQL	(Ljava/lang/String;[Ljava/lang/Object;)V
    //   3768: aload_0
    //   3769: invokevirtual 604	com/google/android/gms/internal/zzcim:zzaws	()Lcom/google/android/gms/internal/zzcgo;
    //   3772: invokevirtual 1153	com/google/android/gms/internal/zzcgo:setTransactionSuccessful	()V
    //   3775: aload_0
    //   3776: invokevirtual 604	com/google/android/gms/internal/zzcim:zzaws	()Lcom/google/android/gms/internal/zzcgo;
    //   3779: invokevirtual 1156	com/google/android/gms/internal/zzcgo:endTransaction	()V
    //   3782: iconst_1
    //   3783: ireturn
    //   3784: aload 17
    //   3786: getfield 1627	com/google/android/gms/internal/zzcme:zzjlp	[Lcom/google/android/gms/internal/zzcmb;
    //   3789: arraylength
    //   3790: ifle -140 -> 3650
    //   3793: aload 18
    //   3795: invokevirtual 1856	com/google/android/gms/internal/zzcgh:zzaxf	()J
    //   3798: lstore_2
    //   3799: lload_2
    //   3800: lconst_0
    //   3801: lcmp
    //   3802: ifeq +364 -> 4166
    //   3805: lload_2
    //   3806: invokestatic 497	java/lang/Long:valueOf	(J)Ljava/lang/Long;
    //   3809: astore_1
    //   3810: aload 17
    //   3812: aload_1
    //   3813: putfield 1859	com/google/android/gms/internal/zzcme:zzjlv	Ljava/lang/Long;
    //   3816: aload 18
    //   3818: invokevirtual 1862	com/google/android/gms/internal/zzcgh:zzaxe	()J
    //   3821: lstore 10
    //   3823: lload 10
    //   3825: lconst_0
    //   3826: lcmp
    //   3827: ifne +167 -> 3994
    //   3830: lload_2
    //   3831: lconst_0
    //   3832: lcmp
    //   3833: ifeq +338 -> 4171
    //   3836: lload_2
    //   3837: invokestatic 497	java/lang/Long:valueOf	(J)Ljava/lang/Long;
    //   3840: astore_1
    //   3841: aload 17
    //   3843: aload_1
    //   3844: putfield 1865	com/google/android/gms/internal/zzcme:zzjlu	Ljava/lang/Long;
    //   3847: aload 18
    //   3849: invokevirtual 1868	com/google/android/gms/internal/zzcgh:zzaxo	()V
    //   3852: aload 17
    //   3854: aload 18
    //   3856: invokevirtual 1871	com/google/android/gms/internal/zzcgh:zzaxl	()J
    //   3859: l2i
    //   3860: invokestatic 344	java/lang/Integer:valueOf	(I)Ljava/lang/Integer;
    //   3863: putfield 1874	com/google/android/gms/internal/zzcme:zzjmg	Ljava/lang/Integer;
    //   3866: aload 18
    //   3868: aload 17
    //   3870: getfield 1352	com/google/android/gms/internal/zzcme:zzjls	Ljava/lang/Long;
    //   3873: invokevirtual 563	java/lang/Long:longValue	()J
    //   3876: invokevirtual 1404	com/google/android/gms/internal/zzcgh:zzal	(J)V
    //   3879: aload 18
    //   3881: aload 17
    //   3883: getfield 1355	com/google/android/gms/internal/zzcme:zzjlt	Ljava/lang/Long;
    //   3886: invokevirtual 563	java/lang/Long:longValue	()J
    //   3889: invokevirtual 1407	com/google/android/gms/internal/zzcgh:zzam	(J)V
    //   3892: aload 17
    //   3894: aload 18
    //   3896: invokevirtual 1877	com/google/android/gms/internal/zzcgh:zzaxw	()Ljava/lang/String;
    //   3899: putfield 1878	com/google/android/gms/internal/zzcme:zzixw	Ljava/lang/String;
    //   3902: aload_0
    //   3903: invokevirtual 604	com/google/android/gms/internal/zzcim:zzaws	()Lcom/google/android/gms/internal/zzcgo;
    //   3906: aload 18
    //   3908: invokevirtual 1429	com/google/android/gms/internal/zzcgo:zza	(Lcom/google/android/gms/internal/zzcgh;)V
    //   3911: goto -261 -> 3650
    //   3914: aload_0
    //   3915: invokevirtual 293	com/google/android/gms/internal/zzcim:zzawy	()Lcom/google/android/gms/internal/zzchm;
    //   3918: invokevirtual 296	com/google/android/gms/internal/zzchm:zzazf	()Lcom/google/android/gms/internal/zzcho;
    //   3921: ldc_w 1880
    //   3924: aload 22
    //   3926: getfield 1623	com/google/android/gms/internal/zzcim$zza:zzjgi	Lcom/google/android/gms/internal/zzcme;
    //   3929: getfield 1259	com/google/android/gms/internal/zzcme:zzcn	Ljava/lang/String;
    //   3932: invokestatic 441	com/google/android/gms/internal/zzchm:zzjk	(Ljava/lang/String;)Ljava/lang/Object;
    //   3935: invokevirtual 348	com/google/android/gms/internal/zzcho:zzj	(Ljava/lang/String;Ljava/lang/Object;)V
    //   3938: goto -227 -> 3711
    //   3941: aload 17
    //   3943: aload_1
    //   3944: getfield 1838	com/google/android/gms/internal/zzcly:zzjkw	Ljava/lang/Long;
    //   3947: putfield 1841	com/google/android/gms/internal/zzcme:zzjmn	Ljava/lang/Long;
    //   3950: goto -239 -> 3711
    //   3953: astore 17
    //   3955: aload_1
    //   3956: invokevirtual 273	com/google/android/gms/internal/zzcjk:zzawy	()Lcom/google/android/gms/internal/zzchm;
    //   3959: invokevirtual 320	com/google/android/gms/internal/zzchm:zzazd	()Lcom/google/android/gms/internal/zzcho;
    //   3962: ldc_w 1882
    //   3965: aload 16
    //   3967: invokestatic 441	com/google/android/gms/internal/zzchm:zzjk	(Ljava/lang/String;)Ljava/lang/Object;
    //   3970: aload 17
    //   3972: invokevirtual 455	com/google/android/gms/internal/zzcho:zze	(Ljava/lang/String;Ljava/lang/Object;Ljava/lang/Object;)V
    //   3975: goto -207 -> 3768
    //   3978: aload_0
    //   3979: invokevirtual 604	com/google/android/gms/internal/zzcim:zzaws	()Lcom/google/android/gms/internal/zzcgo;
    //   3982: invokevirtual 1153	com/google/android/gms/internal/zzcgo:setTransactionSuccessful	()V
    //   3985: aload_0
    //   3986: invokevirtual 604	com/google/android/gms/internal/zzcim:zzaws	()Lcom/google/android/gms/internal/zzcgo;
    //   3989: invokevirtual 1156	com/google/android/gms/internal/zzcgo:endTransaction	()V
    //   3992: iconst_0
    //   3993: ireturn
    //   3994: lload 10
    //   3996: lstore_2
    //   3997: goto -167 -> 3830
    //   4000: goto -992 -> 3008
    //   4003: iconst_1
    //   4004: istore 6
    //   4006: goto -1157 -> 2849
    //   4009: goto +114 -> 4123
    //   4012: iconst_1
    //   4013: istore 13
    //   4015: goto -1907 -> 2108
    //   4018: goto +96 -> 4114
    //   4021: goto -3570 -> 451
    //   4024: astore 16
    //   4026: aconst_null
    //   4027: astore 17
    //   4029: aconst_null
    //   4030: astore_1
    //   4031: goto -2831 -> 1200
    //   4034: astore 18
    //   4036: aconst_null
    //   4037: astore 17
    //   4039: aload 16
    //   4041: astore_1
    //   4042: aload 18
    //   4044: astore 16
    //   4046: goto -2846 -> 1200
    //   4049: astore 16
    //   4051: aload 18
    //   4053: astore 17
    //   4055: goto -2855 -> 1200
    //   4058: astore_1
    //   4059: goto -2641 -> 1418
    //   4062: astore_1
    //   4063: aload 17
    //   4065: astore 16
    //   4067: goto +32 -> 4099
    //   4070: astore_1
    //   4071: aload 18
    //   4073: astore 16
    //   4075: goto +24 -> 4099
    //   4078: astore 16
    //   4080: goto -2880 -> 1200
    //   4083: iconst_1
    //   4084: istore 4
    //   4086: goto -3884 -> 202
    //   4089: iconst_1
    //   4090: istore 5
    //   4092: goto -3712 -> 380
    //   4095: astore_1
    //   4096: aconst_null
    //   4097: astore 16
    //   4099: goto -2681 -> 1418
    //   4102: iconst_0
    //   4103: istore 4
    //   4105: goto -3903 -> 202
    //   4108: iconst_0
    //   4109: istore 5
    //   4111: goto -3731 -> 380
    //   4114: iload 7
    //   4116: iconst_1
    //   4117: iadd
    //   4118: istore 7
    //   4120: goto -2540 -> 1580
    //   4123: iload 5
    //   4125: iconst_1
    //   4126: iadd
    //   4127: istore 5
    //   4129: goto -1869 -> 2260
    //   4132: iload 5
    //   4134: iconst_1
    //   4135: iadd
    //   4136: istore 5
    //   4138: goto -2132 -> 2006
    //   4141: iload 14
    //   4143: istore 12
    //   4145: goto -1794 -> 2351
    //   4148: iconst_0
    //   4149: istore 13
    //   4151: goto -1117 -> 3034
    //   4154: goto -1351 -> 2803
    //   4157: iload 4
    //   4159: iconst_1
    //   4160: iadd
    //   4161: istore 4
    //   4163: goto -642 -> 3521
    //   4166: aconst_null
    //   4167: astore_1
    //   4168: goto -358 -> 3810
    //   4171: aconst_null
    //   4172: astore_1
    //   4173: goto -332 -> 3841
    // Local variable table:
    //   start	length	slot	name	signature
    //   0	4176	0	this	zzcim
    //   0	4176	1	paramString	String
    //   0	4176	2	paramLong	long
    //   202	3960	4	i	int
    //   380	3757	5	j	int
    //   239	3766	6	k	int
    //   1575	2544	7	m	int
    //   1578	1030	8	n	int
    //   1572	13	9	i1	int
    //   28	3967	10	l	long
    //   161	3983	12	bool1	boolean
    //   2008	2142	13	bool2	boolean
    //   1479	2663	14	bool3	boolean
    //   1465	676	15	bool4	boolean
    //   101	1068	16	localObject1	Object
    //   1198	22	16	localSQLiteException1	SQLiteException
    //   1258	34	16	localObject2	Object
    //   1363	61	16	localIOException1	IOException
    //   1591	2375	16	localObject3	Object
    //   4024	16	16	localSQLiteException2	SQLiteException
    //   4044	1	16	localObject4	Object
    //   4049	1	16	localSQLiteException3	SQLiteException
    //   4065	9	16	localObject5	Object
    //   4078	1	16	localSQLiteException4	SQLiteException
    //   4097	1	16	localObject6	Object
    //   153	3789	17	localObject7	Object
    //   3953	18	17	localSQLiteException5	SQLiteException
    //   4027	37	17	localObject8	Object
    //   496	587	18	localObject9	Object
    //   1116	73	18	localIOException2	IOException
    //   1193	2714	18	localObject10	Object
    //   4034	38	18	localSQLiteException6	SQLiteException
    //   573	2858	19	localObject11	Object
    //   828	2299	20	localObject12	Object
    //   862	1749	21	localObject13	Object
    //   16	3909	22	localZza	zzcim.zza
    //   22	3374	23	localZzcgo	zzcgo
    //   51	3335	24	localObject14	Object
    // Exception table:
    //   from	to	target	type
    //   7	46	633	finally
    //   172	178	633	finally
    //   178	199	633	finally
    //   210	235	633	finally
    //   241	377	633	finally
    //   385	451	633	finally
    //   623	630	633	finally
    //   751	757	633	finally
    //   1107	1113	633	finally
    //   1151	1158	633	finally
    //   1228	1234	633	finally
    //   1354	1360	633	finally
    //   1409	1415	633	finally
    //   1423	1430	633	finally
    //   1430	1432	633	finally
    //   1432	1467	633	finally
    //   1472	1477	633	finally
    //   1481	1505	633	finally
    //   1508	1551	633	finally
    //   1551	1574	633	finally
    //   1593	1616	633	finally
    //   1622	1645	633	finally
    //   1661	1798	633	finally
    //   1803	1940	633	finally
    //   1940	2003	633	finally
    //   2010	2051	633	finally
    //   2056	2069	633	finally
    //   2069	2098	633	finally
    //   2098	2104	633	finally
    //   2112	2136	633	finally
    //   2149	2240	633	finally
    //   2242	2254	633	finally
    //   2274	2288	633	finally
    //   2294	2308	633	finally
    //   2323	2347	633	finally
    //   2351	2374	633	finally
    //   2387	2404	633	finally
    //   2411	2435	633	finally
    //   2442	2475	633	finally
    //   2475	2576	633	finally
    //   2579	2600	633	finally
    //   2617	2663	633	finally
    //   2671	2700	633	finally
    //   2700	2744	633	finally
    //   2744	2786	633	finally
    //   2812	2849	633	finally
    //   2854	2877	633	finally
    //   2897	2913	633	finally
    //   2917	2939	633	finally
    //   2947	3008	633	finally
    //   3008	3026	633	finally
    //   3034	3041	633	finally
    //   3064	3086	633	finally
    //   3090	3097	633	finally
    //   3097	3119	633	finally
    //   3126	3163	633	finally
    //   3179	3201	633	finally
    //   3201	3227	633	finally
    //   3234	3311	633	finally
    //   3327	3352	633	finally
    //   3352	3378	633	finally
    //   3385	3414	633	finally
    //   3417	3443	633	finally
    //   3443	3456	633	finally
    //   3456	3493	633	finally
    //   3496	3518	633	finally
    //   3521	3569	633	finally
    //   3569	3597	633	finally
    //   3600	3621	633	finally
    //   3626	3650	633	finally
    //   3650	3675	633	finally
    //   3679	3686	633	finally
    //   3686	3711	633	finally
    //   3711	3723	633	finally
    //   3723	3746	633	finally
    //   3746	3768	633	finally
    //   3768	3775	633	finally
    //   3784	3799	633	finally
    //   3805	3810	633	finally
    //   3810	3823	633	finally
    //   3836	3841	633	finally
    //   3841	3911	633	finally
    //   3914	3938	633	finally
    //   3941	3950	633	finally
    //   3955	3975	633	finally
    //   3978	3985	633	finally
    //   871	879	1116	java/io/IOException
    //   1072	1081	1198	android/database/sqlite/SQLiteException
    //   1084	1103	1198	android/database/sqlite/SQLiteException
    //   1240	1248	1198	android/database/sqlite/SQLiteException
    //   1251	1260	1198	android/database/sqlite/SQLiteException
    //   1263	1274	1198	android/database/sqlite/SQLiteException
    //   1277	1286	1198	android/database/sqlite/SQLiteException
    //   1289	1297	1198	android/database/sqlite/SQLiteException
    //   1300	1312	1198	android/database/sqlite/SQLiteException
    //   1315	1330	1198	android/database/sqlite/SQLiteException
    //   1333	1345	1198	android/database/sqlite/SQLiteException
    //   1368	1389	1198	android/database/sqlite/SQLiteException
    //   1392	1400	1198	android/database/sqlite/SQLiteException
    //   1289	1297	1363	java/io/IOException
    //   3746	3768	3953	android/database/sqlite/SQLiteException
    //   46	60	4024	android/database/sqlite/SQLiteException
    //   103	149	4024	android/database/sqlite/SQLiteException
    //   683	728	4024	android/database/sqlite/SQLiteException
    //   155	163	4034	android/database/sqlite/SQLiteException
    //   489	498	4034	android/database/sqlite/SQLiteException
    //   734	742	4034	android/database/sqlite/SQLiteException
    //   786	795	4034	android/database/sqlite/SQLiteException
    //   801	807	4034	android/database/sqlite/SQLiteException
    //   501	510	4049	android/database/sqlite/SQLiteException
    //   513	519	4049	android/database/sqlite/SQLiteException
    //   530	575	4058	finally
    //   582	592	4058	finally
    //   599	618	4058	finally
    //   820	830	4058	finally
    //   837	848	4058	finally
    //   855	864	4058	finally
    //   871	879	4058	finally
    //   886	896	4058	finally
    //   903	922	4058	finally
    //   929	936	4058	finally
    //   943	952	4058	finally
    //   973	979	4058	finally
    //   998	1007	4058	finally
    //   1018	1066	4058	finally
    //   1125	1146	4058	finally
    //   1173	1179	4058	finally
    //   155	163	4062	finally
    //   489	498	4062	finally
    //   501	510	4062	finally
    //   513	519	4062	finally
    //   734	742	4062	finally
    //   786	795	4062	finally
    //   801	807	4062	finally
    //   1072	1081	4070	finally
    //   1084	1103	4070	finally
    //   1203	1224	4070	finally
    //   1240	1248	4070	finally
    //   1251	1260	4070	finally
    //   1263	1274	4070	finally
    //   1277	1286	4070	finally
    //   1289	1297	4070	finally
    //   1300	1312	4070	finally
    //   1315	1330	4070	finally
    //   1333	1345	4070	finally
    //   1368	1389	4070	finally
    //   1392	1400	4070	finally
    //   530	575	4078	android/database/sqlite/SQLiteException
    //   582	592	4078	android/database/sqlite/SQLiteException
    //   599	618	4078	android/database/sqlite/SQLiteException
    //   820	830	4078	android/database/sqlite/SQLiteException
    //   837	848	4078	android/database/sqlite/SQLiteException
    //   855	864	4078	android/database/sqlite/SQLiteException
    //   871	879	4078	android/database/sqlite/SQLiteException
    //   886	896	4078	android/database/sqlite/SQLiteException
    //   903	922	4078	android/database/sqlite/SQLiteException
    //   929	936	4078	android/database/sqlite/SQLiteException
    //   943	952	4078	android/database/sqlite/SQLiteException
    //   973	979	4078	android/database/sqlite/SQLiteException
    //   998	1007	4078	android/database/sqlite/SQLiteException
    //   1018	1066	4078	android/database/sqlite/SQLiteException
    //   1125	1146	4078	android/database/sqlite/SQLiteException
    //   1173	1179	4078	android/database/sqlite/SQLiteException
    //   46	60	4095	finally
    //   103	149	4095	finally
    //   683	728	4095	finally
  }
  
  @WorkerThread
  private final zzcgi zzjw(String paramString)
  {
    zzcgh localZzcgh = zzaws().zzjb(paramString);
    if ((localZzcgh == null) || (TextUtils.isEmpty(localZzcgh.zzvj())))
    {
      zzawy().zzazi().zzj("No app data available; dropping", paramString);
      return null;
    }
    try
    {
      String str = zzbhf.zzdb(this.mContext).getPackageInfo(paramString, 0).versionName;
      if ((localZzcgh.zzvj() != null) && (!localZzcgh.zzvj().equals(str)))
      {
        zzawy().zzazf().zzj("App version does not match; dropping. appId", zzchm.zzjk(paramString));
        return null;
      }
    }
    catch (PackageManager.NameNotFoundException localNameNotFoundException) {}
    return new zzcgi(paramString, localZzcgh.getGmpAppId(), localZzcgh.zzvj(), localZzcgh.zzaxg(), localZzcgh.zzaxh(), localZzcgh.zzaxi(), localZzcgh.zzaxj(), null, localZzcgh.zzaxk(), false, localZzcgh.zzaxd(), localZzcgh.zzaxx(), 0L, 0, localZzcgh.zzaxy());
  }
  
  public final Context getContext()
  {
    return this.mContext;
  }
  
  @WorkerThread
  public final boolean isEnabled()
  {
    boolean bool = false;
    zzawx().zzve();
    zzxf();
    if (this.zzjew.zzaya()) {
      return false;
    }
    Boolean localBoolean = this.zzjew.zziy("firebase_analytics_collection_enabled");
    if (localBoolean != null) {
      bool = localBoolean.booleanValue();
    }
    for (;;)
    {
      return zzawz().zzbn(bool);
      if (!zzbz.zzaji()) {
        bool = true;
      }
    }
  }
  
  @WorkerThread
  protected final void start()
  {
    zzawx().zzve();
    zzaws().zzayh();
    if (zzawz().zzjcr.get() == 0L) {
      zzawz().zzjcr.set(this.zzata.currentTimeMillis());
    }
    if (Long.valueOf(zzawz().zzjcw.get()).longValue() == 0L)
    {
      zzawy().zzazj().zzj("Persisting first open", Long.valueOf(this.zzjgg));
      zzawz().zzjcw.set(this.zzjgg);
    }
    if (!zzazv())
    {
      if (isEnabled())
      {
        if (!zzawu().zzeb("android.permission.INTERNET")) {
          zzawy().zzazd().log("App is missing INTERNET permission");
        }
        if (!zzawu().zzeb("android.permission.ACCESS_NETWORK_STATE")) {
          zzawy().zzazd().log("App is missing ACCESS_NETWORK_STATE permission");
        }
        if (!zzbhf.zzdb(this.mContext).zzamu())
        {
          if (!zzcid.zzbk(this.mContext)) {
            zzawy().zzazd().log("AppMeasurementReceiver not registered/enabled");
          }
          if (!zzcla.zzk(this.mContext, false)) {
            zzawy().zzazd().log("AppMeasurementService not registered/enabled");
          }
        }
        zzawy().zzazd().log("Uploading is not possible. App measurement disabled");
      }
      zzbaj();
      return;
    }
    Object localObject;
    if (!TextUtils.isEmpty(zzawn().getGmpAppId()))
    {
      localObject = zzawz().zzazm();
      if (localObject != null) {
        break label422;
      }
      zzawz().zzjo(zzawn().getGmpAppId());
    }
    for (;;)
    {
      zzawm().zzjp(zzawz().zzjcx.zzazr());
      if (TextUtils.isEmpty(zzawn().getGmpAppId())) {
        break;
      }
      localObject = zzawm();
      ((zzcjk)localObject).zzve();
      ((zzcjl)localObject).zzxf();
      if (((zzcjn)localObject).zziwf.zzazv())
      {
        ((zzcjk)localObject).zzawp().zzbar();
        String str = ((zzcjk)localObject).zzawz().zzazq();
        if (!TextUtils.isEmpty(str))
        {
          ((zzcjk)localObject).zzawo().zzxf();
          if (!str.equals(Build.VERSION.RELEASE))
          {
            Bundle localBundle = new Bundle();
            localBundle.putString("_po", str);
            ((zzcjn)localObject).zzc("auto", "_ou", localBundle);
          }
        }
      }
      zzawp().zza(new AtomicReference());
      break;
      label422:
      if (!((String)localObject).equals(zzawn().getGmpAppId()))
      {
        zzawy().zzazh().log("Rechecking which service to use due to a GMP App Id change");
        zzawz().zzazp();
        this.zzjfk.disconnect();
        this.zzjfk.zzyc();
        zzawz().zzjo(zzawn().getGmpAppId());
        zzawz().zzjcw.set(this.zzjgg);
        zzawz().zzjcx.zzjq(null);
      }
    }
  }
  
  /* Error */
  @WorkerThread
  protected final void zza(int paramInt, Throwable paramThrowable, byte[] paramArrayOfByte)
  {
    // Byte code:
    //   0: aload_0
    //   1: invokevirtual 308	com/google/android/gms/internal/zzcim:zzawx	()Lcom/google/android/gms/internal/zzcih;
    //   4: invokevirtual 311	com/google/android/gms/internal/zzcjk:zzve	()V
    //   7: aload_0
    //   8: invokevirtual 915	com/google/android/gms/internal/zzcim:zzxf	()V
    //   11: aload_3
    //   12: astore 6
    //   14: aload_3
    //   15: ifnonnull +8 -> 23
    //   18: iconst_0
    //   19: newarray byte
    //   21: astore 6
    //   23: aload_0
    //   24: getfield 2020	com/google/android/gms/internal/zzcim:zzjfx	Ljava/util/List;
    //   27: astore_3
    //   28: aload_0
    //   29: aconst_null
    //   30: putfield 2020	com/google/android/gms/internal/zzcim:zzjfx	Ljava/util/List;
    //   33: iload_1
    //   34: sipush 200
    //   37: if_icmpeq +10 -> 47
    //   40: iload_1
    //   41: sipush 204
    //   44: if_icmpne +316 -> 360
    //   47: aload_2
    //   48: ifnonnull +312 -> 360
    //   51: aload_0
    //   52: invokevirtual 883	com/google/android/gms/internal/zzcim:zzawz	()Lcom/google/android/gms/internal/zzchx;
    //   55: getfield 979	com/google/android/gms/internal/zzchx:zzjcr	Lcom/google/android/gms/internal/zzcia;
    //   58: aload_0
    //   59: getfield 111	com/google/android/gms/internal/zzcim:zzata	Lcom/google/android/gms/common/util/zzd;
    //   62: invokeinterface 117 1 0
    //   67: invokevirtual 907	com/google/android/gms/internal/zzcia:set	(J)V
    //   70: aload_0
    //   71: invokevirtual 883	com/google/android/gms/internal/zzcim:zzawz	()Lcom/google/android/gms/internal/zzchx;
    //   74: getfield 982	com/google/android/gms/internal/zzchx:zzjcs	Lcom/google/android/gms/internal/zzcia;
    //   77: lconst_0
    //   78: invokevirtual 907	com/google/android/gms/internal/zzcia:set	(J)V
    //   81: aload_0
    //   82: invokespecial 1515	com/google/android/gms/internal/zzcim:zzbaj	()V
    //   85: aload_0
    //   86: invokevirtual 293	com/google/android/gms/internal/zzcim:zzawy	()Lcom/google/android/gms/internal/zzchm;
    //   89: invokevirtual 277	com/google/android/gms/internal/zzchm:zzazj	()Lcom/google/android/gms/internal/zzcho;
    //   92: ldc_w 2022
    //   95: iload_1
    //   96: invokestatic 344	java/lang/Integer:valueOf	(I)Ljava/lang/Integer;
    //   99: aload 6
    //   101: arraylength
    //   102: invokestatic 344	java/lang/Integer:valueOf	(I)Ljava/lang/Integer;
    //   105: invokevirtual 455	com/google/android/gms/internal/zzcho:zze	(Ljava/lang/String;Ljava/lang/Object;Ljava/lang/Object;)V
    //   108: aload_0
    //   109: invokevirtual 604	com/google/android/gms/internal/zzcim:zzaws	()Lcom/google/android/gms/internal/zzcgo;
    //   112: invokevirtual 1146	com/google/android/gms/internal/zzcgo:beginTransaction	()V
    //   115: aload_3
    //   116: invokeinterface 1063 1 0
    //   121: astore_3
    //   122: aload_3
    //   123: invokeinterface 1068 1 0
    //   128: ifeq +163 -> 291
    //   131: aload_3
    //   132: invokeinterface 1071 1 0
    //   137: checkcast 494	java/lang/Long
    //   140: astore 6
    //   142: aload_0
    //   143: invokevirtual 604	com/google/android/gms/internal/zzcim:zzaws	()Lcom/google/android/gms/internal/zzcgo;
    //   146: astore_2
    //   147: aload 6
    //   149: invokevirtual 563	java/lang/Long:longValue	()J
    //   152: lstore 4
    //   154: aload_2
    //   155: invokevirtual 311	com/google/android/gms/internal/zzcjk:zzve	()V
    //   158: aload_2
    //   159: invokevirtual 630	com/google/android/gms/internal/zzcjl:zzxf	()V
    //   162: aload_2
    //   163: invokevirtual 634	com/google/android/gms/internal/zzcgo:getWritableDatabase	()Landroid/database/sqlite/SQLiteDatabase;
    //   166: astore 6
    //   168: aload 6
    //   170: ldc_w 2024
    //   173: ldc_w 2026
    //   176: iconst_1
    //   177: anewarray 445	java/lang/String
    //   180: dup
    //   181: iconst_0
    //   182: lload 4
    //   184: invokestatic 1587	java/lang/String:valueOf	(J)Ljava/lang/String;
    //   187: aastore
    //   188: invokevirtual 2030	android/database/sqlite/SQLiteDatabase:delete	(Ljava/lang/String;Ljava/lang/String;[Ljava/lang/String;)I
    //   191: iconst_1
    //   192: if_icmpeq -70 -> 122
    //   195: new 528	android/database/sqlite/SQLiteException
    //   198: dup
    //   199: ldc_w 2032
    //   202: invokespecial 2033	android/database/sqlite/SQLiteException:<init>	(Ljava/lang/String;)V
    //   205: athrow
    //   206: astore_3
    //   207: aload_2
    //   208: invokevirtual 273	com/google/android/gms/internal/zzcjk:zzawy	()Lcom/google/android/gms/internal/zzchm;
    //   211: invokevirtual 320	com/google/android/gms/internal/zzchm:zzazd	()Lcom/google/android/gms/internal/zzcho;
    //   214: ldc_w 2035
    //   217: aload_3
    //   218: invokevirtual 348	com/google/android/gms/internal/zzcho:zzj	(Ljava/lang/String;Ljava/lang/Object;)V
    //   221: aload_3
    //   222: athrow
    //   223: astore_2
    //   224: aload_0
    //   225: invokevirtual 604	com/google/android/gms/internal/zzcim:zzaws	()Lcom/google/android/gms/internal/zzcgo;
    //   228: invokevirtual 1156	com/google/android/gms/internal/zzcgo:endTransaction	()V
    //   231: aload_2
    //   232: athrow
    //   233: astore_2
    //   234: aload_0
    //   235: invokevirtual 293	com/google/android/gms/internal/zzcim:zzawy	()Lcom/google/android/gms/internal/zzchm;
    //   238: invokevirtual 320	com/google/android/gms/internal/zzchm:zzazd	()Lcom/google/android/gms/internal/zzcho;
    //   241: ldc_w 2037
    //   244: aload_2
    //   245: invokevirtual 348	com/google/android/gms/internal/zzcho:zzj	(Ljava/lang/String;Ljava/lang/Object;)V
    //   248: aload_0
    //   249: aload_0
    //   250: getfield 111	com/google/android/gms/internal/zzcim:zzata	Lcom/google/android/gms/common/util/zzd;
    //   253: invokeinterface 932 1 0
    //   258: putfield 927	com/google/android/gms/internal/zzcim:zzjgc	J
    //   261: aload_0
    //   262: invokevirtual 293	com/google/android/gms/internal/zzcim:zzawy	()Lcom/google/android/gms/internal/zzchm;
    //   265: invokevirtual 277	com/google/android/gms/internal/zzchm:zzazj	()Lcom/google/android/gms/internal/zzcho;
    //   268: ldc_w 2039
    //   271: aload_0
    //   272: getfield 927	com/google/android/gms/internal/zzcim:zzjgc	J
    //   275: invokestatic 497	java/lang/Long:valueOf	(J)Ljava/lang/Long;
    //   278: invokevirtual 348	com/google/android/gms/internal/zzcho:zzj	(Ljava/lang/String;Ljava/lang/Object;)V
    //   281: aload_0
    //   282: iconst_0
    //   283: putfield 1044	com/google/android/gms/internal/zzcim:zzjge	Z
    //   286: aload_0
    //   287: invokespecial 2041	com/google/android/gms/internal/zzcim:zzban	()V
    //   290: return
    //   291: aload_0
    //   292: invokevirtual 604	com/google/android/gms/internal/zzcim:zzaws	()Lcom/google/android/gms/internal/zzcgo;
    //   295: invokevirtual 1153	com/google/android/gms/internal/zzcgo:setTransactionSuccessful	()V
    //   298: aload_0
    //   299: invokevirtual 604	com/google/android/gms/internal/zzcim:zzaws	()Lcom/google/android/gms/internal/zzcgo;
    //   302: invokevirtual 1156	com/google/android/gms/internal/zzcgo:endTransaction	()V
    //   305: aload_0
    //   306: invokevirtual 817	com/google/android/gms/internal/zzcim:zzbab	()Lcom/google/android/gms/internal/zzchq;
    //   309: invokevirtual 1020	com/google/android/gms/internal/zzchq:zzzs	()Z
    //   312: ifeq +34 -> 346
    //   315: aload_0
    //   316: invokespecial 953	com/google/android/gms/internal/zzcim:zzbai	()Z
    //   319: ifeq +27 -> 346
    //   322: aload_0
    //   323: invokevirtual 2044	com/google/android/gms/internal/zzcim:zzbah	()V
    //   326: aload_0
    //   327: lconst_0
    //   328: putfield 927	com/google/android/gms/internal/zzcim:zzjgc	J
    //   331: goto -50 -> 281
    //   334: astore_2
    //   335: aload_0
    //   336: iconst_0
    //   337: putfield 1044	com/google/android/gms/internal/zzcim:zzjge	Z
    //   340: aload_0
    //   341: invokespecial 2041	com/google/android/gms/internal/zzcim:zzban	()V
    //   344: aload_2
    //   345: athrow
    //   346: aload_0
    //   347: ldc2_w 100
    //   350: putfield 103	com/google/android/gms/internal/zzcim:zzjgb	J
    //   353: aload_0
    //   354: invokespecial 1515	com/google/android/gms/internal/zzcim:zzbaj	()V
    //   357: goto -31 -> 326
    //   360: aload_0
    //   361: invokevirtual 293	com/google/android/gms/internal/zzcim:zzawy	()Lcom/google/android/gms/internal/zzchm;
    //   364: invokevirtual 277	com/google/android/gms/internal/zzchm:zzazj	()Lcom/google/android/gms/internal/zzcho;
    //   367: ldc_w 2046
    //   370: iload_1
    //   371: invokestatic 344	java/lang/Integer:valueOf	(I)Ljava/lang/Integer;
    //   374: aload_2
    //   375: invokevirtual 455	com/google/android/gms/internal/zzcho:zze	(Ljava/lang/String;Ljava/lang/Object;Ljava/lang/Object;)V
    //   378: aload_0
    //   379: invokevirtual 883	com/google/android/gms/internal/zzcim:zzawz	()Lcom/google/android/gms/internal/zzchx;
    //   382: getfield 982	com/google/android/gms/internal/zzchx:zzjcs	Lcom/google/android/gms/internal/zzcia;
    //   385: aload_0
    //   386: getfield 111	com/google/android/gms/internal/zzcim:zzata	Lcom/google/android/gms/common/util/zzd;
    //   389: invokeinterface 117 1 0
    //   394: invokevirtual 907	com/google/android/gms/internal/zzcia:set	(J)V
    //   397: iload_1
    //   398: sipush 503
    //   401: if_icmpeq +48 -> 449
    //   404: iload_1
    //   405: sipush 429
    //   408: if_icmpne +36 -> 444
    //   411: goto +38 -> 449
    //   414: iload_1
    //   415: ifeq +22 -> 437
    //   418: aload_0
    //   419: invokevirtual 883	com/google/android/gms/internal/zzcim:zzawz	()Lcom/google/android/gms/internal/zzchx;
    //   422: getfield 1028	com/google/android/gms/internal/zzchx:zzjct	Lcom/google/android/gms/internal/zzcia;
    //   425: aload_0
    //   426: getfield 111	com/google/android/gms/internal/zzcim:zzata	Lcom/google/android/gms/common/util/zzd;
    //   429: invokeinterface 117 1 0
    //   434: invokevirtual 907	com/google/android/gms/internal/zzcia:set	(J)V
    //   437: aload_0
    //   438: invokespecial 1515	com/google/android/gms/internal/zzcim:zzbaj	()V
    //   441: goto -160 -> 281
    //   444: iconst_0
    //   445: istore_1
    //   446: goto -32 -> 414
    //   449: iconst_1
    //   450: istore_1
    //   451: goto -37 -> 414
    // Local variable table:
    //   start	length	slot	name	signature
    //   0	454	0	this	zzcim
    //   0	454	1	paramInt	int
    //   0	454	2	paramThrowable	Throwable
    //   0	454	3	paramArrayOfByte	byte[]
    //   152	31	4	l	long
    //   12	157	6	localObject	Object
    // Exception table:
    //   from	to	target	type
    //   168	206	206	android/database/sqlite/SQLiteException
    //   115	122	223	finally
    //   122	168	223	finally
    //   168	206	223	finally
    //   207	223	223	finally
    //   291	298	223	finally
    //   51	115	233	android/database/sqlite/SQLiteException
    //   224	233	233	android/database/sqlite/SQLiteException
    //   298	326	233	android/database/sqlite/SQLiteException
    //   326	331	233	android/database/sqlite/SQLiteException
    //   346	357	233	android/database/sqlite/SQLiteException
    //   18	23	334	finally
    //   23	33	334	finally
    //   51	115	334	finally
    //   224	233	334	finally
    //   234	281	334	finally
    //   298	326	334	finally
    //   326	331	334	finally
    //   346	357	334	finally
    //   360	397	334	finally
    //   418	437	334	finally
    //   437	441	334	finally
  }
  
  @WorkerThread
  public final byte[] zza(@NonNull zzcha paramZzcha, @Size(min=1L) String paramString)
  {
    zzxf();
    zzawx().zzve();
    zzawi();
    zzbq.checkNotNull(paramZzcha);
    zzbq.zzgm(paramString);
    zzcmd localZzcmd = new zzcmd();
    zzaws().beginTransaction();
    zzcgh localZzcgh;
    zzcme localZzcme;
    Object localObject1;
    try
    {
      localZzcgh = zzaws().zzjb(paramString);
      if (localZzcgh == null)
      {
        zzawy().zzazi().zzj("Log and bundle not available. package_name", paramString);
        return new byte[0];
      }
      if (!localZzcgh.zzaxk())
      {
        zzawy().zzazi().zzj("Log and bundle disabled. package_name", paramString);
        return new byte[0];
      }
      if ((("_iap".equals(paramZzcha.name)) || ("ecommerce_purchase".equals(paramZzcha.name))) && (!zza(paramString, paramZzcha))) {
        zzawy().zzazf().zzj("Failed to handle purchase event at single event bundle creation. appId", zzchm.zzjk(paramString));
      }
      localZzcme = new zzcme();
      localZzcmd.zzjlm = new zzcme[] { localZzcme };
      localZzcme.zzjlo = Integer.valueOf(1);
      localZzcme.zzjlw = "android";
      localZzcme.zzcn = localZzcgh.getAppId();
      localZzcme.zzixt = localZzcgh.zzaxh();
      localZzcme.zzifm = localZzcgh.zzvj();
      l1 = localZzcgh.zzaxg();
      if (l1 == -2147483648L) {}
      int i;
      for (localObject1 = null;; localObject1 = Integer.valueOf((int)l1))
      {
        localZzcme.zzjmj = ((Integer)localObject1);
        localZzcme.zzjma = Long.valueOf(localZzcgh.zzaxi());
        localZzcme.zzixs = localZzcgh.getGmpAppId();
        localZzcme.zzjmf = Long.valueOf(localZzcgh.zzaxj());
        if ((isEnabled()) && (zzcgn.zzaye()) && (this.zzjew.zziz(localZzcme.zzcn)))
        {
          zzawn();
          localZzcme.zzjmo = null;
        }
        localObject1 = zzawz().zzjm(localZzcgh.getAppId());
        if ((localZzcgh.zzaxy()) && (localObject1 != null) && (!TextUtils.isEmpty((CharSequence)((Pair)localObject1).first)))
        {
          localZzcme.zzjmc = ((String)((Pair)localObject1).first);
          localZzcme.zzjmd = ((Boolean)((Pair)localObject1).second);
        }
        zzawo().zzxf();
        localZzcme.zzjlx = Build.MODEL;
        zzawo().zzxf();
        localZzcme.zzdb = Build.VERSION.RELEASE;
        localZzcme.zzjlz = Integer.valueOf((int)zzawo().zzayu());
        localZzcme.zzjly = zzawo().zzayv();
        localZzcme.zzjme = localZzcgh.getAppInstanceId();
        localZzcme.zziya = localZzcgh.zzaxd();
        localObject1 = zzaws().zzja(localZzcgh.getAppId());
        localZzcme.zzjlq = new zzcmg[((List)localObject1).size()];
        i = 0;
        while (i < ((List)localObject1).size())
        {
          localObject2 = new zzcmg();
          localZzcme.zzjlq[i] = localObject2;
          ((zzcmg)localObject2).name = ((zzclp)((List)localObject1).get(i)).mName;
          ((zzcmg)localObject2).zzjms = Long.valueOf(((zzclp)((List)localObject1).get(i)).zzjjm);
          zzawu().zza((zzcmg)localObject2, ((zzclp)((List)localObject1).get(i)).mValue);
          i += 1;
        }
      }
      localObject1 = paramZzcha.zzizt.zzayx();
      if ("_iap".equals(paramZzcha.name))
      {
        ((Bundle)localObject1).putLong("_c", 1L);
        zzawy().zzazi().log("Marking in-app purchase as real-time");
        ((Bundle)localObject1).putLong("_r", 1L);
      }
      ((Bundle)localObject1).putString("_o", paramZzcha.zziyf);
      if (zzawu().zzkj(localZzcme.zzcn))
      {
        zzawu().zza((Bundle)localObject1, "_dbg", Long.valueOf(1L));
        zzawu().zza((Bundle)localObject1, "_r", Long.valueOf(1L));
      }
      Object localObject2 = zzaws().zzae(paramString, paramZzcha.name);
      if (localObject2 == null)
      {
        localObject2 = new zzcgw(paramString, paramZzcha.name, 1L, 0L, paramZzcha.zzizu, 0L, null, null, null);
        zzaws().zza((zzcgw)localObject2);
        l1 = 0L;
      }
      for (;;)
      {
        paramZzcha = new zzcgv(this, paramZzcha.zziyf, paramString, paramZzcha.name, paramZzcha.zzizu, l1, (Bundle)localObject1);
        localObject1 = new zzcmb();
        localZzcme.zzjlp = new zzcmb[] { localObject1 };
        ((zzcmb)localObject1).zzjli = Long.valueOf(paramZzcha.zzfij);
        ((zzcmb)localObject1).name = paramZzcha.mName;
        ((zzcmb)localObject1).zzjlj = Long.valueOf(paramZzcha.zzizi);
        ((zzcmb)localObject1).zzjlh = new zzcmc[paramZzcha.zzizj.size()];
        localObject2 = paramZzcha.zzizj.iterator();
        i = 0;
        while (((Iterator)localObject2).hasNext())
        {
          Object localObject3 = (String)((Iterator)localObject2).next();
          zzcmc localZzcmc = new zzcmc();
          ((zzcmb)localObject1).zzjlh[i] = localZzcmc;
          localZzcmc.name = ((String)localObject3);
          localObject3 = paramZzcha.zzizj.get((String)localObject3);
          zzawu().zza(localZzcmc, localObject3);
          i += 1;
        }
        l1 = ((zzcgw)localObject2).zzizm;
        localObject2 = ((zzcgw)localObject2).zzbb(paramZzcha.zzizu).zzayw();
        zzaws().zza((zzcgw)localObject2);
      }
      localZzcme.zzjmi = zza(localZzcgh.getAppId(), localZzcme.zzjlq, localZzcme.zzjlp);
    }
    finally
    {
      zzaws().endTransaction();
    }
    localZzcme.zzjls = ((zzcmb)localObject1).zzjli;
    localZzcme.zzjlt = ((zzcmb)localObject1).zzjli;
    long l1 = localZzcgh.zzaxf();
    long l2;
    if (l1 != 0L)
    {
      paramZzcha = Long.valueOf(l1);
      localZzcme.zzjlv = paramZzcha;
      l2 = localZzcgh.zzaxe();
      if (l2 != 0L) {
        break label1295;
      }
    }
    for (;;)
    {
      if (l1 != 0L) {}
      for (paramZzcha = Long.valueOf(l1);; paramZzcha = null)
      {
        localZzcme.zzjlu = paramZzcha;
        localZzcgh.zzaxo();
        localZzcme.zzjmg = Integer.valueOf((int)localZzcgh.zzaxl());
        localZzcme.zzjmb = Long.valueOf(11910L);
        localZzcme.zzjlr = Long.valueOf(this.zzata.currentTimeMillis());
        localZzcme.zzjmh = Boolean.TRUE;
        localZzcgh.zzal(localZzcme.zzjls.longValue());
        localZzcgh.zzam(localZzcme.zzjlt.longValue());
        zzaws().zza(localZzcgh);
        zzaws().setTransactionSuccessful();
        zzaws().endTransaction();
        try
        {
          paramZzcha = new byte[localZzcmd.zzho()];
          localObject1 = zzfjk.zzo(paramZzcha, 0, paramZzcha.length);
          localZzcmd.zza((zzfjk)localObject1);
          ((zzfjk)localObject1).zzcwt();
          paramZzcha = zzawu().zzq(paramZzcha);
          return paramZzcha;
        }
        catch (IOException paramZzcha)
        {
          zzawy().zzazd().zze("Data loss. Failed to bundle and serialize. appId", zzchm.zzjk(paramString), paramZzcha);
          return null;
        }
        paramZzcha = null;
        break;
      }
      label1295:
      l1 = l2;
    }
  }
  
  public final zzcgd zzawk()
  {
    zza(this.zzjfr);
    return this.zzjfr;
  }
  
  public final zzcgk zzawl()
  {
    zza(this.zzjfq);
    return this.zzjfq;
  }
  
  public final zzcjn zzawm()
  {
    zza(this.zzjfm);
    return this.zzjfm;
  }
  
  public final zzchh zzawn()
  {
    zza(this.zzjfn);
    return this.zzjfn;
  }
  
  public final zzcgu zzawo()
  {
    zza(this.zzjfl);
    return this.zzjfl;
  }
  
  public final zzckg zzawp()
  {
    zza(this.zzjfk);
    return this.zzjfk;
  }
  
  public final zzckc zzawq()
  {
    zza(this.zzjfj);
    return this.zzjfj;
  }
  
  public final zzchi zzawr()
  {
    zza(this.zzjfh);
    return this.zzjfh;
  }
  
  public final zzcgo zzaws()
  {
    zza(this.zzjfg);
    return this.zzjfg;
  }
  
  public final zzchk zzawt()
  {
    zza(this.zzjff);
    return this.zzjff;
  }
  
  public final zzclq zzawu()
  {
    zza(this.zzjfe);
    return this.zzjfe;
  }
  
  public final zzcig zzawv()
  {
    zza(this.zzjfb);
    return this.zzjfb;
  }
  
  public final zzclf zzaww()
  {
    zza(this.zzjfa);
    return this.zzjfa;
  }
  
  public final zzcih zzawx()
  {
    zza(this.zzjez);
    return this.zzjez;
  }
  
  public final zzchm zzawy()
  {
    zza(this.zzjey);
    return this.zzjey;
  }
  
  public final zzchx zzawz()
  {
    zza(this.zzjex);
    return this.zzjex;
  }
  
  public final zzcgn zzaxa()
  {
    return this.zzjew;
  }
  
  @WorkerThread
  protected final boolean zzazv()
  {
    boolean bool2 = false;
    zzxf();
    zzawx().zzve();
    if ((this.zzjft == null) || (this.zzjfu == 0L) || ((this.zzjft != null) && (!this.zzjft.booleanValue()) && (Math.abs(this.zzata.elapsedRealtime() - this.zzjfu) > 1000L)))
    {
      this.zzjfu = this.zzata.elapsedRealtime();
      boolean bool1 = bool2;
      if (zzawu().zzeb("android.permission.INTERNET"))
      {
        bool1 = bool2;
        if (zzawu().zzeb("android.permission.ACCESS_NETWORK_STATE")) {
          if (!zzbhf.zzdb(this.mContext).zzamu())
          {
            bool1 = bool2;
            if (zzcid.zzbk(this.mContext))
            {
              bool1 = bool2;
              if (!zzcla.zzk(this.mContext, false)) {}
            }
          }
          else
          {
            bool1 = true;
          }
        }
      }
      this.zzjft = Boolean.valueOf(bool1);
      if (this.zzjft.booleanValue()) {
        this.zzjft = Boolean.valueOf(zzawu().zzkg(zzawn().getGmpAppId()));
      }
    }
    return this.zzjft.booleanValue();
  }
  
  public final zzchm zzazx()
  {
    if ((this.zzjey != null) && (this.zzjey.isInitialized())) {
      return this.zzjey;
    }
    return null;
  }
  
  final zzcih zzazy()
  {
    return this.zzjez;
  }
  
  public final AppMeasurement zzazz()
  {
    return this.zzjfc;
  }
  
  @WorkerThread
  final void zzb(zzcgl paramZzcgl, zzcgi paramZzcgi)
  {
    int i = 1;
    zzbq.checkNotNull(paramZzcgl);
    zzbq.zzgm(paramZzcgl.packageName);
    zzbq.checkNotNull(paramZzcgl.zziyf);
    zzbq.checkNotNull(paramZzcgl.zziyg);
    zzbq.zzgm(paramZzcgl.zziyg.name);
    zzawx().zzve();
    zzxf();
    if (TextUtils.isEmpty(paramZzcgi.zzixs)) {
      return;
    }
    if (!paramZzcgi.zzixx)
    {
      zzg(paramZzcgi);
      return;
    }
    paramZzcgl = new zzcgl(paramZzcgl);
    paramZzcgl.zziyi = false;
    zzaws().beginTransaction();
    for (;;)
    {
      try
      {
        Object localObject = zzaws().zzah(paramZzcgl.packageName, paramZzcgl.zziyg.name);
        if ((localObject != null) && (!((zzcgl)localObject).zziyf.equals(paramZzcgl.zziyf))) {
          zzawy().zzazf().zzd("Updating a conditional user property with different origin. name, origin, origin (from DB)", zzawt().zzjj(paramZzcgl.zziyg.name), paramZzcgl.zziyf, ((zzcgl)localObject).zziyf);
        }
        if ((localObject != null) && (((zzcgl)localObject).zziyi))
        {
          paramZzcgl.zziyf = ((zzcgl)localObject).zziyf;
          paramZzcgl.zziyh = ((zzcgl)localObject).zziyh;
          paramZzcgl.zziyl = ((zzcgl)localObject).zziyl;
          paramZzcgl.zziyj = ((zzcgl)localObject).zziyj;
          paramZzcgl.zziym = ((zzcgl)localObject).zziym;
          paramZzcgl.zziyi = ((zzcgl)localObject).zziyi;
          paramZzcgl.zziyg = new zzcln(paramZzcgl.zziyg.name, ((zzcgl)localObject).zziyg.zzjji, paramZzcgl.zziyg.getValue(), ((zzcgl)localObject).zziyg.zziyf);
          i = 0;
          if (paramZzcgl.zziyi)
          {
            localObject = paramZzcgl.zziyg;
            localObject = new zzclp(paramZzcgl.packageName, paramZzcgl.zziyf, ((zzcln)localObject).name, ((zzcln)localObject).zzjji, ((zzcln)localObject).getValue());
            if (!zzaws().zza((zzclp)localObject)) {
              break label534;
            }
            zzawy().zzazi().zzd("User property updated immediately", paramZzcgl.packageName, zzawt().zzjj(((zzclp)localObject).mName), ((zzclp)localObject).mValue);
            if ((i != 0) && (paramZzcgl.zziym != null)) {
              zzc(new zzcha(paramZzcgl.zziym, paramZzcgl.zziyh), paramZzcgi);
            }
          }
          if (!zzaws().zza(paramZzcgl)) {
            break label574;
          }
          zzawy().zzazi().zzd("Conditional property added", paramZzcgl.packageName, zzawt().zzjj(paramZzcgl.zziyg.name), paramZzcgl.zziyg.getValue());
          zzaws().setTransactionSuccessful();
        }
        else
        {
          if (!TextUtils.isEmpty(paramZzcgl.zziyj)) {
            break label618;
          }
          paramZzcgl.zziyg = new zzcln(paramZzcgl.zziyg.name, paramZzcgl.zziyh, paramZzcgl.zziyg.getValue(), paramZzcgl.zziyg.zziyf);
          paramZzcgl.zziyi = true;
          continue;
        }
        zzawy().zzazd().zzd("(2)Too many active user properties, ignoring", zzchm.zzjk(paramZzcgl.packageName), zzawt().zzjj(((zzclp)localObject).mName), ((zzclp)localObject).mValue);
      }
      finally
      {
        zzaws().endTransaction();
      }
      label534:
      continue;
      label574:
      zzawy().zzazd().zzd("Too many conditional properties, ignoring", zzchm.zzjk(paramZzcgl.packageName), zzawt().zzjj(paramZzcgl.zziyg.name), paramZzcgl.zziyg.getValue());
      continue;
      label618:
      i = 0;
    }
  }
  
  @WorkerThread
  final void zzb(zzcha paramZzcha, zzcgi paramZzcgi)
  {
    zzbq.checkNotNull(paramZzcgi);
    zzbq.zzgm(paramZzcgi.packageName);
    zzawx().zzve();
    zzxf();
    Object localObject2 = paramZzcgi.packageName;
    long l = paramZzcha.zzizu;
    zzawu();
    if (!zzclq.zzd(paramZzcha, paramZzcgi)) {
      return;
    }
    if (!paramZzcgi.zzixx)
    {
      zzg(paramZzcgi);
      return;
    }
    zzaws().beginTransaction();
    for (;;)
    {
      try
      {
        localObject1 = zzaws();
        zzbq.zzgm((String)localObject2);
        ((zzcjk)localObject1).zzve();
        ((zzcjl)localObject1).zzxf();
        if (l < 0L)
        {
          ((zzcjk)localObject1).zzawy().zzazf().zze("Invalid time querying timed out conditional properties", zzchm.zzjk((String)localObject2), Long.valueOf(l));
          localObject1 = Collections.emptyList();
          localObject1 = ((List)localObject1).iterator();
          if (!((Iterator)localObject1).hasNext()) {
            break;
          }
          localObject3 = (zzcgl)((Iterator)localObject1).next();
          if (localObject3 == null) {
            continue;
          }
          zzawy().zzazi().zzd("User property timed out", ((zzcgl)localObject3).packageName, zzawt().zzjj(((zzcgl)localObject3).zziyg.name), ((zzcgl)localObject3).zziyg.getValue());
          if (((zzcgl)localObject3).zziyk != null) {
            zzc(new zzcha(((zzcgl)localObject3).zziyk, l), paramZzcgi);
          }
          zzaws().zzai((String)localObject2, ((zzcgl)localObject3).zziyg.name);
          continue;
        }
      }
      finally
      {
        zzaws().endTransaction();
      }
      tmp272_269[0] = localObject2;
      String[] tmp277_272 = tmp272_269;
      tmp277_272[1] = String.valueOf(l);
      localObject1 = ((zzcgo)localObject1).zzc("active=0 and app_id=? and abs(? - creation_timestamp) > trigger_timeout", tmp277_272);
    }
    Object localObject1 = zzaws();
    zzbq.zzgm((String)localObject2);
    ((zzcjk)localObject1).zzve();
    ((zzcjl)localObject1).zzxf();
    if (l < 0L) {
      ((zzcjk)localObject1).zzawy().zzazf().zze("Invalid time querying expired conditional properties", zzchm.zzjk((String)localObject2), Long.valueOf(l));
    }
    Object localObject4;
    for (localObject1 = Collections.emptyList();; localObject1 = ((zzcgo)localObject1).zzc("active<>0 and app_id=? and abs(? - triggered_timestamp) > time_to_live", new String[] { localObject2, String.valueOf(l) }))
    {
      localObject3 = new ArrayList(((List)localObject1).size());
      localObject1 = ((List)localObject1).iterator();
      while (((Iterator)localObject1).hasNext())
      {
        localObject4 = (zzcgl)((Iterator)localObject1).next();
        if (localObject4 != null)
        {
          zzawy().zzazi().zzd("User property expired", ((zzcgl)localObject4).packageName, zzawt().zzjj(((zzcgl)localObject4).zziyg.name), ((zzcgl)localObject4).zziyg.getValue());
          zzaws().zzaf((String)localObject2, ((zzcgl)localObject4).zziyg.name);
          if (((zzcgl)localObject4).zziyo != null) {
            ((List)localObject3).add(((zzcgl)localObject4).zziyo);
          }
          zzaws().zzai((String)localObject2, ((zzcgl)localObject4).zziyg.name);
        }
      }
    }
    localObject1 = (ArrayList)localObject3;
    int j = ((ArrayList)localObject1).size();
    int i = 0;
    while (i < j)
    {
      localObject3 = ((ArrayList)localObject1).get(i);
      i += 1;
      zzc(new zzcha((zzcha)localObject3, l), paramZzcgi);
    }
    localObject1 = zzaws();
    Object localObject3 = paramZzcha.name;
    zzbq.zzgm((String)localObject2);
    zzbq.zzgm((String)localObject3);
    ((zzcjk)localObject1).zzve();
    ((zzcjl)localObject1).zzxf();
    if (l < 0L)
    {
      ((zzcjk)localObject1).zzawy().zzazf().zzd("Invalid time querying triggered conditional properties", zzchm.zzjk((String)localObject2), ((zzcjk)localObject1).zzawt().zzjh((String)localObject3), Long.valueOf(l));
      localObject1 = Collections.emptyList();
      localObject2 = new ArrayList(((List)localObject1).size());
      localObject1 = ((List)localObject1).iterator();
      label694:
      do
      {
        if (!((Iterator)localObject1).hasNext()) {
          break;
        }
        localObject3 = (zzcgl)((Iterator)localObject1).next();
      } while (localObject3 == null);
      localObject4 = ((zzcgl)localObject3).zziyg;
      localObject4 = new zzclp(((zzcgl)localObject3).packageName, ((zzcgl)localObject3).zziyf, ((zzcln)localObject4).name, l, ((zzcln)localObject4).getValue());
      if (!zzaws().zza((zzclp)localObject4)) {
        break label895;
      }
      zzawy().zzazi().zzd("User property triggered", ((zzcgl)localObject3).packageName, zzawt().zzjj(((zzclp)localObject4).mName), ((zzclp)localObject4).mValue);
    }
    for (;;)
    {
      if (((zzcgl)localObject3).zziym != null) {
        ((List)localObject2).add(((zzcgl)localObject3).zziym);
      }
      ((zzcgl)localObject3).zziyg = new zzcln((zzclp)localObject4);
      ((zzcgl)localObject3).zziyi = true;
      zzaws().zza((zzcgl)localObject3);
      break label694;
      localObject1 = ((zzcgo)localObject1).zzc("active=0 and app_id=? and trigger_event_name=? and abs(? - creation_timestamp) <= trigger_timeout", new String[] { localObject2, localObject3, String.valueOf(l) });
      break;
      label895:
      zzawy().zzazd().zzd("Too many active user properties, ignoring", zzchm.zzjk(((zzcgl)localObject3).packageName), zzawt().zzjj(((zzclp)localObject4).mName), ((zzclp)localObject4).mValue);
    }
    zzc(paramZzcha, paramZzcgi);
    paramZzcha = (ArrayList)localObject2;
    j = paramZzcha.size();
    i = 0;
    while (i < j)
    {
      localObject1 = paramZzcha.get(i);
      i += 1;
      zzc(new zzcha((zzcha)localObject1, l), paramZzcgi);
    }
    zzaws().setTransactionSuccessful();
    zzaws().endTransaction();
  }
  
  @WorkerThread
  final void zzb(zzcha paramZzcha, String paramString)
  {
    zzcgh localZzcgh = zzaws().zzjb(paramString);
    if ((localZzcgh == null) || (TextUtils.isEmpty(localZzcgh.zzvj())))
    {
      zzawy().zzazi().zzj("No app data available; dropping event", paramString);
      return;
    }
    try
    {
      String str = zzbhf.zzdb(this.mContext).getPackageInfo(paramString, 0).versionName;
      if ((localZzcgh.zzvj() != null) && (!localZzcgh.zzvj().equals(str)))
      {
        zzawy().zzazf().zzj("App version does not match; dropping event. appId", zzchm.zzjk(paramString));
        return;
      }
    }
    catch (PackageManager.NameNotFoundException localNameNotFoundException)
    {
      if (!"_ui".equals(paramZzcha.name)) {
        zzawy().zzazf().zzj("Could not find package. appId", zzchm.zzjk(paramString));
      }
      zzb(paramZzcha, new zzcgi(paramString, localZzcgh.getGmpAppId(), localZzcgh.zzvj(), localZzcgh.zzaxg(), localZzcgh.zzaxh(), localZzcgh.zzaxi(), localZzcgh.zzaxj(), null, localZzcgh.zzaxk(), false, localZzcgh.zzaxd(), localZzcgh.zzaxx(), 0L, 0, localZzcgh.zzaxy()));
    }
  }
  
  final void zzb(zzcjl paramZzcjl)
  {
    this.zzjfz += 1;
  }
  
  /* Error */
  @WorkerThread
  final void zzb(zzcln paramZzcln, zzcgi paramZzcgi)
  {
    // Byte code:
    //   0: iconst_0
    //   1: istore 4
    //   3: iconst_0
    //   4: istore_3
    //   5: aload_0
    //   6: invokevirtual 308	com/google/android/gms/internal/zzcim:zzawx	()Lcom/google/android/gms/internal/zzcih;
    //   9: invokevirtual 311	com/google/android/gms/internal/zzcjk:zzve	()V
    //   12: aload_0
    //   13: invokevirtual 915	com/google/android/gms/internal/zzcim:zzxf	()V
    //   16: aload_2
    //   17: getfield 1284	com/google/android/gms/internal/zzcgi:zzixs	Ljava/lang/String;
    //   20: invokestatic 403	android/text/TextUtils:isEmpty	(Ljava/lang/CharSequence;)Z
    //   23: ifeq +4 -> 27
    //   26: return
    //   27: aload_2
    //   28: getfield 1095	com/google/android/gms/internal/zzcgi:zzixx	Z
    //   31: ifne +9 -> 40
    //   34: aload_0
    //   35: aload_2
    //   36: invokespecial 1098	com/google/android/gms/internal/zzcim:zzg	(Lcom/google/android/gms/internal/zzcgi;)V
    //   39: return
    //   40: aload_0
    //   41: invokevirtual 426	com/google/android/gms/internal/zzcim:zzawu	()Lcom/google/android/gms/internal/zzclq;
    //   44: aload_1
    //   45: getfield 2154	com/google/android/gms/internal/zzcln:name	Ljava/lang/String;
    //   48: invokevirtual 2269	com/google/android/gms/internal/zzclq:zzkd	(Ljava/lang/String;)I
    //   51: istore 5
    //   53: iload 5
    //   55: ifeq +55 -> 110
    //   58: aload_0
    //   59: invokevirtual 426	com/google/android/gms/internal/zzcim:zzawu	()Lcom/google/android/gms/internal/zzclq;
    //   62: pop
    //   63: aload_1
    //   64: getfield 2154	com/google/android/gms/internal/zzcln:name	Ljava/lang/String;
    //   67: bipush 24
    //   69: iconst_1
    //   70: invokestatic 2272	com/google/android/gms/internal/zzclq:zza	(Ljava/lang/String;IZ)Ljava/lang/String;
    //   73: astore 7
    //   75: aload_1
    //   76: getfield 2154	com/google/android/gms/internal/zzcln:name	Ljava/lang/String;
    //   79: ifnull +11 -> 90
    //   82: aload_1
    //   83: getfield 2154	com/google/android/gms/internal/zzcln:name	Ljava/lang/String;
    //   86: invokevirtual 597	java/lang/String:length	()I
    //   89: istore_3
    //   90: aload_0
    //   91: invokevirtual 426	com/google/android/gms/internal/zzcim:zzawu	()Lcom/google/android/gms/internal/zzclq;
    //   94: aload_2
    //   95: getfield 1084	com/google/android/gms/internal/zzcgi:packageName	Ljava/lang/String;
    //   98: iload 5
    //   100: ldc_w 1117
    //   103: aload 7
    //   105: iload_3
    //   106: invokevirtual 673	com/google/android/gms/internal/zzclq:zza	(Ljava/lang/String;ILjava/lang/String;Ljava/lang/String;I)V
    //   109: return
    //   110: aload_0
    //   111: invokevirtual 426	com/google/android/gms/internal/zzcim:zzawu	()Lcom/google/android/gms/internal/zzclq;
    //   114: aload_1
    //   115: getfield 2154	com/google/android/gms/internal/zzcln:name	Ljava/lang/String;
    //   118: aload_1
    //   119: invokevirtual 2182	com/google/android/gms/internal/zzcln:getValue	()Ljava/lang/Object;
    //   122: invokevirtual 2276	com/google/android/gms/internal/zzclq:zzl	(Ljava/lang/String;Ljava/lang/Object;)I
    //   125: istore 5
    //   127: iload 5
    //   129: ifeq +77 -> 206
    //   132: aload_0
    //   133: invokevirtual 426	com/google/android/gms/internal/zzcim:zzawu	()Lcom/google/android/gms/internal/zzclq;
    //   136: pop
    //   137: aload_1
    //   138: getfield 2154	com/google/android/gms/internal/zzcln:name	Ljava/lang/String;
    //   141: bipush 24
    //   143: iconst_1
    //   144: invokestatic 2272	com/google/android/gms/internal/zzclq:zza	(Ljava/lang/String;IZ)Ljava/lang/String;
    //   147: astore 7
    //   149: aload_1
    //   150: invokevirtual 2182	com/google/android/gms/internal/zzcln:getValue	()Ljava/lang/Object;
    //   153: astore_1
    //   154: iload 4
    //   156: istore_3
    //   157: aload_1
    //   158: ifnull +28 -> 186
    //   161: aload_1
    //   162: instanceof 445
    //   165: ifne +13 -> 178
    //   168: iload 4
    //   170: istore_3
    //   171: aload_1
    //   172: instanceof 405
    //   175: ifeq +11 -> 186
    //   178: aload_1
    //   179: invokestatic 594	java/lang/String:valueOf	(Ljava/lang/Object;)Ljava/lang/String;
    //   182: invokevirtual 597	java/lang/String:length	()I
    //   185: istore_3
    //   186: aload_0
    //   187: invokevirtual 426	com/google/android/gms/internal/zzcim:zzawu	()Lcom/google/android/gms/internal/zzclq;
    //   190: aload_2
    //   191: getfield 1084	com/google/android/gms/internal/zzcgi:packageName	Ljava/lang/String;
    //   194: iload 5
    //   196: ldc_w 1117
    //   199: aload 7
    //   201: iload_3
    //   202: invokevirtual 673	com/google/android/gms/internal/zzclq:zza	(Ljava/lang/String;ILjava/lang/String;Ljava/lang/String;I)V
    //   205: return
    //   206: aload_0
    //   207: invokevirtual 426	com/google/android/gms/internal/zzcim:zzawu	()Lcom/google/android/gms/internal/zzclq;
    //   210: aload_1
    //   211: getfield 2154	com/google/android/gms/internal/zzcln:name	Ljava/lang/String;
    //   214: aload_1
    //   215: invokevirtual 2182	com/google/android/gms/internal/zzcln:getValue	()Ljava/lang/Object;
    //   218: invokevirtual 2280	com/google/android/gms/internal/zzclq:zzm	(Ljava/lang/String;Ljava/lang/Object;)Ljava/lang/Object;
    //   221: astore 7
    //   223: aload 7
    //   225: ifnull -199 -> 26
    //   228: new 610	com/google/android/gms/internal/zzclp
    //   231: dup
    //   232: aload_2
    //   233: getfield 1084	com/google/android/gms/internal/zzcgi:packageName	Ljava/lang/String;
    //   236: aload_1
    //   237: getfield 2183	com/google/android/gms/internal/zzcln:zziyf	Ljava/lang/String;
    //   240: aload_1
    //   241: getfield 2154	com/google/android/gms/internal/zzcln:name	Ljava/lang/String;
    //   244: aload_1
    //   245: getfield 2181	com/google/android/gms/internal/zzcln:zzjji	J
    //   248: aload 7
    //   250: invokespecial 651	com/google/android/gms/internal/zzclp:<init>	(Ljava/lang/String;Ljava/lang/String;Ljava/lang/String;JLjava/lang/Object;)V
    //   253: astore_1
    //   254: aload_0
    //   255: invokevirtual 293	com/google/android/gms/internal/zzcim:zzawy	()Lcom/google/android/gms/internal/zzchm;
    //   258: invokevirtual 711	com/google/android/gms/internal/zzchm:zzazi	()Lcom/google/android/gms/internal/zzcho;
    //   261: ldc_w 2282
    //   264: aload_0
    //   265: invokevirtual 660	com/google/android/gms/internal/zzcim:zzawt	()Lcom/google/android/gms/internal/zzchk;
    //   268: aload_1
    //   269: getfield 663	com/google/android/gms/internal/zzclp:mName	Ljava/lang/String;
    //   272: invokevirtual 666	com/google/android/gms/internal/zzchk:zzjj	(Ljava/lang/String;)Ljava/lang/String;
    //   275: aload 7
    //   277: invokevirtual 455	com/google/android/gms/internal/zzcho:zze	(Ljava/lang/String;Ljava/lang/Object;Ljava/lang/Object;)V
    //   280: aload_0
    //   281: invokevirtual 604	com/google/android/gms/internal/zzcim:zzaws	()Lcom/google/android/gms/internal/zzcgo;
    //   284: invokevirtual 1146	com/google/android/gms/internal/zzcgo:beginTransaction	()V
    //   287: aload_0
    //   288: aload_2
    //   289: invokespecial 1098	com/google/android/gms/internal/zzcim:zzg	(Lcom/google/android/gms/internal/zzcgi;)V
    //   292: aload_0
    //   293: invokevirtual 604	com/google/android/gms/internal/zzcim:zzaws	()Lcom/google/android/gms/internal/zzcgo;
    //   296: aload_1
    //   297: invokevirtual 654	com/google/android/gms/internal/zzcgo:zza	(Lcom/google/android/gms/internal/zzclp;)Z
    //   300: istore 6
    //   302: aload_0
    //   303: invokevirtual 604	com/google/android/gms/internal/zzcim:zzaws	()Lcom/google/android/gms/internal/zzcgo;
    //   306: invokevirtual 1153	com/google/android/gms/internal/zzcgo:setTransactionSuccessful	()V
    //   309: iload 6
    //   311: ifeq +39 -> 350
    //   314: aload_0
    //   315: invokevirtual 293	com/google/android/gms/internal/zzcim:zzawy	()Lcom/google/android/gms/internal/zzchm;
    //   318: invokevirtual 711	com/google/android/gms/internal/zzchm:zzazi	()Lcom/google/android/gms/internal/zzcho;
    //   321: ldc_w 2284
    //   324: aload_0
    //   325: invokevirtual 660	com/google/android/gms/internal/zzcim:zzawt	()Lcom/google/android/gms/internal/zzchk;
    //   328: aload_1
    //   329: getfield 663	com/google/android/gms/internal/zzclp:mName	Ljava/lang/String;
    //   332: invokevirtual 666	com/google/android/gms/internal/zzchk:zzjj	(Ljava/lang/String;)Ljava/lang/String;
    //   335: aload_1
    //   336: getfield 614	com/google/android/gms/internal/zzclp:mValue	Ljava/lang/Object;
    //   339: invokevirtual 455	com/google/android/gms/internal/zzcho:zze	(Ljava/lang/String;Ljava/lang/Object;Ljava/lang/Object;)V
    //   342: aload_0
    //   343: invokevirtual 604	com/google/android/gms/internal/zzcim:zzaws	()Lcom/google/android/gms/internal/zzcgo;
    //   346: invokevirtual 1156	com/google/android/gms/internal/zzcgo:endTransaction	()V
    //   349: return
    //   350: aload_0
    //   351: invokevirtual 293	com/google/android/gms/internal/zzcim:zzawy	()Lcom/google/android/gms/internal/zzchm;
    //   354: invokevirtual 320	com/google/android/gms/internal/zzchm:zzazd	()Lcom/google/android/gms/internal/zzcho;
    //   357: ldc_w 2286
    //   360: aload_0
    //   361: invokevirtual 660	com/google/android/gms/internal/zzcim:zzawt	()Lcom/google/android/gms/internal/zzchk;
    //   364: aload_1
    //   365: getfield 663	com/google/android/gms/internal/zzclp:mName	Ljava/lang/String;
    //   368: invokevirtual 666	com/google/android/gms/internal/zzchk:zzjj	(Ljava/lang/String;)Ljava/lang/String;
    //   371: aload_1
    //   372: getfield 614	com/google/android/gms/internal/zzclp:mValue	Ljava/lang/Object;
    //   375: invokevirtual 455	com/google/android/gms/internal/zzcho:zze	(Ljava/lang/String;Ljava/lang/Object;Ljava/lang/Object;)V
    //   378: aload_0
    //   379: invokevirtual 426	com/google/android/gms/internal/zzcim:zzawu	()Lcom/google/android/gms/internal/zzclq;
    //   382: aload_2
    //   383: getfield 1084	com/google/android/gms/internal/zzcgi:packageName	Ljava/lang/String;
    //   386: bipush 9
    //   388: aconst_null
    //   389: aconst_null
    //   390: iconst_0
    //   391: invokevirtual 673	com/google/android/gms/internal/zzclq:zza	(Ljava/lang/String;ILjava/lang/String;Ljava/lang/String;I)V
    //   394: goto -52 -> 342
    //   397: astore_1
    //   398: aload_0
    //   399: invokevirtual 604	com/google/android/gms/internal/zzcim:zzaws	()Lcom/google/android/gms/internal/zzcgo;
    //   402: invokevirtual 1156	com/google/android/gms/internal/zzcgo:endTransaction	()V
    //   405: aload_1
    //   406: athrow
    // Local variable table:
    //   start	length	slot	name	signature
    //   0	407	0	this	zzcim
    //   0	407	1	paramZzcln	zzcln
    //   0	407	2	paramZzcgi	zzcgi
    //   4	198	3	i	int
    //   1	168	4	j	int
    //   51	144	5	k	int
    //   300	10	6	bool	boolean
    //   73	203	7	localObject	Object
    // Exception table:
    //   from	to	target	type
    //   287	309	397	finally
    //   314	342	397	finally
    //   350	394	397	finally
  }
  
  @WorkerThread
  final void zzb(String paramString, int paramInt, Throwable paramThrowable, byte[] paramArrayOfByte, Map<String, List<String>> paramMap)
  {
    int j = 1;
    zzawx().zzve();
    zzxf();
    zzbq.zzgm(paramString);
    byte[] arrayOfByte = paramArrayOfByte;
    if (paramArrayOfByte == null) {}
    for (;;)
    {
      try
      {
        arrayOfByte = new byte[0];
        zzawy().zzazj().zzj("onConfigFetched. Response size", Integer.valueOf(arrayOfByte.length));
        zzaws().beginTransaction();
        try
        {
          paramArrayOfByte = zzaws().zzjb(paramString);
          if ((paramInt == 200) || (paramInt == 204)) {
            break label543;
          }
          if (paramInt == 304)
          {
            break label543;
            if (paramArrayOfByte == null)
            {
              zzawy().zzazf().zzj("App does not exist in onConfigFetched. appId", zzchm.zzjk(paramString));
              zzaws().setTransactionSuccessful();
              zzaws().endTransaction();
            }
          }
          else
          {
            i = 0;
            continue;
          }
          if ((i == 0) && (paramInt != 404)) {
            break label416;
          }
          if (paramMap != null)
          {
            paramThrowable = (List)paramMap.get("Last-Modified");
            if ((paramThrowable != null) && (paramThrowable.size() > 0))
            {
              paramThrowable = (String)paramThrowable.get(0);
              break label553;
              if (zzawv().zzjs(paramString) != null) {
                continue;
              }
              bool = zzawv().zzb(paramString, null, null);
              if (bool) {
                continue;
              }
              zzaws().endTransaction();
            }
          }
          else
          {
            paramThrowable = null;
            continue;
          }
          paramThrowable = null;
          break label553;
          boolean bool = zzawv().zzb(paramString, arrayOfByte, paramThrowable);
          if (!bool)
          {
            zzaws().endTransaction();
            return;
          }
          paramArrayOfByte.zzar(this.zzata.currentTimeMillis());
          zzaws().zza(paramArrayOfByte);
          if (paramInt == 404)
          {
            zzawy().zzazg().zzj("Config not found. Using empty config. appId", paramString);
            if ((!zzbab().zzzs()) || (!zzbai())) {
              break label409;
            }
            zzbah();
            continue;
            paramString = finally;
          }
        }
        finally
        {
          zzaws().endTransaction();
        }
        zzawy().zzazj().zze("Successfully fetched config. Got network response. code, size", Integer.valueOf(paramInt), Integer.valueOf(arrayOfByte.length));
      }
      finally
      {
        this.zzjgd = false;
        zzban();
      }
      continue;
      label409:
      zzbaj();
      continue;
      label416:
      paramArrayOfByte.zzas(this.zzata.currentTimeMillis());
      zzaws().zza(paramArrayOfByte);
      zzawy().zzazj().zze("Fetching config failed. code, error", Integer.valueOf(paramInt), paramThrowable);
      zzawv().zzju(paramString);
      zzawz().zzjcs.set(this.zzata.currentTimeMillis());
      int i = j;
      if (paramInt != 503) {
        if (paramInt != 429) {
          break label537;
        }
      }
      label537:
      for (i = j;; i = 0)
      {
        if (i != 0) {
          zzawz().zzjct.set(this.zzata.currentTimeMillis());
        }
        zzbaj();
        break;
      }
      label543:
      if (paramThrowable == null)
      {
        i = 1;
        continue;
        label553:
        if (paramInt != 404) {
          if (paramInt != 304) {}
        }
      }
    }
  }
  
  public final FirebaseAnalytics zzbaa()
  {
    return this.zzjfd;
  }
  
  public final zzchq zzbab()
  {
    zza(this.zzjfi);
    return this.zzjfi;
  }
  
  final long zzbaf()
  {
    Long localLong = Long.valueOf(zzawz().zzjcw.get());
    if (localLong.longValue() == 0L) {
      return this.zzjgg;
    }
    return Math.min(this.zzjgg, localLong.longValue());
  }
  
  @WorkerThread
  public final void zzbah()
  {
    zzawx().zzve();
    zzxf();
    this.zzjgf = true;
    int i;
    int j;
    for (;;)
    {
      long l1;
      Object localObject4;
      try
      {
        Object localObject1 = zzawp().zzbas();
        if (localObject1 == null)
        {
          zzawy().zzazf().log("Upload data called on the client side before use of service was decided");
          return;
        }
        if (((Boolean)localObject1).booleanValue())
        {
          zzawy().zzazd().log("Upload called in the client side when service should be used");
          return;
        }
        if (this.zzjgc > 0L)
        {
          zzbaj();
          return;
        }
        zzawx().zzve();
        if (this.zzjfx != null)
        {
          i = 1;
          if (i != 0) {
            zzawy().zzazj().log("Uploading requested multiple times");
          }
        }
        else
        {
          i = 0;
          continue;
        }
        if (!zzbab().zzzs())
        {
          zzawy().zzazj().log("Network not connected, ignoring upload request");
          zzbaj();
          return;
        }
        l1 = this.zzata.currentTimeMillis();
        zzg(null, l1 - zzcgn.zzayc());
        long l2 = zzawz().zzjcr.get();
        if (l2 != 0L) {
          zzawy().zzazi().zzj("Uploading events. Elapsed time since last upload attempt (ms)", Long.valueOf(Math.abs(l1 - l2)));
        }
        str = zzaws().zzayf();
        if (TextUtils.isEmpty(str)) {
          break label953;
        }
        if (this.zzjgb == -1L) {
          this.zzjgb = zzaws().zzaym();
        }
        i = this.zzjew.zzb(str, zzchc.zzjaj);
        j = Math.max(0, this.zzjew.zzb(str, zzchc.zzjak));
        localObject4 = zzaws().zzl(str, i, j);
        zzcmd localZzcmd;
        label533:
        byte[] arrayOfByte;
        if (!((List)localObject4).isEmpty())
        {
          localObject1 = ((List)localObject4).iterator();
          if (!((Iterator)localObject1).hasNext()) {
            break label1020;
          }
          localObject5 = (zzcme)((Pair)((Iterator)localObject1).next()).first;
          if (TextUtils.isEmpty(((zzcme)localObject5).zzjmc)) {
            continue;
          }
          localObject1 = ((zzcme)localObject5).zzjmc;
          break label1023;
          if (i >= ((List)localObject4).size()) {
            break label1013;
          }
          localObject5 = (zzcme)((Pair)((List)localObject4).get(i)).first;
          if ((TextUtils.isEmpty(((zzcme)localObject5).zzjmc)) || (((zzcme)localObject5).zzjmc.equals(localObject1))) {
            break label1045;
          }
          localObject1 = ((List)localObject4).subList(0, i);
          localZzcmd = new zzcmd();
          localZzcmd.zzjlm = new zzcme[((List)localObject1).size()];
          localObject4 = new ArrayList(((List)localObject1).size());
          if ((!zzcgn.zzaye()) || (!this.zzjew.zziz(str))) {
            break label1052;
          }
          i = 1;
          break;
          if (j < localZzcmd.zzjlm.length)
          {
            localZzcmd.zzjlm[j] = ((zzcme)((Pair)((List)localObject1).get(j)).first);
            ((List)localObject4).add((Long)((Pair)((List)localObject1).get(j)).second);
            localZzcmd.zzjlm[j].zzjmb = Long.valueOf(11910L);
            localZzcmd.zzjlm[j].zzjlr = Long.valueOf(l1);
            localZzcmd.zzjlm[j].zzjmh = Boolean.valueOf(false);
            if (i != 0) {
              break label1038;
            }
            localZzcmd.zzjlm[j].zzjmo = null;
            break label1038;
          }
          if (!zzawy().zzae(2)) {
            break label1007;
          }
          localObject1 = zzawt().zza(localZzcmd);
          arrayOfByte = zzawu().zzb(localZzcmd);
          localObject5 = (String)zzchc.zzjat.get();
        }
        try
        {
          URL localURL = new URL((String)localObject5);
          if (((List)localObject4).isEmpty()) {
            continue;
          }
          bool = true;
          zzbq.checkArgument(bool);
          if (this.zzjfx == null) {
            continue;
          }
          zzawy().zzazd().log("Set uploading progress before finishing the previous upload");
          zzawz().zzjcs.set(l1);
          localObject4 = "?";
          if (localZzcmd.zzjlm.length > 0) {
            localObject4 = localZzcmd.zzjlm[0].zzcn;
          }
          zzawy().zzazj().zzd("Uploading data. app, uncompressed size, data", localObject4, Integer.valueOf(arrayOfByte.length), localObject1);
          this.zzjge = true;
          localObject1 = zzbab();
          localObject4 = new zzcip(this);
          ((zzcjk)localObject1).zzve();
          ((zzcjl)localObject1).zzxf();
          zzbq.checkNotNull(localURL);
          zzbq.checkNotNull(arrayOfByte);
          zzbq.checkNotNull(localObject4);
          ((zzcjk)localObject1).zzawx().zzh(new zzchu((zzchq)localObject1, str, localURL, arrayOfByte, null, (zzchs)localObject4));
        }
        catch (MalformedURLException localMalformedURLException)
        {
          boolean bool;
          zzawy().zzazd().zze("Failed to parse upload URL. Not uploading. appId", zzchm.zzjk(str), localObject5);
          continue;
        }
        return;
      }
      finally
      {
        String str;
        Object localObject5;
        this.zzjgf = false;
        zzban();
      }
      bool = false;
      continue;
      this.zzjfx = new ArrayList((Collection)localObject4);
      continue;
      label953:
      this.zzjgb = -1L;
      Object localObject3 = zzaws().zzba(l1 - zzcgn.zzayc());
      if (!TextUtils.isEmpty((CharSequence)localObject3))
      {
        localObject3 = zzaws().zzjb((String)localObject3);
        if (localObject3 != null)
        {
          zzb((zzcgh)localObject3);
          continue;
          label1007:
          localObject3 = null;
          continue;
          label1013:
          label1020:
          label1023:
          do
          {
            localObject3 = localObject4;
            break;
            localObject3 = null;
          } while (localObject3 == null);
          i = 0;
        }
      }
    }
    for (;;)
    {
      j = 0;
      break label533;
      label1038:
      j += 1;
      break label533;
      label1045:
      i += 1;
      break;
      label1052:
      i = 0;
    }
  }
  
  final void zzbak()
  {
    this.zzjga += 1;
  }
  
  @WorkerThread
  final void zzbal()
  {
    zzawx().zzve();
    zzxf();
    int i;
    int j;
    if (!this.zzjfs)
    {
      zzawy().zzazh().log("This instance being marked as an uploader");
      zzawx().zzve();
      zzxf();
      if ((zzbam()) && (zzbae()))
      {
        i = zza(this.zzjfw);
        j = zzawn().zzaza();
        zzawx().zzve();
        if (i <= j) {
          break label116;
        }
        zzawy().zzazd().zze("Panic: can't downgrade version. Previous, current version", Integer.valueOf(i), Integer.valueOf(j));
      }
    }
    for (;;)
    {
      this.zzjfs = true;
      zzbaj();
      return;
      label116:
      if (i < j) {
        if (zza(j, this.zzjfw)) {
          zzawy().zzazj().zze("Storage version upgraded. Previous, current version", Integer.valueOf(i), Integer.valueOf(j));
        } else {
          zzawy().zzazd().zze("Storage version upgrade failed. Previous, current version", Integer.valueOf(i), Integer.valueOf(j));
        }
      }
    }
  }
  
  public final void zzbo(boolean paramBoolean)
  {
    zzbaj();
  }
  
  /* Error */
  @WorkerThread
  final void zzc(zzcgl paramZzcgl, zzcgi paramZzcgi)
  {
    // Byte code:
    //   0: aload_1
    //   1: invokestatic 94	com/google/android/gms/common/internal/zzbq:checkNotNull	(Ljava/lang/Object;)Ljava/lang/Object;
    //   4: pop
    //   5: aload_1
    //   6: getfield 2146	com/google/android/gms/internal/zzcgl:packageName	Ljava/lang/String;
    //   9: invokestatic 627	com/google/android/gms/common/internal/zzbq:zzgm	(Ljava/lang/String;)Ljava/lang/String;
    //   12: pop
    //   13: aload_1
    //   14: getfield 2151	com/google/android/gms/internal/zzcgl:zziyg	Lcom/google/android/gms/internal/zzcln;
    //   17: invokestatic 94	com/google/android/gms/common/internal/zzbq:checkNotNull	(Ljava/lang/Object;)Ljava/lang/Object;
    //   20: pop
    //   21: aload_1
    //   22: getfield 2151	com/google/android/gms/internal/zzcgl:zziyg	Lcom/google/android/gms/internal/zzcln;
    //   25: getfield 2154	com/google/android/gms/internal/zzcln:name	Ljava/lang/String;
    //   28: invokestatic 627	com/google/android/gms/common/internal/zzbq:zzgm	(Ljava/lang/String;)Ljava/lang/String;
    //   31: pop
    //   32: aload_0
    //   33: invokevirtual 308	com/google/android/gms/internal/zzcim:zzawx	()Lcom/google/android/gms/internal/zzcih;
    //   36: invokevirtual 311	com/google/android/gms/internal/zzcjk:zzve	()V
    //   39: aload_0
    //   40: invokevirtual 915	com/google/android/gms/internal/zzcim:zzxf	()V
    //   43: aload_2
    //   44: getfield 1284	com/google/android/gms/internal/zzcgi:zzixs	Ljava/lang/String;
    //   47: invokestatic 403	android/text/TextUtils:isEmpty	(Ljava/lang/CharSequence;)Z
    //   50: ifeq +4 -> 54
    //   53: return
    //   54: aload_2
    //   55: getfield 1095	com/google/android/gms/internal/zzcgi:zzixx	Z
    //   58: ifne +9 -> 67
    //   61: aload_0
    //   62: aload_2
    //   63: invokespecial 1098	com/google/android/gms/internal/zzcim:zzg	(Lcom/google/android/gms/internal/zzcgi;)V
    //   66: return
    //   67: aload_0
    //   68: invokevirtual 604	com/google/android/gms/internal/zzcim:zzaws	()Lcom/google/android/gms/internal/zzcgo;
    //   71: invokevirtual 1146	com/google/android/gms/internal/zzcgo:beginTransaction	()V
    //   74: aload_0
    //   75: aload_2
    //   76: invokespecial 1098	com/google/android/gms/internal/zzcim:zzg	(Lcom/google/android/gms/internal/zzcgi;)V
    //   79: aload_0
    //   80: invokevirtual 604	com/google/android/gms/internal/zzcim:zzaws	()Lcom/google/android/gms/internal/zzcgo;
    //   83: aload_1
    //   84: getfield 2146	com/google/android/gms/internal/zzcgl:packageName	Ljava/lang/String;
    //   87: aload_1
    //   88: getfield 2151	com/google/android/gms/internal/zzcgl:zziyg	Lcom/google/android/gms/internal/zzcln;
    //   91: getfield 2154	com/google/android/gms/internal/zzcln:name	Ljava/lang/String;
    //   94: invokevirtual 2163	com/google/android/gms/internal/zzcgo:zzah	(Ljava/lang/String;Ljava/lang/String;)Lcom/google/android/gms/internal/zzcgl;
    //   97: astore 4
    //   99: aload 4
    //   101: ifnull +158 -> 259
    //   104: aload_0
    //   105: invokevirtual 293	com/google/android/gms/internal/zzcim:zzawy	()Lcom/google/android/gms/internal/zzchm;
    //   108: invokevirtual 711	com/google/android/gms/internal/zzchm:zzazi	()Lcom/google/android/gms/internal/zzcho;
    //   111: ldc_w 2401
    //   114: aload_1
    //   115: getfield 2146	com/google/android/gms/internal/zzcgl:packageName	Ljava/lang/String;
    //   118: aload_0
    //   119: invokevirtual 660	com/google/android/gms/internal/zzcim:zzawt	()Lcom/google/android/gms/internal/zzchk;
    //   122: aload_1
    //   123: getfield 2151	com/google/android/gms/internal/zzcgl:zziyg	Lcom/google/android/gms/internal/zzcln;
    //   126: getfield 2154	com/google/android/gms/internal/zzcln:name	Ljava/lang/String;
    //   129: invokevirtual 666	com/google/android/gms/internal/zzchk:zzjj	(Ljava/lang/String;)Ljava/lang/String;
    //   132: invokevirtual 455	com/google/android/gms/internal/zzcho:zze	(Ljava/lang/String;Ljava/lang/Object;Ljava/lang/Object;)V
    //   135: aload_0
    //   136: invokevirtual 604	com/google/android/gms/internal/zzcim:zzaws	()Lcom/google/android/gms/internal/zzcgo;
    //   139: aload_1
    //   140: getfield 2146	com/google/android/gms/internal/zzcgl:packageName	Ljava/lang/String;
    //   143: aload_1
    //   144: getfield 2151	com/google/android/gms/internal/zzcgl:zziyg	Lcom/google/android/gms/internal/zzcln;
    //   147: getfield 2154	com/google/android/gms/internal/zzcln:name	Ljava/lang/String;
    //   150: invokevirtual 2218	com/google/android/gms/internal/zzcgo:zzai	(Ljava/lang/String;Ljava/lang/String;)I
    //   153: pop
    //   154: aload 4
    //   156: getfield 2160	com/google/android/gms/internal/zzcgl:zziyi	Z
    //   159: ifeq +21 -> 180
    //   162: aload_0
    //   163: invokevirtual 604	com/google/android/gms/internal/zzcim:zzaws	()Lcom/google/android/gms/internal/zzcgo;
    //   166: aload_1
    //   167: getfield 2146	com/google/android/gms/internal/zzcgl:packageName	Ljava/lang/String;
    //   170: aload_1
    //   171: getfield 2151	com/google/android/gms/internal/zzcgl:zziyg	Lcom/google/android/gms/internal/zzcln;
    //   174: getfield 2154	com/google/android/gms/internal/zzcln:name	Ljava/lang/String;
    //   177: invokevirtual 2232	com/google/android/gms/internal/zzcgo:zzaf	(Ljava/lang/String;Ljava/lang/String;)V
    //   180: aload_1
    //   181: getfield 2235	com/google/android/gms/internal/zzcgl:zziyo	Lcom/google/android/gms/internal/zzcha;
    //   184: ifnull +60 -> 244
    //   187: aconst_null
    //   188: astore_3
    //   189: aload_1
    //   190: getfield 2235	com/google/android/gms/internal/zzcgl:zziyo	Lcom/google/android/gms/internal/zzcha;
    //   193: getfield 534	com/google/android/gms/internal/zzcha:zzizt	Lcom/google/android/gms/internal/zzcgx;
    //   196: ifnull +14 -> 210
    //   199: aload_1
    //   200: getfield 2235	com/google/android/gms/internal/zzcgl:zziyo	Lcom/google/android/gms/internal/zzcha;
    //   203: getfield 534	com/google/android/gms/internal/zzcha:zzizt	Lcom/google/android/gms/internal/zzcgx;
    //   206: invokevirtual 1195	com/google/android/gms/internal/zzcgx:zzayx	()Landroid/os/Bundle;
    //   209: astore_3
    //   210: aload_0
    //   211: aload_0
    //   212: invokevirtual 426	com/google/android/gms/internal/zzcim:zzawu	()Lcom/google/android/gms/internal/zzclq;
    //   215: aload_1
    //   216: getfield 2235	com/google/android/gms/internal/zzcgl:zziyo	Lcom/google/android/gms/internal/zzcha;
    //   219: getfield 544	com/google/android/gms/internal/zzcha:name	Ljava/lang/String;
    //   222: aload_3
    //   223: aload 4
    //   225: getfield 2147	com/google/android/gms/internal/zzcgl:zziyf	Ljava/lang/String;
    //   228: aload_1
    //   229: getfield 2235	com/google/android/gms/internal/zzcgl:zziyo	Lcom/google/android/gms/internal/zzcha;
    //   232: getfield 1215	com/google/android/gms/internal/zzcha:zzizu	J
    //   235: iconst_1
    //   236: iconst_0
    //   237: invokevirtual 2404	com/google/android/gms/internal/zzclq:zza	(Ljava/lang/String;Landroid/os/Bundle;Ljava/lang/String;JZZ)Lcom/google/android/gms/internal/zzcha;
    //   240: aload_2
    //   241: invokespecial 2193	com/google/android/gms/internal/zzcim:zzc	(Lcom/google/android/gms/internal/zzcha;Lcom/google/android/gms/internal/zzcgi;)V
    //   244: aload_0
    //   245: invokevirtual 604	com/google/android/gms/internal/zzcim:zzaws	()Lcom/google/android/gms/internal/zzcgo;
    //   248: invokevirtual 1153	com/google/android/gms/internal/zzcgo:setTransactionSuccessful	()V
    //   251: aload_0
    //   252: invokevirtual 604	com/google/android/gms/internal/zzcim:zzaws	()Lcom/google/android/gms/internal/zzcgo;
    //   255: invokevirtual 1156	com/google/android/gms/internal/zzcgo:endTransaction	()V
    //   258: return
    //   259: aload_0
    //   260: invokevirtual 293	com/google/android/gms/internal/zzcim:zzawy	()Lcom/google/android/gms/internal/zzchm;
    //   263: invokevirtual 296	com/google/android/gms/internal/zzchm:zzazf	()Lcom/google/android/gms/internal/zzcho;
    //   266: ldc_w 2406
    //   269: aload_1
    //   270: getfield 2146	com/google/android/gms/internal/zzcgl:packageName	Ljava/lang/String;
    //   273: invokestatic 441	com/google/android/gms/internal/zzchm:zzjk	(Ljava/lang/String;)Ljava/lang/Object;
    //   276: aload_0
    //   277: invokevirtual 660	com/google/android/gms/internal/zzcim:zzawt	()Lcom/google/android/gms/internal/zzchk;
    //   280: aload_1
    //   281: getfield 2151	com/google/android/gms/internal/zzcgl:zziyg	Lcom/google/android/gms/internal/zzcln;
    //   284: getfield 2154	com/google/android/gms/internal/zzcln:name	Ljava/lang/String;
    //   287: invokevirtual 666	com/google/android/gms/internal/zzchk:zzjj	(Ljava/lang/String;)Ljava/lang/String;
    //   290: invokevirtual 455	com/google/android/gms/internal/zzcho:zze	(Ljava/lang/String;Ljava/lang/Object;Ljava/lang/Object;)V
    //   293: goto -49 -> 244
    //   296: astore_1
    //   297: aload_0
    //   298: invokevirtual 604	com/google/android/gms/internal/zzcim:zzaws	()Lcom/google/android/gms/internal/zzcgo;
    //   301: invokevirtual 1156	com/google/android/gms/internal/zzcgo:endTransaction	()V
    //   304: aload_1
    //   305: athrow
    // Local variable table:
    //   start	length	slot	name	signature
    //   0	306	0	this	zzcim
    //   0	306	1	paramZzcgl	zzcgl
    //   0	306	2	paramZzcgi	zzcgi
    //   188	35	3	localBundle	Bundle
    //   97	127	4	localZzcgl	zzcgl
    // Exception table:
    //   from	to	target	type
    //   74	99	296	finally
    //   104	180	296	finally
    //   180	187	296	finally
    //   189	210	296	finally
    //   210	244	296	finally
    //   244	251	296	finally
    //   259	293	296	finally
  }
  
  @WorkerThread
  final void zzc(zzcln paramZzcln, zzcgi paramZzcgi)
  {
    zzawx().zzve();
    zzxf();
    if (TextUtils.isEmpty(paramZzcgi.zzixs)) {
      return;
    }
    if (!paramZzcgi.zzixx)
    {
      zzg(paramZzcgi);
      return;
    }
    zzawy().zzazi().zzj("Removing user property", zzawt().zzjj(paramZzcln.name));
    zzaws().beginTransaction();
    try
    {
      zzg(paramZzcgi);
      zzaws().zzaf(paramZzcgi.packageName, paramZzcln.name);
      zzaws().setTransactionSuccessful();
      zzawy().zzazi().zzj("User property removed", zzawt().zzjj(paramZzcln.name));
      return;
    }
    finally
    {
      zzaws().endTransaction();
    }
  }
  
  final void zzd(zzcgi paramZzcgi)
  {
    zzaws().zzjb(paramZzcgi.packageName);
    localZzcgo = zzaws();
    str = paramZzcgi.packageName;
    zzbq.zzgm(str);
    localZzcgo.zzve();
    localZzcgo.zzxf();
    try
    {
      SQLiteDatabase localSQLiteDatabase = localZzcgo.getWritableDatabase();
      String[] arrayOfString = new String[1];
      arrayOfString[0] = str;
      int i = localSQLiteDatabase.delete("apps", "app_id=?", arrayOfString);
      int j = localSQLiteDatabase.delete("events", "app_id=?", arrayOfString);
      int k = localSQLiteDatabase.delete("user_attributes", "app_id=?", arrayOfString);
      int m = localSQLiteDatabase.delete("conditional_properties", "app_id=?", arrayOfString);
      int n = localSQLiteDatabase.delete("raw_events", "app_id=?", arrayOfString);
      int i1 = localSQLiteDatabase.delete("raw_events_metadata", "app_id=?", arrayOfString);
      int i2 = localSQLiteDatabase.delete("queue", "app_id=?", arrayOfString);
      i = localSQLiteDatabase.delete("audience_filter_values", "app_id=?", arrayOfString) + (i + 0 + j + k + m + n + i1 + i2);
      if (i > 0) {
        localZzcgo.zzawy().zzazj().zze("Reset analytics data. app, records", str, Integer.valueOf(i));
      }
    }
    catch (SQLiteException localSQLiteException)
    {
      for (;;)
      {
        localZzcgo.zzawy().zzazd().zze("Error resetting analytics data. appId, error", zzchm.zzjk(str), localSQLiteException);
      }
    }
    zzf(zza(this.mContext, paramZzcgi.packageName, paramZzcgi.zzixs, paramZzcgi.zzixx, paramZzcgi.zziye));
  }
  
  @WorkerThread
  final void zzd(zzcgl paramZzcgl)
  {
    zzcgi localZzcgi = zzjw(paramZzcgl.packageName);
    if (localZzcgi != null) {
      zzb(paramZzcgl, localZzcgi);
    }
  }
  
  final void zze(zzcgi paramZzcgi)
  {
    zzawx().zzve();
    zzxf();
    zzbq.zzgm(paramZzcgi.packageName);
    zzg(paramZzcgi);
  }
  
  @WorkerThread
  final void zze(zzcgl paramZzcgl)
  {
    zzcgi localZzcgi = zzjw(paramZzcgl.packageName);
    if (localZzcgi != null) {
      zzc(paramZzcgl, localZzcgi);
    }
  }
  
  @WorkerThread
  public final void zzf(zzcgi paramZzcgi)
  {
    zzawx().zzve();
    zzxf();
    zzbq.checkNotNull(paramZzcgi);
    zzbq.zzgm(paramZzcgi.packageName);
    if (TextUtils.isEmpty(paramZzcgi.zzixs)) {
      return;
    }
    Object localObject1 = zzaws().zzjb(paramZzcgi.packageName);
    if ((localObject1 != null) && (TextUtils.isEmpty(((zzcgh)localObject1).getGmpAppId())) && (!TextUtils.isEmpty(paramZzcgi.zzixs)))
    {
      ((zzcgh)localObject1).zzar(0L);
      zzaws().zza((zzcgh)localObject1);
      zzawv().zzjv(paramZzcgi.packageName);
    }
    if (!paramZzcgi.zzixx)
    {
      zzg(paramZzcgi);
      return;
    }
    long l2 = paramZzcgi.zziyc;
    long l1 = l2;
    if (l2 == 0L) {
      l1 = this.zzata.currentTimeMillis();
    }
    int i = paramZzcgi.zziyd;
    Object localObject2;
    if ((i != 0) && (i != 1))
    {
      zzawy().zzazf().zze("Incorrect app type, assuming installed app. appId, appType", zzchm.zzjk(paramZzcgi.packageName), Integer.valueOf(i));
      i = 0;
      zzaws().beginTransaction();
      for (;;)
      {
        try
        {
          localObject2 = zzaws().zzjb(paramZzcgi.packageName);
          localObject1 = localObject2;
          if (localObject2 != null)
          {
            localObject1 = localObject2;
            if (((zzcgh)localObject2).getGmpAppId() != null)
            {
              localObject1 = localObject2;
              if (!((zzcgh)localObject2).getGmpAppId().equals(paramZzcgi.zzixs))
              {
                zzawy().zzazf().zzj("New GMP App Id passed in. Removing cached database data. appId", zzchm.zzjk(((zzcgh)localObject2).getAppId()));
                localObject1 = zzaws();
                localObject2 = ((zzcgh)localObject2).getAppId();
                ((zzcjl)localObject1).zzxf();
                ((zzcjk)localObject1).zzve();
                zzbq.zzgm((String)localObject2);
              }
            }
          }
          try
          {
            localObject3 = ((zzcgo)localObject1).getWritableDatabase();
            String[] arrayOfString = new String[1];
            arrayOfString[0] = localObject2;
            int j = ((SQLiteDatabase)localObject3).delete("events", "app_id=?", arrayOfString);
            int k = ((SQLiteDatabase)localObject3).delete("user_attributes", "app_id=?", arrayOfString);
            int m = ((SQLiteDatabase)localObject3).delete("conditional_properties", "app_id=?", arrayOfString);
            int n = ((SQLiteDatabase)localObject3).delete("apps", "app_id=?", arrayOfString);
            int i1 = ((SQLiteDatabase)localObject3).delete("raw_events", "app_id=?", arrayOfString);
            int i2 = ((SQLiteDatabase)localObject3).delete("raw_events_metadata", "app_id=?", arrayOfString);
            int i3 = ((SQLiteDatabase)localObject3).delete("event_filters", "app_id=?", arrayOfString);
            int i4 = ((SQLiteDatabase)localObject3).delete("property_filters", "app_id=?", arrayOfString);
            j = ((SQLiteDatabase)localObject3).delete("audience_filter_values", "app_id=?", arrayOfString) + (j + 0 + k + m + n + i1 + i2 + i3 + i4);
            if (j > 0) {
              ((zzcjk)localObject1).zzawy().zzazj().zze("Deleted application data. app, records", localObject2, Integer.valueOf(j));
            }
          }
          catch (SQLiteException localSQLiteException)
          {
            Object localObject3;
            ((zzcjk)localObject1).zzawy().zzazd().zze("Error deleting application data. appId, error", zzchm.zzjk((String)localObject2), localSQLiteException);
            continue;
          }
          localObject1 = null;
          if ((localObject1 != null) && (((zzcgh)localObject1).zzvj() != null) && (!((zzcgh)localObject1).zzvj().equals(paramZzcgi.zzifm)))
          {
            localObject2 = new Bundle();
            ((Bundle)localObject2).putString("_pv", ((zzcgh)localObject1).zzvj());
            zzb(new zzcha("_au", new zzcgx((Bundle)localObject2), "auto", l1), paramZzcgi);
          }
          zzg(paramZzcgi);
          localObject1 = null;
          if (i == 0)
          {
            localObject1 = zzaws().zzae(paramZzcgi.packageName, "_f");
            if (localObject1 != null) {
              break label1280;
            }
            l2 = (1L + l1 / 3600000L) * 3600000L;
            if (i != 0) {
              break label1180;
            }
            zzb(new zzcln("_fot", l1, Long.valueOf(l2), "auto"), paramZzcgi);
            zzawx().zzve();
            zzxf();
            localObject3 = new Bundle();
            ((Bundle)localObject3).putLong("_c", 1L);
            ((Bundle)localObject3).putLong("_r", 1L);
            ((Bundle)localObject3).putLong("_uwa", 0L);
            ((Bundle)localObject3).putLong("_pfo", 0L);
            ((Bundle)localObject3).putLong("_sys", 0L);
            ((Bundle)localObject3).putLong("_sysu", 0L);
            if (this.mContext.getPackageManager() != null) {
              break;
            }
            zzawy().zzazd().zzj("PackageManager is null, first open report might be inaccurate. appId", zzchm.zzjk(paramZzcgi.packageName));
            label754:
            localObject1 = zzaws();
            localObject2 = paramZzcgi.packageName;
            zzbq.zzgm((String)localObject2);
            ((zzcjk)localObject1).zzve();
            ((zzcjl)localObject1).zzxf();
            l2 = ((zzcgo)localObject1).zzal((String)localObject2, "first_open_count");
            if (l2 >= 0L) {
              ((Bundle)localObject3).putLong("_pfo", l2);
            }
            zzb(new zzcha("_f", new zzcgx((Bundle)localObject3), "auto", l1), paramZzcgi);
            label840:
            localObject1 = new Bundle();
            ((Bundle)localObject1).putLong("_et", 1L);
            zzb(new zzcha("_e", new zzcgx((Bundle)localObject1), "auto", l1), paramZzcgi);
            label887:
            zzaws().setTransactionSuccessful();
            return;
          }
        }
        finally
        {
          zzaws().endTransaction();
        }
        if (i == 1) {
          localObject1 = zzaws().zzae(paramZzcgi.packageName, "_v");
        }
      }
      localObject1 = null;
    }
    for (;;)
    {
      try
      {
        localObject2 = zzbhf.zzdb(this.mContext).getPackageInfo(paramZzcgi.packageName, 0);
        localObject1 = localObject2;
        if ((localObject1 != null) && (((PackageInfo)localObject1).firstInstallTime != 0L))
        {
          i = 0;
          if (((PackageInfo)localObject1).firstInstallTime == ((PackageInfo)localObject1).lastUpdateTime) {
            break label1327;
          }
          localSQLiteException.putLong("_uwa", 1L);
          if (i == 0) {
            break label1332;
          }
          l2 = 1L;
          zzb(new zzcln("_fi", l1, Long.valueOf(l2), "auto"), paramZzcgi);
        }
      }
      catch (PackageManager.NameNotFoundException localNameNotFoundException2)
      {
        try
        {
          localObject1 = zzbhf.zzdb(this.mContext).getApplicationInfo(paramZzcgi.packageName, 0);
          if (localObject1 == null) {
            break label754;
          }
          if ((((ApplicationInfo)localObject1).flags & 0x1) != 0) {
            localSQLiteException.putLong("_sys", 1L);
          }
          if ((((ApplicationInfo)localObject1).flags & 0x80) == 0) {
            break label754;
          }
          localSQLiteException.putLong("_sysu", 1L);
          break label754;
          localNameNotFoundException2 = localNameNotFoundException2;
          zzawy().zzazd().zze("Package info is null, first open report might be inaccurate. appId", zzchm.zzjk(paramZzcgi.packageName), localNameNotFoundException2);
        }
        catch (PackageManager.NameNotFoundException localNameNotFoundException1)
        {
          zzawy().zzazd().zze("Application info is null, first open report might be inaccurate. appId", zzchm.zzjk(paramZzcgi.packageName), localNameNotFoundException1);
          localBundle = null;
          continue;
        }
      }
      label1180:
      if (i != 1) {
        break label840;
      }
      zzb(new zzcln("_fvt", l1, Long.valueOf(l2), "auto"), paramZzcgi);
      zzawx().zzve();
      zzxf();
      Bundle localBundle = new Bundle();
      localBundle.putLong("_c", 1L);
      localBundle.putLong("_r", 1L);
      zzb(new zzcha("_v", new zzcgx(localBundle), "auto", l1), paramZzcgi);
      break label840;
      label1280:
      if (!paramZzcgi.zzixy) {
        break label887;
      }
      zzb(new zzcha("_cd", new zzcgx(new Bundle()), "auto", l1), paramZzcgi);
      break label887;
      break;
      label1327:
      i = 1;
      continue;
      label1332:
      l2 = 0L;
    }
  }
  
  @WorkerThread
  final void zzi(Runnable paramRunnable)
  {
    zzawx().zzve();
    if (this.zzjfy == null) {
      this.zzjfy = new ArrayList();
    }
    this.zzjfy.add(paramRunnable);
  }
  
  public final String zzjx(String paramString)
  {
    Object localObject = zzawx().zzc(new zzcio(this, paramString));
    try
    {
      localObject = (String)((Future)localObject).get(30000L, TimeUnit.MILLISECONDS);
      return localObject;
    }
    catch (TimeoutException localTimeoutException)
    {
      zzawy().zzazd().zze("Failed to get app instance id. appId", zzchm.zzjk(paramString), localTimeoutException);
      return null;
    }
    catch (ExecutionException localExecutionException)
    {
      for (;;) {}
    }
    catch (InterruptedException localInterruptedException)
    {
      for (;;) {}
    }
  }
  
  public final zzd zzws()
  {
    return this.zzata;
  }
  
  final void zzxf()
  {
    if (!this.zzdtb) {
      throw new IllegalStateException("AppMeasurement is not initialized");
    }
  }
}
