package com.mobile.ui.unsuretransaction.fragment;

import android.os.Bundle;
import android.support.annotation.Nullable;
import android.view.View;
import android.widget.TextView;
import butterknife.BindView;
import com.mobile.ui.App;
import com.mobile.ui.common.fragment.BaseFragment;
import com.mobile.ui.statement.mvp.TransactionDetailsViewModel;
import javax.inject.Inject;
import kkkkkk.diiiid;
import kkkkkk.gguuuu;
import kkkkkk.uyyyyy;

public class UnsureTransactionFragment
  extends BaseFragment
{
  public static int b042F042F042FЯ042FЯЯЯ042F = 1;
  public static int b042FЯ042FЯ042FЯЯЯ042F = 96;
  public static int bЯ042F042FЯ042FЯЯЯ042F = 0;
  public static int bЯЯЯ042F042FЯЯЯ042F = 2;
  @BindView(2131494608)
  public TextView callUsLink;
  @Inject
  public diiiid mTransactionDetailsAnalytics;
  
  public UnsureTransactionFragment() {}
  
  public static int b042FЯЯ042F042FЯЯЯ042F()
  {
    return 2;
  }
  
  public static int b042FЯЯЯЯ042FЯЯ042F()
  {
    return 0;
  }
  
  public static int bЯ042FЯЯЯ042FЯЯ042F()
  {
    return 2;
  }
  
  public static int bЯЯЯЯЯ042FЯЯ042F()
  {
    return 1;
  }
  
  public static UnsureTransactionFragment newInstance(TransactionDetailsViewModel paramTransactionDetailsViewModel)
  {
    UnsureTransactionFragment localUnsureTransactionFragment = new UnsureTransactionFragment();
    Bundle localBundle = new Bundle();
    localBundle.putParcelable(gguuuu.bк043Aккк043Aкк043A043A("\033\026+2('\027%+\032\035/%,,>$&6$-19F>2/BK:=35=", 't', 'Z', '\003'), paramTransactionDetailsViewModel);
    localUnsureTransactionFragment.setArguments(localBundle);
    if ((b042FЯ042FЯ042FЯЯЯ042F + b042F042F042FЯ042FЯЯЯ042F) * b042FЯ042FЯ042FЯЯЯ042F % bЯЯЯ042F042FЯЯЯ042F != bЯ042F042FЯ042FЯЯЯ042F)
    {
      if ((b042FЯ042FЯ042FЯЯЯ042F + b042F042F042FЯ042FЯЯЯ042F) * b042FЯ042FЯ042FЯЯЯ042F % bЯЯЯ042F042FЯЯЯ042F != bЯ042F042FЯ042FЯЯЯ042F)
      {
        b042FЯ042FЯ042FЯЯЯ042F = b042FЯЯ042F042FЯЯЯ042F();
        bЯ042F042FЯ042FЯЯЯ042F = 53;
      }
      b042FЯ042FЯ042FЯЯЯ042F = b042FЯЯ042F042FЯЯЯ042F();
      bЯ042F042FЯ042FЯЯЯ042F = 63;
    }
    return localUnsureTransactionFragment;
  }
  
  private void setCallUsLink()
  {
    throw new Runtime("d2j fail translate: java.lang.IndexOutOfBoundsException: fromIndex < 0: -1\n\tat java.util.BitSet.nextSetBit(BitSet.java:712)\n\tat com.googlecode.dex2jar.ir.ts.array.FillArrayTransformer.makeSureAllElementAreAssigned(FillArrayTransformer.java:505)\n\tat com.googlecode.dex2jar.ir.ts.array.FillArrayTransformer.transformReportChanged(FillArrayTransformer.java:123)\n\tat com.googlecode.dex2jar.ir.ts.StatedTransformer.transform(StatedTransformer.java:10)\n\tat com.googlecode.d2j.dex.Dex2jar$2.optimize(Dex2jar.java:149)\n\tat com.googlecode.d2j.dex.Dex2Asm.convertCode(Dex2Asm.java:414)\n\tat com.googlecode.d2j.dex.ExDex2Asm.convertCode(ExDex2Asm.java:42)\n\tat com.googlecode.d2j.dex.Dex2jar$2.convertCode(Dex2jar.java:128)\n\tat com.googlecode.d2j.dex.Dex2Asm.convertMethod(Dex2Asm.java:509)\n\tat com.googlecode.d2j.dex.Dex2Asm.convertClass(Dex2Asm.java:406)\n\tat com.googlecode.d2j.dex.Dex2Asm.convertDex(Dex2Asm.java:422)\n\tat com.googlecode.d2j.dex.Dex2jar.doTranslate(Dex2jar.java:172)\n\tat com.googlecode.d2j.dex.Dex2jar.to(Dex2jar.java:272)\n\tat com.googlecode.dex2jar.tools.Dex2jarCmd.doCommandLine(Dex2jarCmd.java:108)\n\tat com.googlecode.dex2jar.tools.BaseCmd.doMain(BaseCmd.java:288)\n\tat com.googlecode.dex2jar.tools.Dex2jarCmd.main(Dex2jarCmd.java:32)\n");
  }
  
  public void onCreate(@Nullable Bundle paramBundle)
  {
    if ((b042FЯЯ042F042FЯЯЯ042F() + b042F042F042FЯ042FЯЯЯ042F) * b042FЯЯ042F042FЯЯЯ042F() % bЯЯЯ042F042FЯЯЯ042F != bЯ042F042FЯ042FЯЯЯ042F)
    {
      b042FЯ042FЯ042FЯЯЯ042F = b042FЯЯ042F042FЯЯЯ042F();
      bЯ042F042FЯ042FЯЯЯ042F = 36;
    }
    switch (1)
    {
    case 0: 
    default: 
      for (;;)
      {
        switch (1)
        {
        }
      }
    }
    super.onCreate(paramBundle);
    int i = b042FЯ042FЯ042FЯЯЯ042F;
    switch (i * (b042F042F042FЯ042FЯЯЯ042F + i) % bЯЯЯ042F042FЯЯЯ042F)
    {
    default: 
      b042FЯ042FЯ042FЯЯЯ042F = 77;
      bЯ042F042FЯ042FЯЯЯ042F = 4;
    }
    App.get().getAppComponent().b0418041804180418И0418ИИИ0418(this);
  }
  
  /* Error */
  @Nullable
  public View onCreateView(android.view.LayoutInflater paramLayoutInflater, @Nullable android.view.ViewGroup paramViewGroup, @Nullable Bundle paramBundle)
  {
    // Byte code:
    //   0: getstatic 103	com/mobile/ui/R$layout:fragment_transaction_info	I
    //   3: istore 4
    //   5: getstatic 55	com/mobile/ui/unsuretransaction/fragment/UnsureTransactionFragment:b042FЯ042FЯ042FЯЯЯ042F	I
    //   8: istore 5
    //   10: getstatic 57	com/mobile/ui/unsuretransaction/fragment/UnsureTransactionFragment:b042F042F042FЯ042FЯЯЯ042F	I
    //   13: istore 6
    //   15: getstatic 55	com/mobile/ui/unsuretransaction/fragment/UnsureTransactionFragment:b042FЯ042FЯ042FЯЯЯ042F	I
    //   18: istore 7
    //   20: getstatic 59	com/mobile/ui/unsuretransaction/fragment/UnsureTransactionFragment:bЯЯЯ042F042FЯЯЯ042F	I
    //   23: istore 8
    //   25: iload 5
    //   27: iload 6
    //   29: iadd
    //   30: iload 7
    //   32: imul
    //   33: iload 8
    //   35: irem
    //   36: getstatic 61	com/mobile/ui/unsuretransaction/fragment/UnsureTransactionFragment:bЯ042F042FЯ042FЯЯЯ042F	I
    //   39: if_icmpeq +13 -> 52
    //   42: bipush 75
    //   44: putstatic 55	com/mobile/ui/unsuretransaction/fragment/UnsureTransactionFragment:b042FЯ042FЯ042FЯЯЯ042F	I
    //   47: bipush 69
    //   49: putstatic 61	com/mobile/ui/unsuretransaction/fragment/UnsureTransactionFragment:bЯ042F042FЯ042FЯЯЯ042F	I
    //   52: aload_1
    //   53: iload 4
    //   55: aload_2
    //   56: iconst_0
    //   57: invokevirtual 109	android/view/LayoutInflater:inflate	(ILandroid/view/ViewGroup;Z)Landroid/view/View;
    //   60: astore_1
    //   61: aload_1
    //   62: areturn
    //   63: astore_1
    //   64: aload_1
    //   65: athrow
    //   66: astore_1
    //   67: aload_1
    //   68: athrow
    // Local variable table:
    //   start	length	slot	name	signature
    //   0	69	0	this	UnsureTransactionFragment
    //   0	69	1	paramLayoutInflater	android.view.LayoutInflater
    //   0	69	2	paramViewGroup	android.view.ViewGroup
    //   0	69	3	paramBundle	Bundle
    //   3	51	4	i	int
    //   8	22	5	j	int
    //   13	17	6	k	int
    //   18	15	7	m	int
    //   23	13	8	n	int
    // Exception table:
    //   from	to	target	type
    //   0	25	63	java/lang/Exception
    //   25	52	66	java/lang/Exception
    //   52	61	66	java/lang/Exception
  }
  
  public void onViewCreated(View paramView, @Nullable Bundle paramBundle)
  {
    super.onViewCreated(paramView, paramBundle);
    int i = b042FЯ042FЯ042FЯЯЯ042F;
    int j = b042F042F042FЯ042FЯЯЯ042F;
    switch (1)
    {
    case 0: 
    default: 
      for (;;)
      {
        switch (1)
        {
        }
      }
    }
    switch (i * (j + i) % bЯЯЯ042F042FЯЯЯ042F)
    {
    default: 
      b042FЯ042FЯ042FЯЯЯ042F = 82;
      bЯ042F042FЯ042FЯЯЯ042F = b042FЯЯ042F042FЯЯЯ042F();
    }
    if ((b042FЯ042FЯ042FЯЯЯ042F + b042F042F042FЯ042FЯЯЯ042F) * b042FЯ042FЯ042FЯЯЯ042F % bЯЯЯ042F042FЯЯЯ042F != bЯ042F042FЯ042FЯЯЯ042F)
    {
      b042FЯ042FЯ042FЯЯЯ042F = b042FЯЯ042F042FЯЯЯ042F();
      bЯ042F042FЯ042FЯЯЯ042F = 54;
    }
    switch (0)
    {
    case 1: 
    default: 
      for (;;)
      {
        switch (0)
        {
        }
      }
    }
    setCallUsLink();
  }
  
  /* Error */
  public void trackScreenView()
  {
    // Byte code:
    //   0: aload_0
    //   1: invokevirtual 121	com/mobile/ui/unsuretransaction/fragment/UnsureTransactionFragment:getArguments	()Landroid/os/Bundle;
    //   4: ldc 123
    //   6: bipush 34
    //   8: iconst_3
    //   9: invokestatic 127	kkkkkk/gguuuu:bккккк043Aкк043A043A	(Ljava/lang/String;CC)Ljava/lang/String;
    //   12: invokevirtual 131	android/os/Bundle:getParcelable	(Ljava/lang/String;)Landroid/os/Parcelable;
    //   15: checkcast 133	com/mobile/ui/statement/mvp/TransactionDetailsViewModel
    //   18: astore_2
    //   19: aload_2
    //   20: ifnull +99 -> 119
    //   23: getstatic 55	com/mobile/ui/unsuretransaction/fragment/UnsureTransactionFragment:b042FЯ042FЯ042FЯЯЯ042F	I
    //   26: istore_1
    //   27: iload_1
    //   28: getstatic 57	com/mobile/ui/unsuretransaction/fragment/UnsureTransactionFragment:b042F042F042FЯ042FЯЯЯ042F	I
    //   31: iload_1
    //   32: iadd
    //   33: imul
    //   34: invokestatic 135	com/mobile/ui/unsuretransaction/fragment/UnsureTransactionFragment:bЯ042FЯЯЯ042FЯЯ042F	()I
    //   37: irem
    //   38: tableswitch	default:+18->56, 0:+27->65
    //   56: bipush 21
    //   58: putstatic 55	com/mobile/ui/unsuretransaction/fragment/UnsureTransactionFragment:b042FЯ042FЯ042FЯЯЯ042F	I
    //   61: iconst_5
    //   62: putstatic 61	com/mobile/ui/unsuretransaction/fragment/UnsureTransactionFragment:bЯ042F042FЯ042FЯЯЯ042F	I
    //   65: aload_0
    //   66: getfield 137	com/mobile/ui/unsuretransaction/fragment/UnsureTransactionFragment:mTransactionDetailsAnalytics	Lkkkkkk/diiiid;
    //   69: astore_3
    //   70: aload_2
    //   71: invokevirtual 141	com/mobile/ui/statement/mvp/TransactionDetailsViewModel:getArrangementTypeDomain	()Lkkkkkk/ccrrcc;
    //   74: astore 4
    //   76: invokestatic 63	com/mobile/ui/unsuretransaction/fragment/UnsureTransactionFragment:b042FЯЯ042F042FЯЯЯ042F	()I
    //   79: getstatic 57	com/mobile/ui/unsuretransaction/fragment/UnsureTransactionFragment:b042F042F042FЯ042FЯЯЯ042F	I
    //   82: iadd
    //   83: invokestatic 63	com/mobile/ui/unsuretransaction/fragment/UnsureTransactionFragment:b042FЯЯ042F042FЯЯЯ042F	()I
    //   86: imul
    //   87: invokestatic 135	com/mobile/ui/unsuretransaction/fragment/UnsureTransactionFragment:bЯ042FЯЯЯ042FЯЯ042F	()I
    //   90: irem
    //   91: invokestatic 143	com/mobile/ui/unsuretransaction/fragment/UnsureTransactionFragment:b042FЯЯЯЯ042FЯЯ042F	()I
    //   94: if_icmpeq +15 -> 109
    //   97: invokestatic 63	com/mobile/ui/unsuretransaction/fragment/UnsureTransactionFragment:b042FЯЯ042F042FЯЯЯ042F	()I
    //   100: putstatic 55	com/mobile/ui/unsuretransaction/fragment/UnsureTransactionFragment:b042FЯ042FЯ042FЯЯЯ042F	I
    //   103: invokestatic 63	com/mobile/ui/unsuretransaction/fragment/UnsureTransactionFragment:b042FЯЯ042F042FЯЯЯ042F	()I
    //   106: putstatic 61	com/mobile/ui/unsuretransaction/fragment/UnsureTransactionFragment:bЯ042F042FЯ042FЯЯЯ042F	I
    //   109: aload_3
    //   110: aload 4
    //   112: aload_2
    //   113: invokevirtual 147	com/mobile/ui/statement/mvp/TransactionDetailsViewModel:getPaymentType	()Ljava/lang/String;
    //   116: invokevirtual 153	kkkkkk/diiiid:bНННН041DН041D041DНН	(Lkkkkkk/ccrrcc;Ljava/lang/String;)V
    //   119: return
    //   120: astore_2
    //   121: aload_2
    //   122: athrow
    //   123: astore_2
    //   124: aload_2
    //   125: athrow
    // Local variable table:
    //   start	length	slot	name	signature
    //   0	126	0	this	UnsureTransactionFragment
    //   26	8	1	i	int
    //   18	95	2	localTransactionDetailsViewModel	TransactionDetailsViewModel
    //   120	2	2	localException1	Exception
    //   123	2	2	localException2	Exception
    //   69	41	3	localDiiiid	diiiid
    //   74	37	4	localCcrrcc	kkkkkk.ccrrcc
    // Exception table:
    //   from	to	target	type
    //   0	19	120	java/lang/Exception
    //   65	76	120	java/lang/Exception
    //   109	119	123	java/lang/Exception
  }
}
